{
  "type": "Feature",
  "properties": {
    "iso:country":"NL",
    "sg:address":"Gorredyksterwg 78",
    "sg:city":"Jubbega",
    "sg:orig_category":"Puien",
    "sg:phone":"+31 6 53376869",
    "sg:postcode":"8411 KG",
    "sg:province":"Friesland",
    "wof:name":"Doorn, G Van",
    "wof:placetype":"venue"
},
  "geometry": {"coordinates":[6.096426,52.985558],"type":"Point"}
}