{
  "type": "Feature",
  "properties": {
    "addr:full":"Kennedysngl 1 Reeuwijk South Holland 2811 VA",
    "addr:housenumber":"1",
    "addr:postcode":"2811",
    "addr:street":"Kennedysngl",
    "iso:country":"NL",
    "sg:address":"Kennedysngl 1",
    "sg:city":"Reeuwijk",
    "sg:orig_category":"Verenigingsgebouwen",
    "sg:phone":"+31 182 392 082",
    "sg:postcode":"2811 VA",
    "sg:province":"South Holland",
    "wof:name":"Jeugdhonk Reeuwijk",
    "wof:placetype":"venue"
},
  "geometry": {"coordinates":[4.722337,52.044903],"type":"Point"}
}