{
  "type": "Feature",
  "properties": {
    "iso:country":"NL",
    "sg:address":"Herenstraat 68",
    "sg:city":"Rijswijk Zh",
    "sg:orig_category":"Huishoudapparatuur, Televisies And Radio'S",
    "sg:phone":"+31 70 390 2673",
    "sg:postcode":"2282 BX",
    "sg:province":"Zuid-Holland",
    "wof:name":"Van Den Belt Electra",
    "wof:placetype":"venue"
},
  "geometry": {"coordinates":[4.333506,52.055527],"type":"Point"}
}