{
  "type": "Feature",
  "properties": {
    "iso:country":"NL",
    "sg:address":"A Noordewierln 38",
    "sg:city":"Bussum",
    "sg:orig_category":"Verzekeringen - Verzekeringskantoren",
    "sg:phone":"+31 35 693 4035",
    "sg:postcode":"1403 JD",
    "sg:province":"North Holland",
    "wof:name":"Santen, Van",
    "wof:placetype":"venue"
},
  "geometry": {"coordinates":[5.162605,52.276829],"type":"Point"}
}