{
  "type": "Feature",
  "properties": {
    "addr:full":"Weststr 25 Nieuwerkerk Zeeland 4306 CM",
    "addr:housenumber":"25",
    "addr:postcode":"4306 cm",
    "addr:street":"Weststr",
    "iso:country":"NL",
    "sg:address":"Weststr 25",
    "sg:city":"Nieuwerkerk",
    "sg:orig_category":"Pottenbakkerijen",
    "sg:phone":"+31 111 647 648",
    "sg:postcode":"4306 CM",
    "sg:province":"Zeeland",
    "wof:name":"Gina",
    "wof:placetype":"venue"
},
  "geometry": {"coordinates":[3.997672,51.649342],"type":"Point"}
}