{
  "type": "Feature",
  "properties": {
    "addr:full":"P V Haarenstr 30 Tilburg Noord-Brabant 5022 CS",
    "addr:housenumber":"30",
    "addr:postcode":"5022 cs",
    "addr:street":"Haarenstr",
    "iso:country":"NL",
    "sg:address":"P V Haarenstr 30",
    "sg:city":"Tilburg",
    "sg:orig_category":"Onderhoudswerken",
    "sg:phone":"+31 13 535 3082",
    "sg:postcode":"5022 CS",
    "sg:province":"Noord-Brabant",
    "sg:website":"http://www.vanhautum.nl",
    "wof:name":"Hautum Onderhoudsbedrijf, Van",
    "wof:placetype":"venue"
},
  "geometry": {"coordinates":[5.09431,51.541271],"type":"Point"}
}