{
  "type": "Feature",
  "properties": {
    "addr:full":"Wynhaven 19 Rotterdam South Holland 3011 WH",
    "addr:housenumber":"19",
    "addr:postcode":"3011 wh",
    "addr:street":"Wynhaven",
    "iso:country":"NL",
    "sg:address":"Wynhaven 19",
    "sg:city":"Rotterdam",
    "sg:orig_category":"Zalenverhuur",
    "sg:phone":"+31 10 233 1311",
    "sg:postcode":"3011 WH",
    "sg:province":"South Holland",
    "sg:website":"http://www.detijdgeest.nl",
    "wof:name":"Pakhuis Wijnen",
    "wof:placetype":"venue"
},
  "geometry": {"coordinates":[4.478455,51.922836],"type":"Point"}
}