{
  "type": "Feature",
  "properties": {
    "addr:full":"Aan De Noot 34 Vaals Limburg 6291 VX",
    "addr:housenumber":"34",
    "addr:postcode":"6291 vx",
    "addr:street":"Aan De Noot",
    "iso:country":"NL",
    "sg:address":"Aan De Noot 34",
    "sg:city":"Vaals",
    "sg:orig_category":"Verzekeringen - Verzekeringskantoren",
    "sg:phone":"+31 43 306 3558",
    "sg:postcode":"6291 VX",
    "sg:province":"Limburg",
    "wof:name":"Schleipen",
    "wof:placetype":"venue"
},
  "geometry": {"coordinates":[6.012546,50.769283],"type":"Point"}
}