{
  "type": "Feature",
  "properties": {
    "addr:full":"A Plesmanwg 35G Rotterdam Zuid-Holland 3088 GA",
    "addr:housenumber":"35g",
    "addr:postcode":"3088 ga",
    "addr:street":"Plesmanwg",
    "iso:country":"NL",
    "sg:address":"A Plesmanwg 35G",
    "sg:city":"Rotterdam",
    "sg:orig_category":"Mobiele- En Autotelefoons",
    "sg:phone":"+31 10 294 4455",
    "sg:postcode":"3088 GA",
    "sg:province":"Zuid-Holland",
    "sg:website":"http://www.carmobile.nl",
    "wof:name":"Car Mobile",
    "wof:placetype":"venue"
},
  "geometry": {"coordinates":[4.452922,51.876358],"type":"Point"}
}