{
  "type": "Feature",
  "properties": {
    "iso:country":"NL",
    "sg:address":"Molukkenstr 85",
    "sg:city":"Amsterdam",
    "sg:orig_category":"Accumulatoren",
    "sg:phone":"+31 20 665 7457",
    "sg:postcode":"1095 AX",
    "sg:province":"North Holland",
    "wof:name":"Storage",
    "wof:placetype":"venue"
},
  "geometry": {"coordinates":[4.93974,52.362793],"type":"Point"}
}