{
  "type": "Feature",
  "properties": {
    "iso:country":"NL",
    "sg:address":"Kastanjeln 52",
    "sg:city":"Woudrichem",
    "sg:orig_category":"Nagelstudio'S",
    "sg:phone":"+31 183 307 023",
    "sg:postcode":"4285 DD",
    "sg:province":"Noord-Brabant",
    "wof:name":"Nice Nails",
    "wof:placetype":"venue"
},
  "geometry": {"coordinates":[5.002828,51.810295],"type":"Point"}
}