{
  "type": "Feature",
  "properties": {
    "iso:country":"NL",
    "sg:address":"Lagedk 22",
    "sg:city":"Helmond",
    "sg:orig_category":"Belastingconsulenten/ Belastingadviseurs",
    "sg:phone":"+31 492 551 582",
    "sg:postcode":"5705 BZ",
    "sg:province":"Noord-Brabant",
    "wof:name":"Dl Advice",
    "wof:placetype":"venue"
},
  "geometry": {"coordinates":[5.678837,51.468056],"type":"Point"}
}