{
  "type": "Feature",
  "properties": {
    "addr:full":"Haven Zuidzijde 15 Scheemda Groningen 9679 TD",
    "addr:housenumber":"15",
    "addr:postcode":"9679 td",
    "addr:street":"Haven Zuidzijde",
    "iso:country":"NL",
    "sg:address":"Haven Zuidzijde 15",
    "sg:city":"Scheemda",
    "sg:orig_category":"Goederenvervoer Over De Weg",
    "sg:phone":"+31 597 591 290",
    "sg:postcode":"9679 TD",
    "sg:province":"Groningen",
    "wof:name":"Vof Transportbedrijf W. Musch",
    "wof:placetype":"venue"
},
  "geometry": {"coordinates":[6.993403,53.163597],"type":"Point"}
}