{
  "type": "Feature",
  "properties": {
    "addr:full":"Leusderweg 161 Amersfoort Utrecht 3818 AC",
    "addr:housenumber":"161",
    "addr:postcode":"3818 ac",
    "addr:street":"Leusderweg",
    "iso:country":"NL",
    "sg:address":"Leusderweg 161",
    "sg:city":"Amersfoort",
    "sg:orig_category":"Fotostudio'S And Fotografen",
    "sg:phone":"+31 33 465 1678",
    "sg:postcode":"3818 AC",
    "sg:province":"Utrecht",
    "wof:name":"Studio Rmb Fotografie En Reclame",
    "wof:placetype":"venue"
},
  "geometry": {"coordinates":[5.378619,52.141544],"type":"Point"}
}