{
  "type": "Feature",
  "properties": {
    "addr:full":"Pegasusstr 86-90 Haarlem Noord-Holland 2024 VS",
    "addr:housenumber":"86-90",
    "addr:postcode":"2024 vs",
    "iso:country":"NL",
    "sg:address":"Pegasusstr 86-90",
    "sg:city":"Haarlem",
    "sg:classifiers":[
        {
            "category":"Retail",
            "subcategory":"Auto Repair",
            "type":"Services"
        }
    ],
    "sg:phone":"+31 23 525 4856",
    "sg:postcode":"2024 VS",
    "sg:province":"Noord-Holland",
    "sg:tags":[
        "garage"
    ],
    "sg:website":"http://www.autobedrijfvanlaar.nl",
    "wof:name":"Laar Bv, Autobedrijf Van",
    "wof:placetype":"venue"
},
  "geometry": {"coordinates":[4.640492,52.405437],"type":"Point"}
}