{
  "type": "Feature",
  "properties": {
    "addr:full":"Brugakker 6210 Zeist Utrecht 3704 RE",
    "addr:housenumber":"6210",
    "addr:postcode":"3704",
    "addr:street":"Brugakker",
    "iso:country":"NL",
    "sg:address":"Brugakker 6210",
    "sg:city":"Zeist",
    "sg:orig_category":"Administratie- En Boekhoudkantoren",
    "sg:phone":"+31 30 695 2025",
    "sg:postcode":"3704 RE",
    "sg:province":"Utrecht",
    "wof:name":"Coak",
    "wof:placetype":"venue"
},
  "geometry": {"coordinates":[5.208937,52.085106],"type":"Point"}
}