{
  "type": "Feature",
  "properties": {
    "addr:full":"Bocksmeulen 35 Dokkum Friesland 9101 RA",
    "addr:housenumber":"35",
    "addr:postcode":"9101 ra",
    "addr:street":"Bocksmeulen",
    "iso:country":"NL",
    "sg:address":"Bocksmeulen 35",
    "sg:city":"Dokkum",
    "sg:orig_category":"Grafkisten",
    "sg:phone":"+31 519 295 400",
    "sg:postcode":"9101 RA",
    "sg:province":"Friesland",
    "wof:name":"Kaspersma Bv",
    "wof:placetype":"venue"
},
  "geometry": {"coordinates":[6.016711,53.319809],"type":"Point"}
}