{
  "type": "Feature",
  "properties": {
    "iso:country":"NL",
    "sg:address":"Ryksstrwg 2",
    "sg:city":"Olst",
    "sg:orig_category":"Grondwerken",
    "sg:phone":"+31 570 531 244",
    "sg:postcode":"8121 PD",
    "sg:province":"NL.08",
    "wof:name":"Broeke, G H Ten",
    "wof:placetype":"venue"
},
  "geometry": {"coordinates":[6.112995,52.337841],"type":"Point"}
}