{
  "type": "Feature",
  "properties": {
    "addr:full":"Spaarndammerdk 57C Amsterdam North Holland 1013 ZR",
    "addr:housenumber":"57c",
    "addr:postcode":"1013 zr",
    "addr:street":"Spaarndammerdk",
    "iso:country":"NL",
    "sg:address":"Spaarndammerdk 57C",
    "sg:city":"Amsterdam",
    "sg:orig_category":"Metselwerken",
    "sg:phone":"+31 20 684 0272",
    "sg:postcode":"1013 ZR",
    "sg:province":"North Holland",
    "wof:name":"Gale, S G",
    "wof:placetype":"venue"
},
  "geometry": {"coordinates":[4.875864,52.392658],"type":"Point"}
}