{
  "type": "Feature",
  "properties": {
    "addr:full":"De Eglantier 152 Apeldoorn Gelderland 7329 DD",
    "addr:housenumber":"152",
    "addr:postcode":"7329 dd",
    "addr:street":"De Eglantier;Gelderland",
    "iso:country":"NL",
    "sg:address":"De Eglantier 152",
    "sg:city":"Apeldoorn",
    "sg:orig_category":"Opticiens",
    "sg:phone":"+31 55 534 3889",
    "sg:postcode":"7329 DD",
    "sg:province":"Gelderland",
    "sg:website":"http://www.pearle.nl",
    "wof:name":"Pearle",
    "wof:placetype":"venue"
},
  "geometry": {"coordinates":[6.0046949387,52.1952056885],"type":"Point"}
}