{
  "type": "Feature",
  "properties": {
    "addr:full":"Dr Cuypersln 38 Eindhoven Noord-Brabant 5623 BB",
    "addr:housenumber":"38",
    "addr:postcode":"5623 bb",
    "iso:country":"NL",
    "sg:address":"Dr Cuypersln 38",
    "sg:city":"Eindhoven",
    "sg:classifiers":[
        {
            "category":"Retail",
            "subcategory":"Auto Repair",
            "type":"Services"
        }
    ],
    "sg:phone":"+31 40 244 3432",
    "sg:postcode":"5623 BB",
    "sg:province":"Noord-Brabant",
    "sg:tags":[
        "garage"
    ],
    "wof:name":"Vugt, Van",
    "wof:placetype":"venue"
},
  "geometry": {"coordinates":[5.47708,51.460041],"type":"Point"}
}