{
  "type": "Feature",
  "properties": {
    "addr:full":"A V Burenpln 7 Bathmen NL.08 7437 XP",
    "addr:housenumber":"7;nl.08",
    "addr:postcode":"7437 xp",
    "addr:street":"A;Burenpln",
    "iso:country":"NL",
    "sg:address":"A V Burenpln 7",
    "sg:city":"Bathmen",
    "sg:orig_category":"Kappers",
    "sg:phone":"+31 570 542 697",
    "sg:postcode":"7437 XP",
    "sg:province":"NL.08",
    "wof:name":"Ingrid",
    "wof:placetype":"venue"
},
  "geometry": {"coordinates":[6.3384251595,52.2529983521],"type":"Point"}
}