{
  "type": "Feature",
  "properties": {
    "addr:full":"Brahmsln 1 Hoogezand Groningen 9603 CA",
    "addr:housenumber":"1",
    "addr:postcode":"9603 ca",
    "addr:street":"Brahmsln",
    "iso:country":"NL",
    "sg:address":"Brahmsln 1",
    "sg:city":"Hoogezand",
    "sg:orig_category":"Administratie- En Boekhoudkantoren",
    "sg:phone":"+31 598 326 500",
    "sg:postcode":"9603 CA",
    "sg:province":"Groningen",
    "wof:name":"Bleeker Bv, Bureau",
    "wof:placetype":"venue"
},
  "geometry": {"coordinates":[6.79338,53.12278],"type":"Point"}
}