{
  "type": "Feature",
  "properties": {
    "addr:full":"Burg Mijnlieffstr 1 Anna Paulowna North Holland 1761 BK",
    "addr:housenumber":"1",
    "addr:postcode":"1761 bk",
    "addr:street":"Burg Mijnlieffstr",
    "iso:country":"NL",
    "sg:address":"Burg Mijnlieffstr 1",
    "sg:city":"Anna Paulowna",
    "sg:orig_category":"Overheidsdiensten",
    "sg:phone":"+31 223 536 100",
    "sg:postcode":"1761 BK",
    "sg:province":"North Holland",
    "wof:name":"Gemeente Anna Paulowna",
    "wof:placetype":"venue"
},
  "geometry": {"coordinates":[4.8337302208,52.8610877991],"type":"Point"}
}