{
  "type": "Feature",
  "properties": {
    "addr:full":"Dirk De Derdelaan 267 Vlaardingen South Holland 3132 HG",
    "addr:housenumber":"267",
    "addr:postcode":"3132 hg",
    "addr:street":"Dirk De Derdelaan",
    "iso:country":"NL",
    "sg:address":"Dirk De Derdelaan 267",
    "sg:city":"Vlaardingen",
    "sg:orig_category":"Paramedische Behandelingen",
    "sg:phone":"+31 10 435 1706",
    "sg:postcode":"3132 HG",
    "sg:province":"South Holland",
    "wof:name":"Logopediepraktijk Westwijk G.C. Van Mourik",
    "wof:placetype":"venue"
},
  "geometry": {"coordinates":[4.316519,51.914265],"type":"Point"}
}