{
  "type": "Feature",
  "properties": {
    "addr:full":"Bergfluiter 13 Nieuwegein Utrecht 3435 AT",
    "addr:housenumber":"13",
    "addr:postcode":"3435",
    "addr:street":"Bergfluiter",
    "iso:country":"NL",
    "sg:address":"Bergfluiter 13",
    "sg:city":"Nieuwegein",
    "sg:orig_category":"Vertaal- And Tolkenbureaus",
    "sg:phone":"+31 30 630 1746",
    "sg:postcode":"3435 AT",
    "sg:province":"Utrecht",
    "wof:name":"English Language Service",
    "wof:placetype":"venue"
},
  "geometry": {"coordinates":[5.071471,52.025272],"type":"Point"}
}