{
  "type": "Feature",
  "properties": {
    "iso:country":"NL",
    "sg:address":"Stephensonstr 88",
    "sg:city":"Hoogeveen",
    "sg:orig_category":"Betonwerken",
    "sg:phone":"+31 528 279 091",
    "sg:postcode":"7903 AW",
    "sg:province":"Drenthe",
    "wof:name":"Annen",
    "wof:placetype":"venue"
},
  "geometry": {"coordinates":[6.527976,52.728085],"type":"Point"}
}