{
  "type": "Feature",
  "properties": {
    "iso:country":"NL",
    "sg:address":"Centrumpassage 71",
    "sg:city":"Capelle A/D Ijssel",
    "sg:orig_category":"Herenmodezaken",
    "sg:phone":"+31 10 442 4433",
    "sg:postcode":"2903 HB",
    "sg:province":"Zuid-Holland",
    "wof:name":"Marchetto",
    "wof:placetype":"venue"
},
  "geometry": {"coordinates":[4.589003,51.931877],"type":"Point"}
}