{
  "type": "Feature",
  "properties": {
    "iso:country":"NL",
    "sg:address":"Meerten Verhoffstraat 3",
    "sg:city":"Breda",
    "sg:orig_category":"Bedrijfs- And Managementsconsultants",
    "sg:phone":"+31 76 513 9258",
    "sg:postcode":"4811 AR",
    "sg:province":"Noord-Brabant",
    "wof:name":"Unlimited Promotions",
    "wof:placetype":"venue"
},
  "geometry": {"coordinates":[4.781018,51.593277],"type":"Point"}
}