{
  "type": "Feature",
  "properties": {
    "addr:full":"Dijkstraat 40 Aalten Gelderland 7121 EV",
    "addr:housenumber":"40",
    "addr:postcode":"7121 ev",
    "addr:street":"Dijkstraat;Gelderland",
    "iso:country":"NL",
    "sg:address":"Dijkstraat 40",
    "sg:city":"Aalten",
    "sg:orig_category":"Kappers",
    "sg:phone":"+31 543 472 552",
    "sg:postcode":"7121 EV",
    "sg:province":"Gelderland",
    "wof:name":"Papillot Haarmode",
    "wof:placetype":"venue"
},
  "geometry": {"coordinates":[6.580625,51.923149],"type":"Point"}
}