{
  "type": "Feature",
  "properties": {
    "iso:country":"NL",
    "sg:address":"Reitdiepstraat 50A",
    "sg:city":"Utrecht",
    "sg:orig_category":"Partycatering And -Organisatie",
    "sg:phone":"+31 30 287 0292",
    "sg:postcode":"3522 GL",
    "sg:province":"Utrecht",
    "wof:name":"Gouden De Lepel",
    "wof:placetype":"venue"
},
  "geometry": {"coordinates":[5.114941,52.069641],"type":"Point"}
}