{
  "type": "Feature",
  "properties": {
    "addr:full":"Schutseln 4 Coevorden Drenthe 7741 AP",
    "addr:housenumber":"4",
    "addr:postcode":"7741 ap",
    "addr:street":"Schutseln",
    "iso:country":"NL",
    "sg:address":"Schutseln 4",
    "sg:city":"Coevorden",
    "sg:orig_category":"Adviesbureaus Bedrijfsorganisatie",
    "sg:phone":"+31 524 518 732",
    "sg:postcode":"7741 AP",
    "sg:province":"Drenthe",
    "wof:name":"Liahona",
    "wof:placetype":"venue"
},
  "geometry": {"coordinates":[6.746935,52.666286],"type":"Point"}
}