{
  "type": "Feature",
  "properties": {
    "addr:full":"Heerlerbaan 229 A Heerlen Limburg 6418 CE",
    "addr:housenumber":"229 a",
    "addr:postcode":"6418 ce",
    "addr:street":"Heerlerbaan",
    "iso:country":"NL",
    "sg:address":"Heerlerbaan 229 A",
    "sg:city":"Heerlen",
    "sg:orig_category":"Diverse Consumentenartikelen Gh",
    "sg:phone":"+31 45 542 0665",
    "sg:postcode":"6418 CE",
    "sg:province":"Limburg",
    "wof:name":"Bora International Bv",
    "wof:placetype":"venue"
},
  "geometry": {"coordinates":[6.003788,50.864315],"type":"Point"}
}