{
  "type": "Feature",
  "properties": {
    "addr:full":"Akkerhof 1 Biddinghuizen NL. 8256 BK",
    "addr:housenumber":"1",
    "addr:postcode":"8256 bk",
    "addr:street":"Akkerhof;Nl.",
    "iso:country":"NL",
    "sg:address":"Akkerhof 1",
    "sg:city":"Biddinghuizen",
    "sg:classifiers":[
        {
            "category":"Education",
            "subcategory":"Preschool",
            "type":"Public Place"
        }
    ],
    "sg:phone":"+31 321 331 502",
    "sg:postcode":"8256 BK",
    "sg:province":"NL.",
    "sg:tags":[
        "kleuteronderwijs",
        "basis-"
    ],
    "wof:name":"Openbare Basisschool De Akkerwinde",
    "wof:placetype":"venue"
},
  "geometry": {"coordinates":[5.691176,52.456848],"type":"Point"}
}