{
  "type": "Feature",
  "properties": {
    "addr:full":"Benzenraderweg 99 Heerlen Limburg 6417 SK",
    "addr:housenumber":"99",
    "addr:street":"Benzenraderweg;6417",
    "iso:country":"NL",
    "sg:address":"Benzenraderweg 99",
    "sg:city":"Heerlen",
    "sg:orig_category":"Kappers",
    "sg:phone":"+31 45 571 3642",
    "sg:postcode":"6417 SK",
    "sg:province":"Limburg",
    "wof:name":"Srg Haarmode Heerlen",
    "wof:placetype":"venue"
},
  "geometry": {"coordinates":[5.979681,50.879475],"type":"Point"}
}