{
  "type": "Feature",
  "properties": {
    "addr:full":"Reewal 22H Reeuwyk Zuid-Holland 2811 PT",
    "addr:housenumber":"22h",
    "addr:postcode":"2811 pt",
    "addr:street":"Reewal",
    "iso:country":"NL",
    "sg:address":"Reewal 22H",
    "sg:city":"Reeuwyk",
    "sg:orig_category":"Straalbedrijven",
    "sg:phone":"+31 182 393 006",
    "sg:postcode":"2811 PT",
    "sg:province":"Zuid-Holland",
    "wof:name":"Groot & Zn Vof",
    "wof:placetype":"venue"
},
  "geometry": {"coordinates":[4.689738,52.052216],"type":"Point"}
}