{
  "type": "Feature",
  "properties": {
    "addr:full":"W Alexanderstr 27 Asten Noord-Brabant 5721 LX",
    "addr:housenumber":"27",
    "addr:postcode":"5721 lx",
    "addr:street":"W",
    "iso:country":"NL",
    "sg:address":"W Alexanderstr 27",
    "sg:city":"Asten",
    "sg:orig_category":"Verzekeringen - Verzekeringskantoren",
    "sg:phone":"+31 493 692 013",
    "sg:postcode":"5721 LX",
    "sg:province":"Noord-Brabant",
    "wof:name":"Asten",
    "wof:placetype":"venue"
},
  "geometry": {"coordinates":[5.736868,51.399647],"type":"Point"}
}