{
  "type": "Feature",
  "properties": {
    "addr:full":"Amstelpln 33 Uithoorn North Holland 1421 SB",
    "addr:housenumber":"33",
    "addr:postcode":"1421 sb",
    "addr:street":"Amstelpln",
    "iso:country":"NL",
    "sg:address":"Amstelpln 33",
    "sg:city":"Uithoorn",
    "sg:orig_category":"Juweliers",
    "sg:phone":"+31 297 561 355",
    "sg:postcode":"1421 SB",
    "sg:province":"North Holland",
    "wof:name":"Sparnaaij",
    "wof:placetype":"venue"
},
  "geometry": {"coordinates":[4.828068,52.232697],"type":"Point"}
}