{
  "type": "Feature",
  "properties": {
    "addr:full":"Perkinsbaan 11 Nieuwegein Utrecht 3439 ND",
    "addr:housenumber":"11",
    "addr:postcode":"3439 nd",
    "addr:street":"Perkinsbaan",
    "iso:country":"NL",
    "sg:address":"Perkinsbaan 11",
    "sg:city":"Nieuwegein",
    "sg:orig_category":"Kantoorartikelen",
    "sg:phone":"+31 30 603 0229",
    "sg:postcode":"3439 ND",
    "sg:province":"Utrecht",
    "wof:name":"Teac Nederland Bv",
    "wof:placetype":"venue"
},
  "geometry": {"coordinates":[5.100107193,52.0326843262],"type":"Point"}
}