{
  "type": "Feature",
  "properties": {
    "addr:full":"Pachtersveld 26 Apeldoorn Gelderland 7327 CR",
    "addr:housenumber":"26",
    "addr:postcode":"7327 cr",
    "addr:street":"Pachtersveld;Gelderland",
    "iso:country":"NL",
    "sg:address":"Pachtersveld 26",
    "sg:city":"Apeldoorn",
    "sg:orig_category":"Organisatiebureaus",
    "sg:phone":"+31 6 54340887",
    "sg:postcode":"7327 CR",
    "sg:province":"Gelderland",
    "wof:name":"Steenbergen Cc Bv",
    "wof:placetype":"venue"
},
  "geometry": {"coordinates":[5.9942498207,52.1919746399],"type":"Point"}
}