{
  "type": "Feature",
  "properties": {
    "addr:full":"Eiland 80 Leerdam Zuid-Holland 4143 ET",
    "addr:housenumber":"80",
    "addr:postcode":"4143 et",
    "addr:street":"Eiland",
    "iso:country":"NL",
    "sg:address":"Eiland 80",
    "sg:city":"Leerdam",
    "sg:orig_category":"Apotheken",
    "sg:phone":"+31 345 618 183",
    "sg:postcode":"4143 ET",
    "sg:province":"Zuid-Holland",
    "wof:name":"Eiland, Het",
    "wof:placetype":"venue"
},
  "geometry": {"coordinates":[5.091343,51.897923],"type":"Point"}
}