{
  "type": "Feature",
  "properties": {
    "iso:country":"NL",
    "sg:address":"Ondernemersstraat 3",
    "sg:city":"Ijsselmuiden",
    "sg:orig_category":"Loodgieterswerk, Verwarming And Sanitaire Installaties",
    "sg:phone":"+31 38 332 7799",
    "sg:postcode":"8271 RS",
    "sg:province":"Overijssel",
    "wof:name":"Breman Ijsselmuiden Bv",
    "wof:placetype":"venue"
},
  "geometry": {"coordinates":[5.936438,52.553822],"type":"Point"}
}