{
  "type": "Feature",
  "properties": {
    "addr:full":"Keizerstr 93 S Gravenhage Zuid-Holland 2584 BC",
    "addr:housenumber":"93;gravenhage",
    "addr:postcode":"2584 bc",
    "addr:street":"Keizerstr;S",
    "iso:country":"NL",
    "sg:address":"Keizerstr 93",
    "sg:city":"S Gravenhage",
    "sg:orig_category":"Juweliers",
    "sg:phone":"+31 70 355 1182",
    "sg:postcode":"2584 BC",
    "sg:province":"Zuid-Holland",
    "wof:name":"Gouden Keizer, Juwelier De",
    "wof:placetype":"venue"
},
  "geometry": {"coordinates":[4.28131,52.103199],"type":"Point"}
}