{
  "type": "Feature",
  "properties": {
    "addr:full":"Schoolstraat 4 Hansweert Zeeland 4417 AB",
    "addr:housenumber":"4",
    "addr:postcode":"4417 ab",
    "addr:street":"Schoolstraat",
    "iso:country":"NL",
    "sg:address":"Schoolstraat 4",
    "sg:city":"Hansweert",
    "sg:orig_category":"Metaalwerken",
    "sg:phone":"+31 113 383 848",
    "sg:postcode":"4417 AB",
    "sg:province":"Zeeland",
    "wof:name":"Polfliet Vof",
    "wof:placetype":"venue"
},
  "geometry": {"coordinates":[4.005595,51.447636],"type":"Point"}
}