{
  "type": "Feature",
  "properties": {
    "iso:country":"NL",
    "sg:address":"De Zeilmakerij 3",
    "sg:city":"Leusden",
    "sg:orig_category":"Handelsbemiddeling Textiel And Lederwaren",
    "sg:phone":"+31 33 494 0609",
    "sg:postcode":"3831 CV",
    "sg:province":"Utrecht",
    "wof:name":"Stuiver-Agenturen Bv",
    "wof:placetype":"venue"
},
  "geometry": {"coordinates":[5.427441,52.127228],"type":"Point"}
}