{
  "type": "Feature",
  "properties": {
    "iso:country":"NL",
    "sg:address":"Postbus 202",
    "sg:city":"Nieuw Vennep",
    "sg:orig_category":"Directmail",
    "sg:phone":"+31 252 672 849",
    "sg:postcode":"2150 AE",
    "sg:website":"http://www.comprador.nl",
    "wof:name":"Comprador Group Bv",
    "wof:placetype":"venue"
},
  "geometry": {"coordinates":[4.6335,52.26474],"type":"Point"}
}