{
  "type": "Feature",
  "properties": {
    "iso:country":"NL",
    "sg:address":"Azinkdk 8",
    "sg:city":"Almen",
    "sg:orig_category":"Land- En Tuinbouw - Mechanisatie",
    "sg:phone":"+31 575 431 297",
    "sg:postcode":"7218 NG",
    "sg:province":"Kansas",
    "wof:name":"Brinkman Almen Bv",
    "wof:placetype":"venue"
},
  "geometry": {"coordinates":[-99.738663,39.936443],"type":"Point"}
}