{
  "type": "Feature",
  "properties": {
    "addr:full":"Velswykwg 48 Zelhem Gelderland 7021 KT",
    "addr:housenumber":"48",
    "addr:postcode":"7021 kt",
    "addr:street":"Velswykwg;Gelderland",
    "iso:country":"NL",
    "sg:address":"Velswykwg 48",
    "sg:city":"Zelhem",
    "sg:orig_category":"Peuterspeelzalen",
    "sg:phone":"+31 314 641 667",
    "sg:postcode":"7021 KT",
    "sg:province":"Gelderland",
    "wof:name":"Draejtol, De",
    "wof:placetype":"venue"
},
  "geometry": {"coordinates":[6.302644,52.010365],"type":"Point"}
}