{
  "type": "Feature",
  "properties": {
    "addr:full":"Straatwg 138C Rotterdam Zuid-Holland 3051 BN",
    "addr:housenumber":"138c",
    "addr:postcode":"3051 bn",
    "addr:street":"Straatwg",
    "iso:country":"NL",
    "sg:address":"Straatwg 138C",
    "sg:city":"Rotterdam",
    "sg:orig_category":"Adviesbureaus Bedrijfsorganisatie",
    "sg:phone":"+31 10 461 1577",
    "sg:postcode":"3051 BN",
    "sg:province":"Zuid-Holland",
    "wof:name":"Sluyter Remmers & Van Beuningen",
    "wof:placetype":"venue"
},
  "geometry": {"coordinates":[4.48498,51.947319],"type":"Point"}
}