{
  "type": "Feature",
  "properties": {
    "addr:full":"Postbus 232 Hoofddorp Noord-Holland 2130 AE",
    "addr:housenumber":"232",
    "addr:postcode":"2130 ae",
    "addr:street":"Postbus",
    "iso:country":"NL",
    "sg:address":"Postbus 232",
    "sg:city":"Hoofddorp",
    "sg:orig_category":"Adviesbureaus Bedrijfsorganisatie",
    "sg:phone":"+31 23 557 6486",
    "sg:postcode":"2130 AE",
    "sg:province":"Noord-Holland",
    "sg:website":"http://www.tpqm.nl",
    "wof:name":"Tpqm Business Development Bv",
    "wof:placetype":"venue"
},
  "geometry": {"coordinates":[4.68729,52.308708],"type":"Point"}
}