{
  "type": "Feature",
  "properties": {
    "addr:full":"Azaleastr 13 Aalsmeer Noord-Holland 1431 SH",
    "addr:housenumber":"13;1431",
    "addr:postcode":"sh",
    "addr:street":"Azaleastr",
    "iso:country":"NL",
    "sg:address":"Azaleastr 13",
    "sg:city":"Aalsmeer",
    "sg:orig_category":"Verenigingen En Stichtingen",
    "sg:phone":"+31 297 326 090",
    "sg:postcode":"1431 SH",
    "sg:province":"Noord-Holland",
    "wof:name":"Zonnebloem Regio Amstelland, De",
    "wof:placetype":"venue"
},
  "geometry": {"coordinates":[4.757961,52.264969],"type":"Point"}
}