{
  "type": "Feature",
  "properties": {
    "iso:country":"NL",
    "sg:address":"Heemraadschapsln 83",
    "sg:city":"Amstelveen",
    "sg:orig_category":"Wegenbouw",
    "sg:phone":"+31 20 640 5660",
    "sg:postcode":"1181 VA",
    "sg:province":"Noord-Holland",
    "wof:name":"Egmond Bv, Van",
    "wof:placetype":"venue"
},
  "geometry": {"coordinates":[4.8583459854,52.3070602417],"type":"Point"}
}