{
  "type": "Feature",
  "properties": {
    "addr:full":"Sinderensewg 5 Varsseveld Gelderland 7051 HD",
    "addr:housenumber":"5",
    "addr:postcode":"7051 hd",
    "addr:street":"Sinderensewg;Gelderland",
    "iso:country":"NL",
    "sg:address":"Sinderensewg 5",
    "sg:city":"Varsseveld",
    "sg:orig_category":"Oldtimers",
    "sg:phone":"+31 315 642 970",
    "sg:postcode":"7051 HD",
    "sg:province":"Gelderland",
    "wof:name":"Kempink, Onno",
    "wof:placetype":"venue"
},
  "geometry": {"coordinates":[6.463845,51.937527],"type":"Point"}
}