{
  "type": "Feature",
  "properties": {
    "addr:full":"Koningsakkers 39 Siddeburen Groningen 9628 EG",
    "addr:housenumber":"39",
    "addr:postcode":"9628 eg",
    "addr:street":"Koningsakkers",
    "iso:country":"NL",
    "sg:address":"Koningsakkers 39",
    "sg:city":"Siddeburen",
    "sg:orig_category":"Verenigingen En Stichtingen",
    "sg:phone":"+31 598 432 733",
    "sg:postcode":"9628 EG",
    "sg:province":"Groningen",
    "wof:name":"Anbo",
    "wof:placetype":"venue"
},
  "geometry": {"coordinates":[6.872787,53.247849],"type":"Point"}
}