{
  "type": "Feature",
  "properties": {
    "addr:full":"Marthastr 20 Hengelo Ov Overijssel 7555 DX",
    "addr:housenumber":"20",
    "addr:postcode":"7555 dx",
    "addr:street":"Marthastr;Ov",
    "iso:country":"NL",
    "sg:address":"Marthastr 20",
    "sg:city":"Hengelo Ov",
    "sg:orig_category":"Modeontwerpen",
    "sg:phone":"+31 74 291 5665",
    "sg:postcode":"7555 DX",
    "sg:province":"Overijssel",
    "wof:name":"Hellzapoppin",
    "wof:placetype":"venue"
},
  "geometry": {"coordinates":[6.771177,52.258324],"type":"Point"}
}