{
  "type": "Feature",
  "properties": {
    "addr:full":"Ryksstrwg 64 Haarlem Noord-Holland 2022 DB",
    "addr:housenumber":"64",
    "addr:postcode":"2022 db",
    "addr:street":"Ryksstrwg",
    "iso:country":"NL",
    "sg:address":"Ryksstrwg 64",
    "sg:city":"Haarlem",
    "sg:orig_category":"Videotheken",
    "sg:phone":"+31 23 537 1674",
    "sg:postcode":"2022 DB",
    "sg:province":"Noord-Holland",
    "sg:website":"http://www.videoland.nl",
    "wof:name":"Videoland",
    "wof:placetype":"venue"
},
  "geometry": {"coordinates":[4.65061,52.402458],"type":"Point"}
}