{
  "type": "Feature",
  "properties": {
    "addr:full":"Reigerstraat 34 Amersfoort Utrecht 3816 AX",
    "addr:housenumber":"34",
    "addr:postcode":"3816 ax",
    "addr:street":"Reigerstraat",
    "iso:country":"NL",
    "sg:address":"Reigerstraat 34",
    "sg:city":"Amersfoort",
    "sg:orig_category":"Bloemen And Planten Gh",
    "sg:phone":"+31 33 475 5192",
    "sg:postcode":"3816 AX",
    "sg:province":"Utrecht",
    "wof:name":"Handelsonderneming Niels Sakkers",
    "wof:placetype":"venue"
},
  "geometry": {"coordinates":[5.398311,52.1521],"type":"Point"}
}