{
  "type": "Feature",
  "properties": {
    "addr:full":"Oesterzwam 17 Standdaarbuiten Noord-Brabant 4758 CA",
    "addr:housenumber":"17",
    "addr:postcode":"4758 ca",
    "addr:street":"Oesterzwam",
    "iso:country":"NL",
    "sg:address":"Oesterzwam 17",
    "sg:city":"Standdaarbuiten",
    "sg:orig_category":"Kappers",
    "sg:phone":"+31 165 318 393",
    "sg:postcode":"4758 CA",
    "sg:province":"Noord-Brabant",
    "wof:name":"E. Frijters",
    "wof:placetype":"venue"
},
  "geometry": {"coordinates":[4.5164008141,51.6150436401],"type":"Point"}
}