{
  "type": "Feature",
  "properties": {
    "addr:full":"Assendorperstr 10 Zwolle NL.08 8011 KB",
    "addr:housenumber":"10",
    "addr:postcode":"8011 kb",
    "addr:street":"Assendorperstr",
    "iso:country":"NL",
    "sg:address":"Assendorperstr 10",
    "sg:city":"Zwolle",
    "sg:orig_category":"Parketvloeren",
    "sg:phone":"+31 38 422 3738",
    "sg:postcode":"8011 KB",
    "sg:province":"NL.08",
    "sg:website":"http://www.bruynzeel-vloeren.nl",
    "wof:name":"Bruynzeel Vloeren",
    "wof:placetype":"venue"
},
  "geometry": {"coordinates":[6.098093,52.50832],"type":"Point"}
}