{
  "type": "Feature",
  "properties": {
    "iso:country":"NL",
    "sg:address":"Rozenln 5",
    "sg:city":"Valkenburg Zh",
    "sg:orig_category":"Bloemen En Planten - Groothandel",
    "sg:phone":"+31 71 407 6724",
    "sg:postcode":"2235 ER",
    "sg:province":"Zuid-Holland",
    "wof:name":"Zwaan Vof, J & H",
    "wof:placetype":"venue"
},
  "geometry": {"coordinates":[4.434805,52.180035],"type":"Point"}
}