{
  "type": "Feature",
  "properties": {
    "addr:full":"Schrijnwerkerstraat 65 Schiedam South Holland 3123 EJ",
    "addr:housenumber":"65",
    "addr:postcode":"3123 ej",
    "addr:street":"Schrijnwerkerstraat",
    "iso:country":"NL",
    "sg:address":"Schrijnwerkerstraat 65",
    "sg:city":"Schiedam",
    "sg:orig_category":"Vertaal- And Tolkenbureaus",
    "sg:phone":"+31 10 470 7017",
    "sg:postcode":"3123 EJ",
    "sg:province":"South Holland",
    "wof:name":"Vertaalbureau Crea-Trans",
    "wof:placetype":"venue"
},
  "geometry": {"coordinates":[4.362827,51.941319],"type":"Point"}
}