{
  "type": "Feature",
  "properties": {
    "addr:full":"Vondelstraat 120 Amsterdam Noord-Holland 1054 GS",
    "addr:housenumber":"120",
    "addr:postcode":"1054 gs",
    "addr:street":"Vondelstraat",
    "iso:country":"NL",
    "sg:address":"Vondelstraat 120",
    "sg:city":"Amsterdam",
    "sg:orig_category":"Koeriersdiensten",
    "sg:phone":"+31 900 2357489",
    "sg:postcode":"1054 GS",
    "sg:province":"Noord-Holland",
    "wof:name":"Ritzen Koeriers",
    "wof:placetype":"venue"
},
  "geometry": {"coordinates":[4.873805,52.36132],"type":"Point"}
}