{
  "type": "Feature",
  "properties": {
    "iso:country":"NL",
    "sg:address":"Margrietstr 8",
    "sg:city":"Oud Beyerland",
    "sg:orig_category":"Paardensport",
    "sg:phone":"+31 186 625 016",
    "sg:postcode":"3261 AN",
    "sg:province":"Zuid-Holland",
    "wof:name":"Horse Supply",
    "wof:placetype":"venue"
},
  "geometry": {"coordinates":[4.417607,51.819916],"type":"Point"}
}