{
  "type": "Feature",
  "properties": {
    "addr:full":"Kerkegaard 47 Maastricht Limburg 6227 ET",
    "addr:housenumber":"47",
    "addr:postcode":"6227 et",
    "addr:street":"Kerkegaard",
    "iso:country":"NL",
    "sg:address":"Kerkegaard 47",
    "sg:city":"Maastricht",
    "sg:orig_category":"Meubels And Huishoudapparatuur Gh",
    "sg:phone":"+31 43 361 6088",
    "sg:postcode":"6227 ET",
    "sg:province":"Limburg",
    "wof:name":"M. Kicken Vof",
    "wof:placetype":"venue"
},
  "geometry": {"coordinates":[5.721544,50.832359],"type":"Point"}
}