{
  "type": "Feature",
  "properties": {
    "addr:full":"Middelgronden 5 Huizen Noord-Holland 1274 BA",
    "addr:housenumber":"5",
    "addr:postcode":"1274 ba",
    "addr:street":"Middelgronden",
    "iso:country":"NL",
    "sg:address":"Middelgronden 5",
    "sg:city":"Huizen",
    "sg:orig_category":"Autorijscholen",
    "sg:phone":"+31 35 526 7725",
    "sg:postcode":"1274 BA",
    "sg:province":"Noord-Holland",
    "wof:name":"Lestbest",
    "wof:placetype":"venue"
},
  "geometry": {"coordinates":[5.270063,52.300335],"type":"Point"}
}