{
  "type": "Feature",
  "properties": {
    "iso:country":"NL",
    "sg:address":"Oude Broeksittarderweg 2",
    "sg:city":"Sittard",
    "sg:classifiers":[
        {
            "category":"Fast Food",
            "type":"Food & Drink"
        }
    ],
    "sg:phone":"+31 46 451 3900",
    "sg:postcode":"6131 HE",
    "sg:province":"Limburg",
    "sg:tags":[
        "afhaal",
        "restaurant"
    ],
    "wof:name":"Pizzeria Kiko",
    "wof:placetype":"venue"
},
  "geometry": {"coordinates":[5.874342,50.999607],"type":"Point"}
}