{
  "type": "Feature",
  "properties": {
    "iso:country":"NL",
    "sg:address":"Floraplein 23",
    "sg:city":"Eindhoven",
    "sg:orig_category":"Diverse Opleidingen And Onderwijs",
    "sg:phone":"+31 40 211 4162",
    "sg:postcode":"5644 JS",
    "sg:province":"Noord-Brabant",
    "wof:name":"Esperanto Nederland",
    "wof:placetype":"venue"
},
  "geometry": {"coordinates":[5.495684,51.416145],"type":"Point"}
}