{
  "type": "Feature",
  "properties": {
    "addr:full":"Wiedehoek 6A Veendam Groningen 9645 LW",
    "addr:housenumber":"6a",
    "addr:postcode":"9645 lw",
    "addr:street":"Wiedehoek",
    "iso:country":"NL",
    "sg:address":"Wiedehoek 6A",
    "sg:city":"Veendam",
    "sg:orig_category":"Autoschade- Herstelbedrijven",
    "sg:phone":"+31 6 55945074",
    "sg:postcode":"9645 LW",
    "sg:province":"Groningen",
    "sg:website":"http://www.lakreparatienoordnederland.nl",
    "wof:name":"Lakreparatie Noord-Nederland",
    "wof:placetype":"venue"
},
  "geometry": {"coordinates":[6.8855,53.118645],"type":"Point"}
}