{
  "type": "Feature",
  "properties": {
    "addr:full":"Wattstr 48A Zoetermeer Zuid-Holland 2723 RC",
    "addr:housenumber":"48a",
    "addr:postcode":"2723 rc",
    "addr:street":"Wattstr",
    "iso:country":"NL",
    "sg:address":"Wattstr 48A",
    "sg:city":"Zoetermeer",
    "sg:orig_category":"Handenarbeid",
    "sg:phone":"+31 79 343 1329",
    "sg:postcode":"2723 RC",
    "sg:province":"Zuid-Holland",
    "sg:website":"http://www.funhobbyshop.com",
    "wof:name":"The Fun Hobby Shop",
    "wof:placetype":"venue"
},
  "geometry": {"coordinates":[4.523602,52.058079],"type":"Point"}
}