{
  "type": "Feature",
  "properties": {
    "addr:full":"Speenkruidstraat 60 Groningen Groningen 9731 GW",
    "addr:housenumber":"60",
    "addr:postcode":"9731 gw",
    "addr:street":"Speenkruidstraat",
    "iso:country":"NL",
    "sg:address":"Speenkruidstraat 60",
    "sg:city":"Groningen",
    "sg:orig_category":"Diverse Grafische Activiteiten",
    "sg:phone":"+31 50 549 2122",
    "sg:postcode":"9731 GW",
    "sg:province":"Groningen",
    "wof:name":"Q-Text Prepress Bv",
    "wof:placetype":"venue"
},
  "geometry": {"coordinates":[6.600147,53.23003],"type":"Point"}
}