{
  "type": "Feature",
  "properties": {
    "addr:full":"Handelswg 10B Alphen Aan Den Ryn South Holland 2404 CD",
    "addr:housenumber":"10b",
    "addr:postcode":"2404 cd",
    "addr:street":"Handelswg;Aan Den Ryn",
    "iso:country":"NL",
    "sg:address":"Handelswg 10B",
    "sg:city":"Alphen Aan Den Ryn",
    "sg:orig_category":"Waterbehandeling En Waterzuiverings- Systemen",
    "sg:phone":"+31 172 438 841",
    "sg:postcode":"2404 CD",
    "sg:province":"South Holland",
    "wof:name":"Scalewatcher Bv",
    "wof:placetype":"venue"
},
  "geometry": {"coordinates":[4.6398658752,52.1309623718],"type":"Point"}
}