{
  "type": "Feature",
  "properties": {
    "addr:full":"Ploegspoor 12 Haarlem Noord-Holland 2033 CT",
    "addr:housenumber":"12",
    "addr:postcode":"2033 ct",
    "addr:street":"Ploegspoor",
    "iso:country":"NL",
    "sg:address":"Ploegspoor 12",
    "sg:city":"Haarlem",
    "sg:orig_category":"Juridische Dienstverlening",
    "sg:phone":"+31 23 545 0183",
    "sg:postcode":"2033 CT",
    "sg:province":"Noord-Holland",
    "wof:name":"Bureau Bakker, Adviseur Ruimtel.Ordening",
    "wof:placetype":"venue"
},
  "geometry": {"coordinates":[4.671198,52.375519],"type":"Point"}
}