{
  "type": "Feature",
  "properties": {
    "addr:full":"Stadionkd 19 Amsterdam North Holland 1077 VK",
    "addr:housenumber":"19",
    "addr:postcode":"1077 vk",
    "addr:street":"Stadionkd",
    "iso:country":"NL",
    "sg:address":"Stadionkd 19",
    "sg:city":"Amsterdam",
    "sg:orig_category":"Pensioenen",
    "sg:phone":"+31 20 676 4637",
    "sg:postcode":"1077 VK",
    "sg:province":"North Holland",
    "wof:name":"Reinbergen & Partn",
    "wof:placetype":"venue"
},
  "geometry": {"coordinates":[4.872548,52.340622],"type":"Point"}
}