{
  "type": "Feature",
  "properties": {
    "addr:full":"Parkstraat 99 Den Haag Zuid-Holland 2514 JH",
    "addr:housenumber":"99",
    "addr:postcode":"2514 jh",
    "addr:street":"Parkstraat",
    "iso:country":"NL",
    "sg:address":"Parkstraat 99",
    "sg:city":"Den Haag",
    "sg:orig_category":"Elektronische Bedrijfsinstallaties",
    "sg:phone":"+31 70 363 4098",
    "sg:postcode":"2514 JH",
    "sg:province":"Zuid-Holland",
    "wof:name":"Abc Internet.Nl",
    "wof:placetype":"venue"
},
  "geometry": {"coordinates":[4.307118,52.084221],"type":"Point"}
}