{
  "type": "Feature",
  "properties": {
    "iso:country":"NL",
    "sg:address":"Scheepersdijk 2",
    "sg:city":"Oisterwijk",
    "sg:orig_category":"Bedrijfsinventaris Gh",
    "sg:phone":"+31 13 528 6940",
    "sg:postcode":"5062 EC",
    "sg:province":"Noord-Brabant",
    "wof:name":"Mirjan",
    "wof:placetype":"venue"
},
  "geometry": {"coordinates":[5.201891,51.578999],"type":"Point"}
}