{
  "type": "Feature",
  "properties": {
    "addr:full":"De Genestetstr 1-I Amsterdam Noord-Holland 1054 AW",
    "addr:housenumber":"1-i",
    "addr:postcode":"1054 aw",
    "iso:country":"NL",
    "sg:address":"De Genestetstr 1-I",
    "sg:city":"Amsterdam",
    "sg:orig_category":"Homeopathie",
    "sg:phone":"+31 20 627 6475",
    "sg:postcode":"1054 AW",
    "sg:province":"Noord-Holland",
    "wof:name":"Geboortecentrum A'Dam",
    "wof:placetype":"venue"
},
  "geometry": {"coordinates":[4.86857,52.361408],"type":"Point"}
}