{
  "type": "Feature",
  "properties": {
    "addr:full":"Dobbe 73 Zwolle Overijssel 8032 JX",
    "addr:housenumber":"73",
    "addr:postcode":"8032 jx",
    "addr:street":"Dobbe",
    "iso:country":"NL",
    "sg:address":"Dobbe 73",
    "sg:city":"Zwolle",
    "sg:orig_category":"Projectontwikkeling",
    "sg:phone":"+31 38 452 7111",
    "sg:postcode":"8032 JX",
    "sg:province":"Overijssel",
    "wof:name":"Stadshagen Vof",
    "wof:placetype":"venue"
},
  "geometry": {"coordinates":[6.103579,52.528473],"type":"Point"}
}