{
  "type": "Feature",
  "properties": {
    "addr:full":"Grt Markt 43 Almere NL. 1315 JB",
    "addr:housenumber":"43",
    "addr:postcode":"1315 jb",
    "addr:street":"Markt;Nl.",
    "iso:country":"NL",
    "sg:address":"Grt Markt 43",
    "sg:city":"Almere",
    "sg:orig_category":"Opticiens",
    "sg:phone":"+31 36 534 2532",
    "sg:postcode":"1315 JB",
    "sg:province":"NL.",
    "wof:name":"Eyes",
    "wof:placetype":"venue"
},
  "geometry": {"coordinates":[5.219979763,52.3745307922],"type":"Point"}
}