{
  "type": "Feature",
  "properties": {
    "iso:country":"NL",
    "sg:address":"Grt Markt 43",
    "sg:city":"Almere",
    "sg:orig_category":"Opticiens",
    "sg:phone":"+31 36 534 2532",
    "sg:postcode":"1315 JB",
    "sg:province":"NL.",
    "wof:name":"Eyes",
    "wof:placetype":"venue"
},
  "geometry": {"coordinates":[5.219979763,52.3745307922],"type":"Point"}
}