{
  "type": "Feature",
  "properties": {
    "addr:full":"Agorawg 11 Lelystad Flevoland 8224 BZ",
    "addr:housenumber":"11",
    "addr:postcode":"8224 bz",
    "addr:street":"Agorawg;Flevoland",
    "iso:country":"NL",
    "sg:address":"Agorawg 11",
    "sg:city":"Lelystad",
    "sg:classifiers":[
        {
            "category":"Travel",
            "subcategory":"Hotels & Motels",
            "type":"Entertainment"
        }
    ],
    "sg:phone":"+31 320 242 444",
    "sg:postcode":"8224 BZ",
    "sg:province":"Flevoland",
    "wof:name":"Mercure",
    "wof:placetype":"venue"
},
  "geometry": {"coordinates":[5.477221,52.510361],"type":"Point"}
}