{
  "type": "Feature",
  "properties": {
    "addr:full":"J Israelsstr 43A Groningen Groningen 9718 GC",
    "addr:housenumber":"43a",
    "addr:postcode":"9718 gc",
    "iso:country":"NL",
    "sg:address":"J Israelsstr 43A",
    "sg:city":"Groningen",
    "sg:orig_category":"Psychotherapeuten",
    "sg:phone":"+31 50 313 1480",
    "sg:postcode":"9718 GC",
    "sg:province":"Groningen",
    "wof:name":"Jeronimus, Drs D",
    "wof:placetype":"venue"
},
  "geometry": {"coordinates":[6.553581,53.216427],"type":"Point"}
}