{
  "type": "Feature",
  "properties": {
    "addr:full":"Dirk Klompweg 110 Bergen Nh North Holland 1861 NG",
    "addr:housenumber":"110",
    "addr:postcode":"1861 ng",
    "addr:street":"Dirk Klompweg;Nh North",
    "iso:country":"NL",
    "sg:address":"Dirk Klompweg 110",
    "sg:city":"Bergen Nh",
    "sg:orig_category":"Fotostudio'S And Fotografen",
    "sg:phone":"+31 72 589 7485",
    "sg:postcode":"1861 NG",
    "sg:province":"North Holland",
    "wof:name":"Highway Productions International",
    "wof:placetype":"venue"
},
  "geometry": {"coordinates":[4.7067,52.662888],"type":"Point"}
}