{
  "type": "Feature",
  "properties": {
    "addr:full":"Losplaatsweg 10 Noordwijk Zh Zuid-Holland 2201 CV",
    "addr:housenumber":"10",
    "addr:postcode":"2201 cv",
    "addr:street":"Losplaatsweg",
    "iso:country":"NL",
    "sg:address":"Losplaatsweg 10",
    "sg:city":"Noordwijk Zh",
    "sg:orig_category":"Metaalwerken",
    "sg:phone":"+31 71 361 5329",
    "sg:postcode":"2201 CV",
    "sg:province":"Zuid-Holland",
    "wof:name":"Jan Smit Systeemplafonds Bv",
    "wof:placetype":"venue"
},
  "geometry": {"coordinates":[4.442041,52.233196],"type":"Point"}
}