{
  "type": "Feature",
  "properties": {
    "iso:country":"NL",
    "sg:address":"Plecht 5",
    "sg:city":"Oss",
    "sg:orig_category":"Natuurgeneeskundigen",
    "sg:phone":"+31 412 650 574",
    "sg:postcode":"5345 BT",
    "sg:province":"Noord-Brabant",
    "wof:name":"Nagel-Heijnen, M",
    "wof:placetype":"venue"
},
  "geometry": {"coordinates":[-91.224678,44.575642],"type":"Point"}
}