{
  "type": "Feature",
  "properties": {
    "iso:country":"NL",
    "sg:address":"Ptr Kusterswg 24",
    "sg:city":"Cadier En Keer",
    "sg:orig_category":"Verenigingen En Stichtingen",
    "sg:phone":"+31 43 407 2589",
    "sg:postcode":"6267 NL",
    "sg:province":"Limburg",
    "wof:name":"Unicef",
    "wof:placetype":"venue"
},
  "geometry": {"coordinates":[5.76826,50.826172],"type":"Point"}
}