{
  "type": "Feature",
  "properties": {
    "addr:full":"A Verherentstr 5 Heemskerk North Holland 1961 GD",
    "addr:housenumber":"5",
    "addr:postcode":"1961 gd",
    "iso:country":"NL",
    "sg:address":"A Verherentstr 5",
    "sg:city":"Heemskerk",
    "sg:orig_category":"Omroep",
    "sg:phone":"+31 251 233 333",
    "sg:postcode":"1961 GD",
    "sg:province":"North Holland",
    "wof:name":"Radio Heemskerk",
    "wof:placetype":"venue"
},
  "geometry": {"coordinates":[4.674024,52.512024],"type":"Point"}
}