{
  "type": "Feature",
  "properties": {
    "iso:country":"NL",
    "sg:address":"Mantingerdk 12",
    "sg:city":"Mantinge",
    "sg:orig_category":"Adviesbureaus Bedrijfsorganisatie",
    "sg:phone":"+31 593 552 328",
    "sg:postcode":"9436 PN",
    "sg:province":"Drenthe",
    "wof:name":"Shield Star Bv",
    "wof:placetype":"venue"
},
  "geometry": {"coordinates":[6.63133,52.790195],"type":"Point"}
}