{
  "type": "Feature",
  "properties": {
    "addr:full":"Mantingerdk 12 Mantinge Drenthe 9436 PN",
    "addr:housenumber":"12",
    "addr:postcode":"9436 pn",
    "addr:street":"Mantingerdk",
    "iso:country":"NL",
    "sg:address":"Mantingerdk 12",
    "sg:city":"Mantinge",
    "sg:orig_category":"Adviesbureaus Bedrijfsorganisatie",
    "sg:phone":"+31 593 552 328",
    "sg:postcode":"9436 PN",
    "sg:province":"Drenthe",
    "wof:name":"Shield Star Bv",
    "wof:placetype":"venue"
},
  "geometry": {"coordinates":[6.63133,52.790195],"type":"Point"}
}