{
  "type": "Feature",
  "properties": {
    "iso:country":"NL",
    "sg:address":"Nieuwe S-Gravelandseweg 1",
    "sg:city":"Bussum",
    "sg:orig_category":"Bloemen And Planten",
    "sg:phone":"+31 35 693 1877",
    "sg:postcode":"1405 HH",
    "sg:province":"North Holland",
    "wof:name":"Mille- Fleurs",
    "wof:placetype":"venue"
},
  "geometry": {"coordinates":[5.157189846,52.278301239],"type":"Point"}
}