{
  "type": "Feature",
  "properties": {
    "addr:full":"Zevenend 49 Laren Nh North Holland 1251 RL",
    "addr:housenumber":"49",
    "addr:postcode":"1251 rl",
    "addr:street":"Zevenend;Nh North",
    "iso:country":"NL",
    "sg:address":"Zevenend 49",
    "sg:city":"Laren Nh",
    "sg:orig_category":"Meubelmakerijen",
    "sg:phone":"+31 35 538 9709",
    "sg:postcode":"1251 RL",
    "sg:province":"North Holland",
    "wof:name":"Laurens Veltmeijer, Meubelmakerij",
    "wof:placetype":"venue"
},
  "geometry": {"coordinates":[5.229181,52.252003],"type":"Point"}
}