{
  "type": "Feature",
  "properties": {
    "addr:full":"Hommelstraat 45 Arnhem Gelderland 6828 AJ",
    "addr:housenumber":"45",
    "addr:postcode":"6828 aj",
    "addr:street":"Hommelstraat",
    "iso:country":"NL",
    "sg:address":"Hommelstraat 45",
    "sg:city":"Arnhem",
    "sg:orig_category":"Juweliers",
    "sg:phone":"+31 26 442 8663",
    "sg:postcode":"6828 AJ",
    "sg:province":"Gelderland",
    "wof:name":"Karatay Sarafiye",
    "wof:placetype":"venue"
},
  "geometry": {"coordinates":[5.914156,51.984867],"type":"Point"}
}