{
  "type": "Feature",
  "properties": {
    "addr:full":"Aldringastraat 3 Niekerk Grootegast Groningen 9822 AM",
    "addr:housenumber":"3",
    "addr:postcode":"9822",
    "addr:street":"Aldringastraat",
    "iso:country":"NL",
    "sg:address":"Aldringastraat 3",
    "sg:city":"Niekerk Grootegast",
    "sg:orig_category":"Banken And Kredietinstellingen",
    "sg:phone":"+31 594 554 444",
    "sg:postcode":"9822 AM",
    "sg:province":"Groningen",
    "wof:name":"Rabobank",
    "wof:placetype":"venue"
},
  "geometry": {"coordinates":[6.353531,53.22567],"type":"Point"}
}