{
  "type": "Feature",
  "properties": {
    "addr:full":"Biezelingeplein 9 Rotterdam Zuid-Holland 3086 SB",
    "addr:housenumber":"9",
    "addr:postcode":"3086 sb",
    "addr:street":"Biezelingeplein",
    "iso:country":"NL",
    "sg:address":"Biezelingeplein 9",
    "sg:city":"Rotterdam",
    "sg:orig_category":"Artsen And Specialisten",
    "sg:phone":"+31 10 480 4575",
    "sg:postcode":"3086 SB",
    "sg:province":"Zuid-Holland",
    "wof:name":"C.M. Davidsz",
    "wof:placetype":"venue"
},
  "geometry": {"coordinates":[4.459378,51.871529],"type":"Point"}
}