{
  "type": "Feature",
  "properties": {
    "addr:full":"Ptr Ullingsstr 3 Budel Schoot North Brabant 6023 AM",
    "addr:housenumber":"3",
    "addr:postcode":"6023",
    "addr:street":"Ullingsstr",
    "iso:country":"NL",
    "sg:address":"Ptr Ullingsstr 3",
    "sg:city":"Budel Schoot",
    "sg:orig_category":"Scholen Voor Basisonderwijs",
    "sg:phone":"+31 495 494 343",
    "sg:postcode":"6023 AM",
    "sg:province":"North Brabant",
    "wof:name":"Bert Van Gils Rk",
    "wof:placetype":"venue"
},
  "geometry": {"coordinates":[5.564961,51.251881],"type":"Point"}
}