{
  "type": "Feature",
  "properties": {
    "addr:full":"Brugstr 11 Roermond Limburg 6041 EP",
    "addr:housenumber":"11",
    "addr:postcode":"6041 ep",
    "addr:street":"Brugstr",
    "iso:country":"NL",
    "sg:address":"Brugstr 11",
    "sg:city":"Roermond",
    "sg:orig_category":"Bloemen En Planten",
    "sg:phone":"+31 475 317 722",
    "sg:postcode":"6041 EP",
    "sg:province":"Limburg",
    "wof:name":"Centrum Bv, 'T",
    "wof:placetype":"venue"
},
  "geometry": {"coordinates":[5.98481,51.194424],"type":"Point"}
}