{
  "type": "Feature",
  "properties": {
    "addr:full":"Noordplein 113 Rotterdam Zuid-Holland 3035 EC",
    "addr:housenumber":"113",
    "addr:postcode":"3035 ec",
    "addr:street":"Noordplein",
    "iso:country":"NL",
    "sg:address":"Noordplein 113",
    "sg:city":"Rotterdam",
    "sg:classifiers":[
        {
            "category":"Fast Food",
            "type":"Food & Drink"
        }
    ],
    "sg:phone":"+31 10 465 8814",
    "sg:postcode":"3035 EC",
    "sg:province":"Zuid-Holland",
    "sg:tags":[
        "afhaal",
        "restaurant"
    ],
    "wof:name":"Grillroom Noordplein",
    "wof:placetype":"venue"
},
  "geometry": {"coordinates":[4.484078,51.930927],"type":"Point"}
}