{
  "type": "Feature",
  "properties": {
    "addr:full":"Pr Bisschopsngl 22 Maastricht Limburg 6211 JX",
    "addr:housenumber":"22",
    "addr:postcode":"6211 jx",
    "iso:country":"NL",
    "sg:address":"Pr Bisschopsngl 22",
    "sg:city":"Maastricht",
    "sg:classifiers":[
        {
            "category":"Professional",
            "subcategory":"Accounting & Tax Preparation",
            "type":"Services"
        }
    ],
    "sg:phone":"+31 43 321 7443",
    "sg:postcode":"6211 JX",
    "sg:province":"Limburg",
    "sg:tags":[
        "accountant",
        "en",
        "-kantoren",
        "register-"
    ],
    "wof:name":"Kpmg",
    "wof:placetype":"venue"
},
  "geometry": {"coordinates":[5.68829,50.849831],"type":"Point"}
}