{
  "type": "Feature",
  "properties": {
    "addr:full":"Varkensmarkt 13 Culemborg Gelderland 4101 CK",
    "addr:housenumber":"13",
    "addr:postcode":"4101 ck",
    "addr:street":"Varkensmarkt;Gelderland",
    "iso:country":"NL",
    "sg:address":"Varkensmarkt 13",
    "sg:city":"Culemborg",
    "sg:orig_category":"Woninginrichting",
    "sg:phone":"+31 345 512 118",
    "sg:postcode":"4101 CK",
    "sg:province":"Gelderland",
    "wof:name":"Irma",
    "wof:placetype":"venue"
},
  "geometry": {"coordinates":[5.2260518074,51.9554023743],"type":"Point"}
}