{
  "type": "Feature",
  "properties": {
    "iso:country":"NL",
    "sg:address":"Molukkenstraat 200",
    "sg:city":"Amsterdam",
    "sg:orig_category":"Bedrijfs- And Managementsconsultants",
    "sg:phone":"+31 20 465 7777",
    "sg:postcode":"1098 TW",
    "sg:province":"North Holland",
    "wof:name":"Van Kessel Select",
    "wof:placetype":"venue"
},
  "geometry": {"coordinates":[4.940942,52.358059],"type":"Point"}
}