{
  "type": "Feature",
  "properties": {
    "addr:full":"Hogebroeksweg 32 Raalte Overijssel 8102 RK",
    "addr:housenumber":"32",
    "addr:postcode":"8102 rk",
    "addr:street":"Hogebroeksweg",
    "iso:country":"NL",
    "sg:address":"Hogebroeksweg 32",
    "sg:city":"Raalte",
    "sg:orig_category":"Architecten",
    "sg:phone":"+31 572 362 263",
    "sg:postcode":"8102 RK",
    "sg:province":"Overijssel",
    "wof:name":"Brewer Horticultural Consultants Bv",
    "wof:placetype":"venue"
},
  "geometry": {"coordinates":[6.26908,52.426189],"type":"Point"}
}