{
  "type": "Feature",
  "properties": {
    "addr:full":"Westerwg 21 Limmen Noord-Holland 1906 EE",
    "addr:housenumber":"21",
    "addr:postcode":"1906 ee",
    "addr:street":"Westerwg",
    "iso:country":"NL",
    "sg:address":"Westerwg 21",
    "sg:city":"Limmen",
    "sg:orig_category":"Koeriersdiensten",
    "sg:phone":"+31 72 505 3663",
    "sg:postcode":"1906 EE",
    "sg:province":"Noord-Holland",
    "wof:name":"Groot, J E",
    "wof:placetype":"venue"
},
  "geometry": {"coordinates":[4.692436,52.570141],"type":"Point"}
}