{
  "type": "Feature",
  "properties": {
    "addr:full":"Postbus 40151 Zwolle Overijssel 8004 DD",
    "addr:postcode":"40151;8004 dd",
    "addr:street":"Postbus",
    "iso:country":"NL",
    "sg:address":"Postbus 40151",
    "sg:city":"Zwolle",
    "sg:orig_category":"Kantoorbenodigdheden",
    "sg:phone":"+31 38 465 1038",
    "sg:postcode":"8004 DD",
    "sg:province":"Overijssel",
    "sg:website":"HTTP://www.deschooltas.nl",
    "wof:name":"Schooltas, De",
    "wof:placetype":"venue"
},
  "geometry": {"coordinates":[6.0924301147,52.5122299194],"type":"Point"}
}