{
  "type": "Feature",
  "properties": {
    "addr:full":"Pr Julianastr 1 Vianen Zh South Holland 4132 CA",
    "addr:housenumber":"1",
    "addr:postcode":"zh;4132 ca",
    "iso:country":"NL",
    "sg:address":"Pr Julianastr 1",
    "sg:city":"Vianen Zh",
    "sg:orig_category":"Schilders",
    "sg:phone":"+31 347 372 790",
    "sg:postcode":"4132 CA",
    "sg:province":"South Holland",
    "wof:name":"Beest, Marcel Van",
    "wof:placetype":"venue"
},
  "geometry": {"coordinates":[5.096152,51.992416],"type":"Point"}
}