{
  "type": "Feature",
  "properties": {
    "addr:full":"Marijkestraat 2 Wateringen Zuid-Holland 2291 TK",
    "addr:housenumber":"2",
    "addr:postcode":"2291 tk",
    "addr:street":"Marijkestraat",
    "iso:country":"NL",
    "sg:address":"Marijkestraat 2",
    "sg:city":"Wateringen",
    "sg:orig_category":"Bloemen And Planten",
    "sg:phone":"+31 174 292 014",
    "sg:postcode":"2291 TK",
    "sg:province":"Zuid-Holland",
    "wof:name":"Noman Flowers Bv",
    "wof:placetype":"venue"
},
  "geometry": {"coordinates":[4.26573,52.026638],"type":"Point"}
}