{
  "type": "Feature",
  "properties": {
    "addr:full":"Veldsngl 29 Malden Gelderland 6581 TC",
    "addr:housenumber":"29",
    "addr:postcode":"6581 tc",
    "addr:street":"Veldsngl;Gelderland",
    "iso:country":"NL",
    "sg:address":"Veldsngl 29",
    "sg:city":"Malden",
    "sg:orig_category":"Peuterspeelzalen",
    "sg:phone":"+31 24 358 5889",
    "sg:postcode":"6581 TC",
    "sg:province":"Gelderland",
    "wof:name":"Peuterspeelzalen Malden, Ver",
    "wof:placetype":"venue"
},
  "geometry": {"coordinates":[5.852469,51.781147],"type":"Point"}
}