{
  "type": "Feature",
  "properties": {
    "addr:full":"Kromstr 10 Valkenswaard North Brabant 5554 NH",
    "addr:housenumber":"10",
    "addr:postcode":"5554 nh",
    "addr:street":"Kromstr",
    "iso:country":"NL",
    "sg:address":"Kromstr 10",
    "sg:city":"Valkenswaard",
    "sg:orig_category":"Verenigingen En Stichtingen",
    "sg:phone":"+31 40 201 9939",
    "sg:postcode":"5554 NH",
    "sg:province":"North Brabant",
    "wof:name":"Ouderensoci\u00f9teit Adelaar, Sticht",
    "wof:placetype":"venue"
},
  "geometry": {"coordinates":[5.453353,51.349266],"type":"Point"}
}