{
  "type": "Feature",
  "properties": {
    "addr:full":"Henricuskade 67 'S-Gravenhage South Holland 2497 NB",
    "addr:housenumber":"67",
    "addr:postcode":"2497 nb",
    "addr:street":"Henricuskade",
    "iso:country":"NL",
    "sg:address":"Henricuskade 67",
    "sg:city":"'S-Gravenhage",
    "sg:orig_category":"Honden- En Kattentrimsalons",
    "sg:phone":"+31 6 24920535",
    "sg:postcode":"2497 NB",
    "sg:province":"South Holland",
    "sg:website":"http://www.trimboerderij.nl",
    "wof:name":"Trimboerderij, De",
    "wof:placetype":"venue"
},
  "geometry": {"coordinates":[4.368334,52.031742],"type":"Point"}
}