{
  "type": "Feature",
  "properties": {
    "addr:full":"Prinsengracht 715 Amsterdam Noord-Holland 1017 JW",
    "addr:housenumber":"715",
    "addr:postcode":"1017 jw",
    "addr:street":"Prinsengracht",
    "iso:country":"NL",
    "sg:address":"Prinsengracht 715",
    "sg:city":"Amsterdam",
    "sg:orig_category":"Fitnesscentra",
    "sg:phone":"+31 20 625 4100",
    "sg:postcode":"1017 JW",
    "sg:province":"Noord-Holland",
    "wof:name":"Mandate Amsterdam",
    "wof:placetype":"venue"
},
  "geometry": {"coordinates":[4.885445,52.364799],"type":"Point"}
}