{
  "type": "Feature",
  "properties": {
    "addr:full":"De Kwakels 2 Zaandam Noord-Holland 1509 BX",
    "addr:housenumber":"2",
    "addr:postcode":"1509 bx",
    "addr:street":"De Kwakels",
    "iso:country":"NL",
    "sg:address":"De Kwakels 2",
    "sg:city":"Zaandam",
    "sg:orig_category":"Watersportartikelen",
    "sg:phone":"+31 75 670 2312",
    "sg:postcode":"1509 BX",
    "sg:province":"Noord-Holland",
    "wof:name":"Hut Van De Kapitein, De",
    "wof:placetype":"venue"
},
  "geometry": {"coordinates":[4.8172049522,52.4726638794],"type":"Point"}
}