{
  "type": "Feature",
  "properties": {
    "addr:full":"Laagraven 59 Nieuwegein Utrecht 3439 LL",
    "addr:housenumber":"59",
    "addr:postcode":"3439 ll",
    "addr:street":"Laagraven",
    "iso:country":"NL",
    "sg:address":"Laagraven 59",
    "sg:city":"Nieuwegein",
    "sg:orig_category":"Koffers En Tassen - Fabrieken En Groothandel",
    "sg:phone":"+31 30 267 2828",
    "sg:postcode":"3439 LL",
    "sg:province":"Utrecht",
    "wof:name":"Europalace",
    "wof:placetype":"venue"
},
  "geometry": {"coordinates":[5.123569,52.051079],"type":"Point"}
}