{
  "type": "Feature",
  "properties": {
    "addr:full":"De Koppele 391 Eindhoven North Brabant 5632 LN",
    "addr:housenumber":"391",
    "addr:postcode":"5632 ln",
    "addr:street":"De Koppele",
    "iso:country":"NL",
    "sg:address":"De Koppele 391",
    "sg:city":"Eindhoven",
    "sg:orig_category":"Verenigingen En Stichtingen",
    "sg:phone":"+31 40 290 3361",
    "sg:postcode":"5632 LN",
    "sg:province":"North Brabant",
    "wof:name":"Edc Int, Sticht",
    "wof:placetype":"venue"
},
  "geometry": {"coordinates":[5.491051,51.479557],"type":"Point"}
}