{
  "type": "Feature",
  "properties": {
    "addr:full":"Hollandseln 3 Hilversum North Holland 1213 AM",
    "addr:housenumber":"3",
    "addr:postcode":"1213",
    "addr:street":"Hollandseln",
    "iso:country":"NL",
    "sg:address":"Hollandseln 3",
    "sg:city":"Hilversum",
    "sg:orig_category":"Achtergrondmuziek",
    "sg:phone":"+31 35 623 8896",
    "sg:postcode":"1213 AM",
    "sg:province":"North Holland",
    "sg:website":"http://www.musicuniverse.com",
    "wof:name":"Musicuniverse",
    "wof:placetype":"venue"
},
  "geometry": {"coordinates":[5.181405,52.219048],"type":"Point"}
}