{
  "type": "Feature",
  "properties": {
    "iso:country":"NL",
    "sg:address":"Teleportboulev 110",
    "sg:city":"Amsterdam",
    "sg:orig_category":"Reisbureaus",
    "sg:phone":"+31 20 475 1357",
    "sg:postcode":"1043 EJ",
    "sg:province":"North Holland",
    "sg:website":"http://www.paradisegettaways.com",
    "wof:name":"Paradise",
    "wof:placetype":"venue"
},
  "geometry": {"coordinates":[4.840348,52.387581],"type":"Point"}
}