{
  "type": "Feature",
  "properties": {
    "addr:full":"Zilkerduinweg 358 De Zilk Zuid-Holland 2191 AT",
    "addr:housenumber":"358",
    "addr:postcode":"2191",
    "addr:street":"Zilkerduinweg",
    "iso:country":"NL",
    "sg:address":"Zilkerduinweg 358",
    "sg:city":"De Zilk",
    "sg:orig_category":"Huizensloop And Bouwrijp Maken",
    "sg:phone":"+31 252 517 705",
    "sg:postcode":"2191 AT",
    "sg:province":"Zuid-Holland",
    "wof:name":"W.J.M. Duivenvoorde De Zilk Bv",
    "wof:placetype":"venue"
},
  "geometry": {"coordinates":[4.555068,52.308712],"type":"Point"}
}