{
  "type": "Feature",
  "properties": {
    "addr:full":"Moerbeilaan 43 Hilversum Noord-Holland 1214 LV",
    "addr:housenumber":"43",
    "addr:postcode":"1214",
    "addr:street":"Moerbeilaan",
    "iso:country":"NL",
    "sg:address":"Moerbeilaan 43",
    "sg:city":"Hilversum",
    "sg:orig_category":"Public Relationbureaus",
    "sg:phone":"+31 35 623 9241",
    "sg:postcode":"1214 LV",
    "sg:province":"Noord-Holland",
    "wof:name":"Mr. P.P. Ijkelenstam",
    "wof:placetype":"venue"
},
  "geometry": {"coordinates":[5.168123,52.208469],"type":"Point"}
}