{
  "type": "Feature",
  "properties": {
    "addr:full":"Saenredamstraat 17Zw Haarlem North Holland 2021 ZM",
    "addr:housenumber":"17zw",
    "addr:postcode":"2021 zm",
    "addr:street":"Saenredamstraat",
    "iso:country":"NL",
    "sg:address":"Saenredamstraat 17Zw",
    "sg:city":"Haarlem",
    "sg:orig_category":"Modellenbureaus",
    "sg:phone":"+31 23 526 8196",
    "sg:postcode":"2021 ZM",
    "sg:province":"North Holland",
    "wof:name":"Chameleons International",
    "wof:placetype":"venue"
},
  "geometry": {"coordinates":[4.638453,52.392235],"type":"Point"}
}