{
  "type": "Feature",
  "properties": {
    "addr:full":"Raadhuisstraat 77 Heemstede Noord-Holland 2101 HD",
    "addr:housenumber":"77",
    "addr:postcode":"2101 hd",
    "addr:street":"Raadhuisstraat",
    "iso:country":"NL",
    "sg:address":"Raadhuisstraat 77",
    "sg:city":"Heemstede",
    "sg:classifiers":[
        {
            "category":"Bakery",
            "type":"Food & Drink"
        }
    ],
    "sg:phone":"+31 23 528 2374",
    "sg:postcode":"2101 HD",
    "sg:province":"Noord-Holland",
    "sg:tags":[
        "brood",
        "banket"
    ],
    "wof:name":"Vof Th. Van Dijk",
    "wof:placetype":"venue"
},
  "geometry": {"coordinates":[4.62073,52.348965],"type":"Point"}
}