{
  "type": "Feature",
  "properties": {
    "addr:full":"Nieuwpoortstraat 88 Amsterdam Noord-Holland 1055 RZ",
    "addr:housenumber":"88",
    "addr:postcode":"1055 rz",
    "addr:street":"Nieuwpoortstraat",
    "iso:country":"NL",
    "sg:address":"Nieuwpoortstraat 88",
    "sg:city":"Amsterdam",
    "sg:orig_category":"Werving And Selectie Van Vast Personeel",
    "sg:phone":"+31 20 682 8796",
    "sg:postcode":"1055 RZ",
    "sg:province":"Noord-Holland",
    "wof:name":"Adviesbureau I & E Transfer",
    "wof:placetype":"venue"
},
  "geometry": {"coordinates":[4.8577780724,52.3842086792],"type":"Point"}
}