{
  "type": "Feature",
  "properties": {
    "addr:full":"Julianalaan 37 Kaag Zuid-Holland 2159 LD",
    "addr:housenumber":"37",
    "addr:postcode":"2159 ld",
    "addr:street":"Julianalaan",
    "iso:country":"NL",
    "sg:address":"Julianalaan 37",
    "sg:city":"Kaag",
    "sg:orig_category":"Watersport-, Sport- And Kampeerbenodigdheden Verhuur",
    "sg:phone":"+31 252 544 205",
    "sg:postcode":"2159 LD",
    "sg:province":"Zuid-Holland",
    "wof:name":"Zeilbotenverhuur Het Witte Huis",
    "wof:placetype":"venue"
},
  "geometry": {"coordinates":[4.5565562248,52.2134742737],"type":"Point"}
}