{
  "type": "Feature",
  "properties": {
    "iso:country":"NL",
    "sg:address":"Ravenswade 82",
    "sg:city":"Nieuwegein",
    "sg:orig_category":"Zuivelindustrie - Apparaten En Installaties",
    "sg:phone":"+31 30 280 1203",
    "sg:postcode":"3439 LD",
    "sg:province":"Utrecht",
    "sg:website":"http://www.parc.club.tip.nl",
    "wof:name":"Parc Enterprise Int",
    "wof:placetype":"venue"
},
  "geometry": {"coordinates":[5.114309,52.050598],"type":"Point"}
}