{
  "type": "Feature",
  "properties": {
    "iso:country":"NL",
    "sg:address":"Postbus 49",
    "sg:city":"Mierlo",
    "sg:orig_category":"Wegenbouw",
    "sg:phone":"+31 492 430 221",
    "sg:postcode":"5730 AA",
    "sg:province":"Noord-Brabant",
    "wof:name":"Kerkhof",
    "wof:placetype":"venue"
},
  "geometry": {"coordinates":[5.6200399399,51.4437217712],"type":"Point"}
}