{
  "type": "Feature",
  "properties": {
    "iso:country":"NL",
    "sg:address":"Noorderstraat 265",
    "sg:city":"Sappemeer",
    "sg:orig_category":"Huizensloop And Bouwrijp Maken",
    "sg:phone":"+31 598 394 623",
    "sg:postcode":"9611 AG",
    "sg:province":"Groningen",
    "wof:name":"Aannemersbedrijf R.Brondijk Bv",
    "wof:placetype":"venue"
},
  "geometry": {"coordinates":[6.802333,53.164593],"type":"Point"}
}