{
  "type": "Feature",
  "properties": {
    "addr:full":"Ruiterweg 3 Eibergen Gelderland 7152 DE",
    "addr:housenumber":"3",
    "addr:postcode":"7152 de",
    "addr:street":"Ruiterweg;Gelderland",
    "iso:country":"NL",
    "sg:address":"Ruiterweg 3",
    "sg:city":"Eibergen",
    "sg:orig_category":"Loodgieterswerk, Verwarming And Sanitaire Installaties",
    "sg:phone":"+31 544 462 950",
    "sg:postcode":"7152 DE",
    "sg:province":"Gelderland",
    "wof:name":"J.T.M. Zieverink",
    "wof:placetype":"venue"
},
  "geometry": {"coordinates":[6.643872,52.059929],"type":"Point"}
}