{
  "type": "Feature",
  "properties": {
    "addr:full":"Ganzenweel 17 Terheijden Noord-Brabant 4844 TK",
    "addr:housenumber":"17",
    "addr:postcode":"4844 tk",
    "addr:street":"Ganzenweel",
    "iso:country":"NL",
    "sg:address":"Ganzenweel 17",
    "sg:city":"Terheijden",
    "sg:orig_category":"Goederenvervoer Over De Weg",
    "sg:phone":"+31 76 593 3430",
    "sg:postcode":"4844 TK",
    "sg:province":"Noord-Brabant",
    "wof:name":"Verhoeven Transport",
    "wof:placetype":"venue"
},
  "geometry": {"coordinates":[4.760278,51.645668],"type":"Point"}
}