{
  "type": "Feature",
  "properties": {
    "iso:country":"NL",
    "sg:address":"Prins Bernhardstraat 21",
    "sg:city":"Asten",
    "sg:classifiers":[
        {
            "category":"Fast Food",
            "type":"Food & Drink"
        }
    ],
    "sg:phone":"+31 493 695 842",
    "sg:postcode":"5721 GA",
    "sg:province":"North Brabant",
    "sg:tags":[
        "afhaal",
        "restaurant"
    ],
    "wof:name":"Grillroom Pyramide",
    "wof:placetype":"venue"
},
  "geometry": {"coordinates":[5.7462601662,51.4054756165],"type":"Point"}
}