{
  "type": "Feature",
  "properties": {
    "addr:full":"Heense Molenwg 23 De Heen Noord-Brabant 4655 TB",
    "addr:housenumber":"23",
    "addr:postcode":"4655 tb",
    "iso:country":"NL",
    "sg:address":"Heense Molenwg 23",
    "sg:city":"De Heen",
    "sg:orig_category":"Evenementenverzorging",
    "sg:phone":"+31 167 502 621",
    "sg:postcode":"4655 TB",
    "sg:province":"Noord-Brabant",
    "sg:website":"http://www.akkermansoutdoor.nl",
    "wof:name":"Akkermans, Outdoor Centre",
    "wof:placetype":"venue"
},
  "geometry": {"coordinates":[4.245795,51.607723],"type":"Point"}
}