{
  "type": "Feature",
  "properties": {
    "iso:country":"NL",
    "sg:address":"Hooghuisstr 11",
    "sg:city":"Eindhoven",
    "sg:orig_category":"Herenkleding",
    "sg:phone":"+31 40 293 9938",
    "sg:postcode":"5611 GS",
    "sg:province":"Noord-Brabant",
    "wof:name":"Mensroom Bv",
    "wof:placetype":"venue"
},
  "geometry": {"coordinates":[5.478052,51.437931],"type":"Point"}
}