{
  "type": "Feature",
  "properties": {
    "iso:country":"NL",
    "sg:address":"Groenstraat 8-8A",
    "sg:city":"Geleen",
    "sg:orig_category":"Werving And Selectie Van Tijdelijk Personeel And Uitzendkantoren",
    "sg:phone":"+31 46 423 1040",
    "sg:postcode":"6162 ER",
    "sg:province":"Limburg",
    "wof:name":"Manpower Uitzendorganisatie Bv",
    "wof:placetype":"venue"
},
  "geometry": {"coordinates":[5.8303928375,50.9708862305],"type":"Point"}
}