{
  "type": "Feature",
  "properties": {
    "addr:full":"Zuid - Westsingel 196 Bergen Op Zoom North Brabant 4611 KH",
    "addr:housenumber":"196",
    "addr:postcode":"4611 kh",
    "addr:street":"Westsingel",
    "iso:country":"NL",
    "sg:address":"Zuid - Westsingel 196",
    "sg:city":"Bergen Op Zoom",
    "sg:orig_category":"Keramische Producten Fab",
    "sg:phone":"+31 164 259 334",
    "sg:postcode":"4611 KH",
    "sg:province":"North Brabant",
    "wof:name":"Pottenbakkerij Horletoet",
    "wof:placetype":"venue"
},
  "geometry": {"coordinates":[4.282006,51.491959],"type":"Point"}
}