{
  "type": "Feature",
  "properties": {
    "iso:country":"NL",
    "sg:address":"Grutterij 1",
    "sg:city":"Amstelveen",
    "sg:orig_category":"Hout Gh",
    "sg:phone":"+31 20 640 4906",
    "sg:postcode":"1185 ZT",
    "sg:province":"Noord-Holland",
    "wof:name":"Gamma",
    "wof:placetype":"venue"
},
  "geometry": {"coordinates":[4.83471,52.280964],"type":"Point"}
}