{
  "type": "Feature",
  "properties": {
    "addr:full":"Snydersstr 4 Lelystad Flevoland 8224 AA",
    "addr:housenumber":"4",
    "addr:postcode":"8224 aa",
    "addr:street":"Snydersstr;Flevoland",
    "iso:country":"NL",
    "sg:address":"Snydersstr 4",
    "sg:city":"Lelystad",
    "sg:orig_category":"Natuurvoeding En Reformartikelen",
    "sg:phone":"+31 320 244 366",
    "sg:postcode":"8224 AA",
    "sg:province":"Flevoland",
    "wof:name":"Vomeko",
    "wof:placetype":"venue"
},
  "geometry": {"coordinates":[5.483477,52.519264],"type":"Point"}
}