{
  "type": "Feature",
  "properties": {
    "addr:full":"Hemonyln 26 Amsterdam North Holland 1074 BJ",
    "addr:housenumber":"26",
    "addr:postcode":"1074 bj",
    "addr:street":"Hemonyln",
    "iso:country":"NL",
    "sg:address":"Hemonyln 26",
    "sg:city":"Amsterdam",
    "sg:orig_category":"Artsen - Huisartsen",
    "sg:phone":"+31 20 676 6974",
    "sg:postcode":"1074 BJ",
    "sg:province":"North Holland",
    "wof:name":"Doorenbosch, R",
    "wof:placetype":"venue"
},
  "geometry": {"coordinates":[4.901759,52.357616],"type":"Point"}
}