{
  "type": "Feature",
  "properties": {
    "addr:full":"S V Wurtembergln 7 Eindhoven Noord-Brabant 5616 BM",
    "addr:housenumber":"7",
    "addr:postcode":"5616 bm",
    "addr:street":"Wurtembergln",
    "iso:country":"NL",
    "sg:address":"S V Wurtembergln 7",
    "sg:city":"Eindhoven",
    "sg:orig_category":"Woningstoffeerders",
    "sg:phone":"+31 40 252 9129",
    "sg:postcode":"5616 BM",
    "sg:province":"Noord-Brabant",
    "wof:name":"Nefkens, Jeroen",
    "wof:placetype":"venue"
},
  "geometry": {"coordinates":[5.4841051102,51.4344711304],"type":"Point"}
}