{
  "type": "Feature",
  "properties": {
    "iso:country":"NL",
    "sg:address":"Plechelmusstraat 23",
    "sg:city":"De Lutte",
    "sg:orig_category":"Verzekeringen",
    "sg:phone":"+31 541 551 330",
    "sg:postcode":"7587 AL",
    "sg:province":"NL.08",
    "wof:name":"H.J.A. Nijhuis",
    "wof:placetype":"venue"
},
  "geometry": {"coordinates":[6.985878,52.316872],"type":"Point"}
}