{
  "type": "Feature",
  "properties": {
    "addr:full":"Jan Glaudemanslaan 7 Driebergen-Rijsenburg Utrecht 3972 EW",
    "addr:housenumber":"7",
    "addr:postcode":"3972 ew",
    "addr:street":"Jan Glaudemanslaan",
    "iso:country":"NL",
    "sg:address":"Jan Glaudemanslaan 7",
    "sg:city":"Driebergen-Rijsenburg",
    "sg:orig_category":"Diverse Grafische Activiteiten",
    "sg:phone":"+31 343 514 876",
    "sg:postcode":"3972 EW",
    "sg:province":"Utrecht",
    "wof:name":"Binderij Hoekstra-Van Dijk",
    "wof:placetype":"venue"
},
  "geometry": {"coordinates":[5.272536,52.056683],"type":"Point"}
}