{
  "type": "Feature",
  "properties": {
    "addr:full":"Beatrixlaan 6 Melissant Zuid-Holland 3248 AB",
    "addr:housenumber":"6",
    "addr:postcode":"3248 ab",
    "addr:street":"Beatrixlaan",
    "iso:country":"NL",
    "sg:address":"Beatrixlaan 6",
    "sg:city":"Melissant",
    "sg:classifiers":[
        {
            "category":"Education",
            "subcategory":"Preschool",
            "type":"Public Place"
        }
    ],
    "sg:phone":"+31 187 601 806",
    "sg:postcode":"3248 AB",
    "sg:province":"Zuid-Holland",
    "sg:tags":[
        "kleuteronderwijs",
        "basis-"
    ],
    "wof:name":"De Regenboog School Met De Bijbel",
    "wof:placetype":"venue"
},
  "geometry": {"coordinates":[4.071276,51.769875],"type":"Point"}
}