{
  "type": "Feature",
  "properties": {
    "iso:country":"NL",
    "sg:address":"Sleepnetstr 619",
    "sg:city":"S Gravenhage",
    "sg:orig_category":"Vertalers",
    "sg:phone":"+31 6 17294664",
    "sg:postcode":"2584 GG",
    "sg:province":"Zuid-Holland",
    "wof:name":"Moretti, G",
    "wof:placetype":"venue"
},
  "geometry": {"coordinates":[4.28131,52.103199],"type":"Point"}
}