{
  "type": "Feature",
  "properties": {
    "addr:full":"Marktstr 7 Zevenaar Gelderland 6901 AK",
    "addr:housenumber":"7",
    "addr:postcode":"6901 ak",
    "addr:street":"Marktstr",
    "iso:country":"NL",
    "sg:address":"Marktstr 7",
    "sg:city":"Zevenaar",
    "sg:classifiers":[
        {
            "category":"Food & Beverages",
            "subcategory":"Bakery",
            "type":"Retail Goods"
        }
    ],
    "sg:phone":"+31 316 345 625",
    "sg:postcode":"6901 AK",
    "sg:province":"Gelderland",
    "sg:tags":[
        "brood",
        "en",
        "banket"
    ],
    "wof:name":"Bart",
    "wof:placetype":"venue"
},
  "geometry": {"coordinates":[6.076511,51.927879],"type":"Point"}
}