{
  "type": "Feature",
  "properties": {
    "addr:full":"Lotusbloemwg 1 Almere NL. 1338 VT",
    "addr:housenumber":"1",
    "addr:postcode":"1338",
    "addr:street":"Lotusbloemwg;Nl.",
    "iso:country":"NL",
    "sg:address":"Lotusbloemwg 1",
    "sg:city":"Almere",
    "sg:orig_category":"Meubelmakerijen",
    "sg:phone":"+31 36 532 9388",
    "sg:postcode":"1338 VT",
    "sg:province":"NL.",
    "wof:name":"Holin",
    "wof:placetype":"venue"
},
  "geometry": {"coordinates":[5.282316,52.385624],"type":"Point"}
}