{
  "type": "Feature",
  "properties": {
    "addr:full":"Plantage Kerkln 25A Amsterdam North Holland 1018 CV",
    "addr:housenumber":"25a",
    "addr:postcode":"1018 cv",
    "addr:street":"Plantage Kerkln",
    "iso:country":"NL",
    "sg:address":"Plantage Kerkln 25A",
    "sg:city":"Amsterdam",
    "sg:classifiers":[
        {
            "category":"Travel",
            "subcategory":"Hotels & Motels",
            "type":"Entertainment"
        }
    ],
    "sg:phone":"+31 20 620 5544",
    "sg:postcode":"1018 CV",
    "sg:province":"North Holland",
    "sg:website":"http://www.hotelplantage.nl",
    "wof:name":"Plantage",
    "wof:placetype":"venue"
},
  "geometry": {"coordinates":[4.911741,52.366608],"type":"Point"}
}