{
  "type": "Feature",
  "properties": {
    "addr:full":"Mozartlaan 10 Heesch Noord-Brabant 5384 CG",
    "addr:housenumber":"10",
    "addr:postcode":"5384 cg",
    "addr:street":"Mozartlaan",
    "iso:country":"NL",
    "sg:address":"Mozartlaan 10",
    "sg:city":"Heesch",
    "sg:orig_category":"Sportcentra",
    "sg:phone":"+31 412 452 390",
    "sg:postcode":"5384 CG",
    "sg:province":"Noord-Brabant",
    "wof:name":"Sporthal Lindershof",
    "wof:placetype":"venue"
},
  "geometry": {"coordinates":[5.534187,51.73254],"type":"Point"}
}