{
  "type": "Feature",
  "properties": {
    "iso:country":"NL",
    "sg:address":"Boulevard Barnaart 30",
    "sg:city":"Zandvoort",
    "sg:orig_category":"Kampeerterreinen",
    "sg:phone":"+31 23 571 3035",
    "sg:postcode":"2041 JA",
    "sg:province":"North Holland",
    "wof:name":"Camping De Branding",
    "wof:placetype":"venue"
},
  "geometry": {"coordinates":[4.5304198265,52.3808708191],"type":"Point"}
}