{
  "type": "Feature",
  "properties": {
    "addr:full":"Ockenburghpk 60 Helmond North Brabant 5709 ML",
    "addr:housenumber":"60",
    "addr:postcode":"5709 ml",
    "addr:street":"Ockenburghpk",
    "iso:country":"NL",
    "sg:address":"Ockenburghpk 60",
    "sg:city":"Helmond",
    "sg:orig_category":"Projectontwikkeling",
    "sg:phone":"+31 492 514 957",
    "sg:postcode":"5709 ML",
    "sg:province":"North Brabant",
    "wof:name":"Coranti Bv",
    "wof:placetype":"venue"
},
  "geometry": {"coordinates":[5.686904,51.491928],"type":"Point"}
}