{
  "type": "Feature",
  "properties": {
    "addr:full":"Badhuislaan 43 Bussum Noord-Holland 1402 SR",
    "addr:housenumber":"43;1402",
    "addr:postcode":"sr",
    "addr:street":"Badhuislaan",
    "iso:country":"NL",
    "sg:address":"Badhuislaan 43",
    "sg:city":"Bussum",
    "sg:orig_category":"Watersport-, Sport- And Kampeerbenodigdheden Verhuur",
    "sg:phone":"+31 35 691 5576",
    "sg:postcode":"1402 SR",
    "sg:province":"Noord-Holland",
    "wof:name":"Gunnar Sailing Services",
    "wof:placetype":"venue"
},
  "geometry": {"coordinates":[5.1735091209,52.2734107971],"type":"Point"}
}