{
  "type": "Feature",
  "properties": {
    "addr:full":"Dorpsstr 55A Heerjansdam South Holland 2995 XD",
    "addr:housenumber":"55a",
    "addr:postcode":"2995 xd",
    "addr:street":"Dorpsstr",
    "iso:country":"NL",
    "sg:address":"Dorpsstr 55A",
    "sg:city":"Heerjansdam",
    "sg:orig_category":"Parketvloeren",
    "sg:phone":"+31 6 50286823",
    "sg:postcode":"2995 XD",
    "sg:province":"South Holland",
    "wof:name":"Old-Floor",
    "wof:placetype":"venue"
},
  "geometry": {"coordinates":[4.561662,51.835987],"type":"Point"}
}