{
  "type": "Feature",
  "properties": {
    "addr:full":"Oude Ryn 57 Leiden Zuid-Holland 2312 HC",
    "addr:housenumber":"57",
    "addr:postcode":"2312 hc",
    "addr:street":"Oude Ryn",
    "iso:country":"NL",
    "sg:address":"Oude Ryn 57",
    "sg:city":"Leiden",
    "sg:orig_category":"Omroep",
    "sg:phone":"+31 71 512 7515",
    "sg:postcode":"2312 HC",
    "sg:province":"Zuid-Holland",
    "sg:website":"http://www.hollandcentraal.nl",
    "wof:name":"Holland Centraal",
    "wof:placetype":"venue"
},
  "geometry": {"coordinates":[4.49742,52.160126],"type":"Point"}
}