{
  "type": "Feature",
  "properties": {
    "addr:full":"Industriestr 6 Goirle North Brabant 5051 HR",
    "addr:housenumber":"6",
    "addr:postcode":"5051 hr",
    "addr:street":"Industriestr",
    "iso:country":"NL",
    "sg:address":"Industriestr 6",
    "sg:city":"Goirle",
    "sg:orig_category":"Kunststof Ramen",
    "sg:phone":"+31 13 534 2587",
    "sg:postcode":"5051 HR",
    "sg:province":"North Brabant",
    "sg:website":"http://www.westphallkozijnen.nl",
    "wof:name":"Westphal, Gebr",
    "wof:placetype":"venue"
},
  "geometry": {"coordinates":[5.058501,51.517834],"type":"Point"}
}