{
  "type": "Feature",
  "properties": {
    "addr:full":"Koestr 101 Schoonhoven Zuid-Holland 2871 DP",
    "addr:housenumber":"101",
    "addr:postcode":"2871 dp",
    "iso:country":"NL",
    "sg:address":"Koestr 101",
    "sg:city":"Schoonhoven",
    "sg:orig_category":"Woninginrichting",
    "sg:phone":"+31 182 382 450",
    "sg:postcode":"2871 DP",
    "sg:province":"Zuid-Holland",
    "wof:name":"Stigter",
    "wof:placetype":"venue"
},
  "geometry": {"coordinates":[4.850522995,51.9475784302],"type":"Point"}
}