{
  "type": "Feature",
  "properties": {
    "iso:country":"NL",
    "sg:address":"Nieuwendijk 9",
    "sg:city":"Wijhe",
    "sg:orig_category":"Kappers",
    "sg:phone":"+31 570 524 852",
    "sg:postcode":"8131 CD",
    "sg:province":"NL.08",
    "wof:name":"Maison Pavette",
    "wof:placetype":"venue"
},
  "geometry": {"coordinates":[6.134671,52.389469],"type":"Point"}
}