{
  "type": "Feature",
  "properties": {
    "addr:full":"Martena 21 Drachten Friesland 9202 KA",
    "addr:housenumber":"21",
    "addr:postcode":"9202 ka",
    "addr:street":"Martena",
    "iso:country":"NL",
    "sg:address":"Martena 21",
    "sg:city":"Drachten",
    "sg:orig_category":"Fotoreportages",
    "sg:phone":"+31 512 549 224",
    "sg:postcode":"9202 KA",
    "sg:province":"Friesland",
    "wof:name":"Defobie",
    "wof:placetype":"venue"
},
  "geometry": {"coordinates":[6.124651,53.109028],"type":"Point"}
}