{
  "type": "Feature",
  "properties": {
    "addr:full":"Zuidpolderdk 4 Baarland Zeeland 4435 PW",
    "addr:housenumber":"4",
    "addr:postcode":"4435 pw",
    "addr:street":"Zuidpolderdk",
    "iso:country":"NL",
    "sg:address":"Zuidpolderdk 4",
    "sg:city":"Baarland",
    "sg:orig_category":"Kantoor- En Secretariaatsservice",
    "sg:phone":"+31 113 639 510",
    "sg:postcode":"4435 PW",
    "sg:province":"Zeeland",
    "wof:name":"Zeegers",
    "wof:placetype":"venue"
},
  "geometry": {"coordinates":[3.8785510063,51.4019851685],"type":"Point"}
}