{
  "type": "Feature",
  "properties": {
    "addr:full":"Mereveldplein 3 De Meern Utrecht 3454 CJ",
    "addr:housenumber":"3",
    "addr:postcode":"3454 cj",
    "addr:street":"Mereveldplein",
    "iso:country":"NL",
    "sg:address":"Mereveldplein 3",
    "sg:city":"De Meern",
    "sg:classifiers":[
        {
            "category":"Food & Beverages",
            "subcategory":"Fruits & Vegetables",
            "type":"Retail Goods"
        }
    ],
    "sg:phone":"+31 30 666 3255",
    "sg:postcode":"3454 CJ",
    "sg:province":"Utrecht",
    "sg:tags":[
        "groenten"
    ],
    "wof:name":"Firma De Ridder Hodn Van De Werf",
    "wof:placetype":"venue"
},
  "geometry": {"coordinates":[5.038787,52.079388],"type":"Point"}
}