{
  "type": "Feature",
  "properties": {
    "addr:full":"Parelvissersstraat 203 Apeldoorn Gelderland 7323 BM",
    "addr:housenumber":"203",
    "addr:postcode":"7323 bm",
    "addr:street":"Parelvissersstraat;Gelderland",
    "iso:country":"NL",
    "sg:address":"Parelvissersstraat 203",
    "sg:city":"Apeldoorn",
    "sg:classifiers":[
        {
            "category":"Education",
            "subcategory":"Preschool",
            "type":"Public Place"
        }
    ],
    "sg:phone":"+31 55 366 0012",
    "sg:postcode":"7323 BM",
    "sg:province":"Gelderland",
    "sg:tags":[
        "kleuteronderwijs",
        "basis-"
    ],
    "wof:name":"Obs John F. Kennedy",
    "wof:placetype":"venue"
},
  "geometry": {"coordinates":[5.980931,52.232487],"type":"Point"}
}