{
  "type": "Feature",
  "properties": {
    "iso:country":"NL",
    "sg:address":"Repelweg 6",
    "sg:city":"Marknesse",
    "sg:orig_category":"Pleziervaartuigen And Reparatie",
    "sg:phone":"+31 527 241 384",
    "sg:postcode":"8316 PV",
    "sg:province":"Flevoland",
    "wof:name":"Jachtwerf De Voorst Bv",
    "wof:placetype":"venue"
},
  "geometry": {"coordinates":[5.930331,52.671452],"type":"Point"}
}