{
  "type": "Feature",
  "properties": {
    "addr:full":"Delwg 2A Zevenaar Gelderland 6902 PJ",
    "addr:housenumber":"2a",
    "addr:postcode":"6902 pj",
    "addr:street":"Delwg",
    "iso:country":"NL",
    "sg:address":"Delwg 2A",
    "sg:city":"Zevenaar",
    "sg:orig_category":"Autoradio'S",
    "sg:phone":"+31 316 332 600",
    "sg:postcode":"6902 PJ",
    "sg:province":"Gelderland",
    "wof:name":"Krist, Wim",
    "wof:placetype":"venue"
},
  "geometry": {"coordinates":[6.081552,51.935764],"type":"Point"}
}