{
  "type": "Feature",
  "properties": {
    "addr:full":"1E Jacob Van Campenstr 14 Amsterdam Noord-Holland 1072 BE",
    "addr:housenumber":"14",
    "addr:postcode":"1072",
    "addr:street":"1E Jacob Van Campenstr",
    "iso:country":"NL",
    "sg:address":"1E Jacob Van Campenstr 14",
    "sg:city":"Amsterdam",
    "sg:orig_category":"Fotostudio'S And Fotografen",
    "sg:phone":"+31 20 664 4369",
    "sg:postcode":"1072 BE",
    "sg:province":"Noord-Holland",
    "wof:name":"Van Laar Fotografie",
    "wof:placetype":"venue"
},
  "geometry": {"coordinates":[4.887677,52.357403],"type":"Point"}
}