{
  "type": "Feature",
  "properties": {
    "addr:full":"Jagersberg 64 Roosendaal Noord-Brabant 4708 MJ",
    "addr:housenumber":"64",
    "addr:postcode":"4708 mj",
    "addr:street":"Jagersberg",
    "iso:country":"NL",
    "sg:address":"Jagersberg 64",
    "sg:city":"Roosendaal",
    "sg:orig_category":"Adviesbureaus Bouwkunde",
    "sg:phone":"+31 165 553 910",
    "sg:postcode":"4708 MJ",
    "sg:province":"Noord-Brabant",
    "wof:name":"Brooijmans Adviesburo W",
    "wof:placetype":"venue"
},
  "geometry": {"coordinates":[4.432887,51.506725],"type":"Point"}
}