{
  "type": "Feature",
  "properties": {
    "addr:full":"Elandsgr 59 Amsterdam North Holland 1016 TN",
    "addr:housenumber":"59",
    "addr:postcode":"1016",
    "addr:street":"Elandsgr",
    "iso:country":"NL",
    "sg:address":"Elandsgr 59",
    "sg:city":"Amsterdam",
    "sg:orig_category":"Wasserettes And Stomerijen",
    "sg:phone":"+31 20 625 0731",
    "sg:postcode":"1016 TN",
    "sg:province":"North Holland",
    "wof:name":"De Eland",
    "wof:placetype":"venue"
},
  "geometry": {"coordinates":[4.880464077,52.3692970276],"type":"Point"}
}