{
  "type": "Feature",
  "properties": {
    "addr:full":"De Cavaletti 6 Dronten NL. 8252 GE",
    "addr:housenumber":"6",
    "addr:postcode":"8252",
    "addr:street":"De Cavaletti;Nl.",
    "iso:country":"NL",
    "sg:address":"De Cavaletti 6",
    "sg:city":"Dronten",
    "sg:orig_category":"Diverse Grafische Activiteiten",
    "sg:phone":"+31 321 313 156",
    "sg:postcode":"8252 GE",
    "sg:province":"NL.",
    "wof:name":"J.W. De Geus",
    "wof:placetype":"venue"
},
  "geometry": {"coordinates":[5.708442,52.514317],"type":"Point"}
}