{
  "type": "Feature",
  "properties": {
    "iso:country":"NL",
    "sg:address":"Ammonsln 23",
    "sg:city":"Wassenaar",
    "sg:orig_category":"Verzekeringen - Verzekeringskantoren",
    "sg:phone":"+31 70 517 8684",
    "sg:postcode":"2241 BR",
    "sg:province":"South Holland",
    "wof:name":"Ammerlaan, J M B",
    "wof:placetype":"venue"
},
  "geometry": {"coordinates":[4.423909,52.149353],"type":"Point"}
}