{
  "type": "Feature",
  "properties": {
    "addr:full":"Suikerbakkerstraat 36 Hoogvliet Rt South Holland 3194 AK",
    "addr:housenumber":"36",
    "addr:postcode":"3194 ak",
    "addr:street":"Suikerbakkerstraat;Rt South",
    "iso:country":"NL",
    "sg:address":"Suikerbakkerstraat 36",
    "sg:city":"Hoogvliet Rt",
    "sg:orig_category":"Verhuur Diversen",
    "sg:phone":"+31 10 438 0276",
    "sg:postcode":"3194 AK",
    "sg:province":"South Holland",
    "wof:name":"M Koebrugge Bv",
    "wof:placetype":"venue"
},
  "geometry": {"coordinates":[4.377808,51.868828],"type":"Point"}
}