{
  "type": "Feature",
  "properties": {
    "addr:full":"Rynzichtwg 28 Oegstgeest Zuid-Holland 2341 AC",
    "addr:housenumber":"28",
    "addr:postcode":"2341 ac",
    "addr:street":"Rynzichtwg",
    "iso:country":"NL",
    "sg:address":"Rynzichtwg 28",
    "sg:city":"Oegstgeest",
    "sg:orig_category":"Modevakscholen",
    "sg:phone":"+31 71 517 3505",
    "sg:postcode":"2341 AC",
    "sg:province":"Zuid-Holland",
    "wof:name":"Modevakschool",
    "wof:placetype":"venue"
},
  "geometry": {"coordinates":[4.460464,52.179573],"type":"Point"}
}