{
  "type": "Feature",
  "properties": {
    "iso:country":"NL",
    "sg:address":"Schoolstr 27",
    "sg:city":"Beek Gem Bergh",
    "sg:orig_category":"Bloemen En Planten",
    "sg:phone":"+31 316 532 253",
    "sg:postcode":"7037 AS",
    "sg:province":"Gelderland",
    "wof:name":"Fleur",
    "wof:placetype":"venue"
},
  "geometry": {"coordinates":[6.187938,51.906292],"type":"Point"}
}