{
  "type": "Feature",
  "properties": {
    "addr:full":"Haven 47 Schoonhoven Zuid-Holland 2871 CL",
    "addr:housenumber":"47",
    "addr:postcode":"2871",
    "addr:street":"Haven",
    "iso:country":"NL",
    "sg:address":"Haven 47",
    "sg:city":"Schoonhoven",
    "sg:orig_category":"Banken And Kredietinstellingen",
    "sg:phone":"+31 182 321 321",
    "sg:postcode":"2871 CL",
    "sg:province":"Zuid-Holland",
    "wof:name":"Rabobank",
    "wof:placetype":"venue"
},
  "geometry": {"coordinates":[4.852051,51.945606],"type":"Point"}
}