{
  "type": "Feature",
  "properties": {
    "addr:full":"Hoekeinde 5 Sleeuwyk North Brabant 4254 LM",
    "addr:housenumber":"5",
    "addr:postcode":"4254 lm",
    "addr:street":"Hoekeinde",
    "iso:country":"NL",
    "sg:address":"Hoekeinde 5",
    "sg:city":"Sleeuwyk",
    "sg:orig_category":"Duikers",
    "sg:phone":"+31 183 307 900",
    "sg:postcode":"4254 LM",
    "sg:province":"North Brabant",
    "wof:name":"Seascape Diving",
    "wof:placetype":"venue"
},
  "geometry": {"coordinates":[4.961409,51.817238],"type":"Point"}
}