{
  "type": "Feature",
  "properties": {
    "iso:country":"NL",
    "sg:address":"Professor Molenaarlaan 51",
    "sg:city":"Wassenaar",
    "sg:orig_category":"Bibliotheken And Openbare Archieven",
    "sg:phone":"+31 70 511 8458",
    "sg:postcode":"2241 RB",
    "sg:province":"Zuid-Holland",
    "wof:name":"Delta-10",
    "wof:placetype":"venue"
},
  "geometry": {"coordinates":[4.402272,52.151806],"type":"Point"}
}