{
  "type": "Feature",
  "properties": {
    "iso:country":"NL",
    "sg:address":"De Chamotte 7",
    "sg:city":"Geldermalsen",
    "sg:classifiers":[
        {
            "category":"Fast Food",
            "type":"Food & Drink"
        }
    ],
    "sg:phone":"+31 345 577 348",
    "sg:postcode":"4091 GT",
    "sg:province":"Gelderland",
    "sg:tags":[
        "afhaal",
        "restaurant"
    ],
    "wof:name":"Jeromekes Friet",
    "wof:placetype":"venue"
},
  "geometry": {"coordinates":[5.302774,51.877045],"type":"Point"}
}