{
  "type": "Feature",
  "properties": {
    "addr:full":"Schietbergen 21 Nuenen North Brabant 5672 SJ",
    "addr:housenumber":"21",
    "addr:postcode":"5672",
    "addr:street":"Schietbergen",
    "iso:country":"NL",
    "sg:address":"Schietbergen 21",
    "sg:city":"Nuenen",
    "sg:orig_category":"Verzekeringen",
    "sg:phone":"+31 40 290 8105",
    "sg:postcode":"5672 SJ",
    "sg:province":"North Brabant",
    "wof:name":"Rietdijk Assurantien",
    "wof:placetype":"venue"
},
  "geometry": {"coordinates":[5.554924,51.460262],"type":"Point"}
}