{
  "type": "Feature",
  "properties": {
    "addr:full":"K Doormanwg 5 Breukelen Ut Utrecht 3621 JV",
    "addr:housenumber":"5",
    "addr:postcode":"3621 jv",
    "addr:street":"Doormanwg",
    "iso:country":"NL",
    "sg:address":"K Doormanwg 5",
    "sg:city":"Breukelen Ut",
    "sg:orig_category":"Adviesbureaus Bedrijfsorganisatie",
    "sg:phone":"+31 346 265 182",
    "sg:postcode":"3621 JV",
    "sg:province":"Utrecht",
    "wof:name":"Dexar Bv",
    "wof:placetype":"venue"
},
  "geometry": {"coordinates":[5.001585,52.172958],"type":"Point"}
}