{
  "type": "Feature",
  "properties": {
    "iso:country":"NL",
    "sg:address":"Schillingwg 51",
    "sg:city":"Nieuw Vennep",
    "sg:orig_category":"Wegbebakening En Beveiliging - Materialen",
    "sg:phone":"+31 252 681 305",
    "sg:postcode":"2153 PL",
    "sg:province":"North Holland",
    "wof:name":"Trip & Co Bv",
    "wof:placetype":"venue"
},
  "geometry": {"coordinates":[4.6296429634,52.2557792664],"type":"Point"}
}