{
  "type": "Feature",
  "properties": {
    "addr:full":"Wageningselaan 10 Veenendaal Utrecht 3903 LA",
    "addr:housenumber":"10",
    "addr:postcode":"3903 la",
    "addr:street":"Wageningselaan",
    "iso:country":"NL",
    "sg:address":"Wageningselaan 10",
    "sg:city":"Veenendaal",
    "sg:orig_category":"Kantoorartikelen",
    "sg:phone":"+31 318 518 351",
    "sg:postcode":"3903 LA",
    "sg:province":"Utrecht",
    "wof:name":"Gdb Ned Bv",
    "wof:placetype":"venue"
},
  "geometry": {"coordinates":[5.5712499619,52.0115890503],"type":"Point"}
}