{
  "type": "Feature",
  "properties": {
    "addr:full":"Hg Veldwg 1 St Jansklooster Overijssel 8326 BE",
    "addr:housenumber":"1",
    "addr:postcode":"8326",
    "addr:street":"St Jansklooster Overijssel",
    "iso:country":"NL",
    "sg:address":"Hg Veldwg 1",
    "sg:city":"St Jansklooster",
    "sg:orig_category":"Kappers",
    "sg:phone":"+31 527 246 121",
    "sg:postcode":"8326 BE",
    "sg:province":"Overijssel",
    "wof:name":"Coba",
    "wof:placetype":"venue"
},
  "geometry": {"coordinates":[6.0094127655,52.6632652283],"type":"Point"}
}