{
  "type": "Feature",
  "properties": {
    "addr:full":"Frankrykstr 122 Eindhoven Noord-Brabant 5622 AH",
    "addr:housenumber":"122",
    "addr:postcode":"5622 ah",
    "iso:country":"NL",
    "sg:address":"Frankrykstr 122",
    "sg:city":"Eindhoven",
    "sg:orig_category":"Winkelinrichting",
    "sg:phone":"+31 40 255 2535",
    "sg:postcode":"5622 AH",
    "sg:province":"Noord-Brabant",
    "sg:website":"http://www.shopvisie.nl",
    "wof:name":"Shopvisie Winkelmaterialen",
    "wof:placetype":"venue"
},
  "geometry": {"coordinates":[5.4629101753,51.4593811035],"type":"Point"}
}