{
  "type": "Feature",
  "properties": {
    "iso:country":"NL",
    "sg:address":"Robert Kochstraat 5",
    "sg:city":"Hoogerheide",
    "sg:orig_category":"Verzekeringen",
    "sg:phone":"+31 164 620 050",
    "sg:postcode":"4631 LK",
    "sg:province":"Noord-Brabant",
    "wof:name":"Zuidwesthoek Verzekeringen",
    "wof:placetype":"venue"
},
  "geometry": {"coordinates":[4.323576,51.426704],"type":"Point"}
}