{
  "type": "Feature",
  "properties": {
    "addr:full":"Oude Binnenweg 42 Rotterdam Zuid-Holland 3012 JE",
    "addr:housenumber":"42",
    "addr:postcode":"3012 je",
    "addr:street":"Oude Binnenweg",
    "iso:country":"NL",
    "sg:address":"Oude Binnenweg 42",
    "sg:city":"Rotterdam",
    "sg:orig_category":"Schoenen",
    "sg:phone":"+31 10 213 3978",
    "sg:postcode":"3012 JE",
    "sg:province":"Zuid-Holland",
    "wof:name":"De Schoenkampioen",
    "wof:placetype":"venue"
},
  "geometry": {"coordinates":[4.476573,51.91777],"type":"Point"}
}