{
  "type": "Feature",
  "properties": {
    "iso:country":"NL",
    "sg:address":"Oude Binnenweg 42",
    "sg:city":"Rotterdam",
    "sg:orig_category":"Schoenen",
    "sg:phone":"+31 10 213 3978",
    "sg:postcode":"3012 JE",
    "sg:province":"Zuid-Holland",
    "wof:name":"De Schoenkampioen",
    "wof:placetype":"venue"
},
  "geometry": {"coordinates":[4.476573,51.91777],"type":"Point"}
}