{
  "type": "Feature",
  "properties": {
    "iso:country":"NL",
    "sg:address":"Haageyk 4",
    "sg:city":"Gemert",
    "sg:orig_category":"Woninginrichting",
    "sg:phone":"+31 492 362 718",
    "sg:postcode":"5421 KW",
    "sg:province":"North Brabant",
    "sg:website":"http://www.decohome.nl",
    "wof:name":"Snijders",
    "wof:placetype":"venue"
},
  "geometry": {"coordinates":[5.6821789742,51.5583152771],"type":"Point"}
}