{
  "type": "Feature",
  "properties": {
    "iso:country":"NL",
    "sg:address":"Moesdk 11D",
    "sg:city":"Weert",
    "sg:orig_category":"Keukens",
    "sg:phone":"+31 495 545 651",
    "sg:postcode":"6004 AX",
    "sg:province":"Limburg",
    "wof:name":"R-Perium",
    "wof:placetype":"venue"
},
  "geometry": {"coordinates":[5.734245,51.247631],"type":"Point"}
}