{
  "type": "Feature",
  "properties": {
    "addr:full":"Moesdk 11D Weert Limburg 6004 AX",
    "addr:housenumber":"11d",
    "addr:postcode":"6004 ax",
    "addr:street":"Moesdk",
    "iso:country":"NL",
    "sg:address":"Moesdk 11D",
    "sg:city":"Weert",
    "sg:orig_category":"Keukens",
    "sg:phone":"+31 495 545 651",
    "sg:postcode":"6004 AX",
    "sg:province":"Limburg",
    "wof:name":"R-Perium",
    "wof:placetype":"venue"
},
  "geometry": {"coordinates":[5.734245,51.247631],"type":"Point"}
}