{
  "type": "Feature",
  "properties": {
    "iso:country":"NL",
    "sg:address":"Valutaboulevard 27",
    "sg:city":"Amsterdam",
    "sg:orig_category":"Marktonderzoekbureaus",
    "sg:phone":"+31 20 421 2484",
    "sg:postcode":"1060 RX",
    "sg:province":"Noord-Holland",
    "wof:name":"Van Nuland Advies",
    "wof:placetype":"venue"
},
  "geometry": {"coordinates":[4.788724,52.348309],"type":"Point"}
}