{
  "type": "Feature",
  "properties": {
    "addr:full":"Kerkstr 224 Brunssum Limburg 6441 BK",
    "addr:housenumber":"224",
    "addr:postcode":"6441 bk",
    "addr:street":"Brunssum Limburg",
    "iso:country":"NL",
    "sg:address":"Kerkstr 224",
    "sg:city":"Brunssum",
    "sg:orig_category":"Warenhuizen",
    "sg:phone":"+31 45 564 6500",
    "sg:postcode":"6441 BK",
    "sg:province":"Limburg",
    "wof:name":"Hema",
    "wof:placetype":"venue"
},
  "geometry": {"coordinates":[5.9720921516,50.946559906],"type":"Point"}
}