{
  "type": "Feature",
  "properties": {
    "addr:full":"Heiligenbergerwg 71 Amersfoort Utrecht 3816 AG",
    "addr:housenumber":"71",
    "addr:postcode":"3816",
    "addr:street":"Heiligenbergerwg",
    "iso:country":"NL",
    "sg:address":"Heiligenbergerwg 71",
    "sg:city":"Amersfoort",
    "sg:orig_category":"Galeries",
    "sg:phone":"+31 33 476 8211",
    "sg:postcode":"3816 AG",
    "sg:province":"Utrecht",
    "sg:website":"http://www.de-keijzer.nl",
    "wof:name":"Keijzer, T De",
    "wof:placetype":"venue"
},
  "geometry": {"coordinates":[5.398849,52.152695],"type":"Point"}
}