{
  "type": "Feature",
  "properties": {
    "iso:country":"NL",
    "sg:address":"Eemnesserwg 42",
    "sg:city":"Laren Nh",
    "sg:orig_category":"Bejaarden - Verzorgingstehuizen",
    "sg:phone":"+31 35 539 4200",
    "sg:postcode":"1251 ND",
    "sg:province":"Noord-Holland",
    "sg:website":"http://www.zorghart.nl",
    "wof:name":"Johannes Hove, Zorgcentrum",
    "wof:placetype":"venue"
},
  "geometry": {"coordinates":[5.234236,52.255299],"type":"Point"}
}