{
  "type": "Feature",
  "properties": {
    "addr:full":"Klipperwerf 9 Leiden Zuid-Holland 2317 DX",
    "addr:housenumber":"9",
    "addr:postcode":"2317 dx",
    "addr:street":"Klipperwerf",
    "iso:country":"NL",
    "sg:address":"Klipperwerf 9",
    "sg:city":"Leiden",
    "sg:orig_category":"Verzekeringen",
    "sg:phone":"+31 71 521 6363",
    "sg:postcode":"2317 DX",
    "sg:province":"Zuid-Holland",
    "wof:name":"F.J.L. Van Rossum",
    "wof:placetype":"venue"
},
  "geometry": {"coordinates":[4.514725,52.174259],"type":"Point"}
}