{
  "type": "Feature",
  "properties": {
    "iso:country":"NL",
    "sg:address":"Wulverhorstln 2",
    "sg:city":"Utrecht",
    "sg:orig_category":"Administratie- En Boekhoudkantoren",
    "sg:phone":"+31 30 285 1414",
    "sg:postcode":"3525 EC",
    "sg:province":"Utrecht",
    "wof:name":"Algebra",
    "wof:placetype":"venue"
},
  "geometry": {"coordinates":[5.1204,52.062744],"type":"Point"}
}