{
  "type": "Feature",
  "properties": {
    "addr:full":"Voorstraat 208 Dordrecht South Holland 3311 ET",
    "addr:housenumber":"208",
    "addr:postcode":"3311 et",
    "addr:street":"Voorstraat",
    "iso:country":"NL",
    "sg:address":"Voorstraat 208",
    "sg:city":"Dordrecht",
    "sg:orig_category":"Kunst And Kunstenaarsbenodigdheden",
    "sg:phone":"+31 78 613 6577",
    "sg:postcode":"3311 ET",
    "sg:province":"South Holland",
    "wof:name":"Kunsthandel Nieuborg Bv",
    "wof:placetype":"venue"
},
  "geometry": {"coordinates":[4.66934,51.815819],"type":"Point"}
}