{
  "type": "Feature",
  "properties": {
    "addr:full":"Moenspln 8 Beverwyk Noord-Holland 1942 ER",
    "addr:housenumber":"8",
    "addr:postcode":"1942 er",
    "addr:street":"Moenspln",
    "iso:country":"NL",
    "sg:address":"Moenspln 8",
    "sg:city":"Beverwyk",
    "sg:orig_category":"Projectinrichting",
    "sg:phone":"+31 251 226 803",
    "sg:postcode":"1942 ER",
    "sg:province":"Noord-Holland",
    "wof:name":"Denbo Bv",
    "wof:placetype":"venue"
},
  "geometry": {"coordinates":[4.652806,52.483513],"type":"Point"}
}