{
  "type": "Feature",
  "properties": {
    "addr:full":"P C Hooftstr 62 Amsterdam Missouri 1071 CA",
    "addr:housenumber":"62",
    "addr:postcode":"1071 ca",
    "addr:street":"P C Hooftstr",
    "iso:country":"NL",
    "sg:address":"P C Hooftstr 62",
    "sg:city":"Amsterdam",
    "sg:orig_category":"Herenkleding",
    "sg:phone":"+31 20 379 0479",
    "sg:postcode":"1071 CA",
    "sg:province":"Missouri",
    "wof:name":"Baldessarini-Hugo Boss",
    "wof:placetype":"venue"
},
  "geometry": {"coordinates":[-94.58503,38.350479],"type":"Point"}
}