{
  "type": "Feature",
  "properties": {
    "iso:country":"NL",
    "sg:address":"Steenbergsestr 20-22",
    "sg:city":"Bergen Op Zoom",
    "sg:orig_category":"Kappers",
    "sg:phone":"+31 164 211 193",
    "sg:postcode":"4611 TG",
    "sg:province":"Noord-Brabant",
    "wof:name":"Hairjockey Team",
    "wof:placetype":"venue"
},
  "geometry": {"coordinates":[4.2845678329,51.4963378906],"type":"Point"}
}