{
  "type": "Feature",
  "properties": {
    "iso:country":"NL",
    "sg:address":"J W Van Puttestraat 37",
    "sg:city":"Ameide",
    "sg:orig_category":"Zuivelproducten And Spijsoli?n Gh",
    "sg:phone":"+31 183 601 270",
    "sg:postcode":"4233 EJ",
    "sg:province":"Zuid-Holland",
    "wof:name":"Berendsen Kaashandel Bv",
    "wof:placetype":"venue"
},
  "geometry": {"coordinates":[4.960446,51.95668],"type":"Point"}
}