{
  "type": "Feature",
  "properties": {
    "addr:full":"Voorjaarsweg 5 Enschede Overijssel 7532 SJ",
    "addr:housenumber":"5",
    "addr:postcode":"7532",
    "addr:street":"Voorjaarsweg",
    "iso:country":"NL",
    "sg:address":"Voorjaarsweg 5",
    "sg:city":"Enschede",
    "sg:orig_category":"Huishoudelijk Textiel Fab",
    "sg:phone":"+31 53 461 5055",
    "sg:postcode":"7532 SJ",
    "sg:province":"Overijssel",
    "wof:name":"Arli International Bv",
    "wof:placetype":"venue"
},
  "geometry": {"coordinates":[6.95112,52.223866],"type":"Point"}
}