{
  "type": "Feature",
  "properties": {
    "iso:country":"NL",
    "sg:address":"Standaardmolen 36",
    "sg:city":"Alphen Aan Den Ryn",
    "sg:orig_category":"Adviesbureaus",
    "sg:phone":"+31 172 472 612",
    "sg:postcode":"2406 JK",
    "sg:province":"Zuid-Holland",
    "wof:name":"Berends & Doelman Bv",
    "wof:placetype":"venue"
},
  "geometry": {"coordinates":[4.669419,52.12199],"type":"Point"}
}