{
  "type": "Feature",
  "properties": {
    "iso:country":"NL",
    "sg:address":"Assendorperstraat 165",
    "sg:city":"Zwolle",
    "sg:classifiers":[
        {
            "category":"Fast Food",
            "type":"Food & Drink"
        }
    ],
    "sg:phone":"+31 38 421 9811",
    "sg:postcode":"8012 DL",
    "sg:province":"Overijssel",
    "sg:tags":[
        "afhaal",
        "restaurant"
    ],
    "wof:name":"Snackpoint Kolk",
    "wof:placetype":"venue"
},
  "geometry": {"coordinates":[6.105547,52.503258],"type":"Point"}
}