{
  "type": "Feature",
  "properties": {
    "iso:country":"NL",
    "sg:address":"Diamant 30",
    "sg:city":"Mijdrecht",
    "sg:orig_category":"Reclamebureaus",
    "sg:phone":"+31 297 242 442",
    "sg:postcode":"3643 AK",
    "sg:province":"Utrecht",
    "wof:name":"Vier-5-6",
    "wof:placetype":"venue"
},
  "geometry": {"coordinates":[4.861688,52.216618],"type":"Point"}
}