{
  "type": "Feature",
  "properties": {
    "addr:full":"Ysselmeer 33 Barendrecht South Holland 2993 PH",
    "addr:housenumber":"33",
    "addr:postcode":"2993",
    "addr:street":"Ysselmeer",
    "iso:country":"NL",
    "sg:address":"Ysselmeer 33",
    "sg:city":"Barendrecht",
    "sg:orig_category":"Kinderactiviteiten",
    "sg:phone":"+31 180 617 362",
    "sg:postcode":"2993 PH",
    "sg:province":"South Holland",
    "wof:name":"Huisje Boompje Feestje",
    "wof:placetype":"venue"
},
  "geometry": {"coordinates":[4.48534,51.858334],"type":"Point"}
}