{
  "type": "Feature",
  "properties": {
    "iso:country":"NL",
    "sg:address":"Waaier 38",
    "sg:city":"Leimuiden",
    "sg:orig_category":"Wijnkoperijen En -Groothandel",
    "sg:phone":"+31 172 507 809",
    "sg:postcode":"2451 VW",
    "sg:province":"Zuid-Holland",
    "wof:name":"Pleasure Of Taste",
    "wof:placetype":"venue"
},
  "geometry": {"coordinates":[4.6817660332,52.2236289978],"type":"Point"}
}