{
  "type": "Feature",
  "properties": {
    "addr:full":"Poortenaarlaan 44 Nieuwegein Utrecht 3431 RH",
    "addr:housenumber":"44",
    "addr:postcode":"3431 rh",
    "addr:street":"Poortenaarlaan",
    "iso:country":"NL",
    "sg:address":"Poortenaarlaan 44",
    "sg:city":"Nieuwegein",
    "sg:orig_category":"Schilderwerk",
    "sg:phone":"+31 30 604 4042",
    "sg:postcode":"3431 RH",
    "sg:province":"Utrecht",
    "wof:name":"Schildersbedrijf Gebroeders Van Vugt",
    "wof:placetype":"venue"
},
  "geometry": {"coordinates":[5.078106,52.03307],"type":"Point"}
}