{
  "type": "Feature",
  "properties": {
    "addr:full":"Hoofdstraat 99 Noordwijk South Holland 2202  E",
    "addr:housenumber":"99;2202",
    "addr:street":"Hoofdstraat;E",
    "iso:country":"NL",
    "sg:address":"Hoofdstraat 99",
    "sg:city":"Noordwijk",
    "sg:orig_category":"Boekenuitgeverijen",
    "sg:phone":"+31 71 361 7505",
    "sg:postcode":"2202  E",
    "sg:province":"South Holland",
    "wof:name":"Bruna",
    "wof:placetype":"venue"
},
  "geometry": {"coordinates":[4.431251,52.243408],"type":"Point"}
}