{
  "type": "Feature",
  "properties": {
    "addr:full":"Fivelingo 253 Utrecht Utrecht 3524 BN",
    "addr:housenumber":"253",
    "addr:postcode":"3524 bn",
    "addr:street":"Fivelingo",
    "iso:country":"NL",
    "sg:address":"Fivelingo 253",
    "sg:city":"Utrecht",
    "sg:orig_category":"Verenigingen En Stichtingen",
    "sg:phone":"+31 30 280 0432",
    "sg:postcode":"3524 BN",
    "sg:province":"Utrecht",
    "sg:website":"http://www.creatievetherapie.nl",
    "wof:name":"Nvct",
    "wof:placetype":"venue"
},
  "geometry": {"coordinates":[5.141359,52.06575],"type":"Point"}
}