{
  "type": "Feature",
  "properties": {
    "addr:full":"Zuidergrachtswal 3 Leeuwarden Friesland 8933 AD",
    "addr:housenumber":"3",
    "addr:postcode":"8933 ad",
    "addr:street":"Zuidergrachtswal",
    "iso:country":"NL",
    "sg:address":"Zuidergrachtswal 3",
    "sg:city":"Leeuwarden",
    "sg:orig_category":"Adviesbureaus Bedrijfsorganisatie",
    "sg:phone":"+31 58 233 7833",
    "sg:postcode":"8933 AD",
    "sg:province":"Friesland",
    "wof:name":"E & S Bv",
    "wof:placetype":"venue"
},
  "geometry": {"coordinates":[5.799557,53.19899],"type":"Point"}
}