{
  "type": "Feature",
  "properties": {
    "addr:full":"Markeloseweg 43 Laren Gld Gelderland 7245 TP",
    "addr:housenumber":"43",
    "addr:postcode":"7245",
    "addr:street":"Markeloseweg;Gld Gelderland",
    "iso:country":"NL",
    "sg:address":"Markeloseweg 43",
    "sg:city":"Laren Gld",
    "sg:orig_category":"Levende Dieren Gh",
    "sg:phone":"+31 573 221 285",
    "sg:postcode":"7245 TP",
    "sg:province":"Gelderland",
    "wof:name":"Handelsbedrijf Braakman - Tap",
    "wof:placetype":"venue"
},
  "geometry": {"coordinates":[6.426176,52.224693],"type":"Point"}
}