{
  "type": "Feature",
  "properties": {
    "iso:country":"NL",
    "sg:address":"Markeloseweg 43",
    "sg:city":"Laren Gld",
    "sg:orig_category":"Levende Dieren Gh",
    "sg:phone":"+31 573 221 285",
    "sg:postcode":"7245 TP",
    "sg:province":"Gelderland",
    "wof:name":"Handelsbedrijf Braakman - Tap",
    "wof:placetype":"venue"
},
  "geometry": {"coordinates":[6.426176,52.224693],"type":"Point"}
}