{
  "type": "Feature",
  "properties": {
    "addr:full":"Borgstee 8 Assen Provincie Drenthe 9403 TV",
    "addr:housenumber":"8",
    "addr:postcode":"9403 tv",
    "addr:street":"Borgstee;Provincie Drenthe",
    "iso:country":"NL",
    "sg:address":"Borgstee 8",
    "sg:city":"Assen",
    "sg:orig_category":"Woninginrichting",
    "sg:phone":"+31 592 375 177",
    "sg:postcode":"9403 TV",
    "sg:province":"Provincie Drenthe",
    "wof:name":"Leen Bakker",
    "wof:placetype":"venue"
},
  "geometry": {"coordinates":[6.5742850304,53.0116195679],"type":"Point"}
}