{
  "type": "Feature",
  "properties": {
    "iso:country":"NL",
    "sg:address":"Achterstraat 11",
    "sg:city":"Asperen",
    "sg:orig_category":"Meubeltextiel Fab",
    "sg:phone":"+31 345 617 822",
    "sg:postcode":"4147 AA",
    "sg:province":"South Holland",
    "wof:name":"M Den Besten Zeilmakerij",
    "wof:placetype":"venue"
},
  "geometry": {"coordinates":[5.114583,51.882923],"type":"Point"}
}