{
  "type": "Feature",
  "properties": {
    "addr:full":"Uitleg 4 Nunspeet Gelderland 8071 ZX",
    "addr:housenumber":"4",
    "addr:postcode":"8071 zx",
    "addr:street":"Uitleg;Gelderland",
    "iso:country":"NL",
    "sg:address":"Uitleg 4",
    "sg:city":"Nunspeet",
    "sg:orig_category":"Metaalwerken",
    "sg:phone":"+31 341 253 331",
    "sg:postcode":"8071 ZX",
    "sg:province":"Gelderland",
    "wof:name":"Odi",
    "wof:placetype":"venue"
},
  "geometry": {"coordinates":[5.767422,52.372875],"type":"Point"}
}