{
  "type": "Feature",
  "properties": {
    "iso:country":"NL",
    "sg:address":"Grutto 48",
    "sg:city":"Berkel En Rodenrys",
    "sg:orig_category":"Administratie- En Boekhoudkantoren",
    "sg:phone":"+31 10 511 2206",
    "sg:postcode":"2651 ZD",
    "sg:province":"Zuid-Holland",
    "wof:name":"E & P",
    "wof:placetype":"venue"
},
  "geometry": {"coordinates":[4.469619,51.987324],"type":"Point"}
}