{
  "type": "Feature",
  "properties": {
    "iso:country":"NL",
    "sg:address":"Coenhavenweg 8",
    "sg:city":"Amsterdam",
    "sg:orig_category":"Koeriersdiensten",
    "sg:phone":"+31 20 686 7808",
    "sg:postcode":"1013 BL",
    "sg:province":"North Holland",
    "wof:name":"Ica Koeriersdienst",
    "wof:placetype":"venue"
},
  "geometry": {"coordinates":[4.862637,52.403255],"type":"Point"}
}