{
  "type": "Feature",
  "properties": {
    "iso:country":"NL",
    "sg:address":"Tolhuisln 23",
    "sg:city":"Nykerk Gld",
    "sg:classifiers":[
        {
            "category":"Professional",
            "subcategory":"Management & Consulting",
            "type":"Services"
        }
    ],
    "sg:phone":"+31 33 246 0651",
    "sg:postcode":"3862 WK",
    "sg:province":"Gelderland",
    "sg:tags":[
        "relation",
        "adviesbureaus",
        "public"
    ],
    "wof:name":"B & S Vof",
    "wof:placetype":"venue"
},
  "geometry": {"coordinates":[5.62297,52.20557],"type":"Point"}
}