{
  "type": "Feature",
  "properties": {
    "addr:full":"Stationsweg 4 Hoofddorp North Holland 2131 XG",
    "addr:housenumber":"4",
    "addr:postcode":"2131 xg",
    "addr:street":"Stationsweg",
    "iso:country":"NL",
    "sg:address":"Stationsweg 4",
    "sg:city":"Hoofddorp",
    "sg:classifiers":[
        {
            "category":"Professional",
            "subcategory":"Accounting & Tax Preparation",
            "type":"Services"
        }
    ],
    "sg:phone":"+31 23 562 1924",
    "sg:postcode":"2131 XG",
    "sg:province":"North Holland",
    "sg:tags":[
        "accountant"
    ],
    "wof:name":"Enter Winter Accountants",
    "wof:placetype":"venue"
},
  "geometry": {"coordinates":[4.694458,52.30724],"type":"Point"}
}