{
  "type": "Feature",
  "properties": {
    "addr:full":"2E Sweelinckstr 124 S Gravenhage Zuid-Holland 2517 HA",
    "addr:housenumber":"124;gravenhage",
    "addr:postcode":"2517 ha",
    "addr:street":"2E Sweelinckstr;S",
    "iso:country":"NL",
    "sg:address":"2E Sweelinckstr 124",
    "sg:city":"S Gravenhage",
    "sg:orig_category":"Artsen - Huisartsen",
    "sg:phone":"+31 70 345 0650",
    "sg:postcode":"2517 HA",
    "sg:province":"Zuid-Holland",
    "sg:website":"http://www.peters.praktijkinfo.nl",
    "wof:name":"Peters, R J",
    "wof:placetype":"venue"
},
  "geometry": {"coordinates":[4.28708,52.08667],"type":"Point"}
}