{
  "type": "Feature",
  "properties": {
    "addr:full":"Brekeldln 11 Ryssen Overijssel 7462 PA",
    "addr:housenumber":"11",
    "addr:postcode":"7462",
    "addr:street":"Brekeldln;Overijssel",
    "iso:country":"NL",
    "sg:address":"Brekeldln 11",
    "sg:city":"Ryssen",
    "sg:orig_category":"Meubellakkerijen En -Spuiterijen",
    "sg:phone":"+31 548 541 575",
    "sg:postcode":"7462 PA",
    "sg:province":"Overijssel",
    "wof:name":"Grouwe Bv",
    "wof:placetype":"venue"
},
  "geometry": {"coordinates":[-77.604507,40.99464],"type":"Point"}
}