{
  "type": "Feature",
  "properties": {
    "iso:country":"NL",
    "sg:address":"Wijenweg 187",
    "sg:city":"Brunssum",
    "sg:orig_category":"Verzekeringen",
    "sg:phone":"+31 45 521 5858",
    "sg:postcode":"6446 AL",
    "sg:province":"Limburg",
    "wof:name":"P Van Hardefeld",
    "wof:placetype":"venue"
},
  "geometry": {"coordinates":[5.94844,50.936523],"type":"Point"}
}