{
  "type": "Feature",
  "properties": {
    "addr:full":"Dorpsstr 52 Geesteren Ov Overijssel 7678 AX",
    "addr:housenumber":"52",
    "addr:postcode":"7678 ax",
    "addr:street":"Dorpsstr;Ov",
    "iso:country":"NL",
    "sg:address":"Dorpsstr 52",
    "sg:city":"Geesteren Ov",
    "sg:orig_category":"Opticiens",
    "sg:phone":"+31 546 631 200",
    "sg:postcode":"7678 AX",
    "sg:province":"Overijssel",
    "wof:name":"Twentse Optiek Centrale",
    "wof:placetype":"venue"
},
  "geometry": {"coordinates":[6.7349510193,52.4205589294],"type":"Point"}
}