{
  "type": "Feature",
  "properties": {
    "addr:full":"Obrechtstr 37 Utrecht Utrecht 3572 EC",
    "addr:housenumber":"37",
    "addr:postcode":"3572 ec",
    "addr:street":"Obrechtstr",
    "iso:country":"NL",
    "sg:address":"Obrechtstr 37",
    "sg:city":"Utrecht",
    "sg:orig_category":"Grafisch Ontwerpers",
    "sg:phone":"+31 30 273 0712",
    "sg:postcode":"3572 EC",
    "sg:province":"Utrecht",
    "wof:name":"Cruijsen, Dini",
    "wof:placetype":"venue"
},
  "geometry": {"coordinates":[5.130069,52.096497],"type":"Point"}
}