{
  "type": "Feature",
  "properties": {
    "addr:full":"Broersvest 42 Schiedam Zuid-Holland 3112 DE",
    "addr:housenumber":"42",
    "addr:postcode":"3112 de",
    "addr:street":"Broersvest",
    "iso:country":"NL",
    "sg:address":"Broersvest 42",
    "sg:city":"Schiedam",
    "sg:orig_category":"Behangselpapier En Wandbekleding",
    "sg:phone":"+31 10 426 2238",
    "sg:postcode":"3112 DE",
    "sg:province":"Zuid-Holland",
    "wof:name":"Behang Super",
    "wof:placetype":"venue"
},
  "geometry": {"coordinates":[4.402682,51.915859],"type":"Point"}
}