{
  "type": "Feature",
  "properties": {
    "iso:country":"NL",
    "sg:address":"Liguster 44",
    "sg:city":"Leidschendam",
    "sg:orig_category":"Horloges En Klokken",
    "sg:phone":"+31 70 317 6975",
    "sg:postcode":"2262 AC",
    "sg:province":"Zuid-Holland",
    "wof:name":"Time Store Horloges",
    "wof:placetype":"venue"
},
  "geometry": {"coordinates":[4.38459,52.088009],"type":"Point"}
}