{
  "type": "Feature",
  "properties": {
    "iso:country":"NL",
    "sg:address":"De Hemeltjes 5",
    "sg:city":"Goirle",
    "sg:orig_category":"Keukens",
    "sg:phone":"+31 13 534 5327",
    "sg:postcode":"5051 JR",
    "sg:province":"Noord-Brabant",
    "wof:name":"Marjo",
    "wof:placetype":"venue"
},
  "geometry": {"coordinates":[5.054558,51.510662],"type":"Point"}
}