{
  "type": "Feature",
  "properties": {
    "addr:full":"Wagnerlaan 55 Arnhem Gelderland 6815 AD",
    "addr:housenumber":"55",
    "addr:postcode":"6815 ad",
    "addr:street":"Wagnerlaan",
    "iso:country":"NL",
    "sg:address":"Wagnerlaan 55",
    "sg:city":"Arnhem",
    "sg:orig_category":"Partycatering And -Organisatie",
    "sg:phone":"+31 26 378 7888",
    "sg:postcode":"6815 AD",
    "sg:province":"Gelderland",
    "wof:name":"Multi Cuisine Arnhem Bv",
    "wof:placetype":"venue"
},
  "geometry": {"coordinates":[5.909449,52.000568],"type":"Point"}
}