{
  "type": "Feature",
  "properties": {
    "addr:full":"Berlynstr 22 Hengelo Ov Overijssel 7559 WH",
    "addr:housenumber":"22",
    "addr:postcode":"7559 wh",
    "addr:street":"Berlynstr;Ov",
    "iso:country":"NL",
    "sg:address":"Berlynstr 22",
    "sg:city":"Hengelo Ov",
    "sg:orig_category":"Kappers",
    "sg:phone":"+31 74 278 1466",
    "sg:postcode":"7559 WH",
    "sg:province":"Overijssel",
    "wof:name":"Patricia",
    "wof:placetype":"venue"
},
  "geometry": {"coordinates":[6.80188,52.298168],"type":"Point"}
}