{
  "type": "Feature",
  "properties": {
    "addr:full":"Tussendiepen 62 Drachten Friesland 9206 AE",
    "addr:housenumber":"62",
    "addr:postcode":"9206 ae",
    "addr:street":"Tussendiepen",
    "iso:country":"NL",
    "sg:address":"Tussendiepen 62",
    "sg:city":"Drachten",
    "sg:orig_category":"Parketvloeren",
    "sg:phone":"+31 512 540 087",
    "sg:postcode":"9206 AE",
    "sg:province":"Friesland",
    "wof:name":"Drachten Bv",
    "wof:placetype":"venue"
},
  "geometry": {"coordinates":[6.06355,53.107327],"type":"Point"}
}