{
  "type": "Feature",
  "properties": {
    "addr:full":"Kattenburg 45A Druten Gelderland 6651 AM",
    "addr:housenumber":"45a",
    "addr:postcode":"6651",
    "addr:street":"Kattenburg",
    "iso:country":"NL",
    "sg:address":"Kattenburg 45A",
    "sg:city":"Druten",
    "sg:orig_category":"Hypotheken",
    "sg:phone":"+31 487 532 505",
    "sg:postcode":"6651 AM",
    "sg:province":"Gelderland",
    "sg:website":"http://www.hypotheekportaal.nl",
    "wof:name":"Hypotheekportaal",
    "wof:placetype":"venue"
},
  "geometry": {"coordinates":[5.608894,51.891926],"type":"Point"}
}