{
  "type": "Feature",
  "properties": {
    "addr:full":"Jan Jacobus Smitpad 19 Schiedam Zuid-Holland 3123 CG",
    "addr:housenumber":"19",
    "addr:postcode":"3123 cg",
    "addr:street":"Jan Jacobus Smitpad",
    "iso:country":"NL",
    "sg:address":"Jan Jacobus Smitpad 19",
    "sg:city":"Schiedam",
    "sg:orig_category":"Metaalafval, Schrootrecycling And Sloperijen",
    "sg:phone":"+31 10 471 5747",
    "sg:postcode":"3123 CG",
    "sg:province":"Zuid-Holland",
    "wof:name":"K J Kuperus",
    "wof:placetype":"venue"
},
  "geometry": {"coordinates":[4.367687,51.94371],"type":"Point"}
}