{
  "type": "Feature",
  "properties": {
    "addr:full":"Oenselsestr 27 Zaltbommel Gelderland 5301 EN",
    "addr:housenumber":"27",
    "addr:postcode":"5301 en",
    "addr:street":"Oenselsestr;Gelderland",
    "iso:country":"NL",
    "sg:address":"Oenselsestr 27",
    "sg:city":"Zaltbommel",
    "sg:orig_category":"Adviesbureaus Bedrijfsorganisatie",
    "sg:phone":"+31 418 517 889",
    "sg:postcode":"5301 EN",
    "sg:province":"Gelderland",
    "wof:name":"Sila, Management Group Bv",
    "wof:placetype":"venue"
},
  "geometry": {"coordinates":[5.253003,51.813686],"type":"Point"}
}