{
  "type": "Feature",
  "properties": {
    "iso:country":"NL",
    "sg:address":"Marsdiepstraat 313",
    "sg:city":"Den Helder",
    "sg:orig_category":"Werving And Selectie Van Tijdelijk Personeel And Uitzendkantoren",
    "sg:phone":"+31 223 647 271",
    "sg:postcode":"1784 AG",
    "sg:province":"Noord-Holland",
    "wof:name":"2000",
    "wof:placetype":"venue"
},
  "geometry": {"coordinates":[4.7424302101,52.9442939758],"type":"Point"}
}