{
  "type": "Feature",
  "properties": {
    "addr:full":"Kleingraverstr 18 Kerkrade Limburg 6466 EE",
    "addr:housenumber":"18",
    "addr:postcode":"6466 ee",
    "addr:street":"Kleingraverstr",
    "iso:country":"NL",
    "sg:address":"Kleingraverstr 18",
    "sg:city":"Kerkrade",
    "sg:orig_category":"Autoruiten",
    "sg:phone":"+31 6 21544798",
    "sg:postcode":"6466 EE",
    "sg:province":"Limburg",
    "wof:name":"Collaris",
    "wof:placetype":"venue"
},
  "geometry": {"coordinates":[6.036265,50.859619],"type":"Point"}
}