{
  "type": "Feature",
  "properties": {
    "iso:country":"NL",
    "sg:address":"Koningstr 34",
    "sg:city":"Den Helder",
    "sg:orig_category":"Koffie- En Theehuizen",
    "sg:phone":"+31 223 627 242",
    "sg:postcode":"1781 KH",
    "sg:province":"Noord-Holland",
    "wof:name":"Tops",
    "wof:placetype":"venue"
},
  "geometry": {"coordinates":[4.761416,52.961403],"type":"Point"}
}