{
  "type": "Feature",
  "properties": {
    "addr:full":"V Breestr 85 Amsterdam Noord-Holland 1071 ZH",
    "addr:housenumber":"85",
    "addr:postcode":"1071 zh",
    "iso:country":"NL",
    "sg:address":"V Breestr 85",
    "sg:city":"Amsterdam",
    "sg:orig_category":"Verenigingen En Stichtingen",
    "sg:phone":"+31 20 679 1805",
    "sg:postcode":"1071 ZH",
    "sg:province":"Noord-Holland",
    "sg:website":"http://www.amsterdamsegevelstenen.nl",
    "wof:name":"Vrienden A'Damse Gevelstenen",
    "wof:placetype":"venue"
},
  "geometry": {"coordinates":[4.87701,52.355549],"type":"Point"}
}