{
  "type": "Feature",
  "properties": {
    "iso:country":"NL",
    "sg:address":"Volume 50",
    "sg:city":"Purmerend",
    "sg:orig_category":"Administratie- En Boekhoudkantoren",
    "sg:phone":"+31 299 405 390",
    "sg:postcode":"1446 WJ",
    "sg:province":"Noord-Holland",
    "wof:name":"Bosschieter, D",
    "wof:placetype":"venue"
},
  "geometry": {"coordinates":[5.004971,52.509357],"type":"Point"}
}