{
  "type": "Feature",
  "properties": {
    "addr:full":"Volume 50 Purmerend Noord-Holland 1446 WJ",
    "addr:housenumber":"50",
    "addr:postcode":"1446 wj",
    "addr:street":"Volume",
    "iso:country":"NL",
    "sg:address":"Volume 50",
    "sg:city":"Purmerend",
    "sg:orig_category":"Administratie- En Boekhoudkantoren",
    "sg:phone":"+31 299 405 390",
    "sg:postcode":"1446 WJ",
    "sg:province":"Noord-Holland",
    "wof:name":"Bosschieter, D",
    "wof:placetype":"venue"
},
  "geometry": {"coordinates":[5.004971,52.509357],"type":"Point"}
}