{
  "type": "Feature",
  "properties": {
    "addr:full":"Burgemeester Vitringaln 2 Ermelo Gelderland 3851 PM",
    "addr:housenumber":"2",
    "addr:postcode":"3851 pm",
    "addr:street":"Burgemeester Vitringaln;Gelderland",
    "iso:country":"NL",
    "sg:address":"Burgemeester Vitringaln 2",
    "sg:city":"Ermelo",
    "sg:orig_category":"Meubelreparatie And -Restauratie",
    "sg:phone":"+31 341 551 348",
    "sg:postcode":"3851 PM",
    "sg:province":"Gelderland",
    "wof:name":"B. Van Den Akker",
    "wof:placetype":"venue"
},
  "geometry": {"coordinates":[5.623644,52.300426],"type":"Point"}
}