{
  "type": "Feature",
  "properties": {
    "addr:full":"Beverveen 505 Spykenisse Zuid-Holland 3205 AG",
    "addr:housenumber":"505",
    "addr:postcode":"3205",
    "addr:street":"Beverveen",
    "iso:country":"NL",
    "sg:address":"Beverveen 505",
    "sg:city":"Spykenisse",
    "sg:orig_category":"Artsen - Huisartsen",
    "sg:phone":"+31 181 639 222",
    "sg:postcode":"3205 AG",
    "sg:province":"Zuid-Holland",
    "wof:name":"Janssen, A G M",
    "wof:placetype":"venue"
},
  "geometry": {"coordinates":[4.33509,51.83387],"type":"Point"}
}