{
  "type": "Feature",
  "properties": {
    "addr:full":"Oude Baan 26A Rosmalen North Brabant 5242 HS",
    "addr:housenumber":"26a",
    "addr:postcode":"5242 hs",
    "addr:street":"Oude Baan",
    "iso:country":"NL",
    "sg:address":"Oude Baan 26A",
    "sg:city":"Rosmalen",
    "sg:orig_category":"Juridische Adviseurs",
    "sg:phone":"+31 73 521 7177",
    "sg:postcode":"5242 HS",
    "sg:province":"North Brabant",
    "wof:name":"Winkelman Bv, Drs H E",
    "wof:placetype":"venue"
},
  "geometry": {"coordinates":[5.367916,51.708729],"type":"Point"}
}