{
  "type": "Feature",
  "properties": {
    "addr:full":"J H Van 'T Hoffweg 26 Bussum North Holland 1402 VK",
    "addr:housenumber":"26",
    "addr:postcode":"1402 vk",
    "addr:street":"J H Van ' T Hoffweg",
    "iso:country":"NL",
    "sg:address":"J H Van 'T Hoffweg 26",
    "sg:city":"Bussum",
    "sg:orig_category":"Marktonderzoekbureaus",
    "sg:phone":"+31 35 692 2736",
    "sg:postcode":"1402 VK",
    "sg:province":"North Holland",
    "wof:name":"Merle",
    "wof:placetype":"venue"
},
  "geometry": {"coordinates":[5.180253,52.27269],"type":"Point"}
}