{
  "type": "Feature",
  "properties": {
    "addr:full":"Bocksmeulen 27 Dokkum Friesland 9101 RA",
    "addr:housenumber":"27",
    "addr:postcode":"9101 ra",
    "addr:street":"Bocksmeulen",
    "iso:country":"NL",
    "sg:address":"Bocksmeulen 27",
    "sg:city":"Dokkum",
    "sg:orig_category":"Verf En Lak - Fabrieken En Groothandel",
    "sg:phone":"+31 519 229 922",
    "sg:postcode":"9101 RA",
    "sg:province":"Friesland",
    "wof:name":"Olijslager",
    "wof:placetype":"venue"
},
  "geometry": {"coordinates":[6.01581,53.320179],"type":"Point"}
}