{
  "type": "Feature",
  "properties": {
    "addr:full":"Postbus 1365 Enschede Overijssel 7500 BJ",
    "addr:housenumber":"1365",
    "addr:postcode":"7500 bj",
    "addr:street":"Postbus",
    "iso:country":"NL",
    "sg:address":"Postbus 1365",
    "sg:city":"Enschede",
    "sg:orig_category":"Verenigingen En Stichtingen",
    "sg:phone":"+31 53 432 0887",
    "sg:postcode":"7500 BJ",
    "sg:province":"Overijssel",
    "wof:name":"Sdo",
    "wof:placetype":"venue"
},
  "geometry": {"coordinates":[6.89112,52.220821],"type":"Point"}
}