{
  "type": "Feature",
  "properties": {
    "iso:country":"NL",
    "sg:address":"3E Vd Kunstr 34",
    "sg:city":"S Gravenhage",
    "sg:orig_category":"Levensmiddelen - Fabrieken En Groothandel",
    "sg:phone":"+31 70 305 0749",
    "sg:postcode":"2521 BC",
    "sg:province":"South Holland",
    "wof:name":"Aliaf",
    "wof:placetype":"venue"
},
  "geometry": {"coordinates":[4.32071,52.062988],"type":"Point"}
}