{
  "type": "Feature",
  "properties": {
    "addr:full":"Eigenhaardstr 28 Zwolle Overijssel 8012 VG",
    "addr:housenumber":"28",
    "addr:postcode":"8012 vg",
    "addr:street":"Eigenhaardstr",
    "iso:country":"NL",
    "sg:address":"Eigenhaardstr 28",
    "sg:city":"Zwolle",
    "sg:orig_category":"Administratie- En Boekhoudkantoren",
    "sg:phone":"+31 6 20191402",
    "sg:postcode":"8012 VG",
    "sg:province":"Overijssel",
    "wof:name":"Boertjes, Monique",
    "wof:placetype":"venue"
},
  "geometry": {"coordinates":[6.101639,52.506985],"type":"Point"}
}