{
  "type": "Feature",
  "properties": {
    "addr:full":"Heerestr 80 Roden Drenthe 9301 AH",
    "addr:housenumber":"80",
    "addr:postcode":"9301 ah",
    "addr:street":"Heerestr",
    "iso:country":"NL",
    "sg:address":"Heerestr 80",
    "sg:city":"Roden",
    "sg:orig_category":"Warenhuizen",
    "sg:phone":"+31 50 501 4502",
    "sg:postcode":"9301 AH",
    "sg:province":"Drenthe",
    "wof:name":"Hema",
    "wof:placetype":"venue"
},
  "geometry": {"coordinates":[6.4296340942,53.1374092102],"type":"Point"}
}