{
  "type": "Feature",
  "properties": {
    "addr:full":"Bingerwg 14A Haarlem Noord-Holland 2031 AZ",
    "addr:housenumber":"14a",
    "addr:postcode":"2031 az",
    "addr:street":"Bingerwg",
    "iso:country":"NL",
    "sg:address":"Bingerwg 14A",
    "sg:city":"Haarlem",
    "sg:orig_category":"Autopoetsbedrijven",
    "sg:phone":"+31 23 532 3338",
    "sg:postcode":"2031 AZ",
    "sg:province":"Noord-Holland",
    "wof:name":"Fine Cars",
    "wof:placetype":"venue"
},
  "geometry": {"coordinates":[4.662778,52.396877],"type":"Point"}
}