{
  "type": "Feature",
  "properties": {
    "addr:full":"Pr Beatrixstr 17 Elst Gld Gelderland 6661 VN",
    "addr:housenumber":"17",
    "addr:postcode":"6661 vn",
    "addr:street":"Gld Gelderland",
    "iso:country":"NL",
    "sg:address":"Pr Beatrixstr 17",
    "sg:city":"Elst Gld",
    "sg:orig_category":"Autorijscholen",
    "sg:phone":"+31 481 351 135",
    "sg:postcode":"6661 VN",
    "sg:province":"Gelderland",
    "wof:name":"Rohen Autorijschool",
    "wof:placetype":"venue"
},
  "geometry": {"coordinates":[5.842382,51.923485],"type":"Point"}
}