{
  "type": "Feature",
  "properties": {
    "addr:full":"Kennemerstraatw 339 Heiloo North Holland 1851 ND",
    "addr:housenumber":"339",
    "addr:postcode":"1851 nd",
    "iso:country":"NL",
    "sg:address":"Kennemerstraatw 339",
    "sg:city":"Heiloo",
    "sg:orig_category":"Bloembollen - Groothandel",
    "sg:phone":"+31 72 533 1717",
    "sg:postcode":"1851 ND",
    "sg:province":"North Holland",
    "wof:name":"Hommes Iris Bv",
    "wof:placetype":"venue"
},
  "geometry": {"coordinates":[4.713702,52.604191],"type":"Point"}
}