{
  "type": "Feature",
  "properties": {
    "addr:full":"Waalwg 37B Ridderkerk Zuid-Holland 2988 CH",
    "addr:housenumber":"37b",
    "addr:postcode":"2988",
    "addr:street":"Waalwg",
    "iso:country":"NL",
    "sg:address":"Waalwg 37B",
    "sg:city":"Ridderkerk",
    "sg:orig_category":"Metaalbewerking",
    "sg:phone":"+31 180 421 169",
    "sg:postcode":"2988 CH",
    "sg:province":"Zuid-Holland",
    "wof:name":"Wingerden, J Van",
    "wof:placetype":"venue"
},
  "geometry": {"coordinates":[4.585758,51.852177],"type":"Point"}
}