{
  "type": "Feature",
  "properties": {
    "addr:full":"Smidsln 32 Appelscha Provincie Friesland 8426 DE",
    "addr:housenumber":"32;8426",
    "addr:street":"Smidsln;Provincie Friesland;De",
    "iso:country":"NL",
    "sg:address":"Smidsln 32",
    "sg:city":"Appelscha",
    "sg:orig_category":"Fietsen En Bromfietsen Verhuur",
    "sg:phone":"+31 516 432 627",
    "sg:postcode":"8426 DE",
    "sg:province":"Provincie Friesland",
    "wof:name":"Buist, Pia",
    "wof:placetype":"venue"
},
  "geometry": {"coordinates":[6.339048,52.95488],"type":"Point"}
}