{
  "type": "Feature",
  "properties": {
    "addr:full":"Kerkraderwg 90 Heerlen Limburg 6416 CL",
    "addr:housenumber":"90",
    "addr:postcode":"6416",
    "addr:street":"Kerkraderwg",
    "iso:country":"NL",
    "sg:address":"Kerkraderwg 90",
    "sg:city":"Heerlen",
    "sg:orig_category":"Verenigingen En Stichtingen",
    "sg:phone":"+31 45 542 1408",
    "sg:postcode":"6416 CL",
    "sg:province":"Limburg",
    "wof:name":"Martial Arts Dojo, Sticht",
    "wof:placetype":"venue"
},
  "geometry": {"coordinates":[5.998457,50.882648],"type":"Point"}
}