{
  "type": "Feature",
  "properties": {
    "iso:country":"NL",
    "sg:address":"Lugtigheidstr 56",
    "sg:city":"S Gravenzande",
    "sg:orig_category":"Onderhoudswerken",
    "sg:phone":"+31 174 415 657",
    "sg:postcode":"2691 LV",
    "sg:province":"Zuid-Holland",
    "wof:name":"Vugt, D Van",
    "wof:placetype":"venue"
},
  "geometry": {"coordinates":[4.180725,51.98148],"type":"Point"}
}