{
  "type": "Feature",
  "properties": {
    "addr:full":"Spoorstr 122A Gennep Limburg 6591 GW",
    "addr:housenumber":"122a",
    "addr:postcode":"6591 gw",
    "iso:country":"NL",
    "sg:address":"Spoorstr 122A",
    "sg:city":"Gennep",
    "sg:orig_category":"Advocaten En Advocatenkantoren",
    "sg:phone":"+31 485 540 600",
    "sg:postcode":"6591 GW",
    "sg:province":"Limburg",
    "wof:name":"Heutink",
    "wof:placetype":"venue"
},
  "geometry": {"coordinates":[5.972648,51.696083],"type":"Point"}
}