{
  "type": "Feature",
  "properties": {
    "addr:full":"Ophemertstr 69 Rotterdam Zuid-Holland 3089 JD",
    "addr:housenumber":"69",
    "addr:postcode":"3089 jd",
    "addr:street":"Ophemertstr",
    "iso:country":"NL",
    "sg:address":"Ophemertstr 69",
    "sg:city":"Rotterdam",
    "sg:orig_category":"Adviesbureaus Bedrijfsorganisatie",
    "sg:phone":"+31 10 428 1031",
    "sg:postcode":"3089 JD",
    "sg:province":"Zuid-Holland",
    "wof:name":"Linden, C Van Der",
    "wof:placetype":"venue"
},
  "geometry": {"coordinates":[4.435277,51.886253],"type":"Point"}
}