{
  "type": "Feature",
  "properties": {
    "iso:country":"NL",
    "sg:address":"Nw Spiegelstr 40",
    "sg:city":"Amsterdam",
    "sg:orig_category":"Kunsthandel",
    "sg:phone":"+31 20 623 4748",
    "sg:postcode":"1017 DG",
    "sg:province":"Noord-Holland",
    "wof:name":"Vecht, A",
    "wof:placetype":"venue"
},
  "geometry": {"coordinates":[4.88877,52.363792],"type":"Point"}
}