{
  "type": "Feature",
  "properties": {
    "addr:full":"Neckerstr 143 Wydewormer Noord-Holland 1456 BC",
    "addr:housenumber":"143",
    "addr:postcode":"1456 bc",
    "addr:street":"Wydewormer Noord-Holland",
    "iso:country":"NL",
    "sg:address":"Neckerstr 143",
    "sg:city":"Wydewormer",
    "sg:orig_category":"Luchtbehandelings- Apparaten",
    "sg:phone":"+31 299 423 606",
    "sg:postcode":"1456 BC",
    "sg:province":"Noord-Holland",
    "sg:website":"http://www.jpl-bv.nl",
    "wof:name":"Jansen Purmerend Bv",
    "wof:placetype":"venue"
},
  "geometry": {"coordinates":[4.926515,52.509701],"type":"Point"}
}