{
  "type": "Feature",
  "properties": {
    "addr:full":"Oosterhoutsewg 55 57 Ryen Noord-Brabant 5121 RE",
    "addr:housenumber":"55 57",
    "addr:postcode":"5121 re",
    "addr:street":"Oosterhoutsewg",
    "iso:country":"NL",
    "sg:address":"Oosterhoutsewg 55 57",
    "sg:city":"Ryen",
    "sg:orig_category":"Zalenverhuur",
    "sg:phone":"+31 161 223 538",
    "sg:postcode":"5121 RE",
    "sg:province":"Noord-Brabant",
    "wof:name":"Vijfeiken Bv, De",
    "wof:placetype":"venue"
},
  "geometry": {"coordinates":[4.9197,51.588017],"type":"Point"}
}