{
  "type": "Feature",
  "properties": {
    "addr:full":"Wethouder Beversstraat 200 Enschede NL.08 7543 BN",
    "addr:housenumber":"200",
    "addr:postcode":"7543 bn",
    "addr:street":"Wethouder Beversstraat",
    "iso:country":"NL",
    "sg:address":"Wethouder Beversstraat 200",
    "sg:city":"Enschede",
    "sg:orig_category":"Metaalbekleding And -Behandeling",
    "sg:phone":"+31 53 482 9292",
    "sg:postcode":"7543 BN",
    "sg:province":"NL.08",
    "wof:name":"Dcw Bedrijven",
    "wof:placetype":"venue"
},
  "geometry": {"coordinates":[6.88903,52.206402],"type":"Point"}
}