{
  "type": "Feature",
  "properties": {
    "addr:full":"B Franklinstr 16 Zwolle Overijssel 8013 NC",
    "addr:housenumber":"16",
    "addr:postcode":"8013 nc",
    "iso:country":"NL",
    "sg:address":"B Franklinstr 16",
    "sg:city":"Zwolle",
    "sg:orig_category":"Faxapparatuur",
    "sg:phone":"+31 38 466 0090",
    "sg:postcode":"8013 NC",
    "sg:province":"Overijssel",
    "sg:website":"http://www.document-house.nl/zwolle",
    "wof:name":"Document House",
    "wof:placetype":"venue"
},
  "geometry": {"coordinates":[6.121067,52.492863],"type":"Point"}
}