{
  "type": "Feature",
  "properties": {
    "iso:country":"NL",
    "sg:address":"Oeverkamp 22",
    "sg:city":"Bemmel",
    "sg:orig_category":"Bloemen En Planten - Groothandel",
    "sg:phone":"+31 481 464 726",
    "sg:postcode":"6681 MZ",
    "sg:province":"Gelderland",
    "wof:name":"Hendriks, P T M",
    "wof:placetype":"venue"
},
  "geometry": {"coordinates":[5.890616,51.896385],"type":"Point"}
}