{
  "type": "Feature",
  "properties": {
    "addr:full":"Broeksterkleiwg 3 Pieterburen Groningen 9968 TG",
    "addr:housenumber":"3",
    "addr:postcode":"9968 tg",
    "addr:street":"Broeksterkleiwg",
    "iso:country":"NL",
    "sg:address":"Broeksterkleiwg 3",
    "sg:city":"Pieterburen",
    "sg:classifiers":[
        {
            "category":"Travel",
            "subcategory":"Hotels & Motels",
            "type":"Entertainment"
        }
    ],
    "sg:phone":"+31 595 481 632",
    "sg:postcode":"9968 TG",
    "sg:province":"Groningen",
    "sg:website":"HTTP://www.broekstermaar.nl",
    "wof:name":"Broekstermaar, De",
    "wof:placetype":"venue"
},
  "geometry": {"coordinates":[6.423498,53.385544],"type":"Point"}
}