{
  "type": "Feature",
  "properties": {
    "addr:full":"Naberpassage 3 Groningen Groningen 9712 JV",
    "addr:housenumber":"3",
    "addr:postcode":"9712 jv",
    "addr:street":"Naberpassage",
    "iso:country":"NL",
    "sg:address":"Naberpassage 3",
    "sg:city":"Groningen",
    "sg:orig_category":"Woningbouwverenigingen",
    "sg:phone":"+31 50 853 3533",
    "sg:postcode":"9712 JV",
    "sg:province":"Groningen",
    "wof:name":"Nijestee",
    "wof:placetype":"venue"
},
  "geometry": {"coordinates":[6.5687260628,53.2185173035],"type":"Point"}
}