{
  "type": "Feature",
  "properties": {
    "addr:full":"Kapelstr 6 Veghel Noord-Brabant 5466 PC",
    "addr:housenumber":"6",
    "addr:postcode":"5466 pc",
    "addr:street":"Kapelstr",
    "iso:country":"NL",
    "sg:address":"Kapelstr 6",
    "sg:city":"Veghel",
    "sg:orig_category":"Huishoudelijke Apparaten En Artikelen",
    "sg:phone":"+31 413 319 787",
    "sg:postcode":"5466 PC",
    "sg:province":"Noord-Brabant",
    "wof:name":"Biggelaar Vof, Van Den",
    "wof:placetype":"venue"
},
  "geometry": {"coordinates":[5.50117,51.603539],"type":"Point"}
}