{
  "type": "Feature",
  "properties": {
    "iso:country":"NL",
    "sg:address":"Zoelensestraat 52",
    "sg:city":"Kapel Avezaath",
    "sg:orig_category":"Kappers",
    "sg:phone":"+31 344 661 629",
    "sg:postcode":"4013 CS",
    "sg:province":"Gelderland",
    "wof:name":"Josette Smits",
    "wof:placetype":"venue"
},
  "geometry": {"coordinates":[5.3878211975,51.8866882324],"type":"Point"}
}