{
  "type": "Feature",
  "properties": {
    "addr:full":"Gasthuisstr 30 Venlo Limburg 5911 JK",
    "addr:housenumber":"30",
    "addr:postcode":"5911 jk",
    "addr:street":"Gasthuisstr",
    "iso:country":"NL",
    "sg:address":"Gasthuisstr 30",
    "sg:city":"Venlo",
    "sg:orig_category":"Kappers",
    "sg:phone":"+31 77 354 5423",
    "sg:postcode":"5911 JK",
    "sg:province":"Limburg",
    "wof:name":"Team Huizenaar",
    "wof:placetype":"venue"
},
  "geometry": {"coordinates":[6.17013,51.369972],"type":"Point"}
}