{
  "type": "Feature",
  "properties": {
    "addr:full":"Willemstr 1 Breda North Brabant 4811 AH",
    "addr:housenumber":"1",
    "addr:postcode":"4811 ah",
    "addr:street":"Willemstr",
    "iso:country":"NL",
    "sg:address":"Willemstr 1",
    "sg:city":"Breda",
    "sg:orig_category":"Verzekeringen - Verzekeringskantoren",
    "sg:phone":"+31 76 531 3210",
    "sg:postcode":"4811 AH",
    "sg:province":"North Brabant",
    "wof:name":"Stiba",
    "wof:placetype":"venue"
},
  "geometry": {"coordinates":[4.779346,51.593391],"type":"Point"}
}