{
  "type": "Feature",
  "properties": {
    "iso:country":"NL",
    "sg:address":"J Bildersstr 16",
    "sg:city":"S Gravenhage",
    "sg:orig_category":"Adviesbureaus Personeel",
    "sg:phone":"+31 70 324 2874",
    "sg:postcode":"2596 EH",
    "sg:province":"Zuid-Holland",
    "wof:name":"Couzy Bv",
    "wof:placetype":"venue"
},
  "geometry": {"coordinates":[4.31846,52.093311],"type":"Point"}
}