{
  "type": "Feature",
  "properties": {
    "addr:full":"Vyzelmolenln 11A Woerden Utrecht 3447 GX",
    "addr:housenumber":"11a",
    "addr:postcode":"3447 gx",
    "addr:street":"Vyzelmolenln",
    "iso:country":"NL",
    "sg:address":"Vyzelmolenln 11A",
    "sg:city":"Woerden",
    "sg:orig_category":"Accountants - Administratie- Consulenten En -Kantoren",
    "sg:phone":"+31 348 481 817",
    "sg:postcode":"3447 GX",
    "sg:province":"Utrecht",
    "wof:name":"Gibo Groep",
    "wof:placetype":"venue"
},
  "geometry": {"coordinates":[4.887835,52.075809],"type":"Point"}
}