{
  "type": "Feature",
  "properties": {
    "iso:country":"NL",
    "sg:address":"Databankwg 18",
    "sg:city":"Amersfoort",
    "sg:orig_category":"Verhuizingen",
    "sg:phone":"+31 33 450 8210",
    "sg:postcode":"3821 AL",
    "sg:province":"Utrecht",
    "sg:website":"http://www.pot-verhuizingen.nl",
    "wof:name":"Pot Verhuizingen/Logistiek",
    "wof:placetype":"venue"
},
  "geometry": {"coordinates":[5.416917,52.181835],"type":"Point"}
}