{
  "type": "Feature",
  "properties": {
    "addr:full":"Compierekd 8 Alphen Aan Den Ryn South Holland 2404 NA",
    "addr:housenumber":"8",
    "addr:postcode":"2404 na",
    "addr:street":"Compierekd;Aan Den Ryn",
    "iso:country":"NL",
    "sg:address":"Compierekd 8",
    "sg:city":"Alphen Aan Den Ryn",
    "sg:orig_category":"Kaas",
    "sg:phone":"+31 172 589 148",
    "sg:postcode":"2404 NA",
    "sg:province":"South Holland",
    "wof:name":"Lena'S Hoeve",
    "wof:placetype":"venue"
},
  "geometry": {"coordinates":[4.6589207649,52.1271896362],"type":"Point"}
}