{
  "type": "Feature",
  "properties": {
    "addr:full":"Van Woustraat 92 Amsterdam Noord-Holland 1073 LP",
    "addr:housenumber":"92",
    "addr:postcode":"1073 lp",
    "addr:street":"Van Woustraat",
    "iso:country":"NL",
    "sg:address":"Van Woustraat 92",
    "sg:city":"Amsterdam",
    "sg:orig_category":"Werving And Selectie Van Tijdelijk Personeel And Uitzendkantoren",
    "sg:phone":"+31 20 664 1511",
    "sg:postcode":"1073 LP",
    "sg:province":"Noord-Holland",
    "wof:name":"Randstad Uitzendbureau",
    "wof:placetype":"venue"
},
  "geometry": {"coordinates":[4.9010090828,52.3548660278],"type":"Point"}
}