{
  "type": "Feature",
  "properties": {
    "addr:full":"Industriewg 30 Vlaardingen Zuid-Holland 3133 EE",
    "addr:housenumber":"30",
    "addr:postcode":"3133 ee",
    "addr:street":"Industriewg",
    "iso:country":"NL",
    "sg:address":"Industriewg 30",
    "sg:city":"Vlaardingen",
    "sg:orig_category":"Heftrucks",
    "sg:phone":"+31 800 0224888",
    "sg:postcode":"3133 EE",
    "sg:province":"Zuid-Holland",
    "sg:website":"http://www.yale.nl",
    "wof:name":"Yale Nederland Bv",
    "wof:placetype":"venue"
},
  "geometry": {"coordinates":[4.326603,51.902115],"type":"Point"}
}