{
  "type": "Feature",
  "properties": {
    "iso:country":"NL",
    "sg:address":"Oostzeedijk Beneden 99",
    "sg:city":"Rotterdam",
    "sg:classifiers":[
        {
            "category":"Food & Beverages",
            "subcategory":"Fruits & Vegetables",
            "type":"Retail Goods"
        }
    ],
    "sg:phone":"+31 10 412 2655",
    "sg:postcode":"3061 VP",
    "sg:province":"South Holland",
    "sg:tags":[
        "groenten"
    ],
    "wof:name":"B G Kool",
    "wof:placetype":"venue"
},
  "geometry": {"coordinates":[4.50441,51.922138],"type":"Point"}
}