{
  "type": "Feature",
  "properties": {
    "addr:full":"Bronbeeklaan 14 Arnhem Gelderland 6824 PG",
    "addr:housenumber":"14",
    "addr:postcode":"6824 pg",
    "addr:street":"Bronbeeklaan",
    "iso:country":"NL",
    "sg:address":"Bronbeeklaan 14",
    "sg:city":"Arnhem",
    "sg:orig_category":"Public Relationbureaus",
    "sg:phone":"+31 26 364 4402",
    "sg:postcode":"6824 PG",
    "sg:province":"Gelderland",
    "wof:name":"Ovco Promotions",
    "wof:placetype":"venue"
},
  "geometry": {"coordinates":[5.948443,51.996433],"type":"Point"}
}