{
  "type": "Feature",
  "properties": {
    "addr:full":"Grijze Kraai 8 Emmen Drenthe 7827 JW",
    "addr:housenumber":"8",
    "addr:postcode":"7827 jw",
    "addr:street":"Grijze Kraai",
    "iso:country":"NL",
    "sg:address":"Grijze Kraai 8",
    "sg:city":"Emmen",
    "sg:orig_category":"Marktonderzoekbureaus",
    "sg:phone":"+31 591 633 892",
    "sg:postcode":"7827 JW",
    "sg:province":"Drenthe",
    "wof:name":"Look Into The Future",
    "wof:placetype":"venue"
},
  "geometry": {"coordinates":[6.892678,52.745743],"type":"Point"}
}