{
  "type": "Feature",
  "properties": {
    "addr:full":"Markt 9 Boxtel Noord-Brabant 5281 AT",
    "addr:housenumber":"9",
    "addr:postcode":"5281",
    "addr:street":"Markt",
    "iso:country":"NL",
    "sg:address":"Markt 9",
    "sg:city":"Boxtel",
    "sg:orig_category":"Opticiens",
    "sg:phone":"+31 411 674 198",
    "sg:postcode":"5281 AT",
    "sg:province":"Noord-Brabant",
    "wof:name":"Borne, Joop Van Den",
    "wof:placetype":"venue"
},
  "geometry": {"coordinates":[5.32710886,51.5886421204],"type":"Point"}
}