{
  "type": "Feature",
  "properties": {
    "iso:country":"NL",
    "sg:address":"K Leidsedwstr 79",
    "sg:city":"Amsterdam",
    "sg:classifiers":[
        {
            "category":"Travel",
            "subcategory":"Hotels & Motels",
            "type":"Entertainment"
        }
    ],
    "sg:phone":"+31 20 627 2505",
    "sg:postcode":"1017 PW",
    "sg:province":"Noord-Holland",
    "wof:name":"Leidseplein Hotel, Het",
    "wof:placetype":"venue"
},
  "geometry": {"coordinates":[4.879735,52.364559],"type":"Point"}
}