{
  "type": "Feature",
  "properties": {
    "addr:full":"Dkn Zondagln 104 Vogelenzang Noord-Holland 2114 EE",
    "addr:housenumber":"104",
    "addr:postcode":"2114 ee",
    "iso:country":"NL",
    "sg:address":"Dkn Zondagln 104",
    "sg:city":"Vogelenzang",
    "sg:orig_category":"Verenigingen En Stichtingen",
    "sg:phone":"+31 23 584 9696",
    "sg:postcode":"2114 EE",
    "sg:province":"Noord-Holland",
    "wof:name":"Welzijn Ouderen",
    "wof:placetype":"venue"
},
  "geometry": {"coordinates":[4.575664,52.319878],"type":"Point"}
}