{
  "type": "Feature",
  "properties": {
    "iso:country":"NL",
    "sg:address":"Fluitekruid 25",
    "sg:city":"Hardenberg",
    "sg:orig_category":"Verhuur Huishoudartikelen",
    "sg:phone":"+31 523 260 892",
    "sg:postcode":"7772 ND",
    "sg:province":"Overijssel",
    "wof:name":"Waslijn",
    "wof:placetype":"venue"
},
  "geometry": {"coordinates":[6.649578,52.57851],"type":"Point"}
}