{
  "type": "Feature",
  "properties": {
    "addr:full":"Mauritssngl 54A Leiderdorp Zuid-Holland 2351 EG",
    "addr:housenumber":"54a",
    "addr:postcode":"2351 eg",
    "addr:street":"Mauritssngl",
    "iso:country":"NL",
    "sg:address":"Mauritssngl 54A",
    "sg:city":"Leiderdorp",
    "sg:orig_category":"Orthopedische Artikelen",
    "sg:phone":"+31 71 576 1150",
    "sg:postcode":"2351 EG",
    "sg:province":"Zuid-Holland",
    "wof:name":"Royal Rest",
    "wof:placetype":"venue"
},
  "geometry": {"coordinates":[4.5342178345,52.1561737061],"type":"Point"}
}