{
  "type": "Feature",
  "properties": {
    "iso:country":"NL",
    "sg:address":"De Loo 38",
    "sg:city":"Mierlo",
    "sg:orig_category":"Grafisch Ontwerpers",
    "sg:phone":"+31 492 664 410",
    "sg:postcode":"5731 MK",
    "sg:province":"Noord-Brabant",
    "wof:name":"Stapstudio",
    "wof:placetype":"venue"
},
  "geometry": {"coordinates":[5.619095,51.434914],"type":"Point"}
}