{
  "type": "Feature",
  "properties": {
    "iso:country":"NL",
    "sg:address":"Stromenln 113",
    "sg:city":"Woerden",
    "sg:orig_category":"Koeriersdiensten",
    "sg:phone":"+31 348 413 364",
    "sg:postcode":"3448 CD",
    "sg:province":"Utrecht",
    "wof:name":"Ewijk, Van",
    "wof:placetype":"venue"
},
  "geometry": {"coordinates":[4.870701,52.077923],"type":"Point"}
}