{
  "type": "Feature",
  "properties": {
    "addr:full":"Leusderwg 133 Amersfoort Utrecht 3818 AB",
    "addr:housenumber":"133",
    "addr:postcode":"3818 ab",
    "iso:country":"NL",
    "sg:address":"Leusderwg 133",
    "sg:city":"Amersfoort",
    "sg:orig_category":"Juweliers",
    "sg:phone":"+31 33 461 4161",
    "sg:postcode":"3818 AB",
    "sg:province":"Utrecht",
    "wof:name":"Nipshagen, H J A",
    "wof:placetype":"venue"
},
  "geometry": {"coordinates":[5.379418,52.142357],"type":"Point"}
}