{
  "type": "Feature",
  "properties": {
    "addr:full":"Ptr Beatusstr 7 Heerlen Limburg 6411 TR",
    "addr:housenumber":"7",
    "addr:postcode":"6411 tr",
    "addr:street":"Beatusstr",
    "iso:country":"NL",
    "sg:address":"Ptr Beatusstr 7",
    "sg:city":"Heerlen",
    "sg:orig_category":"Verenigingsgebouwen",
    "sg:phone":"+31 45 571 5241",
    "sg:postcode":"6411 TR",
    "sg:province":"Limburg",
    "wof:name":"Loon, 'T",
    "wof:placetype":"venue"
},
  "geometry": {"coordinates":[5.969363,50.888733],"type":"Point"}
}