{
  "type": "Feature",
  "properties": {
    "addr:full":"Grt Kerkstr 83 Leeuwarden Friesland 8911 EB",
    "addr:housenumber":"83",
    "addr:postcode":"8911 eb",
    "iso:country":"NL",
    "sg:address":"Grt Kerkstr 83",
    "sg:city":"Leeuwarden",
    "sg:orig_category":"Bloemen En Planten",
    "sg:phone":"+31 58 215 1938",
    "sg:postcode":"8911 EB",
    "sg:province":"Friesland",
    "wof:name":"Floranova",
    "wof:placetype":"venue"
},
  "geometry": {"coordinates":[5.796958,53.203754],"type":"Point"}
}