{
  "type": "Feature",
  "properties": {
    "addr:full":"Mt Ondinawg 1 Amsterdam North Holland 1033 RE",
    "addr:housenumber":"1",
    "addr:postcode":"1033 re",
    "addr:street":"Mt Ondinawg",
    "iso:country":"NL",
    "sg:address":"Mt Ondinawg 1",
    "sg:city":"Amsterdam",
    "sg:orig_category":"Keukens",
    "sg:phone":"+31 20 493 1110",
    "sg:postcode":"1033 RE",
    "sg:province":"North Holland",
    "wof:name":"Jaap Raat Interieurbouw",
    "wof:placetype":"venue"
},
  "geometry": {"coordinates":[4.892314,52.40163],"type":"Point"}
}