{
  "type": "Feature",
  "properties": {
    "iso:country":"NL",
    "sg:address":"Kersenstr 2",
    "sg:city":"Mierlo",
    "sg:orig_category":"Accountants - Administratie- Consulenten En -Kantoren",
    "sg:phone":"+31 492 432 233",
    "sg:postcode":"5731 GW",
    "sg:province":"Noord-Brabant",
    "sg:website":"http://www.gibogroep.nl",
    "wof:name":"Gibo Groep",
    "wof:placetype":"venue"
},
  "geometry": {"coordinates":[5.623668,51.445068],"type":"Point"}
}