{
  "type": "Feature",
  "properties": {
    "iso:country":"NL",
    "sg:address":"Waardpolderh Wg 32",
    "sg:city":"Kolhorn",
    "sg:orig_category":"Vertaalbureaus",
    "sg:phone":"+31 224 533 004",
    "sg:postcode":"1767 EJ",
    "sg:province":"Noord-Holland",
    "wof:name":"Dexel, Winnie",
    "wof:placetype":"venue"
},
  "geometry": {"coordinates":[4.891574,52.798717],"type":"Point"}
}