{
  "type": "Feature",
  "properties": {
    "addr:full":"Dwarswg 20 Nederhorst D Berg California 1394 AZ",
    "addr:housenumber":"20",
    "addr:postcode":"1394 az",
    "addr:street":"Dwarswg;Nederhorst D Berg",
    "iso:country":"NL",
    "sg:address":"Dwarswg 20",
    "sg:city":"Nederhorst D Berg",
    "sg:orig_category":"Hek- En Rasterwerken",
    "sg:phone":"+31 294 257 025",
    "sg:postcode":"1394 AZ",
    "sg:province":"California",
    "sg:website":"http://www.lamtoegangstechniek.nl",
    "wof:name":"Lam, Toegangstechniek",
    "wof:placetype":"venue"
},
  "geometry": {"coordinates":[-121.624138,39.182121],"type":"Point"}
}