{
  "type": "Feature",
  "properties": {
    "addr:full":"Nijverheidsweg 1 Etten-Leur North Brabant 4879 AP",
    "addr:housenumber":"1",
    "addr:postcode":"4879 ap",
    "addr:street":"Nijverheidsweg",
    "iso:country":"NL",
    "sg:address":"Nijverheidsweg 1",
    "sg:city":"Etten-Leur",
    "sg:orig_category":"Hout Gh",
    "sg:phone":"+31 76 503 6500",
    "sg:postcode":"4879 AP",
    "sg:province":"North Brabant",
    "wof:name":"Van Ierssel Houtimport Bv",
    "wof:placetype":"venue"
},
  "geometry": {"coordinates":[4.62529,51.566765],"type":"Point"}
}