{
  "type": "Feature",
  "properties": {
    "iso:country":"NL",
    "sg:address":"Nieuwewg 44",
    "sg:city":"Dordrecht",
    "sg:orig_category":"Kasregisters",
    "sg:phone":"+31 78 631 7899",
    "sg:postcode":"3314 JS",
    "sg:province":"South Holland",
    "wof:name":"Buys Business Machines",
    "wof:placetype":"venue"
},
  "geometry": {"coordinates":[4.677086,51.800083],"type":"Point"}
}