{
  "type": "Feature",
  "properties": {
    "addr:full":"Pr Hendrikkd 8 Sneek Friesland 8601 CA",
    "addr:housenumber":"8",
    "addr:postcode":"8601 ca",
    "iso:country":"NL",
    "sg:address":"Pr Hendrikkd 8",
    "sg:city":"Sneek",
    "sg:orig_category":"Kunstbloemen En -Planten - Verhuur",
    "sg:phone":"+31 515 438 355",
    "sg:postcode":"8601 CA",
    "sg:province":"Friesland",
    "sg:website":"http://www.treetipzz.nl",
    "wof:name":"Treetipzz",
    "wof:placetype":"venue"
},
  "geometry": {"coordinates":[5.66197,53.033459],"type":"Point"}
}