{
  "type": "Feature",
  "properties": {
    "iso:country":"NL",
    "sg:address":"Alexanderstr 1",
    "sg:city":"Waalre",
    "sg:orig_category":"Video - Faciliteiten En Producties",
    "sg:phone":"+31 40 221 7058",
    "sg:postcode":"5583 BH",
    "sg:province":"North Brabant",
    "wof:name":"Jansen, Frans",
    "wof:placetype":"venue"
},
  "geometry": {"coordinates":[5.47935,51.395256],"type":"Point"}
}