{
  "type": "Feature",
  "properties": {
    "addr:full":"Leliestr 6 Roermond Limburg 6041 GZ",
    "addr:housenumber":"6",
    "addr:postcode":"6041 gz",
    "addr:street":"Leliestr",
    "iso:country":"NL",
    "sg:address":"Leliestr 6",
    "sg:city":"Roermond",
    "sg:orig_category":"Fotojournalisten Freelance",
    "sg:phone":"+31 475 330 217",
    "sg:postcode":"6041 GZ",
    "sg:province":"Limburg",
    "wof:name":"Gori, F",
    "wof:placetype":"venue"
},
  "geometry": {"coordinates":[5.989699,51.193913],"type":"Point"}
}