{
  "type": "Feature",
  "properties": {
    "iso:country":"NL",
    "sg:address":"Burgemeester Meineszlaan 63",
    "sg:city":"Rotterdam",
    "sg:orig_category":"Boekhouders",
    "sg:phone":"+31 10 477 9866",
    "sg:postcode":"3022 BC",
    "sg:province":"South Holland",
    "wof:name":"V.G. Administraties",
    "wof:placetype":"venue"
},
  "geometry": {"coordinates":[4.451744,51.918682],"type":"Point"}
}