{
  "type": "Feature",
  "properties": {
    "addr:full":"Randwg Z 1A Budel North Brabant 6021 PW",
    "addr:housenumber":"1a",
    "addr:postcode":"6021 pw",
    "iso:country":"NL",
    "sg:address":"Randwg Z 1A",
    "sg:city":"Budel",
    "sg:orig_category":"Metaalbewerking",
    "sg:phone":"+31 495 494 600",
    "sg:postcode":"6021 PW",
    "sg:province":"North Brabant",
    "sg:website":"http://www.lacom.nl",
    "wof:name":"Lacom Bv",
    "wof:placetype":"venue"
},
  "geometry": {"coordinates":[5.595976,51.259968],"type":"Point"}
}