{
  "type": "Feature",
  "properties": {
    "addr:full":"V Tuyllstr 8C Hooglanderveen Utrecht 3829 AD",
    "addr:housenumber":"8c",
    "addr:postcode":"3829 ad",
    "addr:street":"Tuyllstr",
    "iso:country":"NL",
    "sg:address":"V Tuyllstr 8C",
    "sg:city":"Hooglanderveen",
    "sg:orig_category":"Banken",
    "sg:phone":"+31 33 257 1224",
    "sg:postcode":"3829 AD",
    "sg:province":"Utrecht",
    "sg:website":"http://www.rabobank.nl",
    "wof:name":"Rabobank",
    "wof:placetype":"venue"
},
  "geometry": {"coordinates":[5.431815,52.188042],"type":"Point"}
}