{
  "type": "Feature",
  "properties": {
    "addr:full":"Fivel 82 Zwolle NL.08 8032 MV",
    "addr:housenumber":"82",
    "addr:postcode":"8032 mv",
    "addr:street":"Fivel",
    "iso:country":"NL",
    "sg:address":"Fivel 82",
    "sg:city":"Zwolle",
    "sg:orig_category":"Zonne-Energie",
    "sg:phone":"+31 38 455 1799",
    "sg:postcode":"8032 MV",
    "sg:province":"NL.08",
    "wof:name":"Sundisc Bv",
    "wof:placetype":"venue"
},
  "geometry": {"coordinates":[6.094144,52.537167],"type":"Point"}
}