{
  "type": "Feature",
  "properties": {
    "addr:full":"Pater Pirestraat 11 Diemen Noord-Holland 1111 KP",
    "addr:housenumber":"11",
    "addr:postcode":"1111 kp",
    "addr:street":"Pater Pirestraat",
    "iso:country":"NL",
    "sg:address":"Pater Pirestraat 11",
    "sg:city":"Diemen",
    "sg:orig_category":"Krantenuitgeverijen",
    "sg:phone":"+31 20 695 0222",
    "sg:postcode":"1111 KP",
    "sg:province":"Noord-Holland",
    "wof:name":"Stichting Essence",
    "wof:placetype":"venue"
},
  "geometry": {"coordinates":[4.963084,52.343002],"type":"Point"}
}