{
  "type": "Feature",
  "properties": {
    "addr:full":"Gaffelstr 31 Amsterdam Noord-Holland 1097 VW",
    "addr:housenumber":"31",
    "addr:postcode":"1097 vw",
    "addr:street":"Gaffelstr",
    "iso:country":"NL",
    "sg:address":"Gaffelstr 31",
    "sg:city":"Amsterdam",
    "sg:orig_category":"Homeopathie",
    "sg:phone":"+31 20 694 9938",
    "sg:postcode":"1097 VW",
    "sg:province":"Noord-Holland",
    "wof:name":"Annemarieke Sibbel",
    "wof:placetype":"venue"
},
  "geometry": {"coordinates":[4.945585,52.342018],"type":"Point"}
}