{
  "type": "Feature",
  "properties": {
    "addr:full":"V Faukenbergestr 76 Voorburg South Holland 2274 SB",
    "addr:housenumber":"76",
    "addr:postcode":"2274 sb",
    "iso:country":"NL",
    "sg:address":"V Faukenbergestr 76",
    "sg:city":"Voorburg",
    "sg:orig_category":"Fotografie Reclame En Mode",
    "sg:phone":"+31 6 15164550",
    "sg:postcode":"2274 SB",
    "sg:province":"South Holland",
    "sg:website":"http://www.pablodelfos.com",
    "wof:name":"Delfos, Pablo",
    "wof:placetype":"venue"
},
  "geometry": {"coordinates":[4.347486,52.076332],"type":"Point"}
}