{
  "type": "Feature",
  "properties": {
    "iso:country":"NL",
    "sg:address":"Douwes Dekkerlaan 3",
    "sg:city":"Papendrecht",
    "sg:classifiers":[
        {
            "category":"Education",
            "subcategory":"Preschool",
            "type":"Public Place"
        }
    ],
    "sg:phone":"+31 78 615 2256",
    "sg:postcode":"3351 CH",
    "sg:province":"Zuid-Holland",
    "sg:tags":[
        "kleuteronderwijs",
        "basis-"
    ],
    "wof:name":"Koningin Beatrixschool",
    "wof:placetype":"venue"
},
  "geometry": {"coordinates":[4.680073,51.833855],"type":"Point"}
}