{
  "type": "Feature",
  "properties": {
    "addr:full":"Brouwersgracht 16 'S Gravenhage South Holland 2512 ER",
    "addr:housenumber":"16",
    "addr:postcode":"2512 er",
    "addr:street":"Brouwersgracht;' S Gravenhage",
    "iso:country":"NL",
    "sg:address":"Brouwersgracht 16",
    "sg:city":"'S Gravenhage",
    "sg:orig_category":"Loodgieterswerk, Verwarming And Sanitaire Installaties",
    "sg:phone":"+31 70 363 7606",
    "sg:postcode":"2512 ER",
    "sg:province":"South Holland",
    "wof:name":"Aerdenberg Installatietechniek",
    "wof:placetype":"venue"
},
  "geometry": {"coordinates":[4.306067,52.073322],"type":"Point"}
}