{
  "type": "Feature",
  "properties": {
    "addr:full":"Tarweln 83 Eindhoven North Brabant 5632 KD",
    "addr:housenumber":"83",
    "addr:postcode":"5632 kd",
    "addr:street":"Tarweln",
    "iso:country":"NL",
    "sg:address":"Tarweln 83",
    "sg:city":"Eindhoven",
    "sg:classifiers":[
        {
            "category":"Personal",
            "subcategory":"Nail Salon",
            "type":"Services"
        }
    ],
    "sg:phone":"+31 40 241 6821",
    "sg:postcode":"5632 KD",
    "sg:province":"North Brabant",
    "sg:tags":[
        "pedicure"
    ],
    "wof:name":"Bressers-Rutten, I M",
    "wof:placetype":"venue"
},
  "geometry": {"coordinates":[5.49848,51.477058],"type":"Point"}
}