{
  "type": "Feature",
  "properties": {
    "iso:country":"NL",
    "sg:address":"De Waard 129",
    "sg:city":"Heiloo",
    "sg:orig_category":"Boeken En Tijdschriften",
    "sg:phone":"+31 72 532 3933",
    "sg:postcode":"1851 RD",
    "sg:province":"Noord-Holland",
    "wof:name":"Munsterman, Media Expresse",
    "wof:placetype":"venue"
},
  "geometry": {"coordinates":[4.713814,52.592297],"type":"Point"}
}