{
  "type": "Feature",
  "properties": {
    "iso:country":"NL",
    "sg:address":"Bovenwg 46B",
    "sg:city":"Doornspijk",
    "sg:orig_category":"Hoefsmederijen",
    "sg:phone":"+31 525 661 774",
    "sg:postcode":"8085 SJ",
    "sg:province":"Gelderland",
    "wof:name":"Endendijk, B J",
    "wof:placetype":"venue"
},
  "geometry": {"coordinates":[5.847603,52.407364],"type":"Point"}
}