{
  "type": "Feature",
  "properties": {
    "addr:full":"Trompstr 63 Alkmaar North Holland 1813 SM",
    "addr:housenumber":"63",
    "addr:postcode":"1813 sm",
    "addr:street":"Trompstr",
    "iso:country":"NL",
    "sg:address":"Trompstr 63",
    "sg:city":"Alkmaar",
    "sg:orig_category":"Elektronica - Ontwikkeling En Groothandel",
    "sg:phone":"+31 72 540 2323",
    "sg:postcode":"1813 SM",
    "sg:province":"North Holland",
    "wof:name":"Heesbeen",
    "wof:placetype":"venue"
},
  "geometry": {"coordinates":[4.76274,52.622425],"type":"Point"}
}