{
  "type": "Feature",
  "properties": {
    "addr:full":"Kraaiersln 26 Noordwykerhout Zuid-Holland 2211 ZE",
    "addr:housenumber":"26",
    "addr:postcode":"2211 ze",
    "addr:street":"Kraaiersln",
    "iso:country":"NL",
    "sg:address":"Kraaiersln 26",
    "sg:city":"Noordwykerhout",
    "sg:orig_category":"Bloembollen - Groothandel",
    "sg:phone":"+31 252 373 218",
    "sg:postcode":"2211 ZE",
    "sg:province":"Zuid-Holland",
    "wof:name":"Soeren, R En R Van",
    "wof:placetype":"venue"
},
  "geometry": {"coordinates":[4.491189,52.26347],"type":"Point"}
}