{
  "type": "Feature",
  "properties": {
    "addr:full":"Geerstr 105 Heerlen Limburg 6411 NP",
    "addr:housenumber":"105",
    "addr:postcode":"6411 np",
    "iso:country":"NL",
    "sg:address":"Geerstr 105",
    "sg:city":"Heerlen",
    "sg:orig_category":"Webdesign Bureaus",
    "sg:phone":"+31 45 560 0222",
    "sg:postcode":"6411 NP",
    "sg:province":"Limburg",
    "sg:website":"http://www.pna-activemedia.nl",
    "wof:name":"Pna Activemedia Bv",
    "wof:placetype":"venue"
},
  "geometry": {"coordinates":[5.9729590416,50.8890342712],"type":"Point"}
}