{
  "type": "Feature",
  "properties": {
    "addr:full":"Kp Laan 22 Meppel Provincie Drenthe 7943 CV",
    "addr:housenumber":"22",
    "addr:postcode":"7943 cv",
    "addr:street":"Laan;Provincie Drenthe",
    "iso:country":"NL",
    "sg:address":"Kp Laan 22",
    "sg:city":"Meppel",
    "sg:classifiers":[
        {
            "category":"Education",
            "subcategory":"Preschool",
            "type":"Public Place"
        }
    ],
    "sg:phone":"+31 522 254 126",
    "sg:postcode":"7943 CV",
    "sg:province":"Provincie Drenthe",
    "sg:tags":[
        "kleuteronderwijs",
        "basis-"
    ],
    "wof:name":"Openbare Basisschool Oosterboerschool",
    "wof:placetype":"venue"
},
  "geometry": {"coordinates":[6.216659,52.695248],"type":"Point"}
}