{
  "type": "Feature",
  "properties": {
    "addr:full":"Postbus 18 Heerhugowaard Noord-Holland 1700 AA",
    "addr:housenumber":"18",
    "addr:postcode":"1700 aa",
    "addr:street":"Postbus",
    "iso:country":"NL",
    "sg:address":"Postbus 18",
    "sg:city":"Heerhugowaard",
    "sg:orig_category":"Administratie- En Boekhoudkantoren",
    "sg:phone":"+31 226 456 040",
    "sg:postcode":"1700 AA",
    "sg:province":"Noord-Holland",
    "sg:website":"http://www.cdh.nu",
    "wof:name":"Cdh U A",
    "wof:placetype":"venue"
},
  "geometry": {"coordinates":[4.827522,52.665195],"type":"Point"}
}