{
  "type": "Feature",
  "properties": {
    "addr:full":"Veerdk 108 Wormer Noord-Holland 1531 MB",
    "addr:housenumber":"108",
    "addr:postcode":"1531 mb",
    "addr:street":"Wormer",
    "iso:country":"NL",
    "sg:address":"Veerdk 108",
    "sg:city":"Wormer",
    "sg:orig_category":"Adviesbureaus Bouwkunde",
    "sg:phone":"+31 6 55714984",
    "sg:postcode":"1531 MB",
    "sg:province":"Noord-Holland",
    "wof:name":"Marcel Van Tol",
    "wof:placetype":"venue"
},
  "geometry": {"coordinates":[4.795425,52.500713],"type":"Point"}
}