{
  "type": "Feature",
  "properties": {
    "addr:full":"Tramstr 7 Hoek Zeeland 4542 BH",
    "addr:housenumber":"7",
    "addr:postcode":"4542 bh",
    "addr:street":"Tramstr",
    "iso:country":"NL",
    "sg:address":"Tramstr 7",
    "sg:city":"Hoek",
    "sg:orig_category":"Fietsen En Bromfietsen Onderdelen - Fabr. En Grooth",
    "sg:phone":"+31 115 441 212",
    "sg:postcode":"4542 BH",
    "sg:province":"Zeeland",
    "wof:name":"Ddzn",
    "wof:placetype":"venue"
},
  "geometry": {"coordinates":[3.780998,51.310001],"type":"Point"}
}