{
  "type": "Feature",
  "properties": {
    "addr:full":"Noorderstr 151A Sappemeer Groningen 9611 AD",
    "addr:housenumber":"151a",
    "addr:postcode":"9611 ad",
    "iso:country":"NL",
    "sg:address":"Noorderstr 151A",
    "sg:city":"Sappemeer",
    "sg:orig_category":"Projectontwikkeling",
    "sg:phone":"+31 598 857 010",
    "sg:postcode":"9611 AD",
    "sg:province":"Groningen",
    "wof:name":"Visser Project",
    "wof:placetype":"venue"
},
  "geometry": {"coordinates":[6.791568,53.164371],"type":"Point"}
}