{
  "type": "Feature",
  "properties": {
    "addr:full":"Nieuwstr 6 Zaltbommel Gelderland 5301 EW",
    "addr:housenumber":"6",
    "addr:postcode":"5301 ew",
    "addr:street":"Nieuwstr;Gelderland",
    "iso:country":"NL",
    "sg:address":"Nieuwstr 6",
    "sg:city":"Zaltbommel",
    "sg:orig_category":"Verenigingen En Stichtingen",
    "sg:phone":"+31 418 513 762",
    "sg:postcode":"5301 EW",
    "sg:province":"Gelderland",
    "wof:name":"Orion",
    "wof:placetype":"venue"
},
  "geometry": {"coordinates":[5.250601,51.811462],"type":"Point"}
}