{
  "type": "Feature",
  "properties": {
    "iso:country":"NL",
    "sg:address":"Lg Hof 4",
    "sg:city":"Kerkdriel",
    "sg:orig_category":"Woninginrichting",
    "sg:phone":"+31 418 633 330",
    "sg:postcode":"5331 CV",
    "sg:province":"Gelderland",
    "wof:name":"Graauw, De",
    "wof:placetype":"venue"
},
  "geometry": {"coordinates":[5.336689949,51.7712440491],"type":"Point"}
}