{
  "type": "Feature",
  "properties": {
    "addr:full":"Boekhorststr 29 S Gravenhage Zuid-Holland 2512 CL",
    "addr:housenumber":"29;gravenhage",
    "addr:postcode":"2512",
    "addr:street":"Boekhorststr;S",
    "iso:country":"NL",
    "sg:address":"Boekhorststr 29",
    "sg:city":"S Gravenhage",
    "sg:orig_category":"Behangselpapier En Wandbekleding",
    "sg:phone":"+31 70 346 3209",
    "sg:postcode":"2512 CL",
    "sg:province":"Zuid-Holland",
    "wof:name":"Stahlecker, Behangwarenhuis",
    "wof:placetype":"venue"
},
  "geometry": {"coordinates":[4.30618,52.073212],"type":"Point"}
}