{
  "type": "Feature",
  "properties": {
    "addr:full":"Utrechtsestr 43 Ijsselstein Utrecht 3401 CT",
    "addr:housenumber":"43",
    "addr:postcode":"3401 ct",
    "addr:street":"Utrechtsestr",
    "iso:country":"NL",
    "sg:address":"Utrechtsestr 43",
    "sg:city":"Ijsselstein",
    "sg:classifiers":[
        {
            "category":"Shopping",
            "subcategory":"Adult",
            "type":"Retail Goods"
        }
    ],
    "sg:phone":"+31 30 688 6606",
    "sg:postcode":"3401 CT",
    "sg:province":"Utrecht",
    "sg:tags":[
        "lingerie",
        "en",
        "tricotage"
    ],
    "wof:name":"Elina",
    "wof:placetype":"venue"
},
  "geometry": {"coordinates":[5.044854,52.020157],"type":"Point"}
}