{
  "type": "Feature",
  "properties": {
    "addr:full":"Twentepoort W 7 Almelo NL.08 7609 RD",
    "addr:housenumber":"7;nl.08",
    "addr:postcode":"7609 rd",
    "addr:street":"Twentepoort W",
    "iso:country":"NL",
    "sg:address":"Twentepoort W 7",
    "sg:city":"Almelo",
    "sg:orig_category":"Keuken- Groot-Installaties",
    "sg:phone":"+31 546 548 048",
    "sg:postcode":"7609 RD",
    "sg:province":"NL.08",
    "wof:name":"Electro Calorique Holl Bv",
    "wof:placetype":"venue"
},
  "geometry": {"coordinates":[6.649359,52.328941],"type":"Point"}
}