{
  "type": "Feature",
  "properties": {
    "addr:full":"Boerhaavepln 4 Amsterdam Noord-Holland 1091 AS",
    "addr:housenumber":"4",
    "addr:postcode":"1091 as",
    "addr:street":"Boerhaavepln",
    "iso:country":"NL",
    "sg:address":"Boerhaavepln 4",
    "sg:city":"Amsterdam",
    "sg:orig_category":"Verenigingen En Stichtingen",
    "sg:phone":"+31 20 665 4171",
    "sg:postcode":"1091 AS",
    "sg:province":"Noord-Holland",
    "wof:name":"Cadre, Sticht",
    "wof:placetype":"venue"
},
  "geometry": {"coordinates":[4.91224,52.359467],"type":"Point"}
}