{
  "type": "Feature",
  "properties": {
    "addr:full":"Fortuinstraat 16 Hardenberg Overijssel 7772 BM",
    "addr:housenumber":"16",
    "addr:postcode":"7772 bm",
    "addr:street":"Fortuinstraat",
    "iso:country":"NL",
    "sg:address":"Fortuinstraat 16",
    "sg:city":"Hardenberg",
    "sg:orig_category":"Herenmodezaken",
    "sg:phone":"+31 523 267 668",
    "sg:postcode":"7772 BM",
    "sg:province":"Overijssel",
    "wof:name":"Klepperman Mannenmode",
    "wof:placetype":"venue"
},
  "geometry": {"coordinates":[6.618952,52.574772],"type":"Point"}
}