{
  "type": "Feature",
  "properties": {
    "iso:country":"NL",
    "sg:address":"Fagelstr 79",
    "sg:city":"Amsterdam",
    "sg:orig_category":"Fotojournalisten Freelance",
    "sg:phone":"+31 20 682 8534",
    "sg:postcode":"1052 GA",
    "sg:province":"Noord-Holland",
    "wof:name":"Oegema, Jan Erik",
    "wof:placetype":"venue"
},
  "geometry": {"coordinates":[-94.58503,38.350479],"type":"Point"}
}