{
  "type": "Feature",
  "properties": {
    "iso:country":"NL",
    "sg:address":"Burgtstr 1",
    "sg:city":"Wageningen",
    "sg:orig_category":"Verenigingen En Stichtingen",
    "sg:phone":"+31 317 422 835",
    "sg:postcode":"6701 DA",
    "sg:province":"Gelderland",
    "wof:name":"Homogroep Wageningen",
    "wof:placetype":"venue"
},
  "geometry": {"coordinates":[5.664132,51.964863],"type":"Point"}
}