{
  "type": "Feature",
  "properties": {
    "addr:full":"Treubplein 19 Voorschoten Zuid-Holland 2251 CV",
    "addr:housenumber":"19",
    "addr:postcode":"2251 cv",
    "addr:street":"Treubplein",
    "iso:country":"NL",
    "sg:address":"Treubplein 19",
    "sg:city":"Voorschoten",
    "sg:orig_category":"Verlichting And Huishoudartikelen",
    "sg:phone":"+31 71 561 7179",
    "sg:postcode":"2251 CV",
    "sg:province":"Zuid-Holland",
    "wof:name":"Hage Woninginrichters Bv",
    "wof:placetype":"venue"
},
  "geometry": {"coordinates":[4.448187,52.125706],"type":"Point"}
}