{
  "type": "Feature",
  "properties": {
    "addr:full":"Hoofdweg 215 Midwolda Groningen 9681 AE",
    "addr:housenumber":"215",
    "addr:postcode":"9681 ae",
    "addr:street":"Hoofdweg",
    "iso:country":"NL",
    "sg:address":"Hoofdweg 215",
    "sg:city":"Midwolda",
    "sg:orig_category":"Banken And Kredietinstellingen",
    "sg:phone":"+31 597 551 349",
    "sg:postcode":"9681 AE",
    "sg:province":"Groningen",
    "wof:name":"Rabobank",
    "wof:placetype":"venue"
},
  "geometry": {"coordinates":[7.020824,53.19648],"type":"Point"}
}