{
  "type": "Feature",
  "properties": {
    "addr:full":"Zuiddijk 209 Zaandam North Holland 1501 CJ",
    "addr:housenumber":"209",
    "addr:postcode":"1501 cj",
    "addr:street":"Zuiddijk",
    "iso:country":"NL",
    "sg:address":"Zuiddijk 209",
    "sg:city":"Zaandam",
    "sg:orig_category":"Artiesten",
    "sg:phone":"+31 75 631 0169",
    "sg:postcode":"1501 CJ",
    "sg:province":"North Holland",
    "wof:name":"Moritz Ebinger",
    "wof:placetype":"venue"
},
  "geometry": {"coordinates":[4.832946,52.434612],"type":"Point"}
}