{
  "type": "Feature",
  "properties": {
    "addr:full":"Nieuwe Binnenweg 252B Rotterdam Zuid-Holland 3021 GP",
    "addr:housenumber":"252b",
    "addr:postcode":"3021 gp",
    "addr:street":"Nieuwe Binnenweg",
    "iso:country":"NL",
    "sg:address":"Nieuwe Binnenweg 252B",
    "sg:city":"Rotterdam",
    "sg:classifiers":[
        {
            "category":"Communications",
            "subcategory":"Television Station",
            "type":"Services"
        }
    ],
    "sg:phone":"+31 10 477 6250",
    "sg:postcode":"3021 GP",
    "sg:province":"Zuid-Holland",
    "sg:tags":[
        "video",
        "audio",
        "verhuur"
    ],
    "wof:name":"Videotheek Sanae",
    "wof:placetype":"venue"
},
  "geometry": {"coordinates":[4.460665,51.913151],"type":"Point"}
}