{
  "type": "Feature",
  "properties": {
    "iso:country":"NL",
    "sg:address":"Valckeslotln 200",
    "sg:city":"Goes",
    "sg:orig_category":"Verenigingen En Stichtingen",
    "sg:phone":"+31 113 270 330",
    "sg:postcode":"4461 SE",
    "sg:province":"Zeeland",
    "wof:name":"Goese Polder, Sticht Jongerenwerk",
    "wof:placetype":"venue"
},
  "geometry": {"coordinates":[-83.914169,39.768833],"type":"Point"}
}