{
  "type": "Feature",
  "properties": {
    "addr:full":"Van Noortstraat 51 Nijkerkerveen Gelderland 3864 ET",
    "addr:housenumber":"51",
    "addr:postcode":"3864 et",
    "addr:street":"Van Noortstraat;Gelderland",
    "iso:country":"NL",
    "sg:address":"Van Noortstraat 51",
    "sg:city":"Nijkerkerveen",
    "sg:orig_category":"Kappers",
    "sg:phone":"+31 33 253 7271",
    "sg:postcode":"3864 ET",
    "sg:province":"Gelderland",
    "wof:name":"Anja'S Haarstudio",
    "wof:placetype":"venue"
},
  "geometry": {"coordinates":[5.4678010941,52.1954841614],"type":"Point"}
}