{
  "type": "Feature",
  "properties": {
    "addr:full":"Heuvelstr 43/17 Tilburg Noord-Brabant 5038 AB",
    "addr:housenumber":"43 / 17",
    "addr:postcode":"5038 ab",
    "addr:street":"Heuvelstr",
    "iso:country":"NL",
    "sg:address":"Heuvelstr 43/17",
    "sg:city":"Tilburg",
    "sg:orig_category":"Biljartzalen",
    "sg:phone":"+31 13 535 1848",
    "sg:postcode":"5038 AB",
    "sg:province":"Noord-Brabant",
    "sg:website":"http://www.bogeys.nl",
    "wof:name":"Bogey'S Pool En Diner",
    "wof:placetype":"venue"
},
  "geometry": {"coordinates":[5.087769,51.556747],"type":"Point"}
}