{
  "type": "Feature",
  "properties": {
    "addr:full":"Zuidlarenstraat 52 'S Gravenhage South Holland 2545 VX",
    "addr:housenumber":"52",
    "addr:postcode":"2545 vx",
    "addr:street":"Zuidlarenstraat;' S Gravenhage",
    "iso:country":"NL",
    "sg:address":"Zuidlarenstraat 52",
    "sg:city":"'S Gravenhage",
    "sg:orig_category":"Werving And Selectie Van Tijdelijk Personeel And Uitzendkantoren",
    "sg:phone":"+31 70 366 9327",
    "sg:postcode":"2545 VX",
    "sg:province":"South Holland",
    "wof:name":"Connect",
    "wof:placetype":"venue"
},
  "geometry": {"coordinates":[4.2670040131,52.0501022339],"type":"Point"}
}