{
  "type": "Feature",
  "properties": {
    "addr:full":"Heilige Stoel 5707 Wijchen Gelderland 6601 TV",
    "addr:housenumber":"5707",
    "addr:postcode":"6601 tv",
    "addr:street":"Heilige Stoel;Gelderland",
    "iso:country":"NL",
    "sg:address":"Heilige Stoel 5707",
    "sg:city":"Wijchen",
    "sg:orig_category":"Loopbaanbegeleiding",
    "sg:phone":"+31 24 329 4810",
    "sg:postcode":"6601 TV",
    "sg:province":"Gelderland",
    "sg:website":"http://www.sophiatraining.nl",
    "wof:name":"Sophia",
    "wof:placetype":"venue"
},
  "geometry": {"coordinates":[5.716667,51.816769],"type":"Point"}
}