{
  "type": "Feature",
  "properties": {
    "addr:full":"2E Brandenburg Wg 19 Bilthoven Utrecht 3721 CG",
    "addr:housenumber":"19",
    "addr:postcode":"3721 cg",
    "addr:street":"2E;Wg",
    "iso:country":"NL",
    "sg:address":"2E Brandenburg Wg 19",
    "sg:city":"Bilthoven",
    "sg:orig_category":"Mobiele- En Autotelefoons",
    "sg:phone":"+31 30 228 0813",
    "sg:postcode":"3721 CG",
    "sg:province":"Utrecht",
    "sg:website":"http://www.vliek.nl",
    "wof:name":"Vliek",
    "wof:placetype":"venue"
},
  "geometry": {"coordinates":[5.19509,52.125645],"type":"Point"}
}