{
  "type": "Feature",
  "properties": {
    "addr:full":"Hoofdwg 147 Rotterdam South Holland 3067 GE",
    "addr:housenumber":"147",
    "addr:postcode":"3067",
    "iso:country":"NL",
    "sg:address":"Hoofdwg 147",
    "sg:city":"Rotterdam",
    "sg:orig_category":"Onderhoudswerken",
    "sg:phone":"+31 10 421 4178",
    "sg:postcode":"3067 GE",
    "sg:province":"South Holland",
    "wof:name":"Uijl, P",
    "wof:placetype":"venue"
},
  "geometry": {"coordinates":[4.539895,51.947262],"type":"Point"}
}