{
  "type": "Feature",
  "properties": {
    "addr:full":"Mina Krusemanstraat 20 Schiedam Zuid-Holland 3123 SJ",
    "addr:housenumber":"20",
    "addr:postcode":"3123",
    "addr:street":"Mina Krusemanstraat",
    "iso:country":"NL",
    "sg:address":"Mina Krusemanstraat 20",
    "sg:city":"Schiedam",
    "sg:orig_category":"Schilderwerk",
    "sg:phone":"+31 10 247 0699",
    "sg:postcode":"3123 SJ",
    "sg:province":"Zuid-Holland",
    "wof:name":"R. Konemann Schilders- En Interieursafw.",
    "wof:placetype":"venue"
},
  "geometry": {"coordinates":[4.370774,51.947159],"type":"Point"}
}