{
  "type": "Feature",
  "properties": {
    "addr:full":"Barend Ubbinkweg 2 Doesburg Gelderland 6981 EC",
    "addr:housenumber":"2",
    "addr:postcode":"6981 ec",
    "addr:street":"Barend Ubbinkweg;Gelderland",
    "iso:country":"NL",
    "sg:address":"Barend Ubbinkweg 2",
    "sg:city":"Doesburg",
    "sg:orig_category":"Metaalbekleding And -Behandeling",
    "sg:phone":"+31 313 476 181",
    "sg:postcode":"6981 EC",
    "sg:province":"Gelderland",
    "wof:name":"Doesburg Components Bv",
    "wof:placetype":"venue"
},
  "geometry": {"coordinates":[6.132202,52.00909],"type":"Point"}
}