{
  "type": "Feature",
  "properties": {
    "addr:full":"Kruisstraat 6 Hoorn Nh Noord-Holland 1621 EJ",
    "addr:housenumber":"6",
    "addr:postcode":"1621 ej",
    "addr:street":"Kruisstraat",
    "iso:country":"NL",
    "sg:address":"Kruisstraat 6",
    "sg:city":"Hoorn Nh",
    "sg:orig_category":"Kappers",
    "sg:phone":"+31 229 215 429",
    "sg:postcode":"1621 EJ",
    "sg:province":"Noord-Holland",
    "wof:name":"Salon Paul En Thea",
    "wof:placetype":"venue"
},
  "geometry": {"coordinates":[5.058866,52.64061],"type":"Point"}
}