{
  "type": "Feature",
  "properties": {
    "addr:full":"A. Van Bergenstraat 77 Breda North Brabant 4811 SN",
    "addr:housenumber":"77",
    "addr:postcode":"4811 sn",
    "addr:street":"A. Van Bergenstraat",
    "iso:country":"NL",
    "sg:address":"A. Van Bergenstraat 77",
    "sg:city":"Breda",
    "sg:orig_category":"Fotostudio'S And Fotografen",
    "sg:phone":"+31 76 515 0755",
    "sg:postcode":"4811 SN",
    "sg:province":"North Brabant",
    "wof:name":"Rien Van Rijthoven",
    "wof:placetype":"venue"
},
  "geometry": {"coordinates":[4.771685,51.591351],"type":"Point"}
}