{
  "type": "Feature",
  "properties": {
    "addr:full":"Ouvertureweg 106 Alphen A/D Rijn Zuid-Holland 2402 DZ",
    "addr:housenumber":"106;2402",
    "addr:postcode":"dz",
    "addr:street":"Ouvertureweg",
    "iso:country":"NL",
    "sg:address":"Ouvertureweg 106",
    "sg:city":"Alphen A/D Rijn",
    "sg:orig_category":"Wegen And Sportterreinen",
    "sg:phone":"+31 172 430 396",
    "sg:postcode":"2402 DZ",
    "sg:province":"Zuid-Holland",
    "wof:name":"Oki",
    "wof:placetype":"venue"
},
  "geometry": {"coordinates":[4.6618218422,52.1491012573],"type":"Point"}
}