{
  "type": "Feature",
  "properties": {
    "addr:full":"Stoepemaheerd 42A Groningen Groningen 9737 TM",
    "addr:housenumber":"42a",
    "addr:postcode":"9737 tm",
    "addr:street":"Stoepemaheerd",
    "iso:country":"NL",
    "sg:address":"Stoepemaheerd 42A",
    "sg:city":"Groningen",
    "sg:orig_category":"Fietsen En Bromfietsen",
    "sg:phone":"+31 50 542 1242",
    "sg:postcode":"9737 TM",
    "sg:province":"Groningen",
    "wof:name":"Kooistra, W H",
    "wof:placetype":"venue"
},
  "geometry": {"coordinates":[6.587901,53.245903],"type":"Point"}
}