{
  "type": "Feature",
  "properties": {
    "addr:full":"Tradeboulevard 4 Zevenbergen Noord-Brabant 4761 RL",
    "addr:housenumber":"4",
    "addr:postcode":"4761 rl",
    "addr:street":"Tradeboulevard",
    "iso:country":"NL",
    "sg:address":"Tradeboulevard 4",
    "sg:city":"Zevenbergen",
    "sg:orig_category":"Goederenvervoer Over De Weg",
    "sg:phone":"+31 168 413 000",
    "sg:postcode":"4761 RL",
    "sg:province":"Noord-Brabant",
    "wof:name":"Furness Logistics Bv",
    "wof:placetype":"venue"
},
  "geometry": {"coordinates":[4.610105,51.644798],"type":"Point"}
}