{
  "type": "Feature",
  "properties": {
    "iso:country":"NL",
    "sg:address":"Scheepvaartweg 23",
    "sg:city":"Roermond",
    "sg:orig_category":"Kantoor- And Schoolbenodigdheden Gh",
    "sg:phone":"+31 475 315 252",
    "sg:postcode":"6041 TE",
    "sg:province":"Limburg",
    "wof:name":"Holbox Golfkarton Bv",
    "wof:placetype":"venue"
},
  "geometry": {"coordinates":[5.9906902313,51.2017402649],"type":"Point"}
}