{
  "type": "Feature",
  "properties": {
    "addr:full":"Zandwg 73 Heerlen Limburg 6417 AS",
    "addr:housenumber":"73",
    "addr:postcode":"6417 as",
    "addr:street":"Zandwg",
    "iso:country":"NL",
    "sg:address":"Zandwg 73",
    "sg:city":"Heerlen",
    "sg:orig_category":"Evenementenverzorging",
    "sg:phone":"+31 45 541 5980",
    "sg:postcode":"6417 AS",
    "sg:province":"Limburg",
    "sg:website":"http://www.d-events.nl",
    "wof:name":"D'Events",
    "wof:placetype":"venue"
},
  "geometry": {"coordinates":[5.98098,50.885506],"type":"Point"}
}