{
  "type": "Feature",
  "properties": {
    "addr:full":"Kapelstraat 3-4 Bussum Noord-Holland 1404 HT",
    "addr:housenumber":"3-4",
    "addr:postcode":"1404 ht",
    "addr:street":"Kapelstraat",
    "iso:country":"NL",
    "sg:address":"Kapelstraat 3-4",
    "sg:city":"Bussum",
    "sg:orig_category":"Glaszetten",
    "sg:phone":"+31 35 693 9393",
    "sg:postcode":"1404 HT",
    "sg:province":"Noord-Holland",
    "wof:name":"Eerste Bussumse Glashandel",
    "wof:placetype":"venue"
},
  "geometry": {"coordinates":[5.16471,52.274948],"type":"Point"}
}