{
  "type": "Feature",
  "properties": {
    "addr:full":"Spaanseweg 4 Ouddorp Zh Zuid-Holland 3253 XJ",
    "addr:housenumber":"4",
    "addr:postcode":"3253 xj",
    "addr:street":"Spaanseweg",
    "iso:country":"NL",
    "sg:address":"Spaanseweg 4",
    "sg:city":"Ouddorp Zh",
    "sg:orig_category":"Tandartsen",
    "sg:phone":"+31 187 681 660",
    "sg:postcode":"3253 XJ",
    "sg:province":"Zuid-Holland",
    "wof:name":"J.H. V.D. Pol",
    "wof:placetype":"venue"
},
  "geometry": {"coordinates":[3.93653,51.806908],"type":"Point"}
}