{
  "type": "Feature",
  "properties": {
    "addr:full":"Roosdomswg 12 Markelo Overijssel 7475 AK",
    "addr:housenumber":"12",
    "addr:postcode":"7475 ak",
    "addr:street":"Roosdomswg",
    "iso:country":"NL",
    "sg:address":"Roosdomswg 12",
    "sg:city":"Markelo",
    "sg:orig_category":"Adviesbureaus Werktuigbouwkunde",
    "sg:phone":"+31 547 364 170",
    "sg:postcode":"7475 AK",
    "sg:province":"Overijssel",
    "wof:name":"Caddy",
    "wof:placetype":"venue"
},
  "geometry": {"coordinates":[6.49561,52.231819],"type":"Point"}
}