{
  "type": "Feature",
  "properties": {
    "iso:country":"NL",
    "sg:address":"Napoleonsweg 128",
    "sg:city":"Nunhem",
    "sg:orig_category":"Chemische Producten Gh",
    "sg:phone":"+31 475 593 565",
    "sg:postcode":"6083 AB",
    "sg:province":"Limburg",
    "wof:name":"P. Pustjens",
    "wof:placetype":"venue"
},
  "geometry": {"coordinates":[5.967479,51.240433],"type":"Point"}
}