{
  "type": "Feature",
  "properties": {
    "iso:country":"NL",
    "sg:address":"Zandstr 59",
    "sg:city":"Culemborg",
    "sg:classifiers":[
        {
            "category":"Professional",
            "subcategory":"Accounting & Tax Preparation",
            "type":"Services"
        }
    ],
    "sg:phone":"+31 345 517 058",
    "sg:postcode":"4101 ED",
    "sg:province":"Gelderland",
    "sg:tags":[
        "accountant",
        "en",
        "-kantoren",
        "register-"
    ],
    "wof:name":"Fsv",
    "wof:placetype":"venue"
},
  "geometry": {"coordinates":[5.227825,51.954121],"type":"Point"}
}