{
  "type": "Feature",
  "properties": {
    "addr:full":"Tweede Van Der Helststr 77 Amsterdam North Holland 1073 AM",
    "addr:housenumber":"77",
    "addr:postcode":"1073",
    "addr:street":"Tweede Van Der Helststr",
    "iso:country":"NL",
    "sg:address":"Tweede Van Der Helststr 77",
    "sg:city":"Amsterdam",
    "sg:orig_category":"Boekhouders",
    "sg:phone":"+31 20 673 2596",
    "sg:postcode":"1073 AM",
    "sg:province":"North Holland",
    "wof:name":"E.H. Mellouk",
    "wof:placetype":"venue"
},
  "geometry": {"coordinates":[4.895047,52.349186],"type":"Point"}
}