{
  "type": "Feature",
  "properties": {
    "iso:country":"NL",
    "sg:address":"Hazeweg 3",
    "sg:city":"Nieuwveen",
    "sg:classifiers":[
        {
            "category":"Education",
            "subcategory":"Preschool",
            "type":"Public Place"
        }
    ],
    "sg:phone":"+31 172 538 854",
    "sg:postcode":"2441 AD",
    "sg:province":"South Holland",
    "sg:tags":[
        "kleuteronderwijs",
        "basis-"
    ],
    "wof:name":"Katholieke Basisschool Sint Nicolaas",
    "wof:placetype":"venue"
},
  "geometry": {"coordinates":[4.752939,52.194721],"type":"Point"}
}