{
  "type": "Feature",
  "properties": {
    "addr:full":"Boterstr 2B Werkendam Noord-Brabant 4251 CC",
    "addr:housenumber":"2b",
    "addr:postcode":"4251 cc",
    "addr:street":"Boterstr",
    "iso:country":"NL",
    "sg:address":"Boterstr 2B",
    "sg:city":"Werkendam",
    "sg:orig_category":"Logopedisten",
    "sg:phone":"+31 183 505 770",
    "sg:postcode":"4251 CC",
    "sg:province":"Noord-Brabant",
    "wof:name":"Verschuren",
    "wof:placetype":"venue"
},
  "geometry": {"coordinates":[4.892807,51.814316],"type":"Point"}
}