{
  "type": "Feature",
  "properties": {
    "addr:full":"Grote N 60 Hoorn Nh Noord-Holland 1621 KK",
    "addr:housenumber":"60",
    "addr:postcode":"1621 kk",
    "addr:street":"Grote N",
    "iso:country":"NL",
    "sg:address":"Grote N 60",
    "sg:city":"Hoorn Nh",
    "sg:orig_category":"Sportschoenen - Winkels",
    "sg:phone":"+31 229 212 089",
    "sg:postcode":"1621 KK",
    "sg:province":"Noord-Holland",
    "sg:website":"http://www.footlocker.com",
    "wof:name":"Foot Locker Bv",
    "wof:placetype":"venue"
},
  "geometry": {"coordinates":[5.057148,52.640858],"type":"Point"}
}