{
  "type": "Feature",
  "properties": {
    "addr:full":"Ecuplein 51 Amsterdam Noord-Holland 1060 RN",
    "addr:housenumber":"51",
    "addr:postcode":"1060 rn",
    "addr:street":"Ecuplein",
    "iso:country":"NL",
    "sg:address":"Ecuplein 51",
    "sg:city":"Amsterdam",
    "sg:orig_category":"Adviesbureaus Bouwkosten",
    "sg:phone":"+31 20 610 9881",
    "sg:postcode":"1060 RN",
    "sg:province":"Noord-Holland",
    "wof:name":"Snh",
    "wof:placetype":"venue"
},
  "geometry": {"coordinates":[4.785198,52.34853],"type":"Point"}
}