{
  "type": "Feature",
  "properties": {
    "addr:full":"Schutwant 52 Hoogvliet Rt Zuid-Holland 3192 JS",
    "addr:housenumber":"52",
    "addr:postcode":"rt;3192 js",
    "addr:street":"Schutwant",
    "iso:country":"NL",
    "sg:address":"Schutwant 52",
    "sg:city":"Hoogvliet Rt",
    "sg:orig_category":"Grafisch Ontwerpers",
    "sg:phone":"+31 10 295 9108",
    "sg:postcode":"3192 JS",
    "sg:province":"Zuid-Holland",
    "wof:name":"Impulse",
    "wof:placetype":"venue"
},
  "geometry": {"coordinates":[4.363963,51.84845],"type":"Point"}
}