{
  "type": "Feature",
  "properties": {
    "iso:country":"NL",
    "sg:address":"Rosendaalsewg 485",
    "sg:city":"Arnhem",
    "sg:orig_category":"Bejaarden - Verzorgingstehuizen",
    "sg:phone":"+31 26 354 9100",
    "sg:postcode":"6824 KK",
    "sg:province":"Gelderland",
    "wof:name":"Drie Gasthuizen, De",
    "wof:placetype":"venue"
},
  "geometry": {"coordinates":[5.932274,51.993729],"type":"Point"}
}