{
  "type": "Feature",
  "properties": {
    "addr:full":"Wilgenbroek 4 Breda Noord-Brabant 4822 XN",
    "addr:housenumber":"4",
    "addr:postcode":"4822 xn",
    "addr:street":"Wilgenbroek",
    "iso:country":"NL",
    "sg:address":"Wilgenbroek 4",
    "sg:city":"Breda",
    "sg:orig_category":"Artiestenbureaus",
    "sg:phone":"+31 76 541 5865",
    "sg:postcode":"4822 XN",
    "sg:province":"Noord-Brabant",
    "wof:name":"Muzjolie Muziekservice",
    "wof:placetype":"venue"
},
  "geometry": {"coordinates":[4.728121,51.604458],"type":"Point"}
}