{
  "type": "Feature",
  "properties": {
    "addr:full":"Goudenregenstraat 124 Hengelo Ov Overijssel 7552 AR",
    "addr:housenumber":"124",
    "addr:postcode":"7552",
    "addr:street":"Goudenregenstraat;Ov",
    "iso:country":"NL",
    "sg:address":"Goudenregenstraat 124",
    "sg:city":"Hengelo Ov",
    "sg:orig_category":"Diverse Consumentenartikelen Gh",
    "sg:phone":"+31 74 291 7071",
    "sg:postcode":"7552 AR",
    "sg:province":"Overijssel",
    "wof:name":"Libre Internationaal",
    "wof:placetype":"venue"
},
  "geometry": {"coordinates":[6.808907,52.248581],"type":"Point"}
}