{
  "type": "Feature",
  "properties": {
    "addr:full":"Zandstraat 14 Sint Michielsgestel Noord-Brabant 5271 TJ",
    "addr:housenumber":"14;michielsgestel",
    "addr:postcode":"5271 tj",
    "addr:street":"Zandstraat",
    "iso:country":"NL",
    "sg:address":"Zandstraat 14",
    "sg:city":"Sint Michielsgestel",
    "sg:orig_category":"Hout Gh",
    "sg:phone":"+31 73 594 2882",
    "sg:postcode":"5271 TJ",
    "sg:province":"Noord-Brabant",
    "wof:name":"M. Smits",
    "wof:placetype":"venue"
},
  "geometry": {"coordinates":[5.372409,51.657871],"type":"Point"}
}