{
  "type": "Feature",
  "properties": {
    "addr:full":"Nassaulaan 1A Berg En Dal Gelderland 6571 AC",
    "addr:housenumber":"1a",
    "addr:postcode":"6571 ac",
    "addr:street":"Nassaulaan",
    "iso:country":"NL",
    "sg:address":"Nassaulaan 1A",
    "sg:city":"Berg En Dal",
    "sg:orig_category":"Glaszetten",
    "sg:phone":"+31 24 684 1555",
    "sg:postcode":"6571 AC",
    "sg:province":"Gelderland",
    "wof:name":"Leenders Glas In Lood",
    "wof:placetype":"venue"
},
  "geometry": {"coordinates":[5.906988,51.826805],"type":"Point"}
}