{
  "type": "Feature",
  "properties": {
    "addr:full":"Wilgenstraat 48 Pannerden Gelderland 6911 BP",
    "addr:housenumber":"48",
    "addr:postcode":"6911 bp",
    "addr:street":"Wilgenstraat;Gelderland",
    "iso:country":"NL",
    "sg:address":"Wilgenstraat 48",
    "sg:city":"Pannerden",
    "sg:classifiers":[
        {
            "category":"Professional",
            "subcategory":"Accounting & Tax Preparation",
            "type":"Services"
        }
    ],
    "sg:phone":"+31 316 371 736",
    "sg:postcode":"6911 BP",
    "sg:province":"Gelderland",
    "sg:tags":[
        "accountant"
    ],
    "wof:name":"Accountants Gelderse Bv",
    "wof:placetype":"venue"
},
  "geometry": {"coordinates":[6.040635,51.891945],"type":"Point"}
}