{
  "type": "Feature",
  "properties": {
    "iso:country":"NL",
    "sg:address":"Elandsstr 2",
    "sg:city":"Amsterdam",
    "sg:orig_category":"Bedrijfsopleidingen",
    "sg:phone":"+31 20 428 5599",
    "sg:postcode":"1016 SG",
    "sg:province":"Noord-Holland",
    "wof:name":"Nomia",
    "wof:placetype":"venue"
},
  "geometry": {"coordinates":[4.882161,52.370342],"type":"Point"}
}