{
  "type": "Feature",
  "properties": {
    "iso:country":"NL",
    "sg:address":"Hoefblad 91",
    "sg:city":"Zwaag",
    "sg:orig_category":"Geluidsinstallaties",
    "sg:phone":"+31 229 234 600",
    "sg:postcode":"1689 ST",
    "sg:province":"Noord-Holland",
    "wof:name":"Spieker",
    "wof:placetype":"venue"
},
  "geometry": {"coordinates":[5.043479,52.666485],"type":"Point"}
}