{
  "type": "Feature",
  "properties": {
    "addr:full":"Karel De Grotelaan 16 Vlaardingen South Holland 3132 JV",
    "addr:housenumber":"16",
    "addr:postcode":"3132 jv",
    "addr:street":"Karel De Grotelaan",
    "iso:country":"NL",
    "sg:address":"Karel De Grotelaan 16",
    "sg:city":"Vlaardingen",
    "sg:orig_category":"Verzekeringen",
    "sg:phone":"+31 10 434 6831",
    "sg:postcode":"3132 JV",
    "sg:province":"South Holland",
    "wof:name":"S.W. Polderman Adviseur In Verzekeringen",
    "wof:placetype":"venue"
},
  "geometry": {"coordinates":[4.323303,51.912907],"type":"Point"}
}