{
  "type": "Feature",
  "properties": {
    "addr:full":"Oude Leedeweg 5 Pijnacker Zuid-Holland 2641 NL",
    "addr:housenumber":"5",
    "addr:postcode":"2641 nl",
    "addr:street":"Oude Leedeweg",
    "iso:country":"NL",
    "sg:address":"Oude Leedeweg 5",
    "sg:city":"Pijnacker",
    "sg:orig_category":"Bloemen And Planten",
    "sg:phone":"+31 15 369 3570",
    "sg:postcode":"2641 NL",
    "sg:province":"Zuid-Holland",
    "wof:name":"Firma C. Van Schie",
    "wof:placetype":"venue"
},
  "geometry": {"coordinates":[4.4409589767,51.9960250854],"type":"Point"}
}