{
  "type": "Feature",
  "properties": {
    "iso:country":"NL",
    "sg:address":"Zuiderzeestraatweg 34",
    "sg:city":"Hattem",
    "sg:orig_category":"Bloemen And Planten Gh",
    "sg:phone":"+31 38 444 9042",
    "sg:postcode":"8051 SN",
    "sg:province":"Gelderland",
    "wof:name":"Kwekerij Souman",
    "wof:placetype":"venue"
},
  "geometry": {"coordinates":[6.031625,52.482452],"type":"Point"}
}