{
  "type": "Feature",
  "properties": {
    "addr:full":"Rynstr 90 Amsterdam Noord-Holland 1079 HM",
    "addr:housenumber":"90",
    "addr:postcode":"1079 hm",
    "addr:street":"Rynstr",
    "iso:country":"NL",
    "sg:address":"Rynstr 90",
    "sg:city":"Amsterdam",
    "sg:orig_category":"Fotozaken",
    "sg:phone":"+31 20 644 9821",
    "sg:postcode":"1079 HM",
    "sg:province":"Noord-Holland",
    "wof:name":"Sunset",
    "wof:placetype":"venue"
},
  "geometry": {"coordinates":[4.89319,52.373119],"type":"Point"}
}