{
  "type": "Feature",
  "properties": {
    "addr:full":"Ferdinand Huycklaan 44 Baarn Utrecht 3743 AN",
    "addr:housenumber":"44",
    "addr:postcode":"3743 an",
    "addr:street":"Ferdinand Huycklaan",
    "iso:country":"NL",
    "sg:address":"Ferdinand Huycklaan 44",
    "sg:city":"Baarn",
    "sg:orig_category":"Haptotherapeuten",
    "sg:phone":"+31 35 543 0180",
    "sg:postcode":"3743 AN",
    "sg:province":"Utrecht",
    "wof:name":"Jansma, R",
    "wof:placetype":"venue"
},
  "geometry": {"coordinates":[5.270267,52.21722],"type":"Point"}
}