{
  "type": "Feature",
  "properties": {
    "addr:full":"Kuunderhof 60 Oosterwolde Fr Friesland 8431 EC",
    "addr:housenumber":"60",
    "addr:postcode":"8431 ec",
    "addr:street":"Kuunderhof",
    "iso:country":"NL",
    "sg:address":"Kuunderhof 60",
    "sg:city":"Oosterwolde Fr",
    "sg:orig_category":"Webdesign Bureaus",
    "sg:phone":"+31 516 522 822",
    "sg:postcode":"8431 EC",
    "sg:province":"Friesland",
    "wof:name":"Groen, Fran?ois",
    "wof:placetype":"venue"
},
  "geometry": {"coordinates":[6.2934651375,52.9823913574],"type":"Point"}
}