{
  "type": "Feature",
  "properties": {
    "addr:full":"Dorpsstr 638 Noord Scharwoude Noord-Holland 1723 HK",
    "addr:housenumber":"638",
    "addr:postcode":"1723 hk",
    "iso:country":"NL",
    "sg:address":"Dorpsstr 638",
    "sg:city":"Noord Scharwoude",
    "sg:orig_category":"Woninginrichting",
    "sg:phone":"+31 226 315 933",
    "sg:postcode":"1723 HK",
    "sg:province":"Noord-Holland",
    "wof:name":"Molenaar, J",
    "wof:placetype":"venue"
},
  "geometry": {"coordinates":[4.811519146,52.7041511536],"type":"Point"}
}