{
  "type": "Feature",
  "properties": {
    "addr:full":"Symfonielaan 1/C34 Nieuwegein Utrecht 3438 EW",
    "addr:housenumber":"1 / c34",
    "addr:postcode":"3438 ew",
    "addr:street":"Symfonielaan",
    "iso:country":"NL",
    "sg:address":"Symfonielaan 1/C34",
    "sg:city":"Nieuwegein",
    "sg:orig_category":"Meubels And Huishoudapparatuur Gh",
    "sg:phone":"+31 30 605 6863",
    "sg:postcode":"3438 EW",
    "sg:province":"Utrecht",
    "wof:name":"Ekv Meubel Bv",
    "wof:placetype":"venue"
},
  "geometry": {"coordinates":[5.082197,52.027325],"type":"Point"}
}