{
  "type": "Feature",
  "properties": {
    "iso:country":"NL",
    "sg:address":"Binnenburg 1",
    "sg:city":"Den Burg",
    "sg:classifiers":[
        {
            "category":"Shopping",
            "subcategory":"Adult",
            "type":"Retail Goods"
        }
    ],
    "sg:phone":"+31 222 312 258",
    "sg:postcode":"1791 CG",
    "sg:province":"Noord-Holland",
    "sg:tags":[
        "lingerie",
        "en",
        "tricotage"
    ],
    "wof:name":"Zegel",
    "wof:placetype":"venue"
},
  "geometry": {"coordinates":[4.797207,53.054478],"type":"Point"}
}