{
  "type": "Feature",
  "properties": {
    "addr:full":"Keulseweg 1 Loerbeek Gelderland 7036 AD",
    "addr:housenumber":"1",
    "addr:postcode":"7036 ad",
    "addr:street":"Keulseweg;Gelderland",
    "iso:country":"NL",
    "sg:address":"Keulseweg 1",
    "sg:city":"Loerbeek",
    "sg:orig_category":"Kappers",
    "sg:phone":"+31 316 532 975",
    "sg:postcode":"7036 AD",
    "sg:province":"Gelderland",
    "wof:name":"Kapsalon Andre Maas",
    "wof:placetype":"venue"
},
  "geometry": {"coordinates":[6.2104878426,51.9297218323],"type":"Point"}
}