{
  "type": "Feature",
  "properties": {
    "addr:full":"Veenmos 2 Nieuwerkerk Yssel South Holland 2914 XH",
    "addr:housenumber":"2",
    "addr:postcode":"2914 xh",
    "addr:street":"Veenmos",
    "iso:country":"NL",
    "sg:address":"Veenmos 2",
    "sg:city":"Nieuwerkerk Yssel",
    "sg:orig_category":"Psychologen",
    "sg:phone":"+31 180 314 599",
    "sg:postcode":"2914 XH",
    "sg:province":"South Holland",
    "sg:website":"http://www.bibu.nl",
    "wof:name":"Cedrus",
    "wof:placetype":"venue"
},
  "geometry": {"coordinates":[4.610142,51.971073],"type":"Point"}
}