{
  "type": "Feature",
  "properties": {
    "addr:full":"De Wetering 89 Oosterhout Nb North Brabant 4906 CT",
    "addr:housenumber":"89;nb",
    "addr:postcode":"4906 ct",
    "addr:street":"De Wetering",
    "iso:country":"NL",
    "sg:address":"De Wetering 89",
    "sg:city":"Oosterhout Nb",
    "sg:orig_category":"Verzekeringen - Verzekeringskantoren",
    "sg:phone":"+31 162 490 899",
    "sg:postcode":"4906 CT",
    "sg:province":"North Brabant",
    "wof:name":"Attentiv Bv",
    "wof:placetype":"venue"
},
  "geometry": {"coordinates":[4.84302,51.65432],"type":"Point"}
}