{
  "type": "Feature",
  "properties": {
    "addr:full":"Gageldijk 104 Utrecht Utrecht 3566 MH",
    "addr:housenumber":"104",
    "addr:postcode":"3566 mh",
    "addr:street":"Gageldijk",
    "iso:country":"NL",
    "sg:address":"Gageldijk 104",
    "sg:city":"Utrecht",
    "sg:orig_category":"Zuivelproducten And Spijsoli?n Gh",
    "sg:phone":"+31 30 261 7604",
    "sg:postcode":"3566 MH",
    "sg:province":"Utrecht",
    "wof:name":"Van Dommelen Kaas Utrecht Bv",
    "wof:placetype":"venue"
},
  "geometry": {"coordinates":[5.108237,52.128521],"type":"Point"}
}