{
  "type": "Feature",
  "properties": {
    "addr:full":"Vredehofstraat 13 Soest Utrecht 3761 HA",
    "addr:housenumber":"13",
    "addr:postcode":"3761 ha",
    "addr:street":"Vredehofstraat",
    "iso:country":"NL",
    "sg:address":"Vredehofstraat 13",
    "sg:city":"Soest",
    "sg:classifiers":[
        {
            "category":"Professional",
            "subcategory":"Accounting & Tax Preparation",
            "type":"Services"
        }
    ],
    "sg:phone":"+31 35 602 9484",
    "sg:postcode":"3761 HA",
    "sg:province":"Utrecht",
    "sg:tags":[
        "accountant"
    ],
    "wof:name":"W&R Registeraccountants Belastingsadviseurs",
    "wof:placetype":"venue"
},
  "geometry": {"coordinates":[5.28325,52.188789],"type":"Point"}
}