{
  "type": "Feature",
  "properties": {
    "addr:full":"Telingstraat 9 Utrecht Utrecht 3512 GV",
    "addr:housenumber":"9",
    "addr:postcode":"3512 gv",
    "addr:street":"Telingstraat",
    "iso:country":"NL",
    "sg:address":"Telingstraat 9",
    "sg:city":"Utrecht",
    "sg:orig_category":"Glaszetten",
    "sg:phone":"+31 30 233 3337",
    "sg:postcode":"3512 GV",
    "sg:province":"Utrecht",
    "wof:name":"Hielke Brugts Glas In Lood",
    "wof:placetype":"venue"
},
  "geometry": {"coordinates":[5.120004,52.09277],"type":"Point"}
}