{
  "type": "Feature",
  "properties": {
    "addr:full":"Rykswal 54A Woudrichem Noord-Brabant 4285 AD",
    "addr:housenumber":"54a",
    "addr:postcode":"4285 ad",
    "addr:street":"Rykswal",
    "iso:country":"NL",
    "sg:address":"Rykswal 54A",
    "sg:city":"Woudrichem",
    "sg:orig_category":"Kunstbemiddeling",
    "sg:phone":"+31 183 304 259",
    "sg:postcode":"4285 AD",
    "sg:province":"Noord-Brabant",
    "wof:name":"Overmans Kunst- & Restauratiebemiddeling, Mr J C",
    "wof:placetype":"venue"
},
  "geometry": {"coordinates":[5.003157,51.818104],"type":"Point"}
}