{
  "type": "Feature",
  "properties": {
    "addr:full":"Olmenln 68 Zwanenburg Noord-Holland 1161 JX",
    "addr:housenumber":"68",
    "addr:postcode":"1161 jx",
    "addr:street":"Olmenln",
    "iso:country":"NL",
    "sg:address":"Olmenln 68",
    "sg:city":"Zwanenburg",
    "sg:orig_category":"Kappers",
    "sg:phone":"+31 20 497 6198",
    "sg:postcode":"1161 JX",
    "sg:province":"Noord-Holland",
    "wof:name":"Knaap, Van Der",
    "wof:placetype":"venue"
},
  "geometry": {"coordinates":[4.749184,52.376068],"type":"Point"}
}