{
  "type": "Feature",
  "properties": {
    "iso:country":"NL",
    "sg:address":"Dorpsweg 100",
    "sg:city":"Hensbroek",
    "sg:orig_category":"Verlichting And Huishoudartikelen",
    "sg:phone":"+31 226 452 342",
    "sg:postcode":"1711 RM",
    "sg:province":"Noord-Holland",
    "wof:name":"Firma Bleeker-Kok",
    "wof:placetype":"venue"
},
  "geometry": {"coordinates":[4.882688,52.657272],"type":"Point"}
}