{
  "type": "Feature",
  "properties": {
    "iso:country":"NL",
    "sg:address":"Rukkerwg 58",
    "sg:city":"Heerlen",
    "sg:classifiers":[
        {
            "category":"Shopping",
            "subcategory":"Gifts & Souvenirs",
            "type":"Retail Goods"
        }
    ],
    "sg:phone":"+31 45 541 8339",
    "sg:postcode":"6418 TX",
    "sg:province":"Limburg",
    "sg:tags":[
        "wens-",
        "en",
        "prentbriefkaarten"
    ],
    "wof:name":"Lucky Cards Vof",
    "wof:placetype":"venue"
},
  "geometry": {"coordinates":[6.0111999512,50.8671607971],"type":"Point"}
}