{
  "type": "Feature",
  "properties": {
    "iso:country":"NL",
    "sg:address":"Bieslandsekd 196",
    "sg:city":"Delft",
    "sg:orig_category":"Huishoudelijke Apparaten En Artikelen",
    "sg:phone":"+31 15 213 2090",
    "sg:postcode":"2612 JZ",
    "sg:province":"Zuid-Holland",
    "wof:name":"Delftse Witgoed Service",
    "wof:placetype":"venue"
},
  "geometry": {"coordinates":[4.372174,52.01482],"type":"Point"}
}