{
  "type": "Feature",
  "properties": {
    "addr:full":"Rosarium 14 Nootdorp Zuid-Holland 2631 GN",
    "addr:housenumber":"14",
    "addr:postcode":"2631 gn",
    "addr:street":"Rosarium",
    "iso:country":"NL",
    "sg:address":"Rosarium 14",
    "sg:city":"Nootdorp",
    "sg:orig_category":"Adviesbureaus Werktuigbouwkunde",
    "sg:phone":"+31 15 310 7008",
    "sg:postcode":"2631 GN",
    "sg:province":"Zuid-Holland",
    "wof:name":"Bohemen, Van",
    "wof:placetype":"venue"
},
  "geometry": {"coordinates":[4.398018,52.047108],"type":"Point"}
}