{
  "type": "Feature",
  "properties": {
    "addr:full":"Herelsestr 110 Heerle Noord-Brabant 4726 AH",
    "addr:housenumber":"110",
    "addr:postcode":"4726 ah",
    "iso:country":"NL",
    "sg:address":"Herelsestr 110",
    "sg:city":"Heerle",
    "sg:orig_category":"Scholen Voor Basisonderwijs",
    "sg:phone":"+31 165 301 806",
    "sg:postcode":"4726 AH",
    "sg:province":"Noord-Brabant",
    "wof:name":"Berkenveld",
    "wof:placetype":"venue"
},
  "geometry": {"coordinates":[4.362095,51.518883],"type":"Point"}
}