{
  "type": "Feature",
  "properties": {
    "addr:full":"Kerkstr 2A Zaltbommel Gelderland 5301 EH",
    "addr:housenumber":"2a",
    "addr:postcode":"5301 eh",
    "addr:street":"Kerkstr;Gelderland",
    "iso:country":"NL",
    "sg:address":"Kerkstr 2A",
    "sg:city":"Zaltbommel",
    "sg:orig_category":"Adviesbureaus",
    "sg:phone":"+31 418 513 415",
    "sg:postcode":"5301 EH",
    "sg:province":"Gelderland",
    "wof:name":"Mar Monumenten Archieven & Redaktie",
    "wof:placetype":"venue"
},
  "geometry": {"coordinates":[5.249997,51.813713],"type":"Point"}
}