{
  "type": "Feature",
  "properties": {
    "addr:full":"Trekvalk 17 Veenendaal Utrecht 3905 RC",
    "addr:housenumber":"17",
    "addr:postcode":"3905 rc",
    "addr:street":"Trekvalk",
    "iso:country":"NL",
    "sg:address":"Trekvalk 17",
    "sg:city":"Veenendaal",
    "sg:orig_category":"Farmaceutische Producten Gh",
    "sg:phone":"+31 318 517 513",
    "sg:postcode":"3905 RC",
    "sg:province":"Utrecht",
    "wof:name":"Van Den Brink Instrumenten",
    "wof:placetype":"venue"
},
  "geometry": {"coordinates":[5.534795,52.028259],"type":"Point"}
}