{
  "type": "Feature",
  "properties": {
    "addr:full":"Nusterwg 96 Sittard Limburg 6136 KV",
    "addr:housenumber":"96",
    "addr:postcode":"6136 kv",
    "addr:street":"Nusterwg",
    "iso:country":"NL",
    "sg:address":"Nusterwg 96",
    "sg:city":"Sittard",
    "sg:orig_category":"Kanteldeuren",
    "sg:phone":"+31 46 420 0666",
    "sg:postcode":"6136 KV",
    "sg:province":"Limburg",
    "sg:website":"http://www.tfe-doco.com",
    "wof:name":"Torque Force Europa Doco Bv",
    "wof:placetype":"venue"
},
  "geometry": {"coordinates":[5.863380909,51.0222167969],"type":"Point"}
}