{
  "type": "Feature",
  "properties": {
    "iso:country":"NL",
    "sg:address":"Paul Krugerlaan 273",
    "sg:city":"'S Gravenhage",
    "sg:orig_category":"Opticiens",
    "sg:phone":"+31 70 365 0974",
    "sg:postcode":"2571 HJ",
    "sg:province":"Zuid-Holland",
    "wof:name":"Romani Transvaal",
    "wof:placetype":"venue"
},
  "geometry": {"coordinates":[4.2938070297,52.0682258606],"type":"Point"}
}