{
  "type": "Feature",
  "properties": {
    "addr:full":"Velddreef 330 Zoetermeer South Holland 2727 CV",
    "addr:housenumber":"330",
    "addr:postcode":"2727 cv",
    "addr:street":"Velddreef",
    "iso:country":"NL",
    "sg:address":"Velddreef 330",
    "sg:city":"Zoetermeer",
    "sg:orig_category":"Fitnesscentra",
    "sg:phone":"+31 79 316 4930",
    "sg:postcode":"2727 CV",
    "sg:province":"South Holland",
    "wof:name":"Baukdu",
    "wof:placetype":"venue"
},
  "geometry": {"coordinates":[4.515906,52.069744],"type":"Point"}
}