{
  "type": "Feature",
  "properties": {
    "addr:full":"Plesmanstr 67 Hoogeveen Drenthe 7903 BG",
    "addr:housenumber":"67",
    "addr:postcode":"7903",
    "addr:street":"Plesmanstr",
    "iso:country":"NL",
    "sg:address":"Plesmanstr 67",
    "sg:city":"Hoogeveen",
    "sg:classifiers":[
        {
            "category":"Wholesale",
            "subcategory":"Meat",
            "type":"Manufacturing & Wholesale Goods"
        }
    ],
    "sg:phone":"+31 528 229 888",
    "sg:postcode":"7903 BG",
    "sg:province":"Drenthe",
    "sg:tags":[
        "regeltechniek",
        "en",
        "meet-"
    ],
    "wof:name":"Rensen Bv",
    "wof:placetype":"venue"
},
  "geometry": {"coordinates":[6.519661,52.735767],"type":"Point"}
}