{
  "type": "Feature",
  "properties": {
    "addr:full":"Bartokpad 8 Delft Zuid-Holland 2625 AB",
    "addr:housenumber":"8",
    "addr:postcode":"2625 ab",
    "addr:street":"Bartokpad",
    "iso:country":"NL",
    "sg:address":"Bartokpad 8",
    "sg:city":"Delft",
    "sg:classifiers":[
        {
            "category":"Fast Food",
            "type":"Food & Drink"
        }
    ],
    "sg:phone":"+31 15 256 3735",
    "sg:postcode":"2625 AB",
    "sg:province":"Zuid-Holland",
    "sg:tags":[
        "afhaal",
        "restaurant"
    ],
    "wof:name":"China Garden",
    "wof:placetype":"venue"
},
  "geometry": {"coordinates":[4.342227,51.996136],"type":"Point"}
}