{
  "type": "Feature",
  "properties": {
    "addr:full":"Vloed 102 Breda North Brabant 4813 PG",
    "addr:housenumber":"102",
    "addr:postcode":"4813 pg",
    "addr:street":"Vloed",
    "iso:country":"NL",
    "sg:address":"Vloed 102",
    "sg:city":"Breda",
    "sg:orig_category":"Verenigingen En Stichtingen",
    "sg:phone":"+31 76 514 9926",
    "sg:postcode":"4813 PG",
    "sg:province":"North Brabant",
    "wof:name":"Huisvrouwen, Nederlandse Ver Van",
    "wof:placetype":"venue"
},
  "geometry": {"coordinates":[4.742038,51.570827],"type":"Point"}
}