{
  "type": "Feature",
  "properties": {
    "addr:full":"Kon Julianaln 19 Paterswolde Drenthe 9765 AH",
    "addr:housenumber":"19",
    "addr:postcode":"9765 ah",
    "addr:street":"Kon",
    "iso:country":"NL",
    "sg:address":"Kon Julianaln 19",
    "sg:city":"Paterswolde",
    "sg:orig_category":"Boekhandels",
    "sg:phone":"+31 50 308 0088",
    "sg:postcode":"9765 AH",
    "sg:province":"Drenthe",
    "sg:website":"http://www.amasusbooks.net",
    "wof:name":"Amasus",
    "wof:placetype":"venue"
},
  "geometry": {"coordinates":[83.34802999999999,24.4242],"type":"Point"}
}