{
  "type": "Feature",
  "properties": {
    "iso:country":"NL",
    "sg:address":"Lysterbesln 40",
    "sg:city":"Ter Aar",
    "sg:orig_category":"Administratie- En Boekhoudkantoren",
    "sg:phone":"+31 172 604 812",
    "sg:postcode":"2461 DA",
    "sg:province":"Zuid-Holland",
    "wof:name":"Krete",
    "wof:placetype":"venue"
},
  "geometry": {"coordinates":[4.707053,52.170143],"type":"Point"}
}