{
  "type": "Feature",
  "properties": {
    "addr:full":"Fazantenwg 5 Renesse Zeeland 4325 GB",
    "addr:housenumber":"5",
    "addr:postcode":"4325 gb",
    "addr:street":"Fazantenwg",
    "iso:country":"NL",
    "sg:address":"Fazantenwg 5",
    "sg:city":"Renesse",
    "sg:classifiers":[
        {
            "category":"Organizations",
            "subcategory":"Community Association",
            "type":"Services"
        }
    ],
    "sg:phone":"+31 111 463 728",
    "sg:postcode":"4325 GB",
    "sg:province":"Zeeland",
    "sg:tags":[
        "badge"
    ],
    "wof:name":"Sos Talisman Holland",
    "wof:placetype":"venue"
},
  "geometry": {"coordinates":[3.771577,51.735779],"type":"Point"}
}