{
  "type": "Feature",
  "properties": {
    "addr:full":"Kerkendk 152A Someren Noord-Brabant 5712 EZ",
    "addr:housenumber":"152a",
    "addr:postcode":"5712 ez",
    "iso:country":"NL",
    "sg:address":"Kerkendk 152A",
    "sg:city":"Someren",
    "sg:orig_category":"Zonweringen",
    "sg:phone":"+31 495 697 417",
    "sg:postcode":"5712 EZ",
    "sg:province":"Noord-Brabant",
    "wof:name":"Glas Coating Someren",
    "wof:placetype":"venue"
},
  "geometry": {"coordinates":[5.694363,51.340778],"type":"Point"}
}