{
  "type": "Feature",
  "properties": {
    "addr:full":"Sinnigvelderstr 331 Weesp Noord-Holland 1382 EZ",
    "addr:housenumber":"331",
    "addr:postcode":"1382 ez",
    "iso:country":"NL",
    "sg:address":"Sinnigvelderstr 331",
    "sg:city":"Weesp",
    "sg:orig_category":"Verzekeringen - Verzekeringskantoren",
    "sg:phone":"+31 294 430 122",
    "sg:postcode":"1382 EZ",
    "sg:province":"Noord-Holland",
    "wof:name":"Brink, Van Den",
    "wof:placetype":"venue"
},
  "geometry": {"coordinates":[5.028877,52.311897],"type":"Point"}
}