{
  "type": "Feature",
  "properties": {
    "iso:country":"NL",
    "sg:address":"Jacob Bontiusplaats 9",
    "sg:city":"Amsterdam",
    "sg:classifiers":[
        {
            "category":"Professional",
            "subcategory":"Computer Services",
            "type":"Services"
        }
    ],
    "sg:postcode":"1018 LL",
    "sg:tags":[
        "web-services",
        "software",
        "software-development",
        "it",
        "remote"
    ],
    "sg:website":"https://secure.logmein.com",
    "wof:name":"LogMeIn",
    "wof:placetype":"venue"
},
  "geometry": {"coordinates":[4.9277653,52.3710089],"type":"Point"}
}