{
  "type": "Feature",
  "properties": {
    "addr:full":"Larixln 10 Driebergen Rysenb Utrecht 3971 RB",
    "addr:housenumber":"10",
    "addr:postcode":"3971 rb",
    "addr:street":"Larixln;Rysenb",
    "iso:country":"NL",
    "sg:address":"Larixln 10",
    "sg:city":"Driebergen Rysenb",
    "sg:orig_category":"Juridische Adviseurs",
    "sg:phone":"+31 343 515 221",
    "sg:postcode":"3971 RB",
    "sg:province":"Utrecht",
    "wof:name":"Herik, Mr W Van Den",
    "wof:placetype":"venue"
},
  "geometry": {"coordinates":[5.30052,52.065571],"type":"Point"}
}