{
  "type": "Feature",
  "properties": {
    "addr:full":"G Flinckstr 352 Amsterdam Noord-Holland 1074 CG",
    "addr:housenumber":"352",
    "addr:postcode":"1074 cg",
    "iso:country":"NL",
    "sg:address":"G Flinckstr 352",
    "sg:city":"Amsterdam",
    "sg:orig_category":"Keukens",
    "sg:phone":"+31 20 662 9213",
    "sg:postcode":"1074 CG",
    "sg:province":"Noord-Holland",
    "wof:name":"Schram, Keukenstudio",
    "wof:placetype":"venue"
},
  "geometry": {"coordinates":[4.901063,52.356918],"type":"Point"}
}