{
  "type": "Feature",
  "properties": {
    "iso:country":"NL",
    "sg:address":"Kinlozen 35",
    "sg:city":"Nieuw Vennep",
    "sg:orig_category":"Schoonheidsinstituten",
    "sg:phone":"+31 252 621 504",
    "sg:postcode":"2151 XB",
    "sg:province":"Noord-Holland",
    "wof:name":"Jady Beauty",
    "wof:placetype":"venue"
},
  "geometry": {"coordinates":[4.621894,52.262222],"type":"Point"}
}