{
  "type": "Feature",
  "properties": {
    "iso:country":"NL",
    "sg:address":"Hoofdstr O 23",
    "sg:city":"Noordwolde Fr",
    "sg:classifiers":[
        {
            "category":"Food & Beverages",
            "subcategory":"Bakery",
            "type":"Retail Goods"
        }
    ],
    "sg:phone":"+31 561 433 432",
    "sg:postcode":"8391 AS",
    "sg:province":"Provincie Friesland",
    "sg:tags":[
        "pizza"
    ],
    "wof:name":"Sphinx",
    "wof:placetype":"venue"
},
  "geometry": {"coordinates":[6.14197,52.891758],"type":"Point"}
}