{
  "type": "Feature",
  "properties": {
    "addr:full":"Hoefkensdijk 50 Kuitaart Zeeland 4584 RR",
    "addr:housenumber":"50",
    "addr:postcode":"4584 rr",
    "addr:street":"Hoefkensdijk",
    "iso:country":"NL",
    "sg:address":"Hoefkensdijk 50",
    "sg:city":"Kuitaart",
    "sg:orig_category":"Fotostudio'S And Fotografen",
    "sg:phone":"+31 114 690 704",
    "sg:postcode":"4584 RR",
    "sg:province":"Zeeland",
    "wof:name":"Fotografie Ton Sondag",
    "wof:placetype":"venue"
},
  "geometry": {"coordinates":[4.048161,51.337986],"type":"Point"}
}