{
  "type": "Feature",
  "properties": {
    "addr:full":"Kapittelwg 2E Hilversum North Holland 1216 JE",
    "addr:housenumber":"2e",
    "addr:postcode":"1216 je",
    "addr:street":"Kapittelwg",
    "iso:country":"NL",
    "sg:address":"Kapittelwg 2E",
    "sg:city":"Hilversum",
    "sg:orig_category":"Vakorganisaties",
    "sg:phone":"+31 35 624 2253",
    "sg:postcode":"1216 JE",
    "sg:province":"North Holland",
    "wof:name":"Fnv",
    "wof:placetype":"venue"
},
  "geometry": {"coordinates":[5.142955,52.215164],"type":"Point"}
}