{
  "type": "Feature",
  "properties": {
    "addr:full":"Markt 33 Veere Zeeland 4351 AG",
    "addr:housenumber":"33",
    "addr:postcode":"4351",
    "addr:street":"Markt",
    "iso:country":"NL",
    "sg:address":"Markt 33",
    "sg:city":"Veere",
    "sg:orig_category":"Herenkleding",
    "sg:phone":"+31 118 502 161",
    "sg:postcode":"4351 AG",
    "sg:province":"Zeeland",
    "wof:name":"Baaskees",
    "wof:placetype":"venue"
},
  "geometry": {"coordinates":[3.668678,51.548271],"type":"Point"}
}