{
  "type": "Feature",
  "properties": {
    "addr:full":"Rijndijk 209 Hazerswoude Rijndijk Zuid-Holland 2394 CC",
    "addr:housenumber":"209",
    "addr:postcode":"2394 cc",
    "addr:street":"Rijndijk;Hazerswoude Rijndijk",
    "iso:country":"NL",
    "sg:address":"Rijndijk 209",
    "sg:city":"Hazerswoude Rijndijk",
    "sg:orig_category":"Boekhouders",
    "sg:phone":"+31 71 341 6747",
    "sg:postcode":"2394 CC",
    "sg:province":"Zuid-Holland",
    "wof:name":"De Schepper Administratie Advieskantoor",
    "wof:placetype":"venue"
},
  "geometry": {"coordinates":[4.606205,52.129402],"type":"Point"}
}