{
  "type": "Feature",
  "properties": {
    "addr:full":"Van Coothplein 16 Breda Noord-Brabant 4811 NE",
    "addr:housenumber":"16;4811",
    "addr:postcode":"ne",
    "addr:street":"Van Coothplein",
    "iso:country":"NL",
    "sg:address":"Van Coothplein 16",
    "sg:city":"Breda",
    "sg:orig_category":"Werving And Selectie Van Tijdelijk Personeel And Uitzendkantoren",
    "sg:phone":"+31 76 520 4304",
    "sg:postcode":"4811 NE",
    "sg:province":"Noord-Brabant",
    "wof:name":"Tence! Uitzendburo",
    "wof:placetype":"venue"
},
  "geometry": {"coordinates":[4.7772259712,51.5831756592],"type":"Point"}
}