{
  "type": "Feature",
  "properties": {
    "addr:full":"Nooitgedacht 2 Zeist Utrecht 3701 AN",
    "addr:housenumber":"2",
    "addr:postcode":"3701 an",
    "addr:street":"Nooitgedacht",
    "iso:country":"NL",
    "sg:address":"Nooitgedacht 2",
    "sg:city":"Zeist",
    "sg:orig_category":"Werving And Selectie Van Vast Personeel",
    "sg:phone":"+31 30 691 6161",
    "sg:postcode":"3701 AN",
    "sg:province":"Utrecht",
    "wof:name":"Aedius It Diensten",
    "wof:placetype":"venue"
},
  "geometry": {"coordinates":[5.241396904,52.0820007324],"type":"Point"}
}