{
  "type": "Feature",
  "properties": {
    "addr:full":"Radonstr 299 Zoetermeer South Holland 2718 SV",
    "addr:housenumber":"299",
    "addr:postcode":"2718 sv",
    "iso:country":"NL",
    "sg:address":"Radonstr 299",
    "sg:city":"Zoetermeer",
    "sg:orig_category":"Kettingen En Kettingwielen",
    "sg:phone":"+31 79 361 5271",
    "sg:postcode":"2718 SV",
    "sg:province":"South Holland",
    "sg:website":"http://www.kettingimport.com",
    "wof:name":"Ketting Import Mij Bv",
    "wof:placetype":"venue"
},
  "geometry": {"coordinates":[4.505699,52.03397],"type":"Point"}
}