{
  "type": "Feature",
  "properties": {
    "addr:full":"De Schorpioen 11 'S Hertogenbosch North Brabant 5215 MD",
    "addr:housenumber":"11",
    "addr:postcode":"5215",
    "addr:street":"De Schorpioen;' S Hertogenbosch",
    "iso:country":"NL",
    "sg:address":"De Schorpioen 11",
    "sg:city":"'S Hertogenbosch",
    "sg:orig_category":"Schilderwerk",
    "sg:phone":"+31 73 691 0527",
    "sg:postcode":"5215 MD",
    "sg:province":"North Brabant",
    "wof:name":"T Pennings",
    "wof:placetype":"venue"
},
  "geometry": {"coordinates":[5.364094,51.686127],"type":"Point"}
}