{
  "type": "Feature",
  "properties": {
    "iso:country":"NL",
    "sg:address":"Victoria Regiastraat 10",
    "sg:city":"Almere",
    "sg:orig_category":"Juridische Dienstverlening",
    "sg:phone":"+31 36 537 1785",
    "sg:postcode":"1338 ZA",
    "sg:province":"Flevoland",
    "wof:name":"Adviesburo Ten Brink",
    "wof:placetype":"venue"
},
  "geometry": {"coordinates":[5.289066,52.390171],"type":"Point"}
}