{
  "type": "Feature",
  "properties": {
    "iso:country":"NL",
    "sg:address":"Woenselse Markt 44",
    "sg:city":"Eindhoven",
    "sg:orig_category":"Algemene Werktuigbouw",
    "sg:phone":"+31 40 243 5480",
    "sg:postcode":"5612 CS",
    "sg:province":"Noord-Brabant",
    "wof:name":"P Van Grimbergen",
    "wof:placetype":"venue"
},
  "geometry": {"coordinates":[5.471493,51.450836],"type":"Point"}
}