{
  "type": "Feature",
  "properties": {
    "addr:full":"Schoterwg 7A Haarlem Noord-Holland 2021 HZ",
    "addr:housenumber":"7a",
    "addr:postcode":"2021 hz",
    "addr:street":"Schoterwg",
    "iso:country":"NL",
    "sg:address":"Schoterwg 7A",
    "sg:city":"Haarlem",
    "sg:orig_category":"Kappers",
    "sg:phone":"+31 251 270 802",
    "sg:postcode":"2021 HZ",
    "sg:province":"Noord-Holland",
    "wof:name":"Estilo Latino",
    "wof:placetype":"venue"
},
  "geometry": {"coordinates":[4.6404099464,52.3910751343],"type":"Point"}
}