{
  "type": "Feature",
  "properties": {
    "addr:full":"Nieuwstraat 24 Budel Noord-Brabant 6021 HS",
    "addr:housenumber":"24",
    "addr:postcode":"6021 hs",
    "addr:street":"Nieuwstraat",
    "iso:country":"NL",
    "sg:address":"Nieuwstraat 24",
    "sg:city":"Budel",
    "sg:orig_category":"Opticiens",
    "sg:phone":"+31 495 494 363",
    "sg:postcode":"6021 HS",
    "sg:province":"Noord-Brabant",
    "wof:name":"Optiek Lunette",
    "wof:placetype":"venue"
},
  "geometry": {"coordinates":[5.5730772018,51.2723121643],"type":"Point"}
}