{
  "type": "Feature",
  "properties": {
    "addr:full":"Rijshoutweg 31 Zaandam Noord-Holland 1505 HL",
    "addr:housenumber":"31",
    "addr:postcode":"1505 hl",
    "addr:street":"Rijshoutweg",
    "iso:country":"NL",
    "sg:address":"Rijshoutweg 31",
    "sg:city":"Zaandam",
    "sg:classifiers":[
        {
            "category":"Retail",
            "subcategory":"Storage",
            "type":"Services"
        }
    ],
    "sg:phone":"+31 75 616 1514",
    "sg:postcode":"1505 HL",
    "sg:province":"Noord-Holland",
    "sg:tags":[
        "opslag",
        "bewaring"
    ],
    "wof:name":"Overslagsilo De Sluis Bv",
    "wof:placetype":"venue"
},
  "geometry": {"coordinates":[4.8471832275,52.4223098755],"type":"Point"}
}