{
  "type": "Feature",
  "properties": {
    "iso:country":"NL",
    "sg:address":"Herculeshof 23-25",
    "sg:city":"Maastricht",
    "sg:orig_category":"Bloemen And Planten",
    "sg:phone":"+31 43 347 3434",
    "sg:postcode":"6215 BE",
    "sg:province":"Limburg",
    "wof:name":"Bloemisterij Bloesem",
    "wof:placetype":"venue"
},
  "geometry": {"coordinates":[5.65089,50.839161],"type":"Point"}
}