{
  "type": "Feature",
  "properties": {
    "addr:full":"Transformatorweg 37 Amsterdam Noord-Holland 1014 AJ",
    "addr:housenumber":"37",
    "addr:postcode":"1014 aj",
    "addr:street":"Transformatorweg",
    "iso:country":"NL",
    "sg:address":"Transformatorweg 37",
    "sg:city":"Amsterdam",
    "sg:orig_category":"Diverse Bedrijfsinstallaties Gh",
    "sg:phone":"+31 20 686 8711",
    "sg:postcode":"1014 AJ",
    "sg:province":"Noord-Holland",
    "wof:name":"Johan Putzfeld Bv",
    "wof:placetype":"venue"
},
  "geometry": {"coordinates":[4.849892,52.391441],"type":"Point"}
}