{
  "type": "Feature",
  "properties": {
    "addr:full":"Andromedaring 1 Dordrecht South Holland 3328 HB",
    "addr:housenumber":"1",
    "addr:postcode":"3328 hb",
    "addr:street":"Andromedaring",
    "iso:country":"NL",
    "sg:address":"Andromedaring 1",
    "sg:city":"Dordrecht",
    "sg:orig_category":"Pianostemmen En -Reparatie",
    "sg:phone":"+31 78 617 8296",
    "sg:postcode":"3328 HB",
    "sg:province":"South Holland",
    "wof:name":"Emmery, Richard",
    "wof:placetype":"venue"
},
  "geometry": {"coordinates":[4.685585,51.780979],"type":"Point"}
}