{
  "type": "Feature",
  "properties": {
    "iso:country":"NL",
    "sg:address":"Postbus 252",
    "sg:city":"Leusden",
    "sg:orig_category":"Verenigingen En Stichtingen",
    "sg:phone":"+31 33 496 0285",
    "sg:postcode":"3830 AG",
    "sg:province":"Utrecht",
    "sg:website":"http://www.jongnederland.nl",
    "wof:name":"Jong Nedederland, Stichting",
    "wof:placetype":"venue"
},
  "geometry": {"coordinates":[5.42959,52.131248],"type":"Point"}
}