{
  "type": "Feature",
  "properties": {
    "addr:full":"Hondsruglaan 91 Eindhoven Noord-Brabant 5628 DB",
    "addr:housenumber":"91",
    "addr:postcode":"5628 db",
    "addr:street":"Hondsruglaan",
    "iso:country":"NL",
    "sg:address":"Hondsruglaan 91",
    "sg:city":"Eindhoven",
    "sg:orig_category":"Verzekeringen",
    "sg:phone":"+31 40 241 1611",
    "sg:postcode":"5628 DB",
    "sg:province":"Noord-Brabant",
    "wof:name":"Profidas Bv",
    "wof:placetype":"venue"
},
  "geometry": {"coordinates":[5.457709,51.482845],"type":"Point"}
}