{
  "type": "Feature",
  "properties": {
    "addr:full":"Slabbecoornweg 48 Tholen Zeeland 4691 RZ",
    "addr:housenumber":"48",
    "addr:postcode":"4691 rz",
    "addr:street":"Slabbecoornweg",
    "iso:country":"NL",
    "sg:address":"Slabbecoornweg 48",
    "sg:city":"Tholen",
    "sg:orig_category":"Drukkerijen And Copyshops",
    "sg:phone":"+31 166 604 400",
    "sg:postcode":"4691 RZ",
    "sg:province":"Zeeland",
    "wof:name":"Npn Grafimedia Bv",
    "wof:placetype":"venue"
},
  "geometry": {"coordinates":[4.232991,51.548557],"type":"Point"}
}