{
  "type": "Feature",
  "properties": {
    "addr:full":"St Jacobstr 9 Rotterdam South Holland 3011 DK",
    "addr:housenumber":"9",
    "addr:postcode":"3011 dk",
    "iso:country":"NL",
    "sg:address":"St Jacobstr 9",
    "sg:city":"Rotterdam",
    "sg:orig_category":"Makelaars En Adviseurs Roerende Goederen",
    "sg:phone":"+31 10 270 9313",
    "sg:postcode":"3011 DK",
    "sg:province":"South Holland",
    "sg:website":"http://www.wozadvies.nl",
    "wof:name":"Woz, Van Der",
    "wof:placetype":"venue"
},
  "geometry": {"coordinates":[4.482476,51.923409],"type":"Point"}
}