{
  "type": "Feature",
  "properties": {
    "addr:full":"Anne Frankkade 26 Alphen A/D Rijn Zuid-Holland 2406 DH",
    "addr:housenumber":"26",
    "addr:postcode":"2406 dh",
    "iso:country":"NL",
    "sg:address":"Anne Frankkade 26",
    "sg:city":"Alphen A/D Rijn",
    "sg:orig_category":"Werving And Selectie Van Tijdelijk Personeel And Uitzendkantoren",
    "sg:phone":"+31 172 492 951",
    "sg:postcode":"2406 DH",
    "sg:province":"Zuid-Holland",
    "wof:name":"Vedior Personeelsdiensten",
    "wof:placetype":"venue"
},
  "geometry": {"coordinates":[4.664285183,52.1305656433],"type":"Point"}
}