{
  "type": "Feature",
  "properties": {
    "addr:full":"Cruquiuswg To 85 Amsterdam North Holland 1019 AT",
    "addr:housenumber":"85",
    "addr:postcode":"1019",
    "iso:country":"NL",
    "sg:address":"Cruquiuswg To 85",
    "sg:city":"Amsterdam",
    "sg:orig_category":"Oud Metaal",
    "sg:phone":"+31 20 663 0362",
    "sg:postcode":"1019 AT",
    "sg:province":"North Holland",
    "wof:name":"Neuteboom, N",
    "wof:placetype":"venue"
},
  "geometry": {"coordinates":[4.9520549774,52.3683509827],"type":"Point"}
}