{
  "type": "Feature",
  "properties": {
    "addr:full":"Windmolen 74 Ridderkerk Zuid-Holland 2986 TK",
    "addr:housenumber":"74",
    "addr:postcode":"2986 tk",
    "addr:street":"Windmolen",
    "iso:country":"NL",
    "sg:address":"Windmolen 74",
    "sg:city":"Ridderkerk",
    "sg:orig_category":"Administratie- En Boekhoudkantoren",
    "sg:phone":"+31 180 422 170",
    "sg:postcode":"2986 TK",
    "sg:province":"Zuid-Holland",
    "wof:name":"Heeselaars, A J",
    "wof:placetype":"venue"
},
  "geometry": {"coordinates":[4.614343,51.860996],"type":"Point"}
}