{
  "type": "Feature",
  "properties": {
    "addr:full":"Bloemendaalseweg 249 Overveen Noord-Holland 2051 GC",
    "addr:housenumber":"249",
    "addr:postcode":"2051 gc",
    "addr:street":"Bloemendaalseweg",
    "iso:country":"NL",
    "sg:address":"Bloemendaalseweg 249",
    "sg:city":"Overveen",
    "sg:orig_category":"Alternatieve Geneeskunde",
    "sg:phone":"+31 23 526 6743",
    "sg:postcode":"2051 GC",
    "sg:province":"Noord-Holland",
    "wof:name":"Toets Balans Therapie",
    "wof:placetype":"venue"
},
  "geometry": {"coordinates":[4.60972,52.391731],"type":"Point"}
}