{
  "type": "Feature",
  "properties": {
    "addr:full":"Htg Reinoudsngl 188 Venlo Limburg 5913 XH",
    "addr:housenumber":"188",
    "addr:postcode":"5913 xh",
    "iso:country":"NL",
    "sg:address":"Htg Reinoudsngl 188",
    "sg:city":"Venlo",
    "sg:orig_category":"Pruiken",
    "sg:phone":"+31 77 351 2076",
    "sg:postcode":"5913 XH",
    "sg:province":"Limburg",
    "wof:name":"Huizenaar Haarwerk Specialisten",
    "wof:placetype":"venue"
},
  "geometry": {"coordinates":[6.17286,51.372421],"type":"Point"}
}