{
  "type": "Feature",
  "properties": {
    "iso:country":"NL",
    "sg:address":"Westwal 9",
    "sg:city":"Goes",
    "sg:orig_category":"Hypotheken And Hypotheekbanken",
    "sg:phone":"+31 113 232 548",
    "sg:postcode":"4461 CM",
    "sg:province":"Zeeland",
    "wof:name":"Hypotheekcentrum Nederland Bv",
    "wof:placetype":"venue"
},
  "geometry": {"coordinates":[-83.914169,39.768833],"type":"Point"}
}