{
  "type": "Feature",
  "properties": {
    "addr:full":"Javastraat 52 Alphen A/D Rijn Zuid-Holland 2405 CS",
    "addr:housenumber":"52",
    "addr:postcode":"2405 cs",
    "addr:street":"Javastraat",
    "iso:country":"NL",
    "sg:address":"Javastraat 52",
    "sg:city":"Alphen A/D Rijn",
    "sg:orig_category":"Metaalwerken",
    "sg:phone":"+31 172 495 625",
    "sg:postcode":"2405 CS",
    "sg:province":"Zuid-Holland",
    "wof:name":"Decobeter Zonweringen",
    "wof:placetype":"venue"
},
  "geometry": {"coordinates":[4.659748,52.133762],"type":"Point"}
}