{
  "type": "Feature",
  "properties": {
    "addr:full":"Nassaulaan 36 Delft South Holland 2628 GJ",
    "addr:housenumber":"36",
    "addr:postcode":"2628 gj",
    "addr:street":"Nassaulaan",
    "iso:country":"NL",
    "sg:address":"Nassaulaan 36",
    "sg:city":"Delft",
    "sg:classifiers":[
        {
            "category":"Fast Food",
            "type":"Food & Drink"
        }
    ],
    "sg:phone":"+31 15 257 0929",
    "sg:postcode":"2628 GJ",
    "sg:province":"South Holland",
    "sg:tags":[
        "afhaal",
        "restaurant"
    ],
    "wof:name":"Hannibal Bv",
    "wof:placetype":"venue"
},
  "geometry": {"coordinates":[4.376824,52.007164],"type":"Point"}
}