{
  "type": "Feature",
  "properties": {
    "iso:country":"NL",
    "sg:address":"Hoofdweg 30",
    "sg:city":"Amsterdam",
    "sg:orig_category":"Diverse Kredietdiensten",
    "sg:postcode":"1058 BC",
    "sg:province":"Noord-Holland",
    "wof:name":"Rabobank Geldautomaat",
    "wof:placetype":"venue"
},
  "geometry": {"coordinates":[4.853533,52.359959],"type":"Point"}
}