{
  "type": "Feature",
  "properties": {
    "iso:country":"NL",
    "sg:address":"Wilhelminahav Nz 17",
    "sg:city":"Vlaardingen",
    "sg:orig_category":"Margarine, Olie En Vet - Industrie",
    "sg:phone":"+31 10 445 3500",
    "sg:postcode":"3134 KE",
    "sg:province":"Zuid-Holland",
    "wof:name":"Romi Smilfood Bv",
    "wof:placetype":"venue"
},
  "geometry": {"coordinates":[4.354687,51.905075],"type":"Point"}
}