{
  "type": "Feature",
  "properties": {
    "addr:full":"Kerkstraat 9 Groot Ammers Zuid-Holland 2964 BT",
    "addr:housenumber":"9",
    "addr:postcode":"2964 bt",
    "addr:street":"Kerkstraat;Groot Ammers",
    "iso:country":"NL",
    "sg:address":"Kerkstraat 9",
    "sg:city":"Groot Ammers",
    "sg:classifiers":[
        {
            "category":"Shopping",
            "subcategory":"Gifts & Souvenirs",
            "type":"Retail Goods"
        }
    ],
    "sg:phone":"+31 184 662 811",
    "sg:postcode":"2964 BT",
    "sg:province":"Zuid-Holland",
    "sg:tags":[
        "geschenken"
    ],
    "wof:name":"Kado En Homedecoration De Rozenboog",
    "wof:placetype":"venue"
},
  "geometry": {"coordinates":[4.818238,51.923466],"type":"Point"}
}