{
  "type": "Feature",
  "properties": {
    "iso:country":"NL",
    "sg:address":"Molenlaan 42",
    "sg:city":"Hillegom",
    "sg:orig_category":"Bloemen And Planten Gh",
    "sg:phone":"+31 252 518 238",
    "sg:postcode":"2181 GE",
    "sg:province":"Zuid-Holland",
    "wof:name":"H P Rijnbeek & Zonen",
    "wof:placetype":"venue"
},
  "geometry": {"coordinates":[4.587306,52.299046],"type":"Point"}
}