{
  "type": "Feature",
  "properties": {
    "addr:full":"Wilgenstraat 14 Aadorp Overijssel 7611 AE",
    "addr:housenumber":"14",
    "addr:postcode":"7611 ae",
    "addr:street":"Wilgenstraat",
    "iso:country":"NL",
    "sg:address":"Wilgenstraat 14",
    "sg:city":"Aadorp",
    "sg:orig_category":"Technische Studies And Onderzoek",
    "sg:phone":"+31 546 864 092",
    "sg:postcode":"7611 AE",
    "sg:province":"Overijssel",
    "wof:name":"Johan Veneman Engineering",
    "wof:placetype":"venue"
},
  "geometry": {"coordinates":[6.630092,52.381783],"type":"Point"}
}