{
  "type": "Feature",
  "properties": {
    "addr:full":"Westhavenkd 67 Vlaardingen South Holland 3131 AG",
    "addr:housenumber":"67",
    "addr:postcode":"3131",
    "addr:street":"Westhavenkd",
    "iso:country":"NL",
    "sg:address":"Westhavenkd 67",
    "sg:city":"Vlaardingen",
    "sg:orig_category":"Projectontwikkeling",
    "sg:phone":"+31 10 486 8000",
    "sg:postcode":"3131 AG",
    "sg:province":"South Holland",
    "sg:website":"http://www.trs.nl",
    "wof:name":"Trs Bv",
    "wof:placetype":"venue"
},
  "geometry": {"coordinates":[4.345535,51.904991],"type":"Point"}
}