{
  "type": "Feature",
  "properties": {
    "addr:full":"Kloosterstr 126 Oldenzaal NL.08 7571 DD",
    "addr:housenumber":"126;nl.08",
    "addr:postcode":"7571 dd",
    "iso:country":"NL",
    "sg:address":"Kloosterstr 126",
    "sg:city":"Oldenzaal",
    "sg:orig_category":"Logopedisten",
    "sg:phone":"+31 541 519 500",
    "sg:postcode":"7571 DD",
    "sg:province":"NL.08",
    "wof:name":"Pezij, E H",
    "wof:placetype":"venue"
},
  "geometry": {"coordinates":[6.927992,52.314945],"type":"Point"}
}