{
  "type": "Feature",
  "properties": {
    "iso:country":"NL",
    "sg:address":"Mernaweg 8",
    "sg:city":"Wehe Den Hoorn",
    "sg:orig_category":"Psychotherapeuten",
    "sg:phone":"+31 595 413 521",
    "sg:postcode":"9964 AS",
    "sg:province":"Groningen",
    "wof:name":"Khams Sos",
    "wof:placetype":"venue"
},
  "geometry": {"coordinates":[6.417752,53.361031],"type":"Point"}
}