{
  "type": "Feature",
  "properties": {
    "iso:country":"NL",
    "sg:address":"Ettemastr 21",
    "sg:city":"Zeddam",
    "sg:orig_category":"Hek- En Rasterwerken",
    "sg:phone":"+31 314 651 488",
    "sg:postcode":"7038 CN",
    "sg:province":"Gelderland",
    "wof:name":"Rikken, Fa R",
    "wof:placetype":"venue"
},
  "geometry": {"coordinates":[6.25509,51.905827],"type":"Point"}
}