{
  "type": "Feature",
  "properties": {
    "addr:full":"Dennenlaan 91 Zwanenburg Noord-Holland 1161 CM",
    "addr:housenumber":"91",
    "addr:postcode":"1161 cm",
    "addr:street":"Dennenlaan",
    "iso:country":"NL",
    "sg:address":"Dennenlaan 91",
    "sg:city":"Zwanenburg",
    "sg:orig_category":"Medische Apparatuur And Prothesen Fab",
    "sg:phone":"+31 20 497 6330",
    "sg:postcode":"1161 CM",
    "sg:province":"Noord-Holland",
    "wof:name":"Tandtechniek Zwanenburg",
    "wof:placetype":"venue"
},
  "geometry": {"coordinates":[4.748407,52.377663],"type":"Point"}
}