{
  "type": "Feature",
  "properties": {
    "iso:country":"NL",
    "sg:address":"Stampioendreef 7",
    "sg:city":"Bergschenhoek",
    "sg:orig_category":"Scholen Voor Basisonderwijs",
    "sg:phone":"+31 10 521 1242",
    "sg:postcode":"2661 SR",
    "sg:province":"Zuid-Holland",
    "wof:name":"Groenehoek Openb, De",
    "wof:placetype":"venue"
},
  "geometry": {"coordinates":[4.500133,51.989536],"type":"Point"}
}