{
  "type": "Feature",
  "properties": {
    "iso:country":"NL",
    "sg:address":"Herenstraat 5",
    "sg:city":"Rijswijk",
    "sg:orig_category":"Boekenuitgeverijen",
    "sg:phone":"+31 70 399 4007",
    "sg:postcode":"2282  B",
    "sg:province":"Zuid-Holland",
    "wof:name":"Bruna",
    "wof:placetype":"venue"
},
  "geometry": {"coordinates":[4.337046,52.056389],"type":"Point"}
}