{
  "type": "Feature",
  "properties": {
    "addr:full":"Hanzewwg 19 Gouda Zuid-Holland 2803 MC",
    "addr:housenumber":"19;2803",
    "addr:postcode":"mc",
    "addr:street":"Hanzewwg",
    "iso:country":"NL",
    "sg:address":"Hanzewwg 19",
    "sg:city":"Gouda",
    "sg:orig_category":"Werving And Selectie Van Tijdelijk Personeel And Uitzendkantoren",
    "sg:phone":"+31 182 555 159",
    "sg:postcode":"2803 MC",
    "sg:province":"Zuid-Holland",
    "wof:name":"Jes Project Service B.V.",
    "wof:placetype":"venue"
},
  "geometry": {"coordinates":[4.6757721901,52.0238342285],"type":"Point"}
}