{
  "type": "Feature",
  "properties": {
    "iso:country":"NL",
    "sg:address":"De Weidedijk 4",
    "sg:city":"Langedijke",
    "sg:orig_category":"Overheidsdiensten",
    "sg:phone":"+31 516 513 534",
    "sg:postcode":"8425 SV",
    "sg:province":"Provincie Friesland",
    "wof:name":"Dorpshuus Oons Langedijke",
    "wof:placetype":"venue"
},
  "geometry": {"coordinates":[6.2891159058,52.9650306702],"type":"Point"}
}