{
  "type": "Feature",
  "properties": {
    "iso:country":"NL",
    "sg:address":"Kronenburgpromenade 30",
    "sg:city":"Arnhem",
    "sg:orig_category":"Verzekeringen",
    "sg:phone":"+31 26 323 0463",
    "sg:postcode":"6831 EA",
    "sg:province":"Gelderland",
    "wof:name":"Van Heteren Assurantien Arnhem Bv",
    "wof:placetype":"venue"
},
  "geometry": {"coordinates":[5.897193,51.958237],"type":"Point"}
}