{
  "type": "Feature",
  "properties": {
    "iso:country":"NL",
    "sg:address":"Rietvink 8",
    "sg:city":"Ridderkerk",
    "sg:orig_category":"Waterbehandeling En Waterzuiverings- Systemen",
    "sg:phone":"+31 180 420 278",
    "sg:postcode":"2986 XD",
    "sg:province":"Zuid-Holland",
    "wof:name":"Aqua In Motion",
    "wof:placetype":"venue"
},
  "geometry": {"coordinates":[4.6089758873,51.860496521],"type":"Point"}
}