{
  "type": "Feature",
  "properties": {
    "iso:country":"NL",
    "sg:address":"S V Haerlemstr 134",
    "sg:city":"Heemskerk",
    "sg:orig_category":"Autorijscholen",
    "sg:phone":"+31 251 245 643",
    "sg:postcode":"1962 VE",
    "sg:province":"Noord-Holland",
    "sg:website":"http://www.ates.nl",
    "wof:name":"Ates",
    "wof:placetype":"venue"
},
  "geometry": {"coordinates":[4.66983,52.513546],"type":"Point"}
}