{
  "type": "Feature",
  "properties": {
    "addr:full":"Edisonstraat 17 Zoetermeer Zuid-Holland 2723 RS",
    "addr:housenumber":"17",
    "addr:postcode":"2723 rs",
    "addr:street":"Edisonstraat",
    "iso:country":"NL",
    "sg:address":"Edisonstraat 17",
    "sg:city":"Zoetermeer",
    "sg:orig_category":"Binnenhuisarchitecten",
    "sg:phone":"+31 79 341 2253",
    "sg:postcode":"2723 RS",
    "sg:province":"Zuid-Holland",
    "wof:name":"Van Der Goes Projektinrichting Bv",
    "wof:placetype":"venue"
},
  "geometry": {"coordinates":[4.521898,52.0616],"type":"Point"}
}