{
  "type": "Feature",
  "properties": {
    "addr:full":"Stationswg 114 Drachten Provincie Friesland 9201 GS",
    "addr:housenumber":"114",
    "addr:postcode":"9201 gs",
    "addr:street":"Provincie Friesland",
    "iso:country":"NL",
    "sg:address":"Stationswg 114",
    "sg:city":"Drachten",
    "sg:orig_category":"Banken",
    "sg:phone":"+31 512 545 454",
    "sg:postcode":"9201 GS",
    "sg:province":"Provincie Friesland",
    "wof:name":"Regio Bank",
    "wof:placetype":"venue"
},
  "geometry": {"coordinates":[6.097125,53.114002],"type":"Point"}
}