{
  "type": "Feature",
  "properties": {
    "iso:country":"NL",
    "sg:address":"Akerstr N 74",
    "sg:city":"Hoensbroek",
    "sg:orig_category":"Artsen - Huisartsen",
    "sg:phone":"+31 45 521 4821",
    "sg:postcode":"6431 HN",
    "sg:province":"Limburg",
    "wof:name":"Gezondheidscentrum Hoensbroek-Noord",
    "wof:placetype":"venue"
},
  "geometry": {"coordinates":[5.933073,50.931919],"type":"Point"}
}