{
  "type": "Feature",
  "properties": {
    "iso:country":"NL",
    "sg:address":"David Van Bourgondieweg 1",
    "sg:city":"Wijk Bij Duurstede",
    "sg:classifiers":[
        {
            "category":"Education",
            "subcategory":"Preschool",
            "type":"Public Place"
        }
    ],
    "sg:phone":"+31 343 597 025",
    "sg:postcode":"3961 VZ",
    "sg:province":"Utrecht",
    "sg:tags":[
        "kleuteronderwijs",
        "basis-"
    ],
    "wof:name":"Openbare Basisschool De Opstap",
    "wof:placetype":"venue"
},
  "geometry": {"coordinates":[5.341188,51.973606],"type":"Point"}
}