{
  "type": "Feature",
  "properties": {
    "addr:full":"Rademakerstraat 13 Soesterberg Utrecht 3769 BB",
    "addr:housenumber":"13",
    "addr:postcode":"3769 bb",
    "addr:street":"Rademakerstraat",
    "iso:country":"NL",
    "sg:address":"Rademakerstraat 13",
    "sg:city":"Soesterberg",
    "sg:orig_category":"Meubelzaken, Woning- And Keukeninrichting",
    "sg:phone":"+31 346 351 845",
    "sg:postcode":"3769 BB",
    "sg:province":"Utrecht",
    "wof:name":"De Bedstee",
    "wof:placetype":"venue"
},
  "geometry": {"coordinates":[5.284252,52.120678],"type":"Point"}
}