{
  "type": "Feature",
  "properties": {
    "iso:country":"NL",
    "sg:address":"Breehorn 100",
    "sg:city":"Lelystad",
    "sg:orig_category":"Fotostudio'S And Fotografen",
    "sg:phone":"+31 320 244 203",
    "sg:postcode":"8223 CS",
    "sg:province":"Flevoland",
    "wof:name":"G.S. Vaklaboratorium",
    "wof:placetype":"venue"
},
  "geometry": {"coordinates":[5.491877,52.522156],"type":"Point"}
}