{
  "type": "Feature",
  "properties": {
    "addr:full":"Seeduneweg 1 Schiermonnikoog Friesland 9166 RX",
    "addr:housenumber":"1",
    "addr:postcode":"9166 rx",
    "addr:street":"Seeduneweg",
    "iso:country":"NL",
    "sg:address":"Seeduneweg 1",
    "sg:city":"Schiermonnikoog",
    "sg:orig_category":"Kampeerterreinen",
    "sg:phone":"+31 519 531 398",
    "sg:postcode":"9166 RX",
    "sg:province":"Friesland",
    "wof:name":"Camping Seedune Bv",
    "wof:placetype":"venue"
},
  "geometry": {"coordinates":[6.1595711708,53.4848518372],"type":"Point"}
}