{
  "type": "Feature",
  "properties": {
    "addr:full":"Postbus 467 Hengelo Ov 7550 AL",
    "addr:housenumber":"467",
    "addr:postcode":"7550",
    "addr:street":"Postbus;Ov",
    "iso:country":"NL",
    "sg:address":"Postbus 467",
    "sg:city":"Hengelo Ov",
    "sg:orig_category":"Webdesign Bureaus",
    "sg:phone":"+31 74 243 9021",
    "sg:postcode":"7550 AL",
    "sg:website":"http://www.aerosoldesign.nl",
    "wof:name":"Aerosoldesign",
    "wof:placetype":"venue"
},
  "geometry": {"coordinates":[6.7897100449,52.266330719],"type":"Point"}
}