{
  "type": "Feature",
  "properties": {
    "addr:full":"Kanaalweg 14 Mook Limburg 6585 AX",
    "addr:housenumber":"14",
    "addr:postcode":"6585 ax",
    "addr:street":"Kanaalweg",
    "iso:country":"NL",
    "sg:address":"Kanaalweg 14",
    "sg:city":"Mook",
    "sg:orig_category":"Watersport-, Sport- And Kampeerbenodigdheden Verhuur",
    "sg:phone":"+31 24 696 2310",
    "sg:postcode":"6585 AX",
    "sg:province":"Limburg",
    "wof:name":"Dolfijn Watersport",
    "wof:placetype":"venue"
},
  "geometry": {"coordinates":[5.885474205,51.7466011047],"type":"Point"}
}