{
  "type": "Feature",
  "properties": {
    "addr:full":"Hoogte Kadk 400 Amsterdam North Holland 1018 BW",
    "addr:housenumber":"400",
    "addr:postcode":"1018 bw",
    "addr:street":"Hoogte Kadk",
    "iso:country":"NL",
    "sg:address":"Hoogte Kadk 400",
    "sg:city":"Amsterdam",
    "sg:orig_category":"Milieu",
    "sg:phone":"+31 20 421 5966",
    "sg:postcode":"1018 BW",
    "sg:province":"North Holland",
    "wof:name":"Milieuzorg Amsterdam",
    "wof:placetype":"venue"
},
  "geometry": {"coordinates":[4.921532,52.367016],"type":"Point"}
}