{
  "type": "Feature",
  "properties": {
    "addr:full":"Ysselmeerstr 6 Huizen Noord-Holland 1271 AA",
    "addr:housenumber":"6",
    "addr:postcode":"1271 aa",
    "addr:street":"Ysselmeerstr",
    "iso:country":"NL",
    "sg:address":"Ysselmeerstr 6",
    "sg:city":"Huizen",
    "sg:orig_category":"Kunstenaars- Benodigdheden",
    "sg:phone":"+31 35 528 5488",
    "sg:postcode":"1271 AA",
    "sg:province":"Noord-Holland",
    "wof:name":"Imperliner Bv",
    "wof:placetype":"venue"
},
  "geometry": {"coordinates":[5.238241,52.305901],"type":"Point"}
}