{
  "type": "Feature",
  "properties": {
    "addr:full":"Meerweg 7 Kronenberg Schleswig-Holstein 5976 NS",
    "addr:housenumber":"7",
    "addr:postcode":"5976 ns",
    "addr:street":"Meerweg",
    "iso:country":"NL",
    "sg:address":"Meerweg 7",
    "sg:city":"Kronenberg",
    "sg:classifiers":[
        {
            "category":"Education",
            "subcategory":"Preschool",
            "type":"Public Place"
        }
    ],
    "sg:phone":"+31 77 467 1875",
    "sg:postcode":"5976 NS",
    "sg:province":"Schleswig-Holstein",
    "sg:tags":[
        "kleuteronderwijs",
        "basis-"
    ],
    "wof:name":"D'N Eerste Stap",
    "wof:placetype":"venue"
},
  "geometry": {"coordinates":[9.38505,54.403831],"type":"Point"}
}