{
  "type": "Feature",
  "properties": {
    "addr:full":"Nederlandpln 106 Eindhoven North Brabant 5628 AJ",
    "addr:housenumber":"106",
    "addr:postcode":"5628 aj",
    "iso:country":"NL",
    "sg:address":"Nederlandpln 106",
    "sg:city":"Eindhoven",
    "sg:orig_category":"Kappers",
    "sg:phone":"+31 40 242 0226",
    "sg:postcode":"5628 AJ",
    "sg:province":"North Brabant",
    "wof:name":"Team",
    "wof:placetype":"venue"
},
  "geometry": {"coordinates":[5.463136,51.478855],"type":"Point"}
}