{
  "type": "Feature",
  "properties": {
    "iso:country":"NL",
    "sg:address":"Postjeskd 149",
    "sg:city":"Amsterdam",
    "sg:orig_category":"Geluidsopnamestudio'S",
    "sg:phone":"+31 20 419 2054",
    "sg:postcode":"1058 DN",
    "sg:province":"Noord-Holland",
    "wof:name":"Cablejuice",
    "wof:placetype":"venue"
},
  "geometry": {"coordinates":[4.850256,52.361374],"type":"Point"}
}