{
  "type": "Feature",
  "properties": {
    "iso:country":"NL",
    "sg:address":"Hoofdwg 132",
    "sg:city":"Nyensleek",
    "sg:orig_category":"Onderhoudswerken",
    "sg:phone":"+31 521 381 766",
    "sg:postcode":"8383 EK",
    "sg:province":"Provincie Drenthe",
    "wof:name":"Hkb",
    "wof:placetype":"venue"
},
  "geometry": {"coordinates":[6.16815,52.837582],"type":"Point"}
}