{
  "type": "Feature",
  "properties": {
    "addr:full":"42E Laan 10 Wildervank Groningen 9648 GH",
    "addr:housenumber":"10",
    "addr:postcode":"9648 gh",
    "addr:street":"42E Laan",
    "iso:country":"NL",
    "sg:address":"42E Laan 10",
    "sg:city":"Wildervank",
    "sg:orig_category":"Voegwerken",
    "sg:phone":"+31 598 626 522",
    "sg:postcode":"9648 GH",
    "sg:province":"Groningen",
    "wof:name":"Laan, Bart Van Der",
    "wof:placetype":"venue"
},
  "geometry": {"coordinates":[6.852853,53.064884],"type":"Point"}
}