{
  "type": "Feature",
  "properties": {
    "addr:full":"C Petitwg 14 Teteringen North Brabant 4847 NW",
    "addr:housenumber":"14",
    "addr:postcode":"4847 nw",
    "iso:country":"NL",
    "sg:address":"C Petitwg 14",
    "sg:city":"Teteringen",
    "sg:orig_category":"Loodgieters",
    "sg:phone":"+31 76 581 2187",
    "sg:postcode":"4847 NW",
    "sg:province":"North Brabant",
    "wof:name":"Flipsen - Aarts Bv",
    "wof:placetype":"venue"
},
  "geometry": {"coordinates":[4.814294,51.610271],"type":"Point"}
}