{
  "type": "Feature",
  "properties": {
    "addr:full":"Dr Nolensln 113A Sittard Limburg 6136 GM",
    "addr:housenumber":"113a",
    "addr:postcode":"6136 gm",
    "addr:street":"Sittard Limburg",
    "iso:country":"NL",
    "sg:address":"Dr Nolensln 113A",
    "sg:city":"Sittard",
    "sg:orig_category":"Verf En Lak - Fabrieken En Groothandel",
    "sg:phone":"+31 46 451 2760",
    "sg:postcode":"6136 GM",
    "sg:province":"Limburg",
    "wof:name":"Limburg Bv",
    "wof:placetype":"venue"
},
  "geometry": {"coordinates":[5.873038,51.016354],"type":"Point"}
}