{
  "type": "Feature",
  "properties": {
    "iso:country":"NL",
    "sg:address":"Utrechtseweg 108",
    "sg:city":"Oosterbeek",
    "sg:orig_category":"Drogisterijen",
    "sg:phone":"+31 26 333 2330",
    "sg:postcode":"6862 AP",
    "sg:province":"Gelderland",
    "wof:name":"Kruidvat",
    "wof:placetype":"venue"
},
  "geometry": {"coordinates":[5.8466391563,51.9867324829],"type":"Point"}
}