{
  "type": "Feature",
  "properties": {
    "addr:full":"Hanenberglanden 128 Enschede Overijssel 7542 EC",
    "addr:housenumber":"128",
    "addr:postcode":"7542 ec",
    "addr:street":"Hanenberglanden",
    "iso:country":"NL",
    "sg:address":"Hanenberglanden 128",
    "sg:city":"Enschede",
    "sg:orig_category":"Vertaalbureaus",
    "sg:phone":"+31 53 477 1890",
    "sg:postcode":"7542 EC",
    "sg:province":"Overijssel",
    "wof:name":"Budapest Tolk- En Vertaalbureau",
    "wof:placetype":"venue"
},
  "geometry": {"coordinates":[6.908723,52.188957],"type":"Point"}
}