{
  "type": "Feature",
  "properties": {
    "addr:full":"Postbus 2016 Emmen Provincie Drenthe 7801 CA",
    "addr:postcode":"2016 emmen;7801 ca",
    "addr:street":"Postbus;Drenthe",
    "iso:country":"NL",
    "sg:address":"Postbus 2016",
    "sg:city":"Emmen",
    "sg:orig_category":"Projectontwikkeling",
    "sg:phone":"+31 591 633 266",
    "sg:postcode":"7801 CA",
    "sg:province":"Provincie Drenthe",
    "wof:name":"Boer Bv, De",
    "wof:placetype":"venue"
},
  "geometry": {"coordinates":[6.89971,52.795959],"type":"Point"}
}