{
  "type": "Feature",
  "properties": {
    "addr:full":"Dwarsgracht 37 Giethoorn Overijssel 8355 CV",
    "addr:housenumber":"37",
    "addr:postcode":"8355 cv",
    "addr:street":"Dwarsgracht",
    "iso:country":"NL",
    "sg:address":"Dwarsgracht 37",
    "sg:city":"Giethoorn",
    "sg:orig_category":"Huizensloop And Bouwrijp Maken",
    "sg:phone":"+31 521 361 942",
    "sg:postcode":"8355 CV",
    "sg:province":"Overijssel",
    "wof:name":"W. Piek Baggerbedrijf",
    "wof:placetype":"venue"
},
  "geometry": {"coordinates":[6.037093,52.725052],"type":"Point"}
}