{
  "type": "Feature",
  "properties": {
    "addr:full":"Boskamp 24 Olst Overijssel 8121 CX",
    "addr:housenumber":"24",
    "addr:postcode":"8121 cx",
    "addr:street":"Boskamp",
    "iso:country":"NL",
    "sg:address":"Boskamp 24",
    "sg:city":"Olst",
    "sg:orig_category":"Zalenverhuur",
    "sg:phone":"+31 570 561 412",
    "sg:postcode":"8121 CX",
    "sg:province":"Overijssel",
    "wof:name":"Ijsseldijk",
    "wof:placetype":"venue"
},
  "geometry": {"coordinates":[6.130272,52.331043],"type":"Point"}
}