{
  "type": "Feature",
  "properties": {
    "addr:full":"Wykerstrwg 217 Velsen Noord Noord-Holland 1951 EE",
    "addr:housenumber":"217",
    "addr:postcode":"1951 ee",
    "addr:street":"Velsen",
    "iso:country":"NL",
    "sg:address":"Wykerstrwg 217",
    "sg:city":"Velsen Noord",
    "sg:orig_category":"Huishoudelijke Apparaten En Artikelen",
    "sg:phone":"+31 251 212 131",
    "sg:postcode":"1951 EE",
    "sg:province":"Noord-Holland",
    "wof:name":"Arxhoek Vof",
    "wof:placetype":"venue"
},
  "geometry": {"coordinates":[4.645905,52.472397],"type":"Point"}
}