{
  "type": "Feature",
  "properties": {
    "addr:full":"J Perkstr 13 Papendrecht Zuid-Holland 3351 CP",
    "addr:housenumber":"13",
    "addr:postcode":"3351 cp",
    "addr:street":"Papendrecht",
    "iso:country":"NL",
    "sg:address":"J Perkstr 13",
    "sg:city":"Papendrecht",
    "sg:orig_category":"Organisatiebureaus",
    "sg:phone":"+31 78 642 6646",
    "sg:postcode":"3351 CP",
    "sg:province":"Zuid-Holland",
    "sg:website":"http://www.eventpromotions.nl",
    "wof:name":"Events Promotions",
    "wof:placetype":"venue"
},
  "geometry": {"coordinates":[4.6765060425,51.8338088989],"type":"Point"}
}