{
  "type": "Feature",
  "properties": {
    "iso:country":"NL",
    "sg:address":"Postbus 255",
    "sg:city":"Aalsmeer",
    "sg:classifiers":[
        {
            "category":"Wholesale",
            "subcategory":"Meat",
            "type":"Manufacturing & Wholesale Goods"
        }
    ],
    "sg:phone":"+31 297 219 190",
    "sg:postcode":"1430 AG",
    "sg:province":"North Holland",
    "sg:tags":[
        "regeltechniek",
        "en",
        "meet-"
    ],
    "sg:website":"http://www.bls-bv.com",
    "wof:name":"Bls Bv",
    "wof:placetype":"venue"
},
  "geometry": {"coordinates":[4.749068,52.266991],"type":"Point"}
}