{
  "type": "Feature",
  "properties": {
    "addr:full":"Brugstraat 4 Wilhelminadorp Zeeland 4475 AP",
    "addr:housenumber":"4",
    "addr:postcode":"4475 ap",
    "addr:street":"Brugstraat",
    "iso:country":"NL",
    "sg:address":"Brugstraat 4",
    "sg:city":"Wilhelminadorp",
    "sg:orig_category":"Overheidsdiensten",
    "sg:phone":"+31 113 216 984",
    "sg:postcode":"4475 AP",
    "sg:province":"Zeeland",
    "wof:name":"Het Wilhelminahuis",
    "wof:placetype":"venue"
},
  "geometry": {"coordinates":[3.8980178833,51.5299377441],"type":"Point"}
}