{
  "type": "Feature",
  "properties": {
    "addr:full":"Akkerheide 22 Kerkrade Limburg 6463 DA",
    "addr:housenumber":"22",
    "addr:postcode":"6463 da",
    "addr:street":"Akkerheide",
    "iso:country":"NL",
    "sg:address":"Akkerheide 22",
    "sg:city":"Kerkrade",
    "sg:orig_category":"Kappers",
    "sg:phone":"+31 45 545 4088",
    "sg:postcode":"6463 DA",
    "sg:province":"Limburg",
    "wof:name":"N.A.P. Nelissen",
    "wof:placetype":"venue"
},
  "geometry": {"coordinates":[6.064479,50.877483],"type":"Point"}
}