{
  "type": "Feature",
  "properties": {
    "addr:full":"Zuidwal 94 S Gravenhage Zuid-Holland 2512 XV",
    "addr:housenumber":"94;gravenhage",
    "addr:postcode":"2512 xv",
    "addr:street":"Zuidwal;S",
    "iso:country":"NL",
    "sg:address":"Zuidwal 94",
    "sg:city":"S Gravenhage",
    "sg:orig_category":"Verenigingen En Stichtingen",
    "sg:phone":"+31 70 361 6689",
    "sg:postcode":"2512 XV",
    "sg:province":"Zuid-Holland",
    "wof:name":"Chinese Brug, Sticht De",
    "wof:placetype":"venue"
},
  "geometry": {"coordinates":[4.30618,52.073212],"type":"Point"}
}