{
  "type": "Feature",
  "properties": {
    "addr:full":"De Wieken 30 Malden Gelderland 6581 DE",
    "addr:housenumber":"30;6581",
    "addr:street":"De Wieken;Gelderland;De",
    "iso:country":"NL",
    "sg:address":"De Wieken 30",
    "sg:city":"Malden",
    "sg:orig_category":"Grafische Bedrijven",
    "sg:phone":"+31 24 358 3029",
    "sg:postcode":"6581 DE",
    "sg:province":"Gelderland",
    "wof:name":"Joma",
    "wof:placetype":"venue"
},
  "geometry": {"coordinates":[5.853141,51.787643],"type":"Point"}
}