{
  "type": "Feature",
  "properties": {
    "addr:full":"Brugstraat 39 Stadskanaal Groningen 9503 HM",
    "addr:housenumber":"39",
    "addr:postcode":"9503 hm",
    "addr:street":"Brugstraat",
    "iso:country":"NL",
    "sg:address":"Brugstraat 39",
    "sg:city":"Stadskanaal",
    "sg:orig_category":"Kappers",
    "sg:phone":"+31 599 613 770",
    "sg:postcode":"9503 HM",
    "sg:province":"Groningen",
    "wof:name":"L Ramaker",
    "wof:placetype":"venue"
},
  "geometry": {"coordinates":[6.957328,52.975479],"type":"Point"}
}