{
  "type": "Feature",
  "properties": {
    "iso:country":"NL",
    "sg:address":"Frans Halsstraat 27",
    "sg:city":"Ridderkerk",
    "sg:orig_category":"Kappers",
    "sg:phone":"+31 180 427 565",
    "sg:postcode":"2981 CD",
    "sg:province":"South Holland",
    "wof:name":"Kapsalon Coupe & Colour",
    "wof:placetype":"venue"
},
  "geometry": {"coordinates":[4.5958819389,51.8705444336],"type":"Point"}
}