{
  "type": "Feature",
  "properties": {
    "iso:country":"NL",
    "sg:address":"Kerkstr 31",
    "sg:city":"Baexem",
    "sg:orig_category":"Pottenbakkerijen",
    "sg:phone":"+31 475 453 070",
    "sg:postcode":"6095 BD",
    "sg:province":"Limburg",
    "wof:name":"Dutch Connection Ceramics",
    "wof:placetype":"venue"
},
  "geometry": {"coordinates":[5.879087,51.227779],"type":"Point"}
}