{
  "type": "Feature",
  "properties": {
    "addr:full":"De Mors 115/117 Ootmarsum Overijssel 7631 BA",
    "addr:housenumber":"115 / 117",
    "addr:postcode":"7631 ba",
    "addr:street":"De Mors",
    "iso:country":"NL",
    "sg:address":"De Mors 115/117",
    "sg:city":"Ootmarsum",
    "sg:orig_category":"Pompen - Fabrieken",
    "sg:phone":"+31 541 291 741",
    "sg:postcode":"7631 BA",
    "sg:province":"Overijssel",
    "sg:website":"http://www.kabra.nl",
    "wof:name":"Kabra Buizen",
    "wof:placetype":"venue"
},
  "geometry": {"coordinates":[6.911,52.412861],"type":"Point"}
}