{
  "type": "Feature",
  "properties": {
    "addr:full":"Klaverhof 146 Alphen Aan Den Ryn Zuid-Holland 2403 XJ",
    "addr:housenumber":"146",
    "addr:postcode":"2403 xj",
    "addr:street":"Klaverhof;Aan Den Ryn",
    "iso:country":"NL",
    "sg:address":"Klaverhof 146",
    "sg:city":"Alphen Aan Den Ryn",
    "sg:orig_category":"Partyservice",
    "sg:phone":"+31 172 437 642",
    "sg:postcode":"2403 XJ",
    "sg:province":"Zuid-Holland",
    "wof:name":"Topaz",
    "wof:placetype":"venue"
},
  "geometry": {"coordinates":[4.685444,52.14344],"type":"Point"}
}