{
  "type": "Feature",
  "properties": {
    "addr:full":"Linneauskade 2 Amsterdam Noord-Holland 1098 BC",
    "addr:housenumber":"2",
    "addr:postcode":"1098 bc",
    "addr:street":"Linneauskade",
    "iso:country":"NL",
    "sg:address":"Linneauskade 2",
    "sg:city":"Amsterdam",
    "sg:classifiers":[
        {
            "category":"Fast Food",
            "type":"Food & Drink"
        }
    ],
    "sg:phone":"+31 20 463 9140",
    "sg:postcode":"1098 BC",
    "sg:province":"Noord-Holland",
    "sg:tags":[
        "afhaal",
        "restaurant"
    ],
    "wof:name":"Kediri",
    "wof:placetype":"venue"
},
  "geometry": {"coordinates":[4.92885,52.355087],"type":"Point"}
}