{
  "type": "Feature",
  "properties": {
    "addr:full":"Wymerts 14 Zwolle NL.08 8032 MB",
    "addr:housenumber":"14",
    "addr:postcode":"8032 mb",
    "addr:street":"Wymerts",
    "iso:country":"NL",
    "sg:address":"Wymerts 14",
    "sg:city":"Zwolle",
    "sg:orig_category":"Adviesbureaus Bouwkunde",
    "sg:phone":"+31 38 454 7385",
    "sg:postcode":"8032 MB",
    "sg:province":"NL.08",
    "wof:name":"Hamming",
    "wof:placetype":"venue"
},
  "geometry": {"coordinates":[6.09413,52.5355],"type":"Point"}
}