{
  "type": "Feature",
  "properties": {
    "addr:full":"Vogelzang 7 Maastricht Limburg 6229 VM",
    "addr:housenumber":"7",
    "addr:postcode":"6229 vm",
    "addr:street":"Vogelzang",
    "iso:country":"NL",
    "sg:address":"Vogelzang 7",
    "sg:city":"Maastricht",
    "sg:orig_category":"Warenhuizen",
    "sg:phone":"+31 43 450 5830",
    "sg:postcode":"6229 VM",
    "sg:province":"Limburg",
    "wof:name":"Boerenbond",
    "wof:placetype":"venue"
},
  "geometry": {"coordinates":[5.7160792351,50.825252533],"type":"Point"}
}