{
  "type": "Feature",
  "properties": {
    "addr:full":"Poststraat 4 Delfzijl Groningen 9934 BE",
    "addr:housenumber":"4",
    "addr:postcode":"9934",
    "addr:street":"Poststraat",
    "iso:country":"NL",
    "sg:address":"Poststraat 4",
    "sg:city":"Delfzijl",
    "sg:orig_category":"Boekhandels",
    "sg:phone":"+31 596 633 130",
    "sg:postcode":"9934 BE",
    "sg:province":"Groningen",
    "wof:name":"De Boekelier",
    "wof:placetype":"venue"
},
  "geometry": {"coordinates":[6.92749,53.331604],"type":"Point"}
}