{
  "type": "Feature",
  "properties": {
    "addr:full":"Kamperfoelie 18 Tiel Gelderland 4007 TL",
    "addr:housenumber":"18",
    "addr:postcode":"4007 tl",
    "addr:street":"Kamperfoelie;Gelderland",
    "iso:country":"NL",
    "sg:address":"Kamperfoelie 18",
    "sg:city":"Tiel",
    "sg:orig_category":"Opticiens",
    "sg:phone":"+31 344 626 642",
    "sg:postcode":"4007 TL",
    "sg:province":"Gelderland",
    "wof:name":"Es, Van",
    "wof:placetype":"venue"
},
  "geometry": {"coordinates":[5.4001507759,51.8708267212],"type":"Point"}
}