{
  "type": "Feature",
  "properties": {
    "iso:country":"NL",
    "sg:address":"Reitscheweg 28",
    "sg:city":"'S Hertogenbosch",
    "sg:orig_category":"Verhuur Gereedschapsmachines And Gereedschappen",
    "sg:phone":"+31 73 642 0255",
    "sg:postcode":"5232 BZ",
    "sg:province":"Noord-Brabant",
    "wof:name":"Boels Verhuur",
    "wof:placetype":"venue"
},
  "geometry": {"coordinates":[5.338052,51.710369],"type":"Point"}
}