{
  "type": "Feature",
  "properties": {
    "addr:full":"Appelgaarde 67 Voorburg South Holland 2272 TB",
    "addr:housenumber":"67",
    "addr:postcode":"2272 tb",
    "addr:street":"Appelgaarde",
    "iso:country":"NL",
    "sg:address":"Appelgaarde 67",
    "sg:city":"Voorburg",
    "sg:orig_category":"Kantoorartikelen",
    "sg:phone":"+31 70 327 1027",
    "sg:postcode":"2272 TB",
    "sg:province":"South Holland",
    "wof:name":"As Kantoormachines",
    "wof:placetype":"venue"
},
  "geometry": {"coordinates":[4.3716540337,52.0888977051],"type":"Point"}
}