{
  "type": "Feature",
  "properties": {
    "addr:full":"Sloterwg 1269 Amsterdam Noord-Holland 1066 CJ",
    "addr:housenumber":"1269",
    "addr:postcode":"1066 cj",
    "iso:country":"NL",
    "sg:address":"Sloterwg 1269",
    "sg:city":"Amsterdam",
    "sg:classifiers":[
        {
            "category":"Retail",
            "subcategory":"Auto Repair",
            "type":"Services"
        }
    ],
    "sg:phone":"+31 20 615 3818",
    "sg:postcode":"1066 CJ",
    "sg:province":"Noord-Holland",
    "sg:tags":[
        "garage"
    ],
    "wof:name":"Kuykhoven",
    "wof:placetype":"venue"
},
  "geometry": {"coordinates":[4.79699,52.341499],"type":"Point"}
}