{
  "type": "Feature",
  "properties": {
    "addr:full":"C Houtmanstr 7 Schiedam Zuid-Holland 3124 LB",
    "addr:housenumber":"7",
    "addr:postcode":"3124 lb",
    "addr:street":"Houtmanstr",
    "iso:country":"NL",
    "sg:address":"C Houtmanstr 7",
    "sg:city":"Schiedam",
    "sg:orig_category":"Fitnesscentra",
    "sg:phone":"+31 10 471 3838",
    "sg:postcode":"3124 LB",
    "sg:province":"Zuid-Holland",
    "wof:name":"Olympia",
    "wof:placetype":"venue"
},
  "geometry": {"coordinates":[4.381023,51.937622],"type":"Point"}
}