{
  "type": "Feature",
  "properties": {
    "addr:full":"Vechtstr 7 Oss Wisconsin 5347 KH",
    "addr:housenumber":"7",
    "addr:postcode":"5347 kh",
    "addr:street":"Vechtstr",
    "iso:country":"NL",
    "sg:address":"Vechtstr 7",
    "sg:city":"Oss",
    "sg:orig_category":"Motoren - Onderdelen",
    "sg:phone":"+31 412 626 947",
    "sg:postcode":"5347 KH",
    "sg:province":"Wisconsin",
    "sg:website":"http://www.polini-minibikes.nl",
    "wof:name":"Polini Vacirca",
    "wof:placetype":"venue"
},
  "geometry": {"coordinates":[-91.22442599999999,44.577396],"type":"Point"}
}