{
  "type": "Feature",
  "properties": {
    "addr:full":"Nw Ebbingestr 58 Groningen Groningen 9712 NM",
    "addr:housenumber":"58",
    "addr:postcode":"9712",
    "iso:country":"NL",
    "sg:address":"Nw Ebbingestr 58",
    "sg:city":"Groningen",
    "sg:orig_category":"Herenkleding",
    "sg:phone":"+31 50 312 9352",
    "sg:postcode":"9712 NM",
    "sg:province":"Groningen",
    "sg:website":"http://www.allesingroningen.nl",
    "wof:name":"Oosterhoff Mannenmode",
    "wof:placetype":"venue"
},
  "geometry": {"coordinates":[6.562818,53.224075],"type":"Point"}
}