{
  "type": "Feature",
  "properties": {
    "addr:full":"Huizerwg 188 , (Mobiele Telefoon) Bussum Noord-Holland 1402 AN",
    "addr:housenumber":"188",
    "addr:postcode":"an",
    "addr:street":"Mobiele Telefoon",
    "iso:country":"NL",
    "sg:address":"Huizerwg 188 , (Mobiele Telefoon)",
    "sg:city":"Bussum",
    "sg:orig_category":"Woningstoffeerders",
    "sg:phone":"+31 6 51810593",
    "sg:postcode":"1402 AN",
    "sg:province":"Noord-Holland",
    "wof:name":"Dijkman",
    "wof:placetype":"venue"
},
  "geometry": {"coordinates":[5.1818590164,52.2771339417],"type":"Point"}
}