{
  "type": "Feature",
  "properties": {
    "addr:full":"K Doormanln 14 Aerdenhout North Holland 2111 XD",
    "addr:housenumber":"14",
    "addr:postcode":"2111 xd",
    "addr:street":"Doormanln",
    "iso:country":"NL",
    "sg:address":"K Doormanln 14",
    "sg:city":"Aerdenhout",
    "sg:orig_category":"Beeldende Kunstenaars",
    "sg:phone":"+31 23 524 2016",
    "sg:postcode":"2111 XD",
    "sg:province":"North Holland",
    "wof:name":"Mourik-Pohl, A Van",
    "wof:placetype":"venue"
},
  "geometry": {"coordinates":[4.598078,52.372162],"type":"Point"}
}