{
  "type": "Feature",
  "properties": {
    "addr:full":"Ceramstr 2 Dordrecht Zuid-Holland 3312 SH",
    "addr:housenumber":"2",
    "addr:postcode":"3312 sh",
    "addr:street":"Ceramstr",
    "iso:country":"NL",
    "sg:address":"Ceramstr 2",
    "sg:city":"Dordrecht",
    "sg:orig_category":"Journalisten Freelance",
    "sg:phone":"+31 78 613 3976",
    "sg:postcode":"3312 SH",
    "sg:province":"Zuid-Holland",
    "wof:name":"Dekker, Geert",
    "wof:placetype":"venue"
},
  "geometry": {"coordinates":[4.688715,51.809471],"type":"Point"}
}