{
  "type": "Feature",
  "properties": {
    "iso:country":"NL",
    "sg:address":"Ring 54-56",
    "sg:city":"Middelharnis",
    "sg:orig_category":"Verzekeringen - Verzekeringskantoren",
    "sg:phone":"+31 187 485 537",
    "sg:postcode":"3241 CS",
    "sg:province":"South Holland",
    "sg:website":"http://www.vandis.nl",
    "wof:name":"Dis Assurantiekantoor, Van",
    "wof:placetype":"venue"
},
  "geometry": {"coordinates":[4.165422,51.757103],"type":"Point"}
}