{
  "type": "Feature",
  "properties": {
    "addr:full":"Martinuswg 19 Herwen Gelderland 6914 AL",
    "addr:housenumber":"19",
    "addr:postcode":"6914",
    "addr:street":"Martinuswg;Gelderland",
    "iso:country":"NL",
    "sg:address":"Martinuswg 19",
    "sg:city":"Herwen",
    "sg:orig_category":"Horecabenodigdheden",
    "sg:phone":"+31 316 248 716",
    "sg:postcode":"6914 AL",
    "sg:province":"Gelderland",
    "wof:name":"Kuper",
    "wof:placetype":"venue"
},
  "geometry": {"coordinates":[6.101465,51.884571],"type":"Point"}
}