{
  "type": "Feature",
  "properties": {
    "iso:country":"NL",
    "sg:address":"Quaedvliegln 5",
    "sg:city":"Landgraaf",
    "sg:orig_category":"Verzekeringen - Verzekeringskantoren",
    "sg:phone":"+31 45 531 3008",
    "sg:postcode":"6371 HA",
    "sg:province":"Limburg",
    "wof:name":"Funcken",
    "wof:placetype":"venue"
},
  "geometry": {"coordinates":[6.013706,50.896366],"type":"Point"}
}