{
  "type": "Feature",
  "properties": {
    "addr:full":"Ceintuurbaan 14 Deventer Overijssel 7415 AL",
    "addr:housenumber":"14",
    "addr:postcode":"7415 al",
    "addr:street":"Ceintuurbaan",
    "iso:country":"NL",
    "sg:address":"Ceintuurbaan 14",
    "sg:city":"Deventer",
    "sg:orig_category":"Artsen - Huisartsen",
    "sg:phone":"+31 570 626 118",
    "sg:postcode":"7415 AL",
    "sg:province":"Overijssel",
    "wof:name":"Komry & J P Van Hijst, L",
    "wof:placetype":"venue"
},
  "geometry": {"coordinates":[6.163565,52.263008],"type":"Point"}
}