{
  "type": "Feature",
  "properties": {
    "addr:full":"Haven 72 Schoonhoven South Holland 2871 CR",
    "addr:housenumber":"72",
    "addr:postcode":"2871 cr",
    "addr:street":"Haven",
    "iso:country":"NL",
    "sg:address":"Haven 72",
    "sg:city":"Schoonhoven",
    "sg:classifiers":[
        {
            "category":"Communications",
            "subcategory":"Television Station",
            "type":"Services"
        }
    ],
    "sg:phone":"+31 182 386 897",
    "sg:postcode":"2871 CR",
    "sg:province":"South Holland",
    "sg:tags":[
        "video",
        "audio",
        "verhuur"
    ],
    "wof:name":"Filmclub Beverly Hills 1",
    "wof:placetype":"venue"
},
  "geometry": {"coordinates":[4.851345,51.945717],"type":"Point"}
}