{
  "type": "Feature",
  "properties": {
    "addr:full":"St Theresiastr 38 Eindhoven Noord-Brabant 5652 ET",
    "addr:housenumber":"38",
    "addr:postcode":"5652 et",
    "iso:country":"NL",
    "sg:address":"St Theresiastr 38",
    "sg:city":"Eindhoven",
    "sg:orig_category":"Verhuur",
    "sg:phone":"+31 40 252 7707",
    "sg:postcode":"5652 ET",
    "sg:province":"Noord-Brabant",
    "sg:website":"http://www.aartstoiletcabine.nl",
    "wof:name":"Aarts Toiletcabines",
    "wof:placetype":"venue"
},
  "geometry": {"coordinates":[5.441134,51.438354],"type":"Point"}
}