{
  "type": "Feature",
  "properties": {
    "iso:country":"NL",
    "sg:address":"Roggewg 59",
    "sg:city":"Hengelo Ov",
    "sg:orig_category":"Homeopathie",
    "sg:phone":"+31 74 259 4994",
    "sg:postcode":"7552 EK",
    "sg:province":"Overijssel",
    "wof:name":"Jongen, Paula",
    "wof:placetype":"venue"
},
  "geometry": {"coordinates":[6.809796,52.260674],"type":"Point"}
}