{
  "type": "Feature",
  "properties": {
    "iso:country":"NL",
    "sg:address":"A V Roonhof 23",
    "sg:city":"Rhoon",
    "sg:orig_category":"Homeopathie",
    "sg:phone":"+31 10 501 3644",
    "sg:postcode":"3161 KT",
    "sg:province":"South Holland",
    "wof:name":"Amelie Bijma",
    "wof:placetype":"venue"
},
  "geometry": {"coordinates":[4.419975,51.855656],"type":"Point"}
}