{
  "type": "Feature",
  "properties": {
    "addr:full":"Boerenkamplaan 21 Someren Noord-Brabant 5712 AA",
    "addr:housenumber":"21",
    "addr:postcode":"5712 aa",
    "addr:street":"Boerenkamplaan",
    "iso:country":"NL",
    "sg:address":"Boerenkamplaan 21",
    "sg:city":"Someren",
    "sg:orig_category":"Auto'S And Voertuigen",
    "sg:phone":"+31 493 493 111",
    "sg:postcode":"5712 AA",
    "sg:province":"Noord-Brabant",
    "wof:name":"Autobedrijf Stienen Someren Bv",
    "wof:placetype":"venue"
},
  "geometry": {"coordinates":[5.7204,51.377346],"type":"Point"}
}