{
  "type": "Feature",
  "properties": {
    "addr:full":"Stationsstr 12 Tiel Gelderland 4001 CE",
    "addr:housenumber":"12",
    "addr:postcode":"4001 ce",
    "addr:street":"Stationsstr;Gelderland",
    "iso:country":"NL",
    "sg:address":"Stationsstr 12",
    "sg:city":"Tiel",
    "sg:orig_category":"Hulpverlening Sociaal",
    "sg:phone":"+31 344 634 459",
    "sg:postcode":"4001 CE",
    "sg:province":"Gelderland",
    "wof:name":"Jeugdzorg Rivierenland, Bur",
    "wof:placetype":"venue"
},
  "geometry": {"coordinates":[5.430696,51.888096],"type":"Point"}
}