{
  "type": "Feature",
  "properties": {
    "iso:country":"NL",
    "sg:address":"Grote Kampweg 53",
    "sg:city":"Haelen",
    "sg:orig_category":"Loodgieterswerk, Verwarming And Sanitaire Installaties",
    "sg:phone":"+31 475 592 132",
    "sg:postcode":"6081 CM",
    "sg:province":"Limburg",
    "wof:name":"J.M.E. Rumen",
    "wof:placetype":"venue"
},
  "geometry": {"coordinates":[5.946104,51.237217],"type":"Point"}
}