{
  "type": "Feature",
  "properties": {
    "iso:country":"NL",
    "sg:address":"Binnenweg 3",
    "sg:city":"Blaricum",
    "sg:orig_category":"Verzekeringen",
    "sg:phone":"+31 35 538 9371",
    "sg:postcode":"1261 EK",
    "sg:province":"North Holland",
    "wof:name":"M.A. Bek",
    "wof:placetype":"venue"
},
  "geometry": {"coordinates":[5.248965,52.273945],"type":"Point"}
}