{
  "type": "Feature",
  "properties": {
    "addr:full":"W M Dudokwg 39 Heerhugowaard Noord-Holland 1703 DA",
    "addr:housenumber":"39",
    "addr:postcode":"1703 da",
    "addr:street":"W",
    "iso:country":"NL",
    "sg:address":"W M Dudokwg 39",
    "sg:city":"Heerhugowaard",
    "sg:orig_category":"Notarissen En Notariskantoren",
    "sg:phone":"+31 72 571 8016",
    "sg:postcode":"1703 DA",
    "sg:province":"Noord-Holland",
    "sg:website":"http://www.actusnotarissen.nl",
    "wof:name":"Actus Notarissen",
    "wof:placetype":"venue"
},
  "geometry": {"coordinates":[4.819827,52.666142],"type":"Point"}
}