{
  "type": "Feature",
  "properties": {
    "addr:full":"Vleesmarkt 7 Dokkum Provincie Friesland 9101 MH",
    "addr:housenumber":"7",
    "addr:postcode":"9101 mh",
    "addr:street":"Vleesmarkt;Provincie Friesland",
    "iso:country":"NL",
    "sg:address":"Vleesmarkt 7",
    "sg:city":"Dokkum",
    "sg:orig_category":"Banken And Kredietinstellingen",
    "sg:phone":"+31 519 293 815",
    "sg:postcode":"9101 MH",
    "sg:province":"Provincie Friesland",
    "wof:name":"Ing Bank",
    "wof:placetype":"venue"
},
  "geometry": {"coordinates":[5.997428,53.324715],"type":"Point"}
}