{
  "type": "Feature",
  "properties": {
    "addr:full":"Oostdorperwg 18 Wassenaar Zuid-Holland 2242 NK",
    "addr:housenumber":"18",
    "addr:postcode":"2242 nk",
    "addr:street":"Oostdorperwg",
    "iso:country":"NL",
    "sg:address":"Oostdorperwg 18",
    "sg:city":"Wassenaar",
    "sg:orig_category":"Zonweringen",
    "sg:phone":"+31 70 511 2284",
    "sg:postcode":"2242 NK",
    "sg:province":"Zuid-Holland",
    "wof:name":"Zalm Saunabouw, Van Der",
    "wof:placetype":"venue"
},
  "geometry": {"coordinates":[4.395132,52.14735],"type":"Point"}
}