{
  "type": "Feature",
  "properties": {
    "iso:country":"NL",
    "sg:address":"Fien De La Marstraat 15",
    "sg:city":"Pijnacker",
    "sg:orig_category":"Bedrijfs- And Managementsconsultants",
    "sg:phone":"+31 15 369 8528",
    "sg:postcode":"2642 BV",
    "sg:province":"Zuid-Holland",
    "wof:name":"Image Process, Buro Voor Doc. Inf. Voorz",
    "wof:placetype":"venue"
},
  "geometry": {"coordinates":[4.44649,52.016869],"type":"Point"}
}