{
  "type": "Feature",
  "properties": {
    "iso:country":"NL",
    "sg:address":"Brusselln 2Ter",
    "sg:city":"Eindhoven",
    "sg:orig_category":"Wasmachines En Wasdrogers",
    "sg:phone":"+31 40 248 4392",
    "sg:postcode":"5628 TC",
    "sg:province":"Noord-Brabant",
    "wof:name":"Martens",
    "wof:placetype":"venue"
},
  "geometry": {"coordinates":[5.4719099998,51.4801101685],"type":"Point"}
}