{
  "type": "Feature",
  "properties": {
    "addr:full":"Heuvelpoort 315 Tilburg Noord-Brabant 5038 DT",
    "addr:housenumber":"315",
    "addr:postcode":"5038 dt",
    "addr:street":"Heuvelpoort",
    "iso:country":"NL",
    "sg:address":"Heuvelpoort 315",
    "sg:city":"Tilburg",
    "sg:classifiers":[
        {
            "category":"Shopping",
            "subcategory":"Gifts & Souvenirs",
            "type":"Retail Goods"
        }
    ],
    "sg:phone":"+31 13 581 1055",
    "sg:postcode":"5038 DT",
    "sg:province":"Noord-Brabant",
    "sg:tags":[
        "geschenken"
    ],
    "wof:name":"Paul En Trudy Aarts",
    "wof:placetype":"venue"
},
  "geometry": {"coordinates":[5.09071,51.556904],"type":"Point"}
}