{
  "type": "Feature",
  "properties": {
    "addr:full":"G Grootestr 9 Deventer Overijssel 7411 GS",
    "addr:housenumber":"9",
    "addr:postcode":"7411 gs",
    "iso:country":"NL",
    "sg:address":"G Grootestr 9",
    "sg:city":"Deventer",
    "sg:orig_category":"Accountants - Administratie- Consulenten En -Kantoren",
    "sg:phone":"+31 570 612 654",
    "sg:postcode":"7411 GS",
    "sg:province":"Overijssel",
    "wof:name":"Kieskamp",
    "wof:placetype":"venue"
},
  "geometry": {"coordinates":[6.161318,52.254158],"type":"Point"}
}