{
  "type": "Feature",
  "properties": {
    "addr:full":"Strandweg 3A 'S Gravenhage Zuid-Holland 2586 JK",
    "addr:housenumber":"3a '",
    "addr:postcode":"2586 jk",
    "addr:street":"Strandweg",
    "iso:country":"NL",
    "sg:address":"Strandweg 3A",
    "sg:city":"'S Gravenhage",
    "sg:orig_category":"Organisaties And Verenigingen",
    "sg:phone":"+31 70 355 2775",
    "sg:postcode":"2586 JK",
    "sg:province":"Zuid-Holland",
    "wof:name":"Koninklijke Nederlandse Redding Mij",
    "wof:placetype":"venue"
},
  "geometry": {"coordinates":[4.2782859802,52.1120376587],"type":"Point"}
}