{
  "type": "Feature",
  "properties": {
    "addr:full":"Larikslaan 141 Rotterdam 3053 LA",
    "addr:housenumber":"141",
    "addr:postcode":"3053 la",
    "addr:street":"Larikslaan",
    "iso:country":"NL",
    "sg:address":"Larikslaan 141",
    "sg:city":"Rotterdam",
    "sg:classifiers":[
        {
            "category":"Professional",
            "subcategory":"Advertising",
            "type":"Services"
        }
    ],
    "sg:postcode":"3053 LA",
    "sg:tags":[
        "social-media",
        "web-design",
        "web-development",
        "outsourcing",
        "web-agency",
        "nearshoring",
        "morocco",
        "africa",
        "online-advertising",
        "seo",
        "agadir",
        "interactive-agency",
        "cms",
        "content-management-system",
        "offshoring",
        "blog",
        "maroc",
        "france",
        "belgique",
        "the-netherlands",
        "netherlands"
    ],
    "sg:website":"http://www.synergie-media.com",
    "wof:name":"Synergie Media",
    "wof:placetype":"venue"
},
  "geometry": {"coordinates":[4.474856,51.960189],"type":"Point"}
}