{
  "type": "Feature",
  "properties": {
    "addr:full":"Galvanistraat 17 Nijkerk Gld Gelderland 3861 NJ",
    "addr:housenumber":"17",
    "addr:postcode":"3861",
    "addr:street":"Galvanistraat;Gld Gelderland",
    "iso:country":"NL",
    "sg:address":"Galvanistraat 17",
    "sg:city":"Nijkerk Gld",
    "sg:classifiers":[
        {
            "category":"Retail",
            "subcategory":"Storage",
            "type":"Services"
        }
    ],
    "sg:phone":"+31 33 245 5000",
    "sg:postcode":"3861 NJ",
    "sg:province":"Gelderland",
    "sg:tags":[
        "opslag",
        "bewaring"
    ],
    "wof:name":"M. Bouw & Zonen Transport Bv",
    "wof:placetype":"venue"
},
  "geometry": {"coordinates":[5.4695448875,52.2368392944],"type":"Point"}
}