{
  "type": "Feature",
  "properties": {
    "iso:country":"NL",
    "sg:address":"Handelskd W 7",
    "sg:city":"Enschede",
    "sg:orig_category":"Metaalbewerking",
    "sg:phone":"+31 53 430 6072",
    "sg:postcode":"7547 AW",
    "sg:province":"NL.08",
    "wof:name":"Hct Bv",
    "wof:placetype":"venue"
},
  "geometry": {"coordinates":[6.85766,52.223225],"type":"Point"}
}