{
  "type": "Feature",
  "properties": {
    "addr:full":"Handelskd W 7 Enschede NL.08 7547 AW",
    "addr:housenumber":"7",
    "addr:postcode":"7547 aw",
    "addr:street":"W",
    "iso:country":"NL",
    "sg:address":"Handelskd W 7",
    "sg:city":"Enschede",
    "sg:orig_category":"Metaalbewerking",
    "sg:phone":"+31 53 430 6072",
    "sg:postcode":"7547 AW",
    "sg:province":"NL.08",
    "wof:name":"Hct Bv",
    "wof:placetype":"venue"
},
  "geometry": {"coordinates":[6.85766,52.223225],"type":"Point"}
}