{
  "type": "Feature",
  "properties": {
    "addr:full":"Westeinde 175/F S Gravenhage Zuid-Holland 2512 GX",
    "addr:housenumber":"175 / f s",
    "addr:postcode":"2512 gx",
    "addr:street":"Westeinde",
    "iso:country":"NL",
    "sg:address":"Westeinde 175/F",
    "sg:city":"S Gravenhage",
    "sg:orig_category":"Meubelstoffering",
    "sg:phone":"+31 70 365 5262",
    "sg:postcode":"2512 GX",
    "sg:province":"Zuid-Holland",
    "wof:name":"Junho Ontwerpen",
    "wof:placetype":"venue"
},
  "geometry": {"coordinates":[4.30618,52.073212],"type":"Point"}
}