{
  "type": "Feature",
  "properties": {
    "addr:full":"Meent 28 Krimpen Aan De Lek Zuid-Holland 2931 LE",
    "addr:housenumber":"28",
    "addr:postcode":"aan;lek;2931 le",
    "addr:street":"Meent",
    "iso:country":"NL",
    "sg:address":"Meent 28",
    "sg:city":"Krimpen Aan De Lek",
    "sg:orig_category":"Fietsen En Bromfietsen",
    "sg:phone":"+31 180 522 635",
    "sg:postcode":"2931 LE",
    "sg:province":"Zuid-Holland",
    "wof:name":"Adrie Roest",
    "wof:placetype":"venue"
},
  "geometry": {"coordinates":[4.642163,51.899174],"type":"Point"}
}