{
  "type": "Feature",
  "properties": {
    "addr:full":"Wycker Brugstr 28 Maastricht Limburg 6221 ED",
    "addr:housenumber":"28",
    "addr:postcode":"6221 ed",
    "addr:street":"Wycker",
    "iso:country":"NL",
    "sg:address":"Wycker Brugstr 28",
    "sg:city":"Maastricht",
    "sg:orig_category":"Gelegenheidskleding",
    "sg:phone":"+31 43 321 9192",
    "sg:postcode":"6221 ED",
    "sg:province":"Limburg",
    "wof:name":"Flori",
    "wof:placetype":"venue"
},
  "geometry": {"coordinates":[5.699295,50.849575],"type":"Point"}
}