{
  "type": "Feature",
  "properties": {
    "addr:full":"Diezerkade 5 Zwolle Overijssel 8021 CW",
    "addr:housenumber":"5",
    "addr:postcode":"8021 cw",
    "addr:street":"Diezerkade",
    "iso:country":"NL",
    "sg:address":"Diezerkade 5",
    "sg:city":"Zwolle",
    "sg:orig_category":"Verlichting And Huishoudartikelen",
    "sg:phone":"+31 38 453 5879",
    "sg:postcode":"8021 CW",
    "sg:province":"Overijssel",
    "wof:name":"Fa L Bekenkamp En Zoon",
    "wof:placetype":"venue"
},
  "geometry": {"coordinates":[6.100483,52.515388],"type":"Point"}
}