{
  "type": "Feature",
  "properties": {
    "iso:country":"NL",
    "sg:address":"Dorpsstr 2",
    "sg:city":"Bemmel",
    "sg:orig_category":"Makelaars En Adviseurs Onroerende Goederen",
    "sg:phone":"+31 481 464 666",
    "sg:postcode":"6681 BN",
    "sg:province":"Gelderland",
    "wof:name":"Guijt",
    "wof:placetype":"venue"
},
  "geometry": {"coordinates":[5.902298,51.89468],"type":"Point"}
}