{
  "type": "Feature",
  "properties": {
    "addr:full":"Kluiversgang 6 Eibergen Gelderland 7151 CB",
    "addr:housenumber":"6",
    "addr:postcode":"7151 cb",
    "addr:street":"Kluiversgang;Gelderland",
    "iso:country":"NL",
    "sg:address":"Kluiversgang 6",
    "sg:city":"Eibergen",
    "sg:orig_category":"Opticiens",
    "sg:phone":"+31 545 475 500",
    "sg:postcode":"7151 CB",
    "sg:province":"Gelderland",
    "wof:name":"Hofland Optiek",
    "wof:placetype":"venue"
},
  "geometry": {"coordinates":[6.6496100426,52.1023483276],"type":"Point"}
}