{
  "type": "Feature",
  "properties": {
    "iso:country":"NL",
    "sg:address":"Beutenaken 26",
    "sg:city":"Beutenaken",
    "sg:orig_category":"Vakantieverblijven",
    "sg:phone":"+31 43 457 3268",
    "sg:postcode":"6278 NB",
    "sg:province":"Limburg",
    "wof:name":"Le Bijou",
    "wof:placetype":"venue"
},
  "geometry": {"coordinates":[5.855696,50.782921],"type":"Point"}
}