{
  "type": "Feature",
  "properties": {
    "addr:full":"Beutenaken 26 Beutenaken Limburg 6278 NB",
    "addr:housenumber":"26",
    "addr:postcode":"6278 nb",
    "addr:street":"Beutenaken",
    "iso:country":"NL",
    "sg:address":"Beutenaken 26",
    "sg:city":"Beutenaken",
    "sg:orig_category":"Vakantieverblijven",
    "sg:phone":"+31 43 457 3268",
    "sg:postcode":"6278 NB",
    "sg:province":"Limburg",
    "wof:name":"Le Bijou",
    "wof:placetype":"venue"
},
  "geometry": {"coordinates":[5.855696,50.782921],"type":"Point"}
}