{
  "type": "Feature",
  "properties": {
    "iso:country":"NL",
    "sg:address":"Zuideinde 159",
    "sg:city":"Oostzaan",
    "sg:orig_category":"Verzekeringen - Verzekeringskantoren",
    "sg:phone":"+31 75 684 2940",
    "sg:postcode":"1511 GD",
    "sg:province":"North Holland",
    "wof:name":"Neptunus Bv",
    "wof:placetype":"venue"
},
  "geometry": {"coordinates":[4.88161,52.432571],"type":"Point"}
}