{
  "type": "Feature",
  "properties": {
    "addr:full":"Oranjeboomln 27 Wezep Gelderland 8091 BZ",
    "addr:housenumber":"27",
    "addr:postcode":"8091 bz",
    "addr:street":"Oranjeboomln",
    "iso:country":"NL",
    "sg:address":"Oranjeboomln 27",
    "sg:city":"Wezep",
    "sg:orig_category":"Verenigingsgebouwen",
    "sg:phone":"+31 38 376 1811",
    "sg:postcode":"8091 BZ",
    "sg:province":"Gelderland",
    "wof:name":"Schakel, De",
    "wof:placetype":"venue"
},
  "geometry": {"coordinates":[5.994331,52.461037],"type":"Point"}
}