{
  "type": "Feature",
  "properties": {
    "addr:full":"Brakersweg 69 Castricum North Holland 1901 XZ",
    "addr:housenumber":"69",
    "addr:postcode":"1901 xz",
    "addr:street":"Brakersweg",
    "iso:country":"NL",
    "sg:address":"Brakersweg 69",
    "sg:city":"Castricum",
    "sg:orig_category":"Bloemen And Planten",
    "sg:phone":"+31 251 659 755",
    "sg:postcode":"1901 XZ",
    "sg:province":"North Holland",
    "wof:name":"Tuincentrum Ed Schut Fijnhoveniers Bv",
    "wof:placetype":"venue"
},
  "geometry": {"coordinates":[4.67113,52.559605],"type":"Point"}
}