{
  "type": "Feature",
  "properties": {
    "addr:full":"Weststraat 33 Aardenburg Zeeland 4527 BR",
    "addr:housenumber":"33",
    "addr:postcode":"4527 br",
    "addr:street":"Weststraat",
    "iso:country":"NL",
    "sg:address":"Weststraat 33",
    "sg:city":"Aardenburg",
    "sg:orig_category":"Binnenhuisarchitecten",
    "sg:phone":"+31 117 492 492",
    "sg:postcode":"4527 BR",
    "sg:province":"Zeeland",
    "wof:name":"Interieuridee",
    "wof:placetype":"venue"
},
  "geometry": {"coordinates":[3.44525,51.273796],"type":"Point"}
}