{
  "type": "Feature",
  "properties": {
    "addr:full":"Meengatstraat 44 Brummen Gelderland 6971 VE",
    "addr:housenumber":"44",
    "addr:postcode":"6971",
    "addr:street":"Meengatstraat;Gelderland;Ve",
    "iso:country":"NL",
    "sg:address":"Meengatstraat 44",
    "sg:city":"Brummen",
    "sg:orig_category":"Alternatieve Geneeskunde",
    "sg:phone":"+31 575 563 809",
    "sg:postcode":"6971 VE",
    "sg:province":"Gelderland",
    "wof:name":"A A F Uit De Weerd-Noordermeer",
    "wof:placetype":"venue"
},
  "geometry": {"coordinates":[6.158525,52.096542],"type":"Point"}
}