{
  "type": "Feature",
  "properties": {
    "iso:country":"NL",
    "sg:address":"Buttingasngl 57",
    "sg:city":"Oosterwolde Fr",
    "sg:orig_category":"Voetbalverenigingen",
    "sg:phone":"+31 516 516 796",
    "sg:postcode":"8431 AX",
    "sg:province":"Friesland",
    "wof:name":"Griffioen, De",
    "wof:placetype":"venue"
},
  "geometry": {"coordinates":[6.291785,52.991199],"type":"Point"}
}