{
  "type": "Feature",
  "properties": {
    "addr:full":"Broekhovensewg 10A Riethoven North Brabant 5561 TT",
    "addr:housenumber":"10a",
    "addr:postcode":"5561 tt",
    "addr:street":"Broekhovensewg",
    "iso:country":"NL",
    "sg:address":"Broekhovensewg 10A",
    "sg:city":"Riethoven",
    "sg:orig_category":"Bedrijfsmechanisatie En -Automatisering",
    "sg:phone":"+31 497 516 064",
    "sg:postcode":"5561 TT",
    "sg:province":"North Brabant",
    "wof:name":"Crt",
    "wof:placetype":"venue"
},
  "geometry": {"coordinates":[5.379554,51.362667],"type":"Point"}
}