{
  "type": "Feature",
  "properties": {
    "iso:country":"NL",
    "sg:address":"Maastrichterstraat 154",
    "sg:city":"Brunssum",
    "sg:classifiers":[
        {
            "category":"Fast Food",
            "type":"Food & Drink"
        }
    ],
    "sg:phone":"+31 45 525 7249",
    "sg:postcode":"6444 GK",
    "sg:province":"Limburg",
    "sg:tags":[
        "afhaal",
        "restaurant"
    ],
    "wof:name":"Friture De Leeuw",
    "wof:placetype":"venue"
},
  "geometry": {"coordinates":[5.950815,50.940536],"type":"Point"}
}