{
  "type": "Feature",
  "properties": {
    "iso:country":"NL",
    "sg:address":"Singel 9",
    "sg:city":"Deventer",
    "sg:orig_category":"Banken And Kredietinstellingen",
    "sg:phone":"+31 570 684 911",
    "sg:postcode":"7411 HV",
    "sg:province":"Overijssel",
    "wof:name":"Rabobank",
    "wof:placetype":"venue"
},
  "geometry": {"coordinates":[6.155132,52.257355],"type":"Point"}
}