{
  "type": "Feature",
  "properties": {
    "iso:country":"NL",
    "sg:address":"Osdorppln 370",
    "sg:city":"Amsterdam",
    "sg:orig_category":"Schoenen",
    "sg:phone":"+31 20 619 1224",
    "sg:postcode":"1068 EV",
    "sg:province":"Noord-Holland",
    "wof:name":"Nelson",
    "wof:placetype":"venue"
},
  "geometry": {"coordinates":[4.80371,52.359791],"type":"Point"}
}