{
  "type": "Feature",
  "properties": {
    "iso:country":"NL",
    "sg:address":"Muiderwaard 414",
    "sg:city":"Alkmaar",
    "sg:orig_category":"Verhuur",
    "sg:phone":"+31 72 561 1225",
    "sg:postcode":"1824 XT",
    "sg:province":"North Holland",
    "sg:website":"http://www.hekeltje.nl",
    "wof:name":"Hekeltje, 'T",
    "wof:placetype":"venue"
},
  "geometry": {"coordinates":[4.749394,52.64571],"type":"Point"}
}