{
  "type": "Feature",
  "properties": {
    "addr:full":"St Jacobsstr 11C Leeuwarden Provincie Friesland 8911 HR",
    "addr:housenumber":"11c",
    "addr:postcode":"8911 hr",
    "addr:street":"Provincie Friesland",
    "iso:country":"NL",
    "sg:address":"St Jacobsstr 11C",
    "sg:city":"Leeuwarden",
    "sg:orig_category":"Balletscholen",
    "sg:phone":"+31 58 213 5566",
    "sg:postcode":"8911 HR",
    "sg:province":"Provincie Friesland",
    "wof:name":"Nynke Van Duinen",
    "wof:placetype":"venue"
},
  "geometry": {"coordinates":[5.79644,53.201431],"type":"Point"}
}