{
  "type": "Feature",
  "properties": {
    "addr:full":"Keppelstraat 30 Dokkum Provincie Friesland 9101 MV",
    "addr:housenumber":"30",
    "addr:postcode":"9101 mv",
    "addr:street":"Keppelstraat;Provincie Friesland",
    "iso:country":"NL",
    "sg:address":"Keppelstraat 30",
    "sg:city":"Dokkum",
    "sg:orig_category":"Boekhandels",
    "sg:phone":"+31 519 294 105",
    "sg:postcode":"9101 MV",
    "sg:province":"Provincie Friesland",
    "wof:name":"Evangelische Boektiek",
    "wof:placetype":"venue"
},
  "geometry": {"coordinates":[5.999649,53.32391],"type":"Point"}
}