{
  "type": "Feature",
  "properties": {
    "iso:country":"NL",
    "sg:address":"H C Pootstr 106",
    "sg:city":"Hengelo Ov",
    "sg:orig_category":"Psychotherapeuten",
    "sg:phone":"+31 74 250 2526",
    "sg:postcode":"7552 WS",
    "sg:province":"Overijssel",
    "wof:name":"Wasmann",
    "wof:placetype":"venue"
},
  "geometry": {"coordinates":[6.822172,52.265095],"type":"Point"}
}