{
  "type": "Feature",
  "properties": {
    "addr:full":"Struytse Hoeck 17 Hellevoetsluis Zuid-Holland 3224 HA",
    "addr:housenumber":"17",
    "addr:postcode":"3224 ha",
    "addr:street":"Struytse Hoeck",
    "iso:country":"NL",
    "sg:address":"Struytse Hoeck 17",
    "sg:city":"Hellevoetsluis",
    "sg:orig_category":"Apothekers",
    "sg:phone":"+31 181 311 184",
    "sg:postcode":"3224 HA",
    "sg:province":"Zuid-Holland",
    "wof:name":"Apotheek De Struytse Hoeck Bv",
    "wof:placetype":"venue"
},
  "geometry": {"coordinates":[4.145478,51.82962],"type":"Point"}
}