{
  "type": "Feature",
  "properties": {
    "addr:full":"Crocusstr 29 Rotterdam South Holland 3053 XL",
    "addr:housenumber":"29",
    "addr:postcode":"3053 xl",
    "addr:street":"Crocusstr",
    "iso:country":"NL",
    "sg:address":"Crocusstr 29",
    "sg:city":"Rotterdam",
    "sg:classifiers":[
        {
            "category":"Personal",
            "subcategory":"Nail Salon",
            "type":"Services"
        }
    ],
    "sg:phone":"+31 10 418 9147",
    "sg:postcode":"3053 XL",
    "sg:province":"South Holland",
    "sg:tags":[
        "pedicure"
    ],
    "wof:name":"Kalishoek, H",
    "wof:placetype":"venue"
},
  "geometry": {"coordinates":[4.469379,51.962315],"type":"Point"}
}