{
  "type": "Feature",
  "properties": {
    "addr:full":"Dorpsstraat 15 Eesergroen Provincie Drenthe 9537 TB",
    "addr:housenumber":"15",
    "addr:postcode":"9537 tb",
    "addr:street":"Dorpsstraat;Provincie Drenthe",
    "iso:country":"NL",
    "sg:address":"Dorpsstraat 15",
    "sg:city":"Eesergroen",
    "sg:orig_category":"Kledingaccessoires",
    "sg:phone":"+31 599 287 345",
    "sg:postcode":"9537 TB",
    "sg:province":"Provincie Drenthe",
    "wof:name":"Oregon Trail Tack Store",
    "wof:placetype":"venue"
},
  "geometry": {"coordinates":[6.776954,52.886684],"type":"Point"}
}