{
  "type": "Feature",
  "properties": {
    "addr:full":"Schoolstr 21 Oldehove Groningen 9883 PG",
    "addr:housenumber":"21",
    "addr:postcode":"9883 pg",
    "addr:street":"Schoolstr",
    "iso:country":"NL",
    "sg:address":"Schoolstr 21",
    "sg:city":"Oldehove",
    "sg:classifiers":[
        {
            "category":"Retail",
            "subcategory":"Auto Repair",
            "type":"Services"
        }
    ],
    "sg:phone":"+31 594 591 291",
    "sg:postcode":"9883 PG",
    "sg:province":"Groningen",
    "sg:tags":[
        "garage"
    ],
    "wof:name":"Jansma, E M",
    "wof:placetype":"venue"
},
  "geometry": {"coordinates":[6.393269,53.304787],"type":"Point"}
}