{
  "type": "Feature",
  "properties": {
    "iso:country":"NL",
    "sg:address":"Hovenierslaantje 11",
    "sg:city":"Tiel",
    "sg:classifiers":[
        {
            "category":"Professional",
            "subcategory":"Accounting & Tax Preparation",
            "type":"Services"
        }
    ],
    "sg:phone":"+31 344 622 273",
    "sg:postcode":"4001 HN",
    "sg:province":"Gelderland",
    "sg:tags":[
        "accountant"
    ],
    "wof:name":"G.J. Wouterse",
    "wof:placetype":"venue"
},
  "geometry": {"coordinates":[5.434276,51.890125],"type":"Point"}
}