{
  "type": "Feature",
  "properties": {
    "addr:full":"Baljuwstraat 139 Den Helder North Holland 1785 SH",
    "addr:housenumber":"139",
    "addr:postcode":"1785 sh",
    "addr:street":"Baljuwstraat",
    "iso:country":"NL",
    "sg:address":"Baljuwstraat 139",
    "sg:city":"Den Helder",
    "sg:orig_category":"Benzinestations And Brandstoffen",
    "sg:phone":"+31 223 660 099",
    "sg:postcode":"1785 SH",
    "sg:province":"North Holland",
    "wof:name":"Tank Service Den Helder",
    "wof:placetype":"venue"
},
  "geometry": {"coordinates":[4.770253,52.935135],"type":"Point"}
}