{
  "type": "Feature",
  "properties": {
    "iso:country":"NL",
    "sg:address":"Lindengr 27",
    "sg:city":"Opmeer",
    "sg:orig_category":"Verzekeringen - Verzekeringskantoren",
    "sg:phone":"+31 226 354 144",
    "sg:postcode":"1716 DD",
    "sg:province":"Noord-Holland",
    "sg:website":"http://www.generali.nl/palet/s&g",
    "wof:name":"S & G",
    "wof:placetype":"venue"
},
  "geometry": {"coordinates":[4.950346,52.7043],"type":"Point"}
}