{
  "type": "Feature",
  "properties": {
    "addr:full":"Kerkstr 47 Makkum Fr Provincie Friesland 8754 CR",
    "addr:housenumber":"47;8754",
    "addr:postcode":"cr",
    "addr:street":"Kerkstr;Friesland",
    "iso:country":"NL",
    "sg:address":"Kerkstr 47",
    "sg:city":"Makkum Fr",
    "sg:orig_category":"Bloemen En Planten",
    "sg:phone":"+31 515 231 390",
    "sg:postcode":"8754 CR",
    "sg:province":"Provincie Friesland",
    "wof:name":"Woude Vof, A Van Der",
    "wof:placetype":"venue"
},
  "geometry": {"coordinates":[5.40258,53.057034],"type":"Point"}
}