{
  "type": "Feature",
  "properties": {
    "addr:full":"Onder De Kerk 8 Maastricht Limburg 6227 BH",
    "addr:housenumber":"8",
    "addr:postcode":"6227 bh",
    "addr:street":"Onder De Kerk",
    "iso:country":"NL",
    "sg:address":"Onder De Kerk 8",
    "sg:city":"Maastricht",
    "sg:orig_category":"Vertaal- And Tolkenbureaus",
    "sg:phone":"+31 43 367 1567",
    "sg:postcode":"6227 BH",
    "sg:province":"Limburg",
    "wof:name":"Vertaler H.W. Versluys",
    "wof:placetype":"venue"
},
  "geometry": {"coordinates":[5.726501,50.842258],"type":"Point"}
}