{
  "type": "Feature",
  "properties": {
    "addr:full":"Amsterdamseweg 15 Arnhem Gelderland 6814 CM",
    "addr:housenumber":"15",
    "addr:postcode":"6814 cm",
    "addr:street":"Amsterdamseweg",
    "iso:country":"NL",
    "sg:address":"Amsterdamseweg 15",
    "sg:city":"Arnhem",
    "sg:orig_category":"Hoger Onderwijs",
    "sg:phone":"+31 26 351 6500",
    "sg:postcode":"6814 CM",
    "sg:province":"Gelderland",
    "wof:name":"Instituut De Boer",
    "wof:placetype":"venue"
},
  "geometry": {"coordinates":[5.897479,51.98666],"type":"Point"}
}