{
  "type": "Feature",
  "properties": {
    "addr:full":"Jan Palachweg 85 Assen Drenthe 9403 JT",
    "addr:housenumber":"85",
    "addr:postcode":"9403 jt",
    "addr:street":"Jan Palachweg",
    "iso:country":"NL",
    "sg:address":"Jan Palachweg 85",
    "sg:city":"Assen",
    "sg:orig_category":"Boekhouders",
    "sg:phone":"+31 592 372 351",
    "sg:postcode":"9403 JT",
    "sg:province":"Drenthe",
    "wof:name":"Marrink Administraties",
    "wof:placetype":"venue"
},
  "geometry": {"coordinates":[6.584489,53.022438],"type":"Point"}
}