{
  "type": "Feature",
  "properties": {
    "addr:full":"Theemswg 9 Amsterdam North Holland 1043 BD",
    "addr:housenumber":"9",
    "addr:postcode":"1043 bd",
    "addr:street":"Theemswg",
    "iso:country":"NL",
    "sg:address":"Theemswg 9",
    "sg:city":"Amsterdam",
    "sg:classifiers":[
        {
            "category":"Arena",
            "subcategory":"Auto Racetrack",
            "type":"Entertainment"
        }
    ],
    "sg:phone":"+31 20 611 1642",
    "sg:postcode":"1043 BD",
    "sg:province":"North Holland",
    "sg:tags":[
        "en",
        "racebanen",
        "kart-"
    ],
    "sg:website":"http://www.kartbaanamsterdam.nl",
    "wof:name":"Kartbaan Amsterdam",
    "wof:placetype":"venue"
},
  "geometry": {"coordinates":[4.80925,52.38945],"type":"Point"}
}