{
  "type": "Feature",
  "properties": {
    "addr:full":"De Kromme Geer 68 Helmond Noord-Brabant 5709 ME",
    "addr:housenumber":"68",
    "addr:postcode":"5709 me",
    "addr:street":"De Kromme Geer",
    "iso:country":"NL",
    "sg:address":"De Kromme Geer 68",
    "sg:city":"Helmond",
    "sg:orig_category":"Grafisch Ontwerpers",
    "sg:phone":"+31 492 516 918",
    "sg:postcode":"5709 ME",
    "sg:province":"Noord-Brabant",
    "wof:name":"Perfect-Line",
    "wof:placetype":"venue"
},
  "geometry": {"coordinates":[5.694774,51.491085],"type":"Point"}
}