{
  "type": "Feature",
  "properties": {
    "iso:country":"NL",
    "sg:address":"Hub Van Doorneweg 7",
    "sg:city":"Sassenheim",
    "sg:orig_category":"Loodgieterswerk, Verwarming And Sanitaire Installaties",
    "sg:phone":"+31 252 260 101",
    "sg:postcode":"2171 KZ",
    "sg:province":"Zuid-Holland",
    "wof:name":"Ijsselmuiden En Zn Bv",
    "wof:placetype":"venue"
},
  "geometry": {"coordinates":[4.508311,52.214809],"type":"Point"}
}