{
  "type": "Feature",
  "properties": {
    "iso:country":"NL",
    "sg:address":"Twijnen 9",
    "sg:city":"Oudewater",
    "sg:orig_category":"Bedrijfs- And Managementsconsultants",
    "sg:phone":"+31 348 563 275",
    "sg:postcode":"3421 JM",
    "sg:province":"Utrecht",
    "wof:name":"Scope Managementondersteuning Bv",
    "wof:placetype":"venue"
},
  "geometry": {"coordinates":[4.870335,52.030815],"type":"Point"}
}