{
  "type": "Feature",
  "properties": {
    "addr:full":"Verfmolenstraat 78 Almere Flevoland 1333 AW",
    "addr:housenumber":"78",
    "addr:postcode":"1333 aw",
    "addr:street":"Verfmolenstraat;Flevoland",
    "iso:country":"NL",
    "sg:address":"Verfmolenstraat 78",
    "sg:city":"Almere",
    "sg:orig_category":"Artiesten",
    "sg:phone":"+31 36 532 5965",
    "sg:postcode":"1333 AW",
    "sg:province":"Flevoland",
    "wof:name":"Simon Bolhuis",
    "wof:placetype":"venue"
},
  "geometry": {"coordinates":[5.268421,52.396221],"type":"Point"}
}