{
  "type": "Feature",
  "properties": {
    "addr:full":"Kalymnosdreef 178 Utrecht Utrecht 3562 XN",
    "addr:housenumber":"178",
    "addr:postcode":"3562 xn",
    "addr:street":"Kalymnosdreef",
    "iso:country":"NL",
    "sg:address":"Kalymnosdreef 178",
    "sg:city":"Utrecht",
    "sg:orig_category":"Webdesign Bureaus",
    "sg:phone":"+31 6 24620073",
    "sg:postcode":"3562 XN",
    "sg:province":"Utrecht",
    "sg:website":"http://www.5arca5m.com",
    "wof:name":"5Arca5M",
    "wof:placetype":"venue"
},
  "geometry": {"coordinates":[5.1114249229,52.1171569824],"type":"Point"}
}