{
  "type": "Feature",
  "properties": {
    "iso:country":"NL",
    "sg:address":"Oostgouweweg 5",
    "sg:city":"Alphen A/D Rijn",
    "sg:orig_category":"Pompen And Compressoren Fab",
    "sg:phone":"+31 172 494 965",
    "sg:postcode":"2407 AD",
    "sg:province":"Zuid-Holland",
    "wof:name":"Desman Water Bv",
    "wof:placetype":"venue"
},
  "geometry": {"coordinates":[4.675271,52.116753],"type":"Point"}
}