{
  "type": "Feature",
  "properties": {
    "iso:country":"NL",
    "sg:address":"Hitchcocklaan 56",
    "sg:city":"Almere",
    "sg:orig_category":"Kappers",
    "sg:phone":"+31 36 537 4262",
    "sg:postcode":"1325 TE",
    "sg:province":"NL.",
    "wof:name":"Dames En Herenkapsalon Ebony En Ivory",
    "wof:placetype":"venue"
},
  "geometry": {"coordinates":[5.2455368042,52.3588981628],"type":"Point"}
}