{
  "type": "Feature",
  "properties": {
    "addr:full":"Graaf Hendriklaan 1 Amersfoort Utrecht 3818 DL",
    "addr:housenumber":"1",
    "addr:postcode":"3818 dl",
    "addr:street":"Graaf Hendriklaan",
    "iso:country":"NL",
    "sg:address":"Graaf Hendriklaan 1",
    "sg:city":"Amersfoort",
    "sg:orig_category":"Bedrijfs- And Managementsconsultants",
    "sg:phone":"+31 6 53488105",
    "sg:postcode":"3818 DL",
    "sg:province":"Utrecht",
    "wof:name":"Bommelsteyn Management Consultancy",
    "wof:placetype":"venue"
},
  "geometry": {"coordinates":[5.380269,52.148327],"type":"Point"}
}