{
  "type": "Feature",
  "properties": {
    "addr:full":"Jungfrau 83 Utrecht Utrecht 3524 WJ",
    "addr:housenumber":"83",
    "addr:postcode":"3524 wj",
    "addr:street":"Jungfrau",
    "iso:country":"NL",
    "sg:address":"Jungfrau 83",
    "sg:city":"Utrecht",
    "sg:orig_category":"Overheidsdiensten",
    "sg:phone":"+31 30 288 0824",
    "sg:postcode":"3524 WJ",
    "sg:province":"Utrecht",
    "wof:name":"Ussv Sportvereniging",
    "wof:placetype":"venue"
},
  "geometry": {"coordinates":[5.1290540695,52.0629692078],"type":"Point"}
}