{
  "type": "Feature",
  "properties": {
    "addr:full":"Kerkstraat 1 Heerde Gelderland 8181 JA",
    "addr:housenumber":"1",
    "addr:postcode":"8181 ja",
    "addr:street":"Kerkstraat;Gelderland",
    "iso:country":"NL",
    "sg:address":"Kerkstraat 1",
    "sg:city":"Heerde",
    "sg:classifiers":[
        {
            "category":"Professional",
            "subcategory":"Accounting & Tax Preparation",
            "type":"Services"
        }
    ],
    "sg:phone":"+31 578 691 670",
    "sg:postcode":"8181 JA",
    "sg:province":"Gelderland",
    "sg:tags":[
        "accountant"
    ],
    "wof:name":"Meeuwsen Ten Hoopen & Co",
    "wof:placetype":"venue"
},
  "geometry": {"coordinates":[6.042018,52.386745],"type":"Point"}
}