{
  "type": "Feature",
  "properties": {
    "addr:full":"Ericastr 24 Groesbeek Gelderland 6561 VZ",
    "addr:housenumber":"24",
    "addr:postcode":"6561 vz",
    "addr:street":"Ericastr;Gelderland",
    "iso:country":"NL",
    "sg:address":"Ericastr 24",
    "sg:city":"Groesbeek",
    "sg:orig_category":"Artiesten/Gezelschappen",
    "sg:phone":"+31 24 397 6566",
    "sg:postcode":"6561 VZ",
    "sg:province":"Gelderland",
    "wof:name":"Maple Leaf",
    "wof:placetype":"venue"
},
  "geometry": {"coordinates":[5.921979,51.787308],"type":"Point"}
}