{
  "type": "Feature",
  "properties": {
    "addr:full":"Bemuurde Weerd Wz 5 Utrecht Utrecht 3513 BH",
    "addr:housenumber":"5",
    "addr:postcode":"3513 bh",
    "addr:street":"Bemuurde Weerd Wz",
    "iso:country":"NL",
    "sg:address":"Bemuurde Weerd Wz 5",
    "sg:city":"Utrecht",
    "sg:orig_category":"Vakorganisaties",
    "sg:phone":"+31 30 230 2647",
    "sg:postcode":"3513 BH",
    "sg:province":"Utrecht",
    "wof:name":"Nvsph",
    "wof:placetype":"venue"
},
  "geometry": {"coordinates":[5.114402,52.09753],"type":"Point"}
}