{
  "type": "Feature",
  "properties": {
    "addr:full":"Thermiekstraat 12 Nuth Limburg 6361 HB",
    "addr:housenumber":"12",
    "addr:postcode":"6361 hb",
    "addr:street":"Thermiekstraat",
    "iso:country":"NL",
    "sg:address":"Thermiekstraat 12",
    "sg:city":"Nuth",
    "sg:orig_category":"Elektronische Bedrijfsinstallaties",
    "sg:phone":"+31 45 524 4962",
    "sg:postcode":"6361 HB",
    "sg:province":"Limburg",
    "wof:name":"Ultrasec Telecom En Beveiligingstechniek Bv",
    "wof:placetype":"venue"
},
  "geometry": {"coordinates":[5.880478,50.924004],"type":"Point"}
}