{
  "type": "Feature",
  "properties": {
    "addr:full":"Oude Binnenweg 95A Rotterdam Zuid-Holland 3012 JA",
    "addr:housenumber":"95a",
    "addr:postcode":"3012 ja",
    "addr:street":"Oude Binnenweg",
    "iso:country":"NL",
    "sg:address":"Oude Binnenweg 95A",
    "sg:city":"Rotterdam",
    "sg:orig_category":"Zuivelproducten",
    "sg:phone":"+31 10 413 8644",
    "sg:postcode":"3012 JA",
    "sg:province":"Zuid-Holland",
    "wof:name":"Kaashoeve",
    "wof:placetype":"venue"
},
  "geometry": {"coordinates":[4.475374,51.917732],"type":"Point"}
}