{
  "type": "Feature",
  "properties": {
    "addr:full":"Munnikensteeg 26 Zwijndrecht Zuid-Holland 3335 LJ",
    "addr:housenumber":"26",
    "addr:postcode":"3335 lj",
    "addr:street":"Munnikensteeg",
    "iso:country":"NL",
    "sg:address":"Munnikensteeg 26",
    "sg:city":"Zwijndrecht",
    "sg:orig_category":"Benzinestations And Brandstoffen",
    "sg:phone":"+31 78 610 6000",
    "sg:postcode":"3335 LJ",
    "sg:province":"Zuid-Holland",
    "wof:name":"Bp",
    "wof:placetype":"venue"
},
  "geometry": {"coordinates":[4.603064,51.822819],"type":"Point"}
}