{
  "type": "Feature",
  "properties": {
    "iso:country":"NL",
    "sg:address":"De Wheer 153",
    "sg:city":"Almelo",
    "sg:orig_category":"Kappers",
    "sg:phone":"+31 546 499 057",
    "sg:postcode":"7603 DK",
    "sg:province":"Overijssel",
    "wof:name":"Wendy'S Knipmobiel",
    "wof:placetype":"venue"
},
  "geometry": {"coordinates":[6.683159,52.369423],"type":"Point"}
}