{
  "type": "Feature",
  "properties": {
    "addr:full":"W Beukelszoonstr 10A S Gravenhage Zuid-Holland 2584 XR",
    "addr:housenumber":"10a;gravenhage",
    "addr:postcode":"2584 xr",
    "addr:street":"W;S",
    "iso:country":"NL",
    "sg:address":"W Beukelszoonstr 10A",
    "sg:city":"S Gravenhage",
    "sg:orig_category":"Journalisten Freelance",
    "sg:phone":"+31 70 350 2053",
    "sg:postcode":"2584 XR",
    "sg:province":"Zuid-Holland",
    "wof:name":"Enk, Frits",
    "wof:placetype":"venue"
},
  "geometry": {"coordinates":[4.28131,52.103199],"type":"Point"}
}