{
  "type": "Feature",
  "properties": {
    "addr:full":"Hobbemastraat 5 'S Gravenhage Zuid-Holland 2526 JE",
    "addr:housenumber":"5 ';2526",
    "addr:postcode":"je",
    "addr:street":"Hobbemastraat",
    "iso:country":"NL",
    "sg:address":"Hobbemastraat 5",
    "sg:city":"'S Gravenhage",
    "sg:classifiers":[
        {
            "category":"Fast Food",
            "type":"Food & Drink"
        }
    ],
    "sg:phone":"+31 70 388 2244",
    "sg:postcode":"2526 JE",
    "sg:province":"Zuid-Holland",
    "sg:tags":[
        "afhaal",
        "restaurant"
    ],
    "wof:name":"Shoarma Turan",
    "wof:placetype":"venue"
},
  "geometry": {"coordinates":[4.30653,52.07024],"type":"Point"}
}