{
  "type": "Feature",
  "properties": {
    "addr:full":"Engelsestr 25 Bergen Op Zoom Noord-Brabant 4611 RP",
    "addr:housenumber":"25",
    "addr:postcode":"4611 rp",
    "addr:street":"Engelsestr",
    "iso:country":"NL",
    "sg:address":"Engelsestr 25",
    "sg:city":"Bergen Op Zoom",
    "sg:orig_category":"Verenigingen En Stichtingen",
    "sg:phone":"+31 164 233 531",
    "sg:postcode":"4611 RP",
    "sg:province":"Noord-Brabant",
    "wof:name":"Vincentiusver",
    "wof:placetype":"venue"
},
  "geometry": {"coordinates":[4.288126,51.496117],"type":"Point"}
}