{
  "type": "Feature",
  "properties": {
    "addr:full":"Postwg 55 Soesterberg Utrecht 3769 BV",
    "addr:housenumber":"55",
    "addr:postcode":"3769 bv",
    "addr:street":"Postwg",
    "iso:country":"NL",
    "sg:address":"Postwg 55",
    "sg:city":"Soesterberg",
    "sg:orig_category":"Koeriersdiensten",
    "sg:phone":"+31 346 568 000",
    "sg:postcode":"3769 BV",
    "sg:province":"Utrecht",
    "wof:name":"Aalberts Service Bv",
    "wof:placetype":"venue"
},
  "geometry": {"coordinates":[5.279984,52.124069],"type":"Point"}
}