{
  "type": "Feature",
  "properties": {
    "addr:full":"Keizersgr 440 Amsterdam Noord-Holland 1016 GD",
    "addr:housenumber":"440",
    "addr:postcode":"1016 gd",
    "iso:country":"NL",
    "sg:address":"Keizersgr 440",
    "sg:city":"Amsterdam",
    "sg:orig_category":"Bibliotheken En Leeszalen Openbare",
    "sg:phone":"+31 20 523 0780",
    "sg:postcode":"1016 GD",
    "sg:province":"Noord-Holland",
    "sg:website":"http://www.oba.nl",
    "wof:name":"Onderwijsmediatheek",
    "wof:placetype":"venue"
},
  "geometry": {"coordinates":[4.883957,52.367729],"type":"Point"}
}