{
  "type": "Feature",
  "properties": {
    "iso:country":"NL",
    "sg:address":"Couwenhoven 9056",
    "sg:city":"Zeist",
    "sg:orig_category":"Boekhouders",
    "sg:phone":"+31 30 695 5920",
    "sg:postcode":"3703 GE",
    "sg:province":"Utrecht",
    "wof:name":"Petit Restaurant Francois Franchising",
    "wof:placetype":"venue"
},
  "geometry": {"coordinates":[5.22569,52.076488],"type":"Point"}
}