{
  "type": "Feature",
  "properties": {
    "addr:full":"Brugstr 17 Sittard Limburg 6131 AC",
    "addr:housenumber":"17",
    "addr:postcode":"6131 ac",
    "addr:street":"Brugstr",
    "iso:country":"NL",
    "sg:address":"Brugstr 17",
    "sg:city":"Sittard",
    "sg:orig_category":"Schoonheidsinstituten",
    "sg:phone":"+31 46 451 4460",
    "sg:postcode":"6131 AC",
    "sg:province":"Limburg",
    "wof:name":"Webers, A",
    "wof:placetype":"venue"
},
  "geometry": {"coordinates":[5.859141,50.999702],"type":"Point"}
}