{
  "type": "Feature",
  "properties": {
    "addr:full":"Veerwg 26 Numansdorp South Holland 3281 LX",
    "addr:housenumber":"26",
    "addr:postcode":"3281 lx",
    "addr:street":"Veerwg",
    "iso:country":"NL",
    "sg:address":"Veerwg 26",
    "sg:city":"Numansdorp",
    "sg:orig_category":"Sportverenigingen En Ontspannings- Verenigingen",
    "sg:phone":"+31 186 654 455",
    "sg:postcode":"3281 LX",
    "sg:province":"South Holland",
    "wof:name":"Cromstrijen, Golfclub",
    "wof:placetype":"venue"
},
  "geometry": {"coordinates":[4.41949,51.722099],"type":"Point"}
}