{
  "type": "Feature",
  "properties": {
    "addr:full":"A Paulownastr 95 S Gravenhage South Holland 2518 BC",
    "addr:housenumber":"95",
    "addr:postcode":"2518 bc",
    "addr:street":"S Gravenhage",
    "iso:country":"NL",
    "sg:address":"A Paulownastr 95",
    "sg:city":"S Gravenhage",
    "sg:orig_category":"Gordijnen",
    "sg:phone":"+31 70 427 9815",
    "sg:postcode":"2518 BC",
    "sg:province":"South Holland",
    "wof:name":"Jacques",
    "wof:placetype":"venue"
},
  "geometry": {"coordinates":[4.29348,52.080318],"type":"Point"}
}