{
  "type": "Feature",
  "properties": {
    "addr:full":"Dreef 1 Wadenoijen Gelderland 4014 MJ",
    "addr:housenumber":"1",
    "addr:postcode":"4014 mj",
    "addr:street":"Dreef;Gelderland",
    "iso:country":"NL",
    "sg:address":"Dreef 1",
    "sg:city":"Wadenoijen",
    "sg:classifiers":[
        {
            "category":"Education",
            "subcategory":"Preschool",
            "type":"Public Place"
        }
    ],
    "sg:phone":"+31 344 661 527",
    "sg:postcode":"4014 MJ",
    "sg:province":"Gelderland",
    "sg:tags":[
        "kleuteronderwijs",
        "basis-"
    ],
    "wof:name":"De Waayer",
    "wof:placetype":"venue"
},
  "geometry": {"coordinates":[5.373066,51.870449],"type":"Point"}
}