{
  "type": "Feature",
  "properties": {
    "iso:country":"NL",
    "sg:address":"Dominikanerk Str 3",
    "sg:city":"Maastricht",
    "sg:orig_category":"Glas, Porselein En Aardewerk",
    "sg:phone":"+31 43 321 4001",
    "sg:postcode":"6211 CZ",
    "sg:province":"Limburg",
    "wof:name":"Schoonbrood Roeland",
    "wof:placetype":"venue"
},
  "geometry": {"coordinates":[5.689742,50.849911],"type":"Point"}
}