{
  "type": "Feature",
  "properties": {
    "addr:full":"Chopinln 21 Helmond Noord-Brabant 5707 RD",
    "addr:housenumber":"21",
    "addr:postcode":"5707 rd",
    "addr:street":"Chopinln",
    "iso:country":"NL",
    "sg:address":"Chopinln 21",
    "sg:city":"Helmond",
    "sg:orig_category":"Adviesbureaus Bedrijfsorganisatie",
    "sg:phone":"+31 6 51038737",
    "sg:postcode":"5707 RD",
    "sg:province":"Noord-Brabant",
    "wof:name":"Vkm",
    "wof:placetype":"venue"
},
  "geometry": {"coordinates":[5.647379,51.488503],"type":"Point"}
}