{
  "type": "Feature",
  "properties": {
    "addr:full":"H Mulierstr 80 Haarlem North Holland 2024 VE",
    "addr:housenumber":"80",
    "addr:postcode":"2024",
    "addr:street":"Ve",
    "iso:country":"NL",
    "sg:address":"H Mulierstr 80",
    "sg:city":"Haarlem",
    "sg:orig_category":"Onderhoudswerken",
    "sg:phone":"+31 23 525 3867",
    "sg:postcode":"2024 VE",
    "sg:province":"North Holland",
    "wof:name":"Peters Onderhoudsbedrijf",
    "wof:placetype":"venue"
},
  "geometry": {"coordinates":[4.644177,52.403748],"type":"Point"}
}