{
  "type": "Feature",
  "properties": {
    "addr:full":"Beethovenlaan 134 Delft Zuid-Holland 2625 RT",
    "addr:housenumber":"134",
    "addr:postcode":"2625 rt",
    "addr:street":"Beethovenlaan",
    "iso:country":"NL",
    "sg:address":"Beethovenlaan 134",
    "sg:city":"Delft",
    "sg:orig_category":"Loodgieterswerk, Verwarming And Sanitaire Installaties",
    "sg:phone":"+31 15 262 1199",
    "sg:postcode":"2625 RT",
    "sg:province":"Zuid-Holland",
    "wof:name":"Centrale Verwarmingsbedrijf Rijnstreek Bv",
    "wof:placetype":"venue"
},
  "geometry": {"coordinates":[4.339166,51.989883],"type":"Point"}
}