{
  "type": "Feature",
  "properties": {
    "addr:full":"Hoogstraat 4 Purmerend Noord-Holland 1441  B",
    "addr:housenumber":"4;1441 b",
    "addr:street":"Hoogstraat",
    "iso:country":"NL",
    "sg:address":"Hoogstraat 4",
    "sg:city":"Purmerend",
    "sg:orig_category":"Boekenuitgeverijen",
    "sg:phone":"+31 299 434 455",
    "sg:postcode":"1441  B",
    "sg:province":"Noord-Holland",
    "wof:name":"Bruna",
    "wof:placetype":"venue"
},
  "geometry": {"coordinates":[4.945511,52.509537],"type":"Point"}
}