{
  "type": "Feature",
  "properties": {
    "addr:full":"A Schweitzerstr 11 Deurne North Brabant 5751 MG",
    "addr:housenumber":"11",
    "addr:postcode":"5751 mg",
    "iso:country":"NL",
    "sg:address":"A Schweitzerstr 11",
    "sg:city":"Deurne",
    "sg:classifiers":[
        {
            "category":"Personal",
            "subcategory":"Nail Salon",
            "type":"Services"
        }
    ],
    "sg:phone":"+31 493 311 350",
    "sg:postcode":"5751 MG",
    "sg:province":"North Brabant",
    "sg:tags":[
        "pedicure"
    ],
    "wof:name":"Lizanne",
    "wof:placetype":"venue"
},
  "geometry": {"coordinates":[5.797477,51.467644],"type":"Point"}
}