{
  "type": "Feature",
  "properties": {
    "addr:full":"De Hofstede 36 Lienden Gelderland 4033 BV",
    "addr:housenumber":"36",
    "addr:postcode":"4033 bv",
    "addr:street":"De Hofstede;Gelderland",
    "iso:country":"NL",
    "sg:address":"De Hofstede 36",
    "sg:city":"Lienden",
    "sg:orig_category":"Geluidsinstallaties - Verhuur",
    "sg:phone":"+31 344 604 803",
    "sg:postcode":"4033 BV",
    "sg:province":"Gelderland",
    "wof:name":"St",
    "wof:placetype":"venue"
},
  "geometry": {"coordinates":[5.520969,51.938927],"type":"Point"}
}