{
  "type": "Feature",
  "properties": {
    "addr:full":"Bronwg 4A Bornerbroek Overijssel 7627 NJ",
    "addr:housenumber":"4a",
    "addr:postcode":"7627 nj",
    "addr:street":"Bronwg",
    "iso:country":"NL",
    "sg:address":"Bronwg 4A",
    "sg:city":"Bornerbroek",
    "sg:orig_category":"Metselwerken",
    "sg:phone":"+31 74 384 1783",
    "sg:postcode":"7627 NJ",
    "sg:province":"Overijssel",
    "wof:name":"Oude Nijhuis, J H A",
    "wof:placetype":"venue"
},
  "geometry": {"coordinates":[6.651884,52.302315],"type":"Point"}
}