{
  "type": "Feature",
  "properties": {
    "addr:full":"Dorpsstr 70 Eckelrade Limburg 6252 NE",
    "addr:housenumber":"70",
    "addr:postcode":"6252 ne",
    "addr:street":"Dorpsstr",
    "iso:country":"NL",
    "sg:address":"Dorpsstr 70",
    "sg:city":"Eckelrade",
    "sg:orig_category":"Horloges En Klokken - Reparatie En Onderhoud",
    "sg:phone":"+31 43 408 2720",
    "sg:postcode":"6252 NE",
    "sg:province":"Limburg",
    "wof:name":"Driessen, H",
    "wof:placetype":"venue"
},
  "geometry": {"coordinates":[5.766055,50.806271],"type":"Point"}
}