{
  "type": "Feature",
  "properties": {
    "addr:full":"Rembrandtlaan 45 Sliedrecht Zuid-Holland 3362 AC",
    "addr:housenumber":"45",
    "addr:postcode":"3362 ac",
    "addr:street":"Rembrandtlaan",
    "iso:country":"NL",
    "sg:address":"Rembrandtlaan 45",
    "sg:city":"Sliedrecht",
    "sg:orig_category":"Huishoudapparatuur, Televisies And Radio'S",
    "sg:phone":"+31 184 413 336",
    "sg:postcode":"3362 AC",
    "sg:province":"Zuid-Holland",
    "wof:name":"Electrotechnisch Handelsbedrijf J. Van Dijk Bv",
    "wof:placetype":"venue"
},
  "geometry": {"coordinates":[4.775574,51.822376],"type":"Point"}
}