{
  "type": "Feature",
  "properties": {
    "iso:country":"NL",
    "sg:address":"Elandweide 2",
    "sg:city":"Nieuwegein",
    "sg:orig_category":"Schilders",
    "sg:phone":"+31 30 609 0104",
    "sg:postcode":"3437 CR",
    "sg:province":"Utrecht",
    "sg:website":"http://www.balfoortschilders.nl",
    "wof:name":"Balfoort Schilderwerk",
    "wof:placetype":"venue"
},
  "geometry": {"coordinates":[5.070216,52.042339],"type":"Point"}
}