{
  "type": "Feature",
  "properties": {
    "iso:country":"NL",
    "sg:address":"Dragsholm 1A",
    "sg:city":"Hoofddorp",
    "sg:orig_category":"Administratie- En Boekhoudkantoren",
    "sg:phone":"+31 23 562 4957",
    "sg:postcode":"2133 AM",
    "sg:province":"Noord-Holland",
    "wof:name":"Bootsman",
    "wof:placetype":"venue"
},
  "geometry": {"coordinates":[4.678843,52.312016],"type":"Point"}
}