{
  "type": "Feature",
  "properties": {
    "addr:full":"Marishof 62-64 Lichtenvoorde Gelderland 7131 TM",
    "addr:housenumber":"62-64",
    "addr:postcode":"7131 tm",
    "addr:street":"Marishof;Gelderland",
    "iso:country":"NL",
    "sg:address":"Marishof 62-64",
    "sg:city":"Lichtenvoorde",
    "sg:orig_category":"Kinderopvang",
    "sg:phone":"+31 900 9864",
    "sg:postcode":"7131 TM",
    "sg:province":"Gelderland",
    "wof:name":"Yunio",
    "wof:placetype":"venue"
},
  "geometry": {"coordinates":[6.573811,51.99361],"type":"Point"}
}