{
  "type": "Feature",
  "properties": {
    "addr:full":"Stobbenven 6 Roden Drenthe 9302 EP",
    "addr:housenumber":"6",
    "addr:postcode":"9302 ep",
    "addr:street":"Stobbenven",
    "iso:country":"NL",
    "sg:address":"Stobbenven 6",
    "sg:city":"Roden",
    "sg:orig_category":"Kantoor- En Secretariaatsservice",
    "sg:phone":"+31 6 12887515",
    "sg:postcode":"9302 EP",
    "sg:province":"Drenthe",
    "sg:website":"http://www.officelinq.nl",
    "wof:name":"Officelinq",
    "wof:placetype":"venue"
},
  "geometry": {"coordinates":[6.4028029442,53.1394119263],"type":"Point"}
}