{
  "type": "Feature",
  "properties": {
    "addr:full":"Prinses Beatrixstraat 54 Eck En Wiel Gelderland 4024 HN",
    "addr:housenumber":"54",
    "addr:postcode":"4024 hn",
    "addr:street":"Prinses Beatrixstraat",
    "iso:country":"NL",
    "sg:address":"Prinses Beatrixstraat 54",
    "sg:city":"Eck En Wiel",
    "sg:orig_category":"Wegen And Sportterreinen",
    "sg:phone":"+31 344 693 211",
    "sg:postcode":"4024 HN",
    "sg:province":"Gelderland",
    "wof:name":"Van Gelderen Wegenbouw",
    "wof:placetype":"venue"
},
  "geometry": {"coordinates":[5.4545822144,51.967628479],"type":"Point"}
}