{
  "type": "Feature",
  "properties": {
    "addr:full":"Waterrmanstraat 41 Apeldoorn Gelderland 7323 PZ",
    "addr:housenumber":"41",
    "addr:postcode":"7323 pz",
    "addr:street":"Waterrmanstraat;Gelderland",
    "iso:country":"NL",
    "sg:address":"Waterrmanstraat 41",
    "sg:city":"Apeldoorn",
    "sg:orig_category":"Werving And Selectie Van Tijdelijk Personeel And Uitzendkantoren",
    "sg:phone":"+31 55 366 1088",
    "sg:postcode":"7323 PZ",
    "sg:province":"Gelderland",
    "wof:name":"Ruac Bv",
    "wof:placetype":"venue"
},
  "geometry": {"coordinates":[5.984459877,52.2409210205],"type":"Point"}
}