{
  "type": "Feature",
  "properties": {
    "iso:country":"NL",
    "sg:address":"Binnenweg 1",
    "sg:city":"Staphorst",
    "sg:orig_category":"Huishoudapparatuur, Televisies And Radio'S",
    "sg:phone":"+31 522 462 176",
    "sg:postcode":"7951 DE",
    "sg:province":"Overijssel",
    "wof:name":"Elektro Winkelier E Akkerman",
    "wof:placetype":"venue"
},
  "geometry": {"coordinates":[6.206145,52.641991],"type":"Point"}
}