{
  "type": "Feature",
  "properties": {
    "addr:full":"Lijsterstr 17 Hapert Noord-Brabant 5527 HS",
    "addr:housenumber":"17",
    "addr:postcode":"5527 hs",
    "addr:street":"Lijsterstr",
    "iso:country":"NL",
    "sg:address":"Lijsterstr 17",
    "sg:city":"Hapert",
    "sg:classifiers":[
        {
            "category":"Personal",
            "subcategory":"Nail Salon",
            "type":"Services"
        }
    ],
    "sg:phone":"+31 497 382 661",
    "sg:postcode":"5527 HS",
    "sg:province":"Noord-Brabant",
    "sg:tags":[
        "pedicure"
    ],
    "wof:name":"Peters-Somers, M P S E",
    "wof:placetype":"venue"
},
  "geometry": {"coordinates":[5.250922,51.366718],"type":"Point"}
}