{
  "type": "Feature",
  "properties": {
    "iso:country":"NL",
    "sg:address":"Vlietsngl 18",
    "sg:city":"Medemblik",
    "sg:orig_category":"Verzekeringen - Verzekeringskantoren",
    "sg:phone":"+31 227 542 387",
    "sg:postcode":"1671 MZ",
    "sg:province":"Noord-Holland",
    "wof:name":"Hoogendijk, J P Th",
    "wof:placetype":"venue"
},
  "geometry": {"coordinates":[5.106715,52.771942],"type":"Point"}
}