{
  "type": "Feature",
  "properties": {
    "addr:full":"Grebbebergln 76 Eindhoven North Brabant 5628 GK",
    "addr:housenumber":"76",
    "addr:postcode":"5628 gk",
    "addr:street":"Grebbebergln",
    "iso:country":"NL",
    "sg:address":"Grebbebergln 76",
    "sg:city":"Eindhoven",
    "sg:orig_category":"Artsen - Huisartsen",
    "sg:phone":"+31 40 241 1227",
    "sg:postcode":"5628 GK",
    "sg:province":"North Brabant",
    "wof:name":"Heijl, D J C",
    "wof:placetype":"venue"
},
  "geometry": {"coordinates":[5.461797,51.481327],"type":"Point"}
}