{
  "type": "Feature",
  "properties": {
    "addr:full":"Maelsonstr 12 Hoorn Nh Noord-Holland 1624 NP",
    "addr:housenumber":"12",
    "addr:postcode":"1624 np",
    "addr:street":"Maelsonstr",
    "iso:country":"NL",
    "sg:address":"Maelsonstr 12",
    "sg:city":"Hoorn Nh",
    "sg:orig_category":"Woningbouw- Verenigingen En -Stichtingen",
    "sg:phone":"+31 229 258 500",
    "sg:postcode":"1624 NP",
    "sg:province":"Noord-Holland",
    "wof:name":"Intermaris Woondiensten",
    "wof:placetype":"venue"
},
  "geometry": {"coordinates":[5.05392313,52.6490478516],"type":"Point"}
}