{
  "type": "Feature",
  "properties": {
    "addr:full":"Vlietstraat 29 Sleeuwijk Noord-Brabant 4254 AD",
    "addr:housenumber":"29",
    "addr:postcode":"4254 ad",
    "addr:street":"Vlietstraat",
    "iso:country":"NL",
    "sg:address":"Vlietstraat 29",
    "sg:city":"Sleeuwijk",
    "sg:orig_category":"Autokeuringen",
    "sg:phone":"+31 183 303 247",
    "sg:postcode":"4254 AD",
    "sg:province":"Noord-Brabant",
    "wof:name":"Gebr. Van Krugten",
    "wof:placetype":"venue"
},
  "geometry": {"coordinates":[4.949959,51.812038],"type":"Point"}
}