{
  "type": "Feature",
  "properties": {
    "addr:full":"S Robertsonstr 6 Spykenisse Zuid-Holland 3207 VN",
    "addr:housenumber":"6",
    "addr:postcode":"spykenisse;3207 vn",
    "iso:country":"NL",
    "sg:address":"S Robertsonstr 6",
    "sg:city":"Spykenisse",
    "sg:orig_category":"Administratie- En Boekhoudkantoren",
    "sg:phone":"+31 181 643 490",
    "sg:postcode":"3207 VN",
    "sg:province":"Zuid-Holland",
    "wof:name":"Afdn",
    "wof:placetype":"venue"
},
  "geometry": {"coordinates":[4.364837,51.836403],"type":"Point"}
}