{
  "type": "Feature",
  "properties": {
    "addr:full":"Viaductwg 19 S Gravenhage South Holland 2525 KK",
    "addr:housenumber":"19",
    "addr:postcode":"2525 kk",
    "addr:street":"Viaductwg;S Gravenhage",
    "iso:country":"NL",
    "sg:address":"Viaductwg 19",
    "sg:city":"S Gravenhage",
    "sg:orig_category":"Onderhoudswerken",
    "sg:phone":"+31 70 380 1774",
    "sg:postcode":"2525 KK",
    "sg:province":"South Holland",
    "wof:name":"Blokdijk, A",
    "wof:placetype":"venue"
},
  "geometry": {"coordinates":[4.30248,52.062462],"type":"Point"}
}