{
  "type": "Feature",
  "properties": {
    "addr:full":"Speerpuntkreek 37 Wassenaar South Holland 2241 MS",
    "addr:housenumber":"37",
    "addr:postcode":"2241 ms",
    "addr:street":"Speerpuntkreek",
    "iso:country":"NL",
    "sg:address":"Speerpuntkreek 37",
    "sg:city":"Wassenaar",
    "sg:orig_category":"Bloemen And Planten Gh",
    "sg:phone":"+31 70 511 8698",
    "sg:postcode":"2241 MS",
    "sg:province":"South Holland",
    "wof:name":"Theo Vollebregt Flowers",
    "wof:placetype":"venue"
},
  "geometry": {"coordinates":[4.410943,52.15274],"type":"Point"}
}