{
  "type": "Feature",
  "properties": {
    "addr:full":"Molenstraat 1 Bladel Noord-Brabant 5531 EC",
    "addr:housenumber":"1",
    "addr:postcode":"5531 ec",
    "addr:street":"Molenstraat",
    "iso:country":"NL",
    "sg:address":"Molenstraat 1",
    "sg:city":"Bladel",
    "sg:orig_category":"Werving And Selectie Van Tijdelijk Personeel And Uitzendkantoren",
    "sg:phone":"+31 497 387 363",
    "sg:postcode":"5531 EC",
    "sg:province":"Noord-Brabant",
    "wof:name":"Creyf'S Interim",
    "wof:placetype":"venue"
},
  "geometry": {"coordinates":[5.2219719887,51.3677101135],"type":"Point"}
}