{
  "type": "Feature",
  "properties": {
    "addr:full":"Marsdiep 13 Urk Flevoland 8321 MC",
    "addr:housenumber":"13;8321",
    "addr:street":"Marsdiep;Flevoland;Mc",
    "iso:country":"NL",
    "sg:address":"Marsdiep 13",
    "sg:city":"Urk",
    "sg:orig_category":"Goederenvervoer Over De Weg",
    "sg:phone":"+31 527 681 664",
    "sg:postcode":"8321 MC",
    "sg:province":"Flevoland",
    "wof:name":"Mulder V/H De Vries Transport- Expeditiebedrijf Bv",
    "wof:placetype":"venue"
},
  "geometry": {"coordinates":[5.618569,52.65527],"type":"Point"}
}