{
  "type": "Feature",
  "properties": {
    "addr:full":"Meije 66 Bodegraven South Holland 2411 PK",
    "addr:housenumber":"66",
    "addr:postcode":"2411 pk",
    "addr:street":"Meije",
    "iso:country":"NL",
    "sg:address":"Meije 66",
    "sg:city":"Bodegraven",
    "sg:orig_category":"Autokeuringen",
    "sg:phone":"+31 172 685 544",
    "sg:postcode":"2411 PK",
    "sg:province":"South Holland",
    "wof:name":"Autobedrijf Toon Van Eijk",
    "wof:placetype":"venue"
},
  "geometry": {"coordinates":[4.762133,52.113564],"type":"Point"}
}