{
  "type": "Feature",
  "properties": {
    "iso:country":"NL",
    "sg:address":"Kolholsterweg 5",
    "sg:city":"Zijldijk",
    "sg:orig_category":"Hoefdierhouderijen",
    "sg:phone":"+31 596 581 463",
    "sg:postcode":"9987 NL",
    "sg:province":"Groningen",
    "wof:name":"Stal Nijhoff",
    "wof:placetype":"venue"
},
  "geometry": {"coordinates":[6.776355,53.397671],"type":"Point"}
}