{
  "type": "Feature",
  "properties": {
    "addr:full":"Klarendalseweg 271 Arnhem Gelderland 6822 GL",
    "addr:housenumber":"271",
    "addr:postcode":"6822 gl",
    "addr:street":"Klarendalseweg",
    "iso:country":"NL",
    "sg:address":"Klarendalseweg 271",
    "sg:city":"Arnhem",
    "sg:orig_category":"Autokeuringen",
    "sg:phone":"+31 26 445 1271",
    "sg:postcode":"6822 GL",
    "sg:province":"Gelderland",
    "wof:name":"Vof Autoservice Storteboom/Berendsen",
    "wof:placetype":"venue"
},
  "geometry": {"coordinates":[5.927969,51.992077],"type":"Point"}
}