{
  "type": "Feature",
  "properties": {
    "addr:full":"Kattenburgerstr 150 Amsterdam North Holland 1018 JH",
    "addr:housenumber":"150",
    "addr:postcode":"1018 jh",
    "iso:country":"NL",
    "sg:address":"Kattenburgerstr 150",
    "sg:city":"Amsterdam",
    "sg:orig_category":"Verenigingsgebouwen",
    "sg:phone":"+31 20 626 7844",
    "sg:postcode":"1018 JH",
    "sg:province":"North Holland",
    "wof:name":"Ver Nieuw Kattenburg",
    "wof:placetype":"venue"
},
  "geometry": {"coordinates":[4.919349,52.373035],"type":"Point"}
}