{
  "type": "Feature",
  "properties": {
    "addr:full":"Hoflaan 1 Loenen A/D Vecht Utrecht 3632 BT",
    "addr:housenumber":"1;a / d",
    "addr:postcode":"3632 bt",
    "addr:street":"Hoflaan;Vecht",
    "iso:country":"NL",
    "sg:address":"Hoflaan 1",
    "sg:city":"Loenen A/D Vecht",
    "sg:classifiers":[
        {
            "category":"Professional",
            "subcategory":"Accounting & Tax Preparation",
            "type":"Services"
        }
    ],
    "sg:phone":"+31 294 234 624",
    "sg:postcode":"3632 BT",
    "sg:province":"Utrecht",
    "sg:tags":[
        "accountant"
    ],
    "wof:name":"Mevrouw S. Harms -Van Estrik",
    "wof:placetype":"venue"
},
  "geometry": {"coordinates":[5.017996,52.208923],"type":"Point"}
}