{
  "type": "Feature",
  "properties": {
    "addr:full":"Hildo Kroplaan 133 'S Gravenhage South Holland 2552 XR",
    "addr:housenumber":"133 '",
    "addr:postcode":"2552 xr",
    "addr:street":"Hildo Kroplaan",
    "iso:country":"NL",
    "sg:address":"Hildo Kroplaan 133",
    "sg:city":"'S Gravenhage",
    "sg:orig_category":"Metaalwerken",
    "sg:phone":"+31 70 391 0939",
    "sg:postcode":"2552 XR",
    "sg:province":"South Holland",
    "wof:name":"Cnm",
    "wof:placetype":"venue"
},
  "geometry": {"coordinates":[4.249885,52.054482],"type":"Point"}
}