{
  "type": "Feature",
  "properties": {
    "addr:full":"Jonge Arnoldusstraat 37 Zaandam Noord-Holland 1501 VR",
    "addr:housenumber":"37",
    "addr:postcode":"1501 vr",
    "addr:street":"Jonge Arnoldusstraat",
    "iso:country":"NL",
    "sg:address":"Jonge Arnoldusstraat 37",
    "sg:city":"Zaandam",
    "sg:classifiers":[
        {
            "category":"Education",
            "subcategory":"Preschool",
            "type":"Public Place"
        }
    ],
    "sg:phone":"+31 75 616 3348",
    "sg:postcode":"1501 VR",
    "sg:province":"Noord-Holland",
    "sg:tags":[
        "kleuteronderwijs",
        "basis-"
    ],
    "wof:name":"Christelijke Basisschool Tamarinde",
    "wof:placetype":"venue"
},
  "geometry": {"coordinates":[4.833134,52.435482],"type":"Point"}
}