{
  "type": "Feature",
  "properties": {
    "addr:full":"Jan Tooropstraat 14 Almelo Overijssel 7606 JT",
    "addr:housenumber":"14",
    "addr:postcode":"7606 jt",
    "addr:street":"Jan Tooropstraat",
    "iso:country":"NL",
    "sg:address":"Jan Tooropstraat 14",
    "sg:city":"Almelo",
    "sg:orig_category":"Technische Studies And Onderzoek",
    "sg:phone":"+31 546 827 298",
    "sg:postcode":"7606 JT",
    "sg:province":"Overijssel",
    "wof:name":"P.A. Hoebink",
    "wof:placetype":"venue"
},
  "geometry": {"coordinates":[6.642003,52.343414],"type":"Point"}
}