{
  "type": "Feature",
  "properties": {
    "addr:full":"Waalbroek 3 Simpelveld Limburg 6369 TE",
    "addr:housenumber":"3",
    "addr:postcode":"6369 te",
    "addr:street":"Waalbroek",
    "iso:country":"NL",
    "sg:address":"Waalbroek 3",
    "sg:city":"Simpelveld",
    "sg:orig_category":"Bedrijfs- And Managementsconsultants",
    "sg:phone":"+31 45 568 8830",
    "sg:postcode":"6369 TE",
    "sg:province":"Limburg",
    "wof:name":"Westerhoutgroep",
    "wof:placetype":"venue"
},
  "geometry": {"coordinates":[5.992889,50.828678],"type":"Point"}
}