{
  "type": "Feature",
  "properties": {
    "addr:full":"Fokkerstr 23 Leusden Utrecht 3833 LD",
    "addr:housenumber":"23",
    "addr:postcode":"3833 ld",
    "addr:street":"Fokkerstr",
    "iso:country":"NL",
    "sg:address":"Fokkerstr 23",
    "sg:city":"Leusden",
    "sg:classifiers":[
        {
            "category":"Sports & Exercise",
            "subcategory":"Stables",
            "type":"Entertainment"
        }
    ],
    "sg:phone":"+31 33 433 2220",
    "sg:postcode":"3833 LD",
    "sg:province":"Utrecht",
    "sg:tags":[
        "maneges"
    ],
    "wof:name":"Nieuw Hagenauwe",
    "wof:placetype":"venue"
},
  "geometry": {"coordinates":[5.416832,52.145226],"type":"Point"}
}