{
  "type": "Feature",
  "properties": {
    "iso:country":"NL",
    "sg:address":"Eursing 2",
    "sg:city":"Beilen",
    "sg:orig_category":"Hypotheken And Hypotheekbanken",
    "sg:phone":"+31 593 522 499",
    "sg:postcode":"9411 XC",
    "sg:province":"Drenthe",
    "wof:name":"Visscher & De Boer Assurantiegroep",
    "wof:placetype":"venue"
},
  "geometry": {"coordinates":[6.5239,52.876347],"type":"Point"}
}