{
  "type": "Feature",
  "properties": {
    "addr:full":"Oudegr 84 Utrecht Utrecht 3511 AT",
    "addr:housenumber":"84",
    "addr:postcode":"3511",
    "addr:street":"Oudegr",
    "iso:country":"NL",
    "sg:address":"Oudegr 84",
    "sg:city":"Utrecht",
    "sg:orig_category":"Psychotherapeuten",
    "sg:phone":"+31 30 231 6080",
    "sg:postcode":"3511 AT",
    "sg:province":"Utrecht",
    "sg:website":"http://www.oudegracht84.nl",
    "wof:name":"Oudegracht Psychotherapieprakt",
    "wof:placetype":"venue"
},
  "geometry": {"coordinates":[5.115405,52.088932],"type":"Point"}
}