{
  "type": "Feature",
  "properties": {
    "addr:full":"Annie M G Schmidtplein 14 Waalwijk North Brabant 5144 ZB",
    "addr:housenumber":"14",
    "addr:postcode":"5144 zb",
    "addr:street":"Annie M;Schmidtplein",
    "iso:country":"NL",
    "sg:address":"Annie M G Schmidtplein 14",
    "sg:city":"Waalwijk",
    "sg:orig_category":"Vertaal- And Tolkenbureaus",
    "sg:phone":"+31 416 331 586",
    "sg:postcode":"5144 ZB",
    "sg:province":"North Brabant",
    "wof:name":"Carmen Van Loon Sodoleanu",
    "wof:placetype":"venue"
},
  "geometry": {"coordinates":[5.067639,51.672211],"type":"Point"}
}