{
  "type": "Feature",
  "properties": {
    "addr:full":"Lisdodde 60 Drachten Provincie Friesland 9207 AT",
    "addr:housenumber":"60",
    "addr:postcode":"9207",
    "addr:street":"Lisdodde;Provincie Friesland",
    "iso:country":"NL",
    "sg:address":"Lisdodde 60",
    "sg:city":"Drachten",
    "sg:orig_category":"Vakorganisaties",
    "sg:phone":"+31 512 544 512",
    "sg:postcode":"9207 AT",
    "sg:province":"Provincie Friesland",
    "wof:name":"Vlbv/Beeldaspecten",
    "wof:placetype":"venue"
},
  "geometry": {"coordinates":[6.095541,53.120857],"type":"Point"}
}