{
  "type": "Feature",
  "properties": {
    "iso:country":"NL",
    "sg:address":"Koninginneplein 3",
    "sg:city":"Oosterland",
    "sg:orig_category":"Boekhouders",
    "sg:phone":"+31 111 641 232",
    "sg:postcode":"4307 BA",
    "sg:province":"Zeeland",
    "wof:name":"Administratiekantoor Stuy",
    "wof:placetype":"venue"
},
  "geometry": {"coordinates":[4.037133,51.649818],"type":"Point"}
}