{
  "type": "Feature",
  "properties": {
    "addr:full":"Eperweg 46 Nunspeet Gelderland 8072 DB",
    "addr:housenumber":"46",
    "addr:postcode":"8072 db",
    "addr:street":"Eperweg;Gelderland",
    "iso:country":"NL",
    "sg:address":"Eperweg 46",
    "sg:city":"Nunspeet",
    "sg:orig_category":"Woningbouwverenigingen",
    "sg:phone":"+31 341 255 911",
    "sg:postcode":"8072 DB",
    "sg:province":"Gelderland",
    "wof:name":"De Sparrenhorst",
    "wof:placetype":"venue"
},
  "geometry": {"coordinates":[5.7876110077,52.3765182495],"type":"Point"}
}