{
  "type": "Feature",
  "properties": {
    "iso:country":"NL",
    "sg:address":"Merelhof 26",
    "sg:city":"Norg",
    "sg:orig_category":"Administratie- En Boekhoudkantoren",
    "sg:phone":"+31 592 613 043",
    "sg:postcode":"9331 KL",
    "sg:province":"Drenthe",
    "wof:name":"Hagenouw",
    "wof:placetype":"venue"
},
  "geometry": {"coordinates":[6.447402,53.065334],"type":"Point"}
}