{
  "type": "Feature",
  "properties": {
    "addr:full":"Wega 76 Dordrecht South Holland 3328 PJ",
    "addr:housenumber":"76",
    "addr:postcode":"3328 pj",
    "addr:street":"Wega",
    "iso:country":"NL",
    "sg:address":"Wega 76",
    "sg:city":"Dordrecht",
    "sg:orig_category":"Glaszetten",
    "sg:phone":"+31 78 617 9910",
    "sg:postcode":"3328 PJ",
    "sg:province":"South Holland",
    "wof:name":"M & R De Grijp",
    "wof:placetype":"venue"
},
  "geometry": {"coordinates":[4.674799,51.778683],"type":"Point"}
}