{
  "type": "Feature",
  "properties": {
    "iso:country":"NL",
    "sg:address":"In De Cramer 166",
    "sg:city":"Heerlen",
    "sg:orig_category":"Keukens",
    "sg:phone":"+31 45 575 4240",
    "sg:postcode":"6412 PM",
    "sg:province":"Limburg",
    "sg:website":"http://www.brugman.nl",
    "wof:name":"Brugman",
    "wof:placetype":"venue"
},
  "geometry": {"coordinates":[5.942476,50.900349],"type":"Point"}
}