{
  "type": "Feature",
  "properties": {
    "addr:full":"Van Bijnkershoeklaan 89 Utrecht Utrecht 3527 XB",
    "addr:housenumber":"89",
    "addr:postcode":"3527 xb",
    "addr:street":"Van Bijnkershoeklaan",
    "iso:country":"NL",
    "sg:address":"Van Bijnkershoeklaan 89",
    "sg:city":"Utrecht",
    "sg:orig_category":"Farmaceutische Producten Gh",
    "sg:phone":"+31 30 296 1664",
    "sg:postcode":"3527 XB",
    "sg:province":"Utrecht",
    "wof:name":"Keyvox Benelux",
    "wof:placetype":"venue"
},
  "geometry": {"coordinates":[5.096219,52.079502],"type":"Point"}
}