{
  "type": "Feature",
  "properties": {
    "iso:country":"NL",
    "sg:address":"Orthen 16",
    "sg:city":"S Hertogenbosch",
    "sg:orig_category":"Meubelen",
    "sg:phone":"+31 73 614 6080",
    "sg:postcode":"5231 XS",
    "sg:province":"North Brabant",
    "wof:name":"Fantasie",
    "wof:placetype":"venue"
},
  "geometry": {"coordinates":[5.302976,51.704464],"type":"Point"}
}