{
  "type": "Feature",
  "properties": {
    "iso:country":"NL",
    "sg:address":"Van Oldenbarneveltplein 5",
    "sg:city":"Dordrecht",
    "sg:orig_category":"Huishoudapparatuur, Televisies And Radio'S",
    "sg:phone":"+31 78 618 7400",
    "sg:postcode":"3317 EP",
    "sg:province":"Zuid-Holland",
    "wof:name":"De Heer Reparatie & Onderdelen Serv. Europart",
    "wof:placetype":"venue"
},
  "geometry": {"coordinates":[4.663603,51.79105],"type":"Point"}
}