{
  "type": "Feature",
  "properties": {
    "addr:full":"Dukatenburg 78 Nieuwegein Utrecht 3437 AE",
    "addr:housenumber":"78",
    "addr:postcode":"3437 ae",
    "addr:street":"Dukatenburg",
    "iso:country":"NL",
    "sg:address":"Dukatenburg 78",
    "sg:city":"Nieuwegein",
    "sg:orig_category":"Verenigingen En Stichtingen",
    "sg:phone":"+31 30 605 6399",
    "sg:postcode":"3437 AE",
    "sg:province":"Utrecht",
    "wof:name":"Geotextiel Org, Ned",
    "wof:placetype":"venue"
},
  "geometry": {"coordinates":[5.077939,52.040203],"type":"Point"}
}