{
  "type": "Feature",
  "properties": {
    "addr:full":"Prinsengracht 757 Amsterdam Noord-Holland 1017 JZ",
    "addr:housenumber":"757",
    "addr:postcode":"1017 jz",
    "addr:street":"Prinsengracht",
    "iso:country":"NL",
    "sg:address":"Prinsengracht 757",
    "sg:city":"Amsterdam",
    "sg:orig_category":"Geluidsopnamen",
    "sg:phone":"+31 20 626 9277",
    "sg:postcode":"1017 JZ",
    "sg:province":"Noord-Holland",
    "wof:name":"Studio Le Roy",
    "wof:placetype":"venue"
},
  "geometry": {"coordinates":[4.886608,52.364029],"type":"Point"}
}