{
  "type": "Feature",
  "properties": {
    "addr:full":"Prinsengracht 526 Amsterdam Noord-Holland 1017 KJ",
    "addr:housenumber":"526",
    "addr:postcode":"1017 kj",
    "addr:street":"Prinsengracht",
    "iso:country":"NL",
    "sg:address":"Prinsengracht 526",
    "sg:city":"Amsterdam",
    "sg:orig_category":"Architecten",
    "sg:phone":"+31 20 624 4380",
    "sg:postcode":"1017 KJ",
    "sg:province":"Noord-Holland",
    "wof:name":"Architectenbureau Jowa Bv",
    "wof:placetype":"venue"
},
  "geometry": {"coordinates":[4.886338,52.363346],"type":"Point"}
}