{
  "type": "Feature",
  "properties": {
    "addr:full":"Venneperweg 457 Nieuw Vennep North Holland 2153 AD",
    "addr:housenumber":"457",
    "addr:postcode":"2153 ad",
    "addr:street":"Venneperweg;Nieuw Vennep North",
    "iso:country":"NL",
    "sg:address":"Venneperweg 457",
    "sg:city":"Nieuw Vennep",
    "sg:classifiers":[
        {
            "category":"Fast Food",
            "type":"Food & Drink"
        }
    ],
    "sg:phone":"+31 252 689 568",
    "sg:postcode":"2153 AD",
    "sg:province":"North Holland",
    "sg:tags":[
        "afhaal",
        "restaurant"
    ],
    "wof:name":"Pizzeria Shoarma Mamma Mia",
    "wof:placetype":"venue"
},
  "geometry": {"coordinates":[4.636558,52.263554],"type":"Point"}
}