{
  "type": "Feature",
  "properties": {
    "addr:full":"Melkwg 38 Goirle North Brabant 5051 VH",
    "addr:housenumber":"38",
    "addr:postcode":"5051 vh",
    "addr:street":"Melkwg",
    "iso:country":"NL",
    "sg:address":"Melkwg 38",
    "sg:city":"Goirle",
    "sg:orig_category":"Onderhoudswerken",
    "sg:phone":"+31 13 534 7249",
    "sg:postcode":"5051 VH",
    "sg:province":"North Brabant",
    "wof:name":"Laat, A A W M De",
    "wof:placetype":"venue"
},
  "geometry": {"coordinates":[5.07535,51.522804],"type":"Point"}
}