{
  "type": "Feature",
  "properties": {
    "addr:full":"Zwarte Zeestr 14 Emmeloord Flevoland 8303 EW",
    "addr:housenumber":"14",
    "addr:postcode":"8303 ew",
    "addr:street":"Flevoland",
    "iso:country":"NL",
    "sg:address":"Zwarte Zeestr 14",
    "sg:city":"Emmeloord",
    "sg:orig_category":"Honden- En Kattentrimsalons",
    "sg:phone":"+31 527 699 216",
    "sg:postcode":"8303 EW",
    "sg:province":"Flevoland",
    "wof:name":"Tanja",
    "wof:placetype":"venue"
},
  "geometry": {"coordinates":[5.735264,52.710178],"type":"Point"}
}