{
  "type": "Feature",
  "properties": {
    "addr:full":"Breudk 1A Harmelen Utrecht 3481 LM",
    "addr:housenumber":"1a",
    "addr:postcode":"3481 lm",
    "addr:street":"Breudk",
    "iso:country":"NL",
    "sg:address":"Breudk 1A",
    "sg:city":"Harmelen",
    "sg:orig_category":"Kunststoffen- Verwerkende Industrie",
    "sg:phone":"+31 348 434 332",
    "sg:postcode":"3481 LM",
    "sg:province":"Utrecht",
    "wof:name":"Leisure Lightweight",
    "wof:placetype":"venue"
},
  "geometry": {"coordinates":[4.94282,52.099739],"type":"Point"}
}