{
  "type": "Feature",
  "properties": {
    "addr:full":"Burgemeester V Geusauwg 20 Geldermalsen Gelderland 4191 KW",
    "addr:housenumber":"20",
    "addr:postcode":"4191 kw",
    "addr:street":"Burgemeester V Geusauwg;Gelderland",
    "iso:country":"NL",
    "sg:address":"Burgemeester V Geusauwg 20",
    "sg:city":"Geldermalsen",
    "sg:orig_category":"Loodgieterswerk, Verwarming And Sanitaire Installaties",
    "sg:phone":"+31 345 572 780",
    "sg:postcode":"4191 KW",
    "sg:province":"Gelderland",
    "wof:name":"Ing. J.Th. Duin",
    "wof:placetype":"venue"
},
  "geometry": {"coordinates":[5.275111,51.883244],"type":"Point"}
}