{
  "type": "Feature",
  "properties": {
    "addr:full":"Batteryln 4 Bussum Noord-Holland 1402 SN",
    "addr:housenumber":"4;1402",
    "addr:postcode":"sn",
    "addr:street":"Batteryln",
    "iso:country":"NL",
    "sg:address":"Batteryln 4",
    "sg:city":"Bussum",
    "sg:orig_category":"Projectontwikkeling",
    "sg:phone":"+31 35 693 0646",
    "sg:postcode":"1402 SN",
    "sg:province":"Noord-Holland",
    "wof:name":"Splinter Bv, A G M",
    "wof:placetype":"venue"
},
  "geometry": {"coordinates":[5.162605,52.276829],"type":"Point"}
}