{
  "type": "Feature",
  "properties": {
    "addr:full":"Heiveld 12 Rysbergen North Brabant 4891 VC",
    "addr:housenumber":"12",
    "addr:postcode":"4891 vc",
    "addr:street":"Heiveld",
    "iso:country":"NL",
    "sg:address":"Heiveld 12",
    "sg:city":"Rysbergen",
    "sg:orig_category":"Verzekeringen - Verzekeringskantoren",
    "sg:phone":"+31 76 596 3474",
    "sg:postcode":"4891 VC",
    "sg:province":"North Brabant",
    "wof:name":"Berenschot",
    "wof:placetype":"venue"
},
  "geometry": {"coordinates":[4.693415,51.519352],"type":"Point"}
}