{
  "type": "Feature",
  "properties": {
    "addr:full":"Koestr 58 Schoonhoven Zuid-Holland 2871 DR",
    "addr:housenumber":"58;2871",
    "addr:postcode":"dr",
    "addr:street":"Koestr",
    "iso:country":"NL",
    "sg:address":"Koestr 58",
    "sg:city":"Schoonhoven",
    "sg:orig_category":"Loodgieters",
    "sg:phone":"+31 182 382 573",
    "sg:postcode":"2871 DR",
    "sg:province":"Zuid-Holland",
    "wof:name":"Dam, L Van",
    "wof:placetype":"venue"
},
  "geometry": {"coordinates":[4.850584,51.945286],"type":"Point"}
}