{
  "type": "Feature",
  "properties": {
    "iso:country":"NL",
    "sg:address":"Wilhelminasngl 44",
    "sg:city":"Maastricht",
    "sg:orig_category":"Podotherapeuten",
    "sg:phone":"+31 43 321 2386",
    "sg:postcode":"6221 BK",
    "sg:province":"Limburg",
    "wof:name":"Limpt, L J H Van",
    "wof:placetype":"venue"
},
  "geometry": {"coordinates":[5.70527,50.850399],"type":"Point"}
}