{
  "type": "Feature",
  "properties": {
    "addr:full":"Annie Romeinsingel 72 Leiden Zuid-Holland 2331 ST",
    "addr:housenumber":"72",
    "addr:postcode":"2331 st",
    "addr:street":"Annie Romeinsingel",
    "iso:country":"NL",
    "sg:address":"Annie Romeinsingel 72",
    "sg:city":"Leiden",
    "sg:orig_category":"Glaszetten",
    "sg:phone":"+31 71 579 0235",
    "sg:postcode":"2331 ST",
    "sg:province":"Zuid-Holland",
    "wof:name":"Glaszettersbedrijf I. Hartevelt",
    "wof:placetype":"venue"
},
  "geometry": {"coordinates":[4.452994,52.145161],"type":"Point"}
}