{
  "type": "Feature",
  "properties": {
    "addr:full":"Kamille 10 Sprang Capelle North Brabant 5161 XV",
    "addr:housenumber":"10",
    "addr:postcode":"5161 xv",
    "addr:street":"Kamille",
    "iso:country":"NL",
    "sg:address":"Kamille 10",
    "sg:city":"Sprang Capelle",
    "sg:orig_category":"Webdesign Bureaus",
    "sg:phone":"+31 416 540 999",
    "sg:postcode":"5161 XV",
    "sg:province":"North Brabant",
    "sg:website":"http://www.lifestyle-media.nl",
    "wof:name":"Lifestyle, Graphic Designs",
    "wof:placetype":"venue"
},
  "geometry": {"coordinates":[5.0234289169,51.6756629944],"type":"Point"}
}