{
  "type": "Feature",
  "properties": {
    "addr:full":"Stationsstr 17/C Swalmen Limburg 6071 KA",
    "addr:housenumber":"17 / c",
    "addr:postcode":"6071 ka",
    "addr:street":"Stationsstr",
    "iso:country":"NL",
    "sg:address":"Stationsstr 17/C",
    "sg:city":"Swalmen",
    "sg:orig_category":"Adviesbureaus Bouwkunde",
    "sg:phone":"+31 475 508 074",
    "sg:postcode":"6071 KA",
    "sg:province":"Limburg",
    "wof:name":"Geraedts",
    "wof:placetype":"venue"
},
  "geometry": {"coordinates":[6.035672,51.23489],"type":"Point"}
}