{
  "type": "Feature",
  "properties": {
    "iso:country":"NL",
    "sg:address":"Marktlaan 28",
    "sg:city":"Hoofddorp",
    "sg:orig_category":"Herenmodezaken",
    "sg:phone":"+31 23 564 3108",
    "sg:postcode":"2132 DM",
    "sg:province":"Noord-Holland",
    "wof:name":"Dubelaar Herenmode",
    "wof:placetype":"venue"
},
  "geometry": {"coordinates":[4.693231,52.303612],"type":"Point"}
}