{
  "type": "Feature",
  "properties": {
    "addr:full":"Marktlaan 28 Hoofddorp Noord-Holland 2132 DM",
    "addr:housenumber":"28",
    "addr:postcode":"2132 dm",
    "addr:street":"Marktlaan",
    "iso:country":"NL",
    "sg:address":"Marktlaan 28",
    "sg:city":"Hoofddorp",
    "sg:orig_category":"Herenmodezaken",
    "sg:phone":"+31 23 564 3108",
    "sg:postcode":"2132 DM",
    "sg:province":"Noord-Holland",
    "wof:name":"Dubelaar Herenmode",
    "wof:placetype":"venue"
},
  "geometry": {"coordinates":[4.693231,52.303612],"type":"Point"}
}