{
  "type": "Feature",
  "properties": {
    "addr:full":"S Gravenstr 30 S Gravenpolder Zeeland 4431 AC",
    "addr:housenumber":"30",
    "addr:postcode":"4431 ac",
    "addr:street":"S Gravenpolder Zeeland",
    "iso:country":"NL",
    "sg:address":"S Gravenstr 30",
    "sg:city":"S Gravenpolder",
    "sg:orig_category":"Zonweringen",
    "sg:phone":"+31 113 312 044",
    "sg:postcode":"4431 AC",
    "sg:province":"Zeeland",
    "wof:name":"Rollux Zonwering",
    "wof:placetype":"venue"
},
  "geometry": {"coordinates":[3.900565,51.458294],"type":"Point"}
}