{
  "type": "Feature",
  "properties": {
    "addr:full":"Antoniusln 45 Venlo Limburg 5921 KB",
    "addr:housenumber":"45",
    "addr:postcode":"5921 kb",
    "addr:street":"Antoniusln",
    "iso:country":"NL",
    "sg:address":"Antoniusln 45",
    "sg:city":"Venlo",
    "sg:orig_category":"Makelaars En Adviseurs Onroerende Goederen",
    "sg:phone":"+31 77 323 0707",
    "sg:postcode":"5921 KB",
    "sg:province":"Limburg",
    "wof:name":"Dohmen, Jo",
    "wof:placetype":"venue"
},
  "geometry": {"coordinates":[6.156649,51.368168],"type":"Point"}
}