{
  "type": "Feature",
  "properties": {
    "addr:full":"Marketentster 2 Hoorn Nh Noord-Holland 1625 WB",
    "addr:housenumber":"2",
    "addr:postcode":"1625 wb",
    "addr:street":"Marketentster",
    "iso:country":"NL",
    "sg:address":"Marketentster 2",
    "sg:city":"Hoorn Nh",
    "sg:classifiers":[
        {
            "category":"Education",
            "subcategory":"Preschool",
            "type":"Public Place"
        }
    ],
    "sg:phone":"+31 229 230 251",
    "sg:postcode":"1625 WB",
    "sg:province":"Noord-Holland",
    "sg:tags":[
        "kleuteronderwijs",
        "basis-"
    ],
    "wof:name":"Oecumenisch Basisschool De Rakkers",
    "wof:placetype":"venue"
},
  "geometry": {"coordinates":[5.047933,52.655598],"type":"Point"}
}