{
  "type": "Feature",
  "properties": {
    "addr:full":"Nrd Koninginnewal 11 Helmond North Brabant 5701 NJ",
    "addr:housenumber":"11",
    "addr:postcode":"5701 nj",
    "addr:street":"Nrd Koninginnewal",
    "iso:country":"NL",
    "sg:address":"Nrd Koninginnewal 11",
    "sg:city":"Helmond",
    "sg:classifiers":[
        {
            "category":"Retail",
            "subcategory":"Photofinishing",
            "type":"Services"
        }
    ],
    "sg:phone":"+31 492 541 802",
    "sg:postcode":"5701 NJ",
    "sg:province":"North Brabant",
    "sg:tags":[
        "foto",
        "film"
    ],
    "wof:name":"Take-It Electroniks Bv",
    "wof:placetype":"venue"
},
  "geometry": {"coordinates":[5.657562,51.47945],"type":"Point"}
}