{
  "type": "Feature",
  "properties": {
    "addr:full":"Ged Burgwal 30A S Gravenhage Zuid-Holland 2512 BV",
    "addr:housenumber":"30a;gravenhage",
    "addr:postcode":"2512 bv",
    "addr:street":"Burgwal;S",
    "iso:country":"NL",
    "sg:address":"Ged Burgwal 30A",
    "sg:city":"S Gravenhage",
    "sg:orig_category":"Woningbouw- Verenigingen En -Stichtingen",
    "sg:phone":"+31 70 365 6588",
    "sg:postcode":"2512 BV",
    "sg:province":"Zuid-Holland",
    "wof:name":"Mercurius Bv",
    "wof:placetype":"venue"
},
  "geometry": {"coordinates":[4.3061800003,52.0732116699],"type":"Point"}
}