{
  "type": "Feature",
  "properties": {
    "addr:full":"Floralaan 42 Hardenberg NL.08 7772 LL",
    "addr:housenumber":"42;nl.08",
    "addr:postcode":"7772 ll",
    "addr:street":"Floralaan",
    "iso:country":"NL",
    "sg:address":"Floralaan 42",
    "sg:city":"Hardenberg",
    "sg:orig_category":"Kappers",
    "sg:phone":"+31 523 268 450",
    "sg:postcode":"7772 LL",
    "sg:province":"NL.08",
    "wof:name":"Kapsalon Schaar De",
    "wof:placetype":"venue"
},
  "geometry": {"coordinates":[6.6423149109,52.5751953125],"type":"Point"}
}