{
  "type": "Feature",
  "properties": {
    "addr:full":"Pettelaarsewg 172 S Hertogenbosch Noord-Brabant 5216 BW",
    "addr:housenumber":"172",
    "addr:postcode":"5216 bw",
    "addr:street":"S Hertogenbosch",
    "iso:country":"NL",
    "sg:address":"Pettelaarsewg 172",
    "sg:city":"S Hertogenbosch",
    "sg:orig_category":"Cafetaria'S",
    "sg:phone":"+31 73 613 3613",
    "sg:postcode":"5216 BW",
    "sg:province":"Noord-Brabant",
    "wof:name":"Pettelaartje, 'T",
    "wof:placetype":"venue"
},
  "geometry": {"coordinates":[5.315594,51.681057],"type":"Point"}
}