{
  "type": "Feature",
  "properties": {
    "addr:full":"Kanaalwg 51 Beverwyk North Holland 1948 PL",
    "addr:housenumber":"51",
    "addr:postcode":"1948 pl",
    "addr:street":"Kanaalwg;North",
    "iso:country":"NL",
    "sg:address":"Kanaalwg 51",
    "sg:city":"Beverwyk",
    "sg:orig_category":"Verhuizingen",
    "sg:phone":"+31 251 223 184",
    "sg:postcode":"1948 PL",
    "sg:province":"North Holland",
    "sg:website":"http://www.brakenhoff.nl",
    "wof:name":"Brakenhoff Verhuizingen",
    "wof:placetype":"venue"
},
  "geometry": {"coordinates":[4.6719,52.479191],"type":"Point"}
}