{
  "type": "Feature",
  "properties": {
    "addr:full":"De Wiekslag 30 Veghel Noord-Brabant 5461 KD",
    "addr:housenumber":"30",
    "addr:postcode":"5461 kd",
    "addr:street":"De Wiekslag",
    "iso:country":"NL",
    "sg:address":"De Wiekslag 30",
    "sg:city":"Veghel",
    "sg:orig_category":"Opticiens",
    "sg:phone":"+31 413 342 909",
    "sg:postcode":"5461 KD",
    "sg:province":"Noord-Brabant",
    "wof:name":"Th. Van Hout Veghel Bv",
    "wof:placetype":"venue"
},
  "geometry": {"coordinates":[5.5453929901,51.6171302795],"type":"Point"}
}