{
  "type": "Feature",
  "properties": {
    "iso:country":"NL",
    "sg:address":"G V Prinstererstr 10",
    "sg:city":"Nunspeet",
    "sg:orig_category":"Beeldende Kunstenaars",
    "sg:phone":"+31 341 256 078",
    "sg:postcode":"8072 XT",
    "sg:province":"Gelderland",
    "wof:name":"Baas, J K",
    "wof:placetype":"venue"
},
  "geometry": {"coordinates":[5.772205,52.374981],"type":"Point"}
}