{
  "type": "Feature",
  "properties": {
    "addr:full":"Geuzenpln 19 Schiedam Zuid-Holland 3123 CK",
    "addr:housenumber":"19",
    "addr:postcode":"3123 ck",
    "addr:street":"Geuzenpln",
    "iso:country":"NL",
    "sg:address":"Geuzenpln 19",
    "sg:city":"Schiedam",
    "sg:orig_category":"Bloemen En Planten",
    "sg:phone":"+31 10 470 5894",
    "sg:postcode":"3123 CK",
    "sg:province":"Zuid-Holland",
    "wof:name":"Plantenbeurs",
    "wof:placetype":"venue"
},
  "geometry": {"coordinates":[4.36661,51.941879],"type":"Point"}
}