{
  "type": "Feature",
  "properties": {
    "addr:full":"Freddy Van Riemsdijkweg 15 Eindhoven North Brabant 5657 EE",
    "addr:housenumber":"15",
    "addr:postcode":"5657 ee",
    "addr:street":"Freddy Van Riemsdijkweg",
    "iso:country":"NL",
    "sg:address":"Freddy Van Riemsdijkweg 15",
    "sg:city":"Eindhoven",
    "sg:orig_category":"Kantoorartikelen",
    "sg:phone":"+31 40 259 1111",
    "sg:postcode":"5657 EE",
    "sg:province":"North Brabant",
    "wof:name":"Mansveld Expo Techniek & Imp Bv",
    "wof:placetype":"venue"
},
  "geometry": {"coordinates":[5.3959832191,51.4580345154],"type":"Point"}
}