{
  "type": "Feature",
  "properties": {
    "addr:full":"Blaarthemseweg 18 Veldhoven North Brabant 5502 JV",
    "addr:housenumber":"18",
    "addr:postcode":"5502 jv",
    "addr:street":"Blaarthemseweg",
    "iso:country":"NL",
    "sg:address":"Blaarthemseweg 18",
    "sg:city":"Veldhoven",
    "sg:orig_category":"Overheidsdiensten",
    "sg:phone":"+31 40 253 2103",
    "sg:postcode":"5502 JV",
    "sg:province":"North Brabant",
    "wof:name":"Gemeenschapshuis Zeelst",
    "wof:placetype":"venue"
},
  "geometry": {"coordinates":[5.417318821,51.4246101379],"type":"Point"}
}