{
  "type": "Feature",
  "properties": {
    "addr:full":"Zaansgroen 13 Zoetermeer Zuid-Holland 2718 GL",
    "addr:housenumber":"13",
    "addr:postcode":"2718 gl",
    "addr:street":"Zaansgroen",
    "iso:country":"NL",
    "sg:address":"Zaansgroen 13",
    "sg:city":"Zoetermeer",
    "sg:orig_category":"Psychotherapeuten",
    "sg:phone":"+31 79 361 2272",
    "sg:postcode":"2718 GL",
    "sg:province":"Zuid-Holland",
    "wof:name":"Valk, Drs F H J Van Der",
    "wof:placetype":"venue"
},
  "geometry": {"coordinates":[4.492245,52.040516],"type":"Point"}
}