{
  "type": "Feature",
  "properties": {
    "addr:full":"Laarwoud 13 Almelo Overijssel 7608 AG",
    "addr:housenumber":"13",
    "addr:postcode":"7608",
    "addr:street":"Laarwoud",
    "iso:country":"NL",
    "sg:address":"Laarwoud 13",
    "sg:city":"Almelo",
    "sg:orig_category":"Adviesbureaus Financieel",
    "sg:phone":"+31 546 867 158",
    "sg:postcode":"7608 AG",
    "sg:province":"Overijssel",
    "wof:name":"Finconsult",
    "wof:placetype":"venue"
},
  "geometry": {"coordinates":[6.688771,52.379635],"type":"Point"}
}