{
  "type": "Feature",
  "properties": {
    "addr:full":"Jonkersvaart 19 De Wilp Gn Groningen 9367 TL",
    "addr:housenumber":"19",
    "addr:postcode":"gn;9367 tl",
    "addr:street":"Jonkersvaart",
    "iso:country":"NL",
    "sg:address":"Jonkersvaart 19",
    "sg:city":"De Wilp Gn",
    "sg:orig_category":"Kappers",
    "sg:phone":"+31 594 641 443",
    "sg:postcode":"9367 TL",
    "sg:province":"Groningen",
    "wof:name":"A.E. Ausma",
    "wof:placetype":"venue"
},
  "geometry": {"coordinates":[6.2825050354,53.1264839172],"type":"Point"}
}