{
  "type": "Feature",
  "properties": {
    "addr:full":"Zylstr 20-22 Haarlem Noord-Holland 2011 TN",
    "addr:housenumber":"20-22",
    "addr:postcode":"2011",
    "iso:country":"NL",
    "sg:address":"Zylstr 20-22",
    "sg:city":"Haarlem",
    "sg:orig_category":"Biljarts - Fabrieken",
    "sg:phone":"+31 23 531 7622",
    "sg:postcode":"2011 TN",
    "sg:province":"Noord-Holland",
    "wof:name":"Broek En Zn, W A M V/D",
    "wof:placetype":"venue"
},
  "geometry": {"coordinates":[4.642253,52.380562],"type":"Point"}
}