{
  "type": "Feature",
  "properties": {
    "addr:full":"Geestwg 19 Bergen Nh Noord-Holland 1861 TL",
    "addr:housenumber":"19",
    "addr:postcode":"1861 tl",
    "addr:street":"Geestwg",
    "iso:country":"NL",
    "sg:address":"Geestwg 19",
    "sg:city":"Bergen Nh",
    "sg:orig_category":"Scholen Voor Algemeen Voortgezet Onderwijs",
    "sg:phone":"+31 72 581 3437",
    "sg:postcode":"1861 TL",
    "sg:province":"Noord-Holland",
    "sg:website":"http://www.multiweb.nl/~canisius/",
    "wof:name":"Petrus Canisius College",
    "wof:placetype":"venue"
},
  "geometry": {"coordinates":[4.70139,52.664299],"type":"Point"}
}