{
  "type": "Feature",
  "properties": {
    "addr:full":"Parkwg 89 Groningen Groningen 9725 ED",
    "addr:housenumber":"89",
    "addr:postcode":"9725 ed",
    "addr:street":"Parkwg",
    "iso:country":"NL",
    "sg:address":"Parkwg 89",
    "sg:city":"Groningen",
    "sg:orig_category":"Fietsen En Bromfietsen",
    "sg:phone":"+31 50 525 3731",
    "sg:postcode":"9725 ED",
    "sg:province":"Groningen",
    "wof:name":"Klei",
    "wof:placetype":"venue"
},
  "geometry": {"coordinates":[6.563848,53.208004],"type":"Point"}
}