{
  "type": "Feature",
  "properties": {
    "addr:full":"Johannes Meybeeklaan 8 Voorburg South Holland 2273 HD",
    "addr:housenumber":"8",
    "addr:postcode":"2273 hd",
    "addr:street":"Johannes Meybeeklaan",
    "iso:country":"NL",
    "sg:address":"Johannes Meybeeklaan 8",
    "sg:city":"Voorburg",
    "sg:orig_category":"Makelaars In Onroerend Goed",
    "sg:phone":"+31 70 387 4060",
    "sg:postcode":"2273 HD",
    "sg:province":"South Holland",
    "wof:name":"Ampio Bv",
    "wof:placetype":"venue"
},
  "geometry": {"coordinates":[4.359745,52.080235],"type":"Point"}
}