{
  "type": "Feature",
  "properties": {
    "addr:full":"Astraat 7 Groningen Groningen 9718 CP",
    "addr:housenumber":"7",
    "addr:postcode":"9718 cp",
    "addr:street":"Astraat",
    "iso:country":"NL",
    "sg:address":"Astraat 7",
    "sg:city":"Groningen",
    "sg:classifiers":[
        {
            "category":"Bakery",
            "type":"Food & Drink"
        }
    ],
    "sg:phone":"+31 50 313 3103",
    "sg:postcode":"9718 CP",
    "sg:province":"Groningen",
    "sg:tags":[
        "brood",
        "banket"
    ],
    "wof:name":"Droppie",
    "wof:placetype":"venue"
},
  "geometry": {"coordinates":[6.574715,53.217144],"type":"Point"}
}