{
  "type": "Feature",
  "properties": {
    "addr:full":"Rijssensestraat 146 Nijverdal NL.08 7441 AK",
    "addr:housenumber":"146;nl.08",
    "addr:postcode":"7441 ak",
    "addr:street":"Rijssensestraat",
    "iso:country":"NL",
    "sg:address":"Rijssensestraat 146",
    "sg:city":"Nijverdal",
    "sg:orig_category":"Autokeuringen",
    "sg:phone":"+31 548 613 820",
    "sg:postcode":"7441 AK",
    "sg:province":"NL.08",
    "wof:name":"Shell",
    "wof:placetype":"venue"
},
  "geometry": {"coordinates":[6.464489,52.356468],"type":"Point"}
}