{
  "type": "Feature",
  "properties": {
    "iso:country":"NL",
    "sg:address":"Rijksweg 253",
    "sg:city":"Gaanderen",
    "sg:orig_category":"Loodgieterswerk, Verwarming And Sanitaire Installaties",
    "sg:phone":"+31 315 329 181",
    "sg:postcode":"7011 DZ",
    "sg:province":"Gelderland",
    "wof:name":"Centrale Verwarming Doetinchems Cv Bedrijf",
    "wof:placetype":"venue"
},
  "geometry": {"coordinates":[6.360342,51.924454],"type":"Point"}
}