{
  "type": "Feature",
  "properties": {
    "iso:country":"NL",
    "sg:address":"Jan Van Galenstraat 14",
    "sg:city":"Amsterdam",
    "sg:classifiers":[
        {
            "category":"Food & Beverages",
            "subcategory":"Fruits & Vegetables",
            "type":"Retail Goods"
        }
    ],
    "sg:phone":"+31 20 682 3306",
    "sg:postcode":"1051 KM",
    "sg:province":"North Holland",
    "sg:tags":[
        "groenten"
    ],
    "wof:name":"G. Van Smeerdijk Groenten En Fruit Bv",
    "wof:placetype":"venue"
},
  "geometry": {"coordinates":[4.866024,52.375835],"type":"Point"}
}