{
  "type": "Feature",
  "properties": {
    "iso:country":"NL",
    "sg:address":"Strawinskyln 441",
    "sg:city":"Amsterdam",
    "sg:orig_category":"Verzekeringen - Verzekeringskantoren",
    "sg:phone":"+31 20 471 4414",
    "sg:postcode":"1077 XX",
    "sg:province":"North Holland",
    "wof:name":"Nissan Fire & Marine, The",
    "wof:placetype":"venue"
},
  "geometry": {"coordinates":[4.873036,52.340588],"type":"Point"}
}