{
  "type": "Feature",
  "properties": {
    "addr:full":"Hendrik Ringenoldusstr 49 Gorredijk Provincie Friesland 8401 PW",
    "addr:housenumber":"49",
    "addr:postcode":"8401 pw",
    "addr:street":"Provincie Friesland",
    "iso:country":"NL",
    "sg:address":"Hendrik Ringenoldusstr 49",
    "sg:city":"Gorredijk",
    "sg:classifiers":[
        {
            "category":"Education",
            "subcategory":"Preschool",
            "type":"Public Place"
        }
    ],
    "sg:phone":"+31 513 461 557",
    "sg:postcode":"8401 PW",
    "sg:province":"Provincie Friesland",
    "sg:tags":[
        "kleuteronderwijs",
        "basis-"
    ],
    "wof:name":"Basisschool De Tsjerne",
    "wof:placetype":"venue"
},
  "geometry": {"coordinates":[6.07469,53.007423],"type":"Point"}
}