{
  "type": "Feature",
  "properties": {
    "addr:full":"Groenveldsdk 44 St Maarten Noord-Holland 1744 GE",
    "addr:housenumber":"44",
    "addr:postcode":"1744",
    "addr:street":"Groenveldsdk;St Maarten Noord-Holland",
    "iso:country":"NL",
    "sg:address":"Groenveldsdk 44",
    "sg:city":"St Maarten",
    "sg:orig_category":"Bloembollen - Groothandel",
    "sg:phone":"+31 224 552 237",
    "sg:postcode":"1744 GE",
    "sg:province":"Noord-Holland",
    "sg:website":"http://www.maveridge.com",
    "wof:name":"Maveridge Int Bv",
    "wof:placetype":"venue"
},
  "geometry": {"coordinates":[4.78564,52.769169],"type":"Point"}
}