{
  "type": "Feature",
  "properties": {
    "addr:full":"Rykestr 15A S Gravendeel Zuid-Holland 3295 BS",
    "addr:housenumber":"15a",
    "addr:postcode":"3295 bs",
    "addr:street":"Rykestr;S Gravendeel",
    "iso:country":"NL",
    "sg:address":"Rykestr 15A",
    "sg:city":"S Gravendeel",
    "sg:orig_category":"Onderhoudswerken",
    "sg:phone":"+31 78 673 5585",
    "sg:postcode":"3295 BS",
    "sg:province":"Zuid-Holland",
    "sg:website":"http://www.vanderbijl.nu",
    "wof:name":"Bijl, Van Der",
    "wof:placetype":"venue"
},
  "geometry": {"coordinates":[4.619425,51.779083],"type":"Point"}
}