{
  "type": "Feature",
  "properties": {
    "addr:full":"M H Trompstr 20 Zutphen Gelderland 7204 GB",
    "addr:housenumber":"20",
    "addr:postcode":"7204 gb",
    "addr:street":"M;Gelderland",
    "iso:country":"NL",
    "sg:address":"M H Trompstr 20",
    "sg:city":"Zutphen",
    "sg:classifiers":[
        {
            "category":"Personal",
            "subcategory":"Nail Salon",
            "type":"Services"
        }
    ],
    "sg:phone":"+31 575 514 901",
    "sg:postcode":"7204 GB",
    "sg:province":"Gelderland",
    "sg:tags":[
        "pedicure"
    ],
    "wof:name":"Neferti",
    "wof:placetype":"venue"
},
  "geometry": {"coordinates":[6.191525,52.140202],"type":"Point"}
}