{
  "type": "Feature",
  "properties": {
    "iso:country":"NL",
    "sg:address":"Krabbenhoeksewg 2",
    "sg:city":"Nieuwerkerk",
    "sg:orig_category":"Honden- En Kattentrimsalons",
    "sg:phone":"+31 111 641 389",
    "sg:postcode":"4306 NL",
    "sg:province":"Zeeland",
    "wof:name":"El Perro",
    "wof:placetype":"venue"
},
  "geometry": {"coordinates":[4.012896,51.670681],"type":"Point"}
}