{
  "type": "Feature",
  "properties": {
    "addr:full":"Kerkstr 67 Stryen Zuid-Holland 3291 AK",
    "addr:housenumber":"67",
    "addr:postcode":"3291 ak",
    "addr:street":"Kerkstr",
    "iso:country":"NL",
    "sg:address":"Kerkstr 67",
    "sg:city":"Stryen",
    "sg:orig_category":"Kappers",
    "sg:phone":"+31 78 674 1295",
    "sg:postcode":"3291 AK",
    "sg:province":"Zuid-Holland",
    "wof:name":"Haarlokaal",
    "wof:placetype":"venue"
},
  "geometry": {"coordinates":[4.5472698212,51.750831604],"type":"Point"}
}