{
  "type": "Feature",
  "properties": {
    "addr:full":"Zoutmanswg 118 Reeuwyk Zuid-Holland 2811 EW",
    "addr:housenumber":"118",
    "addr:postcode":"2811 ew",
    "addr:street":"Reeuwyk",
    "iso:country":"NL",
    "sg:address":"Zoutmanswg 118",
    "sg:city":"Reeuwyk",
    "sg:orig_category":"Glazenwasserijen",
    "sg:phone":"+31 182 393 784",
    "sg:postcode":"2811 EW",
    "sg:province":"Zuid-Holland",
    "wof:name":"Reeuwijk",
    "wof:placetype":"venue"
},
  "geometry": {"coordinates":[4.719137,52.035496],"type":"Point"}
}