{
  "type": "Feature",
  "properties": {
    "addr:full":"Communicatiewg 12 Heemskerk Noord-Holland 1967 PR",
    "addr:housenumber":"12",
    "addr:postcode":"1967 pr",
    "addr:street":"Communicatiewg",
    "iso:country":"NL",
    "sg:address":"Communicatiewg 12",
    "sg:city":"Heemskerk",
    "sg:orig_category":"Handelscentra",
    "sg:phone":"+31 251 248 864",
    "sg:postcode":"1967 PR",
    "sg:province":"Noord-Holland",
    "wof:name":"Groot Bv, De",
    "wof:placetype":"venue"
},
  "geometry": {"coordinates":[4.70332,52.50132],"type":"Point"}
}