{
  "type": "Feature",
  "properties": {
    "addr:full":"Wildbaan 3 Amerongen Utrecht 3958 DH",
    "addr:housenumber":"3",
    "addr:postcode":"3958 dh",
    "addr:street":"Wildbaan",
    "iso:country":"NL",
    "sg:address":"Wildbaan 3",
    "sg:city":"Amerongen",
    "sg:classifiers":[
        {
            "category":"Professional",
            "subcategory":"Accounting & Tax Preparation",
            "type":"Services"
        }
    ],
    "sg:phone":"+31 343 452 644",
    "sg:postcode":"3958 DH",
    "sg:province":"Utrecht",
    "sg:tags":[
        "accountant"
    ],
    "wof:name":"Administratie En Adviesbureau Van Scherp",
    "wof:placetype":"venue"
},
  "geometry": {"coordinates":[5.465507,52.005169],"type":"Point"}
}