{
  "type": "Feature",
  "properties": {
    "addr:full":"Balkerwg 83 Vinkenbuurt Overijssel 7739 PT",
    "addr:housenumber":"83",
    "addr:postcode":"7739 pt",
    "addr:street":"Balkerwg",
    "iso:country":"NL",
    "sg:address":"Balkerwg 83",
    "sg:city":"Vinkenbuurt",
    "sg:orig_category":"Adviesbureaus Bedrijfsorganisatie",
    "sg:phone":"+31 523 649 949",
    "sg:postcode":"7739 PT",
    "sg:province":"Overijssel",
    "wof:name":"Dam, Ten",
    "wof:placetype":"venue"
},
  "geometry": {"coordinates":[6.38868,52.589233],"type":"Point"}
}