{
  "type": "Feature",
  "properties": {
    "iso:country":"NL",
    "sg:address":"Vlierdensewg 203",
    "sg:city":"Vlierden",
    "sg:classifiers":[
        {
            "category":"Retail",
            "subcategory":"Auto Repair",
            "type":"Services"
        }
    ],
    "sg:phone":"+31 493 313 064",
    "sg:postcode":"5756 AB",
    "sg:province":"Noord-Brabant",
    "sg:tags":[
        "garage"
    ],
    "wof:name":"Snijders, A",
    "wof:placetype":"venue"
},
  "geometry": {"coordinates":[5.760539,51.442642],"type":"Point"}
}