{
  "type": "Feature",
  "properties": {
    "addr:full":"Heiligestr 30 Tiel Gelderland 4001 DM",
    "addr:housenumber":"30",
    "addr:postcode":"4001 dm",
    "addr:street":"Heiligestr;Gelderland",
    "iso:country":"NL",
    "sg:address":"Heiligestr 30",
    "sg:city":"Tiel",
    "sg:orig_category":"Gelegenheidskleding",
    "sg:phone":"+31 344 622 605",
    "sg:postcode":"4001 DM",
    "sg:province":"Gelderland",
    "wof:name":"Briene",
    "wof:placetype":"venue"
},
  "geometry": {"coordinates":[5.427421,51.885414],"type":"Point"}
}