{
  "type": "Feature",
  "properties": {
    "addr:full":"Vijverplein 7 Sleeuwijk North Brabant 4254 AJ",
    "addr:housenumber":"7",
    "addr:postcode":"4254 aj",
    "addr:street":"Vijverplein",
    "iso:country":"NL",
    "sg:address":"Vijverplein 7",
    "sg:city":"Sleeuwijk",
    "sg:orig_category":"Babyartikelen Detailhandel",
    "sg:phone":"+31 183 301 664",
    "sg:postcode":"4254 AJ",
    "sg:province":"North Brabant",
    "wof:name":"Yoepie",
    "wof:placetype":"venue"
},
  "geometry": {"coordinates":[4.954845,51.81213],"type":"Point"}
}