{
  "type": "Feature",
  "properties": {
    "iso:country":"NL",
    "sg:address":"Postbus 841",
    "sg:city":"Zoetermeer",
    "sg:orig_category":"Omroep",
    "sg:phone":"+31 79 331 7287",
    "sg:postcode":"2700 AV",
    "sg:province":"South Holland",
    "sg:website":"http://www.zoetermeerfm.nl",
    "wof:name":"Zoetermeer Fm 107.6",
    "wof:placetype":"venue"
},
  "geometry": {"coordinates":[4.48892,52.06308],"type":"Point"}
}