{
  "type": "Feature",
  "properties": {
    "addr:full":"Oranjepln 32 Goirle North Brabant 5051 LW",
    "addr:housenumber":"32",
    "addr:postcode":"5051 lw",
    "addr:street":"Oranjepln",
    "iso:country":"NL",
    "sg:address":"Oranjepln 32",
    "sg:city":"Goirle",
    "sg:orig_category":"Zalenverhuur",
    "sg:phone":"+31 13 534 8698",
    "sg:postcode":"5051 LW",
    "sg:province":"North Brabant",
    "wof:name":"Fust, 'T",
    "wof:placetype":"venue"
},
  "geometry": {"coordinates":[5.069561,51.522678],"type":"Point"}
}