{
  "type": "Feature",
  "properties": {
    "addr:full":"Stikkenwg 22 Zelhem Gelderland 7021 BN",
    "addr:housenumber":"22",
    "addr:postcode":"7021 bn",
    "addr:street":"Stikkenwg;Gelderland",
    "iso:country":"NL",
    "sg:address":"Stikkenwg 22",
    "sg:city":"Zelhem",
    "sg:orig_category":"Wijnkoperijen En -Groothandel",
    "sg:phone":"+31 314 622 078",
    "sg:postcode":"7021 BN",
    "sg:province":"Gelderland",
    "sg:website":"http://www.polyvin.nl",
    "wof:name":"Polyvin",
    "wof:placetype":"venue"
},
  "geometry": {"coordinates":[6.3487129211,51.9991149902],"type":"Point"}
}