{
  "type": "Feature",
  "properties": {
    "addr:full":"Nijverheidsweg 4 Callantsoog Noord-Holland 1759 JR",
    "addr:housenumber":"4",
    "addr:postcode":"1759 jr",
    "addr:street":"Nijverheidsweg",
    "iso:country":"NL",
    "sg:address":"Nijverheidsweg 4",
    "sg:city":"Callantsoog",
    "sg:orig_category":"Verhuur Audiovisuele Apparatuur",
    "sg:phone":"+31 224 582 948",
    "sg:postcode":"1759 JR",
    "sg:province":"Noord-Holland",
    "wof:name":"Thide'S Sound And Light",
    "wof:placetype":"venue"
},
  "geometry": {"coordinates":[4.721227,52.845039],"type":"Point"}
}