{
  "type": "Feature",
  "properties": {
    "addr:full":"Rozenplnts 2 Moordrecht South Holland 2841 AN",
    "addr:housenumber":"2",
    "addr:postcode":"2841 an",
    "addr:street":"Rozenplnts",
    "iso:country":"NL",
    "sg:address":"Rozenplnts 2",
    "sg:city":"Moordrecht",
    "sg:orig_category":"Luchtfotografie",
    "sg:phone":"+31 182 375 818",
    "sg:postcode":"2841 AN",
    "sg:province":"South Holland",
    "wof:name":"Ernst, R",
    "wof:placetype":"venue"
},
  "geometry": {"coordinates":[4.667987,51.987827],"type":"Point"}
}