{
  "type": "Feature",
  "properties": {
    "iso:country":"NL",
    "sg:address":"Ruineln 15",
    "sg:city":"Bergen Nh",
    "sg:classifiers":[
        {
            "category":"Travel",
            "subcategory":"Hotels & Motels",
            "type":"Entertainment"
        }
    ],
    "sg:phone":"+31 72 581 2530",
    "sg:postcode":"1861 LK",
    "sg:province":"North Holland",
    "wof:name":"Witte Huis, Het",
    "wof:placetype":"venue"
},
  "geometry": {"coordinates":[4.701395,52.669979],"type":"Point"}
}