{
  "type": "Feature",
  "properties": {
    "addr:full":"Rozenstraat 1 Ravenswaaij Gelderland 4119 LW",
    "addr:housenumber":"1",
    "addr:postcode":"4119 lw",
    "addr:street":"Rozenstraat;Gelderland",
    "iso:country":"NL",
    "sg:address":"Rozenstraat 1",
    "sg:city":"Ravenswaaij",
    "sg:orig_category":"Overheidsdiensten",
    "sg:phone":"+31 345 558 571",
    "sg:postcode":"4119 LW",
    "sg:province":"Gelderland",
    "wof:name":"De Rozenhoek",
    "wof:placetype":"venue"
},
  "geometry": {"coordinates":[5.3275518417,51.9515419006],"type":"Point"}
}