{
  "type": "Feature",
  "properties": {
    "iso:country":"NL",
    "sg:address":"Rolderstraat 6",
    "sg:city":"Grolloo",
    "sg:orig_category":"Verhuur Audiovisuele Apparatuur",
    "sg:phone":"+31 592 501 556",
    "sg:postcode":"9444 XC",
    "sg:province":"Drenthe",
    "wof:name":"Double Dutch",
    "wof:placetype":"venue"
},
  "geometry": {"coordinates":[6.672357,52.939587],"type":"Point"}
}