{
  "type": "Feature",
  "properties": {
    "iso:country":"NL",
    "sg:address":"Heidewg 8",
    "sg:city":"Harfsen",
    "sg:orig_category":"Lasbedrijven",
    "sg:phone":"+31 573 431 579",
    "sg:postcode":"7217 TE",
    "sg:province":"Gelderland",
    "wof:name":"Kruitbosch",
    "wof:placetype":"venue"
},
  "geometry": {"coordinates":[6.274624,52.209038],"type":"Point"}
}