{
  "type": "Feature",
  "properties": {
    "iso:country":"NL",
    "sg:address":"Breestr 73",
    "sg:city":"Koog Aan De Zaan",
    "sg:orig_category":"Schilders",
    "sg:phone":"+31 75 616 2563",
    "sg:postcode":"1541 EC",
    "sg:province":"Noord-Holland",
    "wof:name":"Finke",
    "wof:placetype":"venue"
},
  "geometry": {"coordinates":[4.809024,52.460552],"type":"Point"}
}