{
  "type": "Feature",
  "properties": {
    "addr:full":"Anjerstraat 79 Zwijndrecht Zuid-Holland 3333 GC",
    "addr:housenumber":"79",
    "addr:postcode":"3333 gc",
    "addr:street":"Anjerstraat",
    "iso:country":"NL",
    "sg:address":"Anjerstraat 79",
    "sg:city":"Zwijndrecht",
    "sg:orig_category":"Bibliotheken And Openbare Archieven",
    "sg:phone":"+31 78 612 5661",
    "sg:postcode":"3333 GC",
    "sg:province":"Zuid-Holland",
    "wof:name":"Stichting Verenigde Openbare Bibliotheken Zwijndre",
    "wof:placetype":"venue"
},
  "geometry": {"coordinates":[4.622894,51.813671],"type":"Point"}
}