{
  "type": "Feature",
  "properties": {
    "addr:full":"Bentmaatweg 14 Enschede Overijssel 7525 PD",
    "addr:housenumber":"14",
    "addr:postcode":"7525 pd",
    "addr:street":"Bentmaatweg",
    "iso:country":"NL",
    "sg:address":"Bentmaatweg 14",
    "sg:city":"Enschede",
    "sg:orig_category":"Visspeciaalzaken",
    "sg:phone":"+31 53 435 2575",
    "sg:postcode":"7525 PD",
    "sg:province":"Overijssel",
    "wof:name":"Firma Rillmann-Van Dijk En Zonen",
    "wof:placetype":"venue"
},
  "geometry": {"coordinates":[6.923337,52.253857],"type":"Point"}
}