{
  "type": "Feature",
  "properties": {
    "iso:country":"NL",
    "sg:address":"Van Woustraat 157",
    "sg:city":"Amsterdam",
    "sg:orig_category":"Werving And Selectie Van Tijdelijk Personeel And Uitzendkantoren",
    "sg:phone":"+31 20 670 9969",
    "sg:postcode":"1074 AK",
    "sg:province":"Noord-Holland",
    "wof:name":"Laborflex Bv",
    "wof:placetype":"venue"
},
  "geometry": {"coordinates":[4.9030981064,52.3524856567],"type":"Point"}
}