{
  "type": "Feature",
  "properties": {
    "addr:full":"Stompwijkseweg 18 Leidschendam Zuid-Holland 2266 GE",
    "addr:housenumber":"18",
    "addr:postcode":"2266",
    "addr:street":"Stompwijkseweg",
    "iso:country":"NL",
    "sg:address":"Stompwijkseweg 18",
    "sg:city":"Leidschendam",
    "sg:orig_category":"Meubelzaken, Woning- And Keukeninrichting",
    "sg:phone":"+31 70 320 1885",
    "sg:postcode":"2266 GE",
    "sg:province":"Zuid-Holland",
    "wof:name":"Ambachtelijke Meubelmakerij De Stoof Bv",
    "wof:placetype":"venue"
},
  "geometry": {"coordinates":[4.414286,52.079346],"type":"Point"}
}