{
  "type": "Feature",
  "properties": {
    "addr:full":"Heideburen 71 Heerenveen Friesland 8441 GM",
    "addr:housenumber":"71",
    "addr:postcode":"8441 gm",
    "addr:street":"Heideburen",
    "iso:country":"NL",
    "sg:address":"Heideburen 71",
    "sg:city":"Heerenveen",
    "sg:orig_category":"Verenigingen En Stichtingen",
    "sg:phone":"+31 513 623 207",
    "sg:postcode":"8441 GM",
    "sg:province":"Friesland",
    "wof:name":"Ken U Zelven Vrijmetselaarsloge",
    "wof:placetype":"venue"
},
  "geometry": {"coordinates":[5.927739,52.961491],"type":"Point"}
}