{
  "type": "Feature",
  "properties": {
    "iso:country":"NL",
    "sg:address":"Clusiuserf 29",
    "sg:city":"Boskoop",
    "sg:orig_category":"Wegenbouw",
    "sg:phone":"+31 172 212 890",
    "sg:postcode":"2771 ST",
    "sg:province":"Zuid-Holland",
    "wof:name":"Werf Adviesbureau, Van Der",
    "wof:placetype":"venue"
},
  "geometry": {"coordinates":[4.6478672028,52.0672874451],"type":"Point"}
}