{
  "type": "Feature",
  "properties": {
    "addr:full":"Margrietstr 15 Zwartsluis NL.08 8064 BK",
    "addr:housenumber":"15;nl.08",
    "addr:postcode":"8064 bk",
    "addr:street":"Margrietstr",
    "iso:country":"NL",
    "sg:address":"Margrietstr 15",
    "sg:city":"Zwartsluis",
    "sg:orig_category":"Bedrijfskleding",
    "sg:phone":"+31 38 386 9519",
    "sg:postcode":"8064 BK",
    "sg:province":"NL.08",
    "wof:name":"Booij, H",
    "wof:placetype":"venue"
},
  "geometry": {"coordinates":[6.065817,52.641262],"type":"Point"}
}