{
  "type": "Feature",
  "properties": {
    "addr:full":"Oude Nykerkerwg 165 Ermelo Gelderland 3853 JP",
    "addr:housenumber":"165",
    "addr:postcode":"3853 jp",
    "addr:street":"Oude Nykerkerwg;Gelderland",
    "iso:country":"NL",
    "sg:address":"Oude Nykerkerwg 165",
    "sg:city":"Ermelo",
    "sg:orig_category":"Grondwerken",
    "sg:phone":"+31 341 564 480",
    "sg:postcode":"3853 JP",
    "sg:province":"Gelderland",
    "wof:name":"Grevenhof, H Van",
    "wof:placetype":"venue"
},
  "geometry": {"coordinates":[5.613628,52.319542],"type":"Point"}
}