{
  "type": "Feature",
  "properties": {
    "addr:full":"Ericaweg 16 Epe Gelderland 8162 PR",
    "addr:housenumber":"16",
    "addr:postcode":"8162 pr",
    "addr:street":"Ericaweg;Gelderland",
    "iso:country":"NL",
    "sg:address":"Ericaweg 16",
    "sg:city":"Epe",
    "sg:orig_category":"Bloemen And Planten Gh",
    "sg:phone":"+31 578 627 903",
    "sg:postcode":"8162 PR",
    "sg:province":"Gelderland",
    "wof:name":"H. Van Den Berg",
    "wof:placetype":"venue"
},
  "geometry": {"coordinates":[5.946665,52.346848],"type":"Point"}
}