{
  "type": "Feature",
  "properties": {
    "iso:country":"NL",
    "sg:address":"Ericaweg 16",
    "sg:city":"Epe",
    "sg:orig_category":"Bloemen And Planten Gh",
    "sg:phone":"+31 578 627 903",
    "sg:postcode":"8162 PR",
    "sg:province":"Gelderland",
    "wof:name":"H. Van Den Berg",
    "wof:placetype":"venue"
},
  "geometry": {"coordinates":[5.946665,52.346848],"type":"Point"}
}