{
  "type": "Feature",
  "properties": {
    "addr:full":"Wonnebuursterwg 10 Ferwoude Provincie Friesland 8761 PG",
    "addr:housenumber":"10",
    "addr:postcode":"8761",
    "addr:street":"Wonnebuursterwg;Provincie Friesland;Pg",
    "iso:country":"NL",
    "sg:address":"Wonnebuursterwg 10",
    "sg:city":"Ferwoude",
    "sg:orig_category":"Zuivel - Groothandel",
    "sg:phone":"+31 515 542 199",
    "sg:postcode":"8761 PG",
    "sg:province":"Provincie Friesland",
    "wof:name":"Butterblom, De",
    "wof:placetype":"venue"
},
  "geometry": {"coordinates":[5.438631,53.014698],"type":"Point"}
}