{
  "type": "Feature",
  "properties": {
    "addr:full":"Costa Ricadreef 9 Utrecht Utrecht 3563 TA",
    "addr:housenumber":"9",
    "addr:postcode":"3563 ta",
    "addr:street":"Costa Ricadreef",
    "iso:country":"NL",
    "sg:address":"Costa Ricadreef 9",
    "sg:city":"Utrecht",
    "sg:orig_category":"Bejaarden - Verzorgingstehuizen",
    "sg:phone":"+31 30 264 6668",
    "sg:postcode":"3563 TA",
    "sg:province":"Utrecht",
    "sg:website":"http://www.huisadvecht.nl",
    "wof:name":"Huis Aan De Vecht, 'T",
    "wof:placetype":"venue"
},
  "geometry": {"coordinates":[5.093211,52.119961],"type":"Point"}
}