{
  "type": "Feature",
  "properties": {
    "addr:full":"De Lasso Z 8 Roelofarendsveen Zuid-Holland 2371 EW",
    "addr:housenumber":"8",
    "addr:postcode":"2371 ew",
    "addr:street":"De Lasso Z",
    "iso:country":"NL",
    "sg:address":"De Lasso Z 8",
    "sg:city":"Roelofarendsveen",
    "sg:orig_category":"Accountants - Administratie- Consulenten En -Kantoren",
    "sg:phone":"+31 71 331 9689",
    "sg:postcode":"2371 EW",
    "sg:province":"Zuid-Holland",
    "wof:name":"Koning Bv Accountantskantoor, De",
    "wof:placetype":"venue"
},
  "geometry": {"coordinates":[4.632897,52.204285],"type":"Point"}
}