{
  "type": "Feature",
  "properties": {
    "addr:full":"Deltakd 8 Venlo Limburg 5928 PX",
    "addr:housenumber":"8",
    "addr:postcode":"5928 px",
    "addr:street":"Deltakd",
    "iso:country":"NL",
    "sg:address":"Deltakd 8",
    "sg:city":"Venlo",
    "sg:orig_category":"Metaalgroothandel",
    "sg:phone":"+31 77 382 9641",
    "sg:postcode":"5928 PX",
    "sg:province":"Limburg",
    "sg:website":"http://www.metaalketen.nl",
    "wof:name":"Metaalketen Zuid Bv",
    "wof:placetype":"venue"
},
  "geometry": {"coordinates":[6.11955,51.395309],"type":"Point"}
}