{
  "type": "Feature",
  "properties": {
    "addr:full":"Prins Hendrikweg 9 Wijk Bij Duurstede Utrecht 3962 EK",
    "addr:housenumber":"9",
    "addr:postcode":"3962 ek",
    "addr:street":"Prins Hendrikweg",
    "iso:country":"NL",
    "sg:address":"Prins Hendrikweg 9",
    "sg:city":"Wijk Bij Duurstede",
    "sg:orig_category":"Bedrijfs- And Managementsconsultants",
    "sg:phone":"+31 343 597 337",
    "sg:postcode":"3962 EK",
    "sg:province":"Utrecht",
    "wof:name":"Ardon Consult",
    "wof:placetype":"venue"
},
  "geometry": {"coordinates":[5.347141,51.975994],"type":"Point"}
}