{
  "type": "Feature",
  "properties": {
    "iso:country":"NL",
    "sg:address":"Kloosterstraat 1",
    "sg:city":"Chaam",
    "sg:orig_category":"Groententeelt",
    "sg:phone":"+31 161 492 278",
    "sg:postcode":"4861 PA",
    "sg:province":"Noord-Brabant",
    "wof:name":"Champignonkwekerij Gebroeders Van Den Hout",
    "wof:placetype":"venue"
},
  "geometry": {"coordinates":[4.872759,51.517719],"type":"Point"}
}