{
  "type": "Feature",
  "properties": {
    "addr:full":"Koolstr 37A Groningen Groningen 9717 KB",
    "addr:housenumber":"37a",
    "addr:postcode":"9717 kb",
    "addr:street":"Koolstr",
    "iso:country":"NL",
    "sg:address":"Koolstr 37A",
    "sg:city":"Groningen",
    "sg:orig_category":"Postorderbedrijven",
    "sg:phone":"+31 50 571 4537",
    "sg:postcode":"9717 KB",
    "sg:province":"Groningen",
    "sg:website":"http://www.boomrecords.com",
    "wof:name":"Boom",
    "wof:placetype":"venue"
},
  "geometry": {"coordinates":[6.555406,53.228367],"type":"Point"}
}