{
  "type": "Feature",
  "properties": {
    "addr:full":"Mezendaal 31 Nieuwerkerk Ad Ijssel Zuid-Holland 2914 ED",
    "addr:housenumber":"31",
    "addr:postcode":"ijssel;2914 ed",
    "addr:street":"Mezendaal",
    "iso:country":"NL",
    "sg:address":"Mezendaal 31",
    "sg:city":"Nieuwerkerk Ad Ijssel",
    "sg:orig_category":"Boekhouders",
    "sg:phone":"+31 180 314 510",
    "sg:postcode":"2914 ED",
    "sg:province":"Zuid-Holland",
    "wof:name":"P.A. Van Drenth Administratieve Dienstve",
    "wof:placetype":"venue"
},
  "geometry": {"coordinates":[4.614429,51.968987],"type":"Point"}
}