{
  "type": "Feature",
  "properties": {
    "iso:country":"NL",
    "sg:address":"Kaaistraat 57",
    "sg:city":"Steenbergen Nb",
    "sg:orig_category":"Herenmodezaken",
    "sg:phone":"+31 167 565 206",
    "sg:postcode":"4651 BM",
    "sg:province":"Noord-Brabant",
    "wof:name":"Jan Van Drunen Mode Voor Mannen",
    "wof:placetype":"venue"
},
  "geometry": {"coordinates":[4.317553,51.586975],"type":"Point"}
}