{
  "type": "Feature",
  "properties": {
    "addr:full":"Ln V Scheltema 5 S Gravenhage Zuid-Holland 2548 AW",
    "addr:housenumber":"5;gravenhage",
    "addr:postcode":"2548 aw",
    "addr:street":"Ln V Scheltema;S",
    "iso:country":"NL",
    "sg:address":"Ln V Scheltema 5",
    "sg:city":"S Gravenhage",
    "sg:orig_category":"Voegwerken",
    "sg:phone":"+31 174 298 705",
    "sg:postcode":"2548 AW",
    "sg:province":"Zuid-Holland",
    "wof:name":"Smits & Adrichem",
    "wof:placetype":"venue"
},
  "geometry": {"coordinates":[4.2901,52.029888],"type":"Point"}
}