{
  "type": "Feature",
  "properties": {
    "addr:full":"Burg Maenenstr 45 Elsloo Lb BE.05 6181 EA",
    "addr:housenumber":"45",
    "addr:postcode":"6181 ea",
    "addr:street":"Burg;Lb",
    "iso:country":"NL",
    "sg:address":"Burg Maenenstr 45",
    "sg:city":"Elsloo Lb",
    "sg:orig_category":"Zalenverhuur",
    "sg:phone":"+31 46 437 3575",
    "sg:postcode":"6181 EA",
    "sg:province":"BE.05",
    "wof:name":"Maaslandcentrum",
    "wof:placetype":"venue"
},
  "geometry": {"coordinates":[5.738695,50.960476],"type":"Point"}
}