{
  "type": "Feature",
  "properties": {
    "addr:full":"Franekerhoeve 18 Vlaardingen Zuid-Holland 3137 GC",
    "addr:housenumber":"18",
    "addr:postcode":"3137 gc",
    "addr:street":"Franekerhoeve",
    "iso:country":"NL",
    "sg:address":"Franekerhoeve 18",
    "sg:city":"Vlaardingen",
    "sg:orig_category":"Boekhouders",
    "sg:phone":"+31 10 474 1807",
    "sg:postcode":"3137 GC",
    "sg:province":"Zuid-Holland",
    "wof:name":"G.J. Langhorst",
    "wof:placetype":"venue"
},
  "geometry": {"coordinates":[4.352329,51.942303],"type":"Point"}
}