{
  "type": "Feature",
  "properties": {
    "addr:full":"Vragenderweg 66 B Vragender Gelderland 7134 NA",
    "addr:housenumber":"66 b",
    "addr:postcode":"7134 na",
    "addr:street":"Vragenderweg;Gelderland",
    "iso:country":"NL",
    "sg:address":"Vragenderweg 66 B",
    "sg:city":"Vragender",
    "sg:orig_category":"Viskwekerijen",
    "sg:phone":"+31 544 377 395",
    "sg:postcode":"7134 NA",
    "sg:province":"Gelderland",
    "wof:name":"Forellenpark Lichtenvoorde",
    "wof:placetype":"venue"
},
  "geometry": {"coordinates":[6.591462,51.988529],"type":"Point"}
}