{
  "type": "Feature",
  "properties": {
    "addr:full":"Oorsprongweg 8 Schoorl Noord-Holland 1871 HA",
    "addr:housenumber":"8",
    "addr:postcode":"1871 ha",
    "addr:street":"Oorsprongweg",
    "iso:country":"NL",
    "sg:address":"Oorsprongweg 8",
    "sg:city":"Schoorl",
    "sg:orig_category":"Kampeerterreinen",
    "sg:phone":"+31 72 509 1242",
    "sg:postcode":"1871 HA",
    "sg:province":"Noord-Holland",
    "wof:name":"Koekoeksbos",
    "wof:placetype":"venue"
},
  "geometry": {"coordinates":[4.6898360252,52.7067451477],"type":"Point"}
}