{
  "type": "Feature",
  "properties": {
    "addr:full":"Grachterstr 56 Kerkrade Limburg 6465 AN",
    "addr:housenumber":"56",
    "addr:postcode":"6465 an",
    "addr:street":"Grachterstr",
    "iso:country":"NL",
    "sg:address":"Grachterstr 56",
    "sg:city":"Kerkrade",
    "sg:orig_category":"Scholen Voor Basisonderwijs",
    "sg:phone":"+31 45 541 3053",
    "sg:postcode":"6465 AN",
    "sg:province":"Limburg",
    "wof:name":"Gracht Rk, De",
    "wof:placetype":"venue"
},
  "geometry": {"coordinates":[6.027895,50.851711],"type":"Point"}
}