{
  "type": "Feature",
  "properties": {
    "addr:full":"Oude Zylvest 37Zw Haarlem Noord-Holland 2011 VR",
    "addr:housenumber":"37zw",
    "addr:postcode":"2011 vr",
    "addr:street":"Oude Zylvest",
    "iso:country":"NL",
    "sg:address":"Oude Zylvest 37Zw",
    "sg:city":"Haarlem",
    "sg:orig_category":"Pottenbakkerijen",
    "sg:phone":"+31 23 531 1304",
    "sg:postcode":"2011 VR",
    "sg:province":"Noord-Holland",
    "wof:name":"Bolle Deur, De",
    "wof:placetype":"venue"
},
  "geometry": {"coordinates":[4.62854,52.380173],"type":"Point"}
}