{
  "type": "Feature",
  "properties": {
    "addr:full":"Veldhuizerweg 12 Ede Gld Gelderland 6712 DE",
    "addr:housenumber":"12;6712",
    "addr:street":"Veldhuizerweg;Gld Gelderland;De",
    "iso:country":"NL",
    "sg:address":"Veldhuizerweg 12",
    "sg:city":"Ede Gld",
    "sg:orig_category":"Daken And Skeletbouw",
    "sg:phone":"+31 318 642 186",
    "sg:postcode":"6712 DE",
    "sg:province":"Gelderland",
    "wof:name":"Dakbedekkingsbedrijf A. Van Der Linden Bv",
    "wof:placetype":"venue"
},
  "geometry": {"coordinates":[5.655391,52.047329],"type":"Point"}
}