{
  "type": "Feature",
  "properties": {
    "addr:full":"Koeleweg 1 Ossendrecht Noord-Brabant 4641 SW",
    "addr:housenumber":"1",
    "addr:postcode":"4641 sw",
    "addr:street":"Koeleweg",
    "iso:country":"NL",
    "sg:address":"Koeleweg 1",
    "sg:city":"Ossendrecht",
    "sg:classifiers":[
        {
            "category":"Parking",
            "subcategory":"Lot",
            "type":"Transportation"
        }
    ],
    "sg:phone":"+31 164 674 618",
    "sg:postcode":"4641 SW",
    "sg:province":"Noord-Brabant",
    "sg:tags":[
        "fab",
        "metalen",
        "tank"
    ],
    "wof:name":"De Weert Pijpleidingen Bv",
    "wof:placetype":"venue"
},
  "geometry": {"coordinates":[4.328183,51.384369],"type":"Point"}
}