{
  "type": "Feature",
  "properties": {
    "iso:country":"NL",
    "sg:address":"Kerkpln 4",
    "sg:city":"Stramproy",
    "sg:orig_category":"Fietsen En Bromfietsen",
    "sg:phone":"+31 495 562 916",
    "sg:postcode":"6039 GH",
    "sg:province":"Limburg",
    "wof:name":"Janssen Bike Totaal",
    "wof:placetype":"venue"
},
  "geometry": {"coordinates":[5.723132,51.19305],"type":"Point"}
}