{
  "type": "Feature",
  "properties": {
    "addr:full":"Zeeweg 5 Huizen Noord-Holland 1271 VV",
    "addr:housenumber":"5",
    "addr:postcode":"1271 vv",
    "addr:street":"Zeeweg",
    "iso:country":"NL",
    "sg:address":"Zeeweg 5",
    "sg:city":"Huizen",
    "sg:orig_category":"Diverse Opleidingen And Onderwijs",
    "sg:phone":"+31 35 539 3980",
    "sg:postcode":"1271 VV",
    "sg:province":"Noord-Holland",
    "wof:name":"Gooiconsult",
    "wof:placetype":"venue"
},
  "geometry": {"coordinates":[5.232466,52.300598],"type":"Point"}
}