{
  "type": "Feature",
  "properties": {
    "addr:full":"Nw Duinwg 19 Katwyk Zh Zuid-Holland 2224 ED",
    "addr:housenumber":"19",
    "addr:postcode":"2224 ed",
    "addr:street":"Katwyk",
    "iso:country":"NL",
    "sg:address":"Nw Duinwg 19",
    "sg:city":"Katwyk Zh",
    "sg:orig_category":"Bloemen En Planten - Groothandel",
    "sg:phone":"+31 71 401 3145",
    "sg:postcode":"2224 ED",
    "sg:province":"Zuid-Holland",
    "wof:name":"Kromhout En Zn Bv, Adriaan",
    "wof:placetype":"venue"
},
  "geometry": {"coordinates":[4.42057,52.187599],"type":"Point"}
}