{
  "type": "Feature",
  "properties": {
    "addr:full":"Koningstraat 51 Arnhem Gelderland 6811 DH",
    "addr:housenumber":"51",
    "addr:postcode":"6811 dh",
    "addr:street":"Koningstraat",
    "iso:country":"NL",
    "sg:address":"Koningstraat 51",
    "sg:city":"Arnhem",
    "sg:orig_category":"Discountwinkels",
    "sg:phone":"+31 26 389 2283",
    "sg:postcode":"6811 DH",
    "sg:province":"Gelderland",
    "wof:name":"Yankee Arnhem",
    "wof:placetype":"venue"
},
  "geometry": {"coordinates":[5.910184,51.980091],"type":"Point"}
}