{
  "type": "Feature",
  "properties": {
    "iso:country":"NL",
    "sg:address":"Pieter Van Ijpelaarstr 47",
    "sg:city":"Geertruidenberg",
    "sg:orig_category":"Metaalwerken",
    "sg:phone":"+31 162 521 125",
    "sg:postcode":"4931 RV",
    "sg:province":"Noord-Brabant",
    "wof:name":"El Sol",
    "wof:placetype":"venue"
},
  "geometry": {"coordinates":[4.85716,51.705498],"type":"Point"}
}