{
  "type": "Feature",
  "properties": {
    "addr:full":"F Schurerpln 2 Heerenveen Friesland 8441 PT",
    "addr:housenumber":"2",
    "addr:postcode":"8441 pt",
    "addr:street":"Schurerpln",
    "iso:country":"NL",
    "sg:address":"F Schurerpln 2",
    "sg:city":"Heerenveen",
    "sg:orig_category":"Scholen Voor Algemeen Voortgezet Onderwijs",
    "sg:phone":"+31 513 657 385",
    "sg:postcode":"8441 PT",
    "sg:province":"Friesland",
    "sg:website":"http://www.sevenwolden.nl",
    "wof:name":"Osg Sevenwolden",
    "wof:placetype":"venue"
},
  "geometry": {"coordinates":[5.915497,52.971367],"type":"Point"}
}