{
  "type": "Feature",
  "properties": {
    "addr:full":"Tromplaan 1 Baarn Utrecht 3742 AA",
    "addr:housenumber":"1",
    "addr:postcode":"3742 aa",
    "addr:street":"Tromplaan",
    "iso:country":"NL",
    "sg:address":"Tromplaan 1",
    "sg:city":"Baarn",
    "sg:orig_category":"Bedrijfs- And Managementsconsultants",
    "sg:phone":"+31 35 548 6500",
    "sg:postcode":"3742 AA",
    "sg:province":"Utrecht",
    "wof:name":"Unlimited Incentives Travel & Group Bv",
    "wof:placetype":"venue"
},
  "geometry": {"coordinates":[5.299664,52.213017],"type":"Point"}
}