{
  "type": "Feature",
  "properties": {
    "addr:full":"De Vlonder 131-133 Boekel Noord-Brabant 5427 DD",
    "addr:postcode":"131-133;5427 dd",
    "addr:street":"De Vlonder",
    "iso:country":"NL",
    "sg:address":"De Vlonder 131-133",
    "sg:city":"Boekel",
    "sg:classifiers":[
        {
            "category":"Retail",
            "subcategory":"Auto Repair",
            "type":"Services"
        }
    ],
    "sg:phone":"+31 492 324 975",
    "sg:postcode":"5427 DD",
    "sg:province":"Noord-Brabant",
    "sg:tags":[
        "garage"
    ],
    "wof:name":"Velden, Van Der",
    "wof:placetype":"venue"
},
  "geometry": {"coordinates":[5.67239,51.607101],"type":"Point"}
}