{
  "type": "Feature",
  "properties": {
    "iso:country":"NL",
    "sg:address":"Mariastraat 28",
    "sg:city":"Utrecht",
    "sg:orig_category":"Opticiens",
    "sg:phone":"+31 30 232 8186",
    "sg:postcode":"3511 LP",
    "sg:province":"Utrecht",
    "wof:name":"Optical Art",
    "wof:placetype":"venue"
},
  "geometry": {"coordinates":[5.1171588898,52.0906066895],"type":"Point"}
}