{
  "type": "Feature",
  "properties": {
    "iso:country":"NL",
    "sg:address":"Aalsmeerderdijk 660",
    "sg:city":"Rijsenhout",
    "sg:orig_category":"Loodgieterswerk, Verwarming And Sanitaire Installaties",
    "sg:phone":"+31 297 383 292",
    "sg:postcode":"1435 BX",
    "sg:province":"North Holland",
    "wof:name":"Lanser Installatietechniek Rijsenhout Bv",
    "wof:placetype":"venue"
},
  "geometry": {"coordinates":[4.718719,52.258472],"type":"Point"}
}