{
  "type": "Feature",
  "properties": {
    "addr:full":"V Hogendorpstr 5 Utrecht Utrecht 3581 KA",
    "addr:housenumber":"5",
    "addr:postcode":"3581 ka",
    "addr:street":"Hogendorpstr",
    "iso:country":"NL",
    "sg:address":"V Hogendorpstr 5",
    "sg:city":"Utrecht",
    "sg:orig_category":"Verzekeringen - Verzekeringskantoren",
    "sg:phone":"+31 30 251 0701",
    "sg:postcode":"3581 KA",
    "sg:province":"Utrecht",
    "sg:website":"http://www.scherrenberg.nl",
    "wof:name":"Scherrenberg",
    "wof:placetype":"venue"
},
  "geometry": {"coordinates":[5.13447,52.089989],"type":"Point"}
}