{
  "type": "Feature",
  "properties": {
    "addr:full":"Marswg 6 Wyster Provincie Drenthe 9418 PT",
    "addr:housenumber":"6",
    "addr:postcode":"9418",
    "addr:street":"Marswg;Provincie Drenthe;Pt",
    "iso:country":"NL",
    "sg:address":"Marswg 6",
    "sg:city":"Wyster",
    "sg:orig_category":"Bedrijfsopleidingen",
    "sg:phone":"+31 593 567 292",
    "sg:postcode":"9418 PT",
    "sg:province":"Provincie Drenthe",
    "wof:name":"Assembly",
    "wof:placetype":"venue"
},
  "geometry": {"coordinates":[6.531486,52.812244],"type":"Point"}
}