{
  "type": "Feature",
  "properties": {
    "iso:country":"NL",
    "sg:address":"Parkwg 76",
    "sg:city":"Ede Gld",
    "sg:orig_category":"Cafetaria'S",
    "sg:phone":"+31 318 636 475",
    "sg:postcode":"6717 HV",
    "sg:province":"Gelderland",
    "wof:name":"Luifel, De",
    "wof:placetype":"venue"
},
  "geometry": {"coordinates":[5.665942,52.027775],"type":"Point"}
}