{
  "type": "Feature",
  "properties": {
    "addr:full":"Stockholm 15 Barendrecht South Holland 2993 LM",
    "addr:housenumber":"15",
    "addr:postcode":"2993 lm",
    "addr:street":"Stockholm",
    "iso:country":"NL",
    "sg:address":"Stockholm 15",
    "sg:city":"Barendrecht",
    "sg:orig_category":"Horecabenodigdheden",
    "sg:phone":"+31 180 644 366",
    "sg:postcode":"2993 LM",
    "sg:province":"South Holland",
    "sg:website":"http://www.meiko.nl",
    "wof:name":"Meiko Nederland Bv",
    "wof:placetype":"venue"
},
  "geometry": {"coordinates":[4.510129,51.85004],"type":"Point"}
}