{
  "type": "Feature",
  "properties": {
    "iso:country":"NL",
    "sg:address":"Enserweg 15",
    "sg:city":"Ens",
    "sg:orig_category":"Bloemen And Planten Gh",
    "sg:phone":"+31 527 253 311",
    "sg:postcode":"8307 PK",
    "sg:province":"NL.",
    "wof:name":"Bloemengroothandel Thom Slootman",
    "wof:placetype":"venue"
},
  "geometry": {"coordinates":[5.839465,52.624817],"type":"Point"}
}