{
  "type": "Feature",
  "properties": {
    "addr:full":"Lopikerweg Oost 36B Lopik Utrecht 3411 JG",
    "addr:housenumber":"36b",
    "addr:postcode":"3411 jg",
    "addr:street":"Lopikerweg Oost",
    "iso:country":"NL",
    "sg:address":"Lopikerweg Oost 36B",
    "sg:city":"Lopik",
    "sg:orig_category":"Goederenvervoer Over De Weg",
    "sg:phone":"+31 348 552 300",
    "sg:postcode":"3411 JG",
    "sg:province":"Utrecht",
    "wof:name":"Gebr. Verburg Bv",
    "wof:placetype":"venue"
},
  "geometry": {"coordinates":[4.964916,51.977222],"type":"Point"}
}