{
  "type": "Feature",
  "properties": {
    "addr:full":"Gersteland 16 Leusden Utrecht 3833 CS",
    "addr:housenumber":"16",
    "addr:postcode":"3833 cs",
    "addr:street":"Gersteland",
    "iso:country":"NL",
    "sg:address":"Gersteland 16",
    "sg:city":"Leusden",
    "sg:orig_category":"Grafisch Ontwerpers",
    "sg:phone":"+31 33 433 2255",
    "sg:postcode":"3833 CS",
    "sg:province":"Utrecht",
    "wof:name":"Ultramarijn",
    "wof:placetype":"venue"
},
  "geometry": {"coordinates":[5.4187,52.132195],"type":"Point"}
}