{
  "type": "Feature",
  "properties": {
    "addr:full":"Verspronckweg 243 Haarlem North Holland 2023 BH",
    "addr:housenumber":"243",
    "addr:postcode":"2023 bh",
    "addr:street":"Verspronckweg",
    "iso:country":"NL",
    "sg:address":"Verspronckweg 243",
    "sg:city":"Haarlem",
    "sg:orig_category":"Boekhouders",
    "sg:phone":"+31 23 551 3630",
    "sg:postcode":"2023 BH",
    "sg:province":"North Holland",
    "wof:name":"Aims Fianancieel",
    "wof:placetype":"venue"
},
  "geometry": {"coordinates":[4.625598,52.394321],"type":"Point"}
}