{
  "type": "Feature",
  "properties": {
    "addr:full":"Raadhuisplein 42 Wervershoof Noord-Holland 1693 EA",
    "addr:housenumber":"42",
    "addr:postcode":"1693 ea",
    "addr:street":"Raadhuisplein",
    "iso:country":"NL",
    "sg:address":"Raadhuisplein 42",
    "sg:city":"Wervershoof",
    "sg:orig_category":"Kappers",
    "sg:phone":"+31 228 581 243",
    "sg:postcode":"1693 EA",
    "sg:province":"Noord-Holland",
    "wof:name":"Kapsalon Angela",
    "wof:placetype":"venue"
},
  "geometry": {"coordinates":[5.1503949165,52.7283630371],"type":"Point"}
}