{
  "type": "Feature",
  "properties": {
    "addr:full":"Leyweg 1094 'S Gravenhage South Holland 2545 GZ",
    "addr:housenumber":"1094 '",
    "addr:postcode":"2545 gz",
    "addr:street":"Leyweg",
    "iso:country":"NL",
    "sg:address":"Leyweg 1094",
    "sg:city":"'S Gravenhage",
    "sg:orig_category":"Banken And Kredietinstellingen",
    "sg:phone":"+31 70 366 3010",
    "sg:postcode":"2545 GZ",
    "sg:province":"South Holland",
    "wof:name":"Postkantoor",
    "wof:placetype":"venue"
},
  "geometry": {"coordinates":[4.27793,52.047634],"type":"Point"}
}