{
  "type": "Feature",
  "properties": {
    "addr:full":"P C Hooftstraat 14 Ridderkerk Zuid-Holland 2985 BK",
    "addr:housenumber":"14",
    "addr:postcode":"2985 bk",
    "addr:street":"P C Hooftstraat",
    "iso:country":"NL",
    "sg:address":"P C Hooftstraat 14",
    "sg:city":"Ridderkerk",
    "sg:orig_category":"Autoverhuur",
    "sg:phone":"+31 180 430 277",
    "sg:postcode":"2985 BK",
    "sg:province":"Zuid-Holland",
    "wof:name":"Autoverhuur Leasing Aristo Bv",
    "wof:placetype":"venue"
},
  "geometry": {"coordinates":[4.602751,51.867371],"type":"Point"}
}