{
  "type": "Feature",
  "properties": {
    "addr:full":"Tetterodestr 72 Haarlem Noord-Holland 2023 XR",
    "addr:housenumber":"72",
    "addr:postcode":"2023 xr",
    "addr:street":"Tetterodestr",
    "iso:country":"NL",
    "sg:address":"Tetterodestr 72",
    "sg:city":"Haarlem",
    "sg:orig_category":"Luchtbehandelings- Apparaten",
    "sg:phone":"+31 23 525 5018",
    "sg:postcode":"2023 XR",
    "sg:province":"Noord-Holland",
    "wof:name":"Biotron International",
    "wof:placetype":"venue"
},
  "geometry": {"coordinates":[4.627958,52.39167],"type":"Point"}
}