{
  "type": "Feature",
  "properties": {
    "addr:full":"Kanaalstr 105 Someren North Brabant 5711 EG",
    "addr:housenumber":"105",
    "addr:postcode":"5711 eg",
    "iso:country":"NL",
    "sg:address":"Kanaalstr 105",
    "sg:city":"Someren",
    "sg:orig_category":"Bodemonderzoek",
    "sg:phone":"+31 493 479 394",
    "sg:postcode":"5711 EG",
    "sg:province":"North Brabant",
    "sg:website":"http://www.ockhuizen.nl",
    "wof:name":"Ockhuizen Bv",
    "wof:placetype":"venue"
},
  "geometry": {"coordinates":[5.711272,51.384651],"type":"Point"}
}