{
  "type": "Feature",
  "properties": {
    "iso:country":"NL",
    "sg:address":"Broekstraat 3",
    "sg:city":"Belfeld",
    "sg:orig_category":"Honden- En Kattentrimsalons",
    "sg:phone":"+31 6 20599665",
    "sg:postcode":"5951 BX",
    "sg:province":"Limburg",
    "wof:name":"Woemy",
    "wof:placetype":"venue"
},
  "geometry": {"coordinates":[6.116955,51.30875],"type":"Point"}
}