{
  "type": "Feature",
  "properties": {
    "addr:full":"Heerlerwg 7A Voerendaal Limburg 6367 AA",
    "addr:housenumber":"7a",
    "addr:postcode":"6367 aa",
    "addr:street":"Heerlerwg",
    "iso:country":"NL",
    "sg:address":"Heerlerwg 7A",
    "sg:city":"Voerendaal",
    "sg:orig_category":"Fotolaboratoria",
    "sg:phone":"+31 45 562 0075",
    "sg:postcode":"6367 AA",
    "sg:province":"Limburg",
    "wof:name":"Spectrum",
    "wof:placetype":"venue"
},
  "geometry": {"coordinates":[5.944928,50.876003],"type":"Point"}
}