{
  "type": "Feature",
  "properties": {
    "addr:full":"Christinaln 70 Posterholt Limburg 6061 CZ",
    "addr:housenumber":"70",
    "addr:postcode":"6061",
    "addr:street":"Christinaln",
    "iso:country":"NL",
    "sg:address":"Christinaln 70",
    "sg:city":"Posterholt",
    "sg:orig_category":"Autorijscholen",
    "sg:phone":"+31 475 403 324",
    "sg:postcode":"6061 CZ",
    "sg:province":"Limburg",
    "wof:name":"Aktief",
    "wof:placetype":"venue"
},
  "geometry": {"coordinates":[6.041317,51.120335],"type":"Point"}
}