{
  "type": "Feature",
  "properties": {
    "addr:full":"Ulrumpad 22 Arnhem Gelderland 6835 AP",
    "addr:housenumber":"22",
    "addr:postcode":"6835 ap",
    "addr:street":"Ulrumpad",
    "iso:country":"NL",
    "sg:address":"Ulrumpad 22",
    "sg:city":"Arnhem",
    "sg:orig_category":"Video - Faciliteiten En Producties",
    "sg:phone":"+31 26 327 2800",
    "sg:postcode":"6835 AP",
    "sg:province":"Gelderland",
    "sg:website":"http://www.multimavision.nl",
    "wof:name":"Multimavision",
    "wof:placetype":"venue"
},
  "geometry": {"coordinates":[5.905627,51.955212],"type":"Point"}
}