{
  "type": "Feature",
  "properties": {
    "addr:full":"Lynckerstraat 22 'S Gravenhage Zuid-Holland 2562 NZ",
    "addr:housenumber":"22",
    "addr:postcode":"2562 nz",
    "addr:street":"Lynckerstraat;' S",
    "iso:country":"NL",
    "sg:address":"Lynckerstraat 22",
    "sg:city":"'S Gravenhage",
    "sg:orig_category":"Bedrijfsinventaris Gh",
    "sg:phone":"+31 70 360 8206",
    "sg:postcode":"2562 NZ",
    "sg:province":"Zuid-Holland",
    "wof:name":"Vof Superli Kosmetika Verkoopdivisie",
    "wof:placetype":"venue"
},
  "geometry": {"coordinates":[4.286594,52.072002],"type":"Point"}
}