{
  "type": "Feature",
  "properties": {
    "addr:full":"Heyhoefpromenade 34 Tilburg Noord-Brabant 5043 RM",
    "addr:housenumber":"34",
    "addr:postcode":"5043 rm",
    "addr:street":"Heyhoefpromenade",
    "iso:country":"NL",
    "sg:address":"Heyhoefpromenade 34",
    "sg:city":"Tilburg",
    "sg:orig_category":"Schoenen",
    "sg:phone":"+31 13 572 0914",
    "sg:postcode":"5043 RM",
    "sg:province":"Noord-Brabant",
    "wof:name":"Haren, Van",
    "wof:placetype":"venue"
},
  "geometry": {"coordinates":[5.006151,51.577713],"type":"Point"}
}