{
  "type": "Feature",
  "properties": {
    "iso:country":"NL",
    "sg:address":"De Middend 2",
    "sg:city":"Bovenkarspel",
    "sg:orig_category":"Overheidsdiensten",
    "sg:phone":"+31 228 510 111",
    "sg:postcode":"1611 KW",
    "sg:province":"Noord-Holland",
    "wof:name":"Gemeente Stede Broec",
    "wof:placetype":"venue"
},
  "geometry": {"coordinates":[5.2352371216,52.6959915161],"type":"Point"}
}