{
  "type": "Feature",
  "properties": {
    "addr:full":"J Huizingaln 112 Amsterdam Noord-Holland 1065 JE",
    "addr:housenumber":"112",
    "addr:postcode":"1065 je",
    "iso:country":"NL",
    "sg:address":"J Huizingaln 112",
    "sg:city":"Amsterdam",
    "sg:orig_category":"Exploitatie- Maatschappijen",
    "sg:phone":"+31 20 617 4161",
    "sg:postcode":"1065 JE",
    "sg:province":"Noord-Holland",
    "wof:name":"Rojahar Vof",
    "wof:placetype":"venue"
},
  "geometry": {"coordinates":[4.826925,52.361671],"type":"Point"}
}