{
  "type": "Feature",
  "properties": {
    "iso:country":"NL",
    "sg:address":"Dorpsstr 4",
    "sg:city":"Broek Op Langedyk",
    "sg:orig_category":"Kappers",
    "sg:phone":"+31 226 314 478",
    "sg:postcode":"1721 BK",
    "sg:province":"North Holland",
    "wof:name":"Gerard",
    "wof:placetype":"venue"
},
  "geometry": {"coordinates":[4.8054728508,52.6748123169],"type":"Point"}
}