{
  "type": "Feature",
  "properties": {
    "iso:country":"NL",
    "sg:address":"Irisln 67-69",
    "sg:city":"Oegstgeest",
    "sg:orig_category":"Badmode",
    "sg:phone":"+31 71 517 5397",
    "sg:postcode":"2343 CH",
    "sg:province":"Zuid-Holland",
    "wof:name":"Body Fashion",
    "wof:placetype":"venue"
},
  "geometry": {"coordinates":[4.468242,52.176617],"type":"Point"}
}