{
  "type": "Feature",
  "properties": {
    "iso:country":"NL",
    "sg:address":"Nieuwstraat 159",
    "sg:city":"Apeldoorn",
    "sg:orig_category":"Werving And Selectie Van Tijdelijk Personeel And Uitzendkantoren",
    "sg:phone":"+31 55 578 5200",
    "sg:postcode":"7311 BN",
    "sg:province":"Gelderland",
    "wof:name":"Manpower Uitzendorganisatie Bv",
    "wof:placetype":"venue"
},
  "geometry": {"coordinates":[5.9604148865,52.2140960693],"type":"Point"}
}