{
  "type": "Feature",
  "properties": {
    "iso:country":"NL",
    "sg:address":"Haaghuishof 7",
    "sg:city":"Leiderdorp",
    "sg:orig_category":"Alternatieve Geneeskunde",
    "sg:phone":"+31 71 541 1725",
    "sg:postcode":"2352 SV",
    "sg:province":"Zuid-Holland",
    "wof:name":"Yoga-Studio Leiderdorp",
    "wof:placetype":"venue"
},
  "geometry": {"coordinates":[4.522713,52.15686],"type":"Point"}
}