{
  "type": "Feature",
  "properties": {
    "addr:full":"Huizersdk 6 Zevenbergen Noord-Brabant 4761 PV",
    "addr:housenumber":"6",
    "addr:postcode":"4761 pv",
    "addr:street":"Huizersdk",
    "iso:country":"NL",
    "sg:address":"Huizersdk 6",
    "sg:city":"Zevenbergen",
    "sg:orig_category":"Kunststof Ramen",
    "sg:phone":"+31 168 336 678",
    "sg:postcode":"4761 PV",
    "sg:province":"Noord-Brabant",
    "wof:name":"Vectra Bv",
    "wof:placetype":"venue"
},
  "geometry": {"coordinates":[4.59773,51.64167],"type":"Point"}
}