{
  "type": "Feature",
  "properties": {
    "iso:country":"NL",
    "sg:address":"Zandstraat 24",
    "sg:city":"Culemborg",
    "sg:orig_category":"Verhuur Audiovisuele Apparatuur",
    "sg:phone":"+31 345 512 142",
    "sg:postcode":"4101 EG",
    "sg:province":"Gelderland",
    "wof:name":"Videotheek De Bron",
    "wof:placetype":"venue"
},
  "geometry": {"coordinates":[5.227124,51.954971],"type":"Point"}
}