{
  "type": "Feature",
  "properties": {
    "iso:country":"NL",
    "sg:address":"Burg Van Claarenbeekstr 43",
    "sg:city":"Ravenstein",
    "sg:orig_category":"Kappers",
    "sg:phone":"+31 486 412 301",
    "sg:postcode":"5371 BK",
    "sg:province":"North Brabant",
    "wof:name":"J.L.M. Van Dorst-Gruitrooy",
    "wof:placetype":"venue"
},
  "geometry": {"coordinates":[5.6451630592,51.7954025269],"type":"Point"}
}