{
  "type": "Feature",
  "properties": {
    "addr:full":"Heerbaan 15 Millingen A/D Rijn Gelderland 6566 EC",
    "addr:housenumber":"15;a / d",
    "addr:postcode":"6566 ec",
    "addr:street":"Heerbaan;Rijn Gelderland",
    "iso:country":"NL",
    "sg:address":"Heerbaan 15",
    "sg:city":"Millingen A/D Rijn",
    "sg:classifiers":[
        {
            "category":"Food & Beverages",
            "subcategory":"Fruits & Vegetables",
            "type":"Retail Goods"
        }
    ],
    "sg:phone":"+31 481 431 280",
    "sg:postcode":"6566 EC",
    "sg:province":"Gelderland",
    "sg:tags":[
        "groenten"
    ],
    "wof:name":"G.J. De Groot",
    "wof:placetype":"venue"
},
  "geometry": {"coordinates":[6.06019,51.860146],"type":"Point"}
}