{
  "type": "Feature",
  "properties": {
    "addr:full":"Singel 82A Sneek Provincie Friesland 8601 AM",
    "addr:housenumber":"82a;8601",
    "addr:street":"Singel;Provincie Friesland",
    "iso:country":"NL",
    "sg:address":"Singel 82A",
    "sg:city":"Sneek",
    "sg:orig_category":"Verenigingen En Stichtingen",
    "sg:phone":"+31 515 411 034",
    "sg:postcode":"8601 AM",
    "sg:province":"Provincie Friesland",
    "sg:website":"http://www.yfc.nl",
    "wof:name":"Youth For Christ",
    "wof:placetype":"venue"
},
  "geometry": {"coordinates":[5.662578,53.031384],"type":"Point"}
}