{
  "type": "Feature",
  "properties": {
    "addr:full":"Wellseindsedijk 8 Well Gld Gelderland 5325 KD",
    "addr:housenumber":"8",
    "addr:postcode":"5325 kd",
    "addr:street":"Wellseindsedijk;Gld Gelderland",
    "iso:country":"NL",
    "sg:address":"Wellseindsedijk 8",
    "sg:city":"Well Gld",
    "sg:orig_category":"Autokeuringen",
    "sg:phone":"+31 418 552 681",
    "sg:postcode":"5325 KD",
    "sg:province":"Gelderland",
    "wof:name":"Handelsonderneming De Potter",
    "wof:placetype":"venue"
},
  "geometry": {"coordinates":[5.187527,51.759697],"type":"Point"}
}