{
  "type": "Feature",
  "properties": {
    "addr:full":"Nieuw Amsterdamlaan 25 Utrecht Utrecht 3526 AE",
    "addr:housenumber":"25",
    "addr:postcode":"3526 ae",
    "addr:street":"Nieuw Amsterdamlaan",
    "iso:country":"NL",
    "sg:address":"Nieuw Amsterdamlaan 25",
    "sg:city":"Utrecht",
    "sg:orig_category":"Metaalwerken",
    "sg:phone":"+31 30 288 7026",
    "sg:postcode":"3526 AE",
    "sg:province":"Utrecht",
    "wof:name":"Spb Plafonds Bv",
    "wof:placetype":"venue"
},
  "geometry": {"coordinates":[5.104702,52.063446],"type":"Point"}
}