{
  "type": "Feature",
  "properties": {
    "iso:country":"NL",
    "sg:address":"Lange Hille 26",
    "sg:city":"Oud Beijerland",
    "sg:orig_category":"Boekhouders",
    "sg:phone":"+31 186 615 955",
    "sg:postcode":"3261 TL",
    "sg:province":"South Holland",
    "wof:name":"Ferdie Poppelier Adviesburo",
    "wof:placetype":"venue"
},
  "geometry": {"coordinates":[4.424979,51.827667],"type":"Point"}
}