{
  "type": "Feature",
  "properties": {
    "addr:full":"Vincent Van Goghplein 20 Etten-Leur North Brabant 4872 BB",
    "addr:housenumber":"20",
    "addr:postcode":"4872 bb",
    "addr:street":"Vincent Van Goghplein",
    "iso:country":"NL",
    "sg:address":"Vincent Van Goghplein 20",
    "sg:city":"Etten-Leur",
    "sg:orig_category":"Fietshandelaren",
    "sg:phone":"+31 76 501 2765",
    "sg:postcode":"4872 BB",
    "sg:province":"North Brabant",
    "wof:name":"Martien Boere En Zonen",
    "wof:placetype":"venue"
},
  "geometry": {"coordinates":[4.643202,51.572617],"type":"Point"}
}