{
  "type": "Feature",
  "properties": {
    "addr:full":"Raadhuisstraat 63 Roosendaal Noord-Brabant 4701 PM",
    "addr:housenumber":"63",
    "addr:postcode":"4701 pm",
    "addr:street":"Raadhuisstraat",
    "iso:country":"NL",
    "sg:address":"Raadhuisstraat 63",
    "sg:city":"Roosendaal",
    "sg:orig_category":"Notarissen",
    "sg:phone":"+31 165 544 930",
    "sg:postcode":"4701 PM",
    "sg:province":"Noord-Brabant",
    "wof:name":"Vreijling & Beijsers Notarissen",
    "wof:placetype":"venue"
},
  "geometry": {"coordinates":[4.459745,51.531693],"type":"Point"}
}