{
  "type": "Feature",
  "properties": {
    "addr:full":"Verseputseweg 2 Kerkwerve Zeeland 4321 AA",
    "addr:housenumber":"2",
    "addr:postcode":"4321 aa",
    "addr:street":"Verseputseweg",
    "iso:country":"NL",
    "sg:address":"Verseputseweg 2",
    "sg:city":"Kerkwerve",
    "sg:orig_category":"Goederenvervoer Over De Weg",
    "sg:phone":"+31 111 412 967",
    "sg:postcode":"4321 AA",
    "sg:province":"Zeeland",
    "wof:name":"W.P. Bolkenbaas",
    "wof:placetype":"venue"
},
  "geometry": {"coordinates":[3.896907,51.683903],"type":"Point"}
}