{
  "type": "Feature",
  "properties": {
    "addr:full":"Barbizonln 76 Capelle Ad Yssel Zuid-Holland 2908 ME",
    "addr:housenumber":"76",
    "addr:postcode":"2908 me",
    "addr:street":"Barbizonln",
    "iso:country":"NL",
    "sg:address":"Barbizonln 76",
    "sg:city":"Capelle Ad Yssel",
    "sg:orig_category":"Adviesbureaus Bedrijfsorganisatie",
    "sg:phone":"+31 10 209 9922",
    "sg:postcode":"2908 ME",
    "sg:province":"Zuid-Holland",
    "sg:website":"http://www.piersgroep.nl",
    "wof:name":"Piers Groep",
    "wof:placetype":"venue"
},
  "geometry": {"coordinates":[4.5846,51.923401],"type":"Point"}
}