{
  "type": "Feature",
  "properties": {
    "addr:full":"Kopermolen 14 Leiden Zuid-Holland 2317 PB",
    "addr:housenumber":"14",
    "addr:postcode":"2317 pb",
    "addr:street":"Kopermolen",
    "iso:country":"NL",
    "sg:address":"Kopermolen 14",
    "sg:city":"Leiden",
    "sg:orig_category":"Herenkleding",
    "sg:phone":"+31 71 523 3631",
    "sg:postcode":"2317 PB",
    "sg:province":"Zuid-Holland",
    "wof:name":"Edcar",
    "wof:placetype":"venue"
},
  "geometry": {"coordinates":[4.506276,52.176353],"type":"Point"}
}