{
  "type": "Feature",
  "properties": {
    "iso:country":"NL",
    "sg:address":"Dreespln 4",
    "sg:city":"Naaldwyk",
    "sg:classifiers":[
        {
            "category":"Shopping",
            "subcategory":"News",
            "type":"Retail Goods"
        }
    ],
    "sg:phone":"+31 174 621 886",
    "sg:postcode":"2672 EA",
    "sg:province":"South Holland",
    "sg:tags":[
        "maandbladen",
        "en",
        "week-"
    ],
    "wof:name":"Groot Naaldwijk",
    "wof:placetype":"venue"
},
  "geometry": {"coordinates":[4.222214222,51.995262146],"type":"Point"}
}