{
  "type": "Feature",
  "properties": {
    "addr:full":"Hogestraat 26 Rijsbergen Noord-Brabant 4891 CB",
    "addr:housenumber":"26",
    "addr:postcode":"4891 cb",
    "addr:street":"Hogestraat",
    "iso:country":"NL",
    "sg:address":"Hogestraat 26",
    "sg:city":"Rijsbergen",
    "sg:orig_category":"Architecten",
    "sg:phone":"+31 76 596 3151",
    "sg:postcode":"4891 CB",
    "sg:province":"Noord-Brabant",
    "wof:name":"De Nieuwe Kombinatie Blom Partners Bv",
    "wof:placetype":"venue"
},
  "geometry": {"coordinates":[4.706369,51.517597],"type":"Point"}
}