{
  "type": "Feature",
  "properties": {
    "addr:full":"Staringpln 20 Amsterdam Noord-Holland 1054 VL",
    "addr:housenumber":"20",
    "addr:postcode":"1054 vl",
    "addr:street":"Staringpln",
    "iso:country":"NL",
    "sg:address":"Staringpln 20",
    "sg:city":"Amsterdam",
    "sg:orig_category":"Fietsen En Bromfietsen",
    "sg:phone":"+31 20 683 0636",
    "sg:postcode":"1054 VL",
    "sg:province":"Noord-Holland",
    "wof:name":"Izzo",
    "wof:placetype":"venue"
},
  "geometry": {"coordinates":[4.863142,52.360355],"type":"Point"}
}