{
  "type": "Feature",
  "properties": {
    "iso:country":"NL",
    "sg:address":"Aviolandaln 20",
    "sg:city":"Hoogerheide",
    "sg:orig_category":"Kinderopvang",
    "sg:phone":"+31 164 614 168",
    "sg:postcode":"4631 RM",
    "sg:province":"Noord-Brabant",
    "wof:name":"Polleke",
    "wof:placetype":"venue"
},
  "geometry": {"coordinates":[4.325936,51.421288],"type":"Point"}
}