{
  "type": "Feature",
  "properties": {
    "iso:country":"NL",
    "sg:address":"Rijksweg 18",
    "sg:city":"Oosterland",
    "sg:orig_category":"Makelaars In Onroerend Goed",
    "sg:phone":"+31 111 642 698",
    "sg:postcode":"4307 LG",
    "sg:province":"Zeeland",
    "wof:name":"Van Veldhuizen Bv",
    "wof:placetype":"venue"
},
  "geometry": {"coordinates":[4.046816,51.657162],"type":"Point"}
}