{
  "type": "Feature",
  "properties": {
    "iso:country":"NL",
    "sg:address":"Marktplein 7",
    "sg:city":"Uithoorn",
    "sg:orig_category":"Banken And Kredietinstellingen",
    "sg:phone":"+31 297 561 667",
    "sg:postcode":"1421 AC",
    "sg:province":"Noord-Holland",
    "wof:name":"Abn Amro",
    "wof:placetype":"venue"
},
  "geometry": {"coordinates":[4.832394,52.233093],"type":"Point"}
}