{
  "type": "Feature",
  "properties": {
    "addr:full":"W De Zwygersngl 5 Gouda South Holland 2805 BP",
    "addr:housenumber":"5",
    "addr:postcode":"2805 bp",
    "addr:street":"W De Zwygersngl",
    "iso:country":"NL",
    "sg:address":"W De Zwygersngl 5",
    "sg:city":"Gouda",
    "sg:orig_category":"Scholen Voor Basisonderwijs",
    "sg:phone":"+31 182 513 555",
    "sg:postcode":"2805 BP",
    "sg:province":"South Holland",
    "wof:name":"Johannes Calvijn",
    "wof:placetype":"venue"
},
  "geometry": {"coordinates":[4.710715,52.010006],"type":"Point"}
}