{
  "type": "Feature",
  "properties": {
    "addr:full":"Curiewg 16 Alphen Aan Den Ryn Zuid-Holland 2408 BZ",
    "addr:housenumber":"16",
    "addr:postcode":"2408 bz",
    "addr:street":"Curiewg;Aan Den Ryn",
    "iso:country":"NL",
    "sg:address":"Curiewg 16",
    "sg:city":"Alphen Aan Den Ryn",
    "sg:orig_category":"Elektrotechnische Installatiebureaus",
    "sg:phone":"+31 6 50210646",
    "sg:postcode":"2408 BZ",
    "sg:province":"Zuid-Holland",
    "wof:name":"Ravensbergen, L",
    "wof:placetype":"venue"
},
  "geometry": {"coordinates":[4.630748,52.126144],"type":"Point"}
}