{
  "type": "Feature",
  "properties": {
    "addr:full":"Ruimzicht 98 Amsterdam Noord-Holland 1068 CP",
    "addr:housenumber":"98",
    "addr:postcode":"1068 cp",
    "addr:street":"Ruimzicht",
    "iso:country":"NL",
    "sg:address":"Ruimzicht 98",
    "sg:city":"Amsterdam",
    "sg:orig_category":"Adviesbureaus Bedrijfsorganisatie",
    "sg:phone":"+31 20 610 6975",
    "sg:postcode":"1068 CP",
    "sg:province":"Noord-Holland",
    "wof:name":"Otter Bv",
    "wof:placetype":"venue"
},
  "geometry": {"coordinates":[4.807225,52.361813],"type":"Point"}
}