{
  "type": "Feature",
  "properties": {
    "iso:country":"NL",
    "sg:address":"Groningerstraat 37",
    "sg:city":"Assen",
    "sg:orig_category":"Werving And Selectie Van Tijdelijk Personeel And Uitzendkantoren",
    "sg:phone":"+31 592 331 440",
    "sg:postcode":"9401 BH",
    "sg:province":"Provincie Drenthe",
    "wof:name":"Olympia Uitzendburo",
    "wof:placetype":"venue"
},
  "geometry": {"coordinates":[6.5638179779,52.9971084595],"type":"Point"}
}