{
  "type": "Feature",
  "properties": {
    "addr:full":"Bentrotstraat 44 Enschede NL.08 7531 AB",
    "addr:housenumber":"44",
    "addr:postcode":"7531 ab",
    "addr:street":"Bentrotstraat",
    "iso:country":"NL",
    "sg:address":"Bentrotstraat 44",
    "sg:city":"Enschede",
    "sg:orig_category":"Kantoor- And Schoolbenodigdheden Gh",
    "sg:phone":"+31 53 435 2725",
    "sg:postcode":"7531 AB",
    "sg:province":"NL.08",
    "wof:name":"Ter Hofte Verpakkingen Bv",
    "wof:placetype":"venue"
},
  "geometry": {"coordinates":[6.9024510384,52.2288703918],"type":"Point"}
}