{
  "type": "Feature",
  "properties": {
    "addr:full":"Hamersveldseweg 91 Leusden Utrecht 3833 GM",
    "addr:housenumber":"91",
    "addr:postcode":"3833 gm",
    "addr:street":"Hamersveldseweg",
    "iso:country":"NL",
    "sg:address":"Hamersveldseweg 91",
    "sg:city":"Leusden",
    "sg:orig_category":"Kantoorartikelen",
    "sg:phone":"+31 33 494 1144",
    "sg:postcode":"3833 GM",
    "sg:province":"Utrecht",
    "wof:name":"Computer Multi Media Centre",
    "wof:placetype":"venue"
},
  "geometry": {"coordinates":[5.4261569977,52.1289100647],"type":"Point"}
}