{
  "type": "Feature",
  "properties": {
    "addr:full":"Langestraat 23 Amersfoort Utrecht 3811  A",
    "addr:housenumber":"23;3811 a",
    "addr:street":"Langestraat",
    "iso:country":"NL",
    "sg:address":"Langestraat 23",
    "sg:city":"Amersfoort",
    "sg:orig_category":"Boekenuitgeverijen",
    "sg:phone":"+31 33 461 7030",
    "sg:postcode":"3811  A",
    "sg:province":"Utrecht",
    "wof:name":"Bruna",
    "wof:placetype":"venue"
},
  "geometry": {"coordinates":[5.386085,52.152325],"type":"Point"}
}