{
  "type": "Feature",
  "properties": {
    "addr:full":"Plesmanlaan 131 'S-Gravenhage 2497 CG",
    "addr:housenumber":"131",
    "addr:postcode":"2497 cg",
    "addr:street":"Plesmanlaan",
    "iso:country":"NL",
    "sg:address":"Plesmanlaan 131",
    "sg:city":"'S-Gravenhage",
    "sg:orig_category":"Bejaarden - Verzorgingstehuizen",
    "sg:phone":"+31 70 319 4740",
    "sg:postcode":"2497 CG",
    "wof:name":"Exfa",
    "wof:placetype":"venue"
},
  "geometry": {"coordinates":[4.365978,52.039288],"type":"Point"}
}