{
  "type": "Feature",
  "properties": {
    "addr:full":"Goudwespmeent 31 Hilversum North Holland 1218 GN",
    "addr:housenumber":"31",
    "addr:postcode":"1218 gn",
    "addr:street":"Goudwespmeent",
    "iso:country":"NL",
    "sg:address":"Goudwespmeent 31",
    "sg:city":"Hilversum",
    "sg:orig_category":"Juridische Dienstverlening",
    "sg:phone":"+31 35 693 0808",
    "sg:postcode":"1218 GN",
    "sg:province":"North Holland",
    "wof:name":"B & C -Consultancy",
    "wof:placetype":"venue"
},
  "geometry": {"coordinates":[5.137763,52.266396],"type":"Point"}
}