{
  "type": "Feature",
  "properties": {
    "addr:full":"Rietveldenwg 68D S Hertogenbosch Noord-Brabant 5222 AS",
    "addr:housenumber":"68d",
    "addr:postcode":"5222 as",
    "addr:street":"Rietveldenwg",
    "iso:country":"NL",
    "sg:address":"Rietveldenwg 68D",
    "sg:city":"S Hertogenbosch",
    "sg:orig_category":"Accountants - Administratie- Consulenten En -Kantoren",
    "sg:phone":"+31 73 623 2450",
    "sg:postcode":"5222 AS",
    "sg:province":"Noord-Brabant",
    "wof:name":"Deykerhoff Accountants",
    "wof:placetype":"venue"
},
  "geometry": {"coordinates":[5.268128,51.704906],"type":"Point"}
}