{
  "type": "Feature",
  "properties": {
    "iso:country":"NL",
    "sg:address":"Eems 29",
    "sg:city":"Gasselternijveen",
    "sg:orig_category":"Levende Dieren Gh",
    "sg:phone":"+31 599 512 216",
    "sg:postcode":"9514 EE",
    "sg:province":"Drenthe",
    "wof:name":"Wildhandel Ploeger",
    "wof:placetype":"venue"
},
  "geometry": {"coordinates":[6.848601,52.985405],"type":"Point"}
}