{
  "type": "Feature",
  "properties": {
    "addr:full":"Suikerland 2 Arnhem Gelderland 6833 BA",
    "addr:housenumber":"2",
    "addr:postcode":"6833 ba",
    "addr:street":"Suikerland",
    "iso:country":"NL",
    "sg:address":"Suikerland 2",
    "sg:city":"Arnhem",
    "sg:orig_category":"Kappers",
    "sg:phone":"+31 26 322 9171",
    "sg:postcode":"6833 BA",
    "sg:province":"Gelderland",
    "wof:name":"Chez Daoudi",
    "wof:placetype":"venue"
},
  "geometry": {"coordinates":[5.908700943,51.9683647156],"type":"Point"}
}