{
  "type": "Feature",
  "properties": {
    "addr:full":"Piazza 1 Eindhoven Noord-Brabant 5611 AE",
    "addr:housenumber":"1",
    "addr:postcode":"5611 ae",
    "addr:street":"Piazza",
    "iso:country":"NL",
    "sg:address":"Piazza 1",
    "sg:city":"Eindhoven",
    "sg:orig_category":"Juweliers",
    "sg:phone":"+31 40 244 4885",
    "sg:postcode":"5611 AE",
    "sg:province":"Noord-Brabant",
    "wof:name":"Diamond Point Bv",
    "wof:placetype":"venue"
},
  "geometry": {"coordinates":[5.47676,51.441853],"type":"Point"}
}