{
  "type": "Feature",
  "properties": {
    "addr:full":"Briljant 10 Eindhoven Noord-Brabant 5629 HG",
    "addr:housenumber":"10",
    "addr:postcode":"5629 hg",
    "addr:street":"Briljant",
    "iso:country":"NL",
    "sg:address":"Briljant 10",
    "sg:city":"Eindhoven",
    "sg:orig_category":"Psychologen",
    "sg:phone":"+31 40 248 4648",
    "sg:postcode":"5629 HG",
    "sg:province":"Noord-Brabant",
    "wof:name":"Fastenau, Drs J",
    "wof:placetype":"venue"
},
  "geometry": {"coordinates":[5.460875,51.48835],"type":"Point"}
}