{
  "type": "Feature",
  "properties": {
    "addr:full":"Min Nelissenstr 31 Breda Noord-Brabant 4818 HS",
    "addr:housenumber":"31",
    "addr:postcode":"4818 hs",
    "iso:country":"NL",
    "sg:address":"Min Nelissenstr 31",
    "sg:city":"Breda",
    "sg:orig_category":"Adviesbureaus Bedrijfsorganisatie",
    "sg:phone":"+31 76 521 8399",
    "sg:postcode":"4818 HS",
    "sg:province":"Noord-Brabant",
    "wof:name":"Signo & S",
    "wof:placetype":"venue"
},
  "geometry": {"coordinates":[4.78242,51.577244],"type":"Point"}
}