{
  "type": "Feature",
  "properties": {
    "addr:full":"J.F. Kennedylaan 100 Baarn Utrecht 3741 EH",
    "addr:housenumber":"100",
    "addr:postcode":"3741 eh",
    "addr:street":"J.F. Kennedylaan",
    "iso:country":"NL",
    "sg:address":"J.F. Kennedylaan 100",
    "sg:city":"Baarn",
    "sg:orig_category":"Bedrijfs- And Managementsconsultants",
    "sg:phone":"+31 35 548 6800",
    "sg:postcode":"3741 EH",
    "sg:province":"Utrecht",
    "wof:name":"The Boston Consulting Group",
    "wof:placetype":"venue"
},
  "geometry": {"coordinates":[5.274651,52.219292],"type":"Point"}
}