{
  "type": "Feature",
  "properties": {
    "addr:full":"Klaproosstr 31 Rosmalen North Brabant 5241 XL",
    "addr:housenumber":"31",
    "addr:postcode":"5241 xl",
    "addr:street":"Klaproosstr",
    "iso:country":"NL",
    "sg:address":"Klaproosstr 31",
    "sg:city":"Rosmalen",
    "sg:orig_category":"Wegenbouw",
    "sg:phone":"+31 73 521 2563",
    "sg:postcode":"5241 XL",
    "sg:province":"North Brabant",
    "wof:name":"Tuijl Bv, Van",
    "wof:placetype":"venue"
},
  "geometry": {"coordinates":[5.3518629074,51.7169723511],"type":"Point"}
}