{
  "type": "Feature",
  "properties": {
    "addr:full":"Rappardstr 30 Arnhem Gelderland 6822 CX",
    "addr:housenumber":"30",
    "addr:postcode":"6822 cx",
    "addr:street":"Rappardstr",
    "iso:country":"NL",
    "sg:address":"Rappardstr 30",
    "sg:city":"Arnhem",
    "sg:orig_category":"Verenigingen En Stichtingen",
    "sg:phone":"+31 26 351 3428",
    "sg:postcode":"6822 CX",
    "sg:province":"Gelderland",
    "wof:name":"Klarendal",
    "wof:placetype":"venue"
},
  "geometry": {"coordinates":[5.920791,51.986637],"type":"Point"}
}