{
  "type": "Feature",
  "properties": {
    "addr:full":"Eibergsestr 9 Haaksbergen Overijssel 7481 HE",
    "addr:housenumber":"9",
    "addr:postcode":"7481 he",
    "addr:street":"Eibergsestr",
    "iso:country":"NL",
    "sg:address":"Eibergsestr 9",
    "sg:city":"Haaksbergen",
    "sg:orig_category":"Poeliers",
    "sg:phone":"+31 53 572 8551",
    "sg:postcode":"7481 HE",
    "sg:province":"Overijssel",
    "wof:name":"Satink",
    "wof:placetype":"venue"
},
  "geometry": {"coordinates":[6.74028,52.152996],"type":"Point"}
}