{
  "type": "Feature",
  "properties": {
    "addr:full":"Kortenhoefsedijk 189 Kortenhoef North Holland 1241 NA",
    "addr:housenumber":"189",
    "addr:postcode":"1241 na",
    "addr:street":"Kortenhoefsedijk",
    "iso:country":"NL",
    "sg:address":"Kortenhoefsedijk 189",
    "sg:city":"Kortenhoef",
    "sg:orig_category":"Pleziervaartuigen And Reparatie",
    "sg:phone":"+31 35 656 2932",
    "sg:postcode":"1241 NA",
    "sg:province":"North Holland",
    "wof:name":"P. Schouten",
    "wof:placetype":"venue"
},
  "geometry": {"coordinates":[5.086637,52.22773],"type":"Point"}
}