{
  "type": "Feature",
  "properties": {
    "iso:country":"NL",
    "sg:address":"Kanaaldk 106-B",
    "sg:city":"Landsmeer",
    "sg:orig_category":"Bruggenbouw",
    "sg:phone":"+31 20 633 4357",
    "sg:postcode":"1121 NZ",
    "sg:province":"Noord-Holland",
    "wof:name":"Braams Bv",
    "wof:placetype":"venue"
},
  "geometry": {"coordinates":[4.944294,52.418335],"type":"Point"}
}