{
  "type": "Feature",
  "properties": {
    "addr:full":"H V Dinterstr 8 Nootdorp South Holland 2631 BR",
    "addr:housenumber":"8",
    "addr:postcode":"2631 br",
    "addr:street":"H V Dinterstr",
    "iso:country":"NL",
    "sg:address":"H V Dinterstr 8",
    "sg:city":"Nootdorp",
    "sg:orig_category":"Woninginrichting",
    "sg:phone":"+31 15 310 7211",
    "sg:postcode":"2631 BR",
    "sg:province":"South Holland",
    "wof:name":"Jasperse, T",
    "wof:placetype":"venue"
},
  "geometry": {"coordinates":[4.3920249939,52.0427017212],"type":"Point"}
}