{
  "type": "Feature",
  "properties": {
    "addr:full":"Adm De Ruyterwg 75 Amsterdam Noord-Holland 1057 JZ",
    "addr:housenumber":"75",
    "addr:postcode":"1057 jz",
    "iso:country":"NL",
    "sg:address":"Adm De Ruyterwg 75",
    "sg:city":"Amsterdam",
    "sg:orig_category":"Fotolaboratoria",
    "sg:phone":"+31 20 412 5523",
    "sg:postcode":"1057 JZ",
    "sg:province":"Noord-Holland",
    "wof:name":"Lumino",
    "wof:placetype":"venue"
},
  "geometry": {"coordinates":[4.85364,52.367519],"type":"Point"}
}