{
  "type": "Feature",
  "properties": {
    "iso:country":"NL",
    "sg:address":"Molenstraat 25",
    "sg:city":"Ameide",
    "sg:orig_category":"Goederenvervoer Over De Weg",
    "sg:phone":"+31 183 601 227",
    "sg:postcode":"4233 EP",
    "sg:province":"Zuid-Holland",
    "wof:name":"Fa P Peterse En Zoon",
    "wof:placetype":"venue"
},
  "geometry": {"coordinates":[4.962897,51.95697],"type":"Point"}
}