{
  "type": "Feature",
  "properties": {
    "addr:full":"Meeuwenln 110A 2Hg Amsterdam North Holland 1021 JM",
    "addr:housenumber":"110a",
    "addr:postcode":"1021 jm",
    "addr:street":"2Hg",
    "iso:country":"NL",
    "sg:address":"Meeuwenln 110A 2Hg",
    "sg:city":"Amsterdam",
    "sg:orig_category":"Modeontwerpen",
    "sg:phone":"+31 20 637 3642",
    "sg:postcode":"1021 JM",
    "sg:province":"North Holland",
    "wof:name":"Hoek, Edwin Van Den",
    "wof:placetype":"venue"
},
  "geometry": {"coordinates":[4.922948,52.385998],"type":"Point"}
}