{
  "type": "Feature",
  "properties": {
    "addr:full":"Zilvermeeuw 171 Etten Leur Noord-Brabant 4872 RV",
    "addr:housenumber":"171",
    "addr:postcode":"4872 rv",
    "addr:street":"Zilvermeeuw",
    "iso:country":"NL",
    "sg:address":"Zilvermeeuw 171",
    "sg:city":"Etten Leur",
    "sg:orig_category":"Adviesbureaus Bedrijfsorganisatie",
    "sg:phone":"+31 6 24249083",
    "sg:postcode":"4872 RV",
    "sg:province":"Noord-Brabant",
    "sg:website":"http://www.ordecon.nl",
    "wof:name":"Ordecon",
    "wof:placetype":"venue"
},
  "geometry": {"coordinates":[4.660269,51.577461],"type":"Point"}
}