{
  "type": "Feature",
  "properties": {
    "addr:full":"Singelwg 11 Grypskerke Zeeland 4364 LA",
    "addr:housenumber":"11",
    "addr:postcode":"4364",
    "addr:street":"Singelwg;Zeeland",
    "iso:country":"NL",
    "sg:address":"Singelwg 11",
    "sg:city":"Grypskerke",
    "sg:orig_category":"Galeries",
    "sg:phone":"+31 118 625 284",
    "sg:postcode":"4364 LA",
    "sg:province":"Zeeland",
    "wof:name":"Osseberg, De",
    "wof:placetype":"venue"
},
  "geometry": {"coordinates":[3.590585,51.525265],"type":"Point"}
}