{
  "type": "Feature",
  "properties": {
    "iso:country":"NL",
    "sg:address":"Burg V Tuyllkd 8",
    "sg:city":"Utrecht",
    "sg:orig_category":"Administratie- En Boekhoudkantoren",
    "sg:phone":"+31 30 246 8041",
    "sg:postcode":"3553 AH",
    "sg:province":"Utrecht",
    "sg:website":"http://www.cabb.citron.nl/cabb",
    "wof:name":"Cabb",
    "wof:placetype":"venue"
},
  "geometry": {"coordinates":[5.08441,52.109322],"type":"Point"}
}