{
  "type": "Feature",
  "properties": {
    "iso:country":"NL",
    "sg:address":"Prinsenstr 6",
    "sg:city":"Bredevoort",
    "sg:orig_category":"Goudsmeden En Zilversmeden",
    "sg:phone":"+31 543 451 825",
    "sg:postcode":"7126 AX",
    "sg:province":"Gelderland",
    "sg:website":"http://www.elcerlyck.nl",
    "wof:name":"Elcerlyck",
    "wof:placetype":"venue"
},
  "geometry": {"coordinates":[6.617181,51.943802],"type":"Point"}
}