{
  "type": "Feature",
  "properties": {
    "addr:full":"Palladiostr 164 Rotterdam Zuid-Holland 3066 AK",
    "addr:housenumber":"164",
    "addr:postcode":"3066 ak",
    "iso:country":"NL",
    "sg:address":"Palladiostr 164",
    "sg:city":"Rotterdam",
    "sg:orig_category":"Schilders",
    "sg:phone":"+31 10 228 1983",
    "sg:postcode":"3066 AK",
    "sg:province":"Zuid-Holland",
    "wof:name":"Andr? Mijs",
    "wof:placetype":"venue"
},
  "geometry": {"coordinates":[4.55052,51.938442],"type":"Point"}
}