{
  "type": "Feature",
  "properties": {
    "addr:full":"Diezerstraat 13 Zwolle Overijssel 8011 RA",
    "addr:housenumber":"13",
    "addr:postcode":"8011 ra",
    "addr:street":"Diezerstraat",
    "iso:country":"NL",
    "sg:address":"Diezerstraat 13",
    "sg:city":"Zwolle",
    "sg:orig_category":"Drogisterijen",
    "sg:phone":"+31 38 423 1693",
    "sg:postcode":"8011 RA",
    "sg:province":"Overijssel",
    "wof:name":"De Tuin Van Zwolle",
    "wof:placetype":"venue"
},
  "geometry": {"coordinates":[6.093802,52.512493],"type":"Point"}
}