{
  "type": "Feature",
  "properties": {
    "addr:full":"Puttenweg 99 Ijsselsteyn Lb Limburg 5813 BB",
    "addr:housenumber":"99",
    "addr:postcode":"lb;5813 bb",
    "addr:street":"Puttenweg",
    "iso:country":"NL",
    "sg:address":"Puttenweg 99",
    "sg:city":"Ijsselsteyn Lb",
    "sg:orig_category":"Autokeuringen",
    "sg:phone":"+31 478 541 278",
    "sg:postcode":"5813 BB",
    "sg:province":"Limburg",
    "wof:name":"J.H. Coenen",
    "wof:placetype":"venue"
},
  "geometry": {"coordinates":[5.927092,51.473412],"type":"Point"}
}