{
  "type": "Feature",
  "properties": {
    "iso:country":"NL",
    "sg:address":"Edisonstr 13",
    "sg:city":"Goirle",
    "sg:orig_category":"Machinehandel",
    "sg:phone":"+31 13 530 0154",
    "sg:postcode":"5051 DS",
    "sg:province":"North Brabant",
    "wof:name":"Cort Bv, Machineshandel De",
    "wof:placetype":"venue"
},
  "geometry": {"coordinates":[5.05075,51.506771],"type":"Point"}
}