{
  "type": "Feature",
  "properties": {
    "addr:full":"Van Baerlestraat 62 Amsterdam Noord-Holland 1071 BA",
    "addr:housenumber":"62",
    "addr:postcode":"1071 ba",
    "addr:street":"Van Baerlestraat",
    "iso:country":"NL",
    "sg:address":"Van Baerlestraat 62",
    "sg:city":"Amsterdam",
    "sg:orig_category":"Bedrijfs- And Managementsconsultants",
    "sg:phone":"+31 20 664 2442",
    "sg:postcode":"1071 BA",
    "sg:province":"Noord-Holland",
    "wof:name":"Adviesbureau Roma",
    "wof:placetype":"venue"
},
  "geometry": {"coordinates":[4.878434,52.357861],"type":"Point"}
}