{
  "type": "Feature",
  "properties": {
    "addr:full":"Nz Haven 18 Bergen Op Zoom Noord-Brabant 4611 GS",
    "addr:housenumber":"18",
    "addr:postcode":"4611 gs",
    "addr:street":"Nz Haven",
    "iso:country":"NL",
    "sg:address":"Nz Haven 18",
    "sg:city":"Bergen Op Zoom",
    "sg:orig_category":"Begrafenisverzorging",
    "sg:phone":"+31 164 248 739",
    "sg:postcode":"4611 GS",
    "sg:province":"Noord-Brabant",
    "wof:name":"Reijpert, R",
    "wof:placetype":"venue"
},
  "geometry": {"coordinates":[4.281987,51.495953],"type":"Point"}
}