{
  "type": "Feature",
  "properties": {
    "addr:full":"Singel 68 Amsterdam Noord-Holland 1015 AC",
    "addr:housenumber":"68",
    "addr:postcode":"1015 ac",
    "addr:street":"Singel",
    "iso:country":"NL",
    "sg:address":"Singel 68",
    "sg:city":"Amsterdam",
    "sg:orig_category":"Diverse Grafische Activiteiten",
    "sg:phone":"+31 20 622 3801",
    "sg:postcode":"1015 AC",
    "sg:province":"Noord-Holland",
    "wof:name":"Dart Design Bv",
    "wof:placetype":"venue"
},
  "geometry": {"coordinates":[4.892069,52.377571],"type":"Point"}
}