{
  "type": "Feature",
  "properties": {
    "addr:full":"Hommelsewg 2 Arnhem Gelderland 6821 LL",
    "addr:housenumber":"2",
    "addr:postcode":"6821 ll",
    "addr:street":"Hommelsewg",
    "iso:country":"NL",
    "sg:address":"Hommelsewg 2",
    "sg:city":"Arnhem",
    "sg:orig_category":"Honden- En Kattentrimsalons",
    "sg:phone":"+31 26 442 3425",
    "sg:postcode":"6821 LL",
    "sg:province":"Gelderland",
    "wof:name":"Charmant",
    "wof:placetype":"venue"
},
  "geometry": {"coordinates":[5.914277,51.986015],"type":"Point"}
}