{
  "type": "Feature",
  "properties": {
    "addr:full":"Berlostr 9 Voerendaal Limburg 6367 CA",
    "addr:housenumber":"9",
    "addr:postcode":"6367 ca",
    "addr:street":"Berlostr",
    "iso:country":"NL",
    "sg:address":"Berlostr 9",
    "sg:city":"Voerendaal",
    "sg:orig_category":"Adviesbureaus Bedrijfsorganisatie",
    "sg:phone":"+31 45 562 0678",
    "sg:postcode":"6367 CA",
    "sg:province":"Limburg",
    "wof:name":"Lenoir Bv, Drs H J H",
    "wof:placetype":"venue"
},
  "geometry": {"coordinates":[5.936806,50.880615],"type":"Point"}
}