{
  "type": "Feature",
  "properties": {
    "addr:full":"T Zandblauwtje 6 Maarheeze North Brabant 6026 VT",
    "addr:housenumber":"6",
    "addr:postcode":"6026",
    "addr:street":"T Zandblauwtje",
    "iso:country":"NL",
    "sg:address":"T Zandblauwtje 6",
    "sg:city":"Maarheeze",
    "sg:orig_category":"Verzekeringen",
    "sg:phone":"+31 495 591 624",
    "sg:postcode":"6026 VT",
    "sg:province":"North Brabant",
    "wof:name":"Assurantie- & Financ Kantoor M.F. Van De",
    "wof:placetype":"venue"
},
  "geometry": {"coordinates":[5.624077,51.308704],"type":"Point"}
}