{
  "type": "Feature",
  "properties": {
    "addr:full":"Jislumerdk 5 Birdaard Provincie Friesland 9111 HC",
    "addr:housenumber":"5",
    "addr:postcode":"9111 hc",
    "addr:street":"Jislumerdk;Provincie Friesland",
    "iso:country":"NL",
    "sg:address":"Jislumerdk 5",
    "sg:city":"Birdaard",
    "sg:orig_category":"Machineonderhoud En -Reparatie",
    "sg:phone":"+31 519 332 446",
    "sg:postcode":"9111 HC",
    "sg:province":"Provincie Friesland",
    "wof:name":"Instamac Bv",
    "wof:placetype":"venue"
},
  "geometry": {"coordinates":[5.878654,53.295761],"type":"Point"}
}