{
  "type": "Feature",
  "properties": {
    "addr:full":"Oranjestr 121 Arnhem Gelderland 6812 CN",
    "addr:housenumber":"121",
    "addr:postcode":"6812 cn",
    "iso:country":"NL",
    "sg:address":"Oranjestr 121",
    "sg:city":"Arnhem",
    "sg:orig_category":"Galeries",
    "sg:phone":"+31 26 446 0595",
    "sg:postcode":"6812 CN",
    "sg:province":"Gelderland",
    "wof:name":"Keramaikos",
    "wof:placetype":"venue"
},
  "geometry": {"coordinates":[5.8818,51.983822],"type":"Point"}
}