{
  "type": "Feature",
  "properties": {
    "addr:full":"Gangboord 9 Groningen Groningen 9733 GA",
    "addr:housenumber":"9",
    "addr:postcode":"9733 ga",
    "addr:street":"Gangboord",
    "iso:country":"NL",
    "sg:address":"Gangboord 9",
    "sg:city":"Groningen",
    "sg:orig_category":"Wasmachines En Wasdrogers - Verhuur",
    "sg:phone":"+31 50 542 4731",
    "sg:postcode":"9733 GA",
    "sg:province":"Groningen",
    "wof:name":"Waslijn, De",
    "wof:placetype":"venue"
},
  "geometry": {"coordinates":[6.6167712212,53.2395057678],"type":"Point"}
}