{
  "type": "Feature",
  "properties": {
    "addr:full":"Tiendweg 13 Tienhoven Zh South Holland 4235 VW",
    "addr:housenumber":"13",
    "addr:postcode":"zh;4235 vw",
    "addr:street":"Tiendweg",
    "iso:country":"NL",
    "sg:address":"Tiendweg 13",
    "sg:city":"Tienhoven Zh",
    "sg:orig_category":"Fruitteelt",
    "sg:phone":"+31 183 601 261",
    "sg:postcode":"4235 VW",
    "sg:province":"South Holland",
    "wof:name":"H. Zweeren En Zoon C.V.",
    "wof:placetype":"venue"
},
  "geometry": {"coordinates":[4.939021,51.94503],"type":"Point"}
}