{
  "type": "Feature",
  "properties": {
    "addr:full":"Coba Ritsemastraat 31 Tilburg Noord-Brabant 5038 KL",
    "addr:housenumber":"31",
    "addr:postcode":"5038 kl",
    "addr:street":"Coba Ritsemastraat",
    "iso:country":"NL",
    "sg:address":"Coba Ritsemastraat 31",
    "sg:city":"Tilburg",
    "sg:orig_category":"Boekenuitgeverijen",
    "sg:phone":"+31 13 463 5083",
    "sg:postcode":"5038 KL",
    "sg:province":"Noord-Brabant",
    "wof:name":"Drukkerij En Uitgeverij Nas Ii",
    "wof:placetype":"venue"
},
  "geometry": {"coordinates":[5.066725,51.55547],"type":"Point"}
}