{
  "type": "Feature",
  "properties": {
    "addr:full":"Ansinghlaan 42 Nieuwegein Utrecht 3431 GV",
    "addr:housenumber":"42",
    "addr:postcode":"3431 gv",
    "addr:street":"Ansinghlaan",
    "iso:country":"NL",
    "sg:address":"Ansinghlaan 42",
    "sg:city":"Nieuwegein",
    "sg:orig_category":"Meubeltextiel Fab",
    "sg:phone":"+31 30 604 3680",
    "sg:postcode":"3431 GV",
    "sg:province":"Utrecht",
    "wof:name":"Hofstede",
    "wof:placetype":"venue"
},
  "geometry": {"coordinates":[5.079685,52.036236],"type":"Point"}
}