{
  "type": "Feature",
  "properties": {
    "addr:full":"O Kinderdk 345 Alblasserdam South Holland 2953 CN",
    "addr:housenumber":"345",
    "addr:postcode":"2953 cn",
    "iso:country":"NL",
    "sg:address":"O Kinderdk 345",
    "sg:city":"Alblasserdam",
    "sg:orig_category":"Kappers",
    "sg:phone":"+31 78 691 2914",
    "sg:postcode":"2953 CN",
    "sg:province":"South Holland",
    "wof:name":"Waal, C De",
    "wof:placetype":"venue"
},
  "geometry": {"coordinates":[4.637485,51.87072],"type":"Point"}
}