{
  "type": "Feature",
  "properties": {
    "addr:full":"Grootzeil 9 Zeewolde Flevoland 3891 KH",
    "addr:housenumber":"9",
    "addr:postcode":"3891 kh",
    "addr:street":"Grootzeil;Flevoland",
    "iso:country":"NL",
    "sg:address":"Grootzeil 9",
    "sg:city":"Zeewolde",
    "sg:orig_category":"Hang- And Sluitwerk Fab",
    "sg:phone":"+31 36 522 7744",
    "sg:postcode":"3891 KH",
    "sg:province":"Flevoland",
    "wof:name":"Winkhaus Nederland",
    "wof:placetype":"venue"
},
  "geometry": {"coordinates":[5.525006,52.337566],"type":"Point"}
}