{
  "type": "Feature",
  "properties": {
    "iso:country":"NL",
    "sg:address":"Verl Herewg 137",
    "sg:city":"Groningen",
    "sg:orig_category":"Haptotherapeuten",
    "sg:phone":"+31 50 526 9379",
    "sg:postcode":"9721 AL",
    "sg:province":"Groningen",
    "sg:website":"http://www.haptotherapeuten-vvh.nl",
    "wof:name":"Graaf, E G De",
    "wof:placetype":"venue"
},
  "geometry": {"coordinates":[6.58123,53.195782],"type":"Point"}
}