{
  "type": "Feature",
  "properties": {
    "addr:full":"Rijnstraat 10 Woerden Utrecht 3441 BT",
    "addr:housenumber":"10",
    "addr:postcode":"3441 bt",
    "addr:street":"Rijnstraat",
    "iso:country":"NL",
    "sg:address":"Rijnstraat 10",
    "sg:city":"Woerden",
    "sg:orig_category":"Werving And Selectie Van Tijdelijk Personeel And Uitzendkantoren",
    "sg:phone":"+31 348 480 088",
    "sg:postcode":"3441 BT",
    "sg:province":"Utrecht",
    "wof:name":"Adecco",
    "wof:placetype":"venue"
},
  "geometry": {"coordinates":[4.8837499619,52.0870323181],"type":"Point"}
}