{
  "type": "Feature",
  "properties": {
    "addr:full":"Plantsoen 10 Lage Zwaluwe North Brabant 4926 RB",
    "addr:housenumber":"10",
    "addr:postcode":"4926 rb",
    "addr:street":"Plantsoen",
    "iso:country":"NL",
    "sg:address":"Plantsoen 10",
    "sg:city":"Lage Zwaluwe",
    "sg:orig_category":"Peuterspeelzalen",
    "sg:phone":"+31 168 484 667",
    "sg:postcode":"4926 RB",
    "sg:province":"North Brabant",
    "wof:name":"Speeldoos, De",
    "wof:placetype":"venue"
},
  "geometry": {"coordinates":[4.709338,51.704697],"type":"Point"}
}