{
  "type": "Feature",
  "properties": {
    "addr:full":"P Karel Drossaartstr 54 Vlaardingen Zuid-Holland 3131 PE",
    "addr:housenumber":"54",
    "addr:postcode":"3131 pe",
    "addr:street":"Karel Drossaartstr",
    "iso:country":"NL",
    "sg:address":"P Karel Drossaartstr 54",
    "sg:city":"Vlaardingen",
    "sg:classifiers":[
        {
            "category":"Food & Beverages",
            "subcategory":"Fruits & Vegetables",
            "type":"Retail Goods"
        }
    ],
    "sg:phone":"+31 10 434 3718",
    "sg:postcode":"3131 PE",
    "sg:province":"Zuid-Holland",
    "sg:tags":[
        "groenten"
    ],
    "wof:name":"J. Van Soest Agf",
    "wof:placetype":"venue"
},
  "geometry": {"coordinates":[4.340483,51.906189],"type":"Point"}
}