{
  "type": "Feature",
  "properties": {
    "addr:full":"Kromstr 40 Valkenswaard Noord-Brabant 5554 NH",
    "addr:housenumber":"40",
    "addr:postcode":"5554 nh",
    "addr:street":"Kromstr",
    "iso:country":"NL",
    "sg:address":"Kromstr 40",
    "sg:city":"Valkenswaard",
    "sg:orig_category":"Organisatiebureaus",
    "sg:phone":"+31 40 204 4991",
    "sg:postcode":"5554 NH",
    "sg:province":"Noord-Brabant",
    "wof:name":"Aparties",
    "wof:placetype":"venue"
},
  "geometry": {"coordinates":[5.4507808685,51.3480453491],"type":"Point"}
}