{
  "type": "Feature",
  "properties": {
    "addr:full":"Forellenweg 20 Raamsdonksveer Noord-Brabant 4941 SJ",
    "addr:housenumber":"20",
    "addr:postcode":"4941",
    "addr:street":"Forellenweg",
    "iso:country":"NL",
    "sg:address":"Forellenweg 20",
    "sg:city":"Raamsdonksveer",
    "sg:orig_category":"Levende Dieren Gh",
    "sg:phone":"+31 162 522 666",
    "sg:postcode":"4941 SJ",
    "sg:province":"Noord-Brabant",
    "wof:name":"Schelle Trading Bv",
    "wof:placetype":"venue"
},
  "geometry": {"coordinates":[4.87447,51.715897],"type":"Point"}
}