{
  "type": "Feature",
  "properties": {
    "addr:full":"Tielsestr 112 Herveld Gelderland 6674 AC",
    "addr:housenumber":"112",
    "addr:postcode":"6674 ac",
    "addr:street":"Gelderland",
    "iso:country":"NL",
    "sg:address":"Tielsestr 112",
    "sg:city":"Herveld",
    "sg:orig_category":"Adviesbureaus Bedrijfsorganisatie",
    "sg:phone":"+31 488 454 340",
    "sg:postcode":"6674 AC",
    "sg:province":"Gelderland",
    "wof:name":"Cramer",
    "wof:placetype":"venue"
},
  "geometry": {"coordinates":[5.768575,51.899948],"type":"Point"}
}