{
  "type": "Feature",
  "properties": {
    "addr:full":"Oosterhamrikkade 82 Groningen Groningen 9714 BH",
    "addr:housenumber":"82",
    "addr:postcode":"9714 bh",
    "addr:street":"Oosterhamrikkade",
    "iso:country":"NL",
    "sg:address":"Oosterhamrikkade 82",
    "sg:city":"Groningen",
    "sg:orig_category":"Drukkerijen And Copyshops",
    "sg:phone":"+31 50 577 2605",
    "sg:postcode":"9714 BH",
    "sg:province":"Groningen",
    "wof:name":"Drukkerij Van Denderen Bv",
    "wof:placetype":"venue"
},
  "geometry": {"coordinates":[6.5768,53.230419],"type":"Point"}
}