{
  "type": "Feature",
  "properties": {
    "iso:country":"NL",
    "sg:address":"J V Galenstr 168",
    "sg:city":"Amsterdam",
    "sg:orig_category":"Kappers",
    "sg:phone":"+31 20 489 8465",
    "sg:postcode":"1056 CJ",
    "sg:province":"Noord-Holland",
    "wof:name":"Sedat",
    "wof:placetype":"venue"
},
  "geometry": {"coordinates":[4.85478,52.373699],"type":"Point"}
}