{
  "type": "Feature",
  "properties": {
    "addr:full":"Stompwijkseweg 9 Zoeterwoude Zuid-Holland 2381 BH",
    "addr:housenumber":"9",
    "addr:postcode":"2381 bh",
    "addr:street":"Stompwijkseweg",
    "iso:country":"NL",
    "sg:address":"Stompwijkseweg 9",
    "sg:city":"Zoeterwoude",
    "sg:orig_category":"Verzekeringen",
    "sg:phone":"+31 71 580 1445",
    "sg:postcode":"2381 BH",
    "sg:province":"Zuid-Holland",
    "wof:name":"C.W.Th. Schuur Verzekeringen",
    "wof:placetype":"venue"
},
  "geometry": {"coordinates":[4.496476,52.115299],"type":"Point"}
}