{
  "type": "Feature",
  "properties": {
    "addr:full":"Rucphensebaan 46 Roosendaal Noord-Brabant 4706 PJ",
    "addr:housenumber":"46",
    "addr:postcode":"4706 pj",
    "addr:street":"Rucphensebaan",
    "iso:country":"NL",
    "sg:address":"Rucphensebaan 46",
    "sg:city":"Roosendaal",
    "sg:orig_category":"Grafmonumenten",
    "sg:phone":"+31 165 521 742",
    "sg:postcode":"4706 PJ",
    "sg:province":"Noord-Brabant",
    "wof:name":"Kort Gedenkstenen, De",
    "wof:placetype":"venue"
},
  "geometry": {"coordinates":[4.493782,51.535633],"type":"Point"}
}