{
  "type": "Feature",
  "properties": {
    "addr:full":"Gedempte Gracht 40 'S Gravenhage Zuid-Holland 2512 AM",
    "addr:housenumber":"40",
    "addr:postcode":"2512",
    "addr:street":"Gedempte Gracht;' S",
    "iso:country":"NL",
    "sg:address":"Gedempte Gracht 40",
    "sg:city":"'S Gravenhage",
    "sg:orig_category":"Drogisterijen",
    "sg:phone":"+31 70 363 3222",
    "sg:postcode":"2512 AM",
    "sg:province":"Zuid-Holland",
    "wof:name":"Drogisterij De Gede",
    "wof:placetype":"venue"
},
  "geometry": {"coordinates":[4.314246,52.076595],"type":"Point"}
}