{
  "type": "Feature",
  "properties": {
    "addr:full":"Gijsbrecht Van Amstelstraat 225 Hilversum North Holland 1214 BA",
    "addr:housenumber":"225",
    "addr:postcode":"1214 ba",
    "addr:street":"Gijsbrecht Van Amstelstraat",
    "iso:country":"NL",
    "sg:address":"Gijsbrecht Van Amstelstraat 225",
    "sg:city":"Hilversum",
    "sg:classifiers":[
        {
            "category":"Communications",
            "subcategory":"Television Station",
            "type":"Services"
        }
    ],
    "sg:phone":"+31 35 624 5878",
    "sg:postcode":"1214 BA",
    "sg:province":"North Holland",
    "sg:tags":[
        "video",
        "audio",
        "verhuur"
    ],
    "wof:name":"Filmclub Videotheek Hilversum",
    "wof:placetype":"venue"
},
  "geometry": {"coordinates":[5.165889,52.215168],"type":"Point"}
}