{
  "type": "Feature",
  "properties": {
    "addr:full":"Hoofdweg 116A Veenhuizen Provincie Drenthe 9341 BK",
    "addr:housenumber":"116a",
    "addr:postcode":"9341 bk",
    "addr:street":"Hoofdweg;Provincie Drenthe",
    "iso:country":"NL",
    "sg:address":"Hoofdweg 116A",
    "sg:city":"Veenhuizen",
    "sg:orig_category":"Overheidsdiensten",
    "sg:phone":"+31 592 388 412",
    "sg:postcode":"9341 BK",
    "sg:province":"Provincie Drenthe",
    "wof:name":"Vier Paal",
    "wof:placetype":"venue"
},
  "geometry": {"coordinates":[6.3927960396,53.0310401917],"type":"Point"}
}