{
  "type": "Feature",
  "properties": {
    "addr:full":"H B Blydensteinln 20 Enschede Overijssel 7514 CB",
    "addr:housenumber":"20",
    "addr:postcode":"7514 cb",
    "iso:country":"NL",
    "sg:address":"H B Blydensteinln 20",
    "sg:city":"Enschede",
    "sg:orig_category":"Kappers",
    "sg:phone":"+31 53 435 4801",
    "sg:postcode":"7514 CB",
    "sg:province":"Overijssel",
    "wof:name":"Fiabesco, Salon",
    "wof:placetype":"venue"
},
  "geometry": {"coordinates":[6.8953738213,52.223575592],"type":"Point"}
}