{
  "type": "Feature",
  "properties": {
    "iso:country":"NL",
    "sg:address":"Julianastraat 7",
    "sg:city":"Tegelen",
    "sg:orig_category":"Goederenvervoer Over De Weg",
    "sg:phone":"+31 77 373 3995",
    "sg:postcode":"5932 EH",
    "sg:province":"Limburg",
    "wof:name":"Cremers Transport Tegelen Bv",
    "wof:placetype":"venue"
},
  "geometry": {"coordinates":[6.152385,51.341526],"type":"Point"}
}