{
  "type": "Feature",
  "properties": {
    "addr:full":"Dorpsstr 89 Castricum North Holland 1901 EK",
    "addr:housenumber":"89",
    "addr:postcode":"1901 ek",
    "addr:street":"Dorpsstr",
    "iso:country":"NL",
    "sg:address":"Dorpsstr 89",
    "sg:city":"Castricum",
    "sg:orig_category":"Fotoreportages",
    "sg:phone":"+31 251 659 126",
    "sg:postcode":"1901 EK",
    "sg:province":"North Holland",
    "wof:name":"Beeldwinkel, De",
    "wof:placetype":"venue"
},
  "geometry": {"coordinates":[4.666933,52.547428],"type":"Point"}
}