{
  "type": "Feature",
  "properties": {
    "iso:country":"NL",
    "sg:address":"Fort 18",
    "sg:city":"Veeningen",
    "sg:orig_category":"Kappers",
    "sg:phone":"+31 528 391 735",
    "sg:postcode":"7924 RB",
    "sg:province":"Drenthe",
    "wof:name":"Karin'S Knipperij",
    "wof:placetype":"venue"
},
  "geometry": {"coordinates":[6.3760437965,52.6566352844],"type":"Point"}
}