{
  "type": "Feature",
  "properties": {
    "addr:full":"Paalwg 18 Urmond Limburg 6129 EZ",
    "addr:housenumber":"18",
    "addr:postcode":"6129 ez",
    "addr:street":"Paalwg",
    "iso:country":"NL",
    "sg:address":"Paalwg 18",
    "sg:city":"Urmond",
    "sg:classifiers":[
        {
            "category":"Retail",
            "subcategory":"Auto Repair",
            "type":"Services"
        }
    ],
    "sg:phone":"+31 46 426 1995",
    "sg:postcode":"6129 EZ",
    "sg:province":"Limburg",
    "sg:tags":[
        "garage"
    ],
    "wof:name":"Urmond, Vakgarage",
    "wof:placetype":"venue"
},
  "geometry": {"coordinates":[5.769295,50.989803],"type":"Point"}
}