{
  "type": "Feature",
  "properties": {
    "iso:country":"NL",
    "sg:address":"Veldstr 7",
    "sg:city":"Nymegen",
    "sg:orig_category":"Meubelmakerijen",
    "sg:phone":"+31 24 388 2363",
    "sg:postcode":"6533 CA",
    "sg:province":"Gelderland",
    "sg:website":"http://www.renelansink.nl",
    "wof:name":"Lansink, Ren\u00e9",
    "wof:placetype":"venue"
},
  "geometry": {"coordinates":[-119.270203,37.271832],"type":"Point"}
}