{
  "type": "Feature",
  "properties": {
    "addr:full":"Backer En Ruebweg 30 Breda North Brabant 4825 AA",
    "addr:housenumber":"30",
    "addr:postcode":"4825 aa",
    "addr:street":"Backer En Ruebweg",
    "iso:country":"NL",
    "sg:address":"Backer En Ruebweg 30",
    "sg:city":"Breda",
    "sg:orig_category":"Goederenvervoer Over De Weg",
    "sg:phone":"+31 76 543 1431",
    "sg:postcode":"4825 AA",
    "sg:province":"North Brabant",
    "wof:name":"Holleman Transportbedrijf Bv",
    "wof:placetype":"venue"
},
  "geometry": {"coordinates":[4.754606,51.600704],"type":"Point"}
}