{
  "type": "Feature",
  "properties": {
    "addr:full":"Berkstraat 16 Oldenzaal Overijssel 7572 CB",
    "addr:housenumber":"16",
    "addr:postcode":"7572 cb",
    "addr:street":"Berkstraat",
    "iso:country":"NL",
    "sg:address":"Berkstraat 16",
    "sg:city":"Oldenzaal",
    "sg:classifiers":[
        {
            "category":"Bakery",
            "type":"Food & Drink"
        }
    ],
    "sg:phone":"+31 541 518 236",
    "sg:postcode":"7572 CB",
    "sg:province":"Overijssel",
    "sg:tags":[
        "brood",
        "banket"
    ],
    "wof:name":"J.G. Olde Keizer",
    "wof:placetype":"venue"
},
  "geometry": {"coordinates":[6.925,52.308899],"type":"Point"}
}