{
  "type": "Feature",
  "properties": {
    "iso:country":"NL",
    "sg:address":"Margauxlaan 1",
    "sg:city":"Maastricht",
    "sg:orig_category":"Boekhouders",
    "sg:phone":"+31 43 347 6745",
    "sg:postcode":"6213 EZ",
    "sg:province":"Limburg",
    "wof:name":"Kohler & V. Elstlande",
    "wof:placetype":"venue"
},
  "geometry": {"coordinates":[5.664632,50.839062],"type":"Point"}
}