{
  "type": "Feature",
  "properties": {
    "addr:full":"Boekweitstr 20A Rotterdam Zuid-Holland 3073 DB",
    "addr:housenumber":"20a",
    "addr:postcode":"3073 db",
    "addr:street":"Boekweitstr",
    "iso:country":"NL",
    "sg:address":"Boekweitstr 20A",
    "sg:city":"Rotterdam",
    "sg:orig_category":"Belastingconsulenten/ Belastingadviseurs",
    "sg:phone":"+31 10 483 7511",
    "sg:postcode":"3073 DB",
    "sg:province":"Zuid-Holland",
    "sg:website":"http://www.patronu.nl",
    "wof:name":"Patronus",
    "wof:placetype":"venue"
},
  "geometry": {"coordinates":[4.499079,51.890488],"type":"Point"}
}