{
  "type": "Feature",
  "properties": {
    "iso:country":"NL",
    "sg:address":"Zutphensewg 73",
    "sg:city":"Eefde",
    "sg:orig_category":"Kampeerauto'S",
    "sg:phone":"+31 575 540 317",
    "sg:postcode":"7211 EB",
    "sg:province":"Gelderland",
    "sg:website":"http://www.camperverhuureefde.nl",
    "wof:name":"Auto Service Eefde",
    "wof:placetype":"venue"
},
  "geometry": {"coordinates":[6.2223410606,52.1752204895],"type":"Point"}
}