{
  "type": "Feature",
  "properties": {
    "iso:country":"NL",
    "sg:address":"Kraanvogelstraat 40",
    "sg:city":"Venlo",
    "sg:orig_category":"Fitnesscentra",
    "sg:phone":"+31 77 354 5544",
    "sg:postcode":"5912 XR",
    "sg:province":"Limburg",
    "wof:name":"Sport En Fitness Instituut Dale Tan",
    "wof:placetype":"venue"
},
  "geometry": {"coordinates":[6.159952,51.357925],"type":"Point"}
}