{
  "type": "Feature",
  "properties": {
    "addr:full":"Postbus 2271 Eindhoven Zuid-Holland 5600 CG",
    "addr:housenumber":"2271",
    "addr:postcode":"5600 cg",
    "addr:street":"Postbus",
    "iso:country":"NL",
    "sg:address":"Postbus 2271",
    "sg:city":"Eindhoven",
    "sg:orig_category":"Luchtvaart- Maatschappijen",
    "sg:phone":"+31 40 262 4009",
    "sg:postcode":"5600 CG",
    "sg:province":"Zuid-Holland",
    "sg:website":"http://www.globalaviation.nl",
    "wof:name":"Global Aviation Support",
    "wof:placetype":"venue"
},
  "geometry": {"coordinates":[5.48411,51.434471],"type":"Point"}
}