{
  "type": "Feature",
  "properties": {
    "addr:full":"Wagenaarstr 3 Oosterhout Nb North Brabant 4904 MT",
    "addr:housenumber":"3;nb",
    "addr:postcode":"4904",
    "addr:street":"Wagenaarstr;Mt",
    "iso:country":"NL",
    "sg:address":"Wagenaarstr 3",
    "sg:city":"Oosterhout Nb",
    "sg:orig_category":"Verzekeringen - Verzekeringskantoren",
    "sg:phone":"+31 162 455 815",
    "sg:postcode":"4904 MT",
    "sg:province":"North Brabant",
    "wof:name":"Dijk, G B M Van",
    "wof:placetype":"venue"
},
  "geometry": {"coordinates":[4.851346,51.627106],"type":"Point"}
}