{
  "type": "Feature",
  "properties": {
    "addr:full":"Burg Kehrerstr 58 Doetinchem Gelderland 7002 LD",
    "addr:housenumber":"58",
    "addr:postcode":"7002 ld",
    "addr:street":"Burg;Gelderland",
    "iso:country":"NL",
    "sg:address":"Burg Kehrerstr 58",
    "sg:city":"Doetinchem",
    "sg:orig_category":"Adviesbureaus Bedrijfsorganisatie",
    "sg:phone":"+31 314 364 119",
    "sg:postcode":"7002 LD",
    "sg:province":"Gelderland",
    "sg:website":"http://www.novumadviesentraining.nl",
    "wof:name":"Novum",
    "wof:placetype":"venue"
},
  "geometry": {"coordinates":[6.312964,51.968483],"type":"Point"}
}