{
  "type": "Feature",
  "properties": {
    "addr:full":"Haarlemmerdk 8 Amsterdam North Holland 1013 JC",
    "addr:housenumber":"8",
    "addr:postcode":"1013 jc",
    "addr:street":"Haarlemmerdk",
    "iso:country":"NL",
    "sg:address":"Haarlemmerdk 8",
    "sg:city":"Amsterdam",
    "sg:orig_category":"Onderwijsmateriaal",
    "sg:phone":"+31 6 20886616",
    "sg:postcode":"1013 JC",
    "sg:province":"North Holland",
    "sg:website":"http://www.ontdeknet.nl",
    "wof:name":"Ontdeknet",
    "wof:placetype":"venue"
},
  "geometry": {"coordinates":[4.889082,52.381809],"type":"Point"}
}