{
  "type": "Feature",
  "properties": {
    "addr:full":"Schoolwg 2 Elst Ut Utrecht 3921 CE",
    "addr:housenumber":"2",
    "addr:postcode":"ut;3921 ce",
    "addr:street":"Schoolwg",
    "iso:country":"NL",
    "sg:address":"Schoolwg 2",
    "sg:city":"Elst Ut",
    "sg:classifiers":[
        {
            "category":"Food & Beverages",
            "subcategory":"Bakery",
            "type":"Retail Goods"
        }
    ],
    "sg:phone":"+31 318 472 384",
    "sg:postcode":"3921 CE",
    "sg:province":"Utrecht",
    "sg:tags":[
        "brood",
        "en",
        "banket"
    ],
    "wof:name":"Burger, A",
    "wof:placetype":"venue"
},
  "geometry": {"coordinates":[5.495927,51.985264],"type":"Point"}
}