{
  "type": "Feature",
  "properties": {
    "addr:full":"Marderleane 9A Rijs Friesland 8572 WG",
    "addr:housenumber":"9a",
    "addr:postcode":"8572 wg",
    "addr:street":"Marderleane",
    "iso:country":"NL",
    "sg:address":"Marderleane 9A",
    "sg:city":"Rijs",
    "sg:orig_category":"Kampeerterreinen",
    "sg:phone":"+31 514 581 563",
    "sg:postcode":"8572 WG",
    "sg:province":"Friesland",
    "wof:name":"Camping Op De Hoek",
    "wof:placetype":"venue"
},
  "geometry": {"coordinates":[5.4992818832,52.8627586365],"type":"Point"}
}