{
  "type": "Feature",
  "properties": {
    "iso:country":"NL",
    "sg:address":"Holevoetln 1",
    "sg:city":"Scherpenzeel Gld",
    "sg:orig_category":"Antiquiteiten",
    "sg:phone":"+31 33 277 1998",
    "sg:postcode":"3925 BX",
    "sg:province":"Utrecht",
    "wof:name":"Keulen Antiquair, Van",
    "wof:placetype":"venue"
},
  "geometry": {"coordinates":[5.481806,52.077377],"type":"Point"}
}