{
  "type": "Feature",
  "properties": {
    "iso:country":"NL",
    "sg:address":"Keizer Karelweg 335",
    "sg:city":"Amstelveen",
    "sg:orig_category":"Opticiens",
    "sg:phone":"+31 20 641 0794",
    "sg:postcode":"1181 RD",
    "sg:province":"North Holland",
    "sg:website":"http://www.optilens.nl",
    "wof:name":"Opticiens Contactlenzen",
    "wof:placetype":"venue"
},
  "geometry": {"coordinates":[4.8561911583,52.3071098328],"type":"Point"}
}