{
  "type": "Feature",
  "properties": {
    "iso:country":"NL",
    "sg:address":"Ribesstraat 5",
    "sg:city":"Groningen",
    "sg:orig_category":"Bloemen And Planten",
    "sg:phone":"+31 50 577 3764",
    "sg:postcode":"9741 NH",
    "sg:province":"Groningen",
    "wof:name":"Vof Handelsonderneming Fiori",
    "wof:placetype":"venue"
},
  "geometry": {"coordinates":[6.54783,53.234585],"type":"Point"}
}