{
  "type": "Feature",
  "properties": {
    "addr:full":"Dr Thorbeckeln 99 Heemstede Noord-Holland 2104 XJ",
    "addr:housenumber":"99",
    "addr:postcode":"2104 xj",
    "iso:country":"NL",
    "sg:address":"Dr Thorbeckeln 99",
    "sg:city":"Heemstede",
    "sg:orig_category":"Adviesbureaus Bedrijfsorganisatie",
    "sg:phone":"+31 23 529 8770",
    "sg:postcode":"2104 XJ",
    "sg:province":"Noord-Holland",
    "wof:name":"Breetveld, O",
    "wof:placetype":"venue"
},
  "geometry": {"coordinates":[4.611689,52.332153],"type":"Point"}
}