{
  "type": "Feature",
  "properties": {
    "iso:country":"NL",
    "sg:address":"Schoenerweg 33",
    "sg:city":"Maastricht",
    "sg:orig_category":"Aannemers Woningbouw",
    "sg:phone":"+31 43 363 3232",
    "sg:postcode":"6222 NX",
    "sg:province":"Limburg",
    "wof:name":"Bouwbedrijf I.J. Lemmens Bv",
    "wof:placetype":"venue"
},
  "geometry": {"coordinates":[5.720366,50.876389],"type":"Point"}
}