{
  "type": "Feature",
  "properties": {
    "addr:full":"De Rede 50 Dronten NL. 8251 EW",
    "addr:housenumber":"50",
    "addr:postcode":"8251 ew",
    "addr:street":"De Rede;Nl.",
    "iso:country":"NL",
    "sg:address":"De Rede 50",
    "sg:city":"Dronten",
    "sg:orig_category":"Zalenverhuur",
    "sg:phone":"+31 321 338 887",
    "sg:postcode":"8251 EW",
    "sg:province":"NL.",
    "sg:website":"http://www.hotelhetgaljoen.nl",
    "wof:name":"Galjoen, Hotel Het",
    "wof:placetype":"venue"
},
  "geometry": {"coordinates":[5.723704,52.523144],"type":"Point"}
}