{
  "type": "Feature",
  "properties": {
    "addr:full":"Eerste Van Swindenstraat 34 Amsterdam North Holland 1093 GE",
    "addr:housenumber":"34",
    "addr:postcode":"1093",
    "addr:street":"Eerste Van Swindenstraat",
    "iso:country":"NL",
    "sg:address":"Eerste Van Swindenstraat 34",
    "sg:city":"Amsterdam",
    "sg:orig_category":"Babyartikelen Detailhandel",
    "sg:phone":"+31 20 694 1962",
    "sg:postcode":"1093 GE",
    "sg:province":"North Holland",
    "wof:name":"Kinderwagenhuis Anelja",
    "wof:placetype":"venue"
},
  "geometry": {"coordinates":[4.92577,52.362152],"type":"Point"}
}