{
  "type": "Feature",
  "properties": {
    "addr:full":"Botterstr 30 Lisse Zuid-Holland 2162 LA",
    "addr:housenumber":"30",
    "addr:postcode":"2162 la",
    "addr:street":"Botterstr",
    "iso:country":"NL",
    "sg:address":"Botterstr 30",
    "sg:city":"Lisse",
    "sg:orig_category":"Administratie- En Boekhoudkantoren",
    "sg:phone":"+31 252 420 811",
    "sg:postcode":"2162 LA",
    "sg:province":"Zuid-Holland",
    "wof:name":"Meer, Van Der",
    "wof:placetype":"venue"
},
  "geometry": {"coordinates":[4.561607,52.242939],"type":"Point"}
}