{
  "type": "Feature",
  "properties": {
    "addr:full":"Roostenlaan 140 Eindhoven Noord-Brabant 5644 GJ",
    "addr:housenumber":"140",
    "addr:postcode":"5644 gj",
    "addr:street":"Roostenlaan",
    "iso:country":"NL",
    "sg:address":"Roostenlaan 140",
    "sg:city":"Eindhoven",
    "sg:orig_category":"Discountwinkels",
    "sg:phone":"+31 40 211 7947",
    "sg:postcode":"5644 GJ",
    "sg:province":"Noord-Brabant",
    "wof:name":"Vetex Textielhandel",
    "wof:placetype":"venue"
},
  "geometry": {"coordinates":[5.491792,51.419006],"type":"Point"}
}