{
  "type": "Feature",
  "properties": {
    "addr:full":"Breehoven 117 Bennekom Gelderland 6721 SE",
    "addr:housenumber":"117",
    "addr:postcode":"6721",
    "addr:street":"Breehoven;Gelderland;Se",
    "iso:country":"NL",
    "sg:address":"Breehoven 117",
    "sg:city":"Bennekom",
    "sg:orig_category":"Chemische Producten Gh",
    "sg:phone":"+31 318 414 588",
    "sg:postcode":"6721 SE",
    "sg:province":"Gelderland",
    "wof:name":"L Eshuis-Petter",
    "wof:placetype":"venue"
},
  "geometry": {"coordinates":[5.675925,51.995171],"type":"Point"}
}