{
  "type": "Feature",
  "properties": {
    "iso:country":"NL",
    "sg:address":"Vogelwikke 16",
    "sg:city":"Zevenhoven",
    "sg:orig_category":"Adviesbureaus Bouwkunde",
    "sg:phone":"+31 172 537 788",
    "sg:postcode":"2435 WH",
    "sg:province":"South Holland",
    "wof:name":"Ttav",
    "wof:placetype":"venue"
},
  "geometry": {"coordinates":[4.77559,52.184261],"type":"Point"}
}