{
  "type": "Feature",
  "properties": {
    "addr:full":"Nieuwstr 151-153 Almelo NL.08 7605 AD",
    "addr:housenumber":"151-153;nl.08",
    "addr:postcode":"7605 ad",
    "iso:country":"NL",
    "sg:address":"Nieuwstr 151-153",
    "sg:city":"Almelo",
    "sg:orig_category":"Fietsen En Bromfietsen",
    "sg:phone":"+31 546 812 729",
    "sg:postcode":"7605 AD",
    "sg:province":"NL.08",
    "wof:name":"Wild",
    "wof:placetype":"venue"
},
  "geometry": {"coordinates":[6.664543,52.354954],"type":"Point"}
}