{
  "type": "Feature",
  "properties": {
    "addr:full":"Contactweg 47 Amsterdam North Holland 1014 AN",
    "addr:housenumber":"47",
    "addr:postcode":"1014 an",
    "addr:street":"Contactweg",
    "iso:country":"NL",
    "sg:address":"Contactweg 47",
    "sg:city":"Amsterdam",
    "sg:orig_category":"Autoverhuur",
    "sg:phone":"+31 20 486 7333",
    "sg:postcode":"1014 AN",
    "sg:province":"North Holland",
    "sg:website":"http://www.budget.nl",
    "wof:name":"Budget Rent A Car",
    "wof:placetype":"venue"
},
  "geometry": {"coordinates":[4.8548,52.393982],"type":"Point"}
}