{
  "type": "Feature",
  "properties": {
    "iso:country":"NL",
    "sg:address":"Tweelingenlaan 14",
    "sg:city":"Eindhoven",
    "sg:orig_category":"Marktonderzoekbureaus",
    "sg:phone":"+31 40 246 6233",
    "sg:postcode":"5632 AX",
    "sg:province":"North Brabant",
    "wof:name":"Market Results Consultancy Bv",
    "wof:placetype":"venue"
},
  "geometry": {"coordinates":[5.497485,51.467628],"type":"Point"}
}