{
  "type": "Feature",
  "properties": {
    "addr:full":"Lomanstr 4 Amsterdam Noord-Holland 1075 RA",
    "addr:housenumber":"4",
    "addr:postcode":"1075 ra",
    "addr:street":"Lomanstr",
    "iso:country":"NL",
    "sg:address":"Lomanstr 4",
    "sg:city":"Amsterdam",
    "sg:orig_category":"Mensendieck - Oefentherapeuten",
    "sg:phone":"+31 20 679 0928",
    "sg:postcode":"1075 RA",
    "sg:province":"Noord-Holland",
    "wof:name":"Goll-Raymakers & Wiersma-Raymakers",
    "wof:placetype":"venue"
},
  "geometry": {"coordinates":[4.862138,52.35199],"type":"Point"}
}