{
  "type": "Feature",
  "properties": {
    "iso:country":"NL",
    "sg:address":"Raadhuispln 68-70",
    "sg:city":"Rozenburg Zh",
    "sg:classifiers":[
        {
            "category":"Food & Beverages",
            "subcategory":"Bakery",
            "type":"Retail Goods"
        }
    ],
    "sg:phone":"+31 181 217 205",
    "sg:postcode":"3181 CG",
    "sg:province":"Zuid-Holland",
    "sg:tags":[
        "brood",
        "en",
        "banket"
    ],
    "wof:name":"Breggen, Van Der",
    "wof:placetype":"venue"
},
  "geometry": {"coordinates":[4.24976,51.90591],"type":"Point"}
}