{
  "type": "Feature",
  "properties": {
    "addr:full":"Statenwg 107 Emmen Drenthe 7824 CW",
    "addr:housenumber":"107",
    "addr:postcode":"7824 cw",
    "iso:country":"NL",
    "sg:address":"Statenwg 107",
    "sg:city":"Emmen",
    "sg:orig_category":"Adviesbureaus Beroeps- En Schoolkeuze",
    "sg:phone":"+31 591 623 193",
    "sg:postcode":"7824 CW",
    "sg:province":"Drenthe",
    "sg:website":"http://www.studieadviesbureau-emmen.nl",
    "wof:name":"Studieadviesbureau Emmen",
    "wof:placetype":"venue"
},
  "geometry": {"coordinates":[6.923431,52.779667],"type":"Point"}
}