{
  "type": "Feature",
  "properties": {
    "addr:full":"Tinnegieterwei 19 Valkenswaard North Brabant 5551 SL",
    "addr:housenumber":"19",
    "addr:postcode":"5551 sl",
    "addr:street":"Tinnegieterwei",
    "iso:country":"NL",
    "sg:address":"Tinnegieterwei 19",
    "sg:city":"Valkenswaard",
    "sg:orig_category":"Verhuur Audiovisuele Apparatuur",
    "sg:phone":"+31 40 204 1791",
    "sg:postcode":"5551 SL",
    "sg:province":"North Brabant",
    "wof:name":"Soors Muziek",
    "wof:placetype":"venue"
},
  "geometry": {"coordinates":[5.435145,51.361336],"type":"Point"}
}