{
  "type": "Feature",
  "properties": {
    "iso:country":"NL",
    "sg:address":"Kilstr 31",
    "sg:city":"Maasdam",
    "sg:orig_category":"Postkantoren",
    "sg:phone":"+31 78 676 1221",
    "sg:postcode":"3299 XA",
    "sg:province":"Zuid-Holland",
    "sg:website":"http://www.postkantoor.nl",
    "wof:name":"Postkantoor",
    "wof:placetype":"venue"
},
  "geometry": {"coordinates":[4.553817,51.789761],"type":"Point"}
}