{
  "type": "Feature",
  "properties": {
    "addr:full":"Kinkerstr 43 Amsterdam Noord-Holland 1053 DD",
    "addr:housenumber":"43",
    "addr:postcode":"1053 dd",
    "addr:street":"Kinkerstr",
    "iso:country":"NL",
    "sg:address":"Kinkerstr 43",
    "sg:city":"Amsterdam",
    "sg:orig_category":"Bloemen En Planten",
    "sg:phone":"+31 20 612 5275",
    "sg:postcode":"1053 DD",
    "sg:province":"Noord-Holland",
    "wof:name":"Sandy",
    "wof:placetype":"venue"
},
  "geometry": {"coordinates":[4.874259,52.367676],"type":"Point"}
}