{
  "type": "Feature",
  "properties": {
    "iso:country":"NL",
    "sg:address":"Brederodestr 91",
    "sg:city":"Zandvoort",
    "sg:orig_category":"Marketingbureaus",
    "sg:phone":"+31 23 573 0503",
    "sg:postcode":"2042 BC",
    "sg:province":"Noord-Holland",
    "wof:name":"Vermeij, T",
    "wof:placetype":"venue"
},
  "geometry": {"coordinates":[4.524701,52.368137],"type":"Point"}
}