{
  "type": "Feature",
  "properties": {
    "addr:full":"Thierenswg 3 Naarden North Holland 1411 EW",
    "addr:housenumber":"3",
    "addr:postcode":"1411 ew",
    "addr:street":"Thierenswg",
    "iso:country":"NL",
    "sg:address":"Thierenswg 3",
    "sg:city":"Naarden",
    "sg:orig_category":"Organisatiebureaus",
    "sg:phone":"+31 35 694 5858",
    "sg:postcode":"1411 EW",
    "sg:province":"North Holland",
    "wof:name":"Boomsma, S",
    "wof:placetype":"venue"
},
  "geometry": {"coordinates":[5.1597270966,52.2896461487],"type":"Point"}
}