{
  "type": "Feature",
  "properties": {
    "addr:full":"W Witsenstr 14 Amsterdam Noord-Holland 1077 AZ",
    "addr:housenumber":"14",
    "addr:postcode":"1077 az",
    "addr:street":"W",
    "iso:country":"NL",
    "sg:address":"W Witsenstr 14",
    "sg:city":"Amsterdam",
    "sg:orig_category":"Scholen Voor Basisonderwijs",
    "sg:phone":"+31 20 305 7878",
    "sg:postcode":"1077 AZ",
    "sg:province":"Noord-Holland",
    "wof:name":"Amsterdamse Montessori, De",
    "wof:placetype":"venue"
},
  "geometry": {"coordinates":[4.87049,52.350914],"type":"Point"}
}