{
  "type": "Feature",
  "properties": {
    "addr:full":"Eikenwede 17 Barendrecht Zuid-Holland 2993 GH",
    "addr:housenumber":"17",
    "addr:postcode":"2993 gh",
    "addr:street":"Eikenwede",
    "iso:country":"NL",
    "sg:address":"Eikenwede 17",
    "sg:city":"Barendrecht",
    "sg:orig_category":"Onderhoudswerken",
    "sg:phone":"+31 180 611 240",
    "sg:postcode":"2993 GH",
    "sg:province":"Zuid-Holland",
    "wof:name":"Mechrout, A",
    "wof:placetype":"venue"
},
  "geometry": {"coordinates":[4.504719,51.854889],"type":"Point"}
}