{
  "type": "Feature",
  "properties": {
    "addr:full":"Weissenbruchstr 6 Arnhem Gelderland 6813 KK",
    "addr:housenumber":"6",
    "addr:postcode":"6813 kk",
    "addr:street":"Weissenbruchstr",
    "iso:country":"NL",
    "sg:address":"Weissenbruchstr 6",
    "sg:city":"Arnhem",
    "sg:orig_category":"Psychologen",
    "sg:phone":"+31 26 445 8665",
    "sg:postcode":"6813 KK",
    "sg:province":"Gelderland",
    "wof:name":"Sterrenberg, De",
    "wof:placetype":"venue"
},
  "geometry": {"coordinates":[5.884392,51.993752],"type":"Point"}
}