{
  "type": "Feature",
  "properties": {
    "addr:full":"A Fokkerwg 1 Amsterdam Noord-Holland 1059 CM",
    "addr:housenumber":"1",
    "addr:postcode":"1059 cm",
    "iso:country":"NL",
    "sg:address":"A Fokkerwg 1",
    "sg:city":"Amsterdam",
    "sg:orig_category":"Kantoor- En Secretariaatsservice",
    "sg:phone":"+31 20 518 6799",
    "sg:postcode":"1059 CM",
    "sg:province":"Noord-Holland",
    "wof:name":"Tact",
    "wof:placetype":"venue"
},
  "geometry": {"coordinates":[4.8461828232,52.3451271057],"type":"Point"}
}