{
  "type": "Feature",
  "properties": {
    "iso:country":"NL",
    "sg:address":"Brugstraat 23A",
    "sg:city":"Roermond",
    "sg:orig_category":"Zuivelproducten",
    "sg:phone":"+31 475 315 660",
    "sg:postcode":"6041 EP",
    "sg:province":"Limburg",
    "wof:name":"L.A.N.E. Nizet",
    "wof:placetype":"venue"
},
  "geometry": {"coordinates":[5.984182,51.194458],"type":"Point"}
}