{
  "type": "Feature",
  "properties": {
    "addr:full":"Feiko Clockstraat 183 Oude Pekela Groningen 9665 BK",
    "addr:housenumber":"183",
    "addr:postcode":"pekela;9665 bk",
    "addr:street":"Feiko Clockstraat",
    "iso:country":"NL",
    "sg:address":"Feiko Clockstraat 183",
    "sg:city":"Oude Pekela",
    "sg:classifiers":[
        {
            "category":"Fast Food",
            "type":"Food & Drink"
        }
    ],
    "sg:phone":"+31 597 618 491",
    "sg:postcode":"9665 BK",
    "sg:province":"Groningen",
    "sg:tags":[
        "afhaal",
        "restaurant"
    ],
    "wof:name":"Ijs- En Frituurzaak H. Gerringa",
    "wof:placetype":"venue"
},
  "geometry": {"coordinates":[7.001848,53.100677],"type":"Point"}
}