{
  "type": "Feature",
  "properties": {
    "addr:full":"Ramgatsewg 34 Raamsdonksveer Noord-Brabant 4941 VS",
    "addr:housenumber":"34",
    "addr:postcode":"4941 vs",
    "addr:street":"Ramgatsewg",
    "iso:country":"NL",
    "sg:address":"Ramgatsewg 34",
    "sg:city":"Raamsdonksveer",
    "sg:orig_category":"Oldtimers",
    "sg:phone":"+31 162 520 645",
    "sg:postcode":"4941 VS",
    "sg:province":"Noord-Brabant",
    "wof:name":"Jos Kanters",
    "wof:placetype":"venue"
},
  "geometry": {"coordinates":[4.876914,51.712322],"type":"Point"}
}