{
  "type": "Feature",
  "properties": {
    "addr:full":"Hazelbroek 1 Overloon Noord-Brabant 5825 JN",
    "addr:housenumber":"1",
    "addr:postcode":"5825 jn",
    "addr:street":"Hazelbroek",
    "iso:country":"NL",
    "sg:address":"Hazelbroek 1",
    "sg:city":"Overloon",
    "sg:orig_category":"Diverse Dierenfokkers",
    "sg:phone":"+31 478 641 897",
    "sg:postcode":"5825 JN",
    "sg:province":"Noord-Brabant",
    "wof:name":"Van Herpen Edelpelsdierenfarm Bv",
    "wof:placetype":"venue"
},
  "geometry": {"coordinates":[5.929158,51.580662],"type":"Point"}
}