{
  "type": "Feature",
  "properties": {
    "addr:full":"Zuiderpoort 15 Lelystad Flevoland 8239 AB",
    "addr:housenumber":"15",
    "addr:postcode":"8239 ab",
    "addr:street":"Zuiderpoort;Flevoland",
    "iso:country":"NL",
    "sg:address":"Zuiderpoort 15",
    "sg:city":"Lelystad",
    "sg:orig_category":"Metaalwerken",
    "sg:phone":"+31 320 257 803",
    "sg:postcode":"8239 AB",
    "sg:province":"Flevoland",
    "wof:name":"Carpet-Land",
    "wof:placetype":"venue"
},
  "geometry": {"coordinates":[5.482411,52.491917],"type":"Point"}
}