{
  "type": "Feature",
  "properties": {
    "iso:country":"NL",
    "sg:address":"Baanwegsekade 12",
    "sg:city":"Boskoop",
    "sg:orig_category":"Bloemen And Planten",
    "sg:phone":"+31 172 210 261",
    "sg:postcode":"2771 RZ",
    "sg:province":"South Holland",
    "wof:name":"Arie Van Egmond Sierteeltkwekers C.V.",
    "wof:placetype":"venue"
},
  "geometry": {"coordinates":[4.656898,52.098675],"type":"Point"}
}