{
  "type": "Feature",
  "properties": {
    "addr:full":"Esschebaan 1 Boxtel Noord-Brabant 5282 JK",
    "addr:housenumber":"1",
    "addr:postcode":"5282 jk",
    "addr:street":"Esschebaan",
    "iso:country":"NL",
    "sg:address":"Esschebaan 1",
    "sg:city":"Boxtel",
    "sg:orig_category":"Timmerwerk Van Hout And Kunststof",
    "sg:phone":"+31 411 673 111",
    "sg:postcode":"5282 JK",
    "sg:province":"Noord-Brabant",
    "wof:name":"Bouw- En Timmerbedrijf P. Boons",
    "wof:placetype":"venue"
},
  "geometry": {"coordinates":[5.306537,51.593784],"type":"Point"}
}