{
  "type": "Feature",
  "properties": {
    "addr:full":"Htg Alvastr 34 Venlo Limburg 5923 CK",
    "addr:housenumber":"34",
    "addr:postcode":"5923 ck",
    "iso:country":"NL",
    "sg:address":"Htg Alvastr 34",
    "sg:city":"Venlo",
    "sg:classifiers":[
        {
            "category":"Professional",
            "subcategory":"Printing & Photocopies",
            "type":"Services"
        }
    ],
    "sg:phone":"+31 77 382 0680",
    "sg:postcode":"5923 CK",
    "sg:province":"Limburg",
    "sg:tags":[
        "printer"
    ],
    "wof:name":"Gtb",
    "wof:placetype":"venue"
},
  "geometry": {"coordinates":[6.133346,51.362282],"type":"Point"}
}