{
  "type": "Feature",
  "properties": {
    "iso:country":"NL",
    "sg:address":"Stationsstr 9",
    "sg:city":"Wageningen",
    "sg:orig_category":"Kunsthandel",
    "sg:phone":"+31 317 420 931",
    "sg:postcode":"6701 AM",
    "sg:province":"Gelderland",
    "wof:name":"Motief",
    "wof:placetype":"venue"
},
  "geometry": {"coordinates":[5.665207,51.967854],"type":"Point"}
}