{
  "type": "Feature",
  "properties": {
    "addr:full":"Parallelweg West 54 Vlijmen Noord-Brabant 5251 JG",
    "addr:housenumber":"54",
    "addr:postcode":"5251 jg",
    "addr:street":"Parallelweg West",
    "iso:country":"NL",
    "sg:address":"Parallelweg West 54",
    "sg:city":"Vlijmen",
    "sg:classifiers":[
        {
            "category":"Professional",
            "subcategory":"Accounting & Tax Preparation",
            "type":"Services"
        }
    ],
    "sg:phone":"+31 73 511 6650",
    "sg:postcode":"5251 JG",
    "sg:province":"Noord-Brabant",
    "sg:tags":[
        "accountant"
    ],
    "wof:name":"Timmermans Ra",
    "wof:placetype":"venue"
},
  "geometry": {"coordinates":[5.198661,51.693645],"type":"Point"}
}