{
  "type": "Feature",
  "properties": {
    "addr:full":"A Fokkerwg 49A Rotterdam Zuid-Holland 3088 GE",
    "addr:housenumber":"49a",
    "addr:postcode":"3088",
    "iso:country":"NL",
    "sg:address":"A Fokkerwg 49A",
    "sg:city":"Rotterdam",
    "sg:orig_category":"Verlichtingsartikelen - Groothandel",
    "sg:phone":"+31 10 411 7555",
    "sg:postcode":"3088 GE",
    "sg:province":"Zuid-Holland",
    "wof:name":"Zakenlicht Bv",
    "wof:placetype":"venue"
},
  "geometry": {"coordinates":[4.447941,51.874084],"type":"Point"}
}