{
  "type": "Feature",
  "properties": {
    "addr:full":"De Pas 132 Arnhem Gelderland 6836 HN",
    "addr:housenumber":"132",
    "addr:postcode":"6836 hn",
    "addr:street":"De Pas",
    "iso:country":"NL",
    "sg:address":"De Pas 132",
    "sg:city":"Arnhem",
    "sg:orig_category":"Adviesbureaus Bedrijfsorganisatie",
    "sg:phone":"+31 26 327 3365",
    "sg:postcode":"6836 HN",
    "sg:province":"Gelderland",
    "wof:name":"Effectiveworld",
    "wof:placetype":"venue"
},
  "geometry": {"coordinates":[5.884514,51.942467],"type":"Point"}
}