{
  "type": "Feature",
  "properties": {
    "iso:country":"NL",
    "sg:address":"Industrieweg 28",
    "sg:city":"Beesd",
    "sg:orig_category":"Goederenvervoer Over De Weg",
    "sg:phone":"+31 345 684 344",
    "sg:postcode":"4153 BW",
    "sg:province":"Gelderland",
    "wof:name":"Van Wonderen Transport Bv",
    "wof:placetype":"venue"
},
  "geometry": {"coordinates":[5.192939,51.893299],"type":"Point"}
}