{
  "type": "Feature",
  "properties": {
    "addr:full":"Van Voordenpark 7 Zaltbommel Gelderland 5301 KP",
    "addr:housenumber":"7",
    "addr:postcode":"5301 kp",
    "addr:street":"Van Voordenpark;Gelderland",
    "iso:country":"NL",
    "sg:address":"Van Voordenpark 7",
    "sg:city":"Zaltbommel",
    "sg:orig_category":"Kantoorapparatuur Gh",
    "sg:phone":"+31 418 570 170",
    "sg:postcode":"5301 KP",
    "sg:province":"Gelderland",
    "wof:name":"Rapid Zobel Bv",
    "wof:placetype":"venue"
},
  "geometry": {"coordinates":[5.2592902184,51.7982978821],"type":"Point"}
}