{
  "type": "Feature",
  "properties": {
    "iso:country":"NL",
    "sg:address":"Lakenkoperswg 11",
    "sg:city":"Weesp",
    "sg:orig_category":"Onderhoudswerken",
    "sg:phone":"+31 6 54727985",
    "sg:postcode":"1383 CR",
    "sg:province":"Noord-Holland",
    "wof:name":"Rover, Gebr De",
    "wof:placetype":"venue"
},
  "geometry": {"coordinates":[5.038017,52.298603],"type":"Point"}
}