{
  "type": "Feature",
  "properties": {
    "iso:country":"NL",
    "sg:address":"Leestr 24",
    "sg:city":"Baarn",
    "sg:orig_category":"Automaterialen En Gereedschappen",
    "sg:phone":"+31 35 541 4620",
    "sg:postcode":"3743 EJ",
    "sg:province":"Utrecht",
    "wof:name":"Vos, E",
    "wof:placetype":"venue"
},
  "geometry": {"coordinates":[5.285309,52.211418],"type":"Point"}
}