{
  "type": "Feature",
  "properties": {
    "addr:full":"Stationswg 101 Drachten Friesland 9201 GK",
    "addr:housenumber":"101",
    "addr:postcode":"9201 gk",
    "iso:country":"NL",
    "sg:address":"Stationswg 101",
    "sg:city":"Drachten",
    "sg:orig_category":"Onderhoudswerken",
    "sg:phone":"+31 512 542 656",
    "sg:postcode":"9201 GK",
    "sg:province":"Friesland",
    "wof:name":"Avio",
    "wof:placetype":"venue"
},
  "geometry": {"coordinates":[6.097144,53.11343],"type":"Point"}
}