{
  "type": "Feature",
  "properties": {
    "iso:country":"NL",
    "sg:address":"Trappenberglaan 58",
    "sg:city":"Rijnsburg",
    "sg:orig_category":"Bloemen And Planten Gh",
    "sg:phone":"+31 71 403 1195",
    "sg:postcode":"2231 MV",
    "sg:province":"Zuid-Holland",
    "wof:name":"W. Paauw & Zn Bv",
    "wof:placetype":"venue"
},
  "geometry": {"coordinates":[4.448267,52.209484],"type":"Point"}
}