{
  "type": "Feature",
  "properties": {
    "iso:country":"NL",
    "sg:address":"Chopinrode 17",
    "sg:city":"Zoetermeer",
    "sg:orig_category":"Psychotherapeuten",
    "sg:phone":"+31 79 323 9776",
    "sg:postcode":"2717 BH",
    "sg:province":"Zuid-Holland",
    "wof:name":"Ontmoeting, De",
    "wof:placetype":"venue"
},
  "geometry": {"coordinates":[4.466807,52.067802],"type":"Point"}
}