{
  "type": "Feature",
  "properties": {
    "iso:country":"NL",
    "sg:address":"Molenvaart 228",
    "sg:city":"Breezand",
    "sg:orig_category":"Artsen - Huisartsen",
    "sg:phone":"+31 223 521 250",
    "sg:postcode":"1764 AW",
    "sg:province":"Noord-Holland",
    "wof:name":"Arwert En I M Arwert-Eind, L J",
    "wof:placetype":"venue"
},
  "geometry": {"coordinates":[4.795699,52.875614],"type":"Point"}
}