{
  "type": "Feature",
  "properties": {
    "addr:full":"Stationsstr 20 Drunen Noord-Brabant 5151 HB",
    "addr:housenumber":"20",
    "addr:postcode":"5151 hb",
    "addr:street":"Stationsstr",
    "iso:country":"NL",
    "sg:address":"Stationsstr 20",
    "sg:city":"Drunen",
    "sg:classifiers":[
        {
            "category":"Retail",
            "subcategory":"Auto Repair",
            "type":"Services"
        }
    ],
    "sg:phone":"+31 416 372 159",
    "sg:postcode":"5151 HB",
    "sg:province":"Noord-Brabant",
    "sg:tags":[
        "garage"
    ],
    "wof:name":"Drunens Bv",
    "wof:placetype":"venue"
},
  "geometry": {"coordinates":[5.131826,51.688644],"type":"Point"}
}