{
  "type": "Feature",
  "properties": {
    "addr:full":"Broekstraat 2 Eersel North Brabant 5521 NG",
    "addr:housenumber":"2",
    "addr:postcode":"5521 ng",
    "addr:street":"Broekstraat",
    "iso:country":"NL",
    "sg:address":"Broekstraat 2",
    "sg:city":"Eersel",
    "sg:orig_category":"Huisdierenvoer Fab",
    "sg:phone":"+31 497 512 746",
    "sg:postcode":"5521 NG",
    "sg:province":"North Brabant",
    "wof:name":"Van Adrichem Dierenvoedingsbedrijf Vof",
    "wof:placetype":"venue"
},
  "geometry": {"coordinates":[5.30905,51.358311],"type":"Point"}
}