{
  "type": "Feature",
  "properties": {
    "addr:full":"Buitenwatersloot 341 Delft South Holland 2614 GS",
    "addr:housenumber":"341",
    "addr:postcode":"2614 gs",
    "addr:street":"Buitenwatersloot",
    "iso:country":"NL",
    "sg:address":"Buitenwatersloot 341",
    "sg:city":"Delft",
    "sg:orig_category":"Loodgieterswerk, Verwarming And Sanitaire Installaties",
    "sg:phone":"+31 15 212 1948",
    "sg:postcode":"2614 GS",
    "sg:province":"South Holland",
    "wof:name":"B.W. Bosman Bv",
    "wof:placetype":"venue"
},
  "geometry": {"coordinates":[4.342785,52.003204],"type":"Point"}
}