{
  "type": "Feature",
  "properties": {
    "addr:full":"Zaagmolenstr 94B Rotterdam South Holland 3035 HE",
    "addr:housenumber":"94b",
    "addr:postcode":"3035 he",
    "addr:street":"Zaagmolenstr",
    "iso:country":"NL",
    "sg:address":"Zaagmolenstr 94B",
    "sg:city":"Rotterdam",
    "sg:orig_category":"Koffie- En Theehuizen",
    "sg:phone":"+31 6 29238053",
    "sg:postcode":"3035 HE",
    "sg:province":"South Holland",
    "wof:name":"Depresident Echankouki",
    "wof:placetype":"venue"
},
  "geometry": {"coordinates":[4.486763,51.932938],"type":"Point"}
}