{
  "type": "Feature",
  "properties": {
    "addr:full":"Voorstr 31 Vlaardingen Zuid-Holland 3135 HW",
    "addr:housenumber":"31",
    "addr:postcode":"3135 hw",
    "addr:street":"Voorstr",
    "iso:country":"NL",
    "sg:address":"Voorstr 31",
    "sg:city":"Vlaardingen",
    "sg:orig_category":"Beeldende Kunstenaars",
    "sg:phone":"+31 10 460 2859",
    "sg:postcode":"3135 HW",
    "sg:province":"Zuid-Holland",
    "wof:name":"Dorp, J Van",
    "wof:placetype":"venue"
},
  "geometry": {"coordinates":[4.347982,51.91621],"type":"Point"}
}