{
  "type": "Feature",
  "properties": {
    "addr:full":"Hengelosestr 188 Enschede Overijssel 7521 AK",
    "addr:housenumber":"188",
    "addr:postcode":"7521 ak",
    "iso:country":"NL",
    "sg:address":"Hengelosestr 188",
    "sg:city":"Enschede",
    "sg:orig_category":"Cafetaria'S",
    "sg:phone":"+31 53 435 8820",
    "sg:postcode":"7521 AK",
    "sg:province":"Overijssel",
    "wof:name":"Zwik, 'T",
    "wof:placetype":"venue"
},
  "geometry": {"coordinates":[6.878302,52.227386],"type":"Point"}
}