{
  "type": "Feature",
  "properties": {
    "addr:full":"Nw Stationswg 13 Haren Gn Groningen 9751 SZ",
    "addr:housenumber":"13",
    "addr:postcode":"9751 sz",
    "iso:country":"NL",
    "sg:address":"Nw Stationswg 13",
    "sg:city":"Haren Gn",
    "sg:orig_category":"Arbo- En Bedrijfsgezondheids- Diensten",
    "sg:phone":"+31 50 368 1682",
    "sg:postcode":"9751 SZ",
    "sg:province":"Groningen",
    "wof:name":"Arbo Management Groep",
    "wof:placetype":"venue"
},
  "geometry": {"coordinates":[6.611208,53.172871],"type":"Point"}
}