{
  "type": "Feature",
  "properties": {
    "addr:full":"Kornalynpad 30 Ysselstein Ut Utrecht 3402 ZD",
    "addr:housenumber":"30",
    "addr:postcode":"3402 zd",
    "addr:street":"Kornalynpad",
    "iso:country":"NL",
    "sg:address":"Kornalynpad 30",
    "sg:city":"Ysselstein Ut",
    "sg:orig_category":"Nagelstudio'S",
    "sg:phone":"+31 30 688 5192",
    "sg:postcode":"3402 ZD",
    "sg:province":"Utrecht",
    "sg:website":"http://www.x-nails.nl",
    "wof:name":"X-Nails",
    "wof:placetype":"venue"
},
  "geometry": {"coordinates":[5.048129,52.030361],"type":"Point"}
}