{
  "type": "Feature",
  "properties": {
    "addr:full":"Akkerdreef 291 Zoetermeer Zuid-Holland 2723 XX",
    "addr:housenumber":"291",
    "addr:postcode":"2723 xx",
    "addr:street":"Akkerdreef",
    "iso:country":"NL",
    "sg:address":"Akkerdreef 291",
    "sg:city":"Zoetermeer",
    "sg:orig_category":"Diverse Grafische Activiteiten",
    "sg:phone":"+31 79 331 8215",
    "sg:postcode":"2723 XX",
    "sg:province":"Zuid-Holland",
    "wof:name":"Casual Design",
    "wof:placetype":"venue"
},
  "geometry": {"coordinates":[4.520993,52.065277],"type":"Point"}
}