{
  "type": "Feature",
  "properties": {
    "addr:full":"St Leonardusstr 12 Kerkrade Limburg 6464 AK",
    "addr:housenumber":"12",
    "addr:postcode":"6464 ak",
    "iso:country":"NL",
    "sg:address":"St Leonardusstr 12",
    "sg:city":"Kerkrade",
    "sg:orig_category":"Beeldende Kunstenaars",
    "sg:phone":"+31 45 545 4688",
    "sg:postcode":"6464 AK",
    "sg:province":"Limburg",
    "wof:name":"Steins, P G",
    "wof:placetype":"venue"
},
  "geometry": {"coordinates":[6.069258,50.878464],"type":"Point"}
}