{
  "type": "Feature",
  "properties": {
    "iso:country":"NL",
    "sg:address":"Schoolstraat 34",
    "sg:city":"Rijswijk Zh",
    "sg:orig_category":"Metaalwerken",
    "sg:phone":"+31 70 395 1700",
    "sg:postcode":"2282 RD",
    "sg:province":"South Holland",
    "wof:name":"M. Bode En A. Boers",
    "wof:placetype":"venue"
},
  "geometry": {"coordinates":[4.334014,52.056236],"type":"Point"}
}