{
  "type": "Feature",
  "properties": {
    "addr:full":"Philipsstraat 26 Zoetermeer South Holland 2722 NA",
    "addr:housenumber":"26",
    "addr:postcode":"2722 na",
    "addr:street":"Philipsstraat",
    "iso:country":"NL",
    "sg:address":"Philipsstraat 26",
    "sg:city":"Zoetermeer",
    "sg:orig_category":"Verzekeringen",
    "sg:phone":"+31 79 341 9033",
    "sg:postcode":"2722 NA",
    "sg:province":"South Holland",
    "wof:name":"Bos Verzekeringen & Hypotheken",
    "wof:placetype":"venue"
},
  "geometry": {"coordinates":[4.512167,52.050404],"type":"Point"}
}