{
  "type": "Feature",
  "properties": {
    "addr:full":"Winterstraat 2 Heerlen Limburg 6411 GM",
    "addr:housenumber":"2",
    "addr:postcode":"6411 gm",
    "addr:street":"Winterstraat",
    "iso:country":"NL",
    "sg:address":"Winterstraat 2",
    "sg:city":"Heerlen",
    "sg:orig_category":"Verzekeringen",
    "sg:phone":"+31 45 574 1895",
    "sg:postcode":"6411 GM",
    "sg:province":"Limburg",
    "wof:name":"Assurantie- Adviesburo Mr. Eggen",
    "wof:placetype":"venue"
},
  "geometry": {"coordinates":[5.985522,50.884251],"type":"Point"}
}