{
  "type": "Feature",
  "properties": {
    "addr:full":"Kon Julianawg 43 Leidschendam Zuid-Holland 2264 BB",
    "addr:housenumber":"43",
    "addr:postcode":"2264 bb",
    "addr:street":"Kon",
    "iso:country":"NL",
    "sg:address":"Kon Julianawg 43",
    "sg:city":"Leidschendam",
    "sg:orig_category":"Adviesbureaus Bedrijfsorganisatie",
    "sg:phone":"+31 70 301 0413",
    "sg:postcode":"2264 BB",
    "sg:province":"Zuid-Holland",
    "wof:name":"Balans, Bureau",
    "wof:placetype":"venue"
},
  "geometry": {"coordinates":[4.39354,52.083824],"type":"Point"}
}