{
  "type": "Feature",
  "properties": {
    "addr:full":"Parklaan 44 Katwijk Zh South Holland 2225 SR",
    "addr:housenumber":"44",
    "addr:postcode":"zh;2225 sr",
    "addr:street":"Parklaan",
    "iso:country":"NL",
    "sg:address":"Parklaan 44",
    "sg:city":"Katwijk Zh",
    "sg:orig_category":"Bloemen- And Plantenteelt",
    "sg:phone":"+31 71 401 3225",
    "sg:postcode":"2225 SR",
    "sg:province":"South Holland",
    "wof:name":"Van Der Plas Bloembollen Bv",
    "wof:placetype":"venue"
},
  "geometry": {"coordinates":[4.395962,52.198299],"type":"Point"}
}