{
  "type": "Feature",
  "properties": {
    "iso:country":"NL",
    "sg:address":"Noorderstraat 65",
    "sg:city":"Sappemeer",
    "sg:orig_category":"Banken And Kredietinstellingen",
    "sg:phone":"+31 598 395 820",
    "sg:postcode":"9611 AB",
    "sg:province":"Groningen",
    "wof:name":"Abn Amro",
    "wof:placetype":"venue"
},
  "geometry": {"coordinates":[6.790205,53.163425],"type":"Point"}
}