{
  "type": "Feature",
  "properties": {
    "addr:full":"Churchillln 10 Helmond North Brabant 5705 BK",
    "addr:housenumber":"10",
    "addr:postcode":"5705 bk",
    "addr:street":"Churchillln",
    "iso:country":"NL",
    "sg:address":"Churchillln 10",
    "sg:city":"Helmond",
    "sg:orig_category":"Projectinrichting",
    "sg:phone":"+31 492 534 690",
    "sg:postcode":"5705 BK",
    "sg:province":"North Brabant",
    "wof:name":"Tapetex Bv",
    "wof:placetype":"venue"
},
  "geometry": {"coordinates":[5.658284,51.482239],"type":"Point"}
}