{
  "type": "Feature",
  "properties": {
    "addr:full":"Raadhuisdijk 17 Maasbommel Gelderland 6627 AC",
    "addr:housenumber":"17",
    "addr:postcode":"6627 ac",
    "addr:street":"Raadhuisdijk;Gelderland",
    "iso:country":"NL",
    "sg:address":"Raadhuisdijk 17",
    "sg:city":"Maasbommel",
    "sg:orig_category":"Antiekzaken",
    "sg:phone":"+31 487 562 113",
    "sg:postcode":"6627 AC",
    "sg:province":"Gelderland",
    "wof:name":"Grandmothers Time",
    "wof:placetype":"venue"
},
  "geometry": {"coordinates":[5.54147,51.819324],"type":"Point"}
}