{
  "type": "Feature",
  "properties": {
    "addr:full":"Horsewei 10 Boornzwaag Provincie Friesland 8526 DS",
    "addr:housenumber":"10",
    "addr:postcode":"8526 ds",
    "addr:street":"Horsewei;Provincie Friesland",
    "iso:country":"NL",
    "sg:address":"Horsewei 10",
    "sg:city":"Boornzwaag",
    "sg:orig_category":"Kampeerterreinen",
    "sg:phone":"+31 515 559 814",
    "sg:postcode":"8526 DS",
    "sg:province":"Provincie Friesland",
    "wof:name":"De Tijnjehoeve",
    "wof:placetype":"venue"
},
  "geometry": {"coordinates":[5.716591835,52.9949455261],"type":"Point"}
}