{
  "type": "Feature",
  "properties": {
    "addr:full":"Dries 67 Weert Limburg 6006 HR",
    "addr:housenumber":"67",
    "addr:postcode":"6006 hr",
    "addr:street":"Dries",
    "iso:country":"NL",
    "sg:address":"Dries 67",
    "sg:city":"Weert",
    "sg:orig_category":"Boekhouders",
    "sg:phone":"+31 495 535 734",
    "sg:postcode":"6006 HR",
    "sg:province":"Limburg",
    "wof:name":"Administratiekantoor Moonen P.M.J.M. Moonen",
    "wof:placetype":"venue"
},
  "geometry": {"coordinates":[5.70237,51.247185],"type":"Point"}
}