{
  "type": "Feature",
  "properties": {
    "addr:full":"Heistr 4 Ryen Noord-Brabant 5121 JL",
    "addr:housenumber":"4",
    "addr:postcode":"5121 jl",
    "addr:street":"Heistr",
    "iso:country":"NL",
    "sg:address":"Heistr 4",
    "sg:city":"Ryen",
    "sg:classifiers":[
        {
            "category":"Personal",
            "subcategory":"Nail Salon",
            "type":"Services"
        }
    ],
    "sg:phone":"+31 161 240 568",
    "sg:postcode":"5121 JL",
    "sg:province":"Noord-Brabant",
    "sg:tags":[
        "pedicure"
    ],
    "wof:name":"Bruijn, Tonia De",
    "wof:placetype":"venue"
},
  "geometry": {"coordinates":[4.9197,51.588017],"type":"Point"}
}