{
  "type": "Feature",
  "properties": {
    "iso:country":"NL",
    "sg:address":"Vastenavondk Str 73",
    "sg:city":"Venlo",
    "sg:orig_category":"Verenigingsgebouwen",
    "sg:phone":"+31 77 382 2163",
    "sg:postcode":"5922 AT",
    "sg:province":"Limburg",
    "wof:name":"Muspelheim",
    "wof:placetype":"venue"
},
  "geometry": {"coordinates":[6.139391,51.373962],"type":"Point"}
}