{
  "type": "Feature",
  "properties": {
    "addr:full":"Marktstr 66 Schagen Noord-Holland 1741 AD",
    "addr:housenumber":"66",
    "addr:postcode":"1741 ad",
    "addr:street":"Marktstr",
    "iso:country":"NL",
    "sg:address":"Marktstr 66",
    "sg:city":"Schagen",
    "sg:orig_category":"Onroerende Goederen",
    "sg:phone":"+31 224 298 661",
    "sg:postcode":"1741 AD",
    "sg:province":"Noord-Holland",
    "wof:name":"Boontjes Bv, Cor",
    "wof:placetype":"venue"
},
  "geometry": {"coordinates":[4.793501,52.78825],"type":"Point"}
}