{
  "type": "Feature",
  "properties": {
    "addr:full":"Borneoplein 5 Groningen Groningen 9715 GM",
    "addr:housenumber":"5",
    "addr:postcode":"9715 gm",
    "addr:street":"Borneoplein",
    "iso:country":"NL",
    "sg:address":"Borneoplein 5",
    "sg:city":"Groningen",
    "sg:orig_category":"Biljart- And Snookerzalen",
    "sg:phone":"+31 50 579 7794",
    "sg:postcode":"9715 GM",
    "sg:province":"Groningen",
    "wof:name":"Snookercentrum Bintang",
    "wof:placetype":"venue"
},
  "geometry": {"coordinates":[6.566926,53.229904],"type":"Point"}
}