{
  "type": "Feature",
  "properties": {
    "addr:full":"Verdiln 122 Heesch Noord-Brabant 5384 CN",
    "addr:housenumber":"122",
    "addr:postcode":"5384 cn",
    "iso:country":"NL",
    "sg:address":"Verdiln 122",
    "sg:city":"Heesch",
    "sg:orig_category":"Autorijscholen",
    "sg:phone":"+31 412 450 350",
    "sg:postcode":"5384 CN",
    "sg:province":"Noord-Brabant",
    "wof:name":"Barten",
    "wof:placetype":"venue"
},
  "geometry": {"coordinates":[5.52822,51.735455],"type":"Point"}
}