{
  "type": "Feature",
  "properties": {
    "addr:full":"Granadosln 150 Rotterdam Zuid-Holland 3055 RE",
    "addr:housenumber":"150",
    "addr:postcode":"3055 re",
    "iso:country":"NL",
    "sg:address":"Granadosln 150",
    "sg:city":"Rotterdam",
    "sg:orig_category":"Hypotheken",
    "sg:phone":"+31 10 422 8588",
    "sg:postcode":"3055 RE",
    "sg:province":"Zuid-Holland",
    "wof:name":"Koole Financ Adviesbureau, Drs J E",
    "wof:placetype":"venue"
},
  "geometry": {"coordinates":[4.510035,51.958241],"type":"Point"}
}