{
  "type": "Feature",
  "properties": {
    "iso:country":"NL",
    "sg:address":"Wetering 72",
    "sg:city":"Bergen Nh",
    "sg:orig_category":"Leder",
    "sg:phone":"+31 72 581 3849",
    "sg:postcode":"1862 HT",
    "sg:province":"North Holland",
    "wof:name":"Rt",
    "wof:placetype":"venue"
},
  "geometry": {"coordinates":[4.724357,52.666],"type":"Point"}
}