{
  "type": "Feature",
  "properties": {
    "iso:country":"NL",
    "sg:address":"De Wagenmaker 14",
    "sg:city":"Heiloo",
    "sg:classifiers":[
        {
            "category":"Shopping",
            "subcategory":"Adult",
            "type":"Retail Goods"
        }
    ],
    "sg:phone":"+31 72 532 0072",
    "sg:postcode":"1851 PX",
    "sg:province":"Noord-Holland",
    "sg:tags":[
        "lingerie",
        "en",
        "tricotage"
    ],
    "wof:name":"Groot En Beekman Bv, De",
    "wof:placetype":"venue"
},
  "geometry": {"coordinates":[4.719785,52.592281],"type":"Point"}
}