{
  "type": "Feature",
  "properties": {
    "iso:country":"NL",
    "sg:address":"Zwart Janstr 49B",
    "sg:city":"Rotterdam",
    "sg:classifiers":[
        {
            "category":"Food & Beverages",
            "subcategory":"Bakery",
            "type":"Retail Goods"
        }
    ],
    "sg:phone":"+31 10 467 7857",
    "sg:postcode":"3035 AL",
    "sg:province":"South Holland",
    "sg:tags":[
        "pizza"
    ],
    "wof:name":"Napoli",
    "wof:placetype":"venue"
},
  "geometry": {"coordinates":[4.478872,51.933247],"type":"Point"}
}