{
  "type": "Feature",
  "properties": {
    "addr:full":"Molenstraat 30 Made California 4921 KK",
    "addr:housenumber":"30",
    "addr:postcode":"4921 kk",
    "addr:street":"Molenstraat",
    "iso:country":"NL",
    "sg:address":"Molenstraat 30",
    "sg:city":"Made",
    "sg:orig_category":"Autokeuringen",
    "sg:phone":"+31 162 685 941",
    "sg:postcode":"4921 KK",
    "sg:province":"California",
    "wof:name":"G. Van Laarhoven",
    "wof:placetype":"venue"
},
  "geometry": {"coordinates":[-119.992378,36.905685],"type":"Point"}
}