{
  "type": "Feature",
  "properties": {
    "iso:country":"NL",
    "sg:address":"Hoofdstraat 115",
    "sg:city":"Grootegast",
    "sg:orig_category":"Wasserettes And Stomerijen",
    "sg:phone":"+31 594 613 016",
    "sg:postcode":"9861 AD",
    "sg:province":"Groningen",
    "wof:name":"Gerner Stomen",
    "wof:placetype":"venue"
},
  "geometry": {"coordinates":[6.276154995,53.21326828],"type":"Point"}
}