{
  "type": "Feature",
  "properties": {
    "iso:country":"NL",
    "sg:address":"Kleine Houtweg 139",
    "sg:city":"Haarlem",
    "sg:orig_category":"Bejaardeninstellingen And Serviceflats",
    "sg:phone":"+31 23 531 5555",
    "sg:postcode":"2012 CG",
    "sg:province":"Noord-Holland",
    "wof:name":"Stichting Huize Spaar En Hout",
    "wof:placetype":"venue"
},
  "geometry": {"coordinates":[4.632242,52.369583],"type":"Point"}
}