{
  "type": "Feature",
  "properties": {
    "iso:country":"NL",
    "sg:address":"Vijfhuizenbaan 35",
    "sg:city":"Riel",
    "sg:orig_category":"Verhuur Kantoorapparatuur",
    "sg:phone":"+31 13 518 2160",
    "sg:postcode":"5133 NH",
    "sg:province":"Noord-Brabant",
    "wof:name":"Bakkers",
    "wof:placetype":"venue"
},
  "geometry": {"coordinates":[4.97308,51.526119],"type":"Point"}
}