{
  "type": "Feature",
  "properties": {
    "iso:country":"NL",
    "sg:address":"Dorpergaarden 16",
    "sg:city":"Losser",
    "sg:orig_category":"Elektrische Apparatuur Gh",
    "sg:phone":"+31 53 536 0301",
    "sg:postcode":"7582 HV",
    "sg:province":"Overijssel",
    "wof:name":"Huiskes Aviation Service",
    "wof:placetype":"venue"
},
  "geometry": {"coordinates":[6.994122,52.264351],"type":"Point"}
}