{
  "type": "Feature",
  "properties": {
    "iso:country":"NL",
    "sg:address":"Terborgseweg 38",
    "sg:city":"Doetinchem",
    "sg:orig_category":"Huishoudapparatuur, Televisies And Radio'S",
    "sg:phone":"+31 314 334 911",
    "sg:postcode":"7005 BA",
    "sg:province":"Gelderland",
    "wof:name":"Leo Van Schaijik",
    "wof:placetype":"venue"
},
  "geometry": {"coordinates":[6.292832,51.961563],"type":"Point"}
}