{
  "type": "Feature",
  "properties": {
    "addr:full":"T Dorp 60A Heesch Noord-Brabant 5384 MC",
    "addr:housenumber":"60a",
    "addr:postcode":"5384 mc",
    "addr:street":"T Dorp",
    "iso:country":"NL",
    "sg:address":"T Dorp 60A",
    "sg:city":"Heesch",
    "sg:orig_category":"Kinderkleding",
    "sg:phone":"+31 412 456 269",
    "sg:postcode":"5384 MC",
    "sg:province":"Noord-Brabant",
    "wof:name":"Inimini",
    "wof:placetype":"venue"
},
  "geometry": {"coordinates":[5.528428,51.735569],"type":"Point"}
}