{
  "type": "Feature",
  "properties": {
    "addr:full":"Broersvest 75 Schiedam South Holland 3111 ED",
    "addr:housenumber":"75",
    "addr:postcode":"3111 ed",
    "addr:street":"Broersvest",
    "iso:country":"NL",
    "sg:address":"Broersvest 75",
    "sg:city":"Schiedam",
    "sg:orig_category":"Verenigingen En Stichtingen",
    "sg:phone":"+31 10 473 5518",
    "sg:postcode":"3111 ED",
    "sg:province":"South Holland",
    "wof:name":"Musis, Sticht",
    "wof:placetype":"venue"
},
  "geometry": {"coordinates":[4.402155,51.916359],"type":"Point"}
}