{
  "type": "Feature",
  "properties": {
    "addr:full":"Keizersgr 500-502 Amsterdam Noord-Holland 1017 EH",
    "addr:housenumber":"500-502",
    "addr:postcode":"1017 eh",
    "iso:country":"NL",
    "sg:address":"Keizersgr 500-502",
    "sg:city":"Amsterdam",
    "sg:orig_category":"Woninginrichting",
    "sg:phone":"+31 20 623 7782",
    "sg:postcode":"1017 EH",
    "sg:province":"Noord-Holland",
    "wof:name":"Dols En Co Interieur, Fa",
    "wof:placetype":"venue"
},
  "geometry": {"coordinates":[4.8856511116,52.3659706116],"type":"Point"}
}