{
  "type": "Feature",
  "properties": {
    "iso:country":"NL",
    "sg:address":"J Damsngl 23",
    "sg:city":"Zutphen",
    "sg:orig_category":"Binnenhuisarchitectuur",
    "sg:phone":"+31 575 555 375",
    "sg:postcode":"7201 AR",
    "sg:province":"Gelderland",
    "sg:website":"http://www.boncouleur.nl",
    "wof:name":"Bon Couleur",
    "wof:placetype":"venue"
},
  "geometry": {"coordinates":[-85.97782100000001,42.812248],"type":"Point"}
}