{
  "type": "Feature",
  "properties": {
    "addr:full":"Wannerstraat 14 Heerlen Limburg 6413 EV",
    "addr:housenumber":"14",
    "addr:postcode":"6413 ev",
    "addr:street":"Wannerstraat",
    "iso:country":"NL",
    "sg:address":"Wannerstraat 14",
    "sg:city":"Heerlen",
    "sg:orig_category":"Discountwinkels",
    "sg:phone":"+31 45 563 0103",
    "sg:postcode":"6413 EV",
    "sg:province":"Limburg",
    "wof:name":"Zeeman Textielsupers",
    "wof:placetype":"venue"
},
  "geometry": {"coordinates":[5.955289,50.91576],"type":"Point"}
}