{
  "type": "Feature",
  "properties": {
    "iso:country":"NL",
    "sg:address":"Nieuwemeerdijk 71",
    "sg:city":"Badhoevedorp",
    "sg:orig_category":"Muziekinstrumenten",
    "sg:phone":"+31 20 659 2309",
    "sg:postcode":"1171 ND",
    "sg:province":"Noord-Holland",
    "wof:name":"Piet Klaassen Drumservice",
    "wof:placetype":"venue"
},
  "geometry": {"coordinates":[4.793005,52.339077],"type":"Point"}
}