{
  "type": "Feature",
  "properties": {
    "iso:country":"NL",
    "sg:address":"Steenovenweg 50",
    "sg:city":"Helmond",
    "sg:orig_category":"Wegen And Sportterreinen",
    "sg:phone":"+31 492 541 855",
    "sg:postcode":"5708 HN",
    "sg:province":"North Brabant",
    "wof:name":"Bv Aannemingsbedrijf De Kempen",
    "wof:placetype":"venue"
},
  "geometry": {"coordinates":[5.6339998245,51.4764633179],"type":"Point"}
}