{
  "type": "Feature",
  "properties": {
    "iso:country":"NL",
    "sg:address":"Collinsstraat 4",
    "sg:city":"Urmond",
    "sg:orig_category":"Film-, Tv- And Videoproductie",
    "sg:phone":"+31 46 426 0577",
    "sg:postcode":"6129 HH",
    "sg:province":"Limburg",
    "wof:name":"Tmi Entertainment & Communicatie",
    "wof:placetype":"venue"
},
  "geometry": {"coordinates":[5.780615,50.991875],"type":"Point"}
}