{
  "type": "Feature",
  "properties": {
    "addr:full":"Bisschop Ludgerstraat 29 Zaltbommel Gelderland 5302 XL",
    "addr:housenumber":"29",
    "addr:postcode":"5302 xl",
    "addr:street":"Bisschop Ludgerstraat;Gelderland",
    "iso:country":"NL",
    "sg:address":"Bisschop Ludgerstraat 29",
    "sg:city":"Zaltbommel",
    "sg:orig_category":"Fotostudio'S And Fotografen",
    "sg:phone":"+31 418 684 249",
    "sg:postcode":"5302 XL",
    "sg:province":"Gelderland",
    "wof:name":"Fotoprodukties Paul Van Galen",
    "wof:placetype":"venue"
},
  "geometry": {"coordinates":[5.247147,51.799973],"type":"Point"}
}