{
  "type": "Feature",
  "properties": {
    "iso:country":"NL",
    "sg:address":"Heldensedijk 2",
    "sg:city":"Roggel",
    "sg:orig_category":"Fitnesscentra",
    "sg:phone":"+31 475 491 667",
    "sg:postcode":"6088 NT",
    "sg:province":"Limburg",
    "wof:name":"Mico Sport",
    "wof:placetype":"venue"
},
  "geometry": {"coordinates":[5.935176,51.276066],"type":"Point"}
}