{
  "type": "Feature",
  "properties": {
    "iso:country":"NL",
    "sg:address":"Veldtzigtlaan 1",
    "sg:city":"Haarlem",
    "sg:orig_category":"Organisaties And Verenigingen",
    "sg:phone":"+31 23 527 7168",
    "sg:postcode":"2015 CD",
    "sg:province":"Noord-Holland",
    "wof:name":"Vsv Sipke Wynia Studentenvereniging",
    "wof:placetype":"venue"
},
  "geometry": {"coordinates":[4.6136751175,52.388130188],"type":"Point"}
}