{
  "type": "Feature",
  "properties": {
    "addr:full":"Hoekeinde 24 Sleeuwyk Noord-Brabant 4254 LN",
    "addr:housenumber":"24",
    "addr:postcode":"4254 ln",
    "addr:street":"Hoekeinde",
    "iso:country":"NL",
    "sg:address":"Hoekeinde 24",
    "sg:city":"Sleeuwyk",
    "sg:orig_category":"Geluidsinstallaties - Verhuur",
    "sg:phone":"+31 183 310 422",
    "sg:postcode":"4254 LN",
    "sg:province":"Noord-Brabant",
    "sg:website":"http://www.overbeekfaciliteiten.nl",
    "wof:name":"Overbeek, Van",
    "wof:placetype":"venue"
},
  "geometry": {"coordinates":[4.963813,51.818516],"type":"Point"}
}