{
  "type": "Feature",
  "properties": {
    "addr:full":"Bornsedijk 2 Deurningen Overijssel 7561 RA",
    "addr:housenumber":"2",
    "addr:postcode":"7561 ra",
    "addr:street":"Bornsedijk",
    "iso:country":"NL",
    "sg:address":"Bornsedijk 2",
    "sg:city":"Deurningen",
    "sg:orig_category":"Boomkwekerijen",
    "sg:phone":"+31 74 277 0915",
    "sg:postcode":"7561 RA",
    "sg:province":"Overijssel",
    "wof:name":"Boomkwekerij Jeroen Scholten Bv",
    "wof:placetype":"venue"
},
  "geometry": {"coordinates":[6.831863,52.303318],"type":"Point"}
}