{
  "type": "Feature",
  "properties": {
    "addr:full":"I Dammanstr 1 Zaandam North Holland 1507 PG",
    "addr:housenumber":"1",
    "addr:postcode":"1507 pg",
    "iso:country":"NL",
    "sg:address":"I Dammanstr 1",
    "sg:city":"Zaandam",
    "sg:orig_category":"Vertalers",
    "sg:phone":"+31 75 670 2795",
    "sg:postcode":"1507 PG",
    "sg:province":"North Holland",
    "wof:name":"Quak, Vertalers",
    "wof:placetype":"venue"
},
  "geometry": {"coordinates":[4.80102,52.438808],"type":"Point"}
}