{
  "type": "Feature",
  "properties": {
    "iso:country":"NL",
    "sg:address":"Laanakkerwg 16",
    "sg:city":"Vianen Zh",
    "sg:orig_category":"Product-Promotie",
    "sg:phone":"+31 347 379 421",
    "sg:postcode":"4131 PB",
    "sg:province":"Utrecht",
    "wof:name":"Euroboek Bv",
    "wof:placetype":"venue"
},
  "geometry": {"coordinates":[5.095054,51.970844],"type":"Point"}
}