{
  "type": "Feature",
  "properties": {
    "addr:full":"Sarphatipk 99 Amsterdam Noord-Holland 1073 CV",
    "addr:housenumber":"99",
    "addr:postcode":"1073 cv",
    "addr:street":"Sarphatipk",
    "iso:country":"NL",
    "sg:address":"Sarphatipk 99",
    "sg:city":"Amsterdam",
    "sg:orig_category":"Psychologen",
    "sg:phone":"+31 20 673 3831",
    "sg:postcode":"1073 CV",
    "sg:province":"Noord-Holland",
    "wof:name":"Mayer, Drs K",
    "wof:placetype":"venue"
},
  "geometry": {"coordinates":[4.898359,52.355453],"type":"Point"}
}