{
  "type": "Feature",
  "properties": {
    "addr:full":"Mierloseweg 116 Geldrop North Brabant 5666  K",
    "addr:housenumber":"116;5666",
    "addr:postcode":"k",
    "addr:street":"Mierloseweg",
    "iso:country":"NL",
    "sg:address":"Mierloseweg 116",
    "sg:city":"Geldrop",
    "sg:orig_category":"Metaalwerken",
    "sg:phone":"+31 6 53757108",
    "sg:postcode":"5666  K",
    "sg:province":"North Brabant",
    "wof:name":"Theunissen Plafond Systemen",
    "wof:placetype":"venue"
},
  "geometry": {"coordinates":[5.569938,51.428322],"type":"Point"}
}