{
  "type": "Feature",
  "properties": {
    "addr:full":"Karveelstr 7 Alkmaar North Holland 1826 ED",
    "addr:housenumber":"7",
    "addr:postcode":"1826 ed",
    "addr:street":"Karveelstr",
    "iso:country":"NL",
    "sg:address":"Karveelstr 7",
    "sg:city":"Alkmaar",
    "sg:orig_category":"Hulpverlening Sociaal",
    "sg:phone":"+31 72 564 5326",
    "sg:postcode":"1826 ED",
    "sg:province":"North Holland",
    "wof:name":"Exodus, Sticht",
    "wof:placetype":"venue"
},
  "geometry": {"coordinates":[4.760056,52.655743],"type":"Point"}
}