{
  "type": "Feature",
  "properties": {
    "addr:full":"De Hagen 13 Vollenhove NL.08 8325 DB",
    "addr:housenumber":"13;nl.08",
    "addr:postcode":"8325 db",
    "addr:street":"De Hagen",
    "iso:country":"NL",
    "sg:address":"De Hagen 13",
    "sg:city":"Vollenhove",
    "sg:orig_category":"Veiligheidsuitrusting En -Kleding",
    "sg:phone":"+31 527 241 090",
    "sg:postcode":"8325 DB",
    "sg:province":"NL.08",
    "wof:name":"Eurosafe Solutions Bv",
    "wof:placetype":"venue"
},
  "geometry": {"coordinates":[5.970376,52.682274],"type":"Point"}
}