{
  "type": "Feature",
  "properties": {
    "addr:full":"Touwbaan 20 Zierikzee Zeeland 4301 HJ",
    "addr:housenumber":"20",
    "addr:postcode":"4301 hj",
    "addr:street":"Touwbaan",
    "iso:country":"NL",
    "sg:address":"Touwbaan 20",
    "sg:city":"Zierikzee",
    "sg:orig_category":"Artsen And Specialisten",
    "sg:phone":"+31 111 412 280",
    "sg:postcode":"4301 HJ",
    "sg:province":"Zeeland",
    "wof:name":"J. De Jonge",
    "wof:placetype":"venue"
},
  "geometry": {"coordinates":[3.922056,51.653767],"type":"Point"}
}