{
  "type": "Feature",
  "properties": {
    "addr:full":"Noordervaart 74 Stompetoren North Holland 1841 HB",
    "addr:housenumber":"74",
    "addr:postcode":"1841 hb",
    "addr:street":"Noordervaart",
    "iso:country":"NL",
    "sg:address":"Noordervaart 74",
    "sg:city":"Stompetoren",
    "sg:orig_category":"Kaas",
    "sg:phone":"+31 72 503 9580",
    "sg:postcode":"1841 HB",
    "sg:province":"North Holland",
    "wof:name":"Cheese Promotions",
    "wof:placetype":"venue"
},
  "geometry": {"coordinates":[4.8273711205,52.6098709106],"type":"Point"}
}