{
  "type": "Feature",
  "properties": {
    "addr:full":"Joossesweg 2 Westkapelle Zeeland 4361 KA",
    "addr:housenumber":"2",
    "addr:postcode":"4361 ka",
    "addr:street":"Joossesweg",
    "iso:country":"NL",
    "sg:address":"Joossesweg 2",
    "sg:city":"Westkapelle",
    "sg:orig_category":"Kampeerterreinen",
    "sg:phone":"+31 118 571 798",
    "sg:postcode":"4361 KA",
    "sg:province":"Zeeland",
    "wof:name":"Camping `T Hoekje",
    "wof:placetype":"venue"
},
  "geometry": {"coordinates":[3.4558680058,51.515083313],"type":"Point"}
}