{
  "type": "Feature",
  "properties": {
    "addr:full":"Wenckebachwg 49D Amsterdam North Holland 1096 AK",
    "addr:housenumber":"49d",
    "addr:postcode":"1096 ak",
    "addr:street":"Wenckebachwg",
    "iso:country":"NL",
    "sg:address":"Wenckebachwg 49D",
    "sg:city":"Amsterdam",
    "sg:orig_category":"Horecabenodigdheden",
    "sg:phone":"+31 20 422 7227",
    "sg:postcode":"1096 AK",
    "sg:province":"North Holland",
    "sg:website":"http://www.smart-bar.nl",
    "wof:name":"Smart Bar",
    "wof:placetype":"venue"
},
  "geometry": {"coordinates":[4.925825,52.33934],"type":"Point"}
}