{
  "type": "Feature",
  "properties": {
    "addr:full":"Postbus 13 Sint Jacobiparochie Friesland 9079 ZX",
    "addr:housenumber":"13;jacobiparochie",
    "addr:postcode":"9079 zx",
    "addr:street":"Postbus",
    "iso:country":"NL",
    "sg:address":"Postbus 13",
    "sg:city":"Sint Jacobiparochie",
    "sg:orig_category":"Fotoreportages",
    "sg:phone":"+31 6 50922436",
    "sg:postcode":"9079 ZX",
    "sg:province":"Friesland",
    "wof:name":"The Focus Line",
    "wof:placetype":"venue"
},
  "geometry": {"coordinates":[5.60431,53.272709],"type":"Point"}
}