{
  "type": "Feature",
  "properties": {
    "addr:full":"Corisbergwg 205 Heerlen Limburg 6418 CV",
    "addr:housenumber":"205",
    "addr:postcode":"6418 cv",
    "iso:country":"NL",
    "sg:address":"Corisbergwg 205",
    "sg:city":"Heerlen",
    "sg:orig_category":"Bloemen En Planten",
    "sg:phone":"+31 45 542 4247",
    "sg:postcode":"6418 CV",
    "sg:province":"Limburg",
    "wof:name":"Grandi",
    "wof:placetype":"venue"
},
  "geometry": {"coordinates":[6.00522,50.867546],"type":"Point"}
}