{
  "type": "Feature",
  "properties": {
    "addr:full":"Eikenln 20 Loon Op Zand Noord-Brabant 5175 BV",
    "addr:housenumber":"20",
    "addr:postcode":"5175 bv",
    "addr:street":"Eikenln",
    "iso:country":"NL",
    "sg:address":"Eikenln 20",
    "sg:city":"Loon Op Zand",
    "sg:orig_category":"Ovenbouw",
    "sg:phone":"+31 416 362 206",
    "sg:postcode":"5175 BV",
    "sg:province":"Noord-Brabant",
    "wof:name":"Boogers-Gheering Vof, R A A M",
    "wof:placetype":"venue"
},
  "geometry": {"coordinates":[5.0763478279,51.6273994446],"type":"Point"}
}