{
  "type": "Feature",
  "properties": {
    "addr:full":"Hoofdstraat 201 Hoogezand Groningen 9601 EE",
    "addr:housenumber":"201",
    "addr:postcode":"9601 ee",
    "addr:street":"Hoofdstraat",
    "iso:country":"NL",
    "sg:address":"Hoofdstraat 201",
    "sg:city":"Hoogezand",
    "sg:orig_category":"Drogisterijen",
    "sg:phone":"+31 598 392 979",
    "sg:postcode":"9601 EE",
    "sg:province":"Groningen",
    "wof:name":"Drogisterij De Gaper",
    "wof:placetype":"venue"
},
  "geometry": {"coordinates":[6.76976,53.163876],"type":"Point"}
}