{
  "type": "Feature",
  "properties": {
    "addr:full":"Daalsewg 4 Veldhoven North Brabant 5507 LH",
    "addr:housenumber":"4",
    "addr:postcode":"5507 lh",
    "addr:street":"Daalsewg",
    "iso:country":"NL",
    "sg:address":"Daalsewg 4",
    "sg:city":"Veldhoven",
    "sg:orig_category":"Koppensnellen",
    "sg:phone":"+31 40 253 3313",
    "sg:postcode":"5507 LH",
    "sg:province":"North Brabant",
    "wof:name":"Lepper Vof, De",
    "wof:placetype":"venue"
},
  "geometry": {"coordinates":[5.368738,51.424744],"type":"Point"}
}