{
  "type": "Feature",
  "properties": {
    "addr:full":"Postbus 87753 S Gravenhage Drenthe 2508 DD",
    "addr:housenumber":"87753",
    "addr:postcode":"2508 dd",
    "addr:street":"Postbus;S Gravenhage",
    "iso:country":"NL",
    "sg:address":"Postbus 87753",
    "sg:city":"S Gravenhage",
    "sg:orig_category":"Adviesbureaus Bedrijfsorganisatie",
    "sg:phone":"+31 70 322 9722",
    "sg:postcode":"2508 DD",
    "sg:province":"Drenthe",
    "sg:website":"http://www.metafocus.nl",
    "wof:name":"Metafocus",
    "wof:placetype":"venue"
},
  "geometry": {"coordinates":[4.31361,52.07832],"type":"Point"}
}