{
  "type": "Feature",
  "properties": {
    "addr:full":"Houtrakgracht 234 Utrecht Utrecht 3544 SJ",
    "addr:housenumber":"234",
    "addr:postcode":"3544",
    "addr:street":"Houtrakgracht",
    "iso:country":"NL",
    "sg:address":"Houtrakgracht 234",
    "sg:city":"Utrecht",
    "sg:orig_category":"Goederenvervoer Over De Weg",
    "sg:phone":"+31 30 262 8004",
    "sg:postcode":"3544 SJ",
    "sg:province":"Utrecht",
    "wof:name":"Borgers Transport",
    "wof:placetype":"venue"
},
  "geometry": {"coordinates":[5.052841,52.084743],"type":"Point"}
}