{
  "type": "Feature",
  "properties": {
    "addr:full":"De Zwaaikom 2A Veendam Groningen 9641 KV",
    "addr:housenumber":"2a",
    "addr:postcode":"9641 kv",
    "addr:street":"De Zwaaikom",
    "iso:country":"NL",
    "sg:address":"De Zwaaikom 2A",
    "sg:city":"Veendam",
    "sg:orig_category":"Banden",
    "sg:phone":"+31 598 626 888",
    "sg:postcode":"9641 KV",
    "sg:province":"Groningen",
    "sg:website":"http://www.euromaster.com",
    "wof:name":"Euromaster",
    "wof:placetype":"venue"
},
  "geometry": {"coordinates":[6.892203,53.102371],"type":"Point"}
}