{
  "type": "Feature",
  "properties": {
    "iso:country":"NL",
    "sg:address":"Kastanjeln 36",
    "sg:city":"Lochem",
    "sg:orig_category":"Veilingen En Venduhuizen",
    "sg:phone":"+31 573 251 895",
    "sg:postcode":"7241 DZ",
    "sg:province":"Gelderland",
    "wof:name":"Castanghe, De",
    "wof:placetype":"venue"
},
  "geometry": {"coordinates":[6.421436,52.15974],"type":"Point"}
}