{
  "type": "Feature",
  "properties": {
    "iso:country":"NL",
    "sg:address":"Het Haagje 142-150",
    "sg:city":"Hoogeveen",
    "sg:orig_category":"Meubelzaken, Woning- And Keukeninrichting",
    "sg:phone":"+31 528 279 104",
    "sg:postcode":"7906  A",
    "sg:province":"Drenthe",
    "wof:name":"Maestro Meubel",
    "wof:placetype":"venue"
},
  "geometry": {"coordinates":[6.485353,52.721008],"type":"Point"}
}