{
  "type": "Feature",
  "properties": {
    "addr:full":"Tijnjedyk 5 Leeuwarden Provincie Friesland 8934 BT",
    "addr:housenumber":"5",
    "addr:postcode":"8934 bt",
    "addr:street":"Tijnjedyk;Provincie Friesland",
    "iso:country":"NL",
    "sg:address":"Tijnjedyk 5",
    "sg:city":"Leeuwarden",
    "sg:orig_category":"Bloemen And Planten",
    "sg:phone":"+31 58 288 8000",
    "sg:postcode":"8934 BT",
    "sg:province":"Provincie Friesland",
    "wof:name":"Intratuin",
    "wof:placetype":"venue"
},
  "geometry": {"coordinates":[5.812895,53.192482],"type":"Point"}
}