{
  "type": "Feature",
  "properties": {
    "iso:country":"NL",
    "sg:address":"Buitenzorgln 23",
    "sg:city":"Ede Gld",
    "sg:orig_category":"Verenigingen En Stichtingen",
    "sg:phone":"+31 318 611 743",
    "sg:postcode":"6712 GP",
    "sg:province":"Gelderland",
    "wof:name":"Theosofische Ver Ned",
    "wof:placetype":"venue"
},
  "geometry": {"coordinates":[5.665523,52.051296],"type":"Point"}
}