{
  "type": "Feature",
  "properties": {
    "iso:country":"NL",
    "sg:address":"Westerstraat 76",
    "sg:city":"Purmerend",
    "sg:orig_category":"Damesmodezaken",
    "sg:phone":"+31 299 474 730",
    "sg:postcode":"1441 AT",
    "sg:province":"Noord-Holland",
    "wof:name":"Oversized",
    "wof:placetype":"venue"
},
  "geometry": {"coordinates":[4.943778,52.509548],"type":"Point"}
}