{
  "type": "Feature",
  "properties": {
    "addr:full":"Kerkstraat 14 Beesd Gelderland 4153 AG",
    "addr:housenumber":"14",
    "addr:postcode":"4153",
    "addr:street":"Kerkstraat;Gelderland",
    "iso:country":"NL",
    "sg:address":"Kerkstraat 14",
    "sg:city":"Beesd",
    "sg:orig_category":"Verzekeringen",
    "sg:phone":"+31 345 681 512",
    "sg:postcode":"4153 AG",
    "sg:province":"Gelderland",
    "wof:name":"Ass.Kantoor A.S.J. Diks",
    "wof:placetype":"venue"
},
  "geometry": {"coordinates":[5.196024,51.885635],"type":"Point"}
}