{
  "type": "Feature",
  "properties": {
    "addr:full":"Ooststraat 1 Sas Van Gent Zeeland 4551 CB",
    "addr:housenumber":"1",
    "addr:postcode":"4551 cb",
    "addr:street":"Ooststraat",
    "iso:country":"NL",
    "sg:address":"Ooststraat 1",
    "sg:city":"Sas Van Gent",
    "sg:classifiers":[
        {
            "category":"Fast Food",
            "type":"Food & Drink"
        }
    ],
    "sg:phone":"+31 115 451 892",
    "sg:postcode":"4551 CB",
    "sg:province":"Zeeland",
    "sg:tags":[
        "afhaal",
        "restaurant"
    ],
    "wof:name":"De Gastronoom Vof",
    "wof:placetype":"venue"
},
  "geometry": {"coordinates":[3.800933,51.227867],"type":"Point"}
}