{
  "type": "Feature",
  "properties": {
    "iso:country":"NL",
    "sg:address":"Gounodln 51",
    "sg:city":"Tilburg",
    "sg:orig_category":"Mode Artikelen Dames En Heren - Fabrieken En Groothandel",
    "sg:phone":"+31 6 51587958",
    "sg:postcode":"5049 AE",
    "sg:province":"North Brabant",
    "wof:name":"Janszen Bv",
    "wof:placetype":"venue"
},
  "geometry": {"coordinates":[5.07611,51.593761],"type":"Point"}
}