{
  "type": "Feature",
  "properties": {
    "addr:full":"Gounodln 51 Tilburg North Brabant 5049 AE",
    "addr:housenumber":"51",
    "addr:postcode":"5049 ae",
    "addr:street":"Gounodln",
    "iso:country":"NL",
    "sg:address":"Gounodln 51",
    "sg:city":"Tilburg",
    "sg:orig_category":"Mode Artikelen Dames En Heren - Fabrieken En Groothandel",
    "sg:phone":"+31 6 51587958",
    "sg:postcode":"5049 AE",
    "sg:province":"North Brabant",
    "wof:name":"Janszen Bv",
    "wof:placetype":"venue"
},
  "geometry": {"coordinates":[5.07611,51.593761],"type":"Point"}
}