{
  "type": "Feature",
  "properties": {
    "addr:full":"Oosterhamrikkd 84A Groningen Groningen 9714 BH",
    "addr:housenumber":"84a",
    "addr:postcode":"9714 bh",
    "addr:street":"Oosterhamrikkd",
    "iso:country":"NL",
    "sg:address":"Oosterhamrikkd 84A",
    "sg:city":"Groningen",
    "sg:orig_category":"Artiesten/Gezelschappen",
    "sg:phone":"+31 50 312 1455",
    "sg:postcode":"9714 BH",
    "sg:province":"Groningen",
    "wof:name":"Keus, K",
    "wof:placetype":"venue"
},
  "geometry": {"coordinates":[6.577017,53.230518],"type":"Point"}
}