{
  "type": "Feature",
  "properties": {
    "iso:country":"NL",
    "sg:address":"Hg Duin En D Wg 50",
    "sg:city":"Bloemendaal",
    "sg:orig_category":"Fotografie Reclame En Mode",
    "sg:phone":"+31 23 527 4400",
    "sg:postcode":"2061 AH",
    "sg:province":"North Holland",
    "wof:name":"Peeman, Ramon",
    "wof:placetype":"venue"
},
  "geometry": {"coordinates":[4.628374,52.409798],"type":"Point"}
}