{
  "type": "Feature",
  "properties": {
    "iso:country":"NL",
    "sg:address":"Ambachtstraat 11",
    "sg:city":"Meerkerk",
    "sg:orig_category":"Autokeuringen",
    "sg:phone":"+31 183 352 559",
    "sg:postcode":"4231 DP",
    "sg:province":"Zuid-Holland",
    "wof:name":"Vof Arie En Marco Van Noordenne",
    "wof:placetype":"venue"
},
  "geometry": {"coordinates":[4.989505,51.914749],"type":"Point"}
}