{
  "type": "Feature",
  "properties": {
    "addr:full":"Kerkstraat 34 Zuidbroek Groningen 9636 AC",
    "addr:housenumber":"34",
    "addr:postcode":"9636 ac",
    "addr:street":"Kerkstraat;Zuidbroek",
    "iso:country":"NL",
    "sg:address":"Kerkstraat 34",
    "sg:city":"Zuidbroek",
    "sg:orig_category":"Bloemen And Planten",
    "sg:phone":"+31 598 451 726",
    "sg:postcode":"9636 AC",
    "sg:province":"Groningen",
    "wof:name":"Bloemenhuis De Groot",
    "wof:placetype":"venue"
},
  "geometry": {"coordinates":[6.862841,53.163731],"type":"Point"}
}