{
  "type": "Feature",
  "properties": {
    "addr:full":"Hoofdstr 229 Oostwold Gem Leek Groningen 9828 PB",
    "addr:housenumber":"229",
    "addr:postcode":"9828 pb",
    "iso:country":"NL",
    "sg:address":"Hoofdstr 229",
    "sg:city":"Oostwold Gem Leek",
    "sg:orig_category":"Optiek - Fabrieken En Groothandel",
    "sg:phone":"+31 50 551 5200",
    "sg:postcode":"9828 PB",
    "sg:province":"Groningen",
    "sg:website":"http://www.optiplus.nl",
    "wof:name":"Optiplus Bv",
    "wof:placetype":"venue"
},
  "geometry": {"coordinates":[6.4394350052,53.2018432617],"type":"Point"}
}