{
  "type": "Feature",
  "properties": {
    "iso:country":"NL",
    "sg:address":"Alexandriet 2",
    "sg:city":"Heerhugowaard",
    "sg:classifiers":[
        {
            "category":"Personal",
            "subcategory":"Nail Salon",
            "type":"Services"
        }
    ],
    "sg:phone":"+31 72 571 1310",
    "sg:postcode":"1703 BM",
    "sg:province":"North Holland",
    "sg:tags":[
        "pedicure"
    ],
    "wof:name":"Vermaas, T H",
    "wof:placetype":"venue"
},
  "geometry": {"coordinates":[4.813992,52.660999],"type":"Point"}
}