{
  "type": "Feature",
  "properties": {
    "addr:full":"Einsteinln 379 Badhoevedorp North Holland 1171 VX",
    "addr:housenumber":"379",
    "addr:postcode":"1171 vx",
    "iso:country":"NL",
    "sg:address":"Einsteinln 379",
    "sg:city":"Badhoevedorp",
    "sg:orig_category":"Autopoetsbedrijven",
    "sg:phone":"+31 20 358 2243",
    "sg:postcode":"1171 VX",
    "sg:province":"North Holland",
    "wof:name":"Doets, Eddy L",
    "wof:placetype":"venue"
},
  "geometry": {"coordinates":[4.777002,52.341709],"type":"Point"}
}