{
  "type": "Feature",
  "properties": {
    "addr:full":"Zuidplasstr 4 Centr Mag Moerkapelle South Holland 2751 GN",
    "addr:housenumber":"4",
    "addr:postcode":"2751 gn",
    "addr:street":"Zuidplasstr",
    "iso:country":"NL",
    "sg:address":"Zuidplasstr 4 Centr Mag",
    "sg:city":"Moerkapelle",
    "sg:classifiers":[
        {
            "category":"Food & Beverages",
            "subcategory":"Fruits & Vegetables",
            "type":"Retail Goods"
        }
    ],
    "sg:phone":"+31 79 593 2151",
    "sg:postcode":"2751 GN",
    "sg:province":"South Holland",
    "sg:tags":[
        "en",
        "groenten"
    ],
    "wof:name":"Dijk, J Van",
    "wof:placetype":"venue"
},
  "geometry": {"coordinates":[4.57578,52.044224],"type":"Point"}
}