{
  "type": "Feature",
  "properties": {
    "iso:country":"NL",
    "sg:address":"Scheldestr 32",
    "sg:city":"Hengelo Ov",
    "sg:orig_category":"Adviesbureaus Bedrijfsorganisatie",
    "sg:phone":"+31 74 256 6115",
    "sg:postcode":"7555 WS",
    "sg:province":"Overijssel",
    "wof:name":"Blankestijn",
    "wof:placetype":"venue"
},
  "geometry": {"coordinates":[6.762755,52.260277],"type":"Point"}
}