{
  "type": "Feature",
  "properties": {
    "addr:full":"Nieuwe Veenendaalseweg 227 Rhenen Utrecht 3911 MJ",
    "addr:housenumber":"227",
    "addr:postcode":"3911 mj",
    "addr:street":"Nieuwe Veenendaalseweg",
    "iso:country":"NL",
    "sg:address":"Nieuwe Veenendaalseweg 227",
    "sg:city":"Rhenen",
    "sg:orig_category":"Kampeerterreinen",
    "sg:phone":"+31 317 612 384",
    "sg:postcode":"3911 MJ",
    "sg:province":"Utrecht",
    "wof:name":"Recreatiecentrum De Thijmse Berg Bv",
    "wof:placetype":"venue"
},
  "geometry": {"coordinates":[5.5644488335,51.9739303589],"type":"Point"}
}