{
  "type": "Feature",
  "properties": {
    "iso:country":"NL",
    "sg:address":"Rozenstr 67",
    "sg:city":"Didam",
    "sg:orig_category":"Autorijscholen",
    "sg:phone":"+31 316 221 111",
    "sg:postcode":"6942 WG",
    "sg:province":"Gelderland",
    "wof:name":"Bridel, B",
    "wof:placetype":"venue"
},
  "geometry": {"coordinates":[6.135763,51.944447],"type":"Point"}
}