{
  "type": "Feature",
  "properties": {
    "addr:full":"Berkelstr 47 Amersfoort Utrecht 3812 KB",
    "addr:housenumber":"47",
    "addr:postcode":"3812 kb",
    "addr:street":"Berkelstr",
    "iso:country":"NL",
    "sg:address":"Berkelstr 47",
    "sg:city":"Amersfoort",
    "sg:orig_category":"Webdesign Bureaus",
    "sg:phone":"+31 33 463 8233",
    "sg:postcode":"3812 KB",
    "sg:province":"Utrecht",
    "sg:website":"http://www.thecrackerjack.nl",
    "wof:name":"Crackerjack",
    "wof:placetype":"venue"
},
  "geometry": {"coordinates":[5.3643631935,52.1617279053],"type":"Point"}
}