{
  "type": "Feature",
  "properties": {
    "iso:country":"NL",
    "sg:address":"Vleesstr 73",
    "sg:city":"Venlo",
    "sg:orig_category":"Opticiens",
    "sg:phone":"+31 77 351 4075",
    "sg:postcode":"5911 JD",
    "sg:province":"Limburg",
    "wof:name":"Maaren, Carl Van",
    "wof:placetype":"venue"
},
  "geometry": {"coordinates":[6.1678910255,51.3681030273],"type":"Point"}
}