{
  "type": "Feature",
  "properties": {
    "iso:country":"NL",
    "sg:address":"N Sluisstr 70",
    "sg:city":"Hem",
    "sg:orig_category":"Webdesign Bureaus",
    "sg:phone":"+31 6 21803039",
    "sg:postcode":"1607 CT",
    "sg:province":"Georgia",
    "sg:website":"http://www.tenzon.nl",
    "wof:name":"Tenzon",
    "wof:placetype":"venue"
},
  "geometry": {"coordinates":[-84.1719207764,34.8905563354],"type":"Point"}
}