{
  "type": "Feature",
  "properties": {
    "addr:full":"Nieuwenhuyzenstr 38A Breda Noord-Brabant 4818 RJ",
    "addr:housenumber":"38a",
    "addr:postcode":"4818 rj",
    "addr:street":"Nieuwenhuyzenstr",
    "iso:country":"NL",
    "sg:address":"Nieuwenhuyzenstr 38A",
    "sg:city":"Breda",
    "sg:orig_category":"Adviesbureaus Bedrijfsorganisatie",
    "sg:phone":"+31 76 522 8311",
    "sg:postcode":"4818 RJ",
    "sg:province":"Noord-Brabant",
    "wof:name":"Executive Consult Bv",
    "wof:placetype":"venue"
},
  "geometry": {"coordinates":[4.774495,51.578323],"type":"Point"}
}