{
  "type": "Feature",
  "properties": {
    "addr:full":"Daslook 7 Lochem Gelderland 7242 MC",
    "addr:housenumber":"7;7242",
    "addr:street":"Daslook;Gelderland;Mc",
    "iso:country":"NL",
    "sg:address":"Daslook 7",
    "sg:city":"Lochem",
    "sg:orig_category":"Bedrijfsopleidingen",
    "sg:phone":"+31 573 259 183",
    "sg:postcode":"7242 MC",
    "sg:province":"Gelderland",
    "wof:name":"Comsupport",
    "wof:placetype":"venue"
},
  "geometry": {"coordinates":[6.395788,52.151852],"type":"Point"}
}