{
  "type": "Feature",
  "properties": {
    "addr:full":"Pr Hendrikln 16 Utrecht Utrecht 3583 EM",
    "addr:housenumber":"16",
    "addr:postcode":"3583 em",
    "iso:country":"NL",
    "sg:address":"Pr Hendrikln 16",
    "sg:city":"Utrecht",
    "sg:orig_category":"Architecten En Architectenbureaus",
    "sg:phone":"+31 30 252 3585",
    "sg:postcode":"3583 EM",
    "sg:province":"Utrecht",
    "wof:name":"Werkplaats Voor Architektuur",
    "wof:placetype":"venue"
},
  "geometry": {"coordinates":[5.14349,52.08662],"type":"Point"}
}