{
  "type": "Feature",
  "properties": {
    "iso:country":"NL",
    "sg:address":"Heerewaardensestraat 14",
    "sg:city":"Heerewaarden",
    "sg:orig_category":"Autokeuringen",
    "sg:phone":"+31 487 572 463",
    "sg:postcode":"6624 KK",
    "sg:province":"Gelderland",
    "wof:name":"Autohandel W. Van Mourik",
    "wof:placetype":"venue"
},
  "geometry": {"coordinates":[5.400328,51.822617],"type":"Point"}
}