{
  "type": "Feature",
  "properties": {
    "addr:full":"Dr A Ariensstr 1 Steenderen Gelderland 7221 CA",
    "addr:housenumber":"1",
    "addr:postcode":"7221 ca",
    "addr:street":"Dr;Ariensstr;Gelderland",
    "iso:country":"NL",
    "sg:address":"Dr A Ariensstr 1",
    "sg:city":"Steenderen",
    "sg:orig_category":"Zalenverhuur",
    "sg:phone":"+31 575 451 203",
    "sg:postcode":"7221 CA",
    "sg:province":"Gelderland",
    "wof:name":"Engel, De",
    "wof:placetype":"venue"
},
  "geometry": {"coordinates":[-119.270203,37.271832],"type":"Point"}
}