{
  "type": "Feature",
  "properties": {
    "iso:country":"NL",
    "sg:address":"Gulbergsven 3",
    "sg:city":"Eindhoven",
    "sg:orig_category":"Adviesbureaus",
    "sg:phone":"+31 40 293 0823",
    "sg:postcode":"5645 KK",
    "sg:province":"Noord-Brabant",
    "wof:name":"Beekum, J C Van",
    "wof:placetype":"venue"
},
  "geometry": {"coordinates":[5.516398,51.420971],"type":"Point"}
}