{
  "type": "Feature",
  "properties": {
    "iso:country":"NL",
    "sg:address":"Pr Bernhardstr 2B",
    "sg:city":"Leeuwarden",
    "sg:orig_category":"Verzekeringen - Verzekeringskantoren",
    "sg:phone":"+31 58 288 4533",
    "sg:postcode":"8931 DJ",
    "sg:province":"Friesland",
    "wof:name":"Sipkens, J J",
    "wof:placetype":"venue"
},
  "geometry": {"coordinates":[5.795584,53.186024],"type":"Point"}
}