{
  "type": "Feature",
  "properties": {
    "addr:full":"Havelterschans 11 Nieuwegein Utrecht 3432 TW",
    "addr:housenumber":"11",
    "addr:postcode":"3432 tw",
    "addr:street":"Havelterschans",
    "iso:country":"NL",
    "sg:address":"Havelterschans 11",
    "sg:city":"Nieuwegein",
    "sg:orig_category":"Bedrijfsopleidingen",
    "sg:phone":"+31 30 601 8987",
    "sg:postcode":"3432 TW",
    "sg:province":"Utrecht",
    "wof:name":"Authentic Coaching",
    "wof:placetype":"venue"
},
  "geometry": {"coordinates":[5.092129,52.017193],"type":"Point"}
}