{
  "type": "Feature",
  "properties": {
    "iso:country":"NL",
    "sg:address":"Galileistr 34",
    "sg:city":"Heerhugowaard",
    "sg:orig_category":"Meubelen - Fabrieken En Groothandel",
    "sg:phone":"+31 72 574 5999",
    "sg:postcode":"1704 SE",
    "sg:province":"North Holland",
    "wof:name":"Zapp Bv",
    "wof:placetype":"venue"
},
  "geometry": {"coordinates":[4.82814,52.68898],"type":"Point"}
}