{
  "type": "Feature",
  "properties": {
    "addr:full":"Hoofdweg 80 Siddeburen Groningen 9628 CR",
    "addr:housenumber":"80",
    "addr:postcode":"9628 cr",
    "addr:street":"Hoofdweg",
    "iso:country":"NL",
    "sg:address":"Hoofdweg 80",
    "sg:city":"Siddeburen",
    "sg:orig_category":"Autokeuringen",
    "sg:phone":"+31 598 431 721",
    "sg:postcode":"9628 CR",
    "sg:province":"Groningen",
    "wof:name":"Autobedrijf Walma",
    "wof:placetype":"venue"
},
  "geometry": {"coordinates":[6.858006,53.246998],"type":"Point"}
}