{
  "type": "Feature",
  "properties": {
    "addr:full":"Molendk 87 Oud Beyerland Zuid-Holland 3262 AJ",
    "addr:housenumber":"87",
    "addr:postcode":"3262 aj",
    "addr:street":"Molendk;Oud Beyerland",
    "iso:country":"NL",
    "sg:address":"Molendk 87",
    "sg:city":"Oud Beyerland",
    "sg:orig_category":"Grafisch Ontwerpers",
    "sg:phone":"+31 186 623 253",
    "sg:postcode":"3262 AJ",
    "sg:province":"Zuid-Holland",
    "sg:website":"http://www.chimedia.nl",
    "wof:name":"Chimedia",
    "wof:placetype":"venue"
},
  "geometry": {"coordinates":[4.407424,51.827053],"type":"Point"}
}