{
  "type": "Feature",
  "properties": {
    "addr:full":"Jan Oldenburglaan 14 Bergen Nh Noord-Holland 1861 JT",
    "addr:housenumber":"14",
    "addr:postcode":"1861 jt",
    "addr:street":"Jan Oldenburglaan",
    "iso:country":"NL",
    "sg:address":"Jan Oldenburglaan 14",
    "sg:city":"Bergen Nh",
    "sg:classifiers":[
        {
            "category":"Food & Beverages",
            "subcategory":"Fruits & Vegetables",
            "type":"Retail Goods"
        }
    ],
    "sg:phone":"+31 72 581 2323",
    "sg:postcode":"1861 JT",
    "sg:province":"Noord-Holland",
    "sg:tags":[
        "groenten"
    ],
    "wof:name":"Drieluik Bezorgservice Het",
    "wof:placetype":"venue"
},
  "geometry": {"coordinates":[4.70248,52.670452],"type":"Point"}
}