{
  "type": "Feature",
  "properties": {
    "addr:full":"Vleugeltjesbloem 24 Castricum Noord-Holland 1902 GJ",
    "addr:housenumber":"24",
    "addr:postcode":"1902 gj",
    "addr:street":"Vleugeltjesbloem",
    "iso:country":"NL",
    "sg:address":"Vleugeltjesbloem 24",
    "sg:city":"Castricum",
    "sg:orig_category":"Verzekeringen",
    "sg:phone":"+31 251 654 448",
    "sg:postcode":"1902 GJ",
    "sg:province":"Noord-Holland",
    "wof:name":"Hans Mol Verzekeringen",
    "wof:placetype":"venue"
},
  "geometry": {"coordinates":[4.681562,52.552296],"type":"Point"}
}