{
  "type": "Feature",
  "properties": {
    "addr:full":"Heemraadssingel 90 Rotterdam Zuid-Holland 3021 DE",
    "addr:housenumber":"90",
    "addr:postcode":"3021 de",
    "addr:street":"Heemraadssingel",
    "iso:country":"NL",
    "sg:address":"Heemraadssingel 90",
    "sg:city":"Rotterdam",
    "sg:classifiers":[
        {
            "category":"Travel",
            "subcategory":"Hotels & Motels",
            "type":"Entertainment"
        }
    ],
    "sg:phone":"+31 10 477 5461",
    "sg:postcode":"3021 DE",
    "sg:province":"Zuid-Holland",
    "wof:name":"Hotel Heemraad",
    "wof:placetype":"venue"
},
  "geometry": {"coordinates":[4.45607,51.919067],"type":"Point"}
}