{
  "type": "Feature",
  "properties": {
    "addr:full":"Wilhelminastraat 44 Arnhem Gelderland 6812 CW",
    "addr:housenumber":"44",
    "addr:postcode":"6812 cw",
    "addr:street":"Wilhelminastraat",
    "iso:country":"NL",
    "sg:address":"Wilhelminastraat 44",
    "sg:city":"Arnhem",
    "sg:orig_category":"Muziekinstrumenten",
    "sg:phone":"+31 26 351 1632",
    "sg:postcode":"6812 CW",
    "sg:province":"Gelderland",
    "wof:name":"Muziek Het Eiland",
    "wof:placetype":"venue"
},
  "geometry": {"coordinates":[5.879386,51.983719],"type":"Point"}
}