{
  "type": "Feature",
  "properties": {
    "addr:full":"Julianaplnts 148 Diemen North Holland 1111 XV",
    "addr:housenumber":"148",
    "addr:postcode":"1111 xv",
    "iso:country":"NL",
    "sg:address":"Julianaplnts 148",
    "sg:city":"Diemen",
    "sg:orig_category":"Logopedisten",
    "sg:phone":"+31 20 690 2257",
    "sg:postcode":"1111 XV",
    "sg:province":"North Holland",
    "wof:name":"Mens, L J Van",
    "wof:placetype":"venue"
},
  "geometry": {"coordinates":[4.964805,52.34132],"type":"Point"}
}