{
  "type": "Feature",
  "properties": {
    "addr:full":"Stationsstraat 3 Haaksbergen NL.08 7481 JA",
    "addr:housenumber":"3;nl.08",
    "addr:postcode":"7481 ja",
    "addr:street":"Stationsstraat",
    "iso:country":"NL",
    "sg:address":"Stationsstraat 3",
    "sg:city":"Haaksbergen",
    "sg:orig_category":"Musea And Historische Gebouwen",
    "sg:phone":"+31 53 572 1516",
    "sg:postcode":"7481 JA",
    "sg:province":"NL.08",
    "wof:name":"Museum Buurt Spoorweg",
    "wof:placetype":"venue"
},
  "geometry": {"coordinates":[6.738227,52.158344],"type":"Point"}
}