{
  "type": "Feature",
  "properties": {
    "addr:full":"Donaustraat 176 Lelystad Flevoland 8226 LC",
    "addr:housenumber":"176",
    "addr:postcode":"8226 lc",
    "addr:street":"Donaustraat;Flevoland",
    "iso:country":"NL",
    "sg:address":"Donaustraat 176",
    "sg:city":"Lelystad",
    "sg:orig_category":"Diverse Grafische Activiteiten",
    "sg:phone":"+31 320 256 897",
    "sg:postcode":"8226 LC",
    "sg:province":"Flevoland",
    "wof:name":"Van Der Eijk Grafisch Ontwerp",
    "wof:placetype":"venue"
},
  "geometry": {"coordinates":[5.493657,52.489601],"type":"Point"}
}