{
  "type": "Feature",
  "properties": {
    "addr:full":"Brouwerij 61 Amstelveen North Holland 1185 XW",
    "addr:housenumber":"61",
    "addr:postcode":"1185 xw",
    "addr:street":"Brouwerij",
    "iso:country":"NL",
    "sg:address":"Brouwerij 61",
    "sg:city":"Amstelveen",
    "sg:orig_category":"Autoverhuur",
    "sg:phone":"+31 20 643 4740",
    "sg:postcode":"1185 XW",
    "sg:province":"North Holland",
    "sg:website":"http://www.budget.nl http://www.bugdet.nl",
    "wof:name":"Budget Rent A Car",
    "wof:placetype":"venue"
},
  "geometry": {"coordinates":[4.83874,52.282223],"type":"Point"}
}