{
  "type": "Feature",
  "properties": {
    "iso:country":"NL",
    "sg:address":"C De Vrieseln 136",
    "sg:city":"Rotterdam",
    "sg:orig_category":"Marktonderzoekbureaus",
    "sg:phone":"+31 10 425 3685",
    "sg:postcode":"3021 JX",
    "sg:province":"South Holland",
    "wof:name":"Cimart",
    "wof:placetype":"venue"
},
  "geometry": {"coordinates":[4.45925,51.916531],"type":"Point"}
}