{
  "type": "Feature",
  "properties": {
    "addr:full":"Straatwg 185 Rotterdam Zuid-Holland 3054 AD",
    "addr:housenumber":"185",
    "addr:postcode":"3054 ad",
    "iso:country":"NL",
    "sg:address":"Straatwg 185",
    "sg:city":"Rotterdam",
    "sg:orig_category":"Artsen - Huisartsen",
    "sg:phone":"+31 10 418 5560",
    "sg:postcode":"3054 AD",
    "sg:province":"Zuid-Holland",
    "wof:name":"Herman, E M",
    "wof:placetype":"venue"
},
  "geometry": {"coordinates":[4.489591,51.952087],"type":"Point"}
}