{
  "type": "Feature",
  "properties": {
    "addr:full":"Erve Oldenhof 64 Enter Overijssel 7468 JB",
    "addr:housenumber":"64",
    "addr:postcode":"7468 jb",
    "addr:street":"Erve Oldenhof",
    "iso:country":"NL",
    "sg:address":"Erve Oldenhof 64",
    "sg:city":"Enter",
    "sg:orig_category":"Autokeuringen",
    "sg:phone":"+31 547 383 198",
    "sg:postcode":"7468 JB",
    "sg:province":"Overijssel",
    "wof:name":"H. Asbroek",
    "wof:placetype":"venue"
},
  "geometry": {"coordinates":[-76.841904,40.463078],"type":"Point"}
}