{
  "type": "Feature",
  "properties": {
    "addr:full":"Reddingswg 38 Schiermonnikoog Provincie Friesland 9166 PD",
    "addr:housenumber":"38",
    "addr:postcode":"9166 pd",
    "addr:street":"Reddingswg;Provincie Friesland",
    "iso:country":"NL",
    "sg:address":"Reddingswg 38",
    "sg:city":"Schiermonnikoog",
    "sg:orig_category":"Kaas",
    "sg:phone":"+31 519 531 477",
    "sg:postcode":"9166 PD",
    "sg:province":"Provincie Friesland",
    "wof:name":"Florida Kaasboerderij",
    "wof:placetype":"venue"
},
  "geometry": {"coordinates":[6.171184063,53.4820213318],"type":"Point"}
}