{
  "type": "Feature",
  "properties": {
    "addr:full":"Kerkenbos 1228B Nymegen Gelderland 6546 BE",
    "addr:housenumber":"1228b",
    "addr:postcode":"6546",
    "addr:street":"Kerkenbos;Gelderland",
    "iso:country":"NL",
    "sg:address":"Kerkenbos 1228B",
    "sg:city":"Nymegen",
    "sg:orig_category":"Adviesbureaus",
    "sg:phone":"+31 24 358 3996",
    "sg:postcode":"6546 BE",
    "sg:province":"Gelderland",
    "sg:website":"http://www.ir-search.nl",
    "wof:name":"Ir Search",
    "wof:placetype":"venue"
},
  "geometry": {"coordinates":[4.47677,50.500992],"type":"Point"}
}