{
  "type": "Feature",
  "properties": {
    "addr:full":"Pieter Calandlaan 13 Amsterdam North Holland 1065 KH",
    "addr:housenumber":"13",
    "addr:postcode":"1065 kh",
    "addr:street":"Pieter Calandlaan",
    "iso:country":"NL",
    "sg:address":"Pieter Calandlaan 13",
    "sg:city":"Amsterdam",
    "sg:orig_category":"Werving And Selectie Van Tijdelijk Personeel And Uitzendkantoren",
    "sg:phone":"+31 20 617 8866",
    "sg:postcode":"1065 KH",
    "sg:province":"North Holland",
    "wof:name":"Start",
    "wof:placetype":"venue"
},
  "geometry": {"coordinates":[4.8300681114,52.3561172485],"type":"Point"}
}