{
  "type": "Feature",
  "properties": {
    "iso:country":"NL",
    "sg:address":"Nw Waterwegstr 29",
    "sg:city":"Schiedam",
    "sg:orig_category":"On- Offshore",
    "sg:phone":"+31 10 246 6666",
    "sg:postcode":"3115 HE",
    "sg:province":"Zuid-Holland",
    "wof:name":"Emc Ned Bv",
    "wof:placetype":"venue"
},
  "geometry": {"coordinates":[4.39076,51.90073],"type":"Point"}
}