{
  "type": "Feature",
  "properties": {
    "addr:full":"Beverhof 14 Beverwijk North Holland 1941 EC",
    "addr:housenumber":"14",
    "addr:postcode":"1941 ec",
    "addr:street":"Beverhof",
    "iso:country":"NL",
    "sg:address":"Beverhof 14",
    "sg:city":"Beverwijk",
    "sg:orig_category":"Wasserettes And Stomerijen",
    "sg:phone":"+31 251 221 462",
    "sg:postcode":"1941 EC",
    "sg:province":"North Holland",
    "wof:name":"Palthe Stomerijen Bv",
    "wof:placetype":"venue"
},
  "geometry": {"coordinates":[4.6571011543,52.4865226746],"type":"Point"}
}