{
  "type": "Feature",
  "properties": {
    "iso:country":"NL",
    "sg:address":"Regenwulp 10",
    "sg:city":"Goirle",
    "sg:orig_category":"Adviesbureaus Financieel",
    "sg:phone":"+31 13 530 0613",
    "sg:postcode":"5052 WB",
    "sg:province":"Noord-Brabant",
    "wof:name":"Sarenne Consultancy Bv",
    "wof:placetype":"venue"
},
  "geometry": {"coordinates":[5.045087,51.517746],"type":"Point"}
}