{
  "type": "Feature",
  "properties": {
    "addr:full":"Oude Maasweg 11 Rotterdam South Holland 3197 KJ",
    "addr:housenumber":"11",
    "addr:postcode":"3197 kj",
    "addr:street":"Oude Maasweg",
    "iso:country":"NL",
    "sg:address":"Oude Maasweg 11",
    "sg:city":"Rotterdam",
    "sg:classifiers":[
        {
            "category":"Retail",
            "subcategory":"Storage",
            "type":"Services"
        }
    ],
    "sg:phone":"+31 10 438 7366",
    "sg:postcode":"3197 KJ",
    "sg:province":"South Holland",
    "sg:tags":[
        "opslag",
        "bewaring"
    ],
    "wof:name":"Cetem Containers",
    "wof:placetype":"venue"
},
  "geometry": {"coordinates":[4.3208122253,51.8806343079],"type":"Point"}
}