{
  "type": "Feature",
  "properties": {
    "addr:full":"Turkse Tuin 1 Rotterdam Zuid-Holland 3078 EZ",
    "addr:housenumber":"1",
    "addr:postcode":"3078 ez",
    "addr:street":"Turkse Tuin",
    "iso:country":"NL",
    "sg:address":"Turkse Tuin 1",
    "sg:city":"Rotterdam",
    "sg:orig_category":"Plafonds",
    "sg:phone":"+31 10 479 5424",
    "sg:postcode":"3078 EZ",
    "sg:province":"Zuid-Holland",
    "wof:name":"Drenth Bv, A S",
    "wof:placetype":"venue"
},
  "geometry": {"coordinates":[4.555125,51.892857],"type":"Point"}
}