{
  "type": "Feature",
  "properties": {
    "addr:full":"Morelstraat 44 Rockanje South Holland 3235 EL",
    "addr:housenumber":"44",
    "addr:postcode":"3235 el",
    "addr:street":"Morelstraat",
    "iso:country":"NL",
    "sg:address":"Morelstraat 44",
    "sg:city":"Rockanje",
    "sg:orig_category":"Vaste And Vloeibare Brandstoffen",
    "sg:phone":"+31 181 402 522",
    "sg:postcode":"3235 EL",
    "sg:province":"South Holland",
    "wof:name":"Holland Gas",
    "wof:placetype":"venue"
},
  "geometry": {"coordinates":[4.069173,51.866867],"type":"Point"}
}