{
  "type": "Feature",
  "properties": {
    "addr:full":"Frambozenweg 157 Leiden Zuid-Holland 2321 KA",
    "addr:housenumber":"157",
    "addr:postcode":"2321 ka",
    "addr:street":"Frambozenweg",
    "iso:country":"NL",
    "sg:address":"Frambozenweg 157",
    "sg:city":"Leiden",
    "sg:orig_category":"Marktonderzoekbureaus",
    "sg:phone":"+31 71 573 0657",
    "sg:postcode":"2321 KA",
    "sg:province":"Zuid-Holland",
    "wof:name":"Scs Statistical Consultancy & Support",
    "wof:placetype":"venue"
},
  "geometry": {"coordinates":[4.488551,52.147133],"type":"Point"}
}