{
  "type": "Feature",
  "properties": {
    "addr:full":"Ten Oeverstraat 68 Zwolle Overijssel 8012 EW",
    "addr:housenumber":"68",
    "addr:postcode":"8012 ew",
    "addr:street":"Ten Oeverstraat",
    "iso:country":"NL",
    "sg:address":"Ten Oeverstraat 68",
    "sg:city":"Zwolle",
    "sg:orig_category":"Hoger Onderwijs",
    "sg:phone":"+31 38 421 7425",
    "sg:postcode":"8012 EW",
    "sg:province":"Overijssel",
    "wof:name":"Katholieke Pabo Zwolle",
    "wof:placetype":"venue"
},
  "geometry": {"coordinates":[6.107329,52.506264],"type":"Point"}
}