{
  "type": "Feature",
  "properties": {
    "addr:full":"Makadocenter 27 Nieuwegein Utrecht 3431 AW",
    "addr:housenumber":"27",
    "addr:postcode":"3431 aw",
    "addr:street":"Makadocenter",
    "iso:country":"NL",
    "sg:address":"Makadocenter 27",
    "sg:city":"Nieuwegein",
    "sg:orig_category":"Kappers",
    "sg:phone":"+31 30 603 1828",
    "sg:postcode":"3431 AW",
    "sg:province":"Utrecht",
    "wof:name":"Princess",
    "wof:placetype":"venue"
},
  "geometry": {"coordinates":[5.082434,52.033756],"type":"Point"}
}