{
  "type": "Feature",
  "properties": {
    "addr:full":"Steenhouwerslaan 19 Voorthuizen Gelderland 3781 WP",
    "addr:housenumber":"19",
    "addr:postcode":"3781 wp",
    "addr:street":"Steenhouwerslaan;Gelderland",
    "iso:country":"NL",
    "sg:address":"Steenhouwerslaan 19",
    "sg:city":"Voorthuizen",
    "sg:orig_category":"Diverse Bedrijfsinstallaties Gh",
    "sg:phone":"+31 342 475 201",
    "sg:postcode":"3781 WP",
    "sg:province":"Gelderland",
    "wof:name":"Milltech",
    "wof:placetype":"venue"
},
  "geometry": {"coordinates":[5.589974,52.184723],"type":"Point"}
}