{
  "type": "Feature",
  "properties": {
    "addr:full":"Overschiesewg 25 Rotterdam South Holland 3044 EE",
    "addr:housenumber":"25",
    "addr:postcode":"3044 ee",
    "addr:street":"Overschiesewg",
    "iso:country":"NL",
    "sg:address":"Overschiesewg 25",
    "sg:city":"Rotterdam",
    "sg:orig_category":"Zalenverhuur",
    "sg:phone":"+31 10 415 1301",
    "sg:postcode":"3044 EE",
    "sg:province":"South Holland",
    "sg:website":"http://www.doelarie.nl",
    "wof:name":"Doelarie",
    "wof:placetype":"venue"
},
  "geometry": {"coordinates":[4.414407,51.936977],"type":"Point"}
}