{
  "type": "Feature",
  "properties": {
    "addr:full":"D Oultremontweg 16 Elshout North Brabant 5154 PD",
    "addr:housenumber":"16",
    "addr:postcode":"5154 pd",
    "iso:country":"NL",
    "sg:address":"D Oultremontweg 16",
    "sg:city":"Elshout",
    "sg:orig_category":"Fruit And Groenten Gh",
    "sg:phone":"+31 416 373 948",
    "sg:postcode":"5154 PD",
    "sg:province":"North Brabant",
    "wof:name":"Kivits Drunen Bv",
    "wof:placetype":"venue"
},
  "geometry": {"coordinates":[5.162745,51.700245],"type":"Point"}
}