{
  "type": "Feature",
  "properties": {
    "addr:full":"Stationsstr 71 Ryen North Brabant 5121 EC",
    "addr:housenumber":"71",
    "addr:postcode":"5121 ec",
    "addr:street":"Stationsstr",
    "iso:country":"NL",
    "sg:address":"Stationsstr 71",
    "sg:city":"Ryen",
    "sg:orig_category":"Kappers",
    "sg:phone":"+31 161 226 379",
    "sg:postcode":"5121 EC",
    "sg:province":"North Brabant",
    "wof:name":"Coiffure House",
    "wof:placetype":"venue"
},
  "geometry": {"coordinates":[4.9197001457,51.58801651],"type":"Point"}
}