{
  "type": "Feature",
  "properties": {
    "addr:full":"Rietveldenweg 41 'S-Hertogenbosch Noord-Brabant 5222 AP",
    "addr:housenumber":"41",
    "addr:postcode":"5222 ap",
    "addr:street":"Rietveldenweg",
    "iso:country":"NL",
    "sg:address":"Rietveldenweg 41",
    "sg:city":"'S-Hertogenbosch",
    "sg:orig_category":"Telecommunicatie - Apparatuur",
    "sg:phone":"+31 73 627 1212",
    "sg:postcode":"5222 AP",
    "sg:province":"Noord-Brabant",
    "wof:name":"Cellstar",
    "wof:placetype":"venue"
},
  "geometry": {"coordinates":[5.271287,51.703686],"type":"Point"}
}