{
  "type": "Feature",
  "properties": {
    "iso:country":"NL",
    "sg:address":"Molenstr 50A",
    "sg:city":"Lochem",
    "sg:orig_category":"Adviesbureaus Bedrijfsorganisatie",
    "sg:phone":"+31 573 253 774",
    "sg:postcode":"7241 AE",
    "sg:province":"Gelderland",
    "sg:website":"http://www.bowergroup.com",
    "wof:name":"Bower Group, The",
    "wof:placetype":"venue"
},
  "geometry": {"coordinates":[6.41741,52.162411],"type":"Point"}
}