{
  "type": "Feature",
  "properties": {
    "addr:full":"Mercuriuswg 23 Waddinxveen Zuid-Holland 2741 TB",
    "addr:housenumber":"23",
    "addr:postcode":"2741 tb",
    "addr:street":"Mercuriuswg",
    "iso:country":"NL",
    "sg:address":"Mercuriuswg 23",
    "sg:city":"Waddinxveen",
    "sg:classifiers":[
        {
            "category":"Retail",
            "subcategory":"Auto Repair",
            "type":"Services"
        }
    ],
    "sg:phone":"+31 182 617 204",
    "sg:postcode":"2741 TB",
    "sg:province":"Zuid-Holland",
    "sg:tags":[
        "garage"
    ],
    "wof:name":"Klaveren, A D Van",
    "wof:placetype":"venue"
},
  "geometry": {"coordinates":[4.654579,52.033417],"type":"Point"}
}