{
  "type": "Feature",
  "properties": {
    "addr:full":"Nw Uilenburgerstr 5 Amsterdam Noord-Holland 1011 LM",
    "addr:housenumber":"5",
    "addr:postcode":"1011 lm",
    "addr:street":"Uilenburgerstr",
    "iso:country":"NL",
    "sg:address":"Nw Uilenburgerstr 5",
    "sg:city":"Amsterdam",
    "sg:orig_category":"Meubelmakerijen",
    "sg:phone":"+31 20 642 8200",
    "sg:postcode":"1011 LM",
    "sg:province":"Noord-Holland",
    "wof:name":"Aha",
    "wof:placetype":"venue"
},
  "geometry": {"coordinates":[4.904954,52.37001],"type":"Point"}
}