{
  "type": "Feature",
  "properties": {
    "addr:full":"V Maasdykstr 39 Heerenveen Provincie Friesland 8441 CK",
    "addr:housenumber":"39",
    "addr:postcode":"8441 ck",
    "addr:street":"Provincie Friesland",
    "iso:country":"NL",
    "sg:address":"V Maasdykstr 39",
    "sg:city":"Heerenveen",
    "sg:orig_category":"Kappers",
    "sg:phone":"+31 513 625 807",
    "sg:postcode":"8441 CK",
    "sg:province":"Provincie Friesland",
    "wof:name":"Jalving",
    "wof:placetype":"venue"
},
  "geometry": {"coordinates":[5.9290947914,52.9584503174],"type":"Point"}
}