{
  "type": "Feature",
  "properties": {
    "addr:full":"Veldlust 5 Amstelveen North Holland 1188 JK",
    "addr:housenumber":"5",
    "addr:postcode":"1188 jk",
    "addr:street":"Veldlust",
    "iso:country":"NL",
    "sg:address":"Veldlust 5",
    "sg:city":"Amstelveen",
    "sg:orig_category":"Boekhouders",
    "sg:phone":"+31 20 640 7167",
    "sg:postcode":"1188 JK",
    "sg:province":"North Holland",
    "wof:name":"Bkv & Partners Bv",
    "wof:placetype":"venue"
},
  "geometry": {"coordinates":[4.843368,52.282608],"type":"Point"}
}