{
  "type": "Feature",
  "properties": {
    "addr:full":"Zuivelstr 20 Veenendaal Utrecht 3903 AE",
    "addr:housenumber":"20",
    "addr:postcode":"3903 ae",
    "addr:street":"Zuivelstr",
    "iso:country":"NL",
    "sg:address":"Zuivelstr 20",
    "sg:city":"Veenendaal",
    "sg:orig_category":"Verhuur",
    "sg:phone":"+31 318 512 195",
    "sg:postcode":"3903 AE",
    "sg:province":"Utrecht",
    "sg:website":"http://www.pietervalkenburg.nl",
    "wof:name":"Pieter Valkenburg Party Verhuur",
    "wof:placetype":"venue"
},
  "geometry": {"coordinates":[5.551655,52.018112],"type":"Point"}
}