{
  "type": "Feature",
  "properties": {
    "addr:full":"Nisseweg 4 Kruiningen Zeeland 4416 PK",
    "addr:housenumber":"4",
    "addr:postcode":"4416 pk",
    "addr:street":"Nisseweg",
    "iso:country":"NL",
    "sg:address":"Nisseweg 4",
    "sg:city":"Kruiningen",
    "sg:orig_category":"Werving And Selectie Van Tijdelijk Personeel And Uitzendkantoren",
    "sg:phone":"+31 113 322 355",
    "sg:postcode":"4416 PK",
    "sg:province":"Zeeland",
    "wof:name":"H.B. Jansen Uienhandel Bv",
    "wof:placetype":"venue"
},
  "geometry": {"coordinates":[4.0340008736,51.4590606689],"type":"Point"}
}