{
  "type": "Feature",
  "properties": {
    "addr:full":"Gijsbrecht Van Amstelstr 94 Hilversum North Holland 1214 BB",
    "addr:housenumber":"94",
    "addr:postcode":"1214 bb",
    "addr:street":"Gijsbrecht Van Amstelstr",
    "iso:country":"NL",
    "sg:address":"Gijsbrecht Van Amstelstr 94",
    "sg:city":"Hilversum",
    "sg:orig_category":"Autokeuringen",
    "sg:phone":"+31 35 621 2948",
    "sg:postcode":"1214 BB",
    "sg:province":"North Holland",
    "wof:name":"Firma C.J. Van Der Meer En Zonen",
    "wof:placetype":"venue"
},
  "geometry": {"coordinates":[5.172551,52.215912],"type":"Point"}
}