{
  "type": "Feature",
  "properties": {
    "addr:full":"Sijlweg 6 Werkendam Noord-Brabant 4251 NS",
    "addr:housenumber":"6",
    "addr:postcode":"4251 ns",
    "addr:street":"Sijlweg",
    "iso:country":"NL",
    "sg:address":"Sijlweg 6",
    "sg:city":"Werkendam",
    "sg:orig_category":"Algemene Werktuigbouw",
    "sg:phone":"+31 183 502 897",
    "sg:postcode":"4251 NS",
    "sg:province":"Noord-Brabant",
    "wof:name":"R. Van Andel",
    "wof:placetype":"venue"
},
  "geometry": {"coordinates":[4.882531,51.808014],"type":"Point"}
}