{
  "type": "Feature",
  "properties": {
    "addr:full":"Hanzestr 7 Maasbommel North Brabant 6627 AP",
    "addr:housenumber":"7",
    "addr:postcode":"6627 ap",
    "addr:street":"Hanzestr",
    "iso:country":"NL",
    "sg:address":"Hanzestr 7",
    "sg:city":"Maasbommel",
    "sg:orig_category":"Luchtfotografie",
    "sg:phone":"+31 487 562 400",
    "sg:postcode":"6627 AP",
    "sg:province":"North Brabant",
    "wof:name":"Ufo",
    "wof:placetype":"venue"
},
  "geometry": {"coordinates":[5.536439,51.821548],"type":"Point"}
}