{
  "type": "Feature",
  "properties": {
    "addr:full":"Maastrichterlaan 30 Vaals Limburg 6291 ES",
    "addr:housenumber":"30",
    "addr:postcode":"6291 es",
    "addr:street":"Maastrichterlaan",
    "iso:country":"NL",
    "sg:address":"Maastrichterlaan 30",
    "sg:city":"Vaals",
    "sg:orig_category":"Zuivelproducten",
    "sg:phone":"+31 43 306 1202",
    "sg:postcode":"6291 ES",
    "sg:province":"Limburg",
    "wof:name":"Kaas Suylen Vof",
    "wof:placetype":"venue"
},
  "geometry": {"coordinates":[6.018139,50.772766],"type":"Point"}
}