{
  "type": "Feature",
  "properties": {
    "addr:full":"Montfortlaan 7 Meerssen Limburg 6231 CP",
    "addr:housenumber":"7",
    "addr:postcode":"6231 cp",
    "addr:street":"Montfortlaan",
    "iso:country":"NL",
    "sg:address":"Montfortlaan 7",
    "sg:city":"Meerssen",
    "sg:orig_category":"Autokeuringen",
    "sg:phone":"+31 43 364 4306",
    "sg:postcode":"6231 CP",
    "sg:province":"Limburg",
    "wof:name":"Meerssens Revisiebedrijf",
    "wof:placetype":"venue"
},
  "geometry": {"coordinates":[5.751102,50.884567],"type":"Point"}
}