{
  "type": "Feature",
  "properties": {
    "iso:country":"NL",
    "sg:address":"Vivaldistr 6",
    "sg:city":"S Hertogenbosch",
    "sg:orig_category":"Vertaalbureaus",
    "sg:phone":"+31 73 687 2424",
    "sg:postcode":"5216 EL",
    "sg:province":"North Brabant",
    "wof:name":"Hms",
    "wof:placetype":"venue"
},
  "geometry": {"coordinates":[5.317587,51.680275],"type":"Point"}
}