{
  "type": "Feature",
  "properties": {
    "addr:full":"Ambonstraat 9 Meppel Drenthe 7941 VN",
    "addr:housenumber":"9",
    "addr:postcode":"7941 vn",
    "addr:street":"Ambonstraat",
    "iso:country":"NL",
    "sg:address":"Ambonstraat 9",
    "sg:city":"Meppel",
    "sg:orig_category":"Voeding, Dranken And Tabak Gh",
    "sg:phone":"+31 522 251 463",
    "sg:postcode":"7941 VN",
    "sg:province":"Drenthe",
    "wof:name":"Food Service Van Der Veen",
    "wof:placetype":"venue"
},
  "geometry": {"coordinates":[6.193673,52.699944],"type":"Point"}
}