{
  "type": "Feature",
  "properties": {
    "addr:full":"Van Hoytemastraat 67 'S Gravenhage Zuid-Holland 2596 EN",
    "addr:housenumber":"67",
    "addr:postcode":"2596 en",
    "addr:street":"Van Hoytemastraat;' S",
    "iso:country":"NL",
    "sg:address":"Van Hoytemastraat 67",
    "sg:city":"'S Gravenhage",
    "sg:classifiers":[
        {
            "category":"Food & Beverages",
            "subcategory":"Fruits & Vegetables",
            "type":"Retail Goods"
        }
    ],
    "sg:phone":"+31 70 324 4468",
    "sg:postcode":"2596 EN",
    "sg:province":"Zuid-Holland",
    "sg:tags":[
        "groenten"
    ],
    "wof:name":"Smits En Van Halm Groentenbedrijven",
    "wof:placetype":"venue"
},
  "geometry": {"coordinates":[4.324986,52.092972],"type":"Point"}
}