{
  "type": "Feature",
  "properties": {
    "addr:full":"Elzen 4 Boekel Noord-Brabant 5427 RC",
    "addr:housenumber":"4",
    "addr:postcode":"5427 rc",
    "addr:street":"Elzen",
    "iso:country":"NL",
    "sg:address":"Elzen 4",
    "sg:city":"Boekel",
    "sg:orig_category":"Honden- En Kattentrimsalons",
    "sg:phone":"+31 492 321 103",
    "sg:postcode":"5427 RC",
    "sg:province":"Noord-Brabant",
    "wof:name":"Snoopy",
    "wof:placetype":"venue"
},
  "geometry": {"coordinates":[5.662202,51.620693],"type":"Point"}
}