{
  "type": "Feature",
  "properties": {
    "iso:country":"NL",
    "sg:address":"Gerrit Van Der Veenlaan 68",
    "sg:city":"'S Gravenhage",
    "sg:classifiers":[
        {
            "category":"Fast Food",
            "type":"Food & Drink"
        }
    ],
    "sg:phone":"+31 70 397 4151",
    "sg:postcode":"2552 VZ",
    "sg:province":"Zuid-Holland",
    "sg:tags":[
        "afhaal",
        "restaurant"
    ],
    "wof:name":"Chinees Indisch Restaurant Choie-Sing",
    "wof:placetype":"venue"
},
  "geometry": {"coordinates":[4.249434,52.054691],"type":"Point"}
}