{
  "type": "Feature",
  "properties": {
    "addr:full":"C. Huygensstraat 9 Oud Beijerland South Holland 3261 LR",
    "addr:housenumber":"9",
    "addr:postcode":"3261 lr",
    "addr:street":"C. Huygensstraat;Oud Beijerland",
    "iso:country":"NL",
    "sg:address":"C. Huygensstraat 9",
    "sg:city":"Oud Beijerland",
    "sg:orig_category":"Werving And Selectie Van Tijdelijk Personeel And Uitzendkantoren",
    "sg:phone":"+31 186 642 986",
    "sg:postcode":"3261 LR",
    "sg:province":"South Holland",
    "wof:name":"Wadcosupport Bv",
    "wof:placetype":"venue"
},
  "geometry": {"coordinates":[4.4374752045,51.8288650513],"type":"Point"}
}