{
  "type": "Feature",
  "properties": {
    "iso:country":"NL",
    "sg:address":"Groenloseweg 13",
    "sg:city":"Winterswijk",
    "sg:orig_category":"Drukkerijen And Copyshops",
    "sg:phone":"+31 543 512 657",
    "sg:postcode":"7101 AA",
    "sg:province":"Gelderland",
    "wof:name":"Drukkerij Van Loo Bv",
    "wof:placetype":"venue"
},
  "geometry": {"coordinates":[6.71726,51.975536],"type":"Point"}
}