{
  "type": "Feature",
  "properties": {
    "addr:full":"Flevolaan 24 Weesp Noord-Holland 1382 JZ",
    "addr:housenumber":"24",
    "addr:postcode":"1382 jz",
    "addr:street":"Flevolaan",
    "iso:country":"NL",
    "sg:address":"Flevolaan 24",
    "sg:city":"Weesp",
    "sg:orig_category":"Beursorganisaties And Standbouw",
    "sg:phone":"+31 294 450 310",
    "sg:postcode":"1382 JZ",
    "sg:province":"Noord-Holland",
    "wof:name":"Formule C Stand & Decorbouw Bv",
    "wof:placetype":"venue"
},
  "geometry": {"coordinates":[5.02224,52.312473],"type":"Point"}
}