{
  "type": "Feature",
  "properties": {
    "addr:full":"Spittaalstr 62 Zutphen Gelderland 7201 EE",
    "addr:housenumber":"62",
    "addr:postcode":"7201 ee",
    "addr:street":"Spittaalstr;Gelderland",
    "iso:country":"NL",
    "sg:address":"Spittaalstr 62",
    "sg:city":"Zutphen",
    "sg:classifiers":[
        {
            "category":"Food & Beverages",
            "subcategory":"Bakery",
            "type":"Retail Goods"
        }
    ],
    "sg:phone":"+31 575 542 129",
    "sg:postcode":"7201 EE",
    "sg:province":"Gelderland",
    "sg:tags":[
        "pizza"
    ],
    "wof:name":"Viaroma",
    "wof:placetype":"venue"
},
  "geometry": {"coordinates":[6.200128,52.137772],"type":"Point"}
}