{
  "type": "Feature",
  "properties": {
    "addr:full":"Ridderhof 16 Ridderkerk Zuid-Holland 2981 ET",
    "addr:housenumber":"16",
    "addr:postcode":"2981 et",
    "addr:street":"Ridderhof",
    "iso:country":"NL",
    "sg:address":"Ridderhof 16",
    "sg:city":"Ridderkerk",
    "sg:orig_category":"Damesmodezaken",
    "sg:phone":"+31 180 425 139",
    "sg:postcode":"2981 ET",
    "sg:province":"Zuid-Holland",
    "wof:name":"Modehuis Nova Bv",
    "wof:placetype":"venue"
},
  "geometry": {"coordinates":[4.599083,51.869438],"type":"Point"}
}