{
  "type": "Feature",
  "properties": {
    "addr:full":"Geullestr 60 Rotterdam South Holland 3077 TR",
    "addr:housenumber":"60",
    "addr:postcode":"3077 tr",
    "addr:street":"Geullestr",
    "iso:country":"NL",
    "sg:address":"Geullestr 60",
    "sg:city":"Rotterdam",
    "sg:orig_category":"Plafonds",
    "sg:phone":"+31 10 482 5925",
    "sg:postcode":"3077 TR",
    "sg:province":"South Holland",
    "wof:name":"Zwaal, P",
    "wof:placetype":"venue"
},
  "geometry": {"coordinates":[4.563401,51.892742],"type":"Point"}
}