{
  "type": "Feature",
  "properties": {
    "addr:full":"Molendk 23 Oude Tonge South Holland 3255 AL",
    "addr:housenumber":"23",
    "addr:postcode":"3255 al",
    "addr:street":"Molendk",
    "iso:country":"NL",
    "sg:address":"Molendk 23",
    "sg:city":"Oude Tonge",
    "sg:orig_category":"Verhuur",
    "sg:phone":"+31 187 642 827",
    "sg:postcode":"3255 AL",
    "sg:province":"South Holland",
    "wof:name":"Pms Holland Bv",
    "wof:placetype":"venue"
},
  "geometry": {"coordinates":[4.210475,51.689739],"type":"Point"}
}