{
  "type": "Feature",
  "properties": {
    "addr:full":"Braam 34 Huizen Noord-Holland 1273 EA",
    "addr:housenumber":"34",
    "addr:postcode":"1273 ea",
    "addr:street":"Braam",
    "iso:country":"NL",
    "sg:address":"Braam 34",
    "sg:city":"Huizen",
    "sg:orig_category":"Administratie- En Boekhoudkantoren",
    "sg:phone":"+31 35 526 6848",
    "sg:postcode":"1273 EA",
    "sg:province":"Noord-Holland",
    "wof:name":"Ans",
    "wof:placetype":"venue"
},
  "geometry": {"coordinates":[5.251767,52.300632],"type":"Point"}
}