{
  "type": "Feature",
  "properties": {
    "addr:full":"Kerkstraat 8 Hoorn Nh Noord-Holland 1621 CW",
    "addr:housenumber":"8",
    "addr:postcode":"1621 cw",
    "addr:street":"Kerkstraat",
    "iso:country":"NL",
    "sg:address":"Kerkstraat 8",
    "sg:city":"Hoorn Nh",
    "sg:orig_category":"Dierenspeciaalzaken",
    "sg:phone":"+31 229 214 937",
    "sg:postcode":"1621 CW",
    "sg:province":"Noord-Holland",
    "wof:name":"Dierenspeciaalzaak Doesberg",
    "wof:placetype":"venue"
},
  "geometry": {"coordinates":[5.059738,52.639957],"type":"Point"}
}