{
  "type": "Feature",
  "properties": {
    "iso:country":"NL",
    "sg:address":"Rietveldsewg 31",
    "sg:city":"Culemborg",
    "sg:orig_category":"Verenigingsgebouwen",
    "sg:phone":"+31 345 513 459",
    "sg:postcode":"4107 LJ",
    "sg:province":"Gelderland",
    "wof:name":"Veld Wijkver, 'T",
    "wof:placetype":"venue"
},
  "geometry": {"coordinates":[5.170767,51.930981],"type":"Point"}
}