{
  "type": "Feature",
  "properties": {
    "addr:full":"Chopinstraat 12 Utrecht Utrecht 3533 EM",
    "addr:housenumber":"12",
    "addr:postcode":"3533 em",
    "addr:street":"Chopinstraat",
    "iso:country":"NL",
    "sg:address":"Chopinstraat 12",
    "sg:city":"Utrecht",
    "sg:orig_category":"Bedrijfs- And Managementsconsultants",
    "sg:phone":"+31 30 294 3301",
    "sg:postcode":"3533 EM",
    "sg:province":"Utrecht",
    "wof:name":"Stuyt Projekten",
    "wof:placetype":"venue"
},
  "geometry": {"coordinates":[5.0861229897,52.0840377808],"type":"Point"}
}