{
  "type": "Feature",
  "properties": {
    "addr:full":"Canadaln 26 Apeldoorn Gelderland 7316 BX",
    "addr:housenumber":"26",
    "addr:postcode":"7316 bx",
    "addr:street":"Canadaln;Gelderland",
    "iso:country":"NL",
    "sg:address":"Canadaln 26",
    "sg:city":"Apeldoorn",
    "sg:classifiers":[
        {
            "category":"Travel",
            "subcategory":"Hotels & Motels",
            "type":"Entertainment"
        }
    ],
    "sg:phone":"+31 55 522 2433",
    "sg:postcode":"7316 BX",
    "sg:province":"Gelderland",
    "wof:name":"Abbekerk, Hotel",
    "wof:placetype":"venue"
},
  "geometry": {"coordinates":[5.96566,52.216518],"type":"Point"}
}