{
  "type": "Feature",
  "properties": {
    "addr:full":"Postbus 138 Roelofarendsveen Zuid-Holland 2370 AC",
    "addr:housenumber":"138",
    "addr:postcode":"2370 ac",
    "addr:street":"Postbus",
    "iso:country":"NL",
    "sg:address":"Postbus 138",
    "sg:city":"Roelofarendsveen",
    "sg:orig_category":"Omroep",
    "sg:phone":"+31 71 331 9345",
    "sg:postcode":"2370 AC",
    "sg:province":"Zuid-Holland",
    "wof:name":"Tcn Bv",
    "wof:placetype":"venue"
},
  "geometry": {"coordinates":[4.6314,52.203491],"type":"Point"}
}