{
  "type": "Feature",
  "properties": {
    "addr:full":"Oostdorperwg 41 Wassenaar Zuid-Holland 2242 NE",
    "addr:housenumber":"41",
    "addr:postcode":"2242 ne",
    "addr:street":"Oostdorperwg",
    "iso:country":"NL",
    "sg:address":"Oostdorperwg 41",
    "sg:city":"Wassenaar",
    "sg:orig_category":"Hengelsportartikelen",
    "sg:phone":"+31 70 511 3245",
    "sg:postcode":"2242 NE",
    "sg:province":"Zuid-Holland",
    "sg:website":"http://www.sedge.nl",
    "wof:name":"Sedge Fishing Adventures",
    "wof:placetype":"venue"
},
  "geometry": {"coordinates":[4.395874,52.148216],"type":"Point"}
}