{
  "type": "Feature",
  "properties": {
    "iso:country":"NL",
    "sg:address":"Franklinstraat 86",
    "sg:city":"'S Gravenhage",
    "sg:orig_category":"Verzekeringen",
    "sg:phone":"+31 70 365 6531",
    "sg:postcode":"2562 CJ",
    "sg:province":"Zuid-Holland",
    "wof:name":"F R Habieb Ass",
    "wof:placetype":"venue"
},
  "geometry": {"coordinates":[4.284456,52.077873],"type":"Point"}
}