{
  "type": "Feature",
  "properties": {
    "addr:full":"Foarryp 3 Wynaldum Friesland 8857 RE",
    "addr:housenumber":"3",
    "addr:postcode":"8857 re",
    "addr:street":"Foarryp",
    "iso:country":"NL",
    "sg:address":"Foarryp 3",
    "sg:city":"Wynaldum",
    "sg:orig_category":"Hoefsmederijen",
    "sg:phone":"+31 517 591 652",
    "sg:postcode":"8857 RE",
    "sg:province":"Friesland",
    "wof:name":"Dokter, D",
    "wof:placetype":"venue"
},
  "geometry": {"coordinates":[5.46054,53.195881],"type":"Point"}
}