{
  "type": "Feature",
  "properties": {
    "addr:full":"Brouwerspad 13 Zeeland Noord-Brabant 5411 BG",
    "addr:housenumber":"13",
    "addr:postcode":"5411",
    "addr:street":"Brouwerspad",
    "iso:country":"NL",
    "sg:address":"Brouwerspad 13",
    "sg:city":"Zeeland",
    "sg:orig_category":"Banken",
    "sg:phone":"+31 486 451 644",
    "sg:postcode":"5411 BG",
    "sg:province":"Noord-Brabant",
    "wof:name":"Regio Bank",
    "wof:placetype":"venue"
},
  "geometry": {"coordinates":[5.676561,51.697811],"type":"Point"}
}