{
  "type": "Feature",
  "properties": {
    "addr:full":"Bornsestraat 6-8 Almelo NL.08 7607 KN",
    "addr:housenumber":"6-8;nl.08",
    "addr:postcode":"7607 kn",
    "addr:street":"Bornsestraat",
    "iso:country":"NL",
    "sg:address":"Bornsestraat 6-8",
    "sg:city":"Almelo",
    "sg:classifiers":[
        {
            "category":"Fast Food",
            "type":"Food & Drink"
        }
    ],
    "sg:phone":"+31 546 829 285",
    "sg:postcode":"7607 KN",
    "sg:province":"NL.08",
    "sg:tags":[
        "afhaal",
        "restaurant"
    ],
    "wof:name":"Grillhouse Filiz",
    "wof:placetype":"venue"
},
  "geometry": {"coordinates":[6.665207,52.351505],"type":"Point"}
}