{
  "type": "Feature",
  "properties": {
    "iso:country":"NL",
    "sg:address":"Medemblikstr 42",
    "sg:city":"Amsterdam",
    "sg:orig_category":"Onderhoudswerken",
    "sg:phone":"+31 20 632 7769",
    "sg:postcode":"1023 XS",
    "sg:province":"Noord-Holland",
    "wof:name":"Horst, P Van Der",
    "wof:placetype":"venue"
},
  "geometry": {"coordinates":[4.939466,52.39362],"type":"Point"}
}