{
  "type": "Feature",
  "properties": {
    "iso:country":"NL",
    "sg:address":"Mariastr 15",
    "sg:city":"Koog Aan De Zaan",
    "sg:orig_category":"Glazenwasserijen",
    "sg:phone":"+31 6 55884000",
    "sg:postcode":"1541 GC",
    "sg:province":"North Holland",
    "wof:name":"Wissewassie",
    "wof:placetype":"venue"
},
  "geometry": {"coordinates":[4.80678,52.460854],"type":"Point"}
}