{
  "type": "Feature",
  "properties": {
    "addr:full":"Maasdk 21 Nederhemert Gelderland 5317 KP",
    "addr:housenumber":"21",
    "addr:postcode":"5317 kp",
    "addr:street":"Maasdk;Gelderland",
    "iso:country":"NL",
    "sg:address":"Maasdk 21",
    "sg:city":"Nederhemert",
    "sg:orig_category":"Beveiliging",
    "sg:phone":"+31 6 21813579",
    "sg:postcode":"5317 KP",
    "sg:province":"Gelderland",
    "wof:name":"Safe Choice Bv",
    "wof:placetype":"venue"
},
  "geometry": {"coordinates":[5.151954,51.763073],"type":"Point"}
}