{
  "type": "Feature",
  "properties": {
    "addr:full":"Wolfslaardreef 95 Breda Noord-Brabant 4834 SN",
    "addr:housenumber":"95",
    "addr:postcode":"4834 sn",
    "addr:street":"Wolfslaardreef",
    "iso:country":"NL",
    "sg:address":"Wolfslaardreef 95",
    "sg:city":"Breda",
    "sg:classifiers":[
        {
            "category":"Bakery",
            "type":"Food & Drink"
        }
    ],
    "sg:phone":"+31 76 565 5242",
    "sg:postcode":"4834 SN",
    "sg:province":"Noord-Brabant",
    "sg:tags":[
        "brood",
        "banket"
    ],
    "wof:name":"In De Knollentuin",
    "wof:placetype":"venue"
},
  "geometry": {"coordinates":[4.799818,51.561832],"type":"Point"}
}