{
  "type": "Feature",
  "properties": {
    "addr:full":"Dr H Smeengestr 33 Slootdorp Noord-Holland 1774 AB",
    "addr:housenumber":"33",
    "addr:postcode":"1774 ab",
    "addr:street":"Dr",
    "iso:country":"NL",
    "sg:address":"Dr H Smeengestr 33",
    "sg:city":"Slootdorp",
    "sg:orig_category":"Land- En Tuinbouw - Loonbedrijven",
    "sg:phone":"+31 227 581 746",
    "sg:postcode":"1774 AB",
    "sg:province":"Noord-Holland",
    "wof:name":"Zuidema, B",
    "wof:placetype":"venue"
},
  "geometry": {"coordinates":[4.972503,52.839375],"type":"Point"}
}