{
  "type": "Feature",
  "properties": {
    "addr:full":"Kampweg 40 Doorn Utrecht 3941 HJ",
    "addr:housenumber":"40",
    "addr:postcode":"3941 hj",
    "addr:street":"Kampweg",
    "iso:country":"NL",
    "sg:address":"Kampweg 40",
    "sg:city":"Doorn",
    "sg:orig_category":"Paramedische Behandelingen",
    "sg:phone":"+31 343 415 600",
    "sg:postcode":"3941 HJ",
    "sg:province":"Utrecht",
    "wof:name":"Logopediste E. Rollman",
    "wof:placetype":"venue"
},
  "geometry": {"coordinates":[5.343006,52.036728],"type":"Point"}
}