{
  "type": "Feature",
  "properties": {
    "addr:full":"Weststr 50 Axel Zeeland 4571 HM",
    "addr:housenumber":"50",
    "addr:postcode":"4571 hm",
    "addr:street":"Weststr",
    "iso:country":"NL",
    "sg:address":"Weststr 50",
    "sg:city":"Axel",
    "sg:orig_category":"Houtbewerking",
    "sg:phone":"+31 115 565 561",
    "sg:postcode":"4571 HM",
    "sg:province":"Zeeland",
    "wof:name":"Azia Orient",
    "wof:placetype":"venue"
},
  "geometry": {"coordinates":[3.905493,51.265087],"type":"Point"}
}