{
  "type": "Feature",
  "properties": {
    "addr:full":"Aquamarijn 4 Krimpen A/D Ijssel Zuid-Holland 2924 VR",
    "addr:housenumber":"4;a / d",
    "addr:postcode":"2924 vr",
    "addr:street":"Aquamarijn",
    "iso:country":"NL",
    "sg:address":"Aquamarijn 4",
    "sg:city":"Krimpen A/D Ijssel",
    "sg:classifiers":[
        {
            "category":"Professional",
            "subcategory":"Accounting & Tax Preparation",
            "type":"Services"
        }
    ],
    "sg:phone":"+31 180 552 249",
    "sg:postcode":"2924 VR",
    "sg:province":"Zuid-Holland",
    "sg:tags":[
        "accountant"
    ],
    "wof:name":"J. Van Cappellen",
    "wof:placetype":"venue"
},
  "geometry": {"coordinates":[4.607397,51.924759],"type":"Point"}
}