{
  "type": "Feature",
  "properties": {
    "addr:full":"Wiekslag 334 Capelle Ad Yssel South Holland 2903 VG",
    "addr:housenumber":"334",
    "addr:postcode":"2903 vg",
    "addr:street":"Wiekslag;Yssel",
    "iso:country":"NL",
    "sg:address":"Wiekslag 334",
    "sg:city":"Capelle Ad Yssel",
    "sg:orig_category":"Balletscholen",
    "sg:phone":"+31 10 451 6451",
    "sg:postcode":"2903 VG",
    "sg:province":"South Holland",
    "wof:name":"Marijke",
    "wof:placetype":"venue"
},
  "geometry": {"coordinates":[4.592344,51.935173],"type":"Point"}
}