{
  "type": "Feature",
  "properties": {
    "addr:full":"Stokmeestersln 1 Zwolle NL.08 8014 GM",
    "addr:housenumber":"1",
    "addr:postcode":"8014 gm",
    "addr:street":"Stokmeestersln",
    "iso:country":"NL",
    "sg:address":"Stokmeestersln 1",
    "sg:city":"Zwolle",
    "sg:orig_category":"Scholen Voor Basisonderwijs",
    "sg:phone":"+31 38 465 1002",
    "sg:postcode":"8014 GM",
    "sg:province":"NL.08",
    "wof:name":"Bron Prot Chr, De",
    "wof:placetype":"venue"
},
  "geometry": {"coordinates":[6.088738,52.512566],"type":"Point"}
}