{
  "type": "Feature",
  "properties": {
    "addr:full":"De Mulder 65 Sint Michielsgestel North Brabant 5272 RD",
    "addr:housenumber":"65",
    "addr:postcode":"5272 rd",
    "addr:street":"De Mulder;Sint Michielsgestel",
    "iso:country":"NL",
    "sg:address":"De Mulder 65",
    "sg:city":"Sint Michielsgestel",
    "sg:orig_category":"Meubels And Huishoudapparatuur Gh",
    "sg:phone":"+31 73 551 9135",
    "sg:postcode":"5272 RD",
    "sg:province":"North Brabant",
    "wof:name":"C. Wisker",
    "wof:placetype":"venue"
},
  "geometry": {"coordinates":[5.358627,51.647266],"type":"Point"}
}