{
  "type": "Feature",
  "properties": {
    "iso:country":"NL",
    "sg:address":"Kloosterstraat 38",
    "sg:city":"Heythuysen",
    "sg:orig_category":"Kappers",
    "sg:phone":"+31 475 492 182",
    "sg:postcode":"6093 CX",
    "sg:province":"Limburg",
    "wof:name":"M W Prinssen Triepels",
    "wof:placetype":"venue"
},
  "geometry": {"coordinates":[5.889886,51.250233],"type":"Point"}
}