{
  "type": "Feature",
  "properties": {
    "addr:full":"Populierenln 64 Uitgeest Noord-Holland 1911 BM",
    "addr:housenumber":"64",
    "addr:postcode":"1911 bm",
    "addr:street":"Populierenln",
    "iso:country":"NL",
    "sg:address":"Populierenln 64",
    "sg:city":"Uitgeest",
    "sg:orig_category":"Mode Artikelen Dames En Heren - Fabrieken En Groothandel",
    "sg:phone":"+31 251 312 641",
    "sg:postcode":"1911 BM",
    "sg:province":"Noord-Holland",
    "wof:name":"China Direct Bv",
    "wof:placetype":"venue"
},
  "geometry": {"coordinates":[4.7154,52.530399],"type":"Point"}
}