{
  "type": "Feature",
  "properties": {
    "addr:full":"Pr Bernhardstr 1A Angeren Gelderland 6687 AX",
    "addr:housenumber":"1a",
    "addr:postcode":"6687 ax",
    "addr:street":"Gelderland",
    "iso:country":"NL",
    "sg:address":"Pr Bernhardstr 1A",
    "sg:city":"Angeren",
    "sg:orig_category":"Schilders",
    "sg:phone":"+31 26 325 7586",
    "sg:postcode":"6687 AX",
    "sg:province":"Gelderland",
    "wof:name":"Doorn, Van",
    "wof:placetype":"venue"
},
  "geometry": {"coordinates":[5.957459,51.914413],"type":"Point"}
}