{
  "type": "Feature",
  "properties": {
    "iso:country":"NL",
    "sg:address":"P Foggstr 24",
    "sg:city":"Emmen",
    "sg:orig_category":"Verf En Lak - Fabrieken En Groothandel",
    "sg:phone":"+31 591 633 600",
    "sg:postcode":"7821 AK",
    "sg:province":"Provincie Drenthe",
    "sg:website":"http://www.olijslager.nl",
    "wof:name":"Olijslager Bv",
    "wof:placetype":"venue"
},
  "geometry": {"coordinates":[6.925083,52.764114],"type":"Point"}
}