{
  "type": "Feature",
  "properties": {
    "addr:full":"Rooseveltlaan 135 Amsterdam North Holland 1079 AK",
    "addr:housenumber":"135",
    "addr:postcode":"1079 ak",
    "addr:street":"Rooseveltlaan",
    "iso:country":"NL",
    "sg:address":"Rooseveltlaan 135",
    "sg:city":"Amsterdam",
    "sg:orig_category":"Vertaal- And Tolkenbureaus",
    "sg:phone":"+31 20 404 3549",
    "sg:postcode":"1079 AK",
    "sg:province":"North Holland",
    "wof:name":"Elizabeth Mac Fadyen",
    "wof:placetype":"venue"
},
  "geometry": {"coordinates":[4.898786,52.343361],"type":"Point"}
}