{
  "type": "Feature",
  "properties": {
    "addr:full":"H V Halterenstr 5 Lichtenvoorde Gelderland 7131 ZM",
    "addr:housenumber":"5",
    "addr:postcode":"7131 zm",
    "addr:street":"H;Halterenstr;Gelderland",
    "iso:country":"NL",
    "sg:address":"H V Halterenstr 5",
    "sg:city":"Lichtenvoorde",
    "sg:orig_category":"Adviesbureaus Bedrijfsorganisatie",
    "sg:phone":"+31 544 376 473",
    "sg:postcode":"7131 ZM",
    "sg:province":"Gelderland",
    "wof:name":"Awn",
    "wof:placetype":"venue"
},
  "geometry": {"coordinates":[6.56445,51.9883],"type":"Point"}
}