{
  "type": "Feature",
  "properties": {
    "iso:country":"NL",
    "sg:address":"Amstelzijde 87",
    "sg:city":"Amstelveen",
    "sg:orig_category":"Fotostudio'S And Fotografen",
    "sg:phone":"+31 20 496 4656",
    "sg:postcode":"1184 TZ",
    "sg:province":"Noord-Holland",
    "wof:name":"No-Id Creatieve Communicatie",
    "wof:placetype":"venue"
},
  "geometry": {"coordinates":[4.898847,52.297985],"type":"Point"}
}