{
  "type": "Feature",
  "properties": {
    "addr:full":"Ter Apelkan W 133 Ter Apelkanaal Groningen 9563 PG",
    "addr:housenumber":"133",
    "addr:postcode":"9563 pg",
    "addr:street":"W;Ter",
    "iso:country":"NL",
    "sg:address":"Ter Apelkan W 133",
    "sg:city":"Ter Apelkanaal",
    "sg:orig_category":"Wasmachines En Wasdrogers - Onderhoud En Reparatie",
    "sg:phone":"+31 599 412 396",
    "sg:postcode":"9563 PG",
    "sg:province":"Groningen",
    "wof:name":"Hemmen, H H",
    "wof:placetype":"venue"
},
  "geometry": {"coordinates":[7.0476031303,52.914188385],"type":"Point"}
}