{
  "type": "Feature",
  "properties": {
    "addr:full":"Parallelwg 24 Klaaswaal Zuid-Holland 3286 LR",
    "addr:housenumber":"24",
    "addr:postcode":"3286 lr",
    "addr:street":"Parallelwg",
    "iso:country":"NL",
    "sg:address":"Parallelwg 24",
    "sg:city":"Klaaswaal",
    "sg:orig_category":"Banken",
    "sg:phone":"+31 186 571 488",
    "sg:postcode":"3286 LR",
    "sg:province":"Zuid-Holland",
    "wof:name":"Regio Bank",
    "wof:placetype":"venue"
},
  "geometry": {"coordinates":[4.444251,51.767021],"type":"Point"}
}