{
  "type": "Feature",
  "properties": {
    "addr:full":"Dickmansstraat 3 Haarlem Noord-Holland 2015 JA",
    "addr:housenumber":"3",
    "addr:postcode":"2015 ja",
    "addr:street":"Dickmansstraat",
    "iso:country":"NL",
    "sg:address":"Dickmansstraat 3",
    "sg:city":"Haarlem",
    "sg:orig_category":"Diverse Artikelen Fab",
    "sg:phone":"+31 23 524 4038",
    "sg:postcode":"2015 JA",
    "sg:province":"Noord-Holland",
    "wof:name":"R Philippo",
    "wof:placetype":"venue"
},
  "geometry": {"coordinates":[4.604556,52.382053],"type":"Point"}
}