{
  "type": "Feature",
  "properties": {
    "addr:full":"Waagstraat 4 Oldenzaal NL.08 7571 EA",
    "addr:housenumber":"4;nl.08",
    "addr:postcode":"7571 ea",
    "addr:street":"Waagstraat",
    "iso:country":"NL",
    "sg:address":"Waagstraat 4",
    "sg:city":"Oldenzaal",
    "sg:orig_category":"Kunst And Kunstenaarsbenodigdheden",
    "sg:phone":"+31 541 535 151",
    "sg:postcode":"7571 EA",
    "sg:province":"NL.08",
    "wof:name":"Kunstcentrum De Waagh",
    "wof:placetype":"venue"
},
  "geometry": {"coordinates":[6.929509,52.314152],"type":"Point"}
}