{
  "type": "Feature",
  "properties": {
    "iso:country":"NL",
    "sg:address":"Kerkakkers 4",
    "sg:city":"Zeeland",
    "sg:orig_category":"Paramedische Behandelingen",
    "sg:phone":"+31 486 451 621",
    "sg:postcode":"5411 TN",
    "sg:province":"Noord-Brabant",
    "wof:name":"Ing. A.G. Te Meerman",
    "wof:placetype":"venue"
},
  "geometry": {"coordinates":[5.667766,51.696568],"type":"Point"}
}