{
  "type": "Feature",
  "properties": {
    "addr:full":"L Majoorln 50 Bussum Noord-Holland 1401 RP",
    "addr:housenumber":"50",
    "addr:postcode":"1401 rp",
    "iso:country":"NL",
    "sg:address":"L Majoorln 50",
    "sg:city":"Bussum",
    "sg:orig_category":"Autoreclame",
    "sg:phone":"+31 6 53100786",
    "sg:postcode":"1401 RP",
    "sg:province":"Noord-Holland",
    "wof:name":"Bvg, Studio",
    "wof:placetype":"venue"
},
  "geometry": {"coordinates":[5.162605,52.276829],"type":"Point"}
}