{
  "type": "Feature",
  "properties": {
    "addr:full":"Valkhofstr 55 Rotterdam South Holland 3077 SW",
    "addr:housenumber":"55",
    "addr:postcode":"3077 sw",
    "addr:street":"Valkhofstr",
    "iso:country":"NL",
    "sg:address":"Valkhofstr 55",
    "sg:city":"Rotterdam",
    "sg:orig_category":"Voetbalverenigingen",
    "sg:phone":"+31 180 699 620",
    "sg:postcode":"3077 SW",
    "sg:province":"South Holland",
    "wof:name":"Overmaas",
    "wof:placetype":"venue"
},
  "geometry": {"coordinates":[4.564605,51.889015],"type":"Point"}
}