{
  "type": "Feature",
  "properties": {
    "addr:full":"Irisln 36 Berkel En Rodenrys South Holland 2651 PR",
    "addr:housenumber":"36",
    "addr:postcode":"2651 pr",
    "addr:street":"Irisln;Berkel",
    "iso:country":"NL",
    "sg:address":"Irisln 36",
    "sg:city":"Berkel En Rodenrys",
    "sg:orig_category":"Kappers",
    "sg:phone":"+31 10 511 4709",
    "sg:postcode":"2651 PR",
    "sg:province":"South Holland",
    "wof:name":"Martens, I",
    "wof:placetype":"venue"
},
  "geometry": {"coordinates":[4.478555,51.992535],"type":"Point"}
}