{
  "type": "Feature",
  "properties": {
    "addr:full":"Valeriaan 30 S Hertogenbosch North Brabant 5236 TN",
    "addr:housenumber":"30",
    "addr:postcode":"5236",
    "addr:street":"Valeriaan;S Hertogenbosch",
    "iso:country":"NL",
    "sg:address":"Valeriaan 30",
    "sg:city":"S Hertogenbosch",
    "sg:orig_category":"Bijouterie?n",
    "sg:phone":"+31 73 641 0723",
    "sg:postcode":"5236 TN",
    "sg:province":"North Brabant",
    "wof:name":"Heiligenberg",
    "wof:placetype":"venue"
},
  "geometry": {"coordinates":[5.330609,51.734299],"type":"Point"}
}