{
  "type": "Feature",
  "properties": {
    "iso:country":"NL",
    "sg:address":"Europalaan 6",
    "sg:city":"Heerenveen",
    "sg:orig_category":"Sportcentra",
    "sg:phone":"+31 513 624 935",
    "sg:postcode":"8442 GL",
    "sg:province":"Friesland",
    "wof:name":"Sportcentrum De Telle, Sporthal En Overdekt Zwemba",
    "wof:placetype":"venue"
},
  "geometry": {"coordinates":[5.932603,52.955292],"type":"Point"}
}