{
  "type": "Feature",
  "properties": {
    "addr:full":"Doormanstr 13 Dongen Noord-Brabant 5102 VC",
    "addr:housenumber":"13",
    "addr:postcode":"5102 vc",
    "addr:street":"Doormanstr",
    "iso:country":"NL",
    "sg:address":"Doormanstr 13",
    "sg:city":"Dongen",
    "sg:orig_category":"Administratie- En Boekhoudkantoren",
    "sg:phone":"+31 162 315 560",
    "sg:postcode":"5102 VC",
    "sg:province":"Noord-Brabant",
    "wof:name":"Boekensteun Administraties Bv, De",
    "wof:placetype":"venue"
},
  "geometry": {"coordinates":[4.92777,51.632385],"type":"Point"}
}