{
  "type": "Feature",
  "properties": {
    "iso:country":"NL",
    "sg:address":"Grensstr 98A",
    "sg:city":"Landgraaf",
    "sg:orig_category":"Video - Faciliteiten En Producties",
    "sg:phone":"+31 45 569 0350",
    "sg:postcode":"6374 CT",
    "sg:province":"Limburg",
    "sg:website":"http://www.mediaprofile.nl",
    "wof:name":"Media Profile",
    "wof:placetype":"venue"
},
  "geometry": {"coordinates":[6.052041,50.919003],"type":"Point"}
}