{
  "type": "Feature",
  "properties": {
    "addr:full":"Haagsteeg 20 Wageningen Gelderland 6708 PM",
    "addr:housenumber":"20",
    "addr:postcode":"6708 pm",
    "addr:street":"Haagsteeg;Gelderland",
    "iso:country":"NL",
    "sg:address":"Haagsteeg 20",
    "sg:city":"Wageningen",
    "sg:orig_category":"Artsen And Specialisten",
    "sg:phone":"+31 317 414 523",
    "sg:postcode":"6708 PM",
    "sg:province":"Gelderland",
    "wof:name":"J. Landman Huisarts",
    "wof:placetype":"venue"
},
  "geometry": {"coordinates":[5.651021,51.975475],"type":"Point"}
}