{
  "type": "Feature",
  "properties": {
    "iso:country":"NL",
    "sg:address":"Hoofdstraat 174",
    "sg:city":"Voorthuizen",
    "sg:orig_category":"Bloemen And Planten",
    "sg:phone":"+31 342 473 311",
    "sg:postcode":"3781 AK",
    "sg:province":"Gelderland",
    "wof:name":"Bloemenshop Fleurina",
    "wof:placetype":"venue"
},
  "geometry": {"coordinates":[5.606609,52.186947],"type":"Point"}
}