{
  "type": "Feature",
  "properties": {
    "addr:full":"Mr Troelstrastr 68 Hengelo Ov Overijssel 7556 EN",
    "addr:housenumber":"68",
    "addr:postcode":"7556 en",
    "addr:street":"Ov",
    "iso:country":"NL",
    "sg:address":"Mr Troelstrastr 68",
    "sg:city":"Hengelo Ov",
    "sg:orig_category":"Kinderopvang",
    "sg:phone":"+31 74 243 1571",
    "sg:postcode":"7556 EN",
    "sg:province":"Overijssel",
    "wof:name":"Stubo Bv",
    "wof:placetype":"venue"
},
  "geometry": {"coordinates":[6.78971,52.266331],"type":"Point"}
}