{
  "type": "Feature",
  "properties": {
    "addr:full":"Oudezijds Voorburgwal 270 Amsterdam North Holland 1012 GL",
    "addr:housenumber":"270",
    "addr:postcode":"1012 gl",
    "addr:street":"Oudezijds Voorburgwal",
    "iso:country":"NL",
    "sg:address":"Oudezijds Voorburgwal 270",
    "sg:city":"Amsterdam",
    "sg:orig_category":"Diverse Grafische Activiteiten",
    "sg:phone":"+31 20 627 6967",
    "sg:postcode":"1012 GL",
    "sg:province":"North Holland",
    "wof:name":"Ls Ontwerpers Ateliers Koko",
    "wof:placetype":"venue"
},
  "geometry": {"coordinates":[4.894914,52.371399],"type":"Point"}
}