{
  "type": "Feature",
  "properties": {
    "addr:full":"Strawinskylaan 721 Amsterdam North Holland 1077 XX",
    "addr:housenumber":"721",
    "addr:postcode":"1077 xx",
    "addr:street":"Strawinskylaan",
    "iso:country":"NL",
    "sg:address":"Strawinskylaan 721",
    "sg:city":"Amsterdam",
    "sg:orig_category":"Luchtvaart",
    "sg:phone":"+31 20 664 9891",
    "sg:postcode":"1077 XX",
    "sg:province":"North Holland",
    "wof:name":"British Midland Airways Ltd",
    "wof:placetype":"venue"
},
  "geometry": {"coordinates":[4.873351,52.340603],"type":"Point"}
}