{
  "type": "Feature",
  "properties": {
    "addr:full":"V Berckelwg 46 Noordwyk Zh South Holland 2203 LB",
    "addr:housenumber":"46",
    "addr:postcode":"2203 lb",
    "addr:street":"Noordwyk Zh",
    "iso:country":"NL",
    "sg:address":"V Berckelwg 46",
    "sg:city":"Noordwyk Zh",
    "sg:orig_category":"Jachthavens - Jachtwerven",
    "sg:phone":"+31 71 361 6387",
    "sg:postcode":"2203 LB",
    "sg:province":"South Holland",
    "wof:name":"Jachthaven Noordwijk",
    "wof:placetype":"venue"
},
  "geometry": {"coordinates":[4.4477,52.234261],"type":"Point"}
}