{
  "type": "Feature",
  "properties": {
    "addr:full":"Houtduifstraat 6 Oosterhout Nb North Brabant 4901 BP",
    "addr:housenumber":"6;nb",
    "addr:postcode":"4901 bp",
    "addr:street":"Houtduifstraat",
    "iso:country":"NL",
    "sg:address":"Houtduifstraat 6",
    "sg:city":"Oosterhout Nb",
    "sg:orig_category":"Hang- And Sluitwerk Fab",
    "sg:phone":"+31 162 447 720",
    "sg:postcode":"4901 BP",
    "sg:province":"North Brabant",
    "wof:name":"H. Van Nelfen Deurtechniek Bv",
    "wof:placetype":"venue"
},
  "geometry": {"coordinates":[4.85358,51.650261],"type":"Point"}
}