{
  "type": "Feature",
  "properties": {
    "iso:country":"NL",
    "sg:address":"Eikenhof 39",
    "sg:city":"De Lier",
    "sg:orig_category":"Keukens",
    "sg:phone":"+31 174 516 004",
    "sg:postcode":"2678 RB",
    "sg:province":"Zuid-Holland",
    "wof:name":"Vermeer, H",
    "wof:placetype":"venue"
},
  "geometry": {"coordinates":[4.246186,51.977051],"type":"Point"}
}