{
  "type": "Feature",
  "properties": {
    "addr:full":"Middelwg 47 Tricht Gelderland 4196 JG",
    "addr:housenumber":"47",
    "addr:postcode":"4196 jg",
    "addr:street":"Middelwg;Gelderland",
    "iso:country":"NL",
    "sg:address":"Middelwg 47",
    "sg:city":"Tricht",
    "sg:orig_category":"Geluidsinstallaties - Verhuur",
    "sg:phone":"+31 345 581 305",
    "sg:postcode":"4196 JG",
    "sg:province":"Gelderland",
    "wof:name":"Schalk - Sound",
    "wof:placetype":"venue"
},
  "geometry": {"coordinates":[5.252139,51.891838],"type":"Point"}
}