{
  "type": "Feature",
  "properties": {
    "iso:country":"NL",
    "sg:address":"Driezeeg 4",
    "sg:city":"Berlicum Nb",
    "sg:orig_category":"Boekhouders",
    "sg:phone":"+31 73 503 4435",
    "sg:postcode":"5258 LE",
    "sg:province":"North Brabant",
    "wof:name":"Bureau Verkuijlen",
    "wof:placetype":"venue"
},
  "geometry": {"coordinates":[5.417499,51.664028],"type":"Point"}
}