{
  "type": "Feature",
  "properties": {
    "iso:country":"NL",
    "sg:address":"Molukkenstraat 198",
    "sg:city":"Amsterdam",
    "sg:orig_category":"Fotostudio'S And Fotografen",
    "sg:phone":"+31 20 693 8786",
    "sg:postcode":"1098 TW",
    "sg:province":"Noord-Holland",
    "wof:name":"D.J.M. Boink",
    "wof:placetype":"venue"
},
  "geometry": {"coordinates":[4.94096,52.358082],"type":"Point"}
}