{
  "type": "Feature",
  "properties": {
    "addr:full":"Lg Heurnsewg 29 De Heurne Gelderland 7095 AL",
    "addr:housenumber":"29",
    "addr:postcode":"7095 al",
    "addr:street":"Lg",
    "iso:country":"NL",
    "sg:address":"Lg Heurnsewg 29",
    "sg:city":"De Heurne",
    "sg:orig_category":"Machinefabrieken",
    "sg:phone":"+31 315 651 167",
    "sg:postcode":"7095 AL",
    "sg:province":"Gelderland",
    "wof:name":"Aalders Bv",
    "wof:placetype":"venue"
},
  "geometry": {"coordinates":[6.485832,51.883743],"type":"Point"}
}