{
  "type": "Feature",
  "properties": {
    "addr:full":"Lange Kleiweg 4 Rijswijk Zh Zuid-Holland 2288 GK",
    "addr:housenumber":"4",
    "addr:postcode":"zh;2288 gk",
    "addr:street":"Lange Kleiweg",
    "iso:country":"NL",
    "sg:address":"Lange Kleiweg 4",
    "sg:city":"Rijswijk Zh",
    "sg:orig_category":"Kappers",
    "sg:phone":"+31 15 213 6895",
    "sg:postcode":"2288 GK",
    "sg:province":"Zuid-Holland",
    "wof:name":"Allurage",
    "wof:placetype":"venue"
},
  "geometry": {"coordinates":[4.3246188164,52.0371055603],"type":"Point"}
}