{
  "type": "Feature",
  "properties": {
    "addr:full":"Lanen 80 Harlingen Provincie Friesland 8861 CE",
    "addr:housenumber":"80",
    "addr:postcode":"8861 ce",
    "addr:street":"Lanen;Provincie Friesland",
    "iso:country":"NL",
    "sg:address":"Lanen 80",
    "sg:city":"Harlingen",
    "sg:orig_category":"Cafetaria'S",
    "sg:phone":"+31 517 413 079",
    "sg:postcode":"8861 CE",
    "sg:province":"Provincie Friesland",
    "wof:name":"Corner, The",
    "wof:placetype":"venue"
},
  "geometry": {"coordinates":[5.419268,53.173733],"type":"Point"}
}