{
  "type": "Feature",
  "properties": {
    "addr:full":"Nieuwstraat 61 Apeldoorn Gelderland 7311 BP",
    "addr:housenumber":"61",
    "addr:postcode":"7311 bp",
    "addr:street":"Nieuwstraat;Gelderland",
    "iso:country":"NL",
    "sg:address":"Nieuwstraat 61",
    "sg:city":"Apeldoorn",
    "sg:orig_category":"Werving And Selectie Van Tijdelijk Personeel And Uitzendkantoren",
    "sg:phone":"+31 55 577 2857",
    "sg:postcode":"7311 BP",
    "sg:province":"Gelderland",
    "wof:name":"Quality Select",
    "wof:placetype":"venue"
},
  "geometry": {"coordinates":[5.961001873,52.2128295898],"type":"Point"}
}