{
  "type": "Feature",
  "properties": {
    "iso:country":"NL",
    "sg:address":"Boterdiep 20",
    "sg:city":"Groningen",
    "sg:orig_category":"Meubelreparatie And -Restauratie",
    "sg:phone":"+31 50 313 4398",
    "sg:postcode":"9712 LN",
    "sg:province":"Groningen",
    "wof:name":"Dijkema Meubelstoffeerders",
    "wof:placetype":"venue"
},
  "geometry": {"coordinates":[6.565402,53.222954],"type":"Point"}
}