{
  "type": "Feature",
  "properties": {
    "iso:country":"NL",
    "sg:address":"Zuidwenk 14",
    "sg:city":"Bunschoten Spakenburg",
    "sg:orig_category":"Kappers",
    "sg:phone":"+31 33 298 7671",
    "sg:postcode":"3751 CD",
    "sg:province":"Utrecht",
    "wof:name":"Hairstyling Jaennette",
    "wof:placetype":"venue"
},
  "geometry": {"coordinates":[5.3777370453,52.2499504089],"type":"Point"}
}