{
  "type": "Feature",
  "properties": {
    "addr:full":"Ambachtshof 22 Wateringen Zuid-Holland 2291 DX",
    "addr:housenumber":"22",
    "addr:postcode":"2291 dx",
    "addr:street":"Ambachtshof",
    "iso:country":"NL",
    "sg:address":"Ambachtshof 22",
    "sg:city":"Wateringen",
    "sg:orig_category":"Adviesbureaus Bedrijfsorganisatie",
    "sg:phone":"+31 174 298 685",
    "sg:postcode":"2291 DX",
    "sg:province":"Zuid-Holland",
    "wof:name":"Watrema",
    "wof:placetype":"venue"
},
  "geometry": {"coordinates":[4.268265,52.032814],"type":"Point"}
}