{
  "type": "Feature",
  "properties": {
    "iso:country":"NL",
    "sg:address":"Ambachtshof 22",
    "sg:city":"Wateringen",
    "sg:orig_category":"Adviesbureaus Bedrijfsorganisatie",
    "sg:phone":"+31 174 298 685",
    "sg:postcode":"2291 DX",
    "sg:province":"Zuid-Holland",
    "wof:name":"Watrema",
    "wof:placetype":"venue"
},
  "geometry": {"coordinates":[4.268265,52.032814],"type":"Point"}
}