{
  "type": "Feature",
  "properties": {
    "addr:full":"Slichtenhorsterweg 30 Nijkerk Gld Gelderland 3862 NS",
    "addr:housenumber":"30",
    "addr:postcode":"3862 ns",
    "addr:street":"Slichtenhorsterweg;Gld Gelderland",
    "iso:country":"NL",
    "sg:address":"Slichtenhorsterweg 30",
    "sg:city":"Nijkerk Gld",
    "sg:orig_category":"Public Relationbureaus",
    "sg:phone":"+31 33 245 3791",
    "sg:postcode":"3862 NS",
    "sg:province":"Gelderland",
    "wof:name":"Lex Harding Bv",
    "wof:placetype":"venue"
},
  "geometry": {"coordinates":[5.513043,52.205788],"type":"Point"}
}