{
  "type": "Feature",
  "properties": {
    "addr:full":"Zr Gertrudosngl 14 Rosmalen Noord-Brabant 5247 WN",
    "addr:housenumber":"14",
    "addr:postcode":"5247 wn",
    "iso:country":"NL",
    "sg:address":"Zr Gertrudosngl 14",
    "sg:city":"Rosmalen",
    "sg:orig_category":"Geluidsinstallaties - Verhuur",
    "sg:phone":"+31 6 53642305",
    "sg:postcode":"5247 WN",
    "sg:province":"Noord-Brabant",
    "wof:name":"Verkamman, Ren?",
    "wof:placetype":"venue"
},
  "geometry": {"coordinates":[5.367065,51.727131],"type":"Point"}
}