{
  "type": "Feature",
  "properties": {
    "addr:full":"Raadhuisstraat 51 Hengelo Gld Gelderland 7255 BL",
    "addr:housenumber":"51",
    "addr:postcode":"7255 bl",
    "addr:street":"Raadhuisstraat",
    "iso:country":"NL",
    "sg:address":"Raadhuisstraat 51",
    "sg:city":"Hengelo Gld",
    "sg:orig_category":"Visspeciaalzaken",
    "sg:phone":"+31 575 463 460",
    "sg:postcode":"7255 BL",
    "sg:province":"Gelderland",
    "wof:name":"Vishandel Hengel",
    "wof:placetype":"venue"
},
  "geometry": {"coordinates":[6.306188,52.053852],"type":"Point"}
}