{
  "type": "Feature",
  "properties": {
    "addr:full":"Industrieweg 161 Rotterdam South Holland 3044 AS",
    "addr:housenumber":"161",
    "addr:postcode":"3044 as",
    "addr:street":"Industrieweg",
    "iso:country":"NL",
    "sg:address":"Industrieweg 161",
    "sg:city":"Rotterdam",
    "sg:orig_category":"Wasserettes, Stomerijen And Reiniging",
    "sg:phone":"+31 10 437 6261",
    "sg:postcode":"3044 AS",
    "sg:province":"South Holland",
    "wof:name":"Chemdry",
    "wof:placetype":"venue"
},
  "geometry": {"coordinates":[4.4245381355,51.9247627258],"type":"Point"}
}