{
  "type": "Feature",
  "properties": {
    "addr:full":"Roerkd 2 Roermond Limburg 6041 KZ",
    "addr:housenumber":"2",
    "addr:postcode":"6041 kz",
    "addr:street":"Roerkd",
    "iso:country":"NL",
    "sg:address":"Roerkd 2",
    "sg:city":"Roermond",
    "sg:classifiers":[
        {
            "category":"Travel",
            "subcategory":"Hotels & Motels",
            "type":"Entertainment"
        }
    ],
    "sg:phone":"+31 475 316 597",
    "sg:postcode":"6041 KZ",
    "sg:province":"Limburg",
    "wof:name":"Pauw, De",
    "wof:placetype":"venue"
},
  "geometry": {"coordinates":[5.98457,51.196117],"type":"Point"}
}