{
  "type": "Feature",
  "properties": {
    "iso:country":"NL",
    "sg:address":"Zandweg 73",
    "sg:city":"De Meern",
    "sg:orig_category":"Adviesbureaus Bedrijfsorganisatie",
    "sg:phone":"+31 30 662 0071",
    "sg:postcode":"3454 JW",
    "sg:province":"Utrecht",
    "wof:name":"Transmura",
    "wof:placetype":"venue"
},
  "geometry": {"coordinates":[5.045713,52.082088],"type":"Point"}
}