{
  "type": "Feature",
  "properties": {
    "addr:full":"De Middend 16 Bovenkarspel Noord-Holland 1611 KW",
    "addr:housenumber":"16",
    "addr:postcode":"1611 kw",
    "addr:street":"De Middend",
    "iso:country":"NL",
    "sg:address":"De Middend 16",
    "sg:city":"Bovenkarspel",
    "sg:orig_category":"Bloemen En Planten",
    "sg:phone":"+31 228 515 658",
    "sg:postcode":"1611 KW",
    "sg:province":"Noord-Holland",
    "wof:name":"Hofje, 'T",
    "wof:placetype":"venue"
},
  "geometry": {"coordinates":[5.235531,52.696022],"type":"Point"}
}