{
  "type": "Feature",
  "properties": {
    "iso:country":"NL",
    "sg:address":"Zilvermeeuw 35",
    "sg:city":"Noordwyk Zh",
    "sg:orig_category":"Psychologen",
    "sg:phone":"+31 71 361 6072",
    "sg:postcode":"2201 XC",
    "sg:province":"South Holland",
    "wof:name":"Zilvermeeuw, De",
    "wof:placetype":"venue"
},
  "geometry": {"coordinates":[4.447704,52.234268],"type":"Point"}
}