{
  "type": "Feature",
  "properties": {
    "addr:full":"Heliconwg 62 Leeuwarden Provincie Friesland 8914 AT",
    "addr:housenumber":"62",
    "addr:postcode":"8914",
    "addr:street":"Heliconwg;Provincie Friesland",
    "iso:country":"NL",
    "sg:address":"Heliconwg 62",
    "sg:city":"Leeuwarden",
    "sg:orig_category":"Kamers Van Koophandel",
    "sg:phone":"+31 58 295 4321",
    "sg:postcode":"8914 AT",
    "sg:province":"Provincie Friesland",
    "sg:website":"http://www.leeuwarden.kvk.nl",
    "wof:name":"Kamer Van Koophandel Voor Friesland",
    "wof:placetype":"venue"
},
  "geometry": {"coordinates":[5.7744541168,53.198589325],"type":"Point"}
}