{
  "type": "Feature",
  "properties": {
    "iso:country":"NL",
    "sg:address":"Knsm Ln 87",
    "sg:city":"Amsterdam",
    "sg:orig_category":"Bedrijfsopleidingen",
    "sg:phone":"+31 20 419 5570",
    "sg:postcode":"1019 LB",
    "sg:province":"North Holland",
    "wof:name":"Spruit In Company Trainingen Bv",
    "wof:placetype":"venue"
},
  "geometry": {"coordinates":[4.938611,52.377254],"type":"Point"}
}