{
  "type": "Feature",
  "properties": {
    "addr:full":"Pr. Frederiklaan 197 Leidschendam South Holland 2263  H",
    "addr:housenumber":"197;2263 h",
    "addr:street":"Pr. Frederiklaan",
    "iso:country":"NL",
    "sg:address":"Pr. Frederiklaan 197",
    "sg:city":"Leidschendam",
    "sg:orig_category":"Boekenuitgeverijen",
    "sg:phone":"+31 70 327 1206",
    "sg:postcode":"2263  H",
    "sg:province":"South Holland",
    "wof:name":"Bruna",
    "wof:placetype":"venue"
},
  "geometry": {"coordinates":[4.40398,52.096931],"type":"Point"}
}