{
  "type": "Feature",
  "properties": {
    "iso:country":"NL",
    "sg:address":"Plein 6",
    "sg:city":"Almere",
    "sg:orig_category":"Verenigingen En Stichtingen",
    "sg:phone":"+31 36 540 0010",
    "sg:postcode":"1354 LJ",
    "sg:province":"Flevoland",
    "sg:website":"http://www.irda.nl",
    "wof:name":"Irda",
    "wof:placetype":"venue"
},
  "geometry": {"coordinates":[5.218727,52.33511],"type":"Point"}
}