{
  "type": "Feature",
  "properties": {
    "addr:full":"Rozengaarde 75 Rijssen Overijssel 7461 DA",
    "addr:housenumber":"75",
    "addr:postcode":"7461 da",
    "addr:street":"Rozengaarde",
    "iso:country":"NL",
    "sg:address":"Rozengaarde 75",
    "sg:city":"Rijssen",
    "sg:orig_category":"Banken And Kredietinstellingen",
    "sg:phone":"+31 548 521 234",
    "sg:postcode":"7461 DA",
    "sg:province":"Overijssel",
    "wof:name":"Postkantoor",
    "wof:placetype":"venue"
},
  "geometry": {"coordinates":[6.523034,52.307442],"type":"Point"}
}