{
  "type": "Feature",
  "properties": {
    "addr:full":"Verdronkenoord 137 Alkmaar North Holland 1811 BD",
    "addr:housenumber":"137",
    "addr:postcode":"1811 bd",
    "addr:street":"Verdronkenoord",
    "iso:country":"NL",
    "sg:address":"Verdronkenoord 137",
    "sg:city":"Alkmaar",
    "sg:orig_category":"Kappers",
    "sg:phone":"+31 72 511 1946",
    "sg:postcode":"1811 BD",
    "sg:province":"North Holland",
    "wof:name":"Hairstylist Ed Vilten",
    "wof:placetype":"venue"
},
  "geometry": {"coordinates":[4.749601841,52.6299247742],"type":"Point"}
}