{
  "type": "Feature",
  "properties": {
    "addr:full":"Spaarndamsewg 42 Haarlem North Holland 2021 CA",
    "addr:housenumber":"42",
    "addr:postcode":"2021 ca",
    "addr:street":"Spaarndamsewg",
    "iso:country":"NL",
    "sg:address":"Spaarndamsewg 42",
    "sg:city":"Haarlem",
    "sg:orig_category":"Parketvloeren",
    "sg:phone":"+31 23 527 2608",
    "sg:postcode":"2021 CA",
    "sg:province":"North Holland",
    "wof:name":"Smit, J",
    "wof:placetype":"venue"
},
  "geometry": {"coordinates":[4.648605,52.387749],"type":"Point"}
}