{
  "type": "Feature",
  "properties": {
    "iso:country":"NL",
    "sg:address":"Langenhorst 237",
    "sg:city":"Rotterdam",
    "sg:classifiers":[
        {
            "category":"Fast Food",
            "type":"Food & Drink"
        }
    ],
    "sg:phone":"+31 10 481 1055",
    "sg:postcode":"3085 HE",
    "sg:province":"South Holland",
    "sg:tags":[
        "afhaal",
        "restaurant"
    ],
    "wof:name":"Seppel Cafetaria",
    "wof:placetype":"venue"
},
  "geometry": {"coordinates":[4.494298,51.874203],"type":"Point"}
}