{
  "type": "Feature",
  "properties": {
    "addr:full":"1E Weteringplnts 6 Amsterdam North Holland 1017 SK",
    "addr:housenumber":"6",
    "addr:street":"1E Weteringplnts;1017",
    "iso:country":"NL",
    "sg:address":"1E Weteringplnts 6",
    "sg:city":"Amsterdam",
    "sg:orig_category":"Verenigingen En Stichtingen",
    "sg:phone":"+31 20 420 3771",
    "sg:postcode":"1017 SK",
    "sg:province":"North Holland",
    "wof:name":"Defence For Children Int",
    "wof:placetype":"venue"
},
  "geometry": {"coordinates":[4.88783,52.361897],"type":"Point"}
}