{
  "type": "Feature",
  "properties": {
    "addr:full":"Ds T O Hylkemawg 8 Giethoorn Overijssel 8355 CD",
    "addr:housenumber":"8",
    "addr:postcode":"8355 cd",
    "addr:street":"Ds T O Hylkemawg",
    "iso:country":"NL",
    "sg:address":"Ds T O Hylkemawg 8",
    "sg:city":"Giethoorn",
    "sg:orig_category":"Zeilmakerijen",
    "sg:phone":"+31 521 361 343",
    "sg:postcode":"8355 CD",
    "sg:province":"Overijssel",
    "wof:name":"Boer, J",
    "wof:placetype":"venue"
},
  "geometry": {"coordinates":[6.080697,52.722195],"type":"Point"}
}