{
  "type": "Feature",
  "properties": {
    "iso:country":"NL",
    "sg:address":"N Linschoterdk 6",
    "sg:city":"Linschoten",
    "sg:orig_category":"Loonbedrijven",
    "sg:phone":"+31 6 29405114",
    "sg:postcode":"3461 AC",
    "sg:province":"Utrecht",
    "wof:name":"Cromwijk",
    "wof:placetype":"venue"
},
  "geometry": {"coordinates":[4.90528,52.058289],"type":"Point"}
}