{
  "type": "Feature",
  "properties": {
    "addr:full":"Lange Nieuwstraat 751 Ijmuiden Noord-Holland 1971 GG",
    "addr:housenumber":"751",
    "addr:postcode":"1971 gg",
    "addr:street":"Lange Nieuwstraat",
    "iso:country":"NL",
    "sg:address":"Lange Nieuwstraat 751",
    "sg:city":"Ijmuiden",
    "sg:orig_category":"Banken And Kredietinstellingen",
    "sg:phone":"+31 255 519 100",
    "sg:postcode":"1971 GG",
    "sg:province":"Noord-Holland",
    "wof:name":"Fortis Bank",
    "wof:placetype":"venue"
},
  "geometry": {"coordinates":[4.622524,52.459278],"type":"Point"}
}