{
  "type": "Feature",
  "properties": {
    "addr:full":"Zwanenwater 20 Lelystad NL. 8245 BV",
    "addr:housenumber":"20",
    "addr:postcode":"8245 bv",
    "addr:street":"Zwanenwater;Nl.",
    "iso:country":"NL",
    "sg:address":"Zwanenwater 20",
    "sg:city":"Lelystad",
    "sg:orig_category":"Loopbaanbegeleiding",
    "sg:phone":"+31 320 255 374",
    "sg:postcode":"8245 BV",
    "sg:province":"NL.",
    "wof:name":"Teppema",
    "wof:placetype":"venue"
},
  "geometry": {"coordinates":[5.458477,52.497528],"type":"Point"}
}