{
  "type": "Feature",
  "properties": {
    "addr:full":"Prof Lindeboomln 7 Ermelo Gelderland 3853 GE",
    "addr:housenumber":"7",
    "addr:postcode":"3853",
    "addr:street":"Gelderland",
    "iso:country":"NL",
    "sg:address":"Prof Lindeboomln 7",
    "sg:city":"Ermelo",
    "sg:orig_category":"Zonnebank- En Solariumcentra",
    "sg:phone":"+31 341 558 603",
    "sg:postcode":"3853 GE",
    "sg:province":"Gelderland",
    "wof:name":"Fransien",
    "wof:placetype":"venue"
},
  "geometry": {"coordinates":[5.598481,52.30077],"type":"Point"}
}