{
  "type": "Feature",
  "properties": {
    "addr:full":"Buorren 61 Langweer Friesland 8525 EE",
    "addr:housenumber":"61",
    "addr:postcode":"8525 ee",
    "addr:street":"Buorren",
    "iso:country":"NL",
    "sg:address":"Buorren 61",
    "sg:city":"Langweer",
    "sg:orig_category":"Adviesbureaus Bedrijfsorganisatie",
    "sg:phone":"+31 513 499 378",
    "sg:postcode":"8525 EE",
    "sg:province":"Friesland",
    "wof:name":"Interveen",
    "wof:placetype":"venue"
},
  "geometry": {"coordinates":[5.72579,52.959431],"type":"Point"}
}