{
  "type": "Feature",
  "properties": {
    "addr:full":"Paukenstr 68 Almere Flevoland 1312 WN",
    "addr:housenumber":"68",
    "addr:postcode":"1312 wn",
    "addr:street":"Paukenstr;Flevoland",
    "iso:country":"NL",
    "sg:address":"Paukenstr 68",
    "sg:city":"Almere",
    "sg:classifiers":[
        {
            "category":"Professional",
            "subcategory":"Accounting & Tax Preparation",
            "type":"Services"
        }
    ],
    "sg:phone":"+31 36 536 2360",
    "sg:postcode":"1312 WN",
    "sg:province":"Flevoland",
    "sg:tags":[
        "accountant",
        "en",
        "-kantoren",
        "register-"
    ],
    "wof:name":"Peters, Accountants Kantoor",
    "wof:placetype":"venue"
},
  "geometry": {"coordinates":[5.181002,52.373444],"type":"Point"}
}