{
  "type": "Feature",
  "properties": {
    "addr:full":"V Teylingenln 3 Heerhugowaard Noord-Holland 1701 AA",
    "addr:housenumber":"3",
    "addr:postcode":"1701 aa",
    "addr:street":"Teylingenln",
    "iso:country":"NL",
    "sg:address":"V Teylingenln 3",
    "sg:city":"Heerhugowaard",
    "sg:orig_category":"Kinderopvang",
    "sg:phone":"+31 72 534 8611",
    "sg:postcode":"1701 AA",
    "sg:province":"Noord-Holland",
    "sg:website":"http://www.kinderopvang-heerhugowaard.nl",
    "wof:name":"Bonte Papegaai, De",
    "wof:placetype":"venue"
},
  "geometry": {"coordinates":[4.827522,52.665195],"type":"Point"}
}