{
  "type": "Feature",
  "properties": {
    "addr:full":"Prinses Julianastraat 12 Genemuiden NL.08 8281 CL",
    "addr:housenumber":"12;nl.08",
    "addr:postcode":"8281 cl",
    "addr:street":"Prinses Julianastraat",
    "iso:country":"NL",
    "sg:address":"Prinses Julianastraat 12",
    "sg:city":"Genemuiden",
    "sg:orig_category":"Muziekinstrumenten",
    "sg:phone":"+31 38 385 6050",
    "sg:postcode":"8281 CL",
    "sg:province":"NL.08",
    "wof:name":"Van De Kamp'S Muziekhuis De Orgelpijp",
    "wof:placetype":"venue"
},
  "geometry": {"coordinates":[6.041841,52.623455],"type":"Point"}
}