{
  "type": "Feature",
  "properties": {
    "addr:full":"Formosastraat 11A Leiden South Holland 2315 GT",
    "addr:housenumber":"11a",
    "addr:postcode":"2315 gt",
    "addr:street":"Formosastraat",
    "iso:country":"NL",
    "sg:address":"Formosastraat 11A",
    "sg:city":"Leiden",
    "sg:orig_category":"Wegen And Sportterreinen",
    "sg:phone":"+31 71 521 9305",
    "sg:postcode":"2315 GT",
    "sg:province":"South Holland",
    "wof:name":"C.W. De Roode",
    "wof:placetype":"venue"
},
  "geometry": {"coordinates":[4.5106639862,52.1625404358],"type":"Point"}
}