{
  "type": "Feature",
  "properties": {
    "addr:full":"Peulenstraat 243 Hardinxveld Giessend Zuid-Holland 3371 AM",
    "addr:housenumber":"243;giessend",
    "addr:postcode":"3371",
    "addr:street":"Peulenstraat",
    "iso:country":"NL",
    "sg:address":"Peulenstraat 243",
    "sg:city":"Hardinxveld Giessend",
    "sg:classifiers":[
        {
            "category":"Shopping",
            "subcategory":"Gifts & Souvenirs",
            "type":"Retail Goods"
        }
    ],
    "sg:phone":"+31 184 611 641",
    "sg:postcode":"3371 AM",
    "sg:province":"Zuid-Holland",
    "sg:tags":[
        "geschenken"
    ],
    "wof:name":"Merlijn",
    "wof:placetype":"venue"
},
  "geometry": {"coordinates":[4.833573,51.827915],"type":"Point"}
}