{
  "type": "Feature",
  "properties": {
    "iso:country":"NL",
    "sg:address":"Parkln 7",
    "sg:city":"Enkhuizen",
    "sg:classifiers":[
        {
            "category":"Education",
            "subcategory":"Special Training",
            "type":"Public Place"
        }
    ],
    "sg:phone":"+31 228 314 741",
    "sg:postcode":"1601 EK",
    "sg:province":"Noord-Holland",
    "sg:tags":[
        "expertise"
    ],
    "wof:name":"Schuijt Vof, R C",
    "wof:placetype":"venue"
},
  "geometry": {"coordinates":[5.290085,52.703674],"type":"Point"}
}