{
  "type": "Feature",
  "properties": {
    "addr:full":"M Harpertsz Trompwg 229 Dordrecht Zuid-Holland 3317 BS",
    "addr:housenumber":"229",
    "addr:postcode":"3317 bs",
    "addr:street":"M Harpertsz Trompwg",
    "iso:country":"NL",
    "sg:address":"M Harpertsz Trompwg 229",
    "sg:city":"Dordrecht",
    "sg:orig_category":"Verenigingen En Stichtingen",
    "sg:phone":"+31 78 654 8183",
    "sg:postcode":"3317 BS",
    "sg:province":"Zuid-Holland",
    "wof:name":"Nvob",
    "wof:placetype":"venue"
},
  "geometry": {"coordinates":[4.653218,51.789536],"type":"Point"}
}