{
  "type": "Feature",
  "properties": {
    "addr:full":"H Teirlinckstr 38 Rotterdam Zuid-Holland 3069 JT",
    "addr:housenumber":"38",
    "addr:postcode":"3069 jt",
    "iso:country":"NL",
    "sg:address":"H Teirlinckstr 38",
    "sg:city":"Rotterdam",
    "sg:orig_category":"Journalisten Freelance",
    "sg:phone":"+31 10 456 2640",
    "sg:postcode":"3069 JT",
    "sg:province":"Zuid-Holland",
    "wof:name":"Gouweloos",
    "wof:placetype":"venue"
},
  "geometry": {"coordinates":[4.56565,51.968822],"type":"Point"}
}