{
  "type": "Feature",
  "properties": {
    "addr:full":"J B Bakemakd 38 Rotterdam Zuid-Holland 3071 ME",
    "addr:housenumber":"38",
    "addr:postcode":"3071 me",
    "iso:country":"NL",
    "sg:address":"J B Bakemakd 38",
    "sg:city":"Rotterdam",
    "sg:orig_category":"Adviesbureaus Bedrijfsorganisatie",
    "sg:phone":"+31 10 485 1088",
    "sg:postcode":"3071 ME",
    "sg:province":"Zuid-Holland",
    "wof:name":"Kroesulting",
    "wof:placetype":"venue"
},
  "geometry": {"coordinates":[4.50327,51.910591],"type":"Point"}
}