{
  "type": "Feature",
  "properties": {
    "addr:full":"Nassaulaan 24 Vlijmen North Brabant 5251 JC",
    "addr:housenumber":"24",
    "addr:postcode":"5251 jc",
    "addr:street":"Nassaulaan",
    "iso:country":"NL",
    "sg:address":"Nassaulaan 24",
    "sg:city":"Vlijmen",
    "sg:orig_category":"Verhuur Diversen",
    "sg:phone":"+31 73 511 7388",
    "sg:postcode":"5251 JC",
    "sg:province":"North Brabant",
    "wof:name":"Stebas (Verhuur En Advies)",
    "wof:placetype":"venue"
},
  "geometry": {"coordinates":[5.199258,51.691624],"type":"Point"}
}