{
  "type": "Feature",
  "properties": {
    "addr:full":"Bijleveldsingel 11 Nijmegen Gelderland 6521 AM",
    "addr:housenumber":"11",
    "addr:postcode":"6521",
    "addr:street":"Bijleveldsingel;Gelderland",
    "iso:country":"NL",
    "sg:address":"Bijleveldsingel 11",
    "sg:city":"Nijmegen",
    "sg:classifiers":[
        {
            "category":"Professional",
            "subcategory":"Accounting & Tax Preparation",
            "type":"Services"
        }
    ],
    "sg:phone":"+31 24 322 4798",
    "sg:postcode":"6521 AM",
    "sg:province":"Gelderland",
    "sg:tags":[
        "accountant"
    ],
    "wof:name":"Accountantskantoor Boonstra",
    "wof:placetype":"venue"
},
  "geometry": {"coordinates":[5.869998,51.842674],"type":"Point"}
}