{
  "type": "Feature",
  "properties": {
    "addr:full":"Vastenavondkampstraat 142 Venlo Limburg 5922 AX",
    "addr:housenumber":"142",
    "addr:postcode":"5922 ax",
    "addr:street":"Vastenavondkampstraat",
    "iso:country":"NL",
    "sg:address":"Vastenavondkampstraat 142",
    "sg:city":"Venlo",
    "sg:orig_category":"Wasserettes And Stomerijen",
    "sg:phone":"+31 77 382 0293",
    "sg:postcode":"5922 AX",
    "sg:province":"Limburg",
    "wof:name":"Marnita",
    "wof:placetype":"venue"
},
  "geometry": {"coordinates":[6.1397109032,51.3743209839],"type":"Point"}
}