{
  "type": "Feature",
  "properties": {
    "addr:full":"Calandhof 4 Tilburg Noord-Brabant 5025 DP",
    "addr:housenumber":"4",
    "addr:postcode":"5025 dp",
    "addr:street":"Calandhof",
    "iso:country":"NL",
    "sg:address":"Calandhof 4",
    "sg:city":"Tilburg",
    "sg:orig_category":"Drukkerijen",
    "sg:phone":"+31 13 542 2587",
    "sg:postcode":"5025 DP",
    "sg:province":"Noord-Brabant",
    "sg:website":"http://www.drukkerijhultermans.nl",
    "wof:name":"Hultermans",
    "wof:placetype":"venue"
},
  "geometry": {"coordinates":[5.069162,51.549381],"type":"Point"}
}