{
  "type": "Feature",
  "properties": {
    "addr:full":"Schenkkade 65 'S Gravenhage Zuid-Holland 2595 AS",
    "addr:housenumber":"65",
    "addr:postcode":"2595 as",
    "addr:street":"Schenkkade;' S",
    "iso:country":"NL",
    "sg:address":"Schenkkade 65",
    "sg:city":"'S Gravenhage",
    "sg:orig_category":"Verzekeringen",
    "sg:phone":"+31 70 378 1662",
    "sg:postcode":"2595 AS",
    "sg:province":"Zuid-Holland",
    "wof:name":"Transatlantica Herverzekeringsmaatschappij Nv",
    "wof:placetype":"venue"
},
  "geometry": {"coordinates":[4.33526,52.077606],"type":"Point"}
}