{
  "type": "Feature",
  "properties": {
    "iso:country":"NL",
    "sg:address":"Van Eesterenplein 91",
    "sg:city":"Dordrecht",
    "sg:classifiers":[
        {
            "category":"Food & Beverages",
            "subcategory":"Fruits & Vegetables",
            "type":"Retail Goods"
        }
    ],
    "sg:phone":"+31 78 621 5502",
    "sg:postcode":"3315 KT",
    "sg:province":"Zuid-Holland",
    "sg:tags":[
        "groenten"
    ],
    "wof:name":"P. Van Ommen",
    "wof:placetype":"venue"
},
  "geometry": {"coordinates":[4.716542,51.80307],"type":"Point"}
}