{
  "type": "Feature",
  "properties": {
    "iso:country":"NL",
    "sg:address":"Unicefln 1",
    "sg:city":"Utrecht",
    "sg:orig_category":"Verzekerings- Maatschappijen",
    "sg:phone":"+31 30 292 8928",
    "sg:postcode":"3527 WX",
    "sg:province":"Utrecht",
    "wof:name":"Tiel Utrecht Verzekeringen",
    "wof:placetype":"venue"
},
  "geometry": {"coordinates":[5.096656,52.083286],"type":"Point"}
}