{
  "type": "Feature",
  "properties": {
    "addr:full":"Gerrittenweg 23 Venlo Limburg 5916 SC",
    "addr:housenumber":"23",
    "addr:postcode":"5916 sc",
    "addr:street":"Gerrittenweg",
    "iso:country":"NL",
    "sg:address":"Gerrittenweg 23",
    "sg:city":"Venlo",
    "sg:orig_category":"Beautyfarms And Sauna'S",
    "sg:phone":"+31 77 351 6150",
    "sg:postcode":"5916 SC",
    "sg:province":"Limburg",
    "wof:name":"Cosmetique",
    "wof:placetype":"venue"
},
  "geometry": {"coordinates":[6.191397,51.388241],"type":"Point"}
}