{
  "type": "Feature",
  "properties": {
    "addr:full":"Pr Alexanderwg 78-02 Huis Ter Heide Ut Utrecht 3712 AC",
    "addr:housenumber":"78-02",
    "addr:postcode":"3712 ac",
    "iso:country":"NL",
    "sg:address":"Pr Alexanderwg 78-02",
    "sg:city":"Huis Ter Heide Ut",
    "sg:orig_category":"Adviesbureaus",
    "sg:phone":"+31 30 691 8260",
    "sg:postcode":"3712 AC",
    "sg:province":"Utrecht",
    "wof:name":"Harry'S Head Bv",
    "wof:placetype":"venue"
},
  "geometry": {"coordinates":[5.256528,52.108334],"type":"Point"}
}