{
  "type": "Feature",
  "properties": {
    "addr:full":"Bodegraafsestrwg 163 Gouda Zuid-Holland 2805 GN",
    "addr:housenumber":"163",
    "addr:postcode":"2805 gn",
    "iso:country":"NL",
    "sg:address":"Bodegraafsestrwg 163",
    "sg:city":"Gouda",
    "sg:orig_category":"Onroerende Goederen",
    "sg:phone":"+31 182 396 011",
    "sg:postcode":"2805 GN",
    "sg:province":"Zuid-Holland",
    "wof:name":"Wit Bv, De",
    "wof:placetype":"venue"
},
  "geometry": {"coordinates":[4.719185,52.03133],"type":"Point"}
}