{
  "type": "Feature",
  "properties": {
    "iso:country":"NL",
    "sg:address":"Noodwg 49",
    "sg:city":"Hilversum",
    "sg:orig_category":"Luchthavens En Vliegvelden",
    "sg:phone":"+31 35 577 1205",
    "sg:postcode":"1213 PW",
    "sg:province":"Noord-Holland",
    "wof:name":"Vliegveld Hilversum",
    "wof:placetype":"venue"
},
  "geometry": {"coordinates":[5.152438,52.19445],"type":"Point"}
}