{
  "type": "Feature",
  "properties": {
    "addr:full":"President Hopstakenlaan 119 Hoeven Etten-Leur Noord-Brabant 4741 DX",
    "addr:housenumber":"119",
    "addr:postcode":"4741 dx",
    "addr:street":"President Hopstakenlaan",
    "iso:country":"NL",
    "sg:address":"President Hopstakenlaan 119",
    "sg:city":"Hoeven Etten-Leur",
    "sg:orig_category":"Huishoudapparatuur, Televisies And Radio'S",
    "sg:phone":"+31 165 502 101",
    "sg:postcode":"4741 DX",
    "sg:province":"Noord-Brabant",
    "wof:name":"Satellite Systems Hoeven",
    "wof:placetype":"venue"
},
  "geometry": {"coordinates":[4.57493,51.581078],"type":"Point"}
}