{
  "type": "Feature",
  "properties": {
    "addr:full":"Kapperswg 4B Aalten Gelderland 7122 JJ",
    "addr:housenumber":"4b",
    "addr:postcode":"7122 jj",
    "addr:street":"Kapperswg;Gelderland",
    "iso:country":"NL",
    "sg:address":"Kapperswg 4B",
    "sg:city":"Aalten",
    "sg:orig_category":"Kunststof Ramen",
    "sg:phone":"+31 543 466 446",
    "sg:postcode":"7122 JJ",
    "sg:province":"Gelderland",
    "wof:name":"Doppen Hogenelst Montage",
    "wof:placetype":"venue"
},
  "geometry": {"coordinates":[6.578304,51.89777],"type":"Point"}
}