{
  "type": "Feature",
  "properties": {
    "addr:full":"De Gouw 45 Wervershoof Noord-Holland 1693 DB",
    "addr:housenumber":"45",
    "addr:postcode":"1693 db",
    "addr:street":"De Gouw",
    "iso:country":"NL",
    "sg:address":"De Gouw 45",
    "sg:city":"Wervershoof",
    "sg:orig_category":"Verzekeringen - Verzekeringskantoren",
    "sg:phone":"+31 228 584 248",
    "sg:postcode":"1693 DB",
    "sg:province":"Noord-Holland",
    "wof:name":"Relais",
    "wof:placetype":"venue"
},
  "geometry": {"coordinates":[5.14762,52.730137],"type":"Point"}
}