{
  "type": "Feature",
  "properties": {
    "iso:country":"NL",
    "sg:address":"Makadocenter 4",
    "sg:city":"Alblasserdam",
    "sg:orig_category":"Zoetwaren - Winkels",
    "sg:phone":"+31 78 691 8504",
    "sg:postcode":"2951 EJ",
    "sg:province":"South Holland",
    "wof:name":"Lolliepop",
    "wof:placetype":"venue"
},
  "geometry": {"coordinates":[4.657685,51.863308],"type":"Point"}
}