{
  "type": "Feature",
  "properties": {
    "addr:full":"Makadocenter 4 Alblasserdam South Holland 2951 EJ",
    "addr:housenumber":"4",
    "addr:postcode":"2951 ej",
    "addr:street":"Makadocenter",
    "iso:country":"NL",
    "sg:address":"Makadocenter 4",
    "sg:city":"Alblasserdam",
    "sg:orig_category":"Zoetwaren - Winkels",
    "sg:phone":"+31 78 691 8504",
    "sg:postcode":"2951 EJ",
    "sg:province":"South Holland",
    "wof:name":"Lolliepop",
    "wof:placetype":"venue"
},
  "geometry": {"coordinates":[4.657685,51.863308],"type":"Point"}
}