{
  "type": "Feature",
  "properties": {
    "addr:full":"Postbus 117 Bergen Op Zoom Noord-Brabant 4600 AC",
    "addr:housenumber":"117",
    "addr:postcode":"4600 ac",
    "addr:street":"Postbus",
    "iso:country":"NL",
    "sg:address":"Postbus 117",
    "sg:city":"Bergen Op Zoom",
    "sg:orig_category":"Kunststoffen - Fabrieken En Groothandel",
    "sg:phone":"+31 164 292 911",
    "sg:postcode":"4600 AC",
    "sg:province":"Noord-Brabant",
    "sg:website":"http://www.ge.com/plastics",
    "wof:name":"General Electric Bv",
    "wof:placetype":"venue"
},
  "geometry": {"coordinates":[4.28199,51.495949],"type":"Point"}
}