{
  "type": "Feature",
  "properties": {
    "addr:full":"Hofstr 4 Venray Limburg 5801 BJ",
    "addr:housenumber":"4",
    "addr:postcode":"5801 bj",
    "addr:street":"Hofstr",
    "iso:country":"NL",
    "sg:address":"Hofstr 4",
    "sg:city":"Venray",
    "sg:orig_category":"Opticiens",
    "sg:phone":"+31 478 514 711",
    "sg:postcode":"5801 BJ",
    "sg:province":"Limburg",
    "sg:website":"http://www.hansanders.nl",
    "wof:name":"Hans Anders",
    "wof:placetype":"venue"
},
  "geometry": {"coordinates":[5.9761209488,51.5271110535],"type":"Point"}
}