{
  "type": "Feature",
  "properties": {
    "iso:country":"NL",
    "sg:address":"Burg Meester H Popstr 50",
    "sg:city":"Dinteloord",
    "sg:classifiers":[
        {
            "category":"Education",
            "subcategory":"Preschool",
            "type":"Public Place"
        }
    ],
    "sg:phone":"+31 167 523 326",
    "sg:postcode":"4671 ES",
    "sg:province":"Noord-Brabant",
    "sg:tags":[
        "kleuteronderwijs",
        "basis-"
    ],
    "wof:name":"De Regenboog",
    "wof:placetype":"venue"
},
  "geometry": {"coordinates":[4.364748,51.637829],"type":"Point"}
}