{
  "type": "Feature",
  "properties": {
    "addr:full":"Molenweg 50 Maasbracht Limburg 6051 HK",
    "addr:housenumber":"50",
    "addr:postcode":"6051 hk",
    "addr:street":"Molenweg",
    "iso:country":"NL",
    "sg:address":"Molenweg 50",
    "sg:city":"Maasbracht",
    "sg:orig_category":"Autokeuringen",
    "sg:phone":"+31 475 461 807",
    "sg:postcode":"6051 HK",
    "sg:province":"Limburg",
    "wof:name":"Autobedrijf Vos Maasbracht Bv",
    "wof:placetype":"venue"
},
  "geometry": {"coordinates":[5.891545,51.145782],"type":"Point"}
}