{
  "type": "Feature",
  "properties": {
    "addr:full":"Jadestr 47 Breda Noord-Brabant 4817 JH",
    "addr:housenumber":"47",
    "addr:postcode":"4817 jh",
    "addr:street":"Jadestr",
    "iso:country":"NL",
    "sg:address":"Jadestr 47",
    "sg:city":"Breda",
    "sg:orig_category":"Artiesten/Gezelschappen",
    "sg:phone":"+31 76 522 6067",
    "sg:postcode":"4817 JH",
    "sg:province":"Noord-Brabant",
    "wof:name":"Dj Vortex Prod",
    "wof:placetype":"venue"
},
  "geometry": {"coordinates":[4.800987,51.589722],"type":"Point"}
}