{
  "type": "Feature",
  "properties": {
    "addr:full":"Keizersgr 15 Amsterdam North Holland 1015 CC",
    "addr:housenumber":"15",
    "addr:postcode":"1015 cc",
    "addr:street":"Keizersgr",
    "iso:country":"NL",
    "sg:address":"Keizersgr 15",
    "sg:city":"Amsterdam",
    "sg:classifiers":[
        {
            "category":"Travel",
            "subcategory":"Hotels & Motels",
            "type":"Entertainment"
        }
    ],
    "sg:phone":"+31 20 625 1364",
    "sg:postcode":"1015 CC",
    "sg:province":"North Holland",
    "sg:website":"http://www.hotelkeizersgracht.nl",
    "wof:name":"Keizersgracht, Hotel",
    "wof:placetype":"venue"
},
  "geometry": {"coordinates":[4.889816,52.378941],"type":"Point"}
}