{
  "type": "Feature",
  "properties": {
    "iso:country":"NL",
    "sg:address":"Oudestr 4",
    "sg:city":"Gramsbergen",
    "sg:orig_category":"Adviesbureaus Bedrijfsorganisatie",
    "sg:phone":"+31 524 561 749",
    "sg:postcode":"7783 AW",
    "sg:province":"Overijssel",
    "wof:name":"Mon\u00e9 & Oostveen",
    "wof:placetype":"venue"
},
  "geometry": {"coordinates":[6.67311,52.610382],"type":"Point"}
}