{
  "type": "Feature",
  "properties": {
    "addr:full":"Noord Ijsselkade 19 Oudewater Utrecht 3421 BD",
    "addr:housenumber":"19",
    "addr:postcode":"3421 bd",
    "addr:street":"Ijsselkade",
    "iso:country":"NL",
    "sg:address":"Noord Ijsselkade 19",
    "sg:city":"Oudewater",
    "sg:orig_category":"Wasserettes And Stomerijen",
    "sg:phone":"+31 348 563 385",
    "sg:postcode":"3421 BD",
    "sg:province":"Utrecht",
    "wof:name":"Stomerij L W De Wit",
    "wof:placetype":"venue"
},
  "geometry": {"coordinates":[4.8685541153,52.0232315063],"type":"Point"}
}