{
  "type": "Feature",
  "properties": {
    "addr:full":"Kl Oord 181 Arnhem Gelderland 6811 HZ",
    "addr:housenumber":"181",
    "addr:postcode":"6811 hz",
    "addr:street":"Kl Oord",
    "iso:country":"NL",
    "sg:address":"Kl Oord 181",
    "sg:city":"Arnhem",
    "sg:orig_category":"Verenigingen En Stichtingen",
    "sg:phone":"+31 26 442 2833",
    "sg:postcode":"6811 HZ",
    "sg:province":"Gelderland",
    "wof:name":"Vrijwilligerscentrale",
    "wof:placetype":"venue"
},
  "geometry": {"coordinates":[5.905078,51.980396],"type":"Point"}
}