{
  "type": "Feature",
  "properties": {
    "addr:full":"De Glazenmaker 68 Veldhoven North Brabant 5506 EP",
    "addr:housenumber":"68",
    "addr:postcode":"5506 ep",
    "addr:street":"De Glazenmaker",
    "iso:country":"NL",
    "sg:address":"De Glazenmaker 68",
    "sg:city":"Veldhoven",
    "sg:orig_category":"Schoonheidssalons",
    "sg:phone":"+31 40 255 7631",
    "sg:postcode":"5506 EP",
    "sg:province":"North Brabant",
    "wof:name":"Schoonheidssalon Bettine",
    "wof:placetype":"venue"
},
  "geometry": {"coordinates":[5.38637,51.414181],"type":"Point"}
}