{
  "type": "Feature",
  "properties": {
    "addr:full":"J D Huibersstraat 13 Deventer NL.08 7412 JS",
    "addr:housenumber":"13;nl.08",
    "addr:postcode":"7412 js",
    "addr:street":"Huibersstraat",
    "iso:country":"NL",
    "sg:address":"J D Huibersstraat 13",
    "sg:city":"Deventer",
    "sg:orig_category":"Diverse Consumentenartikelen Gh",
    "sg:phone":"+31 570 611 315",
    "sg:postcode":"7412 JS",
    "sg:province":"NL.08",
    "wof:name":"Tine",
    "wof:placetype":"venue"
},
  "geometry": {"coordinates":[6.138525,52.261047],"type":"Point"}
}