{
  "type": "Feature",
  "properties": {
    "addr:full":"Stadhuisplein 2 Vlissingen Zeeland 4382 LG",
    "addr:housenumber":"2",
    "addr:postcode":"4382 lg",
    "addr:street":"Stadhuisplein",
    "iso:country":"NL",
    "sg:address":"Stadhuisplein 2",
    "sg:city":"Vlissingen",
    "sg:orig_category":"Overheidsdiensten",
    "sg:phone":"+31 118 487 000",
    "sg:postcode":"4382 LG",
    "sg:province":"Zeeland",
    "wof:name":"Gemeente Vlissingen",
    "wof:placetype":"venue"
},
  "geometry": {"coordinates":[3.5688920021,51.447681427],"type":"Point"}
}