{
  "type": "Feature",
  "properties": {
    "iso:country":"NL",
    "sg:address":"Maasstr 116",
    "sg:city":"Amsterdam",
    "sg:orig_category":"Cafetaria'S",
    "sg:phone":"+31 20 662 0810",
    "sg:postcode":"1078 HN",
    "sg:province":"Noord-Holland",
    "wof:name":"Pauw, De",
    "wof:placetype":"venue"
},
  "geometry": {"coordinates":[4.895471,52.34383],"type":"Point"}
}