{
  "type": "Feature",
  "properties": {
    "addr:full":"J A Van Vurenstraat 23 Noordeloos South Holland 4225 RJ",
    "addr:housenumber":"23",
    "addr:postcode":"4225 rj",
    "addr:street":"J A Van Vurenstraat",
    "iso:country":"NL",
    "sg:address":"J A Van Vurenstraat 23",
    "sg:city":"Noordeloos",
    "sg:orig_category":"Goederenvervoer Over De Weg",
    "sg:phone":"+31 183 581 603",
    "sg:postcode":"4225 RJ",
    "sg:province":"South Holland",
    "wof:name":"Tas International",
    "wof:placetype":"venue"
},
  "geometry": {"coordinates":[4.944393,51.903973],"type":"Point"}
}