{
  "type": "Feature",
  "properties": {
    "addr:full":"Benschopln 21 Utrecht Utrecht 3527 XV",
    "addr:housenumber":"21",
    "addr:postcode":"3527 xv",
    "addr:street":"Benschopln",
    "iso:country":"NL",
    "sg:address":"Benschopln 21",
    "sg:city":"Utrecht",
    "sg:orig_category":"Begrafenisverzorging",
    "sg:phone":"+31 30 294 7242",
    "sg:postcode":"3527 XV",
    "sg:province":"Utrecht",
    "wof:name":"Dillema",
    "wof:placetype":"venue"
},
  "geometry": {"coordinates":[5.101819,52.076851],"type":"Point"}
}