{
  "type": "Feature",
  "properties": {
    "addr:full":"Gerberaln 65 Naaldwyk South Holland 2671 KB",
    "addr:housenumber":"65",
    "addr:postcode":"2671 kb",
    "addr:street":"Gerberaln",
    "iso:country":"NL",
    "sg:address":"Gerberaln 65",
    "sg:city":"Naaldwyk",
    "sg:orig_category":"Kassenonderhoud",
    "sg:phone":"+31 6 22473704",
    "sg:postcode":"2671 KB",
    "sg:province":"South Holland",
    "wof:name":"Tanke",
    "wof:placetype":"venue"
},
  "geometry": {"coordinates":[4.205249,51.991398],"type":"Point"}
}