{
  "type": "Feature",
  "properties": {
    "addr:full":"Jan Thijssenweg 16 Rijswijk Zh South Holland 2289 AB",
    "addr:housenumber":"16",
    "addr:postcode":"2289 ab",
    "addr:street":"Jan Thijssenweg",
    "iso:country":"NL",
    "sg:address":"Jan Thijssenweg 16",
    "sg:city":"Rijswijk Zh",
    "sg:orig_category":"Kermissen And Pretparken",
    "sg:phone":"+31 70 399 9305",
    "sg:postcode":"2289 AB",
    "sg:province":"South Holland",
    "wof:name":"Familiepark Drievliet Bv",
    "wof:placetype":"venue"
},
  "geometry": {"coordinates":[4.3451,52.05397],"type":"Point"}
}