{
  "type": "Feature",
  "properties": {
    "iso:country":"NL",
    "sg:address":"Grintweg 4",
    "sg:city":"Moerdijk",
    "sg:orig_category":"Meubelzaken, Woning- And Keukeninrichting",
    "sg:phone":"+31 168 412 957",
    "sg:postcode":"4782 AE",
    "sg:province":"North Brabant",
    "wof:name":"Belone",
    "wof:placetype":"venue"
},
  "geometry": {"coordinates":[4.624614,51.702065],"type":"Point"}
}