{
  "type": "Feature",
  "properties": {
    "addr:full":"Philippostr 10 Sassenheim Zuid-Holland 2171 DG",
    "addr:housenumber":"10",
    "addr:postcode":"2171 dg",
    "addr:street":"Philippostr",
    "iso:country":"NL",
    "sg:address":"Philippostr 10",
    "sg:city":"Sassenheim",
    "sg:orig_category":"Administratie- En Boekhoudkantoren",
    "sg:phone":"+31 252 210 498",
    "sg:postcode":"2171 DG",
    "sg:province":"Zuid-Holland",
    "wof:name":"Blom, W",
    "wof:placetype":"venue"
},
  "geometry": {"coordinates":[4.51538,52.220119],"type":"Point"}
}