{
  "type": "Feature",
  "properties": {
    "addr:full":"Arnhemseweg 213 Amersfoort Utrecht 3817 CG",
    "addr:housenumber":"213",
    "addr:postcode":"3817 cg",
    "addr:street":"Arnhemseweg",
    "iso:country":"NL",
    "sg:address":"Arnhemseweg 213",
    "sg:city":"Amersfoort",
    "sg:orig_category":"Marktonderzoekbureaus",
    "sg:phone":"+31 33 461 3124",
    "sg:postcode":"3817 CG",
    "sg:province":"Utrecht",
    "wof:name":"Adviesbureau P.H. Stiel",
    "wof:placetype":"venue"
},
  "geometry": {"coordinates":[5.397241,52.135406],"type":"Point"}
}