{
  "type": "Feature",
  "properties": {
    "iso:country":"NL",
    "sg:address":"Rootstraat 9",
    "sg:city":"Oudewater",
    "sg:orig_category":"Binnenhuisarchitecten",
    "sg:phone":"+31 348 562 917",
    "sg:postcode":"3421 AV",
    "sg:province":"Utrecht",
    "wof:name":"As Montage & Afwerking",
    "wof:placetype":"venue"
},
  "geometry": {"coordinates":[4.8711,52.023155],"type":"Point"}
}