{
  "type": "Feature",
  "properties": {
    "addr:full":"Rootstraat 9 Oudewater Utrecht 3421 AV",
    "addr:housenumber":"9",
    "addr:postcode":"3421 av",
    "addr:street":"Rootstraat",
    "iso:country":"NL",
    "sg:address":"Rootstraat 9",
    "sg:city":"Oudewater",
    "sg:orig_category":"Binnenhuisarchitecten",
    "sg:phone":"+31 348 562 917",
    "sg:postcode":"3421 AV",
    "sg:province":"Utrecht",
    "wof:name":"As Montage & Afwerking",
    "wof:placetype":"venue"
},
  "geometry": {"coordinates":[4.8711,52.023155],"type":"Point"}
}