{
  "type": "Feature",
  "properties": {
    "addr:full":"Pk Arenberg 119 De Bilt Utrecht 3731 ER",
    "addr:housenumber":"119",
    "addr:postcode":"3731 er",
    "addr:street":"Pk Arenberg",
    "iso:country":"NL",
    "sg:address":"Pk Arenberg 119",
    "sg:city":"De Bilt",
    "sg:orig_category":"Adviesbureaus Bedrijfsorganisatie",
    "sg:phone":"+31 30 220 0316",
    "sg:postcode":"3731 ER",
    "sg:province":"Utrecht",
    "wof:name":"Rest Bv, C & C Van",
    "wof:placetype":"venue"
},
  "geometry": {"coordinates":[5.171223,52.106518],"type":"Point"}
}