{
  "type": "Feature",
  "properties": {
    "addr:full":"Pinaskade 40 Zoetermeer South Holland 2725 EP",
    "addr:housenumber":"40",
    "addr:postcode":"2725 ep",
    "addr:street":"Pinaskade",
    "iso:country":"NL",
    "sg:address":"Pinaskade 40",
    "sg:city":"Zoetermeer",
    "sg:orig_category":"Boekhouders",
    "sg:phone":"+31 79 343 7608",
    "sg:postcode":"2725 EP",
    "sg:province":"South Holland",
    "wof:name":"R.R. Newalsing",
    "wof:placetype":"venue"
},
  "geometry": {"coordinates":[4.499881,52.074688],"type":"Point"}
}