{
  "type": "Feature",
  "properties": {
    "addr:full":"Voorheuvel 63-65 Zeist Utrecht 3701 JC",
    "addr:housenumber":"63-65",
    "addr:postcode":"3701 jc",
    "addr:street":"Voorheuvel",
    "iso:country":"NL",
    "sg:address":"Voorheuvel 63-65",
    "sg:city":"Zeist",
    "sg:orig_category":"Loodgieters",
    "sg:phone":"+31 30 691 6307",
    "sg:postcode":"3701 JC",
    "sg:province":"Utrecht",
    "wof:name":"Alblas, Fa",
    "wof:placetype":"venue"
},
  "geometry": {"coordinates":[5.240917,52.088547],"type":"Point"}
}