{
  "type": "Feature",
  "properties": {
    "iso:country":"NL",
    "sg:address":"Wezenland 2",
    "sg:city":"Enkhuizen",
    "sg:orig_category":"Schilders",
    "sg:phone":"+31 228 315 183",
    "sg:postcode":"1602 MA",
    "sg:province":"North Holland",
    "wof:name":"Dirven Schildersbedrijf Herman",
    "wof:placetype":"venue"
},
  "geometry": {"coordinates":[5.273995,52.713638],"type":"Point"}
}