{
  "type": "Feature",
  "properties": {
    "iso:country":"NL",
    "sg:address":"Hoofdstraat 2",
    "sg:city":"Leiderdorp",
    "sg:orig_category":"Bedrijfs- And Managementsconsultants",
    "sg:phone":"+31 71 542 3761",
    "sg:postcode":"2351 AJ",
    "sg:province":"South Holland",
    "wof:name":"Philosopher Stone",
    "wof:placetype":"venue"
},
  "geometry": {"coordinates":[4.522633,52.151936],"type":"Point"}
}