{
  "type": "Feature",
  "properties": {
    "iso:country":"NL",
    "sg:address":"De Schans 18",
    "sg:city":"Amersfoort",
    "sg:orig_category":"Sportverenigingen En Ontspannings- Verenigingen",
    "sg:phone":"+31 33 480 7683",
    "sg:postcode":"3813 TW",
    "sg:province":"Utrecht",
    "wof:name":"Eemkruisers, De",
    "wof:placetype":"venue"
},
  "geometry": {"coordinates":[5.375162,52.168064],"type":"Point"}
}