{
  "type": "Feature",
  "properties": {
    "addr:full":"Midscheeps 64 Delfzyl Groningen 9934 RT",
    "addr:housenumber":"64",
    "addr:postcode":"9934 rt",
    "addr:street":"Midscheeps",
    "iso:country":"NL",
    "sg:address":"Midscheeps 64",
    "sg:city":"Delfzyl",
    "sg:orig_category":"Adviesbureaus Bedrijfsorganisatie",
    "sg:phone":"+31 596 627 194",
    "sg:postcode":"9934 RT",
    "sg:province":"Groningen",
    "wof:name":"Lips, O J M",
    "wof:placetype":"venue"
},
  "geometry": {"coordinates":[6.918614,53.324245],"type":"Point"}
}