{
  "type": "Feature",
  "properties": {
    "addr:full":"Strindbergzyde 8 Zoetermeer Zuid-Holland 2725 PJ",
    "addr:housenumber":"8",
    "addr:postcode":"2725 pj",
    "addr:street":"Strindbergzyde",
    "iso:country":"NL",
    "sg:address":"Strindbergzyde 8",
    "sg:city":"Zoetermeer",
    "sg:orig_category":"Vertaalbureaus",
    "sg:phone":"+31 79 331 3637",
    "sg:postcode":"2725 PJ",
    "sg:province":"Zuid-Holland",
    "wof:name":"Blaas",
    "wof:placetype":"venue"
},
  "geometry": {"coordinates":[4.493866,52.069763],"type":"Point"}
}