{
  "type": "Feature",
  "properties": {
    "iso:country":"NL",
    "sg:address":"Strindbergzyde 8",
    "sg:city":"Zoetermeer",
    "sg:orig_category":"Vertaalbureaus",
    "sg:phone":"+31 79 331 3637",
    "sg:postcode":"2725 PJ",
    "sg:province":"Zuid-Holland",
    "wof:name":"Blaas",
    "wof:placetype":"venue"
},
  "geometry": {"coordinates":[4.493866,52.069763],"type":"Point"}
}