{
  "type": "Feature",
  "properties": {
    "addr:full":"Hooftskd 60 S Gravenhage Zuid-Holland 2526 KA",
    "addr:housenumber":"60;gravenhage",
    "addr:postcode":"2526 ka",
    "addr:street":"Hooftskd;S",
    "iso:country":"NL",
    "sg:address":"Hooftskd 60",
    "sg:city":"S Gravenhage",
    "sg:orig_category":"Adviesbureaus Bedrijfsorganisatie",
    "sg:phone":"+31 6 53950275",
    "sg:postcode":"2526 KA",
    "sg:province":"Zuid-Holland",
    "wof:name":"Cabanon Bv",
    "wof:placetype":"venue"
},
  "geometry": {"coordinates":[4.30555,52.0681],"type":"Point"}
}