{
  "type": "Feature",
  "properties": {
    "iso:country":"NL",
    "sg:address":"Spoorln 13",
    "sg:city":"Capelle Ad Yssel",
    "sg:orig_category":"Beveiliging",
    "sg:phone":"+31 10 284 9330",
    "sg:postcode":"2908 BG",
    "sg:province":"South Holland",
    "wof:name":"Jpz",
    "wof:placetype":"venue"
},
  "geometry": {"coordinates":[4.5846,51.923401],"type":"Point"}
}