{
  "type": "Feature",
  "properties": {
    "addr:full":"Monnikenbos 3 Zoetermeer Zuid-Holland 2716 GT",
    "addr:housenumber":"3",
    "addr:postcode":"2716 gt",
    "addr:street":"Monnikenbos",
    "iso:country":"NL",
    "sg:address":"Monnikenbos 3",
    "sg:city":"Zoetermeer",
    "sg:orig_category":"Fietshandelaren",
    "sg:phone":"+31 79 321 1540",
    "sg:postcode":"2716 GT",
    "sg:province":"Zuid-Holland",
    "wof:name":"Tweewielercentr Zoetermeer",
    "wof:placetype":"venue"
},
  "geometry": {"coordinates":[4.470024,52.05714],"type":"Point"}
}