{
  "type": "Feature",
  "properties": {
    "addr:full":"Cornelis Trooststraat 34 Amsterdam Noord-Holland 1072 JG",
    "addr:housenumber":"34",
    "addr:postcode":"1072 jg",
    "addr:street":"Cornelis Trooststraat",
    "iso:country":"NL",
    "sg:address":"Cornelis Trooststraat 34",
    "sg:city":"Amsterdam",
    "sg:orig_category":"Autokeuringen",
    "sg:phone":"+31 20 662 7752",
    "sg:postcode":"1072 JG",
    "sg:province":"Noord-Holland",
    "wof:name":"Motorrevisiebedrijf Tiggeler",
    "wof:placetype":"venue"
},
  "geometry": {"coordinates":[4.888209,52.350376],"type":"Point"}
}