{
  "type": "Feature",
  "properties": {
    "addr:full":"Forel 42 Amersfoort Utrecht 3824 LB",
    "addr:housenumber":"42",
    "addr:postcode":"3824 lb",
    "addr:street":"Forel",
    "iso:country":"NL",
    "sg:address":"Forel 42",
    "sg:city":"Amersfoort",
    "sg:classifiers":[
        {
            "category":"Utilities",
            "subcategory":"Cable",
            "type":"Services"
        }
    ],
    "sg:phone":"+31 33 455 2961",
    "sg:postcode":"3824 LB",
    "sg:province":"Utrecht",
    "sg:tags":[
        "masseur",
        "en",
        "heilgymnasten"
    ],
    "wof:name":"Touching",
    "wof:placetype":"venue"
},
  "geometry": {"coordinates":[5.366479,52.20356],"type":"Point"}
}