{
  "type": "Feature",
  "properties": {
    "addr:full":"Edisonstraat 13 Zoetermeer Zuid-Holland 2723 RS",
    "addr:housenumber":"13",
    "addr:postcode":"2723 rs",
    "addr:street":"Edisonstraat",
    "iso:country":"NL",
    "sg:address":"Edisonstraat 13",
    "sg:city":"Zoetermeer",
    "sg:orig_category":"Wasserettes And Stomerijen",
    "sg:phone":"+31 79 341 8641",
    "sg:postcode":"2723 RS",
    "sg:province":"Zuid-Holland",
    "wof:name":"Textielreiniging Frista",
    "wof:placetype":"venue"
},
  "geometry": {"coordinates":[4.5219230652,52.0616760254],"type":"Point"}
}