{
  "type": "Feature",
  "properties": {
    "iso:country":"NL",
    "sg:address":"Remusln 58",
    "sg:city":"Eindhoven",
    "sg:orig_category":"Adviesbureaus",
    "sg:phone":"+31 40 213 5196",
    "sg:postcode":"5631 JR",
    "sg:province":"Noord-Brabant",
    "wof:name":"Heeswijk, Van",
    "wof:placetype":"venue"
},
  "geometry": {"coordinates":[5.50844,51.45776],"type":"Point"}
}