{
  "type": "Feature",
  "properties": {
    "addr:full":"Boekenderweg 2 Thorn Limburg 6017 CP",
    "addr:housenumber":"2",
    "addr:postcode":"6017 cp",
    "addr:street":"Boekenderweg",
    "iso:country":"NL",
    "sg:address":"Boekenderweg 2",
    "sg:city":"Thorn",
    "sg:classifiers":[
        {
            "category":"Fast Food",
            "type":"Food & Drink"
        }
    ],
    "sg:phone":"+31 475 561 340",
    "sg:postcode":"6017 CP",
    "sg:province":"Limburg",
    "sg:tags":[
        "afhaal",
        "restaurant"
    ],
    "wof:name":"Snackbar 'T Hemeltje",
    "wof:placetype":"venue"
},
  "geometry": {"coordinates":[5.841043,51.165329],"type":"Point"}
}