{
  "type": "Feature",
  "properties": {
    "addr:full":"Schoolwg 4 Den Helder Noord-Holland 1786 BA",
    "addr:housenumber":"4",
    "addr:postcode":"1786 ba",
    "addr:street":"Schoolwg",
    "iso:country":"NL",
    "sg:address":"Schoolwg 4",
    "sg:city":"Den Helder",
    "sg:orig_category":"Keukens",
    "sg:phone":"+31 223 642 417",
    "sg:postcode":"1786 BA",
    "sg:province":"Noord-Holland",
    "wof:name":"Kameleonkeukens",
    "wof:placetype":"venue"
},
  "geometry": {"coordinates":[4.75808,52.89706],"type":"Point"}
}