{
  "type": "Feature",
  "properties": {
    "addr:full":"Pr Hendrikln 27 Zeist Utrecht 3701 CL",
    "addr:housenumber":"27",
    "addr:postcode":"3701",
    "iso:country":"NL",
    "sg:address":"Pr Hendrikln 27",
    "sg:city":"Zeist",
    "sg:orig_category":"Ziekenhuizen, Sanatoria, Verpleeghuizen",
    "sg:phone":"+31 30 691 8486",
    "sg:postcode":"3701 CL",
    "sg:province":"Utrecht",
    "wof:name":"Zonneburg",
    "wof:placetype":"venue"
},
  "geometry": {"coordinates":[5.252182,52.087795],"type":"Point"}
}