{
  "type": "Feature",
  "properties": {
    "addr:full":"Biezenweg 2 Beek En Donk Noord-Brabant 5741 SB",
    "addr:housenumber":"2",
    "addr:postcode":"5741 sb",
    "addr:street":"Biezenweg",
    "iso:country":"NL",
    "sg:address":"Biezenweg 2",
    "sg:city":"Beek En Donk",
    "sg:orig_category":"Bloemen And Planten",
    "sg:phone":"+31 492 461 310",
    "sg:postcode":"5741 SB",
    "sg:province":"Noord-Brabant",
    "wof:name":"Tuincentrum Groenrijk De Biezen",
    "wof:placetype":"venue"
},
  "geometry": {"coordinates":[5.647541,51.531361],"type":"Point"}
}