{
  "type": "Feature",
  "properties": {
    "iso:country":"NL",
    "sg:address":"Steinln 50",
    "sg:city":"Doetinchem",
    "sg:orig_category":"Bejaarden - Verzorgingstehuizen",
    "sg:phone":"+31 314 323 265",
    "sg:postcode":"7001 DK",
    "sg:province":"Gelderland",
    "wof:name":"Croonemate",
    "wof:placetype":"venue"
},
  "geometry": {"coordinates":[6.293904,51.968338],"type":"Point"}
}