{
  "type": "Feature",
  "properties": {
    "addr:full":"Buizerdln 6 116 Nieuwegein Utrecht 3435 SB",
    "addr:housenumber":"6",
    "addr:postcode":"116;3435 sb",
    "addr:street":"Buizerdln",
    "iso:country":"NL",
    "sg:address":"Buizerdln 6 116",
    "sg:city":"Nieuwegein",
    "sg:orig_category":"Schoenen",
    "sg:phone":"+31 30 603 3966",
    "sg:postcode":"3435 SB",
    "sg:province":"Utrecht",
    "wof:name":"Genemans Bv",
    "wof:placetype":"venue"
},
  "geometry": {"coordinates":[5.082197,52.027325],"type":"Point"}
}