{
  "type": "Feature",
  "properties": {
    "addr:full":"Vissersdk 14 Werkendam Noord-Brabant 4251 ED",
    "addr:housenumber":"14",
    "addr:postcode":"4251 ed",
    "addr:street":"Vissersdk",
    "iso:country":"NL",
    "sg:address":"Vissersdk 14",
    "sg:city":"Werkendam",
    "sg:orig_category":"Product-Promotie",
    "sg:phone":"+31 183 505 922",
    "sg:postcode":"4251 ED",
    "sg:province":"Noord-Brabant",
    "wof:name":"Multi Promotions Bv",
    "wof:placetype":"venue"
},
  "geometry": {"coordinates":[4.89456,51.81361],"type":"Point"}
}