{
  "type": "Feature",
  "properties": {
    "addr:full":"Swinsedreef 16 Rockanje Zuid-Holland 3235 AR",
    "addr:housenumber":"16",
    "addr:postcode":"3235",
    "addr:street":"Swinsedreef",
    "iso:country":"NL",
    "sg:address":"Swinsedreef 16",
    "sg:city":"Rockanje",
    "sg:orig_category":"Administratie- En Boekhoudkantoren",
    "sg:phone":"+31 181 401 667",
    "sg:postcode":"3235 AR",
    "sg:province":"Zuid-Holland",
    "wof:name":"Adfiro Bv",
    "wof:placetype":"venue"
},
  "geometry": {"coordinates":[4.058352,51.872795],"type":"Point"}
}