{
  "type": "Feature",
  "properties": {
    "addr:full":"Voermansweide 1 Nieuwegein Utrecht 3437 DG",
    "addr:housenumber":"1",
    "addr:postcode":"3437 dg",
    "addr:street":"Voermansweide",
    "iso:country":"NL",
    "sg:address":"Voermansweide 1",
    "sg:city":"Nieuwegein",
    "sg:orig_category":"Adviesbureaus Bedrijfsorganisatie",
    "sg:phone":"+31 30 605 4548",
    "sg:postcode":"3437 DG",
    "sg:province":"Utrecht",
    "wof:name":"Shift+",
    "wof:placetype":"venue"
},
  "geometry": {"coordinates":[5.06823,52.046886],"type":"Point"}
}