{
  "type": "Feature",
  "properties": {
    "addr:full":"Zuivelstr 10 Bergen Op Zoom North Brabant 4611 PH",
    "addr:housenumber":"10",
    "addr:postcode":"4611",
    "addr:street":"Zuivelstr",
    "iso:country":"NL",
    "sg:address":"Zuivelstr 10",
    "sg:city":"Bergen Op Zoom",
    "sg:classifiers":[
        {
            "category":"Shopping",
            "subcategory":"Adult",
            "type":"Retail Goods"
        }
    ],
    "sg:phone":"+31 164 210 133",
    "sg:postcode":"4611 PH",
    "sg:province":"North Brabant",
    "sg:tags":[
        "lingerie",
        "en",
        "tricotage"
    ],
    "wof:name":"Livera",
    "wof:placetype":"venue"
},
  "geometry": {"coordinates":[4.288333,51.494797],"type":"Point"}
}