{
  "type": "Feature",
  "properties": {
    "addr:full":"Doctor Schaepmanlaan 10 Bussum North Holland 1402 BT",
    "addr:housenumber":"10",
    "addr:postcode":"1402 bt",
    "addr:street":"Doctor Schaepmanlaan",
    "iso:country":"NL",
    "sg:address":"Doctor Schaepmanlaan 10",
    "sg:city":"Bussum",
    "sg:orig_category":"Overheidsdiensten",
    "sg:phone":"+31 35 692 1969",
    "sg:postcode":"1402 BT",
    "sg:province":"North Holland",
    "wof:name":"Cultureel Educatie Centrum Uitwijk",
    "wof:placetype":"venue"
},
  "geometry": {"coordinates":[5.1710438728,52.2677268982],"type":"Point"}
}