{
  "type": "Feature",
  "properties": {
    "addr:full":"Hillenraadstr 11 Breda North Brabant 4834 JD",
    "addr:housenumber":"11",
    "addr:postcode":"4834 jd",
    "addr:street":"Hillenraadstr",
    "iso:country":"NL",
    "sg:address":"Hillenraadstr 11",
    "sg:city":"Breda",
    "sg:orig_category":"Bedrijfsopleidingen",
    "sg:phone":"+31 76 565 4735",
    "sg:postcode":"4834 JD",
    "sg:province":"North Brabant",
    "wof:name":"Hoek, Van",
    "wof:placetype":"venue"
},
  "geometry": {"coordinates":[4.800744,51.572723],"type":"Point"}
}