{
  "type": "Feature",
  "properties": {
    "addr:full":"Strijdbijl 4 Beuningen Gld Gelderland 6641 HR",
    "addr:housenumber":"4",
    "addr:postcode":"6641 hr",
    "addr:street":"Strijdbijl",
    "iso:country":"NL",
    "sg:address":"Strijdbijl 4",
    "sg:city":"Beuningen Gld",
    "sg:orig_category":"Kantoorartikelen",
    "sg:phone":"+31 24 677 5478",
    "sg:postcode":"6641 HR",
    "sg:province":"Gelderland",
    "wof:name":"H.B. Bartels Roerende Goederen",
    "wof:placetype":"venue"
},
  "geometry": {"coordinates":[5.7658672333,51.8627624512],"type":"Point"}
}