{
  "type": "Feature",
  "properties": {
    "addr:full":"Kruisstraat 12 Beilen Provincie Drenthe 9411 PE",
    "addr:housenumber":"12",
    "addr:postcode":"9411 pe",
    "addr:street":"Kruisstraat;Provincie Drenthe",
    "iso:country":"NL",
    "sg:address":"Kruisstraat 12",
    "sg:city":"Beilen",
    "sg:classifiers":[
        {
            "category":"Fast Food",
            "type":"Food & Drink"
        }
    ],
    "sg:phone":"+31 593 523 828",
    "sg:postcode":"9411 PE",
    "sg:province":"Provincie Drenthe",
    "sg:tags":[
        "afhaal",
        "restaurant"
    ],
    "wof:name":"Restaurant/Snackbar City",
    "wof:placetype":"venue"
},
  "geometry": {"coordinates":[6.518026,52.858639],"type":"Point"}
}