{
  "type": "Feature",
  "properties": {
    "addr:full":"Tamboerpad 2 Leiden Zuid-Holland 2316 ZW",
    "addr:housenumber":"2",
    "addr:postcode":"2316 zw",
    "addr:street":"Tamboerpad",
    "iso:country":"NL",
    "sg:address":"Tamboerpad 2",
    "sg:city":"Leiden",
    "sg:orig_category":"Kinderopvang Behalve Thuis",
    "sg:phone":"+31 71 521 0533",
    "sg:postcode":"2316 ZW",
    "sg:province":"Zuid-Holland",
    "wof:name":"Kinderdagverblijf Petteflet",
    "wof:placetype":"venue"
},
  "geometry": {"coordinates":[4.487415,52.167931],"type":"Point"}
}