{
  "type": "Feature",
  "properties": {
    "iso:country":"NL",
    "sg:address":"Pleinstr 4",
    "sg:city":"Bergambacht",
    "sg:orig_category":"Meubelen",
    "sg:phone":"+31 182 357 123",
    "sg:postcode":"2861 XH",
    "sg:province":"South Holland",
    "wof:name":"Now Bv",
    "wof:placetype":"venue"
},
  "geometry": {"coordinates":[4.783734,51.93557],"type":"Point"}
}