{
  "type": "Feature",
  "properties": {
    "addr:full":"Vlasleeuwenbek 14 Purmerend Noord-Holland 1441 TG",
    "addr:housenumber":"14",
    "addr:postcode":"1441 tg",
    "addr:street":"Vlasleeuwenbek",
    "iso:country":"NL",
    "sg:address":"Vlasleeuwenbek 14",
    "sg:city":"Purmerend",
    "sg:orig_category":"Psychotherapeuten",
    "sg:phone":"+31 299 472 626",
    "sg:postcode":"1441 TG",
    "sg:province":"Noord-Holland",
    "wof:name":"Hellingman, Drs J D",
    "wof:placetype":"venue"
},
  "geometry": {"coordinates":[4.95246,52.49633],"type":"Point"}
}