{
  "type": "Feature",
  "properties": {
    "addr:full":"Herenwal 86 Heerenveen Provincie Friesland 8441 BC",
    "addr:housenumber":"86",
    "addr:postcode":"8441 bc",
    "addr:street":"Herenwal;Provincie Friesland",
    "iso:country":"NL",
    "sg:address":"Herenwal 86",
    "sg:city":"Heerenveen",
    "sg:orig_category":"Automaterialen En Gereedschappen",
    "sg:phone":"+31 513 623 178",
    "sg:postcode":"8441 BC",
    "sg:province":"Provincie Friesland",
    "wof:name":"Vos, J H De",
    "wof:placetype":"venue"
},
  "geometry": {"coordinates":[5.916181,52.962959],"type":"Point"}
}