{
  "type": "Feature",
  "properties": {
    "addr:full":"Markt 12 Helmond Noord-Brabant 5701 RK",
    "addr:housenumber":"12",
    "addr:postcode":"5701 rk",
    "addr:street":"Markt",
    "iso:country":"NL",
    "sg:address":"Markt 12",
    "sg:city":"Helmond",
    "sg:orig_category":"Kinderkleding",
    "sg:phone":"+31 492 390 720",
    "sg:postcode":"5701 RK",
    "sg:province":"Noord-Brabant",
    "wof:name":"Esprit",
    "wof:placetype":"venue"
},
  "geometry": {"coordinates":[5.656139,51.479095],"type":"Point"}
}