{
  "type": "Feature",
  "properties": {
    "addr:full":"Strawinskylaan 3127 Amsterdam North Holland 1077 ZX",
    "addr:housenumber":"3127",
    "addr:postcode":"1077 zx",
    "addr:street":"Strawinskylaan",
    "iso:country":"NL",
    "sg:address":"Strawinskylaan 3127",
    "sg:city":"Amsterdam",
    "sg:classifiers":[
        {
            "category":"Professional",
            "subcategory":"Accounting & Tax Preparation",
            "type":"Services"
        }
    ],
    "sg:phone":"+31 20 568 4100",
    "sg:postcode":"1077 ZX",
    "sg:province":"North Holland",
    "sg:tags":[
        "accountant"
    ],
    "wof:name":"Pricewaterhousecoopers",
    "wof:placetype":"venue"
},
  "geometry": {"coordinates":[4.869371,52.340435],"type":"Point"}
}