{
  "type": "Feature",
  "properties": {
    "addr:full":"Waalstr 180Hs Amsterdam Noord-Holland 1079 EJ",
    "addr:housenumber":"180hs",
    "addr:postcode":"1079 ej",
    "addr:street":"Waalstr",
    "iso:country":"NL",
    "sg:address":"Waalstr 180Hs",
    "sg:city":"Amsterdam",
    "sg:orig_category":"Journalisten Freelance",
    "sg:phone":"+31 20 404 4067",
    "sg:postcode":"1079 EJ",
    "sg:province":"Noord-Holland",
    "wof:name":"Astrid Boshuisen",
    "wof:placetype":"venue"
},
  "geometry": {"coordinates":[4.90167,52.341427],"type":"Point"}
}