{
  "type": "Feature",
  "properties": {
    "addr:full":"Septemb 1944 Str 111 Heerlen Limburg 6418 AW",
    "addr:housenumber":"111",
    "addr:postcode":"6418 aw",
    "addr:street":"Str",
    "iso:country":"NL",
    "sg:address":"Septemb 1944 Str 111",
    "sg:city":"Heerlen",
    "sg:orig_category":"Onderhoudswerken",
    "sg:phone":"+31 6 27552313",
    "sg:postcode":"6418 AW",
    "sg:province":"Limburg",
    "wof:name":"Keba",
    "wof:placetype":"venue"
},
  "geometry": {"coordinates":[5.99949,50.87011],"type":"Point"}
}