{
  "type": "Feature",
  "properties": {
    "addr:full":"Burg V Heusdenwg 42A Terschelling West Provincie Friesland 8881 EE",
    "addr:housenumber":"42a",
    "addr:postcode":"8881 ee",
    "addr:street":"Burg V Heusdenwg;Friesland",
    "iso:country":"NL",
    "sg:address":"Burg V Heusdenwg 42A",
    "sg:city":"Terschelling West",
    "sg:classifiers":[
        {
            "category":"Travel",
            "subcategory":"Hotels & Motels",
            "type":"Entertainment"
        }
    ],
    "sg:phone":"+31 562 442 305",
    "sg:postcode":"8881 EE",
    "sg:province":"Provincie Friesland",
    "sg:website":"http://www.dellewal.nl",
    "wof:name":"Dellewal",
    "wof:placetype":"venue"
},
  "geometry": {"coordinates":[5.214094,53.360294],"type":"Point"}
}