{
  "type": "Feature",
  "properties": {
    "addr:full":"Arnoldystraat 21 Haarlem Noord-Holland 2024 VG",
    "addr:housenumber":"21",
    "addr:postcode":"2024 vg",
    "addr:street":"Arnoldystraat",
    "iso:country":"NL",
    "sg:address":"Arnoldystraat 21",
    "sg:city":"Haarlem",
    "sg:orig_category":"Biljart- And Snookerzalen",
    "sg:phone":"+31 23 526 2181",
    "sg:postcode":"2024 VG",
    "sg:province":"Noord-Holland",
    "wof:name":"1E Haarlemsche Biljartacademie",
    "wof:placetype":"venue"
},
  "geometry": {"coordinates":[4.644226,52.403107],"type":"Point"}
}