{
  "type": "Feature",
  "properties": {
    "addr:full":"De Vrieshof 10 Waalre Noord-Brabant 5581 TW",
    "addr:housenumber":"10",
    "addr:postcode":"5581 tw",
    "addr:street":"De Vrieshof",
    "iso:country":"NL",
    "sg:address":"De Vrieshof 10",
    "sg:city":"Waalre",
    "sg:orig_category":"Adviesbureaus Bedrijfsorganisatie",
    "sg:phone":"+31 40 221 3596",
    "sg:postcode":"5581 TW",
    "sg:province":"Noord-Brabant",
    "wof:name":"Melgert",
    "wof:placetype":"venue"
},
  "geometry": {"coordinates":[5.44307,51.390194],"type":"Point"}
}