{
  "type": "Feature",
  "properties": {
    "addr:full":"Marktstr 19 Aalsmeer Noord-Holland 1431 BD",
    "addr:housenumber":"19",
    "addr:postcode":"1431 bd",
    "addr:street":"Marktstr",
    "iso:country":"NL",
    "sg:address":"Marktstr 19",
    "sg:city":"Aalsmeer",
    "sg:orig_category":"Galeries",
    "sg:phone":"+31 297 368 378",
    "sg:postcode":"1431 BD",
    "sg:province":"Noord-Holland",
    "sg:website":"http://www.deoudeveiling.nl",
    "wof:name":"Oude Veiling, De",
    "wof:placetype":"venue"
},
  "geometry": {"coordinates":[4.749388,52.268147],"type":"Point"}
}