{
  "type": "Feature",
  "properties": {
    "addr:full":"Molenakkerstraat 108 Gemert Noord-Brabant 5421 BP",
    "addr:housenumber":"108",
    "addr:postcode":"5421 bp",
    "addr:street":"Molenakkerstraat",
    "iso:country":"NL",
    "sg:address":"Molenakkerstraat 108",
    "sg:city":"Gemert",
    "sg:classifiers":[
        {
            "category":"Communications",
            "subcategory":"Television Station",
            "type":"Services"
        }
    ],
    "sg:phone":"+31 492 364 906",
    "sg:postcode":"5421 BP",
    "sg:province":"Noord-Brabant",
    "sg:tags":[
        "video",
        "audio",
        "verhuur"
    ],
    "wof:name":"Videotheek Van Berlo",
    "wof:placetype":"venue"
},
  "geometry": {"coordinates":[5.691887,51.557407],"type":"Point"}
}