{
  "type": "Feature",
  "properties": {
    "iso:country":"NL",
    "sg:address":"Zalmhaven 27",
    "sg:city":"Rotterdam",
    "sg:orig_category":"Organisaties And Verenigingen",
    "sg:phone":"+31 10 412 0920",
    "sg:postcode":"3011 BR",
    "sg:province":"Zuid-Holland",
    "wof:name":"Pisculentis Studentenvereniging",
    "wof:placetype":"venue"
},
  "geometry": {"coordinates":[4.4797348976,51.9115180969],"type":"Point"}
}