{
  "type": "Feature",
  "properties": {
    "addr:full":"1E H De Grootstr 20 Amsterdam Noord-Holland 1052 KR",
    "addr:housenumber":"20",
    "addr:postcode":"1052 kr",
    "addr:street":"1E H De Grootstr",
    "iso:country":"NL",
    "sg:address":"1E H De Grootstr 20",
    "sg:city":"Amsterdam",
    "sg:orig_category":"Grafisch Ontwerpers",
    "sg:phone":"+31 20 681 2907",
    "sg:postcode":"1052 KR",
    "sg:province":"Noord-Holland",
    "wof:name":"Jonge, K De",
    "wof:placetype":"venue"
},
  "geometry": {"coordinates":[4.874773,52.376011],"type":"Point"}
}