{
  "type": "Feature",
  "properties": {
    "addr:full":"P Cornelisz Hooftstr 33/3 Amsterdam North Holland 1071 BM",
    "addr:housenumber":"33 / 3",
    "addr:postcode":"1071 bm",
    "addr:street":"P Cornelisz Hooftstr",
    "iso:country":"NL",
    "sg:address":"P Cornelisz Hooftstr 33/3",
    "sg:city":"Amsterdam",
    "sg:orig_category":"Public Relationbureaus",
    "sg:phone":"+31 20 470 6550",
    "sg:postcode":"1071 BM",
    "sg:province":"North Holland",
    "wof:name":"Teledimension Bv",
    "wof:placetype":"venue"
},
  "geometry": {"coordinates":[4.882548,52.3606],"type":"Point"}
}