{
  "type": "Feature",
  "properties": {
    "addr:full":"Nijverheidsweg 1A Roermond Limburg 6041 BM",
    "addr:housenumber":"1a",
    "addr:postcode":"6041 bm",
    "addr:street":"Nijverheidsweg",
    "iso:country":"NL",
    "sg:address":"Nijverheidsweg 1A",
    "sg:city":"Roermond",
    "sg:orig_category":"Metaalbekleding And -Behandeling",
    "sg:phone":"+31 475 420 310",
    "sg:postcode":"6041 BM",
    "sg:province":"Limburg",
    "wof:name":"Constructiebedrijf Senssen",
    "wof:placetype":"venue"
},
  "geometry": {"coordinates":[5.999313,51.207611],"type":"Point"}
}