{
  "type": "Feature",
  "properties": {
    "addr:full":"Vd Duijn V Maasdamln 70 Woerden Utrecht 3445 CC",
    "addr:housenumber":"70",
    "addr:postcode":"3445 cc",
    "addr:street":"Maasdamln",
    "iso:country":"NL",
    "sg:address":"Vd Duijn V Maasdamln 70",
    "sg:city":"Woerden",
    "sg:orig_category":"Diverse Bedrijfsinstallaties Gh",
    "sg:phone":"+31 172 472 052",
    "sg:postcode":"3445 CC",
    "sg:province":"Utrecht",
    "wof:name":"Viking Pump International Inc",
    "wof:placetype":"venue"
},
  "geometry": {"coordinates":[4.887371,52.085117],"type":"Point"}
}