{
  "type": "Feature",
  "properties": {
    "addr:full":"J Vernewg 20 Tilburg Noord-Brabant 5015 BL",
    "addr:housenumber":"20",
    "addr:postcode":"5015 bl",
    "iso:country":"NL",
    "sg:address":"J Vernewg 20",
    "sg:city":"Tilburg",
    "sg:orig_category":"Automaterialen En Gereedschappen",
    "sg:phone":"+31 13 543 6047",
    "sg:postcode":"5015 BL",
    "sg:province":"Noord-Brabant",
    "wof:name":"Bouwmeester Bv",
    "wof:placetype":"venue"
},
  "geometry": {"coordinates":[5.112847,51.56839],"type":"Point"}
}