{
  "type": "Feature",
  "properties": {
    "addr:full":"Damstraat 47 Aalten Gelderland 7121 AX",
    "addr:housenumber":"47",
    "addr:postcode":"7121 ax",
    "addr:street":"Damstraat;Gelderland",
    "iso:country":"NL",
    "sg:address":"Damstraat 47",
    "sg:city":"Aalten",
    "sg:classifiers":[
        {
            "category":"Fast Food",
            "type":"Food & Drink"
        }
    ],
    "sg:phone":"+31 543 471 070",
    "sg:postcode":"7121 AX",
    "sg:province":"Gelderland",
    "sg:tags":[
        "afhaal",
        "restaurant"
    ],
    "wof:name":"Veldkamp Vishandel",
    "wof:placetype":"venue"
},
  "geometry": {"coordinates":[6.586581,51.932014],"type":"Point"}
}