{
  "type": "Feature",
  "properties": {
    "addr:full":"Schaiksewg 26 Leerdam Zuid-Holland 4143 HE",
    "addr:housenumber":"26",
    "addr:postcode":"4143 he",
    "addr:street":"Schaiksewg",
    "iso:country":"NL",
    "sg:address":"Schaiksewg 26",
    "sg:city":"Leerdam",
    "sg:orig_category":"Accumulatoren - Fabrieken En Groothandel",
    "sg:phone":"+31 345 613 242",
    "sg:postcode":"4143 HE",
    "sg:province":"Zuid-Holland",
    "wof:name":"Boogstein'S Ned Bv",
    "wof:placetype":"venue"
},
  "geometry": {"coordinates":[5.101516,51.904293],"type":"Point"}
}