{
  "type": "Feature",
  "properties": {
    "iso:country":"NL",
    "sg:address":"Geldersehoek 24",
    "sg:city":"Lelystad",
    "sg:orig_category":"Beautyfarms And Sauna'S",
    "sg:phone":"+31 320 236 802",
    "sg:postcode":"8223 ZB",
    "sg:province":"NL.",
    "wof:name":"Rose Nagelstudio",
    "wof:placetype":"venue"
},
  "geometry": {"coordinates":[5.478447,52.523708],"type":"Point"}
}