{
  "type": "Feature",
  "properties": {
    "addr:full":"Leenderwg 191 Eindhoven North Brabant 5643 AG",
    "addr:housenumber":"191",
    "addr:postcode":"5643",
    "iso:country":"NL",
    "sg:address":"Leenderwg 191",
    "sg:city":"Eindhoven",
    "sg:orig_category":"Verzekeringen - Verzekeringskantoren",
    "sg:phone":"+31 40 211 9395",
    "sg:postcode":"5643 AG",
    "sg:province":"North Brabant",
    "wof:name":"Fimaro",
    "wof:placetype":"venue"
},
  "geometry": {"coordinates":[5.493582,51.423473],"type":"Point"}
}