{
  "type": "Feature",
  "properties": {
    "addr:full":"Zaagmolenln 4 Woerden Utrecht 3447 GS",
    "addr:housenumber":"4",
    "addr:postcode":"3447 gs",
    "addr:street":"Zaagmolenln",
    "iso:country":"NL",
    "sg:address":"Zaagmolenln 4",
    "sg:city":"Woerden",
    "sg:orig_category":"Adviesbureaus Automatisering",
    "sg:phone":"+31 348 480 464",
    "sg:postcode":"3447 GS",
    "sg:province":"Utrecht",
    "sg:website":"http://www.profinance.nu",
    "wof:name":"Profinance Bv",
    "wof:placetype":"venue"
},
  "geometry": {"coordinates":[4.890831,52.080616],"type":"Point"}
}