{
  "type": "Feature",
  "properties": {
    "iso:country":"NL",
    "sg:address":"Brandewynstg 2",
    "sg:city":"Amsterdam",
    "sg:orig_category":"Veilingen En Venduhuizen",
    "sg:phone":"+31 20 623 1669",
    "sg:postcode":"1011 GN",
    "sg:province":"Noord-Holland",
    "wof:name":"Gendt Bv, Van",
    "wof:placetype":"venue"
},
  "geometry": {"coordinates":[4.901672,52.372952],"type":"Point"}
}