{
  "type": "Feature",
  "properties": {
    "iso:country":"NL",
    "sg:address":"Nicolaas Damesstraat 7",
    "sg:city":"Sassenheim",
    "sg:orig_category":"Verhuur Landbouwmachines",
    "sg:phone":"+31 252 214 163",
    "sg:postcode":"2171 KA",
    "sg:province":"South Holland",
    "wof:name":"Sassenheimse Verhuur Onderneming",
    "wof:placetype":"venue"
},
  "geometry": {"coordinates":[4.518156,52.218678],"type":"Point"}
}