{
  "type": "Feature",
  "properties": {
    "addr:full":"Leeuwerikstr 53 Zwaagwesteinde Provincie Friesland 9271 CR",
    "addr:housenumber":"53;9271",
    "addr:postcode":"cr",
    "addr:street":"Leeuwerikstr;Provincie Friesland",
    "iso:country":"NL",
    "sg:address":"Leeuwerikstr 53",
    "sg:city":"Zwaagwesteinde",
    "sg:orig_category":"Bloemen En Planten",
    "sg:phone":"+31 511 443 068",
    "sg:postcode":"9271 CR",
    "sg:province":"Provincie Friesland",
    "wof:name":"Jilderda Vof",
    "wof:placetype":"venue"
},
  "geometry": {"coordinates":[6.036375,53.248539],"type":"Point"}
}