{
  "type": "Feature",
  "properties": {
    "addr:full":"Nw Teertuinen 17 Amsterdam Noord-Holland 1013 LV",
    "addr:housenumber":"17",
    "addr:postcode":"1013",
    "addr:street":"Nw Teertuinen",
    "iso:country":"NL",
    "sg:address":"Nw Teertuinen 17",
    "sg:city":"Amsterdam",
    "sg:orig_category":"Beeldende Kunstenaars",
    "sg:phone":"+31 20 627 1067",
    "sg:postcode":"1013 LV",
    "sg:province":"Noord-Holland",
    "wof:name":"Linnemann, Th K J",
    "wof:placetype":"venue"
},
  "geometry": {"coordinates":[-74.202896,42.97855],"type":"Point"}
}