{
  "type": "Feature",
  "properties": {
    "addr:full":"Anthuriumwg 43 Bleiswyk South Holland 2665 KV",
    "addr:housenumber":"43",
    "addr:postcode":"2665 kv",
    "addr:street":"Anthuriumwg",
    "iso:country":"NL",
    "sg:address":"Anthuriumwg 43",
    "sg:city":"Bleiswyk",
    "sg:orig_category":"Bloemen En Planten",
    "sg:phone":"+31 10 521 8454",
    "sg:postcode":"2665 KV",
    "sg:province":"South Holland",
    "wof:name":"Imperial Bv",
    "wof:placetype":"venue"
},
  "geometry": {"coordinates":[4.517062,52.004444],"type":"Point"}
}