{
  "type": "Feature",
  "properties": {
    "addr:full":"Aarnoudstr 52 Rotterdam South Holland 3084 PB",
    "addr:housenumber":"52",
    "addr:postcode":"3084 pb",
    "addr:street":"Aarnoudstr",
    "iso:country":"NL",
    "sg:address":"Aarnoudstr 52",
    "sg:city":"Rotterdam",
    "sg:orig_category":"Adviesbureaus Bedrijfsorganisatie",
    "sg:phone":"+31 10 299 0114",
    "sg:postcode":"3084 PB",
    "sg:province":"South Holland",
    "wof:name":"Bvl",
    "wof:placetype":"venue"
},
  "geometry": {"coordinates":[4.459807,51.880947],"type":"Point"}
}