{
  "type": "Feature",
  "properties": {
    "addr:full":"Lindenlaan 374 Amstelveen North Holland 1185 NM",
    "addr:housenumber":"374",
    "addr:postcode":"1185",
    "addr:street":"Lindenlaan",
    "iso:country":"NL",
    "sg:address":"Lindenlaan 374",
    "sg:city":"Amstelveen",
    "sg:orig_category":"Dierenspeciaalzaken",
    "sg:phone":"+31 20 641 3020",
    "sg:postcode":"1185 NM",
    "sg:province":"North Holland",
    "wof:name":"Dierenspeciaalzaak Dimbo",
    "wof:placetype":"venue"
},
  "geometry": {"coordinates":[4.861364,52.295902],"type":"Point"}
}