{
  "type": "Feature",
  "properties": {
    "addr:full":"Buys Ballotstraat 35 'S Gravenhage Zuid-Holland 2563 ZJ",
    "addr:housenumber":"35",
    "addr:postcode":"2563 zj",
    "addr:street":"Buys Ballotstraat;' S",
    "iso:country":"NL",
    "sg:address":"Buys Ballotstraat 35",
    "sg:city":"'S Gravenhage",
    "sg:orig_category":"Bedrijfs- And Managementsconsultants",
    "sg:phone":"+31 70 363 7001",
    "sg:postcode":"2563 ZJ",
    "sg:province":"Zuid-Holland",
    "wof:name":"Blomen Management Consult Bv",
    "wof:placetype":"venue"
},
  "geometry": {"coordinates":[4.274757,52.077332],"type":"Point"}
}