{
  "type": "Feature",
  "properties": {
    "addr:full":"Generatorstraat 23 Veenendaal Utrecht 3903 LH",
    "addr:housenumber":"23",
    "addr:postcode":"3903 lh",
    "addr:street":"Generatorstraat",
    "iso:country":"NL",
    "sg:address":"Generatorstraat 23",
    "sg:city":"Veenendaal",
    "sg:orig_category":"Fruit And Groenten Gh",
    "sg:phone":"+31 318 563 111",
    "sg:postcode":"3903 LH",
    "sg:province":"Utrecht",
    "wof:name":"Frits Zwijnenburg Bv",
    "wof:placetype":"venue"
},
  "geometry": {"coordinates":[5.567298,52.007786],"type":"Point"}
}