{
  "type": "Feature",
  "properties": {
    "addr:full":"Da Costakd 145D Amsterdam North Holland 1053 WT",
    "addr:housenumber":"145d",
    "addr:postcode":"1053 wt",
    "iso:country":"NL",
    "sg:address":"Da Costakd 145D",
    "sg:city":"Amsterdam",
    "sg:orig_category":"Webdesign Bureaus",
    "sg:phone":"+31 6 28444294",
    "sg:postcode":"1053 WT",
    "sg:province":"North Holland",
    "wof:name":"Sitegigs",
    "wof:placetype":"venue"
},
  "geometry": {"coordinates":[4.8673300743,52.3666381836],"type":"Point"}
}