{
  "type": "Feature",
  "properties": {
    "addr:full":"Donkerstg 9-9A Leiden South Holland 2312 HA",
    "addr:housenumber":"9-9a",
    "addr:postcode":"2312 ha",
    "addr:street":"Donkerstg",
    "iso:country":"NL",
    "sg:address":"Donkerstg 9-9A",
    "sg:city":"Leiden",
    "sg:orig_category":"Herenkleding",
    "sg:phone":"+31 71 513 6835",
    "sg:postcode":"2312 HA",
    "sg:province":"South Holland",
    "wof:name":"Reenen, E R Van",
    "wof:placetype":"venue"
},
  "geometry": {"coordinates":[4.491327,52.16],"type":"Point"}
}