{
  "type": "Feature",
  "properties": {
    "addr:full":"Paulus Potterlaan 16 Hilversum Noord-Holland 1213 EX",
    "addr:housenumber":"16",
    "addr:postcode":"1213 ex",
    "addr:street":"Paulus Potterlaan",
    "iso:country":"NL",
    "sg:address":"Paulus Potterlaan 16",
    "sg:city":"Hilversum",
    "sg:orig_category":"Verzekeringen",
    "sg:phone":"+31 35 772 1954",
    "sg:postcode":"1213 EX",
    "sg:province":"Noord-Holland",
    "wof:name":"Busse Assurantien",
    "wof:placetype":"venue"
},
  "geometry": {"coordinates":[5.176073,52.211796],"type":"Point"}
}