{
  "type": "Feature",
  "properties": {
    "iso:country":"NL",
    "sg:address":"Nieuwelandstr 10",
    "sg:city":"Ommen",
    "sg:orig_category":"Bierbrouwerijen",
    "sg:phone":"+31 529 455 564",
    "sg:postcode":"7731 TH",
    "sg:province":"NL.08",
    "wof:name":"Pauw Bv, De",
    "wof:placetype":"venue"
},
  "geometry": {"coordinates":[6.431443,52.526775],"type":"Point"}
}