{
  "type": "Feature",
  "properties": {
    "addr:full":"Boerenkamplaan 70 Someren Noord-Brabant 5712 AG",
    "addr:housenumber":"70",
    "addr:postcode":"5712",
    "addr:street":"Boerenkamplaan",
    "iso:country":"NL",
    "sg:address":"Boerenkamplaan 70",
    "sg:city":"Someren",
    "sg:orig_category":"Diverse Grafische Activiteiten",
    "sg:phone":"+31 493 470 392",
    "sg:postcode":"5712 AG",
    "sg:province":"Noord-Brabant",
    "wof:name":"N.A.M. Van Eijk-Mulder",
    "wof:placetype":"venue"
},
  "geometry": {"coordinates":[5.728509,51.366207],"type":"Point"}
}