{
  "type": "Feature",
  "properties": {
    "addr:full":"Utrechtsewg 11 Hilversum Noord-Holland 1213 TK",
    "addr:housenumber":"11",
    "addr:postcode":"1213 tk",
    "addr:street":"Utrechtsewg",
    "iso:country":"NL",
    "sg:address":"Utrechtsewg 11",
    "sg:city":"Hilversum",
    "sg:orig_category":"Begrafenisverzorging",
    "sg:phone":"+31 35 624 2548",
    "sg:postcode":"1213 TK",
    "sg:province":"Noord-Holland",
    "sg:website":"http://www.guv-uitvaart.nl",
    "wof:name":"Gooische Uitvaartverzorging Ua",
    "wof:placetype":"venue"
},
  "geometry": {"coordinates":[5.183229,52.216995],"type":"Point"}
}