{
  "type": "Feature",
  "properties": {
    "iso:country":"NL",
    "sg:address":"De Hosterd 6",
    "sg:city":"Heumen",
    "sg:orig_category":"Adviesbureaus Bouwkunde",
    "sg:phone":"+31 24 358 3279",
    "sg:postcode":"6582 CB",
    "sg:province":"Gelderland",
    "wof:name":"Arts, G M M",
    "wof:placetype":"venue"
},
  "geometry": {"coordinates":[5.844832,51.765728],"type":"Point"}
}