{
  "type": "Feature",
  "properties": {
    "addr:full":"St Lambertusstr 26 Eindhoven North Brabant 5615 PH",
    "addr:housenumber":"26",
    "addr:postcode":"5615",
    "iso:country":"NL",
    "sg:address":"St Lambertusstr 26",
    "sg:city":"Eindhoven",
    "sg:orig_category":"Meubelen",
    "sg:phone":"+31 40 244 5544",
    "sg:postcode":"5615 PH",
    "sg:province":"North Brabant",
    "wof:name":"Eko, Fa",
    "wof:placetype":"venue"
},
  "geometry": {"coordinates":[5.470168,51.433567],"type":"Point"}
}