{
  "type": "Feature",
  "properties": {
    "addr:full":"Weverstraat 56 Den Burg Arkansas 1791 AE",
    "addr:housenumber":"56",
    "addr:postcode":"1791 ae",
    "addr:street":"Weverstraat",
    "iso:country":"NL",
    "sg:address":"Weverstraat 56",
    "sg:city":"Den Burg",
    "sg:orig_category":"Boekhouders",
    "sg:phone":"+31 222 312 888",
    "sg:postcode":"1791 AE",
    "sg:province":"Arkansas",
    "wof:name":"Administratiekantoor Koorn Bv",
    "wof:placetype":"venue"
},
  "geometry": {"coordinates":[-94.071686,34.232082],"type":"Point"}
}