{
  "type": "Feature",
  "properties": {
    "addr:full":"Kerkstraat 63 Waarland North Holland 1738 BJ",
    "addr:housenumber":"63",
    "addr:postcode":"1738 bj",
    "addr:street":"Kerkstraat",
    "iso:country":"NL",
    "sg:address":"Kerkstraat 63",
    "sg:city":"Waarland",
    "sg:orig_category":"Overheidsdiensten",
    "sg:phone":"+31 226 421 606",
    "sg:postcode":"1738 BJ",
    "sg:province":"North Holland",
    "wof:name":"Waarlands Dorpshuis",
    "wof:placetype":"venue"
},
  "geometry": {"coordinates":[4.8279361725,52.7270011902],"type":"Point"}
}