{
  "type": "Feature",
  "properties": {
    "addr:full":"H Visserpln 5 Emmeloord Flevoland 8302 BW",
    "addr:housenumber":"5",
    "addr:postcode":"8302 bw",
    "addr:street":"Flevoland",
    "iso:country":"NL",
    "sg:address":"H Visserpln 5",
    "sg:city":"Emmeloord",
    "sg:orig_category":"Bibliotheken En Leeszalen Openbare",
    "sg:phone":"+31 527 612 059",
    "sg:postcode":"8302 BW",
    "sg:province":"Flevoland",
    "wof:name":"Openb Bibliotheek",
    "wof:placetype":"venue"
},
  "geometry": {"coordinates":[5.746965,52.710571],"type":"Point"}
}