{
  "type": "Feature",
  "properties": {
    "addr:full":"Mariettahof 25-29 Haarlem North Holland 2033 WS",
    "addr:housenumber":"25-29",
    "addr:postcode":"2033 ws",
    "iso:country":"NL",
    "sg:address":"Mariettahof 25-29",
    "sg:city":"Haarlem",
    "sg:orig_category":"Verkeersbureaus",
    "sg:phone":"+31 23 543 0704",
    "sg:postcode":"2033 WS",
    "sg:province":"North Holland",
    "sg:website":"http://www.inobonaire.com",
    "wof:name":"Bonaire",
    "wof:placetype":"venue"
},
  "geometry": {"coordinates":[4.661007,52.379189],"type":"Point"}
}