{
  "type": "Feature",
  "properties": {
    "addr:full":"Minervum 1260 Breda North Brabant 4817 ZH",
    "addr:housenumber":"1260",
    "addr:postcode":"4817 zh",
    "addr:street":"Minervum",
    "iso:country":"NL",
    "sg:address":"Minervum 1260",
    "sg:city":"Breda",
    "sg:orig_category":"Werving And Selectie Van Tijdelijk Personeel And Uitzendkantoren",
    "sg:phone":"+31 900 7002527",
    "sg:postcode":"4817 ZH",
    "sg:province":"North Brabant",
    "wof:name":"Tempo Team",
    "wof:placetype":"venue"
},
  "geometry": {"coordinates":[4.82791996,51.583820343],"type":"Point"}
}