{
  "type": "Feature",
  "properties": {
    "addr:full":"Havenkd 2 Numansdorp South Holland 3281 LS",
    "addr:housenumber":"2",
    "addr:postcode":"3281 ls",
    "addr:street":"Havenkd",
    "iso:country":"NL",
    "sg:address":"Havenkd 2",
    "sg:city":"Numansdorp",
    "sg:orig_category":"Houtgroothandel",
    "sg:phone":"+31 186 651 722",
    "sg:postcode":"3281 LS",
    "sg:province":"South Holland",
    "wof:name":"Hooft & Van Prooijen Bv, 'T",
    "wof:placetype":"venue"
},
  "geometry": {"coordinates":[4.438345,51.731369],"type":"Point"}
}