{
  "type": "Feature",
  "properties": {
    "addr:full":"Vlistpad 2 Culemborg Gelderland 4105 ZN",
    "addr:housenumber":"2",
    "addr:postcode":"4105 zn",
    "addr:street":"Vlistpad;Gelderland",
    "iso:country":"NL",
    "sg:address":"Vlistpad 2",
    "sg:city":"Culemborg",
    "sg:orig_category":"Adviesbureaus Bedrijfsorganisatie",
    "sg:phone":"+31 345 530 849",
    "sg:postcode":"4105 ZN",
    "sg:province":"Gelderland",
    "sg:website":"http://www.visia.nl",
    "wof:name":"Visia Bv",
    "wof:placetype":"venue"
},
  "geometry": {"coordinates":[5.209619,51.954533],"type":"Point"}
}