{
  "type": "Feature",
  "properties": {
    "addr:full":"Noorderdiep 55 Stadskanaal Groningen 9501 XB",
    "addr:housenumber":"55",
    "addr:postcode":"9501 xb",
    "addr:street":"Noorderdiep",
    "iso:country":"NL",
    "sg:address":"Noorderdiep 55",
    "sg:city":"Stadskanaal",
    "sg:orig_category":"Organisatiebureaus",
    "sg:phone":"+31 599 616 274",
    "sg:postcode":"9501 XB",
    "sg:province":"Groningen",
    "wof:name":"Hopman, W",
    "wof:placetype":"venue"
},
  "geometry": {"coordinates":[6.9249491692,53.00756073],"type":"Point"}
}