{
  "type": "Feature",
  "properties": {
    "addr:full":"Middelveensewg 7C Zuidwolde Dr Drenthe 7921 RM",
    "addr:housenumber":"7c",
    "addr:postcode":"7921 rm",
    "addr:street":"Middelveensewg;Dr",
    "iso:country":"NL",
    "sg:address":"Middelveensewg 7C",
    "sg:city":"Zuidwolde Dr",
    "sg:orig_category":"Grondwerken",
    "sg:phone":"+31 528 371 453",
    "sg:postcode":"7921 RM",
    "sg:province":"Drenthe",
    "sg:website":"http://www.kloosterdekker.nl",
    "wof:name":"Klooster En Dekker",
    "wof:placetype":"venue"
},
  "geometry": {"coordinates":[6.42853,52.67675],"type":"Point"}
}