{
  "type": "Feature",
  "properties": {
    "addr:full":"Prinsegr 4 Centrum S Gravenhage South Holland 2512 GA",
    "addr:housenumber":"4",
    "addr:postcode":"2512 ga",
    "addr:street":"Prinsegr",
    "iso:country":"NL",
    "sg:address":"Prinsegr 4 Centrum",
    "sg:city":"S Gravenhage",
    "sg:orig_category":"Verenigingen En Stichtingen",
    "sg:phone":"+31 70 365 8777",
    "sg:postcode":"2512 GA",
    "sg:province":"South Holland",
    "wof:name":"Cjv",
    "wof:placetype":"venue"
},
  "geometry": {"coordinates":[4.30618,52.073212],"type":"Point"}
}