{
  "type": "Feature",
  "properties": {
    "addr:full":"Pieter Postmapad 4 Rijswijk Zh South Holland 2287 DB",
    "addr:housenumber":"4",
    "addr:postcode":"2287 db",
    "addr:street":"Pieter Postmapad",
    "iso:country":"NL",
    "sg:address":"Pieter Postmapad 4",
    "sg:city":"Rijswijk Zh",
    "sg:orig_category":"Overheidsdiensten",
    "sg:phone":"+31 70 393 0100",
    "sg:postcode":"2287 DB",
    "sg:province":"South Holland",
    "wof:name":"Scorpio",
    "wof:placetype":"venue"
},
  "geometry": {"coordinates":[4.3307800293,52.0278739929],"type":"Point"}
}