{
  "type": "Feature",
  "properties": {
    "addr:full":"Zeelsterstr 59F Eindhoven North Brabant 5652 EB",
    "addr:housenumber":"59f",
    "addr:postcode":"5652 eb",
    "iso:country":"NL",
    "sg:address":"Zeelsterstr 59F",
    "sg:city":"Eindhoven",
    "sg:orig_category":"Matrijzen",
    "sg:phone":"+31 40 257 3328",
    "sg:postcode":"5652 EB",
    "sg:province":"North Brabant",
    "wof:name":"Promaton Bv",
    "wof:placetype":"venue"
},
  "geometry": {"coordinates":[5.447278,51.438629],"type":"Point"}
}