{
  "type": "Feature",
  "properties": {
    "iso:country":"NL",
    "sg:address":"Galileiplnts 104",
    "sg:city":"Amsterdam",
    "sg:orig_category":"Verzekeringen - Verzekeringskantoren",
    "sg:phone":"+31 20 693 9733",
    "sg:postcode":"1098 NC",
    "sg:province":"Noord-Holland",
    "wof:name":"Saleco",
    "wof:placetype":"venue"
},
  "geometry": {"coordinates":[4.94688,52.349209],"type":"Point"}
}