{
  "type": "Feature",
  "properties": {
    "addr:full":"Liswg 2 Oostzaan North Holland 1511 XE",
    "addr:housenumber":"2",
    "addr:postcode":"1511 xe",
    "addr:street":"Liswg",
    "iso:country":"NL",
    "sg:address":"Liswg 2",
    "sg:city":"Oostzaan",
    "sg:orig_category":"Banken",
    "sg:phone":"+31 75 684 7500",
    "sg:postcode":"1511 XE",
    "sg:province":"North Holland",
    "sg:website":"http://www.rabobank.nl",
    "wof:name":"Rabobank",
    "wof:placetype":"venue"
},
  "geometry": {"coordinates":[4.877666,52.437183],"type":"Point"}
}