{
  "type": "Feature",
  "properties": {
    "addr:full":"M Klompeln 4 Woerden Utrecht 3445 CZ",
    "addr:housenumber":"4",
    "addr:postcode":"3445",
    "addr:street":"Woerden",
    "iso:country":"NL",
    "sg:address":"M Klompeln 4",
    "sg:city":"Woerden",
    "sg:orig_category":"Verzekeringen - Verzekeringskantoren",
    "sg:phone":"+31 348 422 917",
    "sg:postcode":"3445 CZ",
    "sg:province":"Utrecht",
    "wof:name":"Bos, C A",
    "wof:placetype":"venue"
},
  "geometry": {"coordinates":[4.901619,52.090752],"type":"Point"}
}