{
  "type": "Feature",
  "properties": {
    "addr:full":"Vimmerik 10 Nieuwkuijk Noord-Brabant 5253 CB",
    "addr:housenumber":"10",
    "addr:postcode":"5253 cb",
    "addr:street":"Vimmerik",
    "iso:country":"NL",
    "sg:address":"Vimmerik 10",
    "sg:city":"Nieuwkuijk",
    "sg:orig_category":"Metaalbekleding And -Behandeling",
    "sg:phone":"+31 73 511 3908",
    "sg:postcode":"5253 CB",
    "sg:province":"Noord-Brabant",
    "wof:name":"Straalbedrijf Van Eggelen Bv",
    "wof:placetype":"venue"
},
  "geometry": {"coordinates":[5.173187,51.69545],"type":"Point"}
}