{
  "type": "Feature",
  "properties": {
    "iso:country":"NL",
    "sg:address":"Beekstraat 33",
    "sg:city":"Epe",
    "sg:orig_category":"Overheidsdiensten",
    "sg:phone":"+31 578 613 710",
    "sg:postcode":"8162 HA",
    "sg:province":"Gelderland",
    "wof:name":"Kerkeraad Van De Gereformeerde Kerk",
    "wof:placetype":"venue"
},
  "geometry": {"coordinates":[5.9785017967,52.3471183777],"type":"Point"}
}