{
  "type": "Feature",
  "properties": {
    "iso:country":"NL",
    "sg:address":"Havenkade 16",
    "sg:city":"Elburg",
    "sg:orig_category":"Visspeciaalzaken",
    "sg:phone":"+31 525 681 919",
    "sg:postcode":"8081 GP",
    "sg:province":"Gelderland",
    "wof:name":"Vishal H. Van Der Heide Vof",
    "wof:placetype":"venue"
},
  "geometry": {"coordinates":[5.83555,52.4478],"type":"Point"}
}