{
  "type": "Feature",
  "properties": {
    "addr:full":"Veldkampsewg 6A Heerde Gelderland 8181 LN",
    "addr:housenumber":"6a",
    "addr:postcode":"8181 ln",
    "addr:street":"Veldkampsewg;Gelderland",
    "iso:country":"NL",
    "sg:address":"Veldkampsewg 6A",
    "sg:city":"Heerde",
    "sg:orig_category":"Meubelmakerijen",
    "sg:phone":"+31 578 691 150",
    "sg:postcode":"8181 LN",
    "sg:province":"Gelderland",
    "wof:name":"Wolff",
    "wof:placetype":"venue"
},
  "geometry": {"coordinates":[6.043178,52.399822],"type":"Point"}
}