{
  "type": "Feature",
  "properties": {
    "addr:full":"Burghstraat 49 Eindhoven Noord-Brabant 5614 BC",
    "addr:housenumber":"49",
    "addr:postcode":"5614 bc",
    "addr:street":"Burghstraat",
    "iso:country":"NL",
    "sg:address":"Burghstraat 49",
    "sg:city":"Eindhoven",
    "sg:orig_category":"Maatschappelijk Werk",
    "sg:phone":"+31 40 211 5571",
    "sg:postcode":"5614 BC",
    "sg:province":"Noord-Brabant",
    "wof:name":"Beroepskeuzepraktijk Eindhoven",
    "wof:placetype":"venue"
},
  "geometry": {"coordinates":[5.493301,51.429649],"type":"Point"}
}