{
  "type": "Feature",
  "properties": {
    "addr:full":"Jan Van Galenstraat 129Bg Amsterdam Noord-Holland 1056 BL",
    "addr:housenumber":"129bg",
    "addr:postcode":"1056 bl",
    "addr:street":"Jan Van Galenstraat",
    "iso:country":"NL",
    "sg:address":"Jan Van Galenstraat 129Bg",
    "sg:city":"Amsterdam",
    "sg:orig_category":"Juweliers",
    "sg:phone":"+31 20 618 7439",
    "sg:postcode":"1056 BL",
    "sg:province":"Noord-Holland",
    "wof:name":"Juwelier Gorji",
    "wof:placetype":"venue"
},
  "geometry": {"coordinates":[4.857774,52.374493],"type":"Point"}
}