{
  "type": "Feature",
  "properties": {
    "addr:full":"Boekelsedk 8 Zeeland Noord-Brabant 5411 NW",
    "addr:housenumber":"8",
    "addr:postcode":"5411 nw",
    "addr:street":"Boekelsedk",
    "iso:country":"NL",
    "sg:address":"Boekelsedk 8",
    "sg:city":"Zeeland",
    "sg:orig_category":"Beeldende Kunstenaars",
    "sg:phone":"+31 486 452 201",
    "sg:postcode":"5411 NW",
    "sg:province":"Noord-Brabant",
    "wof:name":"Heerkens, J A M",
    "wof:placetype":"venue"
},
  "geometry": {"coordinates":[5.671892,51.682262],"type":"Point"}
}