{
  "type": "Feature",
  "properties": {
    "addr:full":"Ehrenstein 1 Eindhoven Noord-Brabant 5655 AA",
    "addr:housenumber":"1",
    "addr:postcode":"5655 aa",
    "addr:street":"Ehrenstein",
    "iso:country":"NL",
    "sg:address":"Ehrenstein 1",
    "sg:city":"Eindhoven",
    "sg:orig_category":"Verzekeringen",
    "sg:phone":"+31 40 255 0043",
    "sg:postcode":"5655 AA",
    "sg:province":"Noord-Brabant",
    "wof:name":"Hendriks, Th. Assurantie",
    "wof:placetype":"venue"
},
  "geometry": {"coordinates":[5.44522,51.417885],"type":"Point"}
}