{
  "type": "Feature",
  "properties": {
    "addr:full":"Rembrandtln 87 Woerden Utrecht 3443 ED",
    "addr:housenumber":"87",
    "addr:postcode":"3443 ed",
    "addr:street":"Rembrandtln",
    "iso:country":"NL",
    "sg:address":"Rembrandtln 87",
    "sg:city":"Woerden",
    "sg:orig_category":"Meubelmakerijen",
    "sg:phone":"+31 348 430 015",
    "sg:postcode":"3443 ED",
    "sg:province":"Utrecht",
    "wof:name":"Jong, M De",
    "wof:placetype":"venue"
},
  "geometry": {"coordinates":[4.876274,52.088985],"type":"Point"}
}