{
  "type": "Feature",
  "properties": {
    "addr:full":"De Grie 21 Sintjohannesga Provincie Friesland 8464 PA",
    "addr:housenumber":"21",
    "addr:postcode":"8464",
    "addr:street":"De Grie;Provincie Friesland",
    "iso:country":"NL",
    "sg:address":"De Grie 21",
    "sg:city":"Sintjohannesga",
    "sg:orig_category":"Voegwerken",
    "sg:phone":"+31 513 551 717",
    "sg:postcode":"8464 PA",
    "sg:province":"Provincie Friesland",
    "wof:name":"Sloothaak, V A",
    "wof:placetype":"venue"
},
  "geometry": {"coordinates":[5.858784,52.931198],"type":"Point"}
}