{
  "type": "Feature",
  "properties": {
    "addr:full":"Noordeinde 21 Landsmeer Noord-Holland 1121 AA",
    "addr:housenumber":"21",
    "addr:postcode":"1121 aa",
    "addr:street":"Noordeinde",
    "iso:country":"NL",
    "sg:address":"Noordeinde 21",
    "sg:city":"Landsmeer",
    "sg:orig_category":"Kaas",
    "sg:phone":"+31 20 482 4334",
    "sg:postcode":"1121 AA",
    "sg:province":"Noord-Holland",
    "wof:name":"Wals, G",
    "wof:placetype":"venue"
},
  "geometry": {"coordinates":[4.9142460823,52.4416542053],"type":"Point"}
}