{
  "type": "Feature",
  "properties": {
    "addr:full":"Dijkweg 66 Honselersdijk Zuid-Holland 2675 AE",
    "addr:housenumber":"66",
    "addr:postcode":"2675 ae",
    "addr:street":"Dijkweg",
    "iso:country":"NL",
    "sg:address":"Dijkweg 66",
    "sg:city":"Honselersdijk",
    "sg:orig_category":"Bloemen And Planten Gh",
    "sg:phone":"+31 174 632 988",
    "sg:postcode":"2675 AE",
    "sg:province":"Zuid-Holland",
    "wof:name":"Johan Van Dijk Bv",
    "wof:placetype":"venue"
},
  "geometry": {"coordinates":[4.22775,52.007736],"type":"Point"}
}