{
  "type": "Feature",
  "properties": {
    "iso:country":"NL",
    "sg:address":"Dijkweg 66",
    "sg:city":"Honselersdijk",
    "sg:orig_category":"Bloemen And Planten Gh",
    "sg:phone":"+31 174 632 988",
    "sg:postcode":"2675 AE",
    "sg:province":"Zuid-Holland",
    "wof:name":"Johan Van Dijk Bv",
    "wof:placetype":"venue"
},
  "geometry": {"coordinates":[4.22775,52.007736],"type":"Point"}
}