{
  "type": "Feature",
  "properties": {
    "iso:country":"NL",
    "sg:address":"St Gerarduspl 15",
    "sg:city":"Eindhoven",
    "sg:orig_category":"Meubelen",
    "sg:phone":"+31 40 211 1626",
    "sg:postcode":"5644 NG",
    "sg:province":"Noord-Brabant",
    "wof:name":"Bos & Zn Vof, C",
    "wof:placetype":"venue"
},
  "geometry": {"coordinates":[5.48629,51.421024],"type":"Point"}
}