{
  "type": "Feature",
  "properties": {
    "addr:full":"Kerkweg 25 Driebruggen South Holland 3465 JG",
    "addr:housenumber":"25",
    "addr:postcode":"3465 jg",
    "addr:street":"Kerkweg",
    "iso:country":"NL",
    "sg:address":"Kerkweg 25",
    "sg:city":"Driebruggen",
    "sg:orig_category":"Autokeuringen",
    "sg:phone":"+31 348 501 316",
    "sg:postcode":"3465 JG",
    "sg:province":"South Holland",
    "wof:name":"T.P. Boerefijn",
    "wof:placetype":"venue"
},
  "geometry": {"coordinates":[4.797913,52.043766],"type":"Point"}
}