{
  "type": "Feature",
  "properties": {
    "addr:full":"Postbus 108 Mierlo Noord-Brabant 5730 AC",
    "addr:housenumber":"108",
    "addr:postcode":"5730 ac",
    "addr:street":"Postbus",
    "iso:country":"NL",
    "sg:address":"Postbus 108",
    "sg:city":"Mierlo",
    "sg:orig_category":"Artiesten/Gezelschappen",
    "sg:phone":"+31 492 665 449",
    "sg:postcode":"5730 AC",
    "sg:province":"Noord-Brabant",
    "sg:website":"http://www.duo-twilightzone.com",
    "wof:name":"Twilight Zone",
    "wof:placetype":"venue"
},
  "geometry": {"coordinates":[5.62004,51.443722],"type":"Point"}
}