{
  "type": "Feature",
  "properties": {
    "addr:full":"Waldeck Pyrmontlaan 16B Amsterdam Noord-Holland 1075 BW",
    "addr:housenumber":"16b",
    "addr:postcode":"1075 bw",
    "addr:street":"Waldeck Pyrmontlaan",
    "iso:country":"NL",
    "sg:address":"Waldeck Pyrmontlaan 16B",
    "sg:city":"Amsterdam",
    "sg:orig_category":"Chemische Producten Gh",
    "sg:phone":"+31 20 679 0809",
    "sg:postcode":"1075 BW",
    "sg:province":"Noord-Holland",
    "wof:name":"J. Fuchs",
    "wof:placetype":"venue"
},
  "geometry": {"coordinates":[4.857182,52.353302],"type":"Point"}
}