{
  "type": "Feature",
  "properties": {
    "addr:full":"Stevenswg 64 Dordrecht Zuid-Holland 3319 AL",
    "addr:housenumber":"64",
    "addr:postcode":"3319 al",
    "addr:street":"Stevenswg",
    "iso:country":"NL",
    "sg:address":"Stevenswg 64",
    "sg:city":"Dordrecht",
    "sg:orig_category":"Administratie- En Boekhoudkantoren",
    "sg:phone":"+31 78 621 0197",
    "sg:postcode":"3319 AL",
    "sg:province":"Zuid-Holland",
    "wof:name":"D\u00f6bken",
    "wof:placetype":"venue"
},
  "geometry": {"coordinates":[4.692857,51.786453],"type":"Point"}
}