{
  "type": "Feature",
  "properties": {
    "addr:full":"Meelstraat 53 Zierikzee Zeeland 4301 EB",
    "addr:housenumber":"53",
    "addr:postcode":"4301 eb",
    "addr:street":"Meelstraat",
    "iso:country":"NL",
    "sg:address":"Meelstraat 53",
    "sg:city":"Zierikzee",
    "sg:classifiers":[
        {
            "category":"Travel",
            "subcategory":"Hotels & Motels",
            "type":"Entertainment"
        }
    ],
    "sg:phone":"+31 111 415 935",
    "sg:postcode":"4301 EB",
    "sg:province":"Zeeland",
    "wof:name":"Pension Beddegoed",
    "wof:placetype":"venue"
},
  "geometry": {"coordinates":[3.917351,51.650417],"type":"Point"}
}