{
  "type": "Feature",
  "properties": {
    "addr:full":"Schans 18 Beverwyk Noord-Holland 1947 JR",
    "addr:postcode":"1947 jr",
    "addr:street":"Schans 18 Beverwyk",
    "iso:country":"NL",
    "sg:address":"Schans 18",
    "sg:city":"Beverwyk",
    "sg:orig_category":"Projectinrichting",
    "sg:phone":"+31 251 222 997",
    "sg:postcode":"1947 JR",
    "sg:province":"Noord-Holland",
    "sg:website":"http://www.inexdesign.nl",
    "wof:name":"Inex Design",
    "wof:placetype":"venue"
},
  "geometry": {"coordinates":[4.662032,52.483349],"type":"Point"}
}