{
  "type": "Feature",
  "properties": {
    "addr:full":"Buitenhofdreef 278 Delft Zuid-Holland 2625 RE",
    "addr:housenumber":"278",
    "addr:postcode":"2625 re",
    "addr:street":"Buitenhofdreef",
    "iso:country":"NL",
    "sg:address":"Buitenhofdreef 278",
    "sg:city":"Delft",
    "sg:orig_category":"Kinderopvang Behalve Thuis",
    "sg:phone":"+31 15 261 4518",
    "sg:postcode":"2625 RE",
    "sg:province":"Zuid-Holland",
    "wof:name":"Buitenhof Octopus Peuterspeelzaal",
    "wof:placetype":"venue"
},
  "geometry": {"coordinates":[4.344168,51.990372],"type":"Point"}
}