{
  "type": "Feature",
  "properties": {
    "addr:full":"Kruisweg 16 Loppersum Groningen 9919 BB",
    "addr:housenumber":"16",
    "addr:postcode":"9919 bb",
    "addr:street":"Kruisweg",
    "iso:country":"NL",
    "sg:address":"Kruisweg 16",
    "sg:city":"Loppersum",
    "sg:orig_category":"Boekenuitgeverijen",
    "sg:phone":"+31 596 571 383",
    "sg:postcode":"9919 BB",
    "sg:province":"Groningen",
    "wof:name":"Boek- En Kantoorboekhandel Noot",
    "wof:placetype":"venue"
},
  "geometry": {"coordinates":[6.7439851761,53.3327598572],"type":"Point"}
}