{
  "type": "Feature",
  "properties": {
    "addr:full":"Binnenhof 64 Amstelveen Noord-Holland 1181 ZJ",
    "addr:housenumber":"64",
    "addr:postcode":"1181 zj",
    "addr:street":"Binnenhof",
    "iso:country":"NL",
    "sg:address":"Binnenhof 64",
    "sg:city":"Amstelveen",
    "sg:orig_category":"Postkantoren",
    "sg:phone":"+31 20 640 0166",
    "sg:postcode":"1181 ZJ",
    "sg:province":"Noord-Holland",
    "sg:website":"http://www.postkantoor.nl",
    "wof:name":"Postkantoor",
    "wof:placetype":"venue"
},
  "geometry": {"coordinates":[4.862055,52.30257],"type":"Point"}
}