{
  "type": "Feature",
  "properties": {
    "addr:full":"Dr C Hofstede De Grootkd 11 Groningen Groningen 9718 KA",
    "addr:housenumber":"11",
    "addr:postcode":"9718 ka",
    "addr:street":"Dr C Hofstede De Grootkd",
    "iso:country":"NL",
    "sg:address":"Dr C Hofstede De Grootkd 11",
    "sg:city":"Groningen",
    "sg:orig_category":"Overheidsdiensten",
    "sg:phone":"+31 50 365 4444",
    "sg:postcode":"9718 KA",
    "sg:province":"Groningen",
    "wof:name":"Belastingdienst Ondernemingen Groningen",
    "wof:placetype":"venue"
},
  "geometry": {"coordinates":[6.5537052155,53.2188529968],"type":"Point"}
}