{
  "type": "Feature",
  "properties": {
    "addr:full":"Akerstraat 47 Heerlen Limburg 6411 GW",
    "addr:housenumber":"47",
    "addr:postcode":"6411 gw",
    "addr:street":"Akerstraat",
    "iso:country":"NL",
    "sg:address":"Akerstraat 47",
    "sg:city":"Heerlen",
    "sg:orig_category":"Wasserettes And Stomerijen",
    "sg:phone":"+31 45 571 4990",
    "sg:postcode":"6411 GW",
    "sg:province":"Limburg",
    "wof:name":"Firma Undine",
    "wof:placetype":"venue"
},
  "geometry": {"coordinates":[5.9823431969,50.8844337463],"type":"Point"}
}