{
  "type": "Feature",
  "properties": {
    "addr:full":"Europaln 1 Epe Gelderland 8161 ZB",
    "addr:housenumber":"1",
    "addr:postcode":"8161 zb",
    "addr:street":"Europaln;Gelderland",
    "iso:country":"NL",
    "sg:address":"Europaln 1",
    "sg:city":"Epe",
    "sg:orig_category":"Architecten En Architectenbureaus",
    "sg:phone":"+31 578 620 814",
    "sg:postcode":"8161 ZB",
    "sg:province":"Gelderland",
    "sg:website":"http://www.bouwkunst.nl",
    "wof:name":"Rensink",
    "wof:placetype":"venue"
},
  "geometry": {"coordinates":[5.986395,52.35199],"type":"Point"}
}