{
  "type": "Feature",
  "properties": {
    "addr:full":"Burg Verwielstr 44 Oisterwyk North Brabant 5062 GD",
    "addr:housenumber":"44",
    "addr:postcode":"5062 gd",
    "addr:street":"Burg;Oisterwyk North",
    "iso:country":"NL",
    "sg:address":"Burg Verwielstr 44",
    "sg:city":"Oisterwyk",
    "sg:orig_category":"Makelaars En Adviseurs Onroerende Goederen",
    "sg:phone":"+31 13 521 9009",
    "sg:postcode":"5062 GD",
    "sg:province":"North Brabant",
    "sg:website":"http://www.quistmakelaars.nl",
    "wof:name":"Quist Makelaars Oz",
    "wof:placetype":"venue"
},
  "geometry": {"coordinates":[5.194632,51.57629],"type":"Point"}
}