{
  "type": "Feature",
  "properties": {
    "iso:country":"NL",
    "sg:address":"Birdieln 68",
    "sg:city":"Lelystad",
    "sg:orig_category":"Adviesbureaus Bedrijfsorganisatie",
    "sg:phone":"+31 320 264 920",
    "sg:postcode":"8241 BC",
    "sg:province":"Flevoland",
    "sg:website":"http://www.innervation.nl",
    "wof:name":"Innervation Bv",
    "wof:placetype":"venue"
},
  "geometry": {"coordinates":[5.46772,52.569462],"type":"Point"}
}