{
  "type": "Feature",
  "properties": {
    "addr:full":"Blasiusstr 25 Deurne Noord-Brabant 5754 AS",
    "addr:housenumber":"25",
    "addr:postcode":"5754 as",
    "addr:street":"Blasiusstr",
    "iso:country":"NL",
    "sg:address":"Blasiusstr 25",
    "sg:city":"Deurne",
    "sg:orig_category":"Kappers",
    "sg:phone":"+31 493 316 283",
    "sg:postcode":"5754 AS",
    "sg:province":"Noord-Brabant",
    "wof:name":"Maas",
    "wof:placetype":"venue"
},
  "geometry": {"coordinates":[5.817492,51.455448],"type":"Point"}
}