{
  "type": "Feature",
  "properties": {
    "addr:full":"Schukkingpad 1 Havelte Drenthe 7971 BV",
    "addr:housenumber":"1",
    "addr:postcode":"7971 bv",
    "addr:street":"Schukkingpad",
    "iso:country":"NL",
    "sg:address":"Schukkingpad 1",
    "sg:city":"Havelte",
    "sg:orig_category":"Handelsbemiddeling Textiel And Lederwaren",
    "sg:phone":"+31 521 341 204",
    "sg:postcode":"7971 BV",
    "sg:province":"Drenthe",
    "wof:name":"Starko",
    "wof:placetype":"venue"
},
  "geometry": {"coordinates":[6.239941,52.771034],"type":"Point"}
}