{
  "type": "Feature",
  "properties": {
    "addr:full":"Klaprozenwg 75 Amsterdam Noord-Holland 1033 NN",
    "addr:housenumber":"75",
    "addr:postcode":"1033 nn",
    "addr:street":"Klaprozenwg",
    "iso:country":"NL",
    "sg:address":"Klaprozenwg 75",
    "sg:city":"Amsterdam",
    "sg:orig_category":"Adviesbureaus Bedrijfsorganisatie",
    "sg:phone":"+31 20 550 3750",
    "sg:postcode":"1033 NN",
    "sg:province":"Noord-Holland",
    "wof:name":"Da Vinci Groep",
    "wof:placetype":"venue"
},
  "geometry": {"coordinates":[4.892036,52.405952],"type":"Point"}
}