{
  "type": "Feature",
  "properties": {
    "addr:full":"Industriewg 135 Rotterdam Zuid-Holland 3044 AS",
    "addr:housenumber":"135",
    "addr:postcode":"3044 as",
    "iso:country":"NL",
    "sg:address":"Industriewg 135",
    "sg:city":"Rotterdam",
    "sg:orig_category":"Accountants - Administratie- Consulenten En -Kantoren",
    "sg:phone":"+31 10 478 2868",
    "sg:postcode":"3044 AS",
    "sg:province":"Zuid-Holland",
    "wof:name":"Middenstand Cv",
    "wof:placetype":"venue"
},
  "geometry": {"coordinates":[4.421576,51.927197],"type":"Point"}
}