{
  "type": "Feature",
  "properties": {
    "addr:full":"Atjehstraat 2 Rotterdam Zuid-Holland 3072 ZD",
    "addr:housenumber":"2",
    "addr:postcode":"3072 zd",
    "addr:street":"Atjehstraat",
    "iso:country":"NL",
    "sg:address":"Atjehstraat 2",
    "sg:city":"Rotterdam",
    "sg:orig_category":"Goederenvervoer Over De Weg",
    "sg:phone":"+31 10 423 0515",
    "sg:postcode":"3072 ZD",
    "sg:province":"Zuid-Holland",
    "wof:name":"Transportbedrijf H.M. Steeman",
    "wof:placetype":"venue"
},
  "geometry": {"coordinates":[4.488536,51.901405],"type":"Point"}
}