{
  "type": "Feature",
  "properties": {
    "addr:full":"Campanulahof 27 Papendrecht Zuid-Holland 3355 BH",
    "addr:housenumber":"27",
    "addr:postcode":"3355 bh",
    "addr:street":"Campanulahof",
    "iso:country":"NL",
    "sg:address":"Campanulahof 27",
    "sg:city":"Papendrecht",
    "sg:orig_category":"Scheepvaartmijen",
    "sg:phone":"+31 6 53198081",
    "sg:postcode":"3355 BH",
    "sg:province":"Zuid-Holland",
    "wof:name":"Jong-Van Der Klei Vof, De",
    "wof:placetype":"venue"
},
  "geometry": {"coordinates":[4.705839,51.836918],"type":"Point"}
}