{
  "type": "Feature",
  "properties": {
    "addr:full":"Carneooldreef 26 Emmen Drenthe 7828 CB",
    "addr:housenumber":"26",
    "addr:postcode":"7828 cb",
    "addr:street":"Carneooldreef",
    "iso:country":"NL",
    "sg:address":"Carneooldreef 26",
    "sg:city":"Emmen",
    "sg:orig_category":"Administratie- En Boekhoudkantoren",
    "sg:phone":"+31 591 676 071",
    "sg:postcode":"7828 CB",
    "sg:province":"Drenthe",
    "wof:name":"Lcs",
    "wof:placetype":"venue"
},
  "geometry": {"coordinates":[6.914837,52.731369],"type":"Point"}
}