{
  "type": "Feature",
  "properties": {
    "addr:full":"Oude Delft 83 Delft Zuid-Holland 2611 BD",
    "addr:housenumber":"83",
    "addr:postcode":"2611 bd",
    "addr:street":"Oude Delft",
    "iso:country":"NL",
    "sg:address":"Oude Delft 83",
    "sg:city":"Delft",
    "sg:orig_category":"Schilders",
    "sg:phone":"+31 15 261 6424",
    "sg:postcode":"2611 BD",
    "sg:province":"Zuid-Holland",
    "wof:name":"Eijk En Zoon Vof, J Van",
    "wof:placetype":"venue"
},
  "geometry": {"coordinates":[4.358008,52.008732],"type":"Point"}
}