{
  "type": "Feature",
  "properties": {
    "addr:full":"Rijnstraat 27 Oss Noord-Brabant 5347 KN",
    "addr:housenumber":"27",
    "addr:postcode":"5347 kn",
    "addr:street":"Rijnstraat",
    "iso:country":"NL",
    "sg:address":"Rijnstraat 27",
    "sg:city":"Oss",
    "sg:orig_category":"Metaalbekleding And -Behandeling",
    "sg:phone":"+31 412 681 459",
    "sg:postcode":"5347 KN",
    "sg:province":"Noord-Brabant",
    "wof:name":"Brabant Components Bv",
    "wof:placetype":"venue"
},
  "geometry": {"coordinates":[-91.145439,44.529385],"type":"Point"}
}