{
  "type": "Feature",
  "properties": {
    "addr:full":"Spinozawg 401 Rotterdam Zuid-Holland 3076 ET",
    "addr:housenumber":"401",
    "addr:postcode":"3076 et",
    "iso:country":"NL",
    "sg:address":"Spinozawg 401",
    "sg:city":"Rotterdam",
    "sg:orig_category":"Juweliers",
    "sg:phone":"+31 10 432 5363",
    "sg:postcode":"3076 ET",
    "sg:province":"Zuid-Holland",
    "wof:name":"Briljant",
    "wof:placetype":"venue"
},
  "geometry": {"coordinates":[4.517528,51.877151],"type":"Point"}
}