{
  "type": "Feature",
  "properties": {
    "addr:full":"Oud Nieuwlandseweg 11 Ouddorp Zh Zuid-Holland 3253 LL",
    "addr:housenumber":"11",
    "addr:postcode":"3253 ll",
    "addr:street":"Oud Nieuwlandseweg",
    "iso:country":"NL",
    "sg:address":"Oud Nieuwlandseweg 11",
    "sg:city":"Ouddorp Zh",
    "sg:classifiers":[
        {
            "category":"Fast Food",
            "type":"Food & Drink"
        }
    ],
    "sg:phone":"+31 187 681 210",
    "sg:postcode":"3253 LL",
    "sg:province":"Zuid-Holland",
    "sg:tags":[
        "afhaal",
        "restaurant"
    ],
    "wof:name":"Snackbar Didi",
    "wof:placetype":"venue"
},
  "geometry": {"coordinates":[3.91493,51.821686],"type":"Point"}
}