{
  "type": "Feature",
  "properties": {
    "addr:full":"Schoenerwg 65 Maastricht Limburg 6222 NX",
    "addr:housenumber":"65",
    "addr:postcode":"6222 nx",
    "addr:street":"Schoenerwg",
    "iso:country":"NL",
    "sg:address":"Schoenerwg 65",
    "sg:city":"Maastricht",
    "sg:orig_category":"Straalbedrijven",
    "sg:phone":"+31 43 363 6666",
    "sg:postcode":"6222 NX",
    "sg:province":"Limburg",
    "wof:name":"Giessen Bv, Straalbedrijf",
    "wof:placetype":"venue"
},
  "geometry": {"coordinates":[5.718581,50.874504],"type":"Point"}
}