{
  "type": "Feature",
  "properties": {
    "addr:full":"Dijkgraafstraat 21 Druten Gelderland 6651 DL",
    "addr:housenumber":"21",
    "addr:postcode":"6651 dl",
    "addr:street":"Dijkgraafstraat",
    "iso:country":"NL",
    "sg:address":"Dijkgraafstraat 21",
    "sg:city":"Druten",
    "sg:orig_category":"Muziekinstrumenten",
    "sg:phone":"+31 487 512 967",
    "sg:postcode":"6651 DL",
    "sg:province":"Gelderland",
    "wof:name":"R H G Holla",
    "wof:placetype":"venue"
},
  "geometry": {"coordinates":[5.602999,51.887074],"type":"Point"}
}