{
  "type": "Feature",
  "properties": {
    "addr:full":"Postbus 81 Borger Drenthe 9530 AB",
    "addr:housenumber":"81",
    "addr:postcode":"9530 ab",
    "addr:street":"Postbus",
    "iso:country":"NL",
    "sg:address":"Postbus 81",
    "sg:city":"Borger",
    "sg:orig_category":"Accountants - Administratie- Consulenten En -Kantoren",
    "sg:phone":"+31 599 234 565",
    "sg:postcode":"9530 AB",
    "sg:province":"Drenthe",
    "wof:name":"Nbc",
    "wof:placetype":"venue"
},
  "geometry": {"coordinates":[6.79143,52.924568],"type":"Point"}
}