{
  "type": "Feature",
  "properties": {
    "addr:full":"Dijk 10 Eersel North Brabant 5521 AX",
    "addr:housenumber":"10",
    "addr:postcode":"5521 ax",
    "addr:street":"Dijk",
    "iso:country":"NL",
    "sg:address":"Dijk 10",
    "sg:city":"Eersel",
    "sg:classifiers":[
        {
            "category":"Personal",
            "subcategory":"Nail Salon",
            "type":"Services"
        }
    ],
    "sg:phone":"+31 497 513 045",
    "sg:postcode":"5521 AX",
    "sg:province":"North Brabant",
    "sg:tags":[
        "pedicure"
    ],
    "wof:name":"Klijberg-Van Thiel, Y",
    "wof:placetype":"venue"
},
  "geometry": {"coordinates":[5.31094,51.357643],"type":"Point"}
}