{
  "type": "Feature",
  "properties": {
    "addr:full":"Kievitlaan 8 Weert Limburg 6005 JV",
    "addr:housenumber":"8",
    "addr:postcode":"6005 jv",
    "addr:street":"Kievitlaan",
    "iso:country":"NL",
    "sg:address":"Kievitlaan 8",
    "sg:city":"Weert",
    "sg:orig_category":"Beautyfarms And Sauna'S",
    "sg:phone":"+31 495 452 009",
    "sg:postcode":"6005 JV",
    "sg:province":"Limburg",
    "wof:name":"H A Vd Velde",
    "wof:placetype":"venue"
},
  "geometry": {"coordinates":[5.722086,51.24625],"type":"Point"}
}