{
  "type": "Feature",
  "properties": {
    "iso:country":"NL",
    "sg:address":"Voorweg 96",
    "sg:city":"Zoetermeer",
    "sg:orig_category":"Bloemen And Planten",
    "sg:phone":"+31 79 320 0522",
    "sg:postcode":"2715 NE",
    "sg:province":"Zuid-Holland",
    "wof:name":"Groenrijk Van Den Bosch Vof",
    "wof:placetype":"venue"
},
  "geometry": {"coordinates":[4.477204,52.060837],"type":"Point"}
}