{
  "type": "Feature",
  "properties": {
    "addr:full":"Kerkstraat 261 Amsterdam Noord-Holland 1017 GW",
    "addr:housenumber":"261",
    "addr:postcode":"1017 gw",
    "addr:street":"Kerkstraat",
    "iso:country":"NL",
    "sg:address":"Kerkstraat 261",
    "sg:city":"Amsterdam",
    "sg:orig_category":"Fotostudio'S And Fotografen",
    "sg:phone":"+31 20 620 9395",
    "sg:postcode":"1017 GW",
    "sg:province":"Noord-Holland",
    "wof:name":"P. Van Raalte",
    "wof:placetype":"venue"
},
  "geometry": {"coordinates":[4.893153,52.362919],"type":"Point"}
}