{
  "type": "Feature",
  "properties": {
    "addr:full":"St Jacobsstr 16 Amsterdam Noord-Holland 1012 NC",
    "addr:housenumber":"16",
    "addr:postcode":"1012 nc",
    "iso:country":"NL",
    "sg:address":"St Jacobsstr 16",
    "sg:city":"Amsterdam",
    "sg:orig_category":"Verenigingen En Stichtingen",
    "sg:phone":"+31 20 625 9272",
    "sg:postcode":"1012 NC",
    "sg:province":"Noord-Holland",
    "wof:name":"Rebel",
    "wof:placetype":"venue"
},
  "geometry": {"coordinates":[4.895643,52.376617],"type":"Point"}
}