{
  "type": "Feature",
  "properties": {
    "iso:country":"NL",
    "sg:address":"Industriestr 2",
    "sg:city":"Sittard",
    "sg:orig_category":"Automaterialen En Gereedschappen",
    "sg:phone":"+31 46 420 1777",
    "sg:postcode":"6135 KH",
    "sg:province":"Limburg",
    "wof:name":"Lasaulec-Van Wijnsberge",
    "wof:placetype":"venue"
},
  "geometry": {"coordinates":[5.845568,50.998306],"type":"Point"}
}