{
  "type": "Feature",
  "properties": {
    "addr:full":"Emmalaan 64 Haren Gn Groningen 9752 KV",
    "addr:housenumber":"64",
    "addr:postcode":"9752 kv",
    "addr:street":"Emmalaan",
    "iso:country":"NL",
    "sg:address":"Emmalaan 64",
    "sg:city":"Haren Gn",
    "sg:orig_category":"Public Relationbureaus",
    "sg:phone":"+31 50 534 9541",
    "sg:postcode":"9752 KV",
    "sg:province":"Groningen",
    "wof:name":"Paul De Roos, Public Relations",
    "wof:placetype":"venue"
},
  "geometry": {"coordinates":[6.598191,53.168369],"type":"Point"}
}