{
  "type": "Feature",
  "properties": {
    "iso:country":"NL",
    "sg:address":"Ketelaarskampwg 17",
    "sg:city":"S Hertogenbosch",
    "sg:orig_category":"Machinefabrieken",
    "sg:phone":"+31 73 621 6408",
    "sg:postcode":"5222 AL",
    "sg:province":"Noord-Brabant",
    "sg:website":"http://www.dedieze.nl",
    "wof:name":"Dieze Bv, De",
    "wof:placetype":"venue"
},
  "geometry": {"coordinates":[5.277026,51.706913],"type":"Point"}
}