{
  "type": "Feature",
  "properties": {
    "addr:full":"Vlierboomstraat 545 'S Gravenhage South Holland 2564 JG",
    "addr:housenumber":"545 '",
    "addr:postcode":"2564 jg",
    "addr:street":"Vlierboomstraat",
    "iso:country":"NL",
    "sg:address":"Vlierboomstraat 545",
    "sg:city":"'S Gravenhage",
    "sg:classifiers":[
        {
            "category":"Fast Food",
            "type":"Food & Drink"
        }
    ],
    "sg:phone":"+31 70 323 2765",
    "sg:postcode":"2564 JG",
    "sg:province":"South Holland",
    "sg:tags":[
        "afhaal",
        "restaurant"
    ],
    "wof:name":"Chinees Indisch Thais Restaurant Foe Yie",
    "wof:placetype":"venue"
},
  "geometry": {"coordinates":[4.254095,52.067471],"type":"Point"}
}