{
  "type": "Feature",
  "properties": {
    "addr:full":"Willemsparkwg 34 Amsterdam Noord-Holland 1071 HG",
    "addr:housenumber":"34",
    "addr:postcode":"1071 hg",
    "addr:street":"Willemsparkwg",
    "iso:country":"NL",
    "sg:address":"Willemsparkwg 34",
    "sg:city":"Amsterdam",
    "sg:orig_category":"Schoenen",
    "sg:phone":"+31 20 626 1506",
    "sg:postcode":"1071 HG",
    "sg:province":"Noord-Holland",
    "wof:name":"Cmax Europe",
    "wof:placetype":"venue"
},
  "geometry": {"coordinates":[4.876482,52.357723],"type":"Point"}
}