{
  "type": "Feature",
  "properties": {
    "addr:full":"Sluisweg 20 Kruiningen Zeeland 4416 RL",
    "addr:housenumber":"20",
    "addr:postcode":"4416 rl",
    "addr:street":"Sluisweg",
    "iso:country":"NL",
    "sg:address":"Sluisweg 20",
    "sg:city":"Kruiningen",
    "sg:orig_category":"Fruit And Groenten Gh",
    "sg:phone":"+31 113 382 295",
    "sg:postcode":"4416 RL",
    "sg:province":"Zeeland",
    "wof:name":"De Keyzer Uienhandel Vof",
    "wof:placetype":"venue"
},
  "geometry": {"coordinates":[4.040119,51.444279],"type":"Point"}
}