{
  "type": "Feature",
  "properties": {
    "addr:full":"Elisabethplaats 61 Gemert Noord-Brabant 5421 LC",
    "addr:housenumber":"61",
    "addr:postcode":"5421 lc",
    "addr:street":"Elisabethplaats",
    "iso:country":"NL",
    "sg:address":"Elisabethplaats 61",
    "sg:city":"Gemert",
    "sg:orig_category":"Kappers",
    "sg:phone":"+31 492 365 308",
    "sg:postcode":"5421 LC",
    "sg:province":"Noord-Brabant",
    "wof:name":"Schuurs, R",
    "wof:placetype":"venue"
},
  "geometry": {"coordinates":[5.681409,51.557518],"type":"Point"}
}