{
  "type": "Feature",
  "properties": {
    "addr:full":"Poeldijksepad 4 Honselersdijk Zuid-Holland 2675 CL",
    "addr:housenumber":"4",
    "addr:postcode":"2675",
    "addr:street":"Poeldijksepad",
    "iso:country":"NL",
    "sg:address":"Poeldijksepad 4",
    "sg:city":"Honselersdijk",
    "sg:orig_category":"Bloemen And Planten",
    "sg:phone":"+31 174 625 743",
    "sg:postcode":"2675 CL",
    "sg:province":"Zuid-Holland",
    "wof:name":"Adr. Valstar Kwekerij Bv",
    "wof:placetype":"venue"
},
  "geometry": {"coordinates":[4.228802,52.0103],"type":"Point"}
}