{
  "type": "Feature",
  "properties": {
    "addr:full":"Burgemeester Kasteleinwg 4 Aalsmeer North Holland 1431 BX",
    "addr:housenumber":"4",
    "addr:postcode":"1431 bx",
    "addr:street":"Burgemeester Kasteleinwg",
    "iso:country":"NL",
    "sg:address":"Burgemeester Kasteleinwg 4",
    "sg:city":"Aalsmeer",
    "sg:orig_category":"Benzinestations And Brandstoffen",
    "sg:phone":"+31 297 360 987",
    "sg:postcode":"1431 BX",
    "sg:province":"North Holland",
    "wof:name":"Shell",
    "wof:placetype":"venue"
},
  "geometry": {"coordinates":[4.753518,52.270664],"type":"Point"}
}