{
  "type": "Feature",
  "properties": {
    "iso:country":"NL",
    "sg:address":"Frank Van Borselenstraat 21",
    "sg:city":"Nieuwe Tonge",
    "sg:orig_category":"Loodgieterswerk, Verwarming And Sanitaire Installaties",
    "sg:phone":"+31 187 652 589",
    "sg:postcode":"3244 XD",
    "sg:province":"Zuid-Holland",
    "wof:name":"De Klussenier",
    "wof:placetype":"venue"
},
  "geometry": {"coordinates":[4.169987,51.712666],"type":"Point"}
}