{
  "type": "Feature",
  "properties": {
    "iso:country":"NL",
    "sg:address":"Texelstroomln 3",
    "sg:city":"Den Helder",
    "sg:orig_category":"Verenigingen En Stichtingen",
    "sg:phone":"+31 223 613 539",
    "sg:postcode":"1784 EA",
    "sg:province":"Noord-Holland",
    "wof:name":"Atv Texelstroom",
    "wof:placetype":"venue"
},
  "geometry": {"coordinates":[4.753039,52.947403],"type":"Point"}
}