{
  "type": "Feature",
  "properties": {
    "addr:full":"Wethouder Ebbenlaan 166 Helmond Noord-Brabant 5702 AG",
    "addr:housenumber":"166",
    "addr:postcode":"5702",
    "addr:street":"Wethouder Ebbenlaan",
    "iso:country":"NL",
    "sg:address":"Wethouder Ebbenlaan 166",
    "sg:city":"Helmond",
    "sg:classifiers":[
        {
            "category":"Education",
            "subcategory":"Preschool",
            "type":"Public Place"
        }
    ],
    "sg:phone":"+31 492 525 177",
    "sg:postcode":"5702 AG",
    "sg:province":"Noord-Brabant",
    "sg:tags":[
        "kleuteronderwijs",
        "basis-"
    ],
    "wof:name":"Basisschool Leonardus",
    "wof:placetype":"venue"
},
  "geometry": {"coordinates":[5.669795,51.488312],"type":"Point"}
}