{
  "type": "Feature",
  "properties": {
    "addr:full":"Venneperwg 545 Nieuw Vennep North Holland 2152 CB",
    "addr:housenumber":"545;2152",
    "addr:postcode":"cb",
    "addr:street":"Nieuw Vennep North",
    "iso:country":"NL",
    "sg:address":"Venneperwg 545",
    "sg:city":"Nieuw Vennep",
    "sg:orig_category":"Kappers",
    "sg:phone":"+31 252 683 397",
    "sg:postcode":"2152 CB",
    "sg:province":"North Holland",
    "wof:name":"Marna",
    "wof:placetype":"venue"
},
  "geometry": {"coordinates":[4.630601,52.266754],"type":"Point"}
}