{
  "type": "Feature",
  "properties": {
    "iso:country":"NL",
    "sg:address":"Z Hollandpln 1",
    "sg:city":"S Gravenhage",
    "sg:orig_category":"Verenigingen En Stichtingen",
    "sg:phone":"+31 70 441 7080",
    "sg:postcode":"2596 AW",
    "sg:province":"Zuid-Holland",
    "wof:name":"Toekomstprijs, Sticht De Nat",
    "wof:placetype":"venue"
},
  "geometry": {"coordinates":[4.31846,52.093311],"type":"Point"}
}