{
  "type": "Feature",
  "properties": {
    "iso:country":"NL",
    "sg:address":"Hoornbladstraat 31",
    "sg:city":"Almelo",
    "sg:orig_category":"Bibliotheken And Openbare Archieven",
    "sg:phone":"+31 546 811 480",
    "sg:postcode":"7601 SZ",
    "sg:province":"Overijssel",
    "wof:name":"Spel- En Sportuitleen",
    "wof:placetype":"venue"
},
  "geometry": {"coordinates":[6.670617,52.343475],"type":"Point"}
}