{
  "type": "Feature",
  "properties": {
    "addr:full":"Winselerhofstr 2 Kerkrade Limburg 6467 CN",
    "addr:housenumber":"2",
    "addr:postcode":"6467 cn",
    "addr:street":"Winselerhofstr",
    "iso:country":"NL",
    "sg:address":"Winselerhofstr 2",
    "sg:city":"Kerkrade",
    "sg:orig_category":"Grafmonumenten",
    "sg:phone":"+31 45 541 1664",
    "sg:postcode":"6467 CN",
    "sg:province":"Limburg",
    "sg:website":"http://www.eymael.nl",
    "wof:name":"Eymael Natuursteenbedr",
    "wof:placetype":"venue"
},
  "geometry": {"coordinates":[6.02681,50.864799],"type":"Point"}
}