{
  "type": "Feature",
  "properties": {
    "addr:full":"Schipholweg 307 Badhoevedorp Noord-Holland 1171 PL",
    "addr:housenumber":"307",
    "addr:postcode":"1171 pl",
    "addr:street":"Schipholweg",
    "iso:country":"NL",
    "sg:address":"Schipholweg 307",
    "sg:city":"Badhoevedorp",
    "sg:orig_category":"Chemische Producten Gh",
    "sg:phone":"+31 20 659 8804",
    "sg:postcode":"1171 PL",
    "sg:province":"Noord-Holland",
    "wof:name":"Hughes Christensen Co",
    "wof:placetype":"venue"
},
  "geometry": {"coordinates":[4.786479,52.329983],"type":"Point"}
}