{
  "type": "Feature",
  "properties": {
    "addr:full":"Montaubanstr 106 Zeist Utrecht 3701 HZ",
    "addr:housenumber":"106",
    "addr:postcode":"3701 hz",
    "iso:country":"NL",
    "sg:address":"Montaubanstr 106",
    "sg:city":"Zeist",
    "sg:orig_category":"Verenigingen En Stichtingen",
    "sg:phone":"+31 30 693 5000",
    "sg:postcode":"3701 HZ",
    "sg:province":"Utrecht",
    "sg:website":"http://www.peppel.demon.nl",
    "wof:name":"Peppel, De",
    "wof:placetype":"venue"
},
  "geometry": {"coordinates":[5.238797,52.085796],"type":"Point"}
}