{
  "type": "Feature",
  "properties": {
    "addr:full":"Heiveldstr 69 Kerkrade Limburg 6466 AH",
    "addr:housenumber":"69",
    "addr:postcode":"6466 ah",
    "addr:street":"Heiveldstr",
    "iso:country":"NL",
    "sg:address":"Heiveldstr 69",
    "sg:city":"Kerkrade",
    "sg:orig_category":"Autorijscholen",
    "sg:phone":"+31 45 542 3993",
    "sg:postcode":"6466 AH",
    "sg:province":"Limburg",
    "wof:name":"Muller, George",
    "wof:placetype":"venue"
},
  "geometry": {"coordinates":[6.040329,50.863827],"type":"Point"}
}