{
  "type": "Feature",
  "properties": {
    "addr:full":"De Zuylenkamp 44 Hummelo Gelderland 6999 CD",
    "addr:housenumber":"44",
    "addr:postcode":"6999 cd",
    "addr:street":"De Zuylenkamp;Gelderland",
    "iso:country":"NL",
    "sg:address":"De Zuylenkamp 44",
    "sg:city":"Hummelo",
    "sg:orig_category":"Verzekeringen - Verzekeringskantoren",
    "sg:phone":"+31 314 381 140",
    "sg:postcode":"6999 CD",
    "sg:province":"Gelderland",
    "wof:name":"Jansen, G J",
    "wof:placetype":"venue"
},
  "geometry": {"coordinates":[-84.332077,37.387794],"type":"Point"}
}