{
  "type": "Feature",
  "properties": {
    "addr:full":"Nw Leliestr 4 Amsterdam North Holland 1015 SP",
    "addr:housenumber":"4",
    "addr:postcode":"1015 sp",
    "addr:street":"Leliestr",
    "iso:country":"NL",
    "sg:address":"Nw Leliestr 4",
    "sg:city":"Amsterdam",
    "sg:orig_category":"Wijnkoperijen En -Groothandel",
    "sg:phone":"+31 20 427 0226",
    "sg:postcode":"1015 SP",
    "sg:province":"North Holland",
    "wof:name":"Quinta",
    "wof:placetype":"venue"
},
  "geometry": {"coordinates":[4.8836989403,52.3760414124],"type":"Point"}
}