{
  "type": "Feature",
  "properties": {
    "iso:country":"NL",
    "sg:address":"Masstede 128",
    "sg:city":"Enschede",
    "sg:orig_category":"Gespecialiseerde Bouw",
    "sg:phone":"+31 53 434 8900",
    "sg:postcode":"7547 TD",
    "sg:province":"NL.08",
    "wof:name":"Dikkerboom Betonboringen Bv",
    "wof:placetype":"venue"
},
  "geometry": {"coordinates":[6.818073,52.216324],"type":"Point"}
}