{
  "type": "Feature",
  "properties": {
    "addr:full":"Dieze 5 Gemert North Brabant 5422 VS",
    "addr:housenumber":"5",
    "addr:postcode":"5422 vs",
    "addr:street":"Dieze",
    "iso:country":"NL",
    "sg:address":"Dieze 5",
    "sg:city":"Gemert",
    "sg:orig_category":"Diverse Consumentenartikelen Gh",
    "sg:phone":"+31 492 391 444",
    "sg:postcode":"5422 VS",
    "sg:province":"North Brabant",
    "wof:name":"Europet Benelux Bv",
    "wof:placetype":"venue"
},
  "geometry": {"coordinates":[5.70714,51.565491],"type":"Point"}
}