{
  "type": "Feature",
  "properties": {
    "addr:full":"Driekant 182 Zoetermeer Zuid-Holland 2711 HC",
    "addr:housenumber":"182",
    "addr:postcode":"2711 hc",
    "addr:street":"Driekant",
    "iso:country":"NL",
    "sg:address":"Driekant 182",
    "sg:city":"Zoetermeer",
    "sg:orig_category":"Herenkleding",
    "sg:phone":"+31 79 342 5380",
    "sg:postcode":"2711 HC",
    "sg:province":"Zuid-Holland",
    "sg:website":"http://www.mcgregor.nl",
    "wof:name":"Mcgregor Shop",
    "wof:placetype":"venue"
},
  "geometry": {"coordinates":[4.492005,52.061447],"type":"Point"}
}