{
  "type": "Feature",
  "properties": {
    "iso:country":"NL",
    "sg:address":"Marijkestraat 22",
    "sg:city":"Breukelen Ut",
    "sg:orig_category":"Fietshandelaren",
    "sg:phone":"+31 346 261 475",
    "sg:postcode":"3621 DC",
    "sg:province":"Utrecht",
    "wof:name":"A Van T Hoff",
    "wof:placetype":"venue"
},
  "geometry": {"coordinates":[4.99756,52.172371],"type":"Point"}
}