{
  "type": "Feature",
  "properties": {
    "addr:full":"Tonnendijk 182 Vroomshoop NL.08 7681 BT",
    "addr:housenumber":"182;nl.08",
    "addr:postcode":"7681 bt",
    "addr:street":"Tonnendijk",
    "iso:country":"NL",
    "sg:address":"Tonnendijk 182",
    "sg:city":"Vroomshoop",
    "sg:orig_category":"Autokeuringen",
    "sg:phone":"+31 546 641 136",
    "sg:postcode":"7681 BT",
    "sg:province":"NL.08",
    "wof:name":"Bandenservice Bergsma",
    "wof:placetype":"venue"
},
  "geometry": {"coordinates":[6.60821,52.46801],"type":"Point"}
}