{
  "type": "Feature",
  "properties": {
    "addr:full":"Ysselsteen 116 Wyk By Duurstede Utrecht 3961 GE",
    "addr:housenumber":"116",
    "addr:postcode":"3961",
    "addr:street":"Wyk By Duurstede",
    "iso:country":"NL",
    "sg:address":"Ysselsteen 116",
    "sg:city":"Wyk By Duurstede",
    "sg:orig_category":"Vertaalbureaus",
    "sg:phone":"+31 6 51412179",
    "sg:postcode":"3961 GE",
    "sg:province":"Utrecht",
    "wof:name":"Dawai",
    "wof:placetype":"venue"
},
  "geometry": {"coordinates":[5.345255,51.972858],"type":"Point"}
}