{
  "type": "Feature",
  "properties": {
    "addr:full":"Julianaplein 1 Zetten California 6671 CA",
    "addr:housenumber":"1",
    "addr:postcode":"6671 ca",
    "addr:street":"Julianaplein",
    "iso:country":"NL",
    "sg:address":"Julianaplein 1",
    "sg:city":"Zetten",
    "sg:orig_category":"Loodgieterswerk, Verwarming And Sanitaire Installaties",
    "sg:phone":"+31 488 452 173",
    "sg:postcode":"6671 CA",
    "sg:province":"California",
    "wof:name":"Loodgietersbedrijf Folkerts Bv",
    "wof:placetype":"venue"
},
  "geometry": {"coordinates":[-119.270203,37.271832],"type":"Point"}
}