{
  "type": "Feature",
  "properties": {
    "addr:full":"De Entree 11 Amsterdam Zuidoost Noord-Holland 1101 BH",
    "addr:housenumber":"11",
    "addr:postcode":"zuidoost;1101 bh",
    "addr:street":"De Entree",
    "iso:country":"NL",
    "sg:address":"De Entree 11",
    "sg:city":"Amsterdam Zuidoost",
    "sg:orig_category":"Banken",
    "sg:phone":"+31 20 312 2999",
    "sg:postcode":"1101 BH",
    "sg:province":"Noord-Holland",
    "wof:name":"Discount Trust Company",
    "wof:placetype":"venue"
},
  "geometry": {"coordinates":[4.938719,52.310982],"type":"Point"}
}