{
  "type": "Feature",
  "properties": {
    "addr:full":"Kapelstr 40 Prinsenbeek Noord-Brabant 4841 GJ",
    "addr:housenumber":"40",
    "addr:postcode":"4841 gj",
    "addr:street":"Kapelstr",
    "iso:country":"NL",
    "sg:address":"Kapelstr 40",
    "sg:city":"Prinsenbeek",
    "sg:orig_category":"Milieu",
    "sg:phone":"+31 76 541 5802",
    "sg:postcode":"4841 GJ",
    "sg:province":"Noord-Brabant",
    "wof:name":"Magneco Bv",
    "wof:placetype":"venue"
},
  "geometry": {"coordinates":[4.7149,51.601791],"type":"Point"}
}