{
  "type": "Feature",
  "properties": {
    "iso:country":"NL",
    "sg:address":"Kapelstr 40",
    "sg:city":"Prinsenbeek",
    "sg:orig_category":"Milieu",
    "sg:phone":"+31 76 541 5802",
    "sg:postcode":"4841 GJ",
    "sg:province":"Noord-Brabant",
    "wof:name":"Magneco Bv",
    "wof:placetype":"venue"
},
  "geometry": {"coordinates":[4.7149,51.601791],"type":"Point"}
}