{
  "type": "Feature",
  "properties": {
    "iso:country":"NL",
    "sg:address":"Aelbrechtskade 148-150",
    "sg:city":"Rotterdam",
    "sg:orig_category":"Autokeuringen",
    "sg:phone":"+31 10 477 4099",
    "sg:postcode":"3023 JJ",
    "sg:province":"South Holland",
    "wof:name":"Automobielbedrijf Trio",
    "wof:placetype":"venue"
},
  "geometry": {"coordinates":[4.448283,51.91188],"type":"Point"}
}