{
  "type": "Feature",
  "properties": {
    "addr:full":"Marktstraat 5 Dedemsvaart Overijssel 7701 GT",
    "addr:housenumber":"5",
    "addr:postcode":"7701 gt",
    "addr:street":"Marktstraat",
    "iso:country":"NL",
    "sg:address":"Marktstraat 5",
    "sg:city":"Dedemsvaart",
    "sg:orig_category":"Bloemen And Planten",
    "sg:phone":"+31 523 613 386",
    "sg:postcode":"7701 GT",
    "sg:province":"Overijssel",
    "wof:name":"Bloemenhuis De Lelie",
    "wof:placetype":"venue"
},
  "geometry": {"coordinates":[6.457491,52.601097],"type":"Point"}
}