{
  "type": "Feature",
  "properties": {
    "iso:country":"NL",
    "sg:address":"Rott 61",
    "sg:city":"Vylen",
    "sg:orig_category":"Vakantieverblijven",
    "sg:phone":"+31 6 51174241",
    "sg:postcode":"6294 NL",
    "sg:province":"Limburg",
    "wof:name":"Hoeve Haan",
    "wof:placetype":"venue"
},
  "geometry": {"coordinates":[5.946423,50.78701],"type":"Point"}
}