{
  "type": "Feature",
  "properties": {
    "iso:country":"NL",
    "sg:address":"Gelderlandplein 131",
    "sg:city":"Amsterdam",
    "sg:orig_category":"Kappers",
    "sg:phone":"+31 20 644 1484",
    "sg:postcode":"1082 LV",
    "sg:province":"Noord-Holland",
    "wof:name":"Kapsalon Fango Bv",
    "wof:placetype":"venue"
},
  "geometry": {"coordinates":[-94.58502960209999,38.350479126],"type":"Point"}
}