{
  "type": "Feature",
  "properties": {
    "iso:country":"NL",
    "sg:address":"Vlierboomstraat 480",
    "sg:city":"'S Gravenhage",
    "sg:orig_category":"Fotostudio'S And Fotografen",
    "sg:phone":"+31 70 323 9925",
    "sg:postcode":"2564 JL",
    "sg:province":"Zuid-Holland",
    "wof:name":"Egbert Zwier Fotografie",
    "wof:placetype":"venue"
},
  "geometry": {"coordinates":[4.257256,52.068203],"type":"Point"}
}