{
  "type": "Feature",
  "properties": {
    "addr:full":"Winkelhof 12 Leiderdorp Zuid-Holland 2353 TR",
    "addr:housenumber":"12",
    "addr:postcode":"2353 tr",
    "addr:street":"Winkelhof",
    "iso:country":"NL",
    "sg:address":"Winkelhof 12",
    "sg:city":"Leiderdorp",
    "sg:orig_category":"Wasserettes And Stomerijen",
    "sg:phone":"+31 71 541 1979",
    "sg:postcode":"2353 TR",
    "sg:province":"Zuid-Holland",
    "wof:name":"Stomerij Abbink",
    "wof:placetype":"venue"
},
  "geometry": {"coordinates":[4.5326838493,52.1631469727],"type":"Point"}
}