{
  "type": "Feature",
  "properties": {
    "addr:full":"Looierstraat 54 Arnhem Gelderland 6811 AZ",
    "addr:housenumber":"54",
    "addr:postcode":"6811 az",
    "addr:street":"Looierstraat",
    "iso:country":"NL",
    "sg:address":"Looierstraat 54",
    "sg:city":"Arnhem",
    "sg:orig_category":"Verhuur Audiovisuele Apparatuur",
    "sg:phone":"+31 26 442 4162",
    "sg:postcode":"6811 AZ",
    "sg:province":"Gelderland",
    "wof:name":"Live Music Recording & Instruments",
    "wof:placetype":"venue"
},
  "geometry": {"coordinates":[5.909738,51.98357],"type":"Point"}
}