{
  "type": "Feature",
  "properties": {
    "iso:country":"NL",
    "sg:address":"Reitschewg 20",
    "sg:city":"S Hertogenbosch",
    "sg:orig_category":"Autoruiten",
    "sg:phone":"+31 73 641 3841",
    "sg:postcode":"5232 BZ",
    "sg:province":"Noord-Brabant",
    "sg:website":"http://www.carglass.nl",
    "wof:name":"Carglass",
    "wof:placetype":"venue"
},
  "geometry": {"coordinates":[5.33802,51.710865],"type":"Point"}
}