{
  "type": "Feature",
  "properties": {
    "addr:full":"S Bikoplaats 79 Rotterdam South Holland 3065 EE",
    "addr:housenumber":"79",
    "addr:postcode":"3065 ee",
    "addr:street":"S Bikoplaats",
    "iso:country":"NL",
    "sg:address":"S Bikoplaats 79",
    "sg:city":"Rotterdam",
    "sg:orig_category":"Facilitaire Dienstverlening",
    "sg:phone":"+31 10 202 6671",
    "sg:postcode":"3065 EE",
    "sg:province":"South Holland",
    "wof:name":"Easy Bel Serv",
    "wof:placetype":"venue"
},
  "geometry": {"coordinates":[4.556692,51.921631],"type":"Point"}
}