{
  "type": "Feature",
  "properties": {
    "iso:country":"NL",
    "sg:address":"Paardskerkhofwg 14",
    "sg:city":"S Hertogenbosch",
    "sg:orig_category":"Organisatiebureaus",
    "sg:phone":"+31 73 627 3600",
    "sg:postcode":"5223 AJ",
    "sg:province":"North Brabant",
    "sg:website":"http://www.eye2key.com",
    "wof:name":"Eye 2 Key",
    "wof:placetype":"venue"
},
  "geometry": {"coordinates":[5.2913241386,51.6966056824],"type":"Point"}
}