{
  "type": "Feature",
  "properties": {
    "addr:full":"Cauwelaersewg 12A Ulvenhout Ac Noord-Brabant 4858 RH",
    "addr:housenumber":"12a",
    "addr:postcode":"4858 rh",
    "addr:street":"Cauwelaersewg",
    "iso:country":"NL",
    "sg:address":"Cauwelaersewg 12A",
    "sg:city":"Ulvenhout Ac",
    "sg:orig_category":"Kinderopvang",
    "sg:phone":"+31 76 560 1404",
    "sg:postcode":"4858 RH",
    "sg:province":"Noord-Brabant",
    "wof:name":"Popje",
    "wof:placetype":"venue"
},
  "geometry": {"coordinates":[4.806483,51.537357],"type":"Point"}
}