{
  "type": "Feature",
  "properties": {
    "addr:full":"Merkusstraat 124 'S Gravenhage South Holland 2593 TP",
    "addr:housenumber":"124 '",
    "addr:postcode":"2593 tp",
    "addr:street":"Merkusstraat",
    "iso:country":"NL",
    "sg:address":"Merkusstraat 124",
    "sg:city":"'S Gravenhage",
    "sg:orig_category":"Verzekeringen",
    "sg:phone":"+31 70 385 1036",
    "sg:postcode":"2593 TP",
    "sg:province":"South Holland",
    "wof:name":"Assurantiekantoor R. Sureveen",
    "wof:placetype":"venue"
},
  "geometry": {"coordinates":[4.34229,52.08812],"type":"Point"}
}