{
  "type": "Feature",
  "properties": {
    "addr:full":"Sint Theresiaplein 11 Eindhoven Noord-Brabant 5652 EV",
    "addr:housenumber":"11",
    "addr:postcode":"5652 ev",
    "addr:street":"Sint Theresiaplein",
    "iso:country":"NL",
    "sg:address":"Sint Theresiaplein 11",
    "sg:city":"Eindhoven",
    "sg:orig_category":"Adviesbureaus Bouwkunde",
    "sg:phone":"+31 40 243 6937",
    "sg:postcode":"5652 EV",
    "sg:province":"Noord-Brabant",
    "wof:name":"Eendracht",
    "wof:placetype":"venue"
},
  "geometry": {"coordinates":[5.440391,51.438641],"type":"Point"}
}