{
  "type": "Feature",
  "properties": {
    "addr:full":"A Dekenln 195 Bussum Noord-Holland 1403 HE",
    "addr:housenumber":"195",
    "addr:postcode":"1403 he",
    "iso:country":"NL",
    "sg:address":"A Dekenln 195",
    "sg:city":"Bussum",
    "sg:orig_category":"Keukens",
    "sg:phone":"+31 35 691 9965",
    "sg:postcode":"1403 HE",
    "sg:province":"Noord-Holland",
    "wof:name":"Veen, E Van Der",
    "wof:placetype":"venue"
},
  "geometry": {"coordinates":[5.191216,52.268463],"type":"Point"}
}