{
  "type": "Feature",
  "properties": {
    "addr:full":"Oude Zeewg 22 Noordwyk Zh Zuid-Holland 2201 TB",
    "addr:housenumber":"22",
    "addr:postcode":"2201 tb",
    "addr:street":"Oude Zeewg",
    "iso:country":"NL",
    "sg:address":"Oude Zeewg 22",
    "sg:city":"Noordwyk Zh",
    "sg:classifiers":[
        {
            "category":"Travel",
            "subcategory":"Hotels & Motels",
            "type":"Entertainment"
        }
    ],
    "sg:phone":"+31 71 361 2417",
    "sg:postcode":"2201 TB",
    "sg:province":"Zuid-Holland",
    "sg:website":"http://www.pirombo.nl",
    "wof:name":"Pirombo",
    "wof:placetype":"venue"
},
  "geometry": {"coordinates":[4.43736,52.236073],"type":"Point"}
}