{
  "type": "Feature",
  "properties": {
    "addr:full":"Gruttolaan 104 Enkhuizen Noord-Holland 1602 PL",
    "addr:housenumber":"104",
    "addr:postcode":"1602 pl",
    "addr:street":"Gruttolaan",
    "iso:country":"NL",
    "sg:address":"Gruttolaan 104",
    "sg:city":"Enkhuizen",
    "sg:orig_category":"Artiestenbureaus",
    "sg:phone":"+31 228 314 484",
    "sg:postcode":"1602 PL",
    "sg:province":"Noord-Holland",
    "wof:name":"Tonny Taphoorn",
    "wof:placetype":"venue"
},
  "geometry": {"coordinates":[5.279786,52.715054],"type":"Point"}
}