{
  "type": "Feature",
  "properties": {
    "addr:full":"Koningspln 4/5 Arnhem Gelderland 6811 BV",
    "addr:housenumber":"4 / 5",
    "addr:postcode":"6811 bv",
    "addr:street":"Koningspln",
    "iso:country":"NL",
    "sg:address":"Koningspln 4/5",
    "sg:city":"Arnhem",
    "sg:orig_category":"Zalenverhuur",
    "sg:phone":"+31 26 442 6692",
    "sg:postcode":"6811 BV",
    "sg:province":"Gelderland",
    "sg:website":"http://www.stadskelder.nl",
    "wof:name":"Stadskelder, De",
    "wof:placetype":"venue"
},
  "geometry": {"coordinates":[5.913179,51.981316],"type":"Point"}
}