{
  "type": "Feature",
  "properties": {
    "addr:full":"De Kwinkelier 49A Bilthoven Utrecht 3722 AS",
    "addr:housenumber":"49a",
    "addr:postcode":"3722 as",
    "addr:street":"De Kwinkelier",
    "iso:country":"NL",
    "sg:address":"De Kwinkelier 49A",
    "sg:city":"Bilthoven",
    "sg:orig_category":"Opticiens",
    "sg:phone":"+31 30 225 3392",
    "sg:postcode":"3722 AS",
    "sg:province":"Utrecht",
    "sg:website":"http://www.hansanders.nl",
    "wof:name":"Hans Anders",
    "wof:placetype":"venue"
},
  "geometry": {"coordinates":[5.2101898193,52.128692627],"type":"Point"}
}