{
  "type": "Feature",
  "properties": {
    "addr:full":"Amstel 256 Amsterdam North Holland 1017 AL",
    "addr:housenumber":"256",
    "addr:postcode":"1017 al",
    "addr:street":"Amstel",
    "iso:country":"NL",
    "sg:address":"Amstel 256",
    "sg:city":"Amsterdam",
    "sg:orig_category":"Boekhouders",
    "sg:phone":"+31 20 622 0180",
    "sg:postcode":"1017 AL",
    "sg:province":"North Holland",
    "wof:name":"Administratiekantoor F.T.C. Visser Bv",
    "wof:placetype":"venue"
},
  "geometry": {"coordinates":[4.901346,52.36359],"type":"Point"}
}