{
  "type": "Feature",
  "properties": {
    "addr:full":"Dorpshuiswg 26 Harkstede Groningen 9617 BN",
    "addr:housenumber":"26",
    "addr:postcode":"9617 bn",
    "addr:street":"Dorpshuiswg",
    "iso:country":"NL",
    "sg:address":"Dorpshuiswg 26",
    "sg:city":"Harkstede",
    "sg:orig_category":"Kaarsen - Fabrieken En Groothandel",
    "sg:phone":"+31 50 404 1256",
    "sg:postcode":"9617 BN",
    "sg:province":"Groningen",
    "wof:name":"Vlinder, De",
    "wof:placetype":"venue"
},
  "geometry": {"coordinates":[6.7017030716,53.2114028931],"type":"Point"}
}