{
  "type": "Feature",
  "properties": {
    "addr:full":"Schiedamseweg 5 Rotterdam Zuid-Holland 3026 AA",
    "addr:housenumber":"5",
    "addr:postcode":"3026 aa",
    "addr:street":"Schiedamseweg",
    "iso:country":"NL",
    "sg:address":"Schiedamseweg 5",
    "sg:city":"Rotterdam",
    "sg:orig_category":"Apothekers",
    "sg:phone":"+31 10 477 1364",
    "sg:postcode":"3026 AA",
    "sg:province":"Zuid-Holland",
    "wof:name":"Apotheek Delfshaven",
    "wof:placetype":"venue"
},
  "geometry": {"coordinates":[4.448243,51.909966],"type":"Point"}
}