{
  "type": "Feature",
  "properties": {
    "addr:full":"Ganzenbeekstr 2 Voorthuizen Gelderland 3781 AV",
    "addr:housenumber":"2",
    "addr:postcode":"3781 av",
    "addr:street":"Ganzenbeekstr;Gelderland",
    "iso:country":"NL",
    "sg:address":"Ganzenbeekstr 2",
    "sg:city":"Voorthuizen",
    "sg:orig_category":"Makelaars En Adviseurs Onroerende Goederen",
    "sg:phone":"+31 342 472 125",
    "sg:postcode":"3781 AV",
    "sg:province":"Gelderland",
    "wof:name":"Eikelenboom Bv",
    "wof:placetype":"venue"
},
  "geometry": {"coordinates":[5.602401,52.185032],"type":"Point"}
}