{
  "type": "Feature",
  "properties": {
    "addr:full":"Dorpsstr 22 Tuitjenhorn Noord-Holland 1747 HD",
    "addr:housenumber":"22",
    "addr:postcode":"1747 hd",
    "addr:street":"Dorpsstr",
    "iso:country":"NL",
    "sg:address":"Dorpsstr 22",
    "sg:city":"Tuitjenhorn",
    "sg:classifiers":[
        {
            "category":"Retail",
            "subcategory":"Auto Repair",
            "type":"Services"
        }
    ],
    "sg:phone":"+31 226 391 204",
    "sg:postcode":"1747 HD",
    "sg:province":"Noord-Holland",
    "sg:tags":[
        "garage"
    ],
    "wof:name":"Stoop",
    "wof:placetype":"venue"
},
  "geometry": {"coordinates":[4.749198,52.737598],"type":"Point"}
}