{
  "type": "Feature",
  "properties": {
    "addr:full":"Hoevenbos 18 Zoetermeer South Holland 2716 PJ",
    "addr:housenumber":"18",
    "addr:postcode":"2716 pj",
    "addr:street":"Hoevenbos",
    "iso:country":"NL",
    "sg:address":"Hoevenbos 18",
    "sg:city":"Zoetermeer",
    "sg:orig_category":"Autorijscholen",
    "sg:phone":"+31 79 352 2855",
    "sg:postcode":"2716 PJ",
    "sg:province":"South Holland",
    "wof:name":"Exact -Saathi",
    "wof:placetype":"venue"
},
  "geometry": {"coordinates":[4.474506,52.060699],"type":"Point"}
}