{
  "type": "Feature",
  "properties": {
    "addr:full":"Boreelstr 15 S Gravenhage Zuid-Holland 2582 TW",
    "addr:housenumber":"15;gravenhage",
    "addr:postcode":"2582 tw",
    "addr:street":"Boreelstr;S",
    "iso:country":"NL",
    "sg:address":"Boreelstr 15",
    "sg:city":"S Gravenhage",
    "sg:orig_category":"Adviesbureaus Bedrijfsorganisatie",
    "sg:phone":"+31 70 351 2000",
    "sg:postcode":"2582 TW",
    "sg:province":"Zuid-Holland",
    "wof:name":"Clim",
    "wof:placetype":"venue"
},
  "geometry": {"coordinates":[4.27852,52.092411],"type":"Point"}
}