{
  "type": "Feature",
  "properties": {
    "iso:country":"NL",
    "sg:address":"De Ambachten 141",
    "sg:city":"Heeze",
    "sg:orig_category":"Partycatering And -Organisatie",
    "sg:phone":"+31 40 226 5874",
    "sg:postcode":"5591 NX",
    "sg:province":"North Brabant",
    "wof:name":"De Cateringspecialist",
    "wof:placetype":"venue"
},
  "geometry": {"coordinates":[5.562229,51.385193],"type":"Point"}
}