{
  "type": "Feature",
  "properties": {
    "addr:full":"Couwenbergstraat 127 Nijmegen Gelderland 6535 RX",
    "addr:housenumber":"127",
    "addr:postcode":"6535 rx",
    "addr:street":"Couwenbergstraat;Gelderland",
    "iso:country":"NL",
    "sg:address":"Couwenbergstraat 127",
    "sg:city":"Nijmegen",
    "sg:classifiers":[
        {
            "category":"Fast Food",
            "type":"Food & Drink"
        }
    ],
    "sg:phone":"+31 24 355 8958",
    "sg:postcode":"6535 RX",
    "sg:province":"Gelderland",
    "sg:tags":[
        "afhaal",
        "restaurant"
    ],
    "wof:name":"Multi Snacks",
    "wof:placetype":"venue"
},
  "geometry": {"coordinates":[5.8237929344,51.8073310852],"type":"Point"}
}