{
  "type": "Feature",
  "properties": {
    "addr:full":"J Dellaertstr 5 Westdorpe Zeeland 4554 BB",
    "addr:housenumber":"5",
    "addr:postcode":"4554 bb",
    "iso:country":"NL",
    "sg:address":"J Dellaertstr 5",
    "sg:city":"Westdorpe",
    "sg:orig_category":"Architecten En Architectenbureaus",
    "sg:phone":"+31 115 452 918",
    "sg:postcode":"4554 BB",
    "sg:province":"Zeeland",
    "wof:name":"Sijnesael, Ir F",
    "wof:placetype":"venue"
},
  "geometry": {"coordinates":[3.825471,51.232052],"type":"Point"}
}