{
  "type": "Feature",
  "properties": {
    "iso:country":"NL",
    "sg:address":"Schrans 54",
    "sg:city":"Leeuwarden",
    "sg:orig_category":"Boekhandels",
    "sg:phone":"+31 58 215 7880",
    "sg:postcode":"8932 NG",
    "sg:province":"Provincie Friesland",
    "wof:name":"Friese Schrijfkamer",
    "wof:placetype":"venue"
},
  "geometry": {"coordinates":[5.798413,53.1954],"type":"Point"}
}