{
  "type": "Feature",
  "properties": {
    "iso:country":"NL",
    "sg:address":"Chauss\u00e9e De Namur 260",
    "sg:city":"Marbais",
    "sg:orig_category":"Product-Promotie",
    "sg:phone":"+31 71870100",
    "sg:postcode":"B-14 95",
    "sg:website":"http://www.the-cotton-group.com",
    "wof:name":"Cotton Group, The",
    "wof:placetype":"venue"
},
  "geometry": {"coordinates":[4.535355,50.545361],"type":"Point"}
}