{
  "type": "Feature",
  "properties": {
    "addr:full":"Zuideinde 53 Grootschermer Noord-Holland 1843 JM",
    "addr:housenumber":"53",
    "addr:postcode":"1843 jm",
    "addr:street":"Zuideinde",
    "iso:country":"NL",
    "sg:address":"Zuideinde 53",
    "sg:city":"Grootschermer",
    "sg:orig_category":"Hoogwerkers",
    "sg:phone":"+31 299 671 413",
    "sg:postcode":"1843 JM",
    "sg:province":"Noord-Holland",
    "sg:website":"http://www.pilkes.com",
    "wof:name":"Pilkes, Verhuur",
    "wof:placetype":"venue"
},
  "geometry": {"coordinates":[4.849371,52.579353],"type":"Point"}
}