{
  "type": "Feature",
  "properties": {
    "addr:full":"Zuideinde 24 Broek In Waterland North Holland 1151 CP",
    "addr:housenumber":"24",
    "addr:postcode":"1151 cp",
    "addr:street":"Zuideinde",
    "iso:country":"NL",
    "sg:address":"Zuideinde 24",
    "sg:city":"Broek In Waterland",
    "sg:orig_category":"Parketvloeren",
    "sg:phone":"+31 20 403 3709",
    "sg:postcode":"1151 CP",
    "sg:province":"North Holland",
    "wof:name":"Houten Huis, Het",
    "wof:placetype":"venue"
},
  "geometry": {"coordinates":[4.998495,52.432011],"type":"Point"}
}