{
  "type": "Feature",
  "properties": {
    "addr:full":"Erkenkamp 3 Tegelen Limburg 5931 BR",
    "addr:housenumber":"3",
    "addr:postcode":"5931 br",
    "addr:street":"Erkenkamp",
    "iso:country":"NL",
    "sg:address":"Erkenkamp 3",
    "sg:city":"Tegelen",
    "sg:orig_category":"Afzuiginstallaties",
    "sg:phone":"+31 77 373 1228",
    "sg:postcode":"5931 BR",
    "sg:province":"Limburg",
    "wof:name":"Lmt Bv",
    "wof:placetype":"venue"
},
  "geometry": {"coordinates":[6.130493,51.339367],"type":"Point"}
}