{
  "type": "Feature",
  "properties": {
    "iso:country":"NL",
    "sg:address":"Korne 84",
    "sg:city":"Rotterdam",
    "sg:orig_category":"Video - Faciliteiten En Producties",
    "sg:phone":"+31 10 420 9325",
    "sg:postcode":"3068 GN",
    "sg:province":"Zuid-Holland",
    "wof:name":"Gimpad",
    "wof:placetype":"venue"
},
  "geometry": {"coordinates":[4.571597,51.960796],"type":"Point"}
}