{
  "type": "Feature",
  "properties": {
    "addr:full":"P V Anrooyln 80 Eindhoven Noord-Brabant 5654 MD",
    "addr:housenumber":"80",
    "addr:postcode":"5654",
    "addr:street":"Anrooyln",
    "iso:country":"NL",
    "sg:address":"P V Anrooyln 80",
    "sg:city":"Eindhoven",
    "sg:orig_category":"Gordijnenateliers",
    "sg:phone":"+31 40 251 7152",
    "sg:postcode":"5654 MD",
    "sg:province":"Noord-Brabant",
    "wof:name":"Hirtum & Janssen, Van",
    "wof:placetype":"venue"
},
  "geometry": {"coordinates":[5.45901,51.420891],"type":"Point"}
}