{
  "type": "Feature",
  "properties": {
    "addr:full":"Ruilverkavel Wg 4 Budel Noord-Brabant 6021 RP",
    "addr:housenumber":"4",
    "addr:postcode":"6021 rp",
    "addr:street":"Wg",
    "iso:country":"NL",
    "sg:address":"Ruilverkavel Wg 4",
    "sg:city":"Budel",
    "sg:orig_category":"Loonbedrijven",
    "sg:phone":"+31 495 491 940",
    "sg:postcode":"6021 RP",
    "sg:province":"Noord-Brabant",
    "wof:name":"Wildenberg, Van Den",
    "wof:placetype":"venue"
},
  "geometry": {"coordinates":[5.607146,51.286961],"type":"Point"}
}