{
  "type": "Feature",
  "properties": {
    "addr:full":"Zernikeln 16 Heemstede Noord-Holland 2105 RN",
    "addr:housenumber":"16",
    "addr:postcode":"2105 rn",
    "addr:street":"Zernikeln",
    "iso:country":"NL",
    "sg:address":"Zernikeln 16",
    "sg:city":"Heemstede",
    "sg:orig_category":"Beeldende Kunstenaars",
    "sg:phone":"+31 23 529 0641",
    "sg:postcode":"2105 RN",
    "sg:province":"Noord-Holland",
    "wof:name":"Graft, H Van Der",
    "wof:placetype":"venue"
},
  "geometry": {"coordinates":[4.621248,52.345287],"type":"Point"}
}