{
  "type": "Feature",
  "properties": {
    "iso:country":"NL",
    "sg:address":"Zesde Vogelstraat 30",
    "sg:city":"Amsterdam",
    "sg:orig_category":"Drukkerijen And Copyshops",
    "sg:phone":"+31 20 634 1381",
    "sg:postcode":"1022 XE",
    "sg:province":"Noord-Holland",
    "wof:name":"Stetyco",
    "wof:placetype":"venue"
},
  "geometry": {"coordinates":[4.928931,52.386532],"type":"Point"}
}