{
  "type": "Feature",
  "properties": {
    "addr:full":"Dorpsstr 183 Harskamp Gelderland 6732 AD",
    "addr:housenumber":"183",
    "addr:postcode":"6732 ad",
    "addr:street":"Gelderland",
    "iso:country":"NL",
    "sg:address":"Dorpsstr 183",
    "sg:city":"Harskamp",
    "sg:orig_category":"Fietsen En Bromfietsen",
    "sg:phone":"+31 318 456 420",
    "sg:postcode":"6732 AD",
    "sg:province":"Gelderland",
    "wof:name":"Hol Tweewielers, G",
    "wof:placetype":"venue"
},
  "geometry": {"coordinates":[5.749965,52.133926],"type":"Point"}
}