{
  "type": "Feature",
  "properties": {
    "addr:full":"Andromedastr 3 Ymuiden Noord-Holland 1973 VW",
    "addr:housenumber":"3",
    "addr:postcode":"1973 vw",
    "addr:street":"Andromedastr",
    "iso:country":"NL",
    "sg:address":"Andromedastr 3",
    "sg:city":"Ymuiden",
    "sg:orig_category":"Homeopathie",
    "sg:phone":"+31 255 525 971",
    "sg:postcode":"1973 VW",
    "sg:province":"Noord-Holland",
    "wof:name":"Groen, Yvonne",
    "wof:placetype":"venue"
},
  "geometry": {"coordinates":[4.597655,52.454666],"type":"Point"}
}