{
  "type": "Feature",
  "properties": {
    "addr:full":"Wolvenrade 53 Den Haag Zuid-Holland 2544  V",
    "addr:housenumber":"53;2544",
    "addr:postcode":"v",
    "addr:street":"Wolvenrade",
    "iso:country":"NL",
    "sg:address":"Wolvenrade 53",
    "sg:city":"Den Haag",
    "sg:orig_category":"Werving And Selectie Van Vast Personeel",
    "sg:phone":"+31 70 321 3480",
    "sg:postcode":"2544  V",
    "sg:province":"Zuid-Holland",
    "wof:name":"Uitzendbureau En Agrarischloonbedrijf De Kroon",
    "wof:placetype":"venue"
},
  "geometry": {"coordinates":[4.2616691589,52.0447692871],"type":"Point"}
}