{
  "type": "Feature",
  "properties": {
    "addr:full":"Fazantwg 5 Klundert Noord-Brabant 4791 RR",
    "addr:housenumber":"5",
    "addr:postcode":"4791 rr",
    "addr:street":"Fazantwg",
    "iso:country":"NL",
    "sg:address":"Fazantwg 5",
    "sg:city":"Klundert",
    "sg:orig_category":"Pijpleidingen",
    "sg:phone":"+31 168 323 500",
    "sg:postcode":"4791 RR",
    "sg:province":"Noord-Brabant",
    "wof:name":"Hcc Bv",
    "wof:placetype":"venue"
},
  "geometry": {"coordinates":[-61.766769,1.84229],"type":"Point"}
}