{
  "type": "Feature",
  "properties": {
    "addr:full":"De Driegang 1 Purmerend North Holland 1447 HX",
    "addr:housenumber":"1",
    "addr:postcode":"1447 hx",
    "addr:street":"De Driegang",
    "iso:country":"NL",
    "sg:address":"De Driegang 1",
    "sg:city":"Purmerend",
    "sg:orig_category":"Peuterspeelzalen",
    "sg:phone":"+31 299 642 506",
    "sg:postcode":"1447 HX",
    "sg:province":"North Holland",
    "wof:name":"Pinquin, De",
    "wof:placetype":"venue"
},
  "geometry": {"coordinates":[4.967856,52.492645],"type":"Point"}
}