{
  "type": "Feature",
  "properties": {
    "addr:full":"Wibautstr 278 Zaandam Noord-Holland 1505 HR",
    "addr:housenumber":"278",
    "addr:postcode":"1505 hr",
    "iso:country":"NL",
    "sg:address":"Wibautstr 278",
    "sg:city":"Zaandam",
    "sg:classifiers":[
        {
            "category":"Travel",
            "subcategory":"Hotels & Motels",
            "type":"Entertainment"
        }
    ],
    "sg:phone":"+31 75 670 6331",
    "sg:postcode":"1505 HR",
    "sg:province":"Noord-Holland",
    "sg:website":"http://www.bastionhotels.nl",
    "wof:name":"Bastion A'Dam/ Zaandam",
    "wof:placetype":"venue"
},
  "geometry": {"coordinates":[4.842449,52.42942],"type":"Point"}
}