{
  "type": "Feature",
  "properties": {
    "addr:full":"J Luykenstr 116 Haarlem North Holland 2026 AJ",
    "addr:housenumber":"116",
    "addr:postcode":"2026 aj",
    "iso:country":"NL",
    "sg:address":"J Luykenstr 116",
    "sg:city":"Haarlem",
    "sg:orig_category":"Acupunctuur",
    "sg:phone":"+31 23 537 3730",
    "sg:postcode":"2026 AJ",
    "sg:province":"North Holland",
    "wof:name":"Schutte G J",
    "wof:placetype":"venue"
},
  "geometry": {"coordinates":[4.653975,52.420166],"type":"Point"}
}