{
  "type": "Feature",
  "properties": {
    "iso:country":"NL",
    "sg:address":"Vechtstr 57",
    "sg:city":"Zwolle",
    "sg:classifiers":[
        {
            "category":"Food & Beverages",
            "subcategory":"Fruits & Vegetables",
            "type":"Retail Goods"
        }
    ],
    "sg:phone":"+31 38 453 4025",
    "sg:postcode":"8021 AS",
    "sg:province":"NL.08",
    "sg:tags":[
        "en",
        "groenten"
    ],
    "wof:name":"Vegt De Echte Groenteman, V/D",
    "wof:placetype":"venue"
},
  "geometry": {"coordinates":[6.106453,52.515663],"type":"Point"}
}