{
  "type": "Feature",
  "properties": {
    "addr:full":"Leidijk 1 Waskemeer Provincie Friesland 8434 NC",
    "addr:housenumber":"1;8434",
    "addr:street":"Leidijk;Provincie Friesland",
    "iso:country":"NL",
    "sg:address":"Leidijk 1",
    "sg:city":"Waskemeer",
    "sg:orig_category":"Verhuur Audiovisuele Apparatuur",
    "sg:phone":"+31 516 421 609",
    "sg:postcode":"8434 NC",
    "sg:province":"Provincie Friesland",
    "wof:name":"Presentatie Techniek Holland",
    "wof:placetype":"venue"
},
  "geometry": {"coordinates":[6.280435,53.055939],"type":"Point"}
}