{
  "type": "Feature",
  "properties": {
    "iso:country":"NL",
    "sg:address":"Leidijk 1",
    "sg:city":"Waskemeer",
    "sg:orig_category":"Verhuur Audiovisuele Apparatuur",
    "sg:phone":"+31 516 421 609",
    "sg:postcode":"8434 NC",
    "sg:province":"Provincie Friesland",
    "wof:name":"Presentatie Techniek Holland",
    "wof:placetype":"venue"
},
  "geometry": {"coordinates":[6.280435,53.055939],"type":"Point"}
}