{
  "type": "Feature",
  "properties": {
    "addr:full":"Laakwg 235 S Gravenhage Zuid-Holland 2521 SW",
    "addr:housenumber":"235;gravenhage;2521",
    "addr:street":"S;Sw",
    "iso:country":"NL",
    "sg:address":"Laakwg 235",
    "sg:city":"S Gravenhage",
    "sg:orig_category":"Verenigingsgebouwen",
    "sg:phone":"+31 70 390 1041",
    "sg:postcode":"2521 SW",
    "sg:province":"Zuid-Holland",
    "wof:name":"Laakkwartier Centraal Jongerencentr",
    "wof:placetype":"venue"
},
  "geometry": {"coordinates":[4.32071,52.062988],"type":"Point"}
}