{
  "type": "Feature",
  "properties": {
    "addr:full":"Boterhoeksestr 48 Heteren Gelderland 6666 GA",
    "addr:housenumber":"48",
    "addr:postcode":"6666 ga",
    "addr:street":"Boterhoeksestr;Gelderland",
    "iso:country":"NL",
    "sg:address":"Boterhoeksestr 48",
    "sg:city":"Heteren",
    "sg:orig_category":"Onderzoekbureaus",
    "sg:phone":"+31 26 479 1111",
    "sg:postcode":"6666 GA",
    "sg:province":"Gelderland",
    "sg:website":"http://www.nioo.nl",
    "wof:name":"Nioo",
    "wof:placetype":"venue"
},
  "geometry": {"coordinates":[-83.222931,32.678131],"type":"Point"}
}