{
  "type": "Feature",
  "properties": {
    "addr:full":"Dykstr 52 Honselersdyk Arizona 2675 AZ",
    "addr:housenumber":"52",
    "addr:postcode":"2675 az",
    "addr:street":"Dykstr",
    "iso:country":"NL",
    "sg:address":"Dykstr 52",
    "sg:city":"Honselersdyk",
    "sg:orig_category":"Boekhandels",
    "sg:phone":"+31 174 610 730",
    "sg:postcode":"2675 AZ",
    "sg:province":"Arizona",
    "wof:name":"Boekelier, De",
    "wof:placetype":"venue"
},
  "geometry": {"coordinates":[-111.93034400000001,34.168091],"type":"Point"}
}