{
  "type": "Feature",
  "properties": {
    "addr:full":"Innovatielaan 11 Nijehaske Friesland 8466 SN",
    "addr:housenumber":"11",
    "addr:postcode":"8466 sn",
    "addr:street":"Innovatielaan",
    "iso:country":"NL",
    "sg:address":"Innovatielaan 11",
    "sg:city":"Nijehaske",
    "sg:orig_category":"Verf En Lak - Grondstoffen",
    "sg:phone":"+31 513 657 500",
    "sg:postcode":"8466 SN",
    "sg:province":"Friesland",
    "sg:website":"http://www.efka.com",
    "wof:name":"Efka Additives Bv",
    "wof:placetype":"venue"
},
  "geometry": {"coordinates":[5.890138,52.968662],"type":"Point"}
}