{
  "type": "Feature",
  "properties": {
    "addr:full":"Galvanistr 29 Nykerk Gld Gelderland 3861 NJ",
    "addr:housenumber":"29",
    "addr:postcode":"3861",
    "addr:street":"Galvanistr;Gld Gelderland",
    "iso:country":"NL",
    "sg:address":"Galvanistr 29",
    "sg:city":"Nykerk Gld",
    "sg:orig_category":"Muziekinstrumenten En Bladmuziek",
    "sg:phone":"+31 33 245 7300",
    "sg:postcode":"3861 NJ",
    "sg:province":"Gelderland",
    "sg:website":"http://www.steenbeekmusic.nl",
    "wof:name":"Theo Steenbeek",
    "wof:placetype":"venue"
},
  "geometry": {"coordinates":[5.47037,52.238476],"type":"Point"}
}