{
  "type": "Feature",
  "properties": {
    "addr:full":"Koningswg 6 Eibergen Gelderland 7152 CD",
    "addr:housenumber":"6",
    "addr:postcode":"7152 cd",
    "addr:street":"Koningswg;Gelderland",
    "iso:country":"NL",
    "sg:address":"Koningswg 6",
    "sg:city":"Eibergen",
    "sg:orig_category":"Adviesbureaus Bouwkunde",
    "sg:phone":"+31 545 478 724",
    "sg:postcode":"7152 CD",
    "sg:province":"Gelderland",
    "wof:name":"Grotenhuis, J B Te",
    "wof:placetype":"venue"
},
  "geometry": {"coordinates":[6.658264,52.078354],"type":"Point"}
}