{
  "type": "Feature",
  "properties": {
    "addr:full":"Betuwestr 14 Amsterdam Noord-Holland 1079 PR",
    "addr:housenumber":"14",
    "addr:postcode":"1079 pr",
    "addr:street":"Betuwestr",
    "iso:country":"NL",
    "sg:address":"Betuwestr 14",
    "sg:city":"Amsterdam",
    "sg:orig_category":"Psychotherapeuten",
    "sg:phone":"+31 20 644 0547",
    "sg:postcode":"1079 PR",
    "sg:province":"Noord-Holland",
    "wof:name":"Koster-Sanders, T M",
    "wof:placetype":"venue"
},
  "geometry": {"coordinates":[4.895526,52.339436],"type":"Point"}
}