{
  "type": "Feature",
  "properties": {
    "addr:full":"Kasteelln 23 Well Lb Limburg 5855 AD",
    "addr:housenumber":"23",
    "addr:postcode":"lb;5855 ad",
    "addr:street":"Kasteelln",
    "iso:country":"NL",
    "sg:address":"Kasteelln 23",
    "sg:city":"Well Lb",
    "sg:orig_category":"Scholen Voor Basisonderwijs",
    "sg:phone":"+31 478 501 155",
    "sg:postcode":"5855 AD",
    "sg:province":"Limburg",
    "wof:name":"Vitus Rk, St",
    "wof:placetype":"venue"
},
  "geometry": {"coordinates":[-93.129936,36.705662],"type":"Point"}
}