{
  "type": "Feature",
  "properties": {
    "addr:full":"Bachstraat 2 Zutphen Gelderland 7204 NT",
    "addr:housenumber":"2",
    "addr:postcode":"7204 nt",
    "addr:street":"Bachstraat;Gelderland",
    "iso:country":"NL",
    "sg:address":"Bachstraat 2",
    "sg:city":"Zutphen",
    "sg:orig_category":"Kinderopvang Behalve Thuis",
    "sg:phone":"+31 575 526 496",
    "sg:postcode":"7204 NT",
    "sg:province":"Gelderland",
    "wof:name":"De Speeldoos Dagcentrum Voor Kinderen",
    "wof:placetype":"venue"
},
  "geometry": {"coordinates":[6.200764,52.1329],"type":"Point"}
}