{
  "type": "Feature",
  "properties": {
    "addr:full":"Niekerkerdiep 1 Niekerk Grootegast Groningen 9822 AH",
    "addr:housenumber":"1",
    "addr:postcode":"9822 ah",
    "addr:street":"Niekerkerdiep",
    "iso:country":"NL",
    "sg:address":"Niekerkerdiep 1",
    "sg:city":"Niekerk Grootegast",
    "sg:orig_category":"Kampeerterreinen",
    "sg:phone":"+31 594 503 446",
    "sg:postcode":"9822 AH",
    "sg:province":"Groningen",
    "wof:name":"Camping De Heerenborgh",
    "wof:placetype":"venue"
},
  "geometry": {"coordinates":[6.3674731255,53.2363624573],"type":"Point"}
}