{
  "type": "Feature",
  "properties": {
    "addr:full":"Laag-Nieuwkoop 12 Kockengen Utrecht 3628 GC",
    "addr:housenumber":"12",
    "addr:postcode":"3628 gc",
    "addr:street":"Laag-Nieuwkoop",
    "iso:country":"NL",
    "sg:address":"Laag-Nieuwkoop 12",
    "sg:city":"Kockengen",
    "sg:orig_category":"Goederenvervoer Over De Weg",
    "sg:phone":"+31 30 677 1698",
    "sg:postcode":"3628 GC",
    "sg:province":"Utrecht",
    "wof:name":"Fa A.C. Van Der Gun En Zn",
    "wof:placetype":"venue"
},
  "geometry": {"coordinates":[4.979968,52.131287],"type":"Point"}
}