{
  "type": "Feature",
  "properties": {
    "addr:full":"Slotplaats 2 Huizen Noord-Holland 1275 DJ",
    "addr:housenumber":"2",
    "addr:postcode":"1275 dj",
    "addr:street":"Slotplaats",
    "iso:country":"NL",
    "sg:address":"Slotplaats 2",
    "sg:city":"Huizen",
    "sg:orig_category":"Kinderopvang Behalve Thuis",
    "sg:phone":"+31 35 526 2810",
    "sg:postcode":"1275 DJ",
    "sg:province":"Noord-Holland",
    "wof:name":"Het Koekoeksnest",
    "wof:placetype":"venue"
},
  "geometry": {"coordinates":[5.263423,52.292255],"type":"Point"}
}