{
  "type": "Feature",
  "properties": {
    "addr:full":"Steenbreek 23 Woubrugge Zuid-Holland 2481 CJ",
    "addr:housenumber":"23",
    "addr:postcode":"2481 cj",
    "addr:street":"Steenbreek",
    "iso:country":"NL",
    "sg:address":"Steenbreek 23",
    "sg:city":"Woubrugge",
    "sg:orig_category":"Jachten - Schilderwerken En Onderhoud",
    "sg:phone":"+31 6 55347544",
    "sg:postcode":"2481 CJ",
    "sg:province":"Zuid-Holland",
    "wof:name":"Kinkel, Dirk",
    "wof:placetype":"venue"
},
  "geometry": {"coordinates":[4.632206,52.173508],"type":"Point"}
}