{
  "type": "Feature",
  "properties": {
    "addr:full":"Noord Spierdijkerweg 181 Spierdijk New Mexico 1643 NM",
    "addr:housenumber":"181;1643",
    "addr:street":"Noord Spierdijkerweg",
    "iso:country":"NL",
    "sg:address":"Noord Spierdijkerweg 181",
    "sg:city":"Spierdijk",
    "sg:orig_category":"Wegen And Sportterreinen",
    "sg:phone":"+31 229 561 613",
    "sg:postcode":"1643 NM",
    "sg:province":"New Mexico",
    "wof:name":"A.J. De Vries",
    "wof:placetype":"venue"
},
  "geometry": {"coordinates":[-106.0261230469,34.1661605835],"type":"Point"}
}