{
  "type": "Feature",
  "properties": {
    "addr:full":"De Hoppen 83 Sneek Friesland 8604 CN",
    "addr:housenumber":"83",
    "addr:postcode":"8604 cn",
    "addr:street":"De Hoppen",
    "iso:country":"NL",
    "sg:address":"De Hoppen 83",
    "sg:city":"Sneek",
    "sg:orig_category":"Verzekeringen",
    "sg:phone":"+31 515 426 181",
    "sg:postcode":"8604 CN",
    "sg:province":"Friesland",
    "wof:name":"Stad Sneek Assurantien",
    "wof:placetype":"venue"
},
  "geometry": {"coordinates":[5.682996,53.028599],"type":"Point"}
}