{
  "type": "Feature",
  "properties": {
    "iso:country":"NL",
    "sg:address":"Havenpk 24",
    "sg:city":"Zierikzee",
    "sg:orig_category":"Journalisten Freelance",
    "sg:phone":"+31 6 51799148",
    "sg:postcode":"4301 CD",
    "sg:province":"Zeeland",
    "wof:name":"Dalebout, Lizette",
    "wof:placetype":"venue"
},
  "geometry": {"coordinates":[3.922,51.649071],"type":"Point"}
}