{
  "type": "Feature",
  "properties": {
    "addr:full":"Havenpk 24 Zierikzee Zeeland 4301 CD",
    "addr:housenumber":"24",
    "addr:postcode":"4301 cd",
    "addr:street":"Havenpk",
    "iso:country":"NL",
    "sg:address":"Havenpk 24",
    "sg:city":"Zierikzee",
    "sg:orig_category":"Journalisten Freelance",
    "sg:phone":"+31 6 51799148",
    "sg:postcode":"4301 CD",
    "sg:province":"Zeeland",
    "wof:name":"Dalebout, Lizette",
    "wof:placetype":"venue"
},
  "geometry": {"coordinates":[3.922,51.649071],"type":"Point"}
}