{
  "type": "Feature",
  "properties": {
    "iso:country":"NL",
    "sg:address":"Raaphorst 61",
    "sg:city":"Leiderdorp",
    "sg:orig_category":"Kappers",
    "sg:phone":"+31 71 589 5545",
    "sg:postcode":"2352 KJ",
    "sg:province":"South Holland",
    "wof:name":"Joke'S Kapsalon",
    "wof:placetype":"venue"
},
  "geometry": {"coordinates":[4.5296177864,52.1572380066],"type":"Point"}
}