{
  "type": "Feature",
  "properties": {
    "addr:full":"Dorpsstraat 59 Bleiswijk Zuid-Holland 2665 BH",
    "addr:housenumber":"59",
    "addr:postcode":"2665 bh",
    "addr:street":"Dorpsstraat",
    "iso:country":"NL",
    "sg:address":"Dorpsstraat 59",
    "sg:city":"Bleiswijk",
    "sg:orig_category":"Boekenuitgeverijen",
    "sg:phone":"+31 10 521 2528",
    "sg:postcode":"2665 BH",
    "sg:province":"Zuid-Holland",
    "wof:name":"Boekhandel Ribberink Bv",
    "wof:placetype":"venue"
},
  "geometry": {"coordinates":[4.530582,52.01107],"type":"Point"}
}