{
  "type": "Feature",
  "properties": {
    "addr:full":"De Braam 132 Deventer Overijssel 7421 CB",
    "addr:housenumber":"132",
    "addr:postcode":"7421 cb",
    "addr:street":"De Braam",
    "iso:country":"NL",
    "sg:address":"De Braam 132",
    "sg:city":"Deventer",
    "sg:orig_category":"Vertalers",
    "sg:phone":"+31 570 510 535",
    "sg:postcode":"7421 CB",
    "sg:province":"Overijssel",
    "wof:name":"Rijnaard, J A",
    "wof:placetype":"venue"
},
  "geometry": {"coordinates":[6.214106,52.243786],"type":"Point"}
}