{
  "type": "Feature",
  "properties": {
    "iso:country":"NL",
    "sg:address":"J Weitkampln 2",
    "sg:city":"Hardenberg",
    "sg:orig_category":"Kinderkleding",
    "sg:phone":"+31 6 22659700",
    "sg:postcode":"7772 SE",
    "sg:province":"Overijssel",
    "wof:name":"Olleke Bolleke",
    "wof:placetype":"venue"
},
  "geometry": {"coordinates":[6.627709,52.571167],"type":"Point"}
}