{
  "type": "Feature",
  "properties": {
    "addr:full":"Raadhuisstr 12 Middenbeemster Noord-Holland 1462 KJ",
    "addr:housenumber":"12",
    "addr:postcode":"1462 kj",
    "addr:street":"Raadhuisstr",
    "iso:country":"NL",
    "sg:address":"Raadhuisstr 12",
    "sg:city":"Middenbeemster",
    "sg:orig_category":"Voegwerken",
    "sg:phone":"+31 299 684 080",
    "sg:postcode":"1462 KJ",
    "sg:province":"Noord-Holland",
    "wof:name":"John",
    "wof:placetype":"venue"
},
  "geometry": {"coordinates":[4.912622,52.550526],"type":"Point"}
}