{
  "type": "Feature",
  "properties": {
    "iso:country":"NL",
    "sg:address":"Kijkakkers 6",
    "sg:city":"Maarheeze",
    "sg:orig_category":"Huishoudapparatuur, Televisies And Radio'S",
    "sg:phone":"+31 495 599 096",
    "sg:postcode":"6026 ER",
    "sg:province":"Noord-Brabant",
    "wof:name":"Satview Schotelantennes",
    "wof:placetype":"venue"
},
  "geometry": {"coordinates":[5.610458,51.313931],"type":"Point"}
}