{
  "type": "Feature",
  "properties": {
    "addr:full":"Brinkstraat 75 Assen Provincie Drenthe 9401 HZ",
    "addr:housenumber":"75",
    "addr:postcode":"9401 hz",
    "addr:street":"Brinkstraat;Provincie Drenthe",
    "iso:country":"NL",
    "sg:address":"Brinkstraat 75",
    "sg:city":"Assen",
    "sg:orig_category":"Wasserettes And Stomerijen",
    "sg:phone":"+31 592 313 686",
    "sg:postcode":"9401 HZ",
    "sg:province":"Provincie Drenthe",
    "wof:name":"Palthe Stomerijen Bv",
    "wof:placetype":"venue"
},
  "geometry": {"coordinates":[6.5633440018,52.9945716858],"type":"Point"}
}