{
  "type": "Feature",
  "properties": {
    "addr:full":"Havikstr 19 Apeldoorn Gelderland 7331 CK",
    "addr:housenumber":"19",
    "addr:postcode":"7331 ck",
    "addr:street":"Havikstr;Gelderland",
    "iso:country":"NL",
    "sg:address":"Havikstr 19",
    "sg:city":"Apeldoorn",
    "sg:orig_category":"Supermarkten - Levensmiddelen",
    "sg:phone":"+31 55 534 0738",
    "sg:postcode":"7331 CK",
    "sg:province":"Gelderland",
    "wof:name":"Komart",
    "wof:placetype":"venue"
},
  "geometry": {"coordinates":[5.967233,52.205856],"type":"Point"}
}