{
  "type": "Feature",
  "properties": {
    "addr:full":"Veursestrwg 280 Leidschendam Zuid-Holland 2265 CL",
    "addr:housenumber":"280",
    "addr:postcode":"2265",
    "iso:country":"NL",
    "sg:address":"Veursestrwg 280",
    "sg:city":"Leidschendam",
    "sg:orig_category":"Boeken En Tijdschriften",
    "sg:phone":"+31 70 337 7733",
    "sg:postcode":"2265 CL",
    "sg:province":"Zuid-Holland",
    "sg:website":"http://www.nbd.nl",
    "wof:name":"Nederlandse Bibliotheek Dienst Bv",
    "wof:placetype":"venue"
},
  "geometry": {"coordinates":[4.40826,52.091621],"type":"Point"}
}