{
  "type": "Feature",
  "properties": {
    "addr:full":"Kapteynstr 33 Leiden Zuid-Holland 2313 RL",
    "addr:housenumber":"33",
    "addr:postcode":"2313 rl",
    "addr:street":"Kapteynstr",
    "iso:country":"NL",
    "sg:address":"Kapteynstr 33",
    "sg:city":"Leiden",
    "sg:classifiers":[
        {
            "category":"Professional",
            "subcategory":"Management & Consulting",
            "type":"Services"
        }
    ],
    "sg:phone":"+31 71 514 0095",
    "sg:postcode":"2313 RL",
    "sg:province":"Zuid-Holland",
    "sg:tags":[
        "relation",
        "adviesbureaus",
        "public"
    ],
    "wof:name":"Beurse, Rob",
    "wof:placetype":"venue"
},
  "geometry": {"coordinates":[4.496096,52.148876],"type":"Point"}
}