{
  "type": "Feature",
  "properties": {
    "addr:full":"Roelantdreef 243 Utrecht Utrecht 3562 KH",
    "addr:housenumber":"243",
    "addr:postcode":"3562 kh",
    "addr:street":"Roelantdreef",
    "iso:country":"NL",
    "sg:address":"Roelantdreef 243",
    "sg:city":"Utrecht",
    "sg:orig_category":"Baby- And Kinderkleding",
    "sg:phone":"+31 30 262 5307",
    "sg:postcode":"3562 KH",
    "sg:province":"Utrecht",
    "wof:name":"We Men",
    "wof:placetype":"venue"
},
  "geometry": {"coordinates":[5.11259,52.113491],"type":"Point"}
}