{
  "type": "Feature",
  "properties": {
    "addr:full":"Schoolpad 7 Noordscheschut Provincie Drenthe 7914 TA",
    "addr:housenumber":"7",
    "addr:postcode":"7914 ta",
    "addr:street":"Schoolpad;Provincie Drenthe",
    "iso:country":"NL",
    "sg:address":"Schoolpad 7",
    "sg:city":"Noordscheschut",
    "sg:orig_category":"Modeontwerpen",
    "sg:phone":"+31 528 344 241",
    "sg:postcode":"7914 TA",
    "sg:province":"Provincie Drenthe",
    "wof:name":"Molen Fashion, Van Der",
    "wof:placetype":"venue"
},
  "geometry": {"coordinates":[6.527364,52.736122],"type":"Point"}
}