{
  "type": "Feature",
  "properties": {
    "addr:full":"Ryksstrwg 202 Haren Gn Groningen 9752 BR",
    "addr:housenumber":"202",
    "addr:postcode":"9752 br",
    "iso:country":"NL",
    "sg:address":"Ryksstrwg 202",
    "sg:city":"Haren Gn",
    "sg:orig_category":"Kantoorbenodigdheden",
    "sg:phone":"+31 50 537 0137",
    "sg:postcode":"9752 BR",
    "sg:province":"Groningen",
    "wof:name":"Boot & Heijmans",
    "wof:placetype":"venue"
},
  "geometry": {"coordinates":[6.6063199043,53.1706581116],"type":"Point"}
}