{
  "type": "Feature",
  "properties": {
    "addr:full":"Gronausestraat 1000 Enschede Overijssel 7534 AN",
    "addr:housenumber":"1000",
    "addr:postcode":"7534 an",
    "addr:street":"Gronausestraat",
    "iso:country":"NL",
    "sg:address":"Gronausestraat 1000",
    "sg:city":"Enschede",
    "sg:orig_category":"Autokeuringen",
    "sg:phone":"+31 53 461 1625",
    "sg:postcode":"7534 AN",
    "sg:province":"Overijssel",
    "wof:name":"Shell Garage H.B. Ten Thij",
    "wof:placetype":"venue"
},
  "geometry": {"coordinates":[6.95486,52.2164],"type":"Point"}
}