{
  "type": "Feature",
  "properties": {
    "iso:country":"NL",
    "sg:address":"Dr P Rinsemastraat 10",
    "sg:city":"Vlagtwedde",
    "sg:classifiers":[
        {
            "category":"Fast Food",
            "type":"Food & Drink"
        }
    ],
    "sg:phone":"+31 599 313 552",
    "sg:postcode":"9541 AL",
    "sg:province":"Groningen",
    "sg:tags":[
        "afhaal",
        "restaurant"
    ],
    "wof:name":"Cafetaria Petit Rest 'T Hart V Westerwolde",
    "wof:placetype":"venue"
},
  "geometry": {"coordinates":[7.106816,53.026402],"type":"Point"}
}