{
  "type": "Feature",
  "properties": {
    "addr:full":"G Gezellestr 14 Sittard Limburg 6136 HX",
    "addr:housenumber":"14",
    "addr:postcode":"6136 hx",
    "addr:street":"Sittard Limburg",
    "iso:country":"NL",
    "sg:address":"G Gezellestr 14",
    "sg:city":"Sittard",
    "sg:orig_category":"Haarwerken",
    "sg:phone":"+31 46 452 6647",
    "sg:postcode":"6136 HX",
    "sg:province":"Limburg",
    "wof:name":"Highstick Vof",
    "wof:placetype":"venue"
},
  "geometry": {"coordinates":[5.872356,51.005184],"type":"Point"}
}