{
  "type": "Feature",
  "properties": {
    "addr:full":"Bommelsestr 12B Ophemert Gelderland 4061 RG",
    "addr:housenumber":"12b",
    "addr:postcode":"4061 rg",
    "addr:street":"Bommelsestr;Gelderland",
    "iso:country":"NL",
    "sg:address":"Bommelsestr 12B",
    "sg:city":"Ophemert",
    "sg:classifiers":[
        {
            "category":"Food & Beverages",
            "subcategory":"Fruits & Vegetables",
            "type":"Retail Goods"
        }
    ],
    "sg:phone":"+31 344 651 516",
    "sg:postcode":"4061 RG",
    "sg:province":"Gelderland",
    "sg:tags":[
        "en",
        "groenten"
    ],
    "wof:name":"Alphen-Wijers, Maatsch Van",
    "wof:placetype":"venue"
},
  "geometry": {"coordinates":[5.362026,51.842777],"type":"Point"}
}