{
  "type": "Feature",
  "properties": {
    "addr:full":"Brouwersvaart 128A Haarlem Noord-Holland 2013 RD",
    "addr:housenumber":"128a",
    "addr:postcode":"2013 rd",
    "addr:street":"Brouwersvaart",
    "iso:country":"NL",
    "sg:address":"Brouwersvaart 128A",
    "sg:city":"Haarlem",
    "sg:orig_category":"Grafisch Ontwerpers",
    "sg:phone":"+31 23 531 4030",
    "sg:postcode":"2013 RD",
    "sg:province":"Noord-Holland",
    "wof:name":"Buro Ik",
    "wof:placetype":"venue"
},
  "geometry": {"coordinates":[4.626689,52.3825],"type":"Point"}
}