{
  "type": "Feature",
  "properties": {
    "iso:country":"NL",
    "sg:address":"Filipynen 116",
    "sg:city":"Utrecht",
    "sg:orig_category":"Grafisch Ontwerpers",
    "sg:phone":"+31 30 280 4044",
    "sg:postcode":"3524 JP",
    "sg:province":"Utrecht",
    "wof:name":"Bert Heesen",
    "wof:placetype":"venue"
},
  "geometry": {"coordinates":[5.131266,52.058022],"type":"Point"}
}