{
  "type": "Feature",
  "properties": {
    "addr:full":"Eebuurt 32 Leeuwarden Friesland 8911 EV",
    "addr:housenumber":"32",
    "addr:street":"Eebuurt",
    "iso:country":"NL",
    "sg:address":"Eebuurt 32",
    "sg:city":"Leeuwarden",
    "sg:orig_category":"Psychotherapeuten",
    "sg:phone":"+31 58 212 4231",
    "sg:postcode":"8911 EV",
    "sg:province":"Friesland",
    "wof:name":"Plooy, Ciny",
    "wof:placetype":"venue"
},
  "geometry": {"coordinates":[5.79257,53.197319],"type":"Point"}
}