{
  "type": "Feature",
  "properties": {
    "iso:country":"NL",
    "sg:address":"Hinthamerstraat 18",
    "sg:city":"'S Hertogenbosch",
    "sg:classifiers":[
        {
            "category":"Bakery",
            "type":"Food & Drink"
        }
    ],
    "sg:phone":"+31 73 612 0954",
    "sg:postcode":"5211 MP",
    "sg:province":"Noord-Brabant",
    "sg:tags":[
        "brood",
        "banket"
    ],
    "wof:name":"Bakkerij Bart",
    "wof:placetype":"venue"
},
  "geometry": {"coordinates":[5.305619,51.689148],"type":"Point"}
}