{
  "type": "Feature",
  "properties": {
    "addr:full":"De Peppel 13 Zeewolde NL. 3891 BB",
    "addr:housenumber":"13",
    "addr:postcode":"3891 bb",
    "addr:street":"De Peppel;Nl.",
    "iso:country":"NL",
    "sg:address":"De Peppel 13",
    "sg:city":"Zeewolde",
    "sg:orig_category":"Zuivelproducten And Spijsoli?n Gh",
    "sg:phone":"+31 36 522 1298",
    "sg:postcode":"3891 BB",
    "sg:province":"NL.",
    "wof:name":"F.W. Etty",
    "wof:placetype":"venue"
},
  "geometry": {"coordinates":[5.539946,52.333344],"type":"Point"}
}