{
  "type": "Feature",
  "properties": {
    "addr:full":"Op De Varsen 9 Maastricht Limburg 6223 GH",
    "addr:housenumber":"9",
    "addr:postcode":"6223 gh",
    "addr:street":"Op De Varsen",
    "iso:country":"NL",
    "sg:address":"Op De Varsen 9",
    "sg:city":"Maastricht",
    "sg:orig_category":"Onderhoud And Reparatie Kantoorapparatuur",
    "sg:phone":"+31 43 364 6770",
    "sg:postcode":"6223 GH",
    "sg:province":"Limburg",
    "wof:name":"W.H.J.M. Kostons",
    "wof:placetype":"venue"
},
  "geometry": {"coordinates":[5.708449,50.895145],"type":"Point"}
}