{
  "type": "Feature",
  "properties": {
    "iso:country":"NL",
    "sg:address":"Op De Varsen 9",
    "sg:city":"Maastricht",
    "sg:orig_category":"Onderhoud And Reparatie Kantoorapparatuur",
    "sg:phone":"+31 43 364 6770",
    "sg:postcode":"6223 GH",
    "sg:province":"Limburg",
    "wof:name":"W.H.J.M. Kostons",
    "wof:placetype":"venue"
},
  "geometry": {"coordinates":[5.708449,50.895145],"type":"Point"}
}