{
  "type": "Feature",
  "properties": {
    "iso:country":"NL",
    "sg:address":"Ring 24",
    "sg:city":"Zuidland",
    "sg:orig_category":"Zalenverhuur",
    "sg:phone":"+31 181 451 434",
    "sg:postcode":"3214 AT",
    "sg:province":"South Holland",
    "wof:name":"Wapen Van Zuidland, 'T",
    "wof:placetype":"venue"
},
  "geometry": {"coordinates":[4.261454,51.822536],"type":"Point"}
}