{
  "type": "Feature",
  "properties": {
    "addr:full":"Prins Bernhardlaan 2 Gennep Limburg 6591 AT",
    "addr:housenumber":"2",
    "addr:postcode":"6591",
    "addr:street":"Prins Bernhardlaan",
    "iso:country":"NL",
    "sg:address":"Prins Bernhardlaan 2",
    "sg:city":"Gennep",
    "sg:orig_category":"Kantoorartikelen",
    "sg:phone":"+31 485 517 624",
    "sg:postcode":"6591 AT",
    "sg:province":"Limburg",
    "wof:name":"Maasstad Gennep Bv",
    "wof:placetype":"venue"
},
  "geometry": {"coordinates":[5.969165802,51.6982078552],"type":"Point"}
}