{
  "type": "Feature",
  "properties": {
    "addr:full":"W Lorestr 59-61 Leeuwarden Friesland 8921 CG",
    "addr:housenumber":"59-61",
    "addr:postcode":"8921 cg",
    "addr:street":"W",
    "iso:country":"NL",
    "sg:address":"W Lorestr 59-61",
    "sg:city":"Leeuwarden",
    "sg:classifiers":[
        {
            "category":"Retail",
            "subcategory":"Auto Repair",
            "type":"Services"
        }
    ],
    "sg:phone":"+31 58 215 2626",
    "sg:postcode":"8921 CG",
    "sg:province":"Friesland",
    "sg:tags":[
        "garage"
    ],
    "wof:name":"Heide & Ritskes, Garagebedrijf",
    "wof:placetype":"venue"
},
  "geometry": {"coordinates":[5.813562,53.201977],"type":"Point"}
}