{
  "type": "Feature",
  "properties": {
    "addr:full":"Korenaarstraat 33 Nieuw Vennep North Holland 2153 BN",
    "addr:housenumber":"33",
    "addr:postcode":"2153 bn",
    "addr:street":"Korenaarstraat;Nieuw Vennep North",
    "iso:country":"NL",
    "sg:address":"Korenaarstraat 33",
    "sg:city":"Nieuw Vennep",
    "sg:orig_category":"Overheidsdiensten",
    "sg:phone":"+31 252 686 125",
    "sg:postcode":"2153 BN",
    "sg:province":"North Holland",
    "wof:name":"Anbo Gebouw",
    "wof:placetype":"venue"
},
  "geometry": {"coordinates":[4.6337809563,52.2624206543],"type":"Point"}
}