{
  "type": "Feature",
  "properties": {
    "addr:full":"Agavedreef 46 Utrecht Utrecht 3563 EN",
    "addr:housenumber":"46",
    "addr:postcode":"3563 en",
    "addr:street":"Agavedreef",
    "iso:country":"NL",
    "sg:address":"Agavedreef 46",
    "sg:city":"Utrecht",
    "sg:orig_category":"Autorijscholen",
    "sg:phone":"+31 6 54677899",
    "sg:postcode":"3563 EN",
    "sg:province":"Utrecht",
    "wof:name":"Via-Via Bennamari",
    "wof:placetype":"venue"
},
  "geometry": {"coordinates":[5.09741,52.12077],"type":"Point"}
}