{
  "type": "Feature",
  "properties": {
    "addr:full":"Caeciliastr 16 Leiden Zuid-Holland 2312 XB",
    "addr:housenumber":"16",
    "addr:postcode":"2312 xb",
    "addr:street":"Caeciliastr",
    "iso:country":"NL",
    "sg:address":"Caeciliastr 16",
    "sg:city":"Leiden",
    "sg:orig_category":"Ziekenhuizen, Sanatoria, Verpleeghuizen",
    "sg:phone":"+31 71 512 2346",
    "sg:postcode":"2312 XB",
    "sg:province":"Zuid-Holland",
    "wof:name":"Elisabeth Gasthuishof, St",
    "wof:placetype":"venue"
},
  "geometry": {"coordinates":[4.486759,52.161873],"type":"Point"}
}