{
  "type": "Feature",
  "properties": {
    "iso:country":"NL",
    "sg:address":"Bermweg 47",
    "sg:city":"Capelle A/D Ijssel",
    "sg:classifiers":[
        {
            "category":"Retail",
            "subcategory":"Photofinishing",
            "type":"Services"
        }
    ],
    "sg:phone":"+31 10 450 6907",
    "sg:postcode":"2906 LB",
    "sg:province":"South Holland",
    "sg:tags":[
        "foto",
        "film"
    ],
    "wof:name":"Foto De Ijssel",
    "wof:placetype":"venue"
},
  "geometry": {"coordinates":[4.577829,51.9366],"type":"Point"}
}