{
  "type": "Feature",
  "properties": {
    "addr:full":"Kalverstr 72 Eindhoven Noord-Brabant 5642 CJ",
    "addr:housenumber":"72",
    "addr:postcode":"5642 cj",
    "addr:street":"Kalverstr",
    "iso:country":"NL",
    "sg:address":"Kalverstr 72",
    "sg:city":"Eindhoven",
    "sg:orig_category":"Drukkerijen",
    "sg:phone":"+31 40 281 4545",
    "sg:postcode":"5642 CJ",
    "sg:province":"Noord-Brabant",
    "wof:name":"Lecturis Bv",
    "wof:placetype":"venue"
},
  "geometry": {"coordinates":[5.504117,51.444386],"type":"Point"}
}