{
  "type": "Feature",
  "properties": {
    "iso:country":"NL",
    "sg:address":"Zandstraat 25",
    "sg:city":"Bergen Op Zoom",
    "sg:orig_category":"Loodgieterswerk, Verwarming And Sanitaire Installaties",
    "sg:phone":"+31 164 253 419",
    "sg:postcode":"4614 CA",
    "sg:province":"North Brabant",
    "wof:name":"Paul Brooymans",
    "wof:placetype":"venue"
},
  "geometry": {"coordinates":[4.289101,51.502155],"type":"Point"}
}