{
  "type": "Feature",
  "properties": {
    "iso:country":"NL",
    "sg:address":"Linnaeuskd 82Hg",
    "sg:city":"Amsterdam",
    "sg:orig_category":"Filmstudio'S En -Productie",
    "sg:phone":"+31 20 694 4448",
    "sg:postcode":"1098 BD",
    "sg:province":"North Holland",
    "wof:name":"Morbid Eye Picture",
    "wof:placetype":"venue"
},
  "geometry": {"coordinates":[4.94688,52.349209],"type":"Point"}
}