{
  "type": "Feature",
  "properties": {
    "addr:full":"Schipperswal 31 Roermond Limburg 6041 TC",
    "addr:housenumber":"31",
    "addr:postcode":"6041 tc",
    "addr:street":"Schipperswal",
    "iso:country":"NL",
    "sg:address":"Schipperswal 31",
    "sg:city":"Roermond",
    "sg:orig_category":"Benzine En Olie - Groothandel",
    "sg:phone":"+31 475 316 851",
    "sg:postcode":"6041 TC",
    "sg:province":"Limburg",
    "wof:name":"Sluijs Bv, Van Der",
    "wof:placetype":"venue"
},
  "geometry": {"coordinates":[5.99232,51.202042],"type":"Point"}
}