{
  "type": "Feature",
  "properties": {
    "addr:full":"Zwarte Plakwg 37 America Limburg 5966 RH",
    "addr:housenumber":"37",
    "addr:postcode":"5966 rh",
    "addr:street":"America Limburg",
    "iso:country":"NL",
    "sg:address":"Zwarte Plakwg 37",
    "sg:city":"America",
    "sg:orig_category":"Grondboringen En Bronbemalingen",
    "sg:phone":"+31 77 464 1233",
    "sg:postcode":"5966 RH",
    "sg:province":"Limburg",
    "wof:name":"Alards Grondboringen",
    "wof:placetype":"venue"
},
  "geometry": {"coordinates":[5.97195,51.431599],"type":"Point"}
}