{
  "type": "Feature",
  "properties": {
    "addr:full":"Koninginnewg 107-2 Amsterdam North Holland 1075 CK",
    "addr:housenumber":"107-2",
    "addr:postcode":"1075 ck",
    "iso:country":"NL",
    "sg:address":"Koninginnewg 107-2",
    "sg:city":"Amsterdam",
    "sg:orig_category":"Psychotherapeuten",
    "sg:phone":"+31 20 670 2478",
    "sg:postcode":"1075 CK",
    "sg:province":"North Holland",
    "wof:name":"Associatie Voor Psychotherapie",
    "wof:placetype":"venue"
},
  "geometry": {"coordinates":[4.864992,52.353531],"type":"Point"}
}