{
  "type": "Feature",
  "properties": {
    "addr:full":"Zuidzydsewg 198 Polsbroek Utrecht 3415 PT",
    "addr:housenumber":"198",
    "addr:postcode":"3415 pt",
    "addr:street":"Polsbroek",
    "iso:country":"NL",
    "sg:address":"Zuidzydsewg 198",
    "sg:city":"Polsbroek",
    "sg:orig_category":"Verhuur",
    "sg:phone":"+31 6 27463202",
    "sg:postcode":"3415 PT",
    "sg:province":"Utrecht",
    "wof:name":"Haaij, De",
    "wof:placetype":"venue"
},
  "geometry": {"coordinates":[4.896701,51.992924],"type":"Point"}
}