{
  "type": "Feature",
  "properties": {
    "addr:full":"Rumpenerstr 60 Brunssum Limburg 6443 CE",
    "addr:housenumber":"60",
    "addr:postcode":"6443 ce",
    "addr:street":"Rumpenerstr",
    "iso:country":"NL",
    "sg:address":"Rumpenerstr 60",
    "sg:city":"Brunssum",
    "sg:classifiers":[
        {
            "category":"Travel",
            "subcategory":"Hotels & Motels",
            "type":"Entertainment"
        }
    ],
    "sg:phone":"+31 45 525 4776",
    "sg:postcode":"6443 CE",
    "sg:province":"Limburg",
    "sg:website":"http://www.rumpenerhof.com",
    "wof:name":"Rumpenerhof Hotel",
    "wof:placetype":"venue"
},
  "geometry": {"coordinates":[5.969513,50.939327],"type":"Point"}
}