{
  "type": "Feature",
  "properties": {
    "iso:country":"NL",
    "sg:address":"Goudenregenstr 24",
    "sg:city":"Capelle Ad Yssel",
    "sg:orig_category":"Boeken En Tijdschriften",
    "sg:phone":"+31 10 442 2212",
    "sg:postcode":"2906 CM",
    "sg:province":"Zuid-Holland",
    "wof:name":"Boekenhoekje, 'T",
    "wof:placetype":"venue"
},
  "geometry": {"coordinates":[4.57606,51.936775],"type":"Point"}
}