{
  "type": "Feature",
  "properties": {
    "addr:full":"Tiber 18 Doetinchem Gelderland 7007 ME",
    "addr:housenumber":"18",
    "addr:postcode":"7007 me",
    "addr:street":"Tiber;Gelderland",
    "iso:country":"NL",
    "sg:address":"Tiber 18",
    "sg:city":"Doetinchem",
    "sg:orig_category":"Administratie- En Boekhoudkantoren",
    "sg:phone":"+31 314 391 363",
    "sg:postcode":"7007 ME",
    "sg:province":"Gelderland",
    "wof:name":"Jmsh",
    "wof:placetype":"venue"
},
  "geometry": {"coordinates":[6.260956,51.953892],"type":"Point"}
}