{
  "type": "Feature",
  "properties": {
    "addr:full":"Elzenhof 27 Middenmeer Noord-Holland 1775 GG",
    "addr:housenumber":"27",
    "addr:postcode":"1775 gg",
    "addr:street":"Elzenhof",
    "iso:country":"NL",
    "sg:address":"Elzenhof 27",
    "sg:city":"Middenmeer",
    "sg:orig_category":"Elektrotechnische Installatiebureaus",
    "sg:phone":"+31 227 502 827",
    "sg:postcode":"1775 GG",
    "sg:province":"Noord-Holland",
    "sg:website":"http://www.middenmeer.nl",
    "wof:name":"Boekhout Elektrotechniek Vof",
    "wof:placetype":"venue"
},
  "geometry": {"coordinates":[5.001556,52.811012],"type":"Point"}
}