{
  "type": "Feature",
  "properties": {
    "addr:full":"Zwanenburgerdijk 333A Zwanenburg Noord-Holland 1161 NN",
    "addr:housenumber":"333a",
    "addr:postcode":"1161 nn",
    "addr:street":"Zwanenburgerdijk",
    "iso:country":"NL",
    "sg:address":"Zwanenburgerdijk 333A",
    "sg:city":"Zwanenburg",
    "sg:orig_category":"Pompen And Compressoren Fab",
    "sg:phone":"+31 20 497 6017",
    "sg:postcode":"1161 NN",
    "sg:province":"Noord-Holland",
    "wof:name":"Hydropower Service",
    "wof:placetype":"venue"
},
  "geometry": {"coordinates":[4.737682,52.384819],"type":"Point"}
}