{
  "type": "Feature",
  "properties": {
    "addr:full":"Elsweg 41 Apeldoorn Gelderland 7311 GT",
    "addr:housenumber":"41",
    "addr:postcode":"7311 gt",
    "addr:street":"Elsweg;Gelderland",
    "iso:country":"NL",
    "sg:address":"Elsweg 41",
    "sg:city":"Apeldoorn",
    "sg:orig_category":"Boekhouders",
    "sg:phone":"+31 55 578 9060",
    "sg:postcode":"7311 GT",
    "sg:province":"Gelderland",
    "wof:name":"A T Bouwservices",
    "wof:placetype":"venue"
},
  "geometry": {"coordinates":[5.954141,52.210926],"type":"Point"}
}