{
  "type": "Feature",
  "properties": {
    "addr:full":"Stadhoudersln 88 Montfoort Utrecht 3417 TX",
    "addr:housenumber":"88",
    "addr:postcode":"3417",
    "addr:street":"Stadhoudersln",
    "iso:country":"NL",
    "sg:address":"Stadhoudersln 88",
    "sg:city":"Montfoort",
    "sg:classifiers":[
        {
            "category":"Professional",
            "subcategory":"Management & Consulting",
            "type":"Services"
        }
    ],
    "sg:phone":"+31 348 468 668",
    "sg:postcode":"3417 TX",
    "sg:province":"Utrecht",
    "sg:tags":[
        "relation",
        "adviesbureaus",
        "public"
    ],
    "sg:website":"http://www.vannorel.com",
    "wof:name":"Norel, Van",
    "wof:placetype":"venue"
},
  "geometry": {"coordinates":[4.9467291832,52.0440673828],"type":"Point"}
}