{
  "type": "Feature",
  "properties": {
    "addr:full":"Burg Grundemannstr 31 Berkel En Rodenrijs Zuid-Holland 2651 EB",
    "addr:housenumber":"31",
    "addr:postcode":"2651 eb",
    "addr:street":"Burg",
    "iso:country":"NL",
    "sg:address":"Burg Grundemannstr 31",
    "sg:city":"Berkel En Rodenrijs",
    "sg:orig_category":"Verzekeringen",
    "sg:phone":"+31 10 511 7179",
    "sg:postcode":"2651 EB",
    "sg:province":"Zuid-Holland",
    "wof:name":"Koens-Castelein Verzekeringen",
    "wof:placetype":"venue"
},
  "geometry": {"coordinates":[4.482544,51.995453],"type":"Point"}
}