{
  "type": "Feature",
  "properties": {
    "iso:country":"NL",
    "sg:address":"Hintzenstr 10",
    "sg:city":"Maastricht",
    "sg:orig_category":"Adviesbureaus Elektrotechniek",
    "sg:phone":"+31 43 343 6035",
    "sg:postcode":"6216 ES",
    "sg:province":"Limburg",
    "wof:name":"Martens",
    "wof:placetype":"venue"
},
  "geometry": {"coordinates":[5.667839,50.845928],"type":"Point"}
}