{
  "type": "Feature",
  "properties": {
    "addr:full":"Notel 3 Oirschot North Brabant 5688 NB",
    "addr:housenumber":"3",
    "addr:postcode":"5688 nb",
    "addr:street":"Notel",
    "iso:country":"NL",
    "sg:address":"Notel 3",
    "sg:city":"Oirschot",
    "sg:orig_category":"Kunsthandel",
    "sg:phone":"+31 6 26526163",
    "sg:postcode":"5688 NB",
    "sg:province":"North Brabant",
    "sg:website":"http://www.reproducties.com",
    "wof:name":"Meesterwerk",
    "wof:placetype":"venue"
},
  "geometry": {"coordinates":[5.32676,51.50655],"type":"Point"}
}