{
  "type": "Feature",
  "properties": {
    "addr:full":"Wolfshoek 62 Elshout Noord-Brabant 5154 AD",
    "addr:housenumber":"62",
    "addr:postcode":"5154 ad",
    "addr:street":"Wolfshoek",
    "iso:country":"NL",
    "sg:address":"Wolfshoek 62",
    "sg:city":"Elshout",
    "sg:orig_category":"Bloemen En Planten",
    "sg:phone":"+31 416 372 508",
    "sg:postcode":"5154 AD",
    "sg:province":"Noord-Brabant",
    "wof:name":"Mook, Gebr Van",
    "wof:placetype":"venue"
},
  "geometry": {"coordinates":[5.146464,51.699852],"type":"Point"}
}