{
  "type": "Feature",
  "properties": {
    "addr:full":"Grt Kerk 36 Hoorn Nh North Holland 1621 ET",
    "addr:housenumber":"36",
    "addr:postcode":"1621 et",
    "addr:street":"Kerk;Nh North",
    "iso:country":"NL",
    "sg:address":"Grt Kerk 36",
    "sg:city":"Hoorn Nh",
    "sg:orig_category":"Babyartikelen",
    "sg:phone":"+31 229 215 186",
    "sg:postcode":"1621 ET",
    "sg:province":"North Holland",
    "sg:website":"http://www.babyplus.nl",
    "wof:name":"Baby Plus",
    "wof:placetype":"venue"
},
  "geometry": {"coordinates":[5.05207,52.642399],"type":"Point"}
}