{
  "type": "Feature",
  "properties": {
    "addr:full":"Hygieapln 44H Amsterdam Noord-Holland 1076 RW",
    "addr:postcode":"1076 rw",
    "iso:country":"NL",
    "sg:address":"Hygieapln 44H",
    "sg:city":"Amsterdam",
    "sg:orig_category":"Artsen - Huisartsen",
    "sg:phone":"+31 20 470 9799",
    "sg:postcode":"1076 RW",
    "sg:province":"Noord-Holland",
    "wof:name":"Berckel Smit, J A C M Van",
    "wof:placetype":"venue"
},
  "geometry": {"coordinates":[4.863657,52.346912],"type":"Point"}
}