{
  "type": "Feature",
  "properties": {
    "addr:full":"Edelstenenbaan 73 Ijsselstein Ut Utrecht 3402 XB",
    "addr:housenumber":"73",
    "addr:postcode":"3402 xb",
    "addr:street":"Edelstenenbaan",
    "iso:country":"NL",
    "sg:address":"Edelstenenbaan 73",
    "sg:city":"Ijsselstein Ut",
    "sg:orig_category":"Kantoorartikelen",
    "sg:phone":"+31 30 687 1407",
    "sg:postcode":"3402 XB",
    "sg:province":"Utrecht",
    "wof:name":"Handelsonderneming Lijnmar",
    "wof:placetype":"venue"
},
  "geometry": {"coordinates":[5.0465769768,52.0318069458],"type":"Point"}
}