{
  "type": "Feature",
  "properties": {
    "iso:country":"NL",
    "sg:address":"Stationsweg 29",
    "sg:city":"Budel Schoot",
    "sg:orig_category":"Bloemen And Planten Gh",
    "sg:phone":"+31 495 493 585",
    "sg:postcode":"6023 AD",
    "sg:province":"Noord-Brabant",
    "wof:name":"W E U Leukel",
    "wof:placetype":"venue"
},
  "geometry": {"coordinates":[5.565614,51.245323],"type":"Point"}
}