{
  "type": "Feature",
  "properties": {
    "addr:full":"Zevensprong 5 Capelle A/D Ijssel Zuid-Holland 2907 TK",
    "addr:housenumber":"5;a / d",
    "addr:postcode":"2907 tk",
    "addr:street":"Zevensprong",
    "iso:country":"NL",
    "sg:address":"Zevensprong 5",
    "sg:city":"Capelle A/D Ijssel",
    "sg:classifiers":[
        {
            "category":"Education",
            "subcategory":"Preschool",
            "type":"Public Place"
        }
    ],
    "sg:phone":"+31 10 227 0994",
    "sg:postcode":"2907 TK",
    "sg:province":"Zuid-Holland",
    "sg:tags":[
        "kleuteronderwijs",
        "basis-"
    ],
    "wof:name":"Gereformeerde Sbo School De Cirkel",
    "wof:placetype":"venue"
},
  "geometry": {"coordinates":[4.569164,51.948219],"type":"Point"}
}