{
  "type": "Feature",
  "properties": {
    "addr:full":"Kastanjeln 32 Driebruggen Zuid-Holland 3465 TD",
    "addr:housenumber":"32",
    "addr:postcode":"3465 td",
    "addr:street":"Kastanjeln",
    "iso:country":"NL",
    "sg:address":"Kastanjeln 32",
    "sg:city":"Driebruggen",
    "sg:orig_category":"Adviesbureaus Bedrijfsorganisatie",
    "sg:phone":"+31 348 502 873",
    "sg:postcode":"3465 TD",
    "sg:province":"Zuid-Holland",
    "wof:name":"Boer, A De",
    "wof:placetype":"venue"
},
  "geometry": {"coordinates":[4.797454,52.042545],"type":"Point"}
}