{
  "type": "Feature",
  "properties": {
    "iso:country":"NL",
    "sg:address":"Herenstraat 5",
    "sg:city":"Werkhoven",
    "sg:classifiers":[
        {
            "category":"Education",
            "subcategory":"Preschool",
            "type":"Public Place"
        }
    ],
    "sg:phone":"+31 343 551 295",
    "sg:postcode":"3985 RP",
    "sg:province":"Utrecht",
    "sg:tags":[
        "kleuteronderwijs",
        "basis-"
    ],
    "wof:name":"Delteykschool",
    "wof:placetype":"venue"
},
  "geometry": {"coordinates":[5.244799,52.02597],"type":"Point"}
}