{
  "type": "Feature",
  "properties": {
    "addr:full":"Karperwg 8B Amsterdam Noord-Holland 1075 LC",
    "addr:housenumber":"8b",
    "addr:postcode":"1075 lc",
    "addr:street":"Karperwg",
    "iso:country":"NL",
    "sg:address":"Karperwg 8B",
    "sg:city":"Amsterdam",
    "sg:classifiers":[
        {
            "category":"Retail",
            "subcategory":"Auto Repair",
            "type":"Services"
        }
    ],
    "sg:phone":"+31 20 671 5115",
    "sg:postcode":"1075 LC",
    "sg:province":"Noord-Holland",
    "sg:tags":[
        "garage"
    ],
    "wof:name":"Kappadokya",
    "wof:placetype":"venue"
},
  "geometry": {"coordinates":[4.855824,52.348537],"type":"Point"}
}