{
  "type": "Feature",
  "properties": {
    "iso:country":"NL",
    "sg:address":"Baronieln 264",
    "sg:city":"Breda",
    "sg:orig_category":"Tekstschrijversters",
    "sg:phone":"+31 76 560 0147",
    "sg:postcode":"4837 BH",
    "sg:province":"Noord-Brabant",
    "wof:name":"Teamwork",
    "wof:placetype":"venue"
},
  "geometry": {"coordinates":[4.76205,51.56707],"type":"Point"}
}