{
  "type": "Feature",
  "properties": {
    "addr:full":"Lemsterpad 56 Lemmer Friesland 8531 AA",
    "addr:housenumber":"56",
    "addr:postcode":"8531 aa",
    "addr:street":"Lemsterpad",
    "iso:country":"NL",
    "sg:address":"Lemsterpad 56",
    "sg:city":"Lemmer",
    "sg:orig_category":"Machinefabrieken",
    "sg:phone":"+31 514 562 415",
    "sg:postcode":"8531 AA",
    "sg:province":"Friesland",
    "wof:name":"Kuiken Hytrans Bv",
    "wof:placetype":"venue"
},
  "geometry": {"coordinates":[5.72609,52.836845],"type":"Point"}
}