{
  "type": "Feature",
  "properties": {
    "addr:full":"Deurningerstr 8 Enschede Overijssel 7514 BH",
    "addr:housenumber":"8",
    "addr:postcode":"7514 bh",
    "addr:street":"Deurningerstr",
    "iso:country":"NL",
    "sg:address":"Deurningerstr 8",
    "sg:city":"Enschede",
    "sg:orig_category":"Psychotherapeuten",
    "sg:phone":"+31 53 434 0283",
    "sg:postcode":"7514 BH",
    "sg:province":"Overijssel",
    "wof:name":"Psychotherapie, Groepspraktijk",
    "wof:placetype":"venue"
},
  "geometry": {"coordinates":[6.892102,52.223751],"type":"Point"}
}