{
  "type": "Feature",
  "properties": {
    "iso:country":"NL",
    "sg:address":"Scheldeln 15",
    "sg:city":"Sliedrecht",
    "sg:orig_category":"Scholen Voor Basisonderwijs",
    "sg:phone":"+31 184 412 788",
    "sg:postcode":"3363 CK",
    "sg:province":"Zuid-Holland",
    "wof:name":"Johannes Calvijn Ref",
    "wof:placetype":"venue"
},
  "geometry": {"coordinates":[4.772605,51.823555],"type":"Point"}
}