{
  "type": "Feature",
  "properties": {
    "iso:country":"NL",
    "sg:address":"Van Der Meerstraat 14",
    "sg:city":"Nijkerk Gld",
    "sg:orig_category":"Goederenvervoer Over De Weg",
    "sg:phone":"+31 33 245 8808",
    "sg:postcode":"3863 AG",
    "sg:province":"Gelderland",
    "wof:name":"E. Bezembinder",
    "wof:placetype":"venue"
},
  "geometry": {"coordinates":[5.48354,52.221371],"type":"Point"}
}