{
  "type": "Feature",
  "properties": {
    "addr:full":"Purmerpln 11 Amsterdam North Holland 1023 BC",
    "addr:housenumber":"11",
    "addr:postcode":"1023 bc",
    "addr:street":"Purmerpln",
    "iso:country":"NL",
    "sg:address":"Purmerpln 11",
    "sg:city":"Amsterdam",
    "sg:orig_category":"Bloemen En Planten",
    "sg:phone":"+31 20 632 7802",
    "sg:postcode":"1023 BC",
    "sg:province":"North Holland",
    "wof:name":"Helena",
    "wof:placetype":"venue"
},
  "geometry": {"coordinates":[4.943968,52.391567],"type":"Point"}
}