{
  "type": "Feature",
  "properties": {
    "iso:country":"NL",
    "sg:address":"C De Vriesweg 50",
    "sg:city":"Dirkshorn",
    "sg:orig_category":"Meubelzaken, Woning- And Keukeninrichting",
    "sg:phone":"+31 224 551 523",
    "sg:postcode":"1746 CM",
    "sg:province":"Noord-Holland",
    "wof:name":"Jac Nota Slaapcomfort",
    "wof:placetype":"venue"
},
  "geometry": {"coordinates":[4.778541,52.749889],"type":"Point"}
}