{
  "type": "Feature",
  "properties": {
    "iso:country":"NL",
    "sg:address":"Tol 14",
    "sg:city":"Werkendam",
    "sg:orig_category":"Ongediertebestrijding En Ontsmetting",
    "sg:phone":"+31 183 301 270",
    "sg:postcode":"4251 PX",
    "sg:province":"North Brabant",
    "sg:website":"http://www.ppd.nl",
    "wof:name":"Ppd Werkendam",
    "wof:placetype":"venue"
},
  "geometry": {"coordinates":[4.935107,51.800392],"type":"Point"}
}