{
  "type": "Feature",
  "properties": {
    "addr:full":"Bleulandwg 382 Gouda South Holland 2803 HP",
    "addr:housenumber":"382",
    "addr:postcode":"2803 hp",
    "iso:country":"NL",
    "sg:address":"Bleulandwg 382",
    "sg:city":"Gouda",
    "sg:orig_category":"Homeopathie",
    "sg:phone":"+31 182 559 388",
    "sg:postcode":"2803 HP",
    "sg:province":"South Holland",
    "wof:name":"Straver, W J",
    "wof:placetype":"venue"
},
  "geometry": {"coordinates":[4.700059,52.020287],"type":"Point"}
}