{
  "type": "Feature",
  "properties": {
    "iso:country":"NL",
    "sg:address":"Postbus 75889",
    "sg:city":"Amsterdam",
    "sg:orig_category":"Makelaars En Adviseurs Verzekeringen",
    "sg:phone":"+31 20 305 0250",
    "sg:postcode":"1070 AW",
    "sg:province":"Overijssel",
    "sg:website":"http://www.dsv-insurance.nl",
    "wof:name":"Dsv Bv",
    "wof:placetype":"venue"
},
  "geometry": {"coordinates":[4.8920497894,52.373550415],"type":"Point"}
}