{
  "type": "Feature",
  "properties": {
    "addr:full":"Tuinstr 18 Werkendam Noord-Brabant 4251 XM",
    "addr:housenumber":"18",
    "addr:postcode":"4251 xm",
    "addr:street":"Tuinstr",
    "iso:country":"NL",
    "sg:address":"Tuinstr 18",
    "sg:city":"Werkendam",
    "sg:orig_category":"Honden- En Kattentrimsalons",
    "sg:phone":"+31 183 678 772",
    "sg:postcode":"4251 XM",
    "sg:province":"Noord-Brabant",
    "wof:name":"Senta",
    "wof:placetype":"venue"
},
  "geometry": {"coordinates":[4.897511,51.808361],"type":"Point"}
}