{
  "type": "Feature",
  "properties": {
    "addr:full":"Computerwg 6 Utrecht Utrecht 3542 DR",
    "addr:housenumber":"6",
    "addr:postcode":"3542 dr",
    "addr:street":"Computerwg",
    "iso:country":"NL",
    "sg:address":"Computerwg 6",
    "sg:city":"Utrecht",
    "sg:orig_category":"Verenigingen En Stichtingen",
    "sg:phone":"+31 346 550 040",
    "sg:postcode":"3542 DR",
    "sg:province":"Utrecht",
    "wof:name":"Entadministratie Utrecht & Noord-Holland, Sticht",
    "wof:placetype":"venue"
},
  "geometry": {"coordinates":[5.04241,52.125774],"type":"Point"}
}