{
  "type": "Feature",
  "properties": {
    "addr:full":"Zeegstraat 25 Reusel Noord-Brabant 5541 EW",
    "addr:housenumber":"25",
    "addr:postcode":"5541 ew",
    "addr:street":"Zeegstraat",
    "iso:country":"NL",
    "sg:address":"Zeegstraat 25",
    "sg:city":"Reusel",
    "sg:orig_category":"Bloemen And Planten",
    "sg:phone":"+31 497 641 934",
    "sg:postcode":"5541 EW",
    "sg:province":"Noord-Brabant",
    "wof:name":"Tuincentrum Jan Van Gestel",
    "wof:placetype":"venue"
},
  "geometry": {"coordinates":[5.157258,51.365715],"type":"Point"}
}