{
  "type": "Feature",
  "properties": {
    "addr:full":"V Hogendorpwg 3 De Bilt Utrecht 3732 XK",
    "addr:housenumber":"3",
    "addr:postcode":"3732 xk",
    "addr:street":"Hogendorpwg",
    "iso:country":"NL",
    "sg:address":"V Hogendorpwg 3",
    "sg:city":"De Bilt",
    "sg:orig_category":"Organisatiebureaus",
    "sg:phone":"+31 30 221 0311",
    "sg:postcode":"3732 XK",
    "sg:province":"Utrecht",
    "wof:name":"Cultuurinzicht",
    "wof:placetype":"venue"
},
  "geometry": {"coordinates":[5.1799049377,52.1080207825],"type":"Point"}
}