{
  "type": "Feature",
  "properties": {
    "addr:full":"Stevinstr 240 S Gravenhage Zuid-Holland 2587 EW",
    "addr:housenumber":"240;gravenhage",
    "addr:postcode":"2587 ew",
    "addr:street":"S",
    "iso:country":"NL",
    "sg:address":"Stevinstr 240",
    "sg:city":"S Gravenhage",
    "sg:orig_category":"Artsen - Huisartsen",
    "sg:phone":"+31 70 350 7882",
    "sg:postcode":"2587 EW",
    "sg:province":"Zuid-Holland",
    "wof:name":"Ashmuth, E J U Von",
    "wof:placetype":"venue"
},
  "geometry": {"coordinates":[4.29118,52.112942],"type":"Point"}
}