{
  "type": "Feature",
  "properties": {
    "addr:full":"Eduard Vetermanstraat 9 Middelburg Zeeland 4333 CJ",
    "addr:housenumber":"9",
    "addr:postcode":"4333 cj",
    "addr:street":"Eduard Vetermanstraat",
    "iso:country":"NL",
    "sg:address":"Eduard Vetermanstraat 9",
    "sg:city":"Middelburg",
    "sg:orig_category":"Juridische Dienstverlening",
    "sg:phone":"+31 118 627 245",
    "sg:postcode":"4333 CJ",
    "sg:province":"Zeeland",
    "wof:name":"Buro Budgethulp",
    "wof:placetype":"venue"
},
  "geometry": {"coordinates":[3.6101169586,51.5114860535],"type":"Point"}
}