{
  "type": "Feature",
  "properties": {
    "addr:full":"Zonnedauwhof 27 Roermond Limburg 6043 KG",
    "addr:housenumber":"27",
    "addr:postcode":"6043 kg",
    "addr:street":"Zonnedauwhof",
    "iso:country":"NL",
    "sg:address":"Zonnedauwhof 27",
    "sg:city":"Roermond",
    "sg:orig_category":"Loodgieterswerk, Verwarming And Sanitaire Installaties",
    "sg:phone":"+31 475 328 323",
    "sg:postcode":"6043 KG",
    "sg:province":"Limburg",
    "wof:name":"Munnix Ventilatie P.M.H. Munnix",
    "wof:placetype":"venue"
},
  "geometry": {"coordinates":[6.024082,51.192314],"type":"Point"}
}