{
  "type": "Feature",
  "properties": {
    "addr:full":"Dorpsstraat 42 Nieuwegein Utrecht 3433 CL",
    "addr:housenumber":"42",
    "addr:postcode":"3433",
    "addr:street":"Dorpsstraat",
    "iso:country":"NL",
    "sg:address":"Dorpsstraat 42",
    "sg:city":"Nieuwegein",
    "sg:classifiers":[
        {
            "category":"Communications",
            "subcategory":"Television Station",
            "type":"Services"
        }
    ],
    "sg:phone":"+31 30 606 2745",
    "sg:postcode":"3433 CL",
    "sg:province":"Utrecht",
    "sg:tags":[
        "video",
        "audio",
        "verhuur"
    ],
    "wof:name":"Videotheek Nieuwegein",
    "wof:placetype":"venue"
},
  "geometry": {"coordinates":[5.094954,52.004463],"type":"Point"}
}