{
  "type": "Feature",
  "properties": {
    "iso:country":"NL",
    "sg:address":"Tungeler Dorpsstr 17",
    "sg:city":"Weert",
    "sg:orig_category":"Melktransporten",
    "sg:phone":"+31 495 562 903",
    "sg:postcode":"6005 RG",
    "sg:province":"Limburg",
    "wof:name":"Saes-Vranken Vof",
    "wof:placetype":"venue"
},
  "geometry": {"coordinates":[5.726042,51.211452],"type":"Point"}
}