{
  "type": "Feature",
  "properties": {
    "addr:full":"Kanaalstr 59 Roden Drenthe 9301 LR",
    "addr:housenumber":"59",
    "addr:postcode":"9301 lr",
    "addr:street":"Kanaalstr",
    "iso:country":"NL",
    "sg:address":"Kanaalstr 59",
    "sg:city":"Roden",
    "sg:orig_category":"Kampeerartikelen",
    "sg:phone":"+31 50 501 3628",
    "sg:postcode":"9301 LR",
    "sg:province":"Drenthe",
    "sg:website":"http://www.dewaardtenten.nl",
    "wof:name":"Waard Tenten, De",
    "wof:placetype":"venue"
},
  "geometry": {"coordinates":[6.4330420494,53.1414794922],"type":"Point"}
}