{
  "type": "Feature",
  "properties": {
    "addr:full":"Ketting 7 Heerenveen Friesland 8446 EG",
    "addr:housenumber":"7",
    "addr:postcode":"8446 eg",
    "addr:street":"Ketting",
    "iso:country":"NL",
    "sg:address":"Ketting 7",
    "sg:city":"Heerenveen",
    "sg:orig_category":"Adviesbureaus Bedrijfsorganisatie",
    "sg:phone":"+31 513 624 030",
    "sg:postcode":"8446 EG",
    "sg:province":"Friesland",
    "wof:name":"Frimab Bv",
    "wof:placetype":"venue"
},
  "geometry": {"coordinates":[5.906212,52.953392],"type":"Point"}
}