{
  "type": "Feature",
  "properties": {
    "addr:full":"Brugstr 3 Almelo Overijssel 7607 XJ",
    "addr:housenumber":"3",
    "addr:postcode":"7607 xj",
    "addr:street":"Brugstr",
    "iso:country":"NL",
    "sg:address":"Brugstr 3",
    "sg:city":"Almelo",
    "sg:orig_category":"Woninginrichting",
    "sg:phone":"+31 546 657 677",
    "sg:postcode":"7607 XJ",
    "sg:province":"Overijssel",
    "sg:website":"http://www.detapijtmobiel.nl",
    "wof:name":"Tapijt Mobiel, De",
    "wof:placetype":"venue"
},
  "geometry": {"coordinates":[6.6597747803,52.3579864502],"type":"Point"}
}