{
  "type": "Feature",
  "properties": {
    "addr:full":"Lg Brink 100 Apeldoorn Gelderland 7317 BD",
    "addr:housenumber":"100",
    "addr:postcode":"7317 bd",
    "addr:street":"Lg Brink;Gelderland",
    "iso:country":"NL",
    "sg:address":"Lg Brink 100",
    "sg:city":"Apeldoorn",
    "sg:orig_category":"Autoverhuur",
    "sg:phone":"+31 55 360 2902",
    "sg:postcode":"7317 BD",
    "sg:province":"Gelderland",
    "sg:website":"http://www.kav.nl",
    "wof:name":"Kav",
    "wof:placetype":"venue"
},
  "geometry": {"coordinates":[5.971213,52.244843],"type":"Point"}
}