{
  "type": "Feature",
  "properties": {
    "addr:full":"Dreef 74 Rotterdam South Holland 3075 HC",
    "addr:housenumber":"74",
    "addr:postcode":"3075 hc",
    "addr:street":"Dreef",
    "iso:country":"NL",
    "sg:address":"Dreef 74",
    "sg:city":"Rotterdam",
    "sg:orig_category":"Antiekzaken",
    "sg:phone":"+31 10 432 2074",
    "sg:postcode":"3075 HC",
    "sg:province":"South Holland",
    "wof:name":"De Dubbele Deur Antiek",
    "wof:placetype":"venue"
},
  "geometry": {"coordinates":[4.510827,51.88726],"type":"Point"}
}