{
  "type": "Feature",
  "properties": {
    "iso:country":"NL",
    "sg:address":"Rembrandtstr 32",
    "sg:city":"Reeuwyk",
    "sg:orig_category":"Land- En Tuinbouw - Loonbedrijven",
    "sg:phone":"+31 182 394 401",
    "sg:postcode":"2811 XC",
    "sg:province":"South Holland",
    "wof:name":"Koppenaal, J",
    "wof:placetype":"venue"
},
  "geometry": {"coordinates":[4.716779,52.04425],"type":"Point"}
}