{
  "type": "Feature",
  "properties": {
    "addr:full":"Oude Spiegelstraat 4Hs Amsterdam North Holland 1016 BM",
    "addr:housenumber":"4hs",
    "addr:postcode":"1016 bm",
    "addr:street":"Oude Spiegelstraat",
    "iso:country":"NL",
    "sg:address":"Oude Spiegelstraat 4Hs",
    "sg:city":"Amsterdam",
    "sg:orig_category":"Kappers",
    "sg:phone":"+31 20 626 6012",
    "sg:postcode":"1016 BM",
    "sg:province":"North Holland",
    "wof:name":"Interline Hairstudio",
    "wof:placetype":"venue"
},
  "geometry": {"coordinates":[4.887611866,52.3703308105],"type":"Point"}
}