{
  "type": "Feature",
  "properties": {
    "addr:full":"Plantage 96 Beverwyk North Holland 1943 LP",
    "addr:housenumber":"96",
    "addr:postcode":"1943 lp",
    "addr:street":"Plantage;North",
    "iso:country":"NL",
    "sg:address":"Plantage 96",
    "sg:city":"Beverwyk",
    "sg:orig_category":"Voegwerken",
    "sg:phone":"+31 251 221 066",
    "sg:postcode":"1943 LP",
    "sg:province":"North Holland",
    "wof:name":"Reuver, C J De",
    "wof:placetype":"venue"
},
  "geometry": {"coordinates":[4.650324,52.489597],"type":"Point"}
}