{
  "type": "Feature",
  "properties": {
    "iso:country":"NL",
    "sg:address":"Reigersbossenlaan 14",
    "sg:city":"Ijmuiden",
    "sg:orig_category":"Boekhouders",
    "sg:phone":"+31 255 519 399",
    "sg:postcode":"1974 XT",
    "sg:province":"Noord-Holland",
    "wof:name":"Raad Ijmuiden Cv",
    "wof:placetype":"venue"
},
  "geometry": {"coordinates":[4.588525,52.449581],"type":"Point"}
}