{
  "type": "Feature",
  "properties": {
    "addr:full":"1E Industriewg 8 Lopik Utrecht 3411 MG",
    "addr:housenumber":"8",
    "addr:postcode":"3411 mg",
    "addr:street":"1E Industriewg",
    "iso:country":"NL",
    "sg:address":"1E Industriewg 8",
    "sg:city":"Lopik",
    "sg:orig_category":"Houtplaatmaterialen",
    "sg:phone":"+31 348 554 501",
    "sg:postcode":"3411 MG",
    "sg:province":"Utrecht",
    "wof:name":"Ijsselfoort Bv",
    "wof:placetype":"venue"
},
  "geometry": {"coordinates":[4.972111,51.983208],"type":"Point"}
}