{
  "type": "Feature",
  "properties": {
    "addr:full":"Stationsweg 124 'S Gravenhage Zuid-Holland 2515 BR",
    "addr:housenumber":"124 '",
    "addr:postcode":"2515 br",
    "addr:street":"Stationsweg",
    "iso:country":"NL",
    "sg:address":"Stationsweg 124",
    "sg:city":"'S Gravenhage",
    "sg:orig_category":"Verzekeringen",
    "sg:phone":"+31 70 388 6611",
    "sg:postcode":"2515 BR",
    "sg:province":"Zuid-Holland",
    "wof:name":"Meyer Ass",
    "wof:placetype":"venue"
},
  "geometry": {"coordinates":[4.320688,52.071812],"type":"Point"}
}