{
  "type": "Feature",
  "properties": {
    "addr:full":"Vaartwg 59 Eemdyk Utrecht 3754 NA",
    "addr:housenumber":"59",
    "addr:postcode":"na",
    "addr:street":"Vaartwg",
    "iso:country":"NL",
    "sg:address":"Vaartwg 59",
    "sg:city":"Eemdyk",
    "sg:orig_category":"Verenigingen En Stichtingen",
    "sg:phone":"+31 33 298 4169",
    "sg:postcode":"3754 NA",
    "sg:province":"Utrecht",
    "wof:name":"Willem Tell, Schietver",
    "wof:placetype":"venue"
},
  "geometry": {"coordinates":[5.33341,52.251999],"type":"Point"}
}