{
  "type": "Feature",
  "properties": {
    "iso:country":"NL",
    "sg:address":"Woudrichemstraat 5",
    "sg:city":"Amsterdam Zuidoost",
    "sg:classifiers":[
        {
            "category":"Education",
            "subcategory":"Preschool",
            "type":"Public Place"
        }
    ],
    "sg:phone":"+31 20 697 2176",
    "sg:postcode":"1107 NE",
    "sg:province":"Noord-Holland",
    "sg:tags":[
        "kleuteronderwijs",
        "basis-"
    ],
    "wof:name":"1Ste Katholieke Montessori Basisschool De Regenboo",
    "wof:placetype":"venue"
},
  "geometry": {"coordinates":[4.987037,52.29377],"type":"Point"}
}