{
  "type": "Feature",
  "properties": {
    "addr:full":"Grote Gracht 33 Maastricht Limburg 6211 ST",
    "addr:housenumber":"33",
    "addr:postcode":"6211 st",
    "addr:street":"Grote Gracht",
    "iso:country":"NL",
    "sg:address":"Grote Gracht 33",
    "sg:city":"Maastricht",
    "sg:orig_category":"Herenmodezaken",
    "sg:phone":"+31 43 321 3666",
    "sg:postcode":"6211 ST",
    "sg:province":"Limburg",
    "wof:name":"Aristo Men'S Accessoires",
    "wof:placetype":"venue"
},
  "geometry": {"coordinates":[5.688461,50.850811],"type":"Point"}
}