{
  "type": "Feature",
  "properties": {
    "addr:full":"Brasserskade 4 Nootdorp South Holland 2631 NC",
    "addr:housenumber":"4",
    "addr:postcode":"2631 nc",
    "addr:street":"Brasserskade",
    "iso:country":"NL",
    "sg:address":"Brasserskade 4",
    "sg:city":"Nootdorp",
    "sg:orig_category":"Omroep",
    "sg:phone":"+31 15 310 6049",
    "sg:postcode":"2631 NC",
    "sg:province":"South Holland",
    "sg:website":"http://www.radioexcellent.nl",
    "wof:name":"Excellent",
    "wof:placetype":"venue"
},
  "geometry": {"coordinates":[4.387056,52.039646],"type":"Point"}
}