{
  "type": "Feature",
  "properties": {
    "iso:country":"NL",
    "sg:address":"Tarwestraat 35",
    "sg:city":"Nieuw Vennep",
    "sg:orig_category":"Verpakkingsmachines Fab",
    "sg:phone":"+31 252 621 734",
    "sg:postcode":"2153 GE",
    "sg:province":"North Holland",
    "wof:name":"Metaalbewerkingsbedrijf R. Schutten Bv",
    "wof:placetype":"venue"
},
  "geometry": {"coordinates":[4.645916,52.267467],"type":"Point"}
}