{
  "type": "Feature",
  "properties": {
    "addr:full":"Nescioplantsoen 28 Almere Flevoland 1321 BJ",
    "addr:housenumber":"28",
    "addr:postcode":"1321 bj",
    "addr:street":"Nescioplantsoen;Flevoland",
    "iso:country":"NL",
    "sg:address":"Nescioplantsoen 28",
    "sg:city":"Almere",
    "sg:orig_category":"Makelaars In Onroerend Goed",
    "sg:phone":"+31 36 546 9935",
    "sg:postcode":"1321 BJ",
    "sg:province":"Flevoland",
    "wof:name":"Ladestein",
    "wof:placetype":"venue"
},
  "geometry": {"coordinates":[5.187778,52.359203],"type":"Point"}
}