{
  "type": "Feature",
  "properties": {
    "addr:full":"Zwanenkamp 160 Maarssen Utrecht 3607 RL",
    "addr:housenumber":"160",
    "addr:postcode":"3607 rl",
    "addr:street":"Zwanenkamp",
    "iso:country":"NL",
    "sg:address":"Zwanenkamp 160",
    "sg:city":"Maarssen",
    "sg:orig_category":"Meubelreparatie And -Restauratie",
    "sg:phone":"+31 346 569 367",
    "sg:postcode":"3607 RL",
    "sg:province":"Utrecht",
    "wof:name":"Atelier Joke Teutscher",
    "wof:placetype":"venue"
},
  "geometry": {"coordinates":[5.01714,52.144348],"type":"Point"}
}