{
  "type": "Feature",
  "properties": {
    "addr:full":"Aalsvoort 31 Lochem Gelderland 7241 MA",
    "addr:housenumber":"31",
    "addr:postcode":"7241 ma",
    "addr:street":"Aalsvoort;Gelderland",
    "iso:country":"NL",
    "sg:address":"Aalsvoort 31",
    "sg:city":"Lochem",
    "sg:orig_category":"Autokeuringen",
    "sg:phone":"+31 573 256 266",
    "sg:postcode":"7241 MA",
    "sg:province":"Gelderland",
    "wof:name":"Ben Moser",
    "wof:placetype":"venue"
},
  "geometry": {"coordinates":[6.389739,52.169052],"type":"Point"}
}