{
  "type": "Feature",
  "properties": {
    "iso:country":"NL",
    "sg:address":"Oosterkaai 51",
    "sg:city":"Genemuiden",
    "sg:orig_category":"Makelaars In Onroerend Goed",
    "sg:phone":"+31 38 385 4077",
    "sg:postcode":"8281 BK",
    "sg:province":"Overijssel",
    "wof:name":"Administratie- En Assurantiekantoor H. Bonthuis",
    "wof:placetype":"venue"
},
  "geometry": {"coordinates":[6.041258,52.624981],"type":"Point"}
}