{
  "type": "Feature",
  "properties": {
    "addr:full":"Buitenplaats 131 Lelystad NL. 8212 AE",
    "addr:housenumber":"131",
    "addr:postcode":"8212 ae",
    "addr:street":"Buitenplaats;Nl.",
    "iso:country":"NL",
    "sg:address":"Buitenplaats 131",
    "sg:city":"Lelystad",
    "sg:orig_category":"Kunsthandel",
    "sg:phone":"+31 320 244 826",
    "sg:postcode":"8212 AE",
    "sg:province":"NL.",
    "wof:name":"Bos",
    "wof:placetype":"venue"
},
  "geometry": {"coordinates":[5.503328,52.517738],"type":"Point"}
}