{
  "type": "Feature",
  "properties": {
    "addr:full":"Zuidlangewg 1 Hoofdplaat Zeeland 4513 KE",
    "addr:housenumber":"1",
    "addr:postcode":"4513 ke",
    "addr:street":"Zuidlangewg",
    "iso:country":"NL",
    "sg:address":"Zuidlangewg 1",
    "sg:city":"Hoofdplaat",
    "sg:orig_category":"Verzekeringen - Verzekeringskantoren",
    "sg:phone":"+31 117 348 369",
    "sg:postcode":"4513 KE",
    "sg:province":"Zeeland",
    "wof:name":"Hagel Mij Ba Onderlinge",
    "wof:placetype":"venue"
},
  "geometry": {"coordinates":[3.65746,51.360893],"type":"Point"}
}