{
  "type": "Feature",
  "properties": {
    "addr:full":"2E Garsteln 1 Westerlee Gn Groningen 9678 RW",
    "addr:housenumber":"1",
    "addr:postcode":"gn;9678 rw",
    "addr:street":"2E Garsteln",
    "iso:country":"NL",
    "sg:address":"2E Garsteln 1",
    "sg:city":"Westerlee Gn",
    "sg:orig_category":"Bouwbureaus",
    "sg:phone":"+31 597 414 052",
    "sg:postcode":"9678 RW",
    "sg:province":"Groningen",
    "wof:name":"Bnc",
    "wof:placetype":"venue"
},
  "geometry": {"coordinates":[6.988435,53.145714],"type":"Point"}
}