{
  "type": "Feature",
  "properties": {
    "addr:full":"Birkstr 43 Soest Utrecht 3768 HC",
    "addr:housenumber":"43",
    "addr:postcode":"3768 hc",
    "addr:street":"Birkstr",
    "iso:country":"NL",
    "sg:address":"Birkstr 43",
    "sg:city":"Soest",
    "sg:orig_category":"Bestratingen",
    "sg:phone":"+31 35 601 8735",
    "sg:postcode":"3768 HC",
    "sg:province":"Utrecht",
    "wof:name":"Snijders Bv, A",
    "wof:placetype":"venue"
},
  "geometry": {"coordinates":[5.31141,52.164703],"type":"Point"}
}