{
  "type": "Feature",
  "properties": {
    "addr:full":"Ter Hallen 810 Schinveld Limburg 6451 CE",
    "addr:housenumber":"810",
    "addr:postcode":"6451 ce",
    "addr:street":"Ter Hallen",
    "iso:country":"NL",
    "sg:address":"Ter Hallen 810",
    "sg:city":"Schinveld",
    "sg:orig_category":"Zalenverhuur",
    "sg:phone":"+31 45 525 7455",
    "sg:postcode":"6451 CE",
    "sg:province":"Limburg",
    "wof:name":"Fa-Si-La",
    "wof:placetype":"venue"
},
  "geometry": {"coordinates":[5.97638,50.970638],"type":"Point"}
}