{
  "type": "Feature",
  "properties": {
    "iso:country":"NL",
    "sg:address":"Radiowg 5",
    "sg:city":"Almere",
    "sg:orig_category":"Muziekinstrumenten En Bladmuziek",
    "sg:phone":"+31 36 546 0030",
    "sg:postcode":"1324 KW",
    "sg:province":"NL.",
    "sg:website":"http://www.nederlandmuziek.com",
    "wof:name":"Nederland Muziek Bv",
    "wof:placetype":"venue"
},
  "geometry": {"coordinates":[5.1996,52.356159],"type":"Point"}
}