{
  "type": "Feature",
  "properties": {
    "addr:full":"Andesdreef 59 Utrecht Utrecht 3563 GB",
    "addr:housenumber":"59",
    "addr:postcode":"3563 gb",
    "addr:street":"Andesdreef",
    "iso:country":"NL",
    "sg:address":"Andesdreef 59",
    "sg:city":"Utrecht",
    "sg:orig_category":"Postkantoren",
    "sg:phone":"+31 30 261 7714",
    "sg:postcode":"3563 GB",
    "sg:province":"Utrecht",
    "sg:website":"http://www.postkantoor.nl",
    "wof:name":"Postkantoor",
    "wof:placetype":"venue"
},
  "geometry": {"coordinates":[5.099658,52.119137],"type":"Point"}
}