{
  "type": "Feature",
  "properties": {
    "addr:full":"Eisenhowerwg 39 Veghel North Brabant 5466 AB",
    "addr:housenumber":"39",
    "addr:postcode":"5466 ab",
    "addr:street":"Eisenhowerwg",
    "iso:country":"NL",
    "sg:address":"Eisenhowerwg 39",
    "sg:city":"Veghel",
    "sg:orig_category":"Wegbebakening En Beveiliging - Materialen",
    "sg:phone":"+31 413 343 830",
    "sg:postcode":"5466 AB",
    "sg:province":"North Brabant",
    "wof:name":"Linden Bv, Van Der",
    "wof:placetype":"venue"
},
  "geometry": {"coordinates":[5.5103049278,51.6113471985],"type":"Point"}
}