{
  "type": "Feature",
  "properties": {
    "addr:full":"Hei En Boeic Wg 24 Hei En Boeicop South Holland 4126 RJ",
    "addr:housenumber":"24",
    "addr:postcode":"4126 rj",
    "addr:street":"Hei En;Wg",
    "iso:country":"NL",
    "sg:address":"Hei En Boeic Wg 24",
    "sg:city":"Hei En Boeicop",
    "sg:orig_category":"Adviesbureaus Bouwkunde",
    "sg:phone":"+31 345 642 326",
    "sg:postcode":"4126 RJ",
    "sg:province":"South Holland",
    "wof:name":"Poly Bv",
    "wof:placetype":"venue"
},
  "geometry": {"coordinates":[5.0893,51.943245],"type":"Point"}
}