{
  "type": "Feature",
  "properties": {
    "iso:country":"NL",
    "sg:address":"Fokkerstr 477",
    "sg:city":"Schiedam",
    "sg:orig_category":"Autoschade- Herstelbedrijven",
    "sg:phone":"+31 10 437 1944",
    "sg:postcode":"3125 BD",
    "sg:province":"Zuid-Holland",
    "wof:name":"Beers, R Van",
    "wof:placetype":"venue"
},
  "geometry": {"coordinates":[4.396532,51.935368],"type":"Point"}
}