{
  "type": "Feature",
  "properties": {
    "iso:country":"NL",
    "sg:address":"Klapperdijk 27",
    "sg:city":"Wapenveld",
    "sg:orig_category":"Boekhandels",
    "sg:phone":"+31 38 447 9870",
    "sg:postcode":"8191 AC",
    "sg:province":"Gelderland",
    "wof:name":"Shalom",
    "wof:placetype":"venue"
},
  "geometry": {"coordinates":[6.073883,52.431946],"type":"Point"}
}