{
  "type": "Feature",
  "properties": {
    "iso:country":"NL",
    "sg:address":"V Wulfenln 8B",
    "sg:city":"Laren Nh",
    "sg:orig_category":"Onroerende Goederen",
    "sg:phone":"+31 35 531 1252",
    "sg:postcode":"1251 CW",
    "sg:province":"Noord-Holland",
    "wof:name":"Eem Bv, De",
    "wof:placetype":"venue"
},
  "geometry": {"coordinates":[5.22387,52.256741],"type":"Point"}
}