{
  "type": "Feature",
  "properties": {
    "addr:full":"Hoogveldseweg 49 Mill Pennsylvania 5451 AA",
    "addr:housenumber":"49",
    "addr:postcode":"5451 aa",
    "addr:street":"Hoogveldseweg",
    "iso:country":"NL",
    "sg:address":"Hoogveldseweg 49",
    "sg:city":"Mill",
    "sg:orig_category":"Kappers",
    "sg:phone":"+31 485 470 773",
    "sg:postcode":"5451 AA",
    "sg:province":"Pennsylvania",
    "wof:name":"Corien",
    "wof:placetype":"venue"
},
  "geometry": {"coordinates":[-77.6870803833,41.9462623596],"type":"Point"}
}