{
  "type": "Feature",
  "properties": {
    "addr:full":"Roerstraat 1 Amsterdam North Holland 1078 LH",
    "addr:housenumber":"1",
    "addr:postcode":"1078 lh",
    "addr:street":"Roerstraat",
    "iso:country":"NL",
    "sg:address":"Roerstraat 1",
    "sg:city":"Amsterdam",
    "sg:orig_category":"Verhuur Medische Uitrustingen",
    "sg:phone":"+31 20 671 4288",
    "sg:postcode":"1078 LH",
    "sg:province":"North Holland",
    "wof:name":"Thuiszorg Ntn",
    "wof:placetype":"venue"
},
  "geometry": {"coordinates":[4.900026,52.344952],"type":"Point"}
}