{
  "type": "Feature",
  "properties": {
    "addr:full":"V Bonninghausenln 56 Lisse Zuid-Holland 2161 ET",
    "addr:housenumber":"56",
    "addr:postcode":"2161 et",
    "iso:country":"NL",
    "sg:address":"V Bonninghausenln 56",
    "sg:city":"Lisse",
    "sg:orig_category":"Antiquiteiten",
    "sg:phone":"+31 252 420 394",
    "sg:postcode":"2161 ET",
    "sg:province":"Zuid-Holland",
    "wof:name":"Harlequin",
    "wof:placetype":"venue"
},
  "geometry": {"coordinates":[4.551899,52.263752],"type":"Point"}
}