{
  "type": "Feature",
  "properties": {
    "addr:full":"Kloosterstr 8 Simpelveld Limburg 6369 AD",
    "addr:housenumber":"8",
    "addr:postcode":"6369 ad",
    "addr:street":"Kloosterstr",
    "iso:country":"NL",
    "sg:address":"Kloosterstr 8",
    "sg:city":"Simpelveld",
    "sg:orig_category":"Fietsen En Bromfietsen",
    "sg:phone":"+31 45 544 1276",
    "sg:postcode":"6369 AD",
    "sg:province":"Limburg",
    "wof:name":"Janssen Fietsen En Bromfietsen",
    "wof:placetype":"venue"
},
  "geometry": {"coordinates":[5.983138,50.834148],"type":"Point"}
}