{
  "type": "Feature",
  "properties": {
    "addr:full":"Kleiwg 19B Rotterdam Zuid-Holland 3051 GH",
    "addr:housenumber":"19b",
    "addr:postcode":"3051 gh",
    "addr:street":"Kleiwg",
    "iso:country":"NL",
    "sg:address":"Kleiwg 19B",
    "sg:city":"Rotterdam",
    "sg:classifiers":[
        {
            "category":"Food & Beverages",
            "subcategory":"Bakery",
            "type":"Retail Goods"
        }
    ],
    "sg:phone":"+31 10 422 7855",
    "sg:postcode":"3051 GH",
    "sg:province":"Zuid-Holland",
    "sg:tags":[
        "pizza"
    ],
    "wof:name":"Bel-Pizza",
    "wof:placetype":"venue"
},
  "geometry": {"coordinates":[4.482136,51.945076],"type":"Point"}
}