{
  "type": "Feature",
  "properties": {
    "addr:full":"Stationsstraat 42 Ermelo Gelderland 3851 NJ",
    "addr:housenumber":"42",
    "addr:postcode":"3851",
    "addr:street":"Stationsstraat;Gelderland",
    "iso:country":"NL",
    "sg:address":"Stationsstraat 42",
    "sg:city":"Ermelo",
    "sg:classifiers":[
        {
            "category":"Communications",
            "subcategory":"Television Station",
            "type":"Services"
        }
    ],
    "sg:phone":"+31 341 554 300",
    "sg:postcode":"3851 NJ",
    "sg:province":"Gelderland",
    "sg:tags":[
        "video",
        "audio",
        "verhuur"
    ],
    "wof:name":"Videoland - Ermelo",
    "wof:placetype":"venue"
},
  "geometry": {"coordinates":[5.625494,52.300514],"type":"Point"}
}