{
  "type": "Feature",
  "properties": {
    "addr:full":"Boekweitstr 23 Dedemsvaart NL.08 7701 VT",
    "addr:housenumber":"23;nl.08",
    "addr:postcode":"7701",
    "addr:street":"Boekweitstr",
    "iso:country":"NL",
    "sg:address":"Boekweitstr 23",
    "sg:city":"Dedemsvaart",
    "sg:orig_category":"Beveiliging",
    "sg:phone":"+31 523 613 459",
    "sg:postcode":"7701 VT",
    "sg:province":"NL.08",
    "sg:website":"http://www.henry-meerman.nl",
    "wof:name":"Henry Meerman",
    "wof:placetype":"venue"
},
  "geometry": {"coordinates":[6.45003,52.597923],"type":"Point"}
}