{
  "type": "Feature",
  "properties": {
    "iso:country":"NL",
    "sg:address":"Sluiswg 14",
    "sg:city":"St Philipsland",
    "sg:orig_category":"Duikers",
    "sg:phone":"+31 167 573 235",
    "sg:postcode":"4675 RS",
    "sg:province":"Zeeland",
    "wof:name":"Seekles, A K",
    "wof:placetype":"venue"
},
  "geometry": {"coordinates":[4.114745,51.649719],"type":"Point"}
}