{
  "type": "Feature",
  "properties": {
    "addr:full":"Dorpsstr 47 Streefkerk Zuid-Holland 2959 AH",
    "addr:housenumber":"47",
    "addr:postcode":"2959 ah",
    "addr:street":"Dorpsstr",
    "iso:country":"NL",
    "sg:address":"Dorpsstr 47",
    "sg:city":"Streefkerk",
    "sg:orig_category":"Artsen - Huisartsen",
    "sg:phone":"+31 184 681 480",
    "sg:postcode":"2959 AH",
    "sg:province":"Zuid-Holland",
    "wof:name":"Bruijn",
    "wof:placetype":"venue"
},
  "geometry": {"coordinates":[4.739486,51.901062],"type":"Point"}
}