{
  "type": "Feature",
  "properties": {
    "addr:full":"Postbus 492 Rotterdam 3000 AL",
    "addr:housenumber":"492",
    "addr:postcode":"3000 al",
    "addr:street":"Postbus",
    "iso:country":"NL",
    "sg:address":"Postbus 492",
    "sg:city":"Rotterdam",
    "sg:orig_category":"Webdesign Bureaus",
    "sg:phone":"+31 10 484 5452",
    "sg:postcode":"3000 AL",
    "sg:website":"http://www.rightprice.nl",
    "wof:name":"Rightprice",
    "wof:placetype":"venue"
},
  "geometry": {"coordinates":[4.470749855,51.922618866],"type":"Point"}
}