{
  "type": "Feature",
  "properties": {
    "addr:full":"Kennemerstraatweg 143 Heiloo Noord-Holland 1851 BD",
    "addr:housenumber":"143",
    "addr:postcode":"1851 bd",
    "addr:street":"Kennemerstraatweg",
    "iso:country":"NL",
    "sg:address":"Kennemerstraatweg 143",
    "sg:city":"Heiloo",
    "sg:orig_category":"Banken And Kredietinstellingen",
    "sg:phone":"+31 251 662 500",
    "sg:postcode":"1851 BD",
    "sg:province":"Noord-Holland",
    "wof:name":"Rabo West Kennemerland",
    "wof:placetype":"venue"
},
  "geometry": {"coordinates":[4.711974,52.60191],"type":"Point"}
}