{
  "type": "Feature",
  "properties": {
    "iso:country":"NL",
    "sg:address":"Pastoor Van Rossumstraat 23",
    "sg:city":"Hengelo Ov",
    "sg:orig_category":"Film-, Tv- And Videoproductie",
    "sg:phone":"+31 74 243 5741",
    "sg:postcode":"7553 VN",
    "sg:province":"Overijssel",
    "wof:name":"E. Kieft",
    "wof:placetype":"venue"
},
  "geometry": {"coordinates":[6.78971,52.266331],"type":"Point"}
}