{
  "type": "Feature",
  "properties": {
    "addr:full":"L Nering 9 Emmeloord Flevoland 8302 EH",
    "addr:housenumber":"9",
    "addr:postcode":"8302 eh",
    "addr:street":"Nering;Flevoland",
    "iso:country":"NL",
    "sg:address":"L Nering 9",
    "sg:city":"Emmeloord",
    "sg:orig_category":"Opticiens",
    "sg:phone":"+31 527 612 331",
    "sg:postcode":"8302 EH",
    "sg:province":"Flevoland",
    "wof:name":"Huis Van Hooff, Het",
    "wof:placetype":"venue"
},
  "geometry": {"coordinates":[5.7543039322,52.7113075256],"type":"Point"}
}