{
  "type": "Feature",
  "properties": {
    "iso:country":"NL",
    "sg:address":"Kerkstr 104",
    "sg:city":"Putten",
    "sg:orig_category":"Verf En Lak",
    "sg:phone":"+31 33 461 1466",
    "sg:postcode":"3882 BV",
    "sg:province":"Gelderland",
    "wof:name":"Avu Profiel",
    "wof:placetype":"venue"
},
  "geometry": {"coordinates":[5.606368,52.255035],"type":"Point"}
}