{
  "type": "Feature",
  "properties": {
    "addr:full":"Seringenlaan 46 Sint Michielsgestel Noord-Brabant 5271 JD",
    "addr:housenumber":"46",
    "addr:postcode":"5271 jd",
    "addr:street":"Seringenlaan;Sint Michielsgestel",
    "iso:country":"NL",
    "sg:address":"Seringenlaan 46",
    "sg:city":"Sint Michielsgestel",
    "sg:orig_category":"Goederenvervoer Over De Weg",
    "sg:phone":"+31 73 551 5617",
    "sg:postcode":"5271 JD",
    "sg:province":"Noord-Brabant",
    "wof:name":"Schellings International Bv",
    "wof:placetype":"venue"
},
  "geometry": {"coordinates":[5.339675,51.638832],"type":"Point"}
}