{
  "type": "Feature",
  "properties": {
    "addr:full":"N Keyserstr 2 Sleeuwyk Noord-Brabant 4254 EP",
    "addr:housenumber":"2",
    "addr:postcode":"4254 ep",
    "addr:street":"N Keyserstr",
    "iso:country":"NL",
    "sg:address":"N Keyserstr 2",
    "sg:city":"Sleeuwyk",
    "sg:orig_category":"Kinderopvang",
    "sg:phone":"+31 183 304 808",
    "sg:postcode":"4254 EP",
    "sg:province":"Noord-Brabant",
    "wof:name":"Nijntje",
    "wof:placetype":"venue"
},
  "geometry": {"coordinates":[4.950798,51.813931],"type":"Point"}
}