{
  "type": "Feature",
  "properties": {
    "addr:full":"Heikantsestr 14 Prinsenbeek North Brabant 4841 EH",
    "addr:housenumber":"14",
    "addr:postcode":"4841 eh",
    "addr:street":"Heikantsestr",
    "iso:country":"NL",
    "sg:address":"Heikantsestr 14",
    "sg:city":"Prinsenbeek",
    "sg:orig_category":"Makelaars En Adviseurs Onroerende Goederen",
    "sg:phone":"+31 76 549 6515",
    "sg:postcode":"4841 EH",
    "sg:province":"North Brabant",
    "wof:name":"Veld, Anneke In 'T",
    "wof:placetype":"venue"
},
  "geometry": {"coordinates":[4.710319,51.602703],"type":"Point"}
}