{
  "type": "Feature",
  "properties": {
    "addr:full":"Paardebloem 11 Deurne Noord-Brabant 5754 SE",
    "addr:housenumber":"11",
    "addr:postcode":"5754 se",
    "addr:street":"Paardebloem",
    "iso:country":"NL",
    "sg:address":"Paardebloem 11",
    "sg:city":"Deurne",
    "sg:orig_category":"Grafisch Ontwerpers",
    "sg:phone":"+31 493 313 173",
    "sg:postcode":"5754 SE",
    "sg:province":"Noord-Brabant",
    "wof:name":"Inez Swinkels",
    "wof:placetype":"venue"
},
  "geometry": {"coordinates":[5.812597,51.469353],"type":"Point"}
}