{
  "type": "Feature",
  "properties": {
    "addr:full":"Planthofswg 49 Almelo NL.08 7601 PH",
    "addr:housenumber":"49;nl.08",
    "addr:postcode":"7601",
    "addr:street":"Planthofswg",
    "iso:country":"NL",
    "sg:address":"Planthofswg 49",
    "sg:city":"Almelo",
    "sg:classifiers":[
        {
            "category":"Retail",
            "subcategory":"Auto Repair",
            "type":"Services"
        }
    ],
    "sg:phone":"+31 546 569 336",
    "sg:postcode":"7601 PH",
    "sg:province":"NL.08",
    "sg:tags":[
        "garage"
    ],
    "wof:name":"Wevers",
    "wof:placetype":"venue"
},
  "geometry": {"coordinates":[6.684579,52.340118],"type":"Point"}
}