{
  "type": "Feature",
  "properties": {
    "iso:country":"NL",
    "sg:address":"Wiltzanghln 60",
    "sg:city":"Amsterdam",
    "sg:orig_category":"Fotografie Reclame En Mode",
    "sg:phone":"+31 20 684 2771",
    "sg:postcode":"1061 HC",
    "sg:province":"North Holland",
    "wof:name":"Jansen, Wouter",
    "wof:placetype":"venue"
},
  "geometry": {"coordinates":[4.843173,52.381844],"type":"Point"}
}