{
  "type": "Feature",
  "properties": {
    "addr:full":"Schelsberg 132 Heerlen Limburg 6413 AG",
    "addr:housenumber":"132",
    "addr:postcode":"6413",
    "addr:street":"Schelsberg",
    "iso:country":"NL",
    "sg:address":"Schelsberg 132",
    "sg:city":"Heerlen",
    "sg:orig_category":"Verzekeringen - Verzekeringskantoren",
    "sg:phone":"+31 45 572 1866",
    "sg:postcode":"6413 AG",
    "sg:province":"Limburg",
    "sg:website":"http://www.jacstel.nl",
    "wof:name":"Stel & Zonen, Jac",
    "wof:placetype":"venue"
},
  "geometry": {"coordinates":[5.966932,50.906178],"type":"Point"}
}