{
  "type": "Feature",
  "properties": {
    "addr:full":"Hoogkarspelstr 145 S Gravenhage South Holland 2547 LM",
    "addr:housenumber":"145",
    "addr:postcode":"2547 lm",
    "addr:street":"S Gravenhage",
    "iso:country":"NL",
    "sg:address":"Hoogkarspelstr 145",
    "sg:city":"S Gravenhage",
    "sg:orig_category":"Leesportefeuilles",
    "sg:phone":"+31 70 323 5664",
    "sg:postcode":"2547 LM",
    "sg:province":"South Holland",
    "wof:name":"Leesland",
    "wof:placetype":"venue"
},
  "geometry": {"coordinates":[4.26694,52.061771],"type":"Point"}
}