{
  "type": "Feature",
  "properties": {
    "addr:full":"Weteringstraat 4 Wamel Gelderland 6659 KM",
    "addr:housenumber":"4",
    "addr:postcode":"6659",
    "addr:street":"Weteringstraat;Gelderland;Km",
    "iso:country":"NL",
    "sg:address":"Weteringstraat 4",
    "sg:city":"Wamel",
    "sg:orig_category":"Hoefdierhouderijen",
    "sg:phone":"+31 487 562 100",
    "sg:postcode":"6659 KM",
    "sg:province":"Gelderland",
    "wof:name":"Africhtings-En Opl. Centrum De Dalhoeve Bv",
    "wof:placetype":"venue"
},
  "geometry": {"coordinates":[5.493841,51.859566],"type":"Point"}
}