{
  "type": "Feature",
  "properties": {
    "addr:full":"Binnenwegpln 23 Rotterdam Zuid-Holland 3012 KA",
    "addr:housenumber":"23",
    "addr:postcode":"3012 ka",
    "addr:street":"Binnenwegpln",
    "iso:country":"NL",
    "sg:address":"Binnenwegpln 23",
    "sg:city":"Rotterdam",
    "sg:orig_category":"Opticiens",
    "sg:phone":"+31 10 414 9436",
    "sg:postcode":"3012 KA",
    "sg:province":"Zuid-Holland",
    "wof:name":"Pearle",
    "wof:placetype":"venue"
},
  "geometry": {"coordinates":[4.4772639275,51.9181938171],"type":"Point"}
}