{
  "type": "Feature",
  "properties": {
    "addr:full":"Hoenderstr 6 Beers Nb North Brabant 5437 AC",
    "addr:housenumber":"6",
    "addr:postcode":"5437 ac",
    "addr:street":"Hoenderstr",
    "iso:country":"NL",
    "sg:address":"Hoenderstr 6",
    "sg:city":"Beers Nb",
    "sg:orig_category":"Vertaalbureaus",
    "sg:phone":"+31 485 315 993",
    "sg:postcode":"5437 AC",
    "sg:province":"North Brabant",
    "wof:name":"Ostrea Holland",
    "wof:placetype":"venue"
},
  "geometry": {"coordinates":[5.841711,51.727028],"type":"Point"}
}