{
  "type": "Feature",
  "properties": {
    "iso:country":"NL",
    "sg:address":"Vd Spiegelstr 56",
    "sg:city":"Goes",
    "sg:orig_category":"Kunstgebitten",
    "sg:phone":"+31 113 231 220",
    "sg:postcode":"4461 LN",
    "sg:province":"Ohio",
    "wof:name":"Dental Goes Bv",
    "wof:placetype":"venue"
},
  "geometry": {"coordinates":[-83.914169,39.768833],"type":"Point"}
}