{
  "type": "Feature",
  "properties": {
    "addr:full":"Duistervoordseweg 64 Twello Gelderland 7391 CG",
    "addr:housenumber":"64",
    "addr:postcode":"7391 cg",
    "addr:street":"Duistervoordseweg;Gelderland",
    "iso:country":"NL",
    "sg:address":"Duistervoordseweg 64",
    "sg:city":"Twello",
    "sg:orig_category":"Wasserettes And Stomerijen",
    "sg:phone":"+31 571 274 309",
    "sg:postcode":"7391 CG",
    "sg:province":"Gelderland",
    "wof:name":"Stomerij Van Ingen",
    "wof:placetype":"venue"
},
  "geometry": {"coordinates":[6.0985498428,52.2353935242],"type":"Point"}
}