{
  "type": "Feature",
  "properties": {
    "addr:full":"Hoofdstr 126 Krimpen Aan De Lek Zuid-Holland 2931 CL",
    "addr:housenumber":"126",
    "addr:postcode":"lek;2931",
    "iso:country":"NL",
    "sg:address":"Hoofdstr 126",
    "sg:city":"Krimpen Aan De Lek",
    "sg:orig_category":"Sanitaire Artikelen",
    "sg:phone":"+31 180 522 327",
    "sg:postcode":"2931 CL",
    "sg:province":"Zuid-Holland",
    "wof:name":"Kaldewei Bv",
    "wof:placetype":"venue"
},
  "geometry": {"coordinates":[4.632331,51.897827],"type":"Point"}
}