{
  "type": "Feature",
  "properties": {
    "addr:full":"Europawg 891 Maasvlakte Rt Zuid-Holland 3199 LD",
    "addr:housenumber":"891;rt",
    "addr:postcode":"3199 ld",
    "addr:street":"Maasvlakte",
    "iso:country":"NL",
    "sg:address":"Europawg 891",
    "sg:city":"Maasvlakte Rt",
    "sg:orig_category":"Milieu",
    "sg:phone":"+31 181 371 010",
    "sg:postcode":"3199 LD",
    "sg:province":"Zuid-Holland",
    "wof:name":"Biomass Nederland Bv",
    "wof:placetype":"venue"
},
  "geometry": {"coordinates":[4.013516,51.97049],"type":"Point"}
}