{
  "type": "Feature",
  "properties": {
    "addr:full":"Uiterwaardenstr 249-1Hoog Amsterdam Noord-Holland 1079 CP",
    "addr:housenumber":"249-1hoog",
    "addr:postcode":"1079 cp",
    "iso:country":"NL",
    "sg:address":"Uiterwaardenstr 249-1Hoog",
    "sg:city":"Amsterdam",
    "sg:orig_category":"Beeldende Kunstenaars",
    "sg:phone":"+31 20 644 8779",
    "sg:postcode":"1079 CP",
    "sg:province":"Noord-Holland",
    "wof:name":"Groningen, P F G Van",
    "wof:placetype":"venue"
},
  "geometry": {"coordinates":[4.896673,52.342007],"type":"Point"}
}