{
  "type": "Feature",
  "properties": {
    "addr:full":"J W Frisostr 9 St Annaparochie Friesland 9076 DB",
    "addr:housenumber":"9",
    "addr:postcode":"9076 db",
    "addr:street":"St",
    "iso:country":"NL",
    "sg:address":"J W Frisostr 9",
    "sg:city":"St Annaparochie",
    "sg:orig_category":"Onroerende Goederen",
    "sg:phone":"+31 518 401 477",
    "sg:postcode":"9076 DB",
    "sg:province":"Friesland",
    "wof:name":"Dijk Cv, Van",
    "wof:placetype":"venue"
},
  "geometry": {"coordinates":[5.662178,53.273819],"type":"Point"}
}