{
  "type": "Feature",
  "properties": {
    "iso:country":"NL",
    "sg:address":"Kerkeln 13",
    "sg:city":"Bergen Nh",
    "sg:orig_category":"Verzekeringen - Verzekeringskantoren",
    "sg:phone":"+31 72 589 8540",
    "sg:postcode":"1861 EA",
    "sg:province":"Noord-Holland",
    "wof:name":"Aab",
    "wof:placetype":"venue"
},
  "geometry": {"coordinates":[4.701395,52.669979],"type":"Point"}
}