{
  "type": "Feature",
  "properties": {
    "iso:country":"NL",
    "sg:address":"Hassinkweg 1",
    "sg:city":"Hengelo Ov",
    "sg:orig_category":"Meubelreparatie And -Restauratie",
    "sg:phone":"+31 74 242 8519",
    "sg:postcode":"7556 BV",
    "sg:province":"NL.08",
    "wof:name":"Meubelstoffeerderij G. Strijker",
    "wof:placetype":"venue"
},
  "geometry": {"coordinates":[6.775784,52.278885],"type":"Point"}
}