{
  "type": "Feature",
  "properties": {
    "addr:full":"Hassinkweg 1 Hengelo Ov NL.08 7556 BV",
    "addr:housenumber":"1",
    "addr:postcode":"7556 bv",
    "addr:street":"Hassinkweg;Ov",
    "iso:country":"NL",
    "sg:address":"Hassinkweg 1",
    "sg:city":"Hengelo Ov",
    "sg:orig_category":"Meubelreparatie And -Restauratie",
    "sg:phone":"+31 74 242 8519",
    "sg:postcode":"7556 BV",
    "sg:province":"NL.08",
    "wof:name":"Meubelstoffeerderij G. Strijker",
    "wof:placetype":"venue"
},
  "geometry": {"coordinates":[6.775784,52.278885],"type":"Point"}
}