{
  "type": "Feature",
  "properties": {
    "iso:country":"NL",
    "sg:address":"Holtherstraat 5",
    "sg:city":"Bruntinge",
    "sg:orig_category":"Geluidsopnamen",
    "sg:phone":"+31 593 552 248",
    "sg:postcode":"9435 TD",
    "sg:province":"Drenthe",
    "wof:name":"Six-Pack Productions Cv",
    "wof:placetype":"venue"
},
  "geometry": {"coordinates":[6.570469,52.823353],"type":"Point"}
}