{
  "type": "Feature",
  "properties": {
    "addr:full":"Voorterweg 140 Eindhoven Noord-Brabant 5611 TS",
    "addr:housenumber":"140",
    "addr:postcode":"5611 ts",
    "addr:street":"Voorterweg",
    "iso:country":"NL",
    "sg:address":"Voorterweg 140",
    "sg:city":"Eindhoven",
    "sg:orig_category":"Autokeuringen",
    "sg:phone":"+31 40 211 8630",
    "sg:postcode":"5611 TS",
    "sg:province":"Noord-Brabant",
    "wof:name":"Bandenspecialist Gebr. Lafaire",
    "wof:placetype":"venue"
},
  "geometry": {"coordinates":[5.493338,51.4338],"type":"Point"}
}