{
  "type": "Feature",
  "properties": {
    "addr:full":"Werfwg 17 Lelystad Flevoland 8243 PG",
    "addr:housenumber":"17",
    "addr:postcode":"8243",
    "addr:street":"Werfwg;Flevoland;Pg",
    "iso:country":"NL",
    "sg:address":"Werfwg 17",
    "sg:city":"Lelystad",
    "sg:orig_category":"Honden- En Kattentrimsalons",
    "sg:phone":"+31 320 262 325",
    "sg:postcode":"8243 PG",
    "sg:province":"Flevoland",
    "wof:name":"Royce",
    "wof:placetype":"venue"
},
  "geometry": {"coordinates":[5.432823,52.497124],"type":"Point"}
}