{
  "type": "Feature",
  "properties": {
    "addr:full":"Laan Van Nieuw Guinea 94 Utrecht Utrecht 3531 JN",
    "addr:housenumber":"94",
    "addr:postcode":"3531 jn",
    "addr:street":"Laan Van Nieuw Guinea",
    "iso:country":"NL",
    "sg:address":"Laan Van Nieuw Guinea 94",
    "sg:city":"Utrecht",
    "sg:classifiers":[
        {
            "category":"Communications",
            "subcategory":"Television Station",
            "type":"Services"
        }
    ],
    "sg:phone":"+31 30 299 1989",
    "sg:postcode":"3531 JN",
    "sg:province":"Utrecht",
    "sg:tags":[
        "video",
        "audio",
        "verhuur"
    ],
    "wof:name":"Videoland",
    "wof:placetype":"venue"
},
  "geometry": {"coordinates":[5.085586,52.09367],"type":"Point"}
}