{
  "type": "Feature",
  "properties": {
    "addr:full":"Leeuwensteinplein 5 Vught North Brabant 5261 EV",
    "addr:housenumber":"5",
    "addr:postcode":"5261 ev",
    "addr:street":"Leeuwensteinplein",
    "iso:country":"NL",
    "sg:address":"Leeuwensteinplein 5",
    "sg:city":"Vught",
    "sg:orig_category":"Overheidsdiensten",
    "sg:phone":"+31 73 658 0670",
    "sg:postcode":"5261 EV",
    "sg:province":"North Brabant",
    "wof:name":"Gemeentelijke Sociale Dienst",
    "wof:placetype":"venue"
},
  "geometry": {"coordinates":[5.3005480766,51.656047821],"type":"Point"}
}