{
  "type": "Feature",
  "properties": {
    "addr:full":"Laagsewg 87 Hezingen Overijssel 7662 PA",
    "addr:housenumber":"87",
    "addr:postcode":"7662 pa",
    "addr:street":"Laagsewg",
    "iso:country":"NL",
    "sg:address":"Laagsewg 87",
    "sg:city":"Hezingen",
    "sg:orig_category":"Hondenscholen",
    "sg:phone":"+31 541 293 796",
    "sg:postcode":"7662 PA",
    "sg:province":"Overijssel",
    "wof:name":"Laagse Paal, Hondenschool De",
    "wof:placetype":"venue"
},
  "geometry": {"coordinates":[6.927703,52.437687],"type":"Point"}
}