{
  "type": "Feature",
  "properties": {
    "iso:country":"NL",
    "sg:address":"Keizersdijk 89",
    "sg:city":"Raamsdonksveer",
    "sg:orig_category":"Pleziervaartuigen And Reparatie",
    "sg:phone":"+31 162 512 220",
    "sg:postcode":"4941 GD",
    "sg:province":"North Brabant",
    "wof:name":"Scheepswerf De Donge",
    "wof:placetype":"venue"
},
  "geometry": {"coordinates":[4.87172,51.699139],"type":"Point"}
}