{
  "type": "Feature",
  "properties": {
    "addr:full":"Jacob Obrechtstraat 29 Amsterdam Noord-Holland 1071 KG",
    "addr:housenumber":"29",
    "addr:postcode":"1071 kg",
    "addr:street":"Jacob Obrechtstraat",
    "iso:country":"NL",
    "sg:address":"Jacob Obrechtstraat 29",
    "sg:city":"Amsterdam",
    "sg:orig_category":"Public Relationbureaus",
    "sg:phone":"+31 20 676 8214",
    "sg:postcode":"1071 KG",
    "sg:province":"Noord-Holland",
    "wof:name":"Important Promotionele Artikelen",
    "wof:placetype":"venue"
},
  "geometry": {"coordinates":[4.875527,52.355938],"type":"Point"}
}