{
  "type": "Feature",
  "properties": {
    "addr:full":"Mgr Bekkersstr 60 Ledeacker Noord-Brabant 5846 AJ",
    "addr:housenumber":"60",
    "addr:postcode":"5846 aj",
    "addr:street":"Bekkersstr",
    "iso:country":"NL",
    "sg:address":"Mgr Bekkersstr 60",
    "sg:city":"Ledeacker",
    "sg:orig_category":"Onderhoudswerken",
    "sg:phone":"+31 6 53331284",
    "sg:postcode":"5846 AJ",
    "sg:province":"Noord-Brabant",
    "wof:name":"Thijssen",
    "wof:placetype":"venue"
},
  "geometry": {"coordinates":[5.884374,51.640148],"type":"Point"}
}