{
  "type": "Feature",
  "properties": {
    "addr:full":"Staringstraat 37 Nijmegen Gelderland 6521 AH",
    "addr:housenumber":"37",
    "addr:postcode":"6521 ah",
    "addr:street":"Staringstraat;Gelderland",
    "iso:country":"NL",
    "sg:address":"Staringstraat 37",
    "sg:city":"Nijmegen",
    "sg:orig_category":"Artsen And Specialisten",
    "sg:phone":"+31 24 322 0889",
    "sg:postcode":"6521 AH",
    "sg:province":"Gelderland",
    "wof:name":"Drs. M.B. Lathouwers",
    "wof:placetype":"venue"
},
  "geometry": {"coordinates":[5.868901,51.841541],"type":"Point"}
}