{
  "type": "Feature",
  "properties": {
    "iso:country":"NL",
    "sg:address":"Nieuwe Laagzijde 19",
    "sg:city":"Schagen",
    "sg:orig_category":"Verlichting And Huishoudartikelen",
    "sg:phone":"+31 224 297 400",
    "sg:postcode":"1741 GE",
    "sg:province":"North Holland",
    "wof:name":"Giraffe Bv",
    "wof:placetype":"venue"
},
  "geometry": {"coordinates":[4.801061,52.787819],"type":"Point"}
}