{
  "type": "Feature",
  "properties": {
    "addr:full":"Voorstraat 20 Utrecht Utrecht 3512 AN",
    "addr:housenumber":"20",
    "addr:postcode":"3512 an",
    "addr:street":"Voorstraat",
    "iso:country":"NL",
    "sg:address":"Voorstraat 20",
    "sg:city":"Utrecht",
    "sg:orig_category":"Kappers",
    "sg:phone":"+31 30 231 7004",
    "sg:postcode":"3512 AN",
    "sg:province":"Utrecht",
    "wof:name":"Bert Deun Intercoiffeur",
    "wof:placetype":"venue"
},
  "geometry": {"coordinates":[5.119166851,52.0943412781],"type":"Point"}
}