{
  "type": "Feature",
  "properties": {
    "addr:full":"Scheepmaker 6 Wilnis Utrecht 3648 KH",
    "addr:housenumber":"6",
    "addr:postcode":"3648 kh",
    "addr:street":"Scheepmaker",
    "iso:country":"NL",
    "sg:address":"Scheepmaker 6",
    "sg:city":"Wilnis",
    "sg:orig_category":"Begrafenisverzorging",
    "sg:phone":"+31 297 289 084",
    "sg:postcode":"3648 KH",
    "sg:province":"Utrecht",
    "wof:name":"Verbree, C H",
    "wof:placetype":"venue"
},
  "geometry": {"coordinates":[4.889695,52.203541],"type":"Point"}
}