{
  "type": "Feature",
  "properties": {
    "addr:full":"Groenlingweg 3 Apeldoorn Gelderland 7331 EB",
    "addr:housenumber":"3",
    "addr:postcode":"7331 eb",
    "addr:street":"Groenlingweg;Gelderland",
    "iso:country":"NL",
    "sg:address":"Groenlingweg 3",
    "sg:city":"Apeldoorn",
    "sg:orig_category":"Boekhouders",
    "sg:phone":"+31 55 534 4545",
    "sg:postcode":"7331 EB",
    "sg:province":"Gelderland",
    "wof:name":"G & A",
    "wof:placetype":"venue"
},
  "geometry": {"coordinates":[5.969281,52.202587],"type":"Point"}
}