{
  "type": "Feature",
  "properties": {
    "iso:country":"NL",
    "sg:address":"Groenlingweg 3",
    "sg:city":"Apeldoorn",
    "sg:orig_category":"Boekhouders",
    "sg:phone":"+31 55 534 4545",
    "sg:postcode":"7331 EB",
    "sg:province":"Gelderland",
    "wof:name":"G & A",
    "wof:placetype":"venue"
},
  "geometry": {"coordinates":[5.969281,52.202587],"type":"Point"}
}