{
  "type": "Feature",
  "properties": {
    "addr:full":"Noordwg 50 Oostkapelle Zeeland 4356 ED",
    "addr:housenumber":"50",
    "addr:postcode":"4356 ed",
    "addr:street":"Noordwg",
    "iso:country":"NL",
    "sg:address":"Noordwg 50",
    "sg:city":"Oostkapelle",
    "sg:orig_category":"Vakantieverblijven",
    "sg:phone":"+31 118 591 974",
    "sg:postcode":"4356 ED",
    "sg:province":"Zeeland",
    "wof:name":"Weltevreden Groepsacc",
    "wof:placetype":"venue"
},
  "geometry": {"coordinates":[3.565076,51.567627],"type":"Point"}
}