{
  "type": "Feature",
  "properties": {
    "addr:full":"Dorpsstraat 62 Bunschoten Spakenburg Utrecht 3751 ES",
    "addr:housenumber":"62",
    "addr:postcode":"3751 es",
    "addr:street":"Dorpsstraat",
    "iso:country":"NL",
    "sg:address":"Dorpsstraat 62",
    "sg:city":"Bunschoten Spakenburg",
    "sg:orig_category":"Antiekzaken",
    "sg:phone":"+31 33 298 2316",
    "sg:postcode":"3751 ES",
    "sg:province":"Utrecht",
    "wof:name":"De Bourgondische Lelie Vof",
    "wof:placetype":"venue"
},
  "geometry": {"coordinates":[5.373838,52.240833],"type":"Point"}
}