{
  "type": "Feature",
  "properties": {
    "addr:full":"Langewg 64 Middelharnis Zuid-Holland 3241 KA",
    "addr:housenumber":"64",
    "addr:postcode":"3241 ka",
    "addr:street":"Langewg",
    "iso:country":"NL",
    "sg:address":"Langewg 64",
    "sg:city":"Middelharnis",
    "sg:orig_category":"Bloemen En Planten - Groothandel",
    "sg:phone":"+31 187 481 500",
    "sg:postcode":"3241 KA",
    "sg:province":"Zuid-Holland",
    "wof:name":"Bloemen H2",
    "wof:placetype":"venue"
},
  "geometry": {"coordinates":[4.156688,51.757313],"type":"Point"}
}