{
  "type": "Feature",
  "properties": {
    "addr:full":"Kroonstr 27 Etten Leur Noord-Brabant 4879 AV",
    "addr:housenumber":"27",
    "addr:postcode":"4879 av",
    "addr:street":"Kroonstr",
    "iso:country":"NL",
    "sg:address":"Kroonstr 27",
    "sg:city":"Etten Leur",
    "sg:orig_category":"Administratie- En Boekhoudkantoren",
    "sg:phone":"+31 76 501 3796",
    "sg:postcode":"4879 AV",
    "sg:province":"Noord-Brabant",
    "wof:name":"Korn",
    "wof:placetype":"venue"
},
  "geometry": {"coordinates":[4.626173,51.559406],"type":"Point"}
}