{
  "type": "Feature",
  "properties": {
    "addr:full":"Laar 10 Nistelrode North Brabant 5388 HE",
    "addr:housenumber":"10",
    "addr:postcode":"5388 he",
    "addr:street":"Laar",
    "iso:country":"NL",
    "sg:address":"Laar 10",
    "sg:city":"Nistelrode",
    "sg:orig_category":"Meubelzaken, Woning- And Keukeninrichting",
    "sg:phone":"+31 412 611 185",
    "sg:postcode":"5388 HE",
    "sg:province":"North Brabant",
    "wof:name":"Vivante Jacobs",
    "wof:placetype":"venue"
},
  "geometry": {"coordinates":[5.561208,51.703541],"type":"Point"}
}