{
  "type": "Feature",
  "properties": {
    "addr:full":"Rentmeesterstraat 44 Almere Flevoland 1315 JS",
    "addr:housenumber":"44",
    "addr:postcode":"1315 js",
    "addr:street":"Rentmeesterstraat;Flevoland",
    "iso:country":"NL",
    "sg:address":"Rentmeesterstraat 44",
    "sg:city":"Almere",
    "sg:orig_category":"Werving And Selectie Van Vast Personeel",
    "sg:phone":"+31 36 534 3004",
    "sg:postcode":"1315 JS",
    "sg:province":"Flevoland",
    "wof:name":"Nieuwland Personeelsadviseurs",
    "wof:placetype":"venue"
},
  "geometry": {"coordinates":[5.2161960602,52.3735542297],"type":"Point"}
}