{
  "type": "Feature",
  "properties": {
    "addr:full":"De Reulver 120 Enschede Overijssel 7544 RT",
    "addr:housenumber":"120",
    "addr:postcode":"7544 rt",
    "addr:street":"De Reulver",
    "iso:country":"NL",
    "sg:address":"De Reulver 120",
    "sg:city":"Enschede",
    "sg:orig_category":"Fitnesscentra",
    "sg:phone":"+31 53 478 1828",
    "sg:postcode":"7544 RT",
    "sg:province":"Overijssel",
    "sg:website":"http://www.twentehallen.nl",
    "wof:name":"Slender You Enschede",
    "wof:placetype":"venue"
},
  "geometry": {"coordinates":[6.887129,52.191319],"type":"Point"}
}