{
  "type": "Feature",
  "properties": {
    "addr:full":"Kerkhofweg 23 Emst Gelderland 8166 HZ",
    "addr:housenumber":"23",
    "addr:postcode":"8166 hz",
    "addr:street":"Kerkhofweg;Gelderland",
    "iso:country":"NL",
    "sg:address":"Kerkhofweg 23",
    "sg:city":"Emst",
    "sg:orig_category":"Autokeuringen",
    "sg:phone":"+31 578 661 316",
    "sg:postcode":"8166 HZ",
    "sg:province":"Gelderland",
    "wof:name":"Vof Tem",
    "wof:placetype":"venue"
},
  "geometry": {"coordinates":[5.973032,52.320534],"type":"Point"}
}