{
  "type": "Feature",
  "properties": {
    "addr:full":"Lemerbergweg 36 C/D Amsterdam Noord-Holland 1101 AH",
    "addr:housenumber":"36 c;d",
    "addr:postcode":"1101 ah",
    "addr:street":"Lemerbergweg;/",
    "iso:country":"NL",
    "sg:address":"Lemerbergweg 36 C/D",
    "sg:city":"Amsterdam",
    "sg:orig_category":"Werving And Selectie Van Tijdelijk Personeel And Uitzendkantoren",
    "sg:phone":"+31 900 7002619",
    "sg:postcode":"1101 AH",
    "sg:province":"Noord-Holland",
    "wof:name":"Tempo Team",
    "wof:placetype":"venue"
},
  "geometry": {"coordinates":[4.9425601959,52.3071517944],"type":"Point"}
}