{
  "type": "Feature",
  "properties": {
    "iso:country":"NL",
    "sg:address":"Julianaweg 49",
    "sg:city":"Volendam",
    "sg:orig_category":"Banken And Kredietinstellingen",
    "sg:phone":"+31 299 364 115",
    "sg:postcode":"1131 CZ",
    "sg:province":"Noord-Holland",
    "wof:name":"Ing Bank",
    "wof:placetype":"venue"
},
  "geometry": {"coordinates":[15.47527,49.803791],"type":"Point"}
}