{
  "type": "Feature",
  "properties": {
    "addr:full":"Kasteellaan 7 Baarlo Lb Limburg 5991 BK",
    "addr:housenumber":"7",
    "addr:postcode":"lb;5991 bk",
    "addr:street":"Kasteellaan",
    "iso:country":"NL",
    "sg:address":"Kasteellaan 7",
    "sg:city":"Baarlo Lb",
    "sg:orig_category":"Schilderwerk",
    "sg:phone":"+31 77 477 1447",
    "sg:postcode":"5991 BK",
    "sg:province":"Limburg",
    "wof:name":"Schildersbedrijf Janssen",
    "wof:placetype":"venue"
},
  "geometry": {"coordinates":[6.100685,51.327374],"type":"Point"}
}