{
  "type": "Feature",
  "properties": {
    "iso:country":"NL",
    "sg:address":"Dorpsstraat 210",
    "sg:city":"Mierlo",
    "sg:orig_category":"Overheidsdiensten",
    "sg:phone":"+31 492 668 000",
    "sg:postcode":"5731 JL",
    "sg:province":"North Brabant",
    "wof:name":"Gemeente Mierlo",
    "wof:placetype":"venue"
},
  "geometry": {"coordinates":[5.6199121475,51.4435691833],"type":"Point"}
}