{
  "type": "Feature",
  "properties": {
    "addr:full":"E N Twilhaarstr 20 Vriezenveen Overijssel 7671 ME",
    "addr:housenumber":"20",
    "addr:postcode":"7671 me",
    "addr:street":"N Twilhaarstr",
    "iso:country":"NL",
    "sg:address":"E N Twilhaarstr 20",
    "sg:city":"Vriezenveen",
    "sg:orig_category":"Voegwerken",
    "sg:phone":"+31 546 565 766",
    "sg:postcode":"7671 ME",
    "sg:province":"Overijssel",
    "wof:name":"Hofmeijer, B J",
    "wof:placetype":"venue"
},
  "geometry": {"coordinates":[6.60951,52.411388],"type":"Point"}
}