{
  "type": "Feature",
  "properties": {
    "addr:full":"S Esmeyerstr 35 Almere NL. 1318 CA",
    "addr:housenumber":"35",
    "addr:postcode":"1318 ca",
    "addr:street":"Nl.",
    "iso:country":"NL",
    "sg:address":"S Esmeyerstr 35",
    "sg:city":"Almere",
    "sg:orig_category":"Vertaalbureaus",
    "sg:phone":"+31 36 545 2642",
    "sg:postcode":"1318 CA",
    "sg:province":"NL.",
    "wof:name":"Interline",
    "wof:placetype":"venue"
},
  "geometry": {"coordinates":[5.22223,52.376598],"type":"Point"}
}