{
  "type": "Feature",
  "properties": {
    "addr:full":"N V Hichtumstr 134 Hoofddorp Noord-Holland 2135 RZ",
    "addr:housenumber":"134",
    "addr:postcode":"2135 rz",
    "addr:street":"N V Hichtumstr",
    "iso:country":"NL",
    "sg:address":"N V Hichtumstr 134",
    "sg:city":"Hoofddorp",
    "sg:orig_category":"Webdesign Bureaus",
    "sg:phone":"+31 23 564 3263",
    "sg:postcode":"2135 RZ",
    "sg:province":"Noord-Holland",
    "wof:name":"Akon",
    "wof:placetype":"venue"
},
  "geometry": {"coordinates":[4.6606798172,52.2973098755],"type":"Point"}
}