{
  "type": "Feature",
  "properties": {
    "iso:country":"NL",
    "sg:address":"Twijnstraat 5",
    "sg:city":"Hengelo Ov",
    "sg:orig_category":"Kappers",
    "sg:phone":"+31 74 291 6358",
    "sg:postcode":"7553 BS",
    "sg:province":"NL.08",
    "wof:name":"Menno V/D Meulen",
    "wof:placetype":"venue"
},
  "geometry": {"coordinates":[6.779662,52.257282],"type":"Point"}
}