{
  "type": "Feature",
  "properties": {
    "addr:full":"Schoolstr 5 Venray Limburg 5801 BN",
    "addr:housenumber":"5",
    "addr:postcode":"5801 bn",
    "addr:street":"Schoolstr",
    "iso:country":"NL",
    "sg:address":"Schoolstr 5",
    "sg:city":"Venray",
    "sg:orig_category":"Fotozaken",
    "sg:phone":"+31 478 512 567",
    "sg:postcode":"5801 BN",
    "sg:province":"Limburg",
    "wof:name":"Chris, 1 Uur Foto'S",
    "wof:placetype":"venue"
},
  "geometry": {"coordinates":[5.974391,51.526611],"type":"Point"}
}