{
  "type": "Feature",
  "properties": {
    "addr:full":"Kapitein Grantstraat 8 Emmen Drenthe 7821 AR",
    "addr:housenumber":"8",
    "addr:postcode":"7821",
    "addr:street":"Kapitein Grantstraat",
    "iso:country":"NL",
    "sg:address":"Kapitein Grantstraat 8",
    "sg:city":"Emmen",
    "sg:classifiers":[
        {
            "category":"Parking",
            "subcategory":"Lot",
            "type":"Transportation"
        }
    ],
    "sg:phone":"+31 591 614 888",
    "sg:postcode":"7821 AR",
    "sg:province":"Drenthe",
    "sg:tags":[
        "fab",
        "metalen",
        "tank"
    ],
    "wof:name":"Holvrieka Ido Bv",
    "wof:placetype":"venue"
},
  "geometry": {"coordinates":[6.91506,52.773689],"type":"Point"}
}