{
  "type": "Feature",
  "properties": {
    "addr:full":"Grt Hagen 22Koo7 Rotterdam South Holland 3078 RA",
    "addr:housenumber":"22koo7",
    "addr:postcode":"3078 ra",
    "iso:country":"NL",
    "sg:address":"Grt Hagen 22Koo7",
    "sg:city":"Rotterdam",
    "sg:orig_category":"Verenigingen En Stichtingen",
    "sg:phone":"+31 10 482 7330",
    "sg:postcode":"3078 RA",
    "sg:province":"South Holland",
    "wof:name":"Hv Ijsselmonde",
    "wof:placetype":"venue"
},
  "geometry": {"coordinates":[4.555454,51.887356],"type":"Point"}
}