{
  "type": "Feature",
  "properties": {
    "addr:full":"Dorpsstraat 108 De Wijk \u00c5land 7957 AX",
    "addr:housenumber":"108",
    "addr:postcode":"7957 ax",
    "addr:street":"Dorpsstraat;Aaland",
    "iso:country":"NL",
    "sg:address":"Dorpsstraat 108",
    "sg:city":"De Wijk",
    "sg:orig_category":"Levende Dieren Gh",
    "sg:phone":"+31 522 442 457",
    "sg:postcode":"7957 AX",
    "sg:province":"\u00c5land",
    "wof:name":"Veehandel Js Van Lunzen",
    "wof:placetype":"venue"
},
  "geometry": {"coordinates":[20.217291,60.19825],"type":"Point"}
}