{
  "type": "Feature",
  "properties": {
    "addr:full":"Past Vd Boomstr 64 Berlicum Nb Noord-Brabant 5258 GE",
    "addr:housenumber":"64",
    "addr:postcode":"5258",
    "addr:street":"Past",
    "iso:country":"NL",
    "sg:address":"Past Vd Boomstr 64",
    "sg:city":"Berlicum Nb",
    "sg:orig_category":"Begrafenisverzorging",
    "sg:phone":"+31 73 503 1518",
    "sg:postcode":"5258 GE",
    "sg:province":"Noord-Brabant",
    "wof:name":"Bijnen, Leo",
    "wof:placetype":"venue"
},
  "geometry": {"coordinates":[5.418169,51.663883],"type":"Point"}
}