{
  "type": "Feature",
  "properties": {
    "addr:full":"Nicolaas Van Der Laanstr 30 Haarlem Noord-Holland 2013 BM",
    "addr:housenumber":"30",
    "addr:postcode":"2013 bm",
    "addr:street":"Nicolaas Van Der Laanstr",
    "iso:country":"NL",
    "sg:address":"Nicolaas Van Der Laanstr 30",
    "sg:city":"Haarlem",
    "sg:classifiers":[
        {
            "category":"Professional",
            "subcategory":"Accounting & Tax Preparation",
            "type":"Services"
        }
    ],
    "sg:phone":"+31 23 532 5599",
    "sg:postcode":"2013 BM",
    "sg:province":"Noord-Holland",
    "sg:tags":[
        "accountant"
    ],
    "wof:name":"Assurantiekantoor P J Handgraaf",
    "wof:placetype":"venue"
},
  "geometry": {"coordinates":[4.628956,52.386162],"type":"Point"}
}