{
  "type": "Feature",
  "properties": {
    "addr:full":"Vinkeln 22 Wassenaar Zuid-Holland 2245 AJ",
    "addr:housenumber":"22",
    "addr:postcode":"2245 aj",
    "addr:street":"Vinkeln",
    "iso:country":"NL",
    "sg:address":"Vinkeln 22",
    "sg:city":"Wassenaar",
    "sg:orig_category":"Olie - Exploratie",
    "sg:phone":"+31 70 511 1542",
    "sg:postcode":"2245 AJ",
    "sg:province":"Zuid-Holland",
    "wof:name":"Georesult Bv",
    "wof:placetype":"venue"
},
  "geometry": {"coordinates":[4.393863,52.14307],"type":"Point"}
}