{
  "type": "Feature",
  "properties": {
    "iso:country":"NL",
    "sg:address":"Burg Magneestr 7",
    "sg:city":"Horn",
    "sg:orig_category":"Schilders",
    "sg:phone":"+31 475 581 704",
    "sg:postcode":"6085 GD",
    "sg:province":"Limburg",
    "wof:name":"Graef, A & O",
    "wof:placetype":"venue"
},
  "geometry": {"coordinates":[-103.439728,42.765663],"type":"Point"}
}