{
  "type": "Feature",
  "properties": {
    "addr:full":"Dorp 114B Benschop Utrecht 3405 BG",
    "addr:housenumber":"114b",
    "addr:postcode":"3405",
    "addr:street":"Dorp",
    "iso:country":"NL",
    "sg:address":"Dorp 114B",
    "sg:city":"Benschop",
    "sg:classifiers":[
        {
            "category":"Professional",
            "subcategory":"Accounting & Tax Preparation",
            "type":"Services"
        }
    ],
    "sg:phone":"+31 348 451 650",
    "sg:postcode":"3405 BG",
    "sg:province":"Utrecht",
    "sg:tags":[
        "accountant",
        "en",
        "-kantoren",
        "register-"
    ],
    "wof:name":"Knol & Nederend",
    "wof:placetype":"venue"
},
  "geometry": {"coordinates":[5.000245,52.010544],"type":"Point"}
}