{
  "type": "Feature",
  "properties": {
    "addr:full":"Floraparkstraat 97 Enschede Overijssel 7531 XG",
    "addr:housenumber":"97",
    "addr:postcode":"7531 xg",
    "addr:street":"Floraparkstraat",
    "iso:country":"NL",
    "sg:address":"Floraparkstraat 97",
    "sg:city":"Enschede",
    "sg:orig_category":"Kappers",
    "sg:phone":"+31 53 431 2600",
    "sg:postcode":"7531 XG",
    "sg:province":"Overijssel",
    "wof:name":"Kapsalon Ida",
    "wof:placetype":"venue"
},
  "geometry": {"coordinates":[6.9132962227,52.2300338745],"type":"Point"}
}