{
  "type": "Feature",
  "properties": {
    "addr:full":"Buitendreef 6 Hoogerheide North Brabant 4631 SV",
    "addr:housenumber":"6",
    "addr:postcode":"4631 sv",
    "addr:street":"Buitendreef",
    "iso:country":"NL",
    "sg:address":"Buitendreef 6",
    "sg:city":"Hoogerheide",
    "sg:orig_category":"Koel- En Vrieshuizen",
    "sg:phone":"+31 164 613 642",
    "sg:postcode":"4631 SV",
    "sg:province":"North Brabant",
    "wof:name":"Schuurbiers Bv",
    "wof:placetype":"venue"
},
  "geometry": {"coordinates":[4.348178,51.425419],"type":"Point"}
}