{
  "type": "Feature",
  "properties": {
    "iso:country":"NL",
    "sg:address":"Dorpsstr 107",
    "sg:city":"Assendelft",
    "sg:orig_category":"Schilders",
    "sg:phone":"+31 75 687 7728",
    "sg:postcode":"1566 AD",
    "sg:province":"Noord-Holland",
    "wof:name":"Bommerson Schildersbedrijf, B",
    "wof:placetype":"venue"
},
  "geometry": {"coordinates":[4.722609,52.448071],"type":"Point"}
}