{
  "type": "Feature",
  "properties": {
    "addr:full":"Wilhelminastraat 17 Beesd Gelderland 4153 BA",
    "addr:housenumber":"17",
    "addr:postcode":"4153 ba",
    "addr:street":"Wilhelminastraat;Gelderland",
    "iso:country":"NL",
    "sg:address":"Wilhelminastraat 17",
    "sg:city":"Beesd",
    "sg:orig_category":"Drukkerijen And Copyshops",
    "sg:phone":"+31 345 683 874",
    "sg:postcode":"4153 BA",
    "sg:province":"Gelderland",
    "wof:name":"Pellicaan",
    "wof:placetype":"venue"
},
  "geometry": {"coordinates":[5.194288,51.887772],"type":"Point"}
}