{
  "type": "Feature",
  "properties": {
    "addr:full":"Berlagelaan 2 Almelo NL.08 7606 ST",
    "addr:housenumber":"2;nl.08",
    "addr:postcode":"7606",
    "addr:street":"Berlagelaan",
    "iso:country":"NL",
    "sg:address":"Berlagelaan 2",
    "sg:city":"Almelo",
    "sg:orig_category":"Overheidsdiensten",
    "sg:phone":"+31 546 816 409",
    "sg:postcode":"7606 ST",
    "sg:province":"NL.08",
    "wof:name":"Stichting De Klup",
    "wof:placetype":"venue"
},
  "geometry": {"coordinates":[6.645483017,52.3504180908],"type":"Point"}
}