{
  "type": "Feature",
  "properties": {
    "iso:country":"NL",
    "sg:address":"Dorpsstr 5",
    "sg:city":"Zoeterwoude",
    "sg:orig_category":"Fietsen En Bromfietsen",
    "sg:phone":"+31 71 580 2199",
    "sg:postcode":"2381 EK",
    "sg:province":"Zuid-Holland",
    "wof:name":"Grim Sport, De",
    "wof:placetype":"venue"
},
  "geometry": {"coordinates":[4.497101,52.121761],"type":"Point"}
}