{
  "type": "Feature",
  "properties": {
    "addr:full":"Ambachtstr 16 Almelo NL.08 7609 RA",
    "addr:housenumber":"16;nl.08",
    "addr:postcode":"7609 ra",
    "addr:street":"Ambachtstr",
    "iso:country":"NL",
    "sg:address":"Ambachtstr 16",
    "sg:city":"Almelo",
    "sg:orig_category":"Waterbehandeling En Waterzuiverings- Systemen",
    "sg:phone":"+31 546 545 020",
    "sg:postcode":"7609 RA",
    "sg:province":"NL.08",
    "sg:website":"http://www.rwbwaterservices.nl",
    "wof:name":"Rwb",
    "wof:placetype":"venue"
},
  "geometry": {"coordinates":[6.6540179253,52.3329696655],"type":"Point"}
}