{
  "type": "Feature",
  "properties": {
    "addr:full":"Javastr 63 Amsterdam North Holland 1094 HA",
    "addr:housenumber":"63",
    "addr:postcode":"1094 ha",
    "addr:street":"Javastr",
    "iso:country":"NL",
    "sg:address":"Javastr 63",
    "sg:city":"Amsterdam",
    "sg:orig_category":"Juwelen - Groothandel",
    "sg:phone":"+31 20 468 8650",
    "sg:postcode":"1094 HA",
    "sg:province":"North Holland",
    "wof:name":"Topkapi Juwelen",
    "wof:placetype":"venue"
},
  "geometry": {"coordinates":[4.934066,52.363827],"type":"Point"}
}