{
  "type": "Feature",
  "properties": {
    "addr:full":"Waalhaven N.Z. 4 Rotterdam Zuid-Holland 3087 BL",
    "addr:housenumber":"4",
    "addr:postcode":"3087 bl",
    "addr:street":"Waalhaven N.Z.",
    "iso:country":"NL",
    "sg:address":"Waalhaven N.Z. 4",
    "sg:city":"Rotterdam",
    "sg:classifiers":[
        {
            "category":"Retail",
            "subcategory":"Storage",
            "type":"Services"
        }
    ],
    "sg:phone":"+31 10 429 9433",
    "sg:postcode":"3087 BL",
    "sg:province":"Zuid-Holland",
    "sg:tags":[
        "opslag",
        "bewaring"
    ],
    "wof:name":"Rotterdams Havenbedrijf Bv",
    "wof:placetype":"venue"
},
  "geometry": {"coordinates":[4.4607510567,51.8934707642],"type":"Point"}
}