{
  "type": "Feature",
  "properties": {
    "addr:full":"B Ingenhoesln 106 Voorburg South Holland 2273 KT",
    "addr:housenumber":"106",
    "addr:postcode":"2273 kt",
    "iso:country":"NL",
    "sg:address":"B Ingenhoesln 106",
    "sg:city":"Voorburg",
    "sg:classifiers":[
        {
            "category":"Food & Beverages",
            "subcategory":"Bakery",
            "type":"Retail Goods"
        }
    ],
    "sg:phone":"+31 70 300 0900",
    "sg:postcode":"2273 KT",
    "sg:province":"South Holland",
    "sg:tags":[
        "pizza"
    ],
    "wof:name":"Original Pizza Company",
    "wof:placetype":"venue"
},
  "geometry": {"coordinates":[4.35977,52.07848],"type":"Point"}
}