{
  "type": "Feature",
  "properties": {
    "addr:full":"Van Leeuwenhoeksingel 9 Delft Zuid-Holland 2611 AA",
    "addr:housenumber":"9",
    "addr:postcode":"2611 aa",
    "addr:street":"Van Leeuwenhoeksingel",
    "iso:country":"NL",
    "sg:address":"Van Leeuwenhoeksingel 9",
    "sg:city":"Delft",
    "sg:orig_category":"Goederenvervoer Over De Weg",
    "sg:phone":"+31 15 213 5326",
    "sg:postcode":"2611 AA",
    "sg:province":"Zuid-Holland",
    "wof:name":"Van Bokhoven Transport",
    "wof:placetype":"venue"
},
  "geometry": {"coordinates":[4.358059,52.004917],"type":"Point"}
}