{
  "type": "Feature",
  "properties": {
    "addr:full":"Boerhaar 20 Wyhe Overijssel 8131 SW",
    "addr:housenumber":"20;8131",
    "addr:street":"Boerhaar;Overijssel;Sw",
    "iso:country":"NL",
    "sg:address":"Boerhaar 20",
    "sg:city":"Wyhe",
    "sg:orig_category":"Scholen Voor Basisonderwijs",
    "sg:phone":"+31 570 521 235",
    "sg:postcode":"8131 SW",
    "sg:province":"Overijssel",
    "wof:name":"Bongerd Katholiek, De",
    "wof:placetype":"venue"
},
  "geometry": {"coordinates":[6.149926,52.37492],"type":"Point"}
}