{
  "type": "Feature",
  "properties": {
    "addr:full":"Staalstr 17 Haarlem Noord-Holland 2033 XG",
    "addr:housenumber":"17",
    "addr:postcode":"2033 xg",
    "addr:street":"Staalstr",
    "iso:country":"NL",
    "sg:address":"Staalstr 17",
    "sg:city":"Haarlem",
    "sg:orig_category":"Fotoreportages",
    "sg:phone":"+31 23 844 0544",
    "sg:postcode":"2033 XG",
    "sg:province":"Noord-Holland",
    "wof:name":"Aacm",
    "wof:placetype":"venue"
},
  "geometry": {"coordinates":[4.665497,52.379093],"type":"Point"}
}