{
  "type": "Feature",
  "properties": {
    "addr:full":"Noordenveld 27 Roden Provincie Drenthe 9301 LG",
    "addr:housenumber":"27",
    "addr:postcode":"9301 lg",
    "addr:street":"Noordenveld;Provincie Drenthe",
    "iso:country":"NL",
    "sg:address":"Noordenveld 27",
    "sg:city":"Roden",
    "sg:orig_category":"Verzekerings- Maatschappijen",
    "sg:phone":"+31 50 501 8768",
    "sg:postcode":"9301 LG",
    "sg:province":"Provincie Drenthe",
    "wof:name":"Onderlinge Paardenverz Mij Wa",
    "wof:placetype":"venue"
},
  "geometry": {"coordinates":[6.434205,53.139305],"type":"Point"}
}