{
  "type": "Feature",
  "properties": {
    "addr:full":"Strengwg 12 Heemskerk Noord-Holland 1969 MG",
    "addr:housenumber":"12",
    "addr:postcode":"1969 mg",
    "addr:street":"Strengwg",
    "iso:country":"NL",
    "sg:address":"Strengwg 12",
    "sg:city":"Heemskerk",
    "sg:orig_category":"Opslag Inboedels",
    "sg:phone":"+31 251 205 051",
    "sg:postcode":"1969 MG",
    "sg:province":"Noord-Holland",
    "sg:website":"http://www.hartrum.nl",
    "wof:name":"Hartrum",
    "wof:placetype":"venue"
},
  "geometry": {"coordinates":[-45.4513511658,-18.5775203705],"type":"Point"}
}