{
  "type": "Feature",
  "properties": {
    "addr:full":"Europalaan 38 Maastricht Limburg 6226 CR",
    "addr:housenumber":"38",
    "addr:postcode":"6226 cr",
    "addr:street":"Europalaan",
    "iso:country":"NL",
    "sg:address":"Europalaan 38",
    "sg:city":"Maastricht",
    "sg:orig_category":"Bedrijfs- And Managementsconsultants",
    "sg:phone":"+31 43 352 0752",
    "sg:postcode":"6226 CR",
    "sg:province":"Limburg",
    "wof:name":"Bpps Business Planning & Partn Search Bv",
    "wof:placetype":"venue"
},
  "geometry": {"coordinates":[5.722181,50.846409],"type":"Point"}
}