{
  "type": "Feature",
  "properties": {
    "addr:full":"De Kroon 1 Wijk En Aalburg Noord-Brabant 4261 TW",
    "addr:housenumber":"1",
    "addr:postcode":"4261 tw",
    "addr:street":"De Kroon",
    "iso:country":"NL",
    "sg:address":"De Kroon 1",
    "sg:city":"Wijk En Aalburg",
    "sg:orig_category":"Bloemen And Planten Gh",
    "sg:phone":"+31 416 694 147",
    "sg:postcode":"4261 TW",
    "sg:province":"Noord-Brabant",
    "wof:name":"Kwetters & Arendse Vof",
    "wof:placetype":"venue"
},
  "geometry": {"coordinates":[5.128901,51.765396],"type":"Point"}
}