{
  "type": "Feature",
  "properties": {
    "addr:full":"Werkersdijk 5 Rhoon South Holland 3161 BL",
    "addr:housenumber":"5",
    "addr:postcode":"3161 bl",
    "addr:street":"Werkersdijk",
    "iso:country":"NL",
    "sg:address":"Werkersdijk 5",
    "sg:city":"Rhoon",
    "sg:orig_category":"Fotostudio'S And Fotografen",
    "sg:phone":"+31 10 501 1722",
    "sg:postcode":"3161 BL",
    "sg:province":"South Holland",
    "wof:name":"Foto Aad",
    "wof:placetype":"venue"
},
  "geometry": {"coordinates":[4.419564,51.855724],"type":"Point"}
}