{
  "type": "Feature",
  "properties": {
    "addr:full":"Boekhorstlaan 17 Voorhout Zuid-Holland 2215 AX",
    "addr:housenumber":"17",
    "addr:postcode":"2215 ax",
    "addr:street":"Boekhorstlaan",
    "iso:country":"NL",
    "sg:address":"Boekhorstlaan 17",
    "sg:city":"Voorhout",
    "sg:orig_category":"Makelaars In Onroerend Goed",
    "sg:phone":"+31 252 231 496",
    "sg:postcode":"2215 AX",
    "sg:province":"Zuid-Holland",
    "wof:name":"Boekhorst",
    "wof:placetype":"venue"
},
  "geometry": {"coordinates":[4.482921,52.222858],"type":"Point"}
}