{
  "type": "Feature",
  "properties": {
    "iso:country":"NL",
    "sg:address":"Klipper 19",
    "sg:city":"Velserbroek",
    "sg:orig_category":"Bedrijfs- And Managementsconsultants",
    "sg:phone":"+31 23 538 8365",
    "sg:postcode":"1991 MH",
    "sg:province":"North Holland",
    "wof:name":"Toussaint Training En Advies Bv",
    "wof:placetype":"venue"
},
  "geometry": {"coordinates":[4.658735,52.427197],"type":"Point"}
}