{
  "type": "Feature",
  "properties": {
    "addr:full":"Strandwg 25 Hoek Van Holland Zuid-Holland 3151 HV",
    "addr:housenumber":"25",
    "addr:postcode":"3151 hv",
    "addr:street":"Strandwg",
    "iso:country":"NL",
    "sg:address":"Strandwg 25",
    "sg:city":"Hoek Van Holland",
    "sg:orig_category":"Loonbedrijven",
    "sg:phone":"+31 174 310 570",
    "sg:postcode":"3151 HV",
    "sg:province":"Zuid-Holland",
    "wof:name":"Zandfort, 'T",
    "wof:placetype":"venue"
},
  "geometry": {"coordinates":[4.118194,51.982231],"type":"Point"}
}