{
  "type": "Feature",
  "properties": {
    "addr:full":"Purmerenderweg 36 Zuidoostbeemster District of Columbia 1461 DC",
    "addr:housenumber":"36",
    "addr:postcode":"1461",
    "addr:street":"Purmerenderweg",
    "iso:country":"NL",
    "sg:address":"Purmerenderweg 36",
    "sg:city":"Zuidoostbeemster",
    "sg:orig_category":"Bloemen- And Plantenteelt",
    "sg:phone":"+31 299 681 221",
    "sg:postcode":"1461 DC",
    "sg:province":"District of Columbia",
    "wof:name":"Firma A. Bakker En Zoon",
    "wof:placetype":"venue"
},
  "geometry": {"coordinates":[-77.01458700000001,38.8937],"type":"Point"}
}