{
  "type": "Feature",
  "properties": {
    "addr:full":"J Luykenstr 40 Amsterdam North Holland 1071 CR",
    "addr:housenumber":"40",
    "addr:postcode":"1071 cr",
    "iso:country":"NL",
    "sg:address":"J Luykenstr 40",
    "sg:city":"Amsterdam",
    "sg:orig_category":"Kappers",
    "sg:phone":"+31 20 673 1328",
    "sg:postcode":"1071 CR",
    "sg:province":"North Holland",
    "wof:name":"Hofman Van Raak, Salon",
    "wof:placetype":"venue"
},
  "geometry": {"coordinates":[4.882133007,52.3601264954],"type":"Point"}
}