{
  "type": "Feature",
  "properties": {
    "addr:full":"Tammingastr 27 Hornhuizen Groningen 9978 PA",
    "addr:housenumber":"27",
    "addr:postcode":"9978 pa",
    "addr:street":"Tammingastr",
    "iso:country":"NL",
    "sg:address":"Tammingastr 27",
    "sg:city":"Hornhuizen",
    "sg:orig_category":"Vertalers",
    "sg:phone":"+31 595 481 690",
    "sg:postcode":"9978 PA",
    "sg:province":"Groningen",
    "wof:name":"Anderson, U",
    "wof:placetype":"venue"
},
  "geometry": {"coordinates":[6.362951,53.388004],"type":"Point"}
}