{
  "type": "Feature",
  "properties": {
    "addr:full":"Kruisstr 71 Delft South Holland 2611 ML",
    "addr:housenumber":"71",
    "addr:postcode":"2611 ml",
    "addr:street":"Kruisstr",
    "iso:country":"NL",
    "sg:address":"Kruisstr 71",
    "sg:city":"Delft",
    "sg:orig_category":"Bibliotheken En Leeszalen Openbare",
    "sg:phone":"+31 15 212 3450",
    "sg:postcode":"2611 ML",
    "sg:province":"South Holland",
    "wof:name":"Openb Bibliotheek",
    "wof:placetype":"venue"
},
  "geometry": {"coordinates":[4.364414,52.010536],"type":"Point"}
}