{
  "type": "Feature",
  "properties": {
    "iso:country":"NL",
    "sg:address":"De Herfstdraad 9",
    "sg:city":"Amersfoort",
    "sg:orig_category":"Psychologen",
    "sg:phone":"+31 33 456 3187",
    "sg:postcode":"3823 CS",
    "sg:province":"Utrecht",
    "wof:name":"Psychologenprakt Amersfoort-Noord",
    "wof:placetype":"venue"
},
  "geometry": {"coordinates":[5.388708,52.186924],"type":"Point"}
}