{
  "type": "Feature",
  "properties": {
    "addr:full":"Uithoornsewg 53 Helmond Noord-Brabant 5701 CA",
    "addr:housenumber":"53",
    "addr:postcode":"5701 ca",
    "addr:street":"Uithoornsewg",
    "iso:country":"NL",
    "sg:address":"Uithoornsewg 53",
    "sg:city":"Helmond",
    "sg:classifiers":[
        {
            "category":"Retail",
            "subcategory":"Auto Repair",
            "type":"Services"
        }
    ],
    "sg:phone":"+31 492 529 658",
    "sg:postcode":"5701 CA",
    "sg:province":"Noord-Brabant",
    "sg:tags":[
        "garage"
    ],
    "wof:name":"Stienezen, Hein",
    "wof:placetype":"venue"
},
  "geometry": {"coordinates":[5.671757,51.483318],"type":"Point"}
}