{
  "type": "Feature",
  "properties": {
    "addr:full":"Zeven Peggenwg 9 Ryssen Virginia 7461 VA",
    "addr:housenumber":"9",
    "addr:postcode":"7461",
    "addr:street":"Peggenwg",
    "iso:country":"NL",
    "sg:address":"Zeven Peggenwg 9",
    "sg:city":"Ryssen",
    "sg:orig_category":"Peuterspeelzalen",
    "sg:phone":"+31 548 519 649",
    "sg:postcode":"7461 VA",
    "sg:province":"Virginia",
    "wof:name":"Kruimeltje, 'T",
    "wof:placetype":"venue"
},
  "geometry": {"coordinates":[-79.771446,38.003349],"type":"Point"}
}