{
  "type": "Feature",
  "properties": {
    "addr:full":"Ptr Damiaanstr 107 Hoofddorp Noord-Holland 2131 EJ",
    "addr:housenumber":"107",
    "addr:postcode":"2131 ej",
    "iso:country":"NL",
    "sg:address":"Ptr Damiaanstr 107",
    "sg:city":"Hoofddorp",
    "sg:orig_category":"Onroerende Goederen",
    "sg:phone":"+31 23 557 3494",
    "sg:postcode":"2131 EJ",
    "sg:province":"Noord-Holland",
    "sg:website":"HTTP://www.hakinejo.nl",
    "wof:name":"Hakinejo",
    "wof:placetype":"venue"
},
  "geometry": {"coordinates":[4.680674,52.299988],"type":"Point"}
}