{
  "type": "Feature",
  "properties": {
    "addr:full":"Nageljongenstraat 4 Amsterdam North Holland 1033 PD",
    "addr:housenumber":"4",
    "addr:postcode":"1033 pd",
    "addr:street":"Nageljongenstraat",
    "iso:country":"NL",
    "sg:address":"Nageljongenstraat 4",
    "sg:city":"Amsterdam",
    "sg:orig_category":"Partycatering And -Organisatie",
    "sg:phone":"+31 20 633 4539",
    "sg:postcode":"1033 PD",
    "sg:province":"North Holland",
    "wof:name":"Labro Food",
    "wof:placetype":"venue"
},
  "geometry": {"coordinates":[4.898909,52.408016],"type":"Point"}
}