{
  "type": "Feature",
  "properties": {
    "iso:country":"NL",
    "sg:address":"Spoorstr 23",
    "sg:city":"Bodegraven",
    "sg:orig_category":"Verloskundigen",
    "sg:phone":"+31 172 614 469",
    "sg:postcode":"2411 ED",
    "sg:province":"Zuid-Holland",
    "wof:name":"Veloskundige Prakt Bodegraven",
    "wof:placetype":"venue"
},
  "geometry": {"coordinates":[4.748013,52.082558],"type":"Point"}
}