{
  "type": "Feature",
  "properties": {
    "addr:full":"Zwanenveld 9068 Nymegen South Carolina 6538 SC",
    "addr:housenumber":"9068;6538",
    "addr:street":"Zwanenveld",
    "iso:country":"NL",
    "sg:address":"Zwanenveld 9068",
    "sg:city":"Nymegen",
    "sg:orig_category":"Herenkleding",
    "sg:phone":"+31 24 344 4485",
    "sg:postcode":"6538 SC",
    "sg:province":"South Carolina",
    "sg:website":"http://www.verhulstmannenmode.nl",
    "wof:name":"Verhulst Mannenmode",
    "wof:placetype":"venue"
},
  "geometry": {"coordinates":[-80.947441,33.624981],"type":"Point"}
}