{
  "type": "Feature",
  "properties": {
    "addr:full":"Korte Hoogstraat 18 A Vlaardingen South Holland 3131 BK",
    "addr:housenumber":"18 a",
    "addr:postcode":"3131 bk",
    "addr:street":"Korte Hoogstraat",
    "iso:country":"NL",
    "sg:address":"Korte Hoogstraat 18 A",
    "sg:city":"Vlaardingen",
    "sg:classifiers":[
        {
            "category":"Communications",
            "subcategory":"Television Station",
            "type":"Services"
        }
    ],
    "sg:phone":"+31 10 435 6822",
    "sg:postcode":"3131 BK",
    "sg:province":"South Holland",
    "sg:tags":[
        "video",
        "audio",
        "verhuur"
    ],
    "wof:name":"Videoland Vlaardingen",
    "wof:placetype":"venue"
},
  "geometry": {"coordinates":[4.342567,51.910885],"type":"Point"}
}