{
  "type": "Feature",
  "properties": {
    "addr:full":"Korenstr 1 Dalfsen NL.08 7722 RS",
    "addr:housenumber":"1;nl.08",
    "addr:postcode":"7722 rs",
    "addr:street":"Korenstr",
    "iso:country":"NL",
    "sg:address":"Korenstr 1",
    "sg:city":"Dalfsen",
    "sg:orig_category":"Loonbedrijven",
    "sg:phone":"+31 6 53808137",
    "sg:postcode":"7722 RS",
    "sg:province":"NL.08",
    "wof:name":"Knotters, H",
    "wof:placetype":"venue"
},
  "geometry": {"coordinates":[6.26932,52.509251],"type":"Point"}
}