{
  "type": "Feature",
  "properties": {
    "addr:full":"Markt 48 Hoensbroek Limburg 6431 LJ",
    "addr:housenumber":"48",
    "addr:postcode":"6431 lj",
    "addr:street":"Markt",
    "iso:country":"NL",
    "sg:address":"Markt 48",
    "sg:city":"Hoensbroek",
    "sg:orig_category":"Wijnkoperijen En -Groothandel",
    "sg:phone":"+31 45 522 4765",
    "sg:postcode":"6431 LJ",
    "sg:province":"Limburg",
    "wof:name":"Gebrooks Wijngenootschap, Het",
    "wof:placetype":"venue"
},
  "geometry": {"coordinates":[5.9251642227,50.9233131409],"type":"Point"}
}