{
  "type": "Feature",
  "properties": {
    "iso:country":"NL",
    "sg:address":"Hoofdweg 44",
    "sg:city":"Westerlee Gn",
    "sg:orig_category":"Kampeerterreinen",
    "sg:phone":"+31 597 413 367",
    "sg:postcode":"9678 PM",
    "sg:province":"Groningen",
    "wof:name":"Camping De Hoeve",
    "wof:placetype":"venue"
},
  "geometry": {"coordinates":[6.9756350517,53.141418457],"type":"Point"}
}