{
  "type": "Feature",
  "properties": {
    "iso:country":"NL",
    "sg:address":"Bagijneland 28",
    "sg:city":"'S Gravenzande",
    "sg:orig_category":"Bloemen And Planten",
    "sg:phone":"+31 174 440 107",
    "sg:postcode":"2691 NC",
    "sg:province":"South Holland",
    "wof:name":"Peter Van Winden Vof",
    "wof:placetype":"venue"
},
  "geometry": {"coordinates":[4.149215,51.983192],"type":"Point"}
}