{
  "type": "Feature",
  "properties": {
    "addr:full":"Kerkdijk 11 Westbroek Utrecht 3615 BA",
    "addr:housenumber":"11",
    "addr:postcode":"3615 ba",
    "addr:street":"Kerkdijk",
    "iso:country":"NL",
    "sg:address":"Kerkdijk 11",
    "sg:city":"Westbroek",
    "sg:orig_category":"Autokeuringen",
    "sg:phone":"+31 346 282 640",
    "sg:postcode":"3615 BA",
    "sg:province":"Utrecht",
    "wof:name":"Schadenet Bv",
    "wof:placetype":"venue"
},
  "geometry": {"coordinates":[-72.44995900000001,41.285973],"type":"Point"}
}