{
  "type": "Feature",
  "properties": {
    "addr:full":"Drumptselaan 6 Tiel Gelderland 4003 HD",
    "addr:housenumber":"6",
    "addr:postcode":"4003 hd",
    "addr:street":"Drumptselaan;Gelderland",
    "iso:country":"NL",
    "sg:address":"Drumptselaan 6",
    "sg:city":"Tiel",
    "sg:orig_category":"Verlichting And Huishoudartikelen",
    "sg:phone":"+31 344 630 490",
    "sg:postcode":"4003 HD",
    "sg:province":"Gelderland",
    "wof:name":"Interbas",
    "wof:placetype":"venue"
},
  "geometry": {"coordinates":[5.415926,51.896606],"type":"Point"}
}