{
  "type": "Feature",
  "properties": {
    "addr:full":"Beekhuizensewg 9 Velp Gld Gelderland 6881 AA",
    "addr:housenumber":"9",
    "addr:postcode":"6881 aa",
    "addr:street":"Beekhuizensewg;Gld Gelderland",
    "iso:country":"NL",
    "sg:address":"Beekhuizensewg 9",
    "sg:city":"Velp Gld",
    "sg:orig_category":"Hulpverlening Sociaal",
    "sg:phone":"+31 26 364 6487",
    "sg:postcode":"6881 AA",
    "sg:province":"Gelderland",
    "wof:name":"Beekhuis, Het",
    "wof:placetype":"venue"
},
  "geometry": {"coordinates":[5.984673,52.000744],"type":"Point"}
}