{
  "type": "Feature",
  "properties": {
    "addr:full":"De Ortolaan 13 Almelo NL.08 7609 MJ",
    "addr:housenumber":"13;nl.08",
    "addr:postcode":"7609 mj",
    "addr:street":"De Ortolaan",
    "iso:country":"NL",
    "sg:address":"De Ortolaan 13",
    "sg:city":"Almelo",
    "sg:orig_category":"Plafonds",
    "sg:phone":"+31 546 657 146",
    "sg:postcode":"7609 MJ",
    "sg:province":"NL.08",
    "wof:name":"Bogri",
    "wof:placetype":"venue"
},
  "geometry": {"coordinates":[6.635579,52.32943],"type":"Point"}
}