{
  "type": "Feature",
  "properties": {
    "iso:country":"NL",
    "sg:address":"Morsestraat 2",
    "sg:city":"Zwolle",
    "sg:orig_category":"Diverse Artikelen Fab",
    "sg:phone":"+31 38 465 7110",
    "sg:postcode":"8013 PP",
    "sg:province":"Overijssel",
    "wof:name":"Verenigde Nederlandse Kaarsfabrieken Bv",
    "wof:placetype":"venue"
},
  "geometry": {"coordinates":[6.126408,52.496311],"type":"Point"}
}