{
  "type": "Feature",
  "properties": {
    "iso:country":"NL",
    "sg:address":"Bieremaln 55",
    "sg:city":"Den Haag",
    "sg:orig_category":"Benzine En Olie - Groothandel",
    "sg:phone":"+31 6 24233109",
    "sg:postcode":"2497 AW",
    "sg:province":"South Holland",
    "wof:name":"Molen, Van Der",
    "wof:placetype":"venue"
},
  "geometry": {"coordinates":[4.357638,52.034683],"type":"Point"}
}