{
  "type": "Feature",
  "properties": {
    "addr:full":"Lorentzstraat 3C Alkmaar Noord-Holland 1821 BR",
    "addr:housenumber":"3c",
    "addr:postcode":"1821 br",
    "addr:street":"Lorentzstraat",
    "iso:country":"NL",
    "sg:address":"Lorentzstraat 3C",
    "sg:city":"Alkmaar",
    "sg:orig_category":"Huizensloop And Bouwrijp Maken",
    "sg:phone":"+31 72 520 4477",
    "sg:postcode":"1821 BR",
    "sg:province":"Noord-Holland",
    "wof:name":"Verberne Baron.Vof",
    "wof:placetype":"venue"
},
  "geometry": {"coordinates":[4.770956,52.626915],"type":"Point"}
}