{
  "type": "Feature",
  "properties": {
    "iso:country":"NL",
    "sg:address":"Begonialaan 4",
    "sg:city":"Oegstgeest",
    "sg:orig_category":"Metaalwerken",
    "sg:phone":"+31 71 517 0203",
    "sg:postcode":"2343 XN",
    "sg:province":"Zuid-Holland",
    "wof:name":"W. V. Steijn",
    "wof:placetype":"venue"
},
  "geometry": {"coordinates":[4.471998,52.189716],"type":"Point"}
}