{
  "type": "Feature",
  "properties": {
    "addr:full":"Voorstr 41A Groot Ammers Zuid-Holland 2964 AH",
    "addr:housenumber":"41a",
    "addr:postcode":"2964 ah",
    "addr:street":"Voorstr;Groot Ammers",
    "iso:country":"NL",
    "sg:address":"Voorstr 41A",
    "sg:city":"Groot Ammers",
    "sg:orig_category":"Opticiens",
    "sg:phone":"+31 184 662 228",
    "sg:postcode":"2964 AH",
    "sg:province":"Zuid-Holland",
    "wof:name":"Goud",
    "wof:placetype":"venue"
},
  "geometry": {"coordinates":[4.8179888725,51.924987793],"type":"Point"}
}