{
  "type": "Feature",
  "properties": {
    "iso:country":"NL",
    "sg:address":"Schipholstraat 80",
    "sg:city":"Rotterdam",
    "sg:orig_category":"Kinderopvang",
    "sg:phone":"+31 10 437 3036",
    "sg:postcode":"3045 XD",
    "sg:province":"South Holland",
    "wof:name":"Ravot",
    "wof:placetype":"venue"
},
  "geometry": {"coordinates":[4.432534,51.944248],"type":"Point"}
}