{
  "type": "Feature",
  "properties": {
    "addr:full":"Galvanistraat 32 Zoetermeer South Holland 2723 RV",
    "addr:housenumber":"32",
    "addr:postcode":"2723 rv",
    "addr:street":"Galvanistraat",
    "iso:country":"NL",
    "sg:address":"Galvanistraat 32",
    "sg:city":"Zoetermeer",
    "sg:orig_category":"Houten Verpakkingen Fab",
    "sg:phone":"+31 79 342 8037",
    "sg:postcode":"2723 RV",
    "sg:province":"South Holland",
    "wof:name":"Pallethandel Zoetermeer",
    "wof:placetype":"venue"
},
  "geometry": {"coordinates":[4.528147,52.057381],"type":"Point"}
}