{
  "type": "Feature",
  "properties": {
    "addr:full":"Groene Kruislaan 7 Bellingwolde Groningen 9695 BB",
    "addr:housenumber":"7",
    "addr:postcode":"9695 bb",
    "addr:street":"Groene Kruislaan",
    "iso:country":"NL",
    "sg:address":"Groene Kruislaan 7",
    "sg:city":"Bellingwolde",
    "sg:orig_category":"Diensten Voor Huisdieren",
    "sg:phone":"+31 597 531 518",
    "sg:postcode":"9695 BB",
    "sg:province":"Groningen",
    "wof:name":"Vogels & Egels",
    "wof:placetype":"venue"
},
  "geometry": {"coordinates":[7.141271,53.100636],"type":"Point"}
}