{
  "type": "Feature",
  "properties": {
    "addr:full":"Hofkamp 1 Wommels Provincie Friesland 8731 BS",
    "addr:housenumber":"1;8731",
    "addr:postcode":"bs",
    "addr:street":"Hofkamp;Provincie Friesland",
    "iso:country":"NL",
    "sg:address":"Hofkamp 1",
    "sg:city":"Wommels",
    "sg:orig_category":"Kinderopvang Behalve Thuis",
    "sg:phone":"+31 515 332 889",
    "sg:postcode":"8731 BS",
    "sg:province":"Provincie Friesland",
    "wof:name":"Kinderopvang Wommels",
    "wof:placetype":"venue"
},
  "geometry": {"coordinates":[5.587121,53.106606],"type":"Point"}
}