{
  "type": "Feature",
  "properties": {
    "iso:country":"NL",
    "sg:address":"Leeuwerikplein 101",
    "sg:city":"Purmerend",
    "sg:classifiers":[
        {
            "category":"Professional",
            "subcategory":"Accounting & Tax Preparation",
            "type":"Services"
        }
    ],
    "sg:phone":"+31 299 430 735",
    "sg:postcode":"1444 HZ",
    "sg:province":"Noord-Holland",
    "sg:tags":[
        "accountant"
    ],
    "wof:name":"Hilgers + Co",
    "wof:placetype":"venue"
},
  "geometry": {"coordinates":[4.962119,52.520996],"type":"Point"}
}