{
  "type": "Feature",
  "properties": {
    "addr:full":"Ambtmanstr 30-1 Tiel Gelderland 4001 MC",
    "addr:housenumber":"30-1;4001",
    "addr:street":"Gelderland;Mc",
    "iso:country":"NL",
    "sg:address":"Ambtmanstr 30-1",
    "sg:city":"Tiel",
    "sg:orig_category":"Logopedisten",
    "sg:phone":"+31 344 630 676",
    "sg:postcode":"4001 MC",
    "sg:province":"Gelderland",
    "wof:name":"Logopediepraktijk Tiel",
    "wof:placetype":"venue"
},
  "geometry": {"coordinates":[5.433411,51.887184],"type":"Point"}
}