{
  "type": "Feature",
  "properties": {
    "addr:full":"Irisln 53 Oegstgeest South Holland 2343 CG",
    "addr:housenumber":"53",
    "addr:postcode":"2343 cg",
    "addr:street":"Irisln",
    "iso:country":"NL",
    "sg:address":"Irisln 53",
    "sg:city":"Oegstgeest",
    "sg:orig_category":"Herenkleding",
    "sg:phone":"+31 71 523 7120",
    "sg:postcode":"2343 CG",
    "sg:province":"South Holland",
    "wof:name":"Klaver",
    "wof:placetype":"venue"
},
  "geometry": {"coordinates":[4.468242,52.176617],"type":"Point"}
}