{
  "type": "Feature",
  "properties": {
    "addr:full":"Ranonkelstr 9 Bleskensgraaf Ca South Holland 2971 BP",
    "addr:housenumber":"9",
    "addr:postcode":"ca;2971 bp",
    "addr:street":"Ranonkelstr",
    "iso:country":"NL",
    "sg:address":"Ranonkelstr 9",
    "sg:city":"Bleskensgraaf Ca",
    "sg:orig_category":"Loonbedrijven",
    "sg:phone":"+31 184 693 078",
    "sg:postcode":"2971 BP",
    "sg:province":"South Holland",
    "wof:name":"Haan, Loonbedrijf A J De",
    "wof:placetype":"venue"
},
  "geometry": {"coordinates":[4.786666,51.87328],"type":"Point"}
}