{
  "type": "Feature",
  "properties": {
    "addr:full":"Kesterendreef 8 Breda Noord-Brabant 4822 WT",
    "addr:housenumber":"8",
    "addr:postcode":"4822 wt",
    "addr:street":"Kesterendreef",
    "iso:country":"NL",
    "sg:address":"Kesterendreef 8",
    "sg:city":"Breda",
    "sg:orig_category":"Bedrijfsmechanisatie En -Automatisering",
    "sg:phone":"+31 76 549 3831",
    "sg:postcode":"4822 WT",
    "sg:province":"Noord-Brabant",
    "wof:name":"At",
    "wof:placetype":"venue"
},
  "geometry": {"coordinates":[4.732308,51.608219],"type":"Point"}
}