{
  "type": "Feature",
  "properties": {
    "addr:full":"Industrieweg 16 Wormerveer North Holland 1521 NC",
    "addr:housenumber":"16;1521",
    "addr:postcode":"nc",
    "addr:street":"Industrieweg",
    "iso:country":"NL",
    "sg:address":"Industrieweg 16",
    "sg:city":"Wormerveer",
    "sg:orig_category":"Effectenmakelaars And Fondsenbeheer",
    "sg:phone":"+31 75 621 2721",
    "sg:postcode":"1521 NC",
    "sg:province":"North Holland",
    "wof:name":"Bedrijvenpark De Woudaap",
    "wof:placetype":"venue"
},
  "geometry": {"coordinates":[4.777204,52.503651],"type":"Point"}
}