{
  "type": "Feature",
  "properties": {
    "addr:full":"Pr Johan Friso Promenade 51 Rijswijk Zh Zuid-Holland 2284 DD",
    "addr:housenumber":"51",
    "addr:postcode":"zh;2284 dd",
    "addr:street":"Johan Friso Promenade",
    "iso:country":"NL",
    "sg:address":"Pr Johan Friso Promenade 51",
    "sg:city":"Rijswijk Zh",
    "sg:classifiers":[
        {
            "category":"Bakery",
            "type":"Food & Drink"
        }
    ],
    "sg:phone":"+31 70 393 4865",
    "sg:postcode":"2284 DD",
    "sg:province":"Zuid-Holland",
    "sg:tags":[
        "brood",
        "banket"
    ],
    "wof:name":"De Warme Bakker Aad De Groot",
    "wof:placetype":"venue"
},
  "geometry": {"coordinates":[4.314204,52.038597],"type":"Point"}
}