{
  "type": "Feature",
  "properties": {
    "iso:country":"NL",
    "sg:address":"Telfordstr 18",
    "sg:city":"Zwolle",
    "sg:orig_category":"Schilders",
    "sg:phone":"+31 38 465 0222",
    "sg:postcode":"8013 RM",
    "sg:province":"Overijssel",
    "wof:name":"Porte & Zn, Vof W",
    "wof:placetype":"venue"
},
  "geometry": {"coordinates":[6.140217,52.487633],"type":"Point"}
}