{
  "type": "Feature",
  "properties": {
    "addr:full":"Hertogstraat 22 Eindhoven Noord-Brabant 5611 PB",
    "addr:housenumber":"22",
    "addr:postcode":"5611 pb",
    "addr:street":"Hertogstraat",
    "iso:country":"NL",
    "sg:address":"Hertogstraat 22",
    "sg:city":"Eindhoven",
    "sg:orig_category":"Marktonderzoekbureaus",
    "sg:phone":"+31 40 212 3818",
    "sg:postcode":"5611 PB",
    "sg:province":"Noord-Brabant",
    "wof:name":"Leon Strijards",
    "wof:placetype":"venue"
},
  "geometry": {"coordinates":[5.485687,51.433399],"type":"Point"}
}