{
  "type": "Feature",
  "properties": {
    "addr:full":"Rotterdamsestr 58 S Gravenhage Zuid-Holland 2586 GM",
    "addr:housenumber":"58;gravenhage",
    "addr:postcode":"2586 gm",
    "addr:street":"Rotterdamsestr;S",
    "iso:country":"NL",
    "sg:address":"Rotterdamsestr 58",
    "sg:city":"S Gravenhage",
    "sg:orig_category":"Fotografie Reclame En Mode",
    "sg:phone":"+31 70 358 4228",
    "sg:postcode":"2586 GM",
    "sg:province":"Zuid-Holland",
    "sg:website":"http://www.zoe-images.com",
    "wof:name":"Zo\u00e9 Images",
    "wof:placetype":"venue"
},
  "geometry": {"coordinates":[4.277215004,52.1067199707],"type":"Point"}
}