{
  "type": "Feature",
  "properties": {
    "addr:full":"Eindstraat 23 Breda Noord-Brabant 4811 KK",
    "addr:housenumber":"23",
    "addr:postcode":"4811 kk",
    "addr:street":"Eindstraat",
    "iso:country":"NL",
    "sg:address":"Eindstraat 23",
    "sg:city":"Breda",
    "sg:orig_category":"Schoenen",
    "sg:phone":"+31 76 521 4053",
    "sg:postcode":"4811 KK",
    "sg:province":"Noord-Brabant",
    "wof:name":"Dolcis Bv",
    "wof:placetype":"venue"
},
  "geometry": {"coordinates":[4.776381,51.586441],"type":"Point"}
}