{
  "type": "Feature",
  "properties": {
    "iso:country":"NL",
    "sg:address":"Javastraat 29",
    "sg:city":"Amsterdam",
    "sg:orig_category":"Bloemen And Planten",
    "sg:phone":"+31 20 694 4966",
    "sg:postcode":"1094 GZ",
    "sg:province":"Noord-Holland",
    "wof:name":"Bloemsierkunst Conny",
    "wof:placetype":"venue"
},
  "geometry": {"coordinates":[4.932844,52.363708],"type":"Point"}
}