{
  "type": "Feature",
  "properties": {
    "iso:country":"NL",
    "sg:address":"Armhoefstraat 56",
    "sg:city":"Tilburg",
    "sg:orig_category":"Hypotheken And Hypotheekbanken",
    "sg:phone":"+31 13 536 2177",
    "sg:postcode":"5018 EK",
    "sg:province":"Noord-Brabant",
    "wof:name":"Vof Assurantiekantoor Jan Horvers",
    "wof:placetype":"venue"
},
  "geometry": {"coordinates":[5.10843,51.558846],"type":"Point"}
}