{
  "type": "Feature",
  "properties": {
    "addr:full":"Achterstraat 10 Hattem Gelderland 8051 GB",
    "addr:housenumber":"10",
    "addr:postcode":"8051 gb",
    "addr:street":"Achterstraat;Gelderland",
    "iso:country":"NL",
    "sg:address":"Achterstraat 10",
    "sg:city":"Hattem",
    "sg:orig_category":"Kappers",
    "sg:phone":"+31 38 444 2742",
    "sg:postcode":"8051 GB",
    "sg:province":"Gelderland",
    "wof:name":"Post Haarmode Vof",
    "wof:placetype":"venue"
},
  "geometry": {"coordinates":[6.06933,52.475281],"type":"Point"}
}