{
  "type": "Feature",
  "properties": {
    "iso:country":"NL",
    "sg:address":"Haverstr Passage 40",
    "sg:city":"Enschede",
    "sg:orig_category":"Boeken En Tijdschriften",
    "sg:phone":"+31 53 430 5743",
    "sg:postcode":"7511 EX",
    "sg:province":"Overijssel",
    "wof:name":"Wizard",
    "wof:placetype":"venue"
},
  "geometry": {"coordinates":[6.898045,52.220612],"type":"Point"}
}