{
  "type": "Feature",
  "properties": {
    "addr:full":"Klooster Leut Str 29 Wyk By Duurstede Utrecht 3961 AX",
    "addr:postcode":"3961 ax",
    "addr:street":"Str 29 Wyk;Duurstede",
    "iso:country":"NL",
    "sg:address":"Klooster Leut Str 29",
    "sg:city":"Wyk By Duurstede",
    "sg:orig_category":"Banken",
    "sg:phone":"+31 343 571 676",
    "sg:postcode":"3961 AX",
    "sg:province":"Utrecht",
    "sg:website":"http://www.sns.nl",
    "wof:name":"Sns",
    "wof:placetype":"venue"
},
  "geometry": {"coordinates":[5.346949,51.972805],"type":"Point"}
}