{
  "type": "Feature",
  "properties": {
    "iso:country":"NL",
    "sg:address":"Kikkerbeet 51",
    "sg:city":"Amersfoort",
    "sg:orig_category":"Kaarsen - Fabrieken En Groothandel",
    "sg:phone":"+31 33 455 0370",
    "sg:postcode":"3824 WT",
    "sg:province":"Utrecht",
    "wof:name":"Lancro",
    "wof:placetype":"venue"
},
  "geometry": {"coordinates":[5.3720850945,52.2054748535],"type":"Point"}
}