{
  "type": "Feature",
  "properties": {
    "addr:full":"Moerweide 71 Reeuwyk South Holland 2811 JC",
    "addr:housenumber":"71",
    "addr:postcode":"2811 jc",
    "addr:street":"Moerweide",
    "iso:country":"NL",
    "sg:address":"Moerweide 71",
    "sg:city":"Reeuwyk",
    "sg:orig_category":"Verkoopautomaten",
    "sg:phone":"+31 182 395 764",
    "sg:postcode":"2811 JC",
    "sg:province":"South Holland",
    "wof:name":"Surprich",
    "wof:placetype":"venue"
},
  "geometry": {"coordinates":[4.729226,52.051888],"type":"Point"}
}