{
  "type": "Feature",
  "properties": {
    "addr:full":"Blokweg 19 Zevenbergen North Brabant 4761 RA",
    "addr:housenumber":"19",
    "addr:postcode":"4761 ra",
    "addr:street":"Blokweg",
    "iso:country":"NL",
    "sg:address":"Blokweg 19",
    "sg:city":"Zevenbergen",
    "sg:orig_category":"Diverse Bedrijfsinstallaties Gh",
    "sg:phone":"+31 168 323 132",
    "sg:postcode":"4761 RA",
    "sg:province":"North Brabant",
    "wof:name":"Baru Services Bv",
    "wof:placetype":"venue"
},
  "geometry": {"coordinates":[4.610665,51.648594],"type":"Point"}
}