{
  "type": "Feature",
  "properties": {
    "addr:full":"Benkoelenstr 28 Haarlem North Holland 2022 PK",
    "addr:housenumber":"28",
    "addr:postcode":"2022 pk",
    "addr:street":"Benkoelenstr",
    "iso:country":"NL",
    "sg:address":"Benkoelenstr 28",
    "sg:city":"Haarlem",
    "sg:orig_category":"Fotoreportages",
    "sg:phone":"+31 23 538 2272",
    "sg:postcode":"2022 PK",
    "sg:province":"North Holland",
    "sg:website":"http://www.severingfotografie.nl",
    "wof:name":"Alex Severing Fotografie",
    "wof:placetype":"venue"
},
  "geometry": {"coordinates":[4.652362,52.406605],"type":"Point"}
}