{
  "type": "Feature",
  "properties": {
    "addr:full":"Gr Sabinastr 2/D Zuid Beyerland South Holland 3284 AP",
    "addr:housenumber":"2 / d",
    "addr:postcode":"3284 ap",
    "addr:street":"Beyerland",
    "iso:country":"NL",
    "sg:address":"Gr Sabinastr 2/D",
    "sg:city":"Zuid Beyerland",
    "sg:orig_category":"Verzekeringen - Verzekeringskantoren",
    "sg:phone":"+31 186 662 500",
    "sg:postcode":"3284 AP",
    "sg:province":"South Holland",
    "wof:name":"Weijers",
    "wof:placetype":"venue"
},
  "geometry": {"coordinates":[4.36709,51.74995],"type":"Point"}
}