{
  "type": "Feature",
  "properties": {
    "addr:full":"Traktiewg 18 Emmeloord Flevoland 8304 BA",
    "addr:housenumber":"18",
    "addr:postcode":"8304 ba",
    "addr:street":"Traktiewg;Flevoland",
    "iso:country":"NL",
    "sg:address":"Traktiewg 18",
    "sg:city":"Emmeloord",
    "sg:orig_category":"Land- En Tuinbouw - Mechanisatie",
    "sg:phone":"+31 527 611 648",
    "sg:postcode":"8304 BA",
    "sg:province":"Flevoland",
    "sg:website":"http://www.oldenhuis.en.prinsen.nl",
    "wof:name":"Oldenhuis & Prinsen Bv",
    "wof:placetype":"venue"
},
  "geometry": {"coordinates":[5.759158,52.693916],"type":"Point"}
}