{
  "type": "Feature",
  "properties": {
    "addr:full":"Muntpromenade 8 Weert Limburg 6001 EH",
    "addr:housenumber":"8",
    "addr:postcode":"6001 eh",
    "addr:street":"Muntpromenade",
    "iso:country":"NL",
    "sg:address":"Muntpromenade 8",
    "sg:city":"Weert",
    "sg:orig_category":"Kappers",
    "sg:phone":"+31 495 524 102",
    "sg:postcode":"6001 EH",
    "sg:province":"Limburg",
    "wof:name":"De Kapper C.E.A.M. Binnenmarsch",
    "wof:placetype":"venue"
},
  "geometry": {"coordinates":[5.7059249878,51.2541847229],"type":"Point"}
}