{
  "type": "Feature",
  "properties": {
    "addr:full":"Benschopperstr 6 Ysselstein Ut Utrecht 3401 DH",
    "addr:housenumber":"6",
    "addr:postcode":"3401 dh",
    "addr:street":"Benschopperstr",
    "iso:country":"NL",
    "sg:address":"Benschopperstr 6",
    "sg:city":"Ysselstein Ut",
    "sg:orig_category":"Wasmachines En Wasdrogers - Onderhoud En Reparatie",
    "sg:phone":"+31 30 688 2378",
    "sg:postcode":"3401 DH",
    "sg:province":"Utrecht",
    "wof:name":"G?lectro Bv",
    "wof:placetype":"venue"
},
  "geometry": {"coordinates":[5.0418348312,52.0184364319],"type":"Point"}
}