{
  "type": "Feature",
  "properties": {
    "addr:full":"Rapenburg 112 Leiden Zuid-Holland 2311 GB",
    "addr:housenumber":"112",
    "addr:postcode":"2311 gb",
    "addr:street":"Rapenburg",
    "iso:country":"NL",
    "sg:address":"Rapenburg 112",
    "sg:city":"Leiden",
    "sg:orig_category":"Makelaars In Onroerend Goed",
    "sg:phone":"+31 71 512 4122",
    "sg:postcode":"2311 GB",
    "sg:province":"Zuid-Holland",
    "wof:name":"Makelaarskantoor P. Moerman",
    "wof:placetype":"venue"
},
  "geometry": {"coordinates":[4.488432,52.156059],"type":"Point"}
}