{
  "type": "Feature",
  "properties": {
    "addr:full":"Witte Molenweg 37 Heesch North Brabant 5384 JA",
    "addr:housenumber":"37",
    "addr:postcode":"5384 ja",
    "addr:street":"Witte Molenweg",
    "iso:country":"NL",
    "sg:address":"Witte Molenweg 37",
    "sg:city":"Heesch",
    "sg:orig_category":"Verzekeringen",
    "sg:phone":"+31 412 451 442",
    "sg:postcode":"5384 JA",
    "sg:province":"North Brabant",
    "wof:name":"Assurantiebedrijf J.Th.J. Van Nistelrooi",
    "wof:placetype":"venue"
},
  "geometry": {"coordinates":[5.525421,51.729744],"type":"Point"}
}