{
  "type": "Feature",
  "properties": {
    "addr:full":"Lipperkerkstraat 24 Enschede Overijssel 7511 DA",
    "addr:housenumber":"24",
    "addr:postcode":"7511 da",
    "addr:street":"Lipperkerkstraat",
    "iso:country":"NL",
    "sg:address":"Lipperkerkstraat 24",
    "sg:city":"Enschede",
    "sg:orig_category":"Kappers",
    "sg:phone":"+31 53 431 2876",
    "sg:postcode":"7511 DA",
    "sg:province":"Overijssel",
    "wof:name":"De Knipsalon",
    "wof:placetype":"venue"
},
  "geometry": {"coordinates":[6.9050917625,52.2204170227],"type":"Point"}
}