{
  "type": "Feature",
  "properties": {
    "iso:country":"NL",
    "sg:address":"Vreelust 69",
    "sg:city":"Gouda",
    "sg:orig_category":"Grafisch Ontwerpers",
    "sg:phone":"+31 182 546 164",
    "sg:postcode":"2804 LG",
    "sg:province":"Zuid-Holland",
    "wof:name":"Heins, Linda",
    "wof:placetype":"venue"
},
  "geometry": {"coordinates":[4.711398,52.037247],"type":"Point"}
}