{
  "type": "Feature",
  "properties": {
    "iso:country":"NL",
    "sg:address":"Lokkershofwg 6",
    "sg:city":"Noordwelle",
    "sg:classifiers":[
        {
            "category":"Banks & Credit Unions",
            "subcategory":"Investment Brokerage",
            "type":"Services"
        }
    ],
    "sg:phone":"+31 111 462 347",
    "sg:postcode":"4326 SE",
    "sg:province":"Zeeland",
    "sg:tags":[
        "pension"
    ],
    "sg:website":"http://www.lockershof.nl",
    "wof:name":"Lockershof",
    "wof:placetype":"venue"
},
  "geometry": {"coordinates":[3.784696,51.712318],"type":"Point"}
}