{
  "type": "Feature",
  "properties": {
    "addr:full":"Grote Stern 83 Rozenburg Zh Zuid-Holland 3181 SC",
    "addr:housenumber":"83",
    "addr:postcode":"zh;3181 sc",
    "addr:street":"Grote Stern",
    "iso:country":"NL",
    "sg:address":"Grote Stern 83",
    "sg:city":"Rozenburg Zh",
    "sg:orig_category":"Kappers",
    "sg:phone":"+31 181 216 324",
    "sg:postcode":"3181 SC",
    "sg:province":"Zuid-Holland",
    "wof:name":"Haarmode Agthoven",
    "wof:placetype":"venue"
},
  "geometry": {"coordinates":[4.2397041321,51.9089393616],"type":"Point"}
}