{
  "type": "Feature",
  "properties": {
    "addr:full":"L J Zielstraweg 2 Groningen Groningen 9713 GX",
    "addr:housenumber":"2",
    "addr:postcode":"9713 gx",
    "addr:street":"L J Zielstraweg",
    "iso:country":"NL",
    "sg:address":"L J Zielstraweg 2",
    "sg:city":"Groningen",
    "sg:orig_category":"Ambassades And Consulaten",
    "sg:phone":"+31 50 588 7777",
    "sg:postcode":"9713 GX",
    "sg:province":"Groningen",
    "wof:name":"Consulaat Van Noorwegen",
    "wof:placetype":"venue"
},
  "geometry": {"coordinates":[6.577448,53.219769],"type":"Point"}
}