{
  "type": "Feature",
  "properties": {
    "iso:country":"NL",
    "sg:address":"Potgieterstraat 1",
    "sg:city":"Lekkerkerk",
    "sg:orig_category":"Autokeuringen",
    "sg:phone":"+31 180 669 023",
    "sg:postcode":"2941 GR",
    "sg:province":"Zuid-Holland",
    "wof:name":"Van Der Graaf'S Services",
    "wof:placetype":"venue"
},
  "geometry": {"coordinates":[4.68027,51.897552],"type":"Point"}
}