{
  "type": "Feature",
  "properties": {
    "addr:full":"Postbus 77 Rheden Gelderland 6990 AB",
    "addr:housenumber":"77",
    "addr:postcode":"6990 ab",
    "addr:street":"Postbus;Gelderland",
    "iso:country":"NL",
    "sg:address":"Postbus 77",
    "sg:city":"Rheden",
    "sg:orig_category":"Verhuizingen",
    "sg:phone":"+31 26 325 2070",
    "sg:postcode":"6990 AB",
    "sg:province":"Gelderland",
    "wof:name":"Snippe",
    "wof:placetype":"venue"
},
  "geometry": {"coordinates":[6.03264,52.002544],"type":"Point"}
}