{
  "type": "Feature",
  "properties": {
    "iso:country":"NL",
    "sg:address":"V Bergenpln 46",
    "sg:city":"Etten Leur",
    "sg:orig_category":"Kappers",
    "sg:phone":"+31 76 503 5787",
    "sg:postcode":"4871 CG",
    "sg:province":"Noord-Brabant",
    "wof:name":"Hairpoint",
    "wof:placetype":"venue"
},
  "geometry": {"coordinates":[4.6395220757,51.5706939697],"type":"Point"}
}