{
  "type": "Feature",
  "properties": {
    "addr:full":"Prinsengracht 581 Amsterdam Noord-Holland 1016 HT",
    "addr:housenumber":"581",
    "addr:postcode":"1016 ht",
    "addr:street":"Prinsengracht",
    "iso:country":"NL",
    "sg:address":"Prinsengracht 581",
    "sg:city":"Amsterdam",
    "sg:orig_category":"Muziekinstrumenten",
    "sg:phone":"+31 20 626 8485",
    "sg:postcode":"1016 HT",
    "sg:province":"Noord-Holland",
    "wof:name":"Cristofori Piano'S & Vleugels",
    "wof:placetype":"venue"
},
  "geometry": {"coordinates":[4.883,52.368027],"type":"Point"}
}