{
  "type": "Feature",
  "properties": {
    "addr:full":"Hoofdstraat 45 Hoensbroek Limburg 6431 LB",
    "addr:housenumber":"45",
    "addr:postcode":"6431 lb",
    "addr:street":"Hoofdstraat",
    "iso:country":"NL",
    "sg:address":"Hoofdstraat 45",
    "sg:city":"Hoensbroek",
    "sg:orig_category":"Juweliers",
    "sg:phone":"+31 45 522 2761",
    "sg:postcode":"6431 LB",
    "sg:province":"Limburg",
    "wof:name":"Juwelier Willems",
    "wof:placetype":"venue"
},
  "geometry": {"coordinates":[5.92451,50.923801],"type":"Point"}
}