{
  "type": "Feature",
  "properties": {
    "addr:full":"Meanderlaan 49 Tholen Zeeland 4691 LJ",
    "addr:housenumber":"49",
    "addr:postcode":"4691 lj",
    "addr:street":"Meanderlaan",
    "iso:country":"NL",
    "sg:address":"Meanderlaan 49",
    "sg:city":"Tholen",
    "sg:orig_category":"Diverse Bedrijfsinstallaties Gh",
    "sg:phone":"+31 166 605 153",
    "sg:postcode":"4691 LJ",
    "sg:province":"Zeeland",
    "wof:name":"Allied Mineral Products Inc.",
    "wof:placetype":"venue"
},
  "geometry": {"coordinates":[4.209252,51.529007],"type":"Point"}
}