{
  "type": "Feature",
  "properties": {
    "iso:country":"NL",
    "sg:address":"Marsdiep 225",
    "sg:city":"Alphen Aan Den Ryn",
    "sg:orig_category":"Fotoreportages",
    "sg:phone":"+31 6 26346911",
    "sg:postcode":"2401 XE",
    "sg:province":"Zuid-Holland",
    "wof:name":"Say Cheese",
    "wof:placetype":"venue"
},
  "geometry": {"coordinates":[4.654675,52.146545],"type":"Point"}
}