{
  "type": "Feature",
  "properties": {
    "addr:full":"Slingerln 15 Otterlo Gelderland 6731 CL",
    "addr:housenumber":"15",
    "addr:postcode":"6731",
    "addr:street":"Slingerln;Gelderland",
    "iso:country":"NL",
    "sg:address":"Slingerln 15",
    "sg:city":"Otterlo",
    "sg:orig_category":"Betonboringen",
    "sg:phone":"+31 318 595 228",
    "sg:postcode":"6731 CL",
    "sg:province":"Gelderland",
    "wof:name":"Franjo Bv Betonboringen",
    "wof:placetype":"venue"
},
  "geometry": {"coordinates":[5.769778,52.094791],"type":"Point"}
}