{
  "type": "Feature",
  "properties": {
    "addr:full":"Draaikolk 51 Oostzaan North Holland 1511 JW",
    "addr:housenumber":"51",
    "addr:postcode":"1511 jw",
    "addr:street":"Draaikolk",
    "iso:country":"NL",
    "sg:address":"Draaikolk 51",
    "sg:city":"Oostzaan",
    "sg:orig_category":"Organisatiebureaus",
    "sg:phone":"+31 75 684 6295",
    "sg:postcode":"1511 JW",
    "sg:province":"North Holland",
    "sg:website":"http://www.riewers.nl",
    "wof:name":"Sunri Beach Unltd",
    "wof:placetype":"venue"
},
  "geometry": {"coordinates":[4.8742442131,52.4340934753],"type":"Point"}
}