{
  "type": "Feature",
  "properties": {
    "addr:full":"G Stoutwg 5 Tiel Gelderland 4005 LE",
    "addr:housenumber":"5",
    "addr:postcode":"4005 le",
    "addr:street":"Gelderland",
    "iso:country":"NL",
    "sg:address":"G Stoutwg 5",
    "sg:city":"Tiel",
    "sg:orig_category":"Onderhoudswerken",
    "sg:phone":"+31 344 612 605",
    "sg:postcode":"4005 LE",
    "sg:province":"Gelderland",
    "wof:name":"Emha Bv",
    "wof:placetype":"venue"
},
  "geometry": {"coordinates":[5.449365,51.899033],"type":"Point"}
}