{
  "type": "Feature",
  "properties": {
    "iso:country":"NL",
    "sg:address":"Damlaan 29",
    "sg:city":"Leidschendam",
    "sg:orig_category":"Verhuur Catering-, Feest- En Evenementbenodigdheden",
    "sg:phone":"+31 70 317 8800",
    "sg:postcode":"2265 AL",
    "sg:province":"Zuid-Holland",
    "wof:name":"Speelautomaten Lagerweij Bv",
    "wof:placetype":"venue"
},
  "geometry": {"coordinates":[4.395841,52.08189],"type":"Point"}
}