{
  "type": "Feature",
  "properties": {
    "iso:country":"NL",
    "sg:address":"Westeind 5D",
    "sg:city":"Rosmalen",
    "sg:orig_category":"Adviesbureaus Automatisering",
    "sg:phone":"+31 73 523 6888",
    "sg:postcode":"5245 NL",
    "sg:province":"North Brabant",
    "sg:website":"http://www.infomeester.nl",
    "wof:name":"Infomeester",
    "wof:placetype":"venue"
},
  "geometry": {"coordinates":[5.348965,51.722492],"type":"Point"}
}