{
  "type": "Feature",
  "properties": {
    "addr:full":"Paul Windhausenweg 13 Breda North Brabant 4818 TA",
    "addr:housenumber":"13",
    "addr:postcode":"4818 ta",
    "addr:street":"Paul Windhausenweg",
    "iso:country":"NL",
    "sg:address":"Paul Windhausenweg 13",
    "sg:city":"Breda",
    "sg:orig_category":"Marktonderzoekbureaus",
    "sg:phone":"+31 76 522 5249",
    "sg:postcode":"4818 TA",
    "sg:province":"North Brabant",
    "wof:name":"Delfi Bv",
    "wof:placetype":"venue"
},
  "geometry": {"coordinates":[4.785101,51.581799],"type":"Point"}
}