{
  "type": "Feature",
  "properties": {
    "iso:country":"NL",
    "sg:address":"Rochussenstr 309A",
    "sg:city":"Rotterdam",
    "sg:orig_category":"Vertalers",
    "sg:phone":"+31 10 477 7041",
    "sg:postcode":"3023 DG",
    "sg:province":"Zuid-Holland",
    "wof:name":"Econ Bv",
    "wof:placetype":"venue"
},
  "geometry": {"coordinates":[4.4556,51.909313],"type":"Point"}
}