{
  "type": "Feature",
  "properties": {
    "addr:full":"Postbus 44 Zwyndrecht 3330 AA",
    "addr:housenumber":"44",
    "addr:postcode":"3330 aa",
    "addr:street":"Postbus",
    "iso:country":"NL",
    "sg:address":"Postbus 44",
    "sg:city":"Zwyndrecht",
    "sg:orig_category":"Kantoor- En Bedrijfsmeubelen",
    "sg:phone":"+31 78 612 5800",
    "sg:postcode":"3330 AA",
    "sg:website":"http://www.bendini.nl",
    "wof:name":"Bendini Bv",
    "wof:placetype":"venue"
},
  "geometry": {"coordinates":[4.6525402069,51.8189888],"type":"Point"}
}