{
  "type": "Feature",
  "properties": {
    "addr:full":"Herengr 8 Weesp Noord-Holland 1382 AE",
    "addr:housenumber":"8",
    "addr:postcode":"1382 ae",
    "addr:street":"Herengr",
    "iso:country":"NL",
    "sg:address":"Herengr 8",
    "sg:city":"Weesp",
    "sg:orig_category":"Medische Installaties En Instrumenten",
    "sg:phone":"+31 294 432 640",
    "sg:postcode":"1382 AE",
    "sg:province":"Noord-Holland",
    "wof:name":"Technilab Ned Bv",
    "wof:placetype":"venue"
},
  "geometry": {"coordinates":[5.042036,52.309204],"type":"Point"}
}