{
  "type": "Feature",
  "properties": {
    "addr:full":"Stichtse Rotonde 27 Amersfoort Utrecht 3818 GV",
    "addr:housenumber":"27",
    "addr:postcode":"3818 gv",
    "addr:street":"Stichtse Rotonde",
    "iso:country":"NL",
    "sg:address":"Stichtse Rotonde 27",
    "sg:city":"Amersfoort",
    "sg:orig_category":"Diverse Bedrijfsinstallaties Gh",
    "sg:phone":"+31 33 461 3115",
    "sg:postcode":"3818 GV",
    "sg:province":"Utrecht",
    "wof:name":"Internationale Handelsmij. Oskamp Bv",
    "wof:placetype":"venue"
},
  "geometry": {"coordinates":[5.359688,52.140125],"type":"Point"}
}