{
  "type": "Feature",
  "properties": {
    "addr:full":"Herenhof 94 Alphen A/D Rijn South Holland 2402 DN",
    "addr:housenumber":"94",
    "addr:postcode":"2402 dn",
    "addr:street":"Herenhof",
    "iso:country":"NL",
    "sg:address":"Herenhof 94",
    "sg:city":"Alphen A/D Rijn",
    "sg:orig_category":"Drogisterijen",
    "sg:phone":"+31 172 420 232",
    "sg:postcode":"2402 DN",
    "sg:province":"South Holland",
    "wof:name":"Da",
    "wof:placetype":"venue"
},
  "geometry": {"coordinates":[4.660858,52.151615],"type":"Point"}
}