{
  "type": "Feature",
  "properties": {
    "iso:country":"NL",
    "sg:address":"Lupinevallei 2",
    "sg:city":"S Hertogenbosch",
    "sg:orig_category":"Kantoor- En Secretariaatsservice",
    "sg:phone":"+31 73 645 0765",
    "sg:postcode":"5237 MB",
    "sg:province":"Noord-Brabant",
    "wof:name":"Mdg",
    "wof:placetype":"venue"
},
  "geometry": {"coordinates":[5.2924799919,51.726184845],"type":"Point"}
}