{
  "type": "Feature",
  "properties": {
    "addr:full":"Molenmakershoek 3 Apeldoorn Gelderland 7328 JK",
    "addr:housenumber":"3",
    "addr:postcode":"7328 jk",
    "addr:street":"Molenmakershoek;Gelderland",
    "iso:country":"NL",
    "sg:address":"Molenmakershoek 3",
    "sg:city":"Apeldoorn",
    "sg:orig_category":"Wegenbouw",
    "sg:phone":"+31 55 539 6767",
    "sg:postcode":"7328 JK",
    "sg:province":"Gelderland",
    "wof:name":"Bam Nbm Wegenbouw Noordoost Bv",
    "wof:placetype":"venue"
},
  "geometry": {"coordinates":[5.981221199,52.2071647644],"type":"Point"}
}