{
  "type": "Feature",
  "properties": {
    "addr:full":"Irenestraat 8 Dreumel Gelderland 6621 ZS",
    "addr:housenumber":"8",
    "addr:postcode":"6621 zs",
    "addr:street":"Irenestraat;Gelderland",
    "iso:country":"NL",
    "sg:address":"Irenestraat 8",
    "sg:city":"Dreumel",
    "sg:orig_category":"Metaalwerken",
    "sg:phone":"+31 487 572 681",
    "sg:postcode":"6621 ZS",
    "sg:province":"Gelderland",
    "wof:name":"Tmt Systeembouw Benelux Bv",
    "wof:placetype":"venue"
},
  "geometry": {"coordinates":[5.436665,51.849583],"type":"Point"}
}