{
  "type": "Feature",
  "properties": {
    "addr:full":"Beekstraat 7 Apeldoorn Gelderland 7311 LD",
    "addr:housenumber":"7",
    "addr:postcode":"7311 ld",
    "addr:street":"Beekstraat;Gelderland",
    "iso:country":"NL",
    "sg:address":"Beekstraat 7",
    "sg:city":"Apeldoorn",
    "sg:orig_category":"Verlichting And Huishoudartikelen",
    "sg:phone":"+31 55 521 3286",
    "sg:postcode":"7311 LD",
    "sg:province":"Gelderland",
    "wof:name":"De Koning Bv",
    "wof:placetype":"venue"
},
  "geometry": {"coordinates":[5.964471,52.213715],"type":"Point"}
}