{
  "type": "Feature",
  "properties": {
    "addr:full":"R Kochstr 114 Apeldoorn Gelderland 7316 HG",
    "addr:housenumber":"114",
    "addr:postcode":"7316 hg",
    "addr:street":"Gelderland",
    "iso:country":"NL",
    "sg:address":"R Kochstr 114",
    "sg:city":"Apeldoorn",
    "sg:orig_category":"Postorderbedrijven",
    "sg:phone":"+31 55 578 9949",
    "sg:postcode":"7316 HG",
    "sg:province":"Gelderland",
    "wof:name":"Hairfocus",
    "wof:placetype":"venue"
},
  "geometry": {"coordinates":[5.966638,52.228592],"type":"Point"}
}