{
  "type": "Feature",
  "properties": {
    "addr:full":"Heldersewg 31 Alkmaar Noord-Holland 1817 BA",
    "addr:housenumber":"31",
    "addr:postcode":"1817 ba",
    "addr:street":"Heldersewg",
    "iso:country":"NL",
    "sg:address":"Heldersewg 31",
    "sg:city":"Alkmaar",
    "sg:orig_category":"Autopoetsbedrijven",
    "sg:phone":"+31 72 520 1121",
    "sg:postcode":"1817 BA",
    "sg:province":"Noord-Holland",
    "sg:website":"http://www.starcarclean.nl",
    "wof:name":"Star, Carclean",
    "wof:placetype":"venue"
},
  "geometry": {"coordinates":[4.744227,52.642792],"type":"Point"}
}