{
  "type": "Feature",
  "properties": {
    "addr:full":"Kouwenberg 9 Aarle-Rixtel North Brabant 5753 GM",
    "addr:housenumber":"9",
    "addr:postcode":"5753 gm",
    "addr:street":"Kouwenberg",
    "iso:country":"NL",
    "sg:address":"Kouwenberg 9",
    "sg:city":"Aarle-Rixtel",
    "sg:classifiers":[
        {
            "category":"Food & Beverages",
            "subcategory":"Fruits & Vegetables",
            "type":"Retail Goods"
        }
    ],
    "sg:phone":"+31 492 384 358",
    "sg:postcode":"5753 GM",
    "sg:province":"North Brabant",
    "sg:tags":[
        "groenten"
    ],
    "wof:name":"De Echte Groenteboer",
    "wof:placetype":"venue"
},
  "geometry": {"coordinates":[5.638002,51.509285],"type":"Point"}
}