{
  "type": "Feature",
  "properties": {
    "addr:full":"Enghuusweg 15 Putten Gelderland 3882 ML",
    "addr:housenumber":"15",
    "addr:postcode":"3882 ml",
    "addr:street":"Enghuusweg;Gelderland",
    "iso:country":"NL",
    "sg:address":"Enghuusweg 15",
    "sg:city":"Putten",
    "sg:orig_category":"Zuivelproducten And Spijsoli?n Gh",
    "sg:phone":"+31 341 354 558",
    "sg:postcode":"3882 ML",
    "sg:province":"Gelderland",
    "wof:name":"Firma S.E.P. Eieren",
    "wof:placetype":"venue"
},
  "geometry": {"coordinates":[5.587292,52.25555],"type":"Point"}
}