{
  "type": "Feature",
  "properties": {
    "addr:full":"Dorpsstr 12 Kiel Windeweer Groningen 9605 PA",
    "addr:housenumber":"12",
    "addr:postcode":"9605 pa",
    "addr:street":"Dorpsstr",
    "iso:country":"NL",
    "sg:address":"Dorpsstr 12",
    "sg:city":"Kiel Windeweer",
    "sg:orig_category":"Land- En Tuinbouw - Loonbedrijven",
    "sg:phone":"+31 598 491 241",
    "sg:postcode":"9605 PA",
    "sg:province":"Groningen",
    "wof:name":"Kamphuis Loonbedrijf, J A",
    "wof:placetype":"venue"
},
  "geometry": {"coordinates":[6.772031,53.121849],"type":"Point"}
}