{
  "type": "Feature",
  "properties": {
    "iso:country":"NL",
    "sg:address":"A Paulownastr 1",
    "sg:city":"Eindhoven",
    "sg:orig_category":"Autoreclame",
    "sg:phone":"+31 40 252 6206",
    "sg:postcode":"5616 AX",
    "sg:province":"Noord-Brabant",
    "sg:website":"http://www.vanstiphoutreklame.nl",
    "wof:name":"Stiphout, Van",
    "wof:placetype":"venue"
},
  "geometry": {"coordinates":[5.466167,51.434948],"type":"Point"}
}