{
  "type": "Feature",
  "properties": {
    "addr:full":"Ekkersrijt 1321 Son Flevoland 5692 AJ",
    "addr:housenumber":"1321",
    "addr:postcode":"5692 aj",
    "addr:street":"Ekkersrijt;Flevoland",
    "iso:country":"NL",
    "sg:address":"Ekkersrijt 1321",
    "sg:city":"Son",
    "sg:orig_category":"Autokeuringen",
    "sg:phone":"+31 499 460 259",
    "sg:postcode":"5692 AJ",
    "sg:province":"Flevoland",
    "wof:name":"J Holscher Autobedrijf",
    "wof:placetype":"venue"
},
  "geometry": {"coordinates":[-101.937622,35.189621],"type":"Point"}
}