{
  "type": "Feature",
  "properties": {
    "iso:country":"NL",
    "sg:address":"R. Holstlaan 772",
    "sg:city":"Delft",
    "sg:orig_category":"Werving And Selectie Van Tijdelijk Personeel And Uitzendkantoren",
    "sg:phone":"+31 15 256 6520",
    "sg:postcode":"2624 JE",
    "sg:province":"Zuid-Holland",
    "wof:name":"Bartus Bv",
    "wof:placetype":"venue"
},
  "geometry": {"coordinates":[4.3544077873,51.9937477112],"type":"Point"}
}