{
  "type": "Feature",
  "properties": {
    "addr:full":"Willibrordusln 50A Waalre North Brabant 5581 GG",
    "addr:housenumber":"50a",
    "addr:postcode":"5581 gg",
    "addr:street":"Willibrordusln",
    "iso:country":"NL",
    "sg:address":"Willibrordusln 50A",
    "sg:city":"Waalre",
    "sg:orig_category":"Makelaars En Adviseurs Onroerende Goederen",
    "sg:phone":"+31 40 223 1010",
    "sg:postcode":"5581 GG",
    "sg:province":"North Brabant",
    "wof:name":"Vos",
    "wof:placetype":"venue"
},
  "geometry": {"coordinates":[5.449343,51.387741],"type":"Point"}
}