{
  "type": "Feature",
  "properties": {
    "addr:full":"Randstad 2202 Almere Flevoland 1316 BX",
    "addr:housenumber":"2202",
    "addr:postcode":"1316 bx",
    "addr:street":"Flevoland",
    "iso:country":"NL",
    "sg:address":"Randstad 2202",
    "sg:city":"Almere",
    "sg:orig_category":"Kopieerservice",
    "sg:phone":"+31 36 549 5490",
    "sg:postcode":"1316 BX",
    "sg:province":"Flevoland",
    "wof:name":"Ted Gigaprint",
    "wof:placetype":"venue"
},
  "geometry": {"coordinates":[5.227952,52.378349],"type":"Point"}
}