{
  "type": "Feature",
  "properties": {
    "addr:full":"Ketelaarskampweg 17 'S Hertogenbosch Noord-Brabant 5222 AL",
    "addr:housenumber":"17",
    "addr:postcode":"5222 al",
    "addr:street":"Ketelaarskampweg;' S",
    "iso:country":"NL",
    "sg:address":"Ketelaarskampweg 17",
    "sg:city":"'S Hertogenbosch",
    "sg:orig_category":"Houten Verpakkingen Fab",
    "sg:phone":"+31 73 621 0052",
    "sg:postcode":"5222 AL",
    "sg:province":"Noord-Brabant",
    "wof:name":"The Best Barrel Bv",
    "wof:placetype":"venue"
},
  "geometry": {"coordinates":[5.276863,51.706818],"type":"Point"}
}