{
  "type": "Feature",
  "properties": {
    "addr:full":"Postbus 2067 Lelystad Flevoland 8203 AB",
    "addr:postcode":"2067;8203 ab",
    "addr:street":"Postbus;Flevoland",
    "iso:country":"NL",
    "sg:address":"Postbus 2067",
    "sg:city":"Lelystad",
    "sg:orig_category":"Arbo- En Bedrijfsgezondheids- Diensten",
    "sg:phone":"+31 320 213 491",
    "sg:postcode":"8203 AB",
    "sg:province":"Flevoland",
    "sg:website":"http://www.wachtlijsthulp.nl",
    "wof:name":"Spare Capacity Bv",
    "wof:placetype":"venue"
},
  "geometry": {"coordinates":[5.47771,52.509998],"type":"Point"}
}