{
  "type": "Feature",
  "properties": {
    "addr:full":"P Meinersstr 54 S Gravenhage Zuid-Holland 2597 VL",
    "addr:housenumber":"54;gravenhage",
    "addr:postcode":"2597 vl",
    "addr:street":"P;S",
    "iso:country":"NL",
    "sg:address":"P Meinersstr 54",
    "sg:city":"S Gravenhage",
    "sg:orig_category":"Vertaalbureaus",
    "sg:phone":"+31 70 328 1847",
    "sg:postcode":"2597 VL",
    "sg:province":"Zuid-Holland",
    "wof:name":"Foreign Language Services",
    "wof:placetype":"venue"
},
  "geometry": {"coordinates":[4.31817,52.11031],"type":"Point"}
}