{
  "type": "Feature",
  "properties": {
    "addr:full":"Jacoba Van Beierenweg 97 Voorhout Zuid-Holland 2215 KW",
    "addr:housenumber":"97",
    "addr:postcode":"2215 kw",
    "addr:street":"Jacoba Van Beierenweg",
    "iso:country":"NL",
    "sg:address":"Jacoba Van Beierenweg 97",
    "sg:city":"Voorhout",
    "sg:orig_category":"Diverse Grafische Activiteiten",
    "sg:phone":"+31 252 223 200",
    "sg:postcode":"2215 KW",
    "sg:province":"Zuid-Holland",
    "wof:name":"Colorscan I L Bv",
    "wof:placetype":"venue"
},
  "geometry": {"coordinates":[4.50531,52.237095],"type":"Point"}
}