{
  "type": "Feature",
  "properties": {
    "iso:country":"NL",
    "sg:address":"Keltenoord 73",
    "sg:city":"Rotterdam",
    "sg:orig_category":"Begrafenisondernemers",
    "sg:phone":"+31 10 292 7141",
    "sg:postcode":"3079 ZD",
    "sg:province":"Zuid-Holland",
    "wof:name":"G.A. De Kramer",
    "wof:placetype":"venue"
},
  "geometry": {"coordinates":[4.559724,51.882401],"type":"Point"}
}