{
  "type": "Feature",
  "properties": {
    "iso:country":"NL",
    "sg:address":"Thomas De Keyserstraat 15",
    "sg:city":"Enschede",
    "sg:orig_category":"Huishoudapparatuur, Televisies And Radio'S",
    "sg:phone":"+31 53 434 0944",
    "sg:postcode":"7545 BA",
    "sg:province":"Overijssel",
    "wof:name":"De Veelzijdige Winkel",
    "wof:placetype":"venue"
},
  "geometry": {"coordinates":[6.8607,52.214352],"type":"Point"}
}