{
  "type": "Feature",
  "properties": {
    "iso:country":"NL",
    "sg:address":"Van Veldekekade 352",
    "sg:city":"'S Hertogenbosch",
    "sg:orig_category":"Mobiele Service Aan Motorvoertuigen",
    "sg:phone":"+31 73 613 7521",
    "sg:postcode":"5216 KT",
    "sg:province":"Noord-Brabant",
    "wof:name":"Automobiel En Takelbedrijf L. Herber Bv",
    "wof:placetype":"venue"
},
  "geometry": {"coordinates":[5.326299,51.686337],"type":"Point"}
}