{
  "type": "Feature",
  "properties": {
    "addr:full":"Oldenzaalsestraat 14A Hengelo Ov Overijssel 7551 AL",
    "addr:housenumber":"14a",
    "addr:postcode":"7551 al",
    "addr:street":"Oldenzaalsestraat;Ov",
    "iso:country":"NL",
    "sg:address":"Oldenzaalsestraat 14A",
    "sg:city":"Hengelo Ov",
    "sg:orig_category":"Verenigingen En Stichtingen",
    "sg:phone":"+31 74 243 2808",
    "sg:postcode":"7551 AL",
    "sg:province":"Overijssel",
    "wof:name":"Popbelang Hengelo, Ver",
    "wof:placetype":"venue"
},
  "geometry": {"coordinates":[6.795328,52.267673],"type":"Point"}
}