{
  "type": "Feature",
  "properties": {
    "addr:full":"Hobelmansdijk 5 Zelhem Gelderland 7021 HS",
    "addr:housenumber":"5",
    "addr:postcode":"7021 hs",
    "addr:street":"Hobelmansdijk;Gelderland",
    "iso:country":"NL",
    "sg:address":"Hobelmansdijk 5",
    "sg:city":"Zelhem",
    "sg:orig_category":"Musea And Historische Gebouwen",
    "sg:phone":"+31 314 632 091",
    "sg:postcode":"7021 HS",
    "sg:province":"Gelderland",
    "wof:name":"Via Nova",
    "wof:placetype":"venue"
},
  "geometry": {"coordinates":[6.350575,52.006802],"type":"Point"}
}