{
  "type": "Feature",
  "properties": {
    "addr:full":"Dukdalfweg 23 Almere Flevoland 1332 BJ",
    "addr:housenumber":"23",
    "addr:postcode":"1332 bj",
    "addr:street":"Dukdalfweg;Flevoland",
    "iso:country":"NL",
    "sg:address":"Dukdalfweg 23",
    "sg:city":"Almere",
    "sg:orig_category":"Huizensloop And Bouwrijp Maken",
    "sg:phone":"+31 36 532 8293",
    "sg:postcode":"1332 BJ",
    "sg:province":"Flevoland",
    "wof:name":"Ljungby Maskin Nederland Bv",
    "wof:placetype":"venue"
},
  "geometry": {"coordinates":[5.255575,52.409382],"type":"Point"}
}