{
  "type": "Feature",
  "properties": {
    "addr:full":"Oude Doesburgsewg 40 Zevenaar Gelderland 6901 HK",
    "addr:housenumber":"40",
    "addr:postcode":"6901 hk",
    "addr:street":"Oude Doesburgsewg",
    "iso:country":"NL",
    "sg:address":"Oude Doesburgsewg 40",
    "sg:city":"Zevenaar",
    "sg:orig_category":"Machinefabrieken",
    "sg:phone":"+31 316 524 679",
    "sg:postcode":"6901 HK",
    "sg:province":"Gelderland",
    "wof:name":"Reus Zevenaar, De",
    "wof:placetype":"venue"
},
  "geometry": {"coordinates":[6.076348,51.933006],"type":"Point"}
}