{
  "type": "Feature",
  "properties": {
    "addr:full":"Van Slingelandtplein 8 Amsterdam North Holland 1051 DD",
    "addr:housenumber":"8",
    "addr:postcode":"1051 dd",
    "addr:street":"Van Slingelandtplein",
    "iso:country":"NL",
    "sg:address":"Van Slingelandtplein 8",
    "sg:city":"Amsterdam",
    "sg:orig_category":"Verf En Lak - Fabrieken En Groothandel",
    "sg:phone":"+31 20 618 2486",
    "sg:postcode":"1051 DD",
    "sg:province":"North Holland",
    "sg:website":"http://www.jonkerverf.nl",
    "wof:name":"Jonker En Co, Fa Th",
    "wof:placetype":"venue"
},
  "geometry": {"coordinates":[4.866187,52.382393],"type":"Point"}
}