{
  "type": "Feature",
  "properties": {
    "addr:full":"Betuwe Sngl 14 Lienden Gelderland 4033 KN",
    "addr:housenumber":"14",
    "addr:postcode":"4033 kn",
    "addr:street":"Sngl;Gelderland",
    "iso:country":"NL",
    "sg:address":"Betuwe Sngl 14",
    "sg:city":"Lienden",
    "sg:orig_category":"Optische Instrumenten",
    "sg:phone":"+31 344 604 340",
    "sg:postcode":"4033 KN",
    "sg:province":"Gelderland",
    "sg:website":"http://www.aquariusoptics.com",
    "wof:name":"Aquarius",
    "wof:placetype":"venue"
},
  "geometry": {"coordinates":[5.4951410294,51.923664093],"type":"Point"}
}