{
  "type": "Feature",
  "properties": {
    "addr:full":"Postbus 4025 Oosterhout Nb 4900 CA",
    "addr:postcode":"4025;4900 ca",
    "addr:street":"Postbus",
    "iso:country":"NL",
    "sg:address":"Postbus 4025",
    "sg:city":"Oosterhout Nb",
    "sg:orig_category":"Grafische Bedrijven",
    "sg:phone":"+31 162 422 629",
    "sg:postcode":"4900 CA",
    "wof:name":"Simons & Partn Bv",
    "wof:placetype":"venue"
},
  "geometry": {"coordinates":[4.8562498093,51.6430511475],"type":"Point"}
}