{
  "type": "Feature",
  "properties": {
    "iso:country":"NL",
    "sg:address":"Boompjesstraat 39",
    "sg:city":"Strijen",
    "sg:orig_category":"Wegen And Sportterreinen",
    "sg:phone":"+31 78 674 1433",
    "sg:postcode":"3291 AA",
    "sg:province":"Zuid-Holland",
    "wof:name":"Aannemingsbedrijf Buitendijk Strijen Bv",
    "wof:placetype":"venue"
},
  "geometry": {"coordinates":[4.5517821312,51.7416267395],"type":"Point"}
}