{
  "type": "Feature",
  "properties": {
    "iso:country":"NL",
    "sg:address":"Kerklaan 48",
    "sg:city":"Groningen",
    "sg:orig_category":"Muziekinstrumenten",
    "sg:phone":"+31 50 314 4170",
    "sg:postcode":"9717 HG",
    "sg:province":"Groningen",
    "wof:name":"Xander Niezing Pianostemmer",
    "wof:placetype":"venue"
},
  "geometry": {"coordinates":[6.552258,53.224716],"type":"Point"}
}