{
  "type": "Feature",
  "properties": {
    "addr:full":"Goudplevierwg 5 Heusden Gem Asten North Brabant 5725 RK",
    "addr:housenumber":"5",
    "addr:postcode":"5725 rk",
    "addr:street":"Goudplevierwg",
    "iso:country":"NL",
    "sg:address":"Goudplevierwg 5",
    "sg:city":"Heusden Gem Asten",
    "sg:orig_category":"Adviesbureaus Bedrijfsorganisatie",
    "sg:phone":"+31 493 560 580",
    "sg:postcode":"5725 RK",
    "sg:province":"North Brabant",
    "wof:name":"W & G Mkb Advies",
    "wof:placetype":"venue"
},
  "geometry": {"coordinates":[5.795062,51.364723],"type":"Point"}
}