{
  "type": "Feature",
  "properties": {
    "iso:country":"NL",
    "sg:address":"Goudplevierwg 5",
    "sg:city":"Heusden Gem Asten",
    "sg:orig_category":"Adviesbureaus Bedrijfsorganisatie",
    "sg:phone":"+31 493 560 580",
    "sg:postcode":"5725 RK",
    "sg:province":"North Brabant",
    "wof:name":"W & G Mkb Advies",
    "wof:placetype":"venue"
},
  "geometry": {"coordinates":[5.795062,51.364723],"type":"Point"}
}