{
  "type": "Feature",
  "properties": {
    "addr:full":"Leeuwarderkd 9 Sneek Friesland 8603 CB",
    "addr:housenumber":"9",
    "addr:postcode":"8603 cb",
    "addr:street":"Leeuwarderkd",
    "iso:country":"NL",
    "sg:address":"Leeuwarderkd 9",
    "sg:city":"Sneek",
    "sg:orig_category":"Watersportartikelen",
    "sg:phone":"+31 515 420 488",
    "sg:postcode":"8603 CB",
    "sg:province":"Friesland",
    "wof:name":"Nostrum, Mare",
    "wof:placetype":"venue"
},
  "geometry": {"coordinates":[5.6619701385,53.0334587097],"type":"Point"}
}