{
  "type": "Feature",
  "properties": {
    "addr:full":"Grt Houtstr 108Rd Haarlem Noord-Holland 2011 ST",
    "addr:housenumber":"108rd",
    "addr:postcode":"2011 st",
    "addr:street":"Houtstr",
    "iso:country":"NL",
    "sg:address":"Grt Houtstr 108Rd",
    "sg:city":"Haarlem",
    "sg:classifiers":[
        {
            "category":"Utilities",
            "subcategory":"Cable",
            "type":"Services"
        }
    ],
    "sg:phone":"+31 23 532 5037",
    "sg:postcode":"2011 ST",
    "sg:province":"Noord-Holland",
    "sg:tags":[
        "masseur",
        "en",
        "heilgymnasten"
    ],
    "wof:name":"Ronde Hoek, De",
    "wof:placetype":"venue"
},
  "geometry": {"coordinates":[4.642253,52.380562],"type":"Point"}
}