{
  "type": "Feature",
  "properties": {
    "addr:full":"Molenakker 20 Vught Noord-Brabant 5262 EV",
    "addr:housenumber":"20",
    "addr:postcode":"5262 ev",
    "addr:street":"Molenakker",
    "iso:country":"NL",
    "sg:address":"Molenakker 20",
    "sg:city":"Vught",
    "sg:orig_category":"Sanitaire Artikelen",
    "sg:phone":"+31 6 53835342",
    "sg:postcode":"5262 EV",
    "sg:province":"Noord-Brabant",
    "sg:website":"http://www.leluxbadkamers.nl",
    "wof:name":"Le Lux",
    "wof:placetype":"venue"
},
  "geometry": {"coordinates":[5.297663,51.660519],"type":"Point"}
}