{
  "type": "Feature",
  "properties": {
    "addr:full":"Industriewg 23 Zierikzee Zeeland 4301 RS",
    "addr:housenumber":"23",
    "addr:postcode":"4301 rs",
    "addr:street":"Industriewg",
    "iso:country":"NL",
    "sg:address":"Industriewg 23",
    "sg:city":"Zierikzee",
    "sg:orig_category":"Makelaars En Adviseurs Baggermaterialen",
    "sg:phone":"+31 111 456 100",
    "sg:postcode":"4301 RS",
    "sg:province":"Zeeland",
    "sg:website":"http://www.seatec.nl",
    "wof:name":"Seatec Bv",
    "wof:placetype":"venue"
},
  "geometry": {"coordinates":[3.9212,51.642624],"type":"Point"}
}