{
  "type": "Feature",
  "properties": {
    "addr:full":"Limburgstr 16 Geleen Limburg 6164 EL",
    "addr:housenumber":"16",
    "addr:postcode":"6164 el",
    "addr:street":"Limburgstr",
    "iso:country":"NL",
    "sg:address":"Limburgstr 16",
    "sg:city":"Geleen",
    "sg:orig_category":"Bloemen En Planten",
    "sg:phone":"+31 46 474 4051",
    "sg:postcode":"6164 EL",
    "sg:province":"Limburg",
    "wof:name":"Koll?, G",
    "wof:placetype":"venue"
},
  "geometry": {"coordinates":[5.833197,50.950439],"type":"Point"}
}