{
  "type": "Feature",
  "properties": {
    "iso:country":"NL",
    "sg:address":"Moerbeibloesem 40",
    "sg:city":"Doetinchem",
    "sg:orig_category":"Verzekeringen - Verzekeringskantoren",
    "sg:phone":"+31 314 325 794",
    "sg:postcode":"7006 MN",
    "sg:province":"Gelderland",
    "wof:name":"Peters, W",
    "wof:placetype":"venue"
},
  "geometry": {"coordinates":[6.256785,51.961758],"type":"Point"}
}