{
  "type": "Feature",
  "properties": {
    "addr:full":"Bottenhoeksewg 3 Teuge Gelderland 7395 SC",
    "addr:housenumber":"3",
    "addr:postcode":"7395",
    "addr:street":"Bottenhoeksewg;Gelderland",
    "iso:country":"NL",
    "sg:address":"Bottenhoeksewg 3",
    "sg:city":"Teuge",
    "sg:orig_category":"Land- En Tuinbouw - Loonbedrijven",
    "sg:phone":"+31 55 323 1484",
    "sg:postcode":"7395 SC",
    "sg:province":"Gelderland",
    "wof:name":"Nikkels, Fa",
    "wof:placetype":"venue"
},
  "geometry": {"coordinates":[6.056367,52.228107],"type":"Point"}
}