{
  "type": "Feature",
  "properties": {
    "addr:full":"Pr Bernhardln 10 Diemen Noord-Holland 1111 ET",
    "addr:housenumber":"10",
    "addr:postcode":"1111 et",
    "iso:country":"NL",
    "sg:address":"Pr Bernhardln 10",
    "sg:city":"Diemen",
    "sg:orig_category":"Peuterspeelzalen",
    "sg:phone":"+31 20 699 9313",
    "sg:postcode":"1111 ET",
    "sg:province":"Noord-Holland",
    "wof:name":"Speelhuis, Het",
    "wof:placetype":"venue"
},
  "geometry": {"coordinates":[4.964805,52.34132],"type":"Point"}
}