{
  "type": "Feature",
  "properties": {
    "addr:full":"Staalwg 12 Culemborg Gelderland 4104 AT",
    "addr:housenumber":"12",
    "addr:postcode":"4104",
    "addr:street":"Staalwg;Gelderland",
    "iso:country":"NL",
    "sg:address":"Staalwg 12",
    "sg:city":"Culemborg",
    "sg:orig_category":"Automaterialen En Gereedschappen",
    "sg:phone":"+31 345 517 594",
    "sg:postcode":"4104 AT",
    "sg:province":"Gelderland",
    "wof:name":"Go Wammes",
    "wof:placetype":"venue"
},
  "geometry": {"coordinates":[5.218843,51.943607],"type":"Point"}
}