{
  "type": "Feature",
  "properties": {
    "addr:full":"Soerabaiastraat 5 Enschede Overijssel 7512 ZX",
    "addr:housenumber":"5",
    "addr:postcode":"7512 zx",
    "addr:street":"Soerabaiastraat",
    "iso:country":"NL",
    "sg:address":"Soerabaiastraat 5",
    "sg:city":"Enschede",
    "sg:orig_category":"Marktonderzoekbureaus",
    "sg:phone":"+31 53 436 0217",
    "sg:postcode":"7512 ZX",
    "sg:province":"Overijssel",
    "wof:name":"Bur Bosch",
    "wof:placetype":"venue"
},
  "geometry": {"coordinates":[6.902002,52.213314],"type":"Point"}
}