{
  "type": "Feature",
  "properties": {
    "iso:country":"NL",
    "sg:address":"Pioniersweg 21",
    "sg:city":"Emmen",
    "sg:orig_category":"Meubels And Huishoudapparatuur Gh",
    "sg:phone":"+31 591 620 620",
    "sg:postcode":"7826 TA",
    "sg:province":"Provincie Drenthe",
    "wof:name":"Promaxa Bv",
    "wof:placetype":"venue"
},
  "geometry": {"coordinates":[6.954281,52.777374],"type":"Point"}
}