{
  "type": "Feature",
  "properties": {
    "iso:country":"NL",
    "sg:address":"Azuurmees 43",
    "sg:city":"Uithoorn",
    "sg:orig_category":"Kappers",
    "sg:phone":"+31 297 531 080",
    "sg:postcode":"1423 PC",
    "sg:province":"North Holland",
    "wof:name":"Janine'S Thuiskappersservice",
    "wof:placetype":"venue"
},
  "geometry": {"coordinates":[4.8097891808,52.2377853394],"type":"Point"}
}