{
  "type": "Feature",
  "properties": {
    "iso:country":"NL",
    "sg:address":"Doornburgln 17",
    "sg:city":"Utrecht",
    "sg:orig_category":"Opticiens",
    "sg:phone":"+31 30 244 3089",
    "sg:postcode":"3554 EP",
    "sg:province":"Utrecht",
    "sg:website":"http://www.pearle.nl",
    "wof:name":"Pearle",
    "wof:placetype":"venue"
},
  "geometry": {"coordinates":[5.0894751549,52.1134033203],"type":"Point"}
}