{
  "type": "Feature",
  "properties": {
    "addr:full":"Lagedk 4B Helmond North Brabant 5705 BZ",
    "addr:housenumber":"4b",
    "addr:postcode":"5705 bz",
    "addr:street":"Lagedk",
    "iso:country":"NL",
    "sg:address":"Lagedk 4B",
    "sg:city":"Helmond",
    "sg:orig_category":"Metaalgroothandel",
    "sg:phone":"+31 492 582 111",
    "sg:postcode":"5705 BZ",
    "sg:province":"North Brabant",
    "wof:name":"Noxon Bv",
    "wof:placetype":"venue"
},
  "geometry": {"coordinates":[5.678633,51.470711],"type":"Point"}
}