{
  "type": "Feature",
  "properties": {
    "iso:country":"NL",
    "sg:address":"Industrieweg 7",
    "sg:city":"Maartensdijk",
    "sg:orig_category":"Metaalbekleding And -Behandeling",
    "sg:phone":"+31 346 211 489",
    "sg:postcode":"3738 JW",
    "sg:province":"Utrecht",
    "wof:name":"Bv Metaalwarenfabriek De Papierklem",
    "wof:placetype":"venue"
},
  "geometry": {"coordinates":[5.167151,52.160072],"type":"Point"}
}