{
  "type": "Feature",
  "properties": {
    "addr:full":"Stationstr 20-22 Simpelveld Limburg 6369 VJ",
    "addr:housenumber":"20-22",
    "addr:postcode":"simpelveld;6369 vj",
    "iso:country":"NL",
    "sg:address":"Stationstr 20-22",
    "sg:city":"Simpelveld",
    "sg:orig_category":"Recreatie",
    "sg:phone":"+31 45 544 0018",
    "sg:postcode":"6369 VJ",
    "sg:province":"Limburg",
    "sg:website":"http://www.zlsm.nl",
    "wof:name":"Zuid Limb Stoomtreinmij Zlsm",
    "wof:placetype":"venue"
},
  "geometry": {"coordinates":[5.982154,50.83474],"type":"Point"}
}