{
  "type": "Feature",
  "properties": {
    "addr:full":"Hammerstraat 44 Epe Gelderland 8161 PH",
    "addr:housenumber":"44",
    "addr:postcode":"8161",
    "addr:street":"Hammerstraat;Gelderland",
    "iso:country":"NL",
    "sg:address":"Hammerstraat 44",
    "sg:city":"Epe",
    "sg:orig_category":"Huizensloop And Bouwrijp Maken",
    "sg:phone":"+31 578 612 748",
    "sg:postcode":"8161 PH",
    "sg:province":"Gelderland",
    "wof:name":"W.A. Rikken En Zonen",
    "wof:placetype":"venue"
},
  "geometry": {"coordinates":[5.999221,52.344704],"type":"Point"}
}