{
  "type": "Feature",
  "properties": {
    "addr:full":"H Mesdagstr 2 Deurne Noord-Brabant 5753 DA",
    "addr:housenumber":"2",
    "addr:postcode":"5753 da",
    "iso:country":"NL",
    "sg:address":"H Mesdagstr 2",
    "sg:city":"Deurne",
    "sg:orig_category":"Product-Promotie",
    "sg:phone":"+31 493 310 000",
    "sg:postcode":"5753 DA",
    "sg:province":"Noord-Brabant",
    "wof:name":"Pullshaw & Roos Bv",
    "wof:placetype":"venue"
},
  "geometry": {"coordinates":[5.79635,51.451401],"type":"Point"}
}