{
  "type": "Feature",
  "properties": {
    "addr:full":"Meer En Duin 40 Lisse Zuid-Holland 2163 HC",
    "addr:housenumber":"40",
    "addr:postcode":"2163 hc",
    "addr:street":"Meer En Duin",
    "iso:country":"NL",
    "sg:address":"Meer En Duin 40",
    "sg:city":"Lisse",
    "sg:orig_category":"Verpakkingsmachines",
    "sg:phone":"+31 252 419 149",
    "sg:postcode":"2163 HC",
    "sg:province":"Zuid-Holland",
    "wof:name":"Certos Holl Bv",
    "wof:placetype":"venue"
},
  "geometry": {"coordinates":[4.563872,52.268749],"type":"Point"}
}