{
  "type": "Feature",
  "properties": {
    "addr:full":"Kruisweg 983 Hoofddorp Noord-Holland 2132 CE",
    "addr:housenumber":"983",
    "addr:postcode":"2132 ce",
    "addr:street":"Kruisweg",
    "iso:country":"NL",
    "sg:address":"Kruisweg 983",
    "sg:city":"Hoofddorp",
    "sg:orig_category":"Opticiens",
    "sg:phone":"+31 23 563 7106",
    "sg:postcode":"2132 CE",
    "sg:province":"Noord-Holland",
    "wof:name":"Pearle Opticiens",
    "wof:placetype":"venue"
},
  "geometry": {"coordinates":[4.6964578629,52.3037376404],"type":"Point"}
}