{
  "type": "Feature",
  "properties": {
    "addr:full":"Binnenwatersloot 17 Delft South Holland 2611 BJ",
    "addr:housenumber":"17",
    "addr:postcode":"2611 bj",
    "addr:street":"Binnenwatersloot",
    "iso:country":"NL",
    "sg:address":"Binnenwatersloot 17",
    "sg:city":"Delft",
    "sg:orig_category":"Verzekeringen - Verzekeringskantoren",
    "sg:phone":"+31 15 213 9810",
    "sg:postcode":"2611 BJ",
    "sg:province":"South Holland",
    "sg:website":"http://www.de-assurantieshop.nl",
    "wof:name":"Assurantieshop, De",
    "wof:placetype":"venue"
},
  "geometry": {"coordinates":[4.356591,52.009537],"type":"Point"}
}