{
  "type": "Feature",
  "properties": {
    "addr:full":"Veemarktkd 8 S Hertogenbosch Noord-Brabant 5222 AE",
    "addr:housenumber":"8",
    "addr:postcode":"5222 ae",
    "addr:street":"Veemarktkd",
    "iso:country":"NL",
    "sg:address":"Veemarktkd 8",
    "sg:city":"S Hertogenbosch",
    "sg:orig_category":"Betonijzervlechten",
    "sg:phone":"+31 73 623 7246",
    "sg:postcode":"5222 AE",
    "sg:province":"Noord-Brabant",
    "wof:name":"Spierings-Zeegers Bv",
    "wof:placetype":"venue"
},
  "geometry": {"coordinates":[5.286278,51.703072],"type":"Point"}
}