{
  "type": "Feature",
  "properties": {
    "addr:full":"De Gildekamp 2032 Nijmegen Gelderland 6545 KD",
    "addr:housenumber":"2032",
    "addr:postcode":"6545 kd",
    "addr:street":"De Gildekamp;Gelderland",
    "iso:country":"NL",
    "sg:address":"De Gildekamp 2032",
    "sg:city":"Nijmegen",
    "sg:orig_category":"Public Relationbureaus",
    "sg:phone":"+31 24 379 0566",
    "sg:postcode":"6545 KD",
    "sg:province":"Gelderland",
    "wof:name":"Pangea Press Agency",
    "wof:placetype":"venue"
},
  "geometry": {"coordinates":[5.798687,51.830002],"type":"Point"}
}