{
  "type": "Feature",
  "properties": {
    "addr:full":"Grotenhoekln 31 Zuidland Zuid-Holland 3214 TJ",
    "addr:housenumber":"31",
    "addr:postcode":"3214 tj",
    "addr:street":"Grotenhoekln",
    "iso:country":"NL",
    "sg:address":"Grotenhoekln 31",
    "sg:city":"Zuidland",
    "sg:orig_category":"Jachten - Schilderwerken En Onderhoud",
    "sg:phone":"+31 181 452 809",
    "sg:postcode":"3214 TJ",
    "sg:province":"Zuid-Holland",
    "wof:name":"Dam, Van",
    "wof:placetype":"venue"
},
  "geometry": {"coordinates":[4.255939,51.826],"type":"Point"}
}