{
  "type": "Feature",
  "properties": {
    "addr:full":"Heivlinder 29 Leiden Zuid-Holland 2317 JS",
    "addr:housenumber":"29",
    "addr:postcode":"2317 js",
    "addr:street":"Heivlinder",
    "iso:country":"NL",
    "sg:address":"Heivlinder 29",
    "sg:city":"Leiden",
    "sg:orig_category":"Administratie- En Boekhoudkantoren",
    "sg:phone":"+31 71 523 0274",
    "sg:postcode":"2317 JS",
    "sg:province":"Zuid-Holland",
    "wof:name":"Asa",
    "wof:placetype":"venue"
},
  "geometry": {"coordinates":[4.511145,52.179825],"type":"Point"}
}