{
  "type": "Feature",
  "properties": {
    "addr:full":"Hoofdstraat 57 Apeldoorn Gelderland 7311 JV",
    "addr:housenumber":"57",
    "addr:postcode":"7311 jv",
    "addr:street":"Hoofdstraat;Gelderland",
    "iso:country":"NL",
    "sg:address":"Hoofdstraat 57",
    "sg:city":"Apeldoorn",
    "sg:classifiers":[
        {
            "category":"Fast Food",
            "type":"Food & Drink"
        }
    ],
    "sg:phone":"+31 55 521 7816",
    "sg:postcode":"7311 JV",
    "sg:province":"Gelderland",
    "sg:tags":[
        "afhaal",
        "restaurant"
    ],
    "wof:name":"Snackbar Appy Happy",
    "wof:placetype":"venue"
},
  "geometry": {"coordinates":[5.964641,52.212299],"type":"Point"}
}