{
  "type": "Feature",
  "properties": {
    "iso:country":"NL",
    "sg:address":"K Muiderwg 14",
    "sg:city":"Weesp",
    "sg:orig_category":"Verzekeringen - Verzekeringskantoren",
    "sg:phone":"+31 294 490 000",
    "sg:postcode":"1382 LS",
    "sg:province":"Noord-Holland",
    "wof:name":"Wijngaarden, Van",
    "wof:placetype":"venue"
},
  "geometry": {"coordinates":[5.052232,52.316906],"type":"Point"}
}