{
  "type": "Feature",
  "properties": {
    "addr:full":"Ketelweg 28 Papendrecht South Holland 3356 LE",
    "addr:housenumber":"28",
    "addr:postcode":"3356 le",
    "addr:street":"Ketelweg",
    "iso:country":"NL",
    "sg:address":"Ketelweg 28",
    "sg:city":"Papendrecht",
    "sg:orig_category":"Warmtetechniek",
    "sg:phone":"+31 78 641 7864",
    "sg:postcode":"3356 LE",
    "sg:province":"South Holland",
    "sg:website":"http://www.heat-engineering.nl",
    "wof:name":"Heat Engineering Bv",
    "wof:placetype":"venue"
},
  "geometry": {"coordinates":[4.7252058983,51.8282089233],"type":"Point"}
}