{
  "type": "Feature",
  "properties": {
    "addr:full":"Frank Van Borselenstraat 8 Delft Zuid-Holland 2613 NL",
    "addr:housenumber":"8",
    "addr:postcode":"2613 nl",
    "addr:street":"Frank Van Borselenstraat",
    "iso:country":"NL",
    "sg:address":"Frank Van Borselenstraat 8",
    "sg:city":"Delft",
    "sg:orig_category":"Koeriersdiensten",
    "sg:phone":"+31 15 212 3368",
    "sg:postcode":"2613 NL",
    "sg:province":"Zuid-Holland",
    "wof:name":"Koeriersdienst Van Den Ende",
    "wof:placetype":"venue"
},
  "geometry": {"coordinates":[4.353373,52.004532],"type":"Point"}
}