{
  "type": "Feature",
  "properties": {
    "addr:full":"Krekelveldstraat 7 Venlo Limburg 5912 GA",
    "addr:housenumber":"7",
    "addr:postcode":"5912 ga",
    "addr:street":"Krekelveldstraat",
    "iso:country":"NL",
    "sg:address":"Krekelveldstraat 7",
    "sg:city":"Venlo",
    "sg:orig_category":"Kappers",
    "sg:phone":"+31 77 351 2693",
    "sg:postcode":"5912 GA",
    "sg:province":"Limburg",
    "wof:name":"Dames- En Herenkapsalon H.W.A. Titulaer",
    "wof:placetype":"venue"
},
  "geometry": {"coordinates":[6.1696710587,51.3611907959],"type":"Point"}
}