{
  "type": "Feature",
  "properties": {
    "iso:country":"NL",
    "sg:address":"Eemhavenweg 18",
    "sg:city":"Rotterdam",
    "sg:orig_category":"Metalen And Ertsen Gh",
    "sg:phone":"+31 10 429 6955",
    "sg:postcode":"3089 KG",
    "sg:province":"South Holland",
    "wof:name":"Haironville Nederland Bv",
    "wof:placetype":"venue"
},
  "geometry": {"coordinates":[4.417821,51.890556],"type":"Point"}
}