{
  "type": "Feature",
  "properties": {
    "addr:full":"Tenewg 22 Broeksterwoude Friesland 9108 AM",
    "addr:housenumber":"22",
    "addr:postcode":"9108",
    "addr:street":"Tenewg",
    "iso:country":"NL",
    "sg:address":"Tenewg 22",
    "sg:city":"Broeksterwoude",
    "sg:orig_category":"Beeldende Kunstenaars",
    "sg:phone":"+31 511 472 783",
    "sg:postcode":"9108 AM",
    "sg:province":"Friesland",
    "wof:name":"Jong, A J F De",
    "wof:placetype":"venue"
},
  "geometry": {"coordinates":[5.95515,53.268402],"type":"Point"}
}