{
  "type": "Feature",
  "properties": {
    "addr:full":"F Bolstr 31 Enschede Overijssel 7545 CM",
    "addr:housenumber":"31",
    "addr:postcode":"7545 cm",
    "iso:country":"NL",
    "sg:address":"F Bolstr 31",
    "sg:city":"Enschede",
    "sg:orig_category":"Fotoreportages",
    "sg:phone":"+31 6 13568382",
    "sg:postcode":"7545 CM",
    "sg:province":"Overijssel",
    "wof:name":"Hendriks, Egon",
    "wof:placetype":"venue"
},
  "geometry": {"coordinates":[6.8566,52.211689],"type":"Point"}
}