{
  "type": "Feature",
  "properties": {
    "addr:full":"Uitterlier 29 De Lier Zuid-Holland 2678 VA",
    "addr:housenumber":"29",
    "addr:postcode":"2678",
    "addr:street":"Uitterlier",
    "iso:country":"NL",
    "sg:address":"Uitterlier 29",
    "sg:city":"De Lier",
    "sg:orig_category":"Goederenvervoer Over De Weg",
    "sg:phone":"+31 174 520 891",
    "sg:postcode":"2678 VA",
    "sg:province":"Zuid-Holland",
    "wof:name":"Intern. Transp. Bedrijf E. Vd Berg Vof",
    "wof:placetype":"venue"
},
  "geometry": {"coordinates":[4.241006,51.979855],"type":"Point"}
}