{
  "type": "Feature",
  "properties": {
    "addr:full":"Molenrynseln 20 Vught North Brabant 5262 TN",
    "addr:housenumber":"20",
    "addr:postcode":"5262",
    "addr:street":"Molenrynseln",
    "iso:country":"NL",
    "sg:address":"Molenrynseln 20",
    "sg:city":"Vught",
    "sg:orig_category":"Juridische Adviseurs",
    "sg:phone":"+31 73 656 1654",
    "sg:postcode":"5262 TN",
    "sg:province":"North Brabant",
    "wof:name":"Hattum, Mr W M M Van",
    "wof:placetype":"venue"
},
  "geometry": {"coordinates":[5.279808,51.647579],"type":"Point"}
}