{
  "type": "Feature",
  "properties": {
    "addr:full":"Mr M Alewynstr 7 Hoogersmilde Drenthe 9423 RH",
    "addr:housenumber":"7",
    "addr:postcode":"9423 rh",
    "addr:street":"Mr;Alewynstr",
    "iso:country":"NL",
    "sg:address":"Mr M Alewynstr 7",
    "sg:city":"Hoogersmilde",
    "sg:classifiers":[
        {
            "category":"Sports & Exercise",
            "subcategory":"Stables",
            "type":"Entertainment"
        }
    ],
    "sg:phone":"+31 592 459 517",
    "sg:postcode":"9423 RH",
    "sg:province":"Drenthe",
    "sg:tags":[
        "maneges"
    ],
    "wof:name":"Boswal, De",
    "wof:placetype":"venue"
},
  "geometry": {"coordinates":[6.39679,52.904781],"type":"Point"}
}