{
  "type": "Feature",
  "properties": {
    "addr:full":"Esdoornstr 2 Maurik Gelderland 4021 XN",
    "addr:housenumber":"2",
    "addr:postcode":"4021 xn",
    "addr:street":"Esdoornstr;Gelderland",
    "iso:country":"NL",
    "sg:address":"Esdoornstr 2",
    "sg:city":"Maurik",
    "sg:orig_category":"Kinderopvang",
    "sg:phone":"+31 344 691 371",
    "sg:postcode":"4021 XN",
    "sg:province":"Gelderland",
    "wof:name":"Voorhuis, 'T",
    "wof:placetype":"venue"
},
  "geometry": {"coordinates":[5.417158,51.958603],"type":"Point"}
}