{
  "type": "Feature",
  "properties": {
    "addr:full":"Hoeckelsweg 23 Doornspijk Gelderland 8085 BG",
    "addr:housenumber":"23",
    "addr:postcode":"8085",
    "addr:street":"Hoeckelsweg;Gelderland",
    "iso:country":"NL",
    "sg:address":"Hoeckelsweg 23",
    "sg:city":"Doornspijk",
    "sg:orig_category":"Grondwerken",
    "sg:phone":"+31 525 662 554",
    "sg:postcode":"8085 BG",
    "sg:province":"Gelderland",
    "wof:name":"Roozeboom",
    "wof:placetype":"venue"
},
  "geometry": {"coordinates":[5.819751,52.421394],"type":"Point"}
}