{
  "type": "Feature",
  "properties": {
    "addr:full":"Soerense Zand 4A Eerbeek Gelderland 6961 LL",
    "addr:housenumber":"4a",
    "addr:postcode":"6961 ll",
    "addr:street":"Soerense Zand;Gelderland",
    "iso:country":"NL",
    "sg:address":"Soerense Zand 4A",
    "sg:city":"Eerbeek",
    "sg:classifiers":[
        {
            "category":"Wholesale",
            "subcategory":"Meat",
            "type":"Manufacturing & Wholesale Goods"
        }
    ],
    "sg:phone":"+31 313 670 170",
    "sg:postcode":"6961 LL",
    "sg:province":"Gelderland",
    "sg:tags":[
        "regeltechniek",
        "en",
        "meet-"
    ],
    "sg:website":"http://www.avantes.com",
    "wof:name":"Avantes Bv",
    "wof:placetype":"venue"
},
  "geometry": {"coordinates":[6.069558,52.101189],"type":"Point"}
}