{
  "type": "Feature",
  "properties": {
    "addr:full":"Brouwerystr 12 Wylre Limburg 6321 AG",
    "addr:housenumber":"12",
    "addr:postcode":"6321",
    "addr:street":"Brouwerystr;Limburg",
    "iso:country":"NL",
    "sg:address":"Brouwerystr 12",
    "sg:city":"Wylre",
    "sg:orig_category":"Vakantieverblijven",
    "sg:phone":"+31 43 450 1195",
    "sg:postcode":"6321 AG",
    "sg:province":"Limburg",
    "sg:website":"http://www.hagelstein-appartementen.nl",
    "wof:name":"Hagelstein",
    "wof:placetype":"venue"
},
  "geometry": {"coordinates":[5.893655,50.831451],"type":"Point"}
}