{
  "type": "Feature",
  "properties": {
    "addr:full":"Langstraat 53 Barneveld Gelderland 3771 BC",
    "addr:housenumber":"53",
    "addr:postcode":"3771 bc",
    "addr:street":"Langstraat;Gelderland",
    "iso:country":"NL",
    "sg:address":"Langstraat 53",
    "sg:city":"Barneveld",
    "sg:orig_category":"Meubelzaken, Woning- And Keukeninrichting",
    "sg:phone":"+31 342 412 134",
    "sg:postcode":"3771 BC",
    "sg:province":"Gelderland",
    "wof:name":"Bv G.J. Broekhuis & Zn",
    "wof:placetype":"venue"
},
  "geometry": {"coordinates":[5.585563,52.139294],"type":"Point"}
}