{
  "type": "Feature",
  "properties": {
    "addr:full":"Ysselmeerstr 5A Huizen Noord-Holland 1271 AA",
    "addr:housenumber":"5a",
    "addr:postcode":"1271 aa",
    "addr:street":"Ysselmeerstr",
    "iso:country":"NL",
    "sg:address":"Ysselmeerstr 5A",
    "sg:city":"Huizen",
    "sg:orig_category":"Verenigingen En Stichtingen",
    "sg:phone":"+31 35 525 7197",
    "sg:postcode":"1271 AA",
    "sg:province":"Noord-Holland",
    "wof:name":"Irene, Muziekver Pr",
    "wof:placetype":"venue"
},
  "geometry": {"coordinates":[5.239256,52.307606],"type":"Point"}
}