{
  "type": "Feature",
  "properties": {
    "addr:full":"Noorderbuurt 25D Drachten Provincie Friesland 9203 AL",
    "addr:housenumber":"25d;9203",
    "addr:postcode":"al",
    "addr:street":"Noorderbuurt;Provincie Friesland",
    "iso:country":"NL",
    "sg:address":"Noorderbuurt 25D",
    "sg:city":"Drachten",
    "sg:orig_category":"Bloemen En Planten",
    "sg:phone":"+31 512 512 463",
    "sg:postcode":"9203 AL",
    "sg:province":"Provincie Friesland",
    "wof:name":"Bouqueterie, La",
    "wof:placetype":"venue"
},
  "geometry": {"coordinates":[6.097836,53.107361],"type":"Point"}
}