{
  "type": "Feature",
  "properties": {
    "addr:full":"Oegstgeesterweg 241 Rijnsburg Zuid-Holland 2231 AV",
    "addr:housenumber":"241",
    "addr:postcode":"2231 av",
    "addr:street":"Oegstgeesterweg",
    "iso:country":"NL",
    "sg:address":"Oegstgeesterweg 241",
    "sg:city":"Rijnsburg",
    "sg:orig_category":"Boekhouders",
    "sg:phone":"+31 71 402 0219",
    "sg:postcode":"2231 AV",
    "sg:province":"Zuid-Holland",
    "wof:name":"Administratiekantoor J.C. Heemskerk",
    "wof:placetype":"venue"
},
  "geometry": {"coordinates":[4.451644,52.192299],"type":"Point"}
}