{
  "type": "Feature",
  "properties": {
    "iso:country":"NL",
    "sg:address":"Pr Marykestr 47",
    "sg:city":"Bergeyk",
    "sg:orig_category":"Kappers",
    "sg:phone":"+31 6 54311933",
    "sg:postcode":"5571 GL",
    "sg:province":"North Brabant",
    "wof:name":"Ellen",
    "wof:placetype":"venue"
},
  "geometry": {"coordinates":[5.3601350784,51.3233261108],"type":"Point"}
}