{
  "type": "Feature",
  "properties": {
    "addr:full":"Burg Meineszln 84B Rotterdam Zuid-Holland 3022 BM",
    "addr:housenumber":"84b",
    "addr:postcode":"3022 bm",
    "addr:street":"Burg Meineszln",
    "iso:country":"NL",
    "sg:address":"Burg Meineszln 84B",
    "sg:city":"Rotterdam",
    "sg:orig_category":"Kappers",
    "sg:phone":"+31 10 476 1566",
    "sg:postcode":"3022 BM",
    "sg:province":"Zuid-Holland",
    "wof:name":"Chabab",
    "wof:placetype":"venue"
},
  "geometry": {"coordinates":[4.4508361816,51.9187889099],"type":"Point"}
}