{
  "type": "Feature",
  "properties": {
    "addr:full":"Middenweydt 2 Schoorl Noord-Holland 1871 VJ",
    "addr:housenumber":"2",
    "addr:postcode":"1871 vj",
    "addr:street":"Middenweydt",
    "iso:country":"NL",
    "sg:address":"Middenweydt 2",
    "sg:city":"Schoorl",
    "sg:orig_category":"Metselwerken",
    "sg:phone":"+31 72 509 4072",
    "sg:postcode":"1871 VJ",
    "sg:province":"Noord-Holland",
    "wof:name":"Admiraal, Ruud",
    "wof:placetype":"venue"
},
  "geometry": {"coordinates":[4.697773,52.710766],"type":"Point"}
}