{
  "type": "Feature",
  "properties": {
    "iso:country":"NL",
    "sg:address":"Fazantenln 2A",
    "sg:city":"Maarn",
    "sg:orig_category":"Journalisten Freelance",
    "sg:phone":"+31 343 442 441",
    "sg:postcode":"3951 AJ",
    "sg:province":"Utrecht",
    "wof:name":"Carbit Ruro",
    "wof:placetype":"venue"
},
  "geometry": {"coordinates":[5.364913,52.061161],"type":"Point"}
}