{
  "type": "Feature",
  "properties": {
    "addr:full":"Oliemaat 8 Vlijmen Noord-Brabant 5251 AG",
    "addr:housenumber":"8",
    "addr:postcode":"5251",
    "addr:street":"Oliemaat",
    "iso:country":"NL",
    "sg:address":"Oliemaat 8",
    "sg:city":"Vlijmen",
    "sg:classifiers":[
        {
            "category":"Food & Beverages",
            "subcategory":"Fruits & Vegetables",
            "type":"Retail Goods"
        }
    ],
    "sg:phone":"+31 73 511 7297",
    "sg:postcode":"5251 AG",
    "sg:province":"Noord-Brabant",
    "sg:tags":[
        "groenten"
    ],
    "wof:name":"De Vitaminentuin",
    "wof:placetype":"venue"
},
  "geometry": {"coordinates":[5.22111,51.69426],"type":"Point"}
}