{
  "type": "Feature",
  "properties": {
    "iso:country":"NL",
    "sg:address":"Westeinde 44",
    "sg:city":"Zwaagwesteinde",
    "sg:orig_category":"Adviesbureaus Bouwkunde",
    "sg:phone":"+31 511 449 871",
    "sg:postcode":"9271 JC",
    "sg:province":"Friesland",
    "wof:name":"Wiersma, K",
    "wof:placetype":"venue"
},
  "geometry": {"coordinates":[6.027558,53.258739],"type":"Point"}
}