{
  "type": "Feature",
  "properties": {
    "addr:full":"Boterhoek 12 Best Texas 5683 AV",
    "addr:housenumber":"12",
    "addr:postcode":"5683 av",
    "addr:street":"Boterhoek",
    "iso:country":"NL",
    "sg:address":"Boterhoek 12",
    "sg:city":"Best",
    "sg:orig_category":"Videoreportages",
    "sg:phone":"+31 499 371 519",
    "sg:postcode":"5683 AV",
    "sg:province":"Texas",
    "wof:name":"Aartsen Video-Foto Reportages",
    "wof:placetype":"venue"
},
  "geometry": {"coordinates":[-101.464432,31.201506],"type":"Point"}
}