{
  "type": "Feature",
  "properties": {
    "addr:full":"Orfeoschouw 38 Zoetermeer Zuid-Holland 2726 JG",
    "addr:housenumber":"38",
    "addr:postcode":"2726 jg",
    "addr:street":"Orfeoschouw",
    "iso:country":"NL",
    "sg:address":"Orfeoschouw 38",
    "sg:city":"Zoetermeer",
    "sg:orig_category":"Werving And Selectie Van Tijdelijk Personeel And Uitzendkantoren",
    "sg:phone":"+31 79 330 1960",
    "sg:postcode":"2726 JG",
    "sg:province":"Zuid-Holland",
    "wof:name":"Luba Intermediair Bv",
    "wof:placetype":"venue"
},
  "geometry": {"coordinates":[4.4928121567,52.0648155212],"type":"Point"}
}