{
  "type": "Feature",
  "properties": {
    "addr:full":"Ambachtswg 20D Katwyk Zh South Holland 2222 AL",
    "addr:housenumber":"20d",
    "addr:postcode":"zh;2222 al",
    "addr:street":"Ambachtswg",
    "iso:country":"NL",
    "sg:address":"Ambachtswg 20D",
    "sg:city":"Katwyk Zh",
    "sg:orig_category":"Keukens",
    "sg:phone":"+31 71 402 1388",
    "sg:postcode":"2222 AL",
    "sg:province":"South Holland",
    "wof:name":"Heen Bv, 'T",
    "wof:placetype":"venue"
},
  "geometry": {"coordinates":[4.433127,52.203102],"type":"Point"}
}