{
  "type": "Feature",
  "properties": {
    "addr:full":"Keizersgr 313 Amsterdam North Holland 1016 EE",
    "addr:housenumber":"313",
    "addr:postcode":"1016 ee",
    "iso:country":"NL",
    "sg:address":"Keizersgr 313",
    "sg:city":"Amsterdam",
    "sg:orig_category":"Makelaars En Adviseurs Onroerende Goederen",
    "sg:phone":"+31 20 535 3085",
    "sg:postcode":"1016 EE",
    "sg:province":"North Holland",
    "sg:website":"http://www.parree.nl",
    "wof:name":"Parr\u00e9e Beheer Bv",
    "wof:placetype":"venue"
},
  "geometry": {"coordinates":[4.885177,52.370037],"type":"Point"}
}