{
  "type": "Feature",
  "properties": {
    "addr:full":"Trix Terwindtstraat 2 Leiden Zuid-Holland 2331 GW",
    "addr:housenumber":"2",
    "addr:postcode":"2331 gw",
    "addr:street":"Trix Terwindtstraat",
    "iso:country":"NL",
    "sg:address":"Trix Terwindtstraat 2",
    "sg:city":"Leiden",
    "sg:orig_category":"Kinderopvang Behalve Thuis",
    "sg:phone":"+31 71 531 8089",
    "sg:postcode":"2331 GW",
    "sg:province":"Zuid-Holland",
    "wof:name":"Kindercentrum Lotte",
    "wof:placetype":"venue"
},
  "geometry": {"coordinates":[4.454511,52.150211],"type":"Point"}
}