{
  "type": "Feature",
  "properties": {
    "addr:full":"Kaepwei 5 Gaastmeer Friesland 8611 JL",
    "addr:housenumber":"5",
    "addr:postcode":"8611 jl",
    "addr:street":"Kaepwei",
    "iso:country":"NL",
    "sg:address":"Kaepwei 5",
    "sg:city":"Gaastmeer",
    "sg:orig_category":"Kampeerterreinen",
    "sg:phone":"+31 515 469 978",
    "sg:postcode":"8611 JL",
    "sg:province":"Friesland",
    "wof:name":"East Ijnje",
    "wof:placetype":"venue"
},
  "geometry": {"coordinates":[5.5137548447,52.9740257263],"type":"Point"}
}