{
  "type": "Feature",
  "properties": {
    "addr:full":"La Fontainestraat 12 Venlo Limburg 5924 AZ",
    "addr:housenumber":"12",
    "addr:postcode":"5924 az",
    "addr:street":"La Fontainestraat",
    "iso:country":"NL",
    "sg:address":"La Fontainestraat 12",
    "sg:city":"Venlo",
    "sg:orig_category":"Kappers",
    "sg:phone":"+31 77 382 3380",
    "sg:postcode":"5924 AZ",
    "sg:province":"Limburg",
    "wof:name":"Kapsalon Keras",
    "wof:placetype":"venue"
},
  "geometry": {"coordinates":[6.1328191757,51.3641891479],"type":"Point"}
}