{
  "type": "Feature",
  "properties": {
    "addr:full":"Bessengaard 93A Spykenisse Zuid-Holland 3206 AG",
    "addr:housenumber":"93a",
    "addr:postcode":"3206",
    "addr:street":"Bessengaard",
    "iso:country":"NL",
    "sg:address":"Bessengaard 93A",
    "sg:city":"Spykenisse",
    "sg:orig_category":"Scholen Voor Basisonderwijs",
    "sg:phone":"+31 181 631 749",
    "sg:postcode":"3206 AG",
    "sg:province":"Zuid-Holland",
    "wof:name":"Rietgors Openb, De",
    "wof:placetype":"venue"
},
  "geometry": {"coordinates":[4.32515,51.829128],"type":"Point"}
}