{
  "type": "Feature",
  "properties": {
    "addr:full":"Provenierssngl 69A Rotterdam South Holland 3033 EH",
    "addr:housenumber":"69a",
    "addr:postcode":"3033 eh",
    "addr:street":"Provenierssngl",
    "iso:country":"NL",
    "sg:address":"Provenierssngl 69A",
    "sg:city":"Rotterdam",
    "sg:classifiers":[
        {
            "category":"Utilities",
            "subcategory":"Cable",
            "type":"Services"
        }
    ],
    "sg:phone":"+31 10 466 5048",
    "sg:postcode":"3033 EH",
    "sg:province":"South Holland",
    "sg:tags":[
        "masseur",
        "en",
        "heilgymnasten"
    ],
    "wof:name":"Tijhuis, D",
    "wof:placetype":"venue"
},
  "geometry": {"coordinates":[4.469809,51.926994],"type":"Point"}
}