{
  "type": "Feature",
  "properties": {
    "iso:country":"NL",
    "sg:address":"Korenaarstr 26",
    "sg:city":"Rotterdam",
    "sg:orig_category":"Kinderopvang",
    "sg:phone":"+31 10 477 2201",
    "sg:postcode":"3023 XG",
    "sg:province":"Zuid-Holland",
    "wof:name":"Beatrix",
    "wof:placetype":"venue"
},
  "geometry": {"coordinates":[4.451997,51.91309],"type":"Point"}
}