{
  "type": "Feature",
  "properties": {
    "addr:full":"Montgomeryln 1 Eindhoven Noord-Brabant 5612 BA",
    "addr:housenumber":"1",
    "addr:postcode":"5612 ba",
    "addr:street":"Montgomeryln",
    "iso:country":"NL",
    "sg:address":"Montgomeryln 1",
    "sg:city":"Eindhoven",
    "sg:classifiers":[
        {
            "category":"Travel",
            "subcategory":"Hotels & Motels",
            "type":"Entertainment"
        }
    ],
    "sg:phone":"+31 40 243 3222",
    "sg:postcode":"5612 BA",
    "sg:province":"Noord-Brabant",
    "sg:website":"HTTP://www.einhoven.holiday-inn.com",
    "wof:name":"Holiday Inn",
    "wof:placetype":"venue"
},
  "geometry": {"coordinates":[5.484105,51.434471],"type":"Point"}
}