{
  "type": "Feature",
  "properties": {
    "addr:full":"V V Goghpln 6 Etten Leur Noord-Brabant 4872 BB",
    "addr:housenumber":"6",
    "addr:postcode":"4872 bb",
    "addr:street":"Goghpln",
    "iso:country":"NL",
    "sg:address":"V V Goghpln 6",
    "sg:city":"Etten Leur",
    "sg:orig_category":"Kappers",
    "sg:phone":"+31 76 501 2165",
    "sg:postcode":"4872 BB",
    "sg:province":"Noord-Brabant",
    "wof:name":"Govaers, Kapsalon",
    "wof:placetype":"venue"
},
  "geometry": {"coordinates":[4.6395220757,51.5706939697],"type":"Point"}
}