{
  "type": "Feature",
  "properties": {
    "iso:country":"NL",
    "sg:address":"Placotiwg 1/A",
    "sg:city":"Vianen Zh",
    "sg:orig_category":"Houtindustrie",
    "sg:phone":"+31 347 371 623",
    "sg:postcode":"4131 NL",
    "sg:province":"South Holland",
    "wof:name":"Mafor Bv",
    "wof:placetype":"venue"
},
  "geometry": {"coordinates":[5.098173,51.986744],"type":"Point"}
}