{
  "type": "Feature",
  "properties": {
    "addr:full":"Ir Sassenstraat 1 Ulft Gelderland 7071 BA",
    "addr:housenumber":"1",
    "addr:postcode":"7071 ba",
    "addr:street":"Ir Sassenstraat;Gelderland",
    "iso:country":"NL",
    "sg:address":"Ir Sassenstraat 1",
    "sg:city":"Ulft",
    "sg:orig_category":"Schoenen",
    "sg:phone":"+31 315 681 542",
    "sg:postcode":"7071 BA",
    "sg:province":"Gelderland",
    "wof:name":"Aalders Schoenmode Vof",
    "wof:placetype":"venue"
},
  "geometry": {"coordinates":[6.382938,51.893169],"type":"Point"}
}