{
  "type": "Feature",
  "properties": {
    "iso:country":"NL",
    "sg:address":"Ir Sassenstraat 1",
    "sg:city":"Ulft",
    "sg:orig_category":"Schoenen",
    "sg:phone":"+31 315 681 542",
    "sg:postcode":"7071 BA",
    "sg:province":"Gelderland",
    "wof:name":"Aalders Schoenmode Vof",
    "wof:placetype":"venue"
},
  "geometry": {"coordinates":[6.382938,51.893169],"type":"Point"}
}