{
  "type": "Feature",
  "properties": {
    "addr:full":"Kanaalstraat 15 Lisse Zuid-Holland 2161 JA",
    "addr:housenumber":"15",
    "addr:postcode":"2161 ja",
    "addr:street":"Kanaalstraat",
    "iso:country":"NL",
    "sg:address":"Kanaalstraat 15",
    "sg:city":"Lisse",
    "sg:orig_category":"Meubelzaken, Woning- And Keukeninrichting",
    "sg:phone":"+31 252 422 383",
    "sg:postcode":"2161 JA",
    "sg:province":"Zuid-Holland",
    "wof:name":"De Verwondering",
    "wof:placetype":"venue"
},
  "geometry": {"coordinates":[4.556042,52.26041],"type":"Point"}
}