{
  "type": "Feature",
  "properties": {
    "addr:full":"Nw Ryn 14 Leiden Zuid-Holland 2312 JC",
    "addr:housenumber":"14",
    "addr:postcode":"2312 jc",
    "addr:street":"Nw Ryn",
    "iso:country":"NL",
    "sg:address":"Nw Ryn 14",
    "sg:city":"Leiden",
    "sg:orig_category":"Aquariumartikelen En Siervissen",
    "sg:phone":"+31 71 512 5480",
    "sg:postcode":"2312 JC",
    "sg:province":"Zuid-Holland",
    "wof:name":"Vivarium-Stol Dierenspeciaalzaak",
    "wof:placetype":"venue"
},
  "geometry": {"coordinates":[4.49463,52.154572],"type":"Point"}
}