{
  "type": "Feature",
  "properties": {
    "addr:full":"Bosschebaan 58 Heesch Noord-Brabant 5384 VZ",
    "addr:housenumber":"58",
    "addr:postcode":"5384 vz",
    "addr:street":"Bosschebaan",
    "iso:country":"NL",
    "sg:address":"Bosschebaan 58",
    "sg:city":"Heesch",
    "sg:orig_category":"Bedrijfs- And Managementsconsultants",
    "sg:phone":"+31 412 457 108",
    "sg:postcode":"5384 VZ",
    "sg:province":"Noord-Brabant",
    "wof:name":"A.E. Mehlbaum",
    "wof:placetype":"venue"
},
  "geometry": {"coordinates":[5.506765,51.732334],"type":"Point"}
}