{
  "type": "Feature",
  "properties": {
    "iso:country":"NL",
    "sg:address":"Het Breed 519",
    "sg:city":"Amsterdam",
    "sg:orig_category":"Fotojournalisten Freelance",
    "sg:phone":"+31 20 632 4583",
    "sg:postcode":"1025 HT",
    "sg:province":"Noord-Holland",
    "wof:name":"Koers, A",
    "wof:placetype":"venue"
},
  "geometry": {"coordinates":[4.939475,52.396442],"type":"Point"}
}