{
  "type": "Feature",
  "properties": {
    "addr:full":"Bloklandstr 166B Rotterdam Zuid-Holland 3036 TT",
    "addr:housenumber":"166b",
    "addr:postcode":"3036 tt",
    "iso:country":"NL",
    "sg:address":"Bloklandstr 166B",
    "sg:city":"Rotterdam",
    "sg:orig_category":"Organisatiebureaus",
    "sg:phone":"+31 10 466 0740",
    "sg:postcode":"3036 TT",
    "sg:province":"Zuid-Holland",
    "sg:website":"http://www.orange-event.nl",
    "wof:name":"Orange Event",
    "wof:placetype":"venue"
},
  "geometry": {"coordinates":[4.4792838097,51.9367980957],"type":"Point"}
}