{
  "type": "Feature",
  "properties": {
    "iso:country":"NL",
    "sg:address":"Bremstraat 96",
    "sg:city":"Sint Willebrord",
    "sg:orig_category":"Wegen And Sportterreinen",
    "sg:phone":"+31 165 387 365",
    "sg:postcode":"4711 CJ",
    "sg:province":"Noord-Brabant",
    "wof:name":"W M Jaspers Stratenmakersbedrijf",
    "wof:placetype":"venue"
},
  "geometry": {"coordinates":[4.5827260017,51.5549888611],"type":"Point"}
}