{
  "type": "Feature",
  "properties": {
    "addr:full":"Zoutestraat 184A Hulst Zeeland 4561 TC",
    "addr:housenumber":"184a",
    "addr:postcode":"4561 tc",
    "addr:street":"Zoutestraat",
    "iso:country":"NL",
    "sg:address":"Zoutestraat 184A",
    "sg:city":"Hulst",
    "sg:orig_category":"Kappers",
    "sg:phone":"+31 114 315 395",
    "sg:postcode":"4561 TC",
    "sg:province":"Zeeland",
    "wof:name":"Haarstudio La Coupe",
    "wof:placetype":"venue"
},
  "geometry": {"coordinates":[4.0712909698,51.2922058105],"type":"Point"}
}