{
  "type": "Feature",
  "properties": {
    "addr:full":"V Schagenstr 2 Elshout Noord-Brabant 5154 PG",
    "addr:housenumber":"2",
    "addr:postcode":"5154 pg",
    "addr:street":"Schagenstr",
    "iso:country":"NL",
    "sg:address":"V Schagenstr 2",
    "sg:city":"Elshout",
    "sg:orig_category":"Autoschade- Herstelbedrijven",
    "sg:phone":"+31 416 376 020",
    "sg:postcode":"5154 PG",
    "sg:province":"Noord-Brabant",
    "wof:name":"Ad Brands",
    "wof:placetype":"venue"
},
  "geometry": {"coordinates":[5.144005,51.702637],"type":"Point"}
}