{
  "type": "Feature",
  "properties": {
    "iso:country":"NL",
    "sg:address":"Rijnstraat 90",
    "sg:city":"Amsterdam",
    "sg:orig_category":"Fotolaboratoria",
    "sg:phone":"+31 20 644 9821",
    "sg:postcode":"1079 HM",
    "sg:province":"Noord-Holland",
    "wof:name":"Foto Sunset",
    "wof:placetype":"venue"
},
  "geometry": {"coordinates":[4.905588,52.344826],"type":"Point"}
}