{
  "type": "Feature",
  "properties": {
    "addr:full":"Rechtestr 62 Eindhoven Noord-Brabant 5611 GR",
    "addr:housenumber":"62",
    "addr:postcode":"5611",
    "addr:street":"Rechtestr",
    "iso:country":"NL",
    "sg:address":"Rechtestr 62",
    "sg:city":"Eindhoven",
    "sg:orig_category":"Woninginrichting",
    "sg:phone":"+31 40 243 3173",
    "sg:postcode":"5611 GR",
    "sg:province":"Noord-Brabant",
    "wof:name":"Jencikova Int Bv",
    "wof:placetype":"venue"
},
  "geometry": {"coordinates":[5.4792900085,51.437412262],"type":"Point"}
}