{
  "type": "Feature",
  "properties": {
    "addr:full":"Overloonseweg 30 Venray Limburg 5804 AV",
    "addr:housenumber":"30",
    "addr:postcode":"5804 av",
    "addr:street":"Overloonseweg",
    "iso:country":"NL",
    "sg:address":"Overloonseweg 30",
    "sg:city":"Venray",
    "sg:orig_category":"Autokeuringen",
    "sg:phone":"+31 478 584 805",
    "sg:postcode":"5804 AV",
    "sg:province":"Limburg",
    "wof:name":"Pelzer Auto'S",
    "wof:placetype":"venue"
},
  "geometry": {"coordinates":[5.968063,51.549995],"type":"Point"}
}