{
  "type": "Feature",
  "properties": {
    "addr:full":"Biesvendreef 6 Duizel Noord-Brabant 5525 KW",
    "addr:housenumber":"6",
    "addr:postcode":"5525 kw",
    "addr:street":"Biesvendreef",
    "iso:country":"NL",
    "sg:address":"Biesvendreef 6",
    "sg:city":"Duizel",
    "sg:orig_category":"Afvalstoffen",
    "sg:phone":"+31 497 517 084",
    "sg:postcode":"5525 KW",
    "sg:province":"Noord-Brabant",
    "wof:name":"Milieustraat Nv Razob",
    "wof:placetype":"venue"
},
  "geometry": {"coordinates":[5.311349,51.3773],"type":"Point"}
}