{
  "type": "Feature",
  "properties": {
    "iso:country":"NL",
    "sg:address":"Duistervoordseweg 35",
    "sg:city":"Twello",
    "sg:orig_category":"Metalen And Ertsen Gh",
    "sg:phone":"+31 571 272 531",
    "sg:postcode":"7391 CA",
    "sg:province":"Gelderland",
    "wof:name":"Ceves-Vergeer Bv",
    "wof:placetype":"venue"
},
  "geometry": {"coordinates":[6.10055,52.235859],"type":"Point"}
}