{
  "type": "Feature",
  "properties": {
    "iso:country":"NL",
    "sg:address":"Ericasestr 71A",
    "sg:city":"Erica",
    "sg:orig_category":"Kassenbouw",
    "sg:phone":"+31 591 555 540",
    "sg:postcode":"7887 GB",
    "sg:province":"Drenthe",
    "wof:name":"Vliet Scherming, Van",
    "wof:placetype":"venue"
},
  "geometry": {"coordinates":[6.927604,52.721859],"type":"Point"}
}