{
  "type": "Feature",
  "properties": {
    "addr:full":"Lange Nieuwstraat 451 Ijmuiden Noord-Holland 1971 GE",
    "addr:housenumber":"451",
    "addr:postcode":"1971",
    "addr:street":"Lange Nieuwstraat",
    "iso:country":"NL",
    "sg:address":"Lange Nieuwstraat 451",
    "sg:city":"Ijmuiden",
    "sg:orig_category":"Opticiens",
    "sg:phone":"+31 255 519 324",
    "sg:postcode":"1971 GE",
    "sg:province":"Noord-Holland",
    "wof:name":"Pearle Opticiens",
    "wof:placetype":"venue"
},
  "geometry": {"coordinates":[4.6186289787,52.4585571289],"type":"Point"}
}