{
  "type": "Feature",
  "properties": {
    "addr:full":"Esschilderstraat 38 Zw Haarlem North Holland 2012 BE",
    "addr:housenumber":"38 zw",
    "addr:postcode":"2012",
    "addr:street":"Esschilderstraat",
    "iso:country":"NL",
    "sg:address":"Esschilderstraat 38 Zw",
    "sg:city":"Haarlem",
    "sg:orig_category":"Beveiligingsdiensten And Bewakingsbedrijven",
    "sg:phone":"+31 23 531 1863",
    "sg:postcode":"2012 BE",
    "sg:province":"North Holland",
    "wof:name":"Spaarne Beveiliging",
    "wof:placetype":"venue"
},
  "geometry": {"coordinates":[4.642253,52.380562],"type":"Point"}
}