{
  "type": "Feature",
  "properties": {
    "addr:full":"Spaarndammerstraat 123 Amsterdam North Holland 1013 TE",
    "addr:housenumber":"123",
    "addr:postcode":"1013 te",
    "addr:street":"Spaarndammerstraat",
    "iso:country":"NL",
    "sg:address":"Spaarndammerstraat 123",
    "sg:city":"Amsterdam",
    "sg:orig_category":"Huishoudapparatuur, Televisies And Radio'S",
    "sg:phone":"+31 20 684 4048",
    "sg:postcode":"1013 TE",
    "sg:province":"North Holland",
    "wof:name":"Mark Foto Video Vof",
    "wof:placetype":"venue"
},
  "geometry": {"coordinates":[4.878028,52.3909],"type":"Point"}
}