{
  "type": "Feature",
  "properties": {
    "addr:full":"Stationstraat 67 Alphen Nb Noord-Brabant 5131 BM",
    "addr:housenumber":"67",
    "addr:postcode":"5131 bm",
    "addr:street":"Stationstraat",
    "iso:country":"NL",
    "sg:address":"Stationstraat 67",
    "sg:city":"Alphen Nb",
    "sg:orig_category":"Airconditioning And Ventilatie",
    "sg:phone":"+31 13 508 2407",
    "sg:postcode":"5131 BM",
    "sg:province":"Noord-Brabant",
    "wof:name":"Van Puijenbroek Installaties Bv",
    "wof:placetype":"venue"
},
  "geometry": {"coordinates":[4.959594,51.47887],"type":"Point"}
}