{
  "type": "Feature",
  "properties": {
    "addr:full":"Slochterenwg 31 Arnhem Gelderland 6835 CE",
    "addr:housenumber":"31",
    "addr:postcode":"6835 ce",
    "addr:street":"Slochterenwg",
    "iso:country":"NL",
    "sg:address":"Slochterenwg 31",
    "sg:city":"Arnhem",
    "sg:orig_category":"Glazenwasserijen",
    "sg:phone":"+31 6 48478665",
    "sg:postcode":"6835 CE",
    "sg:province":"Gelderland",
    "wof:name":"Hagen, M",
    "wof:placetype":"venue"
},
  "geometry": {"coordinates":[5.897116,51.9548],"type":"Point"}
}