{
  "type": "Feature",
  "properties": {
    "addr:full":"Drieherenlaan 31 Heemstede North Holland 2103 SB",
    "addr:housenumber":"31",
    "addr:postcode":"2103 sb",
    "addr:street":"Drieherenlaan",
    "iso:country":"NL",
    "sg:address":"Drieherenlaan 31",
    "sg:city":"Heemstede",
    "sg:orig_category":"Boekhouders",
    "sg:phone":"+31 23 529 4009",
    "sg:postcode":"2103 SB",
    "sg:province":"North Holland",
    "wof:name":"Van Ekeren & Nieuwenhuizen Bv",
    "wof:placetype":"venue"
},
  "geometry": {"coordinates":[4.624441,52.344891],"type":"Point"}
}