{
  "type": "Feature",
  "properties": {
    "addr:full":"Industriewg 18 Bedum Groningen 9781 AC",
    "addr:housenumber":"18",
    "addr:postcode":"9781 ac",
    "addr:street":"Industriewg",
    "iso:country":"NL",
    "sg:address":"Industriewg 18",
    "sg:city":"Bedum",
    "sg:orig_category":"Schilders",
    "sg:phone":"+31 50 301 2812",
    "sg:postcode":"9781 AC",
    "sg:province":"Groningen",
    "wof:name":"Bol Vof",
    "wof:placetype":"venue"
},
  "geometry": {"coordinates":[6.596166,53.296608],"type":"Point"}
}