{
  "type": "Feature",
  "properties": {
    "iso:country":"NL",
    "sg:address":"Slimmeweg 15",
    "sg:city":"Amsterdam",
    "sg:orig_category":"Loodgieterswerk, Verwarming And Sanitaire Installaties",
    "sg:phone":"+31 20 617 8253",
    "sg:postcode":"1066 EV",
    "sg:province":"Noord-Holland",
    "wof:name":"Technisch Bureau Buskens Bv",
    "wof:placetype":"venue"
},
  "geometry": {"coordinates":[4.795874,52.343605],"type":"Point"}
}