{
  "type": "Feature",
  "properties": {
    "addr:full":"Veerstraat 42 Oude Wetering South Holland 2377 AP",
    "addr:housenumber":"42",
    "addr:postcode":"2377 ap",
    "addr:street":"Veerstraat",
    "iso:country":"NL",
    "sg:address":"Veerstraat 42",
    "sg:city":"Oude Wetering",
    "sg:orig_category":"Bloemen And Planten",
    "sg:phone":"+31 71 331 3868",
    "sg:postcode":"2377 AP",
    "sg:province":"South Holland",
    "wof:name":"Tuincentrum Piet Van Der Meer",
    "wof:placetype":"venue"
},
  "geometry": {"coordinates":[4.647594,52.208138],"type":"Point"}
}