{
  "type": "Feature",
  "properties": {
    "addr:full":"Koninginnestr 2A Maastricht Limburg 6225 BR",
    "addr:housenumber":"2a",
    "addr:postcode":"6225 br",
    "addr:street":"Koninginnestr",
    "iso:country":"NL",
    "sg:address":"Koninginnestr 2A",
    "sg:city":"Maastricht",
    "sg:orig_category":"Scholen Voor Basisonderwijs",
    "sg:phone":"+31 43 362 0582",
    "sg:postcode":"6225 BR",
    "sg:province":"Limburg",
    "sg:website":"http://www.bsamby.nl",
    "wof:name":"Amby Rk",
    "wof:placetype":"venue"
},
  "geometry": {"coordinates":[5.7291212082,50.865486145],"type":"Point"}
}