{
  "type": "Feature",
  "properties": {
    "addr:full":"Storkstraat 5 Leusden Utrecht 3833 LB",
    "addr:housenumber":"5",
    "addr:postcode":"3833 lb",
    "addr:street":"Storkstraat",
    "iso:country":"NL",
    "sg:address":"Storkstraat 5",
    "sg:city":"Leusden",
    "sg:orig_category":"Bouwmaterialen Gh",
    "sg:phone":"+31 33 432 3271",
    "sg:postcode":"3833 LB",
    "sg:province":"Utrecht",
    "wof:name":"Sanderink Leusden",
    "wof:placetype":"venue"
},
  "geometry": {"coordinates":[5.421188,52.143856],"type":"Point"}
}