{
  "type": "Feature",
  "properties": {
    "addr:full":"Lammenschanswg 130G Leiden South Holland 2321 JX",
    "addr:housenumber":"130g",
    "addr:postcode":"2321 jx",
    "addr:street":"Lammenschanswg",
    "iso:country":"NL",
    "sg:address":"Lammenschanswg 130G",
    "sg:city":"Leiden",
    "sg:orig_category":"Keukens",
    "sg:phone":"+31 71 532 0487",
    "sg:postcode":"2321 JX",
    "sg:province":"South Holland",
    "wof:name":"Horn",
    "wof:placetype":"venue"
},
  "geometry": {"coordinates":[4.491316,52.146027],"type":"Point"}
}