{
  "type": "Feature",
  "properties": {
    "iso:country":"NL",
    "sg:address":"Kroonlaan 24",
    "sg:city":"Hilversum",
    "sg:orig_category":"Fotostudio'S And Fotografen",
    "sg:phone":"+31 35 624 2324",
    "sg:postcode":"1217 AW",
    "sg:province":"Noord-Holland",
    "wof:name":"Foto Video Neeteson",
    "wof:placetype":"venue"
},
  "geometry": {"coordinates":[5.162674,52.240364],"type":"Point"}
}