{
  "type": "Feature",
  "properties": {
    "addr:full":"Hengelosestr 62 Enschede Overijssel 7514 AJ",
    "addr:housenumber":"62",
    "addr:postcode":"7514 aj",
    "addr:street":"Hengelosestr",
    "iso:country":"NL",
    "sg:address":"Hengelosestr 62",
    "sg:city":"Enschede",
    "sg:orig_category":"Orthopedisch Schoeisel",
    "sg:phone":"+31 53 435 5215",
    "sg:postcode":"7514 AJ",
    "sg:province":"Overijssel",
    "wof:name":"Veensma",
    "wof:placetype":"venue"
},
  "geometry": {"coordinates":[6.887512207,52.2236976624],"type":"Point"}
}