{
  "type": "Feature",
  "properties": {
    "addr:full":"Geldersestr 41 Sittard Limburg 6136 AS",
    "addr:housenumber":"41",
    "addr:postcode":"6136 as",
    "addr:street":"Geldersestr",
    "iso:country":"NL",
    "sg:address":"Geldersestr 41",
    "sg:city":"Sittard",
    "sg:orig_category":"Zalenverhuur",
    "sg:phone":"+31 46 452 6410",
    "sg:postcode":"6136 AS",
    "sg:province":"Limburg",
    "wof:name":"Oos Kaar Overhoven",
    "wof:placetype":"venue"
},
  "geometry": {"coordinates":[5.86681,51.008694],"type":"Point"}
}