{
  "type": "Feature",
  "properties": {
    "addr:full":"Standerdmolen 7 Bergeyk North Brabant 5571 RN",
    "addr:housenumber":"7",
    "addr:postcode":"5571 rn",
    "addr:street":"Standerdmolen",
    "iso:country":"NL",
    "sg:address":"Standerdmolen 7",
    "sg:city":"Bergeyk",
    "sg:orig_category":"Diverse Bedrijfsinstallaties Gh",
    "sg:phone":"+31 497 571 907",
    "sg:postcode":"5571 RN",
    "sg:province":"North Brabant",
    "wof:name":"Btm Bv",
    "wof:placetype":"venue"
},
  "geometry": {"coordinates":[5.343798,51.317955],"type":"Point"}
}