{
  "type": "Feature",
  "properties": {
    "iso:country":"NL",
    "sg:address":"Akelei 4",
    "sg:city":"Westerhaar Vriezenv W",
    "sg:orig_category":"Houten Verpakkingen Fab",
    "sg:phone":"+31 546 658 269",
    "sg:postcode":"7676 DC",
    "sg:province":"NL.08",
    "wof:name":"Kikkert Pallets Vof",
    "wof:placetype":"venue"
},
  "geometry": {"coordinates":[6.617967,52.460495],"type":"Point"}
}