{
  "type": "Feature",
  "properties": {
    "addr:full":"De La Reywg 23 Breda Noord-Brabant 4818 BA",
    "addr:housenumber":"23",
    "addr:postcode":"4818 ba",
    "addr:street":"De La Reywg",
    "iso:country":"NL",
    "sg:address":"De La Reywg 23",
    "sg:city":"Breda",
    "sg:orig_category":"Makelaars En Adviseurs Onroerende Goederen",
    "sg:phone":"+31 76 522 0070",
    "sg:postcode":"4818 BA",
    "sg:province":"Noord-Brabant",
    "wof:name":"Boxsel, A L A M Van",
    "wof:placetype":"venue"
},
  "geometry": {"coordinates":[4.771685,51.591351],"type":"Point"}
}