{
  "type": "Feature",
  "properties": {
    "iso:country":"NL",
    "sg:address":"Molenwg 12",
    "sg:city":"Landgraaf",
    "sg:orig_category":"Administratie- En Boekhoudkantoren",
    "sg:phone":"+31 45 532 2278",
    "sg:postcode":"6372 AN",
    "sg:province":"Limburg",
    "wof:name":"Magermans, M",
    "wof:placetype":"venue"
},
  "geometry": {"coordinates":[6.02026,50.891735],"type":"Point"}
}