{
  "type": "Feature",
  "properties": {
    "addr:full":"Amsterdamsestraatweg 312 Utrecht Utrecht 3551 CT",
    "addr:housenumber":"312",
    "addr:postcode":"3551 ct",
    "addr:street":"Amsterdamsestraatweg",
    "iso:country":"NL",
    "sg:address":"Amsterdamsestraatweg 312",
    "sg:city":"Utrecht",
    "sg:orig_category":"Wasserettes And Stomerijen",
    "sg:phone":"+31 30 244 0504",
    "sg:postcode":"3551 CT",
    "sg:province":"Utrecht",
    "wof:name":"Topvorm Stomerij H.J. Van Arnhem",
    "wof:placetype":"venue"
},
  "geometry": {"coordinates":[5.0980238914,52.1017608643],"type":"Point"}
}