{
  "type": "Feature",
  "properties": {
    "addr:full":"Maliestraat 2 Utrecht Centrum Utrecht 3581 SL",
    "addr:housenumber":"2",
    "addr:street":"Maliestraat",
    "iso:country":"NL",
    "sg:address":"Maliestraat 2",
    "sg:city":"Utrecht Centrum",
    "sg:classifiers":[
        {
            "category":"Travel",
            "subcategory":"Hotels & Motels",
            "type":"Entertainment"
        }
    ],
    "sg:phone":"+31 30 231 6424",
    "sg:postcode":"3581 SL",
    "sg:province":"Utrecht",
    "wof:name":"Malie Hotel",
    "wof:placetype":"venue"
},
  "geometry": {"coordinates":[5.136859,52.094086],"type":"Point"}
}