{
  "type": "Feature",
  "properties": {
    "addr:full":"Martinusweg 11 Twello Gelderland 7391 AC",
    "addr:housenumber":"11",
    "addr:postcode":"7391 ac",
    "addr:street":"Martinusweg;Gelderland",
    "iso:country":"NL",
    "sg:address":"Martinusweg 11",
    "sg:city":"Twello",
    "sg:orig_category":"Apothekers",
    "sg:phone":"+31 571 275 576",
    "sg:postcode":"7391 AC",
    "sg:province":"Gelderland",
    "wof:name":"Apotheek Duistervoorde",
    "wof:placetype":"venue"
},
  "geometry": {"coordinates":[6.093887,52.231094],"type":"Point"}
}