{
  "type": "Feature",
  "properties": {
    "addr:full":"Kanaalstr 28 Amsterdam North Holland 1054 XJ",
    "addr:housenumber":"28",
    "addr:postcode":"1054 xj",
    "addr:street":"Kanaalstr",
    "iso:country":"NL",
    "sg:address":"Kanaalstr 28",
    "sg:city":"Amsterdam",
    "sg:orig_category":"Fotoreportages",
    "sg:phone":"+31 20 616 8869",
    "sg:postcode":"1054 XJ",
    "sg:province":"North Holland",
    "wof:name":"Stills And Portraits",
    "wof:placetype":"venue"
},
  "geometry": {"coordinates":[4.865908,52.362942],"type":"Point"}
}