{
  "type": "Feature",
  "properties": {
    "addr:full":"Soerenseweg 3 Apeldoorn Gelderland 7314 CA",
    "addr:housenumber":"3",
    "addr:postcode":"7314 ca",
    "addr:street":"Soerenseweg;Gelderland",
    "iso:country":"NL",
    "sg:address":"Soerenseweg 3",
    "sg:city":"Apeldoorn",
    "sg:orig_category":"Fietshandelaren",
    "sg:phone":"+31 55 521 5679",
    "sg:postcode":"7314 CA",
    "sg:province":"Gelderland",
    "wof:name":"J. Blakborn",
    "wof:placetype":"venue"
},
  "geometry": {"coordinates":[5.95039,52.220142],"type":"Point"}
}