{
  "type": "Feature",
  "properties": {
    "addr:full":"Burg V Leeuwenln 67 Amsterdam Noord-Holland 1064 KL",
    "addr:housenumber":"67",
    "addr:postcode":"1064 kl",
    "addr:street":"Burg;Leeuwenln",
    "iso:country":"NL",
    "sg:address":"Burg V Leeuwenln 67",
    "sg:city":"Amsterdam",
    "sg:classifiers":[
        {
            "category":"Food & Beverages",
            "subcategory":"Bakery",
            "type":"Retail Goods"
        }
    ],
    "sg:phone":"+31 20 611 8429",
    "sg:postcode":"1064 KL",
    "sg:province":"Noord-Holland",
    "sg:tags":[
        "pizza"
    ],
    "wof:name":"New York Pizza",
    "wof:placetype":"venue"
},
  "geometry": {"coordinates":[4.82176,52.370331],"type":"Point"}
}