{
  "type": "Feature",
  "properties": {
    "addr:full":"Hovenstraat 127 Landgraaf Limburg 6374 HC",
    "addr:housenumber":"127",
    "addr:postcode":"6374 hc",
    "addr:street":"Hovenstraat",
    "iso:country":"NL",
    "sg:address":"Hovenstraat 127",
    "sg:city":"Landgraaf",
    "sg:orig_category":"Damesmodezaken",
    "sg:phone":"+31 45 531 2210",
    "sg:postcode":"6374 HC",
    "sg:province":"Limburg",
    "wof:name":"Bonneterie Lenie",
    "wof:placetype":"venue"
},
  "geometry": {"coordinates":[6.050087,50.91584],"type":"Point"}
}