{
  "type": "Feature",
  "properties": {
    "addr:full":"Fennenpln 80 Leeuwarden Friesland 8918 CS",
    "addr:housenumber":"80",
    "addr:postcode":"8918 cs",
    "addr:street":"Fennenpln",
    "iso:country":"NL",
    "sg:address":"Fennenpln 80",
    "sg:city":"Leeuwarden",
    "sg:orig_category":"Psychotherapeuten",
    "sg:phone":"+31 58 266 0500",
    "sg:postcode":"8918 CS",
    "sg:province":"Friesland",
    "wof:name":"Liefting, Drs J F",
    "wof:placetype":"venue"
},
  "geometry": {"coordinates":[5.798756,53.213844],"type":"Point"}
}