{
  "type": "Feature",
  "properties": {
    "addr:full":"Kerkstraat 20 Enschede NL.08 7532 AT",
    "addr:housenumber":"20",
    "addr:postcode":"7532",
    "addr:street":"Kerkstraat",
    "iso:country":"NL",
    "sg:address":"Kerkstraat 20",
    "sg:city":"Enschede",
    "sg:orig_category":"Architecten",
    "sg:phone":"+31 53 461 4065",
    "sg:postcode":"7532 AT",
    "sg:province":"NL.08",
    "wof:name":"Stichting Dorpsvernieuwing Glanerbrug",
    "wof:placetype":"venue"
},
  "geometry": {"coordinates":[6.97384,52.216866],"type":"Point"}
}