{
  "type": "Feature",
  "properties": {
    "addr:full":"Dorpswg 126 Hoornaar South Holland 4223 NH",
    "addr:housenumber":"126",
    "addr:postcode":"4223 nh",
    "iso:country":"NL",
    "sg:address":"Dorpswg 126",
    "sg:city":"Hoornaar",
    "sg:orig_category":"Modevakscholen",
    "sg:phone":"+31 183 581 649",
    "sg:postcode":"4223 NH",
    "sg:province":"South Holland",
    "wof:name":"Ensaid",
    "wof:placetype":"venue"
},
  "geometry": {"coordinates":[4.946474,51.879917],"type":"Point"}
}