{
  "type": "Feature",
  "properties": {
    "addr:full":"Madame Curiewei 2 Joure Friesland 8501 XC",
    "addr:housenumber":"2",
    "addr:postcode":"8501 xc",
    "iso:country":"NL",
    "sg:address":"Madame Curiewei 2",
    "sg:city":"Joure",
    "sg:orig_category":"Verhuur",
    "sg:phone":"+31 513 415 411",
    "sg:postcode":"8501 XC",
    "sg:province":"Friesland",
    "sg:website":"http://www.rienk.nl",
    "wof:name":"Wis",
    "wof:placetype":"venue"
},
  "geometry": {"coordinates":[5.78984,52.957302],"type":"Point"}
}