{
  "type": "Feature",
  "properties": {
    "addr:full":"L Manintveldstr 22 Rockanje Zuid-Holland 3235 BS",
    "addr:housenumber":"22",
    "addr:postcode":"3235 bs",
    "iso:country":"NL",
    "sg:address":"L Manintveldstr 22",
    "sg:city":"Rockanje",
    "sg:orig_category":"Autorijscholen",
    "sg:phone":"+31 181 401 788",
    "sg:postcode":"3235 BS",
    "sg:province":"Zuid-Holland",
    "wof:name":"Krijgsman",
    "wof:placetype":"venue"
},
  "geometry": {"coordinates":[4.071725,51.872894],"type":"Point"}
}