{
  "type": "Feature",
  "properties": {
    "iso:country":"NL",
    "sg:address":"Eglantier 15",
    "sg:city":"Leidschendam",
    "sg:classifiers":[
        {
            "category":"Food & Beverages",
            "subcategory":"Bakery",
            "type":"Retail Goods"
        }
    ],
    "sg:phone":"+31 70 327 0587",
    "sg:postcode":"2262 AP",
    "sg:province":"Zuid-Holland",
    "sg:tags":[
        "brood",
        "en",
        "banket"
    ],
    "wof:name":"Bart",
    "wof:placetype":"venue"
},
  "geometry": {"coordinates":[4.383507,52.089581],"type":"Point"}
}