{
  "type": "Feature",
  "properties": {
    "addr:full":"Postbus 99 Leimuiden South Holland 2450 AB",
    "addr:housenumber":"99",
    "addr:postcode":"2450 ab",
    "addr:street":"Postbus",
    "iso:country":"NL",
    "sg:address":"Postbus 99",
    "sg:city":"Leimuiden",
    "sg:orig_category":"Video - Faciliteiten En Producties",
    "sg:phone":"+31 6 50698033",
    "sg:postcode":"2450 AB",
    "sg:province":"South Holland",
    "wof:name":"Sparks",
    "wof:placetype":"venue"
},
  "geometry": {"coordinates":[4.67296,52.22448],"type":"Point"}
}