{
  "type": "Feature",
  "properties": {
    "addr:full":"Essendijk 15 Rhoon South Holland 3161 ED",
    "addr:housenumber":"15",
    "addr:postcode":"3161 ed",
    "addr:street":"Essendijk",
    "iso:country":"NL",
    "sg:address":"Essendijk 15",
    "sg:city":"Rhoon",
    "sg:orig_category":"Wegen And Sportterreinen",
    "sg:phone":"+31 180 613 573",
    "sg:postcode":"3161 ED",
    "sg:province":"South Holland",
    "wof:name":"G. Lems Vof",
    "wof:placetype":"venue"
},
  "geometry": {"coordinates":[4.4841618538,51.8462753296],"type":"Point"}
}