{
  "type": "Feature",
  "properties": {
    "addr:full":"Hortensiastraat 20 Amsterdam Noord-Holland 1032 CJ",
    "addr:housenumber":"20",
    "addr:postcode":"1032 cj",
    "addr:street":"Hortensiastraat",
    "iso:country":"NL",
    "sg:address":"Hortensiastraat 20",
    "sg:city":"Amsterdam",
    "sg:orig_category":"Apothekers",
    "sg:phone":"+31 20 636 0108",
    "sg:postcode":"1032 CJ",
    "sg:province":"Noord-Holland",
    "wof:name":"Kamperfoelie Apotheek",
    "wof:placetype":"venue"
},
  "geometry": {"coordinates":[4.914447,52.394424],"type":"Point"}
}