{
  "type": "Feature",
  "properties": {
    "addr:full":"Maasln 197 Helmond Noord-Brabant 5704 LD",
    "addr:housenumber":"197",
    "addr:postcode":"5704 ld",
    "iso:country":"NL",
    "sg:address":"Maasln 197",
    "sg:city":"Helmond",
    "sg:orig_category":"Scholen Voor Basisonderwijs",
    "sg:phone":"+31 492 513 452",
    "sg:postcode":"5704 LD",
    "sg:province":"Noord-Brabant",
    "wof:name":"Vlier Rk, De",
    "wof:placetype":"venue"
},
  "geometry": {"coordinates":[5.658284,51.482239],"type":"Point"}
}