{
  "type": "Feature",
  "properties": {
    "iso:country":"NL",
    "sg:address":"Wilhelminaln 3",
    "sg:city":"Hillegom",
    "sg:orig_category":"Banken",
    "sg:phone":"+31 252 576 100",
    "sg:postcode":"2182 CA",
    "sg:province":"Zuid-Holland",
    "sg:website":"http://www.rabobank.nl",
    "wof:name":"Rabobank",
    "wof:placetype":"venue"
},
  "geometry": {"coordinates":[4.571853,52.293297],"type":"Point"}
}