{
  "type": "Feature",
  "properties": {
    "addr:full":"G Vd Veenstr 72 Amsterdam Noord-Holland 1077 EJ",
    "addr:housenumber":"72",
    "addr:postcode":"1077 ej",
    "iso:country":"NL",
    "sg:address":"G Vd Veenstr 72",
    "sg:city":"Amsterdam",
    "sg:orig_category":"Administratie- En Boekhoudkantoren",
    "sg:phone":"+31 20 679 6751",
    "sg:postcode":"1077 EJ",
    "sg:province":"Noord-Holland",
    "wof:name":"Niekus, G J F",
    "wof:placetype":"venue"
},
  "geometry": {"coordinates":[-94.58503,38.350479],"type":"Point"}
}