{
  "type": "Feature",
  "properties": {
    "iso:country":"NL",
    "sg:address":"P Potterstr 22",
    "sg:city":"Goor",
    "sg:orig_category":"Kunststoffen- Verwerkende Industrie",
    "sg:phone":"+31 547 275 062",
    "sg:postcode":"7471 XJ",
    "sg:province":"Overijssel",
    "wof:name":"Lumago",
    "wof:placetype":"venue"
},
  "geometry": {"coordinates":[6.569414,52.237644],"type":"Point"}
}