{
  "type": "Feature",
  "properties": {
    "iso:country":"NL",
    "sg:address":"Hoogstraat 10",
    "sg:city":"Weert",
    "sg:orig_category":"Schoenen",
    "sg:phone":"+31 495 533 475",
    "sg:postcode":"6001 EV",
    "sg:province":"Limburg",
    "wof:name":"John Coolen Exclusief",
    "wof:placetype":"venue"
},
  "geometry": {"coordinates":[5.703781,51.255016],"type":"Point"}
}