{
  "type": "Feature",
  "properties": {
    "iso:country":"NL",
    "sg:address":"Gasthuisvest 17",
    "sg:city":"Haarlem",
    "sg:classifiers":[
        {
            "category":"Communications",
            "subcategory":"Television Station",
            "type":"Services"
        }
    ],
    "sg:phone":"+31 23 531 3902",
    "sg:postcode":"2011 ET",
    "sg:province":"Noord-Holland",
    "sg:tags":[
        "video",
        "audio",
        "verhuur"
    ],
    "wof:name":"Woord En Beeld",
    "wof:placetype":"venue"
},
  "geometry": {"coordinates":[4.632145,52.376244],"type":"Point"}
}