{
  "type": "Feature",
  "properties": {
    "addr:full":"Noordeinde 202 'S Gravenhage Zuid-Holland 2514 GS",
    "addr:housenumber":"202 '",
    "addr:postcode":"2514 gs",
    "addr:street":"Noordeinde",
    "iso:country":"NL",
    "sg:address":"Noordeinde 202",
    "sg:city":"'S Gravenhage",
    "sg:orig_category":"Boekhouders",
    "sg:phone":"+31 70 365 9503",
    "sg:postcode":"2514 GS",
    "sg:province":"Zuid-Holland",
    "wof:name":"Administratiekantoor W.Ch. Lam",
    "wof:placetype":"venue"
},
  "geometry": {"coordinates":[4.3042,52.083561],"type":"Point"}
}