{
  "type": "Feature",
  "properties": {
    "iso:country":"NL",
    "sg:address":"Grotestr 62",
    "sg:city":"Diepenheim",
    "sg:orig_category":"Woninginrichting",
    "sg:phone":"+31 547 262 777",
    "sg:postcode":"7478 AD",
    "sg:province":"NL.08",
    "sg:website":"http://www.interio.nl",
    "wof:name":"Interio",
    "wof:placetype":"venue"
},
  "geometry": {"coordinates":[6.5522022247,52.2000274658],"type":"Point"}
}