{
  "type": "Feature",
  "properties": {
    "addr:full":"Het Ruim 29 Dronten NL. 8251 EL",
    "addr:housenumber":"29",
    "addr:postcode":"8251 el",
    "addr:street":"Het Ruim;Nl.",
    "iso:country":"NL",
    "sg:address":"Het Ruim 29",
    "sg:city":"Dronten",
    "sg:orig_category":"Visspeciaalzaken",
    "sg:phone":"+31 321 315 713",
    "sg:postcode":"8251 EL",
    "sg:province":"NL.",
    "wof:name":"Woort Urker Vishandel",
    "wof:placetype":"venue"
},
  "geometry": {"coordinates":[5.718827,52.524895],"type":"Point"}
}