{
  "type": "Feature",
  "properties": {
    "addr:full":"De La Reywg 113 S Gravenhage Zuid-Holland 2571 EC",
    "addr:housenumber":"113;gravenhage",
    "addr:postcode":"2571 ec",
    "addr:street":"De La Reywg;S",
    "iso:country":"NL",
    "sg:address":"De La Reywg 113",
    "sg:city":"S Gravenhage",
    "sg:orig_category":"Autorijscholen",
    "sg:phone":"+31 6 54213935",
    "sg:postcode":"2571 EC",
    "sg:province":"Zuid-Holland",
    "wof:name":"Liberty",
    "wof:placetype":"venue"
},
  "geometry": {"coordinates":[4.29037,52.06884],"type":"Point"}
}