{
  "type": "Feature",
  "properties": {
    "addr:full":"Boergoensestraat 120 Rotterdam Zuid-Holland 3082 KD",
    "addr:housenumber":"120",
    "addr:postcode":"3082 kd",
    "addr:street":"Boergoensestraat",
    "iso:country":"NL",
    "sg:address":"Boergoensestraat 120",
    "sg:city":"Rotterdam",
    "sg:orig_category":"Wasserettes And Stomerijen",
    "sg:phone":"+31 10 495 5551",
    "sg:postcode":"3082 KD",
    "sg:province":"Zuid-Holland",
    "wof:name":"Scharlois",
    "wof:placetype":"venue"
},
  "geometry": {"coordinates":[4.4703979492,51.8913917542],"type":"Point"}
}