{
  "type": "Feature",
  "properties": {
    "addr:full":"Baanderheugte 28 Assen Drenthe 9403 HL",
    "addr:housenumber":"28",
    "addr:postcode":"9403 hl",
    "addr:street":"Baanderheugte",
    "iso:country":"NL",
    "sg:address":"Baanderheugte 28",
    "sg:city":"Assen",
    "sg:orig_category":"Fotostudio'S And Fotografen",
    "sg:phone":"+31 592 344 138",
    "sg:postcode":"9403 HL",
    "sg:province":"Drenthe",
    "wof:name":"Witvoet Promotion",
    "wof:placetype":"venue"
},
  "geometry": {"coordinates":[6.580408,53.017063],"type":"Point"}
}