{
  "type": "Feature",
  "properties": {
    "addr:full":"Buiteneinde 20 Strijen South Holland 3291 AH",
    "addr:housenumber":"20",
    "addr:postcode":"3291 ah",
    "addr:street":"Buiteneinde",
    "iso:country":"NL",
    "sg:address":"Buiteneinde 20",
    "sg:city":"Strijen",
    "sg:orig_category":"Autokeuringen",
    "sg:phone":"+31 78 674 1203",
    "sg:postcode":"3291 AH",
    "sg:province":"South Holland",
    "wof:name":"R.W. Dam",
    "wof:placetype":"venue"
},
  "geometry": {"coordinates":[4.547151,51.747681],"type":"Point"}
}