{
  "type": "Feature",
  "properties": {
    "addr:full":"Noordplein 21 Roelofarendsveen South Holland 2371 DA",
    "addr:housenumber":"21",
    "addr:postcode":"2371 da",
    "addr:street":"Noordplein",
    "iso:country":"NL",
    "sg:address":"Noordplein 21",
    "sg:city":"Roelofarendsveen",
    "sg:orig_category":"Opticiens",
    "sg:phone":"+31 71 331 5690",
    "sg:postcode":"2371 DA",
    "sg:province":"South Holland",
    "wof:name":"Ed Fraser Optiek",
    "wof:placetype":"venue"
},
  "geometry": {"coordinates":[4.6318898201,52.2017211914],"type":"Point"}
}