{
  "type": "Feature",
  "properties": {
    "iso:country":"NL",
    "sg:address":"Barndegat 18",
    "sg:city":"Zaandam",
    "sg:orig_category":"Autokeuringen",
    "sg:phone":"+31 75 631 1389",
    "sg:postcode":"1505 HN",
    "sg:province":"North Holland",
    "wof:name":"All Car Service",
    "wof:placetype":"venue"
},
  "geometry": {"coordinates":[4.859691,52.427738],"type":"Point"}
}