{
  "type": "Feature",
  "properties": {
    "iso:country":"NL",
    "sg:address":"De Staetekamer 1-3",
    "sg:city":"Amersfoort",
    "sg:orig_category":"Video - Faciliteiten En Producties",
    "sg:phone":"+31 33 455 1551",
    "sg:postcode":"3823 VN",
    "sg:province":"Utrecht",
    "wof:name":"Sts",
    "wof:placetype":"venue"
},
  "geometry": {"coordinates":[5.401975,52.189606],"type":"Point"}
}