{
  "type": "Feature",
  "properties": {
    "addr:full":"Yslandsestr 7 Delfzyl Groningen 9933 NJ",
    "addr:housenumber":"7",
    "addr:postcode":"9933 nj",
    "addr:street":"Yslandsestr",
    "iso:country":"NL",
    "sg:address":"Yslandsestr 7",
    "sg:city":"Delfzyl",
    "sg:orig_category":"Scholen Voor Basisonderwijs",
    "sg:phone":"+31 596 614 462",
    "sg:postcode":"9933 NJ",
    "sg:province":"Groningen",
    "wof:name":"Noorman, Obs Voor Dalton Onderwijs De",
    "wof:placetype":"venue"
},
  "geometry": {"coordinates":[6.90992,53.337723],"type":"Point"}
}