{
  "type": "Feature",
  "properties": {
    "iso:country":"NL",
    "sg:address":"Industriepk 7A",
    "sg:city":"Zelhem",
    "sg:orig_category":"Kunststoffen - Fabrieken En Groothandel",
    "sg:phone":"+31 314 620 262",
    "sg:postcode":"7021 BK",
    "sg:province":"Gelderland",
    "wof:name":"Putman",
    "wof:placetype":"venue"
},
  "geometry": {"coordinates":[6.347596,52.001228],"type":"Point"}
}