{
  "type": "Feature",
  "properties": {
    "addr:full":"Steenstr 82 Arnhem Gelderland 6828 CN",
    "addr:housenumber":"82",
    "addr:postcode":"6828 cn",
    "addr:street":"Steenstr",
    "iso:country":"NL",
    "sg:address":"Steenstr 82",
    "sg:city":"Arnhem",
    "sg:orig_category":"Poeliers",
    "sg:phone":"+31 26 445 7299",
    "sg:postcode":"6828 CN",
    "sg:province":"Gelderland",
    "sg:website":"http://www.ronvanhal.nl",
    "wof:name":"Hal Poeliersbedrijf, Ron Van",
    "wof:placetype":"venue"
},
  "geometry": {"coordinates":[5.919188,51.984219],"type":"Point"}
}