{
  "type": "Feature",
  "properties": {
    "addr:full":"De Munckhof 26 Sint Geertruid Limburg 6265 BH",
    "addr:housenumber":"26",
    "addr:postcode":"6265 bh",
    "addr:street":"De Munckhof",
    "iso:country":"NL",
    "sg:address":"De Munckhof 26",
    "sg:city":"Sint Geertruid",
    "sg:orig_category":"Fietshandelaren",
    "sg:phone":"+31 43 408 3554",
    "sg:postcode":"6265 BH",
    "sg:province":"Limburg",
    "wof:name":"Motorhuis Felix En Jos Bv",
    "wof:placetype":"venue"
},
  "geometry": {"coordinates":[5.76688,50.798141],"type":"Point"}
}