{
  "type": "Feature",
  "properties": {
    "addr:full":"Kruisstr 47B Eindhoven Noord-Brabant 5612 CC",
    "addr:housenumber":"47b",
    "addr:postcode":"5612 cc",
    "addr:street":"Kruisstr",
    "iso:country":"NL",
    "sg:address":"Kruisstr 47B",
    "sg:city":"Eindhoven",
    "sg:orig_category":"Juweliers",
    "sg:phone":"+31 40 245 3100",
    "sg:postcode":"5612 CC",
    "sg:province":"Noord-Brabant",
    "wof:name":"Bigodi Juweliers & Diamantairs",
    "wof:placetype":"venue"
},
  "geometry": {"coordinates":[5.475088,51.444729],"type":"Point"}
}