{
  "type": "Feature",
  "properties": {
    "addr:full":"Ridderschapstr 4 Utrecht Utrecht 3512 CP",
    "addr:housenumber":"4",
    "addr:postcode":"3512 cp",
    "addr:street":"Ridderschapstr",
    "iso:country":"NL",
    "sg:address":"Ridderschapstr 4",
    "sg:city":"Utrecht",
    "sg:orig_category":"Kinderopvang",
    "sg:phone":"+31 30 234 0392",
    "sg:postcode":"3512 CP",
    "sg:province":"Utrecht",
    "wof:name":"Koetshuis, Het",
    "wof:placetype":"venue"
},
  "geometry": {"coordinates":[5.124531,52.095348],"type":"Point"}
}