{
  "type": "Feature",
  "properties": {
    "addr:full":"J W Frisolaan 2 Ijsselstein Ut Utrecht 3401 AX",
    "addr:housenumber":"2",
    "addr:postcode":"3401 ax",
    "addr:street":"W Frisolaan",
    "iso:country":"NL",
    "sg:address":"J W Frisolaan 2",
    "sg:city":"Ijsselstein Ut",
    "sg:classifiers":[
        {
            "category":"Education",
            "subcategory":"Preschool",
            "type":"Public Place"
        }
    ],
    "sg:phone":"+31 30 688 1821",
    "sg:postcode":"3401 AX",
    "sg:province":"Utrecht",
    "sg:tags":[
        "kleuteronderwijs",
        "basis-"
    ],
    "wof:name":"Openbare Basisschool De Touwladder",
    "wof:placetype":"venue"
},
  "geometry": {"coordinates":[5.042223,52.022095],"type":"Point"}
}