{
  "type": "Feature",
  "properties": {
    "addr:full":"Postbus 314 Aalsmeer Noord-Holland 1430 AH",
    "addr:housenumber":"314",
    "addr:postcode":"1430 ah",
    "addr:street":"Postbus",
    "iso:country":"NL",
    "sg:address":"Postbus 314",
    "sg:city":"Aalsmeer",
    "sg:orig_category":"Bloemen En Planten - Groothandel",
    "sg:phone":"+31 297 341 129",
    "sg:postcode":"1430 AH",
    "sg:province":"Noord-Holland",
    "wof:name":"Dings Bv, Leon",
    "wof:placetype":"venue"
},
  "geometry": {"coordinates":[4.749068,52.266991],"type":"Point"}
}