{
  "type": "Feature",
  "properties": {
    "addr:full":"Oostenburgergr 17 Amsterdam North Holland 1018 NA",
    "addr:housenumber":"17",
    "addr:postcode":"1018 na",
    "addr:street":"Oostenburgergr",
    "iso:country":"NL",
    "sg:address":"Oostenburgergr 17",
    "sg:city":"Amsterdam",
    "sg:orig_category":"Beeldende Kunstenaars",
    "sg:phone":"+31 20 620 1307",
    "sg:postcode":"1018 NA",
    "sg:province":"North Holland",
    "wof:name":"Rubens, J G",
    "wof:placetype":"venue"
},
  "geometry": {"coordinates":[4.92129,52.369171],"type":"Point"}
}