{
  "type": "Feature",
  "properties": {
    "addr:full":"Broekveldseln 1 Bodegraven South Holland 2411 NL",
    "addr:housenumber":"1",
    "addr:postcode":"2411 nl",
    "addr:street":"Broekveldseln",
    "iso:country":"NL",
    "sg:address":"Broekveldseln 1",
    "sg:city":"Bodegraven",
    "sg:orig_category":"Bewakingsdiensten",
    "sg:phone":"+31 172 615 757",
    "sg:postcode":"2411 NL",
    "sg:province":"South Holland",
    "sg:website":"http://www.bbd.nl",
    "wof:name":"Bbd Bodegraafse Bewakingsdienst",
    "wof:placetype":"venue"
},
  "geometry": {"coordinates":[4.744802,52.073009],"type":"Point"}
}