{
  "type": "Feature",
  "properties": {
    "addr:full":"Arent Janszoon Ernststr 55 Amsterdam Noord-Holland 1083 GR",
    "addr:housenumber":"55",
    "addr:postcode":"1083",
    "addr:street":"Arent Janszoon Ernststr",
    "iso:country":"NL",
    "sg:address":"Arent Janszoon Ernststr 55",
    "sg:city":"Amsterdam",
    "sg:classifiers":[
        {
            "category":"Professional",
            "subcategory":"Accounting & Tax Preparation",
            "type":"Services"
        }
    ],
    "sg:phone":"+31 20 301 0301",
    "sg:postcode":"1083 GR",
    "sg:province":"Noord-Holland",
    "sg:tags":[
        "accountant"
    ],
    "wof:name":"Koninklijk Nivra",
    "wof:placetype":"venue"
},
  "geometry": {"coordinates":[4.888777,52.331814],"type":"Point"}
}