{
  "type": "Feature",
  "properties": {
    "addr:full":"Nootwg 30 Loosdrecht Noord-Holland 1231 CV",
    "addr:housenumber":"30",
    "addr:postcode":"1231 cv",
    "addr:street":"Nootwg",
    "iso:country":"NL",
    "sg:address":"Nootwg 30",
    "sg:city":"Loosdrecht",
    "sg:orig_category":"Meubelen",
    "sg:phone":"+31 35 647 1073",
    "sg:postcode":"1231 CV",
    "sg:province":"Noord-Holland",
    "wof:name":"Voorhuis, 'T",
    "wof:placetype":"venue"
},
  "geometry": {"coordinates":[5.139611,52.199551],"type":"Point"}
}