{
  "type": "Feature",
  "properties": {
    "iso:country":"NL",
    "sg:address":"Henderweg 2",
    "sg:city":"Weert",
    "sg:orig_category":"Pluimveehouderijen",
    "sg:phone":"+31 495 536 229",
    "sg:postcode":"6002 SH",
    "sg:province":"Limburg",
    "wof:name":"J.M. Van Heugten",
    "wof:placetype":"venue"
},
  "geometry": {"coordinates":[5.674181,51.253883],"type":"Point"}
}