{
  "type": "Feature",
  "properties": {
    "iso:country":"NL",
    "sg:address":"Manitobadreef 8",
    "sg:city":"Utrecht",
    "sg:orig_category":"Sportverenigingen En Ontspannings- Verenigingen",
    "sg:phone":"+31 30 261 7087",
    "sg:postcode":"3565 CH",
    "sg:province":"Utrecht",
    "wof:name":"Hms, Sportver",
    "wof:placetype":"venue"
},
  "geometry": {"coordinates":[5.086155,52.130928],"type":"Point"}
}