{
  "type": "Feature",
  "properties": {
    "iso:country":"NL",
    "sg:address":"Uraniumwg 15",
    "sg:city":"Amersfoort",
    "sg:orig_category":"Verpakkingsbedrijven",
    "sg:phone":"+31 33 460 1200",
    "sg:postcode":"3812 RJ",
    "sg:province":"Utrecht",
    "sg:website":"http://www.rwa.nl",
    "wof:name":"Rwa Verpakken",
    "wof:placetype":"venue"
},
  "geometry": {"coordinates":[5.35721,52.166794],"type":"Point"}
}