{
  "type": "Feature",
  "properties": {
    "addr:full":"De Tol 12A Ameide Zuid-Holland 4233 GH",
    "addr:housenumber":"12a",
    "addr:postcode":"4233 gh",
    "addr:street":"De Tol",
    "iso:country":"NL",
    "sg:address":"De Tol 12A",
    "sg:city":"Ameide",
    "sg:orig_category":"Kinderopvang Behalve Thuis",
    "sg:phone":"+31 183 602 433",
    "sg:postcode":"4233 GH",
    "sg:province":"Zuid-Holland",
    "wof:name":"Peuterspeelzaal Ot En Sien",
    "wof:placetype":"venue"
},
  "geometry": {"coordinates":[4.961552,51.95253],"type":"Point"}
}