{
  "type": "Feature",
  "properties": {
    "addr:full":"Kokswijk 19 Zevenhuizen Gn Groningen 9354 BV",
    "addr:housenumber":"19;gn",
    "addr:postcode":"9354 bv",
    "addr:street":"Kokswijk",
    "iso:country":"NL",
    "sg:address":"Kokswijk 19",
    "sg:city":"Zevenhuizen Gn",
    "sg:orig_category":"Houtverwerking",
    "sg:phone":"+31 594 632 323",
    "sg:postcode":"9354 BV",
    "sg:province":"Groningen",
    "wof:name":"S. Polling Boomzagerij",
    "wof:placetype":"venue"
},
  "geometry": {"coordinates":[6.352089,53.123077],"type":"Point"}
}