{
  "type": "Feature",
  "properties": {
    "iso:country":"NL",
    "sg:address":"Kerkstraat 3",
    "sg:city":"Geertruidenberg",
    "sg:orig_category":"Boekhouders",
    "sg:phone":"+31 416 352 889",
    "sg:postcode":"4931 AR",
    "sg:province":"Noord-Brabant",
    "wof:name":"Administratiekantoor Joop Rossaert",
    "wof:placetype":"venue"
},
  "geometry": {"coordinates":[4.858335,51.701351],"type":"Point"}
}