{
  "type": "Feature",
  "properties": {
    "addr:full":"Soldeniersveld 117 Apeldoorn Gelderland 7327 GJ",
    "addr:housenumber":"117",
    "addr:postcode":"7327 gj",
    "addr:street":"Soldeniersveld;Gelderland",
    "iso:country":"NL",
    "sg:address":"Soldeniersveld 117",
    "sg:city":"Apeldoorn",
    "sg:orig_category":"Diverse Opleidingen And Onderwijs",
    "sg:phone":"+31 55 541 5353",
    "sg:postcode":"7327 GJ",
    "sg:province":"Gelderland",
    "wof:name":"Kbt",
    "wof:placetype":"venue"
},
  "geometry": {"coordinates":[6.001004,52.185093],"type":"Point"}
}