{
  "type": "Feature",
  "properties": {
    "addr:full":"W De Withstr 31-33 S Gravenhage Zuid-Holland 2518 CP",
    "addr:housenumber":"31-33;gravenhage",
    "addr:postcode":"2518 cp",
    "addr:street":"W De Withstr;S",
    "iso:country":"NL",
    "sg:address":"W De Withstr 31-33",
    "sg:city":"S Gravenhage",
    "sg:orig_category":"Bibliotheken En Leeszalen Openbare",
    "sg:phone":"+31 70 355 9762",
    "sg:postcode":"2518 CP",
    "sg:province":"Zuid-Holland",
    "wof:name":"Deutsche Bibliothek Den Haag",
    "wof:placetype":"venue"
},
  "geometry": {"coordinates":[4.29348,52.080318],"type":"Point"}
}