{
  "type": "Feature",
  "properties": {
    "addr:full":"Via Regia 143B Maastricht Limburg 6216 BV",
    "addr:housenumber":"143b",
    "addr:postcode":"6216 bv",
    "addr:street":"Via Regia",
    "iso:country":"NL",
    "sg:address":"Via Regia 143B",
    "sg:city":"Maastricht",
    "sg:orig_category":"Adviesbureaus Bedrijfsorganisatie",
    "sg:phone":"+31 43 344 0116",
    "sg:postcode":"6216 BV",
    "sg:province":"Limburg",
    "wof:name":"Dokter Bv",
    "wof:placetype":"venue"
},
  "geometry": {"coordinates":[5.666871,50.851933],"type":"Point"}
}