{
  "type": "Feature",
  "properties": {
    "addr:full":"Hazenkoog 15J Alkmaar Noord-Holland 1822 BS",
    "addr:housenumber":"15j",
    "addr:postcode":"1822 bs",
    "addr:street":"Hazenkoog",
    "iso:country":"NL",
    "sg:address":"Hazenkoog 15J",
    "sg:city":"Alkmaar",
    "sg:orig_category":"Partycatering And -Organisatie",
    "sg:phone":"+31 72 561 9492",
    "sg:postcode":"1822 BS",
    "sg:province":"Noord-Holland",
    "wof:name":"Indah Permai",
    "wof:placetype":"venue"
},
  "geometry": {"coordinates":[4.792752,52.651924],"type":"Point"}
}