{
  "type": "Feature",
  "properties": {
    "addr:full":"Startbaan 25 Amstelveen Noord-Holland 1185 XP",
    "addr:housenumber":"25",
    "addr:postcode":"1185 xp",
    "addr:street":"Startbaan",
    "iso:country":"NL",
    "sg:address":"Startbaan 25",
    "sg:city":"Amstelveen",
    "sg:orig_category":"Glaszetten",
    "sg:phone":"+31 20 641 8588",
    "sg:postcode":"1185 XP",
    "sg:province":"Noord-Holland",
    "wof:name":"Schildersbedrijf En Meubelspuiterij Loman Bv",
    "wof:placetype":"venue"
},
  "geometry": {"coordinates":[4.850548,52.287247],"type":"Point"}
}