{
  "type": "Feature",
  "properties": {
    "addr:full":"Schiewg 62 Delft Zuid-Holland 2627 AN",
    "addr:housenumber":"62",
    "addr:postcode":"2627 an",
    "addr:street":"Schiewg",
    "iso:country":"NL",
    "sg:address":"Schiewg 62",
    "sg:city":"Delft",
    "sg:orig_category":"Pneumatische Apparaten En Installaties",
    "sg:phone":"+31 15 251 8899",
    "sg:postcode":"2627 AN",
    "sg:province":"Zuid-Holland",
    "wof:name":"Festo Bv",
    "wof:placetype":"venue"
},
  "geometry": {"coordinates":[4.366818,51.992477],"type":"Point"}
}