{
  "type": "Feature",
  "properties": {
    "addr:full":"Graan Voor Visch 14402 Hoofddorp Noord-Holland 2132 VH",
    "addr:housenumber":"14402",
    "addr:postcode":"2132 vh",
    "addr:street":"Graan Voor Visch",
    "iso:country":"NL",
    "sg:address":"Graan Voor Visch 14402",
    "sg:city":"Hoofddorp",
    "sg:classifiers":[
        {
            "category":"Education",
            "subcategory":"Preschool",
            "type":"Public Place"
        }
    ],
    "sg:phone":"+31 23 561 5029",
    "sg:postcode":"2132 VH",
    "sg:province":"Noord-Holland",
    "sg:tags":[
        "kleuteronderwijs",
        "basis-"
    ],
    "wof:name":"De Wegwijzer",
    "wof:placetype":"venue"
},
  "geometry": {"coordinates":[4.691659,52.294621],"type":"Point"}
}