{
  "type": "Feature",
  "properties": {
    "addr:full":"Koningshoek 92376 Maassluis Zuid-Holland 3144 BA",
    "addr:housenumber":"92376",
    "addr:postcode":"3144 ba",
    "addr:street":"Koningshoek",
    "iso:country":"NL",
    "sg:address":"Koningshoek 92376",
    "sg:city":"Maassluis",
    "sg:orig_category":"Schoenen",
    "sg:phone":"+31 10 592 1275",
    "sg:postcode":"3144 BA",
    "sg:province":"Zuid-Holland",
    "wof:name":"Tiron Bv",
    "wof:placetype":"venue"
},
  "geometry": {"coordinates":[4.239929,51.92791],"type":"Point"}
}