{
  "type": "Feature",
  "properties": {
    "iso:country":"NL",
    "sg:address":"Zustersstr 25",
    "sg:city":"Venlo",
    "sg:orig_category":"Peuterspeelzalen",
    "sg:phone":"+31 77 326 6770",
    "sg:postcode":"5914 XX",
    "sg:province":"Limburg",
    "wof:name":"Christoffeltje",
    "wof:placetype":"venue"
},
  "geometry": {"coordinates":[6.181362,51.37569],"type":"Point"}
}