{
  "type": "Feature",
  "properties": {
    "iso:country":"NL",
    "sg:address":"Verl Middenraai 89",
    "sg:city":"Nieuw Balinge",
    "sg:orig_category":"Honden- En Kattentrimsalons",
    "sg:phone":"+31 528 321 771",
    "sg:postcode":"7938 PB",
    "sg:province":"Drenthe",
    "sg:website":"http://www.riesenschnauzer.myweb.nl",
    "wof:name":"Arno, Hondentrimsalon",
    "wof:placetype":"venue"
},
  "geometry": {"coordinates":[6.605997,52.763714],"type":"Point"}
}