{
  "type": "Feature",
  "properties": {
    "addr:full":"Irawan Soejonostraat 37 Amsterdam Noord-Holland 1069 PG",
    "addr:housenumber":"37",
    "addr:postcode":"1069 pg",
    "addr:street":"Irawan Soejonostraat",
    "iso:country":"NL",
    "sg:address":"Irawan Soejonostraat 37",
    "sg:city":"Amsterdam",
    "sg:orig_category":"Loodgieterswerk, Verwarming And Sanitaire Installaties",
    "sg:phone":"+31 20 619 7877",
    "sg:postcode":"1069 PG",
    "sg:province":"Noord-Holland",
    "wof:name":"Timmerbedrijf Kerkmeer",
    "wof:placetype":"venue"
},
  "geometry": {"coordinates":[4.784296,52.352169],"type":"Point"}
}