{
  "type": "Feature",
  "properties": {
    "iso:country":"NL",
    "sg:address":"Vd Willigenstr 102",
    "sg:city":"Lekkerkerk",
    "sg:orig_category":"Verenigingen En Stichtingen",
    "sg:phone":"+31 180 667 460",
    "sg:postcode":"2941 ES",
    "sg:province":"Zuid-Holland",
    "wof:name":"Isp Wiw, Sticht",
    "wof:placetype":"venue"
},
  "geometry": {"coordinates":[4.683374,51.896568],"type":"Point"}
}