{
  "type": "Feature",
  "properties": {
    "addr:full":"Leeuwenbekstr 9 St Willebrord Noord-Brabant 4711 GZ",
    "addr:housenumber":"9",
    "addr:postcode":"4711 gz",
    "addr:street":"Leeuwenbekstr",
    "iso:country":"NL",
    "sg:address":"Leeuwenbekstr 9",
    "sg:city":"St Willebrord",
    "sg:orig_category":"Kappers",
    "sg:phone":"+31 165 388 786",
    "sg:postcode":"4711 GZ",
    "sg:province":"Noord-Brabant",
    "wof:name":"Nicolette",
    "wof:placetype":"venue"
},
  "geometry": {"coordinates":[4.58428,51.546745],"type":"Point"}
}