{
  "type": "Feature",
  "properties": {
    "addr:full":"Grt Bagynestr 10 Hulst Zeeland 4561 CJ",
    "addr:housenumber":"10",
    "addr:postcode":"4561 cj",
    "iso:country":"NL",
    "sg:address":"Grt Bagynestr 10",
    "sg:city":"Hulst",
    "sg:orig_category":"Verzekeringen - Verzekeringskantoren",
    "sg:phone":"+31 114 312 518",
    "sg:postcode":"4561 CJ",
    "sg:province":"Zeeland",
    "wof:name":"Eeckhout, A J E",
    "wof:placetype":"venue"
},
  "geometry": {"coordinates":[4.055065,51.280945],"type":"Point"}
}