{
  "type": "Feature",
  "properties": {
    "addr:full":"Eswal 2 Vries Drenthe 9481 TK",
    "addr:housenumber":"2",
    "addr:postcode":"9481 tk",
    "addr:street":"Eswal",
    "iso:country":"NL",
    "sg:address":"Eswal 2",
    "sg:city":"Vries",
    "sg:classifiers":[
        {
            "category":"Sports & Exercise",
            "subcategory":"Stables",
            "type":"Entertainment"
        }
    ],
    "sg:phone":"+31 592 541 666",
    "sg:postcode":"9481 TK",
    "sg:province":"Drenthe",
    "sg:tags":[
        "maneges"
    ],
    "wof:name":"Eswal",
    "wof:placetype":"venue"
},
  "geometry": {"coordinates":[-85.944946,42.811916],"type":"Point"}
}