{
  "type": "Feature",
  "properties": {
    "addr:full":"Ronkelskamp 83 Annen Drenthe 9468 ES",
    "addr:housenumber":"83",
    "addr:postcode":"9468 es",
    "addr:street":"Ronkelskamp",
    "iso:country":"NL",
    "sg:address":"Ronkelskamp 83",
    "sg:city":"Annen",
    "sg:orig_category":"Technische Studies And Onderzoek",
    "sg:phone":"+31 592 272 226",
    "sg:postcode":"9468 ES",
    "sg:province":"Drenthe",
    "wof:name":"Rue De Rogier",
    "wof:placetype":"venue"
},
  "geometry": {"coordinates":[-79.253815,33.471233],"type":"Point"}
}