{
  "type": "Feature",
  "properties": {
    "addr:full":"Terborchdreef 14 Oud Beijerland South Holland 3262 NB",
    "addr:housenumber":"14",
    "addr:postcode":"3262 nb",
    "addr:street":"Terborchdreef;Oud Beijerland",
    "iso:country":"NL",
    "sg:address":"Terborchdreef 14",
    "sg:city":"Oud Beijerland",
    "sg:orig_category":"Boekhouders",
    "sg:phone":"+31 186 616 147",
    "sg:postcode":"3262 NB",
    "sg:province":"South Holland",
    "wof:name":"Administratiekantoor C. Van Tilburg Bv",
    "wof:placetype":"venue"
},
  "geometry": {"coordinates":[4.41307,51.817707],"type":"Point"}
}