{
  "type": "Feature",
  "properties": {
    "addr:full":"Maasheseweg 89 Venray Limburg 5804 AB",
    "addr:housenumber":"89",
    "addr:postcode":"5804 ab",
    "addr:street":"Maasheseweg",
    "iso:country":"NL",
    "sg:address":"Maasheseweg 89",
    "sg:city":"Venray",
    "sg:orig_category":"Werving And Selectie Van Tijdelijk Personeel And Uitzendkantoren",
    "sg:phone":"+31 478 580 850",
    "sg:postcode":"5804 AB",
    "sg:province":"Limburg",
    "wof:name":"Start",
    "wof:placetype":"venue"
},
  "geometry": {"coordinates":[5.9951581955,51.5478858948],"type":"Point"}
}