{
  "type": "Feature",
  "properties": {
    "iso:country":"NL",
    "sg:address":"Baarleseweg 1 C",
    "sg:city":"Ulicoten",
    "sg:orig_category":"Kampeerterreinen",
    "sg:phone":"+31 13 519 9264",
    "sg:postcode":"5113 TA",
    "sg:province":"North Brabant",
    "wof:name":"Ncc-Terrein De Smokkelhoek",
    "wof:placetype":"venue"
},
  "geometry": {"coordinates":[4.8874650002,51.4512443542],"type":"Point"}
}