{
  "type": "Feature",
  "properties": {
    "addr:full":"Bongertsweg 45 Hengelo Ov Overijssel 7557 BN",
    "addr:housenumber":"45",
    "addr:postcode":"7557 bn",
    "addr:street":"Bongertsweg;Ov",
    "iso:country":"NL",
    "sg:address":"Bongertsweg 45",
    "sg:city":"Hengelo Ov",
    "sg:orig_category":"Parfum And Cosmetica Gh",
    "sg:phone":"+31 74 291 1960",
    "sg:postcode":"7557 BN",
    "sg:province":"Overijssel",
    "wof:name":"Haarinstituut Het Twentse Haarhuis Bv",
    "wof:placetype":"venue"
},
  "geometry": {"coordinates":[6.804909,52.266163],"type":"Point"}
}