{
  "type": "Feature",
  "properties": {
    "addr:full":"Goeverneurln 387 S Gravenhage South Holland 2523 CA",
    "addr:housenumber":"387",
    "addr:postcode":"2523 ca",
    "addr:street":"S Gravenhage",
    "iso:country":"NL",
    "sg:address":"Goeverneurln 387",
    "sg:city":"S Gravenhage",
    "sg:orig_category":"Onderhoudswerken",
    "sg:phone":"+31 70 336 0083",
    "sg:postcode":"2523 CA",
    "sg:province":"South Holland",
    "wof:name":"Linden",
    "wof:placetype":"venue"
},
  "geometry": {"coordinates":[4.31927,52.056469],"type":"Point"}
}