{
  "type": "Feature",
  "properties": {
    "addr:full":"Zeeanemoonwg 6 Renesse Zeeland 4325 BZ",
    "addr:housenumber":"6",
    "addr:postcode":"4325 bz",
    "addr:street":"Zeeanemoonwg",
    "iso:country":"NL",
    "sg:address":"Zeeanemoonwg 6",
    "sg:city":"Renesse",
    "sg:orig_category":"Banken",
    "sg:phone":"+31 111 418 500",
    "sg:postcode":"4325 BZ",
    "sg:province":"Zeeland",
    "sg:website":"http://www.rabobank.nl",
    "wof:name":"Rabobank",
    "wof:placetype":"venue"
},
  "geometry": {"coordinates":[3.770793,51.73217],"type":"Point"}
}