{
  "type": "Feature",
  "properties": {
    "addr:full":"Van Salm Salmstraat 1 Loon Op Zand Noord-Brabant 5175 CE",
    "addr:housenumber":"1",
    "addr:postcode":"5175 ce",
    "addr:street":"Van Salm Salmstraat",
    "iso:country":"NL",
    "sg:address":"Van Salm Salmstraat 1",
    "sg:city":"Loon Op Zand",
    "sg:orig_category":"Verpakkingsmachines Fab",
    "sg:phone":"+31 416 361 815",
    "sg:postcode":"5175 CE",
    "sg:province":"Noord-Brabant",
    "wof:name":"Van Beers Mechatronica",
    "wof:placetype":"venue"
},
  "geometry": {"coordinates":[5.065515,51.629929],"type":"Point"}
}