{
  "type": "Feature",
  "properties": {
    "addr:full":"D Wierengastr 69 Enkhuizen Noord-Holland 1602 TM",
    "addr:housenumber":"69",
    "addr:postcode":"1602 tm",
    "iso:country":"NL",
    "sg:address":"D Wierengastr 69",
    "sg:city":"Enkhuizen",
    "sg:orig_category":"Verzekeringen - Verzekeringskantoren",
    "sg:phone":"+31 228 312 413",
    "sg:postcode":"1602 TM",
    "sg:province":"Noord-Holland",
    "wof:name":"Kaljee, T H A",
    "wof:placetype":"venue"
},
  "geometry": {"coordinates":[5.281704,52.710503],"type":"Point"}
}