{
  "type": "Feature",
  "properties": {
    "addr:full":"Parkhof 18 Belfeld Limburg 5951 RA",
    "addr:housenumber":"18",
    "addr:postcode":"5951 ra",
    "addr:street":"Parkhof",
    "iso:country":"NL",
    "sg:address":"Parkhof 18",
    "sg:city":"Belfeld",
    "sg:orig_category":"Kappers",
    "sg:phone":"+31 77 475 1618",
    "sg:postcode":"5951 RA",
    "sg:province":"Limburg",
    "wof:name":"M.G. Peulen",
    "wof:placetype":"venue"
},
  "geometry": {"coordinates":[6.118943,51.308029],"type":"Point"}
}