{
  "type": "Feature",
  "properties": {
    "addr:full":"Reigerstr 37 Alphen Aan Den Ryn Zuid-Holland 2406 VC",
    "addr:housenumber":"37",
    "addr:postcode":"2406 vc",
    "addr:street":"Reigerstr;Aan Den Ryn",
    "iso:country":"NL",
    "sg:address":"Reigerstr 37",
    "sg:city":"Alphen Aan Den Ryn",
    "sg:orig_category":"Elektrotechnische Installatiebureaus",
    "sg:phone":"+31 172 494 378",
    "sg:postcode":"2406 VC",
    "sg:province":"Zuid-Holland",
    "wof:name":"Aad Van Uithove Electrotechniek",
    "wof:placetype":"venue"
},
  "geometry": {"coordinates":[4.666096,52.133053],"type":"Point"}
}