{
  "type": "Feature",
  "properties": {
    "addr:full":"St. Annaplein 14 Tilburg North Brabant 5038 TV",
    "addr:housenumber":"14",
    "addr:postcode":"5038 tv",
    "iso:country":"NL",
    "sg:address":"St. Annaplein 14",
    "sg:city":"Tilburg",
    "sg:orig_category":"Medische And Orthopedische Artikelen",
    "sg:phone":"+31 13 535 0017",
    "sg:postcode":"5038 TV",
    "sg:province":"North Brabant",
    "wof:name":"Van Rijswijk Bv",
    "wof:placetype":"venue"
},
  "geometry": {"coordinates":[5.077247,51.554562],"type":"Point"}
}