{
  "type": "Feature",
  "properties": {
    "iso:country":"NL",
    "sg:address":"Broekheurnerwg 13",
    "sg:city":"Haaksbergen",
    "sg:orig_category":"Manueel Therapeuten",
    "sg:phone":"+31 53 569 6503",
    "sg:postcode":"7481 PX",
    "sg:province":"Overijssel",
    "wof:name":"Boer, C M De",
    "wof:placetype":"venue"
},
  "geometry": {"coordinates":[6.827152,52.146748],"type":"Point"}
}