{
  "type": "Feature",
  "properties": {
    "addr:full":"Nieuwstraat 12 Vlaardingen South Holland 3134 EP",
    "addr:housenumber":"12",
    "addr:postcode":"3134 ep",
    "addr:street":"Nieuwstraat",
    "iso:country":"NL",
    "sg:address":"Nieuwstraat 12",
    "sg:city":"Vlaardingen",
    "sg:orig_category":"Kunststof Ramen",
    "sg:phone":"+31 10 232 7010",
    "sg:postcode":"3134 EP",
    "sg:province":"South Holland",
    "wof:name":"Kroon",
    "wof:placetype":"venue"
},
  "geometry": {"coordinates":[4.348209,51.906788],"type":"Point"}
}