{
  "type": "Feature",
  "properties": {
    "addr:full":"Provincialeweg 1 Bergambacht South Holland 2861 EB",
    "addr:housenumber":"1",
    "addr:postcode":"2861 eb",
    "addr:street":"Provincialeweg",
    "iso:country":"NL",
    "sg:address":"Provincialeweg 1",
    "sg:city":"Bergambacht",
    "sg:orig_category":"Waterbehandeling En Waterzuiverings- Systemen",
    "sg:phone":"+31 182 358 555",
    "sg:postcode":"2861 EB",
    "sg:province":"South Holland",
    "sg:website":"http://www.dzh.nl",
    "wof:name":"Dzh Bergambacht",
    "wof:placetype":"venue"
},
  "geometry": {"coordinates":[4.759062767,51.9274978638],"type":"Point"}
}