{
  "type": "Feature",
  "properties": {
    "addr:full":"Lg Akkerwg 17 Someren Noord-Brabant 5711 DD",
    "addr:housenumber":"17",
    "addr:postcode":"5711 dd",
    "addr:street":"Lg",
    "iso:country":"NL",
    "sg:address":"Lg Akkerwg 17",
    "sg:city":"Someren",
    "sg:classifiers":[
        {
            "category":"Wholesale",
            "subcategory":"Meat",
            "type":"Manufacturing & Wholesale Goods"
        }
    ],
    "sg:phone":"+31 493 440 015",
    "sg:postcode":"5711 DD",
    "sg:province":"Noord-Brabant",
    "sg:tags":[
        "regeltechniek",
        "en",
        "meet-"
    ],
    "wof:name":"Eurotherm Bv",
    "wof:placetype":"venue"
},
  "geometry": {"coordinates":[5.731273,51.388359],"type":"Point"}
}