{
  "type": "Feature",
  "properties": {
    "addr:full":"Brink 26 Dwingeloo Provincie Drenthe 7991 CH",
    "addr:housenumber":"26",
    "addr:postcode":"7991",
    "addr:street":"Brink;Provincie Drenthe",
    "iso:country":"NL",
    "sg:address":"Brink 26",
    "sg:city":"Dwingeloo",
    "sg:classifiers":[
        {
            "category":"Travel",
            "subcategory":"Hotels & Motels",
            "type":"Entertainment"
        }
    ],
    "sg:phone":"+31 521 591 544",
    "sg:postcode":"7991 CH",
    "sg:province":"Provincie Drenthe",
    "wof:name":"Wesseling Hotel-Caf?-Restaurant",
    "wof:placetype":"venue"
},
  "geometry": {"coordinates":[6.365521,52.834263],"type":"Point"}
}