{
  "type": "Feature",
  "properties": {
    "addr:full":"Eerste Helmersstraat 267 Amsterdam Noord-Holland 1054 DZ",
    "addr:housenumber":"267",
    "addr:postcode":"1054 dz",
    "addr:street":"Eerste Helmersstraat",
    "iso:country":"NL",
    "sg:address":"Eerste Helmersstraat 267",
    "sg:city":"Amsterdam",
    "sg:orig_category":"Paramedische Behandelingen",
    "sg:phone":"+31 20 618 6157",
    "sg:postcode":"1054 DZ",
    "sg:province":"Noord-Holland",
    "wof:name":"Logopedie Groepspraktijk Oud- West",
    "wof:placetype":"venue"
},
  "geometry": {"coordinates":[4.864335,52.3606],"type":"Point"}
}