{
  "type": "Feature",
  "properties": {
    "iso:country":"NL",
    "sg:address":"Gebroek 71",
    "sg:city":"Roermond",
    "sg:orig_category":"Bloemen And Planten",
    "sg:phone":"+31 475 332 872",
    "sg:postcode":"6044 XC",
    "sg:province":"Limburg",
    "wof:name":"Tuincentrum Bloemisterij Van Eck",
    "wof:placetype":"venue"
},
  "geometry": {"coordinates":[6.002312,51.183163],"type":"Point"}
}