{
  "type": "Feature",
  "properties": {
    "addr:full":"Grasweg 3 Amsterdam Noord North Holland 1031 HW",
    "addr:housenumber":"3",
    "addr:postcode":"1031 hw",
    "addr:street":"Grasweg",
    "iso:country":"NL",
    "sg:address":"Grasweg 3",
    "sg:city":"Amsterdam Noord",
    "sg:orig_category":"Autoreparatie And Auto-Onderhoud",
    "sg:phone":"+31 20 637 1826",
    "sg:postcode":"1031 HW",
    "sg:province":"North Holland",
    "wof:name":"Garagebedrijf D.Faas",
    "wof:placetype":"venue"
},
  "geometry": {"coordinates":[4.905259,52.388638],"type":"Point"}
}