{
  "type": "Feature",
  "properties": {
    "addr:full":"Henschoterln 12 Woudenberg Utrecht 3931 DB",
    "addr:housenumber":"12",
    "addr:postcode":"3931 db",
    "addr:street":"Henschoterln",
    "iso:country":"NL",
    "sg:address":"Henschoterln 12",
    "sg:city":"Woudenberg",
    "sg:orig_category":"Adviesbureaus Bedrijfsorganisatie",
    "sg:phone":"+31 33 286 3962",
    "sg:postcode":"3931 DB",
    "sg:province":"Utrecht",
    "wof:name":"Multief",
    "wof:placetype":"venue"
},
  "geometry": {"coordinates":[5.413554,52.082222],"type":"Point"}
}