{
  "type": "Feature",
  "properties": {
    "iso:country":"NL",
    "sg:address":"J F Kennedylaan 6",
    "sg:city":"Hilvarenbeek",
    "sg:orig_category":"Voeding, Dranken And Tabak Gh",
    "sg:phone":"+31 13 505 1537",
    "sg:postcode":"5081 GK",
    "sg:province":"Noord-Brabant",
    "wof:name":"Ina Vermeer",
    "wof:placetype":"venue"
},
  "geometry": {"coordinates":[5.13379,51.490211],"type":"Point"}
}