{
  "type": "Feature",
  "properties": {
    "iso:country":"NL",
    "sg:address":"Oliemaat 10",
    "sg:city":"Vlijmen",
    "sg:orig_category":"Banken And Kredietinstellingen",
    "sg:phone":"+31 73 511 9015",
    "sg:postcode":"5251 AG",
    "sg:province":"Noord-Brabant",
    "wof:name":"Postkantoor",
    "wof:placetype":"venue"
},
  "geometry": {"coordinates":[5.22111,51.69426],"type":"Point"}
}