{
  "type": "Feature",
  "properties": {
    "iso:country":"NL",
    "sg:address":"De Beeklanden 38",
    "sg:city":"Schoonebeek",
    "sg:orig_category":"Verenigingsgebouwen",
    "sg:phone":"+31 524 531 663",
    "sg:postcode":"7761 DM",
    "sg:province":"Drenthe",
    "wof:name":"Geref Jeugdcentr",
    "wof:placetype":"venue"
},
  "geometry": {"coordinates":[6.882618,52.666214],"type":"Point"}
}