{
  "type": "Feature",
  "properties": {
    "addr:full":"Atjehstr 22A Groningen Groningen 9715 EJ",
    "addr:housenumber":"22a",
    "addr:postcode":"9715 ej",
    "addr:street":"Atjehstr",
    "iso:country":"NL",
    "sg:address":"Atjehstr 22A",
    "sg:city":"Groningen",
    "sg:orig_category":"Artiesten/Gezelschappen",
    "sg:phone":"+31 50 577 3470",
    "sg:postcode":"9715 EJ",
    "sg:province":"Groningen",
    "wof:name":"Windward",
    "wof:placetype":"venue"
},
  "geometry": {"coordinates":[6.564577,53.230072],"type":"Point"}
}