{
  "type": "Feature",
  "properties": {
    "iso:country":"NL",
    "sg:address":"Markt 55",
    "sg:city":"Roosendaal",
    "sg:classifiers":[
        {
            "category":"Retail",
            "subcategory":"Photofinishing",
            "type":"Services"
        }
    ],
    "sg:phone":"+31 165 542 888",
    "sg:postcode":"4701 PC",
    "sg:province":"North Brabant",
    "sg:tags":[
        "foto",
        "film"
    ],
    "wof:name":"Foto Film Kiek Bv",
    "wof:placetype":"venue"
},
  "geometry": {"coordinates":[4.453483,51.533089],"type":"Point"}
}