{
  "type": "Feature",
  "properties": {
    "iso:country":"NL",
    "sg:address":"Wielewaalstr 23",
    "sg:city":"Alphen Aan Den Ryn",
    "sg:orig_category":"Sportverenigingen En Ontspannings- Verenigingen",
    "sg:phone":"+31 172 491 873",
    "sg:postcode":"2406 EA",
    "sg:province":"Zuid-Holland",
    "wof:name":"Alphen, Hengelsportver",
    "wof:placetype":"venue"
},
  "geometry": {"coordinates":[4.669897,52.133526],"type":"Point"}
}