{
  "type": "Feature",
  "properties": {
    "iso:country":"NL",
    "sg:address":"Rivium Boulevard 170",
    "sg:city":"Capelle A/D Ijssel",
    "sg:orig_category":"Kantoorartikelen",
    "sg:phone":"+31 10 266 7811",
    "sg:postcode":"2909 LK",
    "sg:province":"Zuid-Holland",
    "wof:name":"Mall Rivium Bv",
    "wof:placetype":"venue"
},
  "geometry": {"coordinates":[4.5449900627,51.9171714783],"type":"Point"}
}