{
  "type": "Feature",
  "properties": {
    "addr:full":"Russulaln 7 Ermelo Gelderland 3852 ZJ",
    "addr:housenumber":"7",
    "addr:postcode":"3852 zj",
    "addr:street":"Russulaln;Gelderland",
    "iso:country":"NL",
    "sg:address":"Russulaln 7",
    "sg:city":"Ermelo",
    "sg:orig_category":"Adviesbureaus Bedrijfsorganisatie",
    "sg:phone":"+31 341 563 188",
    "sg:postcode":"3852 ZJ",
    "sg:province":"Gelderland",
    "wof:name":"Hoek",
    "wof:placetype":"venue"
},
  "geometry": {"coordinates":[5.63146,52.297852],"type":"Point"}
}