{
  "type": "Feature",
  "properties": {
    "iso:country":"NL",
    "sg:address":"Wilhelminastr 15",
    "sg:city":"Krabbendyke",
    "sg:orig_category":"Verf En Lak - Fabrieken En Groothandel",
    "sg:phone":"+31 113 501 529",
    "sg:postcode":"4413 AW",
    "sg:province":"Zeeland",
    "wof:name":"Veho Verf",
    "wof:placetype":"venue"
},
  "geometry": {"coordinates":[4.115514,51.429859],"type":"Point"}
}