{
  "type": "Feature",
  "properties": {
    "iso:country":"NL",
    "sg:address":"Dorpswg 16D",
    "sg:city":"Rockanje",
    "sg:orig_category":"Wegenbouw - Materialen",
    "sg:phone":"+31 181 403 567",
    "sg:postcode":"3235 AG",
    "sg:province":"Zuid-Holland",
    "wof:name":"Kleinjan, P J",
    "wof:placetype":"venue"
},
  "geometry": {"coordinates":[4.0703778267,51.8747177124],"type":"Point"}
}