{
  "type": "Feature",
  "properties": {
    "iso:country":"NL",
    "sg:address":"Wilteindstraat 1",
    "sg:city":"Goirle",
    "sg:orig_category":"Fruit And Groenten Gh",
    "sg:phone":"+31 13 534 8251",
    "sg:postcode":"5051 SN",
    "sg:province":"Noord-Brabant",
    "wof:name":"C G Van Hoek",
    "wof:placetype":"venue"
},
  "geometry": {"coordinates":[5.0589327812,51.5192871094],"type":"Point"}
}