{
  "type": "Feature",
  "properties": {
    "addr:full":"Fazantlaan 38 Beuningen Gelderland 6641 XX",
    "addr:housenumber":"38",
    "addr:postcode":"6641 xx",
    "addr:street":"Fazantlaan;Gelderland",
    "iso:country":"NL",
    "sg:address":"Fazantlaan 38",
    "sg:city":"Beuningen",
    "sg:orig_category":"Verhuur Audiovisuele Apparatuur",
    "sg:phone":"+31 24 677 7748",
    "sg:postcode":"6641 XX",
    "sg:province":"Gelderland",
    "wof:name":"Kersjes P.A. Verhuur",
    "wof:placetype":"venue"
},
  "geometry": {"coordinates":[5.770857,51.85817],"type":"Point"}
}