{
  "type": "Feature",
  "properties": {
    "iso:country":"NL",
    "sg:address":"Steensedijk 68",
    "sg:city":"Hulst",
    "sg:orig_category":"Kappers",
    "sg:phone":"+31 114 312 760",
    "sg:postcode":"4561 GN",
    "sg:province":"Zeeland",
    "wof:name":"Vof Haarmode Huygens",
    "wof:placetype":"venue"
},
  "geometry": {"coordinates":[4.048341,51.272514],"type":"Point"}
}