{
  "type": "Feature",
  "properties": {
    "iso:country":"NL",
    "sg:address":"Rykswg 116",
    "sg:city":"Limmen",
    "sg:orig_category":"Adviesbureaus Financieel",
    "sg:phone":"+31 72 505 4878",
    "sg:postcode":"1906 BK",
    "sg:province":"Noord-Holland",
    "wof:name":"Oppen Haerd Bv",
    "wof:placetype":"venue"
},
  "geometry": {"coordinates":[4.693751,52.572544],"type":"Point"}
}