{
  "type": "Feature",
  "properties": {
    "addr:full":"Hoefbladln 21 Arnhem Gelderland 6841 CC",
    "addr:housenumber":"21",
    "addr:postcode":"6841 cc",
    "addr:street":"Hoefbladln",
    "iso:country":"NL",
    "sg:address":"Hoefbladln 21",
    "sg:city":"Arnhem",
    "sg:orig_category":"Kaas",
    "sg:phone":"+31 26 321 8007",
    "sg:postcode":"6841 CC",
    "sg:province":"Gelderland",
    "wof:name":"Kaaspunt, Het",
    "wof:placetype":"venue"
},
  "geometry": {"coordinates":[5.9018740654,51.9689292908],"type":"Point"}
}