{
  "type": "Feature",
  "properties": {
    "addr:full":"Past V Muyenwg 12 Heiloo Noord-Holland 1852 EH",
    "addr:housenumber":"12",
    "addr:postcode":"1852 eh",
    "addr:street":"Past;Muyenwg",
    "iso:country":"NL",
    "sg:address":"Past V Muyenwg 12",
    "sg:city":"Heiloo",
    "sg:orig_category":"Verenigingsgebouwen",
    "sg:phone":"+31 72 532 1048",
    "sg:postcode":"1852 EH",
    "sg:province":"Noord-Holland",
    "wof:name":"Buk Buk",
    "wof:placetype":"venue"
},
  "geometry": {"coordinates":[4.713702,52.604191],"type":"Point"}
}