{
  "type": "Feature",
  "properties": {
    "addr:full":"Eendrachtstr 32A Amsterdam North Holland 1078 XZ",
    "addr:housenumber":"32a",
    "addr:postcode":"1078 xz",
    "addr:street":"Eendrachtstr",
    "iso:country":"NL",
    "sg:address":"Eendrachtstr 32A",
    "sg:city":"Amsterdam",
    "sg:orig_category":"Voetbalverenigingen",
    "sg:phone":"+31 20 670 6442",
    "sg:postcode":"1078 XZ",
    "sg:province":"North Holland",
    "wof:name":"Amstelveen Zks Zvv",
    "wof:placetype":"venue"
},
  "geometry": {"coordinates":[4.888755,52.34465],"type":"Point"}
}