{
  "type": "Feature",
  "properties": {
    "iso:country":"NL",
    "sg:address":"Appelhof 29",
    "sg:city":"Langweer",
    "sg:orig_category":"Partycatering And -Organisatie",
    "sg:phone":"+31 513 499 508",
    "sg:postcode":"8525 GJ",
    "sg:province":"Provincie Friesland",
    "wof:name":"My Way",
    "wof:placetype":"venue"
},
  "geometry": {"coordinates":[5.71984,52.958061],"type":"Point"}
}