{
  "type": "Feature",
  "properties": {
    "iso:country":"NL",
    "sg:address":"Heliotroopdk 39",
    "sg:city":"Roosendaal",
    "sg:orig_category":"Adviesbureaus Bedrijfsorganisatie",
    "sg:phone":"+31 165 562 460",
    "sg:postcode":"4706 JN",
    "sg:province":"Noord-Brabant",
    "wof:name":"Parmi, P R",
    "wof:placetype":"venue"
},
  "geometry": {"coordinates":[4.494583,51.529713],"type":"Point"}
}