{
  "type": "Feature",
  "properties": {
    "addr:full":"Heliotroopdk 39 Roosendaal Noord-Brabant 4706 JN",
    "addr:housenumber":"39",
    "addr:postcode":"4706 jn",
    "addr:street":"Heliotroopdk",
    "iso:country":"NL",
    "sg:address":"Heliotroopdk 39",
    "sg:city":"Roosendaal",
    "sg:orig_category":"Adviesbureaus Bedrijfsorganisatie",
    "sg:phone":"+31 165 562 460",
    "sg:postcode":"4706 JN",
    "sg:province":"Noord-Brabant",
    "wof:name":"Parmi, P R",
    "wof:placetype":"venue"
},
  "geometry": {"coordinates":[4.494583,51.529713],"type":"Point"}
}