{
  "type": "Feature",
  "properties": {
    "iso:country":"NL",
    "sg:address":"Industriewg 50",
    "sg:city":"Zwolle",
    "sg:orig_category":"Verf En Lak - Fabrieken En Groothandel",
    "sg:phone":"+31 38 421 6831",
    "sg:postcode":"8031 EC",
    "sg:province":"Overijssel",
    "wof:name":"Sigma Bv",
    "wof:placetype":"venue"
},
  "geometry": {"coordinates":[6.080631,52.520435],"type":"Point"}
}