{
  "type": "Feature",
  "properties": {
    "addr:full":"Industriewg 50 Zwolle Overijssel 8031 EC",
    "addr:housenumber":"50",
    "addr:postcode":"8031 ec",
    "addr:street":"Industriewg",
    "iso:country":"NL",
    "sg:address":"Industriewg 50",
    "sg:city":"Zwolle",
    "sg:orig_category":"Verf En Lak - Fabrieken En Groothandel",
    "sg:phone":"+31 38 421 6831",
    "sg:postcode":"8031 EC",
    "sg:province":"Overijssel",
    "wof:name":"Sigma Bv",
    "wof:placetype":"venue"
},
  "geometry": {"coordinates":[6.080631,52.520435],"type":"Point"}
}