{
  "type": "Feature",
  "properties": {
    "addr:full":"Zevenbergenstr 19 Eindhoven Noord-Brabant 5652 JN",
    "addr:housenumber":"19",
    "addr:postcode":"5652 jn",
    "addr:street":"Zevenbergenstr",
    "iso:country":"NL",
    "sg:address":"Zevenbergenstr 19",
    "sg:city":"Eindhoven",
    "sg:orig_category":"Administratie- En Boekhoudkantoren",
    "sg:phone":"+31 40 252 5046",
    "sg:postcode":"5652 JN",
    "sg:province":"Noord-Brabant",
    "wof:name":"Laar, Van De",
    "wof:placetype":"venue"
},
  "geometry": {"coordinates":[5.436936,51.438786],"type":"Point"}
}