{
  "type": "Feature",
  "properties": {
    "addr:full":"Raadhuisstr 61 Zeewolde Flevoland 3891 EB",
    "addr:housenumber":"61",
    "addr:postcode":"3891 eb",
    "addr:street":"Raadhuisstr;Flevoland",
    "iso:country":"NL",
    "sg:address":"Raadhuisstr 61",
    "sg:city":"Zeewolde",
    "sg:orig_category":"Fotolaboratoria",
    "sg:phone":"+31 36 523 4325",
    "sg:postcode":"3891 EB",
    "sg:province":"Flevoland",
    "wof:name":"Fotoshop, De",
    "wof:placetype":"venue"
},
  "geometry": {"coordinates":[5.543709,52.332008],"type":"Point"}
}