{
  "type": "Feature",
  "properties": {
    "addr:full":"Hoofdstraat 184 Uithuizermeeden Groningen 9982 AK",
    "addr:housenumber":"184",
    "addr:postcode":"9982 ak",
    "addr:street":"Hoofdstraat",
    "iso:country":"NL",
    "sg:address":"Hoofdstraat 184",
    "sg:city":"Uithuizermeeden",
    "sg:orig_category":"Boekenuitgeverijen",
    "sg:phone":"+31 595 412 268",
    "sg:postcode":"9982 AK",
    "sg:province":"Groningen",
    "wof:name":"Uitgeverij Roorda",
    "wof:placetype":"venue"
},
  "geometry": {"coordinates":[6.725853,53.414455],"type":"Point"}
}