{
  "type": "Feature",
  "properties": {
    "addr:full":"Koopvaardijweg 54 Oosterhout Nb Noord-Brabant 4906 CV",
    "addr:housenumber":"54",
    "addr:postcode":"4906 cv",
    "addr:street":"Koopvaardijweg",
    "iso:country":"NL",
    "sg:address":"Koopvaardijweg 54",
    "sg:city":"Oosterhout Nb",
    "sg:orig_category":"Diverse Bedrijfsinstallaties Gh",
    "sg:phone":"+31 162 430 303",
    "sg:postcode":"4906 CV",
    "sg:province":"Noord-Brabant",
    "wof:name":"Reiniging Engineering Kunststoffen Gebr. Van Dijk",
    "wof:placetype":"venue"
},
  "geometry": {"coordinates":[4.84077,51.666069],"type":"Point"}
}