{
  "type": "Feature",
  "properties": {
    "addr:full":"Sportln 1 Landsmeer Noord-Holland 1121 CA",
    "addr:housenumber":"1",
    "addr:postcode":"1121 ca",
    "addr:street":"Sportln",
    "iso:country":"NL",
    "sg:address":"Sportln 1",
    "sg:city":"Landsmeer",
    "sg:orig_category":"Kunststoffen - Fabrieken En Groothandel",
    "sg:phone":"+31 20 482 1667",
    "sg:postcode":"1121 CA",
    "sg:province":"Noord-Holland",
    "sg:website":"http://www.goedeplastics.nl",
    "wof:name":"Goede Plastic-Prodoka Bv",
    "wof:placetype":"venue"
},
  "geometry": {"coordinates":[4.91374,52.429974],"type":"Point"}
}