{
  "type": "Feature",
  "properties": {
    "iso:country":"NL",
    "sg:address":"Baljuwstr 9",
    "sg:city":"Montfoort",
    "sg:orig_category":"Waterbehandeling En Waterzuiverings- Systemen",
    "sg:phone":"+31 348 475 107",
    "sg:postcode":"3417 SB",
    "sg:province":"Utrecht",
    "sg:website":"http://www.romeda.nl",
    "wof:name":"Romeda Bv",
    "wof:placetype":"venue"
},
  "geometry": {"coordinates":[4.9509768486,52.0364227295],"type":"Point"}
}