{
  "type": "Feature",
  "properties": {
    "addr:full":"Nieuwstraat 21 Eindhoven Noord-Brabant 5611 DA",
    "addr:housenumber":"21",
    "addr:postcode":"5611 da",
    "addr:street":"Nieuwstraat",
    "iso:country":"NL",
    "sg:address":"Nieuwstraat 21",
    "sg:city":"Eindhoven",
    "sg:orig_category":"Opticiens",
    "sg:phone":"+31 40 244 9281",
    "sg:postcode":"5611 DA",
    "sg:province":"Noord-Brabant",
    "wof:name":"Havelaer Optiek Het Huis",
    "wof:placetype":"venue"
},
  "geometry": {"coordinates":[5.4841051102,51.4344711304],"type":"Point"}
}