{
  "type": "Feature",
  "properties": {
    "addr:full":"Meerestein 6 Ede Gld Gelderland 6714 CD",
    "addr:housenumber":"6",
    "addr:postcode":"6714 cd",
    "addr:street":"Meerestein;Gld Gelderland",
    "iso:country":"NL",
    "sg:address":"Meerestein 6",
    "sg:city":"Ede Gld",
    "sg:classifiers":[
        {
            "category":"Professional",
            "subcategory":"Management & Consulting",
            "type":"Services"
        }
    ],
    "sg:phone":"+31 318 645 819",
    "sg:postcode":"6714 CD",
    "sg:province":"Gelderland",
    "sg:tags":[
        "relation",
        "adviesbureaus",
        "public"
    ],
    "sg:website":"http://www.gijssencommunicatie.nl",
    "wof:name":"Gijssen Communicatie",
    "wof:placetype":"venue"
},
  "geometry": {"coordinates":[5.649761,52.042831],"type":"Point"}
}