{
  "type": "Feature",
  "properties": {
    "addr:full":"Aardoliestr 5 Hengelo Ov Overijssel 7553 GT",
    "addr:housenumber":"5",
    "addr:postcode":"7553 gt",
    "addr:street":"Aardoliestr;Ov",
    "iso:country":"NL",
    "sg:address":"Aardoliestr 5",
    "sg:city":"Hengelo Ov",
    "sg:orig_category":"Benzine En Olie - Groothandel",
    "sg:phone":"+31 74 250 4319",
    "sg:postcode":"7553 GT",
    "sg:province":"Overijssel",
    "wof:name":"Sluijs, Van Der",
    "wof:placetype":"venue"
},
  "geometry": {"coordinates":[6.799741,52.249027],"type":"Point"}
}