{
  "type": "Feature",
  "properties": {
    "iso:country":"NL",
    "sg:address":"Beethovenln 15",
    "sg:city":"Utrecht",
    "sg:orig_category":"Wasserijen",
    "sg:phone":"+31 30 293 7715",
    "sg:postcode":"3533 ER",
    "sg:province":"Utrecht",
    "wof:name":"Holland",
    "wof:placetype":"venue"
},
  "geometry": {"coordinates":[5.0877170563,52.0860290527],"type":"Point"}
}