{
  "type": "Feature",
  "properties": {
    "addr:full":"Industriewg 1A Hapert Noord-Brabant 5527 AJ",
    "addr:housenumber":"1a",
    "addr:postcode":"5527 aj",
    "addr:street":"Industriewg",
    "iso:country":"NL",
    "sg:address":"Industriewg 1A",
    "sg:city":"Hapert",
    "sg:orig_category":"Podotherapeuten",
    "sg:phone":"+31 497 386 679",
    "sg:postcode":"5527 AJ",
    "sg:province":"Noord-Brabant",
    "wof:name":"Steenis, J Van",
    "wof:placetype":"venue"
},
  "geometry": {"coordinates":[5.264508,51.372059],"type":"Point"}
}