{
  "type": "Feature",
  "properties": {
    "addr:full":"Kerkstraat 23 Noordwijk Zh South Holland 2201 KK",
    "addr:housenumber":"23",
    "addr:postcode":"zh;2201 kk",
    "addr:street":"Kerkstraat",
    "iso:country":"NL",
    "sg:address":"Kerkstraat 23",
    "sg:city":"Noordwijk Zh",
    "sg:classifiers":[
        {
            "category":"Communications",
            "subcategory":"Television Station",
            "type":"Services"
        }
    ],
    "sg:phone":"+31 71 361 9018",
    "sg:postcode":"2201 KK",
    "sg:province":"South Holland",
    "sg:tags":[
        "video",
        "audio",
        "verhuur"
    ],
    "wof:name":"Videoland Noordwijk",
    "wof:placetype":"venue"
},
  "geometry": {"coordinates":[4.446187,52.234413],"type":"Point"}
}