{
  "type": "Feature",
  "properties": {
    "addr:full":"Osdorppln 111 Amsterdam Noord-Holland 1068 SP",
    "addr:housenumber":"111",
    "addr:postcode":"1068 sp",
    "iso:country":"NL",
    "sg:address":"Osdorppln 111",
    "sg:city":"Amsterdam",
    "sg:orig_category":"Warenhuizen",
    "sg:phone":"+31 20 410 0767",
    "sg:postcode":"1068 SP",
    "sg:province":"Noord-Holland",
    "wof:name":"Xenos Bv",
    "wof:placetype":"venue"
},
  "geometry": {"coordinates":[4.8061738014,52.3602714539],"type":"Point"}
}