{
  "type": "Feature",
  "properties": {
    "iso:country":"NL",
    "sg:address":"Heereweg 198",
    "sg:city":"Schoorl",
    "sg:orig_category":"Goederenvervoer Over De Weg",
    "sg:phone":"+31 72 509 1248",
    "sg:postcode":"1871 EN",
    "sg:province":"Noord-Holland",
    "wof:name":"Transportonderneming Th. Meereboer Bv",
    "wof:placetype":"venue"
},
  "geometry": {"coordinates":[4.676947,52.716412],"type":"Point"}
}