{
  "type": "Feature",
  "properties": {
    "addr:full":"Amstelstr 24 Alkmaar Noord-Holland 1823 EV",
    "addr:housenumber":"24",
    "addr:postcode":"1823 ev",
    "addr:street":"Amstelstr",
    "iso:country":"NL",
    "sg:address":"Amstelstr 24",
    "sg:city":"Alkmaar",
    "sg:orig_category":"Grafisch Ontwerpers",
    "sg:phone":"+31 6 21575026",
    "sg:postcode":"1823 EV",
    "sg:province":"Noord-Holland",
    "wof:name":"Alkmaar Design Centre",
    "wof:placetype":"venue"
},
  "geometry": {"coordinates":[4.766882,52.632095],"type":"Point"}
}