{
  "type": "Feature",
  "properties": {
    "iso:country":"NL",
    "sg:address":"Dreef 188",
    "sg:city":"Leersum",
    "sg:orig_category":"Onderhoudswerken",
    "sg:phone":"+31 343 456 847",
    "sg:postcode":"3956 EZ",
    "sg:province":"Utrecht",
    "wof:name":"Koenen, Marcel",
    "wof:placetype":"venue"
},
  "geometry": {"coordinates":[5.427035,52.008881],"type":"Point"}
}