{
  "type": "Feature",
  "properties": {
    "addr:full":"Homerusplein 5 Heerlen Limburg 6411 AW",
    "addr:housenumber":"5",
    "addr:postcode":"6411 aw",
    "addr:street":"Homerusplein",
    "iso:country":"NL",
    "sg:address":"Homerusplein 5",
    "sg:city":"Heerlen",
    "sg:orig_category":"Herenmodezaken",
    "sg:phone":"+31 45 571 6109",
    "sg:postcode":"6411 AW",
    "sg:province":"Limburg",
    "wof:name":"Vranken Herenmode Bv",
    "wof:placetype":"venue"
},
  "geometry": {"coordinates":[5.97111,50.886345],"type":"Point"}
}