{
  "type": "Feature",
  "properties": {
    "iso:country":"NL",
    "sg:address":"Hoofdstraat 37",
    "sg:city":"Westerbork",
    "sg:orig_category":"Kappers",
    "sg:phone":"+31 593 333 333",
    "sg:postcode":"9431 AC",
    "sg:province":"Drenthe",
    "wof:name":"Kapsalon Alice",
    "wof:placetype":"venue"
},
  "geometry": {"coordinates":[6.6122298241,52.8501243591],"type":"Point"}
}