{
  "type": "Feature",
  "properties": {
    "iso:country":"NL",
    "sg:address":"3E Wittenb Dwstr 3A",
    "sg:city":"Amsterdam",
    "sg:orig_category":"Beeldende Kunstenaars",
    "sg:phone":"+31 20 625 8266",
    "sg:postcode":"1018 KR",
    "sg:province":"Noord-Holland",
    "wof:name":"Violier, M H",
    "wof:placetype":"venue"
},
  "geometry": {"coordinates":[4.923504,52.373638],"type":"Point"}
}