{
  "type": "Feature",
  "properties": {
    "addr:full":"Zuster Kortestraat 16 Roodeschool Groningen 9983 SX",
    "addr:housenumber":"16",
    "addr:postcode":"9983 sx",
    "addr:street":"Zuster Kortestraat",
    "iso:country":"NL",
    "sg:address":"Zuster Kortestraat 16",
    "sg:city":"Roodeschool",
    "sg:orig_category":"Autokeuringen",
    "sg:phone":"+31 595 413 485",
    "sg:postcode":"9983 SX",
    "sg:province":"Groningen",
    "wof:name":"F P Coopman",
    "wof:placetype":"venue"
},
  "geometry": {"coordinates":[6.767967,53.418434],"type":"Point"}
}