{
  "type": "Feature",
  "properties": {
    "addr:full":"Rynsburgerwg 143 Leiden South Holland 2334 BN",
    "addr:housenumber":"143",
    "addr:postcode":"2334 bn",
    "iso:country":"NL",
    "sg:address":"Rynsburgerwg 143",
    "sg:city":"Leiden",
    "sg:orig_category":"Verzekeringen - Verzekeringskantoren",
    "sg:phone":"+31 71 517 1141",
    "sg:postcode":"2334 BN",
    "sg:province":"South Holland",
    "wof:name":"Assucom Assuranti\u00ebn",
    "wof:placetype":"venue"
},
  "geometry": {"coordinates":[4.474385,52.173153],"type":"Point"}
}