{
  "type": "Feature",
  "properties": {
    "iso:country":"NL",
    "sg:address":"Ginnekenwg 17",
    "sg:city":"Breda",
    "sg:orig_category":"Galeries",
    "sg:phone":"+31 76 533 0220",
    "sg:postcode":"4818 JA",
    "sg:province":"Noord-Brabant",
    "sg:website":"http://www.ducoart.nl",
    "wof:name":"Duco Art Gallery",
    "wof:placetype":"venue"
},
  "geometry": {"coordinates":[4.779615,51.578262],"type":"Point"}
}