{
  "type": "Feature",
  "properties": {
    "addr:full":"Apollostraat 9 Hilvarenbeek Noord-Brabant 5081 GS",
    "addr:housenumber":"9",
    "addr:postcode":"5081 gs",
    "addr:street":"Apollostraat",
    "iso:country":"NL",
    "sg:address":"Apollostraat 9",
    "sg:city":"Hilvarenbeek",
    "sg:orig_category":"Notarissen",
    "sg:phone":"+31 13 505 3267",
    "sg:postcode":"5081 GS",
    "sg:province":"Noord-Brabant",
    "wof:name":"Notariskantoor J. Kos",
    "wof:placetype":"venue"
},
  "geometry": {"coordinates":[5.135251,51.490128],"type":"Point"}
}