{
  "type": "Feature",
  "properties": {
    "addr:full":"Rolwg 25 Culemborg Gelderland 4104 AV",
    "addr:housenumber":"25",
    "addr:postcode":"4104 av",
    "addr:street":"Rolwg;Gelderland",
    "iso:country":"NL",
    "sg:address":"Rolwg 25",
    "sg:city":"Culemborg",
    "sg:orig_category":"Verpakkingen En Verpakkingsmaterialen",
    "sg:phone":"+31 345 530 753",
    "sg:postcode":"4104 AV",
    "sg:province":"Gelderland",
    "wof:name":"Transpac Ned",
    "wof:placetype":"venue"
},
  "geometry": {"coordinates":[5.215265,51.938156],"type":"Point"}
}