{
  "type": "Feature",
  "properties": {
    "addr:full":"3E Oosterparkstr 2382Hg Amsterdam Noord-Holland 1092 EK",
    "addr:postcode":"2382hg;1092 ek",
    "addr:street":"3E",
    "iso:country":"NL",
    "sg:address":"3E Oosterparkstr 2382Hg",
    "sg:city":"Amsterdam",
    "sg:orig_category":"Adviesbureaus Gezondheidszorg",
    "sg:phone":"+31 20 468 2944",
    "sg:postcode":"1092 EK",
    "sg:province":"Noord-Holland",
    "wof:name":"Aq",
    "wof:placetype":"venue"
},
  "geometry": {"coordinates":[4.92586,52.358898],"type":"Point"}
}