{
  "type": "Feature",
  "properties": {
    "addr:full":"R Dieselstr 4 Zwolle NL.08 8013 NJ",
    "addr:housenumber":"4",
    "addr:postcode":"8013 nj",
    "iso:country":"NL",
    "sg:address":"R Dieselstr 4",
    "sg:city":"Zwolle",
    "sg:orig_category":"Elektrotechnische Apparatuur - Fabrieken En Groothandel",
    "sg:phone":"+31 38 460 2888",
    "sg:postcode":"8013 NJ",
    "sg:province":"NL.08",
    "wof:name":"Bernard Bv",
    "wof:placetype":"venue"
},
  "geometry": {"coordinates":[6.121736,52.49334],"type":"Point"}
}