{
  "type": "Feature",
  "properties": {
    "addr:full":"Noorderdiep 484 Valthermond Drenthe 7876 EA",
    "addr:housenumber":"484",
    "addr:postcode":"7876 ea",
    "addr:street":"Noorderdiep",
    "iso:country":"NL",
    "sg:address":"Noorderdiep 484",
    "sg:city":"Valthermond",
    "sg:orig_category":"Bestratingen",
    "sg:phone":"+31 599 662 071",
    "sg:postcode":"7876 EA",
    "sg:province":"Drenthe",
    "wof:name":"Lamein, A",
    "wof:placetype":"venue"
},
  "geometry": {"coordinates":[6.982627,52.892708],"type":"Point"}
}