{
  "type": "Feature",
  "properties": {
    "iso:country":"NL",
    "sg:address":"Saturnusstraat 23B",
    "sg:city":"Hoofddorp",
    "sg:orig_category":"Drukkerijen And Copyshops",
    "sg:phone":"+31 23 565 3414",
    "sg:postcode":"2132 HB",
    "sg:province":"Noord-Holland",
    "wof:name":"Shinyo Co Ltd",
    "wof:placetype":"venue"
},
  "geometry": {"coordinates":[4.699375,52.295303],"type":"Point"}
}