{
  "type": "Feature",
  "properties": {
    "iso:country":"NL",
    "sg:address":"Poepershoek 2",
    "sg:city":"St Jansklooster",
    "sg:orig_category":"Milieu",
    "sg:phone":"+31 527 245 546",
    "sg:postcode":"8326 BS",
    "sg:province":"Overijssel",
    "wof:name":"Jnh",
    "wof:placetype":"venue"
},
  "geometry": {"coordinates":[6.015421,52.66819],"type":"Point"}
}