{
  "type": "Feature",
  "properties": {
    "iso:country":"NL",
    "sg:address":"Zaailand 121",
    "sg:city":"Leeuwarden",
    "sg:orig_category":"Schoenen",
    "sg:phone":"+31 58 216 4189",
    "sg:postcode":"8911 BL",
    "sg:province":"Friesland",
    "wof:name":"Invito",
    "wof:placetype":"venue"
},
  "geometry": {"coordinates":[5.795401,53.199368],"type":"Point"}
}