{
  "type": "Feature",
  "properties": {
    "addr:full":"Lintelerwg 17 Hengelo Ov Overijssel 7556 PD",
    "addr:housenumber":"17",
    "addr:postcode":"7556 pd",
    "addr:street":"Lintelerwg;Ov",
    "iso:country":"NL",
    "sg:address":"Lintelerwg 17",
    "sg:city":"Hengelo Ov",
    "sg:orig_category":"Verpakkingen En Verpakkingsmaterialen",
    "sg:phone":"+31 74 259 3255",
    "sg:postcode":"7556 PD",
    "sg:province":"Overijssel",
    "wof:name":"Boer Bv, De",
    "wof:placetype":"venue"
},
  "geometry": {"coordinates":[6.778384,52.285854],"type":"Point"}
}