{
  "type": "Feature",
  "properties": {
    "addr:full":"Heezerweg 107 Eindhoven North Brabant 5614 HC",
    "addr:housenumber":"107",
    "addr:postcode":"5614 hc",
    "addr:street":"Heezerweg",
    "iso:country":"NL",
    "sg:address":"Heezerweg 107",
    "sg:city":"Eindhoven",
    "sg:orig_category":"Fietshandelaren",
    "sg:phone":"+31 40 212 5638",
    "sg:postcode":"5614 HC",
    "sg:province":"North Brabant",
    "wof:name":"Algemene Rijwielservice",
    "wof:placetype":"venue"
},
  "geometry": {"coordinates":[5.492451,51.427143],"type":"Point"}
}