{
  "type": "Feature",
  "properties": {
    "addr:full":"Van Heemstraweg 84 Beuningen Gld Gelderland 6641 AG",
    "addr:housenumber":"84",
    "addr:postcode":"6641",
    "addr:street":"Van Heemstraweg",
    "iso:country":"NL",
    "sg:address":"Van Heemstraweg 84",
    "sg:city":"Beuningen Gld",
    "sg:orig_category":"Bedrijfs- And Managementsconsultants",
    "sg:phone":"+31 24 677 4326",
    "sg:postcode":"6641 AG",
    "sg:province":"Gelderland",
    "wof:name":"D. Van Dijk",
    "wof:placetype":"venue"
},
  "geometry": {"coordinates":[5.76956,51.85955],"type":"Point"}
}