{
  "type": "Feature",
  "properties": {
    "iso:country":"NL",
    "sg:address":"Kempensebaan 56",
    "sg:city":"Eindhoven",
    "sg:orig_category":"Beursorganisaties And Standbouw",
    "sg:phone":"+31 40 243 1421",
    "sg:postcode":"5613 JE",
    "sg:province":"Noord-Brabant",
    "wof:name":"Ufo",
    "wof:placetype":"venue"
},
  "geometry": {"coordinates":[5.499125,51.439461],"type":"Point"}
}