{
  "type": "Feature",
  "properties": {
    "addr:full":"Zuiderzeestraatweg 317 Oldebroek Gelderland 8096 BM",
    "addr:housenumber":"317",
    "addr:postcode":"8096 bm",
    "addr:street":"Zuiderzeestraatweg;Gelderland",
    "iso:country":"NL",
    "sg:address":"Zuiderzeestraatweg 317",
    "sg:city":"Oldebroek",
    "sg:orig_category":"Administratie- En Boekhoudkantoren",
    "sg:phone":"+31 525 634 060",
    "sg:postcode":"8096 BM",
    "sg:province":"Gelderland",
    "wof:name":"Bf&A De Meren",
    "wof:placetype":"venue"
},
  "geometry": {"coordinates":[5.938841,52.45927],"type":"Point"}
}