{
  "type": "Feature",
  "properties": {
    "addr:full":"Kerkplein 6 Harderwijk Gelderland 3841 EC",
    "addr:housenumber":"6",
    "addr:postcode":"3841 ec",
    "addr:street":"Kerkplein;Gelderland",
    "iso:country":"NL",
    "sg:address":"Kerkplein 6",
    "sg:city":"Harderwijk",
    "sg:classifiers":[
        {
            "category":"Communications",
            "subcategory":"Television Station",
            "type":"Services"
        }
    ],
    "sg:phone":"+31 341 425 550",
    "sg:postcode":"3841 EC",
    "sg:province":"Gelderland",
    "sg:tags":[
        "video",
        "audio",
        "verhuur"
    ],
    "wof:name":"Videotheek Orca Harderwijk",
    "wof:placetype":"venue"
},
  "geometry": {"coordinates":[5.61514,52.34901],"type":"Point"}
}