{
  "type": "Feature",
  "properties": {
    "iso:country":"NL",
    "sg:address":"Houttuinln 14",
    "sg:city":"Woerden",
    "sg:orig_category":"Kantoorbenodigdheden",
    "sg:phone":"+31 348 486 020",
    "sg:postcode":"3447 GM",
    "sg:province":"Utrecht",
    "sg:website":"http://www.herma.nl",
    "wof:name":"Dorp Brands, Van",
    "wof:placetype":"venue"
},
  "geometry": {"coordinates":[4.8884601593,52.0816612244],"type":"Point"}
}