{
  "type": "Feature",
  "properties": {
    "addr:full":"Adm De Ruyterstr 48 Sliedrecht South Holland 3361 VC",
    "addr:housenumber":"48",
    "addr:postcode":"3361 vc",
    "iso:country":"NL",
    "sg:address":"Adm De Ruyterstr 48",
    "sg:city":"Sliedrecht",
    "sg:orig_category":"Metaalwaren - Groothandel",
    "sg:phone":"+31 184 447 841",
    "sg:postcode":"3361 VC",
    "sg:province":"South Holland",
    "wof:name":"Steel Vof",
    "wof:placetype":"venue"
},
  "geometry": {"coordinates":[4.77367,51.818069],"type":"Point"}
}