{
  "type": "Feature",
  "properties": {
    "iso:country":"NL",
    "sg:address":"Tuinln 50",
    "sg:city":"Schiedam",
    "sg:orig_category":"Zalenverhuur",
    "sg:phone":"+31 10 273 1737",
    "sg:postcode":"3111 AW",
    "sg:province":"Zuid-Holland",
    "wof:name":"Rooie Koffer, In Den",
    "wof:placetype":"venue"
},
  "geometry": {"coordinates":[4.39816,51.918472],"type":"Point"}
}