{
  "type": "Feature",
  "properties": {
    "iso:country":"NL",
    "sg:address":"Eiteren 36",
    "sg:city":"Ysselstein Ut",
    "sg:orig_category":"Dierenvoeder - Fabrieken",
    "sg:phone":"+31 30 688 6489",
    "sg:postcode":"3401 PT",
    "sg:province":"Utrecht",
    "wof:name":"Verkerk & Znn Bv",
    "wof:placetype":"venue"
},
  "geometry": {"coordinates":[5.044523,52.022408],"type":"Point"}
}