{
  "type": "Feature",
  "properties": {
    "addr:full":"Zuidereinde 185 'S Graveland North Holland 1243 KW",
    "addr:housenumber":"185 ' s",
    "addr:postcode":"1243 kw",
    "addr:street":"Zuidereinde;Graveland North",
    "iso:country":"NL",
    "sg:address":"Zuidereinde 185",
    "sg:city":"'S Graveland",
    "sg:orig_category":"Verzekeringen",
    "sg:phone":"+31 35 656 1842",
    "sg:postcode":"1243 KW",
    "sg:province":"North Holland",
    "wof:name":"Assurantiekantoor A J Harskamp",
    "wof:placetype":"venue"
},
  "geometry": {"coordinates":[5.122622,52.222656],"type":"Point"}
}