{
  "type": "Feature",
  "properties": {
    "addr:full":"Skou 25 Joure Friesland 8501 SB",
    "addr:housenumber":"25",
    "addr:postcode":"8501 sb",
    "addr:street":"Skou",
    "iso:country":"NL",
    "sg:address":"Skou 25",
    "sg:city":"Joure",
    "sg:orig_category":"Verenigingen En Stichtingen",
    "sg:phone":"+31 513 411 738",
    "sg:postcode":"8501 SB",
    "sg:province":"Friesland",
    "wof:name":"Ibiss Contactpunt Nederland",
    "wof:placetype":"venue"
},
  "geometry": {"coordinates":[5.801374,52.970623],"type":"Point"}
}