{
  "type": "Feature",
  "properties": {
    "addr:full":"Halstersewg 222A Bergen Op Zoom Noord-Brabant 4613 BC",
    "addr:housenumber":"222a",
    "addr:postcode":"4613 bc",
    "iso:country":"NL",
    "sg:address":"Halstersewg 222A",
    "sg:city":"Bergen Op Zoom",
    "sg:orig_category":"Pijpleidingen - Installatie En Onderhoud",
    "sg:phone":"+31 164 263 829",
    "sg:postcode":"4613 BC",
    "sg:province":"Noord-Brabant",
    "wof:name":"Roma Bv",
    "wof:placetype":"venue"
},
  "geometry": {"coordinates":[4.279336,51.504128],"type":"Point"}
}