{
  "type": "Feature",
  "properties": {
    "addr:full":"Handelsweg 10 Wierden NL.08 7641 AC",
    "addr:housenumber":"10;nl.08",
    "addr:postcode":"7641 ac",
    "addr:street":"Handelsweg",
    "iso:country":"NL",
    "sg:address":"Handelsweg 10",
    "sg:city":"Wierden",
    "sg:orig_category":"Fitnesscentra",
    "sg:phone":"+31 546 571 690",
    "sg:postcode":"7641 AC",
    "sg:province":"NL.08",
    "wof:name":"Fit-Care Center Bodyfit",
    "wof:placetype":"venue"
},
  "geometry": {"coordinates":[6.5978,52.364399],"type":"Point"}
}