{
  "type": "Feature",
  "properties": {
    "addr:full":"Parallel Boulevard 270 Noordwijk Zh Zuid-Holland 2202 HT",
    "addr:housenumber":"270",
    "addr:postcode":"2202 ht",
    "addr:street":"Parallel Boulevard",
    "iso:country":"NL",
    "sg:address":"Parallel Boulevard 270",
    "sg:city":"Noordwijk Zh",
    "sg:orig_category":"Verlichting And Huishoudartikelen",
    "sg:phone":"+31 71 364 7492",
    "sg:postcode":"2202 HT",
    "sg:province":"Zuid-Holland",
    "wof:name":"Agentuur- En Commissiehandel Harry Moonen Bv",
    "wof:placetype":"venue"
},
  "geometry": {"coordinates":[4.433359,52.246479],"type":"Point"}
}