{
  "type": "Feature",
  "properties": {
    "addr:full":"Boerhaaveln 2 Barendrecht Zuid-Holland 2992 KZ",
    "addr:housenumber":"2",
    "addr:postcode":"2992 kz",
    "addr:street":"Boerhaaveln",
    "iso:country":"NL",
    "sg:address":"Boerhaaveln 2",
    "sg:city":"Barendrecht",
    "sg:orig_category":"Ziekenhuizen, Sanatoria, Verpleeghuizen",
    "sg:phone":"+31 180 691 111",
    "sg:postcode":"2992 KZ",
    "sg:province":"Zuid-Holland",
    "wof:name":"Rmpi",
    "wof:placetype":"venue"
},
  "geometry": {"coordinates":[4.54064,51.853176],"type":"Point"}
}