{
  "type": "Feature",
  "properties": {
    "addr:full":"Bergselaan 328B Rotterdam South Holland 3038 CN",
    "addr:housenumber":"328b",
    "addr:postcode":"3038 cn",
    "addr:street":"Bergselaan",
    "iso:country":"NL",
    "sg:address":"Bergselaan 328B",
    "sg:city":"Rotterdam",
    "sg:orig_category":"Vertaal- And Tolkenbureaus",
    "sg:phone":"+31 10 466 5260",
    "sg:postcode":"3038 CN",
    "sg:province":"South Holland",
    "wof:name":"M.C. Van Dijk",
    "wof:placetype":"venue"
},
  "geometry": {"coordinates":[4.466007,51.933861],"type":"Point"}
}