{
  "type": "Feature",
  "properties": {
    "iso:country":"NL",
    "sg:address":"Huijgensstraat 133",
    "sg:city":"Hoogerheide",
    "sg:orig_category":"Autokeuringen",
    "sg:phone":"+31 164 613 834",
    "sg:postcode":"4631 GP",
    "sg:province":"North Brabant",
    "wof:name":"Simonis Carrosserie Spuiterij",
    "wof:placetype":"venue"
},
  "geometry": {"coordinates":[4.335469,51.424141],"type":"Point"}
}