{
  "type": "Feature",
  "properties": {
    "iso:country":"NL",
    "sg:address":"Bernadottelaan 10",
    "sg:city":"Utrecht",
    "sg:orig_category":"Bloemen And Planten",
    "sg:phone":"+31 30 293 2689",
    "sg:postcode":"3527 GB",
    "sg:province":"Utrecht",
    "wof:name":"Bloemboetiek De Lotus",
    "wof:placetype":"venue"
},
  "geometry": {"coordinates":[5.093249,52.075062],"type":"Point"}
}