{
  "type": "Feature",
  "properties": {
    "iso:country":"NL",
    "sg:address":"Lorentzwg 1",
    "sg:city":"Bunschoten Spakenb",
    "sg:classifiers":[
        {
            "category":"Building & Trades",
            "subcategory":"Electrical",
            "type":"Services"
        }
    ],
    "sg:phone":"+31 33 454 2090",
    "sg:postcode":"3752 LH",
    "sg:province":"Utrecht",
    "sg:tags":[
        "distributor"
    ],
    "sg:website":"http://www.kobe-int.com",
    "wof:name":"Kobe International Bv",
    "wof:placetype":"venue"
},
  "geometry": {"coordinates":[5.363302,52.231709],"type":"Point"}
}