{
  "type": "Feature",
  "properties": {
    "addr:full":"Bontekoekd Ab Ab Vak 3 S Gravenhage Zuid-Holland 2516 LA",
    "addr:housenumber":"3;gravenhage;2516",
    "addr:postcode":"la",
    "addr:street":"Vak;S",
    "iso:country":"NL",
    "sg:address":"Bontekoekd Ab Ab Vak 3",
    "sg:city":"S Gravenhage",
    "sg:orig_category":"Tekstschrijversters",
    "sg:phone":"+31 70 365 7351",
    "sg:postcode":"2516 LA",
    "sg:province":"Zuid-Holland",
    "sg:website":"http://www.tekstincontext.com",
    "wof:name":"Tekst In Context",
    "wof:placetype":"venue"
},
  "geometry": {"coordinates":[4.33931,52.06786],"type":"Point"}
}