{
  "type": "Feature",
  "properties": {
    "addr:full":"Hoekwierde 43 Almere Flevoland 1353 PC",
    "addr:housenumber":"43",
    "addr:postcode":"1353 pc",
    "addr:street":"Hoekwierde;Flevoland",
    "iso:country":"NL",
    "sg:address":"Hoekwierde 43",
    "sg:city":"Almere",
    "sg:classifiers":[
        {
            "category":"Utilities",
            "subcategory":"Cable",
            "type":"Services"
        }
    ],
    "sg:phone":"+31 36 531 2545",
    "sg:postcode":"1353 PC",
    "sg:province":"Flevoland",
    "sg:tags":[
        "masseur",
        "en",
        "heilgymnasten"
    ],
    "wof:name":"Wesselo, S",
    "wof:placetype":"venue"
},
  "geometry": {"coordinates":[5.198727,52.337536],"type":"Point"}
}