{
  "type": "Feature",
  "properties": {
    "addr:full":"Europk 20 Oosterhout Nb Noord-Brabant 4904 SX",
    "addr:housenumber":"20",
    "addr:postcode":"4904 sx",
    "addr:street":"Europk",
    "iso:country":"NL",
    "sg:address":"Europk 20",
    "sg:city":"Oosterhout Nb",
    "sg:orig_category":"Farmaceutische Industrie En Groothandel",
    "sg:phone":"+31 162 437 268",
    "sg:postcode":"4904 SX",
    "sg:province":"Noord-Brabant",
    "wof:name":"Wartner Bv",
    "wof:placetype":"venue"
},
  "geometry": {"coordinates":[4.860729,51.629818],"type":"Point"}
}