{
  "type": "Feature",
  "properties": {
    "addr:full":"Korenaar 88 Hellevoetsluis Zuid-Holland 3224 XG",
    "addr:housenumber":"88",
    "addr:postcode":"3224 xg",
    "addr:street":"Korenaar",
    "iso:country":"NL",
    "sg:address":"Korenaar 88",
    "sg:city":"Hellevoetsluis",
    "sg:orig_category":"Autorijscholen",
    "sg:phone":"+31 181 324 681",
    "sg:postcode":"3224 XG",
    "sg:province":"Zuid-Holland",
    "wof:name":"Klinge, Autorijschool Heleen",
    "wof:placetype":"venue"
},
  "geometry": {"coordinates":[4.143137,51.828213],"type":"Point"}
}