{
  "type": "Feature",
  "properties": {
    "addr:full":"Michelangelostr 10 Rotterdam Zuid-Holland 3066 NM",
    "addr:housenumber":"10",
    "addr:postcode":"3066",
    "addr:street":"Michelangelostr",
    "iso:country":"NL",
    "sg:address":"Michelangelostr 10",
    "sg:city":"Rotterdam",
    "sg:orig_category":"Belastingconsulenten/ Belastingadviseurs",
    "sg:phone":"+31 10 289 2555",
    "sg:postcode":"3066 NM",
    "sg:province":"Zuid-Holland",
    "wof:name":"Esch Belastingadviseurs, Van",
    "wof:placetype":"venue"
},
  "geometry": {"coordinates":[4.551652,51.939476],"type":"Point"}
}