{
  "type": "Feature",
  "properties": {
    "addr:full":"Landzigt 22 De Meern Utrecht 3454 PE",
    "addr:housenumber":"22",
    "addr:postcode":"3454 pe",
    "addr:street":"Landzigt",
    "iso:country":"NL",
    "sg:address":"Landzigt 22",
    "sg:city":"De Meern",
    "sg:orig_category":"Autoverhuur",
    "sg:phone":"+31 30 296 9000",
    "sg:postcode":"3454 PE",
    "sg:province":"Utrecht",
    "wof:name":"Euro Mobil",
    "wof:placetype":"venue"
},
  "geometry": {"coordinates":[5.045093,52.073795],"type":"Point"}
}