{
  "type": "Feature",
  "properties": {
    "addr:full":"Churchillwg 26 Zoutkamp Groningen 9974 PC",
    "addr:housenumber":"26",
    "addr:postcode":"9974 pc",
    "addr:street":"Churchillwg",
    "iso:country":"NL",
    "sg:address":"Churchillwg 26",
    "sg:city":"Zoutkamp",
    "sg:orig_category":"Fietsen En Bromfietsen Verhuur",
    "sg:phone":"+31 595 401 374",
    "sg:postcode":"9974 PC",
    "sg:province":"Groningen",
    "wof:name":"Zijlstra'S Tweewielers",
    "wof:placetype":"venue"
},
  "geometry": {"coordinates":[6.302525,53.337227],"type":"Point"}
}