{
  "type": "Feature",
  "properties": {
    "addr:full":"Den Oeversewg 6 Slootdorp Noord-Holland 1774 NB",
    "addr:housenumber":"6",
    "addr:postcode":"1774 nb",
    "iso:country":"NL",
    "sg:address":"Den Oeversewg 6",
    "sg:city":"Slootdorp",
    "sg:orig_category":"Psychotherapeuten",
    "sg:phone":"+31 227 581 574",
    "sg:postcode":"1774 NB",
    "sg:province":"Noord-Holland",
    "wof:name":"Wit K, De",
    "wof:placetype":"venue"
},
  "geometry": {"coordinates":[4.997294,52.880192],"type":"Point"}
}