{
  "type": "Feature",
  "properties": {
    "iso:country":"NL",
    "sg:address":"Dennenlaan 53",
    "sg:city":"Zwanenburg",
    "sg:orig_category":"Zuivelproducten",
    "sg:phone":"+31 20 497 3321",
    "sg:postcode":"1161 CL",
    "sg:province":"North Holland",
    "wof:name":"Kaasboer-Poelier",
    "wof:placetype":"venue"
},
  "geometry": {"coordinates":[4.750013,52.378838],"type":"Point"}
}