{
  "type": "Feature",
  "properties": {
    "addr:full":"Elckerlyclaan 83 Eindhoven North Brabant 5625 EP",
    "addr:housenumber":"83",
    "addr:postcode":"5625 ep",
    "addr:street":"Elckerlyclaan",
    "iso:country":"NL",
    "sg:address":"Elckerlyclaan 83",
    "sg:city":"Eindhoven",
    "sg:classifiers":[
        {
            "category":"Communications",
            "subcategory":"Television Station",
            "type":"Services"
        }
    ],
    "sg:phone":"+31 40 242 8032",
    "sg:postcode":"5625 EP",
    "sg:province":"North Brabant",
    "sg:tags":[
        "video",
        "audio",
        "verhuur"
    ],
    "wof:name":"Videotheek Bakker Woensel Bv",
    "wof:placetype":"venue"
},
  "geometry": {"coordinates":[5.467606,51.474651],"type":"Point"}
}