{
  "type": "Feature",
  "properties": {
    "addr:full":"Hessenweg 27 Hardenberg NL.08 7771 CH",
    "addr:housenumber":"27;nl.08",
    "addr:postcode":"7771",
    "addr:street":"Hessenweg",
    "iso:country":"NL",
    "sg:address":"Hessenweg 27",
    "sg:city":"Hardenberg",
    "sg:orig_category":"Meubelzaken, Woning- And Keukeninrichting",
    "sg:phone":"+31 523 262 955",
    "sg:postcode":"7771 CH",
    "sg:province":"NL.08",
    "sg:website":"http://www.totaalslapen.nl",
    "wof:name":"Totaalslapen",
    "wof:placetype":"venue"
},
  "geometry": {"coordinates":[6.60409,52.574085],"type":"Point"}
}