{
  "type": "Feature",
  "properties": {
    "addr:full":"Hendoweg 3 Dokkum Provincie Friesland 9101 PC",
    "addr:housenumber":"3",
    "addr:postcode":"9101 pc",
    "addr:street":"Hendoweg;Provincie Friesland",
    "iso:country":"NL",
    "sg:address":"Hendoweg 3",
    "sg:city":"Dokkum",
    "sg:orig_category":"Makelaars In Onroerend Goed",
    "sg:phone":"+31 519 296 075",
    "sg:postcode":"9101 PC",
    "sg:province":"Provincie Friesland",
    "wof:name":"Bedrijvencentrum Dokkum Bv",
    "wof:placetype":"venue"
},
  "geometry": {"coordinates":[5.983646,53.326317],"type":"Point"}
}