{
  "type": "Feature",
  "properties": {
    "addr:full":"Werfheegde 23 Haaksbergen Overijssel 7481 JR",
    "addr:housenumber":"23",
    "addr:postcode":"7481 jr",
    "addr:street":"Werfheegde",
    "iso:country":"NL",
    "sg:address":"Werfheegde 23",
    "sg:city":"Haaksbergen",
    "sg:orig_category":"Onderzoekbureaus",
    "sg:phone":"+31 53 572 1360",
    "sg:postcode":"7481 JR",
    "sg:province":"Overijssel",
    "wof:name":"Landbouw Economisch Instituut",
    "wof:placetype":"venue"
},
  "geometry": {"coordinates":[6.733305,52.156055],"type":"Point"}
}