{
  "type": "Feature",
  "properties": {
    "addr:full":"Operaplein 50 Apeldoorn Gelderland 7323 EL",
    "addr:housenumber":"50",
    "addr:postcode":"7323 el",
    "addr:street":"Operaplein;Gelderland",
    "iso:country":"NL",
    "sg:address":"Operaplein 50",
    "sg:city":"Apeldoorn",
    "sg:orig_category":"Fotolaboratoria",
    "sg:phone":"+31 55 366 3751",
    "sg:postcode":"7323 EL",
    "sg:province":"Gelderland",
    "wof:name":"Kruidvat",
    "wof:placetype":"venue"
},
  "geometry": {"coordinates":[5.98613,52.229485],"type":"Point"}
}