{
  "type": "Feature",
  "properties": {
    "addr:full":"T Veer 61 Leek Groningen 9351 DG",
    "addr:housenumber":"61",
    "addr:postcode":"9351 dg",
    "addr:street":"T Veer",
    "iso:country":"NL",
    "sg:address":"T Veer 61",
    "sg:city":"Leek",
    "sg:orig_category":"Administratie- En Boekhoudkantoren",
    "sg:phone":"+31 594 514 730",
    "sg:postcode":"9351 DG",
    "sg:province":"Groningen",
    "wof:name":"Klaver, W",
    "wof:placetype":"venue"
},
  "geometry": {"coordinates":[6.37987,53.156929],"type":"Point"}
}