{
  "type": "Feature",
  "properties": {
    "addr:full":"Slotboomstraat 8 Rotterdam Zuid-Holland 3082 GP",
    "addr:housenumber":"8",
    "addr:postcode":"3082 gp",
    "addr:street":"Slotboomstraat",
    "iso:country":"NL",
    "sg:address":"Slotboomstraat 8",
    "sg:city":"Rotterdam",
    "sg:classifiers":[
        {
            "category":"Fast Food",
            "type":"Food & Drink"
        }
    ],
    "sg:phone":"+31 10 428 0937",
    "sg:postcode":"3082 GP",
    "sg:province":"Zuid-Holland",
    "sg:tags":[
        "afhaal",
        "restaurant"
    ],
    "wof:name":"Snackbar Robin",
    "wof:placetype":"venue"
},
  "geometry": {"coordinates":[4.471904,51.890858],"type":"Point"}
}