{
  "type": "Feature",
  "properties": {
    "iso:country":"NL",
    "sg:address":"Zevenwouden 258",
    "sg:city":"Utrecht",
    "sg:classifiers":[
        {
            "category":"Fast Food",
            "type":"Food & Drink"
        }
    ],
    "sg:phone":"+31 30 289 1898",
    "sg:postcode":"3524 CX",
    "sg:province":"Utrecht",
    "sg:tags":[
        "afhaal",
        "restaurant"
    ],
    "wof:name":"Cafetaria Lunetten",
    "wof:placetype":"venue"
},
  "geometry": {"coordinates":[5.136378,52.065155],"type":"Point"}
}