{
  "type": "Feature",
  "properties": {
    "addr:full":"Oosteinde 233 Vriezenveen Overijssel 7671 AZ",
    "addr:housenumber":"233",
    "addr:postcode":"7671 az",
    "addr:street":"Oosteinde",
    "iso:country":"NL",
    "sg:address":"Oosteinde 233",
    "sg:city":"Vriezenveen",
    "sg:orig_category":"Landbouwmachines Gh",
    "sg:phone":"+31 546 561 572",
    "sg:postcode":"7671 AZ",
    "sg:province":"Overijssel",
    "wof:name":"Servicebedrijf Aman",
    "wof:placetype":"venue"
},
  "geometry": {"coordinates":[6.641342,52.41811],"type":"Point"}
}