{
  "type": "Feature",
  "properties": {
    "addr:full":"Emmastraat 74 Rozenburg Zh South Holland 3181 GC",
    "addr:housenumber":"74",
    "addr:postcode":"zh;3181 gc",
    "addr:street":"Emmastraat",
    "iso:country":"NL",
    "sg:address":"Emmastraat 74",
    "sg:city":"Rozenburg Zh",
    "sg:orig_category":"Bloemen And Planten",
    "sg:phone":"+31 181 214 283",
    "sg:postcode":"3181 GC",
    "sg:province":"South Holland",
    "wof:name":"Bloembinderij Udo",
    "wof:placetype":"venue"
},
  "geometry": {"coordinates":[4.241969,51.906467],"type":"Point"}
}