{
  "type": "Feature",
  "properties": {
    "addr:full":"G Burgerln 4 Vlaardingen South Holland 3131 KZ",
    "addr:housenumber":"4",
    "addr:postcode":"3131 kz",
    "iso:country":"NL",
    "sg:address":"G Burgerln 4",
    "sg:city":"Vlaardingen",
    "sg:orig_category":"Keukens",
    "sg:phone":"+31 10 460 0670",
    "sg:postcode":"3131 KZ",
    "sg:province":"South Holland",
    "wof:name":"Wooning",
    "wof:placetype":"venue"
},
  "geometry": {"coordinates":[4.340359,51.910442],"type":"Point"}
}