{
  "type": "Feature",
  "properties": {
    "addr:full":"Westerkd 23 Utrecht Utrecht 3511 HB",
    "addr:housenumber":"23",
    "addr:postcode":"3511 hb",
    "addr:street":"Westerkd",
    "iso:country":"NL",
    "sg:address":"Westerkd 23",
    "sg:city":"Utrecht",
    "sg:orig_category":"Hulpverlening Sociaal",
    "sg:phone":"+31 30 233 3773",
    "sg:postcode":"3511 HB",
    "sg:province":"Utrecht",
    "sg:website":"http://www.home.wanadoo.nl/~werkloos",
    "wof:name":"Juk",
    "wof:placetype":"venue"
},
  "geometry": {"coordinates":[5.115405,52.088932],"type":"Point"}
}