{
  "type": "Feature",
  "properties": {
    "iso:country":"NL",
    "sg:address":"Dorpsdk 33",
    "sg:city":"Vrouwenpolder",
    "sg:orig_category":"Schilders",
    "sg:phone":"+31 118 592 933",
    "sg:postcode":"4354 AB",
    "sg:province":"Zeeland",
    "wof:name":"Louis Louwerse Schilderwerken",
    "wof:placetype":"venue"
},
  "geometry": {"coordinates":[3.617535,51.576176],"type":"Point"}
}