{
  "type": "Feature",
  "properties": {
    "addr:full":"Mauritsstraat 6 Zaandam Noord-Holland 1506 TZ",
    "addr:housenumber":"6",
    "addr:postcode":"1506 tz",
    "addr:street":"Mauritsstraat",
    "iso:country":"NL",
    "sg:address":"Mauritsstraat 6",
    "sg:city":"Zaandam",
    "sg:orig_category":"Algemene Werktuigbouw",
    "sg:phone":"+31 75 616 4726",
    "sg:postcode":"1506 TZ",
    "sg:province":"Noord-Holland",
    "wof:name":"Singeling Constructie- En Lastechniek Bv",
    "wof:placetype":"venue"
},
  "geometry": {"coordinates":[4.813713,52.442654],"type":"Point"}
}