{
  "type": "Feature",
  "properties": {
    "addr:full":"Johannes Verhulststraat 222 Amsterdam North Holland 1075 HG",
    "addr:housenumber":"222",
    "addr:postcode":"1075 hg",
    "addr:street":"Johannes Verhulststraat",
    "iso:country":"NL",
    "sg:address":"Johannes Verhulststraat 222",
    "sg:city":"Amsterdam",
    "sg:orig_category":"Artsen And Specialisten",
    "sg:phone":"+31 20 676 4196",
    "sg:postcode":"1075 HG",
    "sg:province":"North Holland",
    "wof:name":"Anja Hirschfeld",
    "wof:placetype":"venue"
},
  "geometry": {"coordinates":[4.865857,52.352951],"type":"Point"}
}