{
  "type": "Feature",
  "properties": {
    "addr:full":"Vlaardingenstr 51 Almere NL. 1324 LB",
    "addr:housenumber":"51",
    "addr:postcode":"1324 lb",
    "addr:street":"Vlaardingenstr;Nl.",
    "iso:country":"NL",
    "sg:address":"Vlaardingenstr 51",
    "sg:city":"Almere",
    "sg:orig_category":"Loodgieters",
    "sg:phone":"+31 36 533 1747",
    "sg:postcode":"1324 LB",
    "sg:province":"NL.",
    "sg:website":"http://www.breman.nl",
    "wof:name":"Breman Almere",
    "wof:placetype":"venue"
},
  "geometry": {"coordinates":[5.202309,52.362122],"type":"Point"}
}