{
  "type": "Feature",
  "properties": {
    "iso:country":"NL",
    "sg:address":"De Trompet 1800",
    "sg:city":"Heemskerk",
    "sg:orig_category":"Winkelinrichting",
    "sg:phone":"+31 251 255 169",
    "sg:postcode":"1967 DB",
    "sg:province":"North Holland",
    "wof:name":"A & D Interieurbouw",
    "wof:placetype":"venue"
},
  "geometry": {"coordinates":[4.7011241913,52.503780365],"type":"Point"}
}