{
  "type": "Feature",
  "properties": {
    "addr:full":"Oudeweg 19 Beerta Groningen 9686 VA",
    "addr:housenumber":"19",
    "addr:postcode":"9686",
    "addr:street":"Oudeweg",
    "iso:country":"NL",
    "sg:address":"Oudeweg 19",
    "sg:city":"Beerta",
    "sg:orig_category":"Technische Studies And Onderzoek",
    "sg:phone":"+31 597 332 999",
    "sg:postcode":"9686 VA",
    "sg:province":"Groningen",
    "wof:name":"Mfg Technica",
    "wof:placetype":"venue"
},
  "geometry": {"coordinates":[7.103723,53.180023],"type":"Point"}
}