{
  "type": "Feature",
  "properties": {
    "addr:full":"Dorpstr 12 Grathem Limburg 6096 AJ",
    "addr:housenumber":"12",
    "addr:postcode":"6096 aj",
    "addr:street":"Dorpstr",
    "iso:country":"NL",
    "sg:address":"Dorpstr 12",
    "sg:city":"Grathem",
    "sg:orig_category":"Beeldende Kunstenaars",
    "sg:phone":"+31 475 453 057",
    "sg:postcode":"6096 AJ",
    "sg:province":"Limburg",
    "wof:name":"Har Van Geleuken",
    "wof:placetype":"venue"
},
  "geometry": {"coordinates":[5.858468,51.191738],"type":"Point"}
}