{
  "type": "Feature",
  "properties": {
    "addr:full":"Arnoldystr 21 Haarlem North Holland 2024 VG",
    "addr:housenumber":"21",
    "addr:postcode":"2024 vg",
    "addr:street":"Arnoldystr",
    "iso:country":"NL",
    "sg:address":"Arnoldystr 21",
    "sg:city":"Haarlem",
    "sg:orig_category":"Biljartzalen",
    "sg:phone":"+31 23 526 2181",
    "sg:postcode":"2024 VG",
    "sg:province":"North Holland",
    "wof:name":"Biljartacademie, 1E Haarlemsche",
    "wof:placetype":"venue"
},
  "geometry": {"coordinates":[4.644226,52.403107],"type":"Point"}
}