{
  "type": "Feature",
  "properties": {
    "addr:full":"Techniekwg 5A Emmeloord Flevoland 8304 AW",
    "addr:housenumber":"5a",
    "addr:postcode":"8304 aw",
    "addr:street":"Techniekwg;Flevoland",
    "iso:country":"NL",
    "sg:address":"Techniekwg 5A",
    "sg:city":"Emmeloord",
    "sg:orig_category":"Meubelen",
    "sg:phone":"+31 527 618 373",
    "sg:postcode":"8304 AW",
    "sg:province":"Flevoland",
    "sg:website":"http://www.coronameubelen.nl",
    "wof:name":"Corona",
    "wof:placetype":"venue"
},
  "geometry": {"coordinates":[5.755919,52.69812],"type":"Point"}
}