{
  "type": "Feature",
  "properties": {
    "addr:full":"Dorpsstraat 5A Molenaarsgraaf Zuid-Holland 2973 AB",
    "addr:housenumber":"5a",
    "addr:postcode":"2973 ab",
    "addr:street":"Dorpsstraat",
    "iso:country":"NL",
    "sg:address":"Dorpsstraat 5A",
    "sg:city":"Molenaarsgraaf",
    "sg:orig_category":"Banken And Kredietinstellingen",
    "sg:phone":"+31 184 642 565",
    "sg:postcode":"2973 AB",
    "sg:province":"Zuid-Holland",
    "wof:name":"Postkantoor",
    "wof:placetype":"venue"
},
  "geometry": {"coordinates":[4.819739,51.875973],"type":"Point"}
}