{
  "type": "Feature",
  "properties": {
    "iso:country":"NL",
    "sg:address":"Langestr 54",
    "sg:city":"Winschoten",
    "sg:orig_category":"Fotoreportages",
    "sg:phone":"+31 597 413 238",
    "sg:postcode":"9671 PJ",
    "sg:province":"Groningen",
    "wof:name":"Meijer",
    "wof:placetype":"venue"
},
  "geometry": {"coordinates":[7.035639,53.144814],"type":"Point"}
}