{
  "type": "Feature",
  "properties": {
    "iso:country":"NL",
    "sg:address":"D Almaraswg 151",
    "sg:city":"Nymegen",
    "sg:orig_category":"Juridische Adviseurs",
    "sg:phone":"+31 24 356 6130",
    "sg:postcode":"6525 DV",
    "sg:province":"Gelderland",
    "wof:name":"Klaassen, J P",
    "wof:placetype":"venue"
},
  "geometry": {"coordinates":[5.871904,51.816998],"type":"Point"}
}