{
  "type": "Feature",
  "properties": {
    "addr:full":"Parkweg 20 Helmond Noord-Brabant 5701 PS",
    "addr:housenumber":"20",
    "addr:postcode":"5701 ps",
    "addr:street":"Parkweg",
    "iso:country":"NL",
    "sg:address":"Parkweg 20",
    "sg:city":"Helmond",
    "sg:orig_category":"Kappers",
    "sg:phone":"+31 492 522 934",
    "sg:postcode":"5701 PS",
    "sg:province":"Noord-Brabant",
    "wof:name":"Intercoiffure Jacques Prinssen",
    "wof:placetype":"venue"
},
  "geometry": {"coordinates":[5.6519198418,51.4784011841],"type":"Point"}
}