{
  "type": "Feature",
  "properties": {
    "addr:full":"Sesamhof 18 Utrecht Utrecht 3544 BK",
    "addr:housenumber":"18",
    "addr:postcode":"3544 bk",
    "addr:street":"Sesamhof",
    "iso:country":"NL",
    "sg:address":"Sesamhof 18",
    "sg:city":"Utrecht",
    "sg:orig_category":"Vertalers",
    "sg:phone":"+31 30 603 6060",
    "sg:postcode":"3544 BK",
    "sg:province":"Utrecht",
    "wof:name":"Noordewier, C M",
    "wof:placetype":"venue"
},
  "geometry": {"coordinates":[5.062386,52.089893],"type":"Point"}
}