{
  "type": "Feature",
  "properties": {
    "iso:country":"NL",
    "sg:address":"Zijlbaan 24",
    "sg:city":"Leiderdorp",
    "sg:orig_category":"Meubelzaken, Woning- And Keukeninrichting",
    "sg:phone":"+31 71 542 0354",
    "sg:postcode":"2352 BN",
    "sg:province":"Zuid-Holland",
    "wof:name":"Bedtijd",
    "wof:placetype":"venue"
},
  "geometry": {"coordinates":[4.516776,52.165508],"type":"Point"}
}