{
  "type": "Feature",
  "properties": {
    "addr:full":"W Halfrond 487 Amstelveen Noord-Holland 1183 JD",
    "addr:housenumber":"487",
    "addr:postcode":"1183 jd",
    "addr:street":"W Halfrond",
    "iso:country":"NL",
    "sg:address":"W Halfrond 487",
    "sg:city":"Amstelveen",
    "sg:orig_category":"Hypotheken",
    "sg:phone":"+31 20 345 8686",
    "sg:postcode":"1183 JD",
    "sg:province":"Noord-Holland",
    "sg:website":"http://www.vanbruggen.nl",
    "wof:name":"Bruggen Adviesgroep, Van",
    "wof:placetype":"venue"
},
  "geometry": {"coordinates":[4.873868,52.311821],"type":"Point"}
}