{
  "type": "Feature",
  "properties": {
    "addr:full":"Kerkhofstr 38 Rotterdam Zuid-Holland 3034 TN",
    "addr:housenumber":"38",
    "addr:postcode":"3034",
    "addr:street":"Kerkhofstr",
    "iso:country":"NL",
    "sg:address":"Kerkhofstr 38",
    "sg:city":"Rotterdam",
    "sg:orig_category":"Autorijscholen",
    "sg:phone":"+31 6 51061287",
    "sg:postcode":"3034 TN",
    "sg:province":"Zuid-Holland",
    "wof:name":"Karagoz, C",
    "wof:placetype":"venue"
},
  "geometry": {"coordinates":[4.492371,51.936283],"type":"Point"}
}