{
  "type": "Feature",
  "properties": {
    "iso:country":"NL",
    "sg:address":"Hoofdstr 161-162",
    "sg:city":"Zuidwolde Dr",
    "sg:orig_category":"Fotozaken",
    "sg:phone":"+31 528 371 551",
    "sg:postcode":"7921 AJ",
    "sg:province":"Drenthe",
    "wof:name":"Combi Kees Bunschoten",
    "wof:placetype":"venue"
},
  "geometry": {"coordinates":[6.42853,52.67675],"type":"Point"}
}