{
  "type": "Feature",
  "properties": {
    "addr:full":"Grt Voort 7 Zwolle Overijssel 8041 AM",
    "addr:housenumber":"7",
    "addr:postcode":"8041",
    "addr:street":"Voort",
    "iso:country":"NL",
    "sg:address":"Grt Voort 7",
    "sg:city":"Zwolle",
    "sg:orig_category":"Biljarts - Fabrieken",
    "sg:phone":"+31 38 422 6258",
    "sg:postcode":"8041 AM",
    "sg:province":"Overijssel",
    "sg:website":"http://www.princesse.nl",
    "wof:name":"Princesse",
    "wof:placetype":"venue"
},
  "geometry": {"coordinates":[6.072999,52.512665],"type":"Point"}
}