{
  "type": "Feature",
  "properties": {
    "iso:country":"NL",
    "sg:address":"Hoefstr 85",
    "sg:city":"Tilburg",
    "sg:orig_category":"Meubelstoffering",
    "sg:phone":"+31 13 536 8472",
    "sg:postcode":"5014 NH",
    "sg:province":"Noord-Brabant",
    "wof:name":"Hans De Kruif",
    "wof:placetype":"venue"
},
  "geometry": {"coordinates":[5.087996,51.573673],"type":"Point"}
}