{
  "type": "Feature",
  "properties": {
    "addr:full":"J V Beierenln 73 Leiderdorp Zuid-Holland 2353 DT",
    "addr:housenumber":"73",
    "addr:postcode":"2353 dt",
    "addr:street":"J;Beierenln",
    "iso:country":"NL",
    "sg:address":"J V Beierenln 73",
    "sg:city":"Leiderdorp",
    "sg:orig_category":"Bedrijfsopleidingen",
    "sg:phone":"+31 71 582 0487",
    "sg:postcode":"2353 DT",
    "sg:province":"Zuid-Holland",
    "wof:name":"Boog",
    "wof:placetype":"venue"
},
  "geometry": {"coordinates":[4.534218,52.156174],"type":"Point"}
}