{
  "type": "Feature",
  "properties": {
    "addr:full":"Antillenstraat 7 Groningen Groningen 9714 JT",
    "addr:housenumber":"7",
    "addr:postcode":"9714 jt",
    "addr:street":"Antillenstraat",
    "iso:country":"NL",
    "sg:address":"Antillenstraat 7",
    "sg:city":"Groningen",
    "sg:orig_category":"Loodgieterswerk, Verwarming And Sanitaire Installaties",
    "sg:phone":"+31 50 577 2500",
    "sg:postcode":"9714 JT",
    "sg:province":"Groningen",
    "wof:name":"T. Metus Bv",
    "wof:placetype":"venue"
},
  "geometry": {"coordinates":[6.580448,53.234268],"type":"Point"}
}