{
  "type": "Feature",
  "properties": {
    "iso:country":"NL",
    "sg:address":"Koperslagersstraat 2",
    "sg:city":"Sneek",
    "sg:orig_category":"Kantoorartikelen",
    "sg:phone":"+31 515 427 080",
    "sg:postcode":"8601 WL",
    "sg:province":"Provincie Friesland",
    "wof:name":"Habee Kantoormeubelen Bv",
    "wof:placetype":"venue"
},
  "geometry": {"coordinates":[5.6356611252,53.0289573669],"type":"Point"}
}