{
  "type": "Feature",
  "properties": {
    "iso:country":"NL",
    "sg:address":"Churchillstr 2",
    "sg:city":"Denekamp",
    "sg:orig_category":"Scholen Voor Basisonderwijs",
    "sg:phone":"+31 541 351 935",
    "sg:postcode":"7591 CX",
    "sg:province":"Overijssel",
    "wof:name":"Veldkamp Kath, De",
    "wof:placetype":"venue"
},
  "geometry": {"coordinates":[7.00443,52.379211],"type":"Point"}
}