{
  "type": "Feature",
  "properties": {
    "addr:full":"Gooimeer 16 Naarden North Holland 1411 DE",
    "addr:housenumber":"16",
    "addr:postcode":"1411 de",
    "addr:street":"Gooimeer",
    "iso:country":"NL",
    "sg:address":"Gooimeer 16",
    "sg:city":"Naarden",
    "sg:orig_category":"Autowasserettes",
    "sg:phone":"+31 35 694 6834",
    "sg:postcode":"1411 DE",
    "sg:province":"North Holland",
    "wof:name":"Gooimeer",
    "wof:placetype":"venue"
},
  "geometry": {"coordinates":[5.140217,52.308029],"type":"Point"}
}