{
  "type": "Feature",
  "properties": {
    "iso:country":"NL",
    "sg:address":"Vincent Van Goghstraat 203",
    "sg:city":"Nuenen",
    "sg:orig_category":"Medische Apparatuur And Prothesen Fab",
    "sg:phone":"+31 40 284 0988",
    "sg:postcode":"5671 DT",
    "sg:province":"North Brabant",
    "wof:name":"T Oordopje",
    "wof:placetype":"venue"
},
  "geometry": {"coordinates":[5.554779,51.473686],"type":"Point"}
}