{
  "type": "Feature",
  "properties": {
    "addr:full":"Nw Baarnstr 33 Baarn Utrecht 3743 BN",
    "addr:housenumber":"33",
    "addr:postcode":"3743 bn",
    "iso:country":"NL",
    "sg:address":"Nw Baarnstr 33",
    "sg:city":"Baarn",
    "sg:orig_category":"Gehandicapten - Hulpmiddelen",
    "sg:phone":"+31 35 548 8700",
    "sg:postcode":"3743 BN",
    "sg:province":"Utrecht",
    "sg:website":"http://www.gewanl.nl",
    "wof:name":"Gewa Ned Bv",
    "wof:placetype":"venue"
},
  "geometry": {"coordinates":[5.28306,52.212452],"type":"Point"}
}