{
  "type": "Feature",
  "properties": {
    "addr:full":"Nieuwendk 34 Someren Noord-Brabant 5712 EM",
    "addr:housenumber":"34",
    "addr:postcode":"5712 em",
    "addr:street":"Nieuwendk",
    "iso:country":"NL",
    "sg:address":"Nieuwendk 34",
    "sg:city":"Someren",
    "sg:orig_category":"Verenigingsgebouwen",
    "sg:phone":"+31 493 470 265",
    "sg:postcode":"5712 EM",
    "sg:province":"Noord-Brabant",
    "wof:name":"Komokus",
    "wof:placetype":"venue"
},
  "geometry": {"coordinates":[5.72976,51.35342],"type":"Point"}
}