{
  "type": "Feature",
  "properties": {
    "addr:full":"Langewg 13 Sommelsdyk Zuid-Holland 3245 KE",
    "addr:housenumber":"13",
    "addr:postcode":"3245 ke",
    "addr:street":"Langewg",
    "iso:country":"NL",
    "sg:address":"Langewg 13",
    "sg:city":"Sommelsdyk",
    "sg:classifiers":[
        {
            "category":"Shopping",
            "subcategory":"News",
            "type":"Retail Goods"
        }
    ],
    "sg:phone":"+31 187 471 020",
    "sg:postcode":"3245 KE",
    "sg:province":"Zuid-Holland",
    "sg:tags":[
        "maandbladen",
        "en",
        "week-"
    ],
    "wof:name":"Eilanden Nieuws Bv",
    "wof:placetype":"venue"
},
  "geometry": {"coordinates":[4.1545729637,51.7601966858],"type":"Point"}
}