{
  "type": "Feature",
  "properties": {
    "addr:full":"Vosdeel 10 Boekel Noord-Brabant 5427 RK",
    "addr:housenumber":"10",
    "addr:postcode":"5427 rk",
    "addr:street":"Vosdeel",
    "iso:country":"NL",
    "sg:address":"Vosdeel 10",
    "sg:city":"Boekel",
    "sg:classifiers":[
        {
            "category":"Food & Beverages",
            "subcategory":"Fruits & Vegetables",
            "type":"Retail Goods"
        }
    ],
    "sg:phone":"+31 492 324 069",
    "sg:postcode":"5427 RK",
    "sg:province":"Noord-Brabant",
    "sg:tags":[
        "en",
        "groenten"
    ],
    "wof:name":"Berg Bv, P Van Den",
    "wof:placetype":"venue"
},
  "geometry": {"coordinates":[5.677757,51.627052],"type":"Point"}
}