{
  "type": "Feature",
  "properties": {
    "addr:full":"Ferguutgaarde 25 Apeldoorn Gelderland 7329 BG",
    "addr:housenumber":"25",
    "addr:postcode":"7329",
    "addr:street":"Ferguutgaarde;Gelderland",
    "iso:country":"NL",
    "sg:address":"Ferguutgaarde 25",
    "sg:city":"Apeldoorn",
    "sg:orig_category":"Lichtreclame",
    "sg:phone":"+31 55 541 0154",
    "sg:postcode":"7329 BG",
    "sg:province":"Gelderland",
    "wof:name":"Sierglas 82",
    "wof:placetype":"venue"
},
  "geometry": {"coordinates":[5.996206,52.19381],"type":"Point"}
}