{
  "type": "Feature",
  "properties": {
    "addr:full":"Kleverlaan 6-A Bloemendaal North Holland 2061 TH",
    "addr:housenumber":"6-a",
    "addr:postcode":"2061 th",
    "addr:street":"Kleverlaan",
    "iso:country":"NL",
    "sg:address":"Kleverlaan 6-A",
    "sg:city":"Bloemendaal",
    "sg:orig_category":"Autokeuringen",
    "sg:phone":"+31 23 527 4842",
    "sg:postcode":"2061 TH",
    "sg:province":"North Holland",
    "wof:name":"Kennemer Automobielbedrijf",
    "wof:placetype":"venue"
},
  "geometry": {"coordinates":[4.617594,52.399334],"type":"Point"}
}