{
  "type": "Feature",
  "properties": {
    "addr:full":"J Friso Promenade 41 Ryswyk Zh South Holland 2284 DD",
    "addr:housenumber":"41;zh",
    "addr:postcode":"2284 dd",
    "addr:street":"Friso Promenade",
    "iso:country":"NL",
    "sg:address":"J Friso Promenade 41",
    "sg:city":"Ryswyk Zh",
    "sg:orig_category":"Opticiens",
    "sg:phone":"+31 70 394 1887",
    "sg:postcode":"2284 DD",
    "sg:province":"South Holland",
    "sg:website":"http://www.eyewish.nl",
    "wof:name":"Eye Wish Groeneveld",
    "wof:placetype":"venue"
},
  "geometry": {"coordinates":[4.3243598938,52.0372505188],"type":"Point"}
}