{
  "type": "Feature",
  "properties": {
    "iso:country":"NL",
    "sg:address":"Zwanebloem 3",
    "sg:city":"Purmerend",
    "sg:classifiers":[
        {
            "category":"Bakery",
            "type":"Food & Drink"
        }
    ],
    "sg:phone":"+31 299 436 204",
    "sg:postcode":"1441 TR",
    "sg:province":"Noord-Holland",
    "sg:tags":[
        "brood",
        "banket"
    ],
    "wof:name":"Echte Bakker Kees Gutter",
    "wof:placetype":"venue"
},
  "geometry": {"coordinates":[4.953399,52.49448],"type":"Point"}
}