{
  "type": "Feature",
  "properties": {
    "addr:full":"Nw Binnenwg 109A Rotterdam Zuid-Holland 3014 GH",
    "addr:housenumber":"109a",
    "addr:postcode":"3014 gh",
    "iso:country":"NL",
    "sg:address":"Nw Binnenwg 109A",
    "sg:city":"Rotterdam",
    "sg:orig_category":"Ongediertebestrijding En Ontsmetting",
    "sg:phone":"+31 10 436 2238",
    "sg:postcode":"3014 GH",
    "sg:province":"Zuid-Holland",
    "wof:name":"Motratex Bv",
    "wof:placetype":"venue"
},
  "geometry": {"coordinates":[4.46742,51.915932],"type":"Point"}
}