{
  "type": "Feature",
  "properties": {
    "iso:country":"NL",
    "sg:address":"Ganzenwg 24",
    "sg:city":"Apeldoorn",
    "sg:orig_category":"Verbouwingen",
    "sg:phone":"+31 55 844 0040",
    "sg:postcode":"7331 EX",
    "sg:province":"Gelderland",
    "wof:name":"Giesen, Nanno",
    "wof:placetype":"venue"
},
  "geometry": {"coordinates":[5.96418,52.199341],"type":"Point"}
}