{
  "type": "Feature",
  "properties": {
    "addr:full":"K P Vd Mandeleln 120 Rotterdam South Holland 3062 MB",
    "addr:housenumber":"120",
    "addr:postcode":"3062 mb",
    "addr:street":"K P",
    "iso:country":"NL",
    "sg:address":"K P Vd Mandeleln 120",
    "sg:city":"Rotterdam",
    "sg:orig_category":"Notarissen En Notariskantoren",
    "sg:phone":"+31 10 242 5400",
    "sg:postcode":"3062 MB",
    "sg:province":"South Holland",
    "wof:name":"Agt & Dussel Nv, Van",
    "wof:placetype":"venue"
},
  "geometry": {"coordinates":[4.51759,51.931339],"type":"Point"}
}