{
  "type": "Feature",
  "properties": {
    "iso:country":"NL",
    "sg:address":"Westvoorstr 54",
    "sg:city":"Dinteloord",
    "sg:classifiers":[
        {
            "category":"Food & Beverages",
            "subcategory":"Bakery",
            "type":"Retail Goods"
        }
    ],
    "sg:phone":"+31 167 522 590",
    "sg:postcode":"4671 CE",
    "sg:province":"Noord-Brabant",
    "sg:tags":[
        "brood",
        "en",
        "banket"
    ],
    "wof:name":"Bunt, Henk",
    "wof:placetype":"venue"
},
  "geometry": {"coordinates":[4.369822,51.635754],"type":"Point"}
}