{
  "type": "Feature",
  "properties": {
    "iso:country":"NL",
    "sg:address":"Bonenburgerlaan 13",
    "sg:city":"Heerde",
    "sg:classifiers":[
        {
            "category":"Bakery",
            "type":"Food & Drink"
        }
    ],
    "sg:phone":"+31 578 691 765",
    "sg:postcode":"8181 HA",
    "sg:province":"Gelderland",
    "sg:tags":[
        "brood",
        "banket"
    ],
    "wof:name":"Ommen'S Bakkerij Van",
    "wof:placetype":"venue"
},
  "geometry": {"coordinates":[6.04167,52.386074],"type":"Point"}
}