{
  "type": "Feature",
  "properties": {
    "iso:country":"NL",
    "sg:address":"Boomwg 4",
    "sg:city":"Landgraaf",
    "sg:classifiers":[
        {
            "category":"Sports & Exercise",
            "subcategory":"Stables",
            "type":"Entertainment"
        }
    ],
    "sg:phone":"+31 6 17450779",
    "sg:postcode":"6371 CZ",
    "sg:province":"Limburg",
    "sg:tags":[
        "maneges"
    ],
    "wof:name":"Vliegen, K.",
    "wof:placetype":"venue"
},
  "geometry": {"coordinates":[6.004605,50.906635],"type":"Point"}
}