{
  "type": "Feature",
  "properties": {
    "addr:full":"Rubenslaan 49-Iii Utrecht Oost Utrecht 3582 JA",
    "addr:housenumber":"49-iii",
    "addr:postcode":"3582 ja",
    "addr:street":"Rubenslaan",
    "iso:country":"NL",
    "sg:address":"Rubenslaan 49-Iii",
    "sg:city":"Utrecht Oost",
    "sg:orig_category":"Diverse Grafische Activiteiten",
    "sg:phone":"+31 6 21587260",
    "sg:postcode":"3582 JA",
    "sg:province":"Utrecht",
    "wof:name":"Wizzart Design",
    "wof:placetype":"venue"
},
  "geometry": {"coordinates":[4.89082,53.097439],"type":"Point"}
}