{
  "type": "Feature",
  "properties": {
    "addr:full":"Loswalweg 1 Dordrecht South Holland 3313 LG",
    "addr:housenumber":"1",
    "addr:postcode":"3313 lg",
    "addr:street":"Loswalweg",
    "iso:country":"NL",
    "sg:address":"Loswalweg 1",
    "sg:city":"Dordrecht",
    "sg:orig_category":"Kampeerterreinen",
    "sg:phone":"+31 78 616 3555",
    "sg:postcode":"3313 LG",
    "sg:province":"South Holland",
    "wof:name":"Nivon Natuurvriendenhuis De Kleine Rug",
    "wof:placetype":"venue"
},
  "geometry": {"coordinates":[4.7185759544,51.8074073792],"type":"Point"}
}