{
  "type": "Feature",
  "properties": {
    "iso:country":"NL",
    "sg:address":"Vogelshemwg 14",
    "sg:city":"Gasselternyveen",
    "sg:orig_category":"Hoefsmederijen",
    "sg:phone":"+31 599 512 247",
    "sg:postcode":"9514 BT",
    "sg:province":"Drenthe",
    "wof:name":"Arnold Mulder Vof",
    "wof:placetype":"venue"
},
  "geometry": {"coordinates":[6.842217,52.988091],"type":"Point"}
}