{
  "type": "Feature",
  "properties": {
    "iso:country":"NL",
    "sg:address":"Markenstr 28",
    "sg:city":"Tilburg",
    "sg:orig_category":"Administratie- En Boekhoudkantoren",
    "sg:phone":"+31 13 571 3617",
    "sg:postcode":"5045 JV",
    "sg:province":"Noord-Brabant",
    "wof:name":"Morre",
    "wof:placetype":"venue"
},
  "geometry": {"coordinates":[4.996194,51.592823],"type":"Point"}
}