{
  "type": "Feature",
  "properties": {
    "addr:full":"Markenstr 28 Tilburg Noord-Brabant 5045 JV",
    "addr:housenumber":"28",
    "addr:postcode":"5045 jv",
    "addr:street":"Markenstr",
    "iso:country":"NL",
    "sg:address":"Markenstr 28",
    "sg:city":"Tilburg",
    "sg:orig_category":"Administratie- En Boekhoudkantoren",
    "sg:phone":"+31 13 571 3617",
    "sg:postcode":"5045 JV",
    "sg:province":"Noord-Brabant",
    "wof:name":"Morre",
    "wof:placetype":"venue"
},
  "geometry": {"coordinates":[4.996194,51.592823],"type":"Point"}
}