{
  "type": "Feature",
  "properties": {
    "addr:full":"Schapendonk 114 Raamsdonksveer Noord-Brabant 4942 CG",
    "addr:housenumber":"114",
    "addr:postcode":"4942 cg",
    "addr:street":"Schapendonk",
    "iso:country":"NL",
    "sg:address":"Schapendonk 114",
    "sg:city":"Raamsdonksveer",
    "sg:orig_category":"Schilders",
    "sg:phone":"+31 162 514 925",
    "sg:postcode":"4942 CG",
    "sg:province":"Noord-Brabant",
    "wof:name":"Steyn, Van",
    "wof:placetype":"venue"
},
  "geometry": {"coordinates":[4.876714,51.704758],"type":"Point"}
}