{
  "type": "Feature",
  "properties": {
    "addr:full":"Liendertseweg 112 Amersfoort Utrecht 3815 BJ",
    "addr:housenumber":"112",
    "addr:postcode":"3815 bj",
    "addr:street":"Liendertseweg",
    "iso:country":"NL",
    "sg:address":"Liendertseweg 112",
    "sg:city":"Amersfoort",
    "sg:classifiers":[
        {
            "category":"Professional",
            "subcategory":"Accounting & Tax Preparation",
            "type":"Services"
        }
    ],
    "sg:phone":"+31 33 475 1651",
    "sg:postcode":"3815 BJ",
    "sg:province":"Utrecht",
    "sg:tags":[
        "accountant"
    ],
    "wof:name":"Kamps Accountants",
    "wof:placetype":"venue"
},
  "geometry": {"coordinates":[5.400669,52.167347],"type":"Point"}
}