{
  "type": "Feature",
  "properties": {
    "addr:full":"Jelsumerhof 43 Leeuwarden Provincie Friesland 8917 EM",
    "addr:housenumber":"43",
    "addr:postcode":"8917 em",
    "addr:street":"Jelsumerhof;Provincie Friesland",
    "iso:country":"NL",
    "sg:address":"Jelsumerhof 43",
    "sg:city":"Leeuwarden",
    "sg:orig_category":"Begrafenisverzorging",
    "sg:phone":"+31 58 212 7843",
    "sg:postcode":"8917 EM",
    "sg:province":"Provincie Friesland",
    "sg:website":"http://www.jelsumerhof.nl",
    "wof:name":"Chr Uitvaartvereniging Jelsumerhof",
    "wof:placetype":"venue"
},
  "geometry": {"coordinates":[5.79257,53.197319],"type":"Point"}
}