{
  "type": "Feature",
  "properties": {
    "iso:country":"NL",
    "sg:address":"Zuidbargerstr 110",
    "sg:city":"Emmen",
    "sg:orig_category":"Kappers",
    "sg:phone":"+31 591 632 083",
    "sg:postcode":"7812 AL",
    "sg:province":"Drenthe",
    "wof:name":"Eug?ne",
    "wof:placetype":"venue"
},
  "geometry": {"coordinates":[6.9072971344,52.7485084534],"type":"Point"}
}