{
  "type": "Feature",
  "properties": {
    "addr:full":"Bernsehoef 4 Kaatsheuvel Noord-Brabant 5171 PJ",
    "addr:housenumber":"4",
    "addr:postcode":"5171 pj",
    "addr:street":"Bernsehoef",
    "iso:country":"NL",
    "sg:address":"Bernsehoef 4",
    "sg:city":"Kaatsheuvel",
    "sg:orig_category":"Kantoor- En Secretariaatsservice",
    "sg:phone":"+31 416 540 037",
    "sg:postcode":"5171 PJ",
    "sg:province":"Noord-Brabant",
    "sg:website":"http://www.bureauvite.nl",
    "wof:name":"Vite, Bureau",
    "wof:placetype":"venue"
},
  "geometry": {"coordinates":[5.0327792168,51.6453208923],"type":"Point"}
}