{
  "type": "Feature",
  "properties": {
    "addr:full":"Heistraat 22 Sint Oedenrode Noord-Brabant 5491 BC",
    "addr:housenumber":"22;oedenrode",
    "addr:postcode":"5491 bc",
    "addr:street":"Heistraat",
    "iso:country":"NL",
    "sg:address":"Heistraat 22",
    "sg:city":"Sint Oedenrode",
    "sg:orig_category":"Kinderopvang Behalve Thuis",
    "sg:phone":"+31 413 477 763",
    "sg:postcode":"5491 BC",
    "sg:province":"Noord-Brabant",
    "wof:name":"Kindercentrum Joepie",
    "wof:placetype":"venue"
},
  "geometry": {"coordinates":[5.469415,51.567974],"type":"Point"}
}