{
  "type": "Feature",
  "properties": {
    "addr:full":"Dorpsstraat 30 Rosmalen Noord-Brabant 5241 EC",
    "addr:housenumber":"30",
    "addr:postcode":"5241 ec",
    "addr:street":"Dorpsstraat",
    "iso:country":"NL",
    "sg:address":"Dorpsstraat 30",
    "sg:city":"Rosmalen",
    "sg:orig_category":"Wasserettes And Stomerijen",
    "sg:phone":"+31 73 521 2580",
    "sg:postcode":"5241 EC",
    "sg:province":"Noord-Brabant",
    "wof:name":"De Vliegende Hollander",
    "wof:placetype":"venue"
},
  "geometry": {"coordinates":[5.3624458313,51.7175979614],"type":"Point"}
}