{
  "type": "Feature",
  "properties": {
    "addr:full":"V Geusaustr 93 Voorburg Zuid-Holland 2274 RH",
    "addr:housenumber":"93",
    "addr:postcode":"2274 rh",
    "iso:country":"NL",
    "sg:address":"V Geusaustr 93",
    "sg:city":"Voorburg",
    "sg:orig_category":"Autorijscholen",
    "sg:phone":"+31 70 385 1657",
    "sg:postcode":"2274 RH",
    "sg:province":"Zuid-Holland",
    "sg:website":"http://www.jgschippers.nl",
    "wof:name":"Schippers",
    "wof:placetype":"venue"
},
  "geometry": {"coordinates":[4.34952,52.073792],"type":"Point"}
}