{
  "type": "Feature",
  "properties": {
    "addr:full":"Otterlosewg 16A Wekerom Gelderland 6733 AM",
    "addr:housenumber":"16a",
    "addr:postcode":"6733",
    "addr:street":"Otterlosewg;Gelderland",
    "iso:country":"NL",
    "sg:address":"Otterlosewg 16A",
    "sg:city":"Wekerom",
    "sg:classifiers":[
        {
            "category":"Retail",
            "subcategory":"Auto Repair",
            "type":"Services"
        }
    ],
    "sg:phone":"+31 318 461 234",
    "sg:postcode":"6733 AM",
    "sg:province":"Gelderland",
    "sg:tags":[
        "garage"
    ],
    "wof:name":"Essen, J D Van",
    "wof:placetype":"venue"
},
  "geometry": {"coordinates":[5.721356,52.112495],"type":"Point"}
}