{
  "type": "Feature",
  "properties": {
    "addr:full":"Visserstr 1 Eindhoven North Brabant 5612 BS",
    "addr:housenumber":"1",
    "addr:postcode":"5612 bs",
    "addr:street":"Visserstr",
    "iso:country":"NL",
    "sg:address":"Visserstr 1",
    "sg:city":"Eindhoven",
    "sg:orig_category":"Meubelen",
    "sg:phone":"+31 40 245 5330",
    "sg:postcode":"5612 BS",
    "sg:province":"North Brabant",
    "wof:name":"Profijt Meubelen",
    "wof:placetype":"venue"
},
  "geometry": {"coordinates":[5.475477,51.450806],"type":"Point"}
}