{
  "type": "Feature",
  "properties": {
    "iso:country":"NL",
    "sg:address":"Jensiusstr 37",
    "sg:city":"Rotterdam",
    "sg:orig_category":"Woningbouw- Verenigingen En -Stichtingen",
    "sg:phone":"+31 10 443 2401",
    "sg:postcode":"3035 VC",
    "sg:province":"Zuid-Holland",
    "wof:name":"Woningbedrijf Rotterdam",
    "wof:placetype":"venue"
},
  "geometry": {"coordinates":[4.4826841354,51.9324989319],"type":"Point"}
}