{
  "type": "Feature",
  "properties": {
    "addr:full":"Roerkd 5 Roermond Limburg 6041 KZ",
    "addr:housenumber":"5",
    "addr:postcode":"6041 kz",
    "addr:street":"Roerkd",
    "iso:country":"NL",
    "sg:address":"Roerkd 5",
    "sg:city":"Roermond",
    "sg:orig_category":"Kantoor- En Bedrijfsmeubelen",
    "sg:phone":"+31 475 332 991",
    "sg:postcode":"6041 KZ",
    "sg:province":"Limburg",
    "sg:website":"http://www.bedrijvenplanet.nl",
    "wof:name":"Beiten, Bedrijfsinventaris",
    "wof:placetype":"venue"
},
  "geometry": {"coordinates":[5.9845871925,51.1960067749],"type":"Point"}
}