{
  "type": "Feature",
  "properties": {
    "addr:full":"Singel 466 Amsterdam North Holland 1017 AW",
    "addr:housenumber":"466",
    "addr:postcode":"1017 aw",
    "addr:street":"Singel",
    "iso:country":"NL",
    "sg:address":"Singel 466",
    "sg:city":"Amsterdam",
    "sg:orig_category":"Platenmaatschappijen",
    "sg:phone":"+31 20 550 3838",
    "sg:postcode":"1017 AW",
    "sg:province":"North Holland",
    "wof:name":"Epitaph Europe Bv",
    "wof:placetype":"venue"
},
  "geometry": {"coordinates":[4.889094,52.367249],"type":"Point"}
}