{
  "type": "Feature",
  "properties": {
    "addr:full":"Postbus 382 Emmeloord Flevoland 8300 AJ",
    "addr:housenumber":"382",
    "addr:postcode":"8300 aj",
    "addr:street":"Postbus;Flevoland",
    "iso:country":"NL",
    "sg:address":"Postbus 382",
    "sg:city":"Emmeloord",
    "sg:orig_category":"Omroep",
    "sg:phone":"+31 527 611 873",
    "sg:postcode":"8300 AJ",
    "sg:province":"Flevoland",
    "sg:website":"http://www.atlantisfm.nl",
    "wof:name":"Atlantis Fm",
    "wof:placetype":"venue"
},
  "geometry": {"coordinates":[5.7528,52.709888],"type":"Point"}
}