{
  "type": "Feature",
  "properties": {
    "iso:country":"NL",
    "sg:address":"Molenberg 7",
    "sg:city":"Middelburg",
    "sg:orig_category":"Goederenvervoer Over De Weg",
    "sg:phone":"+31 118 611 416",
    "sg:postcode":"4331 NV",
    "sg:province":"Zeeland",
    "wof:name":"Cetin Transport Vof",
    "wof:placetype":"venue"
},
  "geometry": {"coordinates":[3.607779,51.498863],"type":"Point"}
}