{
  "type": "Feature",
  "properties": {
    "iso:country":"NL",
    "sg:address":"Joseph Ledelstraat 130",
    "sg:city":"'S Gravenhage",
    "sg:orig_category":"Diverse Grafische Activiteiten",
    "sg:phone":"+31 70 364 6461",
    "sg:postcode":"2518 KM",
    "sg:province":"Zuid-Holland",
    "wof:name":"I.C.D. De Haas",
    "wof:placetype":"venue"
},
  "geometry": {"coordinates":[4.290266,52.077705],"type":"Point"}
}