{
  "type": "Feature",
  "properties": {
    "addr:full":"Noordeinde 142-144 'S Gravenhage Zuid-Holland 2514 GP",
    "addr:housenumber":"142-144",
    "addr:postcode":"2514 gp",
    "addr:street":"Noordeinde;' S",
    "iso:country":"NL",
    "sg:address":"Noordeinde 142-144",
    "sg:city":"'S Gravenhage",
    "sg:orig_category":"Kinderopvang Behalve Thuis",
    "sg:phone":"+31 70 364 6365",
    "sg:postcode":"2514 GP",
    "sg:province":"Zuid-Holland",
    "wof:name":"Kinderdagverblijf Boomer",
    "wof:placetype":"venue"
},
  "geometry": {"coordinates":[4.305425,52.082451],"type":"Point"}
}