{
  "type": "Feature",
  "properties": {
    "iso:country":"NL",
    "sg:address":"Leeuwerikln 70",
    "sg:city":"De Lier",
    "sg:orig_category":"Onroerende Goederen",
    "sg:phone":"+31 174 517 852",
    "sg:postcode":"2678 WN",
    "sg:province":"Zuid-Holland",
    "wof:name":"Zalm, Van Der",
    "wof:placetype":"venue"
},
  "geometry": {"coordinates":[4.25138,51.975086],"type":"Point"}
}