{
  "type": "Feature",
  "properties": {
    "addr:full":"Stryensewg 120 S Gravendeel Zuid-Holland 3295 KR",
    "addr:housenumber":"120",
    "addr:postcode":"3295 kr",
    "addr:street":"S",
    "iso:country":"NL",
    "sg:address":"Stryensewg 120",
    "sg:city":"S Gravendeel",
    "sg:orig_category":"Verenigingen En Stichtingen",
    "sg:phone":"+31 78 673 4863",
    "sg:postcode":"3295 KR",
    "sg:province":"Zuid-Holland",
    "sg:website":"http://www.orion.hoeksewaard.nl",
    "wof:name":"Jongeren, Stichting 'S Gravendeel",
    "wof:placetype":"venue"
},
  "geometry": {"coordinates":[4.61675,51.779362],"type":"Point"}
}