{
  "type": "Feature",
  "properties": {
    "addr:full":"Oude Oostrumsewg 4 Venray Limburg 5802 CC",
    "addr:housenumber":"4",
    "addr:postcode":"5802 cc",
    "addr:street":"Oude Oostrumsewg",
    "iso:country":"NL",
    "sg:address":"Oude Oostrumsewg 4",
    "sg:city":"Venray",
    "sg:classifiers":[
        {
            "category":"Retail",
            "subcategory":"Auto Repair",
            "type":"Services"
        }
    ],
    "sg:phone":"+31 478 586 825",
    "sg:postcode":"5802 CC",
    "sg:province":"Limburg",
    "sg:tags":[
        "garage"
    ],
    "sg:website":"http://www.youngcarsvenray.nl",
    "wof:name":"Venray, Youngcars",
    "wof:placetype":"venue"
},
  "geometry": {"coordinates":[5.979901,51.522594],"type":"Point"}
}