{
  "type": "Feature",
  "properties": {
    "addr:full":"Hartenstr 4 Amsterdam Noord-Holland 1016 CB",
    "addr:housenumber":"4",
    "addr:postcode":"1016 cb",
    "addr:street":"Hartenstr",
    "iso:country":"NL",
    "sg:address":"Hartenstr 4",
    "sg:city":"Amsterdam",
    "sg:orig_category":"Horloges En Klokken",
    "sg:phone":"+31 20 389 2789",
    "sg:postcode":"1016 CB",
    "sg:province":"Noord-Holland",
    "sg:website":"http://www.amsterdamwatchcompany.nl",
    "wof:name":"Amsterdam Watch Company",
    "wof:placetype":"venue"
},
  "geometry": {"coordinates":[4.886569,52.372425],"type":"Point"}
}