{
  "type": "Feature",
  "properties": {
    "addr:full":"Van Hoytemastraat 107 'S Gravenhage South Holland 2596 EP",
    "addr:housenumber":"107 '",
    "addr:postcode":"2596 ep",
    "addr:street":"Van Hoytemastraat",
    "iso:country":"NL",
    "sg:address":"Van Hoytemastraat 107",
    "sg:city":"'S Gravenhage",
    "sg:orig_category":"Opticiens",
    "sg:phone":"+31 70 324 9470",
    "sg:postcode":"2596 EP",
    "sg:province":"South Holland",
    "wof:name":"Ergra Optiekspec",
    "wof:placetype":"venue"
},
  "geometry": {"coordinates":[4.3242239952,52.0936851501],"type":"Point"}
}