{
  "type": "Feature",
  "properties": {
    "addr:full":"Parallelwg 12 Aalten Gelderland 7121 VA",
    "addr:housenumber":"12",
    "addr:postcode":"7121",
    "addr:street":"Parallelwg;Gelderland",
    "iso:country":"NL",
    "sg:address":"Parallelwg 12",
    "sg:city":"Aalten",
    "sg:orig_category":"Graniet-, Granito- En Terrazzowerken",
    "sg:phone":"+31 543 476 683",
    "sg:postcode":"7121 VA",
    "sg:province":"Gelderland",
    "wof:name":"K?mink, T",
    "wof:placetype":"venue"
},
  "geometry": {"coordinates":[6.583477,51.921196],"type":"Point"}
}