{
  "type": "Feature",
  "properties": {
    "addr:full":"Muntstr 46 Maastricht Limburg 6211 EK",
    "addr:housenumber":"46",
    "addr:postcode":"6211 ek",
    "addr:street":"Muntstr",
    "iso:country":"NL",
    "sg:address":"Muntstr 46",
    "sg:city":"Maastricht",
    "sg:orig_category":"Horloges En Klokken",
    "sg:phone":"+31 43 323 3777",
    "sg:postcode":"6211 EK",
    "sg:province":"Limburg",
    "wof:name":"Fossil Store",
    "wof:placetype":"venue"
},
  "geometry": {"coordinates":[5.692204,50.849991],"type":"Point"}
}