{
  "type": "Feature",
  "properties": {
    "iso:country":"NL",
    "sg:address":"Muntstr 46",
    "sg:city":"Maastricht",
    "sg:orig_category":"Horloges En Klokken",
    "sg:phone":"+31 43 323 3777",
    "sg:postcode":"6211 EK",
    "sg:province":"Limburg",
    "wof:name":"Fossil Store",
    "wof:placetype":"venue"
},
  "geometry": {"coordinates":[5.692204,50.849991],"type":"Point"}
}