{
  "type": "Feature",
  "properties": {
    "addr:full":"Lucas Bolsstraat 10H Nieuw Vennep Noord-Holland 2152 CZ",
    "addr:housenumber":"10h;2152",
    "addr:street":"Lucas Bolsstraat",
    "iso:country":"NL",
    "sg:address":"Lucas Bolsstraat 10H",
    "sg:city":"Nieuw Vennep",
    "sg:orig_category":"Oliebranders",
    "sg:phone":"+31 252 681 236",
    "sg:postcode":"2152 CZ",
    "sg:province":"Noord-Holland",
    "wof:name":"Globalsantafi",
    "wof:placetype":"venue"
},
  "geometry": {"coordinates":[4.630291,52.27227],"type":"Point"}
}