{
  "type": "Feature",
  "properties": {
    "addr:full":"Scheldekd 21 Terneuzen Zeeland 4531 EG",
    "addr:housenumber":"21",
    "addr:postcode":"4531 eg",
    "addr:street":"Scheldekd",
    "iso:country":"NL",
    "sg:address":"Scheldekd 21",
    "sg:city":"Terneuzen",
    "sg:orig_category":"Projectontwikkeling",
    "sg:phone":"+31 115 614 407",
    "sg:postcode":"4531 EG",
    "sg:province":"Zeeland",
    "sg:website":"HTTP://www.varocom.nl",
    "wof:name":"Varocom",
    "wof:placetype":"venue"
},
  "geometry": {"coordinates":[3.827559,51.338146],"type":"Point"}
}