{
  "type": "Feature",
  "properties": {
    "addr:full":"Geerkd 23 Wilnis Utrecht 3648 NX",
    "addr:housenumber":"23",
    "addr:postcode":"3648 nx",
    "addr:street":"Geerkd",
    "iso:country":"NL",
    "sg:address":"Geerkd 23",
    "sg:city":"Wilnis",
    "sg:orig_category":"Geluidshinderbestrijding",
    "sg:phone":"+31 346 242 774",
    "sg:postcode":"3648 NX",
    "sg:province":"Utrecht",
    "wof:name":"Mowi Nederland",
    "wof:placetype":"venue"
},
  "geometry": {"coordinates":[4.90548,52.196732],"type":"Point"}
}