{
  "type": "Feature",
  "properties": {
    "addr:full":"De Ruyterstr 198 Ymuiden Noord-Holland 1972 BL",
    "addr:housenumber":"198;1972 bl",
    "addr:street":"Ymuiden Noord-Holland",
    "iso:country":"NL",
    "sg:address":"De Ruyterstr 198",
    "sg:city":"Ymuiden",
    "sg:orig_category":"Onderhoudswerken",
    "sg:phone":"+31 255 522 554",
    "sg:postcode":"1972 BL",
    "sg:province":"Noord-Holland",
    "wof:name":"Spaanderman, R",
    "wof:placetype":"venue"
},
  "geometry": {"coordinates":[4.616225,52.461201],"type":"Point"}
}