{
  "type": "Feature",
  "properties": {
    "addr:full":"Nachtegaalstr 39 Utrecht Utrecht 3581 AC",
    "addr:housenumber":"39",
    "addr:postcode":"3581 ac",
    "addr:street":"Nachtegaalstr",
    "iso:country":"NL",
    "sg:address":"Nachtegaalstr 39",
    "sg:city":"Utrecht",
    "sg:orig_category":"Kappers",
    "sg:phone":"+31 30 251 9397",
    "sg:postcode":"3581 AC",
    "sg:province":"Utrecht",
    "sg:website":"http://www.kinkikappers.nl",
    "wof:name":"Kinki",
    "wof:placetype":"venue"
},
  "geometry": {"coordinates":[5.1302461624,52.0920448303],"type":"Point"}
}