{
  "type": "Feature",
  "properties": {
    "addr:full":"Grotekerksplein 5 Dordrecht Zuid-Holland 3311 CC",
    "addr:housenumber":"5",
    "addr:postcode":"3311 cc",
    "addr:street":"Grotekerksplein",
    "iso:country":"NL",
    "sg:address":"Grotekerksplein 5",
    "sg:city":"Dordrecht",
    "sg:orig_category":"Meubelreparatie And -Restauratie",
    "sg:phone":"+31 78 614 1733",
    "sg:postcode":"3311 CC",
    "sg:province":"Zuid-Holland",
    "wof:name":"Antiekrestauratie Atelier De Kro",
    "wof:placetype":"venue"
},
  "geometry": {"coordinates":[4.660851,51.814449],"type":"Point"}
}