{
  "type": "Feature",
  "properties": {
    "addr:full":"Laagty 6 Noordwyk Zh South Holland 2201 WH",
    "addr:housenumber":"6;zh",
    "addr:postcode":"2201 wh",
    "addr:street":"Laagty",
    "iso:country":"NL",
    "sg:address":"Laagty 6",
    "sg:city":"Noordwyk Zh",
    "sg:orig_category":"Onderhoudswerken",
    "sg:phone":"+31 71 361 9177",
    "sg:postcode":"2201 WH",
    "sg:province":"South Holland",
    "wof:name":"Lans Hans, Van Der",
    "wof:placetype":"venue"
},
  "geometry": {"coordinates":[4.447704,52.234268],"type":"Point"}
}