{
  "type": "Feature",
  "properties": {
    "iso:country":"NL",
    "sg:address":"De Bockhofweg 10",
    "sg:city":"Schimmert",
    "sg:orig_category":"Waterbeheer",
    "sg:phone":"+31 45 404 1876",
    "sg:postcode":"6333 AZ",
    "sg:province":"Limburg",
    "wof:name":"Nv Waterleiding Mij. Limburg",
    "wof:placetype":"venue"
},
  "geometry": {"coordinates":[5.824092865,50.8968963623],"type":"Point"}
}