{
  "type": "Feature",
  "properties": {
    "addr:full":"De Bockhofweg 10 Schimmert Limburg 6333 AZ",
    "addr:housenumber":"10",
    "addr:postcode":"6333 az",
    "addr:street":"De Bockhofweg",
    "iso:country":"NL",
    "sg:address":"De Bockhofweg 10",
    "sg:city":"Schimmert",
    "sg:orig_category":"Waterbeheer",
    "sg:phone":"+31 45 404 1876",
    "sg:postcode":"6333 AZ",
    "sg:province":"Limburg",
    "wof:name":"Nv Waterleiding Mij. Limburg",
    "wof:placetype":"venue"
},
  "geometry": {"coordinates":[5.824092865,50.8968963623],"type":"Point"}
}