{
  "type": "Feature",
  "properties": {
    "addr:full":"Groenwg 3A Esch North Brabant 5296 LZ",
    "addr:housenumber":"3a",
    "addr:postcode":"5296 lz",
    "addr:street":"Groenwg",
    "iso:country":"NL",
    "sg:address":"Groenwg 3A",
    "sg:city":"Esch",
    "sg:orig_category":"Meubelmakerijen",
    "sg:phone":"+31 411 686 007",
    "sg:postcode":"5296 LZ",
    "sg:province":"North Brabant",
    "wof:name":"Vucht Interieuratelier, Van",
    "wof:placetype":"venue"
},
  "geometry": {"coordinates":[5.29196,51.611031],"type":"Point"}
}