{
  "type": "Feature",
  "properties": {
    "iso:country":"NL",
    "sg:address":"Groenwg 3A",
    "sg:city":"Esch",
    "sg:orig_category":"Meubelmakerijen",
    "sg:phone":"+31 411 686 007",
    "sg:postcode":"5296 LZ",
    "sg:province":"North Brabant",
    "wof:name":"Vucht Interieuratelier, Van",
    "wof:placetype":"venue"
},
  "geometry": {"coordinates":[5.29196,51.611031],"type":"Point"}
}