{
  "type": "Feature",
  "properties": {
    "addr:full":"Skroef 42 Joure Friesland 8502 BR",
    "addr:housenumber":"42",
    "addr:postcode":"8502 br",
    "addr:street":"Skroef",
    "iso:country":"NL",
    "sg:address":"Skroef 42",
    "sg:city":"Joure",
    "sg:orig_category":"Webdesign Bureaus",
    "sg:phone":"+31 6 51297435",
    "sg:postcode":"8502 BR",
    "sg:province":"Friesland",
    "sg:website":"http://www.bnddigital.nl",
    "wof:name":"B & D Digital",
    "wof:placetype":"venue"
},
  "geometry": {"coordinates":[5.8047862053,52.9778862],"type":"Point"}
}