{
  "type": "Feature",
  "properties": {
    "addr:full":"Landkaartje 8 Ryen Noord-Brabant 5121 MT",
    "addr:housenumber":"8",
    "addr:postcode":"5121",
    "addr:street":"Landkaartje;Mt",
    "iso:country":"NL",
    "sg:address":"Landkaartje 8",
    "sg:city":"Ryen",
    "sg:orig_category":"Bedrijfsopleidingen",
    "sg:phone":"+31 161 227 805",
    "sg:postcode":"5121 MT",
    "sg:province":"Noord-Brabant",
    "wof:name":"Maja Visser",
    "wof:placetype":"venue"
},
  "geometry": {"coordinates":[4.9197,51.588017],"type":"Point"}
}