{
  "type": "Feature",
  "properties": {
    "iso:country":"NL",
    "sg:address":"Spoorstraat 42",
    "sg:city":"Den Helder",
    "sg:orig_category":"Schoenen",
    "sg:phone":"+31 223 613 025",
    "sg:postcode":"1781 JH",
    "sg:province":"Noord-Holland",
    "wof:name":"Koppen'S Schoenhandel Bv",
    "wof:placetype":"venue"
},
  "geometry": {"coordinates":[4.763115,52.959461],"type":"Point"}
}