{
  "type": "Feature",
  "properties": {
    "addr:full":"K Leidsedwstr 74Hs Amsterdam Noord-Holland 1017 RD",
    "addr:postcode":"1017 rd",
    "iso:country":"NL",
    "sg:address":"K Leidsedwstr 74Hs",
    "sg:city":"Amsterdam",
    "sg:orig_category":"Kappers",
    "sg:phone":"+31 20 624 6881",
    "sg:postcode":"1017 RD",
    "sg:province":"Noord-Holland",
    "sg:website":"http://www.cutsandcurls.com",
    "wof:name":"Cuts And Curls",
    "wof:placetype":"venue"
},
  "geometry": {"coordinates":[4.8848338127,52.3653678894],"type":"Point"}
}