{
  "type": "Feature",
  "properties": {
    "addr:full":"Landpoortstraat 19 Willemstad Nb Noord-Brabant 4797 AM",
    "addr:housenumber":"19",
    "addr:postcode":"4797",
    "addr:street":"Landpoortstraat",
    "iso:country":"NL",
    "sg:address":"Landpoortstraat 19",
    "sg:city":"Willemstad Nb",
    "sg:classifiers":[
        {
            "category":"Bakery",
            "type":"Food & Drink"
        }
    ],
    "sg:phone":"+31 168 472 376",
    "sg:postcode":"4797 AM",
    "sg:province":"Noord-Brabant",
    "sg:tags":[
        "brood",
        "banket"
    ],
    "wof:name":"Echte Bakker Bussing",
    "wof:placetype":"venue"
},
  "geometry": {"coordinates":[4.439528,51.691967],"type":"Point"}
}