{
  "type": "Feature",
  "properties": {
    "addr:full":"Muntelbolwerk 1 S Hertogenbosch Noord-Brabant 5213 SZ",
    "addr:housenumber":"1",
    "addr:postcode":"5213 sz",
    "addr:street":"Muntelbolwerk",
    "iso:country":"NL",
    "sg:address":"Muntelbolwerk 1",
    "sg:city":"S Hertogenbosch",
    "sg:orig_category":"Grafisch Ontwerpers",
    "sg:phone":"+31 73 613 2034",
    "sg:postcode":"5213 SZ",
    "sg:province":"Noord-Brabant",
    "wof:name":"Witvliet",
    "wof:placetype":"venue"
},
  "geometry": {"coordinates":[5.317102,51.691982],"type":"Point"}
}