{
  "type": "Feature",
  "properties": {
    "addr:full":"Dorpsstr 683 Noord Scharwoude Noord-Holland 1723 HD",
    "addr:housenumber":"683",
    "addr:postcode":"1723 hd",
    "iso:country":"NL",
    "sg:address":"Dorpsstr 683",
    "sg:city":"Noord Scharwoude",
    "sg:orig_category":"Adviesbureaus Elektrotechniek",
    "sg:phone":"+31 226 340 614",
    "sg:postcode":"1723 HD",
    "sg:province":"Noord-Holland",
    "wof:name":"Hs",
    "wof:placetype":"venue"
},
  "geometry": {"coordinates":[4.810157,52.706535],"type":"Point"}
}