{
  "type": "Feature",
  "properties": {
    "addr:full":"Het Woud 10 Nibbixwoud Noord-Holland 1688 JE",
    "addr:housenumber":"10",
    "addr:postcode":"1688 je",
    "addr:street":"Het Woud",
    "iso:country":"NL",
    "sg:address":"Het Woud 10",
    "sg:city":"Nibbixwoud",
    "sg:orig_category":"Bloemen And Planten",
    "sg:phone":"+31 229 571 629",
    "sg:postcode":"1688 JE",
    "sg:province":"Noord-Holland",
    "wof:name":"Bloemisterij Floridus Tuin- En Adviescentrum",
    "wof:placetype":"venue"
},
  "geometry": {"coordinates":[5.052502,52.695038],"type":"Point"}
}