{
  "type": "Feature",
  "properties": {
    "addr:full":"Boswg 30 St Anthonis Noord-Brabant 5845 EB",
    "addr:housenumber":"30",
    "addr:postcode":"5845 eb",
    "addr:street":"Boswg",
    "iso:country":"NL",
    "sg:address":"Boswg 30",
    "sg:city":"St Anthonis",
    "sg:classifiers":[
        {
            "category":"Retail",
            "subcategory":"Auto Repair",
            "type":"Services"
        }
    ],
    "sg:phone":"+31 485 382 732",
    "sg:postcode":"5845 EB",
    "sg:province":"Noord-Brabant",
    "sg:tags":[
        "garage"
    ],
    "sg:website":"http://www.hencocars.nl",
    "wof:name":"Henco-Cars",
    "wof:placetype":"venue"
},
  "geometry": {"coordinates":[5.868324,51.626293],"type":"Point"}
}