{
  "type": "Feature",
  "properties": {
    "addr:full":"Sarphatistraat 100Hs Amsterdam Noord-Holland 1018 GV",
    "addr:housenumber":"100hs",
    "addr:postcode":"1018 gv",
    "addr:street":"Sarphatistraat",
    "iso:country":"NL",
    "sg:address":"Sarphatistraat 100Hs",
    "sg:city":"Amsterdam",
    "sg:orig_category":"Public Relationbureaus",
    "sg:phone":"+31 20 622 6258",
    "sg:postcode":"1018 GV",
    "sg:province":"Noord-Holland",
    "wof:name":"E. Van Manen",
    "wof:placetype":"venue"
},
  "geometry": {"coordinates":[4.911241,52.361652],"type":"Point"}
}