{
  "type": "Feature",
  "properties": {
    "addr:full":"Laanstr 18 Baarn Utrecht 3743 BE",
    "addr:housenumber":"18",
    "addr:postcode":"3743",
    "addr:street":"Laanstr",
    "iso:country":"NL",
    "sg:address":"Laanstr 18",
    "sg:city":"Baarn",
    "sg:orig_category":"Juweliers",
    "sg:phone":"+31 35 541 5937",
    "sg:postcode":"3743 BE",
    "sg:province":"Utrecht",
    "wof:name":"Sassoon",
    "wof:placetype":"venue"
},
  "geometry": {"coordinates":[5.290118,52.211594],"type":"Point"}
}