{
  "type": "Feature",
  "properties": {
    "addr:full":"Vondelstr 1 Maarssen Utrecht 3601 EX",
    "addr:housenumber":"1",
    "addr:postcode":"3601 ex",
    "addr:street":"Vondelstr",
    "iso:country":"NL",
    "sg:address":"Vondelstr 1",
    "sg:city":"Maarssen",
    "sg:orig_category":"Bejaarden - Verzorgingstehuizen",
    "sg:phone":"+31 346 587 333",
    "sg:postcode":"3601 EX",
    "sg:province":"Utrecht",
    "wof:name":"Maria Dommer Woon-Zorgcentrum",
    "wof:placetype":"venue"
},
  "geometry": {"coordinates":[5.039003,52.143879],"type":"Point"}
}