{
  "type": "Feature",
  "properties": {
    "addr:full":"Wilhelminalaan 51 Zeist Utrecht 3701 BG",
    "addr:housenumber":"51",
    "addr:postcode":"3701",
    "addr:street":"Wilhelminalaan",
    "iso:country":"NL",
    "sg:address":"Wilhelminalaan 51",
    "sg:city":"Zeist",
    "sg:orig_category":"Boekenuitgeverijen",
    "sg:phone":"+31 30 692 1888",
    "sg:postcode":"3701 BG",
    "sg:province":"Utrecht",
    "wof:name":"Archer Media Bv",
    "wof:placetype":"venue"
},
  "geometry": {"coordinates":[5.250648,52.085823],"type":"Point"}
}