{
  "type": "Feature",
  "properties": {
    "addr:full":"Nachtegaalstr 83 Utrecht Utrecht 3581 AE",
    "addr:housenumber":"83",
    "addr:postcode":"3581 ae",
    "addr:street":"Nachtegaalstr",
    "iso:country":"NL",
    "sg:address":"Nachtegaalstr 83",
    "sg:city":"Utrecht",
    "sg:orig_category":"Boeken En Tijdschriften",
    "sg:phone":"+31 30 231 0910",
    "sg:postcode":"3581 AE",
    "sg:province":"Utrecht",
    "sg:website":"http://www.bruna.nl",
    "wof:name":"Bruna",
    "wof:placetype":"venue"
},
  "geometry": {"coordinates":[5.132481,52.091141],"type":"Point"}
}