{
  "type": "Feature",
  "properties": {
    "addr:full":"Schotschestraat 1 Velp Nb Noord-Brabant 5363 TJ",
    "addr:housenumber":"1",
    "addr:postcode":"5363 tj",
    "addr:street":"Schotschestraat",
    "iso:country":"NL",
    "sg:address":"Schotschestraat 1",
    "sg:city":"Velp Nb",
    "sg:orig_category":"Diverse Bedrijfsinstallaties Gh",
    "sg:phone":"+31 486 421 424",
    "sg:postcode":"5363 TJ",
    "sg:province":"Noord-Brabant",
    "wof:name":"Brands Metaaltechniek",
    "wof:placetype":"venue"
},
  "geometry": {"coordinates":[5.713399,51.752121],"type":"Point"}
}