{
  "type": "Feature",
  "properties": {
    "addr:full":"Groenekanseweg 8 Groenekan Utrecht 3737 AG",
    "addr:housenumber":"8",
    "addr:postcode":"3737",
    "addr:street":"Groenekanseweg",
    "iso:country":"NL",
    "sg:address":"Groenekanseweg 8",
    "sg:city":"Groenekan",
    "sg:orig_category":"Metaalbekleding And -Behandeling",
    "sg:phone":"+31 346 214 703",
    "sg:postcode":"3737 AG",
    "sg:province":"Utrecht",
    "wof:name":"Edin Metaal",
    "wof:placetype":"venue"
},
  "geometry": {"coordinates":[5.14783,52.124344],"type":"Point"}
}