{
  "type": "Feature",
  "properties": {
    "addr:full":"Pr Beatrixsngl 2 Valkenburg Lb Limburg 6301 VL",
    "addr:housenumber":"2",
    "addr:postcode":"lb;6301 vl",
    "iso:country":"NL",
    "sg:address":"Pr Beatrixsngl 2",
    "sg:city":"Valkenburg Lb",
    "sg:orig_category":"Bierbrouwerijen",
    "sg:phone":"+31 43 609 8888",
    "sg:postcode":"6301 VL",
    "sg:province":"Limburg",
    "sg:website":"http://www.leeuwbier.com.emleeuwbier.",
    "wof:name":"Leeuw Bv, De",
    "wof:placetype":"venue"
},
  "geometry": {"coordinates":[5.83344,50.861328],"type":"Point"}
}