{
  "type": "Feature",
  "properties": {
    "iso:country":"NL",
    "sg:address":"Den Esker 9",
    "sg:city":"Haaksbergen",
    "sg:orig_category":"Vertaal- And Tolkenbureaus",
    "sg:phone":"+31 53 572 1580",
    "sg:postcode":"7482 HP",
    "sg:province":"Overijssel",
    "wof:name":"J. Tolkamp",
    "wof:placetype":"venue"
},
  "geometry": {"coordinates":[6.718092,52.160378],"type":"Point"}
}