{
  "type": "Feature",
  "properties": {
    "addr:full":"Taag 15 Leidschendam Zuid-Holland 2267 CE",
    "addr:housenumber":"15",
    "addr:postcode":"2267 ce",
    "addr:street":"Taag",
    "iso:country":"NL",
    "sg:address":"Taag 15",
    "sg:city":"Leidschendam",
    "sg:classifiers":[
        {
            "category":"Food & Beverages",
            "subcategory":"Fruits & Vegetables",
            "type":"Retail Goods"
        }
    ],
    "sg:phone":"+31 70 320 7574",
    "sg:postcode":"2267 CE",
    "sg:province":"Zuid-Holland",
    "sg:tags":[
        "groenten"
    ],
    "wof:name":"Bel Impex",
    "wof:placetype":"venue"
},
  "geometry": {"coordinates":[4.40032,52.07888],"type":"Point"}
}