{
  "type": "Feature",
  "properties": {
    "addr:full":"De Vest 62 Valkenswaard Noord-Brabant 5555 XP",
    "addr:housenumber":"62",
    "addr:postcode":"5555 xp",
    "addr:street":"De Vest",
    "iso:country":"NL",
    "sg:address":"De Vest 62",
    "sg:city":"Valkenswaard",
    "sg:orig_category":"Behang Gh",
    "sg:phone":"+31 40 207 8400",
    "sg:postcode":"5555 XP",
    "sg:province":"Noord-Brabant",
    "wof:name":"Kobefab International Bv",
    "wof:placetype":"venue"
},
  "geometry": {"coordinates":[5.475257,51.342594],"type":"Point"}
}