{
  "type": "Feature",
  "properties": {
    "addr:full":"Van Woustraat 244 Amsterdam Noord-Holland 1073 NC",
    "addr:housenumber":"244",
    "addr:postcode":"1073 nc",
    "addr:street":"Van Woustraat",
    "iso:country":"NL",
    "sg:address":"Van Woustraat 244",
    "sg:city":"Amsterdam",
    "sg:orig_category":"Fietshandelaren",
    "sg:phone":"+31 20 679 7803",
    "sg:postcode":"1073 NC",
    "sg:province":"Noord-Holland",
    "wof:name":"Rijwielhandel G. Witter",
    "wof:placetype":"venue"
},
  "geometry": {"coordinates":[4.903807,52.349419],"type":"Point"}
}