{
  "type": "Feature",
  "properties": {
    "iso:country":"NL",
    "sg:address":"Hakvoortseweg 14",
    "sg:city":"Hilvarenbeek",
    "sg:orig_category":"Pluimveehouderijen",
    "sg:phone":"+31 13 505 1376",
    "sg:postcode":"5081 HA",
    "sg:province":"North Brabant",
    "wof:name":"J. Vingerhoets-Moonen",
    "wof:placetype":"venue"
},
  "geometry": {"coordinates":[5.14678,51.489182],"type":"Point"}
}