{
  "type": "Feature",
  "properties": {
    "addr:full":"Rykswg 192 Gaanderen Gelderland 7011 EE",
    "addr:housenumber":"192",
    "addr:postcode":"7011 ee",
    "addr:street":"Gelderland",
    "iso:country":"NL",
    "sg:address":"Rykswg 192",
    "sg:city":"Gaanderen",
    "sg:orig_category":"Verzekeringen - Verzekeringskantoren",
    "sg:phone":"+31 315 341 100",
    "sg:postcode":"7011 EE",
    "sg:province":"Gelderland",
    "wof:name":"Bongers & Lemmers",
    "wof:placetype":"venue"
},
  "geometry": {"coordinates":[6.350315,51.927399],"type":"Point"}
}