{
  "type": "Feature",
  "properties": {
    "addr:full":"Singel 540To Amsterdam Noord-Holland 1017 AZ",
    "addr:housenumber":"540to",
    "addr:postcode":"1017 az",
    "addr:street":"Singel",
    "iso:country":"NL",
    "sg:address":"Singel 540To",
    "sg:city":"Amsterdam",
    "sg:orig_category":"Bloemen En Planten",
    "sg:phone":"+31 20 623 8897",
    "sg:postcode":"1017 AZ",
    "sg:province":"Noord-Holland",
    "wof:name":"Arca Flora",
    "wof:placetype":"venue"
},
  "geometry": {"coordinates":[4.89193,52.366573],"type":"Point"}
}