{
  "type": "Feature",
  "properties": {
    "addr:full":"Sterrebos 6 Oss Noord-Brabant 5344 AM",
    "addr:housenumber":"6",
    "addr:postcode":"5344",
    "addr:street":"Sterrebos",
    "iso:country":"NL",
    "sg:address":"Sterrebos 6",
    "sg:city":"Oss",
    "sg:classifiers":[
        {
            "category":"Fast Food",
            "type":"Food & Drink"
        }
    ],
    "sg:phone":"+31 412 633 386",
    "sg:postcode":"5344 AM",
    "sg:province":"Noord-Brabant",
    "sg:tags":[
        "afhaal",
        "restaurant"
    ],
    "wof:name":"Chinees Specialiteiten- Restaurant Fine Food",
    "wof:placetype":"venue"
},
  "geometry": {"coordinates":[-77.2352142334,38.3125991821],"type":"Point"}
}