{
  "type": "Feature",
  "properties": {
    "addr:full":"Esdoornln 13 Hoogland Utrecht 3828 BK",
    "addr:housenumber":"13",
    "addr:postcode":"3828 bk",
    "addr:street":"Esdoornln",
    "iso:country":"NL",
    "sg:address":"Esdoornln 13",
    "sg:city":"Hoogland",
    "sg:classifiers":[
        {
            "category":"Personal",
            "subcategory":"Nail Salon",
            "type":"Services"
        }
    ],
    "sg:phone":"+31 33 480 5507",
    "sg:postcode":"3828 BK",
    "sg:province":"Utrecht",
    "sg:tags":[
        "pedicure"
    ],
    "wof:name":"Pedimara",
    "wof:placetype":"venue"
},
  "geometry": {"coordinates":[5.377491,52.186813],"type":"Point"}
}