{
  "type": "Feature",
  "properties": {
    "addr:full":"Anjerlaan 7 Hoevelaken Gelderland 3871 EV",
    "addr:housenumber":"7",
    "addr:street":"Anjerlaan;Gelderland",
    "iso:country":"NL",
    "sg:address":"Anjerlaan 7",
    "sg:city":"Hoevelaken",
    "sg:orig_category":"Metaalwerken",
    "sg:phone":"+31 6 21515672",
    "sg:postcode":"3871 EV",
    "sg:province":"Gelderland",
    "wof:name":"Van Der Veer",
    "wof:placetype":"venue"
},
  "geometry": {"coordinates":[5.460535,52.173195],"type":"Point"}
}