{
  "type": "Feature",
  "properties": {
    "addr:full":"Waterlandplein 213 Amsterdam North Holland 1024 LS",
    "addr:housenumber":"213",
    "addr:postcode":"1024 ls",
    "addr:street":"Waterlandplein",
    "iso:country":"NL",
    "sg:address":"Waterlandplein 213",
    "sg:city":"Amsterdam",
    "sg:orig_category":"Opticiens",
    "sg:phone":"+31 20 636 7834",
    "sg:postcode":"1024 LS",
    "sg:province":"North Holland",
    "wof:name":"Cornea Optiek",
    "wof:placetype":"venue"
},
  "geometry": {"coordinates":[4.9556498528,52.3921928406],"type":"Point"}
}