{
  "type": "Feature",
  "properties": {
    "addr:full":"H Staetsln 67 Eindhoven Noord-Brabant 5622 HM",
    "addr:housenumber":"67",
    "addr:postcode":"5622 hm",
    "iso:country":"NL",
    "sg:address":"H Staetsln 67",
    "sg:city":"Eindhoven",
    "sg:orig_category":"Schoenen",
    "sg:phone":"+31 40 243 1106",
    "sg:postcode":"5622 HM",
    "sg:province":"Noord-Brabant",
    "sg:website":"http://www.nimco.nl",
    "wof:name":"Nimco & Ligtvoet",
    "wof:placetype":"venue"
},
  "geometry": {"coordinates":[5.46291,51.459381],"type":"Point"}
}