{
  "type": "Feature",
  "properties": {
    "addr:full":"Lemoen 13B Huissen Gelderland 6852 DS",
    "addr:housenumber":"13b",
    "addr:postcode":"6852 ds",
    "addr:street":"Lemoen;Gelderland",
    "iso:country":"NL",
    "sg:address":"Lemoen 13B",
    "sg:city":"Huissen",
    "sg:orig_category":"Adviesbureaus Bedrijfsorganisatie",
    "sg:phone":"+31 26 364 0445",
    "sg:postcode":"6852 DS",
    "sg:province":"Gelderland",
    "wof:name":"Boscon Bv",
    "wof:placetype":"venue"
},
  "geometry": {"coordinates":[5.927857,51.942436],"type":"Point"}
}