{
  "type": "Feature",
  "properties": {
    "addr:full":"Bernhardpln 76 Den Helder Noord-Holland 1781 HK",
    "addr:housenumber":"76",
    "addr:postcode":"1781 hk",
    "addr:street":"Bernhardpln",
    "iso:country":"NL",
    "sg:address":"Bernhardpln 76",
    "sg:city":"Den Helder",
    "sg:orig_category":"Bibliotheken En Leeszalen Openbare",
    "sg:phone":"+31 223 623 434",
    "sg:postcode":"1781 HK",
    "sg:province":"Noord-Holland",
    "sg:website":"http://www.obdh.nl",
    "wof:name":"Bibliotheek Den Helder",
    "wof:placetype":"venue"
},
  "geometry": {"coordinates":[4.760853,52.958752],"type":"Point"}
}