{
  "type": "Feature",
  "properties": {
    "addr:full":"Achterdk 19 Vierpolders Zuid-Holland 3237 LA",
    "addr:housenumber":"19",
    "addr:postcode":"3237 la",
    "addr:street":"Achterdk",
    "iso:country":"NL",
    "sg:address":"Achterdk 19",
    "sg:city":"Vierpolders",
    "sg:orig_category":"Lasbedrijven",
    "sg:phone":"+31 181 415 654",
    "sg:postcode":"3237 LA",
    "sg:province":"Zuid-Holland",
    "wof:name":"Appelhof, G M",
    "wof:placetype":"venue"
},
  "geometry": {"coordinates":[4.175276,51.874599],"type":"Point"}
}