{
  "type": "Feature",
  "properties": {
    "addr:full":"Wolddijk 80 Noordwolde Gn Groningen 9784 TE",
    "addr:housenumber":"80",
    "addr:postcode":"gn;9784 te",
    "addr:street":"Wolddijk",
    "iso:country":"NL",
    "sg:address":"Wolddijk 80",
    "sg:city":"Noordwolde Gn",
    "sg:orig_category":"Diverse Consumentenartikelen Gh",
    "sg:phone":"+31 50 306 1981",
    "sg:postcode":"9784 TE",
    "sg:province":"Groningen",
    "wof:name":"Instrumentmakerij K. Dijkstra Noordwolde Bv",
    "wof:placetype":"venue"
},
  "geometry": {"coordinates":[6.565208,53.271374],"type":"Point"}
}