{
  "type": "Feature",
  "properties": {
    "addr:full":"Marktstraat 17 Nunspeet Gelderland 8071 GV",
    "addr:housenumber":"17",
    "addr:postcode":"8071 gv",
    "addr:street":"Marktstraat;Gelderland",
    "iso:country":"NL",
    "sg:address":"Marktstraat 17",
    "sg:city":"Nunspeet",
    "sg:orig_category":"Diverse Artikelen Fab",
    "sg:phone":"+31 341 253 221",
    "sg:postcode":"8071 GV",
    "sg:province":"Gelderland",
    "wof:name":"L. J. Kies",
    "wof:placetype":"venue"
},
  "geometry": {"coordinates":[5.782955,52.378067],"type":"Point"}
}