{
  "type": "Feature",
  "properties": {
    "addr:full":"Corridor 4A Veghel Noord-Brabant 5466 RC",
    "addr:housenumber":"4a",
    "addr:postcode":"5466 rc",
    "addr:street":"Corridor",
    "iso:country":"NL",
    "sg:address":"Corridor 4A",
    "sg:city":"Veghel",
    "sg:orig_category":"Zonweringen",
    "sg:phone":"+31 413 367 881",
    "sg:postcode":"5466 RC",
    "sg:province":"Noord-Brabant",
    "wof:name":"Zonnelux Bv",
    "wof:placetype":"venue"
},
  "geometry": {"coordinates":[5.529756,51.607731],"type":"Point"}
}