{
  "type": "Feature",
  "properties": {
    "iso:country":"NL",
    "sg:address":"Parkwg 52A",
    "sg:city":"Groningen",
    "sg:orig_category":"Binnenhuisarchitectuur",
    "sg:phone":"+31 50 525 7641",
    "sg:postcode":"9725 EK",
    "sg:province":"Groningen",
    "wof:name":"Gms",
    "wof:placetype":"venue"
},
  "geometry": {"coordinates":[6.565459,53.208164],"type":"Point"}
}