{
  "type": "Feature",
  "properties": {
    "addr:full":"Dorpsstr 61 Wagenberg North Brabant 4845 CD",
    "addr:housenumber":"61",
    "addr:postcode":"4845 cd",
    "addr:street":"Dorpsstr",
    "iso:country":"NL",
    "sg:address":"Dorpsstr 61",
    "sg:city":"Wagenberg",
    "sg:orig_category":"Bedrijfsopleidingen",
    "sg:phone":"+31 76 593 5056",
    "sg:postcode":"4845 CD",
    "sg:province":"North Brabant",
    "sg:website":"http://www.ernestboel.nl",
    "wof:name":"Ernest Boel",
    "wof:placetype":"venue"
},
  "geometry": {"coordinates":[4.746501,51.66547],"type":"Point"}
}