{
  "type": "Feature",
  "properties": {
    "addr:full":"Kon Julianastr 70 Staphorst Overijssel 7951 BM",
    "addr:housenumber":"70",
    "addr:postcode":"7951 bm",
    "addr:street":"Kon",
    "iso:country":"NL",
    "sg:address":"Kon Julianastr 70",
    "sg:city":"Staphorst",
    "sg:orig_category":"Begrafenisverzorging",
    "sg:phone":"+31 522 462 812",
    "sg:postcode":"7951 BM",
    "sg:province":"Overijssel",
    "wof:name":"Laatste Eer, De",
    "wof:placetype":"venue"
},
  "geometry": {"coordinates":[6.20808,52.646076],"type":"Point"}
}