{
  "type": "Feature",
  "properties": {
    "iso:country":"NL",
    "sg:address":"Wierdensestr 22A",
    "sg:city":"Almelo",
    "sg:classifiers":[
        {
            "category":"Professional",
            "subcategory":"Accounting & Tax Preparation",
            "type":"Services"
        }
    ],
    "sg:phone":"+31 546 824 545",
    "sg:postcode":"7607 GJ",
    "sg:province":"NL.08",
    "sg:tags":[
        "accountant",
        "en",
        "-kantoren",
        "register-"
    ],
    "sg:website":"http://www.ey.nl",
    "wof:name":"Ernst & Young",
    "wof:placetype":"venue"
},
  "geometry": {"coordinates":[6.66161,52.35508],"type":"Point"}
}