{
  "type": "Feature",
  "properties": {
    "addr:full":"Beecksanghln 30 Velsen Noord Noord-Holland 1951 LR",
    "addr:housenumber":"30",
    "addr:postcode":"1951 lr",
    "addr:street":"Beecksanghln;Velsen",
    "iso:country":"NL",
    "sg:address":"Beecksanghln 30",
    "sg:city":"Velsen Noord",
    "sg:orig_category":"Grafisch Ontwerpers",
    "sg:phone":"+31 251 271 254",
    "sg:postcode":"1951 LR",
    "sg:province":"Noord-Holland",
    "wof:name":"Dani?ls En Janssen",
    "wof:placetype":"venue"
},
  "geometry": {"coordinates":[4.647117,52.478107],"type":"Point"}
}