{
  "type": "Feature",
  "properties": {
    "addr:full":"Badhuiswg 9 S Gravenhage Zuid-Holland 2587 CA",
    "addr:housenumber":"9 s",
    "addr:postcode":"2587 ca",
    "addr:street":"Badhuiswg",
    "iso:country":"NL",
    "sg:address":"Badhuiswg 9",
    "sg:city":"S Gravenhage",
    "sg:classifiers":[
        {
            "category":"Travel",
            "subcategory":"Hotels & Motels",
            "type":"Entertainment"
        }
    ],
    "sg:phone":"+31 70 354 6075",
    "sg:postcode":"2587 CA",
    "sg:province":"Zuid-Holland",
    "wof:name":"Lunamare Scheveningen",
    "wof:placetype":"venue"
},
  "geometry": {"coordinates":[4.29118,52.112942],"type":"Point"}
}