{
  "type": "Feature",
  "properties": {
    "addr:full":"Pr Bernhardstr 4 Bunschoten Spakenb Utrecht 3751 CM",
    "addr:housenumber":"4",
    "addr:postcode":"3751 cm",
    "iso:country":"NL",
    "sg:address":"Pr Bernhardstr 4",
    "sg:city":"Bunschoten Spakenb",
    "sg:orig_category":"Kantoor- En Secretariaatsservice",
    "sg:phone":"+31 33 298 2697",
    "sg:postcode":"3751 CM",
    "sg:province":"Utrecht",
    "wof:name":"Jri",
    "wof:placetype":"venue"
},
  "geometry": {"coordinates":[5.3768692017,52.2482070923],"type":"Point"}
}