{
  "type": "Feature",
  "properties": {
    "addr:full":"Weteringkade 36 Noordwijk Zh Zuid-Holland 2201 SJ",
    "addr:housenumber":"36",
    "addr:postcode":"2201",
    "addr:street":"Weteringkade",
    "iso:country":"NL",
    "sg:address":"Weteringkade 36",
    "sg:city":"Noordwijk Zh",
    "sg:orig_category":"Bloemen And Planten",
    "sg:phone":"+31 71 364 6009",
    "sg:postcode":"2201 SJ",
    "sg:province":"Zuid-Holland",
    "wof:name":"J.P. Verkade",
    "wof:placetype":"venue"
},
  "geometry": {"coordinates":[4.445947,52.239784],"type":"Point"}
}