{
  "type": "Feature",
  "properties": {
    "addr:full":"1E Middellandstr 2A Rotterdam Zuid-Holland 3014 BD",
    "addr:housenumber":"2a",
    "addr:postcode":"3014 bd",
    "addr:street":"1E Middellandstr",
    "iso:country":"NL",
    "sg:address":"1E Middellandstr 2A",
    "sg:city":"Rotterdam",
    "sg:orig_category":"Juweliers",
    "sg:phone":"+31 10 436 1992",
    "sg:postcode":"3014 BD",
    "sg:province":"Zuid-Holland",
    "wof:name":"Golden Taj-Mahal",
    "wof:placetype":"venue"
},
  "geometry": {"coordinates":[4.465865,51.919781],"type":"Point"}
}