{
  "type": "Feature",
  "properties": {
    "iso:country":"NL",
    "sg:address":"Sportln 16",
    "sg:city":"T Harde",
    "sg:orig_category":"Bejaarden - Verzorgingstehuizen",
    "sg:phone":"+31 525 653 553",
    "sg:postcode":"8084 VB",
    "sg:province":"Gelderland",
    "wof:name":"Mariposa, Zorgcentrum",
    "wof:placetype":"venue"
},
  "geometry": {"coordinates":[5.883645,52.415775],"type":"Point"}
}