{
  "type": "Feature",
  "properties": {
    "addr:full":"Beukenln 5A Oudenbosch Noord-Brabant 4731 CD",
    "addr:housenumber":"5a",
    "addr:postcode":"4731 cd",
    "addr:street":"Beukenln",
    "iso:country":"NL",
    "sg:address":"Beukenln 5A",
    "sg:city":"Oudenbosch",
    "sg:orig_category":"Verenigingen En Stichtingen",
    "sg:phone":"+31 165 314 310",
    "sg:postcode":"4731 CD",
    "sg:province":"Noord-Brabant",
    "sg:website":"http://www.kbo-westbrabant.nl",
    "wof:name":"Kbo West-Brabant",
    "wof:placetype":"venue"
},
  "geometry": {"coordinates":[4.537806,51.588215],"type":"Point"}
}