{
  "type": "Feature",
  "properties": {
    "addr:full":"Lyonstr 9 Hengelo Ov Overijssel 7559 KL",
    "addr:housenumber":"9",
    "addr:postcode":"7559 kl",
    "addr:street":"Lyonstr;Ov",
    "iso:country":"NL",
    "sg:address":"Lyonstr 9",
    "sg:city":"Hengelo Ov",
    "sg:orig_category":"Kappers",
    "sg:phone":"+31 74 277 5718",
    "sg:postcode":"7559 KL",
    "sg:province":"Overijssel",
    "wof:name":"Mich\u00e8le",
    "wof:placetype":"venue"
},
  "geometry": {"coordinates":[6.803405,52.294994],"type":"Point"}
}