{
  "type": "Feature",
  "properties": {
    "addr:full":"Karel Doormanweg 5 Dordrecht Zuid-Holland 3317 ZD",
    "addr:housenumber":"5",
    "addr:postcode":"3317 zd",
    "addr:street":"Karel Doormanweg",
    "iso:country":"NL",
    "sg:address":"Karel Doormanweg 5",
    "sg:city":"Dordrecht",
    "sg:orig_category":"Autokeuringen",
    "sg:phone":"+31 78 618 1127",
    "sg:postcode":"3317 ZD",
    "sg:province":"Zuid-Holland",
    "wof:name":"Shell",
    "wof:placetype":"venue"
},
  "geometry": {"coordinates":[4.656271,51.794655],"type":"Point"}
}