{
  "type": "Feature",
  "properties": {
    "addr:full":"Beuger 5 Woerden Utrecht 3448 KK",
    "addr:housenumber":"5",
    "addr:postcode":"3448 kk",
    "addr:street":"Beuger",
    "iso:country":"NL",
    "sg:address":"Beuger 5",
    "sg:city":"Woerden",
    "sg:orig_category":"Administratie- En Boekhoudkantoren",
    "sg:phone":"+31 348 420 088",
    "sg:postcode":"3448 KK",
    "sg:province":"Utrecht",
    "wof:name":"Hoogeveen",
    "wof:placetype":"venue"
},
  "geometry": {"coordinates":[4.8553118706,52.0796737671],"type":"Point"}
}