{
  "type": "Feature",
  "properties": {
    "addr:full":"Kastanjeln 6 Staphorst Provincie Drenthe 7951 KE",
    "addr:housenumber":"6",
    "addr:postcode":"7951 ke",
    "addr:street":"Kastanjeln;Provincie Drenthe",
    "iso:country":"NL",
    "sg:address":"Kastanjeln 6",
    "sg:city":"Staphorst",
    "sg:orig_category":"Bloemisterijartikelen - Fabrieken En Groothandel",
    "sg:phone":"+31 522 262 626",
    "sg:postcode":"7951 KE",
    "sg:province":"Provincie Drenthe",
    "sg:website":"http://www.spectra.nu",
    "wof:name":"Spectra",
    "wof:placetype":"venue"
},
  "geometry": {"coordinates":[6.18517,52.680092],"type":"Point"}
}