{
  "type": "Feature",
  "properties": {
    "addr:full":"Hulstersewg 61 Axel Rio de Janeiro 4571 RJ",
    "addr:housenumber":"61",
    "addr:postcode":"4571 rj",
    "addr:street":"Hulstersewg;Rio De Janeiro",
    "iso:country":"NL",
    "sg:address":"Hulstersewg 61",
    "sg:city":"Axel",
    "sg:orig_category":"Grondwerken",
    "sg:phone":"+31 114 650 615",
    "sg:postcode":"4571 RJ",
    "sg:province":"Rio de Janeiro",
    "wof:name":"Evs Bv",
    "wof:placetype":"venue"
},
  "geometry": {"coordinates":[-42.9212,-22.06716],"type":"Point"}
}