{
  "type": "Feature",
  "properties": {
    "addr:full":"Oosthavendam 16-18 Breskens Zeeland 4511 AZ",
    "addr:housenumber":"16-18",
    "addr:postcode":"4511",
    "addr:street":"Oosthavendam",
    "iso:country":"NL",
    "sg:address":"Oosthavendam 16-18",
    "sg:city":"Breskens",
    "sg:orig_category":"Watersportartikelen",
    "sg:phone":"+31 117 385 166",
    "sg:postcode":"4511 AZ",
    "sg:province":"Zeeland",
    "wof:name":"Stuurwiel, 'T",
    "wof:placetype":"venue"
},
  "geometry": {"coordinates":[3.5712668896,51.3946304321],"type":"Point"}
}