{
  "type": "Feature",
  "properties": {
    "addr:full":"G Deynootwg 126/C S Gravenhage South Holland 2586 BP",
    "addr:housenumber":"126 / c",
    "addr:postcode":"2586 bp",
    "iso:country":"NL",
    "sg:address":"G Deynootwg 126/C",
    "sg:city":"S Gravenhage",
    "sg:orig_category":"Kappers",
    "sg:phone":"+31 70 350 0872",
    "sg:postcode":"2586 BP",
    "sg:province":"South Holland",
    "wof:name":"Noordermeer, Sjon",
    "wof:placetype":"venue"
},
  "geometry": {"coordinates":[4.277215,52.10672],"type":"Point"}
}