{
  "type": "Feature",
  "properties": {
    "addr:full":"St Janstr 11B Oosterhout Nb North Brabant 4901 LR",
    "addr:housenumber":"11b;nb",
    "addr:postcode":"4901 lr",
    "iso:country":"NL",
    "sg:address":"St Janstr 11B",
    "sg:city":"Oosterhout Nb",
    "sg:orig_category":"Woninginrichting",
    "sg:phone":"+31 162 453 097",
    "sg:postcode":"4901 LR",
    "sg:province":"North Brabant",
    "wof:name":"Avoird",
    "wof:placetype":"venue"
},
  "geometry": {"coordinates":[4.8589401245,51.6452026367],"type":"Point"}
}