{
  "type": "Feature",
  "properties": {
    "addr:full":"Koekoekstr 13 Sprundel Noord-Brabant 4714 AH",
    "addr:housenumber":"13",
    "addr:postcode":"4714 ah",
    "addr:street":"Koekoekstr",
    "iso:country":"NL",
    "sg:address":"Koekoekstr 13",
    "sg:city":"Sprundel",
    "sg:orig_category":"Adviesbureaus Bedrijfsorganisatie",
    "sg:phone":"+31 165 350 555",
    "sg:postcode":"4714 AH",
    "sg:province":"Noord-Brabant",
    "sg:website":"http://www.organiseit.nl",
    "wof:name":"Organise It Bv",
    "wof:placetype":"venue"
},
  "geometry": {"coordinates":[4.590917,51.535698],"type":"Point"}
}