{
  "type": "Feature",
  "properties": {
    "addr:full":"De Voorweid 45 Assendelft Noord-Holland 1566 XK",
    "addr:housenumber":"45",
    "addr:postcode":"1566 xk",
    "addr:street":"De Voorweid",
    "iso:country":"NL",
    "sg:address":"De Voorweid 45",
    "sg:city":"Assendelft",
    "sg:orig_category":"Webdesign Bureaus",
    "sg:phone":"+31 75 687 5111",
    "sg:postcode":"1566 XK",
    "sg:province":"Noord-Holland",
    "wof:name":"Okky.Nl",
    "wof:placetype":"venue"
},
  "geometry": {"coordinates":[4.744685173,52.4694099426],"type":"Point"}
}