{
  "type": "Feature",
  "properties": {
    "addr:full":"Aartsdijkweg 10 Maasland Zuid-Holland 3155 RR",
    "addr:housenumber":"10",
    "addr:postcode":"3155 rr",
    "addr:street":"Aartsdijkweg",
    "iso:country":"NL",
    "sg:address":"Aartsdijkweg 10",
    "sg:city":"Maasland",
    "sg:orig_category":"Metaalwerken",
    "sg:phone":"+31 174 516 152",
    "sg:postcode":"3155 RR",
    "sg:province":"Zuid-Holland",
    "wof:name":"Agromeco Bv",
    "wof:placetype":"venue"
},
  "geometry": {"coordinates":[4.275135,51.936325],"type":"Point"}
}