{
  "type": "Feature",
  "properties": {
    "addr:full":"Hastelwg 220 Eindhoven Noord-Brabant 5652 CL",
    "addr:housenumber":"220",
    "addr:postcode":"5652",
    "iso:country":"NL",
    "sg:address":"Hastelwg 220",
    "sg:city":"Eindhoven",
    "sg:orig_category":"Horecabenodigdheden",
    "sg:phone":"+31 40 238 0190",
    "sg:postcode":"5652 CL",
    "sg:province":"Noord-Brabant",
    "wof:name":"Blessing Investments Group Bv",
    "wof:placetype":"venue"
},
  "geometry": {"coordinates":[5.442872,51.436008],"type":"Point"}
}