{
  "type": "Feature",
  "properties": {
    "addr:full":"C Vd Lindenstr 187 Goes Zeeland 4463 VH",
    "addr:housenumber":"187",
    "addr:postcode":"4463 vh",
    "iso:country":"NL",
    "sg:address":"C Vd Lindenstr 187",
    "sg:city":"Goes",
    "sg:orig_category":"Adviesbureaus Bedrijfsorganisatie",
    "sg:phone":"+31 113 211 196",
    "sg:postcode":"4463 VH",
    "sg:province":"Zeeland",
    "wof:name":"Verheij Advies",
    "wof:placetype":"venue"
},
  "geometry": {"coordinates":[-83.914169,39.768833],"type":"Point"}
}