{
  "type": "Feature",
  "properties": {
    "addr:full":"Arena Boulev 148 Amsterdam Zuidoost Noord-Holland 1101 DJ",
    "addr:housenumber":"148",
    "addr:postcode":"zuidoost;1101 dj",
    "addr:street":"Boulev",
    "iso:country":"NL",
    "sg:address":"Arena Boulev 148",
    "sg:city":"Amsterdam Zuidoost",
    "sg:orig_category":"Woninginrichting",
    "sg:phone":"+31 20 365 9532",
    "sg:postcode":"1101 DJ",
    "sg:province":"Noord-Holland",
    "wof:name":"Koot Design Bv",
    "wof:placetype":"venue"
},
  "geometry": {"coordinates":[4.9405398369,52.3128585815],"type":"Point"}
}