{
  "type": "Feature",
  "properties": {
    "addr:full":"Stromenln 132 Woerden Utrecht 3448 CH",
    "addr:housenumber":"132",
    "addr:postcode":"3448",
    "addr:street":"Woerden",
    "iso:country":"NL",
    "sg:address":"Stromenln 132",
    "sg:city":"Woerden",
    "sg:orig_category":"Verenigingsgebouwen",
    "sg:phone":"+31 348 410 288",
    "sg:postcode":"3448 CH",
    "sg:province":"Utrecht",
    "wof:name":"Molenvliet Buurthuis",
    "wof:placetype":"venue"
},
  "geometry": {"coordinates":[4.887371,52.085117],"type":"Point"}
}