{
  "type": "Feature",
  "properties": {
    "iso:country":"NL",
    "sg:address":"Veenwg 5A",
    "sg:city":"Noorden",
    "sg:orig_category":"Adviesbureaus Verzekeringen",
    "sg:phone":"+31 172 409 864",
    "sg:postcode":"2432 CA",
    "sg:province":"Zuid-Holland",
    "wof:name":"Noorden Assurantie Advies",
    "wof:placetype":"venue"
},
  "geometry": {"coordinates":[-120.36385300000001,39.320374],"type":"Point"}
}