{
  "type": "Feature",
  "properties": {
    "iso:country":"NL",
    "sg:address":"Molenweg 41",
    "sg:city":"Berkel En Rodenrijs",
    "sg:orig_category":"Metaalwerken",
    "sg:phone":"+31 10 511 7970",
    "sg:postcode":"2651 AC",
    "sg:province":"Zuid-Holland",
    "wof:name":"Brabander Kassenbouw Bv",
    "wof:placetype":"venue"
},
  "geometry": {"coordinates":[4.437906,51.972713],"type":"Point"}
}