{
  "type": "Feature",
  "properties": {
    "addr:full":"Ramsbeekwg 55 Eibergen Gelderland 7152 KR",
    "addr:housenumber":"55",
    "addr:postcode":"7152 kr",
    "addr:street":"Ramsbeekwg;Gelderland",
    "iso:country":"NL",
    "sg:address":"Ramsbeekwg 55",
    "sg:city":"Eibergen",
    "sg:orig_category":"Loopbaanbegeleiding",
    "sg:phone":"+31 545 478 565",
    "sg:postcode":"7152 KR",
    "sg:province":"Gelderland",
    "sg:website":"http://www.vankrimpen.nl",
    "wof:name":"Krimpen Consult, Van",
    "wof:placetype":"venue"
},
  "geometry": {"coordinates":[6.66476,52.102581],"type":"Point"}
}