{
  "type": "Feature",
  "properties": {
    "addr:full":"Beneden Oosterd 64 Veendam Groningen 9641 JE",
    "addr:housenumber":"64",
    "addr:postcode":"9641 je",
    "addr:street":"Beneden Oosterd",
    "iso:country":"NL",
    "sg:address":"Beneden Oosterd 64",
    "sg:city":"Veendam",
    "sg:classifiers":[
        {
            "category":"Shopping",
            "subcategory":"News",
            "type":"Retail Goods"
        }
    ],
    "sg:phone":"+31 598 612 203",
    "sg:postcode":"9641 JE",
    "sg:province":"Groningen",
    "sg:tags":[
        "maandbladen",
        "en",
        "week-"
    ],
    "wof:name":"Verzamelkrant",
    "wof:placetype":"venue"
},
  "geometry": {"coordinates":[6.8835711479,53.1069793701],"type":"Point"}
}