{
  "type": "Feature",
  "properties": {
    "iso:country":"NL",
    "sg:address":"Sont 82",
    "sg:city":"Hoofddorp",
    "sg:orig_category":"Schilders",
    "sg:phone":"+31 23 562 9196",
    "sg:postcode":"2133 HD",
    "sg:province":"Noord-Holland",
    "wof:name":"Tympanon Applicaties",
    "wof:placetype":"venue"
},
  "geometry": {"coordinates":[4.667426,52.312199],"type":"Point"}
}