{
  "type": "Feature",
  "properties": {
    "addr:full":"Van Karnebeeklaan 2 Eesveen Overijssel 8347 WB",
    "addr:housenumber":"2",
    "addr:postcode":"8347 wb",
    "addr:street":"Van Karnebeeklaan",
    "iso:country":"NL",
    "sg:address":"Van Karnebeeklaan 2",
    "sg:city":"Eesveen",
    "sg:orig_category":"Kampeerterreinen",
    "sg:phone":"+31 521 577 292",
    "sg:postcode":"8347 WB",
    "sg:province":"Overijssel",
    "wof:name":"Camping De Hoogte",
    "wof:placetype":"venue"
},
  "geometry": {"coordinates":[6.1107029915,52.8370399475],"type":"Point"}
}