{
  "type": "Feature",
  "properties": {
    "addr:full":"Dorpsstr 80 Giessenburg South Holland 3381 AH",
    "addr:housenumber":"80",
    "addr:postcode":"3381 ah",
    "addr:street":"Dorpsstr",
    "iso:country":"NL",
    "sg:address":"Dorpsstr 80",
    "sg:city":"Giessenburg",
    "sg:orig_category":"Bloemen En Planten",
    "sg:phone":"+31 184 652 709",
    "sg:postcode":"3381 AH",
    "sg:province":"South Holland",
    "wof:name":"Klimop",
    "wof:placetype":"venue"
},
  "geometry": {"coordinates":[4.88671,51.852402],"type":"Point"}
}