{
  "type": "Feature",
  "properties": {
    "iso:country":"NL",
    "sg:address":"Plakhorstweg 46",
    "sg:city":"Doetinchem",
    "sg:orig_category":"Loodgieters- And Verwarmingsmateriaal Gh",
    "sg:phone":"+31 314 350 511",
    "sg:postcode":"7008 AT",
    "sg:province":"Gelderland",
    "wof:name":"Technisch Handelsbureau Rensa Bv",
    "wof:placetype":"venue"
},
  "geometry": {"coordinates":[6.265631,51.972595],"type":"Point"}
}