{
  "type": "Feature",
  "properties": {
    "addr:full":"Plakhorstweg 46 Doetinchem Gelderland 7008 AT",
    "addr:housenumber":"46",
    "addr:postcode":"7008",
    "addr:street":"Plakhorstweg;Gelderland",
    "iso:country":"NL",
    "sg:address":"Plakhorstweg 46",
    "sg:city":"Doetinchem",
    "sg:orig_category":"Loodgieters- And Verwarmingsmateriaal Gh",
    "sg:phone":"+31 314 350 511",
    "sg:postcode":"7008 AT",
    "sg:province":"Gelderland",
    "wof:name":"Technisch Handelsbureau Rensa Bv",
    "wof:placetype":"venue"
},
  "geometry": {"coordinates":[6.265631,51.972595],"type":"Point"}
}