{
  "type": "Feature",
  "properties": {
    "addr:full":"Alaskastroom 13 Huizen North Holland 1271 CV",
    "addr:housenumber":"13",
    "addr:postcode":"1271 cv",
    "addr:street":"Alaskastroom",
    "iso:country":"NL",
    "sg:address":"Alaskastroom 13",
    "sg:city":"Huizen",
    "sg:classifiers":[
        {
            "category":"Professional",
            "subcategory":"Accounting & Tax Preparation",
            "type":"Services"
        }
    ],
    "sg:phone":"+31 35 525 2196",
    "sg:postcode":"1271 CV",
    "sg:province":"North Holland",
    "sg:tags":[
        "accountant"
    ],
    "wof:name":"R.A. Scholten",
    "wof:placetype":"venue"
},
  "geometry": {"coordinates":[5.250496,52.308064],"type":"Point"}
}