{
  "type": "Feature",
  "properties": {
    "addr:full":"Bevelandsestr 30 Rotterdam South Holland 3083 NA",
    "addr:housenumber":"30",
    "addr:postcode":"3083 na",
    "addr:street":"Bevelandsestr",
    "iso:country":"NL",
    "sg:address":"Bevelandsestr 30",
    "sg:city":"Rotterdam",
    "sg:orig_category":"Bejaarden - Verzorgingstehuizen",
    "sg:phone":"+31 10 480 5077",
    "sg:postcode":"3083 NA",
    "sg:province":"South Holland",
    "wof:name":"Nancy Zeelenberg",
    "wof:placetype":"venue"
},
  "geometry": {"coordinates":[4.483076,51.887375],"type":"Point"}
}