{
  "type": "Feature",
  "properties": {
    "iso:country":"NL",
    "sg:address":"Van Laerstraat 15",
    "sg:city":"Venlo",
    "sg:orig_category":"Vertaal- And Tolkenbureaus",
    "sg:phone":"+31 77 382 2169",
    "sg:postcode":"5921 JG",
    "sg:province":"Limburg",
    "wof:name":"Marjan Schuman",
    "wof:placetype":"venue"
},
  "geometry": {"coordinates":[6.154961,51.370316],"type":"Point"}
}