{
  "type": "Feature",
  "properties": {
    "addr:full":"Passage 1 Valkenburg Lb Limburg 6301 DW",
    "addr:housenumber":"1",
    "addr:postcode":"lb;6301 dw",
    "addr:street":"Passage",
    "iso:country":"NL",
    "sg:address":"Passage 1",
    "sg:city":"Valkenburg Lb",
    "sg:classifiers":[
        {
            "category":"Fast Food",
            "type":"Food & Drink"
        }
    ],
    "sg:phone":"+31 43 601 4565",
    "sg:postcode":"6301 DW",
    "sg:province":"Limburg",
    "sg:tags":[
        "afhaal",
        "restaurant"
    ],
    "wof:name":"Pizzeria Della Mamma",
    "wof:placetype":"venue"
},
  "geometry": {"coordinates":[5.831618,50.865105],"type":"Point"}
}