{
  "type": "Feature",
  "properties": {
    "iso:country":"NL",
    "sg:address":"Hoevenstraat 28",
    "sg:city":"Someren",
    "sg:orig_category":"Vertaal- And Tolkenbureaus",
    "sg:phone":"+31 493 493 228",
    "sg:postcode":"5712 GW",
    "sg:province":"Noord-Brabant",
    "wof:name":"Tadellos",
    "wof:placetype":"venue"
},
  "geometry": {"coordinates":[5.701413,51.383072],"type":"Point"}
}