{
  "type": "Feature",
  "properties": {
    "addr:full":"Kerkstr 98 Koningsbosch North Rhine-Westphalia 6104 AD",
    "addr:housenumber":"98",
    "addr:postcode":"6104 ad",
    "addr:street":"Kerkstr",
    "iso:country":"NL",
    "sg:address":"Kerkstr 98",
    "sg:city":"Koningsbosch",
    "sg:orig_category":"Weegbruggen",
    "sg:phone":"+31 475 301 219",
    "sg:postcode":"6104 AD",
    "sg:province":"North Rhine-Westphalia",
    "wof:name":"Ophoven, H P A Van",
    "wof:placetype":"venue"
},
  "geometry": {"coordinates":[5.9534668922,51.0550918579],"type":"Point"}
}