{
  "type": "Feature",
  "properties": {
    "iso:country":"NL",
    "sg:address":"1E Helmersstr 17",
    "sg:city":"Amsterdam",
    "sg:orig_category":"Verenigingen En Stichtingen",
    "sg:phone":"+31 20 616 0460",
    "sg:postcode":"1054 CX",
    "sg:province":"North Holland",
    "wof:name":"Shiva",
    "wof:placetype":"venue"
},
  "geometry": {"coordinates":[4.877487,52.363949],"type":"Point"}
}