{
  "type": "Feature",
  "properties": {
    "iso:country":"NL",
    "sg:address":"Frieseweg 23",
    "sg:city":"Ijsselmuiden",
    "sg:orig_category":"Aanvullende Diensten Watertransport",
    "sg:phone":"+31 38 331 3008",
    "sg:postcode":"8271 PA",
    "sg:province":"Overijssel",
    "wof:name":"Riko Bootservice Vof",
    "wof:placetype":"venue"
},
  "geometry": {"coordinates":[5.917885,52.56818],"type":"Point"}
}