{
  "type": "Feature",
  "properties": {
    "addr:full":"Zandvoortwg 3 Baarn Utrecht 3741 BA",
    "addr:housenumber":"3",
    "addr:postcode":"3741 ba",
    "addr:street":"Zandvoortwg",
    "iso:country":"NL",
    "sg:address":"Zandvoortwg 3",
    "sg:city":"Baarn",
    "sg:orig_category":"Fietsen En Bromfietsen",
    "sg:phone":"+31 35 541 2881",
    "sg:postcode":"3741 BA",
    "sg:province":"Utrecht",
    "wof:name":"Arnold Van Eijden, Tweewielers",
    "wof:placetype":"venue"
},
  "geometry": {"coordinates":[5.291057,52.21442],"type":"Point"}
}