{
  "type": "Feature",
  "properties": {
    "iso:country":"NL",
    "sg:address":"P Buysstr 14A",
    "sg:city":"S Gravenhage",
    "sg:orig_category":"Loodgieters",
    "sg:phone":"+31 70 324 8109",
    "sg:postcode":"2582 CJ",
    "sg:province":"Zuid-Holland",
    "sg:website":"http://www.installatiedijkhuizen.nl",
    "wof:name":"Dijkhuizen Bv, Installatiebedrijf",
    "wof:placetype":"venue"
},
  "geometry": {"coordinates":[4.27852,52.092411],"type":"Point"}
}