{
  "type": "Feature",
  "properties": {
    "addr:full":"Roermondsewg 150 Steyl Limburg 5935 AE",
    "addr:housenumber":"150",
    "addr:postcode":"5935 ae",
    "iso:country":"NL",
    "sg:address":"Roermondsewg 150",
    "sg:city":"Steyl",
    "sg:orig_category":"Machineonderhoud En -Reparatie",
    "sg:phone":"+31 77 373 0077",
    "sg:postcode":"5935 AE",
    "sg:province":"Limburg",
    "wof:name":"Dohmen Ims",
    "wof:placetype":"venue"
},
  "geometry": {"coordinates":[6.12459,51.330379],"type":"Point"}
}