{
  "type": "Feature",
  "properties": {
    "addr:full":"Middelstestr 46B Weert Limburg 6004 BK",
    "addr:housenumber":"46b",
    "addr:postcode":"6004 bk",
    "addr:street":"Middelstestr",
    "iso:country":"NL",
    "sg:address":"Middelstestr 46B",
    "sg:city":"Weert",
    "sg:orig_category":"Vertaalbureaus",
    "sg:phone":"+31 495 541 728",
    "sg:postcode":"6004 BK",
    "sg:province":"Limburg",
    "wof:name":"Olfe, E",
    "wof:placetype":"venue"
},
  "geometry": {"coordinates":[5.73697,51.25095],"type":"Point"}
}