{
  "type": "Feature",
  "properties": {
    "addr:full":"Bloemendaalsewg 249A Overveen Noord-Holland 2051 GC",
    "addr:housenumber":"249a",
    "addr:postcode":"2051 gc",
    "iso:country":"NL",
    "sg:address":"Bloemendaalsewg 249A",
    "sg:city":"Overveen",
    "sg:classifiers":[
        {
            "category":"Personal",
            "subcategory":"Nail Salon",
            "type":"Services"
        }
    ],
    "sg:phone":"+31 23 526 6743",
    "sg:postcode":"2051 GC",
    "sg:province":"Noord-Holland",
    "sg:tags":[
        "pedicure"
    ],
    "wof:name":"Toets Balans Therapie",
    "wof:placetype":"venue"
},
  "geometry": {"coordinates":[4.60972,52.391731],"type":"Point"}
}