{
  "type": "Feature",
  "properties": {
    "addr:full":"Warmoesstraat 95 Amsterdam North Holland 1012 HZ",
    "addr:housenumber":"95",
    "addr:postcode":"1012 hz",
    "addr:street":"Warmoesstraat",
    "iso:country":"NL",
    "sg:address":"Warmoesstraat 95",
    "sg:city":"Amsterdam",
    "sg:classifiers":[
        {
            "category":"Bars & Pubs",
            "type":"Food & Drink"
        }
    ],
    "sg:phone":"+31 20 622 6595",
    "sg:postcode":"1012 HZ",
    "sg:province":"North Holland",
    "wof:name":"Argos Bar",
    "wof:placetype":"venue"
},
  "geometry": {"coordinates":[4.897201,52.374489],"type":"Point"}
}