{
  "type": "Feature",
  "properties": {
    "addr:full":"Beatrixstraat 10 Zoeterwoude Zuid-Holland 2382 VM",
    "addr:housenumber":"10",
    "addr:postcode":"2382 vm",
    "addr:street":"Beatrixstraat",
    "iso:country":"NL",
    "sg:address":"Beatrixstraat 10",
    "sg:city":"Zoeterwoude",
    "sg:orig_category":"Public Relationbureaus",
    "sg:phone":"+31 71 541 5459",
    "sg:postcode":"2382 VM",
    "sg:province":"Zuid-Holland",
    "wof:name":"Bfp Business Facility Partner",
    "wof:placetype":"venue"
},
  "geometry": {"coordinates":[4.52577,52.142433],"type":"Point"}
}