{
  "type": "Feature",
  "properties": {
    "addr:full":"Randweg 21 Ridderkerk South Holland 2983 AL",
    "addr:housenumber":"21",
    "addr:postcode":"2983 al",
    "addr:street":"Randweg",
    "iso:country":"NL",
    "sg:address":"Randweg 21",
    "sg:city":"Ridderkerk",
    "sg:orig_category":"Verzekeringen",
    "sg:phone":"+31 180 411 477",
    "sg:postcode":"2983 AL",
    "sg:province":"South Holland",
    "wof:name":"Assurantiekantoor P.M. Arkesteijn",
    "wof:placetype":"venue"
},
  "geometry": {"coordinates":[4.599156,51.884808],"type":"Point"}
}