{
  "type": "Feature",
  "properties": {
    "addr:full":"Fahrenheitstr 431 S Gravenhage South Holland 2561 DZ",
    "addr:housenumber":"431",
    "addr:postcode":"2561 dz",
    "addr:street":"S Gravenhage",
    "iso:country":"NL",
    "sg:address":"Fahrenheitstr 431",
    "sg:city":"S Gravenhage",
    "sg:orig_category":"Kappers",
    "sg:phone":"+31 70 363 9166",
    "sg:postcode":"2561 DZ",
    "sg:province":"South Holland",
    "wof:name":"Bert",
    "wof:placetype":"venue"
},
  "geometry": {"coordinates":[4.2758097649,52.0745315552],"type":"Point"}
}