{
  "type": "Feature",
  "properties": {
    "iso:country":"NL",
    "sg:address":"Versteegln 128",
    "sg:city":"Groenekan",
    "sg:orig_category":"Bloemen En Planten",
    "sg:phone":"+31 346 214 504",
    "sg:postcode":"3737 XC",
    "sg:province":"Utrecht",
    "wof:name":"Blooming",
    "wof:placetype":"venue"
},
  "geometry": {"coordinates":[5.15225,52.122196],"type":"Point"}
}