{
  "type": "Feature",
  "properties": {
    "addr:full":"Catharina Beersmansstr 20 Rotterdam South Holland 3025 EE",
    "addr:housenumber":"20",
    "addr:postcode":"3025 ee",
    "addr:street":"Catharina Beersmansstr",
    "iso:country":"NL",
    "sg:address":"Catharina Beersmansstr 20",
    "sg:city":"Rotterdam",
    "sg:orig_category":"Bedrijfs- And Managementsconsultants",
    "sg:phone":"+31 10 478 2999",
    "sg:postcode":"3025 EE",
    "sg:province":"South Holland",
    "wof:name":"A.I. Unal",
    "wof:placetype":"venue"
},
  "geometry": {"coordinates":[4.444189,51.908916],"type":"Point"}
}