{
  "type": "Feature",
  "properties": {
    "iso:country":"NL",
    "sg:address":"De Overtoom 26",
    "sg:city":"Alkmaar",
    "sg:orig_category":"Daken And Skeletbouw",
    "sg:phone":"+31 72 512 4300",
    "sg:postcode":"1823 BN",
    "sg:province":"Noord-Holland",
    "wof:name":"Bakker Dakbedekkingen",
    "wof:placetype":"venue"
},
  "geometry": {"coordinates":[4.756978,52.637783],"type":"Point"}
}