{
  "type": "Feature",
  "properties": {
    "iso:country":"NL",
    "sg:address":"Vyzelstr 8-9",
    "sg:city":"Arnhem",
    "sg:orig_category":"Schoenen",
    "sg:phone":"+31 26 443 6224",
    "sg:postcode":"6811 ES",
    "sg:province":"Gelderland",
    "wof:name":"Hessels",
    "wof:placetype":"venue"
},
  "geometry": {"coordinates":[5.90739,51.981747],"type":"Point"}
}