{
  "type": "Feature",
  "properties": {
    "iso:country":"NL",
    "sg:address":"Groenestraat 6",
    "sg:city":"Wadenoijen",
    "sg:orig_category":"Reclamebureaus",
    "sg:phone":"+31 344 662 192",
    "sg:postcode":"4014 MH",
    "sg:province":"Gelderland",
    "wof:name":"Vdp Netwerc",
    "wof:placetype":"venue"
},
  "geometry": {"coordinates":[5.382227,51.872532],"type":"Point"}
}