{
  "type": "Feature",
  "properties": {
    "addr:full":"Croeseln 204 Utrecht Utrecht 3521 CK",
    "addr:housenumber":"204",
    "addr:postcode":"3521 ck",
    "iso:country":"NL",
    "sg:address":"Croeseln 204",
    "sg:city":"Utrecht",
    "sg:orig_category":"Beeldende Kunstenaars",
    "sg:phone":"+31 30 293 1149",
    "sg:postcode":"3521 CK",
    "sg:province":"Utrecht",
    "wof:name":"Dam, Jos? Van",
    "wof:placetype":"venue"
},
  "geometry": {"coordinates":[5.11037,52.084572],"type":"Point"}
}