{
  "type": "Feature",
  "properties": {
    "iso:country":"NL",
    "sg:address":"Jasmijnstraat 19",
    "sg:city":"'S Gravendeel",
    "sg:orig_category":"Goederenvervoer Over De Weg",
    "sg:phone":"+31 78 673 2929",
    "sg:postcode":"3295 RJ",
    "sg:province":"Zuid-Holland",
    "wof:name":"L. De Man Transport",
    "wof:placetype":"venue"
},
  "geometry": {"coordinates":[4.608942,51.781498],"type":"Point"}
}