{
  "type": "Feature",
  "properties": {
    "addr:full":"Past Smidtsstr 8C Venlo Limburg 5921 EA",
    "addr:housenumber":"8c",
    "addr:postcode":"5921 ea",
    "iso:country":"NL",
    "sg:address":"Past Smidtsstr 8C",
    "sg:city":"Venlo",
    "sg:orig_category":"Kunststoffen- Verwerkende Industrie",
    "sg:phone":"+31 77 324 0640",
    "sg:postcode":"5921 EA",
    "sg:province":"Limburg",
    "wof:name":"H3",
    "wof:placetype":"venue"
},
  "geometry": {"coordinates":[6.147146,51.363724],"type":"Point"}
}