{
  "type": "Feature",
  "properties": {
    "iso:country":"NL",
    "sg:address":"Kerkstr Broeksitt 63",
    "sg:city":"Sittard",
    "sg:orig_category":"Fotoreportages",
    "sg:phone":"+31 46 452 8450",
    "sg:postcode":"6137 SM",
    "sg:province":"Limburg",
    "sg:website":"http://www.robnijpels.nl",
    "wof:name":"Nijpels, Rob",
    "wof:placetype":"venue"
},
  "geometry": {"coordinates":[5.890372,51.00309],"type":"Point"}
}