{
  "type": "Feature",
  "properties": {
    "addr:full":"Ommerwg 74 Den Ham Ov Overijssel 7683 AZ",
    "addr:housenumber":"74",
    "addr:postcode":"ov;7683 az",
    "addr:street":"Ommerwg",
    "iso:country":"NL",
    "sg:address":"Ommerwg 74",
    "sg:city":"Den Ham Ov",
    "sg:classifiers":[
        {
            "category":"Sports & Exercise",
            "subcategory":"Stables",
            "type":"Entertainment"
        }
    ],
    "sg:phone":"+31 546 671 266",
    "sg:postcode":"7683 AZ",
    "sg:province":"Overijssel",
    "sg:tags":[
        "maneges"
    ],
    "sg:website":"http://www.hazelhorst.nl",
    "wof:name":"Hazelhorst, De",
    "wof:placetype":"venue"
},
  "geometry": {"coordinates":[6.496274,52.462387],"type":"Point"}
}