{
  "type": "Feature",
  "properties": {
    "addr:full":"W Lodewijkln 15 Vlaardingen South Holland 3136 BS",
    "addr:housenumber":"15",
    "addr:postcode":"3136 bs",
    "addr:street":"W",
    "iso:country":"NL",
    "sg:address":"W Lodewijkln 15",
    "sg:city":"Vlaardingen",
    "sg:orig_category":"Artsen - Huisartsen",
    "sg:phone":"+31 10 474 7878",
    "sg:postcode":"3136 BS",
    "sg:province":"South Holland",
    "wof:name":"Imhoff, J A",
    "wof:placetype":"venue"
},
  "geometry": {"coordinates":[4.340359,51.910442],"type":"Point"}
}