{
  "type": "Feature",
  "properties": {
    "addr:full":"De Flinesstraat 18 Amsterdam Noord-Holland 1099 CC",
    "addr:housenumber":"18;1099",
    "addr:postcode":"cc",
    "addr:street":"De Flinesstraat",
    "iso:country":"NL",
    "sg:address":"De Flinesstraat 18",
    "sg:city":"Amsterdam",
    "sg:orig_category":"Gespecialiseerde Voeding",
    "sg:phone":"+31 20 463 8833",
    "sg:postcode":"1099 CC",
    "sg:province":"Noord-Holland",
    "wof:name":"Wah Nam Hong Superstore Bv",
    "wof:placetype":"venue"
},
  "geometry": {"coordinates":[4.92531,52.325405],"type":"Point"}
}