{
  "type": "Feature",
  "properties": {
    "addr:full":"Aidapln 32 Alphen Aan Den Ryn Zuid-Holland 2402 TG",
    "addr:housenumber":"32",
    "addr:postcode":"2402 tg",
    "addr:street":"Aidapln;Aan Den Ryn",
    "iso:country":"NL",
    "sg:address":"Aidapln 32",
    "sg:city":"Alphen Aan Den Ryn",
    "sg:orig_category":"Acupunctuur",
    "sg:phone":"+31 172 440 576",
    "sg:postcode":"2402 TG",
    "sg:province":"Zuid-Holland",
    "wof:name":"Duindam, A P",
    "wof:placetype":"venue"
},
  "geometry": {"coordinates":[4.675471,52.144283],"type":"Point"}
}