{
  "type": "Feature",
  "properties": {
    "addr:full":"De Kloostertuin 14 Boxmeer Noord-Brabant 5831 JT",
    "addr:housenumber":"14",
    "addr:postcode":"5831 jt",
    "addr:street":"De Kloostertuin",
    "iso:country":"NL",
    "sg:address":"De Kloostertuin 14",
    "sg:city":"Boxmeer",
    "sg:orig_category":"Vers Brood And Banket Fab",
    "sg:phone":"+31 485 576 303",
    "sg:postcode":"5831 JT",
    "sg:province":"Noord-Brabant",
    "wof:name":"Van Den Bergh",
    "wof:placetype":"venue"
},
  "geometry": {"coordinates":[5.94972,51.648422],"type":"Point"}
}