{
  "type": "Feature",
  "properties": {
    "addr:full":"Hellendoornseweg 7 Daarle Overijssel 7688 PC",
    "addr:housenumber":"7",
    "addr:postcode":"7688 pc",
    "addr:street":"Hellendoornseweg",
    "iso:country":"NL",
    "sg:address":"Hellendoornseweg 7",
    "sg:city":"Daarle",
    "sg:orig_category":"Fietshandelaren",
    "sg:phone":"+31 546 697 319",
    "sg:postcode":"7688 PC",
    "sg:province":"Overijssel",
    "wof:name":"Valk Tweewielers",
    "wof:placetype":"venue"
},
  "geometry": {"coordinates":[6.53729,52.431824],"type":"Point"}
}