{
  "type": "Feature",
  "properties": {
    "iso:country":"NL",
    "sg:address":"Duitslandwg 13",
    "sg:city":"Bodegraven",
    "sg:orig_category":"Adviesbureaus",
    "sg:phone":"+31 172 650 737",
    "sg:postcode":"2411 NT",
    "sg:province":"Zuid-Holland",
    "wof:name":"Top Systems Bv",
    "wof:placetype":"venue"
},
  "geometry": {"coordinates":[4.754029,52.068382],"type":"Point"}
}