{
  "type": "Feature",
  "properties": {
    "addr:full":"Eikenln 253C Alphen Aan Den Ryn Zuid-Holland 2404 BP",
    "addr:housenumber":"253c",
    "addr:postcode":"2404 bp",
    "addr:street":"Eikenln;Aan Den Ryn",
    "iso:country":"NL",
    "sg:address":"Eikenln 253C",
    "sg:city":"Alphen Aan Den Ryn",
    "sg:orig_category":"Oud Metaal",
    "sg:phone":"+31 172 492 699",
    "sg:postcode":"2404 BP",
    "sg:province":"Zuid-Holland",
    "wof:name":"Milieu Kompas",
    "wof:placetype":"venue"
},
  "geometry": {"coordinates":[4.6589207649,52.1271896362],"type":"Point"}
}