{
  "type": "Feature",
  "properties": {
    "iso:country":"NL",
    "sg:address":"Rijksweg Noord 53",
    "sg:city":"Elst Gld",
    "sg:orig_category":"Alternatieve Geneeskunde",
    "sg:phone":"+31 481 371 601",
    "sg:postcode":"6661 KC",
    "sg:province":"Gelderland",
    "wof:name":"M P W Visser Dusseldorp",
    "wof:placetype":"venue"
},
  "geometry": {"coordinates":[5.852952,51.922901],"type":"Point"}
}