{
  "type": "Feature",
  "properties": {
    "iso:country":"NL",
    "sg:address":"Stationspln 6",
    "sg:city":"Barneveld",
    "sg:orig_category":"Cafetaria'S",
    "sg:phone":"+31 342 400 273",
    "sg:postcode":"3771 ES",
    "sg:province":"Gelderland",
    "sg:website":"http://www.mclevis.nl",
    "wof:name":"Mc Levi'S",
    "wof:placetype":"venue"
},
  "geometry": {"coordinates":[5.591431,52.142551],"type":"Point"}
}