{
  "type": "Feature",
  "properties": {
    "addr:full":"Egelingln 2B Zeist Utrecht 3705 TC",
    "addr:housenumber":"2b",
    "addr:postcode":"3705 tc",
    "addr:street":"Egelingln",
    "iso:country":"NL",
    "sg:address":"Egelingln 2B",
    "sg:city":"Zeist",
    "sg:orig_category":"Peuterspeelzalen",
    "sg:phone":"+31 30 695 7003",
    "sg:postcode":"3705 TC",
    "sg:province":"Utrecht",
    "wof:name":"Eigen Willetje, Het",
    "wof:placetype":"venue"
},
  "geometry": {"coordinates":[5.240832,52.09531],"type":"Point"}
}