{
  "type": "Feature",
  "properties": {
    "addr:full":"Kwistbeekln 3 Baarlo Lb Limburg 5991 XH",
    "addr:housenumber":"3",
    "addr:postcode":"lb;5991 xh",
    "addr:street":"Kwistbeekln",
    "iso:country":"NL",
    "sg:address":"Kwistbeekln 3",
    "sg:city":"Baarlo Lb",
    "sg:orig_category":"Homeopathie",
    "sg:phone":"+31 77 477 2320",
    "sg:postcode":"5991 XH",
    "sg:province":"Limburg",
    "wof:name":"Derks, C J Th",
    "wof:placetype":"venue"
},
  "geometry": {"coordinates":[6.094882,51.3279],"type":"Point"}
}