{
  "type": "Feature",
  "properties": {
    "iso:country":"NL",
    "sg:address":"Lynbaan 70",
    "sg:city":"Lemmer",
    "sg:orig_category":"Acupunctuur",
    "sg:phone":"+31 514 563 528",
    "sg:postcode":"8531 JV",
    "sg:province":"Friesland",
    "wof:name":"Jongh, W J De",
    "wof:placetype":"venue"
},
  "geometry": {"coordinates":[5.712385,52.844051],"type":"Point"}
}