{
  "type": "Feature",
  "properties": {
    "addr:full":"Lynbaan 70 Lemmer Friesland 8531 JV",
    "addr:housenumber":"70",
    "addr:postcode":"8531 jv",
    "addr:street":"Lynbaan",
    "iso:country":"NL",
    "sg:address":"Lynbaan 70",
    "sg:city":"Lemmer",
    "sg:orig_category":"Acupunctuur",
    "sg:phone":"+31 514 563 528",
    "sg:postcode":"8531 JV",
    "sg:province":"Friesland",
    "wof:name":"Jongh, W J De",
    "wof:placetype":"venue"
},
  "geometry": {"coordinates":[5.712385,52.844051],"type":"Point"}
}