{
  "type": "Feature",
  "properties": {
    "addr:full":"Admiraal De Ruijterweg 60 Amsterdam Noord-Holland 1056 GL",
    "addr:housenumber":"60",
    "addr:postcode":"1056 gl",
    "addr:street":"Admiraal De Ruijterweg",
    "iso:country":"NL",
    "sg:address":"Admiraal De Ruijterweg 60",
    "sg:city":"Amsterdam",
    "sg:orig_category":"Werving And Selectie Van Tijdelijk Personeel And Uitzendkantoren",
    "sg:phone":"+31 20 689 7070",
    "sg:postcode":"1056 GL",
    "sg:province":"Noord-Holland",
    "wof:name":"Abd Bv",
    "wof:placetype":"venue"
},
  "geometry": {"coordinates":[4.8618879318,52.3712539673],"type":"Point"}
}