{
  "type": "Feature",
  "properties": {
    "addr:full":"Bruggenrijt 9 Tilburg Noord-Brabant 5032 BH",
    "addr:housenumber":"9",
    "addr:postcode":"5032 bh",
    "addr:street":"Bruggenrijt",
    "iso:country":"NL",
    "sg:address":"Bruggenrijt 9",
    "sg:city":"Tilburg",
    "sg:orig_category":"Fitnesscentra",
    "sg:phone":"+31 13 468 5639",
    "sg:postcode":"5032 BH",
    "sg:province":"Noord-Brabant",
    "wof:name":"J. De Goede",
    "wof:placetype":"venue"
},
  "geometry": {"coordinates":[5.038292,51.546806],"type":"Point"}
}