{
  "type": "Feature",
  "properties": {
    "addr:full":"Zeekoet 14 Noordwyk Zh Zuid-Holland 2201 XX",
    "addr:housenumber":"14",
    "addr:postcode":"2201 xx",
    "addr:street":"Zeekoet",
    "iso:country":"NL",
    "sg:address":"Zeekoet 14",
    "sg:city":"Noordwyk Zh",
    "sg:orig_category":"Onderhoudswerken",
    "sg:phone":"+31 71 361 6786",
    "sg:postcode":"2201 XX",
    "sg:province":"Zuid-Holland",
    "wof:name":"Cockheijt",
    "wof:placetype":"venue"
},
  "geometry": {"coordinates":[4.447704,52.234268],"type":"Point"}
}