{
  "type": "Feature",
  "properties": {
    "addr:full":"Acacialaan 61 Winschoten Groningen 9674 AB",
    "addr:housenumber":"61",
    "addr:postcode":"9674 ab",
    "addr:street":"Acacialaan",
    "iso:country":"NL",
    "sg:address":"Acacialaan 61",
    "sg:city":"Winschoten",
    "sg:orig_category":"Begrafenisondernemers",
    "sg:phone":"+31 597 413 100",
    "sg:postcode":"9674 AB",
    "sg:province":"Groningen",
    "wof:name":"Uitvaartcentrum Oost-Groningen Bv",
    "wof:placetype":"venue"
},
  "geometry": {"coordinates":[7.014805,53.147793],"type":"Point"}
}