{
  "type": "Feature",
  "properties": {
    "iso:country":"NL",
    "sg:address":"Buitenveldertseln 42",
    "sg:city":"Amsterdam",
    "sg:orig_category":"Hypotheken",
    "sg:phone":"+31 20 301 7702",
    "sg:postcode":"1081 AA",
    "sg:province":"Noord-Holland",
    "sg:website":"http://www.amsterdam.hypotheekshop.nl/583",
    "wof:name":"Hypotheekshop, De",
    "wof:placetype":"venue"
},
  "geometry": {"coordinates":[4.868263,52.331017],"type":"Point"}
}