{
  "type": "Feature",
  "properties": {
    "addr:full":"Maasstraat 220 Den Haag South Holland 2515 AG",
    "addr:housenumber":"220",
    "addr:postcode":"2515",
    "addr:street":"Maasstraat",
    "iso:country":"NL",
    "sg:address":"Maasstraat 220",
    "sg:city":"Den Haag",
    "sg:classifiers":[
        {
            "category":"Fast Food",
            "type":"Food & Drink"
        }
    ],
    "sg:phone":"+31 70 385 1660",
    "sg:postcode":"2515 AG",
    "sg:province":"South Holland",
    "sg:tags":[
        "afhaal",
        "restaurant"
    ],
    "wof:name":"Kajo",
    "wof:placetype":"venue"
},
  "geometry": {"coordinates":[4.327306,52.075958],"type":"Point"}
}