{
  "type": "Feature",
  "properties": {
    "iso:country":"NL",
    "sg:address":"Prins Bernhardlaan 34",
    "sg:city":"Egmond A/D Hoef",
    "sg:orig_category":"Binnenhuisarchitecten",
    "sg:phone":"+31 72 506 4182",
    "sg:postcode":"1934 ES",
    "sg:province":"Noord-Holland",
    "wof:name":"Carry Straathof",
    "wof:placetype":"venue"
},
  "geometry": {"coordinates":[4.656061,52.624634],"type":"Point"}
}