{
  "type": "Feature",
  "properties": {
    "addr:full":"Ringdk 488 Ridderkerk Zuid-Holland 2987 VZ",
    "addr:housenumber":"488",
    "addr:postcode":"2987 vz",
    "iso:country":"NL",
    "sg:address":"Ringdk 488",
    "sg:city":"Ridderkerk",
    "sg:orig_category":"Pijpleidingen",
    "sg:phone":"+31 180 462 819",
    "sg:postcode":"2987 VZ",
    "sg:province":"Zuid-Holland",
    "wof:name":"Seton Bv",
    "wof:placetype":"venue"
},
  "geometry": {"coordinates":[4.5897,51.891941],"type":"Point"}
}