{
  "type": "Feature",
  "properties": {
    "iso:country":"NL",
    "sg:address":"Grietsestr 43",
    "sg:city":"Zevenaar",
    "sg:orig_category":"Kinderkleding",
    "sg:phone":"+31 316 547 976",
    "sg:postcode":"6901 GS",
    "sg:province":"Gelderland",
    "wof:name":"Vito",
    "wof:placetype":"venue"
},
  "geometry": {"coordinates":[6.077258,51.930729],"type":"Point"}
}