{
  "type": "Feature",
  "properties": {
    "iso:country":"NL",
    "sg:address":"Van Swietenlaan 23",
    "sg:city":"Groningen",
    "sg:orig_category":"Film-, Tv- And Videoproductie",
    "sg:phone":"+31 50 853 3200",
    "sg:postcode":"9728 NX",
    "sg:province":"Groningen",
    "wof:name":"Castel Media Bv",
    "wof:placetype":"venue"
},
  "geometry": {"coordinates":[6.547869,53.188938],"type":"Point"}
}