{
  "type": "Feature",
  "properties": {
    "iso:country":"NL",
    "sg:address":"J H Van 'T Hoffweg 1",
    "sg:city":"Bussum",
    "sg:orig_category":"Bedrijfs- And Managementsconsultants",
    "sg:phone":"+31 35 691 3872",
    "sg:postcode":"1402 VG",
    "sg:province":"North Holland",
    "wof:name":"Brasil Eco Bv",
    "wof:placetype":"venue"
},
  "geometry": {"coordinates":[5.178448,52.274071],"type":"Point"}
}