{
  "type": "Feature",
  "properties": {
    "addr:full":"Lavendeltuin 1 Leiden Zuid-Holland 2317 NB",
    "addr:housenumber":"1",
    "addr:postcode":"2317 nb",
    "addr:street":"Lavendeltuin",
    "iso:country":"NL",
    "sg:address":"Lavendeltuin 1",
    "sg:city":"Leiden",
    "sg:orig_category":"Meubelmakerijen",
    "sg:phone":"+31 71 572 7925",
    "sg:postcode":"2317 NB",
    "sg:province":"Zuid-Holland",
    "wof:name":"Lex Mels",
    "wof:placetype":"venue"
},
  "geometry": {"coordinates":[4.4996800423,52.1768722534],"type":"Point"}
}