{
  "type": "Feature",
  "properties": {
    "iso:country":"NL",
    "sg:address":"Burgemeester Van Erpstr 58",
    "sg:city":"Berghem",
    "sg:orig_category":"Fitnesscentra",
    "sg:phone":"+31 412 401 081",
    "sg:postcode":"5351 AX",
    "sg:province":"North Brabant",
    "wof:name":"Sportcentrum H. Van De Coevering",
    "wof:placetype":"venue"
},
  "geometry": {"coordinates":[5.579095,51.775455],"type":"Point"}
}