{
  "type": "Feature",
  "properties": {
    "addr:full":"Plevierweide 2 Houten Utrecht 3993 EP",
    "addr:housenumber":"2",
    "addr:postcode":"3993 ep",
    "addr:street":"Plevierweide",
    "iso:country":"NL",
    "sg:address":"Plevierweide 2",
    "sg:city":"Houten",
    "sg:orig_category":"Fotostudio'S And Fotografen",
    "sg:phone":"+31 30 637 5637",
    "sg:postcode":"3993 EP",
    "sg:province":"Utrecht",
    "wof:name":"Photo Write",
    "wof:placetype":"venue"
},
  "geometry": {"coordinates":[5.172883,52.038425],"type":"Point"}
}