{
  "type": "Feature",
  "properties": {
    "addr:full":"Ryksstrwg 221 Beek Ubbergen Gelderland 6573 CS",
    "addr:housenumber":"221",
    "addr:postcode":"6573 cs",
    "iso:country":"NL",
    "sg:address":"Ryksstrwg 221",
    "sg:city":"Beek Ubbergen",
    "sg:orig_category":"Fotoreportages",
    "sg:phone":"+31 6 53106807",
    "sg:postcode":"6573 CS",
    "sg:province":"Gelderland",
    "sg:website":"http://www.eyes-on-photography.nl",
    "wof:name":"Eyes On Photography",
    "wof:placetype":"venue"
},
  "geometry": {"coordinates":[5.92779,51.831219],"type":"Point"}
}