{
  "type": "Feature",
  "properties": {
    "addr:full":"M Louiseln 20 Lopik Utrecht 3411 XT",
    "addr:housenumber":"20",
    "addr:postcode":"3411 xt",
    "iso:country":"NL",
    "sg:address":"M Louiseln 20",
    "sg:city":"Lopik",
    "sg:orig_category":"Administratie- En Boekhoudkantoren",
    "sg:phone":"+31 348 554 028",
    "sg:postcode":"3411 XT",
    "sg:province":"Utrecht",
    "wof:name":"Abe",
    "wof:placetype":"venue"
},
  "geometry": {"coordinates":[4.945286,51.97467],"type":"Point"}
}