{
  "type": "Feature",
  "properties": {
    "addr:full":"Melkweg 44 Eindhoven Noord-Brabant 5642 CT",
    "addr:housenumber":"44",
    "addr:postcode":"5642 ct",
    "addr:street":"Melkweg",
    "iso:country":"NL",
    "sg:address":"Melkweg 44",
    "sg:city":"Eindhoven",
    "sg:orig_category":"Gespecialiseerde Bouw",
    "sg:phone":"+31 40 281 2558",
    "sg:postcode":"5642 CT",
    "sg:province":"Noord-Brabant",
    "wof:name":"E Braat",
    "wof:placetype":"venue"
},
  "geometry": {"coordinates":[5.506263,51.442612],"type":"Point"}
}