{
  "type": "Feature",
  "properties": {
    "addr:full":"Steniawg 4 Zeist Utrecht 3702 AG",
    "addr:housenumber":"4",
    "addr:postcode":"3702",
    "addr:street":"Steniawg",
    "iso:country":"NL",
    "sg:address":"Steniawg 4",
    "sg:city":"Zeist",
    "sg:orig_category":"Adviesbureaus Bedrijfsorganisatie",
    "sg:phone":"+31 30 692 4124",
    "sg:postcode":"3702 AG",
    "sg:province":"Utrecht",
    "wof:name":"Rothkrans",
    "wof:placetype":"venue"
},
  "geometry": {"coordinates":[5.234562,52.085762],"type":"Point"}
}