{
  "type": "Feature",
  "properties": {
    "addr:full":"Oostmyzerdk 9 Schermerhorn North Holland 1636 WC",
    "addr:housenumber":"9",
    "addr:postcode":"1636 wc",
    "addr:street":"Oostmyzerdk",
    "iso:country":"NL",
    "sg:address":"Oostmyzerdk 9",
    "sg:city":"Schermerhorn",
    "sg:orig_category":"Wolgroothandel",
    "sg:phone":"+31 72 502 2367",
    "sg:postcode":"1636 WC",
    "sg:province":"North Holland",
    "wof:name":"Hermes, Fa J P",
    "wof:placetype":"venue"
},
  "geometry": {"coordinates":[4.8983969688,52.6016845703],"type":"Point"}
}