{
  "type": "Feature",
  "properties": {
    "addr:full":"Obrechtln 6 S Gravenzande Zuid-Holland 2692 BV",
    "addr:housenumber":"6;gravenzande",
    "addr:postcode":"2692 bv",
    "addr:street":"Obrechtln;S",
    "iso:country":"NL",
    "sg:address":"Obrechtln 6",
    "sg:city":"S Gravenzande",
    "sg:orig_category":"Tegelwerken",
    "sg:phone":"+31 174 421 041",
    "sg:postcode":"2692 BV",
    "sg:province":"Zuid-Holland",
    "sg:website":"http://www.westgaaginterbouw.nl",
    "wof:name":"Westgaag Interbouw",
    "wof:placetype":"venue"
},
  "geometry": {"coordinates":[4.157512,52.00135],"type":"Point"}
}