{
  "type": "Feature",
  "properties": {
    "addr:full":"West Kinderdijk 247 Alblasserdam South Holland 2953 XS",
    "addr:housenumber":"247",
    "addr:postcode":"2953 xs",
    "addr:street":"West Kinderdijk",
    "iso:country":"NL",
    "sg:address":"West Kinderdijk 247",
    "sg:city":"Alblasserdam",
    "sg:orig_category":"Voeding, Dranken And Tabak Gh",
    "sg:phone":"+31 78 691 3371",
    "sg:postcode":"2953 XS",
    "sg:province":"South Holland",
    "wof:name":"J.C. Slagboom",
    "wof:placetype":"venue"
},
  "geometry": {"coordinates":[4.641518,51.868587],"type":"Point"}
}