{
  "type": "Feature",
  "properties": {
    "addr:full":"Vivaldilaan 183 Schiedam Zuid-Holland 3122 HZ",
    "addr:housenumber":"183",
    "addr:postcode":"3122 hz",
    "addr:street":"Vivaldilaan",
    "iso:country":"NL",
    "sg:address":"Vivaldilaan 183",
    "sg:city":"Schiedam",
    "sg:orig_category":"Artsen And Specialisten",
    "sg:phone":"+31 10 471 2265",
    "sg:postcode":"3122 HZ",
    "sg:province":"Zuid-Holland",
    "wof:name":"Huisartsenpraktijk E.M.S. Klein",
    "wof:placetype":"venue"
},
  "geometry": {"coordinates":[4.368338,51.93325],"type":"Point"}
}