{
  "type": "Feature",
  "properties": {
    "addr:full":"Hoofdstraat 165 Emmen Drenthe 7811 EM",
    "addr:housenumber":"165",
    "addr:postcode":"7811 em",
    "addr:street":"Hoofdstraat",
    "iso:country":"NL",
    "sg:address":"Hoofdstraat 165",
    "sg:city":"Emmen",
    "sg:orig_category":"Werving And Selectie Van Tijdelijk Personeel And Uitzendkantoren",
    "sg:phone":"+31 591 649 454",
    "sg:postcode":"7811 EM",
    "sg:province":"Drenthe",
    "wof:name":"Content",
    "wof:placetype":"venue"
},
  "geometry": {"coordinates":[6.8946390152,52.7891540527],"type":"Point"}
}