{
  "type": "Feature",
  "properties": {
    "addr:full":"Goldkampstraat 11 Dalfsen Overijssel 7722 RN",
    "addr:housenumber":"11",
    "addr:postcode":"7722 rn",
    "addr:street":"Goldkampstraat",
    "iso:country":"NL",
    "sg:address":"Goldkampstraat 11",
    "sg:city":"Dalfsen",
    "sg:orig_category":"Vers Brood And Banket Fab",
    "sg:phone":"+31 529 431 688",
    "sg:postcode":"7722 RN",
    "sg:province":"Overijssel",
    "wof:name":"Frijling Banket Bv",
    "wof:placetype":"venue"
},
  "geometry": {"coordinates":[6.263241,52.511581],"type":"Point"}
}