{
  "type": "Feature",
  "properties": {
    "addr:full":"Hoofdstraat 33 Hillegom North Holland 2181 EA",
    "addr:housenumber":"33",
    "addr:postcode":"2181 ea",
    "addr:street":"Hoofdstraat",
    "iso:country":"NL",
    "sg:address":"Hoofdstraat 33",
    "sg:city":"Hillegom",
    "sg:orig_category":"Banken And Kredietinstellingen",
    "sg:phone":"+31 252 517 060",
    "sg:postcode":"2181 EA",
    "sg:province":"North Holland",
    "wof:name":"Fortis Bank",
    "wof:placetype":"venue"
},
  "geometry": {"coordinates":[4.580423,52.294304],"type":"Point"}
}