{
  "type": "Feature",
  "properties": {
    "addr:full":"Rijksstraatweg 362 Wassenaar Zuid-Holland 2242 AC",
    "addr:housenumber":"362",
    "addr:postcode":"2242 ac",
    "addr:street":"Rijksstraatweg",
    "iso:country":"NL",
    "sg:address":"Rijksstraatweg 362",
    "sg:city":"Wassenaar",
    "sg:classifiers":[
        {
            "category":"Fast Food",
            "type":"Food & Drink"
        }
    ],
    "sg:phone":"+31 70 511 4799",
    "sg:postcode":"2242 AC",
    "sg:province":"Zuid-Holland",
    "sg:tags":[
        "afhaal",
        "restaurant"
    ],
    "wof:name":"Johnny'S Pizza Place",
    "wof:placetype":"venue"
},
  "geometry": {"coordinates":[4.407152,52.13826],"type":"Point"}
}