{
  "type": "Feature",
  "properties": {
    "addr:full":"Pr Marykeln 15 Maurik Gelderland 4021 EA",
    "addr:housenumber":"15",
    "addr:postcode":"4021 ea",
    "addr:street":"Gelderland",
    "iso:country":"NL",
    "sg:address":"Pr Marykeln 15",
    "sg:city":"Maurik",
    "sg:orig_category":"Banken",
    "sg:phone":"+31 26 479 2000",
    "sg:postcode":"4021 EA",
    "sg:province":"Gelderland",
    "sg:website":"http://www.rabobank.nl",
    "wof:name":"Rabobank",
    "wof:placetype":"venue"
},
  "geometry": {"coordinates":[5.419951,51.962208],"type":"Point"}
}