{
  "type": "Feature",
  "properties": {
    "iso:country":"NL",
    "sg:address":"Merk 23",
    "sg:city":"Workum",
    "sg:orig_category":"Visspeciaalzaken",
    "sg:phone":"+31 515 541 386",
    "sg:postcode":"8711 CM",
    "sg:province":"Provincie Friesland",
    "wof:name":"Firma J Bijlsma & Zn",
    "wof:placetype":"venue"
},
  "geometry": {"coordinates":[5.442933,52.979576],"type":"Point"}
}