{
  "type": "Feature",
  "properties": {
    "addr:full":"Bonegraafseweg 21 Ochten Gelderland 4051 CG",
    "addr:housenumber":"21",
    "addr:postcode":"4051 cg",
    "addr:street":"Bonegraafseweg;Gelderland",
    "iso:country":"NL",
    "sg:address":"Bonegraafseweg 21",
    "sg:city":"Ochten",
    "sg:orig_category":"Auto'S And Voertuigen",
    "sg:phone":"+31 344 641 815",
    "sg:postcode":"4051 CG",
    "sg:province":"Gelderland",
    "wof:name":"A. Van Den Berg",
    "wof:placetype":"venue"
},
  "geometry": {"coordinates":[5.589084,51.916401],"type":"Point"}
}