{
  "type": "Feature",
  "properties": {
    "addr:full":"Margrietln 29 Ede Gld Gelderland 6713 PK",
    "addr:housenumber":"29",
    "addr:postcode":"6713 pk",
    "addr:street":"Margrietln;Gld Gelderland",
    "iso:country":"NL",
    "sg:address":"Margrietln 29",
    "sg:city":"Ede Gld",
    "sg:orig_category":"Verenigingen En Stichtingen",
    "sg:phone":"+31 318 614 935",
    "sg:postcode":"6713 PK",
    "sg:province":"Gelderland",
    "wof:name":"Help Oost-Polen, Sticht",
    "wof:placetype":"venue"
},
  "geometry": {"coordinates":[5.662064,52.035],"type":"Point"}
}