{
  "type": "Feature",
  "properties": {
    "addr:full":"Wagenaarstraat 24 Naaldwijk Zuid-Holland 2671 TZ",
    "addr:housenumber":"24",
    "addr:postcode":"2671 tz",
    "addr:street":"Wagenaarstraat",
    "iso:country":"NL",
    "sg:address":"Wagenaarstraat 24",
    "sg:city":"Naaldwijk",
    "sg:orig_category":"Goederenvervoer Over De Weg",
    "sg:phone":"+31 174 623 298",
    "sg:postcode":"2671 TZ",
    "sg:province":"Zuid-Holland",
    "wof:name":"Kms Japan",
    "wof:placetype":"venue"
},
  "geometry": {"coordinates":[4.215943,51.99305],"type":"Point"}
}