{
  "type": "Feature",
  "properties": {
    "addr:full":"Vlasakker 31 Waddinxveen Zuid-Holland 2743 EZ",
    "addr:housenumber":"31",
    "addr:postcode":"2743 ez",
    "addr:street":"Vlasakker",
    "iso:country":"NL",
    "sg:address":"Vlasakker 31",
    "sg:city":"Waddinxveen",
    "sg:orig_category":"Loodgieterswerk, Verwarming And Sanitaire Installaties",
    "sg:phone":"+31 182 640 809",
    "sg:postcode":"2743 EZ",
    "sg:province":"Zuid-Holland",
    "wof:name":"Hhk Hotel Housekeeping",
    "wof:placetype":"venue"
},
  "geometry": {"coordinates":[4.636276,52.038403],"type":"Point"}
}