{
  "type": "Feature",
  "properties": {
    "addr:full":"C Vd Lindenstr 19 Ryswyk Zh South Holland 2288 EV",
    "addr:housenumber":"19",
    "addr:street":"Ryswyk Zh",
    "iso:country":"NL",
    "sg:address":"C Vd Lindenstr 19",
    "sg:city":"Ryswyk Zh",
    "sg:orig_category":"Kantoorbenodigdheden",
    "sg:phone":"+31 70 395 4299",
    "sg:postcode":"2288 EV",
    "sg:province":"South Holland",
    "sg:website":"http://www.fritsch.nl",
    "wof:name":"Fritsch",
    "wof:placetype":"venue"
},
  "geometry": {"coordinates":[4.3243598938,52.0372505188],"type":"Point"}
}