{
  "type": "Feature",
  "properties": {
    "addr:full":"Haya V Someren-Downerstr 9 Amsterdam Noord-Holland 1067 WP",
    "addr:housenumber":"9",
    "addr:postcode":"1067 wp",
    "addr:street":"Someren-Downerstr",
    "iso:country":"NL",
    "sg:address":"Haya V Someren-Downerstr 9",
    "sg:city":"Amsterdam",
    "sg:orig_category":"Verhuur Diversen",
    "sg:phone":"+31 20 614 7163",
    "sg:postcode":"1067 WP",
    "sg:province":"Noord-Holland",
    "wof:name":"Martens & Snabel",
    "wof:placetype":"venue"
},
  "geometry": {"coordinates":[4.790794,52.382893],"type":"Point"}
}