{
  "type": "Feature",
  "properties": {
    "iso:country":"NL",
    "sg:address":"Mieuwydt 19",
    "sg:city":"Graft",
    "sg:orig_category":"Bejaarden - Verzorgingstehuizen",
    "sg:phone":"+31 299 671 251",
    "sg:postcode":"1484 EE",
    "sg:province":"Noord-Holland",
    "wof:name":"Mieuwijdt, De",
    "wof:placetype":"venue"
},
  "geometry": {"coordinates":[4.831326,52.561199],"type":"Point"}
}