{
  "type": "Feature",
  "properties": {
    "addr:full":"Markt 2 Aalten Gelderland 7121 CS",
    "addr:housenumber":"2",
    "addr:postcode":"7121 cs",
    "addr:street":"Markt;Gelderland",
    "iso:country":"NL",
    "sg:address":"Markt 2",
    "sg:city":"Aalten",
    "sg:orig_category":"Biljart- And Snookerzalen",
    "sg:phone":"+31 543 472 419",
    "sg:postcode":"7121 CS",
    "sg:province":"Gelderland",
    "wof:name":"Firma Stegers",
    "wof:placetype":"venue"
},
  "geometry": {"coordinates":[6.581703,51.927132],"type":"Point"}
}