{
  "type": "Feature",
  "properties": {
    "addr:full":"Eekmolen 16 Delden Overijssel 7491 HN",
    "addr:housenumber":"16",
    "addr:postcode":"7491 hn",
    "addr:street":"Eekmolen",
    "iso:country":"NL",
    "sg:address":"Eekmolen 16",
    "sg:city":"Delden",
    "sg:orig_category":"Adviesbureaus Bedrijfsorganisatie",
    "sg:phone":"+31 74 250 9312",
    "sg:postcode":"7491 HN",
    "sg:province":"Overijssel",
    "wof:name":"High Fidelity",
    "wof:placetype":"venue"
},
  "geometry": {"coordinates":[6.705922,52.263466],"type":"Point"}
}