{
  "type": "Feature",
  "properties": {
    "iso:country":"NL",
    "sg:address":"Middenwg 514",
    "sg:city":"Amsterdam",
    "sg:orig_category":"Glas, Porselein En Aardewerk",
    "sg:phone":"+31 20 665 0661",
    "sg:postcode":"1097 VE",
    "sg:province":"Noord-Holland",
    "wof:name":"Ricardo'S",
    "wof:placetype":"venue"
},
  "geometry": {"coordinates":[4.949824,52.341202],"type":"Point"}
}