{
  "type": "Feature",
  "properties": {
    "addr:full":"Bovenmonde 7 Nieuwegein Utrecht 3434 GS",
    "addr:housenumber":"7",
    "addr:postcode":"3434 gs",
    "addr:street":"Bovenmonde",
    "iso:country":"NL",
    "sg:address":"Bovenmonde 7",
    "sg:city":"Nieuwegein",
    "sg:orig_category":"Open Haarden",
    "sg:phone":"+31 30 608 0004",
    "sg:postcode":"3434 GS",
    "sg:province":"Utrecht",
    "sg:website":"http://www.elbertseopenhaarden.nl",
    "wof:name":"Elbertse Openhaarden",
    "wof:placetype":"venue"
},
  "geometry": {"coordinates":[5.089148,52.004318],"type":"Point"}
}