{
  "type": "Feature",
  "properties": {
    "addr:full":"Fabrieksweg 18 Hollum Friesland 9161 CG",
    "addr:housenumber":"18",
    "addr:postcode":"9161 cg",
    "addr:street":"Fabrieksweg",
    "iso:country":"NL",
    "sg:address":"Fabrieksweg 18",
    "sg:city":"Hollum",
    "sg:orig_category":"Autokeuringen",
    "sg:phone":"+31 519 554 538",
    "sg:postcode":"9161 CG",
    "sg:province":"Friesland",
    "wof:name":"Smederij En Garage Theo Faber",
    "wof:placetype":"venue"
},
  "geometry": {"coordinates":[5.640226,53.443676],"type":"Point"}
}