{
  "type": "Feature",
  "properties": {
    "addr:full":"Brucknerstr 13 Zwolle NL.08 8031 DE",
    "addr:housenumber":"13;8031",
    "addr:street":"Brucknerstr;De",
    "iso:country":"NL",
    "sg:address":"Brucknerstr 13",
    "sg:city":"Zwolle",
    "sg:orig_category":"Adviesbureaus",
    "sg:phone":"+31 38 454 7791",
    "sg:postcode":"8031 DE",
    "sg:province":"NL.08",
    "sg:website":"http://www.petegem.nl",
    "wof:name":"Petegem, J J G Van",
    "wof:placetype":"venue"
},
  "geometry": {"coordinates":[6.092245,52.525681],"type":"Point"}
}