{
  "type": "Feature",
  "properties": {
    "addr:full":"Meerstr 6-8 Hillegom Zuid-Holland 2181 BR",
    "addr:housenumber":"6-8",
    "addr:postcode":"2181 br",
    "addr:street":"Meerstr",
    "iso:country":"NL",
    "sg:address":"Meerstr 6-8",
    "sg:city":"Hillegom",
    "sg:orig_category":"Verf En Lak",
    "sg:phone":"+31 252 515 737",
    "sg:postcode":"2181 BR",
    "sg:province":"Zuid-Holland",
    "wof:name":"Auro",
    "wof:placetype":"venue"
},
  "geometry": {"coordinates":[4.580035,52.292999],"type":"Point"}
}