{
  "type": "Feature",
  "properties": {
    "iso:country":"NL",
    "sg:address":"Architect Berlagelaan 152",
    "sg:city":"'S Gravenhage",
    "sg:orig_category":"Werving And Selectie Van Vast Personeel",
    "sg:phone":"+31 70 404 3162",
    "sg:postcode":"2552 ZG",
    "sg:province":"Zuid-Holland",
    "wof:name":"Halo Jobbing",
    "wof:placetype":"venue"
},
  "geometry": {"coordinates":[4.2545681,52.0585403442],"type":"Point"}
}