{
  "type": "Feature",
  "properties": {
    "addr:full":"A Geertsstraat 20 Olst Overijssel 8121 BL",
    "addr:housenumber":"20",
    "addr:postcode":"8121 bl",
    "addr:street":"A Geertsstraat",
    "iso:country":"NL",
    "sg:address":"A Geertsstraat 20",
    "sg:city":"Olst",
    "sg:orig_category":"Kappers",
    "sg:phone":"+31 570 565 278",
    "sg:postcode":"8121 BL",
    "sg:province":"Overijssel",
    "wof:name":"Art Of Hair",
    "wof:placetype":"venue"
},
  "geometry": {"coordinates":[6.1135411263,52.3374786377],"type":"Point"}
}