{
  "type": "Feature",
  "properties": {
    "iso:country":"NL",
    "sg:address":"Raadhuisplein 81",
    "sg:city":"Krimpen A/D Ijssel",
    "sg:classifiers":[
        {
            "category":"Retail",
            "subcategory":"Photofinishing",
            "type":"Services"
        }
    ],
    "sg:phone":"+31 180 515 954",
    "sg:postcode":"2922 AH",
    "sg:province":"South Holland",
    "sg:tags":[
        "foto",
        "film"
    ],
    "wof:name":"G.J.A. Arkenbout",
    "wof:placetype":"venue"
},
  "geometry": {"coordinates":[4.588399,51.914131],"type":"Point"}
}