{
  "type": "Feature",
  "properties": {
    "addr:full":"Brede Hilledijk 36 Rotterdam South Holland 3072 KG",
    "addr:housenumber":"36",
    "addr:postcode":"3072 kg",
    "addr:street":"Brede Hilledijk",
    "iso:country":"NL",
    "sg:address":"Brede Hilledijk 36",
    "sg:city":"Rotterdam",
    "sg:orig_category":"Werving And Selectie Van Vast Personeel",
    "sg:phone":"+31 10 486 2863",
    "sg:postcode":"3072 KG",
    "sg:province":"South Holland",
    "wof:name":"Stichting Werkbureau Feijenoord",
    "wof:placetype":"venue"
},
  "geometry": {"coordinates":[4.5000119209,51.9031982422],"type":"Point"}
}