{
  "type": "Feature",
  "properties": {
    "addr:full":"De Heurne 9 Hengelo Gld Gelderland 7255 CK",
    "addr:housenumber":"9",
    "addr:postcode":"7255 ck",
    "addr:street":"De Heurne",
    "iso:country":"NL",
    "sg:address":"De Heurne 9",
    "sg:city":"Hengelo Gld",
    "sg:orig_category":"Architecten",
    "sg:phone":"+31 575 463 398",
    "sg:postcode":"7255 CK",
    "sg:province":"Gelderland",
    "wof:name":"Adviesburo Kardol",
    "wof:placetype":"venue"
},
  "geometry": {"coordinates":[6.310447,52.05249],"type":"Point"}
}