{
  "type": "Feature",
  "properties": {
    "addr:full":"Plantagewg 4 Alblasserdam Zuid-Holland 2951 GP",
    "addr:housenumber":"4",
    "addr:postcode":"2951 gp",
    "addr:street":"Plantagewg",
    "iso:country":"NL",
    "sg:address":"Plantagewg 4",
    "sg:city":"Alblasserdam",
    "sg:orig_category":"Poeliers",
    "sg:phone":"+31 78 691 9790",
    "sg:postcode":"2951 GP",
    "sg:province":"Zuid-Holland",
    "wof:name":"Bakker, Jan",
    "wof:placetype":"venue"
},
  "geometry": {"coordinates":[4.660028,51.861874],"type":"Point"}
}