{
  "type": "Feature",
  "properties": {
    "addr:full":"Promenade 4 Breskens Zeeland 4511 RB",
    "addr:housenumber":"4",
    "addr:postcode":"4511 rb",
    "addr:street":"Promenade",
    "iso:country":"NL",
    "sg:address":"Promenade 4",
    "sg:city":"Breskens",
    "sg:classifiers":[
        {
            "category":"Travel",
            "subcategory":"Hotels & Motels",
            "type":"Entertainment"
        }
    ],
    "sg:phone":"+31 117 381 855",
    "sg:postcode":"4511 RB",
    "sg:province":"Zeeland",
    "sg:website":"http://www.milliano.nl",
    "wof:name":"Milliano, De",
    "wof:placetype":"venue"
},
  "geometry": {"coordinates":[3.5525,51.400242],"type":"Point"}
}