{
  "type": "Feature",
  "properties": {
    "addr:full":"Johan Buziaustraat 3 Wageningen Gelderland 6708 NP",
    "addr:housenumber":"3",
    "addr:postcode":"6708 np",
    "addr:street":"Johan Buziaustraat;Gelderland",
    "iso:country":"NL",
    "sg:address":"Johan Buziaustraat 3",
    "sg:city":"Wageningen",
    "sg:orig_category":"Kinderopvang Behalve Thuis",
    "sg:phone":"+31 317 417 924",
    "sg:postcode":"6708 NP",
    "sg:province":"Gelderland",
    "wof:name":"Kinderdagverbijf De Dijkgraaf",
    "wof:placetype":"venue"
},
  "geometry": {"coordinates":[5.653085,51.983795],"type":"Point"}
}