{
  "type": "Feature",
  "properties": {
    "addr:full":"Koningin Wilhelminaplein 2 Amsterdam North Holland 1062 HK",
    "addr:housenumber":"2",
    "addr:postcode":"1062 hk",
    "addr:street":"Koningin Wilhelminaplein",
    "iso:country":"NL",
    "sg:address":"Koningin Wilhelminaplein 2",
    "sg:city":"Amsterdam",
    "sg:classifiers":[
        {
            "category":"Shopping",
            "subcategory":"Clothing, Apparel, & Fashions",
            "type":"Retail Goods"
        }
    ],
    "sg:phone":"+31 20 614 0319",
    "sg:postcode":"1062 HK",
    "sg:province":"North Holland",
    "sg:tags":[
        "ondergoed",
        "lingerie"
    ],
    "wof:name":"Nolte Le Big Bv",
    "wof:placetype":"venue"
},
  "geometry": {"coordinates":[4.840781,52.355427],"type":"Point"}
}