{
  "type": "Feature",
  "properties": {
    "addr:full":"Hoofdweg 98 Damwoude Friesland 9104 BJ",
    "addr:housenumber":"98",
    "addr:postcode":"9104 bj",
    "addr:street":"Hoofdweg",
    "iso:country":"NL",
    "sg:address":"Hoofdweg 98",
    "sg:city":"Damwoude",
    "sg:orig_category":"Autokeuringen",
    "sg:phone":"+31 511 422 483",
    "sg:postcode":"9104 BJ",
    "sg:province":"Friesland",
    "wof:name":"Garage F Feenstra",
    "wof:placetype":"venue"
},
  "geometry": {"coordinates":[5.999172,53.28651],"type":"Point"}
}