{
  "type": "Feature",
  "properties": {
    "iso:country":"NL",
    "sg:address":"Pr Beatrixln 5",
    "sg:city":"Waddinxveen",
    "sg:orig_category":"Adviesbureaus Bedrijfsorganisatie",
    "sg:phone":"+31 182 610 368",
    "sg:postcode":"2741 DE",
    "sg:province":"Zuid-Holland",
    "wof:name":"Lange, De",
    "wof:placetype":"venue"
},
  "geometry": {"coordinates":[4.651831,52.046978],"type":"Point"}
}