{
  "type": "Feature",
  "properties": {
    "addr:full":"Beukenstraat 141 Goes Zeeland 4462 TS",
    "addr:housenumber":"141",
    "addr:postcode":"4462 ts",
    "addr:street":"Beukenstraat",
    "iso:country":"NL",
    "sg:address":"Beukenstraat 141",
    "sg:city":"Goes",
    "sg:orig_category":"Onderhoud And Reparatie Kantoorapparatuur",
    "sg:phone":"+31 113 218 454",
    "sg:postcode":"4462 TS",
    "sg:province":"Zeeland",
    "wof:name":"De Wit",
    "wof:placetype":"venue"
},
  "geometry": {"coordinates":[-83.914169,39.768833],"type":"Point"}
}