{
  "type": "Feature",
  "properties": {
    "addr:full":"Hucht 16 Tiel Gelderland 4001 NK",
    "addr:housenumber":"16",
    "addr:postcode":"4001 nk",
    "addr:street":"Hucht;Gelderland",
    "iso:country":"NL",
    "sg:address":"Hucht 16",
    "sg:city":"Tiel",
    "sg:orig_category":"Grafisch Ontwerpers",
    "sg:phone":"+31 344 635 460",
    "sg:postcode":"4001 NK",
    "sg:province":"Gelderland",
    "wof:name":"Day By Day",
    "wof:placetype":"venue"
},
  "geometry": {"coordinates":[5.435299,51.884506],"type":"Point"}
}