{
  "type": "Feature",
  "properties": {
    "addr:full":"Hoorn 35 Ede Gld Gelderland 6713 KR",
    "addr:housenumber":"35",
    "addr:postcode":"6713 kr",
    "addr:street":"Hoorn;Gld Gelderland",
    "iso:country":"NL",
    "sg:address":"Hoorn 35",
    "sg:city":"Ede Gld",
    "sg:orig_category":"Diverse Grafische Activiteiten",
    "sg:phone":"+31 318 630 890",
    "sg:postcode":"6713 KR",
    "sg:province":"Gelderland",
    "wof:name":"Printing Verweij",
    "wof:placetype":"venue"
},
  "geometry": {"coordinates":[5.651476,52.034004],"type":"Point"}
}