{
  "type": "Feature",
  "properties": {
    "addr:full":"Huningawg 1 Oostwold Scheemda Groningen 9682 PA",
    "addr:housenumber":"1",
    "addr:postcode":"9682 pa",
    "addr:street":"Huningawg",
    "iso:country":"NL",
    "sg:address":"Huningawg 1",
    "sg:city":"Oostwold Scheemda",
    "sg:orig_category":"Artsen - Huisartsen",
    "sg:phone":"+31 597 551 288",
    "sg:postcode":"9682 PA",
    "sg:province":"Groningen",
    "wof:name":"Speelman, W",
    "wof:placetype":"venue"
},
  "geometry": {"coordinates":[7.041896,53.201794],"type":"Point"}
}