{
  "type": "Feature",
  "properties": {
    "addr:full":"Visstg 40 Mill Noord-Brabant 5451 NK",
    "addr:housenumber":"40",
    "addr:postcode":"5451 nk",
    "addr:street":"Visstg",
    "iso:country":"NL",
    "sg:address":"Visstg 40",
    "sg:city":"Mill",
    "sg:orig_category":"Adviesbureaus",
    "sg:phone":"+31 485 451 896",
    "sg:postcode":"5451 NK",
    "sg:province":"Noord-Brabant",
    "wof:name":"Schaaf",
    "wof:placetype":"venue"
},
  "geometry": {"coordinates":[-99.35438499999999,40.920727],"type":"Point"}
}