{
  "type": "Feature",
  "properties": {
    "addr:full":"Danielsstr 17 Landgraaf Limburg 6372 KE",
    "addr:housenumber":"17",
    "addr:postcode":"6372 ke",
    "addr:street":"Danielsstr",
    "iso:country":"NL",
    "sg:address":"Danielsstr 17",
    "sg:city":"Landgraaf",
    "sg:orig_category":"Organisatiebureaus",
    "sg:phone":"+31 45 533 0057",
    "sg:postcode":"6372 KE",
    "sg:province":"Limburg",
    "wof:name":"Service Gilde Landgraaf, Sticht",
    "wof:placetype":"venue"
},
  "geometry": {"coordinates":[6.0145578384,50.8918800354],"type":"Point"}
}