{
  "type": "Feature",
  "properties": {
    "addr:full":"Ceramstr 18 Tilburg Noord-Brabant 5013 BB",
    "addr:housenumber":"18",
    "addr:postcode":"5013 bb",
    "addr:street":"Ceramstr",
    "iso:country":"NL",
    "sg:address":"Ceramstr 18",
    "sg:city":"Tilburg",
    "sg:orig_category":"Meubelen",
    "sg:phone":"+31 13 543 3473",
    "sg:postcode":"5013 BB",
    "sg:province":"Noord-Brabant",
    "wof:name":"Eras",
    "wof:placetype":"venue"
},
  "geometry": {"coordinates":[5.101971,51.564209],"type":"Point"}
}