{
  "type": "Feature",
  "properties": {
    "iso:country":"NL",
    "sg:address":"Kleine Woerdlaan 19",
    "sg:city":"Naaldwijk",
    "sg:orig_category":"Discountwinkels",
    "sg:phone":"+31 174 641 111",
    "sg:postcode":"2671 CA",
    "sg:province":"Zuid-Holland",
    "wof:name":"Dump De Kleine Woerd",
    "wof:placetype":"venue"
},
  "geometry": {"coordinates":[4.207611,51.995792],"type":"Point"}
}