{
  "type": "Feature",
  "properties": {
    "addr:full":"Kleine Woerdlaan 19 Naaldwijk Zuid-Holland 2671 CA",
    "addr:housenumber":"19",
    "addr:postcode":"2671 ca",
    "addr:street":"Kleine Woerdlaan",
    "iso:country":"NL",
    "sg:address":"Kleine Woerdlaan 19",
    "sg:city":"Naaldwijk",
    "sg:orig_category":"Discountwinkels",
    "sg:phone":"+31 174 641 111",
    "sg:postcode":"2671 CA",
    "sg:province":"Zuid-Holland",
    "wof:name":"Dump De Kleine Woerd",
    "wof:placetype":"venue"
},
  "geometry": {"coordinates":[4.207611,51.995792],"type":"Point"}
}