{
  "type": "Feature",
  "properties": {
    "addr:full":"Malusdreef 13 Vlaardingen Zuid-Holland 3137 BV",
    "addr:housenumber":"13",
    "addr:postcode":"3137 bv",
    "addr:street":"Malusdreef",
    "iso:country":"NL",
    "sg:address":"Malusdreef 13",
    "sg:city":"Vlaardingen",
    "sg:orig_category":"Projectontwikkeling",
    "sg:phone":"+31 6 53224856",
    "sg:postcode":"3137 BV",
    "sg:province":"Zuid-Holland",
    "wof:name":"Hermaion Bv",
    "wof:placetype":"venue"
},
  "geometry": {"coordinates":[4.347559,51.939251],"type":"Point"}
}