{
  "type": "Feature",
  "properties": {
    "addr:full":"Gildeplein 66 Purmerend Noord-Holland 1445 BM",
    "addr:housenumber":"66",
    "addr:postcode":"1445 bm",
    "addr:street":"Gildeplein",
    "iso:country":"NL",
    "sg:address":"Gildeplein 66",
    "sg:city":"Purmerend",
    "sg:classifiers":[
        {
            "category":"Fast Food",
            "type":"Food & Drink"
        }
    ],
    "sg:phone":"+31 299 644 388",
    "sg:postcode":"1445 BM",
    "sg:province":"Noord-Holland",
    "sg:tags":[
        "afhaal",
        "restaurant"
    ],
    "wof:name":"Azi\u00eb Chinees Restaurant",
    "wof:placetype":"venue"
},
  "geometry": {"coordinates":[4.985629,52.505898],"type":"Point"}
}