{
  "type": "Feature",
  "properties": {
    "addr:full":"Wismarwg 23 Groningen Groningen 9723 HC",
    "addr:housenumber":"23",
    "addr:postcode":"9723 hc",
    "addr:street":"Wismarwg",
    "iso:country":"NL",
    "sg:address":"Wismarwg 23",
    "sg:city":"Groningen",
    "sg:orig_category":"Verhuizingen",
    "sg:phone":"+31 50 541 8418",
    "sg:postcode":"9723 HC",
    "sg:province":"Groningen",
    "wof:name":"Koot Inventra",
    "wof:placetype":"venue"
},
  "geometry": {"coordinates":[6.609952,53.219528],"type":"Point"}
}