{
  "type": "Feature",
  "properties": {
    "addr:full":"2E Loswal 14 Hilversum North Holland 1216 BC",
    "addr:housenumber":"14",
    "addr:postcode":"1216 bc",
    "addr:street":"2E Loswal",
    "iso:country":"NL",
    "sg:address":"2E Loswal 14",
    "sg:city":"Hilversum",
    "sg:orig_category":"Keukens",
    "sg:phone":"+31 35 640 0000",
    "sg:postcode":"1216 BC",
    "sg:province":"North Holland",
    "sg:website":"http://www.gooiskeukencentrum.nl",
    "wof:name":"Goois Keukencentrum",
    "wof:placetype":"venue"
},
  "geometry": {"coordinates":[5.146527,52.22282],"type":"Point"}
}