{
  "type": "Feature",
  "properties": {
    "addr:full":"Voorstr 89 Vianen Zh Utrecht 4132 AP",
    "addr:housenumber":"89",
    "addr:postcode":"zh;4132 ap",
    "addr:street":"Voorstr",
    "iso:country":"NL",
    "sg:address":"Voorstr 89",
    "sg:city":"Vianen Zh",
    "sg:orig_category":"Kaas",
    "sg:phone":"+31 347 377 126",
    "sg:postcode":"4132 AP",
    "sg:province":"Utrecht",
    "wof:name":"Viaanse Kaashuis, Het",
    "wof:placetype":"venue"
},
  "geometry": {"coordinates":[5.0926771164,51.9930114746],"type":"Point"}
}