{
  "type": "Feature",
  "properties": {
    "iso:country":"NL",
    "sg:address":"Djambistraat 17",
    "sg:city":"Amsterdam",
    "sg:orig_category":"Algemene Werktuigbouw",
    "sg:phone":"+31 20 692 3121",
    "sg:postcode":"1094 AW",
    "sg:province":"Noord-Holland",
    "wof:name":"S R Krook",
    "wof:placetype":"venue"
},
  "geometry": {"coordinates":[4.938197,52.365166],"type":"Point"}
}