{
  "type": "Feature",
  "properties": {
    "addr:full":"Sluispad 37 Burgh Haamstede Zeeland 4328 BK",
    "addr:housenumber":"37",
    "addr:postcode":"4328 bk",
    "addr:street":"Sluispad;Haamstede",
    "iso:country":"NL",
    "sg:address":"Sluispad 37",
    "sg:city":"Burgh Haamstede",
    "sg:orig_category":"Diverse Bedrijfsinstallaties Gh",
    "sg:phone":"+31 111 653 165",
    "sg:postcode":"4328 BK",
    "sg:province":"Zeeland",
    "wof:name":"Vof A.D. En D.H. Den Boer",
    "wof:placetype":"venue"
},
  "geometry": {"coordinates":[3.743255,51.694939],"type":"Point"}
}