{
  "type": "Feature",
  "properties": {
    "addr:full":"Bramenberg 7 Eemnes Utrecht 3755 BT",
    "addr:housenumber":"7",
    "addr:postcode":"3755 bt",
    "addr:street":"Bramenberg",
    "iso:country":"NL",
    "sg:address":"Bramenberg 7",
    "sg:city":"Eemnes",
    "sg:orig_category":"Horecabenodigdheden",
    "sg:phone":"+31 35 538 4176",
    "sg:postcode":"3755 BT",
    "sg:province":"Utrecht",
    "sg:website":"http://www.perier.nl",
    "wof:name":"Perier Bv",
    "wof:placetype":"venue"
},
  "geometry": {"coordinates":[5.249539,52.249058],"type":"Point"}
}