{
  "type": "Feature",
  "properties": {
    "addr:full":"D Dekkerln 206 Papendrecht Zuid-Holland 3351 CJ",
    "addr:housenumber":"206",
    "addr:postcode":"papendrecht;3351 cj",
    "iso:country":"NL",
    "sg:address":"D Dekkerln 206",
    "sg:city":"Papendrecht",
    "sg:orig_category":"Kunststoffen - Fabrieken En Groothandel",
    "sg:phone":"+31 78 641 0313",
    "sg:postcode":"3351 CJ",
    "sg:province":"Zuid-Holland",
    "wof:name":"Rebolit Bv",
    "wof:placetype":"venue"
},
  "geometry": {"coordinates":[4.683685,51.826294],"type":"Point"}
}