{
  "type": "Feature",
  "properties": {
    "addr:full":"Ludgerstraat 47 Aalten Gelderland 7121 EG",
    "addr:housenumber":"47",
    "addr:postcode":"7121 eg",
    "addr:street":"Ludgerstraat;Gelderland",
    "iso:country":"NL",
    "sg:address":"Ludgerstraat 47",
    "sg:city":"Aalten",
    "sg:orig_category":"Vertaal- And Tolkenbureaus",
    "sg:phone":"+31 543 472 057",
    "sg:postcode":"7121 EG",
    "sg:province":"Gelderland",
    "wof:name":"W.F. Tolkamp",
    "wof:placetype":"venue"
},
  "geometry": {"coordinates":[6.58596,51.922714],"type":"Point"}
}