{
  "type": "Feature",
  "properties": {
    "addr:full":"Boerenburgerweg 11 Noordwijk Zh South Holland 2201 PM",
    "addr:housenumber":"11",
    "addr:postcode":"zh;2201 pm",
    "addr:street":"Boerenburgerweg",
    "iso:country":"NL",
    "sg:address":"Boerenburgerweg 11",
    "sg:city":"Noordwijk Zh",
    "sg:orig_category":"Boekhouders",
    "sg:phone":"+31 71 361 3756",
    "sg:postcode":"2201 PM",
    "sg:province":"South Holland",
    "wof:name":"Heemskerk Interim Management",
    "wof:placetype":"venue"
},
  "geometry": {"coordinates":[4.447949,52.238194],"type":"Point"}
}