{
  "type": "Feature",
  "properties": {
    "addr:full":"Piet Heinstraat 11 Zutphen Gelderland 7204 JN",
    "addr:housenumber":"11",
    "addr:postcode":"7204 jn",
    "addr:street":"Piet Heinstraat;Gelderland",
    "iso:country":"NL",
    "sg:address":"Piet Heinstraat 11",
    "sg:city":"Zutphen",
    "sg:orig_category":"Banken And Kredietinstellingen",
    "sg:phone":"+31 575 591 700",
    "sg:postcode":"7204 JN",
    "sg:province":"Gelderland",
    "wof:name":"Rabobank",
    "wof:placetype":"venue"
},
  "geometry": {"coordinates":[6.218603,52.135735],"type":"Point"}
}