{
  "type": "Feature",
  "properties": {
    "addr:full":"Pr Margrietln 15 Bathmen NL.08 7437 VD",
    "addr:housenumber":"15;nl.08",
    "addr:postcode":"7437 vd",
    "iso:country":"NL",
    "sg:address":"Pr Margrietln 15",
    "sg:city":"Bathmen",
    "sg:orig_category":"Begrafenisverzorging",
    "sg:phone":"+31 570 542 763",
    "sg:postcode":"7437 VD",
    "sg:province":"NL.08",
    "wof:name":"Vredehof",
    "wof:placetype":"venue"
},
  "geometry": {"coordinates":[6.297486,52.250641],"type":"Point"}
}