{
  "type": "Feature",
  "properties": {
    "addr:full":"Gruttersdijk 58 Utrecht Utrecht 3514 BJ",
    "addr:housenumber":"58",
    "addr:postcode":"3514 bj",
    "addr:street":"Gruttersdijk",
    "iso:country":"NL",
    "sg:address":"Gruttersdijk 58",
    "sg:city":"Utrecht",
    "sg:orig_category":"Loodgieterswerk, Verwarming And Sanitaire Installaties",
    "sg:phone":"+31 30 272 2112",
    "sg:postcode":"3514 BJ",
    "sg:province":"Utrecht",
    "wof:name":"Veenis R.V.",
    "wof:placetype":"venue"
},
  "geometry": {"coordinates":[5.114626,52.09964],"type":"Point"}
}