{
  "type": "Feature",
  "properties": {
    "addr:full":"Keyserswey 7 Noordwyk Zh Zuid-Holland 2201 CW",
    "addr:housenumber":"7",
    "addr:postcode":"2201 cw",
    "addr:street":"Keyserswey",
    "iso:country":"NL",
    "sg:address":"Keyserswey 7",
    "sg:city":"Noordwyk Zh",
    "sg:orig_category":"Autoschade- Herstelbedrijven",
    "sg:phone":"+31 71 362 2622",
    "sg:postcode":"2201 CW",
    "sg:province":"Zuid-Holland",
    "sg:website":"http://www.autoschadevanderniet.nl",
    "wof:name":"Niet, Van Der",
    "wof:placetype":"venue"
},
  "geometry": {"coordinates":[4.447704,52.234268],"type":"Point"}
}