{
  "type": "Feature",
  "properties": {
    "iso:country":"NL",
    "sg:address":"Hillekensacker 1719",
    "sg:city":"Nijmegen",
    "sg:orig_category":"Reclamebureaus",
    "sg:phone":"+31 24 373 0482",
    "sg:postcode":"6546 KR",
    "sg:province":"Gelderland",
    "wof:name":"Verdijk Design Studio",
    "wof:placetype":"venue"
},
  "geometry": {"coordinates":[5.777914,51.837528],"type":"Point"}
}