{
  "type": "Feature",
  "properties": {
    "iso:country":"NL",
    "sg:address":"Kerkplein 5",
    "sg:city":"Kockengen",
    "sg:orig_category":"Boekhouders",
    "sg:phone":"+31 346 241 242",
    "sg:postcode":"3628 AE",
    "sg:province":"Utrecht",
    "wof:name":"Administratie Kantoor C.P. De Hoop",
    "wof:placetype":"venue"
},
  "geometry": {"coordinates":[4.947086,52.148205],"type":"Point"}
}