{
  "type": "Feature",
  "properties": {
    "iso:country":"NL",
    "sg:address":"Markt 1",
    "sg:city":"Veenendaal",
    "sg:orig_category":"Banken",
    "sg:phone":"+31 318 566 611",
    "sg:postcode":"3901 DM",
    "sg:province":"Utrecht",
    "sg:website":"http://www.sns.nl",
    "wof:name":"Sns",
    "wof:placetype":"venue"
},
  "geometry": {"coordinates":[5.554707,52.02581],"type":"Point"}
}