{
  "type": "Feature",
  "properties": {
    "addr:full":"Zandbergstr 11 Valkenswaard Noord-Brabant 5555 LA",
    "addr:housenumber":"11",
    "addr:postcode":"5555 la",
    "addr:street":"Zandbergstr",
    "iso:country":"NL",
    "sg:address":"Zandbergstr 11",
    "sg:city":"Valkenswaard",
    "sg:orig_category":"Schoenen",
    "sg:phone":"+31 40 204 1982",
    "sg:postcode":"5555 LA",
    "sg:province":"Noord-Brabant",
    "wof:name":"Cox Voet- En Schoencomfort",
    "wof:placetype":"venue"
},
  "geometry": {"coordinates":[5.471055,51.346401],"type":"Point"}
}