{
  "type": "Feature",
  "properties": {
    "addr:full":"Kantershof 201 Amsterdam Zuidoost North Holland 1104 GK",
    "addr:housenumber":"201",
    "addr:postcode":"1104 gk",
    "addr:street":"Kantershof",
    "iso:country":"NL",
    "sg:address":"Kantershof 201",
    "sg:city":"Amsterdam Zuidoost",
    "sg:orig_category":"Kantoormachines - Reparatie En Onderhoud",
    "sg:phone":"+31 20 699 3146",
    "sg:postcode":"1104 GK",
    "sg:province":"North Holland",
    "sg:website":"http://www.olympia.demon.nl",
    "wof:name":"Sbm Olympia",
    "wof:placetype":"venue"
},
  "geometry": {"coordinates":[4.989180088,52.3206977844],"type":"Point"}
}