{
  "type": "Feature",
  "properties": {
    "iso:country":"NL",
    "sg:address":"A Krytsstr 42",
    "sg:city":"Diemen",
    "sg:classifiers":[
        {
            "category":"Personal",
            "subcategory":"Nail Salon",
            "type":"Services"
        }
    ],
    "sg:phone":"+31 20 695 2592",
    "sg:postcode":"1111 AM",
    "sg:province":"Noord-Holland",
    "sg:tags":[
        "pedicure"
    ],
    "wof:name":"Broekhof, J",
    "wof:placetype":"venue"
},
  "geometry": {"coordinates":[4.956202,52.341122],"type":"Point"}
}