{
  "type": "Feature",
  "properties": {
    "addr:full":"Stroet 35 St Maarten Noord-Holland 1744 GJ",
    "addr:housenumber":"35",
    "addr:postcode":"1744 gj",
    "addr:street":"Stroet;St Maarten Noord-Holland",
    "iso:country":"NL",
    "sg:address":"Stroet 35",
    "sg:city":"St Maarten",
    "sg:orig_category":"Geluidsinstallaties - Verhuur",
    "sg:phone":"+31 224 552 148",
    "sg:postcode":"1744 GJ",
    "sg:province":"Noord-Holland",
    "wof:name":"Sound Pact",
    "wof:placetype":"venue"
},
  "geometry": {"coordinates":[4.755025,52.757648],"type":"Point"}
}