{
  "type": "Feature",
  "properties": {
    "addr:full":"Meester Dr Froweinweg 27 Eys Limburg 6287 CA",
    "addr:housenumber":"27",
    "addr:postcode":"6287 ca",
    "addr:street":"Meester Dr Froweinweg",
    "iso:country":"NL",
    "sg:address":"Meester Dr Froweinweg 27",
    "sg:city":"Eys",
    "sg:orig_category":"Bloemen And Planten",
    "sg:phone":"+31 43 451 1345",
    "sg:postcode":"6287 CA",
    "sg:province":"Limburg",
    "wof:name":"Eeser Blumpke",
    "wof:placetype":"venue"
},
  "geometry": {"coordinates":[5.947388,50.824883],"type":"Point"}
}