{
  "type": "Feature",
  "properties": {
    "addr:full":"Groningenlaan 13 Son Noord-Brabant 5691 KH",
    "addr:housenumber":"13",
    "addr:postcode":"5691 kh",
    "addr:street":"Groningenlaan",
    "iso:country":"NL",
    "sg:address":"Groningenlaan 13",
    "sg:city":"Son",
    "sg:orig_category":"Hypotheken And Hypotheekbanken",
    "sg:phone":"+31 499 476 278",
    "sg:postcode":"5691 KH",
    "sg:province":"Noord-Brabant",
    "wof:name":"A. Platje",
    "wof:placetype":"venue"
},
  "geometry": {"coordinates":[-101.937622,35.189621],"type":"Point"}
}