{
  "type": "Feature",
  "properties": {
    "iso:country":"NL",
    "sg:address":"Drift 3",
    "sg:city":"Utrecht",
    "sg:orig_category":"Organisaties And Verenigingen",
    "sg:phone":"+31 30 232 8810",
    "sg:postcode":"3512 BP",
    "sg:province":"Utrecht",
    "wof:name":"Nederlandse Federatie Van Naturistenverenigingen",
    "wof:placetype":"venue"
},
  "geometry": {"coordinates":[5.1233391762,52.0928955078],"type":"Point"}
}