{
  "type": "Feature",
  "properties": {
    "addr:full":"Boterstraat 28 Wageningen Gelderland 6701 CW",
    "addr:housenumber":"28",
    "addr:postcode":"6701 cw",
    "addr:street":"Boterstraat;Gelderland",
    "iso:country":"NL",
    "sg:address":"Boterstraat 28",
    "sg:city":"Wageningen",
    "sg:orig_category":"Architecten",
    "sg:phone":"+31 317 421 088",
    "sg:postcode":"6701 CW",
    "sg:province":"Gelderland",
    "wof:name":"Hydrobiologisch Adviesburo Klink Bv",
    "wof:placetype":"venue"
},
  "geometry": {"coordinates":[5.664443,51.963821],"type":"Point"}
}