{
  "type": "Feature",
  "properties": {
    "addr:full":"Boerestreek 2 Appelscha Friesland 8426 BP",
    "addr:housenumber":"2",
    "addr:postcode":"8426 bp",
    "addr:street":"Boerestreek",
    "iso:country":"NL",
    "sg:address":"Boerestreek 2",
    "sg:city":"Appelscha",
    "sg:classifiers":[
        {
            "category":"Travel",
            "subcategory":"Hotels & Motels",
            "type":"Entertainment"
        }
    ],
    "sg:phone":"+31 516 431 593",
    "sg:postcode":"8426 BP",
    "sg:province":"Friesland",
    "sg:website":"http://www.hotelappelscha.nl",
    "wof:name":"Hotel-Restaurant Appelscha",
    "wof:placetype":"venue"
},
  "geometry": {"coordinates":[6.338649,52.954098],"type":"Point"}
}