{
  "type": "Feature",
  "properties": {
    "addr:full":"De Esdoorns 6 Boekel Noord-Brabant 5427 TK",
    "addr:housenumber":"6",
    "addr:postcode":"5427 tk",
    "addr:street":"De Esdoorns",
    "iso:country":"NL",
    "sg:address":"De Esdoorns 6",
    "sg:city":"Boekel",
    "sg:orig_category":"Autorijscholen",
    "sg:phone":"+31 492 326 032",
    "sg:postcode":"5427 TK",
    "sg:province":"Noord-Brabant",
    "wof:name":"Bie, De",
    "wof:placetype":"venue"
},
  "geometry": {"coordinates":[5.672457,51.597363],"type":"Point"}
}