{
  "type": "Feature",
  "properties": {
    "addr:full":"Grote Hout- Of Koningswg 195 Velsen-Noord Noord-Holland 1951 GP",
    "addr:housenumber":"195",
    "addr:postcode":"1951 gp",
    "addr:street":"Grote Hout Of Koningswg",
    "iso:country":"NL",
    "sg:address":"Grote Hout- Of Koningswg 195",
    "sg:city":"Velsen-Noord",
    "sg:orig_category":"Bedrijfs- And Werkgeversorganisaties",
    "sg:phone":"+31 251 212 852",
    "sg:postcode":"1951 GP",
    "sg:province":"Noord-Holland",
    "wof:name":"Kamer Van Koophandel Amsterdam",
    "wof:placetype":"venue"
},
  "geometry": {"coordinates":[4.636709,52.474331],"type":"Point"}
}