{
  "type": "Feature",
  "properties": {
    "addr:full":"Weerwal 18 Purmerend Noord-Holland 1441 AL",
    "addr:housenumber":"18",
    "addr:postcode":"1441 al",
    "addr:street":"Weerwal",
    "iso:country":"NL",
    "sg:address":"Weerwal 18",
    "sg:city":"Purmerend",
    "sg:classifiers":[
        {
            "category":"Shopping",
            "subcategory":"News",
            "type":"Retail Goods"
        }
    ],
    "sg:phone":"+31 299 429 508",
    "sg:postcode":"1441 AL",
    "sg:province":"Noord-Holland",
    "sg:tags":[
        "maandbladen",
        "en",
        "week-"
    ],
    "wof:name":"Gezinsblad, Het",
    "wof:placetype":"venue"
},
  "geometry": {"coordinates":[4.948141098,52.5101623535],"type":"Point"}
}