{
  "type": "Feature",
  "properties": {
    "addr:full":"Overtoom 522 Amsterdam North Holland 1054 KL",
    "addr:housenumber":"522",
    "addr:postcode":"1054 kl",
    "addr:street":"Overtoom",
    "iso:country":"NL",
    "sg:address":"Overtoom 522",
    "sg:city":"Amsterdam",
    "sg:classifiers":[
        {
            "category":"Personal",
            "subcategory":"Nail Salon",
            "type":"Services"
        }
    ],
    "sg:phone":"+31 20 618 9329",
    "sg:postcode":"1054 KL",
    "sg:province":"North Holland",
    "sg:tags":[
        "pedicure"
    ],
    "wof:name":"Vries, A M De",
    "wof:placetype":"venue"
},
  "geometry": {"coordinates":[4.858751,52.35873],"type":"Point"}
}