{
  "type": "Feature",
  "properties": {
    "addr:full":"A Plesmanstr 2 Barneveld Gelderland 3772 MN",
    "addr:housenumber":"2",
    "addr:postcode":"3772 mn",
    "addr:street":"Gelderland",
    "iso:country":"NL",
    "sg:address":"A Plesmanstr 2",
    "sg:city":"Barneveld",
    "sg:orig_category":"Facilitaire Dienstverlening",
    "sg:phone":"+31 342 405 880",
    "sg:postcode":"3772 MN",
    "sg:province":"Gelderland",
    "sg:website":"http://www.vilico.nl",
    "wof:name":"Vilico Bv",
    "wof:placetype":"venue"
},
  "geometry": {"coordinates":[5.566363,52.126209],"type":"Point"}
}