{
  "type": "Feature",
  "properties": {
    "addr:full":"Hogewg 3 Zuidhorn Groningen 9801 TG",
    "addr:housenumber":"3",
    "addr:postcode":"9801 tg",
    "addr:street":"Hogewg",
    "iso:country":"NL",
    "sg:address":"Hogewg 3",
    "sg:city":"Zuidhorn",
    "sg:orig_category":"Bodemonderzoek",
    "sg:phone":"+31 50 577 9784",
    "sg:postcode":"9801 TG",
    "sg:province":"Groningen",
    "sg:website":"http://www.desteekproef.nl",
    "wof:name":"Steekproef, De",
    "wof:placetype":"venue"
},
  "geometry": {"coordinates":[6.325094,53.284706],"type":"Point"}
}