{
  "type": "Feature",
  "properties": {
    "addr:full":"Sluisplein 16 Anna Paulowna Noord-Holland 1761  B",
    "addr:housenumber":"16;1761 b",
    "addr:street":"Sluisplein",
    "iso:country":"NL",
    "sg:address":"Sluisplein 16",
    "sg:city":"Anna Paulowna",
    "sg:orig_category":"Boekenuitgeverijen",
    "sg:phone":"+31 223 534 573",
    "sg:postcode":"1761  B",
    "sg:province":"Noord-Holland",
    "wof:name":"Bruna",
    "wof:placetype":"venue"
},
  "geometry": {"coordinates":[4.831671,52.861778],"type":"Point"}
}