{
  "type": "Feature",
  "properties": {
    "addr:full":"Naaldaar 10 Zeewolde Flevoland 3892 BN",
    "addr:housenumber":"10",
    "addr:postcode":"3892 bn",
    "addr:street":"Naaldaar;Flevoland",
    "iso:country":"NL",
    "sg:address":"Naaldaar 10",
    "sg:city":"Zeewolde",
    "sg:orig_category":"Organisatiebureaus",
    "sg:phone":"+31 36 522 6622",
    "sg:postcode":"3892 BN",
    "sg:province":"Flevoland",
    "wof:name":"Tency Specials",
    "wof:placetype":"venue"
},
  "geometry": {"coordinates":[5.5441160202,52.325920105],"type":"Point"}
}