{
  "type": "Feature",
  "properties": {
    "addr:full":"Monseigneur Bekkersstr 13 Sambeek Noord-Brabant 5836 BL",
    "addr:housenumber":"13",
    "addr:postcode":"5836 bl",
    "addr:street":"Monseigneur Bekkersstr",
    "iso:country":"NL",
    "sg:address":"Monseigneur Bekkersstr 13",
    "sg:city":"Sambeek",
    "sg:orig_category":"Technische Studies And Onderzoek",
    "sg:phone":"+31 485 521 633",
    "sg:postcode":"5836 BL",
    "sg:province":"Noord-Brabant",
    "wof:name":"Transfer In Progress",
    "wof:placetype":"venue"
},
  "geometry": {"coordinates":[5.968576,51.635105],"type":"Point"}
}