{
  "type": "Feature",
  "properties": {
    "iso:country":"NL",
    "sg:address":"Rembrandtlaan 7",
    "sg:city":"Sint Maartensvlotbrug",
    "sg:orig_category":"Verzekeringen",
    "sg:phone":"+31 224 563 156",
    "sg:postcode":"1753 BH",
    "sg:province":"Ar Rifa\u2019 and Southern Region",
    "wof:name":"G. Wierdsma",
    "wof:placetype":"venue"
},
  "geometry": {"coordinates":[50.5485,26.02475],"type":"Point"}
}