{
  "type": "Feature",
  "properties": {
    "addr:full":"Geraniumhof 4 Beverwyk Noord-Holland 1943 MB",
    "addr:housenumber":"4",
    "addr:postcode":"1943 mb",
    "addr:street":"Geraniumhof",
    "iso:country":"NL",
    "sg:address":"Geraniumhof 4",
    "sg:city":"Beverwyk",
    "sg:orig_category":"Bedrijfsopleidingen",
    "sg:phone":"+31 251 245 766",
    "sg:postcode":"1943 MB",
    "sg:province":"Noord-Holland",
    "sg:website":"http://www.tannash.nl",
    "wof:name":"Tannash",
    "wof:placetype":"venue"
},
  "geometry": {"coordinates":[4.646324,52.491344],"type":"Point"}
}