{
  "type": "Feature",
  "properties": {
    "addr:full":"Liesstraat 100 Breda Noord-Brabant 4838 GT",
    "addr:housenumber":"100",
    "addr:postcode":"4838 gt",
    "addr:street":"Liesstraat",
    "iso:country":"NL",
    "sg:address":"Liesstraat 100",
    "sg:city":"Breda",
    "sg:orig_category":"Pompen And Compressoren Fab",
    "sg:phone":"+31 76 522 0241",
    "sg:postcode":"4838 GT",
    "sg:province":"Noord-Brabant",
    "wof:name":"Ansems Servicedienst",
    "wof:placetype":"venue"
},
  "geometry": {"coordinates":[4.709713,51.571102],"type":"Point"}
}