{
  "type": "Feature",
  "properties": {
    "addr:full":"Antwerpsestraatweg 218 Bergen Op Zoom Noord-Brabant 4624 JJ",
    "addr:housenumber":"218",
    "addr:postcode":"4624 jj",
    "addr:street":"Antwerpsestraatweg",
    "iso:country":"NL",
    "sg:address":"Antwerpsestraatweg 218",
    "sg:city":"Bergen Op Zoom",
    "sg:orig_category":"Fotostudio'S And Fotografen",
    "sg:phone":"+31 164 240 949",
    "sg:postcode":"4624 JJ",
    "sg:province":"Noord-Brabant",
    "wof:name":"Beeldnet",
    "wof:placetype":"venue"
},
  "geometry": {"coordinates":[4.297627,51.482662],"type":"Point"}
}