{
  "type": "Feature",
  "properties": {
    "addr:full":"Monte Cassinostr 32 Doetinchem Gelderland 7002 ES",
    "addr:housenumber":"32",
    "addr:postcode":"7002 es",
    "addr:street":"Gelderland",
    "iso:country":"NL",
    "sg:address":"Monte Cassinostr 32",
    "sg:city":"Doetinchem",
    "sg:orig_category":"Hydrocultuur",
    "sg:phone":"+31 314 345 214",
    "sg:postcode":"7002 ES",
    "sg:province":"Gelderland",
    "wof:name":"Roessink",
    "wof:placetype":"venue"
},
  "geometry": {"coordinates":[6.321667,51.975441],"type":"Point"}
}