{
  "type": "Feature",
  "properties": {
    "iso:country":"NL",
    "sg:address":"Monte Cassinostr 32",
    "sg:city":"Doetinchem",
    "sg:orig_category":"Hydrocultuur",
    "sg:phone":"+31 314 345 214",
    "sg:postcode":"7002 ES",
    "sg:province":"Gelderland",
    "wof:name":"Roessink",
    "wof:placetype":"venue"
},
  "geometry": {"coordinates":[6.321667,51.975441],"type":"Point"}
}