{
  "type": "Feature",
  "properties": {
    "addr:full":"Eikenlaan 19 Middenmeer Noord-Holland 1775 ED",
    "addr:housenumber":"19",
    "addr:postcode":"1775 ed",
    "addr:street":"Eikenlaan",
    "iso:country":"NL",
    "sg:address":"Eikenlaan 19",
    "sg:city":"Middenmeer",
    "sg:orig_category":"Paramedische Behandelingen",
    "sg:phone":"+31 227 501 072",
    "sg:postcode":"1775 ED",
    "sg:province":"Noord-Holland",
    "wof:name":"J. Pieloor",
    "wof:placetype":"venue"
},
  "geometry": {"coordinates":[5.002372,52.806976],"type":"Point"}
}