{
  "type": "Feature",
  "properties": {
    "iso:country":"NL",
    "sg:address":"Binnenhof 5",
    "sg:city":"Amstelveen",
    "sg:classifiers":[
        {
            "category":"Shopping",
            "subcategory":"Gifts & Souvenirs",
            "type":"Retail Goods"
        }
    ],
    "sg:phone":"+31 20 453 4010",
    "sg:postcode":"1181 ZG",
    "sg:province":"North Holland",
    "sg:tags":[
        "geschenken"
    ],
    "wof:name":"Merckx Pen- En Giftshop",
    "wof:placetype":"venue"
},
  "geometry": {"coordinates":[4.862034,52.302464],"type":"Point"}
}