{
  "type": "Feature",
  "properties": {
    "addr:full":"Talmawg 12 Dordrecht Zuid-Holland 3317 RB",
    "addr:housenumber":"12",
    "addr:postcode":"3317 rb",
    "addr:street":"Talmawg",
    "iso:country":"NL",
    "sg:address":"Talmawg 12",
    "sg:city":"Dordrecht",
    "sg:orig_category":"Architecten En Architectenbureaus",
    "sg:phone":"+31 78 618 9334",
    "sg:postcode":"3317 RB",
    "sg:province":"Zuid-Holland",
    "wof:name":"In-Ex Architecten",
    "wof:placetype":"venue"
},
  "geometry": {"coordinates":[4.668005,51.792168],"type":"Point"}
}