{
  "type": "Feature",
  "properties": {
    "addr:full":"Slinge 441 Rotterdam Zuid-Holland 3085 ES",
    "addr:housenumber":"441",
    "addr:postcode":"3085 es",
    "addr:street":"Slinge",
    "iso:country":"NL",
    "sg:address":"Slinge 441",
    "sg:city":"Rotterdam",
    "sg:orig_category":"Fotografische And Optische Artikelen Gh",
    "sg:phone":"+31 10 481 2751",
    "sg:postcode":"3085 ES",
    "sg:province":"Zuid-Holland",
    "wof:name":"Ecu Lens",
    "wof:placetype":"venue"
},
  "geometry": {"coordinates":[4.48649,51.873688],"type":"Point"}
}