{
  "type": "Feature",
  "properties": {
    "iso:country":"NL",
    "sg:address":"Industrieweg 6",
    "sg:city":"Terneuzen",
    "sg:orig_category":"Woningbouwverenigingen",
    "sg:phone":"+31 115 696 255",
    "sg:postcode":"4538 AH",
    "sg:province":"Zeeland",
    "wof:name":"Woningbouwvereniging Terneuzen",
    "wof:placetype":"venue"
},
  "geometry": {"coordinates":[3.8273251057,51.3282318115],"type":"Point"}
}