{
  "type": "Feature",
  "properties": {
    "addr:full":"Koninginneln 105A Apeldoorn Gelderland 7315 BP",
    "addr:housenumber":"105a",
    "addr:postcode":"7315 bp",
    "addr:street":"Gelderland",
    "iso:country":"NL",
    "sg:address":"Koninginneln 105A",
    "sg:city":"Apeldoorn",
    "sg:orig_category":"Kappers",
    "sg:phone":"+31 55 521 4379",
    "sg:postcode":"7315 BP",
    "sg:province":"Gelderland",
    "wof:name":"Piekfijn Haarmode Apeldoorn",
    "wof:placetype":"venue"
},
  "geometry": {"coordinates":[5.957225,52.227081],"type":"Point"}
}