{
  "type": "Feature",
  "properties": {
    "addr:full":"Heezerweg 266 Eindhoven Noord-Brabant 5643 KK",
    "addr:housenumber":"266",
    "addr:postcode":"5643 kk",
    "addr:street":"Heezerweg",
    "iso:country":"NL",
    "sg:address":"Heezerweg 266",
    "sg:city":"Eindhoven",
    "sg:orig_category":"Technische Studies And Onderzoek",
    "sg:phone":"+31 40 213 8085",
    "sg:postcode":"5643 KK",
    "sg:province":"Noord-Brabant",
    "wof:name":"Kbee",
    "wof:placetype":"venue"
},
  "geometry": {"coordinates":[5.49793,51.423824],"type":"Point"}
}