{
  "type": "Feature",
  "properties": {
    "addr:full":"Zuster Van Der Kolkstr 42 Zwolle Overijssel 8017 HV",
    "addr:housenumber":"42",
    "addr:postcode":"8017 hv",
    "addr:street":"Zuster Van Der Kolkstr",
    "iso:country":"NL",
    "sg:address":"Zuster Van Der Kolkstr 42",
    "sg:city":"Zwolle",
    "sg:orig_category":"Public Relationbureaus",
    "sg:phone":"+31 38 465 5807",
    "sg:postcode":"8017 HV",
    "sg:province":"Overijssel",
    "wof:name":"P R Bureau Vice Versa",
    "wof:placetype":"venue"
},
  "geometry": {"coordinates":[6.105665,52.497467],"type":"Point"}
}