{
  "type": "Feature",
  "properties": {
    "addr:full":"Grutterij 14 Amstelveen North Holland 1185 ZV",
    "addr:housenumber":"14",
    "addr:postcode":"1185 zv",
    "addr:street":"Grutterij",
    "iso:country":"NL",
    "sg:address":"Grutterij 14",
    "sg:city":"Amstelveen",
    "sg:orig_category":"Kantoorartikelen",
    "sg:phone":"+31 20 545 7800",
    "sg:postcode":"1185 ZV",
    "sg:province":"North Holland",
    "wof:name":"Markpoint Bv",
    "wof:placetype":"venue"
},
  "geometry": {"coordinates":[4.8341741562,52.2815589905],"type":"Point"}
}