{
  "type": "Feature",
  "properties": {
    "iso:country":"NL",
    "sg:address":"Gr Diederikln 16",
    "sg:city":"Nieuwegein",
    "sg:orig_category":"Honden- En Kattentrimsalons",
    "sg:phone":"+31 30 606 7586",
    "sg:postcode":"3434 ST",
    "sg:province":"Utrecht",
    "wof:name":"Dogstar",
    "wof:placetype":"venue"
},
  "geometry": {"coordinates":[5.092856,52.013367],"type":"Point"}
}