{
  "type": "Feature",
  "properties": {
    "addr:full":"Rozengracht 55Bg Amsterdam Noord-Holland 1016 LS",
    "addr:housenumber":"55bg",
    "addr:postcode":"1016 ls",
    "addr:street":"Rozengracht",
    "iso:country":"NL",
    "sg:address":"Rozengracht 55Bg",
    "sg:city":"Amsterdam",
    "sg:orig_category":"Diverse Grafische Activiteiten",
    "sg:phone":"+31 20 420 4204",
    "sg:postcode":"1016 LS",
    "sg:province":"Noord-Holland",
    "wof:name":"Media Media",
    "wof:placetype":"venue"
},
  "geometry": {"coordinates":[4.881213,52.373375],"type":"Point"}
}