{
  "type": "Feature",
  "properties": {
    "addr:full":"Aletta Jacobsstraat 33 Waalwijk Noord-Brabant 5142 PL",
    "addr:housenumber":"33",
    "addr:postcode":"5142 pl",
    "addr:street":"Aletta Jacobsstraat",
    "iso:country":"NL",
    "sg:address":"Aletta Jacobsstraat 33",
    "sg:city":"Waalwijk",
    "sg:orig_category":"Schoenen Fab",
    "sg:phone":"+31 416 335 722",
    "sg:postcode":"5142 PL",
    "sg:province":"Noord-Brabant",
    "wof:name":"Stikatelier J. Vastre",
    "wof:placetype":"venue"
},
  "geometry": {"coordinates":[5.095753,51.68977],"type":"Point"}
}