{
  "type": "Feature",
  "properties": {
    "addr:full":"Min Aalberseln 39Flat103 Ryswyk Zh Zuid-Holland 2285 EN",
    "addr:postcode":"2285 en",
    "iso:country":"NL",
    "sg:address":"Min Aalberseln 39Flat103",
    "sg:city":"Ryswyk Zh",
    "sg:classifiers":[
        {
            "category":"Wholesale",
            "subcategory":"Petroleum",
            "type":"Manufacturing & Wholesale Goods"
        }
    ],
    "sg:phone":"+31 70 394 4305",
    "sg:postcode":"2285 EN",
    "sg:province":"Zuid-Holland",
    "wof:name":"Houts, Van",
    "wof:placetype":"venue"
},
  "geometry": {"coordinates":[4.32436,52.037251],"type":"Point"}
}