{
  "type": "Feature",
  "properties": {
    "addr:full":"Larenseweg 159 Hilversum North Holland 1221 CL",
    "addr:housenumber":"159",
    "addr:postcode":"1221",
    "addr:street":"Larenseweg",
    "iso:country":"NL",
    "sg:address":"Larenseweg 159",
    "sg:city":"Hilversum",
    "sg:orig_category":"Juridische Dienstverlening",
    "sg:phone":"+31 35 683 1214",
    "sg:postcode":"1221 CL",
    "sg:province":"North Holland",
    "wof:name":"Peermusic Holland Bv",
    "wof:placetype":"venue"
},
  "geometry": {"coordinates":[5.18975,52.232765],"type":"Point"}
}