{
  "type": "Feature",
  "properties": {
    "addr:full":"Bergsngl 299 Rotterdam South Holland 3037 GW",
    "addr:housenumber":"299",
    "addr:postcode":"3037 gw",
    "iso:country":"NL",
    "sg:address":"Bergsngl 299",
    "sg:city":"Rotterdam",
    "sg:orig_category":"Woningbouw- Verenigingen En -Stichtingen",
    "sg:phone":"+31 10 466 8208",
    "sg:postcode":"3037 GW",
    "sg:province":"South Holland",
    "wof:name":"Woongoed Rotterdam",
    "wof:placetype":"venue"
},
  "geometry": {"coordinates":[4.4741601944,51.9370384216],"type":"Point"}
}