{
  "type": "Feature",
  "properties": {
    "addr:full":"Korte Hofstraat 5 Zutphen Gelderland 7201 KH",
    "addr:housenumber":"5",
    "addr:postcode":"7201 kh",
    "addr:street":"Korte Hofstraat;Gelderland",
    "iso:country":"NL",
    "sg:address":"Korte Hofstraat 5",
    "sg:city":"Zutphen",
    "sg:orig_category":"Opticiens",
    "sg:phone":"+31 575 512 202",
    "sg:postcode":"7201 KH",
    "sg:province":"Gelderland",
    "wof:name":"Reveillon",
    "wof:placetype":"venue"
},
  "geometry": {"coordinates":[6.1950550079,52.1419258118],"type":"Point"}
}