{
  "type": "Feature",
  "properties": {
    "addr:full":"Runneboom 16 Warnsveld Gelderland 7232 CX",
    "addr:housenumber":"16",
    "addr:postcode":"7232 cx",
    "addr:street":"Runneboom;Gelderland",
    "iso:country":"NL",
    "sg:address":"Runneboom 16",
    "sg:city":"Warnsveld",
    "sg:orig_category":"Apotheken",
    "sg:phone":"+31 575 572 495",
    "sg:postcode":"7232 CX",
    "sg:province":"Gelderland",
    "wof:name":"Warnsveld",
    "wof:placetype":"venue"
},
  "geometry": {"coordinates":[6.229655,52.134434],"type":"Point"}
}