{
  "type": "Feature",
  "properties": {
    "addr:full":"Stadhouderstr 46 Brunssum Limburg 6441 GV",
    "addr:housenumber":"46",
    "addr:postcode":"6441 gv",
    "addr:street":"Stadhouderstr",
    "iso:country":"NL",
    "sg:address":"Stadhouderstr 46",
    "sg:city":"Brunssum",
    "sg:orig_category":"Autorijscholen",
    "sg:phone":"+31 45 527 3111",
    "sg:postcode":"6441 GV",
    "sg:province":"Limburg",
    "wof:name":"Leijten, Auto-& Motorrijschool",
    "wof:placetype":"venue"
},
  "geometry": {"coordinates":[5.960462,50.947159],"type":"Point"}
}