{
  "type": "Feature",
  "properties": {
    "iso:country":"NL",
    "sg:address":"Boswg 5",
    "sg:city":"Diever",
    "sg:orig_category":"Kaarsen - Fabrieken En Groothandel",
    "sg:phone":"+31 521 591 325",
    "sg:postcode":"7981 LE",
    "sg:province":"Drenthe",
    "wof:name":"Polle, De",
    "wof:placetype":"venue"
},
  "geometry": {"coordinates":[6.3205180168,52.8580856323],"type":"Point"}
}