{
  "type": "Feature",
  "properties": {
    "addr:full":"H Westerstr 59 Oude Pekela Groningen 9665 AN",
    "addr:housenumber":"59",
    "addr:postcode":"pekela;9665 an",
    "addr:street":"Oude",
    "iso:country":"NL",
    "sg:address":"H Westerstr 59",
    "sg:city":"Oude Pekela",
    "sg:orig_category":"Kartonnage - Fabrieken En Groothandel",
    "sg:phone":"+31 597 619 500",
    "sg:postcode":"9665 AN",
    "sg:province":"Groningen",
    "wof:name":"Kappa Attica Bv",
    "wof:placetype":"venue"
},
  "geometry": {"coordinates":[7.016914,53.105305],"type":"Point"}
}