{
  "type": "Feature",
  "properties": {
    "addr:full":"C Fabriciuspk 15 Slyk Ewyk Gelderland 6677 PN",
    "addr:housenumber":"15",
    "addr:postcode":"6677 pn",
    "addr:street":"Slyk Ewyk Gelderland",
    "iso:country":"NL",
    "sg:address":"C Fabriciuspk 15",
    "sg:city":"Slyk Ewyk",
    "sg:classifiers":[
        {
            "category":"Banks & Credit Unions",
            "subcategory":"Investment Brokerage",
            "type":"Services"
        }
    ],
    "sg:phone":"+31 481 481 737",
    "sg:postcode":"6677 PN",
    "sg:province":"Gelderland",
    "sg:tags":[
        "pension"
    ],
    "wof:name":"Remketting, De",
    "wof:placetype":"venue"
},
  "geometry": {"coordinates":[5.78856,51.88554],"type":"Point"}
}