{
  "type": "Feature",
  "properties": {
    "addr:full":"Gasthuisstraat 33 Kaatsheuvel North Brabant 5171 GC",
    "addr:housenumber":"33",
    "addr:postcode":"5171 gc",
    "addr:street":"Gasthuisstraat",
    "iso:country":"NL",
    "sg:address":"Gasthuisstraat 33",
    "sg:city":"Kaatsheuvel",
    "sg:orig_category":"Diverse Consumentenartikelen Gh",
    "sg:phone":"+31 416 272 594",
    "sg:postcode":"5171 GC",
    "sg:province":"North Brabant",
    "wof:name":"Torpe Bv",
    "wof:placetype":"venue"
},
  "geometry": {"coordinates":[5.036498,51.658745],"type":"Point"}
}