{
  "type": "Feature",
  "properties": {
    "iso:country":"NL",
    "sg:address":"2E C Huygensstraat 52",
    "sg:city":"Amsterdam",
    "sg:orig_category":"Juridische Dienstverlening",
    "sg:phone":"+31 20 777 4347",
    "sg:postcode":"1054 CV",
    "sg:province":"North Holland",
    "wof:name":"Emazing",
    "wof:placetype":"venue"
},
  "geometry": {"coordinates":[4.8731679916,52.362663269],"type":"Point"}
}