{
  "type": "Feature",
  "properties": {
    "addr:full":"Nozemanstr 12 Rotterdam Zuid-Holland 3023 TN",
    "addr:housenumber":"12",
    "addr:postcode":"3023",
    "addr:street":"Nozemanstr",
    "iso:country":"NL",
    "sg:address":"Nozemanstr 12",
    "sg:city":"Rotterdam",
    "sg:orig_category":"Kinderopvang",
    "sg:phone":"+31 10 244 0056",
    "sg:postcode":"3023 TN",
    "sg:province":"Zuid-Holland",
    "wof:name":"Luna, La",
    "wof:placetype":"venue"
},
  "geometry": {"coordinates":[4.452654,51.916241],"type":"Point"}
}