{
  "type": "Feature",
  "properties": {
    "addr:full":"Truffinowg 2 Hulst Zeeland 4561 NT",
    "addr:housenumber":"2",
    "addr:postcode":"4561 nt",
    "addr:street":"Truffinowg",
    "iso:country":"NL",
    "sg:address":"Truffinowg 2",
    "sg:city":"Hulst",
    "sg:orig_category":"Podotherapeuten",
    "sg:phone":"+31 6 22930197",
    "sg:postcode":"4561 NT",
    "sg:province":"Zeeland",
    "wof:name":"Derumeaux, V S M",
    "wof:placetype":"venue"
},
  "geometry": {"coordinates":[4.061246,51.290821],"type":"Point"}
}