{
  "type": "Feature",
  "properties": {
    "addr:full":"Alidahoeve 4 Vleuten Utrecht 3451 TK",
    "addr:housenumber":"4",
    "addr:postcode":"3451 tk",
    "addr:street":"Alidahoeve",
    "iso:country":"NL",
    "sg:address":"Alidahoeve 4",
    "sg:city":"Vleuten",
    "sg:orig_category":"Projectontwikkeling",
    "sg:phone":"+31 30 677 5788",
    "sg:postcode":"3451 TK",
    "sg:province":"Utrecht",
    "wof:name":"Midi Center",
    "wof:placetype":"venue"
},
  "geometry": {"coordinates":[5.022747,52.110298],"type":"Point"}
}