{
  "type": "Feature",
  "properties": {
    "addr:full":"Harpy 1 Nieuwegein Utrecht 3435 XL",
    "addr:housenumber":"1",
    "addr:postcode":"3435 xl",
    "addr:street":"Harpy",
    "iso:country":"NL",
    "sg:address":"Harpy 1",
    "sg:city":"Nieuwegein",
    "sg:orig_category":"Binnenhuisarchitectuur",
    "sg:phone":"+31 30 602 2049",
    "sg:postcode":"3435 XL",
    "sg:province":"Utrecht",
    "wof:name":"Koorn-Van Ravenstein, Jeanine",
    "wof:placetype":"venue"
},
  "geometry": {"coordinates":[5.083209,52.041389],"type":"Point"}
}