{
  "type": "Feature",
  "properties": {
    "addr:full":"Westerwijzend 85 Hoogkarspel Noord-Holland 1616 LB",
    "addr:housenumber":"85",
    "addr:postcode":"1616 lb",
    "addr:street":"Westerwijzend",
    "iso:country":"NL",
    "sg:address":"Westerwijzend 85",
    "sg:city":"Hoogkarspel",
    "sg:orig_category":"Fruitteelt",
    "sg:phone":"+31 228 561 362",
    "sg:postcode":"1616 LB",
    "sg:province":"Noord-Holland",
    "wof:name":"Fa Gebroeders P. En J. Van Der Gulik",
    "wof:placetype":"venue"
},
  "geometry": {"coordinates":[5.166679,52.686943],"type":"Point"}
}