{
  "type": "Feature",
  "properties": {
    "addr:full":"Hemelrijkstr 29 St Michielsgestel Noord-Brabant 5271 TX",
    "addr:housenumber":"29",
    "addr:postcode":"5271 tx",
    "addr:street":"Hemelrijkstr;St Michielsgestel",
    "iso:country":"NL",
    "sg:address":"Hemelrijkstr 29",
    "sg:city":"St Michielsgestel",
    "sg:orig_category":"Grondwerken",
    "sg:phone":"+31 73 551 2332",
    "sg:postcode":"5271 TX",
    "sg:province":"Noord-Brabant",
    "wof:name":"Bogaard & Zn, J Van Den",
    "wof:placetype":"venue"
},
  "geometry": {"coordinates":[5.345734,51.656277],"type":"Point"}
}