{
  "type": "Feature",
  "properties": {
    "addr:full":"Hendrik Van Veldekestr 11 Brunssum Limburg 6445 AA",
    "addr:housenumber":"11",
    "addr:postcode":"6445 aa",
    "addr:street":"Hendrik Van Veldekestr",
    "iso:country":"NL",
    "sg:address":"Hendrik Van Veldekestr 11",
    "sg:city":"Brunssum",
    "sg:orig_category":"Boekhouders",
    "sg:phone":"+31 45 525 2159",
    "sg:postcode":"6445 AA",
    "sg:province":"Limburg",
    "wof:name":"Administratiekantoor Hulshof",
    "wof:placetype":"venue"
},
  "geometry": {"coordinates":[5.96505,50.933262],"type":"Point"}
}