{
  "type": "Feature",
  "properties": {
    "addr:full":"Aalsmeerwg 36 Hs Amsterdam Noord-Holland 1059 AK",
    "addr:housenumber":"36 hs",
    "addr:postcode":"1059 ak",
    "addr:street":"Aalsmeerwg",
    "iso:country":"NL",
    "sg:address":"Aalsmeerwg 36 Hs",
    "sg:city":"Amsterdam",
    "sg:orig_category":"Vertaalbureaus",
    "sg:phone":"+31 20 388 0032",
    "sg:postcode":"1059 AK",
    "sg:province":"Noord-Holland",
    "sg:website":"http://www.massardo.com",
    "wof:name":"Isabella Massardo Vertalingen",
    "wof:placetype":"venue"
},
  "geometry": {"coordinates":[4.84673,52.344818],"type":"Point"}
}