{
  "type": "Feature",
  "properties": {
    "iso:country":"NL",
    "sg:address":"T Schwartzestr 105",
    "sg:city":"Almere",
    "sg:orig_category":"Grafisch Ontwerpers",
    "sg:phone":"+31 36 540 4466",
    "sg:postcode":"1328 CC",
    "wof:name":"Pier 3",
    "wof:placetype":"venue"
},
  "geometry": {"coordinates":[5.263462,52.379642],"type":"Point"}
}