{
  "type": "Feature",
  "properties": {
    "addr:full":"Olympus 1 Utrecht Utrecht 3524 WB",
    "addr:housenumber":"1",
    "addr:postcode":"3524 wb",
    "addr:street":"Olympus",
    "iso:country":"NL",
    "sg:address":"Olympus 1",
    "sg:city":"Utrecht",
    "sg:orig_category":"Kantinebeheer",
    "sg:phone":"+31 30 281 7517",
    "sg:postcode":"3524 WB",
    "sg:province":"Utrecht",
    "wof:name":"High-Risk",
    "wof:placetype":"venue"
},
  "geometry": {"coordinates":[5.1286959648,52.0639915466],"type":"Point"}
}