{
  "type": "Feature",
  "properties": {
    "addr:full":"Hof 11 Midwoud North Holland 1679 WH",
    "addr:housenumber":"11",
    "addr:postcode":"1679 wh",
    "addr:street":"Hof",
    "iso:country":"NL",
    "sg:address":"Hof 11",
    "sg:city":"Midwoud",
    "sg:orig_category":"Loodgieterswerk, Verwarming And Sanitaire Installaties",
    "sg:phone":"+31 229 201 975",
    "sg:postcode":"1679 WH",
    "sg:province":"North Holland",
    "wof:name":"Installatie & Klusbedrijf Ploeg",
    "wof:placetype":"venue"
},
  "geometry": {"coordinates":[5.075143,52.716881],"type":"Point"}
}