{
  "type": "Feature",
  "properties": {
    "iso:country":"NL",
    "sg:address":"Rivierenlaan 42",
    "sg:city":"Pijnacker",
    "sg:orig_category":"Diverse Grafische Activiteiten",
    "sg:phone":"+31 15 361 0585",
    "sg:postcode":"2641 VX",
    "sg:province":"Zuid-Holland",
    "wof:name":"Van Puffelen",
    "wof:placetype":"venue"
},
  "geometry": {"coordinates":[4.434647,52.009884],"type":"Point"}
}