{
  "type": "Feature",
  "properties": {
    "addr:full":"A Tinnepln 2 Leiden Zuid-Holland 2331 PN",
    "addr:housenumber":"2",
    "addr:postcode":"2331 pn",
    "iso:country":"NL",
    "sg:address":"A Tinnepln 2",
    "sg:city":"Leiden",
    "sg:orig_category":"Bloemen En Planten",
    "sg:phone":"+31 71 576 9090",
    "sg:postcode":"2331 PN",
    "sg:province":"Zuid-Holland",
    "wof:name":"Flora Ilona",
    "wof:placetype":"venue"
},
  "geometry": {"coordinates":[4.45082,52.151321],"type":"Point"}
}