{
  "type": "Feature",
  "properties": {
    "addr:full":"Pashof 66 Winterswijk Gelderland 7103 BB",
    "addr:housenumber":"66",
    "addr:postcode":"7103 bb",
    "addr:street":"Pashof;Gelderland",
    "iso:country":"NL",
    "sg:address":"Pashof 66",
    "sg:city":"Winterswijk",
    "sg:classifiers":[
        {
            "category":"Fast Food",
            "type":"Food & Drink"
        }
    ],
    "sg:phone":"+31 543 519 457",
    "sg:postcode":"7103 BB",
    "sg:province":"Gelderland",
    "sg:tags":[
        "afhaal",
        "restaurant"
    ],
    "wof:name":"H. Zerouali",
    "wof:placetype":"venue"
},
  "geometry": {"coordinates":[6.711798,51.979488],"type":"Point"}
}