{
  "type": "Feature",
  "properties": {
    "addr:full":"Contrabaswg 142 Almere NL. 1312 WR",
    "addr:housenumber":"142",
    "addr:postcode":"1312",
    "addr:street":"Nl.",
    "iso:country":"NL",
    "sg:address":"Contrabaswg 142",
    "sg:city":"Almere",
    "sg:orig_category":"Adviesbureaus Bouwkunde",
    "sg:phone":"+31 36 536 8283",
    "sg:postcode":"1312 WR",
    "sg:province":"NL.",
    "wof:name":"Bjorndal",
    "wof:placetype":"venue"
},
  "geometry": {"coordinates":[5.176776,52.373478],"type":"Point"}
}