{
  "type": "Feature",
  "properties": {
    "addr:full":"Libra 10 Ysselstein Ut Utrecht 3402 HA",
    "addr:housenumber":"10",
    "addr:postcode":"3402 ha",
    "addr:street":"Libra",
    "iso:country":"NL",
    "sg:address":"Libra 10",
    "sg:city":"Ysselstein Ut",
    "sg:orig_category":"Projectontwikkeling",
    "sg:phone":"+31 30 688 4255",
    "sg:postcode":"3402 HA",
    "sg:province":"Utrecht",
    "wof:name":"Vip",
    "wof:placetype":"venue"
},
  "geometry": {"coordinates":[5.047391,52.027634],"type":"Point"}
}