{
  "type": "Feature",
  "properties": {
    "addr:full":"Nikadel 77 De Koog Noord-Holland 1796 BR",
    "addr:housenumber":"77",
    "addr:postcode":"1796 br",
    "addr:street":"Nikadel",
    "iso:country":"NL",
    "sg:address":"Nikadel 77",
    "sg:city":"De Koog",
    "sg:classifiers":[
        {
            "category":"Retail",
            "subcategory":"Auto Repair",
            "type":"Services"
        }
    ],
    "sg:phone":"+31 222 317 841",
    "sg:postcode":"1796 BR",
    "sg:province":"Noord-Holland",
    "sg:tags":[
        "garage"
    ],
    "wof:name":"Kikkert Bv, R",
    "wof:placetype":"venue"
},
  "geometry": {"coordinates":[4.763607,53.097057],"type":"Point"}
}