{
  "type": "Feature",
  "properties": {
    "addr:full":"Voltawg 21 Bunschoten Spakenb Utrecht 3752 LP",
    "addr:housenumber":"21",
    "addr:postcode":"3752 lp",
    "addr:street":"Voltawg",
    "iso:country":"NL",
    "sg:address":"Voltawg 21",
    "sg:city":"Bunschoten Spakenb",
    "sg:orig_category":"Koeltechniek",
    "sg:phone":"+31 33 299 0502",
    "sg:postcode":"3752 LP",
    "sg:province":"Utrecht",
    "wof:name":"Fresko Bv",
    "wof:placetype":"venue"
},
  "geometry": {"coordinates":[5.359973,52.23188],"type":"Point"}
}