{
  "type": "Feature",
  "properties": {
    "addr:full":"Ardennen 10 Leusden Utrecht 3831 EX",
    "addr:housenumber":"10",
    "addr:postcode":"3831 ex",
    "addr:street":"Ardennen",
    "iso:country":"NL",
    "sg:address":"Ardennen 10",
    "sg:city":"Leusden",
    "sg:orig_category":"Dierenvoeder - Fabrieken",
    "sg:phone":"+31 33 479 3355",
    "sg:postcode":"3831 EX",
    "sg:province":"Utrecht",
    "wof:name":"Jadis Additiva Bv",
    "wof:placetype":"venue"
},
  "geometry": {"coordinates":[5.432524,52.133732],"type":"Point"}
}