{
  "type": "Feature",
  "properties": {
    "iso:country":"NL",
    "sg:address":"Poelendaelewg 18",
    "sg:city":"Middelburg",
    "sg:orig_category":"Organisatiebureaus",
    "sg:phone":"+31 118 635 710",
    "sg:postcode":"4335 HR",
    "sg:province":"Zeeland",
    "wof:name":"Art & Film Support",
    "wof:placetype":"venue"
},
  "geometry": {"coordinates":[3.6052570343,51.4934577942],"type":"Point"}
}