{
  "type": "Feature",
  "properties": {
    "addr:full":"Van Diemenstraat 188 Amsterdam Noord-Holland 1013 CP",
    "addr:housenumber":"188",
    "addr:postcode":"1013 cp",
    "addr:street":"Van Diemenstraat",
    "iso:country":"NL",
    "sg:address":"Van Diemenstraat 188",
    "sg:city":"Amsterdam",
    "sg:orig_category":"Boekhouders",
    "sg:phone":"+31 20 620 0771",
    "sg:postcode":"1013 CP",
    "sg:province":"Noord-Holland",
    "wof:name":"Console Vof",
    "wof:placetype":"venue"
},
  "geometry": {"coordinates":[4.887791,52.39019],"type":"Point"}
}