{
  "type": "Feature",
  "properties": {
    "addr:full":"Schaapbulterweg 35 Meedhuizen Groningen 9937 TL",
    "addr:housenumber":"35",
    "addr:postcode":"9937 tl",
    "addr:street":"Schaapbulterweg",
    "iso:country":"NL",
    "sg:address":"Schaapbulterweg 35",
    "sg:city":"Meedhuizen",
    "sg:orig_category":"Diverse Dierenfokkers",
    "sg:phone":"+31 596 533 218",
    "sg:postcode":"9937 TL",
    "sg:province":"Groningen",
    "wof:name":"Meedhuizen",
    "wof:placetype":"venue"
},
  "geometry": {"coordinates":[6.920597,53.281906],"type":"Point"}
}