{
  "type": "Feature",
  "properties": {
    "addr:full":"Sevillawg 49 Rotterdam Zuid-Holland 3047 AL",
    "addr:housenumber":"49",
    "addr:postcode":"3047 al",
    "addr:street":"Sevillawg",
    "iso:country":"NL",
    "sg:address":"Sevillawg 49",
    "sg:city":"Rotterdam",
    "sg:orig_category":"Administratie- En Boekhoudkantoren",
    "sg:phone":"+31 10 436 0874",
    "sg:postcode":"3047 AL",
    "sg:province":"Zuid-Holland",
    "wof:name":"Jansen & Co Bv",
    "wof:placetype":"venue"
},
  "geometry": {"coordinates":[4.412191,51.940331],"type":"Point"}
}