{
  "type": "Feature",
  "properties": {
    "addr:full":"De Vooysplnts 53 Utrecht Utrecht 3571 ZS",
    "addr:housenumber":"53",
    "addr:postcode":"3571 zs",
    "iso:country":"NL",
    "sg:address":"De Vooysplnts 53",
    "sg:city":"Utrecht",
    "sg:orig_category":"Projectontwikkeling",
    "sg:phone":"+31 30 271 0846",
    "sg:postcode":"3571 ZS",
    "sg:province":"Utrecht",
    "wof:name":"Oostrum En Van Laar Bv, Van",
    "wof:placetype":"venue"
},
  "geometry": {"coordinates":[5.12917,52.108181],"type":"Point"}
}