{
  "type": "Feature",
  "properties": {
    "addr:full":"Hoogwolde 7 Nunspeet Gelderland 8072 PW",
    "addr:housenumber":"7",
    "addr:postcode":"8072 pw",
    "addr:street":"Hoogwolde;Gelderland",
    "iso:country":"NL",
    "sg:address":"Hoogwolde 7",
    "sg:city":"Nunspeet",
    "sg:orig_category":"Werving And Selectie Van Vast Personeel",
    "sg:phone":"+31 341 260 466",
    "sg:postcode":"8072 PW",
    "sg:province":"Gelderland",
    "wof:name":"Frits De Jonge Bv",
    "wof:placetype":"venue"
},
  "geometry": {"coordinates":[5.7893099785,52.3693504333],"type":"Point"}
}