{
  "type": "Feature",
  "properties": {
    "addr:full":"Willibrordusstr 22 Leidschendam Zuid-Holland 2264 XS",
    "addr:housenumber":"22",
    "addr:postcode":"2264 xs",
    "addr:street":"Willibrordusstr",
    "iso:country":"NL",
    "sg:address":"Willibrordusstr 22",
    "sg:city":"Leidschendam",
    "sg:orig_category":"Honden- En Kattentrimsalons",
    "sg:phone":"+31 70 327 8996",
    "sg:postcode":"2264 XS",
    "sg:province":"Zuid-Holland",
    "wof:name":"Petstyle Hondentrimsalon",
    "wof:placetype":"venue"
},
  "geometry": {"coordinates":[4.390893,52.085152],"type":"Point"}
}