{
  "type": "Feature",
  "properties": {
    "iso:country":"NL",
    "sg:address":"Vierhouterweg 46",
    "sg:city":"Elspeet",
    "sg:orig_category":"Zuivelproducten And Spijsoli?n Gh",
    "sg:phone":"+31 577 491 241",
    "sg:postcode":"8075 BJ",
    "sg:province":"Gelderland",
    "wof:name":"Oliehandel Mw. D. Van Den Berg - Zeevat",
    "wof:placetype":"venue"
},
  "geometry": {"coordinates":[5.791216,52.29393],"type":"Point"}
}