{
  "type": "Feature",
  "properties": {
    "addr:full":"Schoolpad 6 Diemen Noord-Holland 1111 CS",
    "addr:housenumber":"6",
    "addr:postcode":"1111 cs",
    "addr:street":"Schoolpad",
    "iso:country":"NL",
    "sg:address":"Schoolpad 6",
    "sg:city":"Diemen",
    "sg:classifiers":[
        {
            "category":"Education",
            "subcategory":"Preschool",
            "type":"Public Place"
        }
    ],
    "sg:phone":"+31 20 690 4133",
    "sg:postcode":"1111 CS",
    "sg:province":"Noord-Holland",
    "sg:tags":[
        "kleuteronderwijs",
        "basis-"
    ],
    "wof:name":"Openbare Basisschool De Octopus",
    "wof:placetype":"venue"
},
  "geometry": {"coordinates":[4.958609,52.341042],"type":"Point"}
}