{
  "type": "Feature",
  "properties": {
    "addr:full":"Dres 29 Westwoud Noord-Holland 1617 JX",
    "addr:housenumber":"29",
    "addr:postcode":"1617 jx",
    "addr:street":"Dres",
    "iso:country":"NL",
    "sg:address":"Dres 29",
    "sg:city":"Westwoud",
    "sg:orig_category":"Banken And Kredietinstellingen",
    "sg:phone":"+31 228 561 410",
    "sg:postcode":"1617 JX",
    "sg:province":"Noord-Holland",
    "wof:name":"Het Posthuis",
    "wof:placetype":"venue"
},
  "geometry": {"coordinates":[5.135885,52.683681],"type":"Point"}
}