{
  "type": "Feature",
  "properties": {
    "addr:full":"Groeskuilen 174 Gemert Noord-Brabant 5421 ZW",
    "addr:housenumber":"174",
    "addr:postcode":"5421 zw",
    "addr:street":"Groeskuilen",
    "iso:country":"NL",
    "sg:address":"Groeskuilen 174",
    "sg:city":"Gemert",
    "sg:orig_category":"Adviesbureaus Bouwkunde",
    "sg:phone":"+31 492 368 148",
    "sg:postcode":"5421 ZW",
    "sg:province":"Noord-Brabant",
    "wof:name":"Smits, N G A W",
    "wof:placetype":"venue"
},
  "geometry": {"coordinates":[5.707294,51.556469],"type":"Point"}
}