{
  "type": "Feature",
  "properties": {
    "addr:full":"Beethovenln 127 Tilburg Noord-Brabant 5011 LE",
    "addr:housenumber":"127",
    "addr:postcode":"5011 le",
    "addr:street":"Tilburg",
    "iso:country":"NL",
    "sg:address":"Beethovenln 127",
    "sg:city":"Tilburg",
    "sg:orig_category":"Administratie- En Boekhoudkantoren",
    "sg:phone":"+31 13 455 3710",
    "sg:postcode":"5011 LE",
    "sg:province":"Noord-Brabant",
    "wof:name":"Louer, J",
    "wof:placetype":"venue"
},
  "geometry": {"coordinates":[5.090334,51.584675],"type":"Point"}
}