{
  "type": "Feature",
  "properties": {
    "iso:country":"NL",
    "sg:address":"Zuidervaart 14A",
    "sg:city":"Zuidschermer",
    "sg:orig_category":"Loonbedrijven",
    "sg:phone":"+31 72 504 4397",
    "sg:postcode":"1846 LJ",
    "sg:province":"North Holland",
    "wof:name":"Roelofsen, A",
    "wof:placetype":"venue"
},
  "geometry": {"coordinates":[4.774959,52.576721],"type":"Point"}
}