{
  "type": "Feature",
  "properties": {
    "addr:full":"Hogekampwg 2 Stroe Gelderland 3776 MB",
    "addr:housenumber":"2",
    "addr:postcode":"3776 mb",
    "addr:street":"Hogekampwg;Gelderland",
    "iso:country":"NL",
    "sg:address":"Hogekampwg 2",
    "sg:city":"Stroe",
    "sg:orig_category":"Bloemen En Planten",
    "sg:phone":"+31 342 441 603",
    "sg:postcode":"3776 MB",
    "sg:province":"Gelderland",
    "wof:name":"Pompoen, De",
    "wof:placetype":"venue"
},
  "geometry": {"coordinates":[5.692476,52.185982],"type":"Point"}
}