{
  "type": "Feature",
  "properties": {
    "addr:full":"Kerketuinenweg 73 Den Haag Zuid South Holland 2544 CZ",
    "addr:housenumber":"73",
    "addr:postcode":"2544",
    "addr:street":"Kerketuinenweg",
    "iso:country":"NL",
    "sg:address":"Kerketuinenweg 73",
    "sg:city":"Den Haag Zuid",
    "sg:orig_category":"Wasserettes And Stomerijen",
    "sg:phone":"+31 70 367 0229",
    "sg:postcode":"2544 CZ",
    "sg:province":"South Holland",
    "wof:name":"Vitrage Gordijn Cleaning",
    "wof:placetype":"venue"
},
  "geometry": {"coordinates":[4.2532668114,52.0488586426],"type":"Point"}
}