{
  "type": "Feature",
  "properties": {
    "addr:full":"Zamenhofstraat 114F Amsterdam Noord-Holland 1022 AG",
    "addr:housenumber":"114f",
    "addr:postcode":"1022",
    "addr:street":"Zamenhofstraat",
    "iso:country":"NL",
    "sg:address":"Zamenhofstraat 114F",
    "sg:city":"Amsterdam",
    "sg:orig_category":"Glaszetten",
    "sg:phone":"+31 20 636 1669",
    "sg:postcode":"1022 AG",
    "sg:province":"Noord-Holland",
    "wof:name":"H.M. V.D. Does",
    "wof:placetype":"venue"
},
  "geometry": {"coordinates":[4.930957,52.386742],"type":"Point"}
}