{
  "type": "Feature",
  "properties": {
    "addr:full":"Buitenkant 14 Zwolle Overijssel 8011 VH",
    "addr:housenumber":"14",
    "addr:postcode":"8011 vh",
    "addr:street":"Buitenkant",
    "iso:country":"NL",
    "sg:address":"Buitenkant 14",
    "sg:city":"Zwolle",
    "sg:orig_category":"Watersportartikelen",
    "sg:phone":"+31 38 421 5188",
    "sg:postcode":"8011 VH",
    "sg:province":"Overijssel",
    "wof:name":"Huisman Bv, H J",
    "wof:placetype":"venue"
},
  "geometry": {"coordinates":[6.0915398598,52.5140762329],"type":"Point"}
}