{
  "type": "Feature",
  "properties": {
    "iso:country":"NL",
    "sg:address":"Castelmoreln 16",
    "sg:city":"Maastricht",
    "sg:orig_category":"Architecten En Architectenbureaus",
    "sg:phone":"+31 43 350 0330",
    "sg:postcode":"6213 CW",
    "sg:province":"Limburg",
    "sg:website":"http://www.huiswerkarchitecten.nl",
    "wof:name":"Huiswerk",
    "wof:placetype":"venue"
},
  "geometry": {"coordinates":[5.6688,50.840816],"type":"Point"}
}