{
  "type": "Feature",
  "properties": {
    "addr:full":"Nieuwe Damlaan 507 Schiedam Zuid-Holland 3119 AL",
    "addr:housenumber":"507",
    "addr:postcode":"3119 al",
    "addr:street":"Nieuwe Damlaan",
    "iso:country":"NL",
    "sg:address":"Nieuwe Damlaan 507",
    "sg:city":"Schiedam",
    "sg:orig_category":"Boekhouders",
    "sg:phone":"+31 10 470 6414",
    "sg:postcode":"3119 AL",
    "sg:province":"Zuid-Holland",
    "wof:name":"Administratiekantoor Van Roey",
    "wof:placetype":"venue"
},
  "geometry": {"coordinates":[4.384744,51.92226],"type":"Point"}
}