{
  "type": "Feature",
  "properties": {
    "addr:full":"Princenhoflaan 11 Leusden Utrecht 3833 BA",
    "addr:housenumber":"11",
    "addr:postcode":"3833 ba",
    "addr:street":"Princenhoflaan",
    "iso:country":"NL",
    "sg:address":"Princenhoflaan 11",
    "sg:city":"Leusden",
    "sg:orig_category":"Verzekeringen",
    "sg:phone":"+31 33 494 5403",
    "sg:postcode":"3833 BA",
    "sg:province":"Utrecht",
    "wof:name":"Assurantiekantoor Jan Van Den Brink",
    "wof:placetype":"venue"
},
  "geometry": {"coordinates":[5.42359,52.136738],"type":"Point"}
}