{
  "type": "Feature",
  "properties": {
    "addr:full":"Schoolstr 36 Vroomshoop NL.08 7681 CM",
    "addr:housenumber":"36;nl.08",
    "addr:postcode":"7681 cm",
    "addr:street":"Schoolstr",
    "iso:country":"NL",
    "sg:address":"Schoolstr 36",
    "sg:city":"Vroomshoop",
    "sg:classifiers":[
        {
            "category":"Personal",
            "subcategory":"Nail Salon",
            "type":"Services"
        }
    ],
    "sg:phone":"+31 546 646 419",
    "sg:postcode":"7681 CM",
    "sg:province":"NL.08",
    "sg:tags":[
        "pedicure"
    ],
    "wof:name":"Knol, M",
    "wof:placetype":"venue"
},
  "geometry": {"coordinates":[6.5720229149,52.4728736877],"type":"Point"}
}