{
  "type": "Feature",
  "properties": {
    "iso:country":"NL",
    "sg:address":"Oosterblokker 48",
    "sg:city":"Oosterblokker",
    "sg:orig_category":"Grondwerken",
    "sg:phone":"+31 229 261 509",
    "sg:postcode":"1696 BH",
    "sg:province":"Noord-Holland",
    "wof:name":"Wagenaar, S",
    "wof:placetype":"venue"
},
  "geometry": {"coordinates":[5.113502,52.666946],"type":"Point"}
}