{
  "type": "Feature",
  "properties": {
    "iso:country":"NL",
    "sg:address":"Rosendaalsestr 153",
    "sg:city":"Arnhem",
    "sg:orig_category":"Postzegels",
    "sg:phone":"+31 26 442 7796",
    "sg:postcode":"6824 CD",
    "sg:province":"Gelderland",
    "wof:name":"Gorseling, Ben",
    "wof:placetype":"venue"
},
  "geometry": {"coordinates":[5.923215,51.987473],"type":"Point"}
}