{
  "type": "Feature",
  "properties": {
    "addr:full":"P Smitstr 94 Enkhuizen North Holland 1602 VD",
    "addr:housenumber":"94",
    "addr:postcode":"1602 vd",
    "addr:street":"P",
    "iso:country":"NL",
    "sg:address":"P Smitstr 94",
    "sg:city":"Enkhuizen",
    "sg:orig_category":"Onderhoudswerken",
    "sg:phone":"+31 6 51798459",
    "sg:postcode":"1602 VD",
    "sg:province":"North Holland",
    "wof:name":"Dijco",
    "wof:placetype":"venue"
},
  "geometry": {"coordinates":[5.283571,52.710167],"type":"Point"}
}