{
  "type": "Feature",
  "properties": {
    "iso:country":"NL",
    "sg:address":"Nieuwstraat 32",
    "sg:city":"Gilze",
    "sg:classifiers":[
        {
            "category":"Fast Food",
            "type":"Food & Drink"
        }
    ],
    "sg:phone":"+31 161 452 651",
    "sg:postcode":"5126 CE",
    "sg:province":"Noord-Brabant",
    "sg:tags":[
        "afhaal",
        "restaurant"
    ],
    "wof:name":"Shoarma Gilze",
    "wof:placetype":"venue"
},
  "geometry": {"coordinates":[4.941521,51.544025],"type":"Point"}
}