{
  "type": "Feature",
  "properties": {
    "addr:full":"Schoterpad 4C Bant Flevoland 8314 PW",
    "addr:housenumber":"4c",
    "addr:postcode":"8314 pw",
    "addr:street":"Schoterpad;Flevoland",
    "iso:country":"NL",
    "sg:address":"Schoterpad 4C",
    "sg:city":"Bant",
    "sg:orig_category":"Webdesign Bureaus",
    "sg:phone":"+31 527 261 173",
    "sg:postcode":"8314 PW",
    "sg:province":"Flevoland",
    "sg:website":"http://www.istos.nl",
    "wof:name":"Istos",
    "wof:placetype":"venue"
},
  "geometry": {"coordinates":[5.7745509148,52.7895011902],"type":"Point"}
}