{
  "type": "Feature",
  "properties": {
    "addr:full":"Molenwg 34 Bunnik Utrecht 3981 CC",
    "addr:housenumber":"34",
    "addr:postcode":"3981 cc",
    "addr:street":"Molenwg",
    "iso:country":"NL",
    "sg:address":"Molenwg 34",
    "sg:city":"Bunnik",
    "sg:orig_category":"Kunsthandel",
    "sg:phone":"+31 30 657 2310",
    "sg:postcode":"3981 CC",
    "sg:province":"Utrecht",
    "sg:website":"http://www.toledofinearts.com",
    "wof:name":"Toledo European Fine Art Bv",
    "wof:placetype":"venue"
},
  "geometry": {"coordinates":[5.201388,52.065434],"type":"Point"}
}