{
  "type": "Feature",
  "properties": {
    "addr:full":"Waterlandlaan 254 Purmerend Noord-Holland 1441 MZ",
    "addr:housenumber":"254",
    "addr:postcode":"1441 mz",
    "addr:street":"Waterlandlaan",
    "iso:country":"NL",
    "sg:address":"Waterlandlaan 254",
    "sg:city":"Purmerend",
    "sg:orig_category":"Woningbouwverenigingen",
    "sg:phone":"+31 299 455 677",
    "sg:postcode":"1441 MZ",
    "sg:province":"Noord-Holland",
    "wof:name":"Wooncompagnie",
    "wof:placetype":"venue"
},
  "geometry": {"coordinates":[4.9665350914,52.5004386902],"type":"Point"}
}