{
  "type": "Feature",
  "properties": {
    "addr:full":"Abbekesdoel 16 Bleskensgraaf Ca Zuid-Holland 2971 VA",
    "addr:housenumber":"16",
    "addr:postcode":"ca;2971",
    "addr:street":"Abbekesdoel",
    "iso:country":"NL",
    "sg:address":"Abbekesdoel 16",
    "sg:city":"Bleskensgraaf Ca",
    "sg:classifiers":[
        {
            "category":"Retail",
            "subcategory":"Auto Repair",
            "type":"Services"
        }
    ],
    "sg:phone":"+31 184 691 446",
    "sg:postcode":"2971 VA",
    "sg:province":"Zuid-Holland",
    "sg:tags":[
        "garage"
    ],
    "wof:name":"Vlot, A",
    "wof:placetype":"venue"
},
  "geometry": {"coordinates":[4.767768,51.869057],"type":"Point"}
}