{
  "type": "Feature",
  "properties": {
    "iso:country":"NL",
    "sg:address":"Raadhuisstr 59A",
    "sg:city":"Hulsberg",
    "sg:classifiers":[
        {
            "category":"Personal",
            "subcategory":"Nail Salon",
            "type":"Services"
        }
    ],
    "sg:phone":"+31 45 405 2648",
    "sg:postcode":"6336 VJ",
    "sg:province":"Limburg",
    "sg:tags":[
        "pedicure"
    ],
    "wof:name":"Schwillens-Kaelen, G",
    "wof:placetype":"venue"
},
  "geometry": {"coordinates":[5.857831,50.886597],"type":"Point"}
}