{
  "type": "Feature",
  "properties": {
    "addr:full":"Maarsbergseweg 53 Leersum Utrecht 3956 KV",
    "addr:housenumber":"53",
    "addr:postcode":"3956 kv",
    "addr:street":"Maarsbergseweg",
    "iso:country":"NL",
    "sg:address":"Maarsbergseweg 53",
    "sg:city":"Leersum",
    "sg:orig_category":"Hout Gh",
    "sg:phone":"+31 343 454 400",
    "sg:postcode":"3956 KV",
    "sg:province":"Utrecht",
    "wof:name":"C.L. Van Vliet Bv",
    "wof:placetype":"venue"
},
  "geometry": {"coordinates":[5.416328,52.028381],"type":"Point"}
}