{
  "type": "Feature",
  "properties": {
    "iso:country":"NL",
    "sg:address":"Raadhuislaan 2",
    "sg:city":"Oss",
    "sg:orig_category":"Overheidsdiensten",
    "sg:phone":"+31 412 629 911",
    "sg:postcode":"5341 GM",
    "sg:province":"Noord-Brabant",
    "wof:name":"Gemeente Oss",
    "wof:placetype":"venue"
},
  "geometry": {"coordinates":[-77.2352142334,38.3125991821],"type":"Point"}
}