{
  "type": "Feature",
  "properties": {
    "iso:country":"NL",
    "sg:address":"Stationsweg 2",
    "sg:city":"Aalsmeer",
    "sg:orig_category":"Opticiens",
    "sg:phone":"+31 297 320 478",
    "sg:postcode":"1431 EG",
    "sg:province":"North Holland",
    "wof:name":"Ed Kriek Optiek",
    "wof:placetype":"venue"
},
  "geometry": {"coordinates":[4.7487659454,52.2666931152],"type":"Point"}
}