{
  "type": "Feature",
  "properties": {
    "addr:full":"Dorpsstr 5 Putten Gelderland 3881 BA",
    "addr:housenumber":"5",
    "addr:postcode":"3881 ba",
    "addr:street":"Dorpsstr;Gelderland",
    "iso:country":"NL",
    "sg:address":"Dorpsstr 5",
    "sg:city":"Putten",
    "sg:orig_category":"Boeken En Tijdschriften",
    "sg:phone":"+31 341 354 432",
    "sg:postcode":"3881 BA",
    "sg:province":"Gelderland",
    "wof:name":"Abc",
    "wof:placetype":"venue"
},
  "geometry": {"coordinates":[5.606148,52.260349],"type":"Point"}
}