{
  "type": "Feature",
  "properties": {
    "addr:full":"Overtoom 215 Amsterdam North Holland 1054 HV",
    "addr:housenumber":"215",
    "addr:postcode":"1054 hv",
    "addr:street":"Overtoom",
    "iso:country":"NL",
    "sg:address":"Overtoom 215",
    "sg:city":"Amsterdam",
    "sg:orig_category":"Kinderopvang Behalve Thuis",
    "sg:phone":"+31 20 683 4027",
    "sg:postcode":"1054 HV",
    "sg:province":"North Holland",
    "wof:name":"Kids Planet",
    "wof:placetype":"venue"
},
  "geometry": {"coordinates":[4.869846,52.361149],"type":"Point"}
}