{
  "type": "Feature",
  "properties": {
    "addr:full":"Elsmorsweg 7 Oldenzaal Overijssel 7575 PD",
    "addr:housenumber":"7",
    "addr:postcode":"7575 pd",
    "addr:street":"Elsmorsweg",
    "iso:country":"NL",
    "sg:address":"Elsmorsweg 7",
    "sg:city":"Oldenzaal",
    "sg:orig_category":"Wegen And Sportterreinen",
    "sg:phone":"+31 541 572 311",
    "sg:postcode":"7575 PD",
    "sg:province":"Overijssel",
    "wof:name":"Aannemersmij Twentse Weg- En Waterbouw Bv",
    "wof:placetype":"venue"
},
  "geometry": {"coordinates":[6.9283027649,52.2912063599],"type":"Point"}
}