{
  "type": "Feature",
  "properties": {
    "iso:country":"NL",
    "sg:address":"Gibraltar 5",
    "sg:city":"Zaandam",
    "sg:orig_category":"Kappers",
    "sg:phone":"+31 75 631 4053",
    "sg:postcode":"1503 BM",
    "sg:province":"Noord-Holland",
    "wof:name":"Kapsalon Goudcoiffure",
    "wof:placetype":"venue"
},
  "geometry": {"coordinates":[4.8466329575,52.4458465576],"type":"Point"}
}