{
  "type": "Feature",
  "properties": {
    "addr:full":"Hooge Zijde 6 Eindhoven Noord-Brabant 5626 DC",
    "addr:housenumber":"6",
    "addr:postcode":"5626",
    "addr:street":"Hooge Zijde",
    "iso:country":"NL",
    "sg:address":"Hooge Zijde 6",
    "sg:city":"Eindhoven",
    "sg:orig_category":"Metaalwaren - Fabrieken",
    "sg:phone":"+31 40 262 9233",
    "sg:postcode":"5626 DC",
    "sg:province":"Noord-Brabant",
    "wof:name":"Inno",
    "wof:placetype":"venue"
},
  "geometry": {"coordinates":[5.422847,51.484509],"type":"Point"}
}