{
  "type": "Feature",
  "properties": {
    "addr:full":"Heldringstraat 41 Maassluis Zuid-Holland 3144 CE",
    "addr:housenumber":"41",
    "addr:postcode":"3144 ce",
    "addr:street":"Heldringstraat",
    "iso:country":"NL",
    "sg:address":"Heldringstraat 41",
    "sg:city":"Maassluis",
    "sg:orig_category":"Houten Verpakkingen Fab",
    "sg:phone":"+31 10 591 8580",
    "sg:postcode":"3144 CE",
    "sg:province":"Zuid-Holland",
    "wof:name":"Pallethandel Dik Lievaart Bv",
    "wof:placetype":"venue"
},
  "geometry": {"coordinates":[4.2481,51.924801],"type":"Point"}
}