{
  "type": "Feature",
  "properties": {
    "addr:full":"V Steenhuysstr 35 Oploo North Brabant 5841 AG",
    "addr:housenumber":"35",
    "addr:postcode":"5841",
    "iso:country":"NL",
    "sg:address":"V Steenhuysstr 35",
    "sg:city":"Oploo",
    "sg:orig_category":"Voetbalverenigingen",
    "sg:phone":"+31 485 382 798",
    "sg:postcode":"5841 AG",
    "sg:province":"North Brabant",
    "wof:name":"Excellent",
    "wof:placetype":"venue"
},
  "geometry": {"coordinates":[5.874205,51.607914],"type":"Point"}
}