{
  "type": "Feature",
  "properties": {
    "addr:full":"Kerkstraat 27 Zeeland North Brabant 5411 EA",
    "addr:housenumber":"27",
    "addr:postcode":"5411 ea",
    "addr:street":"Kerkstraat",
    "iso:country":"NL",
    "sg:address":"Kerkstraat 27",
    "sg:city":"Zeeland",
    "sg:orig_category":"Verlichting And Huishoudartikelen",
    "sg:phone":"+31 486 451 486",
    "sg:postcode":"5411 EA",
    "sg:province":"North Brabant",
    "wof:name":"Van Gemert Woningtextiel Bv",
    "wof:placetype":"venue"
},
  "geometry": {"coordinates":[5.673028,51.695396],"type":"Point"}
}