{
  "type": "Feature",
  "properties": {
    "addr:full":"Galjoen 27 Alphen Aan Den Ryn Zuid-Holland 2401 NB",
    "addr:housenumber":"27",
    "addr:postcode":"2401 nb",
    "addr:street":"Galjoen;Aan Den Ryn",
    "iso:country":"NL",
    "sg:address":"Galjoen 27",
    "sg:city":"Alphen Aan Den Ryn",
    "sg:orig_category":"Adviesbureaus Financieel",
    "sg:phone":"+31 172 415 151",
    "sg:postcode":"2401 NB",
    "sg:province":"Zuid-Holland",
    "wof:name":"Oude Hinderdam Bv, De",
    "wof:placetype":"venue"
},
  "geometry": {"coordinates":[4.644155,52.155869],"type":"Point"}
}