{
  "type": "Feature",
  "properties": {
    "addr:full":"Nieuwstraat 98 Koewacht Zeeland 4576 AM",
    "addr:housenumber":"98",
    "addr:postcode":"4576",
    "addr:street":"Nieuwstraat",
    "iso:country":"NL",
    "sg:address":"Nieuwstraat 98",
    "sg:city":"Koewacht",
    "sg:orig_category":"Overheidsdiensten",
    "sg:phone":"+31 114 361 451",
    "sg:postcode":"4576 AM",
    "sg:province":"Zeeland",
    "wof:name":"Stichting Gemeenschapscentrum De Vlaschaard",
    "wof:placetype":"venue"
},
  "geometry": {"coordinates":[3.9709839821,51.2287940979],"type":"Point"}
}