{
  "type": "Feature",
  "properties": {
    "iso:country":"NL",
    "sg:address":"Bosch 19",
    "sg:city":"Papendrecht",
    "sg:orig_category":"Onderhoudswerken",
    "sg:phone":"+31 78 642 7171",
    "sg:postcode":"3353 GC",
    "sg:province":"Zuid-Holland",
    "wof:name":"Bs Bouwsupport",
    "wof:placetype":"venue"
},
  "geometry": {"coordinates":[4.686778,51.824661],"type":"Point"}
}