{
  "type": "Feature",
  "properties": {
    "addr:full":"H Dunantwg 2C Zutphen Gelderland 7201 EV",
    "addr:housenumber":"2c",
    "addr:postcode":"7201 ev",
    "addr:street":"Gelderland",
    "iso:country":"NL",
    "sg:address":"H Dunantwg 2C",
    "sg:city":"Zutphen",
    "sg:orig_category":"Autoruiten",
    "sg:phone":"+31 575 572 494",
    "sg:postcode":"7201 EV",
    "sg:province":"Gelderland",
    "sg:website":"http://www.glasgarage.nl",
    "wof:name":"Glasgarage Zutphen",
    "wof:placetype":"venue"
},
  "geometry": {"coordinates":[6.196893,52.136005],"type":"Point"}
}