{
  "type": "Feature",
  "properties": {
    "addr:full":"Middelweg 28 Uitgeest Noord-Holland 1911 EG",
    "addr:housenumber":"28",
    "addr:postcode":"1911 eg",
    "addr:street":"Middelweg",
    "iso:country":"NL",
    "sg:address":"Middelweg 28",
    "sg:city":"Uitgeest",
    "sg:orig_category":"Overheidsdiensten",
    "sg:phone":"+31 251 361 111",
    "sg:postcode":"1911 EG",
    "sg:province":"Noord-Holland",
    "wof:name":"Gemeente Uitgeest",
    "wof:placetype":"venue"
},
  "geometry": {"coordinates":[4.7136287689,52.5284004211],"type":"Point"}
}