{
  "type": "Feature",
  "properties": {
    "iso:country":"NL",
    "sg:address":"Dorpsstraat 86",
    "sg:city":"Vaassen",
    "sg:orig_category":"Apothekers",
    "sg:phone":"+31 578 574 848",
    "sg:postcode":"8171 BT",
    "sg:province":"Gelderland",
    "wof:name":"Apotheek Stellendam Bv",
    "wof:placetype":"venue"
},
  "geometry": {"coordinates":[5.96821,52.286846],"type":"Point"}
}