{
  "type": "Feature",
  "properties": {
    "addr:full":"Bisschopsmolenstr 95 Etten Leur North Brabant 4876 AJ",
    "addr:housenumber":"95",
    "addr:postcode":"4876 aj",
    "addr:street":"Bisschopsmolenstr",
    "iso:country":"NL",
    "sg:address":"Bisschopsmolenstr 95",
    "sg:city":"Etten Leur",
    "sg:orig_category":"Opticiens",
    "sg:phone":"+31 76 503 8918",
    "sg:postcode":"4876 AJ",
    "sg:province":"North Brabant",
    "sg:website":"http://www.hansanders.nl",
    "wof:name":"Hans Anders",
    "wof:placetype":"venue"
},
  "geometry": {"coordinates":[4.6363511086,51.5663986206],"type":"Point"}
}