{
  "type": "Feature",
  "properties": {
    "addr:full":"Oude Rykswg 12 Garmerwolde Groningen 9798 PA",
    "addr:housenumber":"12",
    "addr:postcode":"9798 pa",
    "addr:street":"Oude Rykswg",
    "iso:country":"NL",
    "sg:address":"Oude Rykswg 12",
    "sg:city":"Garmerwolde",
    "sg:orig_category":"Verf En Lak - Fabrieken En Groothandel",
    "sg:phone":"+31 50 542 3502",
    "sg:postcode":"9798 PA",
    "sg:province":"Groningen",
    "wof:name":"Wiekel Bv",
    "wof:placetype":"venue"
},
  "geometry": {"coordinates":[6.657576,53.245007],"type":"Point"}
}