{
  "type": "Feature",
  "properties": {
    "addr:full":"Vissersstraat 32 Ouddorp Zh South Holland 3253 XK",
    "addr:housenumber":"32",
    "addr:postcode":"zh;3253 xk",
    "addr:street":"Vissersstraat",
    "iso:country":"NL",
    "sg:address":"Vissersstraat 32",
    "sg:city":"Ouddorp Zh",
    "sg:orig_category":"Visspeciaalzaken",
    "sg:phone":"+31 187 681 716",
    "sg:postcode":"3253 XK",
    "sg:province":"South Holland",
    "wof:name":"Vishandel C Melissant En Zoon",
    "wof:placetype":"venue"
},
  "geometry": {"coordinates":[3.929001,51.8022],"type":"Point"}
}