{
  "type": "Feature",
  "properties": {
    "addr:full":"De Tapuit 16 Almelo Overijssel 7609 VE",
    "addr:housenumber":"16",
    "addr:postcode":"7609",
    "addr:street":"De Tapuit;Ve",
    "iso:country":"NL",
    "sg:address":"De Tapuit 16",
    "sg:city":"Almelo",
    "sg:orig_category":"Metselwerken",
    "sg:phone":"+31 546 458 811",
    "sg:postcode":"7609 VE",
    "sg:province":"Overijssel",
    "wof:name":"Protzman En Bruins",
    "wof:placetype":"venue"
},
  "geometry": {"coordinates":[6.65067,52.335037],"type":"Point"}
}