{
  "type": "Feature",
  "properties": {
    "iso:country":"NL",
    "sg:address":"De Corantyn 37D",
    "sg:city":"Zwaag",
    "sg:orig_category":"Verhuur",
    "sg:phone":"+31 229 248 614",
    "sg:postcode":"1689 AN",
    "sg:province":"Noord-Holland",
    "sg:website":"http://www.welkers.nl",
    "wof:name":"Welkers Hotelbenodigdh & Verhuur",
    "wof:placetype":"venue"
},
  "geometry": {"coordinates":[5.07055,52.671623],"type":"Point"}
}