{
  "type": "Feature",
  "properties": {
    "iso:country":"NL",
    "sg:address":"Ridderhof 5",
    "sg:city":"Ede Gld",
    "sg:orig_category":"Kinderopvang",
    "sg:phone":"+31 318 690 666",
    "sg:postcode":"6715 EL",
    "sg:province":"Gelderland",
    "wof:name":"Pienoo",
    "wof:placetype":"venue"
},
  "geometry": {"coordinates":[5.63317,52.042011],"type":"Point"}
}