{
  "type": "Feature",
  "properties": {
    "addr:full":"Zwaluwtong 40 Monnickendam Noord-Holland 1141 KR",
    "addr:housenumber":"40",
    "addr:postcode":"1141 kr",
    "addr:street":"Zwaluwtong",
    "iso:country":"NL",
    "sg:address":"Zwaluwtong 40",
    "sg:city":"Monnickendam",
    "sg:orig_category":"Adviesbureaus Scheepsbouwkunde",
    "sg:phone":"+31 299 652 495",
    "sg:postcode":"1141 KR",
    "sg:province":"Noord-Holland",
    "wof:name":"Aquarius-Maritiem Bv",
    "wof:placetype":"venue"
},
  "geometry": {"coordinates":[5.041705,52.446575],"type":"Point"}
}