{
  "type": "Feature",
  "properties": {
    "iso:country":"NL",
    "sg:address":"Voorstraat 53",
    "sg:city":"Dordrecht",
    "sg:orig_category":"Antiekzaken",
    "sg:phone":"+31 78 614 5850",
    "sg:postcode":"3311 EM",
    "sg:province":"Zuid-Holland",
    "wof:name":"Dordtse Antiekhandel",
    "wof:placetype":"venue"
},
  "geometry": {"coordinates":[4.67151,51.818691],"type":"Point"}
}