{
  "type": "Feature",
  "properties": {
    "iso:country":"NL",
    "sg:address":"A V Duinkerkenstr 15",
    "sg:city":"Hengelo Ov",
    "sg:orig_category":"Psychologen",
    "sg:phone":"+31 74 250 5025",
    "sg:postcode":"7552 VR",
    "sg:province":"NL.08",
    "wof:name":"Praktijk Voor Leer En Leefproblemen",
    "wof:placetype":"venue"
},
  "geometry": {"coordinates":[6.78971,52.266331],"type":"Point"}
}