{
  "type": "Feature",
  "properties": {
    "addr:full":"Dorpsstr 651 Noord Scharwoude Noord-Holland 1723 HC",
    "addr:housenumber":"651",
    "addr:postcode":"1723 hc",
    "iso:country":"NL",
    "sg:address":"Dorpsstr 651",
    "sg:city":"Noord Scharwoude",
    "sg:orig_category":"Kinderkleding",
    "sg:phone":"+31 226 314 084",
    "sg:postcode":"1723 HC",
    "sg:province":"Noord-Holland",
    "wof:name":"Baby Born",
    "wof:placetype":"venue"
},
  "geometry": {"coordinates":[4.811051,52.704498],"type":"Point"}
}