{
  "type": "Feature",
  "properties": {
    "addr:full":"Utrechtseweg 34 Amersfoort Utrecht 3818 EM",
    "addr:housenumber":"34",
    "addr:postcode":"3818 em",
    "addr:street":"Utrechtseweg",
    "iso:country":"NL",
    "sg:address":"Utrechtseweg 34",
    "sg:city":"Amersfoort",
    "sg:orig_category":"Fietshandelaren",
    "sg:phone":"+31 33 461 4723",
    "sg:postcode":"3818 EM",
    "sg:province":"Utrecht",
    "wof:name":"Fietsshop De Berg",
    "wof:placetype":"venue"
},
  "geometry": {"coordinates":[5.380693,52.15086],"type":"Point"}
}