{
  "type": "Feature",
  "properties": {
    "iso:country":"NL",
    "sg:address":"Dijkerheideweg 5",
    "sg:city":"Horst",
    "sg:orig_category":"Boekhouders",
    "sg:phone":"+31 77 398 4733",
    "sg:postcode":"5961 NC",
    "sg:province":"North Carolina",
    "wof:name":"Vullings",
    "wof:placetype":"venue"
},
  "geometry": {"coordinates":[-80.018333,35.21941],"type":"Point"}
}