{
  "type": "Feature",
  "properties": {
    "iso:country":"NL",
    "sg:address":"Gysingstr 6A",
    "sg:city":"Rotterdam",
    "sg:classifiers":[
        {
            "category":"Retail",
            "subcategory":"Auto Repair",
            "type":"Services"
        }
    ],
    "sg:phone":"+31 10 425 3108",
    "sg:postcode":"3026 RL",
    "sg:province":"Zuid-Holland",
    "sg:tags":[
        "garage"
    ],
    "wof:name":"Apk 2000",
    "wof:placetype":"venue"
},
  "geometry": {"coordinates":[4.445855,51.910545],"type":"Point"}
}