{
  "type": "Feature",
  "properties": {
    "addr:full":"Friesestr 47 Coevorden Drenthe 7741 GT",
    "addr:housenumber":"47",
    "addr:postcode":"7741 gt",
    "addr:street":"Friesestr",
    "iso:country":"NL",
    "sg:address":"Friesestr 47",
    "sg:city":"Coevorden",
    "sg:orig_category":"Bloemen En Planten",
    "sg:phone":"+31 524 524 796",
    "sg:postcode":"7741 GT",
    "sg:province":"Drenthe",
    "wof:name":"Horifleur",
    "wof:placetype":"venue"
},
  "geometry": {"coordinates":[6.73804,52.662277],"type":"Point"}
}