{
  "type": "Feature",
  "properties": {
    "addr:full":"Westerheem 90 Heemskerk Noord-Holland 1964 EJ",
    "addr:housenumber":"90",
    "addr:postcode":"1964 ej",
    "addr:street":"Westerheem",
    "iso:country":"NL",
    "sg:address":"Westerheem 90",
    "sg:city":"Heemskerk",
    "sg:orig_category":"Bejaarden - Verzorgingstehuizen",
    "sg:phone":"+31 251 242 944",
    "sg:postcode":"1964 EJ",
    "sg:province":"Noord-Holland",
    "wof:name":"Westerheem",
    "wof:placetype":"venue"
},
  "geometry": {"coordinates":[4.668368,52.50491],"type":"Point"}
}