{
  "type": "Feature",
  "properties": {
    "addr:full":"Kalverdijk 4 Walsoorden Zeeland 4588 RC",
    "addr:housenumber":"4",
    "addr:postcode":"4588 rc",
    "addr:street":"Kalverdijk",
    "iso:country":"NL",
    "sg:address":"Kalverdijk 4",
    "sg:city":"Walsoorden",
    "sg:orig_category":"Bloemen And Planten Gh",
    "sg:phone":"+31 114 312 844",
    "sg:postcode":"4588 RC",
    "sg:province":"Zeeland",
    "wof:name":"Firma A.C. De Kock En Zoon",
    "wof:placetype":"venue"
},
  "geometry": {"coordinates":[4.01231,51.391499],"type":"Point"}
}