{
  "type": "Feature",
  "properties": {
    "iso:country":"NL",
    "sg:address":"Stieltjesstr 24E",
    "sg:city":"Rotterdam",
    "sg:orig_category":"Scheepvaartservice- Bureaus",
    "sg:phone":"+31 10 483 6740",
    "sg:postcode":"3071 JX",
    "sg:province":"Zuid-Holland",
    "wof:name":"Joosten Vof, R",
    "wof:placetype":"venue"
},
  "geometry": {"coordinates":[4.497718,51.91135],"type":"Point"}
}