{
  "type": "Feature",
  "properties": {
    "addr:full":"Schiel Hg Zeedk W 12 Moordrecht Zuid-Holland 2841 BZ",
    "addr:postcode":"2841 bz",
    "addr:street":"W 12",
    "iso:country":"NL",
    "sg:address":"Schiel Hg Zeedk W 12",
    "sg:city":"Moordrecht",
    "sg:orig_category":"Onderwijsmateriaal",
    "sg:phone":"+31 182 373 259",
    "sg:postcode":"2841 BZ",
    "sg:province":"Zuid-Holland",
    "sg:website":"http://www.elwe.nl",
    "wof:name":"Elwe",
    "wof:placetype":"venue"
},
  "geometry": {"coordinates":[4.667987,51.987827],"type":"Point"}
}