{
  "type": "Feature",
  "properties": {
    "addr:full":"Kalfjesln 40 Delft Zuid-Holland 2623 AJ",
    "addr:housenumber":"40",
    "addr:postcode":"2623 aj",
    "addr:street":"Kalfjesln",
    "iso:country":"NL",
    "sg:address":"Kalfjesln 40",
    "sg:city":"Delft",
    "sg:classifiers":[
        {
            "category":"Wholesale",
            "subcategory":"Meat",
            "type":"Manufacturing & Wholesale Goods"
        }
    ],
    "sg:phone":"+31 15 256 9316",
    "sg:postcode":"2623 AJ",
    "sg:province":"Zuid-Holland",
    "sg:tags":[
        "regeltechniek",
        "en",
        "meet-"
    ],
    "wof:name":"Mks Instruments Benelux",
    "wof:placetype":"venue"
},
  "geometry": {"coordinates":[4.36088,51.98494],"type":"Point"}
}