{
  "type": "Feature",
  "properties": {
    "addr:full":"Flevolaan 41 Naarden 1411 KC",
    "addr:housenumber":"41",
    "addr:postcode":"1411 kc",
    "addr:street":"Flevolaan",
    "iso:country":"NL",
    "sg:address":"Flevolaan 41",
    "sg:city":"Naarden",
    "sg:classifiers":[
        {
            "category":"Professional",
            "subcategory":"Computer Services",
            "type":"Services"
        }
    ],
    "sg:postcode":"1411 KC",
    "sg:tags":[
        "travel",
        "green",
        "sustainable",
        "hotels",
        "flights"
    ],
    "sg:website":"http://www.greenbookings.com",
    "wof:name":"Greenbookings",
    "wof:placetype":"venue"
},
  "geometry": {"coordinates":[5.195153,52.2866152],"type":"Point"}
}