{
  "type": "Feature",
  "properties": {
    "addr:full":"Kasteelln 114 Wychen Gelderland 6603 BJ",
    "addr:housenumber":"114",
    "addr:postcode":"6603 bj",
    "addr:street":"Wychen Gelderland",
    "iso:country":"NL",
    "sg:address":"Kasteelln 114",
    "sg:city":"Wychen",
    "sg:orig_category":"Kappers",
    "sg:phone":"+31 24 645 4772",
    "sg:postcode":"6603 BJ",
    "sg:province":"Gelderland",
    "wof:name":"Eurostyling",
    "wof:placetype":"venue"
},
  "geometry": {"coordinates":[5.7352771759,51.8094177246],"type":"Point"}
}