{
  "type": "Feature",
  "properties": {
    "addr:full":"Dorpsstr 115B St Willebrord Noord-Brabant 4711 EG",
    "addr:housenumber":"115b",
    "addr:postcode":"4711 eg",
    "addr:street":"St",
    "iso:country":"NL",
    "sg:address":"Dorpsstr 115B",
    "sg:city":"St Willebrord",
    "sg:orig_category":"Artsen - Huisartsen",
    "sg:phone":"+31 165 382 951",
    "sg:postcode":"4711 EG",
    "sg:province":"Noord-Brabant",
    "wof:name":"Huisartsen Groep",
    "wof:placetype":"venue"
},
  "geometry": {"coordinates":[4.591719,51.551281],"type":"Point"}
}