{
  "type": "Feature",
  "properties": {
    "iso:country":"NL",
    "sg:address":"Scharnerwg 62",
    "sg:city":"Maastricht",
    "sg:orig_category":"Goudsmeden En Zilversmeden",
    "sg:phone":"+31 43 362 1882",
    "sg:postcode":"6224 JH",
    "sg:province":"Limburg",
    "wof:name":"Pex, Igor",
    "wof:placetype":"venue"
},
  "geometry": {"coordinates":[5.716212,50.848995],"type":"Point"}
}