{
  "type": "Feature",
  "properties": {
    "addr:full":"Steenwykerstrwg 86 Meppel Drenthe 7942 HR",
    "addr:housenumber":"86",
    "addr:postcode":"7942 hr",
    "addr:street":"Steenwykerstrwg",
    "iso:country":"NL",
    "sg:address":"Steenwykerstrwg 86",
    "sg:city":"Meppel",
    "sg:orig_category":"Jachthavens - Jachtwerven",
    "sg:phone":"+31 522 254 007",
    "sg:postcode":"7942 HR",
    "sg:province":"Drenthe",
    "sg:website":"http://www.proaquameppel.nl",
    "wof:name":"Pro Aqua Meppel",
    "wof:placetype":"venue"
},
  "geometry": {"coordinates":[6.196295,52.699615],"type":"Point"}
}