{
  "type": "Feature",
  "properties": {
    "addr:full":"Honigmanstr 11 Heerlen Limburg 6411 LJ",
    "addr:housenumber":"11",
    "addr:postcode":"6411 lj",
    "addr:street":"Honigmanstr",
    "iso:country":"NL",
    "sg:address":"Honigmanstr 11",
    "sg:city":"Heerlen",
    "sg:orig_category":"Beleggingen",
    "sg:phone":"+31 45 571 4599",
    "sg:postcode":"6411 LJ",
    "sg:province":"Limburg",
    "wof:name":"Schoemaker, Frans",
    "wof:placetype":"venue"
},
  "geometry": {"coordinates":[5.976205,50.887188],"type":"Point"}
}