{
  "type": "Feature",
  "properties": {
    "addr:full":"Chopinpad 14 Almere NL. 1323 RX",
    "addr:housenumber":"14",
    "addr:postcode":"1323 rx",
    "addr:street":"Chopinpad;Nl.",
    "iso:country":"NL",
    "sg:address":"Chopinpad 14",
    "sg:city":"Almere",
    "sg:orig_category":"Boekhouders",
    "sg:phone":"+31 36 536 1649",
    "sg:postcode":"1323 RX",
    "sg:province":"NL.",
    "wof:name":"Administratiekantoor M.C. De Lange",
    "wof:placetype":"venue"
},
  "geometry": {"coordinates":[5.189263,52.366444],"type":"Point"}
}