{
  "type": "Feature",
  "properties": {
    "iso:country":"NL",
    "sg:address":"Ambachtsweg 59",
    "sg:city":"Huizen",
    "sg:orig_category":"Meubeltextiel Fab",
    "sg:phone":"+31 35 526 3761",
    "sg:postcode":"1271 AL",
    "sg:province":"Noord-Holland",
    "wof:name":"Zeilmakerij V/D Zwaan",
    "wof:placetype":"venue"
},
  "geometry": {"coordinates":[5.246448,52.308289],"type":"Point"}
}