{
  "type": "Feature",
  "properties": {
    "addr:full":"Mereveldsewg 4 Utrecht Utrecht 3585 LH",
    "addr:housenumber":"4",
    "addr:postcode":"3585 lh",
    "addr:street":"Mereveldsewg",
    "iso:country":"NL",
    "sg:address":"Mereveldsewg 4",
    "sg:city":"Utrecht",
    "sg:orig_category":"Etalageverzorging",
    "sg:phone":"+31 30 258 1221",
    "sg:postcode":"3585 LH",
    "sg:province":"Utrecht",
    "wof:name":"Vecht, Van De",
    "wof:placetype":"venue"
},
  "geometry": {"coordinates":[5.14899,52.062328],"type":"Point"}
}