{
  "type": "Feature",
  "properties": {
    "iso:country":"NL",
    "sg:address":"Muskaat 25",
    "sg:city":"De Lier",
    "sg:orig_category":"Organisatiebureaus",
    "sg:phone":"+31 174 520 702",
    "sg:postcode":"2678 WJ",
    "sg:province":"Zuid-Holland",
    "wof:name":"Projecten Frans",
    "wof:placetype":"venue"
},
  "geometry": {"coordinates":[4.2447910309,51.9795036316],"type":"Point"}
}