{
  "type": "Feature",
  "properties": {
    "addr:full":"Hanstholm 35 Hoofddorp North Holland 2133 KA",
    "addr:housenumber":"35",
    "addr:postcode":"2133 ka",
    "addr:street":"Hanstholm",
    "iso:country":"NL",
    "sg:address":"Hanstholm 35",
    "sg:city":"Hoofddorp",
    "sg:orig_category":"Film-, Tv- And Videoproductie",
    "sg:phone":"+31 23 563 9834",
    "sg:postcode":"2133 KA",
    "sg:province":"North Holland",
    "wof:name":"Van Gerwen",
    "wof:placetype":"venue"
},
  "geometry": {"coordinates":[4.66895,52.315166],"type":"Point"}
}