{
  "type": "Feature",
  "properties": {
    "addr:full":"Burgemeester Aartslaan 37 Bergeyk Noord-Brabant 5571 TR",
    "addr:housenumber":"37",
    "addr:postcode":"5571 tr",
    "addr:street":"Burgemeester Aartslaan",
    "iso:country":"NL",
    "sg:address":"Burgemeester Aartslaan 37",
    "sg:city":"Bergeyk",
    "sg:orig_category":"Kampeerterreinen",
    "sg:phone":"+31 497 573 736",
    "sg:postcode":"5571 TR",
    "sg:province":"Noord-Brabant",
    "wof:name":"T Tabakspad",
    "wof:placetype":"venue"
},
  "geometry": {"coordinates":[5.375166893,51.3008422852],"type":"Point"}
}