{
  "type": "Feature",
  "properties": {
    "iso:country":"NL",
    "sg:address":"Kayersdk 3",
    "sg:city":"Apeldoorn",
    "sg:orig_category":"Autoschade- Herstelbedrijven",
    "sg:phone":"+31 55 541 6625",
    "sg:postcode":"7332 AH",
    "sg:province":"Gelderland",
    "wof:name":"Arie Tamboer Vof",
    "wof:placetype":"venue"
},
  "geometry": {"coordinates":[5.97423,52.208046],"type":"Point"}
}