{
  "type": "Feature",
  "properties": {
    "addr:full":"G Verboonstr 2 Schiedam Zuid-Holland 3111 AA",
    "addr:housenumber":"2",
    "addr:postcode":"3111 aa",
    "iso:country":"NL",
    "sg:address":"G Verboonstr 2",
    "sg:city":"Schiedam",
    "sg:orig_category":"Makelaars En Adviseurs Onroerende Goederen",
    "sg:phone":"+31 10 273 0102",
    "sg:postcode":"3111 AA",
    "sg:province":"Zuid-Holland",
    "wof:name":"Ooms",
    "wof:placetype":"venue"
},
  "geometry": {"coordinates":[4.400625,51.913208],"type":"Point"}
}