{
  "type": "Feature",
  "properties": {
    "addr:full":"Schaperstr 2 Enschede Overijssel 7522 GH",
    "addr:housenumber":"2",
    "addr:postcode":"7522 gh",
    "addr:street":"Schaperstr",
    "iso:country":"NL",
    "sg:address":"Schaperstr 2",
    "sg:city":"Enschede",
    "sg:orig_category":"Psychotherapeuten",
    "sg:phone":"+31 53 435 4900",
    "sg:postcode":"7522 GH",
    "sg:province":"Overijssel",
    "wof:name":"Alfa Training",
    "wof:placetype":"venue"
},
  "geometry": {"coordinates":[6.885171,52.232513],"type":"Point"}
}