{
  "type": "Feature",
  "properties": {
    "addr:full":"Geldersekd 65 Amsterdam Noord-Holland 1011 EK",
    "addr:housenumber":"65",
    "addr:postcode":"1011 ek",
    "addr:street":"Geldersekd",
    "iso:country":"NL",
    "sg:address":"Geldersekd 65",
    "sg:city":"Amsterdam",
    "sg:orig_category":"Journalisten Freelance",
    "sg:phone":"+31 20 420 4833",
    "sg:postcode":"1011 EK",
    "sg:province":"Noord-Holland",
    "wof:name":"Hommes, B",
    "wof:placetype":"venue"
},
  "geometry": {"coordinates":[4.893195,52.373119],"type":"Point"}
}