{
  "type": "Feature",
  "properties": {
    "iso:country":"NL",
    "sg:address":"Hoofdstraat 179",
    "sg:city":"De Lier",
    "sg:orig_category":"Meubelzaken, Woning- And Keukeninrichting",
    "sg:phone":"+31 174 520 880",
    "sg:postcode":"2678 CJ",
    "sg:province":"Zuid-Holland",
    "wof:name":"Interieurverzorging Leen Van Heusden Bv",
    "wof:placetype":"venue"
},
  "geometry": {"coordinates":[4.253426,51.975643],"type":"Point"}
}