{
  "type": "Feature",
  "properties": {
    "addr:full":"Westerkd 32 Utrecht Utrecht 3511 HC",
    "addr:housenumber":"32",
    "addr:postcode":"3511 hc",
    "addr:street":"Westerkd",
    "iso:country":"NL",
    "sg:address":"Westerkd 32",
    "sg:city":"Utrecht",
    "sg:orig_category":"Zetterijen",
    "sg:phone":"+31 30 231 1930",
    "sg:postcode":"3511 HC",
    "sg:province":"Utrecht",
    "wof:name":"Upset",
    "wof:placetype":"venue"
},
  "geometry": {"coordinates":[5.115405,52.088932],"type":"Point"}
}