{
  "type": "Feature",
  "properties": {
    "addr:full":"Weesperzyde 92 Amsterdam Noord-Holland 1091 EK",
    "addr:housenumber":"92",
    "addr:postcode":"1091 ek",
    "addr:street":"Weesperzyde",
    "iso:country":"NL",
    "sg:address":"Weesperzyde 92",
    "sg:city":"Amsterdam",
    "sg:orig_category":"Kunstgebitten",
    "sg:phone":"+31 20 694 1008",
    "sg:postcode":"1091 EK",
    "sg:province":"Noord-Holland",
    "wof:name":"Vries, H De",
    "wof:placetype":"venue"
},
  "geometry": {"coordinates":[4.91306,52.35487],"type":"Point"}
}