{
  "type": "Feature",
  "properties": {
    "iso:country":"NL",
    "sg:address":"Eindhovenseweg 95",
    "sg:city":"Valkenswaard",
    "sg:orig_category":"Kappers",
    "sg:phone":"+31 40 201 8874",
    "sg:postcode":"5552 AA",
    "sg:province":"North Brabant",
    "wof:name":"Jouri Special Hair Care",
    "wof:placetype":"venue"
},
  "geometry": {"coordinates":[5.4607439041,51.3557243347],"type":"Point"}
}