{
  "type": "Feature",
  "properties": {
    "addr:full":"Mon Plaisir 23 Etten-Leur Noord-Brabant 4879 AK",
    "addr:housenumber":"23",
    "addr:postcode":"4879 ak",
    "addr:street":"Mon Plaisir",
    "iso:country":"NL",
    "sg:address":"Mon Plaisir 23",
    "sg:city":"Etten-Leur",
    "sg:orig_category":"Farmaceutische Producten Gh",
    "sg:phone":"+31 76 501 6920",
    "sg:postcode":"4879 AK",
    "sg:province":"Noord-Brabant",
    "wof:name":"Wilten Instrumenten Bv",
    "wof:placetype":"venue"
},
  "geometry": {"coordinates":[4.624769,51.562584],"type":"Point"}
}