{
  "type": "Feature",
  "properties": {
    "addr:full":"Kameleon 35 Heerhugowaard North Holland 1704 VJ",
    "addr:housenumber":"35",
    "addr:postcode":"1704 vj",
    "addr:street":"Kameleon",
    "iso:country":"NL",
    "sg:address":"Kameleon 35",
    "sg:city":"Heerhugowaard",
    "sg:orig_category":"Verzekeringen - Verzekeringskantoren",
    "sg:phone":"+31 72 571 1380",
    "sg:postcode":"1704 VJ",
    "sg:province":"North Holland",
    "wof:name":"Fica",
    "wof:placetype":"venue"
},
  "geometry": {"coordinates":[4.809841,52.656521],"type":"Point"}
}