{
  "type": "Feature",
  "properties": {
    "addr:full":"Herculesstraat 109 Amsterdam Noord-Holland 1076 SH",
    "addr:housenumber":"109;1076",
    "addr:postcode":"sh",
    "addr:street":"Herculesstraat",
    "iso:country":"NL",
    "sg:address":"Herculesstraat 109",
    "sg:city":"Amsterdam",
    "sg:classifiers":[
        {
            "category":"Bakery",
            "type":"Food & Drink"
        }
    ],
    "sg:phone":"+31 20 662 6432",
    "sg:postcode":"1076 SH",
    "sg:province":"Noord-Holland",
    "sg:tags":[
        "brood",
        "banket"
    ],
    "wof:name":"Joop Stolk Vof",
    "wof:placetype":"venue"
},
  "geometry": {"coordinates":[4.861702,52.346615],"type":"Point"}
}