{
  "type": "Feature",
  "properties": {
    "addr:full":"Torenstr 15 Heeswyk Dinther Noord-Brabant 5473 EK",
    "addr:housenumber":"15;dinther",
    "addr:postcode":"5473 ek",
    "addr:street":"Torenstr",
    "iso:country":"NL",
    "sg:address":"Torenstr 15",
    "sg:city":"Heeswyk Dinther",
    "sg:orig_category":"Verhuur",
    "sg:phone":"+31 413 293 729",
    "sg:postcode":"5473 EK",
    "sg:province":"Noord-Brabant",
    "wof:name":"Eijkemans, A",
    "wof:placetype":"venue"
},
  "geometry": {"coordinates":[5.482062,51.64893],"type":"Point"}
}