{
  "type": "Feature",
  "properties": {
    "addr:full":"Verl Hoograv Wg 19 Utrecht Utrecht 3525 BB",
    "addr:housenumber":"19",
    "addr:postcode":"3525 bb",
    "addr:street":"Wg",
    "iso:country":"NL",
    "sg:address":"Verl Hoograv Wg 19",
    "sg:city":"Utrecht",
    "sg:orig_category":"Verenigingsgebouwen",
    "sg:phone":"+31 30 288 9498",
    "sg:postcode":"3525 BB",
    "sg:province":"Utrecht",
    "wof:name":"Wilhelminagroep Zeeverkenners",
    "wof:placetype":"venue"
},
  "geometry": {"coordinates":[5.112504,52.059704],"type":"Point"}
}