{
  "type": "Feature",
  "properties": {
    "addr:full":"Herman Costerstraat 24 Rotterdam Zuid-Holland 3072 PD",
    "addr:housenumber":"24",
    "addr:postcode":"3072 pd",
    "addr:street":"Herman Costerstraat",
    "iso:country":"NL",
    "sg:address":"Herman Costerstraat 24",
    "sg:city":"Rotterdam",
    "sg:classifiers":[
        {
            "category":"Education",
            "subcategory":"Preschool",
            "type":"Public Place"
        }
    ],
    "sg:phone":"+31 10 484 0717",
    "sg:postcode":"3072 PD",
    "sg:province":"Zuid-Holland",
    "sg:tags":[
        "kleuteronderwijs",
        "basis-"
    ],
    "wof:name":"Nelson Mandela",
    "wof:placetype":"venue"
},
  "geometry": {"coordinates":[4.497585,51.900608],"type":"Point"}
}