{
  "type": "Feature",
  "properties": {
    "iso:country":"NL",
    "sg:address":"Fluessen 82",
    "sg:city":"Drachten",
    "sg:orig_category":"Muziekinstrumenten Fab",
    "sg:phone":"+31 512 518 219",
    "sg:postcode":"9204 HM",
    "sg:province":"Friesland",
    "wof:name":"Cornelis B.D. Smit Vof",
    "wof:placetype":"venue"
},
  "geometry": {"coordinates":[6.066265,53.099743],"type":"Point"}
}