{
  "type": "Feature",
  "properties": {
    "iso:country":"NL",
    "sg:address":"Buiskoolstr 7",
    "sg:city":"Schagen",
    "sg:orig_category":"Schilders",
    "sg:phone":"+31 224 212 275",
    "sg:postcode":"1741 EJ",
    "sg:province":"Noord-Holland",
    "wof:name":"Meereboer",
    "wof:placetype":"venue"
},
  "geometry": {"coordinates":[4.803328,52.785522],"type":"Point"}
}