{
  "type": "Feature",
  "properties": {
    "addr:full":"Rokin 140 Amsterdam Noord-Holland 1012 LE",
    "addr:housenumber":"140",
    "addr:postcode":"1012 le",
    "addr:street":"Rokin",
    "iso:country":"NL",
    "sg:address":"Rokin 140",
    "sg:city":"Amsterdam",
    "sg:orig_category":"Nagelstudio'S",
    "sg:phone":"+31 20 623 2381",
    "sg:postcode":"1012 LE",
    "sg:province":"Noord-Holland",
    "wof:name":"Pearly Nails",
    "wof:placetype":"venue"
},
  "geometry": {"coordinates":[4.892454,52.368122],"type":"Point"}
}