{
  "type": "Feature",
  "properties": {
    "addr:full":"Ridderbuurt 35 Alphen A/D Rijn South Holland 2402 NG",
    "addr:housenumber":"35",
    "addr:postcode":"2402 ng",
    "addr:street":"Ridderbuurt",
    "iso:country":"NL",
    "sg:address":"Ridderbuurt 35",
    "sg:city":"Alphen A/D Rijn",
    "sg:orig_category":"Goederenvervoer Over De Weg",
    "sg:phone":"+31 172 419 605",
    "sg:postcode":"2402 NG",
    "sg:province":"South Holland",
    "wof:name":"A.B. Mulder En Zn Bv",
    "wof:placetype":"venue"
},
  "geometry": {"coordinates":[4.673993,52.155128],"type":"Point"}
}