{
  "type": "Feature",
  "properties": {
    "addr:full":"Kl Overstr 24 Deventer Overijssel 7411 JM",
    "addr:housenumber":"24",
    "addr:postcode":"7411 jm",
    "iso:country":"NL",
    "sg:address":"Kl Overstr 24",
    "sg:city":"Deventer",
    "sg:orig_category":"Muziekinstrumenten En Bladmuziek",
    "sg:phone":"+31 570 611 749",
    "sg:postcode":"7411 JM",
    "sg:province":"Overijssel",
    "sg:website":"http://www.musica.deventer.nl",
    "wof:name":"Musica",
    "wof:placetype":"venue"
},
  "geometry": {"coordinates":[6.157772,52.252285],"type":"Point"}
}