{
  "type": "Feature",
  "properties": {
    "addr:full":"Anjerlaan 52 Naaldwijk Zuid-Holland 2671 KJ",
    "addr:housenumber":"52",
    "addr:postcode":"2671 kj",
    "addr:street":"Anjerlaan",
    "iso:country":"NL",
    "sg:address":"Anjerlaan 52",
    "sg:city":"Naaldwijk",
    "sg:classifiers":[
        {
            "category":"Professional",
            "subcategory":"Accounting & Tax Preparation",
            "type":"Services"
        }
    ],
    "sg:phone":"+31 174 630 064",
    "sg:postcode":"2671 KJ",
    "sg:province":"Zuid-Holland",
    "sg:tags":[
        "accountant"
    ],
    "wof:name":"Van Der Eijk Administraties",
    "wof:placetype":"venue"
},
  "geometry": {"coordinates":[4.207523,51.990002],"type":"Point"}
}