{
  "type": "Feature",
  "properties": {
    "addr:full":"Oudegr 240A Utrecht Utrecht 3511 NT",
    "addr:housenumber":"240a",
    "addr:postcode":"3511 nt",
    "iso:country":"NL",
    "sg:address":"Oudegr 240A",
    "sg:city":"Utrecht",
    "sg:orig_category":"Grafische Bedrijven",
    "sg:phone":"+31 6 55757657",
    "sg:postcode":"3511 NT",
    "sg:province":"Utrecht",
    "wof:name":"Jimble & Nini",
    "wof:placetype":"venue"
},
  "geometry": {"coordinates":[5.122038,52.08791],"type":"Point"}
}