{
  "type": "Feature",
  "properties": {
    "iso:country":"NL",
    "sg:address":"Goudenregenstraat 225",
    "sg:city":"'S Gravenhage",
    "sg:orig_category":"Verzekeringen",
    "sg:phone":"+31 70 345 1777",
    "sg:postcode":"2565 ES",
    "sg:province":"Zuid-Holland",
    "wof:name":"G Teeuwisse",
    "wof:placetype":"venue"
},
  "geometry": {"coordinates":[4.263182,52.077614],"type":"Point"}
}