{
  "type": "Feature",
  "properties": {
    "iso:country":"NL",
    "sg:address":"C V Pallandtln 20",
    "sg:city":"Heemstede",
    "sg:orig_category":"Golfbanen",
    "sg:phone":"+31 23 528 2210",
    "sg:postcode":"2104 SP",
    "sg:province":"Noord-Holland",
    "wof:name":"Yarnold",
    "wof:placetype":"venue"
},
  "geometry": {"coordinates":[4.611075,52.330429],"type":"Point"}
}