{
  "type": "Feature",
  "properties": {
    "iso:country":"NL",
    "sg:address":"Zwartewaterallee 25",
    "sg:city":"Zwolle",
    "sg:orig_category":"Projectontwikkeling",
    "sg:phone":"+31 38 422 1255",
    "sg:postcode":"8032 DZ",
    "sg:province":"Overijssel",
    "wof:name":"Amstelland Bv",
    "wof:placetype":"venue"
},
  "geometry": {"coordinates":[6.099745,52.52655],"type":"Point"}
}