{
  "type": "Feature",
  "properties": {
    "addr:full":"Wakkerendk 66 Eemnes Utrecht 3755 DD",
    "addr:housenumber":"66",
    "addr:postcode":"3755 dd",
    "addr:street":"Wakkerendk",
    "iso:country":"NL",
    "sg:address":"Wakkerendk 66",
    "sg:city":"Eemnes",
    "sg:orig_category":"Verzekerings- Maatschappijen",
    "sg:phone":"+31 35 531 7242",
    "sg:postcode":"3755 DD",
    "sg:province":"Utrecht",
    "sg:website":"http://www.accesnet.nl/univehgv",
    "wof:name":"Univ\u00e9",
    "wof:placetype":"venue"
},
  "geometry": {"coordinates":[5.264745,52.24728],"type":"Point"}
}