{
  "type": "Feature",
  "properties": {
    "addr:full":"Parksngl 8 Stadskanaal Groningen 9503 ED",
    "addr:housenumber":"8",
    "addr:postcode":"9503 ed",
    "addr:street":"Parksngl",
    "iso:country":"NL",
    "sg:address":"Parksngl 8",
    "sg:city":"Stadskanaal",
    "sg:orig_category":"Adviesbureaus Bedrijfsorganisatie",
    "sg:phone":"+31 599 611 127",
    "sg:postcode":"9503 ED",
    "sg:province":"Groningen",
    "wof:name":"Bouma, Aize",
    "wof:placetype":"venue"
},
  "geometry": {"coordinates":[6.959475,52.984375],"type":"Point"}
}