{
  "type": "Feature",
  "properties": {
    "addr:full":"Vierlinghstr 15 Werkendam North Brabant 4251 LC",
    "addr:housenumber":"15",
    "addr:postcode":"4251 lc",
    "addr:street":"Vierlinghstr",
    "iso:country":"NL",
    "sg:address":"Vierlinghstr 15",
    "sg:city":"Werkendam",
    "sg:orig_category":"Meubelen",
    "sg:phone":"+31 183 503 909",
    "sg:postcode":"4251 LC",
    "sg:province":"North Brabant",
    "wof:name":"Baas",
    "wof:placetype":"venue"
},
  "geometry": {"coordinates":[4.883387,51.803185],"type":"Point"}
}