{
  "type": "Feature",
  "properties": {
    "iso:country":"NL",
    "sg:address":"Weverstedehof 9",
    "sg:city":"Nieuwegein",
    "sg:orig_category":"Werving And Selectie Van Tijdelijk Personeel And Uitzendkantoren",
    "sg:phone":"+31 30 630 0011",
    "sg:postcode":"3431 HR",
    "sg:province":"Utrecht",
    "wof:name":"Dactylo",
    "wof:placetype":"venue"
},
  "geometry": {"coordinates":[5.0815992355,52.0274009705],"type":"Point"}
}