{
  "type": "Feature",
  "properties": {
    "iso:country":"NL",
    "sg:address":"Singel 30",
    "sg:city":"Sneek",
    "sg:classifiers":[
        {
            "category":"Retail",
            "subcategory":"Photofinishing",
            "type":"Services"
        }
    ],
    "sg:phone":"+31 515 417 231",
    "sg:postcode":"8601 AJ",
    "sg:province":"Provincie Friesland",
    "sg:tags":[
        "foto",
        "film"
    ],
    "wof:name":"Fotografie Erik Hesmerg",
    "wof:placetype":"venue"
},
  "geometry": {"coordinates":[5.662578,53.031384],"type":"Point"}
}