{
  "type": "Feature",
  "properties": {
    "iso:country":"NL",
    "sg:address":"Tormentilstr 10",
    "sg:city":"Arnhem",
    "sg:orig_category":"Psychotherapeuten",
    "sg:phone":"+31 26 442 3932",
    "sg:postcode":"6813 EP",
    "sg:province":"Gelderland",
    "wof:name":"Verhoosel, P",
    "wof:placetype":"venue"
},
  "geometry": {"coordinates":[5.88343,51.988243],"type":"Point"}
}