{
  "type": "Feature",
  "properties": {
    "iso:country":"NL",
    "sg:address":"Aert Van Nesstraat 52",
    "sg:city":"Rotterdam",
    "sg:orig_category":"Verlichting And Huishoudartikelen",
    "sg:phone":"+31 10 412 1995",
    "sg:postcode":"3012 CB",
    "sg:province":"Zuid-Holland",
    "wof:name":"Artistico",
    "wof:placetype":"venue"
},
  "geometry": {"coordinates":[4.475589,51.920414],"type":"Point"}
}