{
  "type": "Feature",
  "properties": {
    "iso:country":"NL",
    "sg:address":"Buikslotermeerpln 251",
    "sg:city":"Amsterdam",
    "sg:orig_category":"Schoenen",
    "sg:phone":"+31 20 494 0308",
    "sg:postcode":"1025 XC",
    "sg:province":"North Holland",
    "sg:website":"http://www.dolcis.nl",
    "wof:name":"Dolcis",
    "wof:placetype":"venue"
},
  "geometry": {"coordinates":[4.93941,52.398464],"type":"Point"}
}