{
  "type": "Feature",
  "properties": {
    "addr:full":"Willemsparkwg 10 Amsterdam North Holland 1071 HD",
    "addr:housenumber":"10",
    "addr:postcode":"1071 hd",
    "addr:street":"Willemsparkwg",
    "iso:country":"NL",
    "sg:address":"Willemsparkwg 10",
    "sg:city":"Amsterdam",
    "sg:orig_category":"Meubelen",
    "sg:phone":"+31 20 664 1384",
    "sg:postcode":"1071 HD",
    "sg:province":"North Holland",
    "wof:name":"Fellini-Interieur",
    "wof:placetype":"venue"
},
  "geometry": {"coordinates":[4.877365,52.357964],"type":"Point"}
}