{
  "type": "Feature",
  "properties": {
    "addr:full":"Duinroosweg 2 'S Gravenhage Zuid-Holland 2597 KJ",
    "addr:housenumber":"2 '",
    "addr:postcode":"2597 kj",
    "addr:street":"Duinroosweg",
    "iso:country":"NL",
    "sg:address":"Duinroosweg 2",
    "sg:city":"'S Gravenhage",
    "sg:orig_category":"Bedrijfs- And Managementsconsultants",
    "sg:phone":"+31 70 354 8104",
    "sg:postcode":"2597 KJ",
    "sg:province":"Zuid-Holland",
    "wof:name":"Psychologisch Adviesbureau Drs. E.J. Kuiper Bv",
    "wof:placetype":"venue"
},
  "geometry": {"coordinates":[4.30347,52.103153],"type":"Point"}
}