{
  "type": "Feature",
  "properties": {
    "addr:full":"Steenstr 5 Arnhem Gelderland 6828 CA",
    "addr:housenumber":"5",
    "addr:postcode":"6828 ca",
    "addr:street":"Steenstr",
    "iso:country":"NL",
    "sg:address":"Steenstr 5",
    "sg:city":"Arnhem",
    "sg:orig_category":"Fotolaboratoria",
    "sg:phone":"+31 26 442 1199",
    "sg:postcode":"6828 CA",
    "sg:province":"Gelderland",
    "wof:name":"Willemz",
    "wof:placetype":"venue"
},
  "geometry": {"coordinates":[5.914674,51.983562],"type":"Point"}
}