{
  "type": "Feature",
  "properties": {
    "addr:full":"Jonge Voolwg 39 Wormerveer Noord-Holland 1521 RH",
    "addr:housenumber":"39",
    "addr:postcode":"1521 rh",
    "iso:country":"NL",
    "sg:address":"Jonge Voolwg 39",
    "sg:city":"Wormerveer",
    "sg:orig_category":"Banden",
    "sg:phone":"+31 75 621 3405",
    "sg:postcode":"1521 RH",
    "sg:province":"Noord-Holland",
    "sg:website":"http://www.abcautos.nl",
    "wof:name":"Abc",
    "wof:placetype":"venue"
},
  "geometry": {"coordinates":[4.78154,52.507969],"type":"Point"}
}