{
  "type": "Feature",
  "properties": {
    "addr:full":"Koninginnewg 63 Kortenhoef Noord-Holland 1241 CW",
    "addr:housenumber":"63",
    "addr:postcode":"1241 cw",
    "addr:street":"Koninginnewg",
    "iso:country":"NL",
    "sg:address":"Koninginnewg 63",
    "sg:city":"Kortenhoef",
    "sg:orig_category":"Filmstudio'S En -Productie",
    "sg:phone":"+31 35 625 9000",
    "sg:postcode":"1241 CW",
    "sg:province":"Noord-Holland",
    "wof:name":"Palazzina Prod Bv",
    "wof:placetype":"venue"
},
  "geometry": {"coordinates":[5.120646,52.243443],"type":"Point"}
}