{
  "type": "Feature",
  "properties": {
    "addr:full":"Elzenbroek 67 Breda Noord-Brabant 4822 XE",
    "addr:housenumber":"67",
    "addr:postcode":"4822 xe",
    "addr:street":"Elzenbroek",
    "iso:country":"NL",
    "sg:address":"Elzenbroek 67",
    "sg:city":"Breda",
    "sg:orig_category":"Kantoor- En Secretariaatsservice",
    "sg:phone":"+31 76 542 8823",
    "sg:postcode":"4822 XE",
    "sg:province":"Noord-Brabant",
    "wof:name":"Shift",
    "wof:placetype":"venue"
},
  "geometry": {"coordinates":[4.7294511795,51.6058158875],"type":"Point"}
}