{
  "type": "Feature",
  "properties": {
    "addr:full":"Bergstraat 42 Eindhoven North Brabant 5611 JZ",
    "addr:housenumber":"42",
    "addr:postcode":"5611 jz",
    "addr:street":"Bergstraat",
    "iso:country":"NL",
    "sg:address":"Bergstraat 42",
    "sg:city":"Eindhoven",
    "sg:orig_category":"Binnenhuisarchitecten",
    "sg:phone":"+31 40 246 8328",
    "sg:postcode":"5611 JZ",
    "sg:province":"North Brabant",
    "wof:name":"Oxo Woonwinkel",
    "wof:placetype":"venue"
},
  "geometry": {"coordinates":[5.484105,51.434471],"type":"Point"}
}