{
  "type": "Feature",
  "properties": {
    "addr:full":"Essesteynstr 2 Voorburg South Holland 2272 XW",
    "addr:housenumber":"2",
    "addr:postcode":"2272 xw",
    "addr:street":"Essesteynstr",
    "iso:country":"NL",
    "sg:address":"Essesteynstr 2",
    "sg:city":"Voorburg",
    "sg:orig_category":"Oppascentrales",
    "sg:phone":"+31 70 386 5369",
    "sg:postcode":"2272 XW",
    "sg:province":"South Holland",
    "wof:name":"Baby-Sit Club, De",
    "wof:placetype":"venue"
},
  "geometry": {"coordinates":[4.3832387924,52.0819244385],"type":"Point"}
}