{
  "type": "Feature",
  "properties": {
    "addr:full":"Melkweg 51 Hoogeveen Drenthe 7904 ER",
    "addr:housenumber":"51",
    "addr:postcode":"7904 er",
    "addr:street":"Melkweg",
    "iso:country":"NL",
    "sg:address":"Melkweg 51",
    "sg:city":"Hoogeveen",
    "sg:orig_category":"Verzekeringen",
    "sg:phone":"+31 528 265 011",
    "sg:postcode":"7904 ER",
    "sg:province":"Drenthe",
    "wof:name":"Schutte Assurantien",
    "wof:placetype":"venue"
},
  "geometry": {"coordinates":[6.50767,52.722759],"type":"Point"}
}