{
  "type": "Feature",
  "properties": {
    "addr:full":"Techniekweg 16 Gorinchem Zuid-Holland 4207 HD",
    "addr:housenumber":"16",
    "addr:postcode":"4207 hd",
    "addr:street":"Techniekweg",
    "iso:country":"NL",
    "sg:address":"Techniekweg 16",
    "sg:city":"Gorinchem",
    "sg:orig_category":"Diverse Bedrijfsinstallaties Gh",
    "sg:phone":"+31 183 622 212",
    "sg:postcode":"4207 HD",
    "sg:province":"Zuid-Holland",
    "wof:name":"Homa Pompen Bv",
    "wof:placetype":"venue"
},
  "geometry": {"coordinates":[4.999365,51.841663],"type":"Point"}
}