{
  "type": "Feature",
  "properties": {
    "addr:full":"Maliesngl 16B Utrecht Utrecht 3581 BD",
    "addr:housenumber":"16b",
    "addr:postcode":"3581 bd",
    "addr:street":"Maliesngl",
    "iso:country":"NL",
    "sg:address":"Maliesngl 16B",
    "sg:city":"Utrecht",
    "sg:orig_category":"Verenigingen En Stichtingen",
    "sg:phone":"+31 30 234 5070",
    "sg:postcode":"3581 BD",
    "sg:province":"Utrecht",
    "wof:name":"Opbouw, Sticht De",
    "wof:placetype":"venue"
},
  "geometry": {"coordinates":[5.13447,52.089989],"type":"Point"}
}