{
  "type": "Feature",
  "properties": {
    "addr:full":"Columbusln 7 Gouda Zuid-Holland 2803 ET",
    "addr:housenumber":"7",
    "addr:postcode":"2803 et",
    "addr:street":"Columbusln",
    "iso:country":"NL",
    "sg:address":"Columbusln 7",
    "sg:city":"Gouda",
    "sg:orig_category":"Webdesign Bureaus",
    "sg:phone":"+31 182 538 829",
    "sg:postcode":"2803 ET",
    "sg:province":"Zuid-Holland",
    "sg:website":"http://www.apv.cjb.net",
    "wof:name":"Apv",
    "wof:placetype":"venue"
},
  "geometry": {"coordinates":[4.7004828453,52.0239372253],"type":"Point"}
}