{
  "type": "Feature",
  "properties": {
    "addr:full":"Strythagenwg 157 Kerkrade Limburg 6467 BR",
    "addr:housenumber":"157",
    "addr:postcode":"6467 br",
    "iso:country":"NL",
    "sg:address":"Strythagenwg 157",
    "sg:city":"Kerkrade",
    "sg:orig_category":"Luchtfotografie",
    "sg:phone":"+31 45 541 1145",
    "sg:postcode":"6467 BR",
    "sg:province":"Limburg",
    "wof:name":"Ernst",
    "wof:placetype":"venue"
},
  "geometry": {"coordinates":[6.033501,50.865391],"type":"Point"}
}