{
  "type": "Feature",
  "properties": {
    "addr:full":"Bergumerdam 3 Burgum Friesland 9251 GB",
    "addr:housenumber":"3",
    "addr:postcode":"9251 gb",
    "addr:street":"Bergumerdam",
    "iso:country":"NL",
    "sg:address":"Bergumerdam 3",
    "sg:city":"Burgum",
    "sg:orig_category":"Huishoudapparatuur, Televisies And Radio'S",
    "sg:phone":"+31 511 464 142",
    "sg:postcode":"9251 GB",
    "sg:province":"Friesland",
    "wof:name":"Vof Visser",
    "wof:placetype":"venue"
},
  "geometry": {"coordinates":[5.991504,53.189011],"type":"Point"}
}