{
  "type": "Feature",
  "properties": {
    "addr:full":"Houttuin 5 Hillegom Zuid-Holland 2181 JG",
    "addr:housenumber":"5",
    "addr:postcode":"2181 jg",
    "addr:street":"Houttuin",
    "iso:country":"NL",
    "sg:address":"Houttuin 5",
    "sg:city":"Hillegom",
    "sg:classifiers":[
        {
            "category":"Farming",
            "subcategory":"Fish & Marine Products",
            "type":"Manufacturing & Wholesale Goods"
        }
    ],
    "sg:phone":"+31 252 522 422",
    "sg:postcode":"2181 JG",
    "sg:province":"Zuid-Holland",
    "sg:tags":[
        "vi"
    ],
    "wof:name":"Maas, D",
    "wof:placetype":"venue"
},
  "geometry": {"coordinates":[4.579429,52.291695],"type":"Point"}
}