{
  "type": "Feature",
  "properties": {
    "iso:country":"NL",
    "sg:address":"Loostr 56",
    "sg:city":"Loo Gld",
    "sg:orig_category":"Kaasgroothandel",
    "sg:phone":"+31 316 261 849",
    "sg:postcode":"6924 AH",
    "sg:province":"Gelderland",
    "wof:name":"Ruiten Varuka, Fa Van",
    "wof:placetype":"venue"
},
  "geometry": {"coordinates":[5.9808020592,51.9300193787],"type":"Point"}
}