{
  "type": "Feature",
  "properties": {
    "addr:full":"Sweelinckln 98 S Gravenzande Zuid-Holland 2692 BE",
    "addr:housenumber":"98;gravenzande",
    "addr:postcode":"2692",
    "addr:street":"Sweelinckln;S",
    "iso:country":"NL",
    "sg:address":"Sweelinckln 98",
    "sg:city":"S Gravenzande",
    "sg:orig_category":"Poppen En Poppenhuismaterialen",
    "sg:phone":"+31 174 414 283",
    "sg:postcode":"2692 BE",
    "sg:province":"Zuid-Holland",
    "wof:name":"Dilian",
    "wof:placetype":"venue"
},
  "geometry": {"coordinates":[4.153481,52.002251],"type":"Point"}
}