{
  "type": "Feature",
  "properties": {
    "addr:full":"Sluiskeshoeven 19 Rosmalen Noord-Brabant 5244 GM",
    "addr:housenumber":"19",
    "addr:postcode":"5244 gm",
    "addr:street":"Sluiskeshoeven",
    "iso:country":"NL",
    "sg:address":"Sluiskeshoeven 19",
    "sg:city":"Rosmalen",
    "sg:orig_category":"Psychologen",
    "sg:phone":"+31 73 521 7269",
    "sg:postcode":"5244 GM",
    "sg:province":"Noord-Brabant",
    "wof:name":"Coolen, Mevr Drs C I M",
    "wof:placetype":"venue"
},
  "geometry": {"coordinates":[5.375994,51.715797],"type":"Point"}
}