{
  "type": "Feature",
  "properties": {
    "addr:full":"Dokter Bauerstraat 134 Gorinchem South Holland 4205 KE",
    "addr:housenumber":"134",
    "addr:postcode":"4205 ke",
    "addr:street":"Dokter Bauerstraat",
    "iso:country":"NL",
    "sg:address":"Dokter Bauerstraat 134",
    "sg:city":"Gorinchem",
    "sg:orig_category":"Boekhouders",
    "sg:phone":"+31 183 699 240",
    "sg:postcode":"4205 KE",
    "sg:province":"South Holland",
    "wof:name":"J. De Leeuw",
    "wof:placetype":"venue"
},
  "geometry": {"coordinates":[4.958068,51.841267],"type":"Point"}
}