{
  "type": "Feature",
  "properties": {
    "addr:full":"Dorpsstraat 94 De Koog Noord-Holland 1796 CE",
    "addr:housenumber":"94",
    "addr:postcode":"1796 ce",
    "addr:street":"Dorpsstraat",
    "iso:country":"NL",
    "sg:address":"Dorpsstraat 94",
    "sg:city":"De Koog",
    "sg:orig_category":"Banken And Kredietinstellingen",
    "sg:phone":"+31 222 317 504",
    "sg:postcode":"1796 CE",
    "sg:province":"Noord-Holland",
    "wof:name":"Rabobank",
    "wof:placetype":"venue"
},
  "geometry": {"coordinates":[4.762196,53.098846],"type":"Point"}
}