{
  "type": "Feature",
  "properties": {
    "addr:full":"M Harpertsz Trompln 20 Enschede Overijssel 7511 JK",
    "addr:housenumber":"20",
    "addr:postcode":"7511 jk",
    "addr:street":"M Harpertsz Trompln",
    "iso:country":"NL",
    "sg:address":"M Harpertsz Trompln 20",
    "sg:city":"Enschede",
    "sg:orig_category":"Notarissen",
    "sg:phone":"+31 53 431 5031",
    "sg:postcode":"7511 JK",
    "sg:province":"Overijssel",
    "wof:name":"Notariskantoor De Rooij & Derkman",
    "wof:placetype":"venue"
},
  "geometry": {"coordinates":[6.895374,52.223576],"type":"Point"}
}