{
  "type": "Feature",
  "properties": {
    "addr:full":"Vechtstr 80 Groningen Groningen 9725 CW",
    "addr:housenumber":"80",
    "addr:postcode":"9725 cw",
    "addr:street":"Vechtstr",
    "iso:country":"NL",
    "sg:address":"Vechtstr 80",
    "sg:city":"Groningen",
    "sg:orig_category":"Artsen - Huisartsen",
    "sg:phone":"+31 50 525 9499",
    "sg:postcode":"9725 CW",
    "sg:province":"Groningen",
    "wof:name":"Tent, B",
    "wof:placetype":"venue"
},
  "geometry": {"coordinates":[6.569247,53.207752],"type":"Point"}
}