{
  "type": "Feature",
  "properties": {
    "iso:country":"NL",
    "sg:address":"Vechtstr 80",
    "sg:city":"Groningen",
    "sg:orig_category":"Artsen - Huisartsen",
    "sg:phone":"+31 50 525 9499",
    "sg:postcode":"9725 CW",
    "sg:province":"Groningen",
    "wof:name":"Tent, B",
    "wof:placetype":"venue"
},
  "geometry": {"coordinates":[6.569247,53.207752],"type":"Point"}
}