{
  "type": "Feature",
  "properties": {
    "addr:full":"Weesperplein 13 Amsterdam North Holland 1018 WZ",
    "addr:housenumber":"13",
    "addr:postcode":"1018 wz",
    "addr:street":"Weesperplein",
    "iso:country":"NL",
    "sg:address":"Weesperplein 13",
    "sg:city":"Amsterdam",
    "sg:classifiers":[
        {
            "category":"Fast Food",
            "type":"Food & Drink"
        }
    ],
    "sg:phone":"+31 20 625 2475",
    "sg:postcode":"1018 WZ",
    "sg:province":"North Holland",
    "sg:tags":[
        "afhaal",
        "restaurant"
    ],
    "wof:name":"Cantarell",
    "wof:placetype":"venue"
},
  "geometry": {"coordinates":[4.908209,52.362041],"type":"Point"}
}