{
  "type": "Feature",
  "properties": {
    "addr:full":"Rabenhauptstr 23 Groningen Groningen 9725 CB",
    "addr:housenumber":"23",
    "addr:postcode":"9725 cb",
    "addr:street":"Rabenhauptstr",
    "iso:country":"NL",
    "sg:address":"Rabenhauptstr 23",
    "sg:city":"Groningen",
    "sg:orig_category":"Psychotherapeuten",
    "sg:phone":"+31 50 542 4939",
    "sg:postcode":"9725 CB",
    "sg:province":"Groningen",
    "wof:name":"Wallis De Vries, Mevr Drs V M",
    "wof:placetype":"venue"
},
  "geometry": {"coordinates":[6.570321,53.209507],"type":"Point"}
}