{
  "type": "Feature",
  "properties": {
    "iso:country":"NL",
    "sg:address":"Brugstraat 8",
    "sg:city":"Ewijk",
    "sg:orig_category":"Bloemen And Planten",
    "sg:phone":"+31 487 521 562",
    "sg:postcode":"6644 AH",
    "sg:province":"Gelderland",
    "wof:name":"Fa Willems",
    "wof:placetype":"venue"
},
  "geometry": {"coordinates":[5.74279,51.87608],"type":"Point"}
}