{
  "type": "Feature",
  "properties": {
    "addr:full":"Witte Kruis 97 Babberich Gelderland 6909 BN",
    "addr:housenumber":"97",
    "addr:postcode":"6909 bn",
    "addr:street":"Witte Kruis;Gelderland",
    "iso:country":"NL",
    "sg:address":"Witte Kruis 97",
    "sg:city":"Babberich",
    "sg:orig_category":"Verenigingen En Stichtingen",
    "sg:phone":"+31 316 246 055",
    "sg:postcode":"6909 BN",
    "sg:province":"Gelderland",
    "sg:website":"http://www.harmonia-nl.org",
    "wof:name":"Harmonia Afd Arnhem",
    "wof:placetype":"venue"
},
  "geometry": {"coordinates":[6.109642,51.90498],"type":"Point"}
}