{
  "type": "Feature",
  "properties": {
    "iso:country":"NL",
    "sg:address":"C Krusemanstr 7",
    "sg:city":"Amsterdam",
    "sg:classifiers":[
        {
            "category":"Food & Beverages",
            "subcategory":"Fruits & Vegetables",
            "type":"Retail Goods"
        }
    ],
    "sg:phone":"+31 20 470 8807",
    "sg:postcode":"1075 NB",
    "sg:province":"North Holland",
    "sg:tags":[
        "en",
        "groenten"
    ],
    "wof:name":"Dolf'S Vitamineshop",
    "wof:placetype":"venue"
},
  "geometry": {"coordinates":[4.863509,52.351303],"type":"Point"}
}