{
  "type": "Feature",
  "properties": {
    "addr:full":"Eesterbrinkweg 5 Gorssel Gelderland 7213 LD",
    "addr:housenumber":"5",
    "addr:postcode":"7213 ld",
    "addr:street":"Eesterbrinkweg;Gelderland",
    "iso:country":"NL",
    "sg:address":"Eesterbrinkweg 5",
    "sg:city":"Gorssel",
    "sg:orig_category":"Bouwmaterialen Gh",
    "sg:phone":"+31 575 492 897",
    "sg:postcode":"7213 LD",
    "sg:province":"Gelderland",
    "wof:name":"Mipa Nederland Bv",
    "wof:placetype":"venue"
},
  "geometry": {"coordinates":[6.204334,52.181335],"type":"Point"}
}