{
  "type": "Feature",
  "properties": {
    "addr:full":"Zwanebloemstr 27 Voorhout Zuid-Holland 2215 GH",
    "addr:housenumber":"27",
    "addr:postcode":"2215 gh",
    "addr:street":"Zwanebloemstr",
    "iso:country":"NL",
    "sg:address":"Zwanebloemstr 27",
    "sg:city":"Voorhout",
    "sg:orig_category":"Kappers",
    "sg:phone":"+31 6 25347411",
    "sg:postcode":"2215 GH",
    "sg:province":"Zuid-Holland",
    "wof:name":"Hout, Anja Van Den",
    "wof:placetype":"venue"
},
  "geometry": {"coordinates":[4.48914814,52.2197952271],"type":"Point"}
}