{
  "type": "Feature",
  "properties": {
    "addr:full":"Molenpk 3 Utrecht Utrecht 3531 ET",
    "addr:housenumber":"3",
    "addr:postcode":"3531 et",
    "addr:street":"Molenpk",
    "iso:country":"NL",
    "sg:address":"Molenpk 3",
    "sg:city":"Utrecht",
    "sg:orig_category":"Musea",
    "sg:phone":"+31 30 299 0174",
    "sg:postcode":"3531 ET",
    "sg:province":"Utrecht",
    "wof:name":"Houtzaagmolen",
    "wof:placetype":"venue"
},
  "geometry": {"coordinates":[5.09999,52.089642],"type":"Point"}
}