{
  "type": "Feature",
  "properties": {
    "addr:full":"Wooldseweg 76 Winterswijk Woold Gelderland 7108 AB",
    "addr:housenumber":"76",
    "addr:postcode":"7108 ab",
    "addr:street":"Wooldseweg",
    "iso:country":"NL",
    "sg:address":"Wooldseweg 76",
    "sg:city":"Winterswijk Woold",
    "sg:orig_category":"Fietshandelaren",
    "sg:phone":"+31 543 564 281",
    "sg:postcode":"7108 AB",
    "sg:province":"Gelderland",
    "wof:name":"G.W.H. Houwers",
    "wof:placetype":"venue"
},
  "geometry": {"coordinates":[6.704928,51.941425],"type":"Point"}
}