{
  "type": "Feature",
  "properties": {
    "addr:full":"Deltahaven 18 Stellendam Zuid-Holland 3251 LC",
    "addr:housenumber":"18",
    "addr:postcode":"3251 lc",
    "addr:street":"Deltahaven",
    "iso:country":"NL",
    "sg:address":"Deltahaven 18",
    "sg:city":"Stellendam",
    "sg:orig_category":"Machinefabrieken",
    "sg:phone":"+31 187 498 020",
    "sg:postcode":"3251 LC",
    "sg:province":"Zuid-Holland",
    "wof:name":"Padmos Stellendam Bv",
    "wof:placetype":"venue"
},
  "geometry": {"coordinates":[4.039297,51.822323],"type":"Point"}
}