{
  "type": "Feature",
  "properties": {
    "addr:full":"Nedermolen 15 Steensel Noord-Brabant 5524 KG",
    "addr:housenumber":"15",
    "addr:postcode":"5524 kg",
    "addr:street":"Nedermolen",
    "iso:country":"NL",
    "sg:address":"Nedermolen 15",
    "sg:city":"Steensel",
    "sg:orig_category":"Pluimveebedrijven En -Handelaren",
    "sg:phone":"+31 497 514 030",
    "sg:postcode":"5524 KG",
    "sg:province":"Noord-Brabant",
    "wof:name":"Hulst, Van",
    "wof:placetype":"venue"
},
  "geometry": {"coordinates":[5.3742,51.373737],"type":"Point"}
}