{
  "type": "Feature",
  "properties": {
    "addr:full":"Hamelenburg 27 Hoofddorp North Holland 2135 EP",
    "addr:housenumber":"27",
    "addr:postcode":"2135 ep",
    "addr:street":"Hamelenburg",
    "iso:country":"NL",
    "sg:address":"Hamelenburg 27",
    "sg:city":"Hoofddorp",
    "sg:orig_category":"Partyservice",
    "sg:phone":"+31 23 563 0738",
    "sg:postcode":"2135 EP",
    "sg:province":"North Holland",
    "sg:website":"http://www.sushiworkshop.nl",
    "wof:name":"Sushi Workshop",
    "wof:placetype":"venue"
},
  "geometry": {"coordinates":[4.663897,52.303997],"type":"Point"}
}