{
  "type": "Feature",
  "properties": {
    "addr:full":"Rottekd 11A Zevenhuizen Zh South Holland 2761 EA",
    "addr:housenumber":"11a;zh",
    "addr:postcode":"2761 ea",
    "addr:street":"Rottekd",
    "iso:country":"NL",
    "sg:address":"Rottekd 11A",
    "sg:city":"Zevenhuizen Zh",
    "sg:orig_category":"Bloemen En Planten - Decoratie",
    "sg:phone":"+31 180 632 363",
    "sg:postcode":"2761 EA",
    "sg:province":"South Holland",
    "sg:website":"http://www.tuinkunst.nl",
    "wof:name":"Groene Tuin",
    "wof:placetype":"venue"
},
  "geometry": {"coordinates":[4.583465,52.008991],"type":"Point"}
}