{
  "type": "Feature",
  "properties": {
    "addr:full":"Armstrongln 26 Reeuwyk Zuid-Holland 2811 SR",
    "addr:housenumber":"26",
    "addr:postcode":"2811 sr",
    "addr:street":"Armstrongln",
    "iso:country":"NL",
    "sg:address":"Armstrongln 26",
    "sg:city":"Reeuwyk",
    "sg:orig_category":"Honden- En Kattentrimsalons",
    "sg:phone":"+31 182 393 819",
    "sg:postcode":"2811 SR",
    "sg:province":"Zuid-Holland",
    "wof:name":"Dorgelo-De Vos, G",
    "wof:placetype":"venue"
},
  "geometry": {"coordinates":[4.727857,52.048496],"type":"Point"}
}