{
  "type": "Feature",
  "properties": {
    "addr:full":"Oranjeplein 13 Bunde Limburg 6241 EN",
    "addr:housenumber":"13",
    "addr:postcode":"6241 en",
    "addr:street":"Oranjeplein",
    "iso:country":"NL",
    "sg:address":"Oranjeplein 13",
    "sg:city":"Bunde",
    "sg:orig_category":"Technische Studies And Onderzoek",
    "sg:phone":"+31 43 358 0370",
    "sg:postcode":"6241 EN",
    "sg:province":"Limburg",
    "wof:name":"Meteo Rob Van Der Giessen",
    "wof:placetype":"venue"
},
  "geometry": {"coordinates":[5.737188,50.898327],"type":"Point"}
}