{
  "type": "Feature",
  "properties": {
    "addr:full":"Westeinde 6 Vriezenveen Overijssel 7671 CC",
    "addr:housenumber":"6",
    "addr:postcode":"7671 cc",
    "addr:street":"Westeinde",
    "iso:country":"NL",
    "sg:address":"Westeinde 6",
    "sg:city":"Vriezenveen",
    "sg:orig_category":"Biljart- And Snookerzalen",
    "sg:phone":"+31 546 562 072",
    "sg:postcode":"7671 CC",
    "sg:province":"Overijssel",
    "wof:name":"Cafe Het Wapen Van Vriezenveen",
    "wof:placetype":"venue"
},
  "geometry": {"coordinates":[6.627727,52.413086],"type":"Point"}
}