{
  "type": "Feature",
  "properties": {
    "addr:full":"Koningstraat 2 Den Helder Noord-Holland 1781 KG",
    "addr:housenumber":"2",
    "addr:postcode":"1781 kg",
    "addr:street":"Koningstraat",
    "iso:country":"NL",
    "sg:address":"Koningstraat 2",
    "sg:city":"Den Helder",
    "sg:classifiers":[
        {
            "category":"Fast Food",
            "type":"Food & Drink"
        }
    ],
    "sg:phone":"+31 223 617 040",
    "sg:postcode":"1781 KG",
    "sg:province":"Noord-Holland",
    "sg:tags":[
        "afhaal",
        "restaurant"
    ],
    "wof:name":"De Farao",
    "wof:placetype":"venue"
},
  "geometry": {"coordinates":[4.760557,52.962013],"type":"Point"}
}