{
  "type": "Feature",
  "properties": {
    "addr:full":"Kanaalstraat 20 Hansweert Zeeland 4417 AJ",
    "addr:housenumber":"20",
    "addr:postcode":"4417 aj",
    "addr:street":"Kanaalstraat",
    "iso:country":"NL",
    "sg:address":"Kanaalstraat 20",
    "sg:city":"Hansweert",
    "sg:orig_category":"Banken And Kredietinstellingen",
    "sg:phone":"+31 113 381 320",
    "sg:postcode":"4417 AJ",
    "sg:province":"Zeeland",
    "wof:name":"Postkantoor",
    "wof:placetype":"venue"
},
  "geometry": {"coordinates":[4.004195,51.447525],"type":"Point"}
}