{
  "type": "Feature",
  "properties": {
    "iso:country":"NL",
    "sg:address":"Kanaalstraat 20",
    "sg:city":"Hansweert",
    "sg:orig_category":"Banken And Kredietinstellingen",
    "sg:phone":"+31 113 381 320",
    "sg:postcode":"4417 AJ",
    "sg:province":"Zeeland",
    "wof:name":"Postkantoor",
    "wof:placetype":"venue"
},
  "geometry": {"coordinates":[4.004195,51.447525],"type":"Point"}
}