{
  "type": "Feature",
  "properties": {
    "addr:full":"Peizerwg 74 Groningen Groningen 9727 AK",
    "addr:housenumber":"74",
    "addr:postcode":"9727 ak",
    "addr:street":"Peizerwg",
    "iso:country":"NL",
    "sg:address":"Peizerwg 74",
    "sg:city":"Groningen",
    "sg:orig_category":"Keukens",
    "sg:phone":"+31 50 527 5522",
    "sg:postcode":"9727 AK",
    "sg:province":"Groningen",
    "wof:name":"Siematic",
    "wof:placetype":"venue"
},
  "geometry": {"coordinates":[6.546565,53.209797],"type":"Point"}
}