{
  "type": "Feature",
  "properties": {
    "addr:full":"Dr Kuyperkade 4 Maassluis Zuid-Holland 3142 GB",
    "addr:housenumber":"4",
    "addr:postcode":"3142 gb",
    "addr:street":"Dr Kuyperkade",
    "iso:country":"NL",
    "sg:address":"Dr Kuyperkade 4",
    "sg:city":"Maassluis",
    "sg:orig_category":"Verlichting And Huishoudartikelen",
    "sg:phone":"+31 10 591 6125",
    "sg:postcode":"3142 GB",
    "sg:province":"Zuid-Holland",
    "wof:name":"Gordijnboetiek Maja Jongebreur",
    "wof:placetype":"venue"
},
  "geometry": {"coordinates":[4.25443,51.922005],"type":"Point"}
}