{
  "type": "Feature",
  "properties": {
    "addr:full":"Lage Made 20 Oudenbosch Noord-Brabant 4731 VR",
    "addr:housenumber":"20",
    "addr:postcode":"4731 vr",
    "addr:street":"Lage Made",
    "iso:country":"NL",
    "sg:address":"Lage Made 20",
    "sg:city":"Oudenbosch",
    "sg:orig_category":"Goederenvervoer Over De Weg",
    "sg:phone":"+31 165 317 076",
    "sg:postcode":"4731 VR",
    "sg:province":"Noord-Brabant",
    "wof:name":"Intrago",
    "wof:placetype":"venue"
},
  "geometry": {"coordinates":[4.528656,51.582104],"type":"Point"}
}