{
  "type": "Feature",
  "properties": {
    "addr:full":"D Hoogenraadstr 214 S Gravenhage Zuid-Holland 2586 TR",
    "addr:housenumber":"214;gravenhage",
    "addr:postcode":"2586 tr",
    "addr:street":"S",
    "iso:country":"NL",
    "sg:address":"D Hoogenraadstr 214",
    "sg:city":"S Gravenhage",
    "sg:classifiers":[
        {
            "category":"Travel",
            "subcategory":"Hotels & Motels",
            "type":"Entertainment"
        }
    ],
    "sg:phone":"+31 70 355 0884",
    "sg:postcode":"2586 TR",
    "sg:province":"Zuid-Holland",
    "wof:name":"Meerbeek, J",
    "wof:placetype":"venue"
},
  "geometry": {"coordinates":[4.277215,52.10672],"type":"Point"}
}