{
  "type": "Feature",
  "properties": {
    "addr:full":"Koningsplein 3 Asten Noord-Brabant 5721 GJ",
    "addr:housenumber":"3",
    "addr:postcode":"5721 gj",
    "addr:street":"Koningsplein",
    "iso:country":"NL",
    "sg:address":"Koningsplein 3",
    "sg:city":"Asten",
    "sg:orig_category":"Overheidsdiensten",
    "sg:phone":"+31 493 671 212",
    "sg:postcode":"5721 GJ",
    "sg:province":"Noord-Brabant",
    "wof:name":"Gemeente Asten",
    "wof:placetype":"venue"
},
  "geometry": {"coordinates":[5.7450928688,51.4037132263],"type":"Point"}
}