{
  "type": "Feature",
  "properties": {
    "addr:full":"Oude Postwg 15 Ambt Delden NL.08 7495 SB",
    "addr:housenumber":"15",
    "addr:postcode":"nl.08 7495 sb",
    "addr:street":"Oude Postwg",
    "iso:country":"NL",
    "sg:address":"Oude Postwg 15",
    "sg:city":"Ambt Delden",
    "sg:orig_category":"Onderhoudswerken",
    "sg:phone":"+31 547 275 782",
    "sg:postcode":"7495 SB",
    "sg:province":"NL.08",
    "wof:name":"Bw",
    "wof:placetype":"venue"
},
  "geometry": {"coordinates":[6.620711,52.240067],"type":"Point"}
}