{
  "type": "Feature",
  "properties": {
    "addr:full":"Molenwg 64 Steenbergen Nb Noord-Brabant 4651 CM",
    "addr:housenumber":"64",
    "addr:postcode":"4651 cm",
    "addr:street":"Molenwg",
    "iso:country":"NL",
    "sg:address":"Molenwg 64",
    "sg:city":"Steenbergen Nb",
    "sg:orig_category":"Juridische Adviseurs",
    "sg:phone":"+31 167 566 755",
    "sg:postcode":"4651 CM",
    "sg:province":"Noord-Brabant",
    "wof:name":"Mooy, De",
    "wof:placetype":"venue"
},
  "geometry": {"coordinates":[4.314555,51.585594],"type":"Point"}
}