{
  "type": "Feature",
  "properties": {
    "addr:full":"Buyenswg 2 Mynsheerenland Zuid-Holland 3271 LE",
    "addr:housenumber":"2",
    "addr:postcode":"3271 le",
    "addr:street":"Buyenswg",
    "iso:country":"NL",
    "sg:address":"Buyenswg 2",
    "sg:city":"Mynsheerenland",
    "sg:orig_category":"Wijnkoperijen En -Groothandel",
    "sg:phone":"+31 186 601 539",
    "sg:postcode":"3271 LE",
    "sg:province":"Zuid-Holland",
    "wof:name":"Hqvins",
    "wof:placetype":"venue"
},
  "geometry": {"coordinates":[4.4921851158,51.7975234985],"type":"Point"}
}