{
  "type": "Feature",
  "properties": {
    "addr:full":"Galerij 2 Oss Noord-Brabant 5341 CL",
    "addr:housenumber":"2",
    "addr:postcode":"5341",
    "addr:street":"Galerij",
    "iso:country":"NL",
    "sg:address":"Galerij 2",
    "sg:city":"Oss",
    "sg:classifiers":[
        {
            "category":"Shopping",
            "subcategory":"Gifts & Souvenirs",
            "type":"Retail Goods"
        }
    ],
    "sg:phone":"+31 412 650 901",
    "sg:postcode":"5341 CL",
    "sg:province":"Noord-Brabant",
    "sg:tags":[
        "geschenken"
    ],
    "wof:name":"Kadoshop Pardoes",
    "wof:placetype":"venue"
},
  "geometry": {"coordinates":[-77.235214,38.312599],"type":"Point"}
}