{
  "type": "Feature",
  "properties": {
    "addr:full":"De Gruyterpassage 10 'S Hertogenbosch Noord-Brabant 5211 TS",
    "addr:housenumber":"10",
    "addr:postcode":"5211 ts",
    "addr:street":"De Gruyterpassage;' S",
    "iso:country":"NL",
    "sg:address":"De Gruyterpassage 10",
    "sg:city":"'S Hertogenbosch",
    "sg:orig_category":"Werving And Selectie Van Tijdelijk Personeel And Uitzendkantoren",
    "sg:phone":"+31 73 614 4545",
    "sg:postcode":"5211 TS",
    "sg:province":"Noord-Brabant",
    "wof:name":"Starjob Secretaresse Uitzendbureau",
    "wof:placetype":"venue"
},
  "geometry": {"coordinates":[5.3007798195,51.6908836365],"type":"Point"}
}