{
  "type": "Feature",
  "properties": {
    "addr:full":"Ruijsdaelplein 35 Naarden Noord-Holland 1411 RD",
    "addr:housenumber":"35",
    "addr:postcode":"1411 rd",
    "addr:street":"Ruijsdaelplein",
    "iso:country":"NL",
    "sg:address":"Ruijsdaelplein 35",
    "sg:city":"Naarden",
    "sg:orig_category":"Public Relationbureaus",
    "sg:phone":"+31 35 695 0062",
    "sg:postcode":"1411 RD",
    "sg:province":"Noord-Holland",
    "wof:name":"Weaver & Partners Public Relations",
    "wof:placetype":"venue"
},
  "geometry": {"coordinates":[5.165661,52.295959],"type":"Point"}
}