{
  "type": "Feature",
  "properties": {
    "addr:full":"Raadhuisplein 54 Krimpen A/D Ijssel South Holland 2922 AG",
    "addr:housenumber":"54;a / d",
    "addr:postcode":"2922",
    "addr:street":"Raadhuisplein;Ijssel South",
    "iso:country":"NL",
    "sg:address":"Raadhuisplein 54",
    "sg:city":"Krimpen A/D Ijssel",
    "sg:orig_category":"Verlichting And Huishoudartikelen",
    "sg:phone":"+31 180 590 854",
    "sg:postcode":"2922 AG",
    "sg:province":"South Holland",
    "wof:name":"Marskramer",
    "wof:placetype":"venue"
},
  "geometry": {"coordinates":[4.59042,51.914471],"type":"Point"}
}