{
  "type": "Feature",
  "properties": {
    "iso:country":"NL",
    "sg:address":"Vondellaan 10",
    "sg:city":"Hazerswoude Rijndijk",
    "sg:orig_category":"Politie",
    "sg:phone":"+31 900 8844",
    "sg:postcode":"2394 EA",
    "sg:province":"Zuid-Holland",
    "wof:name":"Regio Politie Hollands Midden Locatie Rijnwoude Zo",
    "wof:placetype":"venue"
},
  "geometry": {"coordinates":[4.590157,52.129856],"type":"Point"}
}