{
  "type": "Feature",
  "properties": {
    "addr:full":"Postbus 58119 Amsterdam North Holland 1040 HC",
    "addr:postcode":"58119;1040 hc",
    "addr:street":"Postbus",
    "iso:country":"NL",
    "sg:address":"Postbus 58119",
    "sg:city":"Amsterdam",
    "sg:orig_category":"Bedrijfsorganisaties",
    "sg:phone":"+31 20 670 4353",
    "sg:postcode":"1040 HC",
    "sg:province":"North Holland",
    "sg:website":"http://www.tiar-group.nl",
    "wof:name":"Tiar-Group",
    "wof:placetype":"venue"
},
  "geometry": {"coordinates":[4.89205,52.37355],"type":"Point"}
}