{
  "type": "Feature",
  "properties": {
    "iso:country":"NL",
    "sg:address":"Paltzerwg 79",
    "sg:city":"Bilthoven",
    "sg:orig_category":"Adviesbureaus Bedrijfsorganisatie",
    "sg:phone":"+31 6 55780479",
    "sg:postcode":"3722 JC",
    "sg:province":"Utrecht",
    "wof:name":"Gunther Bv",
    "wof:placetype":"venue"
},
  "geometry": {"coordinates":[5.224194,52.135048],"type":"Point"}
}