{
  "type": "Feature",
  "properties": {
    "addr:full":"Burgemeester Colijnweg 2 Amstelveen North Holland 1182 AL",
    "addr:housenumber":"2",
    "addr:postcode":"1182 al",
    "addr:street":"Burgemeester Colijnweg",
    "iso:country":"NL",
    "sg:address":"Burgemeester Colijnweg 2",
    "sg:city":"Amstelveen",
    "sg:classifiers":[
        {
            "category":"Professional",
            "subcategory":"Accounting & Tax Preparation",
            "type":"Services"
        }
    ],
    "sg:phone":"+31 20 545 6121",
    "sg:postcode":"1182 AL",
    "sg:province":"North Holland",
    "sg:tags":[
        "accountant"
    ],
    "wof:name":"Swart & Co Accountants",
    "wof:placetype":"venue"
},
  "geometry": {"coordinates":[4.845722,52.303516],"type":"Point"}
}