{
  "type": "Feature",
  "properties": {
    "iso:country":"NL",
    "sg:address":"Roggelsewg 9",
    "sg:city":"Haelen",
    "sg:orig_category":"Verlichting",
    "sg:phone":"+31 475 591 703",
    "sg:postcode":"6081 CR",
    "sg:province":"Limburg",
    "wof:name":"Bex Elektro",
    "wof:placetype":"venue"
},
  "geometry": {"coordinates":[5.955317,51.236305],"type":"Point"}
}