{
  "type": "Feature",
  "properties": {
    "addr:full":"Bramenberg 17 Eemnes Utrecht 3755 BV",
    "addr:housenumber":"17",
    "addr:postcode":"3755 bv",
    "addr:street":"Bramenberg",
    "iso:country":"NL",
    "sg:address":"Bramenberg 17",
    "sg:city":"Eemnes",
    "sg:orig_category":"Woninginrichting- Fournituren - Fabrieken En Groothandel",
    "sg:phone":"+31 35 538 9740",
    "sg:postcode":"3755 BV",
    "sg:province":"Utrecht",
    "wof:name":"Viool Traditions",
    "wof:placetype":"venue"
},
  "geometry": {"coordinates":[5.2500200272,52.2480278015],"type":"Point"}
}