{
  "type": "Feature",
  "properties": {
    "addr:full":"Vinkebuurt 48 Zwammerdam Zuid-Holland 2471 XC",
    "addr:housenumber":"48",
    "addr:postcode":"2471 xc",
    "addr:street":"Vinkebuurt",
    "iso:country":"NL",
    "sg:address":"Vinkebuurt 48",
    "sg:city":"Zwammerdam",
    "sg:orig_category":"Oud Metaal",
    "sg:phone":"+31 172 613 069",
    "sg:postcode":"2471 XC",
    "sg:province":"Zuid-Holland",
    "wof:name":"Schip, H P Van",
    "wof:placetype":"venue"
},
  "geometry": {"coordinates":[4.7254772186,52.1072845459],"type":"Point"}
}