{
  "type": "Feature",
  "properties": {
    "addr:full":"Ms Oslofjordwg 8A Amsterdam Noord-Holland 1033 SM",
    "addr:housenumber":"8a",
    "addr:postcode":"1033 sm",
    "iso:country":"NL",
    "sg:address":"Ms Oslofjordwg 8A",
    "sg:city":"Amsterdam",
    "sg:orig_category":"Autopoetsbedrijven",
    "sg:phone":"+31 75 771 6233",
    "sg:postcode":"1033 SM",
    "sg:province":"Noord-Holland",
    "wof:name":"Uniek",
    "wof:placetype":"venue"
},
  "geometry": {"coordinates":[4.891732,52.403633],"type":"Point"}
}