{
  "type": "Feature",
  "properties": {
    "addr:full":"Zuidplaspolderwg 4 Moordrecht South Holland 2841 DD",
    "addr:housenumber":"4",
    "addr:postcode":"2841 dd",
    "addr:street":"Zuidplaspolderwg",
    "iso:country":"NL",
    "sg:address":"Zuidplaspolderwg 4",
    "sg:city":"Moordrecht",
    "sg:orig_category":"Bedrijfsopleidingen",
    "sg:phone":"+31 182 376 322",
    "sg:postcode":"2841 DD",
    "sg:province":"South Holland",
    "wof:name":"K & K Bv",
    "wof:placetype":"venue"
},
  "geometry": {"coordinates":[4.670607,51.993332],"type":"Point"}
}