{
  "type": "Feature",
  "properties": {
    "addr:full":"E Mulderweg 2 Wedde Groningen 9698 PH",
    "addr:housenumber":"2",
    "addr:postcode":"9698",
    "addr:street":"E Mulderweg",
    "iso:country":"NL",
    "sg:address":"E Mulderweg 2",
    "sg:city":"Wedde",
    "sg:orig_category":"Verzekeringen",
    "sg:phone":"+31 597 562 674",
    "sg:postcode":"9698 PH",
    "sg:province":"Groningen",
    "wof:name":"Assurantie- En Adviesburo Harry Wolf",
    "wof:placetype":"venue"
},
  "geometry": {"coordinates":[7.070294,53.08633],"type":"Point"}
}