{
  "type": "Feature",
  "properties": {
    "iso:country":"NL",
    "sg:address":"Achter De Vismarkt 74",
    "sg:city":"Gouda",
    "sg:orig_category":"Vertaal- And Tolkenbureaus",
    "sg:phone":"+31 182 548 739",
    "sg:postcode":"2801 ND",
    "sg:province":"South Holland",
    "wof:name":"Vertaalbureau Fases",
    "wof:placetype":"venue"
},
  "geometry": {"coordinates":[4.708538,52.010433],"type":"Point"}
}