{
  "type": "Feature",
  "properties": {
    "addr:full":"Groenhof 115 Amstelveen Noord-Holland 1186 EX",
    "addr:housenumber":"115",
    "addr:postcode":"1186 ex",
    "addr:street":"Groenhof",
    "iso:country":"NL",
    "sg:address":"Groenhof 115",
    "sg:city":"Amstelveen",
    "sg:orig_category":"Cafetaria'S",
    "sg:phone":"+31 20 441 6731",
    "sg:postcode":"1186 EX",
    "sg:province":"Noord-Holland",
    "wof:name":"Vork",
    "wof:placetype":"venue"
},
  "geometry": {"coordinates":[4.870091,52.289486],"type":"Point"}
}