{
  "type": "Feature",
  "properties": {
    "iso:country":"NL",
    "sg:address":"Mr J B Kanw 5",
    "sg:city":"Witteveen",
    "sg:orig_category":"Land- En Tuinbouw - Loonbedrijven",
    "sg:phone":"+31 593 322 208",
    "sg:postcode":"9439 TD",
    "sg:province":"Provincie Drenthe",
    "wof:name":"Meijer, H",
    "wof:placetype":"venue"
},
  "geometry": {"coordinates":[6.66047,52.81424],"type":"Point"}
}