{
  "type": "Feature",
  "properties": {
    "iso:country":"NL",
    "sg:address":"Bittervoorn 13",
    "sg:city":"Krommenie",
    "sg:orig_category":"Verbouwingen",
    "sg:phone":"+31 75 622 7626",
    "sg:postcode":"1562 KG",
    "sg:province":"Noord-Holland",
    "wof:name":"Vries, R C De",
    "wof:placetype":"venue"
},
  "geometry": {"coordinates":[4.775202,52.506203],"type":"Point"}
}