{
  "type": "Feature",
  "properties": {
    "addr:full":"Hofstraat 155 Doetinchem Gelderland 7001 JD",
    "addr:housenumber":"155",
    "addr:postcode":"7001 jd",
    "addr:street":"Hofstraat;Gelderland",
    "iso:country":"NL",
    "sg:address":"Hofstraat 155",
    "sg:city":"Doetinchem",
    "sg:orig_category":"Bioscopen",
    "sg:phone":"+31 314 390 100",
    "sg:postcode":"7001 JD",
    "sg:province":"Gelderland",
    "wof:name":"Cine City",
    "wof:placetype":"venue"
},
  "geometry": {"coordinates":[6.29261,51.97084],"type":"Point"}
}