{
  "type": "Feature",
  "properties": {
    "addr:full":"Schapenland 16 Velserbroek Noord-Holland 1991 CV",
    "addr:housenumber":"16",
    "addr:postcode":"1991 cv",
    "addr:street":"Schapenland",
    "iso:country":"NL",
    "sg:address":"Schapenland 16",
    "sg:city":"Velserbroek",
    "sg:orig_category":"Schilderwerk",
    "sg:phone":"+31 23 538 5286",
    "sg:postcode":"1991 CV",
    "sg:province":"Noord-Holland",
    "wof:name":"Andre Molenaar",
    "wof:placetype":"venue"
},
  "geometry": {"coordinates":[4.658859,52.437321],"type":"Point"}
}