{
  "type": "Feature",
  "properties": {
    "addr:full":"Rijersstraat 18 Helmond Noord-Brabant 5708 KP",
    "addr:housenumber":"18",
    "addr:postcode":"5708 kp",
    "addr:street":"Rijersstraat",
    "iso:country":"NL",
    "sg:address":"Rijersstraat 18",
    "sg:city":"Helmond",
    "sg:classifiers":[
        {
            "category":"Shopping",
            "subcategory":"Clothing, Apparel, & Fashions",
            "type":"Retail Goods"
        }
    ],
    "sg:phone":"+31 492 539 854",
    "sg:postcode":"5708 KP",
    "sg:province":"Noord-Brabant",
    "sg:tags":[
        "ondergoed",
        "lingerie"
    ],
    "wof:name":"Tres Chique",
    "wof:placetype":"venue"
},
  "geometry": {"coordinates":[5.616145,51.491848],"type":"Point"}
}