{
  "type": "Feature",
  "properties": {
    "addr:full":"Industrieweg 12 Zevenbergen Noord-Brabant 4762 AE",
    "addr:housenumber":"12",
    "addr:postcode":"4762 ae",
    "addr:street":"Industrieweg",
    "iso:country":"NL",
    "sg:address":"Industrieweg 12",
    "sg:city":"Zevenbergen",
    "sg:orig_category":"Huizensloop And Bouwrijp Maken",
    "sg:phone":"+31 168 324 879",
    "sg:postcode":"4762 AE",
    "sg:province":"Noord-Brabant",
    "wof:name":"Aannemersbedrijf A.A. Ooijen",
    "wof:placetype":"venue"
},
  "geometry": {"coordinates":[4.615305,51.643322],"type":"Point"}
}