{
  "type": "Feature",
  "properties": {
    "iso:country":"NL",
    "sg:address":"Industrieweg 12",
    "sg:city":"Zevenbergen",
    "sg:orig_category":"Huizensloop And Bouwrijp Maken",
    "sg:phone":"+31 168 324 879",
    "sg:postcode":"4762 AE",
    "sg:province":"Noord-Brabant",
    "wof:name":"Aannemersbedrijf A.A. Ooijen",
    "wof:placetype":"venue"
},
  "geometry": {"coordinates":[4.615305,51.643322],"type":"Point"}
}