{
  "type": "Feature",
  "properties": {
    "addr:full":"Museumstraat 6 Groningen Groningen 9711 HS",
    "addr:housenumber":"6",
    "addr:postcode":"9711 hs",
    "addr:street":"Museumstraat",
    "iso:country":"NL",
    "sg:address":"Museumstraat 6",
    "sg:city":"Groningen",
    "sg:orig_category":"Diverse Grafische Activiteiten",
    "sg:phone":"+31 50 313 0271",
    "sg:postcode":"9711 HS",
    "sg:province":"Groningen",
    "wof:name":"E Ensing",
    "wof:placetype":"venue"
},
  "geometry": {"coordinates":[6.560155,53.215168],"type":"Point"}
}