{
  "type": "Feature",
  "properties": {
    "addr:full":"Prof Gimbrereln 143 Tilburg North Brabant 5037 EJ",
    "addr:housenumber":"143",
    "addr:postcode":"5037 ej",
    "iso:country":"NL",
    "sg:address":"Prof Gimbrereln 143",
    "sg:city":"Tilburg",
    "sg:orig_category":"Kappers",
    "sg:phone":"+31 13 463 4631",
    "sg:postcode":"5037 EJ",
    "sg:province":"North Brabant",
    "wof:name":"Nabbe, H M",
    "wof:placetype":"venue"
},
  "geometry": {"coordinates":[5.050876,51.559631],"type":"Point"}
}