{
  "type": "Feature",
  "properties": {
    "addr:full":"Dorpsstr 130 Winkel Illinois 1731 RK",
    "addr:housenumber":"130",
    "addr:postcode":"1731 rk",
    "iso:country":"NL",
    "sg:address":"Dorpsstr 130",
    "sg:city":"Winkel",
    "sg:orig_category":"Fotoreportages",
    "sg:phone":"+31 224 541 698",
    "sg:postcode":"1731 RK",
    "sg:province":"Illinois",
    "wof:name":"John Oud",
    "wof:placetype":"venue"
},
  "geometry": {"coordinates":[-89.62237500000001,40.348873],"type":"Point"}
}