{
  "type": "Feature",
  "properties": {
    "addr:full":"Achter Het Vleeshuis 36 Maastricht Limburg 6211 GS",
    "addr:housenumber":"36",
    "addr:postcode":"6211 gs",
    "addr:street":"Achter Het Vleeshuis",
    "iso:country":"NL",
    "sg:address":"Achter Het Vleeshuis 36",
    "sg:city":"Maastricht",
    "sg:orig_category":"Damesmodezaken",
    "sg:phone":"+31 43 321 2541",
    "sg:postcode":"6211 GS",
    "sg:province":"Limburg",
    "wof:name":"Modehuis Elegance Pia",
    "wof:placetype":"venue"
},
  "geometry": {"coordinates":[5.691075,50.849194],"type":"Point"}
}