{
  "type": "Feature",
  "properties": {
    "addr:full":"Broekstr 9 Neerkant Noord-Brabant 5758 BG",
    "addr:housenumber":"9",
    "addr:postcode":"5758",
    "addr:street":"Broekstr",
    "iso:country":"NL",
    "sg:address":"Broekstr 9",
    "sg:city":"Neerkant",
    "sg:orig_category":"Artiesten/Gezelschappen",
    "sg:phone":"+31 77 466 1692",
    "sg:postcode":"5758 BG",
    "sg:province":"Noord-Brabant",
    "wof:name":"Zwei D\u00f7Rfer, Die",
    "wof:placetype":"venue"
},
  "geometry": {"coordinates":[5.865585,51.372864],"type":"Point"}
}