{
  "type": "Feature",
  "properties": {
    "iso:country":"NL",
    "sg:address":"Moerbergplnts 22",
    "sg:city":"Ymuiden",
    "sg:orig_category":"Verenigingen En Stichtingen",
    "sg:phone":"+31 255 522 822",
    "sg:postcode":"1972 XG",
    "sg:province":"Noord-Holland",
    "wof:name":"Vluchtelingenwerk Velsen, Sticht",
    "wof:placetype":"venue"
},
  "geometry": {"coordinates":[4.61762,52.458302],"type":"Point"}
}