{
  "type": "Feature",
  "properties": {
    "iso:country":"NL",
    "sg:address":"Albrechtshof 4",
    "sg:city":"Zevenhoven",
    "sg:classifiers":[
        {
            "category":"Bakery",
            "type":"Food & Drink"
        }
    ],
    "sg:phone":"+31 172 539 636",
    "sg:postcode":"2435 WZ",
    "sg:province":"Zuid-Holland",
    "sg:tags":[
        "brood",
        "banket"
    ],
    "wof:name":"P. De Kruijf En Zonen",
    "wof:placetype":"venue"
},
  "geometry": {"coordinates":[4.780547,52.182735],"type":"Point"}
}