{
  "type": "Feature",
  "properties": {
    "addr:full":"Zeeburgerpad 23 Amsterdam Noord-Holland 1018 AH",
    "addr:housenumber":"23",
    "addr:postcode":"1018 ah",
    "addr:street":"Zeeburgerpad",
    "iso:country":"NL",
    "sg:address":"Zeeburgerpad 23",
    "sg:city":"Amsterdam",
    "sg:orig_category":"Hout Gh",
    "sg:phone":"+31 20 665 0416",
    "sg:postcode":"1018 AH",
    "sg:province":"Noord-Holland",
    "wof:name":"Jongevos Houthandel Bv",
    "wof:placetype":"venue"
},
  "geometry": {"coordinates":[4.930813,52.366955],"type":"Point"}
}