{
  "type": "Feature",
  "properties": {
    "iso:country":"NL",
    "sg:address":"Lisztstraat 7",
    "sg:city":"Alkmaar",
    "sg:orig_category":"Boekenuitgeverijen",
    "sg:phone":"+31 72 511 7628",
    "sg:postcode":"1817 HH",
    "sg:province":"Noord-Holland",
    "wof:name":"Uitgeverij Leon Schuijt",
    "wof:placetype":"venue"
},
  "geometry": {"coordinates":[4.734166,52.643574],"type":"Point"}
}