{
  "type": "Feature",
  "properties": {
    "addr:full":"Repensestr 27 Opynen Gelderland 4184 CE",
    "addr:housenumber":"27",
    "addr:postcode":"4184 ce",
    "addr:street":"Repensestr;Gelderland",
    "iso:country":"NL",
    "sg:address":"Repensestr 27",
    "sg:city":"Opynen",
    "sg:orig_category":"Adviesbureaus Bedrijfsorganisatie",
    "sg:phone":"+31 418 652 587",
    "sg:postcode":"4184 CE",
    "sg:province":"Gelderland",
    "wof:name":"Feitsema",
    "wof:placetype":"venue"
},
  "geometry": {"coordinates":[5.296043,51.829937],"type":"Point"}
}