{
  "type": "Feature",
  "properties": {
    "addr:full":"Linnausweg 12 Ijsselstein (Ut) Utrecht 3401 MS",
    "addr:housenumber":"12",
    "addr:postcode":"3401 ms",
    "addr:street":"Linnausweg",
    "iso:country":"NL",
    "sg:address":"Linnausweg 12",
    "sg:city":"Ijsselstein (Ut)",
    "sg:orig_category":"Glaszetten",
    "sg:phone":"+31 30 687 5650",
    "sg:postcode":"3401 MS",
    "sg:province":"Utrecht",
    "wof:name":"Glasservice Ijsselstein",
    "wof:placetype":"venue"
},
  "geometry": {"coordinates":[5.054347,52.017029],"type":"Point"}
}