{
  "type": "Feature",
  "properties": {
    "addr:full":"Wilhelminastraat 4 Angeren Gelderland 6687 BA",
    "addr:housenumber":"4",
    "addr:postcode":"6687 ba",
    "addr:street":"Wilhelminastraat;Gelderland",
    "iso:country":"NL",
    "sg:address":"Wilhelminastraat 4",
    "sg:city":"Angeren",
    "sg:classifiers":[
        {
            "category":"Education",
            "subcategory":"Preschool",
            "type":"Public Place"
        }
    ],
    "sg:phone":"+31 26 325 4291",
    "sg:postcode":"6687 BA",
    "sg:province":"Gelderland",
    "sg:tags":[
        "kleuteronderwijs",
        "basis-"
    ],
    "wof:name":"Peuterspeelzaal Pinkeltje",
    "wof:placetype":"venue"
},
  "geometry": {"coordinates":[5.956154,51.915211],"type":"Point"}
}