{
  "type": "Feature",
  "properties": {
    "iso:country":"NL",
    "sg:address":"Donauring 150",
    "sg:city":"Drunen",
    "sg:orig_category":"Bedrijfs- And Managementsconsultants",
    "sg:phone":"+31 416 379 760",
    "sg:postcode":"5152 TD",
    "sg:province":"Noord-Brabant",
    "wof:name":"Prima!",
    "wof:placetype":"venue"
},
  "geometry": {"coordinates":[5.119522,51.679218],"type":"Point"}
}