{
  "type": "Feature",
  "properties": {
    "addr:full":"Papaverwg 29B Amsterdam Noord-Holland 1032 KE",
    "addr:housenumber":"29b",
    "addr:postcode":"1032 ke",
    "addr:street":"Papaverwg",
    "iso:country":"NL",
    "sg:address":"Papaverwg 29B",
    "sg:city":"Amsterdam",
    "sg:orig_category":"Maquettes",
    "sg:phone":"+31 20 435 0050",
    "sg:postcode":"1032 KE",
    "sg:province":"Noord-Holland",
    "wof:name":"Artitec Bv",
    "wof:placetype":"venue"
},
  "geometry": {"coordinates":[4.909307,52.395123],"type":"Point"}
}