{
  "type": "Feature",
  "properties": {
    "iso:country":"NL",
    "sg:address":"Engelsholm 10",
    "sg:city":"Hoofddorp",
    "sg:orig_category":"Daken And Skeletbouw",
    "sg:phone":"+31 23 562 9465",
    "sg:postcode":"2133 AG",
    "sg:province":"Noord-Holland",
    "wof:name":"Catsburg Engineering",
    "wof:placetype":"venue"
},
  "geometry": {"coordinates":[4.677977,52.313057],"type":"Point"}
}