{
  "type": "Feature",
  "properties": {
    "addr:full":"C Salomonln 8 Pynacker South Holland 2642 CT",
    "addr:housenumber":"8",
    "addr:postcode":"2642 ct",
    "addr:street":"Pynacker South",
    "iso:country":"NL",
    "sg:address":"C Salomonln 8",
    "sg:city":"Pynacker",
    "sg:orig_category":"Sportverenigingen En Ontspannings- Verenigingen",
    "sg:phone":"+31 15 369 6979",
    "sg:postcode":"2642 CT",
    "sg:province":"South Holland",
    "wof:name":"Hallelujah Chr Gemengde Zangver",
    "wof:placetype":"venue"
},
  "geometry": {"coordinates":[4.45025,52.008888],"type":"Point"}
}