{
  "type": "Feature",
  "properties": {
    "addr:full":"Grevensweg 8 Doornspijk Gelderland 8085 PZ",
    "addr:housenumber":"8",
    "addr:postcode":"8085 pz",
    "addr:street":"Grevensweg;Gelderland",
    "iso:country":"NL",
    "sg:address":"Grevensweg 8",
    "sg:city":"Doornspijk",
    "sg:orig_category":"Boekhandels",
    "sg:phone":"+31 525 661 822",
    "sg:postcode":"8085 PZ",
    "sg:province":"Gelderland",
    "wof:name":"De Uithoek",
    "wof:placetype":"venue"
},
  "geometry": {"coordinates":[5.826343,52.409386],"type":"Point"}
}