{
  "type": "Feature",
  "properties": {
    "iso:country":"NL",
    "sg:address":"Voltawg 32",
    "sg:city":"Bunschoten Spakenb",
    "sg:orig_category":"Bedrijfs- En Werkplaats- Inrichtingen",
    "sg:phone":"+31 33 298 8122",
    "sg:postcode":"3752 LP",
    "sg:province":"Utrecht",
    "sg:website":"http://www.lebon.nl",
    "wof:name":"Lebon & Gimbrair Bv",
    "wof:placetype":"venue"
},
  "geometry": {"coordinates":[5.35884,52.229359],"type":"Point"}
}