{
  "type": "Feature",
  "properties": {
    "iso:country":"NL",
    "sg:address":"Koornmarkt 89",
    "sg:city":"Delft",
    "sg:orig_category":"Metaalwerken",
    "sg:phone":"+31 15 212 4273",
    "sg:postcode":"2611 ED",
    "sg:province":"Zuid-Holland",
    "wof:name":"Vof Van Witteloostuyn",
    "wof:placetype":"venue"
},
  "geometry": {"coordinates":[4.358347,52.009876],"type":"Point"}
}