{
  "type": "Feature",
  "properties": {
    "addr:full":"Beethovenstraat 69 Amsterdam North Holland 1077 HP",
    "addr:housenumber":"69",
    "addr:postcode":"1077 hp",
    "addr:street":"Beethovenstraat",
    "iso:country":"NL",
    "sg:address":"Beethovenstraat 69",
    "sg:city":"Amsterdam",
    "sg:orig_category":"Zuivelproducten",
    "sg:phone":"+31 20 679 9037",
    "sg:postcode":"1077 HP",
    "sg:province":"North Holland",
    "wof:name":"Tromp Kaas",
    "wof:placetype":"venue"
},
  "geometry": {"coordinates":[4.877179,52.347301],"type":"Point"}
}