{
  "type": "Feature",
  "properties": {
    "addr:full":"Postbus 40133 Enschede Gelderland 7504 RC",
    "addr:housenumber":"40133",
    "addr:postcode":"7504 rc",
    "addr:street":"Postbus;Gelderland",
    "iso:country":"NL",
    "sg:address":"Postbus 40133",
    "sg:city":"Enschede",
    "sg:orig_category":"Begrafenisverzorging",
    "sg:phone":"+31 53 477 9938",
    "sg:postcode":"7504 RC",
    "sg:province":"Gelderland",
    "wof:name":"Barbara, Ver St",
    "wof:placetype":"venue"
},
  "geometry": {"coordinates":[6.89112,52.220821],"type":"Point"}
}