{
  "type": "Feature",
  "properties": {
    "addr:full":"Postbus 242 Beilen Provincie Drenthe 9410 AE",
    "addr:housenumber":"242",
    "addr:postcode":"9410 ae",
    "addr:street":"Postbus;Provincie Drenthe",
    "iso:country":"NL",
    "sg:address":"Postbus 242",
    "sg:city":"Beilen",
    "sg:orig_category":"Verzekeringen - Verzekeringskantoren",
    "sg:phone":"+31 593 541 130",
    "sg:postcode":"9410 AE",
    "sg:province":"Provincie Drenthe",
    "wof:name":"Slofstra Vof",
    "wof:placetype":"venue"
},
  "geometry": {"coordinates":[6.51571,52.857861],"type":"Point"}
}