{
  "type": "Feature",
  "properties": {
    "addr:full":"Leutherwg 31A Venlo Limburg 5915 CA",
    "addr:housenumber":"31a",
    "addr:postcode":"5915 ca",
    "addr:street":"Leutherwg",
    "iso:country":"NL",
    "sg:address":"Leutherwg 31A",
    "sg:city":"Venlo",
    "sg:orig_category":"Kappers",
    "sg:phone":"+31 77 351 3754",
    "sg:postcode":"5915 CA",
    "sg:province":"Limburg",
    "wof:name":"All Style Hair Salon",
    "wof:placetype":"venue"
},
  "geometry": {"coordinates":[6.1819710732,51.3588294983],"type":"Point"}
}