{
  "type": "Feature",
  "properties": {
    "iso:country":"NL",
    "sg:address":"Saxenrodeweg 58",
    "sg:city":"Bentveld",
    "sg:orig_category":"Verzekeringen",
    "sg:phone":"+31 23 524 1596",
    "sg:postcode":"2116 VC",
    "sg:province":"North Holland",
    "wof:name":"J.R. Everts Insurance Research Consultancy",
    "wof:placetype":"venue"
},
  "geometry": {"coordinates":[4.57181,52.367207],"type":"Point"}
}