{
  "type": "Feature",
  "properties": {
    "addr:full":"Ruurloseweg 79 Hengelo Gld Gelderland 7255 MA",
    "addr:housenumber":"79",
    "addr:postcode":"7255 ma",
    "addr:street":"Ruurloseweg",
    "iso:country":"NL",
    "sg:address":"Ruurloseweg 79",
    "sg:city":"Hengelo Gld",
    "sg:orig_category":"Pluimveehouderijen",
    "sg:phone":"+31 575 463 420",
    "sg:postcode":"7255 MA",
    "sg:province":"Gelderland",
    "wof:name":"W. Ten Pas",
    "wof:placetype":"venue"
},
  "geometry": {"coordinates":[6.341814,52.06097],"type":"Point"}
}