{
  "type": "Feature",
  "properties": {
    "addr:full":"Emmalaan 3 Wognum Noord-Holland 1687 BB",
    "addr:housenumber":"3",
    "addr:postcode":"1687 bb",
    "addr:street":"Emmalaan",
    "iso:country":"NL",
    "sg:address":"Emmalaan 3",
    "sg:city":"Wognum",
    "sg:orig_category":"Bedrijfs- And Managementsconsultants",
    "sg:phone":"+31 229 573 720",
    "sg:postcode":"1687 BB",
    "sg:province":"Noord-Holland",
    "wof:name":"His Wilms Consult",
    "wof:placetype":"venue"
},
  "geometry": {"coordinates":[5.027952,52.682251],"type":"Point"}
}