{
  "type": "Feature",
  "properties": {
    "iso:country":"NL",
    "sg:address":"Ridderhof 93",
    "sg:city":"Ridderkerk",
    "sg:orig_category":"Postkantoren",
    "sg:phone":"+31 180 432 344",
    "sg:postcode":"2981 ET",
    "sg:province":"Zuid-Holland",
    "sg:website":"http://www.postkantoor.nl",
    "wof:name":"Postkantoor",
    "wof:placetype":"venue"
},
  "geometry": {"coordinates":[4.59851,51.869762],"type":"Point"}
}