{
  "type": "Feature",
  "properties": {
    "addr:full":"Domeinenstr 3 Mill Noord-Brabant 5451 AD",
    "addr:housenumber":"3",
    "addr:postcode":"5451 ad",
    "addr:street":"Domeinenstr",
    "iso:country":"NL",
    "sg:address":"Domeinenstr 3",
    "sg:city":"Mill",
    "sg:classifiers":[
        {
            "category":"Home & Garden",
            "subcategory":"Garden Supply",
            "type":"Retail Goods"
        }
    ],
    "sg:phone":"+31 485 451 626",
    "sg:postcode":"5451 AD",
    "sg:province":"Noord-Brabant",
    "sg:tags":[
        "zand",
        "en",
        "grind"
    ],
    "wof:name":"Coenen En Zn, Fa G",
    "wof:placetype":"venue"
},
  "geometry": {"coordinates":[-88.40593699999999,31.767021],"type":"Point"}
}