{
  "type": "Feature",
  "properties": {
    "addr:full":"Gelderselaan 9K Nijmegen Gelderland 6523 LJ",
    "addr:housenumber":"9k;lj",
    "addr:postcode":"6523",
    "addr:street":"Gelderselaan;Gelderland",
    "iso:country":"NL",
    "sg:address":"Gelderselaan 9K",
    "sg:city":"Nijmegen",
    "sg:orig_category":"Marketingbureaus",
    "sg:phone":"+31 24 350 3064",
    "sg:postcode":"6523 LJ",
    "sg:province":"Gelderland",
    "sg:website":"http://www.ecer.nl",
    "wof:name":"Ecer Cv",
    "wof:placetype":"venue"
},
  "geometry": {"coordinates":[5.876531,51.83139],"type":"Point"}
}