{
  "type": "Feature",
  "properties": {
    "iso:country":"NL",
    "sg:address":"Lange Voorhout 86",
    "sg:city":"'S Gravenhage",
    "sg:orig_category":"Parfum And Cosmetica Gh",
    "sg:phone":"+31 70 361 5996",
    "sg:postcode":"2514 EJ",
    "sg:province":"South Holland",
    "wof:name":"Guerlain Benelux Sa",
    "wof:placetype":"venue"
},
  "geometry": {"coordinates":[4.31455,52.083122],"type":"Point"}
}