{
  "type": "Feature",
  "properties": {
    "addr:full":"Hoogstr 103 Utrecht Utrecht 3552 XL",
    "addr:housenumber":"103",
    "addr:postcode":"3552 xl",
    "iso:country":"NL",
    "sg:address":"Hoogstr 103",
    "sg:city":"Utrecht",
    "sg:orig_category":"Horecabenodigdheden",
    "sg:phone":"+31 30 262 8679",
    "sg:postcode":"3552 XL",
    "sg:province":"Utrecht",
    "sg:website":"http://www.kirpensteijn.nl",
    "wof:name":"Kirpensteijn Bv, W",
    "wof:placetype":"venue"
},
  "geometry": {"coordinates":[5.109644,52.107265],"type":"Point"}
}