{
  "type": "Feature",
  "properties": {
    "addr:full":"Edisonweg 21 Gorinchem Zuid-Holland 4207 HE",
    "addr:housenumber":"21",
    "addr:postcode":"4207 he",
    "addr:street":"Edisonweg",
    "iso:country":"NL",
    "sg:address":"Edisonweg 21",
    "sg:city":"Gorinchem",
    "sg:orig_category":"Fotografische And Optische Artikelen Gh",
    "sg:phone":"+31 183 697 501",
    "sg:postcode":"4207 HE",
    "sg:province":"Zuid-Holland",
    "wof:name":"International Optical Service Bv",
    "wof:placetype":"venue"
},
  "geometry": {"coordinates":[4.997179,51.843258],"type":"Point"}
}