{
  "type": "Feature",
  "properties": {
    "iso:country":"NL",
    "sg:address":"Berkelstr 49",
    "sg:city":"Amersfoort",
    "sg:orig_category":"Webdesign Bureaus",
    "sg:phone":"+31 33 465 6135",
    "sg:postcode":"3812 KB",
    "sg:province":"Utrecht",
    "sg:website":"http://www.parocom.nl",
    "wof:name":"Parocom Vof",
    "wof:placetype":"venue"
},
  "geometry": {"coordinates":[5.3643808365,52.1617736816],"type":"Point"}
}