{
  "type": "Feature",
  "properties": {
    "addr:full":"Papenpad 38 Zaandam Noord-Holland 1506 GS",
    "addr:housenumber":"38",
    "addr:postcode":"1506 gs",
    "addr:street":"Papenpad",
    "iso:country":"NL",
    "sg:address":"Papenpad 38",
    "sg:city":"Zaandam",
    "sg:classifiers":[
        {
            "category":"Personal",
            "subcategory":"Nail Salon",
            "type":"Services"
        }
    ],
    "sg:phone":"+31 75 616 5681",
    "sg:postcode":"1506 GS",
    "sg:province":"Noord-Holland",
    "sg:tags":[
        "pedicure"
    ],
    "wof:name":"Papeneijnd",
    "wof:placetype":"venue"
},
  "geometry": {"coordinates":[4.816053,52.447571],"type":"Point"}
}