{
  "type": "Feature",
  "properties": {
    "addr:full":"Wilgenln 4 Renswoude Utrecht 3927 AM",
    "addr:housenumber":"4",
    "addr:postcode":"3927",
    "addr:street":"Wilgenln",
    "iso:country":"NL",
    "sg:address":"Wilgenln 4",
    "sg:city":"Renswoude",
    "sg:orig_category":"Autorijscholen",
    "sg:phone":"+31 318 571 652",
    "sg:postcode":"3927 AM",
    "sg:province":"Utrecht",
    "wof:name":"Hartog, M Den",
    "wof:placetype":"venue"
},
  "geometry": {"coordinates":[5.541955,52.07402],"type":"Point"}
}