{
  "type": "Feature",
  "properties": {
    "iso:country":"NL",
    "sg:address":"Bloemhaven 8",
    "sg:city":"Vinkeveen",
    "sg:orig_category":"Bedrijfsopleidingen",
    "sg:phone":"+31 297 263 424",
    "sg:postcode":"3645 HK",
    "sg:province":"Utrecht",
    "wof:name":"Video Management Ned Bv",
    "wof:placetype":"venue"
},
  "geometry": {"coordinates":[4.932774,52.211807],"type":"Point"}
}