{
  "type": "Feature",
  "properties": {
    "addr:full":"Sarphatikd 20 Amsterdam North Holland 1017 WV",
    "addr:housenumber":"20",
    "addr:postcode":"1017 wv",
    "addr:street":"Sarphatikd",
    "iso:country":"NL",
    "sg:address":"Sarphatikd 20",
    "sg:city":"Amsterdam",
    "sg:orig_category":"Kunsthandel",
    "sg:phone":"+31 20 626 6174",
    "sg:postcode":"1017 WV",
    "sg:province":"North Holland",
    "wof:name":"Kleisen, Jacqueline",
    "wof:placetype":"venue"
},
  "geometry": {"coordinates":[4.893195,52.373119],"type":"Point"}
}