{
  "type": "Feature",
  "properties": {
    "addr:full":"Gasthuisstr 4 Tegelen Limburg 5931 NV",
    "addr:housenumber":"4",
    "addr:postcode":"5931 nv",
    "addr:street":"Gasthuisstr",
    "iso:country":"NL",
    "sg:address":"Gasthuisstr 4",
    "sg:city":"Tegelen",
    "sg:orig_category":"Opticiens",
    "sg:phone":"+31 77 373 1453",
    "sg:postcode":"5931 NV",
    "sg:province":"Limburg",
    "wof:name":"Janssen, Andr?",
    "wof:placetype":"venue"
},
  "geometry": {"coordinates":[6.1364030838,51.3424987793],"type":"Point"}
}