{
  "type": "Feature",
  "properties": {
    "iso:country":"NL",
    "sg:address":"Oostdijk 1",
    "sg:city":"Oud Beijerland",
    "sg:classifiers":[
        {
            "category":"Shopping",
            "subcategory":"Clothing, Apparel, & Fashions",
            "type":"Retail Goods"
        }
    ],
    "sg:phone":"+31 186 640 213",
    "sg:postcode":"3261 KB",
    "sg:province":"Zuid-Holland",
    "sg:tags":[
        "ondergoed",
        "lingerie"
    ],
    "wof:name":"Livera",
    "wof:placetype":"venue"
},
  "geometry": {"coordinates":[4.413275,51.826427],"type":"Point"}
}