{
  "type": "Feature",
  "properties": {
    "addr:full":"Loet 16 Schagen Noord-Holland 1741 BP",
    "addr:housenumber":"16",
    "addr:postcode":"1741 bp",
    "addr:street":"Loet",
    "iso:country":"NL",
    "sg:address":"Loet 16",
    "sg:city":"Schagen",
    "sg:orig_category":"Projectontwikkeling",
    "sg:phone":"+31 224 212 896",
    "sg:postcode":"1741 BP",
    "sg:province":"Noord-Holland",
    "wof:name":"Tromp Bv",
    "wof:placetype":"venue"
},
  "geometry": {"coordinates":[4.793595,52.785336],"type":"Point"}
}