{
  "type": "Feature",
  "properties": {
    "addr:full":"Hazeldonk 1818 Breda Noord-Brabant 4836 LM",
    "addr:housenumber":"1818",
    "addr:postcode":"breda;4836 lm",
    "addr:street":"Hazeldonk",
    "iso:country":"NL",
    "sg:address":"Hazeldonk 1818",
    "sg:city":"Breda",
    "sg:orig_category":"Koel- En Vrieshuizen",
    "sg:phone":"+31 76 596 3451",
    "sg:postcode":"4836 LM",
    "sg:province":"Noord-Brabant",
    "wof:name":"Arco",
    "wof:placetype":"venue"
},
  "geometry": {"coordinates":[9.816856,45.692623],"type":"Point"}
}