{
  "type": "Feature",
  "properties": {
    "addr:full":"Postbus 43 Papendrecht Zuid-Holland 3350 AA",
    "addr:housenumber":"43",
    "addr:postcode":"3350 aa",
    "addr:street":"Postbus",
    "iso:country":"NL",
    "sg:address":"Postbus 43",
    "sg:city":"Papendrecht",
    "sg:orig_category":"Baggerwerken",
    "sg:phone":"+31 78 696 9000",
    "sg:postcode":"3350 AA",
    "sg:province":"Zuid-Holland",
    "sg:website":"http://www.boskalis.com",
    "wof:name":"Koninklijke Boskalis Westminster Nv",
    "wof:placetype":"venue"
},
  "geometry": {"coordinates":[4.683685,51.826294],"type":"Point"}
}