{
  "type": "Feature",
  "properties": {
    "addr:full":"Ganker 48 Nibbixwoud Noord-Holland 1688 CT",
    "addr:housenumber":"48",
    "addr:postcode":"1688 ct",
    "addr:street":"Ganker",
    "iso:country":"NL",
    "sg:address":"Ganker 48",
    "sg:city":"Nibbixwoud",
    "sg:orig_category":"Banken And Kredietinstellingen",
    "sg:phone":"+31 229 572 526",
    "sg:postcode":"1688 CT",
    "sg:province":"Noord-Holland",
    "wof:name":"Postkantoor",
    "wof:placetype":"venue"
},
  "geometry": {"coordinates":[5.056705,52.692394],"type":"Point"}
}