{
  "type": "Feature",
  "properties": {
    "addr:full":"Normaln 52 Nieuwegein Utrecht 3438 ER",
    "addr:housenumber":"52",
    "addr:postcode":"3438 er",
    "addr:street":"Normaln",
    "iso:country":"NL",
    "sg:address":"Normaln 52",
    "sg:city":"Nieuwegein",
    "sg:orig_category":"Administratie- En Boekhoudkantoren",
    "sg:phone":"+31 30 687 8733",
    "sg:postcode":"3438 ER",
    "sg:province":"Utrecht",
    "wof:name":"Eijk Vof, Van",
    "wof:placetype":"venue"
},
  "geometry": {"coordinates":[5.0914430618,52.0441856384],"type":"Point"}
}