{
  "type": "Feature",
  "properties": {
    "addr:full":"Schaepmanlaan 103 Oss British Columbia 5344 BC",
    "addr:housenumber":"103",
    "addr:postcode":"5344 bc",
    "addr:street":"Schaepmanlaan",
    "iso:country":"NL",
    "sg:address":"Schaepmanlaan 103",
    "sg:city":"Oss",
    "sg:orig_category":"Zuivelproducten",
    "sg:phone":"+31 412 622 528",
    "sg:postcode":"5344 BC",
    "sg:province":"British Columbia",
    "wof:name":"De Mangerie",
    "wof:placetype":"venue"
},
  "geometry": {"coordinates":[-126.555511,54.485668],"type":"Point"}
}