{
  "type": "Feature",
  "properties": {
    "addr:full":"Vlijtseweg 176 Apeldoorn Gelderland 7317 AK",
    "addr:housenumber":"176",
    "addr:postcode":"7317 ak",
    "addr:street":"Vlijtseweg;Gelderland",
    "iso:country":"NL",
    "sg:address":"Vlijtseweg 176",
    "sg:city":"Apeldoorn",
    "sg:orig_category":"Fietshandelaren",
    "sg:phone":"+31 55 522 6272",
    "sg:postcode":"7317 AK",
    "sg:province":"Gelderland",
    "wof:name":"Han Maaskant Tweewielers",
    "wof:placetype":"venue"
},
  "geometry": {"coordinates":[5.972474,52.22971],"type":"Point"}
}