{
  "type": "Feature",
  "properties": {
    "addr:full":"Burg Reigerstr 77 Utrecht Utrecht 3581 KP",
    "addr:housenumber":"77",
    "addr:postcode":"3581 kp",
    "addr:street":"Burg",
    "iso:country":"NL",
    "sg:address":"Burg Reigerstr 77",
    "sg:city":"Utrecht",
    "sg:orig_category":"Advocaten En Advocatenkantoren",
    "sg:phone":"+31 30 233 3415",
    "sg:postcode":"3581 KP",
    "sg:province":"Utrecht",
    "sg:website":"http://www.b-ladvocaten.nl",
    "wof:name":"Brink & Luttikhuis, Van Den",
    "wof:placetype":"venue"
},
  "geometry": {"coordinates":[5.137062,52.088821],"type":"Point"}
}