{
  "type": "Feature",
  "properties": {
    "addr:full":"Prins Bernhardlaan 14 Bilthoven Utrecht 3722 AG",
    "addr:housenumber":"14",
    "addr:postcode":"3722",
    "addr:street":"Prins Bernhardlaan",
    "iso:country":"NL",
    "sg:address":"Prins Bernhardlaan 14",
    "sg:city":"Bilthoven",
    "sg:orig_category":"Vertaal- And Tolkenbureaus",
    "sg:phone":"+31 30 229 1866",
    "sg:postcode":"3722 AG",
    "sg:province":"Utrecht",
    "wof:name":"Crossroads",
    "wof:placetype":"venue"
},
  "geometry": {"coordinates":[5.207172,52.130512],"type":"Point"}
}