{
  "type": "Feature",
  "properties": {
    "iso:country":"NL",
    "sg:address":"Dorpsstr 3",
    "sg:city":"Vorden",
    "sg:orig_category":"Bibliotheken En Leeszalen Openbare",
    "sg:phone":"+31 575 551 500",
    "sg:postcode":"7251 BA",
    "sg:province":"Gelderland",
    "wof:name":"Openb Bibliotheek",
    "wof:placetype":"venue"
},
  "geometry": {"coordinates":[6.314478,52.103821],"type":"Point"}
}