{
  "type": "Feature",
  "properties": {
    "iso:country":"NL",
    "sg:address":"Grote Spui 39",
    "sg:city":"Amersfoort",
    "sg:orig_category":"Public Relationbureaus",
    "sg:phone":"+31 33 479 4050",
    "sg:postcode":"3813 EZ",
    "sg:province":"Utrecht",
    "wof:name":"Rec Adviseurs Van Vastgoed Communicatie En Strateg",
    "wof:placetype":"venue"
},
  "geometry": {"coordinates":[5.384846,52.159348],"type":"Point"}
}