{
  "type": "Feature",
  "properties": {
    "addr:full":"Eltenseweg 8 Lobith North Rhine-Westphalia 6915 KA",
    "addr:housenumber":"8",
    "addr:postcode":"6915 ka",
    "addr:street":"Eltenseweg",
    "iso:country":"NL",
    "sg:address":"Eltenseweg 8",
    "sg:city":"Lobith",
    "sg:orig_category":"Fruitteelt",
    "sg:phone":"+31 316 541 666",
    "sg:postcode":"6915 KA",
    "sg:province":"North Rhine-Westphalia",
    "wof:name":"Peters Fruitteeltbedrijf Cv",
    "wof:placetype":"venue"
},
  "geometry": {"coordinates":[6.125519,51.864788],"type":"Point"}
}