{
  "type": "Feature",
  "properties": {
    "addr:full":"Robynhof 1 Leiden Zuid-Holland 2332 KJ",
    "addr:housenumber":"1",
    "addr:postcode":"2332 kj",
    "addr:street":"Robynhof",
    "iso:country":"NL",
    "sg:address":"Robynhof 1",
    "sg:city":"Leiden",
    "sg:orig_category":"Bejaarden - Verzorgingstehuizen",
    "sg:phone":"+31 71 581 7100",
    "sg:postcode":"2332 KJ",
    "sg:province":"Zuid-Holland",
    "sg:website":"http://wwww.derobijn.nl",
    "wof:name":"Robijn, De",
    "wof:placetype":"venue"
},
  "geometry": {"coordinates":[4.462215,52.154644],"type":"Point"}
}