{
  "type": "Feature",
  "properties": {
    "addr:full":"Onsenoortsestraat 13 Nieuwkuijk North Brabant 5253 AA",
    "addr:housenumber":"13",
    "addr:postcode":"5253 aa",
    "addr:street":"Onsenoortsestraat",
    "iso:country":"NL",
    "sg:address":"Onsenoortsestraat 13",
    "sg:city":"Nieuwkuijk",
    "sg:orig_category":"Meubelzaken, Woning- And Keukeninrichting",
    "sg:phone":"+31 73 511 3561",
    "sg:postcode":"5253 AA",
    "sg:province":"North Brabant",
    "wof:name":"Caspar Dekkers Interieurs",
    "wof:placetype":"venue"
},
  "geometry": {"coordinates":[5.193087,51.693707],"type":"Point"}
}