{
  "type": "Feature",
  "properties": {
    "iso:country":"NL",
    "sg:address":"Boompjes 19",
    "sg:city":"Ouddorp Zh",
    "sg:classifiers":[
        {
            "category":"Fast Food",
            "type":"Food & Drink"
        }
    ],
    "sg:phone":"+31 187 682 395",
    "sg:postcode":"3253 AC",
    "sg:province":"Zuid-Holland",
    "sg:tags":[
        "afhaal",
        "restaurant"
    ],
    "wof:name":"Snackbar 'T Centrum",
    "wof:placetype":"venue"
},
  "geometry": {"coordinates":[3.93565,51.809624],"type":"Point"}
}