{
  "type": "Feature",
  "properties": {
    "iso:country":"NL",
    "sg:address":"De Bitterstraat 4",
    "sg:city":"Arnhem",
    "sg:orig_category":"Kinderopvang Behalve Thuis",
    "sg:phone":"+31 26 362 1299",
    "sg:postcode":"6826 PZ",
    "sg:province":"Gelderland",
    "wof:name":"De Harlekijn",
    "wof:placetype":"venue"
},
  "geometry": {"coordinates":[5.952974,51.980152],"type":"Point"}
}