{
  "type": "Feature",
  "properties": {
    "addr:full":"Minahassastr 1 Amsterdam North Holland 1094 RS",
    "addr:housenumber":"1",
    "addr:postcode":"1094 rs",
    "addr:street":"Minahassastr",
    "iso:country":"NL",
    "sg:address":"Minahassastr 1",
    "sg:city":"Amsterdam",
    "sg:orig_category":"Bedrijfshuisvesting",
    "sg:phone":"+31 20 692 9310",
    "sg:postcode":"1094 RS",
    "sg:province":"North Holland",
    "wof:name":"Archipel",
    "wof:placetype":"venue"
},
  "geometry": {"coordinates":[4.93366,52.360397],"type":"Point"}
}