{
  "type": "Feature",
  "properties": {
    "addr:full":"Ooststg 135 Wageningen Gelderland 6708 AT",
    "addr:housenumber":"135",
    "addr:postcode":"6708",
    "addr:street":"Gelderland",
    "iso:country":"NL",
    "sg:address":"Ooststg 135",
    "sg:city":"Wageningen",
    "sg:orig_category":"Verhuur",
    "sg:phone":"+31 317 413 196",
    "sg:postcode":"6708 AT",
    "sg:province":"Gelderland",
    "wof:name":"Dobbe",
    "wof:placetype":"venue"
},
  "geometry": {"coordinates":[5.660976,51.964355],"type":"Point"}
}