{
  "type": "Feature",
  "properties": {
    "iso:country":"NL",
    "sg:address":"Orchisln 1",
    "sg:city":"Arnhem",
    "sg:orig_category":"Fotografie Reclame En Mode",
    "sg:phone":"+31 26 321 5067",
    "sg:postcode":"6833 AB",
    "sg:province":"Gelderland",
    "wof:name":"Vermu\u00eb, Piet",
    "wof:placetype":"venue"
},
  "geometry": {"coordinates":[5.92045,51.965302],"type":"Point"}
}