{
  "type": "Feature",
  "properties": {
    "addr:full":"Kennipwerf 2 Hendrik Ido Ambacht Zuid-Holland 3343 BB",
    "addr:housenumber":"2",
    "addr:postcode":"3343 bb",
    "addr:street":"Kennipwerf",
    "iso:country":"NL",
    "sg:address":"Kennipwerf 2",
    "sg:city":"Hendrik Ido Ambacht",
    "sg:orig_category":"Juridische Dienstverlening",
    "sg:phone":"+31 78 684 0170",
    "sg:postcode":"3343 BB",
    "sg:province":"Zuid-Holland",
    "wof:name":"Kleefman Rechtskundig Adviesbureau",
    "wof:placetype":"venue"
},
  "geometry": {"coordinates":[4.630332,51.839817],"type":"Point"}
}