{
  "type": "Feature",
  "properties": {
    "addr:full":"Tongerenseweg 1 Vierhouten Gelderland 8076 PV",
    "addr:housenumber":"1",
    "addr:postcode":"8076 pv",
    "addr:street":"Tongerenseweg;Gelderland",
    "iso:country":"NL",
    "sg:address":"Tongerenseweg 1",
    "sg:city":"Vierhouten",
    "sg:classifiers":[
        {
            "category":"Travel",
            "subcategory":"Hotels & Motels",
            "type":"Entertainment"
        }
    ],
    "sg:phone":"+31 577 411 521",
    "sg:postcode":"8076 PV",
    "sg:province":"Gelderland",
    "wof:name":"Pension De Rozenboog",
    "wof:placetype":"venue"
},
  "geometry": {"coordinates":[5.831245,52.332485],"type":"Point"}
}