{
  "type": "Feature",
  "properties": {
    "addr:full":"Vetkamp 106 Nijkerk Gld Gelderland 3861 JS",
    "addr:housenumber":"106",
    "addr:postcode":"3861 js",
    "addr:street":"Vetkamp;Gld Gelderland",
    "iso:country":"NL",
    "sg:address":"Vetkamp 106",
    "sg:city":"Nijkerk Gld",
    "sg:orig_category":"Granen, Zaden And Diervoeders Gh",
    "sg:phone":"+31 33 245 9483",
    "sg:postcode":"3861 JS",
    "sg:province":"Gelderland",
    "wof:name":"R. Van Veldhuisen",
    "wof:placetype":"venue"
},
  "geometry": {"coordinates":[5.490789,52.227535],"type":"Point"}
}