{
  "type": "Feature",
  "properties": {
    "addr:full":"Saffierborch 2 Rosmalen Noord-Brabant 5241 LN",
    "addr:housenumber":"2",
    "addr:postcode":"5241 ln",
    "addr:street":"Saffierborch",
    "iso:country":"NL",
    "sg:address":"Saffierborch 2",
    "sg:city":"Rosmalen",
    "sg:orig_category":"Elektronische Bedrijfsinstallaties",
    "sg:phone":"+31 73 521 6306",
    "sg:postcode":"5241 LN",
    "sg:province":"Noord-Brabant",
    "wof:name":"Van Vliet Installaties",
    "wof:placetype":"venue"
},
  "geometry": {"coordinates":[5.349961,51.721169],"type":"Point"}
}