{
  "type": "Feature",
  "properties": {
    "addr:full":"Zebraspoor 452 Maarssen Utrecht 3605 HA",
    "addr:housenumber":"452",
    "addr:postcode":"3605 ha",
    "addr:street":"Zebraspoor",
    "iso:country":"NL",
    "sg:address":"Zebraspoor 452",
    "sg:city":"Maarssen",
    "sg:orig_category":"Journalisten Freelance",
    "sg:phone":"+31 346 564 936",
    "sg:postcode":"3605 HA",
    "sg:province":"Utrecht",
    "wof:name":"Meijer, J En I",
    "wof:placetype":"venue"
},
  "geometry": {"coordinates":[5.020144,52.140976],"type":"Point"}
}