{
  "type": "Feature",
  "properties": {
    "addr:full":"Lente 15 Dronten Flevoland 8251 NT",
    "addr:housenumber":"15",
    "addr:postcode":"8251 nt",
    "addr:street":"Lente;Flevoland",
    "iso:country":"NL",
    "sg:address":"Lente 15",
    "sg:city":"Dronten",
    "sg:orig_category":"Administratie- En Boekhoudkantoren",
    "sg:phone":"+31 321 311 380",
    "sg:postcode":"8251 NT",
    "sg:province":"Flevoland",
    "wof:name":"Klink, Christine",
    "wof:placetype":"venue"
},
  "geometry": {"coordinates":[5.717835,52.49918],"type":"Point"}
}