{
  "type": "Feature",
  "properties": {
    "iso:country":"NL",
    "sg:address":"Schepenstraat 74",
    "sg:city":"Rotterdam",
    "sg:orig_category":"Boekenuitgeverijen",
    "sg:phone":"+31 10 466 6656",
    "sg:postcode":"3039 NL",
    "sg:province":"South Holland",
    "wof:name":"Hesperia",
    "wof:placetype":"venue"
},
  "geometry": {"coordinates":[4.46623,51.929508],"type":"Point"}
}