{
  "type": "Feature",
  "properties": {
    "addr:full":"Overwinningspln 40 Groningen Groningen 9728 GT",
    "addr:housenumber":"40",
    "addr:postcode":"9728 gt",
    "addr:street":"Overwinningspln",
    "iso:country":"NL",
    "sg:address":"Overwinningspln 40",
    "sg:city":"Groningen",
    "sg:orig_category":"Grafisch Ontwerpers",
    "sg:phone":"+31 50 525 7684",
    "sg:postcode":"9728 GT",
    "sg:province":"Groningen",
    "wof:name":"Buroo G",
    "wof:placetype":"venue"
},
  "geometry": {"coordinates":[6.55931,53.197994],"type":"Point"}
}