{
  "type": "Feature",
  "properties": {
    "addr:full":"De Schoof 190 Hendrik Ido Ambacht Zuid-Holland 3341 EW",
    "addr:housenumber":"190",
    "addr:postcode":"3341 ew",
    "addr:street":"De Schoof",
    "iso:country":"NL",
    "sg:address":"De Schoof 190",
    "sg:city":"Hendrik Ido Ambacht",
    "sg:orig_category":"Bloemen And Planten",
    "sg:phone":"+31 78 681 2834",
    "sg:postcode":"3341 EW",
    "sg:province":"Zuid-Holland",
    "wof:name":"De Sitter Bloemen",
    "wof:placetype":"venue"
},
  "geometry": {"coordinates":[4.644039,51.84885],"type":"Point"}
}