{
  "type": "Feature",
  "properties": {
    "addr:full":"Oostwal 19 Oldenzaal Overijssel 7571 CR",
    "addr:housenumber":"19",
    "addr:postcode":"7571 cr",
    "addr:street":"Oostwal",
    "iso:country":"NL",
    "sg:address":"Oostwal 19",
    "sg:city":"Oldenzaal",
    "sg:orig_category":"Diverse Consumentenartikelen Gh",
    "sg:phone":"+31 541 519 866",
    "sg:postcode":"7571 CR",
    "sg:province":"Overijssel",
    "wof:name":"Fabri Sport",
    "wof:placetype":"venue"
},
  "geometry": {"coordinates":[6.932401,52.314007],"type":"Point"}
}