{
  "type": "Feature",
  "properties": {
    "addr:full":"Valckenierstr 9 Arnhem Gelderland 6828 RM",
    "addr:housenumber":"9",
    "addr:postcode":"6828 rm",
    "addr:street":"Valckenierstr",
    "iso:country":"NL",
    "sg:address":"Valckenierstr 9",
    "sg:city":"Arnhem",
    "sg:orig_category":"Kinderopvang",
    "sg:phone":"+31 26 351 6406",
    "sg:postcode":"6828 RM",
    "sg:province":"Gelderland",
    "wof:name":"Stoplicht, 'T",
    "wof:placetype":"venue"
},
  "geometry": {"coordinates":[5.9318,51.978512],"type":"Point"}
}