{
  "type": "Feature",
  "properties": {
    "iso:country":"NL",
    "sg:address":"Pr W Alexanderwg 26",
    "sg:city":"Houten",
    "sg:orig_category":"Psychotherapeuten",
    "sg:phone":"+31 30 635 3570",
    "sg:postcode":"3991 CB",
    "sg:province":"Utrecht",
    "wof:name":"Gedragsther Training & Coaching, Prakt Voor",
    "wof:placetype":"venue"
},
  "geometry": {"coordinates":[5.168762,52.03109],"type":"Point"}
}