{
  "type": "Feature",
  "properties": {
    "addr:full":"Kuluutsheuvel 74 Overloon Noord-Brabant 5825 BG",
    "addr:housenumber":"74",
    "addr:postcode":"5825",
    "addr:street":"Kuluutsheuvel",
    "iso:country":"NL",
    "sg:address":"Kuluutsheuvel 74",
    "sg:city":"Overloon",
    "sg:orig_category":"Platenmaatschappijen",
    "sg:phone":"+31 478 642 548",
    "sg:postcode":"5825 BG",
    "sg:province":"Noord-Brabant",
    "wof:name":"Holland Produkties",
    "wof:placetype":"venue"
},
  "geometry": {"coordinates":[5.952085,51.575848],"type":"Point"}
}