{
  "type": "Feature",
  "properties": {
    "iso:country":"NL",
    "sg:address":"De Wouden 197",
    "sg:city":"Assen",
    "sg:orig_category":"Diverse Grafische Activiteiten",
    "sg:phone":"+31 592 399 193",
    "sg:postcode":"9405 HH",
    "sg:province":"Provincie Drenthe",
    "wof:name":"J. M. Van Der Vliet-Dekker",
    "wof:placetype":"venue"
},
  "geometry": {"coordinates":[6.530374,52.986294],"type":"Point"}
}