{
  "type": "Feature",
  "properties": {
    "addr:full":"Koningswg 104 Utrecht Utrecht 3582 GL",
    "addr:housenumber":"104",
    "addr:postcode":"3582 gl",
    "iso:country":"NL",
    "sg:address":"Koningswg 104",
    "sg:city":"Utrecht",
    "sg:orig_category":"Wasserijen",
    "sg:phone":"+31 30 251 4165",
    "sg:postcode":"3582 GL",
    "sg:province":"Utrecht",
    "wof:name":"Aurora Utrecht Bv",
    "wof:placetype":"venue"
},
  "geometry": {"coordinates":[5.1366238594,52.0763282776],"type":"Point"}
}