{
  "type": "Feature",
  "properties": {
    "iso:country":"NL",
    "sg:address":"Nieuwstr 34",
    "sg:city":"Hengelo Ov",
    "sg:classifiers":[
        {
            "category":"Shopping",
            "subcategory":"News",
            "type":"Retail Goods"
        }
    ],
    "sg:phone":"+31 74 291 8851",
    "sg:postcode":"7551 CZ",
    "sg:province":"Overijssel",
    "sg:tags":[
        "maandbladen",
        "en",
        "week-"
    ],
    "wof:name":"Hengelo'S Weekblad",
    "wof:placetype":"venue"
},
  "geometry": {"coordinates":[6.7897119522,52.2663612366],"type":"Point"}
}