{
  "type": "Feature",
  "properties": {
    "addr:full":"Nieuwe Binnenweg 352 B Rotterdam South Holland 3023 ES",
    "addr:housenumber":"352 b",
    "addr:postcode":"3023 es",
    "addr:street":"Nieuwe Binnenweg",
    "iso:country":"NL",
    "sg:address":"Nieuwe Binnenweg 352 B",
    "sg:city":"Rotterdam",
    "sg:orig_category":"Boekenuitgeverijen",
    "sg:phone":"+31 10 425 8334",
    "sg:postcode":"3023 ES",
    "sg:province":"South Holland",
    "wof:name":"7 Uitgeverijen",
    "wof:placetype":"venue"
},
  "geometry": {"coordinates":[4.454606,51.911999],"type":"Point"}
}