{
  "type": "Feature",
  "properties": {
    "addr:full":"Dorpsstr 28 Rosmalen Noord-Brabant 5241 EC",
    "addr:housenumber":"28",
    "addr:postcode":"5241 ec",
    "addr:street":"Dorpsstr",
    "iso:country":"NL",
    "sg:address":"Dorpsstr 28",
    "sg:city":"Rosmalen",
    "sg:orig_category":"Kinderkleding",
    "sg:phone":"+31 73 521 4040",
    "sg:postcode":"5241 EC",
    "sg:province":"Noord-Brabant",
    "wof:name":"Harlekino, Kinder & Jeugdmode",
    "wof:placetype":"venue"
},
  "geometry": {"coordinates":[5.362489,51.717812],"type":"Point"}
}