{
  "type": "Feature",
  "properties": {
    "addr:full":"Voorburgsewg 52 Leidschendam Zuid-Holland 2264 AH",
    "addr:housenumber":"52",
    "addr:postcode":"2264 ah",
    "addr:street":"Voorburgsewg",
    "iso:country":"NL",
    "sg:address":"Voorburgsewg 52",
    "sg:city":"Leidschendam",
    "sg:orig_category":"Verzekeringen - Verzekeringskantoren",
    "sg:phone":"+31 70 320 6999",
    "sg:postcode":"2264 AH",
    "sg:province":"Zuid-Holland",
    "wof:name":"Novapolis",
    "wof:placetype":"venue"
},
  "geometry": {"coordinates":[4.390171,52.081692],"type":"Point"}
}