{
  "type": "Feature",
  "properties": {
    "addr:full":"Purmerwg 33A Purmerend Noord-Holland 1441 RA",
    "addr:housenumber":"33a",
    "addr:postcode":"1441 ra",
    "addr:street":"Purmerwg",
    "iso:country":"NL",
    "sg:address":"Purmerwg 33A",
    "sg:city":"Purmerend",
    "sg:orig_category":"Fotoapparatuur En -Artikelen - Groothandel",
    "sg:phone":"+31 299 428 005",
    "sg:postcode":"1441 RA",
    "sg:province":"Noord-Holland",
    "wof:name":"Provak Bv",
    "wof:placetype":"venue"
},
  "geometry": {"coordinates":[4.966874,52.504025],"type":"Point"}
}