{
  "type": "Feature",
  "properties": {
    "addr:full":"Weegbreestr 2 Bergen Op Zoom Noord-Brabant 4621 BW",
    "addr:housenumber":"2",
    "addr:postcode":"4621 bw",
    "addr:street":"Weegbreestr",
    "iso:country":"NL",
    "sg:address":"Weegbreestr 2",
    "sg:city":"Bergen Op Zoom",
    "sg:orig_category":"Verenigingen En Stichtingen",
    "sg:phone":"+31 164 239 762",
    "sg:postcode":"4621 BW",
    "sg:province":"Noord-Brabant",
    "wof:name":"Steunpunt Ouderen Elsenborch",
    "wof:placetype":"venue"
},
  "geometry": {"coordinates":[4.303748,51.490707],"type":"Point"}
}