{
  "type": "Feature",
  "properties": {
    "iso:country":"NL",
    "sg:address":"Markt 15",
    "sg:city":"Almere",
    "sg:orig_category":"Verenigingen En Stichtingen",
    "sg:phone":"+31 36 531 5335",
    "sg:postcode":"1354 AP",
    "sg:province":"Flevoland",
    "wof:name":"Corrosia",
    "wof:placetype":"venue"
},
  "geometry": {"coordinates":[5.219005,52.336147],"type":"Point"}
}