{
  "type": "Feature",
  "properties": {
    "addr:full":"Markt 15 Almere Flevoland 1354 AP",
    "addr:housenumber":"15",
    "addr:postcode":"1354 ap",
    "addr:street":"Markt;Flevoland",
    "iso:country":"NL",
    "sg:address":"Markt 15",
    "sg:city":"Almere",
    "sg:orig_category":"Verenigingen En Stichtingen",
    "sg:phone":"+31 36 531 5335",
    "sg:postcode":"1354 AP",
    "sg:province":"Flevoland",
    "wof:name":"Corrosia",
    "wof:placetype":"venue"
},
  "geometry": {"coordinates":[5.219005,52.336147],"type":"Point"}
}