{
  "type": "Feature",
  "properties": {
    "addr:full":"Valburgseweg 102 Elst Gld Gelderland 6661 NR",
    "addr:housenumber":"102",
    "addr:postcode":"6661",
    "addr:street":"Valburgseweg;Gld Gelderland;Nr",
    "iso:country":"NL",
    "sg:address":"Valburgseweg 102",
    "sg:city":"Elst Gld",
    "sg:orig_category":"Autokeuringen",
    "sg:phone":"+31 481 371 366",
    "sg:postcode":"6661 NR",
    "sg:province":"Gelderland",
    "wof:name":"Vof Autobedrijf J. Van De Kuilen",
    "wof:placetype":"venue"
},
  "geometry": {"coordinates":[5.813323,51.916439],"type":"Point"}
}