{
  "type": "Feature",
  "properties": {
    "iso:country":"NL",
    "sg:address":"Hoofdstr 44/C",
    "sg:city":"Kloosterburen",
    "sg:orig_category":"Kappers",
    "sg:phone":"+31 595 481 573",
    "sg:postcode":"9977 RE",
    "sg:province":"Groningen",
    "wof:name":"Kolk, De",
    "wof:placetype":"venue"
},
  "geometry": {"coordinates":[6.396575,53.387688],"type":"Point"}
}