{
  "type": "Feature",
  "properties": {
    "addr:full":"Keizersgr 790 Amsterdam Noord-Holland 1017 EC",
    "addr:housenumber":"790",
    "addr:postcode":"1017 ec",
    "iso:country":"NL",
    "sg:address":"Keizersgr 790",
    "sg:city":"Amsterdam",
    "sg:orig_category":"Mensendieck - Oefentherapeuten",
    "sg:phone":"+31 20 427 6545",
    "sg:postcode":"1017 EC",
    "sg:province":"Noord-Holland",
    "wof:name":"Grol & M Haarmans, M",
    "wof:placetype":"venue"
},
  "geometry": {"coordinates":[4.899659,52.363724],"type":"Point"}
}