{
  "type": "Feature",
  "properties": {
    "addr:full":"Zeestr 48 Beverwyk Noord-Holland 1942 AR",
    "addr:housenumber":"48",
    "addr:postcode":"1942",
    "addr:street":"Zeestr",
    "iso:country":"NL",
    "sg:address":"Zeestr 48",
    "sg:city":"Beverwyk",
    "sg:orig_category":"Babyartikelen",
    "sg:phone":"+31 251 224 926",
    "sg:postcode":"1942 AR",
    "sg:province":"Noord-Holland",
    "sg:website":"http://www.babykleuterhuis.nl",
    "wof:name":"Baby En Kleuterhuis",
    "wof:placetype":"venue"
},
  "geometry": {"coordinates":[4.653116,52.481743],"type":"Point"}
}