{
  "type": "Feature",
  "properties": {
    "iso:country":"NL",
    "sg:address":"Luytenstr 12",
    "sg:city":"Lekkerkerk",
    "sg:classifiers":[
        {
            "category":"Wholesale",
            "subcategory":"Motor Vehicles",
            "type":"Manufacturing & Wholesale Goods"
        }
    ],
    "sg:phone":"+31 180 662 179",
    "sg:postcode":"2941 CE",
    "sg:province":"Zuid-Holland",
    "sg:tags":[
        "scooter",
        "en"
    ],
    "wof:name":"Dirk Alblas Motoren",
    "wof:placetype":"venue"
},
  "geometry": {"coordinates":[4.691318,51.901863],"type":"Point"}
}