{
  "type": "Feature",
  "properties": {
    "addr:full":"Postbus 10 Voorst Gem Voorst Gelderland 7383 ZG",
    "addr:housenumber":"10",
    "addr:postcode":"7383 zg",
    "addr:street":"Postbus;Gem;Gelderland",
    "iso:country":"NL",
    "sg:address":"Postbus 10",
    "sg:city":"Voorst Gem Voorst",
    "sg:orig_category":"Makelaars En Adviseurs Onroerende Goederen",
    "sg:phone":"+31 575 501 650",
    "sg:postcode":"7383 ZG",
    "sg:province":"Gelderland",
    "wof:name":"Hensbergen, J B",
    "wof:placetype":"venue"
},
  "geometry": {"coordinates":[6.142395,52.170658],"type":"Point"}
}