{
  "type": "Feature",
  "properties": {
    "addr:full":"Emmastr 33 Velp Gelderland 6881 SP",
    "addr:housenumber":"33",
    "addr:postcode":"6881 sp",
    "addr:street":"Emmastr;Gelderland",
    "iso:country":"NL",
    "sg:address":"Emmastr 33",
    "sg:city":"Velp",
    "sg:orig_category":"Fietsen En Bromfietsen",
    "sg:phone":"+31 26 362 0183",
    "sg:postcode":"6881 SP",
    "sg:province":"Gelderland",
    "wof:name":"Jansen, T F",
    "wof:placetype":"venue"
},
  "geometry": {"coordinates":[5.973999,51.994495],"type":"Point"}
}