{
  "type": "Feature",
  "properties": {
    "iso:country":"NL",
    "sg:address":"J V Goyenstr 121",
    "sg:city":"Alkmaar",
    "sg:orig_category":"Adviesbureaus Bedrijfsorganisatie",
    "sg:phone":"+31 72 511 4344",
    "sg:postcode":"1816 ED",
    "sg:province":"Noord-Holland",
    "sg:website":"http://www.managersdesk.nl",
    "wof:name":"Managersdesk, De",
    "wof:placetype":"venue"
},
  "geometry": {"coordinates":[4.746258,52.634361],"type":"Point"}
}