{
  "type": "Feature",
  "properties": {
    "iso:country":"NL",
    "sg:address":"A J Ernststr 865",
    "sg:city":"Amsterdam",
    "sg:orig_category":"Juweliers",
    "sg:phone":"+31 20 404 0200",
    "sg:postcode":"1082 LN",
    "sg:province":"North Holland",
    "sg:website":"http://www.goudonline.nl",
    "wof:name":"Goudonline Bv",
    "wof:placetype":"venue"
},
  "geometry": {"coordinates":[4.87756,52.330521],"type":"Point"}
}