{
  "type": "Feature",
  "properties": {
    "addr:full":"Ysseltjalk 2 Velserbroek Minnesota 1991 MN",
    "addr:housenumber":"2;1991",
    "addr:postcode":"mn",
    "addr:street":"Ysseltjalk;Minnesota",
    "iso:country":"NL",
    "sg:address":"Ysseltjalk 2",
    "sg:city":"Velserbroek",
    "sg:orig_category":"Onderhoudswerken",
    "sg:phone":"+31 6 24283661",
    "sg:postcode":"1991 MN",
    "sg:province":"Minnesota",
    "wof:name":"Koopen Timmer/Onderh Bedrijf",
    "wof:placetype":"venue"
},
  "geometry": {"coordinates":[-93.365471,46.441929],"type":"Point"}
}