{
  "type": "Feature",
  "properties": {
    "addr:full":"Hogendk 5 Ouderkerk Amstel Noord-Holland 1191 LH",
    "addr:housenumber":"5",
    "addr:postcode":"1191 lh",
    "addr:street":"Hogendk;Ouderkerk Amstel",
    "iso:country":"NL",
    "sg:address":"Hogendk 5",
    "sg:city":"Ouderkerk Amstel",
    "sg:orig_category":"Balletscholen",
    "sg:phone":"+31 294 281 345",
    "sg:postcode":"1191 LH",
    "sg:province":"Noord-Holland",
    "wof:name":"Robertson, B",
    "wof:placetype":"venue"
},
  "geometry": {"coordinates":[4.918858,52.299152],"type":"Point"}
}