{
  "type": "Feature",
  "properties": {
    "addr:full":"Telefoonweg 124 Ede Gld Gelderland 6713 AL",
    "addr:housenumber":"124;6713",
    "addr:postcode":"al",
    "addr:street":"Telefoonweg;Gld Gelderland",
    "iso:country":"NL",
    "sg:address":"Telefoonweg 124",
    "sg:city":"Ede Gld",
    "sg:orig_category":"Overheidsdiensten",
    "sg:phone":"+31 318 680 498",
    "sg:postcode":"6713 AL",
    "sg:province":"Gelderland",
    "wof:name":"Gemeente Ede Hoofdafdeling Werk En Zorg",
    "wof:placetype":"venue"
},
  "geometry": {"coordinates":[5.6673550606,52.0432662964],"type":"Point"}
}