{
  "type": "Feature",
  "properties": {
    "iso:country":"NL",
    "sg:address":"Keersoppermolen 84",
    "sg:city":"Eindhoven",
    "sg:orig_category":"Psychologen",
    "sg:phone":"+31 40 243 4216",
    "sg:postcode":"5612 DE",
    "sg:province":"Noord-Brabant",
    "wof:name":"Dorien Otten Drs",
    "wof:placetype":"venue"
},
  "geometry": {"coordinates":[5.478232,51.447361],"type":"Point"}
}