{
  "type": "Feature",
  "properties": {
    "addr:full":"Burgemeester Royaardsln 1 Scherpenzeel Gld Gelderland 3925 GG",
    "addr:housenumber":"1",
    "addr:postcode":"3925 gg",
    "addr:street":"Burgemeester Royaardsln;Gld Gelderland",
    "iso:country":"NL",
    "sg:address":"Burgemeester Royaardsln 1",
    "sg:city":"Scherpenzeel Gld",
    "sg:orig_category":"Overheidsdiensten",
    "sg:phone":"+31 33 277 2324",
    "sg:postcode":"3925 GG",
    "sg:province":"Gelderland",
    "wof:name":"Gemeente Scherpenzeel",
    "wof:placetype":"venue"
},
  "geometry": {"coordinates":[5.4870347977,52.0785064697],"type":"Point"}
}