{
  "type": "Feature",
  "properties": {
    "addr:full":"Amazonedreef 35 Utrecht Utrecht 3563 CA",
    "addr:housenumber":"35",
    "addr:postcode":"3563 ca",
    "addr:street":"Amazonedreef",
    "iso:country":"NL",
    "sg:address":"Amazonedreef 35",
    "sg:city":"Utrecht",
    "sg:orig_category":"Kunstgebitten",
    "sg:phone":"+31 30 261 4888",
    "sg:postcode":"3563 CA",
    "sg:province":"Utrecht",
    "wof:name":"Marbus",
    "wof:placetype":"venue"
},
  "geometry": {"coordinates":[5.101156,52.118988],"type":"Point"}
}