{
  "type": "Feature",
  "properties": {
    "addr:full":"Assenstr 13 Deventer NL.08 7411 JR",
    "addr:housenumber":"13;nl.08",
    "addr:postcode":"7411 jr",
    "addr:street":"Assenstr",
    "iso:country":"NL",
    "sg:address":"Assenstr 13",
    "sg:city":"Deventer",
    "sg:orig_category":"Verenigingen En Stichtingen",
    "sg:phone":"+31 570 600 410",
    "sg:postcode":"7411 JR",
    "sg:province":"NL.08",
    "wof:name":"Walhalla Sticht",
    "wof:placetype":"venue"
},
  "geometry": {"coordinates":[6.157699,52.251678],"type":"Point"}
}