{
  "type": "Feature",
  "properties": {
    "addr:full":"Bergse Dorpsstr 44 Rotterdam Zuid-Holland 3054 GE",
    "addr:housenumber":"44",
    "addr:postcode":"3054",
    "addr:street":"Bergse Dorpsstr",
    "iso:country":"NL",
    "sg:address":"Bergse Dorpsstr 44",
    "sg:city":"Rotterdam",
    "sg:orig_category":"Herenkleding",
    "sg:phone":"+31 10 461 2166",
    "sg:postcode":"3054 GE",
    "sg:province":"Zuid-Holland",
    "wof:name":"Country House",
    "wof:placetype":"venue"
},
  "geometry": {"coordinates":[4.494134,51.956337],"type":"Point"}
}