{
  "type": "Feature",
  "properties": {
    "addr:full":"Molenstr 55 Roosendaal Noord-Brabant 4701 JN",
    "addr:housenumber":"55",
    "addr:postcode":"4701 jn",
    "addr:street":"Molenstr",
    "iso:country":"NL",
    "sg:address":"Molenstr 55",
    "sg:city":"Roosendaal",
    "sg:orig_category":"Geschenkartikelen",
    "sg:phone":"+31 165 533 819",
    "sg:postcode":"4701 JN",
    "sg:province":"Noord-Brabant",
    "wof:name":"Kadosjop",
    "wof:placetype":"venue"
},
  "geometry": {"coordinates":[4.458413,51.534409],"type":"Point"}
}