{
  "type": "Feature",
  "properties": {
    "addr:full":"Grt Houtstr 115 Haarlem North Holland 2011 SJ",
    "addr:housenumber":"115",
    "addr:postcode":"2011",
    "iso:country":"NL",
    "sg:address":"Grt Houtstr 115",
    "sg:city":"Haarlem",
    "sg:orig_category":"Verenigingsgebouwen",
    "sg:phone":"+31 23 531 1474",
    "sg:postcode":"2011 SJ",
    "sg:province":"North Holland",
    "wof:name":"Trou Moet Blycken",
    "wof:placetype":"venue"
},
  "geometry": {"coordinates":[4.632366,52.378098],"type":"Point"}
}