{
  "type": "Feature",
  "properties": {
    "addr:full":"Gedempte Gr 17 Schagen North Holland 1741 GA",
    "addr:housenumber":"17",
    "addr:postcode":"1741 ga",
    "addr:street":"Gedempte Gr",
    "iso:country":"NL",
    "sg:address":"Gedempte Gr 17",
    "sg:city":"Schagen",
    "sg:orig_category":"Dameskleding",
    "sg:phone":"+31 224 216 617",
    "sg:postcode":"1741 GA",
    "sg:province":"North Holland",
    "wof:name":"Fame",
    "wof:placetype":"venue"
},
  "geometry": {"coordinates":[4.797877,52.786819],"type":"Point"}
}