{
  "type": "Feature",
  "properties": {
    "addr:full":"Industriewg 27 Andelst Gelderland 6673 DE",
    "addr:housenumber":"27",
    "addr:postcode":"6673 de",
    "addr:street":"Industriewg;Gelderland",
    "iso:country":"NL",
    "sg:address":"Industriewg 27",
    "sg:city":"Andelst",
    "sg:orig_category":"Papier - Fabrieken En Groothandel",
    "sg:phone":"+31 488 474 747",
    "sg:postcode":"6673 DE",
    "sg:province":"Gelderland",
    "wof:name":"Buhomij Bv",
    "wof:placetype":"venue"
},
  "geometry": {"coordinates":[5.7272648811,51.9074783325],"type":"Point"}
}