{
  "type": "Feature",
  "properties": {
    "addr:full":"Willemsparkwg 1142Hg Amsterdam Noord-Holland 1071 HN",
    "addr:postcode":"1142hg;1071 hn",
    "addr:street":"Willemsparkwg",
    "iso:country":"NL",
    "sg:address":"Willemsparkwg 1142Hg",
    "sg:city":"Amsterdam",
    "sg:orig_category":"Artiesten/Gezelschappen",
    "sg:phone":"+31 20 675 4061",
    "sg:postcode":"1071 HN",
    "sg:province":"Noord-Holland",
    "wof:name":"Klinkhamer Van Der Vliet",
    "wof:placetype":"venue"
},
  "geometry": {"coordinates":[4.86816,52.355289],"type":"Point"}
}