{
  "type": "Feature",
  "properties": {
    "addr:full":"Evertsenplein 94 Hellevoetsluis Zuid-Holland 3221 BL",
    "addr:housenumber":"94",
    "addr:postcode":"3221 bl",
    "addr:street":"Evertsenplein",
    "iso:country":"NL",
    "sg:address":"Evertsenplein 94",
    "sg:city":"Hellevoetsluis",
    "sg:orig_category":"Bloemen And Planten",
    "sg:phone":"+31 181 321 820",
    "sg:postcode":"3221 BL",
    "sg:province":"Zuid-Holland",
    "wof:name":"De Duinroos",
    "wof:placetype":"venue"
},
  "geometry": {"coordinates":[4.129861,51.833858],"type":"Point"}
}