{
  "type": "Feature",
  "properties": {
    "addr:full":"W V Otterlostr 32 Hengelo Ov Overijssel 7558 BV",
    "addr:housenumber":"32",
    "addr:postcode":"7558 bv",
    "addr:street":"W V Otterlostr;Ov",
    "iso:country":"NL",
    "sg:address":"W V Otterlostr 32",
    "sg:city":"Hengelo Ov",
    "sg:orig_category":"Artsen - Huisartsen",
    "sg:phone":"+31 74 277 0200",
    "sg:postcode":"7558 BV",
    "sg:province":"Overijssel",
    "wof:name":"Gezondheidscentrum Hasseler-Es",
    "wof:placetype":"venue"
},
  "geometry": {"coordinates":[6.78971,52.266331],"type":"Point"}
}