{
  "type": "Feature",
  "properties": {
    "iso:country":"NL",
    "sg:address":"Tussen Meer 71",
    "sg:city":"Amsterdam",
    "sg:orig_category":"Schoenen",
    "sg:phone":"+31 20 619 2255",
    "sg:postcode":"1068 EZ",
    "sg:province":"North Holland",
    "wof:name":"Hoften Vof, Van",
    "wof:placetype":"venue"
},
  "geometry": {"coordinates":[4.800754,52.358109],"type":"Point"}
}