{
  "type": "Feature",
  "properties": {
    "addr:full":"Molenvliet 4 Rotterdam Zuid-Holland 3076 CK",
    "addr:housenumber":"4",
    "addr:postcode":"3076 ck",
    "addr:street":"Molenvliet",
    "iso:country":"NL",
    "sg:address":"Molenvliet 4",
    "sg:city":"Rotterdam",
    "sg:orig_category":"Afvalstoffen",
    "sg:phone":"+31 10 492 9299",
    "sg:postcode":"3076 CK",
    "sg:province":"Zuid-Holland",
    "sg:website":"http://www.klokcontainers.nl",
    "wof:name":"Klok Containers Bv",
    "wof:placetype":"venue"
},
  "geometry": {"coordinates":[4.52288,51.885757],"type":"Point"}
}