{
  "type": "Feature",
  "properties": {
    "addr:full":"Toernooistraat 5 Enschede Overijssel 7535 BX",
    "addr:housenumber":"5",
    "addr:postcode":"7535 bx",
    "addr:street":"Toernooistraat",
    "iso:country":"NL",
    "sg:address":"Toernooistraat 5",
    "sg:city":"Enschede",
    "sg:orig_category":"Boekhouders",
    "sg:phone":"+31 53 431 8646",
    "sg:postcode":"7535 BX",
    "sg:province":"Overijssel",
    "wof:name":"Bsp Enschede",
    "wof:placetype":"venue"
},
  "geometry": {"coordinates":[6.91517,52.207561],"type":"Point"}
}