{
  "type": "Feature",
  "properties": {
    "addr:full":"Dorpsstr 95 Abbekerk Noord-Holland 1657 AD",
    "addr:housenumber":"95",
    "addr:postcode":"1657 ad",
    "addr:street":"Dorpsstr",
    "iso:country":"NL",
    "sg:address":"Dorpsstr 95",
    "sg:city":"Abbekerk",
    "sg:orig_category":"Postkantoren",
    "sg:phone":"+31 229 581 210",
    "sg:postcode":"1657 AD",
    "sg:province":"Noord-Holland",
    "sg:website":"http://www.postkantoor.nl",
    "wof:name":"Postkantoor",
    "wof:placetype":"venue"
},
  "geometry": {"coordinates":[5.020295,52.731339],"type":"Point"}
}