{
  "type": "Feature",
  "properties": {
    "addr:full":"K Doormanpln 2 Hillegom Zuid-Holland 2182 XC",
    "addr:housenumber":"2",
    "addr:postcode":"2182 xc",
    "addr:street":"Doormanpln",
    "iso:country":"NL",
    "sg:address":"K Doormanpln 2",
    "sg:city":"Hillegom",
    "sg:orig_category":"Zalenverhuur",
    "sg:phone":"+31 252 516 208",
    "sg:postcode":"2182 XC",
    "sg:province":"Zuid-Holland",
    "wof:name":"Hoeksteen, De",
    "wof:placetype":"venue"
},
  "geometry": {"coordinates":[4.578816,52.297722],"type":"Point"}
}