{
  "type": "Feature",
  "properties": {
    "addr:full":"Vivaldipassage 9 Landgraaf Limburg 6371 LL",
    "addr:housenumber":"9",
    "addr:postcode":"6371 ll",
    "addr:street":"Vivaldipassage",
    "iso:country":"NL",
    "sg:address":"Vivaldipassage 9",
    "sg:city":"Landgraaf",
    "sg:orig_category":"Schoenen",
    "sg:phone":"+31 45 569 0529",
    "sg:postcode":"6371 LL",
    "sg:province":"Limburg",
    "wof:name":"Haren Bv, Van",
    "wof:placetype":"venue"
},
  "geometry": {"coordinates":[6.024094,50.906082],"type":"Point"}
}