{
  "type": "Feature",
  "properties": {
    "addr:full":"Kallestr 1A Hunsel Limburg 6013 RM",
    "addr:housenumber":"1a",
    "addr:postcode":"6013 rm",
    "addr:street":"Kallestr",
    "iso:country":"NL",
    "sg:address":"Kallestr 1A",
    "sg:city":"Hunsel",
    "sg:orig_category":"Poeliers",
    "sg:phone":"+31 475 565 960",
    "sg:postcode":"6013 RM",
    "sg:province":"Limburg",
    "wof:name":"Bakker Vof, De",
    "wof:placetype":"venue"
},
  "geometry": {"coordinates":[5.812674,51.190121],"type":"Point"}
}