{
  "type": "Feature",
  "properties": {
    "addr:full":"Weverstr 1 Lent Gelderland 6663 AV",
    "addr:housenumber":"1",
    "addr:postcode":"6663 av",
    "addr:street":"Weverstr;Gelderland",
    "iso:country":"NL",
    "sg:address":"Weverstr 1",
    "sg:city":"Lent",
    "sg:orig_category":"Adviesbureaus",
    "sg:phone":"+31 24 360 5002",
    "sg:postcode":"6663 AV",
    "sg:province":"Gelderland",
    "wof:name":"Baten",
    "wof:placetype":"venue"
},
  "geometry": {"coordinates":[-77.241432,38.151344],"type":"Point"}
}