{
  "type": "Feature",
  "properties": {
    "addr:full":"Herengracht 10 Terneuzen Zeeland 4531 GM",
    "addr:housenumber":"10",
    "addr:postcode":"4531 gm",
    "addr:street":"Herengracht",
    "iso:country":"NL",
    "sg:address":"Herengracht 10",
    "sg:city":"Terneuzen",
    "sg:orig_category":"Notarissen",
    "sg:phone":"+31 115 617 977",
    "sg:postcode":"4531 GM",
    "sg:province":"Zeeland",
    "wof:name":"Notaris Seijdlitz & Loof & Segers",
    "wof:placetype":"venue"
},
  "geometry": {"coordinates":[3.828592,51.33572],"type":"Point"}
}