{
  "type": "Feature",
  "properties": {
    "addr:full":"Berg En Dalseweg 172 Nijmegen Gelderland 6522 CC",
    "addr:housenumber":"172",
    "addr:postcode":"6522 cc",
    "addr:street":"Berg En Dalseweg;Gelderland",
    "iso:country":"NL",
    "sg:address":"Berg En Dalseweg 172",
    "sg:city":"Nijmegen",
    "sg:orig_category":"Artsen And Specialisten",
    "sg:phone":"+31 24 322 9386",
    "sg:postcode":"6522 CC",
    "sg:province":"Gelderland",
    "wof:name":"J.A.M. Van Dijk Huisarts",
    "wof:placetype":"venue"
},
  "geometry": {"coordinates":[5.882837,51.837856],"type":"Point"}
}