{
  "type": "Feature",
  "properties": {
    "iso:country":"NL",
    "sg:address":"Postbus 43",
    "sg:city":"Alphen Aan Den Ryn",
    "sg:orig_category":"Wijnkoperijen En -Groothandel",
    "sg:phone":"+31 172 421 648",
    "sg:postcode":"2400 AA",
    "wof:name":"Delices Du Vin, Les",
    "wof:placetype":"venue"
},
  "geometry": {"coordinates":[4.6889500618,52.1310882568],"type":"Point"}
}