{
  "type": "Feature",
  "properties": {
    "addr:full":"Zuiderkerkpln 9 Enkhuizen Noord-Holland 1601 HK",
    "addr:housenumber":"9",
    "addr:postcode":"1601 hk",
    "addr:street":"Zuiderkerkpln",
    "iso:country":"NL",
    "sg:address":"Zuiderkerkpln 9",
    "sg:city":"Enkhuizen",
    "sg:orig_category":"Notarissen En Notariskantoren",
    "sg:phone":"+31 228 317 244",
    "sg:postcode":"1601 HK",
    "sg:province":"Noord-Holland",
    "wof:name":"Enkhuizer Notariaat",
    "wof:placetype":"venue"
},
  "geometry": {"coordinates":[5.292329,52.703514],"type":"Point"}
}