{
  "type": "Feature",
  "properties": {
    "addr:full":"Leerdamhof 433 Amsterdam Zuidoost Noord-Holland 1108 CL",
    "addr:housenumber":"433",
    "addr:postcode":"zuidoost;1108",
    "addr:street":"Leerdamhof",
    "iso:country":"NL",
    "sg:address":"Leerdamhof 433",
    "sg:city":"Amsterdam Zuidoost",
    "sg:orig_category":"Horecabenodigdheden",
    "sg:phone":"+31 20 697 2310",
    "sg:postcode":"1108 CL",
    "sg:province":"Noord-Holland",
    "sg:website":"http://www.kuijsconnections.nl",
    "wof:name":"Kuijs",
    "wof:placetype":"venue"
},
  "geometry": {"coordinates":[4.977579,52.305595],"type":"Point"}
}