{
  "type": "Feature",
  "properties": {
    "iso:country":"NL",
    "sg:address":"Jutfaseweg 1",
    "sg:city":"Utrecht",
    "sg:orig_category":"Hypotheken And Hypotheekbanken",
    "sg:phone":"+31 30 289 3434",
    "sg:postcode":"3522 HA",
    "sg:province":"Utrecht",
    "wof:name":"Rijnlandse Hypotheekbank Bv",
    "wof:placetype":"venue"
},
  "geometry": {"coordinates":[5.1213140488,52.0781097412],"type":"Point"}
}