{
  "type": "Feature",
  "properties": {
    "addr:full":"Kenaupark 25 Haarlem North Holland 2011 MR",
    "addr:housenumber":"25",
    "addr:postcode":"2011 mr",
    "addr:street":"Kenaupark",
    "iso:country":"NL",
    "sg:address":"Kenaupark 25",
    "sg:city":"Haarlem",
    "sg:orig_category":"Kappers",
    "sg:phone":"+31 23 531 0716",
    "sg:postcode":"2011 MR",
    "sg:province":"North Holland",
    "wof:name":"Joop Van Der Laan",
    "wof:placetype":"venue"
},
  "geometry": {"coordinates":[4.6346769333,52.3867759705],"type":"Point"}
}