{
  "type": "Feature",
  "properties": {
    "iso:country":"NL",
    "sg:address":"Nieuwewg 1",
    "sg:city":"Poeldyk",
    "sg:orig_category":"Energiebedrijven",
    "sg:phone":"+31 174 236 500",
    "sg:postcode":"2685 AP",
    "sg:province":"Zuid-Holland",
    "sg:website":"http://www.westlandenergie.nl",
    "wof:name":"Westland Energie",
    "wof:placetype":"venue"
},
  "geometry": {"coordinates":[4.215951,52.025696],"type":"Point"}
}