{
  "type": "Feature",
  "properties": {
    "addr:full":"De Run 6811 Veldhoven Gelderland 5504 DW",
    "addr:housenumber":"6811",
    "addr:postcode":"5504 dw",
    "addr:street":"De Run;Gelderland",
    "iso:country":"NL",
    "sg:address":"De Run 6811",
    "sg:city":"Veldhoven",
    "sg:orig_category":"Elektronische Bedrijfsinstallaties",
    "sg:phone":"+31 40 254 2252",
    "sg:postcode":"5504 DW",
    "sg:province":"Gelderland",
    "wof:name":"Solyscreen Rolluiken En Zonwering Bv",
    "wof:placetype":"venue"
},
  "geometry": {"coordinates":[5.409635,51.403255],"type":"Point"}
}