{
  "type": "Feature",
  "properties": {
    "iso:country":"NL",
    "sg:address":"Zuidgouw 1",
    "sg:city":"Ursem",
    "sg:orig_category":"Peuterspeelzalen",
    "sg:phone":"+31 72 502 2089",
    "sg:postcode":"1645 PA",
    "sg:province":"North Holland",
    "wof:name":"Ursem",
    "wof:placetype":"venue"
},
  "geometry": {"coordinates":[4.89289,52.62611],"type":"Point"}
}