{
  "type": "Feature",
  "properties": {
    "addr:full":"Straatwg 130B Breukelen Ut Utrecht 3621 BV",
    "addr:housenumber":"130b",
    "addr:postcode":"3621 bv",
    "iso:country":"NL",
    "sg:address":"Straatwg 130B",
    "sg:city":"Breukelen Ut",
    "sg:orig_category":"Boekhandels",
    "sg:phone":"+31 346 265 711",
    "sg:postcode":"3621 BV",
    "sg:province":"Utrecht",
    "wof:name":"Plantage",
    "wof:placetype":"venue"
},
  "geometry": {"coordinates":[5.001595,52.172562],"type":"Point"}
}