{
  "type": "Feature",
  "properties": {
    "iso:country":"NL",
    "sg:address":"Oranjelaan 20",
    "sg:city":"De Meern",
    "sg:orig_category":"Banken And Kredietinstellingen",
    "sg:phone":"+31 30 666 1290",
    "sg:postcode":"3454 BT",
    "sg:province":"Utrecht",
    "wof:name":"Postkantoor",
    "wof:placetype":"venue"
},
  "geometry": {"coordinates":[5.039404,52.079708],"type":"Point"}
}