{
  "type": "Feature",
  "properties": {
    "iso:country":"NL",
    "sg:address":"K Doormanln 79",
    "sg:city":"Zwyndrecht",
    "sg:classifiers":[
        {
            "category":"Travel",
            "subcategory":"Hotels & Motels",
            "type":"Entertainment"
        }
    ],
    "sg:phone":"+31 78 619 5060",
    "sg:postcode":"3333 AK",
    "sg:province":"South Holland",
    "wof:name":"Karel Doorman",
    "wof:placetype":"venue"
},
  "geometry": {"coordinates":[4.63394,51.81358],"type":"Point"}
}