{
  "type": "Feature",
  "properties": {
    "iso:country":"NL",
    "sg:address":"Kuiperstr 52",
    "sg:city":"Vlaardingen",
    "sg:orig_category":"Kinderkleding",
    "sg:phone":"+31 10 434 8440",
    "sg:postcode":"3131 CH",
    "sg:province":"South Holland",
    "wof:name":"Boefjes, De",
    "wof:placetype":"venue"
},
  "geometry": {"coordinates":[4.34187,51.909142],"type":"Point"}
}