{
  "type": "Feature",
  "properties": {
    "addr:full":"Gaaspstraat 41 Amsterdam North Holland 1079 VC",
    "addr:housenumber":"41",
    "addr:postcode":"1079 vc",
    "addr:street":"Gaaspstraat",
    "iso:country":"NL",
    "sg:address":"Gaaspstraat 41",
    "sg:city":"Amsterdam",
    "sg:orig_category":"Bloemen And Planten",
    "sg:phone":"+31 20 642 1734",
    "sg:postcode":"1079 VC",
    "sg:province":"North Holland",
    "wof:name":"Bloemen- En Plantenhal Van Ogtropix",
    "wof:placetype":"venue"
},
  "geometry": {"coordinates":[4.908652,52.344028],"type":"Point"}
}