{
  "type": "Feature",
  "properties": {
    "addr:full":"O L Vrouwestr 181 Zegge Noord-Brabant 4735 AD",
    "addr:housenumber":"181",
    "addr:postcode":"4735 ad",
    "addr:street":"O;Zegge",
    "iso:country":"NL",
    "sg:address":"O L Vrouwestr 181",
    "sg:city":"Zegge",
    "sg:orig_category":"Fietsen En Bromfietsen",
    "sg:phone":"+31 165 540 893",
    "sg:postcode":"4735 AD",
    "sg:province":"Noord-Brabant",
    "wof:name":"Overveld, A Van",
    "wof:placetype":"venue"
},
  "geometry": {"coordinates":[4.516585,51.556709],"type":"Point"}
}