{
  "type": "Feature",
  "properties": {
    "addr:full":"Houtmarkt 47A Haarlem North Holland 2011 AL",
    "addr:housenumber":"47a",
    "addr:postcode":"2011 al",
    "addr:street":"Houtmarkt",
    "iso:country":"NL",
    "sg:address":"Houtmarkt 47A",
    "sg:city":"Haarlem",
    "sg:orig_category":"Psychotherapeuten",
    "sg:phone":"+31 23 533 9079",
    "sg:postcode":"2011 AL",
    "sg:province":"North Holland",
    "wof:name":"Keerpunt",
    "wof:placetype":"venue"
},
  "geometry": {"coordinates":[4.644638,52.380524],"type":"Point"}
}