{
  "type": "Feature",
  "properties": {
    "addr:full":"Lg Brink 90 Apeldoorn Gelderland 7317 BD",
    "addr:housenumber":"90",
    "addr:postcode":"7317 bd",
    "addr:street":"Lg Brink;Gelderland",
    "iso:country":"NL",
    "sg:address":"Lg Brink 90",
    "sg:city":"Apeldoorn",
    "sg:orig_category":"Kermisexploitatie",
    "sg:phone":"+31 55 521 1954",
    "sg:postcode":"7317 BD",
    "sg:province":"Gelderland",
    "wof:name":"Dauphin, G J H",
    "wof:placetype":"venue"
},
  "geometry": {"coordinates":[5.971983,52.244843],"type":"Point"}
}