{
  "type": "Feature",
  "properties": {
    "addr:full":"Wulp 14 Diemen North Holland 1111 WJ",
    "addr:housenumber":"14",
    "addr:postcode":"1111 wj",
    "addr:street":"Wulp",
    "iso:country":"NL",
    "sg:address":"Wulp 14",
    "sg:city":"Diemen",
    "sg:orig_category":"Kappers",
    "sg:phone":"+31 20 690 9169",
    "sg:postcode":"1111 WJ",
    "sg:province":"North Holland",
    "wof:name":"Bresseleers, M J M",
    "wof:placetype":"venue"
},
  "geometry": {"coordinates":[4.9759669304,52.350025177],"type":"Point"}
}