{
  "type": "Feature",
  "properties": {
    "addr:full":"Dukaatslag 69 Houten Utrecht 3991 TB",
    "addr:housenumber":"69",
    "addr:postcode":"3991 tb",
    "addr:street":"Dukaatslag",
    "iso:country":"NL",
    "sg:address":"Dukaatslag 69",
    "sg:city":"Houten",
    "sg:orig_category":"Artsen - Huisartsen",
    "sg:phone":"+31 30 637 4660",
    "sg:postcode":"3991 TB",
    "sg:province":"Utrecht",
    "sg:website":"http://www.hapdukaatslag.praktijkinfo.nl",
    "wof:name":"Deijns En E C De Goede, V A J",
    "wof:placetype":"venue"
},
  "geometry": {"coordinates":[5.151402,52.030842],"type":"Point"}
}