{
  "type": "Feature",
  "properties": {
    "addr:full":"1E Pauwenlandstr 32 Deventer Overijssel 7413 ZA",
    "addr:housenumber":"32",
    "addr:postcode":"7413",
    "addr:street":"1E Pauwenlandstr",
    "iso:country":"NL",
    "sg:address":"1E Pauwenlandstr 32",
    "sg:city":"Deventer",
    "sg:orig_category":"Verf En Lak",
    "sg:phone":"+31 570 623 080",
    "sg:postcode":"7413 ZA",
    "sg:province":"Overijssel",
    "sg:website":"http://www.decohome.nl",
    "wof:name":"Kastelein",
    "wof:placetype":"venue"
},
  "geometry": {"coordinates":[6.164327,52.257832],"type":"Point"}
}