{
  "type": "Feature",
  "properties": {
    "iso:country":"NL",
    "sg:address":"Tongelresestraat 268",
    "sg:city":"Eindhoven",
    "sg:orig_category":"Kappers",
    "sg:phone":"+31 40 245 6898",
    "sg:postcode":"5613 DV",
    "sg:province":"Noord-Brabant",
    "wof:name":"T Kappertje",
    "wof:placetype":"venue"
},
  "geometry": {"coordinates":[5.5022540092,51.4418754578],"type":"Point"}
}