{
  "type": "Feature",
  "properties": {
    "iso:country":"NL",
    "sg:address":"Maasstraat 9",
    "sg:city":"Nijmegen",
    "sg:orig_category":"Elektronische Bedrijfsinstallaties",
    "sg:phone":"+31 24 378 3344",
    "sg:postcode":"6541 ZB",
    "sg:province":"Gelderland",
    "wof:name":"Kuspa",
    "wof:placetype":"venue"
},
  "geometry": {"coordinates":[5.845548,51.849243],"type":"Point"}
}