{
  "type": "Feature",
  "properties": {
    "iso:country":"NL",
    "sg:address":"Sinnigvelderstraat 61",
    "sg:city":"Weesp",
    "sg:orig_category":"Metaalbekleding And -Behandeling",
    "sg:phone":"+31 294 410 400",
    "sg:postcode":"1382 EP",
    "sg:province":"North Holland",
    "wof:name":"Tro Techniek",
    "wof:placetype":"venue"
},
  "geometry": {"coordinates":[5.028872,52.310749],"type":"Point"}
}