{
  "type": "Feature",
  "properties": {
    "addr:full":"Tennesseedreef 24 Utrecht Utrecht 3565 CJ",
    "addr:housenumber":"24",
    "addr:postcode":"3565 cj",
    "addr:street":"Tennesseedreef",
    "iso:country":"NL",
    "sg:address":"Tennesseedreef 24",
    "sg:city":"Utrecht",
    "sg:orig_category":"Horecabenodigdheden",
    "sg:phone":"+31 30 264 1444",
    "sg:postcode":"3565 CJ",
    "sg:province":"Utrecht",
    "wof:name":"Groot, Jan De",
    "wof:placetype":"venue"
},
  "geometry": {"coordinates":[5.084128,52.130669],"type":"Point"}
}