{
  "type": "Feature",
  "properties": {
    "addr:full":"Jhr Sixhof 10 Kortenhoef Noord-Holland 1241 CR",
    "addr:housenumber":"10",
    "addr:postcode":"1241 cr",
    "addr:street":"Jhr Sixhof",
    "iso:country":"NL",
    "sg:address":"Jhr Sixhof 10",
    "sg:city":"Kortenhoef",
    "sg:orig_category":"Administratie- En Boekhoudkantoren",
    "sg:phone":"+31 35 656 2444",
    "sg:postcode":"1241 CR",
    "sg:province":"Noord-Holland",
    "wof:name":"Amks",
    "wof:placetype":"venue"
},
  "geometry": {"coordinates":[5.1203708649,52.241859436],"type":"Point"}
}