{
  "type": "Feature",
  "properties": {
    "addr:full":"Dorpsdk 50 Rhoon Zuid-Holland 3161 KG",
    "addr:housenumber":"50",
    "addr:postcode":"3161 kg",
    "addr:street":"Dorpsdk",
    "iso:country":"NL",
    "sg:address":"Dorpsdk 50",
    "sg:city":"Rhoon",
    "sg:orig_category":"Scheepvaart- Agentschappen",
    "sg:phone":"+31 10 506 0155",
    "sg:postcode":"3161 KG",
    "sg:province":"Zuid-Holland",
    "wof:name":"Hugo Trumpy Bv",
    "wof:placetype":"venue"
},
  "geometry": {"coordinates":[4.417685,51.859196],"type":"Point"}
}