{
  "type": "Feature",
  "properties": {
    "addr:full":"Oude Oppenh Wg 6 Sneek Friesland 8606 JC",
    "addr:housenumber":"6",
    "addr:postcode":"8606 jc",
    "addr:street":"Oude;Wg",
    "iso:country":"NL",
    "sg:address":"Oude Oppenh Wg 6",
    "sg:city":"Sneek",
    "sg:orig_category":"Zoetwaren - Fabrieken En Groothandel",
    "sg:phone":"+31 515 414 045",
    "sg:postcode":"8606 JC",
    "sg:province":"Friesland",
    "wof:name":"Rbv Leaf Bv",
    "wof:placetype":"venue"
},
  "geometry": {"coordinates":[5.67283,53.028278],"type":"Point"}
}