{
  "type": "Feature",
  "properties": {
    "iso:country":"NL",
    "sg:address":"Tolakkerweg 162",
    "sg:city":"Hollandsche Rading",
    "sg:orig_category":"Bloemen And Planten",
    "sg:phone":"+31 35 577 1222",
    "sg:postcode":"3739 JT",
    "sg:province":"Utrecht",
    "wof:name":"Orchideeen Wubben",
    "wof:placetype":"venue"
},
  "geometry": {"coordinates":[5.173138,52.171993],"type":"Point"}
}