{
  "type": "Feature",
  "properties": {
    "iso:country":"NL",
    "sg:address":"Schutsboomstr 23A",
    "sg:city":"Schayk",
    "sg:orig_category":"Verf En Lak",
    "sg:phone":"+31 486 463 686",
    "sg:postcode":"5374 CA",
    "sg:province":"California",
    "wof:name":"Profiel Schayk",
    "wof:placetype":"venue"
},
  "geometry": {"coordinates":[-119.270203,37.271832],"type":"Point"}
}