{
  "type": "Feature",
  "properties": {
    "addr:full":"Burchtstraat 3 Middelstum Groningen 9991 AA",
    "addr:housenumber":"3",
    "addr:postcode":"9991 aa",
    "addr:street":"Burchtstraat",
    "iso:country":"NL",
    "sg:address":"Burchtstraat 3",
    "sg:city":"Middelstum",
    "sg:orig_category":"Kappers",
    "sg:phone":"+31 595 551 586",
    "sg:postcode":"9991 AA",
    "sg:province":"Groningen",
    "wof:name":"Fa Tabak",
    "wof:placetype":"venue"
},
  "geometry": {"coordinates":[6.6427388191,53.3491401672],"type":"Point"}
}