{
  "type": "Feature",
  "properties": {
    "iso:country":"NL",
    "sg:address":"Goirkestr 126",
    "sg:city":"Tilburg",
    "sg:orig_category":"Machineonderhoud En -Reparatie",
    "sg:phone":"+31 13 542 4390",
    "sg:postcode":"5046 GP",
    "sg:province":"Noord-Brabant",
    "wof:name":"Schoenmakers, A",
    "wof:placetype":"venue"
},
  "geometry": {"coordinates":[5.077666,51.569679],"type":"Point"}
}