{
  "type": "Feature",
  "properties": {
    "addr:full":"St. Bavostraat 104A Rijsbergen Noord-Brabant 4891 CK",
    "addr:housenumber":"104a",
    "addr:postcode":"4891 ck",
    "addr:street":"St. Bavostraat",
    "iso:country":"NL",
    "sg:address":"St. Bavostraat 104A",
    "sg:city":"Rijsbergen",
    "sg:orig_category":"Landbouwmachines Gh",
    "sg:phone":"+31 76 596 2059",
    "sg:postcode":"4891 CK",
    "sg:province":"Noord-Brabant",
    "wof:name":"Agrarische Bedrijfsuitrusting Abemec Bv",
    "wof:placetype":"venue"
},
  "geometry": {"coordinates":[4.70113,51.51572],"type":"Point"}
}