{
  "type": "Feature",
  "properties": {
    "addr:full":"Amstelveenseweg 146/148 Amsterdam Noord-Holland 1075 XM",
    "addr:housenumber":"146 / 148",
    "addr:postcode":"1075 xm",
    "addr:street":"Amstelveenseweg",
    "iso:country":"NL",
    "sg:address":"Amstelveenseweg 146/148",
    "sg:city":"Amsterdam",
    "sg:orig_category":"Binnenhuisarchitecten",
    "sg:phone":"+31 20 305 1162",
    "sg:postcode":"1075 XM",
    "sg:province":"Noord-Holland",
    "wof:name":"Oscar Trends",
    "wof:placetype":"venue"
},
  "geometry": {"coordinates":[4.855445,52.353912],"type":"Point"}
}