{
  "type": "Feature",
  "properties": {
    "iso:country":"NL",
    "sg:address":"Oud Bodegraafsewg 2",
    "sg:city":"Bodegraven",
    "sg:orig_category":"Fietsen En Bromfietsen",
    "sg:phone":"+31 172 612 977",
    "sg:postcode":"2411 HS",
    "sg:province":"Zuid-Holland",
    "wof:name":"Veelenturf Bv",
    "wof:placetype":"venue"
},
  "geometry": {"coordinates":[4.74512,52.084499],"type":"Point"}
}