{
  "type": "Feature",
  "properties": {
    "addr:full":"Oosterstraat 14 Steenwijk NL.08 8331 HD",
    "addr:housenumber":"14;nl.08",
    "addr:postcode":"8331 hd",
    "addr:street":"Oosterstraat",
    "iso:country":"NL",
    "sg:address":"Oosterstraat 14",
    "sg:city":"Steenwijk",
    "sg:orig_category":"Herenmodezaken",
    "sg:phone":"+31 521 511 001",
    "sg:postcode":"8331 HD",
    "sg:province":"NL.08",
    "wof:name":"Intens",
    "wof:placetype":"venue"
},
  "geometry": {"coordinates":[6.118138,52.787308],"type":"Point"}
}