{
  "type": "Feature",
  "properties": {
    "addr:full":"Gareel 36 Hasselt Overijssel 8061 MZ",
    "addr:housenumber":"36",
    "addr:postcode":"8061 mz",
    "addr:street":"Gareel",
    "iso:country":"NL",
    "sg:address":"Gareel 36",
    "sg:city":"Hasselt",
    "sg:orig_category":"Verenigingen En Stichtingen",
    "sg:phone":"+31 38 344 6525",
    "sg:postcode":"8061 MZ",
    "sg:province":"Overijssel",
    "wof:name":"Vrienden Van D'Olde Mesiene, Sticht",
    "wof:placetype":"venue"
},
  "geometry": {"coordinates":[6.107451,52.597221],"type":"Point"}
}