{
  "type": "Feature",
  "properties": {
    "addr:full":"Parallelwg 13 Hierden Gelderland 3849 MJ",
    "addr:housenumber":"13",
    "addr:postcode":"3849 mj",
    "addr:street":"Parallelwg;Gelderland",
    "iso:country":"NL",
    "sg:address":"Parallelwg 13",
    "sg:city":"Hierden",
    "sg:orig_category":"Meubelen Gebruikte",
    "sg:phone":"+31 341 420 973",
    "sg:postcode":"3849 MJ",
    "sg:province":"Gelderland",
    "wof:name":"Jarikos",
    "wof:placetype":"venue"
},
  "geometry": {"coordinates":[5.662231,52.342819],"type":"Point"}
}