{
  "type": "Feature",
  "properties": {
    "addr:full":"Westersingel 68 Sneek Provincie Friesland 8601 EP",
    "addr:housenumber":"68;8601 ep",
    "addr:street":"Westersingel;Provincie Friesland",
    "iso:country":"NL",
    "sg:address":"Westersingel 68",
    "sg:city":"Sneek",
    "sg:orig_category":"Verzekeringen",
    "sg:phone":"+31 515 417 062",
    "sg:postcode":"8601 EP",
    "sg:province":"Provincie Friesland",
    "wof:name":"Assurantiekantoor R.H. Osinga",
    "wof:placetype":"venue"
},
  "geometry": {"coordinates":[5.658019,53.029659],"type":"Point"}
}