{
  "type": "Feature",
  "properties": {
    "addr:full":"Grotestr 132A Waalwyk Noord-Brabant 5141 HC",
    "addr:housenumber":"132a",
    "addr:postcode":"5141 hc",
    "addr:street":"Waalwyk",
    "iso:country":"NL",
    "sg:address":"Grotestr 132A",
    "sg:city":"Waalwyk",
    "sg:orig_category":"Accountants - Administratie- Consulenten En -Kantoren",
    "sg:phone":"+31 416 567 878",
    "sg:postcode":"5141 HC",
    "sg:province":"Noord-Brabant",
    "sg:website":"http://www.hofgroep.nl",
    "wof:name":"Hof Groep Ned Bv",
    "wof:placetype":"venue"
},
  "geometry": {"coordinates":[5.062876,51.689789],"type":"Point"}
}