{
  "type": "Feature",
  "properties": {
    "addr:full":"St Antoniesluis 31 Amsterdam Noord-Holland 1011 JB",
    "addr:housenumber":"31",
    "addr:postcode":"1011 jb",
    "addr:street":"St Antoniesluis",
    "iso:country":"NL",
    "sg:address":"St Antoniesluis 31",
    "sg:city":"Amsterdam",
    "sg:orig_category":"Beeldende Kunstenaars",
    "sg:phone":"+31 20 625 1069",
    "sg:postcode":"1011 JB",
    "sg:province":"Noord-Holland",
    "sg:website":"http://bernhardalbani.artolive.vom",
    "wof:name":"Albani, B",
    "wof:placetype":"venue"
},
  "geometry": {"coordinates":[4.90128,52.369946],"type":"Point"}
}