{
  "type": "Feature",
  "properties": {
    "addr:full":"Buizerdlaan 6 Nieuwegein Utrecht 3435 SB",
    "addr:housenumber":"6",
    "addr:postcode":"3435 sb",
    "addr:street":"Buizerdlaan",
    "iso:country":"NL",
    "sg:address":"Buizerdlaan 6",
    "sg:city":"Nieuwegein",
    "sg:orig_category":"Bedrijfsinventaris Gh",
    "sg:phone":"+31 30 603 9105",
    "sg:postcode":"3435 SB",
    "sg:province":"Utrecht",
    "wof:name":"Herman Jacobs Design Bv",
    "wof:placetype":"venue"
},
  "geometry": {"coordinates":[5.068993,52.027054],"type":"Point"}
}