{
  "type": "Feature",
  "properties": {
    "addr:full":"Niekerkerdiep Nz 13 Briltil Groningen 9805 TG",
    "addr:housenumber":"13",
    "addr:postcode":"9805 tg",
    "addr:street":"Niekerkerdiep Nz",
    "iso:country":"NL",
    "sg:address":"Niekerkerdiep Nz 13",
    "sg:city":"Briltil",
    "sg:orig_category":"Acupunctuur",
    "sg:phone":"+31 594 500 179",
    "sg:postcode":"9805 TG",
    "sg:province":"Groningen",
    "wof:name":"Tesselaar, R J F",
    "wof:placetype":"venue"
},
  "geometry": {"coordinates":[6.375861,53.2388],"type":"Point"}
}