{
  "type": "Feature",
  "properties": {
    "iso:country":"NL",
    "sg:address":"Westerwg 20A",
    "sg:city":"Den Burg",
    "sg:orig_category":"Vakantieverblijven",
    "sg:phone":"+31 222 311 262",
    "sg:postcode":"1791 PH",
    "sg:province":"Noord-Holland",
    "wof:name":"Immetjes Hoeve",
    "wof:placetype":"venue"
},
  "geometry": {"coordinates":[4.777058,53.050892],"type":"Point"}
}