{
  "type": "Feature",
  "properties": {
    "iso:country":"NL",
    "sg:address":"Meerlesewg 7",
    "sg:city":"Ulicoten",
    "sg:orig_category":"Milieu",
    "sg:phone":"+31 13 519 9476",
    "sg:postcode":"5113 BL",
    "sg:province":"North Brabant",
    "wof:name":"Kennes",
    "wof:placetype":"venue"
},
  "geometry": {"coordinates":[4.848504,51.459881],"type":"Point"}
}