{
  "type": "Feature",
  "properties": {
    "addr:full":"Isabellaland 2282 S Gravenhage Zuid-Holland 2591 CZ",
    "addr:housenumber":"2282;gravenhage;2591",
    "addr:street":"Isabellaland;S",
    "iso:country":"NL",
    "sg:address":"Isabellaland 2282",
    "sg:city":"S Gravenhage",
    "sg:orig_category":"Onderhoudswerken",
    "sg:phone":"+31 70 366 5434",
    "sg:postcode":"2591 CZ",
    "sg:province":"Zuid-Holland",
    "wof:name":"Dewus",
    "wof:placetype":"venue"
},
  "geometry": {"coordinates":[4.33481,52.050961],"type":"Point"}
}