{
  "type": "Feature",
  "properties": {
    "addr:full":"Pal Maleterstraat 42 Utrecht Utrecht 3573 PH",
    "addr:housenumber":"42",
    "addr:postcode":"3573",
    "addr:street":"Pal Maleterstraat",
    "iso:country":"NL",
    "sg:address":"Pal Maleterstraat 42",
    "sg:city":"Utrecht",
    "sg:orig_category":"Schilderwerk",
    "sg:phone":"+31 30 273 5084",
    "sg:postcode":"3573 PH",
    "sg:province":"Utrecht",
    "wof:name":"Van Selm Schilder- En Afwerkingsbedrijf",
    "wof:placetype":"venue"
},
  "geometry": {"coordinates":[5.143319,52.108067],"type":"Point"}
}