{
  "type": "Feature",
  "properties": {
    "addr:full":"J Luikenstr 44 Eindhoven Noord-Brabant 5615 JM",
    "addr:housenumber":"44",
    "addr:postcode":"5615 jm",
    "iso:country":"NL",
    "sg:address":"J Luikenstr 44",
    "sg:city":"Eindhoven",
    "sg:orig_category":"Parkeersystemen",
    "sg:phone":"+31 40 292 0740",
    "sg:postcode":"5615 JM",
    "sg:province":"Noord-Brabant",
    "sg:website":"http://www.cvss.nl",
    "wof:name":"Cvss",
    "wof:placetype":"venue"
},
  "geometry": {"coordinates":[5.472777,51.428764],"type":"Point"}
}