{
  "type": "Feature",
  "properties": {
    "addr:full":"Schoolstraat 2 Petten North Holland 1755 NE",
    "addr:housenumber":"2",
    "addr:postcode":"1755 ne",
    "addr:street":"Schoolstraat",
    "iso:country":"NL",
    "sg:address":"Schoolstraat 2",
    "sg:city":"Petten",
    "sg:classifiers":[
        {
            "category":"Education",
            "subcategory":"Preschool",
            "type":"Public Place"
        }
    ],
    "sg:phone":"+31 226 381 920",
    "sg:postcode":"1755 NE",
    "sg:province":"North Holland",
    "sg:tags":[
        "kleuteronderwijs",
        "basis-"
    ],
    "wof:name":"Openbare Basisschool De Springschans",
    "wof:placetype":"venue"
},
  "geometry": {"coordinates":[4.66518,52.767647],"type":"Point"}
}