{
  "type": "Feature",
  "properties": {
    "iso:country":"NL",
    "sg:address":"Javastraat 136",
    "sg:city":"'S Gravenhage",
    "sg:orig_category":"Werving And Selectie Van Tijdelijk Personeel And Uitzendkantoren",
    "sg:phone":"+31 70 363 2956",
    "sg:postcode":"2585 AX",
    "sg:province":"Zuid-Holland",
    "wof:name":"Manpower Uitzendorganisatie Bv",
    "wof:placetype":"venue"
},
  "geometry": {"coordinates":[4.3108739853,52.0895462036],"type":"Point"}
}