{
  "type": "Feature",
  "properties": {
    "addr:full":"Heirbaan 6 Moergestel North Brabant 5066 CN",
    "addr:housenumber":"6",
    "addr:postcode":"5066 cn",
    "addr:street":"Heirbaan",
    "iso:country":"NL",
    "sg:address":"Heirbaan 6",
    "sg:city":"Moergestel",
    "sg:orig_category":"Loodgieterswerk, Verwarming And Sanitaire Installaties",
    "sg:phone":"+31 13 513 3275",
    "sg:postcode":"5066 CN",
    "sg:province":"North Brabant",
    "wof:name":"A.G. Van Doormaal",
    "wof:placetype":"venue"
},
  "geometry": {"coordinates":[5.219696,51.531166],"type":"Point"}
}