{
  "type": "Feature",
  "properties": {
    "addr:full":"Rapenburgerstr 774 Amsterdam Noord-Holland 1011 VK",
    "addr:housenumber":"774",
    "addr:postcode":"1011 vk",
    "iso:country":"NL",
    "sg:address":"Rapenburgerstr 774",
    "sg:city":"Amsterdam",
    "sg:orig_category":"Beeldende Kunstenaars",
    "sg:phone":"+31 20 422 1294",
    "sg:postcode":"1011 VK",
    "sg:province":"Noord-Holland",
    "wof:name":"Majel V/D Meulen",
    "wof:placetype":"venue"
},
  "geometry": {"coordinates":[4.90588,52.368301],"type":"Point"}
}