{
  "type": "Feature",
  "properties": {
    "addr:full":"Statensngl 4 Ysselstein Ut Utrecht 3404 ZT",
    "addr:housenumber":"4",
    "addr:postcode":"3404 zt",
    "addr:street":"Statensngl",
    "iso:country":"NL",
    "sg:address":"Statensngl 4",
    "sg:city":"Ysselstein Ut",
    "sg:orig_category":"Autopoetsbedrijven",
    "sg:phone":"+31 30 688 0185",
    "sg:postcode":"3404 ZT",
    "sg:province":"Utrecht",
    "wof:name":"Zaffa Bv",
    "wof:placetype":"venue"
},
  "geometry": {"coordinates":[5.03968,52.008289],"type":"Point"}
}