{
  "type": "Feature",
  "properties": {
    "addr:full":"Sportwg 20 Hoevelaken Gelderland 3871 HH",
    "addr:housenumber":"20",
    "addr:postcode":"3871 hh",
    "addr:street":"Sportwg;Gelderland",
    "iso:country":"NL",
    "sg:address":"Sportwg 20",
    "sg:city":"Hoevelaken",
    "sg:orig_category":"Voetverzorging",
    "sg:phone":"+31 33 253 4511",
    "sg:postcode":"3871 HH",
    "sg:province":"Gelderland",
    "wof:name":"Bood, Annemarie",
    "wof:placetype":"venue"
},
  "geometry": {"coordinates":[5.454958,52.172874],"type":"Point"}
}