{
  "type": "Feature",
  "properties": {
    "iso:country":"NL",
    "sg:address":"Tolhuis 2415A",
    "sg:city":"Nymegen",
    "sg:orig_category":"Accountants - Administratie- Consulenten En -Kantoren",
    "sg:phone":"+31 24 343 0990",
    "sg:postcode":"6537 MG",
    "sg:province":"Gelderland",
    "wof:name":"Cj",
    "wof:placetype":"venue"
},
  "geometry": {"coordinates":[-45.451351,-18.57752],"type":"Point"}
}