{
  "type": "Feature",
  "properties": {
    "addr:full":"Hoeksteen 153 Hoofddorp North Holland 2132 MX",
    "addr:housenumber":"153",
    "addr:postcode":"2132 mx",
    "addr:street":"Hoeksteen",
    "iso:country":"NL",
    "sg:address":"Hoeksteen 153",
    "sg:city":"Hoofddorp",
    "sg:orig_category":"Luchtvrachtexpediteurs",
    "sg:phone":"+31 20 658 0011",
    "sg:postcode":"2132 MX",
    "sg:province":"North Holland",
    "wof:name":"Nagel Air Freight Nederland",
    "wof:placetype":"venue"
},
  "geometry": {"coordinates":[4.724231,52.291374],"type":"Point"}
}