{
  "type": "Feature",
  "properties": {
    "addr:full":"Wilhelminakade 5A Uithoorn Noord-Holland 1421 AB",
    "addr:housenumber":"5a",
    "addr:postcode":"1421 ab",
    "addr:street":"Wilhelminakade",
    "iso:country":"NL",
    "sg:address":"Wilhelminakade 5A",
    "sg:city":"Uithoorn",
    "sg:orig_category":"Beursorganisaties And Standbouw",
    "sg:phone":"+31 297 525 454",
    "sg:postcode":"1421 AB",
    "sg:province":"Noord-Holland",
    "sg:website":"http://www.fabevents.nl",
    "wof:name":"Fabevents",
    "wof:placetype":"venue"
},
  "geometry": {"coordinates":[4.834271,52.233433],"type":"Point"}
}