{
  "type": "Feature",
  "properties": {
    "iso:country":"NL",
    "sg:address":"Hoofdstraat 20",
    "sg:city":"Driebergen Rijsenburg",
    "sg:orig_category":"Artistiek Onderwijs",
    "sg:phone":"+31 343 533 880",
    "sg:postcode":"3972 LA",
    "sg:province":"Utrecht",
    "wof:name":"Werkgroepkunsten",
    "wof:placetype":"venue"
},
  "geometry": {"coordinates":[5.26308,52.063587],"type":"Point"}
}