{
  "type": "Feature",
  "properties": {
    "addr:full":"Dalmatie 3 Leusden Utrecht 3831 EE",
    "addr:housenumber":"3",
    "addr:postcode":"3831 ee",
    "addr:street":"Dalmatie",
    "iso:country":"NL",
    "sg:address":"Dalmatie 3",
    "sg:city":"Leusden",
    "sg:orig_category":"Juridische Dienstverlening",
    "sg:phone":"+31 33 432 3040",
    "sg:postcode":"3831 EE",
    "sg:province":"Utrecht",
    "wof:name":"Bureau Vd Spek Vof",
    "wof:placetype":"venue"
},
  "geometry": {"coordinates":[5.434553,52.135178],"type":"Point"}
}