{
  "type": "Feature",
  "properties": {
    "addr:full":"Domaniale Mynstr 30 Kerkrade Limburg 6462 HA",
    "addr:housenumber":"30",
    "addr:postcode":"6462 ha",
    "iso:country":"NL",
    "sg:address":"Domaniale Mynstr 30",
    "sg:city":"Kerkrade",
    "sg:orig_category":"Beeldende Kunstenaars",
    "sg:phone":"+31 45 567 0783",
    "sg:postcode":"6462 HA",
    "sg:province":"Limburg",
    "wof:name":"Thalen, Rob",
    "wof:placetype":"venue"
},
  "geometry": {"coordinates":[6.067357,50.859821],"type":"Point"}
}