{
  "type": "Feature",
  "properties": {
    "addr:full":"Schieringerweg 169 Leeuwarden Provincie Friesland 8924 HT",
    "addr:housenumber":"169",
    "addr:postcode":"8924 ht",
    "addr:street":"Schieringerweg;Provincie Friesland",
    "iso:country":"NL",
    "sg:address":"Schieringerweg 169",
    "sg:city":"Leeuwarden",
    "sg:orig_category":"Loodgieterswerk, Verwarming And Sanitaire Installaties",
    "sg:phone":"+31 6 26377956",
    "sg:postcode":"8924 HT",
    "sg:province":"Provincie Friesland",
    "wof:name":"Afbouw Sjors",
    "wof:placetype":"venue"
},
  "geometry": {"coordinates":[5.820866,53.21162],"type":"Point"}
}