{
  "type": "Feature",
  "properties": {
    "addr:full":"Garderenstr 22 Tilburg Noord-Brabant 5043 NG",
    "addr:housenumber":"22",
    "addr:postcode":"5043 ng",
    "addr:street":"Garderenstr",
    "iso:country":"NL",
    "sg:address":"Garderenstr 22",
    "sg:city":"Tilburg",
    "sg:orig_category":"Kunststoffen- Verwerkende Industrie",
    "sg:phone":"+31 13 570 2936",
    "sg:postcode":"5043 NG",
    "sg:province":"Noord-Brabant",
    "wof:name":"Iso-Air",
    "wof:placetype":"venue"
},
  "geometry": {"coordinates":[5.009635,51.582787],"type":"Point"}
}