{
  "type": "Feature",
  "properties": {
    "addr:full":"S Groenewegln 9 Amstelveen Noord-Holland 1183 EK",
    "addr:housenumber":"9",
    "addr:postcode":"1183 ek",
    "iso:country":"NL",
    "sg:address":"S Groenewegln 9",
    "sg:city":"Amstelveen",
    "sg:orig_category":"Psychologen",
    "sg:phone":"+31 20 640 7582",
    "sg:postcode":"1183 EK",
    "sg:province":"Noord-Holland",
    "sg:website":"http://healthfun.amstelveennet.nl",
    "wof:name":"Health Fun",
    "wof:placetype":"venue"
},
  "geometry": {"coordinates":[4.879064,52.313492],"type":"Point"}
}