{
  "type": "Feature",
  "properties": {
    "addr:full":"Kanaalstr 6A Lisse Zuid-Holland 2161 JL",
    "addr:housenumber":"6a",
    "addr:postcode":"2161 jl",
    "addr:street":"Kanaalstr",
    "iso:country":"NL",
    "sg:address":"Kanaalstr 6A",
    "sg:city":"Lisse",
    "sg:orig_category":"Woningbureaus",
    "sg:phone":"+31 252 225 450",
    "sg:postcode":"2161 JL",
    "sg:province":"Zuid-Holland",
    "sg:website":"http://www.interhouse.nl",
    "wof:name":"Interhouse",
    "wof:placetype":"venue"
},
  "geometry": {"coordinates":[4.5549712181,52.260509491],"type":"Point"}
}