{
  "type": "Feature",
  "properties": {
    "addr:full":"Marktstraat 88 Musselkanaal Groningen 9581 AD",
    "addr:housenumber":"88",
    "addr:postcode":"9581 ad",
    "addr:street":"Marktstraat",
    "iso:country":"NL",
    "sg:address":"Marktstraat 88",
    "sg:city":"Musselkanaal",
    "sg:orig_category":"Fruit And Groenten Gh",
    "sg:phone":"+31 599 413 049",
    "sg:postcode":"9581 AD",
    "sg:province":"Groningen",
    "wof:name":"Lubbers Bv",
    "wof:placetype":"venue"
},
  "geometry": {"coordinates":[7.015725,52.928509],"type":"Point"}
}