{
  "type": "Feature",
  "properties": {
    "iso:country":"NL",
    "sg:address":"Brink 12",
    "sg:city":"Den Ham Ov",
    "sg:orig_category":"Kappers",
    "sg:phone":"+31 546 671 247",
    "sg:postcode":"7683 BP",
    "sg:province":"Overijssel",
    "wof:name":"Kapsalon Kobes",
    "wof:placetype":"venue"
},
  "geometry": {"coordinates":[6.4956068993,52.4643669128],"type":"Point"}
}