{
  "type": "Feature",
  "properties": {
    "iso:country":"NL",
    "sg:address":"Lombertstraat 3",
    "sg:city":"Grave",
    "sg:orig_category":"Schoenen",
    "sg:phone":"+31 486 420 044",
    "sg:postcode":"5361 GR",
    "sg:province":"Arkansas",
    "wof:name":"Jit Mar Design And Selling",
    "wof:placetype":"venue"
},
  "geometry": {"coordinates":[-93.690285,34.884838],"type":"Point"}
}