{
  "type": "Feature",
  "properties": {
    "addr:full":"Heerbaan 123 Millingen Ad Ryn Gelderland 6566 EH",
    "addr:housenumber":"123",
    "addr:postcode":"6566 eh",
    "addr:street":"Heerbaan;Gelderland",
    "iso:country":"NL",
    "sg:address":"Heerbaan 123",
    "sg:city":"Millingen Ad Ryn",
    "sg:orig_category":"Artsen - Huisartsen",
    "sg:phone":"+31 481 432 244",
    "sg:postcode":"6566 EH",
    "sg:province":"Gelderland",
    "sg:website":"http://www.milbergen.nl",
    "wof:name":"Janssen, Dr G J T H",
    "wof:placetype":"venue"
},
  "geometry": {"coordinates":[6.044838,51.865295],"type":"Point"}
}