{
  "type": "Feature",
  "properties": {
    "addr:full":"Humbergweg 15 Botlek Rt Zuid-Holland 3197 KE",
    "addr:housenumber":"15",
    "addr:postcode":"rt;3197 ke",
    "addr:street":"Humbergweg",
    "iso:country":"NL",
    "sg:address":"Humbergweg 15",
    "sg:city":"Botlek Rt",
    "sg:orig_category":"Goederenvervoer Over De Weg",
    "sg:phone":"+31 181 212 344",
    "sg:postcode":"3197 KE",
    "sg:province":"Zuid-Holland",
    "wof:name":"Havenserv Rozenburg Bv",
    "wof:placetype":"venue"
},
  "geometry": {"coordinates":[4.25138,51.884109],"type":"Point"}
}