{
  "type": "Feature",
  "properties": {
    "addr:full":"Ginnekenweg 4 Breda Noord-Brabant 4818 JE",
    "addr:housenumber":"4",
    "addr:postcode":"4818 je",
    "addr:street":"Ginnekenweg",
    "iso:country":"NL",
    "sg:address":"Ginnekenweg 4",
    "sg:city":"Breda",
    "sg:orig_category":"Verlichting And Huishoudartikelen",
    "sg:phone":"+31 76 522 5527",
    "sg:postcode":"4818 JE",
    "sg:province":"Noord-Brabant",
    "wof:name":"Galerie Safi",
    "wof:placetype":"venue"
},
  "geometry": {"coordinates":[4.778804,51.578457],"type":"Point"}
}