{
  "type": "Feature",
  "properties": {
    "addr:full":"Apollostr 123 Rotterdam Zuid-Holland 3054 TA",
    "addr:housenumber":"123",
    "addr:postcode":"3054 ta",
    "iso:country":"NL",
    "sg:address":"Apollostr 123",
    "sg:city":"Rotterdam",
    "sg:orig_category":"Grafisch Ontwerpers",
    "sg:phone":"+31 10 461 3635",
    "sg:postcode":"3054 TA",
    "sg:province":"Zuid-Holland",
    "sg:website":"http://www.studioplankton.nl",
    "wof:name":"Plankton, Studio",
    "wof:placetype":"venue"
},
  "geometry": {"coordinates":[4.491393,51.962921],"type":"Point"}
}