{
  "type": "Feature",
  "properties": {
    "iso:country":"NL",
    "sg:address":"Gomarushof 29",
    "sg:city":"Hilversum",
    "sg:orig_category":"Boekhouders",
    "sg:phone":"+31 35 621 1392",
    "sg:postcode":"1216 HL",
    "sg:province":"Noord-Holland",
    "wof:name":"Mieke Van Vliet, Administraties",
    "wof:placetype":"venue"
},
  "geometry": {"coordinates":[5.139124,52.219666],"type":"Point"}
}