{
  "type": "Feature",
  "properties": {
    "addr:full":"Tractiewg 34 Utrecht Utrecht 3534 AP",
    "addr:housenumber":"34",
    "addr:postcode":"3534 ap",
    "addr:street":"Tractiewg",
    "iso:country":"NL",
    "sg:address":"Tractiewg 34",
    "sg:city":"Utrecht",
    "sg:orig_category":"Pluimveevoeder - Fabrieken En Groothandel",
    "sg:phone":"+31 30 243 0033",
    "sg:postcode":"3534 AP",
    "sg:province":"Utrecht",
    "wof:name":"Waard Utrecht Bv, De",
    "wof:placetype":"venue"
},
  "geometry": {"coordinates":[5.079818,52.106052],"type":"Point"}
}