{
  "type": "Feature",
  "properties": {
    "addr:full":"Hoofdstraat 177 Sassenheim South Holland 2171 BB",
    "addr:housenumber":"177",
    "addr:postcode":"2171 bb",
    "addr:street":"Hoofdstraat",
    "iso:country":"NL",
    "sg:address":"Hoofdstraat 177",
    "sg:city":"Sassenheim",
    "sg:orig_category":"Meubelzaken, Woning- And Keukeninrichting",
    "sg:phone":"+31 252 222 762",
    "sg:postcode":"2171 BB",
    "sg:province":"South Holland",
    "wof:name":"Slaapkamer/Matrassen Speciaalzaak Kelto",
    "wof:placetype":"venue"
},
  "geometry": {"coordinates":[4.520611,52.225533],"type":"Point"}
}