{
  "type": "Feature",
  "properties": {
    "iso:country":"NL",
    "sg:address":"Sluisstraat 32",
    "sg:city":"Veghel",
    "sg:classifiers":[
        {
            "category":"Fast Food",
            "type":"Food & Drink"
        }
    ],
    "sg:phone":"+31 413 343 279",
    "sg:postcode":"5462 CB",
    "sg:province":"North Brabant",
    "sg:tags":[
        "afhaal",
        "restaurant"
    ],
    "wof:name":"Snackbar 'T Sluiske",
    "wof:placetype":"venue"
},
  "geometry": {"coordinates":[5.537168,51.61348],"type":"Point"}
}