{
  "type": "Feature",
  "properties": {
    "addr:full":"De Twaalfmaat 16 Uitgeest Noord-Holland 1911 RD",
    "addr:housenumber":"16",
    "addr:postcode":"1911 rd",
    "addr:street":"De Twaalfmaat",
    "iso:country":"NL",
    "sg:address":"De Twaalfmaat 16",
    "sg:city":"Uitgeest",
    "sg:orig_category":"Goederenvervoer Over De Weg",
    "sg:phone":"+31 251 319 345",
    "sg:postcode":"1911 RD",
    "sg:province":"Noord-Holland",
    "wof:name":"E.F. Vegter",
    "wof:placetype":"venue"
},
  "geometry": {"coordinates":[4.709829,52.535061],"type":"Point"}
}