{
  "type": "Feature",
  "properties": {
    "iso:country":"NL",
    "sg:address":"St Jansgildestr 16",
    "sg:city":"Beek Gem Bergh",
    "sg:orig_category":"Matrijzen",
    "sg:phone":"+31 316 531 977",
    "sg:postcode":"7037 DM",
    "sg:province":"Gelderland",
    "wof:name":"Dexter",
    "wof:placetype":"venue"
},
  "geometry": {"coordinates":[6.195322,51.916107],"type":"Point"}
}