{
  "type": "Feature",
  "properties": {
    "addr:full":"L Stammerdk 18 Amsterdam Zuidoost North Holland 1109 BN",
    "addr:housenumber":"18",
    "addr:postcode":"1109 bn",
    "iso:country":"NL",
    "sg:address":"L Stammerdk 18",
    "sg:city":"Amsterdam Zuidoost",
    "sg:orig_category":"Kappers",
    "sg:phone":"+31 294 417 791",
    "sg:postcode":"1109 BN",
    "sg:province":"North Holland",
    "wof:name":"Griffioen, Rianne",
    "wof:placetype":"venue"
},
  "geometry": {"coordinates":[5.0165500641,52.305721283],"type":"Point"}
}