{
  "type": "Feature",
  "properties": {
    "addr:full":"Colijnstraat 70 Nunspeet Gelderland 8072 AW",
    "addr:housenumber":"70",
    "addr:postcode":"8072 aw",
    "addr:street":"Colijnstraat;Gelderland",
    "iso:country":"NL",
    "sg:address":"Colijnstraat 70",
    "sg:city":"Nunspeet",
    "sg:orig_category":"Banken And Kredietinstellingen",
    "sg:phone":"+31 341 271 362",
    "sg:postcode":"8072 AW",
    "sg:province":"Gelderland",
    "wof:name":"Rabobank",
    "wof:placetype":"venue"
},
  "geometry": {"coordinates":[5.80345,52.382729],"type":"Point"}
}