{
  "type": "Feature",
  "properties": {
    "iso:country":"NL",
    "sg:address":"Hofstraat 22",
    "sg:city":"Apeldoorn",
    "sg:orig_category":"Wasserettes And Stomerijen",
    "sg:phone":"+31 55 521 2875",
    "sg:postcode":"7311 KV",
    "sg:province":"Gelderland",
    "wof:name":"Palthe Stomerijen Bv",
    "wof:placetype":"venue"
},
  "geometry": {"coordinates":[5.9629268646,52.2118492126],"type":"Point"}
}