{
  "type": "Feature",
  "properties": {
    "addr:full":"Visafslagweg 3 'S Gravenhage Zuid-Holland 2583 DM",
    "addr:housenumber":"3 '",
    "addr:postcode":"2583 dm",
    "addr:street":"Visafslagweg",
    "iso:country":"NL",
    "sg:address":"Visafslagweg 3",
    "sg:city":"'S Gravenhage",
    "sg:orig_category":"Bedrijfsinventaris Gh",
    "sg:phone":"+31 70 350 0900",
    "sg:postcode":"2583 DM",
    "sg:province":"Zuid-Holland",
    "wof:name":"Koeltechn Handelsonderneming Gebr. Roeleveld",
    "wof:placetype":"venue"
},
  "geometry": {"coordinates":[4.263781,52.099987],"type":"Point"}
}