{
  "type": "Feature",
  "properties": {
    "addr:full":"Zijlstraat 90 Haarlem North Holland 2011 TR",
    "addr:housenumber":"90",
    "addr:postcode":"2011 tr",
    "addr:street":"Zijlstraat",
    "iso:country":"NL",
    "sg:address":"Zijlstraat 90",
    "sg:city":"Haarlem",
    "sg:orig_category":"Werving And Selectie Van Tijdelijk Personeel And Uitzendkantoren",
    "sg:phone":"+31 23 532 8950",
    "sg:postcode":"2011 TR",
    "sg:province":"North Holland",
    "wof:name":"Manpower Bv",
    "wof:placetype":"venue"
},
  "geometry": {"coordinates":[4.6340370178,52.3818321228],"type":"Point"}
}