{
  "type": "Feature",
  "properties": {
    "addr:full":"Donker Curtiusstraat 188 'S Gravenhage Zuid-Holland 2555 VX",
    "addr:housenumber":"188 '",
    "addr:postcode":"2555 vx",
    "addr:street":"Donker Curtiusstraat",
    "iso:country":"NL",
    "sg:address":"Donker Curtiusstraat 188",
    "sg:city":"'S Gravenhage",
    "sg:orig_category":"Medische Apparatuur And Prothesen Fab",
    "sg:phone":"+31 70 323 1611",
    "sg:postcode":"2555 VX",
    "sg:province":"Zuid-Holland",
    "wof:name":"H Terlouw",
    "wof:placetype":"venue"
},
  "geometry": {"coordinates":[4.247357,52.065792],"type":"Point"}
}