{
  "type": "Feature",
  "properties": {
    "iso:country":"NL",
    "sg:address":"Donker Curtiusstraat 188",
    "sg:city":"'S Gravenhage",
    "sg:orig_category":"Medische Apparatuur And Prothesen Fab",
    "sg:phone":"+31 70 323 1611",
    "sg:postcode":"2555 VX",
    "sg:province":"Zuid-Holland",
    "wof:name":"H Terlouw",
    "wof:placetype":"venue"
},
  "geometry": {"coordinates":[4.247357,52.065792],"type":"Point"}
}