{
  "type": "Feature",
  "properties": {
    "addr:full":"Verl Hoograv Wg 224 Utrecht Utrecht 3523 KH",
    "addr:housenumber":"224",
    "addr:postcode":"3523 kh",
    "addr:street":"Wg",
    "iso:country":"NL",
    "sg:address":"Verl Hoograv Wg 224",
    "sg:city":"Utrecht",
    "sg:orig_category":"Onderhoudswerken",
    "sg:phone":"+31 30 289 4760",
    "sg:postcode":"3523 KH",
    "sg:province":"Utrecht",
    "wof:name":"Hs2000",
    "wof:placetype":"venue"
},
  "geometry": {"coordinates":[5.118132,52.06683],"type":"Point"}
}