{
  "type": "Feature",
  "properties": {
    "addr:full":"Meerstr 9 Hillegom North Holland 2181 BH",
    "addr:housenumber":"9",
    "addr:postcode":"2181 bh",
    "addr:street":"Meerstr",
    "iso:country":"NL",
    "sg:address":"Meerstr 9",
    "sg:city":"Hillegom",
    "sg:orig_category":"Kinderkleding",
    "sg:phone":"+31 252 530 780",
    "sg:postcode":"2181 BH",
    "sg:province":"North Holland",
    "wof:name":"Vink",
    "wof:placetype":"venue"
},
  "geometry": {"coordinates":[4.58029,52.293217],"type":"Point"}
}