{
  "type": "Feature",
  "properties": {
    "iso:country":"NL",
    "sg:address":"Zeelantlaan 31",
    "sg:city":"Utrecht",
    "sg:orig_category":"Meubelzaken, Woning- And Keukeninrichting",
    "sg:phone":"+31 30 288 7878",
    "sg:postcode":"3526 AK",
    "sg:province":"Utrecht",
    "wof:name":"Lucky Leder",
    "wof:placetype":"venue"
},
  "geometry": {"coordinates":[5.101903,52.06263],"type":"Point"}
}