{
  "type": "Feature",
  "properties": {
    "addr:full":"Dalweg 33 Eexterzandvoort Provincie Drenthe 9464 TE",
    "addr:housenumber":"33;9464",
    "addr:postcode":"te",
    "addr:street":"Dalweg;Provincie Drenthe",
    "iso:country":"NL",
    "sg:address":"Dalweg 33",
    "sg:city":"Eexterzandvoort",
    "sg:orig_category":"Goederenvervoer Over De Weg",
    "sg:phone":"+31 598 468 135",
    "sg:postcode":"9464 TE",
    "sg:province":"Provincie Drenthe",
    "wof:name":"H. Schipper Hzn.",
    "wof:placetype":"venue"
},
  "geometry": {"coordinates":[6.795002,53.033161],"type":"Point"}
}