{
  "type": "Feature",
  "properties": {
    "addr:full":"Dahliaveld 3 Nieuwerkerk Yssel Zuid-Holland 2914 CA",
    "addr:housenumber":"3",
    "addr:postcode":"2914 ca",
    "addr:street":"Dahliaveld",
    "iso:country":"NL",
    "sg:address":"Dahliaveld 3",
    "sg:city":"Nieuwerkerk Yssel",
    "sg:orig_category":"Autorijscholen",
    "sg:phone":"+31 180 321 776",
    "sg:postcode":"2914 CA",
    "sg:province":"Zuid-Holland",
    "wof:name":"Sh Verkeersschool",
    "wof:placetype":"venue"
},
  "geometry": {"coordinates":[4.619418,51.970684],"type":"Point"}
}