{
  "type": "Feature",
  "properties": {
    "addr:full":"Lynbaan 5 Gorredyk Friesland 8401 VL",
    "addr:housenumber":"5",
    "addr:postcode":"8401 vl",
    "addr:street":"Lynbaan",
    "iso:country":"NL",
    "sg:address":"Lynbaan 5",
    "sg:city":"Gorredyk",
    "sg:orig_category":"Drukkerijen",
    "sg:phone":"+31 513 463 863",
    "sg:postcode":"8401 VL",
    "sg:province":"Friesland",
    "wof:name":"Lageveen",
    "wof:placetype":"venue"
},
  "geometry": {"coordinates":[6.06447,53.00478],"type":"Point"}
}