{
  "type": "Feature",
  "properties": {
    "addr:full":"Nassaupln 14 S Gravenhage Zuid-Holland 2585 EB",
    "addr:housenumber":"14;gravenhage",
    "addr:postcode":"2585 eb",
    "addr:street":"Nassaupln;S",
    "iso:country":"NL",
    "sg:address":"Nassaupln 14",
    "sg:city":"S Gravenhage",
    "sg:orig_category":"Adviesbureaus Bedrijfsorganisatie",
    "sg:phone":"+31 70 364 3028",
    "sg:postcode":"2585 EB",
    "sg:province":"Zuid-Holland",
    "sg:website":"http://www.bellherrmann.nl",
    "wof:name":"Bell & Herrmann",
    "wof:placetype":"venue"
},
  "geometry": {"coordinates":[4.29777,52.094799],"type":"Point"}
}