{
  "type": "Feature",
  "properties": {
    "addr:full":"Maasstraat 61-63 Amsterdam Noord-Holland 1078 HD",
    "addr:housenumber":"61-63",
    "addr:postcode":"1078 hd",
    "addr:street":"Maasstraat",
    "iso:country":"NL",
    "sg:address":"Maasstraat 61-63",
    "sg:city":"Amsterdam",
    "sg:classifiers":[
        {
            "category":"Retail",
            "subcategory":"Photofinishing",
            "type":"Services"
        }
    ],
    "sg:phone":"+31 20 671 1903",
    "sg:postcode":"1078 HD",
    "sg:province":"Noord-Holland",
    "sg:tags":[
        "foto",
        "film"
    ],
    "wof:name":"Foto Sanders & Rozemeijer Bv",
    "wof:placetype":"venue"
},
  "geometry": {"coordinates":[4.895035,52.345478],"type":"Point"}
}