{
  "type": "Feature",
  "properties": {
    "addr:full":"Jacob Barneveldstraat 19 Linschoten Utrecht 3461 GA",
    "addr:housenumber":"19",
    "addr:postcode":"3461 ga",
    "addr:street":"Jacob Barneveldstraat",
    "iso:country":"NL",
    "sg:address":"Jacob Barneveldstraat 19",
    "sg:city":"Linschoten",
    "sg:orig_category":"Kinderopvang Behalve Thuis",
    "sg:phone":"+31 348 419 301",
    "sg:postcode":"3461 GA",
    "sg:province":"Utrecht",
    "wof:name":"Peuterspeelzaal Duimelotje",
    "wof:placetype":"venue"
},
  "geometry": {"coordinates":[4.918457,52.064491],"type":"Point"}
}