{
  "type": "Feature",
  "properties": {
    "iso:country":"NL",
    "sg:address":"Deilsedijk 10",
    "sg:city":"Deil",
    "sg:orig_category":"Boekhouders",
    "sg:phone":"+31 345 651 778",
    "sg:postcode":"4158 CG",
    "sg:province":"Gelderland",
    "wof:name":"Administratiekantoor A. Rijker",
    "wof:placetype":"venue"
},
  "geometry": {"coordinates":[5.250278,51.883453],"type":"Point"}
}