{
  "type": "Feature",
  "properties": {
    "iso:country":"NL",
    "sg:address":"Ceresstr 19",
    "sg:city":"Wageningen",
    "sg:orig_category":"Dansscholen",
    "sg:phone":"+31 317 420 121",
    "sg:postcode":"6706 AL",
    "sg:province":"Gelderland",
    "sg:website":"http://www.steigam.net/wieledansers",
    "wof:name":"Wageningse Wieledansers",
    "wof:placetype":"venue"
},
  "geometry": {"coordinates":[5.671543,51.970203],"type":"Point"}
}