{
  "type": "Feature",
  "properties": {
    "iso:country":"NL",
    "sg:address":"Laan Van Scheut 10",
    "sg:city":"Nijmegen",
    "sg:orig_category":"Hoger Onderwijs",
    "sg:phone":"+31 24 352 8528",
    "sg:postcode":"6525 EM",
    "sg:province":"Gelderland",
    "wof:name":"Vdo Opleidingen",
    "wof:placetype":"venue"
},
  "geometry": {"coordinates":[5.862324,51.828377],"type":"Point"}
}