{
  "type": "Feature",
  "properties": {
    "addr:full":"Koudenhoek 24 Vlissingen Zeeland 4381 AC",
    "addr:housenumber":"24",
    "addr:postcode":"4381 ac",
    "addr:street":"Koudenhoek",
    "iso:country":"NL",
    "sg:address":"Koudenhoek 24",
    "sg:city":"Vlissingen",
    "sg:orig_category":"Partycatering And -Organisatie",
    "sg:phone":"+31 118 410 612",
    "sg:postcode":"4381 AC",
    "sg:province":"Zeeland",
    "wof:name":"Eetgelegenheid De Sardijn",
    "wof:placetype":"venue"
},
  "geometry": {"coordinates":[3.57923,51.443508],"type":"Point"}
}