{
  "type": "Feature",
  "properties": {
    "addr:full":"A Frankln 20 Pynacker South Holland 2642 BK",
    "addr:housenumber":"20",
    "addr:postcode":"2642 bk",
    "addr:street":"Pynacker South",
    "iso:country":"NL",
    "sg:address":"A Frankln 20",
    "sg:city":"Pynacker",
    "sg:orig_category":"Kappers",
    "sg:phone":"+31 6 41469572",
    "sg:postcode":"2642 BK",
    "sg:province":"South Holland",
    "wof:name":"Hairiette",
    "wof:placetype":"venue"
},
  "geometry": {"coordinates":[4.4502501488,52.0088882446],"type":"Point"}
}