{
  "type": "Feature",
  "properties": {
    "iso:country":"NL",
    "sg:address":"Duivenkamp 889",
    "sg:city":"Maarssen",
    "sg:orig_category":"Adviesbureaus Personeel",
    "sg:phone":"+31 346 574 846",
    "sg:postcode":"3607 WH",
    "sg:province":"Utrecht",
    "wof:name":"Biljard",
    "wof:placetype":"venue"
},
  "geometry": {"coordinates":[5.025208,52.130264],"type":"Point"}
}