{
  "type": "Feature",
  "properties": {
    "addr:full":"W A Scholtenstr 9A Assen Drenthe 9403 AJ",
    "addr:housenumber":"9a",
    "addr:postcode":"9403 aj",
    "addr:street":"W A Scholtenstr",
    "iso:country":"NL",
    "sg:address":"W A Scholtenstr 9A",
    "sg:city":"Assen",
    "sg:orig_category":"Etiketten",
    "sg:phone":"+31 592 408 334",
    "sg:postcode":"9403 AJ",
    "sg:province":"Drenthe",
    "sg:website":"http://www.printingfactory.nl",
    "wof:name":"Printing Factory Bv, The",
    "wof:placetype":"venue"
},
  "geometry": {"coordinates":[6.573759,53.005173],"type":"Point"}
}