{
  "type": "Feature",
  "properties": {
    "addr:full":"Hogeweg 43 Limmen North Holland 1906 CB",
    "addr:housenumber":"43",
    "addr:postcode":"1906 cb",
    "addr:street":"Hogeweg",
    "iso:country":"NL",
    "sg:address":"Hogeweg 43",
    "sg:city":"Limmen",
    "sg:orig_category":"Verzekeringen",
    "sg:phone":"+31 72 505 3061",
    "sg:postcode":"1906 CB",
    "sg:province":"North Holland",
    "wof:name":"Assurantiekantoor W.M. Rotteveel",
    "wof:placetype":"venue"
},
  "geometry": {"coordinates":[4.688639,52.568233],"type":"Point"}
}