{
  "type": "Feature",
  "properties": {
    "addr:full":"Spoorlaan 36 Oss Noord-Brabant 5348 KB",
    "addr:housenumber":"36",
    "addr:postcode":"5348 kb",
    "addr:street":"Spoorlaan",
    "iso:country":"NL",
    "sg:address":"Spoorlaan 36",
    "sg:city":"Oss",
    "sg:classifiers":[
        {
            "category":"Fast Food",
            "type":"Food & Drink"
        }
    ],
    "sg:phone":"+31 412 641 940",
    "sg:postcode":"5348 KB",
    "sg:province":"Noord-Brabant",
    "sg:tags":[
        "afhaal",
        "restaurant"
    ],
    "wof:name":"Mie Li",
    "wof:placetype":"venue"
},
  "geometry": {"coordinates":[-77.235214,38.312599],"type":"Point"}
}