{
  "type": "Feature",
  "properties": {
    "addr:full":"Abtstr 23 Maastricht Limburg 6211 LS",
    "addr:housenumber":"23",
    "addr:postcode":"6211 ls",
    "addr:street":"Abtstr",
    "iso:country":"NL",
    "sg:address":"Abtstr 23",
    "sg:city":"Maastricht",
    "sg:orig_category":"Plotservice",
    "sg:phone":"+31 43 321 9455",
    "sg:postcode":"6211 LS",
    "sg:province":"Limburg",
    "wof:name":"Delnoy Bv",
    "wof:placetype":"venue"
},
  "geometry": {"coordinates":[5.684998,50.846039],"type":"Point"}
}