{
  "type": "Feature",
  "properties": {
    "iso:country":"NL",
    "sg:address":"Roerdompstr 34",
    "sg:city":"Stryen",
    "sg:orig_category":"Video - Faciliteiten En Producties",
    "sg:phone":"+31 78 674 2649",
    "sg:postcode":"3291 VL",
    "sg:province":"Zuid-Holland",
    "wof:name":"Hmr Multimedia",
    "wof:placetype":"venue"
},
  "geometry": {"coordinates":[4.54727,51.750832],"type":"Point"}
}