{
  "type": "Feature",
  "properties": {
    "addr:full":"Bosweg 17 Voorthuizen Gelderland 3781 NG",
    "addr:housenumber":"17",
    "addr:postcode":"3781 ng",
    "addr:street":"Bosweg;Gelderland",
    "iso:country":"NL",
    "sg:address":"Bosweg 17",
    "sg:city":"Voorthuizen",
    "sg:orig_category":"Kampeerterreinen",
    "sg:phone":"+31 342 472 942",
    "sg:postcode":"3781 NG",
    "sg:province":"Gelderland",
    "wof:name":"Evangelische Camping Het Beloofde Land",
    "wof:placetype":"venue"
},
  "geometry": {"coordinates":[5.6228728294,52.1875686646],"type":"Point"}
}