{
  "type": "Feature",
  "properties": {
    "addr:full":"Vliedberg 28 Veere Zeeland 4373 AX",
    "addr:housenumber":"28",
    "addr:postcode":"4373 ax",
    "addr:street":"Vliedberg",
    "iso:country":"NL",
    "sg:address":"Vliedberg 28",
    "sg:city":"Veere",
    "sg:orig_category":"Loodgieterswerk, Verwarming And Sanitaire Installaties",
    "sg:phone":"+31 118 566 139",
    "sg:postcode":"4373 AX",
    "sg:province":"Zeeland",
    "wof:name":"Kees Van Hest Onderhoud-En Klussenbedrijf",
    "wof:placetype":"venue"
},
  "geometry": {"coordinates":[3.529117,51.498714],"type":"Point"}
}