{
  "type": "Feature",
  "properties": {
    "iso:country":"NL",
    "sg:address":"Breestraat 10",
    "sg:city":"Leiden",
    "sg:orig_category":"Kappers",
    "sg:phone":"+31 71 514 6336",
    "sg:postcode":"2311 CR",
    "sg:province":"South Holland",
    "wof:name":"Zizzorz",
    "wof:placetype":"venue"
},
  "geometry": {"coordinates":[4.485598,52.160244],"type":"Point"}
}