{
  "type": "Feature",
  "properties": {
    "addr:full":"Coolhaven 104C Rotterdam Zuid-Holland 3024 AJ",
    "addr:housenumber":"104c",
    "addr:postcode":"3024 aj",
    "addr:street":"Coolhaven",
    "iso:country":"NL",
    "sg:address":"Coolhaven 104C",
    "sg:city":"Rotterdam",
    "sg:classifiers":[
        {
            "category":"Education",
            "subcategory":"Special Training",
            "type":"Public Place"
        }
    ],
    "sg:phone":"+31 10 476 3355",
    "sg:postcode":"3024 AJ",
    "sg:province":"Zuid-Holland",
    "sg:tags":[
        "expertise"
    ],
    "sg:website":"http://www.rotterdambusinesspark.nl/schooco",
    "wof:name":"Schoo & Co, J G",
    "wof:placetype":"venue"
},
  "geometry": {"coordinates":[4.457863,51.907799],"type":"Point"}
}