{
  "type": "Feature",
  "properties": {
    "addr:full":"Hoofddiep 78 Zevenhuizen Gn Groningen 9354 AS",
    "addr:housenumber":"78;gn",
    "addr:postcode":"9354 as",
    "addr:street":"Hoofddiep",
    "iso:country":"NL",
    "sg:address":"Hoofddiep 78",
    "sg:city":"Zevenhuizen Gn",
    "sg:classifiers":[
        {
            "category":"Food & Beverages",
            "subcategory":"Bakery",
            "type":"Retail Goods"
        }
    ],
    "sg:phone":"+31 594 631 260",
    "sg:postcode":"9354 AS",
    "sg:province":"Groningen",
    "sg:tags":[
        "brood",
        "en",
        "banket"
    ],
    "wof:name":"Esch, Ambachtelijke Bakkerij Van",
    "wof:placetype":"venue"
},
  "geometry": {"coordinates":[6.349035,53.125168],"type":"Point"}
}