{
  "type": "Feature",
  "properties": {
    "addr:full":"Akerdk 291A Badhoevedorp North Holland 1171 RC",
    "addr:housenumber":"291a",
    "addr:postcode":"1171 rc",
    "iso:country":"NL",
    "sg:address":"Akerdk 291A",
    "sg:city":"Badhoevedorp",
    "sg:orig_category":"Kantoor- En Bedrijfsmeubelen",
    "sg:phone":"+31 20 659 3303",
    "sg:postcode":"1171 RC",
    "sg:province":"North Holland",
    "wof:name":"Ergonizer Bv",
    "wof:placetype":"venue"
},
  "geometry": {"coordinates":[4.7857689857,52.3433303833],"type":"Point"}
}