{
  "type": "Feature",
  "properties": {
    "addr:full":"Zuiderstraat 22 Eenrum Groningen 9967 RP",
    "addr:housenumber":"22",
    "addr:postcode":"9967 rp",
    "addr:street":"Zuiderstraat",
    "iso:country":"NL",
    "sg:address":"Zuiderstraat 22",
    "sg:city":"Eenrum",
    "sg:orig_category":"Architecten",
    "sg:phone":"+31 595 491 606",
    "sg:postcode":"9967 RP",
    "sg:province":"Groningen",
    "wof:name":"E B Mulder",
    "wof:placetype":"venue"
},
  "geometry": {"coordinates":[6.462293,53.364864],"type":"Point"}
}