{
  "type": "Feature",
  "properties": {
    "addr:full":"Kampstr 3 Ede Gld Gelderland 6711 BS",
    "addr:housenumber":"3;6711",
    "addr:postcode":"bs",
    "addr:street":"Kampstr;Gld Gelderland",
    "iso:country":"NL",
    "sg:address":"Kampstr 3",
    "sg:city":"Ede Gld",
    "sg:classifiers":[
        {
            "category":"Wholesale",
            "subcategory":"Motor Vehicles",
            "type":"Manufacturing & Wholesale Goods"
        }
    ],
    "sg:phone":"+31 318 610 287",
    "sg:postcode":"6711 BS",
    "sg:province":"Gelderland",
    "sg:tags":[
        "scooter",
        "en"
    ],
    "sg:website":"http://www.henksmotorstore.nl",
    "wof:name":"Henk'S Motor Store",
    "wof:placetype":"venue"
},
  "geometry": {"coordinates":[5.670772,52.050488],"type":"Point"}
}