{
  "type": "Feature",
  "properties": {
    "addr:full":"Veenendaalkade 164 'S Gravenhage Zuid-Holland 2547 AT",
    "addr:housenumber":"164 '",
    "addr:postcode":"2547",
    "addr:street":"Veenendaalkade",
    "iso:country":"NL",
    "sg:address":"Veenendaalkade 164",
    "sg:city":"'S Gravenhage",
    "sg:orig_category":"Artiestenbureaus",
    "sg:phone":"+31 70 309 9752",
    "sg:postcode":"2547 AT",
    "sg:province":"Zuid-Holland",
    "wof:name":"Lichter Laaie",
    "wof:placetype":"venue"
},
  "geometry": {"coordinates":[4.271714,52.060265],"type":"Point"}
}