{
  "type": "Feature",
  "properties": {
    "addr:full":"M Klompeln 24 Ryen Noord-Brabant 5122 BB",
    "addr:housenumber":"24",
    "addr:postcode":"5122 bb",
    "iso:country":"NL",
    "sg:address":"M Klompeln 24",
    "sg:city":"Ryen",
    "sg:orig_category":"Bedrijfsopleidingen",
    "sg:phone":"+31 161 227 217",
    "sg:postcode":"5122 BB",
    "sg:province":"Noord-Brabant",
    "wof:name":"Fens",
    "wof:placetype":"venue"
},
  "geometry": {"coordinates":[4.92752,51.59277],"type":"Point"}
}