{
  "type": "Feature",
  "properties": {
    "addr:full":"Beatrixln 10 Someren North Brabant 5711 AN",
    "addr:housenumber":"10",
    "addr:postcode":"5711 an",
    "addr:street":"Beatrixln",
    "iso:country":"NL",
    "sg:address":"Beatrixln 10",
    "sg:city":"Someren",
    "sg:orig_category":"Podotherapeuten",
    "sg:phone":"+31 493 479 050",
    "sg:postcode":"5711 AN",
    "sg:province":"North Brabant",
    "wof:name":"Praktijk Voor Podotherapie",
    "wof:placetype":"venue"
},
  "geometry": {"coordinates":[5.711272,51.384651],"type":"Point"}
}