{
  "type": "Feature",
  "properties": {
    "addr:full":"Amsteldijk 48 Amsterdam North Holland 1074 HW",
    "addr:housenumber":"48",
    "addr:postcode":"1074 hw",
    "addr:street":"Amsteldijk",
    "iso:country":"NL",
    "sg:address":"Amsteldijk 48",
    "sg:city":"Amsterdam",
    "sg:orig_category":"Boekhouders",
    "sg:phone":"+31 20 676 0721",
    "sg:postcode":"1074 HW",
    "sg:province":"North Holland",
    "wof:name":"Administratiekantoor Mahran",
    "wof:placetype":"venue"
},
  "geometry": {"coordinates":[4.906091,52.354515],"type":"Point"}
}