{
  "type": "Feature",
  "properties": {
    "addr:full":"Westblaak 88 Rotterdam South Holland 3012 KM",
    "addr:housenumber":"88",
    "addr:postcode":"3012 km",
    "addr:street":"Westblaak",
    "iso:country":"NL",
    "sg:address":"Westblaak 88",
    "sg:city":"Rotterdam",
    "sg:orig_category":"Parkeergarages",
    "sg:phone":"+31 10 233 1984",
    "sg:postcode":"3012 KM",
    "sg:province":"South Holland",
    "sg:website":"http://www.apcoa.nl",
    "wof:name":"Apcoa Westblaak",
    "wof:placetype":"venue"
},
  "geometry": {"coordinates":[4.477439,51.916798],"type":"Point"}
}