{
  "type": "Feature",
  "properties": {
    "addr:full":"Nw Hoogstr 8 Amsterdam Noord-Holland 1011 HE",
    "addr:housenumber":"8",
    "addr:postcode":"1011 he",
    "addr:street":"Hoogstr",
    "iso:country":"NL",
    "sg:address":"Nw Hoogstr 8",
    "sg:city":"Amsterdam",
    "sg:orig_category":"Dumpgoederen",
    "sg:phone":"+31 20 625 3526",
    "sg:postcode":"1011 HE",
    "sg:province":"Noord-Holland",
    "sg:website":"http://www.westwood.nl",
    "wof:name":"Angelique Surplus",
    "wof:placetype":"venue"
},
  "geometry": {"coordinates":[4.899258,52.370705],"type":"Point"}
}