{
  "type": "Feature",
  "properties": {
    "addr:full":"Industriepln 3 Hengelo Ov NL.08 7553 LL",
    "addr:housenumber":"3",
    "addr:postcode":"7553 ll",
    "addr:street":"Industriepln;Ov",
    "iso:country":"NL",
    "sg:address":"Industriepln 3",
    "sg:city":"Hengelo Ov",
    "sg:orig_category":"Vertaalbureaus",
    "sg:phone":"+31 74 240 3700",
    "sg:postcode":"7553 LL",
    "sg:province":"NL.08",
    "sg:website":"http://www.sdlintl.com",
    "wof:name":"Sdl International",
    "wof:placetype":"venue"
},
  "geometry": {"coordinates":[6.792977,52.260742],"type":"Point"}
}