{
  "type": "Feature",
  "properties": {
    "addr:full":"Brederoodsewg 86 Santpoort Zuid Noord-Holland 2082 BX",
    "addr:housenumber":"86",
    "addr:postcode":"2082 bx",
    "addr:street":"Brederoodsewg;Santpoort",
    "iso:country":"NL",
    "sg:address":"Brederoodsewg 86",
    "sg:city":"Santpoort Zuid",
    "sg:orig_category":"Administratie- En Boekhoudkantoren",
    "sg:phone":"+31 23 537 5219",
    "sg:postcode":"2082 BX",
    "sg:province":"Noord-Holland",
    "wof:name":"Delta",
    "wof:placetype":"venue"
},
  "geometry": {"coordinates":[4.627995,52.42564],"type":"Point"}
}