{
  "type": "Feature",
  "properties": {
    "iso:country":"NL",
    "sg:address":"Brederoodsewg 86",
    "sg:city":"Santpoort Zuid",
    "sg:orig_category":"Administratie- En Boekhoudkantoren",
    "sg:phone":"+31 23 537 5219",
    "sg:postcode":"2082 BX",
    "sg:province":"Noord-Holland",
    "wof:name":"Delta",
    "wof:placetype":"venue"
},
  "geometry": {"coordinates":[4.627995,52.42564],"type":"Point"}
}