{
  "type": "Feature",
  "properties": {
    "addr:full":"Recordweg 2 Amersfoort Utrecht 3821  A",
    "addr:housenumber":"2;3821 a",
    "addr:street":"Recordweg",
    "iso:country":"NL",
    "sg:address":"Recordweg 2",
    "sg:city":"Amersfoort",
    "sg:orig_category":"Binnenhuisarchitecten",
    "sg:phone":"+31 33 463 4106",
    "sg:postcode":"3821  A",
    "sg:province":"Utrecht",
    "wof:name":"Van Munster Kantoor En Projectinrichters",
    "wof:placetype":"venue"
},
  "geometry": {"coordinates":[5.416279,52.174992],"type":"Point"}
}