{
  "type": "Feature",
  "properties": {
    "addr:full":"M V Hongaryedreef 20 Utrecht Utrecht 3561 TH",
    "addr:housenumber":"20",
    "addr:postcode":"3561 th",
    "addr:street":"Hongaryedreef",
    "iso:country":"NL",
    "sg:address":"M V Hongaryedreef 20",
    "sg:city":"Utrecht",
    "sg:orig_category":"Architecten En Architectenbureaus",
    "sg:phone":"+31 30 261 1655",
    "sg:postcode":"3561 TH",
    "sg:province":"Utrecht",
    "wof:name":"Krasselt & Voorhout",
    "wof:placetype":"venue"
},
  "geometry": {"coordinates":[5.12395,52.11272],"type":"Point"}
}