{
  "type": "Feature",
  "properties": {
    "addr:full":"F Vd Laarpln 30 Maastricht Limburg 6217 NH",
    "addr:housenumber":"30",
    "addr:postcode":"6217 nh",
    "iso:country":"NL",
    "sg:address":"F Vd Laarpln 30",
    "sg:city":"Maastricht",
    "sg:orig_category":"Beeldende Kunstenaars",
    "sg:phone":"+31 43 343 7722",
    "sg:postcode":"6217 NH",
    "sg:province":"Limburg",
    "wof:name":"Mitra",
    "wof:placetype":"venue"
},
  "geometry": {"coordinates":[5.672675,50.856285],"type":"Point"}
}