{
  "type": "Feature",
  "properties": {
    "addr:full":"Stulp 35 Veldhoven Noord-Brabant 5502 VM",
    "addr:housenumber":"35",
    "addr:postcode":"5502 vm",
    "addr:street":"Stulp",
    "iso:country":"NL",
    "sg:address":"Stulp 35",
    "sg:city":"Veldhoven",
    "sg:orig_category":"Koeriersdiensten",
    "sg:phone":"+31 40 206 9632",
    "sg:postcode":"5502 VM",
    "sg:province":"Noord-Brabant",
    "wof:name":"Ippon International",
    "wof:placetype":"venue"
},
  "geometry": {"coordinates":[5.422801,51.421535],"type":"Point"}
}