{
  "type": "Feature",
  "properties": {
    "addr:full":"Willemspln 23 Arnhem Gelderland 6811 KB",
    "addr:housenumber":"23",
    "addr:postcode":"6811 kb",
    "addr:street":"Willemspln",
    "iso:country":"NL",
    "sg:address":"Willemspln 23",
    "sg:city":"Arnhem",
    "sg:orig_category":"Adviesbureaus Bedrijfsorganisatie",
    "sg:phone":"+31 26 442 8242",
    "sg:postcode":"6811 KB",
    "sg:province":"Gelderland",
    "wof:name":"Groot",
    "wof:placetype":"venue"
},
  "geometry": {"coordinates":[5.903176,51.983418],"type":"Point"}
}