{
  "type": "Feature",
  "properties": {
    "addr:full":"Duikerstr 29 Dep Rotterdam Zuid-Holland 3067 CG",
    "addr:housenumber":"29",
    "addr:postcode":"rotterdam;3067 cg",
    "addr:street":"Duikerstr",
    "iso:country":"NL",
    "sg:address":"Duikerstr 29 Dep",
    "sg:city":"Rotterdam",
    "sg:orig_category":"Scholen Voor Basisonderwijs",
    "sg:phone":"+31 10 421 1738",
    "sg:postcode":"3067 CG",
    "sg:province":"Zuid-Holland",
    "sg:website":"http://www.vuurwerk.nl",
    "wof:name":"Veldhuizen Prot Chr, Van",
    "wof:placetype":"venue"
},
  "geometry": {"coordinates":[4.55193,51.944969],"type":"Point"}
}