{
  "type": "Feature",
  "properties": {
    "addr:full":"Normandielaan 48 Eindhoven Noord-Brabant 5627 HT",
    "addr:housenumber":"48",
    "addr:postcode":"5627 ht",
    "addr:street":"Normandielaan",
    "iso:country":"NL",
    "sg:address":"Normandielaan 48",
    "sg:city":"Eindhoven",
    "sg:classifiers":[
        {
            "category":"Education",
            "subcategory":"Preschool",
            "type":"Public Place"
        }
    ],
    "sg:phone":"+31 40 241 7234",
    "sg:postcode":"5627 HT",
    "sg:province":"Noord-Brabant",
    "sg:tags":[
        "kleuteronderwijs",
        "basis-"
    ],
    "wof:name":"Peuterspeelzaal Mallemolen",
    "wof:placetype":"venue"
},
  "geometry": {"coordinates":[5.451386,51.48077],"type":"Point"}
}