{
  "type": "Feature",
  "properties": {
    "addr:full":"Dam 24 Alblasserdam Zuid-Holland 2952 AB",
    "addr:housenumber":"24",
    "addr:postcode":"2952 ab",
    "addr:street":"Dam",
    "iso:country":"NL",
    "sg:address":"Dam 24",
    "sg:city":"Alblasserdam",
    "sg:orig_category":"Biljart- And Snookerzalen",
    "sg:phone":"+31 78 691 4711",
    "sg:postcode":"2952 AB",
    "sg:province":"Zuid-Holland",
    "wof:name":"Het Wapen Van Alblasserdam Bv",
    "wof:placetype":"venue"
},
  "geometry": {"coordinates":[4.659553,51.859112],"type":"Point"}
}