{
  "type": "Feature",
  "properties": {
    "addr:full":"Roosendaalsestraat 43 Wouw North Brabant 4724 AB",
    "addr:housenumber":"43",
    "addr:postcode":"4724 ab",
    "addr:street":"Roosendaalsestraat",
    "iso:country":"NL",
    "sg:address":"Roosendaalsestraat 43",
    "sg:city":"Wouw",
    "sg:orig_category":"Musea And Historische Gebouwen",
    "sg:phone":"+31 165 302 290",
    "sg:postcode":"4724 AB",
    "sg:province":"North Brabant",
    "wof:name":"Grafisch Museum",
    "wof:placetype":"venue"
},
  "geometry": {"coordinates":[4.390784,51.524284],"type":"Point"}
}