{
  "type": "Feature",
  "properties": {
    "addr:full":"Dorpsstraat 76 Giessenburg South Holland 3381 AH",
    "addr:housenumber":"76",
    "addr:postcode":"3381 ah",
    "addr:street":"Dorpsstraat",
    "iso:country":"NL",
    "sg:address":"Dorpsstraat 76",
    "sg:city":"Giessenburg",
    "sg:orig_category":"Kantoorartikelen",
    "sg:phone":"+31 184 651 976",
    "sg:postcode":"3381 AH",
    "sg:province":"South Holland",
    "wof:name":"Boek- En Kantoorboekhandel De Giessen Bv",
    "wof:placetype":"venue"
},
  "geometry": {"coordinates":[4.8869361877,51.8524856567],"type":"Point"}
}