{
  "type": "Feature",
  "properties": {
    "addr:full":"Rykswg 161 Hoogersmilde Drenthe 9423 PC",
    "addr:housenumber":"161",
    "addr:postcode":"9423 pc",
    "iso:country":"NL",
    "sg:address":"Rykswg 161",
    "sg:city":"Hoogersmilde",
    "sg:orig_category":"Galeries",
    "sg:phone":"+31 592 459 392",
    "sg:postcode":"9423 PC",
    "sg:province":"Drenthe",
    "wof:name":"Kalebassenkar, De",
    "wof:placetype":"venue"
},
  "geometry": {"coordinates":[6.403769,52.911556],"type":"Point"}
}