{
  "type": "Feature",
  "properties": {
    "addr:full":"Molenmakershoek 57B Apeldoorn Gelderland 7328 JK",
    "addr:housenumber":"57b",
    "addr:postcode":"7328 jk",
    "addr:street":"Molenmakershoek;Gelderland",
    "iso:country":"NL",
    "sg:address":"Molenmakershoek 57B",
    "sg:city":"Apeldoorn",
    "sg:orig_category":"Projectinrichting",
    "sg:phone":"+31 55 534 3344",
    "sg:postcode":"7328 JK",
    "sg:province":"Gelderland",
    "sg:website":"http://www.vitrapoint.nl",
    "wof:name":"Vitrapoint Apeldoorn",
    "wof:placetype":"venue"
},
  "geometry": {"coordinates":[5.983884,52.207405],"type":"Point"}
}