{
  "type": "Feature",
  "properties": {
    "addr:full":"Tak Van Poortvlietstraat 361 Hoogezand Groningen 9602 PJ",
    "addr:housenumber":"361",
    "addr:postcode":"9602 pj",
    "addr:street":"Tak Van Poortvlietstraat",
    "iso:country":"NL",
    "sg:address":"Tak Van Poortvlietstraat 361",
    "sg:city":"Hoogezand",
    "sg:orig_category":"Woningbouwverenigingen",
    "sg:phone":"+31 598 322 664",
    "sg:postcode":"9602 PJ",
    "sg:province":"Groningen",
    "wof:name":"St De Reensche Compagnie",
    "wof:placetype":"venue"
},
  "geometry": {"coordinates":[6.7539730072,53.1556816101],"type":"Point"}
}