{
  "type": "Feature",
  "properties": {
    "iso:country":"NL",
    "sg:address":"Nicolaas Beetsstraat 36",
    "sg:city":"Alblasserdam",
    "sg:orig_category":"Bloemen And Planten",
    "sg:phone":"+31 78 691 7878",
    "sg:postcode":"2951 XH",
    "sg:province":"Zuid-Holland",
    "wof:name":"Bloemenzaak Van Dijk & Bijl",
    "wof:placetype":"venue"
},
  "geometry": {"coordinates":[4.666505,51.867851],"type":"Point"}
}