{
  "type": "Feature",
  "properties": {
    "iso:country":"NL",
    "sg:address":"Rembrandtweg 47",
    "sg:city":"Amstelveen",
    "sg:orig_category":"Juweliers",
    "sg:phone":"+31 20 640 3465",
    "sg:postcode":"1181 GE",
    "sg:province":"Noord-Holland",
    "wof:name":"Adoree",
    "wof:placetype":"venue"
},
  "geometry": {"coordinates":[4.8611,52.304039],"type":"Point"}
}