{
  "type": "Feature",
  "properties": {
    "addr:full":"Brinklaan 16 Apeldoorn Gelderland 7311 LB",
    "addr:housenumber":"16",
    "addr:postcode":"7311 lb",
    "addr:street":"Brinklaan;Gelderland",
    "iso:country":"NL",
    "sg:address":"Brinklaan 16",
    "sg:city":"Apeldoorn",
    "sg:orig_category":"Discountwinkels",
    "sg:phone":"+31 55 576 0135",
    "sg:postcode":"7311 LB",
    "sg:province":"Gelderland",
    "wof:name":"Zeeman Textielsupers",
    "wof:placetype":"venue"
},
  "geometry": {"coordinates":[5.963309,52.212852],"type":"Point"}
}