{
  "type": "Feature",
  "properties": {
    "addr:full":"2E Schanswg 3 Balkbrug Overijssel 7707 RT",
    "addr:housenumber":"3",
    "addr:postcode":"7707 rt",
    "addr:street":"2E Schanswg",
    "iso:country":"NL",
    "sg:address":"2E Schanswg 3",
    "sg:city":"Balkbrug",
    "sg:orig_category":"Psychologen",
    "sg:phone":"+31 523 657 458",
    "sg:postcode":"7707 RT",
    "sg:province":"Overijssel",
    "wof:name":"Hische, J G",
    "wof:placetype":"venue"
},
  "geometry": {"coordinates":[6.372163,52.596603],"type":"Point"}
}