{
  "type": "Feature",
  "properties": {
    "iso:country":"NL",
    "sg:address":"Udensewg 45",
    "sg:city":"Zeeland",
    "sg:orig_category":"Touringcars",
    "sg:phone":"+31 486 459 997",
    "sg:postcode":"5411 SB",
    "sg:province":"Noord-Brabant",
    "wof:name":"Sato Bv",
    "wof:placetype":"venue"
},
  "geometry": {"coordinates":[5.661063,51.687786],"type":"Point"}
}