{
  "type": "Feature",
  "properties": {
    "addr:full":"Kortemeestraat 12 Bergen Op Zoom Noord-Brabant 4611 TM",
    "addr:housenumber":"12",
    "addr:postcode":"4611 tm",
    "addr:street":"Kortemeestraat",
    "iso:country":"NL",
    "sg:address":"Kortemeestraat 12",
    "sg:city":"Bergen Op Zoom",
    "sg:orig_category":"Verlichting And Huishoudartikelen",
    "sg:phone":"+31 164 233 600",
    "sg:postcode":"4611 TM",
    "sg:province":"Noord-Brabant",
    "wof:name":"Ad Van Wesel Exclusief",
    "wof:placetype":"venue"
},
  "geometry": {"coordinates":[4.285842,51.495304],"type":"Point"}
}