{
  "type": "Feature",
  "properties": {
    "addr:full":"Roetersstr 15 Amsterdam Noord-Holland 1018 WB",
    "addr:housenumber":"15",
    "addr:postcode":"1018 wb",
    "addr:street":"Roetersstr",
    "iso:country":"NL",
    "sg:address":"Roetersstr 15",
    "sg:city":"Amsterdam",
    "sg:orig_category":"Universiteiten",
    "sg:phone":"+31 20 525 6228",
    "sg:postcode":"1018 WB",
    "sg:province":"Noord-Holland",
    "wof:name":"Uva Fac Psychologie",
    "wof:placetype":"venue"
},
  "geometry": {"coordinates":[4.910909,52.362869],"type":"Point"}
}