{
  "type": "Feature",
  "properties": {
    "iso:country":"NL",
    "sg:address":"Nachtegaal 62",
    "sg:city":"Ijsselmuiden",
    "sg:orig_category":"Wasserettes And Stomerijen",
    "sg:phone":"+31 38 332 4870",
    "sg:postcode":"8271 HR",
    "sg:province":"Overijssel",
    "wof:name":"Marianne'S",
    "wof:placetype":"venue"
},
  "geometry": {"coordinates":[5.944524765,52.5631141663],"type":"Point"}
}