{
  "type": "Feature",
  "properties": {
    "addr:full":"Spoorlaan 296 Tilburg North Brabant 5017 JZ",
    "addr:housenumber":"296",
    "addr:postcode":"5017 jz",
    "addr:street":"Spoorlaan",
    "iso:country":"NL",
    "sg:address":"Spoorlaan 296",
    "sg:city":"Tilburg",
    "sg:orig_category":"Banken And Kredietinstellingen",
    "sg:phone":"+31 13 537 9911",
    "sg:postcode":"5017 JZ",
    "sg:province":"North Brabant",
    "wof:name":"Rabobank",
    "wof:placetype":"venue"
},
  "geometry": {"coordinates":[5.096345,51.559509],"type":"Point"}
}