{
  "type": "Feature",
  "properties": {
    "addr:full":"Haagdijk 50 Breda North Brabant 4811 TV",
    "addr:housenumber":"50",
    "addr:postcode":"4811 tv",
    "addr:street":"Haagdijk",
    "iso:country":"NL",
    "sg:address":"Haagdijk 50",
    "sg:city":"Breda",
    "sg:orig_category":"Meubelzaken, Woning- And Keukeninrichting",
    "sg:phone":"+31 76 522 8533",
    "sg:postcode":"4811 TV",
    "sg:province":"North Brabant",
    "wof:name":"Kastenshop - Jong Wonen",
    "wof:placetype":"venue"
},
  "geometry": {"coordinates":[4.769744,51.588268],"type":"Point"}
}