{
  "type": "Feature",
  "properties": {
    "addr:full":"Hegeterp 3 Winsum Fr Friesland 8831 XT",
    "addr:housenumber":"3",
    "addr:postcode":"8831 xt",
    "addr:street":"Hegeterp",
    "iso:country":"NL",
    "sg:address":"Hegeterp 3",
    "sg:city":"Winsum Fr",
    "sg:orig_category":"Metaalwerken",
    "sg:phone":"+31 517 341 417",
    "sg:postcode":"8831 XT",
    "sg:province":"Friesland",
    "wof:name":"Mvm",
    "wof:placetype":"venue"
},
  "geometry": {"coordinates":[5.632018,53.151154],"type":"Point"}
}