{
  "type": "Feature",
  "properties": {
    "addr:full":"Hooftstr 146 Alphen Aan Den Ryn Zuid-Holland 2406 GN",
    "addr:housenumber":"146",
    "addr:postcode":"2406 gn",
    "addr:street":"Aan Den Ryn",
    "iso:country":"NL",
    "sg:address":"Hooftstr 146",
    "sg:city":"Alphen Aan Den Ryn",
    "sg:classifiers":[
        {
            "category":"Shopping",
            "subcategory":"Adult",
            "type":"Retail Goods"
        }
    ],
    "sg:phone":"+31 172 473 014",
    "sg:postcode":"2406 GN",
    "sg:province":"Zuid-Holland",
    "sg:tags":[
        "lingerie",
        "en",
        "tricotage"
    ],
    "wof:name":"Schilden, Van Der",
    "wof:placetype":"venue"
},
  "geometry": {"coordinates":[4.663848,52.135216],"type":"Point"}
}