{
  "type": "Feature",
  "properties": {
    "addr:full":"Ir Leemansstr 37 Nieuwerkerk Yssel Zuid-Holland 2912 CD",
    "addr:housenumber":"37",
    "addr:postcode":"2912 cd",
    "iso:country":"NL",
    "sg:address":"Ir Leemansstr 37",
    "sg:city":"Nieuwerkerk Yssel",
    "sg:orig_category":"Projectinrichting",
    "sg:phone":"+31 180 314 892",
    "sg:postcode":"2912 CD",
    "sg:province":"Zuid-Holland",
    "wof:name":"Steenbergen",
    "wof:placetype":"venue"
},
  "geometry": {"coordinates":[4.6028,51.963692],"type":"Point"}
}