{
  "type": "Feature",
  "properties": {
    "addr:full":"Schapenwg 27 Zeddam Gelderland 7038 BR",
    "addr:housenumber":"27",
    "addr:postcode":"7038 br",
    "addr:street":"Schapenwg;Gelderland",
    "iso:country":"NL",
    "sg:address":"Schapenwg 27",
    "sg:city":"Zeddam",
    "sg:orig_category":"Bestratingen",
    "sg:phone":"+31 314 652 556",
    "sg:postcode":"7038 BR",
    "sg:province":"Gelderland",
    "wof:name":"Braak, Te",
    "wof:placetype":"venue"
},
  "geometry": {"coordinates":[6.258161,51.905708],"type":"Point"}
}