{
  "type": "Feature",
  "properties": {
    "addr:full":"Beethovenlaan 7 Schagen North Holland 1741 HT",
    "addr:housenumber":"7",
    "addr:postcode":"1741 ht",
    "addr:street":"Beethovenlaan",
    "iso:country":"NL",
    "sg:address":"Beethovenlaan 7",
    "sg:city":"Schagen",
    "sg:orig_category":"Medische Apparatuur And Prothesen Fab",
    "sg:phone":"+31 224 217 171",
    "sg:postcode":"1741 HT",
    "sg:province":"North Holland",
    "wof:name":"Tandtechnisch Lab Hensen",
    "wof:placetype":"venue"
},
  "geometry": {"coordinates":[4.79434,52.789375],"type":"Point"}
}