{
  "type": "Feature",
  "properties": {
    "iso:country":"NL",
    "sg:address":"Houtstr 1",
    "sg:city":"Wamel",
    "sg:orig_category":"Meubelstoffering",
    "sg:phone":"+31 487 502 147",
    "sg:postcode":"6659 BT",
    "sg:province":"Gelderland",
    "wof:name":"Gul",
    "wof:placetype":"venue"
},
  "geometry": {"coordinates":[5.466794,51.880726],"type":"Point"}
}