{
  "type": "Feature",
  "properties": {
    "iso:country":"NL",
    "sg:address":"Watergoorweg 63",
    "sg:city":"Nijkerk Gld",
    "sg:orig_category":"Metaalwerken",
    "sg:phone":"+31 33 245 1667",
    "sg:postcode":"3861 MA",
    "sg:province":"Gelderland",
    "wof:name":"Zeilmakerij En Zonwering Gijtenbeek Bv",
    "wof:placetype":"venue"
},
  "geometry": {"coordinates":[5.472649,52.229286],"type":"Point"}
}