{
  "type": "Feature",
  "properties": {
    "addr:full":"Overlekergouw 5 Broek In Waterland Noord-Holland 1151 CX",
    "addr:housenumber":"5",
    "addr:postcode":"1151 cx",
    "addr:street":"Overlekergouw",
    "iso:country":"NL",
    "sg:address":"Overlekergouw 5",
    "sg:city":"Broek In Waterland",
    "sg:orig_category":"Kampeerterreinen",
    "sg:phone":"+31 20 403 1500",
    "sg:postcode":"1151 CX",
    "sg:province":"Noord-Holland",
    "wof:name":"Kampeervereniging De Leek",
    "wof:placetype":"venue"
},
  "geometry": {"coordinates":[5.0038661957,52.4458084106],"type":"Point"}
}