{
  "type": "Feature",
  "properties": {
    "addr:full":"Huizerwg 26A Bussum Noord-Holland 1402 AB",
    "addr:housenumber":"26a",
    "addr:postcode":"1402 ab",
    "addr:street":"Huizerwg",
    "iso:country":"NL",
    "sg:address":"Huizerwg 26A",
    "sg:city":"Bussum",
    "sg:orig_category":"Kantoor- En Bedrijfsmeubelen",
    "sg:phone":"+31 35 692 5025",
    "sg:postcode":"1402 AB",
    "sg:province":"Noord-Holland",
    "wof:name":"Total Office Providers",
    "wof:placetype":"venue"
},
  "geometry": {"coordinates":[5.1687932014,52.27394104],"type":"Point"}
}