{
  "type": "Feature",
  "properties": {
    "addr:full":"Lindeboom 32 Mook Limburg 6585 BR",
    "addr:housenumber":"32",
    "addr:postcode":"6585 br",
    "addr:street":"Lindeboom",
    "iso:country":"NL",
    "sg:address":"Lindeboom 32",
    "sg:city":"Mook",
    "sg:orig_category":"Administratie- En Boekhoudkantoren",
    "sg:phone":"+31 24 696 3677",
    "sg:postcode":"6585 BR",
    "sg:province":"Limburg",
    "wof:name":"Beers Vof, J & L",
    "wof:placetype":"venue"
},
  "geometry": {"coordinates":[5.888373,51.748093],"type":"Point"}
}