{
  "type": "Feature",
  "properties": {
    "addr:full":"Bovenover 359 Amsterdam Noord-Holland 1025 JS",
    "addr:housenumber":"359",
    "addr:postcode":"1025 js",
    "addr:street":"Bovenover",
    "iso:country":"NL",
    "sg:address":"Bovenover 359",
    "sg:city":"Amsterdam",
    "sg:orig_category":"Fotopersbureaus",
    "sg:phone":"+31 20 662 8941",
    "sg:postcode":"1025 JS",
    "sg:province":"Noord-Holland",
    "wof:name":"Picturecom",
    "wof:placetype":"venue"
},
  "geometry": {"coordinates":[4.933417,52.39798],"type":"Point"}
}