{
  "type": "Feature",
  "properties": {
    "addr:full":"Rontgenstraat 20 Heerlen Limburg 6412 VH",
    "addr:housenumber":"20",
    "addr:postcode":"6412 vh",
    "addr:street":"Rontgenstraat",
    "iso:country":"NL",
    "sg:address":"Rontgenstraat 20",
    "sg:city":"Heerlen",
    "sg:orig_category":"Kappers",
    "sg:phone":"+31 45 572 1504",
    "sg:postcode":"6412 VH",
    "sg:province":"Limburg",
    "wof:name":"A Duckers",
    "wof:placetype":"venue"
},
  "geometry": {"coordinates":[5.9741001129,50.8985939026],"type":"Point"}
}