{
  "type": "Feature",
  "properties": {
    "iso:country":"NL",
    "sg:address":"Kloosterstraat 2",
    "sg:city":"Bergen Op Zoom",
    "sg:orig_category":"Kansspelen",
    "sg:phone":"+31 164 257 089",
    "sg:postcode":"4611 MC",
    "sg:province":"Noord-Brabant",
    "wof:name":"Fair Play Center Bergen Op Zoom",
    "wof:placetype":"venue"
},
  "geometry": {"coordinates":[4.2901878357,51.4932441711],"type":"Point"}
}