{
  "type": "Feature",
  "properties": {
    "iso:country":"NL",
    "sg:address":"Vaartdreef 57",
    "sg:city":"Zoetermeer",
    "sg:orig_category":"Fietsen En Bromfietsen",
    "sg:phone":"+31 79 341 6303",
    "sg:postcode":"2724 GB",
    "sg:province":"South Holland",
    "wof:name":"Dijk, Van",
    "wof:placetype":"venue"
},
  "geometry": {"coordinates":[4.50375,52.066658],"type":"Point"}
}