{
  "type": "Feature",
  "properties": {
    "addr:full":"Ryndk 112A Leiden Zuid-Holland 2331 AJ",
    "addr:housenumber":"112a",
    "addr:postcode":"2331 aj",
    "iso:country":"NL",
    "sg:address":"Ryndk 112A",
    "sg:city":"Leiden",
    "sg:orig_category":"Jachthavens - Jachtwerven",
    "sg:phone":"+31 71 576 3865",
    "sg:postcode":"2331 AJ",
    "sg:province":"Zuid-Holland",
    "sg:website":"http://www.albatros21.nl",
    "wof:name":"Albatros",
    "wof:placetype":"venue"
},
  "geometry": {"coordinates":[4.45082,52.151321],"type":"Point"}
}