{
  "type": "Feature",
  "properties": {
    "addr:full":"Zijlstraat 67 Haarlem Noord-Holland 2011 TL",
    "addr:housenumber":"67",
    "addr:postcode":"2011 tl",
    "addr:street":"Zijlstraat",
    "iso:country":"NL",
    "sg:address":"Zijlstraat 67",
    "sg:city":"Haarlem",
    "sg:orig_category":"Antiekzaken",
    "sg:phone":"+31 23 531 0366",
    "sg:postcode":"2011 TL",
    "sg:province":"Noord-Holland",
    "wof:name":"Foto Jan Valks",
    "wof:placetype":"venue"
},
  "geometry": {"coordinates":[4.633723,52.382198],"type":"Point"}
}