{
  "type": "Feature",
  "properties": {
    "addr:full":"Ryksstrwg 151 Elst Ut Utrecht 3921 AD",
    "addr:housenumber":"151",
    "addr:postcode":"ut;3921 ad",
    "addr:street":"Elst",
    "iso:country":"NL",
    "sg:address":"Ryksstrwg 151",
    "sg:city":"Elst Ut",
    "sg:orig_category":"Automaterialen En Gereedschappen",
    "sg:phone":"+31 318 472 525",
    "sg:postcode":"3921 AD",
    "sg:province":"Utrecht",
    "wof:name":"Hev\u00e9",
    "wof:placetype":"venue"
},
  "geometry": {"coordinates":[5.500553,51.983845],"type":"Point"}
}