{
  "type": "Feature",
  "properties": {
    "addr:full":"Middelgraaf 8 Ulft Gelderland 7071 WT",
    "addr:housenumber":"8",
    "addr:postcode":"7071 wt",
    "addr:street":"Middelgraaf;Gelderland",
    "iso:country":"NL",
    "sg:address":"Middelgraaf 8",
    "sg:city":"Ulft",
    "sg:classifiers":[
        {
            "category":"Shopping",
            "subcategory":"Gifts & Souvenirs",
            "type":"Retail Goods"
        }
    ],
    "sg:phone":"+31 315 640 382",
    "sg:postcode":"7071 WT",
    "sg:province":"Gelderland",
    "sg:tags":[
        "geschenken"
    ],
    "wof:name":"Habbekrats",
    "wof:placetype":"venue"
},
  "geometry": {"coordinates":[6.380667,51.890743],"type":"Point"}
}