{
  "type": "Feature",
  "properties": {
    "addr:full":"Lunterenstraat 281 'S Gravenhage Zuid-Holland 2573 PL",
    "addr:housenumber":"281 '",
    "addr:postcode":"2573 pl",
    "addr:street":"Lunterenstraat",
    "iso:country":"NL",
    "sg:address":"Lunterenstraat 281",
    "sg:city":"'S Gravenhage",
    "sg:orig_category":"Boekhouders",
    "sg:phone":"+31 70 365 5502",
    "sg:postcode":"2573 PL",
    "sg:province":"Zuid-Holland",
    "wof:name":"J P A Belast En Admin",
    "wof:placetype":"venue"
},
  "geometry": {"coordinates":[4.277321,52.068012],"type":"Point"}
}