{
  "type": "Feature",
  "properties": {
    "addr:full":"Keizersgr 75 Amsterdam Noord-Holland 1015 CE",
    "addr:housenumber":"75",
    "addr:postcode":"1015 ce",
    "addr:street":"Keizersgr",
    "iso:country":"NL",
    "sg:address":"Keizersgr 75",
    "sg:city":"Amsterdam",
    "sg:orig_category":"Verenigingen En Stichtingen",
    "sg:phone":"+31 20 344 9595",
    "sg:postcode":"1015 CE",
    "sg:province":"Noord-Holland",
    "sg:website":"http://www.wcrf-nl.org",
    "wof:name":"Wereld Kanker Onderzoekfonds",
    "wof:placetype":"venue"
},
  "geometry": {"coordinates":[4.888841,52.377903],"type":"Point"}
}