{
  "type": "Feature",
  "properties": {
    "addr:full":"Splitting 43A Emmen Provincie Drenthe 7826 CN",
    "addr:housenumber":"43a",
    "addr:postcode":"7826 cn",
    "addr:street":"Splitting;Provincie Drenthe",
    "iso:country":"NL",
    "sg:address":"Splitting 43A",
    "sg:city":"Emmen",
    "sg:classifiers":[
        {
            "category":"Food & Beverages",
            "subcategory":"Bakery",
            "type":"Retail Goods"
        }
    ],
    "sg:phone":"+31 591 629 008",
    "sg:postcode":"7826 CN",
    "sg:province":"Provincie Drenthe",
    "sg:tags":[
        "pizza"
    ],
    "wof:name":"Luna, La",
    "wof:placetype":"venue"
},
  "geometry": {"coordinates":[6.958459,52.773067],"type":"Point"}
}