{
  "type": "Feature",
  "properties": {
    "addr:full":"Thorbeckelaan 80 Spijkenisse Zuid-Holland 3201 WK",
    "addr:housenumber":"80",
    "addr:postcode":"3201 wk",
    "addr:street":"Thorbeckelaan",
    "iso:country":"NL",
    "sg:address":"Thorbeckelaan 80",
    "sg:city":"Spijkenisse",
    "sg:orig_category":"Juridische Dienstverlening",
    "sg:phone":"+31 181 690 210",
    "sg:postcode":"3201 WK",
    "sg:province":"Zuid-Holland",
    "wof:name":"Optio Optima Bv",
    "wof:placetype":"venue"
},
  "geometry": {"coordinates":[4.335268,51.847527],"type":"Point"}
}