{
  "type": "Feature",
  "properties": {
    "addr:full":"Vogelenzangseweg 81 Vogelenzang Noord-Holland 2114 CC",
    "addr:housenumber":"81",
    "addr:postcode":"2114 cc",
    "addr:street":"Vogelenzangseweg",
    "iso:country":"NL",
    "sg:address":"Vogelenzangseweg 81",
    "sg:city":"Vogelenzang",
    "sg:orig_category":"Bloemen And Planten Gh",
    "sg:phone":"+31 23 584 8958",
    "sg:postcode":"2114 CC",
    "sg:province":"Noord-Holland",
    "wof:name":"John Van Grieken Bv",
    "wof:placetype":"venue"
},
  "geometry": {"coordinates":[4.57808,52.323097],"type":"Point"}
}