{
  "type": "Feature",
  "properties": {
    "addr:full":"Javastr 31 Amsterdam Noord-Holland 1094 GZ",
    "addr:housenumber":"31",
    "addr:postcode":"1094 gz",
    "addr:street":"Javastr",
    "iso:country":"NL",
    "sg:address":"Javastr 31",
    "sg:city":"Amsterdam",
    "sg:orig_category":"Verzekeringen - Verzekeringskantoren",
    "sg:phone":"+31 20 665 0752",
    "sg:postcode":"1094 GZ",
    "sg:province":"Noord-Holland",
    "wof:name":"Meerendonk, Van",
    "wof:placetype":"venue"
},
  "geometry": {"coordinates":[4.932914,52.363716],"type":"Point"}
}