{
  "type": "Feature",
  "properties": {
    "addr:full":"Salignahout 3 Zoetermeer Zuid-Holland 2719 KG",
    "addr:housenumber":"3",
    "addr:postcode":"2719 kg",
    "addr:street":"Salignahout",
    "iso:country":"NL",
    "sg:address":"Salignahout 3",
    "sg:city":"Zoetermeer",
    "sg:orig_category":"Adviesbureaus Bedrijfsorganisatie",
    "sg:phone":"+31 79 362 0572",
    "sg:postcode":"2719 KG",
    "sg:province":"Zuid-Holland",
    "wof:name":"Master Consult",
    "wof:placetype":"venue"
},
  "geometry": {"coordinates":[4.469899,52.045235],"type":"Point"}
}