{
  "type": "Feature",
  "properties": {
    "addr:full":"Burg Magneestr 38 Bergeyk Noord-Brabant 5571 HE",
    "addr:housenumber":"38",
    "addr:postcode":"5571 he",
    "addr:street":"Burg",
    "iso:country":"NL",
    "sg:address":"Burg Magneestr 38",
    "sg:city":"Bergeyk",
    "sg:orig_category":"Schoenen",
    "sg:phone":"+31 497 571 234",
    "sg:postcode":"5571 HE",
    "sg:province":"Noord-Brabant",
    "wof:name":"Geenen, Schoenmode",
    "wof:placetype":"venue"
},
  "geometry": {"coordinates":[5.360135,51.323326],"type":"Point"}
}