{
  "type": "Feature",
  "properties": {
    "addr:full":"Columbusstraat 12 Emmen Provincie Drenthe 7825 VR",
    "addr:housenumber":"12",
    "addr:postcode":"7825 vr",
    "addr:street":"Columbusstraat;Provincie Drenthe",
    "iso:country":"NL",
    "sg:address":"Columbusstraat 12",
    "sg:city":"Emmen",
    "sg:orig_category":"Loodgieterswerk, Verwarming And Sanitaire Installaties",
    "sg:phone":"+31 591 630 056",
    "sg:postcode":"7825 VR",
    "sg:province":"Provincie Drenthe",
    "wof:name":"Niemeijer Installatietechniek Bv",
    "wof:placetype":"venue"
},
  "geometry": {"coordinates":[6.921609,52.754539],"type":"Point"}
}