{
  "type": "Feature",
  "properties": {
    "iso:country":"NL",
    "sg:address":"Oude Leedeweg 187",
    "sg:city":"Pijnacker",
    "sg:orig_category":"Pluimveehouderijen",
    "sg:phone":"+31 15 369 5052",
    "sg:postcode":"2641 SE",
    "sg:province":"South Holland",
    "wof:name":"J. Slingerland",
    "wof:placetype":"venue"
},
  "geometry": {"coordinates":[4.416423,51.984539],"type":"Point"}
}