{
  "type": "Feature",
  "properties": {
    "iso:country":"NL",
    "sg:address":"Damrak 52",
    "sg:city":"Amsterdam",
    "sg:orig_category":"Kansspelen",
    "sg:phone":"+31 20 626 3226",
    "sg:postcode":"1012 LL",
    "sg:province":"Noord-Holland",
    "wof:name":"Novoplay",
    "wof:placetype":"venue"
},
  "geometry": {"coordinates":[4.8955760002,52.3753623962],"type":"Point"}
}