{
  "type": "Feature",
  "properties": {
    "addr:full":"Damrak 52 Amsterdam Noord-Holland 1012 LL",
    "addr:housenumber":"52",
    "addr:postcode":"1012 ll",
    "addr:street":"Damrak",
    "iso:country":"NL",
    "sg:address":"Damrak 52",
    "sg:city":"Amsterdam",
    "sg:orig_category":"Kansspelen",
    "sg:phone":"+31 20 626 3226",
    "sg:postcode":"1012 LL",
    "sg:province":"Noord-Holland",
    "wof:name":"Novoplay",
    "wof:placetype":"venue"
},
  "geometry": {"coordinates":[4.8955760002,52.3753623962],"type":"Point"}
}