{
  "type": "Feature",
  "properties": {
    "addr:full":"Lindenhof 30 Sittard Limburg 6131 GH",
    "addr:housenumber":"30",
    "addr:postcode":"6131 gh",
    "addr:street":"Lindenhof",
    "iso:country":"NL",
    "sg:address":"Lindenhof 30",
    "sg:city":"Sittard",
    "sg:orig_category":"Grafisch Ontwerpers",
    "sg:phone":"+31 46 458 0657",
    "sg:postcode":"6131 GH",
    "sg:province":"Limburg",
    "wof:name":"Amaze",
    "wof:placetype":"venue"
},
  "geometry": {"coordinates":[5.866227,51.002045],"type":"Point"}
}