{
  "type": "Feature",
  "properties": {
    "addr:full":"Haarl Houttuinen 45K Amsterdam Noord-Holland 1013 GM",
    "addr:housenumber":"45k",
    "addr:postcode":"1013 gm",
    "addr:street":"Houttuinen",
    "iso:country":"NL",
    "sg:address":"Haarl Houttuinen 45K",
    "sg:city":"Amsterdam",
    "sg:orig_category":"Video - Faciliteiten En Producties",
    "sg:phone":"+31 20 623 1901",
    "sg:postcode":"1013 GM",
    "sg:province":"Noord-Holland",
    "wof:name":"Dr John Production",
    "wof:placetype":"venue"
},
  "geometry": {"coordinates":[4.891187,52.381126],"type":"Point"}
}