{
  "type": "Feature",
  "properties": {
    "iso:country":"NL",
    "sg:address":"J V Soesdykstr 47",
    "sg:city":"Diemen",
    "sg:orig_category":"Video - Faciliteiten En Producties",
    "sg:phone":"+31 20 690 1523",
    "sg:postcode":"1111 BB",
    "sg:province":"Noord-Holland",
    "wof:name":"Beeldkader",
    "wof:placetype":"venue"
},
  "geometry": {"coordinates":[4.964805,52.34132],"type":"Point"}
}