{
  "type": "Feature",
  "properties": {
    "addr:full":"De Zevenhoeven 1 Heemskerk Noord-Holland 1963 SB",
    "addr:housenumber":"1",
    "addr:postcode":"1963 sb",
    "addr:street":"De Zevenhoeven",
    "iso:country":"NL",
    "sg:address":"De Zevenhoeven 1",
    "sg:city":"Heemskerk",
    "sg:orig_category":"Onderhoud And Reparatie Kantoorapparatuur",
    "sg:phone":"+31 251 235 724",
    "sg:postcode":"1963 SB",
    "sg:province":"Noord-Holland",
    "wof:name":"R.F. Lettenmeijer",
    "wof:placetype":"venue"
},
  "geometry": {"coordinates":[4.687292,52.51088],"type":"Point"}
}