{
  "type": "Feature",
  "properties": {
    "addr:full":"Bannerschultestr 12 Sleen Provincie Drenthe 7841 AC",
    "addr:housenumber":"12",
    "addr:postcode":"7841 ac",
    "addr:street":"Bannerschultestr;Provincie Drenthe",
    "iso:country":"NL",
    "sg:address":"Bannerschultestr 12",
    "sg:city":"Sleen",
    "sg:orig_category":"Makelaars En Adviseurs Onroerende Goederen",
    "sg:phone":"+31 591 361 388",
    "sg:postcode":"7841 AC",
    "sg:province":"Provincie Drenthe",
    "sg:website":"http://www.ludwig.nl",
    "wof:name":"Ludwig Makelaardij O.Z.",
    "wof:placetype":"venue"
},
  "geometry": {"coordinates":[6.801636,52.773235],"type":"Point"}
}