{
  "type": "Feature",
  "properties": {
    "addr:full":"Wilhelminaplein 6 Someren Noord-Brabant 5711 EK",
    "addr:housenumber":"6",
    "addr:postcode":"5711 ek",
    "addr:street":"Wilhelminaplein",
    "iso:country":"NL",
    "sg:address":"Wilhelminaplein 6",
    "sg:city":"Someren",
    "sg:orig_category":"Apotheken",
    "sg:phone":"+31 493 491 123",
    "sg:postcode":"5711 EK",
    "sg:province":"Noord-Brabant",
    "wof:name":"Evers",
    "wof:placetype":"venue"
},
  "geometry": {"coordinates":[5.711272,51.384651],"type":"Point"}
}