{
  "type": "Feature",
  "properties": {
    "addr:full":"Schiewg 77A Delft Zuid-Holland 2627 AT",
    "addr:housenumber":"77a",
    "addr:postcode":"2627",
    "addr:street":"Schiewg",
    "iso:country":"NL",
    "sg:address":"Schiewg 77A",
    "sg:city":"Delft",
    "sg:orig_category":"Watersportartikelen",
    "sg:phone":"+31 15 262 5514",
    "sg:postcode":"2627 AT",
    "sg:province":"Zuid-Holland",
    "wof:name":"Howi Bv",
    "wof:placetype":"venue"
},
  "geometry": {"coordinates":[4.3711681366,51.9849586487],"type":"Point"}
}