{
  "type": "Feature",
  "properties": {
    "addr:full":"Abraham Van Stolkweg 86 Rotterdam Zuid-Holland 3041 JA",
    "addr:housenumber":"86",
    "addr:postcode":"3041 ja",
    "addr:street":"Abraham Van Stolkweg",
    "iso:country":"NL",
    "sg:address":"Abraham Van Stolkweg 86",
    "sg:city":"Rotterdam",
    "sg:orig_category":"Schoenen",
    "sg:phone":"+31 10 437 6262",
    "sg:postcode":"3041 JA",
    "sg:province":"Zuid-Holland",
    "wof:name":"Barbarella Shoes",
    "wof:placetype":"venue"
},
  "geometry": {"coordinates":[4.436319,51.926956],"type":"Point"}
}