{
  "type": "Feature",
  "properties": {
    "addr:full":"Lutherhof 19 Hilversum North Holland 1216 KP",
    "addr:housenumber":"19",
    "addr:postcode":"1216 kp",
    "addr:street":"Lutherhof",
    "iso:country":"NL",
    "sg:address":"Lutherhof 19",
    "sg:city":"Hilversum",
    "sg:orig_category":"Verenigingen En Stichtingen",
    "sg:phone":"+31 35 623 2926",
    "sg:postcode":"1216 KP",
    "sg:province":"North Holland",
    "wof:name":"Ehbo",
    "wof:placetype":"venue"
},
  "geometry": {"coordinates":[5.139469,52.214417],"type":"Point"}
}