{
  "type": "Feature",
  "properties": {
    "addr:full":"W M Dudokwg 40 Heerhugowaard Noord-Holland 1703 DB",
    "addr:housenumber":"40",
    "addr:postcode":"1703 db",
    "addr:street":"W",
    "iso:country":"NL",
    "sg:address":"W M Dudokwg 40",
    "sg:city":"Heerhugowaard",
    "sg:classifiers":[
        {
            "category":"Wholesale",
            "subcategory":"Meat",
            "type":"Manufacturing & Wholesale Goods"
        }
    ],
    "sg:phone":"+31 72 574 5254",
    "sg:postcode":"1703 DB",
    "sg:province":"Noord-Holland",
    "sg:tags":[
        "regeltechniek",
        "en",
        "meet-"
    ],
    "wof:name":"Lorijn & Loos Bv",
    "wof:placetype":"venue"
},
  "geometry": {"coordinates":[4.817829,52.6665],"type":"Point"}
}