{
  "type": "Feature",
  "properties": {
    "iso:country":"NL",
    "sg:address":"Begoniastraat 1",
    "sg:city":"Lent",
    "sg:orig_category":"Muziekinstrumenten",
    "sg:phone":"+31 24 323 4835",
    "sg:postcode":"6663 DA",
    "sg:province":"Gelderland",
    "wof:name":"V. Heitmeijer",
    "wof:placetype":"venue"
},
  "geometry": {"coordinates":[-77.241432,38.151344],"type":"Point"}
}