{
  "type": "Feature",
  "properties": {
    "iso:country":"NL",
    "sg:address":"Klaverstraat 4",
    "sg:city":"Rotterdam",
    "sg:classifiers":[
        {
            "category":"Retail",
            "subcategory":"Photofinishing",
            "type":"Services"
        }
    ],
    "sg:phone":"+31 10 481 5428",
    "sg:postcode":"3083 VH",
    "sg:province":"Zuid-Holland",
    "sg:tags":[
        "foto",
        "film"
    ],
    "wof:name":"Foto Rinus Van Heel",
    "wof:placetype":"venue"
},
  "geometry": {"coordinates":[4.477576,51.890221],"type":"Point"}
}