{
  "type": "Feature",
  "properties": {
    "addr:full":"Postbus 13 Bergen Nh 1860 AA",
    "addr:housenumber":"13",
    "addr:postcode":"1860 aa",
    "addr:street":"Postbus;Nh",
    "iso:country":"NL",
    "sg:address":"Postbus 13",
    "sg:city":"Bergen Nh",
    "sg:orig_category":"Artiesten/Gezelschappen",
    "sg:phone":"+31 72 589 4429",
    "sg:postcode":"1860 AA",
    "wof:name":"Samba Salad, Sticht",
    "wof:placetype":"venue"
},
  "geometry": {"coordinates":[4.70139,52.669979],"type":"Point"}
}