{
  "type": "Feature",
  "properties": {
    "addr:full":"Kleine Sophiastraat 17 Groningen Groningen 9724 AW",
    "addr:housenumber":"17",
    "addr:postcode":"9724 aw",
    "addr:street":"Kleine Sophiastraat",
    "iso:country":"NL",
    "sg:address":"Kleine Sophiastraat 17",
    "sg:city":"Groningen",
    "sg:orig_category":"Boekenuitgeverijen",
    "sg:phone":"+31 50 314 2645",
    "sg:postcode":"9724 AW",
    "sg:province":"Groningen",
    "wof:name":"De Torenvogel",
    "wof:placetype":"venue"
},
  "geometry": {"coordinates":[6.572674,53.210957],"type":"Point"}
}