{
  "type": "Feature",
  "properties": {
    "iso:country":"NL",
    "sg:address":"Koningskruis 14",
    "sg:city":"Hilvarenbeek",
    "sg:orig_category":"Verenigingen En Stichtingen",
    "sg:phone":"+31 13 505 5190",
    "sg:postcode":"5081 XM",
    "sg:province":"Noord-Brabant",
    "wof:name":"Hartstichting, Ned",
    "wof:placetype":"venue"
},
  "geometry": {"coordinates":[5.141569,51.488319],"type":"Point"}
}