{
  "type": "Feature",
  "properties": {
    "iso:country":"NL",
    "sg:address":"Kerkstr 1-3",
    "sg:city":"Leende",
    "sg:orig_category":"Woninginrichting",
    "sg:phone":"+31 40 206 1245",
    "sg:postcode":"5595 CX",
    "sg:province":"Noord-Brabant",
    "wof:name":"Plas Bv, Van De",
    "wof:placetype":"venue"
},
  "geometry": {"coordinates":[5.5541081429,51.3496513367],"type":"Point"}
}