{
  "type": "Feature",
  "properties": {
    "iso:country":"NL",
    "sg:address":"Molendk 7A",
    "sg:city":"Boxmeer",
    "sg:orig_category":"Psychologen",
    "sg:phone":"+31 485 576 128",
    "sg:postcode":"5831 GW",
    "sg:province":"Noord-Brabant",
    "wof:name":"Jansen, Drs F A J J",
    "wof:placetype":"venue"
},
  "geometry": {"coordinates":[5.962121,51.643768],"type":"Point"}
}