{
  "type": "Feature",
  "properties": {
    "iso:country":"NL",
    "sg:address":"Julianastr 24A",
    "sg:city":"Hoensbroek",
    "sg:orig_category":"Kappers",
    "sg:phone":"+31 45 521 1810",
    "sg:postcode":"6433 GC",
    "sg:province":"Limburg",
    "wof:name":"Hair Care Shop",
    "wof:placetype":"venue"
},
  "geometry": {"coordinates":[5.9259810448,50.9119338989],"type":"Point"}
}