{
  "type": "Feature",
  "properties": {
    "addr:full":"Deventerweg 22 Zutphen Gelderland 7203 AK",
    "addr:housenumber":"22",
    "addr:postcode":"7203 ak",
    "addr:street":"Deventerweg;Gelderland",
    "iso:country":"NL",
    "sg:address":"Deventerweg 22",
    "sg:city":"Zutphen",
    "sg:orig_category":"Architecten",
    "sg:phone":"+31 575 513 278",
    "sg:postcode":"7203 AK",
    "sg:province":"Gelderland",
    "wof:name":"Niek Kruisheer",
    "wof:placetype":"venue"
},
  "geometry": {"coordinates":[6.205019,52.148457],"type":"Point"}
}