{
  "type": "Feature",
  "properties": {
    "addr:full":"Hoenderweg 13 Ermelo Gelderland 3851 RZ",
    "addr:housenumber":"13",
    "addr:postcode":"3851 rz",
    "addr:street":"Hoenderweg;Gelderland",
    "iso:country":"NL",
    "sg:address":"Hoenderweg 13",
    "sg:city":"Ermelo",
    "sg:classifiers":[
        {
            "category":"Professional",
            "subcategory":"Accounting & Tax Preparation",
            "type":"Services"
        }
    ],
    "sg:phone":"+31 341 560 573",
    "sg:postcode":"3851 RZ",
    "sg:province":"Gelderland",
    "sg:tags":[
        "accountant"
    ],
    "wof:name":"Accountantskantoor Kok",
    "wof:placetype":"venue"
},
  "geometry": {"coordinates":[5.617015,52.314262],"type":"Point"}
}