{
  "type": "Feature",
  "properties": {
    "iso:country":"NL",
    "sg:address":"Jan De Windstraat 2",
    "sg:city":"Beverwijk",
    "sg:orig_category":"Auto'S And Voertuigen",
    "sg:phone":"+31 251 242 324",
    "sg:postcode":"1945 SX",
    "sg:province":"North Holland",
    "wof:name":"Autobedrijf Stormvogels Bv",
    "wof:placetype":"venue"
},
  "geometry": {"coordinates":[4.661213,52.491676],"type":"Point"}
}