{
  "type": "Feature",
  "properties": {
    "addr:full":"De Genestetstr 31 Sliedrecht South Holland 3362 TE",
    "addr:housenumber":"31",
    "addr:postcode":"3362 te",
    "iso:country":"NL",
    "sg:address":"De Genestetstr 31",
    "sg:city":"Sliedrecht",
    "sg:orig_category":"Verenigingen En Stichtingen",
    "sg:phone":"+31 184 416 636",
    "sg:postcode":"3362 TE",
    "sg:province":"South Holland",
    "wof:name":"Wilhelmus",
    "wof:placetype":"venue"
},
  "geometry": {"coordinates":[4.779509,51.819447],"type":"Point"}
}