{
  "type": "Feature",
  "properties": {
    "addr:full":"Dirk Ruitenbeekstraat 21 Nijkerkerveen Gelderland 3864 GA",
    "addr:housenumber":"21",
    "addr:postcode":"3864 ga",
    "addr:street":"Dirk Ruitenbeekstraat;Gelderland",
    "iso:country":"NL",
    "sg:address":"Dirk Ruitenbeekstraat 21",
    "sg:city":"Nijkerkerveen",
    "sg:orig_category":"Goederenvervoer Over De Weg",
    "sg:phone":"+31 33 257 2145",
    "sg:postcode":"3864 GA",
    "sg:province":"Gelderland",
    "wof:name":"G. & T. Transport Bv",
    "wof:placetype":"venue"
},
  "geometry": {"coordinates":[5.464752,52.193703],"type":"Point"}
}