{
  "type": "Feature",
  "properties": {
    "iso:country":"NL",
    "sg:address":"Geutoomserf 1",
    "sg:city":"Eemnes",
    "sg:orig_category":"Goederenvervoer Over De Weg",
    "sg:phone":"+31 36 532 8646",
    "sg:postcode":"3755 VL",
    "sg:province":"Utrecht",
    "wof:name":"Speciaal Transport Eemnes/Almere",
    "wof:placetype":"venue"
},
  "geometry": {"coordinates":[5.257003,52.256325],"type":"Point"}
}