{
  "type": "Feature",
  "properties": {
    "addr:full":"Koelerweg 11 Harfsen Gelderland 7217 SR",
    "addr:housenumber":"11",
    "addr:postcode":"7217 sr",
    "addr:street":"Koelerweg;Gelderland",
    "iso:country":"NL",
    "sg:address":"Koelerweg 11",
    "sg:city":"Harfsen",
    "sg:orig_category":"Parfum And Cosmetica Gh",
    "sg:phone":"+31 573 431 861",
    "sg:postcode":"7217 SR",
    "sg:province":"Gelderland",
    "wof:name":"Anteris Laboratorium",
    "wof:placetype":"venue"
},
  "geometry": {"coordinates":[6.322355,52.193836],"type":"Point"}
}