{
  "type": "Feature",
  "properties": {
    "addr:full":"Kerkstr 18 Leerdam South Holland 4141 AW",
    "addr:housenumber":"18",
    "addr:postcode":"4141 aw",
    "addr:street":"Kerkstr",
    "iso:country":"NL",
    "sg:address":"Kerkstr 18",
    "sg:city":"Leerdam",
    "sg:orig_category":"Musea",
    "sg:phone":"+31 345 614 433",
    "sg:postcode":"4141 AW",
    "sg:province":"South Holland",
    "wof:name":"Oude Raadhuis, Het",
    "wof:placetype":"venue"
},
  "geometry": {"coordinates":[5.093996,51.891159],"type":"Point"}
}