{
  "type": "Feature",
  "properties": {
    "addr:full":"Dampln 41 Leidschendam Zuid-Holland 2265 AD",
    "addr:housenumber":"41",
    "addr:postcode":"2265 ad",
    "addr:street":"Dampln",
    "iso:country":"NL",
    "sg:address":"Dampln 41",
    "sg:city":"Leidschendam",
    "sg:orig_category":"Kansspelen",
    "sg:phone":"+31 70 327 5644",
    "sg:postcode":"2265 AD",
    "sg:province":"Zuid-Holland",
    "wof:name":"Champions",
    "wof:placetype":"venue"
},
  "geometry": {"coordinates":[4.3970060349,52.0807418823],"type":"Point"}
}