{
  "type": "Feature",
  "properties": {
    "addr:full":"Dr Y Poortingawg 6 Rinsumageest Friesland 9105 LJ",
    "addr:housenumber":"6",
    "addr:postcode":"9105 lj",
    "addr:street":"Dr Y Poortingawg",
    "iso:country":"NL",
    "sg:address":"Dr Y Poortingawg 6",
    "sg:city":"Rinsumageest",
    "sg:classifiers":[
        {
            "category":"Retail",
            "subcategory":"Auto Repair",
            "type":"Services"
        }
    ],
    "sg:phone":"+31 511 422 483",
    "sg:postcode":"9105 LJ",
    "sg:province":"Friesland",
    "sg:tags":[
        "garage"
    ],
    "wof:name":"Feenstra, F",
    "wof:placetype":"venue"
},
  "geometry": {"coordinates":[5.946643,53.299526],"type":"Point"}
}