{
  "type": "Feature",
  "properties": {
    "iso:country":"NL",
    "sg:address":"Grotestraat 14",
    "sg:city":"Markelo",
    "sg:classifiers":[
        {
            "category":"Fast Food",
            "type":"Food & Drink"
        }
    ],
    "sg:phone":"+31 547 363 040",
    "sg:postcode":"7475 AX",
    "sg:province":"Overijssel",
    "sg:tags":[
        "afhaal",
        "restaurant"
    ],
    "wof:name":"Chinees Indisch Afhaalcentrum Welkom",
    "wof:placetype":"venue"
},
  "geometry": {"coordinates":[6.492075,52.236168],"type":"Point"}
}