{
  "type": "Feature",
  "properties": {
    "iso:country":"NL",
    "sg:address":"Emmaplein 2",
    "sg:city":"Amsterdam",
    "sg:orig_category":"Bedrijfs- And Managementsconsultants",
    "sg:phone":"+31 20 672 0405",
    "sg:postcode":"1075 AW",
    "sg:province":"Noord-Holland",
    "wof:name":"Tobotex Bv",
    "wof:placetype":"venue"
},
  "geometry": {"coordinates":[4.862176,52.354725],"type":"Point"}
}