{
  "type": "Feature",
  "properties": {
    "iso:country":"NL",
    "sg:address":"Schalk Burgerstraat 10",
    "sg:city":"Amsterdam",
    "sg:orig_category":"Loodgieterswerk, Verwarming And Sanitaire Installaties",
    "sg:phone":"+31 20 468 0534",
    "sg:postcode":"1091 LJ",
    "sg:province":"North Holland",
    "wof:name":"Alex Mooyman Waterfittersbedrijf",
    "wof:placetype":"venue"
},
  "geometry": {"coordinates":[4.920147,52.35334],"type":"Point"}
}