{
  "type": "Feature",
  "properties": {
    "addr:full":"Nykerkerstr 14 Amersfoort Utrecht 3821 CE",
    "addr:housenumber":"14",
    "addr:postcode":"3821 ce",
    "addr:street":"Nykerkerstr",
    "iso:country":"NL",
    "sg:address":"Nykerkerstr 14",
    "sg:city":"Amersfoort",
    "sg:orig_category":"Ongediertebestrijding En Ontsmetting",
    "sg:phone":"+31 33 479 0313",
    "sg:postcode":"3821 CE",
    "sg:province":"Utrecht",
    "sg:website":"http://www.ongedierteverdelging.nl",
    "wof:name":"Jonker, J J",
    "wof:placetype":"venue"
},
  "geometry": {"coordinates":[5.415215,52.174911],"type":"Point"}
}