{
  "type": "Feature",
  "properties": {
    "addr:full":"Wykermeerwg 41 Beverwyk Noord-Holland 1948 NT",
    "addr:housenumber":"41",
    "addr:postcode":"1948 nt",
    "addr:street":"Wykermeerwg",
    "iso:country":"NL",
    "sg:address":"Wykermeerwg 41",
    "sg:city":"Beverwyk",
    "sg:orig_category":"Hypotheken",
    "sg:phone":"+31 251 290 900",
    "sg:postcode":"1948 NT",
    "sg:province":"Noord-Holland",
    "sg:website":"http://www.hac.nl",
    "wof:name":"Hypotheek Adviescentrum Beverwijk",
    "wof:placetype":"venue"
},
  "geometry": {"coordinates":[4.668478,52.476028],"type":"Point"}
}