{
  "type": "Feature",
  "properties": {
    "addr:full":"Meidoornpassage 16 Wezep Gelderland 8091 KS",
    "addr:housenumber":"16",
    "addr:postcode":"8091 ks",
    "addr:street":"Meidoornpassage",
    "iso:country":"NL",
    "sg:address":"Meidoornpassage 16",
    "sg:city":"Wezep",
    "sg:orig_category":"Bibliotheken And Openbare Archieven",
    "sg:phone":"+31 38 376 1977",
    "sg:postcode":"8091 KS",
    "sg:province":"Gelderland",
    "wof:name":"Openbare Bibliotheek",
    "wof:placetype":"venue"
},
  "geometry": {"coordinates":[5.998378,52.46175],"type":"Point"}
}