{
  "type": "Feature",
  "properties": {
    "iso:country":"NL",
    "sg:address":"Postbus 40",
    "sg:city":"Druten",
    "sg:classifiers":[
        {
            "category":"Shopping",
            "subcategory":"News",
            "type":"Retail Goods"
        }
    ],
    "sg:phone":"+31 487 512 696",
    "sg:postcode":"6650 AA",
    "sg:province":"Gelderland",
    "sg:tags":[
        "maandbladen",
        "en",
        "week-"
    ],
    "wof:name":"Waalkanter, De",
    "wof:placetype":"venue"
},
  "geometry": {"coordinates":[5.6052598953,51.8856697083],"type":"Point"}
}