{
  "type": "Feature",
  "properties": {
    "addr:full":"Randstad 2002 Almere Flevoland 1314 BA",
    "addr:housenumber":"2002",
    "addr:postcode":"1314 ba",
    "addr:street":"Flevoland",
    "iso:country":"NL",
    "sg:address":"Randstad 2002",
    "sg:city":"Almere",
    "sg:orig_category":"Daken And Skeletbouw",
    "sg:phone":"+31 36 533 0350",
    "sg:postcode":"1314 BA",
    "sg:province":"Flevoland",
    "wof:name":"Bv Nederlandse Dakdekkers Associatie",
    "wof:placetype":"venue"
},
  "geometry": {"coordinates":[5.222558,52.37624],"type":"Point"}
}