{
  "type": "Feature",
  "properties": {
    "addr:full":"Einsteinstr 2 Alkmaar North Holland 1821 BZ",
    "addr:housenumber":"2",
    "addr:postcode":"1821 bz",
    "addr:street":"Einsteinstr",
    "iso:country":"NL",
    "sg:address":"Einsteinstr 2",
    "sg:city":"Alkmaar",
    "sg:classifiers":[
        {
            "category":"Shopping",
            "subcategory":"News",
            "type":"Retail Goods"
        }
    ],
    "sg:phone":"+31 72 519 5950",
    "sg:postcode":"1821 BZ",
    "sg:province":"North Holland",
    "sg:tags":[
        "maandbladen",
        "en",
        "week-"
    ],
    "wof:name":"Alkmaars Weekblad",
    "wof:placetype":"venue"
},
  "geometry": {"coordinates":[4.7676391602,52.6271324158],"type":"Point"}
}