{
  "type": "Feature",
  "properties": {
    "iso:country":"NL",
    "sg:address":"Pelssingel 16",
    "sg:city":"'S Hertogenbosch",
    "sg:orig_category":"Fotostudio'S And Fotografen",
    "sg:phone":"+31 73 613 9400",
    "sg:postcode":"5212 PA",
    "sg:province":"Noord-Brabant",
    "wof:name":"Fotostudio Van Der Vorst",
    "wof:placetype":"venue"
},
  "geometry": {"coordinates":[5.310513,51.692513],"type":"Point"}
}