{
  "type": "Feature",
  "properties": {
    "addr:full":"Lovendaalhoeve 35 Maastricht Limburg 6225 AG",
    "addr:housenumber":"35",
    "addr:postcode":"6225",
    "addr:street":"Lovendaalhoeve",
    "iso:country":"NL",
    "sg:address":"Lovendaalhoeve 35",
    "sg:city":"Maastricht",
    "sg:orig_category":"Administratie- En Boekhoudkantoren",
    "sg:phone":"+31 43 363 2125",
    "sg:postcode":"6225 AG",
    "sg:province":"Limburg",
    "wof:name":"Jmd",
    "wof:placetype":"venue"
},
  "geometry": {"coordinates":[5.726288,50.860256],"type":"Point"}
}