{
  "type": "Feature",
  "properties": {
    "addr:full":"Klein Heiligland 69 Haarlem Noord-Holland 2011 ED",
    "addr:housenumber":"69",
    "addr:postcode":"2011 ed",
    "addr:street":"Klein Heiligland",
    "iso:country":"NL",
    "sg:address":"Klein Heiligland 69",
    "sg:city":"Haarlem",
    "sg:orig_category":"Fotostudio'S And Fotografen",
    "sg:phone":"+31 23 532 0109",
    "sg:postcode":"2011 ED",
    "sg:province":"Noord-Holland",
    "wof:name":"Fotopersburo Arnold Bartman",
    "wof:placetype":"venue"
},
  "geometry": {"coordinates":[4.632904,52.377102],"type":"Point"}
}