{
  "type": "Feature",
  "properties": {
    "addr:full":"Cypresstr 3 Breda North Brabant 4814 PN",
    "addr:housenumber":"3",
    "addr:postcode":"4814 pn",
    "addr:street":"Cypresstr",
    "iso:country":"NL",
    "sg:address":"Cypresstr 3",
    "sg:city":"Breda",
    "sg:orig_category":"Postkantoren",
    "sg:phone":"+31 76 521 4622",
    "sg:postcode":"4814 PN",
    "sg:province":"North Brabant",
    "sg:website":"http://www.postkantoor.nl",
    "wof:name":"Postkantoor",
    "wof:placetype":"venue"
},
  "geometry": {"coordinates":[4.754541,51.58762],"type":"Point"}
}