{
  "type": "Feature",
  "properties": {
    "addr:full":"Laurierstraat 147 'S Gravenhage Zuid-Holland 2563 SG",
    "addr:housenumber":"147 '",
    "addr:postcode":"2563 sg",
    "addr:street":"Laurierstraat",
    "iso:country":"NL",
    "sg:address":"Laurierstraat 147",
    "sg:city":"'S Gravenhage",
    "sg:orig_category":"Autokeuringen",
    "sg:phone":"+31 70 325 7128",
    "sg:postcode":"2563 SG",
    "sg:province":"Zuid-Holland",
    "wof:name":"Servicestation Laurier",
    "wof:placetype":"venue"
},
  "geometry": {"coordinates":[4.2719,52.069969],"type":"Point"}
}