{
  "type": "Feature",
  "properties": {
    "iso:country":"NL",
    "sg:address":"Maresngl 3",
    "sg:city":"Leiden",
    "sg:orig_category":"Scholen Voor Basisonderwijs",
    "sg:phone":"+31 71 524 7670",
    "sg:postcode":"2316 HA",
    "sg:province":"Zuid-Holland",
    "wof:name":"Bureau Openbaar Onderwijs",
    "wof:placetype":"venue"
},
  "geometry": {"coordinates":[4.49463,52.154572],"type":"Point"}
}