{
  "type": "Feature",
  "properties": {
    "addr:full":"Kijckerweg 84 De Lier Zuid-Holland 2678 AE",
    "addr:housenumber":"84",
    "addr:postcode":"2678 ae",
    "addr:street":"Kijckerweg",
    "iso:country":"NL",
    "sg:address":"Kijckerweg 84",
    "sg:city":"De Lier",
    "sg:orig_category":"Metaalwerken",
    "sg:phone":"+31 174 516 755",
    "sg:postcode":"2678 AE",
    "sg:province":"Zuid-Holland",
    "wof:name":"J.M.M. Kester",
    "wof:placetype":"venue"
},
  "geometry": {"coordinates":[4.240755,51.97504],"type":"Point"}
}