{
  "type": "Feature",
  "properties": {
    "addr:full":"Nijhofflaan 122 Dordrecht Zuid-Holland 3319 BS",
    "addr:housenumber":"122",
    "addr:postcode":"3319 bs",
    "addr:street":"Nijhofflaan",
    "iso:country":"NL",
    "sg:address":"Nijhofflaan 122",
    "sg:city":"Dordrecht",
    "sg:orig_category":"Kappers",
    "sg:phone":"+31 78 616 2639",
    "sg:postcode":"3319 BS",
    "sg:province":"Zuid-Holland",
    "wof:name":"H. Dekker",
    "wof:placetype":"venue"
},
  "geometry": {"coordinates":[4.6980772018,51.7974624634],"type":"Point"}
}