{
  "type": "Feature",
  "properties": {
    "addr:full":"Utrechtsestr 138 Amsterdam Noord-Holland 1017 VT",
    "addr:housenumber":"138",
    "addr:postcode":"1017",
    "iso:country":"NL",
    "sg:address":"Utrechtsestr 138",
    "sg:city":"Amsterdam",
    "sg:orig_category":"Drukkerijen",
    "sg:phone":"+31 20 627 7116",
    "sg:postcode":"1017 VT",
    "sg:province":"Noord-Holland",
    "wof:name":"Amstelgraphics",
    "wof:placetype":"venue"
},
  "geometry": {"coordinates":[4.899204,52.361118],"type":"Point"}
}