{
  "type": "Feature",
  "properties": {
    "addr:full":"Triangelhof 34 Zaandyk Noord-Holland 1544 WR",
    "addr:housenumber":"34",
    "addr:postcode":"1544 wr",
    "addr:street":"Triangelhof",
    "iso:country":"NL",
    "sg:address":"Triangelhof 34",
    "sg:city":"Zaandyk",
    "sg:classifiers":[
        {
            "category":"Personal",
            "subcategory":"Nail Salon",
            "type":"Services"
        }
    ],
    "sg:phone":"+31 75 628 6104",
    "sg:postcode":"1544 WR",
    "sg:province":"Noord-Holland",
    "sg:tags":[
        "pedicure"
    ],
    "wof:name":"Weide-Kaminska, S Van Der",
    "wof:placetype":"venue"
},
  "geometry": {"coordinates":[4.79533,52.472836],"type":"Point"}
}