{
  "type": "Feature",
  "properties": {
    "addr:full":"J Eylstr 15 Amsterdam Noord-Holland 1063 EM",
    "addr:housenumber":"15",
    "addr:postcode":"1063 em",
    "iso:country":"NL",
    "sg:address":"J Eylstr 15",
    "sg:city":"Amsterdam",
    "sg:orig_category":"Voegwerken",
    "sg:phone":"+31 20 614 9849",
    "sg:postcode":"1063 EM",
    "sg:province":"Noord-Holland",
    "wof:name":"Meer Bv, Ron V/D",
    "wof:placetype":"venue"
},
  "geometry": {"coordinates":[4.82559,52.3806],"type":"Point"}
}