{
  "type": "Feature",
  "properties": {
    "iso:country":"NL",
    "sg:address":"Grt Houtstr 145",
    "sg:city":"Haarlem",
    "sg:orig_category":"Kinderkleding",
    "sg:phone":"+31 23 534 6921",
    "sg:postcode":"2011 SK",
    "sg:province":"Noord-Holland",
    "wof:name":"Heavenly Angels & Stars",
    "wof:placetype":"venue"
},
  "geometry": {"coordinates":[4.631517,52.377411],"type":"Point"}
}