{
  "type": "Feature",
  "properties": {
    "addr:full":"Hoofdstr 42 Gorssel Gelderland 7213 CX",
    "addr:housenumber":"42",
    "addr:postcode":"7213 cx",
    "addr:street":"Hoofdstr;Gelderland",
    "iso:country":"NL",
    "sg:address":"Hoofdstr 42",
    "sg:city":"Gorssel",
    "sg:orig_category":"Bloemen En Planten",
    "sg:phone":"+31 575 492 176",
    "sg:postcode":"7213 CX",
    "sg:province":"Gelderland",
    "wof:name":"Edelweiss",
    "wof:placetype":"venue"
},
  "geometry": {"coordinates":[6.19949,52.200729],"type":"Point"}
}