{
  "type": "Feature",
  "properties": {
    "addr:full":"L Stam Beesestr 150 Rotterdam Zuid-Holland 3066 HB",
    "addr:housenumber":"150",
    "addr:postcode":"3066 hb",
    "iso:country":"NL",
    "sg:address":"L Stam Beesestr 150",
    "sg:city":"Rotterdam",
    "sg:orig_category":"Verzekeringen - Verzekeringskantoren",
    "sg:phone":"+31 10 411 0731",
    "sg:postcode":"3066 HB",
    "sg:province":"Zuid-Holland",
    "wof:name":"Haanappel Vof, H",
    "wof:placetype":"venue"
},
  "geometry": {"coordinates":[4.545618,51.930035],"type":"Point"}
}