{
  "type": "Feature",
  "properties": {
    "iso:country":"NL",
    "sg:address":"Noordzijde Zoom 74",
    "sg:city":"Bergen Op Zoom",
    "sg:orig_category":"Zalenexploitatie",
    "sg:phone":"+31 164 257 521",
    "sg:postcode":"4614 AE",
    "sg:province":"Noord-Brabant",
    "wof:name":"Evenementenhallen Beheer B.V.",
    "wof:placetype":"venue"
},
  "geometry": {"coordinates":[4.292565,51.500229],"type":"Point"}
}