{
  "type": "Feature",
  "properties": {
    "iso:country":"NL",
    "sg:address":"Trimbaan 22",
    "sg:city":"Biddinghuizen",
    "sg:orig_category":"Juridische Dienstverlening",
    "sg:phone":"+31 321 333 989",
    "sg:postcode":"8256 GL",
    "sg:province":"Flevoland",
    "wof:name":"Juridisch Adviesbureau Heemskerk",
    "wof:placetype":"venue"
},
  "geometry": {"coordinates":[5.695365,52.451653],"type":"Point"}
}