{
  "type": "Feature",
  "properties": {
    "addr:full":"Westkousdk 155-161 Rotterdam Zuid-Holland 3029 BX",
    "addr:housenumber":"155-161",
    "addr:postcode":"3029 bx",
    "iso:country":"NL",
    "sg:address":"Westkousdk 155-161",
    "sg:city":"Rotterdam",
    "sg:orig_category":"Acupunctuur",
    "sg:phone":"+31 10 476 3727",
    "sg:postcode":"3029 BX",
    "sg:province":"Zuid-Holland",
    "wof:name":"Schimmer, G J",
    "wof:placetype":"venue"
},
  "geometry": {"coordinates":[4.444791,51.90403],"type":"Point"}
}