{
  "type": "Feature",
  "properties": {
    "addr:full":"Botnische Golf 3 Woerden Illinois 3446 CN",
    "addr:housenumber":"3",
    "addr:postcode":"3446 cn",
    "addr:street":"Botnische Golf",
    "iso:country":"NL",
    "sg:address":"Botnische Golf 3",
    "sg:city":"Woerden",
    "sg:orig_category":"Loodgieters",
    "sg:phone":"+31 348 413 601",
    "sg:postcode":"3446 CN",
    "sg:province":"Illinois",
    "wof:name":"Plomp Bv",
    "wof:placetype":"venue"
},
  "geometry": {"coordinates":[-89.85790299999999,38.983795],"type":"Point"}
}