{
  "type": "Feature",
  "properties": {
    "addr:full":"Rijswijkseweg 205 'S Gravenhage Zuid-Holland 2516  H",
    "addr:housenumber":"205 ';2516 h",
    "addr:street":"Rijswijkseweg",
    "iso:country":"NL",
    "sg:address":"Rijswijkseweg 205",
    "sg:city":"'S Gravenhage",
    "sg:classifiers":[
        {
            "category":"Fast Food",
            "type":"Food & Drink"
        }
    ],
    "sg:phone":"+31 70 399 9333",
    "sg:postcode":"2516  H",
    "sg:province":"Zuid-Holland",
    "sg:tags":[
        "afhaal",
        "restaurant"
    ],
    "wof:name":"Deli 'S Pizza Italia",
    "wof:placetype":"venue"
},
  "geometry": {"coordinates":[4.331048,52.063461],"type":"Point"}
}