{
  "type": "Feature",
  "properties": {
    "addr:full":"Oostergrachtswal 123 Leeuwarden Friesland 8921 AC",
    "addr:housenumber":"123",
    "addr:postcode":"8921 ac",
    "addr:street":"Oostergrachtswal",
    "iso:country":"NL",
    "sg:address":"Oostergrachtswal 123",
    "sg:city":"Leeuwarden",
    "sg:orig_category":"Fitnesscentra",
    "sg:phone":"+31 58 212 9194",
    "sg:postcode":"8921 AC",
    "sg:province":"Friesland",
    "wof:name":"Leeuw, Sportcentrum De",
    "wof:placetype":"venue"
},
  "geometry": {"coordinates":[5.803113,53.200142],"type":"Point"}
}