{
  "type": "Feature",
  "properties": {
    "iso:country":"NL",
    "sg:address":"Spinsterln 4",
    "sg:city":"De Meern",
    "sg:orig_category":"Gordijnen",
    "sg:phone":"+31 30 666 1282",
    "sg:postcode":"3454 WZ",
    "sg:province":"Utrecht",
    "wof:name":"Verhoef, J A",
    "wof:placetype":"venue"
},
  "geometry": {"coordinates":[5.030259,52.075832],"type":"Point"}
}