{
  "type": "Feature",
  "properties": {
    "addr:full":"Ln Vd Mensenrecht 312 Apeldoorn Gelderland 7331 VX",
    "addr:housenumber":"312",
    "addr:postcode":"7331 vx",
    "addr:street":"Ln;Gelderland",
    "iso:country":"NL",
    "sg:address":"Ln Vd Mensenrecht 312",
    "sg:city":"Apeldoorn",
    "sg:orig_category":"Administratie- En Boekhoudkantoren",
    "sg:phone":"+31 55 533 4654",
    "sg:postcode":"7331 VX",
    "sg:province":"Gelderland",
    "wof:name":"Essen, M E Van",
    "wof:placetype":"venue"
},
  "geometry": {"coordinates":[5.9686,52.208805],"type":"Point"}
}