{
  "type": "Feature",
  "properties": {
    "addr:full":"Hoogeindsestr 7 Tiel Gelderland 4001 AA",
    "addr:housenumber":"7",
    "addr:postcode":"4001 aa",
    "addr:street":"Hoogeindsestr;Gelderland",
    "iso:country":"NL",
    "sg:address":"Hoogeindsestr 7",
    "sg:city":"Tiel",
    "sg:orig_category":"Bloemen En Planten",
    "sg:phone":"+31 344 611 098",
    "sg:postcode":"4001 AA",
    "sg:province":"Gelderland",
    "wof:name":"Bouquetterie, De",
    "wof:placetype":"venue"
},
  "geometry": {"coordinates":[5.432366,51.888054],"type":"Point"}
}