{
  "type": "Feature",
  "properties": {
    "addr:full":"Westhavenplaats 8 Vlaardingen Zuid-Holland 3131 BT",
    "addr:housenumber":"8",
    "addr:postcode":"3131 bt",
    "addr:street":"Westhavenplaats",
    "iso:country":"NL",
    "sg:address":"Westhavenplaats 8",
    "sg:city":"Vlaardingen",
    "sg:orig_category":"Antiekzaken",
    "sg:phone":"+31 10 434 3434",
    "sg:postcode":"3131 BT",
    "sg:province":"Zuid-Holland",
    "wof:name":"D'Antiekzolder",
    "wof:placetype":"venue"
},
  "geometry": {"coordinates":[4.343695,51.910145],"type":"Point"}
}