{
  "type": "Feature",
  "properties": {
    "addr:full":"Dorpsstraat 1 Vught Noord-Brabant 5261 CJ",
    "addr:housenumber":"1",
    "addr:postcode":"5261 cj",
    "addr:street":"Dorpsstraat",
    "iso:country":"NL",
    "sg:address":"Dorpsstraat 1",
    "sg:city":"Vught",
    "sg:orig_category":"Werving And Selectie Van Vast Personeel",
    "sg:phone":"+31 73 657 7526",
    "sg:postcode":"5261 CJ",
    "sg:province":"Noord-Brabant",
    "wof:name":"Psd Consultants",
    "wof:placetype":"venue"
},
  "geometry": {"coordinates":[5.2976632118,51.6605186462],"type":"Point"}
}