{
  "type": "Feature",
  "properties": {
    "addr:full":"Zuidwg 42 Naaldwijk Zuid-Holland 2671 MN",
    "addr:housenumber":"42",
    "addr:postcode":"2671 mn",
    "addr:street":"Zuidwg",
    "iso:country":"NL",
    "sg:address":"Zuidwg 42",
    "sg:city":"Naaldwijk",
    "sg:orig_category":"Verenigingen En Stichtingen",
    "sg:phone":"+31 174 620 360",
    "sg:postcode":"2671 MN",
    "sg:province":"Zuid-Holland",
    "sg:website":"http://www.rhp.nl",
    "wof:name":"Rhp Regeling Handels Potgronden, Sticht",
    "wof:placetype":"venue"
},
  "geometry": {"coordinates":[4.20723,51.987511],"type":"Point"}
}