{
  "type": "Feature",
  "properties": {
    "iso:country":"NL",
    "sg:address":"Prins Mauritssingel 21",
    "sg:city":"Nieuwerkerk Ad Ijssel",
    "sg:orig_category":"Alternatieve Geneeskunde",
    "sg:phone":"+31 180 311 299",
    "sg:postcode":"2912 BG",
    "sg:province":"Zuid-Holland",
    "wof:name":"Huidverzorgingsstudio Gaia",
    "wof:placetype":"venue"
},
  "geometry": {"coordinates":[4.604623,51.963741],"type":"Point"}
}