{
  "type": "Feature",
  "properties": {
    "addr:full":"Hoofdwg 81 Blyham Groningen 9697 NC",
    "addr:housenumber":"81;9697",
    "addr:postcode":"nc",
    "addr:street":"Hoofdwg",
    "iso:country":"NL",
    "sg:address":"Hoofdwg 81",
    "sg:city":"Blyham",
    "sg:orig_category":"Bloemen En Planten",
    "sg:phone":"+31 597 561 019",
    "sg:postcode":"9697 NC",
    "sg:province":"Groningen",
    "wof:name":"Marian",
    "wof:placetype":"venue"
},
  "geometry": {"coordinates":[7.074502,53.105606],"type":"Point"}
}