{
  "type": "Feature",
  "properties": {
    "iso:country":"NL",
    "sg:address":"Postbus 34170",
    "sg:city":"Rotterdam",
    "sg:orig_category":"Schilders",
    "sg:phone":"+31 6 54686200",
    "sg:postcode":"3005 GD",
    "sg:province":"Utrecht",
    "sg:website":"http://www.schilders.com",
    "wof:name":"Blok",
    "wof:placetype":"venue"
},
  "geometry": {"coordinates":[4.47075,51.922619],"type":"Point"}
}