{
  "type": "Feature",
  "properties": {
    "addr:full":"Veldmaterstr 180 Haaksbergen Overijssel 7481 AD",
    "addr:housenumber":"180",
    "addr:postcode":"7481 ad",
    "iso:country":"NL",
    "sg:address":"Veldmaterstr 180",
    "sg:city":"Haaksbergen",
    "sg:orig_category":"Kappers",
    "sg:phone":"+31 53 572 3332",
    "sg:postcode":"7481 AD",
    "sg:province":"Overijssel",
    "wof:name":"Benemonte",
    "wof:placetype":"venue"
},
  "geometry": {"coordinates":[6.7557678223,52.1638870239],"type":"Point"}
}