{
  "type": "Feature",
  "properties": {
    "addr:full":"Maatschapslaan 25 Alphen A/D Rijn Zuid-Holland 2404 CL",
    "addr:housenumber":"25",
    "addr:postcode":"2404",
    "addr:street":"Maatschapslaan",
    "iso:country":"NL",
    "sg:address":"Maatschapslaan 25",
    "sg:city":"Alphen A/D Rijn",
    "sg:orig_category":"Bouwmaterialen Gh",
    "sg:phone":"+31 172 240 019",
    "sg:postcode":"2404 CL",
    "sg:province":"Zuid-Holland",
    "wof:name":"Mocap Benelux Bv",
    "wof:placetype":"venue"
},
  "geometry": {"coordinates":[4.629133,52.133514],"type":"Point"}
}