{
  "type": "Feature",
  "properties": {
    "addr:full":"De Rosmolen 40 Biddinghuizen Flevoland 8256 ED",
    "addr:housenumber":"40",
    "addr:postcode":"8256 ed",
    "addr:street":"De Rosmolen;Flevoland",
    "iso:country":"NL",
    "sg:address":"De Rosmolen 40",
    "sg:city":"Biddinghuizen",
    "sg:orig_category":"Film-, Tv- And Videoproductie",
    "sg:phone":"+31 321 332 722",
    "sg:postcode":"8256 ED",
    "sg:province":"Flevoland",
    "wof:name":"B.G. Metz",
    "wof:placetype":"venue"
},
  "geometry": {"coordinates":[5.698048,52.455349],"type":"Point"}
}