{
  "type": "Feature",
  "properties": {
    "addr:full":"Krimwg 10 De Cocksdorp Noord-Holland 1795 LP",
    "addr:housenumber":"10",
    "addr:postcode":"1795 lp",
    "addr:street":"Krimwg",
    "iso:country":"NL",
    "sg:address":"Krimwg 10",
    "sg:city":"De Cocksdorp",
    "sg:orig_category":"Gasapparaten En -Artikelen",
    "sg:phone":"+31 222 316 306",
    "sg:postcode":"1795 LP",
    "sg:province":"Noord-Holland",
    "wof:name":"Tongelen, Van",
    "wof:placetype":"venue"
},
  "geometry": {"coordinates":[4.859223,53.156952],"type":"Point"}
}