{
  "type": "Feature",
  "properties": {
    "addr:full":"D Visserstr 41 Terneuzen Zeeland 4531 BB",
    "addr:housenumber":"41",
    "addr:postcode":"4531 bb",
    "iso:country":"NL",
    "sg:address":"D Visserstr 41",
    "sg:city":"Terneuzen",
    "sg:orig_category":"Kappers",
    "sg:phone":"+31 115 612 983",
    "sg:postcode":"4531 BB",
    "sg:province":"Zeeland",
    "wof:name":"Meijer, De",
    "wof:placetype":"venue"
},
  "geometry": {"coordinates":[3.824021,51.335838],"type":"Point"}
}