{
  "type": "Feature",
  "properties": {
    "addr:full":"B H Spykerwg 16 Punthorst Overijssel 7715 PW",
    "addr:housenumber":"16",
    "addr:postcode":"7715 pw",
    "addr:street":"B",
    "iso:country":"NL",
    "sg:address":"B H Spykerwg 16",
    "sg:city":"Punthorst",
    "sg:orig_category":"Artiesten/Gezelschappen",
    "sg:phone":"+31 529 427 079",
    "sg:postcode":"7715 PW",
    "sg:province":"Overijssel",
    "sg:website":"http://www.krale.nl",
    "wof:name":"Krale",
    "wof:placetype":"venue"
},
  "geometry": {"coordinates":[6.263585,52.613255],"type":"Point"}
}