{
  "type": "Feature",
  "properties": {
    "addr:full":"V Dieststr 1 Ootmarsum Overijssel 7631 DE",
    "addr:housenumber":"1",
    "addr:postcode":"7631 de",
    "addr:street":"V Dieststr",
    "iso:country":"NL",
    "sg:address":"V Dieststr 1",
    "sg:city":"Ootmarsum",
    "sg:orig_category":"Adviesbureaus Bedrijfsorganisatie",
    "sg:phone":"+31 541 294 126",
    "sg:postcode":"7631 DE",
    "sg:province":"Overijssel",
    "wof:name":"Hoff, Ten",
    "wof:placetype":"venue"
},
  "geometry": {"coordinates":[6.89415,52.406929],"type":"Point"}
}