{
  "type": "Feature",
  "properties": {
    "addr:full":"Dorpsstr 56 Mydrecht Utrecht 3641 ED",
    "addr:housenumber":"56;3641",
    "addr:postcode":"ed",
    "addr:street":"Dorpsstr",
    "iso:country":"NL",
    "sg:address":"Dorpsstr 56",
    "sg:city":"Mydrecht",
    "sg:orig_category":"Makelaars En Adviseurs Onroerende Goederen",
    "sg:phone":"+31 297 285 553",
    "sg:postcode":"3641 ED",
    "sg:province":"Utrecht",
    "sg:website":"http://www.kooplenstra.nl",
    "wof:name":"Koop Lenstra",
    "wof:placetype":"venue"
},
  "geometry": {"coordinates":[4.866354,52.208538],"type":"Point"}
}