{
  "type": "Feature",
  "properties": {
    "addr:full":"Fluitekruid 64 Den Hoorn Zh Zuid-Holland 2635 KT",
    "addr:housenumber":"64",
    "addr:postcode":"2635 kt",
    "addr:street":"Fluitekruid",
    "iso:country":"NL",
    "sg:address":"Fluitekruid 64",
    "sg:city":"Den Hoorn Zh",
    "sg:orig_category":"Administratie- En Boekhoudkantoren",
    "sg:phone":"+31 15 262 2533",
    "sg:postcode":"2635 KT",
    "sg:province":"Zuid-Holland",
    "wof:name":"Agaf Bv",
    "wof:placetype":"venue"
},
  "geometry": {"coordinates":[4.332523,52.004208],"type":"Point"}
}