{
  "type": "Feature",
  "properties": {
    "addr:full":"Noordeinde 1 Zevenhoven Zuid-Holland 2435 AC",
    "addr:housenumber":"1",
    "addr:postcode":"2435 ac",
    "addr:street":"Noordeinde",
    "iso:country":"NL",
    "sg:address":"Noordeinde 1",
    "sg:city":"Zevenhoven",
    "sg:orig_category":"Kappers",
    "sg:phone":"+31 172 539 478",
    "sg:postcode":"2435 AC",
    "sg:province":"Zuid-Holland",
    "wof:name":"Kapsalon De Lelie",
    "wof:placetype":"venue"
},
  "geometry": {"coordinates":[4.7772469521,52.1868133545],"type":"Point"}
}