{
  "type": "Feature",
  "properties": {
    "addr:full":"Garderenseweg 164 Putten Gelderland 3881 NE",
    "addr:housenumber":"164;3881",
    "addr:street":"Garderenseweg;Gelderland;Ne",
    "iso:country":"NL",
    "sg:address":"Garderenseweg 164",
    "sg:city":"Putten",
    "sg:orig_category":"Autokeuringen",
    "sg:phone":"+31 577 462 755",
    "sg:postcode":"3881 NE",
    "sg:province":"Gelderland",
    "wof:name":"Amc Putten",
    "wof:placetype":"venue"
},
  "geometry": {"coordinates":[5.673544,52.236229],"type":"Point"}
}