{
  "type": "Feature",
  "properties": {
    "addr:full":"Winkelcentrum 13 Etten Leur North Brabant 4873 AA",
    "addr:housenumber":"13",
    "addr:postcode":"4873 aa",
    "addr:street":"Winkelcentrum",
    "iso:country":"NL",
    "sg:address":"Winkelcentrum 13",
    "sg:city":"Etten Leur",
    "sg:orig_category":"Fotoreportages",
    "sg:phone":"+31 76 501 2868",
    "sg:postcode":"4873 AA",
    "sg:province":"North Brabant",
    "wof:name":"Marc Verwiel",
    "wof:placetype":"venue"
},
  "geometry": {"coordinates":[4.635622,51.568317],"type":"Point"}
}