{
  "type": "Feature",
  "properties": {
    "addr:full":"K Akkers 24 Veendam Groningen 9644 XT",
    "addr:housenumber":"24",
    "addr:postcode":"9644 xt",
    "addr:street":"K Akkers",
    "iso:country":"NL",
    "sg:address":"K Akkers 24",
    "sg:city":"Veendam",
    "sg:orig_category":"Projectontwikkeling",
    "sg:phone":"+31 598 617 275",
    "sg:postcode":"9644 XT",
    "sg:province":"Groningen",
    "wof:name":"Starke Holding Bv, J",
    "wof:placetype":"venue"
},
  "geometry": {"coordinates":[6.902875,53.090061],"type":"Point"}
}