{
  "type": "Feature",
  "properties": {
    "addr:full":"Oudekamp 18 Utrecht Utrecht 3512 KH",
    "addr:housenumber":"18",
    "addr:postcode":"3512 kh",
    "addr:street":"Oudekamp",
    "iso:country":"NL",
    "sg:address":"Oudekamp 18",
    "sg:city":"Utrecht",
    "sg:orig_category":"Beeldende Kunstenaars",
    "sg:phone":"+31 30 234 1280",
    "sg:postcode":"3512 KH",
    "sg:province":"Utrecht",
    "wof:name":"Donker, Charles",
    "wof:placetype":"venue"
},
  "geometry": {"coordinates":[5.115405,52.088932],"type":"Point"}
}