{
  "type": "Feature",
  "properties": {
    "addr:full":"Hertogstr 119 Nijmegen Gelderland 6511 RX",
    "addr:housenumber":"119",
    "addr:postcode":"6511 rx",
    "addr:street":"Gelderland",
    "iso:country":"NL",
    "sg:address":"Hertogstr 119",
    "sg:city":"Nijmegen",
    "sg:orig_category":"Kappers",
    "sg:phone":"+31 24 322 9423",
    "sg:postcode":"6511 RX",
    "sg:province":"Gelderland",
    "wof:name":"Jansen",
    "wof:placetype":"venue"
},
  "geometry": {"coordinates":[5.8685851097,51.8449935913],"type":"Point"}
}