{
  "type": "Feature",
  "properties": {
    "addr:full":"Putstr 2A Amstenrade Limburg 6436 BV",
    "addr:housenumber":"2a",
    "addr:postcode":"6436 bv",
    "addr:street":"Putstr",
    "iso:country":"NL",
    "sg:address":"Putstr 2A",
    "sg:city":"Amstenrade",
    "sg:orig_category":"Verhuur",
    "sg:phone":"+31 46 442 4999",
    "sg:postcode":"6436 BV",
    "sg:province":"Limburg",
    "wof:name":"Winchester City",
    "wof:placetype":"venue"
},
  "geometry": {"coordinates":[5.923456,50.94099],"type":"Point"}
}