{
  "type": "Feature",
  "properties": {
    "iso:country":"NL",
    "sg:address":"Industriewg 40",
    "sg:city":"Maastricht",
    "sg:orig_category":"Metaalwaren - Fabrieken",
    "sg:phone":"+31 43 351 6666",
    "sg:postcode":"6219 NR",
    "sg:province":"Limburg",
    "sg:website":"http://www.thomasregout.com",
    "wof:name":"Thomas Regout International Bv",
    "wof:placetype":"venue"
},
  "geometry": {"coordinates":[5.684806,50.864635],"type":"Point"}
}