{
  "type": "Feature",
  "properties": {
    "addr:full":"Baarnsewg 57 Den Dolder Utrecht 3734 CA",
    "addr:housenumber":"57",
    "addr:postcode":"3734 ca",
    "addr:street":"Baarnsewg",
    "iso:country":"NL",
    "sg:address":"Baarnsewg 57",
    "sg:city":"Den Dolder",
    "sg:orig_category":"Honden- En Kattentrimsalons",
    "sg:phone":"+31 30 225 3975",
    "sg:postcode":"3734 CA",
    "sg:province":"Utrecht",
    "wof:name":"Trimmerij, De",
    "wof:placetype":"venue"
},
  "geometry": {"coordinates":[5.241746,52.137253],"type":"Point"}
}