{
  "type": "Feature",
  "properties": {
    "iso:country":"NL",
    "sg:address":"Kerkenkavel 49",
    "sg:city":"Hollandscheveld",
    "sg:orig_category":"Bibliotheken En Leeszalen Openbare",
    "sg:phone":"+31 528 341 792",
    "sg:postcode":"7913 AS",
    "sg:province":"Drenthe",
    "wof:name":"Openb Bibliotheek",
    "wof:placetype":"venue"
},
  "geometry": {"coordinates":[6.539462,52.707527],"type":"Point"}
}