{
  "type": "Feature",
  "properties": {
    "addr:full":"Stadsgravenstraat 15 A Enschede Overijssel 7511 EP",
    "addr:housenumber":"15 a",
    "addr:postcode":"7511 ep",
    "addr:street":"Stadsgravenstraat",
    "iso:country":"NL",
    "sg:address":"Stadsgravenstraat 15 A",
    "sg:city":"Enschede",
    "sg:orig_category":"Organisaties And Verenigingen",
    "sg:phone":"+31 53 430 4285",
    "sg:postcode":"7511 EP",
    "sg:province":"Overijssel",
    "wof:name":"Ehtsv",
    "wof:placetype":"venue"
},
  "geometry": {"coordinates":[6.8943328857,52.2214126587],"type":"Point"}
}