{
  "type": "Feature",
  "properties": {
    "addr:full":"Meezenbroekerwg 50 Heerlen Limburg 6412 VK",
    "addr:housenumber":"50",
    "addr:postcode":"6412 vk",
    "addr:street":"Meezenbroekerwg",
    "iso:country":"NL",
    "sg:address":"Meezenbroekerwg 50",
    "sg:city":"Heerlen",
    "sg:orig_category":"Fitnesscentra",
    "sg:phone":"+31 45 572 6213",
    "sg:postcode":"6412 VK",
    "sg:province":"Limburg",
    "wof:name":"Aerobic Martial Center",
    "wof:placetype":"venue"
},
  "geometry": {"coordinates":[5.97882,50.894241],"type":"Point"}
}