{
  "type": "Feature",
  "properties": {
    "iso:country":"NL",
    "sg:address":"Hoofdstr 24",
    "sg:city":"Warffum",
    "sg:orig_category":"Goudsmeden En Zilversmeden",
    "sg:phone":"+31 595 425 059",
    "sg:postcode":"9989 AN",
    "sg:province":"Groningen",
    "wof:name":"La Mesa Verde American Studio",
    "wof:placetype":"venue"
},
  "geometry": {"coordinates":[6.561713,53.391644],"type":"Point"}
}