{
  "type": "Feature",
  "properties": {
    "addr:full":"Londensekaai 9 Middelburg Zeeland 4331 JG",
    "addr:housenumber":"9",
    "addr:postcode":"4331 jg",
    "addr:street":"Londensekaai",
    "iso:country":"NL",
    "sg:address":"Londensekaai 9",
    "sg:city":"Middelburg",
    "sg:orig_category":"Begrafenisverzorging",
    "sg:phone":"+31 118 623 359",
    "sg:postcode":"4331 JG",
    "sg:province":"Zeeland",
    "wof:name":"Janneke Den Besten",
    "wof:placetype":"venue"
},
  "geometry": {"coordinates":[3.616659,51.497925],"type":"Point"}
}