{
  "type": "Feature",
  "properties": {
    "addr:full":"Stadhuispln 349 Tilburg Noord-Brabant 5038 TH",
    "addr:housenumber":"349",
    "addr:postcode":"5038 th",
    "addr:street":"Tilburg",
    "iso:country":"NL",
    "sg:address":"Stadhuispln 349",
    "sg:city":"Tilburg",
    "sg:classifiers":[
        {
            "category":"Shopping",
            "subcategory":"Adult",
            "type":"Retail Goods"
        }
    ],
    "sg:phone":"+31 13 511 9050",
    "sg:postcode":"5038 TH",
    "sg:province":"Noord-Brabant",
    "sg:tags":[
        "lingerie",
        "en",
        "tricotage"
    ],
    "wof:name":"Eee",
    "wof:placetype":"venue"
},
  "geometry": {"coordinates":[5.087042,51.555992],"type":"Point"}
}