{
  "type": "Feature",
  "properties": {
    "iso:country":"NL",
    "sg:address":"Vendelsewg 30",
    "sg:city":"Veenendaal",
    "sg:orig_category":"Scholen Voor Basisonderwijs",
    "sg:phone":"+31 318 511 072",
    "sg:postcode":"3905 LD",
    "sg:province":"Utrecht",
    "wof:name":"Juliana Van Stolberg",
    "wof:placetype":"venue"
},
  "geometry": {"coordinates":[5.552602,52.032673],"type":"Point"}
}