{
  "type": "Feature",
  "properties": {
    "addr:full":"Postbus 989 S Gravenhage 2501 CZ",
    "addr:housenumber":"989;2501",
    "addr:street":"Postbus;S Gravenhage",
    "iso:country":"NL",
    "sg:address":"Postbus 989",
    "sg:city":"S Gravenhage",
    "sg:orig_category":"Beveiliging",
    "sg:phone":"+31 70 356 0805",
    "sg:postcode":"2501 CZ",
    "sg:website":"http://www.lijfwachten.nl",
    "wof:name":"Tba Terpstra Bodyguards Association",
    "wof:placetype":"venue"
},
  "geometry": {"coordinates":[4.31361,52.07832],"type":"Point"}
}