{
  "type": "Feature",
  "properties": {
    "iso:country":"NL",
    "sg:address":"Beatrixstraat 1",
    "sg:city":"Leiden",
    "sg:classifiers":[
        {
            "category":"Bakery",
            "type":"Food & Drink"
        }
    ],
    "sg:phone":"+31 71 521 7850",
    "sg:postcode":"2316 RE",
    "sg:province":"Zuid-Holland",
    "sg:tags":[
        "brood",
        "banket"
    ],
    "wof:name":"Fa Preenen",
    "wof:placetype":"venue"
},
  "geometry": {"coordinates":[4.50428,52.166424],"type":"Point"}
}