{
  "type": "Feature",
  "properties": {
    "addr:full":"Binnenburg 9 Den Burg North Holland 1791 CG",
    "addr:housenumber":"9",
    "addr:postcode":"1791 cg",
    "addr:street":"Binnenburg",
    "iso:country":"NL",
    "sg:address":"Binnenburg 9",
    "sg:city":"Den Burg",
    "sg:orig_category":"Banken",
    "sg:phone":"+31 222 312 920",
    "sg:postcode":"1791 CG",
    "sg:province":"North Holland",
    "wof:name":"Fortis",
    "wof:placetype":"venue"
},
  "geometry": {"coordinates":[4.797087,53.054649],"type":"Point"}
}