{
  "type": "Feature",
  "properties": {
    "addr:full":"Wilhelminastraat 41 Vlaardingen Zuid-Holland 3134 CR",
    "addr:housenumber":"41",
    "addr:postcode":"3134 cr",
    "addr:street":"Wilhelminastraat",
    "iso:country":"NL",
    "sg:address":"Wilhelminastraat 41",
    "sg:city":"Vlaardingen",
    "sg:orig_category":"Loodgieterswerk, Verwarming And Sanitaire Installaties",
    "sg:phone":"+31 10 435 6963",
    "sg:postcode":"3134 CR",
    "sg:province":"Zuid-Holland",
    "wof:name":"Ron Van Uffelen Loodgietersbedrijf",
    "wof:placetype":"venue"
},
  "geometry": {"coordinates":[4.350849,51.90786],"type":"Point"}
}