{
  "type": "Feature",
  "properties": {
    "addr:full":"Oosterhoutsedk 45 Lent Gelderland 6663 KT",
    "addr:housenumber":"45",
    "addr:postcode":"6663 kt",
    "addr:street":"Oosterhoutsedk;Gelderland",
    "iso:country":"NL",
    "sg:address":"Oosterhoutsedk 45",
    "sg:city":"Lent",
    "sg:orig_category":"Kamerverhuur En -Bemiddeling",
    "sg:phone":"+31 24 360 6471",
    "sg:postcode":"6663 KT",
    "sg:province":"Gelderland",
    "wof:name":"Hultog",
    "wof:placetype":"venue"
},
  "geometry": {"coordinates":[-77.2414321899,38.1513442993],"type":"Point"}
}