{
  "type": "Feature",
  "properties": {
    "addr:full":"Langstr 55 Barneveld Gelderland 3771 BC",
    "addr:housenumber":"55",
    "addr:postcode":"3771 bc",
    "addr:street":"Langstr;Gelderland",
    "iso:country":"NL",
    "sg:address":"Langstr 55",
    "sg:city":"Barneveld",
    "sg:orig_category":"Partyservice",
    "sg:phone":"+31 342 414 874",
    "sg:postcode":"3771 BC",
    "sg:province":"Gelderland",
    "wof:name":"Straaljager, De",
    "wof:placetype":"venue"
},
  "geometry": {"coordinates":[5.585655,52.139256],"type":"Point"}
}