{
  "type": "Feature",
  "properties": {
    "addr:full":"Heemsteedse Dreef 19 Heemstede Noord-Holland 2103 LL",
    "addr:housenumber":"19",
    "addr:postcode":"2103 ll",
    "addr:street":"Heemsteedse Dreef",
    "iso:country":"NL",
    "sg:address":"Heemsteedse Dreef 19",
    "sg:city":"Heemstede",
    "sg:classifiers":[
        {
            "category":"Personal",
            "subcategory":"Nail Salon",
            "type":"Services"
        }
    ],
    "sg:phone":"+31 23 547 0736",
    "sg:postcode":"2103 LL",
    "sg:province":"Noord-Holland",
    "sg:tags":[
        "pedicure"
    ],
    "wof:name":"Verhulsdonk",
    "wof:placetype":"venue"
},
  "geometry": {"coordinates":[4.622575,52.345238],"type":"Point"}
}