{
  "type": "Feature",
  "properties": {
    "addr:full":"Ln V Heldenburg 60 Voorburg Zuid-Holland 2271 AV",
    "addr:housenumber":"60",
    "addr:postcode":"2271 av",
    "addr:street":"Ln;Heldenburg",
    "iso:country":"NL",
    "sg:address":"Ln V Heldenburg 60",
    "sg:city":"Voorburg",
    "sg:orig_category":"Adviesbureaus Bedrijfsorganisatie",
    "sg:phone":"+31 70 386 9940",
    "sg:postcode":"2271 AV",
    "sg:province":"Zuid-Holland",
    "wof:name":"Ledcor Bv",
    "wof:placetype":"venue"
},
  "geometry": {"coordinates":[4.363825,52.068233],"type":"Point"}
}