{
  "type": "Feature",
  "properties": {
    "iso:country":"NL",
    "sg:address":"Grebbe 12",
    "sg:city":"Tilburg",
    "sg:orig_category":"Kinderopvang Behalve Thuis",
    "sg:phone":"+31 13 463 4260",
    "sg:postcode":"5032 RT",
    "sg:province":"Noord-Brabant",
    "wof:name":"Peuterspeelzaal 'T Hummeltje",
    "wof:placetype":"venue"
},
  "geometry": {"coordinates":[5.046775,51.545406],"type":"Point"}
}