{
  "type": "Feature",
  "properties": {
    "iso:country":"NL",
    "sg:address":"W Ruyspln 14",
    "sg:city":"Zwyndrecht",
    "sg:orig_category":"Cafetaria'S",
    "sg:phone":"+31 78 612 9125",
    "sg:postcode":"3333 BX",
    "sg:province":"Zuid-Holland",
    "wof:name":"Vermoen'S Taria Zwijndr",
    "wof:placetype":"venue"
},
  "geometry": {"coordinates":[4.63394,51.81358],"type":"Point"}
}