{
  "type": "Feature",
  "properties": {
    "iso:country":"NL",
    "sg:address":"J V Eyckgr 181",
    "sg:city":"Eindhoven",
    "sg:orig_category":"Meubelstoffering",
    "sg:phone":"+31 40 211 2488",
    "sg:postcode":"5645 TH",
    "sg:province":"North Brabant",
    "wof:name":"Capiton, Meubelstoffeerderij",
    "wof:placetype":"venue"
},
  "geometry": {"coordinates":[5.516,51.425571],"type":"Point"}
}