{
  "type": "Feature",
  "properties": {
    "addr:full":"Zuiderzeestrwg W 50 Doornspyk Gelderland 8085 AG",
    "addr:postcode":"8085",
    "addr:street":"W 50 Doornspyk Gelderland",
    "iso:country":"NL",
    "sg:address":"Zuiderzeestrwg W 50",
    "sg:city":"Doornspyk",
    "sg:orig_category":"Banken",
    "sg:phone":"+31 341 271 211",
    "sg:postcode":"8085 AG",
    "sg:province":"Gelderland",
    "sg:website":"http://www.rabobank.nl",
    "wof:name":"Rabobank",
    "wof:placetype":"venue"
},
  "geometry": {"coordinates":[5.81365,52.414104],"type":"Point"}
}