{
  "type": "Feature",
  "properties": {
    "addr:full":"Westersngl 34 Rotterdam Zuid-Holland 3014 GS",
    "addr:housenumber":"34",
    "addr:postcode":"3014 gs",
    "addr:street":"Westersngl",
    "iso:country":"NL",
    "sg:address":"Westersngl 34",
    "sg:city":"Rotterdam",
    "sg:orig_category":"Antiquiteiten",
    "sg:phone":"+31 10 436 9990",
    "sg:postcode":"3014 GS",
    "sg:province":"Zuid-Holland",
    "wof:name":"Majesteit",
    "wof:placetype":"venue"
},
  "geometry": {"coordinates":[4.478455,51.922836],"type":"Point"}
}