{
  "type": "Feature",
  "properties": {
    "addr:full":"4E Industriewg 5 Hattem Gelderland 8051 CK",
    "addr:housenumber":"5",
    "addr:postcode":"8051 ck",
    "addr:street":"4E Industriewg;Gelderland",
    "iso:country":"NL",
    "sg:address":"4E Industriewg 5",
    "sg:city":"Hattem",
    "sg:orig_category":"Drukkerijen",
    "sg:phone":"+31 38 444 2837",
    "sg:postcode":"8051 CK",
    "sg:province":"Gelderland",
    "sg:website":"http://www.padruma.com",
    "wof:name":"Padruma Bv, Drukkerij",
    "wof:placetype":"venue"
},
  "geometry": {"coordinates":[6.07556,52.461899],"type":"Point"}
}