{
  "type": "Feature",
  "properties": {
    "addr:full":"Brugstr 32 Groningen Groningen 9711 HZ",
    "addr:housenumber":"32",
    "addr:postcode":"9711 hz",
    "addr:street":"Brugstr",
    "iso:country":"NL",
    "sg:address":"Brugstr 32",
    "sg:city":"Groningen",
    "sg:orig_category":"Adviesbureaus Bouwkunde",
    "sg:phone":"+31 50 314 7151",
    "sg:postcode":"9711 HZ",
    "sg:province":"Groningen",
    "wof:name":"Prc Bv",
    "wof:placetype":"venue"
},
  "geometry": {"coordinates":[6.559886,53.216446],"type":"Point"}
}