{
  "type": "Feature",
  "properties": {
    "iso:country":"NL",
    "sg:address":"Venenlaan 157",
    "sg:city":"Hoorn Nh",
    "sg:orig_category":"Metaalbekleding And -Behandeling",
    "sg:phone":"+31 229 213 729",
    "sg:postcode":"1623 RD",
    "sg:province":"Noord-Holland",
    "wof:name":"Rws",
    "wof:placetype":"venue"
},
  "geometry": {"coordinates":[5.071573,52.643547],"type":"Point"}
}