{
  "type": "Feature",
  "properties": {
    "addr:full":"Verdiln 27 Rotterdam South Holland 3055 SL",
    "addr:housenumber":"27",
    "addr:postcode":"3055 sl",
    "addr:street":"Verdiln",
    "iso:country":"NL",
    "sg:address":"Verdiln 27",
    "sg:city":"Rotterdam",
    "sg:orig_category":"Psychologen",
    "sg:phone":"+31 10 418 3308",
    "sg:postcode":"3055 SL",
    "sg:province":"South Holland",
    "wof:name":"Calje-Luytjes, Drs E C",
    "wof:placetype":"venue"
},
  "geometry": {"coordinates":[4.50689,51.961319],"type":"Point"}
}