{
  "type": "Feature",
  "properties": {
    "addr:full":"Dorpspln 6-7 Zuidzande Zeeland 4505 AR",
    "addr:housenumber":"6-7",
    "addr:postcode":"4505",
    "addr:street":"Dorpspln",
    "iso:country":"NL",
    "sg:address":"Dorpspln 6-7",
    "sg:city":"Zuidzande",
    "sg:orig_category":"Postkantoren",
    "sg:phone":"+31 117 452 222",
    "sg:postcode":"4505 AR",
    "sg:province":"Zeeland",
    "wof:name":"Postkantoren",
    "wof:placetype":"venue"
},
  "geometry": {"coordinates":[3.450551,51.340969],"type":"Point"}
}