{
  "type": "Feature",
  "properties": {
    "addr:full":"St Joriswg 4 Dordrecht Zuid-Holland 3311 PL",
    "addr:housenumber":"4",
    "addr:postcode":"3311 pl",
    "iso:country":"NL",
    "sg:address":"St Joriswg 4",
    "sg:city":"Dordrecht",
    "sg:orig_category":"Adviesbureaus Financieringen",
    "sg:phone":"+31 78 622 9949",
    "sg:postcode":"3311 PL",
    "sg:province":"Zuid-Holland",
    "wof:name":"Emum",
    "wof:placetype":"venue"
},
  "geometry": {"coordinates":[4.674449,51.814518],"type":"Point"}
}