{
  "type": "Feature",
  "properties": {
    "addr:full":"Makado Centrum 102 Schagen North Holland 1741 JA",
    "addr:housenumber":"102",
    "addr:postcode":"1741 ja",
    "addr:street":"Makado Centrum",
    "iso:country":"NL",
    "sg:address":"Makado Centrum 102",
    "sg:city":"Schagen",
    "sg:orig_category":"Schoenen",
    "sg:phone":"+31 224 296 295",
    "sg:postcode":"1741 JA",
    "sg:province":"North Holland",
    "wof:name":"Eccolet",
    "wof:placetype":"venue"
},
  "geometry": {"coordinates":[4.797948,52.787918],"type":"Point"}
}