{
  "type": "Feature",
  "properties": {
    "addr:full":"Randstad 2124B Almere Flevoland 1314 BM",
    "addr:housenumber":"2124b",
    "addr:postcode":"1314 bm",
    "addr:street":"Flevoland",
    "iso:country":"NL",
    "sg:address":"Randstad 2124B",
    "sg:city":"Almere",
    "sg:orig_category":"Verbandstoffen - Fabrieken En Groothandel",
    "sg:phone":"+31 36 529 5040",
    "sg:postcode":"1314 BM",
    "sg:province":"Flevoland",
    "wof:name":"Noba Verbandmiddelen",
    "wof:placetype":"venue"
},
  "geometry": {"coordinates":[5.223202,52.377983],"type":"Point"}
}