{
  "type": "Feature",
  "properties": {
    "addr:full":"Kempenaar 0142 Lelystad Flevoland 8242 BA",
    "addr:postcode":"0142;8242 ba",
    "addr:street":"Kempenaar;Flevoland",
    "iso:country":"NL",
    "sg:address":"Kempenaar 0142",
    "sg:city":"Lelystad",
    "sg:orig_category":"Bedden En Matrassen",
    "sg:phone":"+31 320 247 173",
    "sg:postcode":"8242 BA",
    "sg:province":"Flevoland",
    "sg:website":"http://www.bobyform.nl",
    "wof:name":"Bodyform",
    "wof:placetype":"venue"
},
  "geometry": {"coordinates":[5.460651,52.518147],"type":"Point"}
}