{
  "type": "Feature",
  "properties": {
    "addr:full":"Zekkenweg 50 Hoek Van Holland Zuid-Holland 3151 ZC",
    "addr:housenumber":"50",
    "addr:postcode":"3151 zc",
    "addr:street":"Zekkenweg",
    "iso:country":"NL",
    "sg:address":"Zekkenweg 50",
    "sg:city":"Hoek Van Holland",
    "sg:orig_category":"Landbouwmachines Gh",
    "sg:phone":"+31 174 387 110",
    "sg:postcode":"3151 ZC",
    "sg:province":"Zuid-Holland",
    "wof:name":"Flamingo Van Der Meer",
    "wof:placetype":"venue"
},
  "geometry": {"coordinates":[4.14413,51.970005],"type":"Point"}
}