{
  "type": "Feature",
  "properties": {
    "addr:full":"Sint Jozeflaan 5 Raamsdonksveer Noord-Brabant 4941 GP",
    "addr:housenumber":"5",
    "addr:postcode":"4941 gp",
    "addr:street":"Sint Jozeflaan",
    "iso:country":"NL",
    "sg:address":"Sint Jozeflaan 5",
    "sg:city":"Raamsdonksveer",
    "sg:orig_category":"Bloemen And Planten",
    "sg:phone":"+31 162 513 109",
    "sg:postcode":"4941 GP",
    "sg:province":"Noord-Brabant",
    "wof:name":"Bloemenweelde",
    "wof:placetype":"venue"
},
  "geometry": {"coordinates":[4.874302,51.693913],"type":"Point"}
}