{
  "type": "Feature",
  "properties": {
    "addr:full":"T Spil 33 Monnickendam Noord-Holland 1141 SG",
    "addr:housenumber":"33",
    "addr:postcode":"1141 sg",
    "addr:street":"T Spil",
    "iso:country":"NL",
    "sg:address":"T Spil 33",
    "sg:city":"Monnickendam",
    "sg:classifiers":[
        {
            "category":"Fast Food",
            "type":"Food & Drink"
        }
    ],
    "sg:phone":"+31 299 653 885",
    "sg:postcode":"1141 SG",
    "sg:province":"Noord-Holland",
    "sg:tags":[
        "afhaal",
        "restaurant"
    ],
    "wof:name":"Snackbar Pim-In",
    "wof:placetype":"venue"
},
  "geometry": {"coordinates":[5.036413,52.450157],"type":"Point"}
}