{
  "type": "Feature",
  "properties": {
    "iso:country":"NL",
    "sg:address":"Ganzert 9",
    "sg:city":"Eck En Wiel",
    "sg:orig_category":"Kunststoffen- Verwerkende Industrie",
    "sg:phone":"+31 344 694 200",
    "sg:postcode":"4024 BS",
    "sg:province":"Basel-Stadt",
    "wof:name":"Profol",
    "wof:placetype":"venue"
},
  "geometry": {"coordinates":[7.58053,47.559662],"type":"Point"}
}