{
  "type": "Feature",
  "properties": {
    "iso:country":"NL",
    "sg:address":"F Bekkerstr 28",
    "sg:city":"Rotterdam",
    "sg:orig_category":"Journalisten Freelance",
    "sg:phone":"+31 10 495 4832",
    "sg:postcode":"3082 TS",
    "sg:province":"Zuid-Holland",
    "wof:name":"Langerveld, Lenny",
    "wof:placetype":"venue"
},
  "geometry": {"coordinates":[4.470301,51.890717],"type":"Point"}
}