{
  "type": "Feature",
  "properties": {
    "addr:full":"Snip 87 Groningen Groningen 9728 XR",
    "addr:housenumber":"87",
    "addr:postcode":"9728 xr",
    "addr:street":"Snip",
    "iso:country":"NL",
    "sg:address":"Snip 87",
    "sg:city":"Groningen",
    "sg:orig_category":"Adviesbureaus Bedrijfsorganisatie",
    "sg:phone":"+31 50 527 2948",
    "sg:postcode":"9728 XR",
    "sg:province":"Groningen",
    "sg:website":"http://www.bcim.nl",
    "wof:name":"Brouwer Cons & Interim Management",
    "wof:placetype":"venue"
},
  "geometry": {"coordinates":[6.542269,53.181389],"type":"Point"}
}