{
  "type": "Feature",
  "properties": {
    "addr:full":"Kagerdreef 90 Sassenheim South Holland 2172 HM",
    "addr:housenumber":"90",
    "addr:postcode":"2172 hm",
    "addr:street":"Kagerdreef",
    "iso:country":"NL",
    "sg:address":"Kagerdreef 90",
    "sg:city":"Sassenheim",
    "sg:classifiers":[
        {
            "category":"Education",
            "subcategory":"Preschool",
            "type":"Public Place"
        }
    ],
    "sg:phone":"+31 252 213 820",
    "sg:postcode":"2172 HM",
    "sg:province":"South Holland",
    "sg:tags":[
        "kleuteronderwijs",
        "basis-"
    ],
    "wof:name":"De Rank Lokatie Kagerdreef",
    "wof:placetype":"venue"
},
  "geometry": {"coordinates":[4.53219,52.22073],"type":"Point"}
}