{
  "type": "Feature",
  "properties": {
    "addr:full":"Faunastr 82 Wormer Noord-Holland 1531 WH",
    "addr:housenumber":"82",
    "addr:postcode":"1531 wh",
    "addr:street":"Faunastr",
    "iso:country":"NL",
    "sg:address":"Faunastr 82",
    "sg:city":"Wormer",
    "sg:orig_category":"Bloemen En Planten",
    "sg:phone":"+31 75 642 4049",
    "sg:postcode":"1531 WH",
    "sg:province":"Noord-Holland",
    "wof:name":"Hortus",
    "wof:placetype":"venue"
},
  "geometry": {"coordinates":[4.812111,52.499096],"type":"Point"}
}