{
  "type": "Feature",
  "properties": {
    "addr:full":"Oude Akerwg 12 Vaals Limburg 6291 DA",
    "addr:housenumber":"12",
    "addr:postcode":"6291 da",
    "addr:street":"Oude Akerwg",
    "iso:country":"NL",
    "sg:address":"Oude Akerwg 12",
    "sg:city":"Vaals",
    "sg:classifiers":[
        {
            "category":"Sports & Exercise",
            "subcategory":"Stables",
            "type":"Entertainment"
        }
    ],
    "sg:phone":"+31 43 306 3687",
    "sg:postcode":"6291 DA",
    "sg:province":"Limburg",
    "sg:tags":[
        "maneges"
    ],
    "wof:name":"Otermans Manege",
    "wof:placetype":"venue"
},
  "geometry": {"coordinates":[5.989916,50.77924],"type":"Point"}
}