{
  "type": "Feature",
  "properties": {
    "addr:full":"Geyaartsborg 2 Maastricht Limburg 6228 AE",
    "addr:housenumber":"2",
    "addr:postcode":"6228 ae",
    "addr:street":"Geyaartsborg",
    "iso:country":"NL",
    "sg:address":"Geyaartsborg 2",
    "sg:city":"Maastricht",
    "sg:orig_category":"Mensendieck - Oefentherapeuten",
    "sg:phone":"+31 43 361 0241",
    "sg:postcode":"6228 AE",
    "sg:province":"Limburg",
    "wof:name":"Overtoom M",
    "wof:placetype":"venue"
},
  "geometry": {"coordinates":[5.726013,50.82896],"type":"Point"}
}