{
  "type": "Feature",
  "properties": {
    "iso:country":"NL",
    "sg:address":"Stationsweg 19",
    "sg:city":"'S Hertogenbosch",
    "sg:orig_category":"Werving And Selectie Van Tijdelijk Personeel And Uitzendkantoren",
    "sg:phone":"+31 73 612 4140",
    "sg:postcode":"5211 TV",
    "sg:province":"North Brabant",
    "wof:name":"Manpower Uitzendorganisatie",
    "wof:placetype":"venue"
},
  "geometry": {"coordinates":[5.2972698212,51.6906204224],"type":"Point"}
}