{
  "type": "Feature",
  "properties": {
    "addr:full":"Johannes Verhulststraat 113 Amsterdam Noord-Holland 1071 MZ",
    "addr:housenumber":"113",
    "addr:postcode":"1071 mz",
    "addr:street":"Johannes Verhulststraat",
    "iso:country":"NL",
    "sg:address":"Johannes Verhulststraat 113",
    "sg:city":"Amsterdam",
    "sg:orig_category":"Film-, Tv- And Videoproductie",
    "sg:phone":"+31 20 664 4201",
    "sg:postcode":"1071 MZ",
    "sg:province":"Noord-Holland",
    "wof:name":"Eerhart & Van Der Linden Bv",
    "wof:placetype":"venue"
},
  "geometry": {"coordinates":[4.871138,52.354069],"type":"Point"}
}