{
  "type": "Feature",
  "properties": {
    "iso:country":"NL",
    "sg:address":"Raadhuisplein 1",
    "sg:city":"Losser",
    "sg:orig_category":"Overheidsdiensten",
    "sg:phone":"+31 53 537 7444",
    "sg:postcode":"7581 AG",
    "sg:province":"Overijssel",
    "wof:name":"Gemeente Losser",
    "wof:placetype":"venue"
},
  "geometry": {"coordinates":[7.0065097809,52.2627639771],"type":"Point"}
}