{
  "type": "Feature",
  "properties": {
    "addr:full":"Siersteenlaan 418 Groningen Groningen 9743 ES",
    "addr:housenumber":"418",
    "addr:postcode":"9743 es",
    "addr:street":"Siersteenlaan",
    "iso:country":"NL",
    "sg:address":"Siersteenlaan 418",
    "sg:city":"Groningen",
    "sg:orig_category":"Juridische Dienstverlening",
    "sg:phone":"+31 50 577 5104",
    "sg:postcode":"9743 ES",
    "sg:province":"Groningen",
    "wof:name":"Buro Sociaal Raadslieden",
    "wof:placetype":"venue"
},
  "geometry": {"coordinates":[6.529773,53.225689],"type":"Point"}
}