{
  "type": "Feature",
  "properties": {
    "addr:full":"Kagerdreef 212 Sassenheim Zuid-Holland 2172 HS",
    "addr:housenumber":"212",
    "addr:postcode":"2172 hs",
    "addr:street":"Kagerdreef",
    "iso:country":"NL",
    "sg:address":"Kagerdreef 212",
    "sg:city":"Sassenheim",
    "sg:orig_category":"Schoonheidsinstituten",
    "sg:phone":"+31 252 217 238",
    "sg:postcode":"2172 HS",
    "sg:province":"Zuid-Holland",
    "wof:name":"She",
    "wof:placetype":"venue"
},
  "geometry": {"coordinates":[4.534567,52.222691],"type":"Point"}
}