{
  "type": "Feature",
  "properties": {
    "addr:full":"Spiegelstraat 10 Bussum Noord-Holland 1405 HW",
    "addr:housenumber":"10",
    "addr:postcode":"1405 hw",
    "addr:street":"Spiegelstraat",
    "iso:country":"NL",
    "sg:address":"Spiegelstraat 10",
    "sg:city":"Bussum",
    "sg:orig_category":"Verlichting And Huishoudartikelen",
    "sg:phone":"+31 35 693 4922",
    "sg:postcode":"1405 HW",
    "sg:province":"Noord-Holland",
    "wof:name":"Kooklust",
    "wof:placetype":"venue"
},
  "geometry": {"coordinates":[5.159226,52.273586],"type":"Point"}
}