{
  "type": "Feature",
  "properties": {
    "addr:full":"Kleverparkweg 10 Haarlem Noord-Holland 2023 CE",
    "addr:housenumber":"10",
    "addr:postcode":"2023 ce",
    "addr:street":"Kleverparkweg",
    "iso:country":"NL",
    "sg:address":"Kleverparkweg 10",
    "sg:city":"Haarlem",
    "sg:classifiers":[
        {
            "category":"Bakery",
            "type":"Food & Drink"
        }
    ],
    "sg:phone":"+31 23 527 1771",
    "sg:postcode":"2023 CE",
    "sg:province":"Noord-Holland",
    "sg:tags":[
        "brood",
        "banket"
    ],
    "wof:name":"Van Vessem Bakker Bv",
    "wof:placetype":"venue"
},
  "geometry": {"coordinates":[4.631279,52.391064],"type":"Point"}
}