{
  "type": "Feature",
  "properties": {
    "addr:full":"Boswachter 14 Leusden Utrecht 3834 CT",
    "addr:housenumber":"14",
    "addr:postcode":"3834 ct",
    "addr:street":"Boswachter",
    "iso:country":"NL",
    "sg:address":"Boswachter 14",
    "sg:city":"Leusden",
    "sg:orig_category":"Adviesbureaus Economie",
    "sg:phone":"+31 33 495 3311",
    "sg:postcode":"3834 CT",
    "sg:province":"Utrecht",
    "wof:name":"Revisie",
    "wof:placetype":"venue"
},
  "geometry": {"coordinates":[5.444705,52.126987],"type":"Point"}
}