{
  "type": "Feature",
  "properties": {
    "addr:full":"L Putstr 11-13 S Hertogenbosch North Brabant 5211 KN",
    "addr:housenumber":"11-13",
    "addr:postcode":"5211 kn",
    "addr:street":"S Hertogenbosch",
    "iso:country":"NL",
    "sg:address":"L Putstr 11-13",
    "sg:city":"S Hertogenbosch",
    "sg:orig_category":"Kappers",
    "sg:phone":"+31 73 689 0044",
    "sg:postcode":"5211 KN",
    "sg:province":"North Brabant",
    "wof:name":"Le Salon",
    "wof:placetype":"venue"
},
  "geometry": {"coordinates":[5.305621,51.686966],"type":"Point"}
}