{
  "type": "Feature",
  "properties": {
    "addr:full":"Weteringschans 106 Amsterdam North Holland 1017 XS",
    "addr:housenumber":"106",
    "addr:postcode":"1017 xs",
    "addr:street":"Weteringschans",
    "iso:country":"NL",
    "sg:address":"Weteringschans 106",
    "sg:city":"Amsterdam",
    "sg:orig_category":"Accountants - Administratie- Consulenten En -Kantoren",
    "sg:phone":"+31 20 627 2727",
    "sg:postcode":"1017 XS",
    "sg:province":"North Holland",
    "wof:name":"Nmo",
    "wof:placetype":"venue"
},
  "geometry": {"coordinates":[4.894827,52.359272],"type":"Point"}
}