{
  "type": "Feature",
  "properties": {
    "addr:full":"Tintelersteeg 31 Putten Gelderland 3882 MK",
    "addr:housenumber":"31",
    "addr:postcode":"3882",
    "addr:street":"Tintelersteeg;Gelderland",
    "iso:country":"NL",
    "sg:address":"Tintelersteeg 31",
    "sg:city":"Putten",
    "sg:orig_category":"Landbouwtractoren Fab",
    "sg:phone":"+31 33 245 2795",
    "sg:postcode":"3882 MK",
    "sg:province":"Gelderland",
    "wof:name":"G.J. Dekker Agrarische Handelsonderneming",
    "wof:placetype":"venue"
},
  "geometry": {"coordinates":[5.525392,52.22937],"type":"Point"}
}