{
  "type": "Feature",
  "properties": {
    "addr:full":"Weper 4 Oosterwolde Fr Provincie Friesland 8431 RH",
    "addr:housenumber":"4",
    "addr:postcode":"8431 rh",
    "addr:street":"Weper;Friesland",
    "iso:country":"NL",
    "sg:address":"Weper 4",
    "sg:city":"Oosterwolde Fr",
    "sg:orig_category":"Bloemen En Planten - Groothandel",
    "sg:phone":"+31 516 514 939",
    "sg:postcode":"8431 RH",
    "sg:province":"Provincie Friesland",
    "wof:name":"Groene Erf, Het",
    "wof:placetype":"venue"
},
  "geometry": {"coordinates":[6.306254,53.008228],"type":"Point"}
}