{
  "type": "Feature",
  "properties": {
    "addr:full":"Hekellaan 32 'S Hertogenbosch Noord-Brabant 5211 LX",
    "addr:housenumber":"32",
    "addr:postcode":"5211 lx",
    "addr:street":"Hekellaan;' S",
    "iso:country":"NL",
    "sg:address":"Hekellaan 32",
    "sg:city":"'S Hertogenbosch",
    "sg:orig_category":"Artsen And Specialisten",
    "sg:phone":"+31 73 613 5550",
    "sg:postcode":"5211 LX",
    "sg:province":"Noord-Brabant",
    "wof:name":"I. Schretlen",
    "wof:placetype":"venue"
},
  "geometry": {"coordinates":[5.313696,51.685616],"type":"Point"}
}