{
  "type": "Feature",
  "properties": {
    "addr:full":"Sluisdk 5 Gouda South Holland 2809 NA",
    "addr:housenumber":"5",
    "addr:postcode":"2809 na",
    "addr:street":"Sluisdk",
    "iso:country":"NL",
    "sg:address":"Sluisdk 5",
    "sg:city":"Gouda",
    "sg:orig_category":"Onderhoudswerken",
    "sg:phone":"+31 182 521 953",
    "sg:postcode":"2809 NA",
    "sg:province":"South Holland",
    "wof:name":"Stolk, R",
    "wof:placetype":"venue"
},
  "geometry": {"coordinates":[4.690135,51.998199],"type":"Point"}
}