{
  "type": "Feature",
  "properties": {
    "addr:full":"Laan Van De Eekharst 281 Emmen Drenthe 7823 AG",
    "addr:housenumber":"281",
    "addr:postcode":"7823",
    "addr:street":"Laan Van De Eekharst",
    "iso:country":"NL",
    "sg:address":"Laan Van De Eekharst 281",
    "sg:city":"Emmen",
    "sg:orig_category":"Alternatieve Geneeskunde",
    "sg:phone":"+31 591 629 419",
    "sg:postcode":"7823 AG",
    "sg:province":"Drenthe",
    "wof:name":"Salon Ylang-Ylang",
    "wof:placetype":"venue"
},
  "geometry": {"coordinates":[6.932873,52.78867],"type":"Point"}
}