{
  "type": "Feature",
  "properties": {
    "iso:country":"NL",
    "sg:address":"A Tasmanstr 21B",
    "sg:city":"Groningen",
    "sg:orig_category":"Artiesten/Gezelschappen",
    "sg:phone":"+31 50 314 1981",
    "sg:postcode":"9726 EG",
    "sg:province":"Groningen",
    "wof:name":"Kapstok",
    "wof:placetype":"venue"
},
  "geometry": {"coordinates":[6.553924,53.211872],"type":"Point"}
}