{
  "type": "Feature",
  "properties": {
    "iso:country":"NL",
    "sg:address":"Kometenlaan 23",
    "sg:city":"Eindhoven",
    "sg:classifiers":[
        {
            "category":"Shopping",
            "subcategory":"Gifts & Souvenirs",
            "type":"Retail Goods"
        }
    ],
    "sg:phone":"+31 40 242 8788",
    "sg:postcode":"5632 DR",
    "sg:province":"Noord-Brabant",
    "sg:tags":[
        "geschenken"
    ],
    "wof:name":"M G Valks",
    "wof:placetype":"venue"
},
  "geometry": {"coordinates":[5.495024,51.473511],"type":"Point"}
}