{
  "type": "Feature",
  "properties": {
    "addr:full":"Wijchenseweg 118 Nijmegen Gelderland 6538 SX",
    "addr:housenumber":"118",
    "addr:postcode":"6538 sx",
    "addr:street":"Wijchenseweg;Gelderland",
    "iso:country":"NL",
    "sg:address":"Wijchenseweg 118",
    "sg:city":"Nijmegen",
    "sg:orig_category":"Werving And Selectie Van Tijdelijk Personeel And Uitzendkantoren",
    "sg:phone":"+31 800 2233539",
    "sg:postcode":"6538 SX",
    "sg:province":"Gelderland",
    "wof:name":"Cadflex Bv",
    "wof:placetype":"venue"
},
  "geometry": {"coordinates":[5.7947092056,51.8250617981],"type":"Point"}
}