{
  "type": "Feature",
  "properties": {
    "addr:full":"Noard 35 Workum Friesland 8711 AB",
    "addr:housenumber":"35",
    "addr:postcode":"8711 ab",
    "addr:street":"Noard",
    "iso:country":"NL",
    "sg:address":"Noard 35",
    "sg:city":"Workum",
    "sg:orig_category":"Verpleegartikelen",
    "sg:phone":"+31 515 542 804",
    "sg:postcode":"8711 AB",
    "sg:province":"Friesland",
    "wof:name":"Meditheek",
    "wof:placetype":"venue"
},
  "geometry": {"coordinates":[5.444016,52.980591],"type":"Point"}
}