{
  "type": "Feature",
  "properties": {
    "iso:country":"NL",
    "sg:address":"Wooldebrink 8",
    "sg:city":"Enschede",
    "sg:orig_category":"Schoonheidssalons",
    "sg:phone":"+31 53 476 6183",
    "sg:postcode":"7544 MT",
    "sg:province":"NL.08",
    "wof:name":"Audry Schoonheidssalon",
    "wof:placetype":"venue"
},
  "geometry": {"coordinates":[6.886116,52.185612],"type":"Point"}
}