{
  "type": "Feature",
  "properties": {
    "addr:full":"Hobbemastr 33 Maassluis South Holland 3141 GH",
    "addr:housenumber":"33",
    "addr:postcode":"3141 gh",
    "addr:street":"Hobbemastr",
    "iso:country":"NL",
    "sg:address":"Hobbemastr 33",
    "sg:city":"Maassluis",
    "sg:orig_category":"Koel- En Vriestransporten",
    "sg:phone":"+31 10 590 3933",
    "sg:postcode":"3141 GH",
    "sg:province":"South Holland",
    "wof:name":"Vrolijk, J",
    "wof:placetype":"venue"
},
  "geometry": {"coordinates":[4.26291,51.918079],"type":"Point"}
}