{
  "type": "Feature",
  "properties": {
    "addr:full":"Oude Peelstraat 79 Helenaveen Noord-Brabant 5759 PB",
    "addr:housenumber":"79",
    "addr:postcode":"5759 pb",
    "addr:street":"Oude Peelstraat",
    "iso:country":"NL",
    "sg:address":"Oude Peelstraat 79",
    "sg:city":"Helenaveen",
    "sg:classifiers":[
        {
            "category":"Food & Beverages",
            "subcategory":"Fruits & Vegetables",
            "type":"Retail Goods"
        }
    ],
    "sg:phone":"+31 493 539 294",
    "sg:postcode":"5759 PB",
    "sg:province":"Noord-Brabant",
    "sg:tags":[
        "groenten"
    ],
    "wof:name":"T Fruithuis",
    "wof:placetype":"venue"
},
  "geometry": {"coordinates":[5.901471,51.390743],"type":"Point"}
}