{
  "type": "Feature",
  "properties": {
    "addr:full":"Slot Assumburgpad 66 Schiedam Zuid-Holland 3123 RR",
    "addr:housenumber":"66",
    "addr:postcode":"3123 rr",
    "addr:street":"Slot Assumburgpad",
    "iso:country":"NL",
    "sg:address":"Slot Assumburgpad 66",
    "sg:city":"Schiedam",
    "sg:orig_category":"Verzekeringen",
    "sg:phone":"+31 10 449 1044",
    "sg:postcode":"3123 RR",
    "sg:province":"Zuid-Holland",
    "wof:name":"Van Doorn",
    "wof:placetype":"venue"
},
  "geometry": {"coordinates":[4.365323,51.945389],"type":"Point"}
}