{
  "type": "Feature",
  "properties": {
    "addr:full":"Lange Tiendeweg 101 Gouda Zuid-Holland 2801 KG",
    "addr:housenumber":"101",
    "addr:postcode":"2801 kg",
    "addr:street":"Lange Tiendeweg",
    "iso:country":"NL",
    "sg:address":"Lange Tiendeweg 101",
    "sg:city":"Gouda",
    "sg:orig_category":"Paramedische Behandelingen",
    "sg:phone":"+31 182 582 067",
    "sg:postcode":"2801 KG",
    "sg:province":"Zuid-Holland",
    "wof:name":"Praktijk Van Logopedie En Remediering",
    "wof:placetype":"venue"
},
  "geometry": {"coordinates":[4.714459,52.01228],"type":"Point"}
}