{
  "type": "Feature",
  "properties": {
    "addr:full":"De Punter 71 Hoogeveen Provincie Drenthe 7908 DV",
    "addr:housenumber":"71",
    "addr:postcode":"7908",
    "addr:street":"De Punter;Provincie;Dv",
    "iso:country":"NL",
    "sg:address":"De Punter 71",
    "sg:city":"Hoogeveen",
    "sg:orig_category":"Begraafplaatsen",
    "sg:phone":"+31 528 260 676",
    "sg:postcode":"7908 DV",
    "sg:province":"Provincie Drenthe",
    "wof:name":"Smitse, De",
    "wof:placetype":"venue"
},
  "geometry": {"coordinates":[6.452601,52.713188],"type":"Point"}
}