{
  "type": "Feature",
  "properties": {
    "iso:country":"NL",
    "sg:address":"G Flinckstr 46",
    "sg:city":"Amersfoort",
    "sg:orig_category":"Bestratingen",
    "sg:phone":"+31 33 479 3030",
    "sg:postcode":"3817 RZ",
    "sg:province":"Utrecht",
    "wof:name":"Gedezo",
    "wof:placetype":"venue"
},
  "geometry": {"coordinates":[5.388112,52.145046],"type":"Point"}
}