{
  "type": "Feature",
  "properties": {
    "addr:full":"Denneweg 144 'S Gravenhage Zuid-Holland 2514 CM",
    "addr:housenumber":"144 '",
    "addr:postcode":"2514 cm",
    "addr:street":"Denneweg",
    "iso:country":"NL",
    "sg:address":"Denneweg 144",
    "sg:city":"'S Gravenhage",
    "sg:orig_category":"Sportterreinen And Installaties Behalve Sportcentra",
    "sg:phone":"+31 70 365 7096",
    "sg:postcode":"2514 CM",
    "sg:province":"Zuid-Holland",
    "wof:name":"Zwemschool De Tuimelaar",
    "wof:placetype":"venue"
},
  "geometry": {"coordinates":[4.311635,52.085869],"type":"Point"}
}