{
  "type": "Feature",
  "properties": {
    "addr:full":"De Wertjes 8 Esch Noord-Brabant 5296 NC",
    "addr:housenumber":"8",
    "addr:postcode":"5296 nc",
    "addr:street":"De Wertjes",
    "iso:country":"NL",
    "sg:address":"De Wertjes 8",
    "sg:city":"Esch",
    "sg:orig_category":"Bloemen En Planten - Groothandel",
    "sg:phone":"+31 411 601 323",
    "sg:postcode":"5296 NC",
    "sg:province":"Noord-Brabant",
    "wof:name":"Serra, La",
    "wof:placetype":"venue"
},
  "geometry": {"coordinates":[5.289097,51.607189],"type":"Point"}
}