{
  "type": "Feature",
  "properties": {
    "addr:full":"Pr Hendrikkd 14 Woerden Utrecht 3441 XD",
    "addr:housenumber":"14",
    "addr:postcode":"3441 xd",
    "addr:street":"Woerden",
    "iso:country":"NL",
    "sg:address":"Pr Hendrikkd 14",
    "sg:city":"Woerden",
    "sg:orig_category":"Verenigingsgebouwen",
    "sg:phone":"+31 348 422 233",
    "sg:postcode":"3441 XD",
    "sg:province":"Utrecht",
    "wof:name":"Kade, De",
    "wof:placetype":"venue"
},
  "geometry": {"coordinates":[4.887371,52.085117],"type":"Point"}
}