{
  "type": "Feature",
  "properties": {
    "addr:full":"Kwikstaart 36 Bunschoten Spakenburg Utrecht 3752 MT",
    "addr:housenumber":"36",
    "addr:postcode":"3752 mt",
    "addr:street":"Kwikstaart",
    "iso:country":"NL",
    "sg:address":"Kwikstaart 36",
    "sg:city":"Bunschoten Spakenburg",
    "sg:orig_category":"Boekhouders",
    "sg:phone":"+31 33 298 3018",
    "sg:postcode":"3752 MT",
    "sg:province":"Utrecht",
    "wof:name":"Administratiekantoor De Jong",
    "wof:placetype":"venue"
},
  "geometry": {"coordinates":[5.359598,52.235989],"type":"Point"}
}