{
  "type": "Feature",
  "properties": {
    "addr:full":"Scheepjeshof 110 Veenendaal Utrecht 3901 CX",
    "addr:housenumber":"110",
    "addr:postcode":"3901 cx",
    "addr:street":"Scheepjeshof",
    "iso:country":"NL",
    "sg:address":"Scheepjeshof 110",
    "sg:city":"Veenendaal",
    "sg:orig_category":"Werving And Selectie Van Tijdelijk Personeel And Uitzendkantoren",
    "sg:phone":"+31 318 561 121",
    "sg:postcode":"3901 CX",
    "sg:province":"Utrecht",
    "wof:name":"Werkwijzer Uitzendbureau",
    "wof:placetype":"venue"
},
  "geometry": {"coordinates":[5.5549688339,52.0292778015],"type":"Point"}
}