{
  "type": "Feature",
  "properties": {
    "addr:full":"Schimmelpenninckstraat 61 Heerlen Limburg 6415 GH",
    "addr:housenumber":"61",
    "addr:postcode":"6415 gh",
    "addr:street":"Schimmelpenninckstraat",
    "iso:country":"NL",
    "sg:address":"Schimmelpenninckstraat 61",
    "sg:city":"Heerlen",
    "sg:orig_category":"Boekhouders",
    "sg:phone":"+31 45 561 0154",
    "sg:postcode":"6415 GH",
    "sg:province":"Limburg",
    "wof:name":"Mutter Administraties",
    "wof:placetype":"venue"
},
  "geometry": {"coordinates":[5.987964,50.893326],"type":"Point"}
}