{
  "type": "Feature",
  "properties": {
    "addr:full":"Kallenbroekerweg 113 Barneveld Gelderland 3771 DC",
    "addr:housenumber":"113",
    "addr:postcode":"3771",
    "addr:street":"Kallenbroekerweg;Gelderland",
    "iso:country":"NL",
    "sg:address":"Kallenbroekerweg 113",
    "sg:city":"Barneveld",
    "sg:orig_category":"Loodgieterswerk, Verwarming And Sanitaire Installaties",
    "sg:phone":"+31 342 417 817",
    "sg:postcode":"3771 DC",
    "sg:province":"Gelderland",
    "wof:name":"J.H.C. Brandsen",
    "wof:placetype":"venue"
},
  "geometry": {"coordinates":[5.568881,52.14106],"type":"Point"}
}