{
  "type": "Feature",
  "properties": {
    "addr:full":"Walramstr 18 Born Limburg 6121 HE",
    "addr:housenumber":"18",
    "addr:postcode":"6121 he",
    "addr:street":"Walramstr",
    "iso:country":"NL",
    "sg:address":"Walramstr 18",
    "sg:city":"Born",
    "sg:orig_category":"Verbouwingen",
    "sg:phone":"+31 46 486 0155",
    "sg:postcode":"6121 HE",
    "sg:province":"Limburg",
    "wof:name":"Vencken, Robert",
    "wof:placetype":"venue"
},
  "geometry": {"coordinates":[8.10303,50.159779],"type":"Point"}
}