{
  "type": "Feature",
  "properties": {
    "addr:full":"Katwijkerlaan 91 Pijnacker Zuid-Holland 2641 PD",
    "addr:housenumber":"91",
    "addr:postcode":"2641 pd",
    "addr:street":"Katwijkerlaan",
    "iso:country":"NL",
    "sg:address":"Katwijkerlaan 91",
    "sg:city":"Pijnacker",
    "sg:orig_category":"Goederenvervoer Over De Weg",
    "sg:phone":"+31 15 369 4270",
    "sg:postcode":"2641 PD",
    "sg:province":"Zuid-Holland",
    "wof:name":"Kouwenhoven",
    "wof:placetype":"venue"
},
  "geometry": {"coordinates":[4.462071,52.037132],"type":"Point"}
}