{
  "type": "Feature",
  "properties": {
    "addr:full":"Utr W 60 Heelsum Gelderland 6866 CM",
    "addr:postcode":"6866 cm",
    "addr:street":"W 60;Gelderland",
    "iso:country":"NL",
    "sg:address":"Utr W 60",
    "sg:city":"Heelsum",
    "sg:orig_category":"Bejaarden - Verzorgingstehuizen",
    "sg:phone":"+31 317 350 021",
    "sg:postcode":"6866 CM",
    "sg:province":"Gelderland",
    "wof:name":"Renkum Lok Beekdal, Zorgcentr",
    "wof:placetype":"venue"
},
  "geometry": {"coordinates":[5.75346,51.983845],"type":"Point"}
}