{
  "type": "Feature",
  "properties": {
    "addr:full":"Zandvaart 57 Breezand North Holland 1764 NL",
    "addr:housenumber":"57",
    "addr:postcode":"1764 nl",
    "addr:street":"Zandvaart",
    "iso:country":"NL",
    "sg:address":"Zandvaart 57",
    "sg:city":"Breezand",
    "sg:orig_category":"Peuterspeelzalen",
    "sg:phone":"+31 223 521 535",
    "sg:postcode":"1764 NL",
    "sg:province":"North Holland",
    "wof:name":"Kwetternest, 'T",
    "wof:placetype":"venue"
},
  "geometry": {"coordinates":[4.804457,52.889244],"type":"Point"}
}