{
  "type": "Feature",
  "properties": {
    "addr:full":"Ostadestr 14 Haarlem North Holland 2023 XA",
    "addr:housenumber":"14",
    "addr:postcode":"2023 xa",
    "addr:street":"Ostadestr",
    "iso:country":"NL",
    "sg:address":"Ostadestr 14",
    "sg:city":"Haarlem",
    "sg:orig_category":"Boekhandels",
    "sg:phone":"+31 23 525 0452",
    "sg:postcode":"2023 XA",
    "sg:province":"North Holland",
    "wof:name":"Ruyter & Zn, J De",
    "wof:placetype":"venue"
},
  "geometry": {"coordinates":[4.631153,52.390652],"type":"Point"}
}