{
  "type": "Feature",
  "properties": {
    "addr:full":"De Zate 20 Dronten NL. 8251 HD",
    "addr:housenumber":"20",
    "addr:postcode":"8251 hd",
    "addr:street":"De Zate;Nl.",
    "iso:country":"NL",
    "sg:address":"De Zate 20",
    "sg:city":"Dronten",
    "sg:classifiers":[
        {
            "category":"Professional",
            "subcategory":"Accounting & Tax Preparation",
            "type":"Services"
        }
    ],
    "sg:phone":"+31 321 318 633",
    "sg:postcode":"8251 HD",
    "sg:province":"NL.",
    "sg:tags":[
        "accountant"
    ],
    "wof:name":"Kamps Accountants",
    "wof:placetype":"venue"
},
  "geometry": {"coordinates":[5.72243,52.527779],"type":"Point"}
}