{
  "type": "Feature",
  "properties": {
    "addr:full":"Voorzand 16 Ridderkerk South Holland 2984 BH",
    "addr:housenumber":"16",
    "addr:postcode":"2984 bh",
    "addr:street":"Voorzand",
    "iso:country":"NL",
    "sg:address":"Voorzand 16",
    "sg:city":"Ridderkerk",
    "sg:orig_category":"Autoruiten",
    "sg:phone":"+31 180 490 300",
    "sg:postcode":"2984 BH",
    "sg:province":"South Holland",
    "wof:name":"Autotaalglas",
    "wof:placetype":"venue"
},
  "geometry": {"coordinates":[4.606955,51.86961],"type":"Point"}
}