{
  "type": "Feature",
  "properties": {
    "addr:full":"Hartkampwg 10 Raalte Overijssel 8101 ZW",
    "addr:housenumber":"10",
    "addr:postcode":"8101 zw",
    "addr:street":"Hartkampwg",
    "iso:country":"NL",
    "sg:address":"Hartkampwg 10",
    "sg:city":"Raalte",
    "sg:orig_category":"Omroep",
    "sg:phone":"+31 572 356 122",
    "sg:postcode":"8101 ZW",
    "sg:province":"Overijssel",
    "wof:name":"Ros Ziekenomroep",
    "wof:placetype":"venue"
},
  "geometry": {"coordinates":[6.270147,52.379345],"type":"Point"}
}