{
  "type": "Feature",
  "properties": {
    "addr:full":"Langestr 195 S Gravenzande Zuid-Holland 2691 BE",
    "addr:housenumber":"195;gravenzande",
    "addr:postcode":"2691",
    "addr:street":"S",
    "iso:country":"NL",
    "sg:address":"Langestr 195",
    "sg:city":"S Gravenzande",
    "sg:orig_category":"Juweliers",
    "sg:phone":"+31 174 440 233",
    "sg:postcode":"2691 BE",
    "sg:province":"Zuid-Holland",
    "sg:website":"http://www.vellekoop.com",
    "wof:name":"Vellekoop",
    "wof:placetype":"venue"
},
  "geometry": {"coordinates":[4.161673,52.001808],"type":"Point"}
}