{
  "type": "Feature",
  "properties": {
    "addr:full":"Prinsenstraat 35 Dalfsen Overijssel 7721 AH",
    "addr:housenumber":"35",
    "addr:postcode":"7721 ah",
    "addr:street":"Prinsenstraat",
    "iso:country":"NL",
    "sg:address":"Prinsenstraat 35",
    "sg:city":"Dalfsen",
    "sg:classifiers":[
        {
            "category":"Shopping",
            "subcategory":"Gifts & Souvenirs",
            "type":"Retail Goods"
        }
    ],
    "sg:phone":"+31 529 432 646",
    "sg:postcode":"7721 AH",
    "sg:province":"Overijssel",
    "sg:tags":[
        "geschenken"
    ],
    "wof:name":"In De Grutte Moole Cv",
    "wof:placetype":"venue"
},
  "geometry": {"coordinates":[6.260224,52.504452],"type":"Point"}
}