{
  "type": "Feature",
  "properties": {
    "iso:country":"NL",
    "sg:address":"Bachstr 15",
    "sg:city":"Amsterdam",
    "sg:orig_category":"Vertalers",
    "sg:phone":"+31 20 470 3890",
    "sg:postcode":"1077 GE",
    "sg:province":"Noord-Holland",
    "wof:name":"Asa",
    "wof:placetype":"venue"
},
  "geometry": {"coordinates":[4.879837,52.348701],"type":"Point"}
}