{
  "type": "Feature",
  "properties": {
    "addr:full":"Cuykschestg 2 Escharen Noord-Brabant 5364 PH",
    "addr:housenumber":"2",
    "addr:postcode":"5364",
    "addr:street":"Cuykschestg",
    "iso:country":"NL",
    "sg:address":"Cuykschestg 2",
    "sg:city":"Escharen",
    "sg:orig_category":"Metaalbewerking",
    "sg:phone":"+31 486 421 242",
    "sg:postcode":"5364 PH",
    "sg:province":"Noord-Brabant",
    "wof:name":"Turn-Parts",
    "wof:placetype":"venue"
},
  "geometry": {"coordinates":[5.753941,51.743984],"type":"Point"}
}