{
  "type": "Feature",
  "properties": {
    "addr:full":"Gringelstraat 9 Heerlen Limburg 6412 AK",
    "addr:housenumber":"9",
    "addr:postcode":"6412 ak",
    "addr:street":"Gringelstraat",
    "iso:country":"NL",
    "sg:address":"Gringelstraat 9",
    "sg:city":"Heerlen",
    "sg:orig_category":"Meubelzaken, Woning- And Keukeninrichting",
    "sg:phone":"+31 45 572 5327",
    "sg:postcode":"6412 AK",
    "sg:province":"Limburg",
    "sg:website":"http://www.kesquetoe.nl",
    "wof:name":"Kesquetoe",
    "wof:placetype":"venue"
},
  "geometry": {"coordinates":[5.980084,50.8909],"type":"Point"}
}