{
  "type": "Feature",
  "properties": {
    "addr:full":"Nassaustraat 176 Ridderkerk Zuid-Holland 2983 RL",
    "addr:housenumber":"176",
    "addr:postcode":"2983 rl",
    "addr:street":"Nassaustraat",
    "iso:country":"NL",
    "sg:address":"Nassaustraat 176",
    "sg:city":"Ridderkerk",
    "sg:orig_category":"Meubelzaken, Woning- And Keukeninrichting",
    "sg:phone":"+31 180 487 012",
    "sg:postcode":"2983 RL",
    "sg:province":"Zuid-Holland",
    "wof:name":"F. Niemeijer",
    "wof:placetype":"venue"
},
  "geometry": {"coordinates":[4.6073231697,51.8806724548],"type":"Point"}
}