{
  "type": "Feature",
  "properties": {
    "addr:full":"Kromme Hook 5 Belfeld Limburg 5951 EL",
    "addr:housenumber":"5",
    "addr:postcode":"5951 el",
    "addr:street":"Kromme Hook",
    "iso:country":"NL",
    "sg:address":"Kromme Hook 5",
    "sg:city":"Belfeld",
    "sg:orig_category":"Boekhouders",
    "sg:phone":"+31 77 475 2247",
    "sg:postcode":"5951 EL",
    "sg:province":"Limburg",
    "wof:name":"Administratiekantoor H.W.T.M. Janzen",
    "wof:placetype":"venue"
},
  "geometry": {"coordinates":[6.122479,51.311386],"type":"Point"}
}