{
  "type": "Feature",
  "properties": {
    "addr:full":"Stationsstr 17 Appingedam Groningen 9901 BL",
    "addr:housenumber":"17",
    "addr:postcode":"9901 bl",
    "addr:street":"Stationsstr",
    "iso:country":"NL",
    "sg:address":"Stationsstr 17",
    "sg:city":"Appingedam",
    "sg:orig_category":"Wolartikelen En Breiwol",
    "sg:phone":"+31 596 680 315",
    "sg:postcode":"9901 BL",
    "sg:province":"Groningen",
    "wof:name":"Lawi 2000",
    "wof:placetype":"venue"
},
  "geometry": {"coordinates":[6.8591809273,53.3224525452],"type":"Point"}
}