{
  "type": "Feature",
  "properties": {
    "addr:full":"Stauntonstr 16 Utrecht Utrecht 3554 EX",
    "addr:housenumber":"16",
    "addr:postcode":"3554 ex",
    "addr:street":"Stauntonstr",
    "iso:country":"NL",
    "sg:address":"Stauntonstr 16",
    "sg:city":"Utrecht",
    "sg:orig_category":"Webdesign Bureaus",
    "sg:phone":"+31 6 23030345",
    "sg:postcode":"3554 EX",
    "sg:province":"Utrecht",
    "sg:website":"http://www.ea-design.nl",
    "wof:name":"Ea-Design",
    "wof:placetype":"venue"
},
  "geometry": {"coordinates":[5.0922517776,52.1123962402],"type":"Point"}
}