{
  "type": "Feature",
  "properties": {
    "addr:full":"Brasemborch 4 Rosmalen Noord-Brabant 5247 VG",
    "addr:housenumber":"4",
    "addr:postcode":"5247 vg",
    "addr:street":"Brasemborch",
    "iso:country":"NL",
    "sg:address":"Brasemborch 4",
    "sg:city":"Rosmalen",
    "sg:orig_category":"Drukkerijen",
    "sg:phone":"+31 73 521 8155",
    "sg:postcode":"5247 VG",
    "sg:province":"Noord-Brabant",
    "wof:name":"Eck, Drukwerk Ontwerp Studio Van",
    "wof:placetype":"venue"
},
  "geometry": {"coordinates":[5.369998,51.725544],"type":"Point"}
}