{
  "type": "Feature",
  "properties": {
    "addr:full":"Planetenhof 31 Maastricht Limburg 6215 TT",
    "addr:housenumber":"31",
    "addr:postcode":"6215 tt",
    "addr:street":"Planetenhof",
    "iso:country":"NL",
    "sg:address":"Planetenhof 31",
    "sg:city":"Maastricht",
    "sg:orig_category":"Loodgieterswerk, Verwarming And Sanitaire Installaties",
    "sg:phone":"+31 43 343 6879",
    "sg:postcode":"6215 TT",
    "sg:province":"Limburg",
    "wof:name":"Kbc",
    "wof:placetype":"venue"
},
  "geometry": {"coordinates":[5.660987,50.842648],"type":"Point"}
}