{
  "type": "Feature",
  "properties": {
    "addr:full":"Dracht 60 Heerenveen Provincie Friesland 8442 BS",
    "addr:housenumber":"60",
    "addr:postcode":"8442 bs",
    "addr:street":"Dracht;Provincie Friesland",
    "iso:country":"NL",
    "sg:address":"Dracht 60",
    "sg:city":"Heerenveen",
    "sg:orig_category":"Boeken En Tijdschriften",
    "sg:phone":"+31 513 622 533",
    "sg:postcode":"8442 BS",
    "sg:province":"Provincie Friesland",
    "sg:website":"http://www.binnertoverdiep.nl",
    "wof:name":"Binnert Overdiep",
    "wof:placetype":"venue"
},
  "geometry": {"coordinates":[5.924443,52.958675],"type":"Point"}
}