{
  "type": "Feature",
  "properties": {
    "addr:full":"Winkelcentrum Woensel 124 Eindhoven Noord-Brabant 5625 AG",
    "addr:housenumber":"124",
    "addr:postcode":"5625",
    "addr:street":"Winkelcentrum Woensel",
    "iso:country":"NL",
    "sg:address":"Winkelcentrum Woensel 124",
    "sg:city":"Eindhoven",
    "sg:orig_category":"Bloemen And Planten",
    "sg:phone":"+31 40 241 5433",
    "sg:postcode":"5625 AG",
    "sg:province":"Noord-Brabant",
    "wof:name":"Sjerp Bloemen En Planten Bv",
    "wof:placetype":"venue"
},
  "geometry": {"coordinates":[5.472733,51.470234],"type":"Point"}
}