{
  "type": "Feature",
  "properties": {
    "addr:full":"Oude Bocholtsebaan 7 Winterswijk Woold Gelderland 7108 AV",
    "addr:housenumber":"7",
    "addr:postcode":"7108 av",
    "addr:street":"Oude Bocholtsebaan",
    "iso:country":"NL",
    "sg:address":"Oude Bocholtsebaan 7",
    "sg:city":"Winterswijk Woold",
    "sg:orig_category":"Public Relationbureaus",
    "sg:phone":"+31 543 564 540",
    "sg:postcode":"7108 AV",
    "sg:province":"Gelderland",
    "wof:name":"De Weijs",
    "wof:placetype":"venue"
},
  "geometry": {"coordinates":[6.722185,51.94154],"type":"Point"}
}