{
  "type": "Feature",
  "properties": {
    "addr:full":"Vivaldistr 13 Lisse Zuid-Holland 2162 AA",
    "addr:housenumber":"13",
    "addr:postcode":"2162 aa",
    "addr:street":"Vivaldistr",
    "iso:country":"NL",
    "sg:address":"Vivaldistr 13",
    "sg:city":"Lisse",
    "sg:orig_category":"Postkantoren",
    "sg:phone":"+31 252 420 283",
    "sg:postcode":"2162 AA",
    "sg:province":"Zuid-Holland",
    "sg:website":"http://www.postkantoor.nl",
    "wof:name":"Postkantoor",
    "wof:placetype":"venue"
},
  "geometry": {"coordinates":[4.561442,52.249332],"type":"Point"}
}