{
  "type": "Feature",
  "properties": {
    "addr:full":"Neerhem 44 Valkenburg Lb Limburg 6301 CJ",
    "addr:housenumber":"44",
    "addr:postcode":"lb;6301 cj",
    "addr:street":"Neerhem",
    "iso:country":"NL",
    "sg:address":"Neerhem 44",
    "sg:city":"Valkenburg Lb",
    "sg:orig_category":"Recreatie",
    "sg:phone":"+31 43 609 0609",
    "sg:postcode":"6301 CJ",
    "sg:province":"Limburg",
    "sg:website":"http://www.kabelbaan.nl",
    "wof:name":"Kabelbaan Valkenburg Bv",
    "wof:placetype":"venue"
},
  "geometry": {"coordinates":[5.834038,50.860016],"type":"Point"}
}