{
  "type": "Feature",
  "properties": {
    "addr:full":"Samenweid 7 Egmond-Binnen Noord-Holland 1935 AZ",
    "addr:housenumber":"7",
    "addr:postcode":"egmond-binnen;1935 az",
    "addr:street":"Samenweid",
    "iso:country":"NL",
    "sg:address":"Samenweid 7",
    "sg:city":"Egmond-Binnen",
    "sg:orig_category":"Bedrijfsinventaris Gh",
    "sg:phone":"+31 72 506 4766",
    "sg:postcode":"1935 AZ",
    "sg:province":"Noord-Holland",
    "wof:name":"Waaijer Electronics",
    "wof:placetype":"venue"
},
  "geometry": {"coordinates":[4.657206,52.592663],"type":"Point"}
}