{
  "type": "Feature",
  "properties": {
    "addr:full":"Borgsche Rieten 75 Terborg Gelderland 7061 ZP",
    "addr:housenumber":"75",
    "addr:postcode":"7061 zp",
    "addr:street":"Borgsche Rieten;Gelderland",
    "iso:country":"NL",
    "sg:address":"Borgsche Rieten 75",
    "sg:city":"Terborg",
    "sg:orig_category":"Verhuur Catering-, Feest- En Evenementbenodigdheden",
    "sg:phone":"+31 315 324 665",
    "sg:postcode":"7061 ZP",
    "sg:province":"Gelderland",
    "wof:name":"Vof Intermed. Beekman Horeca-Adv. & Verk",
    "wof:placetype":"venue"
},
  "geometry": {"coordinates":[6.344121,51.924381],"type":"Point"}
}