{
  "type": "Feature",
  "properties": {
    "iso:country":"NL",
    "sg:address":"Postbus 30",
    "sg:city":"Voorthuizen",
    "sg:orig_category":"Verenigingen En Stichtingen",
    "sg:phone":"+31 342 471 318",
    "sg:postcode":"3780 BA",
    "sg:province":"Gelderland",
    "wof:name":"Near East Ministry",
    "wof:placetype":"venue"
},
  "geometry": {"coordinates":[5.60713,52.18708],"type":"Point"}
}