{
  "type": "Feature",
  "properties": {
    "iso:country":"NL",
    "sg:address":"Mr De Jongwei 20",
    "sg:city":"De Tike",
    "sg:orig_category":"Timmerwerken",
    "sg:phone":"+31 512 372 395",
    "sg:postcode":"9219 VN",
    "sg:province":"Friesland",
    "wof:name":"Spikerbak, De",
    "wof:placetype":"venue"
},
  "geometry": {"coordinates":[6.037498,53.151974],"type":"Point"}
}