{
  "type": "Feature",
  "properties": {
    "iso:country":"NL",
    "sg:address":"Gouden Regenstraat 10",
    "sg:city":"Sint Michielsgestel",
    "sg:orig_category":"Juridische Dienstverlening",
    "sg:phone":"+31 73 551 3129",
    "sg:postcode":"5271 JW",
    "sg:province":"North Brabant",
    "wof:name":"Oele Adviesburo",
    "wof:placetype":"venue"
},
  "geometry": {"coordinates":[5.339498,51.640266],"type":"Point"}
}