{
  "type": "Feature",
  "properties": {
    "addr:full":"Gouden Regenstraat 10 Sint Michielsgestel North Brabant 5271 JW",
    "addr:housenumber":"10;michielsgestel",
    "addr:postcode":"5271 jw",
    "addr:street":"Gouden Regenstraat",
    "iso:country":"NL",
    "sg:address":"Gouden Regenstraat 10",
    "sg:city":"Sint Michielsgestel",
    "sg:orig_category":"Juridische Dienstverlening",
    "sg:phone":"+31 73 551 3129",
    "sg:postcode":"5271 JW",
    "sg:province":"North Brabant",
    "wof:name":"Oele Adviesburo",
    "wof:placetype":"venue"
},
  "geometry": {"coordinates":[5.339498,51.640266],"type":"Point"}
}