{
  "type": "Feature",
  "properties": {
    "addr:full":"Weidedreef 92 Zoetermeer South Holland 2727 EM",
    "addr:housenumber":"92",
    "addr:postcode":"2727 em",
    "addr:street":"Weidedreef",
    "iso:country":"NL",
    "sg:address":"Weidedreef 92",
    "sg:city":"Zoetermeer",
    "sg:orig_category":"Mensendieck - Oefentherapeuten",
    "sg:phone":"+31 79 331 6670",
    "sg:postcode":"2727 EM",
    "sg:province":"South Holland",
    "wof:name":"Boom-Aantjes, P J Van Der",
    "wof:placetype":"venue"
},
  "geometry": {"coordinates":[4.512283,52.073483],"type":"Point"}
}