{
  "type": "Feature",
  "properties": {
    "iso:country":"NL",
    "sg:address":"Rijksweg-Zuid 17",
    "sg:city":"Wellerlooi",
    "sg:orig_category":"Glaszetten",
    "sg:phone":"+31 478 502 582",
    "sg:postcode":"5856 AA",
    "sg:province":"Limburg",
    "wof:name":"Glashandel Fransman Vof",
    "wof:placetype":"venue"
},
  "geometry": {"coordinates":[6.13026,51.532471],"type":"Point"}
}