{
  "type": "Feature",
  "properties": {
    "iso:country":"NL",
    "sg:address":"Lessingln 20",
    "sg:city":"Utrecht",
    "sg:orig_category":"Psychotherapeuten",
    "sg:phone":"+31 30 296 5272",
    "sg:postcode":"3533 AW",
    "sg:province":"Utrecht",
    "sg:website":"http://www.valac.nl/umconsult.htm",
    "wof:name":"Bevort, F",
    "wof:placetype":"venue"
},
  "geometry": {"coordinates":[5.083577,52.090935],"type":"Point"}
}