{
  "type": "Feature",
  "properties": {
    "addr:full":"Zwettestr 20 Leeuwarden Friesland 8912 AH",
    "addr:housenumber":"20",
    "addr:postcode":"8912 ah",
    "addr:street":"Zwettestr",
    "iso:country":"NL",
    "sg:address":"Zwettestr 20",
    "sg:city":"Leeuwarden",
    "sg:orig_category":"Meubelen",
    "sg:phone":"+31 58 213 0027",
    "sg:postcode":"8912 AH",
    "sg:province":"Friesland",
    "wof:name":"Meubeltrend Friesland",
    "wof:placetype":"venue"
},
  "geometry": {"coordinates":[5.76909,53.194149],"type":"Point"}
}