{
  "type": "Feature",
  "properties": {
    "addr:full":"Elzenstraat 16 Winterswijk Gelderland 7101 TT",
    "addr:housenumber":"16",
    "addr:postcode":"7101 tt",
    "addr:street":"Elzenstraat;Gelderland",
    "iso:country":"NL",
    "sg:address":"Elzenstraat 16",
    "sg:city":"Winterswijk",
    "sg:orig_category":"Vertaal- And Tolkenbureaus",
    "sg:phone":"+31 543 521 647",
    "sg:postcode":"7101 TT",
    "sg:province":"Gelderland",
    "wof:name":"J.W. Tolkamp",
    "wof:placetype":"venue"
},
  "geometry": {"coordinates":[6.732618,51.973328],"type":"Point"}
}