{
  "type": "Feature",
  "properties": {
    "addr:full":"Zuiderplantsoen 1 De Meern Utrecht 3454 ES",
    "addr:housenumber":"1",
    "addr:postcode":"3454 es",
    "addr:street":"Zuiderplantsoen",
    "iso:country":"NL",
    "sg:address":"Zuiderplantsoen 1",
    "sg:city":"De Meern",
    "sg:orig_category":"Verzekeringen",
    "sg:phone":"+31 30 666 5511",
    "sg:postcode":"3454 ES",
    "sg:province":"Utrecht",
    "wof:name":"D.H.F. Assurantien",
    "wof:placetype":"venue"
},
  "geometry": {"coordinates":[5.031581,52.076286],"type":"Point"}
}