{
  "type": "Feature",
  "properties": {
    "addr:full":"Kon Wilhelminapln 13 Amsterdam Noord-Holland 1062 HH",
    "addr:housenumber":"13",
    "addr:postcode":"1062 hh",
    "addr:street":"Kon",
    "iso:country":"NL",
    "sg:address":"Kon Wilhelminapln 13",
    "sg:city":"Amsterdam",
    "sg:orig_category":"Hoeden",
    "sg:phone":"+31 20 617 3517",
    "sg:postcode":"1062 HH",
    "sg:province":"Noord-Holland",
    "wof:name":"Mpd",
    "wof:placetype":"venue"
},
  "geometry": {"coordinates":[4.840918,52.354782],"type":"Point"}
}