{
  "type": "Feature",
  "properties": {
    "addr:full":"Ceintuurbaan N 122 Roden Provincie Drenthe 9301 NZ",
    "addr:housenumber":"122",
    "addr:postcode":"9301 nz",
    "addr:street":"Ceintuurbaan N;Provincie Drenthe",
    "iso:country":"NL",
    "sg:address":"Ceintuurbaan N 122",
    "sg:city":"Roden",
    "sg:orig_category":"Autoschade- Herstelbedrijven",
    "sg:phone":"+31 50 501 0047",
    "sg:postcode":"9301 NZ",
    "sg:province":"Provincie Drenthe",
    "wof:name":"Heba Bv",
    "wof:placetype":"venue"
},
  "geometry": {"coordinates":[6.439667,53.145103],"type":"Point"}
}