{
  "type": "Feature",
  "properties": {
    "addr:full":"Bregeleane 16 Stiens Friesland 9051 PM",
    "addr:housenumber":"16",
    "addr:postcode":"9051 pm",
    "addr:street":"Bregeleane",
    "iso:country":"NL",
    "sg:address":"Bregeleane 16",
    "sg:city":"Stiens",
    "sg:orig_category":"Sportclubs",
    "sg:phone":"+31 58 257 1511",
    "sg:postcode":"9051 PM",
    "sg:province":"Friesland",
    "wof:name":"Stiens Tennisvereniging",
    "wof:placetype":"venue"
},
  "geometry": {"coordinates":[5.77444,53.262569],"type":"Point"}
}