{
  "type": "Feature",
  "properties": {
    "addr:full":"Van Heemstraweg 75 Winssen Gelderland 6645 KG",
    "addr:housenumber":"75",
    "addr:postcode":"6645 kg",
    "addr:street":"Van Heemstraweg;Gelderland",
    "iso:country":"NL",
    "sg:address":"Van Heemstraweg 75",
    "sg:city":"Winssen",
    "sg:orig_category":"Goederenvervoer Over De Weg",
    "sg:phone":"+31 487 523 035",
    "sg:postcode":"6645 KG",
    "sg:province":"Gelderland",
    "wof:name":"H.M. Gerrits Transport Bv",
    "wof:placetype":"venue"
},
  "geometry": {"coordinates":[5.695735,51.877686],"type":"Point"}
}