{
  "type": "Feature",
  "properties": {
    "addr:full":"Esdoornstraat 42 Leeuwarden Provincie Friesland 8924 BK",
    "addr:housenumber":"42",
    "addr:postcode":"8924 bk",
    "addr:street":"Esdoornstraat;Provincie Friesland",
    "iso:country":"NL",
    "sg:address":"Esdoornstraat 42",
    "sg:city":"Leeuwarden",
    "sg:classifiers":[
        {
            "category":"Communications",
            "subcategory":"Television Station",
            "type":"Services"
        }
    ],
    "sg:phone":"+31 58 267 1718",
    "sg:postcode":"8924 BK",
    "sg:province":"Provincie Friesland",
    "sg:tags":[
        "video",
        "audio",
        "verhuur"
    ],
    "wof:name":"Videotheek Scooby Doo",
    "wof:placetype":"venue"
},
  "geometry": {"coordinates":[5.824055,53.204498],"type":"Point"}
}