{
  "type": "Feature",
  "properties": {
    "iso:country":"NL",
    "sg:address":"Klompenmakerstraat 20",
    "sg:city":"Hoogvliet Rt",
    "sg:orig_category":"Autokeuringen",
    "sg:phone":"+31 10 416 6483",
    "sg:postcode":"3194 DE",
    "sg:province":"Zuid-Holland",
    "wof:name":"Wanica",
    "wof:placetype":"venue"
},
  "geometry": {"coordinates":[4.378548,51.867989],"type":"Point"}
}