{
  "type": "Feature",
  "properties": {
    "iso:country":"NL",
    "sg:address":"Harp 1",
    "sg:city":"S Hertogenbosch",
    "sg:orig_category":"Pianostemmen En -Reparatie",
    "sg:phone":"+31 6 54270717",
    "sg:postcode":"5231 DE",
    "sg:province":"North Brabant",
    "wof:name":"Weber",
    "wof:placetype":"venue"
},
  "geometry": {"coordinates":[5.301773,51.713715],"type":"Point"}
}