{
  "type": "Feature",
  "properties": {
    "iso:country":"NL",
    "sg:address":"Walstro 8",
    "sg:city":"Abbekerk",
    "sg:orig_category":"Bloemen En Planten",
    "sg:phone":"+31 229 581 368",
    "sg:postcode":"1657 KH",
    "sg:province":"North Holland",
    "wof:name":"Miriam",
    "wof:placetype":"venue"
},
  "geometry": {"coordinates":[5.016043,52.732662],"type":"Point"}
}