{
  "type": "Feature",
  "properties": {
    "addr:full":"Kluisgat 1 Wieringerwerf North Holland 1771 MV",
    "addr:housenumber":"1",
    "addr:postcode":"1771 mv",
    "addr:street":"Kluisgat",
    "iso:country":"NL",
    "sg:address":"Kluisgat 1",
    "sg:city":"Wieringerwerf",
    "sg:orig_category":"Jachthavens - Jachtwerven",
    "sg:phone":"+31 227 542 544",
    "sg:postcode":"1771 MV",
    "sg:province":"North Holland",
    "sg:website":"http://www.jongert.nl",
    "wof:name":"Jongert Jachtwerf Bv",
    "wof:placetype":"venue"
},
  "geometry": {"coordinates":[5.108578,52.855438],"type":"Point"}
}