{
  "type": "Feature",
  "properties": {
    "addr:full":"Nagelpoelwg 62B Apeldoorn Gelderland 7333 NZ",
    "addr:housenumber":"62b",
    "addr:postcode":"7333 nz",
    "addr:street":"Nagelpoelwg;Gelderland",
    "iso:country":"NL",
    "sg:address":"Nagelpoelwg 62B",
    "sg:city":"Apeldoorn",
    "sg:orig_category":"Autoreclame",
    "sg:phone":"+31 55 533 8384",
    "sg:postcode":"7333 NZ",
    "sg:province":"Gelderland",
    "wof:name":"Steneker Reclame Vof",
    "wof:placetype":"venue"
},
  "geometry": {"coordinates":[5.972374,52.17984],"type":"Point"}
}