{
  "type": "Feature",
  "properties": {
    "iso:country":"NL",
    "sg:address":"Kipstr 12",
    "sg:city":"Ossenisse",
    "sg:orig_category":"Verenigingsgebouwen",
    "sg:phone":"+31 114 682 734",
    "sg:postcode":"4589 KR",
    "sg:province":"Zeeland",
    "wof:name":"Hof Ter Nesse",
    "wof:placetype":"venue"
},
  "geometry": {"coordinates":[3.981042,51.387653],"type":"Point"}
}