{
  "type": "Feature",
  "properties": {
    "addr:full":"Verlengde Fortlaan 114 Naarden Noord-Holland 1412 EA",
    "addr:housenumber":"114",
    "addr:postcode":"1412 ea",
    "addr:street":"Verlengde Fortlaan",
    "iso:country":"NL",
    "sg:address":"Verlengde Fortlaan 114",
    "sg:city":"Naarden",
    "sg:orig_category":"Meubelzaken, Woning- And Keukeninrichting",
    "sg:phone":"+31 35 694 5149",
    "sg:postcode":"1412 EA",
    "sg:province":"Noord-Holland",
    "wof:name":"J.W. Poelhekke Agenturen Bv",
    "wof:placetype":"venue"
},
  "geometry": {"coordinates":[5.144507,52.284355],"type":"Point"}
}