{
  "type": "Feature",
  "properties": {
    "addr:full":"Vrede En Vrijheid 26 Den Helder Noord-Holland 1785 RM",
    "addr:housenumber":"26",
    "addr:postcode":"1785 rm",
    "addr:street":"Vrede En Vrijheid",
    "iso:country":"NL",
    "sg:address":"Vrede En Vrijheid 26",
    "sg:city":"Den Helder",
    "sg:orig_category":"Artsen And Specialisten",
    "sg:phone":"+31 223 660 008",
    "sg:postcode":"1785 RM",
    "sg:province":"Noord-Holland",
    "wof:name":"J. Zinkstok",
    "wof:placetype":"venue"
},
  "geometry": {"coordinates":[4.771403,52.936008],"type":"Point"}
}