{
  "type": "Feature",
  "properties": {
    "iso:country":"NL",
    "sg:address":"Zuiderkade 4",
    "sg:city":"Beverwijk",
    "sg:orig_category":"Machinefabrieken",
    "sg:phone":"+31 251 224 209",
    "sg:postcode":"1948 NG",
    "sg:province":"Noord-Holland",
    "wof:name":"Adrichem Bv",
    "wof:placetype":"venue"
},
  "geometry": {"coordinates":[4.65848,52.476181],"type":"Point"}
}