{
  "type": "Feature",
  "properties": {
    "iso:country":"NL",
    "sg:address":"Binnenhof 19B",
    "sg:city":"Almelo",
    "sg:orig_category":"Schoenen - Reparaties",
    "sg:phone":"+31 546 862 975",
    "sg:postcode":"7608 KG",
    "sg:province":"Overijssel",
    "wof:name":"Hayko",
    "wof:placetype":"venue"
},
  "geometry": {"coordinates":[6.678837,52.378845],"type":"Point"}
}