{
  "type": "Feature",
  "properties": {
    "addr:full":"Binnenhof 19B Almelo Overijssel 7608 KG",
    "addr:housenumber":"19b",
    "addr:postcode":"7608 kg",
    "addr:street":"Binnenhof",
    "iso:country":"NL",
    "sg:address":"Binnenhof 19B",
    "sg:city":"Almelo",
    "sg:orig_category":"Schoenen - Reparaties",
    "sg:phone":"+31 546 862 975",
    "sg:postcode":"7608 KG",
    "sg:province":"Overijssel",
    "wof:name":"Hayko",
    "wof:placetype":"venue"
},
  "geometry": {"coordinates":[6.678837,52.378845],"type":"Point"}
}