{
  "type": "Feature",
  "properties": {
    "addr:full":"Koningin Wilhelminasingel 83 Waddinxveen Zuid-Holland 2741 VX",
    "addr:housenumber":"83",
    "addr:postcode":"2741 vx",
    "addr:street":"Koningin Wilhelminasingel",
    "iso:country":"NL",
    "sg:address":"Koningin Wilhelminasingel 83",
    "sg:city":"Waddinxveen",
    "sg:orig_category":"Verzekeringen",
    "sg:phone":"+31 182 612 539",
    "sg:postcode":"2741 VX",
    "sg:province":"Zuid-Holland",
    "wof:name":"Verweij Verzekeringen",
    "wof:placetype":"venue"
},
  "geometry": {"coordinates":[4.654345,52.052963],"type":"Point"}
}