{
  "type": "Feature",
  "properties": {
    "addr:full":"Botter 3906 Lelystad Flevoland 8243 KB",
    "addr:postcode":"3906;8243 kb",
    "addr:street":"Botter;Flevoland",
    "iso:country":"NL",
    "sg:address":"Botter 3906",
    "sg:city":"Lelystad",
    "sg:orig_category":"Verenigingen En Stichtingen",
    "sg:phone":"+31 320 257 007",
    "sg:postcode":"8243 KB",
    "sg:province":"Flevoland",
    "wof:name":"Skaf",
    "wof:placetype":"venue"
},
  "geometry": {"coordinates":[5.460414,52.505447],"type":"Point"}
}