{
  "type": "Feature",
  "properties": {
    "iso:country":"NL",
    "sg:address":"Ambachtsweg 39F",
    "sg:city":"Pijnacker",
    "sg:orig_category":"Bestratingen",
    "sg:phone":"+31 15 369 6260",
    "sg:postcode":"2641 KT",
    "sg:province":"Zuid-Holland",
    "wof:name":"Springer",
    "wof:placetype":"venue"
},
  "geometry": {"coordinates":[4.444097,52.026543],"type":"Point"}
}