{
  "type": "Feature",
  "properties": {
    "addr:full":"Eikstraat 2 Steenbergen Nb Noord-Brabant 4651 KE",
    "addr:housenumber":"2",
    "addr:postcode":"4651 ke",
    "addr:street":"Eikstraat",
    "iso:country":"NL",
    "sg:address":"Eikstraat 2",
    "sg:city":"Steenbergen Nb",
    "sg:orig_category":"Parketvloeren",
    "sg:phone":"+31 167 566 549",
    "sg:postcode":"4651 KE",
    "sg:province":"Noord-Brabant",
    "wof:name":"Azeba",
    "wof:placetype":"venue"
},
  "geometry": {"coordinates":[4.317545,51.576885],"type":"Point"}
}