{
  "type": "Feature",
  "properties": {
    "addr:full":"Gedempte Pol 36 Sneek Friesland 8601 BZ",
    "addr:housenumber":"36",
    "addr:postcode":"8601 bz",
    "addr:street":"Gedempte Pol",
    "iso:country":"NL",
    "sg:address":"Gedempte Pol 36",
    "sg:city":"Sneek",
    "sg:orig_category":"Zuivelproducten",
    "sg:phone":"+31 515 417 276",
    "sg:postcode":"8601 BZ",
    "sg:province":"Friesland",
    "wof:name":"Kaashandel De Heus",
    "wof:placetype":"venue"
},
  "geometry": {"coordinates":[5.661165,53.033733],"type":"Point"}
}