{
  "type": "Feature",
  "properties": {
    "iso:country":"NL",
    "sg:address":"Gedempte Pol 36",
    "sg:city":"Sneek",
    "sg:orig_category":"Zuivelproducten",
    "sg:phone":"+31 515 417 276",
    "sg:postcode":"8601 BZ",
    "sg:province":"Friesland",
    "wof:name":"Kaashandel De Heus",
    "wof:placetype":"venue"
},
  "geometry": {"coordinates":[5.661165,53.033733],"type":"Point"}
}