{
  "type": "Feature",
  "properties": {
    "addr:full":"Professor Mulderslaan 3 Oudenbosch Noord-Brabant 4731 BR",
    "addr:housenumber":"3",
    "addr:postcode":"4731 br",
    "addr:street":"Professor Mulderslaan",
    "iso:country":"NL",
    "sg:address":"Professor Mulderslaan 3",
    "sg:city":"Oudenbosch",
    "sg:orig_category":"Kappers",
    "sg:phone":"+31 165 312 083",
    "sg:postcode":"4731 BR",
    "sg:province":"Noord-Brabant",
    "wof:name":"Kapsalon Van Nassau",
    "wof:placetype":"venue"
},
  "geometry": {"coordinates":[4.5438318253,51.5895042419],"type":"Point"}
}