{
  "type": "Feature",
  "properties": {
    "addr:full":"Ninaberln Hellendoorn NL.08 7447 AD",
    "addr:postcode":"7447 ad",
    "iso:country":"NL",
    "sg:address":"Ninaberln",
    "sg:city":"Hellendoorn",
    "sg:orig_category":"Begraafplaatsen",
    "sg:phone":"+31 548 655 140",
    "sg:postcode":"7447 AD",
    "sg:province":"NL.08",
    "wof:name":"Gemeentelijke Begraafplaats",
    "wof:placetype":"venue"
},
  "geometry": {"coordinates":[6.447976,52.390255],"type":"Point"}
}