{
  "type": "Feature",
  "properties": {
    "addr:full":"Maartensdijksewg 1 Bilthoven Utrecht 3723 MC",
    "addr:housenumber":"1",
    "addr:postcode":"3723 mc",
    "addr:street":"Maartensdijksewg",
    "iso:country":"NL",
    "sg:address":"Maartensdijksewg 1",
    "sg:city":"Bilthoven",
    "sg:orig_category":"Open Haard Houtblokken",
    "sg:phone":"+31 35 666 8471",
    "sg:postcode":"3723 MC",
    "sg:province":"Utrecht",
    "wof:name":"Terra Nova",
    "wof:placetype":"venue"
},
  "geometry": {"coordinates":[5.218169,52.164219],"type":"Point"}
}