{
  "type": "Feature",
  "properties": {
    "addr:full":"Boerhaaveln 10 Oosterhout Nb Noord-Brabant 4904 KG",
    "addr:housenumber":"10",
    "addr:postcode":"4904 kg",
    "addr:street":"Boerhaaveln",
    "iso:country":"NL",
    "sg:address":"Boerhaaveln 10",
    "sg:city":"Oosterhout Nb",
    "sg:orig_category":"Antiquiteiten",
    "sg:phone":"+31 162 426 913",
    "sg:postcode":"4904 KG",
    "sg:province":"Noord-Brabant",
    "wof:name":"Oosterhoutse Kunsthdl",
    "wof:placetype":"venue"
},
  "geometry": {"coordinates":[4.85625,51.643051],"type":"Point"}
}