{
  "type": "Feature",
  "properties": {
    "addr:full":"Leywg 709A S Gravenhage Zuid-Holland 2545 GM",
    "addr:housenumber":"709a;gravenhage",
    "addr:postcode":"2545 gm",
    "addr:street":"S",
    "iso:country":"NL",
    "sg:address":"Leywg 709A",
    "sg:city":"S Gravenhage",
    "sg:orig_category":"Schoenen",
    "sg:phone":"+31 70 404 4390",
    "sg:postcode":"2545 GM",
    "sg:province":"Zuid-Holland",
    "sg:website":"http://www.dolcis.nl",
    "wof:name":"Dolcis",
    "wof:placetype":"venue"
},
  "geometry": {"coordinates":[4.27049,52.05093],"type":"Point"}
}