{
  "type": "Feature",
  "properties": {
    "iso:country":"NL",
    "sg:address":"Lithoyensedk 16",
    "sg:city":"Lithoyen",
    "sg:orig_category":"Betonmortel",
    "sg:phone":"+31 412 481 257",
    "sg:postcode":"5396 NE",
    "sg:province":"Noord-Brabant",
    "wof:name":"Bouwoort, Betoncentrale",
    "wof:placetype":"venue"
},
  "geometry": {"coordinates":[5.463142,51.799271],"type":"Point"}
}