{
  "type": "Feature",
  "properties": {
    "iso:country":"NL",
    "sg:address":"Langs De Tocht 19",
    "sg:city":"Sauwerd",
    "sg:orig_category":"Architecten",
    "sg:phone":"+31 50 306 1515",
    "sg:postcode":"9771 BR",
    "sg:province":"Groningen",
    "wof:name":"E Van Der Beek",
    "wof:placetype":"venue"
},
  "geometry": {"coordinates":[6.53763,53.290524],"type":"Point"}
}