{
  "type": "Feature",
  "properties": {
    "addr:full":"Boskdk 4 Winsum Fr Provincie Friesland 8831 XD",
    "addr:housenumber":"4",
    "addr:postcode":"8831 xd",
    "addr:street":"Boskdk;Friesland",
    "iso:country":"NL",
    "sg:address":"Boskdk 4",
    "sg:city":"Winsum Fr",
    "sg:orig_category":"Heftrucks",
    "sg:phone":"+31 517 341 804",
    "sg:postcode":"8831 XD",
    "sg:province":"Provincie Friesland",
    "sg:website":"http://www.bakkerheftrucks.nl",
    "wof:name":"Bakker Heftrucks",
    "wof:placetype":"venue"
},
  "geometry": {"coordinates":[5.632079,53.153942],"type":"Point"}
}