{
  "type": "Feature",
  "properties": {
    "addr:full":"Brummelhuisweg 1 Markelo Overijssel 7475 MC",
    "addr:housenumber":"1;7475",
    "addr:postcode":"mc",
    "addr:street":"Brummelhuisweg",
    "iso:country":"NL",
    "sg:address":"Brummelhuisweg 1",
    "sg:city":"Markelo",
    "sg:orig_category":"Loodgieterswerk, Verwarming And Sanitaire Installaties",
    "sg:phone":"+31 547 273 997",
    "sg:postcode":"7475 MC",
    "sg:province":"Overijssel",
    "wof:name":"B.J.A. Blokhorst",
    "wof:placetype":"venue"
},
  "geometry": {"coordinates":[6.634531,52.218548],"type":"Point"}
}