{
  "type": "Feature",
  "properties": {
    "addr:full":"Ruimzicht 83 Amsterdam Noord-Holland 1068 CP",
    "addr:housenumber":"83",
    "addr:postcode":"1068 cp",
    "addr:street":"Ruimzicht",
    "iso:country":"NL",
    "sg:address":"Ruimzicht 83",
    "sg:city":"Amsterdam",
    "sg:orig_category":"Kunsthandel",
    "sg:phone":"+31 20 619 8370",
    "sg:postcode":"1068 CP",
    "sg:province":"Noord-Holland",
    "wof:name":"Verschueren, J L",
    "wof:placetype":"venue"
},
  "geometry": {"coordinates":[4.807172,52.361897],"type":"Point"}
}