{
  "type": "Feature",
  "properties": {
    "iso:country":"NL",
    "sg:address":"Dukaton 23",
    "sg:city":"Volendam",
    "sg:orig_category":"Fitnesscentra",
    "sg:phone":"+31 299 362 549",
    "sg:postcode":"1132 RA",
    "sg:province":"North Holland",
    "wof:name":"Slen World",
    "wof:placetype":"venue"
},
  "geometry": {"coordinates":[5.062106,52.505486],"type":"Point"}
}