{
  "type": "Feature",
  "properties": {
    "addr:full":"C Sluterwg 125 Haarlem Noord-Holland 2012 WS",
    "addr:housenumber":"125",
    "addr:postcode":"2012 ws",
    "iso:country":"NL",
    "sg:address":"C Sluterwg 125",
    "sg:city":"Haarlem",
    "sg:orig_category":"Administratie- En Boekhoudkantoren",
    "sg:phone":"+31 23 528 5754",
    "sg:postcode":"2012 WS",
    "sg:province":"Noord-Holland",
    "wof:name":"Adfis Bv",
    "wof:placetype":"venue"
},
  "geometry": {"coordinates":[4.617276,52.362373],"type":"Point"}
}