{
  "type": "Feature",
  "properties": {
    "addr:full":"Beilerstr 13B Westerbork Drenthe 9431 GA",
    "addr:housenumber":"13b",
    "addr:postcode":"9431 ga",
    "addr:street":"Beilerstr",
    "iso:country":"NL",
    "sg:address":"Beilerstr 13B",
    "sg:city":"Westerbork",
    "sg:orig_category":"Zalenverhuur",
    "sg:phone":"+31 593 370 334",
    "sg:postcode":"9431 GA",
    "sg:province":"Drenthe",
    "sg:website":"http://www.dewarrel.nl",
    "wof:name":"Warrel, De",
    "wof:placetype":"venue"
},
  "geometry": {"coordinates":[6.596091,52.853134],"type":"Point"}
}