{
  "type": "Feature",
  "properties": {
    "iso:country":"NL",
    "sg:address":"Kloosterplein 11",
    "sg:city":"Breda",
    "sg:orig_category":"Ambassades And Consulaten",
    "sg:phone":"+31 76 530 7370",
    "sg:postcode":"4811 GP",
    "sg:province":"Noord-Brabant",
    "wof:name":"Consulaat Van Belgie",
    "wof:placetype":"venue"
},
  "geometry": {"coordinates":[4.781971,51.588062],"type":"Point"}
}