{
  "type": "Feature",
  "properties": {
    "iso:country":"NL",
    "sg:address":"Oranjepln 8A",
    "sg:city":"Stellendam",
    "sg:orig_category":"Postkantoren",
    "sg:phone":"+31 187 491 285",
    "sg:postcode":"3251 XE",
    "sg:province":"Zuid-Holland",
    "sg:website":"http://www.postkantoor.nl",
    "wof:name":"Postkantoor",
    "wof:placetype":"venue"
},
  "geometry": {"coordinates":[4.0254,51.805977],"type":"Point"}
}