{
  "type": "Feature",
  "properties": {
    "addr:full":"Van Zeggelenlaan 77 'S Gravenhage South Holland 2524 AB",
    "addr:housenumber":"77",
    "addr:postcode":"2524 ab",
    "addr:street":"Van Zeggelenlaan;' S Gravenhage",
    "iso:country":"NL",
    "sg:address":"Van Zeggelenlaan 77",
    "sg:city":"'S Gravenhage",
    "sg:orig_category":"Discountwinkels",
    "sg:phone":"+31 70 396 1395",
    "sg:postcode":"2524 AB",
    "sg:province":"South Holland",
    "wof:name":"Prins Markthoekje",
    "wof:placetype":"venue"
},
  "geometry": {"coordinates":[4.318792,52.053448],"type":"Point"}
}