{
  "type": "Feature",
  "properties": {
    "addr:full":"G T Rietveldstr 36 Almere Flevoland 1333 LE",
    "addr:housenumber":"36;1333",
    "addr:postcode":"le",
    "addr:street":"Flevoland",
    "iso:country":"NL",
    "sg:address":"G T Rietveldstr 36",
    "sg:city":"Almere",
    "sg:orig_category":"Fotopersbureaus",
    "sg:phone":"+31 36 532 1036",
    "sg:postcode":"1333 LE",
    "sg:province":"Flevoland",
    "wof:name":"Lvo",
    "wof:placetype":"venue"
},
  "geometry": {"coordinates":[5.252829,52.397652],"type":"Point"}
}