{
  "type": "Feature",
  "properties": {
    "iso:country":"NL",
    "sg:address":"G T Rietveldstr 36",
    "sg:city":"Almere",
    "sg:orig_category":"Fotopersbureaus",
    "sg:phone":"+31 36 532 1036",
    "sg:postcode":"1333 LE",
    "sg:province":"Flevoland",
    "wof:name":"Lvo",
    "wof:placetype":"venue"
},
  "geometry": {"coordinates":[5.252829,52.397652],"type":"Point"}
}