{
  "type": "Feature",
  "properties": {
    "addr:full":"Esserbroekw 6 Otterlo Gelderland 6731 DB",
    "addr:housenumber":"6",
    "addr:postcode":"6731 db",
    "addr:street":"Esserbroekw;Gelderland",
    "iso:country":"NL",
    "sg:address":"Esserbroekw 6",
    "sg:city":"Otterlo",
    "sg:orig_category":"Pluimveebedrijven En -Handelaren",
    "sg:phone":"+31 318 591 584",
    "sg:postcode":"6731 DB",
    "sg:province":"Gelderland",
    "wof:name":"Snel, J",
    "wof:placetype":"venue"
},
  "geometry": {"coordinates":[5.771465,52.10001],"type":"Point"}
}