{
  "type": "Feature",
  "properties": {
    "iso:country":"NL",
    "sg:address":"Liviusstraat 9",
    "sg:city":"'S Hertogenbosch",
    "sg:orig_category":"Binnenhuisarchitecten",
    "sg:phone":"+31 73 613 7350",
    "sg:postcode":"5216 CD",
    "sg:province":"Noord-Brabant",
    "wof:name":"M.J. Christan",
    "wof:placetype":"venue"
},
  "geometry": {"coordinates":[5.31528,51.678848],"type":"Point"}
}