{
  "type": "Feature",
  "properties": {
    "addr:full":"Torenstraat 31 Joure Friesland 8501 BV",
    "addr:housenumber":"31",
    "addr:postcode":"8501 bv",
    "addr:street":"Torenstraat",
    "iso:country":"NL",
    "sg:address":"Torenstraat 31",
    "sg:city":"Joure",
    "sg:orig_category":"Kappers",
    "sg:phone":"+31 513 417 733",
    "sg:postcode":"8501 BV",
    "sg:province":"Friesland",
    "wof:name":"Headroom Kappers",
    "wof:placetype":"venue"
},
  "geometry": {"coordinates":[5.7957468033,52.9692649841],"type":"Point"}
}