{
  "type": "Feature",
  "properties": {
    "iso:country":"NL",
    "sg:address":"It Ald Hof 5",
    "sg:city":"Arum",
    "sg:orig_category":"Partyservice",
    "sg:phone":"+31 517 641 764",
    "sg:postcode":"8822 WN",
    "sg:province":"Provincie Friesland",
    "wof:name":"Zee, Van Der",
    "wof:placetype":"venue"
},
  "geometry": {"coordinates":[5.472628,53.128292],"type":"Point"}
}