{
  "type": "Feature",
  "properties": {
    "addr:full":"Zomer 14 De Meern Utrecht 3454 KN",
    "addr:housenumber":"14",
    "addr:postcode":"3454 kn",
    "addr:street":"Zomer",
    "iso:country":"NL",
    "sg:address":"Zomer 14",
    "sg:city":"De Meern",
    "sg:orig_category":"Verzekeringen - Verzekeringskantoren",
    "sg:phone":"+31 30 666 1527",
    "sg:postcode":"3454 KN",
    "sg:province":"Utrecht",
    "wof:name":"Eijk, F C Van",
    "wof:placetype":"venue"
},
  "geometry": {"coordinates":[5.035162,52.087215],"type":"Point"}
}