{
  "type": "Feature",
  "properties": {
    "addr:full":"Lusthofstraat 5 A Rotterdam Zuid-Holland 3062 WB",
    "addr:housenumber":"5 a",
    "addr:postcode":"3062 wb",
    "addr:street":"Lusthofstraat",
    "iso:country":"NL",
    "sg:address":"Lusthofstraat 5 A",
    "sg:city":"Rotterdam",
    "sg:orig_category":"Diverse Grafische Activiteiten",
    "sg:phone":"+31 10 412 1699",
    "sg:postcode":"3062 WB",
    "sg:province":"Zuid-Holland",
    "wof:name":"Susan Strampel",
    "wof:placetype":"venue"
},
  "geometry": {"coordinates":[4.513918,51.92305],"type":"Point"}
}