{
  "type": "Feature",
  "properties": {
    "iso:country":"NL",
    "sg:address":"Spoorstr 3A",
    "sg:city":"Schoonhoven",
    "sg:orig_category":"Bibliotheken En Leeszalen Openbare",
    "sg:phone":"+31 182 385 406",
    "sg:postcode":"2871 TN",
    "sg:province":"Zuid-Holland",
    "sg:website":"http://www.hollandnet.nl",
    "wof:name":"Openb Bibliotheek",
    "wof:placetype":"venue"
},
  "geometry": {"coordinates":[4.849064,51.949059],"type":"Point"}
}