{
  "type": "Feature",
  "properties": {
    "addr:full":"Ln V Meerdervoort 133A S Gravenhage South Holland 2517 AW",
    "addr:housenumber":"133a s",
    "addr:postcode":"2517 aw",
    "addr:street":"Ln;Meerdervoort",
    "iso:country":"NL",
    "sg:address":"Ln V Meerdervoort 133A",
    "sg:city":"S Gravenhage",
    "sg:orig_category":"Grafisch Ontwerpers",
    "sg:phone":"+31 70 365 8730",
    "sg:postcode":"2517 AW",
    "sg:province":"South Holland",
    "wof:name":"Polder, Karen",
    "wof:placetype":"venue"
},
  "geometry": {"coordinates":[4.28708,52.08667],"type":"Point"}
}