{
  "type": "Feature",
  "properties": {
    "addr:full":"Middel 98 Westzaan North Holland 1551 SR",
    "addr:housenumber":"98;1551",
    "addr:postcode":"sr",
    "addr:street":"Middel",
    "iso:country":"NL",
    "sg:address":"Middel 98",
    "sg:city":"Westzaan",
    "sg:orig_category":"Bestratingen",
    "sg:phone":"+31 75 622 2144",
    "sg:postcode":"1551 SR",
    "sg:province":"North Holland",
    "wof:name":"Metze, J D",
    "wof:placetype":"venue"
},
  "geometry": {"coordinates":[4.778304,52.471336],"type":"Point"}
}