{
  "type": "Feature",
  "properties": {
    "addr:full":"Keiweg 1 Alteveer Gn Groningen 9661 TV",
    "addr:housenumber":"1",
    "addr:postcode":"gn;9661 tv",
    "addr:street":"Keiweg",
    "iso:country":"NL",
    "sg:address":"Keiweg 1",
    "sg:city":"Alteveer Gn",
    "sg:orig_category":"Overheidsdiensten",
    "sg:phone":"+31 599 332 552",
    "sg:postcode":"9661 TV",
    "sg:province":"Groningen",
    "wof:name":"De Drijscheer",
    "wof:placetype":"venue"
},
  "geometry": {"coordinates":[7.0058760643,53.0505371094],"type":"Point"}
}