{
  "type": "Feature",
  "properties": {
    "iso:country":"NL",
    "sg:address":"Ms V Riemsdykwg 63",
    "sg:city":"Amsterdam",
    "sg:orig_category":"Verlichtingsartikelen - Groothandel",
    "sg:phone":"+31 20 633 6354",
    "sg:postcode":"1033 RC",
    "sg:province":"North Holland",
    "wof:name":"Kloosterman Bv",
    "wof:placetype":"venue"
},
  "geometry": {"coordinates":[4.88555,52.407909],"type":"Point"}
}