{
  "type": "Feature",
  "properties": {
    "addr:full":"Schoolstr 32 Katwijk South Holland 2225 KT",
    "addr:housenumber":"32",
    "addr:postcode":"2225 kt",
    "addr:street":"Schoolstr",
    "iso:country":"NL",
    "sg:address":"Schoolstr 32",
    "sg:city":"Katwijk",
    "sg:orig_category":"Verenigingen En Stichtingen",
    "sg:phone":"+31 71 407 2813",
    "sg:postcode":"2225 KT",
    "sg:province":"South Holland",
    "wof:name":"Sufi Way",
    "wof:placetype":"venue"
},
  "geometry": {"coordinates":[4.399915,52.200169],"type":"Point"}
}