{
  "type": "Feature",
  "properties": {
    "addr:full":"Kerkraderwg 89 Heerlen Limburg 6416 CG",
    "addr:housenumber":"89",
    "addr:postcode":"6416 cg",
    "addr:street":"Kerkraderwg",
    "iso:country":"NL",
    "sg:address":"Kerkraderwg 89",
    "sg:city":"Heerlen",
    "sg:orig_category":"Kappers",
    "sg:phone":"+31 45 541 6095",
    "sg:postcode":"6416 CG",
    "sg:province":"Limburg",
    "wof:name":"Linden, E Van Der",
    "wof:placetype":"venue"
},
  "geometry": {"coordinates":[5.999845,50.882252],"type":"Point"}
}