{
  "type": "Feature",
  "properties": {
    "addr:full":"Zeisterweg 97 Woudenberg Utrecht 3931 ME",
    "addr:housenumber":"97",
    "addr:postcode":"3931",
    "addr:street":"Zeisterweg",
    "iso:country":"NL",
    "sg:address":"Zeisterweg 97",
    "sg:city":"Woudenberg",
    "sg:orig_category":"Kampeerterreinen",
    "sg:phone":"+31 343 443 006",
    "sg:postcode":"3931 ME",
    "sg:province":"Utrecht",
    "wof:name":"Ncc Camping Den Treek",
    "wof:placetype":"venue"
},
  "geometry": {"coordinates":[5.3629088402,52.0837364197],"type":"Point"}
}