{
  "type": "Feature",
  "properties": {
    "addr:full":"V Riebeeckstr 11 Bis/ A Utrecht Utrecht 3531 EH",
    "addr:housenumber":"11 bis / a",
    "addr:postcode":"3531 eh",
    "iso:country":"NL",
    "sg:address":"V Riebeeckstr 11 Bis/ A",
    "sg:city":"Utrecht",
    "sg:orig_category":"Sportverenigingen En Ontspannings- Verenigingen",
    "sg:phone":"+31 30 293 5907",
    "sg:postcode":"3531 EH",
    "sg:province":"Utrecht",
    "wof:name":"Sno Klaverjasver",
    "wof:placetype":"venue"
},
  "geometry": {"coordinates":[5.09574,52.090012],"type":"Point"}
}