{
  "type": "Feature",
  "properties": {
    "addr:full":"Meutestr 29B Maastricht Limburg 6219 BK",
    "addr:housenumber":"29b",
    "addr:postcode":"6219 bk",
    "addr:street":"Meutestr",
    "iso:country":"NL",
    "sg:address":"Meutestr 29B",
    "sg:city":"Maastricht",
    "sg:orig_category":"Metselwerken",
    "sg:phone":"+31 43 321 9316",
    "sg:postcode":"6219 BK",
    "sg:province":"Limburg",
    "wof:name":"Verhaegen, J H",
    "wof:placetype":"venue"
},
  "geometry": {"coordinates":[5.68925,50.864689],"type":"Point"}
}