{
  "type": "Feature",
  "properties": {
    "addr:full":"Sporthoflaan 11 Sassenheim Zuid-Holland 2172 BP",
    "addr:housenumber":"11",
    "addr:postcode":"2172 bp",
    "addr:street":"Sporthoflaan",
    "iso:country":"NL",
    "sg:address":"Sporthoflaan 11",
    "sg:city":"Sassenheim",
    "sg:orig_category":"Binnenhuisarchitecten",
    "sg:phone":"+31 252 221 678",
    "sg:postcode":"2172 BP",
    "sg:province":"Zuid-Holland",
    "wof:name":"Karin Homan",
    "wof:placetype":"venue"
},
  "geometry": {"coordinates":[4.528492,52.224499],"type":"Point"}
}