{
  "type": "Feature",
  "properties": {
    "iso:country":"NL",
    "sg:address":"Westeinde 3",
    "sg:city":"Venhuizen",
    "sg:orig_category":"Overheidsdiensten",
    "sg:phone":"+31 228 545 100",
    "sg:postcode":"1606 CZ",
    "sg:province":"Noord-Holland",
    "wof:name":"Gemeente Venhuizen",
    "wof:placetype":"venue"
},
  "geometry": {"coordinates":[15.4752702713,49.8037910461],"type":"Point"}
}