{
  "type": "Feature",
  "properties": {
    "addr:full":"Westeinde 3 Venhuizen Noord-Holland 1606 CZ",
    "addr:housenumber":"3",
    "addr:postcode":"1606",
    "addr:street":"Westeinde",
    "iso:country":"NL",
    "sg:address":"Westeinde 3",
    "sg:city":"Venhuizen",
    "sg:orig_category":"Overheidsdiensten",
    "sg:phone":"+31 228 545 100",
    "sg:postcode":"1606 CZ",
    "sg:province":"Noord-Holland",
    "wof:name":"Gemeente Venhuizen",
    "wof:placetype":"venue"
},
  "geometry": {"coordinates":[15.4752702713,49.8037910461],"type":"Point"}
}