{
  "type": "Feature",
  "properties": {
    "addr:full":"Bredestraat 2 Meteren Gelderland 4194 TR",
    "addr:housenumber":"2",
    "addr:postcode":"4194 tr",
    "addr:street":"Bredestraat;Gelderland",
    "iso:country":"NL",
    "sg:address":"Bredestraat 2",
    "sg:city":"Meteren",
    "sg:orig_category":"Bloemen And Planten",
    "sg:phone":"+31 345 569 295",
    "sg:postcode":"4194 TR",
    "sg:province":"Gelderland",
    "wof:name":"Hoveniersbedrijf Hol",
    "wof:placetype":"venue"
},
  "geometry": {"coordinates":[5.2799,51.868107],"type":"Point"}
}