{
  "type": "Feature",
  "properties": {
    "addr:full":"Grotestr 61 Goor Overijssel 7471 BL",
    "addr:housenumber":"61",
    "addr:postcode":"7471 bl",
    "addr:street":"Grotestr",
    "iso:country":"NL",
    "sg:address":"Grotestr 61",
    "sg:city":"Goor",
    "sg:orig_category":"Schoenen",
    "sg:phone":"+31 547 260 891",
    "sg:postcode":"7471 BL",
    "sg:province":"Overijssel",
    "sg:website":"http://www.scapino.nl",
    "wof:name":"Scapino",
    "wof:placetype":"venue"
},
  "geometry": {"coordinates":[6.587251,52.233902],"type":"Point"}
}