{
  "type": "Feature",
  "properties": {
    "iso:country":"NL",
    "sg:address":"Veluwewg 66",
    "sg:city":"Kootwykerbroek",
    "sg:orig_category":"Herenkleding",
    "sg:phone":"+31 342 441 271",
    "sg:postcode":"3774 BN",
    "sg:province":"Gelderland",
    "sg:website":"http://www.hootden-kleding.nl",
    "wof:name":"Hootsen",
    "wof:placetype":"venue"
},
  "geometry": {"coordinates":[5.669152,52.152786],"type":"Point"}
}