{
  "type": "Feature",
  "properties": {
    "addr:full":"Jan Van Galenstraat 151 Amsterdam Noord-Holland 1056 BP",
    "addr:housenumber":"151",
    "addr:postcode":"1056 bp",
    "addr:street":"Jan Van Galenstraat",
    "iso:country":"NL",
    "sg:address":"Jan Van Galenstraat 151",
    "sg:city":"Amsterdam",
    "sg:orig_category":"Artiestenbureaus",
    "sg:phone":"+31 20 683 3846",
    "sg:postcode":"1056 BP",
    "sg:province":"Noord-Holland",
    "wof:name":"Miss Thandi",
    "wof:placetype":"venue"
},
  "geometry": {"coordinates":[4.856846,52.374352],"type":"Point"}
}