{
  "type": "Feature",
  "properties": {
    "iso:country":"NL",
    "sg:address":"Scheepvaartstr 25008",
    "sg:city":"Deventer",
    "sg:orig_category":"Wasmachines En Wasdrogers",
    "sg:phone":"+31 570 677 311",
    "sg:postcode":"7411 MB",
    "sg:province":"Overijssel",
    "wof:name":"Cents, J J",
    "wof:placetype":"venue"
},
  "geometry": {"coordinates":[6.1696681976,52.2489776611],"type":"Point"}
}