{
  "type": "Feature",
  "properties": {
    "iso:country":"NL",
    "sg:address":"Populierendreef 982",
    "sg:city":"Voorburg",
    "sg:orig_category":"Verhuizingen",
    "sg:phone":"+31 70 386 3215",
    "sg:postcode":"2272 HX",
    "sg:province":"Zuid-Holland",
    "sg:website":"http://www.zaat.nl",
    "wof:name":"Zaat Anno 1870",
    "wof:placetype":"venue"
},
  "geometry": {"coordinates":[4.361156,52.084419],"type":"Point"}
}