{
  "type": "Feature",
  "properties": {
    "addr:full":"Pr Karelstr 75 Helmond Noord-Brabant 5701 VK",
    "addr:housenumber":"75",
    "addr:postcode":"5701 vk",
    "iso:country":"NL",
    "sg:address":"Pr Karelstr 75",
    "sg:city":"Helmond",
    "sg:orig_category":"Bloemen En Planten",
    "sg:phone":"+31 492 527 931",
    "sg:postcode":"5701 VK",
    "sg:province":"Noord-Brabant",
    "wof:name":"Silvia",
    "wof:placetype":"venue"
},
  "geometry": {"coordinates":[5.671847,51.479855],"type":"Point"}
}