{
  "type": "Feature",
  "properties": {
    "addr:full":"Beekeerdhamel 17 Assen Provincie Drenthe 9403 XA",
    "addr:housenumber":"17",
    "addr:postcode":"9403 xa",
    "addr:street":"Beekeerdhamel;Provincie Drenthe",
    "iso:country":"NL",
    "sg:address":"Beekeerdhamel 17",
    "sg:city":"Assen",
    "sg:orig_category":"Kappers",
    "sg:phone":"+31 592 409 056",
    "sg:postcode":"9403 XA",
    "sg:province":"Provincie Drenthe",
    "wof:name":"Kniptiek",
    "wof:placetype":"venue"
},
  "geometry": {"coordinates":[6.596745,53.018749],"type":"Point"}
}