{
  "type": "Feature",
  "properties": {
    "addr:full":"Laagraven 15 Nieuwegein Utrecht 3439 LG",
    "addr:housenumber":"15",
    "addr:postcode":"3439 lg",
    "addr:street":"Laagraven",
    "iso:country":"NL",
    "sg:address":"Laagraven 15",
    "sg:city":"Nieuwegein",
    "sg:orig_category":"Voeding, Dranken And Tabak Gh",
    "sg:phone":"+31 30 288 7042",
    "sg:postcode":"3439 LG",
    "sg:province":"Utrecht",
    "wof:name":"Levimex Bv",
    "wof:placetype":"venue"
},
  "geometry": {"coordinates":[5.124637,52.053471],"type":"Point"}
}