{
  "type": "Feature",
  "properties": {
    "addr:full":"D J V Wykstr 30 Geldermalsen Gelderland 4191 ND",
    "addr:housenumber":"30",
    "addr:postcode":"4191 nd",
    "addr:street":"Wykstr;Gelderland",
    "iso:country":"NL",
    "sg:address":"D J V Wykstr 30",
    "sg:city":"Geldermalsen",
    "sg:orig_category":"Modevakscholen",
    "sg:phone":"+31 345 573 179",
    "sg:postcode":"4191 ND",
    "sg:province":"Gelderland",
    "wof:name":"Ensaid",
    "wof:placetype":"venue"
},
  "geometry": {"coordinates":[5.2898988724,51.8828125],"type":"Point"}
}