{
  "type": "Feature",
  "properties": {
    "addr:full":"Denneweg 33 'S Gravenhage Zuid-Holland 2514 CC",
    "addr:housenumber":"33",
    "addr:postcode":"2514 cc",
    "addr:street":"Denneweg;' S",
    "iso:country":"NL",
    "sg:address":"Denneweg 33",
    "sg:city":"'S Gravenhage",
    "sg:orig_category":"Boekenuitgeverijen",
    "sg:phone":"+31 70 345 6872",
    "sg:postcode":"2514 CC",
    "sg:province":"Zuid-Holland",
    "wof:name":"Kornelius",
    "wof:placetype":"venue"
},
  "geometry": {"coordinates":[4.312412,52.085487],"type":"Point"}
}