{
  "type": "Feature",
  "properties": {
    "iso:country":"NL",
    "sg:address":"Jan Evertsenweg 38",
    "sg:city":"Schiedam",
    "sg:orig_category":"Schilderwerk",
    "sg:phone":"+31 10 426 7474",
    "sg:postcode":"3115 JA",
    "sg:province":"Zuid-Holland",
    "wof:name":"Willems Schilderwerken Bv",
    "wof:placetype":"venue"
},
  "geometry": {"coordinates":[4.381367,51.909145],"type":"Point"}
}