{
  "type": "Feature",
  "properties": {
    "addr:full":"Ekkersrijt 16 Tilburg North Brabant 5032 WP",
    "addr:housenumber":"16",
    "addr:postcode":"5032 wp",
    "addr:street":"Ekkersrijt",
    "iso:country":"NL",
    "sg:address":"Ekkersrijt 16",
    "sg:city":"Tilburg",
    "sg:orig_category":"Boekhouders",
    "sg:phone":"+31 13 467 0741",
    "sg:postcode":"5032 WP",
    "sg:province":"North Brabant",
    "wof:name":"Boekhoudbureau J.M. Donders",
    "wof:placetype":"venue"
},
  "geometry": {"coordinates":[5.044781,51.548279],"type":"Point"}
}