{
  "type": "Feature",
  "properties": {
    "addr:full":"J Beeldsnyderwg 11 Deventer NL.08 7424 AM",
    "addr:housenumber":"11;nl.08",
    "addr:postcode":"7424",
    "iso:country":"NL",
    "sg:address":"J Beeldsnyderwg 11",
    "sg:city":"Deventer",
    "sg:orig_category":"Huidtherapeuten",
    "sg:phone":"+31 570 514 314",
    "sg:postcode":"7424 AM",
    "sg:province":"NL.08",
    "wof:name":"Eerten, A L Van",
    "wof:placetype":"venue"
},
  "geometry": {"coordinates":[6.220657,52.2616],"type":"Point"}
}