{
  "type": "Feature",
  "properties": {
    "addr:full":"Hammerwg 69 Ommen NL.08 7731 AL",
    "addr:housenumber":"69;nl.08",
    "addr:postcode":"7731 al",
    "addr:street":"Hammerwg",
    "iso:country":"NL",
    "sg:address":"Hammerwg 69",
    "sg:city":"Ommen",
    "sg:orig_category":"Vertaalbureaus",
    "sg:phone":"+31 529 456 117",
    "sg:postcode":"7731 AL",
    "sg:province":"NL.08",
    "wof:name":"Austral Translations",
    "wof:placetype":"venue"
},
  "geometry": {"coordinates":[6.455448,52.48856],"type":"Point"}
}