{
  "type": "Feature",
  "properties": {
    "iso:country":"NL",
    "sg:address":"L Groenendaal 42",
    "sg:city":"Gouda",
    "sg:orig_category":"Wereldwinkels",
    "sg:phone":"+31 182 525 260",
    "sg:postcode":"2801 LT",
    "sg:province":"Zuid-Holland",
    "wof:name":"Wereldwinkel",
    "wof:placetype":"venue"
},
  "geometry": {"coordinates":[4.7085828781,52.0111808777],"type":"Point"}
}