{
  "type": "Feature",
  "properties": {
    "iso:country":"NL",
    "sg:address":"Oosterkade 7",
    "sg:city":"Groningen",
    "sg:orig_category":"Dumpgoederen",
    "sg:phone":"+31 50 313 4691",
    "sg:postcode":"9711 RS",
    "sg:province":"Groningen",
    "wof:name":"Army Navy Store",
    "wof:placetype":"venue"
},
  "geometry": {"coordinates":[6.578115,53.216763],"type":"Point"}
}