{
  "type": "Feature",
  "properties": {
    "addr:full":"Patentweg 10 Terneuzen Zeeland 4538 BR",
    "addr:housenumber":"10",
    "addr:postcode":"4538 br",
    "addr:street":"Patentweg",
    "iso:country":"NL",
    "sg:address":"Patentweg 10",
    "sg:city":"Terneuzen",
    "sg:orig_category":"Administratie- En Boekhoudkantoren",
    "sg:phone":"+31 115 697 055",
    "sg:postcode":"4538 BR",
    "sg:province":"Zeeland",
    "wof:name":"Adz",
    "wof:placetype":"venue"
},
  "geometry": {"coordinates":[3.850183,51.305588],"type":"Point"}
}