{
  "type": "Feature",
  "properties": {
    "addr:full":"Wilhelminastraat 22 Velp Gld Gelderland 6881 LJ",
    "addr:housenumber":"22;lj",
    "addr:postcode":"6881",
    "addr:street":"Wilhelminastraat;Gld Gelderland",
    "iso:country":"NL",
    "sg:address":"Wilhelminastraat 22",
    "sg:city":"Velp Gld",
    "sg:orig_category":"Autokeuringen",
    "sg:phone":"+31 26 361 3100",
    "sg:postcode":"6881 LJ",
    "sg:province":"Gelderland",
    "wof:name":"J.P. Wijlhuizen",
    "wof:placetype":"venue"
},
  "geometry": {"coordinates":[5.970943,51.997581],"type":"Point"}
}