{
  "type": "Feature",
  "properties": {
    "addr:full":"Wagnerlaan 2 Arnhem Gelderland 6815 AG",
    "addr:housenumber":"2",
    "addr:postcode":"6815",
    "addr:street":"Wagnerlaan",
    "iso:country":"NL",
    "sg:address":"Wagnerlaan 2",
    "sg:city":"Arnhem",
    "sg:orig_category":"Kinderopvang Behalve Thuis",
    "sg:phone":"+31 26 443 8627",
    "sg:postcode":"6815 AG",
    "sg:province":"Gelderland",
    "wof:name":"Kinderdagverblijf De Brummel",
    "wof:placetype":"venue"
},
  "geometry": {"coordinates":[5.909601,51.998894],"type":"Point"}
}