{
  "type": "Feature",
  "properties": {
    "addr:full":"Walewg 12 Stryen South Holland 3291 AX",
    "addr:housenumber":"12",
    "addr:postcode":"3291 ax",
    "addr:street":"Walewg",
    "iso:country":"NL",
    "sg:address":"Walewg 12",
    "sg:city":"Stryen",
    "sg:orig_category":"Bloemen En Planten",
    "sg:phone":"+31 78 674 2162",
    "sg:postcode":"3291 AX",
    "sg:province":"South Holland",
    "wof:name":"Nes Bv, Van",
    "wof:placetype":"venue"
},
  "geometry": {"coordinates":[4.54727,51.750832],"type":"Point"}
}