{
  "type": "Feature",
  "properties": {
    "addr:full":"Rederystr 13B Katwyk Zh Zuid-Holland 2224 RB",
    "addr:housenumber":"13b katwyk",
    "addr:postcode":"2224 rb",
    "addr:street":"Rederystr",
    "iso:country":"NL",
    "sg:address":"Rederystr 13B",
    "sg:city":"Katwyk Zh",
    "sg:orig_category":"Vis En Visproducten - Groothandel",
    "sg:phone":"+31 71 402 9798",
    "sg:postcode":"2224 RB",
    "sg:province":"Zuid-Holland",
    "sg:website":"http://www.schuitemaker-vis.nl",
    "wof:name":"Schuitemaker Vishandel Bv",
    "wof:placetype":"venue"
},
  "geometry": {"coordinates":[4.42057,52.187599],"type":"Point"}
}