{
  "type": "Feature",
  "properties": {
    "addr:full":"Burgemeester Mooijstraat 32 Castricum Noord-Holland 1901 ET",
    "addr:housenumber":"32",
    "addr:postcode":"1901 et",
    "addr:street":"Burgemeester Mooijstraat",
    "iso:country":"NL",
    "sg:address":"Burgemeester Mooijstraat 32",
    "sg:city":"Castricum",
    "sg:orig_category":"Zuivelproducten",
    "sg:phone":"+31 251 655 251",
    "sg:postcode":"1901 ET",
    "sg:province":"Noord-Holland",
    "wof:name":"Kaaswinkeltje",
    "wof:placetype":"venue"
},
  "geometry": {"coordinates":[4.659166,52.546181],"type":"Point"}
}