{
  "type": "Feature",
  "properties": {
    "iso:country":"NL",
    "sg:address":"Beethovenlaan 37",
    "sg:city":"Bergschenhoek",
    "sg:orig_category":"Vertaal- And Tolkenbureaus",
    "sg:phone":"+31 10 521 5975",
    "sg:postcode":"2661 HA",
    "sg:province":"Zuid-Holland",
    "wof:name":"Ne-Ro Connection",
    "wof:placetype":"venue"
},
  "geometry": {"coordinates":[4.501354,51.986038],"type":"Point"}
}