{
  "type": "Feature",
  "properties": {
    "addr:full":"Houtwg 32 Laren Nh North Holland 1251 CT",
    "addr:housenumber":"32",
    "addr:postcode":"1251 ct",
    "addr:street":"Houtwg;Nh North",
    "iso:country":"NL",
    "sg:address":"Houtwg 32",
    "sg:city":"Laren Nh",
    "sg:orig_category":"Organisatiebureaus",
    "sg:phone":"+31 35 531 6372",
    "sg:postcode":"1251 CT",
    "sg:province":"North Holland",
    "wof:name":"In & Out Bv",
    "wof:placetype":"venue"
},
  "geometry": {"coordinates":[5.2115402222,52.2564201355],"type":"Point"}
}