{
  "type": "Feature",
  "properties": {
    "addr:full":"Jansbinnensngl 12 Arnhem Gelderland 6811 AJ",
    "addr:housenumber":"12",
    "addr:postcode":"6811 aj",
    "addr:street":"Jansbinnensngl",
    "iso:country":"NL",
    "sg:address":"Jansbinnensngl 12",
    "sg:city":"Arnhem",
    "sg:orig_category":"Herenkleding",
    "sg:phone":"+31 26 442 4518",
    "sg:postcode":"6811 AJ",
    "sg:province":"Gelderland",
    "wof:name":"High & Mighty",
    "wof:placetype":"venue"
},
  "geometry": {"coordinates":[5.908642,51.984116],"type":"Point"}
}