{
  "type": "Feature",
  "properties": {
    "iso:country":"NL",
    "sg:address":"Goudsbloemlaan 130",
    "sg:city":"'S Gravenhage",
    "sg:orig_category":"Kappers",
    "sg:phone":"+31 70 363 4027",
    "sg:postcode":"2565 CW",
    "sg:province":"Zuid-Holland",
    "wof:name":"Salon Asti",
    "wof:placetype":"venue"
},
  "geometry": {"coordinates":[4.259393,52.076584],"type":"Point"}
}