{
  "type": "Feature",
  "properties": {
    "addr:full":"Vestdijk 159 Eindhoven Noord-Brabant 5611 CB",
    "addr:housenumber":"159",
    "addr:postcode":"5611 cb",
    "addr:street":"Vestdijk",
    "iso:country":"NL",
    "sg:address":"Vestdijk 159",
    "sg:city":"Eindhoven",
    "sg:orig_category":"Wasserettes And Stomerijen",
    "sg:phone":"+31 40 212 7747",
    "sg:postcode":"5611 CB",
    "sg:province":"Noord-Brabant",
    "wof:name":"Les Amis",
    "wof:placetype":"venue"
},
  "geometry": {"coordinates":[5.4862928391,51.4350814819],"type":"Point"}
}