{
  "type": "Feature",
  "properties": {
    "addr:full":"Calandwg 35 Bergen Op Zoom Noord-Brabant 4612 PG",
    "addr:housenumber":"35",
    "addr:postcode":"4612 pg",
    "addr:street":"Calandwg",
    "iso:country":"NL",
    "sg:address":"Calandwg 35",
    "sg:city":"Bergen Op Zoom",
    "sg:orig_category":"Kermisexploitatie",
    "sg:phone":"+31 164 255 570",
    "sg:postcode":"4612 PG",
    "sg:province":"Noord-Brabant",
    "wof:name":"Schimmelpenninck, A M J A",
    "wof:placetype":"venue"
},
  "geometry": {"coordinates":[4.265815,51.492729],"type":"Point"}
}