{
  "type": "Feature",
  "properties": {
    "addr:full":"Postbus 806 Leiden Zuid-Holland 2300 AV",
    "addr:housenumber":"806",
    "addr:postcode":"2300 av",
    "addr:street":"Postbus",
    "iso:country":"NL",
    "sg:address":"Postbus 806",
    "sg:city":"Leiden",
    "sg:orig_category":"Verbouwingen",
    "sg:phone":"+31 71 579 0596",
    "sg:postcode":"2300 AV",
    "sg:province":"Zuid-Holland",
    "wof:name":"Mul, Jan De",
    "wof:placetype":"venue"
},
  "geometry": {"coordinates":[4.49015,52.161091],"type":"Point"}
}