{
  "type": "Feature",
  "properties": {
    "iso:country":"NL",
    "sg:address":"Kolk 29",
    "sg:city":"Brielle",
    "sg:classifiers":[
        {
            "category":"Food & Beverages",
            "subcategory":"Candy",
            "type":"Retail Goods"
        }
    ],
    "sg:phone":"+31 181 416 526",
    "sg:postcode":"3232 EE",
    "sg:province":"Zuid-Holland",
    "sg:tags":[
        "sport-",
        "en",
        "spelartikelen"
    ],
    "wof:name":"Vroco",
    "wof:placetype":"venue"
},
  "geometry": {"coordinates":[4.166849,51.894821],"type":"Point"}
}