{
  "type": "Feature",
  "properties": {
    "addr:full":"Venrayseweg 100 Venlo Limburg 5928 RH",
    "addr:housenumber":"100",
    "addr:postcode":"5928 rh",
    "addr:street":"Venrayseweg",
    "iso:country":"NL",
    "sg:address":"Venrayseweg 100",
    "sg:city":"Venlo",
    "sg:orig_category":"Fruit And Groenten Gh",
    "sg:phone":"+31 77 324 1241",
    "sg:postcode":"5928 RH",
    "sg:province":"Limburg",
    "wof:name":"Aartsenfruit Venlo Bv",
    "wof:placetype":"venue"
},
  "geometry": {"coordinates":[6.132745,51.40218],"type":"Point"}
}