{
  "type": "Feature",
  "properties": {
    "addr:full":"Rivierdk 31 Hardinxv Giessend Zuid-Holland 3372 BE",
    "addr:housenumber":"31;giessend",
    "addr:postcode":"3372",
    "addr:street":"Rivierdk",
    "iso:country":"NL",
    "sg:address":"Rivierdk 31",
    "sg:city":"Hardinxv Giessend",
    "sg:orig_category":"Baggerwerken",
    "sg:phone":"+31 184 615 820",
    "sg:postcode":"3372 BE",
    "sg:province":"Zuid-Holland",
    "wof:name":"Zevenmorgen Vof",
    "wof:placetype":"venue"
},
  "geometry": {"coordinates":[7.693745,47.199856],"type":"Point"}
}