{
  "type": "Feature",
  "properties": {
    "addr:full":"Rutselbosln 5 Oosterhout Nb Noord-Brabant 4901 MD",
    "addr:housenumber":"5",
    "addr:postcode":"4901",
    "addr:street":"Rutselbosln",
    "iso:country":"NL",
    "sg:address":"Rutselbosln 5",
    "sg:city":"Oosterhout Nb",
    "sg:orig_category":"Zonweringen",
    "sg:phone":"+31 162 424 651",
    "sg:postcode":"4901 MD",
    "sg:province":"Noord-Brabant",
    "wof:name":"Bogerd, J",
    "wof:placetype":"venue"
},
  "geometry": {"coordinates":[4.864321,51.646366],"type":"Point"}
}