{
  "type": "Feature",
  "properties": {
    "addr:full":"T Zuden 111 Leek Groningen 9351 LD",
    "addr:housenumber":"111",
    "addr:postcode":"9351 ld",
    "addr:street":"T Zuden",
    "iso:country":"NL",
    "sg:address":"T Zuden 111",
    "sg:city":"Leek",
    "sg:orig_category":"Autorijscholen",
    "sg:phone":"+31 594 512 257",
    "sg:postcode":"9351 LD",
    "sg:province":"Groningen",
    "wof:name":"Veninga",
    "wof:placetype":"venue"
},
  "geometry": {"coordinates":[6.370884,53.165928],"type":"Point"}
}