{
  "type": "Feature",
  "properties": {
    "addr:full":"Schuttersbergweg 21 Arnhem Gelderland 6823 KE",
    "addr:housenumber":"21",
    "addr:postcode":"6823 ke",
    "addr:street":"Schuttersbergweg",
    "iso:country":"NL",
    "sg:address":"Schuttersbergweg 21",
    "sg:city":"Arnhem",
    "sg:orig_category":"Kappers",
    "sg:phone":"+31 26 443 2924",
    "sg:postcode":"6823 KE",
    "sg:province":"Gelderland",
    "wof:name":"Fa Budel-Evers",
    "wof:placetype":"venue"
},
  "geometry": {"coordinates":[5.9382767677,52.0028915405],"type":"Point"}
}