{
  "type": "Feature",
  "properties": {
    "addr:full":"Engelandswg 33 Wezep Gelderland 8091 BA",
    "addr:housenumber":"33",
    "addr:postcode":"8091 ba",
    "addr:street":"Engelandswg",
    "iso:country":"NL",
    "sg:address":"Engelandswg 33",
    "sg:city":"Wezep",
    "sg:classifiers":[
        {
            "category":"Retail",
            "subcategory":"Auto Repair",
            "type":"Services"
        }
    ],
    "sg:phone":"+31 38 376 5443",
    "sg:postcode":"8091 BA",
    "sg:province":"Gelderland",
    "sg:tags":[
        "garage"
    ],
    "wof:name":"Bosman Auto'S",
    "wof:placetype":"venue"
},
  "geometry": {"coordinates":[5.983965,52.44976],"type":"Point"}
}