{
  "type": "Feature",
  "properties": {
    "addr:full":"H V Deventerstr 45 S Gravenhage South Holland 2563 XP",
    "addr:housenumber":"45",
    "addr:postcode":"2563 xp",
    "addr:street":"H V Deventerstr;S Gravenhage",
    "iso:country":"NL",
    "sg:address":"H V Deventerstr 45",
    "sg:city":"S Gravenhage",
    "sg:orig_category":"Verenigingsgebouwen",
    "sg:phone":"+31 70 345 9342",
    "sg:postcode":"2563 XP",
    "sg:province":"South Holland",
    "wof:name":"Westhoek, Sticht De",
    "wof:placetype":"venue"
},
  "geometry": {"coordinates":[4.270956,52.072578],"type":"Point"}
}