{
  "type": "Feature",
  "properties": {
    "addr:full":"Hegedk 8 Gorredyk Friesland 8401 BJ",
    "addr:housenumber":"8",
    "addr:postcode":"8401 bj",
    "addr:street":"Hegedk",
    "iso:country":"NL",
    "sg:address":"Hegedk 8",
    "sg:city":"Gorredyk",
    "sg:orig_category":"Artsen - Huisartsen",
    "sg:phone":"+31 513 461 324",
    "sg:postcode":"8401 BJ",
    "sg:province":"Friesland",
    "wof:name":"Egmond & H Gjaltema, N Van",
    "wof:placetype":"venue"
},
  "geometry": {"coordinates":[6.06033,52.99992],"type":"Point"}
}