{
  "type": "Feature",
  "properties": {
    "addr:full":"Zuidendk 310 Dordrecht Zuid-Holland 3329 LD",
    "addr:housenumber":"310",
    "addr:postcode":"3329 ld",
    "iso:country":"NL",
    "sg:address":"Zuidendk 310",
    "sg:city":"Dordrecht",
    "sg:orig_category":"Accountants - Administratie- Consulenten En -Kantoren",
    "sg:phone":"+31 78 616 6668",
    "sg:postcode":"3329 LD",
    "sg:province":"Zuid-Holland",
    "wof:name":"Veld, In'T",
    "wof:placetype":"venue"
},
  "geometry": {"coordinates":[4.734816,51.789303],"type":"Point"}
}