{
  "type": "Feature",
  "properties": {
    "addr:full":"Postbus 1024 Groningen Noord-Holland 9701 BA",
    "addr:housenumber":"1024",
    "addr:postcode":"9701 ba",
    "addr:street":"Postbus",
    "iso:country":"NL",
    "sg:address":"Postbus 1024",
    "sg:city":"Groningen",
    "sg:orig_category":"Hulpverlening Sociaal",
    "sg:phone":"+31 50 588 7500",
    "sg:postcode":"9701 BA",
    "sg:province":"Noord-Holland",
    "sg:website":"http://www.avg.nl",
    "wof:name":"Verslavingszorg Groningen",
    "wof:placetype":"venue"
},
  "geometry": {"coordinates":[6.56502,53.21645],"type":"Point"}
}