{
  "type": "Feature",
  "properties": {
    "iso:country":"NL",
    "sg:address":"Bretagne 14",
    "sg:city":"Leusden",
    "sg:orig_category":"Psychotherapeuten",
    "sg:phone":"+31 33 432 4362",
    "sg:postcode":"3831 EN",
    "sg:province":"Utrecht",
    "wof:name":"Pannekoek, Drs F A E",
    "wof:placetype":"venue"
},
  "geometry": {"coordinates":[5.436475,52.133465],"type":"Point"}
}