{
  "type": "Feature",
  "properties": {
    "addr:full":"Jhr D S Lohmanstr 37 Ridderkerk Zuid-Holland 2982 RA",
    "addr:housenumber":"37",
    "addr:postcode":"2982 ra",
    "addr:street":"Jhr D S Lohmanstr",
    "iso:country":"NL",
    "sg:address":"Jhr D S Lohmanstr 37",
    "sg:city":"Ridderkerk",
    "sg:orig_category":"Betonwerken",
    "sg:phone":"+31 180 428 439",
    "sg:postcode":"2982 RA",
    "sg:province":"Zuid-Holland",
    "wof:name":"Slingerland, A C P",
    "wof:placetype":"venue"
},
  "geometry": {"coordinates":[4.594622,51.873947],"type":"Point"}
}