{
  "type": "Feature",
  "properties": {
    "iso:country":"NL",
    "sg:address":"Barbaraln 60",
    "sg:city":"Breda",
    "sg:orig_category":"Loodgieters",
    "sg:phone":"+31 76 565 1529",
    "sg:postcode":"4834 SK",
    "sg:province":"Noord-Brabant",
    "wof:name":"Hendriks, Frank",
    "wof:placetype":"venue"
},
  "geometry": {"coordinates":[4.80125,51.56654],"type":"Point"}
}