{
  "type": "Feature",
  "properties": {
    "addr:full":"Kl Broekstr 8 Boxmeer North Brabant 5831 AP",
    "addr:housenumber":"8",
    "addr:postcode":"5831 ap",
    "iso:country":"NL",
    "sg:address":"Kl Broekstr 8",
    "sg:city":"Boxmeer",
    "sg:orig_category":"Pluimveeslachterijen",
    "sg:phone":"+31 485 593 939",
    "sg:postcode":"5831 AP",
    "sg:province":"North Brabant",
    "sg:website":"http://www.friki.com",
    "wof:name":"Dtc Bv",
    "wof:placetype":"venue"
},
  "geometry": {"coordinates":[5.937523,51.641254],"type":"Point"}
}