{
  "type": "Feature",
  "properties": {
    "addr:full":"V Cleefstr 1 Venlo Limburg 5911 BD",
    "addr:housenumber":"1",
    "addr:postcode":"5911 bd",
    "addr:street":"Cleefstr",
    "iso:country":"NL",
    "sg:address":"V Cleefstr 1",
    "sg:city":"Venlo",
    "sg:classifiers":[
        {
            "category":"Professional",
            "subcategory":"Accounting & Tax Preparation",
            "type":"Services"
        }
    ],
    "sg:phone":"+31 77 354 9955",
    "sg:postcode":"5911 BD",
    "sg:province":"Limburg",
    "sg:tags":[
        "accountant",
        "en",
        "-kantoren",
        "register-"
    ],
    "wof:name":"Frische, H J M",
    "wof:placetype":"venue"
},
  "geometry": {"coordinates":[6.17286,51.372421],"type":"Point"}
}