{
  "type": "Feature",
  "properties": {
    "addr:full":"Nw Bredase Baan 4 Breda Noord-Brabant 4825 BP",
    "addr:housenumber":"4",
    "addr:postcode":"4825 bp",
    "addr:street":"Nw Bredase Baan",
    "iso:country":"NL",
    "sg:address":"Nw Bredase Baan 4",
    "sg:city":"Breda",
    "sg:orig_category":"Kunstmest",
    "sg:phone":"+31 76 571 2620",
    "sg:postcode":"4825 BP",
    "sg:province":"Noord-Brabant",
    "wof:name":"Reijt Bv, Van De",
    "wof:placetype":"venue"
},
  "geometry": {"coordinates":[4.769305,51.62178],"type":"Point"}
}