{
  "type": "Feature",
  "properties": {
    "addr:full":"D Kleimanstr 17 Zaandam Noord-Holland 1502 XE",
    "addr:housenumber":"17",
    "addr:postcode":"1502 xe",
    "iso:country":"NL",
    "sg:address":"D Kleimanstr 17",
    "sg:city":"Zaandam",
    "sg:orig_category":"Kunsthandel",
    "sg:phone":"+31 75 670 6333",
    "sg:postcode":"1502 XE",
    "sg:province":"Noord-Holland",
    "wof:name":"Art Trading",
    "wof:placetype":"venue"
},
  "geometry": {"coordinates":[4.833233,52.442738],"type":"Point"}
}