{
  "type": "Feature",
  "properties": {
    "addr:full":"Dwars Havenstr 7 Leiden Zuid-Holland 2312 MC",
    "addr:housenumber":"7",
    "addr:postcode":"2312 mc",
    "iso:country":"NL",
    "sg:address":"Dwars Havenstr 7",
    "sg:city":"Leiden",
    "sg:orig_category":"Adviesbureaus Bedrijfsorganisatie",
    "sg:phone":"+31 71 522 0956",
    "sg:postcode":"2312 MC",
    "sg:province":"Zuid-Holland",
    "sg:website":"http://www.mobilecontrol.nl",
    "wof:name":"Mobile Control",
    "wof:placetype":"venue"
},
  "geometry": {"coordinates":[4.501813,52.161915],"type":"Point"}
}