{
  "type": "Feature",
  "properties": {
    "addr:full":"Holysingel 400 Vlaardingen South Holland 3136 LH",
    "addr:housenumber":"400",
    "addr:postcode":"3136 lh",
    "addr:street":"Holysingel",
    "iso:country":"NL",
    "sg:address":"Holysingel 400",
    "sg:city":"Vlaardingen",
    "sg:orig_category":"Vertaal- And Tolkenbureaus",
    "sg:phone":"+31 10 474 4540",
    "sg:postcode":"3136 LH",
    "sg:province":"South Holland",
    "wof:name":"Inter Cartier",
    "wof:placetype":"venue"
},
  "geometry": {"coordinates":[4.345309,51.926685],"type":"Point"}
}