{
  "type": "Feature",
  "properties": {
    "addr:full":"Haegenbroek 3 Weert Limburg 6002 WG",
    "addr:housenumber":"3",
    "addr:postcode":"6002 wg",
    "addr:street":"Haegenbroek",
    "iso:country":"NL",
    "sg:address":"Haegenbroek 3",
    "sg:city":"Weert",
    "sg:orig_category":"Wasserettes, Stomerijen And Reiniging",
    "sg:phone":"+31 495 532 360",
    "sg:postcode":"6002 WG",
    "sg:province":"Limburg",
    "wof:name":"Chemdry",
    "wof:placetype":"venue"
},
  "geometry": {"coordinates":[5.691411972,51.2618598938],"type":"Point"}
}