{
  "type": "Feature",
  "properties": {
    "addr:full":"Winston Churchilllaan 21C Spijkenisse Zuid-Holland 3202 GN",
    "addr:housenumber":"21c",
    "addr:postcode":"3202 gn",
    "addr:street":"Winston Churchilllaan",
    "iso:country":"NL",
    "sg:address":"Winston Churchilllaan 21C",
    "sg:city":"Spijkenisse",
    "sg:orig_category":"Paramedische Behandelingen",
    "sg:phone":"+31 181 626 168",
    "sg:postcode":"3202 GN",
    "sg:province":"Zuid-Holland",
    "wof:name":"C.M.J. Legen-Eijgenraam",
    "wof:placetype":"venue"
},
  "geometry": {"coordinates":[4.3163318634,51.8540840149],"type":"Point"}
}