{
  "type": "Feature",
  "properties": {
    "addr:full":"Julianastraat 19 Belfeld Limburg 5951 CG",
    "addr:housenumber":"19",
    "addr:postcode":"5951 cg",
    "addr:street":"Julianastraat",
    "iso:country":"NL",
    "sg:address":"Julianastraat 19",
    "sg:city":"Belfeld",
    "sg:orig_category":"Diverse Consumentenartikelen Gh",
    "sg:phone":"+31 77 475 1665",
    "sg:postcode":"5951 CG",
    "sg:province":"Limburg",
    "wof:name":"Brauer Agenturen Nederland",
    "wof:placetype":"venue"
},
  "geometry": {"coordinates":[6.112755,51.311264],"type":"Point"}
}