{
  "type": "Feature",
  "properties": {
    "addr:full":"Haastenburg 126 Gouda Zuid-Holland 2804 VE",
    "addr:housenumber":"126",
    "addr:postcode":"2804",
    "addr:street":"Haastenburg;Ve",
    "iso:country":"NL",
    "sg:address":"Haastenburg 126",
    "sg:city":"Gouda",
    "sg:orig_category":"Elektronica - Ontwikkeling En Groothandel",
    "sg:phone":"+31 182 532 218",
    "sg:postcode":"2804 VE",
    "sg:province":"Zuid-Holland",
    "wof:name":"Herk, Van",
    "wof:placetype":"venue"
},
  "geometry": {"coordinates":[4.702701,52.029648],"type":"Point"}
}