{
  "type": "Feature",
  "properties": {
    "addr:full":"Akerdijk 275 Badhoevedorp Noord-Holland 1171 RC",
    "addr:housenumber":"275",
    "addr:postcode":"1171 rc",
    "addr:street":"Akerdijk",
    "iso:country":"NL",
    "sg:address":"Akerdijk 275",
    "sg:city":"Badhoevedorp",
    "sg:orig_category":"Autokeuringen",
    "sg:phone":"+31 20 659 2915",
    "sg:postcode":"1171 RC",
    "sg:province":"Noord-Holland",
    "wof:name":"Garagebedrijf Henriet",
    "wof:placetype":"venue"
},
  "geometry": {"coordinates":[4.784675,52.343777],"type":"Point"}
}