{
  "type": "Feature",
  "properties": {
    "addr:full":"Singel 87 Bussum Noord-Holland 1402 NR",
    "addr:housenumber":"87",
    "addr:postcode":"1402 nr",
    "addr:street":"Singel",
    "iso:country":"NL",
    "sg:address":"Singel 87",
    "sg:city":"Bussum",
    "sg:classifiers":[
        {
            "category":"Fast Food",
            "type":"Food & Drink"
        }
    ],
    "sg:phone":"+31 35 693 2141",
    "sg:postcode":"1402 NR",
    "sg:province":"Noord-Holland",
    "sg:tags":[
        "afhaal",
        "restaurant"
    ],
    "wof:name":"Henk Snackbar",
    "wof:placetype":"venue"
},
  "geometry": {"coordinates":[5.170282,52.271576],"type":"Point"}
}