{
  "type": "Feature",
  "properties": {
    "addr:full":"Gaasterwg 5 Rotsterhaule Provincie Friesland 8463 TK",
    "addr:housenumber":"5",
    "addr:postcode":"8463 tk",
    "addr:street":"Gaasterwg;Provincie Friesland",
    "iso:country":"NL",
    "sg:address":"Gaasterwg 5",
    "sg:city":"Rotsterhaule",
    "sg:orig_category":"Paardenhandelaren",
    "sg:phone":"+31 513 551 389",
    "sg:postcode":"8463 TK",
    "sg:province":"Provincie Friesland",
    "wof:name":"Soeting, S",
    "wof:placetype":"venue"
},
  "geometry": {"coordinates":[5.86499,52.912296],"type":"Point"}
}