{
  "type": "Feature",
  "properties": {
    "iso:country":"NL",
    "sg:address":"Boekweitstr 31",
    "sg:city":"Nieuw Vennep",
    "sg:orig_category":"Cd'S, Grammofoonpl. En Muziekcass.-Maatschapp. En Grooth",
    "sg:phone":"+31 252 623 823",
    "sg:postcode":"2153 GK",
    "sg:province":"Noord-Holland",
    "sg:website":"http://www.unitedrecordings.com",
    "wof:name":"United Recordings Bv",
    "wof:placetype":"venue"
},
  "geometry": {"coordinates":[4.648876,52.265385],"type":"Point"}
}