{
  "type": "Feature",
  "properties": {
    "addr:full":"Catharinastr 12 Doetinchem Gelderland 7001 BZ",
    "addr:housenumber":"12",
    "addr:postcode":"7001 bz",
    "addr:street":"Catharinastr;Gelderland",
    "iso:country":"NL",
    "sg:address":"Catharinastr 12",
    "sg:city":"Doetinchem",
    "sg:orig_category":"Sportschoenen - Winkels",
    "sg:phone":"+31 314 354 277",
    "sg:postcode":"7001 BZ",
    "sg:province":"Gelderland",
    "wof:name":"Aktiesport",
    "wof:placetype":"venue"
},
  "geometry": {"coordinates":[6.288486,51.966648],"type":"Point"}
}