{
  "type": "Feature",
  "properties": {
    "addr:full":"Rietven 13 Goirle North Brabant 5051 BX",
    "addr:housenumber":"13",
    "addr:postcode":"5051 bx",
    "addr:street":"Rietven",
    "iso:country":"NL",
    "sg:address":"Rietven 13",
    "sg:city":"Goirle",
    "sg:orig_category":"Makelaars In Onroerend Goed",
    "sg:phone":"+31 13 534 5340",
    "sg:postcode":"5051 BX",
    "sg:province":"North Brabant",
    "wof:name":"Laurijssen & De Jong Bv",
    "wof:placetype":"venue"
},
  "geometry": {"coordinates":[5.056455,51.524857],"type":"Point"}
}