{
  "type": "Feature",
  "properties": {
    "iso:country":"NL",
    "sg:address":"Nw Kerkstr 21",
    "sg:city":"Sluiskil",
    "sg:orig_category":"Scholen Voor Basisonderwijs",
    "sg:phone":"+31 115 477 136",
    "sg:postcode":"4541 EB",
    "sg:province":"Zeeland",
    "wof:name":"Antonius, St",
    "wof:placetype":"venue"
},
  "geometry": {"coordinates":[3.835732,51.281387],"type":"Point"}
}