{
  "type": "Feature",
  "properties": {
    "addr:full":"Duinstr 9 Katwyk Zh Zuid-Holland 2225 RA",
    "addr:housenumber":"9",
    "addr:postcode":"2225 ra",
    "addr:street":"Duinstr",
    "iso:country":"NL",
    "sg:address":"Duinstr 9",
    "sg:city":"Katwyk Zh",
    "sg:orig_category":"Kappers",
    "sg:phone":"+31 71 401 6148",
    "sg:postcode":"2225 RA",
    "sg:province":"Zuid-Holland",
    "wof:name":"Eurostyle",
    "wof:placetype":"venue"
},
  "geometry": {"coordinates":[4.3965849876,52.2051086426],"type":"Point"}
}