{
  "type": "Feature",
  "properties": {
    "addr:full":"Kerkstr 33 S Gravendeel Zuid-Holland 3295 BD",
    "addr:housenumber":"33",
    "addr:postcode":"3295 bd",
    "addr:street":"Kerkstr;S Gravendeel",
    "iso:country":"NL",
    "sg:address":"Kerkstr 33",
    "sg:city":"S Gravendeel",
    "sg:orig_category":"Babyartikelen",
    "sg:phone":"+31 78 673 2404",
    "sg:postcode":"3295 BD",
    "sg:province":"Zuid-Holland",
    "wof:name":"Kids Baby",
    "wof:placetype":"venue"
},
  "geometry": {"coordinates":[4.61589,51.778774],"type":"Point"}
}