{
  "type": "Feature",
  "properties": {
    "iso:country":"NL",
    "sg:address":"De Konnighstr 28",
    "sg:city":"S Gravenzande",
    "sg:orig_category":"Loonbedrijven",
    "sg:phone":"+31 174 414 654",
    "sg:postcode":"2691 XK",
    "sg:province":"South Holland",
    "wof:name":"Konnighkracht Bv",
    "wof:placetype":"venue"
},
  "geometry": {"coordinates":[4.167139,52.003197],"type":"Point"}
}