{
  "type": "Feature",
  "properties": {
    "addr:full":"Flevostr 14 Lemmer Provincie Friesland 8531 KS",
    "addr:housenumber":"14",
    "addr:postcode":"8531 ks",
    "addr:street":"Flevostr;Provincie Friesland",
    "iso:country":"NL",
    "sg:address":"Flevostr 14",
    "sg:city":"Lemmer",
    "sg:orig_category":"Betonwerken",
    "sg:phone":"+31 514 568 800",
    "sg:postcode":"8531 KS",
    "sg:province":"Provincie Friesland",
    "wof:name":"Ijsselmeerbeton",
    "wof:placetype":"venue"
},
  "geometry": {"coordinates":[5.708611,52.847698],"type":"Point"}
}