{
  "type": "Feature",
  "properties": {
    "addr:full":"Kattenburgergracht 23 Amsterdam 1018 KN",
    "addr:housenumber":"23",
    "addr:postcode":"1018 kn",
    "addr:street":"Kattenburgergracht",
    "iso:country":"NL",
    "sg:address":"Kattenburgergracht 23",
    "sg:city":"Amsterdam",
    "sg:classifiers":[
        {
            "category":"Professional",
            "subcategory":"Computer Services",
            "type":"Services"
        }
    ],
    "sg:postcode":"1018 KN",
    "sg:tags":[
        "sell-content",
        "sell-articles",
        "sell-article",
        "sell-files",
        "sell-file",
        "sell-ebooks",
        "sell-ebook",
        "monetization",
        "making-money-online"
    ],
    "sg:website":"http://www.oronjo.com",
    "wof:name":"Oronjo",
    "wof:placetype":"venue"
},
  "geometry": {"coordinates":[4.917203,52.370331],"type":"Point"}
}