{
  "type": "Feature",
  "properties": {
    "addr:full":"Loskd 4 Zutphen Gelderland 7202 CZ",
    "addr:housenumber":"4;7202",
    "addr:street":"Loskd;Gelderland",
    "iso:country":"NL",
    "sg:address":"Loskd 4",
    "sg:city":"Zutphen",
    "sg:orig_category":"Drukkerijen",
    "sg:phone":"+31 575 585 300",
    "sg:postcode":"7202 CZ",
    "sg:province":"Gelderland",
    "wof:name":"W\u00f7Hrmann Bv",
    "wof:placetype":"venue"
},
  "geometry": {"coordinates":[6.191525,52.140202],"type":"Point"}
}