{
  "type": "Feature",
  "properties": {
    "iso:country":"NL",
    "sg:address":"Beslingadk 12",
    "sg:city":"Friens",
    "sg:orig_category":"Kappers",
    "sg:phone":"+31 566 601 689",
    "sg:postcode":"9009 XC",
    "sg:province":"Nebraska",
    "wof:name":"Marina",
    "wof:placetype":"venue"
},
  "geometry": {"coordinates":[-97.28701,40.654781],"type":"Point"}
}