{
  "type": "Feature",
  "properties": {
    "addr:full":"Postbus 37 Bedum Groningen 9780 AA",
    "addr:housenumber":"37",
    "addr:postcode":"9780 aa",
    "addr:street":"Postbus",
    "iso:country":"NL",
    "sg:address":"Postbus 37",
    "sg:city":"Bedum",
    "sg:orig_category":"Administratie- En Boekhoudkantoren",
    "sg:phone":"+31 50 301 6015",
    "sg:postcode":"9780 AA",
    "sg:province":"Groningen",
    "wof:name":"Groeneveld, J H",
    "wof:placetype":"venue"
},
  "geometry": {"coordinates":[6.597629,53.300678],"type":"Point"}
}