{
  "type": "Feature",
  "properties": {
    "iso:country":"NL",
    "sg:address":"J Vd Veerstr 6",
    "sg:city":"Den Helder",
    "sg:orig_category":"Autorijscholen",
    "sg:phone":"+31 223 645 247",
    "sg:postcode":"1786 AJ",
    "sg:province":"Noord-Holland",
    "wof:name":"Offerman, Raymond",
    "wof:placetype":"venue"
},
  "geometry": {"coordinates":[4.756594,52.896137],"type":"Point"}
}