{
  "type": "Feature",
  "properties": {
    "addr:full":"Hamminkwg 9 A Vorden Gelderland 7251 PZ",
    "addr:housenumber":"9 a",
    "addr:postcode":"7251 pz",
    "addr:street":"Hamminkwg;Gelderland",
    "iso:country":"NL",
    "sg:address":"Hamminkwg 9 A",
    "sg:city":"Vorden",
    "sg:orig_category":"Kappers",
    "sg:phone":"+31 575 552 816",
    "sg:postcode":"7251 PZ",
    "sg:province":"Gelderland",
    "wof:name":"Monique",
    "wof:placetype":"venue"
},
  "geometry": {"coordinates":[6.293025,52.085617],"type":"Point"}
}