{
  "type": "Feature",
  "properties": {
    "addr:full":"Mr. P.J. Troelstraweg 41E Leeuwarden Provincie Friesland 8916 AB",
    "addr:housenumber":"41e",
    "addr:postcode":"8916 ab",
    "addr:street":"Mr. P.J. Troelstraweg;Provincie Friesland",
    "iso:country":"NL",
    "sg:address":"Mr. P.J. Troelstraweg 41E",
    "sg:city":"Leeuwarden",
    "sg:orig_category":"Makelaars In Onroerend Goed",
    "sg:phone":"+31 58 216 0843",
    "sg:postcode":"8916 AB",
    "sg:province":"Provincie Friesland",
    "wof:name":"Barteld Boerma",
    "wof:placetype":"venue"
},
  "geometry": {"coordinates":[5.78498,53.208649],"type":"Point"}
}