{
  "type": "Feature",
  "properties": {
    "addr:full":"Ranonkelstr 50 Eindhoven Noord-Brabant 5644 LD",
    "addr:housenumber":"50",
    "addr:postcode":"5644 ld",
    "addr:street":"Ranonkelstr",
    "iso:country":"NL",
    "sg:address":"Ranonkelstr 50",
    "sg:city":"Eindhoven",
    "sg:orig_category":"Artiesten/Gezelschappen",
    "sg:phone":"+31 40 211 5363",
    "sg:postcode":"5644 LD",
    "sg:province":"Noord-Brabant",
    "sg:website":"http://www.rosnikovs.nl",
    "wof:name":"Rosnikovs",
    "wof:placetype":"venue"
},
  "geometry": {"coordinates":[5.486819,51.419605],"type":"Point"}
}