{
  "type": "Feature",
  "properties": {
    "addr:full":"Hoofdstraat 52 Best Noord-Brabant 5683 AG",
    "addr:housenumber":"52",
    "addr:postcode":"5683",
    "addr:street":"Hoofdstraat",
    "iso:country":"NL",
    "sg:address":"Hoofdstraat 52",
    "sg:city":"Best",
    "sg:classifiers":[
        {
            "category":"Professional",
            "subcategory":"Accounting & Tax Preparation",
            "type":"Services"
        }
    ],
    "sg:phone":"+31 499 392 431",
    "sg:postcode":"5683 AG",
    "sg:province":"Noord-Brabant",
    "sg:tags":[
        "accountant"
    ],
    "wof:name":"Seres Accountantskantoor",
    "wof:placetype":"venue"
},
  "geometry": {"coordinates":[-101.618134,31.224251],"type":"Point"}
}