{
  "type": "Feature",
  "properties": {
    "addr:full":"Kluyverwg 3 Delft South Holland 2629 HS",
    "addr:housenumber":"3",
    "addr:postcode":"2629 hs",
    "addr:street":"Kluyverwg",
    "iso:country":"NL",
    "sg:address":"Kluyverwg 3",
    "sg:city":"Delft",
    "sg:orig_category":"Onderzoekbureaus",
    "sg:phone":"+31 15 278 5353",
    "sg:postcode":"2629 HS",
    "sg:province":"South Holland",
    "sg:website":"http://www.hi.tudelft.nl",
    "wof:name":"Hechtingsinstituut Tu Delft",
    "wof:placetype":"venue"
},
  "geometry": {"coordinates":[4.379014,51.990631],"type":"Point"}
}