{
  "type": "Feature",
  "properties": {
    "iso:country":"NL",
    "sg:address":"Lage Weidjes 58",
    "sg:city":"Cuijk",
    "sg:orig_category":"Overheidsdiensten",
    "sg:phone":"+31 485 316 423",
    "sg:postcode":"5431 MK",
    "sg:province":"Noord-Brabant",
    "wof:name":"T Fort",
    "wof:placetype":"venue"
},
  "geometry": {"coordinates":[5.8811650276,51.7327804565],"type":"Point"}
}