{
  "type": "Feature",
  "properties": {
    "addr:full":"Nieuwez Voorburgw 104 Amsterdam North Holland 1012 SG",
    "addr:housenumber":"104",
    "addr:postcode":"1012 sg",
    "iso:country":"NL",
    "sg:address":"Nieuwez Voorburgw 104",
    "sg:city":"Amsterdam",
    "sg:orig_category":"Hulpverlening Sociaal",
    "sg:phone":"+31 20 625 3246",
    "sg:postcode":"1012 SG",
    "sg:province":"North Holland",
    "wof:name":"Atas, Sticht",
    "wof:placetype":"venue"
},
  "geometry": {"coordinates":[4.892176,52.375515],"type":"Point"}
}