{
  "type": "Feature",
  "properties": {
    "addr:full":"Kanaalwg 15G Utrecht Utrecht 3526 KL",
    "addr:housenumber":"15g",
    "addr:postcode":"3526 kl",
    "addr:street":"Kanaalwg",
    "iso:country":"NL",
    "sg:address":"Kanaalwg 15G",
    "sg:city":"Utrecht",
    "sg:orig_category":"Koeriersdiensten",
    "sg:phone":"+31 800 1234",
    "sg:postcode":"3526 KL",
    "sg:province":"Utrecht",
    "sg:website":"http://www.tnt.nl",
    "wof:name":"Tnt",
    "wof:placetype":"venue"
},
  "geometry": {"coordinates":[5.109022,52.068665],"type":"Point"}
}