{
  "type": "Feature",
  "properties": {
    "addr:full":"Breedstr 60 Enkhuizen Noord-Holland 1601 KE",
    "addr:housenumber":"60",
    "addr:postcode":"1601 ke",
    "addr:street":"Breedstr",
    "iso:country":"NL",
    "sg:address":"Breedstr 60",
    "sg:city":"Enkhuizen",
    "sg:orig_category":"Artsen - Manuele Geneeskunde",
    "sg:phone":"+31 228 318 255",
    "sg:postcode":"1601 KE",
    "sg:province":"Noord-Holland",
    "wof:name":"Kuiper, F",
    "wof:placetype":"venue"
},
  "geometry": {"coordinates":[5.294429,52.703663],"type":"Point"}
}