{
  "type": "Feature",
  "properties": {
    "addr:full":"Tussendiepen 50 Drachten Friesland 9206 AE",
    "addr:housenumber":"50",
    "addr:postcode":"9206 ae",
    "addr:street":"Tussendiepen",
    "iso:country":"NL",
    "sg:address":"Tussendiepen 50",
    "sg:city":"Drachten",
    "sg:orig_category":"Metaalbewerking",
    "sg:phone":"+31 512 511 918",
    "sg:postcode":"9206 AE",
    "sg:province":"Friesland",
    "wof:name":"R & B Hameco Bv",
    "wof:placetype":"venue"
},
  "geometry": {"coordinates":[6.065817,53.106167],"type":"Point"}
}