{
  "type": "Feature",
  "properties": {
    "addr:full":"Leeghwaterstraat 71 Sliedrecht South Holland 3364 AE",
    "addr:housenumber":"71",
    "addr:postcode":"3364 ae",
    "addr:street":"Leeghwaterstraat",
    "iso:country":"NL",
    "sg:address":"Leeghwaterstraat 71",
    "sg:city":"Sliedrecht",
    "sg:orig_category":"Meubelzaken, Woning- And Keukeninrichting",
    "sg:phone":"+31 184 412 562",
    "sg:postcode":"3364 AE",
    "sg:province":"South Holland",
    "wof:name":"Henk Hartog Meubelcenter Bv",
    "wof:placetype":"venue"
},
  "geometry": {"coordinates":[4.761609,51.829857],"type":"Point"}
}