{
  "type": "Feature",
  "properties": {
    "iso:country":"NL",
    "sg:address":"Kortenhoefsedk 153",
    "sg:city":"Kortenhoef",
    "sg:orig_category":"Adviesbureaus",
    "sg:phone":"+31 35 656 2255",
    "sg:postcode":"1241 LZ",
    "sg:province":"Noord-Holland",
    "wof:name":"Balboa Bv",
    "wof:placetype":"venue"
},
  "geometry": {"coordinates":[5.090643,52.229256],"type":"Point"}
}