{
  "type": "Feature",
  "properties": {
    "addr:full":"Schutstr 120 Hoogeveen Provincie Drenthe 7901 EH",
    "addr:housenumber":"120",
    "addr:postcode":"7901 eh",
    "addr:street":"Provincie",
    "iso:country":"NL",
    "sg:address":"Schutstr 120",
    "sg:city":"Hoogeveen",
    "sg:orig_category":"Verzekerings- Maatschappijen",
    "sg:phone":"+31 528 299 999",
    "sg:postcode":"7901 EH",
    "sg:province":"Provincie Drenthe",
    "sg:website":"http://www.unigarant.nl",
    "wof:name":"Unigarant",
    "wof:placetype":"venue"
},
  "geometry": {"coordinates":[6.469934,52.719814],"type":"Point"}
}