{
  "type": "Feature",
  "properties": {
    "iso:country":"NL",
    "sg:address":"Klopperstraat 29",
    "sg:city":"Enkhuizen",
    "sg:orig_category":"Watersport-, Sport- And Kampeerbenodigdheden Verhuur",
    "sg:phone":"+31 228 314 715",
    "sg:postcode":"1601 CG",
    "sg:province":"North Holland",
    "wof:name":"H. W. Hortensius",
    "wof:placetype":"venue"
},
  "geometry": {"coordinates":[5.283372879,52.701084137],"type":"Point"}
}