{
  "type": "Feature",
  "properties": {
    "addr:full":"Puccinidreef 48 Voorschoten Zuid-Holland 2253 SN",
    "addr:housenumber":"48",
    "addr:postcode":"2253 sn",
    "addr:street":"Puccinidreef",
    "iso:country":"NL",
    "sg:address":"Puccinidreef 48",
    "sg:city":"Voorschoten",
    "sg:orig_category":"Verenigingen En Stichtingen",
    "sg:phone":"+31 71 561 4512",
    "sg:postcode":"2253 SN",
    "sg:province":"Zuid-Holland",
    "wof:name":"Ehbo Voorschoten, Ver",
    "wof:placetype":"venue"
},
  "geometry": {"coordinates":[4.452642,52.137115],"type":"Point"}
}