{
  "type": "Feature",
  "properties": {
    "addr:full":"Raadhuisplein 1 Wervershoof Noord-Holland 1693 EA",
    "addr:housenumber":"1",
    "addr:postcode":"1693 ea",
    "addr:street":"Raadhuisplein",
    "iso:country":"NL",
    "sg:address":"Raadhuisplein 1",
    "sg:city":"Wervershoof",
    "sg:orig_category":"Overheidsdiensten",
    "sg:phone":"+31 228 587 171",
    "sg:postcode":"1693 EA",
    "sg:province":"Noord-Holland",
    "wof:name":"Gemeente Wervershoof",
    "wof:placetype":"venue"
},
  "geometry": {"coordinates":[5.1500668526,52.7277488708],"type":"Point"}
}