{
  "type": "Feature",
  "properties": {
    "addr:full":"Westvest 32 Schiedam South Holland 3111 BW",
    "addr:housenumber":"32",
    "addr:postcode":"3111 bw",
    "addr:street":"Westvest",
    "iso:country":"NL",
    "sg:address":"Westvest 32",
    "sg:city":"Schiedam",
    "sg:orig_category":"Projectontwikkeling",
    "sg:phone":"+31 10 473 7189",
    "sg:postcode":"3111 BW",
    "sg:province":"South Holland",
    "wof:name":"Idd",
    "wof:placetype":"venue"
},
  "geometry": {"coordinates":[4.398988,51.913876],"type":"Point"}
}