{
  "type": "Feature",
  "properties": {
    "addr:full":"Bleekstraat 19 Eindhoven Noord-Brabant 5611 VB",
    "addr:housenumber":"19",
    "addr:postcode":"5611 vb",
    "addr:street":"Bleekstraat",
    "iso:country":"NL",
    "sg:address":"Bleekstraat 19",
    "sg:city":"Eindhoven",
    "sg:orig_category":"Artiestenbureaus",
    "sg:phone":"+31 40 212 4825",
    "sg:postcode":"5611 VB",
    "sg:province":"Noord-Brabant",
    "wof:name":"Emilio De Vlam Produkties/Artiesten/Even",
    "wof:placetype":"venue"
},
  "geometry": {"coordinates":[5.485462,51.436699],"type":"Point"}
}