{
  "type": "Feature",
  "properties": {
    "iso:country":"NL",
    "sg:address":"Minervum 7030",
    "sg:city":"Breda",
    "sg:orig_category":"Verlichting And Huishoudartikelen",
    "sg:phone":"+31 76 572 9900",
    "sg:postcode":"4817 ZL",
    "sg:province":"Noord-Brabant",
    "wof:name":"Karma Design Bv",
    "wof:placetype":"venue"
},
  "geometry": {"coordinates":[4.826754,51.586948],"type":"Point"}
}