{
  "type": "Feature",
  "properties": {
    "iso:country":"NL",
    "sg:address":"Zuster Reichertstraat 26",
    "sg:city":"Leiden",
    "sg:orig_category":"Bloemen And Planten Gh",
    "sg:phone":"+31 71 531 8788",
    "sg:postcode":"2331 CS",
    "sg:province":"Zuid-Holland",
    "wof:name":"Vof Blumengrosshandel S. Van Boheemen",
    "wof:placetype":"venue"
},
  "geometry": {"coordinates":[4.458756,52.151394],"type":"Point"}
}