{
  "type": "Feature",
  "properties": {
    "iso:country":"NL",
    "sg:address":"Hoefstraat 125",
    "sg:city":"Tilburg",
    "sg:orig_category":"Cafetaria'S",
    "sg:phone":"+31 13 511 9140",
    "sg:postcode":"5014 NJ",
    "sg:province":"Noord-Brabant",
    "wof:name":"D'N Up",
    "wof:placetype":"venue"
},
  "geometry": {"coordinates":[5.089122,51.57272],"type":"Point"}
}