{
  "type": "Feature",
  "properties": {
    "addr:full":"Bankastraat 91 'S Gravenhage South Holland 2585 EJ",
    "addr:housenumber":"91",
    "addr:postcode":"2585 ej",
    "addr:street":"Bankastraat;' S Gravenhage",
    "iso:country":"NL",
    "sg:address":"Bankastraat 91",
    "sg:city":"'S Gravenhage",
    "sg:orig_category":"Zuivelproducten",
    "sg:phone":"+31 70 350 4686",
    "sg:postcode":"2585 EJ",
    "sg:province":"South Holland",
    "wof:name":"Rebel'S Kaas Spec",
    "wof:placetype":"venue"
},
  "geometry": {"coordinates":[4.304171,52.091934],"type":"Point"}
}