{
  "type": "Feature",
  "properties": {
    "addr:full":"Pres Kennedyln 144 Oegstgeest Zuid-Holland 2343 GV",
    "addr:housenumber":"144",
    "addr:postcode":"2343 gv",
    "iso:country":"NL",
    "sg:address":"Pres Kennedyln 144",
    "sg:city":"Oegstgeest",
    "sg:orig_category":"Mensendieck - Oefentherapeuten",
    "sg:phone":"+31 71 515 6988",
    "sg:postcode":"2343 GV",
    "sg:province":"Zuid-Holland",
    "wof:name":"Tol, M N",
    "wof:placetype":"venue"
},
  "geometry": {"coordinates":[4.468242,52.176617],"type":"Point"}
}