{
  "type": "Feature",
  "properties": {
    "iso:country":"NL",
    "sg:address":"Pr Ireneln 19",
    "sg:city":"Leusden",
    "sg:orig_category":"Kappers",
    "sg:phone":"+31 33 494 8884",
    "sg:postcode":"3832 CA",
    "sg:province":"Utrecht",
    "wof:name":"Ferry",
    "wof:placetype":"venue"
},
  "geometry": {"coordinates":[5.4032459259,52.1215209961],"type":"Point"}
}