{
  "type": "Feature",
  "properties": {
    "addr:full":"Hasselaarlaan 26 Eemnes Utrecht 3755 AW",
    "addr:housenumber":"26",
    "addr:postcode":"3755 aw",
    "addr:street":"Hasselaarlaan",
    "iso:country":"NL",
    "sg:address":"Hasselaarlaan 26",
    "sg:city":"Eemnes",
    "sg:orig_category":"Bloemen And Planten",
    "sg:phone":"+31 35 538 6915",
    "sg:postcode":"3755 AW",
    "sg:province":"Utrecht",
    "wof:name":"Elsa Leers Flower Design",
    "wof:placetype":"venue"
},
  "geometry": {"coordinates":[5.259602,52.254166],"type":"Point"}
}