{
  "type": "Feature",
  "properties": {
    "iso:country":"NL",
    "sg:address":"Hermanus Boexstraat 21",
    "sg:city":"Eindhoven",
    "sg:orig_category":"Schoenen",
    "sg:phone":"+31 40 295 0879",
    "sg:postcode":"5611 AH",
    "sg:province":"Noord-Brabant",
    "wof:name":"Bovendeert Schoenen Bv",
    "wof:placetype":"venue"
},
  "geometry": {"coordinates":[5.478452,51.440262],"type":"Point"}
}