{
  "type": "Feature",
  "properties": {
    "addr:full":"Kraaivenstr 38-18 Tilburg Noord-Brabant 5048 AB",
    "addr:housenumber":"38-18",
    "addr:postcode":"5048 ab",
    "addr:street":"Tilburg",
    "iso:country":"NL",
    "sg:address":"Kraaivenstr 38-18",
    "sg:city":"Tilburg",
    "sg:orig_category":"Beveiliging",
    "sg:phone":"+31 13 594 2390",
    "sg:postcode":"5048 AB",
    "sg:province":"Noord-Brabant",
    "wof:name":"Network",
    "wof:placetype":"venue"
},
  "geometry": {"coordinates":[5.06427,51.57951],"type":"Point"}
}