{
  "type": "Feature",
  "properties": {
    "addr:full":"Hogestr 67C Druten Gelderland 6651 BH",
    "addr:housenumber":"67c",
    "addr:postcode":"6651 bh",
    "addr:street":"Hogestr",
    "iso:country":"NL",
    "sg:address":"Hogestr 67C",
    "sg:city":"Druten",
    "sg:orig_category":"Schoenen",
    "sg:phone":"+31 487 518 665",
    "sg:postcode":"6651 BH",
    "sg:province":"Gelderland",
    "wof:name":"Schoenenreus",
    "wof:placetype":"venue"
},
  "geometry": {"coordinates":[5.60526,51.88567],"type":"Point"}
}