{
  "type": "Feature",
  "properties": {
    "addr:full":"Paardebloem 104 Zwaag Noord-Holland 1689 RS",
    "addr:housenumber":"104",
    "addr:postcode":"1689 rs",
    "addr:street":"Paardebloem",
    "iso:country":"NL",
    "sg:address":"Paardebloem 104",
    "sg:city":"Zwaag",
    "sg:orig_category":"Keukens",
    "sg:phone":"+31 229 239 238",
    "sg:postcode":"1689 RS",
    "sg:province":"Noord-Holland",
    "wof:name":"Thema",
    "wof:placetype":"venue"
},
  "geometry": {"coordinates":[5.048238,52.664589],"type":"Point"}
}