{
  "type": "Feature",
  "properties": {
    "addr:full":"Arienslaan 5 Utrecht Utrecht 3573 PT",
    "addr:housenumber":"5",
    "addr:postcode":"3573 pt",
    "addr:street":"Arienslaan",
    "iso:country":"NL",
    "sg:address":"Arienslaan 5",
    "sg:city":"Utrecht",
    "sg:orig_category":"Kampeerterreinen",
    "sg:phone":"+31 30 271 3870",
    "sg:postcode":"3573 PT",
    "sg:province":"Utrecht",
    "wof:name":"Camping De Berekuil",
    "wof:placetype":"venue"
},
  "geometry": {"coordinates":[5.1477370262,52.1012840271],"type":"Point"}
}