{
  "type": "Feature",
  "properties": {
    "addr:full":"Burg V Royenstr O 202 Hoogezand Groningen 9602 CN",
    "addr:housenumber":"202",
    "addr:postcode":"9602 cn",
    "addr:street":"Burg V Royenstr O",
    "iso:country":"NL",
    "sg:address":"Burg V Royenstr O 202",
    "sg:city":"Hoogezand",
    "sg:orig_category":"Vakorganisaties",
    "sg:phone":"+31 598 323 518",
    "sg:postcode":"9602 CN",
    "sg:province":"Groningen",
    "wof:name":"Fnv",
    "wof:placetype":"venue"
},
  "geometry": {"coordinates":[6.754265,53.15551],"type":"Point"}
}