{
  "type": "Feature",
  "properties": {
    "addr:full":"Postbus 5336 Naarden Noord-Holland 1410 AH",
    "addr:postcode":"5336 naarden;1410 ah",
    "addr:street":"Postbus",
    "iso:country":"NL",
    "sg:address":"Postbus 5336",
    "sg:city":"Naarden",
    "sg:orig_category":"Tuinaanleg En -Onderhoud",
    "sg:phone":"+31 35 694 3269",
    "sg:postcode":"1410 AH",
    "sg:province":"Noord-Holland",
    "sg:website":"http://www.groencombinatie.nl",
    "wof:name":"Amstel-Ruisendaal Groencombinatie Bv, Van",
    "wof:placetype":"venue"
},
  "geometry": {"coordinates":[5.160918,52.28624],"type":"Point"}
}