{
  "type": "Feature",
  "properties": {
    "iso:country":"NL",
    "sg:address":"Huygensstr 22",
    "sg:city":"Terneuzen",
    "sg:orig_category":"Nagelstudio'S",
    "sg:phone":"+31 115 697 538",
    "sg:postcode":"4532 KB",
    "sg:province":"Zeeland",
    "wof:name":"Machielse, P",
    "wof:placetype":"venue"
},
  "geometry": {"coordinates":[3.850123,51.332745],"type":"Point"}
}