{
  "type": "Feature",
  "properties": {
    "addr:full":"Penningwg 79E Zaandam Noord-Holland 1507 DG",
    "addr:housenumber":"79e",
    "addr:postcode":"1507 dg",
    "addr:street":"Penningwg",
    "iso:country":"NL",
    "sg:address":"Penningwg 79E",
    "sg:city":"Zaandam",
    "sg:orig_category":"Plafonds",
    "sg:phone":"+31 75 631 0138",
    "sg:postcode":"1507 DG",
    "sg:province":"Noord-Holland",
    "wof:name":"Abc Projecten",
    "wof:placetype":"venue"
},
  "geometry": {"coordinates":[4.79171,52.429447],"type":"Point"}
}