{
  "type": "Feature",
  "properties": {
    "addr:full":"Beethovenstr 41 Amsterdam North Holland 1077 HN",
    "addr:housenumber":"41",
    "addr:postcode":"1077 hn",
    "addr:street":"Beethovenstr",
    "iso:country":"NL",
    "sg:address":"Beethovenstr 41",
    "sg:city":"Amsterdam",
    "sg:orig_category":"Glas, Porselein En Aardewerk",
    "sg:phone":"+31 20 662 1737",
    "sg:postcode":"1077 HN",
    "sg:province":"North Holland",
    "wof:name":"Fleur De Lys",
    "wof:placetype":"venue"
},
  "geometry": {"coordinates":[4.877568,52.348534],"type":"Point"}
}