{
  "type": "Feature",
  "properties": {
    "addr:full":"Angelsloerdk 27 Emmen Drenthe 7822 HK",
    "addr:housenumber":"27",
    "addr:postcode":"7822 hk",
    "addr:street":"Angelsloerdk",
    "iso:country":"NL",
    "sg:address":"Angelsloerdk 27",
    "sg:city":"Emmen",
    "sg:orig_category":"Accountants - Administratie- Consulenten En -Kantoren",
    "sg:phone":"+31 591 650 610",
    "sg:postcode":"7822 HK",
    "sg:province":"Drenthe",
    "wof:name":"Cate, Accountantskantoor Ten",
    "wof:placetype":"venue"
},
  "geometry": {"coordinates":[6.909914,52.780949],"type":"Point"}
}