{
  "type": "Feature",
  "properties": {
    "iso:country":"NL",
    "sg:address":"Rooseveltln 2",
    "sg:city":"Veghel",
    "sg:orig_category":"Gassen Industrieel En Medisch",
    "sg:phone":"+31 413 363 421",
    "sg:postcode":"5466 AB",
    "sg:province":"Noord-Brabant",
    "sg:website":"http://www.gaslascentrum.nl",
    "wof:name":"Minigas Glc Veghel Bv",
    "wof:placetype":"venue"
},
  "geometry": {"coordinates":[5.518599,51.602097],"type":"Point"}
}