{
  "type": "Feature",
  "properties": {
    "addr:full":"Eijkersstraat 57 Posterholt Limburg 6061 GS",
    "addr:housenumber":"57",
    "addr:postcode":"6061 gs",
    "addr:street":"Eijkersstraat",
    "iso:country":"NL",
    "sg:address":"Eijkersstraat 57",
    "sg:city":"Posterholt",
    "sg:orig_category":"Diverse Consumentenartikelen Gh",
    "sg:phone":"+31 475 403 919",
    "sg:postcode":"6061 GS",
    "sg:province":"Limburg",
    "wof:name":"Bontekoe Handelsonderneming C. Bontekoe",
    "wof:placetype":"venue"
},
  "geometry": {"coordinates":[6.0182,51.129883],"type":"Point"}
}