{
  "type": "Feature",
  "properties": {
    "addr:full":"Broekveldseln 11 Bodegraven South Holland 2411 NL",
    "addr:housenumber":"11",
    "addr:postcode":"2411 nl",
    "addr:street":"Broekveldseln",
    "iso:country":"NL",
    "sg:address":"Broekveldseln 11",
    "sg:city":"Bodegraven",
    "sg:orig_category":"Loodgieters",
    "sg:phone":"+31 172 612 207",
    "sg:postcode":"2411 NL",
    "sg:province":"South Holland",
    "wof:name":"Lok Bv",
    "wof:placetype":"venue"
},
  "geometry": {"coordinates":[4.747547,52.085552],"type":"Point"}
}