{
  "type": "Feature",
  "properties": {
    "addr:full":"Granidastraat 8 Amsterdam North Holland 1055 HJ",
    "addr:housenumber":"8",
    "addr:postcode":"1055 hj",
    "addr:street":"Granidastraat",
    "iso:country":"NL",
    "sg:address":"Granidastraat 8",
    "sg:city":"Amsterdam",
    "sg:orig_category":"Opticiens",
    "sg:phone":"+31 20 681 7604",
    "sg:postcode":"1055 HJ",
    "sg:province":"North Holland",
    "wof:name":"De Mobiele Opticien",
    "wof:placetype":"venue"
},
  "geometry": {"coordinates":[4.8490009308,52.3789672852],"type":"Point"}
}