{
  "type": "Feature",
  "properties": {
    "addr:full":"Koningsplein 20B Maastricht Limburg 6224 EC",
    "addr:housenumber":"20b",
    "addr:postcode":"6224 ec",
    "addr:street":"Koningsplein",
    "iso:country":"NL",
    "sg:address":"Koningsplein 20B",
    "sg:city":"Maastricht",
    "sg:orig_category":"Architecten",
    "sg:phone":"+31 43 363 2447",
    "sg:postcode":"6224 EC",
    "sg:province":"Limburg",
    "wof:name":"Architectenbureau W.M.G. Thomas",
    "wof:placetype":"venue"
},
  "geometry": {"coordinates":[5.709278,50.849525],"type":"Point"}
}