{
  "type": "Feature",
  "properties": {
    "addr:full":"Schoenmakersperk 2 Leeuwarden Friesland 8911 EM",
    "addr:housenumber":"2",
    "addr:postcode":"8911 em",
    "addr:street":"Schoenmakersperk",
    "iso:country":"NL",
    "sg:address":"Schoenmakersperk 2",
    "sg:city":"Leeuwarden",
    "sg:orig_category":"Musea And Historische Gebouwen",
    "sg:phone":"+31 58 212 9085",
    "sg:postcode":"8911 EM",
    "sg:province":"Friesland",
    "wof:name":"Fries Natuurmuseum",
    "wof:placetype":"venue"
},
  "geometry": {"coordinates":[5.795776,53.204006],"type":"Point"}
}