{
  "type": "Feature",
  "properties": {
    "iso:country":"NL",
    "sg:address":"De Kolk 6",
    "sg:city":"Oude Bildtzyl",
    "sg:orig_category":"Kinderkleding",
    "sg:phone":"+31 518 421 831",
    "sg:postcode":"9078 VH",
    "sg:province":"Friesland",
    "sg:website":"http://www.pre-be-exclusief.nl",
    "wof:name":"Pr\u00e9-Be Exclusief",
    "wof:placetype":"venue"
},
  "geometry": {"coordinates":[5.719585,53.300957],"type":"Point"}
}