{
  "type": "Feature",
  "properties": {
    "addr:full":"Past Palsstr 4 St Willebrord Noord-Brabant 4711 CN",
    "addr:housenumber":"4",
    "addr:postcode":"4711 cn",
    "addr:street":"St",
    "iso:country":"NL",
    "sg:address":"Past Palsstr 4",
    "sg:city":"St Willebrord",
    "sg:orig_category":"Kabelexploitanten",
    "sg:phone":"+31 165 384 888",
    "sg:postcode":"4711 CN",
    "sg:province":"Noord-Brabant",
    "wof:name":"Tv Krant",
    "wof:placetype":"venue"
},
  "geometry": {"coordinates":[4.5871472359,51.5554428101],"type":"Point"}
}