{
  "type": "Feature",
  "properties": {
    "addr:full":"Standermolen 20 Houten Utrecht 3995 AA",
    "addr:housenumber":"20",
    "addr:postcode":"3995 aa",
    "addr:street":"Standermolen",
    "iso:country":"NL",
    "sg:address":"Standermolen 20",
    "sg:city":"Houten",
    "sg:orig_category":"Paramedische Behandelingen",
    "sg:phone":"+31 30 634 1198",
    "sg:postcode":"3995 AA",
    "sg:province":"Utrecht",
    "wof:name":"Saskia De Waal",
    "wof:placetype":"venue"
},
  "geometry": {"coordinates":[5.172159,52.029762],"type":"Point"}
}