{
  "type": "Feature",
  "properties": {
    "addr:full":"Johannahoeve 4 Oosterbeek Gelderland 6861 WJ",
    "addr:housenumber":"4",
    "addr:postcode":"6861 wj",
    "addr:street":"Johannahoeve;Gelderland",
    "iso:country":"NL",
    "sg:address":"Johannahoeve 4",
    "sg:city":"Oosterbeek",
    "sg:orig_category":"Bejaarden - Verzorgingstehuizen",
    "sg:phone":"+31 26 339 8082",
    "sg:postcode":"6861 WJ",
    "sg:province":"Gelderland",
    "wof:name":"Mill Hill Procuur",
    "wof:placetype":"venue"
},
  "geometry": {"coordinates":[5.840523,51.994946],"type":"Point"}
}