{
  "type": "Feature",
  "properties": {
    "addr:full":"Eperwg 26 Nunspeet Gelderland 8071 AX",
    "addr:housenumber":"26",
    "addr:postcode":"8071 ax",
    "addr:street":"Eperwg;Gelderland",
    "iso:country":"NL",
    "sg:address":"Eperwg 26",
    "sg:city":"Nunspeet",
    "sg:orig_category":"Groepsaccommodaties",
    "sg:phone":"+31 341 252 352",
    "sg:postcode":"8071 AX",
    "sg:province":"Gelderland",
    "sg:website":"http://www.deduiventil.nl",
    "wof:name":"Duiventil, Groepsacc De",
    "wof:placetype":"venue"
},
  "geometry": {"coordinates":[5.791928,52.376907],"type":"Point"}
}