{
  "type": "Feature",
  "properties": {
    "iso:country":"NL",
    "sg:address":"Brouwerijstraat 59",
    "sg:city":"Oostburg",
    "sg:orig_category":"Wasserettes And Stomerijen",
    "sg:phone":"+31 117 440 100",
    "sg:postcode":"4501 CN",
    "sg:province":"Wisconsin",
    "wof:name":"Sanne",
    "wof:placetype":"venue"
},
  "geometry": {"coordinates":[-87.7992019653,43.6285514832],"type":"Point"}
}