{
  "type": "Feature",
  "properties": {
    "addr:full":"Huyghensln 2 Arnhem Gelderland 6824 JG",
    "addr:housenumber":"2",
    "addr:postcode":"6824 jg",
    "addr:street":"Huyghensln",
    "iso:country":"NL",
    "sg:address":"Huyghensln 2",
    "sg:city":"Arnhem",
    "sg:orig_category":"Artsen - Huisartsen",
    "sg:phone":"+31 26 442 5577",
    "sg:postcode":"6824 JG",
    "sg:province":"Gelderland",
    "wof:name":"Gribnau, J Th M",
    "wof:placetype":"venue"
},
  "geometry": {"coordinates":[5.93741,51.993671],"type":"Point"}
}