{
  "type": "Feature",
  "properties": {
    "addr:full":"Kalanderstraat 28 Rijssen Overijssel 7461 JM",
    "addr:housenumber":"28",
    "addr:postcode":"7461 jm",
    "addr:street":"Kalanderstraat",
    "iso:country":"NL",
    "sg:address":"Kalanderstraat 28",
    "sg:city":"Rijssen",
    "sg:orig_category":"Autokeuringen",
    "sg:phone":"+31 548 539 505",
    "sg:postcode":"7461 JM",
    "sg:province":"Overijssel",
    "wof:name":"Autoschade Centrum Noordermors Bv",
    "wof:placetype":"venue"
},
  "geometry": {"coordinates":[6.506786,52.322517],"type":"Point"}
}