{
  "type": "Feature",
  "properties": {
    "addr:full":"Taxusrode 8 Helmond Noord-Brabant 5709 HW",
    "addr:housenumber":"8",
    "addr:postcode":"5709 hw",
    "addr:street":"Taxusrode",
    "iso:country":"NL",
    "sg:address":"Taxusrode 8",
    "sg:city":"Helmond",
    "sg:classifiers":[
        {
            "category":"Shopping",
            "subcategory":"Gifts & Souvenirs",
            "type":"Retail Goods"
        }
    ],
    "sg:phone":"+31 492 558 054",
    "sg:postcode":"5709 HW",
    "sg:province":"Noord-Brabant",
    "sg:tags":[
        "geschenken"
    ],
    "wof:name":"Promida Gifts & Game",
    "wof:placetype":"venue"
},
  "geometry": {"coordinates":[5.701514,51.480526],"type":"Point"}
}