{
  "type": "Feature",
  "properties": {
    "addr:full":"Meerheide 49 Eersel North Brabant 5521 DZ",
    "addr:housenumber":"49",
    "addr:postcode":"5521 dz",
    "addr:street":"Meerheide",
    "iso:country":"NL",
    "sg:address":"Meerheide 49",
    "sg:city":"Eersel",
    "sg:orig_category":"Luchtvrachtexpediteurs",
    "sg:phone":"+31 497 532 306",
    "sg:postcode":"5521 DZ",
    "sg:province":"North Brabant",
    "sg:website":"http://www.emeryworld.com",
    "wof:name":"Emery Worldwide",
    "wof:placetype":"venue"
},
  "geometry": {"coordinates":[5.315484,51.375637],"type":"Point"}
}