{
  "type": "Feature",
  "properties": {
    "iso:country":"NL",
    "sg:address":"Mijlweg 4A",
    "sg:city":"'S Gravendeel",
    "sg:orig_category":"Goederenvervoer Over De Weg",
    "sg:phone":"+31 78 673 3572",
    "sg:postcode":"3295 KH",
    "sg:province":"South Holland",
    "wof:name":"A.J. V.D. Hoek",
    "wof:placetype":"venue"
},
  "geometry": {"coordinates":[4.617496,51.784637],"type":"Point"}
}