{
  "type": "Feature",
  "properties": {
    "addr:full":"Wanraay 53 Andelst Gelderland 6673 DM",
    "addr:housenumber":"53",
    "addr:postcode":"6673 dm",
    "addr:street":"Wanraay;Gelderland",
    "iso:country":"NL",
    "sg:address":"Wanraay 53",
    "sg:city":"Andelst",
    "sg:orig_category":"Levensmiddelen - Fabrieken En Groothandel",
    "sg:phone":"+31 488 421 819",
    "sg:postcode":"6673 DM",
    "sg:province":"Gelderland",
    "wof:name":"Snackvision Bv",
    "wof:placetype":"venue"
},
  "geometry": {"coordinates":[5.712854,51.913017],"type":"Point"}
}