{
  "type": "Feature",
  "properties": {
    "iso:country":"NL",
    "sg:address":"Grote Noord 58",
    "sg:city":"Hoorn Nh",
    "sg:orig_category":"Herenmodezaken",
    "sg:phone":"+31 229 214 425",
    "sg:postcode":"1621 KK",
    "sg:province":"North Holland",
    "wof:name":"Van Os Mode",
    "wof:placetype":"venue"
},
  "geometry": {"coordinates":[5.057203,52.64082],"type":"Point"}
}