{
  "type": "Feature",
  "properties": {
    "addr:full":"Noordeinde 14 Wormerveer North Holland 1521 PA",
    "addr:housenumber":"14",
    "addr:postcode":"1521 pa",
    "addr:street":"Noordeinde",
    "iso:country":"NL",
    "sg:address":"Noordeinde 14",
    "sg:city":"Wormerveer",
    "sg:orig_category":"Behangselpapier En Wandbekleding",
    "sg:phone":"+31 75 621 7478",
    "sg:postcode":"1521 PA",
    "sg:province":"North Holland",
    "wof:name":"Groen",
    "wof:placetype":"venue"
},
  "geometry": {"coordinates":[4.792074,52.493919],"type":"Point"}
}