{
  "type": "Feature",
  "properties": {
    "addr:full":"Bydorp O 50 Barendrecht Zuid-Holland 2992 LA",
    "addr:housenumber":"50",
    "addr:postcode":"2992 la",
    "iso:country":"NL",
    "sg:address":"Bydorp O 50",
    "sg:city":"Barendrecht",
    "sg:orig_category":"Bedrijfskleding",
    "sg:phone":"+31 180 641 890",
    "sg:postcode":"2992 LA",
    "sg:province":"Zuid-Holland",
    "sg:website":"http://www.baanbreker.nl",
    "wof:name":"Baan Bv",
    "wof:placetype":"venue"
},
  "geometry": {"coordinates":[4.54064,51.853176],"type":"Point"}
}