{
  "type": "Feature",
  "properties": {
    "addr:full":"Dr. A.F. Philipsweg 43 Assen Provincie Drenthe 9403 AD",
    "addr:housenumber":"43",
    "addr:postcode":"9403 ad",
    "addr:street":"Dr. A.F. Philipsweg;Provincie Drenthe",
    "iso:country":"NL",
    "sg:address":"Dr. A.F. Philipsweg 43",
    "sg:city":"Assen",
    "sg:orig_category":"Metaalvrije Afvalrecycling",
    "sg:phone":"+31 592 370 378",
    "sg:postcode":"9403 AD",
    "sg:province":"Provincie Drenthe",
    "wof:name":"Visser Assen Recycling Bv",
    "wof:placetype":"venue"
},
  "geometry": {"coordinates":[6.581914,53.001286],"type":"Point"}
}