{
  "type": "Feature",
  "properties": {
    "addr:full":"Burg Leenstr 11 Lochem Gelderland 7242 AA",
    "addr:housenumber":"11",
    "addr:postcode":"7242 aa",
    "addr:street":"Burg;Gelderland",
    "iso:country":"NL",
    "sg:address":"Burg Leenstr 11",
    "sg:city":"Lochem",
    "sg:orig_category":"Verenigingen En Stichtingen",
    "sg:phone":"+31 573 252 406",
    "sg:postcode":"7242 AA",
    "sg:province":"Gelderland",
    "wof:name":"Turkse Inw Lochem, Sticht",
    "wof:placetype":"venue"
},
  "geometry": {"coordinates":[6.413483,52.160206],"type":"Point"}
}