{
  "type": "Feature",
  "properties": {
    "addr:full":"Palenbergstr 48 Heerlen Limburg 6415 RD",
    "addr:housenumber":"48",
    "addr:postcode":"6415 rd",
    "addr:street":"Palenbergstr",
    "iso:country":"NL",
    "sg:address":"Palenbergstr 48",
    "sg:city":"Heerlen",
    "sg:orig_category":"Logopedisten",
    "sg:phone":"+31 45 572 5992",
    "sg:postcode":"6415 RD",
    "sg:province":"Limburg",
    "wof:name":"Frings, G",
    "wof:placetype":"venue"
},
  "geometry": {"coordinates":[5.983562,50.90337],"type":"Point"}
}