{
  "type": "Feature",
  "properties": {
    "addr:full":"Zaanstroom 42A Wormerveer Noord-Holland 1521 PL",
    "addr:housenumber":"42a",
    "addr:postcode":"1521 pl",
    "addr:street":"Zaanstroom",
    "iso:country":"NL",
    "sg:address":"Zaanstroom 42A",
    "sg:city":"Wormerveer",
    "sg:orig_category":"Homeopathie",
    "sg:phone":"+31 75 640 0605",
    "sg:postcode":"1521 PL",
    "sg:province":"Noord-Holland",
    "wof:name":"Sap, O G",
    "wof:placetype":"venue"
},
  "geometry": {"coordinates":[4.792763,52.494785],"type":"Point"}
}