{
  "type": "Feature",
  "properties": {
    "addr:full":"Oude Graaf 10 Weert Limburg 6002 NL",
    "addr:housenumber":"10",
    "addr:postcode":"6002 nl",
    "addr:street":"Oude Graaf",
    "iso:country":"NL",
    "sg:address":"Oude Graaf 10",
    "sg:city":"Weert",
    "sg:orig_category":"Betonwaren - Fabrieken",
    "sg:phone":"+31 495 547 427",
    "sg:postcode":"6002 NL",
    "sg:province":"Limburg",
    "wof:name":"Lammers Bv",
    "wof:placetype":"venue"
},
  "geometry": {"coordinates":[5.660349,51.245216],"type":"Point"}
}