{
  "type": "Feature",
  "properties": {
    "addr:full":"Lutkenieuwstr 28 Groningen Groningen 9712 AZ",
    "addr:housenumber":"28",
    "addr:postcode":"9712 az",
    "addr:street":"Lutkenieuwstr",
    "iso:country":"NL",
    "sg:address":"Lutkenieuwstr 28",
    "sg:city":"Groningen",
    "sg:orig_category":"Architecten En Architectenbureaus",
    "sg:phone":"+31 50 314 2245",
    "sg:postcode":"9712 AZ",
    "sg:province":"Groningen",
    "wof:name":"Benus, P",
    "wof:placetype":"venue"
},
  "geometry": {"coordinates":[6.560769,53.21751],"type":"Point"}
}