{
  "type": "Feature",
  "properties": {
    "addr:full":"Engelsewg 235 Helmond North Brabant 5705 AE",
    "addr:housenumber":"235",
    "addr:postcode":"5705 ae",
    "iso:country":"NL",
    "sg:address":"Engelsewg 235",
    "sg:city":"Helmond",
    "sg:orig_category":"Ventilatoren",
    "sg:phone":"+31 492 502 900",
    "sg:postcode":"5705 AE",
    "sg:province":"North Brabant",
    "sg:website":"http://www.wibolucht.nl",
    "wof:name":"Vibo Luchttechniek Bv",
    "wof:placetype":"venue"
},
  "geometry": {"coordinates":[5.684191,51.471352],"type":"Point"}
}