{
  "type": "Feature",
  "properties": {
    "addr:full":"Bierkade 10 Alkmaar Noord-Holland 1811 NJ",
    "addr:housenumber":"10",
    "addr:postcode":"1811 nj",
    "addr:street":"Bierkade",
    "iso:country":"NL",
    "sg:address":"Bierkade 10",
    "sg:city":"Alkmaar",
    "sg:orig_category":"Musea And Historische Gebouwen",
    "sg:phone":"+31 72 515 9418",
    "sg:postcode":"1811 NJ",
    "sg:province":"Noord-Holland",
    "wof:name":"Nederlands Kachelmuseum",
    "wof:placetype":"venue"
},
  "geometry": {"coordinates":[4.75517,52.629246],"type":"Point"}
}