{
  "type": "Feature",
  "properties": {
    "addr:full":"Eindhovenseweg 112 Valkenswaard Noord-Brabant 5552 AD",
    "addr:housenumber":"112",
    "addr:postcode":"5552 ad",
    "addr:street":"Eindhovenseweg",
    "iso:country":"NL",
    "sg:address":"Eindhovenseweg 112",
    "sg:city":"Valkenswaard",
    "sg:orig_category":"Fietshandelaren",
    "sg:phone":"+31 40 201 3810",
    "sg:postcode":"5552 AD",
    "sg:province":"Noord-Brabant",
    "wof:name":"Tweewielerspecialist Vlassak",
    "wof:placetype":"venue"
},
  "geometry": {"coordinates":[5.461421,51.356544],"type":"Point"}
}