{
  "type": "Feature",
  "properties": {
    "addr:full":"Spoorlaan 1 Leidschendam Zuid-Holland 2267 AN",
    "addr:housenumber":"1",
    "addr:postcode":"2267 an",
    "addr:street":"Spoorlaan",
    "iso:country":"NL",
    "sg:address":"Spoorlaan 1",
    "sg:city":"Leidschendam",
    "sg:orig_category":"Autokeuringen",
    "sg:phone":"+31 70 398 9419",
    "sg:postcode":"2267 AN",
    "sg:province":"Zuid-Holland",
    "wof:name":"Unigar Autocenter Van Paassen",
    "wof:placetype":"venue"
},
  "geometry": {"coordinates":[4.40032,52.07888],"type":"Point"}
}