{
  "type": "Feature",
  "properties": {
    "addr:full":"Gochsedijk 96 Siebengewald North Rhine-Westphalia 5853 AE",
    "addr:housenumber":"96",
    "addr:postcode":"5853 ae",
    "addr:street":"Gochsedijk",
    "iso:country":"NL",
    "sg:address":"Gochsedijk 96",
    "sg:city":"Siebengewald",
    "sg:orig_category":"Meubelzaken, Woning- And Keukeninrichting",
    "sg:phone":"+31 485 441 223",
    "sg:postcode":"5853 AE",
    "sg:province":"North Rhine-Westphalia",
    "wof:name":"Ponjee Woninginrichting",
    "wof:placetype":"venue"
},
  "geometry": {"coordinates":[6.10667,51.647739],"type":"Point"}
}