{
  "type": "Feature",
  "properties": {
    "iso:country":"NL",
    "sg:address":"De Ruil 3",
    "sg:city":"Wervershoof",
    "sg:orig_category":"Bloemen En Planten - Groothandel",
    "sg:phone":"+31 228 585 000",
    "sg:postcode":"1693 HD",
    "sg:province":"Noord-Holland",
    "wof:name":"B & B Bv",
    "wof:placetype":"venue"
},
  "geometry": {"coordinates":[5.130373,52.727669],"type":"Point"}
}