{
  "type": "Feature",
  "properties": {
    "iso:country":"NL",
    "sg:address":"Kerkstr 52",
    "sg:city":"Groot Ammers",
    "sg:orig_category":"Verzekeringen - Verzekeringskantoren",
    "sg:phone":"+31 184 661 441",
    "sg:postcode":"2964 BV",
    "sg:province":"Zuid-Holland",
    "wof:name":"Ovm",
    "wof:placetype":"venue"
},
  "geometry": {"coordinates":[4.818917,51.921432],"type":"Point"}
}