{
  "type": "Feature",
  "properties": {
    "addr:full":"Zijlstraat 97 Haarlem Noord-Holland 2011 TM",
    "addr:housenumber":"97",
    "addr:postcode":"2011 tm",
    "addr:street":"Zijlstraat",
    "iso:country":"NL",
    "sg:address":"Zijlstraat 97",
    "sg:city":"Haarlem",
    "sg:orig_category":"Opticiens",
    "sg:phone":"+31 23 531 0181",
    "sg:postcode":"2011 TM",
    "sg:province":"Noord-Holland",
    "wof:name":"Fa W Kuipers & Zonen",
    "wof:placetype":"venue"
},
  "geometry": {"coordinates":[4.6350808144,52.3817634583],"type":"Point"}
}