{
  "type": "Feature",
  "properties": {
    "iso:country":"NL",
    "sg:address":"Tjasker 8",
    "sg:city":"Purmerend",
    "sg:orig_category":"Kappers",
    "sg:phone":"+31 299 431 036",
    "sg:postcode":"1444 GR",
    "sg:province":"Noord-Holland",
    "wof:name":"Dameskapsalon Margareth",
    "wof:placetype":"venue"
},
  "geometry": {"coordinates":[4.9739170074,52.5202598572],"type":"Point"}
}