{
  "type": "Feature",
  "properties": {
    "addr:full":"J Stewartstr 262 Almere NL. 1325 JP",
    "addr:housenumber":"262",
    "addr:postcode":"1325 jp",
    "addr:street":"Nl.",
    "iso:country":"NL",
    "sg:address":"J Stewartstr 262",
    "sg:city":"Almere",
    "sg:orig_category":"Bouwbureaus",
    "sg:phone":"+31 36 523 2598",
    "sg:postcode":"1325 JP",
    "sg:province":"NL.",
    "sg:website":"http://www.zzp-ers.com",
    "wof:name":"Sales Service Holland",
    "wof:placetype":"venue"
},
  "geometry": {"coordinates":[5.233311,52.369423],"type":"Point"}
}