{
  "type": "Feature",
  "properties": {
    "addr:full":"Puccinipassage 1 Capelle A/D Ijssel Zuid-Holland 2901 GK",
    "addr:housenumber":"1;a / d",
    "addr:postcode":"2901 gk",
    "addr:street":"Puccinipassage",
    "iso:country":"NL",
    "sg:address":"Puccinipassage 1",
    "sg:city":"Capelle A/D Ijssel",
    "sg:classifiers":[
        {
            "category":"Fast Food",
            "type":"Food & Drink"
        }
    ],
    "sg:phone":"+31 10 447 2688",
    "sg:postcode":"2901 GK",
    "sg:province":"Zuid-Holland",
    "sg:tags":[
        "afhaal",
        "restaurant"
    ],
    "wof:name":"Verhage Fast Food",
    "wof:placetype":"venue"
},
  "geometry": {"coordinates":[4.565118,51.917763],"type":"Point"}
}