{
  "type": "Feature",
  "properties": {
    "addr:full":"Vecht 149 Nieuwerkerk Yssel Zuid-Holland 2911 ER",
    "addr:housenumber":"149",
    "addr:postcode":"2911 er",
    "addr:street":"Vecht",
    "iso:country":"NL",
    "sg:address":"Vecht 149",
    "sg:city":"Nieuwerkerk Yssel",
    "sg:orig_category":"Adviesbureaus Bedrijfsorganisatie",
    "sg:phone":"+31 180 317 883",
    "sg:postcode":"2911 ER",
    "sg:province":"Zuid-Holland",
    "wof:name":"Internal Affairs",
    "wof:placetype":"venue"
},
  "geometry": {"coordinates":[4.615839,51.957146],"type":"Point"}
}