{
  "type": "Feature",
  "properties": {
    "iso:country":"NL",
    "sg:address":"Reinwardtstraat 262",
    "sg:city":"Amsterdam",
    "sg:orig_category":"Juweliers",
    "sg:phone":"+31 20 663 9213",
    "sg:postcode":"1093 HP",
    "sg:province":"Noord-Holland",
    "wof:name":"Lachman",
    "wof:placetype":"venue"
},
  "geometry": {"coordinates":[4.928173,52.361107],"type":"Point"}
}