{
  "type": "Feature",
  "properties": {
    "iso:country":"NL",
    "sg:address":"Buurtln O 60",
    "sg:city":"Veenendaal",
    "sg:orig_category":"Houtindustrie",
    "sg:phone":"+31 318 565 794",
    "sg:postcode":"3902 DB",
    "sg:province":"Utrecht",
    "wof:name":"Vloet Vof",
    "wof:placetype":"venue"
},
  "geometry": {"coordinates":[5.57641,52.034172],"type":"Point"}
}