{
  "type": "Feature",
  "properties": {
    "addr:full":"Delflandstr 85 Nootdorp South Holland 2631 HB",
    "addr:housenumber":"85",
    "addr:postcode":"2631 hb",
    "addr:street":"Delflandstr",
    "iso:country":"NL",
    "sg:address":"Delflandstr 85",
    "sg:city":"Nootdorp",
    "sg:orig_category":"Onderhoudswerken",
    "sg:phone":"+31 15 310 6941",
    "sg:postcode":"2631 HB",
    "sg:province":"South Holland",
    "wof:name":"Schoonderwoerd, Rob",
    "wof:placetype":"venue"
},
  "geometry": {"coordinates":[4.395717,52.049431],"type":"Point"}
}