{
  "type": "Feature",
  "properties": {
    "iso:country":"NL",
    "sg:address":"Aekerlaethofstraat 9",
    "sg:city":"Margraten",
    "sg:orig_category":"Fruit And Groenten Gh",
    "sg:phone":"+31 43 458 2218",
    "sg:postcode":"6269 DG",
    "sg:province":"Limburg",
    "wof:name":"Luc Wolfs",
    "wof:placetype":"venue"
},
  "geometry": {"coordinates":[5.824949,50.821259],"type":"Point"}
}