{
  "type": "Feature",
  "properties": {
    "addr:full":"Burg Jansenpln 50 Hengelo Ov NL.08 7551 ED",
    "addr:housenumber":"50",
    "addr:postcode":"7551 ed",
    "addr:street":"Burg;Ov",
    "iso:country":"NL",
    "sg:address":"Burg Jansenpln 50",
    "sg:city":"Hengelo Ov",
    "sg:classifiers":[
        {
            "category":"Food & Beverages",
            "subcategory":"Bakery",
            "type":"Retail Goods"
        }
    ],
    "sg:phone":"+31 74 290 9909",
    "sg:postcode":"7551 ED",
    "sg:province":"NL.08",
    "sg:tags":[
        "pizza"
    ],
    "wof:name":"Carello",
    "wof:placetype":"venue"
},
  "geometry": {"coordinates":[6.789712,52.266361],"type":"Point"}
}