{
  "type": "Feature",
  "properties": {
    "addr:full":"Minckelersstraat 4 Heerenveen Friesland 8442 CE",
    "addr:housenumber":"4",
    "addr:postcode":"8442 ce",
    "addr:street":"Minckelersstraat",
    "iso:country":"NL",
    "sg:address":"Minckelersstraat 4",
    "sg:city":"Heerenveen",
    "sg:orig_category":"Kappers",
    "sg:phone":"+31 513 627 333",
    "sg:postcode":"8442 CE",
    "sg:province":"Friesland",
    "wof:name":"Kapsalon Your Style",
    "wof:placetype":"venue"
},
  "geometry": {"coordinates":[5.9260182381,52.9592704773],"type":"Point"}
}