{
  "type": "Feature",
  "properties": {
    "addr:full":"Havenwg 17 Dronten Flevoland 8251 KB",
    "addr:housenumber":"17",
    "addr:postcode":"8251 kb",
    "addr:street":"Havenwg;Flevoland",
    "iso:country":"NL",
    "sg:address":"Havenwg 17",
    "sg:city":"Dronten",
    "sg:orig_category":"Wasmachines En Wasdrogers - Onderhoud En Reparatie",
    "sg:phone":"+31 321 315 489",
    "sg:postcode":"8251 KB",
    "sg:province":"Flevoland",
    "sg:website":"http://www.tsbhetanker.nl",
    "wof:name":"Anker, Het",
    "wof:placetype":"venue"
},
  "geometry": {"coordinates":[5.7176151276,52.529258728],"type":"Point"}
}