{
  "type": "Feature",
  "properties": {
    "addr:full":"Wolvenpln 14 Utrecht Utrecht 3512 CK",
    "addr:housenumber":"14",
    "addr:postcode":"3512 ck",
    "addr:street":"Wolvenpln",
    "iso:country":"NL",
    "sg:address":"Wolvenpln 14",
    "sg:city":"Utrecht",
    "sg:orig_category":"Beeldende Kunstenaars",
    "sg:phone":"+31 30 231 3730",
    "sg:postcode":"3512 CK",
    "sg:province":"Utrecht",
    "wof:name":"Laban En Zalewska",
    "wof:placetype":"venue"
},
  "geometry": {"coordinates":[5.125185,52.096298],"type":"Point"}
}