{
  "type": "Feature",
  "properties": {
    "addr:full":"Brunel 6 Uithoorn Noord-Holland 1422 RK",
    "addr:housenumber":"6",
    "addr:postcode":"1422 rk",
    "addr:street":"Brunel",
    "iso:country":"NL",
    "sg:address":"Brunel 6",
    "sg:city":"Uithoorn",
    "sg:orig_category":"Verzekeringen",
    "sg:phone":"+31 297 531 701",
    "sg:postcode":"1422 RK",
    "sg:province":"Noord-Holland",
    "wof:name":"Assurantiekantoor Bouwmeester",
    "wof:placetype":"venue"
},
  "geometry": {"coordinates":[4.816487,52.253548],"type":"Point"}
}