{
  "type": "Feature",
  "properties": {
    "iso:country":"NL",
    "sg:address":"Terbruggen 18",
    "sg:city":"Eygelshoven",
    "sg:orig_category":"Boekhouders",
    "sg:phone":"+31 45 567 1460",
    "sg:postcode":"6471 JV",
    "sg:province":"Limburg",
    "wof:name":"Administratiekantoor Limpens F R E",
    "wof:placetype":"venue"
},
  "geometry": {"coordinates":[6.057999,50.894161],"type":"Point"}
}