{
  "type": "Feature",
  "properties": {
    "iso:country":"NL",
    "sg:address":"Kleine Sint Jansstraat 11",
    "sg:city":"Amersfoort",
    "sg:orig_category":"Metaalbekleding And -Behandeling",
    "sg:phone":"+31 33 472 1031",
    "sg:postcode":"3811 HV",
    "sg:province":"Utrecht",
    "wof:name":"Ipenburg Bankwerkerij Bv",
    "wof:placetype":"venue"
},
  "geometry": {"coordinates":[5.394002,52.15667],"type":"Point"}
}