{
  "type": "Feature",
  "properties": {
    "iso:country":"NL",
    "sg:address":"Elspeterweg 26",
    "sg:city":"Nunspeet",
    "sg:orig_category":"Benzinestations And Brandstoffen",
    "sg:phone":"+31 341 253 067",
    "sg:postcode":"8071 PA",
    "sg:province":"Gelderland",
    "wof:name":"Shell",
    "wof:placetype":"venue"
},
  "geometry": {"coordinates":[5.785927,52.361362],"type":"Point"}
}