{
  "type": "Feature",
  "properties": {
    "addr:full":"Meerkoet 373 Diemen Noord-Holland 1113 EC",
    "addr:housenumber":"373",
    "addr:postcode":"1113 ec",
    "addr:street":"Meerkoet",
    "iso:country":"NL",
    "sg:address":"Meerkoet 373",
    "sg:city":"Diemen",
    "sg:orig_category":"Verzekeringen",
    "sg:phone":"+31 20 400 0915",
    "sg:postcode":"1113 EC",
    "sg:province":"Noord-Holland",
    "wof:name":"Flevas",
    "wof:placetype":"venue"
},
  "geometry": {"coordinates":[4.978399,52.351482],"type":"Point"}
}