{
  "type": "Feature",
  "properties": {
    "iso:country":"NL",
    "sg:address":"De Koppele 643",
    "sg:city":"Eindhoven",
    "sg:orig_category":"Technische Studies And Onderzoek",
    "sg:phone":"+31 40 241 0496",
    "sg:postcode":"5632 LS",
    "sg:province":"North Brabant",
    "wof:name":"R Looykens",
    "wof:placetype":"venue"
},
  "geometry": {"coordinates":[5.491003,51.481373],"type":"Point"}
}