{
  "type": "Feature",
  "properties": {
    "iso:country":"NL",
    "sg:address":"Tuniserf 34",
    "sg:city":"Rotterdam",
    "sg:orig_category":"Natuurvoeding En Reformartikelen",
    "sg:phone":"+31 10 461 2568",
    "sg:postcode":"3067 WV",
    "sg:province":"Zuid-Holland",
    "wof:name":"Finaly",
    "wof:placetype":"venue"
},
  "geometry": {"coordinates":[4.563438,51.947048],"type":"Point"}
}