{
  "type": "Feature",
  "properties": {
    "addr:full":"Muntpassage 1 Weert Limburg 6001 GL",
    "addr:housenumber":"1",
    "addr:postcode":"6001 gl",
    "addr:street":"Muntpassage",
    "iso:country":"NL",
    "sg:address":"Muntpassage 1",
    "sg:city":"Weert",
    "sg:orig_category":"Juweliers",
    "sg:phone":"+31 495 545 868",
    "sg:postcode":"6001 GL",
    "sg:province":"Limburg",
    "wof:name":"Luigi Lucardi Juweliers",
    "wof:placetype":"venue"
},
  "geometry": {"coordinates":[5.705095,51.25362],"type":"Point"}
}