{
  "type": "Feature",
  "properties": {
    "iso:country":"NL",
    "sg:address":"Dorpsstr 20",
    "sg:city":"Den Ham Ov",
    "sg:orig_category":"Wegenbouw",
    "sg:phone":"+31 546 678 888",
    "sg:postcode":"7683 BJ",
    "sg:province":"Overijssel",
    "wof:name":"Roelofs Bv",
    "wof:placetype":"venue"
},
  "geometry": {"coordinates":[6.4962739944,52.462387085],"type":"Point"}
}