{
  "type": "Feature",
  "properties": {
    "addr:full":"Marykestr 30 Sassenheim South Holland 2171 XD",
    "addr:housenumber":"30",
    "addr:postcode":"2171 xd",
    "addr:street":"Marykestr",
    "iso:country":"NL",
    "sg:address":"Marykestr 30",
    "sg:city":"Sassenheim",
    "sg:orig_category":"Bloemen En Planten - Groothandel",
    "sg:phone":"+31 252 212 896",
    "sg:postcode":"2171 XD",
    "sg:province":"South Holland",
    "sg:website":"http://www.oranjelily.nl",
    "wof:name":"Oranje Lily",
    "wof:placetype":"venue"
},
  "geometry": {"coordinates":[4.513285,52.225693],"type":"Point"}
}