{
  "type": "Feature",
  "properties": {
    "addr:full":"Noorderdijkweg 23 Wieringerwerf North Holland 1771 MJ",
    "addr:housenumber":"23",
    "addr:postcode":"1771 mj",
    "addr:street":"Noorderdijkweg",
    "iso:country":"NL",
    "sg:address":"Noorderdijkweg 23",
    "sg:city":"Wieringerwerf",
    "sg:orig_category":"Vakantiehuizen",
    "sg:phone":"+31 227 663 384",
    "sg:postcode":"1771 MJ",
    "sg:province":"North Holland",
    "wof:name":"Het Boshuis Vh Kamphuis Dijkgatsbos",
    "wof:placetype":"venue"
},
  "geometry": {"coordinates":[5.07744,52.887257],"type":"Point"}
}