{
  "type": "Feature",
  "properties": {
    "iso:country":"NL",
    "sg:address":"Hullerwg 107A",
    "sg:city":"Nunspeet",
    "sg:orig_category":"Horecabenodigdheden",
    "sg:phone":"+31 341 256 474",
    "sg:postcode":"8071 RN",
    "sg:province":"Gelderland",
    "wof:name":"Renselaar Bv",
    "wof:placetype":"venue"
},
  "geometry": {"coordinates":[5.767205,52.378014],"type":"Point"}
}