{
  "type": "Feature",
  "properties": {
    "addr:full":"Oosterengweg 90 Hilversum Noord-Holland 1212 CP",
    "addr:housenumber":"90",
    "addr:postcode":"1212 cp",
    "addr:street":"Oosterengweg",
    "iso:country":"NL",
    "sg:address":"Oosterengweg 90",
    "sg:city":"Hilversum",
    "sg:classifiers":[
        {
            "category":"Food & Beverages",
            "subcategory":"Fruits & Vegetables",
            "type":"Retail Goods"
        }
    ],
    "sg:phone":"+31 35 683 4830",
    "sg:postcode":"1212 CP",
    "sg:province":"Noord-Holland",
    "sg:tags":[
        "groenten"
    ],
    "wof:name":"Jan Zwama Groente- En Fruithoek",
    "wof:placetype":"venue"
},
  "geometry": {"coordinates":[5.19502,52.218803],"type":"Point"}
}