{
  "type": "Feature",
  "properties": {
    "addr:full":"Hogewg 135 Zaltbommel Gelderland 5301 LL",
    "addr:housenumber":"135",
    "addr:postcode":"5301 ll",
    "addr:street":"Gelderland",
    "iso:country":"NL",
    "sg:address":"Hogewg 135",
    "sg:city":"Zaltbommel",
    "sg:orig_category":"Accountants - Administratie- Consulenten En -Kantoren",
    "sg:phone":"+31 418 579 543",
    "sg:postcode":"5301 LL",
    "sg:province":"Gelderland",
    "sg:website":"http://www.noordacc.nl",
    "wof:name":"Noord, Van",
    "wof:placetype":"venue"
},
  "geometry": {"coordinates":[5.2563,51.80101],"type":"Point"}
}