{
  "type": "Feature",
  "properties": {
    "iso:country":"NL",
    "sg:address":"De Strikel 38",
    "sg:city":"Sneek",
    "sg:orig_category":"Verzekeringen - Verzekeringskantoren",
    "sg:phone":"+31 515 433 933",
    "sg:postcode":"8604 VV",
    "sg:province":"Friesland",
    "wof:name":"Kramer, B H",
    "wof:placetype":"venue"
},
  "geometry": {"coordinates":[5.686176,53.040871],"type":"Point"}
}