{
  "type": "Feature",
  "properties": {
    "iso:country":"NL",
    "sg:address":"Homerusstr 16",
    "sg:city":"Apeldoorn",
    "sg:orig_category":"Webdesign Bureaus",
    "sg:phone":"+31 55 367 1452",
    "sg:postcode":"7323 PX",
    "sg:province":"Gelderland",
    "wof:name":"Hendriksen",
    "wof:placetype":"venue"
},
  "geometry": {"coordinates":[6.0035638809,52.2228469849],"type":"Point"}
}