{
  "type": "Feature",
  "properties": {
    "addr:full":"Florijn 134 Hoorn Nh North Holland 1628 RP",
    "addr:housenumber":"134",
    "addr:postcode":"1628 rp",
    "addr:street":"Florijn;Nh North",
    "iso:country":"NL",
    "sg:address":"Florijn 134",
    "sg:city":"Hoorn Nh",
    "sg:orig_category":"Partycatering And -Organisatie",
    "sg:phone":"+31 229 216 102",
    "sg:postcode":"1628 RP",
    "sg:province":"North Holland",
    "wof:name":"Direct Catering",
    "wof:placetype":"venue"
},
  "geometry": {"coordinates":[5.090615,52.649506],"type":"Point"}
}