{
  "type": "Feature",
  "properties": {
    "addr:full":"Vyverpad 22 Gendringen Gelderland 7081 ET",
    "addr:housenumber":"22",
    "addr:postcode":"7081 et",
    "addr:street":"Vyverpad;Gelderland",
    "iso:country":"NL",
    "sg:address":"Vyverpad 22",
    "sg:city":"Gendringen",
    "sg:orig_category":"Adviesbureaus Bedrijfsorganisatie",
    "sg:phone":"+31 315 630 119",
    "sg:postcode":"7081 ET",
    "sg:province":"Gelderland",
    "wof:name":"Ploeg, Van Der",
    "wof:placetype":"venue"
},
  "geometry": {"coordinates":[6.373107,51.869549],"type":"Point"}
}