{
  "type": "Feature",
  "properties": {
    "addr:full":"Postbus 30126 Arnhem Gelderland 6803 AC",
    "addr:postcode":"30126;6803 ac",
    "addr:street":"Postbus",
    "iso:country":"NL",
    "sg:address":"Postbus 30126",
    "sg:city":"Arnhem",
    "sg:orig_category":"Vertalers",
    "sg:phone":"+31 26 327 4230",
    "sg:postcode":"6803 AC",
    "sg:province":"Gelderland",
    "wof:name":"Raisani, Drs N A",
    "wof:placetype":"venue"
},
  "geometry": {"coordinates":[5.9124,51.979729],"type":"Point"}
}