{
  "type": "Feature",
  "properties": {
    "addr:full":"Veldweg 35 Etten-Leur North Brabant 4874 ML",
    "addr:housenumber":"35",
    "addr:postcode":"4874 ml",
    "addr:street":"Veldweg",
    "iso:country":"NL",
    "sg:address":"Veldweg 35",
    "sg:city":"Etten-Leur",
    "sg:orig_category":"Verzekeringen",
    "sg:phone":"+31 76 501 5446",
    "sg:postcode":"4874 ML",
    "sg:province":"North Brabant",
    "wof:name":"Van Ginneken Assurantien Vof",
    "wof:placetype":"venue"
},
  "geometry": {"coordinates":[4.632366,51.577915],"type":"Point"}
}