{
  "type": "Feature",
  "properties": {
    "addr:full":"Haagweg 112 Rijswijk Zh Zuid-Holland 2282 AG",
    "addr:housenumber":"112",
    "addr:postcode":"zh;2282",
    "addr:street":"Haagweg",
    "iso:country":"NL",
    "sg:address":"Haagweg 112",
    "sg:city":"Rijswijk Zh",
    "sg:classifiers":[
        {
            "category":"Professional",
            "subcategory":"Accounting & Tax Preparation",
            "type":"Services"
        }
    ],
    "sg:phone":"+31 70 319 2555",
    "sg:postcode":"2282 AG",
    "sg:province":"Zuid-Holland",
    "sg:tags":[
        "accountant"
    ],
    "wof:name":"Sh&P Accountants",
    "wof:placetype":"venue"
},
  "geometry": {"coordinates":[4.338382,52.05574],"type":"Point"}
}