{
  "type": "Feature",
  "properties": {
    "addr:full":"Delftweg 35 Rotterdam Zuid-Holland 3043 CC",
    "addr:housenumber":"35",
    "addr:postcode":"3043 cc",
    "addr:street":"Delftweg",
    "iso:country":"NL",
    "sg:address":"Delftweg 35",
    "sg:city":"Rotterdam",
    "sg:orig_category":"Boekhouders",
    "sg:phone":"+31 10 437 4503",
    "sg:postcode":"3043 CC",
    "sg:province":"Zuid-Holland",
    "wof:name":"Administratiekantoor Barock",
    "wof:placetype":"venue"
},
  "geometry": {"coordinates":[4.421178,51.941635],"type":"Point"}
}