{
  "type": "Feature",
  "properties": {
    "addr:full":"Plesmanstr 6 Leusden Utrecht 3833 LA",
    "addr:housenumber":"6",
    "addr:postcode":"3833 la",
    "addr:street":"Plesmanstr",
    "iso:country":"NL",
    "sg:address":"Plesmanstr 6",
    "sg:city":"Leusden",
    "sg:orig_category":"Medische Installaties En Instrumenten",
    "sg:phone":"+31 33 434 7050",
    "sg:postcode":"3833 LA",
    "sg:province":"Utrecht",
    "wof:name":"Spectranetics Int Bv",
    "wof:placetype":"venue"
},
  "geometry": {"coordinates":[5.420633,52.144817],"type":"Point"}
}