{
  "type": "Feature",
  "properties": {
    "addr:full":"J Kriegestr 7 Woerden South Holland 3443 TJ",
    "addr:housenumber":"7",
    "addr:postcode":"3443 tj",
    "iso:country":"NL",
    "sg:address":"J Kriegestr 7",
    "sg:city":"Woerden",
    "sg:orig_category":"Loodgieters",
    "sg:phone":"+31 348 413 444",
    "sg:postcode":"3443 TJ",
    "sg:province":"South Holland",
    "wof:name":"Hoogendoorn Bv",
    "wof:placetype":"venue"
},
  "geometry": {"coordinates":[4.873054,52.087807],"type":"Point"}
}