{
  "type": "Feature",
  "properties": {
    "addr:full":"Hillevliet 28A Rotterdam Zuid-Holland 3074 KA",
    "addr:housenumber":"28a",
    "addr:postcode":"3074 ka",
    "addr:street":"Hillevliet",
    "iso:country":"NL",
    "sg:address":"Hillevliet 28A",
    "sg:city":"Rotterdam",
    "sg:orig_category":"Administratie- En Boekhoudkantoren",
    "sg:phone":"+31 10 423 1489",
    "sg:postcode":"3074 KA",
    "sg:province":"Zuid-Holland",
    "wof:name":"Koonings, C P",
    "wof:placetype":"venue"
},
  "geometry": {"coordinates":[4.504097,51.897026],"type":"Point"}
}