{
  "type": "Feature",
  "properties": {
    "addr:full":"Lindeboom 113 Mook Limburg 6585 BH",
    "addr:housenumber":"113",
    "addr:postcode":"6585 bh",
    "addr:street":"Lindeboom",
    "iso:country":"NL",
    "sg:address":"Lindeboom 113",
    "sg:city":"Mook",
    "sg:orig_category":"Fietshandelaren",
    "sg:phone":"+31 24 696 1744",
    "sg:postcode":"6585 BH",
    "sg:province":"Limburg",
    "wof:name":"G.J.A. Hendriks",
    "wof:placetype":"venue"
},
  "geometry": {"coordinates":[5.887576,51.746742],"type":"Point"}
}