{
  "type": "Feature",
  "properties": {
    "addr:full":"Rijnstraat 18 Woerden Utrecht 3441 BT",
    "addr:housenumber":"18",
    "addr:postcode":"3441 bt",
    "addr:street":"Rijnstraat",
    "iso:country":"NL",
    "sg:address":"Rijnstraat 18",
    "sg:city":"Woerden",
    "sg:orig_category":"Boekenuitgeverijen",
    "sg:phone":"+31 348 410 000",
    "sg:postcode":"3441 BT",
    "sg:province":"Utrecht",
    "wof:name":"Ako Woerden",
    "wof:placetype":"venue"
},
  "geometry": {"coordinates":[4.884089,52.086979],"type":"Point"}
}