{
  "type": "Feature",
  "properties": {
    "addr:full":"Binnenpad 102 Giethoorn NL.08 8355 BX",
    "addr:housenumber":"102;nl.08",
    "addr:postcode":"8355 bx",
    "addr:street":"Binnenpad",
    "iso:country":"NL",
    "sg:address":"Binnenpad 102",
    "sg:city":"Giethoorn",
    "sg:orig_category":"Jachthavens - Jachtwerven",
    "sg:phone":"+31 521 361 968",
    "sg:postcode":"8355 BX",
    "sg:province":"NL.08",
    "wof:name":"Jonkersgracht, Jachthaven",
    "wof:placetype":"venue"
},
  "geometry": {"coordinates":[6.07838,52.720314],"type":"Point"}
}