{
  "type": "Feature",
  "properties": {
    "addr:full":"Kanaalstr 187A Lisse Zuid-Holland 2161 JH",
    "addr:housenumber":"187a",
    "addr:postcode":"2161 jh",
    "iso:country":"NL",
    "sg:address":"Kanaalstr 187A",
    "sg:city":"Lisse",
    "sg:orig_category":"Kunstgebitten",
    "sg:phone":"+31 252 425 850",
    "sg:postcode":"2161 JH",
    "sg:province":"Zuid-Holland",
    "sg:website":"http://www.gebitskunst.nl",
    "wof:name":"Beektandprot. Praktijk, H M Van",
    "wof:placetype":"venue"
},
  "geometry": {"coordinates":[4.564462,52.257832],"type":"Point"}
}