{
  "type": "Feature",
  "properties": {
    "addr:full":"J V Wassenaerstr 68 Best Noord-Brabant 5684 CS",
    "addr:housenumber":"68",
    "addr:postcode":"5684 cs",
    "addr:street":"J;Wassenaerstr",
    "iso:country":"NL",
    "sg:address":"J V Wassenaerstr 68",
    "sg:city":"Best",
    "sg:orig_category":"Haptotherapeuten",
    "sg:phone":"+31 499 377 596",
    "sg:postcode":"5684 CS",
    "sg:province":"Noord-Brabant",
    "wof:name":"Schutboom Haptotherapie, De",
    "wof:placetype":"venue"
},
  "geometry": {"coordinates":[-101.618134,31.224251],"type":"Point"}
}