{
  "type": "Feature",
  "properties": {
    "addr:full":"Amstellandlaan 16 Weesp North Holland 1382 CE",
    "addr:housenumber":"16",
    "addr:postcode":"1382 ce",
    "addr:street":"Amstellandlaan",
    "iso:country":"NL",
    "sg:address":"Amstellandlaan 16",
    "sg:city":"Weesp",
    "sg:orig_category":"Opticiens",
    "sg:phone":"+31 294 414 100",
    "sg:postcode":"1382 CE",
    "sg:province":"North Holland",
    "wof:name":"Vroom En Nobbe Speciaal Optiek",
    "wof:placetype":"venue"
},
  "geometry": {"coordinates":[5.0337238312,52.3103713989],"type":"Point"}
}