{
  "type": "Feature",
  "properties": {
    "iso:country":"NL",
    "sg:address":"Spaarnwouderstr 88",
    "sg:city":"Haarlem",
    "sg:classifiers":[
        {
            "category":"Food & Beverages",
            "subcategory":"Bakery",
            "type":"Retail Goods"
        }
    ],
    "sg:phone":"+31 23 540 5192",
    "sg:postcode":"2011 AG",
    "sg:province":"Noord-Holland",
    "sg:tags":[
        "pizza"
    ],
    "wof:name":"Cupola, La",
    "wof:placetype":"venue"
},
  "geometry": {"coordinates":[4.644072,52.37994],"type":"Point"}
}