{
  "type": "Feature",
  "properties": {
    "addr:full":"Goolkatenweg 158 Enschede Overijssel 7521 BJ",
    "addr:housenumber":"158",
    "addr:postcode":"7521 bj",
    "addr:street":"Goolkatenweg",
    "iso:country":"NL",
    "sg:address":"Goolkatenweg 158",
    "sg:city":"Enschede",
    "sg:orig_category":"Artsen And Specialisten",
    "sg:phone":"+31 53 433 3282",
    "sg:postcode":"7521 BJ",
    "sg:province":"Overijssel",
    "wof:name":"Inst. Voor Orthopedagogie Drs. G.V.D. St",
    "wof:placetype":"venue"
},
  "geometry": {"coordinates":[6.874117,52.225983],"type":"Point"}
}