{
  "type": "Feature",
  "properties": {
    "addr:full":"Rondwg W 39 Dokkum Friesland 9101 BE",
    "addr:postcode":"9101",
    "addr:street":"W 39",
    "iso:country":"NL",
    "sg:address":"Rondwg W 39",
    "sg:city":"Dokkum",
    "sg:orig_category":"Keukens",
    "sg:phone":"+31 519 295 320",
    "sg:postcode":"9101 BE",
    "sg:province":"Friesland",
    "wof:name":"Laan Bv, Van Der",
    "wof:placetype":"venue"
},
  "geometry": {"coordinates":[5.986602,53.323933],"type":"Point"}
}