{
  "type": "Feature",
  "properties": {
    "addr:full":"T Koopmanpln 10 Rotterdam Zuid-Holland 3014 RT",
    "addr:housenumber":"10",
    "addr:postcode":"3014 rt",
    "iso:country":"NL",
    "sg:address":"T Koopmanpln 10",
    "sg:city":"Rotterdam",
    "sg:orig_category":"Verzekeringen - Verzekeringskantoren",
    "sg:phone":"+31 10 436 4722",
    "sg:postcode":"3014 RT",
    "sg:province":"Zuid-Holland",
    "wof:name":"Asbo",
    "wof:placetype":"venue"
},
  "geometry": {"coordinates":[4.466981,51.916759],"type":"Point"}
}