{
  "type": "Feature",
  "properties": {
    "addr:full":"Balkwg 4 S Hertogenbosch North Brabant 5232 BV",
    "addr:housenumber":"4",
    "addr:postcode":"5232 bv",
    "addr:street":"Balkwg",
    "iso:country":"NL",
    "sg:address":"Balkwg 4",
    "sg:city":"S Hertogenbosch",
    "sg:orig_category":"Autoverhuur",
    "sg:phone":"+31 73 642 8484",
    "sg:postcode":"5232 BV",
    "sg:province":"North Brabant",
    "sg:website":"http://www.budget.nl",
    "wof:name":"Budget Rent A Car",
    "wof:placetype":"venue"
},
  "geometry": {"coordinates":[5.337007,51.708649],"type":"Point"}
}