{
  "type": "Feature",
  "properties": {
    "addr:full":"Zuideinde 20-22 Monnickendam North Holland 1141 VJ",
    "addr:housenumber":"20-22",
    "addr:postcode":"1141 vj",
    "addr:street":"Zuideinde",
    "iso:country":"NL",
    "sg:address":"Zuideinde 20-22",
    "sg:city":"Monnickendam",
    "sg:orig_category":"Geschenkartikelen",
    "sg:phone":"+31 299 654 599",
    "sg:postcode":"1141 VJ",
    "sg:province":"North Holland",
    "wof:name":"Stadsboerderij",
    "wof:placetype":"venue"
},
  "geometry": {"coordinates":[5.037259,52.458847],"type":"Point"}
}