{
  "type": "Feature",
  "properties": {
    "iso:country":"NL",
    "sg:address":"Langsom 6-8",
    "sg:city":"Amsterdam",
    "sg:orig_category":"Autokeuringen",
    "sg:phone":"+31 20 615 3909",
    "sg:postcode":"1066 EW",
    "sg:province":"Noord-Holland",
    "wof:name":"Hulsebos Autoschade",
    "wof:placetype":"venue"
},
  "geometry": {"coordinates":[4.793866,52.341984],"type":"Point"}
}