{
  "type": "Feature",
  "properties": {
    "addr:full":"Kast Osenstr 1 Roermond Limburg 6043 HW",
    "addr:housenumber":"1",
    "addr:postcode":"6043 hw",
    "iso:country":"NL",
    "sg:address":"Kast Osenstr 1",
    "sg:city":"Roermond",
    "sg:orig_category":"Orthopedagogen",
    "sg:phone":"+31 475 324 145",
    "sg:postcode":"6043 HW",
    "sg:province":"Limburg",
    "wof:name":"Kwee-De Swart, Drs T M",
    "wof:placetype":"venue"
},
  "geometry": {"coordinates":[6.008535862,51.1913375854],"type":"Point"}
}