{
  "type": "Feature",
  "properties": {
    "iso:country":"NL",
    "sg:address":"Oude Ryksstrwg 23",
    "sg:city":"Twello",
    "sg:orig_category":"Sanitaire Artikelen",
    "sg:phone":"+31 571 274 523",
    "sg:postcode":"7391 MB",
    "sg:province":"Gelderland",
    "wof:name":"Kerkhof Installatiebedrijf",
    "wof:placetype":"venue"
},
  "geometry": {"coordinates":[6.091755,52.238213],"type":"Point"}
}