{
  "type": "Feature",
  "properties": {
    "addr:full":"Blankaartwg 1 Zoeterwoude Zuid-Holland 2381 AM",
    "addr:housenumber":"1",
    "addr:postcode":"2381",
    "addr:street":"Blankaartwg",
    "iso:country":"NL",
    "sg:address":"Blankaartwg 1",
    "sg:city":"Zoeterwoude",
    "sg:orig_category":"Grondwerken",
    "sg:phone":"+31 71 580 1141",
    "sg:postcode":"2381 AM",
    "sg:province":"Zuid-Holland",
    "wof:name":"Leeuwen, L Van",
    "wof:placetype":"venue"
},
  "geometry": {"coordinates":[4.49928,52.115891],"type":"Point"}
}