{
  "type": "Feature",
  "properties": {
    "iso:country":"NL",
    "sg:address":"Couperuswg 26",
    "sg:city":"Hilversum",
    "sg:orig_category":"Farmaceutische Industrie En Groothandel",
    "sg:phone":"+31 35 623 0612",
    "sg:postcode":"1217 TB",
    "sg:province":"Noord-Holland",
    "wof:name":"Foxhil Medical",
    "wof:placetype":"venue"
},
  "geometry": {"coordinates":[5.157465,52.222431],"type":"Point"}
}