{
  "type": "Feature",
  "properties": {
    "addr:full":"De Ploegschaar 129 Berkel-Enschot North Brabant 5056 MC",
    "addr:housenumber":"129",
    "addr:postcode":"5056 mc",
    "addr:street":"De Ploegschaar",
    "iso:country":"NL",
    "sg:address":"De Ploegschaar 129",
    "sg:city":"Berkel-Enschot",
    "sg:orig_category":"Beautyfarms And Sauna'S",
    "sg:phone":"+31 13 533 2726",
    "sg:postcode":"5056 MC",
    "sg:province":"North Brabant",
    "wof:name":"La Purete",
    "wof:placetype":"venue"
},
  "geometry": {"coordinates":[5.153777,51.589661],"type":"Point"}
}