{
  "type": "Feature",
  "properties": {
    "addr:full":"Landzichtln 68 Heemstede Noord-Holland 2101 ZK",
    "addr:housenumber":"68",
    "addr:postcode":"2101",
    "addr:street":"Landzichtln;Zk",
    "iso:country":"NL",
    "sg:address":"Landzichtln 68",
    "sg:city":"Heemstede",
    "sg:orig_category":"Organisatiebureaus",
    "sg:phone":"+31 23 529 2448",
    "sg:postcode":"2101 ZK",
    "sg:province":"Noord-Holland",
    "wof:name":"Oude Doos, De",
    "wof:placetype":"venue"
},
  "geometry": {"coordinates":[4.6212477684,52.345287323],"type":"Point"}
}