{
  "type": "Feature",
  "properties": {
    "addr:full":"Middendijk 54 Nijbroek Gelderland 7397 ND",
    "addr:housenumber":"54",
    "addr:postcode":"7397 nd",
    "addr:street":"Middendijk;Gelderland",
    "iso:country":"NL",
    "sg:address":"Middendijk 54",
    "sg:city":"Nijbroek",
    "sg:orig_category":"Levende Dieren Gh",
    "sg:phone":"+31 571 291 438",
    "sg:postcode":"7397 ND",
    "sg:province":"Gelderland",
    "wof:name":"Veehandel A.W. Veldwijk Bv",
    "wof:placetype":"venue"
},
  "geometry": {"coordinates":[6.062102,52.298355],"type":"Point"}
}