{
  "type": "Feature",
  "properties": {
    "addr:full":"S Gravendamseweg 67 Voorhout South Holland 2215 TG",
    "addr:housenumber":"67",
    "addr:postcode":"2215 tg",
    "iso:country":"NL",
    "sg:address":"S Gravendamseweg 67",
    "sg:city":"Voorhout",
    "sg:orig_category":"Verhuur Catering-, Feest- En Evenementbenodigdheden",
    "sg:phone":"+31 252 214 997",
    "sg:postcode":"2215 TG",
    "sg:province":"South Holland",
    "wof:name":"Zenit Horeca",
    "wof:placetype":"venue"
},
  "geometry": {"coordinates":[4.497317,52.243473],"type":"Point"}
}