{
  "type": "Feature",
  "properties": {
    "addr:full":"Noordeinde 15 Aarlanderveen South Holland 2445 XA",
    "addr:housenumber":"15",
    "addr:postcode":"2445 xa",
    "addr:street":"Noordeinde",
    "iso:country":"NL",
    "sg:address":"Noordeinde 15",
    "sg:city":"Aarlanderveen",
    "sg:orig_category":"Vakantiehuizen",
    "sg:phone":"+31 172 571 569",
    "sg:postcode":"2445 XA",
    "sg:province":"South Holland",
    "wof:name":"G.L. Van Veen",
    "wof:placetype":"venue"
},
  "geometry": {"coordinates":[4.724013,52.149487],"type":"Point"}
}