{
  "type": "Feature",
  "properties": {
    "iso:country":"NL",
    "sg:address":"Ln V Vlaanderen 261",
    "sg:city":"Amsterdam",
    "sg:orig_category":"Projectinrichting",
    "sg:phone":"+31 20 617 5830",
    "sg:postcode":"1066 JN",
    "sg:province":"North Holland",
    "wof:name":"Smit, M A",
    "wof:placetype":"venue"
},
  "geometry": {"coordinates":[4.811042,52.344707],"type":"Point"}
}