{
  "type": "Feature",
  "properties": {
    "addr:full":"Laurens Reaalstraat 32 Utrecht Utrecht 3531 GP",
    "addr:housenumber":"32",
    "addr:postcode":"3531 gp",
    "addr:street":"Laurens Reaalstraat",
    "iso:country":"NL",
    "sg:address":"Laurens Reaalstraat 32",
    "sg:city":"Utrecht",
    "sg:orig_category":"Boekhouders",
    "sg:phone":"+31 30 293 9298",
    "sg:postcode":"3531 GP",
    "sg:province":"Utrecht",
    "wof:name":"Haku (Hofman'S Administratiekantoor Utre",
    "wof:placetype":"venue"
},
  "geometry": {"coordinates":[5.096283,52.089203],"type":"Point"}
}