{
  "type": "Feature",
  "properties": {
    "addr:full":"Zeelberg 11 Valkenswaard North Brabant 5555 XH",
    "addr:housenumber":"11",
    "addr:postcode":"5555 xh",
    "addr:street":"Zeelberg",
    "iso:country":"NL",
    "sg:address":"Zeelberg 11",
    "sg:city":"Valkenswaard",
    "sg:orig_category":"Fotopersbureaus",
    "sg:phone":"+31 40 204 2288",
    "sg:postcode":"5555 XH",
    "sg:province":"North Brabant",
    "wof:name":"Nomocharis",
    "wof:placetype":"venue"
},
  "geometry": {"coordinates":[5.475811,51.343567],"type":"Point"}
}