{
  "type": "Feature",
  "properties": {
    "addr:full":"Boskamp 48 Vries Michigan 9481 JG",
    "addr:housenumber":"48",
    "addr:postcode":"9481 jg",
    "addr:street":"Boskamp",
    "iso:country":"NL",
    "sg:address":"Boskamp 48",
    "sg:city":"Vries",
    "sg:orig_category":"Autorijscholen",
    "sg:phone":"+31 592 543 172",
    "sg:postcode":"9481 JG",
    "sg:province":"Michigan",
    "wof:name":"Geerligs",
    "wof:placetype":"venue"
},
  "geometry": {"coordinates":[-85.944946,42.811916],"type":"Point"}
}