{
  "type": "Feature",
  "properties": {
    "iso:country":"NL",
    "sg:address":"Spaans Leger 23",
    "sg:city":"Enkhuizen",
    "sg:orig_category":"Binnenhuisarchitecten",
    "sg:phone":"+31 228 313 748",
    "sg:postcode":"1601 PB",
    "sg:province":"Noord-Holland",
    "wof:name":"Architektenburo Cor Roosendaal Vof",
    "wof:placetype":"venue"
},
  "geometry": {"coordinates":[5.28614,52.704914],"type":"Point"}
}