{
  "type": "Feature",
  "properties": {
    "iso:country":"NL",
    "sg:address":"Boerenburgerwg 11",
    "sg:city":"Noordwyk Zh",
    "sg:orig_category":"Adviesbureaus Bedrijfsorganisatie",
    "sg:phone":"+31 71 362 0471",
    "sg:postcode":"2201 PM",
    "sg:province":"Zuid-Holland",
    "wof:name":"Heemskerk",
    "wof:placetype":"venue"
},
  "geometry": {"coordinates":[4.447949,52.238194],"type":"Point"}
}