{
  "type": "Feature",
  "properties": {
    "addr:full":"Edisonwg 5 Gorinchem South Holland 4207 HE",
    "addr:housenumber":"5",
    "addr:postcode":"4207 he",
    "addr:street":"Edisonwg",
    "iso:country":"NL",
    "sg:address":"Edisonwg 5",
    "sg:city":"Gorinchem",
    "sg:orig_category":"Autolakken",
    "sg:phone":"+31 183 616 175",
    "sg:postcode":"4207 HE",
    "sg:province":"South Holland",
    "sg:website":"http://www.spectrumverf.nl",
    "wof:name":"Spectrum Bv",
    "wof:placetype":"venue"
},
  "geometry": {"coordinates":[4.991247,51.840965],"type":"Point"}
}