{
  "type": "Feature",
  "properties": {
    "addr:full":"Verl Herenstr 47 Sappemeer Groningen 9611 BM",
    "addr:housenumber":"47",
    "addr:postcode":"9611 bm",
    "iso:country":"NL",
    "sg:address":"Verl Herenstr 47",
    "sg:city":"Sappemeer",
    "sg:orig_category":"Kappers",
    "sg:phone":"+31 598 381 688",
    "sg:postcode":"9611 BM",
    "sg:province":"Groningen",
    "wof:name":"New Style",
    "wof:placetype":"venue"
},
  "geometry": {"coordinates":[6.799814,53.165344],"type":"Point"}
}