{
  "type": "Feature",
  "properties": {
    "addr:full":"Maalbroek 145 Roermond Limburg 6042 KM",
    "addr:housenumber":"145",
    "addr:postcode":"6042 km",
    "addr:street":"Maalbroek",
    "iso:country":"NL",
    "sg:address":"Maalbroek 145",
    "sg:city":"Roermond",
    "sg:orig_category":"Schilders",
    "sg:phone":"+31 475 324 425",
    "sg:postcode":"6042 KM",
    "sg:province":"Limburg",
    "wof:name":"Aelmans, F",
    "wof:placetype":"venue"
},
  "geometry": {"coordinates":[6.035779,51.201218],"type":"Point"}
}