{
  "type": "Feature",
  "properties": {
    "addr:full":"Leidsestraat 94 Amsterdam Noord-Holland 1017 PE",
    "addr:housenumber":"94",
    "addr:postcode":"1017 pe",
    "addr:street":"Leidsestraat",
    "iso:country":"NL",
    "sg:address":"Leidsestraat 94",
    "sg:city":"Amsterdam",
    "sg:classifiers":[
        {
            "category":"Fast Food",
            "type":"Food & Drink"
        }
    ],
    "sg:phone":"+31 20 620 8615",
    "sg:postcode":"1017 PE",
    "sg:province":"Noord-Holland",
    "sg:tags":[
        "afhaal",
        "restaurant"
    ],
    "wof:name":"Febo Leidsestraat",
    "wof:placetype":"venue"
},
  "geometry": {"coordinates":[4.883702,52.364834],"type":"Point"}
}