{
  "type": "Feature",
  "properties": {
    "iso:country":"NL",
    "sg:address":"Polderweg 62",
    "sg:city":"Den Helder",
    "sg:orig_category":"Kappers",
    "sg:phone":"+31 223 616 600",
    "sg:postcode":"1782 EB",
    "sg:province":"Noord-Holland",
    "wof:name":"Ju-Line Hairspecialist",
    "wof:placetype":"venue"
},
  "geometry": {"coordinates":[4.7592658997,52.9599227905],"type":"Point"}
}