{
  "type": "Feature",
  "properties": {
    "addr:full":"Wielewaalstr 13 Delft South Holland 2623 GT",
    "addr:housenumber":"13",
    "addr:postcode":"2623 gt",
    "addr:street":"Wielewaalstr",
    "iso:country":"NL",
    "sg:address":"Wielewaalstr 13",
    "sg:city":"Delft",
    "sg:orig_category":"Projectinrichting",
    "sg:phone":"+31 15 257 8026",
    "sg:postcode":"2623 GT",
    "sg:province":"South Holland",
    "wof:name":"Ekelschot, C J",
    "wof:placetype":"venue"
},
  "geometry": {"coordinates":[4.366392,51.984455],"type":"Point"}
}