{
  "type": "Feature",
  "properties": {
    "iso:country":"NL",
    "sg:address":"Brugstraat 23",
    "sg:city":"Hengelo Ov",
    "sg:orig_category":"Verzekeringen",
    "sg:phone":"+31 74 250 0900",
    "sg:postcode":"7551 BX",
    "sg:province":"NL.08",
    "wof:name":"Louis Jannink Assurantien",
    "wof:placetype":"venue"
},
  "geometry": {"coordinates":[6.789112,52.264084],"type":"Point"}
}