{
  "type": "Feature",
  "properties": {
    "iso:country":"NL",
    "sg:address":"Thorbeckeplein 8",
    "sg:city":"Amersfoort",
    "sg:orig_category":"Boekenuitgeverijen",
    "sg:phone":"+31 33 461 0501",
    "sg:postcode":"3818 JL",
    "sg:province":"Utrecht",
    "wof:name":"Stuurman Promotions Vof",
    "wof:placetype":"venue"
},
  "geometry": {"coordinates":[5.368844,52.15126],"type":"Point"}
}