{
  "type": "Feature",
  "properties": {
    "iso:country":"NL",
    "sg:address":"Locht 17-19",
    "sg:city":"Veldhoven",
    "sg:orig_category":"Boekhandels",
    "sg:phone":"+31 40 253 4878",
    "sg:postcode":"5504 KA",
    "sg:province":"Noord-Brabant",
    "wof:name":"Beto Bv",
    "wof:placetype":"venue"
},
  "geometry": {"coordinates":[5.39617,51.401505],"type":"Point"}
}