{
  "type": "Feature",
  "properties": {
    "addr:full":"Triangel 67 Ewyk Gelderland 6644 BA",
    "addr:housenumber":"67",
    "addr:postcode":"6644 ba",
    "addr:street":"Triangel;Gelderland",
    "iso:country":"NL",
    "sg:address":"Triangel 67",
    "sg:city":"Ewyk",
    "sg:orig_category":"Huishoudelijke Apparaten En Artikelen",
    "sg:phone":"+31 487 525 937",
    "sg:postcode":"6644 BA",
    "sg:province":"Gelderland",
    "wof:name":"Big Power",
    "wof:placetype":"venue"
},
  "geometry": {"coordinates":[10.58734,52.508511],"type":"Point"}
}