{
  "type": "Feature",
  "properties": {
    "addr:full":"Marktstg 10A Leiden Zuid-Holland 2312 CS",
    "addr:housenumber":"10a",
    "addr:postcode":"2312 cs",
    "addr:street":"Marktstg",
    "iso:country":"NL",
    "sg:address":"Marktstg 10A",
    "sg:city":"Leiden",
    "sg:orig_category":"Beeldende Kunstenaars",
    "sg:phone":"+31 71 514 1872",
    "sg:postcode":"2312 CS",
    "sg:province":"Zuid-Holland",
    "sg:website":"http://www.kunstenko.nl",
    "wof:name":"Kunst & Ko",
    "wof:placetype":"venue"
},
  "geometry": {"coordinates":[4.488386,52.163197],"type":"Point"}
}