{
  "type": "Feature",
  "properties": {
    "iso:country":"NL",
    "sg:address":"Kelnarijstraat 40",
    "sg:city":"Putten",
    "sg:classifiers":[
        {
            "category":"Education",
            "subcategory":"Preschool",
            "type":"Public Place"
        }
    ],
    "sg:phone":"+31 341 351 959",
    "sg:postcode":"3881 CC",
    "sg:province":"Gelderland",
    "sg:tags":[
        "kleuteronderwijs",
        "basis-"
    ],
    "wof:name":"Gabrielschool",
    "wof:placetype":"venue"
},
  "geometry": {"coordinates":[5.608631,52.263874],"type":"Point"}
}