{
  "type": "Feature",
  "properties": {
    "addr:full":"Jadeln 127 Hoofddorp North Holland 2132 XZ",
    "addr:housenumber":"127",
    "addr:postcode":"2132 xz",
    "iso:country":"NL",
    "sg:address":"Jadeln 127",
    "sg:city":"Hoofddorp",
    "sg:orig_category":"Waterbehandeling En Waterzuiverings- Systemen",
    "sg:phone":"+31 23 555 6624",
    "sg:postcode":"2132 XZ",
    "sg:province":"North Holland",
    "wof:name":"Gr?nbeck Holland Bv",
    "wof:placetype":"venue"
},
  "geometry": {"coordinates":[4.6929597855,52.305393219],"type":"Point"}
}