{
  "type": "Feature",
  "properties": {
    "addr:full":"K Doormanstr 46 Bodegraven Zuid-Holland 2411 VG",
    "addr:housenumber":"46",
    "addr:postcode":"2411 vg",
    "addr:street":"Doormanstr",
    "iso:country":"NL",
    "sg:address":"K Doormanstr 46",
    "sg:city":"Bodegraven",
    "sg:orig_category":"Bestratingen",
    "sg:phone":"+31 172 617 497",
    "sg:postcode":"2411 VG",
    "sg:province":"Zuid-Holland",
    "wof:name":"Kooten, Van",
    "wof:placetype":"venue"
},
  "geometry": {"coordinates":[4.7521,52.087658],"type":"Point"}
}