{
  "type": "Feature",
  "properties": {
    "addr:full":"W V Noortpln 13 Utrecht Utrecht 3514 GK",
    "addr:housenumber":"13",
    "addr:postcode":"3514 gk",
    "addr:street":"W V Noortpln",
    "iso:country":"NL",
    "sg:address":"W V Noortpln 13",
    "sg:city":"Utrecht",
    "sg:orig_category":"Herenkleding",
    "sg:phone":"+31 30 271 1712",
    "sg:postcode":"3514 GK",
    "sg:province":"Utrecht",
    "wof:name":"Bastiaanse",
    "wof:placetype":"venue"
},
  "geometry": {"coordinates":[5.115405,52.088932],"type":"Point"}
}