{
  "type": "Feature",
  "properties": {
    "addr:full":"Ds Theodor Fliednerstr 1 Eindhoven Noord-Brabant 5631 BM",
    "addr:housenumber":"1",
    "addr:postcode":"5631 bm",
    "addr:street":"Ds Theodor Fliednerstr",
    "iso:country":"NL",
    "sg:address":"Ds Theodor Fliednerstr 1",
    "sg:city":"Eindhoven",
    "sg:orig_category":"Bloed- And Andere Donoren",
    "sg:phone":"+31 40 244 1766",
    "sg:postcode":"5631 BM",
    "sg:province":"Noord-Brabant",
    "wof:name":"Bloedbank De Meierij",
    "wof:placetype":"venue"
},
  "geometry": {"coordinates":[5.488118,51.454517],"type":"Point"}
}