{
  "type": "Feature",
  "properties": {
    "addr:full":"Nieuwe Veenendaalseweg 102 Rhenen Utrecht 3911 ML",
    "addr:housenumber":"102",
    "addr:postcode":"3911 ml",
    "addr:street":"Nieuwe Veenendaalseweg",
    "iso:country":"NL",
    "sg:address":"Nieuwe Veenendaalseweg 102",
    "sg:city":"Rhenen",
    "sg:orig_category":"Beursorganisaties And Standbouw",
    "sg:phone":"+31 317 616 169",
    "sg:postcode":"3911 ML",
    "sg:province":"Utrecht",
    "wof:name":"Kramer In-/Exterieur-Vormgeving",
    "wof:placetype":"venue"
},
  "geometry": {"coordinates":[5.568722,51.961483],"type":"Point"}
}