{
  "type": "Feature",
  "properties": {
    "iso:country":"NL",
    "sg:address":"Wetering 13 , (Mobiele Telefoon)",
    "sg:city":"Gemert",
    "sg:orig_category":"Metselwerken",
    "sg:phone":"+31 6 51591943",
    "sg:postcode":"5422 AN",
    "sg:province":"North Brabant",
    "wof:name":"Martens, P",
    "wof:placetype":"venue"
},
  "geometry": {"coordinates":[5.70107,51.557884],"type":"Point"}
}