{
  "type": "Feature",
  "properties": {
    "iso:country":"NL",
    "sg:address":"Tolheksln 1",
    "sg:city":"Frieschepalen",
    "sg:orig_category":"Wasmachines En Wasdrogers - Onderhoud En Reparatie",
    "sg:phone":"+31 512 301 924",
    "sg:postcode":"9249 NN",
    "sg:province":"Friesland",
    "wof:name":"Wagenaar, Piet",
    "wof:placetype":"venue"
},
  "geometry": {"coordinates":[6.2061400414,53.1106758118],"type":"Point"}
}