{
  "type": "Feature",
  "properties": {
    "addr:full":"Grote Staat 5 Maastricht Limburg 6211 CT",
    "addr:housenumber":"5",
    "addr:postcode":"6211 ct",
    "addr:street":"Grote Staat",
    "iso:country":"NL",
    "sg:address":"Grote Staat 5",
    "sg:city":"Maastricht",
    "sg:orig_category":"Verzekeringen",
    "sg:phone":"+31 43 350 0169",
    "sg:postcode":"6211 CT",
    "sg:province":"Limburg",
    "wof:name":"Vendopolis",
    "wof:placetype":"venue"
},
  "geometry": {"coordinates":[5.692074,50.849739],"type":"Point"}
}