{
  "type": "Feature",
  "properties": {
    "iso:country":"NL",
    "sg:address":"De Cordesstr 93",
    "sg:city":"Hoek Van Holland",
    "sg:orig_category":"Projectontwikkeling",
    "sg:phone":"+31 174 382 223",
    "sg:postcode":"3151 BK",
    "sg:province":"South Holland",
    "wof:name":"Gww",
    "wof:placetype":"venue"
},
  "geometry": {"coordinates":[4.133998,51.977291],"type":"Point"}
}