{
  "type": "Feature",
  "properties": {
    "addr:full":"Grotestraat 3 Cuijk North Brabant 5431 DG",
    "addr:housenumber":"3",
    "addr:postcode":"5431 dg",
    "addr:street":"Grotestraat",
    "iso:country":"NL",
    "sg:address":"Grotestraat 3",
    "sg:city":"Cuijk",
    "sg:orig_category":"Verhuur Catering-, Feest- En Evenementbenodigdheden",
    "sg:phone":"+31 485 330 394",
    "sg:postcode":"5431 DG",
    "sg:province":"North Brabant",
    "wof:name":"Flash Amusementscenters",
    "wof:placetype":"venue"
},
  "geometry": {"coordinates":[5.827292,51.725548],"type":"Point"}
}