{
  "type": "Feature",
  "properties": {
    "iso:country":"NL",
    "sg:address":"Roosendaalsewg 188",
    "sg:city":"Putten",
    "sg:orig_category":"Grondwerken",
    "sg:phone":"+31 341 492 233",
    "sg:postcode":"3882 MP",
    "sg:province":"Gelderland",
    "wof:name":"Esveld, J",
    "wof:placetype":"venue"
},
  "geometry": {"coordinates":[5.58369,52.241825],"type":"Point"}
}