{
  "type": "Feature",
  "properties": {
    "addr:full":"Schoorlaan 39 Leidschendam Zuid-Holland 2265 VS",
    "addr:housenumber":"39",
    "addr:postcode":"2265 vs",
    "addr:street":"Schoorlaan",
    "iso:country":"NL",
    "sg:address":"Schoorlaan 39",
    "sg:city":"Leidschendam",
    "sg:orig_category":"Architecten",
    "sg:phone":"+31 70 317 7322",
    "sg:postcode":"2265 VS",
    "sg:province":"Zuid-Holland",
    "wof:name":"Architectenbureau Immerzeel De Vries Bv",
    "wof:placetype":"venue"
},
  "geometry": {"coordinates":[4.399881,52.082619],"type":"Point"}
}