{
  "type": "Feature",
  "properties": {
    "addr:full":"Frankenstr 43 Maastricht Limburg 6226 AB",
    "addr:housenumber":"43",
    "addr:postcode":"6226 ab",
    "addr:street":"Frankenstr",
    "iso:country":"NL",
    "sg:address":"Frankenstr 43",
    "sg:city":"Maastricht",
    "sg:orig_category":"Kappers",
    "sg:phone":"+31 43 362 1545",
    "sg:postcode":"6226 AB",
    "sg:province":"Limburg",
    "wof:name":"Jackson",
    "wof:placetype":"venue"
},
  "geometry": {"coordinates":[5.7185277939,50.8520050049],"type":"Point"}
}