{
  "type": "Feature",
  "properties": {
    "addr:full":"Haagwinde 1 Vught Noord-Brabant 5262 KZ",
    "addr:housenumber":"1",
    "addr:postcode":"5262 kz",
    "addr:street":"Haagwinde",
    "iso:country":"NL",
    "sg:address":"Haagwinde 1",
    "sg:city":"Vught",
    "sg:orig_category":"Binnenhuisarchitecten",
    "sg:phone":"+31 73 657 1519",
    "sg:postcode":"5262 KZ",
    "sg:province":"Noord-Brabant",
    "wof:name":"Projectbureau Fennis",
    "wof:placetype":"venue"
},
  "geometry": {"coordinates":[5.271853,51.640938],"type":"Point"}
}