{
  "type": "Feature",
  "properties": {
    "addr:full":"Oranjerie 360 Apeldoorn Gelderland 7311 WS",
    "addr:housenumber":"360",
    "addr:postcode":"7311 ws",
    "addr:street":"Oranjerie;Gelderland",
    "iso:country":"NL",
    "sg:address":"Oranjerie 360",
    "sg:city":"Apeldoorn",
    "sg:orig_category":"Linnenshops",
    "sg:phone":"+31 55 578 7986",
    "sg:postcode":"7311 WS",
    "sg:province":"Gelderland",
    "wof:name":"Linnengalerie",
    "wof:placetype":"venue"
},
  "geometry": {"coordinates":[5.96253,52.21278],"type":"Point"}
}