{
  "type": "Feature",
  "properties": {
    "iso:country":"NL",
    "sg:address":"Galgeneind 4",
    "sg:city":"De Moer",
    "sg:orig_category":"Vakantieverblijven",
    "sg:phone":"+31 13 515 9233",
    "sg:postcode":"5176 NN",
    "sg:province":"Noord-Brabant",
    "wof:name":"Moertje, 'T",
    "wof:placetype":"venue"
},
  "geometry": {"coordinates":[5.012026,51.615318],"type":"Point"}
}