{
  "type": "Feature",
  "properties": {
    "iso:country":"NL",
    "sg:address":"Beltrumsewg 42",
    "sg:city":"Eibergen",
    "sg:orig_category":"Autorijscholen",
    "sg:phone":"+31 545 473 221",
    "sg:postcode":"7151 EW",
    "sg:province":"Gelderland",
    "wof:name":"Stellinga",
    "wof:placetype":"venue"
},
  "geometry": {"coordinates":[6.637784,52.09882],"type":"Point"}
}