{
  "type": "Feature",
  "properties": {
    "addr:full":"Steenstraat 87 Boxmeer Noord-Brabant 5831 JC",
    "addr:housenumber":"87",
    "addr:postcode":"5831 jc",
    "addr:street":"Steenstraat",
    "iso:country":"NL",
    "sg:address":"Steenstraat 87",
    "sg:city":"Boxmeer",
    "sg:orig_category":"Schoenen",
    "sg:phone":"+31 485 571 452",
    "sg:postcode":"5831 JC",
    "sg:province":"Noord-Brabant",
    "wof:name":"Schoenlederhandel Jos Van Bommel",
    "wof:placetype":"venue"
},
  "geometry": {"coordinates":[5.949169,51.648193],"type":"Point"}
}