{
  "type": "Feature",
  "properties": {
    "iso:country":"NL",
    "sg:address":"Molenstr 22",
    "sg:city":"Oldenzaal",
    "sg:orig_category":"Fotoreportages",
    "sg:phone":"+31 541 512 865",
    "sg:postcode":"7571 CN",
    "sg:province":"Overijssel",
    "wof:name":"Kalma",
    "wof:placetype":"venue"
},
  "geometry": {"coordinates":[6.932074,52.315563],"type":"Point"}
}