{
  "type": "Feature",
  "properties": {
    "addr:full":"Amer 6 Gemert North Brabant 5422 VR",
    "addr:housenumber":"6",
    "addr:postcode":"5422 vr",
    "addr:street":"Amer",
    "iso:country":"NL",
    "sg:address":"Amer 6",
    "sg:city":"Gemert",
    "sg:orig_category":"Meubelreparatie And -Restauratie",
    "sg:phone":"+31 492 390 222",
    "sg:postcode":"5422 VR",
    "sg:province":"North Brabant",
    "wof:name":"Verstegen Meubelstoffering Vof",
    "wof:placetype":"venue"
},
  "geometry": {"coordinates":[5.70518,51.565922],"type":"Point"}
}