{
  "type": "Feature",
  "properties": {
    "addr:full":"Hortusln 6D Sassenheim Zuid-Holland 2171 CK",
    "addr:housenumber":"6d",
    "addr:postcode":"sassenheim;2171 ck",
    "iso:country":"NL",
    "sg:address":"Hortusln 6D",
    "sg:city":"Sassenheim",
    "sg:orig_category":"Fietsen En Bromfietsen",
    "sg:phone":"+31 252 220 906",
    "sg:postcode":"2171 CK",
    "sg:province":"Zuid-Holland",
    "sg:website":"http://www.profile.nl",
    "wof:name":"Profile",
    "wof:placetype":"venue"
},
  "geometry": {"coordinates":[4.519567,52.223663],"type":"Point"}
}