{
  "type": "Feature",
  "properties": {
    "addr:full":"Steenweg Roermond Limburg 6041 HD",
    "addr:postcode":"6041 hd",
    "addr:street":"Steenweg",
    "iso:country":"NL",
    "sg:address":"Steenweg",
    "sg:city":"Roermond",
    "sg:orig_category":"Koopzondagen Zondag 1 December 2002",
    "sg:phone":"+31 263",
    "sg:postcode":"6041 HD",
    "sg:province":"Limburg",
    "wof:name":"Roermond Winkelcentrum City",
    "wof:placetype":"venue"
},
  "geometry": {"coordinates":[5.986942,51.194111],"type":"Point"}
}