{
  "type": "Feature",
  "properties": {
    "addr:full":"H Tollensstr 202 Delft Zuid-Holland 2624 BM",
    "addr:housenumber":"202",
    "addr:postcode":"delft;2624 bm",
    "iso:country":"NL",
    "sg:address":"H Tollensstr 202",
    "sg:city":"Delft",
    "sg:classifiers":[
        {
            "category":"Personal",
            "subcategory":"Nail Salon",
            "type":"Services"
        }
    ],
    "sg:phone":"+31 15 261 4034",
    "sg:postcode":"2624 BM",
    "sg:province":"Zuid-Holland",
    "sg:tags":[
        "pedicure"
    ],
    "wof:name":"Petronella",
    "wof:placetype":"venue"
},
  "geometry": {"coordinates":[4.355809,51.996307],"type":"Point"}
}