{
  "type": "Feature",
  "properties": {
    "addr:full":"Multatuliln 6 Roosendaal Noord-Brabant 4707 LZ",
    "addr:housenumber":"6",
    "addr:postcode":"4707 lz",
    "addr:street":"Multatuliln",
    "iso:country":"NL",
    "sg:address":"Multatuliln 6",
    "sg:city":"Roosendaal",
    "sg:orig_category":"Accountants - Administratie- Consulenten En -Kantoren",
    "sg:phone":"+31 165 594 600",
    "sg:postcode":"4707 LZ",
    "sg:province":"Noord-Brabant",
    "sg:website":"http://www.hhl-groep.nl",
    "wof:name":"Hanegraaf Hoendervangers Luijkx",
    "wof:placetype":"venue"
},
  "geometry": {"coordinates":[4.45767,51.531403],"type":"Point"}
}