{
  "type": "Feature",
  "properties": {
    "iso:country":"NL",
    "sg:address":"Parklaan 9",
    "sg:city":"Rotterdam",
    "sg:orig_category":"Overheidsdiensten",
    "sg:phone":"+31 10 436 2224",
    "sg:postcode":"3016 BA",
    "sg:province":"South Holland",
    "wof:name":"Waterstad Vereniging",
    "wof:placetype":"venue"
},
  "geometry": {"coordinates":[4.4750781059,51.9081268311],"type":"Point"}
}