{
  "type": "Feature",
  "properties": {
    "addr:full":"Boezemwg 13 Waddinxveen Zuid-Holland 2741 MV",
    "addr:housenumber":"13",
    "addr:postcode":"2741 mv",
    "addr:street":"Boezemwg",
    "iso:country":"NL",
    "sg:address":"Boezemwg 13",
    "sg:city":"Waddinxveen",
    "sg:orig_category":"Manueel Therapeuten",
    "sg:phone":"+31 182 618 695",
    "sg:postcode":"2741 MV",
    "sg:province":"Zuid-Holland",
    "wof:name":"Boezemweg",
    "wof:placetype":"venue"
},
  "geometry": {"coordinates":[4.653523,52.037075],"type":"Point"}
}