{
  "type": "Feature",
  "properties": {
    "iso:country":"NL",
    "sg:address":"Boezemwg 13",
    "sg:city":"Waddinxveen",
    "sg:orig_category":"Manueel Therapeuten",
    "sg:phone":"+31 182 618 695",
    "sg:postcode":"2741 MV",
    "sg:province":"Zuid-Holland",
    "wof:name":"Boezemweg",
    "wof:placetype":"venue"
},
  "geometry": {"coordinates":[4.653523,52.037075],"type":"Point"}
}