{
  "type": "Feature",
  "properties": {
    "iso:country":"NL",
    "sg:address":"Cronjestraat 46",
    "sg:city":"Ermelo",
    "sg:classifiers":[
        {
            "category":"Education",
            "subcategory":"Preschool",
            "type":"Public Place"
        }
    ],
    "sg:phone":"+31 341 554 232",
    "sg:postcode":"3851 ZS",
    "sg:province":"Gelderland",
    "sg:tags":[
        "kleuteronderwijs",
        "basis-"
    ],
    "wof:name":"Openbare Basisschool De Waterval",
    "wof:placetype":"venue"
},
  "geometry": {"coordinates":[5.616011,52.291233],"type":"Point"}
}