{
  "type": "Feature",
  "properties": {
    "addr:full":"Achterstr 26E Woerden Utrecht 3441 EH",
    "addr:housenumber":"26e",
    "addr:postcode":"3441 eh",
    "addr:street":"Achterstr",
    "iso:country":"NL",
    "sg:address":"Achterstr 26E",
    "sg:city":"Woerden",
    "sg:orig_category":"Wijnkoperijen En -Groothandel",
    "sg:phone":"+31 348 433 497",
    "sg:postcode":"3441 EH",
    "sg:province":"Utrecht",
    "wof:name":"Krimpenfort-Sommelier, Y",
    "wof:placetype":"venue"
},
  "geometry": {"coordinates":[4.886785984,52.0863647461],"type":"Point"}
}