{
  "type": "Feature",
  "properties": {
    "addr:full":"Prins Frederiklaan 484 Leidschendam Zuid-Holland 2263 HP",
    "addr:housenumber":"484",
    "addr:postcode":"2263 hp",
    "addr:street":"Prins Frederiklaan",
    "iso:country":"NL",
    "sg:address":"Prins Frederiklaan 484",
    "sg:city":"Leidschendam",
    "sg:orig_category":"Artiesten",
    "sg:phone":"+31 70 327 4040",
    "sg:postcode":"2263 HP",
    "sg:province":"Zuid-Holland",
    "wof:name":"Th H J Verharen",
    "wof:placetype":"venue"
},
  "geometry": {"coordinates":[4.402915,52.096977],"type":"Point"}
}