{
  "type": "Feature",
  "properties": {
    "addr:full":"De Hout 28 Hem Georgia 1607 HC",
    "addr:housenumber":"28",
    "addr:postcode":"1607 hc",
    "addr:street":"De Hout;Georgia",
    "iso:country":"NL",
    "sg:address":"De Hout 28",
    "sg:city":"Hem",
    "sg:orig_category":"Bedrijfsopleidingen",
    "sg:phone":"+31 228 542 614",
    "sg:postcode":"1607 HC",
    "sg:province":"Georgia",
    "sg:website":"http://www.swanci.nl",
    "wof:name":"Swan",
    "wof:placetype":"venue"
},
  "geometry": {"coordinates":[-84.171921,34.890556],"type":"Point"}
}