{
  "type": "Feature",
  "properties": {
    "addr:full":"Lombokstraat 1 'S Gravenhage Zuid-Holland 2585 VP",
    "addr:housenumber":"1 '",
    "addr:postcode":"2585 vp",
    "addr:street":"Lombokstraat",
    "iso:country":"NL",
    "sg:address":"Lombokstraat 1",
    "sg:city":"'S Gravenhage",
    "sg:orig_category":"Advocaten And Juridische Adviseurs",
    "sg:phone":"+31 70 352 1880",
    "sg:postcode":"2585 VP",
    "sg:province":"Zuid-Holland",
    "wof:name":"Advocatenkantoor Mr. E. Lievens Bv",
    "wof:placetype":"venue"
},
  "geometry": {"coordinates":[4.304475,52.093758],"type":"Point"}
}