{
  "type": "Feature",
  "properties": {
    "addr:full":"Dorpsstraat 15 Zevenhoven South Holland 2435 AJ",
    "addr:housenumber":"15",
    "addr:postcode":"2435 aj",
    "addr:street":"Dorpsstraat",
    "iso:country":"NL",
    "sg:address":"Dorpsstraat 15",
    "sg:city":"Zevenhoven",
    "sg:orig_category":"Kappers",
    "sg:phone":"+31 172 537 442",
    "sg:postcode":"2435 AJ",
    "sg:province":"South Holland",
    "wof:name":"Belle Et Beau",
    "wof:placetype":"venue"
},
  "geometry": {"coordinates":[4.7823290825,52.1809425354],"type":"Point"}
}