{
  "type": "Feature",
  "properties": {
    "addr:full":"Havikweg 6 Landgraaf Limburg 6374 AZ",
    "addr:housenumber":"6",
    "addr:postcode":"6374 az",
    "addr:street":"Havikweg",
    "iso:country":"NL",
    "sg:address":"Havikweg 6",
    "sg:city":"Landgraaf",
    "sg:orig_category":"Huishoudapparatuur, Televisies And Radio'S",
    "sg:phone":"+31 45 569 5959",
    "sg:postcode":"6374 AZ",
    "sg:province":"Limburg",
    "wof:name":"Karwei Bouwmarkt",
    "wof:placetype":"venue"
},
  "geometry": {"coordinates":[6.029273,50.916481],"type":"Point"}
}