{
  "type": "Feature",
  "properties": {
    "addr:full":"Flaas 19 Kaatsheuvel Noord-Brabant 5172 BJ",
    "addr:housenumber":"19",
    "addr:postcode":"5172 bj",
    "addr:street":"Flaas",
    "iso:country":"NL",
    "sg:address":"Flaas 19",
    "sg:city":"Kaatsheuvel",
    "sg:orig_category":"Orthopedische Artikelen - Fabrieken En Groothandel",
    "sg:phone":"+31 416 282 274",
    "sg:postcode":"5172 BJ",
    "sg:province":"Noord-Brabant",
    "sg:website":"http://www.steunstok.nl",
    "wof:name":"Koolen",
    "wof:placetype":"venue"
},
  "geometry": {"coordinates":[5.0228190422,51.6529846191],"type":"Point"}
}