{
  "type": "Feature",
  "properties": {
    "addr:full":"Schutterspln 14 Milsbeek Limburg 6596 AM",
    "addr:housenumber":"14",
    "addr:postcode":"6596",
    "addr:street":"Schutterspln",
    "iso:country":"NL",
    "sg:address":"Schutterspln 14",
    "sg:city":"Milsbeek",
    "sg:orig_category":"Banken",
    "sg:phone":"+31 485 516 485",
    "sg:postcode":"6596 AM",
    "sg:province":"Limburg",
    "wof:name":"Regio Bank",
    "wof:placetype":"venue"
},
  "geometry": {"coordinates":[5.949899,51.724609],"type":"Point"}
}