{
  "type": "Feature",
  "properties": {
    "iso:country":"NL",
    "sg:address":"Mallemoolen 32",
    "sg:city":"Zevenaar",
    "sg:orig_category":"Kappers",
    "sg:phone":"+31 316 333 233",
    "sg:postcode":"6901 GR",
    "sg:province":"Gelderland",
    "wof:name":"Scheerder Intercoiffure",
    "wof:placetype":"venue"
},
  "geometry": {"coordinates":[6.075579,51.929482],"type":"Point"}
}