{
  "type": "Feature",
  "properties": {
    "iso:country":"NL",
    "sg:address":"Essenburgsingel 120",
    "sg:city":"Rotterdam",
    "sg:orig_category":"Diverse Consumentenartikelen Gh",
    "sg:phone":"+31 10 477 5992",
    "sg:postcode":"3022 EJ",
    "sg:province":"Zuid-Holland",
    "wof:name":"Midva Trade",
    "wof:placetype":"venue"
},
  "geometry": {"coordinates":[4.446064,51.921032],"type":"Point"}
}