{
  "type": "Feature",
  "properties": {
    "addr:full":"V Leeuwenstr 27A Ymuiden North Holland 1972 PG",
    "addr:housenumber":"27a",
    "addr:postcode":"1972 pg",
    "addr:street":"Ymuiden North",
    "iso:country":"NL",
    "sg:address":"V Leeuwenstr 27A",
    "sg:city":"Ymuiden",
    "sg:orig_category":"Postzegels",
    "sg:phone":"+31 255 532 795",
    "sg:postcode":"1972 PG",
    "sg:province":"North Holland",
    "wof:name":"Ijmuiden",
    "wof:placetype":"venue"
},
  "geometry": {"coordinates":[4.61762,52.458302],"type":"Point"}
}