{
  "type": "Feature",
  "properties": {
    "iso:country":"NL",
    "sg:address":"Zeverynstr 24",
    "sg:city":"Hilversum",
    "sg:orig_category":"Drukkerijen",
    "sg:phone":"+31 35 624 9653",
    "sg:postcode":"1216 GK",
    "sg:province":"Noord-Holland",
    "sg:website":"http://www.delamontagne.nl",
    "wof:name":"Montagne Offsetdrukkerij, De La",
    "wof:placetype":"venue"
},
  "geometry": {"coordinates":[5.1695,52.228565],"type":"Point"}
}