{
  "type": "Feature",
  "properties": {
    "addr:full":"Vondelstraat 61 Amsterdam Noord-Holland 1054 GK",
    "addr:housenumber":"61",
    "addr:postcode":"1054 gk",
    "addr:street":"Vondelstraat",
    "iso:country":"NL",
    "sg:address":"Vondelstraat 61",
    "sg:city":"Amsterdam",
    "sg:orig_category":"Fotostudio'S And Fotografen",
    "sg:phone":"+31 20 616 1414",
    "sg:postcode":"1054 GK",
    "sg:province":"Noord-Holland",
    "wof:name":"Stichting Dar Almaghrebe",
    "wof:placetype":"venue"
},
  "geometry": {"coordinates":[4.874823,52.361446],"type":"Point"}
}