{
  "type": "Feature",
  "properties": {
    "iso:country":"NL",
    "sg:address":"Broeker Werf 14",
    "sg:city":"Broek Op Langedyk",
    "sg:orig_category":"Kantoor- En Bedrijfsmeubelen",
    "sg:phone":"+31 226 316 011",
    "sg:postcode":"1721 PC",
    "sg:province":"North Holland",
    "sg:website":"http://www.ottoskantoorcentrum.nl",
    "wof:name":"Otto",
    "wof:placetype":"venue"
},
  "geometry": {"coordinates":[4.8007712364,52.6761894226],"type":"Point"}
}