{
  "type": "Feature",
  "properties": {
    "addr:full":"Stationsstr 37 Schinnen Limburg 6365 CK",
    "addr:housenumber":"37",
    "addr:postcode":"6365 ck",
    "addr:street":"Stationsstr",
    "iso:country":"NL",
    "sg:address":"Stationsstr 37",
    "sg:city":"Schinnen",
    "sg:orig_category":"Bloemen En Planten",
    "sg:phone":"+31 46 443 1261",
    "sg:postcode":"6365 CK",
    "sg:province":"Limburg",
    "wof:name":"Houben Bloemen",
    "wof:placetype":"venue"
},
  "geometry": {"coordinates":[5.881352,50.938751],"type":"Point"}
}