{
  "type": "Feature",
  "properties": {
    "addr:full":"Engelsedijk 5 'S Hertogenbosch Noord-Brabant 5231 EH",
    "addr:housenumber":"5 ' s",
    "addr:postcode":"5231 eh",
    "addr:street":"Engelsedijk",
    "iso:country":"NL",
    "sg:address":"Engelsedijk 5",
    "sg:city":"'S Hertogenbosch",
    "sg:orig_category":"Verhuur Catering-, Feest- En Evenementbenodigdheden",
    "sg:phone":"+31 73 631 2600",
    "sg:postcode":"5231 EH",
    "sg:province":"Noord-Brabant",
    "wof:name":"Moonlight Speelautomaten Bv",
    "wof:placetype":"venue"
},
  "geometry": {"coordinates":[5.28026,51.71487],"type":"Point"}
}