{
  "type": "Feature",
  "properties": {
    "addr:full":"Groenewg 28A Bergen Nh North Holland 1861 PH",
    "addr:housenumber":"28a",
    "addr:postcode":"1861",
    "addr:street":"Groenewg",
    "iso:country":"NL",
    "sg:address":"Groenewg 28A",
    "sg:city":"Bergen Nh",
    "sg:classifiers":[
        {
            "category":"Sports & Exercise",
            "subcategory":"Stables",
            "type":"Entertainment"
        }
    ],
    "sg:phone":"+31 72 581 4303",
    "sg:postcode":"1861 PH",
    "sg:province":"North Holland",
    "sg:tags":[
        "maneges"
    ],
    "wof:name":"Louwris Stal",
    "wof:placetype":"venue"
},
  "geometry": {"coordinates":[4.702408,52.651684],"type":"Point"}
}