{
  "type": "Feature",
  "properties": {
    "iso:country":"NL",
    "sg:address":"Zandstr 110",
    "sg:city":"Culemborg",
    "sg:orig_category":"Begrafenisverzorging",
    "sg:phone":"+31 345 517 127",
    "sg:postcode":"4101 EJ",
    "sg:province":"Gelderland",
    "wof:name":"Culemborgse Uitvaartverzorging",
    "wof:placetype":"venue"
},
  "geometry": {"coordinates":[5.229044,51.953037],"type":"Point"}
}