{
  "type": "Feature",
  "properties": {
    "iso:country":"NL",
    "sg:address":"Terheydensewg 51/A",
    "sg:city":"Breda",
    "sg:orig_category":"Architecten En Architectenbureaus",
    "sg:phone":"+31 76 587 0912",
    "sg:postcode":"4815 BD",
    "sg:province":"Noord-Brabant",
    "sg:website":"http://www.riemsdijkarchitects.nl",
    "wof:name":"Riemsdijk Bv, P J Van",
    "wof:placetype":"venue"
},
  "geometry": {"coordinates":[4.779806,51.598228],"type":"Point"}
}