{
  "type": "Feature",
  "properties": {
    "addr:full":"Tervoortsewg 1 Bavel Noord-Brabant 4854 NE",
    "addr:housenumber":"1",
    "addr:postcode":"4854 ne",
    "addr:street":"Tervoortsewg",
    "iso:country":"NL",
    "sg:address":"Tervoortsewg 1",
    "sg:city":"Bavel",
    "sg:classifiers":[
        {
            "category":"Retail",
            "subcategory":"Auto Repair",
            "type":"Services"
        }
    ],
    "sg:phone":"+31 6 14437260",
    "sg:postcode":"4854 NE",
    "sg:province":"Noord-Brabant",
    "sg:tags":[
        "garage"
    ],
    "wof:name":"Stalling, De",
    "wof:placetype":"venue"
},
  "geometry": {"coordinates":[4.84002,51.574135],"type":"Point"}
}