{
  "type": "Feature",
  "properties": {
    "addr:full":"Krabbendijk 40 Denekamp Overijssel 7591 AX",
    "addr:housenumber":"40",
    "addr:postcode":"7591 ax",
    "addr:street":"Krabbendijk",
    "iso:country":"NL",
    "sg:address":"Krabbendijk 40",
    "sg:city":"Denekamp",
    "sg:orig_category":"Chemische Producten Gh",
    "sg:phone":"+31 541 355 117",
    "sg:postcode":"7591 AX",
    "sg:province":"Overijssel",
    "wof:name":"Handelsonderneming D.J. Schmidt",
    "wof:placetype":"venue"
},
  "geometry": {"coordinates":[7.012147,52.379753],"type":"Point"}
}