{
  "type": "Feature",
  "properties": {
    "addr:full":"Ecliptica 95 Loon Op Zand Noord-Brabant 5175 XH",
    "addr:housenumber":"95",
    "addr:postcode":"5175 xh",
    "addr:street":"Ecliptica",
    "iso:country":"NL",
    "sg:address":"Ecliptica 95",
    "sg:city":"Loon Op Zand",
    "sg:orig_category":"Fotoreportages",
    "sg:phone":"+31 416 361 647",
    "sg:postcode":"5175 XH",
    "sg:province":"Noord-Brabant",
    "wof:name":"La Haye, Bernadette",
    "wof:placetype":"venue"
},
  "geometry": {"coordinates":[5.083635,51.624783],"type":"Point"}
}