{
  "type": "Feature",
  "properties": {
    "addr:full":"Postbus 3096 Ryswyk Zh 2280 GB",
    "addr:housenumber":"3096",
    "addr:postcode":"2280 gb",
    "addr:street":"Postbus;Zh",
    "iso:country":"NL",
    "sg:address":"Postbus 3096",
    "sg:city":"Ryswyk Zh",
    "sg:orig_category":"Adviesbureaus Bouwkunde",
    "sg:phone":"+31 174 226 055",
    "sg:postcode":"2280 GB",
    "sg:website":"http://www.c-m-c.nl",
    "wof:name":"Cmc",
    "wof:placetype":"venue"
},
  "geometry": {"coordinates":[4.32436,52.037251],"type":"Point"}
}