{
  "type": "Feature",
  "properties": {
    "iso:country":"NL",
    "sg:address":"Laan 40 45 31",
    "sg:city":"Vriezenveen",
    "sg:orig_category":"Bloemisterijartikelen - Fabrieken En Groothandel",
    "sg:phone":"+31 546 566 045",
    "sg:postcode":"7671 MT",
    "sg:province":"NL.08",
    "wof:name":"Forest",
    "wof:placetype":"venue"
},
  "geometry": {"coordinates":[6.609222,52.410698],"type":"Point"}
}