{
  "type": "Feature",
  "properties": {
    "addr:full":"Spangesekade 97 Rotterdam Zuid-Holland 3027 GR",
    "addr:housenumber":"97",
    "addr:postcode":"3027",
    "addr:street":"Spangesekade",
    "iso:country":"NL",
    "sg:address":"Spangesekade 97",
    "sg:city":"Rotterdam",
    "sg:orig_category":"Verhuisdiensten",
    "sg:phone":"+31 10 462 2509",
    "sg:postcode":"3027 GR",
    "sg:province":"Zuid-Holland",
    "wof:name":"Vervoersbedrijf Ribos",
    "wof:placetype":"venue"
},
  "geometry": {"coordinates":[4.441513,51.917908],"type":"Point"}
}