{
  "type": "Feature",
  "properties": {
    "iso:country":"NL",
    "sg:address":"Bossewg 7",
    "sg:city":"Best",
    "sg:orig_category":"Kappers",
    "sg:phone":"+31 499 374 271",
    "sg:postcode":"5682 BA",
    "sg:province":"Noord-Brabant",
    "wof:name":"Scissors Hairdesign",
    "wof:placetype":"venue"
},
  "geometry": {"coordinates":[-101.46463799999999,31.196535],"type":"Point"}
}