{
  "type": "Feature",
  "properties": {
    "iso:country":"NL",
    "sg:address":"Herenstraat 22A",
    "sg:city":"Hilversum",
    "sg:orig_category":"Juridische Dienstverlening",
    "sg:phone":"+31 35 621 0509",
    "sg:postcode":"1211 CC",
    "sg:province":"Noord-Holland",
    "wof:name":"Rechtswinkel Hilversum",
    "wof:placetype":"venue"
},
  "geometry": {"coordinates":[5.175104,52.223984],"type":"Point"}
}