{
  "type": "Feature",
  "properties": {
    "iso:country":"NL",
    "sg:address":"Schansweg 12",
    "sg:city":"Den Burg",
    "sg:orig_category":"Vakantiehuizen",
    "sg:phone":"+31 222 312 412",
    "sg:postcode":"1791 LK",
    "sg:province":"Noord-Holland",
    "wof:name":"T J Stiggelbout",
    "wof:placetype":"venue"
},
  "geometry": {"coordinates":[4.818287,53.040886],"type":"Point"}
}