{
  "type": "Feature",
  "properties": {
    "addr:full":"Ryksstrwg 88-90 Haarlem Noord-Holland 2022 DD",
    "addr:housenumber":"88-90",
    "addr:postcode":"2022 dd",
    "iso:country":"NL",
    "sg:address":"Ryksstrwg 88-90",
    "sg:city":"Haarlem",
    "sg:orig_category":"Horeca-Inrichtingen En -Uitrustingen",
    "sg:phone":"+31 23 538 0989",
    "sg:postcode":"2022 DD",
    "sg:province":"Noord-Holland",
    "wof:name":"Comfort, Zonwering",
    "wof:placetype":"venue"
},
  "geometry": {"coordinates":[4.65061,52.402458],"type":"Point"}
}