{
  "type": "Feature",
  "properties": {
    "addr:full":"Jan Kriegestraat 7 Woerden Utrecht 3443 TJ",
    "addr:housenumber":"7",
    "addr:postcode":"3443 tj",
    "addr:street":"Jan Kriegestraat",
    "iso:country":"NL",
    "sg:address":"Jan Kriegestraat 7",
    "sg:city":"Woerden",
    "sg:orig_category":"Loodgieterswerk, Verwarming And Sanitaire Installaties",
    "sg:phone":"+31 348 413 444",
    "sg:postcode":"3443 TJ",
    "sg:province":"Utrecht",
    "wof:name":"Sanitair Installatie Hoogendoorn Bv",
    "wof:placetype":"venue"
},
  "geometry": {"coordinates":[4.873054,52.087807],"type":"Point"}
}