{
  "type": "Feature",
  "properties": {
    "addr:full":"V Noortwyckstr 327 Rotterdam Zuid-Holland 3042 LM",
    "addr:housenumber":"327",
    "addr:postcode":"3042 lm",
    "iso:country":"NL",
    "sg:address":"V Noortwyckstr 327",
    "sg:city":"Rotterdam",
    "sg:orig_category":"Autorijscholen",
    "sg:phone":"+31 6 53602888",
    "sg:postcode":"3042 LM",
    "sg:province":"Zuid-Holland",
    "wof:name":"Man",
    "wof:placetype":"venue"
},
  "geometry": {"coordinates":[4.43381,51.9328],"type":"Point"}
}