{
  "type": "Feature",
  "properties": {
    "addr:full":"Orchideeenstr 16 Eindhoven North Brabant 5644 NK",
    "addr:housenumber":"16",
    "addr:postcode":"5644 nk",
    "addr:street":"Orchideeenstr",
    "iso:country":"NL",
    "sg:address":"Orchideeenstr 16",
    "sg:city":"Eindhoven",
    "sg:orig_category":"Cafetaria'S",
    "sg:phone":"+31 40 212 3646",
    "sg:postcode":"5644 NK",
    "sg:province":"North Brabant",
    "wof:name":"Orchidee",
    "wof:placetype":"venue"
},
  "geometry": {"coordinates":[5.487735,51.421516],"type":"Point"}
}