{
  "type": "Feature",
  "properties": {
    "addr:full":"V Karnebeekln 15 Eesveen NL.08 8347 WD",
    "addr:housenumber":"15;nl.08",
    "addr:postcode":"8347",
    "iso:country":"NL",
    "sg:address":"V Karnebeekln 15",
    "sg:city":"Eesveen",
    "sg:orig_category":"Discotheken",
    "sg:phone":"+31 521 577 558",
    "sg:postcode":"8347 WD",
    "sg:province":"NL.08",
    "sg:website":"http://www.smithys",
    "wof:name":"Smithy'S Palace, Discotheek",
    "wof:placetype":"venue"
},
  "geometry": {"coordinates":[6.142643,52.824024],"type":"Point"}
}