{
  "type": "Feature",
  "properties": {
    "addr:full":"Oosteinde 18 Oostwoud Noord-Holland 1678 HS",
    "addr:housenumber":"18",
    "addr:postcode":"1678 hs",
    "addr:street":"Oosteinde",
    "iso:country":"NL",
    "sg:address":"Oosteinde 18",
    "sg:city":"Oostwoud",
    "sg:orig_category":"Administratie- En Boekhoudkantoren",
    "sg:phone":"+31 229 201 795",
    "sg:postcode":"1678 HS",
    "sg:province":"Noord-Holland",
    "wof:name":"Grg",
    "wof:placetype":"venue"
},
  "geometry": {"coordinates":[5.094204,52.726482],"type":"Point"}
}