{
  "type": "Feature",
  "properties": {
    "iso:country":"NL",
    "sg:address":"Veerweg 20",
    "sg:city":"Eck En Wiel",
    "sg:orig_category":"Verhuur Bouwmachines",
    "sg:phone":"+31 344 692 327",
    "sg:postcode":"4024 BP",
    "sg:province":"Texas",
    "wof:name":"J. Van Der Linden",
    "wof:placetype":"venue"
},
  "geometry": {"coordinates":[-96.059273,33.017281],"type":"Point"}
}