{
  "type": "Feature",
  "properties": {
    "addr:full":"Holterwg 119 Lettele Pennsylvania 7434 PA",
    "addr:housenumber":"119",
    "addr:postcode":"7434 pa",
    "iso:country":"NL",
    "sg:address":"Holterwg 119",
    "sg:city":"Lettele",
    "sg:orig_category":"Benzine En Olie - Groothandel",
    "sg:phone":"+31 570 541 246",
    "sg:postcode":"7434 PA",
    "sg:province":"Pennsylvania",
    "sg:website":"http://www.teriele-olie.nl",
    "wof:name":"Riele, Oliehandel Te",
    "wof:placetype":"venue"
},
  "geometry": {"coordinates":[-77.604507,40.99464],"type":"Point"}
}