{
  "type": "Feature",
  "properties": {
    "addr:full":"Buitendk 4 Zuid Beyerland Zuid-Holland 3284 KC",
    "addr:housenumber":"4;beyerland",
    "addr:postcode":"3284 kc",
    "addr:street":"Buitendk",
    "iso:country":"NL",
    "sg:address":"Buitendk 4",
    "sg:city":"Zuid Beyerland",
    "sg:orig_category":"Kappers",
    "sg:phone":"+31 186 662 736",
    "sg:postcode":"3284 KC",
    "sg:province":"Zuid-Holland",
    "wof:name":"Wolff, Angela De",
    "wof:placetype":"venue"
},
  "geometry": {"coordinates":[4.355941,51.743351],"type":"Point"}
}