{
  "type": "Feature",
  "properties": {
    "addr:full":"De Vlijt 2B Bedum Groningen 9780 AA",
    "addr:housenumber":"2b",
    "addr:postcode":"9780 aa",
    "addr:street":"De Vlijt",
    "iso:country":"NL",
    "sg:address":"De Vlijt 2B",
    "sg:city":"Bedum",
    "sg:classifiers":[
        {
            "category":"Professional",
            "subcategory":"Accounting & Tax Preparation",
            "type":"Services"
        }
    ],
    "sg:phone":"+31 50 304 8090",
    "sg:postcode":"9780 AA",
    "sg:province":"Groningen",
    "sg:tags":[
        "accountant"
    ],
    "wof:name":"Accountantskantoor Groeneveld",
    "wof:placetype":"venue"
},
  "geometry": {"coordinates":[6.601702,53.300083],"type":"Point"}
}