{
  "type": "Feature",
  "properties": {
    "addr:full":"De Kempenaerstr 18 Oegstgeest South Holland 2341 GM",
    "addr:housenumber":"18",
    "addr:postcode":"2341 gm",
    "iso:country":"NL",
    "sg:address":"De Kempenaerstr 18",
    "sg:city":"Oegstgeest",
    "sg:orig_category":"Opticiens",
    "sg:phone":"+31 71 517 1535",
    "sg:postcode":"2341 GM",
    "sg:province":"South Holland",
    "wof:name":"Mastrigt",
    "wof:placetype":"venue"
},
  "geometry": {"coordinates":[4.4690141678,52.1773910522],"type":"Point"}
}