{
  "type": "Feature",
  "properties": {
    "iso:country":"NL",
    "sg:address":"Postbus 1900",
    "sg:city":"Venlo",
    "sg:orig_category":"Hulpverlening Sociaal",
    "sg:phone":"+31 77 359 6528",
    "sg:postcode":"5900 BX",
    "sg:province":"Limburg",
    "wof:name":"Haltsteunpunt Venlo, Bur",
    "wof:placetype":"venue"
},
  "geometry": {"coordinates":[6.17286,51.372421],"type":"Point"}
}