{
  "type": "Feature",
  "properties": {
    "iso:country":"NL",
    "sg:address":"Semarangstr 19",
    "sg:city":"Utrecht",
    "sg:orig_category":"Fotojournalisten Freelance",
    "sg:phone":"+31 30 294 5250",
    "sg:postcode":"3531 RH",
    "sg:province":"Utrecht",
    "wof:name":"Balvert, R Den",
    "wof:placetype":"venue"
},
  "geometry": {"coordinates":[5.099614,52.091782],"type":"Point"}
}