{
  "type": "Feature",
  "properties": {
    "addr:full":"Repel 37 Veldhoven Noord-Brabant 5501 HR",
    "addr:housenumber":"37",
    "addr:postcode":"5501 hr",
    "addr:street":"Repel",
    "iso:country":"NL",
    "sg:address":"Repel 37",
    "sg:city":"Veldhoven",
    "sg:orig_category":"Adviesbureaus Bedrijfsorganisatie",
    "sg:phone":"+31 40 230 1091",
    "sg:postcode":"5501 HR",
    "sg:province":"Noord-Brabant",
    "wof:name":"Cominds",
    "wof:placetype":"venue"
},
  "geometry": {"coordinates":[5.403143,51.421158],"type":"Point"}
}