{
  "type": "Feature",
  "properties": {
    "iso:country":"NL",
    "sg:address":"Den Heuvel 25",
    "sg:city":"Oirschot",
    "sg:orig_category":"Ongediertebestrijding En Ontsmetting",
    "sg:phone":"+31 499 551 080",
    "sg:postcode":"5688 EM",
    "sg:province":"Noord-Brabant",
    "wof:name":"Ohkee",
    "wof:placetype":"venue"
},
  "geometry": {"coordinates":[5.298824,51.500729],"type":"Point"}
}