{
  "type": "Feature",
  "properties": {
    "addr:full":"Usselincxstr 131 S Gravenhage Zuid-Holland 2593 VK",
    "addr:housenumber":"131;gravenhage",
    "addr:postcode":"2593 vk",
    "addr:street":"S",
    "iso:country":"NL",
    "sg:address":"Usselincxstr 131",
    "sg:city":"S Gravenhage",
    "sg:orig_category":"Onderhoudswerken",
    "sg:phone":"+31 70 383 3137",
    "sg:postcode":"2593 VK",
    "sg:province":"Zuid-Holland",
    "wof:name":"Hove, Paul Van Den",
    "wof:placetype":"venue"
},
  "geometry": {"coordinates":[4.34266,52.086121],"type":"Point"}
}