{
  "type": "Feature",
  "properties": {
    "addr:full":"Koolhofstraat 5 Brunssum Limburg 6443 CL",
    "addr:housenumber":"5",
    "addr:postcode":"6443",
    "addr:street":"Koolhofstraat",
    "iso:country":"NL",
    "sg:address":"Koolhofstraat 5",
    "sg:city":"Brunssum",
    "sg:orig_category":"Schilderwerk",
    "sg:phone":"+31 45 525 5373",
    "sg:postcode":"6443 CL",
    "sg:province":"Limburg",
    "wof:name":"E. De Vreede",
    "wof:placetype":"venue"
},
  "geometry": {"coordinates":[5.967832,50.93882],"type":"Point"}
}