{
  "type": "Feature",
  "properties": {
    "addr:full":"Industriestraat 14 Klazienaveen Provincie Drenthe 7891 GV",
    "addr:housenumber":"14",
    "addr:postcode":"7891 gv",
    "addr:street":"Industriestraat;Provincie Drenthe",
    "iso:country":"NL",
    "sg:address":"Industriestraat 14",
    "sg:city":"Klazienaveen",
    "sg:orig_category":"Metaalbekleding And -Behandeling",
    "sg:phone":"+31 591 312 700",
    "sg:postcode":"7891 GV",
    "sg:province":"Provincie Drenthe",
    "wof:name":"Straal- En Conserveringsbedr Klazienavee",
    "wof:placetype":"venue"
},
  "geometry": {"coordinates":[7.010664,52.722103],"type":"Point"}
}