{
  "type": "Feature",
  "properties": {
    "addr:full":"Hoogstr 36A Rotterdam South Holland 3011 PR",
    "addr:housenumber":"36a",
    "addr:postcode":"3011 pr",
    "addr:street":"Hoogstr",
    "iso:country":"NL",
    "sg:address":"Hoogstr 36A",
    "sg:city":"Rotterdam",
    "sg:orig_category":"Webdesign Bureaus",
    "sg:phone":"+31 10 243 9122",
    "sg:postcode":"3011 PR",
    "sg:province":"South Holland",
    "sg:website":"http://www.beeldspraak.com",
    "wof:name":"Beeldspraak",
    "wof:placetype":"venue"
},
  "geometry": {"coordinates":[4.4947400093,51.9230651855],"type":"Point"}
}