{
  "type": "Feature",
  "properties": {
    "addr:full":"Nw Ryn 57 Leiden South Holland 2312 JH",
    "addr:housenumber":"57",
    "addr:postcode":"2312 jh",
    "addr:street":"Nw Ryn",
    "iso:country":"NL",
    "sg:address":"Nw Ryn 57",
    "sg:city":"Leiden",
    "sg:orig_category":"Kunstenaars- Benodigdheden",
    "sg:phone":"+31 71 513 1369",
    "sg:postcode":"2312 JH",
    "sg:province":"South Holland",
    "wof:name":"Terpen Tijn, Kunstschildersmat",
    "wof:placetype":"venue"
},
  "geometry": {"coordinates":[4.49463,52.154572],"type":"Point"}
}