{
  "type": "Feature",
  "properties": {
    "addr:full":"Bloemistendam 5 Warmond Zuid-Holland 2361 GG",
    "addr:housenumber":"5",
    "addr:postcode":"2361 gg",
    "addr:street":"Bloemistendam",
    "iso:country":"NL",
    "sg:address":"Bloemistendam 5",
    "sg:city":"Warmond",
    "sg:orig_category":"Bloembollen - Groothandel",
    "sg:phone":"+31 71 301 1403",
    "sg:postcode":"2361 GG",
    "sg:province":"Zuid-Holland",
    "wof:name":"Winsen En Zn, J Van",
    "wof:placetype":"venue"
},
  "geometry": {"coordinates":[4.505705,52.198589],"type":"Point"}
}