{
  "type": "Feature",
  "properties": {
    "addr:full":"Westvest 56 Schiedam Zuid-Holland 3111 BW",
    "addr:housenumber":"56",
    "addr:postcode":"3111 bw",
    "addr:street":"Westvest",
    "iso:country":"NL",
    "sg:address":"Westvest 56",
    "sg:city":"Schiedam",
    "sg:orig_category":"Verenigingen En Stichtingen",
    "sg:phone":"+31 10 473 8300",
    "sg:postcode":"3111 BW",
    "sg:province":"Zuid-Holland",
    "wof:name":"Buurtwerk Pameijer Keerkring, Sticht",
    "wof:placetype":"venue"
},
  "geometry": {"coordinates":[4.39672,51.914474],"type":"Point"}
}