{
  "type": "Feature",
  "properties": {
    "addr:full":"De Akker 8 Waddinxveen Zuid-Holland 2743 DM",
    "addr:housenumber":"8",
    "addr:postcode":"2743 dm",
    "addr:street":"De Akker",
    "iso:country":"NL",
    "sg:address":"De Akker 8",
    "sg:city":"Waddinxveen",
    "sg:classifiers":[
        {
            "category":"Personal",
            "subcategory":"Nail Salon",
            "type":"Services"
        }
    ],
    "sg:phone":"+31 182 610 219",
    "sg:postcode":"2743 DM",
    "sg:province":"Zuid-Holland",
    "sg:tags":[
        "pedicure"
    ],
    "wof:name":"Lovisa, Henny",
    "wof:placetype":"venue"
},
  "geometry": {"coordinates":[4.642409,52.036549],"type":"Point"}
}