{
  "type": "Feature",
  "properties": {
    "addr:full":"Radarstr 13-15 S Gravenhage Zuid-Holland 2525 KC",
    "addr:housenumber":"13-15;gravenhage",
    "addr:postcode":"2525 kc",
    "addr:street":"S",
    "iso:country":"NL",
    "sg:address":"Radarstr 13-15",
    "sg:city":"S Gravenhage",
    "sg:orig_category":"Machinefabrieken",
    "sg:phone":"+31 70 388 9345",
    "sg:postcode":"2525 KC",
    "sg:province":"Zuid-Holland",
    "sg:website":"http://www.vanzetten.com",
    "wof:name":"Zetten, Van",
    "wof:placetype":"venue"
},
  "geometry": {"coordinates":[4.30248,52.062462],"type":"Point"}
}