{
  "type": "Feature",
  "properties": {
    "addr:full":"Bremberg 5 Bergeyk Noord-Brabant 5571 GP",
    "addr:housenumber":"5",
    "addr:postcode":"5571 gp",
    "addr:street":"Bremberg",
    "iso:country":"NL",
    "sg:address":"Bremberg 5",
    "sg:city":"Bergeyk",
    "sg:orig_category":"Zand En Grind - Vervoer",
    "sg:phone":"+31 497 574 696",
    "sg:postcode":"5571 GP",
    "sg:province":"Noord-Brabant",
    "wof:name":"Daas, M",
    "wof:placetype":"venue"
},
  "geometry": {"coordinates":[5.358063,51.317699],"type":"Point"}
}