{
  "type": "Feature",
  "properties": {
    "addr:full":"Hertenrade 152 S Gravenhage South Holland 2544 HL",
    "addr:housenumber":"152",
    "addr:postcode":"2544 hl",
    "addr:street":"Hertenrade;S Gravenhage",
    "iso:country":"NL",
    "sg:address":"Hertenrade 152",
    "sg:city":"S Gravenhage",
    "sg:orig_category":"Onderhoudswerken",
    "sg:phone":"+31 6 10969421",
    "sg:postcode":"2544 HL",
    "sg:province":"South Holland",
    "wof:name":"Nooitgedacht",
    "wof:placetype":"venue"
},
  "geometry": {"coordinates":[4.25157,52.039551],"type":"Point"}
}