{
  "type": "Feature",
  "properties": {
    "addr:full":"Tunboustr 14 Berlikum Fr Friesland 9041 EB",
    "addr:housenumber":"14",
    "addr:postcode":"9041 eb",
    "addr:street":"Tunboustr",
    "iso:country":"NL",
    "sg:address":"Tunboustr 14",
    "sg:city":"Berlikum Fr",
    "sg:orig_category":"Fotografie Reclame En Mode",
    "sg:phone":"+31 518 462 566",
    "sg:postcode":"9041 EB",
    "sg:province":"Friesland",
    "wof:name":"Tiede T",
    "wof:placetype":"venue"
},
  "geometry": {"coordinates":[5.653159,53.244648],"type":"Point"}
}