{
  "type": "Feature",
  "properties": {
    "iso:country":"NL",
    "sg:address":"Albert Cuijpstraat 74",
    "sg:city":"Bergen Op Zoom",
    "sg:orig_category":"Boekhouders",
    "sg:phone":"+31 164 235 023",
    "sg:postcode":"4625 AM",
    "sg:province":"Noord-Brabant",
    "wof:name":"Administratiefservicebur De Derde Hand",
    "wof:placetype":"venue"
},
  "geometry": {"coordinates":[4.303751,51.474201],"type":"Point"}
}