{
  "type": "Feature",
  "properties": {
    "addr:full":"Torenbaan 49 Heerle Noord-Brabant 4726 AW",
    "addr:housenumber":"49",
    "addr:postcode":"4726 aw",
    "addr:street":"Torenbaan",
    "iso:country":"NL",
    "sg:address":"Torenbaan 49",
    "sg:city":"Heerle",
    "sg:orig_category":"Voetbalverenigingen",
    "sg:phone":"+31 165 304 577",
    "sg:postcode":"4726 AW",
    "sg:province":"Noord-Brabant",
    "wof:name":"Hsc'28",
    "wof:placetype":"venue"
},
  "geometry": {"coordinates":[4.356191,51.519077],"type":"Point"}
}