{
  "type": "Feature",
  "properties": {
    "iso:country":"NL",
    "sg:address":"Baanvak 40",
    "sg:city":"Aalsmeer",
    "sg:orig_category":"Kappers",
    "sg:phone":"+31 297 342 012",
    "sg:postcode":"1431 LK",
    "sg:province":"North Holland",
    "wof:name":"C E Van Der Schilden-Bol",
    "wof:placetype":"venue"
},
  "geometry": {"coordinates":[4.7556171417,52.266254425],"type":"Point"}
}