{
  "type": "Feature",
  "properties": {
    "addr:full":"Wagenmakerstraat 19 Ridderkerk South Holland 2984 BD",
    "addr:housenumber":"19",
    "addr:postcode":"2984 bd",
    "addr:street":"Wagenmakerstraat",
    "iso:country":"NL",
    "sg:address":"Wagenmakerstraat 19",
    "sg:city":"Ridderkerk",
    "sg:orig_category":"Autokeuringen",
    "sg:phone":"+31 180 462 888",
    "sg:postcode":"2984 BD",
    "sg:province":"South Holland",
    "wof:name":"Koks Milieu- En Voertuigtechniek Bv",
    "wof:placetype":"venue"
},
  "geometry": {"coordinates":[4.620664,51.874214],"type":"Point"}
}