{
  "type": "Feature",
  "properties": {
    "addr:full":"Kerkakkerstraat 14 Rijsbergen Noord-Brabant 4891 AG",
    "addr:housenumber":"14",
    "addr:postcode":"4891",
    "addr:street":"Kerkakkerstraat",
    "iso:country":"NL",
    "sg:address":"Kerkakkerstraat 14",
    "sg:city":"Rijsbergen",
    "sg:orig_category":"Huishoudapparatuur, Televisies And Radio'S",
    "sg:phone":"+31 76 596 2066",
    "sg:postcode":"4891 AG",
    "sg:province":"Noord-Brabant",
    "wof:name":"Bertro Wit Bruingoed Reparaties",
    "wof:placetype":"venue"
},
  "geometry": {"coordinates":[4.699129,51.515896],"type":"Point"}
}