{
  "type": "Feature",
  "properties": {
    "addr:full":"Hoofddorpwg 11 Amsterdam Noord-Holland 1059 CS",
    "addr:housenumber":"11",
    "addr:postcode":"1059 cs",
    "addr:street":"Hoofddorpwg",
    "iso:country":"NL",
    "sg:address":"Hoofddorpwg 11",
    "sg:city":"Amsterdam",
    "sg:orig_category":"Fietsen En Bromfietsen",
    "sg:phone":"+31 20 615 7535",
    "sg:postcode":"1059 CS",
    "sg:province":"Noord-Holland",
    "wof:name":"Mantel En Zonen, Cor",
    "wof:placetype":"venue"
},
  "geometry": {"coordinates":[4.85145,52.35088],"type":"Point"}
}