{
  "type": "Feature",
  "properties": {
    "addr:full":"Fnidsen 66 Alkmaar Noord-Holland 1811 NH",
    "addr:housenumber":"66",
    "addr:postcode":"1811 nh",
    "addr:street":"Fnidsen",
    "iso:country":"NL",
    "sg:address":"Fnidsen 66",
    "sg:city":"Alkmaar",
    "sg:orig_category":"Bloemen And Planten",
    "sg:phone":"+31 72 512 3733",
    "sg:postcode":"1811 NH",
    "sg:province":"Noord-Holland",
    "wof:name":"Wim Van Assem Bloembinderij",
    "wof:placetype":"venue"
},
  "geometry": {"coordinates":[4.751192,52.630814],"type":"Point"}
}