{
  "type": "Feature",
  "properties": {
    "addr:full":"Nolensstr 180 Amsterdam Noord-Holland 1067 KL",
    "addr:housenumber":"180",
    "addr:postcode":"1067 kl",
    "iso:country":"NL",
    "sg:address":"Nolensstr 180",
    "sg:city":"Amsterdam",
    "sg:orig_category":"Psychologen",
    "sg:phone":"+31 6 10890760",
    "sg:postcode":"1067 KL",
    "sg:province":"Noord-Holland",
    "wof:name":"Koene, Casper",
    "wof:placetype":"venue"
},
  "geometry": {"coordinates":[4.800547,52.37796],"type":"Point"}
}