{
  "type": "Feature",
  "properties": {
    "addr:full":"Else Mauhsstraat 57 Hengelo Ov NL.08 7558 RG",
    "addr:housenumber":"57",
    "addr:postcode":"7558 rg",
    "addr:street":"Else Mauhsstraat;Ov",
    "iso:country":"NL",
    "sg:address":"Else Mauhsstraat 57",
    "sg:city":"Hengelo Ov",
    "sg:orig_category":"Bedrijfsinventaris Gh",
    "sg:phone":"+31 74 277 8117",
    "sg:postcode":"7558 RG",
    "sg:province":"NL.08",
    "wof:name":"E. Spit",
    "wof:placetype":"venue"
},
  "geometry": {"coordinates":[6.845802,52.283375],"type":"Point"}
}