{
  "type": "Feature",
  "properties": {
    "addr:full":"Molenstraat 23 Cuijk Noord-Brabant 5431 BW",
    "addr:housenumber":"23",
    "addr:postcode":"5431 bw",
    "addr:street":"Molenstraat",
    "iso:country":"NL",
    "sg:address":"Molenstraat 23",
    "sg:city":"Cuijk",
    "sg:orig_category":"Bloemen And Planten",
    "sg:phone":"+31 485 314 379",
    "sg:postcode":"5431 BW",
    "sg:province":"Noord-Brabant",
    "wof:name":"Bloemsierkunst Arts",
    "wof:placetype":"venue"
},
  "geometry": {"coordinates":[5.835201,51.726635],"type":"Point"}
}