{
  "type": "Feature",
  "properties": {
    "addr:full":"Nachtegaalstraat 94 Utrecht Utrecht 3581 AP",
    "addr:housenumber":"94",
    "addr:postcode":"3581 ap",
    "addr:street":"Nachtegaalstraat",
    "iso:country":"NL",
    "sg:address":"Nachtegaalstraat 94",
    "sg:city":"Utrecht",
    "sg:orig_category":"Verlichting And Huishoudartikelen",
    "sg:phone":"+31 30 231 1300",
    "sg:postcode":"3581 AP",
    "sg:province":"Utrecht",
    "wof:name":"Potten & Pannen",
    "wof:placetype":"venue"
},
  "geometry": {"coordinates":[5.132678,52.091351],"type":"Point"}
}