{
  "type": "Feature",
  "properties": {
    "iso:country":"NL",
    "sg:address":"Aelbrechtskade 153",
    "sg:city":"Rotterdam",
    "sg:orig_category":"Autokeuringen",
    "sg:phone":"+31 10 476 4794",
    "sg:postcode":"3023 JK",
    "sg:province":"Zuid-Holland",
    "wof:name":"Melissa Car Clean Center",
    "wof:placetype":"venue"
},
  "geometry": {"coordinates":[4.448688,51.911419],"type":"Point"}
}