{
  "type": "Feature",
  "properties": {
    "addr:full":"Boswg 95 Amersfoort Utrecht 3817 ZG",
    "addr:housenumber":"95",
    "addr:postcode":"3817 zg",
    "addr:street":"Boswg",
    "iso:country":"NL",
    "sg:address":"Boswg 95",
    "sg:city":"Amersfoort",
    "sg:orig_category":"Hulpverlening Sociaal",
    "sg:phone":"+31 33 461 6015",
    "sg:postcode":"3817 ZG",
    "sg:province":"Utrecht",
    "wof:name":"Burgerweeshuis Te Amersfoort, Het",
    "wof:placetype":"venue"
},
  "geometry": {"coordinates":[5.386085,52.152325],"type":"Point"}
}