{
  "type": "Feature",
  "properties": {
    "addr:full":"Rumpenerstr 50 Brunssum Limburg 6443 CE",
    "addr:housenumber":"50",
    "addr:postcode":"6443 ce",
    "addr:street":"Rumpenerstr",
    "iso:country":"NL",
    "sg:address":"Rumpenerstr 50",
    "sg:city":"Brunssum",
    "sg:orig_category":"Hengelsportartikelen",
    "sg:phone":"+31 45 527 1412",
    "sg:postcode":"6443 CE",
    "sg:province":"Limburg",
    "wof:name":"Heynens",
    "wof:placetype":"venue"
},
  "geometry": {"coordinates":[5.969061,50.939968],"type":"Point"}
}