{
  "type": "Feature",
  "properties": {
    "addr:full":"Lammerenhof 16 Zevenaar Gelderland 6902 BA",
    "addr:housenumber":"16",
    "addr:postcode":"6902 ba",
    "addr:street":"Lammerenhof",
    "iso:country":"NL",
    "sg:address":"Lammerenhof 16",
    "sg:city":"Zevenaar",
    "sg:orig_category":"Paramedische Behandelingen",
    "sg:phone":"+31 316 333 049",
    "sg:postcode":"6902 BA",
    "sg:province":"Gelderland",
    "wof:name":"Kraamzorg Liemerscare",
    "wof:placetype":"venue"
},
  "geometry": {"coordinates":[6.087855,51.932117],"type":"Point"}
}