{
  "type": "Feature",
  "properties": {
    "addr:full":"Delfzijlstraat 14 Arnhem Gelderland 6835 CP",
    "addr:housenumber":"14",
    "addr:postcode":"6835 cp",
    "addr:street":"Delfzijlstraat",
    "iso:country":"NL",
    "sg:address":"Delfzijlstraat 14",
    "sg:city":"Arnhem",
    "sg:orig_category":"Diverse Grafische Activiteiten",
    "sg:phone":"+31 26 323 4876",
    "sg:postcode":"6835 CP",
    "sg:province":"Gelderland",
    "wof:name":"Laga",
    "wof:placetype":"venue"
},
  "geometry": {"coordinates":[5.898585,51.953568],"type":"Point"}
}