{
  "type": "Feature",
  "properties": {
    "iso:country":"NL",
    "sg:address":"Wielwg 14",
    "sg:city":"Zwartebroek",
    "sg:classifiers":[
        {
            "category":"Wholesale",
            "subcategory":"Motor Vehicles",
            "type":"Manufacturing & Wholesale Goods"
        }
    ],
    "sg:phone":"+31 342 461 338",
    "sg:postcode":"3785 KR",
    "sg:province":"Gelderland",
    "sg:tags":[
        "scooter",
        "en"
    ],
    "sg:website":"http://www.brouwer.nl",
    "wof:name":"Brouwer Bv",
    "wof:placetype":"venue"
},
  "geometry": {"coordinates":[5.508733,52.179153],"type":"Point"}
}