{
  "type": "Feature",
  "properties": {
    "addr:full":"Boerbank 4 Almelo Overijssel 7603 EJ",
    "addr:housenumber":"4",
    "addr:postcode":"7603 ej",
    "addr:street":"Boerbank",
    "iso:country":"NL",
    "sg:address":"Boerbank 4",
    "sg:city":"Almelo",
    "sg:orig_category":"Hoger Onderwijs",
    "sg:phone":"+31 546 490 156",
    "sg:postcode":"7603 EJ",
    "sg:province":"Overijssel",
    "wof:name":"H Blaak",
    "wof:placetype":"venue"
},
  "geometry": {"coordinates":[6.693815,52.373035],"type":"Point"}
}