{
  "type": "Feature",
  "properties": {
    "addr:full":"Fruitln 24 Goes Ohio 4462 EP",
    "addr:housenumber":"24",
    "addr:postcode":"4462 ep",
    "addr:street":"Fruitln",
    "iso:country":"NL",
    "sg:address":"Fruitln 24",
    "sg:city":"Goes",
    "sg:orig_category":"Bakkerijbenodigdheden En -Grondstoffen",
    "sg:phone":"+31 113 236 400",
    "sg:postcode":"4462 EP",
    "sg:province":"Ohio",
    "wof:name":"Carels Goes Bv",
    "wof:placetype":"venue"
},
  "geometry": {"coordinates":[-83.914169,39.768833],"type":"Point"}
}