{
  "type": "Feature",
  "properties": {
    "addr:full":"Irenestr 52 Wageningen Gelderland 6707 CW",
    "addr:housenumber":"52",
    "addr:postcode":"6707 cw",
    "addr:street":"Irenestr;Gelderland",
    "iso:country":"NL",
    "sg:address":"Irenestr 52",
    "sg:city":"Wageningen",
    "sg:orig_category":"Verzekeringen - Verzekeringskantoren",
    "sg:phone":"+31 317 415 228",
    "sg:postcode":"6707 CW",
    "sg:province":"Gelderland",
    "wof:name":"Roekel, L Van",
    "wof:placetype":"venue"
},
  "geometry": {"coordinates":[5.660694,51.97089],"type":"Point"}
}