{
  "type": "Feature",
  "properties": {
    "addr:full":"Raadhuispln 55B Ridderkerk South Holland 2981 ER",
    "addr:housenumber":"55b",
    "addr:postcode":"2981 er",
    "addr:street":"Raadhuispln",
    "iso:country":"NL",
    "sg:address":"Raadhuispln 55B",
    "sg:city":"Ridderkerk",
    "sg:orig_category":"Banket",
    "sg:phone":"+31 180 497 888",
    "sg:postcode":"2981 ER",
    "sg:province":"South Holland",
    "wof:name":"Ridderke, 'T",
    "wof:placetype":"venue"
},
  "geometry": {"coordinates":[4.599432,51.870884],"type":"Point"}
}