{
  "type": "Feature",
  "properties": {
    "addr:full":"Eendrachtstr 3 Apeldoorn Gelderland 7335 CD",
    "addr:housenumber":"3",
    "addr:postcode":"7335 cd",
    "addr:street":"Eendrachtstr;Gelderland",
    "iso:country":"NL",
    "sg:address":"Eendrachtstr 3",
    "sg:city":"Apeldoorn",
    "sg:orig_category":"Verzekeringen - Verzekeringskantoren",
    "sg:phone":"+31 55 542 0000",
    "sg:postcode":"7335 CD",
    "sg:province":"Gelderland",
    "wof:name":"Vries, De",
    "wof:placetype":"venue"
},
  "geometry": {"coordinates":[5.958477,52.200256],"type":"Point"}
}