{
  "type": "Feature",
  "properties": {
    "iso:country":"NL",
    "sg:address":"Biezendwarsstraat 32",
    "sg:city":"Nijmegen",
    "sg:orig_category":"Beeldende Kunstenaars",
    "sg:phone":"+31 24 377 5921",
    "sg:postcode":"6541 ZH",
    "sg:province":"Gelderland",
    "sg:website":"http://home.wanadoo.nl/miriam.fleuren",
    "wof:name":"Miriam Fleuren",
    "wof:placetype":"venue"
},
  "geometry": {"coordinates":[5.845116,51.847824],"type":"Point"}
}