{
  "type": "Feature",
  "properties": {
    "addr:full":"De Kuul 2 Volendam Noord-Holland 1131 PD",
    "addr:housenumber":"2",
    "addr:postcode":"1131 pd",
    "addr:street":"De Kuul",
    "iso:country":"NL",
    "sg:address":"De Kuul 2",
    "sg:city":"Volendam",
    "sg:orig_category":"Visspeciaalzaken",
    "sg:phone":"+31 299 367 397",
    "sg:postcode":"1131 PD",
    "sg:province":"Noord-Holland",
    "wof:name":"Vishandel Anmaro Bv",
    "wof:placetype":"venue"
},
  "geometry": {"coordinates":[5.082908,52.504478],"type":"Point"}
}