{
  "type": "Feature",
  "properties": {
    "addr:full":"Walter Breedveldplein 2 'S Hertogenbosch Noord-Brabant 5231 ME",
    "addr:housenumber":"2 ' s",
    "addr:postcode":"5231 me",
    "addr:street":"Walter Breedveldplein",
    "iso:country":"NL",
    "sg:address":"Walter Breedveldplein 2",
    "sg:city":"'S Hertogenbosch",
    "sg:orig_category":"Makelaars In Onroerend Goed",
    "sg:phone":"+31 73 645 8500",
    "sg:postcode":"5231 ME",
    "sg:province":"Noord-Brabant",
    "wof:name":"Makelaars- En Assurantiekant B. Van Den Thillart B",
    "wof:placetype":"venue"
},
  "geometry": {"coordinates":[5.312147,51.704994],"type":"Point"}
}