{
  "type": "Feature",
  "properties": {
    "addr:full":"Langewg 7 St Philipsland Zeeland 4675 RJ",
    "addr:housenumber":"7",
    "addr:postcode":"4675 rj",
    "addr:street":"Langewg",
    "iso:country":"NL",
    "sg:address":"Langewg 7",
    "sg:city":"St Philipsland",
    "sg:orig_category":"Verenigingsgebouwen",
    "sg:phone":"+31 167 573 318",
    "sg:postcode":"4675 RJ",
    "sg:province":"Zeeland",
    "wof:name":"Dorphuis Anna Jacobapolder",
    "wof:placetype":"venue"
},
  "geometry": {"coordinates":[4.13067,51.637512],"type":"Point"}
}