{
  "type": "Feature",
  "properties": {
    "addr:full":"Lageweg 9 Burgh Haamstede Zeeland 4328 RS",
    "addr:housenumber":"9",
    "addr:postcode":"4328 rs",
    "addr:street":"Lageweg;Haamstede",
    "iso:country":"NL",
    "sg:address":"Lageweg 9",
    "sg:city":"Burgh Haamstede",
    "sg:orig_category":"Vakantiehuizen",
    "sg:phone":"+31 113 250 295",
    "sg:postcode":"4328 RS",
    "sg:province":"Zeeland",
    "wof:name":"Strandlust",
    "wof:placetype":"venue"
},
  "geometry": {"coordinates":[3.712598,51.675785],"type":"Point"}
}