{
  "type": "Feature",
  "properties": {
    "addr:full":"Klarinetsngl 126 Zwyndrecht Zuid-Holland 3335 DE",
    "addr:housenumber":"126",
    "addr:postcode":"3335 de",
    "addr:street":"Zwyndrecht",
    "iso:country":"NL",
    "sg:address":"Klarinetsngl 126",
    "sg:city":"Zwyndrecht",
    "sg:orig_category":"Goudsmeden En Zilversmeden",
    "sg:phone":"+31 78 610 3688",
    "sg:postcode":"3335 DE",
    "sg:province":"Zuid-Holland",
    "wof:name":"Regeer Goudsmid, F",
    "wof:placetype":"venue"
},
  "geometry": {"coordinates":[4.609644,51.821621],"type":"Point"}
}