{
  "type": "Feature",
  "properties": {
    "iso:country":"NL",
    "sg:address":"Leutherwg 80V",
    "sg:city":"Venlo",
    "sg:classifiers":[
        {
            "category":"Travel",
            "subcategory":"Hotels & Motels",
            "type":"Entertainment"
        }
    ],
    "sg:phone":"+31 77 351 2219",
    "sg:postcode":"5915 CK",
    "sg:province":"Limburg",
    "wof:name":"Goede Tijden, Hotel-Eetcaf?",
    "wof:placetype":"venue"
},
  "geometry": {"coordinates":[6.183925,51.357639],"type":"Point"}
}