{
  "type": "Feature",
  "properties": {
    "iso:country":"NL",
    "sg:address":"Hoogbree 62",
    "sg:city":"Assen",
    "sg:orig_category":"Diverse Grafische Activiteiten",
    "sg:phone":"+31 591 370 810",
    "sg:postcode":"9403 JR",
    "sg:province":"Drenthe",
    "wof:name":"Design Studio Hans Heijmans",
    "wof:placetype":"venue"
},
  "geometry": {"coordinates":[6.580913,53.019924],"type":"Point"}
}