{
  "type": "Feature",
  "properties": {
    "addr:full":"Hoogbree 62 Assen Drenthe 9403 JR",
    "addr:housenumber":"62",
    "addr:postcode":"9403 jr",
    "addr:street":"Hoogbree",
    "iso:country":"NL",
    "sg:address":"Hoogbree 62",
    "sg:city":"Assen",
    "sg:orig_category":"Diverse Grafische Activiteiten",
    "sg:phone":"+31 591 370 810",
    "sg:postcode":"9403 JR",
    "sg:province":"Drenthe",
    "wof:name":"Design Studio Hans Heijmans",
    "wof:placetype":"venue"
},
  "geometry": {"coordinates":[6.580913,53.019924],"type":"Point"}
}