{
  "type": "Feature",
  "properties": {
    "addr:full":"Industriewg O 27 Elst Gld Gelderland 6662 NE",
    "addr:housenumber":"27;6662",
    "addr:street":"Gld Gelderland;Ne",
    "iso:country":"NL",
    "sg:address":"Industriewg O 27",
    "sg:city":"Elst Gld",
    "sg:orig_category":"Gehandicapteninformatie",
    "sg:phone":"+31 481 366 000",
    "sg:postcode":"6662 NE",
    "sg:province":"Gelderland",
    "sg:website":"http://www.driestroom.nl",
    "wof:name":"Driestroom, Sticht De",
    "wof:placetype":"venue"
},
  "geometry": {"coordinates":[5.861998,51.907925],"type":"Point"}
}