{
  "type": "Feature",
  "properties": {
    "addr:full":"Nagelerstraat 23 Emmeloord NL. 8301 XE",
    "addr:housenumber":"23",
    "addr:postcode":"8301 xe",
    "addr:street":"Nagelerstraat;Nl.",
    "iso:country":"NL",
    "sg:address":"Nagelerstraat 23",
    "sg:city":"Emmeloord",
    "sg:orig_category":"Makelaars In Onroerend Goed",
    "sg:phone":"+31 527 697 768",
    "sg:postcode":"8301 XE",
    "sg:province":"NL.",
    "wof:name":"C.P. Thijssen Vastgoed Bv",
    "wof:placetype":"venue"
},
  "geometry": {"coordinates":[5.75426,52.708916],"type":"Point"}
}