{
  "type": "Feature",
  "properties": {
    "addr:full":"Hoofdstraat 53 Apeldoorn Gelderland 7311 JV",
    "addr:housenumber":"53",
    "addr:postcode":"7311 jv",
    "addr:street":"Hoofdstraat;Gelderland",
    "iso:country":"NL",
    "sg:address":"Hoofdstraat 53",
    "sg:city":"Apeldoorn",
    "sg:orig_category":"Verlichting And Huishoudartikelen",
    "sg:phone":"+31 55 521 4381",
    "sg:postcode":"7311 JV",
    "sg:province":"Gelderland",
    "wof:name":"Lampidee",
    "wof:placetype":"venue"
},
  "geometry": {"coordinates":[5.964943,52.21204],"type":"Point"}
}