{
  "type": "Feature",
  "properties": {
    "addr:full":"Euregiowg 320 Enschede Overijssel 7532 SN",
    "addr:housenumber":"320",
    "addr:postcode":"7532 sn",
    "iso:country":"NL",
    "sg:address":"Euregiowg 320",
    "sg:city":"Enschede",
    "sg:orig_category":"Drukkerijen",
    "sg:phone":"+31 53 461 4655",
    "sg:postcode":"7532 SN",
    "sg:province":"Overijssel",
    "wof:name":"Barends Bv",
    "wof:placetype":"venue"
},
  "geometry": {"coordinates":[6.950647,52.224243],"type":"Point"}
}