{
  "type": "Feature",
  "properties": {
    "iso:country":"NL",
    "sg:address":"Lindenstraat 5",
    "sg:city":"'S Gravenzande",
    "sg:orig_category":"Loodgieterswerk, Verwarming And Sanitaire Installaties",
    "sg:phone":"+31 174 421 346",
    "sg:postcode":"2691 DP",
    "sg:province":"Zuid-Holland",
    "wof:name":"Groenewald",
    "wof:placetype":"venue"
},
  "geometry": {"coordinates":[4.165768,51.998375],"type":"Point"}
}