{
  "type": "Feature",
  "properties": {
    "addr:full":"Rijksstraatweg 187 Haren Gn Groningen 9752 BE",
    "addr:housenumber":"187",
    "addr:postcode":"9752",
    "addr:street":"Rijksstraatweg",
    "iso:country":"NL",
    "sg:address":"Rijksstraatweg 187",
    "sg:city":"Haren Gn",
    "sg:classifiers":[
        {
            "category":"Shopping",
            "subcategory":"Clothing, Apparel, & Fashions",
            "type":"Retail Goods"
        }
    ],
    "sg:phone":"+31 50 534 3060",
    "sg:postcode":"9752 BE",
    "sg:province":"Groningen",
    "sg:tags":[
        "ondergoed",
        "lingerie"
    ],
    "wof:name":"Livera Ceres Bv",
    "wof:placetype":"venue"
},
  "geometry": {"coordinates":[6.60434,53.17244],"type":"Point"}
}