{
  "type": "Feature",
  "properties": {
    "addr:full":"Hoofdstr 43 Diever Provincie Drenthe 7981 AD",
    "addr:housenumber":"43",
    "addr:postcode":"7981 ad",
    "addr:street":"Hoofdstr;Provincie Drenthe",
    "iso:country":"NL",
    "sg:address":"Hoofdstr 43",
    "sg:city":"Diever",
    "sg:orig_category":"Zalenverhuur",
    "sg:phone":"+31 521 593 693",
    "sg:postcode":"7981 AD",
    "sg:province":"Provincie Drenthe",
    "wof:name":"Brinkzicht",
    "wof:placetype":"venue"
},
  "geometry": {"coordinates":[6.316218,52.855728],"type":"Point"}
}