{
  "type": "Feature",
  "properties": {
    "iso:country":"NL",
    "sg:address":"Enkstr 81",
    "sg:city":"Deventer",
    "sg:orig_category":"Publiciteitsbureaus",
    "sg:phone":"+31 570 631 307",
    "sg:postcode":"7413 TP",
    "sg:province":"NL.08",
    "wof:name":"Anna Bakker",
    "wof:placetype":"venue"
},
  "geometry": {"coordinates":[6.153606,52.26289],"type":"Point"}
}