{
  "type": "Feature",
  "properties": {
    "iso:country":"NL",
    "sg:address":"Steengroeveweg 1",
    "sg:city":"Winterswijk",
    "sg:orig_category":"Vakantiehuizen",
    "sg:phone":"+31 543 533 127",
    "sg:postcode":"7101 PG",
    "sg:province":"Gelderland",
    "wof:name":"J J Kammeyer",
    "wof:placetype":"venue"
},
  "geometry": {"coordinates":[6.740861,51.969975],"type":"Point"}
}