{
  "type": "Feature",
  "properties": {
    "addr:full":"Roozenburglaan 16 Middelburg Zeeland 4337 JH",
    "addr:housenumber":"16",
    "addr:postcode":"4337 jh",
    "addr:street":"Roozenburglaan",
    "iso:country":"NL",
    "sg:address":"Roozenburglaan 16",
    "sg:city":"Middelburg",
    "sg:orig_category":"Alternatieve Geneeskunde",
    "sg:phone":"+31 118 613 072",
    "sg:postcode":"4337 JH",
    "sg:province":"Zeeland",
    "wof:name":"Fysiotherapiepraktijk Zuid Dauwendaele",
    "wof:placetype":"venue"
},
  "geometry": {"coordinates":[3.623396,51.493061],"type":"Point"}
}