{
  "type": "Feature",
  "properties": {
    "iso:country":"NL",
    "sg:address":"Postbus 239",
    "sg:city":"Den Helder",
    "sg:orig_category":"Sportverenigingen En Ontspannings- Verenigingen",
    "sg:phone":"+31 223 630 073",
    "sg:postcode":"1780 AE",
    "sg:province":"North Holland",
    "wof:name":"Entre Nous Jeu De Boulesver",
    "wof:placetype":"venue"
},
  "geometry": {"coordinates":[4.758825,52.958191],"type":"Point"}
}