{
  "type": "Feature",
  "properties": {
    "addr:full":"Curacaostr 27 Almere Flevoland 1339 KL",
    "addr:housenumber":"27",
    "addr:postcode":"1339 kl",
    "addr:street":"Curacaostr;Flevoland",
    "iso:country":"NL",
    "sg:address":"Curacaostr 27",
    "sg:city":"Almere",
    "sg:orig_category":"Adviesbureaus Bedrijfsorganisatie",
    "sg:phone":"+31 36 537 9752",
    "sg:postcode":"1339 KL",
    "sg:province":"Flevoland",
    "wof:name":"Degen",
    "wof:placetype":"venue"
},
  "geometry": {"coordinates":[5.308802,52.393581],"type":"Point"}
}