{
  "type": "Feature",
  "properties": {
    "addr:full":"Bloesem 7 Huizen Noord-Holland 1275 BC",
    "addr:housenumber":"7",
    "addr:postcode":"1275 bc",
    "addr:street":"Bloesem",
    "iso:country":"NL",
    "sg:address":"Bloesem 7",
    "sg:city":"Huizen",
    "sg:orig_category":"Manueel Therapeuten",
    "sg:phone":"+31 35 526 3596",
    "sg:postcode":"1275 BC",
    "sg:province":"Noord-Holland",
    "wof:name":"Linden, Manueel Therapeut H V/D",
    "wof:placetype":"venue"
},
  "geometry": {"coordinates":[5.262856,52.28886],"type":"Point"}
}