{
  "type": "Feature",
  "properties": {
    "addr:full":"Dorpsstr 10 Hagestein Utrecht 4124 AM",
    "addr:housenumber":"10",
    "addr:postcode":"4124",
    "addr:street":"Dorpsstr",
    "iso:country":"NL",
    "sg:address":"Dorpsstr 10",
    "sg:city":"Hagestein",
    "sg:orig_category":"Zuivel - Groothandel",
    "sg:phone":"+31 347 351 323",
    "sg:postcode":"4124 AM",
    "sg:province":"Utrecht",
    "wof:name":"Weijer, G De",
    "wof:placetype":"venue"
},
  "geometry": {"coordinates":[5.119401,51.980148],"type":"Point"}
}