{
  "type": "Feature",
  "properties": {
    "addr:full":"Waterstr 8 Zutphen Gelderland 7201 HN",
    "addr:housenumber":"8",
    "addr:postcode":"7201 hn",
    "addr:street":"Waterstr;Gelderland",
    "iso:country":"NL",
    "sg:address":"Waterstr 8",
    "sg:city":"Zutphen",
    "sg:orig_category":"Meubelmakerijen",
    "sg:phone":"+31 575 512 299",
    "sg:postcode":"7201 HN",
    "sg:province":"Gelderland",
    "wof:name":"Mels Wellian",
    "wof:placetype":"venue"
},
  "geometry": {"coordinates":[6.193756,52.139816],"type":"Point"}
}