{
  "type": "Feature",
  "properties": {
    "addr:full":"Tamboerenstr 1 Roggel Limburg 6088 CN",
    "addr:housenumber":"1",
    "addr:postcode":"6088 cn",
    "addr:street":"Tamboerenstr",
    "iso:country":"NL",
    "sg:address":"Tamboerenstr 1",
    "sg:city":"Roggel",
    "sg:orig_category":"Pluimveebedrijven En -Handelaren",
    "sg:phone":"+31 475 491 954",
    "sg:postcode":"6088 CN",
    "sg:province":"Limburg",
    "wof:name":"Frenken, J G En J J",
    "wof:placetype":"venue"
},
  "geometry": {"coordinates":[5.916825,51.259125],"type":"Point"}
}