{
  "type": "Feature",
  "properties": {
    "addr:full":"St Anthonystr 4 Leeuwarden Friesland 8911 DV",
    "addr:housenumber":"4",
    "addr:postcode":"8911 dv",
    "iso:country":"NL",
    "sg:address":"St Anthonystr 4",
    "sg:city":"Leeuwarden",
    "sg:orig_category":"Beeldende Kunstenaars",
    "sg:phone":"+31 58 215 3110",
    "sg:postcode":"8911 DV",
    "sg:province":"Friesland",
    "wof:name":"Grafisch Atelier, Sticht",
    "wof:placetype":"venue"
},
  "geometry": {"coordinates":[5.794688,53.201958],"type":"Point"}
}