{
  "type": "Feature",
  "properties": {
    "iso:country":"NL",
    "sg:address":"Maliebaan 104",
    "sg:city":"Utrecht",
    "sg:classifiers":[
        {
            "category":"Professional",
            "subcategory":"Accounting & Tax Preparation",
            "type":"Services"
        }
    ],
    "sg:phone":"+31 30 234 0928",
    "sg:postcode":"3581 CZ",
    "sg:province":"Utrecht",
    "sg:tags":[
        "accountant"
    ],
    "wof:name":"Accountantskantoor Verhoef",
    "wof:placetype":"venue"
},
  "geometry": {"coordinates":[5.137402,52.094414],"type":"Point"}
}