{
  "type": "Feature",
  "properties": {
    "addr:full":"Staddijk 41 Nijmegen Gelderland 6537 TW",
    "addr:housenumber":"41",
    "addr:postcode":"6537 tw",
    "addr:street":"Staddijk;Gelderland",
    "iso:country":"NL",
    "sg:address":"Staddijk 41",
    "sg:city":"Nijmegen",
    "sg:orig_category":"Overheidsdiensten",
    "sg:phone":"+31 24 344 1625",
    "sg:postcode":"6537 TW",
    "sg:province":"Gelderland",
    "wof:name":"Jongerencentrum Staddijk",
    "wof:placetype":"venue"
},
  "geometry": {"coordinates":[5.7946581841,51.8065948486],"type":"Point"}
}