{
  "type": "Feature",
  "properties": {
    "addr:full":"Neerkanne 1 Amsterdam Noord-Holland 1082 BG",
    "addr:housenumber":"1",
    "addr:postcode":"1082",
    "addr:street":"Neerkanne",
    "iso:country":"NL",
    "sg:address":"Neerkanne 1",
    "sg:city":"Amsterdam",
    "sg:orig_category":"Schilderwerk",
    "sg:phone":"+31 20 642 4214",
    "sg:postcode":"1082 BG",
    "sg:province":"Noord-Holland",
    "wof:name":"Dijkema Schilders Amsterdam",
    "wof:placetype":"venue"
},
  "geometry": {"coordinates":[4.870244,52.324512],"type":"Point"}
}