{
  "type": "Feature",
  "properties": {
    "addr:full":"Fabriekstr 40 Deurne Noord-Brabant 5753 AH",
    "addr:housenumber":"40",
    "addr:postcode":"5753 ah",
    "addr:street":"Fabriekstr",
    "iso:country":"NL",
    "sg:address":"Fabriekstr 40",
    "sg:city":"Deurne",
    "sg:orig_category":"Autopoetsbedrijven",
    "sg:phone":"+31 493 351 807",
    "sg:postcode":"5753 AH",
    "sg:province":"Noord-Brabant",
    "wof:name":"Car Cleaning Deurne",
    "wof:placetype":"venue"
},
  "geometry": {"coordinates":[5.796253,51.45372],"type":"Point"}
}