{
  "type": "Feature",
  "properties": {
    "addr:full":"Broekstr 32 Arnhem Gelderland 6828 PZ",
    "addr:housenumber":"32",
    "addr:postcode":"6828 pz",
    "addr:street":"Broekstr",
    "iso:country":"NL",
    "sg:address":"Broekstr 32",
    "sg:city":"Arnhem",
    "sg:orig_category":"Projectontwikkeling",
    "sg:phone":"+31 26 384 4111",
    "sg:postcode":"6828 PZ",
    "sg:province":"Gelderland",
    "sg:website":"http://www.vanwijnen.nl",
    "wof:name":"Wijnen Oost Bv, Van",
    "wof:placetype":"venue"
},
  "geometry": {"coordinates":[5.922008,51.976086],"type":"Point"}
}