{
  "type": "Feature",
  "properties": {
    "addr:full":"Skaverij 21 Grou Friesland 9001 DA",
    "addr:housenumber":"21",
    "addr:postcode":"9001 da",
    "addr:street":"Skaverij",
    "iso:country":"NL",
    "sg:address":"Skaverij 21",
    "sg:city":"Grou",
    "sg:orig_category":"Diverse Consumentenartikelen Gh",
    "sg:phone":"+31 566 601 730",
    "sg:postcode":"9001 DA",
    "sg:province":"Friesland",
    "wof:name":"Van Welsenes - Import & Export",
    "wof:placetype":"venue"
},
  "geometry": {"coordinates":[-113.611923,43.688873],"type":"Point"}
}