{
  "type": "Feature",
  "properties": {
    "addr:full":"Meeuwenlaan 5 Rotterdam Zuid-Holland 3055 CK",
    "addr:housenumber":"5",
    "addr:postcode":"3055 ck",
    "addr:street":"Meeuwenlaan",
    "iso:country":"NL",
    "sg:address":"Meeuwenlaan 5",
    "sg:city":"Rotterdam",
    "sg:orig_category":"Onderhoud And Reparatie Kantoorapparatuur",
    "sg:phone":"+31 10 285 0163",
    "sg:postcode":"3055 CK",
    "sg:province":"Zuid-Holland",
    "wof:name":"Av-Data",
    "wof:placetype":"venue"
},
  "geometry": {"coordinates":[4.501631,51.962734],"type":"Point"}
}