{
  "type": "Feature",
  "properties": {
    "addr:full":"A W Lipsstr 17 Oud Beyerland Zuid-Holland 3262 GA",
    "addr:housenumber":"17",
    "addr:postcode":"3262 ga",
    "addr:street":"A W Lipsstr;Oud Beyerland",
    "iso:country":"NL",
    "sg:address":"A W Lipsstr 17",
    "sg:city":"Oud Beyerland",
    "sg:orig_category":"Bloemen En Planten - Decoratie",
    "sg:phone":"+31 186 615 073",
    "sg:postcode":"3262 GA",
    "sg:province":"Zuid-Holland",
    "wof:name":"Orquidea, La",
    "wof:placetype":"venue"
},
  "geometry": {"coordinates":[4.402012,51.81926],"type":"Point"}
}