{
  "type": "Feature",
  "properties": {
    "addr:full":"Slochterenlaan 1 Bussum Noord-Holland 1405 AL",
    "addr:housenumber":"1",
    "addr:postcode":"1405 al",
    "addr:street":"Slochterenlaan",
    "iso:country":"NL",
    "sg:address":"Slochterenlaan 1",
    "sg:city":"Bussum",
    "sg:orig_category":"Kantoorartikelen",
    "sg:phone":"+31 35 695 1699",
    "sg:postcode":"1405 AL",
    "sg:province":"Noord-Holland",
    "wof:name":"Buter En Smit Handelmij",
    "wof:placetype":"venue"
},
  "geometry": {"coordinates":[5.156648159,52.279258728],"type":"Point"}
}