{
  "type": "Feature",
  "properties": {
    "addr:full":"Fjord 155 Lelystad Flevoland 8224 DJ",
    "addr:housenumber":"155",
    "addr:postcode":"8224 dj",
    "addr:street":"Fjord;Flevoland",
    "iso:country":"NL",
    "sg:address":"Fjord 155",
    "sg:city":"Lelystad",
    "sg:orig_category":"Verenigingen En Stichtingen",
    "sg:phone":"+31 320 222 541",
    "sg:postcode":"8224 DJ",
    "sg:province":"Flevoland",
    "wof:name":"Krakeling, De",
    "wof:placetype":"venue"
},
  "geometry": {"coordinates":[5.490831,52.514771],"type":"Point"}
}