{
  "type": "Feature",
  "properties": {
    "iso:country":"NL",
    "sg:address":"Leeuwerik 3",
    "sg:city":"Bodegraven",
    "sg:orig_category":"Scholen Voor Basisonderwijs",
    "sg:phone":"+31 172 614 330",
    "sg:postcode":"2411 KR",
    "sg:province":"Zuid-Holland",
    "wof:name":"Vogelnest, 'T",
    "wof:placetype":"venue"
},
  "geometry": {"coordinates":[4.749713,52.077278],"type":"Point"}
}