{
  "type": "Feature",
  "properties": {
    "addr:full":"Westsngl 13 Amersfoort Utrecht 3811 BA",
    "addr:housenumber":"13",
    "addr:postcode":"3811 ba",
    "addr:street":"Westsngl",
    "iso:country":"NL",
    "sg:address":"Westsngl 13",
    "sg:city":"Amersfoort",
    "sg:orig_category":"Webdesign Bureaus",
    "sg:phone":"+31 33 461 5757",
    "sg:postcode":"3811 BA",
    "sg:province":"Utrecht",
    "sg:website":"http://www.lighthousepro.nl",
    "wof:name":"Lighthouse Prod",
    "wof:placetype":"venue"
},
  "geometry": {"coordinates":[5.3860850334,52.1523246765],"type":"Point"}
}