{
  "type": "Feature",
  "properties": {
    "addr:full":"Markt 3 Weert Limburg 6001 EJ",
    "addr:housenumber":"3",
    "addr:postcode":"6001 ej",
    "addr:street":"Markt",
    "iso:country":"NL",
    "sg:address":"Markt 3",
    "sg:city":"Weert",
    "sg:orig_category":"Makelaars En Adviseurs Onroerende Goederen",
    "sg:phone":"+31 495 535 939",
    "sg:postcode":"6001 EJ",
    "sg:province":"Limburg",
    "sg:website":"http://www.witte-verheul.nl",
    "wof:name":"Witte En Verheul, Makelaars- & Assurantiekantoor",
    "wof:placetype":"venue"
},
  "geometry": {"coordinates":[5.706589,51.253365],"type":"Point"}
}