{
  "type": "Feature",
  "properties": {
    "addr:full":"Reigerstraat 38 Zaandam North Holland 1506 XV",
    "addr:housenumber":"38",
    "addr:postcode":"1506 xv",
    "addr:street":"Reigerstraat",
    "iso:country":"NL",
    "sg:address":"Reigerstraat 38",
    "sg:city":"Zaandam",
    "sg:orig_category":"Verhuur Audiovisuele Apparatuur",
    "sg:phone":"+31 6 53417645",
    "sg:postcode":"1506 XV",
    "sg:province":"North Holland",
    "wof:name":"J.M. Sound",
    "wof:placetype":"venue"
},
  "geometry": {"coordinates":[4.817432,52.446442],"type":"Point"}
}