{
  "type": "Feature",
  "properties": {
    "iso:country":"NL",
    "sg:address":"Gerretsonlaan 131",
    "sg:city":"Eindhoven",
    "sg:orig_category":"Bloemen And Planten",
    "sg:phone":"+31 40 244 9699",
    "sg:postcode":"5624 JP",
    "sg:province":"Noord-Brabant",
    "wof:name":"Bloembinderij Anemone",
    "wof:placetype":"venue"
},
  "geometry": {"coordinates":[5.463214,51.47031],"type":"Point"}
}