{
  "type": "Feature",
  "properties": {
    "addr:full":"Nw Jachthaven 55 Drimmelen Noord-Brabant 4924 BA",
    "addr:housenumber":"55",
    "addr:postcode":"4924 ba",
    "addr:street":"Jachthaven",
    "iso:country":"NL",
    "sg:address":"Nw Jachthaven 55",
    "sg:city":"Drimmelen",
    "sg:orig_category":"Verenigingsgebouwen",
    "sg:phone":"+31 162 682 264",
    "sg:postcode":"4924 BA",
    "sg:province":"Noord-Brabant",
    "wof:name":"Foksel, 'T",
    "wof:placetype":"venue"
},
  "geometry": {"coordinates":[4.813308,51.709774],"type":"Point"}
}