{
  "type": "Feature",
  "properties": {
    "iso:country":"NL",
    "sg:address":"Nieuweweg 109",
    "sg:city":"Soest",
    "sg:orig_category":"Verzekeringen",
    "sg:phone":"+31 35 603 7103",
    "sg:postcode":"3765 GC",
    "sg:province":"Utrecht",
    "wof:name":"Bernouw En Beishuizen Pensioenconsultants",
    "wof:placetype":"venue"
},
  "geometry": {"coordinates":[5.300385,52.184044],"type":"Point"}
}