{
  "type": "Feature",
  "properties": {
    "iso:country":"NL",
    "sg:address":"Binnenweg 127",
    "sg:city":"Heemstede",
    "sg:orig_category":"Verlichting And Huishoudartikelen",
    "sg:phone":"+31 23 547 4861",
    "sg:postcode":"2101 JE",
    "sg:province":"Noord-Holland",
    "wof:name":"Vof Ecla",
    "wof:placetype":"venue"
},
  "geometry": {"coordinates":[4.620732,52.354481],"type":"Point"}
}