{
  "type": "Feature",
  "properties": {
    "addr:full":"Weteringschans 102 1017 Xs Amsterdam North Holland 1017 XS",
    "addr:housenumber":"102",
    "addr:postcode":"1017 xs;1017 xs",
    "addr:street":"Weteringschans",
    "iso:country":"NL",
    "sg:address":"Weteringschans 102",
    "sg:city":"1017 Xs Amsterdam",
    "sg:classifiers":[
        {
            "category":"Professional",
            "subcategory":"Accounting & Tax Preparation",
            "type":"Services"
        }
    ],
    "sg:phone":"+31 20 626 1523",
    "sg:postcode":"1017 XS",
    "sg:province":"North Holland",
    "sg:tags":[
        "accountant"
    ],
    "sg:website":"http://www.registeraccountant.com",
    "wof:name":"Fabo",
    "wof:placetype":"venue"
},
  "geometry": {"coordinates":[4.893195,52.373119],"type":"Point"}
}