{
  "type": "Feature",
  "properties": {
    "addr:full":"Lemmenhoek 6 Ospel Limburg 6035 AK",
    "addr:housenumber":"6",
    "addr:postcode":"6035 ak",
    "addr:street":"Lemmenhoek",
    "iso:country":"NL",
    "sg:address":"Lemmenhoek 6",
    "sg:city":"Ospel",
    "sg:classifiers":[
        {
            "category":"Personal",
            "subcategory":"Nail Salon",
            "type":"Services"
        }
    ],
    "sg:phone":"+31 495 633 925",
    "sg:postcode":"6035 AK",
    "sg:province":"Limburg",
    "sg:tags":[
        "pedicure"
    ],
    "wof:name":"Kiggen-Kessels, J C D",
    "wof:placetype":"venue"
},
  "geometry": {"coordinates":[-86.165451,34.620892],"type":"Point"}
}