{
  "type": "Feature",
  "properties": {
    "addr:full":"Herengracht 621 Amsterdam Noord-Holland 1017 CE",
    "addr:housenumber":"621",
    "addr:postcode":"1017 ce",
    "addr:street":"Herengracht",
    "iso:country":"NL",
    "sg:address":"Herengracht 621",
    "sg:city":"Amsterdam",
    "sg:orig_category":"Meubels And Huishoudapparatuur Gh",
    "sg:phone":"+31 20 638 3161",
    "sg:postcode":"1017 CE",
    "sg:province":"Noord-Holland",
    "wof:name":"La Cucina Import Benelux Bv",
    "wof:placetype":"venue"
},
  "geometry": {"coordinates":[4.8996601105,52.3657836914],"type":"Point"}
}