{
  "type": "Feature",
  "properties": {
    "addr:full":"Postbus 965 Leeuwarden Friesland 8901 BT",
    "addr:housenumber":"965",
    "addr:postcode":"8901 bt",
    "addr:street":"Postbus",
    "iso:country":"NL",
    "sg:address":"Postbus 965",
    "sg:city":"Leeuwarden",
    "sg:orig_category":"Adviesbureaus Bedrijfsorganisatie",
    "sg:phone":"+31 511 475 348",
    "sg:postcode":"8901 BT",
    "sg:province":"Friesland",
    "wof:name":"Rbc",
    "wof:placetype":"venue"
},
  "geometry": {"coordinates":[5.79143,53.203049],"type":"Point"}
}