{
  "type": "Feature",
  "properties": {
    "addr:full":"Riemenmaker 16 Wormer Noord-Holland 1531 PH",
    "addr:housenumber":"16",
    "addr:postcode":"1531",
    "addr:street":"Riemenmaker",
    "iso:country":"NL",
    "sg:address":"Riemenmaker 16",
    "sg:city":"Wormer",
    "sg:orig_category":"Adviesbureaus Elektrotechniek",
    "sg:phone":"+31 75 642 7298",
    "sg:postcode":"1531 PH",
    "sg:province":"Noord-Holland",
    "wof:name":"Grifhorst Bv",
    "wof:placetype":"venue"
},
  "geometry": {"coordinates":[4.812805,52.491837],"type":"Point"}
}