{
  "type": "Feature",
  "properties": {
    "addr:full":"Boezembocht 12 Rotterdam Zuid-Holland 3034 KA",
    "addr:housenumber":"12",
    "addr:postcode":"3034 ka",
    "addr:street":"Boezembocht",
    "iso:country":"NL",
    "sg:address":"Boezembocht 12",
    "sg:city":"Rotterdam",
    "sg:orig_category":"Jachthavens - Jachtwerven",
    "sg:phone":"+31 10 413 1226",
    "sg:postcode":"3034 KA",
    "sg:province":"Zuid-Holland",
    "wof:name":"Valkhof Bv",
    "wof:placetype":"venue"
},
  "geometry": {"coordinates":[4.493273,51.941341],"type":"Point"}
}