{
  "type": "Feature",
  "properties": {
    "iso:country":"NL",
    "sg:address":"Ryksstrwg 269",
    "sg:city":"Leersum",
    "sg:orig_category":"Verzekeringen - Verzekeringskantoren",
    "sg:phone":"+31 343 469 969",
    "sg:postcode":"3956 CP",
    "sg:province":"Utrecht",
    "wof:name":"Kranenburg Bv, Van",
    "wof:placetype":"venue"
},
  "geometry": {"coordinates":[5.43237,52.010792],"type":"Point"}
}