{
  "type": "Feature",
  "properties": {
    "iso:country":"NL",
    "sg:address":"Lutkenieuwstr 5",
    "sg:city":"Groningen",
    "sg:orig_category":"Adviesbureaus Automatisering",
    "sg:phone":"+31 50 360 0317",
    "sg:postcode":"9712 AW",
    "sg:province":"Groningen",
    "wof:name":"Pro6",
    "wof:placetype":"venue"
},
  "geometry": {"coordinates":[6.56156,53.216961],"type":"Point"}
}