{
  "type": "Feature",
  "properties": {
    "iso:country":"NL",
    "sg:address":"Arent Janszoon Ernststr 187",
    "sg:city":"Amsterdam",
    "sg:orig_category":"Fruit And Groenten Gh",
    "sg:phone":"+31 20 442 1895",
    "sg:postcode":"1083 GV",
    "sg:province":"Noord-Holland",
    "wof:name":"Bras Vruchtensappen Vof",
    "wof:placetype":"venue"
},
  "geometry": {"coordinates":[4.883717,52.331959],"type":"Point"}
}