{
  "type": "Feature",
  "properties": {
    "addr:full":"Oude Wierdenseweg 10 Almelo Overijssel 7604 PC",
    "addr:housenumber":"10",
    "addr:postcode":"7604 pc",
    "addr:street":"Oude Wierdenseweg",
    "iso:country":"NL",
    "sg:address":"Oude Wierdenseweg 10",
    "sg:city":"Almelo",
    "sg:orig_category":"Drukkerijen And Copyshops",
    "sg:phone":"+31 546 811 457",
    "sg:postcode":"7604 PC",
    "sg:province":"Overijssel",
    "wof:name":"Screen- En Filmdruk Platex",
    "wof:placetype":"venue"
},
  "geometry": {"coordinates":[6.628833,52.349762],"type":"Point"}
}