{
  "type": "Feature",
  "properties": {
    "addr:full":"Roermondsewg 154 Steyl Limburg 5935 AE",
    "addr:housenumber":"154",
    "addr:postcode":"5935 ae",
    "iso:country":"NL",
    "sg:address":"Roermondsewg 154",
    "sg:city":"Steyl",
    "sg:orig_category":"Gordijnenateliers",
    "sg:phone":"+31 77 373 7429",
    "sg:postcode":"5935 AE",
    "sg:province":"Limburg",
    "wof:name":"Myl?ne",
    "wof:placetype":"venue"
},
  "geometry": {"coordinates":[6.12459,51.330379],"type":"Point"}
}