{
  "type": "Feature",
  "properties": {
    "addr:full":"Nyverheidswg 22-24 Purmerend Noord-Holland 1442 LD",
    "addr:housenumber":"22-24",
    "addr:postcode":"1442 ld",
    "iso:country":"NL",
    "sg:address":"Nyverheidswg 22-24",
    "sg:city":"Purmerend",
    "sg:orig_category":"Fotoapparatuur En -Artikelen - Groothandel",
    "sg:phone":"+31 299 603 390",
    "sg:postcode":"1442 LD",
    "sg:province":"Noord-Holland",
    "wof:name":"Fimex Bv",
    "wof:placetype":"venue"
},
  "geometry": {"coordinates":[4.977457,52.517113],"type":"Point"}
}