{
  "type": "Feature",
  "properties": {
    "addr:full":"Nieuwe Rijn 48 Leiden Zuid-Holland 2312 JG",
    "addr:housenumber":"48",
    "addr:postcode":"2312 jg",
    "addr:street":"Nieuwe Rijn",
    "iso:country":"NL",
    "sg:address":"Nieuwe Rijn 48",
    "sg:city":"Leiden",
    "sg:orig_category":"Meubelzaken, Woning- And Keukeninrichting",
    "sg:phone":"+31 71 513 3100",
    "sg:postcode":"2312 JG",
    "sg:province":"Zuid-Holland",
    "wof:name":"Hulshoff Wonen",
    "wof:placetype":"venue"
},
  "geometry": {"coordinates":[4.493647,52.157055],"type":"Point"}
}