{
  "type": "Feature",
  "properties": {
    "iso:country":"NL",
    "sg:address":"Antwerpsestraat 146",
    "sg:city":"Putte",
    "sg:orig_category":"Verzekeringen",
    "sg:phone":"+31 164 602 530",
    "sg:postcode":"4645 BN",
    "sg:province":"North Brabant",
    "wof:name":"Assurantie- En Adviesbureau Quireyns Vof",
    "wof:placetype":"venue"
},
  "geometry": {"coordinates":[4.392553,51.362022],"type":"Point"}
}