{
  "type": "Feature",
  "properties": {
    "addr:full":"Meyelsewg 3 Beringe Limburg 5986 NH",
    "addr:housenumber":"3",
    "addr:postcode":"5986 nh",
    "addr:street":"Meyelsewg",
    "iso:country":"NL",
    "sg:address":"Meyelsewg 3",
    "sg:city":"Beringe",
    "sg:orig_category":"Autoverhuur",
    "sg:phone":"+31 77 307 8371",
    "sg:postcode":"5986 NH",
    "sg:province":"Limburg",
    "wof:name":"Harry Geelen",
    "wof:placetype":"venue"
},
  "geometry": {"coordinates":[-71.632828,44.001301],"type":"Point"}
}