{
  "type": "Feature",
  "properties": {
    "iso:country":"NL",
    "sg:address":"Hilvarenbeekse Weg 35",
    "sg:city":"Hilvarenbeek",
    "sg:orig_category":"Wegen And Sportterreinen",
    "sg:phone":"+31 13 535 5747",
    "sg:postcode":"5081 NW",
    "sg:province":"North Brabant",
    "wof:name":"Ooystra Bv",
    "wof:placetype":"venue"
},
  "geometry": {"coordinates":[5.1060900688,51.5374183655],"type":"Point"}
}