{
  "type": "Feature",
  "properties": {
    "addr:full":"Notenpln 67 S Gravenhage Zuid-Holland 2555 ZT",
    "addr:housenumber":"67;gravenhage",
    "addr:postcode":"2555 zt",
    "addr:street":"Notenpln;S",
    "iso:country":"NL",
    "sg:address":"Notenpln 67",
    "sg:city":"S Gravenhage",
    "sg:orig_category":"Meubelen Gebruikte",
    "sg:phone":"+31 70 355 4179",
    "sg:postcode":"2555 ZT",
    "sg:province":"Zuid-Holland",
    "sg:website":"http://www.kooptalles.nl",
    "wof:name":"Berg, V/D",
    "wof:placetype":"venue"
},
  "geometry": {"coordinates":[4.2417,52.06638],"type":"Point"}
}