{
  "type": "Feature",
  "properties": {
    "addr:full":"Akshoek 56 Enschede Overijssel 7546 JG",
    "addr:housenumber":"56",
    "addr:postcode":"7546 jg",
    "addr:street":"Akshoek",
    "iso:country":"NL",
    "sg:address":"Akshoek 56",
    "sg:city":"Enschede",
    "sg:orig_category":"Ballonvaarten En -Reclame",
    "sg:phone":"+31 53 436 5052",
    "sg:postcode":"7546 JG",
    "sg:province":"Overijssel",
    "wof:name":"Gh-Ballooning",
    "wof:placetype":"venue"
},
  "geometry": {"coordinates":[6.859824,52.198105],"type":"Point"}
}