{
  "type": "Feature",
  "properties": {
    "addr:full":"Hegstraat 33 Geleen Limburg 6161 BC",
    "addr:housenumber":"33",
    "addr:postcode":"6161 bc",
    "addr:street":"Hegstraat",
    "iso:country":"NL",
    "sg:address":"Hegstraat 33",
    "sg:city":"Geleen",
    "sg:classifiers":[
        {
            "category":"Education",
            "subcategory":"Preschool",
            "type":"Public Place"
        }
    ],
    "sg:phone":"+31 46 474 6016",
    "sg:postcode":"6161 BC",
    "sg:province":"Limburg",
    "sg:tags":[
        "kleuteronderwijs",
        "basis-"
    ],
    "wof:name":"Basisschool De Meulehook",
    "wof:placetype":"venue"
},
  "geometry": {"coordinates":[5.82424,50.965572],"type":"Point"}
}