{
  "type": "Feature",
  "properties": {
    "addr:full":"Arnhemse Bovenwg 160-178 Zeist Utrecht 3708 AH",
    "addr:postcode":"160-178;3708 ah",
    "addr:street":"Arnhemse",
    "iso:country":"NL",
    "sg:address":"Arnhemse Bovenwg 160-178",
    "sg:city":"Zeist",
    "sg:orig_category":"Levensmiddelen - Fabrieken En Groothandel",
    "sg:phone":"+31 30 697 3700",
    "sg:postcode":"3708 AH",
    "sg:province":"Utrecht",
    "sg:website":"http://www.heinz.com",
    "wof:name":"Heinz Bv, H J",
    "wof:placetype":"venue"
},
  "geometry": {"coordinates":[5.262085,52.071674],"type":"Point"}
}