{
  "type": "Feature",
  "properties": {
    "addr:full":"Westzijde 243 Zaandam Noord-Holland 1506 GE",
    "addr:housenumber":"243",
    "addr:postcode":"1506",
    "addr:street":"Westzijde",
    "iso:country":"NL",
    "sg:address":"Westzijde 243",
    "sg:city":"Zaandam",
    "sg:orig_category":"Kinderopvang Behalve Thuis",
    "sg:phone":"+31 75 616 8293",
    "sg:postcode":"1506 GE",
    "sg:province":"Noord-Holland",
    "wof:name":"Stichting Organisatie Zaanse Kinderopvang",
    "wof:placetype":"venue"
},
  "geometry": {"coordinates":[4.812261,52.453827],"type":"Point"}
}