{
  "type": "Feature",
  "properties": {
    "addr:full":"Noorderringwg 10 Marum Groningen 9363 TC",
    "addr:housenumber":"10",
    "addr:postcode":"9363 tc",
    "addr:street":"Noorderringwg",
    "iso:country":"NL",
    "sg:address":"Noorderringwg 10",
    "sg:city":"Marum",
    "sg:orig_category":"Metaalbewerking",
    "sg:phone":"+31 594 641 902",
    "sg:postcode":"9363 TC",
    "sg:province":"Groningen",
    "wof:name":"Bies Bv",
    "wof:placetype":"venue"
},
  "geometry": {"coordinates":[6.266659,53.151798],"type":"Point"}
}