{
  "type": "Feature",
  "properties": {
    "addr:full":"Grachterstraat 69 Kerkrade Limburg 6465 AL",
    "addr:housenumber":"69",
    "addr:postcode":"6465 al",
    "addr:street":"Grachterstraat",
    "iso:country":"NL",
    "sg:address":"Grachterstraat 69",
    "sg:city":"Kerkrade",
    "sg:orig_category":"Verzekeringen",
    "sg:phone":"+31 45 541 5426",
    "sg:postcode":"6465 AL",
    "sg:province":"Limburg",
    "wof:name":"Jos Scheeren Assurantien",
    "wof:placetype":"venue"
},
  "geometry": {"coordinates":[6.028597,50.851509],"type":"Point"}
}