{
  "type": "Feature",
  "properties": {
    "iso:country":"NL",
    "sg:address":"Kon Wilhelminawg 463",
    "sg:city":"Groenekan",
    "sg:orig_category":"Oldtimers",
    "sg:phone":"+31 346 211 392",
    "sg:postcode":"3737 BE",
    "sg:province":"Utrecht",
    "sg:website":"http://www.thefritz.nl",
    "wof:name":"The Fritz Oldtimers",
    "wof:placetype":"venue"
},
  "geometry": {"coordinates":[5.143571,52.123909],"type":"Point"}
}