{
  "type": "Feature",
  "properties": {
    "addr:full":"Wilhelminastraat 14 Numansdorp South Holland 3281 BZ",
    "addr:housenumber":"14",
    "addr:postcode":"3281 bz",
    "addr:street":"Wilhelminastraat",
    "iso:country":"NL",
    "sg:address":"Wilhelminastraat 14",
    "sg:city":"Numansdorp",
    "sg:orig_category":"Paramedische Behandelingen",
    "sg:phone":"+31 186 651 511",
    "sg:postcode":"3281 BZ",
    "sg:province":"South Holland",
    "wof:name":"St Dagverzorging V Ouderen De Binnenhaven",
    "wof:placetype":"venue"
},
  "geometry": {"coordinates":[4.433874,51.727829],"type":"Point"}
}