{
  "type": "Feature",
  "properties": {
    "iso:country":"NL",
    "sg:address":"Hogerwerf 2",
    "sg:city":"Roosendaal",
    "sg:orig_category":"Oud Metaal",
    "sg:phone":"+31 165 535 216",
    "sg:postcode":"4704 RV",
    "sg:province":"North Brabant",
    "wof:name":"Wortel, J Van",
    "wof:placetype":"venue"
},
  "geometry": {"coordinates":[4.4717111588,51.559627533],"type":"Point"}
}