{
  "type": "Feature",
  "properties": {
    "iso:country":"NL",
    "sg:address":"Kloosterpark 1",
    "sg:city":"De Meern",
    "sg:orig_category":"Wegen And Sportterreinen",
    "sg:phone":"+31 30 666 5300",
    "sg:postcode":"3454 HJ",
    "sg:province":"Utrecht",
    "wof:name":"Pol Bv",
    "wof:placetype":"venue"
},
  "geometry": {"coordinates":[5.0258021355,52.0832366943],"type":"Point"}
}