{
  "type": "Feature",
  "properties": {
    "addr:full":"Bergstraat 37 Eindhoven Noord-Brabant 5611 JX",
    "addr:housenumber":"37",
    "addr:postcode":"5611 jx",
    "addr:street":"Bergstraat",
    "iso:country":"NL",
    "sg:address":"Bergstraat 37",
    "sg:city":"Eindhoven",
    "sg:orig_category":"Herenkleding",
    "sg:phone":"+31 40 844 9262",
    "sg:postcode":"5611 JX",
    "sg:province":"Noord-Brabant",
    "wof:name":"Wesley'S",
    "wof:placetype":"venue"
},
  "geometry": {"coordinates":[5.484105,51.434471],"type":"Point"}
}