{
  "type": "Feature",
  "properties": {
    "addr:full":"Damstr 111 Roosendaal North Brabant 4701 GM",
    "addr:housenumber":"111",
    "addr:postcode":"4701 gm",
    "iso:country":"NL",
    "sg:address":"Damstr 111",
    "sg:city":"Roosendaal",
    "sg:orig_category":"Kappers",
    "sg:phone":"+31 165 534 455",
    "sg:postcode":"4701 GM",
    "sg:province":"North Brabant",
    "wof:name":"Arnoe",
    "wof:placetype":"venue"
},
  "geometry": {"coordinates":[4.4619860649,51.534576416],"type":"Point"}
}