{
  "type": "Feature",
  "properties": {
    "addr:full":"Gorterspad 19 Zaandijk North Holland 1544 RW",
    "addr:housenumber":"19",
    "addr:postcode":"1544 rw",
    "addr:street":"Gorterspad",
    "iso:country":"NL",
    "sg:address":"Gorterspad 19",
    "sg:city":"Zaandijk",
    "sg:orig_category":"Meubelmakerijen",
    "sg:phone":"+31 75 628 2076",
    "sg:postcode":"1544 RW",
    "sg:province":"North Holland",
    "sg:website":"http://www.hetmeubel.nl",
    "wof:name":"Meubel Vof, Het",
    "wof:placetype":"venue"
},
  "geometry": {"coordinates":[4.812735,52.47488],"type":"Point"}
}