{
  "type": "Feature",
  "properties": {
    "iso:country":"NL",
    "sg:address":"Planetenln 2",
    "sg:city":"Leeuwarden",
    "sg:orig_category":"Kampeerartikelen",
    "sg:phone":"+31 58 288 2120",
    "sg:postcode":"8938 AL",
    "sg:province":"Friesland",
    "wof:name":"Mega Camping Totaal",
    "wof:placetype":"venue"
},
  "geometry": {"coordinates":[5.8466320038,53.1952056885],"type":"Point"}
}