{
  "type": "Feature",
  "properties": {
    "addr:full":"Ysbaan 16A Sliedrecht Zuid-Holland 3362 KB",
    "addr:housenumber":"16a",
    "addr:postcode":"3362 kb",
    "addr:street":"Ysbaan",
    "iso:country":"NL",
    "sg:address":"Ysbaan 16A",
    "sg:city":"Sliedrecht",
    "sg:orig_category":"Verzekeringen - Verzekeringskantoren",
    "sg:phone":"+31 184 413 435",
    "sg:postcode":"3362 KB",
    "sg:province":"Zuid-Holland",
    "sg:website":"http://www.houtassu.nl",
    "wof:name":"Hout, Van Der",
    "wof:placetype":"venue"
},
  "geometry": {"coordinates":[4.772605,51.823555],"type":"Point"}
}