{
  "type": "Feature",
  "properties": {
    "iso:country":"NL",
    "sg:address":"Hertog Van Gelrestraat 47",
    "sg:city":"Baarlo Lb",
    "sg:classifiers":[
        {
            "category":"Education",
            "subcategory":"Preschool",
            "type":"Public Place"
        }
    ],
    "sg:phone":"+31 77 477 1785",
    "sg:postcode":"5991 BN",
    "sg:province":"Limburg",
    "sg:tags":[
        "kleuteronderwijs",
        "basis-"
    ],
    "wof:name":"Basisschool De Kwistbeek",
    "wof:placetype":"venue"
},
  "geometry": {"coordinates":[6.094042,51.32597],"type":"Point"}
}