{
  "type": "Feature",
  "properties": {
    "addr:full":"Rijksweg Zuid 49 Sittard Limburg 6131 AM",
    "addr:housenumber":"49",
    "addr:postcode":"6131",
    "addr:street":"Rijksweg Zuid",
    "iso:country":"NL",
    "sg:address":"Rijksweg Zuid 49",
    "sg:city":"Sittard",
    "sg:orig_category":"Werving And Selectie Van Tijdelijk Personeel And Uitzendkantoren",
    "sg:phone":"+31 46 452 6910",
    "sg:postcode":"6131 AM",
    "sg:province":"Limburg",
    "wof:name":"Uitzendbureau Start",
    "wof:placetype":"venue"
},
  "geometry": {"coordinates":[5.8602647781,50.9968757629],"type":"Point"}
}