{
  "type": "Feature",
  "properties": {
    "addr:full":"Hoge Giessen 1 Hoogblokland Zuid-Holland 4221 MA",
    "addr:housenumber":"1",
    "addr:postcode":"4221 ma",
    "addr:street":"Hoge Giessen",
    "iso:country":"NL",
    "sg:address":"Hoge Giessen 1",
    "sg:city":"Hoogblokland",
    "sg:orig_category":"Verzekeringen",
    "sg:phone":"+31 183 582 885",
    "sg:postcode":"4221 MA",
    "sg:province":"Zuid-Holland",
    "wof:name":"Devas",
    "wof:placetype":"venue"
},
  "geometry": {"coordinates":[4.961565,51.880402],"type":"Point"}
}