{
  "type": "Feature",
  "properties": {
    "iso:country":"NL",
    "sg:address":"Woonboulevard 30",
    "sg:city":"Almelo",
    "sg:orig_category":"Woninginrichting",
    "sg:phone":"+31 546 454 907",
    "sg:postcode":"7606 JA",
    "sg:province":"Overijssel",
    "sg:website":"http://www.decorette.nl",
    "wof:name":"Decorette Van Dijk",
    "wof:placetype":"venue"
},
  "geometry": {"coordinates":[6.6440181732,52.3400802612],"type":"Point"}
}