{
  "type": "Feature",
  "properties": {
    "addr:full":"Tiendweg West 17 Lekkerkerk Zuid-Holland 2941 EP",
    "addr:housenumber":"17",
    "addr:postcode":"2941 ep",
    "addr:street":"Tiendweg West",
    "iso:country":"NL",
    "sg:address":"Tiendweg West 17",
    "sg:city":"Lekkerkerk",
    "sg:classifiers":[
        {
            "category":"Professional",
            "subcategory":"Accounting & Tax Preparation",
            "type":"Services"
        }
    ],
    "sg:phone":"+31 180 662 688",
    "sg:postcode":"2941 EP",
    "sg:province":"Zuid-Holland",
    "sg:tags":[
        "accountant"
    ],
    "wof:name":"K.H. Van Herk Accountantskantoor",
    "wof:placetype":"venue"
},
  "geometry": {"coordinates":[4.676569,51.902],"type":"Point"}
}