{
  "type": "Feature",
  "properties": {
    "addr:full":"Harmonieplein 121 Maarssen Utrecht 3603 BS",
    "addr:housenumber":"121",
    "addr:postcode":"3603 bs",
    "addr:street":"Harmonieplein",
    "iso:country":"NL",
    "sg:address":"Harmonieplein 121",
    "sg:city":"Maarssen",
    "sg:orig_category":"Werving And Selectie Van Tijdelijk Personeel And Uitzendkantoren",
    "sg:phone":"+31 346 557 020",
    "sg:postcode":"3603 BS",
    "sg:province":"Utrecht",
    "wof:name":"Carriere",
    "wof:placetype":"venue"
},
  "geometry": {"coordinates":[5.0390181541,52.1383628845],"type":"Point"}
}