{
  "type": "Feature",
  "properties": {
    "addr:full":"Havenhoofd 7A Ridderkerk South Holland 2989 AE",
    "addr:housenumber":"7a",
    "addr:postcode":"2989 ae",
    "addr:street":"Havenhoofd",
    "iso:country":"NL",
    "sg:address":"Havenhoofd 7A",
    "sg:city":"Ridderkerk",
    "sg:orig_category":"Machineonderhoud En -Reparatie",
    "sg:phone":"+31 78 681 2957",
    "sg:postcode":"2989 AE",
    "sg:province":"South Holland",
    "sg:website":"http://www.breon.nl",
    "wof:name":"Breon",
    "wof:placetype":"venue"
},
  "geometry": {"coordinates":[4.642845,51.854443],"type":"Point"}
}