{
  "type": "Feature",
  "properties": {
    "addr:full":"Rillaerse Baan 75 Goirle Noord-Brabant 5053 EA",
    "addr:housenumber":"75",
    "addr:postcode":"5053 ea",
    "addr:street":"Rillaerse Baan",
    "iso:country":"NL",
    "sg:address":"Rillaerse Baan 75",
    "sg:city":"Goirle",
    "sg:orig_category":"Hulpverlening Sociaal",
    "sg:phone":"+31 13 543 5971",
    "sg:postcode":"5053 EA",
    "sg:province":"Noord-Brabant",
    "sg:website":"http://www.stichtingkompaan.nl",
    "wof:name":"Kompaan, Stichting",
    "wof:placetype":"venue"
},
  "geometry": {"coordinates":[5.04057,51.530647],"type":"Point"}
}