{
  "type": "Feature",
  "properties": {
    "addr:full":"Halsewg 25B Zelhem Gelderland 7021 CX",
    "addr:housenumber":"25b",
    "addr:postcode":"7021 cx",
    "addr:street":"Halsewg;Gelderland",
    "iso:country":"NL",
    "sg:address":"Halsewg 25B",
    "sg:city":"Zelhem",
    "sg:orig_category":"Kampeerauto'S",
    "sg:phone":"+31 314 625 872",
    "sg:postcode":"7021 CX",
    "sg:province":"Gelderland",
    "wof:name":"Linvest Vof",
    "wof:placetype":"venue"
},
  "geometry": {"coordinates":[6.3569002151,52.0056190491],"type":"Point"}
}