{
  "type": "Feature",
  "properties": {
    "addr:full":"S Gravenwg 95 Nieuwerkerk Yssel Zuid-Holland 2911 CE",
    "addr:housenumber":"95",
    "addr:postcode":"2911 ce",
    "iso:country":"NL",
    "sg:address":"S Gravenwg 95",
    "sg:city":"Nieuwerkerk Yssel",
    "sg:orig_category":"Verenigingsgebouwen",
    "sg:phone":"+31 180 315 381",
    "sg:postcode":"2911 CE",
    "sg:province":"Zuid-Holland",
    "wof:name":"Taverna",
    "wof:placetype":"venue"
},
  "geometry": {"coordinates":[4.623204,51.963005],"type":"Point"}
}