{
  "type": "Feature",
  "properties": {
    "iso:country":"NL",
    "sg:address":"Koninginnewg 87",
    "sg:city":"Oud Beyerland",
    "sg:classifiers":[
        {
            "category":"Retail",
            "subcategory":"Auto Repair",
            "type":"Services"
        }
    ],
    "sg:phone":"+31 186 612 397",
    "sg:postcode":"3261 CB",
    "sg:province":"Zuid-Holland",
    "sg:tags":[
        "garage"
    ],
    "wof:name":"Verbaas",
    "wof:placetype":"venue"
},
  "geometry": {"coordinates":[4.416438,51.820885],"type":"Point"}
}