{
  "type": "Feature",
  "properties": {
    "iso:country":"NL",
    "sg:address":"Franciscuswg 223",
    "sg:city":"Hilversum",
    "sg:orig_category":"Wegenbouw",
    "sg:phone":"+31 35 623 1002",
    "sg:postcode":"1216 SE",
    "sg:province":"Noord-Holland",
    "wof:name":"Bam Nbm Infra",
    "wof:placetype":"venue"
},
  "geometry": {"coordinates":[5.1469168663,52.2143783569],"type":"Point"}
}