{
  "type": "Feature",
  "properties": {
    "iso:country":"NL",
    "sg:address":"Kluisgat 66",
    "sg:city":"Groningen",
    "sg:orig_category":"Fotoreportages",
    "sg:phone":"+31 50 542 0264",
    "sg:postcode":"9732 EP",
    "sg:province":"Groningen",
    "wof:name":"Jager, H J",
    "wof:placetype":"venue"
},
  "geometry": {"coordinates":[6.618714,53.235313],"type":"Point"}
}