{
  "type": "Feature",
  "properties": {
    "iso:country":"NL",
    "sg:address":"Vlaamse Gaai 2",
    "sg:city":"Oostkapelle",
    "sg:classifiers":[
        {
            "category":"Education",
            "subcategory":"Preschool",
            "type":"Public Place"
        }
    ],
    "sg:phone":"+31 118 583 989",
    "sg:postcode":"4356 DC",
    "sg:province":"Zeeland",
    "sg:tags":[
        "kleuteronderwijs",
        "basis-"
    ],
    "wof:name":"Eben Haezerschool",
    "wof:placetype":"venue"
},
  "geometry": {"coordinates":[3.550562,51.56525],"type":"Point"}
}