{
  "type": "Feature",
  "properties": {
    "iso:country":"NL",
    "sg:address":"Rubensln 5",
    "sg:city":"Scherpenzeel Gld",
    "sg:orig_category":"Logopedisten",
    "sg:phone":"+31 33 277 2525",
    "sg:postcode":"3925 VB",
    "sg:province":"Gelderland",
    "wof:name":"Gerssen-Ligtvoet, J C J G",
    "wof:placetype":"venue"
},
  "geometry": {"coordinates":[5.485805,52.079689],"type":"Point"}
}