{
  "type": "Feature",
  "properties": {
    "addr:full":"Maresngl 55 Leiden South Holland 2316 HE",
    "addr:housenumber":"55",
    "addr:postcode":"2316 he",
    "addr:street":"Maresngl",
    "iso:country":"NL",
    "sg:address":"Maresngl 55",
    "sg:city":"Leiden",
    "sg:orig_category":"Kappers",
    "sg:phone":"+31 71 522 6434",
    "sg:postcode":"2316 HE",
    "sg:province":"South Holland",
    "wof:name":"Carry",
    "wof:placetype":"venue"
},
  "geometry": {"coordinates":[4.4946298599,52.1545715332],"type":"Point"}
}