{
  "type": "Feature",
  "properties": {
    "addr:full":"1E Oude Heseln 25 Nymegen Pennsylvania 6541 PA",
    "addr:housenumber":"25",
    "addr:postcode":"6541 pa",
    "addr:street":"1E;Heseln",
    "iso:country":"NL",
    "sg:address":"1E Oude Heseln 25",
    "sg:city":"Nymegen",
    "sg:orig_category":"Meubelen",
    "sg:phone":"+31 24 377 2111",
    "sg:postcode":"6541 PA",
    "sg:province":"Pennsylvania",
    "wof:name":"Vissers Meubelen Bv",
    "wof:placetype":"venue"
},
  "geometry": {"coordinates":[-77.604507,40.99464],"type":"Point"}
}