{
  "type": "Feature",
  "properties": {
    "addr:full":"V Wyngaardenpln 2 Heerhugowaard Noord-Holland 1701 CE",
    "addr:housenumber":"2",
    "addr:postcode":"1701 ce",
    "addr:street":"Wyngaardenpln",
    "iso:country":"NL",
    "sg:address":"V Wyngaardenpln 2",
    "sg:city":"Heerhugowaard",
    "sg:orig_category":"Kinderopvang",
    "sg:phone":"+31 72 571 5455",
    "sg:postcode":"1701 CE",
    "sg:province":"Noord-Holland",
    "sg:website":"http://www.kinderopvang-heerhugowaard.nl",
    "wof:name":"Ieniemini",
    "wof:placetype":"venue"
},
  "geometry": {"coordinates":[4.827522,52.665195],"type":"Point"}
}