{
  "type": "Feature",
  "properties": {
    "iso:country":"NL",
    "sg:address":"Noorderblokken 9",
    "sg:city":"Drouwenermond",
    "sg:orig_category":"Meubelreparatie And -Restauratie",
    "sg:phone":"+31 599 612 774",
    "sg:postcode":"9523 TJ",
    "sg:province":"Provincie Drenthe",
    "wof:name":"Sterenborg",
    "wof:placetype":"venue"
},
  "geometry": {"coordinates":[6.882143,52.974503],"type":"Point"}
}