{
  "type": "Feature",
  "properties": {
    "addr:full":"De Weide 8 Hoogeveen Drenthe 7908 AB",
    "addr:housenumber":"8",
    "addr:postcode":"7908 ab",
    "addr:street":"De Weide",
    "iso:country":"NL",
    "sg:address":"De Weide 8",
    "sg:city":"Hoogeveen",
    "sg:classifiers":[
        {
            "category":"Shopping",
            "subcategory":"Gifts & Souvenirs",
            "type":"Retail Goods"
        }
    ],
    "sg:phone":"+31 528 274 515",
    "sg:postcode":"7908 AB",
    "sg:province":"Drenthe",
    "sg:tags":[
        "geschenken"
    ],
    "wof:name":"Milo Gemakswinkel",
    "wof:placetype":"venue"
},
  "geometry": {"coordinates":[6.452514,52.718922],"type":"Point"}
}