{
  "type": "Feature",
  "properties": {
    "addr:full":"Brinkstr 22 Zuidlaren Drenthe 9471 EX",
    "addr:housenumber":"22",
    "addr:postcode":"9471 ex",
    "addr:street":"Brinkstr",
    "iso:country":"NL",
    "sg:address":"Brinkstr 22",
    "sg:city":"Zuidlaren",
    "sg:orig_category":"Balletscholen",
    "sg:phone":"+31 50 409 4021",
    "sg:postcode":"9471 EX",
    "sg:province":"Drenthe",
    "wof:name":"Fennie Van Der Haar Balletschool",
    "wof:placetype":"venue"
},
  "geometry": {"coordinates":[6.684276,53.095642],"type":"Point"}
}