{
  "type": "Feature",
  "properties": {
    "iso:country":"NL",
    "sg:address":"Enschedesestr 199",
    "sg:city":"Haaksbergen",
    "sg:orig_category":"Kaas",
    "sg:phone":"+31 53 572 3986",
    "sg:postcode":"7481 CP",
    "sg:province":"NL.08",
    "wof:name":"Siepe, De",
    "wof:placetype":"venue"
},
  "geometry": {"coordinates":[6.772354126,52.1700668335],"type":"Point"}
}