{
  "type": "Feature",
  "properties": {
    "addr:full":"Anna Paulownaplein 4 'S Gravenhage Zuid-Holland 2518 BK",
    "addr:housenumber":"4 '",
    "addr:postcode":"2518 bk",
    "addr:street":"Anna Paulownaplein",
    "iso:country":"NL",
    "sg:address":"Anna Paulownaplein 4",
    "sg:city":"'S Gravenhage",
    "sg:classifiers":[
        {
            "category":"Fast Food",
            "type":"Food & Drink"
        }
    ],
    "sg:phone":"+31 70 364 3120",
    "sg:postcode":"2518 BK",
    "sg:province":"Zuid-Holland",
    "sg:tags":[
        "afhaal",
        "restaurant"
    ],
    "wof:name":"Chin Ind Rest Blauwe Lotus",
    "wof:placetype":"venue"
},
  "geometry": {"coordinates":[4.299236,52.084675],"type":"Point"}
}