{
  "type": "Feature",
  "properties": {
    "addr:full":"Pastoor Van Breugelstr 134 Bosschenhoofd Noord-Brabant 4744 AG",
    "addr:housenumber":"134",
    "addr:postcode":"4744",
    "addr:street":"Pastoor Van Breugelstr",
    "iso:country":"NL",
    "sg:address":"Pastoor Van Breugelstr 134",
    "sg:city":"Bosschenhoofd",
    "sg:orig_category":"Verzekeringen",
    "sg:phone":"+31 165 311 975",
    "sg:postcode":"4744 AG",
    "sg:province":"Noord-Brabant",
    "wof:name":"Rokx Assurantien & Hypotheken",
    "wof:placetype":"venue"
},
  "geometry": {"coordinates":[4.544851,51.558647],"type":"Point"}
}