{
  "type": "Feature",
  "properties": {
    "iso:country":"NL",
    "sg:address":"Koningin Julianaplein 17",
    "sg:city":"Voorburg",
    "sg:orig_category":"Kappers",
    "sg:phone":"+31 70 386 2692",
    "sg:postcode":"2273 BR",
    "sg:province":"South Holland",
    "wof:name":"Robin & Jill",
    "wof:placetype":"venue"
},
  "geometry": {"coordinates":[4.357382,52.076187],"type":"Point"}
}