{
  "type": "Feature",
  "properties": {
    "addr:full":"Zuidsngl 58 Kortenhoef Noord-Holland 1241 HD",
    "addr:housenumber":"58",
    "addr:postcode":"1241 hd",
    "addr:street":"Zuidsngl",
    "iso:country":"NL",
    "sg:address":"Zuidsngl 58",
    "sg:city":"Kortenhoef",
    "sg:orig_category":"Omroep",
    "sg:phone":"+31 35 656 3515",
    "sg:postcode":"1241 HD",
    "sg:province":"Noord-Holland",
    "wof:name":"Aros",
    "wof:placetype":"venue"
},
  "geometry": {"coordinates":[5.115375,52.239986],"type":"Point"}
}