{
  "type": "Feature",
  "properties": {
    "iso:country":"NL",
    "sg:address":"Heemraadsingel 6",
    "sg:city":"Raamsdonk",
    "sg:orig_category":"Boekhouders",
    "sg:phone":"+31 162 521 666",
    "sg:postcode":"4944 VD",
    "sg:province":"North Brabant",
    "wof:name":"Loonbedrijf Van Strien Bv",
    "wof:placetype":"venue"
},
  "geometry": {"coordinates":[4.91149,51.68811],"type":"Point"}
}