{
  "type": "Feature",
  "properties": {
    "addr:full":"Schuitenberg 28 Roermond Limburg 6041 JK",
    "addr:housenumber":"28",
    "addr:postcode":"6041 jk",
    "addr:street":"Schuitenberg",
    "iso:country":"NL",
    "sg:address":"Schuitenberg 28",
    "sg:city":"Roermond",
    "sg:orig_category":"Meubelzaken, Woning- And Keukeninrichting",
    "sg:phone":"+31 475 316 661",
    "sg:postcode":"6041 JK",
    "sg:province":"Limburg",
    "wof:name":"Vof Laro",
    "wof:placetype":"venue"
},
  "geometry": {"coordinates":[5.9885191917,51.1904411316],"type":"Point"}
}