{
  "type": "Feature",
  "properties": {
    "addr:full":"Rynln 9 Kropswolde Groningen 9606 RP",
    "addr:housenumber":"9",
    "addr:postcode":"9606 rp",
    "addr:street":"Rynln",
    "iso:country":"NL",
    "sg:address":"Rynln 9",
    "sg:city":"Kropswolde",
    "sg:orig_category":"Adviesbureaus",
    "sg:phone":"+31 598 325 878",
    "sg:postcode":"9606 RP",
    "sg:province":"Groningen",
    "wof:name":"Martens, H A",
    "wof:placetype":"venue"
},
  "geometry": {"coordinates":[6.723135,53.14196],"type":"Point"}
}