{
  "type": "Feature",
  "properties": {
    "iso:country":"NL",
    "sg:address":"Jan Van Speycklaan 33",
    "sg:city":"Best",
    "sg:orig_category":"Loodgieterswerk, Verwarming And Sanitaire Installaties",
    "sg:phone":"+31 499 395 318",
    "sg:postcode":"5684 BD",
    "sg:province":"Noord-Brabant",
    "wof:name":"Loodgietersbedrijf Klingenberg",
    "wof:placetype":"venue"
},
  "geometry": {"coordinates":[-101.467331,31.19219],"type":"Point"}
}