{
  "type": "Feature",
  "properties": {
    "addr:full":"Meint Veningastraat 86 Hoogezand Groningen 9601 KH",
    "addr:housenumber":"86",
    "addr:postcode":"9601 kh",
    "addr:street":"Meint Veningastraat",
    "iso:country":"NL",
    "sg:address":"Meint Veningastraat 86",
    "sg:city":"Hoogezand",
    "sg:orig_category":"Kantoorartikelen",
    "sg:phone":"+31 598 392 913",
    "sg:postcode":"9601 KH",
    "sg:province":"Groningen",
    "wof:name":"Dumpstore En Deskstore",
    "wof:placetype":"venue"
},
  "geometry": {"coordinates":[6.7492079735,53.1630516052],"type":"Point"}
}