{
  "type": "Feature",
  "properties": {
    "addr:full":"Jaarbeurspln 6 Utrecht Utrecht 3521 AL",
    "addr:housenumber":"6",
    "addr:postcode":"3521 al",
    "addr:street":"Jaarbeurspln",
    "iso:country":"NL",
    "sg:address":"Jaarbeurspln 6",
    "sg:city":"Utrecht",
    "sg:orig_category":"Lederwaren",
    "sg:phone":"+31 30 294 9001",
    "sg:postcode":"3521 AL",
    "sg:province":"Utrecht",
    "wof:name":"Winter, De",
    "wof:placetype":"venue"
},
  "geometry": {"coordinates":[5.1072940826,52.088722229],"type":"Point"}
}