{
  "type": "Feature",
  "properties": {
    "addr:full":"Tesselschadestraat 20 B 'S Hertogenbosch Noord-Brabant 5216 JW",
    "addr:housenumber":"20 b ' s",
    "addr:postcode":"5216 jw",
    "addr:street":"Tesselschadestraat",
    "iso:country":"NL",
    "sg:address":"Tesselschadestraat 20 B",
    "sg:city":"'S Hertogenbosch",
    "sg:orig_category":"Technische Studies And Onderzoek",
    "sg:phone":"+31 73 612 2134",
    "sg:postcode":"5216 JW",
    "sg:province":"Noord-Brabant",
    "wof:name":"Leever Adviesburo Installatietechniek",
    "wof:placetype":"venue"
},
  "geometry": {"coordinates":[5.329802,51.685638],"type":"Point"}
}