{
  "type": "Feature",
  "properties": {
    "addr:full":"Parallelwg 12 Egmond Aan Zee Noord-Holland 1931 EW",
    "addr:housenumber":"12",
    "addr:postcode":"1931 ew",
    "addr:street":"Parallelwg",
    "iso:country":"NL",
    "sg:address":"Parallelwg 12",
    "sg:city":"Egmond Aan Zee",
    "sg:orig_category":"Sanitaire Artikelen",
    "sg:phone":"+31 72 506 7470",
    "sg:postcode":"1931 EW",
    "sg:province":"Noord-Holland",
    "wof:name":"Niba",
    "wof:placetype":"venue"
},
  "geometry": {"coordinates":[4.621826,52.618389],"type":"Point"}
}