{
  "type": "Feature",
  "properties": {
    "addr:full":"Tussen De Markten 14 Roosendaal Noord-Brabant 4701 AS",
    "addr:housenumber":"14",
    "addr:postcode":"4701 as",
    "addr:street":"Tussen De Markten",
    "iso:country":"NL",
    "sg:address":"Tussen De Markten 14",
    "sg:city":"Roosendaal",
    "sg:orig_category":"Juweliers",
    "sg:phone":"+31 165 551 331",
    "sg:postcode":"4701 AS",
    "sg:province":"Noord-Brabant",
    "wof:name":"Juwelier Nur",
    "wof:placetype":"venue"
},
  "geometry": {"coordinates":[4.45767,51.531403],"type":"Point"}
}