{
  "type": "Feature",
  "properties": {
    "addr:full":"Waterpoortstraat 43 Hellevoetsluis Zuid-Holland 3221 XV",
    "addr:housenumber":"43",
    "addr:postcode":"3221 xv",
    "addr:street":"Waterpoortstraat",
    "iso:country":"NL",
    "sg:address":"Waterpoortstraat 43",
    "sg:city":"Hellevoetsluis",
    "sg:orig_category":"Elektronische Bedrijfsinstallaties",
    "sg:phone":"+31 181 399 425",
    "sg:postcode":"3221 XV",
    "sg:province":"Zuid-Holland",
    "wof:name":"P & J Beveiliging Techniek",
    "wof:placetype":"venue"
},
  "geometry": {"coordinates":[4.134106,51.827839],"type":"Point"}
}