{
  "type": "Feature",
  "properties": {
    "addr:full":"Boomstraat 1 Terschelling West Friesland 8881 BS",
    "addr:housenumber":"1",
    "addr:postcode":"8881 bs",
    "addr:street":"Boomstraat",
    "iso:country":"NL",
    "sg:address":"Boomstraat 1",
    "sg:city":"Terschelling West",
    "sg:classifiers":[
        {
            "category":"Travel",
            "subcategory":"Hotels & Motels",
            "type":"Entertainment"
        }
    ],
    "sg:phone":"+31 562 442 194",
    "sg:postcode":"8881 BS",
    "sg:province":"Friesland",
    "wof:name":"Lutine",
    "wof:placetype":"venue"
},
  "geometry": {"coordinates":[5.214667,53.360226],"type":"Point"}
}