{
  "type": "Feature",
  "properties": {
    "addr:full":"Monstersewg 9 Poeldyk Zuid-Holland 2685 LJ",
    "addr:housenumber":"9",
    "addr:postcode":"2685 lj",
    "addr:street":"Monstersewg",
    "iso:country":"NL",
    "sg:address":"Monstersewg 9",
    "sg:city":"Poeldyk",
    "sg:orig_category":"Acupunctuur",
    "sg:phone":"+31 174 280 640",
    "sg:postcode":"2685 LJ",
    "sg:province":"Zuid-Holland",
    "wof:name":"Houtman-Van Der Wal, C G",
    "wof:placetype":"venue"
},
  "geometry": {"coordinates":[4.209227,52.022884],"type":"Point"}
}