{
  "type": "Feature",
  "properties": {
    "addr:full":"De Huikert 12 Nuenen Noord-Brabant 5674 RG",
    "addr:housenumber":"12",
    "addr:postcode":"5674 rg",
    "addr:street":"De Huikert",
    "iso:country":"NL",
    "sg:address":"De Huikert 12",
    "sg:city":"Nuenen",
    "sg:orig_category":"Kantoorartikelen",
    "sg:phone":"+31 40 283 5782",
    "sg:postcode":"5674 RG",
    "sg:province":"Noord-Brabant",
    "wof:name":"Av-Trading",
    "wof:placetype":"venue"
},
  "geometry": {"coordinates":[5.5639519691,51.4904937744],"type":"Point"}
}