{
  "type": "Feature",
  "properties": {
    "addr:full":"Menkemaborgstr 12 Hellevoetsluis South Holland 3223 WD",
    "addr:housenumber":"12",
    "addr:postcode":"3223 wd",
    "addr:street":"Menkemaborgstr",
    "iso:country":"NL",
    "sg:address":"Menkemaborgstr 12",
    "sg:city":"Hellevoetsluis",
    "sg:orig_category":"Onderhoudswerken",
    "sg:phone":"+31 181 311 682",
    "sg:postcode":"3223 WD",
    "sg:province":"South Holland",
    "wof:name":"Hellevoet",
    "wof:placetype":"venue"
},
  "geometry": {"coordinates":[4.1540408134,51.8406524658],"type":"Point"}
}