{
  "type": "Feature",
  "properties": {
    "addr:full":"Blyverswg 18 Rypwetering Zuid-Holland 2375 XX",
    "addr:housenumber":"18",
    "addr:postcode":"2375 xx",
    "addr:street":"Blyverswg",
    "iso:country":"NL",
    "sg:address":"Blyverswg 18",
    "sg:city":"Rypwetering",
    "sg:orig_category":"Betonwerken",
    "sg:phone":"+31 71 501 3640",
    "sg:postcode":"2375 XX",
    "sg:province":"Zuid-Holland",
    "wof:name":"Fennes, H W",
    "wof:placetype":"venue"
},
  "geometry": {"coordinates":[4.585019,52.190571],"type":"Point"}
}