{
  "type": "Feature",
  "properties": {
    "addr:full":"Blokdijk 3 Wijdenes North Holland 1608 HH",
    "addr:housenumber":"3",
    "addr:postcode":"1608 hh",
    "addr:street":"Blokdijk",
    "iso:country":"NL",
    "sg:address":"Blokdijk 3",
    "sg:city":"Wijdenes",
    "sg:orig_category":"Bedrijfsinventaris Gh",
    "sg:phone":"+31 229 501 222",
    "sg:postcode":"1608 HH",
    "sg:province":"North Holland",
    "wof:name":"Aventuur Thema Vormgevers",
    "wof:placetype":"venue"
},
  "geometry": {"coordinates":[5.150662,52.661289],"type":"Point"}
}