{
  "type": "Feature",
  "properties": {
    "addr:full":"Sportln 1 Bedum Groningen 9781 CL",
    "addr:housenumber":"1",
    "addr:postcode":"9781",
    "addr:street":"Sportln",
    "iso:country":"NL",
    "sg:address":"Sportln 1",
    "sg:city":"Bedum",
    "sg:orig_category":"Pensioenen",
    "sg:phone":"+31 50 301 0213",
    "sg:postcode":"9781 CL",
    "sg:province":"Groningen",
    "wof:name":"Firamed",
    "wof:placetype":"venue"
},
  "geometry": {"coordinates":[6.597629,53.300678],"type":"Point"}
}