{
  "type": "Feature",
  "properties": {
    "addr:full":"Slingerwg 108 Breda North Brabant 4814 AZ",
    "addr:housenumber":"108",
    "addr:postcode":"4814 az",
    "iso:country":"NL",
    "sg:address":"Slingerwg 108",
    "sg:city":"Breda",
    "sg:orig_category":"Kantoor- En Bedrijfsmeubelen",
    "sg:phone":"+31 76 520 7004",
    "sg:postcode":"4814 AZ",
    "sg:province":"North Brabant",
    "wof:name":"Jaspers Bv",
    "wof:placetype":"venue"
},
  "geometry": {"coordinates":[4.7657079697,51.5925102234],"type":"Point"}
}