{
  "type": "Feature",
  "properties": {
    "addr:full":"Paltrokstr 7 Uitgeest North Holland 1911 XM",
    "addr:housenumber":"7",
    "addr:postcode":"1911 xm",
    "addr:street":"Paltrokstr",
    "iso:country":"NL",
    "sg:address":"Paltrokstr 7",
    "sg:city":"Uitgeest",
    "sg:orig_category":"Bloemen En Planten - Decoratie",
    "sg:phone":"+31 251 318 159",
    "sg:postcode":"1911 XM",
    "sg:province":"North Holland",
    "wof:name":"Haute Fleurie",
    "wof:placetype":"venue"
},
  "geometry": {"coordinates":[4.71049,52.533054],"type":"Point"}
}