{
  "type": "Feature",
  "properties": {
    "addr:full":"Hoogsestraat 8 Valburg Gelderland 6675 BJ",
    "addr:housenumber":"8",
    "addr:postcode":"6675 bj",
    "addr:street":"Hoogsestraat;Gelderland",
    "iso:country":"NL",
    "sg:address":"Hoogsestraat 8",
    "sg:city":"Valburg",
    "sg:orig_category":"Bloemen And Planten",
    "sg:phone":"+31 488 431 372",
    "sg:postcode":"6675 BJ",
    "sg:province":"Gelderland",
    "wof:name":"Bloemisterij Willemsen",
    "wof:placetype":"venue"
},
  "geometry": {"coordinates":[5.779626,51.913002],"type":"Point"}
}