{
  "type": "Feature",
  "properties": {
    "iso:country":"NL",
    "sg:address":"Trompln 72",
    "sg:city":"Weert",
    "sg:orig_category":"Verbouwingen",
    "sg:phone":"+31 495 531 138",
    "sg:postcode":"6004 EP",
    "sg:province":"Limburg",
    "wof:name":"Lenders, Bouwbedrijf Johan",
    "wof:placetype":"venue"
},
  "geometry": {"coordinates":[5.732074,51.250549],"type":"Point"}
}