{
  "type": "Feature",
  "properties": {
    "iso:country":"NL",
    "sg:address":"Hofwg 5-7",
    "sg:city":"S Gravenhage",
    "sg:classifiers":[
        {
            "category":"Travel",
            "subcategory":"Hotels & Motels",
            "type":"Entertainment"
        }
    ],
    "sg:phone":"+31 70 364 8846",
    "sg:postcode":"2511 AA",
    "sg:province":"Zuid-Holland",
    "sg:website":"http://www.novotel.nl",
    "wof:name":"Novotel Den Haag Centrum",
    "wof:placetype":"venue"
},
  "geometry": {"coordinates":[4.31627,52.07896],"type":"Point"}
}