{
  "type": "Feature",
  "properties": {
    "addr:full":"Jodenstraat 30 Venlo Limburg 5911 HK",
    "addr:housenumber":"30",
    "addr:postcode":"5911 hk",
    "addr:street":"Jodenstraat",
    "iso:country":"NL",
    "sg:address":"Jodenstraat 30",
    "sg:city":"Venlo",
    "sg:orig_category":"Opticiens",
    "sg:phone":"+31 77 354 5094",
    "sg:postcode":"5911 HK",
    "sg:province":"Limburg",
    "wof:name":"Hans Anders Prijsoptiek",
    "wof:placetype":"venue"
},
  "geometry": {"coordinates":[6.1666150093,51.369102478],"type":"Point"}
}