{
  "type": "Feature",
  "properties": {
    "addr:full":"J V Nassaustr 44 S Gravenhage Zuid-Holland 2596 BV",
    "addr:housenumber":"44;gravenhage",
    "addr:postcode":"2596 bv",
    "addr:street":"J;Nassaustr;S",
    "iso:country":"NL",
    "sg:address":"J V Nassaustr 44",
    "sg:city":"S Gravenhage",
    "sg:orig_category":"Verenigingen En Stichtingen",
    "sg:phone":"+31 70 324 5571",
    "sg:postcode":"2596 BV",
    "sg:province":"Zuid-Holland",
    "wof:name":"Haagse Ver Van 1854 Tot Verbetering Van Woningen",
    "wof:placetype":"venue"
},
  "geometry": {"coordinates":[4.31846,52.093311],"type":"Point"}
}