{
  "type": "Feature",
  "properties": {
    "addr:full":"Emmawijk 8 Zwolle Overijssel 8011 CM",
    "addr:housenumber":"8",
    "addr:postcode":"8011 cm",
    "addr:street":"Emmawijk",
    "iso:country":"NL",
    "sg:address":"Emmawijk 8",
    "sg:city":"Zwolle",
    "sg:orig_category":"Bedrijfs- And Managementsconsultants",
    "sg:phone":"+31 38 421 0288",
    "sg:postcode":"8011 CM",
    "sg:province":"Overijssel",
    "wof:name":"Van Ede & Partners",
    "wof:placetype":"venue"
},
  "geometry": {"coordinates":[6.086564,52.509693],"type":"Point"}
}