{
  "type": "Feature",
  "properties": {
    "addr:full":"Osdorppln 731 Amsterdam North Holland 1068 TC",
    "addr:housenumber":"731",
    "addr:postcode":"1068 tc",
    "iso:country":"NL",
    "sg:address":"Osdorppln 731",
    "sg:city":"Amsterdam",
    "sg:orig_category":"Zoetwaren - Winkels",
    "sg:phone":"+31 20 619 6113",
    "sg:postcode":"1068 TC",
    "sg:province":"North Holland",
    "sg:website":"http://www.mecca.nl",
    "wof:name":"Jamin",
    "wof:placetype":"venue"
},
  "geometry": {"coordinates":[4.805405,52.358898],"type":"Point"}
}