{
  "type": "Feature",
  "properties": {
    "addr:full":"Zijkanaal C 15 Spaarndam Noord-Holland 2064 KA",
    "addr:housenumber":"15",
    "addr:postcode":"2064 ka",
    "addr:street":"Zijkanaal C",
    "iso:country":"NL",
    "sg:address":"Zijkanaal C 15",
    "sg:city":"Spaarndam",
    "sg:orig_category":"Pleziervaartuigen And Reparatie",
    "sg:phone":"+31 23 537 3951",
    "sg:postcode":"2064 KA",
    "sg:province":"Noord-Holland",
    "wof:name":"De Viking",
    "wof:placetype":"venue"
},
  "geometry": {"coordinates":[4.687344,52.416054],"type":"Point"}
}