{
  "type": "Feature",
  "properties": {
    "addr:full":"Heerenweg 211 Heiloo North Holland 1851 KR",
    "addr:housenumber":"211",
    "addr:postcode":"1851 kr",
    "addr:street":"Heerenweg",
    "iso:country":"NL",
    "sg:address":"Heerenweg 211",
    "sg:city":"Heiloo",
    "sg:orig_category":"Verlichting And Huishoudartikelen",
    "sg:phone":"+31 72 533 1166",
    "sg:postcode":"1851 KR",
    "sg:province":"North Holland",
    "wof:name":"Het Porceleyn Huys",
    "wof:placetype":"venue"
},
  "geometry": {"coordinates":[4.701863,52.59951],"type":"Point"}
}