{
  "type": "Feature",
  "properties": {
    "addr:full":"Spuistr 185A Amsterdam North Holland 1012 VN",
    "addr:housenumber":"185a",
    "addr:postcode":"1012 vn",
    "iso:country":"NL",
    "sg:address":"Spuistr 185A",
    "sg:city":"Amsterdam",
    "sg:orig_category":"Verenigingen En Stichtingen",
    "sg:phone":"+31 20 420 5438",
    "sg:postcode":"1012 VN",
    "sg:province":"North Holland",
    "wof:name":"Tibet",
    "wof:placetype":"venue"
},
  "geometry": {"coordinates":[4.889633,52.372086],"type":"Point"}
}