{
  "type": "Feature",
  "properties": {
    "addr:full":"Breeuwershoeve 101 Apeldoorn Gelderland 7326 SP",
    "addr:housenumber":"101",
    "addr:postcode":"7326 sp",
    "addr:street":"Breeuwershoeve;Gelderland",
    "iso:country":"NL",
    "sg:address":"Breeuwershoeve 101",
    "sg:city":"Apeldoorn",
    "sg:orig_category":"Autorijscholen",
    "sg:phone":"+31 55 542 2410",
    "sg:postcode":"7326 SP",
    "sg:province":"Gelderland",
    "wof:name":"Sportief",
    "wof:placetype":"venue"
},
  "geometry": {"coordinates":[6.015838,52.189857],"type":"Point"}
}