{
  "type": "Feature",
  "properties": {
    "addr:full":"T Flieren 22 Vianen Nb Noord-Brabant 5434 LB",
    "addr:housenumber":"22",
    "addr:postcode":"5434 lb",
    "addr:street":"T Flieren",
    "iso:country":"NL",
    "sg:address":"T Flieren 22",
    "sg:city":"Vianen Nb",
    "sg:classifiers":[
        {
            "category":"Fast Food",
            "type":"Food & Drink"
        }
    ],
    "sg:phone":"+31 485 312 058",
    "sg:postcode":"5434 LB",
    "sg:province":"Noord-Brabant",
    "sg:tags":[
        "afhaal",
        "restaurant"
    ],
    "wof:name":"Cafetaria Chez Wiellie",
    "wof:placetype":"venue"
},
  "geometry": {"coordinates":[5.859305,51.718616],"type":"Point"}
}