{
  "type": "Feature",
  "properties": {
    "addr:full":"Roelantdreef 235 Utrecht Utrecht 3562 KH",
    "addr:housenumber":"235",
    "addr:postcode":"3562 kh",
    "addr:street":"Roelantdreef",
    "iso:country":"NL",
    "sg:address":"Roelantdreef 235",
    "sg:city":"Utrecht",
    "sg:orig_category":"Banken",
    "sg:phone":"+31 30 261 4229",
    "sg:postcode":"3562 KH",
    "sg:province":"Utrecht",
    "wof:name":"Fortis",
    "wof:placetype":"venue"
},
  "geometry": {"coordinates":[5.11313,52.112415],"type":"Point"}
}