{
  "type": "Feature",
  "properties": {
    "addr:full":"Vervoornstraat 83 Putten Gelderland 3882 XM",
    "addr:housenumber":"83",
    "addr:postcode":"3882 xm",
    "addr:street":"Vervoornstraat;Gelderland",
    "iso:country":"NL",
    "sg:address":"Vervoornstraat 83",
    "sg:city":"Putten",
    "sg:orig_category":"Architecten",
    "sg:phone":"+31 341 361 219",
    "sg:postcode":"3882 XM",
    "sg:province":"Gelderland",
    "wof:name":"Tuinontwerpburo Ingeborg Hovind",
    "wof:placetype":"venue"
},
  "geometry": {"coordinates":[5.604327,52.250931],"type":"Point"}
}