{
  "type": "Feature",
  "properties": {
    "addr:full":"Postbus 87 Bennebroek Noord-Holland 2120 AB",
    "addr:housenumber":"87",
    "addr:postcode":"2120 ab",
    "addr:street":"Postbus",
    "iso:country":"NL",
    "sg:address":"Postbus 87",
    "sg:city":"Bennebroek",
    "sg:orig_category":"Horloges - Groothandel",
    "sg:phone":"+31 23 584 1731",
    "sg:postcode":"2120 AB",
    "sg:province":"Noord-Holland",
    "sg:website":"http://www.tng.nl",
    "wof:name":"Tack & Gybe Int Bv",
    "wof:placetype":"venue"
},
  "geometry": {"coordinates":[4.593208,52.32214],"type":"Point"}
}