{
  "type": "Feature",
  "properties": {
    "addr:full":"H De Keyserstr 27A Utrecht Utrecht 3583 TE",
    "addr:housenumber":"27a",
    "addr:postcode":"3583 te",
    "iso:country":"NL",
    "sg:address":"H De Keyserstr 27A",
    "sg:city":"Utrecht",
    "sg:orig_category":"Psychologen",
    "sg:phone":"+31 30 251 8138",
    "sg:postcode":"3583 TE",
    "sg:province":"Utrecht",
    "wof:name":"Veen, H A Van Der",
    "wof:placetype":"venue"
},
  "geometry": {"coordinates":[5.14371,52.086601],"type":"Point"}
}