{
  "type": "Feature",
  "properties": {
    "addr:full":"Eendenstr 5 Venlo Limburg 5912 VE",
    "addr:housenumber":"5",
    "addr:postcode":"5912",
    "addr:street":"Eendenstr;Ve",
    "iso:country":"NL",
    "sg:address":"Eendenstr 5",
    "sg:city":"Venlo",
    "sg:orig_category":"Oud Metaal",
    "sg:phone":"+31 77 354 3484",
    "sg:postcode":"5912 VE",
    "sg:province":"Limburg",
    "wof:name":"Burhenne, L",
    "wof:placetype":"venue"
},
  "geometry": {"coordinates":[6.1696038246,51.3591918945],"type":"Point"}
}