{
  "type": "Feature",
  "properties": {
    "addr:full":"Annevillelaan 11 Ulvenhout Noord-Brabant 4851 CA",
    "addr:housenumber":"11",
    "addr:postcode":"4851 ca",
    "addr:street":"Annevillelaan",
    "iso:country":"NL",
    "sg:address":"Annevillelaan 11",
    "sg:city":"Ulvenhout",
    "sg:orig_category":"Wegen And Sportterreinen",
    "sg:phone":"+31 76 560 2254",
    "sg:postcode":"4851 CA",
    "sg:province":"Noord-Brabant",
    "wof:name":"J.M. Van Den Broek Bv",
    "wof:placetype":"venue"
},
  "geometry": {"coordinates":[4.7990999222,51.5496177673],"type":"Point"}
}