{
  "type": "Feature",
  "properties": {
    "addr:full":"Schoolstr Oudleus 7 Dalfsen NL.08 7722 SZ",
    "addr:housenumber":"7;nl.08",
    "addr:postcode":"7722 sz",
    "addr:street":"Oudleus",
    "iso:country":"NL",
    "sg:address":"Schoolstr Oudleus 7",
    "sg:city":"Dalfsen",
    "sg:orig_category":"Adviesbureaus Bouwkunde",
    "sg:phone":"+31 529 471 434",
    "sg:postcode":"7722 SZ",
    "sg:province":"NL.08",
    "wof:name":"Hogenkamp, T",
    "wof:placetype":"venue"
},
  "geometry": {"coordinates":[6.310535,52.533569],"type":"Point"}
}