{
  "type": "Feature",
  "properties": {
    "addr:full":"Kennemerstrwg 121 Heiloo North Holland 1851 BC",
    "addr:housenumber":"121",
    "addr:postcode":"1851 bc",
    "iso:country":"NL",
    "sg:address":"Kennemerstrwg 121",
    "sg:city":"Heiloo",
    "sg:orig_category":"Onderhoudswerken",
    "sg:phone":"+31 72 512 8005",
    "sg:postcode":"1851 BC",
    "sg:province":"North Holland",
    "wof:name":"Klaase, Aannemersbedrijf",
    "wof:placetype":"venue"
},
  "geometry": {"coordinates":[4.713702,52.604191],"type":"Point"}
}