{
  "type": "Feature",
  "properties": {
    "iso:country":"NL",
    "sg:address":"Kapelaan J A Heerenstr 7",
    "sg:city":"Best",
    "sg:orig_category":"Werving And Selectie Van Tijdelijk Personeel And Uitzendkantoren",
    "sg:phone":"+31 499 375 550",
    "sg:postcode":"5683 ED",
    "sg:province":"Texas",
    "wof:name":"Adecco",
    "wof:placetype":"venue"
},
  "geometry": {"coordinates":[-101.46463775629999,31.1965351105],"type":"Point"}
}