{
  "type": "Feature",
  "properties": {
    "addr:full":"Postbus 346 Tiel Gelderland 4000 AH",
    "addr:housenumber":"346",
    "addr:postcode":"4000 ah",
    "addr:street":"Postbus;Gelderland",
    "iso:country":"NL",
    "sg:address":"Postbus 346",
    "sg:city":"Tiel",
    "sg:orig_category":"Verenigingen En Stichtingen",
    "sg:phone":"+31 344 615 718",
    "sg:postcode":"4000 AH",
    "sg:province":"Gelderland",
    "wof:name":"Alg Ver Gehandicapten Ned",
    "wof:placetype":"venue"
},
  "geometry": {"coordinates":[5.430696,51.888096],"type":"Point"}
}