{
  "type": "Feature",
  "properties": {
    "iso:country":"NL",
    "sg:address":"Industriestr 29C",
    "sg:city":"Klazienaveen",
    "sg:orig_category":"Kunststoffen- Verwerkende Industrie",
    "sg:phone":"+31 591 301 907",
    "sg:postcode":"7891 GV",
    "sg:province":"Provincie Drenthe",
    "sg:website":"http://www.lfs-kme.com",
    "wof:name":"Km - Enginering",
    "wof:placetype":"venue"
},
  "geometry": {"coordinates":[7.014833,52.722198],"type":"Point"}
}