{
  "type": "Feature",
  "properties": {
    "addr:full":"Koperwerf 25 S Gravenhage Zuid-Holland 2544 EM",
    "addr:housenumber":"25;gravenhage",
    "addr:postcode":"2544 em",
    "addr:street":"Koperwerf;S",
    "iso:country":"NL",
    "sg:address":"Koperwerf 25",
    "sg:city":"S Gravenhage",
    "sg:classifiers":[
        {
            "category":"Food & Beverages",
            "subcategory":"Bakery",
            "type":"Retail Goods"
        }
    ],
    "sg:phone":"+31 70 329 8585",
    "sg:postcode":"2544 EM",
    "sg:province":"Zuid-Holland",
    "sg:tags":[
        "brood",
        "en",
        "banket"
    ],
    "wof:name":"Kempen, C J Van",
    "wof:placetype":"venue"
},
  "geometry": {"coordinates":[4.25157,52.039551],"type":"Point"}
}