{
  "type": "Feature",
  "properties": {
    "addr:full":"Pasteurstr 14B Zandvoort Noord-Holland 2041 VA",
    "addr:housenumber":"14b",
    "addr:postcode":"2041",
    "addr:street":"Pasteurstr",
    "iso:country":"NL",
    "sg:address":"Pasteurstr 14B",
    "sg:city":"Zandvoort",
    "sg:orig_category":"Psychologen",
    "sg:phone":"+31 23 572 0291",
    "sg:postcode":"2041 VA",
    "sg:province":"Noord-Holland",
    "wof:name":"Aerts-Baljon, Drs E E L",
    "wof:placetype":"venue"
},
  "geometry": {"coordinates":[4.549504,52.378658],"type":"Point"}
}