{
  "type": "Feature",
  "properties": {
    "iso:country":"NL",
    "sg:address":"Pasteurstr 14B",
    "sg:city":"Zandvoort",
    "sg:orig_category":"Psychologen",
    "sg:phone":"+31 23 572 0291",
    "sg:postcode":"2041 VA",
    "sg:province":"Noord-Holland",
    "wof:name":"Aerts-Baljon, Drs E E L",
    "wof:placetype":"venue"
},
  "geometry": {"coordinates":[4.549504,52.378658],"type":"Point"}
}