{
  "type": "Feature",
  "properties": {
    "iso:country":"NL",
    "sg:address":"Streek 17",
    "sg:city":"Gieterveen",
    "sg:orig_category":"Pluimveebedrijven En -Handelaren",
    "sg:phone":"+31 599 648 223",
    "sg:postcode":"9511 PJ",
    "sg:province":"Provincie Drenthe",
    "wof:name":"Honijgro",
    "wof:placetype":"venue"
},
  "geometry": {"coordinates":[6.859931,53.026527],"type":"Point"}
}