{
  "type": "Feature",
  "properties": {
    "addr:full":"Kamperfoeliestraat 2 Nieuw Vennep Noord-Holland 2153 BG",
    "addr:housenumber":"2",
    "addr:postcode":"2153",
    "addr:street":"Kamperfoeliestraat;Nieuw Vennep",
    "iso:country":"NL",
    "sg:address":"Kamperfoeliestraat 2",
    "sg:city":"Nieuw Vennep",
    "sg:orig_category":"Autokeuringen",
    "sg:phone":"+31 252 672 798",
    "sg:postcode":"2153 BG",
    "sg:province":"Noord-Holland",
    "wof:name":"Pim Kennis Autocleaning",
    "wof:placetype":"venue"
},
  "geometry": {"coordinates":[4.636859,52.261017],"type":"Point"}
}