{
  "type": "Feature",
  "properties": {
    "addr:full":"Industriewg 16 Heemstede North Holland 2102 LH",
    "addr:housenumber":"16",
    "addr:postcode":"2102 lh",
    "addr:street":"Industriewg",
    "iso:country":"NL",
    "sg:address":"Industriewg 16",
    "sg:city":"Heemstede",
    "sg:orig_category":"Verpakkingsbedrijven",
    "sg:phone":"+31 23 547 1870",
    "sg:postcode":"2102 LH",
    "sg:province":"North Holland",
    "sg:website":"http://www.ipneurope.com",
    "wof:name":"Ipn Europe Bv",
    "wof:placetype":"venue"
},
  "geometry": {"coordinates":[4.62776,52.348068],"type":"Point"}
}