{
  "type": "Feature",
  "properties": {
    "addr:full":"Lindtsedk 241A Zwyndrecht South Holland 3336 LD",
    "addr:housenumber":"241a",
    "addr:postcode":"3336 ld",
    "iso:country":"NL",
    "sg:address":"Lindtsedk 241A",
    "sg:city":"Zwyndrecht",
    "sg:orig_category":"Honden- En Kattentrimsalons",
    "sg:phone":"+31 78 610 3440",
    "sg:postcode":"3336 LD",
    "sg:province":"South Holland",
    "wof:name":"Prima Hondentrimsalon",
    "wof:placetype":"venue"
},
  "geometry": {"coordinates":[4.60844,51.809719],"type":"Point"}
}