{
  "type": "Feature",
  "properties": {
    "addr:full":"Tiggeltsebergstr 25 Rysbergen Noord-Brabant 4891 TC",
    "addr:housenumber":"25",
    "addr:postcode":"4891 tc",
    "addr:street":"Tiggeltsebergstr",
    "iso:country":"NL",
    "sg:address":"Tiggeltsebergstr 25",
    "sg:city":"Rysbergen",
    "sg:orig_category":"Juridische Adviseurs",
    "sg:phone":"+31 76 596 8127",
    "sg:postcode":"4891 TC",
    "sg:province":"Noord-Brabant",
    "sg:website":"http://www.pbr-databank.demon.nl",
    "wof:name":"Pbr",
    "wof:placetype":"venue"
},
  "geometry": {"coordinates":[4.671754,51.52084],"type":"Point"}
}