{
  "type": "Feature",
  "properties": {
    "addr:full":"P Hellendaalstr 14 Spykenisse Zuid-Holland 3208 AP",
    "addr:housenumber":"14",
    "addr:postcode":"3208 ap",
    "addr:street":"P",
    "iso:country":"NL",
    "sg:address":"P Hellendaalstr 14",
    "sg:city":"Spykenisse",
    "sg:orig_category":"Woningstoffeerders",
    "sg:phone":"+31 181 643 955",
    "sg:postcode":"3208 AP",
    "sg:province":"Zuid-Holland",
    "wof:name":"Fht",
    "wof:placetype":"venue"
},
  "geometry": {"coordinates":[4.3115200996,51.8283309937],"type":"Point"}
}