{
  "type": "Feature",
  "properties": {
    "addr:full":"Emmalaan 602 Etten-Leur Noord-Brabant 4872 CH",
    "addr:housenumber":"602",
    "addr:postcode":"4872",
    "addr:street":"Emmalaan",
    "iso:country":"NL",
    "sg:address":"Emmalaan 602",
    "sg:city":"Etten-Leur",
    "sg:orig_category":"Huishoudapparatuur, Televisies And Radio'S",
    "sg:phone":"+31 76 502 2236",
    "sg:postcode":"4872 CH",
    "sg:province":"Noord-Brabant",
    "wof:name":"Ast",
    "wof:placetype":"venue"
},
  "geometry": {"coordinates":[4.648633,51.576965],"type":"Point"}
}