{
  "type": "Feature",
  "properties": {
    "addr:full":"Wiekerstraat 5 Rossum Ov NL.08 7596 NH",
    "addr:housenumber":"5",
    "addr:postcode":"7596 nh",
    "addr:street":"Wiekerstraat;Ov",
    "iso:country":"NL",
    "sg:address":"Wiekerstraat 5",
    "sg:city":"Rossum Ov",
    "sg:orig_category":"Kampeerterreinen",
    "sg:phone":"+31 541 625 287",
    "sg:postcode":"7596 NH",
    "sg:province":"NL.08",
    "wof:name":"Camping 'T Rikhof",
    "wof:placetype":"venue"
},
  "geometry": {"coordinates":[6.9319219589,52.3605995178],"type":"Point"}
}