{
  "type": "Feature",
  "properties": {
    "iso:country":"NL",
    "sg:address":"Industrieweg 4",
    "sg:city":"Mierlo",
    "sg:orig_category":"Boekhouders",
    "sg:phone":"+31 492 662 020",
    "sg:postcode":"5731 HR",
    "sg:province":"Noord-Brabant",
    "wof:name":"Fiscalex Mierlo Bv",
    "wof:placetype":"venue"
},
  "geometry": {"coordinates":[5.62537,51.447517],"type":"Point"}
}