{
  "type": "Feature",
  "properties": {
    "addr:full":"Postbus 699 Gouda Buenos Aires 2800 AR",
    "addr:housenumber":"699",
    "addr:postcode":"2800",
    "addr:street":"Postbus;Buenos Aires",
    "iso:country":"NL",
    "sg:address":"Postbus 699",
    "sg:city":"Gouda",
    "sg:orig_category":"Loodgieters",
    "sg:phone":"+31 182 689 238",
    "sg:postcode":"2800 AR",
    "sg:province":"Buenos Aires",
    "wof:name":"Schaefers",
    "wof:placetype":"venue"
},
  "geometry": {"coordinates":[-58.99535,-34.081829],"type":"Point"}
}