{
  "type": "Feature",
  "properties": {
    "addr:full":"Fabriciusln 34 Drachten Friesland 9203 LG",
    "addr:housenumber":"34",
    "addr:postcode":"9203 lg",
    "addr:street":"Fabriciusln",
    "iso:country":"NL",
    "sg:address":"Fabriciusln 34",
    "sg:city":"Drachten",
    "sg:orig_category":"Bedrijfshuisvesting",
    "sg:phone":"+31 512 512 017",
    "sg:postcode":"9203 LG",
    "sg:province":"Friesland",
    "wof:name":"Schroor, H J",
    "wof:placetype":"venue"
},
  "geometry": {"coordinates":[6.090426,53.09856],"type":"Point"}
}