{
  "type": "Feature",
  "properties": {
    "addr:full":"Burgemeester Aalberslaan 41 Krimpen A/D Ijssel Zuid-Holland 2922 BC",
    "addr:housenumber":"41;a / d",
    "addr:postcode":"2922 bc",
    "addr:street":"Burgemeester Aalberslaan",
    "iso:country":"NL",
    "sg:address":"Burgemeester Aalberslaan 41",
    "sg:city":"Krimpen A/D Ijssel",
    "sg:orig_category":"Overheidsdiensten",
    "sg:phone":"+31 180 515 126",
    "sg:postcode":"2922 BC",
    "sg:province":"Zuid-Holland",
    "wof:name":"De Ark",
    "wof:placetype":"venue"
},
  "geometry": {"coordinates":[4.5932860374,51.916519165],"type":"Point"}
}