{
  "type": "Feature",
  "properties": {
    "addr:full":"Koninginnegr 81 S Gravenhage South Holland 2514 AJ",
    "addr:housenumber":"81",
    "addr:postcode":"2514 aj",
    "addr:street":"Koninginnegr;S Gravenhage",
    "iso:country":"NL",
    "sg:address":"Koninginnegr 81",
    "sg:city":"S Gravenhage",
    "sg:orig_category":"Waterbehandeling En Waterzuiverings- Systemen",
    "sg:phone":"+31 70 338 7047",
    "sg:postcode":"2514 AJ",
    "sg:province":"South Holland",
    "wof:name":"Holland Waterfiltration Syst Bv",
    "wof:placetype":"venue"
},
  "geometry": {"coordinates":[4.3093500137,52.084148407],"type":"Point"}
}