{
  "type": "Feature",
  "properties": {
    "addr:full":"Lysterstr 1 Den Helder Noord-Holland 1781 WC",
    "addr:housenumber":"1",
    "addr:postcode":"1781 wc",
    "addr:street":"Lysterstr",
    "iso:country":"NL",
    "sg:address":"Lysterstr 1",
    "sg:city":"Den Helder",
    "sg:orig_category":"Scholen Voor Basisonderwijs",
    "sg:phone":"+31 223 619 447",
    "sg:postcode":"1781 WC",
    "sg:province":"Noord-Holland",
    "wof:name":"Eben Ha?zer Prot Chr",
    "wof:placetype":"venue"
},
  "geometry": {"coordinates":[4.771291,52.952103],"type":"Point"}
}