{
  "type": "Feature",
  "properties": {
    "addr:full":"Helmstr 16C Maastricht Limburg 6211 TA",
    "addr:housenumber":"16c",
    "addr:postcode":"6211 ta",
    "addr:street":"Helmstr",
    "iso:country":"NL",
    "sg:address":"Helmstr 16C",
    "sg:city":"Maastricht",
    "sg:orig_category":"Adviesbureaus Bedrijfsorganisatie",
    "sg:phone":"+31 43 327 0163",
    "sg:postcode":"6211 TA",
    "sg:province":"Limburg",
    "sg:website":"http://www.pentascope.nl",
    "wof:name":"Penta Scope Zuid",
    "wof:placetype":"venue"
},
  "geometry": {"coordinates":[5.688879,50.849937],"type":"Point"}
}