{
  "type": "Feature",
  "properties": {
    "addr:full":"Raadhuisstr 35 Moergestel Noord-Brabant 5066 AP",
    "addr:housenumber":"35",
    "addr:postcode":"5066 ap",
    "addr:street":"Raadhuisstr",
    "iso:country":"NL",
    "sg:address":"Raadhuisstr 35",
    "sg:city":"Moergestel",
    "sg:orig_category":"Adviesbureaus Bedrijfsorganisatie",
    "sg:phone":"+31 13 513 6220",
    "sg:postcode":"5066 AP",
    "sg:province":"Noord-Brabant",
    "wof:name":"Mextone Cons Bv",
    "wof:placetype":"venue"
},
  "geometry": {"coordinates":[5.1861,51.545761],"type":"Point"}
}