{
  "type": "Feature",
  "properties": {
    "iso:country":"NL",
    "sg:address":"Sint Janstraat 58",
    "sg:city":"Hoeven",
    "sg:orig_category":"Autokeuringen",
    "sg:phone":"+31 165 502 429",
    "sg:postcode":"4741 AR",
    "sg:province":"Catamarca",
    "wof:name":"A.J. Wagemakers En Zonen",
    "wof:placetype":"venue"
},
  "geometry": {"coordinates":[-66.172859,-27.607229],"type":"Point"}
}