{
  "type": "Feature",
  "properties": {
    "addr:full":"St P Canisiusln 50 Eindhoven Noord-Brabant 5643 WG",
    "addr:housenumber":"50",
    "addr:postcode":"5643 wg",
    "addr:street":"St;Canisiusln",
    "iso:country":"NL",
    "sg:address":"St P Canisiusln 50",
    "sg:city":"Eindhoven",
    "sg:orig_category":"Honden- En Kattentrimsalons",
    "sg:phone":"+31 40 211 2210",
    "sg:postcode":"5643 WG",
    "sg:province":"Noord-Brabant",
    "wof:name":"Hondenkapper",
    "wof:placetype":"venue"
},
  "geometry": {"coordinates":[5.509216,51.428562],"type":"Point"}
}