{
  "type": "Feature",
  "properties": {
    "iso:country":"NL",
    "sg:address":"Van Miereveltstraat 176",
    "sg:city":"'S Gravenhage",
    "sg:orig_category":"Boekhouders",
    "sg:phone":"+31 70 402 3492",
    "sg:postcode":"2525 EJ",
    "sg:province":"South Holland",
    "wof:name":"Administratiekantoor F. Gurel",
    "wof:placetype":"venue"
},
  "geometry": {"coordinates":[4.298965,52.065685],"type":"Point"}
}