{
  "type": "Feature",
  "properties": {
    "addr:full":"Kleiweg 57 Gouda Zuid-Holland 2801 GC",
    "addr:housenumber":"57",
    "addr:postcode":"2801 gc",
    "addr:street":"Kleiweg",
    "iso:country":"NL",
    "sg:address":"Kleiweg 57",
    "sg:city":"Gouda",
    "sg:orig_category":"Damesmodezaken",
    "sg:phone":"+31 182 512 038",
    "sg:postcode":"2801 GC",
    "sg:province":"Zuid-Holland",
    "wof:name":"Modehuis Schocon Bv",
    "wof:placetype":"venue"
},
  "geometry": {"coordinates":[4.709773,52.014],"type":"Point"}
}