{
  "type": "Feature",
  "properties": {
    "iso:country":"NL",
    "sg:address":"Neptunusstraat 67",
    "sg:city":"Wieringerwerf",
    "sg:orig_category":"Kappers",
    "sg:phone":"+31 227 602 449",
    "sg:postcode":"1771 BT",
    "sg:province":"Noord-Holland",
    "wof:name":"J. Kluin Bolhuis",
    "wof:placetype":"venue"
},
  "geometry": {"coordinates":[5.0337409973,52.8506088257],"type":"Point"}
}