{
  "type": "Feature",
  "properties": {
    "addr:full":"Keesomstr 517 Zandvoort North Holland 2041 XV",
    "addr:housenumber":"517",
    "addr:postcode":"2041 xv",
    "addr:street":"Zandvoort North",
    "iso:country":"NL",
    "sg:address":"Keesomstr 517",
    "sg:city":"Zandvoort",
    "sg:orig_category":"Autopoetsbedrijven",
    "sg:phone":"+31 23 573 0364",
    "sg:postcode":"2041 XV",
    "sg:province":"North Holland",
    "wof:name":"Ftc",
    "wof:placetype":"venue"
},
  "geometry": {"coordinates":[4.555997,52.379639],"type":"Point"}
}