{
  "type": "Feature",
  "properties": {
    "addr:full":"Talmastraat 2 Hoogezand Groningen 9602 GX",
    "addr:housenumber":"2",
    "addr:postcode":"9602 gx",
    "addr:street":"Talmastraat",
    "iso:country":"NL",
    "sg:address":"Talmastraat 2",
    "sg:city":"Hoogezand",
    "sg:classifiers":[
        {
            "category":"Education",
            "subcategory":"Preschool",
            "type":"Public Place"
        }
    ],
    "sg:phone":"+31 598 321 574",
    "sg:postcode":"9602 GX",
    "sg:province":"Groningen",
    "sg:tags":[
        "kleuteronderwijs",
        "basis-"
    ],
    "wof:name":"Basisschool Sint Gerardus Majella",
    "wof:placetype":"venue"
},
  "geometry": {"coordinates":[6.744103,53.154144],"type":"Point"}
}