{
  "type": "Feature",
  "properties": {
    "addr:full":"Scheperstr 145 Epe Gelderland 8162 WP",
    "addr:housenumber":"145",
    "addr:postcode":"8162 wp",
    "addr:street":"Gelderland",
    "iso:country":"NL",
    "sg:address":"Scheperstr 145",
    "sg:city":"Epe",
    "sg:orig_category":"Bejaarden - Verzorgingstehuizen",
    "sg:phone":"+31 578 614 933",
    "sg:postcode":"8162 WP",
    "sg:province":"Gelderland",
    "wof:name":"Klaarbeek, De",
    "wof:placetype":"venue"
},
  "geometry": {"coordinates":[5.978653,52.341602],"type":"Point"}
}