{
  "type": "Feature",
  "properties": {
    "iso:country":"NL",
    "sg:address":"Groentewg 24",
    "sg:city":"S Gravenhage",
    "sg:orig_category":"Fotoreportages",
    "sg:phone":"+31 70 380 4634",
    "sg:postcode":"2525 JS",
    "sg:province":"Zuid-Holland",
    "sg:website":"http://www.vhbfoto.nl",
    "wof:name":"Badeloe, Henry",
    "wof:placetype":"venue"
},
  "geometry": {"coordinates":[4.30248,52.062462],"type":"Point"}
}