{
  "type": "Feature",
  "properties": {
    "addr:full":"Polonaisestraat 20 Almere Flevoland 1326 RS",
    "addr:housenumber":"20",
    "addr:postcode":"1326 rs",
    "addr:street":"Polonaisestraat;Flevoland",
    "iso:country":"NL",
    "sg:address":"Polonaisestraat 20",
    "sg:city":"Almere",
    "sg:orig_category":"Geluidsopnamen",
    "sg:phone":"+31 36 523 1105",
    "sg:postcode":"1326 RS",
    "sg:province":"Flevoland",
    "wof:name":"J.M.P.M. Baggen",
    "wof:placetype":"venue"
},
  "geometry": {"coordinates":[5.256659,52.361198],"type":"Point"}
}