{
  "type": "Feature",
  "properties": {
    "addr:full":"Wynstr 140 Dordrecht Zuid-Holland 3311 BZ",
    "addr:housenumber":"140",
    "addr:postcode":"3311 bz",
    "iso:country":"NL",
    "sg:address":"Wynstr 140",
    "sg:city":"Dordrecht",
    "sg:orig_category":"Antiquiteiten",
    "sg:phone":"+31 78 613 3104",
    "sg:postcode":"3311 BZ",
    "sg:province":"Zuid-Holland",
    "wof:name":"Beaumont",
    "wof:placetype":"venue"
},
  "geometry": {"coordinates":[4.656506,51.811916],"type":"Point"}
}