{
  "type": "Feature",
  "properties": {
    "addr:full":"Parallelwg 104B Beverwyk New Mexico 1948 NM",
    "addr:housenumber":"104b;1948",
    "addr:street":"Beverwyk",
    "iso:country":"NL",
    "sg:address":"Parallelwg 104B",
    "sg:city":"Beverwyk",
    "sg:orig_category":"Woninginrichting",
    "sg:phone":"+31 251 223 330",
    "sg:postcode":"1948 NM",
    "sg:province":"New Mexico",
    "wof:name":"Home Plaza",
    "wof:placetype":"venue"
},
  "geometry": {"coordinates":[-106.0261230469,34.1661605835],"type":"Point"}
}