{
  "type": "Feature",
  "properties": {
    "addr:full":"Alsteedsewg 73 Haaksbergen NL.08 7481 RT",
    "addr:housenumber":"73;nl.08",
    "addr:postcode":"7481 rt",
    "addr:street":"Alsteedsewg",
    "iso:country":"NL",
    "sg:address":"Alsteedsewg 73",
    "sg:city":"Haaksbergen",
    "sg:orig_category":"Vakantieverblijven",
    "sg:phone":"+31 53 569 6234",
    "sg:postcode":"7481 RT",
    "sg:province":"NL.08",
    "wof:name":"Broam, Den",
    "wof:placetype":"venue"
},
  "geometry": {"coordinates":[6.853617,52.136303],"type":"Point"}
}