{
  "type": "Feature",
  "properties": {
    "iso:country":"NL",
    "sg:address":"Ringersstr 10",
    "sg:city":"Schiedam",
    "sg:orig_category":"Bakkerijbenodigdheden En -Grondstoffen",
    "sg:phone":"+31 10 437 2033",
    "sg:postcode":"3125 BP",
    "sg:province":"Zuid-Holland",
    "wof:name":"Civoba Vof",
    "wof:placetype":"venue"
},
  "geometry": {"coordinates":[4.405642,51.933243],"type":"Point"}
}