{
  "type": "Feature",
  "properties": {
    "addr:full":"Roosbergsewg 9 Bavel North Brabant 4854 PL",
    "addr:housenumber":"9",
    "addr:postcode":"4854 pl",
    "addr:street":"Roosbergsewg",
    "iso:country":"NL",
    "sg:address":"Roosbergsewg 9",
    "sg:city":"Bavel",
    "sg:classifiers":[
        {
            "category":"Food & Beverages",
            "subcategory":"Fruits & Vegetables",
            "type":"Retail Goods"
        }
    ],
    "sg:phone":"+31 161 431 537",
    "sg:postcode":"4854 PL",
    "sg:province":"North Brabant",
    "sg:tags":[
        "en",
        "groenten"
    ],
    "wof:name":"Bastiaansen, A",
    "wof:placetype":"venue"
},
  "geometry": {"coordinates":[4.835006,51.557533],"type":"Point"}
}