{
  "type": "Feature",
  "properties": {
    "addr:full":"Enthovensewg 8 Tilburg North Brabant 5017 JP",
    "addr:housenumber":"8",
    "addr:postcode":"5017 jp",
    "addr:street":"Enthovensewg",
    "iso:country":"NL",
    "sg:address":"Enthovensewg 8",
    "sg:city":"Tilburg",
    "sg:orig_category":"Psychologen",
    "sg:phone":"+31 13 543 8625",
    "sg:postcode":"5017 JP",
    "sg:province":"North Brabant",
    "wof:name":"Kuijk, Mevr Drs M M L Van",
    "wof:placetype":"venue"
},
  "geometry": {"coordinates":[5.101696,51.560154],"type":"Point"}
}