{
  "type": "Feature",
  "properties": {
    "addr:full":"Amstelkade 92 Amsterdam North Holland 1078 AN",
    "addr:housenumber":"92",
    "addr:postcode":"1078 an",
    "addr:street":"Amstelkade",
    "iso:country":"NL",
    "sg:address":"Amstelkade 92",
    "sg:city":"Amsterdam",
    "sg:orig_category":"Onderhoud And Reparatie Kantoorapparatuur",
    "sg:phone":"+31 6 51235411",
    "sg:postcode":"1078 AN",
    "sg:province":"North Holland",
    "wof:name":"Zimmer West-East Trading",
    "wof:placetype":"venue"
},
  "geometry": {"coordinates":[4.897154,52.347748],"type":"Point"}
}