{
  "type": "Feature",
  "properties": {
    "addr:full":"Schoener 4434 Lelystad NL. 8243 XH",
    "addr:postcode":"4434;8243 xh",
    "addr:street":"Schoener;Nl.",
    "iso:country":"NL",
    "sg:address":"Schoener 4434",
    "sg:city":"Lelystad",
    "sg:orig_category":"Glazenwasserijen",
    "sg:phone":"+31 320 242 874",
    "sg:postcode":"8243 XH",
    "sg:province":"NL.",
    "wof:name":"Thuis & Zoon, S M B",
    "wof:placetype":"venue"
},
  "geometry": {"coordinates":[5.458625,52.498344],"type":"Point"}
}