{
  "type": "Feature",
  "properties": {
    "addr:full":"Balistr 16 Hengelo Ov NL.08 7556 AJ",
    "addr:housenumber":"16",
    "addr:postcode":"7556 aj",
    "addr:street":"Balistr;Ov",
    "iso:country":"NL",
    "sg:address":"Balistr 16",
    "sg:city":"Hengelo Ov",
    "sg:orig_category":"Homeopathie",
    "sg:phone":"+31 74 259 0870",
    "sg:postcode":"7556 AJ",
    "sg:province":"NL.08",
    "wof:name":"Gemmert, Gerri Van",
    "wof:placetype":"venue"
},
  "geometry": {"coordinates":[6.783801,52.269505],"type":"Point"}
}