{
  "type": "Feature",
  "properties": {
    "addr:full":"Koekoekslaan 32 Schiedam Zuid-Holland 3121 XK",
    "addr:housenumber":"32",
    "addr:postcode":"3121 xk",
    "addr:street":"Koekoekslaan",
    "iso:country":"NL",
    "sg:address":"Koekoekslaan 32",
    "sg:city":"Schiedam",
    "sg:orig_category":"Huizensloop And Bouwrijp Maken",
    "sg:phone":"+31 10 471 6352",
    "sg:postcode":"3121 XK",
    "sg:province":"Zuid-Holland",
    "wof:name":"M.C. Van Schie",
    "wof:placetype":"venue"
},
  "geometry": {"coordinates":[4.382055,51.934898],"type":"Point"}
}