{
  "type": "Feature",
  "properties": {
    "addr:full":"Thomsonlaan 114 'S Gravenhage Zuid-Holland 2565 JG",
    "addr:housenumber":"114 '",
    "addr:postcode":"2565 jg",
    "addr:street":"Thomsonlaan",
    "iso:country":"NL",
    "sg:address":"Thomsonlaan 114",
    "sg:city":"'S Gravenhage",
    "sg:orig_category":"Granen, Zaden And Diervoeders Gh",
    "sg:phone":"+31 70 345 0306",
    "sg:postcode":"2565 JG",
    "sg:province":"Zuid-Holland",
    "wof:name":"Vof Vogel & Zaadhand Joh Zandvliet",
    "wof:placetype":"venue"
},
  "geometry": {"coordinates":[4.2681,52.078182],"type":"Point"}
}