{
  "type": "Feature",
  "properties": {
    "addr:full":"J Buziaustr 14 Hengelo Ov NL.08 7558 LA",
    "addr:housenumber":"14;7558",
    "addr:street":"Ov;La",
    "iso:country":"NL",
    "sg:address":"J Buziaustr 14",
    "sg:city":"Hengelo Ov",
    "sg:orig_category":"Scholen Voor Basisonderwijs",
    "sg:phone":"+31 74 278 0775",
    "sg:postcode":"7558 LA",
    "sg:province":"NL.08",
    "sg:website":"http://www.eimink.nl",
    "wof:name":"Eimink Kath, 'T",
    "wof:placetype":"venue"
},
  "geometry": {"coordinates":[6.830825,52.287441],"type":"Point"}
}