{
  "type": "Feature",
  "properties": {
    "addr:full":"Laurens Kosterplein 8 Tilburg North Brabant 5025 EC",
    "addr:housenumber":"8",
    "addr:postcode":"5025 ec",
    "addr:street":"Laurens Kosterplein",
    "iso:country":"NL",
    "sg:address":"Laurens Kosterplein 8",
    "sg:city":"Tilburg",
    "sg:orig_category":"Overheidsdiensten",
    "sg:phone":"+31 13 543 0919",
    "sg:postcode":"5025 EC",
    "sg:province":"North Brabant",
    "wof:name":"De Vleugel",
    "wof:placetype":"venue"
},
  "geometry": {"coordinates":[5.0746059418,51.5477981567],"type":"Point"}
}