{
  "type": "Feature",
  "properties": {
    "addr:full":"Westhaven 73 Gouda Zuid-Holland 2801 PN",
    "addr:housenumber":"73",
    "addr:postcode":"2801 pn",
    "addr:street":"Westhaven",
    "iso:country":"NL",
    "sg:address":"Westhaven 73",
    "sg:city":"Gouda",
    "sg:orig_category":"Administratie- En Boekhoudkantoren",
    "sg:phone":"+31 182 582 982",
    "sg:postcode":"2801 PN",
    "sg:province":"Zuid-Holland",
    "wof:name":"Delta Support Gouda",
    "wof:placetype":"venue"
},
  "geometry": {"coordinates":[4.713319,52.007557],"type":"Point"}
}