{
  "type": "Feature",
  "properties": {
    "iso:country":"NL",
    "sg:address":"Voorsterwg 1",
    "sg:city":"Loenen Gld",
    "sg:orig_category":"Scholen Voor Basisonderwijs",
    "sg:phone":"+31 55 505 1222",
    "sg:postcode":"7371 GA",
    "sg:province":"Gelderland",
    "wof:name":"Aventurijn",
    "wof:placetype":"venue"
},
  "geometry": {"coordinates":[6.038328,52.131939],"type":"Point"}
}