{
  "type": "Feature",
  "properties": {
    "addr:full":"Transportbaan 1 Winschoten Groningen 9672 BJ",
    "addr:housenumber":"1",
    "addr:postcode":"9672 bj",
    "addr:street":"Transportbaan",
    "iso:country":"NL",
    "sg:address":"Transportbaan 1",
    "sg:city":"Winschoten",
    "sg:classifiers":[
        {
            "category":"Professional",
            "type":"Services"
        }
    ],
    "sg:phone":"+31 597 430 144",
    "sg:postcode":"9672 BJ",
    "sg:province":"Groningen",
    "sg:tags":[
        "leasing"
    ],
    "wof:name":"Travel",
    "wof:placetype":"venue"
},
  "geometry": {"coordinates":[7.045977,53.145721],"type":"Point"}
}