{
  "type": "Feature",
  "properties": {
    "addr:full":"Westerkade 15 Groningen Groningen 9718 AS",
    "addr:housenumber":"15",
    "addr:postcode":"9718 as",
    "addr:street":"Westerkade",
    "iso:country":"NL",
    "sg:address":"Westerkade 15",
    "sg:city":"Groningen",
    "sg:orig_category":"Film-, Tv- And Videoproductie",
    "sg:phone":"+31 50 579 1084",
    "sg:postcode":"9718 AS",
    "sg:province":"Groningen",
    "wof:name":"Pavlov Media",
    "wof:placetype":"venue"
},
  "geometry": {"coordinates":[6.557541,53.215096],"type":"Point"}
}