{
  "type": "Feature",
  "properties": {
    "iso:country":"NL",
    "sg:address":"Bisschopweg 82",
    "sg:city":"Lunteren",
    "sg:orig_category":"Koeriersdiensten",
    "sg:phone":"+31 6 53933772",
    "sg:postcode":"6741 XC",
    "sg:province":"Gelderland",
    "wof:name":"Pater Koeriers & Sneltransport",
    "wof:placetype":"venue"
},
  "geometry": {"coordinates":[5.612989,52.091824],"type":"Point"}
}