{
  "type": "Feature",
  "properties": {
    "addr:full":"Platenmakersstraat 2 Nijmegen Gelderland 6511 TZ",
    "addr:housenumber":"2",
    "addr:postcode":"6511 tz",
    "addr:street":"Platenmakersstraat;Gelderland",
    "iso:country":"NL",
    "sg:address":"Platenmakersstraat 2",
    "sg:city":"Nijmegen",
    "sg:classifiers":[
        {
            "category":"Fast Food",
            "type":"Food & Drink"
        }
    ],
    "sg:phone":"+31 24 323 3870",
    "sg:postcode":"6511 TZ",
    "sg:province":"Gelderland",
    "sg:tags":[
        "afhaal",
        "restaurant"
    ],
    "wof:name":"Grillroom Fean",
    "wof:placetype":"venue"
},
  "geometry": {"coordinates":[5.865173,51.847748],"type":"Point"}
}