{
  "type": "Feature",
  "properties": {
    "addr:full":"Ridderstraat 19 Breda Noord-Brabant 4811 JA",
    "addr:housenumber":"19",
    "addr:postcode":"4811 ja",
    "addr:street":"Ridderstraat",
    "iso:country":"NL",
    "sg:address":"Ridderstraat 19",
    "sg:city":"Breda",
    "sg:orig_category":"Damesmodezaken",
    "sg:phone":"+31 76 521 7446",
    "sg:postcode":"4811 JA",
    "sg:province":"Noord-Brabant",
    "wof:name":"Paddy Point T.H.O.D.N. Bistro De Tricot",
    "wof:placetype":"venue"
},
  "geometry": {"coordinates":[4.776348,51.587307],"type":"Point"}
}