{
  "type": "Feature",
  "properties": {
    "addr:full":"Hummelosewg 16 Zelhem Gelderland 7021 AE",
    "addr:housenumber":"16",
    "addr:postcode":"7021 ae",
    "addr:street":"Hummelosewg;Gelderland",
    "iso:country":"NL",
    "sg:address":"Hummelosewg 16",
    "sg:city":"Zelhem",
    "sg:orig_category":"Architecten En Architectenbureaus",
    "sg:phone":"+31 314 624 348",
    "sg:postcode":"7021 AE",
    "sg:province":"Gelderland",
    "wof:name":"Gelderland Bv",
    "wof:placetype":"venue"
},
  "geometry": {"coordinates":[6.34121,52.006348],"type":"Point"}
}