{
  "type": "Feature",
  "properties": {
    "addr:full":"Kerkwg 73 Puth Limburg 6155 KK",
    "addr:housenumber":"73",
    "addr:postcode":"6155 kk",
    "addr:street":"Kerkwg",
    "iso:country":"NL",
    "sg:address":"Kerkwg 73",
    "sg:city":"Puth",
    "sg:orig_category":"Wijnkoperijen En -Groothandel",
    "sg:phone":"+31 46 443 8090",
    "sg:postcode":"6155 KK",
    "sg:province":"Limburg",
    "sg:website":"http://www.gvfdebourgogne.nl",
    "wof:name":"Gvf De Bourgogne",
    "wof:placetype":"venue"
},
  "geometry": {"coordinates":[5.8735060692,50.9504241943],"type":"Point"}
}