{
  "type": "Feature",
  "properties": {
    "addr:full":"Boekweitskorrel 9 Laren Nh North Holland 1251 ZH",
    "addr:housenumber":"9",
    "addr:postcode":"1251 zh",
    "addr:street":"Boekweitskorrel;Nh North",
    "iso:country":"NL",
    "sg:address":"Boekweitskorrel 9",
    "sg:city":"Laren Nh",
    "sg:orig_category":"Fietsen En Bromfietsen Onderdelen - Fabr. En Grooth",
    "sg:phone":"+31 35 538 9504",
    "sg:postcode":"1251 ZH",
    "sg:province":"North Holland",
    "wof:name":"Superspark",
    "wof:placetype":"venue"
},
  "geometry": {"coordinates":[5.225382,52.252426],"type":"Point"}
}