{
  "type": "Feature",
  "properties": {
    "addr:full":"Parallelwg 16 Neede Gelderland 7161 AG",
    "addr:housenumber":"16",
    "addr:postcode":"7161",
    "addr:street":"Parallelwg;Gelderland",
    "iso:country":"NL",
    "sg:address":"Parallelwg 16",
    "sg:city":"Neede",
    "sg:orig_category":"Geluidsinstallaties - Verhuur",
    "sg:phone":"+31 545 291 658",
    "sg:postcode":"7161 AG",
    "sg:province":"Gelderland",
    "wof:name":"Temmink",
    "wof:placetype":"venue"
},
  "geometry": {"coordinates":[-121.31706200000001,38.299633],"type":"Point"}
}