{
  "type": "Feature",
  "properties": {
    "addr:full":"Barrevoetestr 2-3 Haarlem Noord-Holland 2011 WP",
    "addr:housenumber":"2-3",
    "addr:postcode":"2011 wp",
    "addr:street":"Barrevoetestr",
    "iso:country":"NL",
    "sg:address":"Barrevoetestr 2-3",
    "sg:city":"Haarlem",
    "sg:orig_category":"Antiquiteiten",
    "sg:phone":"+31 23 531 4378",
    "sg:postcode":"2011 WP",
    "sg:province":"Noord-Holland",
    "wof:name":"Roon, Van",
    "wof:placetype":"venue"
},
  "geometry": {"coordinates":[4.629606,52.380032],"type":"Point"}
}