{
  "type": "Feature",
  "properties": {
    "iso:country":"NL",
    "sg:address":"Hoefstr 175",
    "sg:city":"Tilburg",
    "sg:orig_category":"Verenigingsgebouwen",
    "sg:phone":"+31 13 543 5909",
    "sg:postcode":"5014 NK",
    "sg:province":"North Brabant",
    "wof:name":"Baselaer, De",
    "wof:placetype":"venue"
},
  "geometry": {"coordinates":[5.090909,51.570599],"type":"Point"}
}