{
  "type": "Feature",
  "properties": {
    "addr:full":"Hof V Parma 7 Doetinchem Gelderland 7007 KK",
    "addr:housenumber":"7",
    "addr:postcode":"7007 kk",
    "addr:street":"Parma;Gelderland",
    "iso:country":"NL",
    "sg:address":"Hof V Parma 7",
    "sg:city":"Doetinchem",
    "sg:orig_category":"Webdesign Bureaus",
    "sg:phone":"+31 314 323 767",
    "sg:postcode":"7007 KK",
    "sg:province":"Gelderland",
    "sg:website":"http://www.visionextendaz.nl",
    "wof:name":"Vision Extendaz",
    "wof:placetype":"venue"
},
  "geometry": {"coordinates":[6.2910552025,51.963596344],"type":"Point"}
}