{
  "type": "Feature",
  "properties": {
    "iso:country":"NL",
    "sg:address":"Postbus 7050 J H",
    "sg:city":"Leeuwarden",
    "sg:orig_category":"Verenigingen En Stichtingen",
    "sg:phone":"+31 58 213 3533",
    "sg:postcode":"8903 JB",
    "sg:province":"Provincie Friesland",
    "wof:name":"Knooppunt, 'T",
    "wof:placetype":"venue"
},
  "geometry": {"coordinates":[5.79143,53.203049],"type":"Point"}
}