{
  "type": "Feature",
  "properties": {
    "addr:full":"Fauna 13 Huizen Noord-Holland 1273 GV",
    "addr:housenumber":"13",
    "addr:postcode":"1273 gv",
    "addr:street":"Fauna",
    "iso:country":"NL",
    "sg:address":"Fauna 13",
    "sg:city":"Huizen",
    "sg:orig_category":"Homeopathie",
    "sg:phone":"+31 35 523 0824",
    "sg:postcode":"1273 GV",
    "sg:province":"Noord-Holland",
    "wof:name":"Dijkstra-Salda\u00b1A, A",
    "wof:placetype":"venue"
},
  "geometry": {"coordinates":[5.257578,52.297646],"type":"Point"}
}