{
  "type": "Feature",
  "properties": {
    "addr:full":"Saturnusstr 20 Ymuiden North Holland 1973 XG",
    "addr:housenumber":"20",
    "addr:postcode":"1973 xg",
    "addr:street":"Saturnusstr;North",
    "iso:country":"NL",
    "sg:address":"Saturnusstr 20",
    "sg:city":"Ymuiden",
    "sg:orig_category":"Onderhoudswerken",
    "sg:phone":"+31 6 10080679",
    "sg:postcode":"1973 XG",
    "sg:province":"North Holland",
    "wof:name":"Stet Onderhoudsbedrijf, W",
    "wof:placetype":"venue"
},
  "geometry": {"coordinates":[4.603524,52.454624],"type":"Point"}
}