{
  "type": "Feature",
  "properties": {
    "iso:country":"NL",
    "sg:address":"Spiegelgr 14-16",
    "sg:city":"Amsterdam",
    "sg:orig_category":"Galeries",
    "sg:phone":"+31 20 623 6538",
    "sg:postcode":"1017 JR",
    "sg:province":"Noord-Holland",
    "wof:name":"Hoopman",
    "wof:placetype":"venue"
},
  "geometry": {"coordinates":[4.88712,52.36245],"type":"Point"}
}