{
  "type": "Feature",
  "properties": {
    "addr:full":"Vriendschapspln 6 Schiedam South Holland 3117 NW",
    "addr:housenumber":"6",
    "addr:postcode":"3117 nw",
    "addr:street":"Vriendschapspln",
    "iso:country":"NL",
    "sg:address":"Vriendschapspln 6",
    "sg:city":"Schiedam",
    "sg:orig_category":"Onderhoudswerken",
    "sg:phone":"+31 10 246 7331",
    "sg:postcode":"3117 NW",
    "sg:province":"South Holland",
    "wof:name":"Soc",
    "wof:placetype":"venue"
},
  "geometry": {"coordinates":[4.392237,51.915768],"type":"Point"}
}