{
  "type": "Feature",
  "properties": {
    "addr:full":"Heyendaalsewg 192 Nymegen Gelderland 6525 SJ",
    "addr:housenumber":"192",
    "addr:postcode":"6525",
    "addr:street":"Nymegen Gelderland",
    "iso:country":"NL",
    "sg:address":"Heyendaalsewg 192",
    "sg:city":"Nymegen",
    "sg:orig_category":"Kappers",
    "sg:phone":"+31 24 355 1847",
    "sg:postcode":"6525 SJ",
    "sg:province":"Gelderland",
    "wof:name":"Leenders",
    "wof:placetype":"venue"
},
  "geometry": {"coordinates":[5.866784,51.815205],"type":"Point"}
}