{
  "type": "Feature",
  "properties": {
    "addr:full":"Tesselschadeln 2 Apeldoorn Gelderland 7314 LL",
    "addr:housenumber":"2",
    "addr:postcode":"7314 ll",
    "addr:street":"Tesselschadeln;Gelderland",
    "iso:country":"NL",
    "sg:address":"Tesselschadeln 2",
    "sg:city":"Apeldoorn",
    "sg:orig_category":"Kinderopvang",
    "sg:phone":"+31 55 355 5577",
    "sg:postcode":"7314 LL",
    "sg:province":"Gelderland",
    "wof:name":"Snoopy",
    "wof:placetype":"venue"
},
  "geometry": {"coordinates":[5.96566,52.216518],"type":"Point"}
}