{
  "type": "Feature",
  "properties": {
    "addr:full":"Hazelaarwg 48 Hengelo Ov Overijssel 7556 DP",
    "addr:housenumber":"48",
    "addr:postcode":"7556 dp",
    "addr:street":"Hazelaarwg;Ov",
    "iso:country":"NL",
    "sg:address":"Hazelaarwg 48",
    "sg:city":"Hengelo Ov",
    "sg:orig_category":"Wasserijen",
    "sg:phone":"+31 74 291 3281",
    "sg:postcode":"7556 DP",
    "sg:province":"Overijssel",
    "wof:name":"Rosink Wasserij, F",
    "wof:placetype":"venue"
},
  "geometry": {"coordinates":[6.7931919098,52.2724380493],"type":"Point"}
}