{
  "type": "Feature",
  "properties": {
    "addr:full":"Johanna Naber-Erf 320 Dordrecht Zuid-Holland 3315 HJ",
    "addr:housenumber":"320",
    "addr:postcode":"3315 hj",
    "addr:street":"Johanna Naber-Erf",
    "iso:country":"NL",
    "sg:address":"Johanna Naber-Erf 320",
    "sg:city":"Dordrecht",
    "sg:orig_category":"Schilderwerk",
    "sg:phone":"+31 78 617 2367",
    "sg:postcode":"3315 HJ",
    "sg:province":"Zuid-Holland",
    "wof:name":"Schildersbedrijf W Van Heeren En Zn",
    "wof:placetype":"venue"
},
  "geometry": {"coordinates":[4.734058,51.802509],"type":"Point"}
}