{
  "type": "Feature",
  "properties": {
    "iso:country":"NL",
    "sg:address":"Heimolen 56",
    "sg:city":"Bergen Op Zoom",
    "sg:orig_category":"Kampeerterreinen",
    "sg:phone":"+31 164 233 391",
    "sg:postcode":"4625 DD",
    "sg:province":"Noord-Brabant",
    "wof:name":"Kampeercentrum Uit En Thuis Bv",
    "wof:placetype":"venue"
},
  "geometry": {"coordinates":[4.3225951195,51.469127655],"type":"Point"}
}