{
  "type": "Feature",
  "properties": {
    "addr:full":"Heimolen 56 Bergen Op Zoom Noord-Brabant 4625 DD",
    "addr:housenumber":"56",
    "addr:postcode":"4625 dd",
    "addr:street":"Heimolen",
    "iso:country":"NL",
    "sg:address":"Heimolen 56",
    "sg:city":"Bergen Op Zoom",
    "sg:orig_category":"Kampeerterreinen",
    "sg:phone":"+31 164 233 391",
    "sg:postcode":"4625 DD",
    "sg:province":"Noord-Brabant",
    "wof:name":"Kampeercentrum Uit En Thuis Bv",
    "wof:placetype":"venue"
},
  "geometry": {"coordinates":[4.3225951195,51.469127655],"type":"Point"}
}