{
  "type": "Feature",
  "properties": {
    "addr:full":"Havenstraat 30 Numansdorp Zuid-Holland 3281 XE",
    "addr:housenumber":"30",
    "addr:postcode":"3281 xe",
    "addr:street":"Havenstraat",
    "iso:country":"NL",
    "sg:address":"Havenstraat 30",
    "sg:city":"Numansdorp",
    "sg:orig_category":"Fitnesscentra",
    "sg:phone":"+31 186 654 715",
    "sg:postcode":"3281 XE",
    "sg:province":"Zuid-Holland",
    "wof:name":"Highway Sport & Fitness Centre",
    "wof:placetype":"venue"
},
  "geometry": {"coordinates":[4.437267,51.728367],"type":"Point"}
}