{
  "type": "Feature",
  "properties": {
    "iso:country":"NL",
    "sg:address":"Boeier 217",
    "sg:city":"Lelystad",
    "sg:orig_category":"Administratie- En Boekhoudkantoren",
    "sg:phone":"+31 320 227 500",
    "sg:postcode":"8242 CD",
    "sg:province":"Flevoland",
    "wof:name":"Ebg",
    "wof:placetype":"venue"
},
  "geometry": {"coordinates":[5.446507,52.52071],"type":"Point"}
}