{
  "type": "Feature",
  "properties": {
    "addr:full":"Vyverhofstr 94-98 Rotterdam Zuid-Holland 3032 SP",
    "addr:housenumber":"94-98",
    "addr:postcode":"rotterdam;3032 sp",
    "iso:country":"NL",
    "sg:address":"Vyverhofstr 94-98",
    "sg:city":"Rotterdam",
    "sg:orig_category":"Schilders",
    "sg:phone":"+31 10 467 5511",
    "sg:postcode":"3032 SP",
    "sg:province":"Zuid-Holland",
    "wof:name":"Ijzerloo Rotterdam Bv, M J Van",
    "wof:placetype":"venue"
},
  "geometry": {"coordinates":[4.472939,51.931129],"type":"Point"}
}