{
  "type": "Feature",
  "properties": {
    "iso:country":"NL",
    "sg:address":"Hollantln 18-20",
    "sg:city":"Utrecht",
    "sg:orig_category":"Woninginrichting",
    "sg:phone":"+31 30 288 6742",
    "sg:postcode":"3526 AM",
    "sg:province":"Utrecht",
    "wof:name":"Leen Bakker",
    "wof:placetype":"venue"
},
  "geometry": {"coordinates":[5.103541851,52.0617980957],"type":"Point"}
}