{
  "type": "Feature",
  "properties": {
    "addr:full":"Berlicumsewg 12 Rosmalen Noord-Brabant 5248 NT",
    "addr:housenumber":"12",
    "addr:postcode":"5248 nt",
    "addr:street":"Berlicumsewg",
    "iso:country":"NL",
    "sg:address":"Berlicumsewg 12",
    "sg:city":"Rosmalen",
    "sg:orig_category":"Adviesbureaus Personeel",
    "sg:phone":"+31 73 523 1270",
    "sg:postcode":"5248 NT",
    "sg:province":"Noord-Brabant",
    "sg:website":"http://www.castorfibergroep.nl",
    "wof:name":"Castor Fiber Groep",
    "wof:placetype":"venue"
},
  "geometry": {"coordinates":[5.368124,51.698578],"type":"Point"}
}