{
  "type": "Feature",
  "properties": {
    "addr:full":"Edisonstr 67 Roosendaal North Brabant 4702 NB",
    "addr:housenumber":"67",
    "addr:postcode":"4702 nb",
    "addr:street":"Edisonstr",
    "iso:country":"NL",
    "sg:address":"Edisonstr 67",
    "sg:city":"Roosendaal",
    "sg:orig_category":"Keukens",
    "sg:phone":"+31 165 547 038",
    "sg:postcode":"4702 NB",
    "sg:province":"North Brabant",
    "wof:name":"Bogers",
    "wof:placetype":"venue"
},
  "geometry": {"coordinates":[4.48097,51.539593],"type":"Point"}
}