{
  "type": "Feature",
  "properties": {
    "addr:full":"Noorderstr 200 Sappemeer Groningen 9611 AR",
    "addr:housenumber":"200",
    "addr:postcode":"9611",
    "iso:country":"NL",
    "sg:address":"Noorderstr 200",
    "sg:city":"Sappemeer",
    "sg:orig_category":"Kappers",
    "sg:phone":"+31 598 391 818",
    "sg:postcode":"9611 AR",
    "sg:province":"Groningen",
    "wof:name":"Haarmode Sappemeer",
    "wof:placetype":"venue"
},
  "geometry": {"coordinates":[6.7872800827,53.1639518738],"type":"Point"}
}