{
  "type": "Feature",
  "properties": {
    "addr:full":"Hoofdweg 137 Schildwolde Groningen 9626 AC",
    "addr:housenumber":"137",
    "addr:postcode":"9626 ac",
    "addr:street":"Hoofdweg",
    "iso:country":"NL",
    "sg:address":"Hoofdweg 137",
    "sg:city":"Schildwolde",
    "sg:orig_category":"Goederenvervoer Over De Weg",
    "sg:phone":"+31 598 421 653",
    "sg:postcode":"9626 AC",
    "sg:province":"Groningen",
    "wof:name":"B F Snijder",
    "wof:placetype":"venue"
},
  "geometry": {"coordinates":[6.817621,53.233715],"type":"Point"}
}