{
  "type": "Feature",
  "properties": {
    "addr:full":"Banckertstr 36 Helmond Noord-Brabant 5703 BM",
    "addr:housenumber":"36",
    "addr:postcode":"5703 bm",
    "addr:street":"Banckertstr",
    "iso:country":"NL",
    "sg:address":"Banckertstr 36",
    "sg:city":"Helmond",
    "sg:classifiers":[
        {
            "category":"Personal",
            "subcategory":"Nail Salon",
            "type":"Services"
        }
    ],
    "sg:phone":"+31 492 543 521",
    "sg:postcode":"5703 BM",
    "sg:province":"Noord-Brabant",
    "sg:tags":[
        "pedicure"
    ],
    "wof:name":"Weerts-Van Hoof",
    "wof:placetype":"venue"
},
  "geometry": {"coordinates":[5.685599,51.474876],"type":"Point"}
}