{
  "type": "Feature",
  "properties": {
    "addr:full":"Van Wassenaerplein 1 Ter Aar South Holland 2461 RN",
    "addr:housenumber":"1",
    "addr:postcode":"2461 rn",
    "addr:street":"Van Wassenaerplein",
    "iso:country":"NL",
    "sg:address":"Van Wassenaerplein 1",
    "sg:city":"Ter Aar",
    "sg:orig_category":"Fruit And Groenten Gh",
    "sg:phone":"+31 172 603 136",
    "sg:postcode":"2461 RN",
    "sg:province":"South Holland",
    "wof:name":"G.W. Van Lammeren",
    "wof:placetype":"venue"
},
  "geometry": {"coordinates":[4.70642,52.167164],"type":"Point"}
}