{
  "type": "Feature",
  "properties": {
    "addr:full":"Postweg 9 Oldenzaal Overijssel 7574 PD",
    "addr:housenumber":"9",
    "addr:postcode":"7574 pd",
    "addr:street":"Postweg",
    "iso:country":"NL",
    "sg:address":"Postweg 9",
    "sg:city":"Oldenzaal",
    "sg:orig_category":"Loodgieterswerk, Verwarming And Sanitaire Installaties",
    "sg:phone":"+31 541 533 772",
    "sg:postcode":"7574 PD",
    "sg:province":"Overijssel",
    "wof:name":"A.H.M. Wekking",
    "wof:placetype":"venue"
},
  "geometry": {"coordinates":[6.935998,52.289852],"type":"Point"}
}