{
  "type": "Feature",
  "properties": {
    "addr:full":"Scheepmakerstraat 23 Katwijk Zh Zuid-Holland 2222 AB",
    "addr:housenumber":"23",
    "addr:postcode":"2222 ab",
    "addr:street":"Scheepmakerstraat",
    "iso:country":"NL",
    "sg:address":"Scheepmakerstraat 23",
    "sg:city":"Katwijk Zh",
    "sg:orig_category":"Houten Verpakkingen Fab",
    "sg:phone":"+31 71 402 2683",
    "sg:postcode":"2222 AB",
    "sg:province":"Zuid-Holland",
    "wof:name":"Rijnlandse Vatenhandel Bv",
    "wof:placetype":"venue"
},
  "geometry": {"coordinates":[4.431223,52.198727],"type":"Point"}
}