{
  "type": "Feature",
  "properties": {
    "addr:full":"Dorpsstraat 58 Chaam North Brabant 4861 AD",
    "addr:housenumber":"58",
    "addr:postcode":"4861 ad",
    "addr:street":"Dorpsstraat",
    "iso:country":"NL",
    "sg:address":"Dorpsstraat 58",
    "sg:city":"Chaam",
    "sg:orig_category":"Verlichting And Huishoudartikelen",
    "sg:phone":"+31 161 491 285",
    "sg:postcode":"4861 AD",
    "sg:province":"North Brabant",
    "wof:name":"De Gedekte Tafel Vof",
    "wof:placetype":"venue"
},
  "geometry": {"coordinates":[4.85987,51.50602],"type":"Point"}
}