{
  "type": "Feature",
  "properties": {
    "iso:country":"NL",
    "sg:address":"Eksterstraat 38",
    "sg:city":"Oosterhout Nb",
    "sg:orig_category":"Kantoorartikelen",
    "sg:phone":"+31 162 450 772",
    "sg:postcode":"4901 BB",
    "sg:province":"North Brabant",
    "wof:name":"Vissers Technisch Advies Buro",
    "wof:placetype":"venue"
},
  "geometry": {"coordinates":[4.8574180603,51.6506004333],"type":"Point"}
}