{
  "type": "Feature",
  "properties": {
    "addr:full":"Dambroek 27 Baak Gelderland 7223 DT",
    "addr:housenumber":"27",
    "addr:postcode":"7223 dt",
    "addr:street":"Dambroek;Gelderland",
    "iso:country":"NL",
    "sg:address":"Dambroek 27",
    "sg:city":"Baak",
    "sg:orig_category":"Pallets - Fabrieken En Groothandel",
    "sg:phone":"+31 575 441 078",
    "sg:postcode":"7223 DT",
    "sg:province":"Gelderland",
    "wof:name":"Palletrecycling Bv",
    "wof:placetype":"venue"
},
  "geometry": {"coordinates":[6.21701,52.069492],"type":"Point"}
}