{
  "type": "Feature",
  "properties": {
    "addr:full":"Sielandsreed 23 Gaast Provincie Friesland 8757 JZ",
    "addr:housenumber":"23",
    "addr:postcode":"8757 jz",
    "addr:street":"Sielandsreed;Provincie Friesland",
    "iso:country":"NL",
    "sg:address":"Sielandsreed 23",
    "sg:city":"Gaast",
    "sg:orig_category":"Boekhouders",
    "sg:phone":"+31 515 543 195",
    "sg:postcode":"8757 JZ",
    "sg:province":"Provincie Friesland",
    "wof:name":"Administratie Kantoor Kalsbeek",
    "wof:placetype":"venue"
},
  "geometry": {"coordinates":[5.41084,53.016258],"type":"Point"}
}