{
  "type": "Feature",
  "properties": {
    "iso:country":"NL",
    "sg:address":"Sielandsreed 23",
    "sg:city":"Gaast",
    "sg:orig_category":"Boekhouders",
    "sg:phone":"+31 515 543 195",
    "sg:postcode":"8757 JZ",
    "sg:province":"Provincie Friesland",
    "wof:name":"Administratie Kantoor Kalsbeek",
    "wof:placetype":"venue"
},
  "geometry": {"coordinates":[5.41084,53.016258],"type":"Point"}
}