{
  "type": "Feature",
  "properties": {
    "iso:country":"NL",
    "sg:address":"Kl Achterwg 49A",
    "sg:city":"Naaldwyk",
    "sg:orig_category":"Bloemen En Planten - Decoratie",
    "sg:phone":"+31 174 629 069",
    "sg:postcode":"2671 LV",
    "sg:province":"Zuid-Holland",
    "sg:website":"http://www.creaparte.nl",
    "wof:name":"Creaparte",
    "wof:placetype":"venue"
},
  "geometry": {"coordinates":[4.205249,51.991398],"type":"Point"}
}