{
  "type": "Feature",
  "properties": {
    "addr:full":"Chrysanthemumln 12 Heemstede Noord-Holland 2106 BN",
    "addr:housenumber":"12",
    "addr:postcode":"2106 bn",
    "addr:street":"Chrysanthemumln",
    "iso:country":"NL",
    "sg:address":"Chrysanthemumln 12",
    "sg:city":"Heemstede",
    "sg:orig_category":"Adviesbureaus",
    "sg:phone":"+31 23 547 0497",
    "sg:postcode":"2106 BN",
    "sg:province":"Noord-Holland",
    "wof:name":"Scientific Advisor",
    "wof:placetype":"venue"
},
  "geometry": {"coordinates":[4.614062,52.361717],"type":"Point"}
}