{
  "type": "Feature",
  "properties": {
    "iso:country":"NL",
    "sg:address":"Coosje Buskenstraat 141",
    "sg:city":"Vlissingen",
    "sg:orig_category":"Hypotheken And Hypotheekbanken",
    "sg:phone":"+31 118 417 771",
    "sg:postcode":"4381 LD",
    "sg:province":"Zeeland",
    "wof:name":"Hypotheek Adviesbureau Huis En Hypotheek",
    "wof:placetype":"venue"
},
  "geometry": {"coordinates":[3.571019,51.445004],"type":"Point"}
}