{
  "type": "Feature",
  "properties": {
    "iso:country":"NL",
    "sg:address":"Trompmoledyk 4",
    "sg:city":"Ijlst",
    "sg:orig_category":"Metaalwerken",
    "sg:phone":"+31 515 532 752",
    "sg:postcode":"8651 ER",
    "sg:province":"Friesland",
    "wof:name":"Fa G De Jong Plafondbedrijf",
    "wof:placetype":"venue"
},
  "geometry": {"coordinates":[5.623223,53.015793],"type":"Point"}
}