{
  "type": "Feature",
  "properties": {
    "addr:full":"Eisenhowerlaan 1 Oude-Tonge South Holland 3255 VA",
    "addr:housenumber":"1",
    "addr:postcode":"3255",
    "addr:street":"Eisenhowerlaan",
    "iso:country":"NL",
    "sg:address":"Eisenhowerlaan 1",
    "sg:city":"Oude-Tonge",
    "sg:orig_category":"Overheidsdiensten",
    "sg:phone":"+31 187 642 200",
    "sg:postcode":"3255 VA",
    "sg:province":"South Holland",
    "wof:name":"Gemeente Oostflakkee",
    "wof:placetype":"venue"
},
  "geometry": {"coordinates":[4.2177271843,51.692489624],"type":"Point"}
}