{
  "type": "Feature",
  "properties": {
    "iso:country":"NL",
    "sg:address":"Prins Bernhardstraat 69",
    "sg:city":"Zwijndrecht",
    "sg:orig_category":"Goederenvervoer Over De Weg",
    "sg:phone":"+31 78 612 0628",
    "sg:postcode":"3331 BP",
    "sg:province":"South Holland",
    "wof:name":"P.M. Bezemer Int. Transport",
    "wof:placetype":"venue"
},
  "geometry": {"coordinates":[4.645625,51.819656],"type":"Point"}
}