{
  "type": "Feature",
  "properties": {
    "addr:full":"Oranjepark 3 Veendam Groningen 9645 NT",
    "addr:housenumber":"3",
    "addr:postcode":"9645 nt",
    "addr:street":"Oranjepark",
    "iso:country":"NL",
    "sg:address":"Oranjepark 3",
    "sg:city":"Veendam",
    "sg:orig_category":"Architecten",
    "sg:phone":"+31 598 626 602",
    "sg:postcode":"9645 NT",
    "sg:province":"Groningen",
    "wof:name":"R. Smit Architekt Avb Bna",
    "wof:placetype":"venue"
},
  "geometry": {"coordinates":[6.879703,53.112141],"type":"Point"}
}