{
  "type": "Feature",
  "properties": {
    "iso:country":"NL",
    "sg:address":"Jan Cornelisz Maylaan 18",
    "sg:city":"Utrecht",
    "sg:orig_category":"Woningbouwverenigingen",
    "sg:phone":"+31 30 282 7911",
    "sg:postcode":"3526 GV",
    "sg:province":"Utrecht",
    "wof:name":"Stichting Bo Ex '91",
    "wof:placetype":"venue"
},
  "geometry": {"coordinates":[5.093911171,52.0701713562],"type":"Point"}
}