{
  "type": "Feature",
  "properties": {
    "iso:country":"NL",
    "sg:address":"Den Hoogenkant 13",
    "sg:city":"Nuland",
    "sg:orig_category":"Kappers",
    "sg:phone":"+31 73 532 4127",
    "sg:postcode":"5391 GB",
    "sg:province":"Noord-Brabant",
    "wof:name":"Marijke",
    "wof:placetype":"venue"
},
  "geometry": {"coordinates":[5.434565,51.723175],"type":"Point"}
}