{
  "type": "Feature",
  "properties": {
    "addr:full":"Den Hoogenkant 13 Nuland Noord-Brabant 5391 GB",
    "addr:housenumber":"13",
    "addr:postcode":"5391 gb",
    "addr:street":"Den Hoogenkant",
    "iso:country":"NL",
    "sg:address":"Den Hoogenkant 13",
    "sg:city":"Nuland",
    "sg:orig_category":"Kappers",
    "sg:phone":"+31 73 532 4127",
    "sg:postcode":"5391 GB",
    "sg:province":"Noord-Brabant",
    "wof:name":"Marijke",
    "wof:placetype":"venue"
},
  "geometry": {"coordinates":[5.434565,51.723175],"type":"Point"}
}