{
  "type": "Feature",
  "properties": {
    "iso:country":"NL",
    "sg:address":"Holmsterheerd 18",
    "sg:city":"Groningen",
    "sg:classifiers":[
        {
            "category":"Personal",
            "subcategory":"Nail Salon",
            "type":"Services"
        }
    ],
    "sg:phone":"+31 50 541 8067",
    "sg:postcode":"9737 LT",
    "sg:province":"Groningen",
    "sg:tags":[
        "pedicure"
    ],
    "wof:name":"Wind, Hilda",
    "wof:placetype":"venue"
},
  "geometry": {"coordinates":[6.596592,53.244762],"type":"Point"}
}