{
  "type": "Feature",
  "properties": {
    "addr:full":"Meddoseweg 11 Eibergen Gelderland 7152 EM",
    "addr:housenumber":"11",
    "addr:postcode":"7152 em",
    "addr:street":"Meddoseweg;Gelderland",
    "iso:country":"NL",
    "sg:address":"Meddoseweg 11",
    "sg:city":"Eibergen",
    "sg:orig_category":"Landbouwmachines Gh",
    "sg:phone":"+31 544 462 161",
    "sg:postcode":"7152 EM",
    "sg:province":"Gelderland",
    "wof:name":"Wellink Landbouwmechanisatie Bv",
    "wof:placetype":"venue"
},
  "geometry": {"coordinates":[6.652961,52.031422],"type":"Point"}
}