{
  "type": "Feature",
  "properties": {
    "addr:full":"Kamperfoelie 8 Tiel Gelderland 4007 TL",
    "addr:housenumber":"8",
    "addr:postcode":"4007 tl",
    "addr:street":"Kamperfoelie;Gelderland",
    "iso:country":"NL",
    "sg:address":"Kamperfoelie 8",
    "sg:city":"Tiel",
    "sg:classifiers":[
        {
            "category":"Food & Beverages",
            "subcategory":"Bakery",
            "type":"Retail Goods"
        }
    ],
    "sg:phone":"+31 344 626 387",
    "sg:postcode":"4007 TL",
    "sg:province":"Gelderland",
    "sg:tags":[
        "brood",
        "en",
        "banket"
    ],
    "wof:name":"Ehren",
    "wof:placetype":"venue"
},
  "geometry": {"coordinates":[5.400438,51.870625],"type":"Point"}
}