{
  "type": "Feature",
  "properties": {
    "addr:full":"Muiderbos 102 , Winkelcentrum Het Paradijs Hoofddorp Noord-Holland 2134 SV",
    "addr:housenumber":"102",
    "addr:postcode":"2134 sv",
    "addr:street":"Muiderbos;Het Paradijs",
    "iso:country":"NL",
    "sg:address":"Muiderbos 102 , Winkelcentrum Het Paradijs",
    "sg:city":"Hoofddorp",
    "sg:classifiers":[
        {
            "category":"Food & Beverages",
            "subcategory":"Bakery",
            "type":"Retail Goods"
        }
    ],
    "sg:phone":"+31 23 563 7355",
    "sg:postcode":"2134 SV",
    "sg:province":"Noord-Holland",
    "sg:tags":[
        "brood",
        "en",
        "banket"
    ],
    "wof:name":"Voorn, J Van Der",
    "wof:placetype":"venue"
},
  "geometry": {"coordinates":[4.65001,52.310471],"type":"Point"}
}