{
  "type": "Feature",
  "properties": {
    "addr:full":"Raadhuisstr 102 Alphen Aan Den Ryn South Holland 2406 AH",
    "addr:housenumber":"102",
    "addr:postcode":"2406 ah",
    "addr:street":"Aan Den Ryn",
    "iso:country":"NL",
    "sg:address":"Raadhuisstr 102",
    "sg:city":"Alphen Aan Den Ryn",
    "sg:orig_category":"Autorijscholen",
    "sg:phone":"+31 172 440 744",
    "sg:postcode":"2406 AH",
    "sg:province":"South Holland",
    "sg:website":"http://www.autorijschoolreflex.nl",
    "wof:name":"Reflex Verkeersschool",
    "wof:placetype":"venue"
},
  "geometry": {"coordinates":[4.663482,52.126347],"type":"Point"}
}