{
  "type": "Feature",
  "properties": {
    "addr:full":"Chaamseweg 6 Alphen Nb North Brabant 5131 NG",
    "addr:housenumber":"6;nb",
    "addr:postcode":"5131 ng",
    "addr:street":"Chaamseweg",
    "iso:country":"NL",
    "sg:address":"Chaamseweg 6",
    "sg:city":"Alphen Nb",
    "sg:orig_category":"Boekhouders",
    "sg:phone":"+31 13 508 1911",
    "sg:postcode":"5131 NG",
    "sg:province":"North Brabant",
    "wof:name":"Boekhoudbureau Trommelen Alphen Bv",
    "wof:placetype":"venue"
},
  "geometry": {"coordinates":[4.951392,51.483986],"type":"Point"}
}