{
  "type": "Feature",
  "properties": {
    "addr:full":"Julianaln 315 Haarlem Noord-Holland 2015 BP",
    "addr:housenumber":"315",
    "addr:postcode":"2015 bp",
    "iso:country":"NL",
    "sg:address":"Julianaln 315",
    "sg:city":"Haarlem",
    "sg:orig_category":"Haptotherapeuten",
    "sg:phone":"+31 23 531 0363",
    "sg:postcode":"2015 BP",
    "sg:province":"Noord-Holland",
    "wof:name":"Bert Lenselink",
    "wof:placetype":"venue"
},
  "geometry": {"coordinates":[4.62062,52.386574],"type":"Point"}
}