{
  "type": "Feature",
  "properties": {
    "addr:full":"Bouvigne 28 Eindhoven Noord-Brabant 5653 LH",
    "addr:housenumber":"28",
    "addr:postcode":"5653 lh",
    "addr:street":"Bouvigne",
    "iso:country":"NL",
    "sg:address":"Bouvigne 28",
    "sg:city":"Eindhoven",
    "sg:orig_category":"Keukens",
    "sg:phone":"+31 40 251 9594",
    "sg:postcode":"5653 LH",
    "sg:province":"Noord-Brabant",
    "wof:name":"Hout, Van",
    "wof:placetype":"venue"
},
  "geometry": {"coordinates":[5.433647,51.421848],"type":"Point"}
}