{
  "type": "Feature",
  "properties": {
    "addr:full":"Fellenoord 370 Eindhoven Noord-Brabant 5611 ZL",
    "addr:housenumber":"370",
    "addr:postcode":"5611 zl",
    "addr:street":"Fellenoord",
    "iso:country":"NL",
    "sg:address":"Fellenoord 370",
    "sg:city":"Eindhoven",
    "sg:orig_category":"Verzekeringen",
    "sg:phone":"+31 40 243 4286",
    "sg:postcode":"5611 ZL",
    "sg:province":"Noord-Brabant",
    "wof:name":"Heijnis & Koelman Bv",
    "wof:placetype":"venue"
},
  "geometry": {"coordinates":[5.472839,51.442581],"type":"Point"}
}