{
  "type": "Feature",
  "properties": {
    "addr:full":"Spoorstraat 7 'S Gravenpolder Zeeland 4431 NK",
    "addr:housenumber":"7 '",
    "addr:postcode":"4431 nk",
    "addr:street":"Spoorstraat",
    "iso:country":"NL",
    "sg:address":"Spoorstraat 7",
    "sg:city":"'S Gravenpolder",
    "sg:orig_category":"Autokeuringen",
    "sg:phone":"+31 113 313 203",
    "sg:postcode":"4431 NK",
    "sg:province":"Zeeland",
    "wof:name":"John Smit",
    "wof:placetype":"venue"
},
  "geometry": {"coordinates":[3.881677,51.450726],"type":"Point"}
}