{
  "type": "Feature",
  "properties": {
    "addr:full":"Castricummer Werf 40 Castricum North Holland 1901 RV",
    "addr:housenumber":"40",
    "addr:postcode":"1901 rv",
    "addr:street":"Castricummer Werf",
    "iso:country":"NL",
    "sg:address":"Castricummer Werf 40",
    "sg:city":"Castricum",
    "sg:orig_category":"Verhuizingen",
    "sg:phone":"+31 251 652 439",
    "sg:postcode":"1901 RV",
    "sg:province":"North Holland",
    "sg:website":"http://www.aaddewit.nl",
    "wof:name":"Aad De Wit Verhuizingen",
    "wof:placetype":"venue"
},
  "geometry": {"coordinates":[4.665086,52.541199],"type":"Point"}
}