{
  "type": "Feature",
  "properties": {
    "addr:full":"Postbus 465 Alphen Aan Den Ryn 2400 AL",
    "addr:housenumber":"465",
    "addr:postcode":"2400",
    "addr:street":"Postbus;Aan Den Ryn",
    "iso:country":"NL",
    "sg:address":"Postbus 465",
    "sg:city":"Alphen Aan Den Ryn",
    "sg:orig_category":"Adviesbureaus Bouwkunde",
    "sg:phone":"+31 172 472 219",
    "sg:postcode":"2400 AL",
    "wof:name":"Bath",
    "wof:placetype":"venue"
},
  "geometry": {"coordinates":[4.68895,52.131088],"type":"Point"}
}