{
  "type": "Feature",
  "properties": {
    "addr:full":"Medelsestr 13 Tiel Gelderland 4005 VA",
    "addr:housenumber":"13",
    "addr:postcode":"4005",
    "addr:street":"Medelsestr;Gelderland",
    "iso:country":"NL",
    "sg:address":"Medelsestr 13",
    "sg:city":"Tiel",
    "sg:orig_category":"Fotojournalisten Freelance",
    "sg:phone":"+31 344 616 296",
    "sg:postcode":"4005 VA",
    "sg:province":"Gelderland",
    "wof:name":"Bouwhuis, Jan",
    "wof:placetype":"venue"
},
  "geometry": {"coordinates":[5.442098,51.895596],"type":"Point"}
}