{
  "type": "Feature",
  "properties": {
    "addr:full":"Zairestr 39 Delft Zuid-Holland 2622 ER",
    "addr:housenumber":"39",
    "addr:postcode":"2622 er",
    "addr:street":"Zairestr",
    "iso:country":"NL",
    "sg:address":"Zairestr 39",
    "sg:city":"Delft",
    "sg:orig_category":"Adviesbureaus Bouwkunde",
    "sg:phone":"+31 15 261 9047",
    "sg:postcode":"2622 ER",
    "sg:province":"Zuid-Holland",
    "wof:name":"Quintus",
    "wof:placetype":"venue"
},
  "geometry": {"coordinates":[4.342201,51.981617],"type":"Point"}
}