{
  "type": "Feature",
  "properties": {
    "addr:full":"Zuiderwg 2 Lageland Groningen 9623 PD",
    "addr:housenumber":"2",
    "addr:postcode":"9623 pd",
    "addr:street":"Zuiderwg;Lageland",
    "iso:country":"NL",
    "sg:address":"Zuiderwg 2",
    "sg:city":"Lageland",
    "sg:orig_category":"Luchtverwarming",
    "sg:phone":"+31 50 549 6215",
    "sg:postcode":"9623 PD",
    "sg:province":"Groningen",
    "wof:name":"Moeken Vof",
    "wof:placetype":"venue"
},
  "geometry": {"coordinates":[6.661502,53.239372],"type":"Point"}
}