{
  "type": "Feature",
  "properties": {
    "addr:full":"Spanjaardswg 3 Wedde Groningen 9698 BT",
    "addr:housenumber":"3",
    "addr:postcode":"9698 bt",
    "addr:street":"Spanjaardswg",
    "iso:country":"NL",
    "sg:address":"Spanjaardswg 3",
    "sg:city":"Wedde",
    "sg:orig_category":"Lpg-Installaties",
    "sg:phone":"+31 597 561 257",
    "sg:postcode":"9698 BT",
    "sg:province":"Groningen",
    "wof:name":"Hemmes",
    "wof:placetype":"venue"
},
  "geometry": {"coordinates":[7.086639,53.068913],"type":"Point"}
}