{
  "type": "Feature",
  "properties": {
    "addr:full":"Molenstr 46 Veghel North Brabant 5461 JR",
    "addr:housenumber":"46",
    "addr:postcode":"5461 jr",
    "addr:street":"Molenstr",
    "iso:country":"NL",
    "sg:address":"Molenstr 46",
    "sg:city":"Veghel",
    "sg:orig_category":"Videotheken",
    "sg:phone":"+31 413 365 999",
    "sg:postcode":"5461 JR",
    "sg:province":"North Brabant",
    "sg:website":"http://www.videoland.nl",
    "wof:name":"Videoland",
    "wof:placetype":"venue"
},
  "geometry": {"coordinates":[5.545422,51.618275],"type":"Point"}
}