{
  "type": "Feature",
  "properties": {
    "addr:full":"Hoofdstraat 23 Zuidwolde Dr Drenthe 7921 AB",
    "addr:housenumber":"23",
    "addr:postcode":"7921 ab",
    "addr:street":"Hoofdstraat;Dr",
    "iso:country":"NL",
    "sg:address":"Hoofdstraat 23",
    "sg:city":"Zuidwolde Dr",
    "sg:orig_category":"Architecten",
    "sg:phone":"+31 528 373 169",
    "sg:postcode":"7921 AB",
    "sg:province":"Drenthe",
    "wof:name":"Architectenburo Ing. Bert Vrielink",
    "wof:placetype":"venue"
},
  "geometry": {"coordinates":[6.42853,52.67675],"type":"Point"}
}