{
  "type": "Feature",
  "properties": {
    "addr:full":"Malusln 74 Groningen Groningen 9741 LN",
    "addr:housenumber":"74",
    "addr:postcode":"9741 ln",
    "addr:street":"Malusln",
    "iso:country":"NL",
    "sg:address":"Malusln 74",
    "sg:city":"Groningen",
    "sg:orig_category":"Marktonderzoekbureaus",
    "sg:phone":"+31 50 577 9991",
    "sg:postcode":"9741 LN",
    "sg:province":"Groningen",
    "wof:name":"Witterholt, S",
    "wof:placetype":"venue"
},
  "geometry": {"coordinates":[6.55068,53.23254],"type":"Point"}
}