{
  "type": "Feature",
  "properties": {
    "iso:country":"NL",
    "sg:address":"Huizerwg 89",
    "sg:city":"Bussum",
    "sg:orig_category":"Ademhalingstherapeuten",
    "sg:phone":"+31 35 691 0284",
    "sg:postcode":"1401 GK",
    "sg:province":"Noord-Holland",
    "wof:name":"Buteyko, Benelux",
    "wof:placetype":"venue"
},
  "geometry": {"coordinates":[5.18402,52.278156],"type":"Point"}
}