{
  "type": "Feature",
  "properties": {
    "addr:full":"Eperw 1 Uitv Centr F Heerde Gelderland 8181 ET",
    "addr:housenumber":"1",
    "addr:postcode":"8181 et",
    "addr:street":"Eperw;Gelderland",
    "iso:country":"NL",
    "sg:address":"Eperw 1 Uitv Centr F",
    "sg:city":"Heerde",
    "sg:orig_category":"Begrafenisverzorging",
    "sg:phone":"+31 578 691 846",
    "sg:postcode":"8181 ET",
    "sg:province":"Gelderland",
    "wof:name":"Memento Mori",
    "wof:placetype":"venue"
},
  "geometry": {"coordinates":[6.037087,52.386574],"type":"Point"}
}