{
  "type": "Feature",
  "properties": {
    "addr:full":"Midstraat 205 Joure Friesland 8501 AM",
    "addr:housenumber":"205",
    "addr:postcode":"8501",
    "addr:street":"Midstraat",
    "iso:country":"NL",
    "sg:address":"Midstraat 205",
    "sg:city":"Joure",
    "sg:orig_category":"Fietshandelaren",
    "sg:phone":"+31 513 415 303",
    "sg:postcode":"8501 AM",
    "sg:province":"Friesland",
    "wof:name":"Bike & Light",
    "wof:placetype":"venue"
},
  "geometry": {"coordinates":[5.79987,52.965424],"type":"Point"}
}