{
  "type": "Feature",
  "properties": {
    "addr:full":"Dorpsstraat 61 Lattrop Breklenkamp NL.08 7635 NB",
    "addr:housenumber":"61",
    "addr:postcode":"nl.08 7635 nb",
    "addr:street":"Dorpsstraat",
    "iso:country":"NL",
    "sg:address":"Dorpsstraat 61",
    "sg:city":"Lattrop Breklenkamp",
    "sg:orig_category":"Banken And Kredietinstellingen",
    "sg:phone":"+31 541 229 203",
    "sg:postcode":"7635 NB",
    "sg:province":"NL.08",
    "wof:name":"Rabobank",
    "wof:placetype":"venue"
},
  "geometry": {"coordinates":[6.976319,52.426872],"type":"Point"}
}