{
  "type": "Feature",
  "properties": {
    "addr:full":"Achter De Dom 12 Utrecht Utrecht 3512 JP",
    "addr:housenumber":"12",
    "addr:postcode":"3512 jp",
    "addr:street":"Achter De Dom",
    "iso:country":"NL",
    "sg:address":"Achter De Dom 12",
    "sg:city":"Utrecht",
    "sg:orig_category":"Zalenverhuur",
    "sg:phone":"+31 30 231 7781",
    "sg:postcode":"3512 JP",
    "sg:province":"Utrecht",
    "wof:name":"Nieuwe Gracht",
    "wof:placetype":"venue"
},
  "geometry": {"coordinates":[5.123175,52.090855],"type":"Point"}
}