{
  "type": "Feature",
  "properties": {
    "addr:full":"Dorpsstr 25 Bakel North Brabant 5761 BL",
    "addr:housenumber":"25",
    "addr:postcode":"5761 bl",
    "addr:street":"Dorpsstr",
    "iso:country":"NL",
    "sg:address":"Dorpsstr 25",
    "sg:city":"Bakel",
    "sg:orig_category":"Verenigingsgebouwen",
    "sg:phone":"+31 492 342 896",
    "sg:postcode":"5761 BL",
    "sg:province":"North Brabant",
    "wof:name":"Fuse",
    "wof:placetype":"venue"
},
  "geometry": {"coordinates":[5.741939,51.504234],"type":"Point"}
}