{
  "type": "Feature",
  "properties": {
    "iso:country":"NL",
    "sg:address":"Langebergln 4",
    "sg:city":"Brunssum",
    "sg:orig_category":"Betonijzervlechten",
    "sg:phone":"+31 45 525 6859",
    "sg:postcode":"6445 AS",
    "sg:province":"Limburg",
    "wof:name":"K\u00f7Rver",
    "wof:placetype":"venue"
},
  "geometry": {"coordinates":[5.972551,50.934978],"type":"Point"}
}