{
  "type": "Feature",
  "properties": {
    "addr:full":"Smidstraat 5 Katwijk Zh Zuid-Holland 2222 AS",
    "addr:housenumber":"5",
    "addr:postcode":"2222 as",
    "addr:street":"Smidstraat",
    "iso:country":"NL",
    "sg:address":"Smidstraat 5",
    "sg:city":"Katwijk Zh",
    "sg:orig_category":"Mobiele Service Aan Motorvoertuigen",
    "sg:phone":"+31 71 408 0734",
    "sg:postcode":"2222 AS",
    "sg:province":"Zuid-Holland",
    "wof:name":"Auto Schuller Bv",
    "wof:placetype":"venue"
},
  "geometry": {"coordinates":[4.432359,52.197868],"type":"Point"}
}