{
  "type": "Feature",
  "properties": {
    "iso:country":"NL",
    "sg:address":"Van Karnebeekstraat 11",
    "sg:city":"Heerlen",
    "sg:orig_category":"Medische Apparatuur And Prothesen Fab",
    "sg:phone":"+31 45 572 3735",
    "sg:postcode":"6415 EK",
    "sg:province":"Limburg",
    "wof:name":"M Verdoes Frame-Techniek",
    "wof:placetype":"venue"
},
  "geometry": {"coordinates":[5.991907,50.897247],"type":"Point"}
}