{
  "type": "Feature",
  "properties": {
    "iso:country":"NL",
    "sg:address":"Markt 7",
    "sg:city":"Vlaardingen",
    "sg:orig_category":"Antiekzaken",
    "sg:phone":"+31 10 435 9797",
    "sg:postcode":"3131 CR",
    "sg:province":"Zuid-Holland",
    "wof:name":"Kunsthandel Prentenkabinet P. Van Der Hoeven",
    "wof:placetype":"venue"
},
  "geometry": {"coordinates":[4.342487,51.908237],"type":"Point"}
}