{
  "type": "Feature",
  "properties": {
    "addr:full":"Munnikenwoud 17 Zwaag Noord-Holland 1689 BA",
    "addr:housenumber":"17",
    "addr:postcode":"1689 ba",
    "addr:street":"Munnikenwoud",
    "iso:country":"NL",
    "sg:address":"Munnikenwoud 17",
    "sg:city":"Zwaag",
    "sg:orig_category":"Montagebedrijven",
    "sg:phone":"+31 229 262 421",
    "sg:postcode":"1689 BA",
    "sg:province":"Noord-Holland",
    "wof:name":"Gks",
    "wof:placetype":"venue"
},
  "geometry": {"coordinates":[5.079997,52.667641],"type":"Point"}
}