{
  "type": "Feature",
  "properties": {
    "iso:country":"NL",
    "sg:address":"Boeyinkweg 6",
    "sg:city":"Keijenborg",
    "sg:orig_category":"Zuivelproducten And Spijsoli?n Gh",
    "sg:phone":"+31 575 462 303",
    "sg:postcode":"7256 KS",
    "sg:province":"Gelderland",
    "wof:name":"Eierhandel B.G. Overmaat",
    "wof:placetype":"venue"
},
  "geometry": {"coordinates":[6.315967,52.03072],"type":"Point"}
}