{
  "type": "Feature",
  "properties": {
    "addr:full":"Sint Jansgildestraat 61 Beek Gem Bergh Gelderland 7037 CB",
    "addr:housenumber":"61",
    "addr:postcode":"7037 cb",
    "addr:street":"Sint Jansgildestraat",
    "iso:country":"NL",
    "sg:address":"Sint Jansgildestraat 61",
    "sg:city":"Beek Gem Bergh",
    "sg:orig_category":"Alternatieve Geneeskunde",
    "sg:phone":"+31 316 531 885",
    "sg:postcode":"7037 CB",
    "sg:province":"Gelderland",
    "wof:name":"J.L.G. Buiting",
    "wof:placetype":"venue"
},
  "geometry": {"coordinates":[6.191053,51.909245],"type":"Point"}
}