{
  "type": "Feature",
  "properties": {
    "addr:full":"Hessen Kasselstraat 3 Eindhoven Noord-Brabant 5615 SM",
    "addr:housenumber":"3",
    "addr:postcode":"5615 sm",
    "addr:street":"Hessen Kasselstraat",
    "iso:country":"NL",
    "sg:address":"Hessen Kasselstraat 3",
    "sg:city":"Eindhoven",
    "sg:orig_category":"Autokeuringen",
    "sg:phone":"+31 40 251 8283",
    "sg:postcode":"5615 SM",
    "sg:province":"Noord-Brabant",
    "wof:name":"J. Louwersse",
    "wof:placetype":"venue"
},
  "geometry": {"coordinates":[5.466012,51.430588],"type":"Point"}
}