{
  "type": "Feature",
  "properties": {
    "addr:full":"Deventerstr 38 Apeldoorn Gelderland 7311 LW",
    "addr:housenumber":"38",
    "addr:postcode":"7311 lw",
    "addr:street":"Deventerstr;Gelderland",
    "iso:country":"NL",
    "sg:address":"Deventerstr 38",
    "sg:city":"Apeldoorn",
    "sg:orig_category":"Verenigingen En Stichtingen",
    "sg:phone":"+31 55 522 6283",
    "sg:postcode":"7311 LW",
    "sg:province":"Gelderland",
    "wof:name":"Ioof",
    "wof:placetype":"venue"
},
  "geometry": {"coordinates":[5.967672,52.216789],"type":"Point"}
}