{
  "type": "Feature",
  "properties": {
    "iso:country":"NL",
    "sg:address":"Lindenlaan 52",
    "sg:city":"Bergen Nh",
    "sg:orig_category":"Bejaardeninstellingen And Serviceflats",
    "sg:phone":"+31 72 589 4346",
    "sg:postcode":"1861 HD",
    "sg:province":"Noord-Holland",
    "wof:name":"Serviceflat Frankenstate",
    "wof:placetype":"venue"
},
  "geometry": {"coordinates":[4.698806,52.675304],"type":"Point"}
}