{
  "type": "Feature",
  "properties": {
    "addr:full":"Nieuwstr 10 Amersfoort Utrecht 3811 JZ",
    "addr:housenumber":"10",
    "addr:postcode":"3811 jz",
    "addr:street":"Nieuwstr",
    "iso:country":"NL",
    "sg:address":"Nieuwstr 10",
    "sg:city":"Amersfoort",
    "sg:orig_category":"Omroep",
    "sg:phone":"+31 33 461 7772",
    "sg:postcode":"3811 JZ",
    "sg:province":"Utrecht",
    "wof:name":"Golfbreker, De",
    "wof:placetype":"venue"
},
  "geometry": {"coordinates":[5.386085,52.152325],"type":"Point"}
}