{
  "type": "Feature",
  "properties": {
    "addr:full":"Urlusstr 23 Utrecht Utrecht 3533 SM",
    "addr:housenumber":"23",
    "addr:postcode":"3533 sm",
    "addr:street":"Urlusstr",
    "iso:country":"NL",
    "sg:address":"Urlusstr 23",
    "sg:city":"Utrecht",
    "sg:orig_category":"Adviesbureaus Bedrijfsorganisatie",
    "sg:phone":"+31 6 51591299",
    "sg:postcode":"3533 SM",
    "sg:province":"Utrecht",
    "sg:website":"http://www.leisurematch.nl",
    "wof:name":"Leisurematch",
    "wof:placetype":"venue"
},
  "geometry": {"coordinates":[5.081821,52.085667],"type":"Point"}
}