{
  "type": "Feature",
  "properties": {
    "addr:full":"Grt Brugs Grintwg 72 Tiel Gelderland 4005 AJ",
    "addr:housenumber":"72",
    "addr:postcode":"4005 aj",
    "addr:street":"Gelderland",
    "iso:country":"NL",
    "sg:address":"Grt Brugs Grintwg 72",
    "sg:city":"Tiel",
    "sg:orig_category":"Touringcars",
    "sg:phone":"+31 344 611 111",
    "sg:postcode":"4005 AJ",
    "sg:province":"Gelderland",
    "sg:website":"http://www.krolreizen.nl",
    "wof:name":"Krol Reizen",
    "wof:placetype":"venue"
},
  "geometry": {"coordinates":[5.440266,51.891914],"type":"Point"}
}