{
  "type": "Feature",
  "properties": {
    "iso:country":"NL",
    "sg:address":"Viswg 2A",
    "sg:city":"Driehuizen",
    "sg:orig_category":"Adviesbureaus",
    "sg:phone":"+31 299 673 890",
    "sg:postcode":"1844 KM",
    "sg:province":"Noord-Holland",
    "wof:name":"Halewijn",
    "wof:placetype":"venue"
},
  "geometry": {"coordinates":[4.812685,52.579128],"type":"Point"}
}