{
  "type": "Feature",
  "properties": {
    "iso:country":"NL",
    "sg:address":"Foarwei 24",
    "sg:city":"Oudwoude",
    "sg:orig_category":"Goederenvervoer Over De Weg",
    "sg:phone":"+31 511 451 941",
    "sg:postcode":"9294 KD",
    "sg:province":"Friesland",
    "wof:name":"Fa. Transportbedrijf H.T.N.",
    "wof:placetype":"venue"
},
  "geometry": {"coordinates":[6.115986,53.279785],"type":"Point"}
}