{
  "type": "Feature",
  "properties": {
    "addr:full":"Meerweg 167 Haren Gn Groningen 9752 XA",
    "addr:housenumber":"167",
    "addr:postcode":"9752 xa",
    "addr:street":"Meerweg",
    "iso:country":"NL",
    "sg:address":"Meerweg 167",
    "sg:city":"Haren Gn",
    "sg:orig_category":"Goederenvervoer Over De Weg",
    "sg:phone":"+31 50 309 4169",
    "sg:postcode":"9752 XA",
    "sg:province":"Groningen",
    "wof:name":"Gemaha",
    "wof:placetype":"venue"
},
  "geometry": {"coordinates":[6.585979,53.165215],"type":"Point"}
}