{
  "type": "Feature",
  "properties": {
    "addr:full":"Jan Frederik Vlekkeweg 8 Tilburg Noord-Brabant 5026 RJ",
    "addr:housenumber":"8",
    "addr:postcode":"5026 rj",
    "addr:street":"Jan Frederik Vlekkeweg",
    "iso:country":"NL",
    "sg:address":"Jan Frederik Vlekkeweg 8",
    "sg:city":"Tilburg",
    "sg:orig_category":"Glaszetten",
    "sg:phone":"+31 13 590 0480",
    "sg:postcode":"5026 RJ",
    "sg:province":"Noord-Brabant",
    "wof:name":"Albert Van Der Meijs",
    "wof:placetype":"venue"
},
  "geometry": {"coordinates":[5.061415,51.541187],"type":"Point"}
}