{
  "type": "Feature",
  "properties": {
    "iso:country":"NL",
    "sg:address":"Woestduinstraat 51",
    "sg:city":"Amsterdam",
    "sg:orig_category":"Loodgieterswerk, Verwarming And Sanitaire Installaties",
    "sg:phone":"+31 20 615 7641",
    "sg:postcode":"1058 TB",
    "sg:province":"Noord-Holland",
    "wof:name":"Jan Schipper Klussenbedrijf",
    "wof:placetype":"venue"
},
  "geometry": {"coordinates":[4.84801,52.353226],"type":"Point"}
}