{
  "type": "Feature",
  "properties": {
    "addr:full":"Kruisdijk 3 Hulsel Noord-Brabant 5096 BB",
    "addr:housenumber":"3",
    "addr:postcode":"5096 bb",
    "addr:street":"Kruisdijk",
    "iso:country":"NL",
    "sg:address":"Kruisdijk 3",
    "sg:city":"Hulsel",
    "sg:orig_category":"Diverse Bedrijfsinstallaties Gh",
    "sg:phone":"+31 13 509 1578",
    "sg:postcode":"5096 BB",
    "sg:province":"Noord-Brabant",
    "wof:name":"Kouwenbergh Machinefabriek Bv",
    "wof:placetype":"venue"
},
  "geometry": {"coordinates":[5.165787,51.388561],"type":"Point"}
}