{
  "type": "Feature",
  "properties": {
    "addr:full":"Vlasrootwg 1C Groesbeek Gelderland 6562 ZE",
    "addr:housenumber":"1c",
    "addr:postcode":"6562",
    "addr:street":"Vlasrootwg;Gelderland",
    "iso:country":"NL",
    "sg:address":"Vlasrootwg 1C",
    "sg:city":"Groesbeek",
    "sg:orig_category":"Acupunctuur",
    "sg:phone":"+31 24 397 7494",
    "sg:postcode":"6562 ZE",
    "sg:province":"Gelderland",
    "sg:website":"http://www.reinders.alles.nl",
    "wof:name":"Reinders, Jan",
    "wof:placetype":"venue"
},
  "geometry": {"coordinates":[5.932427,51.771576],"type":"Point"}
}