{
  "type": "Feature",
  "properties": {
    "addr:full":"Dorpstr 43 Oirsbeek Limburg 6438 JS",
    "addr:housenumber":"43",
    "addr:postcode":"6438 js",
    "addr:street":"Dorpstr",
    "iso:country":"NL",
    "sg:address":"Dorpstr 43",
    "sg:city":"Oirsbeek",
    "sg:orig_category":"Autorijscholen",
    "sg:phone":"+31 46 442 3170",
    "sg:postcode":"6438 JS",
    "sg:province":"Limburg",
    "wof:name":"Lindelauf, J",
    "wof:placetype":"venue"
},
  "geometry": {"coordinates":[5.913254,50.949081],"type":"Point"}
}