{
  "type": "Feature",
  "properties": {
    "iso:country":"NL",
    "sg:address":"Kamgras 23",
    "sg:city":"Rotterdam",
    "sg:orig_category":"Verenigingen En Stichtingen",
    "sg:phone":"+31 10 420 9844",
    "sg:postcode":"3068 CB",
    "sg:province":"Zuid-Holland",
    "wof:name":"Nanai, Sticht",
    "wof:placetype":"venue"
},
  "geometry": {"coordinates":[4.546242,51.954601],"type":"Point"}
}