{
  "type": "Feature",
  "properties": {
    "addr:full":"Nieuwez Voorburgw 302 Amsterdam North Holland 1012 RT",
    "addr:housenumber":"302",
    "addr:postcode":"1012 rt",
    "iso:country":"NL",
    "sg:address":"Nieuwez Voorburgw 302",
    "sg:city":"Amsterdam",
    "sg:orig_category":"Postzegels",
    "sg:phone":"+31 20 622 3765",
    "sg:postcode":"1012 RT",
    "sg:province":"North Holland",
    "sg:website":"http://www.bulterman.nl",
    "wof:name":"Bulterman Filatelie",
    "wof:placetype":"venue"
},
  "geometry": {"coordinates":[4.889989,52.370525],"type":"Point"}
}