{
  "type": "Feature",
  "properties": {
    "iso:country":"NL",
    "sg:address":"Paasheuvelweg 38",
    "sg:city":"Amsterdam Zuidoost",
    "sg:orig_category":"Metaalwerken",
    "sg:phone":"+31 20 564 8465",
    "sg:postcode":"1105 BJ",
    "sg:province":"Noord-Holland",
    "wof:name":"Astrimex Bv",
    "wof:placetype":"venue"
},
  "geometry": {"coordinates":[4.951944,52.297321],"type":"Point"}
}