{
  "type": "Feature",
  "properties": {
    "addr:full":"Kapelstraat 27 Bussum North Holland 1404 HV",
    "addr:housenumber":"27",
    "addr:postcode":"1404 hv",
    "addr:street":"Kapelstraat",
    "iso:country":"NL",
    "sg:address":"Kapelstraat 27",
    "sg:city":"Bussum",
    "sg:orig_category":"Kappers",
    "sg:phone":"+31 35 692 1551",
    "sg:postcode":"1404 HV",
    "sg:province":"North Holland",
    "wof:name":"Tutti Frutti Hairshop",
    "wof:placetype":"venue"
},
  "geometry": {"coordinates":[5.165131,52.274052],"type":"Point"}
}