{
  "type": "Feature",
  "properties": {
    "addr:full":"Hoogeveenenwg 8 Nieuwerkerk Yssel Zuid-Holland 2913 LV",
    "addr:housenumber":"8",
    "addr:postcode":"2913",
    "addr:street":"Hoogeveenenwg",
    "iso:country":"NL",
    "sg:address":"Hoogeveenenwg 8",
    "sg:city":"Nieuwerkerk Yssel",
    "sg:orig_category":"Gassen Industrieel En Medisch",
    "sg:phone":"+31 180 313 028",
    "sg:postcode":"2913 LV",
    "sg:province":"Zuid-Holland",
    "wof:name":"Hatek Bv",
    "wof:placetype":"venue"
},
  "geometry": {"coordinates":[4.612739,51.980373],"type":"Point"}
}