{
  "type": "Feature",
  "properties": {
    "iso:country":"NL",
    "sg:address":"Deventerwg 23",
    "sg:city":"Laren Gld",
    "sg:orig_category":"Makelaars En Adviseurs Onroerende Goederen",
    "sg:phone":"+31 573 401 200",
    "sg:postcode":"7245 AW",
    "sg:province":"Gelderland",
    "wof:name":"Meuleman, B J",
    "wof:placetype":"venue"
},
  "geometry": {"coordinates":[6.361059,52.194855],"type":"Point"}
}