{
  "type": "Feature",
  "properties": {
    "addr:full":"Smalle Havenstraat 3 Vlaardingen South Holland 3131 BS",
    "addr:housenumber":"3",
    "addr:postcode":"3131 bs",
    "addr:street":"Smalle Havenstraat",
    "iso:country":"NL",
    "sg:address":"Smalle Havenstraat 3",
    "sg:city":"Vlaardingen",
    "sg:classifiers":[
        {
            "category":"Fast Food",
            "type":"Food & Drink"
        }
    ],
    "sg:phone":"+31 10 460 3580",
    "sg:postcode":"3131 BS",
    "sg:province":"South Holland",
    "sg:tags":[
        "afhaal",
        "restaurant"
    ],
    "wof:name":"Shoarma Cairo",
    "wof:placetype":"venue"
},
  "geometry": {"coordinates":[4.343787,51.90863],"type":"Point"}
}