{
  "type": "Feature",
  "properties": {
    "iso:country":"NL",
    "sg:address":"Leidsevaartwg 1B",
    "sg:city":"Heemstede",
    "sg:orig_category":"Fotografie Reclame En Mode",
    "sg:phone":"+31 23 584 7543",
    "sg:postcode":"2106 NA",
    "sg:province":"Noord-Holland",
    "sg:website":"HTTP://www.tref.nl",
    "wof:name":"Laan Bv, Kees Van Der",
    "wof:placetype":"venue"
},
  "geometry": {"coordinates":[4.591349,52.32893],"type":"Point"}
}