{
  "type": "Feature",
  "properties": {
    "addr:full":"Marconiwg 69 Hellevoetsluis Zuid-Holland 3225 LV",
    "addr:housenumber":"69",
    "addr:postcode":"3225",
    "addr:street":"Marconiwg",
    "iso:country":"NL",
    "sg:address":"Marconiwg 69",
    "sg:city":"Hellevoetsluis",
    "sg:classifiers":[
        {
            "category":"Retail",
            "subcategory":"Auto Repair",
            "type":"Services"
        }
    ],
    "sg:phone":"+31 181 337 070",
    "sg:postcode":"3225 LV",
    "sg:province":"Zuid-Holland",
    "sg:tags":[
        "garage"
    ],
    "sg:website":"http://www.bvscars.com",
    "wof:name":"Bvs",
    "wof:placetype":"venue"
},
  "geometry": {"coordinates":[4.166397,51.839104],"type":"Point"}
}