{
  "type": "Feature",
  "properties": {
    "addr:full":"Postbus 43 Hedel Gelderland 5320 AA",
    "addr:housenumber":"43",
    "addr:postcode":"5320 aa",
    "addr:street":"Postbus;Gelderland",
    "iso:country":"NL",
    "sg:address":"Postbus 43",
    "sg:city":"Hedel",
    "sg:orig_category":"Voetbalverenigingen",
    "sg:phone":"+31 73 599 3182",
    "sg:postcode":"5320 AA",
    "sg:province":"Gelderland",
    "wof:name":"Hedel Vv",
    "wof:placetype":"venue"
},
  "geometry": {"coordinates":[5.25931,51.744961],"type":"Point"}
}