{
  "type": "Feature",
  "properties": {
    "addr:full":"Amperestr 13E Purmerend North Holland 1446 TP",
    "addr:housenumber":"13e",
    "addr:postcode":"1446 tp",
    "addr:street":"Amperestr",
    "iso:country":"NL",
    "sg:address":"Amperestr 13E",
    "sg:city":"Purmerend",
    "sg:orig_category":"Boekbinderijen",
    "sg:phone":"+31 299 641 230",
    "sg:postcode":"1446 TP",
    "sg:province":"North Holland",
    "wof:name":"Alty",
    "wof:placetype":"venue"
},
  "geometry": {"coordinates":[4.993717,52.517509],"type":"Point"}
}