{
  "type": "Feature",
  "properties": {
    "iso:country":"NL",
    "sg:address":"Zeestr 21",
    "sg:city":"Volendam",
    "sg:orig_category":"Warenhuizen",
    "sg:phone":"+31 299 350 284",
    "sg:postcode":"1131 ZD",
    "sg:province":"Noord-Holland",
    "wof:name":"Hema",
    "wof:placetype":"venue"
},
  "geometry": {"coordinates":[5.0721421242,52.4944000244],"type":"Point"}
}