{
  "type": "Feature",
  "properties": {
    "addr:full":"Bermweg 296 Capelle Aan Den Ijssel Zuid-Holland 2906 LH",
    "addr:housenumber":"296",
    "addr:postcode":"aan den ijssel;2906 lh",
    "addr:street":"Bermweg",
    "iso:country":"NL",
    "sg:address":"Bermweg 296",
    "sg:city":"Capelle Aan Den Ijssel",
    "sg:orig_category":"Hypotheken And Hypotheekbanken",
    "sg:phone":"+31 10 450 1275",
    "sg:postcode":"2906 LH",
    "sg:province":"Zuid-Holland",
    "wof:name":"Holland Hypotheek Groep",
    "wof:placetype":"venue"
},
  "geometry": {"coordinates":[4.578473,51.936581],"type":"Point"}
}