{
  "type": "Feature",
  "properties": {
    "iso:country":"NL",
    "sg:address":"Adriaan Volkersingel 5",
    "sg:city":"Sliedrecht",
    "sg:orig_category":"Marktonderzoekbureaus",
    "sg:phone":"+31 184 411 666",
    "sg:postcode":"3361 HA",
    "sg:province":"Zuid-Holland",
    "wof:name":"Tetragon Bv",
    "wof:placetype":"venue"
},
  "geometry": {"coordinates":[4.770213,51.816803],"type":"Point"}
}