{
  "type": "Feature",
  "properties": {
    "addr:full":"Stadionwg 1 Amsterdam North Holland 1077 RV",
    "addr:housenumber":"1",
    "addr:postcode":"1077 rv",
    "addr:street":"Stadionwg",
    "iso:country":"NL",
    "sg:address":"Stadionwg 1",
    "sg:city":"Amsterdam",
    "sg:orig_category":"Projectontwikkeling",
    "sg:phone":"+31 20 471 4033",
    "sg:postcode":"1077 RV",
    "sg:province":"North Holland",
    "sg:website":"http://www.vandam-invest.nl",
    "wof:name":"Vandam Bv",
    "wof:placetype":"venue"
},
  "geometry": {"coordinates":[4.884221,52.34911],"type":"Point"}
}