{
  "type": "Feature",
  "properties": {
    "addr:full":"Othello 22 Krimpen Ad Yssel Zuid-Holland 2926 PG",
    "addr:housenumber":"22",
    "addr:postcode":"2926 pg",
    "addr:street":"Othello",
    "iso:country":"NL",
    "sg:address":"Othello 22",
    "sg:city":"Krimpen Ad Yssel",
    "sg:orig_category":"Kantoorbenodigdheden",
    "sg:phone":"+31 180 514 295",
    "sg:postcode":"2926 PG",
    "sg:province":"Zuid-Holland",
    "wof:name":"Vervat, C J J",
    "wof:placetype":"venue"
},
  "geometry": {"coordinates":[4.6078300476,51.9104690552],"type":"Point"}
}