{
  "type": "Feature",
  "properties": {
    "addr:full":"Kochstraat 1 Maastricht Limburg 6216 ER",
    "addr:housenumber":"1",
    "addr:postcode":"6216 er",
    "addr:street":"Kochstraat",
    "iso:country":"NL",
    "sg:address":"Kochstraat 1",
    "sg:city":"Maastricht",
    "sg:orig_category":"Verzekeringen",
    "sg:phone":"+31 43 343 0479",
    "sg:postcode":"6216 ER",
    "sg:province":"Limburg",
    "wof:name":"R.M.M. Braun Assurantien",
    "wof:placetype":"venue"
},
  "geometry": {"coordinates":[5.6682,50.846775],"type":"Point"}
}