{
  "type": "Feature",
  "properties": {
    "addr:full":"Hoekeindsehof 10 Bleiswijk South Holland 2665 JZ",
    "addr:housenumber":"10",
    "addr:postcode":"2665 jz",
    "addr:street":"Hoekeindsehof",
    "iso:country":"NL",
    "sg:address":"Hoekeindsehof 10",
    "sg:city":"Bleiswijk",
    "sg:orig_category":"Makelaars In Onroerend Goed",
    "sg:phone":"+31 10 522 2266",
    "sg:postcode":"2665 JZ",
    "sg:province":"South Holland",
    "wof:name":"Areaal Bv",
    "wof:placetype":"venue"
},
  "geometry": {"coordinates":[4.52887,52.007576],"type":"Point"}
}