{
  "type": "Feature",
  "properties": {
    "addr:full":"Marktstraat 11 Delfzijl Groningen 9934 CH",
    "addr:housenumber":"11",
    "addr:postcode":"9934",
    "addr:street":"Marktstraat",
    "iso:country":"NL",
    "sg:address":"Marktstraat 11",
    "sg:city":"Delfzijl",
    "sg:orig_category":"Huishoudapparatuur, Televisies And Radio'S",
    "sg:phone":"+31 596 633 266",
    "sg:postcode":"9934 CH",
    "sg:province":"Groningen",
    "wof:name":"Radio Henk Kluin En Zoon",
    "wof:placetype":"venue"
},
  "geometry": {"coordinates":[6.928365,53.331158],"type":"Point"}
}