{
  "type": "Feature",
  "properties": {
    "addr:full":"Ruitercamp 227 Houten Utrecht 3992 BZ",
    "addr:housenumber":"227",
    "addr:postcode":"3992 bz",
    "addr:street":"Ruitercamp",
    "iso:country":"NL",
    "sg:address":"Ruitercamp 227",
    "sg:city":"Houten",
    "sg:orig_category":"Adviesbureaus Bedrijfsorganisatie",
    "sg:phone":"+31 30 638 1061",
    "sg:postcode":"3992 BZ",
    "sg:province":"Utrecht",
    "sg:website":"http://www.mawacs.nl",
    "wof:name":"Mawacs Bv",
    "wof:placetype":"venue"
},
  "geometry": {"coordinates":[5.151178,52.032272],"type":"Point"}
}