{
  "type": "Feature",
  "properties": {
    "iso:country":"NL",
    "sg:address":"Eemstr 6",
    "sg:city":"Heerlen",
    "sg:orig_category":"Adviesbureaus Bouwkunde",
    "sg:phone":"+31 45 572 3376",
    "sg:postcode":"6413 WG",
    "sg:province":"Limburg",
    "wof:name":"Hek",
    "wof:placetype":"venue"
},
  "geometry": {"coordinates":[5.960412,50.906178],"type":"Point"}
}