{
  "type": "Feature",
  "properties": {
    "addr:full":"Buitenlanden 32 Beverwyk North Holland 1948 PD",
    "addr:housenumber":"32",
    "addr:postcode":"1948 pd",
    "addr:street":"Buitenlanden;North",
    "iso:country":"NL",
    "sg:address":"Buitenlanden 32",
    "sg:city":"Beverwyk",
    "sg:orig_category":"Herenkleding",
    "sg:phone":"+31 251 214 528",
    "sg:postcode":"1948 PD",
    "sg:province":"North Holland",
    "wof:name":"American-Gigolo",
    "wof:placetype":"venue"
},
  "geometry": {"coordinates":[4.669076,52.480301],"type":"Point"}
}