{
  "type": "Feature",
  "properties": {
    "addr:full":"Adm Banckertwg 26 Leiden Zuid-Holland 2315 SR",
    "addr:housenumber":"26",
    "addr:postcode":"2315 sr",
    "iso:country":"NL",
    "sg:address":"Adm Banckertwg 26",
    "sg:city":"Leiden",
    "sg:orig_category":"Juwelen - Groothandel",
    "sg:phone":"+31 71 528 0461",
    "sg:postcode":"2315 SR",
    "sg:province":"Zuid-Holland",
    "wof:name":"Constant Bv",
    "wof:placetype":"venue"
},
  "geometry": {"coordinates":[4.513466,52.157722],"type":"Point"}
}