{
  "type": "Feature",
  "properties": {
    "addr:full":"V Boetzelaerstr 7 Alphen Aan Den Ryn Zuid-Holland 2406 BC",
    "addr:housenumber":"7",
    "addr:postcode":"2406 bc",
    "addr:street":"Boetzelaerstr;Aan Den Ryn",
    "iso:country":"NL",
    "sg:address":"V Boetzelaerstr 7",
    "sg:city":"Alphen Aan Den Ryn",
    "sg:orig_category":"Herenkleding",
    "sg:phone":"+31 172 493 887",
    "sg:postcode":"2406 BC",
    "sg:province":"Zuid-Holland",
    "wof:name":"Empire",
    "wof:placetype":"venue"
},
  "geometry": {"coordinates":[4.67368,52.12981],"type":"Point"}
}