{
  "type": "Feature",
  "properties": {
    "addr:full":"Populierstr 14 S Gravenhage Zuid-Holland 2565 ML",
    "addr:housenumber":"14;gravenhage",
    "addr:postcode":"2565 ml",
    "addr:street":"Populierstr;S",
    "iso:country":"NL",
    "sg:address":"Populierstr 14",
    "sg:city":"S Gravenhage",
    "sg:orig_category":"Antiquiteiten - Restauratie",
    "sg:phone":"+31 70 345 7054",
    "sg:postcode":"2565 ML",
    "sg:province":"Zuid-Holland",
    "wof:name":"Hoorn, Jeroen Ten",
    "wof:placetype":"venue"
},
  "geometry": {"coordinates":[4.26129,52.076382],"type":"Point"}
}