{
  "type": "Feature",
  "properties": {
    "addr:full":"Vd Weteringstr 6 Utrecht Utrecht 3581 EG",
    "addr:housenumber":"6",
    "addr:postcode":"3581 eg",
    "iso:country":"NL",
    "sg:address":"Vd Weteringstr 6",
    "sg:city":"Utrecht",
    "sg:orig_category":"Adviesbureaus Bedrijfsorganisatie",
    "sg:phone":"+31 30 233 3842",
    "sg:postcode":"3581 EG",
    "sg:province":"Utrecht",
    "wof:name":"Dwarshuis",
    "wof:placetype":"venue"
},
  "geometry": {"coordinates":[5.13447,52.089989],"type":"Point"}
}