{
  "type": "Feature",
  "properties": {
    "iso:country":"NL",
    "sg:address":"De Corantyn 69",
    "sg:city":"Zwaag",
    "sg:orig_category":"Geluidsinstallaties",
    "sg:phone":"+31 229 283 090",
    "sg:postcode":"1689 AN",
    "sg:province":"Noord-Holland",
    "wof:name":"Alcons",
    "wof:placetype":"venue"
},
  "geometry": {"coordinates":[5.067666,52.672585],"type":"Point"}
}