{
  "type": "Feature",
  "properties": {
    "addr:full":"Paviljoenweg 2 Wedde Groningen 9698 XX",
    "addr:housenumber":"2",
    "addr:postcode":"9698 xx",
    "addr:street":"Paviljoenweg",
    "iso:country":"NL",
    "sg:address":"Paviljoenweg 2",
    "sg:city":"Wedde",
    "sg:classifiers":[
        {
            "category":"Fast Food",
            "type":"Food & Drink"
        }
    ],
    "sg:phone":"+31 597 561 576",
    "sg:postcode":"9698 XX",
    "sg:province":"Groningen",
    "sg:tags":[
        "afhaal",
        "restaurant"
    ],
    "wof:name":"Kanoverhuur Wedderbergen",
    "wof:placetype":"venue"
},
  "geometry": {"coordinates":[7.076151,53.08709],"type":"Point"}
}