{
  "type": "Feature",
  "properties": {
    "iso:country":"NL",
    "sg:address":"Verl Schrans 6",
    "sg:city":"Leeuwarden",
    "sg:classifiers":[
        {
            "category":"Shopping",
            "subcategory":"Adult",
            "type":"Retail Goods"
        }
    ],
    "sg:phone":"+31 58 213 2888",
    "sg:postcode":"8932 NN",
    "sg:province":"Friesland",
    "sg:tags":[
        "lingerie",
        "en",
        "tricotage"
    ],
    "wof:name":"Mosselman",
    "wof:placetype":"venue"
},
  "geometry": {"coordinates":[5.797878,53.192532],"type":"Point"}
}