{
  "type": "Feature",
  "properties": {
    "iso:country":"NL",
    "sg:address":"Dorpsstr 95",
    "sg:city":"Krabbendyke",
    "sg:orig_category":"Loodgieters",
    "sg:phone":"+31 113 501 929",
    "sg:postcode":"4413 CD",
    "sg:province":"Zeeland",
    "wof:name":"Looff, De",
    "wof:placetype":"venue"
},
  "geometry": {"coordinates":[4.107604,51.431416],"type":"Point"}
}