{
  "type": "Feature",
  "properties": {
    "addr:full":"Zaaiviool 7 Berghem Noord-Brabant 5351 SR",
    "addr:housenumber":"7",
    "addr:postcode":"5351 sr",
    "addr:street":"Zaaiviool",
    "iso:country":"NL",
    "sg:address":"Zaaiviool 7",
    "sg:city":"Berghem",
    "sg:orig_category":"Voetbalverenigingen",
    "sg:phone":"+31 412 401 329",
    "sg:postcode":"5351 SR",
    "sg:province":"Noord-Brabant",
    "wof:name":"Berghem Sport",
    "wof:placetype":"venue"
},
  "geometry": {"coordinates":[5.57725,51.76823],"type":"Point"}
}