{
  "type": "Feature",
  "properties": {
    "addr:full":"Harmoniumstr 2 Almere Flevoland 1312 HN",
    "addr:housenumber":"2",
    "addr:postcode":"1312 hn",
    "addr:street":"Harmoniumstr;Flevoland",
    "iso:country":"NL",
    "sg:address":"Harmoniumstr 2",
    "sg:city":"Almere",
    "sg:orig_category":"Geluidsinstallaties - Verhuur",
    "sg:phone":"+31 36 536 3097",
    "sg:postcode":"1312 HN",
    "sg:province":"Flevoland",
    "wof:name":"Melissa'S Sound",
    "wof:placetype":"venue"
},
  "geometry": {"coordinates":[5.193571,52.370262],"type":"Point"}
}