{
  "type": "Feature",
  "properties": {
    "addr:full":"De Scherpenburgerwaard 7 Odijk Utrecht 3984 PB",
    "addr:housenumber":"7",
    "addr:postcode":"3984 pb",
    "addr:street":"De Scherpenburgerwaard",
    "iso:country":"NL",
    "sg:address":"De Scherpenburgerwaard 7",
    "sg:city":"Odijk",
    "sg:orig_category":"Public Relationbureaus",
    "sg:phone":"+31 30 656 7220",
    "sg:postcode":"3984 PB",
    "sg:province":"Utrecht",
    "wof:name":"Rienstra Marketing Consultancy Bv",
    "wof:placetype":"venue"
},
  "geometry": {"coordinates":[5.242868,52.051365],"type":"Point"}
}