{
  "type": "Feature",
  "properties": {
    "addr:full":"Kluizerdk 1 Valkenswaard Noord-Brabant 5554 XA",
    "addr:housenumber":"1",
    "addr:postcode":"5554 xa",
    "addr:street":"Kluizerdk",
    "iso:country":"NL",
    "sg:address":"Kluizerdk 1",
    "sg:city":"Valkenswaard",
    "sg:orig_category":"Accountants - Administratie- Consulenten En -Kantoren",
    "sg:phone":"+31 40 208 9000",
    "sg:postcode":"5554 XA",
    "sg:province":"Noord-Brabant",
    "wof:name":"Abab",
    "wof:placetype":"venue"
},
  "geometry": {"coordinates":[5.459158,51.33979],"type":"Point"}
}