{
  "type": "Feature",
  "properties": {
    "addr:full":"Newtonlaan 211 Utrecht Utrecht 3584 BH",
    "addr:housenumber":"211",
    "addr:postcode":"3584 bh",
    "addr:street":"Newtonlaan",
    "iso:country":"NL",
    "sg:address":"Newtonlaan 211",
    "sg:city":"Utrecht",
    "sg:orig_category":"Verzekeringen",
    "sg:phone":"+31 30 252 2335",
    "sg:postcode":"3584 BH",
    "sg:province":"Utrecht",
    "wof:name":"Heijnis & Koelman Bv",
    "wof:placetype":"venue"
},
  "geometry": {"coordinates":[5.147378,52.090206],"type":"Point"}
}