{
  "type": "Feature",
  "properties": {
    "iso:country":"NL",
    "sg:address":"Groenstr 109",
    "sg:city":"Prinsenbeek",
    "sg:orig_category":"Adviesbureaus",
    "sg:phone":"+31 76 542 2199",
    "sg:postcode":"4841 BC",
    "sg:province":"Noord-Brabant",
    "wof:name":"Ottenheim",
    "wof:placetype":"venue"
},
  "geometry": {"coordinates":[4.710148,51.592541],"type":"Point"}
}