{
  "type": "Feature",
  "properties": {
    "iso:country":"NL",
    "sg:address":"Helmondsewg 59",
    "sg:city":"Deurne",
    "sg:orig_category":"Verzekeringen - Verzekeringskantoren",
    "sg:phone":"+31 493 351 500",
    "sg:postcode":"5751 GB",
    "sg:province":"Noord-Brabant",
    "wof:name":"Vrehil",
    "wof:placetype":"venue"
},
  "geometry": {"coordinates":[5.786222,51.462406],"type":"Point"}
}