{
  "type": "Feature",
  "properties": {
    "addr:full":"Achterhoekerwg 1 Hooglanderveen Gelderland 3829 NA",
    "addr:housenumber":"1",
    "addr:postcode":"3829 na",
    "addr:street":"Achterhoekerwg",
    "iso:country":"NL",
    "sg:address":"Achterhoekerwg 1",
    "sg:city":"Hooglanderveen",
    "sg:orig_category":"Accountants - Administratie- Consulenten En -Kantoren",
    "sg:phone":"+31 33 257 1167",
    "sg:postcode":"3829 NA",
    "sg:province":"Gelderland",
    "wof:name":"Abw",
    "wof:placetype":"venue"
},
  "geometry": {"coordinates":[5.41417,52.212662],"type":"Point"}
}