{
  "type": "Feature",
  "properties": {
    "addr:full":"Hoofdweg 81 De Kwakel North Holland 1424 PD",
    "addr:housenumber":"81",
    "addr:postcode":"1424 pd",
    "addr:street":"Hoofdweg",
    "iso:country":"NL",
    "sg:address":"Hoofdweg 81",
    "sg:city":"De Kwakel",
    "sg:orig_category":"Bloemen And Planten",
    "sg:phone":"+31 297 327 544",
    "sg:postcode":"1424 PD",
    "sg:province":"North Holland",
    "wof:name":"Piet Schreurs De Kwakel Bv",
    "wof:placetype":"venue"
},
  "geometry": {"coordinates":[4.774323,52.241459],"type":"Point"}
}