{
  "type": "Feature",
  "properties": {
    "addr:full":"Edelstenenbaan 24 Ysselstein Ut Utrecht 3402 XD",
    "addr:housenumber":"24",
    "addr:postcode":"3402 xd",
    "addr:street":"Edelstenenbaan",
    "iso:country":"NL",
    "sg:address":"Edelstenenbaan 24",
    "sg:city":"Ysselstein Ut",
    "sg:orig_category":"Adviesbureaus Bedrijfsorganisatie",
    "sg:phone":"+31 30 687 0555",
    "sg:postcode":"3402 XD",
    "sg:province":"Utrecht",
    "wof:name":"Miltenburg, Van",
    "wof:placetype":"venue"
},
  "geometry": {"coordinates":[5.047931,52.030907],"type":"Point"}
}