{
  "type": "Feature",
  "properties": {
    "addr:full":"O Voorstr 4-6 Oud Beyerland Zuid-Holland 3262 JE",
    "addr:housenumber":"4-6",
    "addr:postcode":"3262 je",
    "addr:street":"Oud Beyerland",
    "iso:country":"NL",
    "sg:address":"O Voorstr 4-6",
    "sg:city":"Oud Beyerland",
    "sg:orig_category":"Gelegenheidskleding",
    "sg:phone":"+31 186 614 165",
    "sg:postcode":"3262 JE",
    "sg:province":"Zuid-Holland",
    "wof:name":"Gentlemen Mode",
    "wof:placetype":"venue"
},
  "geometry": {"coordinates":[4.41701,51.823044],"type":"Point"}
}