{
  "type": "Feature",
  "properties": {
    "iso:country":"NL",
    "sg:address":"Catharijnesingel 105",
    "sg:city":"Utrecht",
    "sg:orig_category":"Bedrijfs- And Managementsconsultants",
    "sg:phone":"+31 30 231 0751",
    "sg:postcode":"3511 GV",
    "sg:province":"Utrecht",
    "wof:name":"Mobo Promotions Bv",
    "wof:placetype":"venue"
},
  "geometry": {"coordinates":[5.120912,52.08062],"type":"Point"}
}