{
  "type": "Feature",
  "properties": {
    "addr:full":"Burg Rendorpstr 7 Amsterdam Noord-Holland 1064 EL",
    "addr:housenumber":"7;1064",
    "addr:postcode":"el",
    "addr:street":"Burg Rendorpstr",
    "iso:country":"NL",
    "sg:address":"Burg Rendorpstr 7",
    "sg:city":"Amsterdam",
    "sg:orig_category":"Mensendieck - Oefentherapeuten",
    "sg:phone":"+31 20 611 0503",
    "sg:postcode":"1064 EL",
    "sg:province":"Noord-Holland",
    "wof:name":"Galen, E L Van",
    "wof:placetype":"venue"
},
  "geometry": {"coordinates":[4.826702,52.373672],"type":"Point"}
}