{
  "type": "Feature",
  "properties": {
    "iso:country":"NL",
    "sg:address":"J V Scorelstr 52",
    "sg:city":"Heemskerk",
    "sg:orig_category":"Afslankinstituten",
    "sg:phone":"+31 251 238 783",
    "sg:postcode":"1961 EX",
    "sg:province":"Noord-Holland",
    "wof:name":"Slen World",
    "wof:placetype":"venue"
},
  "geometry": {"coordinates":[4.670686,52.511368],"type":"Point"}
}