{
  "type": "Feature",
  "properties": {
    "addr:full":"Heer Arnoudstraat 14 Oosterhout Nb Noord-Brabant 4902 BS",
    "addr:housenumber":"14",
    "addr:postcode":"4902 bs",
    "addr:street":"Heer Arnoudstraat",
    "iso:country":"NL",
    "sg:address":"Heer Arnoudstraat 14",
    "sg:city":"Oosterhout Nb",
    "sg:orig_category":"Zuivelproducten And Spijsoli?n Gh",
    "sg:phone":"+31 162 426 328",
    "sg:postcode":"4902 BS",
    "sg:province":"Noord-Brabant",
    "wof:name":"Schoenmakers Eierhandel Bv",
    "wof:placetype":"venue"
},
  "geometry": {"coordinates":[4.855833,51.636982],"type":"Point"}
}