{
  "type": "Feature",
  "properties": {
    "addr:full":"Postbus 125A Driebergen Rysenb 3970 AC",
    "addr:housenumber":"125a",
    "addr:postcode":"3970 ac",
    "addr:street":"Postbus;Rysenb",
    "iso:country":"NL",
    "sg:address":"Postbus 125A",
    "sg:city":"Driebergen Rysenb",
    "sg:orig_category":"Verenigingen En Stichtingen",
    "sg:phone":"+31 343 513 434",
    "sg:postcode":"3970 AC",
    "sg:website":"http://www.ouders.net",
    "wof:name":"Ouders & Coo",
    "wof:placetype":"venue"
},
  "geometry": {"coordinates":[5.27987,52.053322],"type":"Point"}
}