{
  "type": "Feature",
  "properties": {
    "addr:full":"Houtduif 8 Etten Leur Noord-Brabant 4872 MH",
    "addr:housenumber":"8",
    "addr:postcode":"4872 mh",
    "addr:street":"Houtduif",
    "iso:country":"NL",
    "sg:address":"Houtduif 8",
    "sg:city":"Etten Leur",
    "sg:orig_category":"Bloemen En Planten",
    "sg:phone":"+31 76 502 0133",
    "sg:postcode":"4872 MH",
    "sg:province":"Noord-Brabant",
    "wof:name":"Mistletoe, De",
    "wof:placetype":"venue"
},
  "geometry": {"coordinates":[4.65007,51.576263],"type":"Point"}
}