{
  "type": "Feature",
  "properties": {
    "addr:full":"Aalsvoort 53 Lochem Gelderland 7241 MA",
    "addr:housenumber":"53",
    "addr:postcode":"7241 ma",
    "addr:street":"Aalsvoort;Gelderland",
    "iso:country":"NL",
    "sg:address":"Aalsvoort 53",
    "sg:city":"Lochem",
    "sg:orig_category":"Koeltechniek",
    "sg:phone":"+31 573 255 025",
    "sg:postcode":"7241 MA",
    "sg:province":"Gelderland",
    "wof:name":"Ecr-Lochem",
    "wof:placetype":"venue"
},
  "geometry": {"coordinates":[6.387573,52.169094],"type":"Point"}
}