{
  "type": "Feature",
  "properties": {
    "addr:full":"Oude Vlierweg 13 Ommen Overijssel 7731 SL",
    "addr:housenumber":"13",
    "addr:postcode":"7731 sl",
    "addr:street":"Oude Vlierweg",
    "iso:country":"NL",
    "sg:address":"Oude Vlierweg 13",
    "sg:city":"Ommen",
    "sg:orig_category":"Hoger Onderwijs",
    "sg:phone":"+31 529 453 938",
    "sg:postcode":"7731 SL",
    "sg:province":"Overijssel",
    "wof:name":"E.J. Dijk",
    "wof:placetype":"venue"
},
  "geometry": {"coordinates":[6.430494,52.531719],"type":"Point"}
}