{
  "type": "Feature",
  "properties": {
    "addr:full":"Dubbelsteynln O 160 Dordrecht Zuid-Holland 3319 EG",
    "addr:housenumber":"160",
    "addr:postcode":"3319 eg",
    "iso:country":"NL",
    "sg:address":"Dubbelsteynln O 160",
    "sg:city":"Dordrecht",
    "sg:orig_category":"Haptotherapeuten",
    "sg:phone":"+31 78 616 7656",
    "sg:postcode":"3319 EG",
    "sg:province":"Zuid-Holland",
    "wof:name":"Haptonomie, Praktijk Voor",
    "wof:placetype":"venue"
},
  "geometry": {"coordinates":[4.707275,51.794006],"type":"Point"}
}