{
  "type": "Feature",
  "properties": {
    "addr:full":"Van Egmondlaan 27 Waalre Noord-Brabant 5583 VA",
    "addr:housenumber":"27",
    "addr:postcode":"5583",
    "addr:street":"Van Egmondlaan",
    "iso:country":"NL",
    "sg:address":"Van Egmondlaan 27",
    "sg:city":"Waalre",
    "sg:orig_category":"Technische Studies And Onderzoek",
    "sg:phone":"+31 40 223 0171",
    "sg:postcode":"5583 VA",
    "sg:province":"Noord-Brabant",
    "wof:name":"Vac Aircraft Services Bv",
    "wof:placetype":"venue"
},
  "geometry": {"coordinates":[5.484382,51.400379],"type":"Point"}
}