{
  "type": "Feature",
  "properties": {
    "addr:full":"Herenweg 20 Heemstede Noord-Holland 2104 MK",
    "addr:housenumber":"20",
    "addr:postcode":"2104",
    "addr:street":"Herenweg",
    "iso:country":"NL",
    "sg:address":"Herenweg 20",
    "sg:city":"Heemstede",
    "sg:orig_category":"Schilderwerk",
    "sg:phone":"+31 294 291 546",
    "sg:postcode":"2104 MK",
    "sg:province":"Noord-Holland",
    "wof:name":"Schilder-, Glas- En Wandafwerkingsbedr. H. Blom",
    "wof:placetype":"venue"
},
  "geometry": {"coordinates":[4.60134,52.3339],"type":"Point"}
}