{
  "type": "Feature",
  "properties": {
    "iso:country":"NL",
    "sg:address":"Copernicusstraat 122",
    "sg:city":"'S Gravenhage",
    "sg:orig_category":"Paramedische Behandelingen",
    "sg:phone":"+31 70 346 8288",
    "sg:postcode":"2561 XC",
    "sg:province":"Zuid-Holland",
    "wof:name":"C.G.U. Eckert",
    "wof:placetype":"venue"
},
  "geometry": {"coordinates":[4.279575,52.077366],"type":"Point"}
}