{
  "type": "Feature",
  "properties": {
    "addr:full":"Woldstraat 3 Meppel Drenthe 7941 LE",
    "addr:housenumber":"3",
    "addr:postcode":"7941 le",
    "addr:street":"Woldstraat",
    "iso:country":"NL",
    "sg:address":"Woldstraat 3",
    "sg:city":"Meppel",
    "sg:orig_category":"Diverse Grafische Activiteiten",
    "sg:phone":"+31 522 242 448",
    "sg:postcode":"7941 LE",
    "sg:province":"Drenthe",
    "wof:name":"Kampman Ontwerpwerkzaamheden",
    "wof:placetype":"venue"
},
  "geometry": {"coordinates":[6.190639,52.697914],"type":"Point"}
}