{
  "type": "Feature",
  "properties": {
    "iso:country":"NL",
    "sg:address":"Boulev Bankert 266",
    "sg:city":"Vlissingen",
    "sg:classifiers":[
        {
            "category":"Travel",
            "subcategory":"Hotels & Motels",
            "type":"Entertainment"
        }
    ],
    "sg:phone":"+31 118 410 502",
    "sg:postcode":"4382 AC",
    "sg:province":"Zeeland",
    "sg:website":"http://www.hotelarion.nl",
    "wof:name":"Arion Grand Hotel Boulevard",
    "wof:placetype":"venue"
},
  "geometry": {"coordinates":[3.563988,51.446182],"type":"Point"}
}