{
  "type": "Feature",
  "properties": {
    "addr:full":"Koningin Wilhelminaweg 22 Zaltbommel Gelderland 5301 GH",
    "addr:housenumber":"22",
    "addr:postcode":"5301 gh",
    "addr:street":"Koningin Wilhelminaweg;Gelderland",
    "iso:country":"NL",
    "sg:address":"Koningin Wilhelminaweg 22",
    "sg:city":"Zaltbommel",
    "sg:orig_category":"Verzekeringen",
    "sg:phone":"+31 418 512 752",
    "sg:postcode":"5301 GH",
    "sg:province":"Gelderland",
    "wof:name":"Assurantiekantoor G.W. Ansing Bv",
    "wof:placetype":"venue"
},
  "geometry": {"coordinates":[5.253772,51.809696],"type":"Point"}
}