{
  "type": "Feature",
  "properties": {
    "addr:full":"Leeuwerikstr 25 Made California 4921 VM",
    "addr:housenumber":"25",
    "addr:postcode":"4921 vm",
    "addr:street":"Leeuwerikstr",
    "iso:country":"NL",
    "sg:address":"Leeuwerikstr 25",
    "sg:city":"Made",
    "sg:orig_category":"Begraafplaatsen",
    "sg:phone":"+31 162 684 511",
    "sg:postcode":"4921 VM",
    "sg:province":"California",
    "wof:name":"Alg Begraafplaats",
    "wof:placetype":"venue"
},
  "geometry": {"coordinates":[-120.08332799999999,36.920166],"type":"Point"}
}