{
  "type": "Feature",
  "properties": {
    "addr:full":"Textielstraat 46 Oldenzaal Overijssel 7575 CA",
    "addr:housenumber":"46",
    "addr:postcode":"7575 ca",
    "addr:street":"Textielstraat",
    "iso:country":"NL",
    "sg:address":"Textielstraat 46",
    "sg:city":"Oldenzaal",
    "sg:orig_category":"Diverse Grafische Activiteiten",
    "sg:phone":"+31 541 531 001",
    "sg:postcode":"7575 CA",
    "sg:province":"Overijssel",
    "wof:name":"Pre Press Service Verhaag Bv",
    "wof:placetype":"venue"
},
  "geometry": {"coordinates":[6.92371,52.303036],"type":"Point"}
}