{
  "type": "Feature",
  "properties": {
    "addr:full":"St Pietersberg 40A De Meern Utrecht 3453 PJ",
    "addr:housenumber":"40a",
    "addr:postcode":"3453 pj",
    "addr:street":"St Pietersberg",
    "iso:country":"NL",
    "sg:address":"St Pietersberg 40A",
    "sg:city":"De Meern",
    "sg:orig_category":"Kinderopvang",
    "sg:phone":"+31 30 666 7922",
    "sg:postcode":"3453 PJ",
    "sg:province":"Utrecht",
    "wof:name":"Okido",
    "wof:placetype":"venue"
},
  "geometry": {"coordinates":[5.016403,52.082943],"type":"Point"}
}