{
  "type": "Feature",
  "properties": {
    "addr:full":"Nieboerweg 73 'S Gravenhage South Holland 2583 JV",
    "addr:housenumber":"73",
    "addr:postcode":"2583 jv",
    "addr:street":"Nieboerweg;' S Gravenhage",
    "iso:country":"NL",
    "sg:address":"Nieboerweg 73",
    "sg:city":"'S Gravenhage",
    "sg:classifiers":[
        {
            "category":"Fast Food",
            "type":"Food & Drink"
        }
    ],
    "sg:phone":"+31 70 352 2493",
    "sg:postcode":"2583 JV",
    "sg:province":"South Holland",
    "sg:tags":[
        "afhaal",
        "restaurant"
    ],
    "wof:name":"Cafetaria De 3 B'S",
    "wof:placetype":"venue"
},
  "geometry": {"coordinates":[4.26264,52.090504],"type":"Point"}
}