{
  "type": "Feature",
  "properties": {
    "addr:full":"Vrankenstr 62 Dordrecht South Holland 3311 SW",
    "addr:housenumber":"62",
    "addr:postcode":"3311 sw",
    "addr:street":"Vrankenstr",
    "iso:country":"NL",
    "sg:address":"Vrankenstr 62",
    "sg:city":"Dordrecht",
    "sg:orig_category":"Plafonds",
    "sg:phone":"+31 78 631 2209",
    "sg:postcode":"3311 SW",
    "sg:province":"South Holland",
    "wof:name":"Verhaar, G J",
    "wof:placetype":"venue"
},
  "geometry": {"coordinates":[4.672522,51.816669],"type":"Point"}
}