{
  "type": "Feature",
  "properties": {
    "iso:country":"NL",
    "sg:address":"Arkelstraat 128",
    "sg:city":"Gorinchem",
    "sg:classifiers":[
        {
            "category":"Shopping",
            "subcategory":"News",
            "type":"Retail Goods"
        }
    ],
    "sg:phone":"+31 183 654 500",
    "sg:postcode":"4201 KH",
    "sg:province":"Zuid-Holland",
    "sg:tags":[
        "maandbladen",
        "en",
        "week-"
    ],
    "wof:name":"Gorcumse Courant",
    "wof:placetype":"venue"
},
  "geometry": {"coordinates":[4.9753961563,51.8321418762],"type":"Point"}
}