{
  "type": "Feature",
  "properties": {
    "addr:full":"Elbestr 4 Veghel North Brabant 5463 AG",
    "addr:housenumber":"4",
    "addr:postcode":"5463",
    "addr:street":"Elbestr",
    "iso:country":"NL",
    "sg:address":"Elbestr 4",
    "sg:city":"Veghel",
    "sg:orig_category":"Kappers",
    "sg:phone":"+31 413 353 844",
    "sg:postcode":"5463 AG",
    "sg:province":"North Brabant",
    "wof:name":"Knip, De",
    "wof:placetype":"venue"
},
  "geometry": {"coordinates":[5.541726,51.610676],"type":"Point"}
}