{
  "type": "Feature",
  "properties": {
    "addr:full":"Asschatterweg 211 Leusden Utrecht 3831 JP",
    "addr:housenumber":"211",
    "addr:postcode":"3831 jp",
    "addr:street":"Asschatterweg",
    "iso:country":"NL",
    "sg:address":"Asschatterweg 211",
    "sg:city":"Leusden",
    "sg:orig_category":"Hoefdierhouderijen",
    "sg:phone":"+31 342 452 690",
    "sg:postcode":"3831 JP",
    "sg:province":"Utrecht",
    "wof:name":"Secretariaat Nmprs",
    "wof:placetype":"venue"
},
  "geometry": {"coordinates":[5.458653,52.131203],"type":"Point"}
}