{
  "type": "Feature",
  "properties": {
    "iso:country":"NL",
    "sg:address":"Westhoek 10",
    "sg:city":"Wittem",
    "sg:orig_category":"Voetbalverenigingen",
    "sg:phone":"+31 43 451 2323",
    "sg:postcode":"6286 BS",
    "sg:province":"Limburg",
    "wof:name":"Nijswiller",
    "wof:placetype":"venue"
},
  "geometry": {"coordinates":[5.91146,50.81403],"type":"Point"}
}