{
  "type": "Feature",
  "properties": {
    "addr:full":"Orpheuslaan 21 Eindhoven Noord-Brabant 5631 BP",
    "addr:housenumber":"21",
    "addr:postcode":"5631 bp",
    "addr:street":"Orpheuslaan",
    "iso:country":"NL",
    "sg:address":"Orpheuslaan 21",
    "sg:city":"Eindhoven",
    "sg:orig_category":"Artsen And Specialisten",
    "sg:phone":"+31 40 243 0001",
    "sg:postcode":"5631 BP",
    "sg:province":"Noord-Brabant",
    "wof:name":"A.J.M. Dekkers",
    "wof:placetype":"venue"
},
  "geometry": {"coordinates":[5.490478,51.457657],"type":"Point"}
}