{
  "type": "Feature",
  "properties": {
    "addr:full":"Berenkoog 34 Alkmaar North Holland 1822 BJ",
    "addr:housenumber":"34",
    "addr:postcode":"1822 bj",
    "addr:street":"Berenkoog",
    "iso:country":"NL",
    "sg:address":"Berenkoog 34",
    "sg:city":"Alkmaar",
    "sg:orig_category":"Verf En Lak - Fabrieken En Groothandel",
    "sg:phone":"+31 72 561 7216",
    "sg:postcode":"1822 BJ",
    "sg:province":"North Holland",
    "wof:name":"Sigma Bv",
    "wof:placetype":"venue"
},
  "geometry": {"coordinates":[4.785961,52.647858],"type":"Point"}
}