{
  "type": "Feature",
  "properties": {
    "iso:country":"NL",
    "sg:address":"J P Coenstraat 9",
    "sg:city":"Enschede",
    "sg:classifiers":[
        {
            "category":"Education",
            "subcategory":"Preschool",
            "type":"Public Place"
        }
    ],
    "sg:phone":"+31 53 431 0005",
    "sg:postcode":"7541 BP",
    "sg:province":"Overijssel",
    "sg:tags":[
        "kleuteronderwijs",
        "basis-"
    ],
    "wof:name":"Prins Bernhardschool",
    "wof:placetype":"venue"
},
  "geometry": {"coordinates":[6.908995,52.210392],"type":"Point"}
}