{
  "type": "Feature",
  "properties": {
    "addr:full":"Electronwg 17 Roosendaal North Brabant 4706 PP",
    "addr:housenumber":"17",
    "addr:postcode":"4706 pp",
    "addr:street":"Electronwg",
    "iso:country":"NL",
    "sg:address":"Electronwg 17",
    "sg:city":"Roosendaal",
    "sg:orig_category":"Zoetwaren - Fabrieken En Groothandel",
    "sg:phone":"+31 165 561 800",
    "sg:postcode":"4706 PP",
    "sg:province":"North Brabant",
    "wof:name":"Lekkerland Roosendaal",
    "wof:placetype":"venue"
},
  "geometry": {"coordinates":[4.498445,51.537395],"type":"Point"}
}