{
  "type": "Feature",
  "properties": {
    "addr:full":"Veenkade 5 'S Gravenhage South Holland 2513 EE",
    "addr:housenumber":"5 '",
    "addr:postcode":"2513 ee",
    "addr:street":"Veenkade",
    "iso:country":"NL",
    "sg:address":"Veenkade 5",
    "sg:city":"'S Gravenhage",
    "sg:classifiers":[
        {
            "category":"Travel",
            "subcategory":"Hotels & Motels",
            "type":"Entertainment"
        }
    ],
    "sg:phone":"+31 70 346 3657",
    "sg:postcode":"2513 EE",
    "sg:province":"South Holland",
    "wof:name":"Hotel 'T Centrum",
    "wof:placetype":"venue"
},
  "geometry": {"coordinates":[4.302927,52.080124],"type":"Point"}
}