{
  "type": "Feature",
  "properties": {
    "iso:country":"NL",
    "sg:address":"C Buskenstr 132",
    "sg:city":"Vlissingen",
    "sg:classifiers":[
        {
            "category":"Travel",
            "subcategory":"Hotels & Motels",
            "type":"Entertainment"
        }
    ],
    "sg:phone":"+31 118 412 726",
    "sg:postcode":"4381 LH",
    "sg:province":"Zeeland",
    "wof:name":"Boulevard",
    "wof:placetype":"venue"
},
  "geometry": {"coordinates":[3.570382,51.44429],"type":"Point"}
}