{
  "type": "Feature",
  "properties": {
    "addr:full":"Noorderstr 232 Sappemeer Groningen 9611 AR",
    "addr:housenumber":"232",
    "addr:postcode":"9611",
    "iso:country":"NL",
    "sg:address":"Noorderstr 232",
    "sg:city":"Sappemeer",
    "sg:orig_category":"Kappers",
    "sg:phone":"+31 598 392 473",
    "sg:postcode":"9611 AR",
    "sg:province":"Groningen",
    "wof:name":"La Vie, De",
    "wof:placetype":"venue"
},
  "geometry": {"coordinates":[6.790805,53.164043],"type":"Point"}
}