{
  "type": "Feature",
  "properties": {
    "addr:full":"Sterrenburgstr 25 Spykenisse Zuid-Holland 3201 RB",
    "addr:housenumber":"25",
    "addr:postcode":"3201 rb",
    "addr:street":"Sterrenburgstr",
    "iso:country":"NL",
    "sg:address":"Sterrenburgstr 25",
    "sg:city":"Spykenisse",
    "sg:orig_category":"Meubelmakerijen",
    "sg:phone":"+31 181 698 557",
    "sg:postcode":"3201 RB",
    "sg:province":"Zuid-Holland",
    "sg:website":"http://www.drvinyl.com",
    "wof:name":"Vinyl Spijkenisse",
    "wof:placetype":"venue"
},
  "geometry": {"coordinates":[4.33046,51.847904],"type":"Point"}
}