{
  "type": "Feature",
  "properties": {
    "addr:full":"Dr. Ariensstraat 14 Haaksbergen NL.08 7481 JL",
    "addr:housenumber":"14;nl.08",
    "addr:postcode":"7481 jl",
    "addr:street":"Ariensstraat",
    "iso:country":"NL",
    "sg:address":"Dr. Ariensstraat 14",
    "sg:city":"Haaksbergen",
    "sg:classifiers":[
        {
            "category":"Professional",
            "subcategory":"Accounting & Tax Preparation",
            "type":"Services"
        }
    ],
    "sg:phone":"+31 53 572 3269",
    "sg:postcode":"7481 JL",
    "sg:province":"NL.08",
    "sg:tags":[
        "accountant"
    ],
    "wof:name":"Accountantskantoor L.F.A. Leferink Bv",
    "wof:placetype":"venue"
},
  "geometry": {"coordinates":[6.737685,52.1562],"type":"Point"}
}