{
  "type": "Feature",
  "properties": {
    "addr:full":"V Lennepwg 25 S Gravenhage Zuid-Holland 2597 LG",
    "addr:housenumber":"25;gravenhage",
    "addr:postcode":"2597 lg",
    "addr:street":"S",
    "iso:country":"NL",
    "sg:address":"V Lennepwg 25",
    "sg:city":"S Gravenhage",
    "sg:orig_category":"Adviesbureaus Bedrijfsorganisatie",
    "sg:phone":"+31 70 358 5715",
    "sg:postcode":"2597 LG",
    "sg:province":"Zuid-Holland",
    "sg:website":"http://www.euro-logistics.nl",
    "wof:name":"Eurologistics Bv",
    "wof:placetype":"venue"
},
  "geometry": {"coordinates":[4.31817,52.11031],"type":"Point"}
}