{
  "type": "Feature",
  "properties": {
    "addr:full":"Pottbeckerstr 68 Steyl Limburg 5935 TD",
    "addr:housenumber":"68",
    "addr:postcode":"5935 td",
    "addr:street":"Pottbeckerstr",
    "iso:country":"NL",
    "sg:address":"Pottbeckerstr 68",
    "sg:city":"Steyl",
    "sg:orig_category":"Nagelstudio'S",
    "sg:phone":"+31 77 373 6056",
    "sg:postcode":"5935 TD",
    "sg:province":"Limburg",
    "wof:name":"Brigitte",
    "wof:placetype":"venue"
},
  "geometry": {"coordinates":[6.123025,51.333511],"type":"Point"}
}