{
  "type": "Feature",
  "properties": {
    "addr:full":"Jansbuitensngl 28 Arnhem Gelderland 6811 AE",
    "addr:housenumber":"28",
    "addr:postcode":"6811 ae",
    "addr:street":"Jansbuitensngl",
    "iso:country":"NL",
    "sg:address":"Jansbuitensngl 28",
    "sg:city":"Arnhem",
    "sg:orig_category":"Verenigingen En Stichtingen",
    "sg:phone":"+31 26 443 3511",
    "sg:postcode":"6811 AE",
    "sg:province":"Gelderland",
    "wof:name":"Groote Soci\u00ebteit",
    "wof:placetype":"venue"
},
  "geometry": {"coordinates":[5.910436,51.984665],"type":"Point"}
}