{
  "type": "Feature",
  "properties": {
    "addr:full":"Parallelweg 89 De Krim Overijssel 7782 PJ",
    "addr:housenumber":"89",
    "addr:postcode":"7782 pj",
    "addr:street":"Parallelweg",
    "iso:country":"NL",
    "sg:address":"Parallelweg 89",
    "sg:city":"De Krim",
    "sg:classifiers":[
        {
            "category":"Bakery",
            "type":"Food & Drink"
        }
    ],
    "sg:phone":"+31 524 571 804",
    "sg:postcode":"7782 PJ",
    "sg:province":"Overijssel",
    "sg:tags":[
        "brood",
        "banket"
    ],
    "wof:name":"L. Wassen/De Mikke",
    "wof:placetype":"venue"
},
  "geometry": {"coordinates":[6.649091,52.65395],"type":"Point"}
}