{
  "type": "Feature",
  "properties": {
    "iso:country":"NL",
    "sg:address":"Dorpsstr 3",
    "sg:city":"Bennekom",
    "sg:orig_category":"Fotoreportages",
    "sg:phone":"+31 318 430 607",
    "sg:postcode":"6721 JH",
    "sg:province":"Gelderland",
    "wof:name":"Koster, Gert Jan",
    "wof:placetype":"venue"
},
  "geometry": {"coordinates":[5.676273,51.99942],"type":"Point"}
}