{
  "type": "Feature",
  "properties": {
    "iso:country":"NL",
    "sg:address":"Colosseum 65",
    "sg:city":"Enschede",
    "sg:orig_category":"Voetbalverenigingen",
    "sg:phone":"+31 53 852 5525",
    "sg:postcode":"7521 PP",
    "sg:province":"Overijssel",
    "sg:website":"http://www.geocities.com/Coloseum/Arena/4846",
    "wof:name":"Fc Twente 65, Sticht",
    "wof:placetype":"venue"
},
  "geometry": {"coordinates":[6.836217,52.238083],"type":"Point"}
}