{
  "type": "Feature",
  "properties": {
    "addr:full":"Spaarnwouderstr 63 Haarlem Noord-Holland 2011 AB",
    "addr:housenumber":"63",
    "addr:postcode":"2011 ab",
    "addr:street":"Spaarnwouderstr",
    "iso:country":"NL",
    "sg:address":"Spaarnwouderstr 63",
    "sg:city":"Haarlem",
    "sg:orig_category":"Antiquiteiten - Restauratie",
    "sg:phone":"+31 23 533 6445",
    "sg:postcode":"2011 AB",
    "sg:province":"Noord-Holland",
    "wof:name":"Bos M W Van Den Antiekrestauratie",
    "wof:placetype":"venue"
},
  "geometry": {"coordinates":[4.644598,52.380352],"type":"Point"}
}