{
  "type": "Feature",
  "properties": {
    "iso:country":"NL",
    "sg:address":"Ludenswg 37",
    "sg:city":"Winschoten",
    "sg:classifiers":[
        {
            "category":"Retail",
            "subcategory":"Auto Repair",
            "type":"Services"
        }
    ],
    "sg:phone":"+31 597 412 517",
    "sg:postcode":"9675 AM",
    "sg:province":"Groningen",
    "sg:tags":[
        "garage"
    ],
    "wof:name":"Bruin Autotechniek, De",
    "wof:placetype":"venue"
},
  "geometry": {"coordinates":[7.037238,53.149349],"type":"Point"}
}