{
  "type": "Feature",
  "properties": {
    "addr:full":"Dorpsstraat 12 Rosmalen Noord-Brabant 5241 EC",
    "addr:housenumber":"12",
    "addr:postcode":"5241 ec",
    "addr:street":"Dorpsstraat",
    "iso:country":"NL",
    "sg:address":"Dorpsstraat 12",
    "sg:city":"Rosmalen",
    "sg:classifiers":[
        {
            "category":"Fast Food",
            "type":"Food & Drink"
        }
    ],
    "sg:phone":"+31 73 521 4363",
    "sg:postcode":"5241 EC",
    "sg:province":"Noord-Brabant",
    "sg:tags":[
        "afhaal",
        "restaurant"
    ],
    "wof:name":"De Luifel Bv",
    "wof:placetype":"venue"
},
  "geometry": {"coordinates":[5.362406,51.718468],"type":"Point"}
}