{
  "type": "Feature",
  "properties": {
    "addr:full":"Oudvaart 1 Sneek Friesland 8605 BX",
    "addr:housenumber":"1",
    "addr:postcode":"8605 bx",
    "addr:street":"Oudvaart",
    "iso:country":"NL",
    "sg:address":"Oudvaart 1",
    "sg:city":"Sneek",
    "sg:orig_category":"Autokeuringen",
    "sg:phone":"+31 515 413 091",
    "sg:postcode":"8605 BX",
    "sg:province":"Friesland",
    "wof:name":"Hoppe'S Automobielbedrijf",
    "wof:placetype":"venue"
},
  "geometry": {"coordinates":[5.66197,53.033459],"type":"Point"}
}