{
  "type": "Feature",
  "properties": {
    "addr:full":"J J Slauerhoffln 15 Delft South Holland 2624 JV",
    "addr:housenumber":"15",
    "addr:postcode":"2624 jv",
    "iso:country":"NL",
    "sg:address":"J J Slauerhoffln 15",
    "sg:city":"Delft",
    "sg:orig_category":"Verzekeringen - Verzekeringskantoren",
    "sg:phone":"+31 15 213 7417",
    "sg:postcode":"2624 JV",
    "sg:province":"South Holland",
    "wof:name":"Naaborg Bv",
    "wof:placetype":"venue"
},
  "geometry": {"coordinates":[4.35634,51.995491],"type":"Point"}
}