{
  "type": "Feature",
  "properties": {
    "iso:country":"NL",
    "sg:address":"Postbus 40179",
    "sg:city":"Zwolle",
    "sg:orig_category":"Artiesten",
    "sg:phone":"+31 6 16624022",
    "sg:postcode":"8004  D",
    "sg:province":"Gelderland",
    "wof:name":"O, Die",
    "wof:placetype":"venue"
},
  "geometry": {"coordinates":[6.088738,52.512566],"type":"Point"}
}