{
  "type": "Feature",
  "properties": {
    "addr:full":"F Kruitstr 26 Schagen North Holland 1742 SZ",
    "addr:housenumber":"26",
    "addr:postcode":"1742 sz",
    "iso:country":"NL",
    "sg:address":"F Kruitstr 26",
    "sg:city":"Schagen",
    "sg:orig_category":"Kappers",
    "sg:phone":"+31 224 297 780",
    "sg:postcode":"1742 SZ",
    "sg:province":"North Holland",
    "wof:name":"Artistique",
    "wof:placetype":"venue"
},
  "geometry": {"coordinates":[4.8044247627,52.7767791748],"type":"Point"}
}