{
  "type": "Feature",
  "properties": {
    "addr:full":"Kampstraat 34 Steenwijk Overijssel 8331 GE",
    "addr:housenumber":"34",
    "addr:postcode":"8331",
    "addr:street":"Kampstraat",
    "iso:country":"NL",
    "sg:address":"Kampstraat 34",
    "sg:city":"Steenwijk",
    "sg:orig_category":"Technische Studies And Onderzoek",
    "sg:phone":"+31 521 321 455",
    "sg:postcode":"8331 GE",
    "sg:province":"Overijssel",
    "wof:name":"Utapia",
    "wof:placetype":"venue"
},
  "geometry": {"coordinates":[6.123313,52.784409],"type":"Point"}
}