{
  "type": "Feature",
  "properties": {
    "addr:full":"N V Eschstr 88 Oisterwyk Noord-Brabant 5061 VW",
    "addr:housenumber":"88",
    "addr:postcode":"5061 vw",
    "addr:street":"N V Eschstr",
    "iso:country":"NL",
    "sg:address":"N V Eschstr 88",
    "sg:city":"Oisterwyk",
    "sg:orig_category":"Elektrotechnische Installatiebureaus",
    "sg:phone":"+31 13 522 0751",
    "sg:postcode":"5061 VW",
    "sg:province":"Noord-Brabant",
    "wof:name":"Berkel Electro, Van",
    "wof:placetype":"venue"
},
  "geometry": {"coordinates":[5.1821,51.57653],"type":"Point"}
}