{
  "type": "Feature",
  "properties": {
    "addr:full":"Adonislaan 85 Helmond North Brabant 5702 GH",
    "addr:housenumber":"85",
    "addr:postcode":"5702 gh",
    "addr:street":"Adonislaan",
    "iso:country":"NL",
    "sg:address":"Adonislaan 85",
    "sg:city":"Helmond",
    "sg:classifiers":[
        {
            "category":"Fast Food",
            "type":"Food & Drink"
        }
    ],
    "sg:phone":"+31 492 538 054",
    "sg:postcode":"5702 GH",
    "sg:province":"North Brabant",
    "sg:tags":[
        "afhaal",
        "restaurant"
    ],
    "wof:name":"Cafetaria De Braak",
    "wof:placetype":"venue"
},
  "geometry": {"coordinates":[5.674518,51.497761],"type":"Point"}
}