{
  "type": "Feature",
  "properties": {
    "addr:full":"Zwartewg 16 Noordwyk Zh Zuid-Holland 2201 AB",
    "addr:housenumber":"16",
    "addr:postcode":"2201 ab",
    "addr:street":"Zwartewg",
    "iso:country":"NL",
    "sg:address":"Zwartewg 16",
    "sg:city":"Noordwyk Zh",
    "sg:orig_category":"Verhuizingen",
    "sg:phone":"+31 71 361 7917",
    "sg:postcode":"2201 AB",
    "sg:province":"Zuid-Holland",
    "wof:name":"Binnendijk, H",
    "wof:placetype":"venue"
},
  "geometry": {"coordinates":[4.4477,52.234261],"type":"Point"}
}