{
  "type": "Feature",
  "properties": {
    "iso:country":"NL",
    "sg:address":"Grotestraat 152",
    "sg:city":"Drunen",
    "sg:orig_category":"Werving And Selectie Van Tijdelijk Personeel And Uitzendkantoren",
    "sg:phone":"+31 416 379 699",
    "sg:postcode":"5151 BN",
    "sg:province":"Noord-Brabant",
    "wof:name":"Randstad Uitzendbureau Bv",
    "wof:placetype":"venue"
},
  "geometry": {"coordinates":[5.1346921921,51.6865386963],"type":"Point"}
}