{
  "type": "Feature",
  "properties": {
    "addr:full":"Parkwg 225 Voorburg Zuid-Holland 2271 BB",
    "addr:housenumber":"225",
    "addr:postcode":"2271 bb",
    "iso:country":"NL",
    "sg:address":"Parkwg 225",
    "sg:city":"Voorburg",
    "sg:orig_category":"Verzekeringen - Verzekeringskantoren",
    "sg:phone":"+31 70 386 6268",
    "sg:postcode":"2271 BB",
    "sg:province":"Zuid-Holland",
    "wof:name":"Drie Steden Bv, Ass Kantoor De",
    "wof:placetype":"venue"
},
  "geometry": {"coordinates":[4.371501,52.074738],"type":"Point"}
}