{
  "type": "Feature",
  "properties": {
    "iso:country":"NL",
    "sg:address":"Zuidzydsedk 78",
    "sg:city":"Nieuw Beyerland",
    "sg:orig_category":"Administratie- En Boekhoudkantoren",
    "sg:phone":"+31 186 662 345",
    "sg:postcode":"3264 LJ",
    "sg:province":"South Holland",
    "wof:name":"Agb",
    "wof:placetype":"venue"
},
  "geometry": {"coordinates":[4.360941,51.781696],"type":"Point"}
}