{
  "type": "Feature",
  "properties": {
    "addr:full":"De Vogelweide 5 Drachten Provincie Friesland 9201 TE",
    "addr:housenumber":"5;9201",
    "addr:postcode":"te",
    "addr:street":"De Vogelweide;Provincie Friesland",
    "iso:country":"NL",
    "sg:address":"De Vogelweide 5",
    "sg:city":"Drachten",
    "sg:orig_category":"Peuterspeelzalen",
    "sg:phone":"+31 512 530 889",
    "sg:postcode":"9201 TE",
    "sg:province":"Provincie Friesland",
    "wof:name":"Kouwke, 'T",
    "wof:placetype":"venue"
},
  "geometry": {"coordinates":[6.104927,53.113243],"type":"Point"}
}