{
  "type": "Feature",
  "properties": {
    "addr:full":"Groenewg 54 C Utrecht Utrecht 3531 VG",
    "addr:housenumber":"54 c",
    "addr:postcode":"3531 vg",
    "addr:street":"Groenewg",
    "iso:country":"NL",
    "sg:address":"Groenewg 54 C",
    "sg:city":"Utrecht",
    "sg:orig_category":"Verenigingen En Stichtingen",
    "sg:phone":"+31 30 296 1257",
    "sg:postcode":"3531 VG",
    "sg:province":"Utrecht",
    "wof:name":"Westside, Jongerencentr",
    "wof:placetype":"venue"
},
  "geometry": {"coordinates":[5.091013,52.091244],"type":"Point"}
}