{
  "type": "Feature",
  "properties": {
    "addr:full":"Zilvermeeuw 12 Muiderberg Noord-Holland 1399 KK",
    "addr:housenumber":"12;1399",
    "addr:postcode":"kk",
    "addr:street":"Zilvermeeuw",
    "iso:country":"NL",
    "sg:address":"Zilvermeeuw 12",
    "sg:city":"Muiderberg",
    "sg:orig_category":"Adviesbureaus Bedrijfsorganisatie",
    "sg:phone":"+31 294 270 170",
    "sg:postcode":"1399 KK",
    "sg:province":"Noord-Holland",
    "wof:name":"Intercase",
    "wof:placetype":"venue"
},
  "geometry": {"coordinates":[5.12662,52.325077],"type":"Point"}
}