{
  "type": "Feature",
  "properties": {
    "addr:full":"Demer 31 Eindhoven Noord-Brabant 5611 AP",
    "addr:housenumber":"31",
    "addr:postcode":"5611 ap",
    "addr:street":"Demer",
    "iso:country":"NL",
    "sg:address":"Demer 31",
    "sg:city":"Eindhoven",
    "sg:orig_category":"Schoenen",
    "sg:phone":"+31 40 244 6185",
    "sg:postcode":"5611 AP",
    "sg:province":"Noord-Brabant",
    "sg:website":"http://www.dolcis.nl",
    "wof:name":"Dolcis",
    "wof:placetype":"venue"
},
  "geometry": {"coordinates":[5.477335,51.440144],"type":"Point"}
}