{
  "type": "Feature",
  "properties": {
    "addr:full":"Markt 120 Nieuwegein Utrecht 3431 LC",
    "addr:housenumber":"120",
    "addr:postcode":"3431 lc",
    "addr:street":"Markt",
    "iso:country":"NL",
    "sg:address":"Markt 120",
    "sg:city":"Nieuwegein",
    "sg:orig_category":"Beeldende Kunstenaars",
    "sg:phone":"+31 30 267 4457",
    "sg:postcode":"3431 LC",
    "sg:province":"Utrecht",
    "wof:name":"Shabani, S",
    "wof:placetype":"venue"
},
  "geometry": {"coordinates":[5.082408,52.028084],"type":"Point"}
}