{
  "type": "Feature",
  "properties": {
    "iso:country":"NL",
    "sg:address":"Piet Heinstraat 81",
    "sg:city":"Hengelo Ov",
    "sg:orig_category":"Overheidsdiensten",
    "sg:phone":"+31 74 250 0724",
    "sg:postcode":"7556 XT",
    "sg:province":"Overijssel",
    "wof:name":"Internat Vrouwencentrum Hengelo Ivch",
    "wof:placetype":"venue"
},
  "geometry": {"coordinates":[6.7999992371,52.2710723877],"type":"Point"}
}