{
  "type": "Feature",
  "properties": {
    "addr:full":"Marslaan 135 Nieuw Lekkerland Zuid-Holland 2957 SG",
    "addr:housenumber":"135",
    "addr:postcode":"2957 sg",
    "addr:street":"Marslaan",
    "iso:country":"NL",
    "sg:address":"Marslaan 135",
    "sg:city":"Nieuw Lekkerland",
    "sg:orig_category":"Bedrijfsinventaris Gh",
    "sg:phone":"+31 184 682 655",
    "sg:postcode":"2957 SG",
    "sg:province":"Zuid-Holland",
    "wof:name":"Libimex Bv",
    "wof:placetype":"venue"
},
  "geometry": {"coordinates":[4.670543,51.886898],"type":"Point"}
}