{
  "type": "Feature",
  "properties": {
    "addr:full":"Hoofdwg 1964 Buitenkaag Noord-Holland 2158 MC",
    "addr:housenumber":"1964;2158",
    "addr:postcode":"buitenkaag;mc",
    "iso:country":"NL",
    "sg:address":"Hoofdwg 1964",
    "sg:city":"Buitenkaag",
    "sg:orig_category":"Bloemen En Planten",
    "sg:phone":"+31 252 544 448",
    "sg:postcode":"2158 MC",
    "sg:province":"Noord-Holland",
    "wof:name":"Rodewijk En Zn Bv, G Th",
    "wof:placetype":"venue"
},
  "geometry": {"coordinates":[4.564497,52.222824],"type":"Point"}
}