{
  "type": "Feature",
  "properties": {
    "addr:full":"Koolmeesstr 2 Zwaagwesteinde Provincie Friesland 9271 EC",
    "addr:housenumber":"2",
    "addr:postcode":"9271 ec",
    "addr:street":"Koolmeesstr;Provincie Friesland",
    "iso:country":"NL",
    "sg:address":"Koolmeesstr 2",
    "sg:city":"Zwaagwesteinde",
    "sg:orig_category":"Babyartikelen",
    "sg:phone":"+31 511 443 874",
    "sg:postcode":"9271 EC",
    "sg:province":"Provincie Friesland",
    "wof:name":"Rammelaar, De",
    "wof:placetype":"venue"
},
  "geometry": {"coordinates":[6.034001,53.252266],"type":"Point"}
}