{
  "type": "Feature",
  "properties": {
    "iso:country":"NL",
    "sg:address":"Koolmeesstr 2",
    "sg:city":"Zwaagwesteinde",
    "sg:orig_category":"Babyartikelen",
    "sg:phone":"+31 511 443 874",
    "sg:postcode":"9271 EC",
    "sg:province":"Provincie Friesland",
    "wof:name":"Rammelaar, De",
    "wof:placetype":"venue"
},
  "geometry": {"coordinates":[6.034001,53.252266],"type":"Point"}
}