{
  "type": "Feature",
  "properties": {
    "addr:full":"Dennenrode 100G Amsterdam Zuidoost North Holland 1102 AE",
    "addr:housenumber":"100g",
    "addr:postcode":"1102 ae",
    "addr:street":"Dennenrode",
    "iso:country":"NL",
    "sg:address":"Dennenrode 100G",
    "sg:city":"Amsterdam Zuidoost",
    "sg:orig_category":"Kinderopvang Behalve Thuis",
    "sg:phone":"+31 20 690 7264",
    "sg:postcode":"1102 AE",
    "sg:province":"North Holland",
    "wof:name":"Ala Pikin",
    "wof:placetype":"venue"
},
  "geometry": {"coordinates":[4.953499,52.322124],"type":"Point"}
}