{
  "type": "Feature",
  "properties": {
    "addr:full":"Dykwg 168 Andyk Noord-Holland 1619 HK",
    "addr:housenumber":"168",
    "addr:postcode":"1619 hk",
    "addr:street":"Andyk Noord-Holland",
    "iso:country":"NL",
    "sg:address":"Dykwg 168",
    "sg:city":"Andyk",
    "sg:classifiers":[
        {
            "category":"Banks & Credit Unions",
            "subcategory":"Investment Brokerage",
            "type":"Services"
        }
    ],
    "sg:phone":"+31 228 592 691",
    "sg:postcode":"1619 HK",
    "sg:province":"Noord-Holland",
    "sg:tags":[
        "pension"
    ],
    "wof:name":"Onyx Logeerhuis",
    "wof:placetype":"venue"
},
  "geometry": {"coordinates":[5.22252,52.744362],"type":"Point"}
}