{
  "type": "Feature",
  "properties": {
    "addr:full":"Diamantstraat 19 Amsterdam New York 1074 GA",
    "addr:housenumber":"19;1074",
    "addr:postcode":"ga",
    "addr:street":"Diamantstraat",
    "iso:country":"NL",
    "sg:address":"Diamantstraat 19",
    "sg:city":"Amsterdam",
    "sg:orig_category":"Fietshandelaren",
    "sg:phone":"+31 20 679 7282",
    "sg:postcode":"1074 GA",
    "sg:province":"New York",
    "wof:name":"R M Bruin",
    "wof:placetype":"venue"
},
  "geometry": {"coordinates":[-74.21843699999999,42.966312],"type":"Point"}
}