{
  "type": "Feature",
  "properties": {
    "addr:full":"A.H.G. Fokkerstraat 7-9 Assen Drenthe 9403 AM",
    "addr:housenumber":"7-9",
    "addr:postcode":"9403",
    "addr:street":"A.H.G. Fokkerstraat",
    "iso:country":"NL",
    "sg:address":"A.H.G. Fokkerstraat 7-9",
    "sg:city":"Assen",
    "sg:orig_category":"Verpakkingsbedrijven",
    "sg:phone":"+31 592 379 100",
    "sg:postcode":"9403 AM",
    "sg:province":"Drenthe",
    "wof:name":"Amcor Flexibles Envi Bv",
    "wof:placetype":"venue"
},
  "geometry": {"coordinates":[6.572936,53.003017],"type":"Point"}
}