{
  "type": "Feature",
  "properties": {
    "addr:full":"Beukenln 20 Baarn Utrecht 3741 BP",
    "addr:housenumber":"20",
    "addr:postcode":"3741 bp",
    "addr:street":"Beukenln",
    "iso:country":"NL",
    "sg:address":"Beukenln 20",
    "sg:city":"Baarn",
    "sg:orig_category":"Drukkerijen",
    "sg:phone":"+31 35 542 2479",
    "sg:postcode":"3741 BP",
    "sg:province":"Utrecht",
    "wof:name":"Oxalis",
    "wof:placetype":"venue"
},
  "geometry": {"coordinates":[5.312465,52.224945],"type":"Point"}
}