{
  "type": "Feature",
  "properties": {
    "addr:full":"Weesperstraat 84 Diemen Noord-Holland 1112 AP",
    "addr:housenumber":"84",
    "addr:postcode":"1112 ap",
    "addr:street":"Weesperstraat",
    "iso:country":"NL",
    "sg:address":"Weesperstraat 84",
    "sg:city":"Diemen",
    "sg:orig_category":"Begrafenisondernemers",
    "sg:phone":"+31 20 690 2439",
    "sg:postcode":"1112 AP",
    "sg:province":"Noord-Holland",
    "wof:name":"Begraafplaats Rustoord",
    "wof:placetype":"venue"
},
  "geometry": {"coordinates":[4.966188,52.335949],"type":"Point"}
}