{
  "type": "Feature",
  "properties": {
    "addr:full":"Postbus 97 Anna Paulowna Noord-Holland 1760 AB",
    "addr:housenumber":"97",
    "addr:postcode":"1760 ab",
    "addr:street":"Postbus",
    "iso:country":"NL",
    "sg:address":"Postbus 97",
    "sg:city":"Anna Paulowna",
    "sg:orig_category":"Accountants - Administratie- Consulenten En -Kantoren",
    "sg:phone":"+31 223 531 493",
    "sg:postcode":"1760 AB",
    "sg:province":"Noord-Holland",
    "wof:name":"Tummers Bv, P H A",
    "wof:placetype":"venue"
},
  "geometry": {"coordinates":[4.83282,52.86256],"type":"Point"}
}