{
  "type": "Feature",
  "properties": {
    "addr:full":"Dollardstr 124 Amersfoort Utrecht 3812 EP",
    "addr:housenumber":"124",
    "addr:postcode":"3812 ep",
    "iso:country":"NL",
    "sg:address":"Dollardstr 124",
    "sg:city":"Amersfoort",
    "sg:orig_category":"Plafonds",
    "sg:phone":"+31 33 463 3227",
    "sg:postcode":"3812 EP",
    "sg:province":"Utrecht",
    "wof:name":"Druijff, D",
    "wof:placetype":"venue"
},
  "geometry": {"coordinates":[5.367085,52.162041],"type":"Point"}
}