{
  "type": "Feature",
  "properties": {
    "addr:full":"Emmapark 155 Pijnacker Zuid-Holland 2641 DW",
    "addr:housenumber":"155",
    "addr:postcode":"2641 dw",
    "addr:street":"Emmapark",
    "iso:country":"NL",
    "sg:address":"Emmapark 155",
    "sg:city":"Pijnacker",
    "sg:classifiers":[
        {
            "category":"Shopping",
            "subcategory":"Gifts & Souvenirs",
            "type":"Retail Goods"
        }
    ],
    "sg:phone":"+31 15 369 2233",
    "sg:postcode":"2641 DW",
    "sg:province":"Zuid-Holland",
    "sg:tags":[
        "geschenken"
    ],
    "wof:name":"Kok Woondecoratie",
    "wof:placetype":"venue"
},
  "geometry": {"coordinates":[4.4304,52.018108],"type":"Point"}
}