{
  "type": "Feature",
  "properties": {
    "addr:full":"Numansdorpsestraat 10 Schiedam South Holland 3114 XG",
    "addr:housenumber":"10",
    "addr:postcode":"3114 xg",
    "addr:street":"Numansdorpsestraat",
    "iso:country":"NL",
    "sg:address":"Numansdorpsestraat 10",
    "sg:city":"Schiedam",
    "sg:orig_category":"Film-, Tv- And Videoproductie",
    "sg:phone":"+31 10 246 0341",
    "sg:postcode":"3114 XG",
    "sg:province":"South Holland",
    "wof:name":"Dubbelklik Producties",
    "wof:placetype":"venue"
},
  "geometry": {"coordinates":[4.404737,51.903908],"type":"Point"}
}