{
  "type": "Feature",
  "properties": {
    "addr:full":"Zigzagoven 46 Wijk Bij Duurstede Utrecht 3961 ED",
    "addr:housenumber":"46",
    "addr:postcode":"3961 ed",
    "addr:street":"Zigzagoven",
    "iso:country":"NL",
    "sg:address":"Zigzagoven 46",
    "sg:city":"Wijk Bij Duurstede",
    "sg:orig_category":"Alternatieve Geneeskunde",
    "sg:phone":"+31 343 575 171",
    "sg:postcode":"3961 ED",
    "sg:province":"Utrecht",
    "wof:name":"W.C.A. Kocken",
    "wof:placetype":"venue"
},
  "geometry": {"coordinates":[5.330283,51.977123],"type":"Point"}
}