{
  "type": "Feature",
  "properties": {
    "addr:full":"Rode Kruislaan 156 Nijmegen Gelderland 6525 JP",
    "addr:housenumber":"156",
    "addr:postcode":"6525 jp",
    "addr:street":"Rode Kruislaan;Gelderland",
    "iso:country":"NL",
    "sg:address":"Rode Kruislaan 156",
    "sg:city":"Nijmegen",
    "sg:orig_category":"Architecten",
    "sg:phone":"+31 24 355 8800",
    "sg:postcode":"6525 JP",
    "sg:province":"Gelderland",
    "wof:name":"Marinus Juridisch Advies Bestuursrecht",
    "wof:placetype":"venue"
},
  "geometry": {"coordinates":[5.859846,51.827591],"type":"Point"}
}