{
  "type": "Feature",
  "properties": {
    "addr:full":"Frans Van Mierisstraat 59 Amsterdam North Holland 1071 RL",
    "addr:housenumber":"59",
    "addr:postcode":"1071 rl",
    "addr:street":"Frans Van Mierisstraat",
    "iso:country":"NL",
    "sg:address":"Frans Van Mierisstraat 59",
    "sg:city":"Amsterdam",
    "sg:orig_category":"Adviesbureaus Bedrijfsorganisatie",
    "sg:phone":"+31 20 664 1516",
    "sg:postcode":"1071 RL",
    "sg:province":"North Holland",
    "wof:name":"Vdg",
    "wof:placetype":"venue"
},
  "geometry": {"coordinates":[4.882183,52.354343],"type":"Point"}
}