{
  "type": "Feature",
  "properties": {
    "iso:country":"NL",
    "sg:address":"Glymesstraat 12",
    "sg:city":"Wouw",
    "sg:orig_category":"Granen, Zaden And Diervoeders Gh",
    "sg:phone":"+31 165 301 906",
    "sg:postcode":"4724 AP",
    "sg:province":"Noord-Brabant",
    "wof:name":"H.C.J. Koen",
    "wof:placetype":"venue"
},
  "geometry": {"coordinates":[4.387355,51.524223],"type":"Point"}
}