{
  "type": "Feature",
  "properties": {
    "addr:full":"Enschotsestr 28 Tilburg Noord-Brabant 5013 BD",
    "addr:housenumber":"28",
    "addr:postcode":"5013 bd",
    "addr:street":"Enschotsestr",
    "iso:country":"NL",
    "sg:address":"Enschotsestr 28",
    "sg:city":"Tilburg",
    "sg:orig_category":"Kantinebeheer",
    "sg:phone":"+31 13 542 6410",
    "sg:postcode":"5013 BD",
    "sg:province":"Noord-Brabant",
    "wof:name":"Claassens-Lenaerts Vof",
    "wof:placetype":"venue"
},
  "geometry": {"coordinates":[5.1035480499,51.5671386719],"type":"Point"}
}