{
  "type": "Feature",
  "properties": {
    "addr:full":"Koninginnewg 165 Rotterdam South Holland 3078 GM",
    "addr:housenumber":"165",
    "addr:postcode":"3078 gm",
    "iso:country":"NL",
    "sg:address":"Koninginnewg 165",
    "sg:city":"Rotterdam",
    "sg:orig_category":"Verhuizingen",
    "sg:phone":"+31 10 419 5326",
    "sg:postcode":"3078 GM",
    "sg:province":"South Holland",
    "wof:name":"Izelaar, Gebr",
    "wof:placetype":"venue"
},
  "geometry": {"coordinates":[4.550291,51.895073],"type":"Point"}
}