{
  "type": "Feature",
  "properties": {
    "addr:full":"Antwerpsestraat 13 Bergen Op Zoom North Brabant 4611 AA",
    "addr:housenumber":"13",
    "addr:postcode":"4611 aa",
    "addr:street":"Antwerpsestraat",
    "iso:country":"NL",
    "sg:address":"Antwerpsestraat 13",
    "sg:city":"Bergen Op Zoom",
    "sg:orig_category":"Meubelreparatie And -Restauratie",
    "sg:phone":"+31 164 235 433",
    "sg:postcode":"4611 AA",
    "sg:province":"North Brabant",
    "wof:name":"Meubelstoffeerderij Paul Braat",
    "wof:placetype":"venue"
},
  "geometry": {"coordinates":[4.288472,51.491764],"type":"Point"}
}