{
  "type": "Feature",
  "properties": {
    "addr:full":"Hogehuisstraat 9 Ijsselmuiden Overijssel 8271 BR",
    "addr:housenumber":"9",
    "addr:postcode":"8271 br",
    "addr:street":"Hogehuisstraat",
    "iso:country":"NL",
    "sg:address":"Hogehuisstraat 9",
    "sg:city":"Ijsselmuiden",
    "sg:classifiers":[
        {
            "category":"Bakery",
            "type":"Food & Drink"
        }
    ],
    "sg:phone":"+31 38 332 2396",
    "sg:postcode":"8271 BR",
    "sg:province":"Overijssel",
    "sg:tags":[
        "brood",
        "banket"
    ],
    "wof:name":"Nieuwenhuis Banket En Brood",
    "wof:placetype":"venue"
},
  "geometry": {"coordinates":[5.929446,52.56506],"type":"Point"}
}