{
  "type": "Feature",
  "properties": {
    "addr:full":"Zuiderstr 3 Noordlaren Groningen 9479 PP",
    "addr:housenumber":"3",
    "addr:postcode":"9479 pp",
    "addr:street":"Zuiderstr",
    "iso:country":"NL",
    "sg:address":"Zuiderstr 3",
    "sg:city":"Noordlaren",
    "sg:orig_category":"Kamerverhuur En -Bemiddeling",
    "sg:phone":"+31 50 402 9267",
    "sg:postcode":"9479 PP",
    "sg:province":"Groningen",
    "wof:name":"Slagman",
    "wof:placetype":"venue"
},
  "geometry": {"coordinates":[6.6692662239,53.1192169189],"type":"Point"}
}