{
  "type": "Feature",
  "properties": {
    "iso:country":"NL",
    "sg:address":"Hemmemawg 24",
    "sg:city":"St Annaparochie",
    "sg:orig_category":"Autoverhuur",
    "sg:phone":"+31 518 409 600",
    "sg:postcode":"9076 PH",
    "sg:province":"Provincie Friesland",
    "sg:website":"http://www.laasdouma.nl",
    "wof:name":"Laas Douma",
    "wof:placetype":"venue"
},
  "geometry": {"coordinates":[5.658778,53.270504],"type":"Point"}
}