{
  "type": "Feature",
  "properties": {
    "addr:full":"Remmerden 36 Rhenen Utrecht 3911 TZ",
    "addr:housenumber":"36",
    "addr:postcode":"3911 tz",
    "addr:street":"Remmerden",
    "iso:country":"NL",
    "sg:address":"Remmerden 36",
    "sg:city":"Rhenen",
    "sg:orig_category":"Metaalbekleding And -Behandeling",
    "sg:phone":"+31 317 612 972",
    "sg:postcode":"3911 TZ",
    "sg:province":"Utrecht",
    "wof:name":"Straalbedrijf Spies Bv",
    "wof:placetype":"venue"
},
  "geometry": {"coordinates":[5.535221,51.973141],"type":"Point"}
}