{
  "type": "Feature",
  "properties": {
    "addr:full":"Lochemsewg 1 Borculo Gelderland 7271 WB",
    "addr:housenumber":"1",
    "addr:postcode":"7271 wb",
    "addr:street":"Lochemsewg;Gelderland",
    "iso:country":"NL",
    "sg:address":"Lochemsewg 1",
    "sg:city":"Borculo",
    "sg:orig_category":"Videotheken",
    "sg:phone":"+31 545 273 035",
    "sg:postcode":"7271 WB",
    "sg:province":"Gelderland",
    "wof:name":"Huur En Kijk",
    "wof:placetype":"venue"
},
  "geometry": {"coordinates":[6.522963,52.119404],"type":"Point"}
}