{
  "type": "Feature",
  "properties": {
    "addr:full":"Amstelveensewg 1 Amsterdam Noord-Holland 1054 MB",
    "addr:housenumber":"1",
    "addr:postcode":"1054 mb",
    "addr:street":"Amstelveensewg",
    "iso:country":"NL",
    "sg:address":"Amstelveensewg 1",
    "sg:city":"Amsterdam",
    "sg:orig_category":"Schietbanen",
    "sg:phone":"+31 20 613 4072",
    "sg:postcode":"1054 MB",
    "sg:province":"Noord-Holland",
    "sg:website":"http://www.svtarget.nl",
    "wof:name":"Sv Target",
    "wof:placetype":"venue"
},
  "geometry": {"coordinates":[4.855505,52.357571],"type":"Point"}
}