{
  "type": "Feature",
  "properties": {
    "addr:full":"Kon Julianastr 3 Heino Uttar Pradesh 8141 ET",
    "addr:housenumber":"3",
    "addr:postcode":"8141 et",
    "addr:street":"Kon Julianastr",
    "iso:country":"NL",
    "sg:address":"Kon Julianastr 3",
    "sg:city":"Heino",
    "sg:orig_category":"Scholen Voor Basisonderwijs",
    "sg:phone":"+31 572 391 521",
    "sg:postcode":"8141 ET",
    "sg:province":"Uttar Pradesh",
    "wof:name":"Springplank Openb, De",
    "wof:placetype":"venue"
},
  "geometry": {"coordinates":[83.34802999999999,24.4242],"type":"Point"}
}