{
  "type": "Feature",
  "properties": {
    "addr:full":"Houtduif 2 Schagen Noord-Holland 1742 KR",
    "addr:housenumber":"2",
    "addr:postcode":"1742 kr",
    "addr:street":"Houtduif",
    "iso:country":"NL",
    "sg:address":"Houtduif 2",
    "sg:city":"Schagen",
    "sg:orig_category":"Webdesign Bureaus",
    "sg:phone":"+31 224 298 797",
    "sg:postcode":"1742 KR",
    "sg:province":"Noord-Holland",
    "wof:name":"Xl",
    "wof:placetype":"venue"
},
  "geometry": {"coordinates":[4.7867941856,52.7814826965],"type":"Point"}
}