{
  "type": "Feature",
  "properties": {
    "addr:full":"Ln V Het Kwekebos 311 Emmen Provincie Drenthe 7823 KH",
    "addr:housenumber":"311",
    "addr:postcode":"7823 kh",
    "addr:street":"Ln V Het Kwekebos;Provincie Drenthe",
    "iso:country":"NL",
    "sg:address":"Ln V Het Kwekebos 311",
    "sg:city":"Emmen",
    "sg:orig_category":"Goudsmeden En Zilversmeden",
    "sg:phone":"+31 591 628 808",
    "sg:postcode":"7823 KH",
    "sg:province":"Provincie Drenthe",
    "wof:name":"Tijd Is Goud",
    "wof:placetype":"venue"
},
  "geometry": {"coordinates":[6.941712,52.79538],"type":"Point"}
}