{
  "type": "Feature",
  "properties": {
    "addr:full":"Weena 256 Rotterdam South Holland 3012 NJ",
    "addr:housenumber":"256",
    "addr:postcode":"3012 nj",
    "addr:street":"Weena",
    "iso:country":"NL",
    "sg:address":"Weena 256",
    "sg:city":"Rotterdam",
    "sg:orig_category":"Kantoorapparatuur Gh",
    "sg:phone":"+31 10 411 0440",
    "sg:postcode":"3012 NJ",
    "sg:province":"South Holland",
    "wof:name":"Jones Lang Lasalle Bv",
    "wof:placetype":"venue"
},
  "geometry": {"coordinates":[4.4739761353,51.9233665466],"type":"Point"}
}