{
  "type": "Feature",
  "properties": {
    "addr:full":"Limpenshof 4 Beek Lb Limburg 6191 GX",
    "addr:housenumber":"4",
    "addr:postcode":"lb;6191 gx",
    "addr:street":"Limpenshof",
    "iso:country":"NL",
    "sg:address":"Limpenshof 4",
    "sg:city":"Beek Lb",
    "sg:orig_category":"Adviesbureaus Bedrijfsorganisatie",
    "sg:phone":"+31 46 437 7845",
    "sg:postcode":"6191 GX",
    "sg:province":"Limburg",
    "wof:name":"Winter Projecten",
    "wof:placetype":"venue"
},
  "geometry": {"coordinates":[-93.129936,36.705662],"type":"Point"}
}