{
  "type": "Feature",
  "properties": {
    "iso:country":"NL",
    "sg:address":"Velperpln 10",
    "sg:city":"Arnhem",
    "sg:orig_category":"Bioscopen",
    "sg:phone":"+31 26 445 6045",
    "sg:postcode":"6811 AG",
    "sg:province":"Gelderland",
    "wof:name":"Rembrandt",
    "wof:placetype":"venue"
},
  "geometry": {"coordinates":[5.911792,51.984303],"type":"Point"}
}