{
  "type": "Feature",
  "properties": {
    "iso:country":"NL",
    "sg:address":"Hg Eltensewg 4",
    "sg:city":"Kilder",
    "sg:orig_category":"Modevakscholen",
    "sg:phone":"+31 314 681 640",
    "sg:postcode":"7035 DH",
    "sg:province":"Gelderland",
    "wof:name":"Thijssen-Arts, W J E",
    "wof:placetype":"venue"
},
  "geometry": {"coordinates":[-98.924362,20.49721],"type":"Point"}
}