{
  "type": "Feature",
  "properties": {
    "iso:country":"NL",
    "sg:address":"Koopmansstraat 5",
    "sg:city":"Rijswijk Zh",
    "sg:orig_category":"Diverse Grafische Activiteiten",
    "sg:phone":"+31 70 398 8600",
    "sg:postcode":"2288 BC",
    "sg:province":"Zuid-Holland",
    "wof:name":"Boekbinderij M. Van Beek Bv",
    "wof:placetype":"venue"
},
  "geometry": {"coordinates":[4.33895,52.043613],"type":"Point"}
}