{
  "type": "Feature",
  "properties": {
    "iso:country":"NL",
    "sg:address":"Hagepoortplein 5",
    "sg:city":"Zutphen",
    "sg:orig_category":"Banken And Kredietinstellingen",
    "sg:phone":"+31 575 591 700",
    "sg:postcode":"7201 LN",
    "sg:province":"Gelderland",
    "wof:name":"Rabobank",
    "wof:placetype":"venue"
},
  "geometry": {"coordinates":[6.19868,52.142262],"type":"Point"}
}