{
  "type": "Feature",
  "properties": {
    "addr:full":"Palmstr 75 Amsterdam Noord-Holland 1015 HP",
    "addr:housenumber":"75",
    "addr:postcode":"1015 hp",
    "addr:street":"Palmstr",
    "iso:country":"NL",
    "sg:address":"Palmstr 75",
    "sg:city":"Amsterdam",
    "sg:orig_category":"Meubelmakerijen",
    "sg:phone":"+31 20 623 4345",
    "sg:postcode":"1015 HP",
    "sg:province":"Noord-Holland",
    "wof:name":"Janmaat, B",
    "wof:placetype":"venue"
},
  "geometry": {"coordinates":[4.882919,52.381393],"type":"Point"}
}