{
  "type": "Feature",
  "properties": {
    "addr:full":"Baronieln 60 Breda Noord-Brabant 4818 RB",
    "addr:housenumber":"60",
    "addr:postcode":"4818 rb",
    "addr:street":"Baronieln",
    "iso:country":"NL",
    "sg:address":"Baronieln 60",
    "sg:city":"Breda",
    "sg:orig_category":"Vertaalbureaus",
    "sg:phone":"+31 76 531 9531",
    "sg:postcode":"4818 RB",
    "sg:province":"Noord-Brabant",
    "wof:name":"Hamacavist",
    "wof:placetype":"venue"
},
  "geometry": {"coordinates":[4.771685,51.591351],"type":"Point"}
}