{
  "type": "Feature",
  "properties": {
    "addr:full":"Raadhuisstr 110 Roosendaal Noord-Brabant 4701 PW",
    "addr:housenumber":"110",
    "addr:postcode":"4701 pw",
    "iso:country":"NL",
    "sg:address":"Raadhuisstr 110",
    "sg:city":"Roosendaal",
    "sg:orig_category":"Fietsen En Bromfietsen",
    "sg:phone":"+31 165 399 845",
    "sg:postcode":"4701 PW",
    "sg:province":"Noord-Brabant",
    "sg:website":"http://www.scootercenterroosendaal.nl",
    "wof:name":"Scooter Center Roosendaal",
    "wof:placetype":"venue"
},
  "geometry": {"coordinates":[4.460949,51.53093],"type":"Point"}
}