{
  "type": "Feature",
  "properties": {
    "addr:full":"L Dreef 140 Ryswyk Zh Zuid-Holland 2285 LC",
    "addr:housenumber":"140",
    "addr:postcode":"2285 lc",
    "addr:street":"L Dreef",
    "iso:country":"NL",
    "sg:address":"L Dreef 140",
    "sg:city":"Ryswyk Zh",
    "sg:orig_category":"Bedrijfsopleidingen",
    "sg:phone":"+31 70 396 4558",
    "sg:postcode":"2285 LC",
    "sg:province":"Zuid-Holland",
    "wof:name":"Dijk, Gees Van",
    "wof:placetype":"venue"
},
  "geometry": {"coordinates":[4.32436,52.037251],"type":"Point"}
}