{
  "type": "Feature",
  "properties": {
    "addr:full":"Johannahoevewg 3 Oosterbeek Gelderland 6861 WH",
    "addr:housenumber":"3",
    "addr:postcode":"6861 wh",
    "addr:street":"Johannahoevewg;Gelderland",
    "iso:country":"NL",
    "sg:address":"Johannahoevewg 3",
    "sg:city":"Oosterbeek",
    "sg:orig_category":"Webdesign Bureaus",
    "sg:phone":"+31 26 370 6829",
    "sg:postcode":"6861 WH",
    "sg:province":"Gelderland",
    "sg:website":"http://www.woei.nl",
    "wof:name":"World Of Exciting Internet",
    "wof:placetype":"venue"
},
  "geometry": {"coordinates":[5.8369188309,51.9965629578],"type":"Point"}
}