{
  "type": "Feature",
  "properties": {
    "addr:full":"Pastoor Van Spaandonkstr 24 Breda Noord-Brabant 4813 BS",
    "addr:housenumber":"24",
    "addr:postcode":"4813 bs",
    "addr:street":"Pastoor Van Spaandonkstr",
    "iso:country":"NL",
    "sg:address":"Pastoor Van Spaandonkstr 24",
    "sg:city":"Breda",
    "sg:orig_category":"Huishoudapparatuur, Televisies And Radio'S",
    "sg:phone":"+31 76 530 9520",
    "sg:postcode":"4813 BS",
    "sg:province":"Noord-Brabant",
    "wof:name":"Wasmachineservice Will De Ruijter",
    "wof:placetype":"venue"
},
  "geometry": {"coordinates":[4.738887,51.577972],"type":"Point"}
}