{
  "type": "Feature",
  "properties": {
    "iso:country":"NL",
    "sg:address":"Burgemeester Padmosweg 58",
    "sg:city":"Wilnis",
    "sg:orig_category":"Bloemen And Planten",
    "sg:phone":"+31 297 242 219",
    "sg:postcode":"3648 BH",
    "sg:province":"Utrecht",
    "wof:name":"Ans Bloemen En Planten",
    "wof:placetype":"venue"
},
  "geometry": {"coordinates":[4.893776,52.193878],"type":"Point"}
}