{
  "type": "Feature",
  "properties": {
    "addr:full":"Lubeckstr 2 Deventer Overijssel 7418 EC",
    "addr:housenumber":"2",
    "addr:postcode":"7418 ec",
    "addr:street":"Lubeckstr",
    "iso:country":"NL",
    "sg:address":"Lubeckstr 2",
    "sg:city":"Deventer",
    "sg:orig_category":"Banden",
    "sg:phone":"+31 570 631 395",
    "sg:postcode":"7418 EC",
    "sg:province":"Overijssel",
    "sg:website":"http://www.jcv.nl",
    "wof:name":"Jcv Bv",
    "wof:placetype":"venue"
},
  "geometry": {"coordinates":[6.197329,52.239918],"type":"Point"}
}