{
  "type": "Feature",
  "properties": {
    "addr:full":"Saturnus 7 Duivendrecht Noord-Holland 1115 TC",
    "addr:housenumber":"7",
    "addr:postcode":"1115 tc",
    "addr:street":"Saturnus",
    "iso:country":"NL",
    "sg:address":"Saturnus 7",
    "sg:city":"Duivendrecht",
    "sg:orig_category":"Sanitaire Artikelen - Fabrieken En Groothandel",
    "sg:phone":"+31 20 695 2454",
    "sg:postcode":"1115 TC",
    "sg:province":"Noord-Holland",
    "sg:website":"http://www.badapart.nl",
    "wof:name":"Badapart Bv",
    "wof:placetype":"venue"
},
  "geometry": {"coordinates":[4.93923,52.332958],"type":"Point"}
}