{
  "type": "Feature",
  "properties": {
    "addr:full":"Kranepoort 6 Gouderak South Holland 2831 AK",
    "addr:housenumber":"6",
    "addr:postcode":"2831 ak",
    "addr:street":"Kranepoort",
    "iso:country":"NL",
    "sg:address":"Kranepoort 6",
    "sg:city":"Gouderak",
    "sg:orig_category":"Banken",
    "sg:phone":"+31 182 371 444",
    "sg:postcode":"2831 AK",
    "sg:province":"South Holland",
    "sg:website":"http://www.rabobank.nl",
    "wof:name":"Rabobank",
    "wof:placetype":"venue"
},
  "geometry": {"coordinates":[4.675773,51.984692],"type":"Point"}
}