{
  "type": "Feature",
  "properties": {
    "addr:full":"Wethouder Twaalfhovenstr 45 Uitgeest North Holland 1911 HC",
    "addr:housenumber":"45",
    "addr:postcode":"1911 hc",
    "addr:street":"Wethouder Twaalfhovenstr",
    "iso:country":"NL",
    "sg:address":"Wethouder Twaalfhovenstr 45",
    "sg:city":"Uitgeest",
    "sg:orig_category":"Verhuur Bouwmachines",
    "sg:phone":"+31 251 315 786",
    "sg:postcode":"1911 HC",
    "sg:province":"North Holland",
    "wof:name":"Rob Roest Productions",
    "wof:placetype":"venue"
},
  "geometry": {"coordinates":[4.706543,52.523827],"type":"Point"}
}