{
  "type": "Feature",
  "properties": {
    "addr:full":"Elzenln 37 Marum Groningen 9363 CM",
    "addr:housenumber":"37",
    "addr:postcode":"9363 cm",
    "addr:street":"Elzenln",
    "iso:country":"NL",
    "sg:address":"Elzenln 37",
    "sg:city":"Marum",
    "sg:orig_category":"Zonnebank- En Solariumcentra",
    "sg:phone":"+31 594 642 425",
    "sg:postcode":"9363 CM",
    "sg:province":"Groningen",
    "wof:name":"Mobielsun",
    "wof:placetype":"venue"
},
  "geometry": {"coordinates":[6.269483,53.141632],"type":"Point"}
}