{
  "type": "Feature",
  "properties": {
    "iso:country":"NL",
    "sg:address":"Hoge Larenseweg 11",
    "sg:city":"Hilversum",
    "sg:orig_category":"Organisaties And Verenigingen",
    "sg:phone":"+31 35 772 0533",
    "sg:postcode":"1221 AJ",
    "sg:province":"Noord-Holland",
    "wof:name":"Stichting Helder Denken",
    "wof:placetype":"venue"
},
  "geometry": {"coordinates":[5.1799669266,52.2295455933],"type":"Point"}
}