{
  "type": "Feature",
  "properties": {
    "addr:full":"Industriewg 24 Renkum Gelderland 6871 KA",
    "addr:housenumber":"24",
    "addr:postcode":"6871 ka",
    "addr:street":"Industriewg;Gelderland",
    "iso:country":"NL",
    "sg:address":"Industriewg 24",
    "sg:city":"Renkum",
    "sg:orig_category":"Verpakkingsbedrijven",
    "sg:phone":"+31 317 319 005",
    "sg:postcode":"6871 KA",
    "sg:province":"Gelderland",
    "sg:website":"http://www.alberthoegen.nl",
    "wof:name":"Albert Hoegen Bv",
    "wof:placetype":"venue"
},
  "geometry": {"coordinates":[5.741955,51.986347],"type":"Point"}
}