{
  "type": "Feature",
  "properties": {
    "iso:country":"NL",
    "sg:address":"Zutphensewg 1B",
    "sg:city":"Vorden",
    "sg:orig_category":"Kappers",
    "sg:phone":"+31 575 553 336",
    "sg:postcode":"7251 DG",
    "sg:province":"Gelderland",
    "wof:name":"Ami",
    "wof:placetype":"venue"
},
  "geometry": {"coordinates":[6.312048912,52.1041603088],"type":"Point"}
}