{
  "type": "Feature",
  "properties": {
    "iso:country":"NL",
    "sg:address":"Hessenweg 153",
    "sg:city":"De Bilt",
    "sg:classifiers":[
        {
            "category":"Retail",
            "subcategory":"Photofinishing",
            "type":"Services"
        }
    ],
    "sg:phone":"+31 30 221 1295",
    "sg:postcode":"3731 JG",
    "sg:province":"Utrecht",
    "sg:tags":[
        "foto",
        "film"
    ],
    "wof:name":"Foto Brouwer",
    "wof:placetype":"venue"
},
  "geometry": {"coordinates":[5.181507,52.110653],"type":"Point"}
}