{
  "type": "Feature",
  "properties": {
    "addr:full":"Lg Duin 44 Bennebroek Noord-Holland 2121 CH",
    "addr:housenumber":"44",
    "addr:postcode":"2121",
    "addr:street":"Duin",
    "iso:country":"NL",
    "sg:address":"Lg Duin 44",
    "sg:city":"Bennebroek",
    "sg:orig_category":"Linnenshops",
    "sg:phone":"+31 23 584 9561",
    "sg:postcode":"2121 CH",
    "sg:province":"Noord-Holland",
    "sg:website":"http://www.chiqueensimpel.nl",
    "wof:name":"Chique & Simpel",
    "wof:placetype":"venue"
},
  "geometry": {"coordinates":[4.597769,52.322365],"type":"Point"}
}