{
  "type": "Feature",
  "properties": {
    "addr:full":"J Wiersmawg 19 Eestrum Provincie Friesland 9258 CC",
    "addr:housenumber":"19;9258",
    "addr:postcode":"cc",
    "addr:street":"Eestrum Provincie Friesland",
    "iso:country":"NL",
    "sg:address":"J Wiersmawg 19",
    "sg:city":"Eestrum",
    "sg:orig_category":"Verenigingen En Stichtingen",
    "sg:phone":"+31 512 472 188",
    "sg:postcode":"9258 CC",
    "sg:province":"Provincie Friesland",
    "wof:name":"Jeugdwerk Tietjerksteradeel, Fed Chr",
    "wof:placetype":"venue"
},
  "geometry": {"coordinates":[6.065328,53.212421],"type":"Point"}
}