{
  "type": "Feature",
  "properties": {
    "addr:full":"Hildo Kroplaan 52 'S Gravenhage Zuid-Holland 2552 XS",
    "addr:housenumber":"52",
    "addr:postcode":"2552 xs",
    "addr:street":"Hildo Kroplaan;' S",
    "iso:country":"NL",
    "sg:address":"Hildo Kroplaan 52",
    "sg:city":"'S Gravenhage",
    "sg:orig_category":"Opticiens",
    "sg:phone":"+31 70 397 7077",
    "sg:postcode":"2552 XS",
    "sg:province":"Zuid-Holland",
    "wof:name":"Spektrum Optiek",
    "wof:placetype":"venue"
},
  "geometry": {"coordinates":[4.2502069473,52.0546760559],"type":"Point"}
}