{
  "type": "Feature",
  "properties": {
    "addr:full":"Westvest 24 Delft Zuid-Holland 2611 AZ",
    "addr:housenumber":"24",
    "addr:postcode":"2611 az",
    "addr:street":"Westvest",
    "iso:country":"NL",
    "sg:address":"Westvest 24",
    "sg:city":"Delft",
    "sg:orig_category":"Adviesbureaus Bedrijfsorganisatie",
    "sg:phone":"+31 15 214 8851",
    "sg:postcode":"2611 AZ",
    "sg:province":"Zuid-Holland",
    "wof:name":"Bst Groupe",
    "wof:placetype":"venue"
},
  "geometry": {"coordinates":[4.356907,52.008533],"type":"Point"}
}