{
  "type": "Feature",
  "properties": {
    "iso:country":"NL",
    "sg:address":"Postbus 31",
    "sg:city":"Marknesse",
    "sg:orig_category":"Fitnessapparatuur",
    "sg:phone":"+31 6 53932098",
    "sg:postcode":"8316 ZG",
    "sg:province":"NL.",
    "wof:name":"Denfit Bv",
    "wof:placetype":"venue"
},
  "geometry": {"coordinates":[5.862715,52.707375],"type":"Point"}
}