{
  "type": "Feature",
  "properties": {
    "iso:country":"NL",
    "sg:address":"Woudlust 4",
    "sg:city":"Westwoud",
    "sg:orig_category":"Sportclubs",
    "sg:phone":"+31 228 561 981",
    "sg:postcode":"1617 KG",
    "sg:province":"Noord-Holland",
    "wof:name":"Voetbalvereniging Woudia",
    "wof:placetype":"venue"
},
  "geometry": {"coordinates":[5.139846,52.686295],"type":"Point"}
}