{
  "type": "Feature",
  "properties": {
    "addr:full":"Pr Bernhardstr 51 Drunen Noord-Brabant 5151 VA",
    "addr:housenumber":"51",
    "addr:postcode":"5151",
    "iso:country":"NL",
    "sg:address":"Pr Bernhardstr 51",
    "sg:city":"Drunen",
    "sg:orig_category":"Beveiliging",
    "sg:phone":"+31 416 363 949",
    "sg:postcode":"5151 VA",
    "sg:province":"Noord-Brabant",
    "wof:name":"Premax Beveiligingen",
    "wof:placetype":"venue"
},
  "geometry": {"coordinates":[5.13686,51.690361],"type":"Point"}
}