{
  "type": "Feature",
  "properties": {
    "addr:full":"Grebbedk 19/21 Wageningen Gelderland 6702 DS",
    "addr:housenumber":"19 / 21",
    "addr:postcode":"6702 ds",
    "addr:street":"Grebbedk;Gelderland",
    "iso:country":"NL",
    "sg:address":"Grebbedk 19/21",
    "sg:city":"Wageningen",
    "sg:orig_category":"Benzine En Olie - Groothandel",
    "sg:phone":"+31 317 412 316",
    "sg:postcode":"6702 DS",
    "sg:province":"Gelderland",
    "wof:name":"Sluis, Van De",
    "wof:placetype":"venue"
},
  "geometry": {"coordinates":[5.652472,51.960484],"type":"Point"}
}