{
  "type": "Feature",
  "properties": {
    "addr:full":"Zwart Janstraat 63 Rotterdam South Holland 3035 AL",
    "addr:housenumber":"63",
    "addr:postcode":"3035 al",
    "addr:street":"Zwart Janstraat",
    "iso:country":"NL",
    "sg:address":"Zwart Janstraat 63",
    "sg:city":"Rotterdam",
    "sg:orig_category":"Herenmodezaken",
    "sg:phone":"+31 10 466 8025",
    "sg:postcode":"3035 AL",
    "sg:province":"South Holland",
    "wof:name":"Mistral Damesmode",
    "wof:placetype":"venue"
},
  "geometry": {"coordinates":[4.478431,51.933369],"type":"Point"}
}