{
  "type": "Feature",
  "properties": {
    "iso:country":"NL",
    "sg:address":"Meyerystr 5",
    "sg:city":"Veghel",
    "sg:orig_category":"Hoortoestellen",
    "sg:phone":"+31 413 310 167",
    "sg:postcode":"5461 HK",
    "sg:province":"North Brabant",
    "wof:name":"Beter Horen",
    "wof:placetype":"venue"
},
  "geometry": {"coordinates":[5.54175,51.617222],"type":"Point"}
}