{
  "type": "Feature",
  "properties": {
    "iso:country":"NL",
    "sg:address":"Ginnekenwg 141",
    "sg:city":"Breda",
    "sg:orig_category":"Verenigingen En Stichtingen",
    "sg:phone":"+31 76 521 5886",
    "sg:postcode":"4818 JD",
    "sg:province":"Noord-Brabant",
    "wof:name":"Loges Het Vrij Geweten/Geef U Zelf",
    "wof:placetype":"venue"
},
  "geometry": {"coordinates":[4.782966,51.574623],"type":"Point"}
}