{
  "type": "Feature",
  "properties": {
    "addr:full":"Kolonel Johnsonstraat 1 Veghel Noord-Brabant 5462 CT",
    "addr:housenumber":"1",
    "addr:postcode":"5462 ct",
    "addr:street":"Kolonel Johnsonstraat",
    "iso:country":"NL",
    "sg:address":"Kolonel Johnsonstraat 1",
    "sg:city":"Veghel",
    "sg:classifiers":[
        {
            "category":"Retail",
            "subcategory":"Photofinishing",
            "type":"Services"
        }
    ],
    "sg:phone":"+31 413 363 275",
    "sg:postcode":"5462 CT",
    "sg:province":"Noord-Brabant",
    "sg:tags":[
        "foto",
        "film"
    ],
    "wof:name":"Foto Harry Van Liempd Bv",
    "wof:placetype":"venue"
},
  "geometry": {"coordinates":[5.539611,51.615341],"type":"Point"}
}