{
  "type": "Feature",
  "properties": {
    "iso:country":"NL",
    "sg:address":"Roosje Vosstraat 15",
    "sg:city":"Alkmaar",
    "sg:orig_category":"Kappers",
    "sg:phone":"+31 72 561 0204",
    "sg:postcode":"1827 LZ",
    "sg:province":"North Holland",
    "wof:name":"Sandra Rake-Koenen Thuiskapper",
    "wof:placetype":"venue"
},
  "geometry": {"coordinates":[4.766538,52.66753],"type":"Point"}
}