{
  "type": "Feature",
  "properties": {
    "addr:full":"Antwerpsestrwg 44 Hoogerheide North Brabant 4631 NL",
    "addr:housenumber":"44",
    "addr:postcode":"4631 nl",
    "addr:street":"Antwerpsestrwg",
    "iso:country":"NL",
    "sg:address":"Antwerpsestrwg 44",
    "sg:city":"Hoogerheide",
    "sg:orig_category":"Fietsen En Bromfietsen",
    "sg:phone":"+31 164 612 876",
    "sg:postcode":"4631 NL",
    "sg:province":"North Brabant",
    "wof:name":"Brand, Van Den",
    "wof:placetype":"venue"
},
  "geometry": {"coordinates":[4.319029,51.431526],"type":"Point"}
}