{
  "type": "Feature",
  "properties": {
    "addr:full":"Transformatorwg 37 Amsterdam North Holland 1014 AJ",
    "addr:housenumber":"37",
    "addr:postcode":"1014 aj",
    "addr:street":"Transformatorwg",
    "iso:country":"NL",
    "sg:address":"Transformatorwg 37",
    "sg:city":"Amsterdam",
    "sg:orig_category":"Plastic Producten - Fabrieken En Groothandel",
    "sg:phone":"+31 20 686 8711",
    "sg:postcode":"1014 AJ",
    "sg:province":"North Holland",
    "sg:website":"http://www.putzfeld.nl",
    "wof:name":"P\u00fctzfeld Bv, Johan",
    "wof:placetype":"venue"
},
  "geometry": {"coordinates":[4.849892,52.391441],"type":"Point"}
}