{
  "type": "Feature",
  "properties": {
    "addr:full":"Zwin 2 Ammerzoden Gelderland 5324 AW",
    "addr:housenumber":"2",
    "addr:postcode":"5324 aw",
    "addr:street":"Zwin;Gelderland",
    "iso:country":"NL",
    "sg:address":"Zwin 2",
    "sg:city":"Ammerzoden",
    "sg:orig_category":"Banken",
    "sg:phone":"+31 73 599 8000",
    "sg:postcode":"5324 AW",
    "sg:province":"Gelderland",
    "sg:website":"http://www.rabobank.nl",
    "wof:name":"Rabobank",
    "wof:placetype":"venue"
},
  "geometry": {"coordinates":[5.223238,51.746914],"type":"Point"}
}