{
  "type": "Feature",
  "properties": {
    "addr:full":"Ondiep Zz 2D Utrecht Utrecht 3551 BW",
    "addr:housenumber":"2d",
    "addr:postcode":"3551 bw",
    "addr:street":"Ondiep Zz",
    "iso:country":"NL",
    "sg:address":"Ondiep Zz 2D",
    "sg:city":"Utrecht",
    "sg:orig_category":"Milieu",
    "sg:phone":"+31 30 243 5303",
    "sg:postcode":"3551 BW",
    "sg:province":"Utrecht",
    "wof:name":"Milieunet, Sticht",
    "wof:placetype":"venue"
},
  "geometry": {"coordinates":[5.097334,52.102425],"type":"Point"}
}