{
  "type": "Feature",
  "properties": {
    "addr:full":"Dikkersstraat 1 Ommen Overijssel 7731 DH",
    "addr:housenumber":"1",
    "addr:postcode":"7731 dh",
    "addr:street":"Dikkersstraat",
    "iso:country":"NL",
    "sg:address":"Dikkersstraat 1",
    "sg:city":"Ommen",
    "sg:orig_category":"Bejaardeninstellingen And Serviceflats",
    "sg:phone":"+31 529 451 016",
    "sg:postcode":"7731 DH",
    "sg:province":"Overijssel",
    "wof:name":"Cooperatieve Serviceflat De Stadshaghen Ua",
    "wof:placetype":"venue"
},
  "geometry": {"coordinates":[6.414877,52.520069],"type":"Point"}
}