{
  "type": "Feature",
  "properties": {
    "addr:full":"Skagerrak 220 Hoofddorp Noord-Holland 2133 DW",
    "addr:housenumber":"220",
    "addr:postcode":"2133 dw",
    "addr:street":"Skagerrak",
    "iso:country":"NL",
    "sg:address":"Skagerrak 220",
    "sg:city":"Hoofddorp",
    "sg:orig_category":"Bloemen And Planten",
    "sg:phone":"+31 23 563 0922",
    "sg:postcode":"2133 DW",
    "sg:province":"Noord-Holland",
    "wof:name":"Bloemsierkunst Le Papillon",
    "wof:placetype":"venue"
},
  "geometry": {"coordinates":[4.671696,52.309807],"type":"Point"}
}