{
  "type": "Feature",
  "properties": {
    "addr:full":"Kampenhout 32 Vught North Brabant 5262 JT",
    "addr:housenumber":"32",
    "addr:postcode":"5262 jt",
    "addr:street":"Kampenhout",
    "iso:country":"NL",
    "sg:address":"Kampenhout 32",
    "sg:city":"Vught",
    "sg:orig_category":"Grafologen, Handlezers And Helderzienden",
    "sg:phone":"+31 73 656 9018",
    "sg:postcode":"5262 JT",
    "sg:province":"North Brabant",
    "wof:name":"Aurora Astro Consult",
    "wof:placetype":"venue"
},
  "geometry": {"coordinates":[5.28466,51.637527],"type":"Point"}
}