{
  "type": "Feature",
  "properties": {
    "iso:country":"NL",
    "sg:address":"Rijksstraatweg 70",
    "sg:city":"Wassenaar",
    "sg:orig_category":"Metaalafval, Schrootrecycling And Sloperijen",
    "sg:phone":"+31 70 511 0656",
    "sg:postcode":"2241 BW",
    "sg:province":"Zuid-Holland",
    "wof:name":"Autosloperij W.G. Jansen Bv",
    "wof:placetype":"venue"
},
  "geometry": {"coordinates":[4.426339,52.147331],"type":"Point"}
}