{
  "type": "Feature",
  "properties": {
    "addr:full":"Nieuwe Maanderbuurtweg 63 Ede Gld Gelderland 6717 AP",
    "addr:housenumber":"63",
    "addr:postcode":"6717 ap",
    "addr:street":"Nieuwe Maanderbuurtweg;Gld Gelderland",
    "iso:country":"NL",
    "sg:address":"Nieuwe Maanderbuurtweg 63",
    "sg:city":"Ede Gld",
    "sg:orig_category":"Diverse Bedrijfsinstallaties Gh",
    "sg:phone":"+31 318 690 013",
    "sg:postcode":"6717 AP",
    "sg:province":"Gelderland",
    "wof:name":"Soykan",
    "wof:placetype":"venue"
},
  "geometry": {"coordinates":[5.650141,52.028416],"type":"Point"}
}