{
  "type": "Feature",
  "properties": {
    "addr:full":"Jokweg 14 De Hoeve Friesland 8394 VL",
    "addr:housenumber":"14",
    "addr:postcode":"hoeve;8394 vl",
    "addr:street":"Jokweg",
    "iso:country":"NL",
    "sg:address":"Jokweg 14",
    "sg:city":"De Hoeve",
    "sg:classifiers":[
        {
            "category":"Education",
            "subcategory":"Preschool",
            "type":"Public Place"
        }
    ],
    "sg:phone":"+31 561 432 600",
    "sg:postcode":"8394 VL",
    "sg:province":"Friesland",
    "sg:tags":[
        "kleuteronderwijs",
        "basis-"
    ],
    "wof:name":"Openbare Basisschool De Klaeter",
    "wof:placetype":"venue"
},
  "geometry": {"coordinates":[6.089676,52.887249],"type":"Point"}
}