{
  "type": "Feature",
  "properties": {
    "addr:full":"Torenstr 36A Winschoten Groningen 9671 EE",
    "addr:housenumber":"36a",
    "addr:postcode":"9671 ee",
    "addr:street":"Torenstr",
    "iso:country":"NL",
    "sg:address":"Torenstr 36A",
    "sg:city":"Winschoten",
    "sg:orig_category":"Ziekenhuizen, Sanatoria, Verpleeghuizen",
    "sg:phone":"+31 597 471 000",
    "sg:postcode":"9671 EE",
    "sg:province":"Groningen",
    "sg:website":"http://www.oosterlengte.nl",
    "wof:name":"Wold-Rank, De",
    "wof:placetype":"venue"
},
  "geometry": {"coordinates":[7.039119,53.141064],"type":"Point"}
}