{
  "type": "Feature",
  "properties": {
    "addr:full":"Biltstraat 36 Utrecht Utrecht 3572 BC",
    "addr:housenumber":"36",
    "addr:postcode":"3572 bc",
    "addr:street":"Biltstraat",
    "iso:country":"NL",
    "sg:address":"Biltstraat 36",
    "sg:city":"Utrecht",
    "sg:orig_category":"Werving And Selectie Van Tijdelijk Personeel And Uitzendkantoren",
    "sg:phone":"+31 30 271 2486",
    "sg:postcode":"3572 BC",
    "sg:province":"Utrecht",
    "wof:name":"Manpower",
    "wof:placetype":"venue"
},
  "geometry": {"coordinates":[5.1280207634,52.0952720642],"type":"Point"}
}