{
  "type": "Feature",
  "properties": {
    "iso:country":"NL",
    "sg:address":"Noordmolenwerf 75",
    "sg:city":"Rotterdam",
    "sg:orig_category":"Adviesbureaus Bedrijfsorganisatie",
    "sg:phone":"+31 10 404 6140",
    "sg:postcode":"3011 DC",
    "sg:province":"Zuid-Holland",
    "wof:name":"Lijesen Bv",
    "wof:placetype":"venue"
},
  "geometry": {"coordinates":[4.481535,51.923744],"type":"Point"}
}