{
  "type": "Feature",
  "properties": {
    "addr:full":"Statumwg 4A Lemelerveld Overijssel 8151 AV",
    "addr:housenumber":"4a",
    "addr:postcode":"8151 av",
    "addr:street":"Statumwg",
    "iso:country":"NL",
    "sg:address":"Statumwg 4A",
    "sg:city":"Lemelerveld",
    "sg:orig_category":"Land- En Tuinbouw - Loonbedrijven",
    "sg:phone":"+31 572 371 290",
    "sg:postcode":"8151 AV",
    "sg:province":"Overijssel",
    "wof:name":"Roelofs",
    "wof:placetype":"venue"
},
  "geometry": {"coordinates":[6.362973,52.443417],"type":"Point"}
}