{
  "type": "Feature",
  "properties": {
    "addr:full":"Rosendael 26 Landsmeer North Holland 1121 HH",
    "addr:housenumber":"26",
    "addr:postcode":"1121 hh",
    "addr:street":"Rosendael",
    "iso:country":"NL",
    "sg:address":"Rosendael 26",
    "sg:city":"Landsmeer",
    "sg:orig_category":"Boekhouders",
    "sg:phone":"+31 20 482 4324",
    "sg:postcode":"1121 HH",
    "sg:province":"North Holland",
    "wof:name":"Adm- En Makelaarskantoor Og A.J. Van Zoe",
    "wof:placetype":"venue"
},
  "geometry": {"coordinates":[4.919661,52.426876],"type":"Point"}
}