{
  "type": "Feature",
  "properties": {
    "addr:full":"Norbertynenstr 34 Arnhem Gelderland 6823 PK",
    "addr:housenumber":"34",
    "addr:postcode":"6823 pk",
    "addr:street":"Norbertynenstr",
    "iso:country":"NL",
    "sg:address":"Norbertynenstr 34",
    "sg:city":"Arnhem",
    "sg:orig_category":"Adviesbureaus Bedrijfsorganisatie",
    "sg:phone":"+31 26 361 4126",
    "sg:postcode":"6823 PK",
    "sg:province":"Gelderland",
    "wof:name":"Welker, M",
    "wof:placetype":"venue"
},
  "geometry": {"coordinates":[5.93804,52.002609],"type":"Point"}
}