{
  "type": "Feature",
  "properties": {
    "addr:full":"Hoofdstraat 231 Bovenkarspel Noord-Holland 1611 AG",
    "addr:housenumber":"231",
    "addr:postcode":"1611",
    "addr:street":"Hoofdstraat",
    "iso:country":"NL",
    "sg:address":"Hoofdstraat 231",
    "sg:city":"Bovenkarspel",
    "sg:orig_category":"Bloemen And Planten",
    "sg:phone":"+31 228 519 426",
    "sg:postcode":"1611 AG",
    "sg:province":"Noord-Holland",
    "wof:name":"Flower Seed Technology Bv",
    "wof:placetype":"venue"
},
  "geometry": {"coordinates":[5.251594,52.699062],"type":"Point"}
}