{
  "type": "Feature",
  "properties": {
    "addr:full":"Molenwal 35 Oudewater Utrecht 3421 CM",
    "addr:housenumber":"35",
    "addr:postcode":"3421 cm",
    "addr:street":"Molenwal",
    "iso:country":"NL",
    "sg:address":"Molenwal 35",
    "sg:city":"Oudewater",
    "sg:orig_category":"Metselwerken",
    "sg:phone":"+31 348 565 273",
    "sg:postcode":"3421 CM",
    "sg:province":"Utrecht",
    "wof:name":"Nederend",
    "wof:placetype":"venue"
},
  "geometry": {"coordinates":[4.871945,52.020012],"type":"Point"}
}