{
  "type": "Feature",
  "properties": {
    "addr:full":"Vlaswiek 2 Hellevoetsluis Zuid-Holland 3220 ",
    "addr:housenumber":"2",
    "addr:postcode":"3220",
    "addr:street":"Vlaswiek",
    "iso:country":"NL",
    "sg:address":"Vlaswiek 2",
    "sg:city":"Hellevoetsluis",
    "sg:orig_category":"Film-, Tv- And Videoproductie",
    "sg:phone":"+31 181 322 515",
    "sg:postcode":"3220 ",
    "sg:province":"Zuid-Holland",
    "wof:name":"Rens Video Produkties V.O.F.",
    "wof:placetype":"venue"
},
  "geometry": {"coordinates":[4.144326,51.825436],"type":"Point"}
}