{
  "type": "Feature",
  "properties": {
    "addr:full":"Heuvelstr 114 Tilburg Noord-Brabant 5038 AH",
    "addr:housenumber":"114",
    "addr:postcode":"5038 ah",
    "addr:street":"Tilburg",
    "iso:country":"NL",
    "sg:address":"Heuvelstr 114",
    "sg:city":"Tilburg",
    "sg:orig_category":"Huishoudelijke Apparaten En Artikelen",
    "sg:phone":"+31 13 542 0338",
    "sg:postcode":"5038 AH",
    "sg:province":"Noord-Brabant",
    "wof:name":"Schlappi",
    "wof:placetype":"venue"
},
  "geometry": {"coordinates":[5.083641,51.555073],"type":"Point"}
}