{
  "type": "Feature",
  "properties": {
    "iso:country":"NL",
    "sg:address":"Hennenberg 11",
    "sg:city":"Pynacker",
    "sg:orig_category":"Webdesign Bureaus",
    "sg:phone":"+31 15 369 5503",
    "sg:postcode":"2641 LS",
    "sg:province":"Zuid-Holland",
    "sg:website":"http://www.mybegin.nl",
    "wof:name":"My Begin",
    "wof:placetype":"venue"
},
  "geometry": {"coordinates":[4.4403119087,52.010887146],"type":"Point"}
}