{
  "type": "Feature",
  "properties": {
    "addr:full":"Strijkviertel 44 De Meern Utrecht 3454 PN",
    "addr:housenumber":"44",
    "addr:postcode":"3454 pn",
    "addr:street":"Strijkviertel",
    "iso:country":"NL",
    "sg:address":"Strijkviertel 44",
    "sg:city":"De Meern",
    "sg:orig_category":"Autokeuringen",
    "sg:phone":"+31 30 666 4868",
    "sg:postcode":"3454 PN",
    "sg:province":"Utrecht",
    "wof:name":"J.C. En J. Donker Vof",
    "wof:placetype":"venue"
},
  "geometry": {"coordinates":[5.05933,52.08036],"type":"Point"}
}