{
  "type": "Feature",
  "properties": {
    "addr:full":"Westzijde 113 Zaandam Noord-Holland 1506 GB",
    "addr:housenumber":"113",
    "addr:postcode":"1506 gb",
    "addr:street":"Westzijde",
    "iso:country":"NL",
    "sg:address":"Westzijde 113",
    "sg:city":"Zaandam",
    "sg:orig_category":"Kappers",
    "sg:phone":"+31 75 616 4651",
    "sg:postcode":"1506 GB",
    "sg:province":"Noord-Holland",
    "wof:name":"Kapsalon Kaper",
    "wof:placetype":"venue"
},
  "geometry": {"coordinates":[4.8190321922,52.447429657],"type":"Point"}
}