{
  "type": "Feature",
  "properties": {
    "addr:full":"Oostergowg 5 Leeuwarden Provincie Friesland 8911 MA",
    "addr:housenumber":"5",
    "addr:postcode":"8911 ma",
    "addr:street":"Oostergowg;Provincie Friesland",
    "iso:country":"NL",
    "sg:address":"Oostergowg 5",
    "sg:city":"Leeuwarden",
    "sg:orig_category":"Medische Keuringen",
    "sg:phone":"+31 58 234 0808",
    "sg:postcode":"8911 MA",
    "sg:province":"Provincie Friesland",
    "sg:website":"http://www.zvnadvies.nl",
    "wof:name":"Zvn Nv",
    "wof:placetype":"venue"
},
  "geometry": {"coordinates":[5.797672,53.197208],"type":"Point"}
}