{
  "type": "Feature",
  "properties": {
    "iso:country":"NL",
    "sg:address":"Voorstr 25",
    "sg:city":"Zwaagwesteinde",
    "sg:orig_category":"Artsen - Huisartsen",
    "sg:phone":"+31 511 441 274",
    "sg:postcode":"9271 KE",
    "sg:province":"Friesland",
    "wof:name":"Hoogwater, W J",
    "wof:placetype":"venue"
},
  "geometry": {"coordinates":[6.035156,53.261845],"type":"Point"}
}