{
  "type": "Feature",
  "properties": {
    "iso:country":"NL",
    "sg:address":"Zeelandsestraat 36",
    "sg:city":"Millingen A/D Rijn",
    "sg:orig_category":"Kappers",
    "sg:phone":"+31 481 432 683",
    "sg:postcode":"6566 DJ",
    "sg:province":"Gelderland",
    "wof:name":"Jacqueline'S Haarservice",
    "wof:placetype":"venue"
},
  "geometry": {"coordinates":[6.0411272049,51.862361908],"type":"Point"}
}