{
  "type": "Feature",
  "properties": {
    "addr:full":"De Morgen 1 Hellouw Gelderland 4174 GW",
    "addr:housenumber":"1",
    "addr:postcode":"4174 gw",
    "addr:street":"De Morgen;Gelderland",
    "iso:country":"NL",
    "sg:address":"De Morgen 1",
    "sg:city":"Hellouw",
    "sg:orig_category":"Verenigingsgebouwen",
    "sg:phone":"+31 418 581 541",
    "sg:postcode":"4174 GW",
    "sg:province":"Gelderland",
    "sg:website":"http://www.biskamp.nl",
    "wof:name":"Biskamp, De",
    "wof:placetype":"venue"
},
  "geometry": {"coordinates":[5.177954,51.827785],"type":"Point"}
}