{
  "type": "Feature",
  "properties": {
    "addr:full":"Ypeloweg 41 Wierden Overijssel 7642 NT",
    "addr:housenumber":"41",
    "addr:postcode":"7642 nt",
    "addr:street":"Ypeloweg",
    "iso:country":"NL",
    "sg:address":"Ypeloweg 41",
    "sg:city":"Wierden",
    "sg:orig_category":"Fruit And Groenten Gh",
    "sg:phone":"+31 546 571 923",
    "sg:postcode":"7642 NT",
    "sg:province":"Overijssel",
    "wof:name":"J.A.H. Eertink",
    "wof:placetype":"venue"
},
  "geometry": {"coordinates":[6.58652,52.338806],"type":"Point"}
}