{
  "type": "Feature",
  "properties": {
    "addr:full":"Kreugelstr 37 Eindhoven Noord-Brabant 5616 SE",
    "addr:housenumber":"37",
    "addr:postcode":"5616 se",
    "addr:street":"Kreugelstr",
    "iso:country":"NL",
    "sg:address":"Kreugelstr 37",
    "sg:city":"Eindhoven",
    "sg:orig_category":"Psychotherapeuten",
    "sg:phone":"+31 40 844 0024",
    "sg:postcode":"5616 SE",
    "sg:province":"Noord-Brabant",
    "wof:name":"Huijnen, M J G F",
    "wof:placetype":"venue"
},
  "geometry": {"coordinates":[5.448874,51.446743],"type":"Point"}
}