{
  "type": "Feature",
  "properties": {
    "iso:country":"NL",
    "sg:address":"Lage Brugweg 10",
    "sg:city":"Helenaveen",
    "sg:orig_category":"Hoefdierhouderijen",
    "sg:phone":"+31 493 539 542",
    "sg:postcode":"5759 PK",
    "sg:province":"Noord-Brabant",
    "wof:name":"Dressuurstal Rohan Vof",
    "wof:placetype":"venue"
},
  "geometry": {"coordinates":[5.909866,51.386009],"type":"Point"}
}