{
  "type": "Feature",
  "properties": {
    "addr:full":"Wencopperwg 41 Barneveld Gelderland 3771 PN",
    "addr:housenumber":"41",
    "addr:postcode":"3771 pn",
    "addr:street":"Wencopperwg;Gelderland",
    "iso:country":"NL",
    "sg:address":"Wencopperwg 41",
    "sg:city":"Barneveld",
    "sg:orig_category":"Verenigingen En Stichtingen",
    "sg:phone":"+31 342 464 104",
    "sg:postcode":"3771 PN",
    "sg:province":"Gelderland",
    "wof:name":"Zeumerpop",
    "wof:placetype":"venue"
},
  "geometry": {"coordinates":[5.629873,52.163372],"type":"Point"}
}