{
  "type": "Feature",
  "properties": {
    "addr:full":"Galgeriet 11 Monnickendam Noord-Holland 1141 GC",
    "addr:housenumber":"11",
    "addr:postcode":"1141 gc",
    "addr:street":"Galgeriet",
    "iso:country":"NL",
    "sg:address":"Galgeriet 11",
    "sg:city":"Monnickendam",
    "sg:orig_category":"Autoschade- Herstelbedrijven",
    "sg:phone":"+31 299 651 894",
    "sg:postcode":"1141 GC",
    "sg:province":"Noord-Holland",
    "wof:name":"Lingen En Zoon, J Van Der",
    "wof:placetype":"venue"
},
  "geometry": {"coordinates":[5.039682,52.459122],"type":"Point"}
}