{
  "type": "Feature",
  "properties": {
    "addr:full":"Burgemeester Reigerstr 72 Utrecht Utrecht 3581 KW",
    "addr:housenumber":"72",
    "addr:postcode":"3581 kw",
    "addr:street":"Burgemeester Reigerstr",
    "iso:country":"NL",
    "sg:address":"Burgemeester Reigerstr 72",
    "sg:city":"Utrecht",
    "sg:orig_category":"Verpakkingsmachines Fab",
    "sg:phone":"+31 30 251 8880",
    "sg:postcode":"3581 KW",
    "sg:province":"Utrecht",
    "wof:name":"Dutch Pack International Bv",
    "wof:placetype":"venue"
},
  "geometry": {"coordinates":[5.136913,52.089188],"type":"Point"}
}