{
  "type": "Feature",
  "properties": {
    "addr:full":"Helftheuv Passage 88 S Hertogenbosch North Brabant 5224 AP",
    "addr:housenumber":"88",
    "addr:postcode":"5224 ap",
    "addr:street":"Passage;S Hertogenbosch",
    "iso:country":"NL",
    "sg:address":"Helftheuv Passage 88",
    "sg:city":"S Hertogenbosch",
    "sg:classifiers":[
        {
            "category":"Food & Beverages",
            "subcategory":"Fruits & Vegetables",
            "type":"Retail Goods"
        }
    ],
    "sg:phone":"+31 73 614 6573",
    "sg:postcode":"5224 AP",
    "sg:province":"North Brabant",
    "sg:tags":[
        "en",
        "groenten"
    ],
    "wof:name":"Brusselse Poort, De",
    "wof:placetype":"venue"
},
  "geometry": {"coordinates":[5.26795,51.695225],"type":"Point"}
}