{
  "type": "Feature",
  "properties": {
    "addr:full":"J Craandykstr 31 Haarlem North Holland 2032 HP",
    "addr:housenumber":"31",
    "addr:postcode":"2032 hp",
    "iso:country":"NL",
    "sg:address":"J Craandykstr 31",
    "sg:city":"Haarlem",
    "sg:orig_category":"Onteigening",
    "sg:phone":"+31 23 538 8755",
    "sg:postcode":"2032 HP",
    "sg:province":"North Holland",
    "sg:website":"http://www.romeijnsenvastgoed.nl",
    "wof:name":"Romeijnsen Vastgoed Bv",
    "wof:placetype":"venue"
},
  "geometry": {"coordinates":[4.65788,52.379791],"type":"Point"}
}