{
  "type": "Feature",
  "properties": {
    "addr:full":"Dalmsholterdijk 17 Dalmsholte Overijssel 8146 PE",
    "addr:housenumber":"17",
    "addr:postcode":"8146 pe",
    "addr:street":"Dalmsholterdijk",
    "iso:country":"NL",
    "sg:address":"Dalmsholterdijk 17",
    "sg:city":"Dalmsholte",
    "sg:orig_category":"Zuivelproducten",
    "sg:phone":"+31 529 458 232",
    "sg:postcode":"8146 PE",
    "sg:province":"Overijssel",
    "wof:name":"Kaasboerdery Heileuver",
    "wof:placetype":"venue"
},
  "geometry": {"coordinates":[6.34986,52.480476],"type":"Point"}
}