{
  "type": "Feature",
  "properties": {
    "addr:full":"Langestr 104 Delden Overijssel 7491 AK",
    "addr:housenumber":"104",
    "addr:postcode":"7491 ak",
    "iso:country":"NL",
    "sg:address":"Langestr 104",
    "sg:city":"Delden",
    "sg:orig_category":"Cafetaria'S",
    "sg:phone":"+31 74 376 1133",
    "sg:postcode":"7491 AK",
    "sg:province":"Overijssel",
    "wof:name":"Schwerings Bedrijven Vof",
    "wof:placetype":"venue"
},
  "geometry": {"coordinates":[6.703992,52.261093],"type":"Point"}
}