{
  "type": "Feature",
  "properties": {
    "addr:full":"A Jacobsln 25 Amersfoort Utrecht 3818 LP",
    "addr:housenumber":"25",
    "addr:postcode":"3818 lp",
    "iso:country":"NL",
    "sg:address":"A Jacobsln 25",
    "sg:city":"Amersfoort",
    "sg:orig_category":"Vertaalbureaus",
    "sg:phone":"+31 33 465 7620",
    "sg:postcode":"3818 LP",
    "sg:province":"Utrecht",
    "wof:name":"Syntagma",
    "wof:placetype":"venue"
},
  "geometry": {"coordinates":[5.386085,52.152325],"type":"Point"}
}