{
  "type": "Feature",
  "properties": {
    "addr:full":"Dorpsstraat 25 Giessenburg Zuid-Holland 3381 AD",
    "addr:housenumber":"25",
    "addr:postcode":"3381 ad",
    "addr:street":"Dorpsstraat",
    "iso:country":"NL",
    "sg:address":"Dorpsstraat 25",
    "sg:city":"Giessenburg",
    "sg:orig_category":"Technische Studies And Onderzoek",
    "sg:phone":"+31 184 652 163",
    "sg:postcode":"3381 AD",
    "sg:province":"Zuid-Holland",
    "wof:name":"Montage Rb",
    "wof:placetype":"venue"
},
  "geometry": {"coordinates":[4.890084,51.852383],"type":"Point"}
}