{
  "type": "Feature",
  "properties": {
    "addr:full":"Tungeler Dorpsstr 84 Weert Limburg 6005 RK",
    "addr:housenumber":"84",
    "addr:postcode":"6005 rk",
    "addr:street":"Tungeler;Weert Limburg",
    "iso:country":"NL",
    "sg:address":"Tungeler Dorpsstr 84",
    "sg:city":"Weert",
    "sg:orig_category":"Wassalons",
    "sg:phone":"+31 495 563 558",
    "sg:postcode":"6005 RK",
    "sg:province":"Limburg",
    "wof:name":"Strijkcentrale",
    "wof:placetype":"venue"
},
  "geometry": {"coordinates":[5.745349884,51.2140808105],"type":"Point"}
}