{
  "type": "Feature",
  "properties": {
    "addr:full":"Orthen 53 Den Bosch Noord-Brabant 5231 XP",
    "addr:housenumber":"53",
    "addr:postcode":"5231 xp",
    "addr:street":"Orthen",
    "iso:country":"NL",
    "sg:address":"Orthen 53",
    "sg:city":"Den Bosch",
    "sg:orig_category":"Architecten",
    "sg:phone":"+31 73 641 2133",
    "sg:postcode":"5231 XP",
    "sg:province":"Noord-Brabant",
    "wof:name":"Passchier & Visser Architecten Bv",
    "wof:placetype":"venue"
},
  "geometry": {"coordinates":[5.30419,51.705769],"type":"Point"}
}