{
  "type": "Feature",
  "properties": {
    "addr:full":"De Dieze 22 Best Noord-Brabant 5684 PT",
    "addr:housenumber":"22",
    "addr:postcode":"5684 pt",
    "addr:street":"De Dieze",
    "iso:country":"NL",
    "sg:address":"De Dieze 22",
    "sg:city":"Best",
    "sg:orig_category":"Hogedrukreinigings- Apparatuur",
    "sg:phone":"+31 499 375 445",
    "sg:postcode":"5684 PT",
    "sg:province":"Noord-Brabant",
    "wof:name":"K?rcher Benelux",
    "wof:placetype":"venue"
},
  "geometry": {"coordinates":[-101.619545,31.221083],"type":"Point"}
}