{
  "type": "Feature",
  "properties": {
    "addr:full":"Beelsln 9 Haarlem North Holland 2012 PK",
    "addr:housenumber":"9",
    "addr:postcode":"2012 pk",
    "addr:street":"Beelsln",
    "iso:country":"NL",
    "sg:address":"Beelsln 9",
    "sg:city":"Haarlem",
    "sg:orig_category":"Ziekenhuizen, Sanatoria, Verpleeghuizen",
    "sg:phone":"+31 23 548 4500",
    "sg:postcode":"2012 PK",
    "sg:province":"North Holland",
    "wof:name":"Zuiderhout",
    "wof:placetype":"venue"
},
  "geometry": {"coordinates":[4.642253,52.380562],"type":"Point"}
}