{
  "type": "Feature",
  "properties": {
    "iso:country":"NL",
    "sg:address":"W C De Withstraat 1",
    "sg:city":"Zuidhorn",
    "sg:orig_category":"Bejaardeninstellingen And Serviceflats",
    "sg:phone":"+31 594 502 731",
    "sg:postcode":"9801 GA",
    "sg:province":"Groningen",
    "wof:name":"Zorgcentrum Westerburcht",
    "wof:placetype":"venue"
},
  "geometry": {"coordinates":[6.401463,53.240906],"type":"Point"}
}