{
  "type": "Feature",
  "properties": {
    "addr:full":"Postbus 45 Breukelen Ut 3620 AA",
    "addr:housenumber":"45",
    "addr:postcode":"3620 aa",
    "addr:street":"Postbus",
    "iso:country":"NL",
    "sg:address":"Postbus 45",
    "sg:city":"Breukelen Ut",
    "sg:orig_category":"Scholen Voor Basisonderwijs",
    "sg:phone":"+31 346 261 820",
    "sg:postcode":"3620 AA",
    "wof:name":"Vijverhof",
    "wof:placetype":"venue"
},
  "geometry": {"coordinates":[5.00158,52.172958],"type":"Point"}
}