{
  "type": "Feature",
  "properties": {
    "addr:full":"John F Kennedylaan 2 Eindhoven Noord-Brabant 5612 AB",
    "addr:housenumber":"2",
    "addr:postcode":"5612 ab",
    "addr:street":"John F Kennedylaan",
    "iso:country":"NL",
    "sg:address":"John F Kennedylaan 2",
    "sg:city":"Eindhoven",
    "sg:orig_category":"Bedrijfsopleidingen",
    "sg:phone":"+31 40 232 3242",
    "sg:postcode":"5612 AB",
    "sg:province":"Noord-Brabant",
    "wof:name":"Bedrijfskunde Leergang, Stichting",
    "wof:placetype":"venue"
},
  "geometry": {"coordinates":[5.481396,51.445889],"type":"Point"}
}