{
  "type": "Feature",
  "properties": {
    "iso:country":"NL",
    "sg:address":"Concordiastr 14B",
    "sg:city":"Breda",
    "sg:orig_category":"Onderwijsmateriaal",
    "sg:phone":"+31 76 522 6142",
    "sg:postcode":"4811 NA",
    "sg:province":"Noord-Brabant",
    "wof:name":"Nexus",
    "wof:placetype":"venue"
},
  "geometry": {"coordinates":[4.775519,51.583988],"type":"Point"}
}