{
  "type": "Feature",
  "properties": {
    "addr:full":"Zwinstraat 50 Den Oever Noord-Holland 1779 BH",
    "addr:housenumber":"50",
    "addr:postcode":"1779 bh",
    "addr:street":"Zwinstraat",
    "iso:country":"NL",
    "sg:address":"Zwinstraat 50",
    "sg:city":"Den Oever",
    "sg:classifiers":[
        {
            "category":"Education",
            "subcategory":"Preschool",
            "type":"Public Place"
        }
    ],
    "sg:phone":"+31 227 511 787",
    "sg:postcode":"1779 BH",
    "sg:province":"Noord-Holland",
    "sg:tags":[
        "kleuteronderwijs",
        "basis-"
    ],
    "wof:name":"Openbare Basisschool Om De Oost",
    "wof:placetype":"venue"
},
  "geometry": {"coordinates":[5.032267,52.934071],"type":"Point"}
}