{
  "type": "Feature",
  "properties": {
    "iso:country":"NL",
    "sg:address":"Zuiderdiep 210",
    "sg:city":"Valthermond",
    "sg:orig_category":"Bouwmaterialen Gh",
    "sg:phone":"+31 599 662 232",
    "sg:postcode":"7876 AL",
    "sg:province":"Drenthe",
    "wof:name":"Air-O-Tunnel Bv",
    "wof:placetype":"venue"
},
  "geometry": {"coordinates":[6.942007,52.869949],"type":"Point"}
}