{
  "type": "Feature",
  "properties": {
    "addr:full":"Anjerstr 16 Raalte Overijssel 8102 ZX",
    "addr:housenumber":"16",
    "addr:postcode":"8102 zx",
    "addr:street":"Anjerstr",
    "iso:country":"NL",
    "sg:address":"Anjerstr 16",
    "sg:city":"Raalte",
    "sg:orig_category":"Autorijscholen",
    "sg:phone":"+31 572 354 648",
    "sg:postcode":"8102 ZX",
    "sg:province":"Overijssel",
    "wof:name":"Brink, J Van",
    "wof:placetype":"venue"
},
  "geometry": {"coordinates":[6.271671,52.39257],"type":"Point"}
}