{
  "type": "Feature",
  "properties": {
    "addr:full":"Werfpad 7 'S Hertogenbosch Noord-Brabant 5212 VJ",
    "addr:housenumber":"7 ' s",
    "addr:postcode":"5212 vj",
    "addr:street":"Werfpad",
    "iso:country":"NL",
    "sg:address":"Werfpad 7",
    "sg:city":"'S Hertogenbosch",
    "sg:orig_category":"Fitnesscentra",
    "sg:phone":"+31 73 614 6238",
    "sg:postcode":"5212 VJ",
    "sg:province":"Noord-Brabant",
    "wof:name":"Sport- En Bewegingscentrum Olympia Bv",
    "wof:placetype":"venue"
},
  "geometry": {"coordinates":[5.302475,51.697289],"type":"Point"}
}