{
  "type": "Feature",
  "properties": {
    "addr:full":"Oude Vismarkt 44 Zwolle Overijssel 8011 TB",
    "addr:housenumber":"44",
    "addr:postcode":"8011 tb",
    "addr:street":"Oude Vismarkt",
    "iso:country":"NL",
    "sg:address":"Oude Vismarkt 44",
    "sg:city":"Zwolle",
    "sg:orig_category":"Werving And Selectie Van Tijdelijk Personeel And Uitzendkantoren",
    "sg:phone":"+31 38 426 0920",
    "sg:postcode":"8011 TB",
    "sg:province":"Overijssel",
    "wof:name":"Unique Uitzendburo",
    "wof:placetype":"venue"
},
  "geometry": {"coordinates":[6.0947737694,52.5116539001],"type":"Point"}
}