{
  "type": "Feature",
  "properties": {
    "addr:full":"Kievitsweg 22 Grijpskerk Groningen 9843 HA",
    "addr:housenumber":"22",
    "addr:postcode":"9843 ha",
    "addr:street":"Kievitsweg",
    "iso:country":"NL",
    "sg:address":"Kievitsweg 22",
    "sg:city":"Grijpskerk",
    "sg:orig_category":"Makelaars In Onroerend Goed",
    "sg:phone":"+31 594 212 687",
    "sg:postcode":"9843 HA",
    "sg:province":"Groningen",
    "wof:name":"Balkema Bedrijvencentrum",
    "wof:placetype":"venue"
},
  "geometry": {"coordinates":[6.306842,53.267811],"type":"Point"}
}