{
  "type": "Feature",
  "properties": {
    "addr:full":"Dominee D A Vd Boschstr 25 Zwijndrecht Zuid-Holland 3333 BB",
    "addr:housenumber":"25",
    "addr:postcode":"3333 bb",
    "addr:street":"Dominee D A",
    "iso:country":"NL",
    "sg:address":"Dominee D A Vd Boschstr 25",
    "sg:city":"Zwijndrecht",
    "sg:orig_category":"Verzekeringen",
    "sg:phone":"+31 78 612 7184",
    "sg:postcode":"3333 BB",
    "sg:province":"Zuid-Holland",
    "wof:name":"A.B.C. Vd Stel Ass Kant + Acc En Belast",
    "wof:placetype":"venue"
},
  "geometry": {"coordinates":[4.629039,51.80978],"type":"Point"}
}