{
  "type": "Feature",
  "properties": {
    "addr:full":"Gans 5 Zoeterwoude Zuid-Holland 2381 KA",
    "addr:housenumber":"5",
    "addr:postcode":"2381 ka",
    "addr:street":"Gans",
    "iso:country":"NL",
    "sg:address":"Gans 5",
    "sg:city":"Zoeterwoude",
    "sg:classifiers":[
        {
            "category":"Personal",
            "subcategory":"Nail Salon",
            "type":"Services"
        }
    ],
    "sg:phone":"+31 71 580 4403",
    "sg:postcode":"2381 KA",
    "sg:province":"Zuid-Holland",
    "sg:tags":[
        "pedicure"
    ],
    "wof:name":"Swart Corrie",
    "wof:placetype":"venue"
},
  "geometry": {"coordinates":[4.49331,52.121357],"type":"Point"}
}