{
  "type": "Feature",
  "properties": {
    "addr:full":"Oorgat 36 Edam North Holland 1135 CR",
    "addr:housenumber":"36",
    "addr:postcode":"1135 cr",
    "addr:street":"Oorgat",
    "iso:country":"NL",
    "sg:address":"Oorgat 36",
    "sg:city":"Edam",
    "sg:orig_category":"Fotostudio'S And Fotografen",
    "sg:phone":"+31 299 315 081",
    "sg:postcode":"1135 CR",
    "sg:province":"North Holland",
    "wof:name":"Bas Vroege",
    "wof:placetype":"venue"
},
  "geometry": {"coordinates":[5.064673,52.515396],"type":"Point"}
}