{
  "type": "Feature",
  "properties": {
    "addr:full":"De Kolk 29 Swifterbant Flevoland 8255 PA",
    "addr:housenumber":"29",
    "addr:postcode":"8255",
    "addr:street":"De Kolk;Flevoland",
    "iso:country":"NL",
    "sg:address":"De Kolk 29",
    "sg:city":"Swifterbant",
    "sg:classifiers":[
        {
            "category":"Retail",
            "subcategory":"Auto Repair",
            "type":"Services"
        }
    ],
    "sg:phone":"+31 321 335 070",
    "sg:postcode":"8255 PA",
    "sg:province":"Flevoland",
    "sg:tags":[
        "garage"
    ],
    "wof:name":"Flevoservice & Flevowash Bv",
    "wof:placetype":"venue"
},
  "geometry": {"coordinates":[5.649555,52.574093],"type":"Point"}
}