{
  "type": "Feature",
  "properties": {
    "addr:full":"Industrieweg N 4C Amerongen Utrecht 3958 VT",
    "addr:housenumber":"4c",
    "addr:postcode":"3958",
    "addr:street":"Industrieweg N",
    "iso:country":"NL",
    "sg:address":"Industrieweg N 4C",
    "sg:city":"Amerongen",
    "sg:orig_category":"Fitnesscentra",
    "sg:phone":"+31 343 461 397",
    "sg:postcode":"3958 VT",
    "sg:province":"Utrecht",
    "wof:name":"Fitcentrum Aart Stigter'S",
    "wof:placetype":"venue"
},
  "geometry": {"coordinates":[5.454883,52.003807],"type":"Point"}
}