{
  "type": "Feature",
  "properties": {
    "addr:full":"Grebbestraat 5 Amersfoort Utrecht 3812 JC",
    "addr:housenumber":"5",
    "addr:postcode":"3812 jc",
    "addr:street":"Grebbestraat",
    "iso:country":"NL",
    "sg:address":"Grebbestraat 5",
    "sg:city":"Amersfoort",
    "sg:orig_category":"Meubelstoffering",
    "sg:phone":"+31 33 461 9067",
    "sg:postcode":"3812 JC",
    "sg:province":"Utrecht",
    "wof:name":"Koolaard, A",
    "wof:placetype":"venue"
},
  "geometry": {"coordinates":[5.365126,52.160618],"type":"Point"}
}