{
  "type": "Feature",
  "properties": {
    "iso:country":"NL",
    "sg:address":"Marwyksoord 3",
    "sg:city":"Marwyksoord",
    "sg:orig_category":"Begrafenisverzorging",
    "sg:phone":"+31 592 242 764",
    "sg:postcode":"9448 XA",
    "sg:province":"Drenthe",
    "wof:name":"Rolde Eo",
    "wof:placetype":"venue"
},
  "geometry": {"coordinates":[6.66101,52.960274],"type":"Point"}
}