{
  "type": "Feature",
  "properties": {
    "addr:full":"Reeweg 12 Werkendam Noord-Brabant 4251 XJ",
    "addr:housenumber":"12",
    "addr:postcode":"4251 xj",
    "addr:street":"Reeweg",
    "iso:country":"NL",
    "sg:address":"Reeweg 12",
    "sg:city":"Werkendam",
    "sg:orig_category":"Makelaars In Onroerend Goed",
    "sg:phone":"+31 183 505 124",
    "sg:postcode":"4251 XJ",
    "sg:province":"Noord-Brabant",
    "wof:name":"De Keijzer Vof",
    "wof:placetype":"venue"
},
  "geometry": {"coordinates":[4.897136,51.809994],"type":"Point"}
}