{
  "type": "Feature",
  "properties": {
    "addr:full":"Stedekestr 11 Goirle Noord-Brabant 5051 RR",
    "addr:housenumber":"11",
    "addr:postcode":"5051 rr",
    "addr:street":"Stedekestr",
    "iso:country":"NL",
    "sg:address":"Stedekestr 11",
    "sg:city":"Goirle",
    "sg:orig_category":"Makelaars En Adviseurs Onroerende Goederen",
    "sg:phone":"+31 13 534 5346",
    "sg:postcode":"5051 RR",
    "sg:province":"Noord-Brabant",
    "wof:name":"Simons, P A M",
    "wof:placetype":"venue"
},
  "geometry": {"coordinates":[5.06241,51.521473],"type":"Point"}
}