{
  "type": "Feature",
  "properties": {
    "addr:full":"Noordkade 92A Waddinxveen Zuid-Holland 2741 GA",
    "addr:housenumber":"92a",
    "addr:postcode":"2741 ga",
    "addr:street":"Noordkade",
    "iso:country":"NL",
    "sg:address":"Noordkade 92A",
    "sg:city":"Waddinxveen",
    "sg:orig_category":"Gordijnen",
    "sg:phone":"+31 182 611 419",
    "sg:postcode":"2741 GA",
    "sg:province":"Zuid-Holland",
    "wof:name":"Jongeneel Gordijnen",
    "wof:placetype":"venue"
},
  "geometry": {"coordinates":[4.661855,52.055027],"type":"Point"}
}