{
  "type": "Feature",
  "properties": {
    "addr:full":"Weteringpad 34 Soest Utrecht 3762 EN",
    "addr:housenumber":"34",
    "addr:postcode":"3762 en",
    "addr:street":"Weteringpad",
    "iso:country":"NL",
    "sg:address":"Weteringpad 34",
    "sg:city":"Soest",
    "sg:orig_category":"Administratie- En Boekhoudkantoren",
    "sg:phone":"+31 35 609 0307",
    "sg:postcode":"3762 EN",
    "sg:province":"Utrecht",
    "wof:name":"Bruin, De",
    "wof:placetype":"venue"
},
  "geometry": {"coordinates":[5.276314,52.180477],"type":"Point"}
}