{
  "type": "Feature",
  "properties": {
    "iso:country":"NL",
    "sg:address":"Postbus 597",
    "sg:city":"Hoofddorp",
    "sg:orig_category":"Elektronica - Ontwikkeling En Groothandel",
    "sg:phone":"+31 252 412 736",
    "sg:postcode":"2130 AN",
    "sg:province":"Noord-Holland",
    "wof:name":"Lime",
    "wof:placetype":"venue"
},
  "geometry": {"coordinates":[4.68729,52.308708],"type":"Point"}
}