{
  "type": "Feature",
  "properties": {
    "iso:country":"NL",
    "sg:address":"Verl Stationswg 16",
    "sg:city":"Zuidlaren",
    "sg:classifiers":[
        {
            "category":"Retail",
            "subcategory":"Auto Repair",
            "type":"Services"
        }
    ],
    "sg:phone":"+31 50 409 2420",
    "sg:postcode":"9471 PL",
    "sg:province":"Drenthe",
    "sg:tags":[
        "garage"
    ],
    "wof:name":"Hogenberg, D",
    "wof:placetype":"venue"
},
  "geometry": {"coordinates":[6.663299,53.088161],"type":"Point"}
}