{
  "type": "Feature",
  "properties": {
    "addr:full":"Kerkstraat 76 Sprang-Capelle North Brabant 5161 EE",
    "addr:housenumber":"76",
    "addr:postcode":"5161 ee",
    "addr:street":"Kerkstraat",
    "iso:country":"NL",
    "sg:address":"Kerkstraat 76",
    "sg:city":"Sprang-Capelle",
    "sg:orig_category":"Kappers",
    "sg:phone":"+31 416 273 681",
    "sg:postcode":"5161 EE",
    "sg:province":"North Brabant",
    "wof:name":"Maison Antoine",
    "wof:placetype":"venue"
},
  "geometry": {"coordinates":[5.047831,51.669575],"type":"Point"}
}