{
  "type": "Feature",
  "properties": {
    "iso:country":"NL",
    "sg:address":"C Fabritiusln 12",
    "sg:city":"Oegstgeest",
    "sg:orig_category":"Pensioenen",
    "sg:phone":"+31 71 515 6372",
    "sg:postcode":"2343 SG",
    "sg:province":"South Holland",
    "wof:name":"Meijer, Mr B H G",
    "wof:placetype":"venue"
},
  "geometry": {"coordinates":[4.478868,52.187065],"type":"Point"}
}