{
  "type": "Feature",
  "properties": {
    "addr:full":"Industriewg 4E Assendelft North Holland 1566 JP",
    "addr:housenumber":"4e",
    "addr:postcode":"1566 jp",
    "addr:street":"Industriewg",
    "iso:country":"NL",
    "sg:address":"Industriewg 4E",
    "sg:city":"Assendelft",
    "sg:orig_category":"Autoreclame",
    "sg:phone":"+31 75 642 7324",
    "sg:postcode":"1566 JP",
    "sg:province":"North Holland",
    "wof:name":"Sign Factory, The",
    "wof:placetype":"venue"
},
  "geometry": {"coordinates":[4.765964,52.490788],"type":"Point"}
}