{
  "type": "Feature",
  "properties": {
    "addr:full":"Stevinstraat 155/2 'S Gravenhage South Holland 2587 ED",
    "addr:housenumber":"155 / 2",
    "addr:postcode":"2587 ed",
    "addr:street":"Stevinstraat;' S Gravenhage",
    "iso:country":"NL",
    "sg:address":"Stevinstraat 155/2",
    "sg:city":"'S Gravenhage",
    "sg:orig_category":"Paramedische Behandelingen",
    "sg:phone":"+31 70 351 4700",
    "sg:postcode":"2587 ED",
    "sg:province":"South Holland",
    "wof:name":"K. Jironet",
    "wof:placetype":"venue"
},
  "geometry": {"coordinates":[4.290311,52.110294],"type":"Point"}
}