{
  "type": "Feature",
  "properties": {
    "addr:full":"Torenvalk 36 Raalte Overijssel 8103 GK",
    "addr:housenumber":"36",
    "addr:postcode":"8103 gk",
    "addr:street":"Torenvalk",
    "iso:country":"NL",
    "sg:address":"Torenvalk 36",
    "sg:city":"Raalte",
    "sg:orig_category":"Kappers",
    "sg:phone":"+31 572 354 997",
    "sg:postcode":"8103 GK",
    "sg:province":"Overijssel",
    "wof:name":"Thea",
    "wof:placetype":"venue"
},
  "geometry": {"coordinates":[6.289708,52.39782],"type":"Point"}
}