{
  "type": "Feature",
  "properties": {
    "addr:full":"Ryksstrwg 54A Ridderkerk Zuid-Holland 2988 BK",
    "addr:housenumber":"54a",
    "addr:postcode":"2988 bk",
    "addr:street":"Ryksstrwg",
    "iso:country":"NL",
    "sg:address":"Ryksstrwg 54A",
    "sg:city":"Ridderkerk",
    "sg:orig_category":"Wegenbouw - Materieel",
    "sg:phone":"+31 180 423 779",
    "sg:postcode":"2988 BK",
    "sg:province":"Zuid-Holland",
    "wof:name":"Bosua",
    "wof:placetype":"venue"
},
  "geometry": {"coordinates":[4.5966901779,51.8496437073],"type":"Point"}
}