{
  "type": "Feature",
  "properties": {
    "iso:country":"NL",
    "sg:address":"Hallenweg 28",
    "sg:city":"Best",
    "sg:orig_category":"Kantoorartikelen",
    "sg:phone":"+31 499 397 830",
    "sg:postcode":"5683 CT",
    "sg:province":"Texas",
    "wof:name":"Cieba Kantoor-Projektinrichting Bv",
    "wof:placetype":"venue"
},
  "geometry": {"coordinates":[-101.6181335449,31.2242507935],"type":"Point"}
}