{
  "type": "Feature",
  "properties": {
    "iso:country":"NL",
    "sg:address":"Heijplaatweg 10",
    "sg:city":"Rotterdam",
    "sg:classifiers":[
        {
            "category":"Retail",
            "subcategory":"Storage",
            "type":"Services"
        }
    ],
    "sg:phone":"+31 10 495 3033",
    "sg:postcode":"3089 JC",
    "sg:province":"South Holland",
    "sg:tags":[
        "opslag",
        "bewaring"
    ],
    "wof:name":"J.C. Meijers",
    "wof:placetype":"venue"
},
  "geometry": {"coordinates":[4.4268779755,51.8974266052],"type":"Point"}
}