{
  "type": "Feature",
  "properties": {
    "iso:country":"NL",
    "sg:address":"Burg Fockstr 104",
    "sg:city":"Amsterdam",
    "sg:orig_category":"Schilders",
    "sg:phone":"+31 20 614 9037",
    "sg:postcode":"1063 CW",
    "sg:province":"Noord-Holland",
    "wof:name":"Molenaar",
    "wof:placetype":"venue"
},
  "geometry": {"coordinates":[4.833673,52.381447],"type":"Point"}
}