{
  "type": "Feature",
  "properties": {
    "addr:full":"Benedenweg 117 Sint Pancras Noord-Holland 1834 AL",
    "addr:housenumber":"117",
    "addr:postcode":"1834 al",
    "addr:street":"Benedenweg",
    "iso:country":"NL",
    "sg:address":"Benedenweg 117",
    "sg:city":"Sint Pancras",
    "sg:orig_category":"Elektronische Bedrijfsinstallaties",
    "sg:phone":"+31 72 564 1393",
    "sg:postcode":"1834 AL",
    "sg:province":"Noord-Holland",
    "wof:name":"Winter Security Bv",
    "wof:placetype":"venue"
},
  "geometry": {"coordinates":[4.782116,52.662109],"type":"Point"}
}