{
  "type": "Feature",
  "properties": {
    "iso:country":"NL",
    "sg:address":"Zuidereinde 1D",
    "sg:city":"S Graveland",
    "sg:orig_category":"Grafisch Ontwerpers",
    "sg:phone":"+31 35 656 0073",
    "sg:postcode":"1243 KG",
    "sg:province":"Noord-Holland",
    "wof:name":"Bard '87",
    "wof:placetype":"venue"
},
  "geometry": {"coordinates":[5.121892,52.23793],"type":"Point"}
}