{
  "type": "Feature",
  "properties": {
    "addr:full":"Reitschewg 1 S Hertogenbosch Noord-Brabant 5232 BX",
    "addr:housenumber":"1",
    "addr:postcode":"5232 bx",
    "addr:street":"Reitschewg",
    "iso:country":"NL",
    "sg:address":"Reitschewg 1",
    "sg:city":"S Hertogenbosch",
    "sg:orig_category":"Adviesbureaus Bouwkunde",
    "sg:phone":"+31 73 640 9409",
    "sg:postcode":"5232 BX",
    "sg:province":"Noord-Brabant",
    "sg:website":"http://www.hevo.nl",
    "wof:name":"Hevo Bv",
    "wof:placetype":"venue"
},
  "geometry": {"coordinates":[5.338929,51.708649],"type":"Point"}
}