{
  "type": "Feature",
  "properties": {
    "addr:full":"Piusplein 75 Tilburg Noord-Brabant 5038 WP",
    "addr:housenumber":"75",
    "addr:postcode":"5038 wp",
    "addr:street":"Piusplein",
    "iso:country":"NL",
    "sg:address":"Piusplein 75",
    "sg:city":"Tilburg",
    "sg:classifiers":[
        {
            "category":"Fast Food",
            "type":"Food & Drink"
        }
    ],
    "sg:phone":"+31 13 580 2634",
    "sg:postcode":"5038 WP",
    "sg:province":"Noord-Brabant",
    "sg:tags":[
        "afhaal",
        "restaurant"
    ],
    "wof:name":"Mcdonald'S Restaurant Tilburg",
    "wof:placetype":"venue"
},
  "geometry": {"coordinates":[5.090572,51.555637],"type":"Point"}
}