{
  "type": "Feature",
  "properties": {
    "addr:full":"Noord 61 Franeker Provincie Friesland 8801 KT",
    "addr:housenumber":"61",
    "addr:postcode":"8801 kt",
    "addr:street":"Noord;Provincie Friesland",
    "iso:country":"NL",
    "sg:address":"Noord 61",
    "sg:city":"Franeker",
    "sg:orig_category":"Woningbouw- Verenigingen En -Stichtingen",
    "sg:phone":"+31 517 396 377",
    "sg:postcode":"8801 KT",
    "sg:province":"Provincie Friesland",
    "wof:name":"Wooncentr Ockingahiem",
    "wof:placetype":"venue"
},
  "geometry": {"coordinates":[5.5434589386,53.1871070862],"type":"Point"}
}