{
  "type": "Feature",
  "properties": {
    "addr:full":"Rusthoflaan 50A Rotterdam South Holland 3034 XM",
    "addr:housenumber":"50a",
    "addr:postcode":"3034 xm",
    "addr:street":"Rusthoflaan",
    "iso:country":"NL",
    "sg:address":"Rusthoflaan 50A",
    "sg:city":"Rotterdam",
    "sg:orig_category":"Fietshandelaren",
    "sg:phone":"+31 10 413 4370",
    "sg:postcode":"3034 XM",
    "sg:province":"South Holland",
    "wof:name":"Firma C J Van Den Dool & Zoon",
    "wof:placetype":"venue"
},
  "geometry": {"coordinates":[4.495922,51.935608],"type":"Point"}
}