{
  "type": "Feature",
  "properties": {
    "addr:full":"Kastanjeln 8 Hoensbroek Limburg 6431 GL",
    "addr:housenumber":"8",
    "addr:postcode":"6431 gl",
    "addr:street":"Kastanjeln",
    "iso:country":"NL",
    "sg:address":"Kastanjeln 8",
    "sg:city":"Hoensbroek",
    "sg:orig_category":"Kappers",
    "sg:phone":"+31 45 523 2146",
    "sg:postcode":"6431 GL",
    "sg:province":"Limburg",
    "wof:name":"Look Ahead",
    "wof:placetype":"venue"
},
  "geometry": {"coordinates":[5.93659,50.929508],"type":"Point"}
}