{
  "type": "Feature",
  "properties": {
    "addr:full":"Cort Van Der Lindenlaan 13 Naarden Noord-Holland 1412 BW",
    "addr:housenumber":"13",
    "addr:postcode":"1412 bw",
    "addr:street":"Cort Van Der Lindenlaan",
    "iso:country":"NL",
    "sg:address":"Cort Van Der Lindenlaan 13",
    "sg:city":"Naarden",
    "sg:orig_category":"Makelaars In Onroerend Goed",
    "sg:phone":"+31 35 694 1947",
    "sg:postcode":"1412 BW",
    "sg:province":"Noord-Holland",
    "wof:name":"Ass. Kantoor Van Der Schaar, Visser & Sm",
    "wof:placetype":"venue"
},
  "geometry": {"coordinates":[5.147064,52.282944],"type":"Point"}
}