{
  "type": "Feature",
  "properties": {
    "addr:full":"Den Ilp 63 Den Ilp Noord-Holland 1127 PE",
    "addr:housenumber":"63",
    "addr:postcode":"ilp;1127 pe",
    "addr:street":"Den Ilp",
    "iso:country":"NL",
    "sg:address":"Den Ilp 63",
    "sg:city":"Den Ilp",
    "sg:orig_category":"Beeldende Kunstenaars",
    "sg:phone":"+31 20 482 1378",
    "sg:postcode":"1127 PE",
    "sg:province":"Noord-Holland",
    "wof:name":"Heijboer Malomajo Vof",
    "wof:placetype":"venue"
},
  "geometry": {"coordinates":[4.908918,52.450691],"type":"Point"}
}