{
  "type": "Feature",
  "properties": {
    "iso:country":"NL",
    "sg:address":"Buikslotermeerplein 6",
    "sg:city":"Amsterdam",
    "sg:orig_category":"Kansspelen",
    "sg:phone":"+31 20 634 0444",
    "sg:postcode":"1025 EV",
    "sg:province":"North Holland",
    "wof:name":"Lucky Jack",
    "wof:placetype":"venue"
},
  "geometry": {"coordinates":[4.9351100922,52.3993797302],"type":"Point"}
}