{
  "type": "Feature",
  "properties": {
    "addr:full":"Buikslotermeerplein 6 Amsterdam North Holland 1025 EV",
    "addr:housenumber":"6",
    "addr:postcode":"1025 ev",
    "addr:street":"Buikslotermeerplein",
    "iso:country":"NL",
    "sg:address":"Buikslotermeerplein 6",
    "sg:city":"Amsterdam",
    "sg:orig_category":"Kansspelen",
    "sg:phone":"+31 20 634 0444",
    "sg:postcode":"1025 EV",
    "sg:province":"North Holland",
    "wof:name":"Lucky Jack",
    "wof:placetype":"venue"
},
  "geometry": {"coordinates":[4.9351100922,52.3993797302],"type":"Point"}
}