{
  "type": "Feature",
  "properties": {
    "addr:full":"K Blekersstr 12 Amsterdam Noord-Holland 1053 TM",
    "addr:housenumber":"12",
    "addr:postcode":"1053 tm",
    "addr:street":"Blekersstr",
    "iso:country":"NL",
    "sg:address":"K Blekersstr 12",
    "sg:city":"Amsterdam",
    "sg:orig_category":"Verenigingen En Stichtingen",
    "sg:phone":"+31 20 618 9912",
    "sg:postcode":"1053 TM",
    "sg:province":"Noord-Holland",
    "wof:name":"Nerel",
    "wof:placetype":"venue"
},
  "geometry": {"coordinates":[4.865956,52.369583],"type":"Point"}
}