{
  "type": "Feature",
  "properties": {
    "addr:full":"Bunsenstr 125 Dordrecht Zuid-Holland 3316 GC",
    "addr:housenumber":"125",
    "addr:postcode":"3316 gc",
    "iso:country":"NL",
    "sg:address":"Bunsenstr 125",
    "sg:city":"Dordrecht",
    "sg:orig_category":"Elektrotechnische Installatiebureaus",
    "sg:phone":"+31 78 652 0520",
    "sg:postcode":"3316 GC",
    "sg:province":"Zuid-Holland",
    "wof:name":"Merwestroom Bv",
    "wof:placetype":"venue"
},
  "geometry": {"coordinates":[4.63194,51.774529],"type":"Point"}
}