{
  "type": "Feature",
  "properties": {
    "addr:full":"Grt Houtstr 112 Haarlem Noord-Holland 2011 ST",
    "addr:housenumber":"112",
    "addr:postcode":"2011 st",
    "iso:country":"NL",
    "sg:address":"Grt Houtstr 112",
    "sg:city":"Haarlem",
    "sg:orig_category":"Huishoudelijke Apparaten En Artikelen",
    "sg:phone":"+31 23 531 2521",
    "sg:postcode":"2011 ST",
    "sg:province":"Noord-Holland",
    "wof:name":"Blokker Bv",
    "wof:placetype":"venue"
},
  "geometry": {"coordinates":[4.632023,52.378269],"type":"Point"}
}