{
  "type": "Feature",
  "properties": {
    "iso:country":"NL",
    "sg:address":"Brink 14",
    "sg:city":"Baarn",
    "sg:classifiers":[
        {
            "category":"Food & Beverages",
            "subcategory":"Fruits & Vegetables",
            "type":"Retail Goods"
        }
    ],
    "sg:phone":"+31 35 541 5026",
    "sg:postcode":"3741 AL",
    "sg:province":"Utrecht",
    "sg:tags":[
        "groenten"
    ],
    "wof:name":"J Kraay",
    "wof:placetype":"venue"
},
  "geometry": {"coordinates":[5.292252,52.212227],"type":"Point"}
}