{
  "type": "Feature",
  "properties": {
    "addr:full":"Schiebroeksesingel 1 Rotterdam Zuid-Holland 3051 JL",
    "addr:housenumber":"1",
    "addr:postcode":"3051 jl",
    "addr:street":"Schiebroeksesingel",
    "iso:country":"NL",
    "sg:address":"Schiebroeksesingel 1",
    "sg:city":"Rotterdam",
    "sg:orig_category":"Autokeuringen",
    "sg:phone":"+31 10 418 4020",
    "sg:postcode":"3051 JL",
    "sg:province":"Zuid-Holland",
    "wof:name":"Vof M.T. Van Der Wilt & Zoon",
    "wof:placetype":"venue"
},
  "geometry": {"coordinates":[4.474327,51.94622],"type":"Point"}
}