{
  "type": "Feature",
  "properties": {
    "addr:full":"Aluminiumstr 101 Zoetermeer Zuid-Holland 2718 RB",
    "addr:housenumber":"101",
    "addr:postcode":"2718 rb",
    "iso:country":"NL",
    "sg:address":"Aluminiumstr 101",
    "sg:city":"Zoetermeer",
    "sg:orig_category":"Autoschade- Herstelbedrijven",
    "sg:phone":"+31 79 361 1022",
    "sg:postcode":"2718 RB",
    "sg:province":"Zuid-Holland",
    "wof:name":"Elzen Bv, Gebr Den",
    "wof:placetype":"venue"
},
  "geometry": {"coordinates":[4.507835,52.039314],"type":"Point"}
}