{
  "type": "Feature",
  "properties": {
    "addr:full":"Nw Ebbingestr 86 Groningen Groningen 9712 NP",
    "addr:housenumber":"86",
    "addr:postcode":"9712 np",
    "iso:country":"NL",
    "sg:address":"Nw Ebbingestr 86",
    "sg:city":"Groningen",
    "sg:orig_category":"Wasmachines En Wasdrogers - Onderhoud En Reparatie",
    "sg:phone":"+31 50 318 7599",
    "sg:postcode":"9712 NP",
    "sg:province":"Groningen",
    "wof:name":"Onderdelenhuis, Het",
    "wof:placetype":"venue"
},
  "geometry": {"coordinates":[6.5615448952,53.225276947],"type":"Point"}
}