{
  "type": "Feature",
  "properties": {
    "addr:full":"Wittevrouwenstraat 13 Utrecht Utrecht 3512 CS",
    "addr:housenumber":"13",
    "addr:postcode":"3512 cs",
    "addr:street":"Wittevrouwenstraat",
    "iso:country":"NL",
    "sg:address":"Wittevrouwenstraat 13",
    "sg:city":"Utrecht",
    "sg:orig_category":"Wasserettes And Stomerijen",
    "sg:phone":"+31 30 231 8746",
    "sg:postcode":"3512 CS",
    "sg:province":"Utrecht",
    "wof:name":"Wasserette P. Lialiangas",
    "wof:placetype":"venue"
},
  "geometry": {"coordinates":[5.1251978874,52.0949707031],"type":"Point"}
}