{
  "type": "Feature",
  "properties": {
    "addr:full":"Begine 9 Workum Friesland 8711 BG",
    "addr:housenumber":"9",
    "addr:postcode":"8711",
    "addr:street":"Begine",
    "iso:country":"NL",
    "sg:address":"Begine 9",
    "sg:city":"Workum",
    "sg:orig_category":"Keramische Producten Fab",
    "sg:phone":"+31 515 541 926",
    "sg:postcode":"8711 BG",
    "sg:province":"Friesland",
    "wof:name":"Pottenbakkerij Kunst",
    "wof:placetype":"venue"
},
  "geometry": {"coordinates":[5.444276,52.979137],"type":"Point"}
}