{
  "type": "Feature",
  "properties": {
    "addr:full":"Korenbeursstraat 10 Bergen Op Zoom Noord-Brabant 4611 PW",
    "addr:housenumber":"10",
    "addr:postcode":"4611 pw",
    "addr:street":"Korenbeursstraat",
    "iso:country":"NL",
    "sg:address":"Korenbeursstraat 10",
    "sg:city":"Bergen Op Zoom",
    "sg:orig_category":"Verlichting And Huishoudartikelen",
    "sg:phone":"+31 164 235 703",
    "sg:postcode":"4611 PW",
    "sg:province":"Noord-Brabant",
    "wof:name":"Firma Schepers",
    "wof:placetype":"venue"
},
  "geometry": {"coordinates":[4.291527,51.495602],"type":"Point"}
}