{
  "type": "Feature",
  "properties": {
    "iso:country":"NL",
    "sg:address":"Poppestraat 5",
    "sg:city":"Sint Willebrord",
    "sg:classifiers":[
        {
            "category":"Retail",
            "subcategory":"Photofinishing",
            "type":"Services"
        }
    ],
    "sg:phone":"+31 165 382 600",
    "sg:postcode":"4711 JP",
    "sg:province":"North Brabant",
    "sg:tags":[
        "foto",
        "film"
    ],
    "wof:name":"Foto Luykx",
    "wof:placetype":"venue"
},
  "geometry": {"coordinates":[4.590613,51.546627],"type":"Point"}
}