{
  "type": "Feature",
  "properties": {
    "addr:full":"Poppestraat 5 Sint Willebrord North Brabant 4711 JP",
    "addr:housenumber":"5",
    "addr:postcode":"4711 jp",
    "addr:street":"Poppestraat",
    "iso:country":"NL",
    "sg:address":"Poppestraat 5",
    "sg:city":"Sint Willebrord",
    "sg:classifiers":[
        {
            "category":"Retail",
            "subcategory":"Photofinishing",
            "type":"Services"
        }
    ],
    "sg:phone":"+31 165 382 600",
    "sg:postcode":"4711 JP",
    "sg:province":"North Brabant",
    "sg:tags":[
        "foto",
        "film"
    ],
    "wof:name":"Foto Luykx",
    "wof:placetype":"venue"
},
  "geometry": {"coordinates":[4.590613,51.546627],"type":"Point"}
}