{
  "type": "Feature",
  "properties": {
    "addr:full":"Colvenierstr 4 S Hertogenbosch Noord-Brabant 5211 AV",
    "addr:housenumber":"4",
    "addr:postcode":"5211 av",
    "addr:street":"Colvenierstr",
    "iso:country":"NL",
    "sg:address":"Colvenierstr 4",
    "sg:city":"S Hertogenbosch",
    "sg:orig_category":"Organisatiebureaus",
    "sg:phone":"+31 73 614 1615",
    "sg:postcode":"5211 AV",
    "sg:province":"Noord-Brabant",
    "sg:website":"http://www.jazzinduketown.nl",
    "wof:name":"Jazz In Duketown, Sticht",
    "wof:placetype":"venue"
},
  "geometry": {"coordinates":[5.2952947617,51.6890525818],"type":"Point"}
}