{
  "type": "Feature",
  "properties": {
    "iso:country":"NL",
    "sg:address":"Drienerloln 5",
    "sg:city":"Enschede",
    "sg:classifiers":[
        {
            "category":"Travel",
            "subcategory":"Hotels & Motels",
            "type":"Entertainment"
        }
    ],
    "sg:phone":"+31 53 433 1366",
    "sg:postcode":"7522 NB",
    "sg:province":"Overijssel",
    "sg:website":"http://www.drienerburght.nl",
    "wof:name":"Drienerburght",
    "wof:placetype":"venue"
},
  "geometry": {"coordinates":[6.851867,52.24065],"type":"Point"}
}