{
  "type": "Feature",
  "properties": {
    "addr:full":"Legmeerstraat 25 Amsterdam Noord-Holland 1058 NA",
    "addr:housenumber":"25",
    "addr:postcode":"1058 na",
    "addr:street":"Legmeerstraat",
    "iso:country":"NL",
    "sg:address":"Legmeerstraat 25",
    "sg:city":"Amsterdam",
    "sg:orig_category":"Fotostudio'S And Fotografen",
    "sg:phone":"+31 20 669 2344",
    "sg:postcode":"1058 NA",
    "sg:province":"Noord-Holland",
    "wof:name":"Jantien De Bruin Fotografie",
    "wof:placetype":"venue"
},
  "geometry": {"coordinates":[4.851435,52.353966],"type":"Point"}
}