{
  "type": "Feature",
  "properties": {
    "addr:full":"Achterweg 25 Limmen Noord-Holland 1906 AG",
    "addr:housenumber":"25",
    "addr:postcode":"1906",
    "addr:street":"Achterweg",
    "iso:country":"NL",
    "sg:address":"Achterweg 25",
    "sg:city":"Limmen",
    "sg:orig_category":"Goederenvervoer Over De Weg",
    "sg:phone":"+31 72 505 1714",
    "sg:postcode":"1906 AG",
    "sg:province":"Noord-Holland",
    "wof:name":"J A Van Der Steen",
    "wof:placetype":"venue"
},
  "geometry": {"coordinates":[4.698816,52.566246],"type":"Point"}
}