{
  "type": "Feature",
  "properties": {
    "addr:full":"Wiekslag 261 Amersfoort Utrecht 3815 GK",
    "addr:housenumber":"261",
    "addr:postcode":"3815 gk",
    "addr:street":"Wiekslag",
    "iso:country":"NL",
    "sg:address":"Wiekslag 261",
    "sg:city":"Amersfoort",
    "sg:orig_category":"Bloemen En Planten",
    "sg:phone":"+31 33 472 7271",
    "sg:postcode":"3815 GK",
    "sg:province":"Utrecht",
    "wof:name":"Castelijns",
    "wof:placetype":"venue"
},
  "geometry": {"coordinates":[5.408499,52.166843],"type":"Point"}
}