{
  "type": "Feature",
  "properties": {
    "iso:country":"NL",
    "sg:address":"Sumatrastr 30",
    "sg:city":"S Gravenhage",
    "sg:orig_category":"Grafmonumenten",
    "sg:phone":"+31 70 350 4480",
    "sg:postcode":"2585 CS",
    "sg:province":"Zuid-Holland",
    "wof:name":"Jehee Vof, Chr Th",
    "wof:placetype":"venue"
},
  "geometry": {"coordinates":[4.29777,52.094799],"type":"Point"}
}