{
  "type": "Feature",
  "properties": {
    "addr:full":"Westdk 4 Noordbeemster Noord-Holland 1463 PA",
    "addr:housenumber":"4",
    "addr:postcode":"1463 pa",
    "addr:street":"Westdk",
    "iso:country":"NL",
    "sg:address":"Westdk 4",
    "sg:city":"Noordbeemster",
    "sg:orig_category":"Administratie- En Boekhoudkantoren",
    "sg:phone":"+31 299 690 575",
    "sg:postcode":"1463 PA",
    "sg:province":"Noord-Holland",
    "wof:name":"Klinkenberg",
    "wof:placetype":"venue"
},
  "geometry": {"coordinates":[4.892466,52.59581],"type":"Point"}
}