{
  "type": "Feature",
  "properties": {
    "addr:full":"Rosendaalseweg 485 Arnhem Gelderland 6824 KK",
    "addr:housenumber":"485",
    "addr:postcode":"6824 kk",
    "addr:street":"Rosendaalseweg",
    "iso:country":"NL",
    "sg:address":"Rosendaalseweg 485",
    "sg:city":"Arnhem",
    "sg:orig_category":"Kinderopvang Behalve Thuis",
    "sg:phone":"+31 26 351 7474",
    "sg:postcode":"6824 KK",
    "sg:province":"Gelderland",
    "wof:name":"Kinderdagverblijf De Tuinfluiter",
    "wof:placetype":"venue"
},
  "geometry": {"coordinates":[5.932274,51.993729],"type":"Point"}
}