{
  "type": "Feature",
  "properties": {
    "iso:country":"NL",
    "sg:address":"Zandloper 3",
    "sg:city":"Winkel",
    "sg:classifiers":[
        {
            "category":"Retail",
            "subcategory":"Auto Repair",
            "type":"Services"
        }
    ],
    "sg:phone":"+31 224 542 443",
    "sg:postcode":"1731 LM",
    "sg:province":"Noord-Holland",
    "sg:tags":[
        "garage"
    ],
    "wof:name":"Limmen, Autobedrijf",
    "wof:placetype":"venue"
},
  "geometry": {"coordinates":[-110.50483699999999,33.171173],"type":"Point"}
}