{
  "type": "Feature",
  "properties": {
    "addr:full":"Stationsstraat 147 Apeldoorn Gelderland 7311 ME",
    "addr:housenumber":"147",
    "addr:postcode":"7311 me",
    "addr:street":"Stationsstraat;Gelderland",
    "iso:country":"NL",
    "sg:address":"Stationsstraat 147",
    "sg:city":"Apeldoorn",
    "sg:orig_category":"Meubelzaken, Woning- And Keukeninrichting",
    "sg:phone":"+31 55 576 0804",
    "sg:postcode":"7311 ME",
    "sg:province":"Gelderland",
    "wof:name":"Jagers Woonsfeer",
    "wof:placetype":"venue"
},
  "geometry": {"coordinates":[5.96599,52.214355],"type":"Point"}
}