{
  "type": "Feature",
  "properties": {
    "addr:full":"Cypressenhage 1 Stadskanaal Groningen 9501 WK",
    "addr:housenumber":"1",
    "addr:postcode":"9501 wk",
    "addr:street":"Cypressenhage",
    "iso:country":"NL",
    "sg:address":"Cypressenhage 1",
    "sg:city":"Stadskanaal",
    "sg:classifiers":[
        {
            "category":"Personal",
            "subcategory":"Nail Salon",
            "type":"Services"
        }
    ],
    "sg:phone":"+31 599 619 694",
    "sg:postcode":"9501 WK",
    "sg:province":"Groningen",
    "sg:tags":[
        "pedicure"
    ],
    "wof:name":"Siepe, Margriet",
    "wof:placetype":"venue"
},
  "geometry": {"coordinates":[6.963494,52.982841],"type":"Point"}
}