{
  "type": "Feature",
  "properties": {
    "addr:full":"Oosterstr 11 Drachten Friesland 9203 BA",
    "addr:housenumber":"11",
    "addr:postcode":"9203 ba",
    "addr:street":"Oosterstr",
    "iso:country":"NL",
    "sg:address":"Oosterstr 11",
    "sg:city":"Drachten",
    "sg:orig_category":"Meubelen",
    "sg:phone":"+31 512 512 397",
    "sg:postcode":"9203 BA",
    "sg:province":"Friesland",
    "sg:website":"http://www.postmainterieur.nl",
    "wof:name":"Postma Interieur",
    "wof:placetype":"venue"
},
  "geometry": {"coordinates":[6.100174,53.107742],"type":"Point"}
}