{
  "type": "Feature",
  "properties": {
    "iso:country":"NL",
    "sg:address":"Hof Van Spaland",
    "sg:city":"Schiedam",
    "sg:orig_category":"Winkelcentra",
    "sg:phone":"+31 295",
    "sg:postcode":"3111 ",
    "sg:province":"Zuid-Holland",
    "wof:name":"Schiedam Winkelcentrum Spaland",
    "wof:placetype":"venue"
},
  "geometry": {"coordinates":[4.3981599808,51.91847229],"type":"Point"}
}