{
  "type": "Feature",
  "properties": {
    "addr:full":"Pr Bernhardln 82 Maartensdijk Utrecht 3738 DR",
    "addr:housenumber":"82",
    "addr:postcode":"3738 dr",
    "addr:street":"Maartensdijk",
    "iso:country":"NL",
    "sg:address":"Pr Bernhardln 82",
    "sg:city":"Maartensdijk",
    "sg:orig_category":"Verzekeringen - Verzekeringskantoren",
    "sg:phone":"+31 346 211 357",
    "sg:postcode":"3738 DR",
    "sg:province":"Utrecht",
    "wof:name":"Veen-Heemskerk, J Van Der",
    "wof:placetype":"venue"
},
  "geometry": {"coordinates":[5.17565,52.155247],"type":"Point"}
}