{
  "type": "Feature",
  "properties": {
    "addr:full":"Thomsonstr 135 Badhoevedorp North Holland 1171 ZJ",
    "addr:housenumber":"135",
    "addr:postcode":"1171 zj",
    "iso:country":"NL",
    "sg:address":"Thomsonstr 135",
    "sg:city":"Badhoevedorp",
    "sg:orig_category":"Koeriersdiensten",
    "sg:phone":"+31 6 53181371",
    "sg:postcode":"1171 ZJ",
    "sg:province":"North Holland",
    "wof:name":"A Koeriers",
    "wof:placetype":"venue"
},
  "geometry": {"coordinates":[4.781852,52.344021],"type":"Point"}
}