{
  "type": "Feature",
  "properties": {
    "iso:country":"NL",
    "sg:address":"Kelfkensbos 52",
    "sg:city":"Nijmegen",
    "sg:orig_category":"Meubelzaken, Woning- And Keukeninrichting",
    "sg:phone":"+31 24 323 0990",
    "sg:postcode":"6511 TB",
    "sg:province":"Gelderland",
    "wof:name":"De Winkel Van Sinkel",
    "wof:placetype":"venue"
},
  "geometry": {"coordinates":[5.871151,51.84597],"type":"Point"}
}