{
  "type": "Feature",
  "properties": {
    "addr:full":"Stadhoudersln 18 Utrecht Utrecht 3583 JH",
    "addr:housenumber":"18",
    "addr:postcode":"3583 jh",
    "addr:street":"Stadhoudersln",
    "iso:country":"NL",
    "sg:address":"Stadhoudersln 18",
    "sg:city":"Utrecht",
    "sg:orig_category":"Psychotherapeuten",
    "sg:phone":"+31 30 254 0193",
    "sg:postcode":"3583 JH",
    "sg:province":"Utrecht",
    "wof:name":"Wintgens, Drs C",
    "wof:placetype":"venue"
},
  "geometry": {"coordinates":[5.14371,52.086601],"type":"Point"}
}