{
  "type": "Feature",
  "properties": {
    "addr:full":"Veldhovenring 92 Tilburg Noord-Brabant 5041 BE",
    "addr:housenumber":"92",
    "addr:postcode":"5041",
    "addr:street":"Veldhovenring",
    "iso:country":"NL",
    "sg:address":"Veldhovenring 92",
    "sg:city":"Tilburg",
    "sg:orig_category":"Kappers",
    "sg:phone":"+31 13 536 1973",
    "sg:postcode":"5041 BE",
    "sg:province":"Noord-Brabant",
    "wof:name":"Harries Hairline",
    "wof:placetype":"venue"
},
  "geometry": {"coordinates":[5.0838828087,51.5675392151],"type":"Point"}
}