{
  "type": "Feature",
  "properties": {
    "addr:full":"Markt 7 Sas Van Gent Zeeland 4551 BK",
    "addr:housenumber":"7",
    "addr:postcode":"4551 bk",
    "addr:street":"Markt",
    "iso:country":"NL",
    "sg:address":"Markt 7",
    "sg:city":"Sas Van Gent",
    "sg:orig_category":"Banken And Kredietinstellingen",
    "sg:phone":"+31 115 457 200",
    "sg:postcode":"4551 BK",
    "sg:province":"Zeeland",
    "wof:name":"Abn Amro",
    "wof:placetype":"venue"
},
  "geometry": {"coordinates":[3.799588,51.228004],"type":"Point"}
}