{
  "type": "Feature",
  "properties": {
    "addr:full":"Waalstraat 67 Utrecht Utrecht 3522 SC",
    "addr:housenumber":"67",
    "addr:postcode":"3522",
    "addr:street":"Waalstraat",
    "iso:country":"NL",
    "sg:address":"Waalstraat 67",
    "sg:city":"Utrecht",
    "sg:orig_category":"Loodgieterswerk, Verwarming And Sanitaire Installaties",
    "sg:phone":"+31 30 289 2853",
    "sg:postcode":"3522 SC",
    "sg:province":"Utrecht",
    "wof:name":"A & T Onderhoudsbedrijf",
    "wof:placetype":"venue"
},
  "geometry": {"coordinates":[5.116831,52.07394],"type":"Point"}
}