{
  "type": "Feature",
  "properties": {
    "iso:country":"NL",
    "sg:address":"Vossiusstr 43",
    "sg:city":"Amsterdam",
    "sg:classifiers":[
        {
            "category":"Wholesale",
            "subcategory":"Meat",
            "type":"Manufacturing & Wholesale Goods"
        }
    ],
    "sg:phone":"+31 20 679 4411",
    "sg:postcode":"1071 AJ",
    "sg:province":"Noord-Holland",
    "sg:tags":[
        "regeltechniek",
        "en",
        "meet-"
    ],
    "sg:website":"http://www.mefec.nl",
    "wof:name":"Ccp Mefec Bv",
    "wof:placetype":"venue"
},
  "geometry": {"coordinates":[4.878717,52.360344],"type":"Point"}
}