{
  "type": "Feature",
  "properties": {
    "iso:country":"NL",
    "sg:address":"Staalindustrieweg 25",
    "sg:city":"Alblasserdam",
    "sg:orig_category":"Werving And Selectie Van Tijdelijk Personeel And Uitzendkantoren",
    "sg:phone":"+31 78 610 3601",
    "sg:postcode":"2952 AT",
    "sg:province":"Zuid-Holland",
    "wof:name":"Hoteco Uitzendburo Bv",
    "wof:placetype":"venue"
},
  "geometry": {"coordinates":[4.6686048508,51.8526344299],"type":"Point"}
}