{
  "type": "Feature",
  "properties": {
    "addr:full":"C Prinsenln 14 Breda Noord-Brabant 4811 DK",
    "addr:housenumber":"14",
    "addr:postcode":"4811 dk",
    "iso:country":"NL",
    "sg:address":"C Prinsenln 14",
    "sg:city":"Breda",
    "sg:orig_category":"Arbeidsbureaus",
    "sg:phone":"+31 76 504 3330",
    "sg:postcode":"4811 DK",
    "sg:province":"Noord-Brabant",
    "wof:name":"Arbeidsbur",
    "wof:placetype":"venue"
},
  "geometry": {"coordinates":[4.771685,51.591351],"type":"Point"}
}