{
  "type": "Feature",
  "properties": {
    "addr:full":"Helena Rietbergstraat 11 Gouda Zuid-Holland 2806 KP",
    "addr:housenumber":"11",
    "addr:postcode":"2806 kp",
    "addr:street":"Helena Rietbergstraat",
    "iso:country":"NL",
    "sg:address":"Helena Rietbergstraat 11",
    "sg:city":"Gouda",
    "sg:orig_category":"Chemische Producten Gh",
    "sg:phone":"+31 182 514 302",
    "sg:postcode":"2806 KP",
    "sg:province":"Zuid-Holland",
    "wof:name":"Gebroeders Boekamp Exploitatie Mij Bv",
    "wof:placetype":"venue"
},
  "geometry": {"coordinates":[4.729258,52.014656],"type":"Point"}
}