{
  "type": "Feature",
  "properties": {
    "iso:country":"NL",
    "sg:address":"Graaf Willemlaan 155",
    "sg:city":"Monnickendam",
    "sg:orig_category":"Loodgieterswerk, Verwarming And Sanitaire Installaties",
    "sg:phone":"+31 299 653 298",
    "sg:postcode":"1141 XG",
    "sg:province":"Noord-Holland",
    "wof:name":"H.W. Van Buuren",
    "wof:placetype":"venue"
},
  "geometry": {"coordinates":[5.039763,52.453121],"type":"Point"}
}