{
  "type": "Feature",
  "properties": {
    "addr:full":"Kzr Karelpln 2 Maastricht Limburg 6211 TC",
    "addr:housenumber":"2",
    "addr:postcode":"6211 tc",
    "addr:street":"Karelpln",
    "iso:country":"NL",
    "sg:address":"Kzr Karelpln 2",
    "sg:city":"Maastricht",
    "sg:orig_category":"Manueel Therapeuten",
    "sg:phone":"+31 43 321 2496",
    "sg:postcode":"6211 TC",
    "sg:province":"Limburg",
    "wof:name":"Schyns En A Sonneveldt, B",
    "wof:placetype":"venue"
},
  "geometry": {"coordinates":[5.686560154,50.8494682312],"type":"Point"}
}