{
  "type": "Feature",
  "properties": {
    "addr:full":"Wiltonstraat 10-12 Zoetermeer Zuid-Holland 2722 NG",
    "addr:housenumber":"10-12",
    "addr:postcode":"2722 ng",
    "addr:street":"Wiltonstraat",
    "iso:country":"NL",
    "sg:address":"Wiltonstraat 10-12",
    "sg:city":"Zoetermeer",
    "sg:orig_category":"Goederenvervoer Over De Weg",
    "sg:phone":"+31 79 331 9364",
    "sg:postcode":"2722 NG",
    "sg:province":"Zuid-Holland",
    "wof:name":"Translift Original Europa As Bv",
    "wof:placetype":"venue"
},
  "geometry": {"coordinates":[4.51453,52.050449],"type":"Point"}
}