{
  "type": "Feature",
  "properties": {
    "addr:full":"De Jagerwg 154 Dordrecht South Holland 3328 HG",
    "addr:housenumber":"154",
    "addr:postcode":"3328 hg",
    "iso:country":"NL",
    "sg:address":"De Jagerwg 154",
    "sg:city":"Dordrecht",
    "sg:orig_category":"Luchtbehandelings- Apparaten",
    "sg:phone":"+31 78 617 9669",
    "sg:postcode":"3328 HG",
    "sg:province":"South Holland",
    "wof:name":"Silva",
    "wof:placetype":"venue"
},
  "geometry": {"coordinates":[4.683123,51.780544],"type":"Point"}
}