{
  "type": "Feature",
  "properties": {
    "addr:full":"Keenkestraat 4 Gronsveld Limburg 6247 EJ",
    "addr:housenumber":"4",
    "addr:postcode":"6247 ej",
    "addr:street":"Keenkestraat",
    "iso:country":"NL",
    "sg:address":"Keenkestraat 4",
    "sg:city":"Gronsveld",
    "sg:orig_category":"Bloemen And Planten",
    "sg:phone":"+31 43 408 1990",
    "sg:postcode":"6247 EJ",
    "sg:province":"Limburg",
    "wof:name":"G.G.J. Scharnigg",
    "wof:placetype":"venue"
},
  "geometry": {"coordinates":[5.734439,50.809643],"type":"Point"}
}