{
  "type": "Feature",
  "properties": {
    "addr:full":"Burg Snydersstr 9 Wynandsrade Limburg 6363 BG",
    "addr:housenumber":"9",
    "addr:postcode":"6363",
    "addr:street":"Burg Snydersstr",
    "iso:country":"NL",
    "sg:address":"Burg Snydersstr 9",
    "sg:city":"Wynandsrade",
    "sg:orig_category":"Directmail",
    "sg:phone":"+31 45 565 6102",
    "sg:postcode":"6363 BG",
    "sg:province":"Limburg",
    "wof:name":"Verhuisbox Bv, De",
    "wof:placetype":"venue"
},
  "geometry": {"coordinates":[5.9012,50.905365],"type":"Point"}
}