{
  "type": "Feature",
  "properties": {
    "addr:full":"Schuttevaerwg 76 Rotterdam Zuid-Holland 3044 BB",
    "addr:housenumber":"76",
    "addr:postcode":"3044 bb",
    "addr:street":"Schuttevaerwg",
    "iso:country":"NL",
    "sg:address":"Schuttevaerwg 76",
    "sg:city":"Rotterdam",
    "sg:orig_category":"Elektrotechnische Apparatuur - Fabrieken En Groothandel",
    "sg:phone":"+31 10 208 0608",
    "sg:postcode":"3044 BB",
    "sg:province":"Zuid-Holland",
    "wof:name":"Technische Unie",
    "wof:placetype":"venue"
},
  "geometry": {"coordinates":[4.416941,51.927677],"type":"Point"}
}