{
  "type": "Feature",
  "properties": {
    "iso:country":"NL",
    "sg:address":"Lichtenbergsew 28",
    "sg:city":"Silvolde",
    "sg:orig_category":"Kappers",
    "sg:phone":"+31 315 323 558",
    "sg:postcode":"7064 CD",
    "sg:province":"Gelderland",
    "wof:name":"Marjan",
    "wof:placetype":"venue"
},
  "geometry": {"coordinates":[6.385284,51.909092],"type":"Point"}
}