{
  "type": "Feature",
  "properties": {
    "iso:country":"NL",
    "sg:address":"Luxemburgstr 4",
    "sg:city":"Kaatsheuvel",
    "sg:orig_category":"Woningtextiel",
    "sg:phone":"+31 416 543 446",
    "sg:postcode":"5171 PM",
    "sg:province":"Noord-Brabant",
    "wof:name":"Sathin Bv",
    "wof:placetype":"venue"
},
  "geometry": {"coordinates":[5.0250549316,51.6661605835],"type":"Point"}
}