{
  "type": "Feature",
  "properties": {
    "iso:country":"NL",
    "sg:address":"Woestduinstraat 155",
    "sg:city":"Amsterdam",
    "sg:orig_category":"Diverse Grafische Activiteiten",
    "sg:phone":"+31 20 669 4864",
    "sg:postcode":"1059 SV",
    "sg:province":"North Holland",
    "wof:name":"De Zwarte Handel",
    "wof:placetype":"venue"
},
  "geometry": {"coordinates":[4.847866,52.349712],"type":"Point"}
}