{
  "type": "Feature",
  "properties": {
    "addr:full":"Haagbeukstraat 38 Schagen North Holland 1741 VD",
    "addr:housenumber":"38",
    "addr:postcode":"1741 vd",
    "addr:street":"Haagbeukstraat",
    "iso:country":"NL",
    "sg:address":"Haagbeukstraat 38",
    "sg:city":"Schagen",
    "sg:orig_category":"Glaszetten",
    "sg:phone":"+31 224 215 048",
    "sg:postcode":"1741 VD",
    "sg:province":"North Holland",
    "wof:name":"B.E.A. Pieterse",
    "wof:placetype":"venue"
},
  "geometry": {"coordinates":[4.798377,52.797863],"type":"Point"}
}