{
  "type": "Feature",
  "properties": {
    "addr:full":"Wibautstr 45 Amsterdam Noord-Holland 1091 GH",
    "addr:housenumber":"45",
    "addr:postcode":"1091 gh",
    "addr:street":"Wibautstr",
    "iso:country":"NL",
    "sg:address":"Wibautstr 45",
    "sg:city":"Amsterdam",
    "sg:orig_category":"Meubelen",
    "sg:phone":"+31 20 468 3690",
    "sg:postcode":"1091 GH",
    "sg:province":"Noord-Holland",
    "wof:name":"Rob Krol Bv",
    "wof:placetype":"venue"
},
  "geometry": {"coordinates":[4.91082,52.357265],"type":"Point"}
}