{
  "type": "Feature",
  "properties": {
    "addr:full":"Marktstr 1 Ter Apel Groningen 9561 KC",
    "addr:housenumber":"1",
    "addr:postcode":"9561 kc",
    "addr:street":"Marktstr",
    "iso:country":"NL",
    "sg:address":"Marktstr 1",
    "sg:city":"Ter Apel",
    "sg:orig_category":"Bibliotheken En Leeszalen Openbare",
    "sg:phone":"+31 599 581 547",
    "sg:postcode":"9561 KC",
    "sg:province":"Groningen",
    "sg:website":"http://www.ob-terapel.nl",
    "wof:name":"Openb Bibliotheek",
    "wof:placetype":"venue"
},
  "geometry": {"coordinates":[7.057457,52.874859],"type":"Point"}
}