{
  "type": "Feature",
  "properties": {
    "iso:country":"NL",
    "sg:address":"P Dykemawg 86C",
    "sg:city":"Groningen",
    "sg:orig_category":"Verenigingen En Stichtingen",
    "sg:phone":"+31 50 542 0731",
    "sg:postcode":"9731 BH",
    "sg:province":"Groningen",
    "wof:name":"Drenthe, Ver",
    "wof:placetype":"venue"
},
  "geometry": {"coordinates":[6.589816,53.232174],"type":"Point"}
}