{
  "type": "Feature",
  "properties": {
    "addr:full":"Rijkesluisstr 21 Oirschot Noord-Brabant 5688 EC",
    "addr:housenumber":"21",
    "addr:postcode":"5688 ec",
    "addr:street":"Rijkesluisstr",
    "iso:country":"NL",
    "sg:address":"Rijkesluisstr 21",
    "sg:city":"Oirschot",
    "sg:orig_category":"Verzekeringen - Verzekeringskantoren",
    "sg:phone":"+31 499 575 353",
    "sg:postcode":"5688 EC",
    "sg:province":"Noord-Brabant",
    "sg:website":"http://www.verrekijker.nl",
    "wof:name":"Verrekijker, De",
    "wof:placetype":"venue"
},
  "geometry": {"coordinates":[5.31061,51.503376],"type":"Point"}
}