{
  "type": "Feature",
  "properties": {
    "addr:full":"Tormentilstraat 12 Groningen Groningen 9731 DM",
    "addr:housenumber":"12",
    "addr:postcode":"9731 dm",
    "addr:street":"Tormentilstraat",
    "iso:country":"NL",
    "sg:address":"Tormentilstraat 12",
    "sg:city":"Groningen",
    "sg:classifiers":[
        {
            "category":"Professional",
            "subcategory":"Accounting & Tax Preparation",
            "type":"Services"
        }
    ],
    "sg:phone":"+31 50 542 3898",
    "sg:postcode":"9731 DM",
    "sg:province":"Groningen",
    "sg:tags":[
        "accountant"
    ],
    "wof:name":"Accountantskantoor Groeneveld",
    "wof:placetype":"venue"
},
  "geometry": {"coordinates":[6.593779,53.231327],"type":"Point"}
}