{
  "type": "Feature",
  "properties": {
    "addr:full":"Nachtegaalstraat 53 Utrecht Utrecht 3581 AD",
    "addr:housenumber":"53",
    "addr:postcode":"3581 ad",
    "addr:street":"Nachtegaalstraat",
    "iso:country":"NL",
    "sg:address":"Nachtegaalstraat 53",
    "sg:city":"Utrecht",
    "sg:orig_category":"Verlichting And Huishoudartikelen",
    "sg:phone":"+31 30 231 8359",
    "sg:postcode":"3581 AD",
    "sg:province":"Utrecht",
    "wof:name":"Utrechtse Tapijthallen Bv",
    "wof:placetype":"venue"
},
  "geometry": {"coordinates":[5.131261,52.091587],"type":"Point"}
}