{
  "type": "Feature",
  "properties": {
    "iso:country":"NL",
    "sg:address":"Aleidastr 77",
    "sg:city":"Schiedam",
    "sg:orig_category":"Beeldende Kunstenaars",
    "sg:phone":"+31 10 591 4974",
    "sg:postcode":"3117 DB",
    "sg:province":"Zuid-Holland",
    "wof:name":"Gijs De Jong",
    "wof:placetype":"venue"
},
  "geometry": {"coordinates":[4.388767,51.913998],"type":"Point"}
}