{
  "type": "Feature",
  "properties": {
    "addr:full":"Muyeweg 10 Sint Maartensdijk Zeeland 4695 RB",
    "addr:housenumber":"10",
    "addr:postcode":"4695 rb",
    "addr:street":"Muyeweg",
    "iso:country":"NL",
    "sg:address":"Muyeweg 10",
    "sg:city":"Sint Maartensdijk",
    "sg:orig_category":"Kampeerterreinen",
    "sg:phone":"+31 166 662 840",
    "sg:postcode":"4695 RB",
    "sg:province":"Zeeland",
    "wof:name":"Camping De Muie Vof",
    "wof:placetype":"venue"
},
  "geometry": {"coordinates":[4.0659751892,51.536441803],"type":"Point"}
}