{
  "type": "Feature",
  "properties": {
    "addr:full":"M L Kingstate 84 Ede Gld Gelderland 6716 ND",
    "addr:housenumber":"84",
    "addr:postcode":"6716 nd",
    "addr:street":"M L Kingstate;Gld Gelderland",
    "iso:country":"NL",
    "sg:address":"M L Kingstate 84",
    "sg:city":"Ede Gld",
    "sg:orig_category":"Keukens",
    "sg:phone":"+31 6 51269178",
    "sg:postcode":"6716 ND",
    "sg:province":"Gelderland",
    "wof:name":"Tudor, Garantservice",
    "wof:placetype":"venue"
},
  "geometry": {"coordinates":[5.66767,52.044979],"type":"Point"}
}