{
  "type": "Feature",
  "properties": {
    "addr:full":"Oosterstr 47 Benningbroek North Holland 1654 JM",
    "addr:housenumber":"47",
    "addr:postcode":"1654 jm",
    "addr:street":"Oosterstr",
    "iso:country":"NL",
    "sg:address":"Oosterstr 47",
    "sg:city":"Benningbroek",
    "sg:orig_category":"Schoonheidsinstituten",
    "sg:phone":"+31 229 591 912",
    "sg:postcode":"1654 JM",
    "sg:province":"North Holland",
    "wof:name":"Margriet",
    "wof:placetype":"venue"
},
  "geometry": {"coordinates":[5.042512,52.703308],"type":"Point"}
}