{
  "type": "Feature",
  "properties": {
    "addr:full":"Kapelstraat 46 Beek En Donk Noord-Brabant 5741 CE",
    "addr:housenumber":"46",
    "addr:postcode":"5741 ce",
    "addr:street":"Kapelstraat",
    "iso:country":"NL",
    "sg:address":"Kapelstraat 46",
    "sg:city":"Beek En Donk",
    "sg:orig_category":"Boekhouders",
    "sg:phone":"+31 492 463 773",
    "sg:postcode":"5741 CE",
    "sg:province":"Noord-Brabant",
    "wof:name":"H. Pepers-Verschuren",
    "wof:placetype":"venue"
},
  "geometry": {"coordinates":[5.624765,51.540592],"type":"Point"}
}