{
  "type": "Feature",
  "properties": {
    "addr:full":"Christiaan Geurtsweg 10 Apeldoorn Gelderland 7335 JV",
    "addr:housenumber":"10",
    "addr:postcode":"7335 jv",
    "addr:street":"Christiaan Geurtsweg;Gelderland",
    "iso:country":"NL",
    "sg:address":"Christiaan Geurtsweg 10",
    "sg:city":"Apeldoorn",
    "sg:orig_category":"Overheidsdiensten",
    "sg:phone":"+31 55 577 9100",
    "sg:postcode":"7335 JV",
    "sg:province":"Gelderland",
    "wof:name":"Gak Nederland Bv",
    "wof:placetype":"venue"
},
  "geometry": {"coordinates":[5.957239151,52.2064590454],"type":"Point"}
}