{
  "type": "Feature",
  "properties": {
    "addr:full":"Tarweweg 5 Nijmegen Gelderland 6534 AM",
    "addr:housenumber":"5",
    "addr:postcode":"6534",
    "addr:street":"Tarweweg;Gelderland",
    "iso:country":"NL",
    "sg:address":"Tarweweg 5",
    "sg:city":"Nijmegen",
    "sg:orig_category":"Diverse Consumentenartikelen Gh",
    "sg:phone":"+31 24 356 4777",
    "sg:postcode":"6534 AM",
    "sg:province":"Gelderland",
    "wof:name":"Pro-Acoustics Europe Bv",
    "wof:placetype":"venue"
},
  "geometry": {"coordinates":[5.822842,51.818829],"type":"Point"}
}