{
  "type": "Feature",
  "properties": {
    "iso:country":"NL",
    "sg:address":"Peppengouw 50",
    "sg:city":"Almere",
    "sg:orig_category":"Diverse Grafische Activiteiten",
    "sg:phone":"+31 36 531 6315",
    "sg:postcode":"1351 ND",
    "sg:province":"Flevoland",
    "wof:name":"De Muizenkoning",
    "wof:placetype":"venue"
},
  "geometry": {"coordinates":[5.21254,52.346355],"type":"Point"}
}