{
  "type": "Feature",
  "properties": {
    "addr:full":"De Ontdekking 24 Amersfoort Utrecht 3823 DT",
    "addr:housenumber":"24",
    "addr:postcode":"3823 dt",
    "addr:street":"De Ontdekking",
    "iso:country":"NL",
    "sg:address":"De Ontdekking 24",
    "sg:city":"Amersfoort",
    "sg:orig_category":"Marketingbureaus",
    "sg:phone":"+31 33 453 1280",
    "sg:postcode":"3823 DT",
    "sg:province":"Utrecht",
    "wof:name":"Alignment Europe Bv",
    "wof:placetype":"venue"
},
  "geometry": {"coordinates":[5.389879,52.188248],"type":"Point"}
}