{
  "type": "Feature",
  "properties": {
    "addr:full":"Langewijk 366 Dedemsvaart NL.08 7701 AR",
    "addr:housenumber":"366;nl.08",
    "addr:postcode":"7701",
    "addr:street":"Langewijk",
    "iso:country":"NL",
    "sg:address":"Langewijk 366",
    "sg:city":"Dedemsvaart",
    "sg:orig_category":"Fitnesscentra",
    "sg:phone":"+31 523 612 478",
    "sg:postcode":"7701 AR",
    "sg:province":"NL.08",
    "wof:name":"Fitness-Centrum-Dedemsvaart",
    "wof:placetype":"venue"
},
  "geometry": {"coordinates":[6.478185,52.607277],"type":"Point"}
}