{
  "type": "Feature",
  "properties": {
    "iso:country":"NL",
    "sg:address":"Kruisweg 36",
    "sg:city":"Haule",
    "sg:orig_category":"Bloemen And Planten",
    "sg:phone":"+31 516 577 239",
    "sg:postcode":"8432 PS",
    "sg:province":"Provincie Friesland",
    "wof:name":"Tuincentrum Hans Menken",
    "wof:placetype":"venue"
},
  "geometry": {"coordinates":[6.277664,53.031021],"type":"Point"}
}