{
  "type": "Feature",
  "properties": {
    "addr:full":"Pr Alexanderpln 8 Rotterdam Zuid-Holland 3067 GC",
    "addr:housenumber":"8",
    "addr:postcode":"3067 gc",
    "iso:country":"NL",
    "sg:address":"Pr Alexanderpln 8",
    "sg:city":"Rotterdam",
    "sg:orig_category":"Onderzoekbureaus",
    "sg:phone":"+31 10 289 4444",
    "sg:postcode":"3067 GC",
    "sg:province":"Zuid-Holland",
    "sg:website":"http://www.research-int.com",
    "wof:name":"Research Int Bv",
    "wof:placetype":"venue"
},
  "geometry": {"coordinates":[4.552557,51.950916],"type":"Point"}
}