{
  "type": "Feature",
  "properties": {
    "addr:full":"Scholeksterhof 48 Purmerend Noord-Holland 1444 AS",
    "addr:housenumber":"48",
    "addr:postcode":"1444 as",
    "addr:street":"Scholeksterhof",
    "iso:country":"NL",
    "sg:address":"Scholeksterhof 48",
    "sg:city":"Purmerend",
    "sg:orig_category":"Vertaal- And Tolkenbureaus",
    "sg:phone":"+31 299 414 260",
    "sg:postcode":"1444 AS",
    "sg:province":"Noord-Holland",
    "wof:name":"Aty Bobeldijk",
    "wof:placetype":"venue"
},
  "geometry": {"coordinates":[4.960855,52.525593],"type":"Point"}
}