{
  "type": "Feature",
  "properties": {
    "addr:full":"Middellaan 29 Apeldoorn Gelderland 7314 GB",
    "addr:housenumber":"29",
    "addr:postcode":"7314 gb",
    "addr:street":"Middellaan;Gelderland",
    "iso:country":"NL",
    "sg:address":"Middellaan 29",
    "sg:city":"Apeldoorn",
    "sg:orig_category":"Hang- And Sluitwerk Fab",
    "sg:phone":"+31 55 355 0105",
    "sg:postcode":"7314 GB",
    "sg:province":"Gelderland",
    "wof:name":"Ck Design",
    "wof:placetype":"venue"
},
  "geometry": {"coordinates":[5.943437,52.223637],"type":"Point"}
}