{
  "type": "Feature",
  "properties": {
    "addr:full":"P Stastokerf 23 Amersfoort Utrecht 3813 PP",
    "addr:housenumber":"23",
    "addr:postcode":"3813 pp",
    "addr:street":"P Stastokerf",
    "iso:country":"NL",
    "sg:address":"P Stastokerf 23",
    "sg:city":"Amersfoort",
    "sg:orig_category":"Bloemen En Planten",
    "sg:phone":"+31 33 480 5959",
    "sg:postcode":"3813 PP",
    "sg:province":"Utrecht",
    "wof:name":"Bloemhuys, Het",
    "wof:placetype":"venue"
},
  "geometry": {"coordinates":[5.389763,52.173767],"type":"Point"}
}