{
  "type": "Feature",
  "properties": {
    "addr:full":"Geitenkamp 19-25 Arnhem Gelderland 6823 HC",
    "addr:housenumber":"19-25",
    "addr:postcode":"6823 hc",
    "addr:street":"Geitenkamp",
    "iso:country":"NL",
    "sg:address":"Geitenkamp 19-25",
    "sg:city":"Arnhem",
    "sg:orig_category":"Cafetaria'S",
    "sg:phone":"+31 26 442 3453",
    "sg:postcode":"6823 HC",
    "sg:province":"Gelderland",
    "wof:name":"Magneet, De",
    "wof:placetype":"venue"
},
  "geometry": {"coordinates":[5.94074,52.001373],"type":"Point"}
}