{
  "type": "Feature",
  "properties": {
    "addr:full":"J J Allanstraat 453 Westzaan Noord-Holland 1551 RL",
    "addr:housenumber":"453",
    "addr:postcode":"1551 rl",
    "addr:street":"Allanstraat",
    "iso:country":"NL",
    "sg:address":"J J Allanstraat 453",
    "sg:city":"Westzaan",
    "sg:orig_category":"Pleziervaartuigen And Reparatie",
    "sg:phone":"+31 75 628 7887",
    "sg:postcode":"1551 RL",
    "sg:province":"Noord-Holland",
    "wof:name":"Volkers Vof",
    "wof:placetype":"venue"
},
  "geometry": {"coordinates":[4.772782,52.460835],"type":"Point"}
}