{
  "type": "Feature",
  "properties": {
    "addr:full":"Verbindingsweg 4 Dalen Drenthe 7751 BB",
    "addr:housenumber":"4",
    "addr:postcode":"7751 bb",
    "addr:street":"Verbindingsweg",
    "iso:country":"NL",
    "sg:address":"Verbindingsweg 4",
    "sg:city":"Dalen",
    "sg:orig_category":"Granen, Zaden And Diervoeders Gh",
    "sg:phone":"+31 524 552 445",
    "sg:postcode":"7751 BB",
    "sg:province":"Drenthe",
    "wof:name":"Jager Agro Bv",
    "wof:placetype":"venue"
},
  "geometry": {"coordinates":[6.762152,52.70343],"type":"Point"}
}