{
  "type": "Feature",
  "properties": {
    "iso:country":"NL",
    "sg:address":"Hogelanden Wz 45",
    "sg:city":"Utrecht",
    "sg:orig_category":"Fotoreportages",
    "sg:phone":"+31 30 285 1601",
    "sg:postcode":"3552 AC",
    "sg:province":"Utrecht",
    "wof:name":"Teamfotograaf, De",
    "wof:placetype":"venue"
},
  "geometry": {"coordinates":[5.106251,52.107269],"type":"Point"}
}