{
  "type": "Feature",
  "properties": {
    "addr:full":"Dracht 62 Heerenveen Friesland 8442 BS",
    "addr:housenumber":"62",
    "addr:postcode":"8442 bs",
    "addr:street":"Dracht",
    "iso:country":"NL",
    "sg:address":"Dracht 62",
    "sg:city":"Heerenveen",
    "sg:orig_category":"Schoenen",
    "sg:phone":"+31 513 627 200",
    "sg:postcode":"8442 BS",
    "sg:province":"Friesland",
    "wof:name":"Schoenenreus Bv",
    "wof:placetype":"venue"
},
  "geometry": {"coordinates":[5.924454,52.958675],"type":"Point"}
}