{
  "type": "Feature",
  "properties": {
    "addr:full":"Vriesewg 107 Dordrecht South Holland 3311 NV",
    "addr:housenumber":"107",
    "addr:postcode":"3311 nv",
    "iso:country":"NL",
    "sg:address":"Vriesewg 107",
    "sg:city":"Dordrecht",
    "sg:orig_category":"Kunstgebitten",
    "sg:phone":"+31 78 613 5733",
    "sg:postcode":"3311 NV",
    "sg:province":"South Holland",
    "wof:name":"Nieuwenhuyzen",
    "wof:placetype":"venue"
},
  "geometry": {"coordinates":[4.673197,51.810963],"type":"Point"}
}