{
  "type": "Feature",
  "properties": {
    "iso:country":"NL",
    "sg:address":"Beeldhoevewg 8",
    "sg:city":"S Heerenhoek",
    "sg:orig_category":"Gedistilleerd En Likeuren - Fabrieken",
    "sg:phone":"+31 113 352 302",
    "sg:postcode":"4453 TD",
    "sg:province":"Zeeland",
    "wof:name":"Zeeuwsche Keteltje, 'T",
    "wof:placetype":"venue"
},
  "geometry": {"coordinates":[3.785353,51.450665],"type":"Point"}
}