{
  "type": "Feature",
  "properties": {
    "addr:full":"Keinsmerwg 18 T Zand Nh Noord-Holland 1756 AG",
    "addr:housenumber":"18 t",
    "addr:postcode":"1756",
    "addr:street":"Keinsmerwg;Zand Nh Noord-Holland",
    "iso:country":"NL",
    "sg:address":"Keinsmerwg 18",
    "sg:city":"T Zand Nh",
    "sg:orig_category":"Kinderkleding",
    "sg:phone":"+31 224 593 316",
    "sg:postcode":"1756 AG",
    "sg:province":"Noord-Holland",
    "wof:name":"Boezeroentje",
    "wof:placetype":"venue"
},
  "geometry": {"coordinates":[4.754882,52.836479],"type":"Point"}
}