{
  "type": "Feature",
  "properties": {
    "addr:full":"Noordstr 38 Tilburg Noord-Brabant 5038 EJ",
    "addr:housenumber":"38",
    "addr:postcode":"5038 ej",
    "addr:street":"Noordstr",
    "iso:country":"NL",
    "sg:address":"Noordstr 38",
    "sg:city":"Tilburg",
    "sg:orig_category":"Adviesbureaus",
    "sg:phone":"+31 6 24836751",
    "sg:postcode":"5038 EJ",
    "sg:province":"Noord-Brabant",
    "wof:name":"Os, N P M Van",
    "wof:placetype":"venue"
},
  "geometry": {"coordinates":[5.07758,51.556911],"type":"Point"}
}