{
  "type": "Feature",
  "properties": {
    "addr:full":"Godebaldkwartier 327 Utrecht Utrecht 3511 DS",
    "addr:housenumber":"327",
    "addr:postcode":"3511 ds",
    "addr:street":"Godebaldkwartier",
    "iso:country":"NL",
    "sg:address":"Godebaldkwartier 327",
    "sg:city":"Utrecht",
    "sg:orig_category":"Banken And Kredietinstellingen",
    "sg:phone":"+31 30 233 2484",
    "sg:postcode":"3511 DS",
    "sg:province":"Utrecht",
    "wof:name":"Postkantoren Bv Utrecht",
    "wof:placetype":"venue"
},
  "geometry": {"coordinates":[5.112986,52.089951],"type":"Point"}
}