{
  "type": "Feature",
  "properties": {
    "iso:country":"NL",
    "sg:address":"Senecaln 1",
    "sg:city":"S Hertogenbosch",
    "sg:orig_category":"Bejaarden - Verzorgingstehuizen",
    "sg:phone":"+31 73 614 4422",
    "sg:postcode":"5216 CH",
    "sg:province":"North Brabant",
    "wof:name":"Pettelaer, De",
    "wof:placetype":"venue"
},
  "geometry": {"coordinates":[5.29824,51.69075],"type":"Point"}
}