{
  "type": "Feature",
  "properties": {
    "addr:full":"S Gravenweg 88 Nieuwerkerk Ad Ijssel Zuid-Holland 2911 CH",
    "addr:housenumber":"88",
    "addr:postcode":"ijssel;2911",
    "addr:street":"S Gravenweg",
    "iso:country":"NL",
    "sg:address":"S Gravenweg 88",
    "sg:city":"Nieuwerkerk Ad Ijssel",
    "sg:orig_category":"Loodgieterswerk, Verwarming And Sanitaire Installaties",
    "sg:phone":"+31 180 313 897",
    "sg:postcode":"2911 CH",
    "sg:province":"Zuid-Holland",
    "wof:name":"M Quispel Loodgietersbedrijf",
    "wof:placetype":"venue"
},
  "geometry": {"coordinates":[4.616454,51.954098],"type":"Point"}
}