{
  "type": "Feature",
  "properties": {
    "addr:full":"Magdalenastraat 5 Utrecht Utrecht 3512 NH",
    "addr:housenumber":"5",
    "addr:postcode":"3512 nh",
    "addr:street":"Magdalenastraat",
    "iso:country":"NL",
    "sg:address":"Magdalenastraat 5",
    "sg:city":"Utrecht",
    "sg:orig_category":"Verhuisdiensten",
    "sg:phone":"+31 30 231 9091",
    "sg:postcode":"3512 NH",
    "sg:province":"Utrecht",
    "wof:name":"A Tot Z Diensten",
    "wof:placetype":"venue"
},
  "geometry": {"coordinates":[5.127032,52.086678],"type":"Point"}
}