{
  "type": "Feature",
  "properties": {
    "addr:full":"Prof Rontgenstr 21 Apeldoorn Gelderland 7311 AM",
    "addr:housenumber":"21",
    "addr:postcode":"7311",
    "addr:street":"Gelderland",
    "iso:country":"NL",
    "sg:address":"Prof Rontgenstr 21",
    "sg:city":"Apeldoorn",
    "sg:orig_category":"Psychotherapeuten",
    "sg:phone":"+31 55 522 5904",
    "sg:postcode":"7311 AM",
    "sg:province":"Gelderland",
    "wof:name":"Polikliniek Voor Kinder- En Volwassenen Psychiatrie",
    "wof:placetype":"venue"
},
  "geometry": {"coordinates":[5.957115,52.219196],"type":"Point"}
}