{
  "type": "Feature",
  "properties": {
    "addr:full":"Groenestr 6 Wadenoyen Gelderland 4014 MH",
    "addr:housenumber":"6",
    "addr:postcode":"4014 mh",
    "addr:street":"Groenestr;Gelderland",
    "iso:country":"NL",
    "sg:address":"Groenestr 6",
    "sg:city":"Wadenoyen",
    "sg:orig_category":"Honden- En Kattentrimsalons",
    "sg:phone":"+31 344 662 006",
    "sg:postcode":"4014 MH",
    "sg:province":"Gelderland",
    "wof:name":"Vagebond",
    "wof:placetype":"venue"
},
  "geometry": {"coordinates":[5.37321,51.873348],"type":"Point"}
}