{
  "type": "Feature",
  "properties": {
    "addr:full":"Bruggensngl Z 12 Amersfoort Utrecht 3823 BK",
    "addr:housenumber":"12",
    "addr:postcode":"3823 bk",
    "iso:country":"NL",
    "sg:address":"Bruggensngl Z 12",
    "sg:city":"Amersfoort",
    "sg:orig_category":"Bedrijfsopleidingen",
    "sg:phone":"+31 33 455 4368",
    "sg:postcode":"3823 BK",
    "sg:province":"Utrecht",
    "wof:name":"Beleggingsbewijs",
    "wof:placetype":"venue"
},
  "geometry": {"coordinates":[5.391991,52.185406],"type":"Point"}
}