{
  "type": "Feature",
  "properties": {
    "addr:full":"Postbus 7044 Groningen Gelderland 9701 JA",
    "addr:housenumber":"7044",
    "addr:postcode":"9701 ja",
    "addr:street":"Postbus",
    "iso:country":"NL",
    "sg:address":"Postbus 7044",
    "sg:city":"Groningen",
    "sg:orig_category":"Geluidsinstallaties - Verhuur",
    "sg:phone":"+31 50 314 6315",
    "sg:postcode":"9701 JA",
    "sg:province":"Gelderland",
    "sg:website":"http://www.mennowolthuis.nl",
    "wof:name":"Wolthuis, Menno",
    "wof:placetype":"venue"
},
  "geometry": {"coordinates":[6.56502,53.21645],"type":"Point"}
}