{
  "type": "Feature",
  "properties": {
    "addr:full":"Hoofstr 5 Nederweert Limburg 6031 AC",
    "addr:housenumber":"5",
    "addr:postcode":"6031 ac",
    "addr:street":"Hoofstr",
    "iso:country":"NL",
    "sg:address":"Hoofstr 5",
    "sg:city":"Nederweert",
    "sg:orig_category":"Pompen",
    "sg:phone":"+31 495 631 675",
    "sg:postcode":"6031 AC",
    "sg:province":"Limburg",
    "wof:name":"Nieuwenhoven Bv, C Van",
    "wof:placetype":"venue"
},
  "geometry": {"coordinates":[5.769355,51.288277],"type":"Point"}
}