{
  "type": "Feature",
  "properties": {
    "addr:full":"Frederikspln 41 Amsterdam North Holland 1017 XL",
    "addr:housenumber":"41",
    "addr:postcode":"1017 xl",
    "addr:street":"Frederikspln",
    "iso:country":"NL",
    "sg:address":"Frederikspln 41",
    "sg:city":"Amsterdam",
    "sg:orig_category":"Woningtextiel - Fabrieken En Groothandel",
    "sg:phone":"+31 20 530 5400",
    "sg:postcode":"1017 XL",
    "sg:province":"North Holland",
    "wof:name":"P & P Toplines Bv",
    "wof:placetype":"venue"
},
  "geometry": {"coordinates":[4.9011511803,52.3604927063],"type":"Point"}
}