{
  "type": "Feature",
  "properties": {
    "addr:full":"Albert Cuypstraat 141Bg Amsterdam Noord-Holland 1072 CS",
    "addr:housenumber":"141bg",
    "addr:postcode":"1072 cs",
    "addr:street":"Albert Cuypstraat",
    "iso:country":"NL",
    "sg:address":"Albert Cuypstraat 141Bg",
    "sg:city":"Amsterdam",
    "sg:classifiers":[
        {
            "category":"Restaurant",
            "type":"Food & Drink"
        }
    ],
    "sg:phone":"+31 20 676 8168",
    "sg:postcode":"1072 CS",
    "sg:province":"Noord-Holland",
    "wof:name":"Pahop Thai Eethuis",
    "wof:placetype":"venue"
},
  "geometry": {"coordinates":[4.892765,52.355579],"type":"Point"}
}