{
  "type": "Feature",
  "properties": {
    "addr:full":"Kap Heggestr 11 Gaanderen Gelderland 7011 GL",
    "addr:housenumber":"11",
    "addr:postcode":"7011 gl",
    "addr:street":"Gelderland",
    "iso:country":"NL",
    "sg:address":"Kap Heggestr 11",
    "sg:city":"Gaanderen",
    "sg:orig_category":"Fietsen - Fabrieken En Groothandel",
    "sg:phone":"+31 315 341 983",
    "sg:postcode":"7011 GL",
    "sg:province":"Gelderland",
    "wof:name":"Puky Gmbh En Co Kg",
    "wof:placetype":"venue"
},
  "geometry": {"coordinates":[6.345887,51.926807],"type":"Point"}
}