{
  "type": "Feature",
  "properties": {
    "addr:full":"Voorburgstraat 38 Loenersloot Utrecht 3634 AW",
    "addr:housenumber":"38",
    "addr:postcode":"3634 aw",
    "addr:street":"Voorburgstraat",
    "iso:country":"NL",
    "sg:address":"Voorburgstraat 38",
    "sg:city":"Loenersloot",
    "sg:orig_category":"Werving And Selectie Van Vast Personeel",
    "sg:phone":"+31 294 295 043",
    "sg:postcode":"3634 AW",
    "sg:province":"Utrecht",
    "wof:name":"Drs M M Claassen",
    "wof:placetype":"venue"
},
  "geometry": {"coordinates":[5.0012521744,52.2300262451],"type":"Point"}
}