{
  "type": "Feature",
  "properties": {
    "addr:full":"Halve Maan 16 Lobith Gelderland 6915 SW",
    "addr:housenumber":"16;6915",
    "addr:street":"Halve Maan;Gelderland;Sw",
    "iso:country":"NL",
    "sg:address":"Halve Maan 16",
    "sg:city":"Lobith",
    "sg:orig_category":"Zonnebank- En Solariumcentra",
    "sg:phone":"+31 316 542 417",
    "sg:postcode":"6915 SW",
    "sg:province":"Gelderland",
    "wof:name":"Caroline",
    "wof:placetype":"venue"
},
  "geometry": {"coordinates":[6.112044,51.86544],"type":"Point"}
}