{
  "type": "Feature",
  "properties": {
    "addr:full":"Kerkewijk 254 Veenendaal Utrecht 3904 JL",
    "addr:housenumber":"254",
    "addr:postcode":"3904 jl",
    "addr:street":"Kerkewijk",
    "iso:country":"NL",
    "sg:address":"Kerkewijk 254",
    "sg:city":"Veenendaal",
    "sg:orig_category":"Technische Studies And Onderzoek",
    "sg:phone":"+31 318 523 970",
    "sg:postcode":"3904 JL",
    "sg:province":"Utrecht",
    "wof:name":"Van Den Akker Advies",
    "wof:placetype":"venue"
},
  "geometry": {"coordinates":[5.5422,52.009521],"type":"Point"}
}