{
  "type": "Feature",
  "properties": {
    "iso:country":"NL",
    "sg:address":"Hoofdstraat 9",
    "sg:city":"Dalen",
    "sg:classifiers":[
        {
            "category":"Bakery",
            "type":"Food & Drink"
        }
    ],
    "sg:phone":"+31 524 552 300",
    "sg:postcode":"7751 GA",
    "sg:province":"Drenthe",
    "sg:tags":[
        "brood",
        "banket"
    ],
    "wof:name":"Echte Bakker Eising",
    "wof:placetype":"venue"
},
  "geometry": {"coordinates":[6.7564902306,52.6987686157],"type":"Point"}
}