{
  "type": "Feature",
  "properties": {
    "addr:full":"Vriesestraat 114 Dordrecht Zuid-Holland 3311 NJ",
    "addr:housenumber":"114",
    "addr:postcode":"3311 nj",
    "addr:street":"Vriesestraat",
    "iso:country":"NL",
    "sg:address":"Vriesestraat 114",
    "sg:city":"Dordrecht",
    "sg:orig_category":"Huishoudapparatuur, Televisies And Radio'S",
    "sg:phone":"+31 78 613 0064",
    "sg:postcode":"3311 NJ",
    "sg:province":"Zuid-Holland",
    "wof:name":"Stofzuigerhuis Knol",
    "wof:placetype":"venue"
},
  "geometry": {"coordinates":[4.669197,51.813],"type":"Point"}
}