{
  "type": "Feature",
  "properties": {
    "addr:full":"Hofwegen 1 Bleskensgraaf Ca South Holland 2971 XA",
    "addr:housenumber":"1",
    "addr:postcode":"ca;2971 xa",
    "addr:street":"Hofwegen",
    "iso:country":"NL",
    "sg:address":"Hofwegen 1",
    "sg:city":"Bleskensgraaf Ca",
    "sg:orig_category":"Onderhoudswerken",
    "sg:phone":"+31 184 692 951",
    "sg:postcode":"2971 XA",
    "sg:province":"South Holland",
    "wof:name":"Wijk, Jan Van",
    "wof:placetype":"venue"
},
  "geometry": {"coordinates":[4.795202,51.869442],"type":"Point"}
}