{
  "type": "Feature",
  "properties": {
    "addr:full":"Dubbele Buurt 9 Hoorn Nh Noord-Holland 1621 JV",
    "addr:housenumber":"9",
    "addr:postcode":"1621 jv",
    "addr:street":"Dubbele Buurt",
    "iso:country":"NL",
    "sg:address":"Dubbele Buurt 9",
    "sg:city":"Hoorn Nh",
    "sg:classifiers":[
        {
            "category":"Fast Food",
            "type":"Food & Drink"
        }
    ],
    "sg:phone":"+31 229 270 686",
    "sg:postcode":"1621 JV",
    "sg:province":"Noord-Holland",
    "sg:tags":[
        "afhaal",
        "restaurant"
    ],
    "wof:name":"Shoarmazaak Gaziantep",
    "wof:placetype":"venue"
},
  "geometry": {"coordinates":[5.052662,52.642574],"type":"Point"}
}