{
  "type": "Feature",
  "properties": {
    "addr:full":"Halvestraat 21 Deventer NL.08 7412 VN",
    "addr:housenumber":"21;nl.08",
    "addr:postcode":"7412 vn",
    "addr:street":"Halvestraat",
    "iso:country":"NL",
    "sg:address":"Halvestraat 21",
    "sg:city":"Deventer",
    "sg:orig_category":"Gespecialiseerde Voeding",
    "sg:phone":"+31 570 618 170",
    "sg:postcode":"7412 VN",
    "sg:province":"NL.08",
    "wof:name":"A Celik",
    "wof:placetype":"venue"
},
  "geometry": {"coordinates":[6.149969,52.259701],"type":"Point"}
}