{
  "type": "Feature",
  "properties": {
    "addr:full":"Wyzend 70 Wognum North Holland 1687 JA",
    "addr:housenumber":"70",
    "addr:postcode":"1687 ja",
    "addr:street":"Wyzend",
    "iso:country":"NL",
    "sg:address":"Wyzend 70",
    "sg:city":"Wognum",
    "sg:orig_category":"Autopoetsbedrijven",
    "sg:phone":"+31 229 575 040",
    "sg:postcode":"1687 JA",
    "sg:province":"North Holland",
    "wof:name":"Wnm Cars & Cleaning Wognum",
    "wof:placetype":"venue"
},
  "geometry": {"coordinates":[5.028059,52.687603],"type":"Point"}
}