{
  "type": "Feature",
  "properties": {
    "addr:full":"Julianaweg 11 Kortenhoef Noord-Holland 1241 VV",
    "addr:housenumber":"11",
    "addr:postcode":"1241 vv",
    "addr:street":"Julianaweg",
    "iso:country":"NL",
    "sg:address":"Julianaweg 11",
    "sg:city":"Kortenhoef",
    "sg:orig_category":"Goederenvervoer Over De Weg",
    "sg:phone":"+31 35 656 0542",
    "sg:postcode":"1241 VV",
    "sg:province":"Noord-Holland",
    "wof:name":"J W De Groot",
    "wof:placetype":"venue"
},
  "geometry": {"coordinates":[5.117706,52.238564],"type":"Point"}
}