{
  "type": "Feature",
  "properties": {
    "addr:full":"Stationswg 92-94 Alkmaar Noord-Holland 1815 CE",
    "addr:housenumber":"92-94",
    "addr:postcode":"alkmaar;1815 ce",
    "iso:country":"NL",
    "sg:address":"Stationswg 92-94",
    "sg:city":"Alkmaar",
    "sg:classifiers":[
        {
            "category":"Travel",
            "subcategory":"Hotels & Motels",
            "type":"Entertainment"
        }
    ],
    "sg:phone":"+31 72 512 3911",
    "sg:postcode":"1815 CE",
    "sg:province":"Noord-Holland",
    "wof:name":"Stad & Land Hotel",
    "wof:placetype":"venue"
},
  "geometry": {"coordinates":[4.746258,52.634361],"type":"Point"}
}