{
  "type": "Feature",
  "properties": {
    "addr:full":"Koning Willem Ii-Weg 16 'T Zand Nh Noord-Holland 1756 BH",
    "addr:housenumber":"16",
    "addr:postcode":"1756 bh",
    "addr:street":"Koning Willem Ii-Weg",
    "iso:country":"NL",
    "sg:address":"Koning Willem Ii-Weg 16",
    "sg:city":"'T Zand Nh",
    "sg:orig_category":"Metaalbekleding And -Behandeling",
    "sg:phone":"+31 224 593 490",
    "sg:postcode":"1756 BH",
    "sg:province":"Noord-Holland",
    "wof:name":"C M Dijkman Dulkes",
    "wof:placetype":"venue"
},
  "geometry": {"coordinates":[4.7598810196,52.842086792],"type":"Point"}
}