{
  "type": "Feature",
  "properties": {
    "addr:full":"Heidestein 7 Driebergen Rysenb Utrecht 3971 ND",
    "addr:housenumber":"7",
    "addr:postcode":"3971 nd",
    "addr:street":"Heidestein;Rysenb",
    "iso:country":"NL",
    "sg:address":"Heidestein 7",
    "sg:city":"Driebergen Rysenb",
    "sg:orig_category":"Adviesbureaus Bedrijfsorganisatie",
    "sg:phone":"+31 343 518 904",
    "sg:postcode":"3971 ND",
    "sg:province":"Utrecht",
    "wof:name":"Mgp",
    "wof:placetype":"venue"
},
  "geometry": {"coordinates":[5.266401,52.07011],"type":"Point"}
}