{
  "type": "Feature",
  "properties": {
    "addr:full":"Ysvogelstr 4 Enschede Overijssel 7523 WH",
    "addr:housenumber":"4",
    "addr:postcode":"7523 wh",
    "addr:street":"Ysvogelstr",
    "iso:country":"NL",
    "sg:address":"Ysvogelstr 4",
    "sg:city":"Enschede",
    "sg:orig_category":"Kantoor- En Secretariaatsservice",
    "sg:phone":"+31 53 433 2354",
    "sg:postcode":"7523 WH",
    "sg:province":"Overijssel",
    "wof:name":"Ancora",
    "wof:placetype":"venue"
},
  "geometry": {"coordinates":[6.895637989,52.2370796204],"type":"Point"}
}