{
  "type": "Feature",
  "properties": {
    "addr:full":"Westluidensestr 41 Tiel Gelderland 4001 NE",
    "addr:housenumber":"41;4001",
    "addr:street":"Westluidensestr;Gelderland;Ne",
    "iso:country":"NL",
    "sg:address":"Westluidensestr 41",
    "sg:city":"Tiel",
    "sg:orig_category":"Bloemen En Planten",
    "sg:phone":"+31 344 621 957",
    "sg:postcode":"4001 NE",
    "sg:province":"Gelderland",
    "wof:name":"Cactus, De",
    "wof:placetype":"venue"
},
  "geometry": {"coordinates":[5.437723,51.885487],"type":"Point"}
}