{
  "type": "Feature",
  "properties": {
    "addr:full":"Schepenln 33 Medemblik Noord-Holland 1671 RJ",
    "addr:housenumber":"33",
    "addr:postcode":"1671 rj",
    "addr:street":"Schepenln",
    "iso:country":"NL",
    "sg:address":"Schepenln 33",
    "sg:city":"Medemblik",
    "sg:orig_category":"Kappers",
    "sg:phone":"+31 227 543 624",
    "sg:postcode":"1671 RJ",
    "sg:province":"Noord-Holland",
    "wof:name":"Sandra",
    "wof:placetype":"venue"
},
  "geometry": {"coordinates":[5.101507,52.759861],"type":"Point"}
}