{
  "type": "Feature",
  "properties": {
    "iso:country":"NL",
    "sg:address":"President Kennedylaan 206",
    "sg:city":"Roosendaal",
    "sg:orig_category":"Fotostudio'S And Fotografen",
    "sg:phone":"+31 165 568 996",
    "sg:postcode":"4707 BH",
    "sg:province":"North Brabant",
    "wof:name":"Foto Ine",
    "wof:placetype":"venue"
},
  "geometry": {"coordinates":[4.462294,51.5145],"type":"Point"}
}