{
  "type": "Feature",
  "properties": {
    "addr:full":"Da Costaln 14 Amstelveen North Holland 1182 EG",
    "addr:housenumber":"14",
    "addr:postcode":"1182 eg",
    "iso:country":"NL",
    "sg:address":"Da Costaln 14",
    "sg:city":"Amstelveen",
    "sg:orig_category":"Loopbaanbegeleiding",
    "sg:phone":"+31 20 453 9825",
    "sg:postcode":"1182 EG",
    "sg:province":"North Holland",
    "wof:name":"Awater",
    "wof:placetype":"venue"
},
  "geometry": {"coordinates":[4.856945,52.303444],"type":"Point"}
}