{
  "type": "Feature",
  "properties": {
    "addr:full":"Dorpsstraat 217 Barendrecht South Holland 2992 AA",
    "addr:housenumber":"217",
    "addr:postcode":"2992 aa",
    "addr:street":"Dorpsstraat",
    "iso:country":"NL",
    "sg:address":"Dorpsstraat 217",
    "sg:city":"Barendrecht",
    "sg:orig_category":"Boekhouders",
    "sg:phone":"+31 180 690 362",
    "sg:postcode":"2992 AA",
    "sg:province":"South Holland",
    "wof:name":"Aba Administratiekantoor",
    "wof:placetype":"venue"
},
  "geometry": {"coordinates":[4.54064,51.853176],"type":"Point"}
}