{
  "type": "Feature",
  "properties": {
    "iso:country":"NL",
    "sg:address":"Punter 100",
    "sg:city":"Amstelveen",
    "sg:orig_category":"Accountants - Administratie- Consulenten En -Kantoren",
    "sg:phone":"+31 20 643 4543",
    "sg:postcode":"1186 RG",
    "sg:province":"North Holland",
    "wof:name":"Moes Vof, De",
    "wof:placetype":"venue"
},
  "geometry": {"coordinates":[4.863023,52.280884],"type":"Point"}
}