{
  "type": "Feature",
  "properties": {
    "addr:full":"Renbaanstraat 18-24 'S Gravenhage Zuid-Holland 2586 GB",
    "addr:housenumber":"18-24 '",
    "addr:postcode":"2586 gb",
    "addr:street":"Renbaanstraat",
    "iso:country":"NL",
    "sg:address":"Renbaanstraat 18-24",
    "sg:city":"'S Gravenhage",
    "sg:classifiers":[
        {
            "category":"Travel",
            "subcategory":"Hotels & Motels",
            "type":"Entertainment"
        }
    ],
    "sg:phone":"+31 70 354 8137",
    "sg:postcode":"2586 GB",
    "sg:province":"Zuid-Holland",
    "wof:name":"Hotel Mimosa",
    "wof:placetype":"venue"
},
  "geometry": {"coordinates":[4.281676,52.10965],"type":"Point"}
}