{
  "type": "Feature",
  "properties": {
    "addr:full":"Kanisstraat 5 Alkmaar Noord-Holland 1811 GJ",
    "addr:housenumber":"5",
    "addr:postcode":"1811 gj",
    "addr:street":"Kanisstraat",
    "iso:country":"NL",
    "sg:address":"Kanisstraat 5",
    "sg:city":"Alkmaar",
    "sg:orig_category":"Vertaal- And Tolkenbureaus",
    "sg:phone":"+31 72 511 2545",
    "sg:postcode":"1811 GJ",
    "sg:province":"Noord-Holland",
    "wof:name":"Forest-Flier Editorial Services",
    "wof:placetype":"venue"
},
  "geometry": {"coordinates":[4.741414,52.633389],"type":"Point"}
}