{
  "type": "Feature",
  "properties": {
    "addr:full":"Achter De Hoven 4 Maasbree Limburg 5993 CR",
    "addr:housenumber":"4",
    "addr:postcode":"5993 cr",
    "addr:street":"Achter De Hoven",
    "iso:country":"NL",
    "sg:address":"Achter De Hoven 4",
    "sg:city":"Maasbree",
    "sg:orig_category":"Verenigingsgebouwen",
    "sg:phone":"+31 77 465 2248",
    "sg:postcode":"5993 CR",
    "sg:province":"Limburg",
    "wof:name":"Adelaer, D'N",
    "wof:placetype":"venue"
},
  "geometry": {"coordinates":[6.048817,51.358643],"type":"Point"}
}