{
  "type": "Feature",
  "properties": {
    "iso:country":"NL",
    "sg:address":"Houtmanstraat 26",
    "sg:city":"Alkmaar",
    "sg:orig_category":"Autokeuringen",
    "sg:phone":"+31 72 511 5634",
    "sg:postcode":"1817 EL",
    "sg:province":"Noord-Holland",
    "wof:name":"Garage Th De Vries",
    "wof:placetype":"venue"
},
  "geometry": {"coordinates":[4.734029,52.639584],"type":"Point"}
}