{
  "type": "Feature",
  "properties": {
    "iso:country":"NL",
    "sg:address":"Tuinwg 16",
    "sg:city":"Zuid Beyerland",
    "sg:orig_category":"Adviesbureaus Bedrijfsorganisatie",
    "sg:phone":"+31 186 660 640",
    "sg:postcode":"3284 XS",
    "sg:province":"Zuid-Holland",
    "wof:name":"Houcke Bv, H Van",
    "wof:placetype":"venue"
},
  "geometry": {"coordinates":[4.371239,51.752132],"type":"Point"}
}