{
  "type": "Feature",
  "properties": {
    "addr:full":"Klein Westerwijksestraat 16 Biest Houtakker North Brabant 5084 HP",
    "addr:housenumber":"16",
    "addr:postcode":"5084 hp",
    "addr:street":"Klein Westerwijksestraat;Houtakker",
    "iso:country":"NL",
    "sg:address":"Klein Westerwijksestraat 16",
    "sg:city":"Biest Houtakker",
    "sg:classifiers":[
        {
            "category":"Retail",
            "subcategory":"Storage",
            "type":"Services"
        }
    ],
    "sg:phone":"+31 13 505 1792",
    "sg:postcode":"5084 HP",
    "sg:province":"North Brabant",
    "sg:tags":[
        "opslag",
        "bewaring"
    ],
    "wof:name":"Transportbedrijf Jos Soetens",
    "wof:placetype":"venue"
},
  "geometry": {"coordinates":[5.1447739601,51.5133018494],"type":"Point"}
}