{
  "type": "Feature",
  "properties": {
    "addr:full":"Walchersestr 83Ab Rotterdam South Holland 3083 NJ",
    "addr:housenumber":"83ab",
    "addr:postcode":"3083 nj",
    "addr:street":"Walchersestr",
    "iso:country":"NL",
    "sg:address":"Walchersestr 83Ab",
    "sg:city":"Rotterdam",
    "sg:orig_category":"Beeldende Kunstenaars",
    "sg:phone":"+31 10 429 7498",
    "sg:postcode":"3083 NJ",
    "sg:province":"South Holland",
    "wof:name":"Weeda, A G",
    "wof:placetype":"venue"
},
  "geometry": {"coordinates":[4.484159,51.887032],"type":"Point"}
}