{
  "type": "Feature",
  "properties": {
    "addr:full":"Kortenaerstr 24B Rotterdam South Holland 3012 VE",
    "addr:housenumber":"24b",
    "addr:postcode":"3012",
    "addr:street":"Kortenaerstr;Ve",
    "iso:country":"NL",
    "sg:address":"Kortenaerstr 24B",
    "sg:city":"Rotterdam",
    "sg:orig_category":"Kunsthandel",
    "sg:phone":"+31 10 270 9357",
    "sg:postcode":"3012 VE",
    "sg:province":"South Holland",
    "sg:website":"http://www.kunsthandel-esthetica.nl",
    "wof:name":"Esthetica",
    "wof:placetype":"venue"
},
  "geometry": {"coordinates":[4.477155,51.913589],"type":"Point"}
}