{
  "type": "Feature",
  "properties": {
    "addr:full":"Stationsstr 19 Sittard Limburg 6131 AX",
    "addr:housenumber":"19",
    "addr:postcode":"6131 ax",
    "addr:street":"Stationsstr",
    "iso:country":"NL",
    "sg:address":"Stationsstr 19",
    "sg:city":"Sittard",
    "sg:orig_category":"Boeken En Tijdschriften",
    "sg:phone":"+31 46 451 5074",
    "sg:postcode":"6131 AX",
    "sg:province":"Limburg",
    "wof:name":"Atomik",
    "wof:placetype":"venue"
},
  "geometry": {"coordinates":[5.860739,51.001896],"type":"Point"}
}