{
  "type": "Feature",
  "properties": {
    "iso:country":"NL",
    "sg:address":"Emmastr 31A",
    "sg:city":"Bleiswyk",
    "sg:orig_category":"Bloemen En Planten",
    "sg:phone":"+31 10 522 1728",
    "sg:postcode":"2665 CR",
    "sg:province":"Zuid-Holland",
    "wof:name":"Michael",
    "wof:placetype":"venue"
},
  "geometry": {"coordinates":[4.53129,52.008369],"type":"Point"}
}