{
  "type": "Feature",
  "properties": {
    "iso:country":"NL",
    "sg:address":"Past Roozenln 8",
    "sg:city":"Amstelveen",
    "sg:orig_category":"Bloemen En Planten",
    "sg:phone":"+31 20 645 0038",
    "sg:postcode":"1187 AN",
    "sg:province":"North Holland",
    "wof:name":"Duna",
    "wof:placetype":"venue"
},
  "geometry": {"coordinates":[4.837156,52.291519],"type":"Point"}
}