{
  "type": "Feature",
  "properties": {
    "addr:full":"Wyldpaed O 30 Twyzelerheide Friesland 9287 VN",
    "addr:housenumber":"30",
    "addr:postcode":"9287 vn",
    "addr:street":"Wyldpaed O",
    "iso:country":"NL",
    "sg:address":"Wyldpaed O 30",
    "sg:city":"Twyzelerheide",
    "sg:orig_category":"Hoefsmederijen",
    "sg:phone":"+31 511 442 544",
    "sg:postcode":"9287 VN",
    "sg:province":"Friesland",
    "wof:name":"Kramer",
    "wof:placetype":"venue"
},
  "geometry": {"coordinates":[6.074213,53.248161],"type":"Point"}
}