{
  "type": "Feature",
  "properties": {
    "addr:full":"Ambachtshof 13 Dronten Flevoland 8251 KV",
    "addr:housenumber":"13",
    "addr:postcode":"8251 kv",
    "addr:street":"Ambachtshof;Flevoland",
    "iso:country":"NL",
    "sg:address":"Ambachtshof 13",
    "sg:city":"Dronten",
    "sg:orig_category":"Loodgieterswerk, Verwarming And Sanitaire Installaties",
    "sg:phone":"+31 321 313 302",
    "sg:postcode":"8251 KV",
    "sg:province":"Flevoland",
    "wof:name":"Technisch Buro Nijkamp Bv",
    "wof:placetype":"venue"
},
  "geometry": {"coordinates":[5.732327,52.534607],"type":"Point"}
}