{
  "type": "Feature",
  "properties": {
    "iso:country":"NL",
    "sg:address":"Bleiswijkseweg 34",
    "sg:city":"Zoetermeer",
    "sg:orig_category":"Elektrische Apparatuur Gh",
    "sg:phone":"+31 79 341 1364",
    "sg:postcode":"2712 PD",
    "sg:province":"South Holland",
    "wof:name":"Huurman Elektrotechnische Systemen",
    "wof:placetype":"venue"
},
  "geometry": {"coordinates":[4.509993,52.049904],"type":"Point"}
}