{
  "type": "Feature",
  "properties": {
    "iso:country":"NL",
    "sg:address":"Kraaijesteijn 32",
    "sg:city":"Honselersdijk",
    "sg:orig_category":"Metaalwerken",
    "sg:phone":"+31 174 630 010",
    "sg:postcode":"2675 RA",
    "sg:province":"Zuid-Holland",
    "wof:name":"P.A. Mast Kassenbouw",
    "wof:placetype":"venue"
},
  "geometry": {"coordinates":[4.226654,52.010246],"type":"Point"}
}