{
  "type": "Feature",
  "properties": {
    "addr:full":"Vd D V Maasdamwg 2 Hoogezand Groningen 9602 VM",
    "addr:housenumber":"2",
    "addr:postcode":"9602 vm",
    "addr:street":"Maasdamwg",
    "iso:country":"NL",
    "sg:address":"Vd D V Maasdamwg 2",
    "sg:city":"Hoogezand",
    "sg:orig_category":"Wasmachines En Wasdrogers - Onderhoud En Reparatie",
    "sg:phone":"+31 598 326 889",
    "sg:postcode":"9602 VM",
    "sg:province":"Groningen",
    "wof:name":"Expert",
    "wof:placetype":"venue"
},
  "geometry": {"coordinates":[6.7542648315,53.1555099487],"type":"Point"}
}