{
  "type": "Feature",
  "properties": {
    "addr:full":"Microfoonstraat 5 Almere NL. 1322 BN",
    "addr:housenumber":"5",
    "addr:postcode":"1322 bn",
    "addr:street":"Microfoonstraat;Nl.",
    "iso:country":"NL",
    "sg:address":"Microfoonstraat 5",
    "sg:city":"Almere",
    "sg:orig_category":"Huishoudapparatuur, Televisies And Radio'S",
    "sg:phone":"+31 36 546 2600",
    "sg:postcode":"1322 BN",
    "sg:province":"NL.",
    "wof:name":"Radio Holland Electronics",
    "wof:placetype":"venue"
},
  "geometry": {"coordinates":[5.179729,52.347183],"type":"Point"}
}