{
  "type": "Feature",
  "properties": {
    "addr:full":"Zuidzijde 49 Bodegraven Zuid-Holland 2411 RS",
    "addr:housenumber":"49",
    "addr:postcode":"2411 rs",
    "addr:street":"Zuidzijde",
    "iso:country":"NL",
    "sg:address":"Zuidzijde 49",
    "sg:city":"Bodegraven",
    "sg:orig_category":"Begrafenisondernemers",
    "sg:phone":"+31 172 613 498",
    "sg:postcode":"2411 RS",
    "sg:province":"Zuid-Holland",
    "wof:name":"De Laatste Eer",
    "wof:placetype":"venue"
},
  "geometry": {"coordinates":[4.747547,52.085552],"type":"Point"}
}