{
  "type": "Feature",
  "properties": {
    "iso:country":"NL",
    "sg:address":"Nyverheidsstr 60",
    "sg:city":"Oldenzaal",
    "sg:orig_category":"Hijswerktuigen",
    "sg:phone":"+31 541 532 300",
    "sg:postcode":"7575 BK",
    "sg:province":"Overijssel",
    "wof:name":"Ropeblock Bv",
    "wof:placetype":"venue"
},
  "geometry": {"coordinates":[6.92655,52.293892],"type":"Point"}
}