{
  "type": "Feature",
  "properties": {
    "addr:full":"M Michielshof 4 De Ryp North Holland 1483 CC",
    "addr:housenumber":"4;1483",
    "addr:postcode":"cc",
    "addr:street":"M Michielshof;De Ryp North",
    "iso:country":"NL",
    "sg:address":"M Michielshof 4",
    "sg:city":"De Ryp",
    "sg:orig_category":"Adviesbureaus Bedrijfsorganisatie",
    "sg:phone":"+31 299 672 410",
    "sg:postcode":"1483 CC",
    "sg:province":"North Holland",
    "wof:name":"Visser, J M",
    "wof:placetype":"venue"
},
  "geometry": {"coordinates":[4.846465,52.560177],"type":"Point"}
}