{
  "type": "Feature",
  "properties": {
    "iso:country":"NL",
    "sg:address":"M Michielshof 4",
    "sg:city":"De Ryp",
    "sg:orig_category":"Adviesbureaus Bedrijfsorganisatie",
    "sg:phone":"+31 299 672 410",
    "sg:postcode":"1483 CC",
    "sg:province":"North Holland",
    "wof:name":"Visser, J M",
    "wof:placetype":"venue"
},
  "geometry": {"coordinates":[4.846465,52.560177],"type":"Point"}
}