{
  "type": "Feature",
  "properties": {
    "iso:country":"NL",
    "sg:address":"Kerkstraat 24",
    "sg:city":"Bodegraven",
    "sg:orig_category":"Werving And Selectie Van Tijdelijk Personeel And Uitzendkantoren",
    "sg:phone":"+31 172 619 090",
    "sg:postcode":"2411 AD",
    "sg:province":"Zuid-Holland",
    "wof:name":"Start",
    "wof:placetype":"venue"
},
  "geometry": {"coordinates":[4.7475471497,52.0855522156],"type":"Point"}
}