{
  "type": "Feature",
  "properties": {
    "iso:country":"NL",
    "sg:address":"Tonnendijk 73",
    "sg:city":"Vroomshoop",
    "sg:orig_category":"Levende Dieren Gh",
    "sg:phone":"+31 546 642 536",
    "sg:postcode":"7681 BK",
    "sg:province":"NL.08",
    "wof:name":"A J A Wessel",
    "wof:placetype":"venue"
},
  "geometry": {"coordinates":[6.593281,52.465385],"type":"Point"}
}