{
  "type": "Feature",
  "properties": {
    "addr:full":"Landzichtln 84 Heemstede Noord-Holland 2101 ZK",
    "addr:housenumber":"84",
    "addr:postcode":"2101",
    "addr:street":"Landzichtln;Zk",
    "iso:country":"NL",
    "sg:address":"Landzichtln 84",
    "sg:city":"Heemstede",
    "sg:orig_category":"Koeriersdiensten",
    "sg:phone":"+31 23 528 8688",
    "sg:postcode":"2101 ZK",
    "sg:province":"Noord-Holland",
    "wof:name":"Pep",
    "wof:placetype":"venue"
},
  "geometry": {"coordinates":[4.621248,52.345287],"type":"Point"}
}