{
  "type": "Feature",
  "properties": {
    "addr:full":"Van Beekstraat 24 Landsmeer Noord-Holland 1121 NN",
    "addr:housenumber":"24",
    "addr:postcode":"1121 nn",
    "addr:street":"Van Beekstraat",
    "iso:country":"NL",
    "sg:address":"Van Beekstraat 24",
    "sg:city":"Landsmeer",
    "sg:orig_category":"Diverse Grafische Activiteiten",
    "sg:phone":"+31 20 482 4325",
    "sg:postcode":"1121 NN",
    "sg:province":"Noord-Holland",
    "wof:name":"Bv Mach Zettery Van Der Stelt V/H Laverm",
    "wof:placetype":"venue"
},
  "geometry": {"coordinates":[4.916031,52.429314],"type":"Point"}
}