{
  "type": "Feature",
  "properties": {
    "addr:full":"Julianaln 18 Veendam Groningen 9641 LZ",
    "addr:housenumber":"18",
    "addr:postcode":"9641 lz",
    "addr:street":"Julianaln",
    "iso:country":"NL",
    "sg:address":"Julianaln 18",
    "sg:city":"Veendam",
    "sg:orig_category":"Webdesign Bureaus",
    "sg:phone":"+31 598 636 855",
    "sg:postcode":"9641 LZ",
    "sg:province":"Groningen",
    "sg:website":"http://www.vrieso.nl",
    "wof:name":"Staal",
    "wof:placetype":"venue"
},
  "geometry": {"coordinates":[6.8743610382,53.1024932861],"type":"Point"}
}