{
  "type": "Feature",
  "properties": {
    "addr:full":"Harkebuurt 3 Oosterend Nh Noord-Holland 1794 HM",
    "addr:housenumber":"3",
    "addr:postcode":"1794 hm",
    "addr:street":"Harkebuurt",
    "iso:country":"NL",
    "sg:address":"Harkebuurt 3",
    "sg:city":"Oosterend Nh",
    "sg:orig_category":"Diverse Consumentenartikelen Gh",
    "sg:phone":"+31 222 318 661",
    "sg:postcode":"1794 HM",
    "sg:province":"Noord-Holland",
    "wof:name":"D.G.P. Texel",
    "wof:placetype":"venue"
},
  "geometry": {"coordinates":[4.861241,53.086971],"type":"Point"}
}