{
  "type": "Feature",
  "properties": {
    "addr:full":"Pr Hendrikln 15 Bergen Nh North Holland 1862 EK",
    "addr:housenumber":"15",
    "addr:postcode":"1862 ek",
    "iso:country":"NL",
    "sg:address":"Pr Hendrikln 15",
    "sg:city":"Bergen Nh",
    "sg:orig_category":"Verhuizingen",
    "sg:phone":"+31 72 581 2139",
    "sg:postcode":"1862 EK",
    "sg:province":"North Holland",
    "wof:name":"Plomper & De Graaf",
    "wof:placetype":"venue"
},
  "geometry": {"coordinates":[4.704669,52.670723],"type":"Point"}
}