{
  "type": "Feature",
  "properties": {
    "iso:country":"NL",
    "sg:address":"Bylander 8",
    "sg:city":"Huissen",
    "sg:orig_category":"Machineonderhoud En -Reparatie",
    "sg:phone":"+31 26 325 0916",
    "sg:postcode":"6852 DJ",
    "sg:province":"Gelderland",
    "wof:name":"Maakgoed",
    "wof:placetype":"venue"
},
  "geometry": {"coordinates":[5.929588,51.943516],"type":"Point"}
}