{
  "type": "Feature",
  "properties": {
    "iso:country":"NL",
    "sg:address":"Midachten 31",
    "sg:city":"Epe",
    "sg:orig_category":"Kappers",
    "sg:phone":"+31 578 629 634",
    "sg:postcode":"8162 CK",
    "sg:province":"Gelderland",
    "wof:name":"W.J. Van Tongeren",
    "wof:placetype":"venue"
},
  "geometry": {"coordinates":[5.98463,52.355991],"type":"Point"}
}