{
  "type": "Feature",
  "properties": {
    "addr:full":"Harlingerstraatweg 130 Leeuwarden Provincie Friesland 8915 CP",
    "addr:housenumber":"130",
    "addr:postcode":"8915 cp",
    "addr:street":"Harlingerstraatweg;Provincie Friesland",
    "iso:country":"NL",
    "sg:address":"Harlingerstraatweg 130",
    "sg:city":"Leeuwarden",
    "sg:orig_category":"Begrafenisondernemers",
    "sg:phone":"+31 58 212 7274",
    "sg:postcode":"8915 CP",
    "sg:province":"Provincie Friesland",
    "wof:name":"Begraafplaats",
    "wof:placetype":"venue"
},
  "geometry": {"coordinates":[5.7738289833,53.205493927],"type":"Point"}
}