{
  "type": "Feature",
  "properties": {
    "addr:full":"Dkn Goossensln 7 Grave Noord-Brabant 5361 KA",
    "addr:housenumber":"7",
    "addr:postcode":"5361 ka",
    "addr:street":"Goossensln",
    "iso:country":"NL",
    "sg:address":"Dkn Goossensln 7",
    "sg:city":"Grave",
    "sg:orig_category":"Marktonderzoekbureaus",
    "sg:phone":"+31 486 473 807",
    "sg:postcode":"5361 KA",
    "sg:province":"Noord-Brabant",
    "wof:name":"Multifact",
    "wof:placetype":"venue"
},
  "geometry": {"coordinates":[-92.151741,32.929253],"type":"Point"}
}