{
  "type": "Feature",
  "properties": {
    "addr:full":"Randervordestraat 6 Hoogeveen Provincie Drenthe 7906 HM",
    "addr:housenumber":"6",
    "addr:postcode":"7906 hm",
    "addr:street":"Randervordestraat;Provincie",
    "iso:country":"NL",
    "sg:address":"Randervordestraat 6",
    "sg:city":"Hoogeveen",
    "sg:orig_category":"Boekhouders",
    "sg:phone":"+31 528 268 049",
    "sg:postcode":"7906 HM",
    "sg:province":"Provincie Drenthe",
    "wof:name":"Administratie- En Belastingadviesbureau",
    "wof:placetype":"venue"
},
  "geometry": {"coordinates":[6.481074,52.712521],"type":"Point"}
}