{
  "type": "Feature",
  "properties": {
    "iso:country":"NL",
    "sg:address":"Konijnenbergerweg 12",
    "sg:city":"Hattem",
    "sg:orig_category":"Farmaceutische Producten Gh",
    "sg:phone":"+31 38 444 2156",
    "sg:postcode":"8051 CC",
    "sg:province":"Gelderland",
    "wof:name":"Vof Handelsonderneming J. Slijkhuis",
    "wof:placetype":"venue"
},
  "geometry": {"coordinates":[6.074044,52.457207],"type":"Point"}
}