{
  "type": "Feature",
  "properties": {
    "addr:full":"Wilhelminastr 55 Lisse Zuid-Holland 2161 PH",
    "addr:housenumber":"55",
    "addr:postcode":"2161",
    "addr:street":"Wilhelminastr",
    "iso:country":"NL",
    "sg:address":"Wilhelminastr 55",
    "sg:city":"Lisse",
    "sg:orig_category":"Schoonheidsinstituten",
    "sg:phone":"+31 252 414 290",
    "sg:postcode":"2161 PH",
    "sg:province":"Zuid-Holland",
    "wof:name":"Marcelle'S Health International",
    "wof:placetype":"venue"
},
  "geometry": {"coordinates":[4.558938,52.262711],"type":"Point"}
}