{
  "type": "Feature",
  "properties": {
    "addr:full":"Veenwykswg 17 Ravenswoud Friesland 8427 RS",
    "addr:housenumber":"17",
    "addr:postcode":"8427 rs",
    "addr:street":"Veenwykswg",
    "iso:country":"NL",
    "sg:address":"Veenwykswg 17",
    "sg:city":"Ravenswoud",
    "sg:orig_category":"Levensmiddelen- Grondstoffen - Fabrieken En Groothandel",
    "sg:phone":"+31 516 433 477",
    "sg:postcode":"8427 RS",
    "sg:province":"Friesland",
    "wof:name":"Bf & S",
    "wof:placetype":"venue"
},
  "geometry": {"coordinates":[6.382452,52.964394],"type":"Point"}
}