{
  "type": "Feature",
  "properties": {
    "addr:full":"Asterstraat 144 Katwijk Zh Zuid-Holland 2223 VL",
    "addr:housenumber":"144",
    "addr:postcode":"2223 vl",
    "addr:street":"Asterstraat",
    "iso:country":"NL",
    "sg:address":"Asterstraat 144",
    "sg:city":"Katwijk Zh",
    "sg:orig_category":"Kappers",
    "sg:phone":"+31 71 401 6363",
    "sg:postcode":"2223 VL",
    "sg:province":"Zuid-Holland",
    "wof:name":"Hairtrend",
    "wof:placetype":"venue"
},
  "geometry": {"coordinates":[4.4214978218,52.1861724854],"type":"Point"}
}