{
  "type": "Feature",
  "properties": {
    "addr:full":"Reigerstraat 70 Haarlem Noord-Holland 2025 XE",
    "addr:housenumber":"70",
    "addr:postcode":"2025 xe",
    "addr:street":"Reigerstraat",
    "iso:country":"NL",
    "sg:address":"Reigerstraat 70",
    "sg:city":"Haarlem",
    "sg:orig_category":"Alternatieve Geneeskunde",
    "sg:phone":"+31 23 539 3157",
    "sg:postcode":"2025 XE",
    "sg:province":"Noord-Holland",
    "wof:name":"Janine Brouwer",
    "wof:placetype":"venue"
},
  "geometry": {"coordinates":[4.653303,52.413887],"type":"Point"}
}