{
  "type": "Feature",
  "properties": {
    "addr:full":"Kranenburgln 38 Naaldwyk South Holland 2672 ED",
    "addr:housenumber":"38",
    "addr:postcode":"2672 ed",
    "addr:street":"Kranenburgln",
    "iso:country":"NL",
    "sg:address":"Kranenburgln 38",
    "sg:city":"Naaldwyk",
    "sg:orig_category":"Fotoreportages",
    "sg:phone":"+31 6 51137047",
    "sg:postcode":"2672 ED",
    "sg:province":"South Holland",
    "wof:name":"Kraft Frank Fotografie",
    "wof:placetype":"venue"
},
  "geometry": {"coordinates":[4.21783,51.99551],"type":"Point"}
}