{
  "type": "Feature",
  "properties": {
    "iso:country":"NL",
    "sg:address":"Ruysdaelstr 108",
    "sg:city":"Amsterdam",
    "sg:orig_category":"Modellenbureaus En Modellen Freelance",
    "sg:phone":"+31 20 673 1894",
    "sg:postcode":"1071 XH",
    "sg:province":"North Holland",
    "sg:website":"http://www.hansdassen.com",
    "wof:name":"Dassen Produkties, Hans",
    "wof:placetype":"venue"
},
  "geometry": {"coordinates":[4.880118,52.353539],"type":"Point"}
}