{
  "type": "Feature",
  "properties": {
    "addr:full":"Noordlandweg 6 Terschelling Midsland Provincie Friesland 8891 HP",
    "addr:housenumber":"6",
    "addr:postcode":"8891 hp",
    "addr:street":"Noordlandweg;Friesland",
    "iso:country":"NL",
    "sg:address":"Noordlandweg 6",
    "sg:city":"Terschelling Midsland",
    "sg:orig_category":"Kampeerterreinen",
    "sg:phone":"+31 562 448 233",
    "sg:postcode":"8891 HP",
    "sg:province":"Provincie Friesland",
    "wof:name":"Camping Veldzicht",
    "wof:placetype":"venue"
},
  "geometry": {"coordinates":[5.288711071,53.3899688721],"type":"Point"}
}