{
  "type": "Feature",
  "properties": {
    "addr:full":"Hellebeukerwg 2555 Klimmen Limburg 6343 RK",
    "addr:postcode":"2555 klimmen;6343 rk",
    "iso:country":"NL",
    "sg:address":"Hellebeukerwg 2555",
    "sg:city":"Klimmen",
    "sg:orig_category":"Schoonheidsinstituten",
    "sg:phone":"+31 45 405 9177",
    "sg:postcode":"6343 RK",
    "sg:province":"Limburg",
    "wof:name":"Ser?na",
    "wof:placetype":"venue"
},
  "geometry": {"coordinates":[5.86425,50.87682],"type":"Point"}
}