{
  "type": "Feature",
  "properties": {
    "addr:full":"Kerkwg 55 Pynacker South Holland 2641 GB",
    "addr:housenumber":"55",
    "addr:postcode":"2641 gb",
    "addr:street":"Kerkwg;Pynacker South",
    "iso:country":"NL",
    "sg:address":"Kerkwg 55",
    "sg:city":"Pynacker",
    "sg:orig_category":"Keukens",
    "sg:phone":"+31 15 369 2195",
    "sg:postcode":"2641 GB",
    "sg:province":"South Holland",
    "wof:name":"Helm, Leo Van Der",
    "wof:placetype":"venue"
},
  "geometry": {"coordinates":[4.431869,52.016159],"type":"Point"}
}