{
  "type": "Feature",
  "properties": {
    "addr:full":"Kl Kreek 76 Amersfoort Utrecht 3823 JX",
    "addr:housenumber":"76",
    "addr:postcode":"3823 jx",
    "addr:street":"Kl Kreek",
    "iso:country":"NL",
    "sg:address":"Kl Kreek 76",
    "sg:city":"Amersfoort",
    "sg:orig_category":"Schoonheidsinstituten",
    "sg:phone":"+31 33 462 1807",
    "sg:postcode":"3823 JX",
    "sg:province":"Utrecht",
    "wof:name":"Set Neferoe",
    "wof:placetype":"venue"
},
  "geometry": {"coordinates":[5.39616,52.19297],"type":"Point"}
}