{
  "type": "Feature",
  "properties": {
    "addr:full":"A De M Vispoort 46 Deventer NL.08 7411 SM",
    "addr:housenumber":"46;nl.08",
    "addr:postcode":"7411 sm",
    "addr:street":"A De M Vispoort",
    "iso:country":"NL",
    "sg:address":"A De M Vispoort 46",
    "sg:city":"Deventer",
    "sg:orig_category":"Boekbinderijen",
    "sg:phone":"+31 570 611 298",
    "sg:postcode":"7411 SM",
    "sg:province":"NL.08",
    "sg:website":"http://www.geocities.com",
    "wof:name":"Francino",
    "wof:placetype":"venue"
},
  "geometry": {"coordinates":[6.159899,52.251034],"type":"Point"}
}