{
  "type": "Feature",
  "properties": {
    "iso:country":"NL",
    "sg:address":"Jan Hilgersweg 11",
    "sg:city":"Eindhoven",
    "sg:orig_category":"Elektrische Apparatuur Gh",
    "sg:phone":"+31 40 292 8666",
    "sg:postcode":"5657 ES",
    "sg:province":"North Brabant",
    "wof:name":"Molex Interconnect Ag",
    "wof:placetype":"venue"
},
  "geometry": {"coordinates":[5.3942,51.451897],"type":"Point"}
}