{
  "type": "Feature",
  "properties": {
    "addr:full":"Jasonstr 1 Eindhoven North Brabant 5631 JB",
    "addr:housenumber":"1",
    "addr:postcode":"5631 jb",
    "addr:street":"Jasonstr",
    "iso:country":"NL",
    "sg:address":"Jasonstr 1",
    "sg:city":"Eindhoven",
    "sg:orig_category":"Scholen Voor Basisonderwijs",
    "sg:phone":"+31 40 269 1222",
    "sg:postcode":"5631 JB",
    "sg:province":"North Brabant",
    "wof:name":"Evangelische Basisschool",
    "wof:placetype":"venue"
},
  "geometry": {"coordinates":[5.489218,51.466339],"type":"Point"}
}