{
  "type": "Feature",
  "properties": {
    "addr:full":"Raiffeisenln 45A Utrecht Utrecht 3571 TC",
    "addr:housenumber":"45a",
    "addr:postcode":"3571 tc",
    "addr:street":"Raiffeisenln",
    "iso:country":"NL",
    "sg:address":"Raiffeisenln 45A",
    "sg:city":"Utrecht",
    "sg:orig_category":"Advocaten En Advocatenkantoren",
    "sg:phone":"+31 30 271 4541",
    "sg:postcode":"3571 TC",
    "sg:province":"Utrecht",
    "sg:website":"http://www.boulogne.nl",
    "wof:name":"Boulogne, Mr A",
    "wof:placetype":"venue"
},
  "geometry": {"coordinates":[5.126785,52.107445],"type":"Point"}
}