{
  "type": "Feature",
  "properties": {
    "iso:country":"NL",
    "sg:address":"Prins Hendrikkade 84",
    "sg:city":"Amsterdam",
    "sg:orig_category":"Werving And Selectie Van Tijdelijk Personeel And Uitzendkantoren",
    "sg:phone":"+31 20 622 3014",
    "sg:postcode":"1012 AE",
    "sg:province":"Noord-Holland",
    "wof:name":"Individu Uitzendbureau",
    "wof:placetype":"venue"
},
  "geometry": {"coordinates":[4.9014720917,52.3767127991],"type":"Point"}
}