{
  "type": "Feature",
  "properties": {
    "addr:full":"Innsbruckweg 118 Rotterdam Zuid-Holland 3047 AH",
    "addr:housenumber":"118",
    "addr:postcode":"3047 ah",
    "addr:street":"Innsbruckweg",
    "iso:country":"NL",
    "sg:address":"Innsbruckweg 118",
    "sg:city":"Rotterdam",
    "sg:orig_category":"Fruit And Groenten Gh",
    "sg:phone":"+31 10 462 4565",
    "sg:postcode":"3047 AH",
    "sg:province":"Zuid-Holland",
    "wof:name":"Hars & Hagebauer Bv",
    "wof:placetype":"venue"
},
  "geometry": {"coordinates":[4.413825,51.944324],"type":"Point"}
}