{
  "type": "Feature",
  "properties": {
    "addr:full":"Putkamp 8 Herten Limburg 6049 AK",
    "addr:housenumber":"8",
    "addr:postcode":"6049 ak",
    "addr:street":"Putkamp",
    "iso:country":"NL",
    "sg:address":"Putkamp 8",
    "sg:city":"Herten",
    "sg:orig_category":"Kinderopvang",
    "sg:phone":"+31 475 318 937",
    "sg:postcode":"6049 AK",
    "sg:province":"Limburg",
    "wof:name":"Ot En Sien",
    "wof:placetype":"venue"
},
  "geometry": {"coordinates":[5.964695,51.179382],"type":"Point"}
}