{
  "type": "Feature",
  "properties": {
    "iso:country":"NL",
    "sg:address":"Centavoshof 11",
    "sg:city":"Amsterdam",
    "sg:orig_category":"Fotoreportages",
    "sg:phone":"+31 20 667 4858",
    "sg:postcode":"1060 SR",
    "sg:province":"Noord-Holland",
    "sg:website":"http://www.wendybos.nl",
    "wof:name":"Bos Fotoproducties, Wendy",
    "wof:placetype":"venue"
},
  "geometry": {"coordinates":[4.786302,52.345341],"type":"Point"}
}