{
  "type": "Feature",
  "properties": {
    "iso:country":"NL",
    "sg:address":"Verlaat 6",
    "sg:city":"Nijkerk Gld",
    "sg:orig_category":"Meubelzaken, Woning- And Keukeninrichting",
    "sg:phone":"+31 33 245 1332",
    "sg:postcode":"3861 AA",
    "sg:province":"Gelderland",
    "wof:name":"Frans Poorter Slaapcomfort",
    "wof:placetype":"venue"
},
  "geometry": {"coordinates":[5.484165,52.223301],"type":"Point"}
}