{
  "type": "Feature",
  "properties": {
    "addr:full":"Hubrechtstr 2 Leiderdorp South Holland 2351 SG",
    "addr:housenumber":"2",
    "addr:postcode":"2351 sg",
    "addr:street":"Hubrechtstr",
    "iso:country":"NL",
    "sg:address":"Hubrechtstr 2",
    "sg:city":"Leiderdorp",
    "sg:orig_category":"Kappers",
    "sg:phone":"+31 71 589 4838",
    "sg:postcode":"2351 SG",
    "sg:province":"South Holland",
    "wof:name":"Annelies, Haarboetiek",
    "wof:placetype":"venue"
},
  "geometry": {"coordinates":[4.529458046,52.1435394287],"type":"Point"}
}