{
  "type": "Feature",
  "properties": {
    "addr:full":"Nw Binnenwg 262C Rotterdam South Holland 3021 GR",
    "addr:housenumber":"262c",
    "addr:postcode":"3021",
    "iso:country":"NL",
    "sg:address":"Nw Binnenwg 262C",
    "sg:city":"Rotterdam",
    "sg:orig_category":"Fotoreportages",
    "sg:phone":"+31 10 477 6652",
    "sg:postcode":"3021 GR",
    "sg:province":"South Holland",
    "wof:name":"Bos, A",
    "wof:placetype":"venue"
},
  "geometry": {"coordinates":[4.459373,51.912922],"type":"Point"}
}