{
  "type": "Feature",
  "properties": {
    "addr:full":"Vaartdijk 4 Assendelft North Holland 1566 PL",
    "addr:housenumber":"4",
    "addr:postcode":"1566 pl",
    "addr:street":"Vaartdijk",
    "iso:country":"NL",
    "sg:address":"Vaartdijk 4",
    "sg:city":"Assendelft",
    "sg:orig_category":"Granen, Zaden And Diervoeders Gh",
    "sg:phone":"+31 75 687 4596",
    "sg:postcode":"1566 PL",
    "sg:province":"North Holland",
    "wof:name":"Gebroeders Van Eerde",
    "wof:placetype":"venue"
},
  "geometry": {"coordinates":[4.758911,52.454205],"type":"Point"}
}