{
  "type": "Feature",
  "properties": {
    "addr:full":"Provincialewg O 35 Haastrecht South Holland 2851 AA",
    "addr:housenumber":"35",
    "addr:postcode":"2851 aa",
    "iso:country":"NL",
    "sg:address":"Provincialewg O 35",
    "sg:city":"Haastrecht",
    "sg:classifiers":[
        {
            "category":"Retail",
            "subcategory":"Storage",
            "type":"Services"
        }
    ],
    "sg:phone":"+31 182 561 397",
    "sg:postcode":"2851 AA",
    "sg:province":"South Holland",
    "sg:tags":[
        "op-",
        "en",
        "overslagbedrijven"
    ],
    "wof:name":"Visser Vof",
    "wof:placetype":"venue"
},
  "geometry": {"coordinates":[4.832351,52.014915],"type":"Point"}
}