{
  "type": "Feature",
  "properties": {
    "addr:full":"Europawg 1 Zoeterwoude Zuid-Holland 2381 GR",
    "addr:housenumber":"1",
    "addr:postcode":"2381",
    "addr:street":"Europawg",
    "iso:country":"NL",
    "sg:address":"Europawg 1",
    "sg:city":"Zoeterwoude",
    "sg:classifiers":[
        {
            "category":"Retail",
            "subcategory":"Auto Repair",
            "type":"Services"
        }
    ],
    "sg:phone":"+31 71 580 1386",
    "sg:postcode":"2381 GR",
    "sg:province":"Zuid-Holland",
    "sg:tags":[
        "garage"
    ],
    "sg:website":"http://www.versteegenautos.nl",
    "wof:name":"Versteegen Auto'S Bv",
    "wof:placetype":"venue"
},
  "geometry": {"coordinates":[4.496577,52.129753],"type":"Point"}
}