{
  "type": "Feature",
  "properties": {
    "addr:full":"Heining 49 Amsterdam Noord-Holland 1047 AZ",
    "addr:housenumber":"49",
    "addr:postcode":"1047 az",
    "addr:street":"Heining",
    "iso:country":"NL",
    "sg:address":"Heining 49",
    "sg:city":"Amsterdam",
    "sg:orig_category":"Straalbedrijven",
    "sg:phone":"+31 20 497 5389",
    "sg:postcode":"1047 AZ",
    "sg:province":"Noord-Holland",
    "wof:name":"Gritstraal Bv",
    "wof:placetype":"venue"
},
  "geometry": {"coordinates":[4.767591,52.397133],"type":"Point"}
}