{
  "type": "Feature",
  "properties": {
    "addr:full":"Kloosterstraat 22 Simpelveld Limburg 6369 AD",
    "addr:housenumber":"22",
    "addr:postcode":"6369 ad",
    "addr:street":"Kloosterstraat",
    "iso:country":"NL",
    "sg:address":"Kloosterstraat 22",
    "sg:city":"Simpelveld",
    "sg:orig_category":"Meubelzaken, Woning- And Keukeninrichting",
    "sg:phone":"+31 45 544 1346",
    "sg:postcode":"6369 AD",
    "sg:province":"Limburg",
    "wof:name":"Vof Grooten",
    "wof:placetype":"venue"
},
  "geometry": {"coordinates":[5.9839110374,50.8342285156],"type":"Point"}
}