{
  "type": "Feature",
  "properties": {
    "addr:full":"Wagenstraat 27 Maassluis South Holland 3142 CR",
    "addr:housenumber":"27",
    "addr:postcode":"3142 cr",
    "addr:street":"Wagenstraat",
    "iso:country":"NL",
    "sg:address":"Wagenstraat 27",
    "sg:city":"Maassluis",
    "sg:orig_category":"Woninginrichting",
    "sg:phone":"+31 10 591 5100",
    "sg:postcode":"3142 CR",
    "sg:province":"South Holland",
    "wof:name":"Kruijt",
    "wof:placetype":"venue"
},
  "geometry": {"coordinates":[4.2518582344,51.9233856201],"type":"Point"}
}