{
  "type": "Feature",
  "properties": {
    "addr:full":"Parkwg 87 Ede Gld Gelderland 6717 HN",
    "addr:housenumber":"87",
    "addr:postcode":"6717 hn",
    "addr:street":"Parkwg;Gld Gelderland",
    "iso:country":"NL",
    "sg:address":"Parkwg 87",
    "sg:city":"Ede Gld",
    "sg:orig_category":"Zalenverhuur",
    "sg:phone":"+31 318 622 418",
    "sg:postcode":"6717 HN",
    "sg:province":"Gelderland",
    "wof:name":"Broadway",
    "wof:placetype":"venue"
},
  "geometry": {"coordinates":[5.666881,52.027691],"type":"Point"}
}