{
  "type": "Feature",
  "properties": {
    "addr:full":"Reaal 95 Hoorn Noord-Holland 1628 RE",
    "addr:housenumber":"95",
    "addr:postcode":"1628 re",
    "addr:street":"Reaal",
    "iso:country":"NL",
    "sg:address":"Reaal 95",
    "sg:city":"Hoorn",
    "sg:orig_category":"Kantoorartikelen",
    "sg:phone":"+31 229 272 999",
    "sg:postcode":"1628 RE",
    "sg:province":"Noord-Holland",
    "wof:name":"Memo Projectinrichting",
    "wof:placetype":"venue"
},
  "geometry": {"coordinates":[5.0930871964,52.6464614868],"type":"Point"}
}