{
  "type": "Feature",
  "properties": {
    "addr:full":"Klooslaan 52 Ridderkerk Zuid-Holland 2985 CL",
    "addr:housenumber":"52",
    "addr:postcode":"2985",
    "addr:street":"Klooslaan",
    "iso:country":"NL",
    "sg:address":"Klooslaan 52",
    "sg:city":"Ridderkerk",
    "sg:orig_category":"Loodgieterswerk, Verwarming And Sanitaire Installaties",
    "sg:phone":"+31 180 425 144",
    "sg:postcode":"2985 CL",
    "sg:province":"Zuid-Holland",
    "wof:name":"Van Gent Verbouwing & Onderhoud",
    "wof:placetype":"venue"
},
  "geometry": {"coordinates":[4.599393,51.861305],"type":"Point"}
}