{
  "type": "Feature",
  "properties": {
    "iso:country":"NL",
    "sg:address":"Aquamarynstr 75",
    "sg:city":"Hengelo Ov",
    "sg:orig_category":"Kunststoffen- Verwerkende Industrie",
    "sg:phone":"+31 74 243 5980",
    "sg:postcode":"7554 NN",
    "sg:province":"Overijssel",
    "wof:name":"Hemabo Kunststoftechniek",
    "wof:placetype":"venue"
},
  "geometry": {"coordinates":[6.76733,52.236221],"type":"Point"}
}