{
  "type": "Feature",
  "properties": {
    "addr:full":"Aquamarynstr 75 Hengelo Ov Overijssel 7554 NN",
    "addr:housenumber":"75",
    "addr:postcode":"7554 nn",
    "addr:street":"Aquamarynstr;Ov",
    "iso:country":"NL",
    "sg:address":"Aquamarynstr 75",
    "sg:city":"Hengelo Ov",
    "sg:orig_category":"Kunststoffen- Verwerkende Industrie",
    "sg:phone":"+31 74 243 5980",
    "sg:postcode":"7554 NN",
    "sg:province":"Overijssel",
    "wof:name":"Hemabo Kunststoftechniek",
    "wof:placetype":"venue"
},
  "geometry": {"coordinates":[6.76733,52.236221],"type":"Point"}
}