{
  "type": "Feature",
  "properties": {
    "addr:full":"Snellingerdk 4A Oosterwolde Fr Friesland 8431 EM",
    "addr:housenumber":"4a",
    "addr:postcode":"8431 em",
    "addr:street":"Snellingerdk",
    "iso:country":"NL",
    "sg:address":"Snellingerdk 4A",
    "sg:city":"Oosterwolde Fr",
    "sg:orig_category":"Bloemen En Planten",
    "sg:phone":"+31 516 513 469",
    "sg:postcode":"8431 EM",
    "sg:province":"Friesland",
    "wof:name":"Grit Vof",
    "wof:placetype":"venue"
},
  "geometry": {"coordinates":[6.290509,52.988888],"type":"Point"}
}