{
  "type": "Feature",
  "properties": {
    "addr:full":"Madeliefberg 11 Roosendaal Noord-Brabant 4708 NP",
    "addr:housenumber":"11",
    "addr:postcode":"4708 np",
    "addr:street":"Madeliefberg",
    "iso:country":"NL",
    "sg:address":"Madeliefberg 11",
    "sg:city":"Roosendaal",
    "sg:orig_category":"Machineonderhoud En -Reparatie",
    "sg:phone":"+31 165 315 764",
    "sg:postcode":"4708 NP",
    "sg:province":"Noord-Brabant",
    "wof:name":"Verheijen, C",
    "wof:placetype":"venue"
},
  "geometry": {"coordinates":[4.438014,51.521709],"type":"Point"}
}