{
  "type": "Feature",
  "properties": {
    "iso:country":"NL",
    "sg:address":"Handelsweg 10",
    "sg:city":"Amstelveen",
    "sg:orig_category":"Opticiens",
    "sg:phone":"+31 20 645 6796",
    "sg:postcode":"1181 ZA",
    "sg:province":"Noord-Holland",
    "wof:name":"Brilservice Bv",
    "wof:placetype":"venue"
},
  "geometry": {"coordinates":[4.8628659248,52.3024024963],"type":"Point"}
}