{
  "type": "Feature",
  "properties": {
    "addr:full":"Berkhoek 15 Boekel Noord-Brabant 5427 ES",
    "addr:housenumber":"15",
    "addr:postcode":"5427 es",
    "addr:street":"Berkhoek",
    "iso:country":"NL",
    "sg:address":"Berkhoek 15",
    "sg:city":"Boekel",
    "sg:orig_category":"Hek- En Rasterwerken",
    "sg:phone":"+31 492 325 080",
    "sg:postcode":"5427 ES",
    "sg:province":"Noord-Brabant",
    "wof:name":"Vbm",
    "wof:placetype":"venue"
},
  "geometry": {"coordinates":[5.67325,51.60281],"type":"Point"}
}