{
  "type": "Feature",
  "properties": {
    "addr:full":"Poeldijkstraat 10 Amsterdam North Holland 1059 VM",
    "addr:housenumber":"10",
    "addr:postcode":"1059 vm",
    "addr:street":"Poeldijkstraat",
    "iso:country":"NL",
    "sg:address":"Poeldijkstraat 10",
    "sg:city":"Amsterdam",
    "sg:orig_category":"Woningbouwverenigingen",
    "sg:phone":"+31 20 511 8000",
    "sg:postcode":"1059 VM",
    "sg:province":"North Holland",
    "wof:name":"Algemene Woningbouw Vereniging",
    "wof:placetype":"venue"
},
  "geometry": {"coordinates":[4.8437161446,52.3498840332],"type":"Point"}
}