{
  "type": "Feature",
  "properties": {
    "iso:country":"NL",
    "sg:address":"Galgeweg 64",
    "sg:city":"Naaldwijk",
    "sg:orig_category":"Gebouwenafwerking, Renovaties And Reiniging",
    "sg:phone":"+31 174 627 260",
    "sg:postcode":"2671 MS",
    "sg:province":"Zuid-Holland",
    "wof:name":"E.C. Van Dijk",
    "wof:placetype":"venue"
},
  "geometry": {"coordinates":[4.211866,51.977226],"type":"Point"}
}