{
  "type": "Feature",
  "properties": {
    "addr:full":"Leerdamhof 95 Amsterdam Zuidoost Noord-Holland 1108 BH",
    "addr:housenumber":"95",
    "addr:postcode":"zuidoost;1108 bh",
    "addr:street":"Leerdamhof",
    "iso:country":"NL",
    "sg:address":"Leerdamhof 95",
    "sg:city":"Amsterdam Zuidoost",
    "sg:orig_category":"Verenigingen En Stichtingen",
    "sg:phone":"+31 20 697 7990",
    "sg:postcode":"1108 BH",
    "sg:province":"Noord-Holland",
    "wof:name":"Dendrobatidae Ned",
    "wof:placetype":"venue"
},
  "geometry": {"coordinates":[4.975323,52.307842],"type":"Point"}
}