{
  "type": "Feature",
  "properties": {
    "iso:country":"NL",
    "sg:address":"Langeviele 27",
    "sg:city":"Middelburg",
    "sg:orig_category":"Kantoorartikelen",
    "sg:phone":"+31 118 627 317",
    "sg:postcode":"4331 LR",
    "sg:province":"Zeeland",
    "wof:name":"Visser Art Vof",
    "wof:placetype":"venue"
},
  "geometry": {"coordinates":[3.6091470718,51.497844696],"type":"Point"}
}