{
  "type": "Feature",
  "properties": {
    "addr:full":"Drievriendenhof 30 Dordrecht South Holland 3311 NM",
    "addr:housenumber":"30",
    "addr:postcode":"3311",
    "addr:street":"Drievriendenhof",
    "iso:country":"NL",
    "sg:address":"Drievriendenhof 30",
    "sg:city":"Dordrecht",
    "sg:orig_category":"Bloemen En Planten",
    "sg:phone":"+31 78 613 6050",
    "sg:postcode":"3311 NM",
    "sg:province":"South Holland",
    "wof:name":"Multifleur '90",
    "wof:placetype":"venue"
},
  "geometry": {"coordinates":[4.669125,51.813404],"type":"Point"}
}