{
  "type": "Feature",
  "properties": {
    "iso:country":"NL",
    "sg:address":"Hoofdstr 89",
    "sg:city":"Sassenheim",
    "sg:orig_category":"Werving En Selectie",
    "sg:phone":"+31 252 222 888",
    "sg:postcode":"2171 AS",
    "sg:province":"South Holland",
    "wof:name":"Condor Recruitment Group Bv",
    "wof:placetype":"venue"
},
  "geometry": {"coordinates":[4.5137138367,52.2208786011],"type":"Point"}
}