{
  "type": "Feature",
  "properties": {
    "addr:full":"Korvelseweg 6 Tilburg Noord-Brabant 5025 JH",
    "addr:housenumber":"6",
    "addr:postcode":"5025 jh",
    "addr:street":"Korvelseweg",
    "iso:country":"NL",
    "sg:address":"Korvelseweg 6",
    "sg:city":"Tilburg",
    "sg:orig_category":"Schoenen",
    "sg:phone":"+31 13 542 0577",
    "sg:postcode":"5025 JH",
    "sg:province":"Noord-Brabant",
    "wof:name":"Schoenen Pijnenburg",
    "wof:placetype":"venue"
},
  "geometry": {"coordinates":[5.078668,51.55304],"type":"Point"}
}