{
  "type": "Feature",
  "properties": {
    "addr:full":"Klokstg 93 Utrecht Utrecht 3512 EZ",
    "addr:housenumber":"93",
    "addr:postcode":"3512 ez",
    "addr:street":"Klokstg",
    "iso:country":"NL",
    "sg:address":"Klokstg 93",
    "sg:city":"Utrecht",
    "sg:orig_category":"Bedrijfsopleidingen",
    "sg:phone":"+31 30 230 2713",
    "sg:postcode":"3512 EZ",
    "sg:province":"Utrecht",
    "wof:name":"Enkelaar",
    "wof:placetype":"venue"
},
  "geometry": {"coordinates":[5.125296,52.094646],"type":"Point"}
}