{
  "type": "Feature",
  "properties": {
    "addr:full":"Oostelijke Handelskade 29 Amsterdam Noord-Holland 1019 BL",
    "addr:housenumber":"29;1019",
    "addr:postcode":"bl",
    "addr:street":"Oostelijke Handelskade",
    "iso:country":"NL",
    "sg:address":"Oostelijke Handelskade 29",
    "sg:city":"Amsterdam",
    "sg:orig_category":"Huishoudelijk Textiel Fab",
    "sg:phone":"+31 20 418 7664",
    "sg:postcode":"1019 BL",
    "sg:province":"Noord-Holland",
    "wof:name":"Y.L. Wolcken",
    "wof:placetype":"venue"
},
  "geometry": {"coordinates":[4.933527,52.3745],"type":"Point"}
}