{
  "type": "Feature",
  "properties": {
    "addr:full":"Sterrenlaan 2 Veldhoven North Brabant 5505 AJ",
    "addr:housenumber":"2",
    "addr:postcode":"5505 aj",
    "addr:street":"Sterrenlaan",
    "iso:country":"NL",
    "sg:address":"Sterrenlaan 2",
    "sg:city":"Veldhoven",
    "sg:orig_category":"Paramedische Behandelingen",
    "sg:phone":"+31 40 254 1856",
    "sg:postcode":"5505 AJ",
    "sg:province":"North Brabant",
    "wof:name":"A.M.H. Van Gool",
    "wof:placetype":"venue"
},
  "geometry": {"coordinates":[5.396643,51.414474],"type":"Point"}
}