{
  "type": "Feature",
  "properties": {
    "iso:country":"NL",
    "sg:address":"Hunthum 23",
    "sg:city":"Loenen Ad Vecht",
    "sg:orig_category":"Adviesbureaus Bedrijfsorganisatie",
    "sg:phone":"+31 294 233 700",
    "sg:postcode":"3632 XL",
    "sg:province":"Utrecht",
    "wof:name":"Jw",
    "wof:placetype":"venue"
},
  "geometry": {"coordinates":[5.025105,52.213505],"type":"Point"}
}