{
  "type": "Feature",
  "properties": {
    "addr:full":"Kruisstr 19 Valkenburg Lb Limburg 6301 PB",
    "addr:housenumber":"19",
    "addr:postcode":"lb;6301 pb",
    "addr:street":"Kruisstr",
    "iso:country":"NL",
    "sg:address":"Kruisstr 19",
    "sg:city":"Valkenburg Lb",
    "sg:orig_category":"Honden- En Kattentrimsalons",
    "sg:phone":"+31 43 601 4971",
    "sg:postcode":"6301 PB",
    "sg:province":"Limburg",
    "wof:name":"Kohinoor",
    "wof:placetype":"venue"
},
  "geometry": {"coordinates":[5.834382,50.837921],"type":"Point"}
}