{
  "type": "Feature",
  "properties": {
    "addr:full":"Henegouwerweg 26 Waddinxveen Zuid-Holland 2741 KS",
    "addr:housenumber":"26",
    "addr:postcode":"2741 ks",
    "addr:street":"Henegouwerweg",
    "iso:country":"NL",
    "sg:address":"Henegouwerweg 26",
    "sg:city":"Waddinxveen",
    "sg:orig_category":"Bouwmaterialen Gh",
    "sg:phone":"+31 172 213 200",
    "sg:postcode":"2741 KS",
    "sg:province":"Zuid-Holland",
    "wof:name":"Betonfabriek Roggeveen Bv",
    "wof:placetype":"venue"
},
  "geometry": {"coordinates":[4.660341,52.043613],"type":"Point"}
}