{
  "type": "Feature",
  "properties": {
    "iso:country":"NL",
    "sg:address":"Woudhoek 1",
    "sg:city":"Nibbixwoud",
    "sg:orig_category":"Elektrotechnische Installatiebureaus",
    "sg:phone":"+31 6 12905413",
    "sg:postcode":"1688 CX",
    "sg:province":"Noord-Holland",
    "wof:name":"Blauw & Koopman",
    "wof:placetype":"venue"
},
  "geometry": {"coordinates":[5.056521,52.694138],"type":"Point"}
}