{
  "type": "Feature",
  "properties": {
    "addr:full":"Oude Velperwg 50 Arnhem Gelderland 6824 HE",
    "addr:housenumber":"50",
    "addr:postcode":"6824 he",
    "addr:street":"Oude Velperwg",
    "iso:country":"NL",
    "sg:address":"Oude Velperwg 50",
    "sg:city":"Arnhem",
    "sg:orig_category":"Adviesbureaus Bouwkunde",
    "sg:phone":"+31 26 361 7817",
    "sg:postcode":"6824 HE",
    "sg:province":"Gelderland",
    "wof:name":"Damen",
    "wof:placetype":"venue"
},
  "geometry": {"coordinates":[5.9394,51.989079],"type":"Point"}
}