{
  "type": "Feature",
  "properties": {
    "addr:full":"Rietnesse 2 Amsterdam North Holland 1082 CE",
    "addr:housenumber":"2",
    "addr:postcode":"1082 ce",
    "addr:street":"Rietnesse",
    "iso:country":"NL",
    "sg:address":"Rietnesse 2",
    "sg:city":"Amsterdam",
    "sg:orig_category":"Fruit And Groenten Gh",
    "sg:phone":"+31 20 646 0598",
    "sg:postcode":"1082 CE",
    "sg:province":"North Holland",
    "wof:name":"J H Ruyken",
    "wof:placetype":"venue"
},
  "geometry": {"coordinates":[4.878163,52.32616],"type":"Point"}
}