{
  "type": "Feature",
  "properties": {
    "addr:full":"De Hartogstraat 52 Valburg Gelderland 6675 AT",
    "addr:housenumber":"52",
    "addr:postcode":"6675",
    "addr:street":"De Hartogstraat;Gelderland",
    "iso:country":"NL",
    "sg:address":"De Hartogstraat 52",
    "sg:city":"Valburg",
    "sg:orig_category":"Binnenhuisarchitecten",
    "sg:phone":"+31 488 431 486",
    "sg:postcode":"6675 AT",
    "sg:province":"Gelderland",
    "wof:name":"E.J. Rijzewijk",
    "wof:placetype":"venue"
},
  "geometry": {"coordinates":[5.791124,51.913136],"type":"Point"}
}