{
  "type": "Feature",
  "properties": {
    "addr:full":"De Run 2174 Veldhoven Noord-Brabant 5503 LE",
    "addr:housenumber":"2174",
    "addr:postcode":"5503 le",
    "addr:street":"De Run",
    "iso:country":"NL",
    "sg:address":"De Run 2174",
    "sg:city":"Veldhoven",
    "sg:orig_category":"Opslag Inboedels",
    "sg:phone":"+31 800 6064",
    "sg:postcode":"5503 LE",
    "sg:province":"Noord-Brabant",
    "sg:website":"http://www.shurgard.nl",
    "wof:name":"Shurgard Veldhoven",
    "wof:placetype":"venue"
},
  "geometry": {"coordinates":[5.4254398346,51.4161186218],"type":"Point"}
}