{
  "type": "Feature",
  "properties": {
    "addr:full":"Dunantdreef 43 Maassluis Zuid-Holland 3146 VB",
    "addr:housenumber":"43",
    "addr:postcode":"3146 vb",
    "addr:street":"Dunantdreef",
    "iso:country":"NL",
    "sg:address":"Dunantdreef 43",
    "sg:city":"Maassluis",
    "sg:orig_category":"Muziekdrukkerijen En -Uitgeverijen",
    "sg:phone":"+31 10 592 7755",
    "sg:postcode":"3146 VB",
    "sg:province":"Zuid-Holland",
    "wof:name":"Musicscore",
    "wof:placetype":"venue"
},
  "geometry": {"coordinates":[4.22522,51.937096],"type":"Point"}
}