{
  "type": "Feature",
  "properties": {
    "addr:full":"Schiedamsewg 193/B Rotterdam Zuid-Holland 3026 AM",
    "addr:housenumber":"193 / b",
    "addr:postcode":"3026",
    "iso:country":"NL",
    "sg:address":"Schiedamsewg 193/B",
    "sg:city":"Rotterdam",
    "sg:orig_category":"Opticiens",
    "sg:phone":"+31 10 462 4197",
    "sg:postcode":"3026 AM",
    "sg:province":"Zuid-Holland",
    "wof:name":"Optica",
    "wof:placetype":"venue"
},
  "geometry": {"coordinates":[4.4386401176,51.9117774963],"type":"Point"}
}