{
  "type": "Feature",
  "properties": {
    "addr:full":"Schieweg 89 Delft South Holland 2627 AT",
    "addr:housenumber":"89",
    "addr:postcode":"2627",
    "addr:street":"Schieweg",
    "iso:country":"NL",
    "sg:address":"Schieweg 89",
    "sg:city":"Delft",
    "sg:orig_category":"Meubelzaken, Woning- And Keukeninrichting",
    "sg:phone":"+31 15 256 1762",
    "sg:postcode":"2627 AT",
    "sg:province":"South Holland",
    "wof:name":"Slaapkamercentrum",
    "wof:placetype":"venue"
},
  "geometry": {"coordinates":[4.372241,51.98296],"type":"Point"}
}