{
  "type": "Feature",
  "properties": {
    "iso:country":"NL",
    "sg:address":"J Hilgerswg 2",
    "sg:city":"Eindhoven",
    "sg:orig_category":"Luchthavens En Vliegvelden",
    "sg:phone":"+31 40 251 6142",
    "sg:postcode":"5657 ES",
    "sg:province":"Noord-Brabant",
    "wof:name":"Eindhoven Handling Bv",
    "wof:placetype":"venue"
},
  "geometry": {"coordinates":[5.388862,51.453896],"type":"Point"}
}