{
  "type": "Feature",
  "properties": {
    "addr:full":"Mozartln 334 Maassluis South Holland 3144 NH",
    "addr:housenumber":"334",
    "addr:postcode":"3144 nh",
    "iso:country":"NL",
    "sg:address":"Mozartln 334",
    "sg:city":"Maassluis",
    "sg:orig_category":"Keukens",
    "sg:phone":"+31 10 592 0200",
    "sg:postcode":"3144 NH",
    "sg:province":"South Holland",
    "wof:name":"Siematic Bv",
    "wof:placetype":"venue"
},
  "geometry": {"coordinates":[4.251202,51.924381],"type":"Point"}
}