{
  "type": "Feature",
  "properties": {
    "addr:full":"Van Vollenhovenstraat 23 Rotterdam South Holland 3016 BG",
    "addr:housenumber":"23",
    "addr:postcode":"3016",
    "addr:street":"Van Vollenhovenstraat",
    "iso:country":"NL",
    "sg:address":"Van Vollenhovenstraat 23",
    "sg:city":"Rotterdam",
    "sg:orig_category":"Verzekeringen",
    "sg:phone":"+31 10 436 0455",
    "sg:postcode":"3016 BG",
    "sg:province":"South Holland",
    "wof:name":"Adriaanse Assurantie",
    "wof:placetype":"venue"
},
  "geometry": {"coordinates":[4.4782738686,51.9095306396],"type":"Point"}
}