{
  "type": "Feature",
  "properties": {
    "iso:country":"NL",
    "sg:address":"Bourgondischelaan 23",
    "sg:city":"Ridderkerk",
    "sg:orig_category":"Overheidsdiensten",
    "sg:phone":"+31 180 415 541",
    "sg:postcode":"2983 SH",
    "sg:province":"Zuid-Holland",
    "wof:name":"De Dukdalf",
    "wof:placetype":"venue"
},
  "geometry": {"coordinates":[4.6087789536,51.8885803223],"type":"Point"}
}