{
  "type": "Feature",
  "properties": {
    "addr:full":"Postbus 65 Harderwijk Gelderland 3840 AB",
    "addr:housenumber":"65",
    "addr:postcode":"3840 ab",
    "addr:street":"Postbus;Gelderland",
    "iso:country":"NL",
    "sg:address":"Postbus 65",
    "sg:city":"Harderwijk",
    "sg:orig_category":"Verenigingen En Stichtingen",
    "sg:phone":"+31 341 564 488",
    "sg:postcode":"3840 AB",
    "sg:province":"Gelderland",
    "wof:name":"M A F Zendingsvliegers",
    "wof:placetype":"venue"
},
  "geometry": {"coordinates":[5.617184,52.347042],"type":"Point"}
}