{
  "type": "Feature",
  "properties": {
    "iso:country":"NL",
    "sg:address":"Oosthavendam 8",
    "sg:city":"Breskens",
    "sg:orig_category":"Werving And Selectie Van Tijdelijk Personeel And Uitzendkantoren",
    "sg:phone":"+31 117 383 389",
    "sg:postcode":"4511 AZ",
    "sg:province":"Zeeland",
    "wof:name":"Pensa Personeelsdiensten",
    "wof:placetype":"venue"
},
  "geometry": {"coordinates":[3.5707640648,51.3945541382],"type":"Point"}
}