{
  "type": "Feature",
  "properties": {
    "addr:full":"Esrein 9 Hengelo Ov NL.08 7553 CX",
    "addr:housenumber":"9",
    "addr:postcode":"7553 cx",
    "addr:street":"Esrein;Ov",
    "iso:country":"NL",
    "sg:address":"Esrein 9",
    "sg:city":"Hengelo Ov",
    "sg:orig_category":"Balletscholen",
    "sg:phone":"+31 74 291 7597",
    "sg:postcode":"7553 CX",
    "sg:province":"NL.08",
    "wof:name":"Crea Centrum Voor Kunsteducatie",
    "wof:placetype":"venue"
},
  "geometry": {"coordinates":[6.789164,52.25679],"type":"Point"}
}