{
  "type": "Feature",
  "properties": {
    "addr:full":"Rondven 1A Maarheeze Noord-Brabant 6026 PX",
    "addr:housenumber":"1a",
    "addr:postcode":"6026 px",
    "addr:street":"Rondven",
    "iso:country":"NL",
    "sg:address":"Rondven 1A",
    "sg:city":"Maarheeze",
    "sg:orig_category":"Keukens",
    "sg:phone":"+31 6 22570198",
    "sg:postcode":"6026 PX",
    "sg:province":"Noord-Brabant",
    "wof:name":"Emmers",
    "wof:placetype":"venue"
},
  "geometry": {"coordinates":[5.631258,51.311073],"type":"Point"}
}