{
  "type": "Feature",
  "properties": {
    "addr:full":"Cleyburchstraat 55 Rotterdam Zuid-Holland 3039 DC",
    "addr:housenumber":"55",
    "addr:postcode":"3039",
    "addr:street":"Cleyburchstraat",
    "iso:country":"NL",
    "sg:address":"Cleyburchstraat 55",
    "sg:city":"Rotterdam",
    "sg:orig_category":"Metaalwerken",
    "sg:phone":"+31 6 22843408",
    "sg:postcode":"3039 DC",
    "sg:province":"Zuid-Holland",
    "wof:name":"Vincent",
    "wof:placetype":"venue"
},
  "geometry": {"coordinates":[4.454239,51.933399],"type":"Point"}
}