{
  "type": "Feature",
  "properties": {
    "addr:full":"Reigerstraat 13 Haaksbergen NL.08 7481 AE",
    "addr:housenumber":"13;nl.08",
    "addr:postcode":"7481 ae",
    "addr:street":"Reigerstraat",
    "iso:country":"NL",
    "sg:address":"Reigerstraat 13",
    "sg:city":"Haaksbergen",
    "sg:orig_category":"Artsen And Specialisten",
    "sg:phone":"+31 53 572 2207",
    "sg:postcode":"7481 AE",
    "sg:province":"NL.08",
    "wof:name":"Huisartsenpraktijk Van Kempen En Van Der Lugt",
    "wof:placetype":"venue"
},
  "geometry": {"coordinates":[6.752601,52.165649],"type":"Point"}
}