{
  "type": "Feature",
  "properties": {
    "iso:country":"NL",
    "sg:address":"Harlingertrekweg 53-55",
    "sg:city":"Leeuwarden",
    "sg:orig_category":"Verplichte Sociale Verzekeringen",
    "sg:phone":"+31 58 291 3913",
    "sg:postcode":"8913 HR",
    "sg:province":"Provincie Friesland",
    "wof:name":"De Friesland Zorgverzekeraar",
    "wof:placetype":"venue"
},
  "geometry": {"coordinates":[5.779758,53.197872],"type":"Point"}
}