{
  "type": "Feature",
  "properties": {
    "addr:full":"Vennewaterswg 2B Heiloo Noord-Holland 1852 PT",
    "addr:housenumber":"2b",
    "addr:postcode":"1852 pt",
    "addr:street":"Vennewaterswg",
    "iso:country":"NL",
    "sg:address":"Vennewaterswg 2B",
    "sg:city":"Heiloo",
    "sg:orig_category":"Huisbrand- En Industrieolie",
    "sg:phone":"+31 72 531 1311",
    "sg:postcode":"1852 PT",
    "sg:province":"Noord-Holland",
    "sg:website":"http://www.gpgroot.nl",
    "wof:name":"Boha",
    "wof:placetype":"venue"
},
  "geometry": {"coordinates":[4.68492,52.59285],"type":"Point"}
}