{
  "type": "Feature",
  "properties": {
    "addr:full":"Dr W Vd Horstln 42 Pynacker Zuid-Holland 2641 RW",
    "addr:housenumber":"42",
    "addr:postcode":"2641 rw",
    "addr:street":"Dr W Vd Horstln",
    "iso:country":"NL",
    "sg:address":"Dr W Vd Horstln 42",
    "sg:city":"Pynacker",
    "sg:orig_category":"Homeopathie",
    "sg:phone":"+31 15 369 4282",
    "sg:postcode":"2641 RW",
    "sg:province":"Zuid-Holland",
    "wof:name":"Koeppen, H",
    "wof:placetype":"venue"
},
  "geometry": {"coordinates":[4.425071,51.987968],"type":"Point"}
}