{
  "type": "Feature",
  "properties": {
    "addr:full":"Wilhelminalaan 14 Veghel Noord-Brabant 5462 GS",
    "addr:housenumber":"14",
    "addr:postcode":"5462 gs",
    "addr:street":"Wilhelminalaan",
    "iso:country":"NL",
    "sg:address":"Wilhelminalaan 14",
    "sg:city":"Veghel",
    "sg:classifiers":[
        {
            "category":"Fast Food",
            "type":"Food & Drink"
        }
    ],
    "sg:phone":"+31 413 343 780",
    "sg:postcode":"5462 GS",
    "sg:province":"Noord-Brabant",
    "sg:tags":[
        "afhaal",
        "restaurant"
    ],
    "wof:name":"Snackbar Oranjewijk",
    "wof:placetype":"venue"
},
  "geometry": {"coordinates":[5.533543,51.617722],"type":"Point"}
}