{
  "type": "Feature",
  "properties": {
    "addr:full":"Kralingseweg 463 Rotterdam South Holland 3065 RG",
    "addr:housenumber":"463",
    "addr:postcode":"3065 rg",
    "addr:street":"Kralingseweg",
    "iso:country":"NL",
    "sg:address":"Kralingseweg 463",
    "sg:city":"Rotterdam",
    "sg:orig_category":"Kinderopvang Behalve Thuis",
    "sg:phone":"+31 10 202 3044",
    "sg:postcode":"3065 RG",
    "sg:province":"South Holland",
    "wof:name":"De Kleine Plantage",
    "wof:placetype":"venue"
},
  "geometry": {"coordinates":[4.564189,51.931934],"type":"Point"}
}