{
  "type": "Feature",
  "properties": {
    "addr:full":"Diepenbrocklaan 41 Losser Overijssel 7582 CX",
    "addr:housenumber":"41",
    "addr:postcode":"7582 cx",
    "addr:street":"Diepenbrocklaan",
    "iso:country":"NL",
    "sg:address":"Diepenbrocklaan 41",
    "sg:city":"Losser",
    "sg:orig_category":"Artistiek Onderwijs",
    "sg:phone":"+31 53 538 1309",
    "sg:postcode":"7582 CX",
    "sg:province":"Overijssel",
    "wof:name":"Dans- En Muziekcentrum De Sleutel",
    "wof:placetype":"venue"
},
  "geometry": {"coordinates":[7.001265,52.260006],"type":"Point"}
}