{
  "type": "Feature",
  "properties": {
    "addr:full":"Lagedykerwg 34 Schagen Noord-Holland 1742 NC",
    "addr:housenumber":"34",
    "addr:postcode":"1742 nc",
    "addr:street":"Lagedykerwg",
    "iso:country":"NL",
    "sg:address":"Lagedykerwg 34",
    "sg:city":"Schagen",
    "sg:orig_category":"Onderhoudswerken",
    "sg:phone":"+31 224 296 706",
    "sg:postcode":"1742 NC",
    "sg:province":"Noord-Holland",
    "wof:name":"Timmer, R S",
    "wof:placetype":"venue"
},
  "geometry": {"coordinates":[4.777948,52.794437],"type":"Point"}
}