{
  "type": "Feature",
  "properties": {
    "addr:full":"Van Knobelsdorffplein 2 Drachten Friesland 9203 DJ",
    "addr:housenumber":"2",
    "addr:postcode":"9203 dj",
    "addr:street":"Van Knobelsdorffplein",
    "iso:country":"NL",
    "sg:address":"Van Knobelsdorffplein 2",
    "sg:city":"Drachten",
    "sg:orig_category":"Werving And Selectie Van Tijdelijk Personeel And Uitzendkantoren",
    "sg:phone":"+31 512 532 483",
    "sg:postcode":"9203 DJ",
    "sg:province":"Friesland",
    "wof:name":"Start",
    "wof:placetype":"venue"
},
  "geometry": {"coordinates":[6.0987172127,53.1036453247],"type":"Point"}
}