{
  "type": "Feature",
  "properties": {
    "addr:full":"Mercatorwg 50 Hoek Van Holland Zuid-Holland 3151 CJ",
    "addr:housenumber":"50",
    "addr:postcode":"3151 cj",
    "addr:street":"Mercatorwg",
    "iso:country":"NL",
    "sg:address":"Mercatorwg 50",
    "sg:city":"Hoek Van Holland",
    "sg:orig_category":"Bibliotheken En Leeszalen Openbare",
    "sg:phone":"+31 174 382 551",
    "sg:postcode":"3151 CJ",
    "sg:province":"Zuid-Holland",
    "sg:website":"http://www.bibliotheek.rotterdam.nl",
    "wof:name":"Bibliotheek Rotterdam",
    "wof:placetype":"venue"
},
  "geometry": {"coordinates":[4.136922,51.977272],"type":"Point"}
}