{
  "type": "Feature",
  "properties": {
    "iso:country":"NL",
    "sg:address":"Gipskruidweg 16",
    "sg:city":"Almere",
    "sg:orig_category":"Biljart- And Snookerzalen",
    "sg:phone":"+31 36 533 1168",
    "sg:postcode":"1313 CT",
    "sg:province":"Flevoland",
    "wof:name":"Mini-Soccer",
    "wof:placetype":"venue"
},
  "geometry": {"coordinates":[5.203072,52.383026],"type":"Point"}
}