{
  "type": "Feature",
  "properties": {
    "addr:full":"Marktpln 11 Apeldoorn Gelderland 7311 LJ",
    "addr:housenumber":"11;lj",
    "addr:postcode":"7311",
    "addr:street":"Marktpln;Gelderland",
    "iso:country":"NL",
    "sg:address":"Marktpln 11",
    "sg:city":"Apeldoorn",
    "sg:orig_category":"Kamerverhuur En -Bemiddeling",
    "sg:phone":"+31 55 521 3990",
    "sg:postcode":"7311 LJ",
    "sg:province":"Gelderland",
    "wof:name":"Poort Van Kleef, De",
    "wof:placetype":"venue"
},
  "geometry": {"coordinates":[5.9627118111,52.2153892517],"type":"Point"}
}