{
  "type": "Feature",
  "properties": {
    "iso:country":"NL",
    "sg:address":"Rustenburgstraat 1",
    "sg:city":"Apeldoorn",
    "sg:orig_category":"Elektronische Bedrijfsinstallaties",
    "sg:phone":"+31 55 581 3100",
    "sg:postcode":"7311 JA",
    "sg:province":"Gelderland",
    "wof:name":"Verzekeraarshulpdienst Bv",
    "wof:placetype":"venue"
},
  "geometry": {"coordinates":[5.960714,52.211395],"type":"Point"}
}