{
  "type": "Feature",
  "properties": {
    "iso:country":"NL",
    "sg:address":"Verseputsewg 11",
    "sg:city":"Kerkwerve",
    "sg:orig_category":"Loonbedrijven",
    "sg:phone":"+31 111 414 908",
    "sg:postcode":"4321 TC",
    "sg:province":"Zeeland",
    "wof:name":"Leeuwen, Fa Van",
    "wof:placetype":"venue"
},
  "geometry": {"coordinates":[3.876127,51.678329],"type":"Point"}
}