{
  "type": "Feature",
  "properties": {
    "iso:country":"NL",
    "sg:address":"Beekbergerwg 46",
    "sg:city":"Loenen Gld",
    "sg:orig_category":"Makelaars En Adviseurs Onroerende Goederen",
    "sg:phone":"+31 55 505 0933",
    "sg:postcode":"7371 EW",
    "sg:province":"Gelderland",
    "wof:name":"Heesch/De Schansenberg, De",
    "wof:placetype":"venue"
},
  "geometry": {"coordinates":[6.008974,52.128605],"type":"Point"}
}