{
  "type": "Feature",
  "properties": {
    "addr:full":"Postbus 20 Weerselo NL.08 7595 ZG",
    "addr:housenumber":"20;nl.08",
    "addr:postcode":"7595 zg",
    "addr:street":"Postbus",
    "iso:country":"NL",
    "sg:address":"Postbus 20",
    "sg:city":"Weerselo",
    "sg:orig_category":"Woningbouw- Verenigingen En -Stichtingen",
    "sg:phone":"+31 541 661 695",
    "sg:postcode":"7595 ZG",
    "sg:province":"NL.08",
    "wof:name":"Joseph, St",
    "wof:placetype":"venue"
},
  "geometry": {"coordinates":[6.8574299812,52.3519134521],"type":"Point"}
}