{
  "type": "Feature",
  "properties": {
    "addr:full":"Markt 15 Velden Limburg 5941 GA",
    "addr:housenumber":"15",
    "addr:postcode":"5941 ga",
    "addr:street":"Markt",
    "iso:country":"NL",
    "sg:address":"Markt 15",
    "sg:city":"Velden",
    "sg:classifiers":[
        {
            "category":"Food & Beverages",
            "subcategory":"Fruits & Vegetables",
            "type":"Retail Goods"
        }
    ],
    "sg:phone":"+31 77 472 2792",
    "sg:postcode":"5941 GA",
    "sg:province":"Limburg",
    "sg:tags":[
        "groenten"
    ],
    "wof:name":"Groente- En Fruit Spec. De Mert",
    "wof:placetype":"venue"
},
  "geometry": {"coordinates":[6.165529,51.414616],"type":"Point"}
}