{
  "type": "Feature",
  "properties": {
    "addr:full":"Bijster 11 Breda Noord-Brabant 4817 HZ",
    "addr:housenumber":"11",
    "addr:postcode":"4817 hz",
    "addr:street":"Bijster",
    "iso:country":"NL",
    "sg:address":"Bijster 11",
    "sg:city":"Breda",
    "sg:orig_category":"Onderhoud And Reparatie Kantoorapparatuur",
    "sg:phone":"+31 76 531 8585",
    "sg:postcode":"4817 HZ",
    "sg:province":"Noord-Brabant",
    "wof:name":"Euromoss Bv",
    "wof:placetype":"venue"
},
  "geometry": {"coordinates":[4.803684,51.583466],"type":"Point"}
}