{
  "type": "Feature",
  "properties": {
    "addr:full":"Hoogstr 38A Rotterdam Zuid-Holland 3011 PR",
    "addr:housenumber":"38a",
    "addr:postcode":"3011 pr",
    "addr:street":"Hoogstr",
    "iso:country":"NL",
    "sg:address":"Hoogstr 38A",
    "sg:city":"Rotterdam",
    "sg:orig_category":"Geluidsinstallaties - Accessoires En Onderdelen",
    "sg:phone":"+31 10 220 0500",
    "sg:postcode":"3011 PR",
    "sg:province":"Zuid-Holland",
    "wof:name":"Audioforce",
    "wof:placetype":"venue"
},
  "geometry": {"coordinates":[4.494822,51.923092],"type":"Point"}
}