{
  "type": "Feature",
  "properties": {
    "addr:full":"Hogestr 50 Tiel Gelderland 4001 EX",
    "addr:housenumber":"50",
    "addr:postcode":"4001 ex",
    "addr:street":"Hogestr;Gelderland",
    "iso:country":"NL",
    "sg:address":"Hogestr 50",
    "sg:city":"Tiel",
    "sg:orig_category":"Fitnesscentra",
    "sg:phone":"+31 344 612 223",
    "sg:postcode":"4001 EX",
    "sg:province":"Gelderland",
    "sg:website":"http://www.voigtsport.nl",
    "wof:name":"Voigt Bv",
    "wof:placetype":"venue"
},
  "geometry": {"coordinates":[5.430696,51.888096],"type":"Point"}
}