{
  "type": "Feature",
  "properties": {
    "iso:country":"NL",
    "sg:address":"Noorderuitwg 42",
    "sg:city":"Wydenes",
    "sg:orig_category":"Kampeerauto'S",
    "sg:phone":"+31 229 503 181",
    "sg:postcode":"1608 EB",
    "sg:province":"Noord-Holland",
    "wof:name":"Camper Share",
    "wof:placetype":"venue"
},
  "geometry": {"coordinates":[5.1604971886,52.6449050903],"type":"Point"}
}