{
  "type": "Feature",
  "properties": {
    "addr:full":"Kazernestr 17 Deventer NL.08 7417 DG",
    "addr:housenumber":"17;nl.08",
    "addr:postcode":"7417 dg",
    "addr:street":"Kazernestr",
    "iso:country":"NL",
    "sg:address":"Kazernestr 17",
    "sg:city":"Deventer",
    "sg:orig_category":"Kappers",
    "sg:phone":"+31 570 632 168",
    "sg:postcode":"7417 DG",
    "sg:province":"NL.08",
    "wof:name":"Hair-Fantasy",
    "wof:placetype":"venue"
},
  "geometry": {"coordinates":[6.1679677963,52.2525672913],"type":"Point"}
}