{
  "type": "Feature",
  "properties": {
    "iso:country":"NL",
    "sg:address":"Havendk 545",
    "sg:city":"Schiedam",
    "sg:orig_category":"Accountants - Administratie- Consulenten En -Kantoren",
    "sg:phone":"+31 10 426 9400",
    "sg:postcode":"3114 EL",
    "sg:province":"Zuid-Holland",
    "sg:website":"http://www.beslis.nu/vdzant",
    "wof:name":"Zant, Van Der",
    "wof:placetype":"venue"
},
  "geometry": {"coordinates":[4.401074,51.903183],"type":"Point"}
}