{
  "type": "Feature",
  "properties": {
    "iso:country":"NL",
    "sg:address":"Burgstr 22",
    "sg:city":"Giessen",
    "sg:orig_category":"Administratie- En Boekhoudkantoren",
    "sg:phone":"+31 183 443 333",
    "sg:postcode":"4283 GG",
    "sg:province":"Noord-Brabant",
    "wof:name":"Heus-Mostert, De",
    "wof:placetype":"venue"
},
  "geometry": {"coordinates":[5.032864,51.791103],"type":"Point"}
}