{
  "type": "Feature",
  "properties": {
    "addr:full":"Pannekoekstraat 14A Rotterdam Zuid-Holland 3011 LE",
    "addr:housenumber":"14a",
    "addr:postcode":"3011 le",
    "addr:street":"Pannekoekstraat",
    "iso:country":"NL",
    "sg:address":"Pannekoekstraat 14A",
    "sg:city":"Rotterdam",
    "sg:orig_category":"Bloemen And Planten",
    "sg:phone":"+31 10 414 7816",
    "sg:postcode":"3011 LE",
    "sg:province":"Zuid-Holland",
    "wof:name":"Rosa Rosa Bloemen, Fleurs, Flowers",
    "wof:placetype":"venue"
},
  "geometry": {"coordinates":[4.486875,51.923901],"type":"Point"}
}