{
  "type": "Feature",
  "properties": {
    "addr:full":"Peizerwg 1 Bunne Drenthe 9496 PC",
    "addr:housenumber":"1",
    "addr:postcode":"9496 pc",
    "addr:street":"Peizerwg",
    "iso:country":"NL",
    "sg:address":"Peizerwg 1",
    "sg:city":"Bunne",
    "sg:orig_category":"Boten",
    "sg:phone":"+31 50 309 4871",
    "sg:postcode":"9496 PC",
    "sg:province":"Drenthe",
    "wof:name":"Nijdam, Roel",
    "wof:placetype":"venue"
},
  "geometry": {"coordinates":[6.533779,53.118294],"type":"Point"}
}