{
  "type": "Feature",
  "properties": {
    "iso:country":"NL",
    "sg:address":"Lg Bothofstr 312",
    "sg:city":"Enschede",
    "sg:orig_category":"Kermisexploitatie",
    "sg:phone":"+31 53 430 2665",
    "sg:postcode":"7533 AT",
    "sg:province":"NL.08",
    "wof:name":"Heuvel-De Voer, A M Van De",
    "wof:placetype":"venue"
},
  "geometry": {"coordinates":[6.914254,52.223896],"type":"Point"}
}