{
  "type": "Feature",
  "properties": {
    "iso:country":"NL",
    "sg:address":"Aalsmeerderweg 289",
    "sg:city":"Aalsmeer",
    "sg:orig_category":"Beautyfarms And Sauna'S",
    "sg:phone":"+31 297 346 624",
    "sg:postcode":"1432 CN",
    "sg:province":"Noord-Holland",
    "wof:name":"Zonnestudio Holiday",
    "wof:placetype":"venue"
},
  "geometry": {"coordinates":[4.798722,52.281094],"type":"Point"}
}