{
  "type": "Feature",
  "properties": {
    "addr:full":"Markt 44 Geertruidenberg Noord-Brabant 4931 BT",
    "addr:housenumber":"44",
    "addr:postcode":"4931 bt",
    "addr:street":"Markt",
    "iso:country":"NL",
    "sg:address":"Markt 44",
    "sg:city":"Geertruidenberg",
    "sg:orig_category":"Antiekzaken",
    "sg:phone":"+31 162 513 779",
    "sg:postcode":"4931 BT",
    "sg:province":"Noord-Brabant",
    "wof:name":"Elck Syn Sin",
    "wof:placetype":"venue"
},
  "geometry": {"coordinates":[4.860164,51.700634],"type":"Point"}
}