{
  "type": "Feature",
  "properties": {
    "addr:full":"Noorddammerlaan 44 A Amstelveen Noord-Holland 1187 DA",
    "addr:housenumber":"44 a",
    "addr:postcode":"1187 da",
    "addr:street":"Noorddammerlaan",
    "iso:country":"NL",
    "sg:address":"Noorddammerlaan 44 A",
    "sg:city":"Amstelveen",
    "sg:orig_category":"Kappers",
    "sg:phone":"+31 20 641 3829",
    "sg:postcode":"1187 DA",
    "sg:province":"Noord-Holland",
    "wof:name":"Hairstyling Dorion",
    "wof:placetype":"venue"
},
  "geometry": {"coordinates":[4.83934021,52.2925491333],"type":"Point"}
}