{
  "type": "Feature",
  "properties": {
    "iso:country":"NL",
    "sg:address":"Spoorln 2B",
    "sg:city":"Bodegraven",
    "sg:classifiers":[
        {
            "category":"Professional",
            "subcategory":"Accounting & Tax Preparation",
            "type":"Services"
        }
    ],
    "sg:phone":"+31 172 619 317",
    "sg:postcode":"2411 ER",
    "sg:province":"Zuid-Holland",
    "sg:tags":[
        "accountant",
        "en",
        "-kantoren",
        "register-"
    ],
    "sg:website":"http://www.acountanstadviescombinatie.nl",
    "wof:name":"Accountants Advies Combinatie",
    "wof:placetype":"venue"
},
  "geometry": {"coordinates":[4.747547,52.085552],"type":"Point"}
}