{
  "type": "Feature",
  "properties": {
    "addr:full":"Heerlerweg 129 Voerendaal Limburg 6367 AC",
    "addr:housenumber":"129",
    "addr:postcode":"6367 ac",
    "addr:street":"Heerlerweg",
    "iso:country":"NL",
    "sg:address":"Heerlerweg 129",
    "sg:city":"Voerendaal",
    "sg:orig_category":"Autokeuringen",
    "sg:phone":"+31 45 575 1397",
    "sg:postcode":"6367 AC",
    "sg:province":"Limburg",
    "wof:name":"Shell",
    "wof:placetype":"venue"
},
  "geometry": {"coordinates":[5.944928,50.876003],"type":"Point"}
}