{
  "type": "Feature",
  "properties": {
    "addr:full":"Oude Hoofdv Wg 23 Assen Provincie Drenthe 9405 CA",
    "addr:housenumber":"23",
    "addr:postcode":"9405 ca",
    "addr:street":"Oude;Wg;Provincie Drenthe",
    "iso:country":"NL",
    "sg:address":"Oude Hoofdv Wg 23",
    "sg:city":"Assen",
    "sg:orig_category":"Zonweringen",
    "sg:phone":"+31 6 55987534",
    "sg:postcode":"9405 CA",
    "sg:province":"Provincie Drenthe",
    "wof:name":"J&J, Klussen- En Montagebedrijf",
    "wof:placetype":"venue"
},
  "geometry": {"coordinates":[6.535071,52.995899],"type":"Point"}
}