{
  "type": "Feature",
  "properties": {
    "addr:full":"Esbeeksedijk 4 Diessen North Brabant 5087 TG",
    "addr:housenumber":"4",
    "addr:postcode":"5087 tg",
    "addr:street":"Esbeeksedijk",
    "iso:country":"NL",
    "sg:address":"Esbeeksedijk 4",
    "sg:city":"Diessen",
    "sg:orig_category":"Vakantieverblijven",
    "sg:phone":"+31 13 504 1473",
    "sg:postcode":"5087 TG",
    "sg:province":"North Brabant",
    "sg:website":"http://www.elshorst.nl",
    "wof:name":"Elshorst, Groepsaccom",
    "wof:placetype":"venue"
},
  "geometry": {"coordinates":[5.172352,51.45723],"type":"Point"}
}