{
  "type": "Feature",
  "properties": {
    "iso:country":"NL",
    "sg:address":"De Korf 6",
    "sg:city":"Krimpen Ad Yssel",
    "sg:orig_category":"Kappers",
    "sg:phone":"+31 180 519 134",
    "sg:postcode":"2924 AH",
    "sg:province":"Zuid-Holland",
    "wof:name":"Dixalon",
    "wof:placetype":"venue"
},
  "geometry": {"coordinates":[4.6096711159,51.9225273132],"type":"Point"}
}