{
  "type": "Feature",
  "properties": {
    "addr:full":"Akerstr N 121 Heerlen Limburg 6413 JD",
    "addr:housenumber":"121",
    "addr:postcode":"6413 jd",
    "addr:street":"N",
    "iso:country":"NL",
    "sg:address":"Akerstr N 121",
    "sg:city":"Heerlen",
    "sg:orig_category":"Administratie- En Boekhoudkantoren",
    "sg:phone":"+31 45 563 0301",
    "sg:postcode":"6413 JD",
    "sg:province":"Limburg",
    "sg:website":"http://www.profus.nl",
    "wof:name":"Profus",
    "wof:placetype":"venue"
},
  "geometry": {"coordinates":[5.944974,50.922146],"type":"Point"}
}