{
  "type": "Feature",
  "properties": {
    "iso:country":"NL",
    "sg:address":"Hoffmannstr 36",
    "sg:city":"Zwolle",
    "sg:orig_category":"Galeries",
    "sg:phone":"+31 38 421 9863",
    "sg:postcode":"8031 PH",
    "sg:province":"Overijssel",
    "sg:website":"http://www.beeldendekunstenaar.com",
    "wof:name":"Hoffmann",
    "wof:placetype":"venue"
},
  "geometry": {"coordinates":[6.080173,52.522087],"type":"Point"}
}