{
  "type": "Feature",
  "properties": {
    "iso:country":"NL",
    "sg:address":"D Ben Goerionstr 19",
    "sg:city":"Utrecht",
    "sg:orig_category":"Adviesbureaus Bedrijfsorganisatie",
    "sg:phone":"+31 30 271 6583",
    "sg:postcode":"3573 XL",
    "sg:province":"Utrecht",
    "wof:name":"Mees",
    "wof:placetype":"venue"
},
  "geometry": {"coordinates":[5.146897,52.113453],"type":"Point"}
}