{
  "type": "Feature",
  "properties": {
    "addr:full":"Vuurdoornln 20 Ridderkerk Zuid-Holland 2982 BZ",
    "addr:housenumber":"20",
    "addr:postcode":"2982 bz",
    "addr:street":"Vuurdoornln",
    "iso:country":"NL",
    "sg:address":"Vuurdoornln 20",
    "sg:city":"Ridderkerk",
    "sg:orig_category":"Verzekeringen - Verzekeringskantoren",
    "sg:phone":"+31 180 411 911",
    "sg:postcode":"2982 BZ",
    "sg:province":"Zuid-Holland",
    "wof:name":"Kop Bv, W",
    "wof:placetype":"venue"
},
  "geometry": {"coordinates":[4.587903,51.871799],"type":"Point"}
}