{
  "type": "Feature",
  "properties": {
    "addr:full":"Hooge Berkt 31 Bergeyk Noord-Brabant 5571 TG",
    "addr:housenumber":"31",
    "addr:postcode":"5571 tg",
    "addr:street":"Hooge Berkt",
    "iso:country":"NL",
    "sg:address":"Hooge Berkt 31",
    "sg:city":"Bergeyk",
    "sg:orig_category":"Loodgieterswerk, Verwarming And Sanitaire Installaties",
    "sg:phone":"+31 497 571 237",
    "sg:postcode":"5571 TG",
    "sg:province":"Noord-Brabant",
    "wof:name":"C.G.A.M. Bogaerts",
    "wof:placetype":"venue"
},
  "geometry": {"coordinates":[5.337223,51.326771],"type":"Point"}
}