{
  "type": "Feature",
  "properties": {
    "iso:country":"NL",
    "sg:address":"Kerkwg 113",
    "sg:city":"Ouderkerk Ad Yssel",
    "sg:orig_category":"Heiwerken En Funderingstechniek",
    "sg:phone":"+31 180 682 373",
    "sg:postcode":"2935 AH",
    "sg:province":"South Holland",
    "wof:name":"Boere, T",
    "wof:placetype":"venue"
},
  "geometry": {"coordinates":[4.641491,51.930344],"type":"Point"}
}