{
  "type": "Feature",
  "properties": {
    "addr:full":"Burg De Vlugtln 158 Amsterdam Noord-Holland 1063 BS",
    "addr:housenumber":"158",
    "addr:postcode":"1063 bs",
    "iso:country":"NL",
    "sg:address":"Burg De Vlugtln 158",
    "sg:city":"Amsterdam",
    "sg:orig_category":"Herenkleding",
    "sg:phone":"+31 20 613 1671",
    "sg:postcode":"1063 BS",
    "sg:province":"Noord-Holland",
    "wof:name":"Hansh",
    "wof:placetype":"venue"
},
  "geometry": {"coordinates":[4.82559,52.3806],"type":"Point"}
}