{
  "type": "Feature",
  "properties": {
    "iso:country":"NL",
    "sg:address":"Castorstr 29",
    "sg:city":"Hilversum",
    "sg:orig_category":"Kappers",
    "sg:phone":"+31 35 685 7775",
    "sg:postcode":"1223 EW",
    "sg:province":"North Holland",
    "wof:name":"Linda",
    "wof:placetype":"venue"
},
  "geometry": {"coordinates":[5.195808,52.231922],"type":"Point"}
}