{
  "type": "Feature",
  "properties": {
    "addr:full":"Van Oldenbarneveldtstr 42 Amsterdam Noord-Holland 1052 KC",
    "addr:housenumber":"42",
    "addr:postcode":"1052 kc",
    "iso:country":"NL",
    "sg:address":"Van Oldenbarneveldtstr 42",
    "sg:city":"Amsterdam",
    "sg:orig_category":"Kinderopvang Behalve Thuis",
    "sg:phone":"+31 20 686 9721",
    "sg:postcode":"1052 KC",
    "sg:province":"Noord-Holland",
    "wof:name":"Dependance Sww",
    "wof:placetype":"venue"
},
  "geometry": {"coordinates":[4.874804,52.376171],"type":"Point"}
}