{
  "type": "Feature",
  "properties": {
    "addr:full":"Marktstr 34 Ravenstein Noord-Brabant 5371 AD",
    "addr:housenumber":"34",
    "addr:postcode":"5371 ad",
    "addr:street":"Marktstr",
    "iso:country":"NL",
    "sg:address":"Marktstr 34",
    "sg:city":"Ravenstein",
    "sg:orig_category":"Fotoreportages",
    "sg:phone":"+31 486 416 641",
    "sg:postcode":"5371 AD",
    "sg:province":"Noord-Brabant",
    "wof:name":"Maaspoort, Fotografie",
    "wof:placetype":"venue"
},
  "geometry": {"coordinates":[5.652581,51.797291],"type":"Point"}
}