{
  "type": "Feature",
  "properties": {
    "iso:country":"NL",
    "sg:address":"M Kuilerwg 49",
    "sg:city":"Hollandscheveld",
    "sg:orig_category":"Tuinaanleg En -Onderhoud",
    "sg:phone":"+31 528 352 050",
    "sg:postcode":"7913 XG",
    "sg:province":"Provincie Drenthe",
    "wof:name":"Alescon",
    "wof:placetype":"venue"
},
  "geometry": {"coordinates":[6.574487,52.701756],"type":"Point"}
}