{
  "type": "Feature",
  "properties": {
    "addr:full":"Kreek 58 Lelystad Flevoland 8212 XC",
    "addr:housenumber":"58",
    "addr:postcode":"8212 xc",
    "addr:street":"Kreek;Flevoland",
    "iso:country":"NL",
    "sg:address":"Kreek 58",
    "sg:city":"Lelystad",
    "sg:orig_category":"Loodgieterswerk, Verwarming And Sanitaire Installaties",
    "sg:phone":"+31 320 249 069",
    "sg:postcode":"8212 XC",
    "sg:province":"Flevoland",
    "wof:name":"J.H.B. Kaart",
    "wof:placetype":"venue"
},
  "geometry": {"coordinates":[5.498652,52.512436],"type":"Point"}
}