{
  "type": "Feature",
  "properties": {
    "addr:full":"Ysdans 1 Capelle Ad Yssel South Holland 2907 AZ",
    "addr:housenumber":"1",
    "addr:postcode":"2907 az",
    "addr:street":"Ysdans;Yssel",
    "iso:country":"NL",
    "sg:address":"Ysdans 1",
    "sg:city":"Capelle Ad Yssel",
    "sg:orig_category":"Accountants - Administratie- Consulenten En -Kantoren",
    "sg:phone":"+31 10 458 8533",
    "sg:postcode":"2907 AZ",
    "sg:province":"South Holland",
    "wof:name":"Kempen & Co, Van",
    "wof:placetype":"venue"
},
  "geometry": {"coordinates":[4.5846,51.923401],"type":"Point"}
}