{
  "type": "Feature",
  "properties": {
    "addr:full":"Stationspln 69A Zutphen Gelderland 7201 MH",
    "addr:housenumber":"69a",
    "addr:postcode":"7201 mh",
    "addr:street":"Stationspln;Gelderland",
    "iso:country":"NL",
    "sg:address":"Stationspln 69A",
    "sg:city":"Zutphen",
    "sg:classifiers":[
        {
            "category":"Food & Beverages",
            "subcategory":"Bakery",
            "type":"Retail Goods"
        }
    ],
    "sg:phone":"+31 575 511 175",
    "sg:postcode":"7201 MH",
    "sg:province":"Gelderland",
    "sg:tags":[
        "pizza"
    ],
    "wof:name":"Costa Smeralda",
    "wof:placetype":"venue"
},
  "geometry": {"coordinates":[6.191525,52.140202],"type":"Point"}
}