{
  "type": "Feature",
  "properties": {
    "addr:full":"Kerkbuurt 45 Westzaan Noord-Holland 1551 AC",
    "addr:housenumber":"45",
    "addr:postcode":"1551 ac",
    "addr:street":"Kerkbuurt",
    "iso:country":"NL",
    "sg:address":"Kerkbuurt 45",
    "sg:city":"Westzaan",
    "sg:orig_category":"Verzekeringen",
    "sg:phone":"+31 75 628 3286",
    "sg:postcode":"1551 AC",
    "sg:province":"Noord-Holland",
    "wof:name":"Van Renswouw Assurantien",
    "wof:placetype":"venue"
},
  "geometry": {"coordinates":[4.771221,52.464565],"type":"Point"}
}