{
  "type": "Feature",
  "properties": {
    "addr:full":"Stationspln 33 Enschede NL.08 7511 JD",
    "addr:housenumber":"33",
    "addr:postcode":"7511 jd",
    "addr:street":"Stationspln",
    "iso:country":"NL",
    "sg:address":"Stationspln 33",
    "sg:city":"Enschede",
    "sg:orig_category":"Fietsen En Bromfietsen",
    "sg:phone":"+31 53 432 2792",
    "sg:postcode":"7511 JD",
    "sg:province":"NL.08",
    "wof:name":"Bos",
    "wof:placetype":"venue"
},
  "geometry": {"coordinates":[6.89091,52.222404],"type":"Point"}
}