{
  "type": "Feature",
  "properties": {
    "addr:full":"J W Hagemanstr 26A Eibergen Gelderland 7151 AG",
    "addr:housenumber":"26a",
    "addr:postcode":"7151",
    "addr:street":"Gelderland",
    "iso:country":"NL",
    "sg:address":"J W Hagemanstr 26A",
    "sg:city":"Eibergen",
    "sg:orig_category":"Wereldwinkels",
    "sg:phone":"+31 545 474 965",
    "sg:postcode":"7151 AG",
    "sg:province":"Gelderland",
    "wof:name":"Wereldcentr",
    "wof:placetype":"venue"
},
  "geometry": {"coordinates":[6.6507167816,52.1015777588],"type":"Point"}
}