{
  "type": "Feature",
  "properties": {
    "addr:full":"Daltonstr 41B Schiedam South Holland 3112 ZC",
    "addr:housenumber":"41b",
    "addr:postcode":"3112 zc",
    "addr:street":"Daltonstr",
    "iso:country":"NL",
    "sg:address":"Daltonstr 41B",
    "sg:city":"Schiedam",
    "sg:orig_category":"Lichtreclame",
    "sg:phone":"+31 10 262 1512",
    "sg:postcode":"3112 ZC",
    "sg:province":"South Holland",
    "wof:name":"Bari",
    "wof:placetype":"venue"
},
  "geometry": {"coordinates":[4.413968,51.919441],"type":"Point"}
}