{
  "type": "Feature",
  "properties": {
    "addr:full":"Zwin 2 Ammerzoden Gelderland 5324 AW",
    "addr:housenumber":"2",
    "addr:postcode":"5324 aw",
    "addr:street":"Zwin;Gelderland",
    "iso:country":"NL",
    "sg:address":"Zwin 2",
    "sg:city":"Ammerzoden",
    "sg:orig_category":"Kantoorapparatuur Gh",
    "sg:phone":"+31 73 599 4422",
    "sg:postcode":"5324 AW",
    "sg:province":"Gelderland",
    "wof:name":"Vof Lead Ergonomics",
    "wof:placetype":"venue"
},
  "geometry": {"coordinates":[5.2232379913,51.7469139099],"type":"Point"}
}