{
  "type": "Feature",
  "properties": {
    "addr:full":"Kastanjeln 5153 Arnhem Gelderland 6828 GJ",
    "addr:housenumber":"5153",
    "addr:postcode":"6828 gj",
    "iso:country":"NL",
    "sg:address":"Kastanjeln 5153",
    "sg:city":"Arnhem",
    "sg:orig_category":"Verenigingen En Stichtingen",
    "sg:phone":"+31 26 352 3420",
    "sg:postcode":"6828 GJ",
    "sg:province":"Gelderland",
    "sg:website":"http://www.osmose.nl",
    "wof:name":"Osmose, Sticht",
    "wof:placetype":"venue"
},
  "geometry": {"coordinates":[5.91994,51.98],"type":"Point"}
}