{
  "type": "Feature",
  "properties": {
    "addr:full":"Dorpsstr 31 Leimuiden Zuid-Holland 2451 AP",
    "addr:housenumber":"31",
    "addr:postcode":"2451 ap",
    "addr:street":"Dorpsstr",
    "iso:country":"NL",
    "sg:address":"Dorpsstr 31",
    "sg:city":"Leimuiden",
    "sg:orig_category":"Banken",
    "sg:phone":"+31 71 331 9002",
    "sg:postcode":"2451 AP",
    "sg:province":"Zuid-Holland",
    "sg:website":"http://www.rabobank.nl",
    "wof:name":"Rabobank",
    "wof:placetype":"venue"
},
  "geometry": {"coordinates":[4.672393,52.222736],"type":"Point"}
}