{
  "type": "Feature",
  "properties": {
    "addr:full":"Celsiusstraat 5 Didam Gelderland 6942 RA",
    "addr:housenumber":"5",
    "addr:postcode":"6942 ra",
    "addr:street":"Celsiusstraat;Gelderland",
    "iso:country":"NL",
    "sg:address":"Celsiusstraat 5",
    "sg:city":"Didam",
    "sg:orig_category":"Metaalwerken",
    "sg:phone":"+31 316 340 740",
    "sg:postcode":"6942 RA",
    "sg:province":"Gelderland",
    "wof:name":"Constructiebedrijf Ais",
    "wof:placetype":"venue"
},
  "geometry": {"coordinates":[6.128348,51.936817],"type":"Point"}
}