{
  "type": "Feature",
  "properties": {
    "iso:country":"NL",
    "sg:address":"Venkelstraat 42",
    "sg:city":"Zierikzee",
    "sg:orig_category":"Watersport-, Sport- And Kampeerbenodigdheden Verhuur",
    "sg:phone":"+31 111 417 526",
    "sg:postcode":"4301 DB",
    "sg:province":"Zeeland",
    "wof:name":"Vrouwe Jannigje",
    "wof:placetype":"venue"
},
  "geometry": {"coordinates":[3.9205679893,51.6473693848],"type":"Point"}
}