{
  "type": "Feature",
  "properties": {
    "addr:full":"Spreeuwln 20 Bilthoven Utrecht 3722 ZA",
    "addr:housenumber":"20",
    "addr:postcode":"3722",
    "addr:street":"Spreeuwln",
    "iso:country":"NL",
    "sg:address":"Spreeuwln 20",
    "sg:city":"Bilthoven",
    "sg:orig_category":"Verenigingen En Stichtingen",
    "sg:phone":"+31 30 229 0746",
    "sg:postcode":"3722 ZA",
    "sg:province":"Utrecht",
    "wof:name":"Droit Humain Intern, Le",
    "wof:placetype":"venue"
},
  "geometry": {"coordinates":[5.21093,52.121498],"type":"Point"}
}