{
  "type": "Feature",
  "properties": {
    "iso:country":"NL",
    "sg:address":"Postbus 420",
    "sg:city":"Delft",
    "sg:orig_category":"Wijnkoperijen En -Groothandel",
    "sg:phone":"+31 15 251 1777",
    "sg:postcode":"2600 AK",
    "sg:province":"Zuid-Holland",
    "sg:website":"http://www.delcave.nl",
    "wof:name":"Delcave",
    "wof:placetype":"venue"
},
  "geometry": {"coordinates":[4.358689785,52.0115013123],"type":"Point"}
}