{
  "type": "Feature",
  "properties": {
    "iso:country":"NL",
    "sg:address":"Langvennen Oost 43",
    "sg:city":"Oisterwijk",
    "sg:orig_category":"Diverse Grafische Activiteiten",
    "sg:phone":"+31 13 521 6106",
    "sg:postcode":"5061 DK",
    "sg:province":"Noord-Brabant",
    "wof:name":"Cupido",
    "wof:placetype":"venue"
},
  "geometry": {"coordinates":[5.180171,51.582432],"type":"Point"}
}