{
  "type": "Feature",
  "properties": {
    "addr:full":"Troelstralaan 14 Sliedrecht Zuid-Holland 3362 CZ",
    "addr:housenumber":"14",
    "addr:postcode":"3362",
    "addr:street":"Troelstralaan",
    "iso:country":"NL",
    "sg:address":"Troelstralaan 14",
    "sg:city":"Sliedrecht",
    "sg:orig_category":"Vloer- And Wandbedekkingen",
    "sg:phone":"+31 184 415 780",
    "sg:postcode":"3362 CZ",
    "sg:province":"Zuid-Holland",
    "wof:name":"M C Visser",
    "wof:placetype":"venue"
},
  "geometry": {"coordinates":[4.778865,51.824684],"type":"Point"}
}