{
  "type": "Feature",
  "properties": {
    "addr:full":"Hanzeplein 1 Groningen Groningen 9713 GZ",
    "addr:housenumber":"1",
    "addr:postcode":"9713 gz",
    "addr:street":"Hanzeplein",
    "iso:country":"NL",
    "sg:address":"Hanzeplein 1",
    "sg:city":"Groningen",
    "sg:orig_category":"Bloemen And Planten",
    "sg:phone":"+31 50 311 0496",
    "sg:postcode":"9713 GZ",
    "sg:province":"Groningen",
    "wof:name":"Bloemenkiosk Fleur",
    "wof:placetype":"venue"
},
  "geometry": {"coordinates":[6.577043,53.220993],"type":"Point"}
}