{
  "type": "Feature",
  "properties": {
    "addr:full":"Alexanderstraat 4 Tilburg Noord-Brabant 5038 XW",
    "addr:housenumber":"4",
    "addr:postcode":"5038 xw",
    "addr:street":"Alexanderstraat",
    "iso:country":"NL",
    "sg:address":"Alexanderstraat 4",
    "sg:city":"Tilburg",
    "sg:orig_category":"Werving And Selectie Van Tijdelijk Personeel And Uitzendkantoren",
    "sg:phone":"+31 13 583 6060",
    "sg:postcode":"5038 XW",
    "sg:province":"Noord-Brabant",
    "wof:name":"Ad Rem",
    "wof:placetype":"venue"
},
  "geometry": {"coordinates":[5.0863089561,51.5556221008],"type":"Point"}
}