{
  "type": "Feature",
  "properties": {
    "iso:country":"NL",
    "sg:address":"Molenlaan 82",
    "sg:city":"Honselersdijk",
    "sg:orig_category":"Bloemen And Planten",
    "sg:phone":"+31 174 627 572",
    "sg:postcode":"2675 CG",
    "sg:province":"South Holland",
    "wof:name":"Fa Gebr'S A En J Van Der Valk",
    "wof:placetype":"venue"
},
  "geometry": {"coordinates":[4.230798,52.00526],"type":"Point"}
}