{
  "type": "Feature",
  "properties": {
    "addr:full":"Kerkstr 47A Waarland Noord-Holland 1738 BH",
    "addr:housenumber":"47a",
    "addr:postcode":"1738 bh",
    "addr:street":"Kerkstr",
    "iso:country":"NL",
    "sg:address":"Kerkstr 47A",
    "sg:city":"Waarland",
    "sg:classifiers":[
        {
            "category":"Retail",
            "subcategory":"Auto Repair",
            "type":"Services"
        }
    ],
    "sg:phone":"+31 226 421 900",
    "sg:postcode":"1738 BH",
    "sg:province":"Noord-Holland",
    "sg:tags":[
        "garage"
    ],
    "sg:website":"http://www.garagedewaard.nl",
    "wof:name":"Waard, Garage De",
    "wof:placetype":"venue"
},
  "geometry": {"coordinates":[4.828975,52.727417],"type":"Point"}
}