{
  "type": "Feature",
  "properties": {
    "addr:full":"Markt 18-19 Heenvliet Zuid-Holland 3218 AM",
    "addr:postcode":"18-19;3218",
    "addr:street":"Markt",
    "iso:country":"NL",
    "sg:address":"Markt 18-19",
    "sg:city":"Heenvliet",
    "sg:orig_category":"Postkantoren",
    "sg:phone":"+31 181 661 222",
    "sg:postcode":"3218 AM",
    "sg:province":"Zuid-Holland",
    "sg:website":"http://www.postkantoor.nl",
    "wof:name":"Postkantoor",
    "wof:placetype":"venue"
},
  "geometry": {"coordinates":[4.244723,51.863968],"type":"Point"}
}