{
  "type": "Feature",
  "properties": {
    "addr:full":"Prinsengr 366 Amsterdam North Holland 1016 JA",
    "addr:housenumber":"366",
    "addr:postcode":"1016 ja",
    "iso:country":"NL",
    "sg:address":"Prinsengr 366",
    "sg:city":"Amsterdam",
    "sg:orig_category":"Boeken Antiquarische En Gebruikte",
    "sg:phone":"+31 20 427 4154",
    "sg:postcode":"1016 JA",
    "sg:province":"North Holland",
    "wof:name":"Lingua Terrae",
    "wof:placetype":"venue"
},
  "geometry": {"coordinates":[4.882026,52.367794],"type":"Point"}
}