{
  "type": "Feature",
  "properties": {
    "iso:country":"NL",
    "sg:address":"Neckerstr 119",
    "sg:city":"Purmerend",
    "sg:orig_category":"Houtspecialiteiten",
    "sg:phone":"+31 299 421 414",
    "sg:postcode":"1441 KV",
    "sg:province":"North Holland",
    "wof:name":"Prins & Zn Bv",
    "wof:placetype":"venue"
},
  "geometry": {"coordinates":[4.941665,52.510941],"type":"Point"}
}