{
  "type": "Feature",
  "properties": {
    "addr:full":"Voorstraat 3 Numansdorp Zuid-Holland 3281 AT",
    "addr:housenumber":"3",
    "addr:postcode":"3281",
    "addr:street":"Voorstraat",
    "iso:country":"NL",
    "sg:address":"Voorstraat 3",
    "sg:city":"Numansdorp",
    "sg:orig_category":"Autokeuringen",
    "sg:phone":"+31 186 651 349",
    "sg:postcode":"3281 AT",
    "sg:province":"Zuid-Holland",
    "wof:name":"Exploitatiemaatschappij J. Knoot Bv",
    "wof:placetype":"venue"
},
  "geometry": {"coordinates":[4.438345,51.731369],"type":"Point"}
}