{
  "type": "Feature",
  "properties": {
    "iso:country":"NL",
    "sg:address":"P Heinstr 21",
    "sg:city":"Noordwyk Zh",
    "sg:orig_category":"Wassalons",
    "sg:phone":"+31 71 361 3485",
    "sg:postcode":"2202 KS",
    "sg:province":"Zuid-Holland",
    "wof:name":"Piet Hein",
    "wof:placetype":"venue"
},
  "geometry": {"coordinates":[4.4477000237,52.2342605591],"type":"Point"}
}