{
  "type": "Feature",
  "properties": {
    "addr:full":"Boulev Bankert 158 Vlissingen Zeeland 4382 AC",
    "addr:housenumber":"158",
    "addr:postcode":"4382 ac",
    "addr:street":"Bankert",
    "iso:country":"NL",
    "sg:address":"Boulev Bankert 158",
    "sg:city":"Vlissingen",
    "sg:orig_category":"Makelaars En Adviseurs Onroerende Goederen",
    "sg:phone":"+31 118 440 800",
    "sg:postcode":"4382 AC",
    "sg:province":"Zeeland",
    "sg:website":"http://wwww.sinke.nl",
    "wof:name":"Sinke Komejan Bv",
    "wof:placetype":"venue"
},
  "geometry": {"coordinates":[3.564425,51.445953],"type":"Point"}
}