{
  "type": "Feature",
  "properties": {
    "addr:full":"Ryksstrwg 36 Baambrugge Utrecht 1396 JM",
    "addr:housenumber":"36",
    "addr:postcode":"1396 jm",
    "addr:street":"Ryksstrwg",
    "iso:country":"NL",
    "sg:address":"Ryksstrwg 36",
    "sg:city":"Baambrugge",
    "sg:classifiers":[
        {
            "category":"Retail",
            "subcategory":"Auto Repair",
            "type":"Services"
        }
    ],
    "sg:phone":"+31 294 291 395",
    "sg:postcode":"1396 JM",
    "sg:province":"Utrecht",
    "sg:tags":[
        "garage"
    ],
    "wof:name":"Petrogas Bv",
    "wof:placetype":"venue"
},
  "geometry": {"coordinates":[4.990055,52.246281],"type":"Point"}
}