{
  "type": "Feature",
  "properties": {
    "addr:full":"Princestr 19 Katwyk Zh Zuid-Holland 2225 EX",
    "addr:housenumber":"19",
    "addr:postcode":"2225 ex",
    "addr:street":"Princestr",
    "iso:country":"NL",
    "sg:address":"Princestr 19",
    "sg:city":"Katwyk Zh",
    "sg:orig_category":"Kinderkleding",
    "sg:phone":"+31 71 407 6546",
    "sg:postcode":"2225 EX",
    "sg:province":"Zuid-Holland",
    "wof:name":"Time Kids",
    "wof:placetype":"venue"
},
  "geometry": {"coordinates":[4.396585,52.205109],"type":"Point"}
}