{
  "type": "Feature",
  "properties": {
    "addr:full":"Oostervalge 50 Warffum Groningen 9989 EL",
    "addr:housenumber":"50",
    "addr:postcode":"9989 el",
    "addr:street":"Oostervalge",
    "iso:country":"NL",
    "sg:address":"Oostervalge 50",
    "sg:city":"Warffum",
    "sg:orig_category":"Paramedische Behandelingen",
    "sg:phone":"+31 595 422 120",
    "sg:postcode":"9989 EL",
    "sg:province":"Groningen",
    "wof:name":"Wph",
    "wof:placetype":"venue"
},
  "geometry": {"coordinates":[6.561509,53.395748],"type":"Point"}
}