{
  "type": "Feature",
  "properties": {
    "addr:full":"Nievaartpad 40 Leiderdorp Zuid-Holland 2353 SL",
    "addr:housenumber":"40",
    "addr:postcode":"2353 sl",
    "addr:street":"Nievaartpad",
    "iso:country":"NL",
    "sg:address":"Nievaartpad 40",
    "sg:city":"Leiderdorp",
    "sg:orig_category":"Beveiligingsdiensten And Bewakingsbedrijven",
    "sg:phone":"+31 71 589 9288",
    "sg:postcode":"2353 SL",
    "sg:province":"Zuid-Holland",
    "wof:name":"Topsafe Security",
    "wof:placetype":"venue"
},
  "geometry": {"coordinates":[4.525764,52.169895],"type":"Point"}
}