{
  "type": "Feature",
  "properties": {
    "iso:country":"NL",
    "sg:address":"L Geer 44",
    "sg:city":"Delft",
    "sg:orig_category":"Geluidsinstallaties - Verhuur",
    "sg:phone":"+31 6 24910003",
    "sg:postcode":"2611 PW",
    "sg:province":"Zuid-Holland",
    "sg:website":"http://www.a-sound.nl",
    "wof:name":"A-Sound",
    "wof:placetype":"venue"
},
  "geometry": {"coordinates":[4.354973,52.016277],"type":"Point"}
}