{
  "type": "Feature",
  "properties": {
    "addr:full":"Mergelweg 3 Voerendaal Limburg 6367 TP",
    "addr:housenumber":"3",
    "addr:postcode":"6367 tp",
    "addr:street":"Mergelweg",
    "iso:country":"NL",
    "sg:address":"Mergelweg 3",
    "sg:city":"Voerendaal",
    "sg:orig_category":"Binnenhuisarchitecten",
    "sg:phone":"+31 45 575 3585",
    "sg:postcode":"6367 TP",
    "sg:province":"Limburg",
    "wof:name":"Friedrich",
    "wof:placetype":"venue"
},
  "geometry": {"coordinates":[5.92905,50.880432],"type":"Point"}
}