{
  "type": "Feature",
  "properties": {
    "addr:full":"Verlaatwg 72A Lelystad Flevoland 8243 PS",
    "addr:housenumber":"72a",
    "addr:postcode":"8243 ps",
    "addr:street":"Verlaatwg;Flevoland",
    "iso:country":"NL",
    "sg:address":"Verlaatwg 72A",
    "sg:city":"Lelystad",
    "sg:orig_category":"Kunststof Ramen",
    "sg:phone":"+31 320 213 967",
    "sg:postcode":"8243 PS",
    "sg:province":"Flevoland",
    "wof:name":"Brock Moderne Bouwelementen",
    "wof:placetype":"venue"
},
  "geometry": {"coordinates":[5.436592,52.501614],"type":"Point"}
}