{
  "type": "Feature",
  "properties": {
    "addr:full":"Julianaplein 111 Beuningen Gld Gelderland 6641 CS",
    "addr:housenumber":"111",
    "addr:postcode":"6641 cs",
    "addr:street":"Julianaplein",
    "iso:country":"NL",
    "sg:address":"Julianaplein 111",
    "sg:city":"Beuningen Gld",
    "sg:orig_category":"Kappers",
    "sg:phone":"+31 24 677 6161",
    "sg:postcode":"6641 CS",
    "sg:province":"Gelderland",
    "wof:name":"Haarstudio A1",
    "wof:placetype":"venue"
},
  "geometry": {"coordinates":[5.7718930244,51.8600273132],"type":"Point"}
}