{
  "type": "Feature",
  "properties": {
    "iso:country":"NL",
    "sg:address":"Kernwg 7",
    "sg:city":"Hoorn Nh",
    "sg:orig_category":"Keukens",
    "sg:phone":"+31 229 212 100",
    "sg:postcode":"1627 LC",
    "sg:province":"Noord-Holland",
    "sg:website":"http://www.edmon.nl",
    "wof:name":"Edmon Bv",
    "wof:placetype":"venue"
},
  "geometry": {"coordinates":[5.098167,52.643242],"type":"Point"}
}