{
  "type": "Feature",
  "properties": {
    "addr:full":"Ijsselstraat 4 Oss Noord-Brabant 5347 KG",
    "addr:housenumber":"4",
    "addr:postcode":"5347 kg",
    "addr:street":"Ijsselstraat",
    "iso:country":"NL",
    "sg:address":"Ijsselstraat 4",
    "sg:city":"Oss",
    "sg:orig_category":"Metaalwerken",
    "sg:phone":"+31 412 625 113",
    "sg:postcode":"5347 KG",
    "sg:province":"Noord-Brabant",
    "wof:name":"Cor Van Haaren Woninginrichting",
    "wof:placetype":"venue"
},
  "geometry": {"coordinates":[-77.235214,38.312599],"type":"Point"}
}