{
  "type": "Feature",
  "properties": {
    "addr:full":"Kerkln 20 Oude Pekela Groningen 9665 PB",
    "addr:housenumber":"20",
    "addr:postcode":"pekela;9665 pb",
    "addr:street":"Kerkln",
    "iso:country":"NL",
    "sg:address":"Kerkln 20",
    "sg:city":"Oude Pekela",
    "sg:orig_category":"Loonbedrijven",
    "sg:phone":"+31 597 432 006",
    "sg:postcode":"9665 PB",
    "sg:province":"Groningen",
    "wof:name":"Wortelboer Vof",
    "wof:placetype":"venue"
},
  "geometry": {"coordinates":[7.00891,53.103069],"type":"Point"}
}