{
  "type": "Feature",
  "properties": {
    "iso:country":"NL",
    "sg:address":"Strandwal 4",
    "sg:city":"Haarlem",
    "sg:orig_category":"Fotografie Reclame En Mode",
    "sg:phone":"+31 23 533 8315",
    "sg:postcode":"2033 CZ",
    "sg:province":"Noord-Holland",
    "sg:website":"http://www.fotop.nl",
    "wof:name":"Liliane V Kol",
    "wof:placetype":"venue"
},
  "geometry": {"coordinates":[4.67064,52.374718],"type":"Point"}
}