{
  "type": "Feature",
  "properties": {
    "addr:full":"Nyverheidstr 8 Herwen Gelderland 6914 AD",
    "addr:housenumber":"8",
    "addr:postcode":"6914 ad",
    "addr:street":"Nyverheidstr;Gelderland",
    "iso:country":"NL",
    "sg:address":"Nyverheidstr 8",
    "sg:city":"Herwen",
    "sg:orig_category":"Verhuur",
    "sg:phone":"+31 316 248 999",
    "sg:postcode":"6914 AD",
    "sg:province":"Gelderland",
    "wof:name":"Logiflex Herwen Bv",
    "wof:placetype":"venue"
},
  "geometry": {"coordinates":[6.099603,51.883068],"type":"Point"}
}