{
  "type": "Feature",
  "properties": {
    "addr:full":"Buntlaan 78 Driebergen-Rijsenburg Utrecht 3971 JE",
    "addr:housenumber":"78",
    "addr:postcode":"3971 je",
    "addr:street":"Buntlaan",
    "iso:country":"NL",
    "sg:address":"Buntlaan 78",
    "sg:city":"Driebergen-Rijsenburg",
    "sg:orig_category":"Verhuur Audiovisuele Apparatuur",
    "sg:phone":"+31 343 518 600",
    "sg:postcode":"3971 JE",
    "sg:province":"Utrecht",
    "wof:name":"Technisch Bureau Sterbo",
    "wof:placetype":"venue"
},
  "geometry": {"coordinates":[5.299381,52.054653],"type":"Point"}
}