{
  "type": "Feature",
  "properties": {
    "addr:full":"Daniel Goedkoopstraat 31 Amsterdam North Holland 1096 BD",
    "addr:housenumber":"31",
    "addr:postcode":"1096 bd",
    "addr:street":"Goedkoopstraat",
    "iso:country":"NL",
    "sg:address":"Daniel Goedkoopstraat 31",
    "sg:city":"Amsterdam",
    "sg:orig_category":"Hout Gh",
    "sg:phone":"+31 20 694 6767",
    "sg:postcode":"1096 BD",
    "sg:province":"North Holland",
    "wof:name":"Bouwmaat Amsterdam Bv",
    "wof:placetype":"venue"
},
  "geometry": {"coordinates":[4.921502,52.336243],"type":"Point"}
}