{
  "type": "Feature",
  "properties": {
    "addr:full":"Den Hof 4 Waalre North Brabant 5582 JZ",
    "addr:housenumber":"4",
    "addr:postcode":"5582 jz",
    "addr:street":"Den Hof",
    "iso:country":"NL",
    "sg:address":"Den Hof 4",
    "sg:city":"Waalre",
    "sg:orig_category":"Banken And Kredietinstellingen",
    "sg:phone":"+31 40 221 2213",
    "sg:postcode":"5582 JZ",
    "sg:province":"North Brabant",
    "wof:name":"Postkantoor",
    "wof:placetype":"venue"
},
  "geometry": {"coordinates":[5.475214,51.395546],"type":"Point"}
}