{
  "type": "Feature",
  "properties": {
    "addr:full":"Dordtselaan 71 Rotterdam South Holland 3081 BG",
    "addr:housenumber":"71",
    "addr:postcode":"3081",
    "addr:street":"Dordtselaan",
    "iso:country":"NL",
    "sg:address":"Dordtselaan 71",
    "sg:city":"Rotterdam",
    "sg:classifiers":[
        {
            "category":"Food & Beverages",
            "subcategory":"Fruits & Vegetables",
            "type":"Retail Goods"
        }
    ],
    "sg:phone":"+31 10 485 6524",
    "sg:postcode":"3081 BG",
    "sg:province":"South Holland",
    "sg:tags":[
        "groenten"
    ],
    "wof:name":"De Vrienden",
    "wof:placetype":"venue"
},
  "geometry": {"coordinates":[4.493579,51.89341],"type":"Point"}
}