{
  "type": "Feature",
  "properties": {
    "addr:full":"Brommelen 58A Geulle Limburg 6243 CR",
    "addr:housenumber":"58a",
    "addr:postcode":"6243 cr",
    "addr:street":"Brommelen",
    "iso:country":"NL",
    "sg:address":"Brommelen 58A",
    "sg:city":"Geulle",
    "sg:classifiers":[
        {
            "category":"Bus Charters",
            "type":"Transportation"
        }
    ],
    "sg:phone":"+31 43 365 2563",
    "sg:postcode":"6243 CR",
    "sg:province":"Limburg",
    "sg:tags":[
        "caravan"
    ],
    "wof:name":"Ralon",
    "wof:placetype":"venue"
},
  "geometry": {"coordinates":[5.7361,50.910328],"type":"Point"}
}