{
  "type": "Feature",
  "properties": {
    "iso:country":"NL",
    "sg:address":"Provincialeweg 15",
    "sg:city":"Kornhorn",
    "sg:orig_category":"Kappers",
    "sg:phone":"+31 594 659 720",
    "sg:postcode":"9864 PA",
    "sg:province":"Groningen",
    "wof:name":"Kapsalon Karin",
    "wof:placetype":"venue"
},
  "geometry": {"coordinates":[6.2352972031,53.1801948547],"type":"Point"}
}