{
  "type": "Feature",
  "properties": {
    "addr:full":"Vuurwerkerweg 1 Amsterdam Noord-Holland 1032 KN",
    "addr:housenumber":"1",
    "addr:postcode":"1032 kn",
    "addr:street":"Vuurwerkerweg",
    "iso:country":"NL",
    "sg:address":"Vuurwerkerweg 1",
    "sg:city":"Amsterdam",
    "sg:orig_category":"Meubelzaken, Woning- And Keukeninrichting",
    "sg:phone":"+31 20 634 3455",
    "sg:postcode":"1032 KN",
    "sg:province":"Noord-Holland",
    "wof:name":"De Driehoek Meubelen Bv",
    "wof:placetype":"venue"
},
  "geometry": {"coordinates":[4.906592,52.399212],"type":"Point"}
}