{
  "type": "Feature",
  "properties": {
    "addr:full":"Beneden Oosterd 165 Veendam Groningen 9645 LN",
    "addr:housenumber":"165",
    "addr:postcode":"9645 ln",
    "addr:street":"Beneden Oosterd",
    "iso:country":"NL",
    "sg:address":"Beneden Oosterd 165",
    "sg:city":"Veendam",
    "sg:orig_category":"Bloemen En Planten",
    "sg:phone":"+31 598 619 286",
    "sg:postcode":"9645 LN",
    "sg:province":"Groningen",
    "wof:name":"Fleurshop",
    "wof:placetype":"venue"
},
  "geometry": {"coordinates":[6.886524,53.111404],"type":"Point"}
}