{
  "type": "Feature",
  "properties": {
    "iso:country":"NL",
    "sg:address":"Kievitswg 11-23",
    "sg:city":"Nes Ameland",
    "sg:orig_category":"Juridische Adviseurs",
    "sg:phone":"+31 519 543 376",
    "sg:postcode":"9163 KA",
    "sg:province":"Provincie Friesland",
    "wof:name":"Vink, Mr E T",
    "wof:placetype":"venue"
},
  "geometry": {"coordinates":[5.773275,53.454742],"type":"Point"}
}