{
  "type": "Feature",
  "properties": {
    "addr:full":"Middel Broekweg 29 Honselersdijk Zuid-Holland 2675 KB",
    "addr:housenumber":"29",
    "addr:postcode":"2675 kb",
    "addr:street":"Middel Broekweg",
    "iso:country":"NL",
    "sg:address":"Middel Broekweg 29",
    "sg:city":"Honselersdijk",
    "sg:orig_category":"Bloemen And Planten Gh",
    "sg:phone":"+31 174 631 950",
    "sg:postcode":"2675 KB",
    "sg:province":"Zuid-Holland",
    "wof:name":"Wimex Bv",
    "wof:placetype":"venue"
},
  "geometry": {"coordinates":[4.227969,51.99614],"type":"Point"}
}