{
  "type": "Feature",
  "properties": {
    "addr:full":"Kreunenskamp 8 Hengelo Gld Gelderland 7255 WD",
    "addr:housenumber":"8",
    "addr:postcode":"7255 wd",
    "addr:street":"Kreunenskamp",
    "iso:country":"NL",
    "sg:address":"Kreunenskamp 8",
    "sg:city":"Hengelo Gld",
    "sg:orig_category":"Voegwerken",
    "sg:phone":"+31 575 465 311",
    "sg:postcode":"7255 WD",
    "sg:province":"Gelderland",
    "wof:name":"Harmsen Voegwerken, P",
    "wof:placetype":"venue"
},
  "geometry": {"coordinates":[6.315834,52.047859],"type":"Point"}
}