{
  "type": "Feature",
  "properties": {
    "iso:country":"NL",
    "sg:address":"Huizerwg 118",
    "sg:city":"Bussum",
    "sg:orig_category":"Kappers",
    "sg:phone":"+31 35 693 0013",
    "sg:postcode":"1402 AJ",
    "sg:province":"Noord-Holland",
    "wof:name":"Ingeborg",
    "wof:placetype":"venue"
},
  "geometry": {"coordinates":[5.1767868996,52.2760772705],"type":"Point"}
}