{
  "type": "Feature",
  "properties": {
    "addr:full":"Houterend 42 Stein Lb Missouri 6171 CS",
    "addr:housenumber":"42",
    "addr:postcode":"6171 cs",
    "addr:street":"Houterend",
    "iso:country":"NL",
    "sg:address":"Houterend 42",
    "sg:city":"Stein Lb",
    "sg:orig_category":"Maquettes",
    "sg:phone":"+31 46 433 9716",
    "sg:postcode":"6171 CS",
    "sg:province":"Missouri",
    "wof:name":"Lamers",
    "wof:placetype":"venue"
},
  "geometry": {"coordinates":[-93.129936,36.705662],"type":"Point"}
}