{
  "type": "Feature",
  "properties": {
    "iso:country":"NL",
    "sg:address":"Zeedk 24",
    "sg:city":"Amsterdam",
    "sg:orig_category":"Administratie- En Boekhoudkantoren",
    "sg:phone":"+31 20 420 2413",
    "sg:postcode":"1012 AZ",
    "sg:province":"Noord-Holland",
    "wof:name":"Nefkens",
    "wof:placetype":"venue"
},
  "geometry": {"coordinates":[4.900828,52.375595],"type":"Point"}
}