{
  "type": "Feature",
  "properties": {
    "addr:full":"Rozenstraat 3 Haarlem North Holland 2011 LS",
    "addr:housenumber":"3",
    "addr:postcode":"2011 ls",
    "addr:street":"Rozenstraat",
    "iso:country":"NL",
    "sg:address":"Rozenstraat 3",
    "sg:city":"Haarlem",
    "sg:orig_category":"Boekhouders",
    "sg:phone":"+31 23 542 1644",
    "sg:postcode":"2011 LS",
    "sg:province":"North Holland",
    "wof:name":"Shoebox Office Support",
    "wof:placetype":"venue"
},
  "geometry": {"coordinates":[4.633357,52.387836],"type":"Point"}
}