{
  "type": "Feature",
  "properties": {
    "iso:country":"NL",
    "sg:address":"Toermalynring 1000",
    "sg:city":"Dordrecht",
    "sg:orig_category":"Ventilatiesystemen",
    "sg:phone":"+31 78 655 2020",
    "sg:postcode":"3316 LC",
    "sg:province":"South Holland",
    "wof:name":"Vortvent Bv",
    "wof:placetype":"venue"
},
  "geometry": {"coordinates":[4.63178,51.76606],"type":"Point"}
}