{
  "type": "Feature",
  "properties": {
    "addr:full":"2E Weteringdwstr 63/A1 Amsterdam Noord-Holland 1017 SV",
    "addr:housenumber":"63 / a1",
    "addr:postcode":"1017 sv",
    "addr:street":"2E Weteringdwstr",
    "iso:country":"NL",
    "sg:address":"2E Weteringdwstr 63/A1",
    "sg:city":"Amsterdam",
    "sg:orig_category":"Vertalers",
    "sg:phone":"+31 20 620 1452",
    "sg:postcode":"1017 SV",
    "sg:province":"Noord-Holland",
    "wof:name":"Boer, Drs E Den",
    "wof:placetype":"venue"
},
  "geometry": {"coordinates":[4.893195,52.373119],"type":"Point"}
}