{
  "type": "Feature",
  "properties": {
    "addr:full":"Hattemse Beek 175 Apeldoorn Gelderland 7335 PD",
    "addr:housenumber":"175",
    "addr:postcode":"7335 pd",
    "addr:street":"Hattemse Beek;Gelderland",
    "iso:country":"NL",
    "sg:address":"Hattemse Beek 175",
    "sg:city":"Apeldoorn",
    "sg:orig_category":"Antiekzaken",
    "sg:phone":"+31 55 542 1767",
    "sg:postcode":"7335 PD",
    "sg:province":"Gelderland",
    "wof:name":"De Boek- & Strip(Ver)Wijzer",
    "wof:placetype":"venue"
},
  "geometry": {"coordinates":[5.949993,52.192745],"type":"Point"}
}