{
  "type": "Feature",
  "properties": {
    "addr:full":"Singel 118 Amsterdam Noord-Holland 1015 AE",
    "addr:housenumber":"118",
    "addr:postcode":"1015 ae",
    "addr:street":"Singel",
    "iso:country":"NL",
    "sg:address":"Singel 118",
    "sg:city":"Amsterdam",
    "sg:orig_category":"Adviesbureaus Bedrijfsorganisatie",
    "sg:phone":"+31 20 638 1929",
    "sg:postcode":"1015 AE",
    "sg:province":"Noord-Holland",
    "wof:name":"Evers Retail Bv",
    "wof:placetype":"venue"
},
  "geometry": {"coordinates":[4.890487,52.37616],"type":"Point"}
}