{
  "type": "Feature",
  "properties": {
    "addr:full":"Hendrik De Keyserstraat 64 Rotterdam South Holland 3034 CN",
    "addr:housenumber":"64",
    "addr:postcode":"3034 cn",
    "addr:street":"Hendrik De Keyserstraat",
    "iso:country":"NL",
    "sg:address":"Hendrik De Keyserstraat 64",
    "sg:city":"Rotterdam",
    "sg:orig_category":"Verhuisdiensten",
    "sg:phone":"+31 10 414 2454",
    "sg:postcode":"3034 CN",
    "sg:province":"South Holland",
    "wof:name":"Nimwegen",
    "wof:placetype":"venue"
},
  "geometry": {"coordinates":[4.488712,51.931969],"type":"Point"}
}