{
  "type": "Feature",
  "properties": {
    "iso:country":"NL",
    "sg:address":"Breulingstraat 5",
    "sg:city":"Maastricht",
    "sg:orig_category":"Mode-, Juwelen- And Meubelontwerpers",
    "sg:phone":"+31 43 325 7282",
    "sg:postcode":"6211 SB",
    "sg:province":"Limburg",
    "wof:name":"Paul Tiemans",
    "wof:placetype":"venue"
},
  "geometry": {"coordinates":[5.68963,50.853554],"type":"Point"}
}