{
  "type": "Feature",
  "properties": {
    "iso:country":"NL",
    "sg:address":"Kerkvaart 1",
    "sg:city":"Mijdrecht",
    "sg:orig_category":"Diverse Bedrijfsinstallaties Gh",
    "sg:phone":"+31 297 288 506",
    "sg:postcode":"3641 EN",
    "sg:province":"Utrecht",
    "wof:name":"Handelsonderneming Versleijen Bv",
    "wof:placetype":"venue"
},
  "geometry": {"coordinates":[4.865839,52.208687],"type":"Point"}
}