{
  "type": "Feature",
  "properties": {
    "iso:country":"NL",
    "sg:address":"Dorpsstraat 695",
    "sg:city":"Assendelft",
    "sg:orig_category":"Huishoudapparatuur, Televisies And Radio'S",
    "sg:phone":"+31 75 687 4860",
    "sg:postcode":"1566 ED",
    "sg:province":"North Holland",
    "wof:name":"Srts",
    "wof:placetype":"venue"
},
  "geometry": {"coordinates":[4.751386,52.480942],"type":"Point"}
}