{
  "type": "Feature",
  "properties": {
    "addr:full":"Houtkampweg 7 Otterlo Gelderland 6731 AV",
    "addr:housenumber":"7",
    "addr:postcode":"6731 av",
    "addr:street":"Houtkampweg;Gelderland",
    "iso:country":"NL",
    "sg:address":"Houtkampweg 7",
    "sg:city":"Otterlo",
    "sg:orig_category":"Jeugdherbergen And Berghutten",
    "sg:phone":"+31 318 591 706",
    "sg:postcode":"6731 AV",
    "sg:province":"Gelderland",
    "wof:name":"Pension Boerderij De Houtkamp",
    "wof:placetype":"venue"
},
  "geometry": {"coordinates":[5.782668,52.103165],"type":"Point"}
}