{
  "type": "Feature",
  "properties": {
    "addr:full":"Het Vergun 40 Westervoort Gelderland 6931 KD",
    "addr:housenumber":"40",
    "addr:postcode":"6931 kd",
    "addr:street":"Het Vergun;Gelderland",
    "iso:country":"NL",
    "sg:address":"Het Vergun 40",
    "sg:city":"Westervoort",
    "sg:orig_category":"Fotostudio'S And Fotografen",
    "sg:phone":"+31 26 325 4408",
    "sg:postcode":"6931 KD",
    "sg:province":"Gelderland",
    "wof:name":"Fotografie Rob Sas",
    "wof:placetype":"venue"
},
  "geometry": {"coordinates":[5.980331,51.960457],"type":"Point"}
}