{
  "type": "Feature",
  "properties": {
    "iso:country":"NL",
    "sg:address":"Stadhoudersln 17",
    "sg:city":"Ridderkerk",
    "sg:orig_category":"Beeldende Kunstenaars",
    "sg:phone":"+31 180 410 812",
    "sg:postcode":"2983 CP",
    "sg:province":"Zuid-Holland",
    "wof:name":"Addy De Bruin-Put",
    "wof:placetype":"venue"
},
  "geometry": {"coordinates":[4.598051,51.871727],"type":"Point"}
}