{
  "type": "Feature",
  "properties": {
    "addr:full":"Ohmstraat 23 Hilversum North Holland 1221 GN",
    "addr:housenumber":"23",
    "addr:postcode":"1221 gn",
    "addr:street":"Ohmstraat",
    "iso:country":"NL",
    "sg:address":"Ohmstraat 23",
    "sg:city":"Hilversum",
    "sg:orig_category":"Technische Studies And Onderzoek",
    "sg:phone":"+31 35 683 4738",
    "sg:postcode":"1221 GN",
    "sg:province":"North Holland",
    "wof:name":"Past",
    "wof:placetype":"venue"
},
  "geometry": {"coordinates":[5.191399,52.2286],"type":"Point"}
}