{
  "type": "Feature",
  "properties": {
    "addr:full":"Dokter Rietveldplein 57 Papendrecht Zuid-Holland 3353 SH",
    "addr:housenumber":"57",
    "addr:postcode":"3353 sh",
    "addr:street":"Dokter Rietveldplein",
    "iso:country":"NL",
    "sg:address":"Dokter Rietveldplein 57",
    "sg:city":"Papendrecht",
    "sg:orig_category":"Schoonheidssalons",
    "sg:phone":"+31 78 641 0232",
    "sg:postcode":"3353 SH",
    "sg:province":"Zuid-Holland",
    "wof:name":"Annemiek Van Der Ree",
    "wof:placetype":"venue"
},
  "geometry": {"coordinates":[4.690467,51.824188],"type":"Point"}
}