{
  "type": "Feature",
  "properties": {
    "addr:full":"Arnhemsewg 93 Otterlo Gelderland 6731 BR",
    "addr:housenumber":"93",
    "addr:postcode":"6731 br",
    "addr:street":"Arnhemsewg;Gelderland",
    "iso:country":"NL",
    "sg:address":"Arnhemsewg 93",
    "sg:city":"Otterlo",
    "sg:orig_category":"Adviesbureaus Bedrijfsorganisatie",
    "sg:phone":"+31 318 592 392",
    "sg:postcode":"6731 BR",
    "sg:province":"Gelderland",
    "wof:name":"Oas",
    "wof:placetype":"venue"
},
  "geometry": {"coordinates":[5.773296,52.095524],"type":"Point"}
}