{
  "type": "Feature",
  "properties": {
    "iso:country":"NL",
    "sg:address":"Hakfortlaan 34",
    "sg:city":"Arnhem",
    "sg:orig_category":"Handelsbemiddeling Textiel And Lederwaren",
    "sg:phone":"+31 26 363 0207",
    "sg:postcode":"6825 GH",
    "sg:province":"Gelderland",
    "wof:name":"Sylcolon Bv",
    "wof:placetype":"venue"
},
  "geometry": {"coordinates":[5.969142,51.980129],"type":"Point"}
}