{
  "type": "Feature",
  "properties": {
    "addr:full":"De Kempenaerware 78 Zwolle NL.08 8014 RH",
    "addr:housenumber":"78",
    "addr:postcode":"8014 rh",
    "addr:street":"De Kempenaerware",
    "iso:country":"NL",
    "sg:address":"De Kempenaerware 78",
    "sg:city":"Zwolle",
    "sg:orig_category":"Boekhouders",
    "sg:phone":"+31 38 454 8290",
    "sg:postcode":"8014 RH",
    "sg:province":"NL.08",
    "wof:name":"Administratief Klussenburo Van 'T Veen",
    "wof:placetype":"venue"
},
  "geometry": {"coordinates":[6.113059,52.482132],"type":"Point"}
}