{
  "type": "Feature",
  "properties": {
    "addr:full":"Burg Raymakersln 171 Grave Noord-Brabant 5361 KL",
    "addr:housenumber":"171",
    "addr:postcode":"5361 kl",
    "addr:street":"Burg;Grave",
    "iso:country":"NL",
    "sg:address":"Burg Raymakersln 171",
    "sg:city":"Grave",
    "sg:orig_category":"Adviesbureaus Bouwkunde",
    "sg:phone":"+31 486 454 646",
    "sg:postcode":"5361 KL",
    "sg:province":"Noord-Brabant",
    "wof:name":"Visser Bouwadvies Grave, M",
    "wof:placetype":"venue"
},
  "geometry": {"coordinates":[-92.151741,32.929253],"type":"Point"}
}