{
  "type": "Feature",
  "properties": {
    "addr:full":"Leeuwstr 4 Venray Limburg 5801 BA",
    "addr:housenumber":"4",
    "addr:postcode":"5801 ba",
    "addr:street":"Leeuwstr",
    "iso:country":"NL",
    "sg:address":"Leeuwstr 4",
    "sg:city":"Venray",
    "sg:orig_category":"Webdesign Bureaus",
    "sg:phone":"+31 478 530 030",
    "sg:postcode":"5801 BA",
    "sg:province":"Limburg",
    "sg:website":"http://www.advance-automatisering.nl",
    "wof:name":"Advance Bv",
    "wof:placetype":"venue"
},
  "geometry": {"coordinates":[5.974462986,51.5237312317],"type":"Point"}
}