{
  "type": "Feature",
  "properties": {
    "addr:full":"Haarbeemd 73 Bavel Noord-Brabant 4854 MH",
    "addr:housenumber":"73",
    "addr:postcode":"4854 mh",
    "addr:street":"Haarbeemd",
    "iso:country":"NL",
    "sg:address":"Haarbeemd 73",
    "sg:city":"Bavel",
    "sg:orig_category":"Verhuur",
    "sg:phone":"+31 161 433 344",
    "sg:postcode":"4854 MH",
    "sg:province":"Noord-Brabant",
    "wof:name":"Hupscher",
    "wof:placetype":"venue"
},
  "geometry": {"coordinates":[4.830501,51.57156],"type":"Point"}
}