{
  "type": "Feature",
  "properties": {
    "addr:full":"Orchideeenstraat 16 Rosmalen North Brabant 5241 AH",
    "addr:housenumber":"16",
    "addr:postcode":"5241 ah",
    "addr:street":"Orchideeenstraat",
    "iso:country":"NL",
    "sg:address":"Orchideeenstraat 16",
    "sg:city":"Rosmalen",
    "sg:orig_category":"Boekhouders",
    "sg:phone":"+31 73 521 8533",
    "sg:postcode":"5241 AH",
    "sg:province":"North Brabant",
    "wof:name":"Raad Rosmalen",
    "wof:placetype":"venue"
},
  "geometry": {"coordinates":[5.355857,51.713783],"type":"Point"}
}