{
  "type": "Feature",
  "properties": {
    "addr:full":"Tulpstraat 80 Goes Ohio 4461 PB",
    "addr:housenumber":"80",
    "addr:postcode":"4461 pb",
    "addr:street":"Tulpstraat",
    "iso:country":"NL",
    "sg:address":"Tulpstraat 80",
    "sg:city":"Goes",
    "sg:orig_category":"Fruit And Groenten Gh",
    "sg:phone":"+31 113 227 909",
    "sg:postcode":"4461 PB",
    "sg:province":"Ohio",
    "wof:name":"Firma J.L. Trimpe & Zoon",
    "wof:placetype":"venue"
},
  "geometry": {"coordinates":[-83.914169,39.768833],"type":"Point"}
}