{
  "type": "Feature",
  "properties": {
    "iso:country":"NL",
    "sg:address":"Bergkwartier 9",
    "sg:city":"Venray",
    "sg:orig_category":"Beeldende Kunstenaars",
    "sg:phone":"+31 478 584 245",
    "sg:postcode":"5801 PS",
    "sg:province":"Limburg",
    "wof:name":"Immy Reijnolds",
    "wof:placetype":"venue"
},
  "geometry": {"coordinates":[5.957768,51.518845],"type":"Point"}
}