{
  "type": "Feature",
  "properties": {
    "iso:country":"NL",
    "sg:address":"Arnhemsestrwg 229",
    "sg:city":"Rheden",
    "sg:orig_category":"Psychologen",
    "sg:phone":"+31 26 322 9505",
    "sg:postcode":"6991 AL",
    "sg:province":"Gelderland",
    "wof:name":"Timmermans, Drs",
    "wof:placetype":"venue"
},
  "geometry": {"coordinates":[6.03264,52.002544],"type":"Point"}
}