{
  "type": "Feature",
  "properties": {
    "addr:full":"Kroonstr 33 Etten Leur North Brabant 4879 AV",
    "addr:housenumber":"33",
    "addr:postcode":"4879 av",
    "addr:street":"Kroonstr",
    "iso:country":"NL",
    "sg:address":"Kroonstr 33",
    "sg:city":"Etten Leur",
    "sg:orig_category":"Verpakkingen En Verpakkingsmaterialen",
    "sg:phone":"+31 76 503 4002",
    "sg:postcode":"4879 AV",
    "sg:province":"North Brabant",
    "wof:name":"Cornelis",
    "wof:placetype":"venue"
},
  "geometry": {"coordinates":[4.626762,51.557949],"type":"Point"}
}