{
  "type": "Feature",
  "properties": {
    "iso:country":"NL",
    "sg:address":"Statenlaan 9",
    "sg:city":"'S Hertogenbosch",
    "sg:orig_category":"Advocaten And Juridische Adviseurs",
    "sg:phone":"+31 73 627 1888",
    "sg:postcode":"5223 LA",
    "sg:province":"Noord-Brabant",
    "wof:name":"Van Leeuwen & Van Der Eerden",
    "wof:placetype":"venue"
},
  "geometry": {"coordinates":[5.289984,51.689758],"type":"Point"}
}