{
  "type": "Feature",
  "properties": {
    "addr:full":"Merelln 23 Bilthoven Utrecht 3722 AK",
    "addr:housenumber":"23",
    "addr:postcode":"3722 ak",
    "addr:street":"Merelln",
    "iso:country":"NL",
    "sg:address":"Merelln 23",
    "sg:city":"Bilthoven",
    "sg:orig_category":"Loopbaanbegeleiding",
    "sg:phone":"+31 30 228 4980",
    "sg:postcode":"3722 AK",
    "sg:province":"Utrecht",
    "wof:name":"Twogram",
    "wof:placetype":"venue"
},
  "geometry": {"coordinates":[5.21093,52.121498],"type":"Point"}
}