{
  "type": "Feature",
  "properties": {
    "addr:full":"A V Burenstr 14 Noord Scharwoude Noord-Holland 1723 KL",
    "addr:housenumber":"14",
    "addr:postcode":"1723 kl",
    "addr:street":"A;Burenstr",
    "iso:country":"NL",
    "sg:address":"A V Burenstr 14",
    "sg:city":"Noord Scharwoude",
    "sg:orig_category":"Bedden En Matrassen",
    "sg:phone":"+31 226 314 647",
    "sg:postcode":"1723 KL",
    "sg:province":"Noord-Holland",
    "wof:name":"Jonker",
    "wof:placetype":"venue"
},
  "geometry": {"coordinates":[4.81024,52.698441],"type":"Point"}
}