{
  "type": "Feature",
  "properties": {
    "addr:full":"Putweg 49 Klimmen Limburg 6343 PD",
    "addr:housenumber":"49",
    "addr:postcode":"6343 pd",
    "addr:street":"Putweg",
    "iso:country":"NL",
    "sg:address":"Putweg 49",
    "sg:city":"Klimmen",
    "sg:orig_category":"Autokeuringen",
    "sg:phone":"+31 45 405 1286",
    "sg:postcode":"6343 PD",
    "sg:province":"Limburg",
    "wof:name":"Rouwette Autobanden",
    "wof:placetype":"venue"
},
  "geometry": {"coordinates":[5.890962,50.883007],"type":"Point"}
}