{
  "type": "Feature",
  "properties": {
    "addr:full":"Kerkstraat 6 Dokkum Friesland 9101 LG",
    "addr:housenumber":"6",
    "addr:postcode":"9101 lg",
    "addr:street":"Kerkstraat",
    "iso:country":"NL",
    "sg:address":"Kerkstraat 6",
    "sg:city":"Dokkum",
    "sg:orig_category":"Medische Apparatuur And Prothesen Fab",
    "sg:phone":"+31 519 297 890",
    "sg:postcode":"9101 LG",
    "sg:province":"Friesland",
    "wof:name":"L. De Haan Hoorapparaten Bv",
    "wof:placetype":"venue"
},
  "geometry": {"coordinates":[5.998597,53.326447],"type":"Point"}
}