{
  "type": "Feature",
  "properties": {
    "addr:full":"Handelswg 8 Hasselt NL.08 8061 RL",
    "addr:housenumber":"8",
    "addr:postcode":"8061 rl",
    "addr:street":"Handelswg",
    "iso:country":"NL",
    "sg:address":"Handelswg 8",
    "sg:city":"Hasselt",
    "sg:orig_category":"Babykleding - Fabrieken En Groothandel",
    "sg:phone":"+31 38 355 6552",
    "sg:postcode":"8061 RL",
    "sg:province":"NL.08",
    "wof:name":"B? Bi B? Int Bv",
    "wof:placetype":"venue"
},
  "geometry": {"coordinates":[6.087147,52.580326],"type":"Point"}
}