{
  "type": "Feature",
  "properties": {
    "addr:full":"Lange Elisabethstraat 37 Utrecht Utrecht 3511 JB",
    "addr:housenumber":"37",
    "addr:postcode":"3511 jb",
    "addr:street":"Lange Elisabethstraat",
    "iso:country":"NL",
    "sg:address":"Lange Elisabethstraat 37",
    "sg:city":"Utrecht",
    "sg:orig_category":"Schoenen",
    "sg:phone":"+31 30 231 9528",
    "sg:postcode":"3511 JB",
    "sg:province":"Utrecht",
    "wof:name":"Fooks Bv",
    "wof:placetype":"venue"
},
  "geometry": {"coordinates":[5.115527,52.09169],"type":"Point"}
}