{
  "type": "Feature",
  "properties": {
    "iso:country":"NL",
    "sg:address":"Schans 25",
    "sg:city":"Lemmer",
    "sg:orig_category":"Medische Apparatuur And Prothesen Fab",
    "sg:phone":"+31 514 563 112",
    "sg:postcode":"8531 DV",
    "sg:province":"Provincie Friesland",
    "wof:name":"Tandtechnisch Laboratorium O.De Vries",
    "wof:placetype":"venue"
},
  "geometry": {"coordinates":[5.713887,52.843334],"type":"Point"}
}