{
  "type": "Feature",
  "properties": {
    "addr:full":"Schans 25 Lemmer Provincie Friesland 8531 DV",
    "addr:housenumber":"25",
    "addr:postcode":"8531",
    "addr:street":"Schans;Provincie Friesland",
    "iso:country":"NL",
    "sg:address":"Schans 25",
    "sg:city":"Lemmer",
    "sg:orig_category":"Medische Apparatuur And Prothesen Fab",
    "sg:phone":"+31 514 563 112",
    "sg:postcode":"8531 DV",
    "sg:province":"Provincie Friesland",
    "wof:name":"Tandtechnisch Laboratorium O.De Vries",
    "wof:placetype":"venue"
},
  "geometry": {"coordinates":[5.713887,52.843334],"type":"Point"}
}