{
  "type": "Feature",
  "properties": {
    "addr:full":"De Kar 34 Apeldoorn Gelderland 7325  W",
    "addr:housenumber":"34;7325",
    "addr:street":"De Kar;Gelderland;W",
    "iso:country":"NL",
    "sg:address":"De Kar 34",
    "sg:city":"Apeldoorn",
    "sg:orig_category":"Fietshandelaren",
    "sg:phone":"+31 55 521 4196",
    "sg:postcode":"7325  W",
    "sg:province":"Gelderland",
    "wof:name":"Charles Timmer Tweewielers",
    "wof:placetype":"venue"
},
  "geometry": {"coordinates":[6.05157,52.18961],"type":"Point"}
}