{
  "type": "Feature",
  "properties": {
    "iso:country":"NL",
    "sg:address":"Ter Apelkanaal West 75",
    "sg:city":"Ter Apelkanaal",
    "sg:orig_category":"Binnenhuisarchitecten",
    "sg:phone":"+31 599 417 602",
    "sg:postcode":"9563 PC",
    "sg:province":"Groningen",
    "wof:name":"J.P. Lissauer",
    "wof:placetype":"venue"
},
  "geometry": {"coordinates":[7.047762,52.907932],"type":"Point"}
}