{
  "type": "Feature",
  "properties": {
    "iso:country":"NL",
    "sg:address":"Voltairestraat 36",
    "sg:city":"Venlo",
    "sg:orig_category":"Technische Studies And Onderzoek",
    "sg:phone":"+31 77 382 4407",
    "sg:postcode":"5924 EH",
    "sg:province":"Limburg",
    "wof:name":"M.P.A. Coenen, Gereedschapkonstrukteur",
    "wof:placetype":"venue"
},
  "geometry": {"coordinates":[6.129832,51.364559],"type":"Point"}
}