{
  "type": "Feature",
  "properties": {
    "addr:full":"Fred Van Eedenstraat 3 Almelo Overijssel 7606 BH",
    "addr:housenumber":"3",
    "addr:postcode":"7606 bh",
    "addr:street":"Eedenstraat",
    "iso:country":"NL",
    "sg:address":"Fred Van Eedenstraat 3",
    "sg:city":"Almelo",
    "sg:orig_category":"Meubelzaken, Woning- And Keukeninrichting",
    "sg:phone":"+31 546 852 600",
    "sg:postcode":"7606 BH",
    "sg:province":"Overijssel",
    "wof:name":"Tex Style Garden Bv",
    "wof:placetype":"venue"
},
  "geometry": {"coordinates":[6.664543,52.354954],"type":"Point"}
}