{
  "type": "Feature",
  "properties": {
    "iso:country":"NL",
    "sg:address":"Hoofdstraat 118",
    "sg:city":"Posterholt",
    "sg:orig_category":"Juweliers",
    "sg:phone":"+31 475 403 235",
    "sg:postcode":"6061 CG",
    "sg:province":"Limburg",
    "wof:name":"Juwelier De Goudsmid I.L.P.C. Scholten-M",
    "wof:placetype":"venue"
},
  "geometry": {"coordinates":[6.0364351273,51.1217193604],"type":"Point"}
}