{
  "type": "Feature",
  "properties": {
    "addr:full":"Industriewg 104 Zutphen Gelderland 7202 CB",
    "addr:housenumber":"104",
    "addr:postcode":"7202 cb",
    "addr:street":"Gelderland",
    "iso:country":"NL",
    "sg:address":"Industriewg 104",
    "sg:city":"Zutphen",
    "sg:orig_category":"Betonwerken",
    "sg:phone":"+31 575 515 700",
    "sg:postcode":"7202 CB",
    "sg:province":"Gelderland",
    "wof:name":"Edese Beton Centr Ebc Bv",
    "wof:placetype":"venue"
},
  "geometry": {"coordinates":[6.198519,52.154713],"type":"Point"}
}