{
  "type": "Feature",
  "properties": {
    "addr:full":"Zwollew 5 Gouda Zuid-Holland 2803 PS",
    "addr:housenumber":"5",
    "addr:postcode":"2803 ps",
    "addr:street":"Zwollew",
    "iso:country":"NL",
    "sg:address":"Zwollew 5",
    "sg:city":"Gouda",
    "sg:orig_category":"Warmtetechniek",
    "sg:phone":"+31 182 556 222",
    "sg:postcode":"2803 PS",
    "sg:province":"Zuid-Holland",
    "wof:name":"Eclipse Bv",
    "wof:placetype":"venue"
},
  "geometry": {"coordinates":[4.677295208,52.0232505798],"type":"Point"}
}