{
  "type": "Feature",
  "properties": {
    "iso:country":"NL",
    "sg:address":"Begijnenstraat 22",
    "sg:city":"Beverwijk",
    "sg:orig_category":"Huishoudapparatuur, Televisies And Radio'S",
    "sg:phone":"+31 251 226 292",
    "sg:postcode":"1941 BS",
    "sg:province":"Noord-Holland",
    "wof:name":"De Radiodokter Beverwijk Bv",
    "wof:placetype":"venue"
},
  "geometry": {"coordinates":[4.656729,52.482395],"type":"Point"}
}