{
  "type": "Feature",
  "properties": {
    "iso:country":"NL",
    "sg:address":"Ir Wagterstr 10",
    "sg:city":"Boxmeer",
    "sg:orig_category":"Grafische Machines",
    "sg:phone":"+31 485 597 111",
    "sg:postcode":"5831 AZ",
    "sg:province":"Noord-Brabant",
    "wof:name":"Heidelberg Contiweb Bv",
    "wof:placetype":"venue"
},
  "geometry": {"coordinates":[5.932189,51.641499],"type":"Point"}
}