{
  "type": "Feature",
  "properties": {
    "addr:full":"Boomstraat 27 Terschelling West Provincie Friesland 8881 BS",
    "addr:housenumber":"27",
    "addr:postcode":"8881 bs",
    "addr:street":"Boomstraat;Friesland",
    "iso:country":"NL",
    "sg:address":"Boomstraat 27",
    "sg:city":"Terschelling West",
    "sg:orig_category":"Boekenuitgeverijen",
    "sg:phone":"+31 562 442 098",
    "sg:postcode":"8881 BS",
    "sg:province":"Provincie Friesland",
    "wof:name":"Boekhandel Funke",
    "wof:placetype":"venue"
},
  "geometry": {"coordinates":[5.215891,53.360523],"type":"Point"}
}