{
  "type": "Feature",
  "properties": {
    "addr:full":"Speelbrinkwg 34 T Harde Gelderland 8084 CH",
    "addr:housenumber":"34",
    "addr:postcode":"8084",
    "addr:street":"Speelbrinkwg",
    "iso:country":"NL",
    "sg:address":"Speelbrinkwg 34",
    "sg:city":"T Harde",
    "sg:orig_category":"Onderhoudswerken",
    "sg:phone":"+31 6 22269505",
    "sg:postcode":"8084 CH",
    "sg:province":"Gelderland",
    "wof:name":"Brevoord",
    "wof:placetype":"venue"
},
  "geometry": {"coordinates":[5.879301,52.411919],"type":"Point"}
}