{
  "type": "Feature",
  "properties": {
    "addr:full":"Rhederwg 44 Bellingwolde Groningen 9695 CE",
    "addr:housenumber":"44",
    "addr:postcode":"9695 ce",
    "addr:street":"Rhederwg",
    "iso:country":"NL",
    "sg:address":"Rhederwg 44",
    "sg:city":"Bellingwolde",
    "sg:classifiers":[
        {
            "category":"Personal",
            "subcategory":"Nail Salon",
            "type":"Services"
        }
    ],
    "sg:phone":"+31 597 531 987",
    "sg:postcode":"9695 CE",
    "sg:province":"Groningen",
    "sg:tags":[
        "pedicure"
    ],
    "wof:name":"Egges-Zwinderman, M G",
    "wof:placetype":"venue"
},
  "geometry": {"coordinates":[7.151276,53.098385],"type":"Point"}
}