{
  "type": "Feature",
  "properties": {
    "addr:full":"Industriewg 14 Harlingen Friesland 8861 VH",
    "addr:housenumber":"14",
    "addr:postcode":"8861 vh",
    "addr:street":"Industriewg",
    "iso:country":"NL",
    "sg:address":"Industriewg 14",
    "sg:city":"Harlingen",
    "sg:orig_category":"Margarine, Olie En Vet - Industrie",
    "sg:phone":"+31 517 418 500",
    "sg:postcode":"8861 VH",
    "sg:province":"Friesland",
    "wof:name":"Smilde Bv",
    "wof:placetype":"venue"
},
  "geometry": {"coordinates":[5.435085,53.179359],"type":"Point"}
}