{
  "type": "Feature",
  "properties": {
    "addr:full":"Dollard 296 Drachten Friesland 9204 CZ",
    "addr:housenumber":"296",
    "addr:postcode":"9204",
    "addr:street":"Dollard",
    "iso:country":"NL",
    "sg:address":"Dollard 296",
    "sg:city":"Drachten",
    "sg:orig_category":"Banken",
    "sg:phone":"+31 512 511 144",
    "sg:postcode":"9204 CZ",
    "sg:province":"Friesland",
    "wof:name":"Regio Bank",
    "wof:placetype":"venue"
},
  "geometry": {"coordinates":[6.074356,53.09716],"type":"Point"}
}