{
  "type": "Feature",
  "properties": {
    "addr:full":"Hoofdstr 15 Heeswyk Dinther Noord-Brabant 5473 AN",
    "addr:housenumber":"15;dinther",
    "addr:postcode":"5473 an",
    "addr:street":"Hoofdstr",
    "iso:country":"NL",
    "sg:address":"Hoofdstr 15",
    "sg:city":"Heeswyk Dinther",
    "sg:orig_category":"Fietsen En Bromfietsen",
    "sg:phone":"+31 413 291 640",
    "sg:postcode":"5473 AN",
    "sg:province":"Noord-Brabant",
    "sg:website":"http://www.bikers-heeswijk.nl",
    "wof:name":"Bikers",
    "wof:placetype":"venue"
},
  "geometry": {"coordinates":[5.471602,51.649708],"type":"Point"}
}