{
  "type": "Feature",
  "properties": {
    "addr:full":"Flora 4 Deventer NL.08 7422 LL",
    "addr:housenumber":"4;nl.08",
    "addr:postcode":"7422 ll",
    "addr:street":"Flora",
    "iso:country":"NL",
    "sg:address":"Flora 4",
    "sg:city":"Deventer",
    "sg:classifiers":[
        {
            "category":"Communications",
            "subcategory":"Television Station",
            "type":"Services"
        }
    ],
    "sg:phone":"+31 570 650 202",
    "sg:postcode":"7422 LL",
    "sg:province":"NL.08",
    "sg:tags":[
        "video",
        "audio",
        "verhuur"
    ],
    "wof:name":"Videotheek De Enk",
    "wof:placetype":"venue"
},
  "geometry": {"coordinates":[6.216587,52.247791],"type":"Point"}
}