{
  "type": "Feature",
  "properties": {
    "addr:full":"Diemermere 15 Amsterdam Noord-Holland 1112 TB",
    "addr:housenumber":"15",
    "addr:postcode":"1112 tb",
    "addr:street":"Diemermere",
    "iso:country":"NL",
    "sg:address":"Diemermere 15",
    "sg:city":"Amsterdam",
    "sg:orig_category":"Werving And Selectie Van Tijdelijk Personeel And Uitzendkantoren",
    "sg:phone":"+31 900 7002542",
    "sg:postcode":"1112 TB",
    "sg:province":"Noord-Holland",
    "wof:name":"Tempo Team",
    "wof:placetype":"venue"
},
  "geometry": {"coordinates":[4.9626998901,52.3313903809],"type":"Point"}
}