{
  "type": "Feature",
  "properties": {
    "addr:full":"Adelaarsln 9 Apeldoorn Gelderland 7331 AW",
    "addr:housenumber":"9",
    "addr:postcode":"7331 aw",
    "addr:street":"Adelaarsln;Gelderland",
    "iso:country":"NL",
    "sg:address":"Adelaarsln 9",
    "sg:city":"Apeldoorn",
    "sg:orig_category":"Loodgieters",
    "sg:phone":"+31 55 533 8561",
    "sg:postcode":"7331 AW",
    "sg:province":"Gelderland",
    "sg:website":"http://www.tomassen.net",
    "wof:name":"Tomassen Totaal, Installateur",
    "wof:placetype":"venue"
},
  "geometry": {"coordinates":[5.964108,52.205032],"type":"Point"}
}