{
  "type": "Feature",
  "properties": {
    "iso:country":"NL",
    "sg:address":"Kaldenkerkerwg 34",
    "sg:city":"Venlo",
    "sg:orig_category":"Orthopedisch Schoeisel",
    "sg:phone":"+31 77 351 7258",
    "sg:postcode":"5913 AE",
    "sg:province":"Limburg",
    "wof:name":"Reumkens Orthopedie",
    "wof:placetype":"venue"
},
  "geometry": {"coordinates":[6.1750240326,51.363193512],"type":"Point"}
}