{
  "type": "Feature",
  "properties": {
    "addr:full":"Benoordenhoutsewg 279 S Gravenhage Zuid-Holland 2596 BJ",
    "addr:housenumber":"279;gravenhage",
    "addr:postcode":"2596 bj",
    "addr:street":"S",
    "iso:country":"NL",
    "sg:address":"Benoordenhoutsewg 279",
    "sg:city":"S Gravenhage",
    "sg:orig_category":"Begrafenisverzorging",
    "sg:phone":"+31 70 324 0077",
    "sg:postcode":"2596 BJ",
    "sg:province":"Zuid-Holland",
    "wof:name":"Clingendaelhuys, 'T",
    "wof:placetype":"venue"
},
  "geometry": {"coordinates":[4.31846,52.093311],"type":"Point"}
}