{
  "type": "Feature",
  "properties": {
    "addr:full":"Pater Kustersweg 8 Cadier En Keer Limburg 6267 NL",
    "addr:housenumber":"8",
    "addr:postcode":"6267 nl",
    "addr:street":"Pater Kustersweg",
    "iso:country":"NL",
    "sg:address":"Pater Kustersweg 8",
    "sg:city":"Cadier En Keer",
    "sg:orig_category":"Kinderopvang Behalve Thuis",
    "sg:phone":"+31 43 407 7100",
    "sg:postcode":"6267 NL",
    "sg:province":"Limburg",
    "wof:name":"Stichting Jeugdzorg St. Joseph",
    "wof:placetype":"venue"
},
  "geometry": {"coordinates":[5.76826,50.826172],"type":"Point"}
}