{
  "type": "Feature",
  "properties": {
    "addr:full":"V Eysden Vinkstr 123 Rotterdam Zuid-Holland 3066 JB",
    "addr:housenumber":"123",
    "addr:postcode":"3066 jb",
    "addr:street":"V;Vinkstr",
    "iso:country":"NL",
    "sg:address":"V Eysden Vinkstr 123",
    "sg:city":"Rotterdam",
    "sg:orig_category":"Farmaceutische Industrie En Groothandel",
    "sg:phone":"+31 10 421 5102",
    "sg:postcode":"3066 JB",
    "sg:province":"Zuid-Holland",
    "wof:name":"Jaquet, J",
    "wof:placetype":"venue"
},
  "geometry": {"coordinates":[4.55005,51.934711],"type":"Point"}
}