{
  "type": "Feature",
  "properties": {
    "addr:full":"Arena Boulev 42 Amsterdam Zuidoost Noord-Holland 1101 DJ",
    "addr:housenumber":"42",
    "addr:postcode":"zuidoost;1101 dj",
    "addr:street":"Boulev",
    "iso:country":"NL",
    "sg:address":"Arena Boulev 42",
    "sg:city":"Amsterdam Zuidoost",
    "sg:orig_category":"Verlichting",
    "sg:phone":"+31 20 365 9409",
    "sg:postcode":"1101 DJ",
    "sg:province":"Noord-Holland",
    "wof:name":"Heuvel Bv, Van Den",
    "wof:placetype":"venue"
},
  "geometry": {"coordinates":[4.94054,52.312859],"type":"Point"}
}