{
  "type": "Feature",
  "properties": {
    "iso:country":"NL",
    "sg:address":"Singelstr 15",
    "sg:city":"Deventer",
    "sg:orig_category":"Adviesbureaus",
    "sg:phone":"+31 570 617 902",
    "sg:postcode":"7411 HP",
    "sg:province":"Overijssel",
    "wof:name":"Attema En Van De Wetering",
    "wof:placetype":"venue"
},
  "geometry": {"coordinates":[6.158942,52.255508],"type":"Point"}
}