{
  "type": "Feature",
  "properties": {
    "addr:full":"Vyverhof 8 Voorburg Zuid-Holland 2271 GP",
    "addr:housenumber":"8",
    "addr:postcode":"2271 gp",
    "addr:street":"Vyverhof",
    "iso:country":"NL",
    "sg:address":"Vyverhof 8",
    "sg:city":"Voorburg",
    "sg:orig_category":"Adviesbureaus Bedrijfsorganisatie",
    "sg:phone":"+31 70 386 7212",
    "sg:postcode":"2271 GP",
    "sg:province":"Zuid-Holland",
    "wof:name":"Engelberts",
    "wof:placetype":"venue"
},
  "geometry": {"coordinates":[4.374519,52.077625],"type":"Point"}
}