{
  "type": "Feature",
  "properties": {
    "iso:country":"NL",
    "sg:address":"Veldzigt 6",
    "sg:city":"De Meern",
    "sg:orig_category":"Metaalwaren - Groothandel",
    "sg:phone":"+31 30 666 6868",
    "sg:postcode":"3454 PW",
    "sg:province":"Utrecht",
    "wof:name":"Rokatec Bv",
    "wof:placetype":"venue"
},
  "geometry": {"coordinates":[5.048615,52.073158],"type":"Point"}
}