{
  "type": "Feature",
  "properties": {
    "iso:country":"NL",
    "sg:address":"Steurweg 26",
    "sg:city":"Hoogvliet Rt",
    "sg:classifiers":[
        {
            "category":"Fast Food",
            "type":"Food & Drink"
        }
    ],
    "sg:phone":"+31 10 438 6924",
    "sg:postcode":"3192 AH",
    "sg:province":"South Holland",
    "sg:tags":[
        "afhaal",
        "restaurant"
    ],
    "wof:name":"Snackbar Victoria",
    "wof:placetype":"venue"
},
  "geometry": {"coordinates":[4.351724,51.856575],"type":"Point"}
}