{
  "type": "Feature",
  "properties": {
    "addr:full":"Wildhage 26 Teteringen Noord-Brabant 4847 CR",
    "addr:housenumber":"26",
    "addr:postcode":"4847 cr",
    "addr:street":"Wildhage",
    "iso:country":"NL",
    "sg:address":"Wildhage 26",
    "sg:city":"Teteringen",
    "sg:orig_category":"Pensioenfondsen",
    "sg:phone":"+31 76 587 9387",
    "sg:postcode":"4847 CR",
    "sg:province":"Noord-Brabant",
    "wof:name":"Sophianna Bv",
    "wof:placetype":"venue"
},
  "geometry": {"coordinates":[4.821236,51.602661],"type":"Point"}
}