{
  "type": "Feature",
  "properties": {
    "addr:full":"Einsteinstr 37 Veenendaal Utrecht 3902 HN",
    "addr:housenumber":"37",
    "addr:postcode":"3902 hn",
    "addr:street":"Einsteinstr",
    "iso:country":"NL",
    "sg:address":"Einsteinstr 37",
    "sg:city":"Veenendaal",
    "sg:orig_category":"Grafmonumenten",
    "sg:phone":"+31 318 512 051",
    "sg:postcode":"3902 HN",
    "sg:province":"Utrecht",
    "wof:name":"Pol & Zoon",
    "wof:placetype":"venue"
},
  "geometry": {"coordinates":[5.570023,52.039738],"type":"Point"}
}