{
  "type": "Feature",
  "properties": {
    "addr:full":"Markt 2 Maassluis South Holland 3142 GG",
    "addr:housenumber":"2",
    "addr:postcode":"3142 gg",
    "addr:street":"Markt",
    "iso:country":"NL",
    "sg:address":"Markt 2",
    "sg:city":"Maassluis",
    "sg:orig_category":"Kinderkleding",
    "sg:phone":"+31 10 590 3253",
    "sg:postcode":"3142 GG",
    "sg:province":"South Holland",
    "wof:name":"Marber",
    "wof:placetype":"venue"
},
  "geometry": {"coordinates":[4.254316,51.921864],"type":"Point"}
}