{
  "type": "Feature",
  "properties": {
    "addr:full":"Het Hogerhuis 10 Dronten Flevoland 8251 LZ",
    "addr:housenumber":"10",
    "addr:postcode":"8251 lz",
    "addr:street":"Het Hogerhuis;Flevoland",
    "iso:country":"NL",
    "sg:address":"Het Hogerhuis 10",
    "sg:city":"Dronten",
    "sg:orig_category":"Verenigingsgebouwen",
    "sg:phone":"+31 321 318 917",
    "sg:postcode":"8251 LZ",
    "sg:province":"Flevoland",
    "wof:name":"Lagerhuis, 'T",
    "wof:placetype":"venue"
},
  "geometry": {"coordinates":[5.730265,52.519524],"type":"Point"}
}