{
  "type": "Feature",
  "properties": {
    "addr:full":"Fonteinstr 37 Leerdam South Holland 4141 CE",
    "addr:housenumber":"37",
    "addr:postcode":"4141 ce",
    "addr:street":"Fonteinstr",
    "iso:country":"NL",
    "sg:address":"Fonteinstr 37",
    "sg:city":"Leerdam",
    "sg:orig_category":"Bloemen En Planten",
    "sg:phone":"+31 345 632 322",
    "sg:postcode":"4141 CE",
    "sg:province":"South Holland",
    "wof:name":"Boterbloem, De",
    "wof:placetype":"venue"
},
  "geometry": {"coordinates":[5.093128,51.892265],"type":"Point"}
}