{
  "type": "Feature",
  "properties": {
    "addr:full":"Onsenoortsestr 47 Nieuwkuyk North Brabant 5253 AA",
    "addr:housenumber":"47",
    "addr:postcode":"5253 aa",
    "addr:street":"Onsenoortsestr",
    "iso:country":"NL",
    "sg:address":"Onsenoortsestr 47",
    "sg:city":"Nieuwkuyk",
    "sg:orig_category":"Autorijscholen",
    "sg:phone":"+31 73 511 4408",
    "sg:postcode":"5253 AA",
    "sg:province":"North Brabant",
    "wof:name":"Delft, C J M Van",
    "wof:placetype":"venue"
},
  "geometry": {"coordinates":[5.190089,51.693001],"type":"Point"}
}