{
  "type": "Feature",
  "properties": {
    "iso:country":"NL",
    "sg:address":"Bachlaan 158",
    "sg:city":"Zwolle",
    "sg:classifiers":[
        {
            "category":"Education",
            "subcategory":"Preschool",
            "type":"Public Place"
        }
    ],
    "sg:phone":"+31 38 422 5815",
    "sg:postcode":"8031 HL",
    "sg:province":"NL.08",
    "sg:tags":[
        "kleuteronderwijs",
        "basis-"
    ],
    "wof:name":"Openbare Basisschool Peter Van Anrooy",
    "wof:placetype":"venue"
},
  "geometry": {"coordinates":[6.08817,52.527168],"type":"Point"}
}