{
  "type": "Feature",
  "properties": {
    "addr:full":"Oostsingel 2 Goes Zeeland 4461 KC",
    "addr:housenumber":"2",
    "addr:postcode":"4461 kc",
    "addr:street":"Oostsingel",
    "iso:country":"NL",
    "sg:address":"Oostsingel 2",
    "sg:city":"Goes",
    "sg:orig_category":"Overheidsdiensten",
    "sg:phone":"+31 113 249 600",
    "sg:postcode":"4461 KC",
    "sg:province":"Zeeland",
    "wof:name":"Gemeente Goes",
    "wof:placetype":"venue"
},
  "geometry": {"coordinates":[-83.9141693115,39.7688331604],"type":"Point"}
}