{
  "type": "Feature",
  "properties": {
    "addr:full":"Volberthorst 23 Enschede Overijssel 7531 DX",
    "addr:housenumber":"23",
    "addr:postcode":"7531 dx",
    "addr:street":"Volberthorst",
    "iso:country":"NL",
    "sg:address":"Volberthorst 23",
    "sg:city":"Enschede",
    "sg:orig_category":"Boekenuitgeverijen",
    "sg:phone":"+31 53 433 7058",
    "sg:postcode":"7531 DX",
    "sg:province":"Overijssel",
    "wof:name":"De Hondsrug Pers",
    "wof:placetype":"venue"
},
  "geometry": {"coordinates":[6.926233,52.226173],"type":"Point"}
}