{
  "type": "Feature",
  "properties": {
    "addr:full":"Diepsmeerweg 54 Warmenhuizen Noord-Holland 1749 AZ",
    "addr:housenumber":"54",
    "addr:postcode":"1749 az",
    "addr:street":"Diepsmeerweg",
    "iso:country":"NL",
    "sg:address":"Diepsmeerweg 54",
    "sg:city":"Warmenhuizen",
    "sg:orig_category":"Verhuur Audiovisuele Apparatuur",
    "sg:phone":"+31 226 394 785",
    "sg:postcode":"1749 AZ",
    "sg:province":"Noord-Holland",
    "wof:name":"A & R",
    "wof:placetype":"venue"
},
  "geometry": {"coordinates":[-111.93034400000001,34.168091],"type":"Point"}
}