{
  "type": "Feature",
  "properties": {
    "addr:full":"Dalwagensewg 12 Opheusden Gelderland 4043 MX",
    "addr:housenumber":"12",
    "addr:postcode":"4043 mx",
    "addr:street":"Dalwagensewg;Gelderland",
    "iso:country":"NL",
    "sg:address":"Dalwagensewg 12",
    "sg:city":"Opheusden",
    "sg:orig_category":"Hoeden",
    "sg:phone":"+31 488 441 744",
    "sg:postcode":"4043 MX",
    "sg:province":"Gelderland",
    "wof:name":"Arina",
    "wof:placetype":"venue"
},
  "geometry": {"coordinates":[5.633749,51.93269],"type":"Point"}
}