{
  "type": "Feature",
  "properties": {
    "addr:full":"Provenierssngl 29B Rotterdam Zuid-Holland 3033 EE",
    "addr:housenumber":"29b",
    "addr:postcode":"3033 ee",
    "addr:street":"Provenierssngl",
    "iso:country":"NL",
    "sg:address":"Provenierssngl 29B",
    "sg:city":"Rotterdam",
    "sg:orig_category":"Pottenbakkerijen",
    "sg:phone":"+31 10 465 3983",
    "sg:postcode":"3033 EE",
    "sg:province":"Zuid-Holland",
    "wof:name":"Frogs",
    "wof:placetype":"venue"
},
  "geometry": {"coordinates":[4.471929,51.927914],"type":"Point"}
}