{
  "type": "Feature",
  "properties": {
    "iso:country":"NL",
    "sg:address":"Hogenoord 1",
    "sg:city":"Utrecht",
    "sg:classifiers":[
        {
            "category":"Food & Beverages",
            "subcategory":"Bakery",
            "type":"Retail Goods"
        }
    ],
    "sg:phone":"+31 30 233 6200",
    "sg:postcode":"3513 GX",
    "sg:province":"Utrecht",
    "sg:tags":[
        "brood",
        "en",
        "banket"
    ],
    "wof:name":"Kamps Nederland Bv",
    "wof:placetype":"venue"
},
  "geometry": {"coordinates":[5.1115,52.100449],"type":"Point"}
}