{
  "type": "Feature",
  "properties": {
    "iso:country":"NL",
    "sg:address":"R Hartstr 32",
    "sg:city":"Amsterdam",
    "sg:orig_category":"Hengelsportartikelen",
    "sg:phone":"+31 20 676 4020",
    "sg:postcode":"1071 VK",
    "sg:province":"North Holland",
    "wof:name":"Schreiner En Zn, Jan",
    "wof:placetype":"venue"
},
  "geometry": {"coordinates":[4.883636,52.352299],"type":"Point"}
}