{
  "type": "Feature",
  "properties": {
    "addr:full":"Tafelbergdreef 108 Utrecht Utrecht 3564 AD",
    "addr:housenumber":"108",
    "addr:postcode":"3564 ad",
    "addr:street":"Tafelbergdreef",
    "iso:country":"NL",
    "sg:address":"Tafelbergdreef 108",
    "sg:city":"Utrecht",
    "sg:orig_category":"Alternatieve Geneeskunde",
    "sg:phone":"+31 30 261 0225",
    "sg:postcode":"3564 AD",
    "sg:province":"Utrecht",
    "wof:name":"Fysiotherapiepraktijk Tafelbergdreef",
    "wof:placetype":"venue"
},
  "geometry": {"coordinates":[5.109502,52.117256],"type":"Point"}
}