{
  "type": "Feature",
  "properties": {
    "iso:country":"NL",
    "sg:address":"S Mullerpln 20",
    "sg:city":"Rotterdam",
    "sg:orig_category":"Video - Faciliteiten En Producties",
    "sg:phone":"+31 10 425 7477",
    "sg:postcode":"3023 SK",
    "sg:province":"Zuid-Holland",
    "sg:website":"http://www.rbs/group.nl",
    "wof:name":"Picture Plant Bv, The",
    "wof:placetype":"venue"
},
  "geometry": {"coordinates":[4.446947,51.913876],"type":"Point"}
}