{
  "type": "Feature",
  "properties": {
    "iso:country":"NL",
    "sg:address":"Industrieweg 16",
    "sg:city":"Stramproy",
    "sg:orig_category":"Metaalbekleding And -Behandeling",
    "sg:phone":"+31 495 561 781",
    "sg:postcode":"6039 AP",
    "sg:province":"Limburg",
    "wof:name":"Wbm Staalservice Centrum Bv",
    "wof:placetype":"venue"
},
  "geometry": {"coordinates":[5.718828,51.198528],"type":"Point"}
}