{
  "type": "Feature",
  "properties": {
    "iso:country":"NL",
    "sg:address":"Selenakker 1",
    "sg:city":"Tilburg",
    "sg:classifiers":[
        {
            "category":"Home & Garden",
            "subcategory":"Building Materials",
            "type":"Retail Goods"
        }
    ],
    "sg:phone":"+31 13 570 5435",
    "sg:postcode":"5047 TP",
    "sg:province":"Noord-Brabant",
    "sg:tags":[
        "hout",
        "en",
        "board",
        "triplex"
    ],
    "sg:website":"http://www.vanbebber.demon.nl",
    "wof:name":"Bebber, Van",
    "wof:placetype":"venue"
},
  "geometry": {"coordinates":[5.028512,51.589531],"type":"Point"}
}