{
  "type": "Feature",
  "properties": {
    "addr:full":"Marconistr 34 Heerhugowaard Noord-Holland 1704 RG",
    "addr:housenumber":"34",
    "addr:postcode":"1704 rg",
    "addr:street":"Marconistr",
    "iso:country":"NL",
    "sg:address":"Marconistr 34",
    "sg:city":"Heerhugowaard",
    "sg:orig_category":"Ovenbouw",
    "sg:phone":"+31 72 574 3532",
    "sg:postcode":"1704 RG",
    "sg:province":"Noord-Holland",
    "wof:name":"Dutch Furness Works Bv",
    "wof:placetype":"venue"
},
  "geometry": {"coordinates":[4.8344140053,52.683303833],"type":"Point"}
}