{
  "type": "Feature",
  "properties": {
    "iso:country":"NL",
    "sg:address":"Graafseweg 570",
    "sg:city":"Wijchen",
    "sg:orig_category":"Overheidsdiensten",
    "sg:phone":"+31 24 641 9198",
    "sg:postcode":"6603 CL",
    "sg:province":"Gelderland",
    "wof:name":"Timpe Tampe",
    "wof:placetype":"venue"
},
  "geometry": {"coordinates":[5.759540081,51.8079109192],"type":"Point"}
}