{
  "type": "Feature",
  "properties": {
    "addr:full":"Raadhuisstraat 20-26 Heerhugowaard Noord-Holland 1701 EK",
    "addr:housenumber":"20-26",
    "addr:postcode":"1701 ek",
    "addr:street":"Raadhuisstraat",
    "iso:country":"NL",
    "sg:address":"Raadhuisstraat 20-26",
    "sg:city":"Heerhugowaard",
    "sg:orig_category":"Fruit And Groenten Gh",
    "sg:phone":"+31 72 571 1943",
    "sg:postcode":"1701 EK",
    "sg:province":"Noord-Holland",
    "wof:name":"Het Fruithuis Hoedjes",
    "wof:placetype":"venue"
},
  "geometry": {"coordinates":[4.84479,52.669857],"type":"Point"}
}