{
  "type": "Feature",
  "properties": {
    "iso:country":"NL",
    "sg:address":"S Beckettstr 11",
    "sg:city":"Haarlem",
    "sg:orig_category":"Koeriersdiensten",
    "sg:phone":"+31 23 540 6944",
    "sg:postcode":"2037 MC",
    "sg:province":"North Holland",
    "wof:name":"Stp",
    "wof:placetype":"venue"
},
  "geometry": {"coordinates":[4.66736,52.357822],"type":"Point"}
}