{
  "type": "Feature",
  "properties": {
    "addr:full":"Hugo De Vrieslaan 85 Amsterdam Noord-Holland 1097 EH",
    "addr:housenumber":"85",
    "addr:postcode":"1097 eh",
    "addr:street":"Hugo De Vrieslaan",
    "iso:country":"NL",
    "sg:address":"Hugo De Vrieslaan 85",
    "sg:city":"Amsterdam",
    "sg:orig_category":"Apothekers",
    "sg:phone":"+31 20 462 0988",
    "sg:postcode":"1097 EH",
    "sg:province":"Noord-Holland",
    "wof:name":"Apotheek Mulkens",
    "wof:placetype":"venue"
},
  "geometry": {"coordinates":[4.932062,52.348675],"type":"Point"}
}