{
  "type": "Feature",
  "properties": {
    "addr:full":"St. Annastraat 146 Nijmegen Gelderland 6524 ER",
    "addr:housenumber":"146",
    "addr:postcode":"6524 er",
    "addr:street":"St. Annastraat;Gelderland",
    "iso:country":"NL",
    "sg:address":"St. Annastraat 146",
    "sg:city":"Nijmegen",
    "sg:orig_category":"Hypotheken And Hypotheekbanken",
    "sg:phone":"+31 24 360 2149",
    "sg:postcode":"6524 ER",
    "sg:province":"Gelderland",
    "wof:name":"M.J.D. Advies",
    "wof:placetype":"venue"
},
  "geometry": {"coordinates":[5.858834,51.834869],"type":"Point"}
}