{
  "type": "Feature",
  "properties": {
    "addr:full":"J De Raadtkd 31 Hoogvliet Rt Zuid-Holland 3191 VJ",
    "addr:housenumber":"31",
    "addr:postcode":"rt;3191 vj",
    "addr:street":"J De Raadtkd",
    "iso:country":"NL",
    "sg:address":"J De Raadtkd 31",
    "sg:city":"Hoogvliet Rt",
    "sg:orig_category":"Beeldende Kunstenaars",
    "sg:phone":"+31 10 416 4999",
    "sg:postcode":"3191 VJ",
    "sg:province":"Zuid-Holland",
    "wof:name":"Ren? Vaandrager",
    "wof:placetype":"venue"
},
  "geometry": {"coordinates":[4.3655,51.861012],"type":"Point"}
}