{
  "type": "Feature",
  "properties": {
    "addr:full":"Ravenswade 54 Bis Nieuwegein Utrecht 3439 LD",
    "addr:housenumber":"54 bis",
    "addr:postcode":"3439 ld",
    "addr:street":"Ravenswade",
    "iso:country":"NL",
    "sg:address":"Ravenswade 54 Bis",
    "sg:city":"Nieuwegein",
    "sg:orig_category":"Film-, Tv- And Videoproductie",
    "sg:phone":"+31 30 287 0939",
    "sg:postcode":"3439 LD",
    "sg:province":"Utrecht",
    "wof:name":"Revinco B.V.",
    "wof:placetype":"venue"
},
  "geometry": {"coordinates":[5.117108,52.050915],"type":"Point"}
}