{
  "type": "Feature",
  "properties": {
    "addr:full":"Gorecht O 153H Hoogezand Groningen 9603 AE",
    "addr:housenumber":"153h",
    "addr:postcode":"9603 ae",
    "iso:country":"NL",
    "sg:address":"Gorecht O 153H",
    "sg:city":"Hoogezand",
    "sg:orig_category":"Huishoudelijke Apparaten En Artikelen",
    "sg:phone":"+31 598 350 043",
    "sg:postcode":"9603 AE",
    "sg:province":"Groningen",
    "wof:name":"Blokker Bv",
    "wof:placetype":"venue"
},
  "geometry": {"coordinates":[6.758379,53.154594],"type":"Point"}
}