{
  "type": "Feature",
  "properties": {
    "addr:full":"Gietery 28B Noordwykerhout South Holland 2211 XK",
    "addr:housenumber":"28b noordwykerhout",
    "addr:postcode":"2211 xk",
    "addr:street":"Gietery",
    "iso:country":"NL",
    "sg:address":"Gietery 28B",
    "sg:city":"Noordwykerhout",
    "sg:orig_category":"Grondboringen En Bronbemalingen",
    "sg:phone":"+31 252 374 522",
    "sg:postcode":"2211 XK",
    "sg:province":"South Holland",
    "sg:website":"http://www.idasco.com",
    "wof:name":"Idasco",
    "wof:placetype":"venue"
},
  "geometry": {"coordinates":[4.491886,52.248573],"type":"Point"}
}