{
  "type": "Feature",
  "properties": {
    "addr:full":"Zweringweg 224 Enschede NL.08 7545 DA",
    "addr:housenumber":"224",
    "addr:postcode":"7545 da",
    "addr:street":"Zweringweg",
    "iso:country":"NL",
    "sg:address":"Zweringweg 224",
    "sg:city":"Enschede",
    "sg:classifiers":[
        {
            "category":"Fast Food",
            "type":"Food & Drink"
        }
    ],
    "sg:phone":"+31 53 431 1614",
    "sg:postcode":"7545 DA",
    "sg:province":"NL.08",
    "sg:tags":[
        "afhaal",
        "restaurant"
    ],
    "wof:name":"Vof Cafetaria Stadsveld",
    "wof:placetype":"venue"
},
  "geometry": {"coordinates":[6.862925,52.210361],"type":"Point"}
}