{
  "type": "Feature",
  "properties": {
    "iso:country":"NL",
    "sg:address":"T Eiland 22",
    "sg:city":"Warmenhuizen",
    "sg:orig_category":"Vertaal- And Tolkenbureaus",
    "sg:phone":"+31 226 393 760",
    "sg:postcode":"1749 GA",
    "sg:province":"Georgia",
    "wof:name":"Delis P",
    "wof:placetype":"venue"
},
  "geometry": {"coordinates":[-83.222931,32.678131],"type":"Point"}
}