{
  "type": "Feature",
  "properties": {
    "iso:country":"NL",
    "sg:address":"Parallelweg 3",
    "sg:city":"Opheusden",
    "sg:orig_category":"Boomkwekerijen",
    "sg:phone":"+31 488 441 819",
    "sg:postcode":"4043 KG",
    "sg:province":"Gelderland",
    "wof:name":"Fa. G. Schaap En Zoon",
    "wof:placetype":"venue"
},
  "geometry": {"coordinates":[5.633235,51.926163],"type":"Point"}
}