{
  "type": "Feature",
  "properties": {
    "addr:full":"Narcisstraat 8 Voorschoten Zuid-Holland 2252 XE",
    "addr:housenumber":"8",
    "addr:postcode":"2252 xe",
    "addr:street":"Narcisstraat",
    "iso:country":"NL",
    "sg:address":"Narcisstraat 8",
    "sg:city":"Voorschoten",
    "sg:orig_category":"Bloemen And Planten",
    "sg:phone":"+31 71 561 0999",
    "sg:postcode":"2252 XE",
    "sg:province":"Zuid-Holland",
    "wof:name":"De Groene Kamer",
    "wof:placetype":"venue"
},
  "geometry": {"coordinates":[4.438731,52.126446],"type":"Point"}
}