{
  "type": "Feature",
  "properties": {
    "iso:country":"NL",
    "sg:address":"Sadatstr 2",
    "sg:city":"Rotterdam",
    "sg:orig_category":"Verloskundigen",
    "sg:phone":"+31 10 456 7119",
    "sg:postcode":"3066 VP",
    "sg:province":"Zuid-Holland",
    "wof:name":"Bovendeert, M C",
    "wof:placetype":"venue"
},
  "geometry": {"coordinates":[4.557959,51.932922],"type":"Point"}
}