{
  "type": "Feature",
  "properties": {
    "addr:full":"Godelindedwstr 34 Bussum North Holland 1402 WP",
    "addr:housenumber":"34",
    "addr:postcode":"1402 wp",
    "addr:street":"Godelindedwstr",
    "iso:country":"NL",
    "sg:address":"Godelindedwstr 34",
    "sg:city":"Bussum",
    "sg:orig_category":"Verenigingen En Stichtingen",
    "sg:phone":"+31 35 692 0199",
    "sg:postcode":"1402 WP",
    "sg:province":"North Holland",
    "wof:name":"Achter De Linde, Wijkcentr",
    "wof:placetype":"venue"
},
  "geometry": {"coordinates":[5.182245,52.274059],"type":"Point"}
}