{
  "type": "Feature",
  "properties": {
    "addr:full":"Hendowg 6-8 Dokkum Provincie Friesland 9101 PC",
    "addr:housenumber":"6-8",
    "addr:postcode":"9101 pc",
    "addr:street":"Hendowg;Provincie Friesland",
    "iso:country":"NL",
    "sg:address":"Hendowg 6-8",
    "sg:city":"Dokkum",
    "sg:orig_category":"Bestratingen",
    "sg:phone":"+31 519 221 527",
    "sg:postcode":"9101 PC",
    "sg:province":"Provincie Friesland",
    "wof:name":"Visser, B J",
    "wof:placetype":"venue"
},
  "geometry": {"coordinates":[5.982145,53.326569],"type":"Point"}
}