{
  "type": "Feature",
  "properties": {
    "addr:full":"Herengr 240 Amsterdam North Holland 1016 BT",
    "addr:housenumber":"240",
    "addr:postcode":"1016 bt",
    "iso:country":"NL",
    "sg:address":"Herengr 240",
    "sg:city":"Amsterdam",
    "sg:orig_category":"Werving En Selectie",
    "sg:phone":"+31 20 422 6200",
    "sg:postcode":"1016 BT",
    "sg:province":"North Holland",
    "sg:website":"http://www.peopledotcom.nl",
    "wof:name":"People Dot Com Bv",
    "wof:placetype":"venue"
},
  "geometry": {"coordinates":[4.8865709305,52.3719215393],"type":"Point"}
}