{
  "type": "Feature",
  "properties": {
    "addr:full":"Bankastr 158 Dordrecht Zuid-Holland 3312 GT",
    "addr:housenumber":"158",
    "addr:postcode":"3312 gt",
    "iso:country":"NL",
    "sg:address":"Bankastr 158",
    "sg:city":"Dordrecht",
    "sg:orig_category":"Bejaarden - Verzorgingstehuizen",
    "sg:phone":"+31 78 614 6488",
    "sg:postcode":"3312 GT",
    "sg:province":"Zuid-Holland",
    "wof:name":"Linde, De",
    "wof:placetype":"venue"
},
  "geometry": {"coordinates":[4.686439,51.807735],"type":"Point"}
}