{
  "type": "Feature",
  "properties": {
    "iso:country":"NL",
    "sg:address":"Vlasdonk 29",
    "sg:city":"Diemen",
    "sg:orig_category":"Glazenwasserijen",
    "sg:phone":"+31 20 695 6014",
    "sg:postcode":"1112 JD",
    "sg:province":"North Holland",
    "wof:name":"Braam Glasrenovatie M",
    "wof:placetype":"venue"
},
  "geometry": {"coordinates":[4.949466,52.336182],"type":"Point"}
}