{
  "type": "Feature",
  "properties": {
    "addr:full":"Laarstraat 19 Geldrop North Brabant 5664 BK",
    "addr:housenumber":"19",
    "addr:postcode":"5664 bk",
    "addr:street":"Laarstraat",
    "iso:country":"NL",
    "sg:address":"Laarstraat 19",
    "sg:city":"Geldrop",
    "sg:orig_category":"Loodgieterswerk, Verwarming And Sanitaire Installaties",
    "sg:phone":"+31 40 286 3739",
    "sg:postcode":"5664 BK",
    "sg:province":"North Brabant",
    "wof:name":"Geldrops Klussenbedrijf Van Der Linden V",
    "wof:placetype":"venue"
},
  "geometry": {"coordinates":[5.556267,51.417789],"type":"Point"}
}