{
  "type": "Feature",
  "properties": {
    "addr:full":"Pastoor Op Heijstraat 26 Venlo Limburg 5912 BT",
    "addr:housenumber":"26",
    "addr:postcode":"5912 bt",
    "addr:street":"Pastoor Op Heijstraat",
    "iso:country":"NL",
    "sg:address":"Pastoor Op Heijstraat 26",
    "sg:city":"Venlo",
    "sg:classifiers":[
        {
            "category":"Education",
            "subcategory":"Preschool",
            "type":"Public Place"
        }
    ],
    "sg:phone":"+31 77 351 7906",
    "sg:postcode":"5912 BT",
    "sg:province":"Limburg",
    "sg:tags":[
        "kleuteronderwijs",
        "basis-"
    ],
    "wof:name":"Basisschool De Verrekijker",
    "wof:placetype":"venue"
},
  "geometry": {"coordinates":[6.162401,51.361969],"type":"Point"}
}