{
  "type": "Feature",
  "properties": {
    "addr:full":"T Zand 22 Utrecht Utrecht 3544 NC",
    "addr:housenumber":"22",
    "addr:postcode":"3544 nc",
    "addr:street":"T Zand",
    "iso:country":"NL",
    "sg:address":"T Zand 22",
    "sg:city":"Utrecht",
    "sg:orig_category":"Bloemen And Planten",
    "sg:phone":"+31 30 666 3140",
    "sg:postcode":"3544 NC",
    "sg:province":"Utrecht",
    "wof:name":"Tuincentrum Rodenburg Bv",
    "wof:placetype":"venue"
},
  "geometry": {"coordinates":[5.044763,52.092999],"type":"Point"}
}