{
  "type": "Feature",
  "properties": {
    "addr:full":"Weerterbos 41 Hoofddorp Noord-Holland 2134 HJ",
    "addr:housenumber":"41",
    "addr:postcode":"2134 hj",
    "addr:street":"Weerterbos",
    "iso:country":"NL",
    "sg:address":"Weerterbos 41",
    "sg:city":"Hoofddorp",
    "sg:orig_category":"Adviesbureaus Bedrijfsorganisatie",
    "sg:phone":"+31 23 565 2473",
    "sg:postcode":"2134 HJ",
    "sg:province":"Noord-Holland",
    "sg:website":"http://www.stormhrmconsult.nl",
    "wof:name":"Hrm Consult",
    "wof:placetype":"venue"
},
  "geometry": {"coordinates":[4.654696,52.316677],"type":"Point"}
}