{
  "type": "Feature",
  "properties": {
    "addr:full":"Fresiastraat 20 Katwijk Zh Zuid-Holland 2223 XA",
    "addr:housenumber":"20",
    "addr:postcode":"2223 xa",
    "addr:street":"Fresiastraat",
    "iso:country":"NL",
    "sg:address":"Fresiastraat 20",
    "sg:city":"Katwijk Zh",
    "sg:orig_category":"Bibliotheken And Openbare Archieven",
    "sg:phone":"+31 71 407 5490",
    "sg:postcode":"2223 XA",
    "sg:province":"Zuid-Holland",
    "wof:name":"Bibliotheek",
    "wof:placetype":"venue"
},
  "geometry": {"coordinates":[4.422709,52.186626],"type":"Point"}
}