{
  "type": "Feature",
  "properties": {
    "iso:country":"NL",
    "sg:address":"Cantersveen 4",
    "sg:city":"Haren Gn",
    "sg:orig_category":"Orthopedagogen",
    "sg:phone":"+31 50 534 7241",
    "sg:postcode":"9753 KK",
    "sg:province":"Groningen",
    "wof:name":"Mkd Jeugdzorg Groningen",
    "wof:placetype":"venue"
},
  "geometry": {"coordinates":[6.6327500343,53.1697387695],"type":"Point"}
}