{
  "type": "Feature",
  "properties": {
    "iso:country":"NL",
    "sg:address":"Nassaupln 42",
    "sg:city":"Amsterdam",
    "sg:orig_category":"Yoga-Instituten",
    "sg:phone":"+31 20 684 2939",
    "sg:postcode":"1052 AH",
    "sg:province":"Noord-Holland",
    "wof:name":"Plezier, Sticht",
    "wof:placetype":"venue"
},
  "geometry": {"coordinates":[4.879105,52.382011],"type":"Point"}
}