{
  "type": "Feature",
  "properties": {
    "addr:full":"Keizersgr 74 Amsterdam North Holland 1015 CT",
    "addr:housenumber":"74",
    "addr:postcode":"1015 ct",
    "addr:street":"Keizersgr",
    "iso:country":"NL",
    "sg:address":"Keizersgr 74",
    "sg:city":"Amsterdam",
    "sg:orig_category":"Fotografie Reclame En Mode",
    "sg:phone":"+31 20 625 7383",
    "sg:postcode":"1015 CT",
    "sg:province":"North Holland",
    "sg:website":"http://people.a2000.nl/tuyten/",
    "wof:name":"Uytenhaak, T",
    "wof:placetype":"venue"
},
  "geometry": {"coordinates":[4.887973,52.37817],"type":"Point"}
}