{
  "type": "Feature",
  "properties": {
    "addr:full":"Taalstr 217 Vught North Brabant 5261 BD",
    "addr:housenumber":"217",
    "addr:postcode":"5261 bd",
    "iso:country":"NL",
    "sg:address":"Taalstr 217",
    "sg:city":"Vught",
    "sg:classifiers":[
        {
            "category":"Fast Food",
            "type":"Food & Drink"
        }
    ],
    "sg:phone":"+31 73 656 1606",
    "sg:postcode":"5261 BD",
    "sg:province":"North Brabant",
    "sg:tags":[
        "afhaal",
        "restaurant"
    ],
    "wof:name":"Chinees Indisch Restaurant China",
    "wof:placetype":"venue"
},
  "geometry": {"coordinates":[5.301304,51.659229],"type":"Point"}
}