{
  "type": "Feature",
  "properties": {
    "iso:country":"NL",
    "sg:address":"Dorpsstraat 33",
    "sg:city":"Ledeacker",
    "sg:classifiers":[
        {
            "category":"Education",
            "subcategory":"Preschool",
            "type":"Public Place"
        }
    ],
    "sg:phone":"+31 485 381 200",
    "sg:postcode":"5846 AB",
    "sg:province":"Noord-Brabant",
    "sg:tags":[
        "kleuteronderwijs",
        "basis-"
    ],
    "wof:name":"Basisschool Willem Christiaans",
    "wof:placetype":"venue"
},
  "geometry": {"coordinates":[5.873298,51.635468],"type":"Point"}
}