{
  "type": "Feature",
  "properties": {
    "addr:full":"Bergwg 34 Hengelo Ov Overijssel 7557 BT",
    "addr:housenumber":"34",
    "addr:postcode":"7557 bt",
    "addr:street":"Bergwg;Ov",
    "iso:country":"NL",
    "sg:address":"Bergwg 34",
    "sg:city":"Hengelo Ov",
    "sg:orig_category":"Scholen Voor Basisonderwijs",
    "sg:phone":"+31 74 291 6073",
    "sg:postcode":"7557 BT",
    "sg:province":"Overijssel",
    "sg:website":"http://www.anninksschool.nl",
    "wof:name":"Anninksschool Obs Montessori",
    "wof:placetype":"venue"
},
  "geometry": {"coordinates":[6.78971,52.266331],"type":"Point"}
}