{
  "type": "Feature",
  "properties": {
    "addr:full":"Brusselseweg 150 Maastricht Limburg 6217 HB",
    "addr:housenumber":"150",
    "addr:postcode":"6217 hb",
    "addr:street":"Brusselseweg",
    "iso:country":"NL",
    "sg:address":"Brusselseweg 150",
    "sg:city":"Maastricht",
    "sg:orig_category":"Hoger Onderwijs",
    "sg:phone":"+31 43 346 6666",
    "sg:postcode":"6217 HB",
    "sg:province":"Limburg",
    "wof:name":"Hogeschool Maastricht Onderwijs Pabo",
    "wof:placetype":"venue"
},
  "geometry": {"coordinates":[5.671859,50.854042],"type":"Point"}
}