{
  "type": "Feature",
  "properties": {
    "iso:country":"NL",
    "sg:address":"Middel 146",
    "sg:city":"Westzaan",
    "sg:orig_category":"Waterbouwkundige Werken",
    "sg:phone":"+31 75 628 4662",
    "sg:postcode":"1551 ST",
    "sg:province":"North Holland",
    "wof:name":"Bruyn, P C",
    "wof:placetype":"venue"
},
  "geometry": {"coordinates":[4.7802457809,52.4724311829],"type":"Point"}
}