{
  "type": "Feature",
  "properties": {
    "addr:full":"Otterlaan 13 Veenendaal Utrecht 3903 CW",
    "addr:housenumber":"13",
    "addr:postcode":"3903 cw",
    "addr:street":"Otterlaan",
    "iso:country":"NL",
    "sg:address":"Otterlaan 13",
    "sg:city":"Veenendaal",
    "sg:orig_category":"Binnenhuisarchitecten",
    "sg:phone":"+31 318 556 284",
    "sg:postcode":"3903 CW",
    "sg:province":"Utrecht",
    "wof:name":"Ir. A. Bons Architekten Bv",
    "wof:placetype":"venue"
},
  "geometry": {"coordinates":[5.553469,52.009926],"type":"Point"}
}