{
  "type": "Feature",
  "properties": {
    "addr:full":"Hoofdstraat 59 Ter Apel Groningen 9561 JC",
    "addr:housenumber":"59",
    "addr:postcode":"9561 jc",
    "addr:street":"Hoofdstraat",
    "iso:country":"NL",
    "sg:address":"Hoofdstraat 59",
    "sg:city":"Ter Apel",
    "sg:classifiers":[
        {
            "category":"Fast Food",
            "type":"Food & Drink"
        }
    ],
    "sg:phone":"+31 599 583 299",
    "sg:postcode":"9561 JC",
    "sg:province":"Groningen",
    "sg:tags":[
        "afhaal",
        "restaurant"
    ],
    "wof:name":"Vof Arends Automatic En Cafetaria",
    "wof:placetype":"venue"
},
  "geometry": {"coordinates":[7.059524,52.873966],"type":"Point"}
}