{
  "type": "Feature",
  "properties": {
    "addr:full":"Oudez Voorburgwal 45 Amsterdam North Holland 1012 EJ",
    "addr:housenumber":"45",
    "addr:postcode":"1012 ej",
    "addr:street":"Oudez Voorburgwal",
    "iso:country":"NL",
    "sg:address":"Oudez Voorburgwal 45",
    "sg:city":"Amsterdam",
    "sg:orig_category":"Verenigingen En Stichtingen",
    "sg:phone":"+31 20 622 1006",
    "sg:postcode":"1012 EJ",
    "sg:province":"North Holland",
    "wof:name":"Borgieel, 'T",
    "wof:placetype":"venue"
},
  "geometry": {"coordinates":[4.899468,52.374359],"type":"Point"}
}