{
  "type": "Feature",
  "properties": {
    "addr:full":"Oranjekanaal Noordzijde 37 Zuidveld Drenthe 9432 TR",
    "addr:housenumber":"37",
    "addr:postcode":"9432 tr",
    "addr:street":"Oranjekanaal Noordzijde",
    "iso:country":"NL",
    "sg:address":"Oranjekanaal Noordzijde 37",
    "sg:city":"Zuidveld",
    "sg:orig_category":"Pluimveehouderijen",
    "sg:phone":"+31 593 346 334",
    "sg:postcode":"9432 TR",
    "sg:province":"Drenthe",
    "wof:name":"W. Zoer",
    "wof:placetype":"venue"
},
  "geometry": {"coordinates":[6.638438,52.865112],"type":"Point"}
}