{
  "type": "Feature",
  "properties": {
    "iso:country":"NL",
    "sg:address":"Mr. D. D. Curtiusstraat 6",
    "sg:city":"Katwijk Zh",
    "sg:orig_category":"Goederenvervoer Over De Weg",
    "sg:phone":"+31 71 401 2980",
    "sg:postcode":"2225 ZG",
    "sg:province":"Zuid-Holland",
    "wof:name":"C.J.A.L. Vlieland",
    "wof:placetype":"venue"
},
  "geometry": {"coordinates":[4.398946,52.20612],"type":"Point"}
}