{
  "type": "Feature",
  "properties": {
    "addr:full":"Frederik Hendrikplein 36A 'S Gravenhage Zuid-Holland 2582 AX",
    "addr:housenumber":"36a '",
    "addr:postcode":"2582 ax",
    "addr:street":"Frederik Hendrikplein",
    "iso:country":"NL",
    "sg:address":"Frederik Hendrikplein 36A",
    "sg:city":"'S Gravenhage",
    "sg:classifiers":[
        {
            "category":"Fast Food",
            "type":"Food & Drink"
        }
    ],
    "sg:phone":"+31 70 355 8745",
    "sg:postcode":"2582 AX",
    "sg:province":"Zuid-Holland",
    "sg:tags":[
        "afhaal",
        "restaurant"
    ],
    "wof:name":"Dik'S Snackkar",
    "wof:placetype":"venue"
},
  "geometry": {"coordinates":[4.274846,52.089039],"type":"Point"}
}