{
  "type": "Feature",
  "properties": {
    "addr:full":"Amersfoortsewg 12A Doorn Utrecht 3941 EM",
    "addr:housenumber":"12a",
    "addr:postcode":"3941 em",
    "addr:street":"Amersfoortsewg",
    "iso:country":"NL",
    "sg:address":"Amersfoortsewg 12A",
    "sg:city":"Doorn",
    "sg:orig_category":"Wereldwinkels",
    "sg:phone":"+31 343 416 251",
    "sg:postcode":"3941 EM",
    "sg:province":"Utrecht",
    "wof:name":"Wereldwinkel",
    "wof:placetype":"venue"
},
  "geometry": {"coordinates":[5.3456010818,52.0357894897],"type":"Point"}
}