{
  "type": "Feature",
  "properties": {
    "addr:full":"Spalstraat 17 Hengelo Gld Gelderland 7255 AA",
    "addr:housenumber":"17",
    "addr:postcode":"7255 aa",
    "addr:street":"Spalstraat",
    "iso:country":"NL",
    "sg:address":"Spalstraat 17",
    "sg:city":"Hengelo Gld",
    "sg:orig_category":"Banken And Kredietinstellingen",
    "sg:phone":"+31 575 464 169",
    "sg:postcode":"7255 AA",
    "sg:province":"Gelderland",
    "wof:name":"Postkantoor",
    "wof:placetype":"venue"
},
  "geometry": {"coordinates":[6.31063,52.050793],"type":"Point"}
}