{
  "type": "Feature",
  "properties": {
    "addr:full":"L Nekstr 18A Amsterdam North Holland 1092 GW",
    "addr:housenumber":"18a",
    "addr:postcode":"1092 gw",
    "iso:country":"NL",
    "sg:address":"L Nekstr 18A",
    "sg:city":"Amsterdam",
    "sg:orig_category":"Verenigingen En Stichtingen",
    "sg:phone":"+31 20 693 1970",
    "sg:postcode":"1092 GW",
    "sg:province":"North Holland",
    "wof:name":"Itihaad Chora, Sticht El",
    "wof:placetype":"venue"
},
  "geometry": {"coordinates":[4.922823,52.355995],"type":"Point"}
}