{
  "type": "Feature",
  "properties": {
    "iso:country":"NL",
    "sg:address":"Bleijenburg 156",
    "sg:city":"De Lier",
    "sg:orig_category":"Beursorganisaties And Standbouw",
    "sg:phone":"+31 174 520 040",
    "sg:postcode":"2678 BD",
    "sg:province":"Zuid-Holland",
    "wof:name":"Kreaprom",
    "wof:placetype":"venue"
},
  "geometry": {"coordinates":[4.250598,51.978752],"type":"Point"}
}