{
  "type": "Feature",
  "properties": {
    "addr:full":"Mr Troelstrastr 41 Zandvoort Noord-Holland 2042 BR",
    "addr:housenumber":"41",
    "addr:postcode":"2042 br",
    "addr:street":"Zandvoort",
    "iso:country":"NL",
    "sg:address":"Mr Troelstrastr 41",
    "sg:city":"Zandvoort",
    "sg:orig_category":"Vertaalbureaus",
    "sg:phone":"+31 23 573 1062",
    "sg:postcode":"2042 BR",
    "sg:province":"Noord-Holland",
    "wof:name":"Perfect Business Solutions",
    "wof:placetype":"venue"
},
  "geometry": {"coordinates":[4.525621,52.367661],"type":"Point"}
}