{
  "type": "Feature",
  "properties": {
    "addr:full":"V Voordenpk 5D Zaltbommel Gelderland 5301 KP",
    "addr:housenumber":"5d",
    "addr:postcode":"5301 kp",
    "addr:street":"Gelderland",
    "iso:country":"NL",
    "sg:address":"V Voordenpk 5D",
    "sg:city":"Zaltbommel",
    "sg:orig_category":"Elektronica - Ontwikkeling En Groothandel",
    "sg:phone":"+31 418 680 617",
    "sg:postcode":"5301 KP",
    "sg:province":"Gelderland",
    "sg:website":"http://www.comaxbv.nl",
    "wof:name":"Comax Bv",
    "wof:placetype":"venue"
},
  "geometry": {"coordinates":[5.24478,51.812744],"type":"Point"}
}