{
  "type": "Feature",
  "properties": {
    "addr:full":"Wagenmakerstr 5 Assen Drenthe 9403 VC",
    "addr:housenumber":"5",
    "addr:postcode":"9403 vc",
    "addr:street":"Wagenmakerstr",
    "iso:country":"NL",
    "sg:address":"Wagenmakerstr 5",
    "sg:city":"Assen",
    "sg:orig_category":"Projectinrichting",
    "sg:phone":"+31 592 357 431",
    "sg:postcode":"9403 VC",
    "sg:province":"Drenthe",
    "wof:name":"Rtm",
    "wof:placetype":"venue"
},
  "geometry": {"coordinates":[6.584769,53.011383],"type":"Point"}
}