{
  "type": "Feature",
  "properties": {
    "addr:full":"Kapelstr 71 Veghel Noord-Brabant 5466 PB",
    "addr:housenumber":"71",
    "addr:postcode":"5466 pb",
    "addr:street":"Kapelstr",
    "iso:country":"NL",
    "sg:address":"Kapelstr 71",
    "sg:city":"Veghel",
    "sg:orig_category":"Autorijscholen",
    "sg:phone":"+31 413 364 816",
    "sg:postcode":"5466 PB",
    "sg:province":"Noord-Brabant",
    "wof:name":"Doelen, Fa Van Der",
    "wof:placetype":"venue"
},
  "geometry": {"coordinates":[5.494123,51.605667],"type":"Point"}
}