{
  "type": "Feature",
  "properties": {
    "addr:full":"Bastion Willem 39 Woerden Utrecht 3445 DG",
    "addr:housenumber":"39",
    "addr:postcode":"3445 dg",
    "addr:street":"Bastion Willem",
    "iso:country":"NL",
    "sg:address":"Bastion Willem 39",
    "sg:city":"Woerden",
    "sg:orig_category":"Bedrijfs- And Managementsconsultants",
    "sg:phone":"+31 348 423 480",
    "sg:postcode":"3445 DG",
    "sg:province":"Utrecht",
    "wof:name":"Marjan De Hoog Promotions",
    "wof:placetype":"venue"
},
  "geometry": {"coordinates":[4.893911,52.095402],"type":"Point"}
}