{
  "type": "Feature",
  "properties": {
    "iso:country":"NL",
    "sg:address":"Lindensteinln 75",
    "sg:city":"Leek",
    "sg:orig_category":"Woningbouw- Verenigingen En -Stichtingen",
    "sg:phone":"+31 594 512 161",
    "sg:postcode":"9351 KC",
    "sg:province":"Groningen",
    "sg:website":"http://www.woldwaard.nl",
    "wof:name":"Wold En Waard",
    "wof:placetype":"venue"
},
  "geometry": {"coordinates":[6.3748130798,53.1633415222],"type":"Point"}
}