{
  "type": "Feature",
  "properties": {
    "addr:full":"De Veken 4B Opmeer North Holland 1716 KE",
    "addr:housenumber":"4b",
    "addr:postcode":"1716 ke",
    "addr:street":"De Veken",
    "iso:country":"NL",
    "sg:address":"De Veken 4B",
    "sg:city":"Opmeer",
    "sg:orig_category":"Verlichting",
    "sg:phone":"+31 226 352 379",
    "sg:postcode":"1716 KE",
    "sg:province":"North Holland",
    "wof:name":"Statusfeer Design",
    "wof:placetype":"venue"
},
  "geometry": {"coordinates":[4.956077,52.707253],"type":"Point"}
}