{
  "type": "Feature",
  "properties": {
    "addr:full":"Landhoofd 48 Hellevoetsluis Zuid-Holland 3223 DL",
    "addr:housenumber":"48",
    "addr:postcode":"3223 dl",
    "addr:street":"Landhoofd",
    "iso:country":"NL",
    "sg:address":"Landhoofd 48",
    "sg:city":"Hellevoetsluis",
    "sg:orig_category":"Huishoudelijk Textiel Fab",
    "sg:phone":"+31 181 311 192",
    "sg:postcode":"3223 DL",
    "sg:province":"Zuid-Holland",
    "wof:name":"Gordijnatelier Alfa",
    "wof:placetype":"venue"
},
  "geometry": {"coordinates":[4.146733,51.834206],"type":"Point"}
}