{
  "type": "Feature",
  "properties": {
    "iso:country":"NL",
    "sg:address":"Goethartstr 18",
    "sg:city":"Zaandam",
    "sg:orig_category":"Adviesbureaus Elektrotechniek",
    "sg:phone":"+31 75 616 2988",
    "sg:postcode":"1504 JM",
    "sg:province":"Noord-Holland",
    "wof:name":"Buijsman",
    "wof:placetype":"venue"
},
  "geometry": {"coordinates":[4.851112,52.439018],"type":"Point"}
}