{
  "type": "Feature",
  "properties": {
    "addr:full":"Schiewg 121 Rotterdam Zuid-Holland 3038 AL",
    "addr:housenumber":"121",
    "addr:postcode":"3038 al",
    "iso:country":"NL",
    "sg:address":"Schiewg 121",
    "sg:city":"Rotterdam",
    "sg:orig_category":"Aquariumartikelen En Siervissen",
    "sg:phone":"+31 10 465 2529",
    "sg:postcode":"3038 AL",
    "sg:province":"Zuid-Holland",
    "sg:website":"http://www.worldwide-fish.com",
    "wof:name":"Worldwide-Fish.Com",
    "wof:placetype":"venue"
},
  "geometry": {"coordinates":[4.465931,51.933472],"type":"Point"}
}