{
  "type": "Feature",
  "properties": {
    "addr:full":"Vestingplein 58 Velserbroek Noord-Holland 1991 RK",
    "addr:housenumber":"58",
    "addr:postcode":"1991 rk",
    "addr:street":"Vestingplein",
    "iso:country":"NL",
    "sg:address":"Vestingplein 58",
    "sg:city":"Velserbroek",
    "sg:orig_category":"Sportcentra",
    "sg:phone":"+31 23 537 4218",
    "sg:postcode":"1991 RK",
    "sg:province":"Noord-Holland",
    "wof:name":"Sporthal Het Polderhuis",
    "wof:placetype":"venue"
},
  "geometry": {"coordinates":[4.660421,52.433254],"type":"Point"}
}