{
  "type": "Feature",
  "properties": {
    "addr:full":"Atjehgouw 1 Broek In Waterland North Holland 1151 EB",
    "addr:housenumber":"1",
    "addr:postcode":"1151 eb",
    "addr:street":"Atjehgouw",
    "iso:country":"NL",
    "sg:address":"Atjehgouw 1",
    "sg:city":"Broek In Waterland",
    "sg:orig_category":"Loodgieters",
    "sg:phone":"+31 20 403 3278",
    "sg:postcode":"1151 EB",
    "sg:province":"North Holland",
    "wof:name":"Waterland, Installatietechniek Vof",
    "wof:placetype":"venue"
},
  "geometry": {"coordinates":[5.014038,52.436642],"type":"Point"}
}