{
  "type": "Feature",
  "properties": {
    "addr:full":"Beckerswei 35 Valkenburg Lb Limburg 6301 AX",
    "addr:housenumber":"35",
    "addr:postcode":"lb;6301 ax",
    "addr:street":"Beckerswei",
    "iso:country":"NL",
    "sg:address":"Beckerswei 35",
    "sg:city":"Valkenburg Lb",
    "sg:orig_category":"Verzekeringen - Verzekeringskantoren",
    "sg:phone":"+31 43 601 4404",
    "sg:postcode":"6301 AX",
    "sg:province":"Limburg",
    "wof:name":"Geurts, Paul",
    "wof:placetype":"venue"
},
  "geometry": {"coordinates":[5.825087,50.844418],"type":"Point"}
}