{
  "type": "Feature",
  "properties": {
    "addr:full":"Westelijk Halfrond 429 Amstelveen Noord-Holland 1183 JD",
    "addr:housenumber":"429",
    "addr:postcode":"1183 jd",
    "addr:street":"Westelijk Halfrond",
    "iso:country":"NL",
    "sg:address":"Westelijk Halfrond 429",
    "sg:city":"Amstelveen",
    "sg:orig_category":"Werving And Selectie Van Vast Personeel",
    "sg:phone":"+31 20 441 6714",
    "sg:postcode":"1183 JD",
    "sg:province":"Noord-Holland",
    "wof:name":"Flexfirm",
    "wof:placetype":"venue"
},
  "geometry": {"coordinates":[4.8737888336,52.3115653992],"type":"Point"}
}