{
  "type": "Feature",
  "properties": {
    "addr:full":"Zwanenburgerdk 81 Vyfhuizen Noord-Holland 2141 BM",
    "addr:housenumber":"81",
    "addr:postcode":"2141 bm",
    "addr:street":"Zwanenburgerdk",
    "iso:country":"NL",
    "sg:address":"Zwanenburgerdk 81",
    "sg:city":"Vyfhuizen",
    "sg:orig_category":"Autorijscholen",
    "sg:phone":"+31 23 536 0949",
    "sg:postcode":"2141 BM",
    "sg:province":"Noord-Holland",
    "wof:name":"Truus Gladon",
    "wof:placetype":"venue"
},
  "geometry": {"coordinates":[4.70098,52.380928],"type":"Point"}
}