{
  "type": "Feature",
  "properties": {
    "iso:country":"NL",
    "sg:address":"Zwanenburgerdk 81",
    "sg:city":"Vyfhuizen",
    "sg:orig_category":"Autorijscholen",
    "sg:phone":"+31 23 536 0949",
    "sg:postcode":"2141 BM",
    "sg:province":"Noord-Holland",
    "wof:name":"Truus Gladon",
    "wof:placetype":"venue"
},
  "geometry": {"coordinates":[4.70098,52.380928],"type":"Point"}
}