{
  "type": "Feature",
  "properties": {
    "addr:full":"Grotestr 6 Oyen Noord-Brabant 5394 LG",
    "addr:housenumber":"6",
    "addr:postcode":"5394 lg",
    "addr:street":"Grotestr",
    "iso:country":"NL",
    "sg:address":"Grotestr 6",
    "sg:city":"Oyen",
    "sg:orig_category":"Hek- En Rasterwerken",
    "sg:phone":"+31 412 495 017",
    "sg:postcode":"5394 LG",
    "sg:province":"Noord-Brabant",
    "wof:name":"Bruggen, D Van Der",
    "wof:placetype":"venue"
},
  "geometry": {"coordinates":[-96.055939,42.820534],"type":"Point"}
}