{
  "type": "Feature",
  "properties": {
    "iso:country":"NL",
    "sg:address":"Wibautstr 7375",
    "sg:city":"Amsterdam",
    "sg:orig_category":"Verlichtingsartikelen - Fabrieken",
    "sg:phone":"+31 20 665 4268",
    "sg:postcode":"1091 GK",
    "sg:province":"Noord-Holland",
    "wof:name":"Project Licht Bv",
    "wof:placetype":"venue"
},
  "geometry": {"coordinates":[4.912712,52.353722],"type":"Point"}
}