{
  "type": "Feature",
  "properties": {
    "addr:full":"Nijkerkerwg 155 Voorthuizen Gelderland 3781 LA",
    "addr:housenumber":"155",
    "addr:postcode":"3781",
    "addr:street":"Gelderland",
    "iso:country":"NL",
    "sg:address":"Nijkerkerwg 155",
    "sg:city":"Voorthuizen",
    "sg:classifiers":[
        {
            "category":"Sports & Exercise",
            "subcategory":"Stables",
            "type":"Entertainment"
        }
    ],
    "sg:phone":"+31 342 491 528",
    "sg:postcode":"3781 LA",
    "sg:province":"Gelderland",
    "sg:tags":[
        "maneges"
    ],
    "wof:name":"Hippisch Centr Barneveld",
    "wof:placetype":"venue"
},
  "geometry": {"coordinates":[5.572866,52.168095],"type":"Point"}
}