{
  "type": "Feature",
  "properties": {
    "iso:country":"NL",
    "sg:address":"Dorpen 24",
    "sg:city":"Schagen",
    "sg:orig_category":"Zonnebank- En Solariumcentra",
    "sg:phone":"+31 224 212 552",
    "sg:postcode":"1741 EE",
    "sg:province":"North Holland",
    "wof:name":"Joyce En Peggy, Lijfstijl",
    "wof:placetype":"venue"
},
  "geometry": {"coordinates":[4.801573,52.784443],"type":"Point"}
}