{
  "type": "Feature",
  "properties": {
    "addr:full":"Operettewg 42 Almere Flevoland 1323 VB",
    "addr:housenumber":"42",
    "addr:postcode":"1323 vb",
    "addr:street":"Operettewg;Flevoland",
    "iso:country":"NL",
    "sg:address":"Operettewg 42",
    "sg:city":"Almere",
    "sg:orig_category":"Keukens",
    "sg:phone":"+31 36 531 4302",
    "sg:postcode":"1323 VB",
    "sg:province":"Flevoland",
    "sg:website":"http://www.bogaard.nl",
    "wof:name":"Bogaard Keukens & Badkamers",
    "wof:placetype":"venue"
},
  "geometry": {"coordinates":[5.185643,52.364693],"type":"Point"}
}