{
  "type": "Feature",
  "properties": {
    "iso:country":"NL",
    "sg:address":"Elvieraland 1",
    "sg:city":"Den Haag",
    "sg:orig_category":"Diverse Grafische Activiteiten",
    "sg:phone":"+31 70 347 6284",
    "sg:postcode":"2591 GW",
    "sg:province":"Zuid-Holland",
    "wof:name":"Quickzet",
    "wof:placetype":"venue"
},
  "geometry": {"coordinates":[4.36268,52.095257],"type":"Point"}
}