{
  "type": "Feature",
  "properties": {
    "addr:full":"Hoogstraat 80 Oosterhout Nb North Brabant 4901 PK",
    "addr:housenumber":"80;nb",
    "addr:postcode":"4901 pk",
    "addr:street":"Hoogstraat",
    "iso:country":"NL",
    "sg:address":"Hoogstraat 80",
    "sg:city":"Oosterhout Nb",
    "sg:orig_category":"Keramische Producten Fab",
    "sg:phone":"+31 162 422 995",
    "sg:postcode":"4901 PK",
    "sg:province":"North Brabant",
    "wof:name":"Pottenbakkerij St Paulusabdij",
    "wof:placetype":"venue"
},
  "geometry": {"coordinates":[4.87311,51.639309],"type":"Point"}
}