{
  "type": "Feature",
  "properties": {
    "iso:country":"NL",
    "sg:address":"Sportln 23",
    "sg:city":"Wolvega",
    "sg:orig_category":"Bejaarden - Verzorgingstehuizen",
    "sg:phone":"+31 6 52163585",
    "sg:postcode":"8471 NP",
    "sg:province":"Friesland",
    "wof:name":"Trans4Matie",
    "wof:placetype":"venue"
},
  "geometry": {"coordinates":[5.99809,52.87521],"type":"Point"}
}