{
  "type": "Feature",
  "properties": {
    "addr:full":"Wilhelminastraat 25 Vlijmen Noord-Brabant 5251 ER",
    "addr:housenumber":"25",
    "addr:postcode":"5251 er",
    "addr:street":"Wilhelminastraat",
    "iso:country":"NL",
    "sg:address":"Wilhelminastraat 25",
    "sg:city":"Vlijmen",
    "sg:orig_category":"Artsen And Specialisten",
    "sg:phone":"+31 73 511 5828",
    "sg:postcode":"5251 ER",
    "sg:province":"Noord-Brabant",
    "wof:name":"Broeren",
    "wof:placetype":"venue"
},
  "geometry": {"coordinates":[5.221135,51.698578],"type":"Point"}
}