{
  "type": "Feature",
  "properties": {
    "addr:full":"Nieuwstg 23 Tricht Gelderland 4196 AK",
    "addr:housenumber":"23",
    "addr:postcode":"4196 ak",
    "addr:street":"Nieuwstg;Gelderland",
    "iso:country":"NL",
    "sg:address":"Nieuwstg 23",
    "sg:city":"Tricht",
    "sg:orig_category":"Adviesbureaus Bedrijfsorganisatie",
    "sg:phone":"+31 345 581 212",
    "sg:postcode":"4196 AK",
    "sg:province":"Gelderland",
    "wof:name":"Noordconsult",
    "wof:placetype":"venue"
},
  "geometry": {"coordinates":[5.268362,51.890984],"type":"Point"}
}