{
  "type": "Feature",
  "properties": {
    "addr:full":"Rooyakkersstr 6 Eindhoven North Brabant 5652 BB",
    "addr:housenumber":"6",
    "addr:postcode":"5652 bb",
    "addr:street":"Rooyakkersstr",
    "iso:country":"NL",
    "sg:address":"Rooyakkersstr 6",
    "sg:city":"Eindhoven",
    "sg:orig_category":"Verf En Lak - Fabrieken En Groothandel",
    "sg:phone":"+31 40 252 8527",
    "sg:postcode":"5652 BB",
    "sg:province":"North Brabant",
    "wof:name":"Husan Bv",
    "wof:placetype":"venue"
},
  "geometry": {"coordinates":[5.4376,51.435398],"type":"Point"}
}