{
  "type": "Feature",
  "properties": {
    "addr:full":"Hoofdstraat 91 Driebergen-Rijsenburg Utrecht 3971 KE",
    "addr:housenumber":"91",
    "addr:postcode":"3971 ke",
    "addr:street":"Hoofdstraat",
    "iso:country":"NL",
    "sg:address":"Hoofdstraat 91",
    "sg:city":"Driebergen-Rijsenburg",
    "sg:orig_category":"Adviesbureaus Bedrijfsorganisatie",
    "sg:phone":"+31 343 532 677",
    "sg:postcode":"3971 KE",
    "sg:province":"Utrecht",
    "wof:name":"Crown Gillmore Bv",
    "wof:placetype":"venue"
},
  "geometry": {"coordinates":[5.279173,52.053997],"type":"Point"}
}