{
  "type": "Feature",
  "properties": {
    "addr:full":"De Boender 12 Noordwyk Zh Zuid-Holland 2204 AG",
    "addr:housenumber":"12",
    "addr:postcode":"2204",
    "addr:street":"De Boender",
    "iso:country":"NL",
    "sg:address":"De Boender 12",
    "sg:city":"Noordwyk Zh",
    "sg:orig_category":"Bloemen En Planten - Groothandel",
    "sg:phone":"+31 71 403 5279",
    "sg:postcode":"2204 AG",
    "sg:province":"Zuid-Holland",
    "wof:name":"Duif",
    "wof:placetype":"venue"
},
  "geometry": {"coordinates":[4.4477,52.234261],"type":"Point"}
}