{
  "type": "Feature",
  "properties": {
    "addr:full":"Marssteden 94 Enschede NL.08 7547 TD",
    "addr:housenumber":"94",
    "addr:postcode":"7547 td",
    "addr:street":"Marssteden",
    "iso:country":"NL",
    "sg:address":"Marssteden 94",
    "sg:city":"Enschede",
    "sg:orig_category":"Bedrijfsmechanisatie En -Automatisering",
    "sg:phone":"+31 53 428 4980",
    "sg:postcode":"7547 TD",
    "sg:province":"NL.08",
    "sg:website":"http://www.dothill.com",
    "wof:name":"Dot Hill Bv",
    "wof:placetype":"venue"
},
  "geometry": {"coordinates":[6.816471,52.216206],"type":"Point"}
}