{
  "type": "Feature",
  "properties": {
    "addr:full":"Wierdawg 2 Winsum Gn Groningen 9951 TM",
    "addr:housenumber":"2",
    "addr:postcode":"gn;9951 tm",
    "addr:street":"Wierdawg",
    "iso:country":"NL",
    "sg:address":"Wierdawg 2",
    "sg:city":"Winsum Gn",
    "sg:orig_category":"Sportverenigingen En Ontspannings- Verenigingen",
    "sg:phone":"+31 595 442 181",
    "sg:postcode":"9951 TM",
    "sg:province":"Groningen",
    "wof:name":"Dwa, Korfbalver",
    "wof:placetype":"venue"
},
  "geometry": {"coordinates":[6.510925,53.332916],"type":"Point"}
}