{
  "type": "Feature",
  "properties": {
    "addr:full":"Ridderhof 43 Alphen A/D Rijn Zuid-Holland 2402 EN",
    "addr:housenumber":"43",
    "addr:postcode":"2402 en",
    "addr:street":"Ridderhof",
    "iso:country":"NL",
    "sg:address":"Ridderhof 43",
    "sg:city":"Alphen A/D Rijn",
    "sg:orig_category":"Wasserettes And Stomerijen",
    "sg:phone":"+31 172 419 636",
    "sg:postcode":"2402 EN",
    "sg:province":"Zuid-Holland",
    "wof:name":"Palthe Stomerijen Bv",
    "wof:placetype":"venue"
},
  "geometry": {"coordinates":[4.67441082,52.1453094482],"type":"Point"}
}