{
  "type": "Feature",
  "properties": {
    "addr:full":"Maaspoort 23 Weert Limburg 6001 BN",
    "addr:housenumber":"23",
    "addr:postcode":"6001 bn",
    "addr:street":"Maaspoort",
    "iso:country":"NL",
    "sg:address":"Maaspoort 23",
    "sg:city":"Weert",
    "sg:orig_category":"Discountwinkels",
    "sg:phone":"+31 495 546 110",
    "sg:postcode":"6001 BN",
    "sg:province":"Limburg",
    "wof:name":"Big Ben",
    "wof:placetype":"venue"
},
  "geometry": {"coordinates":[5.711352,51.251842],"type":"Point"}
}