{
  "type": "Feature",
  "properties": {
    "addr:full":"S V Zwanenbergln 59 Heesch Noord-Brabant 5384 BV",
    "addr:housenumber":"59",
    "addr:postcode":"5384 bv",
    "addr:street":"Zwanenbergln",
    "iso:country":"NL",
    "sg:address":"S V Zwanenbergln 59",
    "sg:city":"Heesch",
    "sg:orig_category":"Scholen Voor Basisonderwijs",
    "sg:phone":"+31 412 452 239",
    "sg:postcode":"5384 BV",
    "sg:province":"Noord-Brabant",
    "wof:name":"Emmaus Rk",
    "wof:placetype":"venue"
},
  "geometry": {"coordinates":[5.52822,51.735455],"type":"Point"}
}