{
  "type": "Feature",
  "properties": {
    "addr:full":"Molenstr 119 Helmond Noord-Brabant 5701 KB",
    "addr:housenumber":"119",
    "addr:postcode":"5701 kb",
    "addr:street":"Molenstr",
    "iso:country":"NL",
    "sg:address":"Molenstr 119",
    "sg:city":"Helmond",
    "sg:orig_category":"Onderhoudswerken",
    "sg:phone":"+31 492 528 101",
    "sg:postcode":"5701 KB",
    "sg:province":"Noord-Brabant",
    "wof:name":"Veghel, T Van",
    "wof:placetype":"venue"
},
  "geometry": {"coordinates":[5.667072,51.477539],"type":"Point"}
}