{
  "type": "Feature",
  "properties": {
    "iso:country":"NL",
    "sg:address":"A Tasmanstr 23",
    "sg:city":"Emmen",
    "sg:orig_category":"Woninginrichting",
    "sg:phone":"+31 591 631 969",
    "sg:postcode":"7825 VA",
    "sg:province":"Provincie Drenthe",
    "wof:name":"Tapitexx",
    "wof:placetype":"venue"
},
  "geometry": {"coordinates":[6.9162797928,52.7526893616],"type":"Point"}
}