{
  "type": "Feature",
  "properties": {
    "addr:full":"Mergelland 50 Dronten Flevoland 8251 WL",
    "addr:housenumber":"50",
    "addr:postcode":"8251",
    "addr:street":"Mergelland;Flevoland",
    "iso:country":"NL",
    "sg:address":"Mergelland 50",
    "sg:city":"Dronten",
    "sg:orig_category":"Diverse Grafische Activiteiten",
    "sg:phone":"+31 321 336 254",
    "sg:postcode":"8251 WL",
    "sg:province":"Flevoland",
    "wof:name":"Mirror Design",
    "wof:placetype":"venue"
},
  "geometry": {"coordinates":[5.72658,52.514156],"type":"Point"}
}