{
  "type": "Feature",
  "properties": {
    "addr:full":"De C Rebecquepln 5 S Gravenhage Zuid-Holland 2518 RA",
    "addr:housenumber":"5;gravenhage",
    "addr:postcode":"2518 ra",
    "addr:street":"De;Rebecquepln;S",
    "iso:country":"NL",
    "sg:address":"De C Rebecquepln 5",
    "sg:city":"S Gravenhage",
    "sg:orig_category":"Goudsmeden En Zilversmeden",
    "sg:phone":"+31 70 320 5686",
    "sg:postcode":"2518 RA",
    "sg:province":"Zuid-Holland",
    "wof:name":"Lynch, Urline",
    "wof:placetype":"venue"
},
  "geometry": {"coordinates":[4.29348,52.080318],"type":"Point"}
}