{
  "type": "Feature",
  "properties": {
    "iso:country":"NL",
    "sg:address":"Industriewg 25",
    "sg:city":"Berkel En Rodenrys",
    "sg:orig_category":"Plafonds",
    "sg:phone":"+31 10 511 7844",
    "sg:postcode":"2651 BC",
    "sg:province":"Zuid-Holland",
    "wof:name":"Vrij Bv, W De",
    "wof:placetype":"venue"
},
  "geometry": {"coordinates":[4.456183,51.979362],"type":"Point"}
}