{
  "type": "Feature",
  "properties": {
    "iso:country":"NL",
    "sg:address":"Haven 38",
    "sg:city":"Leiden",
    "sg:orig_category":"Wasserettes And Stomerijen",
    "sg:phone":"+31 71 523 1250",
    "sg:postcode":"2312 MK",
    "sg:province":"South Holland",
    "wof:name":"Deniz Clean Company Bv",
    "wof:placetype":"venue"
},
  "geometry": {"coordinates":[4.5024991035,52.1616821289],"type":"Point"}
}