{
  "type": "Feature",
  "properties": {
    "addr:full":"J W Frisoln 37 Hoogezand Groningen 9602 GG",
    "addr:housenumber":"37",
    "addr:postcode":"9602 gg",
    "iso:country":"NL",
    "sg:address":"J W Frisoln 37",
    "sg:city":"Hoogezand",
    "sg:orig_category":"Artsen - Huisartsen",
    "sg:phone":"+31 598 320 186",
    "sg:postcode":"9602 GG",
    "sg:province":"Groningen",
    "wof:name":"Hoekstra, P M",
    "wof:placetype":"venue"
},
  "geometry": {"coordinates":[6.754265,53.15551],"type":"Point"}
}