{
  "type": "Feature",
  "properties": {
    "addr:full":"Stationstr 153 Nuth Limburg 6361 BH",
    "addr:housenumber":"153",
    "addr:postcode":"6361 bh",
    "iso:country":"NL",
    "sg:address":"Stationstr 153",
    "sg:city":"Nuth",
    "sg:orig_category":"Geluidsinstallaties",
    "sg:phone":"+31 45 524 1946",
    "sg:postcode":"6361 BH",
    "sg:province":"Limburg",
    "wof:name":"Future Sound",
    "wof:placetype":"venue"
},
  "geometry": {"coordinates":[5.885999,50.918785],"type":"Point"}
}