{
  "type": "Feature",
  "properties": {
    "addr:full":"De Konnighstraat 12 'S-Gravenzande South Holland 2691 XK",
    "addr:housenumber":"12",
    "addr:postcode":"2691 xk",
    "addr:street":"De Konnighstraat",
    "iso:country":"NL",
    "sg:address":"De Konnighstraat 12",
    "sg:city":"'S-Gravenzande",
    "sg:orig_category":"Glas",
    "sg:phone":"+31 174 420 831",
    "sg:postcode":"2691 XK",
    "sg:province":"South Holland",
    "wof:name":"Wijnbergen",
    "wof:placetype":"venue"
},
  "geometry": {"coordinates":[4.166453,52.003025],"type":"Point"}
}