{
  "type": "Feature",
  "properties": {
    "addr:full":"Postbus 735 Eindhoven Noord-Brabant 5600 AS",
    "addr:housenumber":"735",
    "addr:postcode":"5600 as",
    "addr:street":"Postbus",
    "iso:country":"NL",
    "sg:address":"Postbus 735",
    "sg:city":"Eindhoven",
    "sg:orig_category":"Kamers Van Koophandel",
    "sg:phone":"+31 40 232 3911",
    "sg:postcode":"5600 AS",
    "sg:province":"Noord-Brabant",
    "sg:website":"http://www.kvk.nl",
    "wof:name":"Kamer V Koophandel Oost-Brabant",
    "wof:placetype":"venue"
},
  "geometry": {"coordinates":[5.4841098785,51.4344711304],"type":"Point"}
}