{
  "type": "Feature",
  "properties": {
    "iso:country":"NL",
    "sg:address":"Schepenstr 3C",
    "sg:city":"Rotterdam",
    "sg:orig_category":"Webdesign Bureaus",
    "sg:phone":"+31 10 476 7737",
    "sg:postcode":"3039 NA",
    "sg:province":"Zuid-Holland",
    "sg:website":"http://www.asder.nl",
    "wof:name":"Asder Digital",
    "wof:placetype":"venue"
},
  "geometry": {"coordinates":[4.4664697647,51.9311943054],"type":"Point"}
}