{
  "type": "Feature",
  "properties": {
    "addr:full":"Dorpsstr 24A Bergschenhoek Zuid-Holland 2661 CG",
    "addr:housenumber":"24a",
    "addr:postcode":"2661 cg",
    "addr:street":"Dorpsstr",
    "iso:country":"NL",
    "sg:address":"Dorpsstr 24A",
    "sg:city":"Bergschenhoek",
    "sg:orig_category":"Kappers",
    "sg:phone":"+31 10 521 7266",
    "sg:postcode":"2661 CG",
    "sg:province":"Zuid-Holland",
    "wof:name":"My Way",
    "wof:placetype":"venue"
},
  "geometry": {"coordinates":[4.500276,51.988914],"type":"Point"}
}