{
  "type": "Feature",
  "properties": {
    "addr:full":"Amnesty Intern Wg 53 Haarlem Noord-Holland 2033 AZ",
    "addr:housenumber":"53",
    "addr:postcode":"2033 az",
    "addr:street":"Amnesty;Wg",
    "iso:country":"NL",
    "sg:address":"Amnesty Intern Wg 53",
    "sg:city":"Haarlem",
    "sg:orig_category":"Centrale Verwarming - Installatie En Onderhoud",
    "sg:phone":"+31 23 533 1072",
    "sg:postcode":"2033 AZ",
    "sg:province":"Noord-Holland",
    "wof:name":"A-Ron Wildschut",
    "wof:placetype":"venue"
},
  "geometry": {"coordinates":[4.672255,52.378487],"type":"Point"}
}