{
  "type": "Feature",
  "properties": {
    "addr:full":"Strengwg 8 Heemskerk Noord-Holland 1969 MG",
    "addr:housenumber":"8",
    "addr:postcode":"1969 mg",
    "addr:street":"Strengwg",
    "iso:country":"NL",
    "sg:address":"Strengwg 8",
    "sg:city":"Heemskerk",
    "sg:orig_category":"Autoschade- Herstelbedrijven",
    "sg:phone":"+31 251 254 739",
    "sg:postcode":"1969 MG",
    "sg:province":"Noord-Holland",
    "wof:name":"Muller, C K",
    "wof:placetype":"venue"
},
  "geometry": {"coordinates":[-45.451351,-18.57752],"type":"Point"}
}