{
  "type": "Feature",
  "properties": {
    "addr:full":"Churchillln 40 Rosmalen Noord-Brabant 5242 BE",
    "addr:housenumber":"40",
    "addr:postcode":"5242",
    "addr:street":"Churchillln",
    "iso:country":"NL",
    "sg:address":"Churchillln 40",
    "sg:city":"Rosmalen",
    "sg:orig_category":"Adviesbureaus Bedrijfsorganisatie",
    "sg:phone":"+31 73 521 3591",
    "sg:postcode":"5242 BE",
    "sg:province":"Noord-Brabant",
    "wof:name":"Vermeulen, Drs P A M",
    "wof:placetype":"venue"
},
  "geometry": {"coordinates":[5.36381,51.708569],"type":"Point"}
}