{
  "type": "Feature",
  "properties": {
    "addr:full":"Lonnekerbrugstr 120A Enschede Overijssel 7547 AM",
    "addr:housenumber":"120a",
    "addr:postcode":"7547",
    "iso:country":"NL",
    "sg:address":"Lonnekerbrugstr 120A",
    "sg:city":"Enschede",
    "sg:orig_category":"Meubelmakerijen",
    "sg:phone":"+31 53 434 5334",
    "sg:postcode":"7547 AM",
    "sg:province":"Overijssel",
    "wof:name":"Rato Tafelpaleis",
    "wof:placetype":"venue"
},
  "geometry": {"coordinates":[6.849231,52.230316],"type":"Point"}
}