{
  "type": "Feature",
  "properties": {
    "iso:country":"NL",
    "sg:address":"Kooikerstraat 1",
    "sg:city":"Tilburg",
    "sg:orig_category":"Binnenhuisarchitecten",
    "sg:phone":"+31 13 468 6790",
    "sg:postcode":"5042 XC",
    "sg:province":"Noord-Brabant",
    "wof:name":"Jansen Art Productions",
    "wof:placetype":"venue"
},
  "geometry": {"coordinates":[5.049326,51.574223],"type":"Point"}
}