{
  "type": "Feature",
  "properties": {
    "iso:country":"NL",
    "sg:address":"Postbus 315",
    "sg:city":"Zandvoort",
    "sg:orig_category":"Fotojournalisten Freelance",
    "sg:phone":"+31 23 573 1970",
    "sg:postcode":"2040 AH",
    "sg:province":"Noord-Holland",
    "wof:name":"Essay Prod",
    "wof:placetype":"venue"
},
  "geometry": {"coordinates":[4.52729,52.370747],"type":"Point"}
}