{
  "type": "Feature",
  "properties": {
    "addr:full":"Bisschopsmolenstraat 195 Etten-Leur Noord-Brabant 4876 AL",
    "addr:housenumber":"195",
    "addr:postcode":"4876 al",
    "addr:street":"Bisschopsmolenstraat",
    "iso:country":"NL",
    "sg:address":"Bisschopsmolenstraat 195",
    "sg:city":"Etten-Leur",
    "sg:orig_category":"Verlichting And Huishoudartikelen",
    "sg:phone":"+31 76 501 6709",
    "sg:postcode":"4876 AL",
    "sg:province":"Noord-Brabant",
    "wof:name":"Monart",
    "wof:placetype":"venue"
},
  "geometry": {"coordinates":[4.641667,51.563511],"type":"Point"}
}