{
  "type": "Feature",
  "properties": {
    "addr:full":"Dobbe 1 Fil Zwolle Overijssel 8032 JV",
    "addr:housenumber":"1",
    "addr:postcode":"8032 jv",
    "addr:street":"Dobbe;Fil",
    "iso:country":"NL",
    "sg:address":"Dobbe 1 Fil",
    "sg:city":"Zwolle",
    "sg:orig_category":"Kappers",
    "sg:phone":"+31 38 453 8887",
    "sg:postcode":"8032 JV",
    "sg:province":"Overijssel",
    "wof:name":"Kalf, Hans",
    "wof:placetype":"venue"
},
  "geometry": {"coordinates":[6.1009998322,52.5346984863],"type":"Point"}
}