{
  "type": "Feature",
  "properties": {
    "addr:full":"Snaarmanslaan 69 Alkmaar Noord-Holland 1815 SC",
    "addr:housenumber":"69",
    "addr:postcode":"1815 sc",
    "addr:street":"Snaarmanslaan",
    "iso:country":"NL",
    "sg:address":"Snaarmanslaan 69",
    "sg:city":"Alkmaar",
    "sg:orig_category":"Boekhouders",
    "sg:phone":"+31 72 512 8012",
    "sg:postcode":"1815 SC",
    "sg:province":"Noord-Holland",
    "wof:name":"Administratiekantoor J. De Graaff",
    "wof:placetype":"venue"
},
  "geometry": {"coordinates":[4.741876,52.636829],"type":"Point"}
}