{
  "type": "Feature",
  "properties": {
    "addr:full":"Luybenstr 34 S Hertogenbosch North Brabant 5211 BT",
    "addr:housenumber":"34",
    "addr:postcode":"5211 bt",
    "addr:street":"Luybenstr;S Hertogenbosch",
    "iso:country":"NL",
    "sg:address":"Luybenstr 34",
    "sg:city":"S Hertogenbosch",
    "sg:orig_category":"Mensendieck - Oefentherapeuten",
    "sg:phone":"+31 73 656 6876",
    "sg:postcode":"5211 BT",
    "sg:province":"North Brabant",
    "wof:name":"Broekman-Van Esser, C C M H A",
    "wof:placetype":"venue"
},
  "geometry": {"coordinates":[5.296777,51.689541],"type":"Point"}
}