{
  "type": "Feature",
  "properties": {
    "addr:full":"A Schweitzerstr 20 Goirle North Brabant 5051 KA",
    "addr:housenumber":"20",
    "addr:postcode":"5051 ka",
    "iso:country":"NL",
    "sg:address":"A Schweitzerstr 20",
    "sg:city":"Goirle",
    "sg:orig_category":"Machinehandel",
    "sg:phone":"+31 13 534 3951",
    "sg:postcode":"5051 KA",
    "sg:province":"North Brabant",
    "wof:name":"Tehado",
    "wof:placetype":"venue"
},
  "geometry": {"coordinates":[5.073773,51.527271],"type":"Point"}
}