{
  "type": "Feature",
  "properties": {
    "addr:full":"Neerpolderseweg 3 Giessenburg Zuid-Holland 3381 JP",
    "addr:housenumber":"3",
    "addr:postcode":"3381 jp",
    "addr:street":"Neerpolderseweg",
    "iso:country":"NL",
    "sg:address":"Neerpolderseweg 3",
    "sg:city":"Giessenburg",
    "sg:orig_category":"Verzekeringen",
    "sg:phone":"+31 184 651 414",
    "sg:postcode":"3381 JP",
    "sg:province":"Zuid-Holland",
    "wof:name":"Versluis Aantjes Assurantien",
    "wof:placetype":"venue"
},
  "geometry": {"coordinates":[4.882544,51.851246],"type":"Point"}
}