{
  "type": "Feature",
  "properties": {
    "addr:full":"Einderstraat 10 Wittem Limburg 6286 BK",
    "addr:housenumber":"10",
    "addr:postcode":"6286 bk",
    "addr:street":"Einderstraat",
    "iso:country":"NL",
    "sg:address":"Einderstraat 10",
    "sg:city":"Wittem",
    "sg:classifiers":[
        {
            "category":"Travel",
            "subcategory":"Hotels & Motels",
            "type":"Entertainment"
        }
    ],
    "sg:phone":"+31 43 451 1581",
    "sg:postcode":"6286 BK",
    "sg:province":"Limburg",
    "wof:name":"Pension Counotte Bendermacher",
    "wof:placetype":"venue"
},
  "geometry": {"coordinates":[5.938547,50.810524],"type":"Point"}
}