{
  "type": "Feature",
  "properties": {
    "iso:country":"NL",
    "sg:address":"Bloemstraat 58",
    "sg:city":"Deventer",
    "sg:orig_category":"Verlichting And Huishoudartikelen",
    "sg:phone":"+31 570 642 424",
    "sg:postcode":"7419 BX",
    "sg:province":"NL.08",
    "wof:name":"T Geschenkenhuis",
    "wof:placetype":"venue"
},
  "geometry": {"coordinates":[6.143387,52.249493],"type":"Point"}
}