{
  "type": "Feature",
  "properties": {
    "addr:full":"Bloemstraat 58 Deventer NL.08 7419 BX",
    "addr:housenumber":"58;nl.08",
    "addr:postcode":"7419 bx",
    "addr:street":"Bloemstraat",
    "iso:country":"NL",
    "sg:address":"Bloemstraat 58",
    "sg:city":"Deventer",
    "sg:orig_category":"Verlichting And Huishoudartikelen",
    "sg:phone":"+31 570 642 424",
    "sg:postcode":"7419 BX",
    "sg:province":"NL.08",
    "wof:name":"T Geschenkenhuis",
    "wof:placetype":"venue"
},
  "geometry": {"coordinates":[6.143387,52.249493],"type":"Point"}
}