{
  "type": "Feature",
  "properties": {
    "addr:full":"Overhorsterweg 51 Voorthuizen Gelderland 3781 NC",
    "addr:housenumber":"51;3781",
    "addr:street":"Overhorsterweg;Gelderland",
    "iso:country":"NL",
    "sg:address":"Overhorsterweg 51",
    "sg:city":"Voorthuizen",
    "sg:orig_category":"Verhuur Bouwmachines",
    "sg:phone":"+31 342 472 032",
    "sg:postcode":"3781 NC",
    "sg:province":"Gelderland",
    "wof:name":"Fa K. Van Donkersgoed & Zonen",
    "wof:placetype":"venue"
},
  "geometry": {"coordinates":[5.581219,52.188358],"type":"Point"}
}