{
  "type": "Feature",
  "properties": {
    "addr:full":"Zwynswg 12 Ens Flevoland 8307 PT",
    "addr:housenumber":"12",
    "addr:postcode":"8307",
    "addr:street":"Zwynswg;Flevoland;Pt",
    "iso:country":"NL",
    "sg:address":"Zwynswg 12",
    "sg:city":"Ens",
    "sg:orig_category":"Bloemen En Planten - Decoratie",
    "sg:phone":"+31 527 253 637",
    "sg:postcode":"8307 PT",
    "sg:province":"Flevoland",
    "wof:name":"Anjertje, Het",
    "wof:placetype":"venue"
},
  "geometry": {"coordinates":[5.845254,52.655338],"type":"Point"}
}