{
  "type": "Feature",
  "properties": {
    "addr:full":"Vivaldistr 61 Tilburg Noord-Brabant 5049 JA",
    "addr:housenumber":"61",
    "addr:postcode":"5049 ja",
    "addr:street":"Vivaldistr",
    "iso:country":"NL",
    "sg:address":"Vivaldistr 61",
    "sg:city":"Tilburg",
    "sg:orig_category":"Verbouwingen",
    "sg:phone":"+31 13 456 4141",
    "sg:postcode":"5049 JA",
    "sg:province":"Noord-Brabant",
    "wof:name":"Gouw Afbouw, P De",
    "wof:placetype":"venue"
},
  "geometry": {"coordinates":[5.080472,51.592575],"type":"Point"}
}