{
  "type": "Feature",
  "properties": {
    "iso:country":"NL",
    "sg:address":"J C Beetsln 161",
    "sg:city":"Hoofddorp",
    "sg:orig_category":"Fitnesscentra",
    "sg:phone":"+31 23 561 4999",
    "sg:postcode":"2131 AL",
    "sg:province":"North Holland",
    "sg:website":"http://www.dynamicfamilysport.nl",
    "wof:name":"Dynamic Family Sport",
    "wof:placetype":"venue"
},
  "geometry": {"coordinates":[4.70066,52.322971],"type":"Point"}
}