{
  "type": "Feature",
  "properties": {
    "addr:full":"Zandwg 13-15 Wyk By Duurstede Utrecht 3962 EA",
    "addr:housenumber":"13-15",
    "addr:postcode":"3962 ea",
    "addr:street":"Wyk By Duurstede",
    "iso:country":"NL",
    "sg:address":"Zandwg 13-15",
    "sg:city":"Wyk By Duurstede",
    "sg:orig_category":"Pensioenen",
    "sg:phone":"+31 343 575 065",
    "sg:postcode":"3962 EA",
    "sg:province":"Utrecht",
    "wof:name":"Verenigde Pensioenpartners",
    "wof:placetype":"venue"
},
  "geometry": {"coordinates":[5.3754,51.985378],"type":"Point"}
}