{
  "type": "Feature",
  "properties": {
    "iso:country":"NL",
    "sg:address":"Deldenerdk 59",
    "sg:city":"Hengelo Ov",
    "sg:orig_category":"Onderhoudswerken",
    "sg:phone":"+31 74 367 6633",
    "sg:postcode":"7554 RD",
    "sg:province":"Overijssel",
    "wof:name":"Meijerink, G J",
    "wof:placetype":"venue"
},
  "geometry": {"coordinates":[6.735911,52.225391],"type":"Point"}
}