{
  "type": "Feature",
  "properties": {
    "addr:full":"Verl Broekdk 13 Kloosterhaar Overijssel 7694 TD",
    "addr:housenumber":"13",
    "addr:postcode":"7694 td",
    "iso:country":"NL",
    "sg:address":"Verl Broekdk 13",
    "sg:city":"Kloosterhaar",
    "sg:classifiers":[
        {
            "category":"Personal",
            "subcategory":"Nail Salon",
            "type":"Services"
        }
    ],
    "sg:phone":"+31 523 242 187",
    "sg:postcode":"7694 TD",
    "sg:province":"Overijssel",
    "sg:tags":[
        "pedicure"
    ],
    "wof:name":"Joze",
    "wof:placetype":"venue"
},
  "geometry": {"coordinates":[6.683753,52.501793],"type":"Point"}
}