{
  "type": "Feature",
  "properties": {
    "addr:full":"Waterlandlaan 80 Purmerend Noord-Holland 1441 MR",
    "addr:housenumber":"80",
    "addr:postcode":"1441 mr",
    "addr:street":"Waterlandlaan",
    "iso:country":"NL",
    "sg:address":"Waterlandlaan 80",
    "sg:city":"Purmerend",
    "sg:orig_category":"Bedrijfs- And Werkgeversorganisaties",
    "sg:phone":"+31 299 411 580",
    "sg:postcode":"1441 MR",
    "sg:province":"Noord-Holland",
    "wof:name":"Kamer Van Koophandel En Fabrieken",
    "wof:placetype":"venue"
},
  "geometry": {"coordinates":[4.958709,52.504185],"type":"Point"}
}