{
  "type": "Feature",
  "properties": {
    "addr:full":"Noordlierweg 51 Schipluiden Zuid-Holland 2636 AB",
    "addr:housenumber":"51",
    "addr:postcode":"2636 ab",
    "addr:street":"Noordlierweg",
    "iso:country":"NL",
    "sg:address":"Noordlierweg 51",
    "sg:city":"Schipluiden",
    "sg:orig_category":"Goederenvervoer Over De Weg",
    "sg:phone":"+31 174 513 327",
    "sg:postcode":"2636 AB",
    "sg:province":"Zuid-Holland",
    "wof:name":"Internationaal Transportbedr B.M. Van De",
    "wof:placetype":"venue"
},
  "geometry": {"coordinates":[4.2824401855,51.9864501953],"type":"Point"}
}