{
  "type": "Feature",
  "properties": {
    "addr:full":"Nieuwewg 34C Soest Utrecht 3765 GD",
    "addr:housenumber":"34c",
    "addr:postcode":"3765 gd",
    "addr:street":"Nieuwewg",
    "iso:country":"NL",
    "sg:address":"Nieuwewg 34C",
    "sg:city":"Soest",
    "sg:orig_category":"Kunstgebitten",
    "sg:phone":"+31 35 602 8086",
    "sg:postcode":"3765 GD",
    "sg:province":"Utrecht",
    "wof:name":"Roest, F A",
    "wof:placetype":"venue"
},
  "geometry": {"coordinates":[5.290955,52.168781],"type":"Point"}
}