{
  "type": "Feature",
  "properties": {
    "addr:full":"Kostverlorenhof 55 Amstelveen North Holland 1183 HG",
    "addr:housenumber":"55",
    "addr:postcode":"1183 hg",
    "addr:street":"Kostverlorenhof",
    "iso:country":"NL",
    "sg:address":"Kostverlorenhof 55",
    "sg:city":"Amstelveen",
    "sg:classifiers":[
        {
            "category":"Food & Beverages",
            "subcategory":"Bakery",
            "type":"Retail Goods"
        }
    ],
    "sg:phone":"+31 20 641 8040",
    "sg:postcode":"1183 HG",
    "sg:province":"North Holland",
    "sg:tags":[
        "pizza"
    ],
    "sg:website":"http://www.newyorkpizza.nl",
    "wof:name":"New York Pizza",
    "wof:placetype":"venue"
},
  "geometry": {"coordinates":[4.875206,52.313061],"type":"Point"}
}