{
  "type": "Feature",
  "properties": {
    "addr:full":"Narvikwg 4 Groningen Groningen 9723 TV",
    "addr:housenumber":"4",
    "addr:postcode":"9723 tv",
    "addr:street":"Narvikwg",
    "iso:country":"NL",
    "sg:address":"Narvikwg 4",
    "sg:city":"Groningen",
    "sg:orig_category":"Koel- En Vriestransporten",
    "sg:phone":"+31 50 549 5555",
    "sg:postcode":"9723 TV",
    "sg:province":"Groningen",
    "sg:website":"http://www.thermoking.nl",
    "wof:name":"Thermo King Transportkoeling Bv",
    "wof:placetype":"venue"
},
  "geometry": {"coordinates":[6.608762,53.205231],"type":"Point"}
}