{
  "type": "Feature",
  "properties": {
    "addr:full":"Industriewg 13 Waalwyk Noord-Brabant 5145 PD",
    "addr:housenumber":"13",
    "addr:postcode":"5145 pd",
    "addr:street":"Industriewg",
    "iso:country":"NL",
    "sg:address":"Industriewg 13",
    "sg:city":"Waalwyk",
    "sg:classifiers":[
        {
            "category":"Building & Trades",
            "subcategory":"Electrical",
            "type":"Services"
        }
    ],
    "sg:phone":"+31 416 689 000",
    "sg:postcode":"5145 PD",
    "sg:province":"Noord-Brabant",
    "sg:tags":[
        "distributor"
    ],
    "wof:name":"Srt Bv",
    "wof:placetype":"venue"
},
  "geometry": {"coordinates":[5.061798,51.695717],"type":"Point"}
}