{
  "type": "Feature",
  "properties": {
    "addr:full":"Molendk 47 Herkingen Zuid-Holland 3249 AN",
    "addr:housenumber":"47",
    "addr:postcode":"3249 an",
    "addr:street":"Molendk",
    "iso:country":"NL",
    "sg:address":"Molendk 47",
    "sg:city":"Herkingen",
    "sg:orig_category":"Geluidsinstallaties - Verhuur",
    "sg:phone":"+31 187 669 626",
    "sg:postcode":"3249 AN",
    "sg:province":"Zuid-Holland",
    "wof:name":"Pluto",
    "wof:placetype":"venue"
},
  "geometry": {"coordinates":[4.088242,51.711502],"type":"Point"}
}