{
  "type": "Feature",
  "properties": {
    "addr:full":"Dorpsstr 35 Tuitjenhorn North Holland 1747 HA",
    "addr:housenumber":"35",
    "addr:postcode":"1747 ha",
    "addr:street":"Dorpsstr",
    "iso:country":"NL",
    "sg:address":"Dorpsstr 35",
    "sg:city":"Tuitjenhorn",
    "sg:orig_category":"Scholen Voor Basisonderwijs",
    "sg:phone":"+31 226 391 778",
    "sg:postcode":"1747 HA",
    "sg:province":"North Holland",
    "wof:name":"Barbara Rk, St",
    "wof:placetype":"venue"
},
  "geometry": {"coordinates":[4.748812,52.737755],"type":"Point"}
}