{
  "type": "Feature",
  "properties": {
    "addr:full":"Kerkstraat 65 Oisterwijk North Brabant 5061 EH",
    "addr:housenumber":"65",
    "addr:postcode":"5061 eh",
    "addr:street":"Kerkstraat",
    "iso:country":"NL",
    "sg:address":"Kerkstraat 65",
    "sg:city":"Oisterwijk",
    "sg:orig_category":"Wasserettes And Stomerijen",
    "sg:phone":"+31 13 528 4485",
    "sg:postcode":"5061 EH",
    "sg:province":"North Brabant",
    "wof:name":"Briljant, Chemische Reiniging",
    "wof:placetype":"venue"
},
  "geometry": {"coordinates":[5.1867442131,51.5790367126],"type":"Point"}
}