{
  "type": "Feature",
  "properties": {
    "addr:full":"Den Adelszwet 5 Rijsenhout Noord-Holland 1435 NL",
    "addr:housenumber":"5",
    "addr:postcode":"1435 nl",
    "addr:street":"Den Adelszwet",
    "iso:country":"NL",
    "sg:address":"Den Adelszwet 5",
    "sg:city":"Rijsenhout",
    "sg:orig_category":"Bloemen And Planten Gh",
    "sg:phone":"+31 297 328 444",
    "sg:postcode":"1435 NL",
    "sg:province":"Noord-Holland",
    "wof:name":"M.J. Bevelander Rijsenhout Bv",
    "wof:placetype":"venue"
},
  "geometry": {"coordinates":[4.719036,52.264904],"type":"Point"}
}