{
  "type": "Feature",
  "properties": {
    "addr:full":"Spoorstr 44 Venlo Limburg 5911 KJ",
    "addr:housenumber":"44",
    "addr:postcode":"5911 kj",
    "addr:street":"Spoorstr",
    "iso:country":"NL",
    "sg:address":"Spoorstr 44",
    "sg:city":"Venlo",
    "sg:orig_category":"Enveloppen - Fabrieken En Groothandel",
    "sg:phone":"+31 77 320 1333",
    "sg:postcode":"5911 KJ",
    "sg:province":"Limburg",
    "wof:name":"Koverto Holland Bv",
    "wof:placetype":"venue"
},
  "geometry": {"coordinates":[6.170103,51.367012],"type":"Point"}
}