{
  "type": "Feature",
  "properties": {
    "iso:country":"NL",
    "sg:address":"Heerenvenweg 4",
    "sg:city":"Wellerlooi",
    "sg:orig_category":"Kampeerterreinen",
    "sg:phone":"+31 77 473 1453",
    "sg:postcode":"5856 CJ",
    "sg:province":"North Rhine-Westphalia",
    "wof:name":"Boerdrijcamping Heidehof",
    "wof:placetype":"venue"
},
  "geometry": {"coordinates":[6.2017850876,51.5185241699],"type":"Point"}
}