{
  "type": "Feature",
  "properties": {
    "addr:full":"Wynkd 68 Rotterdam South Holland 3011 VZ",
    "addr:housenumber":"68",
    "addr:postcode":"3011 vz",
    "addr:street":"Wynkd",
    "iso:country":"NL",
    "sg:address":"Wynkd 68",
    "sg:city":"Rotterdam",
    "sg:orig_category":"Vertaalbureaus",
    "sg:phone":"+31 10 412 6068",
    "sg:postcode":"3011 VZ",
    "sg:province":"South Holland",
    "sg:website":"http://www.ruslan.nl",
    "wof:name":"Ruslan",
    "wof:placetype":"venue"
},
  "geometry": {"coordinates":[4.478455,51.922836],"type":"Point"}
}