{
  "type": "Feature",
  "properties": {
    "iso:country":"NL",
    "sg:address":"Dennenln 27",
    "sg:city":"Nieuwe Pekela",
    "sg:orig_category":"Sportverenigingen En Ontspannings- Verenigingen",
    "sg:phone":"+31 597 645 323",
    "sg:postcode":"9663 EN",
    "sg:province":"Groningen",
    "wof:name":"Elad Chr Brassband",
    "wof:placetype":"venue"
},
  "geometry": {"coordinates":[6.963506,53.080845],"type":"Point"}
}