{
  "type": "Feature",
  "properties": {
    "addr:full":"V Loonstr 1B Woerden Utrecht 3441 AL",
    "addr:housenumber":"1b",
    "addr:postcode":"3441 al",
    "addr:street":"Loonstr",
    "iso:country":"NL",
    "sg:address":"V Loonstr 1B",
    "sg:city":"Woerden",
    "sg:orig_category":"Projectontwikkeling",
    "sg:phone":"+31 348 430 012",
    "sg:postcode":"3441 AL",
    "sg:province":"Utrecht",
    "wof:name":"Pelaene",
    "wof:placetype":"venue"
},
  "geometry": {"coordinates":[4.887371,52.085117],"type":"Point"}
}