{
  "type": "Feature",
  "properties": {
    "addr:full":"Postbus 96 Bilthoven Utrecht 3720 AB",
    "addr:housenumber":"96",
    "addr:postcode":"3720 ab",
    "addr:street":"Postbus",
    "iso:country":"NL",
    "sg:address":"Postbus 96",
    "sg:city":"Bilthoven",
    "sg:orig_category":"Kantoor- En Bedrijfsmeubelen",
    "sg:phone":"+31 30 262 0590",
    "sg:postcode":"3720 AB",
    "sg:province":"Utrecht",
    "sg:website":"http://www.gispen.com",
    "wof:name":"Gispen Utrecht",
    "wof:placetype":"venue"
},
  "geometry": {"coordinates":[5.2051401138,52.1294898987],"type":"Point"}
}