{
  "type": "Feature",
  "properties": {
    "iso:country":"NL",
    "sg:address":"Wilgenlaan 21",
    "sg:city":"Aalsmeer",
    "sg:orig_category":"Bedrijfs- And Managementsconsultants",
    "sg:phone":"+31 297 328 326",
    "sg:postcode":"1431 HV",
    "sg:province":"Noord-Holland",
    "wof:name":"Stoof Management Bv",
    "wof:placetype":"venue"
},
  "geometry": {"coordinates":[4.762841,52.267727],"type":"Point"}
}