{
  "type": "Feature",
  "properties": {
    "iso:country":"NL",
    "sg:address":"Noordweg 268",
    "sg:city":"Middelburg",
    "sg:orig_category":"Boekhouders",
    "sg:phone":"+31 118 624 886",
    "sg:postcode":"4333 GP",
    "sg:province":"Zeeland",
    "wof:name":"Parree Administraties",
    "wof:placetype":"venue"
},
  "geometry": {"coordinates":[3.60957,51.503971],"type":"Point"}
}