{
  "type": "Feature",
  "properties": {
    "addr:full":"Bisonspoor 2031 Maarssen Utrecht 3605 LD",
    "addr:housenumber":"2031",
    "addr:postcode":"3605 ld",
    "addr:street":"Bisonspoor",
    "iso:country":"NL",
    "sg:address":"Bisonspoor 2031",
    "sg:city":"Maarssen",
    "sg:orig_category":"Babyartikelen",
    "sg:phone":"+31 346 556 874",
    "sg:postcode":"3605 LD",
    "sg:province":"Utrecht",
    "wof:name":"Pr?natal",
    "wof:placetype":"venue"
},
  "geometry": {"coordinates":[5.03054,52.135529],"type":"Point"}
}