{
  "type": "Feature",
  "properties": {
    "iso:country":"NL",
    "sg:address":"Weena 501",
    "sg:city":"Rotterdam",
    "sg:orig_category":"Banken And Kredietinstellingen",
    "sg:phone":"+31 10 444 6000",
    "sg:postcode":"3013 AL",
    "sg:province":"Zuid-Holland",
    "wof:name":"Ing Bank",
    "wof:placetype":"venue"
},
  "geometry": {"coordinates":[4.46976,51.92297],"type":"Point"}
}