{
  "type": "Feature",
  "properties": {
    "iso:country":"NL",
    "sg:address":"Molenwg 36",
    "sg:city":"Roggel",
    "sg:orig_category":"Agenturen En Commissiehandel",
    "sg:phone":"+31 475 497 155",
    "sg:postcode":"6088 AS",
    "sg:province":"Limburg",
    "wof:name":"Traxim Bv",
    "wof:placetype":"venue"
},
  "geometry": {"coordinates":[5.927782,51.261497],"type":"Point"}
}