{
  "type": "Feature",
  "properties": {
    "iso:country":"NL",
    "sg:address":"Oude Tweebergenpoort 5",
    "sg:city":"Maastricht",
    "sg:orig_category":"Meubelreparatie And -Restauratie",
    "sg:phone":"+31 43 325 7883",
    "sg:postcode":"6211 TD",
    "sg:province":"Limburg",
    "wof:name":"Iskander",
    "wof:placetype":"venue"
},
  "geometry": {"coordinates":[5.685717,50.849503],"type":"Point"}
}