{
  "type": "Feature",
  "properties": {
    "addr:full":"Markt 2 Wyk By Duurstede Utrecht 3961 BC",
    "addr:housenumber":"2",
    "addr:postcode":"duurstede;3961 bc",
    "addr:street":"Markt",
    "iso:country":"NL",
    "sg:address":"Markt 2",
    "sg:city":"Wyk By Duurstede",
    "sg:classifiers":[
        {
            "category":"Travel",
            "subcategory":"Hotels & Motels",
            "type":"Entertainment"
        }
    ],
    "sg:phone":"+31 343 571 372",
    "sg:postcode":"3961 BC",
    "sg:province":"Utrecht",
    "wof:name":"Oude Lantaarn, De",
    "wof:placetype":"venue"
},
  "geometry": {"coordinates":[5.344905,51.972675],"type":"Point"}
}