{
  "type": "Feature",
  "properties": {
    "iso:country":"NL",
    "sg:address":"Nederlandln 1A",
    "sg:city":"Stadskanaal",
    "sg:orig_category":"Kappers",
    "sg:phone":"+31 599 650 000",
    "sg:postcode":"9501 CA",
    "sg:province":"Groningen",
    "wof:name":"Diana",
    "wof:placetype":"venue"
},
  "geometry": {"coordinates":[6.9613080025,52.9872245789],"type":"Point"}
}