{
  "type": "Feature",
  "properties": {
    "addr:full":"Lombardijeweg 50 Alkmaar Noord-Holland 1827 CC",
    "addr:housenumber":"50",
    "addr:postcode":"1827 cc",
    "addr:street":"Lombardijeweg",
    "iso:country":"NL",
    "sg:address":"Lombardijeweg 50",
    "sg:city":"Alkmaar",
    "sg:classifiers":[
        {
            "category":"Education",
            "subcategory":"Preschool",
            "type":"Public Place"
        }
    ],
    "sg:phone":"+31 72 564 6062",
    "sg:postcode":"1827 CC",
    "sg:province":"Noord-Holland",
    "sg:tags":[
        "kleuteronderwijs",
        "basis-"
    ],
    "wof:name":"Katholieke Basisschool De Gondelier",
    "wof:placetype":"venue"
},
  "geometry": {"coordinates":[4.760874,52.664322],"type":"Point"}
}