{
  "type": "Feature",
  "properties": {
    "addr:full":"De Grutto 1 Almelo NL.08 7609 AH",
    "addr:housenumber":"1;nl.08",
    "addr:postcode":"7609 ah",
    "addr:street":"De Grutto",
    "iso:country":"NL",
    "sg:address":"De Grutto 1",
    "sg:city":"Almelo",
    "sg:orig_category":"Kinderopvang Behalve Thuis",
    "sg:phone":"+31 546 820 920",
    "sg:postcode":"7609 AH",
    "sg:province":"NL.08",
    "wof:name":"De Blokkendoos",
    "wof:placetype":"venue"
},
  "geometry": {"coordinates":[6.635745,52.338352],"type":"Point"}
}