{
  "type": "Feature",
  "properties": {
    "addr:full":"Geminiwg 9 Tilburg North Brabant 5015 BP",
    "addr:housenumber":"9",
    "addr:postcode":"5015 bp",
    "addr:street":"Geminiwg",
    "iso:country":"NL",
    "sg:address":"Geminiwg 9",
    "sg:city":"Tilburg",
    "sg:orig_category":"Wijnkoperijen En -Groothandel",
    "sg:phone":"+31 13 584 1210",
    "sg:postcode":"5015 BP",
    "sg:province":"North Brabant",
    "wof:name":"Jean Arnaud Bv",
    "wof:placetype":"venue"
},
  "geometry": {"coordinates":[5.1135821342,51.5709724426],"type":"Point"}
}