{
  "type": "Feature",
  "properties": {
    "addr:full":"Milhezerw 10 Deurne Noord-Brabant 5752 BC",
    "addr:housenumber":"10",
    "addr:postcode":"5752 bc",
    "addr:street":"Milhezerw",
    "iso:country":"NL",
    "sg:address":"Milhezerw 10",
    "sg:city":"Deurne",
    "sg:orig_category":"Peuterspeelzalen",
    "sg:phone":"+31 493 317 212",
    "sg:postcode":"5752 BC",
    "sg:province":"Noord-Brabant",
    "wof:name":"Walsberg",
    "wof:placetype":"venue"
},
  "geometry": {"coordinates":[5.803383,51.47282],"type":"Point"}
}