{
  "type": "Feature",
  "properties": {
    "addr:full":"De Ruyterstr 9A Huizen North Holland 1271 SR",
    "addr:housenumber":"9a",
    "addr:postcode":"1271 sr",
    "iso:country":"NL",
    "sg:address":"De Ruyterstr 9A",
    "sg:city":"Huizen",
    "sg:orig_category":"Psychotherapeuten",
    "sg:phone":"+31 35 526 2522",
    "sg:postcode":"1271 SR",
    "sg:province":"North Holland",
    "wof:name":"Spel",
    "wof:placetype":"venue"
},
  "geometry": {"coordinates":[5.229442,52.298126],"type":"Point"}
}