{
  "type": "Feature",
  "properties": {
    "iso:country":"NL",
    "sg:address":"Maaslandln 2",
    "sg:city":"Weert",
    "sg:orig_category":"Artsen - Huisartsen",
    "sg:phone":"+31 495 533 888",
    "sg:postcode":"6004 GC",
    "sg:province":"Limburg",
    "wof:name":"Weijnen, R C C",
    "wof:placetype":"venue"
},
  "geometry": {"coordinates":[5.715696,51.254524],"type":"Point"}
}