{
  "type": "Feature",
  "properties": {
    "addr:full":"Oosterpk 23 Assen Drenthe 9404 BD",
    "addr:housenumber":"23",
    "addr:postcode":"9404 bd",
    "addr:street":"Oosterpk",
    "iso:country":"NL",
    "sg:address":"Oosterpk 23",
    "sg:city":"Assen",
    "sg:orig_category":"Schoonheidsinstituten",
    "sg:phone":"+31 592 353 987",
    "sg:postcode":"9404 BD",
    "sg:province":"Drenthe",
    "wof:name":"Irma Hekker Schoonheidssalon",
    "wof:placetype":"venue"
},
  "geometry": {"coordinates":[6.574897,52.993587],"type":"Point"}
}