{
  "type": "Feature",
  "properties": {
    "addr:full":"Reigerlaan 35 De Lier Zuid-Holland 2678 WR",
    "addr:housenumber":"35",
    "addr:postcode":"2678 wr",
    "addr:street":"Reigerlaan",
    "iso:country":"NL",
    "sg:address":"Reigerlaan 35",
    "sg:city":"De Lier",
    "sg:orig_category":"Verzekeringen",
    "sg:phone":"+31 174 520 012",
    "sg:postcode":"2678 WR",
    "sg:province":"Zuid-Holland",
    "wof:name":"Guijs Pensioen Adviesburo",
    "wof:placetype":"venue"
},
  "geometry": {"coordinates":[4.250386,51.980026],"type":"Point"}
}