{
  "type": "Feature",
  "properties": {
    "addr:full":"Burg V Haarenln 742 Schiedam Zuid-Holland 3119 GT",
    "addr:housenumber":"742",
    "addr:postcode":"3119 gt",
    "addr:street":"Burg V Haarenln",
    "iso:country":"NL",
    "sg:address":"Burg V Haarenln 742",
    "sg:city":"Schiedam",
    "sg:orig_category":"Kunstgebitten",
    "sg:phone":"+31 10 470 0246",
    "sg:postcode":"3119 GT",
    "sg:province":"Zuid-Holland",
    "wof:name":"Marcodent Tandtechniek",
    "wof:placetype":"venue"
},
  "geometry": {"coordinates":[4.39816,51.918472],"type":"Point"}
}