{
  "type": "Feature",
  "properties": {
    "iso:country":"NL",
    "sg:address":"Gravenwg 5",
    "sg:city":"Landgraaf",
    "sg:orig_category":"Adviesbureaus Bedrijfsorganisatie",
    "sg:phone":"+31 45 531 1897",
    "sg:postcode":"6374 BA",
    "sg:province":"Limburg",
    "wof:name":"Konrad, Ing T C W",
    "wof:placetype":"venue"
},
  "geometry": {"coordinates":[6.039911,50.922546],"type":"Point"}
}