{
  "type": "Feature",
  "properties": {
    "addr:full":"Feithenhofwg 5 Epe Gelderland 8161 BS",
    "addr:housenumber":"5",
    "addr:postcode":"8161 bs",
    "addr:street":"Feithenhofwg;Gelderland",
    "iso:country":"NL",
    "sg:address":"Feithenhofwg 5",
    "sg:city":"Epe",
    "sg:orig_category":"Montagebedrijven",
    "sg:phone":"+31 578 621 687",
    "sg:postcode":"8161 BS",
    "sg:province":"Gelderland",
    "wof:name":"Suurland Vof",
    "wof:placetype":"venue"
},
  "geometry": {"coordinates":[5.998795,52.358105],"type":"Point"}
}