{
  "type": "Feature",
  "properties": {
    "addr:full":"Kon Julianaln 372 Voorburg South Holland 2274 JV",
    "addr:housenumber":"372",
    "addr:postcode":"2274 jv",
    "addr:street":"Kon",
    "iso:country":"NL",
    "sg:address":"Kon Julianaln 372",
    "sg:city":"Voorburg",
    "sg:orig_category":"Kappers",
    "sg:phone":"+31 70 369 2828",
    "sg:postcode":"2274 JV",
    "sg:province":"South Holland",
    "sg:website":"http://www.mario-s.nl",
    "wof:name":"Mario",
    "wof:placetype":"venue"
},
  "geometry": {"coordinates":[4.359316,52.074848],"type":"Point"}
}