{
  "type": "Feature",
  "properties": {
    "addr:full":"Fort Willemwg 12B Maastricht Limburg 6219 PB",
    "addr:housenumber":"12b",
    "addr:postcode":"6219 pb",
    "iso:country":"NL",
    "sg:address":"Fort Willemwg 12B",
    "sg:city":"Maastricht",
    "sg:orig_category":"Koffie- En Theehuizen",
    "sg:phone":"+31 43 321 1455",
    "sg:postcode":"6219 PB",
    "sg:province":"Limburg",
    "sg:website":"http://www.topgrow.com",
    "wof:name":"Topshop Cv",
    "wof:placetype":"venue"
},
  "geometry": {"coordinates":[5.684405,50.861069],"type":"Point"}
}