{
  "type": "Feature",
  "properties": {
    "iso:country":"NL",
    "sg:address":"Boonswg 11",
    "sg:city":"Heinenoord",
    "sg:orig_category":"Grondboringen En Bronbemalingen",
    "sg:phone":"+31 186 607 100",
    "sg:postcode":"3274 LH",
    "sg:province":"Zuid-Holland",
    "sg:website":"http://www.mos.nl",
    "wof:name":"Mos Grondwatertechniek",
    "wof:placetype":"venue"
},
  "geometry": {"coordinates":[4.520492,51.812614],"type":"Point"}
}