{
  "type": "Feature",
  "properties": {
    "addr:full":"J V Ruysdaelstr 20 Hoogezand Groningen 9601 XM",
    "addr:housenumber":"20",
    "addr:postcode":"9601 xm",
    "addr:street":"J;Ruysdaelstr",
    "iso:country":"NL",
    "sg:address":"J V Ruysdaelstr 20",
    "sg:city":"Hoogezand",
    "sg:orig_category":"Kappers",
    "sg:phone":"+31 598 398 499",
    "sg:postcode":"9601 XM",
    "sg:province":"Groningen",
    "wof:name":"Hartman, Jolanda",
    "wof:placetype":"venue"
},
  "geometry": {"coordinates":[6.7485799789,53.1655006409],"type":"Point"}
}