{
  "type": "Feature",
  "properties": {
    "addr:full":"Jaagpad 23 Leiderdorp South Holland 2351 SV",
    "addr:housenumber":"23",
    "addr:postcode":"2351 sv",
    "addr:street":"Jaagpad",
    "iso:country":"NL",
    "sg:address":"Jaagpad 23",
    "sg:city":"Leiderdorp",
    "sg:orig_category":"Zuivelproducten",
    "sg:phone":"+31 71 541 6532",
    "sg:postcode":"2351 SV",
    "sg:province":"South Holland",
    "wof:name":"Melk- En Zuivelhandel Lieverse",
    "wof:placetype":"venue"
},
  "geometry": {"coordinates":[4.530063,52.14241],"type":"Point"}
}