{
  "type": "Feature",
  "properties": {
    "addr:full":"De Frisia 152 Drachten Provincie Friesland 9207 CZ",
    "addr:housenumber":"152;9207",
    "addr:street":"De Frisia;Provincie Friesland",
    "iso:country":"NL",
    "sg:address":"De Frisia 152",
    "sg:city":"Drachten",
    "sg:orig_category":"Scholen Voor Basisonderwijs",
    "sg:phone":"+31 512 521 100",
    "sg:postcode":"9207 CZ",
    "sg:province":"Provincie Friesland",
    "sg:website":"http://www.euronet.nl/~gco_bold/",
    "wof:name":"Bolder Openb, De",
    "wof:placetype":"venue"
},
  "geometry": {"coordinates":[6.083952,53.11964],"type":"Point"}
}