{
  "type": "Feature",
  "properties": {
    "iso:country":"NL",
    "sg:address":"13 Aprilstraat 1",
    "sg:city":"Oosterwolde Fr",
    "sg:orig_category":"Autokeuringen",
    "sg:phone":"+31 516 512 400",
    "sg:postcode":"8431 GE",
    "sg:province":"Friesland",
    "wof:name":"Garage Galama Bv",
    "wof:placetype":"venue"
},
  "geometry": {"coordinates":[6.297852,52.988983],"type":"Point"}
}