{
  "type": "Feature",
  "properties": {
    "addr:full":"Zevenend 66 Laren Nh Noord-Holland 1251 RP",
    "addr:housenumber":"66",
    "addr:postcode":"1251 rp",
    "addr:street":"Zevenend",
    "iso:country":"NL",
    "sg:address":"Zevenend 66",
    "sg:city":"Laren Nh",
    "sg:orig_category":"Adviesbureaus Bedrijfsorganisatie",
    "sg:phone":"+31 35 531 7254",
    "sg:postcode":"1251 RP",
    "sg:province":"Noord-Holland",
    "wof:name":"Louman En Partners",
    "wof:placetype":"venue"
},
  "geometry": {"coordinates":[5.228743,52.24823],"type":"Point"}
}