{
  "type": "Feature",
  "properties": {
    "addr:full":"Postwg 160 Lunteren Gelderland 6741 MN",
    "addr:housenumber":"160",
    "addr:postcode":"6741 mn",
    "addr:street":"Gelderland",
    "iso:country":"NL",
    "sg:address":"Postwg 160",
    "sg:city":"Lunteren",
    "sg:orig_category":"Pluimveebedrijven En -Handelaren",
    "sg:phone":"+31 342 412 758",
    "sg:postcode":"6741 MN",
    "sg:province":"Gelderland",
    "wof:name":"Verbeek Bv",
    "wof:placetype":"venue"
},
  "geometry": {"coordinates":[5.567877,52.098953],"type":"Point"}
}