{
  "type": "Feature",
  "properties": {
    "iso:country":"NL",
    "sg:address":"Repel 11",
    "sg:city":"Zevenbergen",
    "sg:orig_category":"Bedrijfsopleidingen",
    "sg:phone":"+31 168 324 821",
    "sg:postcode":"4761 XB",
    "sg:province":"North Brabant",
    "wof:name":"Bob, Bureau",
    "wof:placetype":"venue"
},
  "geometry": {"coordinates":[4.583828,51.644638],"type":"Point"}
}