{
  "type": "Feature",
  "properties": {
    "iso:country":"NL",
    "sg:address":"Icarusweg 16",
    "sg:city":"Leeuwarden",
    "sg:orig_category":"Makelaars In Onroerend Goed",
    "sg:phone":"+31 58 288 6926",
    "sg:postcode":"8938 AX",
    "sg:province":"Provincie Friesland",
    "wof:name":"Bedrijvencentrum Leeuwarden",
    "wof:placetype":"venue"
},
  "geometry": {"coordinates":[5.8491,53.197128],"type":"Point"}
}