{
  "type": "Feature",
  "properties": {
    "addr:full":"Schaapsdrift 117 Arnhem Gelderland 6824 GR",
    "addr:housenumber":"117",
    "addr:postcode":"6824",
    "addr:street":"Schaapsdrift",
    "iso:country":"NL",
    "sg:address":"Schaapsdrift 117",
    "sg:city":"Arnhem",
    "sg:classifiers":[
        {
            "category":"Wholesale",
            "subcategory":"Meat",
            "type":"Manufacturing & Wholesale Goods"
        }
    ],
    "sg:phone":"+31 26 384 4848",
    "sg:postcode":"6824 GR",
    "sg:province":"Gelderland",
    "sg:tags":[
        "regeltechniek",
        "en",
        "meet-"
    ],
    "sg:website":"http://www.kobold.com",
    "wof:name":"Kobold Instrumentatie Bv",
    "wof:placetype":"venue"
},
  "geometry": {"coordinates":[5.942666,51.987789],"type":"Point"}
}