{
  "type": "Feature",
  "properties": {
    "iso:country":"NL",
    "sg:address":"Beethovenstraat 417",
    "sg:city":"Roermond",
    "sg:orig_category":"Hoger Onderwijs",
    "sg:phone":"+31 475 322 688",
    "sg:postcode":"6044 PP",
    "sg:province":"Limburg",
    "wof:name":"Ensaid",
    "wof:placetype":"venue"
},
  "geometry": {"coordinates":[6.012206,51.183132],"type":"Point"}
}