{
  "type": "Feature",
  "properties": {
    "addr:full":"Kapellestr 17 Veere Zeeland 4351 AL",
    "addr:housenumber":"17",
    "addr:postcode":"4351 al",
    "addr:street":"Kapellestr",
    "iso:country":"NL",
    "sg:address":"Kapellestr 17",
    "sg:city":"Veere",
    "sg:orig_category":"Antiquiteiten",
    "sg:phone":"+31 118 501 213",
    "sg:postcode":"4351 AL",
    "sg:province":"Zeeland",
    "wof:name":"Schenkenberg-Tak",
    "wof:placetype":"venue"
},
  "geometry": {"coordinates":[3.66677,51.547905],"type":"Point"}
}