{
  "type": "Feature",
  "properties": {
    "addr:full":"Kerkbuurt 17 Oostzaan North Holland 1511 BB",
    "addr:housenumber":"17",
    "addr:postcode":"1511 bb",
    "addr:street":"Kerkbuurt",
    "iso:country":"NL",
    "sg:address":"Kerkbuurt 17",
    "sg:city":"Oostzaan",
    "sg:classifiers":[
        {
            "category":"Shopping",
            "subcategory":"Gifts & Souvenirs",
            "type":"Retail Goods"
        }
    ],
    "sg:phone":"+31 75 684 4643",
    "sg:postcode":"1511 BB",
    "sg:province":"North Holland",
    "sg:tags":[
        "geschenken"
    ],
    "wof:name":"G.J. De Klerk",
    "wof:placetype":"venue"
},
  "geometry": {"coordinates":[4.874902,52.440758],"type":"Point"}
}