{
  "type": "Feature",
  "properties": {
    "addr:full":"Banstr 15 Amsterdam North Holland 1071 JV",
    "addr:housenumber":"15",
    "addr:postcode":"1071 jv",
    "addr:street":"Banstr",
    "iso:country":"NL",
    "sg:address":"Banstr 15",
    "sg:city":"Amsterdam",
    "sg:orig_category":"Juridische Adviseurs",
    "sg:phone":"+31 20 671 7887",
    "sg:postcode":"1071 JV",
    "sg:province":"North Holland",
    "wof:name":"Intralegem",
    "wof:placetype":"venue"
},
  "geometry": {"coordinates":[4.874131,52.355186],"type":"Point"}
}