{
  "type": "Feature",
  "properties": {
    "addr:full":"Kerkstr 57 Reutum Overijssel 7667 PV",
    "addr:housenumber":"57",
    "addr:postcode":"7667 pv",
    "addr:street":"Kerkstr",
    "iso:country":"NL",
    "sg:address":"Kerkstr 57",
    "sg:city":"Reutum",
    "sg:orig_category":"Kappers",
    "sg:phone":"+31 541 670 574",
    "sg:postcode":"7667 PV",
    "sg:province":"Overijssel",
    "wof:name":"Oude Luttikhuis, Salon",
    "wof:placetype":"venue"
},
  "geometry": {"coordinates":[6.84453,52.392529],"type":"Point"}
}