{
  "type": "Feature",
  "properties": {
    "iso:country":"NL",
    "sg:address":"Herenstraat 126",
    "sg:city":"Voorhout",
    "sg:orig_category":"Kappers",
    "sg:phone":"+31 252 230 202",
    "sg:postcode":"2215 KL",
    "sg:province":"South Holland",
    "wof:name":"Haarmode Francine",
    "wof:placetype":"venue"
},
  "geometry": {"coordinates":[4.4833159447,52.2223472595],"type":"Point"}
}