{
  "type": "Feature",
  "properties": {
    "addr:full":"Edisonweg 7 Coevorden Drenthe 7741 KS",
    "addr:housenumber":"7",
    "addr:postcode":"7741 ks",
    "addr:street":"Edisonweg",
    "iso:country":"NL",
    "sg:address":"Edisonweg 7",
    "sg:city":"Coevorden",
    "sg:orig_category":"Hout Gh",
    "sg:phone":"+31 524 516 471",
    "sg:postcode":"7741 KS",
    "sg:province":"Drenthe",
    "wof:name":"Deurenspeciaalzaak",
    "wof:placetype":"venue"
},
  "geometry": {"coordinates":[6.727988,52.659245],"type":"Point"}
}