{
  "type": "Feature",
  "properties": {
    "addr:full":"Lombardkd 87 Rotterdam South Holland 3011 ZG",
    "addr:housenumber":"87",
    "addr:postcode":"3011 zg",
    "addr:street":"Lombardkd",
    "iso:country":"NL",
    "sg:address":"Lombardkd 87",
    "sg:city":"Rotterdam",
    "sg:orig_category":"Meubelen",
    "sg:phone":"+31 10 414 8700",
    "sg:postcode":"3011 ZG",
    "sg:province":"South Holland",
    "wof:name":"Vonder Bv",
    "wof:placetype":"venue"
},
  "geometry": {"coordinates":[4.483073,51.922993],"type":"Point"}
}