{
  "type": "Feature",
  "properties": {
    "addr:full":"Stationsstraat 21 Ermelo Gelderland 3851 NA",
    "addr:housenumber":"21",
    "addr:postcode":"3851 na",
    "addr:street":"Stationsstraat;Gelderland",
    "iso:country":"NL",
    "sg:address":"Stationsstraat 21",
    "sg:city":"Ermelo",
    "sg:orig_category":"Bloemen And Planten",
    "sg:phone":"+31 341 551 479",
    "sg:postcode":"3851 NA",
    "sg:province":"Gelderland",
    "wof:name":"Didi'S Flora",
    "wof:placetype":"venue"
},
  "geometry": {"coordinates":[5.628496,52.300629],"type":"Point"}
}