{
  "type": "Feature",
  "properties": {
    "addr:full":"Overspoor 35 Nibbixwoud Noord-Holland 1688 JH",
    "addr:housenumber":"35",
    "addr:postcode":"1688 jh",
    "addr:street":"Overspoor",
    "iso:country":"NL",
    "sg:address":"Overspoor 35",
    "sg:city":"Nibbixwoud",
    "sg:orig_category":"Parfum And Cosmetica Gh",
    "sg:phone":"+31 229 572 999",
    "sg:postcode":"1688 JH",
    "sg:province":"Noord-Holland",
    "wof:name":"Trend Cosmetics Bv",
    "wof:placetype":"venue"
},
  "geometry": {"coordinates":[5.03387,52.68874],"type":"Point"}
}