{
  "type": "Feature",
  "properties": {
    "addr:full":"Gerard Burgerlaan 8 Vlaardingen Zuid-Holland 3131 KZ",
    "addr:housenumber":"8",
    "addr:postcode":"3131 kz",
    "addr:street":"Gerard Burgerlaan",
    "iso:country":"NL",
    "sg:address":"Gerard Burgerlaan 8",
    "sg:city":"Vlaardingen",
    "sg:orig_category":"Meubelzaken, Woning- And Keukeninrichting",
    "sg:phone":"+31 10 248 0149",
    "sg:postcode":"3131 KZ",
    "sg:province":"Zuid-Holland",
    "wof:name":"Witter Wonen",
    "wof:placetype":"venue"
},
  "geometry": {"coordinates":[4.335626,51.917416],"type":"Point"}
}