{
  "type": "Feature",
  "properties": {
    "addr:full":"Schumansngl 23 Ede Gld Gelderland 6716 KC",
    "addr:housenumber":"23",
    "addr:postcode":"6716 kc",
    "addr:street":"Schumansngl;Gld Gelderland",
    "iso:country":"NL",
    "sg:address":"Schumansngl 23",
    "sg:city":"Ede Gld",
    "sg:orig_category":"Land- En Tuinbouw - Loonbedrijven",
    "sg:phone":"+31 318 640 419",
    "sg:postcode":"6716 KC",
    "sg:province":"Gelderland",
    "wof:name":"Roseboom, E W",
    "wof:placetype":"venue"
},
  "geometry": {"coordinates":[5.66767,52.044979],"type":"Point"}
}