{
  "type": "Feature",
  "properties": {
    "addr:full":"Plantsoenstraat 87 Doetinchem Gelderland 7001 AB",
    "addr:housenumber":"87",
    "addr:postcode":"7001 ab",
    "addr:street":"Plantsoenstraat;Gelderland",
    "iso:country":"NL",
    "sg:address":"Plantsoenstraat 87",
    "sg:city":"Doetinchem",
    "sg:orig_category":"Verzekeringen",
    "sg:phone":"+31 314 361 606",
    "sg:postcode":"7001 AB",
    "sg:province":"Gelderland",
    "wof:name":"Pensioendesk Doetinchem",
    "wof:placetype":"venue"
},
  "geometry": {"coordinates":[6.292346,51.965397],"type":"Point"}
}