{
  "type": "Feature",
  "properties": {
    "addr:full":"Steenstr 162A Boxmeer North Brabant 5831 JK",
    "addr:housenumber":"162a",
    "addr:postcode":"5831 jk",
    "iso:country":"NL",
    "sg:address":"Steenstr 162A",
    "sg:city":"Boxmeer",
    "sg:orig_category":"Psychologen",
    "sg:phone":"+31 485 520 582",
    "sg:postcode":"5831 JK",
    "sg:province":"North Brabant",
    "wof:name":"Psychologenpraktijk Boxmeer",
    "wof:placetype":"venue"
},
  "geometry": {"coordinates":[5.945746,51.648647],"type":"Point"}
}