{
  "type": "Feature",
  "properties": {
    "addr:full":"Zwanebloem 37 Kockengen Utrecht 3628 NA",
    "addr:housenumber":"37",
    "addr:postcode":"3628 na",
    "addr:street":"Zwanebloem",
    "iso:country":"NL",
    "sg:address":"Zwanebloem 37",
    "sg:city":"Kockengen",
    "sg:classifiers":[
        {
            "category":"Wholesale",
            "subcategory":"Meat",
            "type":"Manufacturing & Wholesale Goods"
        }
    ],
    "sg:phone":"+31 346 242 188",
    "sg:postcode":"3628 NA",
    "sg:province":"Utrecht",
    "sg:tags":[
        "regeltechniek",
        "en",
        "meet-"
    ],
    "wof:name":"Cad",
    "wof:placetype":"venue"
},
  "geometry": {"coordinates":[4.954395,52.150894],"type":"Point"}
}