{
  "type": "Feature",
  "properties": {
    "addr:full":"Dresselhuysstr 3A Rotterdam Zuid-Holland 3039 ZH",
    "addr:housenumber":"3a",
    "addr:postcode":"3039 zh",
    "addr:street":"Dresselhuysstr",
    "iso:country":"NL",
    "sg:address":"Dresselhuysstr 3A",
    "sg:city":"Rotterdam",
    "sg:orig_category":"Makelaars En Adviseurs Onroerende Goederen",
    "sg:phone":"+31 10 466 3002",
    "sg:postcode":"3039 ZH",
    "sg:province":"Zuid-Holland",
    "sg:website":"http://www.adelbrecht.nl",
    "wof:name":"Adelbrecht Bv",
    "wof:placetype":"venue"
},
  "geometry": {"coordinates":[4.460222,51.930546],"type":"Point"}
}