{
  "type": "Feature",
  "properties": {
    "addr:full":"Stationsstraat 17 Assen Drenthe 9401 KV",
    "addr:housenumber":"17",
    "addr:postcode":"9401 kv",
    "addr:street":"Stationsstraat",
    "iso:country":"NL",
    "sg:address":"Stationsstraat 17",
    "sg:city":"Assen",
    "sg:classifiers":[
        {
            "category":"Travel",
            "subcategory":"Hotels & Motels",
            "type":"Entertainment"
        }
    ],
    "sg:phone":"+31 592 313 517",
    "sg:postcode":"9401 KV",
    "sg:province":"Drenthe",
    "wof:name":"Christerus",
    "wof:placetype":"venue"
},
  "geometry": {"coordinates":[6.567488,52.993465],"type":"Point"}
}