{
  "type": "Feature",
  "properties": {
    "addr:full":"Markt 27 Gouda Zuid-Holland 2801 JJ",
    "addr:housenumber":"27",
    "addr:postcode":"2801 jj",
    "addr:street":"Markt",
    "iso:country":"NL",
    "sg:address":"Markt 27",
    "sg:city":"Gouda",
    "sg:orig_category":"Verenigingen En Stichtingen",
    "sg:phone":"+31 182 511 300",
    "sg:postcode":"2801 JJ",
    "sg:province":"Zuid-Holland",
    "wof:name":"Gouda Hart Van Holland, Sticht",
    "wof:placetype":"venue"
},
  "geometry": {"coordinates":[4.71135,52.011925],"type":"Point"}
}