{
  "type": "Feature",
  "properties": {
    "addr:full":"Stationstr 37 Baarle Nassau North Brabant 5111 CK",
    "addr:housenumber":"37",
    "addr:postcode":"5111 ck",
    "addr:street":"Stationstr;Nassau",
    "iso:country":"NL",
    "sg:address":"Stationstr 37",
    "sg:city":"Baarle Nassau",
    "sg:orig_category":"Kappers",
    "sg:phone":"+31 13 507 8461",
    "sg:postcode":"5111 CK",
    "sg:province":"North Brabant",
    "wof:name":"Hairpoint",
    "wof:placetype":"venue"
},
  "geometry": {"coordinates":[4.9262900352,51.4497413635],"type":"Point"}
}