{
  "type": "Feature",
  "properties": {
    "iso:country":"NL",
    "sg:address":"Tjalk 2305",
    "sg:city":"Lelystad",
    "sg:orig_category":"Kappers",
    "sg:phone":"+31 320 250 328",
    "sg:postcode":"8232 LR",
    "sg:province":"NL.",
    "wof:name":"Pellequeria",
    "wof:placetype":"venue"
},
  "geometry": {"coordinates":[5.47179,52.504253],"type":"Point"}
}