{
  "type": "Feature",
  "properties": {
    "addr:full":"Tjalk 2305 Lelystad NL. 8232 LR",
    "addr:housenumber":"2305",
    "addr:postcode":"8232 lr",
    "addr:street":"Tjalk;Nl.",
    "iso:country":"NL",
    "sg:address":"Tjalk 2305",
    "sg:city":"Lelystad",
    "sg:orig_category":"Kappers",
    "sg:phone":"+31 320 250 328",
    "sg:postcode":"8232 LR",
    "sg:province":"NL.",
    "wof:name":"Pellequeria",
    "wof:placetype":"venue"
},
  "geometry": {"coordinates":[5.47179,52.504253],"type":"Point"}
}