{
  "type": "Feature",
  "properties": {
    "addr:full":"Fivelstr 12 Ten Boer Groningen 9791 LN",
    "addr:housenumber":"12",
    "addr:postcode":"boer;9791 ln",
    "addr:street":"Fivelstr",
    "iso:country":"NL",
    "sg:address":"Fivelstr 12",
    "sg:city":"Ten Boer",
    "sg:orig_category":"Autorijscholen",
    "sg:phone":"+31 50 302 3465",
    "sg:postcode":"9791 LN",
    "sg:province":"Groningen",
    "wof:name":"Tebbens, Jack",
    "wof:placetype":"venue"
},
  "geometry": {"coordinates":[6.698316,53.279945],"type":"Point"}
}