{
  "type": "Feature",
  "properties": {
    "addr:full":"Muiderwg 29 Zeewolde Flevoland 3891 DA",
    "addr:housenumber":"29",
    "addr:postcode":"3891 da",
    "addr:street":"Muiderwg;Flevoland",
    "iso:country":"NL",
    "sg:address":"Muiderwg 29",
    "sg:city":"Zeewolde",
    "sg:orig_category":"Adviesbureaus Bedrijfsorganisatie",
    "sg:phone":"+31 36 540 2992",
    "sg:postcode":"3891 DA",
    "sg:province":"Flevoland",
    "wof:name":"Castanea",
    "wof:placetype":"venue"
},
  "geometry": {"coordinates":[5.528209,52.33477],"type":"Point"}
}