{
  "type": "Feature",
  "properties": {
    "iso:country":"NL",
    "sg:address":"Ln V Rapynen 15",
    "sg:city":"Linschoten",
    "sg:orig_category":"Adviesbureaus Bedrijfsorganisatie",
    "sg:phone":"+31 348 411 102",
    "sg:postcode":"3461 GH",
    "sg:province":"Utrecht",
    "wof:name":"Mims",
    "wof:placetype":"venue"
},
  "geometry": {"coordinates":[4.915227,52.061867],"type":"Point"}
}