{
  "type": "Feature",
  "properties": {
    "addr:full":"V Leeuwenhoekstr 185 Enschede Overijssel 7533 WE",
    "addr:housenumber":"185",
    "addr:postcode":"7533 we",
    "iso:country":"NL",
    "sg:address":"V Leeuwenhoekstr 185",
    "sg:city":"Enschede",
    "sg:orig_category":"Schilders",
    "sg:phone":"+31 53 436 7607",
    "sg:postcode":"7533 WE",
    "sg:province":"Overijssel",
    "wof:name":"Danoun, A",
    "wof:placetype":"venue"
},
  "geometry": {"coordinates":[6.923639,52.221523],"type":"Point"}
}