{
  "type": "Feature",
  "properties": {
    "addr:full":"Rijksstraatweg 110 Haren Gn Groningen 9752 BK",
    "addr:housenumber":"110",
    "addr:postcode":"9752 bk",
    "addr:street":"Rijksstraatweg",
    "iso:country":"NL",
    "sg:address":"Rijksstraatweg 110",
    "sg:city":"Haren Gn",
    "sg:classifiers":[
        {
            "category":"Retail",
            "subcategory":"Storage",
            "type":"Services"
        }
    ],
    "sg:phone":"+31 50 534 5115",
    "sg:postcode":"9752 BK",
    "sg:province":"Groningen",
    "sg:tags":[
        "opslag",
        "bewaring"
    ],
    "wof:name":"Firma Eitens En Zoon",
    "wof:placetype":"venue"
},
  "geometry": {"coordinates":[6.6007699966,53.1755256653],"type":"Point"}
}