{
  "type": "Feature",
  "properties": {
    "iso:country":"NL",
    "sg:address":"A V Kleefstr 65",
    "sg:city":"Oirschot",
    "sg:orig_category":"Logopedisten",
    "sg:phone":"+31 499 578 446",
    "sg:postcode":"5688 AV",
    "sg:province":"Noord-Brabant",
    "wof:name":"Reuzel, Mandy",
    "wof:placetype":"venue"
},
  "geometry": {"coordinates":[5.306918,51.503094],"type":"Point"}
}