{
  "type": "Feature",
  "properties": {
    "addr:full":"Scheldekd 65 Terneuzen Zeeland 4531 EJ",
    "addr:housenumber":"65",
    "addr:postcode":"4531 ej",
    "addr:street":"Scheldekd",
    "iso:country":"NL",
    "sg:address":"Scheldekd 65",
    "sg:city":"Terneuzen",
    "sg:classifiers":[
        {
            "category":"Travel",
            "subcategory":"Hotels & Motels",
            "type":"Entertainment"
        }
    ],
    "sg:phone":"+31 115 694 855",
    "sg:postcode":"4531 EJ",
    "sg:province":"Zeeland",
    "sg:website":"http://www.goldentuliplescaut.nl",
    "wof:name":"L'Escaut",
    "wof:placetype":"venue"
},
  "geometry": {"coordinates":[3.827559,51.338146],"type":"Point"}
}