{
  "type": "Feature",
  "properties": {
    "addr:full":"Geraldadrift 2 Uithuizen Groningen 9981 AK",
    "addr:housenumber":"2",
    "addr:postcode":"9981 ak",
    "addr:street":"Geraldadrift",
    "iso:country":"NL",
    "sg:address":"Geraldadrift 2",
    "sg:city":"Uithuizen",
    "sg:classifiers":[
        {
            "category":"Retail",
            "subcategory":"Auto Repair",
            "type":"Services"
        }
    ],
    "sg:phone":"+31 595 434 020",
    "sg:postcode":"9981 AK",
    "sg:province":"Groningen",
    "sg:tags":[
        "garage"
    ],
    "wof:name":"Kramer Bv",
    "wof:placetype":"venue"
},
  "geometry": {"coordinates":[6.665396,53.409504],"type":"Point"}
}