{
  "type": "Feature",
  "properties": {
    "addr:full":"Fort Jutphaas 3 Nieuwegein Utrecht 3439 LX",
    "addr:housenumber":"3",
    "addr:postcode":"3439 lx",
    "addr:street":"Fort Jutphaas",
    "iso:country":"NL",
    "sg:address":"Fort Jutphaas 3",
    "sg:city":"Nieuwegein",
    "sg:orig_category":"Wijnkoperijen En -Groothandel",
    "sg:phone":"+31 30 603 1708",
    "sg:postcode":"3439 LX",
    "sg:province":"Utrecht",
    "wof:name":"Trouvaille Bv",
    "wof:placetype":"venue"
},
  "geometry": {"coordinates":[5.1000499725,52.0374145508],"type":"Point"}
}