{
  "type": "Feature",
  "properties": {
    "iso:country":"NL",
    "sg:address":"Bylstr 5",
    "sg:city":"Rotterdam",
    "sg:orig_category":"Natuursteen",
    "sg:phone":"+31 10 495 2040",
    "sg:postcode":"3087 AA",
    "sg:province":"Zuid-Holland",
    "sg:website":"http://www.pelt-hooykaas.nl",
    "wof:name":"Pelt & Hooykaas Bv Marmer",
    "wof:placetype":"venue"
},
  "geometry": {"coordinates":[4.459208,51.894024],"type":"Point"}
}