{
  "type": "Feature",
  "properties": {
    "addr:full":"Burg Visschersstr 15 Ulestraten Limburg 6235 EA",
    "addr:housenumber":"15",
    "addr:postcode":"6235 ea",
    "addr:street":"Burg",
    "iso:country":"NL",
    "sg:address":"Burg Visschersstr 15",
    "sg:city":"Ulestraten",
    "sg:orig_category":"Betonboringen",
    "sg:phone":"+31 43 364 9403",
    "sg:postcode":"6235 EA",
    "sg:province":"Limburg",
    "wof:name":"Geurten Bv, Luc",
    "wof:placetype":"venue"
},
  "geometry": {"coordinates":[5.785346,50.90847],"type":"Point"}
}