{
  "type": "Feature",
  "properties": {
    "addr:full":"Voltawg 20 Delft South Holland 2627 BC",
    "addr:housenumber":"20",
    "addr:postcode":"2627 bc",
    "addr:street":"Voltawg",
    "iso:country":"NL",
    "sg:address":"Voltawg 20",
    "sg:city":"Delft",
    "sg:orig_category":"Levensmiddelen - Fabrieken En Groothandel",
    "sg:phone":"+31 15 261 6345",
    "sg:postcode":"2627 BC",
    "sg:province":"South Holland",
    "wof:name":"Holly'S Produkten Bv",
    "wof:placetype":"venue"
},
  "geometry": {"coordinates":[4.374506,51.982788],"type":"Point"}
}