{
  "type": "Feature",
  "properties": {
    "iso:country":"NL",
    "sg:address":"Kometensingel 427",
    "sg:city":"Amsterdam",
    "sg:orig_category":"Loodgieterswerk, Verwarming And Sanitaire Installaties",
    "sg:phone":"+31 20 633 1538",
    "sg:postcode":"1033 BL",
    "sg:province":"Noord-Holland",
    "wof:name":"Ruud Kriger Onderhoudswerk",
    "wof:placetype":"venue"
},
  "geometry": {"coordinates":[4.882826,52.412605],"type":"Point"}
}