{
  "type": "Feature",
  "properties": {
    "addr:full":"Lisdodde 16 Venray Limburg 5803 JX",
    "addr:housenumber":"16",
    "addr:postcode":"5803 jx",
    "addr:street":"Lisdodde",
    "iso:country":"NL",
    "sg:address":"Lisdodde 16",
    "sg:city":"Venray",
    "sg:orig_category":"Adviesbureaus Bedrijfsorganisatie",
    "sg:phone":"+31 478 588 284",
    "sg:postcode":"5803 JX",
    "sg:province":"Limburg",
    "wof:name":"Bommel, Antoon Van",
    "wof:placetype":"venue"
},
  "geometry": {"coordinates":[5.996636,51.535686],"type":"Point"}
}