{
  "type": "Feature",
  "properties": {
    "iso:country":"NL",
    "sg:address":"Havenweg 42",
    "sg:city":"Amersfoort",
    "sg:orig_category":"Personenvervoer Zonder Dienstregeling",
    "sg:phone":"+31 33 465 0360",
    "sg:postcode":"3812 PR",
    "sg:province":"Utrecht",
    "wof:name":"Midnet Tours",
    "wof:placetype":"venue"
},
  "geometry": {"coordinates":[5.369641,52.167904],"type":"Point"}
}