{
  "type": "Feature",
  "properties": {
    "addr:full":"Havenweg 42 Amersfoort Utrecht 3812 PR",
    "addr:housenumber":"42",
    "addr:postcode":"3812 pr",
    "addr:street":"Havenweg",
    "iso:country":"NL",
    "sg:address":"Havenweg 42",
    "sg:city":"Amersfoort",
    "sg:orig_category":"Personenvervoer Zonder Dienstregeling",
    "sg:phone":"+31 33 465 0360",
    "sg:postcode":"3812 PR",
    "sg:province":"Utrecht",
    "wof:name":"Midnet Tours",
    "wof:placetype":"venue"
},
  "geometry": {"coordinates":[5.369641,52.167904],"type":"Point"}
}