{
  "type": "Feature",
  "properties": {
    "addr:full":"Zaagmolen 40 Wyk By Duurstede Utrecht 3962 GB",
    "addr:housenumber":"40",
    "addr:postcode":"duurstede;3962 gb",
    "addr:street":"Zaagmolen",
    "iso:country":"NL",
    "sg:address":"Zaagmolen 40",
    "sg:city":"Wyk By Duurstede",
    "sg:orig_category":"Adviesbureaus Gezondheidszorg",
    "sg:phone":"+31 6 53125036",
    "sg:postcode":"3962 GB",
    "sg:province":"Utrecht",
    "wof:name":"Medidas",
    "wof:placetype":"venue"
},
  "geometry": {"coordinates":[5.347859,51.975487],"type":"Point"}
}