{
  "type": "Feature",
  "properties": {
    "iso:country":"NL",
    "sg:address":"Baanhoek 75",
    "sg:city":"Sliedrecht",
    "sg:orig_category":"Algemene Werktuigbouw",
    "sg:phone":"+31 184 413 515",
    "sg:postcode":"3361 GB",
    "sg:province":"Zuid-Holland",
    "wof:name":"M Baan Hofman",
    "wof:placetype":"venue"
},
  "geometry": {"coordinates":[4.752057,51.823982],"type":"Point"}
}