{
  "type": "Feature",
  "properties": {
    "addr:full":"Ylsterkd 39 Sneek Friesland 8608 AB",
    "addr:housenumber":"39",
    "addr:postcode":"8608 ab",
    "addr:street":"Ylsterkd",
    "iso:country":"NL",
    "sg:address":"Ylsterkd 39",
    "sg:city":"Sneek",
    "sg:orig_category":"Verhuizingen",
    "sg:phone":"+31 515 417 255",
    "sg:postcode":"8608 AB",
    "sg:province":"Friesland",
    "sg:website":"http://www.iventra.nl",
    "wof:name":"Stilma Inventra",
    "wof:placetype":"venue"
},
  "geometry": {"coordinates":[5.65393,53.027611],"type":"Point"}
}