{
  "type": "Feature",
  "properties": {
    "iso:country":"NL",
    "sg:address":"Koudorpstr 34",
    "sg:city":"Westkapelle",
    "sg:classifiers":[
        {
            "category":"Banks & Credit Unions",
            "subcategory":"Investment Brokerage",
            "type":"Services"
        }
    ],
    "sg:phone":"+31 118 571 481",
    "sg:postcode":"4361 BT",
    "sg:province":"Zeeland",
    "sg:tags":[
        "pension"
    ],
    "wof:name":"Gabri\u00eblse-Jansen",
    "wof:placetype":"venue"
},
  "geometry": {"coordinates":[3.43776,51.528927],"type":"Point"}
}