{
  "type": "Feature",
  "properties": {
    "addr:full":"Jan Willem Frisostraat 48A Rotterdam Zuid-Holland 3051 EL",
    "addr:housenumber":"48a",
    "addr:postcode":"3051 el",
    "addr:street":"Jan Willem Frisostraat",
    "iso:country":"NL",
    "sg:address":"Jan Willem Frisostraat 48A",
    "sg:city":"Rotterdam",
    "sg:orig_category":"Zonnebank- En Solariumcentra",
    "sg:phone":"+31 10 418 1699",
    "sg:postcode":"3051 EL",
    "sg:province":"Zuid-Holland",
    "wof:name":"Sun Corner",
    "wof:placetype":"venue"
},
  "geometry": {"coordinates":[4.477575,51.943428],"type":"Point"}
}