{
  "type": "Feature",
  "properties": {
    "addr:full":"Haagweg 270 Breda Noord-Brabant 4812 XG",
    "addr:housenumber":"270",
    "addr:postcode":"4812 xg",
    "addr:street":"Haagweg",
    "iso:country":"NL",
    "sg:address":"Haagweg 270",
    "sg:city":"Breda",
    "sg:orig_category":"Meubelreparatie And -Restauratie",
    "sg:phone":"+31 76 561 2216",
    "sg:postcode":"4812 XG",
    "sg:province":"Noord-Brabant",
    "wof:name":"P.E. Van Glabbeek",
    "wof:placetype":"venue"
},
  "geometry": {"coordinates":[4.754327,51.580196],"type":"Point"}
}