{
  "type": "Feature",
  "properties": {
    "addr:full":"V Stuivenbergwg 40 Winssen Gelderland 6645 AC",
    "addr:housenumber":"40",
    "addr:postcode":"6645 ac",
    "addr:street":"Gelderland",
    "iso:country":"NL",
    "sg:address":"V Stuivenbergwg 40",
    "sg:city":"Winssen",
    "sg:classifiers":[
        {
            "category":"Personal",
            "subcategory":"Nail Salon",
            "type":"Services"
        }
    ],
    "sg:phone":"+31 487 522 821",
    "sg:postcode":"6645 AC",
    "sg:province":"Gelderland",
    "sg:tags":[
        "pedicure"
    ],
    "wof:name":"Kamp-Willems, H Van De",
    "wof:placetype":"venue"
},
  "geometry": {"coordinates":[5.708412,51.882339],"type":"Point"}
}