{
  "type": "Feature",
  "properties": {
    "addr:full":"Hauwert 56 Hauwert North Holland 1691 EH",
    "addr:housenumber":"56",
    "addr:postcode":"1691 eh",
    "addr:street":"Hauwert",
    "iso:country":"NL",
    "sg:address":"Hauwert 56",
    "sg:city":"Hauwert",
    "sg:orig_category":"Bloemen- And Plantenteelt",
    "sg:phone":"+31 229 201 780",
    "sg:postcode":"1691 EH",
    "sg:province":"North Holland",
    "wof:name":"Goldsmith Seeds Europe Bv",
    "wof:placetype":"venue"
},
  "geometry": {"coordinates":[5.096817,52.705341],"type":"Point"}
}