{
  "type": "Feature",
  "properties": {
    "addr:full":"Zaanstraat 24 Geleen Limburg 6163 KW",
    "addr:housenumber":"24",
    "addr:postcode":"6163 kw",
    "addr:street":"Zaanstraat",
    "iso:country":"NL",
    "sg:address":"Zaanstraat 24",
    "sg:city":"Geleen",
    "sg:orig_category":"Autokeuringen",
    "sg:phone":"+31 46 474 7468",
    "sg:postcode":"6163 KW",
    "sg:province":"Limburg",
    "wof:name":"Van Brug Auto'S",
    "wof:placetype":"venue"
},
  "geometry": {"coordinates":[5.832321,50.98315],"type":"Point"}
}