{
  "type": "Feature",
  "properties": {
    "addr:full":"Antilopespoor 107 Maarssen Utrecht 3605 CG",
    "addr:housenumber":"107",
    "addr:postcode":"3605 cg",
    "addr:street":"Antilopespoor",
    "iso:country":"NL",
    "sg:address":"Antilopespoor 107",
    "sg:city":"Maarssen",
    "sg:orig_category":"Onderhoudswerken",
    "sg:phone":"+31 346 568 822",
    "sg:postcode":"3605 CG",
    "sg:province":"Utrecht",
    "wof:name":"Atd",
    "wof:placetype":"venue"
},
  "geometry": {"coordinates":[5.031882,52.134037],"type":"Point"}
}