{
  "type": "Feature",
  "properties": {
    "addr:full":"Buitendams 403 Hardinxveld Giessend South Holland 3371 BH",
    "addr:housenumber":"403",
    "addr:postcode":"3371 bh",
    "addr:street":"Buitendams",
    "iso:country":"NL",
    "sg:address":"Buitendams 403",
    "sg:city":"Hardinxveld Giessend",
    "sg:orig_category":"Diverse Bedrijfsinstallaties Gh",
    "sg:phone":"+31 184 612 777",
    "sg:postcode":"3371 BH",
    "sg:province":"South Holland",
    "wof:name":"Vof J En C Klijn",
    "wof:placetype":"venue"
},
  "geometry": {"coordinates":[4.812224,51.825172],"type":"Point"}
}