{
  "type": "Feature",
  "properties": {
    "addr:full":"Nieuweweg 8 Anna Paulowna Noord-Holland 1761 EH",
    "addr:housenumber":"8",
    "addr:postcode":"1761 eh",
    "addr:street":"Nieuweweg",
    "iso:country":"NL",
    "sg:address":"Nieuweweg 8",
    "sg:city":"Anna Paulowna",
    "sg:classifiers":[
        {
            "category":"Shopping",
            "subcategory":"Gifts & Souvenirs",
            "type":"Retail Goods"
        }
    ],
    "sg:phone":"+31 223 532 234",
    "sg:postcode":"1761 EH",
    "sg:province":"Noord-Holland",
    "sg:tags":[
        "geschenken"
    ],
    "wof:name":"Tina S Little Shop",
    "wof:placetype":"venue"
},
  "geometry": {"coordinates":[4.83282,52.86256],"type":"Point"}
}