{
  "type": "Feature",
  "properties": {
    "addr:full":"Postbus 309 Zaandam Noord-Holland 1500 EH",
    "addr:housenumber":"309",
    "addr:postcode":"1500 eh",
    "addr:street":"Postbus",
    "iso:country":"NL",
    "sg:address":"Postbus 309",
    "sg:city":"Zaandam",
    "sg:orig_category":"Werving En Selectie",
    "sg:phone":"+31 75 772 1508",
    "sg:postcode":"1500 EH",
    "sg:province":"Noord-Holland",
    "sg:website":"http://www.abbonline.nl",
    "wof:name":"Abb Zaanstreek & Waterland",
    "wof:placetype":"venue"
},
  "geometry": {"coordinates":[4.8129501343,52.441619873],"type":"Point"}
}