{
  "type": "Feature",
  "properties": {
    "addr:full":"Celsiusstr 9 Weert Limburg 6003 DG",
    "addr:housenumber":"9",
    "addr:postcode":"6003 dg",
    "addr:street":"Celsiusstr",
    "iso:country":"NL",
    "sg:address":"Celsiusstr 9",
    "sg:city":"Weert",
    "sg:orig_category":"Pompen",
    "sg:phone":"+31 495 457 679",
    "sg:postcode":"6003 DG",
    "sg:province":"Limburg",
    "wof:name":"Nbs Bv",
    "wof:placetype":"venue"
},
  "geometry": {"coordinates":[5.728129,51.271],"type":"Point"}
}