{
  "type": "Feature",
  "properties": {
    "iso:country":"NL",
    "sg:address":"Lonnekerbrugstr 115",
    "sg:city":"Enschede",
    "sg:classifiers":[
        {
            "category":"Professional",
            "type":"Services"
        }
    ],
    "sg:phone":"+31 53 480 1940",
    "sg:postcode":"7547 AM",
    "sg:province":"Overijssel",
    "sg:tags":[
        "leasing"
    ],
    "sg:website":"http://www.technolease.nl",
    "wof:name":"Technolease Bv",
    "wof:placetype":"venue"
},
  "geometry": {"coordinates":[6.850125,52.229752],"type":"Point"}
}