{
  "type": "Feature",
  "properties": {
    "iso:country":"NL",
    "sg:address":"Vechtsteen 28",
    "sg:city":"Wyk By Duurstede",
    "sg:orig_category":"Etiketten",
    "sg:phone":"+31 343 577 267",
    "sg:postcode":"3961 XG",
    "sg:province":"Utrecht",
    "wof:name":"Jf",
    "wof:placetype":"venue"
},
  "geometry": {"coordinates":[5.326381,51.975822],"type":"Point"}
}