{
  "type": "Feature",
  "properties": {
    "addr:full":"Vechtsteen 28 Wyk By Duurstede Utrecht 3961 XG",
    "addr:housenumber":"28",
    "addr:postcode":"duurstede;3961 xg",
    "addr:street":"Vechtsteen",
    "iso:country":"NL",
    "sg:address":"Vechtsteen 28",
    "sg:city":"Wyk By Duurstede",
    "sg:orig_category":"Etiketten",
    "sg:phone":"+31 343 577 267",
    "sg:postcode":"3961 XG",
    "sg:province":"Utrecht",
    "wof:name":"Jf",
    "wof:placetype":"venue"
},
  "geometry": {"coordinates":[5.326381,51.975822],"type":"Point"}
}