{
  "type": "Feature",
  "properties": {
    "iso:country":"NL",
    "sg:address":"Kerkwg 114",
    "sg:city":"Kockengen",
    "sg:orig_category":"Adviesbureaus Financieel",
    "sg:phone":"+31 346 242 351",
    "sg:postcode":"3628 AS",
    "sg:province":"Utrecht",
    "wof:name":"Vav Bv",
    "wof:placetype":"venue"
},
  "geometry": {"coordinates":[4.962688,52.150047],"type":"Point"}
}