{
  "type": "Feature",
  "properties": {
    "addr:full":"Melkmarkt 42 Zwolle Overijssel 8011 ME",
    "addr:housenumber":"42",
    "addr:postcode":"8011 me",
    "addr:street":"Melkmarkt",
    "iso:country":"NL",
    "sg:address":"Melkmarkt 42",
    "sg:city":"Zwolle",
    "sg:orig_category":"Huishoudapparatuur, Televisies And Radio'S",
    "sg:phone":"+31 38 421 1864",
    "sg:postcode":"8011 ME",
    "sg:province":"Overijssel",
    "wof:name":"Handyman",
    "wof:placetype":"venue"
},
  "geometry": {"coordinates":[6.090959,52.513268],"type":"Point"}
}