{
  "type": "Feature",
  "properties": {
    "addr:full":"Funenkd 7 Amsterdam Noord-Holland 1018 AL",
    "addr:housenumber":"7",
    "addr:postcode":"1018 al",
    "addr:street":"Funenkd",
    "iso:country":"NL",
    "sg:address":"Funenkd 7",
    "sg:city":"Amsterdam",
    "sg:orig_category":"Bierbrouwerijen",
    "sg:phone":"+31 20 622 8325",
    "sg:postcode":"1018 AL",
    "sg:province":"Noord-Holland",
    "wof:name":"Ij, 'T",
    "wof:placetype":"venue"
},
  "geometry": {"coordinates":[4.893195,52.373119],"type":"Point"}
}