{
  "type": "Feature",
  "properties": {
    "addr:full":"Ministerlaan 260 Zwolle Overijssel 8014 XM",
    "addr:housenumber":"260",
    "addr:postcode":"8014 xm",
    "addr:street":"Ministerlaan",
    "iso:country":"NL",
    "sg:address":"Ministerlaan 260",
    "sg:city":"Zwolle",
    "sg:orig_category":"Kappers",
    "sg:phone":"+31 38 460 0584",
    "sg:postcode":"8014 XM",
    "sg:province":"Overijssel",
    "wof:name":"Barbershop The Just For Men",
    "wof:placetype":"venue"
},
  "geometry": {"coordinates":[6.1086139679,52.4823684692],"type":"Point"}
}