{
  "type": "Feature",
  "properties": {
    "addr:full":"Duinoordstraat 78 Haarlem Noord-Holland 2023 WE",
    "addr:housenumber":"78",
    "addr:postcode":"2023 we",
    "addr:street":"Duinoordstraat",
    "iso:country":"NL",
    "sg:address":"Duinoordstraat 78",
    "sg:city":"Haarlem",
    "sg:orig_category":"Farmaceutische Producten Gh",
    "sg:phone":"+31 23 527 5060",
    "sg:postcode":"2023 WE",
    "sg:province":"Noord-Holland",
    "wof:name":"Merlijn",
    "wof:placetype":"venue"
},
  "geometry": {"coordinates":[4.633066,52.399933],"type":"Point"}
}