{
  "type": "Feature",
  "properties": {
    "iso:country":"NL",
    "sg:address":"Schimmelpennincklaan 23",
    "sg:city":"Doetinchem",
    "sg:orig_category":"Public Relationbureaus",
    "sg:phone":"+31 314 365 411",
    "sg:postcode":"7003 BN",
    "sg:province":"Gelderland",
    "wof:name":"R. Deutekom",
    "wof:placetype":"venue"
},
  "geometry": {"coordinates":[6.312862,51.965908],"type":"Point"}
}