{
  "type": "Feature",
  "properties": {
    "iso:country":"NL",
    "sg:address":"Vreekesweid 12",
    "sg:city":"Broek Op Langedyk",
    "sg:orig_category":"Verkoopautomaten",
    "sg:phone":"+31 226 331 430",
    "sg:postcode":"1721 PR",
    "sg:province":"Noord-Holland",
    "wof:name":"Bede Bv",
    "wof:placetype":"venue"
},
  "geometry": {"coordinates":[4.79447,52.673218],"type":"Point"}
}