{
  "type": "Feature",
  "properties": {
    "iso:country":"NL",
    "sg:address":"J Naber Erf 237",
    "sg:city":"Dordrecht",
    "sg:orig_category":"Webdesign Bureaus",
    "sg:phone":"+31 6 11113773",
    "sg:postcode":"3315 HG",
    "sg:province":"Zuid-Holland",
    "sg:website":"http://www.multimediasupport.nl",
    "wof:name":"Multimediasupport",
    "wof:placetype":"venue"
},
  "geometry": {"coordinates":[4.7350978851,51.8012962341],"type":"Point"}
}