{
  "type": "Feature",
  "properties": {
    "iso:country":"NL",
    "sg:address":"Lotusstraat 11",
    "sg:city":"Purmerend",
    "sg:orig_category":"Fotostudio'S And Fotografen",
    "sg:phone":"+31 299 472 601",
    "sg:postcode":"1448 BR",
    "sg:province":"North Holland",
    "wof:name":"Stand Evenement Fotografie Yong Vof",
    "wof:placetype":"venue"
},
  "geometry": {"coordinates":[4.946368,52.494156],"type":"Point"}
}