{
  "type": "Feature",
  "properties": {
    "addr:full":"Demer 44 Eindhoven North Brabant 5611 AS",
    "addr:housenumber":"44",
    "addr:postcode":"5611 as",
    "addr:street":"Demer",
    "iso:country":"NL",
    "sg:address":"Demer 44",
    "sg:city":"Eindhoven",
    "sg:orig_category":"Mode-Artikelen Dames En Heren",
    "sg:phone":"+31 40 296 3303",
    "sg:postcode":"5611 AS",
    "sg:province":"North Brabant",
    "wof:name":"Forecast",
    "wof:placetype":"venue"
},
  "geometry": {"coordinates":[5.477067,51.439644],"type":"Point"}
}