{
  "type": "Feature",
  "properties": {
    "addr:full":"Fuikstr 20 Rotterdam Zuid-Holland 3061 LG",
    "addr:housenumber":"20",
    "addr:postcode":"3061 lg",
    "addr:street":"Fuikstr",
    "iso:country":"NL",
    "sg:address":"Fuikstr 20",
    "sg:city":"Rotterdam",
    "sg:orig_category":"Adviesbureaus Bedrijfsorganisatie",
    "sg:phone":"+31 10 453 0685",
    "sg:postcode":"3061 LG",
    "sg:province":"Zuid-Holland",
    "wof:name":"Sims",
    "wof:placetype":"venue"
},
  "geometry": {"coordinates":[4.502032,51.929867],"type":"Point"}
}