{
  "type": "Feature",
  "properties": {
    "addr:full":"A Paulownaln 145 Zeist Utrecht 3708 HP",
    "addr:housenumber":"145",
    "addr:postcode":"3708 hp",
    "iso:country":"NL",
    "sg:address":"A Paulownaln 145",
    "sg:city":"Zeist",
    "sg:orig_category":"Verlichting",
    "sg:phone":"+31 30 691 9699",
    "sg:postcode":"3708 HP",
    "sg:province":"Utrecht",
    "sg:website":"http://www.style-palazzo.com",
    "wof:name":"Style Palazzo Exclusif",
    "wof:placetype":"venue"
},
  "geometry": {"coordinates":[5.262097,52.072857],"type":"Point"}
}