{
  "type": "Feature",
  "properties": {
    "addr:full":"Kempstr 279 S Gravenhage South Holland 2572 GE",
    "addr:housenumber":"279",
    "addr:postcode":"2572",
    "addr:street":"S Gravenhage",
    "iso:country":"NL",
    "sg:address":"Kempstr 279",
    "sg:city":"S Gravenhage",
    "sg:orig_category":"Schilders",
    "sg:phone":"+31 70 346 4845",
    "sg:postcode":"2572 GE",
    "sg:province":"South Holland",
    "wof:name":"Aartsen, R L",
    "wof:placetype":"venue"
},
  "geometry": {"coordinates":[4.29421,52.06422],"type":"Point"}
}