{
  "type": "Feature",
  "properties": {
    "iso:country":"NL",
    "sg:address":"Westzanddk 1",
    "sg:city":"Hellevoetsluis",
    "sg:orig_category":"Onroerende Goederen",
    "sg:phone":"+31 181 390 722",
    "sg:postcode":"3221 AW",
    "sg:province":"South Holland",
    "wof:name":"Kalmthout Bv, Van",
    "wof:placetype":"venue"
},
  "geometry": {"coordinates":[4.127935,51.823158],"type":"Point"}
}