{
  "type": "Feature",
  "properties": {
    "addr:full":"Bellestein 31 Ede Gld Gelderland 6714 DP",
    "addr:housenumber":"31",
    "addr:postcode":"6714 dp",
    "addr:street":"Bellestein;Gld Gelderland",
    "iso:country":"NL",
    "sg:address":"Bellestein 31",
    "sg:city":"Ede Gld",
    "sg:orig_category":"Fietshandelaren",
    "sg:phone":"+31 318 631 202",
    "sg:postcode":"6714 DP",
    "sg:province":"Gelderland",
    "wof:name":"Tweewielershop Veda Fiets",
    "wof:placetype":"venue"
},
  "geometry": {"coordinates":[5.64466,52.042286],"type":"Point"}
}