{
  "type": "Feature",
  "properties": {
    "addr:full":"Minervaweg 12 Delft South Holland 2624 BZ",
    "addr:housenumber":"12",
    "addr:postcode":"2624 bz",
    "addr:street":"Minervaweg",
    "iso:country":"NL",
    "sg:address":"Minervaweg 12",
    "sg:city":"Delft",
    "sg:orig_category":"Kappers",
    "sg:phone":"+31 15 256 1392",
    "sg:postcode":"2624 BZ",
    "sg:province":"South Holland",
    "wof:name":"Dameskapsalon I & I Voor Haar",
    "wof:placetype":"venue"
},
  "geometry": {"coordinates":[4.3556947708,51.996509552],"type":"Point"}
}