{
  "type": "Feature",
  "properties": {
    "addr:full":"1E Atjehstr 94Hs Amsterdam Noord-Holland 1094 KR",
    "addr:housenumber":"94hs",
    "addr:postcode":"1094 kr",
    "addr:street":"1E Atjehstr",
    "iso:country":"NL",
    "sg:address":"1E Atjehstr 94Hs",
    "sg:city":"Amsterdam",
    "sg:classifiers":[
        {
            "category":"Shopping",
            "subcategory":"News",
            "type":"Retail Goods"
        }
    ],
    "sg:phone":"+31 20 663 0228",
    "sg:postcode":"1094 KR",
    "sg:province":"Noord-Holland",
    "sg:tags":[
        "maandbladen",
        "en",
        "week-"
    ],
    "wof:name":"Redoble Agenda Cultural",
    "wof:placetype":"venue"
},
  "geometry": {"coordinates":[4.9353818893,52.3623085022],"type":"Point"}
}