{
  "type": "Feature",
  "properties": {
    "addr:full":"Dorpsstraat 5 Almen Gelderland 7218 AA",
    "addr:housenumber":"5",
    "addr:postcode":"7218 aa",
    "addr:street":"Dorpsstraat;Gelderland",
    "iso:country":"NL",
    "sg:address":"Dorpsstraat 5",
    "sg:city":"Almen",
    "sg:orig_category":"Artistiek Onderwijs",
    "sg:phone":"+31 575 432 057",
    "sg:postcode":"7218 AA",
    "sg:province":"Gelderland",
    "wof:name":"Van Lier Music",
    "wof:placetype":"venue"
},
  "geometry": {"coordinates":[-92.04362500000001,45.431198],"type":"Point"}
}