{
  "type": "Feature",
  "properties": {
    "addr:full":"Spechtln 764 Vlaardingen Zuid-Holland 3136 HW",
    "addr:housenumber":"764",
    "addr:postcode":"3136 hw",
    "iso:country":"NL",
    "sg:address":"Spechtln 764",
    "sg:city":"Vlaardingen",
    "sg:orig_category":"Plafonds",
    "sg:phone":"+31 10 474 3130",
    "sg:postcode":"3136 HW",
    "sg:province":"Zuid-Holland",
    "wof:name":"Marel, R Van Der",
    "wof:placetype":"venue"
},
  "geometry": {"coordinates":[4.352097,51.929035],"type":"Point"}
}