{
  "type": "Feature",
  "properties": {
    "iso:country":"NL",
    "sg:address":"Kerver 15-17",
    "sg:city":"Eersel",
    "sg:orig_category":"Keukens",
    "sg:phone":"+31 497 512 837",
    "sg:postcode":"5521 DA",
    "sg:province":"Noord-Brabant",
    "wof:name":"Vromans",
    "wof:placetype":"venue"
},
  "geometry": {"coordinates":[5.31742,51.366531],"type":"Point"}
}