{
  "type": "Feature",
  "properties": {
    "iso:country":"NL",
    "sg:address":"Texasdreef 5",
    "sg:city":"Utrecht",
    "sg:orig_category":"Kantoorapparatuur Gh",
    "sg:phone":"+31 30 264 2000",
    "sg:postcode":"3565 CL",
    "sg:province":"Utrecht",
    "wof:name":"Mado Bv",
    "wof:placetype":"venue"
},
  "geometry": {"coordinates":[5.0837430954,52.1297683716],"type":"Point"}
}