{
  "type": "Feature",
  "properties": {
    "addr:full":"Zinkerweg 9B Waalwijk Noord-Brabant 5145 NL",
    "addr:housenumber":"9b",
    "addr:postcode":"5145 nl",
    "addr:street":"Zinkerweg",
    "iso:country":"NL",
    "sg:address":"Zinkerweg 9B",
    "sg:city":"Waalwijk",
    "sg:orig_category":"Kantoor- And Schoolbenodigdheden Gh",
    "sg:phone":"+31 416 651 365",
    "sg:postcode":"5145 NL",
    "sg:province":"Noord-Brabant",
    "wof:name":"Packimpro",
    "wof:placetype":"venue"
},
  "geometry": {"coordinates":[5.0491170883,51.6928634644],"type":"Point"}
}