{
  "type": "Feature",
  "properties": {
    "addr:full":"De Wissel 12 St Annaparochie Friesland 9076 PT",
    "addr:housenumber":"12",
    "addr:postcode":"9076 pt",
    "addr:street":"De Wissel",
    "iso:country":"NL",
    "sg:address":"De Wissel 12",
    "sg:city":"St Annaparochie",
    "sg:classifiers":[
        {
            "category":"Retail",
            "subcategory":"Auto Repair",
            "type":"Services"
        }
    ],
    "sg:phone":"+31 518 491 277",
    "sg:postcode":"9076 PT",
    "sg:province":"Friesland",
    "sg:tags":[
        "garage"
    ],
    "wof:name":"Kooy",
    "wof:placetype":"venue"
},
  "geometry": {"coordinates":[5.661298,53.267376],"type":"Point"}
}