{
  "type": "Feature",
  "properties": {
    "addr:full":"Parc Imstenrade 66 Heerlen Limburg 6418 PP",
    "addr:housenumber":"66",
    "addr:postcode":"6418 pp",
    "addr:street":"Parc Imstenrade",
    "iso:country":"NL",
    "sg:address":"Parc Imstenrade 66",
    "sg:city":"Heerlen",
    "sg:orig_category":"Bejaarden - Verzorgingstehuizen",
    "sg:phone":"+31 45 400 4600",
    "sg:postcode":"6418 PP",
    "sg:province":"Limburg",
    "wof:name":"Parc Imstenrade",
    "wof:placetype":"venue"
},
  "geometry": {"coordinates":[5.992308,50.864853],"type":"Point"}
}