{
  "type": "Feature",
  "properties": {
    "iso:country":"NL",
    "sg:address":"Burg Commandeurln 2",
    "sg:city":"Wognum",
    "sg:orig_category":"Banken And Kredietinstellingen",
    "sg:phone":"+31 229 280 808",
    "sg:postcode":"1687 BH",
    "sg:province":"North Holland",
    "wof:name":"Rabobank",
    "wof:placetype":"venue"
},
  "geometry": {"coordinates":[5.024602,52.681789],"type":"Point"}
}