{
  "type": "Feature",
  "properties": {
    "iso:country":"NL",
    "sg:address":"Zandstr 17A",
    "sg:city":"Nuland",
    "sg:orig_category":"Kinderopvang",
    "sg:phone":"+31 73 532 0256",
    "sg:postcode":"5391 AL",
    "sg:province":"North Brabant",
    "wof:name":"Joepie",
    "wof:placetype":"venue"
},
  "geometry": {"coordinates":[5.437118,51.727825],"type":"Point"}
}