{
  "type": "Feature",
  "properties": {
    "addr:full":"Zandstr 17A Nuland North Brabant 5391 AL",
    "addr:housenumber":"17a",
    "addr:postcode":"5391 al",
    "addr:street":"Zandstr",
    "iso:country":"NL",
    "sg:address":"Zandstr 17A",
    "sg:city":"Nuland",
    "sg:orig_category":"Kinderopvang",
    "sg:phone":"+31 73 532 0256",
    "sg:postcode":"5391 AL",
    "sg:province":"North Brabant",
    "wof:name":"Joepie",
    "wof:placetype":"venue"
},
  "geometry": {"coordinates":[5.437118,51.727825],"type":"Point"}
}