{
  "type": "Feature",
  "properties": {
    "iso:country":"NL",
    "sg:address":"Wijkermeerweg 22",
    "sg:city":"Beverwijk",
    "sg:orig_category":"Wegen And Sportterreinen",
    "sg:phone":"+31 251 223 041",
    "sg:postcode":"1948 NW",
    "sg:province":"North Holland",
    "wof:name":"Aannemingsbedrijf Johan De Bie Bv",
    "wof:placetype":"venue"
},
  "geometry": {"coordinates":[4.6672120094,52.4765129089],"type":"Point"}
}