{
  "type": "Feature",
  "properties": {
    "addr:full":"Oostdk 1 Sommelsdyk South Holland 3245 AS",
    "addr:housenumber":"1",
    "addr:postcode":"3245 as",
    "addr:street":"Oostdk",
    "iso:country":"NL",
    "sg:address":"Oostdk 1",
    "sg:city":"Sommelsdyk",
    "sg:orig_category":"Verf En Lak",
    "sg:phone":"+31 187 487 184",
    "sg:postcode":"3245 AS",
    "sg:province":"South Holland",
    "sg:website":"http://www.decohome.nl",
    "wof:name":"Deco Home, Van Rossum",
    "wof:placetype":"venue"
},
  "geometry": {"coordinates":[4.15478,51.760239],"type":"Point"}
}