{
  "type": "Feature",
  "properties": {
    "addr:full":"Doorniksestr 28 S Gravenhage Zuid-Holland 2587 XM",
    "addr:housenumber":"28;gravenhage",
    "addr:postcode":"2587 xm",
    "addr:street":"Doorniksestr;S",
    "iso:country":"NL",
    "sg:address":"Doorniksestr 28",
    "sg:city":"S Gravenhage",
    "sg:orig_category":"Scholen Voor Basisonderwijs",
    "sg:phone":"+31 70 355 6631",
    "sg:postcode":"2587 XM",
    "sg:province":"Zuid-Holland",
    "wof:name":"Buitenschool, Eerste Ned",
    "wof:placetype":"venue"
},
  "geometry": {"coordinates":[4.29118,52.112942],"type":"Point"}
}