{
  "type": "Feature",
  "properties": {
    "iso:country":"NL",
    "sg:address":"Hille Kampkes 19",
    "sg:city":"Maren Kessel",
    "sg:orig_category":"Elektriciens",
    "sg:phone":"+31 412 479 623",
    "sg:postcode":"5398 HV",
    "sg:province":"Gelderland",
    "wof:name":"Van Der Veeken Montage",
    "wof:placetype":"venue"
},
  "geometry": {"coordinates":[5.3929929733,51.7941856384],"type":"Point"}
}