{
  "type": "Feature",
  "properties": {
    "addr:full":"Parkweg 7 Voorburg Zuid-Holland 2271 AD",
    "addr:housenumber":"7",
    "addr:postcode":"2271 ad",
    "addr:street":"Parkweg",
    "iso:country":"NL",
    "sg:address":"Parkweg 7",
    "sg:city":"Voorburg",
    "sg:orig_category":"Diverse Grafische Activiteiten",
    "sg:phone":"+31 70 369 4647",
    "sg:postcode":"2271 AD",
    "sg:province":"Zuid-Holland",
    "wof:name":"Studio V Grafische Vormgeving Jos Tigges",
    "wof:placetype":"venue"
},
  "geometry": {"coordinates":[4.359243,52.068062],"type":"Point"}
}