{
  "type": "Feature",
  "properties": {
    "addr:full":"Haven 1-13 Schoonhoven Zuid-Holland 2871 CK",
    "addr:housenumber":"1-13",
    "addr:postcode":"2871 ck",
    "addr:street":"Haven",
    "iso:country":"NL",
    "sg:address":"Haven 1-13",
    "sg:city":"Schoonhoven",
    "sg:orig_category":"Juweliers",
    "sg:phone":"+31 182 382 651",
    "sg:postcode":"2871 CK",
    "sg:province":"Zuid-Holland",
    "sg:website":"http://www.rikkoertjuweliers.nl",
    "wof:name":"Rikkoert Juweliers-Klokkenhuys",
    "wof:placetype":"venue"
},
  "geometry": {"coordinates":[4.852105,51.944153],"type":"Point"}
}