{
  "type": "Feature",
  "properties": {
    "iso:country":"NL",
    "sg:address":"Burgwal 12",
    "sg:city":"Woudenberg",
    "sg:orig_category":"Bestratingen",
    "sg:phone":"+31 33 286 5548",
    "sg:postcode":"3931 HM",
    "sg:province":"Utrecht",
    "wof:name":"Vulpen, G J Van",
    "wof:placetype":"venue"
},
  "geometry": {"coordinates":[5.411753,52.083759],"type":"Point"}
}