{
  "type": "Feature",
  "properties": {
    "addr:full":"Kabelwg 40 Amsterdam North Holland 1014 BB",
    "addr:housenumber":"40",
    "addr:postcode":"1014 bb",
    "addr:street":"Kabelwg",
    "iso:country":"NL",
    "sg:address":"Kabelwg 40",
    "sg:city":"Amsterdam",
    "sg:orig_category":"Orthopedisch Schoeisel",
    "sg:phone":"+31 20 684 4411",
    "sg:postcode":"1014 BB",
    "sg:province":"North Holland",
    "sg:website":"http://www.toornend.nl",
    "wof:name":"Toornend Orthopedic Services",
    "wof:placetype":"venue"
},
  "geometry": {"coordinates":[4.8474497795,52.3912277222],"type":"Point"}
}