{
  "type": "Feature",
  "properties": {
    "addr:full":"Overhoven 71 Sittard Limburg 6136 EB",
    "addr:housenumber":"71",
    "addr:postcode":"6136 eb",
    "addr:street":"Overhoven",
    "iso:country":"NL",
    "sg:address":"Overhoven 71",
    "sg:city":"Sittard",
    "sg:orig_category":"Drukkerijen",
    "sg:phone":"+31 46 420 0125",
    "sg:postcode":"6136 EB",
    "sg:province":"Limburg",
    "wof:name":"Pasklaar",
    "wof:placetype":"venue"
},
  "geometry": {"coordinates":[5.868007,51.00584],"type":"Point"}
}