{
  "type": "Feature",
  "properties": {
    "addr:full":"Vd Sandepln 6A Wolvega Friesland 8471 RX",
    "addr:housenumber":"6a",
    "addr:postcode":"8471 rx",
    "iso:country":"NL",
    "sg:address":"Vd Sandepln 6A",
    "sg:city":"Wolvega",
    "sg:orig_category":"Administratie- En Boekhoudkantoren",
    "sg:phone":"+31 561 614 971",
    "sg:postcode":"8471 RX",
    "sg:province":"Friesland",
    "wof:name":"Dikken, A",
    "wof:placetype":"venue"
},
  "geometry": {"coordinates":[5.997745,52.873821],"type":"Point"}
}