{
  "type": "Feature",
  "properties": {
    "addr:full":"Korte Blekersweg 29A Epe Gelderland 8162 RL",
    "addr:housenumber":"29a",
    "addr:postcode":"8162 rl",
    "addr:street":"Korte Blekersweg;Gelderland",
    "iso:country":"NL",
    "sg:address":"Korte Blekersweg 29A",
    "sg:city":"Epe",
    "sg:orig_category":"Autokeuringen",
    "sg:phone":"+31 578 612 721",
    "sg:postcode":"8162 RL",
    "sg:province":"Gelderland",
    "wof:name":"Export Cars Epe",
    "wof:placetype":"venue"
},
  "geometry": {"coordinates":[5.958523,52.342438],"type":"Point"}
}