{
  "type": "Feature",
  "properties": {
    "iso:country":"NL",
    "sg:address":"Van Der Waalsstraat 25",
    "sg:city":"Terneuzen",
    "sg:orig_category":"Technische Studies And Onderzoek",
    "sg:phone":"+31 115 694 061",
    "sg:postcode":"4532 LA",
    "sg:province":"Zeeland",
    "wof:name":"Smit Gasturbine Consultant",
    "wof:placetype":"venue"
},
  "geometry": {"coordinates":[3.852686,51.330162],"type":"Point"}
}