{
  "type": "Feature",
  "properties": {
    "addr:full":"Enkhuizerzand 38 Urk Flevoland 8321 ZL",
    "addr:housenumber":"38",
    "addr:postcode":"8321 zl",
    "addr:street":"Enkhuizerzand;Flevoland",
    "iso:country":"NL",
    "sg:address":"Enkhuizerzand 38",
    "sg:city":"Urk",
    "sg:classifiers":[
        {
            "category":"Farming",
            "subcategory":"Fish & Marine Products",
            "type":"Manufacturing & Wholesale Goods"
        }
    ],
    "sg:phone":"+31 527 684 427",
    "sg:postcode":"8321 ZL",
    "sg:province":"Flevoland",
    "sg:tags":[
        "vi"
    ],
    "wof:name":"Boer, T De",
    "wof:placetype":"venue"
},
  "geometry": {"coordinates":[5.622826,52.669575],"type":"Point"}
}