{
  "type": "Feature",
  "properties": {
    "addr:full":"Hinthamerstraat 185 'S Hertogenbosch Noord-Brabant 5211 ML",
    "addr:housenumber":"185 ' s",
    "addr:postcode":"5211 ml",
    "addr:street":"Hinthamerstraat",
    "iso:country":"NL",
    "sg:address":"Hinthamerstraat 185",
    "sg:city":"'S Hertogenbosch",
    "sg:orig_category":"Kappers",
    "sg:phone":"+31 73 614 8584",
    "sg:postcode":"5211 ML",
    "sg:province":"Noord-Brabant",
    "wof:name":"Stars Hairstyling",
    "wof:placetype":"venue"
},
  "geometry": {"coordinates":[5.312726,51.68829],"type":"Point"}
}