{
  "type": "Feature",
  "properties": {
    "iso:country":"NL",
    "sg:address":"Brandlichterwg 63",
    "sg:city":"Denekamp",
    "sg:orig_category":"Administratie- En Boekhoudkantoren",
    "sg:phone":"+31 541 355 785",
    "sg:postcode":"7591 ND",
    "sg:province":"Overijssel",
    "wof:name":"Eik, De",
    "wof:placetype":"venue"
},
  "geometry": {"coordinates":[7.025767,52.376373],"type":"Point"}
}