{
  "type": "Feature",
  "properties": {
    "addr:full":"Thijsselaan 2 Den Burg Noord-Holland 1791 VH",
    "addr:housenumber":"2",
    "addr:postcode":"1791 vh",
    "addr:street":"Thijsselaan",
    "iso:country":"NL",
    "sg:address":"Thijsselaan 2",
    "sg:city":"Den Burg",
    "sg:orig_category":"Werving And Selectie Van Tijdelijk Personeel And Uitzendkantoren",
    "sg:phone":"+31 222 314 047",
    "sg:postcode":"1791 VH",
    "sg:province":"Noord-Holland",
    "wof:name":"Start",
    "wof:placetype":"venue"
},
  "geometry": {"coordinates":[4.8028659821,53.0552825928],"type":"Point"}
}