{
  "type": "Feature",
  "properties": {
    "addr:full":"Sleutelstraat 5A Wessem Limburg 6019 CM",
    "addr:housenumber":"5a",
    "addr:postcode":"6019 cm",
    "addr:street":"Sleutelstraat",
    "iso:country":"NL",
    "sg:address":"Sleutelstraat 5A",
    "sg:city":"Wessem",
    "sg:orig_category":"Kinderopvang Behalve Thuis",
    "sg:phone":"+31 475 562 124",
    "sg:postcode":"6019 CM",
    "sg:province":"Limburg",
    "wof:name":"Peuterspeelzaal De Speeldoos",
    "wof:placetype":"venue"
},
  "geometry": {"coordinates":[5.879348,51.16357],"type":"Point"}
}