{
  "type": "Feature",
  "properties": {
    "iso:country":"NL",
    "sg:address":"Fazantenkamp 307",
    "sg:city":"Maarssen",
    "sg:orig_category":"Boekhouders",
    "sg:phone":"+31 346 573 311",
    "sg:postcode":"3607 CP",
    "sg:province":"Utrecht",
    "wof:name":"Stand-By",
    "wof:placetype":"venue"
},
  "geometry": {"coordinates":[5.015711,52.129898],"type":"Point"}
}