{
  "type": "Feature",
  "properties": {
    "addr:full":"Roermondsestraat 7 Venlo Limburg 5912 AH",
    "addr:housenumber":"7",
    "addr:postcode":"5912 ah",
    "addr:street":"Roermondsestraat",
    "iso:country":"NL",
    "sg:address":"Roermondsestraat 7",
    "sg:city":"Venlo",
    "sg:orig_category":"Meubelzaken, Woning- And Keukeninrichting",
    "sg:phone":"+31 77 321 1060",
    "sg:postcode":"5912 AH",
    "sg:province":"Limburg",
    "wof:name":"Concord Matrassen",
    "wof:placetype":"venue"
},
  "geometry": {"coordinates":[6.166086,51.366619],"type":"Point"}
}