{
  "type": "Feature",
  "properties": {
    "addr:full":"Tussen Meer 217 Amsterdam Noord-Holland 1069 DN",
    "addr:housenumber":"217",
    "addr:postcode":"1069 dn",
    "addr:street":"Tussen Meer",
    "iso:country":"NL",
    "sg:address":"Tussen Meer 217",
    "sg:city":"Amsterdam",
    "sg:orig_category":"Fietshandelaren",
    "sg:phone":"+31 20 410 0245",
    "sg:postcode":"1069 DN",
    "sg:province":"Noord-Holland",
    "wof:name":"Schoonhoven Rijwielen",
    "wof:placetype":"venue"
},
  "geometry": {"coordinates":[4.796183,52.357227],"type":"Point"}
}