{
  "type": "Feature",
  "properties": {
    "iso:country":"NL",
    "sg:address":"Oude Ebbingestr 61-2",
    "sg:city":"Groningen",
    "sg:orig_category":"Mobiele- En Autotelefoons",
    "sg:phone":"+31 50 589 0730",
    "sg:postcode":"9712 HD",
    "sg:province":"Groningen",
    "wof:name":"Telefoon Store",
    "wof:placetype":"venue"
},
  "geometry": {"coordinates":[6.56613,53.220936],"type":"Point"}
}