{
  "type": "Feature",
  "properties": {
    "addr:full":"Lambrecht Van Dalelaan 44 Haarlem Noord-Holland 2015 ET",
    "addr:housenumber":"44",
    "addr:postcode":"2015 et",
    "addr:street":"Lambrecht Van Dalelaan",
    "iso:country":"NL",
    "sg:address":"Lambrecht Van Dalelaan 44",
    "sg:city":"Haarlem",
    "sg:orig_category":"Makelaars In Onroerend Goed",
    "sg:phone":"+31 23 544 0677",
    "sg:postcode":"2015 ET",
    "sg:province":"Noord-Holland",
    "wof:name":"Dupon Vastgoed Ontwikkeling",
    "wof:placetype":"venue"
},
  "geometry": {"coordinates":[4.607168,52.383492],"type":"Point"}
}