{
  "type": "Feature",
  "properties": {
    "addr:full":"Sluiswachterstr 36 Delfgauw South Holland 2645 JC",
    "addr:housenumber":"36",
    "addr:postcode":"2645 jc",
    "addr:street":"Sluiswachterstr",
    "iso:country":"NL",
    "sg:address":"Sluiswachterstr 36",
    "sg:city":"Delfgauw",
    "sg:orig_category":"Grafisch Ontwerpers",
    "sg:phone":"+31 15 256 5720",
    "sg:postcode":"2645 JC",
    "sg:province":"South Holland",
    "wof:name":"Burg, Marjolein Van Der",
    "wof:placetype":"venue"
},
  "geometry": {"coordinates":[4.394176,52.003262],"type":"Point"}
}