{
  "type": "Feature",
  "properties": {
    "addr:full":"Gijzenveld 3 Breda North Brabant 4817 ZE",
    "addr:housenumber":"3",
    "addr:postcode":"4817 ze",
    "addr:street":"Gijzenveld",
    "iso:country":"NL",
    "sg:address":"Gijzenveld 3",
    "sg:city":"Breda",
    "sg:orig_category":"Watersportartikelen",
    "sg:phone":"+31 76 572 0555",
    "sg:postcode":"4817 ZE",
    "sg:province":"North Brabant",
    "sg:website":"http://www.vandulstwatersport.nl",
    "wof:name":"Dulst Watersport, Van",
    "wof:placetype":"venue"
},
  "geometry": {"coordinates":[4.8282299042,51.5959205627],"type":"Point"}
}