{
  "type": "Feature",
  "properties": {
    "iso:country":"NL",
    "sg:address":"Visserstr 42",
    "sg:city":"Aalsmeer",
    "sg:orig_category":"Verpakkingen En Verpakkingsmaterialen",
    "sg:phone":"+31 297 324 235",
    "sg:postcode":"1431 GJ",
    "sg:province":"Noord-Holland",
    "wof:name":"Bol Bv",
    "wof:placetype":"venue"
},
  "geometry": {"coordinates":[4.773041,52.258015],"type":"Point"}
}