{
  "type": "Feature",
  "properties": {
    "addr:full":"Visserstr 42 Aalsmeer Noord-Holland 1431 GJ",
    "addr:housenumber":"42",
    "addr:postcode":"1431 gj",
    "addr:street":"Visserstr",
    "iso:country":"NL",
    "sg:address":"Visserstr 42",
    "sg:city":"Aalsmeer",
    "sg:orig_category":"Verpakkingen En Verpakkingsmaterialen",
    "sg:phone":"+31 297 324 235",
    "sg:postcode":"1431 GJ",
    "sg:province":"Noord-Holland",
    "wof:name":"Bol Bv",
    "wof:placetype":"venue"
},
  "geometry": {"coordinates":[4.773041,52.258015],"type":"Point"}
}