{
  "type": "Feature",
  "properties": {
    "iso:country":"NL",
    "sg:address":"Dorpstr 80",
    "sg:city":"Veldhoven",
    "sg:orig_category":"Autoschade- Herstelbedrijven",
    "sg:phone":"+31 40 253 2060",
    "sg:postcode":"5504 HK",
    "sg:province":"North Brabant",
    "wof:name":"Lierop, J B M Van",
    "wof:placetype":"venue"
},
  "geometry": {"coordinates":[5.405529,51.404991],"type":"Point"}
}