{
  "type": "Feature",
  "properties": {
    "iso:country":"NL",
    "sg:address":"Dr W Beckmansngl 17",
    "sg:city":"Vlaardingen",
    "sg:orig_category":"Voetbalverenigingen",
    "sg:phone":"+31 10 435 7075",
    "sg:postcode":"3132 CL",
    "sg:province":"South Holland",
    "wof:name":"Fortuna Vi",
    "wof:placetype":"venue"
},
  "geometry": {"coordinates":[4.317638,51.910103],"type":"Point"}
}