{
  "type": "Feature",
  "properties": {
    "addr:full":"Vrieslantln 14 Utrecht Utrecht 3526 AA",
    "addr:housenumber":"14",
    "addr:postcode":"3526 aa",
    "addr:street":"Vrieslantln",
    "iso:country":"NL",
    "sg:address":"Vrieslantln 14",
    "sg:city":"Utrecht",
    "sg:orig_category":"Drukkerijen",
    "sg:phone":"+31 30 282 2822",
    "sg:postcode":"3526 AA",
    "sg:province":"Utrecht",
    "sg:website":"http://www.plantijncasparie.nl",
    "wof:name":"Plantijn Casparie Utrecht",
    "wof:placetype":"venue"
},
  "geometry": {"coordinates":[5.103683,52.062229],"type":"Point"}
}