{
  "type": "Feature",
  "properties": {
    "addr:full":"Beneluxln 71 Heerlen Limburg 6414 GT",
    "addr:housenumber":"71",
    "addr:postcode":"6414 gt",
    "addr:street":"Beneluxln",
    "iso:country":"NL",
    "sg:address":"Beneluxln 71",
    "sg:city":"Heerlen",
    "sg:orig_category":"Juweliers",
    "sg:phone":"+31 45 521 1378",
    "sg:postcode":"6414 GT",
    "sg:province":"Limburg",
    "wof:name":"Jambroers",
    "wof:placetype":"venue"
},
  "geometry": {"coordinates":[5.96315,50.921116],"type":"Point"}
}