{
  "type": "Feature",
  "properties": {
    "addr:full":"Harmenkaag 6 Schagen Noord-Holland 1741 LA",
    "addr:housenumber":"6",
    "addr:postcode":"1741 la",
    "addr:street":"Harmenkaag",
    "iso:country":"NL",
    "sg:address":"Harmenkaag 6",
    "sg:city":"Schagen",
    "sg:orig_category":"Parfumerie - Groothandel",
    "sg:phone":"+31 224 214 222",
    "sg:postcode":"1741 LA",
    "sg:province":"Noord-Holland",
    "wof:name":"Ddd Supply Bv",
    "wof:placetype":"venue"
},
  "geometry": {"coordinates":[4.809726,52.783268],"type":"Point"}
}