{
  "type": "Feature",
  "properties": {
    "addr:full":"Arkendonk 70 Oosterhout Nb Noord-Brabant 4907 XP",
    "addr:housenumber":"70",
    "addr:postcode":"4907 xp",
    "addr:street":"Arkendonk",
    "iso:country":"NL",
    "sg:address":"Arkendonk 70",
    "sg:city":"Oosterhout Nb",
    "sg:classifiers":[
        {
            "category":"Fast Food",
            "type":"Food & Drink"
        }
    ],
    "sg:phone":"+31 162 429 365",
    "sg:postcode":"4907 XP",
    "sg:province":"Noord-Brabant",
    "sg:tags":[
        "afhaal",
        "restaurant"
    ],
    "wof:name":"Restaria 'T Pleintje",
    "wof:placetype":"venue"
},
  "geometry": {"coordinates":[4.86469,51.658012],"type":"Point"}
}