{
  "type": "Feature",
  "properties": {
    "addr:full":"Dr. Jan Berendsstraat 6 Nijmegen Gelderland 6512 HB",
    "addr:housenumber":"6",
    "addr:postcode":"6512 hb",
    "addr:street":"Dr. Jan Berendsstraat;Gelderland",
    "iso:country":"NL",
    "sg:address":"Dr. Jan Berendsstraat 6",
    "sg:city":"Nijmegen",
    "sg:classifiers":[
        {
            "category":"Retail",
            "subcategory":"Storage",
            "type":"Services"
        }
    ],
    "sg:phone":"+31 24 642 4368",
    "sg:postcode":"6512 HB",
    "sg:province":"Gelderland",
    "sg:tags":[
        "opslag",
        "bewaring"
    ],
    "wof:name":"Valuepack",
    "wof:placetype":"venue"
},
  "geometry": {"coordinates":[5.8587408066,51.8353881836],"type":"Point"}
}