{
  "type": "Feature",
  "properties": {
    "addr:full":"Ringdk 1 Zwyndrecht Zuid-Holland 3332 LC",
    "addr:housenumber":"1",
    "addr:postcode":"3332 lc",
    "addr:street":"Ringdk",
    "iso:country":"NL",
    "sg:address":"Ringdk 1",
    "sg:city":"Zwyndrecht",
    "sg:orig_category":"Scheepswerven",
    "sg:phone":"+31 78 612 6949",
    "sg:postcode":"3332 LC",
    "sg:province":"Zuid-Holland",
    "wof:name":"Pol Bv, Van Der",
    "wof:placetype":"venue"
},
  "geometry": {"coordinates":[4.65647,51.822247],"type":"Point"}
}