{
  "type": "Feature",
  "properties": {
    "addr:full":"Friesestr 82 Coevorden Drenthe 7741 GX",
    "addr:housenumber":"82",
    "addr:postcode":"7741 gx",
    "addr:street":"Friesestr",
    "iso:country":"NL",
    "sg:address":"Friesestr 82",
    "sg:city":"Coevorden",
    "sg:orig_category":"Warenhuizen",
    "sg:phone":"+31 524 515 123",
    "sg:postcode":"7741 GX",
    "sg:province":"Drenthe",
    "wof:name":"Hema",
    "wof:placetype":"venue"
},
  "geometry": {"coordinates":[6.7378911972,52.6627883911],"type":"Point"}
}