{
  "type": "Feature",
  "properties": {
    "iso:country":"NL",
    "sg:address":"Corellistr 361",
    "sg:city":"Tilburg",
    "sg:orig_category":"Autorijscholen",
    "sg:phone":"+31 13 455 0343",
    "sg:postcode":"5049 EL",
    "sg:province":"North Brabant",
    "wof:name":"Elve, Gilles",
    "wof:placetype":"venue"
},
  "geometry": {"coordinates":[5.076031,51.587128],"type":"Point"}
}