{
  "type": "Feature",
  "properties": {
    "addr:full":"Mauritskd 22B Amsterdam Noord-Holland 1091 GC",
    "addr:housenumber":"22b",
    "addr:postcode":"1091 gc",
    "addr:street":"Mauritskd",
    "iso:country":"NL",
    "sg:address":"Mauritskd 22B",
    "sg:city":"Amsterdam",
    "sg:orig_category":"Verenigingen En Stichtingen",
    "sg:phone":"+31 20 694 4158",
    "sg:postcode":"1091 GC",
    "sg:province":"Noord-Holland",
    "wof:name":"Marokkaanse Vrouwen In A'Dam, Sticht",
    "wof:placetype":"venue"
},
  "geometry": {"coordinates":[4.919681,52.354916],"type":"Point"}
}