{
  "type": "Feature",
  "properties": {
    "addr:full":"De Eem 37 Woerden South Holland 3448 DS",
    "addr:housenumber":"37",
    "addr:postcode":"3448 ds",
    "addr:street":"De Eem",
    "iso:country":"NL",
    "sg:address":"De Eem 37",
    "sg:city":"Woerden",
    "sg:orig_category":"Binnenhuisarchitecten",
    "sg:phone":"+31 348 411 055",
    "sg:postcode":"3448 DS",
    "sg:province":"South Holland",
    "wof:name":"Kleuradviesbureau Wim Van Velsen",
    "wof:placetype":"venue"
},
  "geometry": {"coordinates":[4.866505,52.075794],"type":"Point"}
}