{
  "type": "Feature",
  "properties": {
    "addr:full":"De Mossendam 8 Goor NL.08 7471 SJ",
    "addr:housenumber":"8;nl.08",
    "addr:postcode":"7471",
    "addr:street":"De Mossendam",
    "iso:country":"NL",
    "sg:address":"De Mossendam 8",
    "sg:city":"Goor",
    "sg:orig_category":"Fitnesscentra",
    "sg:phone":"+31 547 276 980",
    "sg:postcode":"7471 SJ",
    "sg:province":"NL.08",
    "sg:website":"http://www.fit-care.nl",
    "wof:name":"Fit-Care Center Wijnen, Van",
    "wof:placetype":"venue"
},
  "geometry": {"coordinates":[6.59714,52.241428],"type":"Point"}
}