{
  "type": "Feature",
  "properties": {
    "addr:full":"Flora 14 Deventer Overijssel 7422 LL",
    "addr:housenumber":"14",
    "addr:postcode":"7422 ll",
    "addr:street":"Flora",
    "iso:country":"NL",
    "sg:address":"Flora 14",
    "sg:city":"Deventer",
    "sg:classifiers":[
        {
            "category":"Shopping",
            "subcategory":"Adult",
            "type":"Retail Goods"
        }
    ],
    "sg:phone":"+31 570 511 483",
    "sg:postcode":"7422 LL",
    "sg:province":"Overijssel",
    "sg:tags":[
        "lingerie",
        "en",
        "tricotage"
    ],
    "wof:name":"Qinn Bodywear",
    "wof:placetype":"venue"
},
  "geometry": {"coordinates":[6.216329,52.247803],"type":"Point"}
}