{
  "type": "Feature",
  "properties": {
    "addr:full":"Heivlinderwg 57 Diemen Noord-Holland 1113 LS",
    "addr:housenumber":"57",
    "addr:postcode":"1113 ls",
    "addr:street":"Heivlinderwg",
    "iso:country":"NL",
    "sg:address":"Heivlinderwg 57",
    "sg:city":"Diemen",
    "sg:orig_category":"Administratie- En Boekhoudkantoren",
    "sg:phone":"+31 20 695 6077",
    "sg:postcode":"1113 LS",
    "sg:province":"Noord-Holland",
    "wof:name":"Meijer Vof, P De",
    "wof:placetype":"venue"
},
  "geometry": {"coordinates":[4.984131,52.346359],"type":"Point"}
}