{
  "type": "Feature",
  "properties": {
    "addr:full":"Vroonlant 17 Den Burg Noord-Holland 1791 WK",
    "addr:housenumber":"17",
    "addr:postcode":"1791 wk",
    "addr:street":"Vroonlant",
    "iso:country":"NL",
    "sg:address":"Vroonlant 17",
    "sg:city":"Den Burg",
    "sg:orig_category":"Paramedische Behandelingen",
    "sg:phone":"+31 222 315 454",
    "sg:postcode":"1791 WK",
    "sg:province":"Noord-Holland",
    "wof:name":"Logopediste J De Porto",
    "wof:placetype":"venue"
},
  "geometry": {"coordinates":[-83.29684399999999,41.286724],"type":"Point"}
}