{
  "type": "Feature",
  "properties": {
    "addr:full":"Einsteinwg 4 Coevorden Drenthe 7741 KP",
    "addr:housenumber":"4",
    "addr:postcode":"7741 kp",
    "addr:street":"Einsteinwg",
    "iso:country":"NL",
    "sg:address":"Einsteinwg 4",
    "sg:city":"Coevorden",
    "sg:orig_category":"Gordijnenateliers",
    "sg:phone":"+31 524 513 749",
    "sg:postcode":"7741 KP",
    "sg:province":"Drenthe",
    "sg:website":"http://www.heco.nl",
    "wof:name":"Heco Gordijnatelier Bv",
    "wof:placetype":"venue"
},
  "geometry": {"coordinates":[6.727971,52.65667],"type":"Point"}
}