{
  "type": "Feature",
  "properties": {
    "iso:country":"NL",
    "sg:address":"De Kling 31",
    "sg:city":"Schimmert",
    "sg:orig_category":"Vertaalbureaus",
    "sg:phone":"+31 45 404 0136",
    "sg:postcode":"6333 ER",
    "sg:province":"Limburg",
    "wof:name":"Gretton & Willems Vof",
    "wof:placetype":"venue"
},
  "geometry": {"coordinates":[5.806196,50.911057],"type":"Point"}
}