{
  "type": "Feature",
  "properties": {
    "addr:full":"Rembrandtwg 109 Amstelveen Noord-Holland 1181 GE",
    "addr:housenumber":"109",
    "addr:postcode":"1181",
    "iso:country":"NL",
    "sg:address":"Rembrandtwg 109",
    "sg:city":"Amstelveen",
    "sg:orig_category":"Schoenen",
    "sg:phone":"+31 20 641 9397",
    "sg:postcode":"1181 GE",
    "sg:province":"Noord-Holland",
    "wof:name":"Blokland Vof",
    "wof:placetype":"venue"
},
  "geometry": {"coordinates":[4.861464,52.304955],"type":"Point"}
}