{
  "type": "Feature",
  "properties": {
    "addr:full":"Dr A Mathysenstr 37 Budel North Brabant 6021 CK",
    "addr:housenumber":"37",
    "addr:postcode":"6021 ck",
    "addr:street":"Dr;Mathysenstr",
    "iso:country":"NL",
    "sg:address":"Dr A Mathysenstr 37",
    "sg:city":"Budel",
    "sg:orig_category":"Grondwerken",
    "sg:phone":"+31 495 491 102",
    "sg:postcode":"6021 CK",
    "sg:province":"North Brabant",
    "wof:name":"Boudrie, Jos",
    "wof:placetype":"venue"
},
  "geometry": {"coordinates":[5.580084,51.277035],"type":"Point"}
}