{
  "type": "Feature",
  "properties": {
    "addr:full":"Vechtdijk 135 Utrecht Utrecht 3563 MA",
    "addr:housenumber":"135",
    "addr:postcode":"3563 ma",
    "addr:street":"Vechtdijk",
    "iso:country":"NL",
    "sg:address":"Vechtdijk 135",
    "sg:city":"Utrecht",
    "sg:orig_category":"Grafisch Ontwerpers",
    "sg:phone":"+31 30 230 0635",
    "sg:postcode":"3563 MA",
    "sg:province":"Utrecht",
    "wof:name":"Beeldbuis",
    "wof:placetype":"venue"
},
  "geometry": {"coordinates":[5.09585,52.11581],"type":"Point"}
}