{
  "type": "Feature",
  "properties": {
    "addr:full":"Oudelandsedijk 101 Sommelsdijk South Holland 3245 LG",
    "addr:housenumber":"101",
    "addr:postcode":"3245 lg",
    "addr:street":"Oudelandsedijk",
    "iso:country":"NL",
    "sg:address":"Oudelandsedijk 101",
    "sg:city":"Sommelsdijk",
    "sg:orig_category":"Fietshandelaren",
    "sg:phone":"+31 187 470 166",
    "sg:postcode":"3245 LG",
    "sg:province":"South Holland",
    "wof:name":"Hans Groenendijk Fietsen",
    "wof:placetype":"venue"
},
  "geometry": {"coordinates":[4.146208,51.761635],"type":"Point"}
}