{
  "type": "Feature",
  "properties": {
    "addr:full":"Havenpln 17 Wassenaar Zuid-Holland 2242 NB",
    "addr:housenumber":"17",
    "addr:postcode":"2242 nb",
    "addr:street":"Havenpln",
    "iso:country":"NL",
    "sg:address":"Havenpln 17",
    "sg:city":"Wassenaar",
    "sg:orig_category":"Modelbouw",
    "sg:phone":"+31 70 514 4875",
    "sg:postcode":"2242 NB",
    "sg:province":"Zuid-Holland",
    "wof:name":"Rp Import",
    "wof:placetype":"venue"
},
  "geometry": {"coordinates":[4.395496,52.146946],"type":"Point"}
}