{
  "type": "Feature",
  "properties": {
    "addr:full":"Rengerskerkestraat 9 I Amsterdam Noord-Holland 1069 HT",
    "addr:housenumber":"9 i",
    "addr:postcode":"1069 ht",
    "addr:street":"Rengerskerkestraat",
    "iso:country":"NL",
    "sg:address":"Rengerskerkestraat 9 I",
    "sg:city":"Amsterdam",
    "sg:orig_category":"Film-, Tv- And Videoproductie",
    "sg:phone":"+31 20 610 5858",
    "sg:postcode":"1069 HT",
    "sg:province":"Noord-Holland",
    "wof:name":"B.A.T.",
    "wof:placetype":"venue"
},
  "geometry": {"coordinates":[4.78913,52.35305],"type":"Point"}
}