{
  "type": "Feature",
  "properties": {
    "addr:full":"De Kupe 10 Wijhe Overijssel 8131 CM",
    "addr:housenumber":"10",
    "addr:postcode":"8131 cm",
    "addr:street":"De Kupe",
    "iso:country":"NL",
    "sg:address":"De Kupe 10",
    "sg:city":"Wijhe",
    "sg:orig_category":"Boekhouders",
    "sg:phone":"+31 570 521 250",
    "sg:postcode":"8131 CM",
    "sg:province":"Overijssel",
    "wof:name":"Administratiekantoor Zwakenberg",
    "wof:placetype":"venue"
},
  "geometry": {"coordinates":[6.131243,52.388893],"type":"Point"}
}