{
  "type": "Feature",
  "properties": {
    "addr:full":"Erasmusstr 137 Rotterdam South Holland 3035 LD",
    "addr:housenumber":"137",
    "addr:postcode":"3035 ld",
    "iso:country":"NL",
    "sg:address":"Erasmusstr 137",
    "sg:city":"Rotterdam",
    "sg:orig_category":"Verenigingen En Stichtingen",
    "sg:phone":"+31 10 467 7561",
    "sg:postcode":"3035 LD",
    "sg:province":"South Holland",
    "wof:name":"Dultepe Moskee",
    "wof:placetype":"venue"
},
  "geometry": {"coordinates":[4.482267,51.931213],"type":"Point"}
}