{
  "type": "Feature",
  "properties": {
    "iso:country":"NL",
    "sg:address":"Molenstr 44",
    "sg:city":"Bruinisse",
    "sg:orig_category":"Peuterspeelzalen",
    "sg:phone":"+31 111 482 980",
    "sg:postcode":"4311 ED",
    "sg:province":"Zeeland",
    "wof:name":"Krukels, De",
    "wof:placetype":"venue"
},
  "geometry": {"coordinates":[4.09305,51.66156],"type":"Point"}
}