{
  "type": "Feature",
  "properties": {
    "addr:full":"Roelofsstraat 11 Nieuwkoop Zuid-Holland 2421 GA",
    "addr:housenumber":"11",
    "addr:postcode":"2421 ga",
    "addr:street":"Roelofsstraat",
    "iso:country":"NL",
    "sg:address":"Roelofsstraat 11",
    "sg:city":"Nieuwkoop",
    "sg:orig_category":"Geluidsopnamen",
    "sg:phone":"+31 172 575 965",
    "sg:postcode":"2421 GA",
    "sg:province":"Zuid-Holland",
    "wof:name":"Abbing Produkties",
    "wof:placetype":"venue"
},
  "geometry": {"coordinates":[-83.222931,32.678131],"type":"Point"}
}