{
  "type": "Feature",
  "properties": {
    "addr:full":"Beatrijsstraat 69 'S Gravenhage Zuid-Holland 2531 XD",
    "addr:housenumber":"69",
    "addr:postcode":"2531 xd",
    "addr:street":"Beatrijsstraat;' S",
    "iso:country":"NL",
    "sg:address":"Beatrijsstraat 69",
    "sg:city":"'S Gravenhage",
    "sg:orig_category":"Aannemers Woningbouw",
    "sg:phone":"+31 74 380 9936",
    "sg:postcode":"2531 XD",
    "sg:province":"Zuid-Holland",
    "wof:name":"B Guth Onderhoud",
    "wof:placetype":"venue"
},
  "geometry": {"coordinates":[4.298421,52.056232],"type":"Point"}
}