{
  "type": "Feature",
  "properties": {
    "iso:country":"NL",
    "sg:address":"Lignestraat 33",
    "sg:city":"Made",
    "sg:orig_category":"Kappers",
    "sg:phone":"+31 162 683 281",
    "sg:postcode":"4921 ET",
    "sg:province":"Noord-Brabant",
    "wof:name":"J.A. Van Dijk",
    "wof:placetype":"venue"
},
  "geometry": {"coordinates":[-119.938117981,36.8766784668],"type":"Point"}
}