{
  "type": "Feature",
  "properties": {
    "addr:full":"Mercuriusplein 30 Berlicum Nb North Brabant 5258 AX",
    "addr:housenumber":"30;nb",
    "addr:postcode":"5258 ax",
    "addr:street":"Mercuriusplein",
    "iso:country":"NL",
    "sg:address":"Mercuriusplein 30",
    "sg:city":"Berlicum Nb",
    "sg:orig_category":"Bloemen And Planten",
    "sg:phone":"+31 73 503 4738",
    "sg:postcode":"5258 AX",
    "sg:province":"North Brabant",
    "wof:name":"Bloemsierkunst Ebronia",
    "wof:placetype":"venue"
},
  "geometry": {"coordinates":[5.418169,51.663883],"type":"Point"}
}