{
  "type": "Feature",
  "properties": {
    "iso:country":"NL",
    "sg:address":"Damrak 37",
    "sg:city":"Amsterdam",
    "sg:orig_category":"Kappers",
    "sg:phone":"+31 20 624 3125",
    "sg:postcode":"1012 LK",
    "sg:province":"Noord-Holland",
    "wof:name":"Haarverzorging Mared",
    "wof:placetype":"venue"
},
  "geometry": {"coordinates":[4.896376133,52.3759155273],"type":"Point"}
}