{
  "type": "Feature",
  "properties": {
    "addr:full":"Spinnekopmolenstr 60 Almere Flevoland 1333 CV",
    "addr:housenumber":"60",
    "addr:postcode":"1333 cv",
    "addr:street":"Spinnekopmolenstr;Flevoland",
    "iso:country":"NL",
    "sg:address":"Spinnekopmolenstr 60",
    "sg:city":"Almere",
    "sg:orig_category":"Balletscholen",
    "sg:phone":"+31 36 532 5197",
    "sg:postcode":"1333 CV",
    "sg:province":"Flevoland",
    "wof:name":"Bayad?re, La",
    "wof:placetype":"venue"
},
  "geometry": {"coordinates":[5.273171,52.401546],"type":"Point"}
}