{
  "type": "Feature",
  "properties": {
    "iso:country":"NL",
    "sg:address":"Hoofdstr 161",
    "sg:city":"Krimpen A/D Lek",
    "sg:orig_category":"Administratie- En Boekhoudkantoren",
    "sg:phone":"+31 180 522 340",
    "sg:postcode":"2931 CJ",
    "sg:province":"Zuid-Holland",
    "wof:name":"Boer, J",
    "wof:placetype":"venue"
},
  "geometry": {"coordinates":[4.632159,51.896053],"type":"Point"}
}