{
  "type": "Feature",
  "properties": {
    "addr:full":"Gravery 41 Drachten Friesland 9202 NM",
    "addr:housenumber":"41",
    "addr:postcode":"9202",
    "addr:street":"Gravery",
    "iso:country":"NL",
    "sg:address":"Gravery 41",
    "sg:city":"Drachten",
    "sg:orig_category":"Onderhoudswerken",
    "sg:phone":"+31 512 522 339",
    "sg:postcode":"9202 NM",
    "sg:province":"Friesland",
    "wof:name":"Egbert",
    "wof:placetype":"venue"
},
  "geometry": {"coordinates":[6.116134,53.101166],"type":"Point"}
}