{
  "type": "Feature",
  "properties": {
    "addr:full":"Oldenzaalsestraat 304 Enschede Overijssel 7523 AH",
    "addr:housenumber":"304",
    "addr:postcode":"7523 ah",
    "addr:street":"Oldenzaalsestraat",
    "iso:country":"NL",
    "sg:address":"Oldenzaalsestraat 304",
    "sg:city":"Enschede",
    "sg:orig_category":"Geluidsopnamen",
    "sg:phone":"+31 53 431 4906",
    "sg:postcode":"7523 AH",
    "sg:province":"Overijssel",
    "wof:name":"Top Sound",
    "wof:placetype":"venue"
},
  "geometry": {"coordinates":[6.902723,52.230766],"type":"Point"}
}