{
  "type": "Feature",
  "properties": {
    "addr:full":"Grotestr 66 Ede Gld Gelderland 6711 AN",
    "addr:housenumber":"66",
    "addr:postcode":"6711 an",
    "addr:street":"Grotestr;Gld Gelderland",
    "iso:country":"NL",
    "sg:address":"Grotestr 66",
    "sg:city":"Ede Gld",
    "sg:orig_category":"Bloemen En Planten",
    "sg:phone":"+31 318 610 424",
    "sg:postcode":"6711 AN",
    "sg:province":"Gelderland",
    "sg:website":"http://www.bloombinders.com",
    "wof:name":"Bloom Binders",
    "wof:placetype":"venue"
},
  "geometry": {"coordinates":[5.671328,52.046581],"type":"Point"}
}