{
  "type": "Feature",
  "properties": {
    "addr:full":"Kl Poelln 12 Rysenhout Noord-Holland 1435 GP",
    "addr:housenumber":"12",
    "addr:postcode":"1435 gp",
    "addr:street":"Rysenhout Noord-Holland",
    "iso:country":"NL",
    "sg:address":"Kl Poelln 12",
    "sg:city":"Rysenhout",
    "sg:orig_category":"Administratie- En Boekhoudkantoren",
    "sg:phone":"+31 297 327 167",
    "sg:postcode":"1435 GP",
    "sg:province":"Noord-Holland",
    "wof:name":"Demmendaal",
    "wof:placetype":"venue"
},
  "geometry": {"coordinates":[4.714654,52.25753],"type":"Point"}
}