{
  "type": "Feature",
  "properties": {
    "addr:full":"Gotlandpier 3 Zaandam Noord-Holland 1506 BP",
    "addr:housenumber":"3",
    "addr:postcode":"1506 bp",
    "addr:street":"Gotlandpier",
    "iso:country":"NL",
    "sg:address":"Gotlandpier 3",
    "sg:city":"Zaandam",
    "sg:orig_category":"Journalisten Freelance",
    "sg:phone":"+31 75 612 0666",
    "sg:postcode":"1506 BP",
    "sg:province":"Noord-Holland",
    "wof:name":"Boukje Van Den Ende",
    "wof:placetype":"venue"
},
  "geometry": {"coordinates":[4.829268,52.432056],"type":"Point"}
}