{
  "type": "Feature",
  "properties": {
    "addr:full":"Haarlemmerdk 91 Amsterdam North Holland 1013 KC",
    "addr:housenumber":"91",
    "addr:postcode":"1013 kc",
    "addr:street":"Haarlemmerdk",
    "iso:country":"NL",
    "sg:address":"Haarlemmerdk 91",
    "sg:city":"Amsterdam",
    "sg:orig_category":"Kappers",
    "sg:phone":"+31 20 626 9449",
    "sg:postcode":"1013 KC",
    "sg:province":"North Holland",
    "wof:name":"Haarstijl",
    "wof:placetype":"venue"
},
  "geometry": {"coordinates":[4.8866639137,52.3829345703],"type":"Point"}
}