{
  "type": "Feature",
  "properties": {
    "addr:full":"Bovendyks 9 Garrelsweer Groningen 9918 RA",
    "addr:housenumber":"9",
    "addr:postcode":"9918 ra",
    "addr:street":"Bovendyks",
    "iso:country":"NL",
    "sg:address":"Bovendyks 9",
    "sg:city":"Garrelsweer",
    "sg:orig_category":"Begrafenisverzorging",
    "sg:phone":"+31 596 571 287",
    "sg:postcode":"9918 RA",
    "sg:province":"Groningen",
    "wof:name":"Laatste Eer, De",
    "wof:placetype":"venue"
},
  "geometry": {"coordinates":[6.770616,53.310745],"type":"Point"}
}