{
  "type": "Feature",
  "properties": {
    "iso:country":"NL",
    "sg:address":"Renesselaan 18",
    "sg:city":"De Meern",
    "sg:orig_category":"Partycatering And -Organisatie",
    "sg:phone":"+31 30 241 3556",
    "sg:postcode":"3454 XX",
    "sg:province":"Utrecht",
    "wof:name":"Nico Lindeman Catering",
    "wof:placetype":"venue"
},
  "geometry": {"coordinates":[5.03657,52.07666],"type":"Point"}
}