{
  "type": "Feature",
  "properties": {
    "addr:full":"Adsteeg 23 Beek Lb Limburg 6191 PW",
    "addr:housenumber":"23",
    "addr:postcode":"lb;6191 pw",
    "addr:street":"Adsteeg",
    "iso:country":"NL",
    "sg:address":"Adsteeg 23",
    "sg:city":"Beek Lb",
    "sg:orig_category":"Kappers",
    "sg:phone":"+31 46 437 6278",
    "sg:postcode":"6191 PW",
    "sg:province":"Limburg",
    "wof:name":"Haarmode Marion Meis",
    "wof:placetype":"venue"
},
  "geometry": {"coordinates":[5.7970819473,50.9347686768],"type":"Point"}
}