{
  "type": "Feature",
  "properties": {
    "iso:country":"NL",
    "sg:address":"Steurstraat 1",
    "sg:city":"Hank",
    "sg:classifiers":[
        {
            "category":"Education",
            "subcategory":"Preschool",
            "type":"Public Place"
        }
    ],
    "sg:phone":"+31 162 402 947",
    "sg:postcode":"4273 EN",
    "sg:province":"Noord-Brabant",
    "sg:tags":[
        "kleuteronderwijs",
        "basis-"
    ],
    "wof:name":"Basisschool De Wilgenhoek",
    "wof:placetype":"venue"
},
  "geometry": {"coordinates":[-103.80326100000001,48.60268],"type":"Point"}
}