{
  "type": "Feature",
  "properties": {
    "addr:full":"Industriewg O 13M Elst Gld Gelderland 6662 NE",
    "addr:housenumber":"13m;6662",
    "addr:street":"Gld Gelderland;Ne",
    "iso:country":"NL",
    "sg:address":"Industriewg O 13M",
    "sg:city":"Elst Gld",
    "sg:orig_category":"Accountants - Administratie- Consulenten En -Kantoren",
    "sg:phone":"+31 481 373 591",
    "sg:postcode":"6662 NE",
    "sg:province":"Gelderland",
    "sg:website":"http://www.brethouwer-partners.nl",
    "wof:name":"Brethouwer & Partners",
    "wof:placetype":"venue"
},
  "geometry": {"coordinates":[5.861792,51.910397],"type":"Point"}
}