{
  "type": "Feature",
  "properties": {
    "addr:full":"Oosterstr 21 Benningbroek North Holland 1654 JK",
    "addr:housenumber":"21",
    "addr:postcode":"1654 jk",
    "addr:street":"Oosterstr",
    "iso:country":"NL",
    "sg:address":"Oosterstr 21",
    "sg:city":"Benningbroek",
    "sg:orig_category":"Bloembollen - Groothandel",
    "sg:phone":"+31 229 575 165",
    "sg:postcode":"1654 JK",
    "sg:province":"North Holland",
    "sg:website":"http://www.ptimmerman.nl",
    "wof:name":"Timmerman, P",
    "wof:placetype":"venue"
},
  "geometry": {"coordinates":[5.035322,52.702824],"type":"Point"}
}