{
  "type": "Feature",
  "properties": {
    "addr:full":"Smissenhaag 151 Maastricht Limburg 6228 HM",
    "addr:housenumber":"151",
    "addr:postcode":"6228 hm",
    "addr:street":"Smissenhaag",
    "iso:country":"NL",
    "sg:address":"Smissenhaag 151",
    "sg:city":"Maastricht",
    "sg:orig_category":"Arbo- En Bedrijfsgezondheids- Diensten",
    "sg:phone":"+31 6 23707524",
    "sg:postcode":"6228 HM",
    "sg:province":"Limburg",
    "wof:name":"Smile",
    "wof:placetype":"venue"
},
  "geometry": {"coordinates":[5.72285,50.827816],"type":"Point"}
}