{
  "type": "Feature",
  "properties": {
    "addr:full":"Ijssel 36 Zaandam Noord-Holland 1509 JB",
    "addr:housenumber":"36",
    "addr:postcode":"1509 jb",
    "addr:street":"Ijssel",
    "iso:country":"NL",
    "sg:address":"Ijssel 36",
    "sg:city":"Zaandam",
    "sg:orig_category":"Bedrijfs- And Managementsconsultants",
    "sg:phone":"+31 75 615 6997",
    "sg:postcode":"1509 JB",
    "sg:province":"Noord-Holland",
    "wof:name":"Search Consult Bv",
    "wof:placetype":"venue"
},
  "geometry": {"coordinates":[4.845463,52.469078],"type":"Point"}
}