{
  "type": "Feature",
  "properties": {
    "addr:full":"Bonengang 19 Gemert Noord-Brabant 5421 BZ",
    "addr:housenumber":"19",
    "addr:postcode":"5421 bz",
    "addr:street":"Bonengang",
    "iso:country":"NL",
    "sg:address":"Bonengang 19",
    "sg:city":"Gemert",
    "sg:orig_category":"Metaalbekleding And -Behandeling",
    "sg:phone":"+31 492 363 497",
    "sg:postcode":"5421 BZ",
    "sg:province":"Noord-Brabant",
    "wof:name":"Swaans Metaal",
    "wof:placetype":"venue"
},
  "geometry": {"coordinates":[5.682859,51.555241],"type":"Point"}
}