{
  "type": "Feature",
  "properties": {
    "addr:full":"Geldersekd 97 Amsterdam Noord-Holland 1011 EM",
    "addr:housenumber":"97",
    "addr:postcode":"1011 em",
    "addr:street":"Geldersekd",
    "iso:country":"NL",
    "sg:address":"Geldersekd 97",
    "sg:city":"Amsterdam",
    "sg:orig_category":"Adviesbureaus Bedrijfsorganisatie",
    "sg:phone":"+31 20 620 0447",
    "sg:postcode":"1011 EM",
    "sg:province":"Noord-Holland",
    "wof:name":"Lhb Management",
    "wof:placetype":"venue"
},
  "geometry": {"coordinates":[4.893195,52.373119],"type":"Point"}
}