{
  "type": "Feature",
  "properties": {
    "addr:full":"Zuiderzeewg 2 Amsterdam Noord-Holland 1095 KG",
    "addr:housenumber":"2",
    "addr:postcode":"1095 kg",
    "addr:street":"Zuiderzeewg",
    "iso:country":"NL",
    "sg:address":"Zuiderzeewg 2",
    "sg:city":"Amsterdam",
    "sg:orig_category":"Boten",
    "sg:phone":"+31 20 694 7527",
    "sg:postcode":"1095 KG",
    "sg:province":"Noord-Holland",
    "wof:name":"Holland Sport Boat Centre Bv",
    "wof:placetype":"venue"
},
  "geometry": {"coordinates":[4.962421,52.370686],"type":"Point"}
}