{
  "type": "Feature",
  "properties": {
    "iso:country":"NL",
    "sg:address":"Dorpsstr 33",
    "sg:city":"Zoeterwoude",
    "sg:orig_category":"Artsen - Huisartsen",
    "sg:phone":"+31 71 580 1614",
    "sg:postcode":"2381 EK",
    "sg:province":"Zuid-Holland",
    "wof:name":"Kortmann, L B A J M",
    "wof:placetype":"venue"
},
  "geometry": {"coordinates":[4.495892,52.120426],"type":"Point"}
}