{
  "type": "Feature",
  "properties": {
    "addr:full":"Dorpsstraat 9 Oeffelt Noord-Brabant 5441 AC",
    "addr:housenumber":"9",
    "addr:postcode":"5441 ac",
    "addr:street":"Dorpsstraat",
    "iso:country":"NL",
    "sg:address":"Dorpsstraat 9",
    "sg:city":"Oeffelt",
    "sg:classifiers":[
        {
            "category":"Food & Beverages",
            "subcategory":"Fruits & Vegetables",
            "type":"Retail Goods"
        }
    ],
    "sg:phone":"+31 485 361 257",
    "sg:postcode":"5441 AC",
    "sg:province":"Noord-Brabant",
    "sg:tags":[
        "groenten"
    ],
    "wof:name":"Mamon Sorteer Bv",
    "wof:placetype":"venue"
},
  "geometry": {"coordinates":[5.936224,51.695011],"type":"Point"}
}