{
  "type": "Feature",
  "properties": {
    "addr:full":"Henrick De Keijserstraat 27 Amsterdam Noord-Holland 1073 TG",
    "addr:housenumber":"27",
    "addr:postcode":"1073 tg",
    "addr:street":"Henrick De Keijserstraat",
    "iso:country":"NL",
    "sg:address":"Henrick De Keijserstraat 27",
    "sg:city":"Amsterdam",
    "sg:orig_category":"Verhuur Catering-, Feest- En Evenementbenodigdheden",
    "sg:phone":"+31 20 662 8097",
    "sg:postcode":"1073 TG",
    "sg:province":"Noord-Holland",
    "wof:name":"Cafe A.P.M. Hollander",
    "wof:placetype":"venue"
},
  "geometry": {"coordinates":[4.897637,52.351833],"type":"Point"}
}