{
  "type": "Feature",
  "properties": {
    "iso:country":"NL",
    "sg:address":"Houtsestr 67",
    "sg:city":"Helmond",
    "sg:orig_category":"Bloemen En Planten",
    "sg:phone":"+31 492 522 649",
    "sg:postcode":"5706 LR",
    "sg:province":"Noord-Brabant",
    "wof:name":"Rens Van Dijk",
    "wof:placetype":"venue"
},
  "geometry": {"coordinates":[5.630489,51.458355],"type":"Point"}
}