{
  "type": "Feature",
  "properties": {
    "addr:full":"Verl Hofln 72 Arnhem Gelderland 6822 ED",
    "addr:housenumber":"72",
    "addr:postcode":"6822 ed",
    "iso:country":"NL",
    "sg:address":"Verl Hofln 72",
    "sg:city":"Arnhem",
    "sg:orig_category":"Verenigingen En Stichtingen",
    "sg:phone":"+31 26 445 5572",
    "sg:postcode":"6822 ED",
    "sg:province":"Gelderland",
    "wof:name":"Leergeld Arnhem, Sticht",
    "wof:placetype":"venue"
},
  "geometry": {"coordinates":[5.92376,51.997181],"type":"Point"}
}