{
  "type": "Feature",
  "properties": {
    "addr:full":"Julianastr 2 Venlo Limburg 5911 AX",
    "addr:housenumber":"2",
    "addr:postcode":"5911 ax",
    "addr:street":"Julianastr",
    "iso:country":"NL",
    "sg:address":"Julianastr 2",
    "sg:city":"Venlo",
    "sg:classifiers":[
        {
            "category":"Wholesale",
            "subcategory":"Meat",
            "type":"Manufacturing & Wholesale Goods"
        }
    ],
    "sg:phone":"+31 77 352 0997",
    "sg:postcode":"5911 AX",
    "sg:province":"Limburg",
    "sg:tags":[
        "regeltechniek",
        "en",
        "meet-"
    ],
    "wof:name":"Marinex",
    "wof:placetype":"venue"
},
  "geometry": {"coordinates":[6.174885,51.371342],"type":"Point"}
}