{
  "type": "Feature",
  "properties": {
    "addr:full":"De Linie 3R Capelle Ad Yssel Zuid-Holland 2905 AX",
    "addr:housenumber":"3r",
    "addr:postcode":"2905 ax",
    "addr:street":"De Linie",
    "iso:country":"NL",
    "sg:address":"De Linie 3R",
    "sg:city":"Capelle Ad Yssel",
    "sg:orig_category":"Projectontwikkeling",
    "sg:phone":"+31 10 450 2967",
    "sg:postcode":"2905 AX",
    "sg:province":"Zuid-Holland",
    "wof:name":"Octavo Bv",
    "wof:placetype":"venue"
},
  "geometry": {"coordinates":[4.598605,51.934635],"type":"Point"}
}