{
  "type": "Feature",
  "properties": {
    "iso:country":"NL",
    "sg:address":"Herengracht 469-473",
    "sg:city":"1017",
    "sg:classifiers":[
        {
            "category":"Banks & Credit Unions",
            "subcategory":"Bank",
            "type":"Services"
        }
    ],
    "sg:phone":"+31 20 620 2111",
    "sg:postcode":"AMST ER",
    "sg:province":"North Holland",
    "wof:name":"Phillipine, National Bank",
    "wof:placetype":"venue"
},
  "geometry": {"coordinates":[4.890336,52.366039],"type":"Point"}
}