{
  "type": "Feature",
  "properties": {
    "addr:full":"Overtoom 155 Amsterdam Noord-Holland 1054 HG",
    "addr:housenumber":"155",
    "addr:postcode":"1054 hg",
    "addr:street":"Overtoom",
    "iso:country":"NL",
    "sg:address":"Overtoom 155",
    "sg:city":"Amsterdam",
    "sg:orig_category":"Psychologen",
    "sg:phone":"+31 20 685 2636",
    "sg:postcode":"1054 HG",
    "sg:province":"Noord-Holland",
    "wof:name":"Bugel, Drs Job",
    "wof:placetype":"venue"
},
  "geometry": {"coordinates":[4.872364,52.361801],"type":"Point"}
}