{
  "type": "Feature",
  "properties": {
    "addr:full":"Venneslatwg 8 Eibergen Gelderland 7151 HD",
    "addr:housenumber":"8",
    "addr:postcode":"7151 hd",
    "addr:street":"Venneslatwg;Gelderland",
    "iso:country":"NL",
    "sg:address":"Venneslatwg 8",
    "sg:city":"Eibergen",
    "sg:orig_category":"Honden- En Kattentrimsalons",
    "sg:phone":"+31 545 477 804",
    "sg:postcode":"7151 HD",
    "sg:province":"Gelderland",
    "wof:name":"Marlies",
    "wof:placetype":"venue"
},
  "geometry": {"coordinates":[6.640202,52.091335],"type":"Point"}
}