{
  "type": "Feature",
  "properties": {
    "iso:country":"NL",
    "sg:address":"J De Wittstr 144",
    "sg:city":"Groningen",
    "sg:orig_category":"Afslankinstituten",
    "sg:phone":"+31 50 577 3232",
    "sg:postcode":"9716 CK",
    "sg:province":"Groningen",
    "wof:name":"Jansma, M",
    "wof:placetype":"venue"
},
  "geometry": {"coordinates":[6.560269,53.231415],"type":"Point"}
}