{
  "type": "Feature",
  "properties": {
    "iso:country":"NL",
    "sg:address":"Dominicanenstraat 18",
    "sg:city":"Nijmegen",
    "sg:orig_category":"Boekhouders",
    "sg:phone":"+31 24 323 1609",
    "sg:postcode":"6521 KD",
    "sg:province":"Gelderland",
    "wof:name":"F.G. Uitterhoeve",
    "wof:placetype":"venue"
},
  "geometry": {"coordinates":[5.8732261658,51.8413963318],"type":"Point"}
}