{
  "type": "Feature",
  "properties": {
    "iso:country":"NL",
    "sg:address":"Venneperweg 300",
    "sg:city":"Nieuw Vennep",
    "sg:orig_category":"Verlichting And Huishoudartikelen",
    "sg:phone":"+31 252 673 438",
    "sg:postcode":"2153 AE",
    "sg:province":"Noord-Holland",
    "wof:name":"Da Costa",
    "wof:placetype":"venue"
},
  "geometry": {"coordinates":[4.639062,52.26186],"type":"Point"}
}