{
  "type": "Feature",
  "properties": {
    "iso:country":"NL",
    "sg:address":"Grachtwg 75A",
    "sg:city":"Lisse",
    "sg:orig_category":"Veilingen En Venduhuizen",
    "sg:phone":"+31 252 431 431",
    "sg:postcode":"2161 HM",
    "sg:province":"Zuid-Holland",
    "wof:name":"Cnb",
    "wof:placetype":"venue"
},
  "geometry": {"coordinates":[4.558483,52.258217],"type":"Point"}
}