{
  "type": "Feature",
  "properties": {
    "iso:country":"NL",
    "sg:address":"Htg Janpln 21",
    "sg:city":"Erp",
    "sg:orig_category":"Banken",
    "sg:phone":"+31 413 346 666",
    "sg:postcode":"5469 BJ",
    "sg:province":"Noord-Brabant",
    "sg:website":"http://www.rabobank.nl",
    "wof:name":"Rabobank",
    "wof:placetype":"venue"
},
  "geometry": {"coordinates":[2.31313,9.32204],"type":"Point"}
}