{
  "type": "Feature",
  "properties": {
    "iso:country":"NL",
    "sg:address":"Somerweide 24",
    "sg:city":"Breda",
    "sg:orig_category":"Organisaties And Verenigingen",
    "sg:phone":"+31 76 542 1753",
    "sg:postcode":"4824 EW",
    "sg:province":"Noord-Brabant",
    "wof:name":"Scouting Haagse Beemden",
    "wof:placetype":"venue"
},
  "geometry": {"coordinates":[4.748210907,51.6113586426],"type":"Point"}
}