{
  "type": "Feature",
  "properties": {
    "addr:full":"Klavermaten 1 Goor Overijssel 7472 DD",
    "addr:housenumber":"1",
    "addr:postcode":"7472 dd",
    "addr:street":"Klavermaten",
    "iso:country":"NL",
    "sg:address":"Klavermaten 1",
    "sg:city":"Goor",
    "sg:classifiers":[
        {
            "category":"Retail",
            "subcategory":"Auto Repair",
            "type":"Services"
        }
    ],
    "sg:phone":"+31 547 272 727",
    "sg:postcode":"7472 DD",
    "sg:province":"Overijssel",
    "sg:tags":[
        "garage"
    ],
    "wof:name":"Klumpers Vof",
    "wof:placetype":"venue"
},
  "geometry": {"coordinates":[6.59367,52.245998],"type":"Point"}
}