{
  "type": "Feature",
  "properties": {
    "addr:full":"Driesveldln 99 Weert Limburg 6001 KC",
    "addr:housenumber":"99",
    "addr:postcode":"6001 kc",
    "addr:street":"Driesveldln",
    "iso:country":"NL",
    "sg:address":"Driesveldln 99",
    "sg:city":"Weert",
    "sg:classifiers":[
        {
            "category":"Travel",
            "subcategory":"Hotels & Motels",
            "type":"Entertainment"
        }
    ],
    "sg:phone":"+31 495 539 655",
    "sg:postcode":"6001 KC",
    "sg:province":"Limburg",
    "sg:website":"http://www.goldentulipweert.nl",
    "wof:name":"Golden Tulip Weert",
    "wof:placetype":"venue"
},
  "geometry": {"coordinates":[5.702766,51.249813],"type":"Point"}
}