{
  "type": "Feature",
  "properties": {
    "addr:full":"Fluitekruid 12 Bergschenhoek Zuid-Holland 2661 JB",
    "addr:housenumber":"12",
    "addr:postcode":"2661 jb",
    "addr:street":"Fluitekruid",
    "iso:country":"NL",
    "sg:address":"Fluitekruid 12",
    "sg:city":"Bergschenhoek",
    "sg:orig_category":"Scheepvaart- Agentschappen",
    "sg:phone":"+31 10 529 0368",
    "sg:postcode":"2661 JB",
    "sg:province":"Zuid-Holland",
    "wof:name":"Dumar Chartering Bv",
    "wof:placetype":"venue"
},
  "geometry": {"coordinates":[4.50377,51.985252],"type":"Point"}
}