{
  "type": "Feature",
  "properties": {
    "addr:full":"Compagniewg 6 Barneveld Gelderland 3771 NH",
    "addr:housenumber":"6",
    "addr:postcode":"3771 nh",
    "addr:street":"Compagniewg;Gelderland",
    "iso:country":"NL",
    "sg:address":"Compagniewg 6",
    "sg:city":"Barneveld",
    "sg:orig_category":"Machineonderhoud En -Reparatie",
    "sg:phone":"+31 342 420 653",
    "sg:postcode":"3771 NH",
    "sg:province":"Gelderland",
    "wof:name":"Microtech",
    "wof:placetype":"venue"
},
  "geometry": {"coordinates":[5.610567,52.165661],"type":"Point"}
}