{
  "type": "Feature",
  "properties": {
    "addr:full":"Heereweg 1 Terschelling Midsland Friesland 8891 HS",
    "addr:housenumber":"1",
    "addr:postcode":"8891 hs",
    "addr:street":"Heereweg",
    "iso:country":"NL",
    "sg:address":"Heereweg 1",
    "sg:city":"Terschelling Midsland",
    "sg:orig_category":"Banken And Kredietinstellingen",
    "sg:phone":"+31 562 448 700",
    "sg:postcode":"8891 HS",
    "sg:province":"Friesland",
    "wof:name":"Postkantoor",
    "wof:placetype":"venue"
},
  "geometry": {"coordinates":[5.2844,53.383377],"type":"Point"}
}