{
  "type": "Feature",
  "properties": {
    "iso:country":"NL",
    "sg:address":"Gulden Hoeve 12",
    "sg:city":"Vleuten",
    "sg:orig_category":"Onderhoudswerken",
    "sg:phone":"+31 30 677 2959",
    "sg:postcode":"3451 TG",
    "sg:province":"Utrecht",
    "wof:name":"Roned",
    "wof:placetype":"venue"
},
  "geometry": {"coordinates":[5.024725,52.109241],"type":"Point"}
}