{
  "type": "Feature",
  "properties": {
    "addr:full":"Vellengastr 18 Zwartebroek Gelderland 3785 LA",
    "addr:housenumber":"18;3785",
    "addr:street":"Vellengastr;Gelderland",
    "iso:country":"NL",
    "sg:address":"Vellengastr 18",
    "sg:city":"Zwartebroek",
    "sg:orig_category":"Scholen Voor Basisonderwijs",
    "sg:phone":"+31 342 461 836",
    "sg:postcode":"3785 LA",
    "sg:province":"Gelderland",
    "wof:name":"Anker, Het",
    "wof:placetype":"venue"
},
  "geometry": {"coordinates":[5.506953,52.177876],"type":"Point"}
}