{
  "type": "Feature",
  "properties": {
    "iso:country":"NL",
    "sg:address":"Wouterskampen 78",
    "sg:city":"Hierden",
    "sg:orig_category":"Loodgieters",
    "sg:phone":"+31 6 25511484",
    "sg:postcode":"3849 BC",
    "sg:province":"Gelderland",
    "wof:name":"Poolen, Peter",
    "wof:placetype":"venue"
},
  "geometry": {"coordinates":[5.677936,52.359394],"type":"Point"}
}