{
  "type": "Feature",
  "properties": {
    "iso:country":"NL",
    "sg:address":"Halvestraat 2",
    "sg:city":"Deventer",
    "sg:orig_category":"Meubelreparatie And -Restauratie",
    "sg:phone":"+31 570 615 033",
    "sg:postcode":"7412 VN",
    "sg:province":"Overijssel",
    "wof:name":"Meubelstoffering Hupkes",
    "wof:placetype":"venue"
},
  "geometry": {"coordinates":[6.149466,52.25946],"type":"Point"}
}