{
  "type": "Feature",
  "properties": {
    "addr:full":"V Diemenstr 196 S Gravenhage South Holland 2518 VH",
    "addr:housenumber":"196",
    "addr:postcode":"2518 vh",
    "addr:street":"V Diemenstr;S Gravenhage",
    "iso:country":"NL",
    "sg:address":"V Diemenstr 196",
    "sg:city":"S Gravenhage",
    "sg:orig_category":"Kamerverhuur En -Bemiddeling",
    "sg:phone":"+31 70 392 4772",
    "sg:postcode":"2518 VH",
    "sg:province":"South Holland",
    "wof:name":"Franke Beheer O/G",
    "wof:placetype":"venue"
},
  "geometry": {"coordinates":[4.2934799194,52.0803184509],"type":"Point"}
}