{
  "type": "Feature",
  "properties": {
    "addr:full":"Sprengenweg 28 Apeldoorn Gelderland 7314 ET",
    "addr:housenumber":"28",
    "addr:postcode":"7314 et",
    "addr:street":"Sprengenweg;Gelderland",
    "iso:country":"NL",
    "sg:address":"Sprengenweg 28",
    "sg:city":"Apeldoorn",
    "sg:orig_category":"Kappers",
    "sg:phone":"+31 55 521 9459",
    "sg:postcode":"7314 ET",
    "sg:province":"Gelderland",
    "wof:name":"Le Coiffeur",
    "wof:placetype":"venue"
},
  "geometry": {"coordinates":[5.951839,52.217285],"type":"Point"}
}