{
  "type": "Feature",
  "properties": {
    "addr:full":"Westeinde 41 Waalwyk North Brabant 5141 AB",
    "addr:housenumber":"41",
    "addr:postcode":"5141 ab",
    "addr:street":"Westeinde",
    "iso:country":"NL",
    "sg:address":"Westeinde 41",
    "sg:city":"Waalwyk",
    "sg:orig_category":"Jachthavens - Jachtwerven",
    "sg:phone":"+31 416 336 563",
    "sg:postcode":"5141 AB",
    "sg:province":"North Brabant",
    "wof:name":"Hoven Vof, B Van Den",
    "wof:placetype":"venue"
},
  "geometry": {"coordinates":[5.046452,51.68829],"type":"Point"}
}