{
  "type": "Feature",
  "properties": {
    "addr:full":"L Vd Maesenstr 11 Valkenburg Lb Limburg 6301 EA",
    "addr:housenumber":"11",
    "addr:postcode":"lb;6301 ea",
    "iso:country":"NL",
    "sg:address":"L Vd Maesenstr 11",
    "sg:city":"Valkenburg Lb",
    "sg:orig_category":"Makelaars En Adviseurs Onroerende Goederen",
    "sg:phone":"+31 43 601 4010",
    "sg:postcode":"6301 EA",
    "sg:province":"Limburg",
    "sg:website":"http://www.roks-eurlings.nl",
    "wof:name":"Roks & Eurlings Vastgoed",
    "wof:placetype":"venue"
},
  "geometry": {"coordinates":[5.83344,50.861328],"type":"Point"}
}