{
  "type": "Feature",
  "properties": {
    "addr:full":"Kuipers Rietbergk 33 Middelburg Zeeland 4333 EK",
    "addr:housenumber":"33",
    "addr:postcode":"4333 ek",
    "iso:country":"NL",
    "sg:address":"Kuipers Rietbergk 33",
    "sg:city":"Middelburg",
    "sg:orig_category":"Scholen Voor Basisonderwijs",
    "sg:phone":"+31 118 614 448",
    "sg:postcode":"4333 EK",
    "sg:province":"Zeeland",
    "wof:name":"Herman Faukeliusschool Reform",
    "wof:placetype":"venue"
},
  "geometry": {"coordinates":[3.611062,51.508381],"type":"Point"}
}