{
  "type": "Feature",
  "properties": {
    "addr:full":"Windroospln 94 Amsterdam North Holland 1018 ZW",
    "addr:housenumber":"94",
    "addr:postcode":"1018 zw",
    "addr:street":"Windroospln",
    "iso:country":"NL",
    "sg:address":"Windroospln 94",
    "sg:city":"Amsterdam",
    "sg:orig_category":"Modelbouw",
    "sg:phone":"+31 20 625 3000",
    "sg:postcode":"1018 ZW",
    "sg:province":"North Holland",
    "wof:name":"Wittenburg",
    "wof:placetype":"venue"
},
  "geometry": {"coordinates":[4.924861,52.373093],"type":"Point"}
}