{
  "type": "Feature",
  "properties": {
    "iso:country":"NL",
    "sg:address":"Pagenln 6",
    "sg:city":"Limmen",
    "sg:orig_category":"Bloemen En Planten - Groothandel",
    "sg:phone":"+31 72 505 1343",
    "sg:postcode":"1906 CT",
    "sg:province":"Connecticut",
    "wof:name":"Verver Zn, H A",
    "wof:placetype":"venue"
},
  "geometry": {"coordinates":[-72.75747699999999,41.515572],"type":"Point"}
}