{
  "type": "Feature",
  "properties": {
    "addr:full":"Meuluntersewg 18 Lunteren Gelderland 6741 HN",
    "addr:housenumber":"18",
    "addr:postcode":"6741 hn",
    "addr:street":"Meuluntersewg;Gelderland",
    "iso:country":"NL",
    "sg:address":"Meuluntersewg 18",
    "sg:city":"Lunteren",
    "sg:orig_category":"Pluimveebedrijven En -Handelaren",
    "sg:phone":"+31 318 482 601",
    "sg:postcode":"6741 HN",
    "sg:province":"Gelderland",
    "wof:name":"Berg, H Van Den",
    "wof:placetype":"venue"
},
  "geometry": {"coordinates":[5.624232,52.102333],"type":"Point"}
}