{
  "type": "Feature",
  "properties": {
    "iso:country":"NL",
    "sg:address":"Zuideinde 3",
    "sg:city":"Meppel",
    "sg:orig_category":"Hypotheken",
    "sg:phone":"+31 522 246 409",
    "sg:postcode":"7941 GA",
    "sg:province":"Drenthe",
    "wof:name":"Rendement Adviesgroep Meppel",
    "wof:placetype":"venue"
},
  "geometry": {"coordinates":[6.196295,52.699615],"type":"Point"}
}