{
  "type": "Feature",
  "properties": {
    "addr:full":"H Geestkerkhof 2 Delft Zuid-Holland 2611 HP",
    "addr:housenumber":"2",
    "addr:postcode":"2611 hp",
    "addr:street":"Geestkerkhof",
    "iso:country":"NL",
    "sg:address":"H Geestkerkhof 2",
    "sg:city":"Delft",
    "sg:orig_category":"Kaartverkoop En Reserveringen",
    "sg:phone":"+31 15 213 6050",
    "sg:postcode":"2611 HP",
    "sg:province":"Zuid-Holland",
    "wof:name":"Kaartenhuis",
    "wof:placetype":"venue"
},
  "geometry": {"coordinates":[4.3556141853,52.0121765137],"type":"Point"}
}