{
  "type": "Feature",
  "properties": {
    "addr:full":"Gondulfusstraat 12 Brunssum Limburg 6444 VB",
    "addr:housenumber":"12",
    "addr:postcode":"6444 vb",
    "addr:street":"Gondulfusstraat",
    "iso:country":"NL",
    "sg:address":"Gondulfusstraat 12",
    "sg:city":"Brunssum",
    "sg:classifiers":[
        {
            "category":"Fast Food",
            "type":"Food & Drink"
        }
    ],
    "sg:phone":"+31 45 525 6514",
    "sg:postcode":"6444 VB",
    "sg:province":"Limburg",
    "sg:tags":[
        "afhaal",
        "restaurant"
    ],
    "wof:name":"R.L.S.E. Berkloo-Den Ronde",
    "wof:placetype":"venue"
},
  "geometry": {"coordinates":[5.95764,50.936668],"type":"Point"}
}