{
  "type": "Feature",
  "properties": {
    "addr:full":"Koepoortswg 23 Hoorn Nh North Holland 1624 AB",
    "addr:housenumber":"23",
    "addr:postcode":"1624 ab",
    "addr:street":"Koepoortswg;Nh North",
    "iso:country":"NL",
    "sg:address":"Koepoortswg 23",
    "sg:city":"Hoorn Nh",
    "sg:orig_category":"Fietsen En Bromfietsen",
    "sg:phone":"+31 229 215 427",
    "sg:postcode":"1624 AB",
    "sg:province":"North Holland",
    "wof:name":"Beck, Bromfietsen",
    "wof:placetype":"venue"
},
  "geometry": {"coordinates":[5.05894,52.644379],"type":"Point"}
}