{
  "type": "Feature",
  "properties": {
    "iso:country":"NL",
    "sg:address":"Middenwg 598",
    "sg:city":"Heerhugowaard",
    "sg:orig_category":"Hek- En Rasterwerken",
    "sg:phone":"+31 72 571 5927",
    "sg:postcode":"1704 BS",
    "sg:province":"Noord-Holland",
    "wof:name":"B & S, Hekwerk/Kennelbouw",
    "wof:placetype":"venue"
},
  "geometry": {"coordinates":[4.852599,52.712605],"type":"Point"}
}