{
  "type": "Feature",
  "properties": {
    "addr:full":"Abdisstraat 35 Prinsenbeek Noord-Brabant 4841 HE",
    "addr:housenumber":"35",
    "addr:postcode":"4841 he",
    "addr:street":"Abdisstraat",
    "iso:country":"NL",
    "sg:address":"Abdisstraat 35",
    "sg:city":"Prinsenbeek",
    "sg:orig_category":"Technische Studies And Onderzoek",
    "sg:phone":"+31 76 541 3692",
    "sg:postcode":"4841 HE",
    "sg:province":"Noord-Brabant",
    "wof:name":"R.C.E. (Roovers Control Engineering)",
    "wof:placetype":"venue"
},
  "geometry": {"coordinates":[4.714657,51.603638],"type":"Point"}
}