{
  "type": "Feature",
  "properties": {
    "addr:full":"Oergongswei 15 Scharnegoutum Provincie Friesland 8629 SZ",
    "addr:housenumber":"15",
    "addr:postcode":"8629 sz",
    "addr:street":"Oergongswei;Provincie Friesland",
    "iso:country":"NL",
    "sg:address":"Oergongswei 15",
    "sg:city":"Scharnegoutum",
    "sg:orig_category":"Metaalbewerking",
    "sg:phone":"+31 515 540 953",
    "sg:postcode":"8629 SZ",
    "sg:province":"Provincie Friesland",
    "sg:website":"http://www.jhpmotorparts.nl",
    "wof:name":"Jhp Motorparts",
    "wof:placetype":"venue"
},
  "geometry": {"coordinates":[5.67182,53.061691],"type":"Point"}
}