{
  "type": "Feature",
  "properties": {
    "iso:country":"NL",
    "sg:address":"Trommelaarshoeve 119",
    "sg:city":"Apeldoorn",
    "sg:orig_category":"Adviesbureaus Bedrijfsorganisatie",
    "sg:phone":"+31 6 21930755",
    "sg:postcode":"7326 VR",
    "sg:province":"Gelderland",
    "wof:name":"Lift Up",
    "wof:placetype":"venue"
},
  "geometry": {"coordinates":[6.003293,52.191105],"type":"Point"}
}