{
  "type": "Feature",
  "properties": {
    "addr:full":"Verhulstln 69 Tilburg Noord-Brabant 5012 GA",
    "addr:housenumber":"69",
    "addr:postcode":"5012 ga",
    "addr:street":"Verhulstln",
    "iso:country":"NL",
    "sg:address":"Verhulstln 69",
    "sg:city":"Tilburg",
    "sg:orig_category":"Administratie- En Boekhoudkantoren",
    "sg:phone":"+31 13 542 3412",
    "sg:postcode":"5012 GA",
    "sg:province":"Noord-Brabant",
    "wof:name":"Erick De Veer",
    "wof:placetype":"venue"
},
  "geometry": {"coordinates":[5.106271,51.554928],"type":"Point"}
}