{
  "type": "Feature",
  "properties": {
    "iso:country":"NL",
    "sg:address":"Denemarkenweg 9-11",
    "sg:city":"Bodegraven",
    "sg:orig_category":"Zuivelproducten And Spijsoli?n Gh",
    "sg:phone":"+31 172 610 808",
    "sg:postcode":"2411 RK",
    "sg:province":"Zuid-Holland",
    "wof:name":"Centraal Promotiepunt",
    "wof:placetype":"venue"
},
  "geometry": {"coordinates":[4.763529,52.070629],"type":"Point"}
}