{
  "type": "Feature",
  "properties": {
    "addr:full":"Oosteind 20 Sprang-Capelle North Brabant 5161 MJ",
    "addr:housenumber":"20",
    "addr:postcode":"5161 mj",
    "addr:street":"Oosteind",
    "iso:country":"NL",
    "sg:address":"Oosteind 20",
    "sg:city":"Sprang-Capelle",
    "sg:orig_category":"Loodgieterswerk, Verwarming And Sanitaire Installaties",
    "sg:phone":"+31 416 283 061",
    "sg:postcode":"5161 MJ",
    "sg:province":"North Brabant",
    "wof:name":"Hensen Synergie Vof",
    "wof:placetype":"venue"
},
  "geometry": {"coordinates":[5.02336,51.670841],"type":"Point"}
}