{
  "type": "Feature",
  "properties": {
    "addr:full":"Groenland 5 Vinkeveen Utrecht 3645 LG",
    "addr:housenumber":"5",
    "addr:postcode":"3645 lg",
    "addr:street":"Groenland",
    "iso:country":"NL",
    "sg:address":"Groenland 5",
    "sg:city":"Vinkeveen",
    "sg:orig_category":"Boekhouders",
    "sg:phone":"+31 297 262 759",
    "sg:postcode":"3645 LG",
    "sg:province":"Utrecht",
    "wof:name":"N.J.H. Kessen-Hendriks",
    "wof:placetype":"venue"
},
  "geometry": {"coordinates":[4.922551,52.208061],"type":"Point"}
}