{
  "type": "Feature",
  "properties": {
    "addr:full":"Hofstr 8 Ysselstein Ut Utrecht 3401 DE",
    "addr:housenumber":"8",
    "addr:postcode":"3401 de",
    "addr:street":"Hofstr",
    "iso:country":"NL",
    "sg:address":"Hofstr 8",
    "sg:city":"Ysselstein Ut",
    "sg:orig_category":"Woninginrichting",
    "sg:phone":"+31 30 688 2652",
    "sg:postcode":"3401 DE",
    "sg:province":"Utrecht",
    "wof:name":"Brokking, Woonhuis",
    "wof:placetype":"venue"
},
  "geometry": {"coordinates":[5.0435781479,52.0202598572],"type":"Point"}
}