{
  "type": "Feature",
  "properties": {
    "iso:country":"NL",
    "sg:address":"Van Boshuizenstraat 671",
    "sg:city":"Amsterdam",
    "sg:orig_category":"Vertaal- And Tolkenbureaus",
    "sg:phone":"+31 20 644 3636",
    "sg:postcode":"1082 AZ",
    "sg:province":"Noord-Holland",
    "wof:name":"De Taalmeesters",
    "wof:placetype":"venue"
},
  "geometry": {"coordinates":[4.871477,52.324409],"type":"Point"}
}