{
  "type": "Feature",
  "properties": {
    "addr:full":"Eemhof 10 Eemnes Utrecht 3755 JA",
    "addr:housenumber":"10",
    "addr:postcode":"3755 ja",
    "addr:street":"Eemhof",
    "iso:country":"NL",
    "sg:address":"Eemhof 10",
    "sg:city":"Eemnes",
    "sg:orig_category":"Kappers",
    "sg:phone":"+31 35 538 6670",
    "sg:postcode":"3755 JA",
    "sg:province":"Utrecht",
    "wof:name":"Eemhof Kappers",
    "wof:placetype":"venue"
},
  "geometry": {"coordinates":[5.2580370903,52.2584762573],"type":"Point"}
}