{
  "type": "Feature",
  "properties": {
    "addr:full":"Steureiland 18 S Gravenhage 2492 NB",
    "addr:housenumber":"18;2492",
    "addr:postcode":"nb",
    "addr:street":"Steureiland;S Gravenhage",
    "iso:country":"NL",
    "sg:address":"Steureiland 18",
    "sg:city":"S Gravenhage",
    "sg:orig_category":"Autorijscholen",
    "sg:phone":"+31 70 327 1566",
    "sg:postcode":"2492 NB",
    "wof:name":"Kisoen",
    "wof:placetype":"venue"
},
  "geometry": {"coordinates":[4.40783,52.067459],"type":"Point"}
}