{
  "type": "Feature",
  "properties": {
    "addr:full":"W Sonneveldstr 43 Haarlem Noord-Holland 2033 ZR",
    "addr:housenumber":"43",
    "addr:postcode":"2033 zr",
    "addr:street":"W",
    "iso:country":"NL",
    "sg:address":"W Sonneveldstr 43",
    "sg:city":"Haarlem",
    "sg:orig_category":"Plafonds",
    "sg:phone":"+31 23 533 2387",
    "sg:postcode":"2033 ZR",
    "sg:province":"Noord-Holland",
    "wof:name":"Ruiter, E De",
    "wof:placetype":"venue"
},
  "geometry": {"coordinates":[4.664724,52.381111],"type":"Point"}
}