{
  "type": "Feature",
  "properties": {
    "iso:country":"NL",
    "sg:address":"Buorren 10",
    "sg:city":"Wijnaldum",
    "sg:classifiers":[
        {
            "category":"Education",
            "subcategory":"Preschool",
            "type":"Public Place"
        }
    ],
    "sg:phone":"+31 517 591 780",
    "sg:postcode":"8857 BL",
    "sg:province":"Friesland",
    "sg:tags":[
        "kleuteronderwijs",
        "basis-"
    ],
    "wof:name":"E.P. De Boerschool",
    "wof:placetype":"venue"
},
  "geometry": {"coordinates":[5.462447,53.195133],"type":"Point"}
}