{
  "type": "Feature",
  "properties": {
    "addr:full":"Leidsestrwg 7A Woerden Utrecht 3443 BP",
    "addr:housenumber":"7a",
    "addr:postcode":"3443 bp",
    "addr:street":"Leidsestrwg",
    "iso:country":"NL",
    "sg:address":"Leidsestrwg 7A",
    "sg:city":"Woerden",
    "sg:orig_category":"Biljartzalen",
    "sg:phone":"+31 348 415 785",
    "sg:postcode":"3443 BP",
    "sg:province":"Utrecht",
    "wof:name":"Snooker",
    "wof:placetype":"venue"
},
  "geometry": {"coordinates":[4.887371,52.085117],"type":"Point"}
}