{
  "type": "Feature",
  "properties": {
    "addr:full":"Olivien 1A S Gravenzande Zuid-Holland 2691 HS",
    "addr:housenumber":"1a;gravenzande",
    "addr:postcode":"2691 hs",
    "addr:street":"Olivien;S",
    "iso:country":"NL",
    "sg:address":"Olivien 1A",
    "sg:city":"S Gravenzande",
    "sg:orig_category":"Orthopedisch Schoeisel",
    "sg:phone":"+31 174 444 201",
    "sg:postcode":"2691 HS",
    "sg:province":"Zuid-Holland",
    "wof:name":"Ortho-Combi",
    "wof:placetype":"venue"
},
  "geometry": {"coordinates":[4.1674938202,51.9943618774],"type":"Point"}
}