{
  "type": "Feature",
  "properties": {
    "addr:full":"Raadhuisstr 61 Voorburg Zuid-Holland 2271 CW",
    "addr:housenumber":"61",
    "addr:postcode":"2271 cw",
    "addr:street":"Raadhuisstr",
    "iso:country":"NL",
    "sg:address":"Raadhuisstr 61",
    "sg:city":"Voorburg",
    "sg:orig_category":"Loopbaanbegeleiding",
    "sg:phone":"+31 70 386 3232",
    "sg:postcode":"2271 CW",
    "sg:province":"Zuid-Holland",
    "wof:name":"Hohage",
    "wof:placetype":"venue"
},
  "geometry": {"coordinates":[4.365697,52.067043],"type":"Point"}
}