{
  "type": "Feature",
  "properties": {
    "addr:full":"J F Kennedyln 17 Valkenswaard North Brabant 5555 XC",
    "addr:housenumber":"17",
    "addr:postcode":"5555 xc",
    "addr:street":"J F Kennedyln",
    "iso:country":"NL",
    "sg:address":"J F Kennedyln 17",
    "sg:city":"Valkenswaard",
    "sg:orig_category":"Ovenbouw",
    "sg:phone":"+31 40 208 2020",
    "sg:postcode":"5555 XC",
    "sg:province":"North Brabant",
    "sg:website":"http://www.infrabaker.com",
    "wof:name":"Infrabaker Int",
    "wof:placetype":"venue"
},
  "geometry": {"coordinates":[5.4589700699,51.3505096436],"type":"Point"}
}