{
  "type": "Feature",
  "properties": {
    "iso:country":"NL",
    "sg:address":"Bronckhorststr 27A",
    "sg:city":"Noordwyk Zh",
    "sg:orig_category":"Peuterspeelzalen",
    "sg:phone":"+31 71 361 0183",
    "sg:postcode":"2201 KV",
    "sg:province":"Zuid-Holland",
    "wof:name":"Pippeloentje",
    "wof:placetype":"venue"
},
  "geometry": {"coordinates":[4.444231,52.234737],"type":"Point"}
}