{
  "type": "Feature",
  "properties": {
    "addr:full":"Arie De Jongstraat 20 'S Gravenhage Zuid-Holland 2553 RK",
    "addr:housenumber":"20",
    "addr:postcode":"2553 rk",
    "addr:street":"Arie De Jongstraat;' S",
    "iso:country":"NL",
    "sg:address":"Arie De Jongstraat 20",
    "sg:city":"'S Gravenhage",
    "sg:orig_category":"Goederenvervoer Over De Weg",
    "sg:phone":"+31 70 440 0140",
    "sg:postcode":"2553 RK",
    "sg:province":"Zuid-Holland",
    "wof:name":"Hvg",
    "wof:placetype":"venue"
},
  "geometry": {"coordinates":[4.214504,52.04451],"type":"Point"}
}