{
  "type": "Feature",
  "properties": {
    "addr:full":"Meelstraat 48 Tilburg Noord-Brabant 5025 KN",
    "addr:housenumber":"48",
    "addr:postcode":"5025 kn",
    "addr:street":"Meelstraat",
    "iso:country":"NL",
    "sg:address":"Meelstraat 48",
    "sg:city":"Tilburg",
    "sg:orig_category":"Airconditioning And Ventilatie",
    "sg:phone":"+31 13 542 4109",
    "sg:postcode":"5025 KN",
    "sg:province":"Noord-Brabant",
    "wof:name":"Verwarmingsmaatschappij Thermos Bv",
    "wof:placetype":"venue"
},
  "geometry": {"coordinates":[5.071219,51.552643],"type":"Point"}
}