{
  "type": "Feature",
  "properties": {
    "iso:country":"NL",
    "sg:address":"Pettendk 10",
    "sg:city":"Maasdyk",
    "sg:orig_category":"Bloemen En Planten - Groothandel",
    "sg:phone":"+31 6 20438588",
    "sg:postcode":"2676 BK",
    "sg:province":"Zuid-Holland",
    "wof:name":"Belnaver, Firma",
    "wof:placetype":"venue"
},
  "geometry": {"coordinates":[4.21651,51.95908],"type":"Point"}
}