{
  "type": "Feature",
  "properties": {
    "addr:full":"Deilsewg 7 Geldermalsen Gelderland 4191 NX",
    "addr:housenumber":"7",
    "addr:postcode":"4191 nx",
    "addr:street":"Deilsewg;Gelderland",
    "iso:country":"NL",
    "sg:address":"Deilsewg 7",
    "sg:city":"Geldermalsen",
    "sg:orig_category":"Facilitaire Dienstverlening",
    "sg:phone":"+31 345 578 600",
    "sg:postcode":"4191 NX",
    "sg:province":"Gelderland",
    "wof:name":"Inova Bv",
    "wof:placetype":"venue"
},
  "geometry": {"coordinates":[5.269491,51.881721],"type":"Point"}
}