{
  "type": "Feature",
  "properties": {
    "addr:full":"Mozartstr 74 Zutphen Gelderland 7204 PG",
    "addr:housenumber":"74",
    "addr:postcode":"7204",
    "addr:street":"Mozartstr;Gelderland;Pg",
    "iso:country":"NL",
    "sg:address":"Mozartstr 74",
    "sg:city":"Zutphen",
    "sg:orig_category":"Verhuur",
    "sg:phone":"+31 575 571 133",
    "sg:postcode":"7204 PG",
    "sg:province":"Gelderland",
    "wof:name":"Sport-Spel Uitleen",
    "wof:placetype":"venue"
},
  "geometry": {"coordinates":[6.200796,52.132469],"type":"Point"}
}