{
  "type": "Feature",
  "properties": {
    "addr:full":"Wipperspark 17 Maassluis South Holland 3141 RA",
    "addr:housenumber":"17",
    "addr:postcode":"3141 ra",
    "addr:street":"Wipperspark",
    "iso:country":"NL",
    "sg:address":"Wipperspark 17",
    "sg:city":"Maassluis",
    "sg:orig_category":"Diverse Opleidingen And Onderwijs",
    "sg:phone":"+31 10 591 5563",
    "sg:postcode":"3141 RA",
    "sg:province":"South Holland",
    "wof:name":"J Biesbroek-De Haas",
    "wof:placetype":"venue"
},
  "geometry": {"coordinates":[4.265646,51.923424],"type":"Point"}
}