{
  "type": "Feature",
  "properties": {
    "addr:full":"De Jol 30 Baarn Utrecht 3742 GL",
    "addr:housenumber":"30",
    "addr:postcode":"3742 gl",
    "addr:street":"De Jol",
    "iso:country":"NL",
    "sg:address":"De Jol 30",
    "sg:city":"Baarn",
    "sg:orig_category":"Adviesbureaus Bedrijfsorganisatie",
    "sg:phone":"+31 35 541 3669",
    "sg:postcode":"3742 GL",
    "sg:province":"Utrecht",
    "wof:name":"Ed Interim",
    "wof:placetype":"venue"
},
  "geometry": {"coordinates":[5.303927,52.204262],"type":"Point"}
}