{
  "type": "Feature",
  "properties": {
    "addr:full":"Europawg 148 Nieuw Schoonebeek Drenthe 7766 AP",
    "addr:housenumber":"148",
    "addr:postcode":"7766 ap",
    "addr:street":"Nieuw Schoonebeek",
    "iso:country":"NL",
    "sg:address":"Europawg 148",
    "sg:city":"Nieuw Schoonebeek",
    "sg:orig_category":"Schilders",
    "sg:phone":"+31 524 541 467",
    "sg:postcode":"7766 AP",
    "sg:province":"Drenthe",
    "wof:name":"Conen, J B",
    "wof:placetype":"venue"
},
  "geometry": {"coordinates":[6.987514,52.646065],"type":"Point"}
}