{
  "type": "Feature",
  "properties": {
    "addr:full":"Ulvenhoutseln 93 Breda Noord-Brabant 4834 MD",
    "addr:housenumber":"93",
    "addr:postcode":"4834",
    "addr:street":"Ulvenhoutseln",
    "iso:country":"NL",
    "sg:address":"Ulvenhoutseln 93",
    "sg:city":"Breda",
    "sg:orig_category":"Ongediertebestrijding En Ontsmetting",
    "sg:phone":"+31 76 564 0893",
    "sg:postcode":"4834 MD",
    "sg:province":"Noord-Brabant",
    "wof:name":"Gef Holland",
    "wof:placetype":"venue"
},
  "geometry": {"coordinates":[4.792598,51.560535],"type":"Point"}
}