{
  "type": "Feature",
  "properties": {
    "addr:full":"Nieuweweg 101 Tiel Gelderland 4001 NS",
    "addr:housenumber":"101",
    "addr:postcode":"4001 ns",
    "addr:street":"Nieuweweg;Gelderland",
    "iso:country":"NL",
    "sg:address":"Nieuweweg 101",
    "sg:city":"Tiel",
    "sg:orig_category":"Beursorganisaties And Standbouw",
    "sg:phone":"+31 344 618 077",
    "sg:postcode":"4001 NS",
    "sg:province":"Gelderland",
    "wof:name":"Presentbouw",
    "wof:placetype":"venue"
},
  "geometry": {"coordinates":[5.430696,51.888096],"type":"Point"}
}