{
  "type": "Feature",
  "properties": {
    "addr:full":"Vredewoldplnts 4 Leek Provincie Drenthe 9351 BN",
    "addr:housenumber":"4",
    "addr:postcode":"9351 bn",
    "addr:street":"Vredewoldplnts;Provincie Drenthe",
    "iso:country":"NL",
    "sg:address":"Vredewoldplnts 4",
    "sg:city":"Leek",
    "sg:orig_category":"Bejaarden - Verzorgingstehuizen",
    "sg:phone":"+31 594 510 358",
    "sg:postcode":"9351 BN",
    "sg:province":"Provincie Drenthe",
    "wof:name":"Woonhaven Leek",
    "wof:placetype":"venue"
},
  "geometry": {"coordinates":[6.392695,53.162521],"type":"Point"}
}