{
  "type": "Feature",
  "properties": {
    "iso:country":"NL",
    "sg:address":"Ranonkelstr 3",
    "sg:city":"Swifterbant",
    "sg:orig_category":"Vertaalbureaus",
    "sg:phone":"+31 321 324 494",
    "sg:postcode":"8255 BW",
    "sg:province":"Flevoland",
    "wof:name":"Beier, A",
    "wof:placetype":"venue"
},
  "geometry": {"coordinates":[5.640129,52.566311],"type":"Point"}
}