{
  "type": "Feature",
  "properties": {
    "addr:full":"Ambachtsweg 3 Groesbeek Gelderland 6562 AZ",
    "addr:housenumber":"3",
    "addr:postcode":"6562",
    "addr:street":"Ambachtsweg;Gelderland",
    "iso:country":"NL",
    "sg:address":"Ambachtsweg 3",
    "sg:city":"Groesbeek",
    "sg:orig_category":"Meubelzaken, Woning- And Keukeninrichting",
    "sg:phone":"+31 24 397 2518",
    "sg:postcode":"6562 AZ",
    "sg:province":"Gelderland",
    "wof:name":"Wennekers Wonen Bv",
    "wof:placetype":"venue"
},
  "geometry": {"coordinates":[5.944823,51.775738],"type":"Point"}
}