{
  "type": "Feature",
  "properties": {
    "addr:full":"Dalmsholterweg 2 Giethmen Overijssel 8147 RB",
    "addr:housenumber":"2",
    "addr:postcode":"8147 rb",
    "addr:street":"Dalmsholterweg",
    "iso:country":"NL",
    "sg:address":"Dalmsholterweg 2",
    "sg:city":"Giethmen",
    "sg:orig_category":"Kampeerterreinen",
    "sg:phone":"+31 529 451 671",
    "sg:postcode":"8147 RB",
    "sg:province":"Overijssel",
    "wof:name":"Camping T Voshuus",
    "wof:placetype":"venue"
},
  "geometry": {"coordinates":[6.4085211754,52.4887504578],"type":"Point"}
}