{
  "type": "Feature",
  "properties": {
    "addr:full":"Schelmaatstr 19 Oldenzaal NL.08 7575 BC",
    "addr:housenumber":"19;nl.08",
    "addr:postcode":"7575 bc",
    "addr:street":"Schelmaatstr",
    "iso:country":"NL",
    "sg:address":"Schelmaatstr 19",
    "sg:city":"Oldenzaal",
    "sg:orig_category":"Hijswerktuigen",
    "sg:phone":"+31 541 532 045",
    "sg:postcode":"7575 BC",
    "sg:province":"NL.08",
    "wof:name":"Kwint Bv",
    "wof:placetype":"venue"
},
  "geometry": {"coordinates":[6.927172,52.297821],"type":"Point"}
}