{
  "type": "Feature",
  "properties": {
    "iso:country":"NL",
    "sg:address":"Kamphuizenln 29",
    "sg:city":"Arnhem",
    "sg:orig_category":"Schilders",
    "sg:phone":"+31 26 361 7784",
    "sg:postcode":"6825 EA",
    "sg:province":"Gelderland",
    "wof:name":"Bailly",
    "wof:placetype":"venue"
},
  "geometry": {"coordinates":[5.965469,51.982082],"type":"Point"}
}