{
  "type": "Feature",
  "properties": {
    "addr:full":"Eilandseweg 32 Nederhorst Den Berg Noord-Holland 1394 JG",
    "addr:housenumber":"32",
    "addr:postcode":"1394 jg",
    "addr:street":"Eilandseweg",
    "iso:country":"NL",
    "sg:address":"Eilandseweg 32",
    "sg:city":"Nederhorst Den Berg",
    "sg:orig_category":"Kampeerterreinen",
    "sg:phone":"+31 294 251 692",
    "sg:postcode":"1394 JG",
    "sg:province":"Noord-Holland",
    "wof:name":"Euroase Nederhorst Den Berg",
    "wof:placetype":"venue"
},
  "geometry": {"coordinates":[5.0331811905,52.2549629211],"type":"Point"}
}