{
  "type": "Feature",
  "properties": {
    "addr:full":"M Stolpstr 12 Schagerbrug Noord-Holland 1751 CZ",
    "addr:housenumber":"12;1751",
    "iso:country":"NL",
    "sg:address":"M Stolpstr 12",
    "sg:city":"Schagerbrug",
    "sg:orig_category":"Onderhoudswerken",
    "sg:phone":"+31 224 218 486",
    "sg:postcode":"1751 CZ",
    "sg:province":"Noord-Holland",
    "wof:name":"Gielens, P",
    "wof:placetype":"venue"
},
  "geometry": {"coordinates":[4.758934,52.801323],"type":"Point"}
}