{
  "type": "Feature",
  "properties": {
    "iso:country":"NL",
    "sg:address":"Ijsselmeer 36",
    "sg:city":"Zwijndrecht",
    "sg:orig_category":"Overheidsdiensten",
    "sg:phone":"+31 78 620 6820",
    "sg:postcode":"3332 EX",
    "sg:province":"South Holland",
    "wof:name":"Gak",
    "wof:placetype":"venue"
},
  "geometry": {"coordinates":[4.6488099098,51.8219490051],"type":"Point"}
}