{
  "type": "Feature",
  "properties": {
    "addr:full":"Broekwegzijde 123 Zoetermeer South Holland 2725 PD",
    "addr:housenumber":"123",
    "addr:postcode":"2725 pd",
    "addr:street":"Broekwegzijde",
    "iso:country":"NL",
    "sg:address":"Broekwegzijde 123",
    "sg:city":"Zoetermeer",
    "sg:classifiers":[
        {
            "category":"Communications",
            "subcategory":"Television Station",
            "type":"Services"
        }
    ],
    "sg:phone":"+31 79 342 8269",
    "sg:postcode":"2725 PD",
    "sg:province":"South Holland",
    "sg:tags":[
        "video",
        "audio",
        "verhuur"
    ],
    "wof:name":"Gezinsvideotheek De Filmfreak",
    "wof:placetype":"venue"
},
  "geometry": {"coordinates":[4.493894,52.071671],"type":"Point"}
}