{
  "type": "Feature",
  "properties": {
    "addr:full":"Wilhelminalaan 10 Maasbracht Limburg 6051 BJ",
    "addr:housenumber":"10",
    "addr:postcode":"6051 bj",
    "addr:street":"Wilhelminalaan",
    "iso:country":"NL",
    "sg:address":"Wilhelminalaan 10",
    "sg:city":"Maasbracht",
    "sg:orig_category":"Wapens En Munitie",
    "sg:phone":"+31 475 466 869",
    "sg:postcode":"6051 BJ",
    "sg:province":"Limburg",
    "sg:website":"http://www.ht-antiqueguns.com",
    "wof:name":"H & T Vof",
    "wof:placetype":"venue"
},
  "geometry": {"coordinates":[5.8871598244,51.146446228],"type":"Point"}
}