{
  "type": "Feature",
  "properties": {
    "iso:country":"NL",
    "sg:address":"Postbus 20",
    "sg:city":"Almkerk",
    "sg:orig_category":"Scholen Voor Basisonderwijs",
    "sg:phone":"+31 183 401 625",
    "sg:postcode":"4286 ZG",
    "sg:province":"Noord-Brabant",
    "wof:name":"Halm Geref, De",
    "wof:placetype":"venue"
},
  "geometry": {"coordinates":[4.9645,51.771969],"type":"Point"}
}