{
  "type": "Feature",
  "properties": {
    "addr:full":"Beneluxlaan 35 Beverwijk North Holland 1946 WH",
    "addr:housenumber":"35",
    "addr:postcode":"1946 wh",
    "addr:street":"Beneluxlaan",
    "iso:country":"NL",
    "sg:address":"Beneluxlaan 35",
    "sg:city":"Beverwijk",
    "sg:orig_category":"Metaalbekleding And -Behandeling",
    "sg:phone":"+31 251 247 312",
    "sg:postcode":"1946 WH",
    "sg:province":"North Holland",
    "wof:name":"Wijker Konstruktie Maatschappij Bv",
    "wof:placetype":"venue"
},
  "geometry": {"coordinates":[4.671272,52.492348],"type":"Point"}
}