{
  "type": "Feature",
  "properties": {
    "addr:full":"Vechtstraat 1 Ridderkerk Zuid-Holland 2987 CX",
    "addr:housenumber":"1",
    "addr:postcode":"2987 cx",
    "addr:street":"Vechtstraat",
    "iso:country":"NL",
    "sg:address":"Vechtstraat 1",
    "sg:city":"Ridderkerk",
    "sg:orig_category":"Zuivelproducten",
    "sg:phone":"+31 180 410 230",
    "sg:postcode":"2987 CX",
    "sg:province":"Zuid-Holland",
    "wof:name":"Waayer De Kaasboer Bv",
    "wof:placetype":"venue"
},
  "geometry": {"coordinates":[4.579915,51.892574],"type":"Point"}
}