{
  "type": "Feature",
  "properties": {
    "addr:full":"Zuiderweg 32 Wijdewormer Noord-Holland 1456 ND",
    "addr:housenumber":"32",
    "addr:postcode":"1456 nd",
    "addr:street":"Zuiderweg",
    "iso:country":"NL",
    "sg:address":"Zuiderweg 32",
    "sg:city":"Wijdewormer",
    "sg:orig_category":"Wegen And Sportterreinen",
    "sg:phone":"+31 299 470 176",
    "sg:postcode":"1456 ND",
    "sg:province":"Noord-Holland",
    "wof:name":"Alex E. De Kroon Bv",
    "wof:placetype":"venue"
},
  "geometry": {"coordinates":[4.9017529488,52.489025116],"type":"Point"}
}