{
  "type": "Feature",
  "properties": {
    "addr:full":"Oude Dijk 1 Schagen Noord-Holland 1742 NH",
    "addr:housenumber":"1",
    "addr:postcode":"1742 nh",
    "addr:street":"Oude Dijk",
    "iso:country":"NL",
    "sg:address":"Oude Dijk 1",
    "sg:city":"Schagen",
    "sg:orig_category":"Kampeerterreinen",
    "sg:phone":"+31 224 212 523",
    "sg:postcode":"1742 NH",
    "sg:province":"Noord-Holland",
    "wof:name":"Camping Burghorn",
    "wof:placetype":"venue"
},
  "geometry": {"coordinates":[4.7715039253,52.7880973816],"type":"Point"}
}