{
  "type": "Feature",
  "properties": {
    "addr:full":"Koningswg 39 Akersloot Noord-Holland 1921 AS",
    "addr:housenumber":"39",
    "addr:postcode":"1921 as",
    "addr:street":"Koningswg",
    "iso:country":"NL",
    "sg:address":"Koningswg 39",
    "sg:city":"Akersloot",
    "sg:orig_category":"Montagebedrijven",
    "sg:phone":"+31 251 315 896",
    "sg:postcode":"1921 AS",
    "sg:province":"Noord-Holland",
    "wof:name":"Aeta",
    "wof:placetype":"venue"
},
  "geometry": {"coordinates":[4.732397,52.556145],"type":"Point"}
}