{
  "type": "Feature",
  "properties": {
    "iso:country":"NL",
    "sg:address":"Weldam 9",
    "sg:city":"Amsterdam",
    "sg:orig_category":"Psychotherapeuten",
    "sg:phone":"+31 20 471 3630",
    "sg:postcode":"1081 HN",
    "sg:province":"Noord-Holland",
    "wof:name":"Verheugt-Pleiter, J E",
    "wof:placetype":"venue"
},
  "geometry": {"coordinates":[4.860946,52.3311],"type":"Point"}
}