{
  "type": "Feature",
  "properties": {
    "iso:country":"NL",
    "sg:address":"Tolstr 101-1",
    "sg:city":"Amsterdam",
    "sg:orig_category":"Filmstudio'S En -Productie",
    "sg:phone":"+31 20 471 1102",
    "sg:postcode":"1074 VG",
    "sg:province":"Noord-Holland",
    "sg:website":"http://www.persuader.nl",
    "wof:name":"Persuader Films",
    "wof:placetype":"venue"
},
  "geometry": {"coordinates":[4.90359,52.352417],"type":"Point"}
}