{
  "type": "Feature",
  "properties": {
    "addr:full":"Vissenstraat 28 Apeldoorn Gelderland 7324 AL",
    "addr:housenumber":"28",
    "addr:postcode":"7324",
    "addr:street":"Vissenstraat;Gelderland",
    "iso:country":"NL",
    "sg:address":"Vissenstraat 28",
    "sg:city":"Apeldoorn",
    "sg:classifiers":[
        {
            "category":"Parking",
            "subcategory":"Lot",
            "type":"Transportation"
        }
    ],
    "sg:phone":"+31 55 323 2870",
    "sg:postcode":"7324 AL",
    "sg:province":"Gelderland",
    "sg:tags":[
        "fab",
        "metalen",
        "tank"
    ],
    "wof:name":"Avk Rewag Bv",
    "wof:placetype":"venue"
},
  "geometry": {"coordinates":[5.983255,52.240459],"type":"Point"}
}