{
  "type": "Feature",
  "properties": {
    "iso:country":"NL",
    "sg:address":"Utrechtseweg 15",
    "sg:city":"Zeist",
    "sg:orig_category":"Elektronische Bedrijfsinstallaties",
    "sg:phone":"+31 30 699 7699",
    "sg:postcode":"3704 HA",
    "sg:province":"Utrecht",
    "wof:name":"Sensormatic Bv",
    "wof:placetype":"venue"
},
  "geometry": {"coordinates":[5.213836,52.097263],"type":"Point"}
}