{
  "type": "Feature",
  "properties": {
    "addr:full":"Van Lawick Van Pabststr 109 Arnhem Gelderland 6814 HC",
    "addr:housenumber":"109",
    "addr:postcode":"6814 hc",
    "addr:street":"Van Lawick Van Pabststr",
    "iso:country":"NL",
    "sg:address":"Van Lawick Van Pabststr 109",
    "sg:city":"Arnhem",
    "sg:orig_category":"Banken And Kredietinstellingen",
    "sg:phone":"+31 26 446 0300",
    "sg:postcode":"6814 HC",
    "sg:province":"Gelderland",
    "wof:name":"Postkantoor",
    "wof:placetype":"venue"
},
  "geometry": {"coordinates":[5.893604,51.989769],"type":"Point"}
}