{
  "type": "Feature",
  "properties": {
    "iso:country":"NL",
    "sg:address":"Korte Westerstraat 7",
    "sg:city":"Enkhuizen",
    "sg:classifiers":[
        {
            "category":"Education",
            "subcategory":"Preschool",
            "type":"Public Place"
        }
    ],
    "sg:phone":"+31 228 312 118",
    "sg:postcode":"1601 RH",
    "sg:province":"North Holland",
    "sg:tags":[
        "kleuteronderwijs",
        "basis-"
    ],
    "wof:name":"De Tweemaster",
    "wof:placetype":"venue"
},
  "geometry": {"coordinates":[5.28366,52.703178],"type":"Point"}
}