{
  "type": "Feature",
  "properties": {
    "addr:full":"Poeldykstr 10 Amsterdam North Holland 1059 VM",
    "addr:housenumber":"10",
    "addr:postcode":"1059 vm",
    "addr:street":"Poeldykstr",
    "iso:country":"NL",
    "sg:address":"Poeldykstr 10",
    "sg:city":"Amsterdam",
    "sg:orig_category":"Woningbouw- Verenigingen En -Stichtingen",
    "sg:phone":"+31 20 511 8000",
    "sg:postcode":"1059 VM",
    "sg:province":"North Holland",
    "sg:website":"http://www.awv.nl",
    "wof:name":"Algemene Woningbouw Vereniging",
    "wof:placetype":"venue"
},
  "geometry": {"coordinates":[4.8437161446,52.3498840332],"type":"Point"}
}