{
  "type": "Feature",
  "properties": {
    "addr:full":"Spoorstr 5 Den Helder North Holland 1781 JB",
    "addr:housenumber":"5",
    "addr:postcode":"1781 jb",
    "addr:street":"Spoorstr",
    "iso:country":"NL",
    "sg:address":"Spoorstr 5",
    "sg:city":"Den Helder",
    "sg:orig_category":"Banket",
    "sg:phone":"+31 223 680 580",
    "sg:postcode":"1781 JB",
    "sg:province":"North Holland",
    "wof:name":"Multi-Vlaai",
    "wof:placetype":"venue"
},
  "geometry": {"coordinates":[4.761617,52.959049],"type":"Point"}
}