{
  "type": "Feature",
  "properties": {
    "iso:country":"NL",
    "sg:address":"Spoorstr 5",
    "sg:city":"Den Helder",
    "sg:orig_category":"Banket",
    "sg:phone":"+31 223 680 580",
    "sg:postcode":"1781 JB",
    "sg:province":"North Holland",
    "wof:name":"Multi-Vlaai",
    "wof:placetype":"venue"
},
  "geometry": {"coordinates":[4.761617,52.959049],"type":"Point"}
}