{
  "type": "Feature",
  "properties": {
    "addr:full":"De La Reylaan 40 Gouda Zuid-Holland 2806 DB",
    "addr:housenumber":"40",
    "addr:postcode":"2806 db",
    "addr:street":"De La Reylaan",
    "iso:country":"NL",
    "sg:address":"De La Reylaan 40",
    "sg:city":"Gouda",
    "sg:orig_category":"Overheidsdiensten",
    "sg:phone":"+31 182 515 082",
    "sg:postcode":"2806 DB",
    "sg:province":"Zuid-Holland",
    "wof:name":"T Spant",
    "wof:placetype":"venue"
},
  "geometry": {"coordinates":[4.7220711708,52.009262085],"type":"Point"}
}