{
  "type": "Feature",
  "properties": {
    "addr:full":"Ywg 978-A Hoofddorp Noord-Holland 2131 LW",
    "addr:housenumber":"978-a",
    "addr:postcode":"2131 lw",
    "iso:country":"NL",
    "sg:address":"Ywg 978-A",
    "sg:city":"Hoofddorp",
    "sg:orig_category":"Meubelmakerijen",
    "sg:phone":"+31 23 562 4203",
    "sg:postcode":"2131 LW",
    "sg:province":"Noord-Holland",
    "wof:name":"Roelofs",
    "wof:placetype":"venue"
},
  "geometry": {"coordinates":[4.70066,52.322971],"type":"Point"}
}