{
  "type": "Feature",
  "properties": {
    "addr:full":"Brueghelstr 287-289 S Gravenhage South Holland 2525 RG",
    "addr:housenumber":"287-289",
    "addr:postcode":"2525 rg",
    "addr:street":"S Gravenhage",
    "iso:country":"NL",
    "sg:address":"Brueghelstr 287-289",
    "sg:city":"S Gravenhage",
    "sg:orig_category":"Verenigingen En Stichtingen",
    "sg:phone":"+31 70 384 1334",
    "sg:postcode":"2525 RG",
    "sg:province":"South Holland",
    "wof:name":"Haags Islamitisch Platform Ship, Sticht",
    "wof:placetype":"venue"
},
  "geometry": {"coordinates":[4.30248,52.062462],"type":"Point"}
}