{
  "type": "Feature",
  "properties": {
    "addr:full":"De Meteoor 15 Dronten Flevoland 8251 AK",
    "addr:housenumber":"15",
    "addr:postcode":"8251 ak",
    "addr:street":"De Meteoor;Flevoland",
    "iso:country":"NL",
    "sg:address":"De Meteoor 15",
    "sg:city":"Dronten",
    "sg:orig_category":"Waterbehandeling En Waterzuiverings- Systemen",
    "sg:phone":"+31 321 316 161",
    "sg:postcode":"8251 AK",
    "sg:province":"Flevoland",
    "wof:name":"Lutra",
    "wof:placetype":"venue"
},
  "geometry": {"coordinates":[5.7113108635,52.5202713013],"type":"Point"}
}