{
  "type": "Feature",
  "properties": {
    "iso:country":"NL",
    "sg:address":"Kerkstraat 44",
    "sg:city":"Noordwijkerhout",
    "sg:orig_category":"Bloemen And Planten Gh",
    "sg:phone":"+31 252 372 280",
    "sg:postcode":"2211 RK",
    "sg:province":"Zuid-Holland",
    "wof:name":"J.L. Heemskerk",
    "wof:placetype":"venue"
},
  "geometry": {"coordinates":[4.490492,52.255428],"type":"Point"}
}