{
  "type": "Feature",
  "properties": {
    "addr:full":"Vd Loostr 3 Veen Noord-Brabant 4264 RP",
    "addr:housenumber":"3",
    "addr:postcode":"4264 rp",
    "iso:country":"NL",
    "sg:address":"Vd Loostr 3",
    "sg:city":"Veen",
    "sg:orig_category":"Artsen - Huisartsen",
    "sg:phone":"+31 416 691 250",
    "sg:postcode":"4264 RP",
    "sg:province":"Noord-Brabant",
    "wof:name":"Weerd En J M Van Der Weerd-Van Der Leun, B G J Van Der",
    "wof:placetype":"venue"
},
  "geometry": {"coordinates":[6.65772,46.56155],"type":"Point"}
}