{
  "type": "Feature",
  "properties": {
    "addr:full":"Ambachtsweg 27 Maarsbergen Utrecht 3953 BZ",
    "addr:housenumber":"27",
    "addr:postcode":"3953 bz",
    "addr:street":"Ambachtsweg",
    "iso:country":"NL",
    "sg:address":"Ambachtsweg 27",
    "sg:city":"Maarsbergen",
    "sg:orig_category":"Gespecialiseerde Bouw",
    "sg:phone":"+31 343 431 236",
    "sg:postcode":"3953 BZ",
    "sg:province":"Utrecht",
    "wof:name":"Marver Plaatwerk Bv",
    "wof:placetype":"venue"
},
  "geometry": {"coordinates":[5.413264,52.054462],"type":"Point"}
}