{
  "type": "Feature",
  "properties": {
    "addr:full":"Biestsestraat 94 Biest Houtakker Noord-Brabant 5084 HV",
    "addr:housenumber":"94",
    "addr:postcode":"5084 hv",
    "addr:street":"Biestsestraat",
    "iso:country":"NL",
    "sg:address":"Biestsestraat 94",
    "sg:city":"Biest Houtakker",
    "sg:orig_category":"Verhuur Gereedschapsmachines And Gereedschappen",
    "sg:phone":"+31 13 505 1666",
    "sg:postcode":"5084 HV",
    "sg:province":"Noord-Brabant",
    "wof:name":"J Van Dijck",
    "wof:placetype":"venue"
},
  "geometry": {"coordinates":[5.152469,51.511833],"type":"Point"}
}