{
  "type": "Feature",
  "properties": {
    "addr:full":"Weerdingerstraat 254B Emmen Drenthe 7811 CM",
    "addr:housenumber":"254b",
    "addr:postcode":"7811 cm",
    "addr:street":"Weerdingerstraat",
    "iso:country":"NL",
    "sg:address":"Weerdingerstraat 254B",
    "sg:city":"Emmen",
    "sg:classifiers":[
        {
            "category":"Professional",
            "subcategory":"Accounting & Tax Preparation",
            "type":"Services"
        }
    ],
    "sg:phone":"+31 591 686 226",
    "sg:postcode":"7811 CM",
    "sg:province":"Drenthe",
    "sg:tags":[
        "accountant"
    ],
    "wof:name":"Accountants Adviesgroep Nno",
    "wof:placetype":"venue"
},
  "geometry": {"coordinates":[6.893681,52.789227],"type":"Point"}
}