{
  "type": "Feature",
  "properties": {
    "addr:full":"Ringdijk 4 Helmond North Brabant 5705 CT",
    "addr:housenumber":"4",
    "addr:postcode":"5705 ct",
    "addr:street":"Ringdijk",
    "iso:country":"NL",
    "sg:address":"Ringdijk 4",
    "sg:city":"Helmond",
    "sg:orig_category":"Metaalbekleding And -Behandeling",
    "sg:phone":"+31 492 524 390",
    "sg:postcode":"5705 CT",
    "sg:province":"North Brabant",
    "wof:name":"Straal- En Conserveringsbedr Meulendijks Helmond B",
    "wof:placetype":"venue"
},
  "geometry": {"coordinates":[5.658284,51.482239],"type":"Point"}
}