{
  "type": "Feature",
  "properties": {
    "addr:full":"Beemdstr 15 Eindhoven Noord-Brabant 5653 MA",
    "addr:housenumber":"15",
    "addr:postcode":"5653 ma",
    "addr:street":"Beemdstr",
    "iso:country":"NL",
    "sg:address":"Beemdstr 15",
    "sg:city":"Eindhoven",
    "sg:orig_category":"Kantoor- En Bedrijfsmeubelen",
    "sg:phone":"+31 40 259 2630",
    "sg:postcode":"5653 MA",
    "sg:province":"Noord-Brabant",
    "sg:website":"http://www.staalinterieur.nl",
    "wof:name":"Staalinterieur Kantoorinrichting",
    "wof:placetype":"venue"
},
  "geometry": {"coordinates":[5.4493598938,51.4294776917],"type":"Point"}
}