{
  "type": "Feature",
  "properties": {
    "addr:full":"Oostergouw 1 Zwaag North Holland 1689 AH",
    "addr:housenumber":"1",
    "addr:postcode":"1689 ah",
    "addr:street":"Oostergouw;Holland",
    "iso:country":"NL",
    "sg:address":"Oostergouw 1",
    "sg:city":"Zwaag",
    "sg:orig_category":"Goederenvervoer Over De Weg",
    "sg:phone":"+31 229 244 164",
    "sg:postcode":"1689 AH",
    "sg:province":"North Holland",
    "wof:name":"D.L. Transport- En Handelsbemiddeling Bv",
    "wof:placetype":"venue"
},
  "geometry": {"coordinates":[5.060298,52.671837],"type":"Point"}
}