{
  "type": "Feature",
  "properties": {
    "addr:full":"Trompenburg 21 Amstelveen Noord-Holland 1181 NM",
    "addr:housenumber":"21",
    "addr:postcode":"1181",
    "addr:street":"Trompenburg",
    "iso:country":"NL",
    "sg:address":"Trompenburg 21",
    "sg:city":"Amstelveen",
    "sg:orig_category":"Platenmaatschappijen",
    "sg:phone":"+31 20 645 5499",
    "sg:postcode":"1181 NM",
    "sg:province":"Noord-Holland",
    "wof:name":"Hike Music",
    "wof:placetype":"venue"
},
  "geometry": {"coordinates":[4.861824,52.312569],"type":"Point"}
}