{
  "type": "Feature",
  "properties": {
    "addr:full":"Persephonestr 5-01 Tilburg North Brabant 5047 TT",
    "addr:housenumber":"5-01",
    "addr:postcode":"5047 tt",
    "iso:country":"NL",
    "sg:address":"Persephonestr 5-01",
    "sg:city":"Tilburg",
    "sg:orig_category":"Bloemisterijartikelen - Fabrieken En Groothandel",
    "sg:phone":"+31 13 580 2756",
    "sg:postcode":"5047 TT",
    "sg:province":"North Brabant",
    "sg:website":"http://www.businessroom.nl",
    "wof:name":"Taparte",
    "wof:placetype":"venue"
},
  "geometry": {"coordinates":[5.013624,51.590462],"type":"Point"}
}