{
  "type": "Feature",
  "properties": {
    "addr:full":"Enkwg 55 Eerbeek Gelderland 6961 GX",
    "addr:housenumber":"55",
    "addr:postcode":"6961 gx",
    "addr:street":"Enkwg;Gelderland",
    "iso:country":"NL",
    "sg:address":"Enkwg 55",
    "sg:city":"Eerbeek",
    "sg:orig_category":"Metaalbewerking",
    "sg:phone":"+31 313 651 621",
    "sg:postcode":"6961 GX",
    "sg:province":"Gelderland",
    "wof:name":"Koenders Bv",
    "wof:placetype":"venue"
},
  "geometry": {"coordinates":[6.059702,52.097664],"type":"Point"}
}