{
  "type": "Feature",
  "properties": {
    "addr:full":"Zilverstr 56 S Gravenhage Zuid-Holland 2544 EL",
    "addr:housenumber":"56;gravenhage;2544",
    "addr:postcode":"el",
    "addr:street":"Zilverstr;S",
    "iso:country":"NL",
    "sg:address":"Zilverstr 56",
    "sg:city":"S Gravenhage",
    "sg:orig_category":"Metaalbewerking",
    "sg:phone":"+31 70 366 4002",
    "sg:postcode":"2544 EL",
    "sg:province":"Zuid-Holland",
    "wof:name":"Lamboy, Constructiebedrijf J H De",
    "wof:placetype":"venue"
},
  "geometry": {"coordinates":[4.25157,52.039551],"type":"Point"}
}