{
  "type": "Feature",
  "properties": {
    "addr:full":"Helmondseweg 18 Deurne Noord-Brabant 5751 GD",
    "addr:housenumber":"18",
    "addr:postcode":"5751 gd",
    "addr:street":"Helmondseweg",
    "iso:country":"NL",
    "sg:address":"Helmondseweg 18",
    "sg:city":"Deurne",
    "sg:orig_category":"Autokeuringen",
    "sg:phone":"+31 493 312 493",
    "sg:postcode":"5751 GD",
    "sg:province":"Noord-Brabant",
    "wof:name":"Garage Van Ham Bv",
    "wof:placetype":"venue"
},
  "geometry": {"coordinates":[5.792157,51.463909],"type":"Point"}
}