{
  "type": "Feature",
  "properties": {
    "addr:full":"Koninginnestr 66 Breda Noord-Brabant 4818 HD",
    "addr:housenumber":"66",
    "addr:postcode":"4818 hd",
    "addr:street":"Koninginnestr",
    "iso:country":"NL",
    "sg:address":"Koninginnestr 66",
    "sg:city":"Breda",
    "sg:orig_category":"Grafisch Ontwerpers",
    "sg:phone":"+31 76 521 2699",
    "sg:postcode":"4818 HD",
    "sg:province":"Noord-Brabant",
    "sg:website":"http://www.kompagnie-k2.nl",
    "wof:name":"Kompagnie, K2",
    "wof:placetype":"venue"
},
  "geometry": {"coordinates":[4.782504,51.579285],"type":"Point"}
}