{
  "type": "Feature",
  "properties": {
    "iso:country":"NL",
    "sg:address":"Schoorveken 88",
    "sg:city":"Rijen",
    "sg:orig_category":"Levende Dieren Gh",
    "sg:phone":"+31 161 222 980",
    "sg:postcode":"5121 NM",
    "sg:province":"North Brabant",
    "wof:name":"P. Ackermans Veehandel",
    "wof:placetype":"venue"
},
  "geometry": {"coordinates":[4.925075,51.592884],"type":"Point"}
}