{
  "type": "Feature",
  "properties": {
    "addr:full":"Senecaln 24 Sittard Limburg 6135 HS",
    "addr:housenumber":"24",
    "addr:postcode":"6135 hs",
    "addr:street":"Senecaln",
    "iso:country":"NL",
    "sg:address":"Senecaln 24",
    "sg:city":"Sittard",
    "sg:orig_category":"Adviesbureaus",
    "sg:phone":"+31 46 451 1640",
    "sg:postcode":"6135 HS",
    "sg:province":"Limburg",
    "wof:name":"Theo Maassen",
    "wof:placetype":"venue"
},
  "geometry": {"coordinates":[5.85235,51.006458],"type":"Point"}
}