{
  "type": "Feature",
  "properties": {
    "addr:full":"Remmingwg 45 Almere NL. 1332 BD",
    "addr:housenumber":"45",
    "addr:postcode":"1332 bd",
    "addr:street":"Remmingwg;Nl.",
    "iso:country":"NL",
    "sg:address":"Remmingwg 45",
    "sg:city":"Almere",
    "sg:orig_category":"Betonwerken",
    "sg:phone":"+31 36 549 2700",
    "sg:postcode":"1332 BD",
    "sg:province":"NL.",
    "wof:name":"Hemubo Bv",
    "wof:placetype":"venue"
},
  "geometry": {"coordinates":[5.25876,52.408859],"type":"Point"}
}