{
  "type": "Feature",
  "properties": {
    "addr:full":"Touwbaan 11 Gorinchem South Holland 4205 AB",
    "addr:housenumber":"11",
    "addr:postcode":"4205 ab",
    "addr:street":"Touwbaan",
    "iso:country":"NL",
    "sg:address":"Touwbaan 11",
    "sg:city":"Gorinchem",
    "sg:orig_category":"Gezondheidszorg Geestelijke -",
    "sg:phone":"+31 183 654 100",
    "sg:postcode":"4205 AB",
    "sg:province":"South Holland",
    "wof:name":"Touwbaan Cicuit Volwassenen",
    "wof:placetype":"venue"
},
  "geometry": {"coordinates":[4.965843,51.83297],"type":"Point"}
}