{
  "type": "Feature",
  "properties": {
    "addr:full":"Oude Borg 16 Haren Gn Groningen 9753 BV",
    "addr:housenumber":"16",
    "addr:postcode":"9753 bv",
    "addr:street":"Oude Borg",
    "iso:country":"NL",
    "sg:address":"Oude Borg 16",
    "sg:city":"Haren Gn",
    "sg:orig_category":"Kinderkleding",
    "sg:phone":"+31 50 534 2972",
    "sg:postcode":"9753 BV",
    "sg:province":"Groningen",
    "wof:name":"Just 4 Kids",
    "wof:placetype":"venue"
},
  "geometry": {"coordinates":[6.627988,53.177197],"type":"Point"}
}