{
  "type": "Feature",
  "properties": {
    "addr:full":"Goudmijnstraat 3 Oss Virginia 5348 JH",
    "addr:housenumber":"3",
    "addr:postcode":"5348 jh",
    "addr:street":"Goudmijnstraat",
    "iso:country":"NL",
    "sg:address":"Goudmijnstraat 3",
    "sg:city":"Oss",
    "sg:orig_category":"Werving And Selectie Van Tijdelijk Personeel And Uitzendkantoren",
    "sg:phone":"+31 412 632 113",
    "sg:postcode":"5348 JH",
    "sg:province":"Virginia",
    "wof:name":"Manpower Uitzendorganisatie Bv",
    "wof:placetype":"venue"
},
  "geometry": {"coordinates":[-77.2352142334,38.3125991821],"type":"Point"}
}