{
  "type": "Feature",
  "properties": {
    "iso:country":"NL",
    "sg:address":"Hoofdveste 17",
    "sg:city":"Houten",
    "sg:orig_category":"Film-, Tv- And Videoproductie",
    "sg:phone":"+31 30 634 2064",
    "sg:postcode":"3992 DH",
    "sg:province":"Utrecht",
    "wof:name":"Pit Automatisering",
    "wof:placetype":"venue"
},
  "geometry": {"coordinates":[5.139925,52.026745],"type":"Point"}
}