{
  "type": "Feature",
  "properties": {
    "addr:full":"Ambacht 24 Oostzaan North Holland 1511 JZ",
    "addr:housenumber":"24",
    "addr:postcode":"1511 jz",
    "addr:street":"Ambacht",
    "iso:country":"NL",
    "sg:address":"Ambacht 24",
    "sg:city":"Oostzaan",
    "sg:orig_category":"Houtgroothandel",
    "sg:phone":"+31 75 684 1412",
    "sg:postcode":"1511 JZ",
    "sg:province":"North Holland",
    "wof:name":"Wiro Oostzaan Bv",
    "wof:placetype":"venue"
},
  "geometry": {"coordinates":[4.863243,52.433247],"type":"Point"}
}