{
  "type": "Feature",
  "properties": {
    "addr:full":"Europawg 21-23 Hardenberg NL.08 7772 BN",
    "addr:housenumber":"21-23;nl.08",
    "addr:postcode":"7772 bn",
    "iso:country":"NL",
    "sg:address":"Europawg 21-23",
    "sg:city":"Hardenberg",
    "sg:orig_category":"Bloemen En Planten",
    "sg:phone":"+31 523 271 400",
    "sg:postcode":"7772 BN",
    "sg:province":"NL.08",
    "wof:name":"Biggelaar Bloembinderij, J Van Den",
    "wof:placetype":"venue"
},
  "geometry": {"coordinates":[6.617097,52.573212],"type":"Point"}
}