{
  "type": "Feature",
  "properties": {
    "addr:full":"Molenstraat 23 Cuijk Noord-Brabant 5431 BW",
    "addr:housenumber":"23",
    "addr:postcode":"5431 bw",
    "addr:street":"Molenstraat",
    "iso:country":"NL",
    "sg:address":"Molenstraat 23",
    "sg:city":"Cuijk",
    "sg:orig_category":"Kappers",
    "sg:phone":"+31 485 312 017",
    "sg:postcode":"5431 BW",
    "sg:province":"Noord-Brabant",
    "wof:name":"Dames- En Herenkapper Henry Van Uden",
    "wof:placetype":"venue"
},
  "geometry": {"coordinates":[5.8352007866,51.7266349792],"type":"Point"}
}