{
  "type": "Feature",
  "properties": {
    "addr:full":"Sterkenburg 57 Eindhoven Noord-Brabant 5653 NC",
    "addr:housenumber":"57",
    "addr:postcode":"5653 nc",
    "addr:street":"Sterkenburg",
    "iso:country":"NL",
    "sg:address":"Sterkenburg 57",
    "sg:city":"Eindhoven",
    "sg:orig_category":"Vertalers",
    "sg:phone":"+31 40 252 7272",
    "sg:postcode":"5653 NC",
    "sg:province":"Noord-Brabant",
    "wof:name":"Hoyer, A",
    "wof:placetype":"venue"
},
  "geometry": {"coordinates":[5.442917,51.421268],"type":"Point"}
}