{
  "type": "Feature",
  "properties": {
    "iso:country":"NL",
    "sg:address":"Vogelweide 86",
    "sg:city":"Doorn",
    "sg:orig_category":"Bloemen En Planten",
    "sg:phone":"+31 343 415 589",
    "sg:postcode":"3941 NB",
    "sg:province":"Utrecht",
    "sg:website":"http://www.atelier-het-klokhuus.nl",
    "wof:name":"Klokhuus, Het",
    "wof:placetype":"venue"
},
  "geometry": {"coordinates":[5.34238,52.02663],"type":"Point"}
}