{
  "type": "Feature",
  "properties": {
    "addr:full":"Nieuwe Dijk 15 Coevorden Drenthe 7741 NN",
    "addr:housenumber":"15",
    "addr:postcode":"7741 nn",
    "addr:street":"Nieuwe Dijk",
    "iso:country":"NL",
    "sg:address":"Nieuwe Dijk 15",
    "sg:city":"Coevorden",
    "sg:orig_category":"Kampeerterreinen",
    "sg:phone":"+31 524 571 068",
    "sg:postcode":"7741 NN",
    "sg:province":"Drenthe",
    "wof:name":"Camping-Kampeerboerderij De Klaverhoeve",
    "wof:placetype":"venue"
},
  "geometry": {"coordinates":[6.6683568954,52.6620597839],"type":"Point"}
}