{
  "type": "Feature",
  "properties": {
    "addr:full":"Dorpspln 17 Soesterberg Utrecht 3769 DA",
    "addr:housenumber":"17",
    "addr:postcode":"3769 da",
    "addr:street":"Dorpspln",
    "iso:country":"NL",
    "sg:address":"Dorpspln 17",
    "sg:city":"Soesterberg",
    "sg:orig_category":"Schoonheidsinstituten",
    "sg:phone":"+31 346 353 746",
    "sg:postcode":"3769 DA",
    "sg:province":"Utrecht",
    "wof:name":"Eveline",
    "wof:placetype":"venue"
},
  "geometry": {"coordinates":[5.282895,52.119373],"type":"Point"}
}