{
  "type": "Feature",
  "properties": {
    "iso:country":"NL",
    "sg:address":"Van Der Lekstraat 34",
    "sg:city":"Hendrik Ido Ambacht",
    "sg:orig_category":"Verzekeringen",
    "sg:phone":"+31 78 681 5404",
    "sg:postcode":"3341 GX",
    "sg:province":"Zuid-Holland",
    "wof:name":"J. De Moei Assurantien",
    "wof:placetype":"venue"
},
  "geometry": {"coordinates":[4.645024,51.844444],"type":"Point"}
}