{
  "type": "Feature",
  "properties": {
    "addr:full":"Hogeweg 69 Voerendaal Limburg 6367 BB",
    "addr:housenumber":"69",
    "addr:postcode":"6367 bb",
    "addr:street":"Hogeweg",
    "iso:country":"NL",
    "sg:address":"Hogeweg 69",
    "sg:city":"Voerendaal",
    "sg:classifiers":[
        {
            "category":"Fast Food",
            "type":"Food & Drink"
        }
    ],
    "sg:phone":"+31 45 575 3042",
    "sg:postcode":"6367 BB",
    "sg:province":"Limburg",
    "sg:tags":[
        "afhaal",
        "restaurant"
    ],
    "wof:name":"Chin. Ind. Rest. Pom Lai",
    "wof:placetype":"venue"
},
  "geometry": {"coordinates":[5.932465,50.877811],"type":"Point"}
}