{
  "type": "Feature",
  "properties": {
    "addr:full":"Marktpln 77A Broek Op Langedyk North Holland 1721 CK",
    "addr:housenumber":"77a",
    "addr:postcode":"1721 ck",
    "addr:street":"Marktpln;Op Langedyk North",
    "iso:country":"NL",
    "sg:address":"Marktpln 77A",
    "sg:city":"Broek Op Langedyk",
    "sg:orig_category":"Makelaars En Adviseurs Onroerende Goederen",
    "sg:phone":"+31 226 315 341",
    "sg:postcode":"1721 CK",
    "sg:province":"North Holland",
    "sg:website":"http://www.era.nl/ridder",
    "wof:name":"Ridder, Van De",
    "wof:placetype":"venue"
},
  "geometry": {"coordinates":[4.803532,52.678837],"type":"Point"}
}