{
  "type": "Feature",
  "properties": {
    "iso:country":"NL",
    "sg:address":"Strawinskyln 907",
    "sg:city":"Amsterdam",
    "sg:orig_category":"Zelfklevende Materialen",
    "sg:phone":"+31 20 673 3566",
    "sg:postcode":"1077 XX",
    "sg:province":"North Holland",
    "wof:name":"Lintec Eur Bv",
    "wof:placetype":"venue"
},
  "geometry": {"coordinates":[4.873559,52.340649],"type":"Point"}
}