{
  "type": "Feature",
  "properties": {
    "addr:full":"Rokin 92 Amsterdam Noord-Holland 1012 KZ",
    "addr:housenumber":"92",
    "addr:postcode":"1012 kz",
    "addr:street":"Rokin",
    "iso:country":"NL",
    "sg:address":"Rokin 92",
    "sg:city":"Amsterdam",
    "sg:orig_category":"Overheidsdiensten",
    "sg:phone":"+31 20 523 3133",
    "sg:postcode":"1012 KZ",
    "sg:province":"Noord-Holland",
    "wof:name":"Gemeente Amsterdam",
    "wof:placetype":"venue"
},
  "geometry": {"coordinates":[4.892001152,52.3697471619],"type":"Point"}
}