{
  "type": "Feature",
  "properties": {
    "addr:full":"Kimswerderweg 2 Harlingen Provincie Friesland 8862 TS",
    "addr:housenumber":"2",
    "addr:postcode":"8862 ts",
    "addr:street":"Kimswerderweg;Provincie Friesland",
    "iso:country":"NL",
    "sg:address":"Kimswerderweg 2",
    "sg:city":"Harlingen",
    "sg:orig_category":"Politie",
    "sg:phone":"+31 900 8844",
    "sg:postcode":"8862 TS",
    "sg:province":"Provincie Friesland",
    "wof:name":"Politie District De Wadden Basiseenh Franeker/Harl",
    "wof:placetype":"venue"
},
  "geometry": {"coordinates":[5.427523,53.169468],"type":"Point"}
}