{
  "type": "Feature",
  "properties": {
    "addr:full":"Weststr 11 Domburg Zeeland 4357 BL",
    "addr:housenumber":"11",
    "addr:postcode":"4357 bl",
    "addr:street":"Weststr",
    "iso:country":"NL",
    "sg:address":"Weststr 11",
    "sg:city":"Domburg",
    "sg:orig_category":"Bloemen En Planten",
    "sg:phone":"+31 118 581 758",
    "sg:postcode":"4357 BL",
    "sg:province":"Zeeland",
    "wof:name":"Brand",
    "wof:placetype":"venue"
},
  "geometry": {"coordinates":[3.495478,51.562531],"type":"Point"}
}