{
  "type": "Feature",
  "properties": {
    "addr:full":"Gelderlandplein 135 Amsterdam Missouri 1082 LV",
    "addr:housenumber":"135",
    "addr:postcode":"1082",
    "addr:street":"Gelderlandplein",
    "iso:country":"NL",
    "sg:address":"Gelderlandplein 135",
    "sg:city":"Amsterdam",
    "sg:orig_category":"Herenmodezaken",
    "sg:phone":"+31 20 644 1162",
    "sg:postcode":"1082 LV",
    "sg:province":"Missouri",
    "wof:name":"Moorman Mannenmode Bv",
    "wof:placetype":"venue"
},
  "geometry": {"coordinates":[-94.58503,38.350479],"type":"Point"}
}