{
  "type": "Feature",
  "properties": {
    "addr:full":"Gen Cronjestr 117 Haarlem Noord-Holland 2021 JE",
    "addr:housenumber":"117",
    "addr:postcode":"2021 je",
    "iso:country":"NL",
    "sg:address":"Gen Cronjestr 117",
    "sg:city":"Haarlem",
    "sg:orig_category":"Kappers",
    "sg:phone":"+31 23 527 8147",
    "sg:postcode":"2021 JE",
    "sg:province":"Noord-Holland",
    "sg:website":"http://www.hizihair.nl",
    "wof:name":"Hizihair",
    "wof:placetype":"venue"
},
  "geometry": {"coordinates":[4.6420211792,52.3954315186],"type":"Point"}
}