{
  "type": "Feature",
  "properties": {
    "addr:full":"Deurningerstr 30 Enschede Overijssel 7514 BJ",
    "addr:housenumber":"30",
    "addr:postcode":"7514 bj",
    "addr:street":"Deurningerstr",
    "iso:country":"NL",
    "sg:address":"Deurningerstr 30",
    "sg:city":"Enschede",
    "sg:orig_category":"Nachtclubs",
    "sg:phone":"+31 53 433 4703",
    "sg:postcode":"7514 BJ",
    "sg:province":"Overijssel",
    "wof:name":"Horizon",
    "wof:placetype":"venue"
},
  "geometry": {"coordinates":[6.891242,52.226124],"type":"Point"}
}