{
  "type": "Feature",
  "properties": {
    "iso:country":"NL",
    "sg:address":"Deurningerstr 30",
    "sg:city":"Enschede",
    "sg:orig_category":"Nachtclubs",
    "sg:phone":"+31 53 433 4703",
    "sg:postcode":"7514 BJ",
    "sg:province":"Overijssel",
    "wof:name":"Horizon",
    "wof:placetype":"venue"
},
  "geometry": {"coordinates":[6.891242,52.226124],"type":"Point"}
}