{
  "type": "Feature",
  "properties": {
    "addr:full":"Ruyghweg 55 Den Helder Noord-Holland 1781 DB",
    "addr:housenumber":"55",
    "addr:postcode":"1781 db",
    "addr:street":"Ruyghweg",
    "iso:country":"NL",
    "sg:address":"Ruyghweg 55",
    "sg:city":"Den Helder",
    "sg:orig_category":"Werving And Selectie Van Tijdelijk Personeel And Uitzendkantoren",
    "sg:phone":"+31 223 614 747",
    "sg:postcode":"1781 DB",
    "sg:province":"Noord-Holland",
    "wof:name":"Bv Residentie Service Bedrijf",
    "wof:placetype":"venue"
},
  "geometry": {"coordinates":[4.7656030655,52.9536132812],"type":"Point"}
}