{
  "type": "Feature",
  "properties": {
    "addr:full":"Mierlosewg 331 Helmond Noord-Brabant 5707 AK",
    "addr:housenumber":"331",
    "addr:postcode":"5707 ak",
    "iso:country":"NL",
    "sg:address":"Mierlosewg 331",
    "sg:city":"Helmond",
    "sg:orig_category":"Drukkerijen",
    "sg:phone":"+31 492 538 710",
    "sg:postcode":"5707 AK",
    "sg:province":"Noord-Brabant",
    "wof:name":"Animo",
    "wof:placetype":"venue"
},
  "geometry": {"coordinates":[5.634819,51.469631],"type":"Point"}
}