{
  "type": "Feature",
  "properties": {
    "iso:country":"NL",
    "sg:address":"Zoetermeerstr 8",
    "sg:city":"Hoofddorp",
    "sg:orig_category":"Adviesbureaus Bedrijfsorganisatie",
    "sg:phone":"+31 23 561 4192",
    "sg:postcode":"2131 DS",
    "sg:province":"Noord-Holland",
    "wof:name":"Imata Bv",
    "wof:placetype":"venue"
},
  "geometry": {"coordinates":[4.686288,52.311543],"type":"Point"}
}