{
  "type": "Feature",
  "properties": {
    "addr:full":"Reguliersgr 49 Amsterdam North Holland 1017 LL",
    "addr:housenumber":"49",
    "addr:postcode":"1017 ll",
    "addr:street":"Reguliersgr",
    "iso:country":"NL",
    "sg:address":"Reguliersgr 49",
    "sg:city":"Amsterdam",
    "sg:orig_category":"Fotojournalisten Freelance",
    "sg:phone":"+31 20 626 6512",
    "sg:postcode":"1017 LL",
    "sg:province":"North Holland",
    "wof:name":"Denderen, Ad Van",
    "wof:placetype":"venue"
},
  "geometry": {"coordinates":[4.896388,52.362938],"type":"Point"}
}