{
  "type": "Feature",
  "properties": {
    "iso:country":"NL",
    "sg:address":"De Boedingen 31",
    "sg:city":"Oosterhout Nb",
    "sg:orig_category":"Automaterialen En Gereedschappen",
    "sg:phone":"+31 162 447 300",
    "sg:postcode":"4906 BA",
    "sg:province":"North Brabant",
    "wof:name":"Broekhuizen",
    "wof:placetype":"venue"
},
  "geometry": {"coordinates":[4.83438,51.655071],"type":"Point"}
}