{
  "type": "Feature",
  "properties": {
    "iso:country":"NL",
    "sg:address":"Frans Halsstraat 54",
    "sg:city":"Eindhoven",
    "sg:orig_category":"Metaalbekleding And -Behandeling",
    "sg:phone":"+31 40 245 6365",
    "sg:postcode":"5613 KW",
    "sg:province":"Noord-Brabant",
    "wof:name":"E.F. Muller",
    "wof:placetype":"venue"
},
  "geometry": {"coordinates":[5.498277,51.440472],"type":"Point"}
}