{
  "type": "Feature",
  "properties": {
    "addr:full":"Printer 23 Coevorden Provincie Drenthe 7741 ME",
    "addr:housenumber":"23",
    "addr:postcode":"7741 me",
    "addr:street":"Printer;Provincie Drenthe",
    "iso:country":"NL",
    "sg:address":"Printer 23",
    "sg:city":"Coevorden",
    "sg:orig_category":"Gespecialiseerde Bouw",
    "sg:phone":"+31 524 512 464",
    "sg:postcode":"7741 ME",
    "sg:province":"Provincie Drenthe",
    "wof:name":"Dikkerboom Betonboringen Bv",
    "wof:placetype":"venue"
},
  "geometry": {"coordinates":[6.73891,52.6642],"type":"Point"}
}