{
  "type": "Feature",
  "properties": {
    "addr:full":"Catharyneln 34 Lisse Zuid-Holland 2161 CK",
    "addr:housenumber":"34",
    "addr:postcode":"2161 ck",
    "addr:street":"Catharyneln",
    "iso:country":"NL",
    "sg:address":"Catharyneln 34",
    "sg:city":"Lisse",
    "sg:orig_category":"Bloemen En Planten",
    "sg:phone":"+31 252 216 509",
    "sg:postcode":"2161 CK",
    "sg:province":"Zuid-Holland",
    "wof:name":"Mens, Gebr",
    "wof:placetype":"venue"
},
  "geometry": {"coordinates":[4.535805,52.245052],"type":"Point"}
}