{
  "type": "Feature",
  "properties": {
    "addr:full":"Van Ijsendijkstraat 150 Purmerend Noord-Holland 1442 LC",
    "addr:housenumber":"150",
    "addr:postcode":"1442 lc",
    "addr:street":"Van Ijsendijkstraat",
    "iso:country":"NL",
    "sg:address":"Van Ijsendijkstraat 150",
    "sg:city":"Purmerend",
    "sg:orig_category":"Drukkerijen And Copyshops",
    "sg:phone":"+31 299 418 418",
    "sg:postcode":"1442 LC",
    "sg:province":"Noord-Holland",
    "wof:name":"Henkes Senefelder Bv",
    "wof:placetype":"venue"
},
  "geometry": {"coordinates":[4.976591,52.515202],"type":"Point"}
}