{
  "type": "Feature",
  "properties": {
    "addr:full":"Touwbaan 43 Lekkerkerk South Holland 2941 XV",
    "addr:housenumber":"43",
    "addr:postcode":"2941 xv",
    "addr:street":"Touwbaan",
    "iso:country":"NL",
    "sg:address":"Touwbaan 43",
    "sg:city":"Lekkerkerk",
    "sg:orig_category":"Fotostudio'S And Fotografen",
    "sg:phone":"+31 180 664 418",
    "sg:postcode":"2941 XV",
    "sg:province":"South Holland",
    "wof:name":"Frans Marks Fotografie",
    "wof:placetype":"venue"
},
  "geometry": {"coordinates":[4.685593,51.898319],"type":"Point"}
}