{
  "type": "Feature",
  "properties": {
    "iso:country":"NL",
    "sg:address":"Kastelenpln 168C",
    "sg:city":"Eindhoven",
    "sg:orig_category":"Adviesbureaus Bouwkosten",
    "sg:phone":"+31 40 250 4200",
    "sg:postcode":"5653 LX",
    "sg:province":"Noord-Brabant",
    "sg:website":"http://www.dukers-decock.nl",
    "wof:name":"Dukers & De Cock Cost Consult Bv",
    "wof:placetype":"venue"
},
  "geometry": {"coordinates":[5.442754,51.419086],"type":"Point"}
}