{
  "type": "Feature",
  "properties": {
    "iso:country":"NL",
    "sg:address":"Witvensedijk 21",
    "sg:city":"Esch",
    "sg:orig_category":"Hoefdierhouderijen",
    "sg:phone":"+31 411 602 047",
    "sg:postcode":"5296 KH",
    "sg:province":"Noord-Brabant",
    "wof:name":"F.J.M. V.D. Steen",
    "wof:placetype":"venue"
},
  "geometry": {"coordinates":[5.284026,51.622101],"type":"Point"}
}