{
  "type": "Feature",
  "properties": {
    "addr:full":"Dennenstraat 71 Nijmegen Gelderland 6543 JP",
    "addr:housenumber":"71",
    "addr:postcode":"6543 jp",
    "addr:street":"Dennenstraat;Gelderland",
    "iso:country":"NL",
    "sg:address":"Dennenstraat 71",
    "sg:city":"Nijmegen",
    "sg:orig_category":"Kinderopvang Behalve Thuis",
    "sg:phone":"+31 24 378 9572",
    "sg:postcode":"6543 JP",
    "sg:province":"Gelderland",
    "wof:name":"De Dennen Kindercentrum",
    "wof:placetype":"venue"
},
  "geometry": {"coordinates":[5.823708,51.832649],"type":"Point"}
}