{
  "type": "Feature",
  "properties": {
    "addr:full":"Past Sterckenstr 16 Meerssen Limburg 6231 JG",
    "addr:housenumber":"16",
    "addr:postcode":"6231 jg",
    "iso:country":"NL",
    "sg:address":"Past Sterckenstr 16",
    "sg:city":"Meerssen",
    "sg:orig_category":"Woninginrichting",
    "sg:phone":"+31 43 364 2908",
    "sg:postcode":"6231 JG",
    "sg:province":"Limburg",
    "wof:name":"Leerssen",
    "wof:placetype":"venue"
},
  "geometry": {"coordinates":[5.7531409264,50.8886108398],"type":"Point"}
}