{
  "type": "Feature",
  "properties": {
    "iso:country":"NL",
    "sg:address":"Woldpromenade 19",
    "sg:city":"Steenwijk",
    "sg:classifiers":[
        {
            "category":"Retail",
            "subcategory":"Photofinishing",
            "type":"Services"
        }
    ],
    "sg:phone":"+31 521 514 732",
    "sg:postcode":"8331 JD",
    "sg:province":"NL.08",
    "sg:tags":[
        "foto",
        "film"
    ],
    "wof:name":"Foto Jan Vredenburg Vof",
    "wof:placetype":"venue"
},
  "geometry": {"coordinates":[6.113502,52.786518],"type":"Point"}
}