{
  "type": "Feature",
  "properties": {
    "addr:full":"Wassenaarseweg 19 De Zilk South Holland 2191 BH",
    "addr:housenumber":"19",
    "addr:postcode":"2191 bh",
    "addr:street":"Wassenaarseweg",
    "iso:country":"NL",
    "sg:address":"Wassenaarseweg 19",
    "sg:city":"De Zilk",
    "sg:orig_category":"Autokeuringen",
    "sg:phone":"+31 252 515 758",
    "sg:postcode":"2191 BH",
    "sg:province":"South Holland",
    "wof:name":"J T Turnhout",
    "wof:placetype":"venue"
},
  "geometry": {"coordinates":[4.546312,52.301624],"type":"Point"}
}