{
  "type": "Feature",
  "properties": {
    "addr:full":"Herenwg 22B Warmond South Holland 2361 ER",
    "addr:housenumber":"22b",
    "addr:postcode":"2361 er",
    "addr:street":"Herenwg",
    "iso:country":"NL",
    "sg:address":"Herenwg 22B",
    "sg:city":"Warmond",
    "sg:orig_category":"Bloembollen - Groothandel",
    "sg:phone":"+31 71 301 0339",
    "sg:postcode":"2361 ER",
    "sg:province":"South Holland",
    "wof:name":"Winsen & Zn, M G Van",
    "wof:placetype":"venue"
},
  "geometry": {"coordinates":[4.497423,52.193607],"type":"Point"}
}