{
  "type": "Feature",
  "properties": {
    "addr:full":"Noord 18 Franeker Provincie Friesland 8801 KP",
    "addr:housenumber":"18",
    "addr:postcode":"8801 kp",
    "addr:street":"Noord;Provincie Friesland",
    "iso:country":"NL",
    "sg:address":"Noord 18",
    "sg:city":"Franeker",
    "sg:orig_category":"Kappers",
    "sg:phone":"+31 517 392 206",
    "sg:postcode":"8801 KP",
    "sg:province":"Provincie Friesland",
    "wof:name":"Kapsalons Phiro",
    "wof:placetype":"venue"
},
  "geometry": {"coordinates":[5.542965889,53.1874923706],"type":"Point"}
}