{
  "type": "Feature",
  "properties": {
    "addr:full":"Hoofdvaart 6 Dedemsvaart Overijssel 7701 JL",
    "addr:housenumber":"6",
    "addr:postcode":"7701 jl",
    "addr:street":"Hoofdvaart",
    "iso:country":"NL",
    "sg:address":"Hoofdvaart 6",
    "sg:city":"Dedemsvaart",
    "sg:orig_category":"Geluidsinstallaties - Verhuur",
    "sg:phone":"+31 6 24862007",
    "sg:postcode":"7701 JL",
    "sg:province":"Overijssel",
    "wof:name":"Pro Audio Verhuur",
    "wof:placetype":"venue"
},
  "geometry": {"coordinates":[6.456065,52.599262],"type":"Point"}
}