{
  "type": "Feature",
  "properties": {
    "iso:country":"NL",
    "sg:address":"Nieuwstr 85",
    "sg:city":"Oostburg",
    "sg:orig_category":"Onderhoudswerken",
    "sg:phone":"+31 117 453 406",
    "sg:postcode":"4501 ND",
    "sg:province":"Zeeland",
    "wof:name":"Wever, W De",
    "wof:placetype":"venue"
},
  "geometry": {"coordinates":[3.479294,51.319286],"type":"Point"}
}