{
  "type": "Feature",
  "properties": {
    "addr:full":"Nieuwstr 85 Oostburg Zeeland 4501 ND",
    "addr:housenumber":"85",
    "addr:postcode":"4501 nd",
    "addr:street":"Nieuwstr",
    "iso:country":"NL",
    "sg:address":"Nieuwstr 85",
    "sg:city":"Oostburg",
    "sg:orig_category":"Onderhoudswerken",
    "sg:phone":"+31 117 453 406",
    "sg:postcode":"4501 ND",
    "sg:province":"Zeeland",
    "wof:name":"Wever, W De",
    "wof:placetype":"venue"
},
  "geometry": {"coordinates":[3.479294,51.319286],"type":"Point"}
}