{
  "type": "Feature",
  "properties": {
    "addr:full":"Amelandsestr 45 Rotterdam South Holland 3083 SN",
    "addr:housenumber":"45",
    "addr:postcode":"3083 sn",
    "addr:street":"Amelandsestr",
    "iso:country":"NL",
    "sg:address":"Amelandsestr 45",
    "sg:city":"Rotterdam",
    "sg:orig_category":"Kappers",
    "sg:phone":"+31 10 481 2456",
    "sg:postcode":"3083 SN",
    "sg:province":"South Holland",
    "wof:name":"Manifarges, L A",
    "wof:placetype":"venue"
},
  "geometry": {"coordinates":[4.48399,51.889141],"type":"Point"}
}