{
  "type": "Feature",
  "properties": {
    "addr:full":"Postbus 1344 Tilburg North Brabant 5004 BH",
    "addr:housenumber":"1344",
    "addr:postcode":"5004 bh",
    "addr:street":"Postbus",
    "iso:country":"NL",
    "sg:address":"Postbus 1344",
    "sg:city":"Tilburg",
    "sg:orig_category":"Journalisten Freelance",
    "sg:phone":"+31 13 463 3360",
    "sg:postcode":"5004 BH",
    "sg:province":"North Brabant",
    "wof:name":"Doremalen, Henk Van",
    "wof:placetype":"venue"
},
  "geometry": {"coordinates":[5.09065,51.555241],"type":"Point"}
}