{
  "type": "Feature",
  "properties": {
    "addr:full":"Torenstraat 142 'S Gravenhage Zuid-Holland 2513 BW",
    "addr:housenumber":"142 '",
    "addr:postcode":"2513 bw",
    "addr:street":"Torenstraat",
    "iso:country":"NL",
    "sg:address":"Torenstraat 142",
    "sg:city":"'S Gravenhage",
    "sg:classifiers":[
        {
            "category":"Communications",
            "subcategory":"Television Station",
            "type":"Services"
        }
    ],
    "sg:phone":"+31 70 364 6646",
    "sg:postcode":"2513 BW",
    "sg:province":"Zuid-Holland",
    "sg:tags":[
        "video",
        "audio",
        "verhuur"
    ],
    "wof:name":"Videotheek Mega",
    "wof:placetype":"venue"
},
  "geometry": {"coordinates":[4.304259,52.078369],"type":"Point"}
}