{
  "type": "Feature",
  "properties": {
    "iso:country":"NL",
    "sg:address":"Molendijk 57",
    "sg:city":"Melissant",
    "sg:orig_category":"Granen, Zaden And Diervoeders Gh",
    "sg:phone":"+31 187 601 372",
    "sg:postcode":"3248 BA",
    "sg:province":"Zuid-Holland",
    "wof:name":"L. Leijdens",
    "wof:placetype":"venue"
},
  "geometry": {"coordinates":[4.05569,51.76709],"type":"Point"}
}