{
  "type": "Feature",
  "properties": {
    "addr:full":"Lekdijk-Oost 48 Bergambacht Zuid-Holland 2861 GB",
    "addr:housenumber":"48",
    "addr:postcode":"2861 gb",
    "addr:street":"Lekdijk-Oost",
    "iso:country":"NL",
    "sg:address":"Lekdijk-Oost 48",
    "sg:city":"Bergambacht",
    "sg:orig_category":"Bloemen And Planten",
    "sg:phone":"+31 182 351 462",
    "sg:postcode":"2861 GB",
    "sg:province":"Zuid-Holland",
    "wof:name":"W. Stout",
    "wof:placetype":"venue"
},
  "geometry": {"coordinates":[4.796276,51.924023],"type":"Point"}
}