{
  "type": "Feature",
  "properties": {
    "iso:country":"NL",
    "sg:address":"Van Den Berglaan 12",
    "sg:city":"Voorthuizen",
    "sg:classifiers":[
        {
            "category":"Education",
            "subcategory":"Preschool",
            "type":"Public Place"
        }
    ],
    "sg:phone":"+31 342 473 052",
    "sg:postcode":"3781 GG",
    "sg:province":"Gelderland",
    "sg:tags":[
        "kleuteronderwijs",
        "basis-"
    ],
    "wof:name":"Koningin Wilhelmina School",
    "wof:placetype":"venue"
},
  "geometry": {"coordinates":[5.606786,52.185383],"type":"Point"}
}