{
  "type": "Feature",
  "properties": {
    "addr:full":"Droogbloem 4 Castricum Noord-Holland 1902 GG",
    "addr:housenumber":"4",
    "addr:postcode":"1902 gg",
    "addr:street":"Droogbloem",
    "iso:country":"NL",
    "sg:address":"Droogbloem 4",
    "sg:city":"Castricum",
    "sg:orig_category":"Bedrijfs- And Managementsconsultants",
    "sg:phone":"+31 251 651 401",
    "sg:postcode":"1902 GG",
    "sg:province":"Noord-Holland",
    "wof:name":"Adviesbureau Skoop",
    "wof:placetype":"venue"
},
  "geometry": {"coordinates":[4.680283,52.55217],"type":"Point"}
}