{
  "type": "Feature",
  "properties": {
    "addr:full":"Brouwersgracht 167 Amsterdam Noord-Holland 1015 GH",
    "addr:housenumber":"167",
    "addr:postcode":"1015 gh",
    "addr:street":"Brouwersgracht",
    "iso:country":"NL",
    "sg:address":"Brouwersgracht 167",
    "sg:city":"Amsterdam",
    "sg:orig_category":"Kantoor- And Schoolbenodigdheden Gh",
    "sg:phone":"+31 20 622 3858",
    "sg:postcode":"1015 GH",
    "sg:province":"Noord-Holland",
    "wof:name":"Stuivinga & Wagter Bv",
    "wof:placetype":"venue"
},
  "geometry": {"coordinates":[4.8851780891,52.381942749],"type":"Point"}
}