{
  "type": "Feature",
  "properties": {
    "iso:country":"NL",
    "sg:address":"Broekboomstraat 19",
    "sg:city":"Lichtenvoorde",
    "sg:orig_category":"Werving And Selectie Van Tijdelijk Personeel And Uitzendkantoren",
    "sg:phone":"+31 544 376 988",
    "sg:postcode":"7131 DT",
    "sg:province":"Gelderland",
    "wof:name":"Start",
    "wof:placetype":"venue"
},
  "geometry": {"coordinates":[6.565764904,51.9862136841],"type":"Point"}
}