{
  "type": "Feature",
  "properties": {
    "iso:country":"NL",
    "sg:address":"Hemstea 11",
    "sg:city":"Eibergen",
    "sg:orig_category":"Adviesbureaus Bouwkunde",
    "sg:phone":"+31 6 22605019",
    "sg:postcode":"7152 BD",
    "sg:province":"Gelderland",
    "wof:name":"Ben Mateman, Timmerbedrijf",
    "wof:placetype":"venue"
},
  "geometry": {"coordinates":[6.654832,52.101948],"type":"Point"}
}