{
  "type": "Feature",
  "properties": {
    "addr:full":"Wanssumsewg 12 Oostrum Lb Limburg 5807 EA",
    "addr:housenumber":"12",
    "addr:postcode":"lb;5807 ea",
    "addr:street":"Wanssumsewg",
    "iso:country":"NL",
    "sg:address":"Wanssumsewg 12",
    "sg:city":"Oostrum Lb",
    "sg:orig_category":"Ziekenhuizen, Sanatoria, Verpleeghuizen",
    "sg:phone":"+31 478 527 815",
    "sg:postcode":"5807 EA",
    "sg:province":"Limburg",
    "wof:name":"Paschalis",
    "wof:placetype":"venue"
},
  "geometry": {"coordinates":[-93.129936,36.705662],"type":"Point"}
}