{
  "type": "Feature",
  "properties": {
    "addr:full":"Dorpsstr 12 Schipluiden Zuid-Holland 2636 CC",
    "addr:housenumber":"12",
    "addr:postcode":"2636 cc",
    "addr:street":"Dorpsstr",
    "iso:country":"NL",
    "sg:address":"Dorpsstr 12",
    "sg:city":"Schipluiden",
    "sg:orig_category":"Fietsen En Bromfietsen",
    "sg:phone":"+31 15 380 1188",
    "sg:postcode":"2636 CC",
    "sg:province":"Zuid-Holland",
    "wof:name":"Willemsen, Paul",
    "wof:placetype":"venue"
},
  "geometry": {"coordinates":[4.315211,51.976971],"type":"Point"}
}