{
  "type": "Feature",
  "properties": {
    "addr:full":"Willibrordusstr 6 Batenburg Gelderland 6634 AM",
    "addr:housenumber":"6",
    "addr:postcode":"6634",
    "addr:street":"Willibrordusstr;Gelderland",
    "iso:country":"NL",
    "sg:address":"Willibrordusstr 6",
    "sg:city":"Batenburg",
    "sg:orig_category":"Voetbalverenigingen",
    "sg:phone":"+31 487 541 641",
    "sg:postcode":"6634 AM",
    "sg:province":"Gelderland",
    "wof:name":"Fc Ria",
    "wof:placetype":"venue"
},
  "geometry": {"coordinates":[5.629122,51.82449],"type":"Point"}
}