{
  "type": "Feature",
  "properties": {
    "iso:country":"NL",
    "sg:address":"Volkerakstr 97",
    "sg:city":"Den Helder",
    "sg:orig_category":"Werving En Selectie",
    "sg:phone":"+31 223 632 310",
    "sg:postcode":"1784 HD",
    "sg:province":"North Holland",
    "wof:name":"Bapas",
    "wof:placetype":"venue"
},
  "geometry": {"coordinates":[4.7358021736,52.9369506836],"type":"Point"}
}