{
  "type": "Feature",
  "properties": {
    "iso:country":"NL",
    "sg:address":"Voorstraat 73",
    "sg:city":"Vianen Zh",
    "sg:orig_category":"Zuivelproducten",
    "sg:phone":"+31 347 328 537",
    "sg:postcode":"4132 AP",
    "sg:province":"Utrecht",
    "wof:name":"De Jonge Bv",
    "wof:placetype":"venue"
},
  "geometry": {"coordinates":[5.092556,51.993351],"type":"Point"}
}