{
  "type": "Feature",
  "properties": {
    "addr:full":"Piet Heinstraat 4 Enschede Overijssel 7511 JE",
    "addr:housenumber":"4",
    "addr:postcode":"7511 je",
    "addr:street":"Piet Heinstraat",
    "iso:country":"NL",
    "sg:address":"Piet Heinstraat 4",
    "sg:city":"Enschede",
    "sg:orig_category":"Werving And Selectie Van Tijdelijk Personeel And Uitzendkantoren",
    "sg:phone":"+31 53 483 8585",
    "sg:postcode":"7511 JE",
    "sg:province":"Overijssel",
    "wof:name":"Randstad Uitzendbureau Bv",
    "wof:placetype":"venue"
},
  "geometry": {"coordinates":[6.8912601471,52.2210426331],"type":"Point"}
}