{
  "type": "Feature",
  "properties": {
    "addr:full":"Utrechtseweg 34 Utrecht Utrecht 3544 NA",
    "addr:housenumber":"34",
    "addr:postcode":"3544 na",
    "addr:street":"Utrechtseweg",
    "iso:country":"NL",
    "sg:address":"Utrechtseweg 34",
    "sg:city":"Utrecht",
    "sg:orig_category":"Bloemen And Planten",
    "sg:phone":"+31 30 677 1773",
    "sg:postcode":"3544 NA",
    "sg:province":"Utrecht",
    "wof:name":"Visser Vleuten",
    "wof:placetype":"venue"
},
  "geometry": {"coordinates":[5.039271,52.099705],"type":"Point"}
}