{
  "type": "Feature",
  "properties": {
    "iso:country":"NL",
    "sg:address":"Utrechtseweg 34",
    "sg:city":"Utrecht",
    "sg:orig_category":"Bloemen And Planten",
    "sg:phone":"+31 30 677 1773",
    "sg:postcode":"3544 NA",
    "sg:province":"Utrecht",
    "wof:name":"Visser Vleuten",
    "wof:placetype":"venue"
},
  "geometry": {"coordinates":[5.039271,52.099705],"type":"Point"}
}