{
  "type": "Feature",
  "properties": {
    "addr:full":"Kerkstr 11 Wagenberg North Brabant 4845 EC",
    "addr:housenumber":"11",
    "addr:postcode":"4845 ec",
    "addr:street":"Kerkstr",
    "iso:country":"NL",
    "sg:address":"Kerkstr 11",
    "sg:city":"Wagenberg",
    "sg:orig_category":"Cafetaria'S",
    "sg:phone":"+31 76 593 1601",
    "sg:postcode":"4845 EC",
    "sg:province":"North Brabant",
    "wof:name":"Driedorp",
    "wof:placetype":"venue"
},
  "geometry": {"coordinates":[4.751019,51.662926],"type":"Point"}
}