{
  "type": "Feature",
  "properties": {
    "addr:full":"Goudsbloemstr 112-Ii Amsterdam Noord-Holland 1015 JT",
    "addr:housenumber":"112-ii",
    "addr:postcode":"1015 jt",
    "addr:street":"Goudsbloemstr",
    "iso:country":"NL",
    "sg:address":"Goudsbloemstr 112-Ii",
    "sg:city":"Amsterdam",
    "sg:orig_category":"Kindermeubelen",
    "sg:phone":"+31 20 421 5056",
    "sg:postcode":"1015 JT",
    "sg:province":"Noord-Holland",
    "wof:name":"Dotties",
    "wof:placetype":"venue"
},
  "geometry": {"coordinates":[4.893195,52.373119],"type":"Point"}
}