{
  "type": "Feature",
  "properties": {
    "addr:full":"Leeuwendalerswg 1 Meisjescentr Nina Amsterdam North Holland 1055 JE",
    "addr:housenumber":"1",
    "addr:postcode":"1055 je",
    "addr:street":"Leeuwendalerswg;Nina",
    "iso:country":"NL",
    "sg:address":"Leeuwendalerswg 1 Meisjescentr Nina",
    "sg:city":"Amsterdam",
    "sg:orig_category":"Verenigingsgebouwen",
    "sg:phone":"+31 20 686 5243",
    "sg:postcode":"1055 JE",
    "sg:province":"North Holland",
    "wof:name":"Buurtservicepunt",
    "wof:placetype":"venue"
},
  "geometry": {"coordinates":[4.85337,52.380409],"type":"Point"}
}