{
  "type": "Feature",
  "properties": {
    "addr:full":"Poststr 16 Hoensbroek Limburg 6431 HL",
    "addr:housenumber":"16",
    "addr:postcode":"6431 hl",
    "addr:street":"Poststr",
    "iso:country":"NL",
    "sg:address":"Poststr 16",
    "sg:city":"Hoensbroek",
    "sg:orig_category":"Opticiens",
    "sg:phone":"+31 45 521 2251",
    "sg:postcode":"6431 HL",
    "sg:province":"Limburg",
    "wof:name":"Els, Charles Van",
    "wof:placetype":"venue"
},
  "geometry": {"coordinates":[5.9306650162,50.9253425598],"type":"Point"}
}