{
  "type": "Feature",
  "properties": {
    "addr:full":"Atoomweg 6 Hoorn Nh Noord-Holland 1627 LE",
    "addr:housenumber":"6",
    "addr:postcode":"1627 le",
    "addr:street":"Atoomweg",
    "iso:country":"NL",
    "sg:address":"Atoomweg 6",
    "sg:city":"Hoorn Nh",
    "sg:orig_category":"Autokeuringen",
    "sg:phone":"+31 229 211 497",
    "sg:postcode":"1627 LE",
    "sg:province":"Noord-Holland",
    "wof:name":"Horstman Occasionsdealer",
    "wof:placetype":"venue"
},
  "geometry": {"coordinates":[5.092689,52.642563],"type":"Point"}
}