{
  "type": "Feature",
  "properties": {
    "iso:country":"NL",
    "sg:address":"Prinsenlaan 101",
    "sg:city":"Middelburg",
    "sg:orig_category":"Glaszetten",
    "sg:phone":"+31 118 616 275",
    "sg:postcode":"4336 HK",
    "sg:province":"Zeeland",
    "wof:name":"Studio Wisteria",
    "wof:placetype":"venue"
},
  "geometry": {"coordinates":[3.621197,51.481739],"type":"Point"}
}