{
  "type": "Feature",
  "properties": {
    "addr:full":"Albert Einsteinweg 4 Drunen Noord-Brabant 5151 DL",
    "addr:housenumber":"4",
    "addr:postcode":"5151 dl",
    "addr:street":"Albert Einsteinweg",
    "iso:country":"NL",
    "sg:address":"Albert Einsteinweg 4",
    "sg:city":"Drunen",
    "sg:orig_category":"Pompen And Compressoren Fab",
    "sg:phone":"+31 416 387 280",
    "sg:postcode":"5151 DL",
    "sg:province":"Noord-Brabant",
    "wof:name":"Dab Pumps Bv",
    "wof:placetype":"venue"
},
  "geometry": {"coordinates":[5.155384,51.695213],"type":"Point"}
}