{
  "type": "Feature",
  "properties": {
    "addr:full":"Soestdijkerstrwg 38 Hilversum North Holland 1213 XC",
    "addr:housenumber":"38",
    "addr:postcode":"1213 xc",
    "addr:street":"Soestdijkerstrwg",
    "iso:country":"NL",
    "sg:address":"Soestdijkerstrwg 38",
    "sg:city":"Hilversum",
    "sg:orig_category":"Sportverenigingen En Ontspannings- Verenigingen",
    "sg:phone":"+31 35 685 6380",
    "sg:postcode":"1213 XC",
    "sg:province":"North Holland",
    "sg:website":"http://www.gach.nl",
    "wof:name":"Gooise Atletiekcl",
    "wof:placetype":"venue"
},
  "geometry": {"coordinates":[5.1695,52.228565],"type":"Point"}
}