{
  "type": "Feature",
  "properties": {
    "addr:full":"Dorpsstr 206 Wormer Noord-Holland 1531 HS",
    "addr:housenumber":"206",
    "addr:postcode":"1531 hs",
    "addr:street":"Wormer",
    "iso:country":"NL",
    "sg:address":"Dorpsstr 206",
    "sg:city":"Wormer",
    "sg:orig_category":"Verenigingsgebouwen",
    "sg:phone":"+31 75 642 3247",
    "sg:postcode":"1531 HS",
    "sg:province":"Noord-Holland",
    "wof:name":"Scwo",
    "wof:placetype":"venue"
},
  "geometry": {"coordinates":[4.823543,52.500084],"type":"Point"}
}