{
  "type": "Feature",
  "properties": {
    "iso:country":"NL",
    "sg:address":"Brinkwg 32",
    "sg:city":"Zelhem",
    "sg:orig_category":"Meubelen",
    "sg:phone":"+31 314 622 286",
    "sg:postcode":"7021 BW",
    "sg:province":"Gelderland",
    "wof:name":"Lorre",
    "wof:placetype":"venue"
},
  "geometry": {"coordinates":[6.35129,52.00211],"type":"Point"}
}