{
  "type": "Feature",
  "properties": {
    "iso:country":"NL",
    "sg:address":"Dorpsstr 59",
    "sg:city":"Vaassen",
    "sg:orig_category":"Postkantoren",
    "sg:phone":"+31 578 576 519",
    "sg:postcode":"8171 BL",
    "sg:province":"Gelderland",
    "sg:website":"http://www.postkantoor.nl",
    "wof:name":"Postkantoor",
    "wof:placetype":"venue"
},
  "geometry": {"coordinates":[5.968612,52.288448],"type":"Point"}
}