{
  "type": "Feature",
  "properties": {
    "addr:full":"Varkenmarkt 55 Dordrecht Zuid-Holland 3311 BR",
    "addr:housenumber":"55",
    "addr:postcode":"3311 br",
    "addr:street":"Varkenmarkt",
    "iso:country":"NL",
    "sg:address":"Varkenmarkt 55",
    "sg:city":"Dordrecht",
    "sg:orig_category":"Autokeuringen",
    "sg:phone":"+31 78 614 1552",
    "sg:postcode":"3311 BR",
    "sg:province":"Zuid-Holland",
    "wof:name":"Autoplaatwerkerij De Merwede",
    "wof:placetype":"venue"
},
  "geometry": {"coordinates":[4.664741,51.815876],"type":"Point"}
}