{
  "type": "Feature",
  "properties": {
    "addr:full":"Venkelveld 64 Doetinchem Gelderland 7006 TL",
    "addr:housenumber":"64",
    "addr:postcode":"7006 tl",
    "addr:street":"Venkelveld;Gelderland",
    "iso:country":"NL",
    "sg:address":"Venkelveld 64",
    "sg:city":"Doetinchem",
    "sg:orig_category":"Artsen - Huisartsen",
    "sg:phone":"+31 314 346 278",
    "sg:postcode":"7006 TL",
    "sg:province":"Gelderland",
    "wof:name":"Ellis, E L",
    "wof:placetype":"venue"
},
  "geometry": {"coordinates":[6.244317,51.962715],"type":"Point"}
}