{
  "type": "Feature",
  "properties": {
    "addr:full":"Amsterdamsestrwg 38 Halfweg Nh North Holland 1165 MA",
    "addr:housenumber":"38",
    "addr:postcode":"1165 ma",
    "addr:street":"Amsterdamsestrwg;Nh North",
    "iso:country":"NL",
    "sg:address":"Amsterdamsestrwg 38",
    "sg:city":"Halfweg Nh",
    "sg:classifiers":[
        {
            "category":"Travel",
            "subcategory":"Hotels & Motels",
            "type":"Entertainment"
        }
    ],
    "sg:phone":"+31 20 497 2941",
    "sg:postcode":"1165 MA",
    "sg:province":"North Holland",
    "wof:name":"Keizerskroon, De",
    "wof:placetype":"venue"
},
  "geometry": {"coordinates":[4.75446,52.383404],"type":"Point"}
}