{
  "type": "Feature",
  "properties": {
    "iso:country":"NL",
    "sg:address":"Amsterdamsestrwg 38",
    "sg:city":"Halfweg Nh",
    "sg:classifiers":[
        {
            "category":"Travel",
            "subcategory":"Hotels & Motels",
            "type":"Entertainment"
        }
    ],
    "sg:phone":"+31 20 497 2941",
    "sg:postcode":"1165 MA",
    "sg:province":"North Holland",
    "wof:name":"Keizerskroon, De",
    "wof:placetype":"venue"
},
  "geometry": {"coordinates":[4.75446,52.383404],"type":"Point"}
}