{
  "type": "Feature",
  "properties": {
    "addr:full":"Sparrendaal 35 Enschede NL.08 7544 NN",
    "addr:housenumber":"35",
    "addr:postcode":"7544 nn",
    "addr:street":"Sparrendaal",
    "iso:country":"NL",
    "sg:address":"Sparrendaal 35",
    "sg:city":"Enschede",
    "sg:orig_category":"Verzekeringen - Verzekeringskantoren",
    "sg:phone":"+31 53 476 4161",
    "sg:postcode":"7544 NN",
    "sg:province":"NL.08",
    "wof:name":"Cak Enschede",
    "wof:placetype":"venue"
},
  "geometry": {"coordinates":[6.873718,52.19997],"type":"Point"}
}