{
  "type": "Feature",
  "properties": {
    "addr:full":"Polsbroekstraat 40 Amsterdam Zuidoost Noord-Holland 1106 BB",
    "addr:housenumber":"40",
    "addr:postcode":"zuidoost;1106 bb",
    "addr:street":"Polsbroekstraat",
    "iso:country":"NL",
    "sg:address":"Polsbroekstraat 40",
    "sg:city":"Amsterdam Zuidoost",
    "sg:orig_category":"Koeriersdiensten",
    "sg:phone":"+31 20 609 0720",
    "sg:postcode":"1106 BB",
    "sg:province":"Noord-Holland",
    "wof:name":"Flash Couriers",
    "wof:placetype":"venue"
},
  "geometry": {"coordinates":[4.978819,52.300106],"type":"Point"}
}