{
  "type": "Feature",
  "properties": {
    "iso:country":"NL",
    "sg:address":"Plenkertstraat 46",
    "sg:city":"Valkenburg Lb",
    "sg:classifiers":[
        {
            "category":"Fast Food",
            "type":"Food & Drink"
        }
    ],
    "sg:phone":"+31 43 601 2576",
    "sg:postcode":"6301 GM",
    "sg:province":"Limburg",
    "sg:tags":[
        "afhaal",
        "restaurant"
    ],
    "wof:name":"Chinees Indisch Restaurant China",
    "wof:placetype":"venue"
},
  "geometry": {"coordinates":[5.827613,50.864555],"type":"Point"}
}