{
  "type": "Feature",
  "properties": {
    "addr:full":"Prandinga 10 Oosterwolde Fr Friesland 8431 VP",
    "addr:housenumber":"10",
    "addr:postcode":"8431 vp",
    "addr:street":"Prandinga",
    "iso:country":"NL",
    "sg:address":"Prandinga 10",
    "sg:city":"Oosterwolde Fr",
    "sg:orig_category":"Elektrotechnische Apparatuur - Fabrieken En Groothandel",
    "sg:phone":"+31 516 513 839",
    "sg:postcode":"8431 VP",
    "sg:province":"Friesland",
    "wof:name":"Terpstra Bv",
    "wof:placetype":"venue"
},
  "geometry": {"coordinates":[6.280635,52.99638],"type":"Point"}
}