{
  "type": "Feature",
  "properties": {
    "addr:full":"Heythuyserwg 12A Horn Limburg 6085 NH",
    "addr:housenumber":"12a",
    "addr:postcode":"6085 nh",
    "addr:street":"Heythuyserwg",
    "iso:country":"NL",
    "sg:address":"Heythuyserwg 12A",
    "sg:city":"Horn",
    "sg:orig_category":"Kampeerartikelen",
    "sg:phone":"+31 475 582 367",
    "sg:postcode":"6085 NH",
    "sg:province":"Limburg",
    "wof:name":"Eilers, Gonja",
    "wof:placetype":"venue"
},
  "geometry": {"coordinates":[-103.4397277832,42.765663147],"type":"Point"}
}