{
  "type": "Feature",
  "properties": {
    "addr:full":"Schouwsedijk 1 Brouwershaven Zeeland 4318 TM",
    "addr:housenumber":"1",
    "addr:postcode":"4318 tm",
    "addr:street":"Schouwsedijk",
    "iso:country":"NL",
    "sg:address":"Schouwsedijk 1",
    "sg:city":"Brouwershaven",
    "sg:orig_category":"Kampeerterreinen",
    "sg:phone":"+31 111 691 223",
    "sg:postcode":"4318 TM",
    "sg:province":"Zeeland",
    "wof:name":"Camping Noorder Nieuwland",
    "wof:placetype":"venue"
},
  "geometry": {"coordinates":[3.907761097,51.7301635742],"type":"Point"}
}