{
  "type": "Feature",
  "properties": {
    "iso:country":"NL",
    "sg:address":"Van Oldenbarneveltlaan 73",
    "sg:city":"Hilversum",
    "sg:orig_category":"Kappers",
    "sg:phone":"+31 35 624 9431",
    "sg:postcode":"1215 GE",
    "sg:province":"Noord-Holland",
    "wof:name":"Dameskapsalon Lamme",
    "wof:placetype":"venue"
},
  "geometry": {"coordinates":[5.1598510742,52.2147598267],"type":"Point"}
}