{
  "type": "Feature",
  "properties": {
    "addr:full":"Mauritsweg 22 Renesse Zeeland 4325 AH",
    "addr:housenumber":"22",
    "addr:postcode":"4325 ah",
    "addr:street":"Mauritsweg",
    "iso:country":"NL",
    "sg:address":"Mauritsweg 22",
    "sg:city":"Renesse",
    "sg:orig_category":"Bloemen And Planten Gh",
    "sg:phone":"+31 111 461 204",
    "sg:postcode":"4325 AH",
    "sg:province":"Zeeland",
    "wof:name":"South American Flower",
    "wof:placetype":"venue"
},
  "geometry": {"coordinates":[3.777982,51.732368],"type":"Point"}
}