{
  "type": "Feature",
  "properties": {
    "addr:full":"H. De Grootplein 10 Amsterdam West Noord-Holland 1052 KW",
    "addr:housenumber":"10",
    "addr:postcode":"1052 kw",
    "addr:street":"H. De Grootplein",
    "iso:country":"NL",
    "sg:address":"H. De Grootplein 10",
    "sg:city":"Amsterdam West",
    "sg:classifiers":[
        {
            "category":"Food & Beverages",
            "subcategory":"Fruits & Vegetables",
            "type":"Retail Goods"
        }
    ],
    "sg:phone":"+31 20 684 5017",
    "sg:postcode":"1052 KW",
    "sg:province":"Noord-Holland",
    "sg:tags":[
        "groenten"
    ],
    "wof:name":"M. A. M. El-Shal",
    "wof:placetype":"venue"
},
  "geometry": {"coordinates":[4.873241,52.374802],"type":"Point"}
}