{
  "type": "Feature",
  "properties": {
    "iso:country":"NL",
    "sg:address":"Leliegr 21",
    "sg:city":"Amsterdam",
    "sg:orig_category":"Filmstudio'S En -Productie",
    "sg:phone":"+31 20 620 2485",
    "sg:postcode":"1016 GR",
    "sg:province":"Noord-Holland",
    "sg:website":"http://www.keos.com",
    "wof:name":"Keos Bv",
    "wof:placetype":"venue"
},
  "geometry": {"coordinates":[4.886463,52.374969],"type":"Point"}
}