{
  "type": "Feature",
  "properties": {
    "iso:country":"NL",
    "sg:address":"Vletstr 41",
    "sg:city":"Rotterdam",
    "sg:classifiers":[
        {
            "category":"Retail",
            "subcategory":"Auto Repair",
            "type":"Services"
        }
    ],
    "sg:phone":"+31 10 465 9522",
    "sg:postcode":"3035 ZB",
    "sg:province":"Zuid-Holland",
    "sg:tags":[
        "garage"
    ],
    "wof:name":"Quick Servicebedrijf Vof",
    "wof:placetype":"venue"
},
  "geometry": {"coordinates":[4.484948,51.933449],"type":"Point"}
}