{
  "type": "Feature",
  "properties": {
    "addr:full":"Randenbroekerweg 56 Amersfoort Utrecht 3816 BK",
    "addr:housenumber":"56",
    "addr:postcode":"3816 bk",
    "addr:street":"Randenbroekerweg",
    "iso:country":"NL",
    "sg:address":"Randenbroekerweg 56",
    "sg:city":"Amersfoort",
    "sg:orig_category":"Schilderwerk",
    "sg:phone":"+31 33 475 0259",
    "sg:postcode":"3816 BK",
    "sg:province":"Utrecht",
    "wof:name":"E.F. Van Slooten",
    "wof:placetype":"venue"
},
  "geometry": {"coordinates":[5.404983,52.154285],"type":"Point"}
}