{
  "type": "Feature",
  "properties": {
    "addr:full":"Geldropseweg 63 Eindhoven North Brabant 5611 SE",
    "addr:housenumber":"63",
    "addr:postcode":"5611 se",
    "addr:street":"Geldropseweg",
    "iso:country":"NL",
    "sg:address":"Geldropseweg 63",
    "sg:city":"Eindhoven",
    "sg:orig_category":"Binnenhuisarchitecten",
    "sg:phone":"+31 40 211 2891",
    "sg:postcode":"5611 SE",
    "sg:province":"North Brabant",
    "wof:name":"Pennings Binnenhuisarchitect",
    "wof:placetype":"venue"
},
  "geometry": {"coordinates":[5.488488,51.43383],"type":"Point"}
}