{
  "type": "Feature",
  "properties": {
    "iso:country":"NL",
    "sg:address":"Hoofdstraat 193",
    "sg:city":"Voorthuizen",
    "sg:classifiers":[
        {
            "category":"Communications",
            "subcategory":"Television Station",
            "type":"Services"
        }
    ],
    "sg:phone":"+31 342 475 387",
    "sg:postcode":"3781 AE",
    "sg:province":"Gelderland",
    "sg:tags":[
        "video",
        "audio",
        "verhuur"
    ],
    "wof:name":"Videotheek Surprise",
    "wof:placetype":"venue"
},
  "geometry": {"coordinates":[5.608819,52.187466],"type":"Point"}
}