{
  "type": "Feature",
  "properties": {
    "addr:full":"V Bonninghaus Str 24 Tubbergen Overijssel 7651 AB",
    "addr:housenumber":"24",
    "addr:postcode":"7651 ab",
    "addr:street":"Str",
    "iso:country":"NL",
    "sg:address":"V Bonninghaus Str 24",
    "sg:city":"Tubbergen",
    "sg:orig_category":"Meubelen - Fabrieken En Groothandel",
    "sg:phone":"+31 546 624 402",
    "sg:postcode":"7651 AB",
    "sg:province":"Overijssel",
    "wof:name":"Stindo",
    "wof:placetype":"venue"
},
  "geometry": {"coordinates":[6.782,52.405697],"type":"Point"}
}