{
  "type": "Feature",
  "properties": {
    "iso:country":"NL",
    "sg:address":"A Blamanstr 32",
    "sg:city":"Alkmaar",
    "sg:orig_category":"Adviesbureaus Bedrijfsorganisatie",
    "sg:phone":"+31 72 562 0796",
    "sg:postcode":"1827 LX",
    "sg:province":"Noord-Holland",
    "wof:name":"Lienen, Van",
    "wof:placetype":"venue"
},
  "geometry": {"coordinates":[4.768718,52.668404],"type":"Point"}
}