{
  "type": "Feature",
  "properties": {
    "addr:full":"Dorpsstr 17 Ouderkerk Amstel North Holland 1191 BH",
    "addr:housenumber":"17",
    "addr:postcode":"1191 bh",
    "addr:street":"Dorpsstr;Ouderkerk Amstel",
    "iso:country":"NL",
    "sg:address":"Dorpsstr 17",
    "sg:city":"Ouderkerk Amstel",
    "sg:orig_category":"Bloemen En Planten",
    "sg:phone":"+31 20 496 3310",
    "sg:postcode":"1191 BH",
    "sg:province":"North Holland",
    "wof:name":"Roza",
    "wof:placetype":"venue"
},
  "geometry": {"coordinates":[4.903042,52.296928],"type":"Point"}
}