{
  "type": "Feature",
  "properties": {
    "addr:full":"Bosstraat 248 Nieuw Vennep Noord-Holland 2153 AW",
    "addr:housenumber":"248",
    "addr:postcode":"2153 aw",
    "addr:street":"Bosstraat;Nieuw Vennep",
    "iso:country":"NL",
    "sg:address":"Bosstraat 248",
    "sg:city":"Nieuw Vennep",
    "sg:orig_category":"Loodgieterswerk, Verwarming And Sanitaire Installaties",
    "sg:phone":"+31 252 675 234",
    "sg:postcode":"2153 AW",
    "sg:province":"Noord-Holland",
    "wof:name":"Vof M. Van Den Bos",
    "wof:placetype":"venue"
},
  "geometry": {"coordinates":[4.642444,52.262253],"type":"Point"}
}