{
  "type": "Feature",
  "properties": {
    "addr:full":"Zomertuin 9 Laren Nh Noord-Holland 1251 LZ",
    "addr:housenumber":"9",
    "addr:postcode":"1251 lz",
    "addr:street":"Zomertuin",
    "iso:country":"NL",
    "sg:address":"Zomertuin 9",
    "sg:city":"Laren Nh",
    "sg:orig_category":"Schoenen",
    "sg:phone":"+31 35 602 2322",
    "sg:postcode":"1251 LZ",
    "sg:province":"Noord-Holland",
    "sg:website":"http://www.timothyshoes.nl",
    "wof:name":"Timothy",
    "wof:placetype":"venue"
},
  "geometry": {"coordinates":[5.224216,52.255844],"type":"Point"}
}