{
  "type": "Feature",
  "properties": {
    "addr:full":"Hoogstr 130 Goirle Noord-Brabant 5051 RX",
    "addr:housenumber":"130",
    "addr:postcode":"goirle;5051 rx",
    "iso:country":"NL",
    "sg:address":"Hoogstr 130",
    "sg:city":"Goirle",
    "sg:orig_category":"Verbouwingen",
    "sg:phone":"+31 13 534 0468",
    "sg:postcode":"5051 RX",
    "sg:province":"Noord-Brabant",
    "wof:name":"Amelsfort/Verhoeven, Van",
    "wof:placetype":"venue"
},
  "geometry": {"coordinates":[5.060977,51.521629],"type":"Point"}
}