{
  "type": "Feature",
  "properties": {
    "iso:country":"NL",
    "sg:address":"Croonenburgh 110",
    "sg:city":"Oud Beyerland",
    "sg:orig_category":"Autorijscholen",
    "sg:phone":"+31 186 614 673",
    "sg:postcode":"3261 RJ",
    "sg:province":"South Holland",
    "wof:name":"Jong Verkeersschool, Jo 'T",
    "wof:placetype":"venue"
},
  "geometry": {"coordinates":[4.419042,51.818966],"type":"Point"}
}