{
  "type": "Feature",
  "properties": {
    "iso:country":"NL",
    "sg:address":"Mensinge 12",
    "sg:city":"Almelo",
    "sg:orig_category":"Verpakkingen En Verpakkingsmaterialen",
    "sg:phone":"+31 546 473 755",
    "sg:postcode":"7608 AV",
    "sg:province":"NL.08",
    "sg:website":"HTTP://www.janvangroningen.nl",
    "wof:name":"Groningen, Jan Van",
    "wof:placetype":"venue"
},
  "geometry": {"coordinates":[6.688002,52.381561],"type":"Point"}
}