{
  "type": "Feature",
  "properties": {
    "addr:full":"Zuidergr 56 Soest Utrecht 3763 LW",
    "addr:housenumber":"56",
    "addr:postcode":"3763 lw",
    "addr:street":"Zuidergr",
    "iso:country":"NL",
    "sg:address":"Zuidergr 56",
    "sg:city":"Soest",
    "sg:orig_category":"Grondwerken",
    "sg:phone":"+31 35 601 5175",
    "sg:postcode":"3763 LW",
    "sg:province":"Utrecht",
    "wof:name":"Dorresteijn Bv, H G Van",
    "wof:placetype":"venue"
},
  "geometry": {"coordinates":[5.262542,52.176983],"type":"Point"}
}