{
  "type": "Feature",
  "properties": {
    "addr:full":"Hekelen 24 Oudewater Utrecht 3421 JW",
    "addr:housenumber":"24",
    "addr:postcode":"3421 jw",
    "addr:street":"Hekelen",
    "iso:country":"NL",
    "sg:address":"Hekelen 24",
    "sg:city":"Oudewater",
    "sg:orig_category":"Boekhouders",
    "sg:phone":"+31 348 561 445",
    "sg:postcode":"3421 JW",
    "sg:province":"Utrecht",
    "wof:name":"R. Spijkers-Van Brunschot",
    "wof:placetype":"venue"
},
  "geometry": {"coordinates":[4.872338,52.028652],"type":"Point"}
}