{
  "type": "Feature",
  "properties": {
    "addr:full":"Noorderlicht 75 Amersfoort Utrecht 3824 EC",
    "addr:housenumber":"75",
    "addr:postcode":"3824 ec",
    "addr:street":"Noorderlicht",
    "iso:country":"NL",
    "sg:address":"Noorderlicht 75",
    "sg:city":"Amersfoort",
    "sg:orig_category":"Orthopedagogen",
    "sg:phone":"+31 33 456 4662",
    "sg:postcode":"3824 EC",
    "sg:province":"Utrecht",
    "wof:name":"Emaus, Drs H J M",
    "wof:placetype":"venue"
},
  "geometry": {"coordinates":[5.378267765,52.1992874146],"type":"Point"}
}