{
  "type": "Feature",
  "properties": {
    "iso:country":"NL",
    "sg:address":"Ooievaarswg 23",
    "sg:city":"Nieuwe Niedorp",
    "sg:orig_category":"Bloembollen - Groothandel",
    "sg:phone":"+31 226 411 319",
    "sg:postcode":"1733 NH",
    "sg:province":"North Holland",
    "wof:name":"Deen, Fa Gebr",
    "wof:placetype":"venue"
},
  "geometry": {"coordinates":[4.923264,52.738533],"type":"Point"}
}