{
  "type": "Feature",
  "properties": {
    "addr:full":"J V Stolbergln 90A Rotterdam South Holland 3051 CK",
    "addr:housenumber":"90a",
    "addr:postcode":"3051 ck",
    "addr:street":"J;Stolbergln",
    "iso:country":"NL",
    "sg:address":"J V Stolbergln 90A",
    "sg:city":"Rotterdam",
    "sg:orig_category":"Onderhoudswerken",
    "sg:phone":"+31 10 461 2892",
    "sg:postcode":"3051 CK",
    "sg:province":"South Holland",
    "wof:name":"Technobouw",
    "wof:placetype":"venue"
},
  "geometry": {"coordinates":[4.4782,51.945049],"type":"Point"}
}