{
  "type": "Feature",
  "properties": {
    "addr:full":"Abeelstraat 30 'S Gravenhage South Holland 2565 XP",
    "addr:housenumber":"30",
    "addr:postcode":"2565 xp",
    "addr:street":"Abeelstraat;' S Gravenhage",
    "iso:country":"NL",
    "sg:address":"Abeelstraat 30",
    "sg:city":"'S Gravenhage",
    "sg:classifiers":[
        {
            "category":"Education",
            "subcategory":"Preschool",
            "type":"Public Place"
        }
    ],
    "sg:phone":"+31 70 360 7053",
    "sg:postcode":"2565 XP",
    "sg:province":"South Holland",
    "sg:tags":[
        "kleuteronderwijs",
        "basis-"
    ],
    "wof:name":"Christelijke Montessorischool",
    "wof:placetype":"venue"
},
  "geometry": {"coordinates":[4.268575,52.077721],"type":"Point"}
}