{
  "type": "Feature",
  "properties": {
    "iso:country":"NL",
    "sg:address":"Borculosewg 3",
    "sg:city":"Barchem",
    "sg:orig_category":"Fietsen En Bromfietsen Verhuur",
    "sg:phone":"+31 573 441 258",
    "sg:postcode":"7244 AR",
    "sg:province":"Arkansas",
    "wof:name":"Koeleman Barchem",
    "wof:placetype":"venue"
},
  "geometry": {"coordinates":[-92.131348,34.751888],"type":"Point"}
}