{
  "type": "Feature",
  "properties": {
    "addr:full":"Burg V Udenstr 3 Budel Noord-Brabant 6021 AK",
    "addr:housenumber":"3",
    "addr:postcode":"6021 ak",
    "addr:street":"Burg V Udenstr",
    "iso:country":"NL",
    "sg:address":"Burg V Udenstr 3",
    "sg:city":"Budel",
    "sg:orig_category":"Schoonheidsinstituten",
    "sg:phone":"+31 495 430 236",
    "sg:postcode":"6021 AK",
    "sg:province":"Noord-Brabant",
    "wof:name":"Feron",
    "wof:placetype":"venue"
},
  "geometry": {"coordinates":[5.576494,51.274277],"type":"Point"}
}