{
  "type": "Feature",
  "properties": {
    "addr:full":"J J Vorrinkstr 12 Papendrecht South Holland 3354 AM",
    "addr:housenumber":"12",
    "addr:postcode":"3354",
    "iso:country":"NL",
    "sg:address":"J J Vorrinkstr 12",
    "sg:city":"Papendrecht",
    "sg:orig_category":"Schoonheidsinstituten",
    "sg:phone":"+31 78 615 9218",
    "sg:postcode":"3354 AM",
    "sg:province":"South Holland",
    "sg:website":"http://www.faceline.nl",
    "wof:name":"Face Line",
    "wof:placetype":"venue"
},
  "geometry": {"coordinates":[4.702995,51.829109],"type":"Point"}
}