{
  "type": "Feature",
  "properties": {
    "iso:country":"NL",
    "sg:address":"Hastelweg 250",
    "sg:city":"Eindhoven",
    "sg:orig_category":"Kantoorartikelen",
    "sg:phone":"+31 40 256 9200",
    "sg:postcode":"5652 CN",
    "sg:province":"Noord-Brabant",
    "wof:name":"Kantoormeubelland",
    "wof:placetype":"venue"
},
  "geometry": {"coordinates":[5.4364590645,51.4369125366],"type":"Point"}
}