{
  "type": "Feature",
  "properties": {
    "addr:full":"Herenwg 36 Spanbroek Noord-Holland 1715 EH",
    "addr:housenumber":"36",
    "addr:postcode":"1715 eh",
    "addr:street":"Herenwg",
    "iso:country":"NL",
    "sg:address":"Herenwg 36",
    "sg:city":"Spanbroek",
    "sg:classifiers":[
        {
            "category":"Food & Beverages",
            "subcategory":"Fruits & Vegetables",
            "type":"Retail Goods"
        }
    ],
    "sg:phone":"+31 226 353 545",
    "sg:postcode":"1715 EH",
    "sg:province":"Noord-Holland",
    "sg:tags":[
        "en",
        "groenten"
    ],
    "wof:name":"Buysman, M M",
    "wof:placetype":"venue"
},
  "geometry": {"coordinates":[4.946975,52.700771],"type":"Point"}
}