{
  "type": "Feature",
  "properties": {
    "addr:full":"Krachtveld 24 Almere Flevoland 1359 KH",
    "addr:housenumber":"24",
    "addr:postcode":"1359 kh",
    "addr:street":"Krachtveld;Flevoland",
    "iso:country":"NL",
    "sg:address":"Krachtveld 24",
    "sg:city":"Almere",
    "sg:orig_category":"Verenigingen En Stichtingen",
    "sg:phone":"+31 36 537 4689",
    "sg:postcode":"1359 KH",
    "sg:province":"Flevoland",
    "wof:name":"Turning Spirit Almere",
    "wof:placetype":"venue"
},
  "geometry": {"coordinates":[5.195823,52.338676],"type":"Point"}
}