{
  "type": "Feature",
  "properties": {
    "addr:full":"Ampereln 1 Drachten Friesland 9207 AM",
    "addr:housenumber":"1",
    "addr:postcode":"9207",
    "addr:street":"Ampereln",
    "iso:country":"NL",
    "sg:address":"Ampereln 1",
    "sg:city":"Drachten",
    "sg:orig_category":"Adviesbureaus Bouwkunde",
    "sg:phone":"+31 512 589 831",
    "sg:postcode":"9207 AM",
    "sg:province":"Friesland",
    "sg:website":"http://www.via-tva.nl",
    "wof:name":"Via Advies",
    "wof:placetype":"venue"
},
  "geometry": {"coordinates":[6.135265,53.109901],"type":"Point"}
}