{
  "type": "Feature",
  "properties": {
    "addr:full":"Kamperstr 11-13 Zwolle Overijssel 8011 LJ",
    "addr:housenumber":"11-13",
    "addr:postcode":"8011 lj",
    "iso:country":"NL",
    "sg:address":"Kamperstr 11-13",
    "sg:city":"Zwolle",
    "sg:orig_category":"Verenigingen En Stichtingen",
    "sg:phone":"+31 38 422 5030",
    "sg:postcode":"8011 LJ",
    "sg:province":"Overijssel",
    "sg:website":"http://www.kco.nl",
    "wof:name":"Kunst & Cultuur Overijssel",
    "wof:placetype":"venue"
},
  "geometry": {"coordinates":[6.089795,52.511246],"type":"Point"}
}