{
  "type": "Feature",
  "properties": {
    "addr:full":"A V Hensbeeksngl 399 Gouda Zuid-Holland 2803 LW",
    "addr:housenumber":"399",
    "addr:postcode":"2803 lw",
    "addr:street":"A;Hensbeeksngl",
    "iso:country":"NL",
    "sg:address":"A V Hensbeeksngl 399",
    "sg:city":"Gouda",
    "sg:orig_category":"Kappers",
    "sg:phone":"+31 182 539 478",
    "sg:postcode":"2803 LW",
    "sg:province":"Zuid-Holland",
    "wof:name":"Hazendonk, Van",
    "wof:placetype":"venue"
},
  "geometry": {"coordinates":[4.710714817,52.0100059509],"type":"Point"}
}