{
  "type": "Feature",
  "properties": {
    "addr:full":"Leidsekade 72 Amsterdam North Holland 1016 DA",
    "addr:housenumber":"72",
    "addr:postcode":"1016 da",
    "addr:street":"Leidsekade",
    "iso:country":"NL",
    "sg:address":"Leidsekade 72",
    "sg:city":"Amsterdam",
    "sg:orig_category":"Werving And Selectie Van Tijdelijk Personeel And Uitzendkantoren",
    "sg:phone":"+31 20 623 9191",
    "sg:postcode":"1016 DA",
    "sg:province":"North Holland",
    "wof:name":"Hospitality Services",
    "wof:placetype":"venue"
},
  "geometry": {"coordinates":[4.8797659874,52.3653831482],"type":"Point"}
}