{
  "type": "Feature",
  "properties": {
    "iso:country":"NL",
    "sg:address":"Cronjestr 17",
    "sg:city":"Amsterdam",
    "sg:orig_category":"Onderhoudswerken",
    "sg:phone":"+31 6 10921398",
    "sg:postcode":"1092 JC",
    "sg:province":"North Holland",
    "wof:name":"Quinfel",
    "wof:placetype":"venue"
},
  "geometry": {"coordinates":[4.922329,52.352894],"type":"Point"}
}