{
  "type": "Feature",
  "properties": {
    "addr:full":"C Bakker V Bossestr 40 Eindhoven Noord-Brabant 5612 SB",
    "addr:housenumber":"40",
    "addr:postcode":"5612 sb",
    "addr:street":"C;Bossestr",
    "iso:country":"NL",
    "sg:address":"C Bakker V Bossestr 40",
    "sg:city":"Eindhoven",
    "sg:orig_category":"Overheidsdiensten",
    "sg:phone":"+31 40 244 3547",
    "sg:postcode":"5612 SB",
    "sg:province":"Noord-Brabant",
    "wof:name":"Interwater",
    "wof:placetype":"venue"
},
  "geometry": {"coordinates":[5.4841051102,51.4344711304],"type":"Point"}
}