{
  "type": "Feature",
  "properties": {
    "addr:full":"Harddraverslaan 24 Santpoort-Zuid North Holland 2082 HM",
    "addr:housenumber":"24",
    "addr:postcode":"2082 hm",
    "addr:street":"Harddraverslaan",
    "iso:country":"NL",
    "sg:address":"Harddraverslaan 24",
    "sg:city":"Santpoort-Zuid",
    "sg:orig_category":"Public Relationbureaus",
    "sg:phone":"+31 23 538 2463",
    "sg:postcode":"2082 HM",
    "sg:province":"North Holland",
    "wof:name":"Hurts Communicatie Advies Bv",
    "wof:placetype":"venue"
},
  "geometry": {"coordinates":[4.633901,52.422302],"type":"Point"}
}