{
  "type": "Feature",
  "properties": {
    "iso:country":"NL",
    "sg:address":"Peizerweg 261",
    "sg:city":"Groningen",
    "sg:orig_category":"Begrafenisondernemers",
    "sg:phone":"+31 50 525 1800",
    "sg:postcode":"9744 BD",
    "sg:province":"Groningen",
    "wof:name":"H.H. Hulzebus Grafkisten En Rouwautobedr",
    "wof:placetype":"venue"
},
  "geometry": {"coordinates":[6.53169,53.204659],"type":"Point"}
}