{
  "type": "Feature",
  "properties": {
    "addr:full":"Hoogstr 118B Eindhoven Noord-Brabant 5615 PT",
    "addr:housenumber":"118b",
    "addr:postcode":"5615 pt",
    "iso:country":"NL",
    "sg:address":"Hoogstr 118B",
    "sg:city":"Eindhoven",
    "sg:orig_category":"Artsen - Huisartsen",
    "sg:phone":"+31 40 251 7583",
    "sg:postcode":"5615 PT",
    "sg:province":"Noord-Brabant",
    "wof:name":"Zuurmond, P V L",
    "wof:placetype":"venue"
},
  "geometry": {"coordinates":[5.484105,51.434471],"type":"Point"}
}