{
  "type": "Feature",
  "properties": {
    "addr:full":"Heike 19 Veldhoven Noord-Brabant 5508 PA",
    "addr:housenumber":"19",
    "addr:postcode":"5508 pa",
    "addr:street":"Heike",
    "iso:country":"NL",
    "sg:address":"Heike 19",
    "sg:city":"Veldhoven",
    "sg:classifiers":[
        {
            "category":"Education",
            "subcategory":"Preschool",
            "type":"Public Place"
        }
    ],
    "sg:phone":"+31 40 253 2774",
    "sg:postcode":"5508 PA",
    "sg:province":"Noord-Brabant",
    "sg:tags":[
        "kleuteronderwijs",
        "basis-"
    ],
    "wof:name":"Prof. Dr. R. Casimirschool",
    "wof:placetype":"venue"
},
  "geometry": {"coordinates":[5.39644,51.424522],"type":"Point"}
}