{
  "type": "Feature",
  "properties": {
    "addr:full":"Emingaheerd 108 Groningen Groningen 9737 GA",
    "addr:housenumber":"108",
    "addr:postcode":"9737 ga",
    "addr:street":"Emingaheerd",
    "iso:country":"NL",
    "sg:address":"Emingaheerd 108",
    "sg:city":"Groningen",
    "sg:orig_category":"Kappers",
    "sg:phone":"+31 50 542 2177",
    "sg:postcode":"9737 GA",
    "sg:province":"Groningen",
    "wof:name":"Haarstudio Ergoline",
    "wof:placetype":"venue"
},
  "geometry": {"coordinates":[6.5908961296,53.2443199158],"type":"Point"}
}