{
  "type": "Feature",
  "properties": {
    "addr:full":"Dorpsstr 12 Goudswaard Zuid-Holland 3267 AG",
    "addr:housenumber":"12",
    "addr:postcode":"3267",
    "addr:street":"Dorpsstr",
    "iso:country":"NL",
    "sg:address":"Dorpsstr 12",
    "sg:city":"Goudswaard",
    "sg:orig_category":"Geluidsinstallaties - Verhuur",
    "sg:phone":"+31 186 613 933",
    "sg:postcode":"3267 AG",
    "sg:province":"Zuid-Holland",
    "wof:name":"Andeweg Rental Bv",
    "wof:placetype":"venue"
},
  "geometry": {"coordinates":[4.273546,51.795898],"type":"Point"}
}