{
  "type": "Feature",
  "properties": {
    "iso:country":"NL",
    "sg:address":"Balladestraat 143",
    "sg:city":"Nijmegen",
    "sg:orig_category":"Bedrijfs- And Managementsconsultants",
    "sg:phone":"+31 24 373 3426",
    "sg:postcode":"6544 WN",
    "sg:province":"Gelderland",
    "wof:name":"Data-Assist",
    "wof:placetype":"venue"
},
  "geometry": {"coordinates":[5.816349,51.828445],"type":"Point"}
}