{
  "type": "Feature",
  "properties": {
    "addr:full":"Nieuwe Binnenweg 316 Rotterdam South Holland 3021 GV",
    "addr:housenumber":"316",
    "addr:postcode":"3021 gv",
    "addr:street":"Nieuwe Binnenweg",
    "iso:country":"NL",
    "sg:address":"Nieuwe Binnenweg 316",
    "sg:city":"Rotterdam",
    "sg:classifiers":[
        {
            "category":"Communications",
            "subcategory":"Television Station",
            "type":"Services"
        }
    ],
    "sg:phone":"+31 10 478 1229",
    "sg:postcode":"3021 GV",
    "sg:province":"South Holland",
    "sg:tags":[
        "video",
        "audio",
        "verhuur"
    ],
    "wof:name":"Videotheek Chabab",
    "wof:placetype":"venue"
},
  "geometry": {"coordinates":[4.457291,51.912537],"type":"Point"}
}