{
  "type": "Feature",
  "properties": {
    "addr:full":"Vennestr 4D Lisse North Holland 2161 LE",
    "addr:housenumber":"4d",
    "addr:postcode":"2161 le",
    "iso:country":"NL",
    "sg:address":"Vennestr 4D",
    "sg:city":"Lisse",
    "sg:orig_category":"Kunststoffen- Verwerkende Industrie",
    "sg:phone":"+31 252 426 871",
    "sg:postcode":"2161 LE",
    "sg:province":"North Holland",
    "wof:name":"Minken",
    "wof:placetype":"venue"
},
  "geometry": {"coordinates":[4.553053,52.252033],"type":"Point"}
}