{
  "type": "Feature",
  "properties": {
    "addr:full":"Melkweg 47 Hoogeveen Drenthe 7904 ER",
    "addr:housenumber":"47",
    "addr:postcode":"7904 er",
    "addr:street":"Melkweg",
    "iso:country":"NL",
    "sg:address":"Melkweg 47",
    "sg:city":"Hoogeveen",
    "sg:orig_category":"Hoger Onderwijs",
    "sg:phone":"+31 528 264 190",
    "sg:postcode":"7904 ER",
    "sg:province":"Drenthe",
    "wof:name":"A. Van Doorn",
    "wof:placetype":"venue"
},
  "geometry": {"coordinates":[6.507676,52.723026],"type":"Point"}
}