{
  "type": "Feature",
  "properties": {
    "addr:full":"Texelstr 31 Eindhoven Noord-Brabant 5628 KV",
    "addr:housenumber":"31",
    "addr:postcode":"5628 kv",
    "addr:street":"Texelstr",
    "iso:country":"NL",
    "sg:address":"Texelstr 31",
    "sg:city":"Eindhoven",
    "sg:orig_category":"Kinderactiviteiten",
    "sg:phone":"+31 40 241 2181",
    "sg:postcode":"5628 KV",
    "sg:province":"Noord-Brabant",
    "wof:name":"Keil, D",
    "wof:placetype":"venue"
},
  "geometry": {"coordinates":[5.467288,51.477161],"type":"Point"}
}