{
  "type": "Feature",
  "properties": {
    "addr:full":"Lignestr 60 Made Minnesota 4921 EV",
    "addr:housenumber":"60",
    "addr:street":"Lignestr;Minnesota",
    "iso:country":"NL",
    "sg:address":"Lignestr 60",
    "sg:city":"Made",
    "sg:orig_category":"Verenigingen En Stichtingen",
    "sg:phone":"+31 162 684 990",
    "sg:postcode":"4921 EV",
    "sg:province":"Minnesota",
    "wof:name":"Katholiek Onderwijs Drimmelen, Sticht",
    "wof:placetype":"venue"
},
  "geometry": {"coordinates":[-94.36657,44.076088],"type":"Point"}
}