{
  "type": "Feature",
  "properties": {
    "iso:country":"NL",
    "sg:address":"Voorbancken 26",
    "sg:city":"Vinkeveen",
    "sg:orig_category":"Fitnesscentra",
    "sg:phone":"+31 297 264 666",
    "sg:postcode":"3645 GV",
    "sg:province":"Utrecht",
    "wof:name":"Pk Sport Vinkeveen",
    "wof:placetype":"venue"
},
  "geometry": {"coordinates":[4.919983,52.204239],"type":"Point"}
}