{
  "type": "Feature",
  "properties": {
    "addr:full":"Neuweg 223 Hilversum Noord-Holland 1214 GR",
    "addr:housenumber":"223",
    "addr:postcode":"1214",
    "addr:street":"Neuweg",
    "iso:country":"NL",
    "sg:address":"Neuweg 223",
    "sg:city":"Hilversum",
    "sg:classifiers":[
        {
            "category":"Food & Beverages",
            "subcategory":"Fruits & Vegetables",
            "type":"Retail Goods"
        }
    ],
    "sg:phone":"+31 35 621 0841",
    "sg:postcode":"1214 GR",
    "sg:province":"Noord-Holland",
    "sg:tags":[
        "groenten"
    ],
    "wof:name":"Jan Verwey Nv",
    "wof:placetype":"venue"
},
  "geometry": {"coordinates":[5.171928,52.216084],"type":"Point"}
}