{
  "type": "Feature",
  "properties": {
    "addr:full":"Noordhaven 66 Zevenbergen Noord-Brabant 4761 DB",
    "addr:housenumber":"66",
    "addr:postcode":"4761 db",
    "addr:street":"Noordhaven",
    "iso:country":"NL",
    "sg:address":"Noordhaven 66",
    "sg:city":"Zevenbergen",
    "sg:orig_category":"Verlichting And Huishoudartikelen",
    "sg:phone":"+31 168 324 515",
    "sg:postcode":"4761 DB",
    "sg:province":"Noord-Brabant",
    "wof:name":"Pieters Luxe- En Huish. Art.",
    "wof:placetype":"venue"
},
  "geometry": {"coordinates":[4.605444,51.645348],"type":"Point"}
}