{
  "type": "Feature",
  "properties": {
    "addr:full":"Frederik Hendriklaan 228 'S Gravenhage Zuid-Holland 2582 BL",
    "addr:housenumber":"228 '",
    "addr:postcode":"2582 bl",
    "addr:street":"Frederik Hendriklaan",
    "iso:country":"NL",
    "sg:address":"Frederik Hendriklaan 228",
    "sg:city":"'S Gravenhage",
    "sg:orig_category":"Verlichting And Huishoudartikelen",
    "sg:phone":"+31 70 355 9195",
    "sg:postcode":"2582 BL",
    "sg:province":"Zuid-Holland",
    "wof:name":"Spectrum Design",
    "wof:placetype":"venue"
},
  "geometry": {"coordinates":[4.274498,52.090855],"type":"Point"}
}