{
  "type": "Feature",
  "properties": {
    "addr:full":"Roserije 117 Maastricht Limburg 6228 DK",
    "addr:housenumber":"117",
    "addr:postcode":"6228 dk",
    "addr:street":"Roserije",
    "iso:country":"NL",
    "sg:address":"Roserije 117",
    "sg:city":"Maastricht",
    "sg:classifiers":[
        {
            "category":"Fast Food",
            "type":"Food & Drink"
        }
    ],
    "sg:phone":"+31 43 361 3454",
    "sg:postcode":"6228 DK",
    "sg:province":"Limburg",
    "sg:tags":[
        "afhaal",
        "restaurant"
    ],
    "wof:name":"Happy Meeting",
    "wof:placetype":"venue"
},
  "geometry": {"coordinates":[5.726345,50.827705],"type":"Point"}
}