{
  "type": "Feature",
  "properties": {
    "addr:full":"Bennebroekwg 1 Zoeterwoude Zuid-Holland 2381 BS",
    "addr:housenumber":"1",
    "addr:postcode":"2381 bs",
    "addr:street":"Bennebroekwg",
    "iso:country":"NL",
    "sg:address":"Bennebroekwg 1",
    "sg:city":"Zoeterwoude",
    "sg:orig_category":"Bejaarden - Verzorgingstehuizen",
    "sg:phone":"+31 71 580 9203",
    "sg:postcode":"2381 BS",
    "sg:province":"Zuid-Holland",
    "wof:name":"Stichting Zorgnet Groenwoude",
    "wof:placetype":"venue"
},
  "geometry": {"coordinates":[4.494874,52.119095],"type":"Point"}
}