{
  "type": "Feature",
  "properties": {
    "iso:country":"NL",
    "sg:address":"Groningerstraatweg 42",
    "sg:city":"Leeuwarden",
    "sg:orig_category":"Metaalwerken",
    "sg:phone":"+31 58 213 2988",
    "sg:postcode":"8921 TR",
    "sg:province":"Friesland",
    "wof:name":"Zonwering Correct",
    "wof:placetype":"venue"
},
  "geometry": {"coordinates":[5.805223,53.20829],"type":"Point"}
}