{
  "type": "Feature",
  "properties": {
    "addr:full":"V Maerlantln 4 Vlaardingen South Holland 3132 PS",
    "addr:housenumber":"4",
    "addr:postcode":"3132 ps",
    "addr:street":"Maerlantln",
    "iso:country":"NL",
    "sg:address":"V Maerlantln 4",
    "sg:city":"Vlaardingen",
    "sg:orig_category":"Verenigingen En Stichtingen",
    "sg:phone":"+31 10 434 3356",
    "sg:postcode":"3132 PS",
    "sg:province":"South Holland",
    "wof:name":"Sokkel, De",
    "wof:placetype":"venue"
},
  "geometry": {"coordinates":[4.340359,51.910442],"type":"Point"}
}