{
  "type": "Feature",
  "properties": {
    "addr:full":"Diemerzeedk 35 Amsterdam Noord-Holland 1095 KK",
    "addr:housenumber":"35",
    "addr:postcode":"1095 kk",
    "addr:street":"Diemerzeedk",
    "iso:country":"NL",
    "sg:address":"Diemerzeedk 35",
    "sg:city":"Amsterdam",
    "sg:orig_category":"Jachthavens - Jachtwerven",
    "sg:phone":"+31 20 665 5701",
    "sg:postcode":"1095 KK",
    "sg:province":"Noord-Holland",
    "sg:website":"http://www.epeek.nl",
    "wof:name":"E/Peek Jacht & Verkoophaven Bv",
    "wof:placetype":"venue"
},
  "geometry": {"coordinates":[4.968257,52.360596],"type":"Point"}
}