{
  "type": "Feature",
  "properties": {
    "addr:full":"Veerhuiswg 1 Donkerbroek Friesland 8435 SC",
    "addr:housenumber":"1",
    "addr:postcode":"8435 sc",
    "addr:street":"Veerhuiswg",
    "iso:country":"NL",
    "sg:address":"Veerhuiswg 1",
    "sg:city":"Donkerbroek",
    "sg:orig_category":"Parketvloeren",
    "sg:phone":"+31 516 491 345",
    "sg:postcode":"8435 SC",
    "sg:province":"Friesland",
    "sg:website":"http://www.qualityparket.nl",
    "wof:name":"Quality Parket",
    "wof:placetype":"venue"
},
  "geometry": {"coordinates":[-80.947441,33.624981],"type":"Point"}
}