{
  "type": "Feature",
  "properties": {
    "iso:country":"NL",
    "sg:address":"Dintelwg 39",
    "sg:city":"Europoort Rt",
    "sg:orig_category":"Loonbedrijven",
    "sg:phone":"+31 181 263 489",
    "sg:postcode":"3198 LB",
    "sg:province":"South Holland",
    "wof:name":"Liberco",
    "wof:placetype":"venue"
},
  "geometry": {"coordinates":[4.13754,51.935799],"type":"Point"}
}