{
  "type": "Feature",
  "properties": {
    "addr:full":"Flevostr 146 Purmerend Noord-Holland 1442 PZ",
    "addr:housenumber":"146",
    "addr:postcode":"1442 pz",
    "iso:country":"NL",
    "sg:address":"Flevostr 146",
    "sg:city":"Purmerend",
    "sg:orig_category":"Autopoetsbedrijven",
    "sg:phone":"+31 299 470 817",
    "sg:postcode":"1442 PZ",
    "sg:province":"Noord-Holland",
    "sg:website":"http://www.tompoets.nl",
    "wof:name":"Tompoets",
    "wof:placetype":"venue"
},
  "geometry": {"coordinates":[4.980642,52.518326],"type":"Point"}
}