{
  "type": "Feature",
  "properties": {
    "iso:country":"NL",
    "sg:address":"St Pieterstr 7",
    "sg:city":"Valkenburg Lb",
    "sg:orig_category":"Architecten En Architectenbureaus",
    "sg:phone":"+31 43 601 5688",
    "sg:postcode":"6301 DP",
    "sg:province":"Limburg",
    "wof:name":"Hurk, H A M Van Den",
    "wof:placetype":"venue"
},
  "geometry": {"coordinates":[5.83451,50.86441],"type":"Point"}
}