{
  "type": "Feature",
  "properties": {
    "iso:country":"NL",
    "sg:address":"Kerkerinklaan 23",
    "sg:city":"Santpoort-Noord",
    "sg:orig_category":"Kappers",
    "sg:phone":"+31 23 537 6402",
    "sg:postcode":"2071 RJ",
    "sg:province":"Rio de Janeiro",
    "wof:name":"Mod'Elle",
    "wof:placetype":"venue"
},
  "geometry": {"coordinates":[-42.9212,-22.06716],"type":"Point"}
}