{
  "type": "Feature",
  "properties": {
    "addr:full":"Melkkd 4 Coevorden Drenthe 7741 JS",
    "addr:housenumber":"4",
    "addr:postcode":"7741 js",
    "addr:street":"Melkkd",
    "iso:country":"NL",
    "sg:address":"Melkkd 4",
    "sg:city":"Coevorden",
    "sg:orig_category":"Accountants - Administratie- Consulenten En -Kantoren",
    "sg:phone":"+31 524 515 551",
    "sg:postcode":"7741 JS",
    "sg:province":"Drenthe",
    "wof:name":"Veldhuis Bv G H",
    "wof:placetype":"venue"
},
  "geometry": {"coordinates":[6.73891,52.6642],"type":"Point"}
}