{
  "type": "Feature",
  "properties": {
    "addr:full":"Libellenveld 2 Leiden South Holland 2318 VG",
    "addr:housenumber":"2",
    "addr:postcode":"2318 vg",
    "addr:street":"Libellenveld",
    "iso:country":"NL",
    "sg:address":"Libellenveld 2",
    "sg:city":"Leiden",
    "sg:orig_category":"Paramedische Behandelingen",
    "sg:phone":"+31 71 521 5369",
    "sg:postcode":"2318 VG",
    "sg:province":"South Holland",
    "wof:name":"A.H. Kobben-Van Vessem",
    "wof:placetype":"venue"
},
  "geometry": {"coordinates":[4.507515,52.180885],"type":"Point"}
}