{
  "type": "Feature",
  "properties": {
    "iso:country":"NL",
    "sg:address":"De Klim 7",
    "sg:city":"Drachten",
    "sg:orig_category":"Autoverhuur",
    "sg:phone":"+31 512 512 484",
    "sg:postcode":"9202 TM",
    "sg:province":"Friesland",
    "wof:name":"Kijlstra Drachten",
    "wof:placetype":"venue"
},
  "geometry": {"coordinates":[6.109638,53.105869],"type":"Point"}
}