{
  "type": "Feature",
  "properties": {
    "addr:full":"Dorpsstr 10 Gulpen Limburg 6271 BL",
    "addr:housenumber":"10",
    "addr:postcode":"6271 bl",
    "addr:street":"Dorpsstr",
    "iso:country":"NL",
    "sg:address":"Dorpsstr 10",
    "sg:city":"Gulpen",
    "sg:classifiers":[
        {
            "category":"Travel",
            "subcategory":"Hotels & Motels",
            "type":"Entertainment"
        }
    ],
    "sg:phone":"+31 43 450 1562",
    "sg:postcode":"6271 BL",
    "sg:province":"Limburg",
    "wof:name":"Holland Inn",
    "wof:placetype":"venue"
},
  "geometry": {"coordinates":[5.890606,50.816193],"type":"Point"}
}