{
  "type": "Feature",
  "properties": {
    "iso:country":"NL",
    "sg:address":"Jaartsveldstr 19",
    "sg:city":"Oldenzaal",
    "sg:orig_category":"Houtdraaierijen",
    "sg:phone":"+31 541 512 489",
    "sg:postcode":"7575 BP",
    "sg:province":"Overijssel",
    "wof:name":"Hazewinkel Houtwaren Vof",
    "wof:placetype":"venue"
},
  "geometry": {"coordinates":[6.926683,52.295685],"type":"Point"}
}