{
  "type": "Feature",
  "properties": {
    "addr:full":"Langelermaatweg 47 Hengelo (Ov) Overijssel 7553 JE",
    "addr:housenumber":"47",
    "addr:postcode":"7553 je",
    "addr:street":"Langelermaatweg;Ov",
    "iso:country":"NL",
    "sg:address":"Langelermaatweg 47",
    "sg:city":"Hengelo (Ov)",
    "sg:orig_category":"Verhuur Diversen",
    "sg:phone":"+31 74 242 5566",
    "sg:postcode":"7553 JE",
    "sg:province":"Overijssel",
    "wof:name":"Kulpe Hw",
    "wof:placetype":"venue"
},
  "geometry": {"coordinates":[6.793301,52.258484],"type":"Point"}
}