{
  "type": "Feature",
  "properties": {
    "addr:full":"F Daamenstr 45 Ulft Gelderland 7071 AV",
    "addr:housenumber":"45",
    "addr:postcode":"7071 av",
    "addr:street":"Gelderland",
    "iso:country":"NL",
    "sg:address":"F Daamenstr 45",
    "sg:city":"Ulft",
    "sg:orig_category":"Fietsen En Bromfietsen",
    "sg:phone":"+31 315 681 496",
    "sg:postcode":"7071 AV",
    "sg:province":"Gelderland",
    "wof:name":"Wim Van Meerveld",
    "wof:placetype":"venue"
},
  "geometry": {"coordinates":[6.378644,51.897339],"type":"Point"}
}