{
  "type": "Feature",
  "properties": {
    "addr:full":"Nieuwstraat 2 Hengelo Ov Overijssel 7551 CW",
    "addr:housenumber":"2",
    "addr:postcode":"7551 cw",
    "addr:street":"Nieuwstraat;Ov",
    "iso:country":"NL",
    "sg:address":"Nieuwstraat 2",
    "sg:city":"Hengelo Ov",
    "sg:orig_category":"Damesmodezaken",
    "sg:phone":"+31 74 291 3486",
    "sg:postcode":"7551 CW",
    "sg:province":"Overijssel",
    "wof:name":"Oostvogel Hengelo Bv",
    "wof:placetype":"venue"
},
  "geometry": {"coordinates":[6.789712,52.266361],"type":"Point"}
}