{
  "type": "Feature",
  "properties": {
    "addr:full":"Pothofweg 14 Anevelde Overijssel 7785 JB",
    "addr:housenumber":"14",
    "addr:postcode":"7785 jb",
    "addr:street":"Pothofweg",
    "iso:country":"NL",
    "sg:address":"Pothofweg 14",
    "sg:city":"Anevelde",
    "sg:orig_category":"Hoefdierhouderijen",
    "sg:phone":"+31 524 562 406",
    "sg:postcode":"7785 JB",
    "sg:province":"Overijssel",
    "wof:name":"Rosabella",
    "wof:placetype":"venue"
},
  "geometry": {"coordinates":[6.650257,52.597603],"type":"Point"}
}