{
  "type": "Feature",
  "properties": {
    "addr:full":"Roggelseweg 4 Haelen Limburg 6081 CT",
    "addr:housenumber":"4",
    "addr:postcode":"6081 ct",
    "addr:street":"Roggelseweg",
    "iso:country":"NL",
    "sg:address":"Roggelseweg 4",
    "sg:city":"Haelen",
    "sg:classifiers":[
        {
            "category":"Fast Food",
            "type":"Food & Drink"
        }
    ],
    "sg:phone":"+31 475 591 515",
    "sg:postcode":"6081 CT",
    "sg:province":"Limburg",
    "sg:tags":[
        "afhaal",
        "restaurant"
    ],
    "wof:name":"J.J.H. Smeets",
    "wof:placetype":"venue"
},
  "geometry": {"coordinates":[5.955324,51.23658],"type":"Point"}
}