{
  "type": "Feature",
  "properties": {
    "iso:country":"NL",
    "sg:address":"Dwarsvliet 13",
    "sg:city":"Zevenbergen",
    "sg:orig_category":"Boekhouders",
    "sg:phone":"+31 168 323 085",
    "sg:postcode":"4761 HV",
    "sg:province":"North Brabant",
    "wof:name":"Boekhoudbureau De Jager",
    "wof:placetype":"venue"
},
  "geometry": {"coordinates":[4.596389,51.650307],"type":"Point"}
}