{
  "type": "Feature",
  "properties": {
    "addr:full":"Dwarsvliet 13 Zevenbergen North Brabant 4761 HV",
    "addr:housenumber":"13",
    "addr:postcode":"4761 hv",
    "addr:street":"Dwarsvliet",
    "iso:country":"NL",
    "sg:address":"Dwarsvliet 13",
    "sg:city":"Zevenbergen",
    "sg:orig_category":"Boekhouders",
    "sg:phone":"+31 168 323 085",
    "sg:postcode":"4761 HV",
    "sg:province":"North Brabant",
    "wof:name":"Boekhoudbureau De Jager",
    "wof:placetype":"venue"
},
  "geometry": {"coordinates":[4.596389,51.650307],"type":"Point"}
}