{
  "type": "Feature",
  "properties": {
    "iso:country":"NL",
    "sg:address":"Batavenstraat 33",
    "sg:city":"Aalten",
    "sg:orig_category":"Zuivelproducten",
    "sg:phone":"+31 543 473 915",
    "sg:postcode":"7122 ZT",
    "sg:province":"Gelderland",
    "wof:name":"Vof Winkelhorst Zuivel",
    "wof:placetype":"venue"
},
  "geometry": {"coordinates":[6.577895,51.930313],"type":"Point"}
}