{
  "type": "Feature",
  "properties": {
    "iso:country":"NL",
    "sg:address":"Van Oldenbarneveldtstr 83",
    "sg:city":"Arnhem",
    "sg:orig_category":"Aannemers Woningbouw",
    "sg:phone":"+31 26 442 5080",
    "sg:postcode":"6828 ZN",
    "sg:province":"Gelderland",
    "wof:name":"Aannemersbedrijf J. Lusing",
    "wof:placetype":"venue"
},
  "geometry": {"coordinates":[5.921497,51.976334],"type":"Point"}
}