{
  "type": "Feature",
  "properties": {
    "addr:full":"Brink 64 Deventer NL.08 7411 BW",
    "addr:housenumber":"64;nl.08",
    "addr:postcode":"7411 bw",
    "addr:street":"Brink",
    "iso:country":"NL",
    "sg:address":"Brink 64",
    "sg:city":"Deventer",
    "sg:orig_category":"Fotojournalisten Freelance",
    "sg:phone":"+31 570 611 507",
    "sg:postcode":"7411 BW",
    "sg:province":"NL.08",
    "wof:name":"Bram Van Welsen",
    "wof:placetype":"venue"
},
  "geometry": {"coordinates":[6.159237,52.251114],"type":"Point"}
}