{
  "type": "Feature",
  "properties": {
    "addr:full":"Herikhof 29 Leusden Utrecht 3831 AN",
    "addr:housenumber":"29",
    "addr:postcode":"3831 an",
    "addr:street":"Herikhof",
    "iso:country":"NL",
    "sg:address":"Herikhof 29",
    "sg:city":"Leusden",
    "sg:orig_category":"Mensendieck - Oefentherapeuten",
    "sg:phone":"+31 33 494 3561",
    "sg:postcode":"3831 AN",
    "sg:province":"Utrecht",
    "wof:name":"Textor M D & V Diepen J M",
    "wof:placetype":"venue"
},
  "geometry": {"coordinates":[5.440188,52.139645],"type":"Point"}
}