{
  "type": "Feature",
  "properties": {
    "addr:full":"Noorderwg 68 Hilversum Noord-Holland 1221 AB",
    "addr:housenumber":"68",
    "addr:postcode":"1221 ab",
    "addr:street":"Noorderwg",
    "iso:country":"NL",
    "sg:address":"Noorderwg 68",
    "sg:city":"Hilversum",
    "sg:orig_category":"Arbo- En Bedrijfsgezondheids- Diensten",
    "sg:phone":"+31 35 688 0300",
    "sg:postcode":"1221 AB",
    "sg:province":"Noord-Holland",
    "wof:name":"Klm Bv",
    "wof:placetype":"venue"
},
  "geometry": {"coordinates":[5.18608,52.226601],"type":"Point"}
}