{
  "type": "Feature",
  "properties": {
    "addr:full":"J V Brabantln 43 Hilvarenbeek Noord-Brabant 5081 SC",
    "addr:housenumber":"43",
    "addr:postcode":"5081 sc",
    "addr:street":"J;Brabantln",
    "iso:country":"NL",
    "sg:address":"J V Brabantln 43",
    "sg:city":"Hilvarenbeek",
    "sg:orig_category":"Adviesbureaus Bouwkunde",
    "sg:phone":"+31 13 505 2404",
    "sg:postcode":"5081 SC",
    "sg:province":"Noord-Brabant",
    "wof:name":"Spil, Ir B C A",
    "wof:placetype":"venue"
},
  "geometry": {"coordinates":[5.136008,51.485294],"type":"Point"}
}