{
  "type": "Feature",
  "properties": {
    "addr:full":"Radarweg 511 Amsterdam Noord-Holland 1043 NZ",
    "addr:housenumber":"511",
    "addr:postcode":"1043 nz",
    "addr:street":"Radarweg",
    "iso:country":"NL",
    "sg:address":"Radarweg 511",
    "sg:city":"Amsterdam",
    "sg:orig_category":"Werving And Selectie Van Tijdelijk Personeel And Uitzendkantoren",
    "sg:phone":"+31 20 586 1190",
    "sg:postcode":"1043 NZ",
    "sg:province":"Noord-Holland",
    "wof:name":"Fhm Group",
    "wof:placetype":"venue"
},
  "geometry": {"coordinates":[4.8351812363,52.3853416443],"type":"Point"}
}