{
  "type": "Feature",
  "properties": {
    "addr:full":"Hoofdwg 39 Emst Gelderland 8166 AC",
    "addr:housenumber":"39",
    "addr:postcode":"8166 ac",
    "addr:street":"Hoofdwg;Gelderland",
    "iso:country":"NL",
    "sg:address":"Hoofdwg 39",
    "sg:city":"Emst",
    "sg:orig_category":"Postkantoren",
    "sg:phone":"+31 578 661 231",
    "sg:postcode":"8166 AC",
    "sg:province":"Gelderland",
    "sg:website":"http://www.postkantoor.nl",
    "wof:name":"Postkantoor",
    "wof:placetype":"venue"
},
  "geometry": {"coordinates":[5.975762,52.317986],"type":"Point"}
}