{
  "type": "Feature",
  "properties": {
    "iso:country":"NL",
    "sg:address":"Hoofdwg 39",
    "sg:city":"Emst",
    "sg:orig_category":"Postkantoren",
    "sg:phone":"+31 578 661 231",
    "sg:postcode":"8166 AC",
    "sg:province":"Gelderland",
    "sg:website":"http://www.postkantoor.nl",
    "wof:name":"Postkantoor",
    "wof:placetype":"venue"
},
  "geometry": {"coordinates":[5.975762,52.317986],"type":"Point"}
}