{
  "type": "Feature",
  "properties": {
    "addr:full":"Iewal 44 Woudsend Provincie Friesland 8551 PT",
    "addr:housenumber":"44",
    "addr:postcode":"8551",
    "addr:street":"Iewal;Provincie Friesland;Pt",
    "iso:country":"NL",
    "sg:address":"Iewal 44",
    "sg:city":"Woudsend",
    "sg:orig_category":"Pleziervaartuigen And Reparatie",
    "sg:phone":"+31 514 591 645",
    "sg:postcode":"8551 PT",
    "sg:province":"Provincie Friesland",
    "wof:name":"Technisch Watersportbedrijf Van Der Kooij",
    "wof:placetype":"venue"
},
  "geometry": {"coordinates":[5.629482,52.942253],"type":"Point"}
}