{
  "type": "Feature",
  "properties": {
    "iso:country":"NL",
    "sg:address":"Kuperswg 2X",
    "sg:city":"Wierden",
    "sg:orig_category":"Galeries",
    "sg:phone":"+31 546 579 156",
    "sg:postcode":"7641 AL",
    "sg:province":"Overijssel",
    "wof:name":"Petit Drokje",
    "wof:placetype":"venue"
},
  "geometry": {"coordinates":[6.589311,52.366524],"type":"Point"}
}