{
  "type": "Feature",
  "properties": {
    "iso:country":"NL",
    "sg:address":"Benedeneind Zuidzijde 357",
    "sg:city":"Benschop",
    "sg:orig_category":"Zuivelproducten And Spijsoli?n Gh",
    "sg:phone":"+31 348 452 100",
    "sg:postcode":"3405 CM",
    "sg:province":"Utrecht",
    "wof:name":"W Schep",
    "wof:placetype":"venue"
},
  "geometry": {"coordinates":[4.929528,51.999573],"type":"Point"}
}