{
  "type": "Feature",
  "properties": {
    "addr:full":"Zonnebaan 12 Utrecht Utrecht 3542 EC",
    "addr:housenumber":"12",
    "addr:postcode":"3542 ec",
    "addr:street":"Zonnebaan",
    "iso:country":"NL",
    "sg:address":"Zonnebaan 12",
    "sg:city":"Utrecht",
    "sg:orig_category":"Kunststofverpakkingen Fab",
    "sg:phone":"+31 30 241 2042",
    "sg:postcode":"3542 EC",
    "sg:province":"Utrecht",
    "wof:name":"Mediane International Bv",
    "wof:placetype":"venue"
},
  "geometry": {"coordinates":[5.042021,52.119297],"type":"Point"}
}