{
  "type": "Feature",
  "properties": {
    "addr:full":"Dorpsstr 193 Lunteren Gelderland 6741 AG",
    "addr:housenumber":"193",
    "addr:postcode":"6741",
    "addr:street":"Gelderland",
    "iso:country":"NL",
    "sg:address":"Dorpsstr 193",
    "sg:city":"Lunteren",
    "sg:orig_category":"Warenhuizen",
    "sg:phone":"+31 318 482 336",
    "sg:postcode":"6741 AG",
    "sg:province":"Gelderland",
    "wof:name":"Brr",
    "wof:placetype":"venue"
},
  "geometry": {"coordinates":[5.6185789108,52.0882225037],"type":"Point"}
}