{
  "type": "Feature",
  "properties": {
    "addr:full":"Einsteinstr 11 Hillegom North Holland 2181 AA",
    "addr:housenumber":"11",
    "addr:postcode":"2181 aa",
    "addr:street":"Einsteinstr",
    "iso:country":"NL",
    "sg:address":"Einsteinstr 11",
    "sg:city":"Hillegom",
    "sg:orig_category":"Verpakkingen En Verpakkingsmaterialen",
    "sg:phone":"+31 252 515 265",
    "sg:postcode":"2181 AA",
    "sg:province":"North Holland",
    "sg:website":"http://www.voges.nl",
    "wof:name":"Voges Bv",
    "wof:placetype":"venue"
},
  "geometry": {"coordinates":[4.587808,52.289284],"type":"Point"}
}