{
  "type": "Feature",
  "properties": {
    "addr:full":"Bloemenwg 5 Gaanderen Gelderland 7011 AH",
    "addr:housenumber":"5",
    "addr:postcode":"7011 ah",
    "addr:street":"Bloemenwg;Gelderland",
    "iso:country":"NL",
    "sg:address":"Bloemenwg 5",
    "sg:city":"Gaanderen",
    "sg:orig_category":"Woninginrichting",
    "sg:phone":"+31 315 323 615",
    "sg:postcode":"7011 AH",
    "sg:province":"Gelderland",
    "wof:name":"Koster Vof",
    "wof:placetype":"venue"
},
  "geometry": {"coordinates":[6.3487977982,51.9316902161],"type":"Point"}
}