{
  "type": "Feature",
  "properties": {
    "addr:full":"Churchillln 201 Helmond Noord-Brabant 5705 BK",
    "addr:housenumber":"201",
    "addr:postcode":"5705 bk",
    "iso:country":"NL",
    "sg:address":"Churchillln 201",
    "sg:city":"Helmond",
    "sg:orig_category":"Betonmortel",
    "sg:phone":"+31 492 537 800",
    "sg:postcode":"5705 BK",
    "sg:province":"Noord-Brabant",
    "wof:name":"Helmondse Betoncentr Bv",
    "wof:placetype":"venue"
},
  "geometry": {"coordinates":[5.658284,51.482239],"type":"Point"}
}