{
  "type": "Feature",
  "properties": {
    "iso:country":"NL",
    "sg:address":"Dr A Schweitzerln 17",
    "sg:city":"Purmerend",
    "sg:orig_category":"Geluidsinstallaties - Verhuur",
    "sg:phone":"+31 20 689 1339",
    "sg:postcode":"1443 WN",
    "sg:province":"Noord-Holland",
    "sg:website":"http://www.topmusicservice.nl",
    "wof:name":"Top Music Service",
    "wof:placetype":"venue"
},
  "geometry": {"coordinates":[4.94793,52.507607],"type":"Point"}
}