{
  "type": "Feature",
  "properties": {
    "addr:full":"St Ignatiusstr 217B Breda Noord-Brabant 4817 KJ",
    "addr:housenumber":"217b",
    "addr:postcode":"4817 kj",
    "iso:country":"NL",
    "sg:address":"St Ignatiusstr 217B",
    "sg:city":"Breda",
    "sg:orig_category":"Fotografie Reclame En Mode",
    "sg:phone":"+31 76 521 5991",
    "sg:postcode":"4817 KJ",
    "sg:province":"Noord-Brabant",
    "wof:name":"Buul, Joost Van",
    "wof:placetype":"venue"
},
  "geometry": {"coordinates":[4.80125,51.591293],"type":"Point"}
}