{
  "type": "Feature",
  "properties": {
    "iso:country":"NL",
    "sg:address":"Van 'T Hoffstraat 134",
    "sg:city":"Haarlem",
    "sg:orig_category":"Schilderwerk",
    "sg:phone":"+31 23 524 3949",
    "sg:postcode":"2014 RK",
    "sg:province":"Noord-Holland",
    "wof:name":"Bv Schildersbedrijf H. Kuyl En Zoon",
    "wof:placetype":"venue"
},
  "geometry": {"coordinates":[4.614686,52.375481],"type":"Point"}
}