{
  "type": "Feature",
  "properties": {
    "addr:full":"Delistraat 72 Enschede NL.08 7512 BN",
    "addr:housenumber":"72",
    "addr:postcode":"7512 bn",
    "addr:street":"Delistraat",
    "iso:country":"NL",
    "sg:address":"Delistraat 72",
    "sg:city":"Enschede",
    "sg:orig_category":"Fotostudio'S And Fotografen",
    "sg:phone":"+31 53 432 4199",
    "sg:postcode":"7512 BN",
    "sg:province":"NL.08",
    "wof:name":"T. Heier",
    "wof:placetype":"venue"
},
  "geometry": {"coordinates":[6.88956,52.213921],"type":"Point"}
}