{
  "type": "Feature",
  "properties": {
    "addr:full":"Ringoven 16 Arnhem Gelderland 6826 TR",
    "addr:housenumber":"16",
    "addr:postcode":"6826 tr",
    "addr:street":"Ringoven",
    "iso:country":"NL",
    "sg:address":"Ringoven 16",
    "sg:city":"Arnhem",
    "sg:orig_category":"Zonnebanken En Solaria - Fabrieken En Groothandel",
    "sg:phone":"+31 26 364 2128",
    "sg:postcode":"6826 TR",
    "sg:province":"Gelderland",
    "sg:website":"http://www.bernisun.nl",
    "wof:name":"Bernisun",
    "wof:placetype":"venue"
},
  "geometry": {"coordinates":[5.958357,51.975761],"type":"Point"}
}