{
  "type": "Feature",
  "properties": {
    "iso:country":"NL",
    "sg:address":"St Pieterskd 26",
    "sg:city":"Maastricht",
    "sg:orig_category":"Koeriersdiensten",
    "sg:phone":"+31 45 525 7847",
    "sg:postcode":"6212 AD",
    "sg:province":"Limburg",
    "wof:name":"Argonout Koeriers Service",
    "wof:placetype":"venue"
},
  "geometry": {"coordinates":[5.695384,50.840458],"type":"Point"}
}