{
  "type": "Feature",
  "properties": {
    "addr:full":"V Z V Nijeveltstr 175 Wassenaar Zuid-Holland 2242 LD",
    "addr:housenumber":"175",
    "addr:postcode":"2242 ld",
    "addr:street":"V Z V Nijeveltstr",
    "iso:country":"NL",
    "sg:address":"V Z V Nijeveltstr 175",
    "sg:city":"Wassenaar",
    "sg:orig_category":"Onroerende Goederen",
    "sg:phone":"+31 70 511 2512",
    "sg:postcode":"2242 LD",
    "sg:province":"Zuid-Holland",
    "wof:name":"Duton Bv",
    "wof:placetype":"venue"
},
  "geometry": {"coordinates":[4.393863,52.14307],"type":"Point"}
}