{
  "type": "Feature",
  "properties": {
    "iso:country":"NL",
    "sg:address":"Voltastraat 10",
    "sg:city":"Numansdorp",
    "sg:classifiers":[
        {
            "category":"Retail",
            "subcategory":"Storage",
            "type":"Services"
        }
    ],
    "sg:phone":"+31 186 651 909",
    "sg:postcode":"3281 NG",
    "sg:province":"South Holland",
    "sg:tags":[
        "opslag",
        "bewaring"
    ],
    "wof:name":"Cromstrijen Warehousing Bv",
    "wof:placetype":"venue"
},
  "geometry": {"coordinates":[4.4472088814,51.7479972839],"type":"Point"}
}