{
  "type": "Feature",
  "properties": {
    "addr:full":"Citrusstr 14 Heerlen Limburg 6412 WL",
    "addr:housenumber":"14",
    "addr:postcode":"6412 wl",
    "addr:street":"Citrusstr",
    "iso:country":"NL",
    "sg:address":"Citrusstr 14",
    "sg:city":"Heerlen",
    "sg:orig_category":"Schilders",
    "sg:phone":"+31 45 572 2140",
    "sg:postcode":"6412 WL",
    "sg:province":"Limburg",
    "wof:name":"Ernst",
    "wof:placetype":"venue"
},
  "geometry": {"coordinates":[5.98006,50.893486],"type":"Point"}
}