{
  "type": "Feature",
  "properties": {
    "addr:full":"De Ruijterstraat 2 Rijnsburg South Holland 2231 RV",
    "addr:housenumber":"2",
    "addr:postcode":"2231 rv",
    "addr:street":"De Ruijterstraat",
    "iso:country":"NL",
    "sg:address":"De Ruijterstraat 2",
    "sg:city":"Rijnsburg",
    "sg:classifiers":[
        {
            "category":"Professional",
            "subcategory":"Accounting & Tax Preparation",
            "type":"Services"
        }
    ],
    "sg:phone":"+31 71 402 1621",
    "sg:postcode":"2231 RV",
    "sg:province":"South Holland",
    "sg:tags":[
        "accountant"
    ],
    "wof:name":"Driebergen & Driebergen Accountants En Belastingad",
    "wof:placetype":"venue"
},
  "geometry": {"coordinates":[4.436223,52.195076],"type":"Point"}
}