{
  "type": "Feature",
  "properties": {
    "addr:full":"Buitenwatersloot 61 Delft Zuid-Holland 2613 TB",
    "addr:housenumber":"61",
    "addr:postcode":"2613 tb",
    "addr:street":"Buitenwatersloot",
    "iso:country":"NL",
    "sg:address":"Buitenwatersloot 61",
    "sg:city":"Delft",
    "sg:orig_category":"Paramedische Behandelingen",
    "sg:phone":"+31 15 213 1458",
    "sg:postcode":"2613 TB",
    "sg:province":"Zuid-Holland",
    "wof:name":"Verloskundigenpraktijk",
    "wof:placetype":"venue"
},
  "geometry": {"coordinates":[4.35343,52.008083],"type":"Point"}
}