{
  "type": "Feature",
  "properties": {
    "addr:full":"Vondelkd 32 Heemstede Noord-Holland 2106 AK",
    "addr:housenumber":"32",
    "addr:postcode":"2106 ak",
    "addr:street":"Vondelkd",
    "iso:country":"NL",
    "sg:address":"Vondelkd 32",
    "sg:city":"Heemstede",
    "sg:orig_category":"Bedrijfsopleidingen",
    "sg:phone":"+31 23 524 7045",
    "sg:postcode":"2106 AK",
    "sg:province":"Noord-Holland",
    "wof:name":"Hoop, N Van Der",
    "wof:placetype":"venue"
},
  "geometry": {"coordinates":[4.621248,52.345287],"type":"Point"}
}