{
  "type": "Feature",
  "properties": {
    "addr:full":"Stolperwg 29 Schagerbrug North Holland 1751 DH",
    "addr:housenumber":"29",
    "addr:postcode":"1751 dh",
    "addr:street":"Stolperwg",
    "iso:country":"NL",
    "sg:address":"Stolperwg 29",
    "sg:city":"Schagerbrug",
    "sg:orig_category":"Vakantieverblijven",
    "sg:phone":"+31 224 571 339",
    "sg:postcode":"1751 DH",
    "sg:province":"North Holland",
    "wof:name":"Wardenaar",
    "wof:placetype":"venue"
},
  "geometry": {"coordinates":[4.722697,52.814857],"type":"Point"}
}