{
  "type": "Feature",
  "properties": {
    "addr:full":"Modem 2D Coevorden Drenthe 7741 MJ",
    "addr:housenumber":"2d",
    "addr:postcode":"7741 mj",
    "addr:street":"Modem",
    "iso:country":"NL",
    "sg:address":"Modem 2D",
    "sg:city":"Coevorden",
    "sg:orig_category":"Fitnesscentra",
    "sg:phone":"+31 524 518 819",
    "sg:postcode":"7741 MJ",
    "sg:province":"Drenthe",
    "sg:website":"http://www.slenderline.net",
    "wof:name":"Slender Line",
    "wof:placetype":"venue"
},
  "geometry": {"coordinates":[6.724501,52.66095],"type":"Point"}
}