{
  "type": "Feature",
  "properties": {
    "addr:full":"Vossendreef 14 Ulvenhout Noord-Brabant 4851 BP",
    "addr:housenumber":"14",
    "addr:postcode":"4851 bp",
    "addr:street":"Vossendreef",
    "iso:country":"NL",
    "sg:address":"Vossendreef 14",
    "sg:city":"Ulvenhout",
    "sg:orig_category":"Fotostudio'S And Fotografen",
    "sg:phone":"+31 76 560 1977",
    "sg:postcode":"4851 BP",
    "sg:province":"Noord-Brabant",
    "wof:name":"M.A. Van Poppel",
    "wof:placetype":"venue"
},
  "geometry": {"coordinates":[4.81036,51.547916],"type":"Point"}
}