{
  "type": "Feature",
  "properties": {
    "addr:full":"Zjoekowln 17 Delft South Holland 2625 PJ",
    "addr:housenumber":"17",
    "addr:postcode":"2625 pj",
    "addr:street":"Zjoekowln",
    "iso:country":"NL",
    "sg:address":"Zjoekowln 17",
    "sg:city":"Delft",
    "sg:orig_category":"Grafisch Ontwerpers",
    "sg:phone":"+31 15 251 0783",
    "sg:postcode":"2625 PJ",
    "sg:province":"South Holland",
    "wof:name":"Geheid",
    "wof:placetype":"venue"
},
  "geometry": {"coordinates":[4.34184,51.992352],"type":"Point"}
}