{
  "type": "Feature",
  "properties": {
    "addr:full":"Noordsngl 128B Rotterdam Zuid-Holland 3032 BJ",
    "addr:housenumber":"128b",
    "addr:postcode":"3032 bj",
    "iso:country":"NL",
    "sg:address":"Noordsngl 128B",
    "sg:city":"Rotterdam",
    "sg:orig_category":"Verenigingen En Stichtingen",
    "sg:phone":"+31 10 467 8248",
    "sg:postcode":"3032 BJ",
    "sg:province":"Zuid-Holland",
    "wof:name":"Incasso Advocaten, Ver Van",
    "wof:placetype":"venue"
},
  "geometry": {"coordinates":[4.47767,51.92852],"type":"Point"}
}