{
  "type": "Feature",
  "properties": {
    "addr:full":"Bierstr 10 Lochem Gelderland 7241 AH",
    "addr:housenumber":"10",
    "addr:postcode":"7241 ah",
    "addr:street":"Bierstr;Gelderland",
    "iso:country":"NL",
    "sg:address":"Bierstr 10",
    "sg:city":"Lochem",
    "sg:classifiers":[
        {
            "category":"Restaurant",
            "type":"Food & Drink"
        }
    ],
    "sg:phone":"+31 573 253 036",
    "sg:postcode":"7241 AH",
    "sg:province":"Gelderland",
    "wof:name":"Vinci, Da",
    "wof:placetype":"venue"
},
  "geometry": {"coordinates":[6.41562,52.16119],"type":"Point"}
}