{
  "type": "Feature",
  "properties": {
    "addr:full":"Oudez Voorburgwal 197 Amsterdam Noord-Holland 1012 EX",
    "addr:housenumber":"197",
    "addr:postcode":"1012 ex",
    "addr:street":"Oudez Voorburgwal",
    "iso:country":"NL",
    "sg:address":"Oudez Voorburgwal 197",
    "sg:city":"Amsterdam",
    "sg:orig_category":"Bloemen En Planten",
    "sg:phone":"+31 20 638 7240",
    "sg:postcode":"1012 EX",
    "sg:province":"Noord-Holland",
    "wof:name":"Scheepstra, P",
    "wof:placetype":"venue"
},
  "geometry": {"coordinates":[4.895431,52.371082],"type":"Point"}
}