{
  "type": "Feature",
  "properties": {
    "addr:full":"Sterappel 11 Tiel Gelderland 4007 ZV",
    "addr:housenumber":"11",
    "addr:postcode":"4007 zv",
    "addr:street":"Sterappel;Gelderland",
    "iso:country":"NL",
    "sg:address":"Sterappel 11",
    "sg:city":"Tiel",
    "sg:orig_category":"Bedrijfs- And Managementsconsultants",
    "sg:phone":"+31 344 635 585",
    "sg:postcode":"4007 ZV",
    "sg:province":"Gelderland",
    "wof:name":"Pro Lance",
    "wof:placetype":"venue"
},
  "geometry": {"coordinates":[5.402524,51.874279],"type":"Point"}
}