{
  "type": "Feature",
  "properties": {
    "iso:country":"NL",
    "sg:address":"Bontekoestraat 66",
    "sg:city":"Veenendaal",
    "sg:orig_category":"Goederenvervoer Over De Weg",
    "sg:phone":"+31 318 552 282",
    "sg:postcode":"3906 EG",
    "sg:province":"Utrecht",
    "wof:name":"Veenendaals Transportbedrijf G.J. Van Ho",
    "wof:placetype":"venue"
},
  "geometry": {"coordinates":[5.525946,52.023323],"type":"Point"}
}