{
  "type": "Feature",
  "properties": {
    "addr:full":"Past Kripsstr 11 Born Alaska 6121 KM",
    "addr:housenumber":"11",
    "addr:postcode":"6121",
    "addr:street":"Alaska;Km",
    "iso:country":"NL",
    "sg:address":"Past Kripsstr 11",
    "sg:city":"Born",
    "sg:orig_category":"Administratie- En Boekhoudkantoren",
    "sg:phone":"+31 46 485 6522",
    "sg:postcode":"6121 KM",
    "sg:province":"Alaska",
    "wof:name":"Brouwers Born, Bur",
    "wof:placetype":"venue"
},
  "geometry": {"coordinates":[-156.93781999999999,67.060463],"type":"Point"}
}