{
  "type": "Feature",
  "properties": {
    "addr:full":"Berkenstr 26 Deurne Noord-Brabant 5753 GK",
    "addr:housenumber":"26",
    "addr:postcode":"5753 gk",
    "addr:street":"Berkenstr",
    "iso:country":"NL",
    "sg:address":"Berkenstr 26",
    "sg:city":"Deurne",
    "sg:orig_category":"Woninginrichting",
    "sg:phone":"+31 493 320 399",
    "sg:postcode":"5753 GK",
    "sg:province":"Noord-Brabant",
    "wof:name":"Grunsven, Van",
    "wof:placetype":"venue"
},
  "geometry": {"coordinates":[5.7796268463,51.4498901367],"type":"Point"}
}