{
  "type": "Feature",
  "properties": {
    "addr:full":"Prinses Christinalaan 121 Uithoorn North Holland 1421 BH",
    "addr:housenumber":"121",
    "addr:postcode":"1421 bh",
    "addr:street":"Prinses Christinalaan",
    "iso:country":"NL",
    "sg:address":"Prinses Christinalaan 121",
    "sg:city":"Uithoorn",
    "sg:orig_category":"Kantoorapparatuur Gh",
    "sg:phone":"+31 297 540 187",
    "sg:postcode":"1421 BH",
    "sg:province":"North Holland",
    "wof:name":"H.T. Copy Vof",
    "wof:placetype":"venue"
},
  "geometry": {"coordinates":[4.823387146,52.2381210327],"type":"Point"}
}