{
  "type": "Feature",
  "properties": {
    "addr:full":"Groene Hilledk 336 Rotterdam Zuid-Holland 3075 EB",
    "addr:housenumber":"336",
    "addr:postcode":"3075 eb",
    "addr:street":"Groene Hilledk",
    "iso:country":"NL",
    "sg:address":"Groene Hilledk 336",
    "sg:city":"Rotterdam",
    "sg:orig_category":"Apotheken",
    "sg:phone":"+31 10 419 5879",
    "sg:postcode":"3075 EB",
    "sg:province":"Zuid-Holland",
    "wof:name":"Son'S Tuindorp, Dr Van",
    "wof:placetype":"venue"
},
  "geometry": {"coordinates":[4.507607,51.88855],"type":"Point"}
}