{
  "type": "Feature",
  "properties": {
    "addr:full":"Frambozenln 95 Apeldoorn Gelderland 7322 TJ",
    "addr:housenumber":"95",
    "addr:postcode":"7322 tj",
    "addr:street":"Frambozenln;Gelderland",
    "iso:country":"NL",
    "sg:address":"Frambozenln 95",
    "sg:city":"Apeldoorn",
    "sg:orig_category":"Verenigingen En Stichtingen",
    "sg:phone":"+31 55 366 6065",
    "sg:postcode":"7322 TJ",
    "sg:province":"Gelderland",
    "wof:name":"Gideons International, The",
    "wof:placetype":"venue"
},
  "geometry": {"coordinates":[5.980593,52.219109],"type":"Point"}
}