{
  "type": "Feature",
  "properties": {
    "iso:country":"NL",
    "sg:address":"Disselvoorde 3",
    "sg:city":"Spijkenisse",
    "sg:orig_category":"Goederenvervoer Over De Weg",
    "sg:phone":"+31 181 633 343",
    "sg:postcode":"3204 SE",
    "sg:province":"Zuid-Holland",
    "wof:name":"Richard Koning Transport",
    "wof:placetype":"venue"
},
  "geometry": {"coordinates":[4.322058,51.834408],"type":"Point"}
}