{
  "type": "Feature",
  "properties": {
    "addr:full":"Doctor Cuyperslaan 86 Eindhoven Noord-Brabant 5623 BB",
    "addr:housenumber":"86",
    "addr:postcode":"5623 bb",
    "addr:street":"Doctor Cuyperslaan",
    "iso:country":"NL",
    "sg:address":"Doctor Cuyperslaan 86",
    "sg:city":"Eindhoven",
    "sg:orig_category":"Medische And Orthopedische Artikelen",
    "sg:phone":"+31 40 244 8836",
    "sg:postcode":"5623 BB",
    "sg:province":"Noord-Brabant",
    "wof:name":"Buchrnhornen Bv",
    "wof:placetype":"venue"
},
  "geometry": {"coordinates":[5.469769,51.462002],"type":"Point"}
}