{
  "type": "Feature",
  "properties": {
    "iso:country":"NL",
    "sg:address":"Zonnenberg 17",
    "sg:city":"Zoetermeer",
    "sg:orig_category":"Vertalers",
    "sg:phone":"+31 79 321 2197",
    "sg:postcode":"2716 PG",
    "sg:province":"Zuid-Holland",
    "wof:name":"Bridi\u00e9, Drs E A",
    "wof:placetype":"venue"
},
  "geometry": {"coordinates":[4.461179,52.061195],"type":"Point"}
}