{
  "type": "Feature",
  "properties": {
    "addr:full":"Heerlenerweg 1 Sittard Limburg 6132 CK",
    "addr:housenumber":"1",
    "addr:postcode":"6132 ck",
    "addr:street":"Heerlenerweg",
    "iso:country":"NL",
    "sg:address":"Heerlenerweg 1",
    "sg:city":"Sittard",
    "sg:orig_category":"Hypotheken And Hypotheekbanken",
    "sg:phone":"+31 46 452 1999",
    "sg:postcode":"6132 CK",
    "sg:province":"Limburg",
    "wof:name":"Wante Bv",
    "wof:placetype":"venue"
},
  "geometry": {"coordinates":[5.867005,50.984093],"type":"Point"}
}