{
  "type": "Feature",
  "properties": {
    "iso:country":"NL",
    "sg:address":"Watermanseweg 14",
    "sg:city":"Rijsbergen",
    "sg:orig_category":"Levende Dieren Gh",
    "sg:phone":"+31 76 596 1780",
    "sg:postcode":"4891 SZ",
    "sg:province":"North Brabant",
    "wof:name":"C.H.P.M. Van Haperen",
    "wof:placetype":"venue"
},
  "geometry": {"coordinates":[4.70491,51.528698],"type":"Point"}
}