{
  "type": "Feature",
  "properties": {
    "iso:country":"NL",
    "sg:address":"1E Exloermond 128",
    "sg:city":"Eerste Exloermond",
    "sg:orig_category":"Begrafenisondernemers",
    "sg:phone":"+31 599 416 858",
    "sg:postcode":"9573 PG",
    "sg:province":"Drenthe",
    "wof:name":"Onderlinge Uitvaartvereniging Nieuw Buinen Buinerv",
    "wof:placetype":"venue"
},
  "geometry": {"coordinates":[6.974866,52.94442],"type":"Point"}
}