{
  "type": "Feature",
  "properties": {
    "addr:full":"Bisschopsmolenstraat 51 Etten-Leur Noord-Brabant 4876 AJ",
    "addr:housenumber":"51",
    "addr:postcode":"4876 aj",
    "addr:street":"Bisschopsmolenstraat",
    "iso:country":"NL",
    "sg:address":"Bisschopsmolenstraat 51",
    "sg:city":"Etten-Leur",
    "sg:orig_category":"Meubelzaken, Woning- And Keukeninrichting",
    "sg:phone":"+31 76 503 4150",
    "sg:postcode":"4876 AJ",
    "sg:province":"Noord-Brabant",
    "wof:name":"Wooncentrum",
    "wof:placetype":"venue"
},
  "geometry": {"coordinates":[4.635421,51.567986],"type":"Point"}
}