{
  "type": "Feature",
  "properties": {
    "addr:full":"Andreaspln 14 Katwyk Zh Zuid-Holland 2225 GR",
    "addr:housenumber":"14",
    "addr:postcode":"2225",
    "addr:street":"Andreaspln",
    "iso:country":"NL",
    "sg:address":"Andreaspln 14",
    "sg:city":"Katwyk Zh",
    "sg:orig_category":"Makelaars En Adviseurs Onroerende Goederen",
    "sg:phone":"+31 71 407 6144",
    "sg:postcode":"2225 GR",
    "sg:province":"Zuid-Holland",
    "sg:website":"http://www.deleeuw.nl",
    "wof:name":"Leeuw Bv, De",
    "wof:placetype":"venue"
},
  "geometry": {"coordinates":[4.393859,52.202408],"type":"Point"}
}