{
  "type": "Feature",
  "properties": {
    "addr:full":"Soomerwegh 1 Castricum Noord-Holland 1902 CE",
    "addr:housenumber":"1",
    "addr:postcode":"1902 ce",
    "addr:street":"Soomerwegh",
    "iso:country":"NL",
    "sg:address":"Soomerwegh 1",
    "sg:city":"Castricum",
    "sg:classifiers":[
        {
            "category":"Retail",
            "subcategory":"Auto Repair",
            "type":"Services"
        }
    ],
    "sg:phone":"+31 251 655 050",
    "sg:postcode":"1902 CE",
    "sg:province":"Noord-Holland",
    "sg:tags":[
        "garage"
    ],
    "wof:name":"Heemskerk Bv",
    "wof:placetype":"venue"
},
  "geometry": {"coordinates":[4.677675,52.556412],"type":"Point"}
}