{
  "type": "Feature",
  "properties": {
    "iso:country":"NL",
    "sg:address":"Groningerstraat 10",
    "sg:city":"Surhuisterveen",
    "sg:orig_category":"Verlichting And Huishoudartikelen",
    "sg:phone":"+31 512 363 405",
    "sg:postcode":"9231 CL",
    "sg:province":"Provincie Friesland",
    "wof:name":"Tapijtcentrum Van Der Ploeg",
    "wof:placetype":"venue"
},
  "geometry": {"coordinates":[6.165774,53.181438],"type":"Point"}
}