{
  "type": "Feature",
  "properties": {
    "iso:country":"NL",
    "sg:address":"Du Meelaan 264",
    "sg:city":"Zoetermeer",
    "sg:orig_category":"Artiestenbureaus",
    "sg:phone":"+31 79 341 7443",
    "sg:postcode":"2722 ZE",
    "sg:province":"Zuid-Holland",
    "wof:name":"Goochelaar Stroganoff",
    "wof:placetype":"venue"
},
  "geometry": {"coordinates":[4.499463,52.060669],"type":"Point"}
}