{
  "type": "Feature",
  "properties": {
    "addr:full":"Zorgvlietstr 501 Breda Noord-Brabant 4834 NH",
    "addr:housenumber":"501",
    "addr:postcode":"4834 nh",
    "iso:country":"NL",
    "sg:address":"Zorgvlietstr 501",
    "sg:city":"Breda",
    "sg:orig_category":"Verzekeringen - Verzekeringskantoren",
    "sg:phone":"+31 76 565 0517",
    "sg:postcode":"4834 NH",
    "sg:province":"Noord-Brabant",
    "wof:name":"Jacobs",
    "wof:placetype":"venue"
},
  "geometry": {"coordinates":[4.813221,51.573196],"type":"Point"}
}