{
  "type": "Feature",
  "properties": {
    "addr:full":"Beilerstraat 3 Hijken Provincie Drenthe 9415 TB",
    "addr:housenumber":"3",
    "addr:postcode":"9415 tb",
    "addr:street":"Beilerstraat;Provincie Drenthe",
    "iso:country":"NL",
    "sg:address":"Beilerstraat 3",
    "sg:city":"Hijken",
    "sg:orig_category":"Bloemen- And Plantenteelt",
    "sg:phone":"+31 593 541 185",
    "sg:postcode":"9415 TB",
    "sg:province":"Provincie Drenthe",
    "wof:name":"H. Pijl",
    "wof:placetype":"venue"
},
  "geometry": {"coordinates":[6.503771,52.886833],"type":"Point"}
}