{
  "type": "Feature",
  "properties": {
    "addr:full":"Dorpsstr 6 Woudenberg Utrecht 3931 EG",
    "addr:housenumber":"6",
    "addr:postcode":"3931 eg",
    "addr:street":"Dorpsstr",
    "iso:country":"NL",
    "sg:address":"Dorpsstr 6",
    "sg:city":"Woudenberg",
    "sg:orig_category":"Projectinrichting",
    "sg:phone":"+31 33 286 6487",
    "sg:postcode":"3931 EG",
    "sg:province":"Utrecht",
    "sg:website":"http://www.detheeroos.nl",
    "wof:name":"Theeroos, De",
    "wof:placetype":"venue"
},
  "geometry": {"coordinates":[5.415417,52.082092],"type":"Point"}
}