{
  "type": "Feature",
  "properties": {
    "addr:full":"Breemhaarswg 8A Geesteren Ov Overijssel 7678 TJ",
    "addr:housenumber":"8a",
    "addr:postcode":"7678 tj",
    "addr:street":"Breemhaarswg;Ov",
    "iso:country":"NL",
    "sg:address":"Breemhaarswg 8A",
    "sg:city":"Geesteren Ov",
    "sg:orig_category":"Autoschade- Herstelbedrijven",
    "sg:phone":"+31 546 632 274",
    "sg:postcode":"7678 TJ",
    "sg:province":"Overijssel",
    "wof:name":"Dura",
    "wof:placetype":"venue"
},
  "geometry": {"coordinates":[6.721225,52.422482],"type":"Point"}
}