{
  "type": "Feature",
  "properties": {
    "addr:full":"Bijlmermeerstraat 32 Hoofddorp Noord-Holland 2131 HC",
    "addr:housenumber":"32",
    "addr:postcode":"2131 hc",
    "addr:street":"Bijlmermeerstraat",
    "iso:country":"NL",
    "sg:address":"Bijlmermeerstraat 32",
    "sg:city":"Hoofddorp",
    "sg:classifiers":[
        {
            "category":"Retail",
            "subcategory":"Storage",
            "type":"Services"
        }
    ],
    "sg:phone":"+31 23 562 2000",
    "sg:postcode":"2131 HC",
    "sg:province":"Noord-Holland",
    "sg:tags":[
        "opslag",
        "bewaring"
    ],
    "wof:name":"Mac Dermid Color Span Emea",
    "wof:placetype":"venue"
},
  "geometry": {"coordinates":[4.6899290085,52.3160896301],"type":"Point"}
}