{
  "type": "Feature",
  "properties": {
    "iso:country":"NL",
    "sg:address":"M Klompeln 11-13",
    "sg:city":"Ryen",
    "sg:orig_category":"Administratie- En Boekhoudkantoren",
    "sg:phone":"+31 161 223 494",
    "sg:postcode":"5122 BN",
    "sg:province":"Noord-Brabant",
    "wof:name":"Heijmans Advies Bv",
    "wof:placetype":"venue"
},
  "geometry": {"coordinates":[4.92752,51.59277],"type":"Point"}
}