{
  "type": "Feature",
  "properties": {
    "addr:full":"Burg Th Wackersstr 1 Roermond Limburg 6041 AJ",
    "addr:housenumber":"1",
    "addr:postcode":"6041 aj",
    "addr:street":"Burg;Wackersstr",
    "iso:country":"NL",
    "sg:address":"Burg Th Wackersstr 1",
    "sg:city":"Roermond",
    "sg:classifiers":[
        {
            "category":"Food & Beverages",
            "subcategory":"Bakery",
            "type":"Retail Goods"
        }
    ],
    "sg:phone":"+31 475 333 671",
    "sg:postcode":"6041 AJ",
    "sg:province":"Limburg",
    "sg:tags":[
        "brood",
        "en",
        "banket"
    ],
    "wof:name":"Caris, J",
    "wof:placetype":"venue"
},
  "geometry": {"coordinates":[5.99759,51.212299],"type":"Point"}
}