{
  "type": "Feature",
  "properties": {
    "iso:country":"NL",
    "sg:address":"Hemonystraat 27",
    "sg:city":"Amsterdam",
    "sg:orig_category":"Technische Studies And Onderzoek",
    "sg:phone":"+31 20 662 5187",
    "sg:postcode":"1074 BM",
    "sg:province":"North Holland",
    "wof:name":"Itay Simhony Yacht Designs",
    "wof:placetype":"venue"
},
  "geometry": {"coordinates":[4.902619,52.357216],"type":"Point"}
}