{
  "type": "Feature",
  "properties": {
    "addr:full":"Krabstg 21 Gorinchem South Holland 4201 ES",
    "addr:housenumber":"21",
    "addr:postcode":"4201 es",
    "addr:street":"Krabstg",
    "iso:country":"NL",
    "sg:address":"Krabstg 21",
    "sg:city":"Gorinchem",
    "sg:orig_category":"Verenigingsgebouwen",
    "sg:phone":"+31 183 634 622",
    "sg:postcode":"4201 ES",
    "sg:province":"South Holland",
    "wof:name":"Harmonie, De",
    "wof:placetype":"venue"
},
  "geometry": {"coordinates":[4.97338,51.827473],"type":"Point"}
}