{
  "type": "Feature",
  "properties": {
    "iso:country":"NL",
    "sg:address":"Eikstraat 20",
    "sg:city":"Hoorn Nh",
    "sg:orig_category":"Watersport-, Sport- And Kampeerbenodigdheden Verhuur",
    "sg:phone":"+31 229 219 554",
    "sg:postcode":"1623 LS",
    "sg:province":"Noord-Holland",
    "wof:name":"Firma Veldhuis De Eenhoorn",
    "wof:placetype":"venue"
},
  "geometry": {"coordinates":[5.0631232262,52.6441040039],"type":"Point"}
}