{
  "type": "Feature",
  "properties": {
    "iso:country":"NL",
    "sg:address":"Transportwg 3",
    "sg:city":"Veendam",
    "sg:orig_category":"Keukens",
    "sg:phone":"+31 598 632 363",
    "sg:postcode":"9645 KZ",
    "sg:province":"Groningen",
    "wof:name":"Tulp",
    "wof:placetype":"venue"
},
  "geometry": {"coordinates":[6.889945,53.110439],"type":"Point"}
}