{
  "type": "Feature",
  "properties": {
    "addr:full":"Akerstr 35A Kerkrade Limburg 6466 HA",
    "addr:housenumber":"35a",
    "addr:postcode":"6466 ha",
    "addr:street":"Akerstr",
    "iso:country":"NL",
    "sg:address":"Akerstr 35A",
    "sg:city":"Kerkrade",
    "sg:orig_category":"Koffie- En Theehuizen",
    "sg:phone":"+31 45 542 9823",
    "sg:postcode":"6466 HA",
    "sg:province":"Limburg",
    "wof:name":"Kruimeltje",
    "wof:placetype":"venue"
},
  "geometry": {"coordinates":[6.026481,50.856606],"type":"Point"}
}