{
  "type": "Feature",
  "properties": {
    "addr:full":"Veerstraat 38 Oude Wetering Zuid-Holland 2377 AP",
    "addr:housenumber":"38",
    "addr:postcode":"wetering;2377 ap",
    "addr:street":"Veerstraat",
    "iso:country":"NL",
    "sg:address":"Veerstraat 38",
    "sg:city":"Oude Wetering",
    "sg:orig_category":"Banken And Kredietinstellingen",
    "sg:phone":"+31 172 509 540",
    "sg:postcode":"2377 AP",
    "sg:province":"Zuid-Holland",
    "wof:name":"Rabobank",
    "wof:placetype":"venue"
},
  "geometry": {"coordinates":[4.647631,52.208366],"type":"Point"}
}