{
  "type": "Feature",
  "properties": {
    "addr:full":"Telefoonwg 64B Ede Gld Gelderland 6713 AL",
    "addr:housenumber":"64b;6713",
    "addr:postcode":"al",
    "addr:street":"Telefoonwg;Gld Gelderland",
    "iso:country":"NL",
    "sg:address":"Telefoonwg 64B",
    "sg:city":"Ede Gld",
    "sg:orig_category":"Boeken En Tijdschriften",
    "sg:phone":"+31 318 617 555",
    "sg:postcode":"6713 AL",
    "sg:province":"Gelderland",
    "wof:name":"Hardeman, F",
    "wof:placetype":"venue"
},
  "geometry": {"coordinates":[5.667489,52.04491],"type":"Point"}
}