{
  "type": "Feature",
  "properties": {
    "addr:full":"Lindenlaan 21 Huizen Noord-Holland 1271 AV",
    "addr:housenumber":"21",
    "addr:postcode":"1271 av",
    "addr:street":"Lindenlaan",
    "iso:country":"NL",
    "sg:address":"Lindenlaan 21",
    "sg:city":"Huizen",
    "sg:orig_category":"Verlichting And Huishoudartikelen",
    "sg:phone":"+31 35 525 0790",
    "sg:postcode":"1271 AV",
    "sg:province":"Noord-Holland",
    "wof:name":"J Visser",
    "wof:placetype":"venue"
},
  "geometry": {"coordinates":[5.235817,52.296803],"type":"Point"}
}