{
  "type": "Feature",
  "properties": {
    "addr:full":"Nieuwstr 19A Nieuw Vennep Noord-Holland 2152 BE",
    "addr:housenumber":"19a nieuw vennep",
    "addr:postcode":"2152",
    "addr:street":"Nieuwstr",
    "iso:country":"NL",
    "sg:address":"Nieuwstr 19A",
    "sg:city":"Nieuw Vennep",
    "sg:orig_category":"Logopedisten",
    "sg:phone":"+31 252 689 122",
    "sg:postcode":"2152 BE",
    "sg:province":"Noord-Holland",
    "wof:name":"Steeman, M C",
    "wof:placetype":"venue"
},
  "geometry": {"coordinates":[4.634031,52.266296],"type":"Point"}
}