{
  "type": "Feature",
  "properties": {
    "addr:full":"Jan Van Der Heydenstraat 24 Bleiswijk Zuid-Holland 2665 JA",
    "addr:housenumber":"24",
    "addr:postcode":"2665 ja",
    "addr:street":"Jan Van Der Heydenstraat",
    "iso:country":"NL",
    "sg:address":"Jan Van Der Heydenstraat 24",
    "sg:city":"Bleiswijk",
    "sg:orig_category":"Kantoorartikelen",
    "sg:phone":"+31 10 521 9488",
    "sg:postcode":"2665 JA",
    "sg:province":"Zuid-Holland",
    "wof:name":"Mauser Mega Kantoor- En Magazijninrichting Bv",
    "wof:placetype":"venue"
},
  "geometry": {"coordinates":[4.5380330086,52.0126113892],"type":"Point"}
}