{
  "type": "Feature",
  "properties": {
    "addr:full":"Steeg 16 Echt Limburg 6101 AR",
    "addr:housenumber":"16",
    "addr:postcode":"6101",
    "addr:street":"Steeg",
    "iso:country":"NL",
    "sg:address":"Steeg 16",
    "sg:city":"Echt",
    "sg:orig_category":"Damesmodezaken",
    "sg:phone":"+31 475 485 454",
    "sg:postcode":"6101 AR",
    "sg:province":"Limburg",
    "wof:name":"Modehuis G. Delsing Bv",
    "wof:placetype":"venue"
},
  "geometry": {"coordinates":[-62.845249,-34.20557],"type":"Point"}
}