{
  "type": "Feature",
  "properties": {
    "iso:country":"NL",
    "sg:address":"Hemonystr 22",
    "sg:city":"Amsterdam",
    "sg:orig_category":"Vertalers",
    "sg:phone":"+31 20 664 7737",
    "sg:postcode":"1074 BP",
    "sg:province":"North Holland",
    "wof:name":"Michael, J",
    "wof:placetype":"venue"
},
  "geometry": {"coordinates":[4.902175,52.357166],"type":"Point"}
}