{
  "type": "Feature",
  "properties": {
    "iso:country":"NL",
    "sg:address":"Oosteinde 31",
    "sg:city":"Scherpenzeel Gld",
    "sg:orig_category":"Land- En Tuinbouw - Loonbedrijven",
    "sg:phone":"+31 33 277 8216",
    "sg:postcode":"3925 LA",
    "sg:province":"Gelderland",
    "wof:name":"Maaten, R Ter",
    "wof:placetype":"venue"
},
  "geometry": {"coordinates":[5.502076,52.077484],"type":"Point"}
}