{
  "type": "Feature",
  "properties": {
    "addr:full":"Warfstr 1 Winsum Gn Groningen 9951 BS",
    "addr:housenumber":"1",
    "addr:postcode":"gn;9951 bs",
    "addr:street":"Warfstr",
    "iso:country":"NL",
    "sg:address":"Warfstr 1",
    "sg:city":"Winsum Gn",
    "sg:orig_category":"Verenigingen En Stichtingen",
    "sg:phone":"+31 595 441 123",
    "sg:postcode":"9951 BS",
    "sg:province":"Groningen",
    "wof:name":"Welzijn Winsum, Sticht",
    "wof:placetype":"venue"
},
  "geometry": {"coordinates":[6.52042,53.325287],"type":"Point"}
}