{
  "type": "Feature",
  "properties": {
    "iso:country":"NL",
    "sg:address":"Pannenweg 231",
    "sg:city":"Nederweert",
    "sg:orig_category":"Drukkerijen And Copyshops",
    "sg:phone":"+31 495 632 625",
    "sg:postcode":"6031 RK",
    "sg:province":"Limburg",
    "wof:name":"Drukkerij Van Deursen Bv",
    "wof:placetype":"venue"
},
  "geometry": {"coordinates":[5.752279,51.276821],"type":"Point"}
}