{
  "type": "Feature",
  "properties": {
    "addr:full":"Houtsberg 5A Nederweert Eind Limburg 6034 ST",
    "addr:housenumber":"5a;6034",
    "addr:street":"Houtsberg;Eind Limburg",
    "iso:country":"NL",
    "sg:address":"Houtsberg 5A",
    "sg:city":"Nederweert Eind",
    "sg:orig_category":"Pluimveehouderijen",
    "sg:phone":"+31 495 651 569",
    "sg:postcode":"6034 ST",
    "sg:province":"Limburg",
    "wof:name":"S. Wijen-Van Helmond",
    "wof:placetype":"venue"
},
  "geometry": {"coordinates":[5.787784,51.262592],"type":"Point"}
}