{
  "type": "Feature",
  "properties": {
    "addr:full":"Schorpioen 2 Katwyk Zh Zuid-Holland 2221 MZ",
    "addr:housenumber":"2",
    "addr:postcode":"2221 mz",
    "addr:street":"Schorpioen",
    "iso:country":"NL",
    "sg:address":"Schorpioen 2",
    "sg:city":"Katwyk Zh",
    "sg:orig_category":"Administratie- En Boekhoudkantoren",
    "sg:phone":"+31 71 408 1620",
    "sg:postcode":"2221 MZ",
    "sg:province":"Zuid-Holland",
    "wof:name":"Documenten Opmaak Bureau",
    "wof:placetype":"venue"
},
  "geometry": {"coordinates":[4.42048,52.21299],"type":"Point"}
}