{
  "type": "Feature",
  "properties": {
    "iso:country":"NL",
    "sg:address":"Oranjeplein 21",
    "sg:city":"Loon Op Zand",
    "sg:orig_category":"Verzekeringen - Verzekeringskantoren",
    "sg:phone":"+31 416 369 000",
    "sg:postcode":"5175 BE",
    "sg:province":"Noord-Brabant",
    "sg:website":"http://www.mediair.nl",
    "wof:name":"Mediair",
    "wof:placetype":"venue"
},
  "geometry": {"coordinates":[5.073681,51.627876],"type":"Point"}
}