{
  "type": "Feature",
  "properties": {
    "iso:country":"NL",
    "sg:address":"Helhoek 10",
    "sg:city":"Groessen",
    "sg:orig_category":"Farmaceutische Producten Gh",
    "sg:phone":"+31 316 527 762",
    "sg:postcode":"6923 PE",
    "sg:province":"Gelderland",
    "wof:name":"P. Derksen",
    "wof:placetype":"venue"
},
  "geometry": {"coordinates":[6.042199,51.934628],"type":"Point"}
}