{
  "type": "Feature",
  "properties": {
    "addr:full":"Fluitekruidwg 149 Zaandam North Holland 1508 AD",
    "addr:housenumber":"149",
    "addr:postcode":"1508 ad",
    "iso:country":"NL",
    "sg:address":"Fluitekruidwg 149",
    "sg:city":"Zaandam",
    "sg:orig_category":"Grafische Bedrijven",
    "sg:phone":"+31 75 612 1794",
    "sg:postcode":"1508 AD",
    "sg:province":"North Holland",
    "sg:website":"http://www.jankojanko.com",
    "wof:name":"Jankojanko",
    "wof:placetype":"venue"
},
  "geometry": {"coordinates":[4.833903,52.458401],"type":"Point"}
}