{
  "type": "Feature",
  "properties": {
    "addr:full":"Helmhof 27 Alphen Aan Den Ryn South Holland 2403 VM",
    "addr:housenumber":"27",
    "addr:postcode":"2403 vm",
    "addr:street":"Helmhof;Aan Den Ryn",
    "iso:country":"NL",
    "sg:address":"Helmhof 27",
    "sg:city":"Alphen Aan Den Ryn",
    "sg:orig_category":"Schoonheidsinstituten",
    "sg:phone":"+31 172 434 990",
    "sg:postcode":"2403 VM",
    "sg:province":"South Holland",
    "wof:name":"Sensibon Salon",
    "wof:placetype":"venue"
},
  "geometry": {"coordinates":[4.687199,52.143124],"type":"Point"}
}