{
  "type": "Feature",
  "properties": {
    "iso:country":"NL",
    "sg:address":"Van De Mortelstraat 254",
    "sg:city":"Noordwijk Zh",
    "sg:orig_category":"Autokeuringen",
    "sg:phone":"+31 71 364 8740",
    "sg:postcode":"2203 JM",
    "sg:province":"Zuid-Holland",
    "wof:name":"Shell",
    "wof:placetype":"venue"
},
  "geometry": {"coordinates":[4.446733,52.2411],"type":"Point"}
}