{
  "type": "Feature",
  "properties": {
    "addr:full":"Tuinstraat 95 Veenendaal Utrecht 3901 RA",
    "addr:housenumber":"95",
    "addr:postcode":"3901 ra",
    "addr:street":"Tuinstraat",
    "iso:country":"NL",
    "sg:address":"Tuinstraat 95",
    "sg:city":"Veenendaal",
    "sg:orig_category":"Kleding And Schoenen Gh",
    "sg:phone":"+31 318 510 662",
    "sg:postcode":"3901 RA",
    "sg:province":"Utrecht",
    "wof:name":"Vogtschmidt Outdoor Center",
    "wof:placetype":"venue"
},
  "geometry": {"coordinates":[5.556866,52.026737],"type":"Point"}
}