{
  "type": "Feature",
  "properties": {
    "addr:full":"De Savornin Lohmanlaan 37 Amstelveen Noord-Holland 1181 XL",
    "addr:housenumber":"37",
    "addr:postcode":"1181 xl",
    "addr:street":"De Savornin Lohmanlaan",
    "iso:country":"NL",
    "sg:address":"De Savornin Lohmanlaan 37",
    "sg:city":"Amstelveen",
    "sg:orig_category":"Verzekeringen",
    "sg:phone":"+31 20 641 9120",
    "sg:postcode":"1181 XL",
    "sg:province":"Noord-Holland",
    "wof:name":"Phillip A. Brink Employee Benefits And",
    "wof:placetype":"venue"
},
  "geometry": {"coordinates":[4.854488,52.305557],"type":"Point"}
}