{
  "type": "Feature",
  "properties": {
    "addr:full":"Horstlindeln 78 Enschede Overijssel 7522 JJ",
    "addr:housenumber":"78",
    "addr:postcode":"7522 jj",
    "addr:street":"Horstlindeln",
    "iso:country":"NL",
    "sg:address":"Horstlindeln 78",
    "sg:city":"Enschede",
    "sg:orig_category":"Verzekeringen - Verzekeringskantoren",
    "sg:phone":"+31 53 433 9028",
    "sg:postcode":"7522 JJ",
    "sg:province":"Overijssel",
    "wof:name":"Hardeman, F",
    "wof:placetype":"venue"
},
  "geometry": {"coordinates":[6.877526,52.241589],"type":"Point"}
}