{
  "type": "Feature",
  "properties": {
    "iso:country":"NL",
    "sg:address":"Detmoldstraat 11",
    "sg:city":"Utrecht",
    "sg:orig_category":"Autokeuringen",
    "sg:phone":"+31 30 288 1373",
    "sg:postcode":"3523 GA",
    "sg:province":"Utrecht",
    "wof:name":"Garage Robles",
    "wof:placetype":"venue"
},
  "geometry": {"coordinates":[5.125658,52.071758],"type":"Point"}
}