{
  "type": "Feature",
  "properties": {
    "iso:country":"NL",
    "sg:address":"Lindberghstr 5",
    "sg:city":"Hoogeveen",
    "sg:orig_category":"Zonweringen",
    "sg:phone":"+31 528 350 652",
    "sg:postcode":"7903 BM",
    "sg:province":"Provincie Drenthe",
    "sg:website":"http://www.kroezon.nl",
    "wof:name":"Kroezon Zonwering",
    "wof:placetype":"venue"
},
  "geometry": {"coordinates":[6.52201,52.732571],"type":"Point"}
}