{
  "type": "Feature",
  "properties": {
    "iso:country":"NL",
    "sg:address":"Oergongswei 11",
    "sg:city":"Scharnegoutum",
    "sg:orig_category":"Wegen And Sportterreinen",
    "sg:phone":"+31 515 430 036",
    "sg:postcode":"8629 SZ",
    "sg:province":"Friesland",
    "wof:name":"Handelsonderneming De Boemerang Bv",
    "wof:placetype":"venue"
},
  "geometry": {"coordinates":[5.6725988388,53.0621871948],"type":"Point"}
}