{
  "type": "Feature",
  "properties": {
    "addr:full":"Marktstraat 1 Ravenstein North Brabant 5371 AC",
    "addr:housenumber":"1",
    "addr:postcode":"5371 ac",
    "addr:street":"Marktstraat",
    "iso:country":"NL",
    "sg:address":"Marktstraat 1",
    "sg:city":"Ravenstein",
    "sg:orig_category":"Kappers",
    "sg:phone":"+31 486 412 577",
    "sg:postcode":"5371 AC",
    "sg:province":"North Brabant",
    "wof:name":"Haarmode Lepoutre",
    "wof:placetype":"venue"
},
  "geometry": {"coordinates":[5.6511011124,51.7966117859],"type":"Point"}
}