{
  "type": "Feature",
  "properties": {
    "iso:country":"NL",
    "sg:address":"Slimmewg 2",
    "sg:city":"Amsterdam",
    "sg:orig_category":"Ventilatiesystemen",
    "sg:phone":"+31 20 615 3914",
    "sg:postcode":"1066 EV",
    "sg:province":"North Holland",
    "wof:name":"Belos Bv",
    "wof:placetype":"venue"
},
  "geometry": {"coordinates":[4.794686,52.341854],"type":"Point"}
}