{
  "type": "Feature",
  "properties": {
    "addr:full":"Hoofdweg 5 Boerakker Groningen 9361 PA",
    "addr:housenumber":"5",
    "addr:postcode":"9361 pa",
    "addr:street":"Hoofdweg",
    "iso:country":"NL",
    "sg:address":"Hoofdweg 5",
    "sg:city":"Boerakker",
    "sg:orig_category":"Levende Dieren Gh",
    "sg:phone":"+31 594 549 016",
    "sg:postcode":"9361 PA",
    "sg:province":"Groningen",
    "wof:name":"S. Sikkema",
    "wof:placetype":"venue"
},
  "geometry": {"coordinates":[6.330412,53.18084],"type":"Point"}
}