{
  "type": "Feature",
  "properties": {
    "iso:country":"NL",
    "sg:address":"Boerenweg 22",
    "sg:city":"Arcen",
    "sg:classifiers":[
        {
            "category":"Education",
            "subcategory":"Preschool",
            "type":"Public Place"
        }
    ],
    "sg:phone":"+31 77 473 1894",
    "sg:postcode":"5944 EK",
    "sg:province":"Limburg",
    "sg:tags":[
        "kleuteronderwijs",
        "basis-"
    ],
    "wof:name":"Basisschool Wijdtveld",
    "wof:placetype":"venue"
},
  "geometry": {"coordinates":[6.182441,51.478477],"type":"Point"}
}