{
  "type": "Feature",
  "properties": {
    "addr:full":"Klarendalseweg 143 Arnhem Gelderland 6822 GG",
    "addr:housenumber":"143",
    "addr:postcode":"6822 gg",
    "addr:street":"Klarendalseweg",
    "iso:country":"NL",
    "sg:address":"Klarendalseweg 143",
    "sg:city":"Arnhem",
    "sg:classifiers":[
        {
            "category":"Fast Food",
            "type":"Food & Drink"
        }
    ],
    "sg:phone":"+31 26 389 2398",
    "sg:postcode":"6822 GG",
    "sg:province":"Gelderland",
    "sg:tags":[
        "afhaal",
        "restaurant"
    ],
    "wof:name":"Cafetaria 'T Trefpunt",
    "wof:placetype":"venue"
},
  "geometry": {"coordinates":[5.922448,51.988991],"type":"Point"}
}