{
  "type": "Feature",
  "properties": {
    "addr:full":"Sandrastg 5 Deventer Overijssel 7411 KS",
    "addr:housenumber":"5",
    "addr:postcode":"7411 ks",
    "addr:street":"Sandrastg",
    "iso:country":"NL",
    "sg:address":"Sandrastg 5",
    "sg:city":"Deventer",
    "sg:orig_category":"Fitnesscentra",
    "sg:phone":"+31 570 614 628",
    "sg:postcode":"7411 KS",
    "sg:province":"Overijssel",
    "wof:name":"Body Shape",
    "wof:placetype":"venue"
},
  "geometry": {"coordinates":[6.156069,52.252766],"type":"Point"}
}