{
  "type": "Feature",
  "properties": {
    "addr:full":"Reisvennestr 42 Valkenswaard Noord-Brabant 5554 EV",
    "addr:housenumber":"42",
    "addr:postcode":"5554 ev",
    "addr:street":"Reisvennestr",
    "iso:country":"NL",
    "sg:address":"Reisvennestr 42",
    "sg:city":"Valkenswaard",
    "sg:orig_category":"Schilders",
    "sg:phone":"+31 40 204 5333",
    "sg:postcode":"5554 EV",
    "sg:province":"Noord-Brabant",
    "wof:name":"Bots, J",
    "wof:placetype":"venue"
},
  "geometry": {"coordinates":[5.461722,51.344627],"type":"Point"}
}