{
  "type": "Feature",
  "properties": {
    "iso:country":"NL",
    "sg:address":"R J H Fortuynpln 26",
    "sg:city":"Amsterdam",
    "sg:orig_category":"Binnenhuisarchitectuur",
    "sg:phone":"+31 20 419 7244",
    "sg:postcode":"1019 WL",
    "sg:province":"Noord-Holland",
    "wof:name":"W En M",
    "wof:placetype":"venue"
},
  "geometry": {"coordinates":[4.946178,52.372047],"type":"Point"}
}