{
  "type": "Feature",
  "properties": {
    "iso:country":"NL",
    "sg:address":"Wolterswg 44",
    "sg:city":"Hengelo Ov",
    "sg:orig_category":"Binnenhuisarchitectuur",
    "sg:phone":"+31 6 20442397",
    "sg:postcode":"7552 DD",
    "sg:province":"Overijssel",
    "wof:name":"J T Consultants Bv",
    "wof:placetype":"venue"
},
  "geometry": {"coordinates":[6.807735,52.260715],"type":"Point"}
}