{
  "type": "Feature",
  "properties": {
    "addr:full":"Talmastraat 36 Nijkerkerveen Gelderland 3864 DE",
    "addr:housenumber":"36",
    "addr:postcode":"3864 de",
    "addr:street":"Talmastraat;Gelderland",
    "iso:country":"NL",
    "sg:address":"Talmastraat 36",
    "sg:city":"Nijkerkerveen",
    "sg:orig_category":"Levende Dieren Gh",
    "sg:phone":"+31 33 253 7333",
    "sg:postcode":"3864 DE",
    "sg:province":"Gelderland",
    "wof:name":"J. Franken",
    "wof:placetype":"venue"
},
  "geometry": {"coordinates":[5.470493,52.196011],"type":"Point"}
}