{
  "type": "Feature",
  "properties": {
    "addr:full":"Ceintuurbaan 326-328 Amsterdam North Holland 1072 GM",
    "addr:housenumber":"326-328",
    "addr:postcode":"1072 gm",
    "addr:street":"Ceintuurbaan",
    "iso:country":"NL",
    "sg:address":"Ceintuurbaan 326-328",
    "sg:city":"Amsterdam",
    "sg:orig_category":"Babyartikelen Detailhandel",
    "sg:phone":"+31 20 671 2267",
    "sg:postcode":"1072 GM",
    "sg:province":"North Holland",
    "wof:name":"Babyplanet",
    "wof:placetype":"venue"
},
  "geometry": {"coordinates":[4.893265,52.35294],"type":"Point"}
}