{
  "type": "Feature",
  "properties": {
    "addr:full":"Hegdambroek 1509 Nymegen Gelderland 6546 VN",
    "addr:housenumber":"1509",
    "addr:postcode":"6546 vn",
    "addr:street":"Hegdambroek;Gelderland",
    "iso:country":"NL",
    "sg:address":"Hegdambroek 1509",
    "sg:city":"Nymegen",
    "sg:orig_category":"Adviesbureaus Bouwkunde",
    "sg:phone":"+31 24 360 1427",
    "sg:postcode":"6546 VN",
    "sg:province":"Gelderland",
    "wof:name":"Derkzen",
    "wof:placetype":"venue"
},
  "geometry": {"coordinates":[5.791109,51.83115],"type":"Point"}
}