{
  "type": "Feature",
  "properties": {
    "addr:full":"Beatrixwg 26 Vaassen Gelderland 8171 VX",
    "addr:housenumber":"26",
    "addr:postcode":"8171 vx",
    "addr:street":"Beatrixwg;Gelderland",
    "iso:country":"NL",
    "sg:address":"Beatrixwg 26",
    "sg:city":"Vaassen",
    "sg:orig_category":"Voegwerken",
    "sg:phone":"+31 578 571 324",
    "sg:postcode":"8171 VX",
    "sg:province":"Gelderland",
    "wof:name":"Einde, J Van 'T",
    "wof:placetype":"venue"
},
  "geometry": {"coordinates":[5.963952,52.287651],"type":"Point"}
}