{
  "type": "Feature",
  "properties": {
    "addr:full":"Molenstr 43 Tilburg Noord-Brabant 5014 NA",
    "addr:housenumber":"43",
    "addr:postcode":"5014 na",
    "addr:street":"Molenstr",
    "iso:country":"NL",
    "sg:address":"Molenstr 43",
    "sg:city":"Tilburg",
    "sg:orig_category":"Wassalons",
    "sg:phone":"+31 13 580 1088",
    "sg:postcode":"5014 NA",
    "sg:province":"Noord-Brabant",
    "sg:website":"http://www.texon.nl",
    "wof:name":"Texon",
    "wof:placetype":"venue"
},
  "geometry": {"coordinates":[5.094148159,51.5649299622],"type":"Point"}
}