{
  "type": "Feature",
  "properties": {
    "iso:country":"NL",
    "sg:address":"Minderbroederstr 46",
    "sg:city":"Zierikzee",
    "sg:orig_category":"Banden",
    "sg:phone":"+31 111 417 040",
    "sg:postcode":"4301 EX",
    "sg:province":"Zeeland",
    "sg:website":"http://www.bandenbeurs.nl",
    "wof:name":"Bandenbeurs Nl",
    "wof:placetype":"venue"
},
  "geometry": {"coordinates":[3.915452,51.651344],"type":"Point"}
}