{
  "type": "Feature",
  "properties": {
    "addr:full":"Groenestr 66 Rheden Gelderland 6991 GH",
    "addr:housenumber":"66",
    "addr:postcode":"6991 gh",
    "addr:street":"Groenestr;Gelderland",
    "iso:country":"NL",
    "sg:address":"Groenestr 66",
    "sg:city":"Rheden",
    "sg:orig_category":"Bloemen En Planten",
    "sg:phone":"+31 26 495 4222",
    "sg:postcode":"6991 GH",
    "sg:province":"Gelderland",
    "wof:name":"Petite Fleur",
    "wof:placetype":"venue"
},
  "geometry": {"coordinates":[6.035325,52.005108],"type":"Point"}
}