{
  "type": "Feature",
  "properties": {
    "addr:full":"W Hofman Pootstr 56 Spykenisse South Holland 3207 DC",
    "addr:housenumber":"56",
    "addr:postcode":"3207",
    "addr:street":"W;Pootstr",
    "iso:country":"NL",
    "sg:address":"W Hofman Pootstr 56",
    "sg:city":"Spykenisse",
    "sg:orig_category":"Postzegels",
    "sg:phone":"+31 181 636 465",
    "sg:postcode":"3207 DC",
    "sg:province":"South Holland",
    "wof:name":"Vlies, P A R Van Der",
    "wof:placetype":"venue"
},
  "geometry": {"coordinates":[4.352245,51.837334],"type":"Point"}
}