{
  "type": "Feature",
  "properties": {
    "addr:full":"Veldm Montgomeryln 435 Eindhoven North Brabant 5612 BK",
    "addr:housenumber":"435",
    "addr:postcode":"5612 bk",
    "iso:country":"NL",
    "sg:address":"Veldm Montgomeryln 435",
    "sg:city":"Eindhoven",
    "sg:orig_category":"Bedrijfs- And Managementsconsultants",
    "sg:phone":"+31 40 243 1261",
    "sg:postcode":"5612 BK",
    "sg:province":"North Brabant",
    "wof:name":"A.J. V.D. Graaf",
    "wof:placetype":"venue"
},
  "geometry": {"coordinates":[5.484105,51.434471],"type":"Point"}
}