{
  "type": "Feature",
  "properties": {
    "addr:full":"Eendrachtstraat 47 Middelharnis Zuid-Holland 3241 CC",
    "addr:housenumber":"47",
    "addr:postcode":"3241 cc",
    "addr:street":"Eendrachtstraat",
    "iso:country":"NL",
    "sg:address":"Eendrachtstraat 47",
    "sg:city":"Middelharnis",
    "sg:classifiers":[
        {
            "category":"Shopping",
            "subcategory":"Gifts & Souvenirs",
            "type":"Retail Goods"
        }
    ],
    "sg:phone":"+31 187 482 939",
    "sg:postcode":"3241 CC",
    "sg:province":"Zuid-Holland",
    "sg:tags":[
        "geschenken"
    ],
    "wof:name":"Het Ambacht",
    "wof:placetype":"venue"
},
  "geometry": {"coordinates":[4.162733,51.759514],"type":"Point"}
}