{
  "type": "Feature",
  "properties": {
    "addr:full":"Jan Van Galenstraat 190 Amsterdam North Holland 1056 CJ",
    "addr:housenumber":"190",
    "addr:postcode":"1056 cj",
    "addr:street":"Jan Van Galenstraat",
    "iso:country":"NL",
    "sg:address":"Jan Van Galenstraat 190",
    "sg:city":"Amsterdam",
    "sg:orig_category":"Werving And Selectie Van Tijdelijk Personeel And Uitzendkantoren",
    "sg:phone":"+31 20 448 1807",
    "sg:postcode":"1056 CJ",
    "sg:province":"North Holland",
    "wof:name":"Equipe Vof",
    "wof:placetype":"venue"
},
  "geometry": {"coordinates":[4.8487458229,52.3727798462],"type":"Point"}
}