{
  "type": "Feature",
  "properties": {
    "addr:full":"Ommerenveldsewg 29 Ommeren Gelderland 4032 NA",
    "addr:housenumber":"29",
    "addr:postcode":"4032 na",
    "addr:street":"Ommerenveldsewg;Gelderland",
    "iso:country":"NL",
    "sg:address":"Ommerenveldsewg 29",
    "sg:city":"Ommeren",
    "sg:orig_category":"Foerage",
    "sg:phone":"+31 344 601 431",
    "sg:postcode":"4032 NA",
    "sg:province":"Gelderland",
    "wof:name":"Ommeren",
    "wof:placetype":"venue"
},
  "geometry": {"coordinates":[5.48355,51.934986],"type":"Point"}
}