{
  "type": "Feature",
  "properties": {
    "iso:country":"NL",
    "sg:address":"V Riebeeckstr 32",
    "sg:city":"Barneveld",
    "sg:orig_category":"Webdesign Bureaus",
    "sg:phone":"+31 6 24781375",
    "sg:postcode":"3772 KE",
    "sg:province":"Gelderland",
    "sg:website":"http://www.come-on.nl",
    "wof:name":"Come-On",
    "wof:placetype":"venue"
},
  "geometry": {"coordinates":[5.5888428688,52.1412162781],"type":"Point"}
}