{
  "type": "Feature",
  "properties": {
    "addr:full":"Bedrijfsweg 33 Dronten Flevoland 8251 KK",
    "addr:housenumber":"33",
    "addr:postcode":"8251 kk",
    "addr:street":"Bedrijfsweg;Flevoland",
    "iso:country":"NL",
    "sg:address":"Bedrijfsweg 33",
    "sg:city":"Dronten",
    "sg:orig_category":"Diverse Bedrijfsinstallaties Gh",
    "sg:phone":"+31 321 386 600",
    "sg:postcode":"8251 KK",
    "sg:province":"Flevoland",
    "wof:name":"Lets Bv",
    "wof:placetype":"venue"
},
  "geometry": {"coordinates":[5.717225,52.532322],"type":"Point"}
}