{
  "type": "Feature",
  "properties": {
    "addr:full":"Rudbeckialn 27 Heerhugowaard Noord-Holland 1702 LH",
    "addr:housenumber":"27",
    "addr:postcode":"1702 lh",
    "addr:street":"Rudbeckialn",
    "iso:country":"NL",
    "sg:address":"Rudbeckialn 27",
    "sg:city":"Heerhugowaard",
    "sg:orig_category":"Montagebedrijven",
    "sg:phone":"+31 72 574 1173",
    "sg:postcode":"1702 LH",
    "sg:province":"Noord-Holland",
    "wof:name":"Rlj",
    "wof:placetype":"venue"
},
  "geometry": {"coordinates":[4.848461,52.662247],"type":"Point"}
}