{
  "type": "Feature",
  "properties": {
    "addr:full":"Nieuwstraat 76 Bussum Noord-Holland 1404 JN",
    "addr:housenumber":"76",
    "addr:postcode":"1404 jn",
    "addr:street":"Nieuwstraat",
    "iso:country":"NL",
    "sg:address":"Nieuwstraat 76",
    "sg:city":"Bussum",
    "sg:orig_category":"Metaalwerken",
    "sg:phone":"+31 35 693 0358",
    "sg:postcode":"1404 JN",
    "sg:province":"Noord-Holland",
    "wof:name":"Helios Zonwering Vof",
    "wof:placetype":"venue"
},
  "geometry": {"coordinates":[5.165496,52.272663],"type":"Point"}
}