{
  "type": "Feature",
  "properties": {
    "addr:full":"Sluissedijk 4 Standdaarbuiten Noord-Brabant 4758 TW",
    "addr:housenumber":"4",
    "addr:postcode":"4758 tw",
    "addr:street":"Sluissedijk",
    "iso:country":"NL",
    "sg:address":"Sluissedijk 4",
    "sg:city":"Standdaarbuiten",
    "sg:orig_category":"Technische Studies And Onderzoek",
    "sg:phone":"+31 165 317 114",
    "sg:postcode":"4758 TW",
    "sg:province":"Noord-Brabant",
    "wof:name":"Rutten Bedrijfselectronica",
    "wof:placetype":"venue"
},
  "geometry": {"coordinates":[4.50495,51.617653],"type":"Point"}
}