{
  "type": "Feature",
  "properties": {
    "iso:country":"NL",
    "sg:address":"Bovenkerkerwg 112",
    "sg:city":"Amstelveen",
    "sg:orig_category":"Verlichtingsartikelen - Groothandel",
    "sg:phone":"+31 297 582 702",
    "sg:postcode":"1188 XH",
    "sg:province":"Noord-Holland",
    "sg:website":"http://www.westiform.com",
    "wof:name":"Westiform International Gmbh",
    "wof:placetype":"venue"
},
  "geometry": {"coordinates":[4.837759,52.263168],"type":"Point"}
}