{
  "type": "Feature",
  "properties": {
    "iso:country":"NL",
    "sg:address":"Nieuwstraat 83",
    "sg:city":"Eibergen",
    "sg:orig_category":"Bouwmaterialen Gh",
    "sg:phone":"+31 545 461 515",
    "sg:postcode":"7151 CD",
    "sg:province":"Gelderland",
    "wof:name":"Bouwcenter Ecb",
    "wof:placetype":"venue"
},
  "geometry": {"coordinates":[6.643418,52.100014],"type":"Point"}
}