{
  "type": "Feature",
  "properties": {
    "addr:full":"Echtenstein 100N Amsterdam Zuidoost North Holland 1103 AB",
    "addr:housenumber":"100n",
    "addr:postcode":"1103 ab",
    "addr:street":"Echtenstein",
    "iso:country":"NL",
    "sg:address":"Echtenstein 100N",
    "sg:city":"Amsterdam Zuidoost",
    "sg:orig_category":"Adviesbureaus Bedrijfsorganisatie",
    "sg:phone":"+31 20 600 6336",
    "sg:postcode":"1103 AB",
    "sg:province":"North Holland",
    "wof:name":"Ondernemershuis, Het",
    "wof:placetype":"venue"
},
  "geometry": {"coordinates":[4.961032,52.324863],"type":"Point"}
}