{
  "type": "Feature",
  "properties": {
    "addr:full":"Zwanebloem 9 Purmerend Noord-Holland 1441 TR",
    "addr:housenumber":"9",
    "addr:postcode":"1441 tr",
    "addr:street":"Zwanebloem",
    "iso:country":"NL",
    "sg:address":"Zwanebloem 9",
    "sg:city":"Purmerend",
    "sg:orig_category":"Postkantoren",
    "sg:phone":"+31 299 426 651",
    "sg:postcode":"1441 TR",
    "sg:province":"Noord-Holland",
    "sg:website":"http://www.postkantoor.nl",
    "wof:name":"Postkantoor",
    "wof:placetype":"venue"
},
  "geometry": {"coordinates":[4.952664,52.493885],"type":"Point"}
}