{
  "type": "Feature",
  "properties": {
    "addr:full":"Kapolder 7 Wijlre Limburg 6321 PT",
    "addr:housenumber":"7",
    "addr:postcode":"6321 pt",
    "addr:street":"Kapolder",
    "iso:country":"NL",
    "sg:address":"Kapolder 7",
    "sg:city":"Wijlre",
    "sg:orig_category":"Bloemen And Planten",
    "sg:phone":"+31 43 450 1764",
    "sg:postcode":"6321 PT",
    "sg:province":"Limburg",
    "wof:name":"Plantencentrum Kapolder",
    "wof:placetype":"venue"
},
  "geometry": {"coordinates":[5.900441,50.825916],"type":"Point"}
}