{
  "type": "Feature",
  "properties": {
    "addr:full":"Boswg 8 Putte North Brabant 4645 RB",
    "addr:housenumber":"8",
    "addr:postcode":"4645 rb",
    "addr:street":"Boswg",
    "iso:country":"NL",
    "sg:address":"Boswg 8",
    "sg:city":"Putte",
    "sg:orig_category":"Machinefabrieken",
    "sg:phone":"+31 164 602 233",
    "sg:postcode":"4645 RB",
    "sg:province":"North Brabant",
    "wof:name":"Rodiwe Bv",
    "wof:placetype":"venue"
},
  "geometry": {"coordinates":[4.401774,51.363903],"type":"Point"}
}