{
  "type": "Feature",
  "properties": {
    "addr:full":"Lange Nieuwstraat 169 Schiedam Zuid-Holland 3111 AJ",
    "addr:housenumber":"169",
    "addr:postcode":"3111 aj",
    "addr:street":"Lange Nieuwstraat",
    "iso:country":"NL",
    "sg:address":"Lange Nieuwstraat 169",
    "sg:city":"Schiedam",
    "sg:orig_category":"Architecten",
    "sg:phone":"+31 10 473 2948",
    "sg:postcode":"3111 AJ",
    "sg:province":"Zuid-Holland",
    "wof:name":"H. Meijer",
    "wof:placetype":"venue"
},
  "geometry": {"coordinates":[4.401801,51.912151],"type":"Point"}
}