{
  "type": "Feature",
  "properties": {
    "addr:full":"C V Uitgeeststr 2D Zaandam Noord-Holland 1508 EH",
    "addr:housenumber":"2d",
    "addr:postcode":"1508 eh",
    "addr:street":"V Uitgeeststr",
    "iso:country":"NL",
    "sg:address":"C V Uitgeeststr 2D",
    "sg:city":"Zaandam",
    "sg:orig_category":"Architecten En Architectenbureaus",
    "sg:phone":"+31 75 670 0695",
    "sg:postcode":"1508 EH",
    "sg:province":"Noord-Holland",
    "sg:website":"http://www.wester-carree.nl",
    "wof:name":"Wester En Carree",
    "wof:placetype":"venue"
},
  "geometry": {"coordinates":[4.81295,52.44162],"type":"Point"}
}