{
  "type": "Feature",
  "properties": {
    "addr:full":"Molenwg 54 Oud Vossemeer Zeeland 4698 PM",
    "addr:housenumber":"54",
    "addr:postcode":"4698 pm",
    "addr:street":"Molenwg",
    "iso:country":"NL",
    "sg:address":"Molenwg 54",
    "sg:city":"Oud Vossemeer",
    "sg:classifiers":[
        {
            "category":"Sports & Exercise",
            "subcategory":"Stables",
            "type":"Entertainment"
        }
    ],
    "sg:phone":"+31 166 672 489",
    "sg:postcode":"4698 PM",
    "sg:province":"Zeeland",
    "sg:tags":[
        "maneges"
    ],
    "wof:name":"Fjorden Plezier",
    "wof:placetype":"venue"
},
  "geometry": {"coordinates":[4.199506,51.556133],"type":"Point"}
}