{
  "type": "Feature",
  "properties": {
    "addr:full":"R De Beerenb Pln 5 Delft Zuid-Holland 2613 AR",
    "addr:housenumber":"5",
    "addr:postcode":"2613",
    "addr:street":"Pln",
    "iso:country":"NL",
    "sg:address":"R De Beerenb Pln 5",
    "sg:city":"Delft",
    "sg:orig_category":"Makelaars En Adviseurs Onroerende Goederen",
    "sg:phone":"+31 15 215 4848",
    "sg:postcode":"2613 AR",
    "sg:province":"Zuid-Holland",
    "sg:website":"http://www.roeststaalduinen.nl",
    "wof:name":"Roest/Staalduinen",
    "wof:placetype":"venue"
},
  "geometry": {"coordinates":[-95.0895,43.990925],"type":"Point"}
}