{
  "type": "Feature",
  "properties": {
    "addr:full":"Klaphekwg 47 Ede Gld Gelderland 6713 HM",
    "addr:housenumber":"47",
    "addr:postcode":"6713 hm",
    "addr:street":"Klaphekwg;Gld Gelderland",
    "iso:country":"NL",
    "sg:address":"Klaphekwg 47",
    "sg:city":"Ede Gld",
    "sg:orig_category":"Kappers",
    "sg:phone":"+31 318 611 256",
    "sg:postcode":"6713 HM",
    "sg:province":"Gelderland",
    "wof:name":"Haak, E Ter",
    "wof:placetype":"venue"
},
  "geometry": {"coordinates":[5.654692173,52.0340499878],"type":"Point"}
}