{
  "type": "Feature",
  "properties": {
    "addr:full":"S Gravenzandsewg 91 Naaldwyk South Holland 2671 JK",
    "addr:housenumber":"91",
    "addr:postcode":"2671 jk",
    "addr:street":"Naaldwyk South",
    "iso:country":"NL",
    "sg:address":"S Gravenzandsewg 91",
    "sg:city":"Naaldwyk",
    "sg:orig_category":"Luchtvaart- Maatschappijen",
    "sg:phone":"+31 6 22239809",
    "sg:postcode":"2671 JK",
    "sg:province":"South Holland",
    "sg:website":"http://www.flytopfun.nl",
    "wof:name":"Top Fun",
    "wof:placetype":"venue"
},
  "geometry": {"coordinates":[4.201244,51.989971],"type":"Point"}
}