{
  "type": "Feature",
  "properties": {
    "addr:full":"Molenwg 1 Heerde Gelderland 8181 BJ",
    "addr:housenumber":"1",
    "addr:postcode":"8181 bj",
    "addr:street":"Molenwg;Gelderland",
    "iso:country":"NL",
    "sg:address":"Molenwg 1",
    "sg:city":"Heerde",
    "sg:orig_category":"Woningbouw- Verenigingen En -Stichtingen",
    "sg:phone":"+31 578 676 630",
    "sg:postcode":"8181 BJ",
    "sg:province":"Gelderland",
    "wof:name":"Triada Wonen",
    "wof:placetype":"venue"
},
  "geometry": {"coordinates":[6.049077034,52.3997573853],"type":"Point"}
}