{
  "type": "Feature",
  "properties": {
    "iso:country":"NL",
    "sg:address":"Lijsterlaan 8",
    "sg:city":"Apeldoorn",
    "sg:orig_category":"Gespecialiseerde Bouw",
    "sg:phone":"+31 55 533 4563",
    "sg:postcode":"7331 TV",
    "sg:province":"Gelderland",
    "wof:name":"F Van Den Bosch",
    "wof:placetype":"venue"
},
  "geometry": {"coordinates":[5.969794,52.204277],"type":"Point"}
}