{
  "type": "Feature",
  "properties": {
    "addr:full":"Scholeksterstraat 16 Leiderdorp Zuid-Holland 2352 EE",
    "addr:housenumber":"16",
    "addr:postcode":"2352 ee",
    "addr:street":"Scholeksterstraat",
    "iso:country":"NL",
    "sg:address":"Scholeksterstraat 16",
    "sg:city":"Leiderdorp",
    "sg:orig_category":"Krantenuitgeverijen",
    "sg:phone":"+31 71 542 1400",
    "sg:postcode":"2352 EE",
    "sg:province":"Zuid-Holland",
    "wof:name":"Deo Publishing",
    "wof:placetype":"venue"
},
  "geometry": {"coordinates":[4.524803,52.161648],"type":"Point"}
}