{
  "type": "Feature",
  "properties": {
    "addr:full":"Brugwg 35 Waddinxveen Zuid-Holland 2741 KT",
    "addr:housenumber":"35",
    "addr:postcode":"2741 kt",
    "addr:street":"Brugwg",
    "iso:country":"NL",
    "sg:address":"Brugwg 35",
    "sg:city":"Waddinxveen",
    "sg:orig_category":"Adviesbureaus Bedrijfsorganisatie",
    "sg:phone":"+31 182 610 212",
    "sg:postcode":"2741 KT",
    "sg:province":"Zuid-Holland",
    "sg:website":"http://www.jwrconsult.com",
    "wof:name":"Jwr Consult",
    "wof:placetype":"venue"
},
  "geometry": {"coordinates":[4.662076,52.043716],"type":"Point"}
}