{
  "type": "Feature",
  "properties": {
    "iso:country":"NL",
    "sg:address":"Dorpswg 148",
    "sg:city":"Arkel",
    "sg:orig_category":"Lederwaren - Fabrieken En Groothandel",
    "sg:phone":"+31 183 565 039",
    "sg:postcode":"4241 LC",
    "sg:province":"Zuid-Holland",
    "sg:website":"HTTP://www.liams.nl",
    "wof:name":"Liams Lederwaren Vof",
    "wof:placetype":"venue"
},
  "geometry": {"coordinates":[4.98772,51.873878],"type":"Point"}
}