{
  "type": "Feature",
  "properties": {
    "addr:full":"Sprendlingenstraat 18 Oisterwijk North Brabant 5061 KN",
    "addr:housenumber":"18",
    "addr:postcode":"5061 kn",
    "addr:street":"Sprendlingenstraat",
    "iso:country":"NL",
    "sg:address":"Sprendlingenstraat 18",
    "sg:city":"Oisterwijk",
    "sg:orig_category":"Webdesign Bureaus",
    "sg:phone":"+31 13 523 4958",
    "sg:postcode":"5061 KN",
    "sg:province":"North Brabant",
    "sg:website":"http://www.pharosmultimedia.nl",
    "wof:name":"Pharos Bv",
    "wof:placetype":"venue"
},
  "geometry": {"coordinates":[5.1883449554,51.5852851868],"type":"Point"}
}