{
  "type": "Feature",
  "properties": {
    "addr:full":"Dorpsstraat 387 Assendelft North Holland 1566 BE",
    "addr:housenumber":"387",
    "addr:postcode":"1566",
    "addr:street":"Dorpsstraat",
    "iso:country":"NL",
    "sg:address":"Dorpsstraat 387",
    "sg:city":"Assendelft",
    "sg:orig_category":"Juweliers",
    "sg:phone":"+31 75 687 7343",
    "sg:postcode":"1566 BE",
    "sg:province":"North Holland",
    "wof:name":"Juwelier Sandra Brandse",
    "wof:placetype":"venue"
},
  "geometry": {"coordinates":[4.740697,52.4664],"type":"Point"}
}