{
  "type": "Feature",
  "properties": {
    "addr:full":"Fokkerstr 497 Schiedam Zuid-Holland 3125 BD",
    "addr:housenumber":"497",
    "addr:postcode":"3125 bd",
    "iso:country":"NL",
    "sg:address":"Fokkerstr 497",
    "sg:city":"Schiedam",
    "sg:orig_category":"Machinehandel",
    "sg:phone":"+31 10 437 8686",
    "sg:postcode":"3125 BD",
    "sg:province":"Zuid-Holland",
    "wof:name":"Migromatic Bv",
    "wof:placetype":"venue"
},
  "geometry": {"coordinates":[4.397858,51.933151],"type":"Point"}
}