{
  "type": "Feature",
  "properties": {
    "iso:country":"NL",
    "sg:address":"Bergse Dorpsstraat 142",
    "sg:city":"Rotterdam",
    "sg:orig_category":"Biljart- And Snookerzalen",
    "sg:phone":"+31 10 422 9853",
    "sg:postcode":"3054 GH",
    "sg:province":"South Holland",
    "wof:name":"Van Eijk",
    "wof:placetype":"venue"
},
  "geometry": {"coordinates":[4.494487,51.958607],"type":"Point"}
}