{
  "type": "Feature",
  "properties": {
    "addr:full":"Bysterhuizen 1101 Nymegen Distrito Federal 6546 AR",
    "addr:housenumber":"1101",
    "addr:postcode":"6546",
    "addr:street":"Nymegen",
    "iso:country":"NL",
    "sg:address":"Bysterhuizen 1101",
    "sg:city":"Nymegen",
    "sg:orig_category":"Benzine En Olie - Groothandel",
    "sg:phone":"+31 24 344 4422",
    "sg:postcode":"6546 AR",
    "sg:province":"Distrito Federal",
    "wof:name":"Nijol Oliemaatschappij Bv",
    "wof:placetype":"venue"
},
  "geometry": {"coordinates":[-58.369381,-34.587158],"type":"Point"}
}