{
  "type": "Feature",
  "properties": {
    "addr:full":"Brandewyk 2B Boelenslaan Provincie Friesland 9233 KK",
    "addr:housenumber":"2b",
    "addr:postcode":"9233 kk",
    "addr:street":"Brandewyk;Provincie Friesland",
    "iso:country":"NL",
    "sg:address":"Brandewyk 2B",
    "sg:city":"Boelenslaan",
    "sg:orig_category":"Wegen And Sportterreinen",
    "sg:phone":"+31 512 341 739",
    "sg:postcode":"9233 KK",
    "sg:province":"Provincie Friesland",
    "wof:name":"L. V.D. Veen",
    "wof:placetype":"venue"
},
  "geometry": {"coordinates":[6.1413230896,53.1624832153],"type":"Point"}
}