{
  "type": "Feature",
  "properties": {
    "addr:full":"Handelswg 1A Maarssen Utrecht 3606 AA",
    "addr:housenumber":"1a",
    "addr:postcode":"3606 aa",
    "addr:street":"Handelswg",
    "iso:country":"NL",
    "sg:address":"Handelswg 1A",
    "sg:city":"Maarssen",
    "sg:orig_category":"Bakkerijbenodigdheden En -Grondstoffen",
    "sg:phone":"+31 346 562 276",
    "sg:postcode":"3606 AA",
    "sg:province":"Utrecht",
    "wof:name":"Buyl Utrecht Bv",
    "wof:placetype":"venue"
},
  "geometry": {"coordinates":[5.036495,52.130108],"type":"Point"}
}