{
  "type": "Feature",
  "properties": {
    "iso:country":"NL",
    "sg:address":"Nw Vissershaven 5",
    "sg:city":"Harlingen",
    "sg:orig_category":"Scheepvaartmijen",
    "sg:phone":"+31 517 415 442",
    "sg:postcode":"8861 NX",
    "sg:province":"Provincie Friesland",
    "sg:website":"http://www.vanstee.com",
    "wof:name":"Stee Survey & Supply, Van",
    "wof:placetype":"venue"
},
  "geometry": {"coordinates":[5.423044,53.182846],"type":"Point"}
}