{
  "type": "Feature",
  "properties": {
    "addr:full":"Meerstr 15 Puiflijk Gelderland 6655 AS",
    "addr:housenumber":"15",
    "addr:postcode":"6655 as",
    "addr:street":"Meerstr;Gelderland",
    "iso:country":"NL",
    "sg:address":"Meerstr 15",
    "sg:city":"Puiflijk",
    "sg:orig_category":"Artsen - Huisartsen",
    "sg:phone":"+31 487 513 486",
    "sg:postcode":"6655 AS",
    "sg:province":"Gelderland",
    "wof:name":"Piek, J P L",
    "wof:placetype":"venue"
},
  "geometry": {"coordinates":[5.586546,51.874641],"type":"Point"}
}