{
  "type": "Feature",
  "properties": {
    "addr:full":"Spykerboorstg 15 Leiden South Holland 2312 GN",
    "addr:housenumber":"15",
    "addr:postcode":"2312 gn",
    "addr:street":"Spykerboorstg",
    "iso:country":"NL",
    "sg:address":"Spykerboorstg 15",
    "sg:city":"Leiden",
    "sg:orig_category":"Zalenverhuur",
    "sg:phone":"+31 71 514 2473",
    "sg:postcode":"2312 GN",
    "sg:province":"South Holland",
    "wof:name":"Romanuszaal",
    "wof:placetype":"venue"
},
  "geometry": {"coordinates":[4.490506,52.160969],"type":"Point"}
}