{
  "type": "Feature",
  "properties": {
    "addr:full":"Gedempte Baansloot 11 Alkmaar Noord-Holland 1811 DJ",
    "addr:housenumber":"11",
    "addr:postcode":"1811 dj",
    "addr:street":"Gedempte Baansloot",
    "iso:country":"NL",
    "sg:address":"Gedempte Baansloot 11",
    "sg:city":"Alkmaar",
    "sg:orig_category":"Autokeuringen",
    "sg:phone":"+31 72 511 7634",
    "sg:postcode":"1811 DJ",
    "sg:province":"Noord-Holland",
    "wof:name":"Victoria Garage Servicestation",
    "wof:placetype":"venue"
},
  "geometry": {"coordinates":[4.747083,52.628544],"type":"Point"}
}