{
  "type": "Feature",
  "properties": {
    "addr:full":"Molenwal 2 Gorredyk Friesland 8401 CD",
    "addr:housenumber":"2",
    "addr:postcode":"8401 cd",
    "addr:street":"Molenwal",
    "iso:country":"NL",
    "sg:address":"Molenwal 2",
    "sg:city":"Gorredyk",
    "sg:orig_category":"Kappers",
    "sg:phone":"+31 513 461 580",
    "sg:postcode":"8401 CD",
    "sg:province":"Friesland",
    "wof:name":"Kees En Sita",
    "wof:placetype":"venue"
},
  "geometry": {"coordinates":[6.0635027885,53.0027542114],"type":"Point"}
}