{
  "type": "Feature",
  "properties": {
    "addr:full":"Sneeuwberglaan 1 Vaals Limburg 6291 HB",
    "addr:housenumber":"1",
    "addr:postcode":"6291 hb",
    "addr:street":"Sneeuwberglaan",
    "iso:country":"NL",
    "sg:address":"Sneeuwberglaan 1",
    "sg:city":"Vaals",
    "sg:orig_category":"Overheidsdiensten",
    "sg:phone":"+31 43 306 2109",
    "sg:postcode":"6291 HB",
    "sg:province":"Limburg",
    "wof:name":"Spuugh 70",
    "wof:placetype":"venue"
},
  "geometry": {"coordinates":[6.0211529732,50.7752838135],"type":"Point"}
}