{
  "type": "Feature",
  "properties": {
    "iso:country":"NL",
    "sg:address":"Kerkstr 57",
    "sg:city":"Uden",
    "sg:orig_category":"Kunsthandel",
    "sg:phone":"+31 413 260 299",
    "sg:postcode":"5401 BD",
    "sg:province":"Noord-Brabant",
    "wof:name":"Brabant",
    "wof:placetype":"venue"
},
  "geometry": {"coordinates":[89.262512,25.728161],"type":"Point"}
}