{
  "type": "Feature",
  "properties": {
    "iso:country":"NL",
    "sg:address":"Hg Giessen 7",
    "sg:city":"Hoogblokland",
    "sg:orig_category":"Zeilmakerijen",
    "sg:phone":"+31 183 582 530",
    "sg:postcode":"4221 MA",
    "sg:province":"South Holland",
    "wof:name":"Koster - Romeijn Vof",
    "wof:placetype":"venue"
},
  "geometry": {"coordinates":[4.96263,51.880562],"type":"Point"}
}