{
  "type": "Feature",
  "properties": {
    "addr:full":"Veerweg 104 Papendrecht Zuid-Holland 3353 GW",
    "addr:housenumber":"104",
    "addr:postcode":"3353 gw",
    "addr:street":"Veerweg",
    "iso:country":"NL",
    "sg:address":"Veerweg 104",
    "sg:city":"Papendrecht",
    "sg:orig_category":"Goederenvervoer Over De Weg",
    "sg:phone":"+31 78 615 8769",
    "sg:postcode":"3353 GW",
    "sg:province":"Zuid-Holland",
    "wof:name":"Troost Transport Papendrecht",
    "wof:placetype":"venue"
},
  "geometry": {"coordinates":[4.686637,51.82896],"type":"Point"}
}