{
  "type": "Feature",
  "properties": {
    "addr:full":"De Wingerd 11 Beek En Donk North Brabant 5741 DH",
    "addr:housenumber":"11",
    "addr:postcode":"5741 dh",
    "addr:street":"De Wingerd",
    "iso:country":"NL",
    "sg:address":"De Wingerd 11",
    "sg:city":"Beek En Donk",
    "sg:orig_category":"Kappers",
    "sg:phone":"+31 492 465 445",
    "sg:postcode":"5741 DH",
    "sg:province":"North Brabant",
    "wof:name":"Bouw Rijdende Kapsalon Miranda",
    "wof:placetype":"venue"
},
  "geometry": {"coordinates":[5.6197490692,51.5425415039],"type":"Point"}
}