{
  "type": "Feature",
  "properties": {
    "addr:full":"Voorbaan 60 Huizen Noord-Holland 1271 WS",
    "addr:housenumber":"60",
    "addr:postcode":"1271 ws",
    "addr:street":"Voorbaan",
    "iso:country":"NL",
    "sg:address":"Voorbaan 60",
    "sg:city":"Huizen",
    "sg:orig_category":"Kappers",
    "sg:phone":"+31 35 525 0997",
    "sg:postcode":"1271 WS",
    "sg:province":"Noord-Holland",
    "wof:name":"Pointen Hairstyling",
    "wof:placetype":"venue"
},
  "geometry": {"coordinates":[5.233883,52.29929],"type":"Point"}
}