{
  "type": "Feature",
  "properties": {
    "iso:country":"NL",
    "sg:address":"Villawal 21",
    "sg:city":"Nieuwegein",
    "sg:orig_category":"Projectontwikkeling",
    "sg:phone":"+31 30 604 1734",
    "sg:postcode":"3432 NX",
    "sg:province":"Utrecht",
    "wof:name":"Nawon Groep Bv",
    "wof:placetype":"venue"
},
  "geometry": {"coordinates":[5.089723,52.028545],"type":"Point"}
}