{
  "type": "Feature",
  "properties": {
    "addr:full":"Lemselosestraat 5 Weerselo NL.08 7595 ML",
    "addr:housenumber":"5;nl.08",
    "addr:postcode":"7595 ml",
    "addr:street":"Lemselosestraat",
    "iso:country":"NL",
    "sg:address":"Lemselosestraat 5",
    "sg:city":"Weerselo",
    "sg:orig_category":"Levende Dieren Gh",
    "sg:phone":"+31 541 661 745",
    "sg:postcode":"7595 ML",
    "sg:province":"NL.08",
    "wof:name":"Tonny Bossink",
    "wof:placetype":"venue"
},
  "geometry": {"coordinates":[6.870047,52.339615],"type":"Point"}
}