{
  "type": "Feature",
  "properties": {
    "addr:full":"Voortswg 107 Enschede NL.08 7523 CD",
    "addr:housenumber":"107",
    "addr:postcode":"7523 cd",
    "iso:country":"NL",
    "sg:address":"Voortswg 107",
    "sg:city":"Enschede",
    "sg:classifiers":[
        {
            "category":"Farming",
            "subcategory":"Fish & Marine Products",
            "type":"Manufacturing & Wholesale Goods"
        }
    ],
    "sg:phone":"+31 53 435 8338",
    "sg:postcode":"7523 CD",
    "sg:province":"NL.08",
    "sg:tags":[
        "vi"
    ],
    "wof:name":"Keizer, B",
    "wof:placetype":"venue"
},
  "geometry": {"coordinates":[6.899615,52.231968],"type":"Point"}
}