{
  "type": "Feature",
  "properties": {
    "iso:country":"NL",
    "sg:address":"Dr Ottestr 105",
    "sg:city":"Vlissingen",
    "sg:classifiers":[
        {
            "category":"Travel",
            "subcategory":"Hotels & Motels",
            "type":"Entertainment"
        }
    ],
    "sg:phone":"+31 118 444 550",
    "sg:postcode":"4382 LV",
    "sg:province":"Zeeland",
    "wof:name":"Dix",
    "wof:placetype":"venue"
},
  "geometry": {"coordinates":[3.5706009865,51.449344635],"type":"Point"}
}