{
  "type": "Feature",
  "properties": {
    "addr:full":"Verlaatswg 18 Rysenhout North Holland 1435 GW",
    "addr:housenumber":"18",
    "addr:postcode":"1435 gw",
    "addr:street":"Verlaatswg;North",
    "iso:country":"NL",
    "sg:address":"Verlaatswg 18",
    "sg:city":"Rysenhout",
    "sg:orig_category":"Fotojournalisten Freelance",
    "sg:phone":"+31 297 340 850",
    "sg:postcode":"1435 GW",
    "sg:province":"North Holland",
    "wof:name":"Joore, Robert",
    "wof:placetype":"venue"
},
  "geometry": {"coordinates":[4.70562,52.25679],"type":"Point"}
}