{
  "type": "Feature",
  "properties": {
    "addr:full":"Grotestraat 70 Waalwijk Noord-Brabant 5141 HB",
    "addr:housenumber":"70",
    "addr:postcode":"5141 hb",
    "addr:street":"Grotestraat",
    "iso:country":"NL",
    "sg:address":"Grotestraat 70",
    "sg:city":"Waalwijk",
    "sg:orig_category":"Werving And Selectie Van Tijdelijk Personeel And Uitzendkantoren",
    "sg:phone":"+31 416 651 919",
    "sg:postcode":"5141 HB",
    "sg:province":"Noord-Brabant",
    "wof:name":"Eksakt",
    "wof:placetype":"venue"
},
  "geometry": {"coordinates":[5.0550041199,51.6890869141],"type":"Point"}
}