{
  "type": "Feature",
  "properties": {
    "addr:full":"Optwizel 48 Twyzel Provincie Friesland 9286 EE",
    "addr:housenumber":"48",
    "addr:postcode":"9286 ee",
    "addr:street":"Optwizel;Provincie Friesland",
    "iso:country":"NL",
    "sg:address":"Optwizel 48",
    "sg:city":"Twyzel",
    "sg:orig_category":"Cafetaria'S",
    "sg:phone":"+31 511 544 739",
    "sg:postcode":"9286 EE",
    "sg:province":"Provincie Friesland",
    "wof:name":"Groot, K De",
    "wof:placetype":"venue"
},
  "geometry": {"coordinates":[6.089611,53.231354],"type":"Point"}
}