{
  "type": "Feature",
  "properties": {
    "addr:full":"Haarstraat 15 Rijssen NL.08 7462 AK",
    "addr:housenumber":"15;nl.08",
    "addr:postcode":"7462 ak",
    "addr:street":"Haarstraat",
    "iso:country":"NL",
    "sg:address":"Haarstraat 15",
    "sg:city":"Rijssen",
    "sg:orig_category":"Discountwinkels",
    "sg:phone":"+31 548 512 584",
    "sg:postcode":"7462 AK",
    "sg:province":"NL.08",
    "wof:name":"Koedijk'S Linnenhuis",
    "wof:placetype":"venue"
},
  "geometry": {"coordinates":[6.519698,52.307648],"type":"Point"}
}