{
  "type": "Feature",
  "properties": {
    "addr:full":"Adriaen Van Ostadehof 18 Deurne Noord-Brabant 5753 CP",
    "addr:housenumber":"18",
    "addr:postcode":"5753 cp",
    "addr:street":"Adriaen Van Ostadehof",
    "iso:country":"NL",
    "sg:address":"Adriaen Van Ostadehof 18",
    "sg:city":"Deurne",
    "sg:orig_category":"Tandartsen",
    "sg:phone":"+31 493 311 720",
    "sg:postcode":"5753 CP",
    "sg:province":"Noord-Brabant",
    "wof:name":"J.A.M. Koolen",
    "wof:placetype":"venue"
},
  "geometry": {"coordinates":[5.788125,51.454407],"type":"Point"}
}