{
  "type": "Feature",
  "properties": {
    "addr:full":"Reggestraat 23 Deventer Overijssel 7417 XS",
    "addr:housenumber":"23",
    "addr:postcode":"7417 xs",
    "addr:street":"Reggestraat",
    "iso:country":"NL",
    "sg:address":"Reggestraat 23",
    "sg:city":"Deventer",
    "sg:orig_category":"Meubelreparatie And -Restauratie",
    "sg:phone":"+31 570 621 009",
    "sg:postcode":"7417 XS",
    "sg:province":"Overijssel",
    "wof:name":"Kramer Reparatieatelier",
    "wof:placetype":"venue"
},
  "geometry": {"coordinates":[6.17742,52.254906],"type":"Point"}
}