{
  "type": "Feature",
  "properties": {
    "addr:full":"Arkelse Onderwg 83 Gorinchem Zuid-Holland 4206 AG",
    "addr:housenumber":"83",
    "addr:postcode":"4206",
    "iso:country":"NL",
    "sg:address":"Arkelse Onderwg 83",
    "sg:city":"Gorinchem",
    "sg:orig_category":"Adviesbureaus Bedrijfsorganisatie",
    "sg:phone":"+31 183 699 488",
    "sg:postcode":"4206 AG",
    "sg:province":"Zuid-Holland",
    "wof:name":"Prospect",
    "wof:placetype":"venue"
},
  "geometry": {"coordinates":[4.984712,51.84296],"type":"Point"}
}