{
  "type": "Feature",
  "properties": {
    "iso:country":"NL",
    "sg:address":"Postbus 95191",
    "sg:city":"Amsterdam",
    "sg:orig_category":"Hotels: Reservation",
    "sg:phone":"+31 20 679 9203",
    "sg:postcode":"1090 HD",
    "sg:province":"Noord-Holland",
    "sg:website":"http://www.housinghunters.com",
    "wof:name":"Holiday-Exchanges Humij Bv",
    "wof:placetype":"venue"
},
  "geometry": {"coordinates":[4.89205,52.37355],"type":"Point"}
}