{
  "type": "Feature",
  "properties": {
    "addr:full":"Kruisakker 12 Nuenen Noord-Brabant 5674 TZ",
    "addr:housenumber":"12",
    "addr:postcode":"5674 tz",
    "addr:street":"Kruisakker",
    "iso:country":"NL",
    "sg:address":"Kruisakker 12",
    "sg:city":"Nuenen",
    "sg:orig_category":"Medische And Orthopedische Artikelen",
    "sg:phone":"+31 40 283 6442",
    "sg:postcode":"5674 TZ",
    "sg:province":"Noord-Brabant",
    "wof:name":"Tripod Autoaanpassingen Bv",
    "wof:placetype":"venue"
},
  "geometry": {"coordinates":[5.544539,51.448673],"type":"Point"}
}