{
  "type": "Feature",
  "properties": {
    "addr:full":"Rijksweg 160 Limmen Valais 1906 BL",
    "addr:housenumber":"160",
    "addr:postcode":"1906 bl",
    "addr:street":"Rijksweg",
    "iso:country":"NL",
    "sg:address":"Rijksweg 160",
    "sg:city":"Limmen",
    "sg:orig_category":"Autokeuringen",
    "sg:phone":"+31 72 505 3645",
    "sg:postcode":"1906 BL",
    "sg:province":"Valais",
    "wof:name":"Harry Levering Autobedrijf",
    "wof:placetype":"venue"
},
  "geometry": {"coordinates":[7.129689,46.124989],"type":"Point"}
}