{
  "type": "Feature",
  "properties": {
    "addr:full":"Herenwg 165 Vinkeveen Utrecht 3645 DK",
    "addr:housenumber":"165",
    "addr:postcode":"3645 dk",
    "addr:street":"Vinkeveen",
    "iso:country":"NL",
    "sg:address":"Herenwg 165",
    "sg:city":"Vinkeveen",
    "sg:classifiers":[
        {
            "category":"Retail",
            "subcategory":"Auto Repair",
            "type":"Services"
        }
    ],
    "sg:phone":"+31 297 261 333",
    "sg:postcode":"3645 DK",
    "sg:province":"Utrecht",
    "sg:tags":[
        "garage"
    ],
    "sg:website":"http://www.ford.nl",
    "wof:name":"Stoof Vinkeveen, Autobedrijf",
    "wof:placetype":"venue"
},
  "geometry": {"coordinates":[4.933081,52.218998],"type":"Point"}
}