{
  "type": "Feature",
  "properties": {
    "addr:full":"Concoursln 104 Hoofddorp Noord-Holland 2132 DK",
    "addr:housenumber":"104",
    "addr:postcode":"2132 dk",
    "iso:country":"NL",
    "sg:address":"Concoursln 104",
    "sg:city":"Hoofddorp",
    "sg:orig_category":"Babyartikelen",
    "sg:phone":"+31 23 555 4479",
    "sg:postcode":"2132 DK",
    "sg:province":"Noord-Holland",
    "wof:name":"Pr?natal",
    "wof:placetype":"venue"
},
  "geometry": {"coordinates":[4.69296,52.305393],"type":"Point"}
}