{
  "type": "Feature",
  "properties": {
    "addr:full":"Moeraszegge 22 Nieuw Lekkerland Zuid-Holland 2957 RL",
    "addr:housenumber":"22",
    "addr:postcode":"lekkerland;2957 rl",
    "addr:street":"Moeraszegge",
    "iso:country":"NL",
    "sg:address":"Moeraszegge 22",
    "sg:city":"Nieuw Lekkerland",
    "sg:orig_category":"Boekhouders",
    "sg:phone":"+31 184 684 606",
    "sg:postcode":"2957 RL",
    "sg:province":"Zuid-Holland",
    "wof:name":"Administratiekantoor De Heer",
    "wof:placetype":"venue"
},
  "geometry": {"coordinates":[4.681567,51.886906],"type":"Point"}
}