{
  "type": "Feature",
  "properties": {
    "addr:full":"Oud Loosdrechtsedijk 35 Loosdrecht Noord-Holland 1231 LP",
    "addr:housenumber":"35",
    "addr:postcode":"1231 lp",
    "addr:street":"Oud Loosdrechtsedijk",
    "iso:country":"NL",
    "sg:address":"Oud Loosdrechtsedijk 35",
    "sg:city":"Loosdrecht",
    "sg:orig_category":"Bedrijfsinventaris Gh",
    "sg:phone":"+31 35 582 3105",
    "sg:postcode":"1231 LP",
    "sg:province":"Noord-Holland",
    "wof:name":"Van Zijtveld Machineverhuur Vof",
    "wof:placetype":"venue"
},
  "geometry": {"coordinates":[5.117235,52.206699],"type":"Point"}
}