{
  "type": "Feature",
  "properties": {
    "addr:full":"Kopsehof 23 Arnhem Gelderland 6834 EJ",
    "addr:housenumber":"23",
    "addr:postcode":"6834 ej",
    "addr:street":"Kopsehof",
    "iso:country":"NL",
    "sg:address":"Kopsehof 23",
    "sg:city":"Arnhem",
    "sg:orig_category":"Zonweringen",
    "sg:phone":"+31 26 321 0334",
    "sg:postcode":"6834 EJ",
    "sg:province":"Gelderland",
    "wof:name":"Jordens",
    "wof:placetype":"venue"
},
  "geometry": {"coordinates":[5.924208,51.952209],"type":"Point"}
}