{
  "type": "Feature",
  "properties": {
    "addr:full":"Seringenstraat 15 Kerkrade Limburg 6466 XL",
    "addr:housenumber":"15",
    "addr:postcode":"6466 xl",
    "addr:street":"Seringenstraat",
    "iso:country":"NL",
    "sg:address":"Seringenstraat 15",
    "sg:city":"Kerkrade",
    "sg:orig_category":"Beautyfarms And Sauna'S",
    "sg:phone":"+31 45 541 5092",
    "sg:postcode":"6466 XL",
    "sg:province":"Limburg",
    "wof:name":"M G H Prumpeler",
    "wof:placetype":"venue"
},
  "geometry": {"coordinates":[6.037462,50.863739],"type":"Point"}
}