{
  "type": "Feature",
  "properties": {
    "iso:country":"NL",
    "sg:address":"H Dunantstr 25",
    "sg:city":"Oostrum Lb",
    "sg:classifiers":[
        {
            "category":"Retail",
            "subcategory":"Auto Repair",
            "type":"Services"
        }
    ],
    "sg:phone":"+31 478 511 933",
    "sg:postcode":"5807 ES",
    "sg:province":"Limburg",
    "sg:tags":[
        "garage"
    ],
    "sg:website":"http://www.brauckmann.nl",
    "wof:name":"Brauckmann Vakgarage",
    "wof:placetype":"venue"
},
  "geometry": {"coordinates":[-93.129936,36.705662],"type":"Point"}
}