{
  "type": "Feature",
  "properties": {
    "addr:full":"Kruisstraat 11 Hoorn Nh North Holland 1621 EH",
    "addr:housenumber":"11",
    "addr:postcode":"1621 eh",
    "addr:street":"Kruisstraat;Nh North",
    "iso:country":"NL",
    "sg:address":"Kruisstraat 11",
    "sg:city":"Hoorn Nh",
    "sg:orig_category":"Opticiens",
    "sg:phone":"+31 229 269 779",
    "sg:postcode":"1621 EH",
    "sg:province":"North Holland",
    "wof:name":"Van A Tot Z Kompleet Optiek",
    "wof:placetype":"venue"
},
  "geometry": {"coordinates":[5.0583081245,52.6406974792],"type":"Point"}
}