{
  "type": "Feature",
  "properties": {
    "addr:full":"Hogestr 34 Druten Gelderland 6651 BL",
    "addr:housenumber":"34",
    "addr:postcode":"6651 bl",
    "addr:street":"Hogestr",
    "iso:country":"NL",
    "sg:address":"Hogestr 34",
    "sg:city":"Druten",
    "sg:classifiers":[
        {
            "category":"Food & Beverages",
            "subcategory":"Bakery",
            "type":"Retail Goods"
        }
    ],
    "sg:phone":"+31 487 512 553",
    "sg:postcode":"6651 BL",
    "sg:province":"Gelderland",
    "sg:tags":[
        "brood",
        "en",
        "banket"
    ],
    "wof:name":"Vonk Bakkerij, Geert",
    "wof:placetype":"venue"
},
  "geometry": {"coordinates":[5.60526,51.88567],"type":"Point"}
}