{
  "type": "Feature",
  "properties": {
    "addr:full":"Newtonstr 20 Terneuzen Zeeland 4532 KH",
    "addr:housenumber":"20",
    "addr:postcode":"4532 kh",
    "addr:street":"Newtonstr",
    "iso:country":"NL",
    "sg:address":"Newtonstr 20",
    "sg:city":"Terneuzen",
    "sg:orig_category":"Tekstschrijversters",
    "sg:phone":"+31 115 630 365",
    "sg:postcode":"4532 KH",
    "sg:province":"Zeeland",
    "wof:name":"Ma Plus",
    "wof:placetype":"venue"
},
  "geometry": {"coordinates":[3.854666,51.33268],"type":"Point"}
}