{
  "type": "Feature",
  "properties": {
    "iso:country":"NL",
    "sg:address":"Kon Julianastr 5",
    "sg:city":"Mook",
    "sg:orig_category":"Scholen Voor Basisonderwijs",
    "sg:phone":"+31 24 696 2763",
    "sg:postcode":"6585 XP",
    "sg:province":"Limburg",
    "wof:name":"Adalbert Basisschool Rk",
    "wof:placetype":"venue"
},
  "geometry": {"coordinates":[5.88446,51.750713],"type":"Point"}
}