{
  "type": "Feature",
  "properties": {
    "addr:full":"Waterland 37 Huizen Noord-Holland 1274 KR",
    "addr:housenumber":"37",
    "addr:postcode":"1274 kr",
    "addr:street":"Waterland",
    "iso:country":"NL",
    "sg:address":"Waterland 37",
    "sg:city":"Huizen",
    "sg:orig_category":"Hulpverlening Sociaal",
    "sg:phone":"+31 35 526 3198",
    "sg:postcode":"1274 KR",
    "sg:province":"Noord-Holland",
    "wof:name":"Boddaertcentr Huizen",
    "wof:placetype":"venue"
},
  "geometry": {"coordinates":[5.271768,52.295101],"type":"Point"}
}