{
  "type": "Feature",
  "properties": {
    "addr:full":"Lynbaan 150 Rotterdam Zuid-Holland 3012 ER",
    "addr:housenumber":"150",
    "addr:postcode":"3012 er",
    "iso:country":"NL",
    "sg:address":"Lynbaan 150",
    "sg:city":"Rotterdam",
    "sg:orig_category":"Muziekinstrumenten En Bladmuziek",
    "sg:phone":"+31 10 412 1900",
    "sg:postcode":"3012 ER",
    "sg:province":"Zuid-Holland",
    "sg:website":"http://www.shbladmuziek.nl",
    "wof:name":"Stolk & Van Der Heijde",
    "wof:placetype":"venue"
},
  "geometry": {"coordinates":[4.478455,51.922836],"type":"Point"}
}