{
  "type": "Feature",
  "properties": {
    "addr:full":"Jeroen Boschlaan 9 Lopik Utrecht 3411 VE",
    "addr:housenumber":"9",
    "addr:postcode":"3411",
    "addr:street":"Jeroen Boschlaan",
    "iso:country":"NL",
    "sg:address":"Jeroen Boschlaan 9",
    "sg:city":"Lopik",
    "sg:orig_category":"Gespecialiseerde Bouw",
    "sg:phone":"+31 348 554 098",
    "sg:postcode":"3411 VE",
    "sg:province":"Utrecht",
    "wof:name":"Bema Voegwerken",
    "wof:placetype":"venue"
},
  "geometry": {"coordinates":[4.937542,51.974728],"type":"Point"}
}