{
  "type": "Feature",
  "properties": {
    "addr:full":"Santpoorterstr 1B Haarlem Noord-Holland 2023 DA",
    "addr:housenumber":"1b",
    "addr:postcode":"2023 da",
    "addr:street":"Santpoorterstr",
    "iso:country":"NL",
    "sg:address":"Santpoorterstr 1B",
    "sg:city":"Haarlem",
    "sg:orig_category":"Manueel Therapeuten",
    "sg:phone":"+31 23 526 0909",
    "sg:postcode":"2023 DA",
    "sg:province":"Noord-Holland",
    "sg:website":"http://www.diagnostiek.freeler.nl",
    "wof:name":"Boonstra Haarlem Rm&Jw Boonstra",
    "wof:placetype":"venue"
},
  "geometry": {"coordinates":[4.628012,52.390003],"type":"Point"}
}