{
  "type": "Feature",
  "properties": {
    "addr:full":"Stationsplein 1B Nijmegen Gelderland 6512 AA",
    "addr:housenumber":"1b",
    "addr:postcode":"6512 aa",
    "addr:street":"Stationsplein;Gelderland",
    "iso:country":"NL",
    "sg:address":"Stationsplein 1B",
    "sg:city":"Nijmegen",
    "sg:orig_category":"Kappers",
    "sg:phone":"+31 24 322 4901",
    "sg:postcode":"6512 AA",
    "sg:province":"Gelderland",
    "wof:name":"Stationskapsalon Van Hees",
    "wof:placetype":"venue"
},
  "geometry": {"coordinates":[5.85262,51.842396],"type":"Point"}
}