{
  "type": "Feature",
  "properties": {
    "addr:full":"Twikkelstr 15 Breda Noord-Brabant 4834 LL",
    "addr:housenumber":"15",
    "addr:postcode":"4834 ll",
    "addr:street":"Twikkelstr",
    "iso:country":"NL",
    "sg:address":"Twikkelstr 15",
    "sg:city":"Breda",
    "sg:orig_category":"Adviesbureaus Bedrijfsorganisatie",
    "sg:phone":"+31 76 561 1499",
    "sg:postcode":"4834 LL",
    "sg:province":"Noord-Brabant",
    "wof:name":"Hetterschijt",
    "wof:placetype":"venue"
},
  "geometry": {"coordinates":[4.80831,51.572197],"type":"Point"}
}