{
  "type": "Feature",
  "properties": {
    "addr:full":"M Stolpstr 18 Schagerbrug North Holland 1751 CZ",
    "addr:housenumber":"18;1751",
    "iso:country":"NL",
    "sg:address":"M Stolpstr 18",
    "sg:city":"Schagerbrug",
    "sg:orig_category":"Pensioenen",
    "sg:phone":"+31 224 571 717",
    "sg:postcode":"1751 CZ",
    "sg:province":"North Holland",
    "wof:name":"Vonk",
    "wof:placetype":"venue"
},
  "geometry": {"coordinates":[4.758719,52.801105],"type":"Point"}
}