{
  "type": "Feature",
  "properties": {
    "addr:full":"Wagenstraat 59A Den Haag Zuid-Holland 2512 AP",
    "addr:housenumber":"59a",
    "addr:postcode":"2512 ap",
    "addr:street":"Wagenstraat",
    "iso:country":"NL",
    "sg:address":"Wagenstraat 59A",
    "sg:city":"Den Haag",
    "sg:orig_category":"Werving And Selectie Van Tijdelijk Personeel And Uitzendkantoren",
    "sg:phone":"+31 70 636 6306",
    "sg:postcode":"2512 AP",
    "sg:province":"Zuid-Holland",
    "wof:name":"Barendse Bv",
    "wof:placetype":"venue"
},
  "geometry": {"coordinates":[4.3125019073,52.0757598877],"type":"Point"}
}