{
  "type": "Feature",
  "properties": {
    "addr:full":"Kromme Mijdrecht 44 De Hoef Utrecht 1426 AC",
    "addr:housenumber":"44",
    "addr:postcode":"1426 ac",
    "addr:street":"Kromme Mijdrecht",
    "iso:country":"NL",
    "sg:address":"Kromme Mijdrecht 44",
    "sg:city":"De Hoef",
    "sg:orig_category":"Metaalbekleding And -Behandeling",
    "sg:phone":"+31 297 567 990",
    "sg:postcode":"1426 AC",
    "sg:province":"Utrecht",
    "wof:name":"Van Wijk Industrie-Service",
    "wof:placetype":"venue"
},
  "geometry": {"coordinates":[4.817825,52.225483],"type":"Point"}
}