{
  "type": "Feature",
  "properties": {
    "iso:country":"NL",
    "sg:address":"Schepersmaat 2",
    "sg:city":"Assen",
    "sg:orig_category":"Olie - Exploratie",
    "sg:phone":"+31 592 369 111",
    "sg:postcode":"9405 TA",
    "sg:province":"Drenthe",
    "sg:website":"http://www.nam.nl",
    "wof:name":"Ned Aardolie Mij Bv",
    "wof:placetype":"venue"
},
  "geometry": {"coordinates":[6.561233,52.975353],"type":"Point"}
}