{
  "type": "Feature",
  "properties": {
    "addr:full":"Burg D Beaufortln 3 Abcoude Utrecht 1391 CK",
    "addr:housenumber":"3",
    "addr:postcode":"1391 ck",
    "addr:street":"Burg;Beaufortln",
    "iso:country":"NL",
    "sg:address":"Burg D Beaufortln 3",
    "sg:city":"Abcoude",
    "sg:classifiers":[
        {
            "category":"Professional",
            "subcategory":"Accounting & Tax Preparation",
            "type":"Services"
        }
    ],
    "sg:phone":"+31 294 285 278",
    "sg:postcode":"1391 CK",
    "sg:province":"Utrecht",
    "sg:tags":[
        "accountant"
    ],
    "wof:name":"H. Aalders",
    "wof:placetype":"venue"
},
  "geometry": {"coordinates":[4.975086,52.269814],"type":"Point"}
}