{
  "type": "Feature",
  "properties": {
    "iso:country":"NL",
    "sg:address":"Speelveld 2",
    "sg:city":"Etten Leur",
    "sg:orig_category":"Grafisch Ontwerpers",
    "sg:phone":"+31 76 501 4647",
    "sg:postcode":"4873 DV",
    "sg:province":"Noord-Brabant",
    "wof:name":"Wal, Ontwerpburo V/D",
    "wof:placetype":"venue"
},
  "geometry": {"coordinates":[4.654037,51.565598],"type":"Point"}
}