{
  "type": "Feature",
  "properties": {
    "addr:full":"Dinkelstr 39 Groningen Groningen 9725 KK",
    "addr:housenumber":"39",
    "addr:postcode":"9725 kk",
    "addr:street":"Dinkelstr",
    "iso:country":"NL",
    "sg:address":"Dinkelstr 39",
    "sg:city":"Groningen",
    "sg:orig_category":"Verenigingen En Stichtingen",
    "sg:phone":"+31 50 526 5783",
    "sg:postcode":"9725 KK",
    "sg:province":"Groningen",
    "wof:name":"Bso Schildersbuurt, Sticht",
    "wof:placetype":"venue"
},
  "geometry": {"coordinates":[6.568586,53.207172],"type":"Point"}
}