{
  "type": "Feature",
  "properties": {
    "addr:full":"Fazantln 82 Budel North Brabant 6021 ZH",
    "addr:housenumber":"82",
    "addr:postcode":"6021 zh",
    "addr:street":"Fazantln",
    "iso:country":"NL",
    "sg:address":"Fazantln 82",
    "sg:city":"Budel",
    "sg:orig_category":"Kampeerartikelen",
    "sg:phone":"+31 495 664 005",
    "sg:postcode":"6021 ZH",
    "sg:province":"North Brabant",
    "wof:name":"Produits Oranges",
    "wof:placetype":"venue"
},
  "geometry": {"coordinates":[5.5740151405,51.2681236267],"type":"Point"}
}