{
  "type": "Feature",
  "properties": {
    "iso:country":"NL",
    "sg:address":"Benzenraderwg 20",
    "sg:city":"Heerlen",
    "sg:orig_category":"Horloges En Klokken - Reparatie En Onderhoud",
    "sg:phone":"+31 45 560 0766",
    "sg:postcode":"6411 ED",
    "sg:province":"Limburg",
    "wof:name":"Clockhouse De Til",
    "wof:placetype":"venue"
},
  "geometry": {"coordinates":[5.978559,50.882179],"type":"Point"}
}