{
  "type": "Feature",
  "properties": {
    "iso:country":"NL",
    "sg:address":"Industriewg 3R",
    "sg:city":"Vught",
    "sg:orig_category":"Zeilmakerijen",
    "sg:phone":"+31 73 684 0325",
    "sg:postcode":"5262 GJ",
    "sg:province":"North Brabant",
    "wof:name":"Jatex Int",
    "wof:placetype":"venue"
},
  "geometry": {"coordinates":[5.291997,51.646824],"type":"Point"}
}