{
  "type": "Feature",
  "properties": {
    "addr:full":"Raadhuisstr 152 Alphen Aan Den Ryn South Holland 2406 AJ",
    "addr:housenumber":"152",
    "addr:postcode":"2406 aj",
    "addr:street":"Aan Den Ryn",
    "iso:country":"NL",
    "sg:address":"Raadhuisstr 152",
    "sg:city":"Alphen Aan Den Ryn",
    "sg:orig_category":"Parketvloeren",
    "sg:phone":"+31 172 517 171",
    "sg:postcode":"2406 AJ",
    "sg:province":"South Holland",
    "sg:website":"http://www.raadhuisparket.nl",
    "wof:name":"Raadhuis, Parket & Interieur 'T",
    "wof:placetype":"venue"
},
  "geometry": {"coordinates":[4.663411,52.127335],"type":"Point"}
}