{
  "type": "Feature",
  "properties": {
    "iso:country":"NL",
    "sg:address":"Postbus 208",
    "sg:city":"Gemert",
    "sg:orig_category":"Kaasgroothandel",
    "sg:phone":"+31 492 371 271",
    "sg:postcode":"5420 AE",
    "sg:province":"North Brabant",
    "wof:name":"Segers Bv, Cor",
    "wof:placetype":"venue"
},
  "geometry": {"coordinates":[5.6822900772,51.554309845],"type":"Point"}
}