{
  "type": "Feature",
  "properties": {
    "iso:country":"NL",
    "sg:address":"Zandvoortseln 34",
    "sg:city":"Heemstede",
    "sg:orig_category":"Fietsen En Bromfietsen",
    "sg:phone":"+31 23 528 3172",
    "sg:postcode":"2106 CP",
    "sg:province":"Noord-Holland",
    "wof:name":"Hart & Zn, Rijwielhandel",
    "wof:placetype":"venue"
},
  "geometry": {"coordinates":[4.611532,52.359428],"type":"Point"}
}