{
  "type": "Feature",
  "properties": {
    "iso:country":"NL",
    "sg:address":"Hendriklaan 3",
    "sg:city":"Harmelen",
    "sg:classifiers":[
        {
            "category":"Education",
            "subcategory":"Preschool",
            "type":"Public Place"
        }
    ],
    "sg:phone":"+31 348 442 410",
    "sg:postcode":"3481 VR",
    "sg:province":"Utrecht",
    "sg:tags":[
        "kleuteronderwijs",
        "basis-"
    ],
    "wof:name":"Openbare Basisschool De Horizon",
    "wof:placetype":"venue"
},
  "geometry": {"coordinates":[4.964076,52.085621],"type":"Point"}
}