{
  "type": "Feature",
  "properties": {
    "addr:full":"Hoofdweg 19 Echten Fr Friesland 8537 SC",
    "addr:housenumber":"19",
    "addr:postcode":"8537 sc",
    "addr:street":"Hoofdweg",
    "iso:country":"NL",
    "sg:address":"Hoofdweg 19",
    "sg:city":"Echten Fr",
    "sg:orig_category":"Diverse Consumentenartikelen Gh",
    "sg:phone":"+31 514 541 295",
    "sg:postcode":"8537 SC",
    "sg:province":"Friesland",
    "wof:name":"G.K. De Vries En Zn",
    "wof:placetype":"venue"
},
  "geometry": {"coordinates":[5.800716,52.87376],"type":"Point"}
}