{
  "type": "Feature",
  "properties": {
    "iso:country":"NL",
    "sg:address":"J Bakerstr 65",
    "sg:city":"Almere",
    "sg:orig_category":"Schilders",
    "sg:phone":"+31 36 536 8373",
    "sg:postcode":"1311 GC",
    "sg:province":"Flevoland",
    "wof:name":"Barneveld Bv",
    "wof:placetype":"venue"
},
  "geometry": {"coordinates":[5.173411,52.365959],"type":"Point"}
}