{
  "type": "Feature",
  "properties": {
    "addr:full":"Grindweg 57 Munnekeburen Provincie Friesland 8485 JD",
    "addr:housenumber":"57",
    "addr:postcode":"8485 jd",
    "addr:street":"Grindweg;Provincie Friesland",
    "iso:country":"NL",
    "sg:address":"Grindweg 57",
    "sg:city":"Munnekeburen",
    "sg:orig_category":"Landbouwmachines Gh",
    "sg:phone":"+31 561 481 278",
    "sg:postcode":"8485 JD",
    "sg:province":"Provincie Friesland",
    "wof:name":"Koop Van Der Wal Vof",
    "wof:placetype":"venue"
},
  "geometry": {"coordinates":[5.884035,52.847549],"type":"Point"}
}