{
  "type": "Feature",
  "properties": {
    "addr:full":"Ijselweg 20 Zutphen Gelderland 7207 DJ",
    "addr:housenumber":"20",
    "addr:postcode":"7207 dj",
    "addr:street":"Ijselweg;Gelderland",
    "iso:country":"NL",
    "sg:address":"Ijselweg 20",
    "sg:city":"Zutphen",
    "sg:orig_category":"Fotostudio'S And Fotografen",
    "sg:phone":"+31 575 521 894",
    "sg:postcode":"7207 DJ",
    "sg:province":"Gelderland",
    "wof:name":"Geert De Groot",
    "wof:placetype":"venue"
},
  "geometry": {"coordinates":[6.223898,52.109917],"type":"Point"}
}