{
  "type": "Feature",
  "properties": {
    "addr:full":"Hoofdstraat 220 Sassenheim Zuid-Holland 2171 BN",
    "addr:housenumber":"220",
    "addr:postcode":"2171 bn",
    "addr:street":"Hoofdstraat",
    "iso:country":"NL",
    "sg:address":"Hoofdstraat 220",
    "sg:city":"Sassenheim",
    "sg:orig_category":"Verzekeringen",
    "sg:phone":"+31 252 211 091",
    "sg:postcode":"2171 BN",
    "sg:province":"Zuid-Holland",
    "wof:name":"Assurantiekantoor Bijdorp-Holland Bv",
    "wof:placetype":"venue"
},
  "geometry": {"coordinates":[4.521343,52.225594],"type":"Point"}
}