{
  "type": "Feature",
  "properties": {
    "addr:full":"Elsweg 11 Noordwolde Fr Provincie Friesland 8391 KB",
    "addr:housenumber":"11",
    "addr:postcode":"8391 kb",
    "addr:street":"Elsweg;Friesland",
    "iso:country":"NL",
    "sg:address":"Elsweg 11",
    "sg:city":"Noordwolde Fr",
    "sg:orig_category":"Kampeerterreinen",
    "sg:phone":"+31 561 431 901",
    "sg:postcode":"8391 KB",
    "sg:province":"Provincie Friesland",
    "wof:name":"Camping Hanestede",
    "wof:placetype":"venue"
},
  "geometry": {"coordinates":[6.1362009048,52.8830871582],"type":"Point"}
}