{
  "type": "Feature",
  "properties": {
    "iso:country":"NL",
    "sg:address":"Churchillln 11",
    "sg:city":"Utrecht",
    "sg:orig_category":"Verenigingen En Stichtingen",
    "sg:phone":"+31 30 290 0360",
    "sg:postcode":"3527 GV",
    "sg:province":"Utrecht",
    "wof:name":"Fodok, Sticht",
    "wof:placetype":"venue"
},
  "geometry": {"coordinates":[5.09488,52.078011],"type":"Point"}
}