{
  "type": "Feature",
  "properties": {
    "iso:country":"NL",
    "sg:address":"Zandstr 36",
    "sg:city":"Sas Van Gent",
    "sg:orig_category":"Verenigingen En Stichtingen",
    "sg:phone":"+31 115 472 560",
    "sg:postcode":"4551 LH",
    "sg:province":"Zeeland",
    "wof:name":"Straete Wijkver, De",
    "wof:placetype":"venue"
},
  "geometry": {"coordinates":[3.811747,51.265778],"type":"Point"}
}