{
  "type": "Feature",
  "properties": {
    "addr:full":"Keizersgracht 463 Amsterdam Noord-Holland 1017 DK",
    "addr:housenumber":"463",
    "addr:postcode":"1017 dk",
    "addr:street":"Keizersgracht",
    "iso:country":"NL",
    "sg:address":"Keizersgracht 463",
    "sg:city":"Amsterdam",
    "sg:orig_category":"Ambassades And Consulaten",
    "sg:phone":"+31 20 624 1530",
    "sg:postcode":"1017 DK",
    "sg:province":"Noord-Holland",
    "wof:name":"Consulaat Van Nepal",
    "wof:placetype":"venue"
},
  "geometry": {"coordinates":[-94.58503,38.350479],"type":"Point"}
}