{
  "type": "Feature",
  "properties": {
    "addr:full":"Vleerdamsedk 2 Rockanje Zuid-Holland 3235 NW",
    "addr:housenumber":"2",
    "addr:postcode":"3235 nw",
    "addr:street":"Vleerdamsedk",
    "iso:country":"NL",
    "sg:address":"Vleerdamsedk 2",
    "sg:city":"Rockanje",
    "sg:orig_category":"Poeliers",
    "sg:phone":"+31 181 401 469",
    "sg:postcode":"3235 NW",
    "sg:province":"Zuid-Holland",
    "wof:name":"Vries, J De",
    "wof:placetype":"venue"
},
  "geometry": {"coordinates":[4.067052,51.875492],"type":"Point"}
}