{
  "type": "Feature",
  "properties": {
    "addr:full":"Ruychrocklaan 121 'S Gravenhage Zuid-Holland 2597 EL",
    "addr:housenumber":"121 ';2597",
    "addr:postcode":"el",
    "addr:street":"Ruychrocklaan",
    "iso:country":"NL",
    "sg:address":"Ruychrocklaan 121",
    "sg:city":"'S Gravenhage",
    "sg:orig_category":"Apothekers",
    "sg:phone":"+31 70 324 4435",
    "sg:postcode":"2597 EL",
    "sg:province":"Zuid-Holland",
    "wof:name":"Duinrand Apotheek",
    "wof:placetype":"venue"
},
  "geometry": {"coordinates":[4.317172,52.098991],"type":"Point"}
}