{
  "type": "Feature",
  "properties": {
    "iso:country":"NL",
    "sg:address":"Grotestraat 65",
    "sg:city":"Almelo",
    "sg:orig_category":"Schoenen",
    "sg:phone":"+31 546 820 221",
    "sg:postcode":"7607 CD",
    "sg:province":"Overijssel",
    "wof:name":"Schoenenreus",
    "wof:placetype":"venue"
},
  "geometry": {"coordinates":[6.6646,52.356987],"type":"Point"}
}