{
  "type": "Feature",
  "properties": {
    "addr:full":"Heekln 133 Helmond Noord-Brabant 5706 BP",
    "addr:housenumber":"133",
    "addr:postcode":"5706 bp",
    "iso:country":"NL",
    "sg:address":"Heekln 133",
    "sg:city":"Helmond",
    "sg:orig_category":"Geschenkartikelen",
    "sg:phone":"+31 492 528 837",
    "sg:postcode":"5706 BP",
    "sg:province":"Noord-Brabant",
    "wof:name":"Snuffelhoek, De",
    "wof:placetype":"venue"
},
  "geometry": {"coordinates":[5.658284,51.482239],"type":"Point"}
}