{
  "type": "Feature",
  "properties": {
    "addr:full":"Claudiushof 8 Maastricht Limburg 6215 EZ",
    "addr:housenumber":"8",
    "addr:postcode":"6215 ez",
    "addr:street":"Claudiushof",
    "iso:country":"NL",
    "sg:address":"Claudiushof 8",
    "sg:city":"Maastricht",
    "sg:orig_category":"Sportverenigingen En Ontspannings- Verenigingen",
    "sg:phone":"+31 43 347 0109",
    "sg:postcode":"6215 EZ",
    "sg:province":"Limburg",
    "wof:name":"Maastrichtse Reddingsbrigade",
    "wof:placetype":"venue"
},
  "geometry": {"coordinates":[5.64531,50.839966],"type":"Point"}
}