{
  "type": "Feature",
  "properties": {
    "addr:full":"Weidehek 99 Breda Noord-Brabant 4824 AT",
    "addr:housenumber":"99",
    "addr:postcode":"4824",
    "addr:street":"Weidehek",
    "iso:country":"NL",
    "sg:address":"Weidehek 99",
    "sg:city":"Breda",
    "sg:orig_category":"Verhuur Catering-, Feest- En Evenementbenodigdheden",
    "sg:phone":"+31 76 561 3087",
    "sg:postcode":"4824 AT",
    "sg:province":"Noord-Brabant",
    "wof:name":"Woninginrichting Malipaard Bv",
    "wof:placetype":"venue"
},
  "geometry": {"coordinates":[4.758892,51.616035],"type":"Point"}
}