{
  "type": "Feature",
  "properties": {
    "iso:country":"NL",
    "sg:address":"Weidehek 99",
    "sg:city":"Breda",
    "sg:orig_category":"Verhuur Catering-, Feest- En Evenementbenodigdheden",
    "sg:phone":"+31 76 561 3087",
    "sg:postcode":"4824 AT",
    "sg:province":"Noord-Brabant",
    "wof:name":"Woninginrichting Malipaard Bv",
    "wof:placetype":"venue"
},
  "geometry": {"coordinates":[4.758892,51.616035],"type":"Point"}
}