{
  "type": "Feature",
  "properties": {
    "addr:full":"J Slagter D Tuin 27 Heerhugowaard North Holland 1705 HV",
    "addr:housenumber":"27",
    "addr:postcode":"1705 hv",
    "addr:street":"Tuin",
    "iso:country":"NL",
    "sg:address":"J Slagter D Tuin 27",
    "sg:city":"Heerhugowaard",
    "sg:orig_category":"Autorijscholen",
    "sg:phone":"+31 72 574 7159",
    "sg:postcode":"1705 HV",
    "sg:province":"North Holland",
    "sg:website":"http://www.rijschoolvanheumen.nl",
    "wof:name":"Heumen, R & R Van",
    "wof:placetype":"venue"
},
  "geometry": {"coordinates":[4.829,52.64492],"type":"Point"}
}