{
  "type": "Feature",
  "properties": {
    "addr:full":"Anjelierstr 56 Heerlen Limburg 6414 EW",
    "addr:housenumber":"56",
    "addr:postcode":"6414 ew",
    "addr:street":"Anjelierstr",
    "iso:country":"NL",
    "sg:address":"Anjelierstr 56",
    "sg:city":"Heerlen",
    "sg:orig_category":"Bloemen En Planten",
    "sg:phone":"+31 45 521 9292",
    "sg:postcode":"6414 EW",
    "sg:province":"Limburg",
    "wof:name":"Hoffleur",
    "wof:placetype":"venue"
},
  "geometry": {"coordinates":[5.967622,50.923512],"type":"Point"}
}