{
  "type": "Feature",
  "properties": {
    "addr:full":"Eniggaburren 25 Workum Friesland 8711 HP",
    "addr:housenumber":"25",
    "addr:postcode":"8711 hp",
    "addr:street":"Eniggaburren",
    "iso:country":"NL",
    "sg:address":"Eniggaburren 25",
    "sg:city":"Workum",
    "sg:orig_category":"Scheepsmotoren - Reparatie",
    "sg:phone":"+31 515 542 422",
    "sg:postcode":"8711 HP",
    "sg:province":"Friesland",
    "wof:name":"Heida",
    "wof:placetype":"venue"
},
  "geometry": {"coordinates":[5.460145,52.976273],"type":"Point"}
}