{
  "type": "Feature",
  "properties": {
    "iso:country":"NL",
    "sg:address":"Weebosch 16",
    "sg:city":"Bergeyk",
    "sg:orig_category":"Graszoden",
    "sg:phone":"+31 497 542 710",
    "sg:postcode":"5571 LX",
    "sg:province":"Noord-Brabant",
    "wof:name":"Aarts Graszoden",
    "wof:placetype":"venue"
},
  "geometry": {"coordinates":[5.29952,51.312164],"type":"Point"}
}