{
  "type": "Feature",
  "properties": {
    "addr:full":"Frisoln 52 Apeldoorn Gelderland 7316 DD",
    "addr:housenumber":"52",
    "addr:postcode":"7316 dd",
    "addr:street":"Frisoln;Gelderland",
    "iso:country":"NL",
    "sg:address":"Frisoln 52",
    "sg:city":"Apeldoorn",
    "sg:orig_category":"Adviesbureaus Bedrijfsorganisatie",
    "sg:phone":"+31 55 521 7220",
    "sg:postcode":"7316 DD",
    "sg:province":"Gelderland",
    "wof:name":"Orticonsult Bv",
    "wof:placetype":"venue"
},
  "geometry": {"coordinates":[5.96566,52.216518],"type":"Point"}
}