{
  "type": "Feature",
  "properties": {
    "iso:country":"NL",
    "sg:address":"Nieuwpoortstr 96B",
    "sg:city":"Amsterdam",
    "sg:orig_category":"Koffie-Automaten",
    "sg:phone":"+31 20 688 2277",
    "sg:postcode":"1055 RZ",
    "sg:province":"North Holland",
    "wof:name":"Urbain Trade Automaten Service",
    "wof:placetype":"venue"
},
  "geometry": {"coordinates":[4.857095,52.384174],"type":"Point"}
}