{
  "type": "Feature",
  "properties": {
    "addr:full":"Nieuwpoortstr 96B Amsterdam North Holland 1055 RZ",
    "addr:housenumber":"96b",
    "addr:postcode":"1055 rz",
    "addr:street":"Nieuwpoortstr",
    "iso:country":"NL",
    "sg:address":"Nieuwpoortstr 96B",
    "sg:city":"Amsterdam",
    "sg:orig_category":"Koffie-Automaten",
    "sg:phone":"+31 20 688 2277",
    "sg:postcode":"1055 RZ",
    "sg:province":"North Holland",
    "wof:name":"Urbain Trade Automaten Service",
    "wof:placetype":"venue"
},
  "geometry": {"coordinates":[4.857095,52.384174],"type":"Point"}
}