{
  "type": "Feature",
  "properties": {
    "addr:full":"Grotestraat 65 Eibergen Gelderland 7151 BB",
    "addr:housenumber":"65",
    "addr:postcode":"7151 bb",
    "addr:street":"Grotestraat;Gelderland",
    "iso:country":"NL",
    "sg:address":"Grotestraat 65",
    "sg:city":"Eibergen",
    "sg:classifiers":[
        {
            "category":"Bakery",
            "type":"Food & Drink"
        }
    ],
    "sg:phone":"+31 545 475 673",
    "sg:postcode":"7151 BB",
    "sg:province":"Gelderland",
    "sg:tags":[
        "brood",
        "banket"
    ],
    "wof:name":"Vlaaienshop",
    "wof:placetype":"venue"
},
  "geometry": {"coordinates":[6.645518,52.102951],"type":"Point"}
}