{
  "type": "Feature",
  "properties": {
    "addr:full":"Pieter Postlaan 90 Rotterdam South Holland 3042 CL",
    "addr:housenumber":"90",
    "addr:postcode":"3042",
    "addr:street":"Pieter Postlaan",
    "iso:country":"NL",
    "sg:address":"Pieter Postlaan 90",
    "sg:city":"Rotterdam",
    "sg:orig_category":"Autokeuringen",
    "sg:phone":"+31 10 462 1412",
    "sg:postcode":"3042 CL",
    "sg:province":"South Holland",
    "wof:name":"Garage Van Dartel & Zn. Vof",
    "wof:placetype":"venue"
},
  "geometry": {"coordinates":[4.435928,51.932129],"type":"Point"}
}