{
  "type": "Feature",
  "properties": {
    "iso:country":"NL",
    "sg:address":"Acaciastr 61",
    "sg:city":"Oud Beyerland",
    "sg:orig_category":"Automaterialen En Gereedschappen",
    "sg:phone":"+31 186 621 026",
    "sg:postcode":"3261 RB",
    "sg:province":"South Holland",
    "wof:name":"Rodrico Gossini Cv",
    "wof:placetype":"venue"
},
  "geometry": {"coordinates":[4.424875,51.818401],"type":"Point"}
}