{
  "type": "Feature",
  "properties": {
    "iso:country":"NL",
    "sg:address":"Valkenpad 7",
    "sg:city":"Leiden",
    "sg:orig_category":"Scholen Voor Basisonderwijs",
    "sg:phone":"+31 71 523 4378",
    "sg:postcode":"2317 AN",
    "sg:province":"Zuid-Holland",
    "wof:name":"Springplank Prot Chr, De",
    "wof:placetype":"venue"
},
  "geometry": {"coordinates":[4.507232,52.17382],"type":"Point"}
}