{
  "type": "Feature",
  "properties": {
    "iso:country":"NL",
    "sg:address":"Wilhelminastraat 46",
    "sg:city":"Gouda",
    "sg:orig_category":"Meubelzaken, Woning- And Keukeninrichting",
    "sg:phone":"+31 182 514 364",
    "sg:postcode":"2801 XK",
    "sg:province":"Zuid-Holland",
    "wof:name":"De Rietboetiek Bv",
    "wof:placetype":"venue"
},
  "geometry": {"coordinates":[4.712737,52.012981],"type":"Point"}
}