{
  "type": "Feature",
  "properties": {
    "addr:full":"Concertgebouwpln 5 Amsterdam Noord-Holland 1071 LL",
    "addr:housenumber":"5",
    "addr:postcode":"1071 ll",
    "addr:street":"Concertgebouwpln",
    "iso:country":"NL",
    "sg:address":"Concertgebouwpln 5",
    "sg:city":"Amsterdam",
    "sg:orig_category":"Onroerende Goederen",
    "sg:phone":"+31 20 673 3361",
    "sg:postcode":"1071 LL",
    "sg:province":"Noord-Holland",
    "wof:name":"Altaville Bv",
    "wof:placetype":"venue"
},
  "geometry": {"coordinates":[4.879641,52.355602],"type":"Point"}
}