{
  "type": "Feature",
  "properties": {
    "addr:full":"Markt 4 Venlo Limburg 5911 HD",
    "addr:housenumber":"4",
    "addr:postcode":"5911 hd",
    "addr:street":"Markt",
    "iso:country":"NL",
    "sg:address":"Markt 4",
    "sg:city":"Venlo",
    "sg:orig_category":"Goudsmeden En Zilversmeden",
    "sg:phone":"+31 77 351 2221",
    "sg:postcode":"5911 HD",
    "sg:province":"Limburg",
    "wof:name":"Frits Nellissen",
    "wof:placetype":"venue"
},
  "geometry": {"coordinates":[6.169323,51.370335],"type":"Point"}
}