{
  "type": "Feature",
  "properties": {
    "addr:full":"J De Wittln 17 Arnhem Gelderland 6828 XB",
    "addr:housenumber":"17",
    "addr:postcode":"6828 xb",
    "addr:street":"J De Wittln",
    "iso:country":"NL",
    "sg:address":"J De Wittln 17",
    "sg:city":"Arnhem",
    "sg:orig_category":"Bloemen En Planten",
    "sg:phone":"+31 26 445 4445",
    "sg:postcode":"6828 XB",
    "sg:province":"Gelderland",
    "wof:name":"Marco",
    "wof:placetype":"venue"
},
  "geometry": {"coordinates":[5.92598,51.98053],"type":"Point"}
}