{
  "type": "Feature",
  "properties": {
    "addr:full":"Transportweg 3 Oostburg Zeeland 4501 PS",
    "addr:housenumber":"3",
    "addr:postcode":"4501 ps",
    "addr:street":"Transportweg",
    "iso:country":"NL",
    "sg:address":"Transportweg 3",
    "sg:city":"Oostburg",
    "sg:orig_category":"Autokeuringen",
    "sg:phone":"+31 117 452 660",
    "sg:postcode":"4501 PS",
    "sg:province":"Zeeland",
    "wof:name":"Garage De Bliek",
    "wof:placetype":"venue"
},
  "geometry": {"coordinates":[3.495414,51.333668],"type":"Point"}
}