{
  "type": "Feature",
  "properties": {
    "addr:full":"Rettestraat 6 Chaam North Brabant 4861 CD",
    "addr:housenumber":"6",
    "addr:postcode":"4861 cd",
    "addr:street":"Rettestraat",
    "iso:country":"NL",
    "sg:address":"Rettestraat 6",
    "sg:city":"Chaam",
    "sg:orig_category":"Diverse Consumentenartikelen Gh",
    "sg:phone":"+31 161 493 107",
    "sg:postcode":"4861 CD",
    "sg:province":"North Brabant",
    "wof:name":"Handelsonderneming E. Den Ridder",
    "wof:placetype":"venue"
},
  "geometry": {"coordinates":[4.836091,51.504341],"type":"Point"}
}