{
  "type": "Feature",
  "properties": {
    "addr:full":"Loosduinse Hoofdstraat 255A 'S-Gravenhage Zuid-Holland 2552 AD",
    "addr:housenumber":"255a",
    "addr:postcode":"s-gravenhage;2552 ad",
    "addr:street":"Loosduinse Hoofdstraat",
    "iso:country":"NL",
    "sg:address":"Loosduinse Hoofdstraat 255A",
    "sg:city":"'S-Gravenhage",
    "sg:classifiers":[
        {
            "category":"Real Estate",
            "subcategory":"Real Estate Operator",
            "type":"Services"
        }
    ],
    "sg:phone":"+31 70 397 9273",
    "sg:postcode":"2552 AD",
    "sg:province":"Zuid-Holland",
    "sg:tags":[
        "appartementen",
        "en",
        "flat"
    ],
    "wof:name":"Klokhuis, 'T",
    "wof:placetype":"venue"
},
  "geometry": {"coordinates":[4.237773,52.054226],"type":"Point"}
}