{
  "type": "Feature",
  "properties": {
    "iso:country":"NL",
    "sg:address":"Wilhelminapln 12",
    "sg:city":"Rotterdam",
    "sg:orig_category":"Verzekeringen - Verzekeringskantoren",
    "sg:phone":"+31 10 441 8888",
    "sg:postcode":"3072 DE",
    "sg:province":"Zuid-Holland",
    "sg:website":"http://www.saa.nl",
    "wof:name":"Saa Nederland Bv",
    "wof:placetype":"venue"
},
  "geometry": {"coordinates":[4.491224,51.907524],"type":"Point"}
}