{
  "type": "Feature",
  "properties": {
    "addr:full":"Postbus 177 Beverwijk Noord-Holland 1940 AD",
    "addr:housenumber":"177",
    "addr:postcode":"1940 ad",
    "addr:street":"Postbus",
    "iso:country":"NL",
    "sg:address":"Postbus 177",
    "sg:city":"Beverwijk",
    "sg:orig_category":"Lasapparaten En Benodigdheden",
    "sg:phone":"+31 251 213 550",
    "sg:postcode":"1940 AD",
    "sg:province":"Noord-Holland",
    "sg:website":"http://www.waned.nl",
    "wof:name":"Welding Alloys Ned",
    "wof:placetype":"venue"
},
  "geometry": {"coordinates":[4.657101,52.486523],"type":"Point"}
}