{
  "type": "Feature",
  "properties": {
    "addr:full":"Zwenkgras 30 Gouda Zuid-Holland 2804 NJ",
    "addr:housenumber":"30",
    "addr:postcode":"2804 nj",
    "addr:street":"Zwenkgras",
    "iso:country":"NL",
    "sg:address":"Zwenkgras 30",
    "sg:city":"Gouda",
    "sg:orig_category":"Verpakkingen En Verpakkingsmaterialen",
    "sg:phone":"+31 182 579 609",
    "sg:postcode":"2804 NJ",
    "sg:province":"Zuid-Holland",
    "wof:name":"Luinen, Van",
    "wof:placetype":"venue"
},
  "geometry": {"coordinates":[4.712928,52.033489],"type":"Point"}
}