{
  "type": "Feature",
  "properties": {
    "iso:country":"NL",
    "sg:address":"Zwenkgras 30",
    "sg:city":"Gouda",
    "sg:orig_category":"Verpakkingen En Verpakkingsmaterialen",
    "sg:phone":"+31 182 579 609",
    "sg:postcode":"2804 NJ",
    "sg:province":"Zuid-Holland",
    "wof:name":"Luinen, Van",
    "wof:placetype":"venue"
},
  "geometry": {"coordinates":[4.712928,52.033489],"type":"Point"}
}