{
  "type": "Feature",
  "properties": {
    "addr:full":"Robynborch 9 Rosmalen North Brabant 5241 LK",
    "addr:housenumber":"9",
    "addr:postcode":"5241 lk",
    "addr:street":"Robynborch",
    "iso:country":"NL",
    "sg:address":"Robynborch 9",
    "sg:city":"Rosmalen",
    "sg:orig_category":"Machinehandel",
    "sg:phone":"+31 73 521 6036",
    "sg:postcode":"5241 LK",
    "sg:province":"North Brabant",
    "sg:website":"http://www.dgmtrilplaten.nl",
    "wof:name":"Dgm, Handelsonderneming",
    "wof:placetype":"venue"
},
  "geometry": {"coordinates":[5.35118,51.721878],"type":"Point"}
}