{
  "type": "Feature",
  "properties": {
    "addr:full":"Piuslaan 181 Eindhoven North Brabant 5643 PB",
    "addr:housenumber":"181",
    "addr:postcode":"5643 pb",
    "addr:street":"Piuslaan",
    "iso:country":"NL",
    "sg:address":"Piuslaan 181",
    "sg:city":"Eindhoven",
    "sg:orig_category":"Boekhouders",
    "sg:phone":"+31 40 212 1087",
    "sg:postcode":"5643 PB",
    "sg:province":"North Brabant",
    "wof:name":"Cedent Vof Administratiekantoor",
    "wof:placetype":"venue"
},
  "geometry": {"coordinates":[5.495781,51.425549],"type":"Point"}
}