{
  "type": "Feature",
  "properties": {
    "addr:full":"Wolframstr 29 Apeldoorn Gelderland 7334 BL",
    "addr:housenumber":"29",
    "addr:postcode":"7334 bl",
    "addr:street":"Wolframstr;Gelderland",
    "iso:country":"NL",
    "sg:address":"Wolframstr 29",
    "sg:city":"Apeldoorn",
    "sg:orig_category":"Voetbalverenigingen",
    "sg:phone":"+31 55 844 0313",
    "sg:postcode":"7334 BL",
    "sg:province":"Gelderland",
    "wof:name":"Ddh",
    "wof:placetype":"venue"
},
  "geometry": {"coordinates":[5.958153,52.191471],"type":"Point"}
}