{
  "type": "Feature",
  "properties": {
    "addr:full":"Enthovenplein 1 'S Gravenhage South Holland 2521 DA",
    "addr:housenumber":"1 '",
    "addr:postcode":"2521 da",
    "addr:street":"Enthovenplein",
    "iso:country":"NL",
    "sg:address":"Enthovenplein 1",
    "sg:city":"'S Gravenhage",
    "sg:orig_category":"Organisaties And Verenigingen",
    "sg:phone":"+31 70 445 4545",
    "sg:postcode":"2521 DA",
    "sg:province":"South Holland",
    "wof:name":"Consumentenbond",
    "wof:placetype":"venue"
},
  "geometry": {"coordinates":[4.3257417679,52.0692558289],"type":"Point"}
}