{
  "type": "Feature",
  "properties": {
    "addr:full":"Polsbroekpassage 24 Zutphen Gelderland 7201 CA",
    "addr:housenumber":"24",
    "addr:postcode":"7201 ca",
    "addr:street":"Polsbroekpassage;Gelderland",
    "iso:country":"NL",
    "sg:address":"Polsbroekpassage 24",
    "sg:city":"Zutphen",
    "sg:orig_category":"Afslankinstituten",
    "sg:phone":"+31 575 512 345",
    "sg:postcode":"7201 CA",
    "sg:province":"Gelderland",
    "wof:name":"Slender You Iduna",
    "wof:placetype":"venue"
},
  "geometry": {"coordinates":[6.200803,52.140965],"type":"Point"}
}