{
  "type": "Feature",
  "properties": {
    "addr:full":"Beeklaan 326 'S Gravenhage Zuid-Holland 2562 AW",
    "addr:housenumber":"326 '",
    "addr:postcode":"2562 aw",
    "addr:street":"Beeklaan",
    "iso:country":"NL",
    "sg:address":"Beeklaan 326",
    "sg:city":"'S Gravenhage",
    "sg:orig_category":"Fotostudio'S And Fotografen",
    "sg:phone":"+31 70 362 2252",
    "sg:postcode":"2562 AW",
    "sg:province":"Zuid-Holland",
    "wof:name":"K.S. Harzing",
    "wof:placetype":"venue"
},
  "geometry": {"coordinates":[4.28326,52.075001],"type":"Point"}
}