{
  "type": "Feature",
  "properties": {
    "addr:full":"Nw Spiegelstr 46 Amsterdam North Holland 1017 DG",
    "addr:housenumber":"46",
    "addr:postcode":"1017 dg",
    "iso:country":"NL",
    "sg:address":"Nw Spiegelstr 46",
    "sg:city":"Amsterdam",
    "sg:orig_category":"Kunsthandel",
    "sg:phone":"+31 20 624 8599",
    "sg:postcode":"1017 DG",
    "sg:province":"North Holland",
    "wof:name":"Duyvendijk Brouwer, Van",
    "wof:placetype":"venue"
},
  "geometry": {"coordinates":[4.888664,52.363678],"type":"Point"}
}