{
  "type": "Feature",
  "properties": {
    "addr:full":"Min Kanstr 4 Emmen Drenthe 7811 GP",
    "addr:housenumber":"4",
    "addr:postcode":"7811 gp",
    "addr:street":"Kanstr",
    "iso:country":"NL",
    "sg:address":"Min Kanstr 4",
    "sg:city":"Emmen",
    "sg:orig_category":"Juweliers",
    "sg:phone":"+31 591 614 470",
    "sg:postcode":"7811 GP",
    "sg:province":"Drenthe",
    "sg:website":"http://www.woltersjuweliers.nl",
    "wof:name":"Wolters",
    "wof:placetype":"venue"
},
  "geometry": {"coordinates":[6.8964,52.782017],"type":"Point"}
}