{
  "type": "Feature",
  "properties": {
    "addr:full":"Zeelbergsewg 30 Valkenswaard Noord-Brabant 5555 LC",
    "addr:housenumber":"30",
    "addr:postcode":"5555 lc",
    "addr:street":"Zeelbergsewg",
    "iso:country":"NL",
    "sg:address":"Zeelbergsewg 30",
    "sg:city":"Valkenswaard",
    "sg:orig_category":"Verhuur",
    "sg:phone":"+31 40 204 9559",
    "sg:postcode":"5555 LC",
    "sg:province":"Noord-Brabant",
    "wof:name":"Toolco",
    "wof:placetype":"venue"
},
  "geometry": {"coordinates":[5.471366,51.344223],"type":"Point"}
}