{
  "type": "Feature",
  "properties": {
    "addr:full":"Hoogakker 21 Bennekom Gelderland 6721 ZG",
    "addr:housenumber":"21",
    "addr:postcode":"6721 zg",
    "addr:street":"Hoogakker;Gelderland",
    "iso:country":"NL",
    "sg:address":"Hoogakker 21",
    "sg:city":"Bennekom",
    "sg:orig_category":"Kappers",
    "sg:phone":"+31 318 413 921",
    "sg:postcode":"6721 ZG",
    "sg:province":"Gelderland",
    "wof:name":"Jolanda'S Hairexpress",
    "wof:placetype":"venue"
},
  "geometry": {"coordinates":[5.6712341309,52.0018539429],"type":"Point"}
}