{
  "type": "Feature",
  "properties": {
    "addr:full":"Postbus 20 Sassenheim South Holland 2170 AA",
    "addr:housenumber":"20",
    "addr:postcode":"2170 aa",
    "addr:street":"Postbus",
    "iso:country":"NL",
    "sg:address":"Postbus 20",
    "sg:city":"Sassenheim",
    "sg:orig_category":"Verenigingen En Stichtingen",
    "sg:phone":"+31 252 224 189",
    "sg:postcode":"2170 AA",
    "sg:province":"South Holland",
    "wof:name":"Euparal",
    "wof:placetype":"venue"
},
  "geometry": {"coordinates":[4.52109,52.226662],"type":"Point"}
}