{
  "type": "Feature",
  "properties": {
    "iso:country":"NL",
    "sg:address":"Tussendijken 14",
    "sg:city":"Bergum",
    "sg:orig_category":"Artsen - Huisartsen",
    "sg:phone":"+31 511 462 269",
    "sg:postcode":"9251 LW",
    "sg:province":"Provincie Friesland",
    "wof:name":"Gualth\u00e9rie Van Weezel, S P",
    "wof:placetype":"venue"
},
  "geometry": {"coordinates":[5.991733,53.201588],"type":"Point"}
}