{
  "type": "Feature",
  "properties": {
    "iso:country":"NL",
    "sg:address":"Zomerdijk 11",
    "sg:city":"Zaandam",
    "sg:orig_category":"Autokeuringen",
    "sg:phone":"+31 75 616 2227",
    "sg:postcode":"1505 HW",
    "sg:province":"North Holland",
    "wof:name":"Garage Zomerdijk",
    "wof:placetype":"venue"
},
  "geometry": {"coordinates":[4.843546,52.424301],"type":"Point"}
}