{
  "type": "Feature",
  "properties": {
    "iso:country":"NL",
    "sg:address":"Utrechtsestraat 77",
    "sg:city":"Amsterdam",
    "sg:orig_category":"Schoenen",
    "sg:phone":"+31 20 626 9627",
    "sg:postcode":"1017 VJ",
    "sg:province":"Noord-Holland",
    "wof:name":"Fred De La Bretoniere",
    "wof:placetype":"venue"
},
  "geometry": {"coordinates":[4.898719,52.363289],"type":"Point"}
}