{
  "type": "Feature",
  "properties": {
    "addr:full":"Prinses Irenestraat 2 Kerkrade Limburg 6463 BS",
    "addr:housenumber":"2",
    "addr:postcode":"6463 bs",
    "addr:street":"Prinses Irenestraat",
    "iso:country":"NL",
    "sg:address":"Prinses Irenestraat 2",
    "sg:city":"Kerkrade",
    "sg:orig_category":"Meubelzaken, Woning- And Keukeninrichting",
    "sg:phone":"+31 45 535 4180",
    "sg:postcode":"6463 BS",
    "sg:province":"Limburg",
    "wof:name":"Aqua America Bedding",
    "wof:placetype":"venue"
},
  "geometry": {"coordinates":[6.067389,50.873363],"type":"Point"}
}