{
  "type": "Feature",
  "properties": {
    "addr:full":"Sumatrastr 33 Amersfoort Utrecht 3818 RE",
    "addr:housenumber":"33",
    "addr:postcode":"3818",
    "addr:street":"Sumatrastr",
    "iso:country":"NL",
    "sg:address":"Sumatrastr 33",
    "sg:city":"Amersfoort",
    "sg:orig_category":"Goudsmeden En Zilversmeden",
    "sg:phone":"+31 33 475 1620",
    "sg:postcode":"3818 RE",
    "sg:province":"Utrecht",
    "wof:name":"Cora, Vonk",
    "wof:placetype":"venue"
},
  "geometry": {"coordinates":[5.376898,52.141144],"type":"Point"}
}