{
  "type": "Feature",
  "properties": {
    "iso:country":"NL",
    "sg:address":"Emmapln 24",
    "sg:city":"S Hertogenbosch",
    "sg:orig_category":"Fotojournalisten Freelance",
    "sg:phone":"+31 73 612 1655",
    "sg:postcode":"5211 VW",
    "sg:province":"North Brabant",
    "wof:name":"Budelman, Jet",
    "wof:placetype":"venue"
},
  "geometry": {"coordinates":[5.296507,51.692211],"type":"Point"}
}