{
  "type": "Feature",
  "properties": {
    "addr:full":"Nieuweweg 3 Megchelen Gelderland 7078 AK",
    "addr:housenumber":"3",
    "addr:postcode":"7078 ak",
    "addr:street":"Nieuweweg;Gelderland",
    "iso:country":"NL",
    "sg:address":"Nieuweweg 3",
    "sg:city":"Megchelen",
    "sg:orig_category":"Chemische Producten Gh",
    "sg:phone":"+31 315 377 711",
    "sg:postcode":"7078 AK",
    "sg:province":"Gelderland",
    "wof:name":"Kiwitz Megchelen Bv",
    "wof:placetype":"venue"
},
  "geometry": {"coordinates":[6.391283,51.83812],"type":"Point"}
}