{
  "type": "Feature",
  "properties": {
    "addr:full":"Binnenhof 30 Amstelveen North Holland 1181 ZH",
    "addr:housenumber":"30",
    "addr:postcode":"1181 zh",
    "addr:street":"Binnenhof",
    "iso:country":"NL",
    "sg:address":"Binnenhof 30",
    "sg:city":"Amstelveen",
    "sg:orig_category":"Juweliers",
    "sg:phone":"+31 20 641 9356",
    "sg:postcode":"1181 ZH",
    "sg:province":"North Holland",
    "wof:name":"Eweg, J",
    "wof:placetype":"venue"
},
  "geometry": {"coordinates":[4.862007,52.302517],"type":"Point"}
}