{
  "type": "Feature",
  "properties": {
    "iso:country":"NL",
    "sg:address":"Kwintrum 5",
    "sg:city":"Kwintsheul",
    "sg:orig_category":"Kappers",
    "sg:phone":"+31 174 294 865",
    "sg:postcode":"2295 HZ",
    "sg:province":"South Holland",
    "wof:name":"Hair - Fashion - Kwintsheul",
    "wof:placetype":"venue"
},
  "geometry": {"coordinates":[4.2555379868,52.0147628784],"type":"Point"}
}