{
  "type": "Feature",
  "properties": {
    "addr:full":"Heuvel 8 Westerhoven North Brabant 5563 AP",
    "addr:housenumber":"8",
    "addr:postcode":"5563 ap",
    "addr:street":"Heuvel",
    "iso:country":"NL",
    "sg:address":"Heuvel 8",
    "sg:city":"Westerhoven",
    "sg:orig_category":"Banken And Kredietinstellingen",
    "sg:phone":"+31 497 551 855",
    "sg:postcode":"5563 AP",
    "sg:province":"North Brabant",
    "wof:name":"Rabobank",
    "wof:placetype":"venue"
},
  "geometry": {"coordinates":[5.401037,51.332596],"type":"Point"}
}