{
  "type": "Feature",
  "properties": {
    "addr:full":"Van Der Heijdenstraat 38 Enschede Overijssel 7533 WT",
    "addr:housenumber":"38",
    "addr:postcode":"7533 wt",
    "addr:street":"Van Der Heijdenstraat",
    "iso:country":"NL",
    "sg:address":"Van Der Heijdenstraat 38",
    "sg:city":"Enschede",
    "sg:orig_category":"Landbouwmachines Gh",
    "sg:phone":"+31 53 431 8403",
    "sg:postcode":"7533 WT",
    "sg:province":"Overijssel",
    "wof:name":"Heka Mw",
    "wof:placetype":"venue"
},
  "geometry": {"coordinates":[6.918191,52.221775],"type":"Point"}
}