{
  "type": "Feature",
  "properties": {
    "addr:full":"Driehuizen 35 Andyk North Holland 1619 GL",
    "addr:housenumber":"35",
    "addr:postcode":"1619 gl",
    "addr:street":"Driehuizen",
    "iso:country":"NL",
    "sg:address":"Driehuizen 35",
    "sg:city":"Andyk",
    "sg:orig_category":"Kaas",
    "sg:phone":"+31 228 585 702",
    "sg:postcode":"1619 GL",
    "sg:province":"North Holland",
    "wof:name":"Westfriesedijk Vof, De",
    "wof:placetype":"venue"
},
  "geometry": {"coordinates":[5.2225251198,52.7443618774],"type":"Point"}
}