{
  "type": "Feature",
  "properties": {
    "addr:full":"Koningswg 22 Soest Utrecht 3762 EC",
    "addr:housenumber":"22",
    "addr:postcode":"3762 ec",
    "addr:street":"Koningswg",
    "iso:country":"NL",
    "sg:address":"Koningswg 22",
    "sg:city":"Soest",
    "sg:orig_category":"Drukkerijen",
    "sg:phone":"+31 35 601 4751",
    "sg:postcode":"3762 EC",
    "sg:province":"Utrecht",
    "wof:name":"Atlas Bv",
    "wof:placetype":"venue"
},
  "geometry": {"coordinates":[5.271677,52.178013],"type":"Point"}
}