{
  "type": "Feature",
  "properties": {
    "addr:full":"Punterdiep 96 Zwolle Overijssel 8032 TX",
    "addr:housenumber":"96",
    "addr:postcode":"8032 tx",
    "addr:street":"Punterdiep",
    "iso:country":"NL",
    "sg:address":"Punterdiep 96",
    "sg:city":"Zwolle",
    "sg:orig_category":"Bloemen En Planten",
    "sg:phone":"+31 38 454 2732",
    "sg:postcode":"8032 TX",
    "sg:province":"Overijssel",
    "wof:name":"Tulen, F B H",
    "wof:placetype":"venue"
},
  "geometry": {"coordinates":[6.101683,52.53706],"type":"Point"}
}