{
  "type": "Feature",
  "properties": {
    "iso:country":"NL",
    "sg:address":"Stadhuisplein 354",
    "sg:city":"Tilburg",
    "sg:orig_category":"Werving And Selectie Van Tijdelijk Personeel And Uitzendkantoren",
    "sg:phone":"+31 13 462 7444",
    "sg:postcode":"5038 TH",
    "sg:province":"North Brabant",
    "wof:name":"Kelly Services",
    "wof:placetype":"venue"
},
  "geometry": {"coordinates":[5.0870451927,51.5560150146],"type":"Point"}
}