{
  "type": "Feature",
  "properties": {
    "addr:full":"4E Industrieweg 2 Lopik Utrecht 3411 MC",
    "addr:housenumber":"2",
    "addr:postcode":"3411 mc",
    "addr:street":"4E Industrieweg",
    "iso:country":"NL",
    "sg:address":"4E Industrieweg 2",
    "sg:city":"Lopik",
    "sg:orig_category":"Marktonderzoekbureaus",
    "sg:phone":"+31 348 559 214",
    "sg:postcode":"3411 MC",
    "sg:province":"Utrecht",
    "wof:name":"United Entertainment Limited",
    "wof:placetype":"venue"
},
  "geometry": {"coordinates":[4.97146,51.985355],"type":"Point"}
}