{
  "type": "Feature",
  "properties": {
    "addr:full":"Azaleastraat 120 Leeuwarden Provincie Friesland 8922 GN",
    "addr:housenumber":"120",
    "addr:postcode":"8922 gn",
    "addr:street":"Azaleastraat;Provincie Friesland",
    "iso:country":"NL",
    "sg:address":"Azaleastraat 120",
    "sg:city":"Leeuwarden",
    "sg:orig_category":"Verzekeringen",
    "sg:phone":"+31 58 266 6711",
    "sg:postcode":"8922 GN",
    "sg:province":"Provincie Friesland",
    "wof:name":"H. De Jong Assurantie- Spaaradviesburo",
    "wof:placetype":"venue"
},
  "geometry": {"coordinates":[5.810119,53.211773],"type":"Point"}
}