{
  "type": "Feature",
  "properties": {
    "addr:full":"Osdorpplein 505 Amsterdam Noord-Holland 1068 TA",
    "addr:housenumber":"505",
    "addr:postcode":"1068 ta",
    "addr:street":"Osdorpplein",
    "iso:country":"NL",
    "sg:address":"Osdorpplein 505",
    "sg:city":"Amsterdam",
    "sg:orig_category":"Werving And Selectie Van Tijdelijk Personeel And Uitzendkantoren",
    "sg:phone":"+31 20 610 1061",
    "sg:postcode":"1068 TA",
    "sg:province":"Noord-Holland",
    "wof:name":"Holland",
    "wof:placetype":"venue"
},
  "geometry": {"coordinates":[4.8033370972,52.358379364],"type":"Point"}
}