{
  "type": "Feature",
  "properties": {
    "addr:full":"Oldewierde 170 Almere Flevoland 1353 HV",
    "addr:housenumber":"170",
    "addr:postcode":"1353 hv",
    "addr:street":"Oldewierde;Flevoland",
    "iso:country":"NL",
    "sg:address":"Oldewierde 170",
    "sg:city":"Almere",
    "sg:orig_category":"Overheidsdiensten",
    "sg:phone":"+31 36 531 4036",
    "sg:postcode":"1353 HV",
    "sg:province":"Flevoland",
    "wof:name":"Buurtcentrum De Wierden",
    "wof:placetype":"venue"
},
  "geometry": {"coordinates":[5.2066807747,52.3393363953],"type":"Point"}
}