{
  "type": "Feature",
  "properties": {
    "addr:full":"Asterstraat 13 Katwijk Zh Zuid-Holland 2223 VG",
    "addr:housenumber":"13",
    "addr:postcode":"2223 vg",
    "addr:street":"Asterstraat",
    "iso:country":"NL",
    "sg:address":"Asterstraat 13",
    "sg:city":"Katwijk Zh",
    "sg:orig_category":"Bedrijfs- And Managementsconsultants",
    "sg:phone":"+31 71 407 3188",
    "sg:postcode":"2223 VG",
    "sg:province":"Zuid-Holland",
    "wof:name":"Advies & Service Bureau Rapo",
    "wof:placetype":"venue"
},
  "geometry": {"coordinates":[4.425307,52.186996],"type":"Point"}
}