{
  "type": "Feature",
  "properties": {
    "addr:full":"Kamerlingswyk Wz 87 Zwartemeer Drenthe 7894 AN",
    "addr:housenumber":"87",
    "addr:postcode":"7894 an",
    "addr:street":"Kamerlingswyk Wz",
    "iso:country":"NL",
    "sg:address":"Kamerlingswyk Wz 87",
    "sg:city":"Zwartemeer",
    "sg:orig_category":"Voegwerken",
    "sg:phone":"+31 591 315 846",
    "sg:postcode":"7894 AN",
    "sg:province":"Drenthe",
    "wof:name":"Doek, Gebr",
    "wof:placetype":"venue"
},
  "geometry": {"coordinates":[7.045698,52.710388],"type":"Point"}
}