{
  "type": "Feature",
  "properties": {
    "addr:full":"Vondellaan 12 Haren Gn Groningen 9752 EC",
    "addr:housenumber":"12",
    "addr:postcode":"9752 ec",
    "addr:street":"Vondellaan",
    "iso:country":"NL",
    "sg:address":"Vondellaan 12",
    "sg:city":"Haren Gn",
    "sg:orig_category":"Verzekeringen",
    "sg:phone":"+31 50 534 1181",
    "sg:postcode":"9752 EC",
    "sg:province":"Groningen",
    "wof:name":"S Dijkstra",
    "wof:placetype":"venue"
},
  "geometry": {"coordinates":[6.599709,53.172859],"type":"Point"}
}