{
  "type": "Feature",
  "properties": {
    "iso:country":"NL",
    "sg:address":"Sonnemerestraat 1",
    "sg:city":"Rotterdam",
    "sg:orig_category":"Verhuur Bouwmachines",
    "sg:phone":"+31 10 437 5622",
    "sg:postcode":"3044 EJ",
    "sg:province":"Zuid-Holland",
    "wof:name":"Vdk Leasing Bv",
    "wof:placetype":"venue"
},
  "geometry": {"coordinates":[4.415614,51.923161],"type":"Point"}
}