{
  "type": "Feature",
  "properties": {
    "iso:country":"NL",
    "sg:address":"Panhuizerwg 10",
    "sg:city":"Kesteren",
    "sg:orig_category":"Metaalbewerking",
    "sg:phone":"+31 488 480 825",
    "sg:postcode":"4041 CN",
    "sg:province":"Gelderland",
    "wof:name":"Hecoma",
    "wof:placetype":"venue"
},
  "geometry": {"coordinates":[5.587608,51.935249],"type":"Point"}
}