{
  "type": "Feature",
  "properties": {
    "addr:full":"Dorpsstr 67A Krimpen Aan De Lek Zuid-Holland 2931 AD",
    "addr:housenumber":"67a",
    "addr:postcode":"lek;2931 ad",
    "addr:street":"Dorpsstr",
    "iso:country":"NL",
    "sg:address":"Dorpsstr 67A",
    "sg:city":"Krimpen Aan De Lek",
    "sg:orig_category":"Hydraulische Apparaten En Installaties",
    "sg:phone":"+31 180 511 577",
    "sg:postcode":"2931 AD",
    "sg:province":"Zuid-Holland",
    "sg:website":"http://www.vdvelden.nl",
    "wof:name":"Velden Bv, A Van Der",
    "wof:placetype":"venue"
},
  "geometry": {"coordinates":[4.62182,51.892418],"type":"Point"}
}