{
  "type": "Feature",
  "properties": {
    "iso:country":"NL",
    "sg:address":"Emmastraat 139",
    "sg:city":"Vlaardingen",
    "sg:orig_category":"Huishoudapparatuur, Televisies And Radio'S",
    "sg:phone":"+31 10 248 9544",
    "sg:postcode":"3134 CK",
    "sg:province":"Zuid-Holland",
    "wof:name":"J.A. Dijkhuizen",
    "wof:placetype":"venue"
},
  "geometry": {"coordinates":[4.353222,51.910221],"type":"Point"}
}