{
  "type": "Feature",
  "properties": {
    "addr:full":"Poelestraat 40 Groningen Groningen 9712 KC",
    "addr:housenumber":"40",
    "addr:postcode":"9712 kc",
    "addr:street":"Poelestraat",
    "iso:country":"NL",
    "sg:address":"Poelestraat 40",
    "sg:city":"Groningen",
    "sg:orig_category":"Damesmodezaken",
    "sg:phone":"+31 50 314 5835",
    "sg:postcode":"9712 KC",
    "sg:province":"Groningen",
    "wof:name":"Nick",
    "wof:placetype":"venue"
},
  "geometry": {"coordinates":[6.571443,53.218494],"type":"Point"}
}