{
  "type": "Feature",
  "properties": {
    "iso:country":"NL",
    "sg:address":"Aalsterwg 287",
    "sg:city":"Eindhoven",
    "sg:orig_category":"Scholen Voor Algemeen Voortgezet Onderwijs",
    "sg:phone":"+31 40 212 1125",
    "sg:postcode":"5644 RE",
    "sg:province":"Noord-Brabant",
    "wof:name":"Roc",
    "wof:placetype":"venue"
},
  "geometry": {"coordinates":[5.486476,51.408863],"type":"Point"}
}