{
  "type": "Feature",
  "properties": {
    "iso:country":"NL",
    "sg:address":"Spikkerweg 162",
    "sg:city":"Roermond",
    "sg:orig_category":"Schilderwerk",
    "sg:phone":"+31 475 326 584",
    "sg:postcode":"6042 KS",
    "sg:province":"Limburg",
    "wof:name":"Schildersbedrijf Guus Van Helden En Zn.",
    "wof:placetype":"venue"
},
  "geometry": {"coordinates":[6.041267,51.197517],"type":"Point"}
}