{
  "type": "Feature",
  "properties": {
    "iso:country":"NL",
    "sg:address":"J Wagenaarring 16",
    "sg:city":"Haarlem",
    "sg:orig_category":"Onderhoudswerken",
    "sg:phone":"+31 23 536 5639",
    "sg:postcode":"2033 NZ",
    "sg:province":"Noord-Holland",
    "wof:name":"Remijn",
    "wof:placetype":"venue"
},
  "geometry": {"coordinates":[4.654248,52.374565],"type":"Point"}
}