{
  "type": "Feature",
  "properties": {
    "addr:full":"Reijmerstokkerdorpsstr 77 Reijmerstok Limburg 6274 NH",
    "addr:housenumber":"77",
    "addr:postcode":"6274 nh",
    "addr:street":"Reijmerstokkerdorpsstr",
    "iso:country":"NL",
    "sg:address":"Reijmerstokkerdorpsstr 77",
    "sg:city":"Reijmerstok",
    "sg:classifiers":[
        {
            "category":"Travel",
            "subcategory":"Hotels & Motels",
            "type":"Entertainment"
        }
    ],
    "sg:phone":"+31 43 457 1778",
    "sg:postcode":"6274 NH",
    "sg:province":"Limburg",
    "wof:name":"Pension Croonen",
    "wof:placetype":"venue"
},
  "geometry": {"coordinates":[5.83994,50.801285],"type":"Point"}
}