{
  "type": "Feature",
  "properties": {
    "addr:full":"Prins Hendrikstraat 10 Culemborg Gelderland 4101 JW",
    "addr:housenumber":"10",
    "addr:postcode":"4101 jw",
    "addr:street":"Prins Hendrikstraat;Gelderland",
    "iso:country":"NL",
    "sg:address":"Prins Hendrikstraat 10",
    "sg:city":"Culemborg",
    "sg:orig_category":"Meubelreparatie And -Restauratie",
    "sg:phone":"+31 345 518 922",
    "sg:postcode":"4101 JW",
    "sg:province":"Gelderland",
    "wof:name":"Meubelstoffeerderij Speyer",
    "wof:placetype":"venue"
},
  "geometry": {"coordinates":[5.237443,51.958576],"type":"Point"}
}