{
  "type": "Feature",
  "properties": {
    "addr:full":"Hoofdstraat 54 Meppel Provincie Drenthe 7941 AK",
    "addr:housenumber":"54",
    "addr:postcode":"7941 ak",
    "addr:street":"Hoofdstraat;Provincie Drenthe",
    "iso:country":"NL",
    "sg:address":"Hoofdstraat 54",
    "sg:city":"Meppel",
    "sg:classifiers":[
        {
            "category":"Fast Food",
            "type":"Food & Drink"
        }
    ],
    "sg:phone":"+31 522 243 451",
    "sg:postcode":"7941 AK",
    "sg:province":"Provincie Drenthe",
    "sg:tags":[
        "afhaal",
        "restaurant"
    ],
    "wof:name":"Vork Vastfood Meppel",
    "wof:placetype":"venue"
},
  "geometry": {"coordinates":[6.196295,52.699615],"type":"Point"}
}