{
  "type": "Feature",
  "properties": {
    "addr:full":"Bankapln 3 S Gravenhage Zuid-Holland 2585 EV",
    "addr:housenumber":"3;gravenhage",
    "addr:street":"Bankapln;S",
    "iso:country":"NL",
    "sg:address":"Bankapln 3",
    "sg:city":"S Gravenhage",
    "sg:classifiers":[
        {
            "category":"Professional",
            "subcategory":"Management & Consulting",
            "type":"Services"
        }
    ],
    "sg:phone":"+31 70 416 1616",
    "sg:postcode":"2585 EV",
    "sg:province":"Zuid-Holland",
    "sg:tags":[
        "relation",
        "adviesbureaus",
        "public"
    ],
    "sg:website":"http://www.wenvh.nl",
    "wof:name":"Winkelman & Van Hessen Bv",
    "wof:placetype":"venue"
},
  "geometry": {"coordinates":[4.29777,52.094799],"type":"Point"}
}