{
  "type": "Feature",
  "properties": {
    "addr:full":"C Huygensstr 18-22 Wychen Gelderland 6603 BC",
    "addr:housenumber":"18-22",
    "addr:postcode":"6603 bc",
    "addr:street":"Wychen Gelderland",
    "iso:country":"NL",
    "sg:address":"C Huygensstr 18-22",
    "sg:city":"Wychen",
    "sg:orig_category":"Bestratingen",
    "sg:phone":"+31 24 641 4027",
    "sg:postcode":"6603 BC",
    "sg:province":"Gelderland",
    "wof:name":"Wijchens Wegenbouwbedrijf Bv",
    "wof:placetype":"venue"
},
  "geometry": {"coordinates":[-126.555511,54.485668],"type":"Point"}
}