{
  "type": "Feature",
  "properties": {
    "addr:full":"Hoofdstr 139 Bergambacht Zuid-Holland 2861 AN",
    "addr:housenumber":"139",
    "addr:postcode":"2861 an",
    "iso:country":"NL",
    "sg:address":"Hoofdstr 139",
    "sg:city":"Bergambacht",
    "sg:orig_category":"Artsen - Huisartsen",
    "sg:phone":"+31 182 351 216",
    "sg:postcode":"2861 AN",
    "sg:province":"Zuid-Holland",
    "wof:name":"Kool, G B De",
    "wof:placetype":"venue"
},
  "geometry": {"coordinates":[4.783376,51.937206],"type":"Point"}
}