{
  "type": "Feature",
  "properties": {
    "iso:country":"NL",
    "sg:address":"Elsbeekw 49",
    "sg:city":"Hengelo",
    "sg:orig_category":"Modelmakerijen",
    "sg:phone":"+31 74 291 3512",
    "sg:postcode":"7557 CB",
    "sg:province":"NL.08",
    "wof:name":"Oldenhof",
    "wof:placetype":"venue"
},
  "geometry": {"coordinates":[6.804333,52.266674],"type":"Point"}
}