{
  "type": "Feature",
  "properties": {
    "addr:full":"Crocusstr 12 Eindhoven North Brabant 5615 BA",
    "addr:housenumber":"12",
    "addr:postcode":"5615 ba",
    "addr:street":"Crocusstr",
    "iso:country":"NL",
    "sg:address":"Crocusstr 12",
    "sg:city":"Eindhoven",
    "sg:orig_category":"Fotografie Reclame En Mode",
    "sg:phone":"+31 40 244 8234",
    "sg:postcode":"5615 BA",
    "sg:province":"North Brabant",
    "wof:name":"Dingo By Night Pictures",
    "wof:placetype":"venue"
},
  "geometry": {"coordinates":[5.491356,51.424805],"type":"Point"}
}