{
  "type": "Feature",
  "properties": {
    "addr:full":"Julianaln 26 Heemstede North Holland 2101 ZB",
    "addr:housenumber":"26",
    "addr:postcode":"2101 zb",
    "addr:street":"Julianaln",
    "iso:country":"NL",
    "sg:address":"Julianaln 26",
    "sg:city":"Heemstede",
    "sg:orig_category":"Kinderopvang",
    "sg:phone":"+31 23 547 4674",
    "sg:postcode":"2101 ZB",
    "sg:province":"North Holland",
    "wof:name":"Midas, Bureau",
    "wof:placetype":"venue"
},
  "geometry": {"coordinates":[4.623008,52.352745],"type":"Point"}
}