{
  "type": "Feature",
  "properties": {
    "addr:full":"De Vlinderhoven 63 Schiedam Zuid-Holland 3124 BS",
    "addr:housenumber":"63",
    "addr:postcode":"3124 bs",
    "addr:street":"De Vlinderhoven",
    "iso:country":"NL",
    "sg:address":"De Vlinderhoven 63",
    "sg:city":"Schiedam",
    "sg:orig_category":"Kappers",
    "sg:phone":"+31 10 471 6919",
    "sg:postcode":"3124 BS",
    "sg:province":"Zuid-Holland",
    "wof:name":"De Mobiele Haarspecialiste",
    "wof:placetype":"venue"
},
  "geometry": {"coordinates":[4.380314827,51.9407920837],"type":"Point"}
}