{
  "type": "Feature",
  "properties": {
    "iso:country":"NL",
    "sg:address":"Oudedk 21",
    "sg:city":"Rotterdam",
    "sg:orig_category":"Bedrijfshuisvesting",
    "sg:phone":"+31 10 452 1744",
    "sg:postcode":"3062 AB",
    "sg:province":"Zuid-Holland",
    "wof:name":"Batenburg",
    "wof:placetype":"venue"
},
  "geometry": {"coordinates":[4.515227,51.924816],"type":"Point"}
}