{
  "type": "Feature",
  "properties": {
    "addr:full":"Sloterweg 312 Badhoevedorp Noord-Holland 1171 VJ",
    "addr:housenumber":"312",
    "addr:postcode":"1171 vj",
    "addr:street":"Sloterweg",
    "iso:country":"NL",
    "sg:address":"Sloterweg 312",
    "sg:city":"Badhoevedorp",
    "sg:orig_category":"Verzekeringen",
    "sg:phone":"+31 20 659 2560",
    "sg:postcode":"1171 VJ",
    "sg:province":"Noord-Holland",
    "wof:name":"Joke Bakker Assurantien",
    "wof:placetype":"venue"
},
  "geometry": {"coordinates":[4.769072,52.33075],"type":"Point"}
}