{
  "type": "Feature",
  "properties": {
    "iso:country":"NL",
    "sg:address":"Kerkradersteenweg 25",
    "sg:city":"Kerkrade",
    "sg:orig_category":"Kantoorapparatuur Gh",
    "sg:phone":"+31 45 546 0427",
    "sg:postcode":"6466 PA",
    "sg:province":"Limburg",
    "wof:name":"Burweij Handelsonderneming",
    "wof:placetype":"venue"
},
  "geometry": {"coordinates":[6.0520319939,50.8679275513],"type":"Point"}
}