{
  "type": "Feature",
  "properties": {
    "addr:full":"Vissersstraat 23 Eersel North Brabant 5521 VL",
    "addr:housenumber":"23",
    "addr:postcode":"5521 vl",
    "addr:street":"Vissersstraat",
    "iso:country":"NL",
    "sg:address":"Vissersstraat 23",
    "sg:city":"Eersel",
    "sg:orig_category":"Boekhouders",
    "sg:phone":"+31 497 382 859",
    "sg:postcode":"5521 VL",
    "sg:province":"North Brabant",
    "wof:name":"Suykerbuyk Bedrijfsadviseur- Belastingku",
    "wof:placetype":"venue"
},
  "geometry": {"coordinates":[5.317047,51.354404],"type":"Point"}
}