{
  "type": "Feature",
  "properties": {
    "addr:full":"Rouwenboschweg 5 Nijmegen Gelderland 6545 AE",
    "addr:housenumber":"5",
    "addr:postcode":"6545 ae",
    "addr:street":"Rouwenboschweg;Gelderland",
    "iso:country":"NL",
    "sg:address":"Rouwenboschweg 5",
    "sg:city":"Nijmegen",
    "sg:orig_category":"Autokeuringen",
    "sg:phone":"+31 24 378 0044",
    "sg:postcode":"6545 AE",
    "sg:province":"Gelderland",
    "wof:name":"Schmidt Trucks",
    "wof:placetype":"venue"
},
  "geometry": {"coordinates":[5.812933,51.849232],"type":"Point"}
}