{
  "type": "Feature",
  "properties": {
    "addr:full":"De Biezen 11 Ysselstein Ut Utrecht 3401 GD",
    "addr:housenumber":"11",
    "addr:postcode":"3401 gd",
    "addr:street":"De Biezen",
    "iso:country":"NL",
    "sg:address":"De Biezen 11",
    "sg:city":"Ysselstein Ut",
    "sg:orig_category":"Bloemen En Planten",
    "sg:phone":"+31 30 688 9483",
    "sg:postcode":"3401 GD",
    "sg:province":"Utrecht",
    "wof:name":"Blomhof, De",
    "wof:placetype":"venue"
},
  "geometry": {"coordinates":[5.04266,52.017044],"type":"Point"}
}