{
  "type": "Feature",
  "properties": {
    "addr:full":"Torricellistr 7 Badhoevedorp Noord-Holland 1171 CB",
    "addr:housenumber":"7",
    "addr:postcode":"1171 cb",
    "addr:street":"Torricellistr",
    "iso:country":"NL",
    "sg:address":"Torricellistr 7",
    "sg:city":"Badhoevedorp",
    "sg:orig_category":"Verzekeringen - Verzekeringskantoren",
    "sg:phone":"+31 20 659 9461",
    "sg:postcode":"1171 CB",
    "sg:province":"Noord-Holland",
    "wof:name":"Binasco",
    "wof:placetype":"venue"
},
  "geometry": {"coordinates":[4.774101,52.335842],"type":"Point"}
}