{
  "type": "Feature",
  "properties": {
    "iso:country":"NL",
    "sg:address":"Schuilingenwg 8",
    "sg:city":"S Gravendeel",
    "sg:orig_category":"Zonne-Energie",
    "sg:phone":"+31 78 673 5310",
    "sg:postcode":"3295 GL",
    "sg:province":"Zuid-Holland",
    "wof:name":"Sustainables Bv",
    "wof:placetype":"venue"
},
  "geometry": {"coordinates":[4.612292,51.783302],"type":"Point"}
}