{
  "type": "Feature",
  "properties": {
    "addr:full":"Kalverstr 12A Harmelen Utrecht 3481 ES",
    "addr:housenumber":"12a",
    "addr:postcode":"3481 es",
    "addr:street":"Kalverstr",
    "iso:country":"NL",
    "sg:address":"Kalverstr 12A",
    "sg:city":"Harmelen",
    "sg:classifiers":[
        {
            "category":"Food & Beverages",
            "subcategory":"Bakery",
            "type":"Retail Goods"
        }
    ],
    "sg:phone":"+31 348 441 887",
    "sg:postcode":"3481 ES",
    "sg:province":"Utrecht",
    "sg:tags":[
        "brood",
        "en",
        "banket"
    ],
    "wof:name":"Carl Siegert Sinds 1891 Bv",
    "wof:placetype":"venue"
},
  "geometry": {"coordinates":[4.963245,52.090912],"type":"Point"}
}