{
  "type": "Feature",
  "properties": {
    "addr:full":"Schapedrift 87 Hardinxveld Giessend Zuid-Holland 3371 JJ",
    "addr:housenumber":"87;giessend",
    "addr:postcode":"3371 jj",
    "addr:street":"Schapedrift",
    "iso:country":"NL",
    "sg:address":"Schapedrift 87",
    "sg:city":"Hardinxveld Giessend",
    "sg:orig_category":"Fitnesscentra",
    "sg:phone":"+31 184 612 761",
    "sg:postcode":"3371 JJ",
    "sg:province":"Zuid-Holland",
    "wof:name":"Konditie- En Fitnesscentrum Slank En Fit Bv",
    "wof:placetype":"venue"
},
  "geometry": {"coordinates":[4.82401,51.829411],"type":"Point"}
}