{
  "type": "Feature",
  "properties": {
    "addr:full":"Sint Gregoriuslaan 13 Brunssum Limburg 6442 AE",
    "addr:housenumber":"13",
    "addr:postcode":"6442 ae",
    "addr:street":"Sint Gregoriuslaan",
    "iso:country":"NL",
    "sg:address":"Sint Gregoriuslaan 13",
    "sg:city":"Brunssum",
    "sg:orig_category":"Boekhouders",
    "sg:phone":"+31 45 525 7337",
    "sg:postcode":"6442 AE",
    "sg:province":"Limburg",
    "wof:name":"Onderwijsstichting Brunssum",
    "wof:placetype":"venue"
},
  "geometry": {"coordinates":[5.979473,50.950871],"type":"Point"}
}