{
  "type": "Feature",
  "properties": {
    "addr:full":"Maaskd 154A Rotterdam Zuid-Holland 3071 NP",
    "addr:housenumber":"154a",
    "addr:postcode":"3071 np",
    "iso:country":"NL",
    "sg:address":"Maaskd 154A",
    "sg:city":"Rotterdam",
    "sg:orig_category":"Fotolaboratoria",
    "sg:phone":"+31 10 433 0600",
    "sg:postcode":"3071 NP",
    "sg:province":"Zuid-Holland",
    "wof:name":"Quality Color",
    "wof:placetype":"venue"
},
  "geometry": {"coordinates":[4.50327,51.910591],"type":"Point"}
}