{
  "type": "Feature",
  "properties": {
    "iso:country":"NL",
    "sg:address":"Passage 21",
    "sg:city":"Waddinxveen",
    "sg:orig_category":"Discountwinkels",
    "sg:phone":"+31 182 614 132",
    "sg:postcode":"2741 HB",
    "sg:province":"South Holland",
    "wof:name":"Van Der Linde Bv (Kledingzaak)",
    "wof:placetype":"venue"
},
  "geometry": {"coordinates":[4.65116,52.045029],"type":"Point"}
}