{
  "type": "Feature",
  "properties": {
    "addr:full":"Hondsdijk 71 Koudekerk A/D Rijn South Holland 2396 HK",
    "addr:housenumber":"71;a / d",
    "addr:postcode":"2396 hk",
    "addr:street":"Hondsdijk;Rijn South",
    "iso:country":"NL",
    "sg:address":"Hondsdijk 71",
    "sg:city":"Koudekerk A/D Rijn",
    "sg:orig_category":"Auto'S And Voertuigen",
    "sg:phone":"+31 71 341 2090",
    "sg:postcode":"2396 HK",
    "sg:province":"South Holland",
    "wof:name":"A. Van Elven",
    "wof:placetype":"venue"
},
  "geometry": {"coordinates":[4.585416,52.129753],"type":"Point"}
}