{
  "type": "Feature",
  "properties": {
    "addr:full":"Vriesewg 115 Dordrecht Zuid-Holland 3311 NV",
    "addr:housenumber":"115",
    "addr:postcode":"3311 nv",
    "iso:country":"NL",
    "sg:address":"Vriesewg 115",
    "sg:city":"Dordrecht",
    "sg:orig_category":"Kappers",
    "sg:phone":"+31 78 613 7309",
    "sg:postcode":"3311 NV",
    "sg:province":"Zuid-Holland",
    "wof:name":"Le Bigoudi Coiffure",
    "wof:placetype":"venue"
},
  "geometry": {"coordinates":[4.673383,51.810974],"type":"Point"}
}