{
  "type": "Feature",
  "properties": {
    "iso:country":"NL",
    "sg:address":"Hoofdstr 212",
    "sg:city":"Epe",
    "sg:orig_category":"Verzekeringen - Verzekeringskantoren",
    "sg:phone":"+31 578 616 927",
    "sg:postcode":"8162 AT",
    "sg:province":"Gelderland",
    "wof:name":"Vos Assuranti\u00ebn",
    "wof:placetype":"venue"
},
  "geometry": {"coordinates":[5.980613,52.337948],"type":"Point"}
}