{
  "type": "Feature",
  "properties": {
    "addr:full":"Karel Doormanlaan 66 Bussum North Holland 1403 TN",
    "addr:housenumber":"66",
    "addr:postcode":"1403",
    "addr:street":"Karel Doormanlaan",
    "iso:country":"NL",
    "sg:address":"Karel Doormanlaan 66",
    "sg:city":"Bussum",
    "sg:orig_category":"Kappers",
    "sg:phone":"+31 35 693 3066",
    "sg:postcode":"1403 TN",
    "sg:province":"North Holland",
    "wof:name":"A.M. V.D. Pijl",
    "wof:placetype":"venue"
},
  "geometry": {"coordinates":[5.1784582138,52.2651329041],"type":"Point"}
}