{
  "type": "Feature",
  "properties": {
    "iso:country":"NL",
    "sg:address":"Karel Doormanlaan 66",
    "sg:city":"Bussum",
    "sg:orig_category":"Kappers",
    "sg:phone":"+31 35 693 3066",
    "sg:postcode":"1403 TN",
    "sg:province":"North Holland",
    "wof:name":"A.M. V.D. Pijl",
    "wof:placetype":"venue"
},
  "geometry": {"coordinates":[5.1784582138,52.2651329041],"type":"Point"}
}