{
  "type": "Feature",
  "properties": {
    "addr:full":"Distelstr 21 Purmerend North Holland 1441 PV",
    "addr:housenumber":"21",
    "addr:postcode":"1441 pv",
    "addr:street":"Distelstr",
    "iso:country":"NL",
    "sg:address":"Distelstr 21",
    "sg:city":"Purmerend",
    "sg:orig_category":"Afslankinstituten",
    "sg:phone":"+31 299 425 567",
    "sg:postcode":"1441 PV",
    "sg:province":"North Holland",
    "wof:name":"Ega Int",
    "wof:placetype":"venue"
},
  "geometry": {"coordinates":[4.95729,52.495476],"type":"Point"}
}