{
  "type": "Feature",
  "properties": {
    "iso:country":"NL",
    "sg:address":"Oude Boomgaard 6",
    "sg:city":"Montfoort",
    "sg:orig_category":"Schilders",
    "sg:phone":"+31 348 474 043",
    "sg:postcode":"3417 HX",
    "sg:province":"Utrecht",
    "sg:website":"http://www.bonschilderwerken.nl",
    "wof:name":"Bon Schilderwerken",
    "wof:placetype":"venue"
},
  "geometry": {"coordinates":[4.948281,52.044102],"type":"Point"}
}