{
  "type": "Feature",
  "properties": {
    "addr:full":"W V Harselaarln 46 Nykerk Gld Gelderland 3863 XZ",
    "addr:housenumber":"46",
    "addr:postcode":"3863 xz",
    "addr:street":"W V Harselaarln;Gld Gelderland",
    "iso:country":"NL",
    "sg:address":"W V Harselaarln 46",
    "sg:city":"Nykerk Gld",
    "sg:orig_category":"Pneumatische Apparaten En Installaties",
    "sg:phone":"+31 33 247 0646",
    "sg:postcode":"3863 XZ",
    "sg:province":"Gelderland",
    "sg:website":"http://www.st-projects.nl",
    "wof:name":"St-Projects Bv",
    "wof:placetype":"venue"
},
  "geometry": {"coordinates":[5.464432,52.21619],"type":"Point"}
}