{
  "type": "Feature",
  "properties": {
    "addr:full":"Peperstraat 13 Naarden Noord-Holland 1411 DX",
    "addr:housenumber":"13",
    "addr:postcode":"1411 dx",
    "addr:street":"Peperstraat",
    "iso:country":"NL",
    "sg:address":"Peperstraat 13",
    "sg:city":"Naarden",
    "sg:orig_category":"Kappers",
    "sg:phone":"+31 35 694 2020",
    "sg:postcode":"1411 DX",
    "sg:province":"Noord-Holland",
    "wof:name":"Okhuysen Kapsalon",
    "wof:placetype":"venue"
},
  "geometry": {"coordinates":[5.16212,52.294609],"type":"Point"}
}