{
  "type": "Feature",
  "properties": {
    "iso:country":"NL",
    "sg:address":"Klaproos 66",
    "sg:city":"Driebergen Rysenb",
    "sg:orig_category":"Bedrijfsopleidingen",
    "sg:phone":"+31 343 513 344",
    "sg:postcode":"3972 PZ",
    "sg:province":"Utrecht",
    "sg:website":"http://www.dejongtraining.nl",
    "wof:name":"Jong Training En Advies",
    "wof:placetype":"venue"
},
  "geometry": {"coordinates":[5.26961,52.052761],"type":"Point"}
}