{
  "type": "Feature",
  "properties": {
    "addr:full":"Handelln 6 Enschede NL.08 7522 KM",
    "addr:housenumber":"6",
    "addr:street":"Handelln;7522 Km",
    "iso:country":"NL",
    "sg:address":"Handelln 6",
    "sg:city":"Enschede",
    "sg:orig_category":"Plaatwerk",
    "sg:phone":"+31 53 434 6680",
    "sg:postcode":"7522 KM",
    "sg:province":"NL.08",
    "sg:website":"http://www.richter.nl",
    "wof:name":"Richter Bv",
    "wof:placetype":"venue"
},
  "geometry": {"coordinates":[6.878817,52.240879],"type":"Point"}
}