{
  "type": "Feature",
  "properties": {
    "iso:country":"NL",
    "sg:address":"Vlierdensedijk 45",
    "sg:city":"Helmond",
    "sg:orig_category":"Drukkerijen And Copyshops",
    "sg:phone":"+31 492 551 551",
    "sg:postcode":"5705 CK",
    "sg:province":"Noord-Brabant",
    "wof:name":"Drukkerij Van Stiphout Bv",
    "wof:placetype":"venue"
},
  "geometry": {"coordinates":[5.682818,51.467941],"type":"Point"}
}