{
  "type": "Feature",
  "properties": {
    "iso:country":"NL",
    "sg:address":"Engbersstr 25",
    "sg:city":"Vasse",
    "sg:orig_category":"Kantoor- En Secretariaatsservice",
    "sg:phone":"+31 541 680 010",
    "sg:postcode":"7661 PG",
    "sg:province":"Overijssel",
    "wof:name":"Monique",
    "wof:placetype":"venue"
},
  "geometry": {"coordinates":[-79.2818374634,35.2577438354],"type":"Point"}
}