{
  "type": "Feature",
  "properties": {
    "addr:full":"Putweg 28 Valkenburg Lb Limburg 6301 KL",
    "addr:housenumber":"28",
    "addr:postcode":"lb;6301 kl",
    "addr:street":"Putweg",
    "iso:country":"NL",
    "sg:address":"Putweg 28",
    "sg:city":"Valkenburg Lb",
    "sg:orig_category":"Wegen And Sportterreinen",
    "sg:phone":"+31 43 604 0607",
    "sg:postcode":"6301 KL",
    "sg:province":"Limburg",
    "wof:name":"P.C.G. (Paul Curfs Grondwerken)",
    "wof:placetype":"venue"
},
  "geometry": {"coordinates":[5.7823781967,50.8718910217],"type":"Point"}
}