{
  "type": "Feature",
  "properties": {
    "iso:country":"NL",
    "sg:address":"Putweg 28",
    "sg:city":"Valkenburg Lb",
    "sg:orig_category":"Wegen And Sportterreinen",
    "sg:phone":"+31 43 604 0607",
    "sg:postcode":"6301 KL",
    "sg:province":"Limburg",
    "wof:name":"P.C.G. (Paul Curfs Grondwerken)",
    "wof:placetype":"venue"
},
  "geometry": {"coordinates":[5.7823781967,50.8718910217],"type":"Point"}
}