{
  "type": "Feature",
  "properties": {
    "addr:full":"Noordbargerstr 26 Emmen Provincie Drenthe 7811 KG",
    "addr:housenumber":"26",
    "addr:postcode":"7811 kg",
    "addr:street":"Noordbargerstr;Provincie Drenthe",
    "iso:country":"NL",
    "sg:address":"Noordbargerstr 26",
    "sg:city":"Emmen",
    "sg:orig_category":"Cafetaria'S",
    "sg:phone":"+31 591 613 948",
    "sg:postcode":"7811 KG",
    "sg:province":"Provincie Drenthe",
    "wof:name":"Zandsteeg, De",
    "wof:placetype":"venue"
},
  "geometry": {"coordinates":[6.894109,52.776096],"type":"Point"}
}