{
  "type": "Feature",
  "properties": {
    "iso:country":"NL",
    "sg:address":"Dreef 144",
    "sg:city":"Deventer",
    "sg:orig_category":"Postkantoren",
    "sg:phone":"+31 570 640 116",
    "sg:postcode":"7414 EJ",
    "sg:province":"Overijssel",
    "sg:website":"http://www.postkantoor.nl",
    "wof:name":"Postkantoor",
    "wof:placetype":"venue"
},
  "geometry": {"coordinates":[6.151943,52.273735],"type":"Point"}
}