{
  "type": "Feature",
  "properties": {
    "iso:country":"NL",
    "sg:address":"T Bysterveld 17",
    "sg:city":"Helmond",
    "sg:orig_category":"Verzekeringen - Verzekeringskantoren",
    "sg:phone":"+31 492 578 242",
    "sg:postcode":"5701 GW",
    "sg:province":"Noord-Brabant",
    "wof:name":"Vcl",
    "wof:placetype":"venue"
},
  "geometry": {"coordinates":[5.673942,51.483356],"type":"Point"}
}