{
  "type": "Feature",
  "properties": {
    "iso:country":"NL",
    "sg:address":"Kerkstr 51",
    "sg:city":"Goirle",
    "sg:orig_category":"Kunststoffen - Fabrieken En Groothandel",
    "sg:phone":"+31 13 530 8530",
    "sg:postcode":"5051 LA",
    "sg:province":"Noord-Brabant",
    "sg:website":"http://www.vanbesouw.nl",
    "wof:name":"Besouw Bv, Van",
    "wof:placetype":"venue"
},
  "geometry": {"coordinates":[5.071473,51.519608],"type":"Point"}
}