{
  "type": "Feature",
  "properties": {
    "addr:full":"Dorpsstr 76 Krimpen Aan De Lek South Holland 2931 AG",
    "addr:housenumber":"76",
    "addr:postcode":"2931",
    "addr:street":"Dorpsstr",
    "iso:country":"NL",
    "sg:address":"Dorpsstr 76",
    "sg:city":"Krimpen Aan De Lek",
    "sg:orig_category":"Kabelexploitanten",
    "sg:phone":"+31 180 550 833",
    "sg:postcode":"2931 AG",
    "sg:province":"South Holland",
    "wof:name":"Kabelextra Bv",
    "wof:placetype":"venue"
},
  "geometry": {"coordinates":[4.6246709824,51.8916473389],"type":"Point"}
}