{
  "type": "Feature",
  "properties": {
    "addr:full":"Donkerestg 7 Zutphen Gelderland 7201 CR",
    "addr:housenumber":"7;7201",
    "addr:postcode":"cr",
    "addr:street":"Donkerestg;Gelderland",
    "iso:country":"NL",
    "sg:address":"Donkerestg 7",
    "sg:city":"Zutphen",
    "sg:orig_category":"Drogisterijen",
    "sg:phone":"+31 575 541 449",
    "sg:postcode":"7201 CR",
    "sg:province":"Gelderland",
    "wof:name":"Kruidvat",
    "wof:placetype":"venue"
},
  "geometry": {"coordinates":[6.201834,52.140656],"type":"Point"}
}