{
  "type": "Feature",
  "properties": {
    "addr:full":"Wg-Plein 702 Amsterdam North Holland 1054 SK",
    "addr:housenumber":"702",
    "addr:street":"Wg-Plein;1054",
    "iso:country":"NL",
    "sg:address":"Wg-Plein 702",
    "sg:city":"Amsterdam",
    "sg:orig_category":"Werving And Selectie Van Vast Personeel",
    "sg:phone":"+31 20 412 0667",
    "sg:postcode":"1054 SK",
    "sg:province":"North Holland",
    "wof:name":"Noorderlicht",
    "wof:placetype":"venue"
},
  "geometry": {"coordinates":[4.8720631599,52.3644866943],"type":"Point"}
}