{
  "type": "Feature",
  "properties": {
    "addr:full":"Couwenhoven 6113 Zeist Utrecht 3703 HH",
    "addr:housenumber":"6113",
    "addr:postcode":"3703 hh",
    "addr:street":"Couwenhoven",
    "iso:country":"NL",
    "sg:address":"Couwenhoven 6113",
    "sg:city":"Zeist",
    "sg:orig_category":"Verzekeringen",
    "sg:phone":"+31 30 695 8241",
    "sg:postcode":"3703 HH",
    "sg:province":"Utrecht",
    "wof:name":"Adviesbureau Zeijlemaker",
    "wof:placetype":"venue"
},
  "geometry": {"coordinates":[5.225887,52.077663],"type":"Point"}
}