{
  "type": "Feature",
  "properties": {
    "addr:full":"Eindhovenseweg 68 Valkenswaard Noord-Brabant 5554 AD",
    "addr:housenumber":"68",
    "addr:postcode":"5554 ad",
    "addr:street":"Eindhovenseweg",
    "iso:country":"NL",
    "sg:address":"Eindhovenseweg 68",
    "sg:city":"Valkenswaard",
    "sg:orig_category":"Huishoudapparatuur, Televisies And Radio'S",
    "sg:phone":"+31 40 204 4494",
    "sg:postcode":"5554 AD",
    "sg:province":"Noord-Brabant",
    "wof:name":"Maxwell Bv",
    "wof:placetype":"venue"
},
  "geometry": {"coordinates":[5.460357,51.354027],"type":"Point"}
}