{
  "type": "Feature",
  "properties": {
    "addr:full":"Ekkelwg 8 Hellendoorn Overijssel 7447 ST",
    "addr:housenumber":"8",
    "addr:postcode":"7447 st",
    "addr:street":"Ekkelwg",
    "iso:country":"NL",
    "sg:address":"Ekkelwg 8",
    "sg:city":"Hellendoorn",
    "sg:orig_category":"Honden- En Kattentrimsalons",
    "sg:phone":"+31 6 44216189",
    "sg:postcode":"7447 ST",
    "sg:province":"Overijssel",
    "wof:name":"Teugelhof, De",
    "wof:placetype":"venue"
},
  "geometry": {"coordinates":[6.494222,52.432182],"type":"Point"}
}