{
  "type": "Feature",
  "properties": {
    "addr:full":"Mgr Verhagenstr 53 Beek En Donk Noord-Brabant 5741 EH",
    "addr:housenumber":"53",
    "addr:postcode":"5741 eh",
    "addr:street":"Verhagenstr",
    "iso:country":"NL",
    "sg:address":"Mgr Verhagenstr 53",
    "sg:city":"Beek En Donk",
    "sg:orig_category":"Honden- En Kattentrimsalons",
    "sg:phone":"+31 492 465 997",
    "sg:postcode":"5741 EH",
    "sg:province":"Noord-Brabant",
    "wof:name":"Robbedoes",
    "wof:placetype":"venue"
},
  "geometry": {"coordinates":[5.634317,51.541225],"type":"Point"}
}