{
  "type": "Feature",
  "properties": {
    "addr:full":"Zwartemeerweg 24 Kraggenburg Flevoland 8317 PB",
    "addr:housenumber":"24",
    "addr:postcode":"8317 pb",
    "addr:street":"Zwartemeerweg;Flevoland",
    "iso:country":"NL",
    "sg:address":"Zwartemeerweg 24",
    "sg:city":"Kraggenburg",
    "sg:orig_category":"Geluidsopnamen",
    "sg:phone":"+31 527 252 351",
    "sg:postcode":"8317 PB",
    "sg:province":"Flevoland",
    "wof:name":"Eissens Muziekprodukties En Audiofacilit",
    "wof:placetype":"venue"
},
  "geometry": {"coordinates":[5.891211,52.633465],"type":"Point"}
}