{
  "type": "Feature",
  "properties": {
    "iso:country":"NL",
    "sg:address":"Schipholwg 109",
    "sg:city":"Leiden",
    "sg:orig_category":"Belastingconsulenten/ Belastingadviseurs",
    "sg:phone":"+31 71 362 0950",
    "sg:postcode":"2316 XC",
    "sg:province":"South Holland",
    "wof:name":"Paridon, Van",
    "wof:placetype":"venue"
},
  "geometry": {"coordinates":[4.488266,52.169487],"type":"Point"}
}