{
  "type": "Feature",
  "properties": {
    "iso:country":"NL",
    "sg:address":"Kanaalweg 17",
    "sg:city":"Utrecht",
    "sg:orig_category":"Diverse Opleidingen And Onderwijs",
    "sg:phone":"+31 30 298 5070",
    "sg:postcode":"3526 KL",
    "sg:province":"Utrecht",
    "wof:name":"Evoke Internet Advies & Training",
    "wof:placetype":"venue"
},
  "geometry": {"coordinates":[5.110386,52.068916],"type":"Point"}
}