{
  "type": "Feature",
  "properties": {
    "addr:full":"Boomstede 107 Maarssen Utrecht 3608 AE",
    "addr:housenumber":"107",
    "addr:postcode":"3608 ae",
    "addr:street":"Boomstede",
    "iso:country":"NL",
    "sg:address":"Boomstede 107",
    "sg:city":"Maarssen",
    "sg:orig_category":"Vertaalbureaus",
    "sg:phone":"+31 346 566 872",
    "sg:postcode":"3608 AE",
    "sg:province":"Utrecht",
    "wof:name":"Sluis, Y W F",
    "wof:placetype":"venue"
},
  "geometry": {"coordinates":[5.030721,52.122837],"type":"Point"}
}