{
  "type": "Feature",
  "properties": {
    "addr:full":"Paardenstr 21 Hilvarenbeek Noord-Brabant 5081 CG",
    "addr:housenumber":"21",
    "addr:postcode":"5081 cg",
    "addr:street":"Paardenstr",
    "iso:country":"NL",
    "sg:address":"Paardenstr 21",
    "sg:city":"Hilvarenbeek",
    "sg:orig_category":"Zonweringen",
    "sg:phone":"+31 13 505 4803",
    "sg:postcode":"5081 CG",
    "sg:province":"Noord-Brabant",
    "sg:website":"http://www.ambiancezonwering.nl",
    "wof:name":"Kolsters",
    "wof:placetype":"venue"
},
  "geometry": {"coordinates":[5.138012,51.486416],"type":"Point"}
}