{
  "type": "Feature",
  "properties": {
    "addr:full":"St Helenahof 28 Harkstede Groningen 9617 EJ",
    "addr:housenumber":"28",
    "addr:postcode":"9617 ej",
    "addr:street":"St Helenahof",
    "iso:country":"NL",
    "sg:address":"St Helenahof 28",
    "sg:city":"Harkstede",
    "sg:orig_category":"Autorijscholen",
    "sg:phone":"+31 50 404 1199",
    "sg:postcode":"9617 EJ",
    "sg:province":"Groningen",
    "wof:name":"Schomaker, Wim",
    "wof:placetype":"venue"
},
  "geometry": {"coordinates":[6.701764,53.208961],"type":"Point"}
}