{
  "type": "Feature",
  "properties": {
    "iso:country":"NL",
    "sg:address":"Finisterelaan 64",
    "sg:city":"Eindhoven",
    "sg:orig_category":"Loodgieterswerk, Verwarming And Sanitaire Installaties",
    "sg:phone":"+31 40 248 4711",
    "sg:postcode":"5627 TD",
    "sg:province":"Noord-Brabant",
    "wof:name":"S.C.V.S. (Schoonen Centrale Verwarm. Ser",
    "wof:placetype":"venue"
},
  "geometry": {"coordinates":[5.440356,51.491035],"type":"Point"}
}