{
  "type": "Feature",
  "properties": {
    "addr:full":"K Goog 2A Roelofarendsveen South Holland 2371 GJ",
    "addr:housenumber":"2a",
    "addr:postcode":"2371 gj",
    "addr:street":"K Goog",
    "iso:country":"NL",
    "sg:address":"K Goog 2A",
    "sg:city":"Roelofarendsveen",
    "sg:orig_category":"Metaalbewerking",
    "sg:phone":"+31 71 331 5082",
    "sg:postcode":"2371 GJ",
    "sg:province":"South Holland",
    "wof:name":"Hooymans Products",
    "wof:placetype":"venue"
},
  "geometry": {"coordinates":[4.63099,52.206722],"type":"Point"}
}