{
  "type": "Feature",
  "properties": {
    "iso:country":"NL",
    "sg:address":"Prof. Oppenheimstraat 29",
    "sg:city":"Veghel",
    "sg:orig_category":"Schilderwerk",
    "sg:phone":"+31 413 363 970",
    "sg:postcode":"5463 ED",
    "sg:province":"North Brabant",
    "wof:name":"Swinkels Schildersbedrijf",
    "wof:placetype":"venue"
},
  "geometry": {"coordinates":[5.554051,51.613811],"type":"Point"}
}