{
  "type": "Feature",
  "properties": {
    "addr:full":"2E Nieuwstadsweg 2 Wierden Overijssel 7642 NH",
    "addr:housenumber":"2",
    "addr:postcode":"7642 nh",
    "addr:street":"2E Nieuwstadsweg",
    "iso:country":"NL",
    "sg:address":"2E Nieuwstadsweg 2",
    "sg:city":"Wierden",
    "sg:orig_category":"Levende Dieren Gh",
    "sg:phone":"+31 548 520 332",
    "sg:postcode":"7642 NH",
    "sg:province":"Overijssel",
    "wof:name":"H.J. Weenk",
    "wof:placetype":"venue"
},
  "geometry": {"coordinates":[6.559431,52.33218],"type":"Point"}
}