{
  "type": "Feature",
  "properties": {
    "addr:full":"Rijksweg Zuid 7C Swalmen Limburg 6071 HT",
    "addr:housenumber":"7c",
    "addr:postcode":"6071 ht",
    "addr:street":"Rijksweg Zuid",
    "iso:country":"NL",
    "sg:address":"Rijksweg Zuid 7C",
    "sg:city":"Swalmen",
    "sg:orig_category":"Meubelzaken, Woning- And Keukeninrichting",
    "sg:phone":"+31 475 501 819",
    "sg:postcode":"6071 HT",
    "sg:province":"Limburg",
    "wof:name":"Het Beddenhuis",
    "wof:placetype":"venue"
},
  "geometry": {"coordinates":[6.035754,51.229542],"type":"Point"}
}