{
  "type": "Feature",
  "properties": {
    "addr:full":"V Sysenstr 67 Groningen Groningen 9724 NM",
    "addr:housenumber":"67",
    "addr:postcode":"9724",
    "iso:country":"NL",
    "sg:address":"V Sysenstr 67",
    "sg:city":"Groningen",
    "sg:orig_category":"Vertalers",
    "sg:phone":"+31 50 313 3770",
    "sg:postcode":"9724 NM",
    "sg:province":"Groningen",
    "wof:name":"Frappa",
    "wof:placetype":"venue"
},
  "geometry": {"coordinates":[6.57675,53.211639],"type":"Point"}
}