{
  "type": "Feature",
  "properties": {
    "addr:full":"Over De Vesten 3 Schiedam Zuid-Holland 3116 AD",
    "addr:housenumber":"3",
    "addr:postcode":"3116 ad",
    "addr:street":"Over De Vesten",
    "iso:country":"NL",
    "sg:address":"Over De Vesten 3",
    "sg:city":"Schiedam",
    "sg:orig_category":"Hypotheken",
    "sg:phone":"+31 10 273 0777",
    "sg:postcode":"3116 AD",
    "sg:province":"Zuid-Holland",
    "wof:name":"Schiedam",
    "wof:placetype":"venue"
},
  "geometry": {"coordinates":[4.398901,51.91214],"type":"Point"}
}