{
  "type": "Feature",
  "properties": {
    "addr:full":"Groenewg 12 Schiedam Zuid-Holland 3124 KA",
    "addr:housenumber":"12",
    "addr:postcode":"3124 ka",
    "addr:street":"Groenewg",
    "iso:country":"NL",
    "sg:address":"Groenewg 12",
    "sg:city":"Schiedam",
    "sg:orig_category":"Autoschade- Herstelbedrijven",
    "sg:phone":"+31 10 471 5180",
    "sg:postcode":"3124 KA",
    "sg:province":"Zuid-Holland",
    "wof:name":"Driel, Van",
    "wof:placetype":"venue"
},
  "geometry": {"coordinates":[4.384357,51.950729],"type":"Point"}
}