{
  "type": "Feature",
  "properties": {
    "addr:full":"Kerkplein 5 Oeffelt North Brabant 5441 BE",
    "addr:housenumber":"5",
    "addr:postcode":"5441",
    "addr:street":"Kerkplein",
    "iso:country":"NL",
    "sg:address":"Kerkplein 5",
    "sg:city":"Oeffelt",
    "sg:orig_category":"Diverse Artikelen Fab",
    "sg:phone":"+31 485 363 008",
    "sg:postcode":"5441 BE",
    "sg:province":"North Brabant",
    "wof:name":"Mies Metselaar",
    "wof:placetype":"venue"
},
  "geometry": {"coordinates":[5.937263,51.699242],"type":"Point"}
}