{
  "type": "Feature",
  "properties": {
    "addr:full":"Burg Zaneveldstraat 182 Maassluis South Holland 3145 RK",
    "addr:housenumber":"182",
    "addr:postcode":"3145 rk",
    "addr:street":"Burg Zaneveldstraat",
    "iso:country":"NL",
    "sg:address":"Burg Zaneveldstraat 182",
    "sg:city":"Maassluis",
    "sg:orig_category":"Boekhouders",
    "sg:phone":"+31 10 591 6040",
    "sg:postcode":"3145 RK",
    "sg:province":"South Holland",
    "wof:name":"Adviesburo Mazo",
    "wof:placetype":"venue"
},
  "geometry": {"coordinates":[4.232195,51.937626],"type":"Point"}
}