{
  "type": "Feature",
  "properties": {
    "iso:country":"NL",
    "sg:address":"Sebastiaansdoelen 4",
    "sg:city":"Leiden",
    "sg:orig_category":"Vertaal- And Tolkenbureaus",
    "sg:phone":"+31 71 512 4978",
    "sg:postcode":"2311 WN",
    "sg:province":"Zuid-Holland",
    "wof:name":"Vertaalburo Arbi",
    "wof:placetype":"venue"
},
  "geometry": {"coordinates":[4.49463,52.154572],"type":"Point"}
}