{
  "type": "Feature",
  "properties": {
    "addr:full":"Meerheide 64 Eersel Noord-Brabant 5521 DZ",
    "addr:housenumber":"64",
    "addr:postcode":"5521 dz",
    "addr:street":"Meerheide",
    "iso:country":"NL",
    "sg:address":"Meerheide 64",
    "sg:city":"Eersel",
    "sg:orig_category":"Waterkoelers En Drinkwaterinstallaties",
    "sg:phone":"+31 497 552 080",
    "sg:postcode":"5521 DZ",
    "sg:province":"Noord-Brabant",
    "sg:website":"http://www.mardeau.com",
    "wof:name":"Mardeau-Sun Spring",
    "wof:placetype":"venue"
},
  "geometry": {"coordinates":[5.3157348633,51.3747596741],"type":"Point"}
}