{
  "type": "Feature",
  "properties": {
    "addr:full":"Burgemeester Wijnenstr 12 Asten North Brabant 5721 AJ",
    "addr:housenumber":"12",
    "addr:postcode":"5721 aj",
    "addr:street":"Burgemeester Wijnenstr",
    "iso:country":"NL",
    "sg:address":"Burgemeester Wijnenstr 12",
    "sg:city":"Asten",
    "sg:orig_category":"Wasserettes And Stomerijen",
    "sg:phone":"+31 493 691 873",
    "sg:postcode":"5721 AJ",
    "sg:province":"North Brabant",
    "wof:name":"Peters Stomerij",
    "wof:placetype":"venue"
},
  "geometry": {"coordinates":[5.7450828552,51.4042778015],"type":"Point"}
}