{
  "type": "Feature",
  "properties": {
    "addr:full":"Zwaan 6 Zoeterwoude Zuid-Holland 2381 KH",
    "addr:housenumber":"6",
    "addr:postcode":"2381 kh",
    "addr:street":"Zwaan",
    "iso:country":"NL",
    "sg:address":"Zwaan 6",
    "sg:city":"Zoeterwoude",
    "sg:orig_category":"Verpakkingsmachines Fab",
    "sg:phone":"+31 71 580 2986",
    "sg:postcode":"2381 KH",
    "sg:province":"Zuid-Holland",
    "wof:name":"Loonbedrijf Hoekstra",
    "wof:placetype":"venue"
},
  "geometry": {"coordinates":[4.492582,52.121525],"type":"Point"}
}