{
  "type": "Feature",
  "properties": {
    "iso:country":"NL",
    "sg:address":"Hoofdstr 110",
    "sg:city":"Bergambacht",
    "sg:orig_category":"Postkantoren",
    "sg:phone":"+31 182 354 588",
    "sg:postcode":"2861 AT",
    "sg:province":"Zuid-Holland",
    "sg:website":"http://www.postkantoor.nl",
    "wof:name":"Postkantoor",
    "wof:placetype":"venue"
},
  "geometry": {"coordinates":[4.782899,51.936428],"type":"Point"}
}