{
  "type": "Feature",
  "properties": {
    "addr:full":"Dunckelln 12 Sittard Limburg 6132 BL",
    "addr:housenumber":"12",
    "addr:postcode":"6132 bl",
    "addr:street":"Dunckelln",
    "iso:country":"NL",
    "sg:address":"Dunckelln 12",
    "sg:city":"Sittard",
    "sg:orig_category":"Adviesbureaus Bouwkunde",
    "sg:phone":"+31 46 451 1397",
    "sg:postcode":"6132 BL",
    "sg:province":"Limburg",
    "wof:name":"Paulissen",
    "wof:placetype":"venue"
},
  "geometry": {"coordinates":[5.883671,50.987377],"type":"Point"}
}