{
  "type": "Feature",
  "properties": {
    "addr:full":"Dalweg 16-18 Rotterdam Zuid-Holland 3075 LR",
    "addr:housenumber":"16-18",
    "addr:postcode":"3075 lr",
    "addr:street":"Dalweg",
    "iso:country":"NL",
    "sg:address":"Dalweg 16-18",
    "sg:city":"Rotterdam",
    "sg:orig_category":"Fietshandelaren",
    "sg:phone":"+31 10 419 2240",
    "sg:postcode":"3075 LR",
    "sg:province":"Zuid-Holland",
    "wof:name":"Anton'S Rijwielcorner",
    "wof:placetype":"venue"
},
  "geometry": {"coordinates":[4.517039,51.88966],"type":"Point"}
}