{
  "type": "Feature",
  "properties": {
    "addr:full":"Hollandseln 47 Stadskanaal Groningen 9501 BB",
    "addr:housenumber":"47",
    "addr:postcode":"9501 bb",
    "addr:street":"Hollandseln",
    "iso:country":"NL",
    "sg:address":"Hollandseln 47",
    "sg:city":"Stadskanaal",
    "sg:orig_category":"Gordijnenateliers",
    "sg:phone":"+31 599 620 531",
    "sg:postcode":"9501 BB",
    "sg:province":"Groningen",
    "wof:name":"Naaibox, De",
    "wof:placetype":"venue"
},
  "geometry": {"coordinates":[6.956183,52.992943],"type":"Point"}
}