{
  "type": "Feature",
  "properties": {
    "iso:country":"NL",
    "sg:address":"Almeloplein 44",
    "sg:city":"'S Gravenhage",
    "sg:classifiers":[
        {
            "category":"Fast Food",
            "type":"Food & Drink"
        }
    ],
    "sg:phone":"+31 70 366 2283",
    "sg:postcode":"2533 AC",
    "sg:province":"South Holland",
    "sg:tags":[
        "afhaal",
        "restaurant"
    ],
    "wof:name":"Chin Ind Rest Kam Fat",
    "wof:placetype":"venue"
},
  "geometry": {"coordinates":[4.27476,52.05595],"type":"Point"}
}