{
  "type": "Feature",
  "properties": {
    "addr:full":"Amstelkd 12-Iii Amsterdam North Holland 1078 AB",
    "addr:housenumber":"12-iii",
    "addr:postcode":"1078 ab",
    "addr:street":"Amstelkd",
    "iso:country":"NL",
    "sg:address":"Amstelkd 12-Iii",
    "sg:city":"Amsterdam",
    "sg:orig_category":"Beeldende Kunstenaars",
    "sg:phone":"+31 20 679 1621",
    "sg:postcode":"1078 AB",
    "sg:province":"North Holland",
    "sg:website":"http://www.mea.nl",
    "wof:name":"Mea Producties",
    "wof:placetype":"venue"
},
  "geometry": {"coordinates":[4.89178,52.34341],"type":"Point"}
}