{
  "type": "Feature",
  "properties": {
    "iso:country":"NL",
    "sg:address":"Vlietlaan 35/B",
    "sg:city":"Rotterdam",
    "sg:orig_category":"Partycatering And -Organisatie",
    "sg:phone":"+31 10 452 8442",
    "sg:postcode":"3061 DT",
    "sg:province":"Zuid-Holland",
    "wof:name":"De Lunchpauze",
    "wof:placetype":"venue"
},
  "geometry": {"coordinates":[4.501943,51.929501],"type":"Point"}
}