{
  "type": "Feature",
  "properties": {
    "addr:full":"Kerklaan 18 Hoogland Utrecht 3828 EB",
    "addr:housenumber":"18",
    "addr:postcode":"3828 eb",
    "addr:street":"Kerklaan",
    "iso:country":"NL",
    "sg:address":"Kerklaan 18",
    "sg:city":"Hoogland",
    "sg:orig_category":"Meubelzaken, Woning- And Keukeninrichting",
    "sg:phone":"+31 33 480 1379",
    "sg:postcode":"3828 EB",
    "sg:province":"Utrecht",
    "wof:name":"Van Lunteren Voor Woningen En Projecten Bv",
    "wof:placetype":"venue"
},
  "geometry": {"coordinates":[5.382466,52.190254],"type":"Point"}
}