{
  "type": "Feature",
  "properties": {
    "addr:full":"Nassauln 1B Bussum Noord-Holland 1404 CL",
    "addr:housenumber":"1b",
    "addr:postcode":"1404",
    "addr:street":"Nassauln",
    "iso:country":"NL",
    "sg:address":"Nassauln 1B",
    "sg:city":"Bussum",
    "sg:orig_category":"Schoenen",
    "sg:phone":"+31 35 691 0751",
    "sg:postcode":"1404 CL",
    "sg:province":"Noord-Holland",
    "wof:name":"Kort Bv",
    "wof:placetype":"venue"
},
  "geometry": {"coordinates":[5.162605,52.276829],"type":"Point"}
}