{
  "type": "Feature",
  "properties": {
    "addr:full":"Voorweg 1 Schoorl Noord-Holland 1871 CK",
    "addr:housenumber":"1",
    "addr:postcode":"1871 ck",
    "addr:street":"Voorweg",
    "iso:country":"NL",
    "sg:address":"Voorweg 1",
    "sg:city":"Schoorl",
    "sg:orig_category":"Verzekeringen",
    "sg:phone":"+31 72 509 1785",
    "sg:postcode":"1871 CK",
    "sg:province":"Noord-Holland",
    "wof:name":"Ringnalda Lease",
    "wof:placetype":"venue"
},
  "geometry": {"coordinates":[4.704258,52.704681],"type":"Point"}
}