{
  "type": "Feature",
  "properties": {
    "iso:country":"NL",
    "sg:address":"Borselestr 61",
    "sg:city":"Tilburg",
    "sg:orig_category":"Modevakscholen",
    "sg:phone":"+31 13 570 3177",
    "sg:postcode":"5043 AP",
    "sg:province":"Noord-Brabant",
    "wof:name":"Schoot, R Van Der",
    "wof:placetype":"venue"
},
  "geometry": {"coordinates":[5.014268,51.584698],"type":"Point"}
}