{
  "type": "Feature",
  "properties": {
    "addr:full":"H De Manstr 2 Vianen Zh Utrecht 4132 XS",
    "addr:housenumber":"2",
    "addr:postcode":"zh;4132 xs",
    "iso:country":"NL",
    "sg:address":"H De Manstr 2",
    "sg:city":"Vianen Zh",
    "sg:classifiers":[
        {
            "category":"Professional",
            "subcategory":"Management & Consulting",
            "type":"Services"
        }
    ],
    "sg:phone":"+31 347 375 350",
    "sg:postcode":"4132 XS",
    "sg:province":"Utrecht",
    "sg:tags":[
        "relation",
        "adviesbureaus",
        "public"
    ],
    "wof:name":"Botek",
    "wof:placetype":"venue"
},
  "geometry": {"coordinates":[5.096152,51.992416],"type":"Point"}
}