{
  "type": "Feature",
  "properties": {
    "iso:country":"NL",
    "sg:address":"Sperwerstraat 22",
    "sg:city":"Zwijndrecht",
    "sg:orig_category":"Boekhouders",
    "sg:phone":"+31 78 612 5871",
    "sg:postcode":"3334 AL",
    "sg:province":"Zuid-Holland",
    "wof:name":"Administratiekantoor Lamet Bijkerk",
    "wof:placetype":"venue"
},
  "geometry": {"coordinates":[4.619576,51.813553],"type":"Point"}
}