{
  "type": "Feature",
  "properties": {
    "addr:full":"Dorpsstr 36 De Wyk Drenthe 7957 AV",
    "addr:housenumber":"36",
    "addr:postcode":"7957 av",
    "addr:street":"Dorpsstr;De Wyk",
    "iso:country":"NL",
    "sg:address":"Dorpsstr 36",
    "sg:city":"De Wyk",
    "sg:orig_category":"Kappers",
    "sg:phone":"+31 522 443 400",
    "sg:postcode":"7957 AV",
    "sg:province":"Drenthe",
    "wof:name":"Bianca",
    "wof:placetype":"venue"
},
  "geometry": {"coordinates":[6.2845768929,52.6728057861],"type":"Point"}
}