{
  "type": "Feature",
  "properties": {
    "addr:full":"Graafs Megenstr 12 Oisterwyk Noord-Brabant 5061 XS",
    "addr:housenumber":"12",
    "addr:postcode":"5061 xs",
    "addr:street":"Oisterwyk",
    "iso:country":"NL",
    "sg:address":"Graafs Megenstr 12",
    "sg:city":"Oisterwyk",
    "sg:classifiers":[
        {
            "category":"Food & Beverages",
            "subcategory":"Bakery",
            "type":"Retail Goods"
        }
    ],
    "sg:phone":"+31 13 528 7080",
    "sg:postcode":"5061 XS",
    "sg:province":"Noord-Brabant",
    "sg:tags":[
        "brood",
        "en",
        "banket"
    ],
    "wof:name":"Koppens, Astrid",
    "wof:placetype":"venue"
},
  "geometry": {"coordinates":[5.1821,51.57653],"type":"Point"}
}