{
  "type": "Feature",
  "properties": {
    "addr:full":"Edisonstr 33 Reeuwyk Zuid-Holland 2811 EM",
    "addr:housenumber":"33",
    "addr:postcode":"2811 em",
    "addr:street":"Edisonstr",
    "iso:country":"NL",
    "sg:address":"Edisonstr 33",
    "sg:city":"Reeuwyk",
    "sg:orig_category":"Accountants - Administratie- Consulenten En -Kantoren",
    "sg:phone":"+31 182 396 500",
    "sg:postcode":"2811 EM",
    "sg:province":"Zuid-Holland",
    "wof:name":"Bode",
    "wof:placetype":"venue"
},
  "geometry": {"coordinates":[4.71765,52.039661],"type":"Point"}
}