{
  "type": "Feature",
  "properties": {
    "addr:full":"De Krom 6 Wilnis Utrecht 3648 CT",
    "addr:housenumber":"6",
    "addr:postcode":"3648 ct",
    "addr:street":"De Krom",
    "iso:country":"NL",
    "sg:address":"De Krom 6",
    "sg:city":"Wilnis",
    "sg:orig_category":"Adviesbureaus Bedrijfsorganisatie",
    "sg:phone":"+31 297 272 655",
    "sg:postcode":"3648 CT",
    "sg:province":"Utrecht",
    "wof:name":"Hoefs",
    "wof:placetype":"venue"
},
  "geometry": {"coordinates":[4.893233,52.194855],"type":"Point"}
}