{
  "type": "Feature",
  "properties": {
    "iso:country":"NL",
    "sg:address":"Graaf Florisweg 126",
    "sg:city":"Gouda",
    "sg:orig_category":"Begraafplaatsen",
    "sg:phone":"+31 182 514 497",
    "sg:postcode":"2805 AP",
    "sg:province":"South Holland",
    "wof:name":"Rk",
    "wof:placetype":"venue"
},
  "geometry": {"coordinates":[4.719005,52.018303],"type":"Point"}
}