{
  "type": "Feature",
  "properties": {
    "addr:full":"Molendijk 12 'S Heerenhoek Zeeland 4453 AE",
    "addr:housenumber":"12",
    "addr:postcode":"4453 ae",
    "addr:street":"Molendijk;' S Heerenhoek Zeeland",
    "iso:country":"NL",
    "sg:address":"Molendijk 12",
    "sg:city":"'S Heerenhoek",
    "sg:orig_category":"Kappers",
    "sg:phone":"+31 113 351 764",
    "sg:postcode":"4453 AE",
    "sg:province":"Zeeland",
    "wof:name":"Herenkapsalon Rentmeester",
    "wof:placetype":"venue"
},
  "geometry": {"coordinates":[3.7683179379,51.4545516968],"type":"Point"}
}