{
  "type": "Feature",
  "properties": {
    "addr:full":"Goeseelsstraat 12 Breda North Brabant 4817 MV",
    "addr:housenumber":"12",
    "addr:postcode":"4817 mv",
    "addr:street":"Goeseelsstraat",
    "iso:country":"NL",
    "sg:address":"Goeseelsstraat 12",
    "sg:city":"Breda",
    "sg:orig_category":"Loodgieterswerk, Verwarming And Sanitaire Installaties",
    "sg:phone":"+31 76 571 4606",
    "sg:postcode":"4817 MV",
    "sg:province":"North Brabant",
    "wof:name":"Tapijt Advies Hoppenbrouwers",
    "wof:placetype":"venue"
},
  "geometry": {"coordinates":[4.797283,51.594025],"type":"Point"}
}