{
  "type": "Feature",
  "properties": {
    "addr:full":"Boylerwg 97 Boyl Friesland 8392 ND",
    "addr:housenumber":"97",
    "addr:postcode":"8392 nd",
    "addr:street":"Boylerwg",
    "iso:country":"NL",
    "sg:address":"Boylerwg 97",
    "sg:city":"Boyl",
    "sg:classifiers":[
        {
            "category":"Retail",
            "subcategory":"Auto Repair",
            "type":"Services"
        }
    ],
    "sg:phone":"+31 561 421 420",
    "sg:postcode":"8392 ND",
    "sg:province":"Friesland",
    "sg:tags":[
        "garage"
    ],
    "wof:name":"Wever Vof, A",
    "wof:placetype":"venue"
},
  "geometry": {"coordinates":[-90.72695899999999,33.703896],"type":"Point"}
}