{
  "type": "Feature",
  "properties": {
    "iso:country":"NL",
    "sg:address":"Mr Troelstrawei 31",
    "sg:city":"Grouw",
    "sg:orig_category":"Sportverenigingen En Ontspannings- Verenigingen",
    "sg:phone":"+31 566 623 733",
    "sg:postcode":"9001 CS",
    "sg:province":"Friesland",
    "wof:name":"Marf?Gels Korfbalver",
    "wof:placetype":"venue"
},
  "geometry": {"coordinates":[-10.95086,21.006809],"type":"Point"}
}