{
  "type": "Feature",
  "properties": {
    "addr:full":"Elzenoordln 1 Vrouwenpolder Zeeland 4354 AG",
    "addr:housenumber":"1",
    "addr:postcode":"4354",
    "addr:street":"Elzenoordln",
    "iso:country":"NL",
    "sg:address":"Elzenoordln 1",
    "sg:city":"Vrouwenpolder",
    "sg:orig_category":"Kappers",
    "sg:phone":"+31 118 593 131",
    "sg:postcode":"4354 AG",
    "sg:province":"Zeeland",
    "wof:name":"Knip Inn",
    "wof:placetype":"venue"
},
  "geometry": {"coordinates":[3.61476,51.576962],"type":"Point"}
}