{
  "type": "Feature",
  "properties": {
    "addr:full":"Schoolstraat 2 Bedum Groningen 9781 JN",
    "addr:housenumber":"2",
    "addr:postcode":"9781 jn",
    "addr:street":"Schoolstraat",
    "iso:country":"NL",
    "sg:address":"Schoolstraat 2",
    "sg:city":"Bedum",
    "sg:orig_category":"Verlichting And Huishoudartikelen",
    "sg:phone":"+31 50 301 5722",
    "sg:postcode":"9781 JN",
    "sg:province":"Groningen",
    "wof:name":"Novalux",
    "wof:placetype":"venue"
},
  "geometry": {"coordinates":[6.601334,53.300728],"type":"Point"}
}