{
  "type": "Feature",
  "properties": {
    "iso:country":"NL",
    "sg:address":"Venneperhof 5A",
    "sg:city":"Nieuw Vennep",
    "sg:orig_category":"Meubelen",
    "sg:phone":"+31 252 621 715",
    "sg:postcode":"2151 AW",
    "sg:province":"Noord-Holland",
    "wof:name":"Mardi",
    "wof:placetype":"venue"
},
  "geometry": {"coordinates":[4.631268,52.264061],"type":"Point"}
}