{
  "type": "Feature",
  "properties": {
    "iso:country":"NL",
    "sg:address":"Grotestr 15",
    "sg:city":"Sambeek",
    "sg:orig_category":"Elektrotechnische Installatiebureaus",
    "sg:phone":"+31 485 576 141",
    "sg:postcode":"5836 AA",
    "sg:province":"North Brabant",
    "wof:name":"Berkvens, Electro",
    "wof:placetype":"venue"
},
  "geometry": {"coordinates":[5.962429,51.63966],"type":"Point"}
}