{
  "type": "Feature",
  "properties": {
    "addr:full":"Van Der Heijdenlaan 90 Zeist Utrecht 3705 EJ",
    "addr:housenumber":"90",
    "addr:postcode":"3705 ej",
    "addr:street":"Van Der Heijdenlaan",
    "iso:country":"NL",
    "sg:address":"Van Der Heijdenlaan 90",
    "sg:city":"Zeist",
    "sg:orig_category":"Kinderopvang Behalve Thuis",
    "sg:phone":"+31 30 696 3036",
    "sg:postcode":"3705 EJ",
    "sg:province":"Utrecht",
    "wof:name":"Stichting Kinderopvang Zeist",
    "wof:placetype":"venue"
},
  "geometry": {"coordinates":[5.241842,52.096794],"type":"Point"}
}