{
  "type": "Feature",
  "properties": {
    "addr:full":"Hoofdstraat 166 Epe Gelderland 8162 AR",
    "addr:housenumber":"166",
    "addr:postcode":"8162",
    "addr:street":"Hoofdstraat;Gelderland",
    "iso:country":"NL",
    "sg:address":"Hoofdstraat 166",
    "sg:city":"Epe",
    "sg:orig_category":"Werving And Selectie Van Tijdelijk Personeel And Uitzendkantoren",
    "sg:phone":"+31 578 569 950",
    "sg:postcode":"8162 AR",
    "sg:province":"Gelderland",
    "wof:name":"Randstad Uitzendbureau Bv",
    "wof:placetype":"venue"
},
  "geometry": {"coordinates":[-88.124168396,32.6893348694],"type":"Point"}
}