{
  "type": "Feature",
  "properties": {
    "addr:full":"Oude Norgerweg 6 Zeijen Provincie Drenthe 9491 AK",
    "addr:housenumber":"6",
    "addr:postcode":"9491 ak",
    "addr:street":"Oude Norgerweg;Provincie Drenthe",
    "iso:country":"NL",
    "sg:address":"Oude Norgerweg 6",
    "sg:city":"Zeijen",
    "sg:orig_category":"Goederenvervoer Over De Weg",
    "sg:phone":"+31 592 291 241",
    "sg:postcode":"9491 AK",
    "sg:province":"Provincie Drenthe",
    "wof:name":"Transportbedrijf Ganzeveld",
    "wof:placetype":"venue"
},
  "geometry": {"coordinates":[6.5437,53.050289],"type":"Point"}
}