{
  "type": "Feature",
  "properties": {
    "addr:full":"Aart Van Der Leeuwlaan 4 Delft Zuid-Holland 2624 LD",
    "addr:housenumber":"4",
    "addr:postcode":"2624 ld",
    "addr:street":"Aart Van Der Leeuwlaan",
    "iso:country":"NL",
    "sg:address":"Aart Van Der Leeuwlaan 4",
    "sg:city":"Delft",
    "sg:orig_category":"Kinderopvang Behalve Thuis",
    "sg:phone":"+31 15 261 1672",
    "sg:postcode":"2624 LD",
    "sg:province":"Zuid-Holland",
    "wof:name":"Berend Botje Octopus Peuterspeelzaal",
    "wof:placetype":"venue"
},
  "geometry": {"coordinates":[4.349834,51.996826],"type":"Point"}
}