{
  "type": "Feature",
  "properties": {
    "iso:country":"NL",
    "sg:address":"Hargaln 2",
    "sg:city":"Schiedam",
    "sg:classifiers":[
        {
            "category":"Travel",
            "subcategory":"Hotels & Motels",
            "type":"Entertainment"
        }
    ],
    "sg:phone":"+31 10 471 3322",
    "sg:postcode":"3118 JA",
    "sg:province":"Zuid-Holland",
    "sg:website":"http://www.novotel.nl",
    "wof:name":"Novotel",
    "wof:placetype":"venue"
},
  "geometry": {"coordinates":[4.39816,51.918472],"type":"Point"}
}