{
  "type": "Feature",
  "properties": {
    "addr:full":"Prinses Irenelaan 2 Uitgeest Noord-Holland 1911 HW",
    "addr:housenumber":"2",
    "addr:postcode":"1911 hw",
    "addr:street":"Prinses Irenelaan",
    "iso:country":"NL",
    "sg:address":"Prinses Irenelaan 2",
    "sg:city":"Uitgeest",
    "sg:orig_category":"Apothekers",
    "sg:phone":"+31 251 314 170",
    "sg:postcode":"1911 HW",
    "sg:province":"Noord-Holland",
    "wof:name":"Apotheek Scharlei",
    "wof:placetype":"venue"
},
  "geometry": {"coordinates":[4.709765,52.529552],"type":"Point"}
}