{
  "type": "Feature",
  "properties": {
    "addr:full":"De Eglantier 219 Apeldoorn Gelderland 7329 DG",
    "addr:housenumber":"219",
    "addr:postcode":"7329 dg",
    "addr:street":"De Eglantier;Gelderland",
    "iso:country":"NL",
    "sg:address":"De Eglantier 219",
    "sg:city":"Apeldoorn",
    "sg:orig_category":"Schoenen",
    "sg:phone":"+31 55 541 5487",
    "sg:postcode":"7329 DG",
    "sg:province":"Gelderland",
    "wof:name":"Jansen & Jansen",
    "wof:placetype":"venue"
},
  "geometry": {"coordinates":[6.00623,52.195728],"type":"Point"}
}