{
  "type": "Feature",
  "properties": {
    "addr:full":"Kamperweg 10 Heerde Gelderland 8181 CM",
    "addr:housenumber":"10",
    "addr:postcode":"8181 cm",
    "addr:street":"Kamperweg;Gelderland",
    "iso:country":"NL",
    "sg:address":"Kamperweg 10",
    "sg:city":"Heerde",
    "sg:orig_category":"Architecten",
    "sg:phone":"+31 578 691 720",
    "sg:postcode":"8181 CM",
    "sg:province":"Gelderland",
    "wof:name":"Buro Kranendonk",
    "wof:placetype":"venue"
},
  "geometry": {"coordinates":[6.037207,52.391254],"type":"Point"}
}