{
  "type": "Feature",
  "properties": {
    "iso:country":"NL",
    "sg:address":"Smetanalaan 32",
    "sg:city":"Schiedam",
    "sg:orig_category":"Paramedische Behandelingen",
    "sg:phone":"+31 10 470 3329",
    "sg:postcode":"3122 HR",
    "sg:province":"Zuid-Holland",
    "wof:name":"Logopedie J.A.G. Dijkstra-Hagendijk",
    "wof:placetype":"venue"
},
  "geometry": {"coordinates":[4.365179,51.935051],"type":"Point"}
}