{
  "type": "Feature",
  "properties": {
    "addr:full":"Afrikastr 1 Ittervoort Limburg 6014 CG",
    "addr:housenumber":"1",
    "addr:postcode":"6014 cg",
    "addr:street":"Afrikastr",
    "iso:country":"NL",
    "sg:address":"Afrikastr 1",
    "sg:city":"Ittervoort",
    "sg:orig_category":"Heftrucks",
    "sg:phone":"+31 475 565 900",
    "sg:postcode":"6014 CG",
    "sg:province":"Limburg",
    "sg:website":"http://www.lima-ittervoort.nl",
    "wof:name":"Lima Heftruck Service Bv",
    "wof:placetype":"venue"
},
  "geometry": {"coordinates":[5.838472,51.178867],"type":"Point"}
}