{
  "type": "Feature",
  "properties": {
    "addr:full":"Nyhoffpln 20 Schiedam Zuid-Holland 3123 NH",
    "addr:housenumber":"20",
    "addr:postcode":"3123 nh",
    "addr:street":"Nyhoffpln",
    "iso:country":"NL",
    "sg:address":"Nyhoffpln 20",
    "sg:city":"Schiedam",
    "sg:orig_category":"Peuterspeelzalen",
    "sg:phone":"+31 10 471 7191",
    "sg:postcode":"3123 NH",
    "sg:province":"Zuid-Holland",
    "wof:name":"Pippeloentje",
    "wof:placetype":"venue"
},
  "geometry": {"coordinates":[4.36915,51.93848],"type":"Point"}
}