{
  "type": "Feature",
  "properties": {
    "addr:full":"Treubwg 35 Diemen Noord-Holland 1112 BA",
    "addr:housenumber":"35",
    "addr:postcode":"1112 ba",
    "addr:street":"Treubwg",
    "iso:country":"NL",
    "sg:address":"Treubwg 35",
    "sg:city":"Diemen",
    "sg:orig_category":"Horeca-Inrichtingen En -Uitrustingen",
    "sg:phone":"+31 20 639 0922",
    "sg:postcode":"1112 BA",
    "sg:province":"Noord-Holland",
    "sg:website":"http://www.tapgroep.nl",
    "wof:name":"Tapgroep Nederland",
    "wof:placetype":"venue"
},
  "geometry": {"coordinates":[4.972482,52.331139],"type":"Point"}
}