{
  "type": "Feature",
  "properties": {
    "iso:country":"NL",
    "sg:address":"Boerhaavelaan 85",
    "sg:city":"Hengelo Ov",
    "sg:orig_category":"Bejaardeninstellingen And Serviceflats",
    "sg:phone":"+31 74 245 3453",
    "sg:postcode":"7555 BK",
    "sg:province":"Overijssel",
    "wof:name":"Dr. P.C. Borsthuis",
    "wof:placetype":"venue"
},
  "geometry": {"coordinates":[6.767474,52.264904],"type":"Point"}
}