{
  "type": "Feature",
  "properties": {
    "addr:full":"Boerhaavelaan 85 Hengelo Ov Overijssel 7555 BK",
    "addr:housenumber":"85",
    "addr:postcode":"7555 bk",
    "addr:street":"Boerhaavelaan;Ov",
    "iso:country":"NL",
    "sg:address":"Boerhaavelaan 85",
    "sg:city":"Hengelo Ov",
    "sg:orig_category":"Bejaardeninstellingen And Serviceflats",
    "sg:phone":"+31 74 245 3453",
    "sg:postcode":"7555 BK",
    "sg:province":"Overijssel",
    "wof:name":"Dr. P.C. Borsthuis",
    "wof:placetype":"venue"
},
  "geometry": {"coordinates":[6.767474,52.264904],"type":"Point"}
}