{
  "type": "Feature",
  "properties": {
    "iso:country":"NL",
    "sg:address":"Abtswg 24 Fil",
    "sg:city":"Rotterdam",
    "sg:classifiers":[
        {
            "category":"Food & Beverages",
            "subcategory":"Fruits & Vegetables",
            "type":"Retail Goods"
        }
    ],
    "sg:phone":"+31 10 437 8500",
    "sg:postcode":"3042 GD",
    "sg:province":"South Holland",
    "sg:tags":[
        "en",
        "groenten"
    ],
    "wof:name":"Gelder, G Van",
    "wof:placetype":"venue"
},
  "geometry": {"coordinates":[4.43381,51.9328],"type":"Point"}
}