{
  "type": "Feature",
  "properties": {
    "addr:full":"T Oost 56 Oosterwolde Fr Friesland 8431 LK",
    "addr:housenumber":"56",
    "addr:postcode":"8431 lk",
    "addr:street":"T Oost",
    "iso:country":"NL",
    "sg:address":"T Oost 56",
    "sg:city":"Oosterwolde Fr",
    "sg:orig_category":"Ballonvaarten En -Reclame",
    "sg:phone":"+31 516 520 226",
    "sg:postcode":"8431 LK",
    "sg:province":"Friesland",
    "sg:website":"http://www.aeroballoons.nl",
    "wof:name":"Aero, Balloons",
    "wof:placetype":"venue"
},
  "geometry": {"coordinates":[6.299479,52.995995],"type":"Point"}
}