{
  "type": "Feature",
  "properties": {
    "addr:full":"Oosterengweg 88 Hilversum North Holland 1212 CP",
    "addr:housenumber":"88",
    "addr:postcode":"1212 cp",
    "addr:street":"Oosterengweg",
    "iso:country":"NL",
    "sg:address":"Oosterengweg 88",
    "sg:city":"Hilversum",
    "sg:orig_category":"Bloemen And Planten",
    "sg:phone":"+31 35 685 5473",
    "sg:postcode":"1212 CP",
    "sg:province":"North Holland",
    "wof:name":"Schipper'S Bloemen",
    "wof:placetype":"venue"
},
  "geometry": {"coordinates":[5.195007,52.218826],"type":"Point"}
}