{
  "type": "Feature",
  "properties": {
    "addr:full":"Keizersgr 403 Amsterdam Noord-Holland 1016 EK",
    "addr:housenumber":"403",
    "addr:postcode":"1016 ek",
    "iso:country":"NL",
    "sg:address":"Keizersgr 403",
    "sg:city":"Amsterdam",
    "sg:orig_category":"Advocaten En Advocatenkantoren",
    "sg:phone":"+31 20 623 4501",
    "sg:postcode":"1016 EK",
    "sg:province":"Noord-Holland",
    "wof:name":"Werner, Mr A P",
    "wof:placetype":"venue"
},
  "geometry": {"coordinates":[4.884926,52.367622],"type":"Point"}
}