{
  "type": "Feature",
  "properties": {
    "iso:country":"NL",
    "sg:address":"De Schutter 24",
    "sg:city":"Oirschot",
    "sg:orig_category":"Autorijscholen",
    "sg:phone":"+31 499 550 005",
    "sg:postcode":"5688 VH",
    "sg:province":"North Brabant",
    "wof:name":"Aart Wolff",
    "wof:placetype":"venue"
},
  "geometry": {"coordinates":[5.31655,51.502708],"type":"Point"}
}