{
  "type": "Feature",
  "properties": {
    "iso:country":"NL",
    "sg:address":"Achterbos 22B",
    "sg:city":"Vinkeveen",
    "sg:orig_category":"Jachten - Schilderwerken En Onderhoud",
    "sg:phone":"+31 6 51564425",
    "sg:postcode":"3645 CD",
    "sg:province":"Utrecht",
    "wof:name":"Piet Hein",
    "wof:placetype":"venue"
},
  "geometry": {"coordinates":[4.926029,52.225353],"type":"Point"}
}