{
  "type": "Feature",
  "properties": {
    "addr:full":"Grintwg 255 Wageningen Gelderland 6704 AN",
    "addr:housenumber":"255",
    "addr:postcode":"6704 an",
    "addr:street":"Gelderland",
    "iso:country":"NL",
    "sg:address":"Grintwg 255",
    "sg:city":"Wageningen",
    "sg:orig_category":"Wasmachines En Wasdrogers",
    "sg:phone":"+31 317 411 183",
    "sg:postcode":"6704 AN",
    "sg:province":"Gelderland",
    "wof:name":"Brink, Jan Van Den",
    "wof:placetype":"venue"
},
  "geometry": {"coordinates":[5.6759848595,51.9833450317],"type":"Point"}
}