{
  "type": "Feature",
  "properties": {
    "addr:full":"Maaibeemd 107 Breda North Brabant 4824 ND",
    "addr:housenumber":"107",
    "addr:postcode":"4824 nd",
    "addr:street":"Maaibeemd",
    "iso:country":"NL",
    "sg:address":"Maaibeemd 107",
    "sg:city":"Breda",
    "sg:orig_category":"Huishoudapparatuur, Televisies And Radio'S",
    "sg:phone":"+31 76 541 8333",
    "sg:postcode":"4824 ND",
    "sg:province":"North Brabant",
    "wof:name":"Jentronics",
    "wof:placetype":"venue"
},
  "geometry": {"coordinates":[4.741371,51.608479],"type":"Point"}
}