{
  "type": "Feature",
  "properties": {
    "addr:full":"Langestr 42 Winschoten Groningen 9671 PH",
    "addr:housenumber":"42",
    "addr:postcode":"9671",
    "addr:street":"Langestr",
    "iso:country":"NL",
    "sg:address":"Langestr 42",
    "sg:city":"Winschoten",
    "sg:orig_category":"Herenkleding",
    "sg:phone":"+31 597 412 656",
    "sg:postcode":"9671 PH",
    "sg:province":"Groningen",
    "wof:name":"R\u00f7Ben Bv",
    "wof:placetype":"venue"
},
  "geometry": {"coordinates":[7.036447,53.144505],"type":"Point"}
}