{
  "type": "Feature",
  "properties": {
    "addr:full":"E Ten Boom Erf 11 Heerhugowaard North Holland 1705 JB",
    "addr:housenumber":"11",
    "addr:postcode":"1705 jb",
    "addr:street":"E Ten Boom Erf",
    "iso:country":"NL",
    "sg:address":"E Ten Boom Erf 11",
    "sg:city":"Heerhugowaard",
    "sg:orig_category":"Fotografie Reclame En Mode",
    "sg:phone":"+31 72 571 8757",
    "sg:postcode":"1705 JB",
    "sg:province":"North Holland",
    "wof:name":"Westerburger",
    "wof:placetype":"venue"
},
  "geometry": {"coordinates":[4.829465,52.643829],"type":"Point"}
}