{
  "type": "Feature",
  "properties": {
    "iso:country":"NL",
    "sg:address":"Melegardeweg 7",
    "sg:city":"Zeddam",
    "sg:orig_category":"Juridische Adviseurs",
    "sg:phone":"+31 314 653 041",
    "sg:postcode":"7038 ER",
    "sg:province":"Gelderland",
    "wof:name":"Pennington Company",
    "wof:placetype":"venue"
},
  "geometry": {"coordinates":[6.265965,51.90184],"type":"Point"}
}