{
  "type": "Feature",
  "properties": {
    "addr:full":"J Leysterstr 9 Meppel Drenthe 7944 AA",
    "addr:housenumber":"9",
    "addr:postcode":"7944 aa",
    "iso:country":"NL",
    "sg:address":"J Leysterstr 9",
    "sg:city":"Meppel",
    "sg:orig_category":"Bodemonderzoek",
    "sg:phone":"+31 522 260 084",
    "sg:postcode":"7944 AA",
    "sg:province":"Drenthe",
    "wof:name":"Koops Grondmechanica Vof",
    "wof:placetype":"venue"
},
  "geometry": {"coordinates":[6.184569,52.683704],"type":"Point"}
}