{
  "type": "Feature",
  "properties": {
    "addr:full":"Madridweg 20 Almere Flevoland 1334 DP",
    "addr:housenumber":"20",
    "addr:postcode":"1334 dp",
    "addr:street":"Madridweg;Flevoland",
    "iso:country":"NL",
    "sg:address":"Madridweg 20",
    "sg:city":"Almere",
    "sg:orig_category":"Kappers",
    "sg:phone":"+31 36 532 5391",
    "sg:postcode":"1334 DP",
    "sg:province":"Flevoland",
    "wof:name":"Bibob",
    "wof:placetype":"venue"
},
  "geometry": {"coordinates":[5.2778158188,52.3950767517],"type":"Point"}
}