{
  "type": "Feature",
  "properties": {
    "addr:full":"Dorpsstr 4850 Hazerswoude Dorp Zuid-Holland 2391 BJ",
    "addr:postcode":"4850;2391 bj",
    "addr:street":"Hazerswoude",
    "iso:country":"NL",
    "sg:address":"Dorpsstr 4850",
    "sg:city":"Hazerswoude Dorp",
    "sg:orig_category":"Woningbouw- Verenigingen En -Stichtingen",
    "sg:phone":"+31 172 583 111",
    "sg:postcode":"2391 BJ",
    "sg:province":"Zuid-Holland",
    "wof:name":"Habeko Wonen",
    "wof:placetype":"venue"
},
  "geometry": {"coordinates":[4.5756797791,52.0968894958],"type":"Point"}
}