{
  "type": "Feature",
  "properties": {
    "addr:full":"Meulenakker 9 Sleen Drenthe 7841 EP",
    "addr:housenumber":"9",
    "addr:postcode":"7841 ep",
    "addr:street":"Meulenakker",
    "iso:country":"NL",
    "sg:address":"Meulenakker 9",
    "sg:city":"Sleen",
    "sg:orig_category":"Beveiliging",
    "sg:phone":"+31 591 361 928",
    "sg:postcode":"7841 EP",
    "sg:province":"Drenthe",
    "sg:website":"http://www.trample.nl",
    "wof:name":"Trample",
    "wof:placetype":"venue"
},
  "geometry": {"coordinates":[6.807843,52.766132],"type":"Point"}
}