{
  "type": "Feature",
  "properties": {
    "addr:full":"Munneholm 6 Groningen Groningen 9711 JA",
    "addr:housenumber":"6",
    "addr:postcode":"9711 ja",
    "addr:street":"Munneholm",
    "iso:country":"NL",
    "sg:address":"Munneholm 6",
    "sg:city":"Groningen",
    "sg:orig_category":"Herenmodezaken",
    "sg:phone":"+31 50 313 8173",
    "sg:postcode":"9711 JA",
    "sg:province":"Groningen",
    "wof:name":"Harvie Bv",
    "wof:placetype":"venue"
},
  "geometry": {"coordinates":[6.574715,53.217144],"type":"Point"}
}