{
  "type": "Feature",
  "properties": {
    "iso:country":"NL",
    "sg:address":"Oosterseweg 8",
    "sg:city":"Zuidwolde Gn",
    "sg:orig_category":"Overheidsdiensten",
    "sg:phone":"+31 50 301 2789",
    "sg:postcode":"9785 AE",
    "sg:province":"Groningen",
    "wof:name":"Irene",
    "wof:placetype":"venue"
},
  "geometry": {"coordinates":[6.5932688713,53.2600593567],"type":"Point"}
}