{
  "type": "Feature",
  "properties": {
    "addr:full":"Cereslaan 1 Veendam Groningen 9645 MJ",
    "addr:housenumber":"1",
    "addr:postcode":"9645 mj",
    "addr:street":"Cereslaan",
    "iso:country":"NL",
    "sg:address":"Cereslaan 1",
    "sg:city":"Veendam",
    "sg:orig_category":"Autokeuringen",
    "sg:phone":"+31 598 630 390",
    "sg:postcode":"9645 MJ",
    "sg:province":"Groningen",
    "wof:name":"Mac Veendam",
    "wof:placetype":"venue"
},
  "geometry": {"coordinates":[6.890411,53.10075],"type":"Point"}
}