{
  "type": "Feature",
  "properties": {
    "iso:country":"NL",
    "sg:address":"Postbus 682",
    "sg:city":"Gouda",
    "sg:orig_category":"Metselwerken",
    "sg:phone":"+31 182 523 510",
    "sg:postcode":"2800 AR",
    "sg:province":"Buenos Aires",
    "wof:name":"Brug, Van De",
    "wof:placetype":"venue"
},
  "geometry": {"coordinates":[-58.99535,-34.081829],"type":"Point"}
}