{
  "type": "Feature",
  "properties": {
    "iso:country":"NL",
    "sg:address":"Korhoenderweg 16",
    "sg:city":"Holten",
    "sg:orig_category":"Paramedische Behandelingen",
    "sg:phone":"+31 548 366 876",
    "sg:postcode":"7451 HB",
    "sg:province":"Overijssel",
    "wof:name":"Logopediste R M Van Couwelaar-Vd Ven",
    "wof:placetype":"venue"
},
  "geometry": {"coordinates":[6.440922,52.293552],"type":"Point"}
}