{
  "type": "Feature",
  "properties": {
    "addr:full":"Prinsenstr 102 Almelo Overijssel 7607 JZ",
    "addr:housenumber":"102",
    "addr:postcode":"7607 jz",
    "iso:country":"NL",
    "sg:address":"Prinsenstr 102",
    "sg:city":"Almelo",
    "sg:orig_category":"Huidtherapeuten",
    "sg:phone":"+31 546 538 753",
    "sg:postcode":"7607 JZ",
    "sg:province":"Overijssel",
    "wof:name":"Hauschka, Dr",
    "wof:placetype":"venue"
},
  "geometry": {"coordinates":[6.663617,52.353271],"type":"Point"}
}