{
  "type": "Feature",
  "properties": {
    "addr:full":"Zeebruggestraat 1 Eindhoven North Brabant 5628 NH",
    "addr:housenumber":"1",
    "addr:postcode":"5628 nh",
    "addr:street":"Zeebruggestraat",
    "iso:country":"NL",
    "sg:address":"Zeebruggestraat 1",
    "sg:city":"Eindhoven",
    "sg:orig_category":"Verzekeringen",
    "sg:phone":"+31 40 255 3397",
    "sg:postcode":"5628 NH",
    "sg:province":"North Brabant",
    "wof:name":"Safe 'N Sure Assurantien",
    "wof:placetype":"venue"
},
  "geometry": {"coordinates":[5.475636,51.477524],"type":"Point"}
}