{
  "type": "Feature",
  "properties": {
    "addr:full":"Curacaolaan 12 Hilversum Noord-Holland 1213 VK",
    "addr:housenumber":"12",
    "addr:postcode":"1213 vk",
    "addr:street":"Curacaolaan",
    "iso:country":"NL",
    "sg:address":"Curacaolaan 12",
    "sg:city":"Hilversum",
    "sg:orig_category":"Effectenmakelaars And Fondsenbeheer",
    "sg:phone":"+31 35 685 5914",
    "sg:postcode":"1213 VK",
    "sg:province":"Noord-Holland",
    "wof:name":"B.H. Henkelman Marketmakers Bv",
    "wof:placetype":"venue"
},
  "geometry": {"coordinates":[5.196993,52.2117],"type":"Point"}
}