{
  "type": "Feature",
  "properties": {
    "iso:country":"NL",
    "sg:address":"Kanaalwg 34",
    "sg:city":"Veenendaal",
    "sg:orig_category":"Waterleidingbedrijven",
    "sg:phone":"+31 318 519 162",
    "sg:postcode":"3905 AA",
    "sg:province":"Utrecht",
    "wof:name":"Waterleidingbedrijf Midden Ned, Nv",
    "wof:placetype":"venue"
},
  "geometry": {"coordinates":[5.5456600189,52.0248298645],"type":"Point"}
}