{
  "type": "Feature",
  "properties": {
    "iso:country":"NL",
    "sg:address":"Schoolstraat 32",
    "sg:city":"Venray",
    "sg:orig_category":"Schoenen",
    "sg:phone":"+31 478 510 701",
    "sg:postcode":"5801 BP",
    "sg:province":"Limburg",
    "wof:name":"E- Voi",
    "wof:placetype":"venue"
},
  "geometry": {"coordinates":[5.974384,51.525532],"type":"Point"}
}