{
  "type": "Feature",
  "properties": {
    "addr:full":"Spui 36 Stryen Zuid-Holland 3291 EV",
    "addr:housenumber":"36",
    "addr:street":"Spui",
    "iso:country":"NL",
    "sg:address":"Spui 36",
    "sg:city":"Stryen",
    "sg:orig_category":"Scholen Voor Basisonderwijs",
    "sg:phone":"+31 78 674 2624",
    "sg:postcode":"3291 EV",
    "sg:province":"Zuid-Holland",
    "wof:name":"Spui Chr, Het",
    "wof:placetype":"venue"
},
  "geometry": {"coordinates":[4.54727,51.750832],"type":"Point"}
}