{
  "type": "Feature",
  "properties": {
    "addr:full":"Nieuwersluisstraat 36 'S Gravenhage South Holland 2546 RX",
    "addr:housenumber":"36",
    "addr:postcode":"2546 rx",
    "addr:street":"Nieuwersluisstraat;' S Gravenhage",
    "iso:country":"NL",
    "sg:address":"Nieuwersluisstraat 36",
    "sg:city":"'S Gravenhage",
    "sg:orig_category":"Dansscholen",
    "sg:phone":"+31 70 366 5868",
    "sg:postcode":"2546 RX",
    "sg:province":"South Holland",
    "wof:name":"Fafa",
    "wof:placetype":"venue"
},
  "geometry": {"coordinates":[4.268606,52.057686],"type":"Point"}
}