{
  "type": "Feature",
  "properties": {
    "addr:full":"Staddijk 21 Nijmegen Gelderland 6537 TW",
    "addr:housenumber":"21",
    "addr:postcode":"6537 tw",
    "addr:street":"Staddijk;Gelderland",
    "iso:country":"NL",
    "sg:address":"Staddijk 21",
    "sg:city":"Nijmegen",
    "sg:orig_category":"Overheidsdiensten",
    "sg:phone":"+31 24 345 1101",
    "sg:postcode":"6537 TW",
    "sg:province":"Gelderland",
    "wof:name":"Staddijk",
    "wof:placetype":"venue"
},
  "geometry": {"coordinates":[5.7987928391,51.8017807007],"type":"Point"}
}