{
  "type": "Feature",
  "properties": {
    "iso:country":"NL",
    "sg:address":"Hoefblad 47",
    "sg:city":"Huizen",
    "sg:orig_category":"Sportverenigingen En Ontspannings- Verenigingen",
    "sg:phone":"+31 35 525 5928",
    "sg:postcode":"1273 AC",
    "sg:province":"Noord-Holland",
    "wof:name":"Huizen'96 Badmintonver",
    "wof:placetype":"venue"
},
  "geometry": {"coordinates":[5.246514,52.299183],"type":"Point"}
}