{
  "type": "Feature",
  "properties": {
    "addr:full":"Arnhemsewg 279 Apeldoorn Gelderland 7333 NC",
    "addr:housenumber":"279;7333",
    "addr:street":"Gelderland",
    "iso:country":"NL",
    "sg:address":"Arnhemsewg 279",
    "sg:city":"Apeldoorn",
    "sg:orig_category":"Peuterspeelzalen",
    "sg:phone":"+31 55 543 3558",
    "sg:postcode":"7333 NC",
    "sg:province":"Gelderland",
    "wof:name":"Oki-Doki",
    "wof:placetype":"venue"
},
  "geometry": {"coordinates":[5.962425,52.191902],"type":"Point"}
}