{
  "type": "Feature",
  "properties": {
    "addr:full":"Schiedamse Vest 180 Rotterdam South Holland 3011 BH",
    "addr:housenumber":"180",
    "addr:postcode":"3011 bh",
    "addr:street":"Schiedamse Vest",
    "iso:country":"NL",
    "sg:address":"Schiedamse Vest 180",
    "sg:city":"Rotterdam",
    "sg:orig_category":"Ziekenhuizen, Sanatoria, Verpleeghuizen",
    "sg:phone":"+31 10 401 7666",
    "sg:postcode":"3011 BH",
    "sg:province":"South Holland",
    "wof:name":"European Assoc Of Eye Hospitals, The",
    "wof:placetype":"venue"
},
  "geometry": {"coordinates":[4.48189,51.911961],"type":"Point"}
}