{
  "type": "Feature",
  "properties": {
    "addr:full":"Tramwg 31 Oude Tonge Zuid-Holland 3255 MB",
    "addr:housenumber":"31",
    "addr:postcode":"3255 mb",
    "addr:street":"Tramwg",
    "iso:country":"NL",
    "sg:address":"Tramwg 31",
    "sg:city":"Oude Tonge",
    "sg:orig_category":"Scheepvaartinspectie",
    "sg:phone":"+31 187 643 177",
    "sg:postcode":"3255 MB",
    "sg:province":"Zuid-Holland",
    "sg:website":"http://www.arefcon.com",
    "wof:name":"Arefcon Hisma Bv",
    "wof:placetype":"venue"
},
  "geometry": {"coordinates":[4.216104,51.696484],"type":"Point"}
}