{
  "type": "Feature",
  "properties": {
    "addr:full":"Vlietplein 8 Ridderkerk Zuid-Holland 2986 GH",
    "addr:housenumber":"8",
    "addr:postcode":"2986 gh",
    "addr:street":"Vlietplein",
    "iso:country":"NL",
    "sg:address":"Vlietplein 8",
    "sg:city":"Ridderkerk",
    "sg:orig_category":"Opticiens",
    "sg:phone":"+31 180 423 201",
    "sg:postcode":"2986 GH",
    "sg:province":"Zuid-Holland",
    "wof:name":"Opdriestiek",
    "wof:placetype":"venue"
},
  "geometry": {"coordinates":[4.6196007729,51.8657455444],"type":"Point"}
}