{
  "type": "Feature",
  "properties": {
    "addr:full":"Nieuwstraat 58 Medemblik Noord-Holland 1671 BG",
    "addr:housenumber":"58",
    "addr:postcode":"1671",
    "addr:street":"Nieuwstraat",
    "iso:country":"NL",
    "sg:address":"Nieuwstraat 58",
    "sg:city":"Medemblik",
    "sg:classifiers":[
        {
            "category":"Food & Beverages",
            "subcategory":"Fruits & Vegetables",
            "type":"Retail Goods"
        }
    ],
    "sg:phone":"+31 227 541 576",
    "sg:postcode":"1671 BG",
    "sg:province":"Noord-Holland",
    "sg:tags":[
        "groenten"
    ],
    "wof:name":"Wed H. Bos En Zonen",
    "wof:placetype":"venue"
},
  "geometry": {"coordinates":[5.106411,52.771797],"type":"Point"}
}