{
  "type": "Feature",
  "properties": {
    "addr:full":"Anthony Fokkerstraat 4 Goes Zeeland 4462 ET",
    "addr:housenumber":"4",
    "addr:postcode":"4462 et",
    "addr:street":"Anthony Fokkerstraat",
    "iso:country":"NL",
    "sg:address":"Anthony Fokkerstraat 4",
    "sg:city":"Goes",
    "sg:orig_category":"Bedrijfsinventaris Gh",
    "sg:phone":"+31 113 227 506",
    "sg:postcode":"4462 ET",
    "sg:province":"Zeeland",
    "wof:name":"Handelsonderneming J. Eversdijk Bv",
    "wof:placetype":"venue"
},
  "geometry": {"coordinates":[-83.914169,39.768833],"type":"Point"}
}