{
  "type": "Feature",
  "properties": {
    "iso:country":"NL",
    "sg:address":"Weth Ventewg 135",
    "sg:city":"Gouda",
    "sg:orig_category":"Agenturen En Commissiehandel",
    "sg:phone":"+31 182 581 442",
    "sg:postcode":"2805 JN",
    "sg:province":"Zuid-Holland",
    "wof:name":"Okkerse Bv",
    "wof:placetype":"venue"
},
  "geometry": {"coordinates":[4.721457,52.02137],"type":"Point"}
}