{
  "type": "Feature",
  "properties": {
    "iso:country":"NL",
    "sg:address":"J J Van Deinselaan 17",
    "sg:city":"Almelo",
    "sg:orig_category":"Schilderwerk",
    "sg:phone":"+31 546 871 068",
    "sg:postcode":"7602 VM",
    "sg:province":"Overijssel",
    "wof:name":"Schildersbedrijf Gebr. Borggreve Bv",
    "wof:placetype":"venue"
},
  "geometry": {"coordinates":[6.663582,52.37233],"type":"Point"}
}