{
  "type": "Feature",
  "properties": {
    "iso:country":"NL",
    "sg:address":"Kerkstraat 13-15",
    "sg:city":"Diessen",
    "sg:orig_category":"Banken And Kredietinstellingen",
    "sg:phone":"+31 13 504 2799",
    "sg:postcode":"5087 BP",
    "sg:province":"Noord-Brabant",
    "wof:name":"Postkantoor",
    "wof:placetype":"venue"
},
  "geometry": {"coordinates":[5.175558,51.475784],"type":"Point"}
}