{
  "type": "Feature",
  "properties": {
    "iso:country":"NL",
    "sg:address":"Hofrustln 35",
    "sg:city":"Bennekom",
    "sg:orig_category":"Houtwormverdelging",
    "sg:phone":"+31 318 430 096",
    "sg:postcode":"6721 TA",
    "sg:province":"Gelderland",
    "wof:name":"Jollie Houtwormbestrijding",
    "wof:placetype":"venue"
},
  "geometry": {"coordinates":[5.67124,51.99548],"type":"Point"}
}