{
  "type": "Feature",
  "properties": {
    "addr:full":"Hellerweg 23 Enschede NL.08 7547 RK",
    "addr:housenumber":"23",
    "addr:postcode":"7547 rk",
    "addr:street":"Hellerweg",
    "iso:country":"NL",
    "sg:address":"Hellerweg 23",
    "sg:city":"Enschede",
    "sg:orig_category":"Hypotheken And Hypotheekbanken",
    "sg:phone":"+31 53 432 0334",
    "sg:postcode":"7547 RK",
    "sg:province":"NL.08",
    "wof:name":"Premarce Bv",
    "wof:placetype":"venue"
},
  "geometry": {"coordinates":[6.828819,52.228168],"type":"Point"}
}