{
  "type": "Feature",
  "properties": {
    "addr:full":"O Nassauln 14 Zwolle NL.08 8019 ZB",
    "addr:housenumber":"14",
    "addr:postcode":"8019 zb",
    "iso:country":"NL",
    "sg:address":"O Nassauln 14",
    "sg:city":"Zwolle",
    "sg:orig_category":"Peuterspeelzalen",
    "sg:phone":"+31 38 454 2550",
    "sg:postcode":"8019 ZB",
    "sg:province":"NL.08",
    "wof:name":"Doppejan",
    "wof:placetype":"venue"
},
  "geometry": {"coordinates":[6.088738,52.512566],"type":"Point"}
}