{
  "type": "Feature",
  "properties": {
    "addr:full":"De Rosmolen 159 Westervoort Gelderland 6932 NC",
    "addr:housenumber":"159;6932",
    "addr:street":"De Rosmolen;Gelderland",
    "iso:country":"NL",
    "sg:address":"De Rosmolen 159",
    "sg:city":"Westervoort",
    "sg:orig_category":"Motoren - Onderdelen",
    "sg:phone":"+31 26 311 5097",
    "sg:postcode":"6932 NC",
    "sg:province":"Gelderland",
    "wof:name":"Pol, L Van Der",
    "wof:placetype":"venue"
},
  "geometry": {"coordinates":[5.980219,51.944244],"type":"Point"}
}