{
  "type": "Feature",
  "properties": {
    "addr:full":"Rijsdijk 83 Rhoon Zuid-Holland 3161 HM",
    "addr:housenumber":"83",
    "addr:postcode":"3161 hm",
    "addr:street":"Rijsdijk",
    "iso:country":"NL",
    "sg:address":"Rijsdijk 83",
    "sg:city":"Rhoon",
    "sg:orig_category":"Marktonderzoekbureaus",
    "sg:phone":"+31 10 506 7207",
    "sg:postcode":"3161 HM",
    "sg:province":"Zuid-Holland",
    "wof:name":"Markant Adviesburo Voor Marketing Mangement-Onders",
    "wof:placetype":"venue"
},
  "geometry": {"coordinates":[4.431638,51.85577],"type":"Point"}
}