{
  "type": "Feature",
  "properties": {
    "addr:full":"Bovenwg 34 St Pancras Noord-Holland 1834 CE",
    "addr:housenumber":"34",
    "addr:postcode":"1834 ce",
    "addr:street":"Bovenwg",
    "iso:country":"NL",
    "sg:address":"Bovenwg 34",
    "sg:city":"St Pancras",
    "sg:orig_category":"Schilders",
    "sg:phone":"+31 72 564 2758",
    "sg:postcode":"1834 CE",
    "sg:province":"Noord-Holland",
    "wof:name":"Danenberg, C M",
    "wof:placetype":"venue"
},
  "geometry": {"coordinates":[4.785428,52.663937],"type":"Point"}
}