{
  "type": "Feature",
  "properties": {
    "addr:full":"Hoppad 19 Roden Provincie Drenthe 9301 PG",
    "addr:housenumber":"19",
    "addr:postcode":"9301",
    "addr:street":"Hoppad;Provincie Drenthe;Pg",
    "iso:country":"NL",
    "sg:address":"Hoppad 19",
    "sg:city":"Roden",
    "sg:orig_category":"Beeldende Kunstenaars",
    "sg:phone":"+31 50 501 9757",
    "sg:postcode":"9301 PG",
    "sg:province":"Provincie Drenthe",
    "sg:website":"http://www.cbkdrenthe.nl",
    "wof:name":"Bosch, Jelly Van Den",
    "wof:placetype":"venue"
},
  "geometry": {"coordinates":[6.423743,53.145714],"type":"Point"}
}