{
  "type": "Feature",
  "properties": {
    "addr:full":"Erasstr 99 Kaatsheuvel North Brabant 5171 VL",
    "addr:housenumber":"99",
    "addr:postcode":"5171 vl",
    "addr:street":"Erasstr",
    "iso:country":"NL",
    "sg:address":"Erasstr 99",
    "sg:city":"Kaatsheuvel",
    "sg:orig_category":"Honden- En Kattentrimsalons",
    "sg:phone":"+31 416 283 066",
    "sg:postcode":"5171 VL",
    "sg:province":"North Brabant",
    "wof:name":"Marie-Jos?",
    "wof:placetype":"venue"
},
  "geometry": {"coordinates":[5.006123,51.656338],"type":"Point"}
}