{
  "type": "Feature",
  "properties": {
    "iso:country":"NL",
    "sg:address":"Dorpstraat 104",
    "sg:city":"Westervoort",
    "sg:orig_category":"Huishoudapparatuur, Televisies And Radio'S",
    "sg:phone":"+31 26 311 8364",
    "sg:postcode":"6931 BM",
    "sg:province":"Gelderland",
    "wof:name":"Gebr Stegers Radio Tv Electr App Verk & Rep",
    "wof:placetype":"venue"
},
  "geometry": {"coordinates":[5.970251,51.963776],"type":"Point"}
}