{
  "type": "Feature",
  "properties": {
    "addr:full":"Steenwijkerweg 2 Wolvega Friesland 8471 LA",
    "addr:housenumber":"2",
    "addr:postcode":"8471 la",
    "addr:street":"Steenwijkerweg",
    "iso:country":"NL",
    "sg:address":"Steenwijkerweg 2",
    "sg:city":"Wolvega",
    "sg:orig_category":"Banken And Kredietinstellingen",
    "sg:phone":"+31 561 612 154",
    "sg:postcode":"8471 LA",
    "sg:province":"Friesland",
    "wof:name":"Ing Bank",
    "wof:placetype":"venue"
},
  "geometry": {"coordinates":[6.001901,52.876144],"type":"Point"}
}