{
  "type": "Feature",
  "properties": {
    "addr:full":"Bark 35 Barendrecht Zuid-Holland 2991 JA",
    "addr:housenumber":"35",
    "addr:postcode":"2991 ja",
    "addr:street":"Bark",
    "iso:country":"NL",
    "sg:address":"Bark 35",
    "sg:city":"Barendrecht",
    "sg:orig_category":"Autokeuringen",
    "sg:phone":"+31 6 55198288",
    "sg:postcode":"2991 JA",
    "sg:province":"Zuid-Holland",
    "wof:name":"Schaltin",
    "wof:placetype":"venue"
},
  "geometry": {"coordinates":[4.543373,51.848057],"type":"Point"}
}