{
  "type": "Feature",
  "properties": {
    "iso:country":"NL",
    "sg:address":"Oude Molenstr 12-14",
    "sg:city":"Assen",
    "sg:orig_category":"Goudsmeden En Zilversmeden",
    "sg:phone":"+31 592 318 874",
    "sg:postcode":"9401 DC",
    "sg:province":"Provincie Drenthe",
    "wof:name":"For?t D'Or",
    "wof:placetype":"venue"
},
  "geometry": {"coordinates":[6.561713,52.996334],"type":"Point"}
}