{
  "type": "Feature",
  "properties": {
    "iso:country":"NL",
    "sg:address":"Vaart Nz 8",
    "sg:city":"Assen",
    "sg:orig_category":"Verenigingen En Stichtingen",
    "sg:phone":"+31 592 310 710",
    "sg:postcode":"9401 GM",
    "sg:province":"Provincie Drenthe",
    "wof:name":"Maluku Di Drenthe, Instituut",
    "wof:placetype":"venue"
},
  "geometry": {"coordinates":[6.55872,52.99411],"type":"Point"}
}