{
  "type": "Feature",
  "properties": {
    "addr:full":"Wassenaarstraat 13 Gemert North Brabant 5421 BA",
    "addr:housenumber":"13",
    "addr:postcode":"5421 ba",
    "addr:street":"Wassenaarstraat",
    "iso:country":"NL",
    "sg:address":"Wassenaarstraat 13",
    "sg:city":"Gemert",
    "sg:orig_category":"Vertaal- And Tolkenbureaus",
    "sg:phone":"+31 492 367 051",
    "sg:postcode":"5421 BA",
    "sg:province":"North Brabant",
    "wof:name":"Loopstra",
    "wof:placetype":"venue"
},
  "geometry": {"coordinates":[5.6881,51.555813],"type":"Point"}
}