{
  "type": "Feature",
  "properties": {
    "addr:full":"Anemonestr 10 Eindhoven Noord-Brabant 5615 AM",
    "addr:housenumber":"10",
    "addr:postcode":"5615",
    "addr:street":"Anemonestr",
    "iso:country":"NL",
    "sg:address":"Anemonestr 10",
    "sg:city":"Eindhoven",
    "sg:orig_category":"Antiquiteiten - Restauratie",
    "sg:phone":"+31 40 844 0244",
    "sg:postcode":"5615 AM",
    "sg:province":"Noord-Brabant",
    "sg:website":"http://www.keramiko.nl",
    "wof:name":"Keramiko, Restauratie-Atelier",
    "wof:placetype":"venue"
},
  "geometry": {"coordinates":[5.488083,51.424393],"type":"Point"}
}