{
  "type": "Feature",
  "properties": {
    "iso:country":"NL",
    "sg:address":"St Jacobsln 184",
    "sg:city":"Nymegen",
    "sg:orig_category":"Galeries",
    "sg:phone":"+31 24 350 1936",
    "sg:postcode":"6533 VN",
    "sg:province":"Gelderland",
    "wof:name":"Porto Novo",
    "wof:placetype":"venue"
},
  "geometry": {"coordinates":[5.849486,51.81871],"type":"Point"}
}