{
  "type": "Feature",
  "properties": {
    "addr:full":"Rijksweg 2 Molenhoek Lb Limburg 6584 AB",
    "addr:housenumber":"2",
    "addr:postcode":"lb;6584 ab",
    "addr:street":"Rijksweg",
    "iso:country":"NL",
    "sg:address":"Rijksweg 2",
    "sg:city":"Molenhoek Lb",
    "sg:orig_category":"Bloemen And Planten",
    "sg:phone":"+31 24 358 3434",
    "sg:postcode":"6584 AB",
    "sg:province":"Limburg",
    "wof:name":"Vof Kwekerij Molenhoek",
    "wof:placetype":"venue"
},
  "geometry": {"coordinates":[5.869423,51.762257],"type":"Point"}
}