{
  "type": "Feature",
  "properties": {
    "addr:full":"Beukenln 27 Oosterbeek Gelderland 6862 HS",
    "addr:housenumber":"27",
    "addr:postcode":"6862 hs",
    "addr:street":"Beukenln;Gelderland",
    "iso:country":"NL",
    "sg:address":"Beukenln 27",
    "sg:city":"Oosterbeek",
    "sg:orig_category":"Psychologen",
    "sg:phone":"+31 26 333 6757",
    "sg:postcode":"6862 HS",
    "sg:province":"Gelderland",
    "wof:name":"Vermeer, Drs J D",
    "wof:placetype":"venue"
},
  "geometry": {"coordinates":[5.851143,51.98444],"type":"Point"}
}