{
  "type": "Feature",
  "properties": {
    "addr:full":"Van Limburg Stirumlaan 13 Naarden Noord-Holland 1411 BM",
    "addr:housenumber":"13",
    "addr:postcode":"1411 bm",
    "addr:street":"Van Limburg Stirumlaan",
    "iso:country":"NL",
    "sg:address":"Van Limburg Stirumlaan 13",
    "sg:city":"Naarden",
    "sg:orig_category":"Verzekeringen",
    "sg:phone":"+31 35 694 9705",
    "sg:postcode":"1411 BM",
    "sg:province":"Noord-Holland",
    "wof:name":"Verweij Verzekeringen",
    "wof:placetype":"venue"
},
  "geometry": {"coordinates":[5.15395,52.297653],"type":"Point"}
}