{
  "type": "Feature",
  "properties": {
    "addr:full":"Hogeschoorwg 226 Venlo Limburg 5914 CZ",
    "addr:housenumber":"226",
    "addr:postcode":"5914",
    "iso:country":"NL",
    "sg:address":"Hogeschoorwg 226",
    "sg:city":"Venlo",
    "sg:orig_category":"Kunststof Ramen",
    "sg:phone":"+31 77 354 9480",
    "sg:postcode":"5914 CZ",
    "sg:province":"Limburg",
    "wof:name":"Golsteijn, Peter",
    "wof:placetype":"venue"
},
  "geometry": {"coordinates":[6.169841,51.380783],"type":"Point"}
}