{
  "type": "Feature",
  "properties": {
    "addr:full":"V Marlewg 13 Noordscheschut Provincie Drenthe 7914 RB",
    "addr:housenumber":"13",
    "addr:postcode":"7914 rb",
    "addr:street":"Provincie Drenthe",
    "iso:country":"NL",
    "sg:address":"V Marlewg 13",
    "sg:city":"Noordscheschut",
    "sg:orig_category":"Kabelwerken",
    "sg:phone":"+31 528 343 184",
    "sg:postcode":"7914 RB",
    "sg:province":"Provincie Drenthe",
    "wof:name":"Kip",
    "wof:placetype":"venue"
},
  "geometry": {"coordinates":[6.5348501205,52.7244987488],"type":"Point"}
}