{
  "type": "Feature",
  "properties": {
    "iso:country":"NL",
    "sg:address":"V Marlewg 13",
    "sg:city":"Noordscheschut",
    "sg:orig_category":"Kabelwerken",
    "sg:phone":"+31 528 343 184",
    "sg:postcode":"7914 RB",
    "sg:province":"Provincie Drenthe",
    "wof:name":"Kip",
    "wof:placetype":"venue"
},
  "geometry": {"coordinates":[6.5348501205,52.7244987488],"type":"Point"}
}