{
  "type": "Feature",
  "properties": {
    "addr:full":"Nieuw Baarnstraat 33 Baarn Utrecht 3743 BN",
    "addr:housenumber":"33",
    "addr:postcode":"3743 bn",
    "addr:street":"Nieuw Baarnstraat",
    "iso:country":"NL",
    "sg:address":"Nieuw Baarnstraat 33",
    "sg:city":"Baarn",
    "sg:orig_category":"Hoortoestellen",
    "sg:phone":"+31 35 548 8703",
    "sg:postcode":"3743 BN",
    "sg:province":"Utrecht",
    "sg:website":"http://www.gewanl.nl",
    "wof:name":"R?g?",
    "wof:placetype":"venue"
},
  "geometry": {"coordinates":[5.28306,52.212452],"type":"Point"}
}