{
  "type": "Feature",
  "properties": {
    "iso:country":"NL",
    "sg:address":"Van Heemstralaan 101",
    "sg:city":"Arnhem",
    "sg:orig_category":"Bedrijfs- And Managementsconsultants",
    "sg:phone":"+31 26 351 9123",
    "sg:postcode":"6814 KG",
    "sg:province":"Gelderland",
    "wof:name":"B(S)K-Consult Bv",
    "wof:placetype":"venue"
},
  "geometry": {"coordinates":[5.8854780197,51.9957618713],"type":"Point"}
}