{
  "type": "Feature",
  "properties": {
    "iso:country":"NL",
    "sg:address":"Havenweg 12",
    "sg:city":"Enkhuizen",
    "sg:classifiers":[
        {
            "category":"Fast Food",
            "type":"Food & Drink"
        }
    ],
    "sg:phone":"+31 228 315 708",
    "sg:postcode":"1601 GA",
    "sg:province":"Noord-Holland",
    "sg:tags":[
        "afhaal",
        "restaurant"
    ],
    "wof:name":"B. Stammis",
    "wof:placetype":"venue"
},
  "geometry": {"coordinates":[5.291119,52.700699],"type":"Point"}
}