{
  "type": "Feature",
  "properties": {
    "addr:full":"Beukenlaan 3 Doornspijk Gelderland 8085 RK",
    "addr:housenumber":"3",
    "addr:postcode":"8085 rk",
    "addr:street":"Beukenlaan;Gelderland",
    "iso:country":"NL",
    "sg:address":"Beukenlaan 3",
    "sg:city":"Doornspijk",
    "sg:orig_category":"Boekenuitgeverijen",
    "sg:phone":"+31 525 661 823",
    "sg:postcode":"8085 RK",
    "sg:province":"Gelderland",
    "wof:name":"Davaco Publishers Bv",
    "wof:placetype":"venue"
},
  "geometry": {"coordinates":[5.849667,52.407326],"type":"Point"}
}