{
  "type": "Feature",
  "properties": {
    "iso:country":"NL",
    "sg:address":"Beukenlaan 3",
    "sg:city":"Doornspijk",
    "sg:orig_category":"Boekenuitgeverijen",
    "sg:phone":"+31 525 661 823",
    "sg:postcode":"8085 RK",
    "sg:province":"Gelderland",
    "wof:name":"Davaco Publishers Bv",
    "wof:placetype":"venue"
},
  "geometry": {"coordinates":[5.849667,52.407326],"type":"Point"}
}