{
  "type": "Feature",
  "properties": {
    "addr:full":"J Jongkindstr 97 Amsterdam Noord-Holland 1062 CR",
    "addr:housenumber":"97",
    "addr:postcode":"1062 cr",
    "iso:country":"NL",
    "sg:address":"J Jongkindstr 97",
    "sg:city":"Amsterdam",
    "sg:orig_category":"Verenigingen En Stichtingen",
    "sg:phone":"+31 20 408 4400",
    "sg:postcode":"1062 CR",
    "sg:province":"Noord-Holland",
    "sg:website":"http://www.effathaguyot.nl",
    "wof:name":"Effatha",
    "wof:placetype":"venue"
},
  "geometry": {"coordinates":[4.837263,52.3592],"type":"Point"}
}