{
  "type": "Feature",
  "properties": {
    "iso:country":"NL",
    "sg:address":"Emmapassage 26",
    "sg:city":"Tilburg",
    "sg:orig_category":"Glas, Porselein En Aardewerk",
    "sg:phone":"+31 13 543 0262",
    "sg:postcode":"5038 XA",
    "sg:province":"Noord-Brabant",
    "wof:name":"Porcello",
    "wof:placetype":"venue"
},
  "geometry": {"coordinates":[5.089108,51.555733],"type":"Point"}
}