{
  "type": "Feature",
  "properties": {
    "addr:full":"Hurksestr 20A Eindhoven North Brabant 5652 AK",
    "addr:housenumber":"20a",
    "addr:postcode":"5652 ak",
    "addr:street":"Hurksestr",
    "iso:country":"NL",
    "sg:address":"Hurksestr 20A",
    "sg:city":"Eindhoven",
    "sg:orig_category":"Lichtreclame",
    "sg:phone":"+31 40 256 1911",
    "sg:postcode":"5652 AK",
    "sg:province":"North Brabant",
    "wof:name":"Armada Janse Bv",
    "wof:placetype":"venue"
},
  "geometry": {"coordinates":[5.440332,51.433193],"type":"Point"}
}