{
  "type": "Feature",
  "properties": {
    "addr:full":"Dorpskd 31-33 Wateringen South Holland 2291 HN",
    "addr:housenumber":"31-33",
    "addr:postcode":"2291 hn",
    "iso:country":"NL",
    "sg:address":"Dorpskd 31-33",
    "sg:city":"Wateringen",
    "sg:orig_category":"Wijnkoperijen En -Groothandel",
    "sg:phone":"+31 174 270 500",
    "sg:postcode":"2291 HN",
    "sg:province":"South Holland",
    "sg:website":"http://www.residence-wijnen.nl",
    "wof:name":"Residence Bv",
    "wof:placetype":"venue"
},
  "geometry": {"coordinates":[4.2734999657,52.0233306885],"type":"Point"}
}