{
  "type": "Feature",
  "properties": {
    "addr:full":"Hindenweide 26 Zoetermeer Zuid-Holland 2727 GZ",
    "addr:housenumber":"26",
    "addr:postcode":"2727 gz",
    "addr:street":"Hindenweide",
    "iso:country":"NL",
    "sg:address":"Hindenweide 26",
    "sg:city":"Zoetermeer",
    "sg:orig_category":"Beeldende Kunstenaars",
    "sg:phone":"+31 79 342 0106",
    "sg:postcode":"2727 GZ",
    "sg:province":"Zuid-Holland",
    "wof:name":"Wils, Tilly",
    "wof:placetype":"venue"
},
  "geometry": {"coordinates":[4.510786,52.074486],"type":"Point"}
}