{
  "type": "Feature",
  "properties": {
    "iso:country":"NL",
    "sg:address":"Ryksstrwg 30",
    "sg:city":"Elst Ut",
    "sg:orig_category":"Mineralen",
    "sg:phone":"+31 318 471 758",
    "sg:postcode":"3921 AJ",
    "sg:province":"Utrecht",
    "wof:name":"Bisseling",
    "wof:placetype":"venue"
},
  "geometry": {"coordinates":[5.500553,51.983845],"type":"Point"}
}