{
  "type": "Feature",
  "properties": {
    "addr:full":"Burg Serrarisln 7 Breda Noord-Brabant 4835 LG",
    "addr:housenumber":"7",
    "addr:postcode":"4835 lg",
    "addr:street":"Burg Serrarisln",
    "iso:country":"NL",
    "sg:address":"Burg Serrarisln 7",
    "sg:city":"Breda",
    "sg:orig_category":"Wijnkoperijen En -Groothandel",
    "sg:phone":"+31 76 565 4537",
    "sg:postcode":"4835 LG",
    "sg:province":"Noord-Brabant",
    "wof:name":"Chateaux & Domaines Dumont",
    "wof:placetype":"venue"
},
  "geometry": {"coordinates":[4.7850899696,51.5692481995],"type":"Point"}
}