{
  "type": "Feature",
  "properties": {
    "addr:full":"Havenstraat 3 Dirkshorn Noord-Holland 1746 AV",
    "addr:housenumber":"3",
    "addr:postcode":"1746 av",
    "addr:street":"Havenstraat",
    "iso:country":"NL",
    "sg:address":"Havenstraat 3",
    "sg:city":"Dirkshorn",
    "sg:orig_category":"Kunst And Kunstenaarsbenodigdheden",
    "sg:phone":"+31 224 551 940",
    "sg:postcode":"1746 AV",
    "sg:province":"Noord-Holland",
    "wof:name":"Jan Kuindersma'S Kunsthandel",
    "wof:placetype":"venue"
},
  "geometry": {"coordinates":[4.778902,52.749386],"type":"Point"}
}