{
  "type": "Feature",
  "properties": {
    "addr:full":"Wever 29 Best Texas 5683 MN",
    "addr:housenumber":"29",
    "addr:postcode":"5683 mn",
    "addr:street":"Wever",
    "iso:country":"NL",
    "sg:address":"Wever 29",
    "sg:city":"Best",
    "sg:orig_category":"Boekhouders",
    "sg:phone":"+31 499 373 142",
    "sg:postcode":"5683 MN",
    "sg:province":"Texas",
    "wof:name":"Administratiekantoor H. Oppers",
    "wof:placetype":"venue"
},
  "geometry": {"coordinates":[-101.618134,31.224251],"type":"Point"}
}