{
  "type": "Feature",
  "properties": {
    "addr:full":"Laan Ten Boomen 2 Lierop North Brabant 5715 AB",
    "addr:housenumber":"2",
    "addr:postcode":"5715 ab",
    "addr:street":"Laan Ten Boomen",
    "iso:country":"NL",
    "sg:address":"Laan Ten Boomen 2",
    "sg:city":"Lierop",
    "sg:orig_category":"Discountwinkels",
    "sg:phone":"+31 492 331 344",
    "sg:postcode":"5715 AB",
    "sg:province":"North Brabant",
    "wof:name":"W Lemmen",
    "wof:placetype":"venue"
},
  "geometry": {"coordinates":[5.686224,51.421108],"type":"Point"}
}