{
  "type": "Feature",
  "properties": {
    "iso:country":"NL",
    "sg:address":"P C Hooftln 6",
    "sg:city":"Velp Gld",
    "sg:orig_category":"Geluidsinstallaties",
    "sg:phone":"+31 26 361 9962",
    "sg:postcode":"6881 ME",
    "sg:province":"Gelderland",
    "wof:name":"Hiensch Audio",
    "wof:placetype":"venue"
},
  "geometry": {"coordinates":[5.974033,51.996021],"type":"Point"}
}