{
  "type": "Feature",
  "properties": {
    "iso:country":"NL",
    "sg:address":"Zomerakker 159",
    "sg:city":"Spykenisse",
    "sg:orig_category":"Autorijscholen",
    "sg:phone":"+31 181 631 194",
    "sg:postcode":"3206 TM",
    "sg:province":"Zuid-Holland",
    "wof:name":"Hoek & Zoon, J Van Der",
    "wof:placetype":"venue"
},
  "geometry": {"coordinates":[4.31923,51.832352],"type":"Point"}
}