{
  "type": "Feature",
  "properties": {
    "addr:full":"Coltbaan 33 Nieuwegein Utrecht 3439 NG",
    "addr:housenumber":"33",
    "addr:postcode":"3439 ng",
    "addr:street":"Coltbaan",
    "iso:country":"NL",
    "sg:address":"Coltbaan 33",
    "sg:city":"Nieuwegein",
    "sg:orig_category":"Adviesbureaus Bedrijfsorganisatie",
    "sg:phone":"+31 30 282 9600",
    "sg:postcode":"3439 NG",
    "sg:province":"Utrecht",
    "sg:website":"http://www.paconsulting.com/nederlands",
    "wof:name":"Pa Consulting Group",
    "wof:placetype":"venue"
},
  "geometry": {"coordinates":[5.10027,52.030521],"type":"Point"}
}