{
  "type": "Feature",
  "properties": {
    "addr:full":"Bikoln 22 Culemborg Gelderland 4105 GH",
    "addr:housenumber":"22",
    "addr:postcode":"4105 gh",
    "addr:street":"Bikoln;Gelderland",
    "iso:country":"NL",
    "sg:address":"Bikoln 22",
    "sg:city":"Culemborg",
    "sg:orig_category":"Kappers",
    "sg:phone":"+31 345 569 098",
    "sg:postcode":"4105 GH",
    "sg:province":"Gelderland",
    "wof:name":"Jessika",
    "wof:placetype":"venue"
},
  "geometry": {"coordinates":[5.2214798927,51.9521751404],"type":"Point"}
}