{
  "type": "Feature",
  "properties": {
    "iso:country":"NL",
    "sg:address":"Raadhuisplein 25",
    "sg:city":"Drachten",
    "sg:orig_category":"Verlichting And Huishoudartikelen",
    "sg:phone":"+31 512 531 133",
    "sg:postcode":"9203 CZ",
    "sg:province":"Provincie Friesland",
    "wof:name":"Lampenier",
    "wof:placetype":"venue"
},
  "geometry": {"coordinates":[6.099041,53.105492],"type":"Point"}
}