{
  "type": "Feature",
  "properties": {
    "addr:full":"Over De Vesten 3A Schiedam Zuid-Holland 3116 AD",
    "addr:housenumber":"3a",
    "addr:postcode":"3116 ad",
    "addr:street":"Over De Vesten",
    "iso:country":"NL",
    "sg:address":"Over De Vesten 3A",
    "sg:city":"Schiedam",
    "sg:orig_category":"Juridische Adviseurs",
    "sg:phone":"+31 10 473 6600",
    "sg:postcode":"3116 AD",
    "sg:province":"Zuid-Holland",
    "wof:name":"Brouwer Cs, J P H",
    "wof:placetype":"venue"
},
  "geometry": {"coordinates":[4.398901,51.91214],"type":"Point"}
}