{
  "type": "Feature",
  "properties": {
    "iso:country":"NL",
    "sg:address":"Stijn Buysstraat 51",
    "sg:city":"Nijmegen",
    "sg:orig_category":"Juweliers",
    "sg:phone":"+31 24 322 6979",
    "sg:postcode":"6512 CM",
    "sg:province":"Gelderland",
    "wof:name":"Gem & Art Gallery",
    "wof:placetype":"venue"
},
  "geometry": {"coordinates":[5.85978,51.839058],"type":"Point"}
}