{
  "type": "Feature",
  "properties": {
    "addr:full":"K Lakenstr 22 Haarlem Noord-Holland 2011 ZD",
    "addr:housenumber":"22",
    "addr:postcode":"2011 zd",
    "addr:street":"Lakenstr",
    "iso:country":"NL",
    "sg:address":"K Lakenstr 22",
    "sg:city":"Haarlem",
    "sg:orig_category":"Open Haarden",
    "sg:phone":"+31 23 531 8517",
    "sg:postcode":"2011 ZD",
    "sg:province":"Noord-Holland",
    "sg:website":"http://www.schermerhorn.nl",
    "wof:name":"Schermerhorn, Willem",
    "wof:placetype":"venue"
},
  "geometry": {"coordinates":[4.628631,52.377598],"type":"Point"}
}