{
  "type": "Feature",
  "properties": {
    "addr:full":"Paltrokmolen 77 Alphen Aan Den Ryn Zuid-Holland 2406 JS",
    "addr:housenumber":"77",
    "addr:postcode":"2406 js",
    "addr:street":"Paltrokmolen;Aan Den Ryn",
    "iso:country":"NL",
    "sg:address":"Paltrokmolen 77",
    "sg:city":"Alphen Aan Den Ryn",
    "sg:orig_category":"Kappers",
    "sg:phone":"+31 172 490 330",
    "sg:postcode":"2406 JS",
    "sg:province":"Zuid-Holland",
    "wof:name":"Anita",
    "wof:placetype":"venue"
},
  "geometry": {"coordinates":[4.6673760414,52.1214294434],"type":"Point"}
}