{
  "type": "Feature",
  "properties": {
    "iso:country":"NL",
    "sg:address":"Zeehaanstraat 3",
    "sg:city":"Lutjegast",
    "sg:classifiers":[
        {
            "category":"Education",
            "subcategory":"Preschool",
            "type":"Public Place"
        }
    ],
    "sg:phone":"+31 594 612 192",
    "sg:postcode":"9866 AT",
    "sg:province":"Groningen",
    "sg:tags":[
        "kleuteronderwijs",
        "basis-"
    ],
    "wof:name":"Chr Basisschool 'T Fundament",
    "wof:placetype":"venue"
},
  "geometry": {"coordinates":[6.258454,53.233253],"type":"Point"}
}