{
  "type": "Feature",
  "properties": {
    "addr:full":"Wesselerweg 5 Enschede Overijssel 7544 RP",
    "addr:housenumber":"5",
    "addr:postcode":"7544 rp",
    "addr:street":"Wesselerweg",
    "iso:country":"NL",
    "sg:address":"Wesselerweg 5",
    "sg:city":"Enschede",
    "sg:orig_category":"Kinderopvang Behalve Thuis",
    "sg:phone":"+31 53 476 2865",
    "sg:postcode":"7544 RP",
    "sg:province":"Overijssel",
    "wof:name":"Kinderdagcentrum Klim Op",
    "wof:placetype":"venue"
},
  "geometry": {"coordinates":[6.875193,52.189762],"type":"Point"}
}