{
  "type": "Feature",
  "properties": {
    "addr:full":"Veemarktkd 8 S Hertogenbosch North Brabant 5222 AE",
    "addr:housenumber":"8",
    "addr:postcode":"5222 ae",
    "addr:street":"Veemarktkd",
    "iso:country":"NL",
    "sg:address":"Veemarktkd 8",
    "sg:city":"S Hertogenbosch",
    "sg:orig_category":"Projectontwikkeling",
    "sg:phone":"+31 73 623 2419",
    "sg:postcode":"5222 AE",
    "sg:province":"North Brabant",
    "sg:website":"http://www.omoprojecten.nl",
    "wof:name":"O2P",
    "wof:placetype":"venue"
},
  "geometry": {"coordinates":[5.286278,51.703072],"type":"Point"}
}