{
  "type": "Feature",
  "properties": {
    "addr:full":"Mgr Bekkersstr 25 Budel Noord-Brabant 6021 VW",
    "addr:housenumber":"25",
    "addr:postcode":"6021 vw",
    "addr:street":"Bekkersstr",
    "iso:country":"NL",
    "sg:address":"Mgr Bekkersstr 25",
    "sg:city":"Budel",
    "sg:orig_category":"Honden- En Kattentrimsalons",
    "sg:phone":"+31 495 496 484",
    "sg:postcode":"6021 VW",
    "sg:province":"Noord-Brabant",
    "wof:name":"Budie",
    "wof:placetype":"venue"
},
  "geometry": {"coordinates":[5.5676817894,51.2656097412],"type":"Point"}
}