{
  "type": "Feature",
  "properties": {
    "addr:full":"Flintplein 15 Amersfoort Utrecht 3811 WZ",
    "addr:housenumber":"15",
    "addr:postcode":"3811 wz",
    "addr:street":"Flintplein",
    "iso:country":"NL",
    "sg:address":"Flintplein 15",
    "sg:city":"Amersfoort",
    "sg:orig_category":"Diverse Grafische Activiteiten",
    "sg:phone":"+31 33 479 9132",
    "sg:postcode":"3811 WZ",
    "sg:province":"Utrecht",
    "wof:name":"Een Nacht Ijs, Ontwerpburo",
    "wof:placetype":"venue"
},
  "geometry": {"coordinates":[5.392635,52.158817],"type":"Point"}
}