{
  "type": "Feature",
  "properties": {
    "addr:full":"Leywg 890 S Gravenhage South Holland 2545 GT",
    "addr:housenumber":"890",
    "addr:postcode":"2545 gt",
    "addr:street":"S Gravenhage",
    "iso:country":"NL",
    "sg:address":"Leywg 890",
    "sg:city":"S Gravenhage",
    "sg:orig_category":"Banken",
    "sg:phone":"+31 70 371 8888",
    "sg:postcode":"2545 GT",
    "sg:province":"South Holland",
    "sg:website":"http://www.rabobank.nl",
    "wof:name":"Rabobank",
    "wof:placetype":"venue"
},
  "geometry": {"coordinates":[4.27049,52.05093],"type":"Point"}
}