{
  "type": "Feature",
  "properties": {
    "addr:full":"Willem Barentszstraat 1 Veenendaal Gelderland 3902 DE",
    "addr:housenumber":"1;3902",
    "addr:street":"Willem Barentszstraat;Gelderland;De",
    "iso:country":"NL",
    "sg:address":"Willem Barentszstraat 1",
    "sg:city":"Veenendaal",
    "sg:orig_category":"Woningbouwverenigingen",
    "sg:phone":"+31 318 548 583",
    "sg:postcode":"3902 DE",
    "sg:province":"Gelderland",
    "wof:name":"Woningstichting Buitenzorg",
    "wof:placetype":"venue"
},
  "geometry": {"coordinates":[5.5794568062,52.0343704224],"type":"Point"}
}