{
  "type": "Feature",
  "properties": {
    "addr:full":"Buitenruststraat 8 Middelburg Zeeland 4337 EH",
    "addr:housenumber":"8",
    "addr:postcode":"4337 eh",
    "addr:street":"Buitenruststraat",
    "iso:country":"NL",
    "sg:address":"Buitenruststraat 8",
    "sg:city":"Middelburg",
    "sg:classifiers":[
        {
            "category":"Professional",
            "subcategory":"Accounting & Tax Preparation",
            "type":"Services"
        }
    ],
    "sg:phone":"+31 118 671 100",
    "sg:postcode":"4337 EH",
    "sg:province":"Zeeland",
    "sg:tags":[
        "accountant"
    ],
    "wof:name":"Pricewaterhousecoopers Nv",
    "wof:placetype":"venue"
},
  "geometry": {"coordinates":[3.617684,51.492516],"type":"Point"}
}