{
  "type": "Feature",
  "properties": {
    "addr:full":"Planckstraat 7 Dordrecht Zuid-Holland 3316 GS",
    "addr:housenumber":"7",
    "addr:postcode":"3316 gs",
    "addr:street":"Planckstraat",
    "iso:country":"NL",
    "sg:address":"Planckstraat 7",
    "sg:city":"Dordrecht",
    "sg:orig_category":"Projectinrichting",
    "sg:phone":"+31 78 617 5344",
    "sg:postcode":"3316 GS",
    "sg:province":"Zuid-Holland",
    "wof:name":"Plan@Office",
    "wof:placetype":"venue"
},
  "geometry": {"coordinates":[4.635023,51.779224],"type":"Point"}
}