{
  "type": "Feature",
  "properties": {
    "addr:full":"Vonderwg 11 Eindhoven Noord-Brabant 5611 BK",
    "addr:housenumber":"11",
    "addr:postcode":"5611 bk",
    "addr:street":"Vonderwg",
    "iso:country":"NL",
    "sg:address":"Vonderwg 11",
    "sg:city":"Eindhoven",
    "sg:orig_category":"Adviesbureaus",
    "sg:phone":"+31 40 275 7747",
    "sg:postcode":"5611 BK",
    "sg:province":"Noord-Brabant",
    "wof:name":"Cqm Bv",
    "wof:placetype":"venue"
},
  "geometry": {"coordinates":[5.468741,51.440647],"type":"Point"}
}