{
  "type": "Feature",
  "properties": {
    "iso:country":"NL",
    "sg:address":"A V Leeuwenhoekstr 9",
    "sg:city":"Oud Beyerland",
    "sg:orig_category":"Geldtel- En Geldwisselautomaten",
    "sg:phone":"+31 186 643 364",
    "sg:postcode":"3261 LT",
    "sg:province":"Zuid-Holland",
    "sg:website":"http://www.veka-systems.nl",
    "wof:name":"Veka Systems Bv",
    "wof:placetype":"venue"
},
  "geometry": {"coordinates":[4.42806,51.807892],"type":"Point"}
}