{
  "type": "Feature",
  "properties": {
    "addr:full":"Moezel 81 Drachten Friesland 9204 EC",
    "addr:housenumber":"81",
    "addr:postcode":"9204 ec",
    "addr:street":"Moezel",
    "iso:country":"NL",
    "sg:address":"Moezel 81",
    "sg:city":"Drachten",
    "sg:orig_category":"Verenigingen En Stichtingen",
    "sg:phone":"+31 512 513 791",
    "sg:postcode":"9204 EC",
    "sg:province":"Friesland",
    "wof:name":"Reumapati\u00ebntenver Drachten Eo",
    "wof:placetype":"venue"
},
  "geometry": {"coordinates":[6.071116,53.096642],"type":"Point"}
}