{
  "type": "Feature",
  "properties": {
    "addr:full":"Bremhorstlaan 11 Wassenaar Zuid-Holland 2244 EN",
    "addr:housenumber":"11",
    "addr:postcode":"2244 en",
    "addr:street":"Bremhorstlaan",
    "iso:country":"NL",
    "sg:address":"Bremhorstlaan 11",
    "sg:city":"Wassenaar",
    "sg:orig_category":"Binnenhuisarchitecten",
    "sg:phone":"+31 70 517 9700",
    "sg:postcode":"2244 EN",
    "sg:province":"Zuid-Holland",
    "wof:name":"Arti & Disegno",
    "wof:placetype":"venue"
},
  "geometry": {"coordinates":[4.365115,52.11311],"type":"Point"}
}