{
  "type": "Feature",
  "properties": {
    "addr:full":"Markt 11 Etten-Leur Noord-Brabant 4875 CB",
    "addr:housenumber":"11",
    "addr:postcode":"4875 cb",
    "addr:street":"Markt",
    "iso:country":"NL",
    "sg:address":"Markt 11",
    "sg:city":"Etten-Leur",
    "sg:orig_category":"Verzekeringen",
    "sg:phone":"+31 76 501 2230",
    "sg:postcode":"4875 CB",
    "sg:province":"Noord-Brabant",
    "wof:name":"Roels Assurantien",
    "wof:placetype":"venue"
},
  "geometry": {"coordinates":[4.635298,51.570015],"type":"Point"}
}