{
  "type": "Feature",
  "properties": {
    "addr:full":"De Bunder 29 Vierlingsbeek North Brabant 5821 GC",
    "addr:housenumber":"29",
    "addr:postcode":"5821 gc",
    "addr:street":"De Bunder",
    "iso:country":"NL",
    "sg:address":"De Bunder 29",
    "sg:city":"Vierlingsbeek",
    "sg:orig_category":"Metselwerken",
    "sg:phone":"+31 478 631 691",
    "sg:postcode":"5821 GC",
    "sg:province":"North Brabant",
    "wof:name":"Nillesen, Metselwerken",
    "wof:placetype":"venue"
},
  "geometry": {"coordinates":[6.003463,51.598083],"type":"Point"}
}