{
  "type": "Feature",
  "properties": {
    "addr:full":"Pinksterbloem 20 Bennekom Gelderland 6721 RM",
    "addr:housenumber":"20",
    "addr:postcode":"6721 rm",
    "addr:street":"Pinksterbloem;Gelderland",
    "iso:country":"NL",
    "sg:address":"Pinksterbloem 20",
    "sg:city":"Bennekom",
    "sg:orig_category":"Onderhoudswerken",
    "sg:phone":"+31 318 414 455",
    "sg:postcode":"6721 RM",
    "sg:province":"Gelderland",
    "wof:name":"Schreuder",
    "wof:placetype":"venue"
},
  "geometry": {"coordinates":[5.662764,52.001835],"type":"Point"}
}