{
  "type": "Feature",
  "properties": {
    "addr:full":"Kooiln 19 Leiden Zuid-Holland 2315 EB",
    "addr:housenumber":"19",
    "addr:postcode":"2315 eb",
    "addr:street":"Kooiln",
    "iso:country":"NL",
    "sg:address":"Kooiln 19",
    "sg:city":"Leiden",
    "sg:classifiers":[
        {
            "category":"Food & Beverages",
            "subcategory":"Bakery",
            "type":"Retail Goods"
        }
    ],
    "sg:phone":"+31 71 523 0031",
    "sg:postcode":"2315 EB",
    "sg:province":"Zuid-Holland",
    "sg:tags":[
        "brood",
        "en",
        "banket"
    ],
    "wof:name":"Kempen, Van",
    "wof:placetype":"venue"
},
  "geometry": {"coordinates":[4.49463,52.154572],"type":"Point"}
}