{
  "type": "Feature",
  "properties": {
    "addr:full":"Hendrikln 2 Harmelen Utrecht 3481 VR",
    "addr:housenumber":"2",
    "addr:postcode":"3481 vr",
    "addr:street":"Hendrikln",
    "iso:country":"NL",
    "sg:address":"Hendrikln 2",
    "sg:city":"Harmelen",
    "sg:orig_category":"Kantinebeheer",
    "sg:phone":"+31 348 445 057",
    "sg:postcode":"3481 VR",
    "sg:province":"Utrecht",
    "wof:name":"Kroonkurk, De",
    "wof:placetype":"venue"
},
  "geometry": {"coordinates":[4.9637088776,52.0851097107],"type":"Point"}
}