{
  "type": "Feature",
  "properties": {
    "addr:full":"Molenvlietbrink 16-18 Woerden South Holland 3448 HM",
    "addr:housenumber":"16-18",
    "addr:postcode":"3448 hm",
    "addr:street":"Molenvlietbrink",
    "iso:country":"NL",
    "sg:address":"Molenvlietbrink 16-18",
    "sg:city":"Woerden",
    "sg:orig_category":"Postkantoren",
    "sg:phone":"+31 348 420 332",
    "sg:postcode":"3448 HM",
    "sg:province":"South Holland",
    "sg:website":"http://www.postkantoor.nl",
    "wof:name":"Postkantoor",
    "wof:placetype":"venue"
},
  "geometry": {"coordinates":[4.864104,52.078926],"type":"Point"}
}