{
  "type": "Feature",
  "properties": {
    "addr:full":"Gesterweg 17-19 Den Oever North Holland 1779 EG",
    "addr:housenumber":"17-19",
    "addr:postcode":"1779 eg",
    "addr:street":"Gesterweg",
    "iso:country":"NL",
    "sg:address":"Gesterweg 17-19",
    "sg:city":"Den Oever",
    "sg:orig_category":"Kampeerterreinen",
    "sg:phone":"+31 227 511 283",
    "sg:postcode":"1779 EG",
    "sg:province":"North Holland",
    "wof:name":"Camping De Gest",
    "wof:placetype":"venue"
},
  "geometry": {"coordinates":[5.0230998993,52.9315490723],"type":"Point"}
}