{
  "type": "Feature",
  "properties": {
    "addr:full":"Molenwerf 38A Koog A/D Zaan North Holland 1541 WR",
    "addr:housenumber":"38a;a / d",
    "addr:postcode":"1541 wr",
    "addr:street":"Molenwerf;Zaan North",
    "iso:country":"NL",
    "sg:address":"Molenwerf 38A",
    "sg:city":"Koog A/D Zaan",
    "sg:orig_category":"Visspeciaalzaken",
    "sg:phone":"+31 75 617 8209",
    "sg:postcode":"1541 WR",
    "sg:province":"North Holland",
    "wof:name":"Visspeciaalzaak Runderkamp",
    "wof:placetype":"venue"
},
  "geometry": {"coordinates":[4.800906,52.462749],"type":"Point"}
}