{
  "type": "Feature",
  "properties": {
    "addr:full":"Burg Boreelstr 7 Castricum Noord-Holland 1901 BC",
    "addr:housenumber":"7",
    "addr:postcode":"1901 bc",
    "addr:street":"Burg Boreelstr",
    "iso:country":"NL",
    "sg:address":"Burg Boreelstr 7",
    "sg:city":"Castricum",
    "sg:orig_category":"Makelaars En Adviseurs Schepen En Jachten",
    "sg:phone":"+31 251 652 447",
    "sg:postcode":"1901 BC",
    "sg:province":"Noord-Holland",
    "wof:name":"Lunstroo Jr, H",
    "wof:placetype":"venue"
},
  "geometry": {"coordinates":[4.661334,52.54974],"type":"Point"}
}