{
  "type": "Feature",
  "properties": {
    "addr:full":"Wilgenlaan 68 Zwanenburg Noord-Holland 1161 JN",
    "addr:housenumber":"68",
    "addr:postcode":"1161 jn",
    "addr:street":"Wilgenlaan",
    "iso:country":"NL",
    "sg:address":"Wilgenlaan 68",
    "sg:city":"Zwanenburg",
    "sg:orig_category":"Diverse Bedrijfsinstallaties Gh",
    "sg:phone":"+31 20 407 9800",
    "sg:postcode":"1161 JN",
    "sg:province":"Noord-Holland",
    "wof:name":"Ksb Nederland Bv",
    "wof:placetype":"venue"
},
  "geometry": {"coordinates":[4.7558689117,52.3749542236],"type":"Point"}
}