{
  "type": "Feature",
  "properties": {
    "iso:country":"NL",
    "sg:address":"Grt Beer 3",
    "sg:city":"Hoorn Nh",
    "sg:orig_category":"Verenigingen En Stichtingen",
    "sg:phone":"+31 229 280 946",
    "sg:postcode":"1622 ES",
    "sg:province":"North Holland",
    "wof:name":"Dienstverl Gehandikapten, Sticht",
    "wof:placetype":"venue"
},
  "geometry": {"coordinates":[5.037234,52.639194],"type":"Point"}
}