{
  "type": "Feature",
  "properties": {
    "iso:country":"NL",
    "sg:address":"Terschellingkd 52",
    "sg:city":"Woerden",
    "sg:orig_category":"Grafisch Ontwerpers",
    "sg:phone":"+31 6 26822548",
    "sg:postcode":"3446 BK",
    "sg:province":"Utrecht",
    "sg:website":"http://www.ozza.nl",
    "wof:name":"Ozza",
    "wof:placetype":"venue"
},
  "geometry": {"coordinates":[4.903333,52.084717],"type":"Point"}
}