{
  "type": "Feature",
  "properties": {
    "addr:full":"Rompert Pk 27 S Hertogenbosch Noord-Brabant 5233 RJ",
    "addr:postcode":"5233 rj",
    "addr:street":"Rompert Pk 27 S",
    "iso:country":"NL",
    "sg:address":"Rompert Pk 27",
    "sg:city":"S Hertogenbosch",
    "sg:orig_category":"Bijouterie?n - Fabrieken En Groothandel",
    "sg:phone":"+31 73 642 3778",
    "sg:postcode":"5233 RJ",
    "sg:province":"Noord-Brabant",
    "wof:name":"Thomas Trading",
    "wof:placetype":"venue"
},
  "geometry": {"coordinates":[5.310871,51.713531],"type":"Point"}
}