{
  "type": "Feature",
  "properties": {
    "iso:country":"NL",
    "sg:address":"Pelsestr 12",
    "sg:city":"Heusden Gem Heusd",
    "sg:orig_category":"Vertaalbureaus",
    "sg:phone":"+31 416 665 285",
    "sg:postcode":"5256 AT",
    "sg:province":"Noord-Brabant",
    "wof:name":"Cichocki",
    "wof:placetype":"venue"
},
  "geometry": {"coordinates":[5.138655,51.733814],"type":"Point"}
}