{
  "type": "Feature",
  "properties": {
    "addr:full":"Zwanenkamp 921 Maarssen Utrecht 3607 PX",
    "addr:housenumber":"921",
    "addr:postcode":"3607 px",
    "addr:street":"Zwanenkamp",
    "iso:country":"NL",
    "sg:address":"Zwanenkamp 921",
    "sg:city":"Maarssen",
    "sg:orig_category":"Vertaalbureaus",
    "sg:phone":"+31 346 569 975",
    "sg:postcode":"3607 PX",
    "sg:province":"Utrecht",
    "wof:name":"Vak",
    "wof:placetype":"venue"
},
  "geometry": {"coordinates":[5.010122,52.143387],"type":"Point"}
}