{
  "type": "Feature",
  "properties": {
    "addr:full":"Ijssellaan 3A Ouderkerk A/D Ijssel South Holland 2935 CV",
    "addr:housenumber":"3a;a / d",
    "addr:postcode":"2935 cv",
    "addr:street":"Ijssellaan;Ijssel South",
    "iso:country":"NL",
    "sg:address":"Ijssellaan 3A",
    "sg:city":"Ouderkerk A/D Ijssel",
    "sg:orig_category":"Onderhoud And Reparatie Kantoorapparatuur",
    "sg:phone":"+31 180 687 048",
    "sg:postcode":"2935 CV",
    "sg:province":"South Holland",
    "wof:name":"Bosware",
    "wof:placetype":"venue"
},
  "geometry": {"coordinates":[4.632741,51.968258],"type":"Point"}
}