{
  "type": "Feature",
  "properties": {
    "addr:full":"1E Weerdswg 10 Deventer Overijssel 7412 WS",
    "addr:housenumber":"10",
    "addr:postcode":"7412 ws",
    "addr:street":"1E Weerdswg",
    "iso:country":"NL",
    "sg:address":"1E Weerdswg 10",
    "sg:city":"Deventer",
    "sg:orig_category":"Adviesbureaus Bedrijfsorganisatie",
    "sg:phone":"+31 570 671 387",
    "sg:postcode":"7412 WS",
    "sg:province":"Overijssel",
    "wof:name":"Hofman, Joop",
    "wof:placetype":"venue"
},
  "geometry": {"coordinates":[6.146964,52.259869],"type":"Point"}
}