{
  "type": "Feature",
  "properties": {
    "addr:full":"Ganzenmarkt 1 Oldenzaal NL.08 7571 CD",
    "addr:housenumber":"1;nl.08",
    "addr:postcode":"7571 cd",
    "addr:street":"Ganzenmarkt",
    "iso:country":"NL",
    "sg:address":"Ganzenmarkt 1",
    "sg:city":"Oldenzaal",
    "sg:orig_category":"Overheidsdiensten",
    "sg:phone":"+31 541 588 111",
    "sg:postcode":"7571 CD",
    "sg:province":"NL.08",
    "wof:name":"Gemeente Oldenzaal",
    "wof:placetype":"venue"
},
  "geometry": {"coordinates":[6.9301691055,52.312412262],"type":"Point"}
}