{
  "type": "Feature",
  "properties": {
    "iso:country":"NL",
    "sg:address":"Keetweg 9",
    "sg:city":"Arnemuiden",
    "sg:orig_category":"Metaalbekleding And -Behandeling",
    "sg:phone":"+31 118 603 745",
    "sg:postcode":"4341 BJ",
    "sg:province":"Zeeland",
    "wof:name":"Draaicentrum",
    "wof:placetype":"venue"
},
  "geometry": {"coordinates":[3.662899,51.499096],"type":"Point"}
}