{
  "type": "Feature",
  "properties": {
    "addr:full":"Meerstraat 24 Hillegom Zuid-Holland 2181 BR",
    "addr:housenumber":"24",
    "addr:postcode":"2181 br",
    "addr:street":"Meerstraat",
    "iso:country":"NL",
    "sg:address":"Meerstraat 24",
    "sg:city":"Hillegom",
    "sg:orig_category":"Verlichting And Huishoudartikelen",
    "sg:phone":"+31 252 523 043",
    "sg:postcode":"2181 BR",
    "sg:province":"Zuid-Holland",
    "wof:name":"Tapijtspeciaalzaak Engelkes",
    "wof:placetype":"venue"
},
  "geometry": {"coordinates":[4.581536,52.292553],"type":"Point"}
}