{
  "type": "Feature",
  "properties": {
    "addr:full":"Vliegwiel 20 Oudeschild Noord-Holland 1792 CS",
    "addr:housenumber":"20",
    "addr:postcode":"1792 cs",
    "addr:street":"Vliegwiel",
    "iso:country":"NL",
    "sg:address":"Vliegwiel 20",
    "sg:city":"Oudeschild",
    "sg:orig_category":"Mensendieck - Oefentherapeuten",
    "sg:phone":"+31 222 315 405",
    "sg:postcode":"1792 CS",
    "sg:province":"Noord-Holland",
    "wof:name":"Schraag-Van De Wetering, Bianca",
    "wof:placetype":"venue"
},
  "geometry": {"coordinates":[4.846532,53.043873],"type":"Point"}
}