{
  "type": "Feature",
  "properties": {
    "addr:full":"Tongersepln 17 Maastricht Limburg 6211 LW",
    "addr:housenumber":"17",
    "addr:postcode":"6211 lw",
    "addr:street":"Tongersepln",
    "iso:country":"NL",
    "sg:address":"Tongersepln 17",
    "sg:city":"Maastricht",
    "sg:orig_category":"Makelaars En Adviseurs Onroerende Goederen",
    "sg:phone":"+31 43 321 2867",
    "sg:postcode":"6211 LW",
    "sg:province":"Limburg",
    "wof:name":"Theunissen Bv, H",
    "wof:placetype":"venue"
},
  "geometry": {"coordinates":[5.681809,50.84444],"type":"Point"}
}