{
  "type": "Feature",
  "properties": {
    "addr:full":"Zandstr 139 Beneden Leeuwen Gelderland 6658 CS",
    "addr:housenumber":"139",
    "addr:postcode":"6658 cs",
    "iso:country":"NL",
    "sg:address":"Zandstr 139",
    "sg:city":"Beneden Leeuwen",
    "sg:orig_category":"Bloemen En Planten",
    "sg:phone":"+31 487 591 597",
    "sg:postcode":"6658 CS",
    "sg:province":"Gelderland",
    "sg:website":"http://www.deagave.nl",
    "wof:name":"Agave, De",
    "wof:placetype":"venue"
},
  "geometry": {"coordinates":[5.506868,51.880444],"type":"Point"}
}