{
  "type": "Feature",
  "properties": {
    "addr:full":"Gildeplein 4 Purmerend Noord-Holland 1445 BP",
    "addr:housenumber":"4",
    "addr:postcode":"1445 bp",
    "addr:street":"Gildeplein",
    "iso:country":"NL",
    "sg:address":"Gildeplein 4",
    "sg:city":"Purmerend",
    "sg:orig_category":"Banken And Kredietinstellingen",
    "sg:phone":"+31 299 640 246",
    "sg:postcode":"1445 BP",
    "sg:province":"Noord-Holland",
    "wof:name":"Fortis Bank",
    "wof:placetype":"venue"
},
  "geometry": {"coordinates":[4.985933,52.505825],"type":"Point"}
}