{
  "type": "Feature",
  "properties": {
    "addr:full":"Breitnerln 45 S Gravenhage Zuid-Holland 2596 GW",
    "addr:housenumber":"45;gravenhage",
    "addr:postcode":"2596 gw",
    "addr:street":"Breitnerln;S",
    "iso:country":"NL",
    "sg:address":"Breitnerln 45",
    "sg:city":"S Gravenhage",
    "sg:orig_category":"Adviesbureaus Bedrijfsorganisatie",
    "sg:phone":"+31 70 326 2412",
    "sg:postcode":"2596 GW",
    "sg:province":"Zuid-Holland",
    "wof:name":"Mk Konsult",
    "wof:placetype":"venue"
},
  "geometry": {"coordinates":[4.31846,52.093311],"type":"Point"}
}