{
  "type": "Feature",
  "properties": {
    "addr:full":"Engweg 8 Putten Gelderland 3882 AL",
    "addr:housenumber":"8",
    "addr:postcode":"3882",
    "addr:street":"Engweg;Gelderland",
    "iso:country":"NL",
    "sg:address":"Engweg 8",
    "sg:city":"Putten",
    "sg:orig_category":"Paramedische Behandelingen",
    "sg:phone":"+31 341 438 823",
    "sg:postcode":"3882 AL",
    "sg:province":"Gelderland",
    "wof:name":"Icare Thuiszorg Veluwe",
    "wof:placetype":"venue"
},
  "geometry": {"coordinates":[5.60168,52.258327],"type":"Point"}
}