{
  "type": "Feature",
  "properties": {
    "addr:full":"Stadhouderskade 23 B Amsterdam North Holland 1054 ES",
    "addr:housenumber":"23 b",
    "addr:postcode":"1054 es",
    "addr:street":"Stadhouderskade",
    "iso:country":"NL",
    "sg:address":"Stadhouderskade 23 B",
    "sg:city":"Amsterdam",
    "sg:orig_category":"Luchtvaart",
    "sg:phone":"+31 20 412 0302",
    "sg:postcode":"1054 ES",
    "sg:province":"North Holland",
    "wof:name":"China Southern Airlines",
    "wof:placetype":"venue"
},
  "geometry": {"coordinates":[4.881261,52.361938],"type":"Point"}
}