{
  "type": "Feature",
  "properties": {
    "addr:full":"Hoofdstr 23 Eenrum Groningen 9967 RJ",
    "addr:housenumber":"23",
    "addr:postcode":"9967 rj",
    "addr:street":"Hoofdstr",
    "iso:country":"NL",
    "sg:address":"Hoofdstr 23",
    "sg:city":"Eenrum",
    "sg:orig_category":"Verenigingsgebouwen",
    "sg:phone":"+31 595 491 357",
    "sg:postcode":"9967 RJ",
    "sg:province":"Groningen",
    "wof:name":"Jeugdhaven",
    "wof:placetype":"venue"
},
  "geometry": {"coordinates":[6.458664,53.364929],"type":"Point"}
}