{
  "type": "Feature",
  "properties": {
    "addr:full":"Ln V De Sport 5 Hoogezand Groningen 9603 TG",
    "addr:housenumber":"5",
    "addr:postcode":"9603 tg",
    "addr:street":"Ln V De Sport",
    "iso:country":"NL",
    "sg:address":"Ln V De Sport 5",
    "sg:city":"Hoogezand",
    "sg:orig_category":"Verenigingen En Stichtingen",
    "sg:phone":"+31 598 325 243",
    "sg:postcode":"9603 TG",
    "sg:province":"Groningen",
    "wof:name":"Aktiviteitencentr",
    "wof:placetype":"venue"
},
  "geometry": {"coordinates":[6.79338,53.12278],"type":"Point"}
}