{
  "type": "Feature",
  "properties": {
    "addr:full":"Burg. De Beaufortplein 13 Markelo Overijssel 7475 AG",
    "addr:housenumber":"13",
    "addr:postcode":"7475",
    "addr:street":"Burg. De Beaufortplein",
    "iso:country":"NL",
    "sg:address":"Burg. De Beaufortplein 13",
    "sg:city":"Markelo",
    "sg:orig_category":"Verzekeringen",
    "sg:phone":"+31 547 362 020",
    "sg:postcode":"7475 AG",
    "sg:province":"Overijssel",
    "wof:name":"Unive Oost",
    "wof:placetype":"venue"
},
  "geometry": {"coordinates":[6.494653,52.233772],"type":"Point"}
}