{
  "type": "Feature",
  "properties": {
    "addr:full":"Jan Steenstraat 13 Oisterwijk Noord-Brabant 5062 LP",
    "addr:housenumber":"13",
    "addr:postcode":"5062 lp",
    "addr:street":"Jan Steenstraat",
    "iso:country":"NL",
    "sg:address":"Jan Steenstraat 13",
    "sg:city":"Oisterwijk",
    "sg:orig_category":"Architecten",
    "sg:phone":"+31 13 522 0999",
    "sg:postcode":"5062 LP",
    "sg:province":"Noord-Brabant",
    "wof:name":"Ing. M.A.C.N.M. Ogier",
    "wof:placetype":"venue"
},
  "geometry": {"coordinates":[5.184794,51.57357],"type":"Point"}
}