{
  "type": "Feature",
  "properties": {
    "addr:full":"Keelakker 28 Kaatsheuvel Noord-Brabant 5171 VZ",
    "addr:housenumber":"28",
    "addr:postcode":"5171 vz",
    "addr:street":"Keelakker",
    "iso:country":"NL",
    "sg:address":"Keelakker 28",
    "sg:city":"Kaatsheuvel",
    "sg:orig_category":"Schilders",
    "sg:phone":"+31 416 282 878",
    "sg:postcode":"5171 VZ",
    "sg:province":"Noord-Brabant",
    "wof:name":"Verschut, Rob",
    "wof:placetype":"venue"
},
  "geometry": {"coordinates":[5.034726,51.652874],"type":"Point"}
}