{
  "type": "Feature",
  "properties": {
    "addr:full":"Oeverkruid 3 Raamsdonksveer North Brabant 4941 VV",
    "addr:housenumber":"3",
    "addr:postcode":"4941 vv",
    "addr:street":"Oeverkruid",
    "iso:country":"NL",
    "sg:address":"Oeverkruid 3",
    "sg:city":"Raamsdonksveer",
    "sg:orig_category":"Autokeuringen",
    "sg:phone":"+31 162 521 397",
    "sg:postcode":"4941 VV",
    "sg:province":"North Brabant",
    "wof:name":"Autoschadebedrijf Van Damme",
    "wof:placetype":"venue"
},
  "geometry": {"coordinates":[4.884369,51.708965],"type":"Point"}
}