{
  "type": "Feature",
  "properties": {
    "iso:country":"NL",
    "sg:address":"St Joostdk 61",
    "sg:city":"Oosterland",
    "sg:orig_category":"Voetbalverenigingen",
    "sg:phone":"+31 111 642 648",
    "sg:postcode":"4307 AS",
    "sg:province":"Zeeland",
    "wof:name":"Duiveland",
    "wof:placetype":"venue"
},
  "geometry": {"coordinates":[4.040928,51.649048],"type":"Point"}
}