{
  "type": "Feature",
  "properties": {
    "addr:full":"Metaalhof 57B Rotterdam Zuid-Holland 3067 GM",
    "addr:housenumber":"57b",
    "addr:postcode":"3067 gm",
    "addr:street":"Metaalhof",
    "iso:country":"NL",
    "sg:address":"Metaalhof 57B",
    "sg:city":"Rotterdam",
    "sg:orig_category":"Fitnesscentra",
    "sg:phone":"+31 10 455 7074",
    "sg:postcode":"3067 GM",
    "sg:province":"Zuid-Holland",
    "sg:website":"http://www.studioalexander",
    "wof:name":"Slender You Studio Alexander",
    "wof:placetype":"venue"
},
  "geometry": {"coordinates":[4.543849,51.948837],"type":"Point"}
}