{
  "type": "Feature",
  "properties": {
    "addr:full":"Ged Molenwyk 59 Heerenveen Provincie Friesland 8442 BH",
    "addr:housenumber":"59",
    "addr:postcode":"8442 bh",
    "addr:street":"Provincie Friesland",
    "iso:country":"NL",
    "sg:address":"Ged Molenwyk 59",
    "sg:city":"Heerenveen",
    "sg:orig_category":"Bedden En Matrassen",
    "sg:phone":"+31 513 624 836",
    "sg:postcode":"8442 BH",
    "sg:province":"Provincie Friesland",
    "wof:name":"Droomparadijs",
    "wof:placetype":"venue"
},
  "geometry": {"coordinates":[5.9290947914,52.9584503174],"type":"Point"}
}