{
  "type": "Feature",
  "properties": {
    "addr:full":"Mariastr 1 Utrecht Utrecht 3511 LN",
    "addr:housenumber":"1",
    "addr:postcode":"3511 ln",
    "addr:street":"Mariastr",
    "iso:country":"NL",
    "sg:address":"Mariastr 1",
    "sg:city":"Utrecht",
    "sg:orig_category":"Sportschoenen - Winkels",
    "sg:phone":"+31 30 236 9994",
    "sg:postcode":"3511 LN",
    "sg:province":"Utrecht",
    "wof:name":"Coach",
    "wof:placetype":"venue"
},
  "geometry": {"coordinates":[5.116987,52.090721],"type":"Point"}
}