{
  "type": "Feature",
  "properties": {
    "iso:country":"NL",
    "sg:address":"Noordvliet 13",
    "sg:city":"Leeuwarden",
    "sg:orig_category":"Discotheken",
    "sg:phone":"+31 58 212 6082",
    "sg:postcode":"8921 GD",
    "sg:province":"Provincie Friesland",
    "wof:name":"Incognito",
    "wof:placetype":"venue"
},
  "geometry": {"coordinates":[5.810602,53.20327],"type":"Point"}
}