{
  "type": "Feature",
  "properties": {
    "addr:full":"Goirkestr 80 Tilburg Noord-Brabant 5046 GM",
    "addr:housenumber":"80",
    "addr:postcode":"5046 gm",
    "addr:street":"Goirkestr",
    "iso:country":"NL",
    "sg:address":"Goirkestr 80",
    "sg:city":"Tilburg",
    "sg:orig_category":"Verenigingen En Stichtingen",
    "sg:phone":"+31 13 536 6772",
    "sg:postcode":"5046 GM",
    "sg:province":"Noord-Brabant",
    "wof:name":"Sirkulo Antiyano",
    "wof:placetype":"venue"
},
  "geometry": {"coordinates":[5.079924,51.571583],"type":"Point"}
}