{
  "type": "Feature",
  "properties": {
    "iso:country":"NL",
    "sg:address":"Asselsestr 137",
    "sg:city":"Apeldoorn",
    "sg:orig_category":"Woningbureaus",
    "sg:phone":"+31 55 378 1460",
    "sg:postcode":"7311 EJ",
    "sg:province":"Gelderland",
    "sg:website":"http://www.wbawonen.nl",
    "wof:name":"Wba",
    "wof:placetype":"venue"
},
  "geometry": {"coordinates":[5.9516620636,52.2114334106],"type":"Point"}
}