{
  "type": "Feature",
  "properties": {
    "iso:country":"NL",
    "sg:address":"Zuidzijde 94",
    "sg:city":"Bodegraven",
    "sg:orig_category":"Wegen And Sportterreinen",
    "sg:phone":"+31 172 614 344",
    "sg:postcode":"2411 RV",
    "sg:province":"Zuid-Holland",
    "wof:name":"Has",
    "wof:placetype":"venue"
},
  "geometry": {"coordinates":[4.7475471497,52.0855522156],"type":"Point"}
}