{
  "type": "Feature",
  "properties": {
    "addr:full":"Zuidzijde 94 Bodegraven Zuid-Holland 2411 RV",
    "addr:housenumber":"94",
    "addr:postcode":"2411 rv",
    "addr:street":"Zuidzijde",
    "iso:country":"NL",
    "sg:address":"Zuidzijde 94",
    "sg:city":"Bodegraven",
    "sg:orig_category":"Wegen And Sportterreinen",
    "sg:phone":"+31 172 614 344",
    "sg:postcode":"2411 RV",
    "sg:province":"Zuid-Holland",
    "wof:name":"Has",
    "wof:placetype":"venue"
},
  "geometry": {"coordinates":[4.7475471497,52.0855522156],"type":"Point"}
}