{
  "type": "Feature",
  "properties": {
    "addr:full":"Steenpoortestr 43 Andyk Noord-Holland 1619 CV",
    "addr:housenumber":"43",
    "addr:postcode":"1619 cv",
    "addr:street":"Steenpoortestr",
    "iso:country":"NL",
    "sg:address":"Steenpoortestr 43",
    "sg:city":"Andyk",
    "sg:orig_category":"Voetbalverenigingen",
    "sg:phone":"+31 228 593 043",
    "sg:postcode":"1619 CV",
    "sg:province":"Noord-Holland",
    "wof:name":"Andijk Vv",
    "wof:placetype":"venue"
},
  "geometry": {"coordinates":[5.183512,52.739319],"type":"Point"}
}