{
  "type": "Feature",
  "properties": {
    "iso:country":"NL",
    "sg:address":"Hamersestraat 21",
    "sg:city":"Westervoort",
    "sg:orig_category":"Koeriersdiensten",
    "sg:phone":"+31 26 311 2566",
    "sg:postcode":"6931 EV",
    "sg:province":"Gelderland",
    "wof:name":"Data Delivery Service D.D.S.",
    "wof:placetype":"venue"
},
  "geometry": {"coordinates":[5.975544,51.963181],"type":"Point"}
}