{
  "type": "Feature",
  "properties": {
    "addr:full":"G Bruningstr 22 Eindhoven Noord-Brabant 5644 RR",
    "addr:housenumber":"22",
    "addr:postcode":"5644 rr",
    "iso:country":"NL",
    "sg:address":"G Bruningstr 22",
    "sg:city":"Eindhoven",
    "sg:orig_category":"Bloemen En Planten - Decoratie",
    "sg:phone":"+31 40 211 6931",
    "sg:postcode":"5644 RR",
    "sg:province":"Noord-Brabant",
    "wof:name":"Lbflowers",
    "wof:placetype":"venue"
},
  "geometry": {"coordinates":[5.483285,51.41935],"type":"Point"}
}