{
  "type": "Feature",
  "properties": {
    "addr:full":"Grote Beerstraat 9 Zwijndrecht South Holland 3331 TA",
    "addr:housenumber":"9",
    "addr:postcode":"3331 ta",
    "addr:street":"Grote Beerstraat",
    "iso:country":"NL",
    "sg:address":"Grote Beerstraat 9",
    "sg:city":"Zwijndrecht",
    "sg:classifiers":[
        {
            "category":"Fast Food",
            "type":"Food & Drink"
        }
    ],
    "sg:phone":"+31 78 619 5129",
    "sg:postcode":"3331 TA",
    "sg:province":"South Holland",
    "sg:tags":[
        "afhaal",
        "restaurant"
    ],
    "wof:name":"Meihao",
    "wof:placetype":"venue"
},
  "geometry": {"coordinates":[4.637764,51.819996],"type":"Point"}
}