{
  "type": "Feature",
  "properties": {
    "addr:full":"Dokter Kanterslaan 246 Grave North Brabant 5361 NL",
    "addr:housenumber":"246",
    "addr:postcode":"5361 nl",
    "addr:street":"Dokter Kanterslaan",
    "iso:country":"NL",
    "sg:address":"Dokter Kanterslaan 246",
    "sg:city":"Grave",
    "sg:orig_category":"Boekenuitgeverijen",
    "sg:phone":"+31 486 471 193",
    "sg:postcode":"5361 NL",
    "sg:province":"North Brabant",
    "wof:name":"Jos Linders Instituut V Computerboekhoud",
    "wof:placetype":"venue"
},
  "geometry": {"coordinates":[5.750783,51.753597],"type":"Point"}
}