{
  "type": "Feature",
  "properties": {
    "addr:full":"Oranje Nassaustraat 4 Valkenswaard Noord-Brabant 5554 AG",
    "addr:housenumber":"4",
    "addr:postcode":"5554",
    "addr:street":"Oranje Nassaustraat",
    "iso:country":"NL",
    "sg:address":"Oranje Nassaustraat 4",
    "sg:city":"Valkenswaard",
    "sg:classifiers":[
        {
            "category":"Communications",
            "subcategory":"Television Station",
            "type":"Services"
        }
    ],
    "sg:phone":"+31 40 204 4744",
    "sg:postcode":"5554 AG",
    "sg:province":"Noord-Brabant",
    "sg:tags":[
        "video",
        "audio",
        "verhuur"
    ],
    "wof:name":"Videoland Valkenswaard",
    "wof:placetype":"venue"
},
  "geometry": {"coordinates":[5.459196,51.354267],"type":"Point"}
}