{
  "type": "Feature",
  "properties": {
    "iso:country":"NL",
    "sg:address":"Couwenhoven 2809",
    "sg:city":"Zeist",
    "sg:orig_category":"Accountants - Administratie- Consulenten En -Kantoren",
    "sg:phone":"+31 30 695 7529",
    "sg:postcode":"3703 VS",
    "sg:province":"Utrecht",
    "wof:name":"Verbeek, A G",
    "wof:placetype":"venue"
},
  "geometry": {"coordinates":[5.219151,52.080807],"type":"Point"}
}