{
  "type": "Feature",
  "properties": {
    "iso:country":"NL",
    "sg:address":"Stadionln 26",
    "sg:city":"Almelo",
    "sg:orig_category":"Fitnesscentra",
    "sg:phone":"+31 546 568 222",
    "sg:postcode":"7606 JZ",
    "sg:province":"Overijssel",
    "sg:website":"http://www.fit-care.nl",
    "wof:name":"Fit-Care Center Almelo",
    "wof:placetype":"venue"
},
  "geometry": {"coordinates":[6.664543,52.354954],"type":"Point"}
}