{
  "type": "Feature",
  "properties": {
    "addr:full":"Ulsda 7 Beerta Groningen 9686 XW",
    "addr:housenumber":"7",
    "addr:postcode":"9686 xw",
    "addr:street":"Ulsda",
    "iso:country":"NL",
    "sg:address":"Ulsda 7",
    "sg:city":"Beerta",
    "sg:orig_category":"Goederenvervoer Over De Weg",
    "sg:phone":"+31 597 655 286",
    "sg:postcode":"9686 XW",
    "sg:province":"Groningen",
    "wof:name":"Transportbedrijf Feringa",
    "wof:placetype":"venue"
},
  "geometry": {"coordinates":[7.137482,53.159389],"type":"Point"}
}