{
  "type": "Feature",
  "properties": {
    "iso:country":"NL",
    "sg:address":"Stryenln 59",
    "sg:city":"Breda",
    "sg:orig_category":"Bedrijfsopleidingen",
    "sg:phone":"+31 76 564 0021",
    "sg:postcode":"4835 RD",
    "sg:province":"Noord-Brabant",
    "wof:name":"Ctg",
    "wof:placetype":"venue"
},
  "geometry": {"coordinates":[4.78509,51.569248],"type":"Point"}
}