{
  "type": "Feature",
  "properties": {
    "addr:full":"Vyverwg 14 Rotterdam Zuid-Holland 3062 JP",
    "addr:housenumber":"14",
    "addr:postcode":"3062 jp",
    "addr:street":"Vyverwg",
    "iso:country":"NL",
    "sg:address":"Vyverwg 14",
    "sg:city":"Rotterdam",
    "sg:classifiers":[
        {
            "category":"Professional",
            "subcategory":"Management & Consulting",
            "type":"Services"
        }
    ],
    "sg:phone":"+31 10 414 5629",
    "sg:postcode":"3062 JP",
    "sg:province":"Zuid-Holland",
    "sg:tags":[
        "relation",
        "adviesbureaus",
        "public"
    ],
    "wof:name":"Barkmeijer, A",
    "wof:placetype":"venue"
},
  "geometry": {"coordinates":[4.516287,51.920628],"type":"Point"}
}