{
  "type": "Feature",
  "properties": {
    "addr:full":"Europaweg 24 Heerde Gelderland 8181 BH",
    "addr:housenumber":"24",
    "addr:postcode":"8181 bh",
    "addr:street":"Europaweg;Gelderland",
    "iso:country":"NL",
    "sg:address":"Europaweg 24",
    "sg:city":"Heerde",
    "sg:orig_category":"Chemische Producten Gh",
    "sg:phone":"+31 578 692 058",
    "sg:postcode":"8181 BH",
    "sg:province":"Gelderland",
    "wof:name":"Heideveld Polyester Bv",
    "wof:placetype":"venue"
},
  "geometry": {"coordinates":[6.046558,52.398365],"type":"Point"}
}