{
  "type": "Feature",
  "properties": {
    "addr:full":"Parlevinker 4 Amsterdam North Holland 1034 PZ",
    "addr:housenumber":"4",
    "addr:postcode":"1034 pz",
    "addr:street":"Parlevinker",
    "iso:country":"NL",
    "sg:address":"Parlevinker 4",
    "sg:city":"Amsterdam",
    "sg:classifiers":[
        {
            "category":"Fast Food",
            "type":"Food & Drink"
        }
    ],
    "sg:phone":"+31 20 633 2500",
    "sg:postcode":"1034 PZ",
    "sg:province":"North Holland",
    "sg:tags":[
        "afhaal",
        "restaurant"
    ],
    "wof:name":"Snackbar-Afhaalcentrum Garuda",
    "wof:placetype":"venue"
},
  "geometry": {"coordinates":[4.922118,52.411663],"type":"Point"}
}