{
  "type": "Feature",
  "properties": {
    "addr:full":"Glacisstr 165 Vlissingen Zeeland 4381 SE",
    "addr:housenumber":"165",
    "addr:postcode":"4381 se",
    "iso:country":"NL",
    "sg:address":"Glacisstr 165",
    "sg:city":"Vlissingen",
    "sg:orig_category":"Veiligheidsuitrusting En -Kleding",
    "sg:phone":"+31 118 411 290",
    "sg:postcode":"4381 SE",
    "sg:province":"Zeeland",
    "wof:name":"North Safety Europoe Bv",
    "wof:placetype":"venue"
},
  "geometry": {"coordinates":[3.578675,51.44693],"type":"Point"}
}