{
  "type": "Feature",
  "properties": {
    "addr:full":"Grt Staat 20 Maastricht Limburg 6211 CW",
    "addr:housenumber":"20",
    "addr:postcode":"6211 cw",
    "addr:street":"Staat",
    "iso:country":"NL",
    "sg:address":"Grt Staat 20",
    "sg:city":"Maastricht",
    "sg:orig_category":"Herenkleding",
    "sg:phone":"+31 43 351 0640",
    "sg:postcode":"6211 CW",
    "sg:province":"Limburg",
    "wof:name":"Nyaki",
    "wof:placetype":"venue"
},
  "geometry": {"coordinates":[5.691595,50.849945],"type":"Point"}
}