{
  "type": "Feature",
  "properties": {
    "addr:full":"Westhaven 65 Gouda Zuid-Holland 2801 PN",
    "addr:housenumber":"65",
    "addr:postcode":"2801 pn",
    "addr:street":"Westhaven",
    "iso:country":"NL",
    "sg:address":"Westhaven 65",
    "sg:city":"Gouda",
    "sg:orig_category":"Adviesbureaus Bedrijfsorganisatie",
    "sg:phone":"+31 182 504 455",
    "sg:postcode":"2801 PN",
    "sg:province":"Zuid-Holland",
    "sg:website":"http://www.contakt.nl",
    "wof:name":"Contakt Bv",
    "wof:placetype":"venue"
},
  "geometry": {"coordinates":[4.713,52.007362],"type":"Point"}
}