{
  "type": "Feature",
  "properties": {
    "addr:full":"Eendrachtstraat 8 Olst Overijssel 8121 AJ",
    "addr:housenumber":"8",
    "addr:postcode":"8121 aj",
    "addr:street":"Eendrachtstraat",
    "iso:country":"NL",
    "sg:address":"Eendrachtstraat 8",
    "sg:city":"Olst",
    "sg:orig_category":"Bloemen And Planten",
    "sg:phone":"+31 570 561 340",
    "sg:postcode":"8121 AJ",
    "sg:province":"Overijssel",
    "wof:name":"Bloemsierkunst En Tuincentrum J. Hollegi",
    "wof:placetype":"venue"
},
  "geometry": {"coordinates":[6.109251,52.339844],"type":"Point"}
}