{
  "type": "Feature",
  "properties": {
    "addr:full":"L Kleiwg 60J Ryswyk Zh Zuid-Holland 2288 GK",
    "addr:housenumber":"60j",
    "addr:postcode":"2288 gk",
    "addr:street":"Kleiwg",
    "iso:country":"NL",
    "sg:address":"L Kleiwg 60J",
    "sg:city":"Ryswyk Zh",
    "sg:orig_category":"Arbo- En Bedrijfsgezondheids- Diensten",
    "sg:phone":"+31 70 319 7050",
    "sg:postcode":"2288 GK",
    "sg:province":"Zuid-Holland",
    "sg:website":"http://www.arboduo.nl",
    "wof:name":"Arboduo Rijswijk",
    "wof:placetype":"venue"
},
  "geometry": {"coordinates":[4.32436,52.037251],"type":"Point"}
}