{
  "type": "Feature",
  "properties": {
    "addr:full":"Pastoor Gortzstraat 22 Oud Ade Zuid-Holland 2374 BG",
    "addr:housenumber":"22",
    "addr:postcode":"ade;2374",
    "addr:street":"Pastoor Gortzstraat",
    "iso:country":"NL",
    "sg:address":"Pastoor Gortzstraat 22",
    "sg:city":"Oud Ade",
    "sg:orig_category":"Boekhouders",
    "sg:phone":"+31 71 501 2797",
    "sg:postcode":"2374 BG",
    "sg:province":"Zuid-Holland",
    "wof:name":"Administratiekantoor C.P.M. Zwetsloot",
    "wof:placetype":"venue"
},
  "geometry": {"coordinates":[-80.847527,40.293964],"type":"Point"}
}