{
  "type": "Feature",
  "properties": {
    "iso:country":"NL",
    "sg:address":"Condensatorwg 54",
    "sg:city":"Amsterdam",
    "sg:orig_category":"Waterleidingbedrijven",
    "sg:phone":"+31 20 580 2911",
    "sg:postcode":"1014 AX",
    "sg:province":"Noord-Holland",
    "wof:name":"Gemeentewaterleidingen Amsterdam",
    "wof:placetype":"venue"
},
  "geometry": {"coordinates":[4.8459000587,52.3895950317],"type":"Point"}
}