{
  "type": "Feature",
  "properties": {
    "addr:full":"Biltstr 182 Utrecht Utrecht 3572 BR",
    "addr:housenumber":"182",
    "addr:postcode":"3572 br",
    "iso:country":"NL",
    "sg:address":"Biltstr 182",
    "sg:city":"Utrecht",
    "sg:orig_category":"Advocaten En Advocatenkantoren",
    "sg:phone":"+31 30 272 4500",
    "sg:postcode":"3572 BR",
    "sg:province":"Utrecht",
    "wof:name":"Bouwman Van Dommelen",
    "wof:placetype":"venue"
},
  "geometry": {"coordinates":[5.139708,52.09581],"type":"Point"}
}