{
  "type": "Feature",
  "properties": {
    "addr:full":"Schaepmanstraat 3 Sneek Friesland 8603 AW",
    "addr:housenumber":"3",
    "addr:postcode":"8603 aw",
    "addr:street":"Schaepmanstraat",
    "iso:country":"NL",
    "sg:address":"Schaepmanstraat 3",
    "sg:city":"Sneek",
    "sg:orig_category":"Verhuur Audiovisuele Apparatuur",
    "sg:phone":"+31 515 423 030",
    "sg:postcode":"8603 AW",
    "sg:province":"Friesland",
    "wof:name":"G & L Techniek",
    "wof:placetype":"venue"
},
  "geometry": {"coordinates":[5.663978,53.038029],"type":"Point"}
}