{
  "type": "Feature",
  "properties": {
    "iso:country":"NL",
    "sg:address":"Haven 12",
    "sg:city":"Hillegom",
    "sg:orig_category":"Zonnebank- En Solariumcentra",
    "sg:phone":"+31 252 523 828",
    "sg:postcode":"2182 JK",
    "sg:province":"Zuid-Holland",
    "wof:name":"Rent-A-Sun",
    "wof:placetype":"venue"
},
  "geometry": {"coordinates":[4.579035,52.290207],"type":"Point"}
}