{
  "type": "Feature",
  "properties": {
    "addr:full":"Patrimoniumln 2 Veenendaal Utrecht 3904 AD",
    "addr:housenumber":"2",
    "addr:postcode":"3904 ad",
    "addr:street":"Patrimoniumln",
    "iso:country":"NL",
    "sg:address":"Patrimoniumln 2",
    "sg:city":"Veenendaal",
    "sg:orig_category":"Fietsen En Bromfietsen",
    "sg:phone":"+31 318 510 025",
    "sg:postcode":"3904 AD",
    "sg:province":"Utrecht",
    "wof:name":"Wijk Bv, Van",
    "wof:placetype":"venue"
},
  "geometry": {"coordinates":[5.54809,52.018589],"type":"Point"}
}