{
  "type": "Feature",
  "properties": {
    "addr:full":"Sportparklaan 16 Heemstede North Holland 2103 VT",
    "addr:housenumber":"16",
    "addr:postcode":"2103",
    "addr:street":"Sportparklaan",
    "iso:country":"NL",
    "sg:address":"Sportparklaan 16",
    "sg:city":"Heemstede",
    "sg:orig_category":"Fitnesscentra",
    "sg:phone":"+31 23 529 2072",
    "sg:postcode":"2103 VT",
    "sg:province":"North Holland",
    "wof:name":"Optisport Groenendaal",
    "wof:placetype":"venue"
},
  "geometry": {"coordinates":[4.622906,52.338154],"type":"Point"}
}