{
  "type": "Feature",
  "properties": {
    "addr:full":"Hoofdstr 153 Terheyden Noord-Brabant 4844 CD",
    "addr:housenumber":"153",
    "addr:postcode":"4844 cd",
    "addr:street":"Terheyden",
    "iso:country":"NL",
    "sg:address":"Hoofdstr 153",
    "sg:city":"Terheyden",
    "sg:orig_category":"Logopedisten",
    "sg:phone":"+31 76 593 3099",
    "sg:postcode":"4844 CD",
    "sg:province":"Noord-Brabant",
    "wof:name":"Terheyden Logopediepraktijk",
    "wof:placetype":"venue"
},
  "geometry": {"coordinates":[4.758798,51.638737],"type":"Point"}
}