{
  "type": "Feature",
  "properties": {
    "addr:full":"De Bleek 19 Montfoort Utrecht 3417 TR",
    "addr:housenumber":"19",
    "addr:postcode":"3417 tr",
    "addr:street":"De Bleek",
    "iso:country":"NL",
    "sg:address":"De Bleek 19",
    "sg:city":"Montfoort",
    "sg:orig_category":"Fotografie Reclame En Mode",
    "sg:phone":"+31 348 471 410",
    "sg:postcode":"3417 TR",
    "sg:province":"Utrecht",
    "wof:name":"Robert Vendrig",
    "wof:placetype":"venue"
},
  "geometry": {"coordinates":[4.94625,52.042324],"type":"Point"}
}