{
  "type": "Feature",
  "properties": {
    "iso:country":"NL",
    "sg:address":"Wilhelminapk 22",
    "sg:city":"Valkenswaard",
    "sg:orig_category":"Accountants - Administratie- Consulenten En -Kantoren",
    "sg:phone":"+31 40 201 2469",
    "sg:postcode":"5554 JE",
    "sg:province":"North Brabant",
    "wof:name":"Gastel & Neijnens, Van",
    "wof:placetype":"venue"
},
  "geometry": {"coordinates":[5.459863,51.345856],"type":"Point"}
}