{
  "type": "Feature",
  "properties": {
    "addr:full":"Thomaslaan 2 Eindhoven Noord-Brabant 5631 GL",
    "addr:housenumber":"2",
    "addr:postcode":"5631 gl",
    "addr:street":"Thomaslaan",
    "iso:country":"NL",
    "sg:address":"Thomaslaan 2",
    "sg:city":"Eindhoven",
    "sg:orig_category":"Vertaal- And Tolkenbureaus",
    "sg:phone":"+31 40 285 8884",
    "sg:postcode":"5631 GL",
    "sg:province":"Noord-Brabant",
    "wof:name":"Jason Translation Services.",
    "wof:placetype":"venue"
},
  "geometry": {"coordinates":[5.488933,51.462845],"type":"Point"}
}