{
  "type": "Feature",
  "properties": {
    "iso:country":"NL",
    "sg:address":"Vaartweg 88",
    "sg:city":"Espel",
    "sg:orig_category":"Fruit And Groenten Gh",
    "sg:phone":"+31 527 271 657",
    "sg:postcode":"8311 AA",
    "sg:province":"Flevoland",
    "wof:name":"A. Buys Bv",
    "wof:placetype":"venue"
},
  "geometry": {"coordinates":[-95.71624799999999,48.223763],"type":"Point"}
}