{
  "type": "Feature",
  "properties": {
    "addr:full":"Kruishoekstraat 33 Heesch North Brabant 5384 TK",
    "addr:housenumber":"33",
    "addr:postcode":"5384 tk",
    "addr:street":"Kruishoekstraat",
    "iso:country":"NL",
    "sg:address":"Kruishoekstraat 33",
    "sg:city":"Heesch",
    "sg:orig_category":"Metaalwerken",
    "sg:phone":"+31 412 452 930",
    "sg:postcode":"5384 TK",
    "sg:province":"North Brabant",
    "wof:name":"Broeksteeg Van Nistelrooy Plafonds",
    "wof:placetype":"venue"
},
  "geometry": {"coordinates":[5.510956,51.723667],"type":"Point"}
}