{
  "type": "Feature",
  "properties": {
    "addr:full":"Breestraat 130 Leiden South Holland 2311 CX",
    "addr:housenumber":"130",
    "addr:postcode":"2311 cx",
    "addr:street":"Breestraat",
    "iso:country":"NL",
    "sg:address":"Breestraat 130",
    "sg:city":"Leiden",
    "sg:orig_category":"Verlichting And Huishoudartikelen",
    "sg:phone":"+31 71 513 2071",
    "sg:postcode":"2311 CX",
    "sg:province":"South Holland",
    "wof:name":"Giraffe Bv",
    "wof:placetype":"venue"
},
  "geometry": {"coordinates":[4.492081,52.157055],"type":"Point"}
}