{
  "type": "Feature",
  "properties": {
    "addr:full":"Rozengracht 141 Amsterdam Noord-Holland 1016 LW",
    "addr:housenumber":"141",
    "addr:postcode":"1016 lw",
    "addr:street":"Rozengracht",
    "iso:country":"NL",
    "sg:address":"Rozengracht 141",
    "sg:city":"Amsterdam",
    "sg:orig_category":"Verlichting And Huishoudartikelen",
    "sg:phone":"+31 20 623 3541",
    "sg:postcode":"1016 LW",
    "sg:province":"Noord-Holland",
    "wof:name":"Reon Bv",
    "wof:placetype":"venue"
},
  "geometry": {"coordinates":[4.878316,52.372711],"type":"Point"}
}