{
  "type": "Feature",
  "properties": {
    "addr:full":"Gestelsestraat 16 Waalre Noord-Brabant 5582 HH",
    "addr:housenumber":"16",
    "addr:postcode":"5582 hh",
    "addr:street":"Gestelsestraat",
    "iso:country":"NL",
    "sg:address":"Gestelsestraat 16",
    "sg:city":"Waalre",
    "sg:orig_category":"Kunststofverpakkingen Fab",
    "sg:phone":"+31 40 223 0900",
    "sg:postcode":"5582 HH",
    "sg:province":"Noord-Brabant",
    "wof:name":"Dux Trading Bv",
    "wof:placetype":"venue"
},
  "geometry": {"coordinates":[5.476579,51.398521],"type":"Point"}
}