{
  "type": "Feature",
  "properties": {
    "addr:full":"Wilhelminaln 24 Roermond Limburg 6042 EN",
    "addr:housenumber":"24",
    "addr:postcode":"6042 en",
    "addr:street":"Wilhelminaln",
    "iso:country":"NL",
    "sg:address":"Wilhelminaln 24",
    "sg:city":"Roermond",
    "sg:orig_category":"Drukkerijen",
    "sg:phone":"+31 475 371 280",
    "sg:postcode":"6042 EN",
    "sg:province":"Limburg",
    "wof:name":"Polygraphics",
    "wof:placetype":"venue"
},
  "geometry": {"coordinates":[6.011636,51.201092],"type":"Point"}
}