{
  "type": "Feature",
  "properties": {
    "addr:full":"Marktplein 36 Twello Gelderland 7391 DZ",
    "addr:housenumber":"36",
    "addr:postcode":"7391 dz",
    "addr:street":"Marktplein;Gelderland",
    "iso:country":"NL",
    "sg:address":"Marktplein 36",
    "sg:city":"Twello",
    "sg:orig_category":"Werving And Selectie Van Tijdelijk Personeel And Uitzendkantoren",
    "sg:phone":"+31 571 287 777",
    "sg:postcode":"7391 DZ",
    "sg:province":"Gelderland",
    "wof:name":"Tip Bv",
    "wof:placetype":"venue"
},
  "geometry": {"coordinates":[6.104388237,52.2366714478],"type":"Point"}
}