{
  "type": "Feature",
  "properties": {
    "addr:full":"Steenovens 101 Westerhoven Noord-Brabant 5563 CG",
    "addr:housenumber":"101",
    "addr:postcode":"5563 cg",
    "addr:street":"Steenovens",
    "iso:country":"NL",
    "sg:address":"Steenovens 101",
    "sg:city":"Westerhoven",
    "sg:orig_category":"Montagebedrijven",
    "sg:phone":"+31 40 204 2181",
    "sg:postcode":"5563 CG",
    "sg:province":"Noord-Brabant",
    "wof:name":"Westerhoven",
    "wof:placetype":"venue"
},
  "geometry": {"coordinates":[5.401763,51.335995],"type":"Point"}
}