{
  "type": "Feature",
  "properties": {
    "iso:country":"NL",
    "sg:address":"N Beetsstr 22",
    "sg:city":"Papendrecht",
    "sg:orig_category":"Bouwbureaus",
    "sg:phone":"+31 78 615 5370",
    "sg:postcode":"3351 EC",
    "sg:province":"Zuid-Holland",
    "wof:name":"Preboma",
    "wof:placetype":"venue"
},
  "geometry": {"coordinates":[4.674142,51.832771],"type":"Point"}
}