{
  "type": "Feature",
  "properties": {
    "addr:full":"Stokroos 1 Leiden South Holland 2317 EM",
    "addr:housenumber":"1",
    "addr:postcode":"2317 em",
    "addr:street":"Stokroos",
    "iso:country":"NL",
    "sg:address":"Stokroos 1",
    "sg:city":"Leiden",
    "sg:classifiers":[
        {
            "category":"Professional",
            "subcategory":"Accounting & Tax Preparation",
            "type":"Services"
        }
    ],
    "sg:phone":"+31 71 522 1979",
    "sg:postcode":"2317 EM",
    "sg:province":"South Holland",
    "sg:tags":[
        "accountant"
    ],
    "wof:name":"Vandenberg Registeraccountants Praktijk",
    "wof:placetype":"venue"
},
  "geometry": {"coordinates":[4.516851,52.17712],"type":"Point"}
}