{
  "type": "Feature",
  "properties": {
    "addr:full":"Stalbergwg 216 Venlo Limburg 5913 BW",
    "addr:housenumber":"216",
    "addr:postcode":"5913 bw",
    "iso:country":"NL",
    "sg:address":"Stalbergwg 216",
    "sg:city":"Venlo",
    "sg:orig_category":"Orthopedagogen",
    "sg:phone":"+31 77 351 8586",
    "sg:postcode":"5913 BW",
    "sg:province":"Limburg",
    "wof:name":"Bax-Gommans, Drs I W",
    "wof:placetype":"venue"
},
  "geometry": {"coordinates":[6.1843447685,51.3664169312],"type":"Point"}
}