{
  "type": "Feature",
  "properties": {
    "iso:country":"NL",
    "sg:address":"Donk 5",
    "sg:city":"Duizel",
    "sg:orig_category":"Verhuur Bouwmachines",
    "sg:phone":"+31 497 519 500",
    "sg:postcode":"5525 KH",
    "sg:province":"North Brabant",
    "wof:name":"De Geveltoerist Bv",
    "wof:placetype":"venue"
},
  "geometry": {"coordinates":[5.290488,51.367836],"type":"Point"}
}