{
  "type": "Feature",
  "properties": {
    "addr:full":"Burg De Bruinelaan 134 Zwijndrecht Zuid-Holland 3331 AJ",
    "addr:housenumber":"134",
    "addr:postcode":"3331 aj",
    "addr:street":"Bruinelaan",
    "iso:country":"NL",
    "sg:address":"Burg De Bruinelaan 134",
    "sg:city":"Zwijndrecht",
    "sg:orig_category":"Bouwnijverheidsmachines Gh",
    "sg:phone":"+31 78 612 4861",
    "sg:postcode":"3331 AJ",
    "sg:province":"Zuid-Holland",
    "wof:name":"Handelsondern L Vd Heuvel Slikkerveer Bv",
    "wof:placetype":"venue"
},
  "geometry": {"coordinates":[4.646971,51.814938],"type":"Point"}
}