{
  "type": "Feature",
  "properties": {
    "addr:full":"Volmachtenlaan 15 Norg Provincie Drenthe 9331 BK",
    "addr:housenumber":"15",
    "addr:postcode":"9331 bk",
    "addr:street":"Volmachtenlaan;Provincie Drenthe",
    "iso:country":"NL",
    "sg:address":"Volmachtenlaan 15",
    "sg:city":"Norg",
    "sg:classifiers":[
        {
            "category":"Professional",
            "subcategory":"Accounting & Tax Preparation",
            "type":"Services"
        }
    ],
    "sg:phone":"+31 592 613 146",
    "sg:postcode":"9331 BK",
    "sg:province":"Provincie Drenthe",
    "sg:tags":[
        "accountant"
    ],
    "wof:name":"Accountantskantoor T. Hotsma Bv",
    "wof:placetype":"venue"
},
  "geometry": {"coordinates":[6.470887,53.065056],"type":"Point"}
}