{
  "type": "Feature",
  "properties": {
    "iso:country":"NL",
    "sg:address":"Gerrit Van Assendelftstr 24",
    "sg:city":"Heemskerk",
    "sg:orig_category":"Kappers",
    "sg:phone":"+31 251 248 967",
    "sg:postcode":"1961 NK",
    "sg:province":"North Holland",
    "wof:name":"Jacques Coiffures",
    "wof:placetype":"venue"
},
  "geometry": {"coordinates":[4.674516201,52.508808136],"type":"Point"}
}