{
  "type": "Feature",
  "properties": {
    "iso:country":"NL",
    "sg:address":"Overysselln 7",
    "sg:city":"Veendam",
    "sg:orig_category":"Schoonheidsinstituten",
    "sg:phone":"+31 598 615 743",
    "sg:postcode":"9642 HP",
    "sg:province":"Groningen",
    "wof:name":"Rosemarie Voulon",
    "wof:placetype":"venue"
},
  "geometry": {"coordinates":[6.861346,53.090679],"type":"Point"}
}