{
  "type": "Feature",
  "properties": {
    "addr:full":"Pannenschuurpln 50 Oisterwyk North Brabant 5061 WP",
    "addr:housenumber":"50",
    "addr:postcode":"5061 wp",
    "addr:street":"Pannenschuurpln",
    "iso:country":"NL",
    "sg:address":"Pannenschuurpln 50",
    "sg:city":"Oisterwyk",
    "sg:orig_category":"Fietsen En Bromfietsen",
    "sg:phone":"+31 13 521 0623",
    "sg:postcode":"5061 WP",
    "sg:province":"North Brabant",
    "wof:name":"Bert, Bike Shop",
    "wof:placetype":"venue"
},
  "geometry": {"coordinates":[5.17578,51.583218],"type":"Point"}
}