{
  "type": "Feature",
  "properties": {
    "iso:country":"NL",
    "sg:address":"Linnaeusstraat 48",
    "sg:city":"Amsterdam",
    "sg:orig_category":"Bloemen And Planten",
    "sg:phone":"+31 900 7000625",
    "sg:postcode":"1092 CM",
    "sg:province":"Noord-Holland",
    "wof:name":"Bloemenkiosk N. Mulders",
    "wof:placetype":"venue"
},
  "geometry": {"coordinates":[4.926686,52.357449],"type":"Point"}
}