{
  "type": "Feature",
  "properties": {
    "iso:country":"NL",
    "sg:address":"Beusichemsewg 51",
    "sg:city":"T Goy",
    "sg:orig_category":"Verenigingsgebouwen",
    "sg:phone":"+31 30 601 1202",
    "sg:postcode":"3997 MH",
    "sg:province":"Utrecht",
    "wof:name":"Ploeg, De",
    "wof:placetype":"venue"
},
  "geometry": {"coordinates":[5.222712,52.001286],"type":"Point"}
}