{
  "type": "Feature",
  "properties": {
    "addr:full":"Postbus 93010 Amsterdam Drenthe 1090 BA",
    "addr:postcode":"93010;1090 ba",
    "addr:street":"Postbus",
    "iso:country":"NL",
    "sg:address":"Postbus 93010",
    "sg:city":"Amsterdam",
    "sg:orig_category":"Adviesbureaus",
    "sg:phone":"+31 20 772 4820",
    "sg:postcode":"1090 BA",
    "sg:province":"Drenthe",
    "wof:name":"Ag Business Development Bv",
    "wof:placetype":"venue"
},
  "geometry": {"coordinates":[4.89205,52.37355],"type":"Point"}
}