{
  "type": "Feature",
  "properties": {
    "addr:full":"Zyldk 23 Leiderdorp Zuid-Holland 2352 AB",
    "addr:housenumber":"23",
    "addr:postcode":"2352 ab",
    "addr:street":"Zyldk",
    "iso:country":"NL",
    "sg:address":"Zyldk 23",
    "sg:city":"Leiderdorp",
    "sg:orig_category":"Lpg-Installaties",
    "sg:phone":"+31 71 589 7927",
    "sg:postcode":"2352 AB",
    "sg:province":"Zuid-Holland",
    "wof:name":"Perk Bv, Van Der",
    "wof:placetype":"venue"
},
  "geometry": {"coordinates":[4.534218,52.156174],"type":"Point"}
}