{
  "type": "Feature",
  "properties": {
    "iso:country":"NL",
    "sg:address":"Geldropseweg 75",
    "sg:city":"Eindhoven",
    "sg:orig_category":"Huishoudapparatuur, Televisies And Radio'S",
    "sg:phone":"+31 40 211 1865",
    "sg:postcode":"5611 SE",
    "sg:province":"North Brabant",
    "wof:name":"Tv-Centrum Vof",
    "wof:placetype":"venue"
},
  "geometry": {"coordinates":[5.488832,51.433586],"type":"Point"}
}