{
  "type": "Feature",
  "properties": {
    "iso:country":"NL",
    "sg:address":"Hengeloln 403",
    "sg:city":"S Gravenhage",
    "sg:orig_category":"Wassalons",
    "sg:phone":"+31 70 367 9702",
    "sg:postcode":"2545 JN",
    "sg:province":"South Holland",
    "wof:name":"Air Clean Wassen Stomen",
    "wof:placetype":"venue"
},
  "geometry": {"coordinates":[4.2704901695,52.0509300232],"type":"Point"}
}