{
  "type": "Feature",
  "properties": {
    "addr:full":"Banbroek 22 Hippolytushoef Noord-Holland 1777 MR",
    "addr:housenumber":"22",
    "addr:postcode":"1777 mr",
    "addr:street":"Banbroek",
    "iso:country":"NL",
    "sg:address":"Banbroek 22",
    "sg:city":"Hippolytushoef",
    "sg:orig_category":"Aquariumartikelen En Siervissen",
    "sg:phone":"+31 227 593 543",
    "sg:postcode":"1777 MR",
    "sg:province":"Noord-Holland",
    "wof:name":"Tanichthys",
    "wof:placetype":"venue"
},
  "geometry": {"coordinates":[4.971274,52.913422],"type":"Point"}
}