{
  "type": "Feature",
  "properties": {
    "iso:country":"NL",
    "sg:address":"Diamantweg 9",
    "sg:city":"Alkmaar",
    "sg:orig_category":"Bedrijfsinventaris Gh",
    "sg:phone":"+31 72 540 2944",
    "sg:postcode":"1812 RC",
    "sg:province":"North Holland",
    "wof:name":"Sligro Alkmaar",
    "wof:placetype":"venue"
},
  "geometry": {"coordinates":[4.757398,52.610229],"type":"Point"}
}