{
  "type": "Feature",
  "properties": {
    "iso:country":"NL",
    "sg:address":"Olieslagerserf 16",
    "sg:city":"Eerbeek",
    "sg:classifiers":[
        {
            "category":"Personal",
            "subcategory":"Nail Salon",
            "type":"Services"
        }
    ],
    "sg:phone":"+31 313 654 305",
    "sg:postcode":"6961 JT",
    "sg:province":"Gelderland",
    "sg:tags":[
        "pedicure"
    ],
    "wof:name":"Zweers, Tineke",
    "wof:placetype":"venue"
},
  "geometry": {"coordinates":[6.064725,52.10899],"type":"Point"}
}