{
  "type": "Feature",
  "properties": {
    "addr:full":"Papsouwseln 3 Delft South Holland 2624 AE",
    "addr:housenumber":"3",
    "addr:postcode":"2624 ae",
    "addr:street":"Papsouwseln",
    "iso:country":"NL",
    "sg:address":"Papsouwseln 3",
    "sg:city":"Delft",
    "sg:orig_category":"Elektrotechnische Installatiebureaus",
    "sg:phone":"+31 15 261 2150",
    "sg:postcode":"2624 AE",
    "sg:province":"South Holland",
    "sg:website":"http://www.groenewegen.etsb.nl",
    "wof:name":"Groenewegen Elektro Bv, C L",
    "wof:placetype":"venue"
},
  "geometry": {"coordinates":[4.35634,51.995491],"type":"Point"}
}