{
  "type": "Feature",
  "properties": {
    "addr:full":"Gedempte Oude Gracht 37 Haarlem North Holland 2011 GL",
    "addr:housenumber":"37",
    "addr:postcode":"2011 gl",
    "addr:street":"Gedempte Oude Gracht",
    "iso:country":"NL",
    "sg:address":"Gedempte Oude Gracht 37",
    "sg:city":"Haarlem",
    "sg:orig_category":"Kappers",
    "sg:phone":"+31 23 532 4001",
    "sg:postcode":"2011 GL",
    "sg:province":"North Holland",
    "wof:name":"Marjon! Haarmode",
    "wof:placetype":"venue"
},
  "geometry": {"coordinates":[4.632323,52.381115],"type":"Point"}
}