{
  "type": "Feature",
  "properties": {
    "addr:full":"Luikerweg 46 Maastricht Limburg 6212 EW",
    "addr:housenumber":"46",
    "addr:postcode":"6212 ew",
    "addr:street":"Luikerweg",
    "iso:country":"NL",
    "sg:address":"Luikerweg 46",
    "sg:city":"Maastricht",
    "sg:orig_category":"Kappers",
    "sg:phone":"+31 43 321 2069",
    "sg:postcode":"6212 EW",
    "sg:province":"Limburg",
    "wof:name":"P.J.E. Frijns",
    "wof:placetype":"venue"
},
  "geometry": {"coordinates":[5.686866,50.839062],"type":"Point"}
}