{
  "type": "Feature",
  "properties": {
    "iso:country":"NL",
    "sg:address":"Meester Bierkuslaan 41",
    "sg:city":"'S Hertogenbosch",
    "sg:orig_category":"Fotostudio'S And Fotografen",
    "sg:phone":"+31 73 649 8996",
    "sg:postcode":"5237 JB",
    "sg:province":"Noord-Brabant",
    "wof:name":"Fotobureau Colson (A. V. Kooy)",
    "wof:placetype":"venue"
},
  "geometry": {"coordinates":[5.294028,51.732548],"type":"Point"}
}