{
  "type": "Feature",
  "properties": {
    "addr:full":"Prinsengr 1051 Amsterdam North Holland 1017 JE",
    "addr:housenumber":"1051",
    "addr:postcode":"1017 je",
    "iso:country":"NL",
    "sg:address":"Prinsengr 1051",
    "sg:city":"Amsterdam",
    "sg:classifiers":[
        {
            "category":"Travel",
            "subcategory":"Hotels & Motels",
            "type":"Entertainment"
        }
    ],
    "sg:phone":"+31 20 623 0230",
    "sg:postcode":"1017 JE",
    "sg:province":"North Holland",
    "sg:website":"http://www.itc-hotel.com",
    "wof:name":"Itc",
    "wof:placetype":"venue"
},
  "geometry": {"coordinates":[4.898494,52.362324],"type":"Point"}
}