{
  "type": "Feature",
  "properties": {
    "addr:full":"Goudesteyn 30 Ysselstein Ut Utrecht 3401 SM",
    "addr:housenumber":"30",
    "addr:postcode":"3401 sm",
    "addr:street":"Goudesteyn",
    "iso:country":"NL",
    "sg:address":"Goudesteyn 30",
    "sg:city":"Ysselstein Ut",
    "sg:orig_category":"Adviesbureaus Bedrijfsorganisatie",
    "sg:phone":"+31 30 687 6767",
    "sg:postcode":"3401 SM",
    "sg:province":"Utrecht",
    "sg:website":"http://www.efteha.nl",
    "wof:name":"Hat Trick",
    "wof:placetype":"venue"
},
  "geometry": {"coordinates":[5.028806,52.028862],"type":"Point"}
}