{
  "type": "Feature",
  "properties": {
    "addr:full":"Postbus 311 Dokkum Friesland 9100 AH",
    "addr:housenumber":"311",
    "addr:postcode":"9100 ah",
    "addr:street":"Postbus",
    "iso:country":"NL",
    "sg:address":"Postbus 311",
    "sg:city":"Dokkum",
    "sg:orig_category":"Scholen Voor Basisonderwijs",
    "sg:phone":"+31 519 292 570",
    "sg:postcode":"9100 AH",
    "sg:province":"Friesland",
    "wof:name":"Burger",
    "wof:placetype":"venue"
},
  "geometry": {"coordinates":[5.99885,53.328289],"type":"Point"}
}