{
  "type": "Feature",
  "properties": {
    "addr:full":"Leermosstraat 7 Almere Flevoland 1314 MS",
    "addr:housenumber":"7",
    "addr:postcode":"1314",
    "addr:street":"Leermosstraat;Flevoland",
    "iso:country":"NL",
    "sg:address":"Leermosstraat 7",
    "sg:city":"Almere",
    "sg:orig_category":"Kappers",
    "sg:phone":"+31 36 533 0474",
    "sg:postcode":"1314 MS",
    "sg:province":"Flevoland",
    "wof:name":"Hellen Coiffeurs",
    "wof:placetype":"venue"
},
  "geometry": {"coordinates":[5.2098650932,52.3830833435],"type":"Point"}
}