{
  "type": "Feature",
  "properties": {
    "addr:full":"Kl Westerbuiten 17 Edam Noord-Holland 1135 GL",
    "addr:housenumber":"17",
    "addr:postcode":"1135 gl",
    "addr:street":"Westerbuiten",
    "iso:country":"NL",
    "sg:address":"Kl Westerbuiten 17",
    "sg:city":"Edam",
    "sg:classifiers":[
        {
            "category":"Home & Garden",
            "subcategory":"Hardware",
            "type":"Retail Goods"
        }
    ],
    "sg:phone":"+31 299 372 071",
    "sg:postcode":"1135 GL",
    "sg:province":"Noord-Holland",
    "sg:tags":[
        "machine",
        "houtbewerking",
        "-"
    ],
    "wof:name":"Overmars",
    "wof:placetype":"venue"
},
  "geometry": {"coordinates":[5.042557,52.511219],"type":"Point"}
}