{
  "type": "Feature",
  "properties": {
    "iso:country":"NL",
    "sg:address":"Bijster 61",
    "sg:city":"Hoogvliet Rt",
    "sg:orig_category":"Kappers",
    "sg:phone":"+31 10 438 2946",
    "sg:postcode":"3191 SB",
    "sg:province":"Zuid-Holland",
    "wof:name":"Marion Hemelrijk",
    "wof:placetype":"venue"
},
  "geometry": {"coordinates":[4.36636,51.863182],"type":"Point"}
}