{
  "type": "Feature",
  "properties": {
    "addr:full":"Past Koopmanwg 68 Den Helder Noord-Holland 1784 NX",
    "addr:housenumber":"68",
    "addr:postcode":"1784 nx",
    "iso:country":"NL",
    "sg:address":"Past Koopmanwg 68",
    "sg:city":"Den Helder",
    "sg:orig_category":"Fitnesscentra",
    "sg:phone":"+31 223 630 191",
    "sg:postcode":"1784 NX",
    "sg:province":"Noord-Holland",
    "sg:website":"http://www.bodyfitdenhelder.nl",
    "wof:name":"Bodyfit",
    "wof:placetype":"venue"
},
  "geometry": {"coordinates":[4.753012,52.934093],"type":"Point"}
}