{
  "type": "Feature",
  "properties": {
    "addr:full":"Hofstede 125 Lelystad NL. 8212 WJ",
    "addr:housenumber":"125",
    "addr:postcode":"8212 wj",
    "addr:street":"Hofstede;Nl.",
    "iso:country":"NL",
    "sg:address":"Hofstede 125",
    "sg:city":"Lelystad",
    "sg:orig_category":"Schilderwerk",
    "sg:phone":"+31 320 227 835",
    "sg:postcode":"8212 WJ",
    "sg:province":"NL.",
    "wof:name":"T. Van Eeden",
    "wof:placetype":"venue"
},
  "geometry": {"coordinates":[5.505993,52.512577],"type":"Point"}
}