{
  "type": "Feature",
  "properties": {
    "iso:country":"NL",
    "sg:address":"Goudenregenplantsoen 60",
    "sg:city":"Alphen A/D Rijn",
    "sg:classifiers":[
        {
            "category":"Food & Beverages",
            "subcategory":"Fruits & Vegetables",
            "type":"Retail Goods"
        }
    ],
    "sg:phone":"+31 172 473 202",
    "sg:postcode":"2404 EK",
    "sg:province":"Zuid-Holland",
    "sg:tags":[
        "groenten"
    ],
    "wof:name":"De Vitamine Shop",
    "wof:placetype":"venue"
},
  "geometry": {"coordinates":[4.648344,52.132568],"type":"Point"}
}