{
  "type": "Feature",
  "properties": {
    "iso:country":"NL",
    "sg:address":"O Handelskd 1021",
    "sg:city":"Amsterdam",
    "sg:classifiers":[
        {
            "category":"Personal",
            "subcategory":"Nail Salon",
            "type":"Services"
        }
    ],
    "sg:phone":"+31 20 419 7633",
    "sg:postcode":"1019 BW",
    "sg:province":"North Holland",
    "sg:tags":[
        "pedicure"
    ],
    "wof:name":"Hemelrijk, M",
    "wof:placetype":"venue"
},
  "geometry": {"coordinates":[4.893195,52.373119],"type":"Point"}
}