{
  "type": "Feature",
  "properties": {
    "addr:full":"Bruistensingel 142 'S Hertogenbosch Noord-Brabant 5232 AC",
    "addr:housenumber":"142 ' s",
    "addr:postcode":"5232 ac",
    "addr:street":"Bruistensingel",
    "iso:country":"NL",
    "sg:address":"Bruistensingel 142",
    "sg:city":"'S Hertogenbosch",
    "sg:orig_category":"Verzekeringen",
    "sg:phone":"+31 73 640 8800",
    "sg:postcode":"5232 AC",
    "sg:province":"Noord-Brabant",
    "wof:name":"Mees & Zoonen",
    "wof:placetype":"venue"
},
  "geometry": {"coordinates":[5.336056,51.716152],"type":"Point"}
}