{
  "type": "Feature",
  "properties": {
    "addr:full":"Bergstraat 64 Loon Op Zand Noord-Brabant 5175 AB",
    "addr:housenumber":"64",
    "addr:postcode":"5175 ab",
    "addr:street":"Bergstraat",
    "iso:country":"NL",
    "sg:address":"Bergstraat 64",
    "sg:city":"Loon Op Zand",
    "sg:classifiers":[
        {
            "category":"Food & Beverages",
            "subcategory":"Fruits & Vegetables",
            "type":"Retail Goods"
        }
    ],
    "sg:phone":"+31 416 361 450",
    "sg:postcode":"5175 AB",
    "sg:province":"Noord-Brabant",
    "sg:tags":[
        "groenten"
    ],
    "wof:name":"Van Broekhoven Verse Groenten",
    "wof:placetype":"venue"
},
  "geometry": {"coordinates":[5.060506,51.625229],"type":"Point"}
}