{
  "type": "Feature",
  "properties": {
    "addr:full":"Schafterdijk 18 Valkenswaard North Brabant 5556 VK",
    "addr:housenumber":"18",
    "addr:postcode":"5556 vk",
    "addr:street":"Schafterdijk",
    "iso:country":"NL",
    "sg:address":"Schafterdijk 18",
    "sg:city":"Valkenswaard",
    "sg:orig_category":"Bloemen And Planten",
    "sg:phone":"+31 40 206 8727",
    "sg:postcode":"5556 VK",
    "sg:province":"North Brabant",
    "wof:name":"Boomkwekerij Johan Vd Boomen",
    "wof:placetype":"venue"
},
  "geometry": {"coordinates":[5.462868,51.304718],"type":"Point"}
}