{
  "type": "Feature",
  "properties": {
    "addr:full":"Victorialn 10 S Hertogenbosch Noord-Brabant 5213 JE",
    "addr:housenumber":"10",
    "addr:postcode":"5213 je",
    "addr:street":"Victorialn;S",
    "iso:country":"NL",
    "sg:address":"Victorialn 10",
    "sg:city":"S Hertogenbosch",
    "sg:orig_category":"Fitnesscentra",
    "sg:phone":"+31 73 646 4670",
    "sg:postcode":"5213 JE",
    "sg:province":"Noord-Brabant",
    "sg:website":"http://www.sportiom.nl",
    "wof:name":"Health Floor Sportiom",
    "wof:placetype":"venue"
},
  "geometry": {"coordinates":[5.328494,51.701084],"type":"Point"}
}