{
  "type": "Feature",
  "properties": {
    "iso:country":"NL",
    "sg:address":"Baronieln 103",
    "sg:city":"Breda",
    "sg:orig_category":"Verlichtingsartikelen - Fabrieken",
    "sg:phone":"+31 76 531 0870",
    "sg:postcode":"4818 PD",
    "sg:province":"Noord-Brabant",
    "sg:website":"http://www.wever-ducre.com",
    "wof:name":"Wever & Ducre",
    "wof:placetype":"venue"
},
  "geometry": {"coordinates":[4.771685,51.591351],"type":"Point"}
}