{
  "type": "Feature",
  "properties": {
    "iso:country":"NL",
    "sg:address":"Saturnus 34",
    "sg:city":"Duivendrecht",
    "sg:orig_category":"Fotografie Reclame En Mode",
    "sg:phone":"+31 20 699 2009",
    "sg:postcode":"1115 TD",
    "sg:province":"Noord-Holland",
    "wof:name":"Noort, Theo",
    "wof:placetype":"venue"
},
  "geometry": {"coordinates":[4.93631,52.332981],"type":"Point"}
}