{
  "type": "Feature",
  "properties": {
    "addr:full":"Pr Hendrikwg 40 Houten Utrecht 3991 BV",
    "addr:housenumber":"40",
    "addr:postcode":"3991 bv",
    "addr:street":"Houten Utrecht",
    "iso:country":"NL",
    "sg:address":"Pr Hendrikwg 40",
    "sg:city":"Houten",
    "sg:orig_category":"Journalisten Freelance",
    "sg:phone":"+31 30 634 0977",
    "sg:postcode":"3991 BV",
    "sg:province":"Utrecht",
    "sg:website":"http://www.antenna.nl/wiercx/",
    "wof:name":"Wiercx-Woord-Beeld",
    "wof:placetype":"venue"
},
  "geometry": {"coordinates":[5.164374,52.028763],"type":"Point"}
}