{
  "type": "Feature",
  "properties": {
    "iso:country":"NL",
    "sg:address":"Driemanschapsln 5",
    "sg:city":"Gorinchem",
    "sg:orig_category":"Verenigingsgebouwen",
    "sg:phone":"+31 183 620 666",
    "sg:postcode":"4204 XZ",
    "sg:province":"Zuid-Holland",
    "wof:name":"Klaverblad, Het",
    "wof:placetype":"venue"
},
  "geometry": {"coordinates":[4.952248,51.840763],"type":"Point"}
}