{
  "type": "Feature",
  "properties": {
    "addr:full":"Botterstr 125 Elburg Gelderland 8081 JW",
    "addr:housenumber":"125",
    "addr:postcode":"8081 jw",
    "addr:street":"Gelderland",
    "iso:country":"NL",
    "sg:address":"Botterstr 125",
    "sg:city":"Elburg",
    "sg:orig_category":"Autorijscholen",
    "sg:phone":"+31 525 682 745",
    "sg:postcode":"8081 JW",
    "sg:province":"Gelderland",
    "wof:name":"Schraa Vof, Autorijschool",
    "wof:placetype":"venue"
},
  "geometry": {"coordinates":[5.848715,52.451694],"type":"Point"}
}