{
  "type": "Feature",
  "properties": {
    "addr:full":"Vollerstraat 6 Goirle Noord-Brabant 5051 JV",
    "addr:housenumber":"6",
    "addr:postcode":"5051 jv",
    "addr:street":"Vollerstraat",
    "iso:country":"NL",
    "sg:address":"Vollerstraat 6",
    "sg:city":"Goirle",
    "sg:orig_category":"Drukkerijen And Copyshops",
    "sg:phone":"+31 13 534 5694",
    "sg:postcode":"5051 JV",
    "sg:province":"Noord-Brabant",
    "wof:name":"Smit Zeefdrukkerij Goirle",
    "wof:placetype":"venue"
},
  "geometry": {"coordinates":[5.058265,51.513401],"type":"Point"}
}