{
  "type": "Feature",
  "properties": {
    "addr:full":"Altenaweg 30 Waalwijk North Brabant 5145 PC",
    "addr:housenumber":"30",
    "addr:postcode":"5145 pc",
    "addr:street":"Altenaweg",
    "iso:country":"NL",
    "sg:address":"Altenaweg 30",
    "sg:city":"Waalwijk",
    "sg:orig_category":"Goederenvervoer Over De Weg",
    "sg:phone":"+31 416 335 123",
    "sg:postcode":"5145 PC",
    "sg:province":"North Brabant",
    "wof:name":"H. Geven",
    "wof:placetype":"venue"
},
  "geometry": {"coordinates":[5.0657,51.69281],"type":"Point"}
}