{
  "type": "Feature",
  "properties": {
    "addr:full":"Hooiakker 24 Noord Scharwoude Noord-Holland 1723 BN",
    "addr:housenumber":"24",
    "addr:postcode":"1723 bn",
    "addr:street":"Hooiakker",
    "iso:country":"NL",
    "sg:address":"Hooiakker 24",
    "sg:city":"Noord Scharwoude",
    "sg:orig_category":"Kappers",
    "sg:phone":"+31 226 315 085",
    "sg:postcode":"1723 BN",
    "sg:province":"Noord-Holland",
    "wof:name":"Creatief",
    "wof:placetype":"venue"
},
  "geometry": {"coordinates":[4.8060312271,52.6990013123],"type":"Point"}
}