{
  "type": "Feature",
  "properties": {
    "iso:country":"NL",
    "sg:address":"Elingslaan 17",
    "sg:city":"Burgum",
    "sg:classifiers":[
        {
            "category":"Professional",
            "subcategory":"Accounting & Tax Preparation",
            "type":"Services"
        }
    ],
    "sg:phone":"+31 511 464 999",
    "sg:postcode":"9251 MN",
    "sg:province":"Friesland",
    "sg:tags":[
        "accountant"
    ],
    "wof:name":"Kingma Accountants",
    "wof:placetype":"venue"
},
  "geometry": {"coordinates":[-93.365471,46.441929],"type":"Point"}
}