{
  "type": "Feature",
  "properties": {
    "addr:full":"Dreef 2 Zutphen Gelderland 7202 AG",
    "addr:housenumber":"2",
    "addr:postcode":"7202",
    "addr:street":"Dreef;Gelderland",
    "iso:country":"NL",
    "sg:address":"Dreef 2",
    "sg:city":"Zutphen",
    "sg:orig_category":"Boekenuitgeverijen",
    "sg:phone":"+31 575 545 688",
    "sg:postcode":"7202 AG",
    "sg:province":"Gelderland",
    "wof:name":"Uitgeverij Roodbont",
    "wof:placetype":"venue"
},
  "geometry": {"coordinates":[6.196949,52.147942],"type":"Point"}
}