{
  "type": "Feature",
  "properties": {
    "addr:full":"Jupiter 23 Ulft Gelderland 7071 TN",
    "addr:housenumber":"23",
    "addr:postcode":"7071",
    "addr:street":"Jupiter;Gelderland",
    "iso:country":"NL",
    "sg:address":"Jupiter 23",
    "sg:city":"Ulft",
    "sg:orig_category":"Verbouwingen",
    "sg:phone":"+31 315 683 603",
    "sg:postcode":"7071 TN",
    "sg:province":"Gelderland",
    "wof:name":"Bindsbergen, W A Van",
    "wof:placetype":"venue"
},
  "geometry": {"coordinates":[6.378113,51.883511],"type":"Point"}
}