{
  "type": "Feature",
  "properties": {
    "iso:country":"NL",
    "sg:address":"Berkenlaan 35",
    "sg:city":"Aalsmeer",
    "sg:orig_category":"Goederenvervoer Over De Weg",
    "sg:phone":"+31 297 345 364",
    "sg:postcode":"1431 JD",
    "sg:province":"Noord-Holland",
    "wof:name":"H. Jongkind",
    "wof:placetype":"venue"
},
  "geometry": {"coordinates":[4.768543,52.265762],"type":"Point"}
}