{
  "type": "Feature",
  "properties": {
    "addr:full":"Bloemenhof 2 Oosterhout Nb North Brabant 4904 CA",
    "addr:housenumber":"2;nb",
    "addr:postcode":"4904 ca",
    "addr:street":"Bloemenhof",
    "iso:country":"NL",
    "sg:address":"Bloemenhof 2",
    "sg:city":"Oosterhout Nb",
    "sg:orig_category":"Overheidsdiensten",
    "sg:phone":"+31 162 460 521",
    "sg:postcode":"4904 CA",
    "sg:province":"North Brabant",
    "wof:name":"Stichting Niba Oosterhout",
    "wof:placetype":"venue"
},
  "geometry": {"coordinates":[4.8589878082,51.6287002563],"type":"Point"}
}