{
  "type": "Feature",
  "properties": {
    "addr:full":"V Hasseltkd 21 Maastricht Limburg 6211 CD",
    "addr:housenumber":"21",
    "addr:postcode":"6211 cd",
    "iso:country":"NL",
    "sg:address":"V Hasseltkd 21",
    "sg:city":"Maastricht",
    "sg:orig_category":"Gehandicapteninformatie",
    "sg:phone":"+31 43 325 2575",
    "sg:postcode":"6211 CD",
    "sg:province":"Limburg",
    "sg:website":"http://www.start.nl",
    "wof:name":"Start Kans",
    "wof:placetype":"venue"
},
  "geometry": {"coordinates":[5.68829,50.849831],"type":"Point"}
}