{
  "type": "Feature",
  "properties": {
    "addr:full":"Biezeveld 1 Bladel Noord-Brabant 5531 BX",
    "addr:housenumber":"1",
    "addr:postcode":"5531 bx",
    "addr:street":"Biezeveld",
    "iso:country":"NL",
    "sg:address":"Biezeveld 1",
    "sg:city":"Bladel",
    "sg:orig_category":"Boekenuitgeverijen",
    "sg:phone":"+31 497 387 686",
    "sg:postcode":"5531 BX",
    "sg:province":"Noord-Brabant",
    "wof:name":"Vof Uitgeverij De Voorslag",
    "wof:placetype":"venue"
},
  "geometry": {"coordinates":[5.21124,51.372238],"type":"Point"}
}