{
  "type": "Feature",
  "properties": {
    "iso:country":"NL",
    "sg:address":"Klompmakkersstr 1",
    "sg:city":"Bergum",
    "sg:orig_category":"Advocaten En Advocatenkantoren",
    "sg:phone":"+31 511 460 250",
    "sg:postcode":"9251 EG",
    "sg:province":"Friesland",
    "wof:name":"Hoef, Van Der",
    "wof:placetype":"venue"
},
  "geometry": {"coordinates":[5.986921,53.19529],"type":"Point"}
}