{
  "type": "Feature",
  "properties": {
    "iso:country":"NL",
    "sg:address":"Oosterstraat 38",
    "sg:city":"Groningen",
    "sg:orig_category":"Opticiens",
    "sg:phone":"+31 50 312 2358",
    "sg:postcode":"9711 NV",
    "sg:province":"Groningen",
    "wof:name":"W Vrind",
    "wof:placetype":"venue"
},
  "geometry": {"coordinates":[6.5700531006,53.2171859741],"type":"Point"}
}