{
  "type": "Feature",
  "properties": {
    "iso:country":"NL",
    "sg:address":"Zonnedauw 5",
    "sg:city":"Uitgeest",
    "sg:orig_category":"Medische Installaties En Instrumenten",
    "sg:phone":"+31 251 318 778",
    "sg:postcode":"1911 PT",
    "sg:province":"Noord-Holland",
    "wof:name":"Marpeja",
    "wof:placetype":"venue"
},
  "geometry": {"coordinates":[4.708344,52.538033],"type":"Point"}
}