{
  "type": "Feature",
  "properties": {
    "addr:full":"D V Leydenwg 4 Oostvoorne Zuid-Holland 3233 TE",
    "addr:housenumber":"4",
    "addr:postcode":"3233 te",
    "addr:street":"D;Leydenwg",
    "iso:country":"NL",
    "sg:address":"D V Leydenwg 4",
    "sg:city":"Oostvoorne",
    "sg:orig_category":"Psychologen",
    "sg:phone":"+31 181 483 091",
    "sg:postcode":"3233 TE",
    "sg:province":"Zuid-Holland",
    "wof:name":"Vis, L E",
    "wof:placetype":"venue"
},
  "geometry": {"coordinates":[4.103859,51.913956],"type":"Point"}
}