{
  "type": "Feature",
  "properties": {
    "iso:country":"NL",
    "sg:address":"Anodewg 9",
    "sg:city":"Hoorn Nh",
    "sg:orig_category":"Gedistilleerd En Likeuren - Groothandel",
    "sg:phone":"+31 229 217 175",
    "sg:postcode":"1627 LJ",
    "sg:province":"Noord-Holland",
    "wof:name":"Slammers Bv",
    "wof:placetype":"venue"
},
  "geometry": {"coordinates":[5.103195,52.63818],"type":"Point"}
}