{
  "type": "Feature",
  "properties": {
    "addr:full":"Kanaaldk 40A Landsmeer Noord-Holland 1121 NX",
    "addr:housenumber":"40a",
    "addr:postcode":"1121 nx",
    "addr:street":"Kanaaldk",
    "iso:country":"NL",
    "sg:address":"Kanaaldk 40A",
    "sg:city":"Landsmeer",
    "sg:orig_category":"Loodgieters",
    "sg:phone":"+31 20 492 4494",
    "sg:postcode":"1121 NX",
    "sg:province":"Noord-Holland",
    "sg:website":"http://www.willingloodgieters.nl",
    "wof:name":"Willing Vof",
    "wof:placetype":"venue"
},
  "geometry": {"coordinates":[4.949956,52.438755],"type":"Point"}
}