{
  "type": "Feature",
  "properties": {
    "addr:full":"Noorderstationsstraat 17 Groningen Groningen 9716 AN",
    "addr:housenumber":"17",
    "addr:postcode":"9716 an",
    "addr:street":"Noorderstationsstraat",
    "iso:country":"NL",
    "sg:address":"Noorderstationsstraat 17",
    "sg:city":"Groningen",
    "sg:orig_category":"Kappers",
    "sg:phone":"+31 50 571 0062",
    "sg:postcode":"9716 AN",
    "sg:province":"Groningen",
    "wof:name":"Kapsalon Hartlief",
    "wof:placetype":"venue"
},
  "geometry": {"coordinates":[6.5598697662,53.2286338806],"type":"Point"}
}