{
  "type": "Feature",
  "properties": {
    "addr:full":"Dorpsstr 32 Moerkapelle South Holland 2751 BA",
    "addr:housenumber":"32",
    "addr:postcode":"2751 ba",
    "addr:street":"Dorpsstr",
    "iso:country":"NL",
    "sg:address":"Dorpsstr 32",
    "sg:city":"Moerkapelle",
    "sg:orig_category":"Postkantoren",
    "sg:phone":"+31 79 593 1485",
    "sg:postcode":"2751 BA",
    "sg:province":"South Holland",
    "sg:website":"http://www.postkantoor.nl",
    "wof:name":"Postkantoor",
    "wof:placetype":"venue"
},
  "geometry": {"coordinates":[4.575687,52.043465],"type":"Point"}
}