{
  "type": "Feature",
  "properties": {
    "addr:full":"B Shawsngl 292 Amsterdam Zuidoost North Holland 1102 VE",
    "addr:housenumber":"292",
    "addr:postcode":"1102",
    "addr:street":"Ve",
    "iso:country":"NL",
    "sg:address":"B Shawsngl 292",
    "sg:city":"Amsterdam Zuidoost",
    "sg:orig_category":"Webdesign Bureaus",
    "sg:phone":"+31 20 695 2652",
    "sg:postcode":"1102 VE",
    "sg:province":"North Holland",
    "wof:name":"Detlevski",
    "wof:placetype":"venue"
},
  "geometry": {"coordinates":[4.9513149261,52.3161659241],"type":"Point"}
}