{
  "type": "Feature",
  "properties": {
    "addr:full":"Goudsbloemstr 12 Culemborg Gelderland 4101 GZ",
    "addr:housenumber":"12",
    "addr:postcode":"4101 gz",
    "addr:street":"Goudsbloemstr;Gelderland",
    "iso:country":"NL",
    "sg:address":"Goudsbloemstr 12",
    "sg:city":"Culemborg",
    "sg:orig_category":"Etalageverzorging",
    "sg:phone":"+31 345 520 510",
    "sg:postcode":"4101 GZ",
    "sg:province":"Gelderland",
    "wof:name":"Arler Etalage Styling",
    "wof:placetype":"venue"
},
  "geometry": {"coordinates":[5.232477,51.955441],"type":"Point"}
}