{
  "type": "Feature",
  "properties": {
    "iso:country":"NL",
    "sg:address":"Monnikensteeg 29",
    "sg:city":"Arnhem",
    "sg:orig_category":"Schilderwerk",
    "sg:phone":"+31 26 370 4339",
    "sg:postcode":"6823 AA",
    "sg:province":"Gelderland",
    "wof:name":"Schrijen V Spreeken Schilders",
    "wof:placetype":"venue"
},
  "geometry": {"coordinates":[5.932687,51.994869],"type":"Point"}
}