{
  "type": "Feature",
  "properties": {
    "addr:full":"Dorpsstraat 65 Nootdorp Zuid-Holland 2631 CS",
    "addr:housenumber":"65",
    "addr:postcode":"2631 cs",
    "addr:street":"Dorpsstraat",
    "iso:country":"NL",
    "sg:address":"Dorpsstraat 65",
    "sg:city":"Nootdorp",
    "sg:orig_category":"Bejaardeninstellingen And Serviceflats",
    "sg:phone":"+31 15 310 8951",
    "sg:postcode":"2631 CS",
    "sg:province":"Zuid-Holland",
    "wof:name":"Zorgcentrum Veenhage",
    "wof:placetype":"venue"
},
  "geometry": {"coordinates":[4.397688,52.044502],"type":"Point"}
}