{
  "type": "Feature",
  "properties": {
    "addr:full":"Rotterdam Airportbaan 22 Rotterdam Zuid-Holland 3045 AN",
    "addr:housenumber":"22",
    "addr:postcode":"3045 an",
    "addr:street":"Rotterdam Airportbaan",
    "iso:country":"NL",
    "sg:address":"Rotterdam Airportbaan 22",
    "sg:city":"Rotterdam",
    "sg:orig_category":"Advocaten And Juridische Adviseurs",
    "sg:phone":"+31 10 245 9950",
    "sg:postcode":"3045 AN",
    "sg:province":"Zuid-Holland",
    "wof:name":"Vree & De Man Advocaten En Belastingadviseurs",
    "wof:placetype":"venue"
},
  "geometry": {"coordinates":[4.429406,51.947582],"type":"Point"}
}