{
  "type": "Feature",
  "properties": {
    "addr:full":"Aan De Poel 9 Arcen Limburg 5944 ES",
    "addr:housenumber":"9",
    "addr:postcode":"5944 es",
    "addr:street":"Aan De Poel",
    "iso:country":"NL",
    "sg:address":"Aan De Poel 9",
    "sg:city":"Arcen",
    "sg:orig_category":"Marktonderzoekbureaus",
    "sg:phone":"+31 77 473 1901",
    "sg:postcode":"5944 ES",
    "sg:province":"Limburg",
    "wof:name":"Red Line",
    "wof:placetype":"venue"
},
  "geometry": {"coordinates":[6.182328,51.477306],"type":"Point"}
}