{
  "type": "Feature",
  "properties": {
    "addr:full":"Energiewg 28 Beneden Leeuwen Gelderland 6658 AD",
    "addr:housenumber":"28",
    "addr:postcode":"6658 ad",
    "addr:street":"Energiewg",
    "iso:country":"NL",
    "sg:address":"Energiewg 28",
    "sg:city":"Beneden Leeuwen",
    "sg:orig_category":"Houtgroothandel",
    "sg:phone":"+31 487 592 062",
    "sg:postcode":"6658 AD",
    "sg:province":"Gelderland",
    "wof:name":"Apk Bv",
    "wof:placetype":"venue"
},
  "geometry": {"coordinates":[5.528659,51.886581],"type":"Point"}
}