{
  "type": "Feature",
  "properties": {
    "addr:full":"Heinsiusstraat 1 Groningen Groningen 9716 AV",
    "addr:housenumber":"1",
    "addr:postcode":"9716 av",
    "addr:street":"Heinsiusstraat",
    "iso:country":"NL",
    "sg:address":"Heinsiusstraat 1",
    "sg:city":"Groningen",
    "sg:orig_category":"Volwassenenonderwijs",
    "sg:phone":"+31 50 571 0195",
    "sg:postcode":"9716 AV",
    "sg:province":"Groningen",
    "wof:name":"De Hamrik Chr Scholengemeensch Voor Mavo Vbo Ivbo",
    "wof:placetype":"venue"
},
  "geometry": {"coordinates":[6.558483,53.230148],"type":"Point"}
}