{
  "type": "Feature",
  "properties": {
    "addr:full":"Zwarteweg 29 Leusden Utrecht 3833 AK",
    "addr:housenumber":"29",
    "addr:postcode":"3833 ak",
    "addr:street":"Zwarteweg",
    "iso:country":"NL",
    "sg:address":"Zwarteweg 29",
    "sg:city":"Leusden",
    "sg:orig_category":"Fietshandelaren",
    "sg:phone":"+31 33 494 1418",
    "sg:postcode":"3833 AK",
    "sg:province":"Utrecht",
    "wof:name":"Bike Totaal",
    "wof:placetype":"venue"
},
  "geometry": {"coordinates":[5.425752,52.139954],"type":"Point"}
}