{
  "type": "Feature",
  "properties": {
    "addr:full":"Smeekwg 29 Laren Nh Noord-Holland 1251 VH",
    "addr:housenumber":"29",
    "addr:postcode":"1251 vh",
    "addr:street":"Smeekwg",
    "iso:country":"NL",
    "sg:address":"Smeekwg 29",
    "sg:city":"Laren Nh",
    "sg:orig_category":"Kappers",
    "sg:phone":"+31 35 531 2778",
    "sg:postcode":"1251 VH",
    "sg:province":"Noord-Holland",
    "wof:name":"Jos? Kapsalon Laren",
    "wof:placetype":"venue"
},
  "geometry": {"coordinates":[5.2331628799,52.2484893799],"type":"Point"}
}