{
  "type": "Feature",
  "properties": {
    "addr:full":"Bassingracht 8 Den Helder Noord-Holland 1781 CE",
    "addr:housenumber":"8",
    "addr:postcode":"1781 ce",
    "addr:street":"Bassingracht",
    "iso:country":"NL",
    "sg:address":"Bassingracht 8",
    "sg:city":"Den Helder",
    "sg:orig_category":"Artiesten",
    "sg:phone":"+31 223 684 153",
    "sg:postcode":"1781 CE",
    "sg:province":"Noord-Holland",
    "wof:name":"J Dokter",
    "wof:placetype":"venue"
},
  "geometry": {"coordinates":[4.772427,52.955379],"type":"Point"}
}