{
  "type": "Feature",
  "properties": {
    "addr:full":"Burgemeester Weertsstr 19 Arnhem Gelderland 6814 HL",
    "addr:housenumber":"19",
    "addr:postcode":"6814 hl",
    "addr:street":"Burgemeester Weertsstr",
    "iso:country":"NL",
    "sg:address":"Burgemeester Weertsstr 19",
    "sg:city":"Arnhem",
    "sg:orig_category":"Metaalwerken",
    "sg:phone":"+31 26 443 9170",
    "sg:postcode":"6814 HL",
    "sg:province":"Gelderland",
    "wof:name":"Beekman Zonwering",
    "wof:placetype":"venue"
},
  "geometry": {"coordinates":[5.898262,51.989628],"type":"Point"}
}