{
  "type": "Feature",
  "properties": {
    "addr:full":"Kouvenderstr 222 Hoensbroek Limburg 6431 HJ",
    "addr:housenumber":"222",
    "addr:postcode":"6431 hj",
    "addr:street":"Hoensbroek Limburg",
    "iso:country":"NL",
    "sg:address":"Kouvenderstr 222",
    "sg:city":"Hoensbroek",
    "sg:orig_category":"Artsen - Huisartsen",
    "sg:phone":"+31 45 528 0088",
    "sg:postcode":"6431 HJ",
    "sg:province":"Limburg",
    "wof:name":"Emma Huisartsenpraktijk",
    "wof:placetype":"venue"
},
  "geometry": {"coordinates":[5.936812,50.927883],"type":"Point"}
}