{
  "type": "Feature",
  "properties": {
    "iso:country":"NL",
    "sg:address":"Raadhuisplein 1",
    "sg:city":"Arcen",
    "sg:orig_category":"Overheidsdiensten",
    "sg:phone":"+31 77 473 7777",
    "sg:postcode":"5944 AH",
    "sg:province":"Limburg",
    "wof:name":"Gemeente Arcen En Velden",
    "wof:placetype":"venue"
},
  "geometry": {"coordinates":[6.1795930862,51.4737854004],"type":"Point"}
}