{
  "type": "Feature",
  "properties": {
    "iso:country":"NL",
    "sg:address":"Osdorppln 773",
    "sg:city":"Amsterdam",
    "sg:orig_category":"Hoortoestellen",
    "sg:phone":"+31 20 667 4836",
    "sg:postcode":"1068 TC",
    "sg:province":"North Holland",
    "sg:website":"http://www.beterhoren.nl",
    "wof:name":"Beter Horen",
    "wof:placetype":"venue"
},
  "geometry": {"coordinates":[4.806687,52.358608],"type":"Point"}
}