{
  "type": "Feature",
  "properties": {
    "iso:country":"NL",
    "sg:address":"Bezuidenhoutsewg 253",
    "sg:city":"S Gravenhage",
    "sg:orig_category":"Scholen Voor Basisonderwijs",
    "sg:phone":"+31 70 331 5252",
    "sg:postcode":"2594 AM",
    "sg:province":"Zuid-Holland",
    "wof:name":"Vbs",
    "wof:placetype":"venue"
},
  "geometry": {"coordinates":[4.317415,52.083992],"type":"Point"}
}