{
  "type": "Feature",
  "properties": {
    "iso:country":"NL",
    "sg:address":"Evenaar 286A",
    "sg:city":"Alphen Aan Den Ryn",
    "sg:orig_category":"Kinderopvang",
    "sg:phone":"+31 172 475 055",
    "sg:postcode":"2408 ND",
    "sg:province":"Zuid-Holland",
    "wof:name":"Dikkertje Dap",
    "wof:placetype":"venue"
},
  "geometry": {"coordinates":[4.650375,52.12151],"type":"Point"}
}