{
  "type": "Feature",
  "properties": {
    "addr:full":"Bredasewg 106C Oosterhout Nb North Brabant 4902 NS",
    "addr:housenumber":"106c;nb",
    "addr:postcode":"4902 ns",
    "addr:street":"Bredasewg",
    "iso:country":"NL",
    "sg:address":"Bredasewg 106C",
    "sg:city":"Oosterhout Nb",
    "sg:orig_category":"Kantoor- En Bedrijfsmeubelen",
    "sg:phone":"+31 162 460 375",
    "sg:postcode":"4902 NS",
    "sg:province":"North Brabant",
    "wof:name":"Horst, Ter",
    "wof:placetype":"venue"
},
  "geometry": {"coordinates":[4.8485589027,51.6397285461],"type":"Point"}
}