{
  "type": "Feature",
  "properties": {
    "addr:full":"St. Jozefweg 1 Venray Limburg 5801 CW",
    "addr:housenumber":"1",
    "addr:postcode":"5801 cw",
    "addr:street":"St. Jozefweg",
    "iso:country":"NL",
    "sg:address":"St. Jozefweg 1",
    "sg:city":"Venray",
    "sg:orig_category":"Werving And Selectie Van Vast Personeel",
    "sg:phone":"+31 478 524 124",
    "sg:postcode":"5801 CW",
    "sg:province":"Limburg",
    "wof:name":"Arbeidsbureau Venray",
    "wof:placetype":"venue"
},
  "geometry": {"coordinates":[5.9724931717,51.5307579041],"type":"Point"}
}