{
  "type": "Feature",
  "properties": {
    "iso:country":"NL",
    "sg:address":"Adm De Ruyterwg 67",
    "sg:city":"Amsterdam",
    "sg:orig_category":"Kappers",
    "sg:phone":"+31 20 612 7144",
    "sg:postcode":"1057 JX",
    "sg:province":"Noord-Holland",
    "wof:name":"Corrosa",
    "wof:placetype":"venue"
},
  "geometry": {"coordinates":[4.8536400795,52.3675193787],"type":"Point"}
}