{
  "type": "Feature",
  "properties": {
    "addr:full":"Kerkstr 85 Oisterwyk Noord-Brabant 5061 EH",
    "addr:housenumber":"85",
    "addr:postcode":"5061 eh",
    "addr:street":"Kerkstr",
    "iso:country":"NL",
    "sg:address":"Kerkstr 85",
    "sg:city":"Oisterwyk",
    "sg:orig_category":"Adviesbureaus Bedrijfsorganisatie",
    "sg:phone":"+31 13 523 0511",
    "sg:postcode":"5061 EH",
    "sg:province":"Noord-Brabant",
    "sg:website":"http://www.dejongenvanveggel.nl",
    "wof:name":"Jong En Van Veggel, De",
    "wof:placetype":"venue"
},
  "geometry": {"coordinates":[5.185852,51.578957],"type":"Point"}
}