{
  "type": "Feature",
  "properties": {
    "addr:full":"Windestraat 34 Badhoevedorp Noord-Holland 1171 KA",
    "addr:housenumber":"34",
    "addr:postcode":"1171 ka",
    "addr:street":"Windestraat",
    "iso:country":"NL",
    "sg:address":"Windestraat 34",
    "sg:city":"Badhoevedorp",
    "sg:orig_category":"Marktonderzoekbureaus",
    "sg:phone":"+31 20 659 7454",
    "sg:postcode":"1171 KA",
    "sg:province":"Noord-Holland",
    "wof:name":"Marketing Consultant Stefania Mignone",
    "wof:placetype":"venue"
},
  "geometry": {"coordinates":[4.795835,52.332077],"type":"Point"}
}