{
  "type": "Feature",
  "properties": {
    "iso:country":"NL",
    "sg:address":"Schansdk 26",
    "sg:city":"Zevenbergen",
    "sg:orig_category":"Antiquiteiten",
    "sg:phone":"+31 168 329 705",
    "sg:postcode":"4761 RH",
    "sg:province":"Noord-Brabant",
    "sg:website":"http://www.acz.nl",
    "wof:name":"Antiekcentrum Zevenbergen",
    "wof:placetype":"venue"
},
  "geometry": {"coordinates":[4.60761,51.658028],"type":"Point"}
}