{
  "type": "Feature",
  "properties": {
    "addr:full":"Dobbe 69 Zwolle Overijssel 8032 JX",
    "addr:housenumber":"69",
    "addr:postcode":"8032 jx",
    "addr:street":"Dobbe",
    "iso:country":"NL",
    "sg:address":"Dobbe 69",
    "sg:city":"Zwolle",
    "sg:orig_category":"Sportcentra",
    "sg:phone":"+31 38 454 8485",
    "sg:postcode":"8032 JX",
    "sg:province":"Overijssel",
    "wof:name":"Squash Zwolle Bv",
    "wof:placetype":"venue"
},
  "geometry": {"coordinates":[6.102843,52.528301],"type":"Point"}
}