{
  "type": "Feature",
  "properties": {
    "addr:full":"Heerlerbaan 201 Heerlen Limburg 6418 CD",
    "addr:housenumber":"201",
    "addr:postcode":"6418 cd",
    "addr:street":"Heerlerbaan",
    "iso:country":"NL",
    "sg:address":"Heerlerbaan 201",
    "sg:city":"Heerlen",
    "sg:orig_category":"Bloemen And Planten",
    "sg:phone":"+31 45 541 9878",
    "sg:postcode":"6418 CD",
    "sg:province":"Limburg",
    "wof:name":"T Bloemenhofke",
    "wof:placetype":"venue"
},
  "geometry": {"coordinates":[6.00175,50.866112],"type":"Point"}
}