{
  "type": "Feature",
  "properties": {
    "iso:country":"NL",
    "sg:address":"Leendert Tulplaan 6",
    "sg:city":"Ede Gld",
    "sg:orig_category":"Autokeuringen",
    "sg:phone":"+31 318 616 721",
    "sg:postcode":"6713 AW",
    "sg:province":"Gelderland",
    "wof:name":"Garagebedrijf Rien Meijer",
    "wof:placetype":"venue"
},
  "geometry": {"coordinates":[5.664246,52.042191],"type":"Point"}
}