{
  "type": "Feature",
  "properties": {
    "addr:full":"P Poststr 13A Eindhoven Noord-Brabant 5624 BE",
    "addr:housenumber":"13a",
    "addr:postcode":"5624",
    "addr:street":"P",
    "iso:country":"NL",
    "sg:address":"P Poststr 13A",
    "sg:city":"Eindhoven",
    "sg:orig_category":"Scholen Voor Basisonderwijs",
    "sg:phone":"+31 40 244 1242",
    "sg:postcode":"5624 BE",
    "sg:province":"Noord-Brabant",
    "wof:name":"Opbouw Openb, De",
    "wof:placetype":"venue"
},
  "geometry": {"coordinates":[5.456695,51.46347],"type":"Point"}
}