{
  "type": "Feature",
  "properties": {
    "iso:country":"NL",
    "sg:address":"Bedrijvenweg 1",
    "sg:city":"Nieuw Amsterdam",
    "sg:orig_category":"Vaste And Vloeibare Brandstoffen",
    "sg:phone":"+31 591 551 400",
    "sg:postcode":"7833 JG",
    "sg:province":"Drenthe",
    "wof:name":"Witvoet Olieprodukten Bv",
    "wof:placetype":"venue"
},
  "geometry": {"coordinates":[-74.122322,42.913319],"type":"Point"}
}