{
  "type": "Feature",
  "properties": {
    "addr:full":"Ganzepoortstraat 18 Goes Zeeland 4461 JZ",
    "addr:housenumber":"18",
    "addr:postcode":"4461 jz",
    "addr:street":"Ganzepoortstraat",
    "iso:country":"NL",
    "sg:address":"Ganzepoortstraat 18",
    "sg:city":"Goes",
    "sg:orig_category":"Opticiens",
    "sg:phone":"+31 113 232 143",
    "sg:postcode":"4461 JZ",
    "sg:province":"Zeeland",
    "wof:name":"Hans Anders Opticiens/810",
    "wof:placetype":"venue"
},
  "geometry": {"coordinates":[-83.9141693115,39.7688331604],"type":"Point"}
}