{
  "type": "Feature",
  "properties": {
    "iso:country":"NL",
    "sg:address":"Heerestraat 23",
    "sg:city":"Leeuwarden",
    "sg:orig_category":"Fitnesscentra",
    "sg:phone":"+31 58 215 5155",
    "sg:postcode":"8911 LC",
    "sg:province":"Friesland",
    "wof:name":"Aerobic-School Marijke",
    "wof:placetype":"venue"
},
  "geometry": {"coordinates":[5.799123,53.201508],"type":"Point"}
}