{
  "type": "Feature",
  "properties": {
    "addr:full":"Hendrinaland 64 S Gravenhage Zuid-Holland 2591 TL",
    "addr:housenumber":"64;gravenhage",
    "addr:postcode":"2591 tl",
    "addr:street":"Hendrinaland;S",
    "iso:country":"NL",
    "sg:address":"Hendrinaland 64",
    "sg:city":"S Gravenhage",
    "sg:orig_category":"Vertalers",
    "sg:phone":"+31 70 385 9613",
    "sg:postcode":"2591 TL",
    "sg:province":"Zuid-Holland",
    "wof:name":"Interloose",
    "wof:placetype":"venue"
},
  "geometry": {"coordinates":[4.3639,52.09351],"type":"Point"}
}