{
  "type": "Feature",
  "properties": {
    "addr:full":"Ruimzicht 7 Amsterdam Noord-Holland 1068 CL",
    "addr:housenumber":"7",
    "addr:postcode":"1068",
    "addr:street":"Ruimzicht",
    "iso:country":"NL",
    "sg:address":"Ruimzicht 7",
    "sg:city":"Amsterdam",
    "sg:classifiers":[
        {
            "category":"Real Estate",
            "subcategory":"Real Estate Operator",
            "type":"Services"
        }
    ],
    "sg:phone":"+31 20 619 5011",
    "sg:postcode":"1068 CL",
    "sg:province":"Noord-Holland",
    "sg:tags":[
        "appartementen",
        "en",
        "flat"
    ],
    "wof:name":"Panorama Torenwijck",
    "wof:placetype":"venue"
},
  "geometry": {"coordinates":[4.80699,52.362579],"type":"Point"}
}