{
  "type": "Feature",
  "properties": {
    "addr:full":"Zutphensestr 319 Apeldoorn Gelderland 7325 WT",
    "addr:housenumber":"319",
    "addr:postcode":"7325 wt",
    "addr:street":"Gelderland",
    "iso:country":"NL",
    "sg:address":"Zutphensestr 319",
    "sg:city":"Apeldoorn",
    "sg:orig_category":"Aggregaten",
    "sg:phone":"+31 55 301 8501",
    "sg:postcode":"7325 WT",
    "sg:province":"Gelderland",
    "sg:website":"http://www.bredenoord.nl",
    "wof:name":"Bredenoord Aggregaten",
    "wof:placetype":"venue"
},
  "geometry": {"coordinates":[6.05603,52.197029],"type":"Point"}
}