{
  "type": "Feature",
  "properties": {
    "addr:full":"Boterbloemwg 200 Alphen Aan Den Ryn Zuid-Holland 2403 TZ",
    "addr:housenumber":"200",
    "addr:postcode":"2403 tz",
    "addr:street":"Aan Den Ryn",
    "iso:country":"NL",
    "sg:address":"Boterbloemwg 200",
    "sg:city":"Alphen Aan Den Ryn",
    "sg:orig_category":"Verenigingsgebouwen",
    "sg:phone":"+31 172 421 740",
    "sg:postcode":"2403 TZ",
    "sg:province":"Zuid-Holland",
    "wof:name":"Boterbloem, De",
    "wof:placetype":"venue"
},
  "geometry": {"coordinates":[4.687866,52.147194],"type":"Point"}
}