{
  "type": "Feature",
  "properties": {
    "addr:full":"Klaverbladstr 22 Klaaswaal South Holland 3286 VR",
    "addr:housenumber":"22",
    "addr:postcode":"3286 vr",
    "addr:street":"Klaverbladstr",
    "iso:country":"NL",
    "sg:address":"Klaverbladstr 22",
    "sg:city":"Klaaswaal",
    "sg:orig_category":"Autorijscholen",
    "sg:phone":"+31 186 574 416",
    "sg:postcode":"3286 VR",
    "sg:province":"South Holland",
    "wof:name":"Zwart, P H Van Der",
    "wof:placetype":"venue"
},
  "geometry": {"coordinates":[4.44887,51.772781],"type":"Point"}
}