{
  "type": "Feature",
  "properties": {
    "addr:full":"Veldstraat 19 Putten Gelderland 3881 JM",
    "addr:housenumber":"19",
    "addr:postcode":"3881 jm",
    "addr:street":"Veldstraat;Gelderland",
    "iso:country":"NL",
    "sg:address":"Veldstraat 19",
    "sg:city":"Putten",
    "sg:orig_category":"Meubelreparatie And -Restauratie",
    "sg:phone":"+31 341 360 249",
    "sg:postcode":"3881 JM",
    "sg:province":"Gelderland",
    "wof:name":"Arel Stofferingen",
    "wof:placetype":"venue"
},
  "geometry": {"coordinates":[5.610261,52.254997],"type":"Point"}
}