{
  "type": "Feature",
  "properties": {
    "addr:full":"Seinwachterstr 46 Amsterdam Noord-Holland 1019 TE",
    "addr:housenumber":"46;1019",
    "addr:postcode":"te",
    "addr:street":"Seinwachterstr",
    "iso:country":"NL",
    "sg:address":"Seinwachterstr 46",
    "sg:city":"Amsterdam",
    "sg:orig_category":"Vertaalbureaus",
    "sg:phone":"+31 20 421 8949",
    "sg:postcode":"1019 TE",
    "sg:province":"Noord-Holland",
    "sg:website":"http://www.feiken.com",
    "wof:name":"Feiken",
    "wof:placetype":"venue"
},
  "geometry": {"coordinates":[4.947326,52.37421],"type":"Point"}
}