{
  "type": "Feature",
  "properties": {
    "addr:full":"Kromstraat 1 Veldhoven Noord-Brabant 5504 BA",
    "addr:housenumber":"1",
    "addr:postcode":"5504 ba",
    "addr:street":"Kromstraat",
    "iso:country":"NL",
    "sg:address":"Kromstraat 1",
    "sg:city":"Veldhoven",
    "sg:orig_category":"Kappers",
    "sg:phone":"+31 40 254 5329",
    "sg:postcode":"5504 BA",
    "sg:province":"Noord-Brabant",
    "wof:name":"Knipperij Rene",
    "wof:placetype":"venue"
},
  "geometry": {"coordinates":[5.396516,51.403782],"type":"Point"}
}