{
  "type": "Feature",
  "properties": {
    "iso:country":"NL",
    "sg:address":"Oude Maasdijk 39",
    "sg:city":"Dreumel",
    "sg:orig_category":"Boekhouders",
    "sg:phone":"+31 487 572 041",
    "sg:postcode":"6621 AB",
    "sg:province":"Gelderland",
    "wof:name":"Administratie & Advies Buro Gelderland",
    "wof:placetype":"venue"
},
  "geometry": {"coordinates":[5.426592,51.83614],"type":"Point"}
}