{
  "type": "Feature",
  "properties": {
    "addr:full":"Kapelstraat 33 Bussum Noord-Holland 1404 HV",
    "addr:housenumber":"33",
    "addr:postcode":"1404 hv",
    "addr:street":"Kapelstraat",
    "iso:country":"NL",
    "sg:address":"Kapelstraat 33",
    "sg:city":"Bussum",
    "sg:orig_category":"Werving And Selectie Van Tijdelijk Personeel And Uitzendkantoren",
    "sg:phone":"+31 35 692 1606",
    "sg:postcode":"1404 HV",
    "sg:province":"Noord-Holland",
    "wof:name":"Manpower",
    "wof:placetype":"venue"
},
  "geometry": {"coordinates":[5.1647930145,52.273853302],"type":"Point"}
}