{
  "type": "Feature",
  "properties": {
    "addr:full":"Grebberstr 50 Haarlem Noord-Holland 2021 ZB",
    "addr:housenumber":"50",
    "addr:postcode":"2021 zb",
    "addr:street":"Grebberstr",
    "iso:country":"NL",
    "sg:address":"Grebberstr 50",
    "sg:city":"Haarlem",
    "sg:orig_category":"Vertalers",
    "sg:phone":"+31 23 527 1345",
    "sg:postcode":"2021 ZB",
    "sg:province":"Noord-Holland",
    "wof:name":"Koning, A",
    "wof:placetype":"venue"
},
  "geometry": {"coordinates":[4.63488,52.391556],"type":"Point"}
}