{
  "type": "Feature",
  "properties": {
    "iso:country":"NL",
    "sg:address":"Hogekampweg 20",
    "sg:city":"Venlo",
    "sg:orig_category":"Verhuur Voertuigen Behalve Auto'S",
    "sg:phone":"+31 6 55130300",
    "sg:postcode":"5913 TS",
    "sg:province":"Limburg",
    "wof:name":"Sco-Rent",
    "wof:placetype":"venue"
},
  "geometry": {"coordinates":[6.178345,51.365189],"type":"Point"}
}