{
  "type": "Feature",
  "properties": {
    "iso:country":"NL",
    "sg:address":"Driehuizerkerkwg 46",
    "sg:city":"Driehuis Nh",
    "sg:orig_category":"Bloemen En Planten",
    "sg:phone":"+31 255 515 979",
    "sg:postcode":"1985 EM",
    "sg:province":"Noord-Holland",
    "wof:name":"Arabesque",
    "wof:placetype":"venue"
},
  "geometry": {"coordinates":[4.637254,52.448566],"type":"Point"}
}