{
  "type": "Feature",
  "properties": {
    "iso:country":"NL",
    "sg:address":"Nobelstr 4",
    "sg:city":"Hoogeveen",
    "sg:orig_category":"Offsetdrukkerijen",
    "sg:phone":"+31 528 231 068",
    "sg:postcode":"7903 BH",
    "sg:province":"Drenthe",
    "wof:name":"Hagen",
    "wof:placetype":"venue"
},
  "geometry": {"coordinates":[6.515024,52.728497],"type":"Point"}
}