{
  "type": "Feature",
  "properties": {
    "iso:country":"NL",
    "sg:address":"Dr Schaepmanln 3",
    "sg:city":"Amstelveen",
    "sg:orig_category":"Vertalers",
    "sg:phone":"+31 20 441 6637",
    "sg:postcode":"1182 GM",
    "sg:province":"Noord-Holland",
    "wof:name":"Maris, W A",
    "wof:placetype":"venue"
},
  "geometry": {"coordinates":[4.848608,52.304585],"type":"Point"}
}