{
  "type": "Feature",
  "properties": {
    "addr:full":"Zuiderstraat 178 Delft Zuid-Holland 2611 SJ",
    "addr:housenumber":"178",
    "addr:postcode":"2611",
    "addr:street":"Zuiderstraat",
    "iso:country":"NL",
    "sg:address":"Zuiderstraat 178",
    "sg:city":"Delft",
    "sg:orig_category":"Verlichting And Huishoudartikelen",
    "sg:phone":"+31 15 212 5550",
    "sg:postcode":"2611 SJ",
    "sg:province":"Zuid-Holland",
    "wof:name":"Lampenier",
    "wof:placetype":"venue"
},
  "geometry": {"coordinates":[4.364174,52.009388],"type":"Point"}
}