{
  "type": "Feature",
  "properties": {
    "addr:full":"Lorentzkd 224 Haarlem Noord-Holland 2014 CG",
    "addr:housenumber":"224",
    "addr:postcode":"2014 cg",
    "iso:country":"NL",
    "sg:address":"Lorentzkd 224",
    "sg:city":"Haarlem",
    "sg:orig_category":"Adviesbureaus Bedrijfsorganisatie",
    "sg:phone":"+31 23 524 3587",
    "sg:postcode":"2014 CG",
    "sg:province":"Noord-Holland",
    "wof:name":"Dorrepaal Bv",
    "wof:placetype":"venue"
},
  "geometry": {"coordinates":[4.611493,52.374928],"type":"Point"}
}