{
  "type": "Feature",
  "properties": {
    "addr:full":"Bekkenhaarszijweg 14 Hoge Hexel Overijssel 7645 AK",
    "addr:housenumber":"14",
    "addr:postcode":"7645 ak",
    "addr:street":"Bekkenhaarszijweg",
    "iso:country":"NL",
    "sg:address":"Bekkenhaarszijweg 14",
    "sg:city":"Hoge Hexel",
    "sg:orig_category":"Levende Dieren Gh",
    "sg:phone":"+31 546 697 291",
    "sg:postcode":"7645 AK",
    "sg:province":"Overijssel",
    "wof:name":"W. Schooten",
    "wof:placetype":"venue"
},
  "geometry": {"coordinates":[6.563553,52.397137],"type":"Point"}
}