{
  "type": "Feature",
  "properties": {
    "iso:country":"NL",
    "sg:address":"Oosterstr 31",
    "sg:city":"Groningen",
    "sg:orig_category":"Opticiens",
    "sg:phone":"+31 50 318 3348",
    "sg:postcode":"9711 NP",
    "sg:province":"Groningen",
    "sg:website":"http://www.bas-optiek.nl",
    "wof:name":"Bas Optiek",
    "wof:placetype":"venue"
},
  "geometry": {"coordinates":[6.5696229935,53.2173156738],"type":"Point"}
}