{
  "type": "Feature",
  "properties": {
    "iso:country":"NL",
    "sg:address":"Hagemuntwg 43",
    "sg:city":"Etten Leur",
    "sg:orig_category":"Hydrocultuur",
    "sg:phone":"+31 76 503 2282",
    "sg:postcode":"4879 NM",
    "sg:province":"North Brabant",
    "wof:name":"A58",
    "wof:placetype":"venue"
},
  "geometry": {"coordinates":[4.623596,51.555099],"type":"Point"}
}