{
  "type": "Feature",
  "properties": {
    "addr:full":"Kuilsburg 13A Delfzyl Groningen 9933 NB",
    "addr:housenumber":"13a",
    "addr:postcode":"9933 nb",
    "addr:street":"Kuilsburg",
    "iso:country":"NL",
    "sg:address":"Kuilsburg 13A",
    "sg:city":"Delfzyl",
    "sg:orig_category":"Schoenen - Reparaties",
    "sg:phone":"+31 596 630 852",
    "sg:postcode":"9933 NB",
    "sg:province":"Groningen",
    "wof:name":"Bakker",
    "wof:placetype":"venue"
},
  "geometry": {"coordinates":[6.912925,53.336266],"type":"Point"}
}