{
  "type": "Feature",
  "properties": {
    "iso:country":"NL",
    "sg:address":"Weth Vosstr 8",
    "sg:city":"Wanneperveen",
    "sg:orig_category":"Jachthavens - Jachtwerven",
    "sg:phone":"+31 522 282 211",
    "sg:postcode":"7946 AR",
    "sg:province":"Overijssel",
    "sg:website":"http://www.shipcleaning.nl",
    "wof:name":"Huiberts Ship Cleaning",
    "wof:placetype":"venue"
},
  "geometry": {"coordinates":[6.120162,52.702953],"type":"Point"}
}