{
  "type": "Feature",
  "properties": {
    "addr:full":"Gentsestraat 8 Hulst Zeeland 4561 EJ",
    "addr:housenumber":"8",
    "addr:postcode":"4561 ej",
    "addr:street":"Gentsestraat",
    "iso:country":"NL",
    "sg:address":"Gentsestraat 8",
    "sg:city":"Hulst",
    "sg:orig_category":"Vers Brood And Banket Fab",
    "sg:phone":"+31 114 312 360",
    "sg:postcode":"4561 EJ",
    "sg:province":"Zeeland",
    "wof:name":"Rich. Van Rie Brood-Banket",
    "wof:placetype":"venue"
},
  "geometry": {"coordinates":[4.052772,51.279873],"type":"Point"}
}