{
  "type": "Feature",
  "properties": {
    "addr:full":"Draaiboom 55 Lage Mierde Noord-Brabant 5094 CB",
    "addr:housenumber":"55",
    "addr:postcode":"5094 cb",
    "addr:street":"Draaiboom",
    "iso:country":"NL",
    "sg:address":"Draaiboom 55",
    "sg:city":"Lage Mierde",
    "sg:orig_category":"Beeldende Kunstenaars",
    "sg:phone":"+31 13 509 2811",
    "sg:postcode":"5094 CB",
    "sg:province":"Noord-Brabant",
    "wof:name":"Stallenberg",
    "wof:placetype":"venue"
},
  "geometry": {"coordinates":[5.151697,51.402119],"type":"Point"}
}