{
  "type": "Feature",
  "properties": {
    "addr:full":"Hanzewg 14B Lochem Gelderland 7241 CS",
    "addr:housenumber":"14b",
    "addr:postcode":"7241 cs",
    "addr:street":"Hanzewg;Gelderland",
    "iso:country":"NL",
    "sg:address":"Hanzewg 14B",
    "sg:city":"Lochem",
    "sg:classifiers":[
        {
            "category":"Retail",
            "subcategory":"Auto Repair",
            "type":"Services"
        }
    ],
    "sg:phone":"+31 573 258 533",
    "sg:postcode":"7241 CS",
    "sg:province":"Gelderland",
    "sg:tags":[
        "garage"
    ],
    "wof:name":"Oostrum, Rudolf Van",
    "wof:placetype":"venue"
},
  "geometry": {"coordinates":[6.412209,52.165333],"type":"Point"}
}