{
  "type": "Feature",
  "properties": {
    "iso:country":"NL",
    "sg:address":"Hoogte Kadijk 155",
    "sg:city":"Amsterdam",
    "sg:orig_category":"Platenmaatschappijen",
    "sg:phone":"+31 20 622 3221",
    "sg:postcode":"1018 BJ",
    "sg:province":"North Holland",
    "wof:name":"Dikker & Courbois Bv",
    "wof:placetype":"venue"
},
  "geometry": {"coordinates":[4.919987,52.367867],"type":"Point"}
}