{
  "type": "Feature",
  "properties": {
    "iso:country":"NL",
    "sg:address":"Fort Willemwg 37",
    "sg:city":"Maastricht",
    "sg:orig_category":"Automaterialen En Gereedschappen",
    "sg:phone":"+31 43 325 4243",
    "sg:postcode":"6219 PA",
    "sg:province":"Limburg",
    "wof:name":"Centuri Bv",
    "wof:placetype":"venue"
},
  "geometry": {"coordinates":[5.682666,50.859451],"type":"Point"}
}