{
  "type": "Feature",
  "properties": {
    "addr:full":"Zwartezeestr 74 Lelystad Flevoland 8226 CB",
    "addr:housenumber":"74",
    "addr:postcode":"8226 cb",
    "addr:street":"Zwartezeestr;Flevoland",
    "iso:country":"NL",
    "sg:address":"Zwartezeestr 74",
    "sg:city":"Lelystad",
    "sg:orig_category":"Adviesbureaus Gezondheidszorg",
    "sg:phone":"+31 320 262 100",
    "sg:postcode":"8226 CB",
    "sg:province":"Flevoland",
    "wof:name":"A'Bei",
    "wof:placetype":"venue"
},
  "geometry": {"coordinates":[5.497217,52.49548],"type":"Point"}
}