{
  "type": "Feature",
  "properties": {
    "addr:full":"Nieuwendk 11A Geldrop Noord-Brabant 5664 HA",
    "addr:housenumber":"11a",
    "addr:postcode":"5664 ha",
    "addr:street":"Nieuwendk",
    "iso:country":"NL",
    "sg:address":"Nieuwendk 11A",
    "sg:city":"Geldrop",
    "sg:orig_category":"Verzekeringen - Verzekeringskantoren",
    "sg:phone":"+31 40 289 5500",
    "sg:postcode":"5664 HA",
    "sg:province":"Noord-Brabant",
    "wof:name":"Hamburg-Mannheimer",
    "wof:placetype":"venue"
},
  "geometry": {"coordinates":[5.557011,51.422413],"type":"Point"}
}