{
  "type": "Feature",
  "properties": {
    "addr:full":"Adm Banckertwg 19 Leiden Zuid-Holland 2315 SR",
    "addr:housenumber":"19",
    "addr:postcode":"2315 sr",
    "iso:country":"NL",
    "sg:address":"Adm Banckertwg 19",
    "sg:city":"Leiden",
    "sg:orig_category":"Scheepswerven",
    "sg:phone":"+31 71 521 3112",
    "sg:postcode":"2315 SR",
    "sg:province":"Zuid-Holland",
    "wof:name":"Stallinga Scheepswerf",
    "wof:placetype":"venue"
},
  "geometry": {"coordinates":[4.512327,52.156578],"type":"Point"}
}