{
  "type": "Feature",
  "properties": {
    "addr:full":"Wildweg 2 Holten Overijssel 7451 RN",
    "addr:housenumber":"2",
    "addr:postcode":"7451 rn",
    "addr:street":"Wildweg",
    "iso:country":"NL",
    "sg:address":"Wildweg 2",
    "sg:city":"Holten",
    "sg:orig_category":"Kampeerterreinen",
    "sg:phone":"+31 548 512 272",
    "sg:postcode":"7451 RN",
    "sg:province":"Overijssel",
    "wof:name":"De Prins Recreatiepark",
    "wof:placetype":"venue"
},
  "geometry": {"coordinates":[6.4605321884,52.2961769104],"type":"Point"}
}