{
  "type": "Feature",
  "properties": {
    "addr:full":"De Bolder 68 Drachten Friesland 9206 AR",
    "addr:housenumber":"68",
    "addr:postcode":"9206",
    "addr:street":"De Bolder",
    "iso:country":"NL",
    "sg:address":"De Bolder 68",
    "sg:city":"Drachten",
    "sg:orig_category":"Zuivelindustrie - Apparaten En Installaties",
    "sg:phone":"+31 512 543 013",
    "sg:postcode":"9206 AR",
    "sg:province":"Friesland",
    "wof:name":"Delta Instr. Bv",
    "wof:placetype":"venue"
},
  "geometry": {"coordinates":[6.072787,53.116592],"type":"Point"}
}