{
  "type": "Feature",
  "properties": {
    "addr:full":"Weverstraat 95 Den Burg Noord-Holland 1791 AC",
    "addr:housenumber":"95",
    "addr:postcode":"1791 ac",
    "addr:street":"Weverstraat",
    "iso:country":"NL",
    "sg:address":"Weverstraat 95",
    "sg:city":"Den Burg",
    "sg:orig_category":"Apothekers",
    "sg:phone":"+31 222 322 286",
    "sg:postcode":"1791 AC",
    "sg:province":"Noord-Holland",
    "wof:name":"Eerste Hulp Service, Medical Supplies",
    "wof:placetype":"venue"
},
  "geometry": {"coordinates":[4.800197,53.053913],"type":"Point"}
}