{
  "type": "Feature",
  "properties": {
    "addr:full":"Dreef 15 Kockengen Utrecht 3628 BJ",
    "addr:housenumber":"15",
    "addr:postcode":"3628 bj",
    "addr:street":"Dreef",
    "iso:country":"NL",
    "sg:address":"Dreef 15",
    "sg:city":"Kockengen",
    "sg:orig_category":"Woningstoffeerders",
    "sg:phone":"+31 346 242 286",
    "sg:postcode":"3628 BJ",
    "sg:province":"Utrecht",
    "wof:name":"Stam Woningstoffering",
    "wof:placetype":"venue"
},
  "geometry": {"coordinates":[4.9495258331,52.1492500305],"type":"Point"}
}