{
  "type": "Feature",
  "properties": {
    "addr:full":"L J Zielstrawg 1 Groningen Groningen 9713 GX",
    "addr:housenumber":"1",
    "addr:postcode":"9713 gx",
    "addr:street":"L;Zielstrawg",
    "iso:country":"NL",
    "sg:address":"L J Zielstrawg 1",
    "sg:city":"Groningen",
    "sg:orig_category":"Adviesbureaus Bedrijfsorganisatie",
    "sg:phone":"+31 50 311 6030",
    "sg:postcode":"9713 GX",
    "sg:province":"Groningen",
    "sg:website":"http://www.baoconsultants.nl",
    "wof:name":"Ba & O Consultants",
    "wof:placetype":"venue"
},
  "geometry": {"coordinates":[6.574715,53.217144],"type":"Point"}
}