{
  "type": "Feature",
  "properties": {
    "iso:country":"NL",
    "sg:address":"Brink 27A",
    "sg:city":"Laren Nh",
    "sg:orig_category":"Balletscholen",
    "sg:phone":"+31 35 538 6829",
    "sg:postcode":"1251 KS",
    "sg:province":"North Holland",
    "wof:name":"Ballet En Dansstudio Laren",
    "wof:placetype":"venue"
},
  "geometry": {"coordinates":[5.226041,52.256672],"type":"Point"}
}