{
  "type": "Feature",
  "properties": {
    "addr:full":"Aperloheve 87 Elburg Gelderland 8081 JN",
    "addr:housenumber":"87",
    "addr:postcode":"8081 jn",
    "addr:street":"Aperloheve;Gelderland",
    "iso:country":"NL",
    "sg:address":"Aperloheve 87",
    "sg:city":"Elburg",
    "sg:classifiers":[
        {
            "category":"Banks & Credit Unions",
            "subcategory":"Investment Brokerage",
            "type":"Services"
        }
    ],
    "sg:phone":"+31 525 682 018",
    "sg:postcode":"8081 JN",
    "sg:province":"Gelderland",
    "sg:tags":[
        "pension"
    ],
    "wof:name":"Oosting, H J",
    "wof:placetype":"venue"
},
  "geometry": {"coordinates":[5.854345,52.449554],"type":"Point"}
}