{
  "type": "Feature",
  "properties": {
    "iso:country":"NL",
    "sg:address":"Postbus 1252",
    "sg:city":"Eindhoven",
    "sg:orig_category":"Scholen Voor Basisonderwijs",
    "sg:phone":"+31 40 242 3960",
    "sg:postcode":"5602 BG",
    "sg:province":"North Brabant",
    "wof:name":"Vierring Salto, De",
    "wof:placetype":"venue"
},
  "geometry": {"coordinates":[5.48411,51.434471],"type":"Point"}
}