{
  "type": "Feature",
  "properties": {
    "addr:full":"Nieuwstr 105 Scherpenzeel Gld Gelderland 3925 EE",
    "addr:housenumber":"105",
    "addr:postcode":"3925 ee",
    "addr:street":"Gld Gelderland",
    "iso:country":"NL",
    "sg:address":"Nieuwstr 105",
    "sg:city":"Scherpenzeel Gld",
    "sg:orig_category":"Begrafenisverzorging",
    "sg:phone":"+31 33 277 3050",
    "sg:postcode":"3925 EE",
    "sg:province":"Gelderland",
    "wof:name":"Landbalgen",
    "wof:placetype":"venue"
},
  "geometry": {"coordinates":[5.478526,52.074146],"type":"Point"}
}