{
  "type": "Feature",
  "properties": {
    "addr:full":"Lange Brinkweg 21 Soest Utrecht 3764 AA",
    "addr:housenumber":"21",
    "addr:postcode":"3764 aa",
    "addr:street":"Lange Brinkweg",
    "iso:country":"NL",
    "sg:address":"Lange Brinkweg 21",
    "sg:city":"Soest",
    "sg:orig_category":"Architecten",
    "sg:phone":"+31 35 601 1496",
    "sg:postcode":"3764 AA",
    "sg:province":"Utrecht",
    "wof:name":"Tuinarchitectuur De Groene Kamer",
    "wof:placetype":"venue"
},
  "geometry": {"coordinates":[5.302898,52.185337],"type":"Point"}
}