{
  "type": "Feature",
  "properties": {
    "addr:full":"Van Beverningkstraat 85 'S Gravenhage Zuid-Holland 2582 VC",
    "addr:housenumber":"85",
    "addr:postcode":"2582 vc",
    "addr:street":"Van Beverningkstraat;' S",
    "iso:country":"NL",
    "sg:address":"Van Beverningkstraat 85",
    "sg:city":"'S Gravenhage",
    "sg:orig_category":"Diverse Bedrijfsinstallaties Gh",
    "sg:phone":"+31 70 355 0064",
    "sg:postcode":"2582 VC",
    "sg:province":"Zuid-Holland",
    "wof:name":"General Trading Holland",
    "wof:placetype":"venue"
},
  "geometry": {"coordinates":[4.272339,52.091278],"type":"Point"}
}