{
  "type": "Feature",
  "properties": {
    "addr:full":"Willigenburg 22 Enkhuizen Noord-Holland 1601 LJ",
    "addr:housenumber":"22",
    "addr:postcode":"1601 lj",
    "addr:street":"Willigenburg",
    "iso:country":"NL",
    "sg:address":"Willigenburg 22",
    "sg:city":"Enkhuizen",
    "sg:orig_category":"Adviesbureaus Bedrijfsorganisatie",
    "sg:phone":"+31 228 316 145",
    "sg:postcode":"1601 LJ",
    "sg:province":"Noord-Holland",
    "wof:name":"Helmer Consultancy Bv",
    "wof:placetype":"venue"
},
  "geometry": {"coordinates":[5.290071,52.706207],"type":"Point"}
}