{
  "type": "Feature",
  "properties": {
    "addr:full":"Dries 25C St Michielsgestel Noord-Brabant 5271 ZA",
    "addr:housenumber":"25c",
    "addr:postcode":"5271",
    "addr:street":"Dries;St Michielsgestel",
    "iso:country":"NL",
    "sg:address":"Dries 25C",
    "sg:city":"St Michielsgestel",
    "sg:orig_category":"Betonijzervlechten",
    "sg:phone":"+31 73 594 4246",
    "sg:postcode":"5271 ZA",
    "sg:province":"Noord-Brabant",
    "wof:name":"Hoon, De",
    "wof:placetype":"venue"
},
  "geometry": {"coordinates":[5.373489,51.66013],"type":"Point"}
}