{
  "type": "Feature",
  "properties": {
    "addr:full":"Blauw Roodln 62 Zoetermeer South Holland 2718 SJ",
    "addr:housenumber":"62",
    "addr:postcode":"2718",
    "iso:country":"NL",
    "sg:address":"Blauw Roodln 62",
    "sg:city":"Zoetermeer",
    "sg:orig_category":"Loopbaanbegeleiding",
    "sg:phone":"+31 79 361 7533",
    "sg:postcode":"2718 SJ",
    "sg:province":"South Holland",
    "sg:website":"http://www.degelevogel.nl",
    "wof:name":"Gele Vogel, De",
    "wof:placetype":"venue"
},
  "geometry": {"coordinates":[4.500374,52.038986],"type":"Point"}
}