{
  "type": "Feature",
  "properties": {
    "addr:full":"Middenlaan 56 Doorwerth Gelderland 6865 VR",
    "addr:housenumber":"56",
    "addr:postcode":"6865 vr",
    "addr:street":"Middenlaan;Gelderland",
    "iso:country":"NL",
    "sg:address":"Middenlaan 56",
    "sg:city":"Doorwerth",
    "sg:orig_category":"Boekhouders",
    "sg:phone":"+31 26 339 0229",
    "sg:postcode":"6865 VR",
    "sg:province":"Gelderland",
    "wof:name":"Metrum Administratieve Dienstverlening",
    "wof:placetype":"venue"
},
  "geometry": {"coordinates":[5.807052,51.975712],"type":"Point"}
}