{
  "type": "Feature",
  "properties": {
    "iso:country":"NL",
    "sg:address":"Ginnekemarkt 8",
    "sg:city":"Breda",
    "sg:orig_category":"Kappers",
    "sg:phone":"+31 76 565 5295",
    "sg:postcode":"4835 JC",
    "sg:province":"North Brabant",
    "wof:name":"Coiffure House Breda Bv",
    "wof:placetype":"venue"
},
  "geometry": {"coordinates":[4.7851839066,51.5674324036],"type":"Point"}
}