{
  "type": "Feature",
  "properties": {
    "addr:full":"Kerkstr 58 Monnickendam Noord-Holland 1141 BJ",
    "addr:housenumber":"58",
    "addr:postcode":"1141 bj",
    "addr:street":"Kerkstr",
    "iso:country":"NL",
    "sg:address":"Kerkstr 58",
    "sg:city":"Monnickendam",
    "sg:orig_category":"Juweliers",
    "sg:phone":"+31 299 653 023",
    "sg:postcode":"1141 BJ",
    "sg:province":"Noord-Holland",
    "wof:name":"Sako",
    "wof:placetype":"venue"
},
  "geometry": {"coordinates":[5.035525,52.458969],"type":"Point"}
}