{
  "type": "Feature",
  "properties": {
    "addr:full":"Dr B T Broeckestr 9 Steenwyk NL.08 8331 KH",
    "addr:housenumber":"9;nl.08",
    "addr:postcode":"8331 kh",
    "addr:street":"Dr;Steenwyk",
    "iso:country":"NL",
    "sg:address":"Dr B T Broeckestr 9",
    "sg:city":"Steenwyk",
    "sg:orig_category":"Etalageverzorging",
    "sg:phone":"+31 521 516 230",
    "sg:postcode":"8331 KH",
    "sg:province":"NL.08",
    "wof:name":"Vellinga",
    "wof:placetype":"venue"
},
  "geometry": {"coordinates":[6.111866,52.790367],"type":"Point"}
}