{
  "type": "Feature",
  "properties": {
    "addr:full":"Rudonk 23A Breda Noord-Brabant 4824 AJ",
    "addr:housenumber":"23a",
    "addr:postcode":"4824 aj",
    "addr:street":"Rudonk",
    "iso:country":"NL",
    "sg:address":"Rudonk 23A",
    "sg:city":"Breda",
    "sg:orig_category":"Fietsen En Bromfietsen",
    "sg:phone":"+31 76 581 5320",
    "sg:postcode":"4824 AJ",
    "sg:province":"Noord-Brabant",
    "sg:website":"http://www.ajtrans.myweb.nl",
    "wof:name":"Aj Trans Bv",
    "wof:placetype":"venue"
},
  "geometry": {"coordinates":[4.74994,51.612591],"type":"Point"}
}