{
  "type": "Feature",
  "properties": {
    "addr:full":"Scheepvaartwg 73 Schiedam Zuid-Holland 3123 ER",
    "addr:housenumber":"73",
    "addr:postcode":"3123 er",
    "addr:street":"Scheepvaartwg",
    "iso:country":"NL",
    "sg:address":"Scheepvaartwg 73",
    "sg:city":"Schiedam",
    "sg:orig_category":"Kappers",
    "sg:phone":"+31 10 470 5218",
    "sg:postcode":"3123 ER",
    "sg:province":"Zuid-Holland",
    "wof:name":"Fox",
    "wof:placetype":"venue"
},
  "geometry": {"coordinates":[4.3680181503,51.9429702759],"type":"Point"}
}