{
  "type": "Feature",
  "properties": {
    "iso:country":"NL",
    "sg:address":"V Hogendorppln 5",
    "sg:city":"Gouda",
    "sg:orig_category":"Autorijscholen",
    "sg:phone":"+31 182 527 450",
    "sg:postcode":"2805 BM",
    "sg:province":"South Holland",
    "sg:website":"http://www.hansboomsluiter.nl",
    "wof:name":"Boomsluiter, Hans",
    "wof:placetype":"venue"
},
  "geometry": {"coordinates":[4.710715,52.010006],"type":"Point"}
}