{
  "type": "Feature",
  "properties": {
    "addr:full":"V Hogendorppln 5 Gouda South Holland 2805 BM",
    "addr:housenumber":"5",
    "addr:postcode":"2805 bm",
    "addr:street":"Hogendorppln",
    "iso:country":"NL",
    "sg:address":"V Hogendorppln 5",
    "sg:city":"Gouda",
    "sg:orig_category":"Autorijscholen",
    "sg:phone":"+31 182 527 450",
    "sg:postcode":"2805 BM",
    "sg:province":"South Holland",
    "sg:website":"http://www.hansboomsluiter.nl",
    "wof:name":"Boomsluiter, Hans",
    "wof:placetype":"venue"
},
  "geometry": {"coordinates":[4.710715,52.010006],"type":"Point"}
}