{
  "type": "Feature",
  "properties": {
    "addr:full":"Heremaweg 4 Heerenveen Provincie Friesland 8444 AN",
    "addr:housenumber":"4",
    "addr:postcode":"8444 an",
    "addr:street":"Heremaweg;Provincie Friesland",
    "iso:country":"NL",
    "sg:address":"Heremaweg 4",
    "sg:city":"Heerenveen",
    "sg:orig_category":"Kappers",
    "sg:phone":"+31 513 631 813",
    "sg:postcode":"8444 AN",
    "sg:province":"Provincie Friesland",
    "wof:name":"A. Brouwer Boersma",
    "wof:placetype":"venue"
},
  "geometry": {"coordinates":[5.9495539665,52.9383773804],"type":"Point"}
}