{
  "type": "Feature",
  "properties": {
    "iso:country":"NL",
    "sg:address":"Vossenw 15",
    "sg:city":"Liessel",
    "sg:orig_category":"Elektrotechnische Installatiebureaus",
    "sg:phone":"+31 493 341 511",
    "sg:postcode":"5757 AG",
    "sg:province":"Noord-Brabant",
    "wof:name":"Aarts",
    "wof:placetype":"venue"
},
  "geometry": {"coordinates":[5.816623,51.41814],"type":"Point"}
}