{
  "type": "Feature",
  "properties": {
    "addr:full":"Galgkade 80 Vlaardingen Zuid-Holland 3133 KN",
    "addr:housenumber":"80",
    "addr:postcode":"3133 kn",
    "addr:street":"Galgkade",
    "iso:country":"NL",
    "sg:address":"Galgkade 80",
    "sg:city":"Vlaardingen",
    "sg:orig_category":"Metalen And Ertsen Gh",
    "sg:phone":"+31 10 435 4211",
    "sg:postcode":"3133 KN",
    "sg:province":"Zuid-Holland",
    "wof:name":"Staal- En Snijbedrijf Leenderts Bv",
    "wof:placetype":"venue"
},
  "geometry": {"coordinates":[4.344653,51.901943],"type":"Point"}
}