{
  "type": "Feature",
  "properties": {
    "addr:full":"V Versteegpln 11 Zoetermeer Zuid-Holland 2713 HB",
    "addr:housenumber":"11",
    "addr:postcode":"2713 hb",
    "iso:country":"NL",
    "sg:address":"V Versteegpln 11",
    "sg:city":"Zoetermeer",
    "sg:orig_category":"Kappers",
    "sg:phone":"+31 79 321 2706",
    "sg:postcode":"2713 HB",
    "sg:province":"Zuid-Holland",
    "wof:name":"Koos",
    "wof:placetype":"venue"
},
  "geometry": {"coordinates":[4.488925,52.06308],"type":"Point"}
}