{
  "type": "Feature",
  "properties": {
    "iso:country":"NL",
    "sg:address":"Meipoortstr 27",
    "sg:city":"Doesburg",
    "sg:orig_category":"Bloemen En Planten",
    "sg:phone":"+31 313 474 484",
    "sg:postcode":"6981 DH",
    "sg:province":"Gelderland",
    "wof:name":"Hoogeveen",
    "wof:placetype":"venue"
},
  "geometry": {"coordinates":[6.136847,52.013752],"type":"Point"}
}