{
  "type": "Feature",
  "properties": {
    "addr:full":"Molenstraat 52 Cuijk Noord-Brabant 5431 BZ",
    "addr:housenumber":"52",
    "addr:postcode":"5431 bz",
    "addr:street":"Molenstraat",
    "iso:country":"NL",
    "sg:address":"Molenstraat 52",
    "sg:city":"Cuijk",
    "sg:orig_category":"Kappers",
    "sg:phone":"+31 485 316 139",
    "sg:postcode":"5431 BZ",
    "sg:province":"Noord-Brabant",
    "wof:name":"Klaus Kacier",
    "wof:placetype":"venue"
},
  "geometry": {"coordinates":[5.8759160042,51.7292671204],"type":"Point"}
}