{
  "type": "Feature",
  "properties": {
    "addr:full":"Paardeweide 38A Breda Noord-Brabant 4824 EH",
    "addr:housenumber":"38a",
    "addr:postcode":"4824 eh",
    "addr:street":"Paardeweide",
    "iso:country":"NL",
    "sg:address":"Paardeweide 38A",
    "sg:city":"Breda",
    "sg:orig_category":"Non-Classified Establishments",
    "sg:phone":"+31 76 542 4901",
    "sg:postcode":"4824 EH",
    "sg:province":"Noord-Brabant",
    "sg:website":"http://www.soudal.com",
    "wof:name":"Soudal Bv",
    "wof:placetype":"venue"
},
  "geometry": {"coordinates":[4.752972,51.610809],"type":"Point"}
}