{
  "type": "Feature",
  "properties": {
    "addr:full":"Bliek 17 Raamsdonksveer Noord-Brabant 4941 SG",
    "addr:housenumber":"17",
    "addr:postcode":"4941 sg",
    "addr:street":"Bliek",
    "iso:country":"NL",
    "sg:address":"Bliek 17",
    "sg:city":"Raamsdonksveer",
    "sg:orig_category":"Adviesbureaus Bedrijfsorganisatie",
    "sg:phone":"+31 162 570 627",
    "sg:postcode":"4941 SG",
    "sg:province":"Noord-Brabant",
    "wof:name":"Nvk Ned Ver Kwaliteitsverbetering",
    "wof:placetype":"venue"
},
  "geometry": {"coordinates":[4.87412,51.70932],"type":"Point"}
}