{
  "type": "Feature",
  "properties": {
    "iso:country":"NL",
    "sg:address":"Laanhorn 13",
    "sg:city":"Amstelveen",
    "sg:orig_category":"Wasserijen",
    "sg:phone":"+31 20 643 1088",
    "sg:postcode":"1181 BD",
    "sg:province":"North Holland",
    "wof:name":"Laundry Service",
    "wof:placetype":"venue"
},
  "geometry": {"coordinates":[4.8578958511,52.3214225769],"type":"Point"}
}