{
  "type": "Feature",
  "properties": {
    "addr:full":"Laanhorn 13 Amstelveen North Holland 1181 BD",
    "addr:housenumber":"13",
    "addr:postcode":"1181 bd",
    "addr:street":"Laanhorn",
    "iso:country":"NL",
    "sg:address":"Laanhorn 13",
    "sg:city":"Amstelveen",
    "sg:orig_category":"Wasserijen",
    "sg:phone":"+31 20 643 1088",
    "sg:postcode":"1181 BD",
    "sg:province":"North Holland",
    "wof:name":"Laundry Service",
    "wof:placetype":"venue"
},
  "geometry": {"coordinates":[4.8578958511,52.3214225769],"type":"Point"}
}