{
  "type": "Feature",
  "properties": {
    "iso:country":"NL",
    "sg:address":"Hoofdstraat 103",
    "sg:city":"Driebergen-Rijsenburg",
    "sg:orig_category":"Bloemen And Planten",
    "sg:phone":"+31 343 512 838",
    "sg:postcode":"3971 KE",
    "sg:province":"Utrecht",
    "wof:name":"Pet'S Place",
    "wof:placetype":"venue"
},
  "geometry": {"coordinates":[5.280366,52.053204],"type":"Point"}
}