{
  "type": "Feature",
  "properties": {
    "iso:country":"NL",
    "sg:address":"Nieuwstr 56",
    "sg:city":"Veldhoven",
    "sg:orig_category":"Machinefabrieken",
    "sg:phone":"+31 40 222 1160",
    "sg:postcode":"5504 EB",
    "sg:province":"North Brabant",
    "wof:name":"Lp Group",
    "wof:placetype":"venue"
},
  "geometry": {"coordinates":[5.38848,51.403339],"type":"Point"}
}