{
  "type": "Feature",
  "properties": {
    "addr:full":"Ryksstrwg 22 Buurmalsen Gelderland 4197 BC",
    "addr:housenumber":"22",
    "addr:postcode":"4197 bc",
    "addr:street":"Ryksstrwg;Gelderland",
    "iso:country":"NL",
    "sg:address":"Ryksstrwg 22",
    "sg:city":"Buurmalsen",
    "sg:orig_category":"Vertaalbureaus",
    "sg:phone":"+31 345 618 055",
    "sg:postcode":"4197 BC",
    "sg:province":"Gelderland",
    "wof:name":"Vice Versa, Vertalingen",
    "wof:placetype":"venue"
},
  "geometry": {"coordinates":[5.294936,51.8923],"type":"Point"}
}