{
  "type": "Feature",
  "properties": {
    "addr:full":"Dorpsstraat 20 Vorden Gelderland 7251 BB",
    "addr:housenumber":"20",
    "addr:postcode":"7251 bb",
    "addr:street":"Dorpsstraat;Gelderland",
    "iso:country":"NL",
    "sg:address":"Dorpsstraat 20",
    "sg:city":"Vorden",
    "sg:classifiers":[
        {
            "category":"Retail",
            "subcategory":"Photofinishing",
            "type":"Services"
        }
    ],
    "sg:phone":"+31 575 552 812",
    "sg:postcode":"7251 BB",
    "sg:province":"Gelderland",
    "sg:tags":[
        "foto",
        "film"
    ],
    "wof:name":"Foto Temmink",
    "wof:placetype":"venue"
},
  "geometry": {"coordinates":[6.314415,52.10355],"type":"Point"}
}