{
  "type": "Feature",
  "properties": {
    "addr:full":"De Beerebyt 14 Amstelveen Noord-Holland 1181 MN",
    "addr:housenumber":"14",
    "addr:postcode":"1181 mn",
    "iso:country":"NL",
    "sg:address":"De Beerebyt 14",
    "sg:city":"Amstelveen",
    "sg:orig_category":"Woningbureaus",
    "sg:phone":"+31 20 503 6560",
    "sg:postcode":"1181 MN",
    "sg:province":"Noord-Holland",
    "sg:website":"http://www.rotsvast.nl",
    "wof:name":"Rots-Vast Groep Amstelveen",
    "wof:placetype":"venue"
},
  "geometry": {"coordinates":[4.8699860573,52.3101196289],"type":"Point"}
}