{
  "type": "Feature",
  "properties": {
    "iso:country":"NL",
    "sg:address":"Florestanhof 29",
    "sg:city":"Amersfoort",
    "sg:orig_category":"Grafisch Ontwerpers",
    "sg:phone":"+31 33 477 9068",
    "sg:postcode":"3816 SN",
    "sg:province":"Utrecht",
    "wof:name":"Kees Van Pagee",
    "wof:placetype":"venue"
},
  "geometry": {"coordinates":[5.409382,52.157619],"type":"Point"}
}