{
  "type": "Feature",
  "properties": {
    "addr:full":"Postbus 888 Maastricht Limburg 6200 AW",
    "addr:housenumber":"888",
    "addr:postcode":"6200 aw",
    "addr:street":"Postbus",
    "iso:country":"NL",
    "sg:address":"Postbus 888",
    "sg:city":"Maastricht",
    "sg:orig_category":"Verenigingen En Stichtingen",
    "sg:phone":"+31 43 325 1088",
    "sg:postcode":"6200 AW",
    "sg:province":"Limburg",
    "sg:website":"http://www.circumflex.nl",
    "wof:name":"Circumflex",
    "wof:placetype":"venue"
},
  "geometry": {"coordinates":[5.68726,50.84985],"type":"Point"}
}