{
  "type": "Feature",
  "properties": {
    "addr:full":"Czaar Peterstr 213 Amsterdam Noord-Holland 1018 PL",
    "addr:housenumber":"213",
    "addr:postcode":"1018 pl",
    "iso:country":"NL",
    "sg:address":"Czaar Peterstr 213",
    "sg:city":"Amsterdam",
    "sg:orig_category":"Machinefabrieken",
    "sg:phone":"+31 20 523 3700",
    "sg:postcode":"1018 PL",
    "sg:province":"Noord-Holland",
    "wof:name":"Stork Rmo Bv",
    "wof:placetype":"venue"
},
  "geometry": {"coordinates":[4.930322,52.37281],"type":"Point"}
}