{
  "type": "Feature",
  "properties": {
    "addr:full":"Hogestraat 36 Druten Gelderland 6651 BL",
    "addr:housenumber":"36",
    "addr:postcode":"6651 bl",
    "addr:street":"Hogestraat",
    "iso:country":"NL",
    "sg:address":"Hogestraat 36",
    "sg:city":"Druten",
    "sg:orig_category":"Verlichting And Huishoudartikelen",
    "sg:phone":"+31 487 512 235",
    "sg:postcode":"6651 BL",
    "sg:province":"Gelderland",
    "wof:name":"H. Van Der Donk Bv",
    "wof:placetype":"venue"
},
  "geometry": {"coordinates":[5.60526,51.88567],"type":"Point"}
}