{
  "type": "Feature",
  "properties": {
    "addr:full":"H Ter Kuilestr 173 Enschede Overijssel 7547 SK",
    "addr:housenumber":"173",
    "addr:street":"H Ter Kuilestr;7547",
    "iso:country":"NL",
    "sg:address":"H Ter Kuilestr 173",
    "sg:city":"Enschede",
    "sg:orig_category":"Verpakkingsmachines",
    "sg:phone":"+31 53 432 4072",
    "sg:postcode":"7547 SK",
    "sg:province":"Overijssel",
    "sg:website":"http://www.nepas.nl",
    "wof:name":"Nepas Bv Machinefabriek",
    "wof:placetype":"venue"
},
  "geometry": {"coordinates":[6.851797,52.219433],"type":"Point"}
}