{
  "type": "Feature",
  "properties": {
    "addr:full":"Zuiddijk 400 Zaandam Noord-Holland 1505 HE",
    "addr:housenumber":"400",
    "addr:postcode":"1505 he",
    "addr:street":"Zuiddijk",
    "iso:country":"NL",
    "sg:address":"Zuiddijk 400",
    "sg:city":"Zaandam",
    "sg:orig_category":"Technische Studies And Onderzoek",
    "sg:phone":"+31 75 631 4151",
    "sg:postcode":"1505 HE",
    "sg:province":"Noord-Holland",
    "wof:name":"Kenz Cranes Bv",
    "wof:placetype":"venue"
},
  "geometry": {"coordinates":[4.838297,52.427505],"type":"Point"}
}