{
  "type": "Feature",
  "properties": {
    "iso:country":"NL",
    "sg:address":"Zuiddijk 400",
    "sg:city":"Zaandam",
    "sg:orig_category":"Technische Studies And Onderzoek",
    "sg:phone":"+31 75 631 4151",
    "sg:postcode":"1505 HE",
    "sg:province":"Noord-Holland",
    "wof:name":"Kenz Cranes Bv",
    "wof:placetype":"venue"
},
  "geometry": {"coordinates":[4.838297,52.427505],"type":"Point"}
}