{
  "type": "Feature",
  "properties": {
    "iso:country":"NL",
    "sg:address":"Zesstedenwg 188",
    "sg:city":"Grootebroek",
    "sg:orig_category":"Adviesbureaus Verzekeringen",
    "sg:phone":"+31 228 517 777",
    "sg:postcode":"1613 KD",
    "sg:province":"Noord-Holland",
    "sg:website":"http://www.keeman.nl",
    "wof:name":"Keeman Bv, M C",
    "wof:placetype":"venue"
},
  "geometry": {"coordinates":[5.220444,52.697834],"type":"Point"}
}