{
  "type": "Feature",
  "properties": {
    "iso:country":"NL",
    "sg:address":"Rysoordsestr 3",
    "sg:city":"Ridderkerk",
    "sg:orig_category":"Administratie- En Boekhoudkantoren",
    "sg:phone":"+31 180 436 211",
    "sg:postcode":"2988 XP",
    "sg:province":"Zuid-Holland",
    "sg:website":"http://www.check-itadmin.nl",
    "wof:name":"Check-It Administratiekantoor",
    "wof:placetype":"venue"
},
  "geometry": {"coordinates":[4.598146,51.849457],"type":"Point"}
}