{
  "type": "Feature",
  "properties": {
    "addr:full":"Nw Kazerneln 31 Ede Gld Gelderland 6711 JA",
    "addr:housenumber":"31",
    "addr:postcode":"6711 ja",
    "addr:street":"Gld Gelderland",
    "iso:country":"NL",
    "sg:address":"Nw Kazerneln 31",
    "sg:city":"Ede Gld",
    "sg:orig_category":"Voetbalverenigingen",
    "sg:phone":"+31 318 614 546",
    "sg:postcode":"6711 JA",
    "sg:province":"Gelderland",
    "wof:name":"Fortissimo",
    "wof:placetype":"venue"
},
  "geometry": {"coordinates":[5.674121,52.0331],"type":"Point"}
}