{
  "type": "Feature",
  "properties": {
    "iso:country":"NL",
    "sg:address":"Nw Kazerneln 31",
    "sg:city":"Ede Gld",
    "sg:orig_category":"Voetbalverenigingen",
    "sg:phone":"+31 318 614 546",
    "sg:postcode":"6711 JA",
    "sg:province":"Gelderland",
    "wof:name":"Fortissimo",
    "wof:placetype":"venue"
},
  "geometry": {"coordinates":[5.674121,52.0331],"type":"Point"}
}