{
  "type": "Feature",
  "properties": {
    "addr:full":"Thorbeckeln 5 Sliedrecht South Holland 3362 BL",
    "addr:housenumber":"5",
    "addr:postcode":"3362 bl",
    "addr:street":"Thorbeckeln",
    "iso:country":"NL",
    "sg:address":"Thorbeckeln 5",
    "sg:city":"Sliedrecht",
    "sg:orig_category":"Fietsen En Bromfietsen",
    "sg:phone":"+31 184 413 258",
    "sg:postcode":"3362 BL",
    "sg:province":"South Holland",
    "wof:name":"Kramer Profile",
    "wof:placetype":"venue"
},
  "geometry": {"coordinates":[4.772605,51.823555],"type":"Point"}
}