{
  "type": "Feature",
  "properties": {
    "iso:country":"NL",
    "sg:address":"Stationsweg 8",
    "sg:city":"Gorredijk",
    "sg:orig_category":"Verhuur Voertuigen Behalve Auto'S",
    "sg:phone":"+31 513 465 757",
    "sg:postcode":"8401 DP",
    "sg:province":"Provincie Friesland",
    "wof:name":"H B Service",
    "wof:placetype":"venue"
},
  "geometry": {"coordinates":[6.064118,53.005871],"type":"Point"}
}