{
  "type": "Feature",
  "properties": {
    "iso:country":"NL",
    "sg:address":"Borgstee 60",
    "sg:city":"Assen",
    "sg:orig_category":"Administratie- En Boekhoudkantoren",
    "sg:phone":"+31 592 347 057",
    "sg:postcode":"9403 TV",
    "sg:province":"Drenthe",
    "wof:name":"Imc Vof",
    "wof:placetype":"venue"
},
  "geometry": {"coordinates":[6.57349,53.013309],"type":"Point"}
}