{
  "type": "Feature",
  "properties": {
    "addr:full":"G Klokstr 28 Kraggenburg NL. 8317 BP",
    "addr:housenumber":"28",
    "addr:postcode":"8317 bp",
    "addr:street":"Nl.",
    "iso:country":"NL",
    "sg:address":"G Klokstr 28",
    "sg:city":"Kraggenburg",
    "sg:orig_category":"Voetbalverenigingen",
    "sg:phone":"+31 527 252 527",
    "sg:postcode":"8317 BP",
    "sg:province":"NL.",
    "wof:name":"Fc Kraggenburg",
    "wof:placetype":"venue"
},
  "geometry": {"coordinates":[5.89557,52.661823],"type":"Point"}
}