{
  "type": "Feature",
  "properties": {
    "addr:full":"Antwerpsestrwg 42A Hoogerheide North Brabant 4631 NL",
    "addr:housenumber":"42a",
    "addr:postcode":"4631 nl",
    "addr:street":"Antwerpsestrwg",
    "iso:country":"NL",
    "sg:address":"Antwerpsestrwg 42A",
    "sg:city":"Hoogerheide",
    "sg:orig_category":"Kunstmest - Fabrieken En Groothandel",
    "sg:phone":"+31 164 612 857",
    "sg:postcode":"4631 NL",
    "sg:province":"North Brabant",
    "wof:name":"Cehave",
    "wof:placetype":"venue"
},
  "geometry": {"coordinates":[4.319033,51.431427],"type":"Point"}
}