{
  "type": "Feature",
  "properties": {
    "addr:full":"Parkln 14Rd Haarlem North Holland 2011 KV",
    "addr:housenumber":"14rd",
    "addr:postcode":"2011 kv",
    "iso:country":"NL",
    "sg:address":"Parkln 14Rd",
    "sg:city":"Haarlem",
    "sg:orig_category":"Fotopersbureaus",
    "sg:phone":"+31 23 531 0304",
    "sg:postcode":"2011 KV",
    "sg:province":"North Holland",
    "wof:name":"Boer United Photos Bv, De",
    "wof:placetype":"venue"
},
  "geometry": {"coordinates":[4.642253,52.380562],"type":"Point"}
}