{
  "type": "Feature",
  "properties": {
    "addr:full":"Molenstr 120 Zundert Noord-Brabant 4881 CV",
    "addr:housenumber":"120",
    "addr:postcode":"4881 cv",
    "addr:street":"Molenstr",
    "iso:country":"NL",
    "sg:address":"Molenstr 120",
    "sg:city":"Zundert",
    "sg:orig_category":"Kappers",
    "sg:phone":"+31 76 597 4187",
    "sg:postcode":"4881 CV",
    "sg:province":"Noord-Brabant",
    "wof:name":"Jean & Roger",
    "wof:placetype":"venue"
},
  "geometry": {"coordinates":[4.6591777802,51.4699401855],"type":"Point"}
}