{
  "type": "Feature",
  "properties": {
    "iso:country":"NL",
    "sg:address":"Griend 3120",
    "sg:city":"Lelystad",
    "sg:orig_category":"Bedrijfs- And Managementsconsultants",
    "sg:phone":"+31 320 251 349",
    "sg:postcode":"8225 SJ",
    "sg:province":"Flevoland",
    "wof:name":"Pedlar Nederland Inc",
    "wof:placetype":"venue"
},
  "geometry": {"coordinates":[5.48978,52.49865],"type":"Point"}
}