{
  "type": "Feature",
  "properties": {
    "addr:full":"Rembrandtln 118A Schiedam Zuid-Holland 3117 VS",
    "addr:housenumber":"118a",
    "addr:postcode":"3117 vs",
    "iso:country":"NL",
    "sg:address":"Rembrandtln 118A",
    "sg:city":"Schiedam",
    "sg:orig_category":"Babyartikelen",
    "sg:phone":"+31 10 427 1161",
    "sg:postcode":"3117 VS",
    "sg:province":"Zuid-Holland",
    "wof:name":"Wesdorp, D",
    "wof:placetype":"venue"
},
  "geometry": {"coordinates":[4.384862,51.914742],"type":"Point"}
}