{
  "type": "Feature",
  "properties": {
    "addr:full":"Berkenhof 28 Nootdorp South Holland 2631 GK",
    "addr:housenumber":"28",
    "addr:postcode":"2631 gk",
    "addr:street":"Berkenhof",
    "iso:country":"NL",
    "sg:address":"Berkenhof 28",
    "sg:city":"Nootdorp",
    "sg:orig_category":"Technische Studies And Onderzoek",
    "sg:phone":"+31 15 310 9517",
    "sg:postcode":"2631 GK",
    "sg:province":"South Holland",
    "wof:name":"Mavoma",
    "wof:placetype":"venue"
},
  "geometry": {"coordinates":[4.395452,52.047752],"type":"Point"}
}