{
  "type": "Feature",
  "properties": {
    "addr:full":"Kruidendreef 149 Dronten NL. 8252 BZ",
    "addr:housenumber":"149",
    "addr:postcode":"8252 bz",
    "addr:street":"Kruidendreef;Nl.",
    "iso:country":"NL",
    "sg:address":"Kruidendreef 149",
    "sg:city":"Dronten",
    "sg:orig_category":"Verenigingen En Stichtingen",
    "sg:phone":"+31 321 381 260",
    "sg:postcode":"8252 BZ",
    "sg:province":"NL.",
    "wof:name":"Jeugd & Techniek Ned, Sticht",
    "wof:placetype":"venue"
},
  "geometry": {"coordinates":[5.72401,52.509716],"type":"Point"}
}