{
  "type": "Feature",
  "properties": {
    "addr:full":"Eikstr 15 Drunen Noord-Brabant 5151 AG",
    "addr:housenumber":"15",
    "addr:postcode":"5151",
    "addr:street":"Eikstr",
    "iso:country":"NL",
    "sg:address":"Eikstr 15",
    "sg:city":"Drunen",
    "sg:orig_category":"Vertaalbureaus",
    "sg:phone":"+31 416 322 711",
    "sg:postcode":"5151 AG",
    "sg:province":"Noord-Brabant",
    "wof:name":"Smit, De",
    "wof:placetype":"venue"
},
  "geometry": {"coordinates":[5.12023,51.689877],"type":"Point"}
}