{
  "type": "Feature",
  "properties": {
    "addr:full":"Dorp 136 Benschop Utrecht 3405 BG",
    "addr:housenumber":"136",
    "addr:postcode":"3405",
    "addr:street":"Dorp",
    "iso:country":"NL",
    "sg:address":"Dorp 136",
    "sg:city":"Benschop",
    "sg:orig_category":"Fruit And Groenten Gh",
    "sg:phone":"+31 348 451 544",
    "sg:postcode":"3405 BG",
    "sg:province":"Utrecht",
    "wof:name":"Fruithandel D.J. Boer Bv",
    "wof:placetype":"venue"
},
  "geometry": {"coordinates":[4.988989,52.010159],"type":"Point"}
}