{
  "type": "Feature",
  "properties": {
    "iso:country":"NL",
    "sg:address":"Landstraat 12",
    "sg:city":"Bussum",
    "sg:orig_category":"Kappers",
    "sg:phone":"+31 35 691 8225",
    "sg:postcode":"1401 EN",
    "sg:province":"North Holland",
    "wof:name":"Kapsalon Anne",
    "wof:placetype":"venue"
},
  "geometry": {"coordinates":[5.1660990715,52.2743263245],"type":"Point"}
}