{
  "type": "Feature",
  "properties": {
    "addr:full":"Dolomietdk 7 Roosendaal Noord-Brabant 4706 HN",
    "addr:housenumber":"7",
    "addr:postcode":"4706 hn",
    "addr:street":"Dolomietdk",
    "iso:country":"NL",
    "sg:address":"Dolomietdk 7",
    "sg:city":"Roosendaal",
    "sg:orig_category":"Adviesbureaus Bedrijfsorganisatie",
    "sg:phone":"+31 165 535 964",
    "sg:postcode":"4706 HN",
    "sg:province":"Noord-Brabant",
    "wof:name":"Crugten",
    "wof:placetype":"venue"
},
  "geometry": {"coordinates":[4.491741,51.530029],"type":"Point"}
}