{
  "type": "Feature",
  "properties": {
    "iso:country":"NL",
    "sg:address":"Heerewg 196",
    "sg:city":"Schoorl",
    "sg:orig_category":"Vervoercentra",
    "sg:phone":"+31 72 509 1248",
    "sg:postcode":"1871 EN",
    "sg:province":"Noord-Holland",
    "wof:name":"Mrs Vof",
    "wof:placetype":"venue"
},
  "geometry": {"coordinates":[4.6773319244,52.7160148621],"type":"Point"}
}