{
  "type": "Feature",
  "properties": {
    "addr:full":"Noordvliet 169 Leeuwarden Friesland 8921 GE",
    "addr:housenumber":"169",
    "addr:postcode":"8921",
    "addr:street":"Noordvliet",
    "iso:country":"NL",
    "sg:address":"Noordvliet 169",
    "sg:city":"Leeuwarden",
    "sg:orig_category":"Drogisterijen",
    "sg:phone":"+31 58 212 3105",
    "sg:postcode":"8921 GE",
    "sg:province":"Friesland",
    "wof:name":"Fa J Monsma En Zoon-Het Kruidenhuis",
    "wof:placetype":"venue"
},
  "geometry": {"coordinates":[5.807772,53.202885],"type":"Point"}
}