{
  "type": "Feature",
  "properties": {
    "iso:country":"NL",
    "sg:address":"Oranjelaan 52",
    "sg:city":"Rozenburg Zh",
    "sg:orig_category":"Loodgieterswerk, Verwarming And Sanitaire Installaties",
    "sg:phone":"+31 181 212 866",
    "sg:postcode":"3181 HA",
    "sg:province":"South Holland",
    "wof:name":"Piet Noordzij Rozenburg Bv",
    "wof:placetype":"venue"
},
  "geometry": {"coordinates":[4.241977,51.901974],"type":"Point"}
}