{
  "type": "Feature",
  "properties": {
    "addr:full":"Zwaluwstraat 4 Dokkum Provincie Friesland 9101 HG",
    "addr:housenumber":"4",
    "addr:postcode":"9101 hg",
    "addr:street":"Zwaluwstraat;Provincie Friesland",
    "iso:country":"NL",
    "sg:address":"Zwaluwstraat 4",
    "sg:city":"Dokkum",
    "sg:classifiers":[
        {
            "category":"Fast Food",
            "type":"Food & Drink"
        }
    ],
    "sg:phone":"+31 519 294 691",
    "sg:postcode":"9101 HG",
    "sg:province":"Provincie Friesland",
    "sg:tags":[
        "afhaal",
        "restaurant"
    ],
    "wof:name":"P. Van Der Ploeg",
    "wof:placetype":"venue"
},
  "geometry": {"coordinates":[6.012571,53.330124],"type":"Point"}
}