{
  "type": "Feature",
  "properties": {
    "iso:country":"NL",
    "sg:address":"Molenweg 195",
    "sg:city":"Nijmegen",
    "sg:orig_category":"Bloemen And Planten",
    "sg:phone":"+31 24 377 4434",
    "sg:postcode":"6543 VC",
    "sg:province":"Gelderland",
    "wof:name":"De Kluijs Bloemen Nijmegen",
    "wof:placetype":"venue"
},
  "geometry": {"coordinates":[5.830539,51.835514],"type":"Point"}
}