{
  "type": "Feature",
  "properties": {
    "addr:full":"Rykswg N 71 Geleen Limburg 6162 AD",
    "addr:postcode":"6162 ad",
    "addr:street":"N 71",
    "iso:country":"NL",
    "sg:address":"Rykswg N 71",
    "sg:city":"Geleen",
    "sg:orig_category":"Verf En Lak - Fabrieken En Groothandel",
    "sg:phone":"+31 46 474 8583",
    "sg:postcode":"6162 AD",
    "sg:province":"Limburg",
    "wof:name":"Eyck Bv, Jac",
    "wof:placetype":"venue"
},
  "geometry": {"coordinates":[5.836582,50.974754],"type":"Point"}
}