{
  "type": "Feature",
  "properties": {
    "addr:full":"Provincialewg Z 164 Oirsbeek Limburg 6438 BK",
    "addr:housenumber":"164",
    "addr:postcode":"6438 bk",
    "iso:country":"NL",
    "sg:address":"Provincialewg Z 164",
    "sg:city":"Oirsbeek",
    "sg:orig_category":"Adviesbureaus Financieel",
    "sg:phone":"+31 46 442 8555",
    "sg:postcode":"6438 BK",
    "sg:province":"Limburg",
    "wof:name":"Oonk",
    "wof:placetype":"venue"
},
  "geometry": {"coordinates":[5.91598,50.95023],"type":"Point"}
}