{
  "type": "Feature",
  "properties": {
    "addr:full":"Schoolstr 37 Beuningen Gld Gelderland 6641 DB",
    "addr:housenumber":"37",
    "addr:postcode":"6641 db",
    "addr:street":"Schoolstr",
    "iso:country":"NL",
    "sg:address":"Schoolstr 37",
    "sg:city":"Beuningen Gld",
    "sg:orig_category":"Kamerverhuur En -Bemiddeling",
    "sg:phone":"+31 24 675 1143",
    "sg:postcode":"6641 DB",
    "sg:province":"Gelderland",
    "wof:name":"Peters",
    "wof:placetype":"venue"
},
  "geometry": {"coordinates":[5.7725777626,51.8610954285],"type":"Point"}
}