{
  "type": "Feature",
  "properties": {
    "addr:full":"L Koestr 31 Utrecht Utrecht 3511 RL",
    "addr:housenumber":"31",
    "addr:postcode":"3511 rl",
    "iso:country":"NL",
    "sg:address":"L Koestr 31",
    "sg:city":"Utrecht",
    "sg:orig_category":"Woninginrichting",
    "sg:phone":"+31 30 289 8458",
    "sg:postcode":"3511 RL",
    "sg:province":"Utrecht",
    "wof:name":"Schenk",
    "wof:placetype":"venue"
},
  "geometry": {"coordinates":[5.1135659218,52.0936164856],"type":"Point"}
}