{
  "type": "Feature",
  "properties": {
    "addr:full":"Kauwenhoven 3 Lunteren Gelderland 6741 PW",
    "addr:housenumber":"3",
    "addr:postcode":"6741 pw",
    "addr:street":"Kauwenhoven;Gelderland",
    "iso:country":"NL",
    "sg:address":"Kauwenhoven 3",
    "sg:city":"Lunteren",
    "sg:orig_category":"Accountants - Administratie- Consulenten En -Kantoren",
    "sg:phone":"+31 318 483 341",
    "sg:postcode":"6741 PW",
    "sg:province":"Gelderland",
    "sg:website":"http://www.mthco.nl",
    "wof:name":"Meeuwsen Ten Hoopen",
    "wof:placetype":"venue"
},
  "geometry": {"coordinates":[5.600684,52.086613],"type":"Point"}
}