{
  "type": "Feature",
  "properties": {
    "iso:country":"NL",
    "sg:address":"Van Grobbendoncklaan 103",
    "sg:city":"'S Hertogenbosch",
    "sg:orig_category":"Werving And Selectie Van Tijdelijk Personeel And Uitzendkantoren",
    "sg:phone":"+31 73 691 0039",
    "sg:postcode":"5213 AV",
    "sg:province":"Noord-Brabant",
    "wof:name":"Bouwpartners Bv",
    "wof:placetype":"venue"
},
  "geometry": {"coordinates":[5.3200888634,51.6988716125],"type":"Point"}
}