{
  "type": "Feature",
  "properties": {
    "addr:full":"Rietveldenweg 13 'S Hertogenbosch Noord-Brabant 5222 AP",
    "addr:housenumber":"13",
    "addr:postcode":"5222 ap",
    "addr:street":"Rietveldenweg;' S",
    "iso:country":"NL",
    "sg:address":"Rietveldenweg 13",
    "sg:city":"'S Hertogenbosch",
    "sg:orig_category":"Meubelzaken, Woning- And Keukeninrichting",
    "sg:phone":"+31 73 621 8033",
    "sg:postcode":"5222 AP",
    "sg:province":"Noord-Brabant",
    "wof:name":"Meubelgroothandel Palace Bv",
    "wof:placetype":"venue"
},
  "geometry": {"coordinates":[5.283496,51.697147],"type":"Point"}
}