{
  "type": "Feature",
  "properties": {
    "addr:full":"Weersterweg 24 Den Horn Groningen 9832 TE",
    "addr:housenumber":"24",
    "addr:postcode":"9832 te",
    "addr:street":"Weersterweg",
    "iso:country":"NL",
    "sg:address":"Weersterweg 24",
    "sg:city":"Den Horn",
    "sg:orig_category":"Hoefdierhouderijen",
    "sg:phone":"+31 50 551 5713",
    "sg:postcode":"9832 TE",
    "sg:province":"Groningen",
    "wof:name":"Paardenhouderij Hoogemeeden",
    "wof:placetype":"venue"
},
  "geometry": {"coordinates":[6.453254,53.22987],"type":"Point"}
}