{
  "type": "Feature",
  "properties": {
    "iso:country":"NL",
    "sg:address":"Schoolstr 24",
    "sg:city":"Bergambacht",
    "sg:orig_category":"Verenigingsgebouwen",
    "sg:phone":"+31 182 351 276",
    "sg:postcode":"2861 XD",
    "sg:province":"South Holland",
    "wof:name":"Schakel, De",
    "wof:placetype":"venue"
},
  "geometry": {"coordinates":[4.786132,51.933159],"type":"Point"}
}