{
  "type": "Feature",
  "properties": {
    "iso:country":"NL",
    "sg:address":"Magnesiumlaan 23",
    "sg:city":"Groningen",
    "sg:orig_category":"Boekhouders",
    "sg:phone":"+31 50 573 0068",
    "sg:postcode":"9743 TA",
    "sg:province":"Groningen",
    "wof:name":"Administratiekantoor Laning",
    "wof:placetype":"venue"
},
  "geometry": {"coordinates":[6.5331,53.22459],"type":"Point"}
}