{
  "type": "Feature",
  "properties": {
    "addr:full":"Kerkstr 67 Brunssum Limburg 6441 BB",
    "addr:housenumber":"67",
    "addr:postcode":"6441 bb",
    "addr:street":"Kerkstr",
    "iso:country":"NL",
    "sg:address":"Kerkstr 67",
    "sg:city":"Brunssum",
    "sg:orig_category":"Babyartikelen",
    "sg:phone":"+31 45 525 2269",
    "sg:postcode":"6441 BB",
    "sg:province":"Limburg",
    "wof:name":"Petra",
    "wof:placetype":"venue"
},
  "geometry": {"coordinates":[5.971725,50.946751],"type":"Point"}
}