{
  "type": "Feature",
  "properties": {
    "addr:full":"Bosschastr 5 Utrecht Utrecht 3514 HN",
    "addr:housenumber":"5",
    "addr:postcode":"3514 hn",
    "addr:street":"Bosschastr",
    "iso:country":"NL",
    "sg:address":"Bosschastr 5",
    "sg:city":"Utrecht",
    "sg:orig_category":"Artiesten/Gezelschappen",
    "sg:phone":"+31 30 273 0890",
    "sg:postcode":"3514 HN",
    "sg:province":"Utrecht",
    "wof:name":"John De Graaf",
    "wof:placetype":"venue"
},
  "geometry": {"coordinates":[5.125012,52.102161],"type":"Point"}
}