{
  "type": "Feature",
  "properties": {
    "addr:full":"Marthahoeve 12 Amstelveen North Holland 1187 LP",
    "addr:housenumber":"12",
    "addr:postcode":"1187 lp",
    "addr:street":"Marthahoeve",
    "iso:country":"NL",
    "sg:address":"Marthahoeve 12",
    "sg:city":"Amstelveen",
    "sg:orig_category":"Technische Studies And Onderzoek",
    "sg:phone":"+31 20 640 5841",
    "sg:postcode":"1187 LP",
    "sg:province":"North Holland",
    "wof:name":"Invorm Buro Voor Industriele Vormgeving",
    "wof:placetype":"venue"
},
  "geometry": {"coordinates":[4.827264,52.282825],"type":"Point"}
}