{
  "type": "Feature",
  "properties": {
    "addr:full":"Antennestr 31 Almere Flevoland 1322 AH",
    "addr:housenumber":"31",
    "addr:postcode":"1322 ah",
    "addr:street":"Antennestr;Flevoland",
    "iso:country":"NL",
    "sg:address":"Antennestr 31",
    "sg:city":"Almere",
    "sg:orig_category":"Directmail",
    "sg:phone":"+31 36 546 9395",
    "sg:postcode":"1322 AH",
    "sg:province":"Flevoland",
    "sg:website":"http://www.totalmailservice.nl",
    "wof:name":"Total Mail Service",
    "wof:placetype":"venue"
},
  "geometry": {"coordinates":[5.189497,52.35067],"type":"Point"}
}