{
  "type": "Feature",
  "properties": {
    "addr:full":"Tukseweg 34 Steenwijk NL.08 8331 LC",
    "addr:housenumber":"34;nl.08",
    "addr:postcode":"8331 lc",
    "addr:street":"Tukseweg",
    "iso:country":"NL",
    "sg:address":"Tukseweg 34",
    "sg:city":"Steenwijk",
    "sg:orig_category":"Verlichting And Huishoudartikelen",
    "sg:phone":"+31 521 512 003",
    "sg:postcode":"8331 LC",
    "sg:province":"NL.08",
    "wof:name":"Woninginrichting J. Kruider Bv",
    "wof:placetype":"venue"
},
  "geometry": {"coordinates":[6.110792,52.787819],"type":"Point"}
}