{
  "type": "Feature",
  "properties": {
    "addr:full":"Roggenstr 11 Zwolle NL.08 8011 TE",
    "addr:housenumber":"11",
    "addr:postcode":"8011 te",
    "addr:street":"Roggenstr",
    "iso:country":"NL",
    "sg:address":"Roggenstr 11",
    "sg:city":"Zwolle",
    "sg:orig_category":"Opticiens",
    "sg:phone":"+31 38 421 8861",
    "sg:postcode":"8011 TE",
    "sg:province":"NL.08",
    "wof:name":"Nico",
    "wof:placetype":"venue"
},
  "geometry": {"coordinates":[6.092979908,52.512676239],"type":"Point"}
}