{
  "type": "Feature",
  "properties": {
    "addr:full":"Ootmarsumsestraat 251 Almelo Overijssel 7603 AD",
    "addr:housenumber":"251",
    "addr:postcode":"7603 ad",
    "addr:street":"Ootmarsumsestraat",
    "iso:country":"NL",
    "sg:address":"Ootmarsumsestraat 251",
    "sg:city":"Almelo",
    "sg:classifiers":[
        {
            "category":"Food & Beverages",
            "subcategory":"Fruits & Vegetables",
            "type":"Retail Goods"
        }
    ],
    "sg:phone":"+31 546 868 284",
    "sg:postcode":"7603 AD",
    "sg:province":"Overijssel",
    "sg:tags":[
        "groenten"
    ],
    "wof:name":"Groentezaak De Betuwe",
    "wof:placetype":"venue"
},
  "geometry": {"coordinates":[6.68183,52.367409],"type":"Point"}
}