{
  "type": "Feature",
  "properties": {
    "addr:full":"Legedk 22 Scharnegoutum Provincie Friesland 8629 RN",
    "addr:housenumber":"22;8629",
    "addr:postcode":"rn",
    "addr:street":"Legedk;Provincie Friesland",
    "iso:country":"NL",
    "sg:address":"Legedk 22",
    "sg:city":"Scharnegoutum",
    "sg:orig_category":"Woninginrichting",
    "sg:phone":"+31 515 433 235",
    "sg:postcode":"8629 RN",
    "sg:province":"Provincie Friesland",
    "wof:name":"Wiersma, H J",
    "wof:placetype":"venue"
},
  "geometry": {"coordinates":[5.6777539253,53.0600013733],"type":"Point"}
}