{
  "type": "Feature",
  "properties": {
    "addr:full":"1E C Huygensstr 21 Amsterdam North Holland 1054 BP",
    "addr:housenumber":"21",
    "addr:postcode":"1054 bp",
    "addr:street":"1E C Huygensstr",
    "iso:country":"NL",
    "sg:address":"1E C Huygensstr 21",
    "sg:city":"Amsterdam",
    "sg:classifiers":[
        {
            "category":"Fast Food",
            "type":"Food & Drink"
        }
    ],
    "sg:phone":"+31 20 683 4493",
    "sg:postcode":"1054 BP",
    "sg:province":"North Holland",
    "sg:tags":[
        "afhaal",
        "restaurant"
    ],
    "wof:name":"Snackbar Eetcafe Lido",
    "wof:placetype":"venue"
},
  "geometry": {"coordinates":[4.874298,52.364647],"type":"Point"}
}