{
  "type": "Feature",
  "properties": {
    "iso:country":"NL",
    "sg:address":"Onderlangs 36N",
    "sg:city":"Amsterdam",
    "sg:orig_category":"Verenigingen En Stichtingen",
    "sg:phone":"+31 20 692 1588",
    "sg:postcode":"1097 ZK",
    "sg:province":"Noord-Holland",
    "sg:website":"http://www.anbo.nl",
    "wof:name":"Anbo",
    "wof:placetype":"venue"
},
  "geometry": {"coordinates":[4.946668,52.339199],"type":"Point"}
}