{
  "type": "Feature",
  "properties": {
    "addr:full":"Morsestr 1 S Gravenhage Zuid-Holland 2517 RZ",
    "addr:housenumber":"1;gravenhage",
    "addr:postcode":"2517 rz",
    "addr:street":"Morsestr;S",
    "iso:country":"NL",
    "sg:address":"Morsestr 1",
    "sg:city":"S Gravenhage",
    "sg:orig_category":"Kantinebeheer",
    "sg:phone":"+31 70 308 1878",
    "sg:postcode":"2517 RZ",
    "sg:province":"Zuid-Holland",
    "wof:name":"Wijler",
    "wof:placetype":"venue"
},
  "geometry": {"coordinates":[4.2870798111,52.0866699219],"type":"Point"}
}