{
  "type": "Feature",
  "properties": {
    "addr:full":"Edveensweg 14 Oosterhesselen Drenthe 7861 AN",
    "addr:housenumber":"14",
    "addr:postcode":"7861 an",
    "addr:street":"Edveensweg",
    "iso:country":"NL",
    "sg:address":"Edveensweg 14",
    "sg:city":"Oosterhesselen",
    "sg:orig_category":"Banken And Kredietinstellingen",
    "sg:phone":"+31 524 581 209",
    "sg:postcode":"7861 AN",
    "sg:province":"Drenthe",
    "wof:name":"Postkantoor",
    "wof:placetype":"venue"
},
  "geometry": {"coordinates":[6.719196,52.757519],"type":"Point"}
}