{
  "type": "Feature",
  "properties": {
    "addr:full":"Spuistr 15 S Gravenhage Zuid-Holland 2511 BC",
    "addr:housenumber":"15;gravenhage",
    "addr:postcode":"2511 bc",
    "addr:street":"Spuistr;S",
    "iso:country":"NL",
    "sg:address":"Spuistr 15",
    "sg:city":"S Gravenhage",
    "sg:orig_category":"Sportschoenen - Winkels",
    "sg:phone":"+31 70 361 5553",
    "sg:postcode":"2511 BC",
    "sg:province":"Zuid-Holland",
    "wof:name":"Foot Locker",
    "wof:placetype":"venue"
},
  "geometry": {"coordinates":[4.31627,52.07896],"type":"Point"}
}