{
  "type": "Feature",
  "properties": {
    "addr:full":"Haantje 10-A Ryswyk Zh Zuid-Holland 2288 CT",
    "addr:housenumber":"10-a",
    "addr:postcode":"2288 ct",
    "addr:street":"Haantje",
    "iso:country":"NL",
    "sg:address":"Haantje 10-A",
    "sg:city":"Ryswyk Zh",
    "sg:orig_category":"Verbouwingen",
    "sg:phone":"+31 15 212 3516",
    "sg:postcode":"2288 CT",
    "sg:province":"Zuid-Holland",
    "wof:name":"Brouwer & Brouwer",
    "wof:placetype":"venue"
},
  "geometry": {"coordinates":[4.32436,52.037251],"type":"Point"}
}