{
  "type": "Feature",
  "properties": {
    "addr:full":"Groenendijk 278 Nieuwerkerk Ad Ijssel South Holland 2911 BB",
    "addr:housenumber":"278",
    "addr:postcode":"2911 bb",
    "addr:street":"Groenendijk;Ijssel",
    "iso:country":"NL",
    "sg:address":"Groenendijk 278",
    "sg:city":"Nieuwerkerk Ad Ijssel",
    "sg:orig_category":"Pleziervaartuigen And Reparatie",
    "sg:phone":"+31 180 316 221",
    "sg:postcode":"2911 BB",
    "sg:province":"South Holland",
    "wof:name":"Lebbing",
    "wof:placetype":"venue"
},
  "geometry": {"coordinates":[4.6271,51.937538],"type":"Point"}
}