{
  "type": "Feature",
  "properties": {
    "iso:country":"NL",
    "sg:address":"Groenendijk 278",
    "sg:city":"Nieuwerkerk Ad Ijssel",
    "sg:orig_category":"Pleziervaartuigen And Reparatie",
    "sg:phone":"+31 180 316 221",
    "sg:postcode":"2911 BB",
    "sg:province":"South Holland",
    "wof:name":"Lebbing",
    "wof:placetype":"venue"
},
  "geometry": {"coordinates":[4.6271,51.937538],"type":"Point"}
}