{
  "type": "Feature",
  "properties": {
    "addr:full":"Woudvaartkade 10 Sneek Friesland 8606 XT",
    "addr:housenumber":"10",
    "addr:postcode":"8606 xt",
    "addr:street":"Woudvaartkade",
    "iso:country":"NL",
    "sg:address":"Woudvaartkade 10",
    "sg:city":"Sneek",
    "sg:orig_category":"Diverse Consumentenartikelen Gh",
    "sg:phone":"+31 515 419 801",
    "sg:postcode":"8606 XT",
    "sg:province":"Friesland",
    "wof:name":"Sjark",
    "wof:placetype":"venue"
},
  "geometry": {"coordinates":[5.662808,53.028706],"type":"Point"}
}