{
  "type": "Feature",
  "properties": {
    "iso:country":"NL",
    "sg:address":"Hofln 3",
    "sg:city":"Oostvoorne",
    "sg:classifiers":[
        {
            "category":"Travel",
            "subcategory":"Hotels & Motels",
            "type":"Entertainment"
        }
    ],
    "sg:phone":"+31 181 482 339",
    "sg:postcode":"3233 AN",
    "sg:province":"South Holland",
    "wof:name":"Motel Oostvoorne",
    "wof:placetype":"venue"
},
  "geometry": {"coordinates":[4.103859,51.913956],"type":"Point"}
}