{
  "type": "Feature",
  "properties": {
    "addr:full":"Hofln 3 Oostvoorne South Holland 3233 AN",
    "addr:housenumber":"3",
    "addr:postcode":"3233 an",
    "addr:street":"Hofln",
    "iso:country":"NL",
    "sg:address":"Hofln 3",
    "sg:city":"Oostvoorne",
    "sg:classifiers":[
        {
            "category":"Travel",
            "subcategory":"Hotels & Motels",
            "type":"Entertainment"
        }
    ],
    "sg:phone":"+31 181 482 339",
    "sg:postcode":"3233 AN",
    "sg:province":"South Holland",
    "wof:name":"Motel Oostvoorne",
    "wof:placetype":"venue"
},
  "geometry": {"coordinates":[4.103859,51.913956],"type":"Point"}
}