{
  "type": "Feature",
  "properties": {
    "iso:country":"NL",
    "sg:address":"Langstraat 45",
    "sg:city":"Arnemuiden",
    "sg:orig_category":"Boekenuitgeverijen",
    "sg:phone":"+31 118 606 036",
    "sg:postcode":"4341 EC",
    "sg:province":"Zeeland",
    "wof:name":"Boek- En Kantoorboekhandel Joossens",
    "wof:placetype":"venue"
},
  "geometry": {"coordinates":[3.675555,51.50013],"type":"Point"}
}