{
  "type": "Feature",
  "properties": {
    "addr:full":"Noordeinde 48 Monnickendam Noord-Holland 1141 AN",
    "addr:housenumber":"48",
    "addr:postcode":"1141 an",
    "addr:street":"Noordeinde",
    "iso:country":"NL",
    "sg:address":"Noordeinde 48",
    "sg:city":"Monnickendam",
    "sg:orig_category":"Kinderkleding",
    "sg:phone":"+31 299 653 034",
    "sg:postcode":"1141 AN",
    "sg:province":"Noord-Holland",
    "wof:name":"Sanny",
    "wof:placetype":"venue"
},
  "geometry": {"coordinates":[5.035415,52.460754],"type":"Point"}
}