{
  "type": "Feature",
  "properties": {
    "addr:full":"Doornsewg 65A Langbroek Utrecht 3947 MB",
    "addr:housenumber":"65a",
    "addr:postcode":"3947 mb",
    "addr:street":"Doornsewg",
    "iso:country":"NL",
    "sg:address":"Doornsewg 65A",
    "sg:city":"Langbroek",
    "sg:orig_category":"Verzekeringen - Verzekeringskantoren",
    "sg:phone":"+31 343 562 614",
    "sg:postcode":"3947 MB",
    "sg:province":"Utrecht",
    "wof:name":"Haar, Van Der",
    "wof:placetype":"venue"
},
  "geometry": {"coordinates":[5.332403,52.015945],"type":"Point"}
}