{
  "type": "Feature",
  "properties": {
    "addr:full":"Gadestr 3 Geleen Limburg 6165 CH",
    "addr:housenumber":"3",
    "addr:postcode":"6165",
    "addr:street":"Gadestr",
    "iso:country":"NL",
    "sg:address":"Gadestr 3",
    "sg:city":"Geleen",
    "sg:orig_category":"Verhuur",
    "sg:phone":"+31 46 475 7224",
    "sg:postcode":"6165 CH",
    "sg:province":"Limburg",
    "wof:name":"Gtg",
    "wof:placetype":"venue"
},
  "geometry": {"coordinates":[5.831011,50.968933],"type":"Point"}
}