{
  "type": "Feature",
  "properties": {
    "iso:country":"NL",
    "sg:address":"Seinedreef 4",
    "sg:city":"Utrecht",
    "sg:orig_category":"Warenhuizen",
    "sg:phone":"+31 900 9800",
    "sg:postcode":"3562 KN",
    "sg:province":"Utrecht",
    "sg:website":"http://www.kijkshop.nl",
    "wof:name":"Kijkshop",
    "wof:placetype":"venue"
},
  "geometry": {"coordinates":[5.1093878746,52.1138076782],"type":"Point"}
}