{
  "type": "Feature",
  "properties": {
    "iso:country":"NL",
    "sg:address":"Spalstraat 31",
    "sg:city":"Hengelo Gld",
    "sg:orig_category":"Hypotheken And Hypotheekbanken",
    "sg:phone":"+31 575 468 846",
    "sg:postcode":"7255 AB",
    "sg:province":"Gelderland",
    "wof:name":"Gerrits-Lammers Assuradeuren Bv",
    "wof:placetype":"venue"
},
  "geometry": {"coordinates":[6.310242,52.04961],"type":"Point"}
}