{
  "type": "Feature",
  "properties": {
    "addr:full":"Herenweg 340 Noordwijkerhout Zuid-Holland 2211 VG",
    "addr:housenumber":"340",
    "addr:postcode":"2211 vg",
    "addr:street":"Herenweg",
    "iso:country":"NL",
    "sg:address":"Herenweg 340",
    "sg:city":"Noordwijkerhout",
    "sg:orig_category":"Bloemen And Planten Gh",
    "sg:phone":"+31 252 372 267",
    "sg:postcode":"2211 VG",
    "sg:province":"Zuid-Holland",
    "wof:name":"G.A. Verdegaal & Zn Export Bv",
    "wof:placetype":"venue"
},
  "geometry": {"coordinates":[4.513388,52.277256],"type":"Point"}
}