{
  "type": "Feature",
  "properties": {
    "addr:full":"Flemingstr 17 Heerhugowaard North Holland 1704 SL",
    "addr:housenumber":"17",
    "addr:postcode":"1704 sl",
    "addr:street":"Flemingstr",
    "iso:country":"NL",
    "sg:address":"Flemingstr 17",
    "sg:city":"Heerhugowaard",
    "sg:orig_category":"Warmtetechniek",
    "sg:phone":"+31 72 576 1946",
    "sg:postcode":"1704 SL",
    "sg:province":"North Holland",
    "sg:website":"http://www.wardenaarinfraroodverwarming.nl",
    "wof:name":"Wardenaar",
    "wof:placetype":"venue"
},
  "geometry": {"coordinates":[4.831597805,52.69556427],"type":"Point"}
}