{
  "type": "Feature",
  "properties": {
    "addr:full":"Broerstraat 25 Nijmegen Gelderland 6511 KL",
    "addr:housenumber":"25",
    "addr:postcode":"6511 kl",
    "addr:street":"Broerstraat;Gelderland",
    "iso:country":"NL",
    "sg:address":"Broerstraat 25",
    "sg:city":"Nijmegen",
    "sg:orig_category":"Verlichting And Huishoudartikelen",
    "sg:phone":"+31 24 360 8469",
    "sg:postcode":"6511 KL",
    "sg:province":"Gelderland",
    "wof:name":"Blokker",
    "wof:placetype":"venue"
},
  "geometry": {"coordinates":[5.864739,51.846489],"type":"Point"}
}