{
  "type": "Feature",
  "properties": {
    "iso:country":"NL",
    "sg:address":"Zaailand 145",
    "sg:city":"Leeuwarden",
    "sg:orig_category":"Herenkleding",
    "sg:phone":"+31 58 215 9623",
    "sg:postcode":"8911 BL",
    "sg:province":"Friesland",
    "wof:name":"Ksel Vomo",
    "wof:placetype":"venue"
},
  "geometry": {"coordinates":[5.79526,53.199371],"type":"Point"}
}