{
  "type": "Feature",
  "properties": {
    "iso:country":"NL",
    "sg:address":"Postbus 1065",
    "sg:city":"Groningen",
    "sg:orig_category":"Webdesign Bureaus",
    "sg:phone":"+31 50 312 1958",
    "sg:postcode":"9701 BB",
    "sg:province":"Noord-Holland",
    "sg:website":"http://www.webgraphics.nl",
    "wof:name":"Web Graphics",
    "wof:placetype":"venue"
},
  "geometry": {"coordinates":[6.5650200844,53.2164497375],"type":"Point"}
}