{
  "type": "Feature",
  "properties": {
    "iso:country":"NL",
    "sg:address":"Heesbergstraat 19",
    "sg:city":"Heerlen",
    "sg:orig_category":"Kunst And Kunstenaarsbenodigdheden",
    "sg:phone":"+31 45 566 1779",
    "sg:postcode":"6417 AA",
    "sg:province":"Limburg",
    "wof:name":"Nedform",
    "wof:placetype":"venue"
},
  "geometry": {"coordinates":[5.988674,50.876572],"type":"Point"}
}