{
  "type": "Feature",
  "properties": {
    "iso:country":"NL",
    "sg:address":"Terminalwg 12",
    "sg:city":"Amersfoort",
    "sg:orig_category":"Luchtbehandelings- Apparaten",
    "sg:phone":"+31 33 457 1057",
    "sg:postcode":"3821 AJ",
    "sg:province":"Utrecht",
    "wof:name":"Lubbers Bv",
    "wof:placetype":"venue"
},
  "geometry": {"coordinates":[5.414533,52.179096],"type":"Point"}
}