{
  "type": "Feature",
  "properties": {
    "addr:full":"Oosterpark 117 Oostkapelle Zeeland 4356 GN",
    "addr:housenumber":"117",
    "addr:postcode":"4356 gn",
    "addr:street":"Oosterpark",
    "iso:country":"NL",
    "sg:address":"Oosterpark 117",
    "sg:city":"Oostkapelle",
    "sg:orig_category":"Vakantiehuizen",
    "sg:phone":"+31 118 581 897",
    "sg:postcode":"4356 GN",
    "sg:province":"Zeeland",
    "wof:name":"De Boemerang",
    "wof:placetype":"venue"
},
  "geometry": {"coordinates":[3.550532,51.576195],"type":"Point"}
}