{
  "type": "Feature",
  "properties": {
    "addr:full":"Parallelwg 10 Sittard Limburg 6136 AN",
    "addr:housenumber":"10",
    "addr:postcode":"6136 an",
    "addr:street":"Parallelwg",
    "iso:country":"NL",
    "sg:address":"Parallelwg 10",
    "sg:city":"Sittard",
    "sg:classifiers":[
        {
            "category":"Professional",
            "subcategory":"Management & Consulting",
            "type":"Services"
        }
    ],
    "sg:phone":"+31 46 400 7580",
    "sg:postcode":"6136 AN",
    "sg:province":"Limburg",
    "sg:tags":[
        "relation",
        "adviesbureaus",
        "public"
    ],
    "wof:name":"Beurskens, Marloes",
    "wof:placetype":"venue"
},
  "geometry": {"coordinates":[5.861179,51.006428],"type":"Point"}
}