{
  "type": "Feature",
  "properties": {
    "addr:full":"Landbouwstr 23 Schagen North Holland 1741 EG",
    "addr:housenumber":"23",
    "addr:postcode":"1741 eg",
    "addr:street":"Landbouwstr",
    "iso:country":"NL",
    "sg:address":"Landbouwstr 23",
    "sg:city":"Schagen",
    "sg:orig_category":"Videotheken",
    "sg:phone":"+31 224 217 792",
    "sg:postcode":"1741 EG",
    "sg:province":"North Holland",
    "wof:name":"Ster Schagen",
    "wof:placetype":"venue"
},
  "geometry": {"coordinates":[4.802764,52.785961],"type":"Point"}
}