{
  "type": "Feature",
  "properties": {
    "addr:full":"V Oldenbarnev Ln 11 Woerden Utrecht 3445 AD",
    "addr:housenumber":"11",
    "addr:postcode":"3445 ad",
    "addr:street":"Oldenbarnev Ln",
    "iso:country":"NL",
    "sg:address":"V Oldenbarnev Ln 11",
    "sg:city":"Woerden",
    "sg:orig_category":"Bedrijfsopleidingen",
    "sg:phone":"+31 348 433 999",
    "sg:postcode":"3445 AD",
    "sg:province":"Utrecht",
    "sg:website":"http://www.learn2improve.nl",
    "wof:name":"Learn2Improve Bv",
    "wof:placetype":"venue"
},
  "geometry": {"coordinates":[4.887371,52.085117],"type":"Point"}
}