{
  "type": "Feature",
  "properties": {
    "addr:full":"Bussumerstr 58-60 Hilversum North Holland 1211 BL",
    "addr:housenumber":"58-60",
    "addr:postcode":"1211 bl",
    "iso:country":"NL",
    "sg:address":"Bussumerstr 58-60",
    "sg:city":"Hilversum",
    "sg:orig_category":"Keukens",
    "sg:phone":"+31 35 624 3894",
    "sg:postcode":"1211 BL",
    "sg:province":"North Holland",
    "wof:name":"Houtsma Keukens",
    "wof:placetype":"venue"
},
  "geometry": {"coordinates":[5.173287,52.225391],"type":"Point"}
}