{
  "type": "Feature",
  "properties": {
    "addr:full":"Nieuwstr 7 Raalte Overijssel 8102 EH",
    "addr:housenumber":"7",
    "addr:postcode":"8102 eh",
    "addr:street":"Nieuwstr",
    "iso:country":"NL",
    "sg:address":"Nieuwstr 7",
    "sg:city":"Raalte",
    "sg:orig_category":"Administratie- En Boekhoudkantoren",
    "sg:phone":"+31 572 352 084",
    "sg:postcode":"8102 EH",
    "sg:province":"Overijssel",
    "wof:name":"Brinkhuis Raalte Bv",
    "wof:placetype":"venue"
},
  "geometry": {"coordinates":[6.278298,52.388702],"type":"Point"}
}