{
  "type": "Feature",
  "properties": {
    "addr:full":"Schepenstr 2 S Hertogenbosch North Brabant 5236 AK",
    "addr:housenumber":"2",
    "addr:postcode":"5236 ak",
    "addr:street":"Schepenstr",
    "iso:country":"NL",
    "sg:address":"Schepenstr 2",
    "sg:city":"S Hertogenbosch",
    "sg:orig_category":"Grafisch Ontwerpers",
    "sg:phone":"+31 73 642 7957",
    "sg:postcode":"5236 AK",
    "sg:province":"North Brabant",
    "sg:website":"http://www.typoform.nl",
    "wof:name":"Typoform",
    "wof:placetype":"venue"
},
  "geometry": {"coordinates":[5.326031,51.728096],"type":"Point"}
}