{
  "type": "Feature",
  "properties": {
    "iso:country":"NL",
    "sg:address":"Plesmanwg 593",
    "sg:city":"Beverwyk",
    "sg:orig_category":"Autorijscholen",
    "sg:phone":"+31 251 250 846",
    "sg:postcode":"1945 WV",
    "sg:province":"Noord-Holland",
    "wof:name":"Econoom, De",
    "wof:placetype":"venue"
},
  "geometry": {"coordinates":[-80.181808,38.920101],"type":"Point"}
}