{
  "type": "Feature",
  "properties": {
    "iso:country":"NL",
    "sg:address":"Stationsstr 130",
    "sg:city":"Apeldoorn",
    "sg:orig_category":"Keukens",
    "sg:phone":"+31 55 579 0061",
    "sg:postcode":"7311 MJ",
    "sg:province":"Gelderland",
    "sg:website":"http://www.bruynzeel.nl",
    "wof:name":"Bruynzeel",
    "wof:placetype":"venue"
},
  "geometry": {"coordinates":[5.966276,52.214542],"type":"Point"}
}