{
  "type": "Feature",
  "properties": {
    "addr:full":"Oude Amersf Wg 22 Hilversum Noord-Holland 1213 AD",
    "addr:housenumber":"22",
    "addr:postcode":"1213 ad",
    "addr:street":"Oude;Wg",
    "iso:country":"NL",
    "sg:address":"Oude Amersf Wg 22",
    "sg:city":"Hilversum",
    "sg:orig_category":"Webdesign Bureaus",
    "sg:phone":"+31 35 621 7619",
    "sg:postcode":"1213 AD",
    "sg:province":"Noord-Holland",
    "sg:website":"http://www.nibble.nl",
    "wof:name":"Nibble Consultancy Bv",
    "wof:placetype":"venue"
},
  "geometry": {"coordinates":[5.1833100319,52.2193031311],"type":"Point"}
}