{
  "type": "Feature",
  "properties": {
    "addr:full":"Hobbemastr 47 Leeuwarden Friesland 8932 LA",
    "addr:housenumber":"47",
    "addr:postcode":"8932 la",
    "addr:street":"Hobbemastr",
    "iso:country":"NL",
    "sg:address":"Hobbemastr 47",
    "sg:city":"Leeuwarden",
    "sg:orig_category":"Voetbalverenigingen",
    "sg:phone":"+31 58 213 3271",
    "sg:postcode":"8932 LA",
    "sg:province":"Friesland",
    "wof:name":"Cambuur '69",
    "wof:placetype":"venue"
},
  "geometry": {"coordinates":[5.791046,53.19146],"type":"Point"}
}