{
  "type": "Feature",
  "properties": {
    "addr:full":"Minrebroederstraat 13 Utrecht Utrecht 3512 GS",
    "addr:housenumber":"13",
    "addr:postcode":"3512 gs",
    "addr:street":"Minrebroederstraat",
    "iso:country":"NL",
    "sg:address":"Minrebroederstraat 13",
    "sg:city":"Utrecht",
    "sg:orig_category":"Kantoorartikelen",
    "sg:phone":"+31 30 230 6900",
    "sg:postcode":"3512 GS",
    "sg:province":"Utrecht",
    "wof:name":"Library Service Bv",
    "wof:placetype":"venue"
},
  "geometry": {"coordinates":[5.1208958626,52.0923957825],"type":"Point"}
}