{
  "type": "Feature",
  "properties": {
    "iso:country":"NL",
    "sg:address":"Anjerstr 1",
    "sg:city":"Helmond",
    "sg:orig_category":"Nagelstudio'S",
    "sg:phone":"+31 492 527 238",
    "sg:postcode":"5701 EX",
    "sg:province":"Noord-Brabant",
    "sg:website":"http://www.beautynails.nl",
    "wof:name":"Beauty-Nails",
    "wof:placetype":"venue"
},
  "geometry": {"coordinates":[5.672899,51.479679],"type":"Point"}
}