{
  "type": "Feature",
  "properties": {
    "addr:full":"Kerkeveldstraat 2 Brunssum Limburg 6441 BP",
    "addr:housenumber":"2",
    "addr:postcode":"6441 bp",
    "addr:street":"Kerkeveldstraat",
    "iso:country":"NL",
    "sg:address":"Kerkeveldstraat 2",
    "sg:city":"Brunssum",
    "sg:classifiers":[
        {
            "category":"Fast Food",
            "type":"Food & Drink"
        }
    ],
    "sg:phone":"+31 45 525 2961",
    "sg:postcode":"6441 BP",
    "sg:province":"Limburg",
    "sg:tags":[
        "afhaal",
        "restaurant"
    ],
    "wof:name":"Cafetaria Het Smulhuis Vof",
    "wof:placetype":"venue"
},
  "geometry": {"coordinates":[5.972923,50.948788],"type":"Point"}
}