{
  "type": "Feature",
  "properties": {
    "addr:full":"Kibbelgaarn 7 Veendam Groningen 9644 XP",
    "addr:housenumber":"7",
    "addr:postcode":"9644 xp",
    "addr:street":"Kibbelgaarn",
    "iso:country":"NL",
    "sg:address":"Kibbelgaarn 7",
    "sg:city":"Veendam",
    "sg:orig_category":"Bloemen En Planten - Groothandel",
    "sg:phone":"+31 597 615 044",
    "sg:postcode":"9644 XP",
    "sg:province":"Groningen",
    "wof:name":"Zweep, R D",
    "wof:placetype":"venue"
},
  "geometry": {"coordinates":[6.960964,53.111767],"type":"Point"}
}