{
  "type": "Feature",
  "properties": {
    "addr:full":"Rembrandtln 37 Veenendaal Utrecht 3904 ZK",
    "addr:housenumber":"37",
    "addr:postcode":"3904",
    "addr:street":"Rembrandtln",
    "iso:country":"NL",
    "sg:address":"Rembrandtln 37",
    "sg:city":"Veenendaal",
    "sg:orig_category":"Schoonheidsinstituten",
    "sg:phone":"+31 318 512 868",
    "sg:postcode":"3904 ZK",
    "sg:province":"Utrecht",
    "wof:name":"Evers-Hey, J H",
    "wof:placetype":"venue"
},
  "geometry": {"coordinates":[5.546141,52.020878],"type":"Point"}
}