{
  "type": "Feature",
  "properties": {
    "addr:full":"Twentepoort W 39 Almelo NL.08 7609 RD",
    "addr:housenumber":"39;nl.08",
    "addr:postcode":"7609 rd",
    "addr:street":"Twentepoort W",
    "iso:country":"NL",
    "sg:address":"Twentepoort W 39",
    "sg:city":"Almelo",
    "sg:orig_category":"Plafonds",
    "sg:phone":"+31 546 455 577",
    "sg:postcode":"7609 RD",
    "sg:province":"NL.08",
    "sg:website":"http://www.mulder-verweg.nl",
    "wof:name":"Mulder Verweg Bv",
    "wof:placetype":"venue"
},
  "geometry": {"coordinates":[6.646331,52.326824],"type":"Point"}
}