{
  "type": "Feature",
  "properties": {
    "addr:full":"Loeffstraat 107 Waalwijk Noord-Brabant 5142 EP",
    "addr:housenumber":"107",
    "addr:postcode":"5142 ep",
    "addr:street":"Loeffstraat",
    "iso:country":"NL",
    "sg:address":"Loeffstraat 107",
    "sg:city":"Waalwijk",
    "sg:orig_category":"Overheidsdiensten",
    "sg:phone":"+31 416 561 593",
    "sg:postcode":"5142 EP",
    "sg:province":"Noord-Brabant",
    "wof:name":"De Ouwe Toren",
    "wof:placetype":"venue"
},
  "geometry": {"coordinates":[5.0925898552,51.6940689087],"type":"Point"}
}