{
  "type": "Feature",
  "properties": {
    "addr:full":"Oostdorperwg 177 Wassenaar Zuid-Holland 2242 NJ",
    "addr:housenumber":"177",
    "addr:postcode":"2242 nj",
    "iso:country":"NL",
    "sg:address":"Oostdorperwg 177",
    "sg:city":"Wassenaar",
    "sg:classifiers":[
        {
            "category":"Retail",
            "subcategory":"Auto Repair",
            "type":"Services"
        }
    ],
    "sg:phone":"+31 70 511 0630",
    "sg:postcode":"2242 NJ",
    "sg:province":"Zuid-Holland",
    "sg:tags":[
        "garage"
    ],
    "wof:name":"Sirre",
    "wof:placetype":"venue"
},
  "geometry": {"coordinates":[4.40006,52.151611],"type":"Point"}
}