{
  "type": "Feature",
  "properties": {
    "iso:country":"NL",
    "sg:address":"Couwenhoven 6119",
    "sg:city":"Zeist",
    "sg:orig_category":"Marktonderzoekbureaus",
    "sg:phone":"+31 30 696 2320",
    "sg:postcode":"3703 HH",
    "sg:province":"Utrecht",
    "wof:name":"Zuure International Management Consultan",
    "wof:placetype":"venue"
},
  "geometry": {"coordinates":[5.226059,52.077755],"type":"Point"}
}