{
  "type": "Feature",
  "properties": {
    "iso:country":"NL",
    "sg:address":"Kerveldonk 1",
    "sg:city":"Spykenisse",
    "sg:orig_category":"Kantoor- En Secretariaatsservice",
    "sg:phone":"+31 181 673 828",
    "sg:postcode":"3206 ED",
    "sg:province":"Zuid-Holland",
    "wof:name":"Jong, Amanda De",
    "wof:placetype":"venue"
},
  "geometry": {"coordinates":[4.3247609138,51.8299064636],"type":"Point"}
}