{
  "type": "Feature",
  "properties": {
    "iso:country":"NL",
    "sg:address":"Besterdring 62 A",
    "sg:city":"Tilburg",
    "sg:orig_category":"Meubels And Huishoudapparatuur Gh",
    "sg:phone":"+31 13 544 4538",
    "sg:postcode":"5014 HM",
    "sg:province":"Noord-Brabant",
    "wof:name":"Leo Naaijkens Bedden",
    "wof:placetype":"venue"
},
  "geometry": {"coordinates":[5.089607,51.565685],"type":"Point"}
}