{
  "type": "Feature",
  "properties": {
    "iso:country":"NL",
    "sg:address":"Gitstraat 1",
    "sg:city":"Leiden",
    "sg:orig_category":"Begrafenisondernemers",
    "sg:phone":"+31 71 573 0830",
    "sg:postcode":"2332 RB",
    "sg:province":"South Holland",
    "wof:name":"Ad Sanctos",
    "wof:placetype":"venue"
},
  "geometry": {"coordinates":[4.461601,52.159832],"type":"Point"}
}