{
  "type": "Feature",
  "properties": {
    "addr:full":"Daelderweg 23 Nuth Limburg 6361  H",
    "addr:housenumber":"23;6361 h",
    "addr:street":"Daelderweg",
    "iso:country":"NL",
    "sg:address":"Daelderweg 23",
    "sg:city":"Nuth",
    "sg:orig_category":"Bedrijfsinventaris Gh",
    "sg:phone":"+31 45 524 3900",
    "sg:postcode":"6361  H",
    "sg:province":"Limburg",
    "wof:name":"Jvh Exploitatie Nuth",
    "wof:placetype":"venue"
},
  "geometry": {"coordinates":[5.882251,50.925167],"type":"Point"}
}