{
  "type": "Feature",
  "properties": {
    "addr:full":"Grote Achterweg 24 Naaldwijk South Holland 2671 LR",
    "addr:housenumber":"24",
    "addr:postcode":"2671 lr",
    "addr:street":"Grote Achterweg",
    "iso:country":"NL",
    "sg:address":"Grote Achterweg 24",
    "sg:city":"Naaldwijk",
    "sg:orig_category":"Schilderwerk",
    "sg:phone":"+31 174 640 236",
    "sg:postcode":"2671 LR",
    "sg:province":"South Holland",
    "wof:name":"N Van Der Houwen",
    "wof:placetype":"venue"
},
  "geometry": {"coordinates":[4.200548,52.007816],"type":"Point"}
}