{
  "type": "Feature",
  "properties": {
    "iso:country":"NL",
    "sg:address":"Dr Stoltewg 64B",
    "sg:city":"Zwolle",
    "sg:orig_category":"Psychotherapeuten",
    "sg:phone":"+31 38 452 4845",
    "sg:postcode":"8025 AZ",
    "sg:province":"Overijssel",
    "sg:website":"http://www.hsk.nl",
    "wof:name":"Hsk Zwolle",
    "wof:placetype":"venue"
},
  "geometry": {"coordinates":[6.121307,52.515171],"type":"Point"}
}