{
  "type": "Feature",
  "properties": {
    "addr:full":"Bergse L Rottekd 435 Rotterdam South Holland 3069 LV",
    "addr:housenumber":"435",
    "addr:postcode":"3069",
    "addr:street":"Bergse",
    "iso:country":"NL",
    "sg:address":"Bergse L Rottekd 435",
    "sg:city":"Rotterdam",
    "sg:orig_category":"Kinderactiviteiten",
    "sg:phone":"+31 10 420 2094",
    "sg:postcode":"3069 LV",
    "sg:province":"South Holland",
    "wof:name":"Groene Kikker, De",
    "wof:placetype":"venue"
},
  "geometry": {"coordinates":[4.535886,51.969723],"type":"Point"}
}