{
  "type": "Feature",
  "properties": {
    "iso:country":"NL",
    "sg:address":"Pastoor Savenijelaan 17",
    "sg:city":"Oosterhout Gld",
    "sg:classifiers":[
        {
            "category":"Education",
            "subcategory":"Preschool",
            "type":"Public Place"
        }
    ],
    "sg:phone":"+31 481 481 634",
    "sg:postcode":"6678 BK",
    "sg:province":"Gelderland",
    "sg:tags":[
        "kleuteronderwijs",
        "basis-"
    ],
    "wof:name":"Openbare Basisschool De Open Kring",
    "wof:placetype":"venue"
},
  "geometry": {"coordinates":[5.827213,51.877449],"type":"Point"}
}