{
  "type": "Feature",
  "properties": {
    "addr:full":"Postbus 194 Barendrecht South Holland 2990 AD",
    "addr:housenumber":"194",
    "addr:postcode":"2990 ad",
    "addr:street":"Postbus",
    "iso:country":"NL",
    "sg:address":"Postbus 194",
    "sg:city":"Barendrecht",
    "sg:orig_category":"Juridische Adviseurs",
    "sg:phone":"+31 180 616 688",
    "sg:postcode":"2990 AD",
    "sg:province":"South Holland",
    "sg:website":"http://www.oosterbaan.com",
    "wof:name":"Oosterbaan & Partn Bv",
    "wof:placetype":"venue"
},
  "geometry": {"coordinates":[4.54064,51.853176],"type":"Point"}
}