{
  "type": "Feature",
  "properties": {
    "iso:country":"NL",
    "sg:address":"Appelwg 9A",
    "sg:city":"Moerdyk",
    "sg:classifiers":[
        {
            "category":"Retail",
            "subcategory":"Storage",
            "type":"Services"
        }
    ],
    "sg:phone":"+31 168 416 060",
    "sg:postcode":"4782 PX",
    "sg:province":"Noord-Brabant",
    "sg:tags":[
        "op-",
        "en",
        "overslagbedrijven"
    ],
    "wof:name":"Bolsius",
    "wof:placetype":"venue"
},
  "geometry": {"coordinates":[4.614461,51.697632],"type":"Point"}
}