{
  "type": "Feature",
  "properties": {
    "addr:full":"Piet Heinstraat 29 Barendrecht South Holland 2992 BM",
    "addr:housenumber":"29",
    "addr:postcode":"2992 bm",
    "addr:street":"Piet Heinstraat",
    "iso:country":"NL",
    "sg:address":"Piet Heinstraat 29",
    "sg:city":"Barendrecht",
    "sg:orig_category":"Architecten",
    "sg:phone":"+31 180 613 416",
    "sg:postcode":"2992 BM",
    "sg:province":"South Holland",
    "wof:name":"Ab Architectuur & Bouwkunde H. Spek Bv",
    "wof:placetype":"venue"
},
  "geometry": {"coordinates":[4.533665,51.858692],"type":"Point"}
}