{
  "type": "Feature",
  "properties": {
    "iso:country":"NL",
    "sg:address":"De Leijen 23",
    "sg:city":"Gorredijk",
    "sg:orig_category":"Visspeciaalzaken",
    "sg:phone":"+31 513 464 523",
    "sg:postcode":"8401 AX",
    "sg:province":"Friesland",
    "wof:name":"Vishandel J. Krist",
    "wof:placetype":"venue"
},
  "geometry": {"coordinates":[6.066426,52.991821],"type":"Point"}
}