{
  "type": "Feature",
  "properties": {
    "addr:full":"Heereweg 246 Lisse Zuid-Holland 2161 BR",
    "addr:housenumber":"246",
    "addr:postcode":"2161 br",
    "addr:street":"Heereweg",
    "iso:country":"NL",
    "sg:address":"Heereweg 246",
    "sg:city":"Lisse",
    "sg:classifiers":[
        {
            "category":"Bakery",
            "type":"Food & Drink"
        }
    ],
    "sg:phone":"+31 252 418 766",
    "sg:postcode":"2161 BR",
    "sg:province":"Zuid-Holland",
    "sg:tags":[
        "brood",
        "banket"
    ],
    "wof:name":"Echte Bakker Van Maanen",
    "wof:placetype":"venue"
},
  "geometry": {"coordinates":[4.553286,52.258686],"type":"Point"}
}