{
  "type": "Feature",
  "properties": {
    "addr:full":"Hoofdwg 482 Amsterdam North Holland 1055 AC",
    "addr:housenumber":"482",
    "addr:postcode":"1055 ac",
    "iso:country":"NL",
    "sg:address":"Hoofdwg 482",
    "sg:city":"Amsterdam",
    "sg:orig_category":"Wassalons",
    "sg:phone":"+31 20 684 6561",
    "sg:postcode":"1055 AC",
    "sg:province":"North Holland",
    "wof:name":"Hoofdweg Wasserette",
    "wof:placetype":"venue"
},
  "geometry": {"coordinates":[4.8468542099,52.3770866394],"type":"Point"}
}