{
  "type": "Feature",
  "properties": {
    "iso:country":"NL",
    "sg:address":"Hoofdwg 482",
    "sg:city":"Amsterdam",
    "sg:orig_category":"Wassalons",
    "sg:phone":"+31 20 684 6561",
    "sg:postcode":"1055 AC",
    "sg:province":"North Holland",
    "wof:name":"Hoofdweg Wasserette",
    "wof:placetype":"venue"
},
  "geometry": {"coordinates":[4.8468542099,52.3770866394],"type":"Point"}
}