{
  "type": "Feature",
  "properties": {
    "iso:country":"NL",
    "sg:address":"Eendrachtstraat 48",
    "sg:city":"Middelharnis",
    "sg:orig_category":"Loodgieterswerk, Verwarming And Sanitaire Installaties",
    "sg:phone":"+31 187 484 453",
    "sg:postcode":"3241 CD",
    "sg:province":"Zuid-Holland",
    "wof:name":"Loodgietersbedrijf Rijmi",
    "wof:placetype":"venue"
},
  "geometry": {"coordinates":[4.162718,51.759537],"type":"Point"}
}