{
  "type": "Feature",
  "properties": {
    "addr:full":"J Keplerweg 12 Alphen A/D Rijn Zuid-Holland 2408 AC",
    "addr:housenumber":"12",
    "addr:postcode":"2408 ac",
    "addr:street":"J Keplerweg",
    "iso:country":"NL",
    "sg:address":"J Keplerweg 12",
    "sg:city":"Alphen A/D Rijn",
    "sg:orig_category":"Werving And Selectie Van Tijdelijk Personeel And Uitzendkantoren",
    "sg:phone":"+31 172 492 280",
    "sg:postcode":"2408 AC",
    "sg:province":"Zuid-Holland",
    "wof:name":"Start",
    "wof:placetype":"venue"
},
  "geometry": {"coordinates":[4.6381149292,52.1244010925],"type":"Point"}
}