{
  "type": "Feature",
  "properties": {
    "iso:country":"NL",
    "sg:address":"Rio Grande 1",
    "sg:city":"Amstelveen",
    "sg:orig_category":"Vertalers",
    "sg:phone":"+31 20 641 9282",
    "sg:postcode":"1186 JK",
    "sg:province":"North Holland",
    "wof:name":"Porcelijn, Drs H M",
    "wof:placetype":"venue"
},
  "geometry": {"coordinates":[4.869598,52.283295],"type":"Point"}
}