{
  "type": "Feature",
  "properties": {
    "addr:full":"Viandenstr 7A S Gravenhage South Holland 2552 CA",
    "addr:housenumber":"7a",
    "addr:postcode":"2552 ca",
    "addr:street":"Viandenstr;S Gravenhage",
    "iso:country":"NL",
    "sg:address":"Viandenstr 7A",
    "sg:city":"S Gravenhage",
    "sg:classifiers":[
        {
            "category":"Wholesale",
            "subcategory":"Motor Vehicles",
            "type":"Manufacturing & Wholesale Goods"
        }
    ],
    "sg:phone":"+31 70 397 9070",
    "sg:postcode":"2552 CA",
    "sg:province":"South Holland",
    "sg:tags":[
        "scooter",
        "en"
    ],
    "wof:name":"Collections",
    "wof:placetype":"venue"
},
  "geometry": {"coordinates":[4.24958,52.053631],"type":"Point"}
}