{
  "type": "Feature",
  "properties": {
    "iso:country":"NL",
    "sg:address":"Sloetswg 155",
    "sg:city":"Hengelo Ov",
    "sg:orig_category":"Scholen Voor Algemeen Voortgezet Onderwijs",
    "sg:phone":"+31 74 291 4629",
    "sg:postcode":"7556 HM",
    "sg:province":"Overijssel",
    "wof:name":"Osg Hengelo",
    "wof:placetype":"venue"
},
  "geometry": {"coordinates":[6.799129,52.27425],"type":"Point"}
}