{
  "type": "Feature",
  "properties": {
    "addr:full":"Sint Janstraat 64 Enschede Overijssel 7543 TZ",
    "addr:housenumber":"64",
    "addr:postcode":"7543 tz",
    "addr:street":"Sint Janstraat",
    "iso:country":"NL",
    "sg:address":"Sint Janstraat 64",
    "sg:city":"Enschede",
    "sg:orig_category":"Goederenvervoer Over De Weg",
    "sg:phone":"+31 6 51591575",
    "sg:postcode":"7543 TZ",
    "sg:province":"Overijssel",
    "wof:name":"W.G. Newby",
    "wof:placetype":"venue"
},
  "geometry": {"coordinates":[6.877513,52.208733],"type":"Point"}
}