{
  "type": "Feature",
  "properties": {
    "addr:full":"Rutselboslaan 25 Oosterhout Nb Noord-Brabant 4901 MD",
    "addr:housenumber":"25",
    "addr:postcode":"4901",
    "addr:street":"Rutselboslaan",
    "iso:country":"NL",
    "sg:address":"Rutselboslaan 25",
    "sg:city":"Oosterhout Nb",
    "sg:orig_category":"Paramedische Behandelingen",
    "sg:phone":"+31 162 434 202",
    "sg:postcode":"4901 MD",
    "sg:province":"Noord-Brabant",
    "wof:name":"M.H.J. Ten Holter",
    "wof:placetype":"venue"
},
  "geometry": {"coordinates":[4.863714,51.646],"type":"Point"}
}