{
  "type": "Feature",
  "properties": {
    "addr:full":"Plesmanweg 20 Almelo NL.08 7602 PE",
    "addr:housenumber":"20;nl.08",
    "addr:postcode":"7602 pe",
    "addr:street":"Plesmanweg",
    "iso:country":"NL",
    "sg:address":"Plesmanweg 20",
    "sg:city":"Almelo",
    "sg:orig_category":"Autokeuringen",
    "sg:phone":"+31 546 872 170",
    "sg:postcode":"7602 PE",
    "sg:province":"NL.08",
    "wof:name":"Van Der Weij Banden Service Bv",
    "wof:placetype":"venue"
},
  "geometry": {"coordinates":[6.640468,52.372066],"type":"Point"}
}