{
  "type": "Feature",
  "properties": {
    "addr:full":"Wieringenstr 9 Breda Noord-Brabant 4817 AN",
    "addr:housenumber":"9",
    "addr:postcode":"4817 an",
    "addr:street":"Wieringenstr",
    "iso:country":"NL",
    "sg:address":"Wieringenstr 9",
    "sg:city":"Breda",
    "sg:orig_category":"Adviesbureaus Bedrijfsorganisatie",
    "sg:phone":"+31 6 23601823",
    "sg:postcode":"4817 AN",
    "sg:province":"Noord-Brabant",
    "wof:name":"Beside Labour",
    "wof:placetype":"venue"
},
  "geometry": {"coordinates":[4.81473,51.596554],"type":"Point"}
}