{
  "type": "Feature",
  "properties": {
    "addr:full":"Zeilstr 26 Amsterdam Noord-Holland 1075 SH",
    "addr:housenumber":"26;1075",
    "addr:postcode":"sh",
    "addr:street":"Zeilstr",
    "iso:country":"NL",
    "sg:address":"Zeilstr 26",
    "sg:city":"Amsterdam",
    "sg:orig_category":"Verlichting",
    "sg:phone":"+31 20 662 3200",
    "sg:postcode":"1075 SH",
    "sg:province":"Noord-Holland",
    "wof:name":"Helios",
    "wof:placetype":"venue"
},
  "geometry": {"coordinates":[4.855054,52.351227],"type":"Point"}
}