{
  "type": "Feature",
  "properties": {
    "addr:full":"Slachthuiskd 38 Rotterdam South Holland 3034 ES",
    "addr:housenumber":"38",
    "addr:postcode":"3034 es",
    "addr:street":"Slachthuiskd",
    "iso:country":"NL",
    "sg:address":"Slachthuiskd 38",
    "sg:city":"Rotterdam",
    "sg:orig_category":"Verenigingen En Stichtingen",
    "sg:phone":"+31 10 413 4016",
    "sg:postcode":"3034 ES",
    "sg:province":"South Holland",
    "wof:name":"Rotterdamse Postduivenhouders Bond",
    "wof:placetype":"venue"
},
  "geometry": {"coordinates":[4.498428,51.930447],"type":"Point"}
}