{
  "type": "Feature",
  "properties": {
    "addr:full":"Groes 30 Eersel Noord-Brabant 5521 LX",
    "addr:housenumber":"30",
    "addr:postcode":"5521 lx",
    "addr:street":"Groes",
    "iso:country":"NL",
    "sg:address":"Groes 30",
    "sg:city":"Eersel",
    "sg:orig_category":"Wegen And Sportterreinen",
    "sg:phone":"+31 497 518 196",
    "sg:postcode":"5521 LX",
    "sg:province":"Noord-Brabant",
    "wof:name":"Ha Vof",
    "wof:placetype":"venue"
},
  "geometry": {"coordinates":[5.3104801178,51.3514938354],"type":"Point"}
}