{
  "type": "Feature",
  "properties": {
    "addr:full":"Flevoln 27C Weesp North Holland 1382 JX",
    "addr:housenumber":"27c",
    "addr:postcode":"1382 jx",
    "addr:street":"Flevoln",
    "iso:country":"NL",
    "sg:address":"Flevoln 27C",
    "sg:city":"Weesp",
    "sg:orig_category":"Geschenkartikelen",
    "sg:phone":"+31 294 483 097",
    "sg:postcode":"1382 JX",
    "sg:province":"North Holland",
    "sg:website":"http://www.computertelefoonbon.nl",
    "wof:name":"Computerbon Bv, De",
    "wof:placetype":"venue"
},
  "geometry": {"coordinates":[5.03828,52.308315],"type":"Point"}
}