{
  "type": "Feature",
  "properties": {
    "addr:full":"Ophelialaan 104 Aalsmeer North Holland 1431 HM",
    "addr:housenumber":"104",
    "addr:postcode":"1431 hm",
    "addr:street":"Ophelialaan",
    "iso:country":"NL",
    "sg:address":"Ophelialaan 104",
    "sg:city":"Aalsmeer",
    "sg:classifiers":[
        {
            "category":"Food & Beverages",
            "subcategory":"Fruits & Vegetables",
            "type":"Retail Goods"
        }
    ],
    "sg:phone":"+31 297 329 113",
    "sg:postcode":"1431 HM",
    "sg:province":"North Holland",
    "sg:tags":[
        "groenten"
    ],
    "wof:name":"Duijs Vers Vof",
    "wof:placetype":"venue"
},
  "geometry": {"coordinates":[4.761083,52.26403],"type":"Point"}
}