{
  "type": "Feature",
  "properties": {
    "addr:full":"Rokkeveensewg 34 Zoetermeer Zuid-Holland 2712 XZ",
    "addr:housenumber":"34",
    "addr:postcode":"2712 xz",
    "addr:street":"Rokkeveensewg",
    "iso:country":"NL",
    "sg:address":"Rokkeveensewg 34",
    "sg:city":"Zoetermeer",
    "sg:orig_category":"Accountants - Administratie- Consulenten En -Kantoren",
    "sg:phone":"+31 79 341 9856",
    "sg:postcode":"2712 XZ",
    "sg:province":"Zuid-Holland",
    "wof:name":"Lips Bv",
    "wof:placetype":"venue"
},
  "geometry": {"coordinates":[4.505339,52.045971],"type":"Point"}
}