{
  "type": "Feature",
  "properties": {
    "addr:full":"Bosschendijk 195 Oudenbosch Noord-Brabant 4731 DD",
    "addr:housenumber":"195",
    "addr:postcode":"4731 dd",
    "addr:street":"Bosschendijk",
    "iso:country":"NL",
    "sg:address":"Bosschendijk 195",
    "sg:city":"Oudenbosch",
    "sg:orig_category":"Auto'S And Voertuigen",
    "sg:phone":"+31 165 313 944",
    "sg:postcode":"4731 DD",
    "sg:province":"Noord-Brabant",
    "wof:name":"A. Van Beek & Zonen Bv",
    "wof:placetype":"venue"
},
  "geometry": {"coordinates":[4.552071,51.589516],"type":"Point"}
}