{
  "type": "Feature",
  "properties": {
    "addr:full":"Hofwg 19 Warnsveld Gelderland 7231 BG",
    "addr:housenumber":"19",
    "addr:postcode":"7231",
    "addr:street":"Hofwg;Gelderland",
    "iso:country":"NL",
    "sg:address":"Hofwg 19",
    "sg:city":"Warnsveld",
    "sg:orig_category":"Artiesten/Gezelschappen",
    "sg:phone":"+31 575 548 383",
    "sg:postcode":"7231 BG",
    "sg:province":"Gelderland",
    "sg:website":"http://www.djbmaatwerkcabaret.nl",
    "wof:name":"Djb Maatwerkcabaret",
    "wof:placetype":"venue"
},
  "geometry": {"coordinates":[6.223756,52.141724],"type":"Point"}
}