{
  "type": "Feature",
  "properties": {
    "addr:full":"1E Oosterparkstr 95 Amsterdam Noord-Holland 1091 GW",
    "addr:housenumber":"95",
    "addr:postcode":"1091 gw",
    "addr:street":"1E Oosterparkstr",
    "iso:country":"NL",
    "sg:address":"1E Oosterparkstr 95",
    "sg:city":"Amsterdam",
    "sg:orig_category":"Nagelstudio'S",
    "sg:phone":"+31 20 362 3352",
    "sg:postcode":"1091 GW",
    "sg:province":"Noord-Holland",
    "wof:name":"Just Friends",
    "wof:placetype":"venue"
},
  "geometry": {"coordinates":[4.910176,52.356342],"type":"Point"}
}