{
  "type": "Feature",
  "properties": {
    "addr:full":"Fynjekd 82 S Gravenhage Zuid-Holland 2521 CR",
    "addr:housenumber":"82;gravenhage;2521",
    "addr:postcode":"cr",
    "addr:street":"Fynjekd;S",
    "iso:country":"NL",
    "sg:address":"Fynjekd 82",
    "sg:city":"S Gravenhage",
    "sg:orig_category":"Verzekeringen - Verzekeringskantoren",
    "sg:phone":"+31 70 363 4467",
    "sg:postcode":"2521 CR",
    "sg:province":"Zuid-Holland",
    "wof:name":"Kibaima Verzekeringen Bv",
    "wof:placetype":"venue"
},
  "geometry": {"coordinates":[4.3207101822,52.0629882812],"type":"Point"}
}