{
  "type": "Feature",
  "properties": {
    "addr:full":"Julianaln 33 Eefde Gelderland 7211 GS",
    "addr:housenumber":"33",
    "addr:postcode":"7211 gs",
    "addr:street":"Julianaln;Gelderland",
    "iso:country":"NL",
    "sg:address":"Julianaln 33",
    "sg:city":"Eefde",
    "sg:orig_category":"Evenementenverzorging",
    "sg:phone":"+31 575 540 791",
    "sg:postcode":"7211 GS",
    "sg:province":"Gelderland",
    "sg:website":"http://www.aena-evenementen.nl",
    "wof:name":"A & A",
    "wof:placetype":"venue"
},
  "geometry": {"coordinates":[6.222618,52.17168],"type":"Point"}
}