{
  "type": "Feature",
  "properties": {
    "addr:full":"Molenpoort 5 Weert Limburg 6001 HB",
    "addr:housenumber":"5",
    "addr:postcode":"6001 hb",
    "addr:street":"Molenpoort",
    "iso:country":"NL",
    "sg:address":"Molenpoort 5",
    "sg:city":"Weert",
    "sg:orig_category":"Kappers",
    "sg:phone":"+31 495 532 662",
    "sg:postcode":"6001 HB",
    "sg:province":"Limburg",
    "wof:name":"Vof P. Van De Sande",
    "wof:placetype":"venue"
},
  "geometry": {"coordinates":[5.702618,51.254166],"type":"Point"}
}