{
  "type": "Feature",
  "properties": {
    "iso:country":"NL",
    "sg:address":"Rozenstraat 15",
    "sg:city":"Haarlem",
    "sg:orig_category":"Verzekeringen",
    "sg:phone":"+31 23 532 1232",
    "sg:postcode":"2011 LS",
    "sg:province":"Noord-Holland",
    "wof:name":"Assurantiekantoor Kweekduin Bv",
    "wof:placetype":"venue"
},
  "geometry": {"coordinates":[4.633545,52.387913],"type":"Point"}
}