{
  "type": "Feature",
  "properties": {
    "addr:full":"Kortegracht 4 Amersfoort Utrecht 3811 KH",
    "addr:housenumber":"4",
    "addr:postcode":"3811 kh",
    "addr:street":"Kortegracht",
    "iso:country":"NL",
    "sg:address":"Kortegracht 4",
    "sg:city":"Amersfoort",
    "sg:orig_category":"Discountwinkels",
    "sg:phone":"+31 33 461 5250",
    "sg:postcode":"3811 KH",
    "sg:province":"Utrecht",
    "wof:name":"Vof Pritty Mystelle",
    "wof:placetype":"venue"
},
  "geometry": {"coordinates":[5.386085,52.152325],"type":"Point"}
}