{
  "type": "Feature",
  "properties": {
    "addr:full":"Dorpsweg 152 C Rotterdam-Zuid South Holland 3083 LK",
    "addr:housenumber":"152 c rotterdam-zuid",
    "addr:postcode":"3083 lk",
    "addr:street":"Dorpsweg",
    "iso:country":"NL",
    "sg:address":"Dorpsweg 152 C",
    "sg:city":"Rotterdam-Zuid",
    "sg:orig_category":"Begrafenisondernemers",
    "sg:phone":"+31 10 480 3471",
    "sg:postcode":"3083 LK",
    "sg:province":"South Holland",
    "wof:name":"P.A. Van Der Waal & Zn.",
    "wof:placetype":"venue"
},
  "geometry": {"coordinates":[4.472134,51.886391],"type":"Point"}
}