{
  "type": "Feature",
  "properties": {
    "iso:country":"NL",
    "sg:address":"Beneden Oosterdiep 1",
    "sg:city":"Veendam",
    "sg:classifiers":[
        {
            "category":"Fast Food",
            "type":"Food & Drink"
        }
    ],
    "sg:phone":"+31 598 631 951",
    "sg:postcode":"9641 JA",
    "sg:province":"Groningen",
    "sg:tags":[
        "afhaal",
        "restaurant"
    ],
    "wof:name":"Smulcentrum Bestaria",
    "wof:placetype":"venue"
},
  "geometry": {"coordinates":[6.88173,53.105797],"type":"Point"}
}