{
  "type": "Feature",
  "properties": {
    "addr:full":"Ijsbaanlaan 2 Haarlem Noord-Holland 2024 AV",
    "addr:housenumber":"2",
    "addr:postcode":"2024 av",
    "addr:street":"Ijsbaanlaan",
    "iso:country":"NL",
    "sg:address":"Ijsbaanlaan 2",
    "sg:city":"Haarlem",
    "sg:classifiers":[
        {
            "category":"Recreation",
            "subcategory":"Amusement Park",
            "type":"Entertainment"
        }
    ],
    "sg:phone":"+31 23 525 4000",
    "sg:postcode":"2024 AV",
    "sg:province":"Noord-Holland",
    "wof:name":"Kennemerland",
    "wof:placetype":"venue"
},
  "geometry": {"coordinates":[4.626793,52.39925],"type":"Point"}
}