{
  "type": "Feature",
  "properties": {
    "addr:full":"Nieuwstr 79 Medemblik North Holland 1671 BC",
    "addr:housenumber":"79",
    "addr:postcode":"1671 bc",
    "addr:street":"Nieuwstr",
    "iso:country":"NL",
    "sg:address":"Nieuwstr 79",
    "sg:city":"Medemblik",
    "sg:orig_category":"Zonnebanken En Solarium-Installaties",
    "sg:phone":"+31 227 545 181",
    "sg:postcode":"1671 BC",
    "sg:province":"North Holland",
    "wof:name":"Everyday Sun & Sports",
    "wof:placetype":"venue"
},
  "geometry": {"coordinates":[5.107252,52.771549],"type":"Point"}
}