{
  "type": "Feature",
  "properties": {
    "addr:full":"Kleine Veerweg 2 Zwolle NL.08 8017 BS",
    "addr:housenumber":"2;8017",
    "addr:street":"Kleine Veerweg;Bs",
    "iso:country":"NL",
    "sg:address":"Kleine Veerweg 2",
    "sg:city":"Zwolle",
    "sg:orig_category":"Verhuur Landbouwmachines",
    "sg:phone":"+31 38 465 5351",
    "sg:postcode":"8017 BS",
    "sg:province":"NL.08",
    "wof:name":"Agrarisch Verhuur- En Handelsond.",
    "wof:placetype":"venue"
},
  "geometry": {"coordinates":[6.085115,52.49139],"type":"Point"}
}