{
  "type": "Feature",
  "properties": {
    "iso:country":"NL",
    "sg:address":"Houtplein 37",
    "sg:city":"Haarlem",
    "sg:orig_category":"Werving And Selectie Van Tijdelijk Personeel And Uitzendkantoren",
    "sg:phone":"+31 23 531 8018",
    "sg:postcode":"2012 DE",
    "sg:province":"Noord-Holland",
    "wof:name":"Kelly Uitzendburo Bv",
    "wof:placetype":"venue"
},
  "geometry": {"coordinates":[4.6310257912,52.3753166199],"type":"Point"}
}