{
  "type": "Feature",
  "properties": {
    "addr:full":"Dennenlaan 1 Putte North Brabant 4645 RP",
    "addr:housenumber":"1",
    "addr:postcode":"4645 rp",
    "addr:street":"Dennenlaan",
    "iso:country":"NL",
    "sg:address":"Dennenlaan 1",
    "sg:city":"Putte",
    "sg:orig_category":"Verzekeringen",
    "sg:phone":"+31 164 602 906",
    "sg:postcode":"4645 RP",
    "sg:province":"North Brabant",
    "wof:name":"G.A. Vergeer",
    "wof:placetype":"venue"
},
  "geometry": {"coordinates":[4.398626,51.366829],"type":"Point"}
}