{
  "type": "Feature",
  "properties": {
    "addr:full":"V Oldenbarneveltp 378 Rotterdam Zuid-Holland 3012 AN",
    "addr:housenumber":"378",
    "addr:postcode":"3012 an",
    "iso:country":"NL",
    "sg:address":"V Oldenbarneveltp 378",
    "sg:city":"Rotterdam",
    "sg:orig_category":"Fotoreportages",
    "sg:phone":"+31 10 404 7562",
    "sg:postcode":"3012 AN",
    "sg:province":"Zuid-Holland",
    "wof:name":"Nass, Jan",
    "wof:placetype":"venue"
},
  "geometry": {"coordinates":[4.47628,51.919361],"type":"Point"}
}