{
  "type": "Feature",
  "properties": {
    "addr:full":"Duizendschoonstraat 27 Rotterdam Zuid-Holland 3051 SC",
    "addr:housenumber":"27",
    "addr:postcode":"3051 sc",
    "addr:street":"Duizendschoonstraat",
    "iso:country":"NL",
    "sg:address":"Duizendschoonstraat 27",
    "sg:city":"Rotterdam",
    "sg:orig_category":"Verhuur Audiovisuele Apparatuur",
    "sg:phone":"+31 10 461 1558",
    "sg:postcode":"3051 SC",
    "sg:province":"Zuid-Holland",
    "wof:name":"P. Heiden Geluidstechniek",
    "wof:placetype":"venue"
},
  "geometry": {"coordinates":[4.470493,51.943577],"type":"Point"}
}