{
  "type": "Feature",
  "properties": {
    "addr:full":"Haalweide 6 Zaandam North Holland 1507 NL",
    "addr:housenumber":"6",
    "addr:postcode":"1507 nl",
    "addr:street":"Haalweide",
    "iso:country":"NL",
    "sg:address":"Haalweide 6",
    "sg:city":"Zaandam",
    "sg:orig_category":"Kappers",
    "sg:phone":"+31 75 612 5992",
    "sg:postcode":"1507 NL",
    "sg:province":"North Holland",
    "wof:name":"Pauline",
    "wof:placetype":"venue"
},
  "geometry": {"coordinates":[4.804534,52.448341],"type":"Point"}
}