{
  "type": "Feature",
  "properties": {
    "addr:full":"Bergse Dorpsstraat 106 Rotterdam Zuid-Holland 3054 GG",
    "addr:housenumber":"106",
    "addr:postcode":"3054 gg",
    "addr:street":"Bergse Dorpsstraat",
    "iso:country":"NL",
    "sg:address":"Bergse Dorpsstraat 106",
    "sg:city":"Rotterdam",
    "sg:classifiers":[
        {
            "category":"Bakery",
            "type":"Food & Drink"
        }
    ],
    "sg:phone":"+31 10 422 4450",
    "sg:postcode":"3054 GG",
    "sg:province":"Zuid-Holland",
    "sg:tags":[
        "brood",
        "banket"
    ],
    "wof:name":"Echte Bakker Guus Steens",
    "wof:placetype":"venue"
},
  "geometry": {"coordinates":[4.494259,51.957714],"type":"Point"}
}