{
  "type": "Feature",
  "properties": {
    "addr:full":"Aalsmeerderwg 289 Aalsmeer Noord-Holland 1432 CN",
    "addr:housenumber":"289",
    "addr:postcode":"aalsmeer;1432 cn",
    "iso:country":"NL",
    "sg:address":"Aalsmeerderwg 289",
    "sg:city":"Aalsmeer",
    "sg:orig_category":"Saunabaden - Import En Groothandel",
    "sg:phone":"+31 297 324 065",
    "sg:postcode":"1432 CN",
    "sg:province":"Noord-Holland",
    "sg:website":"http://www.zwembadtechniek.nl",
    "wof:name":"Been Zwembadtechniek",
    "wof:placetype":"venue"
},
  "geometry": {"coordinates":[4.798722,52.281094],"type":"Point"}
}