{
  "type": "Feature",
  "properties": {
    "addr:full":"Jarigsmastins 7 Leeuwarden Provincie Friesland 8925 EE",
    "addr:housenumber":"7",
    "addr:postcode":"8925 ee",
    "addr:street":"Jarigsmastins;Provincie Friesland",
    "iso:country":"NL",
    "sg:address":"Jarigsmastins 7",
    "sg:city":"Leeuwarden",
    "sg:orig_category":"Onderhoudswerken",
    "sg:phone":"+31 58 212 6904",
    "sg:postcode":"8925 EE",
    "sg:province":"Provincie Friesland",
    "wof:name":"Apeldoorn, Patrick",
    "wof:placetype":"venue"
},
  "geometry": {"coordinates":[5.845064,53.208649],"type":"Point"}
}