{
  "type": "Feature",
  "properties": {
    "iso:country":"NL",
    "sg:address":"Provincialewg 23",
    "sg:city":"Groede",
    "sg:orig_category":"Adviesbureaus Bedrijfsorganisatie",
    "sg:phone":"+31 117 383 943",
    "sg:postcode":"4503 GD",
    "sg:province":"Zeeland",
    "wof:name":"Menue Raadgevers",
    "wof:placetype":"venue"
},
  "geometry": {"coordinates":[3.548302,51.382919],"type":"Point"}
}