{
  "type": "Feature",
  "properties": {
    "iso:country":"NL",
    "sg:address":"Lloydstraat 9",
    "sg:city":"Rotterdam",
    "sg:orig_category":"Film-, Tv- And Videoproductie",
    "sg:phone":"+31 418 680 056",
    "sg:postcode":"3024 EA",
    "sg:province":"Zuid-Holland",
    "wof:name":"Coart Cgi Bv",
    "wof:placetype":"venue"
},
  "geometry": {"coordinates":[4.45985,51.903728],"type":"Point"}
}