{
  "type": "Feature",
  "properties": {
    "addr:full":"Aardheuvel 23 Best Noord-Brabant 5685 AB",
    "addr:housenumber":"23",
    "addr:postcode":"5685 ab",
    "addr:street":"Aardheuvel",
    "iso:country":"NL",
    "sg:address":"Aardheuvel 23",
    "sg:city":"Best",
    "sg:orig_category":"Algemene Werktuigbouw",
    "sg:phone":"+31 499 310 606",
    "sg:postcode":"5685 AB",
    "sg:province":"Noord-Brabant",
    "wof:name":"Meeuwsen Las- En Montagetechniek Vof",
    "wof:placetype":"venue"
},
  "geometry": {"coordinates":[-101.618134,31.224251],"type":"Point"}
}