{
  "type": "Feature",
  "properties": {
    "addr:full":"Spekhouwerstr 2 Voerendaal Limburg 6367 TV",
    "addr:housenumber":"2",
    "addr:postcode":"6367 tv",
    "addr:street":"Spekhouwerstr",
    "iso:country":"NL",
    "sg:address":"Spekhouwerstr 2",
    "sg:city":"Voerendaal",
    "sg:orig_category":"Banken",
    "sg:phone":"+31 45 562 8282",
    "sg:postcode":"6367 TV",
    "sg:province":"Limburg",
    "sg:website":"http://www.rabobank.nl",
    "wof:name":"Rabobank",
    "wof:placetype":"venue"
},
  "geometry": {"coordinates":[5.925503,50.882999],"type":"Point"}
}