{
  "type": "Feature",
  "properties": {
    "addr:full":"Begoniastraat 34 Veghel North Brabant 5462 AS",
    "addr:housenumber":"34",
    "addr:postcode":"5462 as",
    "addr:street":"Begoniastraat",
    "iso:country":"NL",
    "sg:address":"Begoniastraat 34",
    "sg:city":"Veghel",
    "sg:orig_category":"Goederenvervoer Over De Weg",
    "sg:phone":"+31 413 342 339",
    "sg:postcode":"5462 AS",
    "sg:province":"North Brabant",
    "wof:name":"Internat. Transportbedrijf J. Van De Kerkhof Bv",
    "wof:placetype":"venue"
},
  "geometry": {"coordinates":[5.53025,51.610241],"type":"Point"}
}