{
  "type": "Feature",
  "properties": {
    "iso:country":"NL",
    "sg:address":"Haagwinde 20",
    "sg:city":"Vught",
    "sg:orig_category":"Medische Installaties En Instrumenten",
    "sg:phone":"+31 73 657 6976",
    "sg:postcode":"5262 KZ",
    "sg:province":"Noord-Brabant",
    "wof:name":"Medical Consult Europe Bv",
    "wof:placetype":"venue"
},
  "geometry": {"coordinates":[5.271109,51.640617],"type":"Point"}
}