{
  "type": "Feature",
  "properties": {
    "addr:full":"Postbus 268 Doorn Utrecht 3940 AG",
    "addr:housenumber":"268",
    "addr:postcode":"3940",
    "addr:street":"Postbus",
    "iso:country":"NL",
    "sg:address":"Postbus 268",
    "sg:city":"Doorn",
    "sg:orig_category":"Adviesbureaus Bouwkunde",
    "sg:phone":"+31 343 416 486",
    "sg:postcode":"3940 AG",
    "sg:province":"Utrecht",
    "wof:name":"Junior",
    "wof:placetype":"venue"
},
  "geometry": {"coordinates":[5.34572,52.03336],"type":"Point"}
}