{
  "type": "Feature",
  "properties": {
    "addr:full":"Eekbrouwersweg 4A 'S Hertogenbosch Noord-Brabant 5233 VG",
    "addr:housenumber":"4a ' s",
    "addr:postcode":"5233 vg",
    "addr:street":"Eekbrouwersweg",
    "iso:country":"NL",
    "sg:address":"Eekbrouwersweg 4A",
    "sg:city":"'S Hertogenbosch",
    "sg:orig_category":"Kinderopvang Behalve Thuis",
    "sg:phone":"+31 73 640 0288",
    "sg:postcode":"5233 VG",
    "sg:province":"Noord-Brabant",
    "wof:name":"Kinderdagverblijf De Toverhoedt",
    "wof:placetype":"venue"
},
  "geometry": {"coordinates":[5.316677,51.709564],"type":"Point"}
}