{
  "type": "Feature",
  "properties": {
    "addr:full":"Straatwg 72 Maarssen Utrecht 3604 BC",
    "addr:housenumber":"72",
    "addr:postcode":"3604 bc",
    "addr:street":"Straatwg",
    "iso:country":"NL",
    "sg:address":"Straatwg 72",
    "sg:city":"Maarssen",
    "sg:orig_category":"Onderhoudswerken",
    "sg:phone":"+31 346 554 557",
    "sg:postcode":"3604 BC",
    "sg:province":"Utrecht",
    "wof:name":"Veilig Wonen",
    "wof:placetype":"venue"
},
  "geometry": {"coordinates":[5.04696,52.132481],"type":"Point"}
}