{
  "type": "Feature",
  "properties": {
    "addr:full":"Postbus 53 Huissen Gelderland 6850 AB",
    "addr:housenumber":"53",
    "addr:postcode":"6850 ab",
    "addr:street":"Postbus;Gelderland",
    "iso:country":"NL",
    "sg:address":"Postbus 53",
    "sg:city":"Huissen",
    "sg:orig_category":"Verpakkingen En Verpakkingsmaterialen",
    "sg:phone":"+31 26 325 0863",
    "sg:postcode":"6850 AB",
    "sg:province":"Gelderland",
    "sg:website":"http://www.snelbv.nl",
    "wof:name":"Snel Bv",
    "wof:placetype":"venue"
},
  "geometry": {"coordinates":[5.94138,51.937389],"type":"Point"}
}