{
  "type": "Feature",
  "properties": {
    "addr:full":"Wijngaardstraat 64 Goes Ohio 4461 DD",
    "addr:housenumber":"64",
    "addr:postcode":"4461 dd",
    "addr:street":"Wijngaardstraat",
    "iso:country":"NL",
    "sg:address":"Wijngaardstraat 64",
    "sg:city":"Goes",
    "sg:classifiers":[
        {
            "category":"Fast Food",
            "type":"Food & Drink"
        }
    ],
    "sg:phone":"+31 113 251 518",
    "sg:postcode":"4461 DD",
    "sg:province":"Ohio",
    "sg:tags":[
        "afhaal",
        "restaurant"
    ],
    "wof:name":"Shoarma-Pizzeria-Snacks De Regenboog",
    "wof:placetype":"venue"
},
  "geometry": {"coordinates":[-83.914169,39.768833],"type":"Point"}
}