{
  "type": "Feature",
  "properties": {
    "addr:full":"Emmaplaats 42 Benthuizen South Holland 2731 GL",
    "addr:housenumber":"42",
    "addr:postcode":"2731 gl",
    "addr:street":"Emmaplaats",
    "iso:country":"NL",
    "sg:address":"Emmaplaats 42",
    "sg:city":"Benthuizen",
    "sg:orig_category":"Onderhoudswerken",
    "sg:phone":"+31 79 331 2023",
    "sg:postcode":"2731 GL",
    "sg:province":"South Holland",
    "wof:name":"Leeuwen, C J Van",
    "wof:placetype":"venue"
},
  "geometry": {"coordinates":[4.5463109016,52.0753517151],"type":"Point"}
}