{
  "type": "Feature",
  "properties": {
    "addr:full":"Weesdk 36 Vianen Zh South Holland 4132 BL",
    "addr:housenumber":"36",
    "addr:postcode":"zh;4132 bl",
    "addr:street":"Weesdk",
    "iso:country":"NL",
    "sg:address":"Weesdk 36",
    "sg:city":"Vianen Zh",
    "sg:orig_category":"Orthopedagogen",
    "sg:phone":"+31 347 374 426",
    "sg:postcode":"4132 BL",
    "sg:province":"South Holland",
    "wof:name":"Pedagogische Praktijk Vianen",
    "wof:placetype":"venue"
},
  "geometry": {"coordinates":[5.0948519707,51.9936752319],"type":"Point"}
}