{
  "type": "Feature",
  "properties": {
    "addr:full":"Ijweg 1182 Hoofddorp Noord-Holland 2133 MH",
    "addr:housenumber":"1182",
    "addr:postcode":"2133 mh",
    "addr:street":"Ijweg",
    "iso:country":"NL",
    "sg:address":"Ijweg 1182",
    "sg:city":"Hoofddorp",
    "sg:orig_category":"Metaalafval, Schrootrecycling And Sloperijen",
    "sg:phone":"+31 23 564 0052",
    "sg:postcode":"2133 MH",
    "sg:province":"Noord-Holland",
    "wof:name":"J.M.C. Scharrenborg",
    "wof:placetype":"venue"
},
  "geometry": {"coordinates":[4.653956,52.306175],"type":"Point"}
}