{
  "type": "Feature",
  "properties": {
    "addr:full":"Kerkweg 81 Ter Aar Zuid-Holland 2461 GC",
    "addr:housenumber":"81",
    "addr:postcode":"aar;2461 gc",
    "addr:street":"Kerkweg;Ter",
    "iso:country":"NL",
    "sg:address":"Kerkweg 81",
    "sg:city":"Ter Aar",
    "sg:orig_category":"Bloemen And Planten",
    "sg:phone":"+31 172 603 627",
    "sg:postcode":"2461 GC",
    "sg:province":"Zuid-Holland",
    "wof:name":"Fa S.H. Schreuder & Zoon",
    "wof:placetype":"venue"
},
  "geometry": {"coordinates":[4.721422,52.166245],"type":"Point"}
}