{
  "type": "Feature",
  "properties": {
    "iso:country":"NL",
    "sg:address":"Viaductwg 38-40",
    "sg:city":"S Gravenhage",
    "sg:orig_category":"Verhuur",
    "sg:phone":"+31 70 399 7468",
    "sg:postcode":"2525 KL",
    "sg:province":"Zuid-Holland",
    "wof:name":"Roko, Verhuurbedrijf",
    "wof:placetype":"venue"
},
  "geometry": {"coordinates":[4.30248,52.062462],"type":"Point"}
}