{
  "type": "Feature",
  "properties": {
    "addr:full":"Zesweg 148 Wijchen Gelderland 6604 BP",
    "addr:housenumber":"148",
    "addr:postcode":"6604 bp",
    "addr:street":"Zesweg;Gelderland",
    "iso:country":"NL",
    "sg:address":"Zesweg 148",
    "sg:city":"Wijchen",
    "sg:orig_category":"Goederenvervoer Over De Weg",
    "sg:phone":"+31 24 645 0009",
    "sg:postcode":"6604 BP",
    "sg:province":"Gelderland",
    "wof:name":"Transportbedrijf Kokken",
    "wof:placetype":"venue"
},
  "geometry": {"coordinates":[5.73085,51.808395],"type":"Point"}
}