{
  "type": "Feature",
  "properties": {
    "addr:full":"Karel Du Jardinstraat 35 Amsterdam Noord-Holland 1072 SG",
    "addr:housenumber":"35",
    "addr:postcode":"1072 sg",
    "addr:street":"Karel Du Jardinstraat",
    "iso:country":"NL",
    "sg:address":"Karel Du Jardinstraat 35",
    "sg:city":"Amsterdam",
    "sg:orig_category":"Kinderopvang Behalve Thuis",
    "sg:phone":"+31 20 673 9112",
    "sg:postcode":"1072 SG",
    "sg:province":"Noord-Holland",
    "wof:name":"Kinderdagverblijf Pijp St Uk",
    "wof:placetype":"venue"
},
  "geometry": {"coordinates":[4.893973,52.351334],"type":"Point"}
}