{
  "type": "Feature",
  "properties": {
    "addr:full":"Nieuwe Holleweg 12 Beek Ubbergen Gelderland 6573 DX",
    "addr:housenumber":"12",
    "addr:postcode":"6573 dx",
    "addr:street":"Nieuwe Holleweg",
    "iso:country":"NL",
    "sg:address":"Nieuwe Holleweg 12",
    "sg:city":"Beek Ubbergen",
    "sg:orig_category":"Bejaardeninstellingen And Serviceflats",
    "sg:phone":"+31 24 684 7777",
    "sg:postcode":"6573 DX",
    "sg:province":"Gelderland",
    "wof:name":"Stichting Kalorama",
    "wof:placetype":"venue"
},
  "geometry": {"coordinates":[5.922559,51.826744],"type":"Point"}
}