{
  "type": "Feature",
  "properties": {
    "iso:country":"NL",
    "sg:address":"Adelborst Van Leeuwenln 21",
    "sg:city":"Sassenheim",
    "sg:orig_category":"Binnenhuisarchitecten",
    "sg:phone":"+31 252 221 654",
    "sg:postcode":"2172 AA",
    "sg:province":"Zuid-Holland",
    "wof:name":"De Toverstaf",
    "wof:placetype":"venue"
},
  "geometry": {"coordinates":[4.530308,52.226307],"type":"Point"}
}