{
  "type": "Feature",
  "properties": {
    "iso:country":"NL",
    "sg:address":"Transvaalkd 12A",
    "sg:city":"Leiden",
    "sg:orig_category":"Autorijscholen",
    "sg:phone":"+31 71 512 3625",
    "sg:postcode":"2312 ZE",
    "sg:province":"Zuid-Holland",
    "wof:name":"Jitan, A K",
    "wof:placetype":"venue"
},
  "geometry": {"coordinates":[4.478027,52.162876],"type":"Point"}
}