{
  "type": "Feature",
  "properties": {
    "iso:country":"NL",
    "sg:address":"Brahmsstr 9",
    "sg:city":"Twello",
    "sg:orig_category":"Administratie- En Boekhoudkantoren",
    "sg:phone":"+31 571 272 235",
    "sg:postcode":"7391 SR",
    "sg:province":"Gelderland",
    "wof:name":"Peppelenbos, A G",
    "wof:placetype":"venue"
},
  "geometry": {"coordinates":[6.102432,52.229095],"type":"Point"}
}