{
  "type": "Feature",
  "properties": {
    "addr:full":"Korenpad 8 Prinsenbeek North Brabant 4841 LB",
    "addr:housenumber":"8",
    "addr:postcode":"4841 lb",
    "addr:street":"Korenpad",
    "iso:country":"NL",
    "sg:address":"Korenpad 8",
    "sg:city":"Prinsenbeek",
    "sg:classifiers":[
        {
            "category":"Food & Beverages",
            "subcategory":"Fruits & Vegetables",
            "type":"Retail Goods"
        }
    ],
    "sg:phone":"+31 76 541 4674",
    "sg:postcode":"4841 LB",
    "sg:province":"North Brabant",
    "sg:tags":[
        "groenten"
    ],
    "wof:name":"A.A. Bezemer Bv",
    "wof:placetype":"venue"
},
  "geometry": {"coordinates":[4.683983,51.60321],"type":"Point"}
}