{
  "type": "Feature",
  "properties": {
    "addr:full":"Ruigenhil 86 Alblasserdam Zuid-Holland 2952 AR",
    "addr:housenumber":"86",
    "addr:postcode":"2952",
    "addr:street":"Ruigenhil",
    "iso:country":"NL",
    "sg:address":"Ruigenhil 86",
    "sg:city":"Alblasserdam",
    "sg:orig_category":"Huishoudelijk Textiel Fab",
    "sg:phone":"+31 78 691 2903",
    "sg:postcode":"2952 AR",
    "sg:province":"Zuid-Holland",
    "wof:name":"Labelle Bea",
    "wof:placetype":"venue"
},
  "geometry": {"coordinates":[4.660471,51.855045],"type":"Point"}
}