{
  "type": "Feature",
  "properties": {
    "addr:full":"Eexterwg 60 Gieten Drenthe 9461 BG",
    "addr:housenumber":"60",
    "addr:postcode":"9461",
    "addr:street":"Eexterwg",
    "iso:country":"NL",
    "sg:address":"Eexterwg 60",
    "sg:city":"Gieten",
    "sg:orig_category":"Adviesbureaus Bedrijfsorganisatie",
    "sg:phone":"+31 592 263 985",
    "sg:postcode":"9461 BG",
    "sg:province":"Drenthe",
    "sg:website":"http://www.worldview-consult.nl",
    "wof:name":"Worldview Bv",
    "wof:placetype":"venue"
},
  "geometry": {"coordinates":[6.753001,53.008015],"type":"Point"}
}