{
  "type": "Feature",
  "properties": {
    "iso:country":"NL",
    "sg:address":"Theetuin 3",
    "sg:city":"Oirschot",
    "sg:orig_category":"Lasbedrijven",
    "sg:phone":"+31 499 571 167",
    "sg:postcode":"5688 GE",
    "sg:province":"North Brabant",
    "wof:name":"Gerritsen, H",
    "wof:placetype":"venue"
},
  "geometry": {"coordinates":[5.308385,51.49577],"type":"Point"}
}