{
  "type": "Feature",
  "properties": {
    "addr:full":"Boulevard 51 Roosendaal North Brabant 4701 EP",
    "addr:housenumber":"51",
    "addr:postcode":"4701 ep",
    "addr:street":"Boulevard",
    "iso:country":"NL",
    "sg:address":"Boulevard 51",
    "sg:city":"Roosendaal",
    "sg:orig_category":"Adviesbureaus Bouwkosten",
    "sg:phone":"+31 165 559 129",
    "sg:postcode":"4701 EP",
    "sg:province":"North Brabant",
    "wof:name":"Winket Voor De Bouw/Ir Tim De Jonge",
    "wof:placetype":"venue"
},
  "geometry": {"coordinates":[4.466891,51.534176],"type":"Point"}
}