{
  "type": "Feature",
  "properties": {
    "addr:full":"Miranda 17 Ysselstein Ut Utrecht 3402 HG",
    "addr:housenumber":"17",
    "addr:postcode":"3402 hg",
    "addr:street":"Miranda",
    "iso:country":"NL",
    "sg:address":"Miranda 17",
    "sg:city":"Ysselstein Ut",
    "sg:orig_category":"Verenigingen En Stichtingen",
    "sg:phone":"+31 30 687 4804",
    "sg:postcode":"3402 HG",
    "sg:province":"Utrecht",
    "wof:name":"Sos",
    "wof:placetype":"venue"
},
  "geometry": {"coordinates":[5.045985,52.028446],"type":"Point"}
}