{
  "type": "Feature",
  "properties": {
    "iso:country":"NL",
    "sg:address":"Stationsdwarsweg 29",
    "sg:city":"Rijssen",
    "sg:classifiers":[
        {
            "category":"Fast Food",
            "type":"Food & Drink"
        }
    ],
    "sg:phone":"+31 548 513 277",
    "sg:postcode":"7461 AR",
    "sg:province":"NL.08",
    "sg:tags":[
        "afhaal",
        "restaurant"
    ],
    "wof:name":"Vof Brinkman",
    "wof:placetype":"venue"
},
  "geometry": {"coordinates":[6.523548,52.313152],"type":"Point"}
}