{
  "type": "Feature",
  "properties": {
    "addr:full":"Coriovallumstr 14 Heerlen Limburg 6411 CC",
    "addr:housenumber":"14",
    "addr:postcode":"6411 cc",
    "addr:street":"Coriovallumstr",
    "iso:country":"NL",
    "sg:address":"Coriovallumstr 14",
    "sg:city":"Heerlen",
    "sg:orig_category":"Kappers",
    "sg:phone":"+31 45 571 0574",
    "sg:postcode":"6411 CC",
    "sg:province":"Limburg",
    "wof:name":"John",
    "wof:placetype":"venue"
},
  "geometry": {"coordinates":[5.9772310257,50.8858833313],"type":"Point"}
}