{
  "type": "Feature",
  "properties": {
    "addr:full":"Antillenstraat 44 Amsterdam North Holland 1058 HC",
    "addr:housenumber":"44",
    "addr:postcode":"1058 hc",
    "addr:street":"Antillenstraat",
    "iso:country":"NL",
    "sg:address":"Antillenstraat 44",
    "sg:city":"Amsterdam",
    "sg:orig_category":"Vertaal- And Tolkenbureaus",
    "sg:phone":"+31 20 612 6636",
    "sg:postcode":"1058 HC",
    "sg:province":"North Holland",
    "wof:name":"Olsson-Driessen Mediaprodukties",
    "wof:placetype":"venue"
},
  "geometry": {"coordinates":[4.850199,52.359814],"type":"Point"}
}