{
  "type": "Feature",
  "properties": {
    "addr:full":"Sumatrastr 42 Amsterdam Noord-Holland 1094 NE",
    "addr:housenumber":"42",
    "addr:postcode":"1094 ne",
    "addr:street":"Sumatrastr",
    "iso:country":"NL",
    "sg:address":"Sumatrastr 42",
    "sg:city":"Amsterdam",
    "sg:classifiers":[
        {
            "category":"Food & Beverages",
            "subcategory":"Bakery",
            "type":"Retail Goods"
        }
    ],
    "sg:phone":"+31 20 665 1214",
    "sg:postcode":"1094 NE",
    "sg:province":"Noord-Holland",
    "sg:tags":[
        "brood",
        "en",
        "banket"
    ],
    "wof:name":"Oost, Van",
    "wof:placetype":"venue"
},
  "geometry": {"coordinates":[4.935376,52.363468],"type":"Point"}
}