{
  "type": "Feature",
  "properties": {
    "iso:country":"NL",
    "sg:address":"Plantage 14",
    "sg:city":"Oude Wetering",
    "sg:orig_category":"Land- En Tuinbouw - Mechanisatie",
    "sg:phone":"+31 71 331 9111",
    "sg:postcode":"2377 AH",
    "sg:province":"South Holland",
    "wof:name":"Heto Bv",
    "wof:placetype":"venue"
},
  "geometry": {"coordinates":[4.64746,52.207424],"type":"Point"}
}