{
  "type": "Feature",
  "properties": {
    "addr:full":"Musholm 166 Hoofddorp North Holland 2133 HW",
    "addr:housenumber":"166",
    "addr:postcode":"2133 hw",
    "addr:street":"Musholm",
    "iso:country":"NL",
    "sg:address":"Musholm 166",
    "sg:city":"Hoofddorp",
    "sg:orig_category":"Administratie- En Boekhoudkantoren",
    "sg:phone":"+31 23 565 8181",
    "sg:postcode":"2133 HW",
    "sg:province":"North Holland",
    "sg:website":"http://www.ambo.nu",
    "wof:name":"Ambo",
    "wof:placetype":"venue"
},
  "geometry": {"coordinates":[4.671541,52.31501],"type":"Point"}
}