{
  "type": "Feature",
  "properties": {
    "addr:full":"Galvanistr 40 Zoetermeer Zuid-Holland 2723 RV",
    "addr:housenumber":"40",
    "addr:postcode":"2723 rv",
    "addr:street":"Galvanistr",
    "iso:country":"NL",
    "sg:address":"Galvanistr 40",
    "sg:city":"Zoetermeer",
    "sg:orig_category":"Bestratingen",
    "sg:phone":"+31 79 341 3775",
    "sg:postcode":"2723 RV",
    "sg:province":"Zuid-Holland",
    "wof:name":"Leeuwen En Zn Bv, Van",
    "wof:placetype":"venue"
},
  "geometry": {"coordinates":[4.526578,52.057564],"type":"Point"}
}