{
  "type": "Feature",
  "properties": {
    "addr:full":"Industrieweg 10 Maarssen Utrecht 3606 AS",
    "addr:housenumber":"10",
    "addr:postcode":"3606 as",
    "addr:street":"Industrieweg",
    "iso:country":"NL",
    "sg:address":"Industrieweg 10",
    "sg:city":"Maarssen",
    "sg:orig_category":"Elektronische Bedrijfsinstallaties",
    "sg:phone":"+31 346 570 104",
    "sg:postcode":"3606 AS",
    "sg:province":"Utrecht",
    "wof:name":"Nedap Beveiligingstechniek Bv",
    "wof:placetype":"venue"
},
  "geometry": {"coordinates":[5.040473,52.128059],"type":"Point"}
}