{
  "type": "Feature",
  "properties": {
    "iso:country":"NL",
    "sg:address":"Singel 79",
    "sg:city":"Molenhoek Lb",
    "sg:orig_category":"Vertaalbureaus",
    "sg:phone":"+31 24 373 4660",
    "sg:postcode":"6584 BJ",
    "sg:province":"Limburg",
    "wof:name":"Pasquino-Smits, Drs M C J",
    "wof:placetype":"venue"
},
  "geometry": {"coordinates":[5.875693,51.773014],"type":"Point"}
}