{
  "type": "Feature",
  "properties": {
    "addr:full":"Tesselschadestraat 4-12 Amsterdam North Holland 1054 ET",
    "addr:housenumber":"4-12",
    "addr:postcode":"1054 et",
    "addr:street":"Tesselschadestraat",
    "iso:country":"NL",
    "sg:address":"Tesselschadestraat 4-12",
    "sg:city":"Amsterdam",
    "sg:orig_category":"Video - Faciliteiten En Producties",
    "sg:phone":"+31 20 689 5113",
    "sg:postcode":"1054 ET",
    "sg:province":"North Holland",
    "sg:website":"http://www.mediamachine.nl",
    "wof:name":"Mediamachine",
    "wof:placetype":"venue"
},
  "geometry": {"coordinates":[4.879409,52.362209],"type":"Point"}
}