{
  "type": "Feature",
  "properties": {
    "addr:full":"Koolweg 14 Ouddorp Zh Zuid-Holland 3253 LH",
    "addr:housenumber":"14",
    "addr:postcode":"3253 lh",
    "addr:street":"Koolweg",
    "iso:country":"NL",
    "sg:address":"Koolweg 14",
    "sg:city":"Ouddorp Zh",
    "sg:orig_category":"Watersport-, Sport- And Kampeerbenodigdheden Verhuur",
    "sg:phone":"+31 187 681 635",
    "sg:postcode":"3253 LH",
    "sg:province":"Zuid-Holland",
    "wof:name":"A Mierop",
    "wof:placetype":"venue"
},
  "geometry": {"coordinates":[3.9231300354,51.8202705383],"type":"Point"}
}