{
  "type": "Feature",
  "properties": {
    "iso:country":"NL",
    "sg:address":"Leusderwg 254",
    "sg:city":"Amersfoort",
    "sg:orig_category":"Kappers",
    "sg:phone":"+31 33 463 3868",
    "sg:postcode":"3817 KH",
    "sg:province":"Utrecht",
    "wof:name":"Margreet Coiffures",
    "wof:placetype":"venue"
},
  "geometry": {"coordinates":[5.378047,52.140285],"type":"Point"}
}