{
  "type": "Feature",
  "properties": {
    "addr:full":"Moleneind 24 Kortenhoef Noord-Holland 1241 NG",
    "addr:housenumber":"24",
    "addr:postcode":"1241 ng",
    "addr:street":"Moleneind",
    "iso:country":"NL",
    "sg:address":"Moleneind 24",
    "sg:city":"Kortenhoef",
    "sg:orig_category":"Jachthavens - Jachtwerven",
    "sg:phone":"+31 35 656 1871",
    "sg:postcode":"1241 NG",
    "sg:province":"Noord-Holland",
    "wof:name":"Bouwman Bv",
    "wof:placetype":"venue"
},
  "geometry": {"coordinates":[5.080105,52.22393],"type":"Point"}
}