{
  "type": "Feature",
  "properties": {
    "addr:full":"Middenwg 275 Heerhugowaard North Holland 1701 GD",
    "addr:housenumber":"275",
    "addr:postcode":"1701 gd",
    "iso:country":"NL",
    "sg:address":"Middenwg 275",
    "sg:city":"Heerhugowaard",
    "sg:orig_category":"Onderhoudswerken",
    "sg:phone":"+31 72 574 6203",
    "sg:postcode":"1701 GD",
    "sg:province":"North Holland",
    "wof:name":"Kobus West-Friesland",
    "wof:placetype":"venue"
},
  "geometry": {"coordinates":[4.827522,52.665195],"type":"Point"}
}