{
  "type": "Feature",
  "properties": {
    "addr:full":"Vroenhoutsewg 2B Roosendaal Noord-Brabant 4703 SJ",
    "addr:housenumber":"2b",
    "addr:postcode":"4703",
    "addr:street":"Vroenhoutsewg",
    "iso:country":"NL",
    "sg:address":"Vroenhoutsewg 2B",
    "sg:city":"Roosendaal",
    "sg:orig_category":"Offsetdrukkerijen",
    "sg:phone":"+31 164 674 313",
    "sg:postcode":"4703 SJ",
    "sg:province":"Noord-Brabant",
    "wof:name":"Beo V/H Janssen",
    "wof:placetype":"venue"
},
  "geometry": {"coordinates":[4.416558,51.533585],"type":"Point"}
}