{
  "type": "Feature",
  "properties": {
    "iso:country":"NL",
    "sg:address":"Minister Elandstraat 28",
    "sg:city":"Nijmegen",
    "sg:orig_category":"Kappers",
    "sg:phone":"+31 24 323 2989",
    "sg:postcode":"6523 CT",
    "sg:province":"Gelderland",
    "wof:name":"A Lodenstijn",
    "wof:placetype":"venue"
},
  "geometry": {"coordinates":[5.8810071945,51.8348083496],"type":"Point"}
}