{
  "type": "Feature",
  "properties": {
    "addr:full":"Nagelbeek 87 Schinnen Limburg 6365 EJ",
    "addr:housenumber":"87",
    "addr:postcode":"6365 ej",
    "addr:street":"Nagelbeek",
    "iso:country":"NL",
    "sg:address":"Nagelbeek 87",
    "sg:city":"Schinnen",
    "sg:classifiers":[
        {
            "category":"Home & Garden",
            "subcategory":"Garden Supply",
            "type":"Retail Goods"
        }
    ],
    "sg:phone":"+31 46 443 3882",
    "sg:postcode":"6365 EJ",
    "sg:province":"Limburg",
    "sg:tags":[
        "zand",
        "en",
        "grind"
    ],
    "wof:name":"Bruls Bv",
    "wof:placetype":"venue"
},
  "geometry": {"coordinates":[5.866576,50.933563],"type":"Point"}
}