{
  "type": "Feature",
  "properties": {
    "iso:country":"NL",
    "sg:address":"Kievit 61",
    "sg:city":"Sprang-Capelle",
    "sg:orig_category":"Metaalwerken",
    "sg:phone":"+31 416 281 260",
    "sg:postcode":"5161 WV",
    "sg:province":"Noord-Brabant",
    "wof:name":"J.A. Oversteeg",
    "wof:placetype":"venue"
},
  "geometry": {"coordinates":[5.019613,51.674141],"type":"Point"}
}