{
  "type": "Feature",
  "properties": {
    "addr:full":"Vismarkt 8 Utrecht Utrecht 3511 KR",
    "addr:housenumber":"8",
    "addr:postcode":"3511 kr",
    "addr:street":"Vismarkt",
    "iso:country":"NL",
    "sg:address":"Vismarkt 8",
    "sg:city":"Utrecht",
    "sg:orig_category":"Antiquiteiten",
    "sg:phone":"+31 30 231 3179",
    "sg:postcode":"3511 KR",
    "sg:province":"Utrecht",
    "wof:name":"Oud Holland",
    "wof:placetype":"venue"
},
  "geometry": {"coordinates":[5.120315,52.091251],"type":"Point"}
}