{
  "type": "Feature",
  "properties": {
    "addr:full":"Slotermeerlaan 7 Amsterdam North Holland 1064 GX",
    "addr:housenumber":"7",
    "addr:postcode":"1064 gx",
    "addr:street":"Slotermeerlaan",
    "iso:country":"NL",
    "sg:address":"Slotermeerlaan 7",
    "sg:city":"Amsterdam",
    "sg:orig_category":"Schoonheidssalons",
    "sg:phone":"+31 20 611 1133",
    "sg:postcode":"1064 GX",
    "sg:province":"North Holland",
    "wof:name":"Salon Slotermeerlaan",
    "wof:placetype":"venue"
},
  "geometry": {"coordinates":[4.8184,52.374825],"type":"Point"}
}