{
  "type": "Feature",
  "properties": {
    "addr:full":"Halle-Nijmanweg 9 Halle Gelderland 7025 EG",
    "addr:housenumber":"9",
    "addr:postcode":"7025 eg",
    "addr:street":"Halle-Nijmanweg;Gelderland",
    "iso:country":"NL",
    "sg:address":"Halle-Nijmanweg 9",
    "sg:city":"Halle",
    "sg:orig_category":"Autokeuringen",
    "sg:phone":"+31 314 631 206",
    "sg:postcode":"7025 EG",
    "sg:province":"Gelderland",
    "wof:name":"J M H Roelofs",
    "wof:placetype":"venue"
},
  "geometry": {"coordinates":[6.412155,51.983063],"type":"Point"}
}