{
  "type": "Feature",
  "properties": {
    "iso:country":"NL",
    "sg:address":"Paviljoensgr 76",
    "sg:city":"S Gravenhage",
    "sg:orig_category":"Grafisch Ontwerpers",
    "sg:phone":"+31 70 364 6504",
    "sg:postcode":"2512 BR",
    "sg:province":"Zuid-Holland",
    "wof:name":"Imp Webdesign",
    "wof:placetype":"venue"
},
  "geometry": {"coordinates":[4.30618,52.073212],"type":"Point"}
}