{
  "type": "Feature",
  "properties": {
    "addr:full":"Thorbeckeplein 43 Beuningen Gld Gelderland 6641 CB",
    "addr:housenumber":"43",
    "addr:postcode":"6641 cb",
    "addr:street":"Thorbeckeplein",
    "iso:country":"NL",
    "sg:address":"Thorbeckeplein 43",
    "sg:city":"Beuningen Gld",
    "sg:classifiers":[
        {
            "category":"Shopping",
            "subcategory":"Gifts & Souvenirs",
            "type":"Retail Goods"
        }
    ],
    "sg:phone":"+31 24 677 0657",
    "sg:postcode":"6641 CB",
    "sg:province":"Gelderland",
    "sg:tags":[
        "geschenken"
    ],
    "wof:name":"Wereldwinkel",
    "wof:placetype":"venue"
},
  "geometry": {"coordinates":[5.770766,51.860092],"type":"Point"}
}