{
  "type": "Feature",
  "properties": {
    "addr:full":"Populierln 1 Ryswyk Zh Zuid-Holland 2282 KX",
    "addr:housenumber":"1",
    "addr:postcode":"2282 kx",
    "addr:street":"Populierln",
    "iso:country":"NL",
    "sg:address":"Populierln 1",
    "sg:city":"Ryswyk Zh",
    "sg:orig_category":"Vuilnisafvoer",
    "sg:phone":"+31 70 303 0213",
    "sg:postcode":"2282 KX",
    "sg:province":"Zuid-Holland",
    "wof:name":"Avalex",
    "wof:placetype":"venue"
},
  "geometry": {"coordinates":[4.33694,52.056503],"type":"Point"}
}