{
  "type": "Feature",
  "properties": {
    "addr:full":"Middelkampsewg 34A Nieuwaal Gelderland 5313 BE",
    "addr:housenumber":"34a",
    "addr:postcode":"5313",
    "addr:street":"Middelkampsewg;Gelderland",
    "iso:country":"NL",
    "sg:address":"Middelkampsewg 34A",
    "sg:city":"Nieuwaal",
    "sg:orig_category":"Bloemen En Planten",
    "sg:phone":"+31 418 564 025",
    "sg:postcode":"5313 BE",
    "sg:province":"Gelderland",
    "wof:name":"Waalstroom Bv",
    "wof:placetype":"venue"
},
  "geometry": {"coordinates":[5.17758,51.809849],"type":"Point"}
}