{
  "type": "Feature",
  "properties": {
    "addr:full":"Ulftseweg 60 Silvolde Gelderland 7064 BE",
    "addr:housenumber":"60",
    "addr:postcode":"7064",
    "addr:street":"Ulftseweg;Gelderland",
    "iso:country":"NL",
    "sg:address":"Ulftseweg 60",
    "sg:city":"Silvolde",
    "sg:classifiers":[
        {
            "category":"Bakery",
            "type":"Food & Drink"
        }
    ],
    "sg:phone":"+31 315 340 630",
    "sg:postcode":"7064 BE",
    "sg:province":"Gelderland",
    "sg:tags":[
        "brood",
        "banket"
    ],
    "wof:name":"Jos De Bakker",
    "wof:placetype":"venue"
},
  "geometry": {"coordinates":[6.382898,51.907764],"type":"Point"}
}