{
  "type": "Feature",
  "properties": {
    "addr:full":"R Holstln 1235 Delft Zuid-Holland 2624 KS",
    "addr:housenumber":"1235",
    "addr:postcode":"delft;2624 ks",
    "iso:country":"NL",
    "sg:address":"R Holstln 1235",
    "sg:city":"Delft",
    "sg:orig_category":"Marktonderzoekbureaus",
    "sg:phone":"+31 15 261 7215",
    "sg:postcode":"2624 KS",
    "sg:province":"Zuid-Holland",
    "wof:name":"Fmo",
    "wof:placetype":"venue"
},
  "geometry": {"coordinates":[4.35634,51.995491],"type":"Point"}
}