{
  "type": "Feature",
  "properties": {
    "addr:full":"Wg Pln 456 Amsterdam North Holland 1054 SH",
    "addr:housenumber":"456",
    "addr:postcode":"1054 sh",
    "addr:street":"Wg Pln",
    "iso:country":"NL",
    "sg:address":"Wg Pln 456",
    "sg:city":"Amsterdam",
    "sg:orig_category":"Fotografie Reclame En Mode",
    "sg:phone":"+31 20 683 9192",
    "sg:postcode":"1054 SH",
    "sg:province":"North Holland",
    "sg:website":"http://www.vanemdeboas.nl",
    "wof:name":"Michael Van Emde Boas",
    "wof:placetype":"venue"
},
  "geometry": {"coordinates":[4.871499,52.364391],"type":"Point"}
}