{
  "type": "Feature",
  "properties": {
    "iso:country":"NL",
    "sg:address":"C V Rennesstr 8",
    "sg:city":"S Gravenhage",
    "sg:orig_category":"Bejaarden - Verzorgingstehuizen",
    "sg:phone":"+31 70 325 2220",
    "sg:postcode":"2551 GM",
    "sg:province":"South Holland",
    "sg:website":"http://www.wijndaelercentrum.nl",
    "wof:name":"Wijndaelercentrum",
    "wof:placetype":"venue"
},
  "geometry": {"coordinates":[4.23775,52.058601],"type":"Point"}
}