{
  "type": "Feature",
  "properties": {
    "addr:full":"O Bolwerk 7 Terneuzen Zeeland 4531 GP",
    "addr:housenumber":"7",
    "addr:postcode":"4531 gp",
    "addr:street":"Bolwerk",
    "iso:country":"NL",
    "sg:address":"O Bolwerk 7",
    "sg:city":"Terneuzen",
    "sg:classifiers":[
        {
            "category":"Professional",
            "subcategory":"Accounting & Tax Preparation",
            "type":"Services"
        }
    ],
    "sg:phone":"+31 115 618 300",
    "sg:postcode":"4531 GP",
    "sg:province":"Zeeland",
    "sg:tags":[
        "accountant",
        "en",
        "-kantoren",
        "register-"
    ],
    "wof:name":"Oostelijk Bolwerk, Acc Maatsch",
    "wof:placetype":"venue"
},
  "geometry": {"coordinates":[3.832233,51.337486],"type":"Point"}
}