{
  "type": "Feature",
  "properties": {
    "iso:country":"NL",
    "sg:address":"Marconistraat 80",
    "sg:city":"Rotterdam",
    "sg:orig_category":"Fruit And Groenten Gh",
    "sg:phone":"+31 10 221 1222",
    "sg:postcode":"3029 AK",
    "sg:province":"Zuid-Holland",
    "wof:name":"Nico De Jong Bv",
    "wof:placetype":"venue"
},
  "geometry": {"coordinates":[4.419809,51.912659],"type":"Point"}
}