{
  "type": "Feature",
  "properties": {
    "addr:full":"H Jacobszstr 6 Amsterdam North Holland 1075 PD",
    "addr:housenumber":"6",
    "addr:postcode":"1075 pd",
    "iso:country":"NL",
    "sg:address":"H Jacobszstr 6",
    "sg:city":"Amsterdam",
    "sg:orig_category":"Onderhoudswerken",
    "sg:phone":"+31 20 673 2737",
    "sg:postcode":"1075 PD",
    "sg:province":"North Holland",
    "wof:name":"Oosten, Hendrik Van",
    "wof:placetype":"venue"
},
  "geometry": {"coordinates":[4.859766,52.351986],"type":"Point"}
}