{
  "type": "Feature",
  "properties": {
    "addr:full":"Brabantplein 3 Breda Noord-Brabant 4817 LR",
    "addr:housenumber":"3",
    "addr:postcode":"4817 lr",
    "addr:street":"Brabantplein",
    "iso:country":"NL",
    "sg:address":"Brabantplein 3",
    "sg:city":"Breda",
    "sg:orig_category":"Opticiens",
    "sg:phone":"+31 76 514 9942",
    "sg:postcode":"4817 LR",
    "sg:province":"Noord-Brabant",
    "wof:name":"Optiek Chmielowski",
    "wof:placetype":"venue"
},
  "geometry": {"coordinates":[4.7987518311,51.5908126831],"type":"Point"}
}