{
  "type": "Feature",
  "properties": {
    "iso:country":"NL",
    "sg:address":"Brabantplein 3",
    "sg:city":"Breda",
    "sg:orig_category":"Opticiens",
    "sg:phone":"+31 76 514 9942",
    "sg:postcode":"4817 LR",
    "sg:province":"Noord-Brabant",
    "wof:name":"Optiek Chmielowski",
    "wof:placetype":"venue"
},
  "geometry": {"coordinates":[4.7987518311,51.5908126831],"type":"Point"}
}