{
  "type": "Feature",
  "properties": {
    "iso:country":"NL",
    "sg:address":"Rivieraplein 9",
    "sg:city":"Haarlem",
    "sg:classifiers":[
        {
            "category":"Fast Food",
            "type":"Food & Drink"
        }
    ],
    "sg:phone":"+31 23 545 2107",
    "sg:postcode":"2037 AS",
    "sg:province":"North Holland",
    "sg:tags":[
        "afhaal",
        "restaurant"
    ],
    "wof:name":"Mcdonald'S Restaurant Bv",
    "wof:placetype":"venue"
},
  "geometry": {"coordinates":[4.653604,52.357468],"type":"Point"}
}