{
  "type": "Feature",
  "properties": {
    "addr:full":"Barendijk 5 Groede Zeeland 4503 GT",
    "addr:housenumber":"5",
    "addr:postcode":"4503 gt",
    "addr:street":"Barendijk",
    "iso:country":"NL",
    "sg:address":"Barendijk 5",
    "sg:city":"Groede",
    "sg:orig_category":"Kampeerterreinen",
    "sg:phone":"+31 117 371 311",
    "sg:postcode":"4503 GT",
    "sg:province":"Zeeland",
    "wof:name":"De Bosduif",
    "wof:placetype":"venue"
},
  "geometry": {"coordinates":[3.4987659454,51.3690605164],"type":"Point"}
}