{
  "type": "Feature",
  "properties": {
    "addr:full":"Frans Schleidenstraat 2 Voerendaal Limburg 6367 SM",
    "addr:housenumber":"2",
    "addr:postcode":"6367 sm",
    "addr:street":"Frans Schleidenstraat",
    "iso:country":"NL",
    "sg:address":"Frans Schleidenstraat 2",
    "sg:city":"Voerendaal",
    "sg:orig_category":"Architecten",
    "sg:phone":"+31 45 575 3150",
    "sg:postcode":"6367 SM",
    "sg:province":"Limburg",
    "wof:name":"Ontwerpburo Kleijnen",
    "wof:placetype":"venue"
},
  "geometry": {"coordinates":[5.924105,50.877068],"type":"Point"}
}