{
  "type": "Feature",
  "properties": {
    "addr:full":"Margrietstraat 13 Wilnis Utrecht 3648 BC",
    "addr:housenumber":"13",
    "addr:postcode":"3648 bc",
    "addr:street":"Margrietstraat",
    "iso:country":"NL",
    "sg:address":"Margrietstraat 13",
    "sg:city":"Wilnis",
    "sg:orig_category":"Boekhouders",
    "sg:phone":"+31 297 281 955",
    "sg:postcode":"3648 BC",
    "sg:province":"Utrecht",
    "wof:name":"J.P. Van Der Horn - Kool",
    "wof:placetype":"venue"
},
  "geometry": {"coordinates":[4.89839,52.196098],"type":"Point"}
}