{
  "type": "Feature",
  "properties": {
    "addr:full":"Maasdk 16 Maasdyk Zuid-Holland 2676 AE",
    "addr:housenumber":"16",
    "addr:postcode":"2676 ae",
    "addr:street":"Maasdk",
    "iso:country":"NL",
    "sg:address":"Maasdk 16",
    "sg:city":"Maasdyk",
    "sg:orig_category":"Administratie- En Boekhoudkantoren",
    "sg:phone":"+31 174 521 999",
    "sg:postcode":"2676 AE",
    "sg:province":"Zuid-Holland",
    "wof:name":"Bakker, Marga",
    "wof:placetype":"venue"
},
  "geometry": {"coordinates":[4.207585,51.968201],"type":"Point"}
}