{
  "type": "Feature",
  "properties": {
    "addr:full":"Zuideinde 340 Amsterdam North Holland 1035 PP",
    "addr:housenumber":"340",
    "addr:postcode":"1035 pp",
    "addr:street":"Zuideinde",
    "iso:country":"NL",
    "sg:address":"Zuideinde 340",
    "sg:city":"Amsterdam",
    "sg:orig_category":"Diverse Consumentenartikelen Gh",
    "sg:phone":"+31 20 633 5099",
    "sg:postcode":"1035 PP",
    "sg:province":"North Holland",
    "wof:name":"Vof Ruhe",
    "wof:placetype":"venue"
},
  "geometry": {"coordinates":[4.892444,52.420303],"type":"Point"}
}