{
  "type": "Feature",
  "properties": {
    "iso:country":"NL",
    "sg:address":"Zuideinde 340",
    "sg:city":"Amsterdam",
    "sg:orig_category":"Diverse Consumentenartikelen Gh",
    "sg:phone":"+31 20 633 5099",
    "sg:postcode":"1035 PP",
    "sg:province":"North Holland",
    "wof:name":"Vof Ruhe",
    "wof:placetype":"venue"
},
  "geometry": {"coordinates":[4.892444,52.420303],"type":"Point"}
}