{
  "type": "Feature",
  "properties": {
    "addr:full":"Tsjaerderdyk 3 Wirdum Fr Friesland 9088 CB",
    "addr:housenumber":"3",
    "addr:postcode":"9088 cb",
    "addr:street":"Tsjaerderdyk",
    "iso:country":"NL",
    "sg:address":"Tsjaerderdyk 3",
    "sg:city":"Wirdum Fr",
    "sg:orig_category":"Goederenvervoer Over De Weg",
    "sg:phone":"+31 58 255 1385",
    "sg:postcode":"9088 CB",
    "sg:province":"Friesland",
    "wof:name":"Transportonderneming L. De Jong Bv",
    "wof:placetype":"venue"
},
  "geometry": {"coordinates":[5.80384,53.143406],"type":"Point"}
}