{
  "type": "Feature",
  "properties": {
    "addr:full":"2E Virulystr 1A Rotterdam Zuid-Holland 3022 ZM",
    "addr:housenumber":"1a",
    "addr:postcode":"3022 zm",
    "addr:street":"2E Virulystr",
    "iso:country":"NL",
    "sg:address":"2E Virulystr 1A",
    "sg:city":"Rotterdam",
    "sg:orig_category":"Webdesign Bureaus",
    "sg:phone":"+31 6 24710449",
    "sg:postcode":"3022 ZM",
    "sg:province":"Zuid-Holland",
    "sg:website":"http://home.wxs.nl/~ouden053/",
    "wof:name":"Triple Drop Prod",
    "wof:placetype":"venue"
},
  "geometry": {"coordinates":[4.4504289627,51.9194221497],"type":"Point"}
}