{
  "type": "Feature",
  "properties": {
    "addr:full":"Korne 117 Rotterdam Zuid-Holland 3068 GN",
    "addr:housenumber":"117",
    "addr:postcode":"3068 gn",
    "addr:street":"Korne",
    "iso:country":"NL",
    "sg:address":"Korne 117",
    "sg:city":"Rotterdam",
    "sg:orig_category":"Loopbaanbegeleiding",
    "sg:phone":"+31 10 455 5262",
    "sg:postcode":"3068 GN",
    "sg:province":"Zuid-Holland",
    "wof:name":"Ls & M",
    "wof:placetype":"venue"
},
  "geometry": {"coordinates":[4.570217,51.961273],"type":"Point"}
}