{
  "type": "Feature",
  "properties": {
    "addr:full":"Ansfridusln 30 Leusden Utrecht 3833 BJ",
    "addr:housenumber":"30",
    "addr:postcode":"3833 bj",
    "addr:street":"Ansfridusln",
    "iso:country":"NL",
    "sg:address":"Ansfridusln 30",
    "sg:city":"Leusden",
    "sg:orig_category":"Webdesign Bureaus",
    "sg:phone":"+31 33 432 4902",
    "sg:postcode":"3833 BJ",
    "sg:province":"Utrecht",
    "sg:website":"http://www.vdweb.nl",
    "wof:name":"Vdwd",
    "wof:placetype":"venue"
},
  "geometry": {"coordinates":[5.4254097939,52.1352500916],"type":"Point"}
}