{
  "type": "Feature",
  "properties": {
    "addr:full":"Ambachtsweg 26 Pijnacker Zuid-Holland 2641 KS",
    "addr:housenumber":"26",
    "addr:postcode":"2641 ks",
    "addr:street":"Ambachtsweg",
    "iso:country":"NL",
    "sg:address":"Ambachtsweg 26",
    "sg:city":"Pijnacker",
    "sg:orig_category":"Goederenvervoer Over De Weg",
    "sg:phone":"+31 15 369 2497",
    "sg:postcode":"2641 KS",
    "sg:province":"Zuid-Holland",
    "wof:name":"Transportbedrijf L.C. Van Buytene & Zoon Bv",
    "wof:placetype":"venue"
},
  "geometry": {"coordinates":[4.441472,52.027683],"type":"Point"}
}