{
  "type": "Feature",
  "properties": {
    "addr:full":"Soesterweg 12 Amersfoort Utrecht 3812 BA",
    "addr:housenumber":"12",
    "addr:postcode":"3812 ba",
    "addr:street":"Soesterweg",
    "iso:country":"NL",
    "sg:address":"Soesterweg 12",
    "sg:city":"Amersfoort",
    "sg:orig_category":"Huisdierenfokkers",
    "sg:phone":"+31 33465151",
    "sg:postcode":"3812 BA",
    "sg:province":"Utrecht",
    "wof:name":"Dobermannworld",
    "wof:placetype":"venue"
},
  "geometry": {"coordinates":[5.374956,52.155304],"type":"Point"}
}