{
  "type": "Feature",
  "properties": {
    "addr:full":"Van Groeneveltlaan 11 Wassenaar Zuid-Holland 2241 LH",
    "addr:housenumber":"11",
    "addr:postcode":"2241 lh",
    "addr:street":"Van Groeneveltlaan",
    "iso:country":"NL",
    "sg:address":"Van Groeneveltlaan 11",
    "sg:city":"Wassenaar",
    "sg:orig_category":"Verzekeringen",
    "sg:phone":"+31 70 511 4148",
    "sg:postcode":"2241 LH",
    "sg:province":"Zuid-Holland",
    "wof:name":"Ass Kant Menning",
    "wof:placetype":"venue"
},
  "geometry": {"coordinates":[4.405235,52.146332],"type":"Point"}
}