{
  "type": "Feature",
  "properties": {
    "addr:full":"Witmakersstr 25C Maastricht Limburg 6211 JA",
    "addr:housenumber":"25c",
    "addr:postcode":"6211 ja",
    "addr:street":"Witmakersstr",
    "iso:country":"NL",
    "sg:address":"Witmakersstr 25C",
    "sg:city":"Maastricht",
    "sg:orig_category":"Organisatiebureaus",
    "sg:phone":"+31 43 351 0180",
    "sg:postcode":"6211 JA",
    "sg:province":"Limburg",
    "wof:name":"Maastricht Destination Management",
    "wof:placetype":"venue"
},
  "geometry": {"coordinates":[5.6907219887,50.8465385437],"type":"Point"}
}