{
  "type": "Feature",
  "properties": {
    "iso:country":"NL",
    "sg:address":"Heemskerkstr 15",
    "sg:city":"Erica",
    "sg:orig_category":"Schoonheidsinstituten",
    "sg:phone":"+31 591 303 703",
    "sg:postcode":"7887 AA",
    "sg:province":"Drenthe",
    "wof:name":"Jade Huid- En Voetverzorging",
    "wof:placetype":"venue"
},
  "geometry": {"coordinates":[6.924472,52.71104],"type":"Point"}
}