{
  "type": "Feature",
  "properties": {
    "iso:country":"NL",
    "sg:address":"Munt 201",
    "sg:city":"Heerenveen",
    "sg:orig_category":"Fotografie Reclame En Mode",
    "sg:phone":"+31 513 651 116",
    "sg:postcode":"8446 AT",
    "sg:province":"Provincie Friesland",
    "wof:name":"Das",
    "wof:placetype":"venue"
},
  "geometry": {"coordinates":[5.919262,52.955692],"type":"Point"}
}