{
  "type": "Feature",
  "properties": {
    "addr:full":"Raadhuisplein 26 Nieuwerkerk Ad Ijssel South Holland 2914 KM",
    "addr:housenumber":"26",
    "addr:postcode":"2914 km",
    "addr:street":"Raadhuisplein;Ijssel",
    "iso:country":"NL",
    "sg:address":"Raadhuisplein 26",
    "sg:city":"Nieuwerkerk Ad Ijssel",
    "sg:orig_category":"Boekhouders",
    "sg:phone":"+31 180 319 925",
    "sg:postcode":"2914 KM",
    "sg:province":"South Holland",
    "wof:name":"Carinac Administratie",
    "wof:placetype":"venue"
},
  "geometry": {"coordinates":[4.617012,51.966881],"type":"Point"}
}