{
  "type": "Feature",
  "properties": {
    "addr:full":"Beatrixplein 4 Urmond Limburg 6129 BE",
    "addr:housenumber":"4",
    "addr:postcode":"6129",
    "addr:street":"Beatrixplein",
    "iso:country":"NL",
    "sg:address":"Beatrixplein 4",
    "sg:city":"Urmond",
    "sg:orig_category":"Kappers",
    "sg:phone":"+31 46 433 9926",
    "sg:postcode":"6129 BE",
    "sg:province":"Limburg",
    "wof:name":"West Hairshop - Andre Webers",
    "wof:placetype":"venue"
},
  "geometry": {"coordinates":[5.770804,51.004841],"type":"Point"}
}