{
  "type": "Feature",
  "properties": {
    "addr:full":"Marconistraat 52 Rotterdam Zuid-Holland 3029 AK",
    "addr:housenumber":"52",
    "addr:postcode":"3029 ak",
    "addr:street":"Marconistraat",
    "iso:country":"NL",
    "sg:address":"Marconistraat 52",
    "sg:city":"Rotterdam",
    "sg:orig_category":"Diverse Grafische Activiteiten",
    "sg:phone":"+31 10 476 5811",
    "sg:postcode":"3029 AK",
    "sg:province":"Zuid-Holland",
    "wof:name":"D. Van Steenbergen",
    "wof:placetype":"venue"
},
  "geometry": {"coordinates":[4.422501,51.912457],"type":"Point"}
}