{
  "type": "Feature",
  "properties": {
    "addr:full":"Heymansstr 63 Venlo Limburg 5927 NP",
    "addr:housenumber":"63",
    "addr:postcode":"5927 np",
    "addr:street":"Heymansstr",
    "iso:country":"NL",
    "sg:address":"Heymansstr 63",
    "sg:city":"Venlo",
    "sg:classifiers":[
        {
            "category":"Sports & Exercise",
            "subcategory":"Stables",
            "type":"Entertainment"
        }
    ],
    "sg:phone":"+31 77 382 6464",
    "sg:postcode":"5927 NP",
    "sg:province":"Limburg",
    "sg:tags":[
        "maneges"
    ],
    "wof:name":"Beekshof",
    "wof:placetype":"venue"
},
  "geometry": {"coordinates":[6.122108,51.368305],"type":"Point"}
}