{
  "type": "Feature",
  "properties": {
    "addr:full":"Uithoornstr 22B Amsterdam Noord-Holland 1078 SZ",
    "addr:housenumber":"22b",
    "addr:postcode":"1078 sz",
    "addr:street":"Uithoornstr",
    "iso:country":"NL",
    "sg:address":"Uithoornstr 22B",
    "sg:city":"Amsterdam",
    "sg:orig_category":"Beeldende Kunstenaars",
    "sg:phone":"+31 20 618 5299",
    "sg:postcode":"1078 SZ",
    "sg:province":"Noord-Holland",
    "wof:name":"Mmcr",
    "wof:placetype":"venue"
},
  "geometry": {"coordinates":[4.909113,52.347435],"type":"Point"}
}