{
  "type": "Feature",
  "properties": {
    "iso:country":"NL",
    "sg:address":"Rossenbergln 14",
    "sg:city":"Leusden",
    "sg:orig_category":"Boekhandels",
    "sg:phone":"+31 33 432 4452",
    "sg:postcode":"3833 BN",
    "sg:province":"Utrecht",
    "sg:website":"http://www.readingpen.nl",
    "wof:name":"Lexima Bv",
    "wof:placetype":"venue"
},
  "geometry": {"coordinates":[5.422675,52.132851],"type":"Point"}
}