{
  "type": "Feature",
  "properties": {
    "iso:country":"NL",
    "sg:address":"Develstein 100D",
    "sg:city":"Amsterdam Zuidoost",
    "sg:orig_category":"Kunstgebitten",
    "sg:phone":"+31 20 699 7609",
    "sg:postcode":"1102 AK",
    "sg:province":"North Holland",
    "wof:name":"Ghogli",
    "wof:placetype":"venue"
},
  "geometry": {"coordinates":[4.956152,52.323147],"type":"Point"}
}