{
  "type": "Feature",
  "properties": {
    "iso:country":"NL",
    "sg:address":"Veerseweg 44",
    "sg:city":"Oosterhout Nb",
    "sg:orig_category":"Begrafenisondernemers",
    "sg:phone":"+31 162 457 775",
    "sg:postcode":"4901 ZE",
    "sg:province":"Noord-Brabant",
    "wof:name":"Begrafenis- En Crematie Ondern Bruijns Bv",
    "wof:placetype":"venue"
},
  "geometry": {"coordinates":[4.85625,51.643051],"type":"Point"}
}