{
  "type": "Feature",
  "properties": {
    "addr:full":"Kerkstraat 49 Nederweert Limburg 6031 CG",
    "addr:housenumber":"49",
    "addr:postcode":"6031 cg",
    "addr:street":"Kerkstraat",
    "iso:country":"NL",
    "sg:address":"Kerkstraat 49",
    "sg:city":"Nederweert",
    "sg:orig_category":"Wasserettes And Stomerijen",
    "sg:phone":"+31 495 632 256",
    "sg:postcode":"6031 CG",
    "sg:province":"Limburg",
    "wof:name":"Stomerij Polkamp",
    "wof:placetype":"venue"
},
  "geometry": {"coordinates":[5.7461352348,51.2874298096],"type":"Point"}
}