{
  "type": "Feature",
  "properties": {
    "addr:full":"Baarsjeswg 202 Amsterdam Noord-Holland 1057 HS",
    "addr:housenumber":"202",
    "addr:postcode":"1057 hs",
    "iso:country":"NL",
    "sg:address":"Baarsjeswg 202",
    "sg:city":"Amsterdam",
    "sg:orig_category":"Automaterialen En Gereedschappen",
    "sg:phone":"+31 20 689 3459",
    "sg:postcode":"1057 HS",
    "sg:province":"Noord-Holland",
    "wof:name":"Guijt",
    "wof:placetype":"venue"
},
  "geometry": {"coordinates":[4.860527,52.365879],"type":"Point"}
}