{
  "type": "Feature",
  "properties": {
    "addr:full":"Bloemstraat 13 Arnhem Gelderland 6828 BH",
    "addr:housenumber":"13",
    "addr:postcode":"6828 bh",
    "addr:street":"Bloemstraat",
    "iso:country":"NL",
    "sg:address":"Bloemstraat 13",
    "sg:city":"Arnhem",
    "sg:orig_category":"Juweliers",
    "sg:phone":"+31 26 443 9840",
    "sg:postcode":"6828 BH",
    "sg:province":"Gelderland",
    "wof:name":"Ajay",
    "wof:placetype":"venue"
},
  "geometry": {"coordinates":[5.915596,51.984711],"type":"Point"}
}