{
  "type": "Feature",
  "properties": {
    "addr:full":"Bijenkorf 62 Eerbeek Gelderland 6961 PB",
    "addr:housenumber":"62",
    "addr:postcode":"6961 pb",
    "addr:street":"Bijenkorf;Gelderland",
    "iso:country":"NL",
    "sg:address":"Bijenkorf 62",
    "sg:city":"Eerbeek",
    "sg:orig_category":"Parfum And Cosmetica Gh",
    "sg:phone":"+31 313 654 543",
    "sg:postcode":"6961 PB",
    "sg:province":"Gelderland",
    "wof:name":"Ropadent",
    "wof:placetype":"venue"
},
  "geometry": {"coordinates":[6.047307,52.111984],"type":"Point"}
}