{
  "type": "Feature",
  "properties": {
    "addr:full":"Azurietdk 27 Roosendaal Noord-Brabant 4706 BL",
    "addr:housenumber":"27",
    "addr:postcode":"4706 bl",
    "addr:street":"Azurietdk",
    "iso:country":"NL",
    "sg:address":"Azurietdk 27",
    "sg:city":"Roosendaal",
    "sg:orig_category":"Lichtkranten En Scoreborden",
    "sg:phone":"+31 165 567 113",
    "sg:postcode":"4706 BL",
    "sg:province":"Noord-Brabant",
    "wof:name":"U-Plan",
    "wof:placetype":"venue"
},
  "geometry": {"coordinates":[4.486707,51.523827],"type":"Point"}
}