{
  "type": "Feature",
  "properties": {
    "iso:country":"NL",
    "sg:address":"Koelhuisstraat 9",
    "sg:city":"Huissen",
    "sg:orig_category":"Glaszetten",
    "sg:phone":"+31 26 325 5012",
    "sg:postcode":"6851 NB",
    "sg:province":"Gelderland",
    "wof:name":"Glas In Lood Sietsma",
    "wof:placetype":"venue"
},
  "geometry": {"coordinates":[5.935533,51.931835],"type":"Point"}
}