{
  "type": "Feature",
  "properties": {
    "addr:full":"Binnenweg 131 Heemstede Noord-Holland 2101 JE",
    "addr:housenumber":"131",
    "addr:postcode":"2101 je",
    "addr:street":"Binnenweg",
    "iso:country":"NL",
    "sg:address":"Binnenweg 131",
    "sg:city":"Heemstede",
    "sg:classifiers":[
        {
            "category":"Fast Food",
            "type":"Food & Drink"
        }
    ],
    "sg:phone":"+31 23 528 0592",
    "sg:postcode":"2101 JE",
    "sg:province":"Noord-Holland",
    "sg:tags":[
        "afhaal",
        "restaurant"
    ],
    "wof:name":"Snackbar Victoria",
    "wof:placetype":"venue"
},
  "geometry": {"coordinates":[4.620706,52.354694],"type":"Point"}
}