{
  "type": "Feature",
  "properties": {
    "iso:country":"NL",
    "sg:address":"Katendrechtse Lagedijk 229B",
    "sg:city":"Rotterdam",
    "sg:orig_category":"Geluidsinstallaties",
    "sg:phone":"+31 10 481 3045",
    "sg:postcode":"3083 GC",
    "sg:province":"Zuid-Holland",
    "wof:name":"Top Audio",
    "wof:placetype":"venue"
},
  "geometry": {"coordinates":[4.478684,51.890911],"type":"Point"}
}