{
  "type": "Feature",
  "properties": {
    "iso:country":"NL",
    "sg:address":"Legmeerdijk 204",
    "sg:city":"Amstelveen",
    "sg:orig_category":"Bloemen And Planten",
    "sg:phone":"+31 20 645 6671",
    "sg:postcode":"1187 NK",
    "sg:province":"North Holland",
    "wof:name":"Firma Olijerhoek En Zonen",
    "wof:placetype":"venue"
},
  "geometry": {"coordinates":[4.807955,52.273876],"type":"Point"}
}