{
  "type": "Feature",
  "properties": {
    "addr:full":"Dorpsstraat 38 Nunspeet Gelderland 8071 BZ",
    "addr:housenumber":"38",
    "addr:postcode":"8071 bz",
    "addr:street":"Dorpsstraat;Gelderland",
    "iso:country":"NL",
    "sg:address":"Dorpsstraat 38",
    "sg:city":"Nunspeet",
    "sg:orig_category":"Banken And Kredietinstellingen",
    "sg:phone":"+31 341 271 211",
    "sg:postcode":"8071 BZ",
    "sg:province":"Gelderland",
    "wof:name":"Rabobank",
    "wof:placetype":"venue"
},
  "geometry": {"coordinates":[5.783626,52.376156],"type":"Point"}
}