{
  "type": "Feature",
  "properties": {
    "addr:full":"Schouwtjeslaan 12 Haarlem Noord-Holland 2012 KH",
    "addr:housenumber":"12",
    "addr:postcode":"2012 kh",
    "addr:street":"Schouwtjeslaan",
    "iso:country":"NL",
    "sg:address":"Schouwtjeslaan 12",
    "sg:city":"Haarlem",
    "sg:orig_category":"Autokeuringen",
    "sg:phone":"+31 23 532 1882",
    "sg:postcode":"2012 KH",
    "sg:province":"Noord-Holland",
    "wof:name":"Special Car Service",
    "wof:placetype":"venue"
},
  "geometry": {"coordinates":[4.622531,52.370911],"type":"Point"}
}