{
  "type": "Feature",
  "properties": {
    "addr:full":"Van Hogendorpstraat 3 Breda Noord-Brabant 4812 JA",
    "addr:housenumber":"3",
    "addr:postcode":"4812 ja",
    "addr:street":"Van Hogendorpstraat",
    "iso:country":"NL",
    "sg:address":"Van Hogendorpstraat 3",
    "sg:city":"Breda",
    "sg:orig_category":"Kinderopvang Behalve Thuis",
    "sg:phone":"+31 76 522 7868",
    "sg:postcode":"4812 JA",
    "sg:province":"Noord-Brabant",
    "wof:name":"Nijntje Kinderdagverblijf",
    "wof:placetype":"venue"
},
  "geometry": {"coordinates":[4.749121,51.575069],"type":"Point"}
}