{
  "type": "Feature",
  "properties": {
    "addr:full":"Rietlandenstr 21 Emmen Drenthe 7825 TS",
    "addr:housenumber":"21",
    "addr:postcode":"7825 ts",
    "addr:street":"Rietlandenstr",
    "iso:country":"NL",
    "sg:address":"Rietlandenstr 21",
    "sg:city":"Emmen",
    "sg:orig_category":"Kappers",
    "sg:phone":"+31 591 631 326",
    "sg:postcode":"7825 TS",
    "sg:province":"Drenthe",
    "wof:name":"Rijan",
    "wof:placetype":"venue"
},
  "geometry": {"coordinates":[6.899621,52.754272],"type":"Point"}
}