{
  "type": "Feature",
  "properties": {
    "addr:full":"Kl Leeuw 45 Amstelveen Noord-Holland 1188 AK",
    "addr:housenumber":"45",
    "addr:postcode":"1188 ak",
    "addr:street":"Leeuw",
    "iso:country":"NL",
    "sg:address":"Kl Leeuw 45",
    "sg:city":"Amstelveen",
    "sg:orig_category":"Verenigingen En Stichtingen",
    "sg:phone":"+31 20 647 5332",
    "sg:postcode":"1188 AK",
    "sg:province":"Noord-Holland",
    "wof:name":"Comit\u00e9 Gemeentehulp Israel, Sticht",
    "wof:placetype":"venue"
},
  "geometry": {"coordinates":[4.85639,52.282009],"type":"Point"}
}