{
  "type": "Feature",
  "properties": {
    "iso:country":"NL",
    "sg:address":"De Schans 1922",
    "sg:city":"Lelystad",
    "sg:orig_category":"Schoonheidsinstituten",
    "sg:phone":"+31 320 231 535",
    "sg:postcode":"8231 KM",
    "sg:province":"Flevoland",
    "wof:name":"Evita, Beauty & Nailstudio",
    "wof:placetype":"venue"
},
  "geometry": {"coordinates":[5.47327,52.517052],"type":"Point"}
}