{
  "type": "Feature",
  "properties": {
    "addr:full":"Arnhemsewg 19 Apeldoorn Gelderland 7331 BA",
    "addr:housenumber":"19",
    "addr:postcode":"7331 ba",
    "addr:street":"Arnhemsewg;Gelderland",
    "iso:country":"NL",
    "sg:address":"Arnhemsewg 19",
    "sg:city":"Apeldoorn",
    "sg:orig_category":"Artsen - Huisartsen",
    "sg:phone":"+31 55 533 4369",
    "sg:postcode":"7331 BA",
    "sg:province":"Gelderland",
    "sg:website":"http://www.vaningen-breugem.praktijkinfo.nl",
    "wof:name":"Ingen & J A Breugem, R D Van",
    "wof:placetype":"venue"
},
  "geometry": {"coordinates":[5.9649,52.207535],"type":"Point"}
}