{
  "type": "Feature",
  "properties": {
    "addr:full":"Lierenbout 6 Boxtel Noord-Brabant 5283 AT",
    "addr:housenumber":"6",
    "addr:postcode":"5283",
    "addr:street":"Lierenbout",
    "iso:country":"NL",
    "sg:address":"Lierenbout 6",
    "sg:city":"Boxtel",
    "sg:orig_category":"Sanitaire Artikelen - Fabrieken En Groothandel",
    "sg:phone":"+31 411 611 812",
    "sg:postcode":"5283 AT",
    "sg:province":"Noord-Brabant",
    "sg:website":"http://www.vincomy.nl",
    "wof:name":"Vincomy",
    "wof:placetype":"venue"
},
  "geometry": {"coordinates":[5.344269,51.59111],"type":"Point"}
}