{
  "type": "Feature",
  "properties": {
    "addr:full":"Pallasstraat 24 Tilburg Noord-Brabant 5048 CJ",
    "addr:housenumber":"24",
    "addr:postcode":"5048 cj",
    "addr:street":"Pallasstraat",
    "iso:country":"NL",
    "sg:address":"Pallasstraat 24",
    "sg:city":"Tilburg",
    "sg:orig_category":"Hout Gh",
    "sg:phone":"+31 13 572 1200",
    "sg:postcode":"5048 CJ",
    "sg:province":"Noord-Brabant",
    "wof:name":"Taurus Sales",
    "wof:placetype":"venue"
},
  "geometry": {"coordinates":[5.029775,51.593533],"type":"Point"}
}