{
  "type": "Feature",
  "properties": {
    "addr:full":"Lijnakker 32 Oosterwolde Fr Friesland 8431 PK",
    "addr:housenumber":"32",
    "addr:postcode":"8431 pk",
    "addr:street":"Lijnakker",
    "iso:country":"NL",
    "sg:address":"Lijnakker 32",
    "sg:city":"Oosterwolde Fr",
    "sg:orig_category":"Begrafenisondernemers",
    "sg:phone":"+31 516 512 729",
    "sg:postcode":"8431 PK",
    "sg:province":"Friesland",
    "wof:name":"Uitvaartvereniging De Laatste Eer",
    "wof:placetype":"venue"
},
  "geometry": {"coordinates":[6.285061,52.993488],"type":"Point"}
}