{
  "type": "Feature",
  "properties": {
    "addr:full":"Wingerdstraat 44 'S Gravenhage Zuid-Holland 2565 VC",
    "addr:housenumber":"44",
    "addr:postcode":"2565 vc",
    "addr:street":"Wingerdstraat;' S",
    "iso:country":"NL",
    "sg:address":"Wingerdstraat 44",
    "sg:city":"'S Gravenhage",
    "sg:orig_category":"Metaalwerken",
    "sg:phone":"+31 70 363 2242",
    "sg:postcode":"2565 VC",
    "sg:province":"Zuid-Holland",
    "wof:name":"A J Pronk",
    "wof:placetype":"venue"
},
  "geometry": {"coordinates":[4.260588,52.074192],"type":"Point"}
}