{
  "type": "Feature",
  "properties": {
    "iso:country":"NL",
    "sg:address":"Weikesstraat 6",
    "sg:city":"Alem",
    "sg:orig_category":"Boekhouders",
    "sg:phone":"+31 418 661 395",
    "sg:postcode":"5335 LE",
    "sg:province":"Texas",
    "wof:name":"Administratiekantoor Alem",
    "wof:placetype":"venue"
},
  "geometry": {"coordinates":[-98.04480700000001,31.634657],"type":"Point"}
}