{
  "type": "Feature",
  "properties": {
    "addr:full":"Pr Margrietstr 9 Bunnik Utrecht 3981 BE",
    "addr:housenumber":"9",
    "addr:postcode":"3981",
    "iso:country":"NL",
    "sg:address":"Pr Margrietstr 9",
    "sg:city":"Bunnik",
    "sg:orig_category":"Wegenbouw - Materieel",
    "sg:phone":"+31 30 656 1561",
    "sg:postcode":"3981 BE",
    "sg:province":"Utrecht",
    "wof:name":"Sky",
    "wof:placetype":"venue"
},
  "geometry": {"coordinates":[5.2061080933,52.0673141479],"type":"Point"}
}