{
  "type": "Feature",
  "properties": {
    "iso:country":"NL",
    "sg:address":"Coldenhovenseweg 59",
    "sg:city":"Eerbeek",
    "sg:orig_category":"Kappers",
    "sg:phone":"+31 313 651 004",
    "sg:postcode":"6961 EB",
    "sg:province":"Gelderland",
    "wof:name":"H.P. Van Schoonhoven",
    "wof:placetype":"venue"
},
  "geometry": {"coordinates":[6.0636048317,52.1003646851],"type":"Point"}
}