{
  "type": "Feature",
  "properties": {
    "iso:country":"NL",
    "sg:address":"Schieweg 189A",
    "sg:city":"Rotterdam",
    "sg:orig_category":"Juridische Dienstverlening",
    "sg:phone":"+31 10 467 3271",
    "sg:postcode":"3038 AS",
    "sg:province":"Zuid-Holland",
    "wof:name":"Rechtskundig Bur Mr V J P De Waal",
    "wof:placetype":"venue"
},
  "geometry": {"coordinates":[4.464437,51.93549],"type":"Point"}
}