{
  "type": "Feature",
  "properties": {
    "addr:full":"Prinses Margrietstraat 2 Koudekerk A/D Rijn Zuid-Holland 2396 XD",
    "addr:housenumber":"2;a / d",
    "addr:postcode":"2396 xd",
    "addr:street":"Prinses Margrietstraat",
    "iso:country":"NL",
    "sg:address":"Prinses Margrietstraat 2",
    "sg:city":"Koudekerk A/D Rijn",
    "sg:classifiers":[
        {
            "category":"Education",
            "subcategory":"Preschool",
            "type":"Public Place"
        }
    ],
    "sg:phone":"+31 71 341 2836",
    "sg:postcode":"2396 XD",
    "sg:province":"Zuid-Holland",
    "sg:tags":[
        "kleuteronderwijs",
        "basis-"
    ],
    "wof:name":"Openbare Basisschool De Rijnschans",
    "wof:placetype":"venue"
},
  "geometry": {"coordinates":[4.599796,52.133545],"type":"Point"}
}