{
  "type": "Feature",
  "properties": {
    "iso:country":"NL",
    "sg:address":"Marconistr 32",
    "sg:city":"Goes",
    "sg:orig_category":"Bedden En Matrassen",
    "sg:phone":"+31 118 603 434",
    "sg:postcode":"4461 HH",
    "sg:province":"Ohio",
    "wof:name":"Morgana",
    "wof:placetype":"venue"
},
  "geometry": {"coordinates":[-83.914169,39.768833],"type":"Point"}
}