{
  "type": "Feature",
  "properties": {
    "addr:full":"Kerkendijk 80 Someren Noord-Brabant 5712 EW",
    "addr:housenumber":"80",
    "addr:postcode":"5712 ew",
    "addr:street":"Kerkendijk",
    "iso:country":"NL",
    "sg:address":"Kerkendijk 80",
    "sg:city":"Someren",
    "sg:orig_category":"Levende Dieren Gh",
    "sg:phone":"+31 493 492 279",
    "sg:postcode":"5712 EW",
    "sg:province":"Noord-Brabant",
    "wof:name":"Veehandel En Landbouwbedrijf A. Van Rooi",
    "wof:placetype":"venue"
},
  "geometry": {"coordinates":[5.69689,51.357094],"type":"Point"}
}