{
  "type": "Feature",
  "properties": {
    "addr:full":"Pr Julianawg 63 Dordrecht Zuid-Holland 3314 KS",
    "addr:housenumber":"63",
    "addr:postcode":"3314 ks",
    "iso:country":"NL",
    "sg:address":"Pr Julianawg 63",
    "sg:city":"Dordrecht",
    "sg:orig_category":"Oud Metaal",
    "sg:phone":"+31 78 614 2176",
    "sg:postcode":"3314 KS",
    "sg:province":"Zuid-Holland",
    "wof:name":"Branten Ijzer & Metalen, T",
    "wof:placetype":"venue"
},
  "geometry": {"coordinates":[4.6675949097,51.7997169495],"type":"Point"}
}