{
  "type": "Feature",
  "properties": {
    "iso:country":"NL",
    "sg:address":"Grotestr 33B",
    "sg:city":"Ravenstein",
    "sg:orig_category":"Administratie- En Boekhoudkantoren",
    "sg:phone":"+31 486 411 442",
    "sg:postcode":"5371 BV",
    "sg:province":"Noord-Brabant",
    "wof:name":"A-Vier",
    "wof:placetype":"venue"
},
  "geometry": {"coordinates":[5.6466,51.790283],"type":"Point"}
}