{
  "type": "Feature",
  "properties": {
    "addr:full":"Moorland 5 Oirschot Noord-Brabant 5688 GA",
    "addr:housenumber":"5",
    "addr:postcode":"5688 ga",
    "addr:street":"Moorland",
    "iso:country":"NL",
    "sg:address":"Moorland 5",
    "sg:city":"Oirschot",
    "sg:orig_category":"Gordijnen",
    "sg:phone":"+31 499 571 344",
    "sg:postcode":"5688 GA",
    "sg:province":"Noord-Brabant",
    "wof:name":"Termeer",
    "wof:placetype":"venue"
},
  "geometry": {"coordinates":[5.305372,51.500072],"type":"Point"}
}