{
  "type": "Feature",
  "properties": {
    "addr:full":"Jhr C Sternpln 37 Voorburg Zuid-Holland 2273 WZ",
    "addr:housenumber":"37",
    "addr:postcode":"2273 wz",
    "addr:street":"Jhr C Sternpln",
    "iso:country":"NL",
    "sg:address":"Jhr C Sternpln 37",
    "sg:city":"Voorburg",
    "sg:orig_category":"Nagelstudio'S",
    "sg:phone":"+31 6 10193928",
    "sg:postcode":"2273 WZ",
    "sg:province":"Zuid-Holland",
    "wof:name":"After Hours Nail Service",
    "wof:placetype":"venue"
},
  "geometry": {"coordinates":[4.359058,52.076942],"type":"Point"}
}