{
  "type": "Feature",
  "properties": {
    "iso:country":"NL",
    "sg:address":"R Bosstr 2",
    "sg:city":"Boskoop",
    "sg:orig_category":"Onderhoudswerken",
    "sg:phone":"+31 172 217 215",
    "sg:postcode":"2771 JA",
    "sg:province":"Zuid-Holland",
    "wof:name":"Huis & Tuin",
    "wof:placetype":"venue"
},
  "geometry": {"coordinates":[4.651168,52.065647],"type":"Point"}
}