{
  "type": "Feature",
  "properties": {
    "iso:country":"NL",
    "sg:address":"Dorpstr 86",
    "sg:city":"Veldhoven",
    "sg:orig_category":"Administratie- En Boekhoudkantoren",
    "sg:phone":"+31 40 255 4060",
    "sg:postcode":"5504 HK",
    "sg:province":"Noord-Brabant",
    "wof:name":"Heugten & Vissers Bv, Van",
    "wof:placetype":"venue"
},
  "geometry": {"coordinates":[5.405969,51.405231],"type":"Point"}
}