{
  "type": "Feature",
  "properties": {
    "iso:country":"NL",
    "sg:address":"Konynenln 12",
    "sg:city":"Bilthoven",
    "sg:orig_category":"Autorijscholen",
    "sg:phone":"+31 30 229 1680",
    "sg:postcode":"3721 DE",
    "sg:province":"Utrecht",
    "wof:name":"Zande, J J M Van Der",
    "wof:placetype":"venue"
},
  "geometry": {"coordinates":[5.191409,52.1217],"type":"Point"}
}