{
  "type": "Feature",
  "properties": {
    "addr:full":"Peperstraat 39 Wijk Bij Duurstede Utrecht 3961 AR",
    "addr:housenumber":"39",
    "addr:postcode":"3961",
    "addr:street":"Peperstraat",
    "iso:country":"NL",
    "sg:address":"Peperstraat 39",
    "sg:city":"Wijk Bij Duurstede",
    "sg:orig_category":"Antiekzaken",
    "sg:phone":"+31 343 575 962",
    "sg:postcode":"3961 AR",
    "sg:province":"Utrecht",
    "wof:name":"Dorphie",
    "wof:placetype":"venue"
},
  "geometry": {"coordinates":[5.347625,51.972076],"type":"Point"}
}