{
  "type": "Feature",
  "properties": {
    "addr:full":"Rooseveltwg 367A Wageningen Gelderland 6707 GP",
    "addr:housenumber":"367a",
    "addr:postcode":"6707 gp",
    "addr:street":"Gelderland",
    "iso:country":"NL",
    "sg:address":"Rooseveltwg 367A",
    "sg:city":"Wageningen",
    "sg:orig_category":"Kappers",
    "sg:phone":"+31 317 426 197",
    "sg:postcode":"6707 GP",
    "sg:province":"Gelderland",
    "sg:website":"http://www.maxkappers.nl",
    "wof:name":"Maxx Kappers",
    "wof:placetype":"venue"
},
  "geometry": {"coordinates":[5.664637,51.97121],"type":"Point"}
}