{
  "type": "Feature",
  "properties": {
    "iso:country":"NL",
    "sg:address":"Springwg 7",
    "sg:city":"Utrecht",
    "sg:orig_category":"Acupunctuur",
    "sg:phone":"+31 30 234 1707",
    "sg:postcode":"3511 VH",
    "sg:province":"Utrecht",
    "wof:name":"Praag Instituut, Van",
    "wof:placetype":"venue"
},
  "geometry": {"coordinates":[5.118303,52.088886],"type":"Point"}
}