{
  "type": "Feature",
  "properties": {
    "addr:full":"Singel 18 Bussum Noord-Holland 1402 NT",
    "addr:housenumber":"18",
    "addr:postcode":"1402 nt",
    "addr:street":"Singel",
    "iso:country":"NL",
    "sg:address":"Singel 18",
    "sg:city":"Bussum",
    "sg:orig_category":"Kantoorartikelen",
    "sg:phone":"+31 35 693 4910",
    "sg:postcode":"1402 NT",
    "sg:province":"Noord-Holland",
    "wof:name":"Dadur Bv",
    "wof:placetype":"venue"
},
  "geometry": {"coordinates":[5.1657328606,52.2698326111],"type":"Point"}
}