{
  "type": "Feature",
  "properties": {
    "iso:country":"NL",
    "sg:address":"Windroospln 92",
    "sg:city":"Amsterdam",
    "sg:orig_category":"Belastingconsulenten/ Belastingadviseurs",
    "sg:phone":"+31 20 330 9527",
    "sg:postcode":"1018 ZW",
    "sg:province":"North Holland",
    "sg:website":"http://www.windroosconsult.nl",
    "wof:name":"Windroos",
    "wof:placetype":"venue"
},
  "geometry": {"coordinates":[4.924859,52.373074],"type":"Point"}
}