{
  "type": "Feature",
  "properties": {
    "addr:full":"Tractiewg 89 Utrecht Utrecht 3534 AP",
    "addr:housenumber":"89",
    "addr:postcode":"3534 ap",
    "addr:street":"Tractiewg",
    "iso:country":"NL",
    "sg:address":"Tractiewg 89",
    "sg:city":"Utrecht",
    "sg:orig_category":"Metaalbewerking",
    "sg:phone":"+31 30 670 0345",
    "sg:postcode":"3534 AP",
    "sg:province":"Utrecht",
    "wof:name":"B & K Bv",
    "wof:placetype":"venue"
},
  "geometry": {"coordinates":[5.082419,52.104214],"type":"Point"}
}