{
  "type": "Feature",
  "properties": {
    "addr:full":"A Schweitzerln 51 S Gravenhage South Holland 2552 PD",
    "addr:housenumber":"51",
    "addr:postcode":"2552 pd",
    "addr:street":"S Gravenhage",
    "iso:country":"NL",
    "sg:address":"A Schweitzerln 51",
    "sg:city":"S Gravenhage",
    "sg:orig_category":"Yoga-Instituten",
    "sg:phone":"+31 70 397 1555",
    "sg:postcode":"2552 PD",
    "sg:province":"South Holland",
    "wof:name":"Hekelaar-Koh, C L",
    "wof:placetype":"venue"
},
  "geometry": {"coordinates":[4.24958,52.053631],"type":"Point"}
}