{
  "type": "Feature",
  "properties": {
    "addr:full":"Dorpsstraat 16 Etten Gld Gelderland 7075 AD",
    "addr:housenumber":"16",
    "addr:postcode":"7075 ad",
    "addr:street":"Dorpsstraat;Gld Gelderland",
    "iso:country":"NL",
    "sg:address":"Dorpsstraat 16",
    "sg:city":"Etten Gld",
    "sg:orig_category":"Banken And Kredietinstellingen",
    "sg:phone":"+31 315 324 967",
    "sg:postcode":"7075 AD",
    "sg:province":"Gelderland",
    "wof:name":"J.W.M. Westerhof-Aalders",
    "wof:placetype":"venue"
},
  "geometry": {"coordinates":[6.338288,51.916286],"type":"Point"}
}