{
  "type": "Feature",
  "properties": {
    "addr:full":"Domselaerstraat 102 Amsterdam North Holland 1093 MA",
    "addr:housenumber":"102",
    "addr:postcode":"1093 ma",
    "addr:street":"Domselaerstraat",
    "iso:country":"NL",
    "sg:address":"Domselaerstraat 102",
    "sg:city":"Amsterdam",
    "sg:orig_category":"Fotostudio'S And Fotografen",
    "sg:phone":"+31 20 692 7919",
    "sg:postcode":"1093 MA",
    "sg:province":"North Holland",
    "wof:name":"Essamba Arts Fotografie",
    "wof:placetype":"venue"
},
  "geometry": {"coordinates":[4.928194,52.359921],"type":"Point"}
}