{
  "type": "Feature",
  "properties": {
    "iso:country":"NL",
    "sg:address":"Tochtenwg 35",
    "sg:city":"Rotterdam",
    "sg:orig_category":"Bejaarden - Verzorgingstehuizen",
    "sg:phone":"+31 10 456 7666",
    "sg:postcode":"3069 XZ",
    "sg:province":"South Holland",
    "wof:name":"Sevencamp, De",
    "wof:placetype":"venue"
},
  "geometry": {"coordinates":[4.576644,51.968784],"type":"Point"}
}