{
  "type": "Feature",
  "properties": {
    "addr:full":"Matlingewg 101 Rotterdam South Holland 3044 EV",
    "addr:housenumber":"101",
    "addr:postcode":"3044 ev",
    "iso:country":"NL",
    "sg:address":"Matlingewg 101",
    "sg:city":"Rotterdam",
    "sg:orig_category":"Verpakkingsmachines",
    "sg:phone":"+31 10 437 0966",
    "sg:postcode":"3044 EV",
    "sg:province":"South Holland",
    "wof:name":"Coppens Bv",
    "wof:placetype":"venue"
},
  "geometry": {"coordinates":[4.414064,51.928528],"type":"Point"}
}