{
  "type": "Feature",
  "properties": {
    "iso:country":"NL",
    "sg:address":"F Mullerstr 90",
    "sg:city":"Hoofddorp",
    "sg:orig_category":"Goudsmeden En Zilversmeden",
    "sg:phone":"+31 23 563 2480",
    "sg:postcode":"2135 MS",
    "sg:province":"Noord-Holland",
    "sg:website":"http://www.goudsmideric.nl",
    "wof:name":"Eric V Limpt",
    "wof:placetype":"venue"
},
  "geometry": {"coordinates":[4.66895,52.296093],"type":"Point"}
}