{
  "type": "Feature",
  "properties": {
    "iso:country":"NL",
    "sg:address":"Hoekgraaf 17",
    "sg:city":"Bergharen",
    "sg:orig_category":"Technische Studies And Onderzoek",
    "sg:phone":"+31 487 532 351",
    "sg:postcode":"6617 AX",
    "sg:province":"Gelderland",
    "wof:name":"Leonardo Bv",
    "wof:placetype":"venue"
},
  "geometry": {"coordinates":[5.66599,51.863605],"type":"Point"}
}