{
  "type": "Feature",
  "properties": {
    "addr:full":"Langeraarseweg 177 Ter Aar Zuid-Holland 2461 CJ",
    "addr:housenumber":"177",
    "addr:postcode":"aar;2461 cj",
    "addr:street":"Langeraarseweg;Ter",
    "iso:country":"NL",
    "sg:address":"Langeraarseweg 177",
    "sg:city":"Ter Aar",
    "sg:orig_category":"Verhuur Audiovisuele Apparatuur",
    "sg:phone":"+31 172 602 120",
    "sg:postcode":"2461 CJ",
    "sg:province":"Zuid-Holland",
    "wof:name":"Jansma Electronic Techniek",
    "wof:placetype":"venue"
},
  "geometry": {"coordinates":[4.698587,52.18718],"type":"Point"}
}