{
  "type": "Feature",
  "properties": {
    "addr:full":"Binnenwg 11 Twello Gelderland 7391 GK",
    "addr:housenumber":"11",
    "addr:postcode":"7391 gk",
    "addr:street":"Binnenwg;Gelderland",
    "iso:country":"NL",
    "sg:address":"Binnenwg 11",
    "sg:city":"Twello",
    "sg:orig_category":"Verenigingen En Stichtingen",
    "sg:phone":"+31 571 272 652",
    "sg:postcode":"7391 GK",
    "sg:province":"Gelderland",
    "wof:name":"Mens En Werk, Sticht",
    "wof:placetype":"venue"
},
  "geometry": {"coordinates":[6.108897,52.240047],"type":"Point"}
}