{
  "type": "Feature",
  "properties": {
    "addr:full":"Hoogeind 5 Breda North Brabant 4817 EG",
    "addr:housenumber":"5",
    "addr:postcode":"4817 eg",
    "addr:street":"Hoogeind",
    "iso:country":"NL",
    "sg:address":"Hoogeind 5",
    "sg:city":"Breda",
    "sg:orig_category":"Boekhandels",
    "sg:phone":"+31 76 522 1455",
    "sg:postcode":"4817 EG",
    "sg:province":"North Brabant",
    "wof:name":"O. Van Dongen",
    "wof:placetype":"venue"
},
  "geometry": {"coordinates":[4.806272,51.590538],"type":"Point"}
}