{
  "type": "Feature",
  "properties": {
    "addr:full":"Middenwg 546 Heerhugowaard Noord-Holland 1704 BP",
    "addr:housenumber":"546",
    "addr:postcode":"1704 bp",
    "iso:country":"NL",
    "sg:address":"Middenwg 546",
    "sg:city":"Heerhugowaard",
    "sg:orig_category":"Kappers",
    "sg:phone":"+31 72 571 1221",
    "sg:postcode":"1704 BP",
    "sg:province":"Noord-Holland",
    "wof:name":"Frank",
    "wof:placetype":"venue"
},
  "geometry": {"coordinates":[4.827521801,52.6651954651],"type":"Point"}
}