{
  "type": "Feature",
  "properties": {
    "addr:full":"Zylwg 7 Waalwyk Noord-Brabant 5145 NR",
    "addr:housenumber":"7",
    "addr:postcode":"5145 nr",
    "addr:street":"Zylwg",
    "iso:country":"NL",
    "sg:address":"Zylwg 7",
    "sg:city":"Waalwyk",
    "sg:orig_category":"Metaalbewerking",
    "sg:phone":"+31 416 650 403",
    "sg:postcode":"5145 NR",
    "sg:province":"Noord-Brabant",
    "wof:name":"Ligtvoet, C N J M",
    "wof:placetype":"venue"
},
  "geometry": {"coordinates":[5.0695,51.706451],"type":"Point"}
}