{
  "type": "Feature",
  "properties": {
    "addr:full":"V Brucken Fockln 29 Heemstede Noord-Holland 2102 XB",
    "addr:housenumber":"29",
    "addr:postcode":"2102 xb",
    "addr:street":"V Brucken Fockln",
    "iso:country":"NL",
    "sg:address":"V Brucken Fockln 29",
    "sg:city":"Heemstede",
    "sg:orig_category":"Verzekeringen - Verzekeringskantoren",
    "sg:phone":"+31 23 529 3850",
    "sg:postcode":"2102 XB",
    "sg:province":"Noord-Holland",
    "wof:name":"Goossens",
    "wof:placetype":"venue"
},
  "geometry": {"coordinates":[4.628812,52.351799],"type":"Point"}
}