{
  "type": "Feature",
  "properties": {
    "addr:full":"Operettestraat 15 Apeldoorn Gelderland 7323 KG",
    "addr:housenumber":"15",
    "addr:postcode":"7323 kg",
    "addr:street":"Operettestraat;Gelderland",
    "iso:country":"NL",
    "sg:address":"Operettestraat 15",
    "sg:city":"Apeldoorn",
    "sg:orig_category":"Loodgieterswerk, Verwarming And Sanitaire Installaties",
    "sg:phone":"+31 55 366 8912",
    "sg:postcode":"7323 KG",
    "sg:province":"Gelderland",
    "wof:name":"Grootonderhoudsbedrijf De Haan",
    "wof:placetype":"venue"
},
  "geometry": {"coordinates":[5.993522,52.231602],"type":"Point"}
}