{
  "type": "Feature",
  "properties": {
    "iso:country":"NL",
    "sg:address":"De Factory 63C",
    "sg:city":"Zwaag",
    "sg:orig_category":"Keukens",
    "sg:phone":"+31 229 272 107",
    "sg:postcode":"1689 AK",
    "sg:province":"Noord-Holland",
    "sg:website":"http://www.schouw.nl",
    "wof:name":"Schouw Bv, 'T",
    "wof:placetype":"venue"
},
  "geometry": {"coordinates":[5.06437,52.668266],"type":"Point"}
}