{
  "type": "Feature",
  "properties": {
    "iso:country":"NL",
    "sg:address":"Guldenstr 17",
    "sg:city":"Groningen",
    "sg:orig_category":"Schoenen",
    "sg:phone":"+31 50 312 5198",
    "sg:postcode":"9712 CD",
    "sg:province":"Groningen",
    "wof:name":"Dr Adam'S Bv",
    "wof:placetype":"venue"
},
  "geometry": {"coordinates":[6.565891,53.218342],"type":"Point"}
}