{
  "type": "Feature",
  "properties": {
    "iso:country":"NL",
    "sg:address":"Varenbeukerweg 50",
    "sg:city":"Heerlen",
    "sg:orig_category":"Autokeuringen",
    "sg:phone":"+31 45 521 7734",
    "sg:postcode":"6414 NK",
    "sg:province":"Limburg",
    "wof:name":"Habo Autobedrijf",
    "wof:placetype":"venue"
},
  "geometry": {"coordinates":[5.95899,50.922729],"type":"Point"}
}