{
  "type": "Feature",
  "properties": {
    "addr:full":"Wildeveenstr 26 Rotterdam South Holland 3061 GZ",
    "addr:housenumber":"26",
    "addr:postcode":"3061 gz",
    "addr:street":"Wildeveenstr",
    "iso:country":"NL",
    "sg:address":"Wildeveenstr 26",
    "sg:city":"Rotterdam",
    "sg:classifiers":[
        {
            "category":"Personal",
            "subcategory":"Nail Salon",
            "type":"Services"
        }
    ],
    "sg:phone":"+31 10 452 1665",
    "sg:postcode":"3061 GZ",
    "sg:province":"South Holland",
    "sg:tags":[
        "pedicure"
    ],
    "wof:name":"Willy De Groot",
    "wof:placetype":"venue"
},
  "geometry": {"coordinates":[4.508375,51.931244],"type":"Point"}
}