{
  "type": "Feature",
  "properties": {
    "addr:full":"Orlandopassage 13 Kerkrade Limburg 6461 AM",
    "addr:housenumber":"13",
    "addr:postcode":"6461",
    "addr:street":"Orlandopassage",
    "iso:country":"NL",
    "sg:address":"Orlandopassage 13",
    "sg:city":"Kerkrade",
    "sg:classifiers":[
        {
            "category":"Food & Beverages",
            "subcategory":"Bakery",
            "type":"Retail Goods"
        }
    ],
    "sg:phone":"+31 45 535 1799",
    "sg:postcode":"6461 AM",
    "sg:province":"Limburg",
    "sg:tags":[
        "pizza"
    ],
    "wof:name":"Pizza Point",
    "wof:placetype":"venue"
},
  "geometry": {"coordinates":[6.063885,50.865623],"type":"Point"}
}