{
  "type": "Feature",
  "properties": {
    "addr:full":"Spuiweg 110 Dordrecht South Holland 3311 GV",
    "addr:housenumber":"110",
    "addr:postcode":"3311 gv",
    "addr:street":"Spuiweg",
    "iso:country":"NL",
    "sg:address":"Spuiweg 110",
    "sg:city":"Dordrecht",
    "sg:orig_category":"Kinderopvang Behalve Thuis",
    "sg:phone":"+31 78 631 4546",
    "sg:postcode":"3311 GV",
    "sg:province":"South Holland",
    "wof:name":"Kinderdagverblijf Bambino",
    "wof:placetype":"venue"
},
  "geometry": {"coordinates":[4.663042,51.809875],"type":"Point"}
}