{
  "type": "Feature",
  "properties": {
    "addr:full":"Dorpsstr 12 Zwaag Noord-Holland 1689 EV",
    "addr:housenumber":"12",
    "addr:street":"Dorpsstr",
    "iso:country":"NL",
    "sg:address":"Dorpsstr 12",
    "sg:city":"Zwaag",
    "sg:orig_category":"Woningstoffeerders",
    "sg:phone":"+31 229 239 527",
    "sg:postcode":"1689 EV",
    "sg:province":"Noord-Holland",
    "wof:name":"Hol Freelance Woningstoffeerder L",
    "wof:placetype":"venue"
},
  "geometry": {"coordinates":[5.0470471382,52.6603736877],"type":"Point"}
}