{
  "type": "Feature",
  "properties": {
    "addr:full":"Transportstr 41 Bergambacht Zuid-Holland 2861 DX",
    "addr:housenumber":"41",
    "addr:postcode":"2861 dx",
    "addr:street":"Transportstr",
    "iso:country":"NL",
    "sg:address":"Transportstr 41",
    "sg:city":"Bergambacht",
    "sg:orig_category":"Autoschade- Herstelbedrijven",
    "sg:phone":"+31 182 354 410",
    "sg:postcode":"2861 DX",
    "sg:province":"Zuid-Holland",
    "wof:name":"Jansen",
    "wof:placetype":"venue"
},
  "geometry": {"coordinates":[4.78935,51.928188],"type":"Point"}
}