{
  "type": "Feature",
  "properties": {
    "addr:full":"M Dorpiusstraat 8 Naaldwijk South Holland 2671 ES",
    "addr:housenumber":"8",
    "addr:postcode":"2671 es",
    "addr:street":"Dorpiusstraat",
    "iso:country":"NL",
    "sg:address":"M Dorpiusstraat 8",
    "sg:city":"Naaldwijk",
    "sg:orig_category":"Fotostudio'S And Fotografen",
    "sg:phone":"+31 174 627 035",
    "sg:postcode":"2671 ES",
    "sg:province":"South Holland",
    "wof:name":"Westlands Fotoburo",
    "wof:placetype":"venue"
},
  "geometry": {"coordinates":[4.205428,51.994282],"type":"Point"}
}