{
  "type": "Feature",
  "properties": {
    "addr:full":"Hofstr 36 Groningen Groningen 9712 JC",
    "addr:housenumber":"36",
    "addr:postcode":"9712 jc",
    "addr:street":"Hofstr",
    "iso:country":"NL",
    "sg:address":"Hofstr 36",
    "sg:city":"Groningen",
    "sg:orig_category":"Vertalers",
    "sg:phone":"+31 50 313 4093",
    "sg:postcode":"9712 JC",
    "sg:province":"Groningen",
    "wof:name":"Hove-Meeuse, Drs Pauline Van",
    "wof:placetype":"venue"
},
  "geometry": {"coordinates":[6.567752,53.221436],"type":"Point"}
}