{
  "type": "Feature",
  "properties": {
    "addr:full":"Leidsepln 38 Haarlem Noord-Holland 2013 PZ",
    "addr:housenumber":"38",
    "addr:postcode":"2013 pz",
    "addr:street":"Leidsepln",
    "iso:country":"NL",
    "sg:address":"Leidsepln 38",
    "sg:city":"Haarlem",
    "sg:orig_category":"Verbouwingen",
    "sg:phone":"+31 23 531 8365",
    "sg:postcode":"2013 PZ",
    "sg:province":"Noord-Holland",
    "wof:name":"Fokkema, B D",
    "wof:placetype":"venue"
},
  "geometry": {"coordinates":[4.623592,52.379421],"type":"Point"}
}