{
  "type": "Feature",
  "properties": {
    "iso:country":"NL",
    "sg:address":"C V Maasdykln 1-11",
    "sg:city":"Arnhem",
    "sg:orig_category":"Kappers",
    "sg:phone":"+31 26 353 3590",
    "sg:postcode":"6816 TW",
    "sg:province":"Gelderland",
    "wof:name":"Theo",
    "wof:placetype":"venue"
},
  "geometry": {"coordinates":[5.88115,52.000462],"type":"Point"}
}