{
  "type": "Feature",
  "properties": {
    "addr:full":"Sandenburg 64 Vlissingen Zeeland 4385 GB",
    "addr:housenumber":"64",
    "addr:postcode":"4385 gb",
    "addr:street":"Sandenburg",
    "iso:country":"NL",
    "sg:address":"Sandenburg 64",
    "sg:city":"Vlissingen",
    "sg:orig_category":"Verhuur Bouwmachines",
    "sg:phone":"+31 118 466 550",
    "sg:postcode":"4385 GB",
    "sg:province":"Zeeland",
    "wof:name":"Hdv",
    "wof:placetype":"venue"
},
  "geometry": {"coordinates":[3.574652,51.463123],"type":"Point"}
}