{
  "type": "Feature",
  "properties": {
    "addr:full":"Dukdalfweg 4 Almere Flevoland 1332 BM",
    "addr:housenumber":"4",
    "addr:postcode":"1332 bm",
    "addr:street":"Dukdalfweg;Flevoland",
    "iso:country":"NL",
    "sg:address":"Dukdalfweg 4",
    "sg:city":"Almere",
    "sg:orig_category":"Glaszetten",
    "sg:phone":"+31 36 536 7915",
    "sg:postcode":"1332 BM",
    "sg:province":"Flevoland",
    "wof:name":"Glaszettersbedrijf Van Kesteren Projects Bv",
    "wof:placetype":"venue"
},
  "geometry": {"coordinates":[5.255819,52.408909],"type":"Point"}
}