{
  "type": "Feature",
  "properties": {
    "addr:full":"Einsteinstr 41 Veenendaal Utrecht 3902 HN",
    "addr:housenumber":"41",
    "addr:postcode":"3902 hn",
    "addr:street":"Einsteinstr",
    "iso:country":"NL",
    "sg:address":"Einsteinstr 41",
    "sg:city":"Veenendaal",
    "sg:orig_category":"Automaterialen En Gereedschappen",
    "sg:phone":"+31 318 559 220",
    "sg:postcode":"3902 HN",
    "sg:province":"Utrecht",
    "sg:website":"http://www.remdienst.nl",
    "wof:name":"Axima",
    "wof:placetype":"venue"
},
  "geometry": {"coordinates":[5.570719,52.039516],"type":"Point"}
}