{
  "type": "Feature",
  "properties": {
    "addr:full":"Keizersgr 24 Eindhoven Noord-Brabant 5611 GD",
    "addr:housenumber":"24",
    "addr:postcode":"5611 gd",
    "addr:street":"Keizersgr",
    "iso:country":"NL",
    "sg:address":"Keizersgr 24",
    "sg:city":"Eindhoven",
    "sg:orig_category":"Antiquiteiten",
    "sg:phone":"+31 40 244 1624",
    "sg:postcode":"5611 GD",
    "sg:province":"Noord-Brabant",
    "wof:name":"Keizerin, De",
    "wof:placetype":"venue"
},
  "geometry": {"coordinates":[5.477575,51.436737],"type":"Point"}
}