{
  "type": "Feature",
  "properties": {
    "iso:country":"NL",
    "sg:address":"G V Prinstererstr 12H",
    "sg:city":"Amsterdam",
    "sg:orig_category":"Fotografie Reclame En Mode",
    "sg:phone":"+31 20 486 0664",
    "sg:postcode":"1051 EE",
    "sg:province":"Noord-Holland",
    "wof:name":"Holtslag, Jan",
    "wof:placetype":"venue"
},
  "geometry": {"coordinates":[4.87107,52.37925],"type":"Point"}
}