{
  "type": "Feature",
  "properties": {
    "addr:full":"Woestijgerweg 50 Amersfoort Utrecht 3817 SL",
    "addr:housenumber":"50",
    "addr:postcode":"3817 sl",
    "addr:street":"Woestijgerweg",
    "iso:country":"NL",
    "sg:address":"Woestijgerweg 50",
    "sg:city":"Amersfoort",
    "sg:orig_category":"Artiestenbureaus",
    "sg:phone":"+31 33 463 8257",
    "sg:postcode":"3817 SL",
    "sg:province":"Utrecht",
    "wof:name":"De Combo Boys Vof",
    "wof:placetype":"venue"
},
  "geometry": {"coordinates":[5.385087,52.146191],"type":"Point"}
}