{
  "type": "Feature",
  "properties": {
    "addr:full":"Havenstr 15 Schoonoord Drenthe 7848 AA",
    "addr:housenumber":"15",
    "addr:postcode":"7848 aa",
    "addr:street":"Havenstr",
    "iso:country":"NL",
    "sg:address":"Havenstr 15",
    "sg:city":"Schoonoord",
    "sg:orig_category":"Wegenbouw",
    "sg:phone":"+31 591 381 645",
    "sg:postcode":"7848 AA",
    "sg:province":"Drenthe",
    "sg:website":"http://www.snitjer-geleiderail.nl",
    "wof:name":"Snitjer Geleiderail",
    "wof:placetype":"venue"
},
  "geometry": {"coordinates":[6.7603859901,52.847869873],"type":"Point"}
}