{
  "type": "Feature",
  "properties": {
    "addr:full":"Lindenln 82 Uffelte Drenthe 7975 AJ",
    "addr:housenumber":"82",
    "addr:postcode":"7975 aj",
    "addr:street":"Lindenln",
    "iso:country":"NL",
    "sg:address":"Lindenln 82",
    "sg:city":"Uffelte",
    "sg:orig_category":"Scheepvaartservice- Bureaus",
    "sg:phone":"+31 521 350 050",
    "sg:postcode":"7975 AJ",
    "sg:province":"Drenthe",
    "sg:website":"http://www.schipperij.nl",
    "wof:name":"Schipperij",
    "wof:placetype":"venue"
},
  "geometry": {"coordinates":[6.283956,52.791996],"type":"Point"}
}