{
  "type": "Feature",
  "properties": {
    "addr:full":"Steenovenweg 3 Helmond Noord-Brabant 5708 HN",
    "addr:housenumber":"3",
    "addr:postcode":"5708 hn",
    "addr:street":"Steenovenweg",
    "iso:country":"NL",
    "sg:address":"Steenovenweg 3",
    "sg:city":"Helmond",
    "sg:orig_category":"Bedrijfs- And Managementsconsultants",
    "sg:phone":"+31 492 523 000",
    "sg:postcode":"5708 HN",
    "sg:province":"Noord-Brabant",
    "wof:name":"Ward Cambell International Bv",
    "wof:placetype":"venue"
},
  "geometry": {"coordinates":[5.627172,51.474007],"type":"Point"}
}