{
  "type": "Feature",
  "properties": {
    "addr:full":"Zwet 37 Appingedam Groningen 9902 RM",
    "addr:housenumber":"37",
    "addr:postcode":"9902 rm",
    "addr:street":"Zwet",
    "iso:country":"NL",
    "sg:address":"Zwet 37",
    "sg:city":"Appingedam",
    "sg:orig_category":"Keukens",
    "sg:phone":"+31 596 682 303",
    "sg:postcode":"9902 RM",
    "sg:province":"Groningen",
    "wof:name":"Wildeboer Keukencentrum",
    "wof:placetype":"venue"
},
  "geometry": {"coordinates":[6.882657,53.319874],"type":"Point"}
}