{
  "type": "Feature",
  "properties": {
    "addr:full":"Mercuriusplein 60 Assen Drenthe 9401 DL",
    "addr:housenumber":"60",
    "addr:postcode":"9401 dl",
    "addr:street":"Mercuriusplein",
    "iso:country":"NL",
    "sg:address":"Mercuriusplein 60",
    "sg:city":"Assen",
    "sg:classifiers":[
        {
            "category":"Shopping",
            "subcategory":"Gifts & Souvenirs",
            "type":"Retail Goods"
        }
    ],
    "sg:phone":"+31 592 317 937",
    "sg:postcode":"9401 DL",
    "sg:province":"Drenthe",
    "sg:tags":[
        "geschenken"
    ],
    "wof:name":"Image",
    "wof:placetype":"venue"
},
  "geometry": {"coordinates":[6.559025,52.995899],"type":"Point"}
}