{
  "type": "Feature",
  "properties": {
    "addr:full":"Amersfoortsestr 30 Amersfoort Utrecht 3821 CC",
    "addr:housenumber":"30",
    "addr:postcode":"3821 cc",
    "addr:street":"Amersfoortsestr",
    "iso:country":"NL",
    "sg:address":"Amersfoortsestr 30",
    "sg:city":"Amersfoort",
    "sg:orig_category":"Autoreclame",
    "sg:phone":"+31 33 253 8143",
    "sg:postcode":"3821 CC",
    "sg:province":"Utrecht",
    "sg:website":"http://www.todd.nl",
    "wof:name":"Todd",
    "wof:placetype":"venue"
},
  "geometry": {"coordinates":[5.434151,52.169613],"type":"Point"}
}