{
  "type": "Feature",
  "properties": {
    "addr:full":"Reigerskamp 177 Maarssen Utrecht 3607 HJ",
    "addr:housenumber":"177",
    "addr:postcode":"3607 hj",
    "addr:street":"Reigerskamp",
    "iso:country":"NL",
    "sg:address":"Reigerskamp 177",
    "sg:city":"Maarssen",
    "sg:orig_category":"Adviesbureaus Bedrijfsorganisatie",
    "sg:phone":"+31 346 553 191",
    "sg:postcode":"3607 HJ",
    "sg:province":"Utrecht",
    "wof:name":"Bosch, Geert",
    "wof:placetype":"venue"
},
  "geometry": {"coordinates":[5.013507,52.134109],"type":"Point"}
}