{
  "type": "Feature",
  "properties": {
    "addr:full":"Halkd 36 Ymuiden Noord-Holland 1976 DC",
    "addr:housenumber":"36",
    "addr:postcode":"1976",
    "addr:street":"Halkd",
    "iso:country":"NL",
    "sg:address":"Halkd 36",
    "sg:city":"Ymuiden",
    "sg:orig_category":"Vis En Visproducten - Groothandel",
    "sg:phone":"+31 255 526 939",
    "sg:postcode":"1976 DC",
    "sg:province":"Noord-Holland",
    "wof:name":"Seafood Ijmuiden",
    "wof:placetype":"venue"
},
  "geometry": {"coordinates":[-77.01458700000001,38.8937],"type":"Point"}
}