{
  "type": "Feature",
  "properties": {
    "iso:country":"NL",
    "sg:address":"Sterkenburgerln 54",
    "sg:city":"Doorn",
    "sg:orig_category":"Loodgieters",
    "sg:phone":"+31 343 516 825",
    "sg:postcode":"3941 BD",
    "sg:province":"Utrecht",
    "wof:name":"Gardenier, S",
    "wof:placetype":"venue"
},
  "geometry": {"coordinates":[5.297516,52.034603],"type":"Point"}
}