{
  "type": "Feature",
  "properties": {
    "addr:full":"Fok 61 Heerenveen Provincie Friesland 8441 BP",
    "addr:housenumber":"61",
    "addr:postcode":"8441 bp",
    "addr:street":"Fok;Provincie Friesland",
    "iso:country":"NL",
    "sg:address":"Fok 61",
    "sg:city":"Heerenveen",
    "sg:orig_category":"Bejaarden - Verzorgingstehuizen",
    "sg:phone":"+31 513 624 925",
    "sg:postcode":"8441 BP",
    "sg:province":"Provincie Friesland",
    "wof:name":"Mari?nbosch",
    "wof:placetype":"venue"
},
  "geometry": {"coordinates":[5.918998,52.961742],"type":"Point"}
}