{
  "type": "Feature",
  "properties": {
    "addr:full":"Ringoven 66 Delfzyl Groningen 9934 LE",
    "addr:housenumber":"66",
    "addr:postcode":"9934 le",
    "addr:street":"Ringoven",
    "iso:country":"NL",
    "sg:address":"Ringoven 66",
    "sg:city":"Delfzyl",
    "sg:orig_category":"Verenigingen En Stichtingen",
    "sg:phone":"+31 596 616 554",
    "sg:postcode":"9934 LE",
    "sg:province":"Groningen",
    "wof:name":"Ouderenbond Pcob",
    "wof:placetype":"venue"
},
  "geometry": {"coordinates":[6.905103,53.328468],"type":"Point"}
}