{
  "type": "Feature",
  "properties": {
    "addr:full":"Zuidvliet 204 Leeuwarden Friesland 8921 BN",
    "addr:housenumber":"204",
    "addr:postcode":"8921 bn",
    "addr:street":"Zuidvliet",
    "iso:country":"NL",
    "sg:address":"Zuidvliet 204",
    "sg:city":"Leeuwarden",
    "sg:classifiers":[
        {
            "category":"Fast Food",
            "type":"Food & Drink"
        }
    ],
    "sg:phone":"+31 58 216 2809",
    "sg:postcode":"8921 BN",
    "sg:province":"Friesland",
    "sg:tags":[
        "afhaal",
        "restaurant"
    ],
    "wof:name":"Snackbar Het Vliet",
    "wof:placetype":"venue"
},
  "geometry": {"coordinates":[5.81099,53.205589],"type":"Point"}
}