{
  "type": "Feature",
  "properties": {
    "addr:full":"C Huygensstr 7 Oud Beyerland South Holland 3261 LR",
    "addr:housenumber":"7",
    "addr:postcode":"3261 lr",
    "addr:street":"Oud Beyerland",
    "iso:country":"NL",
    "sg:address":"C Huygensstr 7",
    "sg:city":"Oud Beyerland",
    "sg:orig_category":"Autorijscholen",
    "sg:phone":"+31 186 610 237",
    "sg:postcode":"3261 LR",
    "sg:province":"South Holland",
    "sg:website":"http://www.petropoortvliet.nl",
    "wof:name":"Poortvliet, Petro",
    "wof:placetype":"venue"
},
  "geometry": {"coordinates":[4.43688,51.828804],"type":"Point"}
}