{
  "type": "Feature",
  "properties": {
    "addr:full":"Akerstraat 115 Heerlen Limburg 6417 BM",
    "addr:housenumber":"115",
    "addr:postcode":"6417 bm",
    "addr:street":"Akerstraat",
    "iso:country":"NL",
    "sg:address":"Akerstraat 115",
    "sg:city":"Heerlen",
    "sg:orig_category":"Volwassenenonderwijs",
    "sg:phone":"+31 45 571 3952",
    "sg:postcode":"6417 BM",
    "sg:province":"Limburg",
    "wof:name":"Grotius College",
    "wof:placetype":"venue"
},
  "geometry": {"coordinates":[5.985975,50.879959],"type":"Point"}
}