{
  "type": "Feature",
  "properties": {
    "addr:full":"Obrechtstr 44 Dordrecht Zuid-Holland 3314 EM",
    "addr:housenumber":"44",
    "addr:postcode":"3314 em",
    "addr:street":"Obrechtstr",
    "iso:country":"NL",
    "sg:address":"Obrechtstr 44",
    "sg:city":"Dordrecht",
    "sg:orig_category":"Webdesign Bureaus",
    "sg:phone":"+31 78 639 9051",
    "sg:postcode":"3314 EM",
    "sg:province":"Zuid-Holland",
    "wof:name":"Dabbler Vof",
    "wof:placetype":"venue"
},
  "geometry": {"coordinates":[4.6570248604,51.8028068542],"type":"Point"}
}