{
  "type": "Feature",
  "properties": {
    "iso:country":"NL",
    "sg:address":"Nieuwland 10",
    "sg:city":"Hoorn Nh",
    "sg:orig_category":"Piano'S",
    "sg:phone":"+31 229 219 991",
    "sg:postcode":"1621 HK",
    "sg:province":"North Holland",
    "sg:website":"http://www.moeskopsmuziek.nl",
    "wof:name":"Moeskops Muziek",
    "wof:placetype":"venue"
},
  "geometry": {"coordinates":[5.05917,52.642876],"type":"Point"}
}