{
  "type": "Feature",
  "properties": {
    "addr:full":"Pieter Aertsenhage 50 Nieuwegein Utrecht 3437 NV",
    "addr:housenumber":"50",
    "addr:postcode":"3437 nv",
    "addr:street":"Pieter Aertsenhage",
    "iso:country":"NL",
    "sg:address":"Pieter Aertsenhage 50",
    "sg:city":"Nieuwegein",
    "sg:orig_category":"Artsen And Specialisten",
    "sg:phone":"+31 30 602 2249",
    "sg:postcode":"3437 NV",
    "sg:province":"Utrecht",
    "wof:name":"Fobie Centrum Midden-Nederland",
    "wof:placetype":"venue"
},
  "geometry": {"coordinates":[5.072959,52.052795],"type":"Point"}
}