{
  "type": "Feature",
  "properties": {
    "addr:full":"Hogelandseweg 44 Vianen Zh Utrecht 4132 CW",
    "addr:housenumber":"44",
    "addr:postcode":"zh;4132 cw",
    "addr:street":"Hogelandseweg",
    "iso:country":"NL",
    "sg:address":"Hogelandseweg 44",
    "sg:city":"Vianen Zh",
    "sg:orig_category":"Woningbouwverenigingen",
    "sg:phone":"+31 347 372 020",
    "sg:postcode":"4132 CW",
    "sg:province":"Utrecht",
    "wof:name":"Bouwvereniging Volksbelang",
    "wof:placetype":"venue"
},
  "geometry": {"coordinates":[5.0925769806,51.9872436523],"type":"Point"}
}