{
  "type": "Feature",
  "properties": {
    "iso:country":"NL",
    "sg:address":"Hogehilweg 14",
    "sg:city":"Amsterdam",
    "sg:orig_category":"Juweliers",
    "sg:phone":"+31 20 623 8968",
    "sg:postcode":"1017 VL",
    "sg:province":"North Holland",
    "wof:name":"Westra L J",
    "wof:placetype":"venue"
},
  "geometry": {"coordinates":[4.947931,52.306789],"type":"Point"}
}