{
  "type": "Feature",
  "properties": {
    "iso:country":"NL",
    "sg:address":"Constantijnstraat 11A",
    "sg:city":"Aalsmeer",
    "sg:orig_category":"Kinderopvang Behalve Thuis",
    "sg:phone":"+31 297 324 834",
    "sg:postcode":"1432 HJ",
    "sg:province":"North Holland",
    "wof:name":"Peuterspeelzaal Oost-Kroost",
    "wof:placetype":"venue"
},
  "geometry": {"coordinates":[4.797497,52.275654],"type":"Point"}
}