{
  "type": "Feature",
  "properties": {
    "addr:full":"William Boothlaan 12 Rotterdam Zuid-Holland 3012 VJ",
    "addr:housenumber":"12",
    "addr:postcode":"3012 vj",
    "addr:street":"William Boothlaan",
    "iso:country":"NL",
    "sg:address":"William Boothlaan 12",
    "sg:city":"Rotterdam",
    "sg:orig_category":"Vertaal- And Tolkenbureaus",
    "sg:phone":"+31 10 414 2735",
    "sg:postcode":"3012 VJ",
    "sg:province":"Zuid-Holland",
    "wof:name":"Marielle Crijns Vof",
    "wof:placetype":"venue"
},
  "geometry": {"coordinates":[4.479067,51.915302],"type":"Point"}
}