{
  "type": "Feature",
  "properties": {
    "addr:full":"Prismastr 62 Almere Flevoland 1339 AM",
    "addr:housenumber":"62",
    "addr:postcode":"1339",
    "addr:street":"Prismastr;Flevoland",
    "iso:country":"NL",
    "sg:address":"Prismastr 62",
    "sg:city":"Almere",
    "sg:orig_category":"Woninginrichting",
    "sg:phone":"+31 36 529 6525",
    "sg:postcode":"1339 AM",
    "sg:province":"Flevoland",
    "wof:name":"Casa Design",
    "wof:placetype":"venue"
},
  "geometry": {"coordinates":[5.2933821678,52.39610672],"type":"Point"}
}