{
  "type": "Feature",
  "properties": {
    "addr:full":"Hoofdstr O 14 Winsum Gn Groningen 9951 AH",
    "addr:housenumber":"14",
    "addr:postcode":"gn;9951 ah",
    "iso:country":"NL",
    "sg:address":"Hoofdstr O 14",
    "sg:city":"Winsum Gn",
    "sg:orig_category":"Bloemen En Planten",
    "sg:phone":"+31 595 441 897",
    "sg:postcode":"9951 AH",
    "sg:province":"Groningen",
    "wof:name":"Stekje, 'T",
    "wof:placetype":"venue"
},
  "geometry": {"coordinates":[6.517395,53.334412],"type":"Point"}
}