{
  "type": "Feature",
  "properties": {
    "iso:country":"NL",
    "sg:address":"Garenkokerskd 8",
    "sg:city":"Haarlem",
    "sg:classifiers":[
        {
            "category":"Personal",
            "subcategory":"Nail Salon",
            "type":"Services"
        }
    ],
    "sg:phone":"+31 23 531 5522",
    "sg:postcode":"2013 AM",
    "sg:province":"Noord-Holland",
    "sg:tags":[
        "pedicure"
    ],
    "wof:name":"Tesselaar, G Th",
    "wof:placetype":"venue"
},
  "geometry": {"coordinates":[4.625686,52.386196],"type":"Point"}
}