{
  "type": "Feature",
  "properties": {
    "iso:country":"NL",
    "sg:address":"Marconistr 40",
    "sg:city":"Landgraaf",
    "sg:orig_category":"Verhuur",
    "sg:phone":"+31 45 532 2400",
    "sg:postcode":"6372 PN",
    "sg:province":"Limburg",
    "sg:website":"http://www.franssenfranken.com",
    "wof:name":"Franssen Franken Bv",
    "wof:placetype":"venue"
},
  "geometry": {"coordinates":[6.02641,50.89146],"type":"Point"}
}