{
  "type": "Feature",
  "properties": {
    "addr:full":"Notenpln 155 S Gravenhage South Holland 2555 ZZ",
    "addr:housenumber":"155",
    "addr:postcode":"2555 zz",
    "addr:street":"S Gravenhage",
    "iso:country":"NL",
    "sg:address":"Notenpln 155",
    "sg:city":"S Gravenhage",
    "sg:orig_category":"Kappers",
    "sg:phone":"+31 70 368 1612",
    "sg:postcode":"2555 ZZ",
    "sg:province":"South Holland",
    "wof:name":"G & R",
    "wof:placetype":"venue"
},
  "geometry": {"coordinates":[4.2417001724,52.0663795471],"type":"Point"}
}