{
  "type": "Feature",
  "properties": {
    "addr:full":"Brugstraat 11 Ouderkerk A/D Amstel North Holland 1191 AV",
    "addr:housenumber":"11;a / d;1191",
    "addr:postcode":"av",
    "addr:street":"Brugstraat;Amstel North",
    "iso:country":"NL",
    "sg:address":"Brugstraat 11",
    "sg:city":"Ouderkerk A/D Amstel",
    "sg:orig_category":"Makelaars In Onroerend Goed",
    "sg:phone":"+31 20 496 1244",
    "sg:postcode":"1191 AV",
    "sg:province":"North Holland",
    "wof:name":"C.G. Bellaar Vof",
    "wof:placetype":"venue"
},
  "geometry": {"coordinates":[4.901594,52.297226],"type":"Point"}
}