{
  "type": "Feature",
  "properties": {
    "iso:country":"NL",
    "sg:address":"Brugstraat 11",
    "sg:city":"Ouderkerk A/D Amstel",
    "sg:orig_category":"Makelaars In Onroerend Goed",
    "sg:phone":"+31 20 496 1244",
    "sg:postcode":"1191 AV",
    "sg:province":"North Holland",
    "wof:name":"C.G. Bellaar Vof",
    "wof:placetype":"venue"
},
  "geometry": {"coordinates":[4.901594,52.297226],"type":"Point"}
}