{
  "type": "Feature",
  "properties": {
    "iso:country":"NL",
    "sg:address":"Venkant 7",
    "sg:city":"Sint Michielsgestel",
    "sg:orig_category":"Wegen And Sportterreinen",
    "sg:phone":"+31 73 553 1410",
    "sg:postcode":"5271 SP",
    "sg:province":"North Brabant",
    "wof:name":"Wegenbouwbedrijf Van Breugel Smulders Bv",
    "wof:placetype":"venue"
},
  "geometry": {"coordinates":[5.3604688644,51.6493988037],"type":"Point"}
}