{
  "type": "Feature",
  "properties": {
    "iso:country":"NL",
    "sg:address":"K Smeden 15",
    "sg:city":"Zwolle",
    "sg:orig_category":"Geschenkartikelen",
    "sg:phone":"+31 38 420 3149",
    "sg:postcode":"8011 VC",
    "sg:province":"NL.08",
    "sg:website":"http://www.just4you.nl",
    "wof:name":"Just For You",
    "wof:placetype":"venue"
},
  "geometry": {"coordinates":[6.096871,52.513401],"type":"Point"}
}