{
  "type": "Feature",
  "properties": {
    "addr:full":"F Halsstr 35 Lichtenvoorde Vermont 7131 VT",
    "addr:housenumber":"35",
    "addr:postcode":"7131",
    "addr:street":"Vermont",
    "iso:country":"NL",
    "sg:address":"F Halsstr 35",
    "sg:city":"Lichtenvoorde",
    "sg:orig_category":"Kinderopvang",
    "sg:phone":"+31 900 9864",
    "sg:postcode":"7131 VT",
    "sg:province":"Vermont",
    "wof:name":"Yunio",
    "wof:placetype":"venue"
},
  "geometry": {"coordinates":[-72.451218,43.871769],"type":"Point"}
}