{
  "type": "Feature",
  "properties": {
    "addr:full":"Koningin Julianalaan 343 Voorburg Zuid-Holland 2273 JJ",
    "addr:housenumber":"343",
    "addr:postcode":"2273 jj",
    "addr:street":"Koningin Julianalaan",
    "iso:country":"NL",
    "sg:address":"Koningin Julianalaan 343",
    "sg:city":"Voorburg",
    "sg:orig_category":"Verzekeringen",
    "sg:phone":"+31 70 369 4001",
    "sg:postcode":"2273 JJ",
    "sg:province":"Zuid-Holland",
    "wof:name":"Belpar Spaarhuis Bv",
    "wof:placetype":"venue"
},
  "geometry": {"coordinates":[4.359828,52.075027],"type":"Point"}
}