{
  "type": "Feature",
  "properties": {
    "addr:full":"Terheydensewg 445-447 Breda Noord-Brabant 4825 BK",
    "addr:housenumber":"445-447",
    "addr:postcode":"4825 bk",
    "iso:country":"NL",
    "sg:address":"Terheydensewg 445-447",
    "sg:city":"Breda",
    "sg:orig_category":"Woningtextiel - Fabrieken En Groothandel",
    "sg:phone":"+31 76 579 4444",
    "sg:postcode":"4825 BK",
    "sg:province":"Noord-Brabant",
    "wof:name":"Dehnert & Jansen Bv",
    "wof:placetype":"venue"
},
  "geometry": {"coordinates":[4.7712049484,51.6188583374],"type":"Point"}
}