{
  "type": "Feature",
  "properties": {
    "addr:full":"Pelmolenstr 12A Breda North Brabant 4811 LL",
    "addr:housenumber":"12a",
    "addr:postcode":"4811 ll",
    "addr:street":"Pelmolenstr",
    "iso:country":"NL",
    "sg:address":"Pelmolenstr 12A",
    "sg:city":"Breda",
    "sg:orig_category":"Fitnesscentra",
    "sg:phone":"+31 76 514 0745",
    "sg:postcode":"4811 LL",
    "sg:province":"North Brabant",
    "wof:name":"Savion Gym Survivor",
    "wof:placetype":"venue"
},
  "geometry": {"coordinates":[4.768418,51.58672],"type":"Point"}
}