{
  "type": "Feature",
  "properties": {
    "addr:full":"Leekster Meer 5 Zaandam Noord-Holland 1509 JG",
    "addr:housenumber":"5",
    "addr:postcode":"1509 jg",
    "addr:street":"Meer",
    "iso:country":"NL",
    "sg:address":"Leekster Meer 5",
    "sg:city":"Zaandam",
    "sg:orig_category":"Bestratingen",
    "sg:phone":"+31 75 771 0082",
    "sg:postcode":"1509 JG",
    "sg:province":"Noord-Holland",
    "wof:name":"Wandelee",
    "wof:placetype":"venue"
},
  "geometry": {"coordinates":[4.842589,52.46843],"type":"Point"}
}