{
  "type": "Feature",
  "properties": {
    "addr:full":"Lange Haven 43 Schiedam Zuid-Holland 3111 CB",
    "addr:housenumber":"43",
    "addr:postcode":"3111 cb",
    "addr:street":"Lange Haven",
    "iso:country":"NL",
    "sg:address":"Lange Haven 43",
    "sg:city":"Schiedam",
    "sg:orig_category":"Chemische Producten Gh",
    "sg:phone":"+31 10 473 6111",
    "sg:postcode":"3111 CB",
    "sg:province":"Zuid-Holland",
    "wof:name":"Krul'S Chemicalienhandel Bv",
    "wof:placetype":"venue"
},
  "geometry": {"coordinates":[4.398406,51.914192],"type":"Point"}
}