{
  "type": "Feature",
  "properties": {
    "addr:full":"G Achterberghove 32 Nieuwegein Utrecht 3437 ZE",
    "addr:housenumber":"32",
    "addr:postcode":"3437 ze",
    "addr:street":"Achterberghove",
    "iso:country":"NL",
    "sg:address":"G Achterberghove 32",
    "sg:city":"Nieuwegein",
    "sg:orig_category":"Organisatiebureaus",
    "sg:phone":"+31 30 604 4861",
    "sg:postcode":"3437 ZE",
    "sg:province":"Utrecht",
    "wof:name":"Coltir Bv",
    "wof:placetype":"venue"
},
  "geometry": {"coordinates":[5.0766592026,52.0563240051],"type":"Point"}
}