{
  "type": "Feature",
  "properties": {
    "addr:full":"Kleiwg 43 Rotterdam South Holland 3051 GJ",
    "addr:housenumber":"43",
    "addr:postcode":"3051 gj",
    "addr:street":"Kleiwg",
    "iso:country":"NL",
    "sg:address":"Kleiwg 43",
    "sg:city":"Rotterdam",
    "sg:orig_category":"Poeliers",
    "sg:phone":"+31 10 422 7974",
    "sg:postcode":"3051 GJ",
    "sg:province":"South Holland",
    "wof:name":"Kleiweg Poelierspecialist",
    "wof:placetype":"venue"
},
  "geometry": {"coordinates":[4.481495,51.945152],"type":"Point"}
}