{
  "type": "Feature",
  "properties": {
    "iso:country":"NL",
    "sg:address":"Lindenln 264",
    "sg:city":"Amstelveen",
    "sg:orig_category":"Adviesbureaus Bedrijfsorganisatie",
    "sg:phone":"+31 20 647 0111",
    "sg:postcode":"1185 NH",
    "sg:province":"Noord-Holland",
    "wof:name":"Management Basics",
    "wof:placetype":"venue"
},
  "geometry": {"coordinates":[4.855743,52.29369],"type":"Point"}
}