{
  "type": "Feature",
  "properties": {
    "iso:country":"NL",
    "sg:address":"J Enschedewg 7",
    "sg:city":"Uithoorn",
    "sg:orig_category":"Verhuizingen",
    "sg:phone":"+31 297 514 000",
    "sg:postcode":"1422 DR",
    "sg:province":"Noord-Holland",
    "wof:name":"Rooyen Bv, P A Van",
    "wof:placetype":"venue"
},
  "geometry": {"coordinates":[4.842126,52.244488],"type":"Point"}
}