{
  "type": "Feature",
  "properties": {
    "addr:full":"Kinkhoornstraat 17 Leeuwarden Provincie Friesland 8931 BJ",
    "addr:housenumber":"17",
    "addr:postcode":"8931 bj",
    "addr:street":"Kinkhoornstraat;Provincie Friesland",
    "iso:country":"NL",
    "sg:address":"Kinkhoornstraat 17",
    "sg:city":"Leeuwarden",
    "sg:orig_category":"Wegen And Sportterreinen",
    "sg:phone":"+31 58 288 2365",
    "sg:postcode":"8931 BJ",
    "sg:province":"Provincie Friesland",
    "wof:name":"Bagedo",
    "wof:placetype":"venue"
},
  "geometry": {"coordinates":[5.7797570229,53.1856880188],"type":"Point"}
}