{
  "type": "Feature",
  "properties": {
    "addr:full":"Noordstr 45 Burgh Haamstede Zeeland 4328 AK",
    "addr:housenumber":"45",
    "addr:postcode":"4328 ak",
    "addr:street":"Noordstr;Haamstede",
    "iso:country":"NL",
    "sg:address":"Noordstr 45",
    "sg:city":"Burgh Haamstede",
    "sg:orig_category":"Postkantoren",
    "sg:phone":"+31 111 651 220",
    "sg:postcode":"4328 AK",
    "sg:province":"Zeeland",
    "sg:website":"http://www.postkantoor.nl",
    "wof:name":"Postkantoor",
    "wof:placetype":"venue"
},
  "geometry": {"coordinates":[3.742323,51.699902],"type":"Point"}
}