{
  "type": "Feature",
  "properties": {
    "iso:country":"NL",
    "sg:address":"Heijermansplein 226",
    "sg:city":"Schiedam",
    "sg:orig_category":"Goederenvervoer Over De Weg",
    "sg:phone":"+31 10 470 3012",
    "sg:postcode":"3123 LL",
    "sg:province":"South Holland",
    "wof:name":"Ttv",
    "wof:placetype":"venue"
},
  "geometry": {"coordinates":[4.369782,51.938858],"type":"Point"}
}