{
  "type": "Feature",
  "properties": {
    "addr:full":"Kolevaarserf 38 Ermelo Gelderland 3853 EK",
    "addr:housenumber":"38",
    "addr:postcode":"3853 ek",
    "addr:street":"Kolevaarserf;Gelderland",
    "iso:country":"NL",
    "sg:address":"Kolevaarserf 38",
    "sg:city":"Ermelo",
    "sg:orig_category":"Oli?n Afgewerkte",
    "sg:phone":"+31 341 558 227",
    "sg:postcode":"3853 EK",
    "sg:province":"Gelderland",
    "wof:name":"Last, J",
    "wof:placetype":"venue"
},
  "geometry": {"coordinates":[5.599478,52.299156],"type":"Point"}
}