{
  "type": "Feature",
  "properties": {
    "addr:full":"Nieuwstraat 57 Best Noord-Brabant 5683 KB",
    "addr:housenumber":"57",
    "addr:postcode":"5683 kb",
    "addr:street":"Nieuwstraat",
    "iso:country":"NL",
    "sg:address":"Nieuwstraat 57",
    "sg:city":"Best",
    "sg:orig_category":"Werving And Selectie Van Tijdelijk Personeel And Uitzendkantoren",
    "sg:phone":"+31 499 390 400",
    "sg:postcode":"5683 KB",
    "sg:province":"Noord-Brabant",
    "wof:name":"Creyf'S Interim",
    "wof:placetype":"venue"
},
  "geometry": {"coordinates":[-101.6181335449,31.2242507935],"type":"Point"}
}