{
  "type": "Feature",
  "properties": {
    "addr:full":"Burg Meineszln 45B Rotterdam Zuid-Holland 3022 BB",
    "addr:housenumber":"45b",
    "addr:postcode":"3022 bb",
    "addr:street":"Burg Meineszln",
    "iso:country":"NL",
    "sg:address":"Burg Meineszln 45B",
    "sg:city":"Rotterdam",
    "sg:orig_category":"Kunstgebitten",
    "sg:phone":"+31 10 477 9745",
    "sg:postcode":"3022 BB",
    "sg:province":"Zuid-Holland",
    "sg:website":"http://www.dekunstgebitaanhuisservice.nl",
    "wof:name":"Kunstgebit Aan Huisservice, De",
    "wof:placetype":"venue"
},
  "geometry": {"coordinates":[4.452554,51.918304],"type":"Point"}
}