{
  "type": "Feature",
  "properties": {
    "addr:full":"Boezembocht 23 Rotterdam Zuid-Holland 3034 KA",
    "addr:housenumber":"23",
    "addr:postcode":"3034 ka",
    "addr:street":"Boezembocht",
    "iso:country":"NL",
    "sg:address":"Boezembocht 23",
    "sg:city":"Rotterdam",
    "sg:orig_category":"Metaalgroothandel",
    "sg:phone":"+31 10 240 3210",
    "sg:postcode":"3034 KA",
    "sg:province":"Zuid-Holland",
    "sg:website":"http://www.capricornbv.com",
    "wof:name":"Capricorn",
    "wof:placetype":"venue"
},
  "geometry": {"coordinates":[4.493529,51.941204],"type":"Point"}
}