{
  "type": "Feature",
  "properties": {
    "addr:full":"Nieuwstr 34 Baarn Utrecht 3743 BL",
    "addr:housenumber":"34",
    "addr:postcode":"3743 bl",
    "addr:street":"Nieuwstr",
    "iso:country":"NL",
    "sg:address":"Nieuwstr 34",
    "sg:city":"Baarn",
    "sg:orig_category":"Banket",
    "sg:phone":"+31 35 541 2162",
    "sg:postcode":"3743 BL",
    "sg:province":"Utrecht",
    "wof:name":"Jos Hendricksen",
    "wof:placetype":"venue"
},
  "geometry": {"coordinates":[5.292121,52.21101],"type":"Point"}
}