{
  "type": "Feature",
  "properties": {
    "addr:full":"De Hg Kamp 49 Opende Groningen 9865 BN",
    "addr:housenumber":"49",
    "addr:postcode":"9865 bn",
    "addr:street":"De Hg Kamp",
    "iso:country":"NL",
    "sg:address":"De Hg Kamp 49",
    "sg:city":"Opende",
    "sg:orig_category":"Kantoor- En Secretariaatsservice",
    "sg:phone":"+31 594 657 036",
    "sg:postcode":"9865 BN",
    "sg:province":"Groningen",
    "wof:name":"Nouvelle Delitype",
    "wof:placetype":"venue"
},
  "geometry": {"coordinates":[6.1969399452,53.1715431213],"type":"Point"}
}