{
  "type": "Feature",
  "properties": {
    "addr:full":"Huzarenstr 19 Amersfoort Utrecht 3816 DX",
    "addr:housenumber":"19",
    "addr:postcode":"3816 dx",
    "addr:street":"Huzarenstr",
    "iso:country":"NL",
    "sg:address":"Huzarenstr 19",
    "sg:city":"Amersfoort",
    "sg:orig_category":"Autorijscholen",
    "sg:phone":"+31 33 472 6348",
    "sg:postcode":"3816 DX",
    "sg:province":"Utrecht",
    "wof:name":"Kooiman, Autorijschool Peter",
    "wof:placetype":"venue"
},
  "geometry": {"coordinates":[5.398302,52.154346],"type":"Point"}
}