{
  "type": "Feature",
  "properties": {
    "addr:full":"Bedryvenwg 5 Nistelrode North Brabant 5388 PN",
    "addr:housenumber":"5",
    "addr:postcode":"5388 pn",
    "addr:street":"Bedryvenwg",
    "iso:country":"NL",
    "sg:address":"Bedryvenwg 5",
    "sg:city":"Nistelrode",
    "sg:orig_category":"Keukens",
    "sg:phone":"+31 412 611 756",
    "sg:postcode":"5388 PN",
    "sg:province":"North Brabant",
    "wof:name":"Robben, Harry",
    "wof:placetype":"venue"
},
  "geometry": {"coordinates":[5.562755,51.712719],"type":"Point"}
}