{
  "type": "Feature",
  "properties": {
    "iso:country":"NL",
    "sg:address":"Madeliefstr 32",
    "sg:city":"Krommenie",
    "sg:orig_category":"Postzegels",
    "sg:phone":"+31 75 628 7548",
    "sg:postcode":"1562 RW",
    "sg:province":"North Holland",
    "wof:name":"Westerheiden, E",
    "wof:placetype":"venue"
},
  "geometry": {"coordinates":[4.758877,52.508144],"type":"Point"}
}