{
  "type": "Feature",
  "properties": {
    "addr:full":"Prinsengr 356S Amsterdam Noord-Holland 1016 JA",
    "addr:housenumber":"356s",
    "addr:postcode":"1016 ja",
    "addr:street":"Prinsengr",
    "iso:country":"NL",
    "sg:address":"Prinsengr 356S",
    "sg:city":"Amsterdam",
    "sg:orig_category":"Beeldende Kunstenaars",
    "sg:phone":"+31 20 627 9526",
    "sg:postcode":"1016 JA",
    "sg:province":"Noord-Holland",
    "wof:name":"Stam",
    "wof:placetype":"venue"
},
  "geometry": {"coordinates":[4.882158,52.367977],"type":"Point"}
}