{
  "type": "Feature",
  "properties": {
    "addr:full":"Walderstraat 24 Lochem Gelderland 7241 BJ",
    "addr:housenumber":"24",
    "addr:postcode":"7241 bj",
    "addr:street":"Walderstraat;Gelderland",
    "iso:country":"NL",
    "sg:address":"Walderstraat 24",
    "sg:city":"Lochem",
    "sg:orig_category":"Bloemen And Planten",
    "sg:phone":"+31 573 251 173",
    "sg:postcode":"7241 BJ",
    "sg:province":"Gelderland",
    "wof:name":"Firma H. Steenblik En Zoon",
    "wof:placetype":"venue"
},
  "geometry": {"coordinates":[6.413046,52.162369],"type":"Point"}
}