{
  "type": "Feature",
  "properties": {
    "addr:full":"Ekkersryt 4603 Son Noord-Brabant 5692 DR",
    "addr:postcode":"4603 son;5692 dr",
    "iso:country":"NL",
    "sg:address":"Ekkersryt 4603",
    "sg:city":"Son",
    "sg:orig_category":"Zonweringen",
    "sg:phone":"+31 499 460 000",
    "sg:postcode":"5692 DR",
    "sg:province":"Noord-Brabant",
    "sg:website":"http://www.genzo.nl",
    "wof:name":"Genzo Zonwering",
    "wof:placetype":"venue"
},
  "geometry": {"coordinates":[-101.937622,35.189621],"type":"Point"}
}