{
  "type": "Feature",
  "properties": {
    "addr:full":"Hageland 113Bg Amsterdam North Holland 1066 SB",
    "addr:housenumber":"113bg",
    "addr:postcode":"1066 sb",
    "addr:street":"Hageland",
    "iso:country":"NL",
    "sg:address":"Hageland 113Bg",
    "sg:city":"Amsterdam",
    "sg:orig_category":"Zuivelproducten",
    "sg:phone":"+31 20 669 6631",
    "sg:postcode":"1066 SB",
    "sg:province":"North Holland",
    "wof:name":"Kastino Sloten",
    "wof:placetype":"venue"
},
  "geometry": {"coordinates":[4.812117,52.345566],"type":"Point"}
}