{
  "type": "Feature",
  "properties": {
    "addr:full":"Zwingliwg 45 Amstelveen Noord-Holland 1185 BX",
    "addr:housenumber":"45",
    "addr:postcode":"1185 bx",
    "addr:street":"Zwingliwg",
    "iso:country":"NL",
    "sg:address":"Zwingliwg 45",
    "sg:city":"Amstelveen",
    "sg:orig_category":"Adviesbureaus Verzekeringen",
    "sg:phone":"+31 20 643 9552",
    "sg:postcode":"1185 BX",
    "sg:province":"Noord-Holland",
    "wof:name":"Aabn",
    "wof:placetype":"venue"
},
  "geometry": {"coordinates":[4.862379,52.295113],"type":"Point"}
}