{
  "type": "Feature",
  "properties": {
    "addr:full":"Htg V Beyerenstr 37 Ter Aar Zuid-Holland 2461 EM",
    "addr:housenumber":"37",
    "addr:postcode":"aar;2461 em",
    "addr:street":"Beyerenstr;Ter",
    "iso:country":"NL",
    "sg:address":"Htg V Beyerenstr 37",
    "sg:city":"Ter Aar",
    "sg:orig_category":"Honden- En Kattentrimsalons",
    "sg:phone":"+31 172 603 387",
    "sg:postcode":"2461 EM",
    "sg:province":"Zuid-Holland",
    "wof:name":"Th?r?se",
    "wof:placetype":"venue"
},
  "geometry": {"coordinates":[4.709815,52.19268],"type":"Point"}
}