{
  "type": "Feature",
  "properties": {
    "addr:full":"Thornstraat 10 Kerk Avezaath Gelderland 4012 EJ",
    "addr:housenumber":"10",
    "addr:postcode":"4012 ej",
    "addr:street":"Thornstraat",
    "iso:country":"NL",
    "sg:address":"Thornstraat 10",
    "sg:city":"Kerk Avezaath",
    "sg:orig_category":"Fotostudio'S And Fotografen",
    "sg:phone":"+31 344 682 142",
    "sg:postcode":"4012 EJ",
    "sg:province":"Gelderland",
    "wof:name":"Fotografie Mathijsen",
    "wof:placetype":"venue"
},
  "geometry": {"coordinates":[5.379122,51.89846],"type":"Point"}
}