{
  "type": "Feature",
  "properties": {
    "addr:full":"Ambachtsstr 16 Stadskanaal Groningen 9502 ER",
    "addr:housenumber":"16",
    "addr:postcode":"9502 er",
    "addr:street":"Ambachtsstr",
    "iso:country":"NL",
    "sg:address":"Ambachtsstr 16",
    "sg:city":"Stadskanaal",
    "sg:orig_category":"Metaalbewerking",
    "sg:phone":"+31 599 631 010",
    "sg:postcode":"9502 ER",
    "sg:province":"Groningen",
    "wof:name":"Haveha Bv",
    "wof:placetype":"venue"
},
  "geometry": {"coordinates":[6.97933,52.975899],"type":"Point"}
}