{
  "type": "Feature",
  "properties": {
    "addr:full":"Vierlingsbeeksewg 73B Overloon Noord-Brabant 5825 AV",
    "addr:housenumber":"73b",
    "addr:postcode":"5825 av",
    "addr:street":"Vierlingsbeeksewg",
    "iso:country":"NL",
    "sg:address":"Vierlingsbeeksewg 73B",
    "sg:city":"Overloon",
    "sg:orig_category":"Onroerende Goederen",
    "sg:phone":"+31 478 641 663",
    "sg:postcode":"5825 AV",
    "sg:province":"Noord-Brabant",
    "wof:name":"Al-Fra Overloon Bv",
    "wof:placetype":"venue"
},
  "geometry": {"coordinates":[5.969026,51.580105],"type":"Point"}
}