{
  "type": "Feature",
  "properties": {
    "iso:country":"NL",
    "sg:address":"Sofiastr 8",
    "sg:city":"St Oedenrode",
    "sg:orig_category":"Verloskundigen",
    "sg:phone":"+31 413 472 860",
    "sg:postcode":"5491 JM",
    "sg:province":"Noord-Brabant",
    "wof:name":"Peppelaar, De",
    "wof:placetype":"venue"
},
  "geometry": {"coordinates":[5.457628,51.571522],"type":"Point"}
}