{
  "type": "Feature",
  "properties": {
    "addr:full":"Industriewg 25 Stramproy Limburg 6039 AP",
    "addr:housenumber":"25",
    "addr:postcode":"6039 ap",
    "addr:street":"Industriewg",
    "iso:country":"NL",
    "sg:address":"Industriewg 25",
    "sg:city":"Stramproy",
    "sg:orig_category":"Meubellakkerijen En -Spuiterijen",
    "sg:phone":"+31 495 561 791",
    "sg:postcode":"6039 AP",
    "sg:province":"Limburg",
    "sg:website":"http://www.seevens.nl",
    "wof:name":"Seevens",
    "wof:placetype":"venue"
},
  "geometry": {"coordinates":[5.717074,51.198723],"type":"Point"}
}