{
  "type": "Feature",
  "properties": {
    "addr:full":"Ritsevoort 10 Alkmaar Noord-Holland 1811 DN",
    "addr:housenumber":"10",
    "addr:postcode":"1811 dn",
    "addr:street":"Ritsevoort",
    "iso:country":"NL",
    "sg:address":"Ritsevoort 10",
    "sg:city":"Alkmaar",
    "sg:classifiers":[
        {
            "category":"Fast Food",
            "type":"Food & Drink"
        }
    ],
    "sg:phone":"+31 72 515 1936",
    "sg:postcode":"1811 DN",
    "sg:province":"Noord-Holland",
    "sg:tags":[
        "afhaal",
        "restaurant"
    ],
    "wof:name":"Afhaalcentrum Tempo Doeloe",
    "wof:placetype":"venue"
},
  "geometry": {"coordinates":[4.742951,52.63073],"type":"Point"}
}