{
  "type": "Feature",
  "properties": {
    "addr:full":"Nyverheidsstr 1 Hardenberg Overijssel 7772 TP",
    "addr:housenumber":"1",
    "addr:postcode":"7772 tp",
    "addr:street":"Nyverheidsstr",
    "iso:country":"NL",
    "sg:address":"Nyverheidsstr 1",
    "sg:city":"Hardenberg",
    "sg:orig_category":"Autoschade- Herstelbedrijven",
    "sg:phone":"+31 523 263 775",
    "sg:postcode":"7772 TP",
    "sg:province":"Overijssel",
    "sg:website":"http://www.auto-gruppen.nl",
    "wof:name":"Gruppen Bv",
    "wof:placetype":"venue"
},
  "geometry": {"coordinates":[6.629996,52.558968],"type":"Point"}
}