{
  "type": "Feature",
  "properties": {
    "addr:full":"Pallieterstraat 2 Amstelveen Noord-Holland 1183  L",
    "addr:housenumber":"2;1183",
    "addr:postcode":"l",
    "addr:street":"Pallieterstraat",
    "iso:country":"NL",
    "sg:address":"Pallieterstraat 2",
    "sg:city":"Amstelveen",
    "sg:orig_category":"Alternatieve Geneeskunde Thuisbehandeling",
    "sg:phone":"+31 20 441 6583",
    "sg:postcode":"1183  L",
    "sg:province":"Noord-Holland",
    "wof:name":"D. Jesurun Homeopathie",
    "wof:placetype":"venue"
},
  "geometry": {"coordinates":[4.876748,52.304844],"type":"Point"}
}