{
  "type": "Feature",
  "properties": {
    "addr:full":"Bosschendijk 171 Oudenbosch Noord-Brabant 4731 DD",
    "addr:housenumber":"171",
    "addr:postcode":"4731 dd",
    "addr:street":"Bosschendijk",
    "iso:country":"NL",
    "sg:address":"Bosschendijk 171",
    "sg:city":"Oudenbosch",
    "sg:orig_category":"Waterbeheer",
    "sg:phone":"+31 76 572 7810",
    "sg:postcode":"4731 DD",
    "sg:province":"Noord-Brabant",
    "wof:name":"Nv Waterleidingmaatschappij Noord-West Brabant",
    "wof:placetype":"venue"
},
  "geometry": {"coordinates":[4.54600811,51.5900917053],"type":"Point"}
}