{
  "type": "Feature",
  "properties": {
    "iso:country":"NL",
    "sg:address":"Vyfhuizenberg 99",
    "sg:city":"Roosendaal",
    "sg:orig_category":"Machineonderhoud En -Reparatie",
    "sg:phone":"+31 6 53120334",
    "sg:postcode":"4708 AJ",
    "sg:province":"Noord-Brabant",
    "wof:name":"Blommerde Bv",
    "wof:placetype":"venue"
},
  "geometry": {"coordinates":[4.445969,51.521336],"type":"Point"}
}