{
  "type": "Feature",
  "properties": {
    "addr:full":"Hommelsewg 54 Arnhem Gelderland 6821 LM",
    "addr:housenumber":"54",
    "addr:postcode":"6821 lm",
    "addr:street":"Hommelsewg",
    "iso:country":"NL",
    "sg:address":"Hommelsewg 54",
    "sg:city":"Arnhem",
    "sg:orig_category":"Kappers",
    "sg:phone":"+31 26 445 4183",
    "sg:postcode":"6821 LM",
    "sg:province":"Gelderland",
    "wof:name":"Duray",
    "wof:placetype":"venue"
},
  "geometry": {"coordinates":[5.9144678116,51.9864120483],"type":"Point"}
}