{
  "type": "Feature",
  "properties": {
    "iso:country":"NL",
    "sg:address":"Lieftinckstraat 3",
    "sg:city":"Naaldwijk",
    "sg:orig_category":"Bloemen And Planten",
    "sg:phone":"+31 174 628 987",
    "sg:postcode":"2672 DT",
    "sg:province":"Zuid-Holland",
    "wof:name":"Kwekerij Van Vliet Naaldwijk Bv",
    "wof:placetype":"venue"
},
  "geometry": {"coordinates":[4.221201,51.992798],"type":"Point"}
}