{
  "type": "Feature",
  "properties": {
    "iso:country":"NL",
    "sg:address":"Spoorstraat 24",
    "sg:city":"Schoonhoven",
    "sg:orig_category":"Boekhouders",
    "sg:phone":"+31 182 382 315",
    "sg:postcode":"2871 TN",
    "sg:province":"South Holland",
    "wof:name":"Administratiekantoor Zuid-Holland",
    "wof:placetype":"venue"
},
  "geometry": {"coordinates":[4.8488531113,51.9484596252],"type":"Point"}
}