{
  "type": "Feature",
  "properties": {
    "addr:full":"Kerkstr 27 Panningen Limburg 5981 CD",
    "addr:housenumber":"27",
    "addr:postcode":"5981 cd",
    "addr:street":"Kerkstr",
    "iso:country":"NL",
    "sg:address":"Kerkstr 27",
    "sg:city":"Panningen",
    "sg:orig_category":"Kinderopvang",
    "sg:phone":"+31 77 462 1032",
    "sg:postcode":"5981 CD",
    "sg:province":"Limburg",
    "wof:name":"Bobo",
    "wof:placetype":"venue"
},
  "geometry": {"coordinates":[5.976476,51.327648],"type":"Point"}
}