{
  "type": "Feature",
  "properties": {
    "addr:full":"Tiendwg 8A Naaldwyk South Holland 2671 SB",
    "addr:housenumber":"8a",
    "addr:postcode":"2671 sb",
    "addr:street":"Tiendwg",
    "iso:country":"NL",
    "sg:address":"Tiendwg 8A",
    "sg:city":"Naaldwyk",
    "sg:classifiers":[
        {
            "category":"Professional",
            "subcategory":"Accounting & Tax Preparation",
            "type":"Services"
        }
    ],
    "sg:phone":"+31 174 640 139",
    "sg:postcode":"2671 SB",
    "sg:province":"South Holland",
    "sg:tags":[
        "accountant",
        "en",
        "-kantoren",
        "register-"
    ],
    "wof:name":"Lodder & Co",
    "wof:placetype":"venue"
},
  "geometry": {"coordinates":[4.220108,51.990734],"type":"Point"}
}