{
  "type": "Feature",
  "properties": {
    "addr:full":"H De Vrieswg 45 Haren Gn Groningen 9751 PR",
    "addr:housenumber":"45",
    "addr:postcode":"9751 pr",
    "iso:country":"NL",
    "sg:address":"H De Vrieswg 45",
    "sg:city":"Haren Gn",
    "sg:orig_category":"Psychologen",
    "sg:phone":"+31 592 614 492",
    "sg:postcode":"9751 PR",
    "sg:province":"Groningen",
    "wof:name":"Buma, Drs F",
    "wof:placetype":"venue"
},
  "geometry": {"coordinates":[6.608802,53.178234],"type":"Point"}
}