{
  "type": "Feature",
  "properties": {
    "addr:full":"Wermenbossestr 18A Goirle North Brabant 5051 BA",
    "addr:housenumber":"18a",
    "addr:postcode":"5051 ba",
    "addr:street":"Wermenbossestr",
    "iso:country":"NL",
    "sg:address":"Wermenbossestr 18A",
    "sg:city":"Goirle",
    "sg:classifiers":[
        {
            "category":"Professional",
            "subcategory":"Accounting & Tax Preparation",
            "type":"Services"
        }
    ],
    "sg:phone":"+31 13 534 7659",
    "sg:postcode":"5051 BA",
    "sg:province":"North Brabant",
    "sg:tags":[
        "accountant",
        "en",
        "-kantoren",
        "register-"
    ],
    "wof:name":"Beekmans Bv, Drs E M C A",
    "wof:placetype":"venue"
},
  "geometry": {"coordinates":[5.053557,51.528896],"type":"Point"}
}