{
  "type": "Feature",
  "properties": {
    "addr:full":"Cort Van Der Lindenlaan 7 Baarn Utrecht 3741 TT",
    "addr:housenumber":"7",
    "addr:postcode":"3741 tt",
    "addr:street":"Cort Van Der Lindenlaan",
    "iso:country":"NL",
    "sg:address":"Cort Van Der Lindenlaan 7",
    "sg:city":"Baarn",
    "sg:orig_category":"Boekhouders",
    "sg:phone":"+31 35 541 7193",
    "sg:postcode":"3741 TT",
    "sg:province":"Utrecht",
    "wof:name":"Serv.B. Adm. Autom. S. Van Zijst",
    "wof:placetype":"venue"
},
  "geometry": {"coordinates":[5.290127,52.215633],"type":"Point"}
}