{
  "type": "Feature",
  "properties": {
    "iso:country":"NL",
    "sg:address":"Brielse Meer 4",
    "sg:city":"Zaandam",
    "sg:orig_category":"Artiestenbureaus",
    "sg:phone":"+31 75 615 6542",
    "sg:postcode":"1509 GH",
    "sg:province":"Noord-Holland",
    "wof:name":"Czaar Peter Operette",
    "wof:placetype":"venue"
},
  "geometry": {"coordinates":[4.839435,52.470406],"type":"Point"}
}