{
  "type": "Feature",
  "properties": {
    "addr:full":"Vlierwerf 5 B/C Roosendaal Noord-Brabant 4704 SB",
    "addr:housenumber":"5 b / c",
    "addr:postcode":"4704 sb",
    "addr:street":"Vlierwerf",
    "iso:country":"NL",
    "sg:address":"Vlierwerf 5 B/C",
    "sg:city":"Roosendaal",
    "sg:orig_category":"Autopoetsbedrijven",
    "sg:phone":"+31 165 548 895",
    "sg:postcode":"4704 SB",
    "sg:province":"Noord-Brabant",
    "wof:name":"Vlamings",
    "wof:placetype":"venue"
},
  "geometry": {"coordinates":[4.455331,51.555721],"type":"Point"}
}