{
  "type": "Feature",
  "properties": {
    "addr:full":"Boodtlaan 12 De Koog North Holland 1796 BE",
    "addr:housenumber":"12",
    "addr:postcode":"1796",
    "addr:street":"Boodtlaan",
    "iso:country":"NL",
    "sg:address":"Boodtlaan 12",
    "sg:city":"De Koog",
    "sg:classifiers":[
        {
            "category":"Fast Food",
            "type":"Food & Drink"
        }
    ],
    "sg:phone":"+31 222 317 780",
    "sg:postcode":"1796 BE",
    "sg:province":"North Holland",
    "sg:tags":[
        "afhaal",
        "restaurant"
    ],
    "wof:name":"Paal 20",
    "wof:placetype":"venue"
},
  "geometry": {"coordinates":[4.763573,53.100761],"type":"Point"}
}