{
  "type": "Feature",
  "properties": {
    "addr:full":"Smaragdpln 241 Utrecht Utrecht 3523 EJ",
    "addr:housenumber":"241",
    "addr:postcode":"3523 ej",
    "iso:country":"NL",
    "sg:address":"Smaragdpln 241",
    "sg:city":"Utrecht",
    "sg:orig_category":"Meubelen",
    "sg:phone":"+31 30 288 1499",
    "sg:postcode":"3523 EJ",
    "sg:province":"Utrecht",
    "sg:website":"http://www.terbeek-meubelen.nl",
    "wof:name":"Terbeek Koloniale Meubelen",
    "wof:placetype":"venue"
},
  "geometry": {"coordinates":[5.123456,52.072754],"type":"Point"}
}