{
  "type": "Feature",
  "properties": {
    "addr:full":"Passage Molenpoort 105 Nijmegen Gelderland 6511 HX",
    "addr:housenumber":"105",
    "addr:postcode":"6511 hx",
    "addr:street":"Passage Molenpoort;Gelderland",
    "iso:country":"NL",
    "sg:address":"Passage Molenpoort 105",
    "sg:city":"Nijmegen",
    "sg:orig_category":"Babyartikelen Detailhandel",
    "sg:phone":"+31 24 360 3725",
    "sg:postcode":"6511 HX",
    "sg:province":"Gelderland",
    "wof:name":"Minor Jeugdmode",
    "wof:placetype":"venue"
},
  "geometry": {"coordinates":[5.8627,51.844601],"type":"Point"}
}