{
  "type": "Feature",
  "properties": {
    "addr:full":"Kalverstr 6 Veghel Noord-Brabant 5461 JL",
    "addr:housenumber":"6",
    "addr:postcode":"5461 jl",
    "addr:street":"Kalverstr",
    "iso:country":"NL",
    "sg:address":"Kalverstr 6",
    "sg:city":"Veghel",
    "sg:orig_category":"Wasmachines En Wasdrogers - Onderhoud En Reparatie",
    "sg:phone":"+31 413 367 431",
    "sg:postcode":"5461 JL",
    "sg:province":"Noord-Brabant",
    "wof:name":"Kovac",
    "wof:placetype":"venue"
},
  "geometry": {"coordinates":[5.5426177979,51.6167411804],"type":"Point"}
}