{
  "type": "Feature",
  "properties": {
    "addr:full":"Meidoornln 1 Zaandyk North Holland 1544 AX",
    "addr:housenumber":"1",
    "addr:postcode":"1544 ax",
    "addr:street":"Meidoornln;North",
    "iso:country":"NL",
    "sg:address":"Meidoornln 1",
    "sg:city":"Zaandyk",
    "sg:orig_category":"Wijnkoperijen En -Groothandel",
    "sg:phone":"+31 75 628 2178",
    "sg:postcode":"1544 AX",
    "sg:province":"North Holland",
    "wof:name":"Nicolas, A",
    "wof:placetype":"venue"
},
  "geometry": {"coordinates":[4.8072347641,52.4723854065],"type":"Point"}
}