{
  "type": "Feature",
  "properties": {
    "addr:full":"De Ekster 16 Surhuisterveen Friesland 9231 JT",
    "addr:housenumber":"16",
    "addr:postcode":"9231 jt",
    "addr:street":"De Ekster",
    "iso:country":"NL",
    "sg:address":"De Ekster 16",
    "sg:city":"Surhuisterveen",
    "sg:orig_category":"Kantoor- En Secretariaatsservice",
    "sg:phone":"+31 512 364 007",
    "sg:postcode":"9231 JT",
    "sg:province":"Friesland",
    "wof:name":"Pool-Witteveen, A",
    "wof:placetype":"venue"
},
  "geometry": {"coordinates":[6.1685428619,53.1875076294],"type":"Point"}
}