{
  "type": "Feature",
  "properties": {
    "iso:country":"NL",
    "sg:address":"Malakkastr 6",
    "sg:city":"Utrecht",
    "sg:orig_category":"Kinderopvang",
    "sg:phone":"+31 30 291 7154",
    "sg:postcode":"3531 HM",
    "sg:province":"Utrecht",
    "wof:name":"Portes",
    "wof:placetype":"venue"
},
  "geometry": {"coordinates":[5.095227,52.090046],"type":"Point"}
}