{
  "type": "Feature",
  "properties": {
    "addr:full":"Sluisdijkstraat 77 Den Helder Noord-Holland 1781 EE",
    "addr:housenumber":"77",
    "addr:postcode":"1781 ee",
    "addr:street":"Sluisdijkstraat",
    "iso:country":"NL",
    "sg:address":"Sluisdijkstraat 77",
    "sg:city":"Den Helder",
    "sg:orig_category":"Kappers",
    "sg:phone":"+31 223 612 616",
    "sg:postcode":"1781 EE",
    "sg:province":"Noord-Holland",
    "wof:name":"L Mostert",
    "wof:placetype":"venue"
},
  "geometry": {"coordinates":[4.764351,52.955677],"type":"Point"}
}