{
  "type": "Feature",
  "properties": {
    "iso:country":"NL",
    "sg:address":"Turnhoutlaan 62",
    "sg:city":"Eindhoven",
    "sg:orig_category":"Boekhouders",
    "sg:phone":"+31 40 241 0757",
    "sg:postcode":"5628 RL",
    "sg:province":"Noord-Brabant",
    "wof:name":"Abr Administratie En Advies Bv",
    "wof:placetype":"venue"
},
  "geometry": {"coordinates":[5.480145,51.47884],"type":"Point"}
}