{
  "type": "Feature",
  "properties": {
    "addr:full":"Leuvensbroek 1028 Nijmegen Gelderland 6546 XB",
    "addr:housenumber":"1028",
    "addr:postcode":"6546 xb",
    "addr:street":"Leuvensbroek;Gelderland",
    "iso:country":"NL",
    "sg:address":"Leuvensbroek 1028",
    "sg:city":"Nijmegen",
    "sg:orig_category":"Postkantoren",
    "sg:phone":"+31 24 371 4459",
    "sg:postcode":"6546 XB",
    "sg:province":"Gelderland",
    "wof:name":"Postagentschap",
    "wof:placetype":"venue"
},
  "geometry": {"coordinates":[5.781014,51.832485],"type":"Point"}
}