{
  "type": "Feature",
  "properties": {
    "addr:full":"Nijverheidsstraat 2 Rijssen NL.08 7461 AE",
    "addr:housenumber":"2;nl.08",
    "addr:postcode":"7461 ae",
    "addr:street":"Nijverheidsstraat",
    "iso:country":"NL",
    "sg:address":"Nijverheidsstraat 2",
    "sg:city":"Rijssen",
    "sg:orig_category":"Autokeuringen",
    "sg:phone":"+31 548 513 679",
    "sg:postcode":"7461 AE",
    "sg:province":"NL.08",
    "wof:name":"Automobielbedrijf G.J. Ten Hove",
    "wof:placetype":"venue"
},
  "geometry": {"coordinates":[6.505679,52.311916],"type":"Point"}
}