{
  "type": "Feature",
  "properties": {
    "addr:full":"Lange Pad 28 Helvoirt North Brabant 5268 GE",
    "addr:housenumber":"28",
    "addr:postcode":"5268",
    "addr:street":"Lange Pad",
    "iso:country":"NL",
    "sg:address":"Lange Pad 28",
    "sg:city":"Helvoirt",
    "sg:orig_category":"Wegen And Sportterreinen",
    "sg:phone":"+31 411 644 122",
    "sg:postcode":"5268 GE",
    "sg:province":"North Brabant",
    "wof:name":"H. Klerks",
    "wof:placetype":"venue"
},
  "geometry": {"coordinates":[5.2234611511,51.626209259],"type":"Point"}
}