{
  "type": "Feature",
  "properties": {
    "iso:country":"NL",
    "sg:address":"Parkstr 68",
    "sg:city":"Zaandam",
    "sg:orig_category":"Beeldende Kunstenaars",
    "sg:phone":"+31 75 616 4064",
    "sg:postcode":"1506 WE",
    "sg:province":"North Holland",
    "wof:name":"Noor Bos",
    "wof:placetype":"venue"
},
  "geometry": {"coordinates":[4.816704,52.444324],"type":"Point"}
}