{
  "type": "Feature",
  "properties": {
    "addr:full":"Nieuwstr 6 Kerkwyk Gelderland 5315 AH",
    "addr:housenumber":"6",
    "addr:postcode":"5315 ah",
    "addr:street":"Nieuwstr;Gelderland",
    "iso:country":"NL",
    "sg:address":"Nieuwstr 6",
    "sg:city":"Kerkwyk",
    "sg:orig_category":"Beveiliging",
    "sg:phone":"+31 418 644 113",
    "sg:postcode":"5315 AH",
    "sg:province":"Gelderland",
    "wof:name":"Quik",
    "wof:placetype":"venue"
},
  "geometry": {"coordinates":[5.222269,51.773506],"type":"Point"}
}