{
  "type": "Feature",
  "properties": {
    "iso:country":"NL",
    "sg:address":"Nieuwenhagerheidestraat 49",
    "sg:city":"Landgraaf",
    "sg:orig_category":"Onderhoud And Reparatie Kantoorapparatuur",
    "sg:phone":"+31 45 569 0699",
    "sg:postcode":"6374 EB",
    "sg:province":"Limburg",
    "wof:name":"Service Centre Zuid Nederland Nv",
    "wof:placetype":"venue"
},
  "geometry": {"coordinates":[6.037458,50.912556],"type":"Point"}
}