{
  "type": "Feature",
  "properties": {
    "addr:full":"Nieuwenhagerheidestraat 49 Landgraaf Limburg 6374 EB",
    "addr:housenumber":"49",
    "addr:postcode":"6374 eb",
    "addr:street":"Nieuwenhagerheidestraat",
    "iso:country":"NL",
    "sg:address":"Nieuwenhagerheidestraat 49",
    "sg:city":"Landgraaf",
    "sg:orig_category":"Onderhoud And Reparatie Kantoorapparatuur",
    "sg:phone":"+31 45 569 0699",
    "sg:postcode":"6374 EB",
    "sg:province":"Limburg",
    "wof:name":"Service Centre Zuid Nederland Nv",
    "wof:placetype":"venue"
},
  "geometry": {"coordinates":[6.037458,50.912556],"type":"Point"}
}