{
  "type": "Feature",
  "properties": {
    "addr:full":"Master De Jongwei 31 De Tike Friesland 9219 VM",
    "addr:housenumber":"31",
    "addr:postcode":"9219 vm",
    "addr:street":"Master De Jongwei",
    "iso:country":"NL",
    "sg:address":"Master De Jongwei 31",
    "sg:city":"De Tike",
    "sg:orig_category":"Artiestenbureaus",
    "sg:phone":"+31 512 372 940",
    "sg:postcode":"9219 VM",
    "sg:province":"Friesland",
    "wof:name":"Markant",
    "wof:placetype":"venue"
},
  "geometry": {"coordinates":[6.036639,53.154404],"type":"Point"}
}