{
  "type": "Feature",
  "properties": {
    "iso:country":"NL",
    "sg:address":"Noordeinde 121",
    "sg:city":"Roelofarendsveen",
    "sg:orig_category":"Bloemen En Planten - Groothandel",
    "sg:phone":"+31 71 331 2546",
    "sg:postcode":"2371 CP",
    "sg:province":"Zuid-Holland",
    "wof:name":"Meer, Ruud Van Der",
    "wof:placetype":"venue"
},
  "geometry": {"coordinates":[4.629943,52.198086],"type":"Point"}
}