{
  "type": "Feature",
  "properties": {
    "addr:full":"Lindenln 370 Amstelveen North Holland 1185 NM",
    "addr:housenumber":"370",
    "addr:postcode":"1185",
    "iso:country":"NL",
    "sg:address":"Lindenln 370",
    "sg:city":"Amstelveen",
    "sg:orig_category":"Hoortoestellen",
    "sg:phone":"+31 20 441 6786",
    "sg:postcode":"1185 NM",
    "sg:province":"North Holland",
    "wof:name":"Beter Horen",
    "wof:placetype":"venue"
},
  "geometry": {"coordinates":[4.861324,52.295837],"type":"Point"}
}