{
  "type": "Feature",
  "properties": {
    "addr:full":"Hornstr 99 Zwolle Overijssel 8022 CX",
    "addr:housenumber":"99",
    "addr:postcode":"8022 cx",
    "addr:street":"Hornstr",
    "iso:country":"NL",
    "sg:address":"Hornstr 99",
    "sg:city":"Zwolle",
    "sg:orig_category":"Webdesign Bureaus",
    "sg:phone":"+31 38 455 0463",
    "sg:postcode":"8022 CX",
    "sg:province":"Overijssel",
    "sg:website":"http://www.avmwebdesign.nl",
    "wof:name":"Algra En Van Munster Vof",
    "wof:placetype":"venue"
},
  "geometry": {"coordinates":[6.1019282341,52.522403717],"type":"Point"}
}