{
  "type": "Feature",
  "properties": {
    "addr:full":"Sneeuwbergln 1B Vaals Limburg 6291 HB",
    "addr:housenumber":"1b",
    "addr:postcode":"6291 hb",
    "addr:street":"Sneeuwbergln",
    "iso:country":"NL",
    "sg:address":"Sneeuwbergln 1B",
    "sg:city":"Vaals",
    "sg:orig_category":"Verenigingsgebouwen",
    "sg:phone":"+31 43 306 2109",
    "sg:postcode":"6291 HB",
    "sg:province":"Limburg",
    "wof:name":"Spuugh 70",
    "wof:placetype":"venue"
},
  "geometry": {"coordinates":[6.021153,50.775284],"type":"Point"}
}