{
  "type": "Feature",
  "properties": {
    "addr:full":"Seeligsngl 7 Breda Noord-Brabant 4811 CN",
    "addr:housenumber":"7",
    "addr:postcode":"4811 cn",
    "addr:street":"Seeligsngl",
    "iso:country":"NL",
    "sg:address":"Seeligsngl 7",
    "sg:city":"Breda",
    "sg:orig_category":"Houtplaatmaterialen",
    "sg:phone":"+31 76 520 4020",
    "sg:postcode":"4811 CN",
    "sg:province":"Noord-Brabant",
    "sg:website":"http://wwwmikas.nl",
    "wof:name":"Mikas",
    "wof:placetype":"venue"
},
  "geometry": {"coordinates":[4.771685,51.591351],"type":"Point"}
}