{
  "type": "Feature",
  "properties": {
    "addr:full":"Pepergawg 49 Steggerda Friesland 8395 PB",
    "addr:housenumber":"49",
    "addr:postcode":"8395 pb",
    "addr:street":"Pepergawg",
    "iso:country":"NL",
    "sg:address":"Pepergawg 49",
    "sg:city":"Steggerda",
    "sg:orig_category":"Hoefsmederijen",
    "sg:phone":"+31 6 54901436",
    "sg:postcode":"8395 PB",
    "sg:province":"Friesland",
    "wof:name":"Rijtsma",
    "wof:placetype":"venue"
},
  "geometry": {"coordinates":[-36.777691,-7.16501],"type":"Point"}
}