{
  "type": "Feature",
  "properties": {
    "iso:country":"NL",
    "sg:address":"Liendenlaan 60",
    "sg:city":"Tiel",
    "sg:orig_category":"Bedrijfs- And Managementsconsultants",
    "sg:phone":"+31 344 618 447",
    "sg:postcode":"4006 CR",
    "sg:province":"Gelderland",
    "wof:name":"Succesful Colours",
    "wof:placetype":"venue"
},
  "geometry": {"coordinates":[5.409411,51.878098],"type":"Point"}
}