{
  "type": "Feature",
  "properties": {
    "addr:full":"Prins Bernhardstraat 17 Tubbergen Overijssel 7651 ED",
    "addr:housenumber":"17",
    "addr:postcode":"7651 ed",
    "addr:street":"Prins Bernhardstraat",
    "iso:country":"NL",
    "sg:address":"Prins Bernhardstraat 17",
    "sg:city":"Tubbergen",
    "sg:orig_category":"Autokeuringen",
    "sg:phone":"+31 546 621 314",
    "sg:postcode":"7651 ED",
    "sg:province":"Overijssel",
    "wof:name":"Autobedrijf Pinners",
    "wof:placetype":"venue"
},
  "geometry": {"coordinates":[6.777221,52.406921],"type":"Point"}
}