{
  "type": "Feature",
  "properties": {
    "iso:country":"NL",
    "sg:address":"Goudplevierln 23",
    "sg:city":"Leidschendam",
    "sg:orig_category":"Adviesbureaus",
    "sg:phone":"+31 70 317 7028",
    "sg:postcode":"2261 DD",
    "sg:province":"Zuid-Holland",
    "sg:website":"http://www.same-advise.com",
    "wof:name":"Same Advise",
    "wof:placetype":"venue"
},
  "geometry": {"coordinates":[4.377875,52.090111],"type":"Point"}
}