{
  "type": "Feature",
  "properties": {
    "addr:full":"Zuidweg 11 Zonnemaire Zeeland 4316 AA",
    "addr:housenumber":"11",
    "addr:postcode":"4316 aa",
    "addr:street":"Zuidweg",
    "iso:country":"NL",
    "sg:address":"Zuidweg 11",
    "sg:city":"Zonnemaire",
    "sg:orig_category":"Kampeerterreinen",
    "sg:phone":"+31 111 401 301",
    "sg:postcode":"4316 AA",
    "sg:province":"Zeeland",
    "wof:name":"Camping Zonnemaire",
    "wof:placetype":"venue"
},
  "geometry": {"coordinates":[3.951761961,51.7119941711],"type":"Point"}
}