{
  "type": "Feature",
  "properties": {
    "addr:full":"A Fokkerwg 16 Uithoorn North Holland 1422 AG",
    "addr:housenumber":"16",
    "addr:postcode":"1422",
    "iso:country":"NL",
    "sg:address":"A Fokkerwg 16",
    "sg:city":"Uithoorn",
    "sg:orig_category":"Autoschade- Herstelbedrijven",
    "sg:phone":"+31 297 566 000",
    "sg:postcode":"1422 AG",
    "sg:province":"North Holland",
    "wof:name":"Catsman Bv",
    "wof:placetype":"venue"
},
  "geometry": {"coordinates":[4.834279,52.239441],"type":"Point"}
}