{
  "type": "Feature",
  "properties": {
    "addr:full":"Uiterwaard 3 Zoetermeer Zuid-Holland 2716 VA",
    "addr:housenumber":"3",
    "addr:postcode":"2716",
    "addr:street":"Uiterwaard",
    "iso:country":"NL",
    "sg:address":"Uiterwaard 3",
    "sg:city":"Zoetermeer",
    "sg:orig_category":"Paramedische Behandelingen",
    "sg:phone":"+31 79 321 1274",
    "sg:postcode":"2716 VA",
    "sg:province":"Zuid-Holland",
    "wof:name":"Stichting Thuiszorg Zoetermeer Eo",
    "wof:placetype":"venue"
},
  "geometry": {"coordinates":[4.47024,52.055885],"type":"Point"}
}