{
  "type": "Feature",
  "properties": {
    "addr:full":"Edward Poppelaan 10 Etten-Leur Noord-Brabant 4874 NA",
    "addr:housenumber":"10",
    "addr:postcode":"4874 na",
    "addr:street":"Edward Poppelaan",
    "iso:country":"NL",
    "sg:address":"Edward Poppelaan 10",
    "sg:city":"Etten-Leur",
    "sg:orig_category":"Kappers",
    "sg:phone":"+31 76 501 1019",
    "sg:postcode":"4874 NA",
    "sg:province":"Noord-Brabant",
    "wof:name":"Haar Styl Miranda Otten",
    "wof:placetype":"venue"
},
  "geometry": {"coordinates":[4.6338062286,51.5760116577],"type":"Point"}
}