{
  "type": "Feature",
  "properties": {
    "addr:full":"Berencamperweg 12 Nijkerk Gld Gelderland 3861 MC",
    "addr:housenumber":"12;3861",
    "addr:street":"Berencamperweg;Gld Gelderland;Mc",
    "iso:country":"NL",
    "sg:address":"Berencamperweg 12",
    "sg:city":"Nijkerk Gld",
    "sg:orig_category":"Werving And Selectie Van Tijdelijk Personeel And Uitzendkantoren",
    "sg:phone":"+31 33 247 1424",
    "sg:postcode":"3861 MC",
    "sg:province":"Gelderland",
    "wof:name":"Adecco",
    "wof:placetype":"venue"
},
  "geometry": {"coordinates":[5.4862332344,52.2337188721],"type":"Point"}
}