{
  "type": "Feature",
  "properties": {
    "addr:full":"Waalstraat 14 Ijmuiden North Holland 1972 WS",
    "addr:housenumber":"14",
    "addr:postcode":"1972 ws",
    "addr:street":"Waalstraat",
    "iso:country":"NL",
    "sg:address":"Waalstraat 14",
    "sg:city":"Ijmuiden",
    "sg:orig_category":"Onderhoud And Reparatie Kantoorapparatuur",
    "sg:phone":"+31 255 541 027",
    "sg:postcode":"1972 WS",
    "sg:province":"North Holland",
    "wof:name":"Pc Ambulance",
    "wof:placetype":"venue"
},
  "geometry": {"coordinates":[4.6089,52.453938],"type":"Point"}
}