{
  "type": "Feature",
  "properties": {
    "addr:full":"Bristolstraat 12 Rotterdam South Holland 3047 AB",
    "addr:housenumber":"12",
    "addr:postcode":"3047 ab",
    "addr:street":"Bristolstraat",
    "iso:country":"NL",
    "sg:address":"Bristolstraat 12",
    "sg:city":"Rotterdam",
    "sg:orig_category":"Kleding And Schoenen Gh",
    "sg:phone":"+31 33 450 6211",
    "sg:postcode":"3047 AB",
    "sg:province":"South Holland",
    "wof:name":"Fjallraven Bv",
    "wof:placetype":"venue"
},
  "geometry": {"coordinates":[4.409161,51.945023],"type":"Point"}
}