{
  "type": "Feature",
  "properties": {
    "addr:full":"Arkelstr 41 Gorinchem Zuid-Holland 4201 KB",
    "addr:housenumber":"41",
    "addr:postcode":"4201 kb",
    "addr:street":"Arkelstr",
    "iso:country":"NL",
    "sg:address":"Arkelstr 41",
    "sg:city":"Gorinchem",
    "sg:orig_category":"Warenhuizen",
    "sg:phone":"+31 900 9800",
    "sg:postcode":"4201 KB",
    "sg:province":"Zuid-Holland",
    "sg:website":"http://www.kijkshop.nl",
    "wof:name":"Kijkshop",
    "wof:placetype":"venue"
},
  "geometry": {"coordinates":[4.975317955,51.8311691284],"type":"Point"}
}