{
  "type": "Feature",
  "properties": {
    "addr:full":"Zwanenburgplnts 4 Haarlem Noord-Holland 2012 GT",
    "addr:housenumber":"4",
    "addr:postcode":"2012 gt",
    "addr:street":"Zwanenburgplnts",
    "iso:country":"NL",
    "sg:address":"Zwanenburgplnts 4",
    "sg:city":"Haarlem",
    "sg:orig_category":"Verenigingen En Stichtingen",
    "sg:phone":"+31 23 531 3794",
    "sg:postcode":"2012 GT",
    "sg:province":"Noord-Holland",
    "wof:name":"Haarlem Music Federation",
    "wof:placetype":"venue"
},
  "geometry": {"coordinates":[4.622312,52.374123],"type":"Point"}
}