{
  "type": "Feature",
  "properties": {
    "addr:full":"Schiedamsedijk 26 Vlaardingen South Holland 3134 KK",
    "addr:housenumber":"26",
    "addr:postcode":"3134 kk",
    "addr:street":"Schiedamsedijk",
    "iso:country":"NL",
    "sg:address":"Schiedamsedijk 26",
    "sg:city":"Vlaardingen",
    "sg:orig_category":"Loodgieterswerk, Verwarming And Sanitaire Installaties",
    "sg:phone":"+31 10 234 0576",
    "sg:postcode":"3134 KK",
    "sg:province":"South Holland",
    "wof:name":"A3, Loodgieters En Installatie Bedrijf",
    "wof:placetype":"venue"
},
  "geometry": {"coordinates":[4.368704,51.905582],"type":"Point"}
}