{
  "type": "Feature",
  "properties": {
    "addr:full":"Badstr 2 Katwyk Zh Zuid-Holland 2225 BM",
    "addr:housenumber":"2",
    "addr:postcode":"2225 bm",
    "addr:street":"Badstr",
    "iso:country":"NL",
    "sg:address":"Badstr 2",
    "sg:city":"Katwyk Zh",
    "sg:orig_category":"Drogisterijen",
    "sg:phone":"+31 71 407 5591",
    "sg:postcode":"2225 BM",
    "sg:province":"Zuid-Holland",
    "wof:name":"Kruidvat",
    "wof:placetype":"venue"
},
  "geometry": {"coordinates":[4.396585,52.205109],"type":"Point"}
}