{
  "type": "Feature",
  "properties": {
    "iso:country":"NL",
    "sg:address":"Dorpsstr 152",
    "sg:city":"Zoetermeer",
    "sg:orig_category":"Kunstenaars- Benodigdheden",
    "sg:phone":"+31 79 316 4138",
    "sg:postcode":"2712 AP",
    "sg:province":"Zuid-Holland",
    "sg:website":"http://www.kroonpart.nl",
    "wof:name":"Kroonpart",
    "wof:placetype":"venue"
},
  "geometry": {"coordinates":[4.499862,52.054955],"type":"Point"}
}