{
  "type": "Feature",
  "properties": {
    "addr:full":"Stationspln 12 Assen Drenthe 9401 LB",
    "addr:housenumber":"12",
    "addr:postcode":"9401 lb",
    "addr:street":"Stationspln",
    "iso:country":"NL",
    "sg:address":"Stationspln 12",
    "sg:city":"Assen",
    "sg:orig_category":"Adviesbureaus",
    "sg:phone":"+31 592 338 899",
    "sg:postcode":"9401 LB",
    "sg:province":"Drenthe",
    "sg:website":"http://www.grontmij.com",
    "wof:name":"Grontmij Drenthe",
    "wof:placetype":"venue"
},
  "geometry": {"coordinates":[6.570076,52.992229],"type":"Point"}
}