{
  "type": "Feature",
  "properties": {
    "addr:full":"F Timmermansln 8 Hilvarenbeek Noord-Brabant 5081 SM",
    "addr:housenumber":"8",
    "addr:postcode":"5081 sm",
    "addr:street":"Timmermansln",
    "iso:country":"NL",
    "sg:address":"F Timmermansln 8",
    "sg:city":"Hilvarenbeek",
    "sg:orig_category":"Projectontwikkeling",
    "sg:phone":"+31 13 505 3264",
    "sg:postcode":"5081 SM",
    "sg:province":"Noord-Brabant",
    "wof:name":"Target Bv",
    "wof:placetype":"venue"
},
  "geometry": {"coordinates":[5.146942,51.48119],"type":"Point"}
}