{
  "type": "Feature",
  "properties": {
    "addr:full":"Groenendaal 23A Rotterdam South Holland 3011 SK",
    "addr:housenumber":"23a",
    "addr:street":"Groenendaal;3011",
    "iso:country":"NL",
    "sg:address":"Groenendaal 23A",
    "sg:city":"Rotterdam",
    "sg:orig_category":"Zonnebank- En Solariumcentra",
    "sg:phone":"+31 10 411 6799",
    "sg:postcode":"3011 SK",
    "sg:province":"South Holland",
    "wof:name":"Betty Boop",
    "wof:placetype":"venue"
},
  "geometry": {"coordinates":[4.495414,51.922619],"type":"Point"}
}