{
  "type": "Feature",
  "properties": {
    "addr:full":"Bruggerdk 23 Valkenswaard Noord-Brabant 5556 XA",
    "addr:housenumber":"23",
    "addr:postcode":"5556 xa",
    "addr:street":"Bruggerdk",
    "iso:country":"NL",
    "sg:address":"Bruggerdk 23",
    "sg:city":"Valkenswaard",
    "sg:orig_category":"Voetbalverenigingen",
    "sg:phone":"+31 40 206 8390",
    "sg:postcode":"5556 XA",
    "sg:province":"Noord-Brabant",
    "wof:name":"Bes Vv",
    "wof:placetype":"venue"
},
  "geometry": {"coordinates":[5.436018,51.294689],"type":"Point"}
}