{
  "type": "Feature",
  "properties": {
    "addr:full":"Postbus 1144 Apeldoorn Gelderland 7301 BJ",
    "addr:housenumber":"1144",
    "addr:postcode":"7301 bj",
    "addr:street":"Postbus;Gelderland",
    "iso:country":"NL",
    "sg:address":"Postbus 1144",
    "sg:city":"Apeldoorn",
    "sg:orig_category":"Winkelinrichting",
    "sg:phone":"+31 6 55968408",
    "sg:postcode":"7301 BJ",
    "sg:province":"Gelderland",
    "sg:website":"http://www.tarah.nl",
    "wof:name":"Tarah Trading",
    "wof:placetype":"venue"
},
  "geometry": {"coordinates":[5.962460041,52.2143287659],"type":"Point"}
}