{
  "type": "Feature",
  "properties": {
    "addr:full":"Voorstr 7 Almkerk North Brabant 4286 AK",
    "addr:housenumber":"7",
    "addr:postcode":"4286 ak",
    "addr:street":"Voorstr",
    "iso:country":"NL",
    "sg:address":"Voorstr 7",
    "sg:city":"Almkerk",
    "sg:orig_category":"Begrafenisverzorging",
    "sg:phone":"+31 183 402 880",
    "sg:postcode":"4286 AK",
    "sg:province":"North Brabant",
    "wof:name":"Rouwcentr Almekerck",
    "wof:placetype":"venue"
},
  "geometry": {"coordinates":[4.959316,51.770294],"type":"Point"}
}