{
  "type": "Feature",
  "properties": {
    "iso:country":"NL",
    "sg:address":"Hoofdwg 46",
    "sg:city":"Godlinze",
    "sg:orig_category":"Voetbalverenigingen",
    "sg:phone":"+31 596 581 908",
    "sg:postcode":"9908 PC",
    "sg:province":"Groningen",
    "wof:name":"Godlinze Vv",
    "wof:placetype":"venue"
},
  "geometry": {"coordinates":[6.81245,53.372761],"type":"Point"}
}