{
  "type": "Feature",
  "properties": {
    "addr:full":"Goldkampstr 6 Dalfsen Overijssel 7722 RN",
    "addr:housenumber":"6",
    "addr:postcode":"7722 rn",
    "addr:street":"Goldkampstr",
    "iso:country":"NL",
    "sg:address":"Goldkampstr 6",
    "sg:city":"Dalfsen",
    "sg:orig_category":"Schilders",
    "sg:phone":"+31 529 431 735",
    "sg:postcode":"7722 RN",
    "sg:province":"Overijssel",
    "sg:website":"http://www.brouwerschilders.nl",
    "wof:name":"Brouwer & Zoon Bv, D J",
    "wof:placetype":"venue"
},
  "geometry": {"coordinates":[6.264889,52.509209],"type":"Point"}
}