{
  "type": "Feature",
  "properties": {
    "iso:country":"NL",
    "sg:address":"Verzetslaan 39",
    "sg:city":"Almere",
    "sg:orig_category":"Begrafenisondernemers",
    "sg:phone":"+31 36 537 4775",
    "sg:postcode":"1318 BR",
    "sg:province":"NL.",
    "wof:name":"Advosta-Mortuare",
    "wof:placetype":"venue"
},
  "geometry": {"coordinates":[5.245873,52.380226],"type":"Point"}
}