{
  "type": "Feature",
  "properties": {
    "iso:country":"NL",
    "sg:address":"Tonnendijk 2",
    "sg:city":"Vroomshoop",
    "sg:orig_category":"Banken And Kredietinstellingen",
    "sg:phone":"+31 546 642 572",
    "sg:postcode":"7681 BN",
    "sg:province":"Overijssel",
    "wof:name":"Ing Bank",
    "wof:placetype":"venue"
},
  "geometry": {"coordinates":[6.573838,52.461315],"type":"Point"}
}