{
  "type": "Feature",
  "properties": {
    "addr:full":"L Braakensiekstr 15 Amsterdam Noord-Holland 1065 HM",
    "addr:housenumber":"15",
    "addr:postcode":"1065 hm",
    "iso:country":"NL",
    "sg:address":"L Braakensiekstr 15",
    "sg:city":"Amsterdam",
    "sg:orig_category":"Administratie- En Boekhoudkantoren",
    "sg:phone":"+31 20 617 3598",
    "sg:postcode":"1065 HM",
    "sg:province":"Noord-Holland",
    "wof:name":"Meander",
    "wof:placetype":"venue"
},
  "geometry": {"coordinates":[4.82102,52.355312],"type":"Point"}
}