{
  "type": "Feature",
  "properties": {
    "addr:full":"Visscherspln 160-N14 Utrecht Utrecht 3511 LX",
    "addr:housenumber":"160-n14",
    "addr:postcode":"3511 lx",
    "addr:street":"Visscherspln",
    "iso:country":"NL",
    "sg:address":"Visscherspln 160-N14",
    "sg:city":"Utrecht",
    "sg:orig_category":"Journalisten Freelance",
    "sg:phone":"+31 30 230 2230",
    "sg:postcode":"3511 LX",
    "sg:province":"Utrecht",
    "wof:name":"Krijnen, Rietje",
    "wof:placetype":"venue"
},
  "geometry": {"coordinates":[5.115405,52.088932],"type":"Point"}
}