{
  "type": "Feature",
  "properties": {
    "addr:full":"Julianaplein 25 'S Hertogenbosch Noord-Brabant 5211 BB",
    "addr:housenumber":"25",
    "addr:postcode":"5211 bb",
    "addr:street":"Julianaplein;' S",
    "iso:country":"NL",
    "sg:address":"Julianaplein 25",
    "sg:city":"'S Hertogenbosch",
    "sg:orig_category":"Advocaten And Juridische Adviseurs",
    "sg:phone":"+31 73 690 1306",
    "sg:postcode":"5211 BB",
    "sg:province":"Noord-Brabant",
    "wof:name":"Van Kuppenveld Advocatenkantoor",
    "wof:placetype":"venue"
},
  "geometry": {"coordinates":[5.294917,51.688309],"type":"Point"}
}