{
  "type": "Feature",
  "properties": {
    "addr:full":"Wagenwg 12M Purmerend Noord-Holland 1442 BX",
    "addr:housenumber":"12m",
    "addr:postcode":"1442 bx",
    "addr:street":"Wagenwg",
    "iso:country":"NL",
    "sg:address":"Wagenwg 12M",
    "sg:city":"Purmerend",
    "sg:orig_category":"Logopedisten",
    "sg:phone":"+31 299 430 933",
    "sg:postcode":"1442 BX",
    "sg:province":"Noord-Holland",
    "wof:name":"Wherestate, Praktijk",
    "wof:placetype":"venue"
},
  "geometry": {"coordinates":[4.954201,52.510105],"type":"Point"}
}