{
  "type": "Feature",
  "properties": {
    "addr:full":"Abrikozenstraat 147 'S Gravenhage Zuid-Holland 2564 VN",
    "addr:housenumber":"147 '",
    "addr:postcode":"2564 vn",
    "addr:street":"Abrikozenstraat",
    "iso:country":"NL",
    "sg:address":"Abrikozenstraat 147",
    "sg:city":"'S Gravenhage",
    "sg:orig_category":"Kappers",
    "sg:phone":"+31 70 323 0474",
    "sg:postcode":"2564 VN",
    "sg:province":"Zuid-Holland",
    "wof:name":"Danni Dames- En Herenkapsalon",
    "wof:placetype":"venue"
},
  "geometry": {"coordinates":[4.2554187775,52.0673675537],"type":"Point"}
}