{
  "type": "Feature",
  "properties": {
    "iso:country":"NL",
    "sg:address":"Dr Meuwissenstr 15",
    "sg:city":"St Odilienberg",
    "sg:orig_category":"Adviesbureaus Bedrijfsorganisatie",
    "sg:phone":"+31 475 533 589",
    "sg:postcode":"6077 BP",
    "sg:province":"Limburg",
    "wof:name":"Paragon",
    "wof:placetype":"venue"
},
  "geometry": {"coordinates":[6.001593,51.142673],"type":"Point"}
}