{
  "type": "Feature",
  "properties": {
    "addr:full":"Dr Meuwissenstr 15 St Odilienberg Limburg 6077 BP",
    "addr:housenumber":"15",
    "addr:postcode":"6077 bp",
    "addr:street":"St Odilienberg Limburg",
    "iso:country":"NL",
    "sg:address":"Dr Meuwissenstr 15",
    "sg:city":"St Odilienberg",
    "sg:orig_category":"Adviesbureaus Bedrijfsorganisatie",
    "sg:phone":"+31 475 533 589",
    "sg:postcode":"6077 BP",
    "sg:province":"Limburg",
    "wof:name":"Paragon",
    "wof:placetype":"venue"
},
  "geometry": {"coordinates":[6.001593,51.142673],"type":"Point"}
}