{
  "type": "Feature",
  "properties": {
    "iso:country":"NL",
    "sg:address":"Onderlangs 128",
    "sg:city":"Zoetermeer",
    "sg:classifiers":[
        {
            "category":"Shopping",
            "subcategory":"Gifts & Souvenirs",
            "type":"Retail Goods"
        }
    ],
    "sg:phone":"+31 79 331 2344",
    "sg:postcode":"2711 HX",
    "sg:province":"South Holland",
    "sg:tags":[
        "geschenken"
    ],
    "wof:name":"Art Expo Zoetermeer",
    "wof:placetype":"venue"
},
  "geometry": {"coordinates":[4.487425,52.06036],"type":"Point"}
}