{
  "type": "Feature",
  "properties": {
    "addr:full":"Poldermolen 8 Papendrecht Zuid-Holland 3352 TH",
    "addr:housenumber":"8",
    "addr:postcode":"3352 th",
    "addr:street":"Poldermolen",
    "iso:country":"NL",
    "sg:address":"Poldermolen 8",
    "sg:city":"Papendrecht",
    "sg:orig_category":"Politie",
    "sg:phone":"+31 900 8844",
    "sg:postcode":"3352 TH",
    "sg:province":"Zuid-Holland",
    "wof:name":"Politie Zuid Holland Zuid Bureau Papendrecht",
    "wof:placetype":"venue"
},
  "geometry": {"coordinates":[4.691598,51.836693],"type":"Point"}
}