{
  "type": "Feature",
  "properties": {
    "iso:country":"NL",
    "sg:address":"Poldermolen 8",
    "sg:city":"Papendrecht",
    "sg:orig_category":"Politie",
    "sg:phone":"+31 900 8844",
    "sg:postcode":"3352 TH",
    "sg:province":"Zuid-Holland",
    "wof:name":"Politie Zuid Holland Zuid Bureau Papendrecht",
    "wof:placetype":"venue"
},
  "geometry": {"coordinates":[4.691598,51.836693],"type":"Point"}
}