{
  "type": "Feature",
  "properties": {
    "addr:full":"Papsouwselaan 400 Delft South Holland 2624 EM",
    "addr:housenumber":"400",
    "addr:postcode":"2624 em",
    "addr:street":"Papsouwselaan",
    "iso:country":"NL",
    "sg:address":"Papsouwselaan 400",
    "sg:city":"Delft",
    "sg:orig_category":"Loodgieterswerk, Verwarming And Sanitaire Installaties",
    "sg:phone":"+31 15 262 6836",
    "sg:postcode":"2624 EM",
    "sg:province":"South Holland",
    "wof:name":"Allround",
    "wof:placetype":"venue"
},
  "geometry": {"coordinates":[4.354667,51.998108],"type":"Point"}
}