{
  "type": "Feature",
  "properties": {
    "addr:full":"Verl Voorstr 4 Wyk Aan Zee Noord-Holland 1949 CM",
    "addr:housenumber":"4",
    "addr:postcode":"zee;1949 cm",
    "addr:street":"Voorstr",
    "iso:country":"NL",
    "sg:address":"Verl Voorstr 4",
    "sg:city":"Wyk Aan Zee",
    "sg:orig_category":"Kappers",
    "sg:phone":"+31 251 375 852",
    "sg:postcode":"1949 CM",
    "sg:province":"Noord-Holland",
    "wof:name":"Variant, Kapsalon",
    "wof:placetype":"venue"
},
  "geometry": {"coordinates":[8.50811,51.882469],"type":"Point"}
}