{
  "type": "Feature",
  "properties": {
    "addr:full":"Verdistraat 20 Zevenaar Gelderland 6904 KG",
    "addr:housenumber":"20",
    "addr:postcode":"6904 kg",
    "addr:street":"Verdistraat",
    "iso:country":"NL",
    "sg:address":"Verdistraat 20",
    "sg:city":"Zevenaar",
    "sg:orig_category":"Kinderopvang Behalve Thuis",
    "sg:phone":"+31 316 331 119",
    "sg:postcode":"6904 KG",
    "sg:province":"Gelderland",
    "wof:name":"Peuterspeelzaal Zonnemaat",
    "wof:placetype":"venue"
},
  "geometry": {"coordinates":[6.06454,51.934048],"type":"Point"}
}