{
  "type": "Feature",
  "properties": {
    "addr:full":"Weth Gerbertstr 27-29 Enschede Overijssel 7543 AV",
    "addr:housenumber":"27-29",
    "addr:postcode":"7543 av",
    "addr:street":"Weth Gerbertstr",
    "iso:country":"NL",
    "sg:address":"Weth Gerbertstr 27-29",
    "sg:city":"Enschede",
    "sg:orig_category":"Gordijnen",
    "sg:phone":"+31 53 477 1004",
    "sg:postcode":"7543 AV",
    "sg:province":"Overijssel",
    "wof:name":"Jenny'S Gordijnboetiek Bv",
    "wof:placetype":"venue"
},
  "geometry": {"coordinates":[6.87974,52.20488],"type":"Point"}
}