{
  "type": "Feature",
  "properties": {
    "addr:full":"Nieuwendk 70 Someren North Brabant 5712 EN",
    "addr:housenumber":"70",
    "addr:postcode":"5712 en",
    "addr:street":"Nieuwendk",
    "iso:country":"NL",
    "sg:address":"Nieuwendk 70",
    "sg:city":"Someren",
    "sg:orig_category":"Pensioenen",
    "sg:phone":"+31 493 440 115",
    "sg:postcode":"5712 EN",
    "sg:province":"North Brabant",
    "wof:name":"Looijmans, Mr H C M",
    "wof:placetype":"venue"
},
  "geometry": {"coordinates":[5.72846,51.352745],"type":"Point"}
}