{
  "type": "Feature",
  "properties": {
    "addr:full":"Het Nw Diep 12-14 Den Helder North Holland 1781 AC",
    "addr:housenumber":"12-14",
    "addr:postcode":"1781 ac",
    "addr:street":"Het Nw Diep",
    "iso:country":"NL",
    "sg:address":"Het Nw Diep 12-14",
    "sg:city":"Den Helder",
    "sg:orig_category":"Metaalbewerking",
    "sg:phone":"+31 223 611 120",
    "sg:postcode":"1781 AC",
    "sg:province":"North Holland",
    "wof:name":"Multimetaal Bv",
    "wof:placetype":"venue"
},
  "geometry": {"coordinates":[4.775931,52.957447],"type":"Point"}
}