{
  "type": "Feature",
  "properties": {
    "addr:full":"F Hendrikln 37 Waddinxveen Zuid-Holland 2741 CP",
    "addr:housenumber":"37",
    "addr:postcode":"2741 cp",
    "iso:country":"NL",
    "sg:address":"F Hendrikln 37",
    "sg:city":"Waddinxveen",
    "sg:orig_category":"Autorijscholen",
    "sg:phone":"+31 182 617 216",
    "sg:postcode":"2741 CP",
    "sg:province":"Zuid-Holland",
    "wof:name":"Guit",
    "wof:placetype":"venue"
},
  "geometry": {"coordinates":[4.654255,52.050034],"type":"Point"}
}