{
  "type": "Feature",
  "properties": {
    "addr:full":"Thorbeckelaan 40 Hillegom North Holland 2181 VD",
    "addr:housenumber":"40",
    "addr:postcode":"2181 vd",
    "addr:street":"Thorbeckelaan",
    "iso:country":"NL",
    "sg:address":"Thorbeckelaan 40",
    "sg:city":"Hillegom",
    "sg:classifiers":[
        {
            "category":"Education",
            "subcategory":"Preschool",
            "type":"Public Place"
        }
    ],
    "sg:phone":"+31 252 518 353",
    "sg:postcode":"2181 VD",
    "sg:province":"North Holland",
    "sg:tags":[
        "kleuteronderwijs",
        "basis-"
    ],
    "wof:name":"De Leerwinkel",
    "wof:placetype":"venue"
},
  "geometry": {"coordinates":[4.592258,52.291534],"type":"Point"}
}