{
  "type": "Feature",
  "properties": {
    "iso:country":"NL",
    "sg:address":"Soestdykstr 26",
    "sg:city":"Haarlem",
    "sg:orig_category":"Juridische Adviseurs",
    "sg:phone":"+31 23 531 4097",
    "sg:postcode":"2012 KS",
    "sg:province":"Noord-Holland",
    "wof:name":"Gorsel Bv, Van",
    "wof:placetype":"venue"
},
  "geometry": {"coordinates":[4.6223,52.373318],"type":"Point"}
}