{
  "type": "Feature",
  "properties": {
    "addr:full":"Berkstraat 91 Oldenzaal Overijssel 7572 CA",
    "addr:housenumber":"91",
    "addr:postcode":"7572 ca",
    "addr:street":"Berkstraat",
    "iso:country":"NL",
    "sg:address":"Berkstraat 91",
    "sg:city":"Oldenzaal",
    "sg:orig_category":"Kinderopvang Behalve Thuis",
    "sg:phone":"+31 541 515 399",
    "sg:postcode":"7572 CA",
    "sg:province":"Overijssel",
    "wof:name":"Kiekeboe",
    "wof:placetype":"venue"
},
  "geometry": {"coordinates":[6.92113,52.307289],"type":"Point"}
}