{
  "type": "Feature",
  "properties": {
    "addr:full":"Visarenddreef 1 Lelystad Flevoland 8232 PH",
    "addr:housenumber":"1",
    "addr:postcode":"8232",
    "addr:street":"Visarenddreef;Flevoland",
    "iso:country":"NL",
    "sg:address":"Visarenddreef 1",
    "sg:city":"Lelystad",
    "sg:orig_category":"Overheidsdiensten",
    "sg:phone":"+31 320 265 265",
    "sg:postcode":"8232 PH",
    "sg:province":"Flevoland",
    "wof:name":"Provincie Flevoland",
    "wof:placetype":"venue"
},
  "geometry": {"coordinates":[5.4695892334,52.506980896],"type":"Point"}
}