{
  "type": "Feature",
  "properties": {
    "addr:full":"G. Van Dort Kroonweg 6 Waddinxveen South Holland 2742 KG",
    "addr:housenumber":"6",
    "addr:postcode":"2742 kg",
    "addr:street":"G. Van Dort Kroonweg",
    "iso:country":"NL",
    "sg:address":"G. Van Dort Kroonweg 6",
    "sg:city":"Waddinxveen",
    "sg:orig_category":"Bloemen And Planten",
    "sg:phone":"+31 182 617 667",
    "sg:postcode":"2742 KG",
    "sg:province":"South Holland",
    "wof:name":"Vof P J Stolk",
    "wof:placetype":"venue"
},
  "geometry": {"coordinates":[4.621813,52.028446],"type":"Point"}
}