{
  "type": "Feature",
  "properties": {
    "addr:full":"Zichtenburglaan 15 'S Gravenhage South Holland 2544 EA",
    "addr:housenumber":"15",
    "addr:postcode":"2544 ea",
    "addr:street":"Zichtenburglaan;' S Gravenhage",
    "iso:country":"NL",
    "sg:address":"Zichtenburglaan 15",
    "sg:city":"'S Gravenhage",
    "sg:orig_category":"Film-, Tv- And Videoproductie",
    "sg:phone":"+31 70 321 3537",
    "sg:postcode":"2544 EA",
    "sg:province":"South Holland",
    "wof:name":"Rena Productions",
    "wof:placetype":"venue"
},
  "geometry": {"coordinates":[4.250665,52.047485],"type":"Point"}
}