{
  "type": "Feature",
  "properties": {
    "iso:country":"NL",
    "sg:address":"Spanjaardslaan 149",
    "sg:city":"Leeuwarden",
    "sg:orig_category":"Werving And Selectie Van Vast Personeel",
    "sg:phone":"+31 58 212 0405",
    "sg:postcode":"8917 AS",
    "sg:province":"Friesland",
    "wof:name":"Adviesburo De Rijk",
    "wof:placetype":"venue"
},
  "geometry": {"coordinates":[5.7874798775,53.2059707642],"type":"Point"}
}