{
  "type": "Feature",
  "properties": {
    "addr:full":"Benschopperstraat 29 Ijsselstein Ut Utrecht 3401 DG",
    "addr:housenumber":"29",
    "addr:postcode":"3401 dg",
    "addr:street":"Benschopperstraat",
    "iso:country":"NL",
    "sg:address":"Benschopperstraat 29",
    "sg:city":"Ijsselstein Ut",
    "sg:orig_category":"Verlichting And Huishoudartikelen",
    "sg:phone":"+31 30 687 4909",
    "sg:postcode":"3401 DG",
    "sg:province":"Utrecht",
    "wof:name":"Senderlight",
    "wof:placetype":"venue"
},
  "geometry": {"coordinates":[5.042314,52.019096],"type":"Point"}
}