{
  "type": "Feature",
  "properties": {
    "iso:country":"NL",
    "sg:address":"Borgerstr 272",
    "sg:city":"Amsterdam",
    "sg:orig_category":"Beeldende Kunstenaars",
    "sg:phone":"+31 6 51260886",
    "sg:postcode":"1053 RH",
    "sg:province":"Noord-Holland",
    "wof:name":"Krimpen, Th A Van",
    "wof:placetype":"venue"
},
  "geometry": {"coordinates":[4.859528,52.363567],"type":"Point"}
}