{
  "type": "Feature",
  "properties": {
    "iso:country":"NL",
    "sg:address":"Assinklanden 265",
    "sg:city":"Enschede",
    "sg:orig_category":"Koeriersdiensten",
    "sg:phone":"+31 53 476 7365",
    "sg:postcode":"7542 BH",
    "sg:province":"Overijssel",
    "wof:name":"Hadderingh",
    "wof:placetype":"venue"
},
  "geometry": {"coordinates":[6.901053,52.191235],"type":"Point"}
}