{
  "type": "Feature",
  "properties": {
    "iso:country":"NL",
    "sg:address":"V Bronckhorststr 1",
    "sg:city":"Heemskerk",
    "sg:orig_category":"Verenigingsgebouwen",
    "sg:phone":"+31 251 253 054",
    "sg:postcode":"1962 TV",
    "sg:province":"Noord-Holland",
    "wof:name":"Schuilhoek, De",
    "wof:placetype":"venue"
},
  "geometry": {"coordinates":[4.684505,52.510342],"type":"Point"}
}