{
  "type": "Feature",
  "properties": {
    "addr:full":"Industrieweg 39 Staphorst Overijssel 7951 TA",
    "addr:housenumber":"39",
    "addr:postcode":"7951 ta",
    "addr:street":"Industrieweg",
    "iso:country":"NL",
    "sg:address":"Industrieweg 39",
    "sg:city":"Staphorst",
    "sg:orig_category":"Metaalafval, Schrootrecycling And Sloperijen",
    "sg:phone":"+31 522 463 172",
    "sg:postcode":"7951 TA",
    "sg:province":"Overijssel",
    "wof:name":"J. En J. Engel",
    "wof:placetype":"venue"
},
  "geometry": {"coordinates":[6.223303,52.637882],"type":"Point"}
}