{
  "type": "Feature",
  "properties": {
    "addr:full":"Heymansstr 97-99 Rotterdam South Holland 3076 CE",
    "addr:housenumber":"97-99",
    "addr:postcode":"3076 ce",
    "iso:country":"NL",
    "sg:address":"Heymansstr 97-99",
    "sg:city":"Rotterdam",
    "sg:orig_category":"Behangselpapier En Wandbekleding",
    "sg:phone":"+31 10 419 5066",
    "sg:postcode":"3076 CE",
    "sg:province":"South Holland",
    "sg:website":"http://www.hb-interieurs.nl",
    "wof:name":"Hb-Interieurs",
    "wof:placetype":"venue"
},
  "geometry": {"coordinates":[4.520021,51.87764],"type":"Point"}
}