{
  "type": "Feature",
  "properties": {
    "addr:full":"Op De Vey 64 Geleen Limburg 6165 CD",
    "addr:housenumber":"64",
    "addr:postcode":"6165 cd",
    "addr:street":"Op De Vey",
    "iso:country":"NL",
    "sg:address":"Op De Vey 64",
    "sg:city":"Geleen",
    "sg:classifiers":[
        {
            "category":"Travel",
            "subcategory":"Hotels & Motels",
            "type":"Entertainment"
        }
    ],
    "sg:phone":"+31 46 474 3873",
    "sg:postcode":"6165 CD",
    "sg:province":"Limburg",
    "wof:name":"Amvj Hostel",
    "wof:placetype":"venue"
},
  "geometry": {"coordinates":[5.833498,50.96854],"type":"Point"}
}