{
  "type": "Feature",
  "properties": {
    "iso:country":"NL",
    "sg:address":"Escamplaan 836",
    "sg:city":"'S Gravenhage",
    "sg:orig_category":"Fotostudio'S And Fotografen",
    "sg:phone":"+31 70 323 2883",
    "sg:postcode":"2547 EW",
    "sg:province":"South Holland",
    "wof:name":"Fotoburo Van Huizen",
    "wof:placetype":"venue"
},
  "geometry": {"coordinates":[4.265224,52.0588],"type":"Point"}
}