{
  "type": "Feature",
  "properties": {
    "addr:full":"Krabbendijk 9 Denekamp Overijssel 7591 AW",
    "addr:housenumber":"9",
    "addr:postcode":"7591 aw",
    "addr:street":"Krabbendijk",
    "iso:country":"NL",
    "sg:address":"Krabbendijk 9",
    "sg:city":"Denekamp",
    "sg:orig_category":"Landbouwmachines Gh",
    "sg:phone":"+31 541 351 329",
    "sg:postcode":"7591 AW",
    "sg:province":"Overijssel",
    "wof:name":"Agri Bv",
    "wof:placetype":"venue"
},
  "geometry": {"coordinates":[7.010745,52.378017],"type":"Point"}
}