{
  "type": "Feature",
  "properties": {
    "addr:full":"Larixstr 10 Leeuwarden Provincie Friesland 8924 CP",
    "addr:housenumber":"10",
    "addr:postcode":"8924 cp",
    "addr:street":"Larixstr;Provincie Friesland",
    "iso:country":"NL",
    "sg:address":"Larixstr 10",
    "sg:city":"Leeuwarden",
    "sg:classifiers":[
        {
            "category":"Food & Beverages",
            "subcategory":"Bakery",
            "type":"Retail Goods"
        }
    ],
    "sg:phone":"+31 58 266 3992",
    "sg:postcode":"8924 CP",
    "sg:province":"Provincie Friesland",
    "sg:tags":[
        "pizza"
    ],
    "wof:name":"Super Pizza Service",
    "wof:placetype":"venue"
},
  "geometry": {"coordinates":[5.823221,53.206211],"type":"Point"}
}