{
  "type": "Feature",
  "properties": {
    "iso:country":"NL",
    "sg:address":"Peppelwg 168A",
    "sg:city":"Rotterdam",
    "sg:orig_category":"Broodjeszaken",
    "sg:phone":"+31 10 461 1842",
    "sg:postcode":"3053 GX",
    "sg:province":"Zuid-Holland",
    "wof:name":"Pain-De-Luxe",
    "wof:placetype":"venue"
},
  "geometry": {"coordinates":[4.467894,51.96067],"type":"Point"}
}