{
  "type": "Feature",
  "properties": {
    "addr:full":"Spiraeastr 38 Kerkrade Limburg 6466 SR",
    "addr:housenumber":"38",
    "addr:postcode":"6466 sr",
    "addr:street":"Spiraeastr",
    "iso:country":"NL",
    "sg:address":"Spiraeastr 38",
    "sg:city":"Kerkrade",
    "sg:orig_category":"Bejaarden - Verzorgingstehuizen",
    "sg:phone":"+31 45 549 0391",
    "sg:postcode":"6466 SR",
    "sg:province":"Limburg",
    "wof:name":"Wijkverzorgingsteunpunt Spekholzerheide",
    "wof:placetype":"venue"
},
  "geometry": {"coordinates":[6.027317,50.862362],"type":"Point"}
}