{
  "type": "Feature",
  "properties": {
    "iso:country":"NL",
    "sg:address":"Kerkweg 41",
    "sg:city":"Giethoorn",
    "sg:classifiers":[
        {
            "category":"Travel",
            "subcategory":"Hotels & Motels",
            "type":"Entertainment"
        }
    ],
    "sg:phone":"+31 521 362 148",
    "sg:postcode":"8355 BM",
    "sg:province":"NL.08",
    "wof:name":"W.L. Ulrich",
    "wof:placetype":"venue"
},
  "geometry": {"coordinates":[6.090196,52.729309],"type":"Point"}
}