{
  "type": "Feature",
  "properties": {
    "addr:full":"Hornsedk 4 Buinen Drenthe 9528 PK",
    "addr:housenumber":"4",
    "addr:postcode":"9528 pk",
    "addr:street":"Hornsedk",
    "iso:country":"NL",
    "sg:address":"Hornsedk 4",
    "sg:city":"Buinen",
    "sg:orig_category":"Adviesbureaus Bedrijfsorganisatie",
    "sg:phone":"+31 599 212 267",
    "sg:postcode":"9528 PK",
    "sg:province":"Drenthe",
    "wof:name":"Klaproos, De",
    "wof:placetype":"venue"
},
  "geometry": {"coordinates":[6.837998,52.933502],"type":"Point"}
}