{
  "type": "Feature",
  "properties": {
    "iso:country":"NL",
    "sg:address":"Huizerwg 46",
    "sg:city":"Bussum",
    "sg:orig_category":"Bloemen En Planten",
    "sg:phone":"+31 35 693 2963",
    "sg:postcode":"1402 AD",
    "sg:province":"North Holland",
    "wof:name":"Lavendel Bloembinderij",
    "wof:placetype":"venue"
},
  "geometry": {"coordinates":[5.170241,52.27425],"type":"Point"}
}