{
  "type": "Feature",
  "properties": {
    "addr:full":"Parallelweg 77 Bergen Op Zoom Noord-Brabant 4621 JS",
    "addr:housenumber":"77",
    "addr:postcode":"4621 js",
    "addr:street":"Parallelweg",
    "iso:country":"NL",
    "sg:address":"Parallelweg 77",
    "sg:city":"Bergen Op Zoom",
    "sg:orig_category":"Bedrijfsinventaris Gh",
    "sg:phone":"+31 164 248 855",
    "sg:postcode":"4621 JS",
    "sg:province":"Noord-Brabant",
    "wof:name":"Wietse Van Rijen",
    "wof:placetype":"venue"
},
  "geometry": {"coordinates":[4.296627,51.492725],"type":"Point"}
}