{
  "type": "Feature",
  "properties": {
    "addr:full":"Bakkummerstr 87 Castricum Noord-Holland 1901 HL",
    "addr:housenumber":"87",
    "addr:postcode":"1901 hl",
    "addr:street":"Bakkummerstr",
    "iso:country":"NL",
    "sg:address":"Bakkummerstr 87",
    "sg:city":"Castricum",
    "sg:orig_category":"Loodgieters",
    "sg:phone":"+31 251 652 315",
    "sg:postcode":"1901 HL",
    "sg:province":"Noord-Holland",
    "wof:name":"Bleeker, R T",
    "wof:placetype":"venue"
},
  "geometry": {"coordinates":[4.657087,52.556828],"type":"Point"}
}