{
  "type": "Feature",
  "properties": {
    "addr:full":"Cornelis Evertsenstraat 19 Zwijndrecht Zuid-Holland 3333 TJ",
    "addr:housenumber":"19",
    "addr:postcode":"3333 tj",
    "addr:street":"Cornelis Evertsenstraat",
    "iso:country":"NL",
    "sg:address":"Cornelis Evertsenstraat 19",
    "sg:city":"Zwijndrecht",
    "sg:orig_category":"Goederenvervoer Over De Weg",
    "sg:phone":"+31 78 612 1426",
    "sg:postcode":"3333 TJ",
    "sg:province":"Zuid-Holland",
    "wof:name":"E Meuldijk",
    "wof:placetype":"venue"
},
  "geometry": {"coordinates":[4.633208,51.810745],"type":"Point"}
}