{
  "type": "Feature",
  "properties": {
    "iso:country":"NL",
    "sg:address":"Rykswg Z 58",
    "sg:city":"Swalmen",
    "sg:orig_category":"Verzekeringen - Verzekeringskantoren",
    "sg:phone":"+31 475 508 220",
    "sg:postcode":"6071 HW",
    "sg:province":"Limburg",
    "wof:name":"Caris, Han",
    "wof:placetype":"venue"
},
  "geometry": {"coordinates":[6.03203,51.22794],"type":"Point"}
}