{
  "type": "Feature",
  "properties": {
    "addr:full":"J Wattstr 13J Gouda Zuid-Holland 2809 PA",
    "addr:housenumber":"13j",
    "addr:postcode":"2809 pa",
    "addr:street":"Wattstr",
    "iso:country":"NL",
    "sg:address":"J Wattstr 13J",
    "sg:city":"Gouda",
    "sg:orig_category":"Autoruiten",
    "sg:phone":"+31 182 393 181",
    "sg:postcode":"2809 PA",
    "sg:province":"Zuid-Holland",
    "sg:website":"http://www.riss.nl",
    "wof:name":"Riss Gouda",
    "wof:placetype":"venue"
},
  "geometry": {"coordinates":[4.690799,52.006599],"type":"Point"}
}