{
  "type": "Feature",
  "properties": {
    "iso:country":"NL",
    "sg:address":"Vughterstr 25",
    "sg:city":"S Hertogenbosch",
    "sg:classifiers":[
        {
            "category":"Shopping",
            "subcategory":"Adult",
            "type":"Retail Goods"
        }
    ],
    "sg:phone":"+31 73 612 8774",
    "sg:postcode":"5211 EW",
    "sg:province":"North Brabant",
    "sg:tags":[
        "lingerie",
        "en",
        "tricotage"
    ],
    "wof:name":"Livera",
    "wof:placetype":"venue"
},
  "geometry": {"coordinates":[5.301348,51.687611],"type":"Point"}
}