{
  "type": "Feature",
  "properties": {
    "addr:full":"Parkstr 10 Assen Provincie Drenthe 9401 LJ",
    "addr:housenumber":"10;lj",
    "addr:postcode":"9401",
    "addr:street":"Parkstr;Provincie Drenthe",
    "iso:country":"NL",
    "sg:address":"Parkstr 10",
    "sg:city":"Assen",
    "sg:orig_category":"Verenigingen En Stichtingen",
    "sg:phone":"+31 592 300 004",
    "sg:postcode":"9401 LJ",
    "sg:province":"Provincie Drenthe",
    "wof:name":"Niedos, Sticht",
    "wof:placetype":"venue"
},
  "geometry": {"coordinates":[6.56409,52.989227],"type":"Point"}
}