{
  "type": "Feature",
  "properties": {
    "iso:country":"NL",
    "sg:address":"Rijnstraat 229",
    "sg:city":"Amsterdam",
    "sg:orig_category":"Verhuur Catering-, Feest- En Evenementbenodigdheden",
    "sg:phone":"+31 20 646 0910",
    "sg:postcode":"1079 HH",
    "sg:province":"Noord-Holland",
    "wof:name":"Gebroeders De Waard Bv",
    "wof:placetype":"venue"
},
  "geometry": {"coordinates":[4.907319,52.341316],"type":"Point"}
}