{
  "type": "Feature",
  "properties": {
    "addr:full":"Decimastraat 26 Leiden Zuid-Holland 2315 HK",
    "addr:housenumber":"26",
    "addr:postcode":"2315 hk",
    "addr:street":"Decimastraat",
    "iso:country":"NL",
    "sg:address":"Decimastraat 26",
    "sg:city":"Leiden",
    "sg:orig_category":"Diverse Consumentenartikelen Gh",
    "sg:phone":"+31 71 522 3073",
    "sg:postcode":"2315 HK",
    "sg:province":"Zuid-Holland",
    "wof:name":"Ligtvoet Fashion",
    "wof:placetype":"venue"
},
  "geometry": {"coordinates":[4.507604,52.162468],"type":"Point"}
}