{
  "type": "Feature",
  "properties": {
    "addr:full":"De Doorn 62 Nuenen Noord-Brabant 5673 LP",
    "addr:housenumber":"62",
    "addr:postcode":"5673 lp",
    "addr:street":"De Doorn",
    "iso:country":"NL",
    "sg:address":"De Doorn 62",
    "sg:city":"Nuenen",
    "sg:orig_category":"Schoonheidssalons",
    "sg:phone":"+31 40 283 7396",
    "sg:postcode":"5673 LP",
    "sg:province":"Noord-Brabant",
    "wof:name":"Annelies Feijen",
    "wof:placetype":"venue"
},
  "geometry": {"coordinates":[5.558934,51.470306],"type":"Point"}
}