{
  "type": "Feature",
  "properties": {
    "iso:country":"NL",
    "sg:address":"Marsdiepstr 365-367",
    "sg:city":"Den Helder",
    "sg:orig_category":"Huishoudelijke Apparaten En Artikelen",
    "sg:phone":"+31 223 661 017",
    "sg:postcode":"1784 AH",
    "sg:province":"Noord-Holland",
    "wof:name":"Marskramer Bv",
    "wof:placetype":"venue"
},
  "geometry": {"coordinates":[4.742149,52.943802],"type":"Point"}
}