{
  "type": "Feature",
  "properties": {
    "addr:full":"Tasveld 8 Montfoort Utrecht 3417 XS",
    "addr:housenumber":"8",
    "addr:postcode":"3417 xs",
    "addr:street":"Tasveld",
    "iso:country":"NL",
    "sg:address":"Tasveld 8",
    "sg:city":"Montfoort",
    "sg:orig_category":"Homeopathie",
    "sg:phone":"+31 348 475 211",
    "sg:postcode":"3417 XS",
    "sg:province":"Utrecht",
    "sg:website":"http://www.lumen.nl",
    "wof:name":"Lumen Pharma Bv",
    "wof:placetype":"venue"
},
  "geometry": {"coordinates":[4.934583,52.04353],"type":"Point"}
}