{
  "type": "Feature",
  "properties": {
    "addr:full":"Kastelenakkers 21 Zuidlaren Provincie Drenthe 9472 PK",
    "addr:housenumber":"21",
    "addr:postcode":"9472 pk",
    "addr:street":"Kastelenakkers;Provincie Drenthe",
    "iso:country":"NL",
    "sg:address":"Kastelenakkers 21",
    "sg:city":"Zuidlaren",
    "sg:orig_category":"Verenigingen En Stichtingen",
    "sg:phone":"+31 50 409 3401",
    "sg:postcode":"9472 PK",
    "sg:province":"Provincie Drenthe",
    "wof:name":"Modanka, Sticht",
    "wof:placetype":"venue"
},
  "geometry": {"coordinates":[6.69925,53.072121],"type":"Point"}
}