{
  "type": "Feature",
  "properties": {
    "addr:full":"Kloosterstr 17 Rosmalen Noord-Brabant 5248 NV",
    "addr:housenumber":"17",
    "addr:postcode":"5248 nv",
    "addr:street":"Kloosterstr",
    "iso:country":"NL",
    "sg:address":"Kloosterstr 17",
    "sg:city":"Rosmalen",
    "sg:orig_category":"Autoruiten",
    "sg:phone":"+31 73 522 0460",
    "sg:postcode":"5248 NV",
    "sg:province":"Noord-Brabant",
    "sg:website":"http://www.glasgarage.nl",
    "wof:name":"Glasgarage Rosmalen",
    "wof:placetype":"venue"
},
  "geometry": {"coordinates":[5.359013,51.699509],"type":"Point"}
}