{
  "type": "Feature",
  "properties": {
    "addr:full":"De Hofnar 10 Valkenswaard Noord-Brabant 5554 DA",
    "addr:housenumber":"10",
    "addr:postcode":"5554 da",
    "addr:street":"De Hofnar",
    "iso:country":"NL",
    "sg:address":"De Hofnar 10",
    "sg:city":"Valkenswaard",
    "sg:orig_category":"Artiestenbureaus",
    "sg:phone":"+31 40 207 4010",
    "sg:postcode":"5554 DA",
    "sg:province":"Noord-Brabant",
    "wof:name":"Cultuurcentrum De Hofnar",
    "wof:placetype":"venue"
},
  "geometry": {"coordinates":[5.4599919319,51.3497085571],"type":"Point"}
}