{
  "type": "Feature",
  "properties": {
    "addr:full":"Postbus 2024 Vught Noord-Holland 5260 CA",
    "addr:housenumber":"2024",
    "addr:postcode":"vught;5260 ca",
    "addr:street":"Postbus",
    "iso:country":"NL",
    "sg:address":"Postbus 2024",
    "sg:city":"Vught",
    "sg:orig_category":"Adviesbureaus Bouwkosten",
    "sg:phone":"+31 73 656 4597",
    "sg:postcode":"5260 CA",
    "sg:province":"Noord-Holland",
    "wof:name":"Bobgo Vof",
    "wof:placetype":"venue"
},
  "geometry": {"coordinates":[5.297663,51.660519],"type":"Point"}
}