{
  "type": "Feature",
  "properties": {
    "addr:full":"Baartven 4 Castricum Noord-Holland 1902 AE",
    "addr:housenumber":"4",
    "addr:postcode":"1902 ae",
    "addr:street":"Baartven",
    "iso:country":"NL",
    "sg:address":"Baartven 4",
    "sg:city":"Castricum",
    "sg:classifiers":[
        {
            "category":"Wholesale",
            "subcategory":"Meat",
            "type":"Manufacturing & Wholesale Goods"
        }
    ],
    "sg:phone":"+31 251 654 404",
    "sg:postcode":"1902 AE",
    "sg:province":"Noord-Holland",
    "sg:tags":[
        "regeltechniek",
        "en",
        "meet-"
    ],
    "wof:name":"Calculus",
    "wof:placetype":"venue"
},
  "geometry": {"coordinates":[4.673422,52.54472],"type":"Point"}
}