{
  "type": "Feature",
  "properties": {
    "addr:full":"Muidenweg 10 Wolphaartsdijk Zeeland 4471 NM",
    "addr:housenumber":"10",
    "addr:postcode":"4471",
    "addr:street":"Muidenweg",
    "iso:country":"NL",
    "sg:address":"Muidenweg 10",
    "sg:city":"Wolphaartsdijk",
    "sg:orig_category":"Kampeerterreinen",
    "sg:phone":"+31 113 581 584",
    "sg:postcode":"4471 NM",
    "sg:province":"Zeeland",
    "wof:name":"Gemaal Muidenweg",
    "wof:placetype":"venue"
},
  "geometry": {"coordinates":[3.7661020756,51.542049408],"type":"Point"}
}