{
  "type": "Feature",
  "properties": {
    "iso:country":"NL",
    "sg:address":"De Compagnie 54A",
    "sg:city":"Zwaag",
    "sg:orig_category":"Parketvloeren",
    "sg:phone":"+31 229 249 448",
    "sg:postcode":"1689 AG",
    "sg:province":"Noord-Holland",
    "sg:website":"http://www.berendsvloeren.nl",
    "wof:name":"Berends, Vloeren",
    "wof:placetype":"venue"
},
  "geometry": {"coordinates":[5.05794,52.671127],"type":"Point"}
}