{
  "type": "Feature",
  "properties": {
    "addr:full":"Beresteinlaan 311 'S Gravenhage Zuid-Holland 2542 JJ",
    "addr:housenumber":"311 '",
    "addr:postcode":"2542 jj",
    "addr:street":"Beresteinlaan",
    "iso:country":"NL",
    "sg:address":"Beresteinlaan 311",
    "sg:city":"'S Gravenhage",
    "sg:orig_category":"Meubelzaken, Woning- And Keukeninrichting",
    "sg:phone":"+31 70 329 1318",
    "sg:postcode":"2542 JJ",
    "sg:province":"Zuid-Holland",
    "wof:name":"Meubelhuis Comfort",
    "wof:placetype":"venue"
},
  "geometry": {"coordinates":[4.256094,52.040207],"type":"Point"}
}