{
  "type": "Feature",
  "properties": {
    "addr:full":"Burg Gulcherln 5 Hilversum North Holland 1217 NX",
    "addr:housenumber":"5",
    "addr:postcode":"1217 nx",
    "addr:street":"Burg Gulcherln",
    "iso:country":"NL",
    "sg:address":"Burg Gulcherln 5",
    "sg:city":"Hilversum",
    "sg:orig_category":"Adviesbureaus Bedrijfsorganisatie",
    "sg:phone":"+31 35 624 6506",
    "sg:postcode":"1217 NX",
    "sg:province":"North Holland",
    "wof:name":"Verhaak, J J M",
    "wof:placetype":"venue"
},
  "geometry": {"coordinates":[5.1695,52.228565],"type":"Point"}
}