{
  "type": "Feature",
  "properties": {
    "iso:country":"NL",
    "sg:address":"J Israelsstr 27",
    "sg:city":"Groningen",
    "sg:orig_category":"Projectontwikkeling",
    "sg:phone":"+31 50 318 9104",
    "sg:postcode":"9718 GB",
    "sg:province":"Groningen",
    "wof:name":"Cognac",
    "wof:placetype":"venue"
},
  "geometry": {"coordinates":[6.554312,53.216621],"type":"Point"}
}