{
  "type": "Feature",
  "properties": {
    "addr:full":"F Duwaerstr 14 Almere Flevoland 1318 AB",
    "addr:housenumber":"14",
    "addr:postcode":"1318 ab",
    "addr:street":"Flevoland",
    "iso:country":"NL",
    "sg:address":"F Duwaerstr 14",
    "sg:city":"Almere",
    "sg:orig_category":"Administratie- En Boekhoudkantoren",
    "sg:phone":"+31 36 534 3478",
    "sg:postcode":"1318 AB",
    "sg:province":"Flevoland",
    "wof:name":"Paisagel, Boekhoudburo",
    "wof:placetype":"venue"
},
  "geometry": {"coordinates":[5.238183,52.380344],"type":"Point"}
}