{
  "type": "Feature",
  "properties": {
    "iso:country":"NL",
    "sg:address":"Galvanistr 28-30",
    "sg:city":"Nykerk Gld",
    "sg:orig_category":"Verpakkingen En Verpakkingsmaterialen",
    "sg:phone":"+31 33 245 3349",
    "sg:postcode":"3861 NJ",
    "sg:province":"Gelderland",
    "sg:website":"http://www.tupak.nl",
    "wof:name":"Tupak Bv",
    "wof:placetype":"venue"
},
  "geometry": {"coordinates":[5.469353,52.237919],"type":"Point"}
}