{
  "type": "Feature",
  "properties": {
    "addr:full":"Havikstr 30 Badhoevedorp Noord-Holland 1171 DX",
    "addr:housenumber":"30",
    "addr:postcode":"1171 dx",
    "addr:street":"Havikstr",
    "iso:country":"NL",
    "sg:address":"Havikstr 30",
    "sg:city":"Badhoevedorp",
    "sg:orig_category":"Psychotherapeuten",
    "sg:phone":"+31 20 659 8513",
    "sg:postcode":"1171 DX",
    "sg:province":"Noord-Holland",
    "wof:name":"Kroonenberg, Drs B J",
    "wof:placetype":"venue"
},
  "geometry": {"coordinates":[4.782723,52.3395],"type":"Point"}
}