{
  "type": "Feature",
  "properties": {
    "addr:full":"Karos 30 Hoorn Nh Noord-Holland 1625 HN",
    "addr:housenumber":"30",
    "addr:postcode":"1625 hn",
    "addr:street":"Karos",
    "iso:country":"NL",
    "sg:address":"Karos 30",
    "sg:city":"Hoorn Nh",
    "sg:orig_category":"Kappers",
    "sg:phone":"+31 229 235 560",
    "sg:postcode":"1625 HN",
    "sg:province":"Noord-Holland",
    "wof:name":"Salon Van Onzenoort",
    "wof:placetype":"venue"
},
  "geometry": {"coordinates":[5.0567,52.654503],"type":"Point"}
}