{
  "type": "Feature",
  "properties": {
    "addr:full":"Vlytsewg 13 Apeldoorn Gelderland 7317 AC",
    "addr:housenumber":"13",
    "addr:postcode":"7317 ac",
    "addr:street":"Vlytsewg;Gelderland",
    "iso:country":"NL",
    "sg:address":"Vlytsewg 13",
    "sg:city":"Apeldoorn",
    "sg:orig_category":"Accountants - Administratie- Consulenten En -Kantoren",
    "sg:phone":"+31 55 521 8504",
    "sg:postcode":"7317 AC",
    "sg:province":"Gelderland",
    "wof:name":"Pijnenborg Bv, C A",
    "wof:placetype":"venue"
},
  "geometry": {"coordinates":[5.970002,52.217915],"type":"Point"}
}