{
  "type": "Feature",
  "properties": {
    "addr:full":"Forum 25 Maastricht Limburg 6229 GV",
    "addr:housenumber":"25",
    "addr:postcode":"6229 gv",
    "addr:street":"Forum",
    "iso:country":"NL",
    "sg:address":"Forum 25",
    "sg:city":"Maastricht",
    "sg:orig_category":"Werving And Selectie Van Tijdelijk Personeel And Uitzendkantoren",
    "sg:phone":"+31 43 367 2083",
    "sg:postcode":"6229 GV",
    "sg:province":"Limburg",
    "wof:name":"Quint Partner Bv",
    "wof:placetype":"venue"
},
  "geometry": {"coordinates":[5.7138700485,50.8371315002],"type":"Point"}
}