{
  "type": "Feature",
  "properties": {
    "iso:country":"NL",
    "sg:address":"Het Corteland 12",
    "sg:city":"Rijnsburg",
    "sg:orig_category":"Vertaal- And Tolkenbureaus",
    "sg:phone":"+31 71 408 0831",
    "sg:postcode":"2231 ZJ",
    "sg:province":"Zuid-Holland",
    "wof:name":"Protext Translations",
    "wof:placetype":"venue"
},
  "geometry": {"coordinates":[4.443342,52.183323],"type":"Point"}
}