{
  "type": "Feature",
  "properties": {
    "addr:full":"V Halenstr 9 Weert Limburg 6006 JW",
    "addr:housenumber":"9",
    "addr:postcode":"6006 jw",
    "addr:street":"Halenstr",
    "iso:country":"NL",
    "sg:address":"V Halenstr 9",
    "sg:city":"Weert",
    "sg:orig_category":"Kappers",
    "sg:phone":"+31 495 530 694",
    "sg:postcode":"6006 JW",
    "sg:province":"Limburg",
    "wof:name":"Elja",
    "wof:placetype":"venue"
},
  "geometry": {"coordinates":[5.682199955,51.2212600708],"type":"Point"}
}