{
  "type": "Feature",
  "properties": {
    "addr:full":"Postbus 2828 Utrecht Utrecht 3500 GV",
    "addr:housenumber":"2828",
    "addr:postcode":"3500 gv",
    "addr:street":"Postbus",
    "iso:country":"NL",
    "sg:address":"Postbus 2828",
    "sg:city":"Utrecht",
    "sg:orig_category":"Verenigingen En Stichtingen",
    "sg:phone":"+31 30 291 8171",
    "sg:postcode":"3500 GV",
    "sg:province":"Utrecht",
    "sg:website":"http://www.fietsersbond.nl",
    "wof:name":"Fietsersbond",
    "wof:placetype":"venue"
},
  "geometry": {"coordinates":[5.12289,52.091],"type":"Point"}
}