{
  "type": "Feature",
  "properties": {
    "iso:country":"NL",
    "sg:address":"Burgemeester Brouwerstr 9",
    "sg:city":"Wijngaarden Zh",
    "sg:orig_category":"Overheidsdiensten",
    "sg:phone":"+31 184 414 997",
    "sg:postcode":"3366 BA",
    "sg:province":"Zuid-Holland",
    "wof:name":"De Haveling",
    "wof:placetype":"venue"
},
  "geometry": {"coordinates":[4.7625408173,51.844039917],"type":"Point"}
}