{
  "type": "Feature",
  "properties": {
    "addr:full":"Beneden Oostdk 38 Oud Beyerland South Holland 3261 KX",
    "addr:housenumber":"38",
    "addr:postcode":"3261 kx",
    "addr:street":"Beneden Oostdk;Oud Beyerland",
    "iso:country":"NL",
    "sg:address":"Beneden Oostdk 38",
    "sg:city":"Oud Beyerland",
    "sg:orig_category":"Autopoetsbedrijven",
    "sg:phone":"+31 186 622 515",
    "sg:postcode":"3261 KX",
    "sg:province":"South Holland",
    "wof:name":"Frena, Carcleaning",
    "wof:placetype":"venue"
},
  "geometry": {"coordinates":[4.423533,51.824116],"type":"Point"}
}