{
  "type": "Feature",
  "properties": {
    "addr:full":"Marktstr 2 Wierden Overijssel 7642 AL",
    "addr:housenumber":"2",
    "addr:postcode":"7642 al",
    "addr:street":"Marktstr",
    "iso:country":"NL",
    "sg:address":"Marktstr 2",
    "sg:city":"Wierden",
    "sg:orig_category":"Postkantoren",
    "sg:phone":"+31 546 571 501",
    "sg:postcode":"7642 AL",
    "sg:province":"Overijssel",
    "sg:website":"http://www.postkantoor.nl",
    "wof:name":"Postkantoor",
    "wof:placetype":"venue"
},
  "geometry": {"coordinates":[6.591746,52.358883],"type":"Point"}
}