{
  "type": "Feature",
  "properties": {
    "addr:full":"Rooseveltlaan 1 Axel Zeeland 4571 HT",
    "addr:housenumber":"1",
    "addr:postcode":"4571 ht",
    "addr:street":"Rooseveltlaan",
    "iso:country":"NL",
    "sg:address":"Rooseveltlaan 1",
    "sg:city":"Axel",
    "sg:orig_category":"Bejaardeninstellingen And Serviceflats",
    "sg:phone":"+31 115 562 040",
    "sg:postcode":"4571 HT",
    "sg:province":"Zeeland",
    "wof:name":"Verzorgingshuis De Vurssche",
    "wof:placetype":"venue"
},
  "geometry": {"coordinates":[3.90258,51.265171],"type":"Point"}
}