{
  "type": "Feature",
  "properties": {
    "addr:full":"P A De Kok Pln 162 Dordrecht Zuid-Holland 3318 JW",
    "addr:housenumber":"pln 162",
    "addr:postcode":"3318 jw",
    "addr:street":"P A De Kok",
    "iso:country":"NL",
    "sg:address":"P A De Kok Pln 162",
    "sg:city":"Dordrecht",
    "sg:orig_category":"Acupunctuur",
    "sg:phone":"+31 78 618 0449",
    "sg:postcode":"3318 JW",
    "sg:province":"Zuid-Holland",
    "wof:name":"Slosse",
    "wof:placetype":"venue"
},
  "geometry": {"coordinates":[4.676195,51.785267],"type":"Point"}
}