{
  "type": "Feature",
  "properties": {
    "addr:full":"Paladijnenweg 18 Amersfoort Utrecht 3813 DJ",
    "addr:housenumber":"18",
    "addr:postcode":"3813 dj",
    "addr:street":"Paladijnenweg",
    "iso:country":"NL",
    "sg:address":"Paladijnenweg 18",
    "sg:city":"Amersfoort",
    "sg:orig_category":"Bedrijfs- And Managementsconsultants",
    "sg:phone":"+31 33 472 7190",
    "sg:postcode":"3813 DJ",
    "sg:province":"Utrecht",
    "wof:name":"Theunissen Consultancy",
    "wof:placetype":"venue"
},
  "geometry": {"coordinates":[5.380273,52.167648],"type":"Point"}
}