{
  "type": "Feature",
  "properties": {
    "iso:country":"NL",
    "sg:address":"Gatwickstr 33",
    "sg:city":"Amsterdam",
    "sg:orig_category":"Vakorganisaties",
    "sg:phone":"+31 20 581 8484",
    "sg:postcode":"1043 GL",
    "sg:province":"Noord-Holland",
    "sg:website":"http://www.abvakabo.nl",
    "wof:name":"Abvakabo Fnv",
    "wof:placetype":"venue"
},
  "geometry": {"coordinates":[4.842235,52.390728],"type":"Point"}
}