{
  "type": "Feature",
  "properties": {
    "addr:full":"Elspeterwg 12 Nunspeet Gelderland 8071 PA",
    "addr:housenumber":"12",
    "addr:postcode":"8071",
    "addr:street":"Elspeterwg;Gelderland",
    "iso:country":"NL",
    "sg:address":"Elspeterwg 12",
    "sg:city":"Nunspeet",
    "sg:classifiers":[
        {
            "category":"Professional",
            "subcategory":"Accounting & Tax Preparation",
            "type":"Services"
        }
    ],
    "sg:phone":"+31 341 257 144",
    "sg:postcode":"8071 PA",
    "sg:province":"Gelderland",
    "sg:tags":[
        "accountant",
        "en",
        "-kantoren",
        "register-"
    ],
    "wof:name":"Bdo",
    "wof:placetype":"venue"
},
  "geometry": {"coordinates":[5.782996,52.367817],"type":"Point"}
}