{
  "type": "Feature",
  "properties": {
    "addr:full":"Dorpsstraat 47 Vlieland Friesland 8899 AC",
    "addr:housenumber":"47",
    "addr:postcode":"8899 ac",
    "addr:street":"Dorpsstraat",
    "iso:country":"NL",
    "sg:address":"Dorpsstraat 47",
    "sg:city":"Vlieland",
    "sg:orig_category":"Banken And Kredietinstellingen",
    "sg:phone":"+31 562 451 986",
    "sg:postcode":"8899 AC",
    "sg:province":"Friesland",
    "wof:name":"Postkantoor",
    "wof:placetype":"venue"
},
  "geometry": {"coordinates":[5.070348,53.295879],"type":"Point"}
}