{
  "type": "Feature",
  "properties": {
    "iso:country":"NL",
    "sg:address":"Huis Ter Duinstr 50",
    "sg:city":"Noordwyk Zh",
    "sg:orig_category":"Verzekeringen - Verzekeringskantoren",
    "sg:phone":"+31 71 361 9683",
    "sg:postcode":"2202 CV",
    "sg:province":"South Holland",
    "wof:name":"Duinlander, De",
    "wof:placetype":"venue"
},
  "geometry": {"coordinates":[4.433689,52.241993],"type":"Point"}
}