{
  "type": "Feature",
  "properties": {
    "addr:full":"Zaaierstr 2 Enschede NL.08 7545 XD",
    "addr:housenumber":"2",
    "addr:postcode":"7545 xd",
    "addr:street":"Zaaierstr",
    "iso:country":"NL",
    "sg:address":"Zaaierstr 2",
    "sg:city":"Enschede",
    "sg:orig_category":"Kappers",
    "sg:phone":"+31 6 29496991",
    "sg:postcode":"7545 XD",
    "sg:province":"NL.08",
    "wof:name":"Karina",
    "wof:placetype":"venue"
},
  "geometry": {"coordinates":[6.8680081367,52.2114448547],"type":"Point"}
}