{
  "type": "Feature",
  "properties": {
    "addr:full":"Nyverheidswg 27 Wervershoof Noord-Holland 1693 AM",
    "addr:housenumber":"27",
    "addr:postcode":"1693",
    "addr:street":"Nyverheidswg",
    "iso:country":"NL",
    "sg:address":"Nyverheidswg 27",
    "sg:city":"Wervershoof",
    "sg:classifiers":[
        {
            "category":"Retail",
            "subcategory":"Auto Repair",
            "type":"Services"
        }
    ],
    "sg:phone":"+31 228 581 213",
    "sg:postcode":"1693 AM",
    "sg:province":"Noord-Holland",
    "sg:tags":[
        "garage"
    ],
    "wof:name":"All-Round Bv, Garage",
    "wof:placetype":"venue"
},
  "geometry": {"coordinates":[5.161662,52.736233],"type":"Point"}
}