{
  "type": "Feature",
  "properties": {
    "addr:full":"Ruitercamp 111 Houten Utrecht 3992 BZ",
    "addr:housenumber":"111",
    "addr:postcode":"3992 bz",
    "addr:street":"Ruitercamp",
    "iso:country":"NL",
    "sg:address":"Ruitercamp 111",
    "sg:city":"Houten",
    "sg:orig_category":"Fotostudio'S And Fotografen",
    "sg:phone":"+31 30 634 1696",
    "sg:postcode":"3992 BZ",
    "sg:province":"Utrecht",
    "wof:name":"Rob Meijer Fotografie",
    "wof:placetype":"venue"
},
  "geometry": {"coordinates":[5.14821,52.032188],"type":"Point"}
}