{
  "type": "Feature",
  "properties": {
    "addr:full":"Rynspoor 26 Houten Utrecht 3994 VH",
    "addr:housenumber":"26",
    "addr:postcode":"3994 vh",
    "addr:street":"Rynspoor",
    "iso:country":"NL",
    "sg:address":"Rynspoor 26",
    "sg:city":"Houten",
    "sg:orig_category":"Adviesbureaus Bedrijfsorganisatie",
    "sg:phone":"+31 30 699 2027",
    "sg:postcode":"3994 VH",
    "sg:province":"Utrecht",
    "sg:website":"http://www.denkgoed.nl",
    "wof:name":"Denkgoed",
    "wof:placetype":"venue"
},
  "geometry": {"coordinates":[5.169435,52.036541],"type":"Point"}
}