{
  "type": "Feature",
  "properties": {
    "addr:full":"De Keyzerstr 51 Zwolle Overijssel 8023 VW",
    "addr:housenumber":"51",
    "addr:postcode":"8023 vw",
    "iso:country":"NL",
    "sg:address":"De Keyzerstr 51",
    "sg:city":"Zwolle",
    "sg:orig_category":"Begrafenisverzorging",
    "sg:phone":"+31 38 453 6320",
    "sg:postcode":"8023 VW",
    "sg:province":"Overijssel",
    "wof:name":"Klaassen, Marjon",
    "wof:placetype":"venue"
},
  "geometry": {"coordinates":[6.112217,52.511551],"type":"Point"}
}