{
  "type": "Feature",
  "properties": {
    "addr:full":"Suraeweg 55 Dorst Noord-Brabant 4849 PK",
    "addr:housenumber":"55",
    "addr:postcode":"4849 pk",
    "addr:street":"Suraeweg",
    "iso:country":"NL",
    "sg:address":"Suraeweg 55",
    "sg:city":"Dorst",
    "sg:orig_category":"Partycatering And -Organisatie",
    "sg:phone":"+31 161 412 535",
    "sg:postcode":"4849 PK",
    "sg:province":"Noord-Brabant",
    "wof:name":"Catering Totaal Catering",
    "wof:placetype":"venue"
},
  "geometry": {"coordinates":[4.86037,51.590984],"type":"Point"}
}