{
  "type": "Feature",
  "properties": {
    "addr:full":"Koppelstokstraat 91 'S Gravenhage Zuid-Holland 2583 CB",
    "addr:housenumber":"91",
    "addr:postcode":"2583 cb",
    "addr:street":"Koppelstokstraat;' S",
    "iso:country":"NL",
    "sg:address":"Koppelstokstraat 91",
    "sg:city":"'S Gravenhage",
    "sg:orig_category":"Diverse Grafische Activiteiten",
    "sg:phone":"+31 70 306 3075",
    "sg:postcode":"2583 CB",
    "sg:province":"Zuid-Holland",
    "wof:name":"De 1E Etage",
    "wof:placetype":"venue"
},
  "geometry": {"coordinates":[4.26758,52.095493],"type":"Point"}
}