{
  "type": "Feature",
  "properties": {
    "iso:country":"NL",
    "sg:address":"Marianellastr 66",
    "sg:city":"Amsterdam",
    "sg:orig_category":"Kappers",
    "sg:phone":"+31 20 610 5878",
    "sg:postcode":"1069 NM",
    "sg:province":"North Holland",
    "wof:name":"Hoeve, A Ter",
    "wof:placetype":"venue"
},
  "geometry": {"coordinates":[4.7763528824,52.3539009094],"type":"Point"}
}