{
  "type": "Feature",
  "properties": {
    "addr:full":"Brederoodsewg 39 Santpoort Zuid Noord-Holland 2082 BS",
    "addr:housenumber":"39",
    "addr:postcode":"2082 bs",
    "addr:street":"Brederoodsewg;Santpoort",
    "iso:country":"NL",
    "sg:address":"Brederoodsewg 39",
    "sg:city":"Santpoort Zuid",
    "sg:orig_category":"Adviesbureaus Bedrijfsorganisatie",
    "sg:phone":"+31 23 538 2555",
    "sg:postcode":"2082 BS",
    "sg:province":"Noord-Holland",
    "wof:name":"Koning, A De",
    "wof:placetype":"venue"
},
  "geometry": {"coordinates":[4.62568,52.424187],"type":"Point"}
}