{
  "type": "Feature",
  "properties": {
    "addr:full":"Lodderhoeksestr 14 Angeren Gelderland 6687 LS",
    "addr:housenumber":"14",
    "addr:postcode":"6687 ls",
    "addr:street":"Lodderhoeksestr;Gelderland",
    "iso:country":"NL",
    "sg:address":"Lodderhoeksestr 14",
    "sg:city":"Angeren",
    "sg:orig_category":"Kantoor- En Bedrijfsmeubelen",
    "sg:phone":"+31 26 325 2552",
    "sg:postcode":"6687 LS",
    "sg:province":"Gelderland",
    "wof:name":"Peters",
    "wof:placetype":"venue"
},
  "geometry": {"coordinates":[5.9647369385,51.9110603333],"type":"Point"}
}