{
  "type": "Feature",
  "properties": {
    "addr:full":"Nijverheidsstraat 8 Gorssel Gelderland 7213 DB",
    "addr:housenumber":"8",
    "addr:postcode":"7213 db",
    "addr:street":"Nijverheidsstraat;Gelderland",
    "iso:country":"NL",
    "sg:address":"Nijverheidsstraat 8",
    "sg:city":"Gorssel",
    "sg:orig_category":"Woningbouwverenigingen",
    "sg:phone":"+31 575 492 773",
    "sg:postcode":"7213 DB",
    "sg:province":"Gelderland",
    "wof:name":"Bouwvereniging Gorssel",
    "wof:placetype":"venue"
},
  "geometry": {"coordinates":[6.2016859055,52.2013816833],"type":"Point"}
}