{
  "type": "Feature",
  "properties": {
    "addr:full":"Dierenriemstraat 258 Groningen Groningen 9742 AN",
    "addr:housenumber":"258",
    "addr:postcode":"9742 an",
    "addr:street":"Dierenriemstraat",
    "iso:country":"NL",
    "sg:address":"Dierenriemstraat 258",
    "sg:city":"Groningen",
    "sg:classifiers":[
        {
            "category":"Bakery",
            "type":"Food & Drink"
        }
    ],
    "sg:phone":"+31 50 577 9922",
    "sg:postcode":"9742 AN",
    "sg:province":"Groningen",
    "sg:tags":[
        "brood",
        "banket"
    ],
    "wof:name":"Echte Bakker Petra & Wilfred Haafs",
    "wof:placetype":"venue"
},
  "geometry": {"coordinates":[6.545317,53.230522],"type":"Point"}
}