{
  "type": "Feature",
  "properties": {
    "addr:full":"Nw Zeelandwg 6K Amsterdam Noord-Holland 1045 AL",
    "addr:housenumber":"6k",
    "addr:postcode":"1045 al",
    "addr:street":"Zeelandwg",
    "iso:country":"NL",
    "sg:address":"Nw Zeelandwg 6K",
    "sg:city":"Amsterdam",
    "sg:orig_category":"Meubelmakerijen",
    "sg:phone":"+31 20 632 4688",
    "sg:postcode":"1045 AL",
    "sg:province":"Noord-Holland",
    "wof:name":"Mertens",
    "wof:placetype":"venue"
},
  "geometry": {"coordinates":[4.80161,52.410458],"type":"Point"}
}