{
  "type": "Feature",
  "properties": {
    "addr:full":"Kerkstr 7 Nederhorst D Berg Noord-Holland 1394 CW",
    "addr:housenumber":"7",
    "addr:postcode":"1394 cw",
    "addr:street":"Kerkstr;Nederhorst D Berg",
    "iso:country":"NL",
    "sg:address":"Kerkstr 7",
    "sg:city":"Nederhorst D Berg",
    "sg:orig_category":"Verenigingsgebouwen",
    "sg:phone":"+31 294 254 026",
    "sg:postcode":"1394 CW",
    "sg:province":"Noord-Holland",
    "wof:name":"Bergplaats, De",
    "wof:placetype":"venue"
},
  "geometry": {"coordinates":[-93.019066,36.305519],"type":"Point"}
}