{
  "type": "Feature",
  "properties": {
    "addr:full":"Spaarnbergln 26 Santpoort Noord Noord-Holland 2071 AD",
    "addr:housenumber":"26",
    "addr:postcode":"2071 ad",
    "addr:street":"Spaarnbergln",
    "iso:country":"NL",
    "sg:address":"Spaarnbergln 26",
    "sg:city":"Santpoort Noord",
    "sg:orig_category":"Adviesbureaus Bedrijfsorganisatie",
    "sg:phone":"+31 23 538 8108",
    "sg:postcode":"2071 AD",
    "sg:province":"Noord-Holland",
    "wof:name":"Gista Bv",
    "wof:placetype":"venue"
},
  "geometry": {"coordinates":[-121.95871,39.780125],"type":"Point"}
}