{
  "type": "Feature",
  "properties": {
    "addr:full":"Hoogstr 123 Berlicum Nb Noord-Brabant 5258 BC",
    "addr:housenumber":"123",
    "addr:postcode":"5258 bc",
    "iso:country":"NL",
    "sg:address":"Hoogstr 123",
    "sg:city":"Berlicum Nb",
    "sg:orig_category":"Biljarts - Fabrieken",
    "sg:phone":"+31 73 503 1264",
    "sg:postcode":"5258 BC",
    "sg:province":"Noord-Brabant",
    "sg:website":"http://www.eureka-billard.nl",
    "wof:name":"Eureka",
    "wof:placetype":"venue"
},
  "geometry": {"coordinates":[5.396669,51.679779],"type":"Point"}
}