{
  "type": "Feature",
  "properties": {
    "addr:full":"Witkopeend 16 Uithoorn Noord-Holland 1423 SN",
    "addr:housenumber":"16",
    "addr:postcode":"1423 sn",
    "addr:street":"Witkopeend",
    "iso:country":"NL",
    "sg:address":"Witkopeend 16",
    "sg:city":"Uithoorn",
    "sg:orig_category":"Glazenwasserijen",
    "sg:phone":"+31 297 561 140",
    "sg:postcode":"1423 SN",
    "sg:province":"Noord-Holland",
    "wof:name":"Scheers, J",
    "wof:placetype":"venue"
},
  "geometry": {"coordinates":[4.812491,52.235741],"type":"Point"}
}