{
  "type": "Feature",
  "properties": {
    "iso:country":"NL",
    "sg:address":"Industriewg 90B",
    "sg:city":"Waalwyk",
    "sg:orig_category":"Meubelmakerijen",
    "sg:phone":"+31 416 353 780",
    "sg:postcode":"5145 PW",
    "sg:province":"Noord-Brabant",
    "wof:name":"Kapel, Van",
    "wof:placetype":"venue"
},
  "geometry": {"coordinates":[5.062109,51.705544],"type":"Point"}
}