{
  "type": "Feature",
  "properties": {
    "addr:full":"Aletta Jacobsweg 34 Assen Drenthe 9408 AM",
    "addr:housenumber":"34",
    "addr:postcode":"9408",
    "addr:street":"Aletta Jacobsweg",
    "iso:country":"NL",
    "sg:address":"Aletta Jacobsweg 34",
    "sg:city":"Assen",
    "sg:orig_category":"Administratie- En Boekhoudkantoren",
    "sg:phone":"+31 592 398 066",
    "sg:postcode":"9408 AM",
    "sg:province":"Drenthe",
    "wof:name":"Hogendorf, W B",
    "wof:placetype":"venue"
},
  "geometry": {"coordinates":[6.507428,53.000458],"type":"Point"}
}