{
  "type": "Feature",
  "properties": {
    "addr:full":"Wiekenwg 11 Heerde Gelderland 8181 AX",
    "addr:housenumber":"11",
    "addr:postcode":"8181 ax",
    "addr:street":"Wiekenwg;Gelderland",
    "iso:country":"NL",
    "sg:address":"Wiekenwg 11",
    "sg:city":"Heerde",
    "sg:orig_category":"Machinehandel",
    "sg:phone":"+31 578 696 844",
    "sg:postcode":"8181 AX",
    "sg:province":"Gelderland",
    "sg:website":"http://www.rothi.nl",
    "wof:name":"Rothi Machinehandel",
    "wof:placetype":"venue"
},
  "geometry": {"coordinates":[6.047054,52.39563],"type":"Point"}
}