{
  "type": "Feature",
  "properties": {
    "addr:full":"Hoefblad 18 Rynsburg Zuid-Holland 2231 WS",
    "addr:housenumber":"18",
    "addr:postcode":"2231 ws",
    "addr:street":"Hoefblad",
    "iso:country":"NL",
    "sg:address":"Hoefblad 18",
    "sg:city":"Rynsburg",
    "sg:orig_category":"Verenigingen En Stichtingen",
    "sg:phone":"+31 71 402 7856",
    "sg:postcode":"2231 WS",
    "sg:province":"Zuid-Holland",
    "wof:name":"Amnesty International Groep Rijnsburg",
    "wof:placetype":"venue"
},
  "geometry": {"coordinates":[4.434743,52.194675],"type":"Point"}
}