{
  "type": "Feature",
  "properties": {
    "iso:country":"NL",
    "sg:address":"Ransdalerstraat 95",
    "sg:city":"Ransdaal",
    "sg:orig_category":"Bloemen And Planten",
    "sg:phone":"+31 43 459 1348",
    "sg:postcode":"6311 AX",
    "sg:province":"Limburg",
    "wof:name":"T Magazijn",
    "wof:placetype":"venue"
},
  "geometry": {"coordinates":[5.896152,50.865147],"type":"Point"}
}