{
  "type": "Feature",
  "properties": {
    "iso:country":"NL",
    "sg:address":"Zuidermolenweg 23",
    "sg:city":"Amsterdam",
    "sg:orig_category":"Diverse Grafische Activiteiten",
    "sg:phone":"+31 20 619 6157",
    "sg:postcode":"1069 CE",
    "sg:province":"Noord-Holland",
    "wof:name":"Binderij Lotgering",
    "wof:placetype":"venue"
},
  "geometry": {"coordinates":[4.78199,52.359707],"type":"Point"}
}