{
  "type": "Feature",
  "properties": {
    "addr:full":"Cuneraweg 318 Rhenen Utrecht 3911 RT",
    "addr:housenumber":"318",
    "addr:postcode":"3911 rt",
    "addr:street":"Cuneraweg",
    "iso:country":"NL",
    "sg:address":"Cuneraweg 318",
    "sg:city":"Rhenen",
    "sg:orig_category":"Farmaceutische Producten Gh",
    "sg:phone":"+31 318 513 142",
    "sg:postcode":"3911 RT",
    "sg:province":"Utrecht",
    "wof:name":"Alprovi",
    "wof:placetype":"venue"
},
  "geometry": {"coordinates":[5.549306,51.999397],"type":"Point"}
}