{
  "type": "Feature",
  "properties": {
    "iso:country":"NL",
    "sg:address":"Oostelijke Handelskade 34",
    "sg:city":"Amsterdam",
    "sg:orig_category":"Geluidsopnamen",
    "sg:phone":"+31 20 418 6450",
    "sg:postcode":"1019 BN",
    "sg:province":"Noord-Holland",
    "wof:name":"Ijlandstudio",
    "wof:placetype":"venue"
},
  "geometry": {"coordinates":[4.935694,52.3741],"type":"Point"}
}