{
  "type": "Feature",
  "properties": {
    "iso:country":"NL",
    "sg:address":"De Oude Ros 18",
    "sg:city":"Nistelrode",
    "sg:orig_category":"Meubelmakerijen",
    "sg:phone":"+31 412 613 439",
    "sg:postcode":"5388 PM",
    "sg:province":"Noord-Brabant",
    "wof:name":"Victor",
    "wof:placetype":"venue"
},
  "geometry": {"coordinates":[5.564969,51.713291],"type":"Point"}
}