{
  "type": "Feature",
  "properties": {
    "addr:full":"Vd Glashof 7 Amersfoort Utrecht 3816 MN",
    "addr:housenumber":"7",
    "addr:postcode":"3816 mn",
    "addr:street":"Glashof",
    "iso:country":"NL",
    "sg:address":"Vd Glashof 7",
    "sg:city":"Amersfoort",
    "sg:orig_category":"Hulpverlening Sociaal",
    "sg:phone":"+31 33 494 0752",
    "sg:postcode":"3816 MN",
    "sg:province":"Utrecht",
    "wof:name":"Movement",
    "wof:placetype":"venue"
},
  "geometry": {"coordinates":[5.400649,52.15213],"type":"Point"}
}