{
  "type": "Feature",
  "properties": {
    "addr:full":"De Leim 5 Maastricht Limburg 6227 CT",
    "addr:housenumber":"5",
    "addr:postcode":"6227 ct",
    "addr:street":"De Leim",
    "iso:country":"NL",
    "sg:address":"De Leim 5",
    "sg:city":"Maastricht",
    "sg:orig_category":"Discountwinkels",
    "sg:phone":"+31 43 356 0101",
    "sg:postcode":"6227 CT",
    "sg:province":"Limburg",
    "wof:name":"Zeeman Textielsupers",
    "wof:placetype":"venue"
},
  "geometry": {"coordinates":[5.728277,50.843155],"type":"Point"}
}