{
  "type": "Feature",
  "properties": {
    "addr:full":"P C Hooftln 22 Driehuis Nh Noord-Holland 1985 BJ",
    "addr:housenumber":"22",
    "addr:postcode":"1985 bj",
    "addr:street":"P C Hooftln",
    "iso:country":"NL",
    "sg:address":"P C Hooftln 22",
    "sg:city":"Driehuis Nh",
    "sg:classifiers":[
        {
            "category":"Professional",
            "subcategory":"Management & Consulting",
            "type":"Services"
        }
    ],
    "sg:phone":"+31 255 510 389",
    "sg:postcode":"1985 BJ",
    "sg:province":"Noord-Holland",
    "sg:tags":[
        "relation",
        "adviesbureaus",
        "public"
    ],
    "wof:name":"Galavazi",
    "wof:placetype":"venue"
},
  "geometry": {"coordinates":[4.634897,52.446468],"type":"Point"}
}