{
  "type": "Feature",
  "properties": {
    "addr:full":"Hugo De Grootplein 18 Amsterdam Noord-Holland 1052 KX",
    "addr:housenumber":"18",
    "addr:postcode":"1052 kx",
    "addr:street":"Hugo De Grootplein",
    "iso:country":"NL",
    "sg:address":"Hugo De Grootplein 18",
    "sg:city":"Amsterdam",
    "sg:orig_category":"Kappers",
    "sg:phone":"+31 20 688 1608",
    "sg:postcode":"1052 KX",
    "sg:province":"Noord-Holland",
    "wof:name":"Dameskapsalon Joyce",
    "wof:placetype":"venue"
},
  "geometry": {"coordinates":[4.872387886,52.3749885559],"type":"Point"}
}