{
  "type": "Feature",
  "properties": {
    "addr:full":"Hillenaarln 54 Wassenaar South Holland 2241 JZ",
    "addr:housenumber":"54",
    "addr:postcode":"2241 jz",
    "addr:street":"Hillenaarln",
    "iso:country":"NL",
    "sg:address":"Hillenaarln 54",
    "sg:city":"Wassenaar",
    "sg:orig_category":"Wijnkoperijen En -Groothandel",
    "sg:phone":"+31 70 511 5648",
    "sg:postcode":"2241 JZ",
    "sg:province":"South Holland",
    "wof:name":"Riqueza De Espana",
    "wof:placetype":"venue"
},
  "geometry": {"coordinates":[4.4046349525,52.1425476074],"type":"Point"}
}