{
  "type": "Feature",
  "properties": {
    "addr:full":"Boerhaavestr 9 Bovenkarspel North Holland 1611 ER",
    "addr:housenumber":"9",
    "addr:postcode":"1611 er",
    "addr:street":"Boerhaavestr",
    "iso:country":"NL",
    "sg:address":"Boerhaavestr 9",
    "sg:city":"Bovenkarspel",
    "sg:orig_category":"Winkelinrichting",
    "sg:phone":"+31 228 515 352",
    "sg:postcode":"1611 ER",
    "sg:province":"North Holland",
    "wof:name":"Babonnick",
    "wof:placetype":"venue"
},
  "geometry": {"coordinates":[5.2478141785,52.6906433105],"type":"Point"}
}