{
  "type": "Feature",
  "properties": {
    "iso:country":"NL",
    "sg:address":"Roermondseweg 132",
    "sg:city":"Steijl",
    "sg:orig_category":"Artsen And Specialisten",
    "sg:phone":"+31 77 373 1939",
    "sg:postcode":"5935 AD",
    "sg:province":"Limburg",
    "wof:name":"A.W.M. Gierlings",
    "wof:placetype":"venue"
},
  "geometry": {"coordinates":[6.12579,51.335209],"type":"Point"}
}