{
  "type": "Feature",
  "properties": {
    "addr:full":"Prins Hendrikstraat 221A Hoek Van Holland South Holland 3151 AH",
    "addr:housenumber":"221a",
    "addr:postcode":"3151 ah",
    "addr:street":"Prins Hendrikstraat",
    "iso:country":"NL",
    "sg:address":"Prins Hendrikstraat 221A",
    "sg:city":"Hoek Van Holland",
    "sg:classifiers":[
        {
            "category":"Shopping",
            "subcategory":"Gifts & Souvenirs",
            "type":"Retail Goods"
        }
    ],
    "sg:phone":"+31 174 385 462",
    "sg:postcode":"3151 AH",
    "sg:province":"South Holland",
    "sg:tags":[
        "geschenken"
    ],
    "wof:name":"Wereldwinkel",
    "wof:placetype":"venue"
},
  "geometry": {"coordinates":[4.131546,51.976906],"type":"Point"}
}