{
  "type": "Feature",
  "properties": {
    "addr:full":"Hogewg 2 Dreumel Gelderland 6621 BN",
    "addr:housenumber":"2",
    "addr:postcode":"6621 bn",
    "addr:street":"Hogewg;Gelderland",
    "iso:country":"NL",
    "sg:address":"Hogewg 2",
    "sg:city":"Dreumel",
    "sg:orig_category":"Beeldende Kunstenaars",
    "sg:phone":"+31 487 270 444",
    "sg:postcode":"6621 BN",
    "sg:province":"Gelderland",
    "wof:name":"Goede Moet, De",
    "wof:placetype":"venue"
},
  "geometry": {"coordinates":[5.434173,51.854103],"type":"Point"}
}