{
  "type": "Feature",
  "properties": {
    "iso:country":"NL",
    "sg:address":"Van Helvoortlaan 21",
    "sg:city":"Woerden",
    "sg:orig_category":"Autokeuringen",
    "sg:phone":"+31 348 410 525",
    "sg:postcode":"3443 AP",
    "sg:province":"Utrecht",
    "wof:name":"E. Van Laar",
    "wof:placetype":"venue"
},
  "geometry": {"coordinates":[4.885744,52.091152],"type":"Point"}
}