{
  "type": "Feature",
  "properties": {
    "addr:full":"F Zeilemakerstr 50 Alkmaar Noord-Holland 1827 PH",
    "addr:housenumber":"50",
    "addr:postcode":"1827",
    "iso:country":"NL",
    "sg:address":"F Zeilemakerstr 50",
    "sg:city":"Alkmaar",
    "sg:orig_category":"Adviesbureaus Bedrijfsorganisatie",
    "sg:phone":"+31 72 564 6854",
    "sg:postcode":"1827 PH",
    "sg:province":"Noord-Holland",
    "wof:name":"Breejen, Den",
    "wof:placetype":"venue"
},
  "geometry": {"coordinates":[4.76853,52.669758],"type":"Point"}
}