{
  "type": "Feature",
  "properties": {
    "addr:full":"Vlierstr 780 Enschede NL.08 7544 GV",
    "addr:housenumber":"780",
    "addr:postcode":"7544",
    "addr:street":"Gv",
    "iso:country":"NL",
    "sg:address":"Vlierstr 780",
    "sg:city":"Enschede",
    "sg:orig_category":"Fietsen En Bromfietsen Onderdelen - Fabr. En Grooth",
    "sg:phone":"+31 53 431 5666",
    "sg:postcode":"7544 GV",
    "sg:province":"NL.08",
    "wof:name":"Wagelaar Bv, A J",
    "wof:placetype":"venue"
},
  "geometry": {"coordinates":[6.890048,52.196701],"type":"Point"}
}