{
  "type": "Feature",
  "properties": {
    "iso:country":"NL",
    "sg:address":"Binckhorstln 279",
    "sg:city":"S Gravenhage",
    "sg:orig_category":"Autopoetsbedrijven",
    "sg:phone":"+31 6 12708311",
    "sg:postcode":"2516 BB",
    "sg:province":"South Holland",
    "wof:name":"Amc Service",
    "wof:placetype":"venue"
},
  "geometry": {"coordinates":[4.33931,52.06786],"type":"Point"}
}