{
  "type": "Feature",
  "properties": {
    "addr:full":"Deldenstraat 47 Tilburg North Brabant 5043 GH",
    "addr:housenumber":"47",
    "addr:postcode":"5043 gh",
    "addr:street":"Deldenstraat",
    "iso:country":"NL",
    "sg:address":"Deldenstraat 47",
    "sg:city":"Tilburg",
    "sg:orig_category":"Diverse Grafische Activiteiten",
    "sg:phone":"+31 13 571 6527",
    "sg:postcode":"5043 GH",
    "sg:province":"North Brabant",
    "wof:name":"Break 4 U",
    "wof:placetype":"venue"
},
  "geometry": {"coordinates":[5.01371,51.577332],"type":"Point"}
}