{
  "type": "Feature",
  "properties": {
    "addr:full":"Nieuwewg 6A Eemnes Utrecht 3755 AC",
    "addr:housenumber":"6a",
    "addr:postcode":"3755 ac",
    "addr:street":"Nieuwewg",
    "iso:country":"NL",
    "sg:address":"Nieuwewg 6A",
    "sg:city":"Eemnes",
    "sg:orig_category":"Verpakkingsmachines",
    "sg:phone":"+31 35 538 0805",
    "sg:postcode":"3755 AC",
    "sg:province":"Utrecht",
    "wof:name":"Aquarius Bv",
    "wof:placetype":"venue"
},
  "geometry": {"coordinates":[5.25076,52.254753],"type":"Point"}
}