{
  "type": "Feature",
  "properties": {
    "addr:full":"Paulineweg 9 Bergen Aan Zee Noord-Holland 1865 AD",
    "addr:housenumber":"9",
    "addr:postcode":"1865 ad",
    "addr:street":"Paulineweg",
    "iso:country":"NL",
    "sg:address":"Paulineweg 9",
    "sg:city":"Bergen Aan Zee",
    "sg:classifiers":[
        {
            "category":"Travel",
            "subcategory":"Hotels & Motels",
            "type":"Entertainment"
        }
    ],
    "sg:phone":"+31 72 581 4011",
    "sg:postcode":"1865 AD",
    "sg:province":"Noord-Holland",
    "wof:name":"Zee En Duin",
    "wof:placetype":"venue"
},
  "geometry": {"coordinates":[4.631784,52.659698],"type":"Point"}
}