{
  "type": "Feature",
  "properties": {
    "iso:country":"NL",
    "sg:address":"Ryksstrwg 5",
    "sg:city":"Ridderkerk",
    "sg:orig_category":"Zalenverhuur",
    "sg:phone":"+31 180 420 435",
    "sg:postcode":"2988 BA",
    "sg:province":"South Holland",
    "wof:name":"Struweel, 'T",
    "wof:placetype":"venue"
},
  "geometry": {"coordinates":[4.59669,51.849644],"type":"Point"}
}