{
  "type": "Feature",
  "properties": {
    "addr:full":"Stationstraat 260 Nuth Limburg 6361 BH",
    "addr:housenumber":"260",
    "addr:postcode":"6361 bh",
    "addr:street":"Stationstraat",
    "iso:country":"NL",
    "sg:address":"Stationstraat 260",
    "sg:city":"Nuth",
    "sg:orig_category":"Kappers",
    "sg:phone":"+31 45 524 2009",
    "sg:postcode":"6361 BH",
    "sg:province":"Limburg",
    "wof:name":"Cherrida'S Hairworld",
    "wof:placetype":"venue"
},
  "geometry": {"coordinates":[5.8859992027,50.9187850952],"type":"Point"}
}