{
  "type": "Feature",
  "properties": {
    "addr:full":"Thomsonpln 8 S Gravenhage Zuid-Holland 2565 KS",
    "addr:housenumber":"8 s",
    "addr:postcode":"2565 ks",
    "addr:street":"Thomsonpln",
    "iso:country":"NL",
    "sg:address":"Thomsonpln 8",
    "sg:city":"S Gravenhage",
    "sg:orig_category":"Bejaarden - Verzorgingstehuizen",
    "sg:phone":"+31 70 365 7244",
    "sg:postcode":"2565 KS",
    "sg:province":"Zuid-Holland",
    "wof:name":"Lucinda, Huize",
    "wof:placetype":"venue"
},
  "geometry": {"coordinates":[4.26129,52.076382],"type":"Point"}
}