{
  "type": "Feature",
  "properties": {
    "addr:full":"Wilhelm Tellplaats 40 Hoogvliet Rt South Holland 3194 HT",
    "addr:housenumber":"40",
    "addr:postcode":"3194 ht",
    "addr:street":"Wilhelm Tellplaats;Rt South",
    "iso:country":"NL",
    "sg:address":"Wilhelm Tellplaats 40",
    "sg:city":"Hoogvliet Rt",
    "sg:orig_category":"Kappers",
    "sg:phone":"+31 10 438 0963",
    "sg:postcode":"3194 HT",
    "sg:province":"South Holland",
    "wof:name":"Pour-Vous Coiffures",
    "wof:placetype":"venue"
},
  "geometry": {"coordinates":[4.361885,51.870289],"type":"Point"}
}