{
  "type": "Feature",
  "properties": {
    "addr:full":"Kl Berg 48 Eindhoven North Brabant 5611 JV",
    "addr:housenumber":"48",
    "addr:postcode":"5611 jv",
    "addr:street":"Kl Berg",
    "iso:country":"NL",
    "sg:address":"Kl Berg 48",
    "sg:city":"Eindhoven",
    "sg:orig_category":"Boeken En Tijdschriften",
    "sg:phone":"+31 40 245 6261",
    "sg:postcode":"5611 JV",
    "sg:province":"North Brabant",
    "wof:name":"Boekenberg",
    "wof:placetype":"venue"
},
  "geometry": {"coordinates":[5.476977,51.436241],"type":"Point"}
}