{
  "type": "Feature",
  "properties": {
    "addr:full":"Keenenburgwg 25 Schipluiden South Holland 2636 GK",
    "addr:housenumber":"25",
    "addr:postcode":"2636 gk",
    "addr:street":"Keenenburgwg",
    "iso:country":"NL",
    "sg:address":"Keenenburgwg 25",
    "sg:city":"Schipluiden",
    "sg:orig_category":"Bedrijfsorganisaties",
    "sg:phone":"+31 15 380 7453",
    "sg:postcode":"2636 GK",
    "sg:province":"South Holland",
    "wof:name":"Werkpunt Bv",
    "wof:placetype":"venue"
},
  "geometry": {"coordinates":[4.317642,51.975666],"type":"Point"}
}