{
  "type": "Feature",
  "properties": {
    "addr:full":"Horst 1037 Lelystad NL. 8225 LR",
    "addr:postcode":"1037;8225 lr",
    "addr:street":"Horst;Nl.",
    "iso:country":"NL",
    "sg:address":"Horst 1037",
    "sg:city":"Lelystad",
    "sg:orig_category":"Partycatering And -Organisatie",
    "sg:phone":"+31 320 233 549",
    "sg:postcode":"8225 LR",
    "sg:province":"NL.",
    "wof:name":"Maxi",
    "wof:placetype":"venue"
},
  "geometry": {"coordinates":[5.497994,52.501896],"type":"Point"}
}