{
  "type": "Feature",
  "properties": {
    "iso:country":"NL",
    "sg:address":"Amstelveensewg 647",
    "sg:city":"Amsterdam",
    "sg:orig_category":"Hypotheken",
    "sg:phone":"+31 20 642 8755",
    "sg:postcode":"1081 JD",
    "sg:province":"Noord-Holland",
    "sg:website":"http://www.amsterdam.hypotheekshop.nl/585",
    "wof:name":"Hypotheekshop, De",
    "wof:placetype":"venue"
},
  "geometry": {"coordinates":[4.857613,52.33157],"type":"Point"}
}