{
  "type": "Feature",
  "properties": {
    "addr:full":"Poldermeesterhof 12 Krimpen A/D Ijssel Zuid-Holland 2922 CW",
    "addr:housenumber":"12;a / d",
    "addr:postcode":"2922 cw",
    "addr:street":"Poldermeesterhof",
    "iso:country":"NL",
    "sg:address":"Poldermeesterhof 12",
    "sg:city":"Krimpen A/D Ijssel",
    "sg:orig_category":"Autokeuringen",
    "sg:phone":"+31 180 510 915",
    "sg:postcode":"2922 CW",
    "sg:province":"Zuid-Holland",
    "wof:name":"Jawi Vorkheftrucks",
    "wof:placetype":"venue"
},
  "geometry": {"coordinates":[4.594379,51.920876],"type":"Point"}
}