{
  "type": "Feature",
  "properties": {
    "addr:full":"Badwg 17 Schiermonnikoog Friesland 9166 ND",
    "addr:housenumber":"17",
    "addr:postcode":"9166 nd",
    "addr:street":"Badwg",
    "iso:country":"NL",
    "sg:address":"Badwg 17",
    "sg:city":"Schiermonnikoog",
    "sg:classifiers":[
        {
            "category":"Travel",
            "subcategory":"Hotels & Motels",
            "type":"Entertainment"
        }
    ],
    "sg:phone":"+31 519 531 218",
    "sg:postcode":"9166 ND",
    "sg:province":"Friesland",
    "sg:website":"http://www.schiermonnikoog.net/duinzicht",
    "wof:name":"Duinzicht",
    "wof:placetype":"venue"
},
  "geometry": {"coordinates":[6.160104,53.481651],"type":"Point"}
}