{
  "type": "Feature",
  "properties": {
    "addr:full":"Galgenstraat 40 Amsterdam North Holland 1013 LT",
    "addr:housenumber":"40",
    "addr:postcode":"1013 lt",
    "addr:street":"Galgenstraat",
    "iso:country":"NL",
    "sg:address":"Galgenstraat 40",
    "sg:city":"Amsterdam",
    "sg:orig_category":"Geluidsopnamen",
    "sg:phone":"+31 20 620 0885",
    "sg:postcode":"1013 LT",
    "sg:province":"North Holland",
    "wof:name":"Greenfields Forever",
    "wof:placetype":"venue"
},
  "geometry": {"coordinates":[4.886893,52.385761],"type":"Point"}
}