{
  "type": "Feature",
  "properties": {
    "addr:full":"Asterlo 33 Rotterdam South Holland 3085 AD",
    "addr:housenumber":"33",
    "addr:postcode":"3085 ad",
    "addr:street":"Asterlo",
    "iso:country":"NL",
    "sg:address":"Asterlo 33",
    "sg:city":"Rotterdam",
    "sg:orig_category":"Kappers",
    "sg:phone":"+31 10 480 8802",
    "sg:postcode":"3085 AD",
    "sg:province":"South Holland",
    "wof:name":"Mondaine Haarmode",
    "wof:placetype":"venue"
},
  "geometry": {"coordinates":[4.482726,51.87389],"type":"Point"}
}