{
  "type": "Feature",
  "properties": {
    "iso:country":"NL",
    "sg:address":"Langenhorst 247",
    "sg:city":"Rotterdam",
    "sg:classifiers":[
        {
            "category":"Food & Beverages",
            "subcategory":"Fruits & Vegetables",
            "type":"Retail Goods"
        }
    ],
    "sg:phone":"+31 10 481 6135",
    "sg:postcode":"3085 HE",
    "sg:province":"South Holland",
    "sg:tags":[
        "groenten"
    ],
    "wof:name":"Theo Heezen",
    "wof:placetype":"venue"
},
  "geometry": {"coordinates":[4.494212,51.874195],"type":"Point"}
}