{
  "type": "Feature",
  "properties": {
    "addr:full":"Oosteinderweg 273A Aalsmeer Noord-Holland 1432 AV",
    "addr:housenumber":"273a",
    "addr:postcode":"1432 av",
    "addr:street":"Oosteinderweg",
    "iso:country":"NL",
    "sg:address":"Oosteinderweg 273A",
    "sg:city":"Aalsmeer",
    "sg:orig_category":"Overheidsdiensten",
    "sg:phone":"+31 297 326 529",
    "sg:postcode":"1432 AV",
    "sg:province":"Noord-Holland",
    "wof:name":"T Anker",
    "wof:placetype":"venue"
},
  "geometry": {"coordinates":[4.7895350456,52.2815208435],"type":"Point"}
}