{
  "type": "Feature",
  "properties": {
    "addr:full":"Aquamarynstr 24 Hengelo Ov Overijssel 7554 NS",
    "addr:housenumber":"24",
    "addr:postcode":"7554 ns",
    "addr:street":"Aquamarynstr;Ov",
    "iso:country":"NL",
    "sg:address":"Aquamarynstr 24",
    "sg:city":"Hengelo Ov",
    "sg:orig_category":"Verzekeringen - Verzekeringskantoren",
    "sg:phone":"+31 74 377 7002",
    "sg:postcode":"7554 NS",
    "sg:province":"Overijssel",
    "wof:name":"Rifra",
    "wof:placetype":"venue"
},
  "geometry": {"coordinates":[6.76553,52.238659],"type":"Point"}
}