{
  "type": "Feature",
  "properties": {
    "addr:full":"Oosterstr 6 Nykerk Gld Gelderland 3861 BJ",
    "addr:housenumber":"6",
    "addr:postcode":"3861 bj",
    "addr:street":"Oosterstr;Gld Gelderland",
    "iso:country":"NL",
    "sg:address":"Oosterstr 6",
    "sg:city":"Nykerk Gld",
    "sg:orig_category":"Kantoorinstallaties",
    "sg:phone":"+31 33 245 4722",
    "sg:postcode":"3861 BJ",
    "sg:province":"Gelderland",
    "sg:website":"http://www.vdbunt.com",
    "wof:name":"Bunt, Van De",
    "wof:placetype":"venue"
},
  "geometry": {"coordinates":[5.4830999374,52.2215690613],"type":"Point"}
}