{
  "type": "Feature",
  "properties": {
    "iso:country":"NL",
    "sg:address":"Houtstr 65",
    "sg:city":"Bergambacht",
    "sg:orig_category":"Adviesbureaus Bedrijfsorganisatie",
    "sg:phone":"+31 182 351 224",
    "sg:postcode":"2861 TT",
    "sg:province":"Zuid-Holland",
    "wof:name":"Boon",
    "wof:placetype":"venue"
},
  "geometry": {"coordinates":[4.789895,51.936867],"type":"Point"}
}