{
  "type": "Feature",
  "properties": {
    "iso:country":"NL",
    "sg:address":"Egmondstr 15",
    "sg:city":"Weert",
    "sg:orig_category":"Verbouwingen",
    "sg:phone":"+31 495 524 577",
    "sg:postcode":"6001 XH",
    "sg:province":"Limburg",
    "wof:name":"Multi-Service",
    "wof:placetype":"venue"
},
  "geometry": {"coordinates":[5.712212,51.256306],"type":"Point"}
}