{
  "type": "Feature",
  "properties": {
    "addr:full":"Spaarndamsewg 120V Haarlem North Holland 2021 KA",
    "addr:housenumber":"120v",
    "addr:postcode":"2021 ka",
    "addr:street":"Spaarndamsewg",
    "iso:country":"NL",
    "sg:address":"Spaarndamsewg 120V",
    "sg:city":"Haarlem",
    "sg:orig_category":"Ingenieursbureaus",
    "sg:phone":"+31 23 527 8393",
    "sg:postcode":"2021 KA",
    "sg:province":"North Holland",
    "wof:name":"Geoconsult Bv",
    "wof:placetype":"venue"
},
  "geometry": {"coordinates":[4.649291,52.390614],"type":"Point"}
}