{
  "type": "Feature",
  "properties": {
    "addr:full":"Pr Hendrikln 21 Sassenheim Zuid-Holland 2171 CL",
    "addr:housenumber":"21",
    "addr:postcode":"2171",
    "iso:country":"NL",
    "sg:address":"Pr Hendrikln 21",
    "sg:city":"Sassenheim",
    "sg:orig_category":"Adviesbureaus Bedrijfsorganisatie",
    "sg:phone":"+31 252 223 340",
    "sg:postcode":"2171 CL",
    "sg:province":"Zuid-Holland",
    "wof:name":"Lommerse",
    "wof:placetype":"venue"
},
  "geometry": {"coordinates":[4.516621,52.225746],"type":"Point"}
}