{
  "type": "Feature",
  "properties": {
    "iso:country":"NL",
    "sg:address":"Kalkvliet 9",
    "sg:city":"Terheyden",
    "sg:orig_category":"Psychotherapeuten",
    "sg:phone":"+31 76 593 2257",
    "sg:postcode":"4844 VK",
    "sg:province":"Noord-Brabant",
    "wof:name":"Blom-Mentink, Drs M E",
    "wof:placetype":"venue"
},
  "geometry": {"coordinates":[4.758841,51.639931],"type":"Point"}
}