{
  "type": "Feature",
  "properties": {
    "iso:country":"NL",
    "sg:address":"Gildepln 82",
    "sg:city":"Purmerend",
    "sg:orig_category":"Opticiens",
    "sg:phone":"+31 299 666 063",
    "sg:postcode":"1445 BM",
    "sg:province":"Noord-Holland",
    "wof:name":"Gilde, De",
    "wof:placetype":"venue"
},
  "geometry": {"coordinates":[4.985514164,52.5058822632],"type":"Point"}
}