{
  "type": "Feature",
  "properties": {
    "addr:full":"Keizersgr 824 Amsterdam Noord-Holland 1017 EE",
    "addr:housenumber":"824",
    "addr:postcode":"1017 ee",
    "iso:country":"NL",
    "sg:address":"Keizersgr 824",
    "sg:city":"Amsterdam",
    "sg:orig_category":"Psychotherapeuten",
    "sg:phone":"+31 20 422 0417",
    "sg:postcode":"1017 EE",
    "sg:province":"Noord-Holland",
    "wof:name":"Wijsbek, R W J G",
    "wof:placetype":"venue"
},
  "geometry": {"coordinates":[4.90094,52.363964],"type":"Point"}
}