{
  "type": "Feature",
  "properties": {
    "iso:country":"NL",
    "sg:address":"De Rijklaan 1",
    "sg:city":"Hilversum",
    "sg:orig_category":"Film-, Tv- And Videoproductie",
    "sg:phone":"+31 35 623 1508",
    "sg:postcode":"1217 RD",
    "sg:province":"North Holland",
    "wof:name":"European Media Support Bv",
    "wof:placetype":"venue"
},
  "geometry": {"coordinates":[5.158492,52.22393],"type":"Point"}
}