{
  "type": "Feature",
  "properties": {
    "addr:full":"De Rijklaan 1 Hilversum North Holland 1217 RD",
    "addr:housenumber":"1",
    "addr:postcode":"1217 rd",
    "addr:street":"De Rijklaan",
    "iso:country":"NL",
    "sg:address":"De Rijklaan 1",
    "sg:city":"Hilversum",
    "sg:orig_category":"Film-, Tv- And Videoproductie",
    "sg:phone":"+31 35 623 1508",
    "sg:postcode":"1217 RD",
    "sg:province":"North Holland",
    "wof:name":"European Media Support Bv",
    "wof:placetype":"venue"
},
  "geometry": {"coordinates":[5.158492,52.22393],"type":"Point"}
}