{
  "type": "Feature",
  "properties": {
    "addr:full":"Bosrand 19 Dwingeloo Provincie Drenthe 7991 PA",
    "addr:housenumber":"19",
    "addr:postcode":"7991",
    "addr:street":"Bosrand;Provincie Drenthe",
    "iso:country":"NL",
    "sg:address":"Bosrand 19",
    "sg:city":"Dwingeloo",
    "sg:classifiers":[
        {
            "category":"Personal",
            "subcategory":"Nail Salon",
            "type":"Services"
        }
    ],
    "sg:phone":"+31 521 597 335",
    "sg:postcode":"7991 PA",
    "sg:province":"Provincie Drenthe",
    "sg:tags":[
        "pedicure"
    ],
    "wof:name":"Wobben, T",
    "wof:placetype":"venue"
},
  "geometry": {"coordinates":[6.385425,52.820862],"type":"Point"}
}