{
  "type": "Feature",
  "properties": {
    "addr:full":"Gabriel Metsustraat 2 Amsterdam Noord-Holland 1071 EA",
    "addr:housenumber":"2",
    "addr:postcode":"1071 ea",
    "addr:street":"Gabriel Metsustraat",
    "iso:country":"NL",
    "sg:address":"Gabriel Metsustraat 2",
    "sg:city":"Amsterdam",
    "sg:orig_category":"Werving And Selectie Van Tijdelijk Personeel And Uitzendkantoren",
    "sg:phone":"+31 20 305 5655",
    "sg:postcode":"1071 EA",
    "sg:province":"Noord-Holland",
    "wof:name":"Manpower Uitzendorganisatie Bv",
    "wof:placetype":"venue"
},
  "geometry": {"coordinates":[4.8803429604,52.3560333252],"type":"Point"}
}