{
  "type": "Feature",
  "properties": {
    "addr:full":"Kerkstraat 72 Oisterwijk Noord-Brabant 5061 EK",
    "addr:housenumber":"72",
    "addr:postcode":"5061 ek",
    "addr:street":"Kerkstraat",
    "iso:country":"NL",
    "sg:address":"Kerkstraat 72",
    "sg:city":"Oisterwijk",
    "sg:orig_category":"Kappers",
    "sg:phone":"+31 13 521 6632",
    "sg:postcode":"5061 EK",
    "sg:province":"Noord-Brabant",
    "wof:name":"Garbo Haarstudio",
    "wof:placetype":"venue"
},
  "geometry": {"coordinates":[5.1871528625,51.5793991089],"type":"Point"}
}