{
  "type": "Feature",
  "properties": {
    "addr:full":"Radonstr 2 Zoetermeer Zuid-Holland 2718 TA",
    "addr:housenumber":"2",
    "addr:postcode":"2718 ta",
    "addr:street":"Radonstr",
    "iso:country":"NL",
    "sg:address":"Radonstr 2",
    "sg:city":"Zoetermeer",
    "sg:orig_category":"Machinefabrieken",
    "sg:phone":"+31 79 361 1255",
    "sg:postcode":"2718 TA",
    "sg:province":"Zuid-Holland",
    "sg:website":"http://www.redpoint.nl",
    "wof:name":"Red Point",
    "wof:placetype":"venue"
},
  "geometry": {"coordinates":[4.500936,52.035099],"type":"Point"}
}