{
  "type": "Feature",
  "properties": {
    "iso:country":"NL",
    "sg:address":"Javastraat 11",
    "sg:city":"Amsterdam",
    "sg:orig_category":"Damesmodezaken",
    "sg:phone":"+31 20 665 7810",
    "sg:postcode":"1094 GX",
    "sg:province":"Noord-Holland",
    "wof:name":"Modehuis Eleonoor",
    "wof:placetype":"venue"
},
  "geometry": {"coordinates":[4.932215,52.36364],"type":"Point"}
}