{
  "type": "Feature",
  "properties": {
    "addr:full":"V Konynenburgwg 141 Bergen Op Zoom Noord-Brabant 4612 PL",
    "addr:housenumber":"141",
    "addr:postcode":"4612 pl",
    "iso:country":"NL",
    "sg:address":"V Konynenburgwg 141",
    "sg:city":"Bergen Op Zoom",
    "sg:orig_category":"Waterbehandeling En Waterzuiverings- Systemen",
    "sg:phone":"+31 164 214 141",
    "sg:postcode":"4612 PL",
    "sg:province":"Noord-Brabant",
    "wof:name":"Houseman Bv",
    "wof:placetype":"venue"
},
  "geometry": {"coordinates":[4.262160778,51.5023117065],"type":"Point"}
}