{
  "type": "Feature",
  "properties": {
    "addr:full":"De Polle 8 Blauwhuis Friesland 8615 LT",
    "addr:housenumber":"8",
    "addr:postcode":"8615 lt",
    "addr:street":"De Polle",
    "iso:country":"NL",
    "sg:address":"De Polle 8",
    "sg:city":"Blauwhuis",
    "sg:orig_category":"Overheidsdiensten",
    "sg:phone":"+31 515 579 456",
    "sg:postcode":"8615 LT",
    "sg:province":"Friesland",
    "wof:name":"Sie-Sa",
    "wof:placetype":"venue"
},
  "geometry": {"coordinates":[5.5318799019,53.0222091675],"type":"Point"}
}