{
  "type": "Feature",
  "properties": {
    "iso:country":"NL",
    "sg:address":"Zuidwal 62",
    "sg:city":"'S Gravenhage",
    "sg:orig_category":"Kappers",
    "sg:phone":"+31 70 360 3069",
    "sg:postcode":"2512 ZK",
    "sg:province":"South Holland",
    "wof:name":"Kappersbedrijf Gaida",
    "wof:placetype":"venue"
},
  "geometry": {"coordinates":[4.3087611198,52.0712738037],"type":"Point"}
}