{
  "type": "Feature",
  "properties": {
    "addr:full":"Kikkertstraat 14 De Cocksdorp Noord-Holland 1795 AD",
    "addr:housenumber":"14",
    "addr:postcode":"1795 ad",
    "addr:street":"Kikkertstraat",
    "iso:country":"NL",
    "sg:address":"Kikkertstraat 14",
    "sg:city":"De Cocksdorp",
    "sg:orig_category":"Drogisterijen",
    "sg:phone":"+31 222 316 388",
    "sg:postcode":"1795 AD",
    "sg:province":"Noord-Holland",
    "wof:name":"Kunstnijverheid Van 'T Noordende",
    "wof:placetype":"venue"
},
  "geometry": {"coordinates":[4.871575,53.156044],"type":"Point"}
}