{
  "type": "Feature",
  "properties": {
    "addr:full":"Walstraat 28 Huissen Gelderland 6851 AV",
    "addr:housenumber":"28",
    "addr:postcode":"6851 av",
    "addr:street":"Walstraat;Gelderland",
    "iso:country":"NL",
    "sg:address":"Walstraat 28",
    "sg:city":"Huissen",
    "sg:orig_category":"Loodgieterswerk, Verwarming And Sanitaire Installaties",
    "sg:phone":"+31 26 325 7185",
    "sg:postcode":"6851 AV",
    "sg:province":"Gelderland",
    "wof:name":"Jito Vof",
    "wof:placetype":"venue"
},
  "geometry": {"coordinates":[5.940478,51.938793],"type":"Point"}
}