{
  "type": "Feature",
  "properties": {
    "iso:country":"NL",
    "sg:address":"Wyk 3 98",
    "sg:city":"Urk",
    "sg:orig_category":"Mensendieck - Oefentherapeuten",
    "sg:phone":"+31 527 681 588",
    "sg:postcode":"8321 GB",
    "sg:province":"Flevoland",
    "wof:name":"Romkes, G",
    "wof:placetype":"venue"
},
  "geometry": {"coordinates":[5.603392,52.659443],"type":"Point"}
}