{
  "type": "Feature",
  "properties": {
    "addr:full":"Hoebertwg 4A America Limburg 5966 ND",
    "addr:housenumber":"4a",
    "addr:postcode":"5966 nd",
    "addr:street":"Hoebertwg",
    "iso:country":"NL",
    "sg:address":"Hoebertwg 4A",
    "sg:city":"America",
    "sg:orig_category":"Autoradio'S",
    "sg:phone":"+31 77 464 2070",
    "sg:postcode":"5966 ND",
    "sg:province":"Limburg",
    "sg:website":"http://www.jpelectronics.nl",
    "wof:name":"Jp Electronics",
    "wof:placetype":"venue"
},
  "geometry": {"coordinates":[-94.539925,33.812393],"type":"Point"}
}