{
  "type": "Feature",
  "properties": {
    "addr:full":"F Bilderbeekstr 37 Zwolle NL.08 8017 DS",
    "addr:housenumber":"37",
    "addr:postcode":"8017 ds",
    "iso:country":"NL",
    "sg:address":"F Bilderbeekstr 37",
    "sg:city":"Zwolle",
    "sg:orig_category":"Hulpverlening Sociaal",
    "sg:phone":"+31 38 460 8788",
    "sg:postcode":"8017 DS",
    "sg:province":"NL.08",
    "wof:name":"Klankbord, Coachingpraktijk",
    "wof:placetype":"venue"
},
  "geometry": {"coordinates":[6.088458,52.497353],"type":"Point"}
}