{
  "type": "Feature",
  "properties": {
    "addr:full":"Zeeburgerdk 117 Amsterdam Noord-Holland 1094 AD",
    "addr:housenumber":"117",
    "addr:postcode":"1094 ad",
    "iso:country":"NL",
    "sg:address":"Zeeburgerdk 117",
    "sg:city":"Amsterdam",
    "sg:orig_category":"Begrafenisverzorging",
    "sg:phone":"+31 20 668 2250",
    "sg:postcode":"1094 AD",
    "sg:province":"Noord-Holland",
    "wof:name":"Hilal, Stichting",
    "wof:placetype":"venue"
},
  "geometry": {"coordinates":[4.93795,52.3661],"type":"Point"}
}