{
  "type": "Feature",
  "properties": {
    "addr:full":"Molenwg 91 Harskamp Gelderland 6732 BJ",
    "addr:housenumber":"91",
    "addr:postcode":"6732 bj",
    "addr:street":"Molenwg;Gelderland",
    "iso:country":"NL",
    "sg:address":"Molenwg 91",
    "sg:city":"Harskamp",
    "sg:orig_category":"Matrijzen",
    "sg:phone":"+31 318 457 141",
    "sg:postcode":"6732 BJ",
    "sg:province":"Gelderland",
    "wof:name":"Brink Bv, Van Den",
    "wof:placetype":"venue"
},
  "geometry": {"coordinates":[5.752031,52.124405],"type":"Point"}
}