{
  "type": "Feature",
  "properties": {
    "addr:full":"Didamseweg 37 Beek Gem Bergh Gelderland 7037 DJ",
    "addr:housenumber":"37",
    "addr:postcode":"7037 dj",
    "addr:street":"Didamseweg",
    "iso:country":"NL",
    "sg:address":"Didamseweg 37",
    "sg:city":"Beek Gem Bergh",
    "sg:orig_category":"Schilderwerk",
    "sg:phone":"+31 316 532 350",
    "sg:postcode":"7037 DJ",
    "sg:province":"Gelderland",
    "wof:name":"Josef Rosendaal Schilderwerken Bv",
    "wof:placetype":"venue"
},
  "geometry": {"coordinates":[6.181273,51.926014],"type":"Point"}
}