{
  "type": "Feature",
  "properties": {
    "iso:country":"NL",
    "sg:address":"Touwslagersstraat 26",
    "sg:city":"Dordrecht",
    "sg:orig_category":"Autokeuringen",
    "sg:phone":"+31 78 631 5623",
    "sg:postcode":"3311 MJ",
    "sg:province":"Zuid-Holland",
    "wof:name":"Stichting Werkplaats Dordrecht",
    "wof:placetype":"venue"
},
  "geometry": {"coordinates":[4.680437,51.816448],"type":"Point"}
}