{
  "type": "Feature",
  "properties": {
    "iso:country":"NL",
    "sg:address":"Kerkln 86",
    "sg:city":"Ryswyk Zh",
    "sg:orig_category":"Goudsmeden En Zilversmeden",
    "sg:phone":"+31 70 319 2137",
    "sg:postcode":"2282 CM",
    "sg:province":"Zuid-Holland",
    "wof:name":"Kuil, Jannie",
    "wof:placetype":"venue"
},
  "geometry": {"coordinates":[4.33694,52.056503],"type":"Point"}
}