{
  "type": "Feature",
  "properties": {
    "addr:full":"Levendaal 177 Leiden Zuid-Holland 2311 JK",
    "addr:housenumber":"177",
    "addr:postcode":"2311 jk",
    "addr:street":"Levendaal",
    "iso:country":"NL",
    "sg:address":"Levendaal 177",
    "sg:city":"Leiden",
    "sg:classifiers":[
        {
            "category":"Retail",
            "subcategory":"Auto Repair",
            "type":"Services"
        }
    ],
    "sg:phone":"+31 71 512 8443",
    "sg:postcode":"2311 JK",
    "sg:province":"Zuid-Holland",
    "sg:tags":[
        "garage"
    ],
    "wof:name":"Centurij Janson Leiden Bv",
    "wof:placetype":"venue"
},
  "geometry": {"coordinates":[4.500467,52.154621],"type":"Point"}
}