{
  "type": "Feature",
  "properties": {
    "addr:full":"Denys Van Hullelaan 17 Haarlem Noord-Holland 2015 GM",
    "addr:housenumber":"17",
    "addr:postcode":"2015 gm",
    "addr:street":"Denys Van Hullelaan",
    "iso:country":"NL",
    "sg:address":"Denys Van Hullelaan 17",
    "sg:city":"Haarlem",
    "sg:orig_category":"Public Relationbureaus",
    "sg:phone":"+31 23 544 2751",
    "sg:postcode":"2015 GM",
    "sg:province":"Noord-Holland",
    "wof:name":"Synergos Communicatie",
    "wof:placetype":"venue"
},
  "geometry": {"coordinates":[4.605173,52.383701],"type":"Point"}
}