{
  "type": "Feature",
  "properties": {
    "iso:country":"NL",
    "sg:address":"Bothalaan 7",
    "sg:city":"Baarn",
    "sg:orig_category":"Bedrijfs- And Managementsconsultants",
    "sg:phone":"+31 35 541 8174",
    "sg:postcode":"3743 CS",
    "sg:province":"Utrecht",
    "wof:name":"A.F.Van Hall Consult Bv",
    "wof:placetype":"venue"
},
  "geometry": {"coordinates":[5.278576,52.212303],"type":"Point"}
}