{
  "type": "Feature",
  "properties": {
    "addr:full":"Ds M L Kingwg 205 Zaandam Noord-Holland 1504 DG",
    "addr:housenumber":"205",
    "addr:postcode":"1504 dg",
    "addr:street":"Ds M L Kingwg",
    "iso:country":"NL",
    "sg:address":"Ds M L Kingwg 205",
    "sg:city":"Zaandam",
    "sg:orig_category":"Postkantoren",
    "sg:phone":"+31 75 670 2981",
    "sg:postcode":"1504 DG",
    "sg:province":"Noord-Holland",
    "sg:website":"http://www.postkantoor.nl",
    "wof:name":"Postkantoor",
    "wof:placetype":"venue"
},
  "geometry": {"coordinates":[4.842393,52.437546],"type":"Point"}
}