{
  "type": "Feature",
  "properties": {
    "addr:full":"G Boelensstraat 4A Drachten Friesland 9203 RM",
    "addr:housenumber":"4a",
    "addr:postcode":"9203 rm",
    "addr:street":"Boelensstraat",
    "iso:country":"NL",
    "sg:address":"G Boelensstraat 4A",
    "sg:city":"Drachten",
    "sg:orig_category":"Juridische Dienstverlening",
    "sg:phone":"+31 512 519 959",
    "sg:postcode":"9203 RM",
    "sg:province":"Friesland",
    "wof:name":"Buro Voor Rechtshulp",
    "wof:placetype":"venue"
},
  "geometry": {"coordinates":[6.098565,53.102871],"type":"Point"}
}