{
  "type": "Feature",
  "properties": {
    "iso:country":"NL",
    "sg:address":"Chagallpassage 2",
    "sg:city":"Emmen",
    "sg:orig_category":"Juweliers",
    "sg:phone":"+31 591 649 717",
    "sg:postcode":"7811 DG",
    "sg:province":"Drenthe",
    "wof:name":"Twinkle",
    "wof:placetype":"venue"
},
  "geometry": {"coordinates":[6.893585,52.78447],"type":"Point"}
}