{
  "type": "Feature",
  "properties": {
    "addr:full":"Rozenkamp 39 Eibergen Gelderland 7151 VP",
    "addr:housenumber":"39",
    "addr:postcode":"7151 vp",
    "addr:street":"Rozenkamp;Gelderland",
    "iso:country":"NL",
    "sg:address":"Rozenkamp 39",
    "sg:city":"Eibergen",
    "sg:orig_category":"Boekhouders",
    "sg:phone":"+31 545 472 500",
    "sg:postcode":"7151 VP",
    "sg:province":"Gelderland",
    "wof:name":"Dimmendaal Administratiebureau",
    "wof:placetype":"venue"
},
  "geometry": {"coordinates":[6.641396,52.094105],"type":"Point"}
}