{
  "type": "Feature",
  "properties": {
    "addr:full":"Duikererf 1 Amersfoort Utrecht 3822 WN",
    "addr:housenumber":"1",
    "addr:postcode":"3822 wn",
    "addr:street":"Duikererf",
    "iso:country":"NL",
    "sg:address":"Duikererf 1",
    "sg:city":"Amersfoort",
    "sg:orig_category":"Webdesign Bureaus",
    "sg:phone":"+31 33 456 7951",
    "sg:postcode":"3822 WN",
    "sg:province":"Utrecht",
    "sg:website":"http://www.effitea.nl",
    "wof:name":"Effitea",
    "wof:placetype":"venue"
},
  "geometry": {"coordinates":[5.4030599594,52.1832733154],"type":"Point"}
}