{
  "type": "Feature",
  "properties": {
    "addr:full":"Ln V Meerdervoort 156A S Gravenhage South Holland 2517 BG",
    "addr:housenumber":"156a s",
    "addr:postcode":"2517",
    "addr:street":"Ln;Meerdervoort",
    "iso:country":"NL",
    "sg:address":"Ln V Meerdervoort 156A",
    "sg:city":"S Gravenhage",
    "sg:orig_category":"Open Haarden",
    "sg:phone":"+31 70 361 5999",
    "sg:postcode":"2517 BG",
    "sg:province":"South Holland",
    "sg:website":"http://www.diasschouwen.nl",
    "wof:name":"Dias Schouwen",
    "wof:placetype":"venue"
},
  "geometry": {"coordinates":[4.28708,52.08667],"type":"Point"}
}