{
  "type": "Feature",
  "properties": {
    "addr:full":"Lagedijkerweg 4 Schagen Noord-Holland 1742 NB",
    "addr:housenumber":"4",
    "addr:postcode":"1742 nb",
    "addr:street":"Lagedijkerweg",
    "iso:country":"NL",
    "sg:address":"Lagedijkerweg 4",
    "sg:city":"Schagen",
    "sg:orig_category":"Meubeltextiel Fab",
    "sg:phone":"+31 224 216 365",
    "sg:postcode":"1742 NB",
    "sg:province":"Noord-Holland",
    "wof:name":"Zeilmakerij De Twee Gesusters",
    "wof:placetype":"venue"
},
  "geometry": {"coordinates":[4.787657,52.790794],"type":"Point"}
}