{
  "type": "Feature",
  "properties": {
    "addr:full":"Middenwg 20 Groningen Groningen 9745 BN",
    "addr:housenumber":"20",
    "addr:postcode":"9745 bn",
    "addr:street":"Middenwg",
    "iso:country":"NL",
    "sg:address":"Middenwg 20",
    "sg:city":"Groningen",
    "sg:orig_category":"Beeldende Kunstenaars",
    "sg:phone":"+31 50 556 7970",
    "sg:postcode":"9745 BN",
    "sg:province":"Groningen",
    "wof:name":"Kracht, B",
    "wof:placetype":"venue"
},
  "geometry": {"coordinates":[6.503807,53.214867],"type":"Point"}
}