{
  "type": "Feature",
  "properties": {
    "addr:full":"Waterleliesngl 20 Helmond Noord-Brabant 5709 PD",
    "addr:housenumber":"20",
    "addr:postcode":"5709 pd",
    "addr:street":"Waterleliesngl",
    "iso:country":"NL",
    "sg:address":"Waterleliesngl 20",
    "sg:city":"Helmond",
    "sg:orig_category":"Artsen - Huisartsen",
    "sg:phone":"+31 492 514 121",
    "sg:postcode":"5709 PD",
    "sg:province":"Noord-Brabant",
    "wof:name":"Vijfeijken, F A T C Van",
    "wof:placetype":"venue"
},
  "geometry": {"coordinates":[5.658284,51.482239],"type":"Point"}
}