{
  "type": "Feature",
  "properties": {
    "addr:full":"De Kempkens 7 Veghel Noord-Brabant 5465 NB",
    "addr:housenumber":"7",
    "addr:postcode":"5465 nb",
    "addr:street":"De Kempkens",
    "iso:country":"NL",
    "sg:address":"De Kempkens 7",
    "sg:city":"Veghel",
    "sg:orig_category":"Lasbedrijven",
    "sg:phone":"+31 6 51211762",
    "sg:postcode":"5465 NB",
    "sg:province":"Noord-Brabant",
    "wof:name":"Zutphen, Van",
    "wof:placetype":"venue"
},
  "geometry": {"coordinates":[5.518681,51.593552],"type":"Point"}
}