{
  "type": "Feature",
  "properties": {
    "addr:full":"Leidsevaart 448 Haarlem Noord-Holland 2014 HP",
    "addr:housenumber":"448",
    "addr:postcode":"2014 hp",
    "addr:street":"Leidsevaart",
    "iso:country":"NL",
    "sg:address":"Leidsevaart 448",
    "sg:city":"Haarlem",
    "sg:orig_category":"Granen, Zaden And Diervoeders Gh",
    "sg:phone":"+31 23 524 0144",
    "sg:postcode":"2014 HP",
    "sg:province":"Noord-Holland",
    "wof:name":"Interpolm Grow Shop",
    "wof:placetype":"venue"
},
  "geometry": {"coordinates":[4.614863,52.36776],"type":"Point"}
}