{
  "type": "Feature",
  "properties": {
    "addr:full":"Vanghoutstr 3 Culemborg Gelderland 4105 HE",
    "addr:housenumber":"3",
    "addr:postcode":"4105 he",
    "addr:street":"Vanghoutstr;Gelderland",
    "iso:country":"NL",
    "sg:address":"Vanghoutstr 3",
    "sg:city":"Culemborg",
    "sg:orig_category":"Verzekeringen - Verzekeringskantoren",
    "sg:phone":"+31 345 514 088",
    "sg:postcode":"4105 HE",
    "sg:province":"Gelderland",
    "wof:name":"Kerkhof, M J",
    "wof:placetype":"venue"
},
  "geometry": {"coordinates":[5.213652,51.952732],"type":"Point"}
}