{
  "type": "Feature",
  "properties": {
    "addr:full":"Brouwersgr 278 Amsterdam Noord-Holland 1013 HG",
    "addr:housenumber":"278",
    "addr:postcode":"1013 hg",
    "iso:country":"NL",
    "sg:address":"Brouwersgr 278",
    "sg:city":"Amsterdam",
    "sg:orig_category":"Modellenbureaus En Modellen Freelance",
    "sg:phone":"+31 20 330 0966",
    "sg:postcode":"1013 HG",
    "sg:province":"Noord-Holland",
    "sg:website":"http://www.skinagency.com",
    "wof:name":"Skin Agency",
    "wof:placetype":"venue"
},
  "geometry": {"coordinates":[4.884466,52.383156],"type":"Point"}
}