{
  "type": "Feature",
  "properties": {
    "addr:full":"Abelenln 37 Amstelveen Noord-Holland 1185 RV",
    "addr:housenumber":"37",
    "addr:postcode":"1185 rv",
    "addr:street":"Abelenln",
    "iso:country":"NL",
    "sg:address":"Abelenln 37",
    "sg:city":"Amstelveen",
    "sg:orig_category":"Verzekeringen - Verzekeringskantoren",
    "sg:phone":"+31 20 441 0126",
    "sg:postcode":"1185 RV",
    "sg:province":"Noord-Holland",
    "wof:name":"Schnek, Robert",
    "wof:placetype":"venue"
},
  "geometry": {"coordinates":[4.847528,52.29319],"type":"Point"}
}