{
  "type": "Feature",
  "properties": {
    "addr:full":"Watermanstraat 43 Tilburg North Brabant 5015 TG",
    "addr:housenumber":"43",
    "addr:postcode":"5015 tg",
    "addr:street":"Watermanstraat",
    "iso:country":"NL",
    "sg:address":"Watermanstraat 43",
    "sg:city":"Tilburg",
    "sg:orig_category":"Goederenvervoer Over De Weg",
    "sg:phone":"+31 13 456 4727",
    "sg:postcode":"5015 TG",
    "sg:province":"North Brabant",
    "wof:name":"Varitrans Bv",
    "wof:placetype":"venue"
},
  "geometry": {"coordinates":[5.109695,51.579029],"type":"Point"}
}