{
  "type": "Feature",
  "properties": {
    "iso:country":"NL",
    "sg:address":"Kerkweg 199",
    "sg:city":"Lekkerkerk",
    "sg:orig_category":"Goederenvervoer Over De Weg",
    "sg:phone":"+31 180 662 144",
    "sg:postcode":"2941 BK",
    "sg:province":"Zuid-Holland",
    "wof:name":"Van Der Laan Transport Bv",
    "wof:placetype":"venue"
},
  "geometry": {"coordinates":[4.683997,51.905357],"type":"Point"}
}