{
  "type": "Feature",
  "properties": {
    "iso:country":"NL",
    "sg:address":"De Meeren 54",
    "sg:city":"Zevenbergen",
    "sg:orig_category":"Boekhouders",
    "sg:phone":"+31 168 326 183",
    "sg:postcode":"4761 SM",
    "sg:province":"Noord-Brabant",
    "wof:name":"Administratief Adviesburo E. Bens",
    "wof:placetype":"venue"
},
  "geometry": {"coordinates":[4.592185,51.645668],"type":"Point"}
}