{
  "type": "Feature",
  "properties": {
    "addr:full":"Ysvogel 57 Maarssen Utrecht 3602 XL",
    "addr:housenumber":"57",
    "addr:postcode":"3602 xl",
    "addr:street":"Ysvogel",
    "iso:country":"NL",
    "sg:address":"Ysvogel 57",
    "sg:city":"Maarssen",
    "sg:orig_category":"Bedrijfsopleidingen",
    "sg:phone":"+31 346 283 897",
    "sg:postcode":"3602 XL",
    "sg:province":"Utrecht",
    "sg:website":"http://www.bracketoutdoors.nl",
    "wof:name":"Bracket Outdoor Ivents",
    "wof:placetype":"venue"
},
  "geometry": {"coordinates":[5.040446,52.142956],"type":"Point"}
}