{
  "type": "Feature",
  "properties": {
    "addr:full":"Vondelln 41 Leiden Zuid-Holland 2332 AA",
    "addr:housenumber":"41",
    "addr:postcode":"2332 aa",
    "addr:street":"Vondelln",
    "iso:country":"NL",
    "sg:address":"Vondelln 41",
    "sg:city":"Leiden",
    "sg:classifiers":[
        {
            "category":"Arena",
            "subcategory":"Auto Racetrack",
            "type":"Entertainment"
        }
    ],
    "sg:phone":"+31 71 576 6820",
    "sg:postcode":"2332 AA",
    "sg:province":"Zuid-Holland",
    "sg:tags":[
        "en",
        "racebanen",
        "kart-"
    ],
    "wof:name":"Kaartbaan",
    "wof:placetype":"venue"
},
  "geometry": {"coordinates":[4.473218,52.161839],"type":"Point"}
}