{
  "type": "Feature",
  "properties": {
    "addr:full":"Symfonieln 12 Nieuwegein Utrecht 3438 EV",
    "addr:housenumber":"12",
    "addr:street":"Symfonieln",
    "iso:country":"NL",
    "sg:address":"Symfonieln 12",
    "sg:city":"Nieuwegein",
    "sg:orig_category":"Verzekeringen - Verzekeringskantoren",
    "sg:phone":"+31 30 605 3969",
    "sg:postcode":"3438 EV",
    "sg:province":"Utrecht",
    "wof:name":"Art Bv",
    "wof:placetype":"venue"
},
  "geometry": {"coordinates":[5.096002,52.042423],"type":"Point"}
}