{
  "type": "Feature",
  "properties": {
    "addr:full":"Roerdompstr 15 Badhoevedorp Noord-Holland 1171 HA",
    "addr:housenumber":"15",
    "addr:postcode":"1171 ha",
    "addr:street":"Roerdompstr",
    "iso:country":"NL",
    "sg:address":"Roerdompstr 15",
    "sg:city":"Badhoevedorp",
    "sg:orig_category":"Honden- En Kattentrimsalons",
    "sg:phone":"+31 20 659 6613",
    "sg:postcode":"1171 HA",
    "sg:province":"Noord-Holland",
    "wof:name":"Dogstyle",
    "wof:placetype":"venue"
},
  "geometry": {"coordinates":[4.785211,52.337387],"type":"Point"}
}