{
  "type": "Feature",
  "properties": {
    "addr:full":"Buurmalsenplein 14 Tilburg Noord-Brabant 5043 XL",
    "addr:housenumber":"14",
    "addr:postcode":"5043 xl",
    "addr:street":"Buurmalsenplein",
    "iso:country":"NL",
    "sg:address":"Buurmalsenplein 14",
    "sg:city":"Tilburg",
    "sg:orig_category":"Opticiens",
    "sg:phone":"+31 13 570 1050",
    "sg:postcode":"5043 XL",
    "sg:province":"Noord-Brabant",
    "wof:name":"Van Den Oord Optiek",
    "wof:placetype":"venue"
},
  "geometry": {"coordinates":[5.0167717934,51.5826568604],"type":"Point"}
}