{
  "type": "Feature",
  "properties": {
    "addr:full":"Kerkstr 63A Elshout North Brabant 5154 AN",
    "addr:housenumber":"63a",
    "addr:postcode":"5154 an",
    "addr:street":"Kerkstr",
    "iso:country":"NL",
    "sg:address":"Kerkstr 63A",
    "sg:city":"Elshout",
    "sg:orig_category":"Fietsen En Bromfietsen",
    "sg:phone":"+31 416 376 895",
    "sg:postcode":"5154 AN",
    "sg:province":"North Brabant",
    "wof:name":"Engelen, Van",
    "wof:placetype":"venue"
},
  "geometry": {"coordinates":[5.140257,51.701202],"type":"Point"}
}