{
  "type": "Feature",
  "properties": {
    "addr:full":"Sterrebos 62 Oss Noord-Brabant 5344 AR",
    "addr:housenumber":"62",
    "addr:postcode":"5344",
    "addr:street":"Sterrebos",
    "iso:country":"NL",
    "sg:address":"Sterrebos 62",
    "sg:city":"Oss",
    "sg:orig_category":"Verenigingen En Stichtingen",
    "sg:phone":"+31 412 668 000",
    "sg:postcode":"5344 AR",
    "sg:province":"Noord-Brabant",
    "wof:name":"Wonen Voor Ouderen Maasland, Sticht",
    "wof:placetype":"venue"
},
  "geometry": {"coordinates":[-77.235214,38.312599],"type":"Point"}
}