{
  "type": "Feature",
  "properties": {
    "addr:full":"Clarenburg 13 Utrecht Utrecht 3511 CX",
    "addr:housenumber":"13",
    "addr:postcode":"3511 cx",
    "addr:street":"Clarenburg",
    "iso:country":"NL",
    "sg:address":"Clarenburg 13",
    "sg:city":"Utrecht",
    "sg:orig_category":"Babyartikelen",
    "sg:phone":"+31 30 231 1720",
    "sg:postcode":"3511 CX",
    "sg:province":"Utrecht",
    "wof:name":"Pr?natal",
    "wof:placetype":"venue"
},
  "geometry": {"coordinates":[5.115413,52.090435],"type":"Point"}
}