{
  "type": "Feature",
  "properties": {
    "addr:full":"Wilhelminastr 16 Velp Gld Gelderland 6881 LJ",
    "addr:housenumber":"16;lj",
    "addr:postcode":"6881",
    "addr:street":"Wilhelminastr;Gld Gelderland",
    "iso:country":"NL",
    "sg:address":"Wilhelminastr 16",
    "sg:city":"Velp Gld",
    "sg:orig_category":"Handwerkartikelen",
    "sg:phone":"+31 26 363 8549",
    "sg:postcode":"6881 LJ",
    "sg:province":"Gelderland",
    "sg:website":"http://www.inx-tenzo.nl",
    "wof:name":"In X-Tenzo Borduurspeciaalzaak",
    "wof:placetype":"venue"
},
  "geometry": {"coordinates":[5.97029,51.997189],"type":"Point"}
}