{
  "type": "Feature",
  "properties": {
    "addr:full":"Giekerkstr 110 Tilburg Noord-Brabant 5043 MK",
    "addr:housenumber":"110",
    "addr:postcode":"5043",
    "addr:street":"Tilburg",
    "iso:country":"NL",
    "sg:address":"Giekerkstr 110",
    "sg:city":"Tilburg",
    "sg:orig_category":"Administratie- En Boekhoudkantoren",
    "sg:phone":"+31 13 570 4921",
    "sg:postcode":"5043 MK",
    "sg:province":"Noord-Brabant",
    "wof:name":"Broers",
    "wof:placetype":"venue"
},
  "geometry": {"coordinates":[5.007691,51.57832],"type":"Point"}
}