{
  "type": "Feature",
  "properties": {
    "iso:country":"NL",
    "sg:address":"Rembrandtsngl 5",
    "sg:city":"Capelle Ad Yssel",
    "sg:orig_category":"Acupunctuur",
    "sg:phone":"+31 10 450 5217",
    "sg:postcode":"2902 GR",
    "sg:province":"South Holland",
    "wof:name":"Verbree, B C J",
    "wof:placetype":"venue"
},
  "geometry": {"coordinates":[4.57697,51.926311],"type":"Point"}
}