{
  "type": "Feature",
  "properties": {
    "addr:full":"Grundel 39 Broek Op Langedijk Noord-Holland 1721 GC",
    "addr:housenumber":"39",
    "addr:postcode":"1721 gc",
    "addr:street":"Grundel",
    "iso:country":"NL",
    "sg:address":"Grundel 39",
    "sg:city":"Broek Op Langedijk",
    "sg:orig_category":"Fruit And Groenten Gh",
    "sg:phone":"+31 226 313 938",
    "sg:postcode":"1721 GC",
    "sg:province":"Noord-Holland",
    "wof:name":"Handelsonderneming A.J.P. Leegwater",
    "wof:placetype":"venue"
},
  "geometry": {"coordinates":[4.805997,52.682491],"type":"Point"}
}