{
  "type": "Feature",
  "properties": {
    "addr:full":"Vrinssenstr 49 Stramproy BE.05 6039 GW",
    "addr:housenumber":"49;be.05",
    "addr:postcode":"6039 gw",
    "addr:street":"Vrinssenstr",
    "iso:country":"NL",
    "sg:address":"Vrinssenstr 49",
    "sg:city":"Stramproy",
    "sg:orig_category":"Meubelmakerijen",
    "sg:phone":"+31 495 561 775",
    "sg:postcode":"6039 GW",
    "sg:province":"BE.05",
    "wof:name":"Habel",
    "wof:placetype":"venue"
},
  "geometry": {"coordinates":[5.709189,51.193447],"type":"Point"}
}