{
  "type": "Feature",
  "properties": {
    "addr:full":"De Del 11 Amerongen Utrecht 3958 EH",
    "addr:housenumber":"11",
    "addr:postcode":"3958 eh",
    "addr:street":"De Del",
    "iso:country":"NL",
    "sg:address":"De Del 11",
    "sg:city":"Amerongen",
    "sg:orig_category":"Grondwerken",
    "sg:phone":"+31 343 456 370",
    "sg:postcode":"3958 EH",
    "sg:province":"Utrecht",
    "wof:name":"Garderen Vof, F Van",
    "wof:placetype":"venue"
},
  "geometry": {"coordinates":[5.467226,52.001652],"type":"Point"}
}