{
  "type": "Feature",
  "properties": {
    "addr:full":"Keiweg 153 Oosterhout Nb Noord-Brabant 4902 PD",
    "addr:housenumber":"153",
    "addr:postcode":"4902 pd",
    "addr:street":"Keiweg",
    "iso:country":"NL",
    "sg:address":"Keiweg 153",
    "sg:city":"Oosterhout Nb",
    "sg:orig_category":"Huishoudapparatuur, Televisies And Radio'S",
    "sg:phone":"+31 162 422 486",
    "sg:postcode":"4902 PD",
    "sg:province":"Noord-Brabant",
    "wof:name":"V.D.S. Van Dijk Soundsystems",
    "wof:placetype":"venue"
},
  "geometry": {"coordinates":[4.8663,51.638657],"type":"Point"}
}