{
  "type": "Feature",
  "properties": {
    "addr:full":"Diepenbrocklaan 5 Rotterdam Zuid-Holland 3055 WB",
    "addr:housenumber":"5",
    "addr:postcode":"3055 wb",
    "addr:street":"Diepenbrocklaan",
    "iso:country":"NL",
    "sg:address":"Diepenbrocklaan 5",
    "sg:city":"Rotterdam",
    "sg:orig_category":"Verzekeringen",
    "sg:phone":"+31 10 461 3506",
    "sg:postcode":"3055 WB",
    "sg:province":"Zuid-Holland",
    "wof:name":"J. De Jong Assurantie Adviesburo",
    "wof:placetype":"venue"
},
  "geometry": {"coordinates":[4.50507,51.96468],"type":"Point"}
}