{
  "type": "Feature",
  "properties": {
    "addr:full":"Paduawg 9G Den Dolder Utrecht 3734 GG",
    "addr:housenumber":"9g",
    "addr:postcode":"3734 gg",
    "addr:street":"Paduawg",
    "iso:country":"NL",
    "sg:address":"Paduawg 9G",
    "sg:city":"Den Dolder",
    "sg:orig_category":"Scheepvaartservice- Bureaus",
    "sg:phone":"+31 30 229 4190",
    "sg:postcode":"3734 GG",
    "sg:province":"Utrecht",
    "wof:name":"Scheepslijn, De",
    "wof:placetype":"venue"
},
  "geometry": {"coordinates":[5.238341,52.138748],"type":"Point"}
}