{
  "type": "Feature",
  "properties": {
    "iso:country":"NL",
    "sg:address":"Bontebrug 2",
    "sg:city":"Silvolde",
    "sg:orig_category":"Geluidsinstallaties",
    "sg:phone":"+31 315 631 521",
    "sg:postcode":"7064 LK",
    "sg:province":"Gelderland",
    "wof:name":"Aptronics Service Centrum",
    "wof:placetype":"venue"
},
  "geometry": {"coordinates":[6.398274,51.892788],"type":"Point"}
}