{
  "type": "Feature",
  "properties": {
    "addr:full":"Voorstraat 22 Colijnsplaat Zeeland 4486 AK",
    "addr:housenumber":"22",
    "addr:postcode":"4486 ak",
    "addr:street":"Voorstraat",
    "iso:country":"NL",
    "sg:address":"Voorstraat 22",
    "sg:city":"Colijnsplaat",
    "sg:orig_category":"Diverse Bedrijfsinstallaties Gh",
    "sg:phone":"+31 113 695 881",
    "sg:postcode":"4486 AK",
    "sg:province":"Zeeland",
    "wof:name":"Wisse Kramer Projecten Bv",
    "wof:placetype":"venue"
},
  "geometry": {"coordinates":[3.848045,51.599968],"type":"Point"}
}