{
  "type": "Feature",
  "properties": {
    "iso:country":"NL",
    "sg:address":"Ganzenroer 1",
    "sg:city":"Nieuw Amsterdam",
    "sg:orig_category":"Verzekeringen - Verzekeringskantoren",
    "sg:phone":"+31 591 551 205",
    "sg:postcode":"7833 GH",
    "sg:province":"Drenthe",
    "wof:name":"Veen, Van Der",
    "wof:placetype":"venue"
},
  "geometry": {"coordinates":[6.854184,52.713882],"type":"Point"}
}