{
  "type": "Feature",
  "properties": {
    "addr:full":"Koninginneln 35 Apeldoorn Gelderland 7315 BK",
    "addr:housenumber":"35",
    "addr:postcode":"7315 bk",
    "addr:street":"Koninginneln;Gelderland",
    "iso:country":"NL",
    "sg:address":"Koninginneln 35",
    "sg:city":"Apeldoorn",
    "sg:orig_category":"Bloemen En Planten",
    "sg:phone":"+31 55 522 5051",
    "sg:postcode":"7315 BK",
    "sg:province":"Gelderland",
    "wof:name":"Munster Bloemsierkunst, Wim V",
    "wof:placetype":"venue"
},
  "geometry": {"coordinates":[5.956347,52.222286],"type":"Point"}
}