{
  "type": "Feature",
  "properties": {
    "addr:full":"Lekboulevard 10 Nieuwegein Utrecht 3434 GL",
    "addr:housenumber":"10",
    "addr:postcode":"3434 gl",
    "addr:street":"Lekboulevard",
    "iso:country":"NL",
    "sg:address":"Lekboulevard 10",
    "sg:city":"Nieuwegein",
    "sg:orig_category":"Bejaardeninstellingen And Serviceflats",
    "sg:phone":"+31 30 606 2020",
    "sg:postcode":"3434 GL",
    "sg:province":"Utrecht",
    "wof:name":"Verzorgingshuis Vreeswijk",
    "wof:placetype":"venue"
},
  "geometry": {"coordinates":[5.087011,52.003681],"type":"Point"}
}