{
  "type": "Feature",
  "properties": {
    "addr:full":"Niasstr 212 Amsterdam North Holland 1095 TT",
    "addr:housenumber":"212",
    "addr:postcode":"1095 tt",
    "iso:country":"NL",
    "sg:address":"Niasstr 212",
    "sg:city":"Amsterdam",
    "sg:orig_category":"Webdesign Bureaus",
    "sg:phone":"+31 20 777 1694",
    "sg:postcode":"1095 TT",
    "sg:province":"North Holland",
    "sg:website":"http://www.schoot.com",
    "wof:name":"Schoot",
    "wof:placetype":"venue"
},
  "geometry": {"coordinates":[4.9428620338,52.3650970459],"type":"Point"}
}