{
  "type": "Feature",
  "properties": {
    "addr:full":"Kennemerpark 1 Alkmaar North Holland 1811 DD",
    "addr:housenumber":"1",
    "addr:postcode":"1811 dd",
    "addr:street":"Kennemerpark",
    "iso:country":"NL",
    "sg:address":"Kennemerpark 1",
    "sg:city":"Alkmaar",
    "sg:orig_category":"Gespecialiseerde Bouw",
    "sg:phone":"+31 72 511 5878",
    "sg:postcode":"1811 DD",
    "sg:province":"North Holland",
    "wof:name":"Constructie- En Installatie- Bedrijf Hein Jong",
    "wof:placetype":"venue"
},
  "geometry": {"coordinates":[4.747032,52.628101],"type":"Point"}
}