{
  "type": "Feature",
  "properties": {
    "iso:country":"NL",
    "sg:address":"Wielewaallaan 9",
    "sg:city":"Hurwenen",
    "sg:orig_category":"Goederenvervoer Over De Weg",
    "sg:phone":"+31 418 662 894",
    "sg:postcode":"5327 AN",
    "sg:province":"Gelderland",
    "wof:name":"Geurts Internationaal Transport",
    "wof:placetype":"venue"
},
  "geometry": {"coordinates":[5.315508,51.809227],"type":"Point"}
}