{
  "type": "Feature",
  "properties": {
    "addr:full":"Haarlemmerstraat 196 Leiden South Holland 2312 GH",
    "addr:housenumber":"196",
    "addr:postcode":"2312 gh",
    "addr:street":"Haarlemmerstraat",
    "iso:country":"NL",
    "sg:address":"Haarlemmerstraat 196",
    "sg:city":"Leiden",
    "sg:classifiers":[
        {
            "category":"Retail",
            "subcategory":"Photofinishing",
            "type":"Services"
        }
    ],
    "sg:phone":"+31 71 512 7560",
    "sg:postcode":"2312 GH",
    "sg:province":"South Holland",
    "sg:tags":[
        "foto",
        "film"
    ],
    "wof:name":"Speet Electronics",
    "wof:placetype":"venue"
},
  "geometry": {"coordinates":[4.495068,52.160572],"type":"Point"}
}