{
  "type": "Feature",
  "properties": {
    "addr:full":"Thorbeckelaan 18 Reeuwijk Zuid-Holland 2811 CD",
    "addr:housenumber":"18",
    "addr:postcode":"2811 cd",
    "addr:street":"Thorbeckelaan",
    "iso:country":"NL",
    "sg:address":"Thorbeckelaan 18",
    "sg:city":"Reeuwijk",
    "sg:orig_category":"Bedrijfs- And Managementsconsultants",
    "sg:phone":"+31 182 393 730",
    "sg:postcode":"2811 CD",
    "sg:province":"Zuid-Holland",
    "wof:name":"Steenwijk Management Consultancy Bv",
    "wof:placetype":"venue"
},
  "geometry": {"coordinates":[4.723447,52.044189],"type":"Point"}
}