{
  "type": "Feature",
  "properties": {
    "iso:country":"NL",
    "sg:address":"Waterlinie 10",
    "sg:city":"Huissen",
    "sg:orig_category":"Publiciteitsbureaus",
    "sg:phone":"+31 26 325 2797",
    "sg:postcode":"6852 CT",
    "sg:province":"Gelderland",
    "wof:name":"Trendpers",
    "wof:placetype":"venue"
},
  "geometry": {"coordinates":[5.930462,51.944496],"type":"Point"}
}