{
  "type": "Feature",
  "properties": {
    "addr:full":"Koestr 17 Hellendoorn Overijssel 7447 CE",
    "addr:housenumber":"17",
    "addr:postcode":"7447 ce",
    "addr:street":"Koestr",
    "iso:country":"NL",
    "sg:address":"Koestr 17",
    "sg:city":"Hellendoorn",
    "sg:orig_category":"Homeopathie",
    "sg:phone":"+31 548 657 151",
    "sg:postcode":"7447 CE",
    "sg:province":"Overijssel",
    "wof:name":"Klassieke Homeopathie, Praktijk V",
    "wof:placetype":"venue"
},
  "geometry": {"coordinates":[6.447976,52.390255],"type":"Point"}
}