{
  "type": "Feature",
  "properties": {
    "addr:full":"Heerewg 5 Terschelling Midld Friesland 8891 HS",
    "addr:housenumber":"5",
    "addr:postcode":"8891 hs",
    "addr:street":"Heerewg",
    "iso:country":"NL",
    "sg:address":"Heerewg 5",
    "sg:city":"Terschelling Midld",
    "sg:orig_category":"Discotheken",
    "sg:phone":"+31 562 448 850",
    "sg:postcode":"8891 HS",
    "sg:province":"Friesland",
    "wof:name":"Actania",
    "wof:placetype":"venue"
},
  "geometry": {"coordinates":[5.284489,53.385895],"type":"Point"}
}