{
  "type": "Feature",
  "properties": {
    "addr:full":"Rozenstr 17 Andelst Gelderland 6673 AG",
    "addr:housenumber":"17",
    "addr:postcode":"6673",
    "addr:street":"Rozenstr;Gelderland",
    "iso:country":"NL",
    "sg:address":"Rozenstr 17",
    "sg:city":"Andelst",
    "sg:orig_category":"Bloemen En Planten - Groothandel",
    "sg:phone":"+31 488 451 526",
    "sg:postcode":"6673 AG",
    "sg:province":"Gelderland",
    "wof:name":"Roelofs Tijssen Vof",
    "wof:placetype":"venue"
},
  "geometry": {"coordinates":[5.727288,51.903301],"type":"Point"}
}