{
  "type": "Feature",
  "properties": {
    "addr:full":"Pittsburghstr 31-37 Rotterdam Zuid-Holland 3047 BL",
    "addr:housenumber":"31-37",
    "addr:postcode":"rotterdam;3047 bl",
    "iso:country":"NL",
    "sg:address":"Pittsburghstr 31-37",
    "sg:city":"Rotterdam",
    "sg:orig_category":"Boekhandels",
    "sg:phone":"+31 10 214 3898",
    "sg:postcode":"3047 BL",
    "sg:province":"Zuid-Holland",
    "wof:name":"Xuezi Bv",
    "wof:placetype":"venue"
},
  "geometry": {"coordinates":[4.408876,51.941288],"type":"Point"}
}