{
  "type": "Feature",
  "properties": {
    "addr:full":"Bosscheweg 79 Berkel-Enschot North Brabant 5056 KB",
    "addr:housenumber":"79",
    "addr:postcode":"5056 kb",
    "addr:street":"Bosscheweg",
    "iso:country":"NL",
    "sg:address":"Bosscheweg 79",
    "sg:city":"Berkel-Enschot",
    "sg:orig_category":"Goederenvervoer Over De Weg",
    "sg:phone":"+31 13 533 1318",
    "sg:postcode":"5056 KB",
    "sg:province":"North Brabant",
    "wof:name":"Gebr. A. En H. Dekkers Bv",
    "wof:placetype":"venue"
},
  "geometry": {"coordinates":[5.130603,51.571198],"type":"Point"}
}