{
  "type": "Feature",
  "properties": {
    "addr:full":"Herenstr 32 Hilversum North Holland 1211 CC",
    "addr:housenumber":"32",
    "addr:postcode":"1211 cc",
    "addr:street":"Herenstr",
    "iso:country":"NL",
    "sg:address":"Herenstr 32",
    "sg:city":"Hilversum",
    "sg:orig_category":"Woninginrichting",
    "sg:phone":"+31 35 624 5514",
    "sg:postcode":"1211 CC",
    "sg:province":"North Holland",
    "wof:name":"Heksenbal, De",
    "wof:placetype":"venue"
},
  "geometry": {"coordinates":[5.1736950874,52.2238731384],"type":"Point"}
}