{
  "type": "Feature",
  "properties": {
    "addr:full":"Raadhuispln 5 Meijel Limburg 5768 AR",
    "addr:housenumber":"5",
    "addr:postcode":"5768",
    "addr:street":"Raadhuispln",
    "iso:country":"NL",
    "sg:address":"Raadhuispln 5",
    "sg:city":"Meijel",
    "sg:orig_category":"Kantoorbenodigdheden",
    "sg:phone":"+31 77 466 1865",
    "sg:postcode":"5768 AR",
    "sg:province":"Limburg",
    "wof:name":"Coolen-Pluijm",
    "wof:placetype":"venue"
},
  "geometry": {"coordinates":[5.8858861923,51.3443946838],"type":"Point"}
}