{
  "type": "Feature",
  "properties": {
    "addr:full":"Strengwg 1 Heemskerk North Holland 1969 KP",
    "addr:housenumber":"1",
    "addr:postcode":"1969 kp",
    "addr:street":"Strengwg",
    "iso:country":"NL",
    "sg:address":"Strengwg 1",
    "sg:city":"Heemskerk",
    "sg:orig_category":"Verhuizingen",
    "sg:phone":"+31 251 250 104",
    "sg:postcode":"1969 KP",
    "sg:province":"North Holland",
    "sg:website":"HTTP://www.stetheemskerk.nl",
    "wof:name":"Stet Heemskerk Bv",
    "wof:placetype":"venue"
},
  "geometry": {"coordinates":[4.652426,52.506802],"type":"Point"}
}