{
  "type": "Feature",
  "properties": {
    "addr:full":"Wandelweg 25 Wormerveer Noord-Holland 1521 AA",
    "addr:housenumber":"25",
    "addr:postcode":"1521 aa",
    "addr:street":"Wandelweg",
    "iso:country":"NL",
    "sg:address":"Wandelweg 25",
    "sg:city":"Wormerveer",
    "sg:orig_category":"Kantoor- And Schoolbenodigdheden Gh",
    "sg:phone":"+31 75 628 1138",
    "sg:postcode":"1521 AA",
    "sg:province":"Noord-Holland",
    "wof:name":"H.C. Teer Papier C.V.",
    "wof:placetype":"venue"
},
  "geometry": {"coordinates":[4.796877861,52.4884872437],"type":"Point"}
}