{
  "type": "Feature",
  "properties": {
    "addr:full":"A V Ostadeln 21 Utrecht Utrecht 3583 AA",
    "addr:housenumber":"21",
    "addr:postcode":"3583 aa",
    "addr:street":"A;Ostadeln",
    "iso:country":"NL",
    "sg:address":"A V Ostadeln 21",
    "sg:city":"Utrecht",
    "sg:orig_category":"Webdesign Bureaus",
    "sg:phone":"+31 30 276 3545",
    "sg:postcode":"3583 AA",
    "sg:province":"Utrecht",
    "sg:website":"http://www.webcraft.nl",
    "wof:name":"Webcraft",
    "wof:placetype":"venue"
},
  "geometry": {"coordinates":[5.1437101364,52.0866012573],"type":"Point"}
}