{
  "type": "Feature",
  "properties": {
    "addr:full":"Faradaystr 14 Tiel Gelderland 4004 JZ",
    "addr:housenumber":"14",
    "addr:postcode":"4004 jz",
    "addr:street":"Faradaystr;Gelderland",
    "iso:country":"NL",
    "sg:address":"Faradaystr 14",
    "sg:city":"Tiel",
    "sg:orig_category":"Adviesbureaus Gezondheidszorg",
    "sg:phone":"+31 344 615 300",
    "sg:postcode":"4004 JZ",
    "sg:province":"Gelderland",
    "sg:website":"http://www.medimpex.nl",
    "wof:name":"Medimpex Bv",
    "wof:placetype":"venue"
},
  "geometry": {"coordinates":[5.434639,51.907997],"type":"Point"}
}