{
  "type": "Feature",
  "properties": {
    "iso:country":"NL",
    "sg:address":"Offenbachln 556",
    "sg:city":"Eindhoven",
    "sg:orig_category":"Webdesign Bureaus",
    "sg:phone":"+31 6 55756984",
    "sg:postcode":"5654 RS",
    "sg:province":"Noord-Brabant",
    "sg:website":"http://www.siejet.nl",
    "wof:name":"Siejet",
    "wof:placetype":"venue"
},
  "geometry": {"coordinates":[5.4530448914,51.4230461121],"type":"Point"}
}