{
  "type": "Feature",
  "properties": {
    "addr:full":"Archipel 2541 Lelystad Flevoland 8224 GV",
    "addr:postcode":"2541;8224 gv",
    "addr:street":"Archipel;Flevoland",
    "iso:country":"NL",
    "sg:address":"Archipel 2541",
    "sg:city":"Lelystad",
    "sg:orig_category":"Onderhoud And Reparatie Kantoorapparatuur",
    "sg:phone":"+31 320 231 039",
    "sg:postcode":"8224 GV",
    "sg:province":"Flevoland",
    "wof:name":"Jbb",
    "wof:placetype":"venue"
},
  "geometry": {"coordinates":[5.488578,52.509495],"type":"Point"}
}