{
  "type": "Feature",
  "properties": {
    "addr:full":"Buitenwg 75 Maurik Gelderland 4021 BC",
    "addr:housenumber":"75",
    "addr:postcode":"4021 bc",
    "addr:street":"Buitenwg;Gelderland",
    "iso:country":"NL",
    "sg:address":"Buitenwg 75",
    "sg:city":"Maurik",
    "sg:orig_category":"Webdesign Bureaus",
    "sg:phone":"+31 344 694 948",
    "sg:postcode":"4021 BC",
    "sg:province":"Gelderland",
    "wof:name":"Proweb",
    "wof:placetype":"venue"
},
  "geometry": {"coordinates":[5.434679985,51.9670906067],"type":"Point"}
}