{
  "type": "Feature",
  "properties": {
    "addr:full":"Oude Harderw Wg 63A Doornspyk Gelderland 8085 PE",
    "addr:housenumber":"63a",
    "addr:postcode":"8085 pe",
    "addr:street":"Oude;Wg;Gelderland",
    "iso:country":"NL",
    "sg:address":"Oude Harderw Wg 63A",
    "sg:city":"Doornspyk",
    "sg:orig_category":"Verenigingen En Stichtingen",
    "sg:phone":"+31 525 681 597",
    "sg:postcode":"8085 PE",
    "sg:province":"Gelderland",
    "wof:name":"Ons Huus",
    "wof:placetype":"venue"
},
  "geometry": {"coordinates":[5.81365,52.414104],"type":"Point"}
}