{
  "type": "Feature",
  "properties": {
    "addr:full":"Speelheuvelstraat 2 Someren Noord-Brabant 5711 AT",
    "addr:housenumber":"2",
    "addr:postcode":"5711",
    "addr:street":"Speelheuvelstraat",
    "iso:country":"NL",
    "sg:address":"Speelheuvelstraat 2",
    "sg:city":"Someren",
    "sg:orig_category":"Parfum And Cosmetica Gh",
    "sg:phone":"+31 493 470 164",
    "sg:postcode":"5711 AT",
    "sg:province":"Noord-Brabant",
    "wof:name":"Chronique Cosmetique",
    "wof:placetype":"venue"
},
  "geometry": {"coordinates":[5.712206,51.386036],"type":"Point"}
}