{
  "type": "Feature",
  "properties": {
    "addr:full":"Englaan 4 Hemmen Gelderland 6672 LD",
    "addr:housenumber":"4",
    "addr:postcode":"6672 ld",
    "addr:street":"Englaan;Gelderland",
    "iso:country":"NL",
    "sg:address":"Englaan 4",
    "sg:city":"Hemmen",
    "sg:orig_category":"Bedrijfs- And Managementsconsultants",
    "sg:phone":"+31 488 420 601",
    "sg:postcode":"6672 LD",
    "sg:province":"Gelderland",
    "wof:name":"Industrial Catering Consultancy Icc Bv",
    "wof:placetype":"venue"
},
  "geometry": {"coordinates":[5.703059,51.932156],"type":"Point"}
}