{
  "type": "Feature",
  "properties": {
    "addr:full":"De Stede 26 'S Gravenhage South Holland 2543 BG",
    "addr:housenumber":"26",
    "addr:postcode":"2543",
    "addr:street":"De Stede;' S Gravenhage",
    "iso:country":"NL",
    "sg:address":"De Stede 26",
    "sg:city":"'S Gravenhage",
    "sg:orig_category":"Banken And Kredietinstellingen",
    "sg:phone":"+31 70 366 3317",
    "sg:postcode":"2543 BG",
    "sg:province":"South Holland",
    "wof:name":"Postkantoor",
    "wof:placetype":"venue"
},
  "geometry": {"coordinates":[4.259367,52.043556],"type":"Point"}
}