{
  "type": "Feature",
  "properties": {
    "addr:full":"Leeuwendaalln 21 Ryswyk Zh South Holland 2281 GJ",
    "addr:housenumber":"21;zh",
    "addr:postcode":"2281 gj",
    "addr:street":"Leeuwendaalln",
    "iso:country":"NL",
    "sg:address":"Leeuwendaalln 21",
    "sg:city":"Ryswyk Zh",
    "sg:orig_category":"Administratie- En Boekhoudkantoren",
    "sg:phone":"+31 70 399 5702",
    "sg:postcode":"2281 GJ",
    "sg:province":"South Holland",
    "wof:name":"Hoos Bv, A",
    "wof:placetype":"venue"
},
  "geometry": {"coordinates":[4.341704,52.056934],"type":"Point"}
}