{
  "type": "Feature",
  "properties": {
    "iso:country":"NL",
    "sg:address":"Hoofdwal 119",
    "sg:city":"Gorinchem",
    "sg:orig_category":"Milieu",
    "sg:phone":"+31 183 631 550",
    "sg:postcode":"4207 EC",
    "sg:province":"Zuid-Holland",
    "wof:name":"Prokam",
    "wof:placetype":"venue"
},
  "geometry": {"coordinates":[4.985542,51.835487],"type":"Point"}
}