{
  "type": "Feature",
  "properties": {
    "addr:full":"Randweg 64 Beverwijk Noord-Holland 1948 NS",
    "addr:housenumber":"64",
    "addr:postcode":"1948 ns",
    "addr:street":"Randweg",
    "iso:country":"NL",
    "sg:address":"Randweg 64",
    "sg:city":"Beverwijk",
    "sg:orig_category":"Airconditioning And Ventilatie",
    "sg:phone":"+31 251 210 724",
    "sg:postcode":"1948 NS",
    "sg:province":"Noord-Holland",
    "wof:name":"Merkx Installatietechniek Bv",
    "wof:placetype":"venue"
},
  "geometry": {"coordinates":[4.673303,52.476601],"type":"Point"}
}