{
  "type": "Feature",
  "properties": {
    "addr:full":"Hoogbrugstr 50 Maastricht Limburg 6221 CS",
    "addr:housenumber":"50",
    "addr:postcode":"6221 cs",
    "addr:street":"Hoogbrugstr",
    "iso:country":"NL",
    "sg:address":"Hoogbrugstr 50",
    "sg:city":"Maastricht",
    "sg:orig_category":"Kopieerservice",
    "sg:phone":"+31 43 325 8686",
    "sg:postcode":"6221 CS",
    "sg:province":"Limburg",
    "sg:website":"http://www.qs.nl",
    "wof:name":"Qs Graphics",
    "wof:placetype":"venue"
},
  "geometry": {"coordinates":[5.700069,50.847454],"type":"Point"}
}