{
  "type": "Feature",
  "properties": {
    "iso:country":"NL",
    "sg:address":"Nyverheidswg 13",
    "sg:city":"Maastricht",
    "sg:classifiers":[
        {
            "category":"Retail",
            "subcategory":"Auto Repair",
            "type":"Services"
        }
    ],
    "sg:phone":"+31 43 361 4164",
    "sg:postcode":"6227 AL",
    "sg:province":"Limburg",
    "sg:tags":[
        "garage"
    ],
    "wof:name":"Dassen, Marc",
    "wof:placetype":"venue"
},
  "geometry": {"coordinates":[5.721924,50.842373],"type":"Point"}
}