{
  "type": "Feature",
  "properties": {
    "addr:full":"Keetzyde 9 Edam Noord-Holland 1135 VX",
    "addr:housenumber":"9",
    "addr:postcode":"1135 vx",
    "addr:street":"Keetzyde",
    "iso:country":"NL",
    "sg:address":"Keetzyde 9",
    "sg:city":"Edam",
    "sg:orig_category":"Meubelstoffering",
    "sg:phone":"+31 299 350 807",
    "sg:postcode":"1135 VX",
    "sg:province":"Noord-Holland",
    "wof:name":"Hooijberg, Ewoud",
    "wof:placetype":"venue"
},
  "geometry": {"coordinates":[5.053218,52.511219],"type":"Point"}
}