{
  "type": "Feature",
  "properties": {
    "addr:full":"Oude Amersfoortseweg 177 Hilversum Noord-Holland 1212 AB",
    "addr:housenumber":"177",
    "addr:postcode":"1212 ab",
    "addr:street":"Oude Amersfoortseweg",
    "iso:country":"NL",
    "sg:address":"Oude Amersfoortseweg 177",
    "sg:city":"Hilversum",
    "sg:orig_category":"Artiestenbureaus",
    "sg:phone":"+31 35 642 0465",
    "sg:postcode":"1212 AB",
    "sg:province":"Noord-Holland",
    "wof:name":"D O F Jongen",
    "wof:placetype":"venue"
},
  "geometry": {"coordinates":[5.192862,52.219482],"type":"Point"}
}