{
  "type": "Feature",
  "properties": {
    "addr:full":"Brink 36 Assen Drenthe 9401 HV",
    "addr:housenumber":"36",
    "addr:postcode":"9401 hv",
    "addr:street":"Brink",
    "iso:country":"NL",
    "sg:address":"Brink 36",
    "sg:city":"Assen",
    "sg:orig_category":"Grafisch Ontwerpers",
    "sg:phone":"+31 592 313 976",
    "sg:postcode":"9401 HV",
    "sg:province":"Drenthe",
    "sg:website":"http://www.inontwerp.nl",
    "wof:name":"In Ontwerp Buro V Grafische Vormgeving",
    "wof:placetype":"venue"
},
  "geometry": {"coordinates":[6.559506,52.994041],"type":"Point"}
}