{
  "type": "Feature",
  "properties": {
    "addr:full":"Avenbeeck 76 Hillegom North Holland 2182 RX",
    "addr:housenumber":"76",
    "addr:postcode":"2182 rx",
    "addr:street":"Avenbeeck",
    "iso:country":"NL",
    "sg:address":"Avenbeeck 76",
    "sg:city":"Hillegom",
    "sg:orig_category":"Kampeerartikelen",
    "sg:phone":"+31 252 520 242",
    "sg:postcode":"2182 RX",
    "sg:province":"North Holland",
    "wof:name":"Byrun Trading",
    "wof:placetype":"venue"
},
  "geometry": {"coordinates":[4.5840301514,52.2864265442],"type":"Point"}
}