{
  "type": "Feature",
  "properties": {
    "addr:full":"Traviatawg 75 Hoogvliet Rt Zuid-Holland 3194 JW",
    "addr:housenumber":"75",
    "addr:postcode":"rt;3194 jw",
    "addr:street":"Traviatawg",
    "iso:country":"NL",
    "sg:address":"Traviatawg 75",
    "sg:city":"Hoogvliet Rt",
    "sg:orig_category":"Verenigingen En Stichtingen",
    "sg:phone":"+31 10 216 2819",
    "sg:postcode":"3194 JW",
    "sg:province":"Zuid-Holland",
    "wof:name":"Biljartver Hoogvliet",
    "wof:placetype":"venue"
},
  "geometry": {"coordinates":[4.357334,51.870419],"type":"Point"}
}