{
  "type": "Feature",
  "properties": {
    "addr:full":"Engelenkampstraat 61 Sittard Limburg 6131 JE",
    "addr:housenumber":"61",
    "addr:postcode":"6131 je",
    "addr:street":"Engelenkampstraat",
    "iso:country":"NL",
    "sg:address":"Engelenkampstraat 61",
    "sg:city":"Sittard",
    "sg:orig_category":"Kappers",
    "sg:phone":"+31 46 451 5081",
    "sg:postcode":"6131 JE",
    "sg:province":"Limburg",
    "wof:name":"Dameskapsalon Rene",
    "wof:placetype":"venue"
},
  "geometry": {"coordinates":[5.8669829369,50.9967308044],"type":"Point"}
}