{
  "type": "Feature",
  "properties": {
    "addr:full":"Westermeerwg 17 Tollebeek NL. 8309 PZ",
    "addr:housenumber":"17",
    "addr:postcode":"8309 pz",
    "addr:street":"Westermeerwg;Nl.",
    "iso:country":"NL",
    "sg:address":"Westermeerwg 17",
    "sg:city":"Tollebeek",
    "sg:orig_category":"Koel- En Vrieshuizen",
    "sg:phone":"+31 527 276 162",
    "sg:postcode":"8309 PZ",
    "sg:province":"NL.",
    "wof:name":"Graaf, M D De",
    "wof:placetype":"venue"
},
  "geometry": {"coordinates":[5.606433,52.697395],"type":"Point"}
}