{
  "type": "Feature",
  "properties": {
    "addr:full":"Emmastr 38 Voorburg Zuid-Holland 2271 SR",
    "addr:housenumber":"38",
    "addr:postcode":"2271 sr",
    "addr:street":"Emmastr",
    "iso:country":"NL",
    "sg:address":"Emmastr 38",
    "sg:city":"Voorburg",
    "sg:orig_category":"Schilders",
    "sg:phone":"+31 70 300 0549",
    "sg:postcode":"2271 SR",
    "sg:province":"Zuid-Holland",
    "wof:name":"Berg, G Van De",
    "wof:placetype":"venue"
},
  "geometry": {"coordinates":[4.371812,52.07349],"type":"Point"}
}