{
  "type": "Feature",
  "properties": {
    "iso:country":"NL",
    "sg:address":"Eikbosserweg 46",
    "sg:city":"Hilversum",
    "sg:orig_category":"Goederenvervoer Over De Weg",
    "sg:phone":"+31 35 624 1369",
    "sg:postcode":"1214 AJ",
    "sg:province":"North Holland",
    "wof:name":"G J Kroon",
    "wof:placetype":"venue"
},
  "geometry": {"coordinates":[5.174355,52.217541],"type":"Point"}
}