{
  "type": "Feature",
  "properties": {
    "addr:full":"Plantage Kerkln 14 Amsterdam Noord-Holland 1018 TB",
    "addr:housenumber":"14",
    "addr:postcode":"1018 tb",
    "addr:street":"Plantage Kerkln",
    "iso:country":"NL",
    "sg:address":"Plantage Kerkln 14",
    "sg:city":"Amsterdam",
    "sg:classifiers":[
        {
            "category":"Food & Beverages",
            "subcategory":"Bakery",
            "type":"Retail Goods"
        }
    ],
    "sg:phone":"+31 20 622 5712",
    "sg:postcode":"1018 TB",
    "sg:province":"Noord-Holland",
    "sg:tags":[
        "brood",
        "en",
        "banket"
    ],
    "wof:name":"Ed Rooth Bakkerij",
    "wof:placetype":"venue"
},
  "geometry": {"coordinates":[4.911431,52.365795],"type":"Point"}
}