{
  "type": "Feature",
  "properties": {
    "addr:full":"Raadhuispln 42 , (Wc Crimpenhof) Krimpen Ad Yssel Zuid-Holland 2922 AG",
    "addr:housenumber":"42",
    "addr:postcode":"2922",
    "addr:street":"Raadhuispln;Crimpenhof",
    "iso:country":"NL",
    "sg:address":"Raadhuispln 42 , (Wc Crimpenhof)",
    "sg:city":"Krimpen Ad Yssel",
    "sg:orig_category":"Fotoreportages",
    "sg:phone":"+31 180 512 218",
    "sg:postcode":"2922 AG",
    "sg:province":"Zuid-Holland",
    "wof:name":"Starre, Combi Foto Van Der",
    "wof:placetype":"venue"
},
  "geometry": {"coordinates":[4.59038,51.914467],"type":"Point"}
}