{
  "type": "Feature",
  "properties": {
    "addr:full":"Boschdk 187 Eindhoven Noord-Brabant 5612 HB",
    "addr:housenumber":"187",
    "addr:postcode":"5612 hb",
    "iso:country":"NL",
    "sg:address":"Boschdk 187",
    "sg:city":"Eindhoven",
    "sg:orig_category":"Video - Faciliteiten En Producties",
    "sg:phone":"+31 40 243 4305",
    "sg:postcode":"5612 HB",
    "sg:province":"Noord-Brabant",
    "wof:name":"European Communication Projects Bv",
    "wof:placetype":"venue"
},
  "geometry": {"coordinates":[5.46769,51.448238],"type":"Point"}
}