{
  "type": "Feature",
  "properties": {
    "addr:full":"Smedenerf 2 Roermond Limburg 6043 SG",
    "addr:housenumber":"2",
    "addr:postcode":"6043 sg",
    "addr:street":"Smedenerf",
    "iso:country":"NL",
    "sg:address":"Smedenerf 2",
    "sg:city":"Roermond",
    "sg:classifiers":[
        {
            "category":"Education",
            "subcategory":"Preschool",
            "type":"Public Place"
        }
    ],
    "sg:phone":"+31 475 324 669",
    "sg:postcode":"6043 SG",
    "sg:province":"Limburg",
    "sg:tags":[
        "kleuteronderwijs",
        "basis-"
    ],
    "wof:name":"Openbare Basisschool De Brink",
    "wof:placetype":"venue"
},
  "geometry": {"coordinates":[6.021606,51.18832],"type":"Point"}
}