{
  "type": "Feature",
  "properties": {
    "addr:full":"Marconiweg 5 Hellevoetsluis South Holland 3225 LV",
    "addr:housenumber":"5",
    "addr:postcode":"3225",
    "addr:street":"Marconiweg",
    "iso:country":"NL",
    "sg:address":"Marconiweg 5",
    "sg:city":"Hellevoetsluis",
    "sg:orig_category":"Autokeuringen",
    "sg:phone":"+31 181 319 936",
    "sg:postcode":"3225 LV",
    "sg:province":"South Holland",
    "wof:name":"Meijboom Autoschade Vof",
    "wof:placetype":"venue"
},
  "geometry": {"coordinates":[4.169626,51.840965],"type":"Point"}
}