{
  "type": "Feature",
  "properties": {
    "addr:full":"Stavangerweg 12 Amsterdam Noord-Holland 1013 AT",
    "addr:housenumber":"12",
    "addr:postcode":"1013",
    "addr:street":"Stavangerweg",
    "iso:country":"NL",
    "sg:address":"Stavangerweg 12",
    "sg:city":"Amsterdam",
    "sg:orig_category":"Hout Gh",
    "sg:phone":"+31 20 684 4967",
    "sg:postcode":"1013 AT",
    "sg:province":"Noord-Holland",
    "wof:name":"Gamma",
    "wof:placetype":"venue"
},
  "geometry": {"coordinates":[4.877272,52.393841],"type":"Point"}
}