{
  "type": "Feature",
  "properties": {
    "addr:full":"Markt 7 Goedereede Zuid-Holland 3252 BC",
    "addr:housenumber":"7",
    "addr:postcode":"3252 bc",
    "addr:street":"Markt",
    "iso:country":"NL",
    "sg:address":"Markt 7",
    "sg:city":"Goedereede",
    "sg:orig_category":"Woningbouw- Verenigingen En -Stichtingen",
    "sg:phone":"+31 187 491 539",
    "sg:postcode":"3252 BC",
    "sg:province":"Zuid-Holland",
    "wof:name":"Beter Wonen",
    "wof:placetype":"venue"
},
  "geometry": {"coordinates":[3.9774808884,51.8182258606],"type":"Point"}
}