{
  "type": "Feature",
  "properties": {
    "addr:full":"De Werf 87 Bodegraven Zuid-Holland 2411 RZ",
    "addr:housenumber":"87",
    "addr:postcode":"2411 rz",
    "addr:street":"De Werf",
    "iso:country":"NL",
    "sg:address":"De Werf 87",
    "sg:city":"Bodegraven",
    "sg:orig_category":"Metaalwerken",
    "sg:phone":"+31 172 619 617",
    "sg:postcode":"2411 RZ",
    "sg:province":"Zuid-Holland",
    "wof:name":"Mac Bodegraven",
    "wof:placetype":"venue"
},
  "geometry": {"coordinates":[4.747547,52.085552],"type":"Point"}
}