{
  "type": "Feature",
  "properties": {
    "addr:full":"Akeleiwg 69 Groningen Groningen 9731 JC",
    "addr:housenumber":"69",
    "addr:postcode":"9731 jc",
    "addr:street":"Akeleiwg",
    "iso:country":"NL",
    "sg:address":"Akeleiwg 69",
    "sg:city":"Groningen",
    "sg:orig_category":"Kinderactiviteiten",
    "sg:phone":"+31 50 542 3692",
    "sg:postcode":"9731 JC",
    "sg:province":"Groningen",
    "wof:name":"Beestenborg, De",
    "wof:placetype":"venue"
},
  "geometry": {"coordinates":[6.597658,53.231697],"type":"Point"}
}