{
  "type": "Feature",
  "properties": {
    "iso:country":"NL",
    "sg:address":"Sparrenln 1A",
    "sg:city":"St Michielsgestel",
    "sg:orig_category":"Kinderopvang",
    "sg:phone":"+31 73 551 5188",
    "sg:postcode":"5271 RG",
    "sg:province":"Noord-Brabant",
    "sg:website":"http://www.catalpa.nl",
    "wof:name":"Boefjes, De",
    "wof:placetype":"venue"
},
  "geometry": {"coordinates":[5.333585,51.636089],"type":"Point"}
}