{
  "type": "Feature",
  "properties": {
    "addr:full":"Zuiderdijk 6 Bovenkarspel Noord-Holland 1611 MC",
    "addr:housenumber":"6",
    "addr:postcode":"1611 mc",
    "addr:street":"Zuiderdijk",
    "iso:country":"NL",
    "sg:address":"Zuiderdijk 6",
    "sg:city":"Bovenkarspel",
    "sg:orig_category":"Overheidsdiensten",
    "sg:phone":"+31 228 511 500",
    "sg:postcode":"1611 MC",
    "sg:province":"Noord-Holland",
    "wof:name":"Pampus",
    "wof:placetype":"venue"
},
  "geometry": {"coordinates":[5.2522149086,52.6872367859],"type":"Point"}
}