{
  "type": "Feature",
  "properties": {
    "addr:full":"Soesterbergsestr 44A Soest Utrecht 3768 EJ",
    "addr:housenumber":"44a",
    "addr:postcode":"3768 ej",
    "addr:street":"Soesterbergsestr",
    "iso:country":"NL",
    "sg:address":"Soesterbergsestr 44A",
    "sg:city":"Soest",
    "sg:orig_category":"Bloemen En Planten",
    "sg:phone":"+31 35 647 0707",
    "sg:postcode":"3768 EJ",
    "sg:province":"Utrecht",
    "wof:name":"Oest, H Van",
    "wof:placetype":"venue"
},
  "geometry": {"coordinates":[5.308627,52.165916],"type":"Point"}
}