{
  "type": "Feature",
  "properties": {
    "iso:country":"NL",
    "sg:address":"De Rotery 15A",
    "sg:city":"Burgh Haamstede",
    "sg:orig_category":"Geluidsinstallaties - Verhuur",
    "sg:phone":"+31 111 461 246",
    "sg:postcode":"4328 BB",
    "sg:province":"Zeeland",
    "sg:website":"http://www.sounddelight.nl",
    "wof:name":"Sound De-Light",
    "wof:placetype":"venue"
},
  "geometry": {"coordinates":[3.747885,51.696407],"type":"Point"}
}