{
  "type": "Feature",
  "properties": {
    "addr:full":"Achter De Houttuinen 10 Middelburg Zeeland 4331 NJ",
    "addr:housenumber":"10",
    "addr:postcode":"4331 nj",
    "addr:street":"Achter De Houttuinen",
    "iso:country":"NL",
    "sg:address":"Achter De Houttuinen 10",
    "sg:city":"Middelburg",
    "sg:orig_category":"Politie",
    "sg:phone":"+31 900 8844",
    "sg:postcode":"4331 NJ",
    "sg:province":"Zeeland",
    "wof:name":"Politie Zeeland District Walcheren Bureau Middelbu",
    "wof:placetype":"venue"
},
  "geometry": {"coordinates":[3.606832,51.496731],"type":"Point"}
}