{
  "type": "Feature",
  "properties": {
    "iso:country":"NL",
    "sg:address":"Tweede Nassaustr 8",
    "sg:city":"Amsterdam",
    "sg:orig_category":"Beeldende Kunstenaars",
    "sg:phone":"+31 20 688 0016",
    "sg:postcode":"1052 BM",
    "sg:province":"North Holland",
    "wof:name":"Karssen, H",
    "wof:placetype":"venue"
},
  "geometry": {"coordinates":[4.878854,52.382298],"type":"Point"}
}