{
  "type": "Feature",
  "properties": {
    "addr:full":"Stationsstraat 77 Waalwijk Noord-Brabant 5141 GC",
    "addr:housenumber":"77",
    "addr:postcode":"5141 gc",
    "addr:street":"Stationsstraat",
    "iso:country":"NL",
    "sg:address":"Stationsstraat 77",
    "sg:city":"Waalwijk",
    "sg:orig_category":"Bloemen And Planten",
    "sg:phone":"+31 416 334 994",
    "sg:postcode":"5141 GC",
    "sg:province":"Noord-Brabant",
    "wof:name":"Chris Aarts Bloemdecoraties",
    "wof:placetype":"venue"
},
  "geometry": {"coordinates":[5.06736,51.687294],"type":"Point"}
}