{
  "type": "Feature",
  "properties": {
    "addr:full":"Maastrichter Brugstraat 7 Maastricht Limburg 6211 ES",
    "addr:housenumber":"7",
    "addr:postcode":"6211 es",
    "addr:street":"Maastrichter Brugstraat",
    "iso:country":"NL",
    "sg:address":"Maastrichter Brugstraat 7",
    "sg:city":"Maastricht",
    "sg:orig_category":"Schoenen",
    "sg:phone":"+31 43 321 3297",
    "sg:postcode":"6211 ES",
    "sg:province":"Limburg",
    "wof:name":"Chaussures Mondiales Bv",
    "wof:placetype":"venue"
},
  "geometry": {"coordinates":[5.693925,50.849197],"type":"Point"}
}