{
  "type": "Feature",
  "properties": {
    "addr:full":"Middelste Groes 8 Heesch Noord-Brabant 5384 VV",
    "addr:housenumber":"8",
    "addr:postcode":"5384 vv",
    "addr:street":"Middelste Groes",
    "iso:country":"NL",
    "sg:address":"Middelste Groes 8",
    "sg:city":"Heesch",
    "sg:orig_category":"Dierenvoeder - Fabrieken",
    "sg:phone":"+31 412 454 433",
    "sg:postcode":"5384 VV",
    "sg:province":"Noord-Brabant",
    "wof:name":"Veevoeders Bv",
    "wof:placetype":"venue"
},
  "geometry": {"coordinates":[5.497656,51.733177],"type":"Point"}
}