{
  "type": "Feature",
  "properties": {
    "addr:full":"Zuidlaarderweg 124 Annen South Carolina 9468 AJ",
    "addr:housenumber":"124;9468",
    "addr:postcode":"aj",
    "addr:street":"Zuidlaarderweg",
    "iso:country":"NL",
    "sg:address":"Zuidlaarderweg 124",
    "sg:city":"Annen",
    "sg:orig_category":"Banken And Kredietinstellingen",
    "sg:phone":"+31 592 267 150",
    "sg:postcode":"9468 AJ",
    "sg:province":"South Carolina",
    "wof:name":"Rabobank",
    "wof:placetype":"venue"
},
  "geometry": {"coordinates":[-79.253815,33.471233],"type":"Point"}
}