{
  "type": "Feature",
  "properties": {
    "addr:full":"Nw Nieuwstr 47 Amsterdam Noord-Holland 1012 NG",
    "addr:housenumber":"47",
    "addr:postcode":"1012 ng",
    "iso:country":"NL",
    "sg:address":"Nw Nieuwstr 47",
    "sg:city":"Amsterdam",
    "sg:orig_category":"Natuurvoeding En Reformartikelen",
    "sg:phone":"+31 20 427 4747",
    "sg:postcode":"1012 NG",
    "sg:province":"Noord-Holland",
    "wof:name":"Vitals Bv",
    "wof:placetype":"venue"
},
  "geometry": {"coordinates":[4.893048,52.375191],"type":"Point"}
}