{
  "type": "Feature",
  "properties": {
    "iso:country":"NL",
    "sg:address":"Brunostraat 64-66",
    "sg:city":"Tilburg",
    "sg:orig_category":"Fotostudio'S And Fotografen",
    "sg:phone":"+31 13 467 3183",
    "sg:postcode":"5042 JA",
    "sg:province":"Noord-Brabant",
    "wof:name":"La Haye Fotografie",
    "wof:placetype":"venue"
},
  "geometry": {"coordinates":[5.059341,51.572041],"type":"Point"}
}