{
  "type": "Feature",
  "properties": {
    "addr:full":"Edenstr 3A Eindhoven Noord-Brabant 5611 JM",
    "addr:housenumber":"3a",
    "addr:postcode":"5611 jm",
    "addr:street":"Edenstr",
    "iso:country":"NL",
    "sg:address":"Edenstr 3A",
    "sg:city":"Eindhoven",
    "sg:orig_category":"Zonnebank- En Solariumcentra",
    "sg:phone":"+31 40 245 6362",
    "sg:postcode":"5611 JM",
    "sg:province":"Noord-Brabant",
    "wof:name":"City Sun, Zonnestudio",
    "wof:placetype":"venue"
},
  "geometry": {"coordinates":[5.473038,51.43465],"type":"Point"}
}