{
  "type": "Feature",
  "properties": {
    "addr:full":"Markt 93 Geleen Limburg 6161 GM",
    "addr:housenumber":"93",
    "addr:postcode":"6161 gm",
    "addr:street":"Markt",
    "iso:country":"NL",
    "sg:address":"Markt 93",
    "sg:city":"Geleen",
    "sg:orig_category":"Wasmachines En Wasdrogers - Onderhoud En Reparatie",
    "sg:phone":"+31 46 437 9677",
    "sg:postcode":"6161 GM",
    "sg:province":"Limburg",
    "wof:name":"Paulussen Vof",
    "wof:placetype":"venue"
},
  "geometry": {"coordinates":[5.8272399902,50.9705047607],"type":"Point"}
}