{
  "type": "Feature",
  "properties": {
    "iso:country":"NL",
    "sg:address":"Kalkoenweg 40",
    "sg:city":"Ermelo",
    "sg:orig_category":"Houten Verpakkingen Fab",
    "sg:phone":"+31 341 559 254",
    "sg:postcode":"3851 SC",
    "sg:province":"Gelderland",
    "wof:name":"D.G. De With Ermelo Bv",
    "wof:placetype":"venue"
},
  "geometry": {"coordinates":[5.616765,52.315704],"type":"Point"}
}