{
  "type": "Feature",
  "properties": {
    "addr:full":"Dorpsstr 35 Abbekerk Noord-Holland 1657 AA",
    "addr:housenumber":"35",
    "addr:postcode":"1657 aa",
    "addr:street":"Dorpsstr",
    "iso:country":"NL",
    "sg:address":"Dorpsstr 35",
    "sg:city":"Abbekerk",
    "sg:orig_category":"Luchtvaartelektronica",
    "sg:phone":"+31 229 582 165",
    "sg:postcode":"1657 AA",
    "sg:province":"Noord-Holland",
    "sg:website":"http://www.airlab.nl",
    "wof:name":"Airlab",
    "wof:placetype":"venue"
},
  "geometry": {"coordinates":[5.019754,52.736481],"type":"Point"}
}