{
  "type": "Feature",
  "properties": {
    "iso:country":"NL",
    "sg:address":"Dorpsstr 35",
    "sg:city":"Abbekerk",
    "sg:orig_category":"Luchtvaartelektronica",
    "sg:phone":"+31 229 582 165",
    "sg:postcode":"1657 AA",
    "sg:province":"Noord-Holland",
    "sg:website":"http://www.airlab.nl",
    "wof:name":"Airlab",
    "wof:placetype":"venue"
},
  "geometry": {"coordinates":[5.019754,52.736481],"type":"Point"}
}