{
  "type": "Feature",
  "properties": {
    "iso:country":"NL",
    "sg:address":"Bartokpad 4",
    "sg:city":"Delft",
    "sg:orig_category":"Fietsen En Bromfietsen",
    "sg:phone":"+31 15 257 2545",
    "sg:postcode":"2625 AB",
    "sg:province":"South Holland",
    "wof:name":"Paul Karlas",
    "wof:placetype":"venue"
},
  "geometry": {"coordinates":[4.34213,51.996384],"type":"Point"}
}