{
  "type": "Feature",
  "properties": {
    "addr:full":"Sperwerkamp 87 Driebergen Rysenb Utrecht 3972 WD",
    "addr:housenumber":"87",
    "addr:postcode":"3972 wd",
    "addr:street":"Sperwerkamp;Rysenb",
    "iso:country":"NL",
    "sg:address":"Sperwerkamp 87",
    "sg:city":"Driebergen Rysenb",
    "sg:orig_category":"Fotoreportages",
    "sg:phone":"+31 343 512 739",
    "sg:postcode":"3972 WD",
    "sg:province":"Utrecht",
    "sg:website":"http://www.racepictures.com",
    "wof:name":"Racepictures.Com",
    "wof:placetype":"venue"
},
  "geometry": {"coordinates":[5.268459,52.051033],"type":"Point"}
}