{
  "type": "Feature",
  "properties": {
    "iso:country":"NL",
    "sg:address":"Dorpsstraat 90",
    "sg:city":"Nibbixwoud",
    "sg:orig_category":"Bloemen- And Plantenteelt",
    "sg:phone":"+31 229 571 451",
    "sg:postcode":"1688 CJ",
    "sg:province":"Noord-Holland",
    "wof:name":"C. Vlaming En Zonen",
    "wof:placetype":"venue"
},
  "geometry": {"coordinates":[5.071713,52.691628],"type":"Point"}
}