{
  "type": "Feature",
  "properties": {
    "addr:full":"Vriezekoop 39Ab Leimuiden South Holland 2451 CP",
    "addr:housenumber":"39ab",
    "addr:postcode":"2451 cp",
    "addr:street":"Vriezekoop",
    "iso:country":"NL",
    "sg:address":"Vriezekoop 39Ab",
    "sg:city":"Leimuiden",
    "sg:orig_category":"Onderhoudswerken",
    "sg:phone":"+31 172 509 225",
    "sg:postcode":"2451 CP",
    "sg:province":"South Holland",
    "wof:name":"Zeegers, Hans",
    "wof:placetype":"venue"
},
  "geometry": {"coordinates":[4.706572,52.216244],"type":"Point"}
}