{
  "type": "Feature",
  "properties": {
    "addr:full":"Nobeldreef 173 Maassluis South Holland 3146 AJ",
    "addr:housenumber":"173",
    "addr:postcode":"3146 aj",
    "addr:street":"Nobeldreef",
    "iso:country":"NL",
    "sg:address":"Nobeldreef 173",
    "sg:city":"Maassluis",
    "sg:orig_category":"Bedrijfs- And Managementsconsultants",
    "sg:phone":"+31 10 599 7014",
    "sg:postcode":"3146 AJ",
    "sg:province":"South Holland",
    "wof:name":"Agroservices Klapwijk Bv",
    "wof:placetype":"venue"
},
  "geometry": {"coordinates":[4.224254,51.933807],"type":"Point"}
}