{
  "type": "Feature",
  "properties": {
    "iso:country":"NL",
    "sg:address":"Raadhuisstraat 24",
    "sg:city":"Roosendaal",
    "sg:orig_category":"Kunst And Kunstenaarsbenodigdheden",
    "sg:phone":"+31 165 561 538",
    "sg:postcode":"4701 PS",
    "sg:province":"Noord-Brabant",
    "wof:name":"Lijstenatelier Lijst-In",
    "wof:placetype":"venue"
},
  "geometry": {"coordinates":[4.457781,51.532307],"type":"Point"}
}