{
  "type": "Feature",
  "properties": {
    "addr:full":"Sportdreef 3 Huissen Gelderland 6852 EH",
    "addr:housenumber":"3",
    "addr:postcode":"6852 eh",
    "addr:street":"Sportdreef;Gelderland",
    "iso:country":"NL",
    "sg:address":"Sportdreef 3",
    "sg:city":"Huissen",
    "sg:orig_category":"Paramedische Behandelingen",
    "sg:phone":"+31 26 325 4931",
    "sg:postcode":"6852 EH",
    "sg:province":"Gelderland",
    "wof:name":"Praktijk Voor Logopedie",
    "wof:placetype":"venue"
},
  "geometry": {"coordinates":[5.92604,51.945782],"type":"Point"}
}