{
  "type": "Feature",
  "properties": {
    "addr:full":"Rijksstraatweg 151 Heemskerk Noord-Holland 1969 LE",
    "addr:housenumber":"151",
    "addr:postcode":"1969 le",
    "addr:street":"Rijksstraatweg",
    "iso:country":"NL",
    "sg:address":"Rijksstraatweg 151",
    "sg:city":"Heemskerk",
    "sg:orig_category":"Gebouwenafwerking, Renovaties And Reiniging",
    "sg:phone":"+31 251 232 849",
    "sg:postcode":"1969 LE",
    "sg:province":"Noord-Holland",
    "wof:name":"Jarvo Bv",
    "wof:placetype":"venue"
},
  "geometry": {"coordinates":[4.652647,52.512775],"type":"Point"}
}