{
  "type": "Feature",
  "properties": {
    "iso:country":"NL",
    "sg:address":"Drielandenhoek 51",
    "sg:city":"Haarlem",
    "sg:orig_category":"Verenigingen En Stichtingen",
    "sg:phone":"+31 23 540 5530",
    "sg:postcode":"2034 LT",
    "sg:province":"Noord-Holland",
    "wof:name":"Wandelpool, Sticht De",
    "wof:placetype":"venue"
},
  "geometry": {"coordinates":[4.64677,52.364307],"type":"Point"}
}