{
  "type": "Feature",
  "properties": {
    "addr:full":"Visserswg 10/W Hoogmade Zuid-Holland 2355 AL",
    "addr:housenumber":"10 / w",
    "addr:postcode":"2355 al",
    "addr:street":"Visserswg",
    "iso:country":"NL",
    "sg:address":"Visserswg 10/W",
    "sg:city":"Hoogmade",
    "sg:orig_category":"Jachthavens - Jachtwerven",
    "sg:phone":"+31 71 501 8728",
    "sg:postcode":"2355 AL",
    "sg:province":"Zuid-Holland",
    "wof:name":"Hoogmade Bv",
    "wof:placetype":"venue"
},
  "geometry": {"coordinates":[4.583625,52.169239],"type":"Point"}
}