{
  "type": "Feature",
  "properties": {
    "addr:full":"Hof 10 Bergeyk North Brabant 5571 CC",
    "addr:housenumber":"10",
    "addr:postcode":"5571 cc",
    "addr:street":"Hof",
    "iso:country":"NL",
    "sg:address":"Hof 10",
    "sg:city":"Bergeyk",
    "sg:orig_category":"Geschenkartikelen",
    "sg:phone":"+31 497 575 346",
    "sg:postcode":"5571 CC",
    "sg:province":"North Brabant",
    "wof:name":"Jinday",
    "wof:placetype":"venue"
},
  "geometry": {"coordinates":[5.357868,51.321373],"type":"Point"}
}