{
  "type": "Feature",
  "properties": {
    "iso:country":"NL",
    "sg:address":"Midstraat 1",
    "sg:city":"Joure",
    "sg:orig_category":"Kansspelen",
    "sg:phone":"+31 513 416 245",
    "sg:postcode":"8501 AC",
    "sg:province":"Friesland",
    "wof:name":"Playland",
    "wof:placetype":"venue"
},
  "geometry": {"coordinates":[5.7921538353,52.9692764282],"type":"Point"}
}