{
  "type": "Feature",
  "properties": {
    "addr:full":"Nieuwe Kerkstraat 143 Amsterdam North Holland 1018 VL",
    "addr:housenumber":"143",
    "addr:postcode":"1018 vl",
    "addr:street":"Nieuwe Kerkstraat",
    "iso:country":"NL",
    "sg:address":"Nieuwe Kerkstraat 143",
    "sg:city":"Amsterdam",
    "sg:orig_category":"Fotostudio'S And Fotografen",
    "sg:phone":"+31 20 639 1222",
    "sg:postcode":"1018 VL",
    "sg:province":"North Holland",
    "wof:name":"Kars Fotografie",
    "wof:placetype":"venue"
},
  "geometry": {"coordinates":[4.907898,52.364746],"type":"Point"}
}