{
  "type": "Feature",
  "properties": {
    "addr:full":"Sleperwg 10 Maastricht Limburg 6222 NK",
    "addr:housenumber":"10",
    "addr:postcode":"6222 nk",
    "addr:street":"Sleperwg",
    "iso:country":"NL",
    "sg:address":"Sleperwg 10",
    "sg:city":"Maastricht",
    "sg:orig_category":"Bodemonderzoek",
    "sg:phone":"+31 43 352 4499",
    "sg:postcode":"6222 NK",
    "sg:province":"Limburg",
    "wof:name":"Laboran International",
    "wof:placetype":"venue"
},
  "geometry": {"coordinates":[5.72341,50.87706],"type":"Point"}
}