{
  "type": "Feature",
  "properties": {
    "iso:country":"NL",
    "sg:address":"Hoofdland 7",
    "sg:city":"Mynsheerenland",
    "sg:orig_category":"Medische Installaties En Instrumenten",
    "sg:phone":"+31 186 609 891",
    "sg:postcode":"3271 VC",
    "sg:province":"Zuid-Holland",
    "sg:website":"http://www.rxcare.nl",
    "wof:name":"Rx-Care Bv",
    "wof:placetype":"venue"
},
  "geometry": {"coordinates":[4.477663,51.794128],"type":"Point"}
}