{
  "type": "Feature",
  "properties": {
    "addr:full":"Julianaln 43 Bilthoven Utrecht 3722 GE",
    "addr:housenumber":"43",
    "addr:postcode":"3722",
    "addr:street":"Julianaln",
    "iso:country":"NL",
    "sg:address":"Julianaln 43",
    "sg:city":"Bilthoven",
    "sg:orig_category":"Bedden En Matrassen",
    "sg:phone":"+31 30 228 7451",
    "sg:postcode":"3722 GE",
    "sg:province":"Utrecht",
    "wof:name":"Morpheus",
    "wof:placetype":"venue"
},
  "geometry": {"coordinates":[5.208176,52.129391],"type":"Point"}
}