{
  "type": "Feature",
  "properties": {
    "addr:full":"Gregoriussngl 26 S Hertogenbosch North Brabant 5216 GJ",
    "addr:housenumber":"26",
    "addr:postcode":"5216 gj",
    "addr:street":"Gregoriussngl;S Hertogenbosch",
    "iso:country":"NL",
    "sg:address":"Gregoriussngl 26",
    "sg:city":"S Hertogenbosch",
    "sg:orig_category":"Verzekerings- Maatschappijen",
    "sg:phone":"+31 73 614 3063",
    "sg:postcode":"5216 GJ",
    "sg:province":"North Brabant",
    "wof:name":"Wulp, Van Der",
    "wof:placetype":"venue"
},
  "geometry": {"coordinates":[5.311607,51.684097],"type":"Point"}
}