{
  "type": "Feature",
  "properties": {
    "addr:full":"Evert Van De Beekstraat 32 Schiphol Noord-Holland 1118 CL",
    "addr:housenumber":"32",
    "addr:postcode":"1118",
    "addr:street":"Evert Van De Beekstraat",
    "iso:country":"NL",
    "sg:address":"Evert Van De Beekstraat 32",
    "sg:city":"Schiphol",
    "sg:orig_category":"Werving And Selectie Van Tijdelijk Personeel And Uitzendkantoren",
    "sg:phone":"+31 20 406 7990",
    "sg:postcode":"1118 CL",
    "sg:province":"Noord-Holland",
    "wof:name":"Uitzendbureau De Werkstudent",
    "wof:placetype":"venue"
},
  "geometry": {"coordinates":[4.7652602196,52.2931518555],"type":"Point"}
}