{
  "type": "Feature",
  "properties": {
    "addr:full":"Vd Berghstr 10 Maastricht Limburg 6221 XC",
    "addr:housenumber":"10",
    "addr:postcode":"6221 xc",
    "iso:country":"NL",
    "sg:address":"Vd Berghstr 10",
    "sg:city":"Maastricht",
    "sg:orig_category":"Kappers",
    "sg:phone":"+31 43 321 9253",
    "sg:postcode":"6221 XC",
    "sg:province":"Limburg",
    "wof:name":"Cornie",
    "wof:placetype":"venue"
},
  "geometry": {"coordinates":[5.702009201,50.8527603149],"type":"Point"}
}