{
  "type": "Feature",
  "properties": {
    "addr:full":"Arendln 19 Tilburg North Brabant 5022 AS",
    "addr:housenumber":"19",
    "addr:postcode":"5022 as",
    "addr:street":"Arendln",
    "iso:country":"NL",
    "sg:address":"Arendln 19",
    "sg:city":"Tilburg",
    "sg:orig_category":"Kappers",
    "sg:phone":"+31 13 536 3585",
    "sg:postcode":"5022 AS",
    "sg:province":"North Brabant",
    "wof:name":"Adriaansen, Joke",
    "wof:placetype":"venue"
},
  "geometry": {"coordinates":[5.098429203,51.5436897278],"type":"Point"}
}