{
  "type": "Feature",
  "properties": {
    "addr:full":"Ettensewg 78 Roosendaal North Brabant 4706 PB",
    "addr:housenumber":"78",
    "addr:postcode":"4706 pb",
    "addr:street":"Ettensewg",
    "iso:country":"NL",
    "sg:address":"Ettensewg 78",
    "sg:city":"Roosendaal",
    "sg:orig_category":"Oud Metaal",
    "sg:phone":"+31 165 540 713",
    "sg:postcode":"4706 PB",
    "sg:province":"North Brabant",
    "wof:name":"Mol, G C",
    "wof:placetype":"venue"
},
  "geometry": {"coordinates":[4.5048727989,51.5427322388],"type":"Point"}
}