{
  "type": "Feature",
  "properties": {
    "iso:country":"NL",
    "sg:address":"J Reviusstr 14",
    "sg:city":"Raalte",
    "sg:orig_category":"Verenigingen En Stichtingen",
    "sg:phone":"+31 572 360 560",
    "sg:postcode":"8101 ZT",
    "sg:province":"NL.08",
    "wof:name":"Somalische Gemeenschap Raalte, Sticht",
    "wof:placetype":"venue"
},
  "geometry": {"coordinates":[6.269575,52.378834],"type":"Point"}
}