{
  "type": "Feature",
  "properties": {
    "addr:full":"Raedeckerplantsoen 13 Nieuwegein Utrecht 3431 BX",
    "addr:housenumber":"13",
    "addr:postcode":"3431 bx",
    "addr:street":"Raedeckerplantsoen",
    "iso:country":"NL",
    "sg:address":"Raedeckerplantsoen 13",
    "sg:city":"Nieuwegein",
    "sg:classifiers":[
        {
            "category":"Fast Food",
            "type":"Food & Drink"
        }
    ],
    "sg:phone":"+31 30 604 7565",
    "sg:postcode":"3431 BX",
    "sg:province":"Utrecht",
    "sg:tags":[
        "afhaal",
        "restaurant"
    ],
    "wof:name":"J Jansen",
    "wof:placetype":"venue"
},
  "geometry": {"coordinates":[5.083195,52.032185],"type":"Point"}
}