{
  "type": "Feature",
  "properties": {
    "addr:full":"J Pompevliet 32A Barendrecht South Holland 2992 WP",
    "addr:housenumber":"32a",
    "addr:postcode":"2992 wp",
    "addr:street":"Pompevliet",
    "iso:country":"NL",
    "sg:address":"J Pompevliet 32A",
    "sg:city":"Barendrecht",
    "sg:orig_category":"Artsen - Huisartsen",
    "sg:phone":"+31 180 618 672",
    "sg:postcode":"2992 WP",
    "sg:province":"South Holland",
    "wof:name":"Pijpers, W",
    "wof:placetype":"venue"
},
  "geometry": {"coordinates":[4.533799,51.851013],"type":"Point"}
}