{
  "type": "Feature",
  "properties": {
    "addr:full":"Andries Veenstrastraat 9 Wolvega Provincie Friesland 8471 AW",
    "addr:housenumber":"9",
    "addr:postcode":"8471 aw",
    "addr:street":"Andries Veenstrastraat;Provincie Friesland",
    "iso:country":"NL",
    "sg:address":"Andries Veenstrastraat 9",
    "sg:city":"Wolvega",
    "sg:orig_category":"Diverse Opleidingen And Onderwijs",
    "sg:phone":"+31 561 617 958",
    "sg:postcode":"8471 AW",
    "sg:province":"Provincie Friesland",
    "wof:name":"H J Westerhof",
    "wof:placetype":"venue"
},
  "geometry": {"coordinates":[6.002466,52.87907],"type":"Point"}
}