{
  "type": "Feature",
  "properties": {
    "addr:full":"Wykeroogstr 196 Velsen Noord North Holland 1951 AG",
    "addr:housenumber":"196",
    "addr:postcode":"1951",
    "addr:street":"Velsen Noord North",
    "iso:country":"NL",
    "sg:address":"Wykeroogstr 196",
    "sg:city":"Velsen Noord",
    "sg:orig_category":"Levensmiddelen - Fabrieken En Groothandel",
    "sg:phone":"+31 251 224 089",
    "sg:postcode":"1951 AG",
    "sg:province":"North Holland",
    "wof:name":"Westerbaan Van Der Meij, Fa",
    "wof:placetype":"venue"
},
  "geometry": {"coordinates":[4.649442,52.470013],"type":"Point"}
}