{
  "type": "Feature",
  "properties": {
    "iso:country":"NL",
    "sg:address":"Kon Julianapln 24",
    "sg:city":"Voorburg",
    "sg:orig_category":"Postkantoren",
    "sg:phone":"+31 70 387 7189",
    "sg:postcode":"2273 BR",
    "sg:province":"Zuid-Holland",
    "sg:website":"http://www.postkantoor.nl",
    "wof:name":"Postkantoor",
    "wof:placetype":"venue"
},
  "geometry": {"coordinates":[4.358183,52.076199],"type":"Point"}
}