{
  "type": "Feature",
  "properties": {
    "iso:country":"NL",
    "sg:address":"Hengelolaan 399",
    "sg:city":"'S Gravenhage",
    "sg:orig_category":"Verlichting And Huishoudartikelen",
    "sg:phone":"+31 70 367 6372",
    "sg:postcode":"2545 JN",
    "sg:province":"Zuid-Holland",
    "wof:name":"G.J. Interieur",
    "wof:placetype":"venue"
},
  "geometry": {"coordinates":[4.268524,52.047989],"type":"Point"}
}