{
  "type": "Feature",
  "properties": {
    "iso:country":"NL",
    "sg:address":"Radermacherstraat 32",
    "sg:city":"Arnemuiden",
    "sg:orig_category":"Overheidsdiensten",
    "sg:phone":"+31 118 601 447",
    "sg:postcode":"4341 GX",
    "sg:province":"Zeeland",
    "wof:name":"Buffet Dorpshuis De Arne",
    "wof:placetype":"venue"
},
  "geometry": {"coordinates":[3.6784029007,51.5007324219],"type":"Point"}
}