{
  "type": "Feature",
  "properties": {
    "addr:full":"Hervenpln 2 S Hertogenbosch North Brabant 5232 JE",
    "addr:housenumber":"2",
    "addr:postcode":"5232 je",
    "addr:street":"Hervenpln",
    "iso:country":"NL",
    "sg:address":"Hervenpln 2",
    "sg:city":"S Hertogenbosch",
    "sg:orig_category":"Hypotheken",
    "sg:phone":"+31 73 646 8000",
    "sg:postcode":"5232 JE",
    "sg:province":"North Brabant",
    "sg:website":"http://www.woonfonds.nl",
    "wof:name":"Woonfonds",
    "wof:placetype":"venue"
},
  "geometry": {"coordinates":[5.321278,51.702194],"type":"Point"}
}