{
  "type": "Feature",
  "properties": {
    "iso:country":"NL",
    "sg:address":"Acaciastraat 178",
    "sg:city":"'S Gravenhage",
    "sg:orig_category":"Overheidsdiensten",
    "sg:phone":"+31 70 363 5300",
    "sg:postcode":"2565 KH",
    "sg:province":"Zuid-Holland",
    "wof:name":"De Kruin",
    "wof:placetype":"venue"
},
  "geometry": {"coordinates":[4.2707090378,52.076965332],"type":"Point"}
}