{
  "type": "Feature",
  "properties": {
    "addr:full":"W Bruinstr 89 Almere Flevoland 1333 JX",
    "addr:housenumber":"89",
    "addr:postcode":"1333 jx",
    "addr:street":"W;Flevoland",
    "iso:country":"NL",
    "sg:address":"W Bruinstr 89",
    "sg:city":"Almere",
    "sg:orig_category":"Webdesign Bureaus",
    "sg:phone":"+31 36 529 1090",
    "sg:postcode":"1333 JX",
    "sg:province":"Flevoland",
    "sg:website":"http://www.inaksi.nl",
    "wof:name":"Inaksi",
    "wof:placetype":"venue"
},
  "geometry": {"coordinates":[5.2588739395,52.3952293396],"type":"Point"}
}