{
  "type": "Feature",
  "properties": {
    "addr:full":"Jesuitenstraat 9 Roermond Limburg 6041 ED",
    "addr:housenumber":"9",
    "addr:postcode":"6041 ed",
    "addr:street":"Jesuitenstraat",
    "iso:country":"NL",
    "sg:address":"Jesuitenstraat 9",
    "sg:city":"Roermond",
    "sg:orig_category":"Fitnesscentra",
    "sg:phone":"+31 475 336 206",
    "sg:postcode":"6041 ED",
    "sg:province":"Limburg",
    "wof:name":"Bodywork",
    "wof:placetype":"venue"
},
  "geometry": {"coordinates":[5.987095,51.195518],"type":"Point"}
}