{
  "type": "Feature",
  "properties": {
    "addr:full":"Meidoorn 25 Zeewolde NL. 3892 CJ",
    "addr:housenumber":"25",
    "addr:postcode":"3892 cj",
    "addr:street":"Meidoorn;Nl.",
    "iso:country":"NL",
    "sg:address":"Meidoorn 25",
    "sg:city":"Zeewolde",
    "sg:orig_category":"Boekhouders",
    "sg:phone":"+31 36 522 3215",
    "sg:postcode":"3892 CJ",
    "sg:province":"NL.",
    "wof:name":"H. De Jong Administratie-, Adviesburo",
    "wof:placetype":"venue"
},
  "geometry": {"coordinates":[5.535769,52.326141],"type":"Point"}
}