{
  "type": "Feature",
  "properties": {
    "addr:full":"Einsteinstr 23 Reeuwyk Zuid-Holland 2811 EP",
    "addr:housenumber":"23",
    "addr:postcode":"2811 ep",
    "addr:street":"Einsteinstr",
    "iso:country":"NL",
    "sg:address":"Einsteinstr 23",
    "sg:city":"Reeuwyk",
    "sg:classifiers":[
        {
            "category":"Retail",
            "subcategory":"Auto Repair",
            "type":"Services"
        }
    ],
    "sg:phone":"+31 182 394 052",
    "sg:postcode":"2811 EP",
    "sg:province":"Zuid-Holland",
    "sg:tags":[
        "garage"
    ],
    "sg:website":"http://www.ruton.nl",
    "wof:name":"Ruton",
    "wof:placetype":"venue"
},
  "geometry": {"coordinates":[4.718239,52.03968],"type":"Point"}
}