{
  "type": "Feature",
  "properties": {
    "iso:country":"NL",
    "sg:address":"Maastrichter Brugstraat 3",
    "sg:city":"Maastricht",
    "sg:orig_category":"Wasserettes And Stomerijen",
    "sg:phone":"+31 43 321 3340",
    "sg:postcode":"6211 ES",
    "sg:province":"Limburg",
    "wof:name":"Palthe Stomerijen Bv",
    "wof:placetype":"venue"
},
  "geometry": {"coordinates":[5.694062233,50.8492431641],"type":"Point"}
}