{
  "type": "Feature",
  "properties": {
    "addr:full":"Elzerdijk 7 Eefde Gelderland 7211 LV",
    "addr:housenumber":"7",
    "addr:postcode":"7211",
    "addr:street":"Elzerdijk;Gelderland",
    "iso:country":"NL",
    "sg:address":"Elzerdijk 7",
    "sg:city":"Eefde",
    "sg:orig_category":"Meubelzaken, Woning- And Keukeninrichting",
    "sg:phone":"+31 575 541 438",
    "sg:postcode":"7211 LV",
    "sg:province":"Gelderland",
    "wof:name":"Fa. Gebr. B.J. Rouwenhorst Meubelmakers",
    "wof:placetype":"venue"
},
  "geometry": {"coordinates":[6.249569,52.176453],"type":"Point"}
}