{
  "type": "Feature",
  "properties": {
    "addr:full":"Gronsveldstraat 22 Arnhem Gelderland 6845 HH",
    "addr:housenumber":"22",
    "addr:postcode":"6845 hh",
    "addr:street":"Gronsveldstraat",
    "iso:country":"NL",
    "sg:address":"Gronsveldstraat 22",
    "sg:city":"Arnhem",
    "sg:orig_category":"Organisaties And Verenigingen",
    "sg:phone":"+31 26 381 7166",
    "sg:postcode":"6845 HH",
    "sg:province":"Gelderland",
    "wof:name":"Studentenvereniging Infacta-Newstyle",
    "wof:placetype":"venue"
},
  "geometry": {"coordinates":[5.8729219437,51.9494056702],"type":"Point"}
}