{
  "type": "Feature",
  "properties": {
    "addr:full":"Postelstraat 23 Someren Noord-Brabant 5711 EM",
    "addr:housenumber":"23",
    "addr:postcode":"5711 em",
    "addr:street":"Postelstraat",
    "iso:country":"NL",
    "sg:address":"Postelstraat 23",
    "sg:city":"Someren",
    "sg:orig_category":"Discountwinkels",
    "sg:phone":"+31 493 495 310",
    "sg:postcode":"5711 EM",
    "sg:province":"Noord-Brabant",
    "wof:name":"De Postelsjop",
    "wof:placetype":"venue"
},
  "geometry": {"coordinates":[5.711387,51.384361],"type":"Point"}
}