{
  "type": "Feature",
  "properties": {
    "addr:full":"Binnenwg 71 Ellecom Gelderland 6955 AW",
    "addr:housenumber":"71",
    "addr:postcode":"6955 aw",
    "addr:street":"Binnenwg;Gelderland",
    "iso:country":"NL",
    "sg:address":"Binnenwg 71",
    "sg:city":"Ellecom",
    "sg:orig_category":"Verenigingsgebouwen",
    "sg:phone":"+31 313 414 705",
    "sg:postcode":"6955 AW",
    "sg:province":"Gelderland",
    "wof:name":"Binnenhof, 'T",
    "wof:placetype":"venue"
},
  "geometry": {"coordinates":[6.092262,52.033714],"type":"Point"}
}