{
  "type": "Feature",
  "properties": {
    "iso:country":"NL",
    "sg:address":"Weidehek 73A",
    "sg:city":"Breda",
    "sg:orig_category":"Verlichtingsartikelen - Groothandel",
    "sg:phone":"+31 76 541 9901",
    "sg:postcode":"4824 AT",
    "sg:province":"Noord-Brabant",
    "sg:website":"http://www.d-lighted.nl",
    "wof:name":"D-Lighted",
    "wof:placetype":"venue"
},
  "geometry": {"coordinates":[4.758892,51.616035],"type":"Point"}
}