{
  "type": "Feature",
  "properties": {
    "addr:full":"Beekstr 34 Meerssen Limburg 6231 LG",
    "addr:housenumber":"34",
    "addr:postcode":"6231 lg",
    "addr:street":"Beekstr",
    "iso:country":"NL",
    "sg:address":"Beekstr 34",
    "sg:city":"Meerssen",
    "sg:orig_category":"Artsen - Huisartsen",
    "sg:phone":"+31 43 364 2215",
    "sg:postcode":"6231 LG",
    "sg:province":"Limburg",
    "wof:name":"Erp Van, Th J J M",
    "wof:placetype":"venue"
},
  "geometry": {"coordinates":[5.75503,50.885017],"type":"Point"}
}