{
  "type": "Feature",
  "properties": {
    "addr:full":"Tonnendk 90 Vroomshoop Overijssel 7681 BR",
    "addr:housenumber":"90",
    "addr:postcode":"7681 br",
    "addr:street":"Tonnendk",
    "iso:country":"NL",
    "sg:address":"Tonnendk 90",
    "sg:city":"Vroomshoop",
    "sg:orig_category":"Bestratingen",
    "sg:phone":"+31 546 643 902",
    "sg:postcode":"7681 BR",
    "sg:province":"Overijssel",
    "wof:name":"Makkinga Bv",
    "wof:placetype":"venue"
},
  "geometry": {"coordinates":[6.581378,52.462784],"type":"Point"}
}