{
  "type": "Feature",
  "properties": {
    "addr:full":"Argonautenstr 13 Amsterdam North Holland 1076 KJ",
    "addr:housenumber":"13",
    "addr:postcode":"1076 kj",
    "addr:street":"Argonautenstr",
    "iso:country":"NL",
    "sg:address":"Argonautenstr 13",
    "sg:city":"Amsterdam",
    "sg:orig_category":"Verenigingsgebouwen",
    "sg:phone":"+31 20 679 6017",
    "sg:postcode":"1076 KJ",
    "sg:province":"North Holland",
    "wof:name":"Argo, De",
    "wof:placetype":"venue"
},
  "geometry": {"coordinates":[4.862067,52.343761],"type":"Point"}
}