{
  "type": "Feature",
  "properties": {
    "addr:full":"Vyverberg 24 Rhenen Utrecht 3911 JP",
    "addr:housenumber":"24",
    "addr:postcode":"3911 jp",
    "addr:street":"Vyverberg",
    "iso:country":"NL",
    "sg:address":"Vyverberg 24",
    "sg:city":"Rhenen",
    "sg:orig_category":"Kappers",
    "sg:phone":"+31 317 617 008",
    "sg:postcode":"3911 JP",
    "sg:province":"Utrecht",
    "wof:name":"Karin Van Osch",
    "wof:placetype":"venue"
},
  "geometry": {"coordinates":[5.5605568886,51.9643211365],"type":"Point"}
}