{
  "type": "Feature",
  "properties": {
    "iso:country":"NL",
    "sg:address":"De Maraboe 26",
    "sg:city":"Almelo",
    "sg:orig_category":"Kappers",
    "sg:phone":"+31 546 827 750",
    "sg:postcode":"7609 GW",
    "sg:province":"NL.08",
    "wof:name":"Linda'S",
    "wof:placetype":"venue"
},
  "geometry": {"coordinates":[6.634715,52.33313],"type":"Point"}
}