{
  "type": "Feature",
  "properties": {
    "addr:full":"De Maraboe 26 Almelo NL.08 7609 GW",
    "addr:housenumber":"26;nl.08",
    "addr:postcode":"7609 gw",
    "addr:street":"De Maraboe",
    "iso:country":"NL",
    "sg:address":"De Maraboe 26",
    "sg:city":"Almelo",
    "sg:orig_category":"Kappers",
    "sg:phone":"+31 546 827 750",
    "sg:postcode":"7609 GW",
    "sg:province":"NL.08",
    "wof:name":"Linda'S",
    "wof:placetype":"venue"
},
  "geometry": {"coordinates":[6.634715,52.33313],"type":"Point"}
}