{
  "type": "Feature",
  "properties": {
    "addr:full":"1E Hogeweg 11-13 Zeist Utrecht 3701 HG",
    "addr:housenumber":"11-13",
    "addr:postcode":"3701 hg",
    "addr:street":"1E Hogeweg",
    "iso:country":"NL",
    "sg:address":"1E Hogeweg 11-13",
    "sg:city":"Zeist",
    "sg:orig_category":"Kledingaccessoires",
    "sg:phone":"+31 30 693 3089",
    "sg:postcode":"3701 HG",
    "sg:province":"Utrecht",
    "wof:name":"Sock & Panty Shop",
    "wof:placetype":"venue"
},
  "geometry": {"coordinates":[5.240352,52.085983],"type":"Point"}
}