{
  "type": "Feature",
  "properties": {
    "iso:country":"NL",
    "sg:address":"Nw Dorpswg 31",
    "sg:city":"Fynaart",
    "sg:orig_category":"Verbouwingen",
    "sg:phone":"+31 168 462 477",
    "sg:postcode":"4793 BR",
    "sg:province":"Noord-Brabant",
    "wof:name":"Pex Multi Services",
    "wof:placetype":"venue"
},
  "geometry": {"coordinates":[4.494492,51.660118],"type":"Point"}
}