{
  "type": "Feature",
  "properties": {
    "iso:country":"NL",
    "sg:address":"Wilhelminastraat 63",
    "sg:city":"Asten",
    "sg:orig_category":"Vertaal- And Tolkenbureaus",
    "sg:phone":"+31 493 692 548",
    "sg:postcode":"5721 KH",
    "sg:province":"Noord-Brabant",
    "wof:name":"Dilemma Vertaalbureau",
    "wof:placetype":"venue"
},
  "geometry": {"coordinates":[5.739012,51.399189],"type":"Point"}
}