{
  "type": "Feature",
  "properties": {
    "addr:full":"De Lasso 35A Roelofarendsveen Zuid-Holland 2371 GW",
    "addr:housenumber":"35a",
    "addr:postcode":"2371 gw",
    "addr:street":"De Lasso",
    "iso:country":"NL",
    "sg:address":"De Lasso 35A",
    "sg:city":"Roelofarendsveen",
    "sg:orig_category":"Kantoor- En Secretariaatsservice",
    "sg:phone":"+31 71 331 1726",
    "sg:postcode":"2371 GW",
    "sg:province":"Zuid-Holland",
    "sg:website":"http://www.artifexsupport.com",
    "wof:name":"Artifex Support",
    "wof:placetype":"venue"
},
  "geometry": {"coordinates":[4.6239700317,52.2062644958],"type":"Point"}
}