{
  "type": "Feature",
  "properties": {
    "iso:country":"NL",
    "sg:address":"Hinthamereinde 72-74",
    "sg:city":"S Hertogenbosch",
    "sg:orig_category":"Hulpverlening Sociaal",
    "sg:phone":"+31 73 614 8550",
    "sg:postcode":"5211 PP",
    "sg:province":"Noord-Brabant",
    "wof:name":"Vicki Brown Huis",
    "wof:placetype":"venue"
},
  "geometry": {"coordinates":[5.315746,51.690311],"type":"Point"}
}