{
  "type": "Feature",
  "properties": {
    "addr:full":"Concordialn 139J Etten Leur Noord-Brabant 4871 ZA",
    "addr:housenumber":"139j",
    "addr:postcode":"4871",
    "addr:street":"Concordialn",
    "iso:country":"NL",
    "sg:address":"Concordialn 139J",
    "sg:city":"Etten Leur",
    "sg:orig_category":"Administratie- En Boekhoudkantoren",
    "sg:phone":"+31 76 542 2711",
    "sg:postcode":"4871 ZA",
    "sg:province":"Noord-Brabant",
    "wof:name":"Eeb",
    "wof:placetype":"venue"
},
  "geometry": {"coordinates":[4.637666,51.578671],"type":"Point"}
}