{
  "type": "Feature",
  "properties": {
    "addr:full":"De Esdoorn 32 Zevenhuizen Zh Zuid-Holland 2761 TW",
    "addr:housenumber":"32",
    "addr:postcode":"2761 tw",
    "addr:street":"De Esdoorn",
    "iso:country":"NL",
    "sg:address":"De Esdoorn 32",
    "sg:city":"Zevenhuizen Zh",
    "sg:orig_category":"Keukens",
    "sg:phone":"+31 180 631 601",
    "sg:postcode":"2761 TW",
    "sg:province":"Zuid-Holland",
    "wof:name":"Polder, H",
    "wof:placetype":"venue"
},
  "geometry": {"coordinates":[4.578827,52.006954],"type":"Point"}
}