{
  "type": "Feature",
  "properties": {
    "addr:full":"Berlage-Erf 17 Dordrecht Zuid-Holland 3315 JJ",
    "addr:housenumber":"17",
    "addr:postcode":"3315 jj",
    "addr:street":"Berlage-Erf",
    "iso:country":"NL",
    "sg:address":"Berlage-Erf 17",
    "sg:city":"Dordrecht",
    "sg:orig_category":"Muziekinstrumenten",
    "sg:phone":"+31 78 616 6139",
    "sg:postcode":"3315 JJ",
    "sg:province":"Zuid-Holland",
    "wof:name":"G.M.C. Gospel Music Centre Dordrecht",
    "wof:placetype":"venue"
},
  "geometry": {"coordinates":[4.723246,51.803982],"type":"Point"}
}