{
  "type": "Feature",
  "properties": {
    "addr:full":"1E Loosterwg 1C Hillegom Zuid-Holland 2182 BL",
    "addr:housenumber":"1c",
    "addr:postcode":"2182 bl",
    "addr:street":"1E Loosterwg",
    "iso:country":"NL",
    "sg:address":"1E Loosterwg 1C",
    "sg:city":"Hillegom",
    "sg:orig_category":"Bloemen En Planten - Groothandel",
    "sg:phone":"+31 252 529 715",
    "sg:postcode":"2182 BL",
    "sg:province":"Zuid-Holland",
    "wof:name":"Hachmang & Maas Vof",
    "wof:placetype":"venue"
},
  "geometry": {"coordinates":[4.566981,52.303818],"type":"Point"}
}