{
  "type": "Feature",
  "properties": {
    "iso:country":"NL",
    "sg:address":"Lekdk W 55",
    "sg:city":"Lopik",
    "sg:orig_category":"Loonbedrijven",
    "sg:phone":"+31 182 383 891",
    "sg:postcode":"3411 MX",
    "sg:province":"South Holland",
    "wof:name":"Haay & Zn, C De",
    "wof:placetype":"venue"
},
  "geometry": {"coordinates":[4.880188,51.941326],"type":"Point"}
}