{
  "type": "Feature",
  "properties": {
    "addr:full":"Lekdk W 55 Lopik South Holland 3411 MX",
    "addr:housenumber":"55",
    "addr:postcode":"3411 mx",
    "addr:street":"W",
    "iso:country":"NL",
    "sg:address":"Lekdk W 55",
    "sg:city":"Lopik",
    "sg:orig_category":"Loonbedrijven",
    "sg:phone":"+31 182 383 891",
    "sg:postcode":"3411 MX",
    "sg:province":"South Holland",
    "wof:name":"Haay & Zn, C De",
    "wof:placetype":"venue"
},
  "geometry": {"coordinates":[4.880188,51.941326],"type":"Point"}
}