{
  "type": "Feature",
  "properties": {
    "addr:full":"Mollevite 15 Westervoort Gelderland 6931 KE",
    "addr:housenumber":"15",
    "addr:postcode":"6931 ke",
    "addr:street":"Mollevite;Gelderland",
    "iso:country":"NL",
    "sg:address":"Mollevite 15",
    "sg:city":"Westervoort",
    "sg:orig_category":"Facilitaire Dienstverlening",
    "sg:phone":"+31 26 311 4969",
    "sg:postcode":"6931 KE",
    "sg:province":"Gelderland",
    "wof:name":"Hartman Bv",
    "wof:placetype":"venue"
},
  "geometry": {"coordinates":[5.981281,51.959518],"type":"Point"}
}