{
  "type": "Feature",
  "properties": {
    "iso:country":"NL",
    "sg:address":"Stockholmstr 3",
    "sg:city":"Groningen",
    "sg:orig_category":"Jachthavens - Jachtwerven",
    "sg:phone":"+31 50 311 7711",
    "sg:postcode":"9723 BC",
    "sg:province":"Groningen",
    "wof:name":"Veha Bv",
    "wof:placetype":"venue"
},
  "geometry": {"coordinates":[6.595545,53.215889],"type":"Point"}
}