{
  "type": "Feature",
  "properties": {
    "addr:full":"Stockholmstr 3 Groningen Groningen 9723 BC",
    "addr:housenumber":"3",
    "addr:postcode":"9723 bc",
    "addr:street":"Stockholmstr",
    "iso:country":"NL",
    "sg:address":"Stockholmstr 3",
    "sg:city":"Groningen",
    "sg:orig_category":"Jachthavens - Jachtwerven",
    "sg:phone":"+31 50 311 7711",
    "sg:postcode":"9723 BC",
    "sg:province":"Groningen",
    "wof:name":"Veha Bv",
    "wof:placetype":"venue"
},
  "geometry": {"coordinates":[6.595545,53.215889],"type":"Point"}
}