{
  "type": "Feature",
  "properties": {
    "addr:full":"Dorpsstraat 1 Elim Drenthe 7916 PA",
    "addr:housenumber":"1",
    "addr:postcode":"7916 pa",
    "addr:street":"Dorpsstraat",
    "iso:country":"NL",
    "sg:address":"Dorpsstraat 1",
    "sg:city":"Elim",
    "sg:orig_category":"Verlichting And Huishoudartikelen",
    "sg:phone":"+31 528 351 433",
    "sg:postcode":"7916 PA",
    "sg:province":"Drenthe",
    "wof:name":"Hobby En Geschenkenhuis Zomer",
    "wof:placetype":"venue"
},
  "geometry": {"coordinates":[-162.25607299999999,64.61582900000001],"type":"Point"}
}