{
  "type": "Feature",
  "properties": {
    "addr:full":"Paterswoldsewg 448 Groningen Groningen 9728 BB",
    "addr:housenumber":"448",
    "addr:postcode":"9728 bb",
    "iso:country":"NL",
    "sg:address":"Paterswoldsewg 448",
    "sg:city":"Groningen",
    "sg:orig_category":"Kappers",
    "sg:phone":"+31 50 525 1692",
    "sg:postcode":"9728 BB",
    "sg:province":"Groningen",
    "wof:name":"Jurink",
    "wof:placetype":"venue"
},
  "geometry": {"coordinates":[6.559896946,53.2006187439],"type":"Point"}
}