{
  "type": "Feature",
  "properties": {
    "addr:full":"Zassenkamp 1 Bennekom Gelderland 6721 AK",
    "addr:housenumber":"1",
    "addr:postcode":"6721 ak",
    "addr:street":"Zassenkamp;Gelderland",
    "iso:country":"NL",
    "sg:address":"Zassenkamp 1",
    "sg:city":"Bennekom",
    "sg:orig_category":"Adviesbureaus Bedrijfsorganisatie",
    "sg:phone":"+31 318 415 495",
    "sg:postcode":"6721 AK",
    "sg:province":"Gelderland",
    "wof:name":"Org-Adviesbur Voor Acc- En Administratiekantoren",
    "wof:placetype":"venue"
},
  "geometry": {"coordinates":[5.685819,51.997589],"type":"Point"}
}