{
  "type": "Feature",
  "properties": {
    "iso:country":"NL",
    "sg:address":"De Heugden 94",
    "sg:city":"Heerlen",
    "sg:orig_category":"Artiesten/Gezelschappen",
    "sg:phone":"+31 45 571 0016",
    "sg:postcode":"6411 DN",
    "sg:province":"Limburg",
    "wof:name":"Majcherek, B",
    "wof:placetype":"venue"
},
  "geometry": {"coordinates":[5.971052,50.889874],"type":"Point"}
}