{
  "type": "Feature",
  "properties": {
    "addr:full":"Grt Leyen 37 Appelscha Friesland 8426 JD",
    "addr:housenumber":"37",
    "addr:postcode":"8426 jd",
    "addr:street":"Leyen",
    "iso:country":"NL",
    "sg:address":"Grt Leyen 37",
    "sg:city":"Appelscha",
    "sg:orig_category":"Voetbalverenigingen",
    "sg:phone":"+31 516 433 261",
    "sg:postcode":"8426 JD",
    "sg:province":"Friesland",
    "wof:name":"St\u00e2nfries",
    "wof:placetype":"venue"
},
  "geometry": {"coordinates":[6.366119,52.952129],"type":"Point"}
}