{
  "type": "Feature",
  "properties": {
    "addr:full":"Noord 98 Franeker Provincie Friesland 8801 KS",
    "addr:housenumber":"98",
    "addr:postcode":"8801 ks",
    "addr:street":"Noord;Provincie Friesland",
    "iso:country":"NL",
    "sg:address":"Noord 98",
    "sg:city":"Franeker",
    "sg:orig_category":"Postzegels",
    "sg:phone":"+31 517 390 600",
    "sg:postcode":"8801 KS",
    "sg:province":"Provincie Friesland",
    "sg:website":"http://www.tinga.nl",
    "wof:name":"Tinga",
    "wof:placetype":"venue"
},
  "geometry": {"coordinates":[5.539983,53.187881],"type":"Point"}
}