{
  "type": "Feature",
  "properties": {
    "addr:full":"De Schacht 15 Dongen North Brabant 5107 RD",
    "addr:housenumber":"15",
    "addr:postcode":"5107 rd",
    "addr:street":"De Schacht",
    "iso:country":"NL",
    "sg:address":"De Schacht 15",
    "sg:city":"Dongen",
    "sg:orig_category":"Elektriciens",
    "sg:phone":"+31 162 312 822",
    "sg:postcode":"5107 RD",
    "sg:province":"North Brabant",
    "wof:name":"Chr. Van Wanrooij",
    "wof:placetype":"venue"
},
  "geometry": {"coordinates":[4.928349,51.614437],"type":"Point"}
}