{
  "type": "Feature",
  "properties": {
    "addr:full":"Tulpstraat 13 'S Gravenzande Zuid-Holland 2691 LN",
    "addr:housenumber":"13",
    "addr:postcode":"2691 ln",
    "addr:street":"Tulpstraat;' S",
    "iso:country":"NL",
    "sg:address":"Tulpstraat 13",
    "sg:city":"'S Gravenzande",
    "sg:orig_category":"Glaszetten",
    "sg:phone":"+31 174 419 044",
    "sg:postcode":"2691 LN",
    "sg:province":"Zuid-Holland",
    "wof:name":"Gebrs. M. & E. De Jong",
    "wof:placetype":"venue"
},
  "geometry": {"coordinates":[4.180996,51.982098],"type":"Point"}
}