{
  "type": "Feature",
  "properties": {
    "addr:full":"Paul Gabrielstraat 19 Deurne Noord-Brabant 5753 DG",
    "addr:housenumber":"19",
    "addr:postcode":"5753 dg",
    "addr:street":"Gabrielstraat",
    "iso:country":"NL",
    "sg:address":"Paul Gabrielstraat 19",
    "sg:city":"Deurne",
    "sg:orig_category":"Zuivelproducten And Spijsoli?n Gh",
    "sg:phone":"+31 493 311 972",
    "sg:postcode":"5753 DG",
    "sg:province":"Noord-Brabant",
    "wof:name":"Kaashandel Cor Segers Bv",
    "wof:placetype":"venue"
},
  "geometry": {"coordinates":[5.794685,51.452095],"type":"Point"}
}