{
  "type": "Feature",
  "properties": {
    "addr:full":"Delftweg 230 Rotterdam South Holland 3046 ND",
    "addr:housenumber":"230",
    "addr:postcode":"3046 nd",
    "addr:street":"Delftweg",
    "iso:country":"NL",
    "sg:address":"Delftweg 230",
    "sg:city":"Rotterdam",
    "sg:orig_category":"Begrafenisondernemers",
    "sg:phone":"+31 10 471 2055",
    "sg:postcode":"3046 ND",
    "sg:province":"South Holland",
    "wof:name":"Crematorium Hofwijk",
    "wof:placetype":"venue"
},
  "geometry": {"coordinates":[4.399046,51.956966],"type":"Point"}
}