{
  "type": "Feature",
  "properties": {
    "addr:full":"Sint Annadal 12 Maastricht Limburg 6214 PA",
    "addr:housenumber":"12",
    "addr:postcode":"6214 pa",
    "addr:street":"Sint Annadal",
    "iso:country":"NL",
    "sg:address":"Sint Annadal 12",
    "sg:city":"Maastricht",
    "sg:orig_category":"Paramedische Behandelingen",
    "sg:phone":"+31 43 347 8817",
    "sg:postcode":"6214 PA",
    "sg:province":"Limburg",
    "wof:name":"E.A. Bielders",
    "wof:placetype":"venue"
},
  "geometry": {"coordinates":[5.672809,50.848541],"type":"Point"}
}