{
  "type": "Feature",
  "properties": {
    "iso:country":"NL",
    "sg:address":"R F Wyffelsstr 20",
    "sg:city":"Waspik",
    "sg:orig_category":"Goud En Zilver",
    "sg:phone":"+31 416 311 152",
    "sg:postcode":"5165 EP",
    "sg:province":"Noord-Brabant",
    "wof:name":"Together",
    "wof:placetype":"venue"
},
  "geometry": {"coordinates":[4.944695,51.687012],"type":"Point"}
}