{
  "type": "Feature",
  "properties": {
    "iso:country":"NL",
    "sg:address":"Gruttostraat 33",
    "sg:city":"'S Hertogenbosch",
    "sg:orig_category":"Huishoudapparatuur, Televisies And Radio'S",
    "sg:phone":"+31 73 613 1928",
    "sg:postcode":"5212 VM",
    "sg:province":"Noord-Brabant",
    "wof:name":"Mikro Electro Bv",
    "wof:placetype":"venue"
},
  "geometry": {"coordinates":[5.300913,51.699326],"type":"Point"}
}