{
  "type": "Feature",
  "properties": {
    "addr:full":"Perzikgaard 2 Spijkenisse Zuid-Holland 3206 AL",
    "addr:housenumber":"2",
    "addr:postcode":"3206 al",
    "addr:street":"Perzikgaard",
    "iso:country":"NL",
    "sg:address":"Perzikgaard 2",
    "sg:city":"Spijkenisse",
    "sg:orig_category":"Onderhoud And Reparatie Kantoorapparatuur",
    "sg:phone":"+31 181 687 460",
    "sg:postcode":"3206 AL",
    "sg:province":"Zuid-Holland",
    "wof:name":"Case",
    "wof:placetype":"venue"
},
  "geometry": {"coordinates":[4.33065,51.833092],"type":"Point"}
}