{
  "type": "Feature",
  "properties": {
    "addr:full":"D Stammesstraat 9 Anna Paulowna Noord-Holland 1761 DB",
    "addr:housenumber":"9",
    "addr:postcode":"1761 db",
    "addr:street":"D Stammesstraat",
    "iso:country":"NL",
    "sg:address":"D Stammesstraat 9",
    "sg:city":"Anna Paulowna",
    "sg:orig_category":"Kappers",
    "sg:phone":"+31 223 533 225",
    "sg:postcode":"1761 DB",
    "sg:province":"Noord-Holland",
    "wof:name":"Inge Marttin",
    "wof:placetype":"venue"
},
  "geometry": {"coordinates":[4.8257107735,52.8605537415],"type":"Point"}
}