{
  "type": "Feature",
  "properties": {
    "addr:full":"Raadhuisplein 1 Sint Odilienberg Limburg 6077 AB",
    "addr:housenumber":"1",
    "addr:postcode":"6077 ab",
    "addr:street":"Raadhuisplein;Limburg",
    "iso:country":"NL",
    "sg:address":"Raadhuisplein 1",
    "sg:city":"Sint Odilienberg",
    "sg:orig_category":"Hypotheken And Hypotheekbanken",
    "sg:phone":"+31 475 532 662",
    "sg:postcode":"6077 AB",
    "sg:province":"Limburg",
    "wof:name":"Regionale Hypotheekpartners",
    "wof:placetype":"venue"
},
  "geometry": {"coordinates":[6.000575,51.148037],"type":"Point"}
}