{
  "type": "Feature",
  "properties": {
    "addr:full":"Omloop 8 Stadskanaal Groningen 9502 RJ",
    "addr:housenumber":"8",
    "addr:postcode":"9502 rj",
    "addr:street":"Omloop",
    "iso:country":"NL",
    "sg:address":"Omloop 8",
    "sg:city":"Stadskanaal",
    "sg:orig_category":"Administratie- En Boekhoudkantoren",
    "sg:phone":"+31 599 650 006",
    "sg:postcode":"9502 RJ",
    "sg:province":"Groningen",
    "wof:name":"Bads",
    "wof:placetype":"venue"
},
  "geometry": {"coordinates":[6.97211,52.997261],"type":"Point"}
}