{
  "type": "Feature",
  "properties": {
    "addr:full":"Capelleln 49 Ammerstol Zuid-Holland 2865 AA",
    "addr:housenumber":"49",
    "addr:postcode":"2865 aa",
    "addr:street":"Capelleln",
    "iso:country":"NL",
    "sg:address":"Capelleln 49",
    "sg:city":"Ammerstol",
    "sg:orig_category":"Honden- En Kattentrimsalons",
    "sg:phone":"+31 182 354 172",
    "sg:postcode":"2865 AA",
    "sg:province":"Zuid-Holland",
    "wof:name":"Colinda",
    "wof:placetype":"venue"
},
  "geometry": {"coordinates":[4.80923,51.92757],"type":"Point"}
}