{
  "type": "Feature",
  "properties": {
    "iso:country":"NL",
    "sg:address":"Theerestr 57",
    "sg:city":"St Michielsgestel",
    "sg:orig_category":"Logopedisten",
    "sg:phone":"+31 73 551 2613",
    "sg:postcode":"5271 GB",
    "sg:province":"Noord-Brabant",
    "wof:name":"Lamberts, Drs S I C",
    "wof:placetype":"venue"
},
  "geometry": {"coordinates":[5.344262,51.640717],"type":"Point"}
}