{
  "type": "Feature",
  "properties": {
    "addr:full":"Hazenwg 83 Hengelo Ov Overijssel 7556 BM",
    "addr:housenumber":"83",
    "addr:postcode":"7556 bm",
    "addr:street":"Hazenwg;Ov",
    "iso:country":"NL",
    "sg:address":"Hazenwg 83",
    "sg:city":"Hengelo Ov",
    "sg:orig_category":"Adviesbureaus Bedrijfsorganisatie",
    "sg:phone":"+31 74 250 1414",
    "sg:postcode":"7556 BM",
    "sg:province":"Overijssel",
    "wof:name":"Hdv Bv",
    "wof:placetype":"venue"
},
  "geometry": {"coordinates":[6.779152,52.287304],"type":"Point"}
}