{
  "type": "Feature",
  "properties": {
    "addr:full":"Hoofdstr 143A Zuidwolde Dr Drenthe 7921 AH",
    "addr:housenumber":"143a",
    "addr:postcode":"7921 ah",
    "addr:street":"Zuidwolde Dr",
    "iso:country":"NL",
    "sg:address":"Hoofdstr 143A",
    "sg:city":"Zuidwolde Dr",
    "sg:orig_category":"Autorijscholen",
    "sg:phone":"+31 528 371 462",
    "sg:postcode":"7921 AH",
    "sg:province":"Drenthe",
    "wof:name":"Blokzijl",
    "wof:placetype":"venue"
},
  "geometry": {"coordinates":[6.42853,52.67675],"type":"Point"}
}