{
  "type": "Feature",
  "properties": {
    "addr:full":"Oudshoornseweg 70 Alphen A/D Rijn Zuid-Holland 2401 LB",
    "addr:housenumber":"70;2401",
    "addr:postcode":"lb",
    "addr:street":"Oudshoornseweg",
    "iso:country":"NL",
    "sg:address":"Oudshoornseweg 70",
    "sg:city":"Alphen A/D Rijn",
    "sg:orig_category":"Politie",
    "sg:phone":"+31 900 8844",
    "sg:postcode":"2401 LB",
    "sg:province":"Zuid-Holland",
    "wof:name":"Politie Hollands Midden District Rijn- En Aarlande",
    "wof:placetype":"venue"
},
  "geometry": {"coordinates":[4.661247,52.141346],"type":"Point"}
}