{
  "type": "Feature",
  "properties": {
    "iso:country":"NL",
    "sg:address":"Stationsstr 100A",
    "sg:city":"Beek Lb",
    "sg:orig_category":"Waterbehandeling En Waterzuiverings- Systemen",
    "sg:phone":"+31 46 449 8977",
    "sg:postcode":"6191 BG",
    "sg:province":"Khaskovo",
    "sg:website":"http://www.rezo.nl",
    "wof:name":"Rezo Water And Solar Systems",
    "wof:placetype":"venue"
},
  "geometry": {"coordinates":[25.7736492157,42.6108512878],"type":"Point"}
}