{
  "type": "Feature",
  "properties": {
    "iso:country":"NL",
    "sg:address":"Atlasdreef 203",
    "sg:city":"Utrecht",
    "sg:orig_category":"Homeopathie",
    "sg:phone":"+31 30 261 2774",
    "sg:postcode":"3561 AJ",
    "sg:province":"Utrecht",
    "wof:name":"Boog, E",
    "wof:placetype":"venue"
},
  "geometry": {"coordinates":[5.130127,52.116676],"type":"Point"}
}