{
  "type": "Feature",
  "properties": {
    "addr:full":"Oude Kraan 72 Arnhem Gelderland 6811 LL",
    "addr:housenumber":"72",
    "addr:postcode":"6811 ll",
    "addr:street":"Oude Kraan",
    "iso:country":"NL",
    "sg:address":"Oude Kraan 72",
    "sg:city":"Arnhem",
    "sg:orig_category":"Bedrijfsopleidingen",
    "sg:phone":"+31 26 321 1244",
    "sg:postcode":"6811 LL",
    "sg:province":"Gelderland",
    "sg:website":"http://www.onestep.nl",
    "wof:name":"One Step To Knowledge",
    "wof:placetype":"venue"
},
  "geometry": {"coordinates":[5.897813,51.982937],"type":"Point"}
}