{
  "type": "Feature",
  "properties": {
    "addr:full":"Kanaalwg 2A Scheemda Groningen 9679 HZ",
    "addr:housenumber":"2a",
    "addr:postcode":"9679 hz",
    "addr:street":"Kanaalwg",
    "iso:country":"NL",
    "sg:address":"Kanaalwg 2A",
    "sg:city":"Scheemda",
    "sg:orig_category":"Politie",
    "sg:phone":"+31 900 8844",
    "sg:postcode":"9679 HZ",
    "sg:province":"Groningen",
    "wof:name":"Politie",
    "wof:placetype":"venue"
},
  "geometry": {"coordinates":[6.970384,53.173527],"type":"Point"}
}