{
  "type": "Feature",
  "properties": {
    "iso:country":"NL",
    "sg:address":"Galgenkampswg 2",
    "sg:city":"Meppel",
    "sg:orig_category":"Koel- En Vriestransporten",
    "sg:phone":"+31 522 252 876",
    "sg:postcode":"7942 HD",
    "sg:province":"Drenthe",
    "wof:name":"Laan Meppel Bv, Van Der",
    "wof:placetype":"venue"
},
  "geometry": {"coordinates":[6.184908,52.702877],"type":"Point"}
}