{
  "type": "Feature",
  "properties": {
    "addr:full":"Leusderweg 178 Amersfoort Utrecht 3817 KE",
    "addr:housenumber":"178",
    "addr:postcode":"3817 ke",
    "addr:street":"Leusderweg",
    "iso:country":"NL",
    "sg:address":"Leusderweg 178",
    "sg:city":"Amersfoort",
    "sg:orig_category":"Kappers",
    "sg:phone":"+31 33 461 0077",
    "sg:postcode":"3817 KE",
    "sg:province":"Utrecht",
    "wof:name":"Hairstudio Lanique",
    "wof:placetype":"venue"
},
  "geometry": {"coordinates":[5.3803172112,52.1429786682],"type":"Point"}
}