{
  "type": "Feature",
  "properties": {
    "addr:full":"Stationswg 1 Gorredyk Provincie Friesland 8401 DK",
    "addr:housenumber":"1",
    "addr:postcode":"8401 dk",
    "addr:street":"Stationswg;Provincie Friesland",
    "iso:country":"NL",
    "sg:address":"Stationswg 1",
    "sg:city":"Gorredyk",
    "sg:orig_category":"Banken",
    "sg:phone":"+31 513 467 467",
    "sg:postcode":"8401 DK",
    "sg:province":"Provincie Friesland",
    "sg:website":"http://www.rabobank.nl",
    "wof:name":"Rabobank",
    "wof:placetype":"venue"
},
  "geometry": {"coordinates":[6.063944,53.005856],"type":"Point"}
}