{
  "type": "Feature",
  "properties": {
    "addr:full":"Beekstraat 61 Weert Limburg 6001 GH",
    "addr:housenumber":"61",
    "addr:postcode":"6001 gh",
    "addr:street":"Beekstraat",
    "iso:country":"NL",
    "sg:address":"Beekstraat 61",
    "sg:city":"Weert",
    "sg:classifiers":[
        {
            "category":"Fast Food",
            "type":"Food & Drink"
        }
    ],
    "sg:phone":"+31 495 520 384",
    "sg:postcode":"6001 GH",
    "sg:province":"Limburg",
    "sg:tags":[
        "afhaal",
        "restaurant"
    ],
    "wof:name":"Chinees Indisch Restaurant Familie Wong",
    "wof:placetype":"venue"
},
  "geometry": {"coordinates":[5.705449,51.25589],"type":"Point"}
}