{
  "type": "Feature",
  "properties": {
    "iso:country":"NL",
    "sg:address":"Hilsondusstraat 101",
    "sg:city":"Strijen",
    "sg:orig_category":"Boekhouders",
    "sg:phone":"+31 78 674 7071",
    "sg:postcode":"3291 HD",
    "sg:province":"South Holland",
    "wof:name":"Huco",
    "wof:placetype":"venue"
},
  "geometry": {"coordinates":[4.553094,51.737171],"type":"Point"}
}