{
  "type": "Feature",
  "properties": {
    "addr:full":"Hilsondusstraat 101 Strijen South Holland 3291 HD",
    "addr:housenumber":"101",
    "addr:postcode":"3291 hd",
    "addr:street":"Hilsondusstraat",
    "iso:country":"NL",
    "sg:address":"Hilsondusstraat 101",
    "sg:city":"Strijen",
    "sg:orig_category":"Boekhouders",
    "sg:phone":"+31 78 674 7071",
    "sg:postcode":"3291 HD",
    "sg:province":"South Holland",
    "wof:name":"Huco",
    "wof:placetype":"venue"
},
  "geometry": {"coordinates":[4.553094,51.737171],"type":"Point"}
}