{
  "type": "Feature",
  "properties": {
    "addr:full":"Dorpsstraat 7 Lattrop Breklenkamp NL.08 7635 NA",
    "addr:housenumber":"7",
    "addr:postcode":"nl.08 7635 na",
    "addr:street":"Dorpsstraat",
    "iso:country":"NL",
    "sg:address":"Dorpsstraat 7",
    "sg:city":"Lattrop Breklenkamp",
    "sg:orig_category":"Kampeerterreinen",
    "sg:phone":"+31 541 221 392",
    "sg:postcode":"7635 NA",
    "sg:province":"NL.08",
    "wof:name":"Camping Bossems",
    "wof:placetype":"venue"
},
  "geometry": {"coordinates":[6.9701571465,52.4180030823],"type":"Point"}
}