{
  "type": "Feature",
  "properties": {
    "addr:full":"V Slingerlandstr 42 Voorhout Zuid-Holland 2215 SZ",
    "addr:housenumber":"42",
    "addr:postcode":"2215 sz",
    "iso:country":"NL",
    "sg:address":"V Slingerlandstr 42",
    "sg:city":"Voorhout",
    "sg:orig_category":"Scholen Voor Basisonderwijs",
    "sg:phone":"+31 252 210 264",
    "sg:postcode":"2215 SZ",
    "sg:province":"Zuid-Holland",
    "wof:name":"Antonius Rk",
    "wof:placetype":"venue"
},
  "geometry": {"coordinates":[4.48252,52.221874],"type":"Point"}
}