{
  "type": "Feature",
  "properties": {
    "addr:full":"Oudendk 14 Woudrichem Noord-Brabant 4285 WK",
    "addr:housenumber":"14",
    "addr:postcode":"4285 wk",
    "addr:street":"Oudendk",
    "iso:country":"NL",
    "sg:address":"Oudendk 14",
    "sg:city":"Woudrichem",
    "sg:orig_category":"Adviesbureaus Bedrijfsorganisatie",
    "sg:phone":"+31 6 51566332",
    "sg:postcode":"4285 WK",
    "sg:province":"Noord-Brabant",
    "wof:name":"Touchez",
    "wof:placetype":"venue"
},
  "geometry": {"coordinates":[4.97879,51.806469],"type":"Point"}
}