{
  "type": "Feature",
  "properties": {
    "addr:full":"Stationsstraat 80 Zaandam Noord-Holland 1506 DJ",
    "addr:housenumber":"80",
    "addr:postcode":"1506 dj",
    "addr:street":"Stationsstraat",
    "iso:country":"NL",
    "sg:address":"Stationsstraat 80",
    "sg:city":"Zaandam",
    "sg:orig_category":"Huishoudelijk Textiel Fab",
    "sg:phone":"+31 75 616 1251",
    "sg:postcode":"1506 DJ",
    "sg:province":"Noord-Holland",
    "wof:name":"Texti Made Bv",
    "wof:placetype":"venue"
},
  "geometry": {"coordinates":[4.817496,52.440384],"type":"Point"}
}