{
  "type": "Feature",
  "properties": {
    "addr:full":"Ketelwg 34 Papendrecht Zuid-Holland 3356 LE",
    "addr:housenumber":"34",
    "addr:postcode":"3356 le",
    "addr:street":"Ketelwg",
    "iso:country":"NL",
    "sg:address":"Ketelwg 34",
    "sg:city":"Papendrecht",
    "sg:orig_category":"Levensmiddelen - Fabrieken En Groothandel",
    "sg:phone":"+31 78 642 0720",
    "sg:postcode":"3356 LE",
    "sg:province":"Zuid-Holland",
    "wof:name":"Sillevoldt Bv, Van",
    "wof:placetype":"venue"
},
  "geometry": {"coordinates":[4.727523,51.828167],"type":"Point"}
}