{
  "type": "Feature",
  "properties": {
    "addr:full":"Benzenraderwg 8 Heerlen Limburg 6411 ED",
    "addr:housenumber":"8",
    "addr:postcode":"6411 ed",
    "addr:street":"Benzenraderwg",
    "iso:country":"NL",
    "sg:address":"Benzenraderwg 8",
    "sg:city":"Heerlen",
    "sg:orig_category":"Advocaten En Advocatenkantoren",
    "sg:phone":"+31 45 571 4576",
    "sg:postcode":"6411 ED",
    "sg:province":"Limburg",
    "wof:name":"Boumans",
    "wof:placetype":"venue"
},
  "geometry": {"coordinates":[5.978557,50.88253],"type":"Point"}
}