{
  "type": "Feature",
  "properties": {
    "iso:country":"NL",
    "sg:address":"Grutbroek 26",
    "sg:city":"Doetinchem",
    "sg:orig_category":"Auto-Onderdelen And -Accessoires Gh",
    "sg:phone":"+31 314 345 569",
    "sg:postcode":"7008 AM",
    "sg:province":"Gelderland",
    "wof:name":"Harmen Smit",
    "wof:placetype":"venue"
},
  "geometry": {"coordinates":[6.270718,51.972908],"type":"Point"}
}