{
  "type": "Feature",
  "properties": {
    "iso:country":"NL",
    "sg:address":"Markt 29",
    "sg:city":"Boxtel",
    "sg:orig_category":"Meubelzaken, Woning- And Keukeninrichting",
    "sg:phone":"+31 411 672 874",
    "sg:postcode":"5281 AV",
    "sg:province":"Noord-Brabant",
    "wof:name":"F. Den Ouden",
    "wof:placetype":"venue"
},
  "geometry": {"coordinates":[5.326208,51.588589],"type":"Point"}
}