{
  "type": "Feature",
  "properties": {
    "iso:country":"NL",
    "sg:address":"St. Cornelisplein 6",
    "sg:city":"Weert",
    "sg:orig_category":"Organisaties And Verenigingen",
    "sg:phone":"+31 495 551 754",
    "sg:postcode":"6005 PD",
    "sg:province":"Limburg",
    "wof:name":"Ritzen & Widdershoven",
    "wof:placetype":"venue"
},
  "geometry": {"coordinates":[5.7711620331,51.2301635742],"type":"Point"}
}