{
  "type": "Feature",
  "properties": {
    "addr:full":"Koningswg 49 Alkmaar Noord-Holland 1811 LL",
    "addr:housenumber":"49",
    "addr:postcode":"1811 ll",
    "addr:street":"Koningswg",
    "iso:country":"NL",
    "sg:address":"Koningswg 49",
    "sg:city":"Alkmaar",
    "sg:orig_category":"Verenigingsgebouwen",
    "sg:phone":"+31 72 511 6086",
    "sg:postcode":"1811 LL",
    "sg:province":"Noord-Holland",
    "wof:name":"Burcht, De",
    "wof:placetype":"venue"
},
  "geometry": {"coordinates":[4.747887,52.633205],"type":"Point"}
}