{
  "type": "Feature",
  "properties": {
    "addr:full":"Leidsegracht 8 Amsterdam Noord-Holland 1016 ",
    "addr:housenumber":"8",
    "addr:postcode":"1016",
    "addr:street":"Leidsegracht",
    "iso:country":"NL",
    "sg:address":"Leidsegracht 8",
    "sg:city":"Amsterdam",
    "sg:orig_category":"Boekenuitgeverijen",
    "sg:phone":"+31 20 627 8510",
    "sg:postcode":"1016 ",
    "sg:province":"Noord-Holland",
    "wof:name":"Bres Bv Uitgeverij",
    "wof:placetype":"venue"
},
  "geometry": {"coordinates":[4.8845,52.366909],"type":"Point"}
}