{
  "type": "Feature",
  "properties": {
    "iso:country":"NL",
    "sg:address":"P V Vlietln 10",
    "sg:city":"Ryswyk Zh",
    "sg:orig_category":"Kinderopvang",
    "sg:phone":"+31 70 372 8080",
    "sg:postcode":"2285 XM",
    "sg:province":"Zuid-Holland",
    "sg:website":"http://www.kinderopvang-plein.nl",
    "wof:name":"Stichting Rijswijkse Kinderopvang",
    "wof:placetype":"venue"
},
  "geometry": {"coordinates":[4.32436,52.037251],"type":"Point"}
}