{
  "type": "Feature",
  "properties": {
    "addr:full":"De Hemmen 36 Drachten Friesland 9206 AG",
    "addr:housenumber":"36",
    "addr:postcode":"9206",
    "addr:street":"De Hemmen",
    "iso:country":"NL",
    "sg:address":"De Hemmen 36",
    "sg:city":"Drachten",
    "sg:orig_category":"Kantoorapparatuur Gh",
    "sg:phone":"+31 512 530 385",
    "sg:postcode":"9206 AG",
    "sg:province":"Friesland",
    "wof:name":"Emhi Verhuur & Verkoop",
    "wof:placetype":"venue"
},
  "geometry": {"coordinates":[6.0724339485,53.1123504639],"type":"Point"}
}