{
  "type": "Feature",
  "properties": {
    "iso:country":"NL",
    "sg:address":"Langewg 22",
    "sg:city":"Roelofarendsveen",
    "sg:orig_category":"Fietsen En Bromfietsen",
    "sg:phone":"+31 71 331 2294",
    "sg:postcode":"2371 EG",
    "sg:province":"Zuid-Holland",
    "wof:name":"Schouten",
    "wof:placetype":"venue"
},
  "geometry": {"coordinates":[4.634684,52.202843],"type":"Point"}
}