{
  "type": "Feature",
  "properties": {
    "iso:country":"NL",
    "sg:address":"Schoolstraat 54",
    "sg:city":"Uithuizen",
    "sg:orig_category":"Fietshandelaren",
    "sg:phone":"+31 595 431 245",
    "sg:postcode":"9981 AP",
    "sg:province":"Groningen",
    "wof:name":"Rijwielhandel En Sportkledingbedrijf Bos",
    "wof:placetype":"venue"
},
  "geometry": {"coordinates":[6.670808,53.409081],"type":"Point"}
}