{
  "type": "Feature",
  "properties": {
    "addr:full":"Staalsteden 25 Enschede Overijssel 7547 TA",
    "addr:housenumber":"25",
    "addr:postcode":"7547 ta",
    "addr:street":"Staalsteden",
    "iso:country":"NL",
    "sg:address":"Staalsteden 25",
    "sg:city":"Enschede",
    "sg:classifiers":[
        {
            "category":"Building & Trades",
            "subcategory":"Electrical",
            "type":"Services"
        }
    ],
    "sg:phone":"+31 53 428 3455",
    "sg:postcode":"7547 TA",
    "sg:province":"Overijssel",
    "sg:tags":[
        "distributor"
    ],
    "wof:name":"Timberland Europe Inc",
    "wof:placetype":"venue"
},
  "geometry": {"coordinates":[6.817047,52.214207],"type":"Point"}
}