{
  "type": "Feature",
  "properties": {
    "addr:full":"Leywg 575 S Gravenhage South Holland 2545 GH",
    "addr:housenumber":"575",
    "addr:postcode":"2545 gh",
    "addr:street":"S Gravenhage",
    "iso:country":"NL",
    "sg:address":"Leywg 575",
    "sg:city":"S Gravenhage",
    "sg:orig_category":"Hoortoestellen",
    "sg:phone":"+31 70 321 0981",
    "sg:postcode":"2545 GH",
    "sg:province":"South Holland",
    "sg:website":"http://www.schoonenberg.nl",
    "wof:name":"Schoonenberg Hoorcomfort",
    "wof:placetype":"venue"
},
  "geometry": {"coordinates":[4.2704901695,52.0509300232],"type":"Point"}
}