{
  "type": "Feature",
  "properties": {
    "iso:country":"NL",
    "sg:address":"Brinkstr 691",
    "sg:city":"Enschede",
    "sg:orig_category":"Waterbehandeling En Waterzuiverings- Systemen",
    "sg:phone":"+31 6 20416675",
    "sg:postcode":"7542 PC",
    "sg:province":"Overijssel",
    "wof:name":"Molewijk, E H",
    "wof:placetype":"venue"
},
  "geometry": {"coordinates":[6.9195280075,52.1981048584],"type":"Point"}
}