{
  "type": "Feature",
  "properties": {
    "addr:full":"2E Johannastraat 44A Apeldoorn Gelderland 7331 CJ",
    "addr:housenumber":"44a",
    "addr:postcode":"7331 cj",
    "addr:street":"2E Johannastraat;Gelderland",
    "iso:country":"NL",
    "sg:address":"2E Johannastraat 44A",
    "sg:city":"Apeldoorn",
    "sg:orig_category":"Boekhouders",
    "sg:phone":"+31 55 534 0981",
    "sg:postcode":"7331 CJ",
    "sg:province":"Gelderland",
    "wof:name":"Administratie Advieskantoor E H Allround",
    "wof:placetype":"venue"
},
  "geometry": {"coordinates":[5.965274,52.205086],"type":"Point"}
}