{
  "type": "Feature",
  "properties": {
    "addr:full":"Sint Annenstraat 30 Amsterdam Noord-Holland 1012 HE",
    "addr:housenumber":"30",
    "addr:postcode":"1012 he",
    "addr:street":"Sint Annenstraat",
    "iso:country":"NL",
    "sg:address":"Sint Annenstraat 30",
    "sg:city":"Amsterdam",
    "sg:orig_category":"Fotostudio'S And Fotografen",
    "sg:phone":"+31 20 622 6356",
    "sg:postcode":"1012 HE",
    "sg:province":"Noord-Holland",
    "wof:name":"P.N.J.M. Daalderop",
    "wof:placetype":"venue"
},
  "geometry": {"coordinates":[4.89734,52.373466],"type":"Point"}
}