{
  "type": "Feature",
  "properties": {
    "addr:full":"Dirk Van Ameijdenstraat 1 Oirschot North Brabant 5688 AL",
    "addr:housenumber":"1",
    "addr:postcode":"5688 al",
    "addr:street":"Dirk;Ameijdenstraat",
    "iso:country":"NL",
    "sg:address":"Dirk Van Ameijdenstraat 1",
    "sg:city":"Oirschot",
    "sg:orig_category":"Partycatering And -Organisatie",
    "sg:phone":"+31 499 574 790",
    "sg:postcode":"5688 AL",
    "sg:province":"North Brabant",
    "wof:name":"Le Bon Vivant",
    "wof:placetype":"venue"
},
  "geometry": {"coordinates":[5.307353,51.504162],"type":"Point"}
}