{
  "type": "Feature",
  "properties": {
    "addr:full":"Kerkstraat 5 Doenrade Limburg 6439 AN",
    "addr:housenumber":"5",
    "addr:postcode":"6439 an",
    "addr:street":"Kerkstraat",
    "iso:country":"NL",
    "sg:address":"Kerkstraat 5",
    "sg:city":"Doenrade",
    "sg:orig_category":"Schilderwerk",
    "sg:phone":"+31 46 442 5510",
    "sg:postcode":"6439 AN",
    "sg:province":"Limburg",
    "wof:name":"W.H. Feyge",
    "wof:placetype":"venue"
},
  "geometry": {"coordinates":[5.906864,50.967979],"type":"Point"}
}