{
  "type": "Feature",
  "properties": {
    "addr:full":"Spekenblok 15 Breda North Brabant 4823 JE",
    "addr:housenumber":"15",
    "addr:postcode":"4823 je",
    "addr:street":"Spekenblok",
    "iso:country":"NL",
    "sg:address":"Spekenblok 15",
    "sg:city":"Breda",
    "sg:orig_category":"Metaalwerken",
    "sg:phone":"+31 76 541 6802",
    "sg:postcode":"4823 JE",
    "sg:province":"North Brabant",
    "wof:name":"Glastuinbouw Adviesburo De Jong",
    "wof:placetype":"venue"
},
  "geometry": {"coordinates":[4.738105,51.626209],"type":"Point"}
}