{
  "type": "Feature",
  "properties": {
    "addr:full":"Ericastr 45 Eindhoven Noord-Brabant 5615 BJ",
    "addr:housenumber":"45",
    "addr:postcode":"5615 bj",
    "addr:street":"Ericastr",
    "iso:country":"NL",
    "sg:address":"Ericastr 45",
    "sg:city":"Eindhoven",
    "sg:orig_category":"Psychologen",
    "sg:phone":"+31 40 211 1538",
    "sg:postcode":"5615 BJ",
    "sg:province":"Noord-Brabant",
    "wof:name":"Terzano-Hoeks, Drs W",
    "wof:placetype":"venue"
},
  "geometry": {"coordinates":[5.487111,51.424919],"type":"Point"}
}