{
  "type": "Feature",
  "properties": {
    "addr:full":"Entstr 33 Oudenbosch North Brabant 4731 XH",
    "addr:housenumber":"33",
    "addr:postcode":"4731 xh",
    "addr:street":"Entstr",
    "iso:country":"NL",
    "sg:address":"Entstr 33",
    "sg:city":"Oudenbosch",
    "sg:orig_category":"Verzekeringen - Verzekeringskantoren",
    "sg:phone":"+31 165 312 116",
    "sg:postcode":"4731 XH",
    "sg:province":"North Brabant",
    "sg:website":"http://www.assurantiekantoor-jorissen.nl",
    "wof:name":"Jorissen, A J M",
    "wof:placetype":"venue"
},
  "geometry": {"coordinates":[4.534904,51.58527],"type":"Point"}
}