{
  "type": "Feature",
  "properties": {
    "addr:full":"Landrebenln 29 Oldenzaal Overijssel 7573 AZ",
    "addr:housenumber":"29",
    "addr:postcode":"7573 az",
    "addr:street":"Landrebenln",
    "iso:country":"NL",
    "sg:address":"Landrebenln 29",
    "sg:city":"Oldenzaal",
    "sg:orig_category":"Product-Promotie",
    "sg:phone":"+31 541 532 069",
    "sg:postcode":"7573 AZ",
    "sg:province":"Overijssel",
    "wof:name":"Molnar, Hanny",
    "wof:placetype":"venue"
},
  "geometry": {"coordinates":[6.940893,52.308262],"type":"Point"}
}