{
  "type": "Feature",
  "properties": {
    "addr:full":"Egelskoog 21 Alkmaar Noord-Holland 1822 BM",
    "addr:housenumber":"21",
    "addr:postcode":"1822 bm",
    "addr:street":"Egelskoog",
    "iso:country":"NL",
    "sg:address":"Egelskoog 21",
    "sg:city":"Alkmaar",
    "sg:orig_category":"Land- En Tuinbouw - Loonbedrijven",
    "sg:phone":"+31 72 561 2740",
    "sg:postcode":"1822 BM",
    "sg:province":"Noord-Holland",
    "wof:name":"Molenaar, K",
    "wof:placetype":"venue"
},
  "geometry": {"coordinates":[4.789975,52.648273],"type":"Point"}
}