{
  "type": "Feature",
  "properties": {
    "addr:full":"Noordersngl 26 Eemnes Utrecht 3755 EZ",
    "addr:housenumber":"26",
    "addr:postcode":"3755 ez",
    "addr:street":"Noordersngl",
    "iso:country":"NL",
    "sg:address":"Noordersngl 26",
    "sg:city":"Eemnes",
    "sg:classifiers":[
        {
            "category":"Sports & Exercise",
            "subcategory":"Stables",
            "type":"Entertainment"
        }
    ],
    "sg:phone":"+31 35 538 6851",
    "sg:postcode":"3755 EZ",
    "sg:province":"Utrecht",
    "sg:tags":[
        "maneges"
    ],
    "wof:name":"Schildknecht Manege Bv",
    "wof:placetype":"venue"
},
  "geometry": {"coordinates":[5.25941,52.253288],"type":"Point"}
}