{
  "type": "Feature",
  "properties": {
    "addr:full":"Westblaak 140 Rotterdam South Holland 3012 KM",
    "addr:housenumber":"140",
    "addr:postcode":"3012 km",
    "addr:street":"Westblaak",
    "iso:country":"NL",
    "sg:address":"Westblaak 140",
    "sg:city":"Rotterdam",
    "sg:orig_category":"Machinehandel",
    "sg:phone":"+31 10 412 4138",
    "sg:postcode":"3012 KM",
    "sg:province":"South Holland",
    "wof:name":"Aoki Co Ltd",
    "wof:placetype":"venue"
},
  "geometry": {"coordinates":[4.47649,51.916599],"type":"Point"}
}