{
  "type": "Feature",
  "properties": {
    "addr:full":"Van Hogendorplaan 28 Hilversum Noord-Holland 1215 EH",
    "addr:housenumber":"28",
    "addr:postcode":"1215 eh",
    "addr:street":"Van Hogendorplaan",
    "iso:country":"NL",
    "sg:address":"Van Hogendorplaan 28",
    "sg:city":"Hilversum",
    "sg:orig_category":"Kappers",
    "sg:phone":"+31 35 621 3580",
    "sg:postcode":"1215 EH",
    "sg:province":"Noord-Holland",
    "wof:name":"Hans Haarmode",
    "wof:placetype":"venue"
},
  "geometry": {"coordinates":[5.15583992,52.214630127],"type":"Point"}
}