{
  "type": "Feature",
  "properties": {
    "addr:full":"Havikshorst 92 Deventer Overijssel 7414 HT",
    "addr:housenumber":"92",
    "addr:postcode":"7414 ht",
    "addr:street":"Havikshorst",
    "iso:country":"NL",
    "sg:address":"Havikshorst 92",
    "sg:city":"Deventer",
    "sg:orig_category":"Bedrijfs- And Managementsconsultants",
    "sg:phone":"+31 570 644 904",
    "sg:postcode":"7414 HT",
    "sg:province":"Overijssel",
    "wof:name":"Adviesbureau Van Uden",
    "wof:placetype":"venue"
},
  "geometry": {"coordinates":[6.147659,52.277683],"type":"Point"}
}