{
  "type": "Feature",
  "properties": {
    "addr:full":"Lelie 6 Venray Limburg 5803 JK",
    "addr:housenumber":"6",
    "addr:postcode":"5803 jk",
    "addr:street":"Lelie",
    "iso:country":"NL",
    "sg:address":"Lelie 6",
    "sg:city":"Venray",
    "sg:orig_category":"Diverse Grafische Activiteiten",
    "sg:phone":"+31 478 512 145",
    "sg:postcode":"5803 JK",
    "sg:province":"Limburg",
    "wof:name":"J.H.P. Verstappen",
    "wof:placetype":"venue"
},
  "geometry": {"coordinates":[5.993481,51.532467],"type":"Point"}
}