{
  "type": "Feature",
  "properties": {
    "iso:country":"NL",
    "sg:address":"Gravin Jacobastraat 17",
    "sg:city":"Gouda",
    "sg:orig_category":"Verzekeringen - Verzekeringskantoren",
    "sg:phone":"+31 182 582 205",
    "sg:postcode":"2805 PL",
    "sg:province":"South Holland",
    "wof:name":"Polet",
    "wof:placetype":"venue"
},
  "geometry": {"coordinates":[4.72009,52.017582],"type":"Point"}
}