{
  "type": "Feature",
  "properties": {
    "addr:full":"Laan Van Meerdervoort 437 'S Gravenhage South Holland 2563 AS",
    "addr:housenumber":"437 '",
    "addr:postcode":"2563 as",
    "addr:street":"Laan Van Meerdervoort",
    "iso:country":"NL",
    "sg:address":"Laan Van Meerdervoort 437",
    "sg:city":"'S Gravenhage",
    "sg:orig_category":"Wasserettes And Stomerijen",
    "sg:phone":"+31 70 345 0379",
    "sg:postcode":"2563 AS",
    "sg:province":"South Holland",
    "wof:name":"Palthe Stomerijen Bv",
    "wof:placetype":"venue"
},
  "geometry": {"coordinates":[4.2706418037,52.0766181946],"type":"Point"}
}