{
  "type": "Feature",
  "properties": {
    "addr:full":"Stompersstraat 6 Sint Oedenrode Noord-Brabant 5492 CR",
    "addr:housenumber":"6;oedenrode",
    "addr:postcode":"5492 cr",
    "addr:street":"Stompersstraat",
    "iso:country":"NL",
    "sg:address":"Stompersstraat 6",
    "sg:city":"Sint Oedenrode",
    "sg:orig_category":"Farmaceutische Producten Gh",
    "sg:phone":"+31 413 310 100",
    "sg:postcode":"5492 CR",
    "sg:province":"Noord-Brabant",
    "wof:name":"Hulstijn Medische Produkten Bv",
    "wof:placetype":"venue"
},
  "geometry": {"coordinates":[5.460725,51.565174],"type":"Point"}
}