{
  "type": "Feature",
  "properties": {
    "addr:full":"Bilderdijklaan 49 Rijswijk Zh South Holland 2281 SN",
    "addr:housenumber":"49",
    "addr:postcode":"2281 sn",
    "addr:street":"Bilderdijklaan",
    "iso:country":"NL",
    "sg:address":"Bilderdijklaan 49",
    "sg:city":"Rijswijk Zh",
    "sg:orig_category":"Verzekeringen",
    "sg:phone":"+31 70 395 4211",
    "sg:postcode":"2281 SN",
    "sg:province":"South Holland",
    "wof:name":"Doe Vd Berg Ass",
    "wof:placetype":"venue"
},
  "geometry": {"coordinates":[4.337748,52.05872],"type":"Point"}
}