{
  "type": "Feature",
  "properties": {
    "addr:full":"Markt 14 Waalre Noord-Brabant 5581 GK",
    "addr:housenumber":"14",
    "addr:postcode":"5581 gk",
    "addr:street":"Markt",
    "iso:country":"NL",
    "sg:address":"Markt 14",
    "sg:city":"Waalre",
    "sg:orig_category":"Banken And Kredietinstellingen",
    "sg:phone":"+31 40 223 1200",
    "sg:postcode":"5581 GK",
    "sg:province":"Noord-Brabant",
    "wof:name":"Rabobank",
    "wof:placetype":"venue"
},
  "geometry": {"coordinates":[5.443104,51.386189],"type":"Point"}
}