{
  "type": "Feature",
  "properties": {
    "addr:full":"J V Lennepkd 13 Amsterdam North Holland 1054 ZD",
    "addr:housenumber":"13",
    "addr:postcode":"1054 zd",
    "addr:street":"J;Lennepkd",
    "iso:country":"NL",
    "sg:address":"J V Lennepkd 13",
    "sg:city":"Amsterdam",
    "sg:orig_category":"Psychotherapeuten",
    "sg:phone":"+31 20 683 5547",
    "sg:postcode":"1054 ZD",
    "sg:province":"North Holland",
    "wof:name":"Noort, Drs M Van",
    "wof:placetype":"venue"
},
  "geometry": {"coordinates":[4.86857,52.361408],"type":"Point"}
}