{
  "type": "Feature",
  "properties": {
    "addr:full":"Ferdinand Bolstraat 28 Leeuwarden Friesland 8932 JP",
    "addr:housenumber":"28",
    "addr:postcode":"8932 jp",
    "addr:street":"Ferdinand Bolstraat",
    "iso:country":"NL",
    "sg:address":"Ferdinand Bolstraat 28",
    "sg:city":"Leeuwarden",
    "sg:orig_category":"Metaalwerken",
    "sg:phone":"+31 58 215 2993",
    "sg:postcode":"8932 JP",
    "sg:province":"Friesland",
    "wof:name":"J. Stoelwinder",
    "wof:placetype":"venue"
},
  "geometry": {"coordinates":[5.795422,53.190666],"type":"Point"}
}