{
  "type": "Feature",
  "properties": {
    "iso:country":"NL",
    "sg:address":"Kruipwilg 10",
    "sg:city":"Heemskerk",
    "sg:orig_category":"Fietsen En Bromfietsen Verhuur",
    "sg:phone":"+31 251 241 485",
    "sg:postcode":"1964 MC",
    "sg:province":"Noord-Holland",
    "sg:website":"http://www.fietsverhuur.nl",
    "wof:name":"Joop Van Tunen",
    "wof:placetype":"venue"
},
  "geometry": {"coordinates":[4.656903,52.515598],"type":"Point"}
}