{
  "type": "Feature",
  "properties": {
    "iso:country":"NL",
    "sg:address":"Oud Milligenseweg 19",
    "sg:city":"Garderen",
    "sg:orig_category":"Pluimveehouderijen",
    "sg:phone":"+31 577 461 440",
    "sg:postcode":"3886 MB",
    "sg:province":"Gelderland",
    "wof:name":"J Pluimveeopfokbedrijf Mulder",
    "wof:placetype":"venue"
},
  "geometry": {"coordinates":[5.716732,52.230446],"type":"Point"}
}