{
  "type": "Feature",
  "properties": {
    "addr:full":"Kerkplein 12 Zeewolde Flevoland 3891 ED",
    "addr:housenumber":"12",
    "addr:postcode":"3891 ed",
    "addr:street":"Kerkplein;Flevoland",
    "iso:country":"NL",
    "sg:address":"Kerkplein 12",
    "sg:city":"Zeewolde",
    "sg:orig_category":"Werving And Selectie Van Tijdelijk Personeel And Uitzendkantoren",
    "sg:phone":"+31 36 522 6161",
    "sg:postcode":"3891 ED",
    "sg:province":"Flevoland",
    "wof:name":"Randstad",
    "wof:placetype":"venue"
},
  "geometry": {"coordinates":[5.542181015,52.331035614],"type":"Point"}
}