{
  "type": "Feature",
  "properties": {
    "iso:country":"NL",
    "sg:address":"Crocuserf 12",
    "sg:city":"S Gravendeel",
    "sg:orig_category":"Adviesbureaus Bouwkunde",
    "sg:phone":"+31 78 673 3455",
    "sg:postcode":"3295 SC",
    "sg:province":"Zuid-Holland",
    "wof:name":"Heeren, Van",
    "wof:placetype":"venue"
},
  "geometry": {"coordinates":[4.607756,51.78054],"type":"Point"}
}