{
  "type": "Feature",
  "properties": {
    "addr:full":"Gasselterweg 1 Gasselternijveen Provincie Drenthe 9514 BK",
    "addr:housenumber":"1",
    "addr:postcode":"9514 bk",
    "addr:street":"Gasselterweg;Provincie Drenthe",
    "iso:country":"NL",
    "sg:address":"Gasselterweg 1",
    "sg:city":"Gasselternijveen",
    "sg:orig_category":"Meubelzaken, Woning- And Keukeninrichting",
    "sg:phone":"+31 599 512 207",
    "sg:postcode":"9514 BK",
    "sg:province":"Provincie Drenthe",
    "wof:name":"Kaspers Compleet Wonen",
    "wof:placetype":"venue"
},
  "geometry": {"coordinates":[6.84525,52.98687],"type":"Point"}
}