{
  "type": "Feature",
  "properties": {
    "addr:full":"Oosterspoorpln 2 Amsterdam Noord-Holland 1093 JW",
    "addr:housenumber":"2",
    "addr:postcode":"1093 jw",
    "addr:street":"Oosterspoorpln",
    "iso:country":"NL",
    "sg:address":"Oosterspoorpln 2",
    "sg:city":"Amsterdam",
    "sg:orig_category":"Kappers",
    "sg:phone":"+31 6 51491270",
    "sg:postcode":"1093 JW",
    "sg:province":"Noord-Holland",
    "sg:website":"http://www.haarmetspelden.com",
    "wof:name":"Haar Met Spelden Vof",
    "wof:placetype":"venue"
},
  "geometry": {"coordinates":[4.9309802055,52.3604240417],"type":"Point"}
}