{
  "type": "Feature",
  "properties": {
    "iso:country":"NL",
    "sg:address":"Tiendwg 11",
    "sg:city":"Leerdam",
    "sg:orig_category":"Kinderopvang",
    "sg:phone":"+31 345 639 555",
    "sg:postcode":"4142 EG",
    "sg:province":"Zuid-Holland",
    "wof:name":"Skcn",
    "wof:placetype":"venue"
},
  "geometry": {"coordinates":[5.085816,51.890697],"type":"Point"}
}