{
  "type": "Feature",
  "properties": {
    "addr:full":"Cartografenweg 32 Waalwijk Noord-Brabant 5141 MT",
    "addr:housenumber":"32",
    "addr:postcode":"5141",
    "addr:street":"Cartografenweg;Mt",
    "iso:country":"NL",
    "sg:address":"Cartografenweg 32",
    "sg:city":"Waalwijk",
    "sg:orig_category":"Gebouwenafwerking, Renovaties And Reiniging",
    "sg:phone":"+31 416 651 515",
    "sg:postcode":"5141 MT",
    "sg:province":"Noord-Brabant",
    "wof:name":"Schildersbedrijf Van Veggel Bv",
    "wof:placetype":"venue"
},
  "geometry": {"coordinates":[5.043184,51.685665],"type":"Point"}
}