{
  "type": "Feature",
  "properties": {
    "addr:full":"V Konynenburgwg 44 Bergen Op Zoom Noord-Brabant 4612 PL",
    "addr:housenumber":"44",
    "addr:postcode":"4612 pl",
    "iso:country":"NL",
    "sg:address":"V Konynenburgwg 44",
    "sg:city":"Bergen Op Zoom",
    "sg:orig_category":"Jachthavens - Jachtwerven",
    "sg:phone":"+31 164 240 416",
    "sg:postcode":"4612 PL",
    "sg:province":"Noord-Brabant",
    "wof:name":"Feijen",
    "wof:placetype":"venue"
},
  "geometry": {"coordinates":[4.262161,51.502312],"type":"Point"}
}