{
  "type": "Feature",
  "properties": {
    "addr:full":"Grotestraat 19 Diepenheim Overijssel 7478 AA",
    "addr:housenumber":"19",
    "addr:postcode":"7478 aa",
    "addr:street":"Grotestraat",
    "iso:country":"NL",
    "sg:address":"Grotestraat 19",
    "sg:city":"Diepenheim",
    "sg:orig_category":"Architecten",
    "sg:phone":"+31 547 352 303",
    "sg:postcode":"7478 AA",
    "sg:province":"Overijssel",
    "wof:name":"Henry Betting",
    "wof:placetype":"venue"
},
  "geometry": {"coordinates":[6.550917,52.200592],"type":"Point"}
}