{
  "type": "Feature",
  "properties": {
    "addr:full":"Herentalsweg 5 Eindhoven Noord-Brabant 5628 RD",
    "addr:housenumber":"5",
    "addr:postcode":"5628 rd",
    "addr:street":"Herentalsweg",
    "iso:country":"NL",
    "sg:address":"Herentalsweg 5",
    "sg:city":"Eindhoven",
    "sg:orig_category":"Schilderwerk",
    "sg:phone":"+31 40 241 6421",
    "sg:postcode":"5628 RD",
    "sg:province":"Noord-Brabant",
    "wof:name":"Firma Jac. Mol En Zn",
    "wof:placetype":"venue"
},
  "geometry": {"coordinates":[5.483675,51.476845],"type":"Point"}
}