{
  "type": "Feature",
  "properties": {
    "addr:full":"John F Kennedyplein 7 Purmerend Noord-Holland 1443 EA",
    "addr:housenumber":"7",
    "addr:postcode":"1443 ea",
    "addr:street":"John F Kennedyplein",
    "iso:country":"NL",
    "sg:address":"John F Kennedyplein 7",
    "sg:city":"Purmerend",
    "sg:orig_category":"Opticiens",
    "sg:phone":"+31 299 414 564",
    "sg:postcode":"1443 EA",
    "sg:province":"Noord-Holland",
    "wof:name":"De Gildeopticien",
    "wof:placetype":"venue"
},
  "geometry": {"coordinates":[4.9686179161,52.5088005066],"type":"Point"}
}