{
  "type": "Feature",
  "properties": {
    "addr:full":"Weverskd 6 Maasland South Holland 3155 PD",
    "addr:housenumber":"6",
    "addr:postcode":"3155 pd",
    "addr:street":"Weverskd",
    "iso:country":"NL",
    "sg:address":"Weverskd 6",
    "sg:city":"Maasland",
    "sg:orig_category":"Vertaalbureaus",
    "sg:phone":"+31 10 590 3220",
    "sg:postcode":"3155 PD",
    "sg:province":"South Holland",
    "wof:name":"Hungary Holl Serv",
    "wof:placetype":"venue"
},
  "geometry": {"coordinates":[4.275135,51.936325],"type":"Point"}
}