{
  "type": "Feature",
  "properties": {
    "addr:full":"Herengr 13H S Gravenhage Zuid-Holland 2511 EG",
    "addr:postcode":"2511 eg",
    "iso:country":"NL",
    "sg:address":"Herengr 13H",
    "sg:city":"S Gravenhage",
    "sg:orig_category":"Verenigingen En Stichtingen",
    "sg:phone":"+31 70 392 2341",
    "sg:postcode":"2511 EG",
    "sg:province":"Zuid-Holland",
    "sg:website":"http://www.hardcorelinux.nl",
    "wof:name":"Hardcorelinux.Nl",
    "wof:placetype":"venue"
},
  "geometry": {"coordinates":[4.31627,52.07896],"type":"Point"}
}