{
  "type": "Feature",
  "properties": {
    "iso:country":"NL",
    "sg:address":"Catelynen 1",
    "sg:city":"Rosmalen",
    "sg:orig_category":"Makelaars En Adviseurs Onroerende Goederen",
    "sg:phone":"+31 73 522 3080",
    "sg:postcode":"5241 CW",
    "sg:province":"Noord-Brabant",
    "sg:website":"http://www.matax.nl",
    "wof:name":"Matax",
    "wof:placetype":"venue"
},
  "geometry": {"coordinates":[5.361311,51.717491],"type":"Point"}
}