{
  "type": "Feature",
  "properties": {
    "addr:full":"Jonkersbosje 4 Joure Provincie Friesland 8501 GX",
    "addr:housenumber":"4",
    "addr:postcode":"8501 gx",
    "addr:street":"Jonkersbosje;Provincie Friesland",
    "iso:country":"NL",
    "sg:address":"Jonkersbosje 4",
    "sg:city":"Joure",
    "sg:orig_category":"Metaalbekleding And -Behandeling",
    "sg:phone":"+31 513 412 627",
    "sg:postcode":"8501 GX",
    "sg:province":"Provincie Friesland",
    "wof:name":"Van Der Meulen Edelmetaal",
    "wof:placetype":"venue"
},
  "geometry": {"coordinates":[5.798385,52.964455],"type":"Point"}
}