{
  "type": "Feature",
  "properties": {
    "iso:country":"NL",
    "sg:address":"Burg Grothestr 20",
    "sg:city":"Soest",
    "sg:orig_category":"Piano'S",
    "sg:phone":"+31 35 601 2968",
    "sg:postcode":"3761 CM",
    "sg:province":"Utrecht",
    "wof:name":"Tol Pianohandel, Van",
    "wof:placetype":"venue"
},
  "geometry": {"coordinates":[5.29114,52.187256],"type":"Point"}
}