{
  "type": "Feature",
  "properties": {
    "iso:country":"NL",
    "sg:address":"Gladiolenstr 1",
    "sg:city":"Zwolle",
    "sg:orig_category":"Zoetwaren - Winkels",
    "sg:phone":"+31 38 421 6107",
    "sg:postcode":"8013 ZA",
    "sg:province":"Overijssel",
    "wof:name":"Drop-Shop",
    "wof:placetype":"venue"
},
  "geometry": {"coordinates":[6.113434,52.50341],"type":"Point"}
}