{
  "type": "Feature",
  "properties": {
    "iso:country":"NL",
    "sg:address":"Sterkenburg 182",
    "sg:city":"Ede Gld",
    "sg:orig_category":"Webdesign Bureaus",
    "sg:phone":"+31 318 640 175",
    "sg:postcode":"6714 EZ",
    "sg:province":"Gelderland",
    "sg:website":"http://www.eskes.net",
    "wof:name":"Eskes",
    "wof:placetype":"venue"
},
  "geometry": {"coordinates":[5.6499137878,52.0471878052],"type":"Point"}
}