{
  "type": "Feature",
  "properties": {
    "addr:full":"Plein 2 Blitterswyck Limburg 5863 AT",
    "addr:housenumber":"2",
    "addr:postcode":"5863",
    "addr:street":"Plein",
    "iso:country":"NL",
    "sg:address":"Plein 2",
    "sg:city":"Blitterswyck",
    "sg:orig_category":"Scholen Voor Basisonderwijs",
    "sg:phone":"+31 478 531 817",
    "sg:postcode":"5863 AT",
    "sg:province":"Limburg",
    "wof:name":"Anna Rk, St",
    "wof:placetype":"venue"
},
  "geometry": {"coordinates":[6.109197,51.531628],"type":"Point"}
}