{
  "type": "Feature",
  "properties": {
    "addr:full":"Voorstraat 34 Brielle Zuid-Holland 3231 BJ",
    "addr:housenumber":"34",
    "addr:postcode":"3231 bj",
    "addr:street":"Voorstraat",
    "iso:country":"NL",
    "sg:address":"Voorstraat 34",
    "sg:city":"Brielle",
    "sg:classifiers":[
        {
            "category":"Shopping",
            "subcategory":"Clothing, Apparel, & Fashions",
            "type":"Retail Goods"
        }
    ],
    "sg:phone":"+31 181 412 359",
    "sg:postcode":"3231 BJ",
    "sg:province":"Zuid-Holland",
    "sg:tags":[
        "ondergoed",
        "lingerie"
    ],
    "wof:name":"Jolanda'S Lingerie",
    "wof:placetype":"venue"
},
  "geometry": {"coordinates":[4.165293,51.90303],"type":"Point"}
}