{
  "type": "Feature",
  "properties": {
    "addr:full":"Waalsteen 50 Wijk Bij Duurstede Utrecht 3961 XC",
    "addr:housenumber":"50",
    "addr:postcode":"3961 xc",
    "addr:street":"Waalsteen",
    "iso:country":"NL",
    "sg:address":"Waalsteen 50",
    "sg:city":"Wijk Bij Duurstede",
    "sg:orig_category":"Loodgieterswerk, Verwarming And Sanitaire Installaties",
    "sg:phone":"+31 343 597 222",
    "sg:postcode":"3961 XC",
    "sg:province":"Utrecht",
    "wof:name":"Wuma Onderhoud- En (Af)Bouwservice",
    "wof:placetype":"venue"
},
  "geometry": {"coordinates":[5.327842,51.976025],"type":"Point"}
}