{
  "type": "Feature",
  "properties": {
    "addr:full":"Top Naeffstraat 11 Gorinchem South Holland 4207 MT",
    "addr:housenumber":"11",
    "addr:postcode":"4207",
    "addr:street":"Top Naeffstraat;Mt",
    "iso:country":"NL",
    "sg:address":"Top Naeffstraat 11",
    "sg:city":"Gorinchem",
    "sg:orig_category":"Verzekeringen",
    "sg:phone":"+31 183 624 002",
    "sg:postcode":"4207 MT",
    "sg:province":"South Holland",
    "wof:name":"J H W Terpstra Pensioenadviesburo",
    "wof:placetype":"venue"
},
  "geometry": {"coordinates":[4.99608,51.834988],"type":"Point"}
}