{
  "type": "Feature",
  "properties": {
    "addr:full":"Lessingstr 47 Venlo Limburg 5924 CA",
    "addr:housenumber":"47",
    "addr:postcode":"5924 ca",
    "addr:street":"Lessingstr",
    "iso:country":"NL",
    "sg:address":"Lessingstr 47",
    "sg:city":"Venlo",
    "sg:orig_category":"Autorijscholen",
    "sg:phone":"+31 77 382 5746",
    "sg:postcode":"5924 CA",
    "sg:province":"Limburg",
    "wof:name":"Mulekom, S Van",
    "wof:placetype":"venue"
},
  "geometry": {"coordinates":[6.12597,51.366608],"type":"Point"}
}