{
  "type": "Feature",
  "properties": {
    "addr:full":"Zonnehof 9 Amersfoort Utrecht 3811 ND",
    "addr:housenumber":"9",
    "addr:postcode":"3811 nd",
    "addr:street":"Zonnehof",
    "iso:country":"NL",
    "sg:address":"Zonnehof 9",
    "sg:city":"Amersfoort",
    "sg:orig_category":"Marktonderzoekbureaus",
    "sg:phone":"+31 33 422 7373",
    "sg:postcode":"3811 ND",
    "sg:province":"Utrecht",
    "sg:website":"http://www.censydiam.com",
    "wof:name":"Censydiam Ned Bv",
    "wof:placetype":"venue"
},
  "geometry": {"coordinates":[5.383468,52.151577],"type":"Point"}
}