{
  "type": "Feature",
  "properties": {
    "addr:full":"Kleinzand 94 Sneek Provincie Friesland 8601 BK",
    "addr:housenumber":"94",
    "addr:postcode":"8601 bk",
    "addr:street":"Kleinzand;Provincie Friesland",
    "iso:country":"NL",
    "sg:address":"Kleinzand 94",
    "sg:city":"Sneek",
    "sg:classifiers":[
        {
            "category":"Travel",
            "subcategory":"Hotels & Motels",
            "type":"Entertainment"
        }
    ],
    "sg:phone":"+31 515 424 624",
    "sg:postcode":"8601 BK",
    "sg:province":"Provincie Friesland",
    "wof:name":"Mikrotel Sneek",
    "wof:placetype":"venue"
},
  "geometry": {"coordinates":[5.666087,53.032925],"type":"Point"}
}