{
  "type": "Feature",
  "properties": {
    "addr:full":"Regentesseln 20 Apeldoorn Gelderland 7316 AG",
    "addr:housenumber":"20",
    "addr:postcode":"7316",
    "addr:street":"Regentesseln;Gelderland",
    "iso:country":"NL",
    "sg:address":"Regentesseln 20",
    "sg:city":"Apeldoorn",
    "sg:orig_category":"Adviesbureaus Bedrijfsorganisatie",
    "sg:phone":"+31 55 576 1764",
    "sg:postcode":"7316 AG",
    "sg:province":"Gelderland",
    "wof:name":"Intermetzroo",
    "wof:placetype":"venue"
},
  "geometry": {"coordinates":[5.960027,52.220264],"type":"Point"}
}