{
  "type": "Feature",
  "properties": {
    "addr:full":"Postbus 30239 Rotterdam South Holland 3001 DE",
    "addr:housenumber":"30239",
    "addr:postcode":"3001 de",
    "addr:street":"Postbus",
    "iso:country":"NL",
    "sg:address":"Postbus 30239",
    "sg:city":"Rotterdam",
    "sg:orig_category":"On- Offshore",
    "sg:phone":"+31 10 405 1290",
    "sg:postcode":"3001 DE",
    "sg:province":"South Holland",
    "sg:website":"http://www.fairmount.nl",
    "wof:name":"Fairmount Marine Bv",
    "wof:placetype":"venue"
},
  "geometry": {"coordinates":[4.47075,51.922619],"type":"Point"}
}