{
  "type": "Feature",
  "properties": {
    "addr:full":"Kleveringwg 33 Delft South Holland 2616 LZ",
    "addr:housenumber":"33",
    "addr:postcode":"2616 lz",
    "addr:street":"Kleveringwg",
    "iso:country":"NL",
    "sg:address":"Kleveringwg 33",
    "sg:city":"Delft",
    "sg:orig_category":"Fitnesscentra",
    "sg:phone":"+31 15 256 1010",
    "sg:postcode":"2616 LZ",
    "sg:province":"South Holland",
    "wof:name":"Active Sports",
    "wof:placetype":"venue"
},
  "geometry": {"coordinates":[4.363942,52.025677],"type":"Point"}
}