{
  "type": "Feature",
  "properties": {
    "addr:full":"Morssngl 59 Leiden Zuid-Holland 2312 ES",
    "addr:housenumber":"59",
    "addr:postcode":"2312 es",
    "addr:street":"Morssngl",
    "iso:country":"NL",
    "sg:address":"Morssngl 59",
    "sg:city":"Leiden",
    "sg:orig_category":"Vertalers",
    "sg:phone":"+31 71 512 6405",
    "sg:postcode":"2312 ES",
    "sg:province":"Zuid-Holland",
    "wof:name":"Pols, Dr A",
    "wof:placetype":"venue"
},
  "geometry": {"coordinates":[4.49463,52.154572],"type":"Point"}
}