{
  "type": "Feature",
  "properties": {
    "addr:full":"Valkenhof 3 Ermelo Gelderland 3853 BN",
    "addr:housenumber":"3",
    "addr:postcode":"3853 bn",
    "addr:street":"Valkenhof;Gelderland",
    "iso:country":"NL",
    "sg:address":"Valkenhof 3",
    "sg:city":"Ermelo",
    "sg:orig_category":"Adviesbureaus",
    "sg:phone":"+31 341 553 334",
    "sg:postcode":"3853 BN",
    "sg:province":"Gelderland",
    "wof:name":"Olde Hartman, A",
    "wof:placetype":"venue"
},
  "geometry": {"coordinates":[5.599336,52.298012],"type":"Point"}
}