{
  "type": "Feature",
  "properties": {
    "addr:full":"Wismarwg 26 Groningen Groningen 9723 HB",
    "addr:housenumber":"26",
    "addr:postcode":"9723 hb",
    "addr:street":"Wismarwg",
    "iso:country":"NL",
    "sg:address":"Wismarwg 26",
    "sg:city":"Groningen",
    "sg:orig_category":"Koffie-Automaten",
    "sg:phone":"+31 50 542 6300",
    "sg:postcode":"9723 HB",
    "sg:province":"Groningen",
    "sg:website":"http://www.heslinga.nl",
    "wof:name":"Heslinga Haren Bv",
    "wof:placetype":"venue"
},
  "geometry": {"coordinates":[6.609012,53.219574],"type":"Point"}
}