{
  "type": "Feature",
  "properties": {
    "addr:full":"Bizetln 2 Apeldoorn Gelderland 7333 DN",
    "addr:housenumber":"2",
    "addr:postcode":"7333 dn",
    "addr:street":"Bizetln;Gelderland",
    "iso:country":"NL",
    "sg:address":"Bizetln 2",
    "sg:city":"Apeldoorn",
    "sg:classifiers":[
        {
            "category":"Retail",
            "subcategory":"Auto Repair",
            "type":"Services"
        }
    ],
    "sg:phone":"+31 55 541 3856",
    "sg:postcode":"7333 DN",
    "sg:province":"Gelderland",
    "sg:tags":[
        "garage"
    ],
    "wof:name":"Hoegen, M A",
    "wof:placetype":"venue"
},
  "geometry": {"coordinates":[5.97203,52.183609],"type":"Point"}
}