{
  "type": "Feature",
  "properties": {
    "iso:country":"NL",
    "sg:address":"Raadhuispln 4",
    "sg:city":"Hoogkarspel",
    "sg:orig_category":"Warenhuizen",
    "sg:phone":"+31 228 564 557",
    "sg:postcode":"1616 AV",
    "sg:province":"Noord-Holland",
    "wof:name":"Action",
    "wof:placetype":"venue"
},
  "geometry": {"coordinates":[5.1769208908,52.6953849792],"type":"Point"}
}