{
  "type": "Feature",
  "properties": {
    "addr:full":"Thamerwg 78 Uithoorn North Holland 1422 XL",
    "addr:housenumber":"78",
    "addr:postcode":"1422 xl",
    "addr:street":"Thamerwg",
    "iso:country":"NL",
    "sg:address":"Thamerwg 78",
    "sg:city":"Uithoorn",
    "sg:orig_category":"Metaalbewerking",
    "sg:phone":"+31 297 582 166",
    "sg:postcode":"1422 XL",
    "sg:province":"North Holland",
    "wof:name":"Klaassen, P H",
    "wof:placetype":"venue"
},
  "geometry": {"coordinates":[4.840298,52.240631],"type":"Point"}
}