{
  "type": "Feature",
  "properties": {
    "addr:full":"Gemeenlandsedk Z 18 Abbenbroek Zuid-Holland 3216 AH",
    "addr:housenumber":"18",
    "addr:postcode":"3216 ah",
    "iso:country":"NL",
    "sg:address":"Gemeenlandsedk Z 18",
    "sg:city":"Abbenbroek",
    "sg:orig_category":"Loodgieters",
    "sg:phone":"+31 181 669 299",
    "sg:postcode":"3216 AH",
    "sg:province":"Zuid-Holland",
    "wof:name":"John Vermeer",
    "wof:placetype":"venue"
},
  "geometry": {"coordinates":[4.241445,51.851315],"type":"Point"}
}