{
  "type": "Feature",
  "properties": {
    "iso:country":"NL",
    "sg:address":"Sondelerln 1",
    "sg:city":"Sondel",
    "sg:orig_category":"Machineonderhoud En -Reparatie",
    "sg:phone":"+31 514 603 709",
    "sg:postcode":"8565 HG",
    "sg:province":"Provincie Friesland",
    "wof:name":"Hospes",
    "wof:placetype":"venue"
},
  "geometry": {"coordinates":[5.594707,52.864552],"type":"Point"}
}