{
  "type": "Feature",
  "properties": {
    "addr:full":"Voorstr 4 Kockengen Utrecht 3628 AH",
    "addr:housenumber":"4",
    "addr:postcode":"3628 ah",
    "addr:street":"Voorstr",
    "iso:country":"NL",
    "sg:address":"Voorstr 4",
    "sg:city":"Kockengen",
    "sg:classifiers":[
        {
            "category":"Education",
            "subcategory":"School",
            "type":"Public Place"
        }
    ],
    "sg:phone":"+31 346 241 733",
    "sg:postcode":"3628 AH",
    "sg:province":"Utrecht",
    "sg:tags":[
        "studiebegeleiding",
        "en",
        "school-"
    ],
    "wof:name":"Hannah",
    "wof:placetype":"venue"
},
  "geometry": {"coordinates":[4.948572,52.147141],"type":"Point"}
}