{
  "type": "Feature",
  "properties": {
    "addr:full":"Binnenwg 7 Aardenburg Zeeland 4527 ED",
    "addr:housenumber":"7",
    "addr:postcode":"4527 ed",
    "addr:street":"Binnenwg",
    "iso:country":"NL",
    "sg:address":"Binnenwg 7",
    "sg:city":"Aardenburg",
    "sg:orig_category":"Verzekeringen - Verzekeringskantoren",
    "sg:phone":"+31 117 492 356",
    "sg:postcode":"4527 ED",
    "sg:province":"Zeeland",
    "wof:name":"Daansen",
    "wof:placetype":"venue"
},
  "geometry": {"coordinates":[3.471541,51.269775],"type":"Point"}
}