{
  "type": "Feature",
  "properties": {
    "iso:country":"NL",
    "sg:address":"Binnenwg 7",
    "sg:city":"Aardenburg",
    "sg:orig_category":"Verzekeringen - Verzekeringskantoren",
    "sg:phone":"+31 117 492 356",
    "sg:postcode":"4527 ED",
    "sg:province":"Zeeland",
    "wof:name":"Daansen",
    "wof:placetype":"venue"
},
  "geometry": {"coordinates":[3.471541,51.269775],"type":"Point"}
}