{
  "type": "Feature",
  "properties": {
    "iso:country":"NL",
    "sg:address":"Lebretshoeveweg 1",
    "sg:city":"Deelen",
    "sg:orig_category":"Technische Studies And Onderzoek",
    "sg:phone":"+31 55 506 1305",
    "sg:postcode":"6877 AA",
    "sg:province":"Gelderland",
    "wof:name":"Natuurmonumenten Deelerwoud",
    "wof:placetype":"venue"
},
  "geometry": {"coordinates":[-123.06697800000001,46.099079],"type":"Point"}
}