{
  "type": "Feature",
  "properties": {
    "addr:full":"Dorsvlegelstraat 34 Purmerend North Holland 1445 PB",
    "addr:housenumber":"34",
    "addr:postcode":"1445 pb",
    "addr:street":"Dorsvlegelstraat",
    "iso:country":"NL",
    "sg:address":"Dorsvlegelstraat 34",
    "sg:city":"Purmerend",
    "sg:orig_category":"Verhuur Diversen",
    "sg:phone":"+31 299 642 094",
    "sg:postcode":"1445 PB",
    "sg:province":"North Holland",
    "wof:name":"De Ooievaarslijn",
    "wof:placetype":"venue"
},
  "geometry": {"coordinates":[4.976813,52.502064],"type":"Point"}
}