{
  "type": "Feature",
  "properties": {
    "iso:country":"NL",
    "sg:address":"Raetmansweg 6",
    "sg:city":"Winterswijk Ratum",
    "sg:orig_category":"Boekhouders",
    "sg:phone":"+31 543 562 426",
    "sg:postcode":"7106 CD",
    "sg:province":"Gelderland",
    "wof:name":"Administratiekantoor Uwland",
    "wof:placetype":"venue"
},
  "geometry": {"coordinates":[6.799537,51.974625],"type":"Point"}
}