{
  "type": "Feature",
  "properties": {
    "addr:full":"Ambachtsstraat 13 Nijkerk Gld Gelderland 3861 RH",
    "addr:housenumber":"13",
    "addr:postcode":"3861 rh",
    "addr:street":"Ambachtsstraat;Gld Gelderland",
    "iso:country":"NL",
    "sg:address":"Ambachtsstraat 13",
    "sg:city":"Nijkerk Gld",
    "sg:orig_category":"Diverse Bedrijfsinstallaties Gh",
    "sg:phone":"+31 33 246 0404",
    "sg:postcode":"3861 RH",
    "sg:province":"Gelderland",
    "wof:name":"Ekato Bv",
    "wof:placetype":"venue"
},
  "geometry": {"coordinates":[5.481624,52.233932],"type":"Point"}
}