{
  "type": "Feature",
  "properties": {
    "iso:country":"NL",
    "sg:address":"Aukebaes 13",
    "sg:city":"Joure",
    "sg:orig_category":"Verzekeringen",
    "sg:phone":"+31 513 416 016",
    "sg:postcode":"8501 RP",
    "sg:province":"Friesland",
    "wof:name":"Grijpstra Partners Vof",
    "wof:placetype":"venue"
},
  "geometry": {"coordinates":[5.800996,52.969345],"type":"Point"}
}