{
  "type": "Feature",
  "properties": {
    "addr:full":"Tomeikerwg 55 Geleen Limburg 6161 RB",
    "addr:housenumber":"55",
    "addr:postcode":"6161 rb",
    "addr:street":"Tomeikerwg",
    "iso:country":"NL",
    "sg:address":"Tomeikerwg 55",
    "sg:city":"Geleen",
    "sg:orig_category":"Houtgroothandel Hardhout",
    "sg:phone":"+31 46 423 7979",
    "sg:postcode":"6161 RB",
    "sg:province":"Limburg",
    "sg:website":"http://www.prohout.nl",
    "wof:name":"Prohout Bv",
    "wof:placetype":"venue"
},
  "geometry": {"coordinates":[5.810846,50.958511],"type":"Point"}
}