{
  "type": "Feature",
  "properties": {
    "addr:full":"Bonenburgerlaan 32 Heerde Gelderland 8181 HG",
    "addr:housenumber":"32",
    "addr:postcode":"8181 hg",
    "addr:street":"Bonenburgerlaan;Gelderland",
    "iso:country":"NL",
    "sg:address":"Bonenburgerlaan 32",
    "sg:city":"Heerde",
    "sg:orig_category":"Meubelzaken, Woning- And Keukeninrichting",
    "sg:phone":"+31 578 692 685",
    "sg:postcode":"8181 HG",
    "sg:province":"Gelderland",
    "wof:name":"Van 'T Zand Meubelen",
    "wof:placetype":"venue"
},
  "geometry": {"coordinates":[6.04142,52.384995],"type":"Point"}
}