{
  "type": "Feature",
  "properties": {
    "addr:full":"De Lente 21 Breskens Zeeland 4511 PS",
    "addr:housenumber":"21",
    "addr:postcode":"4511 ps",
    "addr:street":"De Lente",
    "iso:country":"NL",
    "sg:address":"De Lente 21",
    "sg:city":"Breskens",
    "sg:orig_category":"Onroerende Goederen",
    "sg:phone":"+31 117 386 534",
    "sg:postcode":"4511 PS",
    "sg:province":"Zeeland",
    "wof:name":"Holger Kooman Bv",
    "wof:placetype":"venue"
},
  "geometry": {"coordinates":[3.559413,51.390862],"type":"Point"}
}