{
  "type": "Feature",
  "properties": {
    "addr:full":"Leidse Ryn 33 De Meern Utrecht 3454 PZ",
    "addr:housenumber":"33",
    "addr:postcode":"3454 pz",
    "addr:street":"Leidse Ryn",
    "iso:country":"NL",
    "sg:address":"Leidse Ryn 33",
    "sg:city":"De Meern",
    "sg:orig_category":"Administratie- En Boekhoudkantoren",
    "sg:phone":"+31 30 666 4866",
    "sg:postcode":"3454 PZ",
    "sg:province":"Utrecht",
    "sg:website":"http://www.lra.nl",
    "wof:name":"Leidsche Rijn Accountancy Bv",
    "wof:placetype":"venue"
},
  "geometry": {"coordinates":[5.059217,52.08157],"type":"Point"}
}