{
  "type": "Feature",
  "properties": {
    "addr:full":"Zanddk 5 Oostvoorne Zuid-Holland 3233 XJ",
    "addr:housenumber":"5",
    "addr:postcode":"3233 xj",
    "addr:street":"Zanddk",
    "iso:country":"NL",
    "sg:address":"Zanddk 5",
    "sg:city":"Oostvoorne",
    "sg:orig_category":"Jachthavens - Jachtwerven",
    "sg:phone":"+31 181 487 960",
    "sg:postcode":"3233 XJ",
    "sg:province":"Zuid-Holland",
    "wof:name":"Geijsman Bv, H",
    "wof:placetype":"venue"
},
  "geometry": {"coordinates":[4.106747,51.923759],"type":"Point"}
}