{
  "type": "Feature",
  "properties": {
    "iso:country":"NL",
    "sg:address":"Marktstraat 7",
    "sg:city":"Zevenaar",
    "sg:classifiers":[
        {
            "category":"Fast Food",
            "type":"Food & Drink"
        }
    ],
    "sg:phone":"+31 316 528 400",
    "sg:postcode":"6901 GS",
    "sg:province":"Gelderland",
    "sg:tags":[
        "afhaal",
        "restaurant"
    ],
    "wof:name":"Mini Resto Knaven",
    "wof:placetype":"venue"
},
  "geometry": {"coordinates":[6.076511,51.927879],"type":"Point"}
}