{
  "type": "Feature",
  "properties": {
    "addr:full":"Arkelhof 12 Zevenbergen North Brabant 4761 ML",
    "addr:housenumber":"12",
    "addr:postcode":"4761 ml",
    "addr:street":"Arkelhof",
    "iso:country":"NL",
    "sg:address":"Arkelhof 12",
    "sg:city":"Zevenbergen",
    "sg:orig_category":"Goederenvervoer Over De Weg",
    "sg:phone":"+31 168 330 718",
    "sg:postcode":"4761 ML",
    "sg:province":"North Brabant",
    "wof:name":"R. Van Haarlem",
    "wof:placetype":"venue"
},
  "geometry": {"coordinates":[4.588913,51.646072],"type":"Point"}
}