{
  "type": "Feature",
  "properties": {
    "addr:full":"Floraronde 21 Velserbroek Noord-Holland 1991 HH",
    "addr:housenumber":"21",
    "addr:postcode":"1991 hh",
    "addr:street":"Floraronde",
    "iso:country":"NL",
    "sg:address":"Floraronde 21",
    "sg:city":"Velserbroek",
    "sg:orig_category":"Autorijscholen",
    "sg:phone":"+31 23 539 3873",
    "sg:postcode":"1991 HH",
    "sg:province":"Noord-Holland",
    "wof:name":"Geerlings",
    "wof:placetype":"venue"
},
  "geometry": {"coordinates":[4.654239,52.433746],"type":"Point"}
}