{
  "type": "Feature",
  "properties": {
    "addr:full":"Middelie 91 Middelie Noord-Holland 1472 GT",
    "addr:housenumber":"91",
    "addr:postcode":"1472 gt",
    "addr:street":"Middelie",
    "iso:country":"NL",
    "sg:address":"Middelie 91",
    "sg:city":"Middelie",
    "sg:orig_category":"Artsen - Huisartsen",
    "sg:phone":"+31 299 621 350",
    "sg:postcode":"1472 GT",
    "sg:province":"Noord-Holland",
    "wof:name":"Souwer, I H",
    "wof:placetype":"venue"
},
  "geometry": {"coordinates":[5.016164,52.534927],"type":"Point"}
}