{
  "type": "Feature",
  "properties": {
    "addr:full":"Vd Hoevenstr 17 Naaldwijk Zuid-Holland 2671 EG",
    "addr:housenumber":"17",
    "addr:postcode":"2671 eg",
    "iso:country":"NL",
    "sg:address":"Vd Hoevenstr 17",
    "sg:city":"Naaldwijk",
    "sg:orig_category":"Verenigingsgebouwen",
    "sg:phone":"+31 174 625 776",
    "sg:postcode":"2671 EG",
    "sg:province":"Zuid-Holland",
    "wof:name":"Binnenhof, De",
    "wof:placetype":"venue"
},
  "geometry": {"coordinates":[4.206367,51.995911],"type":"Point"}
}