{
  "type": "Feature",
  "properties": {
    "addr:full":"Iepln 47 S Gravenhage Zuid-Holland 2565 LD",
    "addr:housenumber":"47;gravenhage",
    "addr:postcode":"2565 ld",
    "addr:street":"Iepln;S",
    "iso:country":"NL",
    "sg:address":"Iepln 47",
    "sg:city":"S Gravenhage",
    "sg:orig_category":"Journalisten Freelance",
    "sg:phone":"+31 70 362 0080",
    "sg:postcode":"2565 LD",
    "sg:province":"Zuid-Holland",
    "wof:name":"Oerlemans, H",
    "wof:placetype":"venue"
},
  "geometry": {"coordinates":[4.26129,52.076382],"type":"Point"}
}