{
  "type": "Feature",
  "properties": {
    "addr:full":"Blauwpoortsbrug 1A Leiden Zuid-Holland 2312 BV",
    "addr:housenumber":"1a",
    "addr:postcode":"2312 bv",
    "addr:street":"Blauwpoortsbrug",
    "iso:country":"NL",
    "sg:address":"Blauwpoortsbrug 1A",
    "sg:city":"Leiden",
    "sg:orig_category":"Bloemen And Planten",
    "sg:phone":"+31 71 512 7592",
    "sg:postcode":"2312 BV",
    "sg:province":"Zuid-Holland",
    "wof:name":"Bloemenboot De Watertuin",
    "wof:placetype":"venue"
},
  "geometry": {"coordinates":[4.485449,52.161842],"type":"Point"}
}