{
  "type": "Feature",
  "properties": {
    "addr:full":"Marskamp 3 Haaksbergen Overijssel 7482 KH",
    "addr:housenumber":"3",
    "addr:postcode":"7482 kh",
    "addr:street":"Marskamp",
    "iso:country":"NL",
    "sg:address":"Marskamp 3",
    "sg:city":"Haaksbergen",
    "sg:orig_category":"Paramedische Behandelingen",
    "sg:phone":"+31 53 572 6682",
    "sg:postcode":"7482 KH",
    "sg:province":"Overijssel",
    "wof:name":"Verloskundigenpraktijk",
    "wof:placetype":"venue"
},
  "geometry": {"coordinates":[6.721839,52.162697],"type":"Point"}
}