{
  "type": "Feature",
  "properties": {
    "addr:full":"Hollandseweg 20 Oudenhoorn South Holland 3227 CB",
    "addr:housenumber":"20",
    "addr:postcode":"3227 cb",
    "addr:street":"Hollandseweg",
    "iso:country":"NL",
    "sg:address":"Hollandseweg 20",
    "sg:city":"Oudenhoorn",
    "sg:orig_category":"Verzekeringen",
    "sg:phone":"+31 181 461 429",
    "sg:postcode":"3227 CB",
    "sg:province":"South Holland",
    "wof:name":"Assurantiekantoor Keijzerwaard Vof",
    "wof:placetype":"venue"
},
  "geometry": {"coordinates":[4.198567,51.832756],"type":"Point"}
}