{
  "type": "Feature",
  "properties": {
    "iso:country":"NL",
    "sg:address":"Hollandseweg 20",
    "sg:city":"Oudenhoorn",
    "sg:orig_category":"Verzekeringen",
    "sg:phone":"+31 181 461 429",
    "sg:postcode":"3227 CB",
    "sg:province":"South Holland",
    "wof:name":"Assurantiekantoor Keijzerwaard Vof",
    "wof:placetype":"venue"
},
  "geometry": {"coordinates":[4.198567,51.832756],"type":"Point"}
}