{
  "type": "Feature",
  "properties": {
    "addr:full":"Scheldekd 56/A Terneuzen Zeeland 4531 EJ",
    "addr:housenumber":"56 / a",
    "addr:postcode":"4531 ej",
    "addr:street":"Scheldekd",
    "iso:country":"NL",
    "sg:address":"Scheldekd 56/A",
    "sg:city":"Terneuzen",
    "sg:orig_category":"Administratie- En Boekhoudkantoren",
    "sg:phone":"+31 115 694 257",
    "sg:postcode":"4531 EJ",
    "sg:province":"Zeeland",
    "wof:name":"Lyppens",
    "wof:placetype":"venue"
},
  "geometry": {"coordinates":[3.827559,51.338146],"type":"Point"}
}