{
  "type": "Feature",
  "properties": {
    "addr:full":"Skilwei 17 Stiens Friesland 9051 AE",
    "addr:housenumber":"17",
    "addr:postcode":"9051 ae",
    "addr:street":"Skilwei",
    "iso:country":"NL",
    "sg:address":"Skilwei 17",
    "sg:city":"Stiens",
    "sg:orig_category":"Honden- En Kattentrimsalons",
    "sg:phone":"+31 58 257 3939",
    "sg:postcode":"9051 AE",
    "sg:province":"Friesland",
    "wof:name":"Qwispel",
    "wof:placetype":"venue"
},
  "geometry": {"coordinates":[5.754281,53.262707],"type":"Point"}
}