{
  "type": "Feature",
  "properties": {
    "addr:full":"Oranjeboomstraat 21 Westzaan North Holland 1551 BH",
    "addr:housenumber":"21",
    "addr:postcode":"1551 bh",
    "addr:street":"Oranjeboomstraat",
    "iso:country":"NL",
    "sg:address":"Oranjeboomstraat 21",
    "sg:city":"Westzaan",
    "sg:orig_category":"Schilderwerk",
    "sg:phone":"+31 75 670 1175",
    "sg:postcode":"1551 BH",
    "sg:province":"North Holland",
    "wof:name":"Silvio Schilderwerken",
    "wof:placetype":"venue"
},
  "geometry": {"coordinates":[4.76902,52.462223],"type":"Point"}
}