{
  "type": "Feature",
  "properties": {
    "addr:full":"Dr Timmersln 10 Beek En Donk North Brabant 5741 XH",
    "addr:housenumber":"10",
    "addr:postcode":"5741 xh",
    "iso:country":"NL",
    "sg:address":"Dr Timmersln 10",
    "sg:city":"Beek En Donk",
    "sg:orig_category":"Verloskundigen",
    "sg:phone":"+31 492 462 233",
    "sg:postcode":"5741 XH",
    "sg:province":"North Brabant",
    "wof:name":"Diesen & N P C Kreutzelman, W M H Van",
    "wof:placetype":"venue"
},
  "geometry": {"coordinates":[5.631363,51.528637],"type":"Point"}
}