{
  "type": "Feature",
  "properties": {
    "iso:country":"NL",
    "sg:address":"Maasstr 11",
    "sg:city":"Rotterdam",
    "sg:orig_category":"Adviesbureaus Bedrijfsorganisatie",
    "sg:phone":"+31 10 433 1911",
    "sg:postcode":"3016 DB",
    "sg:province":"Zuid-Holland",
    "wof:name":"Buitenlandse Werknemers Rijnmond, Sticht",
    "wof:placetype":"venue"
},
  "geometry": {"coordinates":[4.480801,51.908653],"type":"Point"}
}