{
  "type": "Feature",
  "properties": {
    "addr:full":"Dorpsstraat 172 Halsteren Noord-Brabant 4661 HV",
    "addr:housenumber":"172",
    "addr:postcode":"4661 hv",
    "addr:street":"Dorpsstraat",
    "iso:country":"NL",
    "sg:address":"Dorpsstraat 172",
    "sg:city":"Halsteren",
    "sg:classifiers":[
        {
            "category":"Fast Food",
            "type":"Food & Drink"
        }
    ],
    "sg:phone":"+31 164 682 940",
    "sg:postcode":"4661 HV",
    "sg:province":"Noord-Brabant",
    "sg:tags":[
        "afhaal",
        "restaurant"
    ],
    "wof:name":"Chin. Ind. Rest. Lotus",
    "wof:placetype":"venue"
},
  "geometry": {"coordinates":[4.272225,51.522453],"type":"Point"}
}