{
  "type": "Feature",
  "properties": {
    "iso:country":"NL",
    "sg:address":"Ondernemingswg 6",
    "sg:city":"Alphen Aan Den Ryn",
    "sg:orig_category":"Administratie- En Boekhoudkantoren",
    "sg:phone":"+31 172 490 393",
    "sg:postcode":"2404 HN",
    "sg:province":"Zuid-Holland",
    "wof:name":"Perfect Partners Administratiecons",
    "wof:placetype":"venue"
},
  "geometry": {"coordinates":[4.638941,52.138775],"type":"Point"}
}