{
  "type": "Feature",
  "properties": {
    "addr:full":"Casembrootlaan 28 Poeldijk Zuid-Holland 2685 AC",
    "addr:housenumber":"28",
    "addr:postcode":"2685 ac",
    "addr:street":"Casembrootlaan",
    "iso:country":"NL",
    "sg:address":"Casembrootlaan 28",
    "sg:city":"Poeldijk",
    "sg:orig_category":"Metaalwerken",
    "sg:phone":"+31 174 246 098",
    "sg:postcode":"2685 AC",
    "sg:province":"Zuid-Holland",
    "wof:name":"Montagebedrijf W. Middelburg",
    "wof:placetype":"venue"
},
  "geometry": {"coordinates":[4.20844,52.028152],"type":"Point"}
}