{
  "type": "Feature",
  "properties": {
    "iso:country":"NL",
    "sg:address":"Van Baerlestraat 86",
    "sg:city":"Dordrecht",
    "sg:orig_category":"Boekhouders",
    "sg:phone":"+31 78 614 4368",
    "sg:postcode":"3314 BK",
    "sg:province":"Zuid-Holland",
    "wof:name":"L.J. Van Valen Freelance",
    "wof:placetype":"venue"
},
  "geometry": {"coordinates":[4.659234,51.805393],"type":"Point"}
}