{
  "type": "Feature",
  "properties": {
    "addr:full":"Bouwlustlaan 97 'S Gravenhage Zuid-Holland 2544 JP",
    "addr:housenumber":"97",
    "addr:postcode":"2544 jp",
    "addr:street":"Bouwlustlaan;' S",
    "iso:country":"NL",
    "sg:address":"Bouwlustlaan 97",
    "sg:city":"'S Gravenhage",
    "sg:orig_category":"Fietshandelaren",
    "sg:phone":"+31 70 366 5772",
    "sg:postcode":"2544 JP",
    "sg:province":"Zuid-Holland",
    "wof:name":"Fa. Van Son En Zoon",
    "wof:placetype":"venue"
},
  "geometry": {"coordinates":[4.256479,52.044472],"type":"Point"}
}