{
  "type": "Feature",
  "properties": {
    "iso:country":"NL",
    "sg:address":"Van Den Burghweg 1",
    "sg:city":"Delft",
    "sg:orig_category":"Overheidsdiensten",
    "sg:phone":"+31 15 251 8518",
    "sg:postcode":"2628 CS",
    "sg:province":"Zuid-Holland",
    "wof:name":"Rijkswaterstaat Dienst Weg- En Waterbouwkunde",
    "wof:placetype":"venue"
},
  "geometry": {"coordinates":[4.3781638145,51.9981651306],"type":"Point"}
}