{
  "type": "Feature",
  "properties": {
    "addr:full":"Voorstr 27 Vianen Zh Utrecht 4132 AM",
    "addr:housenumber":"27",
    "addr:postcode":"zh;4132",
    "addr:street":"Voorstr",
    "iso:country":"NL",
    "sg:address":"Voorstr 27",
    "sg:city":"Vianen Zh",
    "sg:orig_category":"Wereldwinkels",
    "sg:phone":"+31 347 344 232",
    "sg:postcode":"4132 AM",
    "sg:province":"Utrecht",
    "wof:name":"Wereldwinkel",
    "wof:placetype":"venue"
},
  "geometry": {"coordinates":[5.0920147896,51.9950180054],"type":"Point"}
}