{
  "type": "Feature",
  "properties": {
    "addr:full":"Voorstraat 75 Brielle South Holland 3231 BG",
    "addr:housenumber":"75",
    "addr:postcode":"3231",
    "addr:street":"Voorstraat",
    "iso:country":"NL",
    "sg:address":"Voorstraat 75",
    "sg:city":"Brielle",
    "sg:orig_category":"Woninginrichting",
    "sg:phone":"+31 181 486 477",
    "sg:postcode":"3231 BG",
    "sg:province":"South Holland",
    "wof:name":"Maison, La",
    "wof:placetype":"venue"
},
  "geometry": {"coordinates":[4.1656079292,51.9045677185],"type":"Point"}
}