{
  "type": "Feature",
  "properties": {
    "iso:country":"NL",
    "sg:address":"Hunsstr 42A",
    "sg:city":"Voerendaal",
    "sg:orig_category":"Wijnkelders En Tapperijen",
    "sg:phone":"+31 45 575 4461",
    "sg:postcode":"6367 JL",
    "sg:province":"Limburg",
    "sg:website":"http://www.fromberg.nl",
    "wof:name":"Fromberg",
    "wof:placetype":"venue"
},
  "geometry": {"coordinates":[5.9517240524,50.8543128967],"type":"Point"}
}