{
  "type": "Feature",
  "properties": {
    "addr:full":"Middendijk 53 Nijbroek Gelderland 7397 NC",
    "addr:housenumber":"53;7397",
    "addr:street":"Middendijk;Gelderland",
    "iso:country":"NL",
    "sg:address":"Middendijk 53",
    "sg:city":"Nijbroek",
    "sg:classifiers":[
        {
            "category":"Education",
            "subcategory":"Preschool",
            "type":"Public Place"
        }
    ],
    "sg:phone":"+31 571 292 162",
    "sg:postcode":"7397 NC",
    "sg:province":"Gelderland",
    "sg:tags":[
        "kleuteronderwijs",
        "basis-"
    ],
    "wof:name":"Christelijke Basisschool Ten Holtens Erve",
    "wof:placetype":"venue"
},
  "geometry": {"coordinates":[6.0623950958,52.2941627502],"type":"Point"}
}