{
  "type": "Feature",
  "properties": {
    "addr:full":"Uilenvliet 20 Zwijndrecht Zuid-Holland 3333 BT",
    "addr:housenumber":"20",
    "addr:postcode":"3333 bt",
    "addr:street":"Uilenvliet",
    "iso:country":"NL",
    "sg:address":"Uilenvliet 20",
    "sg:city":"Zwijndrecht",
    "sg:orig_category":"Homeopathie",
    "sg:phone":"+31 78 612 7872",
    "sg:postcode":"3333 BT",
    "sg:province":"Zuid-Holland",
    "wof:name":"Toorn, A Van",
    "wof:placetype":"venue"
},
  "geometry": {"coordinates":[4.630963,51.807827],"type":"Point"}
}