{
  "type": "Feature",
  "properties": {
    "addr:full":"Rudonk 14 Breda Noord-Brabant 4824 AJ",
    "addr:housenumber":"14",
    "addr:postcode":"4824 aj",
    "addr:street":"Rudonk",
    "iso:country":"NL",
    "sg:address":"Rudonk 14",
    "sg:city":"Breda",
    "sg:orig_category":"Kunststoffen- Verwerkende Industrie",
    "sg:phone":"+31 76 542 4316",
    "sg:postcode":"4824 AJ",
    "sg:province":"Noord-Brabant",
    "wof:name":"Harlinka Production Bv",
    "wof:placetype":"venue"
},
  "geometry": {"coordinates":[4.7499399185,51.6125907898],"type":"Point"}
}