{
  "type": "Feature",
  "properties": {
    "iso:country":"NL",
    "sg:address":"Cartesiusstraat 2",
    "sg:city":"'S Gravenhage",
    "sg:classifiers":[
        {
            "category":"Education",
            "subcategory":"Preschool",
            "type":"Public Place"
        }
    ],
    "sg:phone":"+31 70 363 6219",
    "sg:postcode":"2562 SK",
    "sg:province":"South Holland",
    "sg:tags":[
        "kleuteronderwijs",
        "basis-"
    ],
    "wof:name":"De Dondersteentjes",
    "wof:placetype":"venue"
},
  "geometry": {"coordinates":[4.285294,52.074066],"type":"Point"}
}