{
  "type": "Feature",
  "properties": {
    "addr:full":"Aan De Twijnerij 3 Vaals Limburg 6291 KM",
    "addr:housenumber":"3",
    "addr:street":"Aan De Twijnerij;6291 Km",
    "iso:country":"NL",
    "sg:address":"Aan De Twijnerij 3",
    "sg:city":"Vaals",
    "sg:orig_category":"Vertaal- And Tolkenbureaus",
    "sg:phone":"+31 43 306 4991",
    "sg:postcode":"6291 KM",
    "sg:province":"Limburg",
    "wof:name":"Badorf Vd Akker Texts & Translations",
    "wof:placetype":"venue"
},
  "geometry": {"coordinates":[6.014834,50.776398],"type":"Point"}
}