{
  "type": "Feature",
  "properties": {
    "addr:full":"Oostkade 60 Huizen North Holland 1274 ND",
    "addr:housenumber":"60",
    "addr:postcode":"1274 nd",
    "addr:street":"Oostkade",
    "iso:country":"NL",
    "sg:address":"Oostkade 60",
    "sg:city":"Huizen",
    "sg:orig_category":"Paramedische Behandelingen",
    "sg:phone":"+31 35 526 8715",
    "sg:postcode":"1274 ND",
    "sg:province":"North Holland",
    "wof:name":"Verloskundige Praktijk",
    "wof:placetype":"venue"
},
  "geometry": {"coordinates":[5.26571,52.295803],"type":"Point"}
}