{
  "type": "Feature",
  "properties": {
    "addr:full":"Weenixhof 13 Alkmaar North Holland 1816 KM",
    "addr:housenumber":"13",
    "addr:postcode":"1816 km",
    "addr:street":"Weenixhof",
    "iso:country":"NL",
    "sg:address":"Weenixhof 13",
    "sg:city":"Alkmaar",
    "sg:orig_category":"Wijnkoperijen En -Groothandel",
    "sg:phone":"+31 72 520 7313",
    "sg:postcode":"1816 KM",
    "sg:province":"North Holland",
    "wof:name":"Jamiro",
    "wof:placetype":"venue"
},
  "geometry": {"coordinates":[4.727645874,52.6302261353],"type":"Point"}
}