{
  "type": "Feature",
  "properties": {
    "addr:full":"Lorentzlaan 9 Ijsselstein Ut Utrecht 3401 MX",
    "addr:housenumber":"9",
    "addr:postcode":"3401 mx",
    "addr:street":"Lorentzlaan",
    "iso:country":"NL",
    "sg:address":"Lorentzlaan 9",
    "sg:city":"Ijsselstein Ut",
    "sg:orig_category":"Farmaceutische Producten Gh",
    "sg:phone":"+31 30 687 7494",
    "sg:postcode":"3401 MX",
    "sg:province":"Utrecht",
    "wof:name":"Madiis International Bv",
    "wof:placetype":"venue"
},
  "geometry": {"coordinates":[5.061781,52.013519],"type":"Point"}
}