{
  "type": "Feature",
  "properties": {
    "addr:full":"Westblaak 226 Rotterdam Zuid-Holland 3012 KP",
    "addr:housenumber":"226",
    "addr:postcode":"3012 kp",
    "addr:street":"Westblaak",
    "iso:country":"NL",
    "sg:address":"Westblaak 226",
    "sg:city":"Rotterdam",
    "sg:orig_category":"Milieu",
    "sg:phone":"+31 10 280 5666",
    "sg:postcode":"3012 KP",
    "sg:province":"Zuid-Holland",
    "sg:website":"http://www.cea.nl",
    "wof:name":"Cea",
    "wof:placetype":"venue"
},
  "geometry": {"coordinates":[4.474301,51.916153],"type":"Point"}
}