{
  "type": "Feature",
  "properties": {
    "addr:full":"Goudsesingel 86 Rotterdam Zuid-Holland 3011 KD",
    "addr:housenumber":"86",
    "addr:postcode":"3011 kd",
    "addr:street":"Goudsesingel",
    "iso:country":"NL",
    "sg:address":"Goudsesingel 86",
    "sg:city":"Rotterdam",
    "sg:orig_category":"Boekenuitgeverijen",
    "sg:phone":"+31 10 412 5708",
    "sg:postcode":"3011 KD",
    "sg:province":"Zuid-Holland",
    "wof:name":"Uitgeverij Motorboot Bv",
    "wof:placetype":"venue"
},
  "geometry": {"coordinates":[4.493073,51.923855],"type":"Point"}
}