{
  "type": "Feature",
  "properties": {
    "addr:full":"Lysterbeshof 83 Papendrecht Zuid-Holland 3355 CC",
    "addr:housenumber":"83",
    "addr:postcode":"3355 cc",
    "addr:street":"Lysterbeshof",
    "iso:country":"NL",
    "sg:address":"Lysterbeshof 83",
    "sg:city":"Papendrecht",
    "sg:orig_category":"Adviesbureaus Bedrijfsorganisatie",
    "sg:phone":"+31 78 615 7344",
    "sg:postcode":"3355 CC",
    "sg:province":"Zuid-Holland",
    "sg:website":"http://www.rmcbv.com",
    "wof:name":"R M C Bv",
    "wof:placetype":"venue"
},
  "geometry": {"coordinates":[4.69992,51.83881],"type":"Point"}
}