{
  "type": "Feature",
  "properties": {
    "iso:country":"NL",
    "sg:address":"K Koningsstr 14",
    "sg:city":"Amsterdam",
    "sg:orig_category":"Artsen - Huisartsen",
    "sg:phone":"+31 20 620 8074",
    "sg:postcode":"1011 GA",
    "sg:province":"Noord-Holland",
    "wof:name":"Grooff, Dr B G M",
    "wof:placetype":"venue"
},
  "geometry": {"coordinates":[-74.170609,42.972134],"type":"Point"}
}