{
  "type": "Feature",
  "properties": {
    "addr:full":"Insulindelaan 111 Eindhoven North Brabant 5642 CV",
    "addr:housenumber":"111",
    "addr:postcode":"5642 cv",
    "addr:street":"Insulindelaan",
    "iso:country":"NL",
    "sg:address":"Insulindelaan 111",
    "sg:city":"Eindhoven",
    "sg:orig_category":"Werving And Selectie Van Vast Personeel",
    "sg:phone":"+31 40 292 4000",
    "sg:postcode":"5642 CV",
    "sg:province":"North Brabant",
    "wof:name":"Berendsen & Partners",
    "wof:placetype":"venue"
},
  "geometry": {"coordinates":[5.504032135,51.4427566528],"type":"Point"}
}