{
  "type": "Feature",
  "properties": {
    "addr:full":"Zadelmakerstr 20 Velserbroek Noord-Holland 1991 JE",
    "addr:housenumber":"20",
    "addr:postcode":"1991 je",
    "addr:street":"Zadelmakerstr",
    "iso:country":"NL",
    "sg:address":"Zadelmakerstr 20",
    "sg:city":"Velserbroek",
    "sg:orig_category":"Belastingconsulenten/ Belastingadviseurs",
    "sg:phone":"+31 23 538 8440",
    "sg:postcode":"1991 JE",
    "sg:province":"Noord-Holland",
    "wof:name":"Stevens Glas",
    "wof:placetype":"venue"
},
  "geometry": {"coordinates":[4.653969,52.435848],"type":"Point"}
}