{
  "type": "Feature",
  "properties": {
    "addr:full":"Capellestraat 9 Steenwijk Overijssel 8331 LM",
    "addr:housenumber":"9",
    "addr:postcode":"8331 lm",
    "addr:street":"Capellestraat",
    "iso:country":"NL",
    "sg:address":"Capellestraat 9",
    "sg:city":"Steenwijk",
    "sg:orig_category":"Goederenvervoer Over De Weg",
    "sg:phone":"+31 521 515 448",
    "sg:postcode":"8331 LM",
    "sg:province":"Overijssel",
    "wof:name":"Firma Gebroeders Groen",
    "wof:placetype":"venue"
},
  "geometry": {"coordinates":[6.103638,52.788284],"type":"Point"}
}