{
  "type": "Feature",
  "properties": {
    "iso:country":"NL",
    "sg:address":"Leusderweg 226",
    "sg:city":"Amersfoort",
    "sg:orig_category":"Kappers",
    "sg:phone":"+31 33 461 5827",
    "sg:postcode":"3817 KG",
    "sg:province":"Utrecht",
    "wof:name":"Hair Maxx",
    "wof:placetype":"venue"
},
  "geometry": {"coordinates":[5.3790111542,52.1414260864],"type":"Point"}
}