{
  "type": "Feature",
  "properties": {
    "addr:full":"Veenman 28 Wilnis Utrecht 3648 KT",
    "addr:housenumber":"28",
    "addr:postcode":"3648 kt",
    "addr:street":"Veenman",
    "iso:country":"NL",
    "sg:address":"Veenman 28",
    "sg:city":"Wilnis",
    "sg:orig_category":"Boekhouders",
    "sg:phone":"+31 297 288 477",
    "sg:postcode":"3648 KT",
    "sg:province":"Utrecht",
    "wof:name":"Administratiekantoor Moen",
    "wof:placetype":"venue"
},
  "geometry": {"coordinates":[4.889231,52.20517],"type":"Point"}
}