{
  "type": "Feature",
  "properties": {
    "addr:full":"Cruyscampln 2 Heiloo Noord-Holland 1851 XB",
    "addr:housenumber":"2",
    "addr:postcode":"1851 xb",
    "addr:street":"Cruyscampln",
    "iso:country":"NL",
    "sg:address":"Cruyscampln 2",
    "sg:city":"Heiloo",
    "sg:orig_category":"Homeopathie",
    "sg:phone":"+31 72 533 9894",
    "sg:postcode":"1851 XB",
    "sg:province":"Noord-Holland",
    "wof:name":"Dood, H J C De",
    "wof:placetype":"venue"
},
  "geometry": {"coordinates":[4.702781,52.595463],"type":"Point"}
}