{
  "type": "Feature",
  "properties": {
    "addr:full":"Diepenbrockhof 3 Hoorn Nh Noord-Holland 1628 SL",
    "addr:housenumber":"3",
    "addr:postcode":"1628 sl",
    "addr:street":"Diepenbrockhof",
    "iso:country":"NL",
    "sg:address":"Diepenbrockhof 3",
    "sg:city":"Hoorn Nh",
    "sg:orig_category":"Loodgieterswerk, Verwarming And Sanitaire Installaties",
    "sg:phone":"+31 229 239 998",
    "sg:postcode":"1628 SL",
    "sg:province":"Noord-Holland",
    "wof:name":"Heruer",
    "wof:placetype":"venue"
},
  "geometry": {"coordinates":[5.098051,52.65081],"type":"Point"}
}