{
  "type": "Feature",
  "properties": {
    "iso:country":"NL",
    "sg:address":"Klipper 76",
    "sg:city":"Barendrecht",
    "sg:orig_category":"Verzekeringen",
    "sg:phone":"+31 180 613 511",
    "sg:postcode":"2991 KL",
    "sg:province":"Zuid-Holland",
    "wof:name":"Assurantiekantoor F Kleine",
    "wof:placetype":"venue"
},
  "geometry": {"coordinates":[4.546477,51.848652],"type":"Point"}
}