{
  "type": "Feature",
  "properties": {
    "iso:country":"NL",
    "sg:address":"Rembrandtweg 111",
    "sg:city":"Ridderkerk",
    "sg:orig_category":"Diverse Consumentenartikelen Gh",
    "sg:phone":"+31 180 426 880",
    "sg:postcode":"2981 CV",
    "sg:province":"South Holland",
    "wof:name":"Asiart",
    "wof:placetype":"venue"
},
  "geometry": {"coordinates":[4.596544,51.870663],"type":"Point"}
}