{
  "type": "Feature",
  "properties": {
    "iso:country":"NL",
    "sg:address":"Verwoldsewg 14",
    "sg:city":"Laren Gld",
    "sg:orig_category":"Scholen Voor Basisonderwijs",
    "sg:phone":"+31 573 401 876",
    "sg:postcode":"7245 AH",
    "sg:province":"Gelderland",
    "sg:website":"http://www.expage.com/pages/debranink",
    "wof:name":"Branink Openb Daltonsch, De",
    "wof:placetype":"venue"
},
  "geometry": {"coordinates":[6.36788,52.19305],"type":"Point"}
}