{
  "type": "Feature",
  "properties": {
    "addr:full":"Dom Dubuissonstr 2 Berkel Enschot Noord-Brabant 5056 HN",
    "addr:housenumber":"2",
    "addr:postcode":"5056 hn",
    "addr:street":"Berkel",
    "iso:country":"NL",
    "sg:address":"Dom Dubuissonstr 2",
    "sg:city":"Berkel Enschot",
    "sg:orig_category":"Manueel Therapeuten",
    "sg:phone":"+31 13 533 3307",
    "sg:postcode":"5056 HN",
    "sg:province":"Noord-Brabant",
    "sg:website":"http://www.fysio-berkelenschot.nl",
    "wof:name":"Roosmalen-Festen, I Van",
    "wof:placetype":"venue"
},
  "geometry": {"coordinates":[5.144266,51.589657],"type":"Point"}
}