{
  "type": "Feature",
  "properties": {
    "addr:full":"De Hoeve 3 Randwijk Gelderland 6668 AZ",
    "addr:housenumber":"3",
    "addr:postcode":"6668",
    "addr:street":"De Hoeve;Gelderland",
    "iso:country":"NL",
    "sg:address":"De Hoeve 3",
    "sg:city":"Randwijk",
    "sg:orig_category":"Zuivelproducten And Spijsoli?n Gh",
    "sg:phone":"+31 488 491 287",
    "sg:postcode":"6668 AZ",
    "sg:province":"Gelderland",
    "wof:name":"De Hoeve",
    "wof:placetype":"venue"
},
  "geometry": {"coordinates":[5.722659,51.947407],"type":"Point"}
}