{
  "type": "Feature",
  "properties": {
    "addr:full":"Kanaalstraat 41 Amsterdam Noord-Holland 1054 WZ",
    "addr:housenumber":"41",
    "addr:postcode":"1054 wz",
    "addr:street":"Kanaalstraat",
    "iso:country":"NL",
    "sg:address":"Kanaalstraat 41",
    "sg:city":"Amsterdam",
    "sg:orig_category":"Werving And Selectie Van Vast Personeel",
    "sg:phone":"+31 20 618 3982",
    "sg:postcode":"1054 WZ",
    "sg:province":"Noord-Holland",
    "wof:name":"Syner3",
    "wof:placetype":"venue"
},
  "geometry": {"coordinates":[4.8655657768,52.3625717163],"type":"Point"}
}