{
  "type": "Feature",
  "properties": {
    "addr:full":"Wenckebachweg 111 Amsterdam Noord-Holland 1096 AL",
    "addr:housenumber":"111",
    "addr:postcode":"1096 al",
    "addr:street":"Wenckebachweg",
    "iso:country":"NL",
    "sg:address":"Wenckebachweg 111",
    "sg:city":"Amsterdam",
    "sg:orig_category":"Glaszetten",
    "sg:phone":"+31 20 665 0205",
    "sg:postcode":"1096 AL",
    "sg:province":"Noord-Holland",
    "wof:name":"Diemen Quick Glasservice",
    "wof:placetype":"venue"
},
  "geometry": {"coordinates":[4.927674,52.337765],"type":"Point"}
}