{
  "type": "Feature",
  "properties": {
    "addr:full":"Steeland 14 Westdorpe Zeeland 4554 BS",
    "addr:housenumber":"14",
    "addr:postcode":"4554 bs",
    "addr:street":"Steeland",
    "iso:country":"NL",
    "sg:address":"Steeland 14",
    "sg:city":"Westdorpe",
    "sg:orig_category":"Kinderopvang Behalve Thuis",
    "sg:phone":"+31 115 451 324",
    "sg:postcode":"4554 BS",
    "sg:province":"Zeeland",
    "wof:name":"Peuterspeelzaal Olleke-Bolleke",
    "wof:placetype":"venue"
},
  "geometry": {"coordinates":[3.824626,51.231564],"type":"Point"}
}