{
  "type": "Feature",
  "properties": {
    "addr:full":"Grt Terkooyen 3 Bladel Noord-Brabant 5531 NV",
    "addr:housenumber":"3",
    "addr:postcode":"5531 nv",
    "addr:street":"Terkooyen",
    "iso:country":"NL",
    "sg:address":"Grt Terkooyen 3",
    "sg:city":"Bladel",
    "sg:orig_category":"Elektronica - Ontwikkeling En Groothandel",
    "sg:phone":"+31 497 369 517",
    "sg:postcode":"5531 NV",
    "sg:province":"Noord-Brabant",
    "wof:name":"Duis Holding Bv",
    "wof:placetype":"venue"
},
  "geometry": {"coordinates":[5.232829,51.34684],"type":"Point"}
}