{
  "type": "Feature",
  "properties": {
    "iso:country":"NL",
    "sg:address":"V Roosmalenpln 49",
    "sg:city":"S Hertogenbosch",
    "sg:orig_category":"Bloemen En Planten",
    "sg:phone":"+31 73 613 1077",
    "sg:postcode":"5213 GD",
    "sg:province":"Noord-Brabant",
    "wof:name":"Fleurette",
    "wof:placetype":"venue"
},
  "geometry": {"coordinates":[5.29824,51.69075],"type":"Point"}
}