{
  "type": "Feature",
  "properties": {
    "addr:full":"Kilkd 6 Keet Dordrecht South Holland 3316 BC",
    "addr:housenumber":"6",
    "addr:postcode":"3316 bc",
    "addr:street":"Kilkd;Keet",
    "iso:country":"NL",
    "sg:address":"Kilkd 6 Keet",
    "sg:city":"Dordrecht",
    "sg:orig_category":"Verkeersbureaus",
    "sg:phone":"+31 78 652 0888",
    "sg:postcode":"3316 BC",
    "sg:province":"South Holland",
    "wof:name":"Linden Bv, Van Der",
    "wof:placetype":"venue"
},
  "geometry": {"coordinates":[4.656506,51.811916],"type":"Point"}
}