{
  "type": "Feature",
  "properties": {
    "addr:full":"Boven Oosterdiep 61 Veendam Groningen 9641 JN",
    "addr:housenumber":"61",
    "addr:postcode":"9641 jn",
    "addr:street":"Boven Oosterdiep",
    "iso:country":"NL",
    "sg:address":"Boven Oosterdiep 61",
    "sg:city":"Veendam",
    "sg:orig_category":"Huishoudapparatuur, Televisies And Radio'S",
    "sg:phone":"+31 598 617 458",
    "sg:postcode":"9641 JN",
    "sg:province":"Groningen",
    "wof:name":"Ypma Electronica",
    "wof:placetype":"venue"
},
  "geometry": {"coordinates":[6.875516,53.10022],"type":"Point"}
}