{
  "type": "Feature",
  "properties": {
    "iso:country":"NL",
    "sg:address":"Dam 42",
    "sg:city":"Middelburg",
    "sg:orig_category":"Film-, Tv- And Videoproductie",
    "sg:phone":"+31 118 650 160",
    "sg:postcode":"4331 GK",
    "sg:province":"Zeeland",
    "wof:name":"Mop",
    "wof:placetype":"venue"
},
  "geometry": {"coordinates":[3.619285,51.50066],"type":"Point"}
}