{
  "type": "Feature",
  "properties": {
    "addr:full":"Heistraat 18 Gastel Noord-Brabant 6028 RE",
    "addr:housenumber":"18",
    "addr:postcode":"6028 re",
    "addr:street":"Heistraat",
    "iso:country":"NL",
    "sg:address":"Heistraat 18",
    "sg:city":"Gastel",
    "sg:orig_category":"Metaalbekleding And -Behandeling",
    "sg:phone":"+31 495 494 212",
    "sg:postcode":"6028 RE",
    "sg:province":"Noord-Brabant",
    "wof:name":"Lakspuiterij Verhoeven",
    "wof:placetype":"venue"
},
  "geometry": {"coordinates":[5.553242,51.287601],"type":"Point"}
}