{
  "type": "Feature",
  "properties": {
    "addr:full":"Nieuwehuizen 6 Assen Drenthe 9401 JT",
    "addr:housenumber":"6",
    "addr:postcode":"9401 jt",
    "addr:street":"Nieuwehuizen",
    "iso:country":"NL",
    "sg:address":"Nieuwehuizen 6",
    "sg:city":"Assen",
    "sg:orig_category":"Kledingzaken",
    "sg:phone":"+31 592 310 120",
    "sg:postcode":"9401 JT",
    "sg:province":"Drenthe",
    "wof:name":"Ad Scalas",
    "wof:placetype":"venue"
},
  "geometry": {"coordinates":[6.563838,52.995514],"type":"Point"}
}