{
  "type": "Feature",
  "properties": {
    "addr:full":"Kleine Beer 12 Bleiswijk Zuid-Holland 2665 WR",
    "addr:housenumber":"12",
    "addr:postcode":"2665 wr",
    "addr:street":"Kleine Beer",
    "iso:country":"NL",
    "sg:address":"Kleine Beer 12",
    "sg:city":"Bleiswijk",
    "sg:orig_category":"Meubelreparatie And -Restauratie",
    "sg:phone":"+31 10 521 6858",
    "sg:postcode":"2665 WR",
    "sg:province":"Zuid-Holland",
    "wof:name":"P.N.M. De Jong",
    "wof:placetype":"venue"
},
  "geometry": {"coordinates":[4.544571,52.012695],"type":"Point"}
}