{
  "type": "Feature",
  "properties": {
    "addr:full":"Lombardstr 5 Gorinchem Zuid-Holland 4201 BH",
    "addr:housenumber":"5",
    "addr:postcode":"4201 bh",
    "addr:street":"Lombardstr",
    "iso:country":"NL",
    "sg:address":"Lombardstr 5",
    "sg:city":"Gorinchem",
    "sg:orig_category":"Artsen - Huisartsen",
    "sg:phone":"+31 183 632 122",
    "sg:postcode":"4201 BH",
    "sg:province":"Zuid-Holland",
    "wof:name":"Griffioen, J P",
    "wof:placetype":"venue"
},
  "geometry": {"coordinates":[4.978619,51.8284],"type":"Point"}
}