{
  "type": "Feature",
  "properties": {
    "addr:full":"C De Wittstr 40 Wassenaar South Holland 2242 LW",
    "addr:housenumber":"40",
    "addr:postcode":"2242 lw",
    "addr:street":"C",
    "iso:country":"NL",
    "sg:address":"C De Wittstr 40",
    "sg:city":"Wassenaar",
    "sg:orig_category":"Administratie- En Boekhoudkantoren",
    "sg:phone":"+31 70 511 6592",
    "sg:postcode":"2242 LW",
    "sg:province":"South Holland",
    "wof:name":"Kruk Bv, A C Van Der",
    "wof:placetype":"venue"
},
  "geometry": {"coordinates":[4.398884,52.145309],"type":"Point"}
}