{
  "type": "Feature",
  "properties": {
    "addr:full":"Lagewg 23 Burgh Haamstede Zeeland 4328 RR",
    "addr:housenumber":"23",
    "addr:postcode":"4328 rr",
    "addr:street":"Lagewg;Haamstede",
    "iso:country":"NL",
    "sg:address":"Lagewg 23",
    "sg:city":"Burgh Haamstede",
    "sg:classifiers":[
        {
            "category":"Banks & Credit Unions",
            "subcategory":"Investment Brokerage",
            "type":"Services"
        }
    ],
    "sg:phone":"+31 111 651 356",
    "sg:postcode":"4328 RR",
    "sg:province":"Zeeland",
    "sg:tags":[
        "pension"
    ],
    "wof:name":"Maas, J Van Der",
    "wof:placetype":"venue"
},
  "geometry": {"coordinates":[3.710627,51.674397],"type":"Point"}
}