{
  "type": "Feature",
  "properties": {
    "addr:full":"Kagerdreef 180 Sassenheim Zuid-Holland 2172 HR",
    "addr:housenumber":"180",
    "addr:postcode":"2172 hr",
    "addr:street":"Kagerdreef",
    "iso:country":"NL",
    "sg:address":"Kagerdreef 180",
    "sg:city":"Sassenheim",
    "sg:orig_category":"Verpakkingen En Verpakkingsmaterialen",
    "sg:phone":"+31 252 425 746",
    "sg:postcode":"2172 HR",
    "sg:province":"Zuid-Holland",
    "wof:name":"B & R Holland",
    "wof:placetype":"venue"
},
  "geometry": {"coordinates":[4.533402,52.221626],"type":"Point"}
}