{
  "type": "Feature",
  "properties": {
    "addr:full":"Hooftstraat 70B Alphen Aan Den Rijn South Holland 2406 GL",
    "addr:housenumber":"70b",
    "addr:postcode":"2406 gl",
    "addr:street":"Hooftstraat",
    "iso:country":"NL",
    "sg:address":"Hooftstraat 70B",
    "sg:city":"Alphen Aan Den Rijn",
    "sg:orig_category":"Banket",
    "sg:phone":"+31 172 479 262",
    "sg:postcode":"2406 GL",
    "sg:province":"South Holland",
    "wof:name":"Multivlaai",
    "wof:placetype":"venue"
},
  "geometry": {"coordinates":[4.663678,52.132267],"type":"Point"}
}