{
  "type": "Feature",
  "properties": {
    "addr:full":"Milheezestraat 16 Tilburg Noord-Brabant 5045 EA",
    "addr:housenumber":"16",
    "addr:postcode":"5045 ea",
    "addr:street":"Milheezestraat",
    "iso:country":"NL",
    "sg:address":"Milheezestraat 16",
    "sg:city":"Tilburg",
    "sg:orig_category":"Reinigingsdiensten",
    "sg:phone":"+31 13 571 9065",
    "sg:postcode":"5045 EA",
    "sg:province":"Noord-Brabant",
    "wof:name":"Bruurs",
    "wof:placetype":"venue"
},
  "geometry": {"coordinates":[4.985725,51.593777],"type":"Point"}
}