{
  "type": "Feature",
  "properties": {
    "addr:full":"Hoofdstr 7 Gorredyk Provincie Friesland 8401 BT",
    "addr:housenumber":"7",
    "addr:postcode":"8401 bt",
    "addr:street":"Hoofdstr;Provincie Friesland",
    "iso:country":"NL",
    "sg:address":"Hoofdstr 7",
    "sg:city":"Gorredyk",
    "sg:classifiers":[
        {
            "category":"Personal",
            "subcategory":"Nail Salon",
            "type":"Services"
        }
    ],
    "sg:phone":"+31 513 461 789",
    "sg:postcode":"8401 BT",
    "sg:province":"Provincie Friesland",
    "sg:tags":[
        "pedicure"
    ],
    "wof:name":"Lilian Stuy",
    "wof:placetype":"venue"
},
  "geometry": {"coordinates":[6.065071,53.003937],"type":"Point"}
}