{
  "type": "Feature",
  "properties": {
    "iso:country":"NL",
    "sg:address":"De Stede 3",
    "sg:city":"'S Gravenhage",
    "sg:orig_category":"Meubelzaken, Woning- And Keukeninrichting",
    "sg:phone":"+31 70 367 2372",
    "sg:postcode":"2543 BG",
    "sg:province":"South Holland",
    "wof:name":"Boom Meubelen & Woningtextiel",
    "wof:placetype":"venue"
},
  "geometry": {"coordinates":[4.260556,52.043018],"type":"Point"}
}