{
  "type": "Feature",
  "properties": {
    "addr:full":"Ceintuurbaan 8 Deventer Overijssel 7415 AL",
    "addr:housenumber":"8",
    "addr:postcode":"7415 al",
    "addr:street":"Ceintuurbaan",
    "iso:country":"NL",
    "sg:address":"Ceintuurbaan 8",
    "sg:city":"Deventer",
    "sg:orig_category":"Adviesbureaus Bedrijfsorganisatie",
    "sg:phone":"+31 570 627 116",
    "sg:postcode":"7415 AL",
    "sg:province":"Overijssel",
    "wof:name":"Interkulturele Kommunikatie",
    "wof:placetype":"venue"
},
  "geometry": {"coordinates":[6.165263,52.262367],"type":"Point"}
}