{
  "type": "Feature",
  "properties": {
    "iso:country":"NL",
    "sg:address":"Walmolen 8",
    "sg:city":"Maassluis",
    "sg:orig_category":"Verlichtingsartikelen - Groothandel",
    "sg:phone":"+31 10 590 0039",
    "sg:postcode":"3146 CR",
    "sg:province":"Zuid-Holland",
    "wof:name":"Hlm",
    "wof:placetype":"venue"
},
  "geometry": {"coordinates":[4.231052,51.940281],"type":"Point"}
}