{
  "type": "Feature",
  "properties": {
    "addr:full":"Noordbroeksterstr 66 Sappemeer Groningen 9611 BJ",
    "addr:housenumber":"66",
    "addr:postcode":"9611 bj",
    "addr:street":"Noordbroeksterstr",
    "iso:country":"NL",
    "sg:address":"Noordbroeksterstr 66",
    "sg:city":"Sappemeer",
    "sg:orig_category":"Bloemen En Planten - Groothandel",
    "sg:phone":"+31 598 399 508",
    "sg:postcode":"9611 BJ",
    "sg:province":"Groningen",
    "wof:name":"Koeleman, P A M",
    "wof:placetype":"venue"
},
  "geometry": {"coordinates":[6.8087201118,53.1668395996],"type":"Point"}
}