{
  "type": "Feature",
  "properties": {
    "addr:full":"Batshoek 50 Enschede NL.08 7546 LA",
    "addr:housenumber":"50;7546",
    "addr:street":"Batshoek;La",
    "iso:country":"NL",
    "sg:address":"Batshoek 50",
    "sg:city":"Enschede",
    "sg:orig_category":"Scheepvaartmijen",
    "sg:phone":"+31 53 477 7314",
    "sg:postcode":"7546 LA",
    "sg:province":"NL.08",
    "wof:name":"Kirk, R H",
    "wof:placetype":"venue"
},
  "geometry": {"coordinates":[6.858358,52.199654],"type":"Point"}
}