{
  "type": "Feature",
  "properties": {
    "addr:full":"Hoverhofwg 106 Venlo Limburg 5926 RE",
    "addr:housenumber":"106",
    "addr:postcode":"5926 re",
    "iso:country":"NL",
    "sg:address":"Hoverhofwg 106",
    "sg:city":"Venlo",
    "sg:orig_category":"Bloemen En Planten",
    "sg:phone":"+31 77 387 3035",
    "sg:postcode":"5926 RE",
    "sg:province":"Limburg",
    "wof:name":"Serra Inverno",
    "wof:placetype":"venue"
},
  "geometry": {"coordinates":[6.117868,51.360664],"type":"Point"}
}