{
  "type": "Feature",
  "properties": {
    "addr:full":"Brouwersbos 25 Prinsenbeek Noord-Brabant 4841 CH",
    "addr:housenumber":"25",
    "addr:postcode":"4841",
    "addr:street":"Brouwersbos",
    "iso:country":"NL",
    "sg:address":"Brouwersbos 25",
    "sg:city":"Prinsenbeek",
    "sg:orig_category":"Adviesbureaus Bedrijfsorganisatie",
    "sg:phone":"+31 76 541 3192",
    "sg:postcode":"4841 CH",
    "sg:province":"Noord-Brabant",
    "wof:name":"Perin & Partn",
    "wof:placetype":"venue"
},
  "geometry": {"coordinates":[4.707569,51.595524],"type":"Point"}
}