{
  "type": "Feature",
  "properties": {
    "addr:full":"De Ynfeart 7-210 Heerenveen Friesland 8447 GM",
    "addr:housenumber":"7-210",
    "addr:postcode":"8447 gm",
    "addr:street":"De Ynfeart",
    "iso:country":"NL",
    "sg:address":"De Ynfeart 7-210",
    "sg:city":"Heerenveen",
    "sg:classifiers":[
        {
            "category":"Retail",
            "subcategory":"Auto Repair",
            "type":"Services"
        }
    ],
    "sg:phone":"+31 513 615 042",
    "sg:postcode":"8447 GM",
    "sg:province":"Friesland",
    "sg:tags":[
        "garage"
    ],
    "wof:name":"Rijpma, Erik",
    "wof:placetype":"venue"
},
  "geometry": {"coordinates":[5.892242,52.970333],"type":"Point"}
}