{
  "type": "Feature",
  "properties": {
    "addr:full":"H Dunantwg 2 Leeuwarden Friesland 8934 AD",
    "addr:housenumber":"2",
    "addr:postcode":"8934 ad",
    "iso:country":"NL",
    "sg:address":"H Dunantwg 2",
    "sg:city":"Leeuwarden",
    "sg:orig_category":"Ziekenhuizen, Sanatoria, Verpleeghuizen",
    "sg:phone":"+31 58 286 6260",
    "sg:postcode":"8934 AD",
    "sg:province":"Friesland",
    "wof:name":"Revalidatie Friesland",
    "wof:placetype":"venue"
},
  "geometry": {"coordinates":[5.806805,53.188816],"type":"Point"}
}