{
  "type": "Feature",
  "properties": {
    "iso:country":"NL",
    "sg:address":"Jachthaven 1",
    "sg:city":"Herkingen",
    "sg:orig_category":"Sportverenigingen En Ontspannings- Verenigingen",
    "sg:phone":"+31 187 669 623",
    "sg:postcode":"3249 AX",
    "sg:province":"Zuid-Holland",
    "wof:name":"Herkingen Watersport Ver",
    "wof:placetype":"venue"
},
  "geometry": {"coordinates":[4.084176,51.707996],"type":"Point"}
}