{
  "type": "Feature",
  "properties": {
    "addr:full":"Cliostr 40 Amsterdam Noord-Holland 1077 KJ",
    "addr:housenumber":"40",
    "addr:postcode":"1077 kj",
    "addr:street":"Cliostr",
    "iso:country":"NL",
    "sg:address":"Cliostr 40",
    "sg:city":"Amsterdam",
    "sg:orig_category":"Scholen Voor Basisonderwijs",
    "sg:phone":"+31 20 679 9012",
    "sg:postcode":"1077 KJ",
    "sg:province":"Noord-Holland",
    "wof:name":"Eerste Openluchtsch",
    "wof:placetype":"venue"
},
  "geometry": {"coordinates":[4.874219,52.347523],"type":"Point"}
}