{
  "type": "Feature",
  "properties": {
    "addr:full":"Verlengde Oosterdiep Oz 107 Barger Compascuum Drenthe 7884 RE",
    "addr:housenumber":"107",
    "addr:postcode":"7884 re",
    "addr:street":"Verlengde Oosterdiep Oz",
    "iso:country":"NL",
    "sg:address":"Verlengde Oosterdiep Oz 107",
    "sg:city":"Barger Compascuum",
    "sg:orig_category":"Kappers",
    "sg:phone":"+31 591 349 033",
    "sg:postcode":"7884 RE",
    "sg:province":"Drenthe",
    "wof:name":"G H Wolken",
    "wof:placetype":"venue"
},
  "geometry": {"coordinates":[7.0426459312,52.7550735474],"type":"Point"}
}