{
  "type": "Feature",
  "properties": {
    "addr:full":"Jaspisstr 16 Groningen Groningen 9743 JW",
    "addr:housenumber":"16",
    "addr:postcode":"9743 jw",
    "addr:street":"Jaspisstr",
    "iso:country":"NL",
    "sg:address":"Jaspisstr 16",
    "sg:city":"Groningen",
    "sg:orig_category":"Autorijscholen",
    "sg:phone":"+31 50 314 5635",
    "sg:postcode":"9743 JW",
    "sg:province":"Groningen",
    "sg:website":"http://www.bj-srijopleiding.nl",
    "wof:name":"Bj'S Rijopleiding",
    "wof:placetype":"venue"
},
  "geometry": {"coordinates":[6.526808,53.22757],"type":"Point"}
}