{
  "type": "Feature",
  "properties": {
    "addr:full":"Grt Staat 25 Maastricht Limburg 6211 CT",
    "addr:housenumber":"25",
    "addr:postcode":"6211 ct",
    "addr:street":"Staat",
    "iso:country":"NL",
    "sg:address":"Grt Staat 25",
    "sg:city":"Maastricht",
    "sg:orig_category":"Kinderkleding",
    "sg:phone":"+31 43 326 1218",
    "sg:postcode":"6211 CT",
    "sg:province":"Limburg",
    "wof:name":"Benneton",
    "wof:placetype":"venue"
},
  "geometry": {"coordinates":[5.69114,50.849731],"type":"Point"}
}