{
  "type": "Feature",
  "properties": {
    "addr:full":"Graafseweg 51 Nijmegen Gelderland 6512 BR",
    "addr:housenumber":"51",
    "addr:postcode":"6512 br",
    "addr:street":"Graafseweg;Gelderland",
    "iso:country":"NL",
    "sg:address":"Graafseweg 51",
    "sg:city":"Nijmegen",
    "sg:orig_category":"Kantoorartikelen",
    "sg:phone":"+31 24 323 2280",
    "sg:postcode":"6512 BR",
    "sg:province":"Gelderland",
    "wof:name":"Ideska Bv Kantoor- En Projectinrichting",
    "wof:placetype":"venue"
},
  "geometry": {"coordinates":[5.8556017876,51.8400917053],"type":"Point"}
}