{
  "type": "Feature",
  "properties": {
    "addr:full":"Predikheerenpoort 8 Den Bosch Noord-Brabant 5211 NK",
    "addr:housenumber":"8",
    "addr:postcode":"5211 nk",
    "addr:street":"Predikheerenpoort",
    "iso:country":"NL",
    "sg:address":"Predikheerenpoort 8",
    "sg:city":"Den Bosch",
    "sg:orig_category":"Fotostudio'S And Fotografen",
    "sg:phone":"+31 73 614 2080",
    "sg:postcode":"5211 NK",
    "sg:province":"Noord-Brabant",
    "wof:name":"Foto Rick Wezenaar",
    "wof:placetype":"venue"
},
  "geometry": {"coordinates":[5.29824,51.69075],"type":"Point"}
}