{
  "type": "Feature",
  "properties": {
    "iso:country":"NL",
    "sg:address":"Diepers 30",
    "sg:city":"Heeze",
    "sg:orig_category":"Verpakkingsmachines",
    "sg:phone":"+31 40 224 0284",
    "sg:postcode":"5591 LT",
    "sg:province":"North Brabant",
    "wof:name":"Berg, Van Den",
    "wof:placetype":"venue"
},
  "geometry": {"coordinates":[5.570015,51.382633],"type":"Point"}
}