{
  "type": "Feature",
  "properties": {
    "iso:country":"NL",
    "sg:address":"Goudsesingel 16",
    "sg:city":"Rotterdam",
    "sg:orig_category":"Kappers",
    "sg:phone":"+31 10 411 9138",
    "sg:postcode":"3011 KB",
    "sg:province":"South Holland",
    "wof:name":"Em Je Kappers",
    "wof:placetype":"venue"
},
  "geometry": {"coordinates":[4.4935998917,51.9239501953],"type":"Point"}
}