{
  "type": "Feature",
  "properties": {
    "addr:full":"Kraaiennest 62 Amsterdam Zuidoost North Holland 1104 CD",
    "addr:housenumber":"62",
    "addr:postcode":"1104 cd",
    "addr:street":"Kraaiennest",
    "iso:country":"NL",
    "sg:address":"Kraaiennest 62",
    "sg:city":"Amsterdam Zuidoost",
    "sg:orig_category":"Bloemen And Planten",
    "sg:phone":"+31 20 690 0663",
    "sg:postcode":"1104 CD",
    "sg:province":"North Holland",
    "wof:name":"George Witt",
    "wof:placetype":"venue"
},
  "geometry": {"coordinates":[4.980207,52.316978],"type":"Point"}
}