{
  "type": "Feature",
  "properties": {
    "addr:full":"Nw Leliestr 30 Amsterdam Noord-Holland 1015 SR",
    "addr:housenumber":"30;1015",
    "addr:postcode":"sr",
    "iso:country":"NL",
    "sg:address":"Nw Leliestr 30",
    "sg:city":"Amsterdam",
    "sg:orig_category":"Meubelmakerijen",
    "sg:phone":"+31 20 620 8990",
    "sg:postcode":"1015 SR",
    "sg:province":"Noord-Holland",
    "wof:name":"Lumineus",
    "wof:placetype":"venue"
},
  "geometry": {"coordinates":[4.882887,52.375862],"type":"Point"}
}