{
  "type": "Feature",
  "properties": {
    "addr:full":"Jufferenstr 11 Elburg Gelderland 8081 CP",
    "addr:housenumber":"11",
    "addr:postcode":"8081 cp",
    "addr:street":"Jufferenstr;Gelderland",
    "iso:country":"NL",
    "sg:address":"Jufferenstr 11",
    "sg:city":"Elburg",
    "sg:orig_category":"Elektronica - Ontwikkeling En Groothandel",
    "sg:phone":"+31 525 683 434",
    "sg:postcode":"8081 CP",
    "sg:province":"Gelderland",
    "wof:name":"Vecom",
    "wof:placetype":"venue"
},
  "geometry": {"coordinates":[5.835642,52.447926],"type":"Point"}
}