{
  "type": "Feature",
  "properties": {
    "addr:full":"Schepery 13 Teteringen North Brabant 4847 EZ",
    "addr:housenumber":"13",
    "addr:postcode":"4847 ez",
    "addr:street":"Schepery",
    "iso:country":"NL",
    "sg:address":"Schepery 13",
    "sg:city":"Teteringen",
    "sg:orig_category":"Bibliotheken En Leeszalen Openbare",
    "sg:phone":"+31 76 587 8811",
    "sg:postcode":"4847 EZ",
    "sg:province":"North Brabant",
    "wof:name":"Openb Bibliotheek",
    "wof:placetype":"venue"
},
  "geometry": {"coordinates":[4.822414,51.609707],"type":"Point"}
}