{
  "type": "Feature",
  "properties": {
    "iso:country":"NL",
    "sg:address":"Loosduinse Hoofdstraat 174",
    "sg:city":"'S Gravenhage",
    "sg:orig_category":"Wasserettes And Stomerijen",
    "sg:phone":"+31 70 397 9279",
    "sg:postcode":"2552 AL",
    "sg:province":"Zuid-Holland",
    "wof:name":"Wassalon Elma",
    "wof:placetype":"venue"
},
  "geometry": {"coordinates":[4.2379331589,52.0540008545],"type":"Point"}
}