{
  "type": "Feature",
  "properties": {
    "iso:country":"NL",
    "sg:address":"Wilhelminastr 28",
    "sg:city":"Didam",
    "sg:orig_category":"Fietsen En Bromfietsen",
    "sg:phone":"+31 316 294 498",
    "sg:postcode":"6942 BL",
    "sg:province":"Gelderland",
    "wof:name":"Alexander",
    "wof:placetype":"venue"
},
  "geometry": {"coordinates":[6.126315,51.937477],"type":"Point"}
}