{
  "type": "Feature",
  "properties": {
    "iso:country":"NL",
    "sg:address":"Sweelinckplein 17",
    "sg:city":"Zwolle",
    "sg:orig_category":"Onderhoud And Reparatie Kantoorapparatuur",
    "sg:phone":"+31 38 452 6066",
    "sg:postcode":"8031 BA",
    "sg:province":"NL.08",
    "wof:name":"Alpha Computers",
    "wof:placetype":"venue"
},
  "geometry": {"coordinates":[6.08261,52.532261],"type":"Point"}
}