{
  "type": "Feature",
  "properties": {
    "addr:full":"Rennemigstraat 47 Heerlen Limburg 6413 BS",
    "addr:housenumber":"47",
    "addr:postcode":"6413 bs",
    "addr:street":"Rennemigstraat",
    "iso:country":"NL",
    "sg:address":"Rennemigstraat 47",
    "sg:city":"Heerlen",
    "sg:orig_category":"Farmaceutische Producten Gh",
    "sg:phone":"+31 45 522 5126",
    "sg:postcode":"6413 BS",
    "sg:province":"Limburg",
    "wof:name":"Sanchez Val Alarm",
    "wof:placetype":"venue"
},
  "geometry": {"coordinates":[5.953237,50.910126],"type":"Point"}
}