{
  "type": "Feature",
  "properties": {
    "addr:full":"Pr Marykeln 6 Ouderkerk Amstel North Holland 1191 CA",
    "addr:housenumber":"6",
    "addr:postcode":"1191 ca",
    "addr:street":"Ouderkerk Amstel",
    "iso:country":"NL",
    "sg:address":"Pr Marykeln 6",
    "sg:city":"Ouderkerk Amstel",
    "sg:orig_category":"Beeldende Kunstenaars",
    "sg:phone":"+31 20 496 4042",
    "sg:postcode":"1191 CA",
    "sg:province":"North Holland",
    "wof:name":"Sanders, A",
    "wof:placetype":"venue"
},
  "geometry": {"coordinates":[4.904776,52.296631],"type":"Point"}
}