{
  "type": "Feature",
  "properties": {
    "iso:country":"NL",
    "sg:address":"De Passage 14",
    "sg:city":"Mydrecht",
    "sg:orig_category":"Wereldwinkels",
    "sg:phone":"+31 297 293 799",
    "sg:postcode":"3641 AK",
    "sg:province":"Utrecht",
    "wof:name":"Wereldwinkel",
    "wof:placetype":"venue"
},
  "geometry": {"coordinates":[4.8617801666,52.2057800293],"type":"Point"}
}