{
  "type": "Feature",
  "properties": {
    "addr:full":"Munsel 78 Boxtel Noord-Brabant 5283 TN",
    "addr:housenumber":"78",
    "addr:postcode":"5283",
    "addr:street":"Munsel",
    "iso:country":"NL",
    "sg:address":"Munsel 78",
    "sg:city":"Boxtel",
    "sg:orig_category":"Administratie- En Boekhoudkantoren",
    "sg:phone":"+31 411 683 427",
    "sg:postcode":"5283 TN",
    "sg:province":"Noord-Brabant",
    "wof:name":"Dun, Van",
    "wof:placetype":"venue"
},
  "geometry": {"coordinates":[5.328344,51.597038],"type":"Point"}
}