{
  "type": "Feature",
  "properties": {
    "addr:full":"Kerkstraat 12 Maastricht Limburg 6223 BK",
    "addr:housenumber":"12",
    "addr:postcode":"6223 bk",
    "addr:street":"Kerkstraat",
    "iso:country":"NL",
    "sg:address":"Kerkstraat 12",
    "sg:city":"Maastricht",
    "sg:orig_category":"Verlichting And Huishoudartikelen",
    "sg:phone":"+31 43 363 2110",
    "sg:postcode":"6223 BK",
    "sg:province":"Limburg",
    "wof:name":"C. Gielissen",
    "wof:placetype":"venue"
},
  "geometry": {"coordinates":[5.688597,50.877201],"type":"Point"}
}