{
  "type": "Feature",
  "properties": {
    "addr:full":"Beekstraat 34 Apeldoorn Gelderland 7311 LG",
    "addr:housenumber":"34",
    "addr:postcode":"7311 lg",
    "addr:street":"Beekstraat;Gelderland",
    "iso:country":"NL",
    "sg:address":"Beekstraat 34",
    "sg:city":"Apeldoorn",
    "sg:orig_category":"Kappers",
    "sg:phone":"+31 55 521 3738",
    "sg:postcode":"7311 LG",
    "sg:province":"Gelderland",
    "wof:name":"Maison Jacques",
    "wof:placetype":"venue"
},
  "geometry": {"coordinates":[5.966134,52.214111],"type":"Point"}
}