{
  "type": "Feature",
  "properties": {
    "addr:full":"Wolfskooi 7 Oss Noord-Brabant 5345 MH",
    "addr:housenumber":"7",
    "addr:postcode":"5345 mh",
    "addr:street":"Wolfskooi",
    "iso:country":"NL",
    "sg:address":"Wolfskooi 7",
    "sg:city":"Oss",
    "sg:classifiers":[
        {
            "category":"Food & Beverages",
            "subcategory":"Fruits & Vegetables",
            "type":"Retail Goods"
        }
    ],
    "sg:phone":"+31 412 655 046",
    "sg:postcode":"5345 MH",
    "sg:province":"Noord-Brabant",
    "sg:tags":[
        "groenten"
    ],
    "wof:name":"Van Der Heijden Vof",
    "wof:placetype":"venue"
},
  "geometry": {"coordinates":[-91.22442599999999,44.577396],"type":"Point"}
}