{
  "type": "Feature",
  "properties": {
    "addr:full":"Brinkmannpassage 5 Haarlem North Holland 2011 NZ",
    "addr:housenumber":"5",
    "addr:postcode":"2011 nz",
    "addr:street":"Brinkmannpassage",
    "iso:country":"NL",
    "sg:address":"Brinkmannpassage 5",
    "sg:city":"Haarlem",
    "sg:classifiers":[
        {
            "category":"Food & Beverages",
            "subcategory":"Fruits & Vegetables",
            "type":"Retail Goods"
        }
    ],
    "sg:phone":"+31 23 531 1934",
    "sg:postcode":"2011 NZ",
    "sg:province":"North Holland",
    "sg:tags":[
        "groenten"
    ],
    "wof:name":"De Fruitenier Van Der Plas",
    "wof:placetype":"venue"
},
  "geometry": {"coordinates":[4.635689,52.381737],"type":"Point"}
}