{
  "type": "Feature",
  "properties": {
    "addr:full":"Postbus 1436 Roosendaal Noord-Holland 4700 BK",
    "addr:housenumber":"1436",
    "addr:postcode":"4700 bk",
    "addr:street":"Postbus",
    "iso:country":"NL",
    "sg:address":"Postbus 1436",
    "sg:city":"Roosendaal",
    "sg:orig_category":"Sportverenigingen En Ontspannings- Verenigingen",
    "sg:phone":"+31 165 320 955",
    "sg:postcode":"4700 BK",
    "sg:province":"Noord-Holland",
    "sg:website":"http://www.tref.nl/roosendaal/enpc/default.htm",
    "wof:name":"Eerste Ned Parachutisten Club, De",
    "wof:placetype":"venue"
},
  "geometry": {"coordinates":[4.45767,51.531403],"type":"Point"}
}