{
  "type": "Feature",
  "properties": {
    "iso:country":"NL",
    "sg:address":"Textielwg 20",
    "sg:city":"Culemborg",
    "sg:orig_category":"Meubelen - Fabrieken En Groothandel",
    "sg:phone":"+31 345 514 641",
    "sg:postcode":"4104 AM",
    "sg:province":"Gelderland",
    "wof:name":"Drenth Buighout, Van",
    "wof:placetype":"venue"
},
  "geometry": {"coordinates":[5.21893,51.939571],"type":"Point"}
}