{
  "type": "Feature",
  "properties": {
    "iso:country":"NL",
    "sg:address":"Rijksweg-West 66",
    "sg:city":"Arnhem",
    "sg:classifiers":[
        {
            "category":"Food & Beverages",
            "subcategory":"Fruits & Vegetables",
            "type":"Retail Goods"
        }
    ],
    "sg:phone":"+31 26 381 9261",
    "sg:postcode":"6842 BE",
    "sg:province":"Gelderland",
    "sg:tags":[
        "groenten"
    ],
    "wof:name":"W.C. Van Der Schaft En Zoon",
    "wof:placetype":"venue"
},
  "geometry": {"coordinates":[5.885001,51.960419],"type":"Point"}
}