{
  "type": "Feature",
  "properties": {
    "addr:full":"Chassestraat 71 Amsterdam Noord-Holland 1057 JA",
    "addr:housenumber":"71",
    "addr:postcode":"1057 ja",
    "addr:street":"Chassestraat",
    "iso:country":"NL",
    "sg:address":"Chassestraat 71",
    "sg:city":"Amsterdam",
    "sg:orig_category":"Kantoorapparatuur Gh",
    "sg:phone":"+31 20 612 3905",
    "sg:postcode":"1057 JA",
    "sg:province":"Noord-Holland",
    "wof:name":"Kantoormachinehandel A Vlasman",
    "wof:placetype":"venue"
},
  "geometry": {"coordinates":[4.8611168861,52.3697357178],"type":"Point"}
}