{
  "type": "Feature",
  "properties": {
    "addr:full":"M L Kingln 130 Diemen Noord-Holland 1111 LK",
    "addr:housenumber":"130",
    "addr:postcode":"1111 lk",
    "addr:street":"M",
    "iso:country":"NL",
    "sg:address":"M L Kingln 130",
    "sg:city":"Diemen",
    "sg:orig_category":"Vertaalbureaus",
    "sg:phone":"+31 20 600 5544",
    "sg:postcode":"1111 LK",
    "sg:province":"Noord-Holland",
    "wof:name":"Tradital",
    "wof:placetype":"venue"
},
  "geometry": {"coordinates":[4.964805,52.34132],"type":"Point"}
}