{
  "type": "Feature",
  "properties": {
    "addr:full":"Haagweg 6 Breda North Brabant 4814 GD",
    "addr:housenumber":"6",
    "addr:postcode":"4814 gd",
    "addr:street":"Haagweg",
    "iso:country":"NL",
    "sg:address":"Haagweg 6",
    "sg:city":"Breda",
    "sg:classifiers":[
        {
            "category":"Fast Food",
            "type":"Food & Drink"
        }
    ],
    "sg:phone":"+31 76 521 6241",
    "sg:postcode":"4814 GD",
    "sg:province":"North Brabant",
    "sg:tags":[
        "afhaal",
        "restaurant"
    ],
    "wof:name":"Het Smulhuis",
    "wof:placetype":"venue"
},
  "geometry": {"coordinates":[4.762705,51.585743],"type":"Point"}
}