{
  "type": "Feature",
  "properties": {
    "addr:full":"Grotestr 58 Eibergen Gelderland 7151 BD",
    "addr:housenumber":"58",
    "addr:postcode":"7151 bd",
    "addr:street":"Grotestr;Gelderland",
    "iso:country":"NL",
    "sg:address":"Grotestr 58",
    "sg:city":"Eibergen",
    "sg:orig_category":"Bibliotheken En Leeszalen Openbare",
    "sg:phone":"+31 545 471 353",
    "sg:postcode":"7151 BD",
    "sg:province":"Gelderland",
    "wof:name":"Openb Bibliotheek",
    "wof:placetype":"venue"
},
  "geometry": {"coordinates":[6.647124,52.102879],"type":"Point"}
}