{
  "type": "Feature",
  "properties": {
    "iso:country":"NL",
    "sg:address":"Damweg 30",
    "sg:city":"Ridderkerk",
    "sg:orig_category":"Verhuur Gereedschapsmachines And Gereedschappen",
    "sg:phone":"+31 78 681 4200",
    "sg:postcode":"2989 AD",
    "sg:province":"Zuid-Holland",
    "wof:name":"Maarleveld",
    "wof:placetype":"venue"
},
  "geometry": {"coordinates":[4.641653,51.854088],"type":"Point"}
}