{
  "type": "Feature",
  "properties": {
    "iso:country":"NL",
    "sg:address":"Dorpsstraat 60",
    "sg:city":"Jisp",
    "sg:orig_category":"Verhuur Bouwmachines",
    "sg:phone":"+31 75 642 3240",
    "sg:postcode":"1546 LK",
    "sg:province":"Noord-Holland",
    "wof:name":"Ron Mak",
    "wof:placetype":"venue"
},
  "geometry": {"coordinates":[4.856338,52.507095],"type":"Point"}
}