{
  "type": "Feature",
  "properties": {
    "addr:full":"Oranjelaan 88 Diepenveen Overijssel 7431 AE",
    "addr:housenumber":"88",
    "addr:postcode":"7431 ae",
    "addr:street":"Oranjelaan",
    "iso:country":"NL",
    "sg:address":"Oranjelaan 88",
    "sg:city":"Diepenveen",
    "sg:classifiers":[
        {
            "category":"Fast Food",
            "type":"Food & Drink"
        }
    ],
    "sg:phone":"+31 570 591 634",
    "sg:postcode":"7431 AE",
    "sg:province":"Overijssel",
    "sg:tags":[
        "afhaal",
        "restaurant"
    ],
    "wof:name":"Cafetaria De Komeet",
    "wof:placetype":"venue"
},
  "geometry": {"coordinates":[6.149304,52.284523],"type":"Point"}
}