{
  "type": "Feature",
  "properties": {
    "iso:country":"NL",
    "sg:address":"Engelenweg 20",
    "sg:city":"Loenen Gld",
    "sg:orig_category":"Banken And Kredietinstellingen",
    "sg:phone":"+31 55 505 8500",
    "sg:postcode":"7371 AM",
    "sg:province":"Gelderland",
    "wof:name":"Rabobank",
    "wof:placetype":"venue"
},
  "geometry": {"coordinates":[6.018624,52.119614],"type":"Point"}
}