{
  "type": "Feature",
  "properties": {
    "iso:country":"NL",
    "sg:address":"Nachtegaalln 16A",
    "sg:city":"Bilthoven",
    "sg:orig_category":"Kappers",
    "sg:phone":"+31 30 229 0232",
    "sg:postcode":"3722 AB",
    "sg:province":"Utrecht",
    "wof:name":"Arendsen, Michel",
    "wof:placetype":"venue"
},
  "geometry": {"coordinates":[5.2054209709,52.128616333],"type":"Point"}
}