{
  "type": "Feature",
  "properties": {
    "addr:full":"Hoge Eng-Oost 44 Putten Gelderland 3882 TN",
    "addr:housenumber":"44",
    "addr:postcode":"3882",
    "addr:street":"Hoge Eng-Oost;Gelderland",
    "iso:country":"NL",
    "sg:address":"Hoge Eng-Oost 44",
    "sg:city":"Putten",
    "sg:orig_category":"Huisdierenvoer Fab",
    "sg:phone":"+31 341 358 338",
    "sg:postcode":"3882 TN",
    "sg:province":"Gelderland",
    "wof:name":"S.H. Kiezebrink",
    "wof:placetype":"venue"
},
  "geometry": {"coordinates":[5.604005,52.248875],"type":"Point"}
}