{
  "type": "Feature",
  "properties": {
    "iso:country":"NL",
    "sg:address":"Oude Kerkpad 8",
    "sg:city":"Ter Aar",
    "sg:orig_category":"Bloemen And Planten",
    "sg:phone":"+31 172 603 051",
    "sg:postcode":"2461 EW",
    "sg:province":"Zuid-Holland",
    "wof:name":"Firma J.P.M. Keijzer",
    "wof:placetype":"venue"
},
  "geometry": {"coordinates":[4.730985,52.178001],"type":"Point"}
}