{
  "type": "Feature",
  "properties": {
    "addr:full":"Zypestr 1 St Philipsland Zeeland 4675 CV",
    "addr:housenumber":"1",
    "addr:postcode":"4675 cv",
    "addr:street":"Zypestr",
    "iso:country":"NL",
    "sg:address":"Zypestr 1",
    "sg:city":"St Philipsland",
    "sg:orig_category":"Artsen - Huisartsen",
    "sg:phone":"+31 167 572 500",
    "sg:postcode":"4675 CV",
    "sg:province":"Zeeland",
    "wof:name":"Doesburg, Van",
    "wof:placetype":"venue"
},
  "geometry": {"coordinates":[4.162273,51.619335],"type":"Point"}
}