{
  "type": "Feature",
  "properties": {
    "addr:full":"De Limiet 2 Vianen Zh Utrecht 4131 NR",
    "addr:housenumber":"2",
    "addr:postcode":"zh;4131 nr",
    "addr:street":"De Limiet",
    "iso:country":"NL",
    "sg:address":"De Limiet 2",
    "sg:city":"Vianen Zh",
    "sg:orig_category":"Keuken- Inbouwapparatuur",
    "sg:phone":"+31 347 378 911",
    "sg:postcode":"4131 NR",
    "sg:province":"Utrecht",
    "sg:website":"http://www.imperal.nl",
    "wof:name":"Imperial, Keukenapparaten",
    "wof:placetype":"venue"
},
  "geometry": {"coordinates":[5.094198,51.979389],"type":"Point"}
}