{
  "type": "Feature",
  "properties": {
    "addr:full":"Hefnerstraat 3 Ijmuiden Noord-Holland 1976 BK",
    "addr:housenumber":"3",
    "addr:postcode":"1976 bk",
    "addr:street":"Hefnerstraat",
    "iso:country":"NL",
    "sg:address":"Hefnerstraat 3",
    "sg:city":"Ijmuiden",
    "sg:orig_category":"Autokeuringen",
    "sg:phone":"+31 255 541 156",
    "sg:postcode":"1976 BK",
    "sg:province":"Noord-Holland",
    "wof:name":"Koning Service Center Ksc",
    "wof:placetype":"venue"
},
  "geometry": {"coordinates":[4.581431,52.454891],"type":"Point"}
}