{
  "type": "Feature",
  "properties": {
    "addr:full":"Laagraven 51-53 Nieuwegein Utrecht 3439 LL",
    "addr:housenumber":"51-53",
    "addr:postcode":"3439 ll",
    "addr:street":"Laagraven",
    "iso:country":"NL",
    "sg:address":"Laagraven 51-53",
    "sg:city":"Nieuwegein",
    "sg:orig_category":"Hoogwerkers",
    "sg:phone":"+31 30 289 3844",
    "sg:postcode":"3439 LL",
    "sg:province":"Utrecht",
    "sg:website":"http://www.sgbholland.nl",
    "wof:name":"Sgb Holland",
    "wof:placetype":"venue"
},
  "geometry": {"coordinates":[5.122611,52.051239],"type":"Point"}
}