{
  "type": "Feature",
  "properties": {
    "addr:full":"Atalanta 5 Krommenie Noord-Holland 1562 LC",
    "addr:housenumber":"5",
    "addr:postcode":"1562 lc",
    "addr:street":"Atalanta",
    "iso:country":"NL",
    "sg:address":"Atalanta 5",
    "sg:city":"Krommenie",
    "sg:orig_category":"Elektrotechnische Apparatuur - Fabrieken En Groothandel",
    "sg:phone":"+31 75 628 3717",
    "sg:postcode":"1562 LC",
    "sg:province":"Noord-Holland",
    "sg:website":"http://www.hftechnology.nl",
    "wof:name":"Hf Technology",
    "wof:placetype":"venue"
},
  "geometry": {"coordinates":[4.77065,52.507572],"type":"Point"}
}