{
  "type": "Feature",
  "properties": {
    "addr:full":"Kometenstr 6 Purmerend North Holland 1443 BA",
    "addr:housenumber":"6",
    "addr:postcode":"1443 ba",
    "addr:street":"Kometenstr",
    "iso:country":"NL",
    "sg:address":"Kometenstr 6",
    "sg:city":"Purmerend",
    "sg:orig_category":"Woningbouw- Verenigingen En -Stichtingen",
    "sg:phone":"+31 299 390 980",
    "sg:postcode":"1443 BA",
    "sg:province":"North Holland",
    "wof:name":"Patrimonium",
    "wof:placetype":"venue"
},
  "geometry": {"coordinates":[4.9668951035,52.5094146729],"type":"Point"}
}