{
  "type": "Feature",
  "properties": {
    "addr:full":"Zestienhovensekd 23 Rotterdam Zuid-Holland 3043 KH",
    "addr:housenumber":"23",
    "addr:postcode":"3043 kh",
    "addr:street":"Zestienhovensekd",
    "iso:country":"NL",
    "sg:address":"Zestienhovensekd 23",
    "sg:city":"Rotterdam",
    "sg:orig_category":"Acupunctuur",
    "sg:phone":"+31 10 262 1384",
    "sg:postcode":"3043 KH",
    "sg:province":"Zuid-Holland",
    "wof:name":"Steenkamer, F T A",
    "wof:placetype":"venue"
},
  "geometry": {"coordinates":[4.423597,51.941238],"type":"Point"}
}