{
  "type": "Feature",
  "properties": {
    "addr:full":"Koningsweg 15 Didam Gelderland 6942 NV",
    "addr:housenumber":"15",
    "addr:postcode":"6942 nv",
    "addr:street":"Koningsweg;Gelderland",
    "iso:country":"NL",
    "sg:address":"Koningsweg 15",
    "sg:city":"Didam",
    "sg:orig_category":"Hout Gh",
    "sg:phone":"+31 316 531 857",
    "sg:postcode":"6942 NV",
    "sg:province":"Gelderland",
    "wof:name":"Houthandel Behrenroth",
    "wof:placetype":"venue"
},
  "geometry": {"coordinates":[6.176386,51.926174],"type":"Point"}
}