{
  "type": "Feature",
  "properties": {
    "addr:full":"Kreeftenheide 12A Siebengewald North Rhine-Westphalia 5853 AK",
    "addr:housenumber":"12a",
    "addr:postcode":"5853 ak",
    "addr:street":"Kreeftenheide",
    "iso:country":"NL",
    "sg:address":"Kreeftenheide 12A",
    "sg:city":"Siebengewald",
    "sg:orig_category":"Goederenvervoer Over De Weg",
    "sg:phone":"+31 485 441 282",
    "sg:postcode":"5853 AK",
    "sg:province":"North Rhine-Westphalia",
    "wof:name":"J.L.W. Hopman Huberts",
    "wof:placetype":"venue"
},
  "geometry": {"coordinates":[6.106397,51.648388],"type":"Point"}
}