{
  "type": "Feature",
  "properties": {
    "iso:country":"NL",
    "sg:address":"Sint-Jobsweg 30",
    "sg:city":"Rotterdam",
    "sg:orig_category":"Diverse Grafische Activiteiten",
    "sg:phone":"+31 10 244 1442",
    "sg:postcode":"3024 EJ",
    "sg:province":"Zuid-Holland",
    "wof:name":"Proforma Ontwerp & Advies Bv",
    "wof:placetype":"venue"
},
  "geometry": {"coordinates":[4.460914,51.904549],"type":"Point"}
}