{
  "type": "Feature",
  "properties": {
    "addr:full":"Drieboomlaan 163 Hoorn Nh Noord-Holland 1624 BE",
    "addr:housenumber":"163",
    "addr:postcode":"1624",
    "addr:street":"Drieboomlaan",
    "iso:country":"NL",
    "sg:address":"Drieboomlaan 163",
    "sg:city":"Hoorn Nh",
    "sg:orig_category":"Goederenvervoer Over De Weg",
    "sg:phone":"+31 229 215 572",
    "sg:postcode":"1624 BE",
    "sg:province":"Noord-Holland",
    "wof:name":"Transportonderneming Oud Bv",
    "wof:placetype":"venue"
},
  "geometry": {"coordinates":[5.064786,52.647366],"type":"Point"}
}