{
  "type": "Feature",
  "properties": {
    "addr:full":"Dalkruid 4 Veenendaal Utrecht 3903 EV",
    "addr:housenumber":"4",
    "addr:street":"Dalkruid",
    "iso:country":"NL",
    "sg:address":"Dalkruid 4",
    "sg:city":"Veenendaal",
    "sg:orig_category":"Boekhouders",
    "sg:phone":"+31 318 551 803",
    "sg:postcode":"3903 EV",
    "sg:province":"Utrecht",
    "wof:name":"Administratiekantoor W. Van De Weerdhof",
    "wof:placetype":"venue"
},
  "geometry": {"coordinates":[5.55414,52.002552],"type":"Point"}
}