{
  "type": "Feature",
  "properties": {
    "addr:full":"Utrechtstr 96 Alphen Aan Den Ryn Zuid-Holland 2408 GS",
    "addr:housenumber":"96",
    "addr:postcode":"2408 gs",
    "addr:street":"Utrechtstr;Aan Den Ryn",
    "iso:country":"NL",
    "sg:address":"Utrechtstr 96",
    "sg:city":"Alphen Aan Den Ryn",
    "sg:classifiers":[
        {
            "category":"Food & Beverages",
            "subcategory":"Bakery",
            "type":"Retail Goods"
        }
    ],
    "sg:phone":"+31 172 499 555",
    "sg:postcode":"2408 GS",
    "sg:province":"Zuid-Holland",
    "sg:tags":[
        "pizza"
    ],
    "wof:name":"Golden Gate",
    "wof:placetype":"venue"
},
  "geometry": {"coordinates":[4.654056,52.12431],"type":"Point"}
}