{
  "type": "Feature",
  "properties": {
    "iso:country":"NL",
    "sg:address":"Laan 20",
    "sg:city":"S Gravenhage",
    "sg:orig_category":"Juridische Adviseurs",
    "sg:phone":"+31 70 345 9808",
    "sg:postcode":"2512 GN",
    "sg:province":"South Holland",
    "sg:website":"http://www.binsmedical.com",
    "wof:name":"Bins Bv",
    "wof:placetype":"venue"
},
  "geometry": {"coordinates":[4.30618,52.073212],"type":"Point"}
}