{
  "type": "Feature",
  "properties": {
    "addr:full":"A Cuypstr 203 Amsterdam Noord-Holland 1073 BE",
    "addr:housenumber":"203",
    "addr:postcode":"1073",
    "iso:country":"NL",
    "sg:address":"A Cuypstr 203",
    "sg:city":"Amsterdam",
    "sg:orig_category":"Bloemen En Planten",
    "sg:phone":"+31 20 662 6440",
    "sg:postcode":"1073 BE",
    "sg:province":"Noord-Holland",
    "wof:name":"Tol, Van",
    "wof:placetype":"venue"
},
  "geometry": {"coordinates":[4.895549,52.356148],"type":"Point"}
}