{
  "type": "Feature",
  "properties": {
    "addr:full":"V Halewynln 207 Voorburg Zuid-Holland 2274 TH",
    "addr:housenumber":"207",
    "addr:postcode":"2274 th",
    "iso:country":"NL",
    "sg:address":"V Halewynln 207",
    "sg:city":"Voorburg",
    "sg:orig_category":"Parketvloeren",
    "sg:phone":"+31 70 347 4766",
    "sg:postcode":"2274 TH",
    "sg:province":"Zuid-Holland",
    "wof:name":"Eekhof Parketservice",
    "wof:placetype":"venue"
},
  "geometry": {"coordinates":[4.34952,52.073792],"type":"Point"}
}