{
  "type": "Feature",
  "properties": {
    "iso:country":"NL",
    "sg:address":"Snelleveldstr 69",
    "sg:city":"Amsterdam Zuidoost",
    "sg:orig_category":"Elektrotechnische Installatiebureaus",
    "sg:phone":"+31 20 400 1747",
    "sg:postcode":"1107 VT",
    "sg:province":"Noord-Holland",
    "wof:name":"Buijs Vof",
    "wof:placetype":"venue"
},
  "geometry": {"coordinates":[-72.451218,43.871769],"type":"Point"}
}