{
  "type": "Feature",
  "properties": {
    "addr:full":"Ceintuurbaan West 80 Roden Drenthe 9301 CV",
    "addr:housenumber":"80",
    "addr:postcode":"9301 cv",
    "addr:street":"Ceintuurbaan West",
    "iso:country":"NL",
    "sg:address":"Ceintuurbaan West 80",
    "sg:city":"Roden",
    "sg:orig_category":"Huishoudapparatuur, Televisies And Radio'S",
    "sg:phone":"+31 50 501 9623",
    "sg:postcode":"9301 CV",
    "sg:province":"Drenthe",
    "wof:name":"F S Kroese",
    "wof:placetype":"venue"
},
  "geometry": {"coordinates":[6.41868,53.140057],"type":"Point"}
}