{
  "type": "Feature",
  "properties": {
    "iso:country":"NL",
    "sg:address":"Mendelssohnstr 84",
    "sg:city":"Utrecht",
    "sg:orig_category":"Adviesbureaus Bedrijfsorganisatie",
    "sg:phone":"+31 30 293 0106",
    "sg:postcode":"3533 XJ",
    "sg:province":"Utrecht",
    "wof:name":"Mosa-C",
    "wof:placetype":"venue"
},
  "geometry": {"coordinates":[5.087036,52.087318],"type":"Point"}
}