{
  "type": "Feature",
  "properties": {
    "addr:full":"Oosteinde 7 St Jacobiparochie Friesland 9079 KZ",
    "addr:housenumber":"7",
    "addr:postcode":"9079 kz",
    "addr:street":"Oosteinde",
    "iso:country":"NL",
    "sg:address":"Oosteinde 7",
    "sg:city":"St Jacobiparochie",
    "sg:orig_category":"Cafetaria'S",
    "sg:phone":"+31 518 491 417",
    "sg:postcode":"9079 KZ",
    "sg:province":"Friesland",
    "wof:name":"East End",
    "wof:placetype":"venue"
},
  "geometry": {"coordinates":[5.60402,53.272827],"type":"Point"}
}