{
  "type": "Feature",
  "properties": {
    "iso:country":"NL",
    "sg:address":"Nieuwe Binnenweg 431",
    "sg:city":"Rotterdam",
    "sg:orig_category":"Binnenhuisarchitecten",
    "sg:phone":"+31 10 425 6371",
    "sg:postcode":"3023 EN",
    "sg:province":"South Holland",
    "wof:name":"Waisfisz 3D",
    "wof:placetype":"venue"
},
  "geometry": {"coordinates":[4.451768,51.910671],"type":"Point"}
}