{
  "type": "Feature",
  "properties": {
    "addr:full":"Bydorp W 65 Barendrecht Zuid-Holland 2992 LC",
    "addr:housenumber":"65",
    "addr:postcode":"2992 lc",
    "addr:street":"W",
    "iso:country":"NL",
    "sg:address":"Bydorp W 65",
    "sg:city":"Barendrecht",
    "sg:orig_category":"Parketvloeren",
    "sg:phone":"+31 180 557 007",
    "sg:postcode":"2992 LC",
    "sg:province":"Zuid-Holland",
    "wof:name":"Nieuwpoort Bv",
    "wof:placetype":"venue"
},
  "geometry": {"coordinates":[4.54064,51.853176],"type":"Point"}
}