{
  "type": "Feature",
  "properties": {
    "addr:full":"Beukenhof 32 Lelystad NL. 8212 EB",
    "addr:housenumber":"32",
    "addr:postcode":"8212 eb",
    "addr:street":"Beukenhof;Nl.",
    "iso:country":"NL",
    "sg:address":"Beukenhof 32",
    "sg:city":"Lelystad",
    "sg:orig_category":"Adviesbureaus Bedrijfsorganisatie",
    "sg:phone":"+31 6 26334310",
    "sg:postcode":"8212 EB",
    "sg:province":"NL.",
    "wof:name":"Dineke Meijen",
    "wof:placetype":"venue"
},
  "geometry": {"coordinates":[5.498067,52.509228],"type":"Point"}
}