{
  "type": "Feature",
  "properties": {
    "addr:full":"Utrechtsewg 109C Utrecht Utrecht 3544 NA",
    "addr:housenumber":"109c",
    "addr:postcode":"3544 na",
    "addr:street":"Utrechtsewg",
    "iso:country":"NL",
    "sg:address":"Utrechtsewg 109C",
    "sg:city":"Utrecht",
    "sg:orig_category":"Bloemen En Planten - Groothandel",
    "sg:phone":"+31 30 677 4254",
    "sg:postcode":"3544 NA",
    "sg:province":"Utrecht",
    "sg:website":"http://www.cvianen.nl",
    "wof:name":"Vianen, C",
    "wof:placetype":"venue"
},
  "geometry": {"coordinates":[5.049783,52.098232],"type":"Point"}
}