{
  "type": "Feature",
  "properties": {
    "addr:full":"Westpad 20 Katwyk Zh Zuid-Holland 2225 CP",
    "addr:housenumber":"20",
    "addr:postcode":"2225 cp",
    "addr:street":"Westpad",
    "iso:country":"NL",
    "sg:address":"Westpad 20",
    "sg:city":"Katwyk Zh",
    "sg:orig_category":"Kantoor- En Bedrijfsmeubelen",
    "sg:phone":"+31 71 407 8558",
    "sg:postcode":"2225 CP",
    "sg:province":"Zuid-Holland",
    "sg:website":"http://www.mermaid-furniture.nl/",
    "wof:name":"Mermaid",
    "wof:placetype":"venue"
},
  "geometry": {"coordinates":[4.3965849876,52.2051086426],"type":"Point"}
}