{
  "type": "Feature",
  "properties": {
    "iso:country":"NL",
    "sg:address":"Ommerwg 68",
    "sg:city":"Zuidwolde Dr",
    "sg:classifiers":[
        {
            "category":"Travel",
            "subcategory":"Hotels & Motels",
            "type":"Entertainment"
        }
    ],
    "sg:phone":"+31 528 371 125",
    "sg:postcode":"7921 TE",
    "sg:province":"Provincie Drenthe",
    "wof:name":"Linde, Ter",
    "wof:placetype":"venue"
},
  "geometry": {"coordinates":[6.42853,52.67675],"type":"Point"}
}