{
  "type": "Feature",
  "properties": {
    "iso:country":"NL",
    "sg:address":"Reigerln 43",
    "sg:city":"Nykerk Gld",
    "sg:orig_category":"Autopoetsbedrijven",
    "sg:phone":"+31 6 13388048",
    "sg:postcode":"3862 KX",
    "sg:province":"Gelderland",
    "wof:name":"Aras",
    "wof:placetype":"venue"
},
  "geometry": {"coordinates":[5.62297,52.20557],"type":"Point"}
}