{
  "type": "Feature",
  "properties": {
    "addr:full":"Sibeliuswg 44 Capelle Ad Yssel Zuid-Holland 2901 GH",
    "addr:housenumber":"44",
    "addr:postcode":"2901 gh",
    "addr:street":"Sibeliuswg",
    "iso:country":"NL",
    "sg:address":"Sibeliuswg 44",
    "sg:city":"Capelle Ad Yssel",
    "sg:orig_category":"Psychologen",
    "sg:phone":"+31 10 202 5056",
    "sg:postcode":"2901 GH",
    "sg:province":"Zuid-Holland",
    "wof:name":"Maat, Drs M J J A Van Der",
    "wof:placetype":"venue"
},
  "geometry": {"coordinates":[4.562669,51.917019],"type":"Point"}
}