{
  "type": "Feature",
  "properties": {
    "addr:full":"Vicarishove 9 Leusden Utrecht 3834 XG",
    "addr:housenumber":"9",
    "addr:postcode":"3834 xg",
    "addr:street":"Vicarishove",
    "iso:country":"NL",
    "sg:address":"Vicarishove 9",
    "sg:city":"Leusden",
    "sg:orig_category":"Adviesbureaus Personeel",
    "sg:phone":"+31 33 432 4414",
    "sg:postcode":"3834 XG",
    "sg:province":"Utrecht",
    "wof:name":"Consultancy & Training",
    "wof:placetype":"venue"
},
  "geometry": {"coordinates":[5.436842,52.127872],"type":"Point"}
}