{
  "type": "Feature",
  "properties": {
    "addr:full":"Hofstr 5 Aalten Gelderland 7121 DM",
    "addr:housenumber":"5",
    "addr:postcode":"7121 dm",
    "addr:street":"Hofstr;Gelderland",
    "iso:country":"NL",
    "sg:address":"Hofstr 5",
    "sg:city":"Aalten",
    "sg:orig_category":"Accountants - Administratie- Consulenten En -Kantoren",
    "sg:phone":"+31 543 471 566",
    "sg:postcode":"7121 DM",
    "sg:province":"Gelderland",
    "wof:name":"Adva",
    "wof:placetype":"venue"
},
  "geometry": {"coordinates":[6.5827970505,51.9263725281],"type":"Point"}
}