{
  "type": "Feature",
  "properties": {
    "iso:country":"NL",
    "sg:address":"De Grent 14",
    "sg:city":"Noordwyk Zh",
    "sg:orig_category":"Discotheken",
    "sg:phone":"+31 71 361 2394",
    "sg:postcode":"2202 EL",
    "sg:province":"Zuid-Holland",
    "sg:website":"http://www.debob.nl",
    "wof:name":"Bob, De",
    "wof:placetype":"venue"
},
  "geometry": {"coordinates":[4.430042,52.242496],"type":"Point"}
}