{
  "type": "Feature",
  "properties": {
    "addr:full":"Gravenstr 8 Helmond Noord-Brabant 5707 VZ",
    "addr:housenumber":"8",
    "addr:postcode":"5707 vz",
    "addr:street":"Gravenstr",
    "iso:country":"NL",
    "sg:address":"Gravenstr 8",
    "sg:city":"Helmond",
    "sg:orig_category":"Voegwerken",
    "sg:phone":"+31 492 527 814",
    "sg:postcode":"5707 VZ",
    "sg:province":"Noord-Brabant",
    "wof:name":"Meeuws, Harold",
    "wof:placetype":"venue"
},
  "geometry": {"coordinates":[5.646306,51.474293],"type":"Point"}
}