{
  "type": "Feature",
  "properties": {
    "addr:full":"Patriapln 1 Amstelveen North Holland 1182 CW",
    "addr:housenumber":"1",
    "addr:postcode":"1182 cw",
    "addr:street":"Patriapln",
    "iso:country":"NL",
    "sg:address":"Patriapln 1",
    "sg:city":"Amstelveen",
    "sg:orig_category":"Verenigingen En Stichtingen",
    "sg:phone":"+31 20 647 1089",
    "sg:postcode":"1182 CW",
    "sg:province":"North Holland",
    "wof:name":"Belklus Amstelveen",
    "wof:placetype":"venue"
},
  "geometry": {"coordinates":[4.842224,52.309254],"type":"Point"}
}