{
  "type": "Feature",
  "properties": {
    "addr:full":"2E Industriestr 13 Noord Scharwoude Noord-Holland 1723 LG",
    "addr:housenumber":"13",
    "addr:postcode":"1723 lg",
    "addr:street":"2E Industriestr",
    "iso:country":"NL",
    "sg:address":"2E Industriestr 13",
    "sg:city":"Noord Scharwoude",
    "sg:orig_category":"Meubelmakerijen",
    "sg:phone":"+31 226 312 363",
    "sg:postcode":"1723 LG",
    "sg:province":"Noord-Holland",
    "wof:name":"Aad Engeringh",
    "wof:placetype":"venue"
},
  "geometry": {"coordinates":[4.81024,52.698441],"type":"Point"}
}