{
  "type": "Feature",
  "properties": {
    "iso:country":"NL",
    "sg:address":"Vondelln 55",
    "sg:city":"Alblasserdam",
    "sg:orig_category":"Autorijscholen",
    "sg:phone":"+31 78 691 6362",
    "sg:postcode":"2951 TP",
    "sg:province":"South Holland",
    "wof:name":"Otto",
    "wof:placetype":"venue"
},
  "geometry": {"coordinates":[4.669468,51.864998],"type":"Point"}
}