{
  "type": "Feature",
  "properties": {
    "addr:full":"Batenburg 29 Vlissingen Zeeland 4385 HE",
    "addr:housenumber":"29",
    "addr:postcode":"4385 he",
    "addr:street":"Batenburg",
    "iso:country":"NL",
    "sg:address":"Batenburg 29",
    "sg:city":"Vlissingen",
    "sg:orig_category":"Algemene Werktuigbouw",
    "sg:phone":"+31 118 464 044",
    "sg:postcode":"4385 HE",
    "sg:province":"Zeeland",
    "wof:name":"Werkhoven Montage",
    "wof:placetype":"venue"
},
  "geometry": {"coordinates":[3.570932,51.465027],"type":"Point"}
}