{
  "type": "Feature",
  "properties": {
    "addr:full":"Koopmansstraat 9 Lelystad Flevoland 8223 AH",
    "addr:housenumber":"9",
    "addr:postcode":"8223 ah",
    "addr:street":"Koopmansstraat;Flevoland",
    "iso:country":"NL",
    "sg:address":"Koopmansstraat 9",
    "sg:city":"Lelystad",
    "sg:orig_category":"Discountwinkels",
    "sg:phone":"+31 320 224 093",
    "sg:postcode":"8223 AH",
    "sg:province":"Flevoland",
    "wof:name":"Wibra Bv",
    "wof:placetype":"venue"
},
  "geometry": {"coordinates":[5.485251,52.520569],"type":"Point"}
}