{
  "type": "Feature",
  "properties": {
    "addr:full":"Albatrosstraat 19 Amersfoort Utrecht 3815 KG",
    "addr:housenumber":"19",
    "addr:postcode":"3815 kg",
    "addr:street":"Albatrosstraat",
    "iso:country":"NL",
    "sg:address":"Albatrosstraat 19",
    "sg:city":"Amersfoort",
    "sg:orig_category":"Marktonderzoekbureaus",
    "sg:phone":"+31 33 479 9543",
    "sg:postcode":"3815 KG",
    "sg:province":"Utrecht",
    "wof:name":"Datec",
    "wof:placetype":"venue"
},
  "geometry": {"coordinates":[5.407171,52.162434],"type":"Point"}
}