{
  "type": "Feature",
  "properties": {
    "addr:full":"Ijkenweg 20 Zandhuizen Friesland 8389 TM",
    "addr:housenumber":"20",
    "addr:postcode":"8389 tm",
    "addr:street":"Ijkenweg",
    "iso:country":"NL",
    "sg:address":"Ijkenweg 20",
    "sg:city":"Zandhuizen",
    "sg:orig_category":"Diverse Grafische Activiteiten",
    "sg:phone":"+31 561 431 954",
    "sg:postcode":"8389 TM",
    "sg:province":"Friesland",
    "wof:name":"L. Van Pelt",
    "wof:placetype":"venue"
},
  "geometry": {"coordinates":[6.132101,52.912014],"type":"Point"}
}