{
  "type": "Feature",
  "properties": {
    "addr:full":"Ooyerhoeksewg 8 Zutphen Gelderland 7207 BA",
    "addr:housenumber":"8",
    "addr:postcode":"7207 ba",
    "addr:street":"Ooyerhoeksewg;Gelderland",
    "iso:country":"NL",
    "sg:address":"Ooyerhoeksewg 8",
    "sg:city":"Zutphen",
    "sg:orig_category":"Ziekenhuizen, Sanatoria, Verpleeghuizen",
    "sg:phone":"+31 575 592 592",
    "sg:postcode":"7207 BA",
    "sg:province":"Gelderland",
    "wof:name":"Gelre Ziekenhuizen",
    "wof:placetype":"venue"
},
  "geometry": {"coordinates":[6.219553,52.124397],"type":"Point"}
}