{
  "type": "Feature",
  "properties": {
    "addr:full":"Ophelialn 83 Aalsmeer North Holland 1431 HB",
    "addr:housenumber":"83",
    "addr:postcode":"1431 hb",
    "addr:street":"Ophelialn",
    "iso:country":"NL",
    "sg:address":"Ophelialn 83",
    "sg:city":"Aalsmeer",
    "sg:orig_category":"Accountants - Administratie- Consulenten En -Kantoren",
    "sg:phone":"+31 297 329 980",
    "sg:postcode":"1431 HB",
    "sg:province":"North Holland",
    "wof:name":"Alfa",
    "wof:placetype":"venue"
},
  "geometry": {"coordinates":[4.749068,52.266991],"type":"Point"}
}