{
  "type": "Feature",
  "properties": {
    "iso:country":"NL",
    "sg:address":"Van De Woestijnestraat 10",
    "sg:city":"Rotterdam",
    "sg:classifiers":[
        {
            "category":"Food & Beverages",
            "subcategory":"Fruits & Vegetables",
            "type":"Retail Goods"
        }
    ],
    "sg:phone":"+31 10 432 4836",
    "sg:postcode":"3076 EV",
    "sg:province":"Zuid-Holland",
    "sg:tags":[
        "groenten"
    ],
    "wof:name":"Jan Den Hartog Versmarkt",
    "wof:placetype":"venue"
},
  "geometry": {"coordinates":[4.517218,51.875648],"type":"Point"}
}