{
  "type": "Feature",
  "properties": {
    "iso:country":"NL",
    "sg:address":"Ambachtsmark 11",
    "sg:city":"Almere",
    "sg:orig_category":"Kantoorapparatuur Gh",
    "sg:phone":"+31 36 531 2744",
    "sg:postcode":"1355 EA",
    "sg:province":"NL.",
    "wof:name":"Rosenboom All Office",
    "wof:placetype":"venue"
},
  "geometry": {"coordinates":[5.2244758606,52.3423118591],"type":"Point"}
}