{
  "type": "Feature",
  "properties": {
    "addr:full":"Gravensngl 31 Dordrecht South Holland 3319 EN",
    "addr:housenumber":"31",
    "addr:postcode":"3319 en",
    "addr:street":"Gravensngl",
    "iso:country":"NL",
    "sg:address":"Gravensngl 31",
    "sg:city":"Dordrecht",
    "sg:orig_category":"Psychologen",
    "sg:phone":"+31 78 616 1514",
    "sg:postcode":"3319 EN",
    "sg:province":"South Holland",
    "wof:name":"Versloot, Drs N A",
    "wof:placetype":"venue"
},
  "geometry": {"coordinates":[4.697815,51.792995],"type":"Point"}
}