{
  "type": "Feature",
  "properties": {
    "addr:full":"Melisse 30 Hoogkarspel Noord-Holland 1616 TV",
    "addr:housenumber":"30",
    "addr:postcode":"1616 tv",
    "addr:street":"Melisse",
    "iso:country":"NL",
    "sg:address":"Melisse 30",
    "sg:city":"Hoogkarspel",
    "sg:orig_category":"Machineonderhoud En -Reparatie",
    "sg:phone":"+31 228 563 832",
    "sg:postcode":"1616 TV",
    "sg:province":"Noord-Holland",
    "wof:name":"Hoefsmit, B",
    "wof:placetype":"venue"
},
  "geometry": {"coordinates":[5.189163,52.697887],"type":"Point"}
}