{
  "type": "Feature",
  "properties": {
    "addr:full":"Scheldestraat 1 Hardinxveld Giessend Zuid-Holland 3371 SV",
    "addr:housenumber":"1;giessend",
    "addr:postcode":"3371 sv",
    "addr:street":"Scheldestraat",
    "iso:country":"NL",
    "sg:address":"Scheldestraat 1",
    "sg:city":"Hardinxveld Giessend",
    "sg:orig_category":"Overheidsdiensten",
    "sg:phone":"+31 184 612 771",
    "sg:postcode":"3371 SV",
    "sg:province":"Zuid-Holland",
    "wof:name":"De Ducdalf",
    "wof:placetype":"venue"
},
  "geometry": {"coordinates":[4.827750206,51.8227462769],"type":"Point"}
}