{
  "type": "Feature",
  "properties": {
    "addr:full":"Postbus 170 Zwyndrecht 3330 AD",
    "addr:housenumber":"170",
    "addr:postcode":"3330 ad",
    "addr:street":"Postbus",
    "iso:country":"NL",
    "sg:address":"Postbus 170",
    "sg:city":"Zwyndrecht",
    "sg:orig_category":"Verenigingen En Stichtingen",
    "sg:phone":"+31 78 619 4184",
    "sg:postcode":"3330 AD",
    "wof:name":"Ehbo",
    "wof:placetype":"venue"
},
  "geometry": {"coordinates":[4.65254,51.818989],"type":"Point"}
}