{
  "type": "Feature",
  "properties": {
    "addr:full":"J Leentvaarln 15 Rotterdam Zuid-Holland 3065 DC",
    "addr:housenumber":"15",
    "addr:postcode":"3065",
    "iso:country":"NL",
    "sg:address":"J Leentvaarln 15",
    "sg:city":"Rotterdam",
    "sg:orig_category":"Werving En Selectie",
    "sg:phone":"+31 10 447 2148",
    "sg:postcode":"3065 DC",
    "sg:province":"Zuid-Holland",
    "wof:name":"Efcon Recruiting",
    "wof:placetype":"venue"
},
  "geometry": {"coordinates":[4.5381360054,51.9220848083],"type":"Point"}
}