{
  "type": "Feature",
  "properties": {
    "addr:full":"Reijerskoop 281 Boskoop Zuid-Holland 2771 BK",
    "addr:housenumber":"281",
    "addr:postcode":"2771 bk",
    "addr:street":"Reijerskoop",
    "iso:country":"NL",
    "sg:address":"Reijerskoop 281",
    "sg:city":"Boskoop",
    "sg:orig_category":"Bloemen And Planten",
    "sg:phone":"+31 172 213 823",
    "sg:postcode":"2771 BK",
    "sg:province":"Zuid-Holland",
    "wof:name":"Firma A.N.M. Rijnbeek",
    "wof:placetype":"venue"
},
  "geometry": {"coordinates":[4.679463,52.073399],"type":"Point"}
}