{
  "type": "Feature",
  "properties": {
    "iso:country":"NL",
    "sg:address":"Couwenhovenstr 19",
    "sg:city":"Schiedam",
    "sg:orig_category":"Fotografie Reclame En Mode",
    "sg:phone":"+31 10 426 9469",
    "sg:postcode":"3113 AA",
    "sg:province":"Zuid-Holland",
    "wof:name":"Konings, Rien",
    "wof:placetype":"venue"
},
  "geometry": {"coordinates":[4.409453,51.913826],"type":"Point"}
}