{
  "type": "Feature",
  "properties": {
    "addr:full":"Heggewikke 18 Voerendaal Limburg 6367 DM",
    "addr:housenumber":"18",
    "addr:postcode":"6367 dm",
    "addr:street":"Heggewikke",
    "iso:country":"NL",
    "sg:address":"Heggewikke 18",
    "sg:city":"Voerendaal",
    "sg:orig_category":"Schoonheidsinstituten",
    "sg:phone":"+31 45 562 0090",
    "sg:postcode":"6367 DM",
    "sg:province":"Limburg",
    "wof:name":"Winkeler, Bianca",
    "wof:placetype":"venue"
},
  "geometry": {"coordinates":[5.939507,50.875725],"type":"Point"}
}