{
  "type": "Feature",
  "properties": {
    "iso:country":"NL",
    "sg:address":"P V Wieldrechtln 19",
    "sg:city":"Zeist",
    "sg:orig_category":"Journalisten Freelance",
    "sg:phone":"+31 30 691 4889",
    "sg:postcode":"3701 ES",
    "sg:province":"Utrecht",
    "wof:name":"Visser",
    "wof:placetype":"venue"
},
  "geometry": {"coordinates":[5.24387,52.08548],"type":"Point"}
}