{
  "type": "Feature",
  "properties": {
    "addr:full":"Peppelbos 58 Geldermalsen Gelderland 4191 MG",
    "addr:housenumber":"58",
    "addr:postcode":"4191 mg",
    "addr:street":"Peppelbos;Gelderland",
    "iso:country":"NL",
    "sg:address":"Peppelbos 58",
    "sg:city":"Geldermalsen",
    "sg:classifiers":[
        {
            "category":"Fast Food",
            "type":"Food & Drink"
        }
    ],
    "sg:phone":"+31 345 573 627",
    "sg:postcode":"4191 MG",
    "sg:province":"Gelderland",
    "sg:tags":[
        "afhaal",
        "restaurant"
    ],
    "wof:name":"Martens Horeca Bv",
    "wof:placetype":"venue"
},
  "geometry": {"coordinates":[5.289065,51.875027],"type":"Point"}
}