{
  "type": "Feature",
  "properties": {
    "addr:full":"T Harde 22 Haren Gn Groningen 9752 VD",
    "addr:housenumber":"22",
    "addr:postcode":"9752 vd",
    "addr:street":"T Harde",
    "iso:country":"NL",
    "sg:address":"T Harde 22",
    "sg:city":"Haren Gn",
    "sg:orig_category":"Verzekeringen",
    "sg:phone":"+31 50 534 4723",
    "sg:postcode":"9752 VD",
    "sg:province":"Groningen",
    "wof:name":"Advies-Bureau Voor Financ/Ass/Hyp/Bel Vd",
    "wof:placetype":"venue"
},
  "geometry": {"coordinates":[6.609887,53.162224],"type":"Point"}
}