{
  "type": "Feature",
  "properties": {
    "addr:full":"Strick Van Linschotenstr 48 Beverwijk Noord-Holland 1943 KD",
    "addr:housenumber":"48",
    "addr:postcode":"1943 kd",
    "addr:street":"Strick Van Linschotenstr",
    "iso:country":"NL",
    "sg:address":"Strick Van Linschotenstr 48",
    "sg:city":"Beverwijk",
    "sg:orig_category":"Diverse Grafische Activiteiten",
    "sg:phone":"+31 251 224 176",
    "sg:postcode":"1943 KD",
    "sg:province":"Noord-Holland",
    "wof:name":"B.W. Van Gool",
    "wof:placetype":"venue"
},
  "geometry": {"coordinates":[4.654251,52.486496],"type":"Point"}
}