{
  "type": "Feature",
  "properties": {
    "iso:country":"NL",
    "sg:address":"Prinsengracht 157Hs",
    "sg:city":"Amsterdam",
    "sg:orig_category":"Zalenexploitatie",
    "sg:phone":"+31 20 622 8465",
    "sg:postcode":"1015 DR",
    "sg:province":"Noord-Holland",
    "wof:name":"Galerie Fi Beiti",
    "wof:placetype":"venue"
},
  "geometry": {"coordinates":[4.887019,52.378391],"type":"Point"}
}