{
  "type": "Feature",
  "properties": {
    "iso:country":"NL",
    "sg:address":"Dr A Kuyperstr 58",
    "sg:city":"Moordrecht",
    "sg:orig_category":"Machinehandel",
    "sg:phone":"+31 182 372 930",
    "sg:postcode":"2841 CK",
    "sg:province":"South Holland",
    "wof:name":"Fil\u00e9 Bv, J",
    "wof:placetype":"venue"
},
  "geometry": {"coordinates":[4.66472,51.985458],"type":"Point"}
}