{
  "type": "Feature",
  "properties": {
    "addr:full":"Dr A Kuyperstr 58 Moordrecht South Holland 2841 CK",
    "addr:housenumber":"58",
    "addr:postcode":"2841 ck",
    "addr:street":"Dr;Kuyperstr",
    "iso:country":"NL",
    "sg:address":"Dr A Kuyperstr 58",
    "sg:city":"Moordrecht",
    "sg:orig_category":"Machinehandel",
    "sg:phone":"+31 182 372 930",
    "sg:postcode":"2841 CK",
    "sg:province":"South Holland",
    "wof:name":"Fil\u00e9 Bv, J",
    "wof:placetype":"venue"
},
  "geometry": {"coordinates":[4.66472,51.985458],"type":"Point"}
}