{
  "type": "Feature",
  "properties": {
    "addr:full":"Nieuwlandsedk 75 Lage Zwaluwe Noord-Brabant 4926 AN",
    "addr:housenumber":"75",
    "addr:postcode":"zwaluwe;4926 an",
    "addr:street":"Nieuwlandsedk",
    "iso:country":"NL",
    "sg:address":"Nieuwlandsedk 75",
    "sg:city":"Lage Zwaluwe",
    "sg:orig_category":"Bloemen En Planten",
    "sg:phone":"+31 168 482 461",
    "sg:postcode":"4926 AN",
    "sg:province":"Noord-Brabant",
    "wof:name":"Lentezwaluw, De",
    "wof:placetype":"venue"
},
  "geometry": {"coordinates":[4.69451,51.714191],"type":"Point"}
}