{
  "type": "Feature",
  "properties": {
    "addr:full":"Immeweide 2 Nieuwegein Utrecht 3437 VL",
    "addr:housenumber":"2",
    "addr:postcode":"3437 vl",
    "addr:street":"Immeweide",
    "iso:country":"NL",
    "sg:address":"Immeweide 2",
    "sg:city":"Nieuwegein",
    "sg:orig_category":"Administratie- En Boekhoudkantoren",
    "sg:phone":"+31 30 605 0900",
    "sg:postcode":"3437 VL",
    "sg:province":"Utrecht",
    "wof:name":"Assist 4 You",
    "wof:placetype":"venue"
},
  "geometry": {"coordinates":[5.068609,52.043289],"type":"Point"}
}