{
  "type": "Feature",
  "properties": {
    "addr:full":"Raadhuisplein 45 Krimpen A/D Ijssel Zuid-Holland 2922 AG",
    "addr:housenumber":"45;a / d",
    "addr:postcode":"2922",
    "addr:street":"Raadhuisplein",
    "iso:country":"NL",
    "sg:address":"Raadhuisplein 45",
    "sg:city":"Krimpen A/D Ijssel",
    "sg:orig_category":"Bloemen And Planten",
    "sg:phone":"+31 180 512 907",
    "sg:postcode":"2922 AG",
    "sg:province":"Zuid-Holland",
    "wof:name":"Bloemsierkunst Van Buuren",
    "wof:placetype":"venue"
},
  "geometry": {"coordinates":[4.59039,51.914467],"type":"Point"}
}