{
  "type": "Feature",
  "properties": {
    "iso:country":"NL",
    "sg:address":"Boekweitstraat 25",
    "sg:city":"Nieuw Vennep",
    "sg:orig_category":"Bedrijfs- And Managementsconsultants",
    "sg:phone":"+31 252 622 322",
    "sg:postcode":"2153 GK",
    "sg:province":"Noord-Holland",
    "wof:name":"Ster Entertainment Organisatie Buro",
    "wof:placetype":"venue"
},
  "geometry": {"coordinates":[4.648513,52.265152],"type":"Point"}
}