{
  "type": "Feature",
  "properties": {
    "addr:full":"Landpoortstraat 26 Ravenstein Noord-Brabant 5371 BT",
    "addr:housenumber":"26",
    "addr:postcode":"5371 bt",
    "addr:street":"Landpoortstraat",
    "iso:country":"NL",
    "sg:address":"Landpoortstraat 26",
    "sg:city":"Ravenstein",
    "sg:orig_category":"Juweliers",
    "sg:phone":"+31 486 411 692",
    "sg:postcode":"5371 BT",
    "sg:province":"Noord-Brabant",
    "wof:name":"W.G. Toebast",
    "wof:placetype":"venue"
},
  "geometry": {"coordinates":[5.650376,51.795155],"type":"Point"}
}