{
  "type": "Feature",
  "properties": {
    "addr:full":"Kerkstr 31 Nieuwaal Gelderland 5313 AP",
    "addr:housenumber":"31",
    "addr:postcode":"5313 ap",
    "addr:street":"Kerkstr;Gelderland",
    "iso:country":"NL",
    "sg:address":"Kerkstr 31",
    "sg:city":"Nieuwaal",
    "sg:orig_category":"Verenigingsgebouwen",
    "sg:phone":"+31 418 561 971",
    "sg:postcode":"5313 AP",
    "sg:province":"Gelderland",
    "wof:name":"Hoeksteen, De",
    "wof:placetype":"venue"
},
  "geometry": {"coordinates":[5.177465,51.809685],"type":"Point"}
}