{
  "type": "Feature",
  "properties": {
    "addr:full":"Reguliersgracht 65 Amsterdam North Holland 1017 LL",
    "addr:housenumber":"65",
    "addr:postcode":"1017 ll",
    "addr:street":"Reguliersgracht",
    "iso:country":"NL",
    "sg:address":"Reguliersgracht 65",
    "sg:city":"Amsterdam",
    "sg:orig_category":"Binnenhuisarchitecten",
    "sg:phone":"+31 20 638 0241",
    "sg:postcode":"1017 LL",
    "sg:province":"North Holland",
    "wof:name":"August Meubelen",
    "wof:placetype":"venue"
},
  "geometry": {"coordinates":[4.896385,52.362572],"type":"Point"}
}