{
  "type": "Feature",
  "properties": {
    "addr:full":"Europaplnts 26 Hoogmade Zuid-Holland 2355 AR",
    "addr:housenumber":"26",
    "addr:postcode":"2355",
    "addr:street":"Europaplnts",
    "iso:country":"NL",
    "sg:address":"Europaplnts 26",
    "sg:city":"Hoogmade",
    "sg:orig_category":"Betonboringen",
    "sg:phone":"+31 71 501 2640",
    "sg:postcode":"2355 AR",
    "sg:province":"Zuid-Holland",
    "wof:name":"Disseldorp, J",
    "wof:placetype":"venue"
},
  "geometry": {"coordinates":[4.583625,52.169239],"type":"Point"}
}