{
  "type": "Feature",
  "properties": {
    "addr:full":"Volmerln 9 Ryswyk Zh Zuid-Holland 2288 GD",
    "addr:housenumber":"9",
    "addr:postcode":"2288 gd",
    "addr:street":"Volmerln",
    "iso:country":"NL",
    "sg:address":"Volmerln 9",
    "sg:city":"Ryswyk Zh",
    "sg:orig_category":"Ongediertebestrijding En Ontsmetting",
    "sg:phone":"+31 800 7368654",
    "sg:postcode":"2288 GD",
    "sg:province":"Zuid-Holland",
    "sg:website":"http://www.rentokil.nl",
    "wof:name":"Rentokil Initial Bv",
    "wof:placetype":"venue"
},
  "geometry": {"coordinates":[4.32436,52.037251],"type":"Point"}
}