{
  "type": "Feature",
  "properties": {
    "addr:full":"Mgr Van Roosmalenplein 54 'S Hertogenbosch Noord-Brabant 5213 GD",
    "addr:housenumber":"54",
    "addr:postcode":"5213 gd",
    "addr:street":"Mgr Van Roosmalenplein;' S",
    "iso:country":"NL",
    "sg:address":"Mgr Van Roosmalenplein 54",
    "sg:city":"'S Hertogenbosch",
    "sg:classifiers":[
        {
            "category":"Food & Beverages",
            "subcategory":"Fruits & Vegetables",
            "type":"Retail Goods"
        }
    ],
    "sg:phone":"+31 73 613 9902",
    "sg:postcode":"5213 GD",
    "sg:province":"Noord-Brabant",
    "sg:tags":[
        "groenten"
    ],
    "wof:name":"Groenten- En Fruithdl Harrie Goesten",
    "wof:placetype":"venue"
},
  "geometry": {"coordinates":[5.32952,51.695641],"type":"Point"}
}