{
  "type": "Feature",
  "properties": {
    "addr:full":"De Brink 61 Losser NL.08 7581 JD",
    "addr:housenumber":"61;nl.08",
    "addr:postcode":"7581 jd",
    "addr:street":"De Brink",
    "iso:country":"NL",
    "sg:address":"De Brink 61",
    "sg:city":"Losser",
    "sg:orig_category":"Juweliers",
    "sg:phone":"+31 53 538 3181",
    "sg:postcode":"7581 JD",
    "sg:province":"NL.08",
    "wof:name":"Willy Smit",
    "wof:placetype":"venue"
},
  "geometry": {"coordinates":[7.007679,52.263252],"type":"Point"}
}