{
  "type": "Feature",
  "properties": {
    "iso:country":"NL",
    "sg:address":"Eektestraat 14",
    "sg:city":"Oldenzaal",
    "sg:orig_category":"Kantoorartikelen",
    "sg:phone":"+31 541 585 756",
    "sg:postcode":"7575 AP",
    "sg:province":"Overijssel",
    "wof:name":"Sko Bv",
    "wof:placetype":"venue"
},
  "geometry": {"coordinates":[6.9229931831,52.3025016785],"type":"Point"}
}