{
  "type": "Feature",
  "properties": {
    "addr:full":"Lizzy Ansinghstraat 88 Amsterdam Noord-Holland 1072 RD",
    "addr:housenumber":"88",
    "addr:postcode":"1072 rd",
    "addr:street":"Lizzy Ansinghstraat",
    "iso:country":"NL",
    "sg:address":"Lizzy Ansinghstraat 88",
    "sg:city":"Amsterdam",
    "sg:orig_category":"Fitnesscentra",
    "sg:phone":"+31 20 675 9632",
    "sg:postcode":"1072 RD",
    "sg:province":"Noord-Holland",
    "wof:name":"Wu-Shu Akademie Amsterdamse",
    "wof:placetype":"venue"
},
  "geometry": {"coordinates":[4.894439,52.349819],"type":"Point"}
}