{
  "type": "Feature",
  "properties": {
    "iso:country":"NL",
    "sg:address":"Rading 128",
    "sg:city":"Loosdrecht",
    "sg:orig_category":"Automaterialen En Gereedschappen",
    "sg:phone":"+31 35 582 5184",
    "sg:postcode":"1231 KD",
    "sg:province":"Noord-Holland",
    "sg:website":"http://www.autowessel.nl",
    "wof:name":"Wessel, Auto",
    "wof:placetype":"venue"
},
  "geometry": {"coordinates":[5.144977,52.196831],"type":"Point"}
}