{
  "type": "Feature",
  "properties": {
    "addr:full":"P C Hooftstr 50/1 Amsterdam Missouri 1071 CA",
    "addr:housenumber":"50 / 1",
    "addr:postcode":"1071 ca",
    "addr:street":"P C Hooftstr",
    "iso:country":"NL",
    "sg:address":"P C Hooftstr 50/1",
    "sg:city":"Amsterdam",
    "sg:orig_category":"Kappers",
    "sg:phone":"+31 20 671 7375",
    "sg:postcode":"1071 CA",
    "sg:province":"Missouri",
    "wof:name":"Pc Hair",
    "wof:placetype":"venue"
},
  "geometry": {"coordinates":[-94.58503,38.350479],"type":"Point"}
}