{
  "type": "Feature",
  "properties": {
    "addr:full":"Rijksweg 12 Milsbeek Limburg 6596 AB",
    "addr:housenumber":"12",
    "addr:postcode":"6596 ab",
    "addr:street":"Rijksweg",
    "iso:country":"NL",
    "sg:address":"Rijksweg 12",
    "sg:city":"Milsbeek",
    "sg:orig_category":"Farmaceutische Producten Gh",
    "sg:phone":"+31 485 540 252",
    "sg:postcode":"6596 AB",
    "sg:province":"Limburg",
    "wof:name":"Vof Eisma",
    "wof:placetype":"venue"
},
  "geometry": {"coordinates":[5.954162,51.719666],"type":"Point"}
}