{
  "type": "Feature",
  "properties": {
    "addr:full":"Hoofdwg 153 Zegveld Utrecht 3474 JC",
    "addr:housenumber":"153",
    "addr:postcode":"3474 jc",
    "addr:street":"Zegveld",
    "iso:country":"NL",
    "sg:address":"Hoofdwg 153",
    "sg:city":"Zegveld",
    "sg:orig_category":"Luchtbehandelings- Apparaten",
    "sg:phone":"+31 348 691 665",
    "sg:postcode":"3474 JC",
    "sg:province":"Utrecht",
    "wof:name":"Lousette",
    "wof:placetype":"venue"
},
  "geometry": {"coordinates":[4.845758,52.108574],"type":"Point"}
}