{
  "type": "Feature",
  "properties": {
    "addr:full":"Voorstondensestr 26 Hall Gelderland 6964 CD",
    "addr:housenumber":"26",
    "addr:postcode":"6964 cd",
    "addr:street":"Voorstondensestr;Gelderland",
    "iso:country":"NL",
    "sg:address":"Voorstondensestr 26",
    "sg:city":"Hall",
    "sg:orig_category":"Paardenhandelaren",
    "sg:phone":"+31 313 651 569",
    "sg:postcode":"6964 CD",
    "sg:province":"Gelderland",
    "wof:name":"Welmers, F H",
    "wof:placetype":"venue"
},
  "geometry": {"coordinates":[-113.196388,46.589054],"type":"Point"}
}