{
  "type": "Feature",
  "properties": {
    "addr:full":"Franciscuswg 281 Hilversum Noord-Holland 1216 SG",
    "addr:housenumber":"281",
    "addr:postcode":"hilversum;1216 sg",
    "iso:country":"NL",
    "sg:address":"Franciscuswg 281",
    "sg:city":"Hilversum",
    "sg:orig_category":"Bioscoopreclame",
    "sg:phone":"+31 35 625 4343",
    "sg:postcode":"1216 SG",
    "sg:province":"Noord-Holland",
    "sg:website":"http://www.cineview.nl",
    "wof:name":"Cine-View",
    "wof:placetype":"venue"
},
  "geometry": {"coordinates":[5.148346,52.214005],"type":"Point"}
}