{
  "type": "Feature",
  "properties": {
    "addr:full":"Buitenhaven 9 Nieuwpoort Zuid-Holland 2965 AD",
    "addr:housenumber":"9",
    "addr:postcode":"2965 ad",
    "addr:street":"Buitenhaven",
    "iso:country":"NL",
    "sg:address":"Buitenhaven 9",
    "sg:city":"Nieuwpoort",
    "sg:orig_category":"Woningbouw- Verenigingen En -Stichtingen",
    "sg:phone":"+31 184 601 922",
    "sg:postcode":"2965 AD",
    "sg:province":"Zuid-Holland",
    "wof:name":"Lek En Waard Wonen",
    "wof:placetype":"venue"
},
  "geometry": {"coordinates":[4.8679180145,51.9356994629],"type":"Point"}
}