{
  "type": "Feature",
  "properties": {
    "addr:full":"Andreaspln 11 Katwyk Zh Zuid-Holland 2225 GR",
    "addr:housenumber":"11",
    "addr:postcode":"2225",
    "addr:street":"Andreaspln",
    "iso:country":"NL",
    "sg:address":"Andreaspln 11",
    "sg:city":"Katwyk Zh",
    "sg:orig_category":"Cafetaria'S",
    "sg:phone":"+31 71 407 7159",
    "sg:postcode":"2225 GR",
    "sg:province":"Zuid-Holland",
    "wof:name":"Mosselaar, De",
    "wof:placetype":"venue"
},
  "geometry": {"coordinates":[4.39379,52.202583],"type":"Point"}
}