{
  "type": "Feature",
  "properties": {
    "addr:full":"Lindenburg 82 Roosendaal Noord-Brabant 4707 CR",
    "addr:housenumber":"82",
    "addr:postcode":"4707 cr",
    "addr:street":"Lindenburg",
    "iso:country":"NL",
    "sg:address":"Lindenburg 82",
    "sg:city":"Roosendaal",
    "sg:orig_category":"Verzekeringen - Verzekeringskantoren",
    "sg:phone":"+31 165 521 770",
    "sg:postcode":"4707 CR",
    "sg:province":"Noord-Brabant",
    "wof:name":"Voets Roosendaal Bv",
    "wof:placetype":"venue"
},
  "geometry": {"coordinates":[4.473427,51.520588],"type":"Point"}
}