{
  "type": "Feature",
  "properties": {
    "addr:full":"Oosteinderwg 247A Aalsmeer Noord-Holland 1432 AT",
    "addr:housenumber":"247a",
    "addr:postcode":"1432",
    "iso:country":"NL",
    "sg:address":"Oosteinderwg 247A",
    "sg:city":"Aalsmeer",
    "sg:orig_category":"Kinderactiviteiten",
    "sg:phone":"+31 297 331 259",
    "sg:postcode":"1432 AT",
    "sg:province":"Noord-Holland",
    "sg:website":"http://www.alleskidsinthebeach.nl",
    "wof:name":"Alles Kids In The Beach",
    "wof:placetype":"venue"
},
  "geometry": {"coordinates":[4.7863,52.280369],"type":"Point"}
}