{
  "type": "Feature",
  "properties": {
    "addr:full":"W De Withstr 114-116 Amsterdam Noord-Holland 1057 ZG",
    "addr:housenumber":"114-116",
    "addr:postcode":"1057 zg",
    "addr:street":"W De Withstr",
    "iso:country":"NL",
    "sg:address":"W De Withstr 114-116",
    "sg:city":"Amsterdam",
    "sg:orig_category":"Autorijscholen",
    "sg:phone":"+31 20 616 3042",
    "sg:postcode":"1057 ZG",
    "sg:province":"Noord-Holland",
    "sg:website":"http://www.janblom.nl",
    "wof:name":"Blom Verkeersschool, Jan",
    "wof:placetype":"venue"
},
  "geometry": {"coordinates":[4.859366,52.369396],"type":"Point"}
}