{
  "type": "Feature",
  "properties": {
    "addr:full":"Bramenhof 11 Nykerk Gld Gelderland 3862 WR",
    "addr:housenumber":"11",
    "addr:postcode":"3862",
    "addr:street":"Bramenhof;Gld Gelderland",
    "iso:country":"NL",
    "sg:address":"Bramenhof 11",
    "sg:city":"Nykerk Gld",
    "sg:orig_category":"Adviesbureaus Bedrijfsorganisatie",
    "sg:phone":"+31 33 247 0625",
    "sg:postcode":"3862 WR",
    "sg:province":"Gelderland",
    "wof:name":"Vamar Ned Bv",
    "wof:placetype":"venue"
},
  "geometry": {"coordinates":[5.498657,52.21928],"type":"Point"}
}