{
  "type": "Feature",
  "properties": {
    "addr:full":"Prins Bernhardlaan 50 Heelsum Gelderland 6866 BZ",
    "addr:housenumber":"50",
    "addr:postcode":"6866 bz",
    "addr:street":"Prins Bernhardlaan;Gelderland",
    "iso:country":"NL",
    "sg:address":"Prins Bernhardlaan 50",
    "sg:city":"Heelsum",
    "sg:classifiers":[
        {
            "category":"Professional",
            "subcategory":"Accounting & Tax Preparation",
            "type":"Services"
        }
    ],
    "sg:phone":"+31 317 312 049",
    "sg:postcode":"6866 BZ",
    "sg:province":"Gelderland",
    "sg:tags":[
        "accountant"
    ],
    "wof:name":"Registeraccountant M. Geelkerken",
    "wof:placetype":"venue"
},
  "geometry": {"coordinates":[5.752394,51.983749],"type":"Point"}
}