{
  "type": "Feature",
  "properties": {
    "addr:full":"Niemeijerstraat 21 Wageningen Gelderland 6701 CL",
    "addr:housenumber":"21",
    "addr:postcode":"6701",
    "addr:street":"Niemeijerstraat;Gelderland",
    "iso:country":"NL",
    "sg:address":"Niemeijerstraat 21",
    "sg:city":"Wageningen",
    "sg:orig_category":"Beautyfarms And Sauna'S",
    "sg:phone":"+31 317 411 684",
    "sg:postcode":"6701 CL",
    "sg:province":"Gelderland",
    "wof:name":"J.C. Dee",
    "wof:placetype":"venue"
},
  "geometry": {"coordinates":[5.6623950005,51.9631195068],"type":"Point"}
}