{
  "type": "Feature",
  "properties": {
    "addr:full":"Ettensebaan 30 Breda North Brabant 4814 NN",
    "addr:housenumber":"30",
    "addr:postcode":"4814 nn",
    "addr:street":"Ettensebaan",
    "iso:country":"NL",
    "sg:address":"Ettensebaan 30",
    "sg:city":"Breda",
    "sg:orig_category":"Benzinestations And Brandstoffen",
    "sg:phone":"+31 76 514 3916",
    "sg:postcode":"4814 NN",
    "sg:province":"North Brabant",
    "wof:name":"Esso",
    "wof:placetype":"venue"
},
  "geometry": {"coordinates":[4.750118,51.583309],"type":"Point"}
}