{
  "type": "Feature",
  "properties": {
    "iso:country":"NL",
    "sg:address":"Ettensebaan 30",
    "sg:city":"Breda",
    "sg:orig_category":"Benzinestations And Brandstoffen",
    "sg:phone":"+31 76 514 3916",
    "sg:postcode":"4814 NN",
    "sg:province":"North Brabant",
    "wof:name":"Esso",
    "wof:placetype":"venue"
},
  "geometry": {"coordinates":[4.750118,51.583309],"type":"Point"}
}