{
  "type": "Feature",
  "properties": {
    "addr:full":"Jacob Van Deventerstraat 7 Beverwijk Noord-Holland 1941 EP",
    "addr:housenumber":"7",
    "addr:postcode":"1941 ep",
    "addr:street":"Jacob Van Deventerstraat",
    "iso:country":"NL",
    "sg:address":"Jacob Van Deventerstraat 7",
    "sg:city":"Beverwijk",
    "sg:orig_category":"Makelaars In Onroerend Goed",
    "sg:phone":"+31 251 276 060",
    "sg:postcode":"1941 EP",
    "sg:province":"Noord-Holland",
    "wof:name":"Kuijs Reinder Kakes",
    "wof:placetype":"venue"
},
  "geometry": {"coordinates":[4.660663,52.483253],"type":"Point"}
}