{
  "type": "Feature",
  "properties": {
    "iso:country":"NL",
    "sg:address":"Hoendiep 99D",
    "sg:city":"Groningen",
    "sg:orig_category":"Woninginrichting",
    "sg:phone":"+31 50 313 4204",
    "sg:postcode":"9718 TE",
    "sg:province":"Groningen",
    "wof:name":"Decorette",
    "wof:placetype":"venue"
},
  "geometry": {"coordinates":[6.543129921,53.2135810852],"type":"Point"}
}