{
  "type": "Feature",
  "properties": {
    "addr:full":"Edenstraat 29 Eindhoven Noord-Brabant 5611 JN",
    "addr:housenumber":"29",
    "addr:postcode":"5611 jn",
    "addr:street":"Edenstraat",
    "iso:country":"NL",
    "sg:address":"Edenstraat 29",
    "sg:city":"Eindhoven",
    "sg:orig_category":"Paramedische Behandelingen",
    "sg:phone":"+31 40 244 7251",
    "sg:postcode":"5611 JN",
    "sg:province":"Noord-Brabant",
    "wof:name":"Eindhovens Psychologisch Instituut",
    "wof:placetype":"venue"
},
  "geometry": {"coordinates":[5.477274,51.431763],"type":"Point"}
}