{
  "type": "Feature",
  "properties": {
    "addr:full":"Kalkoensprenk 40 Vlissingen Zeeland 4386 DD",
    "addr:housenumber":"40",
    "addr:postcode":"4386 dd",
    "addr:street":"Kalkoensprenk",
    "iso:country":"NL",
    "sg:address":"Kalkoensprenk 40",
    "sg:city":"Vlissingen",
    "sg:orig_category":"Parketvloeren",
    "sg:phone":"+31 118 472 029",
    "sg:postcode":"4386 DD",
    "sg:province":"Zeeland",
    "wof:name":"Perfekt",
    "wof:placetype":"venue"
},
  "geometry": {"coordinates":[3.577348,51.465733],"type":"Point"}
}