{
  "type": "Feature",
  "properties": {
    "addr:full":"De Ruyterstr 94C S Gravenhage South Holland 2518 AW",
    "addr:housenumber":"94c",
    "addr:postcode":"2518 aw",
    "addr:street":"S Gravenhage",
    "iso:country":"NL",
    "sg:address":"De Ruyterstr 94C",
    "sg:city":"S Gravenhage",
    "sg:orig_category":"Mineralen",
    "sg:phone":"+31 70 364 7909",
    "sg:postcode":"2518 AW",
    "sg:province":"South Holland",
    "wof:name":"Chivine Bv",
    "wof:placetype":"venue"
},
  "geometry": {"coordinates":[4.29348,52.080318],"type":"Point"}
}