{
  "type": "Feature",
  "properties": {
    "addr:full":"Plaszoom 350 Rotterdam Zuid-Holland 3062 CL",
    "addr:housenumber":"350",
    "addr:postcode":"3062",
    "addr:street":"Plaszoom",
    "iso:country":"NL",
    "sg:address":"Plaszoom 350",
    "sg:city":"Rotterdam",
    "sg:orig_category":"Zeilscholen",
    "sg:phone":"+31 10 412 1098",
    "sg:postcode":"3062 CL",
    "sg:province":"Zuid-Holland",
    "sg:website":"http://www.henkvangent.nl",
    "wof:name":"Henk Van Gent Zeilcentrum",
    "wof:placetype":"venue"
},
  "geometry": {"coordinates":[4.52177,51.932499],"type":"Point"}
}