{
  "type": "Feature",
  "properties": {
    "addr:full":"Ettensestraat 19 Terborg Gelderland 7061 AA",
    "addr:housenumber":"19",
    "addr:postcode":"7061 aa",
    "addr:street":"Ettensestraat;Gelderland",
    "iso:country":"NL",
    "sg:address":"Ettensestraat 19",
    "sg:city":"Terborg",
    "sg:orig_category":"Kappers",
    "sg:phone":"+31 315 323 584",
    "sg:postcode":"7061 AA",
    "sg:province":"Gelderland",
    "wof:name":"Kapsalon Trendline Haarmode",
    "wof:placetype":"venue"
},
  "geometry": {"coordinates":[6.3494009972,51.9169960022],"type":"Point"}
}