{
  "type": "Feature",
  "properties": {
    "addr:full":"Hinthamerstr 196-198 S Hertogenbosch Noord-Brabant 5211 MX",
    "addr:housenumber":"196-198",
    "addr:postcode":"5211 mx",
    "addr:street":"S Hertogenbosch",
    "iso:country":"NL",
    "sg:address":"Hinthamerstr 196-198",
    "sg:city":"S Hertogenbosch",
    "sg:orig_category":"Antiquiteiten",
    "sg:phone":"+31 73 613 2060",
    "sg:postcode":"5211 MX",
    "sg:province":"Noord-Brabant",
    "wof:name":"Karel Greven Antiquiteiten",
    "wof:placetype":"venue"
},
  "geometry": {"coordinates":[5.31317,51.688438],"type":"Point"}
}