{
  "type": "Feature",
  "properties": {
    "addr:full":"Beukenlaan 66 Soest Utrecht 3762 AJ",
    "addr:housenumber":"66",
    "addr:postcode":"3762 aj",
    "addr:street":"Beukenlaan",
    "iso:country":"NL",
    "sg:address":"Beukenlaan 66",
    "sg:city":"Soest",
    "sg:orig_category":"Kappers",
    "sg:phone":"+31 35 602 5183",
    "sg:postcode":"3762 AJ",
    "sg:province":"Utrecht",
    "wof:name":"Kapsalon Musab",
    "wof:placetype":"venue"
},
  "geometry": {"coordinates":[5.2907671928,52.1753959656],"type":"Point"}
}