{
  "type": "Feature",
  "properties": {
    "addr:full":"Donkere Spaarne 56 Haarlem North Holland 2011 JH",
    "addr:housenumber":"56",
    "addr:postcode":"2011 jh",
    "addr:street":"Donkere Spaarne",
    "iso:country":"NL",
    "sg:address":"Donkere Spaarne 56",
    "sg:city":"Haarlem",
    "sg:orig_category":"Effectenmakelaars And Fondsenbeheer",
    "sg:phone":"+31 23 531 5186",
    "sg:postcode":"2011 JH",
    "sg:province":"North Holland",
    "wof:name":"Aespen Futures Bv",
    "wof:placetype":"venue"
},
  "geometry": {"coordinates":[4.641664,52.380585],"type":"Point"}
}