{
  "type": "Feature",
  "properties": {
    "addr:full":"Oranjesingel 66 Nijmegen Gelderland 6511 NZ",
    "addr:housenumber":"66",
    "addr:postcode":"6511 nz",
    "addr:street":"Oranjesingel;Gelderland",
    "iso:country":"NL",
    "sg:address":"Oranjesingel 66",
    "sg:city":"Nijmegen",
    "sg:orig_category":"Juridische Dienstverlening",
    "sg:phone":"+31 24 360 7819",
    "sg:postcode":"6511 NZ",
    "sg:province":"Gelderland",
    "wof:name":"Kleijsen Cortenbach & Kuijpers Cs",
    "wof:placetype":"venue"
},
  "geometry": {"coordinates":[5.867047,51.84317],"type":"Point"}
}