{
  "type": "Feature",
  "properties": {
    "addr:full":"Radermacherstr 32 Arnemuiden Zeeland 4341 GX",
    "addr:housenumber":"32",
    "addr:postcode":"4341 gx",
    "addr:street":"Radermacherstr",
    "iso:country":"NL",
    "sg:address":"Radermacherstr 32",
    "sg:city":"Arnemuiden",
    "sg:orig_category":"Verenigingsgebouwen",
    "sg:phone":"+31 118 601 447",
    "sg:postcode":"4341 GX",
    "sg:province":"Zeeland",
    "wof:name":"Arne, De",
    "wof:placetype":"venue"
},
  "geometry": {"coordinates":[3.678403,51.500732],"type":"Point"}
}