{
  "type": "Feature",
  "properties": {
    "addr:full":"Antonia Veerstraat 32 Delft Zuid-Holland 2614 HV",
    "addr:housenumber":"32",
    "addr:postcode":"2614 hv",
    "addr:street":"Antonia Veerstraat",
    "iso:country":"NL",
    "sg:address":"Antonia Veerstraat 32",
    "sg:city":"Delft",
    "sg:orig_category":"Binnenhuisarchitecten",
    "sg:phone":"+31 15 256 7425",
    "sg:postcode":"2614 HV",
    "sg:province":"Zuid-Holland",
    "wof:name":"A. De Kloet",
    "wof:placetype":"venue"
},
  "geometry": {"coordinates":[4.344626,52.001129],"type":"Point"}
}