{
  "type": "Feature",
  "properties": {
    "addr:full":"Stougjesdk 247 Oud Beyerland Zuid-Holland 3261 KV",
    "addr:housenumber":"247",
    "addr:postcode":"3261 kv",
    "addr:street":"Oud Beyerland",
    "iso:country":"NL",
    "sg:address":"Stougjesdk 247",
    "sg:city":"Oud Beyerland",
    "sg:orig_category":"Goudsmeden En Zilversmeden",
    "sg:phone":"+31 186 615 871",
    "sg:postcode":"3261 KV",
    "sg:province":"Zuid-Holland",
    "wof:name":"Wermer-Van Raamt, E G",
    "wof:placetype":"venue"
},
  "geometry": {"coordinates":[4.437202,51.814724],"type":"Point"}
}