{
  "type": "Feature",
  "properties": {
    "addr:full":"Afrikaln 3 Vroomshoop Overijssel 7681 ND",
    "addr:housenumber":"3",
    "addr:postcode":"7681 nd",
    "addr:street":"Afrikaln",
    "iso:country":"NL",
    "sg:address":"Afrikaln 3",
    "sg:city":"Vroomshoop",
    "sg:orig_category":"Keukens",
    "sg:phone":"+31 546 660 400",
    "sg:postcode":"7681 ND",
    "sg:province":"Overijssel",
    "sg:website":"http://www.palazzokeukendesign.nl",
    "wof:name":"Palazzo",
    "wof:placetype":"venue"
},
  "geometry": {"coordinates":[6.581669,52.454456],"type":"Point"}
}