{
  "type": "Feature",
  "properties": {
    "addr:full":"Kouwerplantsoen 18 Utrecht Utrecht 3571 LT",
    "addr:housenumber":"18",
    "addr:postcode":"3571 lt",
    "addr:street":"Kouwerplantsoen",
    "iso:country":"NL",
    "sg:address":"Kouwerplantsoen 18",
    "sg:city":"Utrecht",
    "sg:orig_category":"Boekhouders",
    "sg:phone":"+31 30 271 7107",
    "sg:postcode":"3571 LT",
    "sg:province":"Utrecht",
    "wof:name":"Bureau A.C. Baars Bv",
    "wof:placetype":"venue"
},
  "geometry": {"coordinates":[5.137763,52.107609],"type":"Point"}
}