{
  "type": "Feature",
  "properties": {
    "iso:country":"NL",
    "sg:address":"Clermontstr 5",
    "sg:city":"Margraten",
    "sg:orig_category":"Bloemen En Planten",
    "sg:phone":"+31 43 458 9199",
    "sg:postcode":"6269 CE",
    "sg:province":"Limburg",
    "wof:name":"Anemoontje, 'T",
    "wof:placetype":"venue"
},
  "geometry": {"coordinates":[5.820652,50.821259],"type":"Point"}
}