{
  "type": "Feature",
  "properties": {
    "addr:full":"Myehof 309 Amsterdam Zuidoost North Holland 1106 HJ",
    "addr:housenumber":"309",
    "addr:postcode":"1106 hj",
    "addr:street":"Myehof",
    "iso:country":"NL",
    "sg:address":"Myehof 309",
    "sg:city":"Amsterdam Zuidoost",
    "sg:orig_category":"Kinderkleding",
    "sg:phone":"+31 20 694 2794",
    "sg:postcode":"1106 HJ",
    "sg:province":"North Holland",
    "wof:name":"Vingerhoed, De",
    "wof:placetype":"venue"
},
  "geometry": {"coordinates":[4.966732,52.297852],"type":"Point"}
}