{
  "type": "Feature",
  "properties": {
    "addr:full":"Rosariumstr 61 Apeldoorn Gelderland 7311 JR",
    "addr:housenumber":"61",
    "addr:postcode":"7311 jr",
    "addr:street":"Rosariumstr;Gelderland",
    "iso:country":"NL",
    "sg:address":"Rosariumstr 61",
    "sg:city":"Apeldoorn",
    "sg:orig_category":"Administratie- En Boekhoudkantoren",
    "sg:phone":"+31 55 576 9069",
    "sg:postcode":"7311 JR",
    "sg:province":"Gelderland",
    "wof:name":"Poel & Partners Bv, Administratie- En Advieskantoor",
    "wof:placetype":"venue"
},
  "geometry": {"coordinates":[5.96502,52.211529],"type":"Point"}
}