{
  "type": "Feature",
  "properties": {
    "iso:country":"NL",
    "sg:address":"Grotestraat 199",
    "sg:city":"Waalwijk",
    "sg:orig_category":"Kappers",
    "sg:phone":"+31 416 341 843",
    "sg:postcode":"5141 JS",
    "sg:province":"Noord-Brabant",
    "wof:name":"Coiffure House Waalwijk",
    "wof:placetype":"venue"
},
  "geometry": {"coordinates":[5.063147068,51.6903343201],"type":"Point"}
}