{
  "type": "Feature",
  "properties": {
    "addr:full":"Ridder A V Amstelstraat 36 Polsbroek Utrecht 3415 PN",
    "addr:housenumber":"36",
    "addr:postcode":"3415 pn",
    "addr:street":"Ridder A V Amstelstraat",
    "iso:country":"NL",
    "sg:address":"Ridder A V Amstelstraat 36",
    "sg:city":"Polsbroek",
    "sg:orig_category":"Zuivelproducten And Spijsoli?n Gh",
    "sg:phone":"+31 182 309 626",
    "sg:postcode":"3415 PN",
    "sg:province":"Utrecht",
    "wof:name":"G.J. Verstoep En W.M. Verstoep V/D Vlist",
    "wof:placetype":"venue"
},
  "geometry": {"coordinates":[4.850565,51.976818],"type":"Point"}
}