{
  "type": "Feature",
  "properties": {
    "addr:full":"Ranonkellaan 6 Krommenie Noord-Holland 1562 AT",
    "addr:housenumber":"6",
    "addr:postcode":"1562",
    "addr:street":"Ranonkellaan",
    "iso:country":"NL",
    "sg:address":"Ranonkellaan 6",
    "sg:city":"Krommenie",
    "sg:orig_category":"Diverse Grafische Activiteiten",
    "sg:phone":"+31 75 628 7172",
    "sg:postcode":"1562 AT",
    "sg:province":"Noord-Holland",
    "wof:name":"Van Poorten Grafische Produkties",
    "wof:placetype":"venue"
},
  "geometry": {"coordinates":[4.757721,52.507172],"type":"Point"}
}