{
  "type": "Feature",
  "properties": {
    "addr:full":"Damstraat 21 Yerseke Zeeland 4401 AA",
    "addr:housenumber":"21",
    "addr:postcode":"4401 aa",
    "addr:street":"Damstraat",
    "iso:country":"NL",
    "sg:address":"Damstraat 21",
    "sg:city":"Yerseke",
    "sg:orig_category":"Banken And Kredietinstellingen",
    "sg:phone":"+31 113 571 322",
    "sg:postcode":"4401 AA",
    "sg:province":"Zeeland",
    "wof:name":"Postkantoor",
    "wof:placetype":"venue"
},
  "geometry": {"coordinates":[4.049158,51.494888],"type":"Point"}
}