{
  "type": "Feature",
  "properties": {
    "addr:full":"Stuyvesantstr 82Zw Haarlem Noord-Holland 2023 KR",
    "addr:housenumber":"82zw",
    "addr:postcode":"2023 kr",
    "addr:street":"Stuyvesantstr",
    "iso:country":"NL",
    "sg:address":"Stuyvesantstr 82Zw",
    "sg:city":"Haarlem",
    "sg:orig_category":"Beeldende Kunstenaars",
    "sg:phone":"+31 23 526 3601",
    "sg:postcode":"2023 KR",
    "sg:province":"Noord-Holland",
    "wof:name":"Vondel, Wendy Van",
    "wof:placetype":"venue"
},
  "geometry": {"coordinates":[4.631514,52.40073],"type":"Point"}
}