{
  "type": "Feature",
  "properties": {
    "addr:full":"Mijlstraat 37 Boxtel Noord-Brabant 5281 LJ",
    "addr:housenumber":"37",
    "addr:postcode":"5281 lj",
    "addr:street":"Mijlstraat",
    "iso:country":"NL",
    "sg:address":"Mijlstraat 37",
    "sg:city":"Boxtel",
    "sg:orig_category":"Elektronische Bedrijfsinstallaties",
    "sg:phone":"+31 411 676 539",
    "sg:postcode":"5281 LJ",
    "sg:province":"Noord-Brabant",
    "wof:name":"Schelle Electronica",
    "wof:placetype":"venue"
},
  "geometry": {"coordinates":[5.31197,51.581833],"type":"Point"}
}