{
  "type": "Feature",
  "properties": {
    "iso:country":"NL",
    "sg:address":"Postbus 166",
    "sg:city":"Nymegen",
    "sg:orig_category":"Bedrijfsopleidingen",
    "sg:phone":"+31 24 356 7825",
    "sg:postcode":"6500 AD",
    "wof:name":"Stanza Teambalans",
    "wof:placetype":"venue"
},
  "geometry": {"coordinates":[5.83296,51.842651],"type":"Point"}
}