{
  "type": "Feature",
  "properties": {
    "iso:country":"NL",
    "sg:address":"Graswinckelstr 70",
    "sg:city":"Delft",
    "sg:orig_category":"Onderhoudswerken",
    "sg:phone":"+31 15 213 8750",
    "sg:postcode":"2613 PX",
    "sg:province":"Zuid-Holland",
    "wof:name":"Edje Onderhoudsbedrijf",
    "wof:placetype":"venue"
},
  "geometry": {"coordinates":[4.353686,52.006199],"type":"Point"}
}