{
  "type": "Feature",
  "properties": {
    "addr:full":"Nieuwstraat 40 Middelburg Zeeland 4331 JL",
    "addr:housenumber":"40",
    "addr:postcode":"4331 jl",
    "addr:street":"Nieuwstraat",
    "iso:country":"NL",
    "sg:address":"Nieuwstraat 40",
    "sg:city":"Middelburg",
    "sg:orig_category":"Verhuur Gereedschapsmachines And Gereedschappen",
    "sg:phone":"+31 118 611 309",
    "sg:postcode":"4331 JL",
    "sg:province":"Zeeland",
    "wof:name":"Schets & Zn",
    "wof:placetype":"venue"
},
  "geometry": {"coordinates":[3.617364,51.498714],"type":"Point"}
}