{
  "type": "Feature",
  "properties": {
    "addr:full":"Westerstouwe 31 Staphorst Provincie Drenthe 7951 KH",
    "addr:housenumber":"31",
    "addr:postcode":"7951 kh",
    "addr:street":"Westerstouwe;Provincie Drenthe",
    "iso:country":"NL",
    "sg:address":"Westerstouwe 31",
    "sg:city":"Staphorst",
    "sg:orig_category":"Verlichting And Huishoudartikelen",
    "sg:phone":"+31 522 253 802",
    "sg:postcode":"7951 KH",
    "sg:province":"Provincie Drenthe",
    "wof:name":"Huishoudwinkel Lamb. Pot",
    "wof:placetype":"venue"
},
  "geometry": {"coordinates":[6.182967,52.681953],"type":"Point"}
}