{
  "type": "Feature",
  "properties": {
    "iso:country":"NL",
    "sg:address":"T Loo 51",
    "sg:city":"Heiloo",
    "sg:orig_category":"Kantoorartikelen",
    "sg:phone":"+31 72 533 9774",
    "sg:postcode":"1851 HT",
    "sg:province":"North Holland",
    "wof:name":"Gerard Schoon",
    "wof:placetype":"venue"
},
  "geometry": {"coordinates":[4.7121100426,52.6052932739],"type":"Point"}
}