{
  "type": "Feature",
  "properties": {
    "addr:full":"T Loo 51 Heiloo North Holland 1851 HT",
    "addr:housenumber":"51",
    "addr:postcode":"1851 ht",
    "addr:street":"T Loo",
    "iso:country":"NL",
    "sg:address":"T Loo 51",
    "sg:city":"Heiloo",
    "sg:orig_category":"Kantoorartikelen",
    "sg:phone":"+31 72 533 9774",
    "sg:postcode":"1851 HT",
    "sg:province":"North Holland",
    "wof:name":"Gerard Schoon",
    "wof:placetype":"venue"
},
  "geometry": {"coordinates":[4.7121100426,52.6052932739],"type":"Point"}
}