{
  "type": "Feature",
  "properties": {
    "addr:full":"Burg S Jacobln 2A Bussum Noord-Holland 1401 BM",
    "addr:housenumber":"2a",
    "addr:postcode":"1401 bm",
    "addr:street":"Burg S Jacobln",
    "iso:country":"NL",
    "sg:address":"Burg S Jacobln 2A",
    "sg:city":"Bussum",
    "sg:classifiers":[
        {
            "category":"Professional",
            "subcategory":"Management & Consulting",
            "type":"Services"
        }
    ],
    "sg:phone":"+31 35 693 4577",
    "sg:postcode":"1401 BM",
    "sg:province":"Noord-Holland",
    "sg:tags":[
        "relation",
        "adviesbureaus",
        "public"
    ],
    "sg:website":"http://www.opr-advies.nl",
    "wof:name":"Opr",
    "wof:placetype":"venue"
},
  "geometry": {"coordinates":[5.162605,52.276829],"type":"Point"}
}