{
  "type": "Feature",
  "properties": {
    "addr:full":"Hasselaarln 58A Eemnes Utrecht 3755 AX",
    "addr:housenumber":"58a",
    "addr:postcode":"3755 ax",
    "addr:street":"Hasselaarln",
    "iso:country":"NL",
    "sg:address":"Hasselaarln 58A",
    "sg:city":"Eemnes",
    "sg:orig_category":"Artsen - Huisartsen",
    "sg:phone":"+31 35 538 3827",
    "sg:postcode":"3755 AX",
    "sg:province":"Utrecht",
    "wof:name":"Schapers-De Bruin, C P",
    "wof:placetype":"venue"
},
  "geometry": {"coordinates":[5.25941,52.253288],"type":"Point"}
}