{
  "type": "Feature",
  "properties": {
    "addr:full":"Oostzyde 192B Zaandam Noord-Holland 1502 BM",
    "addr:housenumber":"192b",
    "addr:postcode":"1502 bm",
    "addr:street":"Oostzyde",
    "iso:country":"NL",
    "sg:address":"Oostzyde 192B",
    "sg:city":"Zaandam",
    "sg:classifiers":[
        {
            "category":"Retail",
            "subcategory":"Auto Repair",
            "type":"Services"
        }
    ],
    "sg:phone":"+31 75 616 4444",
    "sg:postcode":"1502 BM",
    "sg:province":"Noord-Holland",
    "sg:tags":[
        "garage"
    ],
    "sg:website":"http://www.autobedrijfoptimaal.nl",
    "wof:name":"Optimaal, Autobedrijf",
    "wof:placetype":"venue"
},
  "geometry": {"coordinates":[4.82731,52.447559],"type":"Point"}
}