{
  "type": "Feature",
  "properties": {
    "addr:full":"Handelsweg 26 Zeewolde NL. 3899 AB",
    "addr:housenumber":"26",
    "addr:postcode":"3899 ab",
    "addr:street":"Handelsweg;Nl.",
    "iso:country":"NL",
    "sg:address":"Handelsweg 26",
    "sg:city":"Zeewolde",
    "sg:classifiers":[
        {
            "category":"Retail",
            "subcategory":"Storage",
            "type":"Services"
        }
    ],
    "sg:phone":"+31 36 521 9521",
    "sg:postcode":"3899 AB",
    "sg:province":"NL.",
    "sg:tags":[
        "opslag",
        "bewaring"
    ],
    "wof:name":"Bakker Logistiek Groep",
    "wof:placetype":"venue"
},
  "geometry": {"coordinates":[5.5122799873,52.3558158875],"type":"Point"}
}