{
  "type": "Feature",
  "properties": {
    "addr:full":"Klemit 7 Well Gld Gelderland 5325 KG",
    "addr:housenumber":"7;5325",
    "addr:postcode":"kg",
    "addr:street":"Klemit;Gld Gelderland",
    "iso:country":"NL",
    "sg:address":"Klemit 7",
    "sg:city":"Well Gld",
    "sg:orig_category":"Autokeuringen",
    "sg:phone":"+31 418 552 425",
    "sg:postcode":"5325 KG",
    "sg:province":"Gelderland",
    "wof:name":"Vof A V. Loon",
    "wof:placetype":"venue"
},
  "geometry": {"coordinates":[5.181081,51.76226],"type":"Point"}
}