{
  "type": "Feature",
  "properties": {
    "addr:full":"Gijsbrecht Van Amstelstr 448 Hilversum Noord-Holland 1216 CD",
    "addr:housenumber":"448",
    "addr:postcode":"1216 cd",
    "addr:street":"Gijsbrecht Van Amstelstr",
    "iso:country":"NL",
    "sg:address":"Gijsbrecht Van Amstelstr 448",
    "sg:city":"Hilversum",
    "sg:orig_category":"Boekhouders",
    "sg:phone":"+31 35 624 0266",
    "sg:postcode":"1216 CD",
    "sg:province":"Noord-Holland",
    "wof:name":"T. Top",
    "wof:placetype":"venue"
},
  "geometry": {"coordinates":[5.1516041756,52.2222518921],"type":"Point"}
}