{
  "type": "Feature",
  "properties": {
    "addr:full":"Vlinderveen 562 Spykenisse South Holland 3205 EN",
    "addr:housenumber":"562",
    "addr:postcode":"3205 en",
    "addr:street":"Vlinderveen",
    "iso:country":"NL",
    "sg:address":"Vlinderveen 562",
    "sg:city":"Spykenisse",
    "sg:orig_category":"Bestratingen",
    "sg:phone":"+31 181 640 403",
    "sg:postcode":"3205 EN",
    "sg:province":"South Holland",
    "wof:name":"Dekker, A P",
    "wof:placetype":"venue"
},
  "geometry": {"coordinates":[4.342739,51.832905],"type":"Point"}
}