{
  "type": "Feature",
  "properties": {
    "addr:full":"Berenkoog 32 Alkmaar North Holland 1822 BJ",
    "addr:housenumber":"32",
    "addr:postcode":"1822 bj",
    "addr:street":"Berenkoog",
    "iso:country":"NL",
    "sg:address":"Berenkoog 32",
    "sg:city":"Alkmaar",
    "sg:orig_category":"Diverse Grafische Activiteiten",
    "sg:phone":"+31 72 561 5254",
    "sg:postcode":"1822 BJ",
    "sg:province":"North Holland",
    "wof:name":"Maryse Spruijt, Grafisch Ontwerp & Uitwe",
    "wof:placetype":"venue"
},
  "geometry": {"coordinates":[4.785765,52.647591],"type":"Point"}
}