{
  "type": "Feature",
  "properties": {
    "iso:country":"NL",
    "sg:address":"Blekerskd 14",
    "sg:city":"Alkmaar",
    "sg:orig_category":"Kappers",
    "sg:phone":"+31 72 515 3191",
    "sg:postcode":"1814 TJ",
    "sg:province":"North Holland",
    "wof:name":"Shavers",
    "wof:placetype":"venue"
},
  "geometry": {"coordinates":[4.746258,52.634361],"type":"Point"}
}