{
  "type": "Feature",
  "properties": {
    "iso:country":"NL",
    "sg:address":"Dominee C Keersstraat 91",
    "sg:city":"Lemelerveld",
    "sg:orig_category":"Bibliotheken And Openbare Archieven",
    "sg:phone":"+31 572 371 928",
    "sg:postcode":"8151 AB",
    "sg:province":"NL.08",
    "wof:name":"Openb Bibliotheken",
    "wof:placetype":"venue"
},
  "geometry": {"coordinates":[6.347784,52.445759],"type":"Point"}
}