{
  "type": "Feature",
  "properties": {
    "addr:full":"Promenade 51 Heemskerk Noord-Holland 1962 PM",
    "addr:housenumber":"51",
    "addr:postcode":"1962 pm",
    "addr:street":"Promenade",
    "iso:country":"NL",
    "sg:address":"Promenade 51",
    "sg:city":"Heemskerk",
    "sg:orig_category":"Architecten",
    "sg:phone":"+31 251 235 719",
    "sg:postcode":"1962 PM",
    "sg:province":"Noord-Holland",
    "wof:name":"Ingenieursbureau Tramper",
    "wof:placetype":"venue"
},
  "geometry": {"coordinates":[4.676941,52.517807],"type":"Point"}
}