{
  "type": "Feature",
  "properties": {
    "addr:full":"Asselsestr 69 Apeldoorn Gelderland 7311 ED",
    "addr:housenumber":"69",
    "addr:postcode":"7311 ed",
    "addr:street":"Asselsestr;Gelderland",
    "iso:country":"NL",
    "sg:address":"Asselsestr 69",
    "sg:city":"Apeldoorn",
    "sg:orig_category":"Zonnebank- En Solariumcentra",
    "sg:phone":"+31 55 521 4918",
    "sg:postcode":"7311 ED",
    "sg:province":"Gelderland",
    "wof:name":"Ayk Suncentre",
    "wof:placetype":"venue"
},
  "geometry": {"coordinates":[5.95599,52.213005],"type":"Point"}
}