{
  "type": "Feature",
  "properties": {
    "iso:country":"NL",
    "sg:address":"Turfmarkt 7",
    "sg:city":"Katwyk Zh",
    "sg:orig_category":"Lpg-Installaties",
    "sg:phone":"+31 71 402 7000",
    "sg:postcode":"2223 EH",
    "sg:province":"Zuid-Holland",
    "wof:name":"Rijnzicht",
    "wof:placetype":"venue"
},
  "geometry": {"coordinates":[4.42437,52.196686],"type":"Point"}
}