{
  "type": "Feature",
  "properties": {
    "addr:full":"Gildebroedersstraat 58 Tilburg North Brabant 5017 BD",
    "addr:housenumber":"58",
    "addr:postcode":"5017 bd",
    "addr:street":"Gildebroedersstraat",
    "iso:country":"NL",
    "sg:address":"Gildebroedersstraat 58",
    "sg:city":"Tilburg",
    "sg:orig_category":"Boekhouders",
    "sg:phone":"+31 13 542 0489",
    "sg:postcode":"5017 BD",
    "sg:province":"North Brabant",
    "wof:name":"Tilburgs Administratie Buro",
    "wof:placetype":"venue"
},
  "geometry": {"coordinates":[5.090292,51.552105],"type":"Point"}
}