{
  "type": "Feature",
  "properties": {
    "addr:full":"Wagenstr 107 S Gravenhage Zuid-Holland 2512 AS",
    "addr:housenumber":"107;gravenhage",
    "addr:postcode":"2512 as",
    "addr:street":"S",
    "iso:country":"NL",
    "sg:address":"Wagenstr 107",
    "sg:city":"S Gravenhage",
    "sg:orig_category":"Kappers",
    "sg:phone":"+31 70 365 7469",
    "sg:postcode":"2512 AS",
    "sg:province":"Zuid-Holland",
    "wof:name":"Dream Lover",
    "wof:placetype":"venue"
},
  "geometry": {"coordinates":[4.3061800003,52.0732116699],"type":"Point"}
}