{
  "type": "Feature",
  "properties": {
    "addr:full":"Vlietln 2 Rotterdam Zuid-Holland 3061 DW",
    "addr:housenumber":"2",
    "addr:postcode":"3061 dw",
    "addr:street":"Vlietln",
    "iso:country":"NL",
    "sg:address":"Vlietln 2",
    "sg:city":"Rotterdam",
    "sg:orig_category":"Postkantoren",
    "sg:phone":"+31 10 212 1126",
    "sg:postcode":"3061 DW",
    "sg:province":"Zuid-Holland",
    "sg:website":"http://www.postkantoor.nl",
    "wof:name":"Postkantoor",
    "wof:placetype":"venue"
},
  "geometry": {"coordinates":[4.50434,51.927422],"type":"Point"}
}