{
  "type": "Feature",
  "properties": {
    "addr:full":"Postbus 3341 Rotterdam South Holland 3003 AH",
    "addr:housenumber":"3341",
    "addr:postcode":"3003 ah",
    "addr:street":"Postbus",
    "iso:country":"NL",
    "sg:address":"Postbus 3341",
    "sg:city":"Rotterdam",
    "sg:classifiers":[
        {
            "category":"Wholesale",
            "subcategory":"Meat",
            "type":"Manufacturing & Wholesale Goods"
        }
    ],
    "sg:phone":"+31 10 243 7121",
    "sg:postcode":"3003 AH",
    "sg:province":"South Holland",
    "sg:tags":[
        "regeltechniek",
        "en",
        "meet-"
    ],
    "wof:name":"Ara Bv",
    "wof:placetype":"venue"
},
  "geometry": {"coordinates":[4.47842,51.92289],"type":"Point"}
}