{
  "type": "Feature",
  "properties": {
    "iso:country":"NL",
    "sg:address":"Nimfkruidvaart 21",
    "sg:city":"Zoetermeer",
    "sg:orig_category":"Boekhouders",
    "sg:phone":"+31 79 341 2928",
    "sg:postcode":"2724 SR",
    "sg:province":"Zuid-Holland",
    "wof:name":"Administratiekantoor E.P.M. Zadelaar-Van Der Lubbe",
    "wof:placetype":"venue"
},
  "geometry": {"coordinates":[4.501205,52.066406],"type":"Point"}
}