{
  "type": "Feature",
  "properties": {
    "addr:full":"Hogelandseweg 78 Nijmegen Gelderland 6545 AB",
    "addr:housenumber":"78",
    "addr:postcode":"6545 ab",
    "addr:street":"Hogelandseweg;Gelderland",
    "iso:country":"NL",
    "sg:address":"Hogelandseweg 78",
    "sg:city":"Nijmegen",
    "sg:orig_category":"Diverse Bedrijfsinstallaties Gh",
    "sg:phone":"+31 24 377 5458",
    "sg:postcode":"6545 AB",
    "sg:province":"Gelderland",
    "wof:name":"Smeba Brandbeveiliging",
    "wof:placetype":"venue"
},
  "geometry": {"coordinates":[5.802439,51.843559],"type":"Point"}
}