{
  "type": "Feature",
  "properties": {
    "addr:full":"Berg 21 Nuenen North Brabant 5671 CA",
    "addr:housenumber":"21",
    "addr:postcode":"5671 ca",
    "addr:street":"Berg",
    "iso:country":"NL",
    "sg:address":"Berg 21",
    "sg:city":"Nuenen",
    "sg:orig_category":"Makelaars In Onroerend Goed",
    "sg:phone":"+31 40 283 3300",
    "sg:postcode":"5671 CA",
    "sg:province":"North Brabant",
    "wof:name":"Woning Verkoop Garantiefonds",
    "wof:placetype":"venue"
},
  "geometry": {"coordinates":[5.550326,51.476219],"type":"Point"}
}