{
  "type": "Feature",
  "properties": {
    "addr:full":"Hoofdstraat 35 Drouwenerveen Drenthe 9525 TD",
    "addr:housenumber":"35",
    "addr:postcode":"9525 td",
    "addr:street":"Hoofdstraat",
    "iso:country":"NL",
    "sg:address":"Hoofdstraat 35",
    "sg:city":"Drouwenerveen",
    "sg:classifiers":[
        {
            "category":"Education",
            "subcategory":"Preschool",
            "type":"Public Place"
        }
    ],
    "sg:phone":"+31 599 512 562",
    "sg:postcode":"9525 TD",
    "sg:province":"Drenthe",
    "sg:tags":[
        "kleuteronderwijs",
        "basis-"
    ],
    "wof:name":"Openbare Basisschool 'T Dobbegie",
    "wof:placetype":"venue"
},
  "geometry": {"coordinates":[6.851992,52.968349],"type":"Point"}
}