{
  "type": "Feature",
  "properties": {
    "addr:full":"Bremstraat 5 Assen Drenthe 9404 GA",
    "addr:housenumber":"5",
    "addr:postcode":"9404 ga",
    "addr:street":"Bremstraat",
    "iso:country":"NL",
    "sg:address":"Bremstraat 5",
    "sg:city":"Assen",
    "sg:classifiers":[
        {
            "category":"Fast Food",
            "type":"Food & Drink"
        }
    ],
    "sg:phone":"+31 592 317 580",
    "sg:postcode":"9404 GA",
    "sg:province":"Drenthe",
    "sg:tags":[
        "afhaal",
        "restaurant"
    ],
    "wof:name":"Cafetaria Vredeveld",
    "wof:placetype":"venue"
},
  "geometry": {"coordinates":[6.580085,52.98856],"type":"Point"}
}