{
  "type": "Feature",
  "properties": {
    "iso:country":"NL",
    "sg:address":"Suitbertusstr 7",
    "sg:city":"Heusden Gem Heusd",
    "sg:orig_category":"Video - Faciliteiten En Producties",
    "sg:phone":"+31 416 661 171",
    "sg:postcode":"5256 GW",
    "sg:province":"Noord-Brabant",
    "wof:name":"Safari Tv",
    "wof:placetype":"venue"
},
  "geometry": {"coordinates":[5.137445,51.724949],"type":"Point"}
}