{
  "type": "Feature",
  "properties": {
    "addr:full":"Bakelsebrug 10 Bakel Noord-Brabant 5761 PM",
    "addr:housenumber":"10",
    "addr:postcode":"5761 pm",
    "addr:street":"Bakelsebrug",
    "iso:country":"NL",
    "sg:address":"Bakelsebrug 10",
    "sg:city":"Bakel",
    "sg:orig_category":"Kunststoffen- Verwerkende Industrie",
    "sg:phone":"+31 492 574 200",
    "sg:postcode":"5761 PM",
    "sg:province":"Noord-Brabant",
    "wof:name":"Tbdv",
    "wof:placetype":"venue"
},
  "geometry": {"coordinates":[5.7138,51.491165],"type":"Point"}
}