{
  "type": "Feature",
  "properties": {
    "addr:full":"Beestenmarkt 9 Leiden South Holland 2312 CC",
    "addr:housenumber":"9",
    "addr:postcode":"2312 cc",
    "addr:street":"Beestenmarkt",
    "iso:country":"NL",
    "sg:address":"Beestenmarkt 9",
    "sg:city":"Leiden",
    "sg:classifiers":[
        {
            "category":"Fast Food",
            "type":"Food & Drink"
        }
    ],
    "sg:phone":"+31 71 512 5534",
    "sg:postcode":"2312 CC",
    "sg:province":"South Holland",
    "sg:tags":[
        "afhaal",
        "restaurant"
    ],
    "wof:name":"Chin Rest Kwangtung",
    "wof:placetype":"venue"
},
  "geometry": {"coordinates":[4.485377,52.163017],"type":"Point"}
}