{
  "type": "Feature",
  "properties": {
    "addr:full":"Elperweg 5 Zwiggelte Provincie Drenthe 9433 TJ",
    "addr:housenumber":"5",
    "addr:postcode":"9433 tj",
    "addr:street":"Elperweg;Provincie Drenthe",
    "iso:country":"NL",
    "sg:address":"Elperweg 5",
    "sg:city":"Zwiggelte",
    "sg:orig_category":"Kampeerterreinen",
    "sg:phone":"+31 593 370 022",
    "sg:postcode":"9433 TJ",
    "sg:province":"Provincie Drenthe",
    "wof:name":"P.R.J. Hamers",
    "wof:placetype":"venue"
},
  "geometry": {"coordinates":[6.6124310493,52.8764038086],"type":"Point"}
}