{
  "type": "Feature",
  "properties": {
    "addr:full":"N Beetsstr 264 Alblasserdam Zuid-Holland 2951 XM",
    "addr:housenumber":"264",
    "addr:postcode":"2951 xm",
    "addr:street":"N",
    "iso:country":"NL",
    "sg:address":"N Beetsstr 264",
    "sg:city":"Alblasserdam",
    "sg:orig_category":"Fotoreportages",
    "sg:phone":"+31 6 20024985",
    "sg:postcode":"2951 XM",
    "sg:province":"Zuid-Holland",
    "wof:name":"Kbs",
    "wof:placetype":"venue"
},
  "geometry": {"coordinates":[4.667342,51.867214],"type":"Point"}
}