{
  "type": "Feature",
  "properties": {
    "addr:full":"Moleneind 65 Kortenhoef Noord-Holland 1241 NK",
    "addr:housenumber":"65",
    "addr:postcode":"1241 nk",
    "addr:street":"Moleneind",
    "iso:country":"NL",
    "sg:address":"Moleneind 65",
    "sg:city":"Kortenhoef",
    "sg:orig_category":"Jachthavens - Jachtwerven",
    "sg:phone":"+31 35 656 0443",
    "sg:postcode":"1241 NK",
    "sg:province":"Noord-Holland",
    "wof:name":"Wijde Blick Jachthaven, De",
    "wof:placetype":"venue"
},
  "geometry": {"coordinates":[5.115375,52.239986],"type":"Point"}
}