{
  "type": "Feature",
  "properties": {
    "addr:full":"Expeditiewg 7 Rucphen Noord-Brabant 4715 RM",
    "addr:housenumber":"7",
    "addr:postcode":"4715 rm",
    "addr:street":"Expeditiewg",
    "iso:country":"NL",
    "sg:address":"Expeditiewg 7",
    "sg:city":"Rucphen",
    "sg:orig_category":"Kunstenaars- Benodigdheden",
    "sg:phone":"+31 165 344 902",
    "sg:postcode":"4715 RM",
    "sg:province":"Noord-Brabant",
    "wof:name":"Artel Bv",
    "wof:placetype":"venue"
},
  "geometry": {"coordinates":[4.576143,51.532871],"type":"Point"}
}