{
  "type": "Feature",
  "properties": {
    "iso:country":"NL",
    "sg:address":"Den Dolvert 12",
    "sg:city":"Heeswyk Dinther",
    "sg:orig_category":"Meubelstoffering",
    "sg:phone":"+31 413 294 869",
    "sg:postcode":"5473 GP",
    "sg:province":"Noord-Brabant",
    "wof:name":"Jv",
    "wof:placetype":"venue"
},
  "geometry": {"coordinates":[5.486922,51.645672],"type":"Point"}
}