{
  "type": "Feature",
  "properties": {
    "addr:full":"Soestdijkerstraatweg 19A Hilversum North Holland 1213 VP",
    "addr:housenumber":"19a",
    "addr:postcode":"1213 vp",
    "addr:street":"Soestdijkerstraatweg",
    "iso:country":"NL",
    "sg:address":"Soestdijkerstraatweg 19A",
    "sg:city":"Hilversum",
    "sg:orig_category":"Artsen And Specialisten",
    "sg:phone":"+31 35 624 8798",
    "sg:postcode":"1213 VP",
    "sg:province":"North Holland",
    "wof:name":"Drs. J.W.P. Dijkstra",
    "wof:placetype":"venue"
},
  "geometry": {"coordinates":[5.185459,52.217346],"type":"Point"}
}