{
  "type": "Feature",
  "properties": {
    "addr:full":"Stedekestr 46 Tilburg Noord-Brabant 5041 DN",
    "addr:housenumber":"46",
    "addr:postcode":"5041 dn",
    "addr:street":"Stedekestr",
    "iso:country":"NL",
    "sg:address":"Stedekestr 46",
    "sg:city":"Tilburg",
    "sg:orig_category":"Lasbedrijven",
    "sg:phone":"+31 13 533 9095",
    "sg:postcode":"5041 DN",
    "sg:province":"Noord-Brabant",
    "wof:name":"Brands, Gebroeders",
    "wof:placetype":"venue"
},
  "geometry": {"coordinates":[5.080593,51.564137],"type":"Point"}
}