{
  "type": "Feature",
  "properties": {
    "iso:country":"NL",
    "sg:address":"W De Withstr 24A",
    "sg:city":"Amsterdam",
    "sg:orig_category":"Verenigingen En Stichtingen",
    "sg:phone":"+31 20 612 9430",
    "sg:postcode":"1057 XW",
    "sg:province":"Noord-Holland",
    "wof:name":"Juttersdok, Het",
    "wof:placetype":"venue"
},
  "geometry": {"coordinates":[4.859571,52.365677],"type":"Point"}
}