{
  "type": "Feature",
  "properties": {
    "addr:full":"Dingstraat 8 Winterswijk Gelderland 7101 GX",
    "addr:housenumber":"8",
    "addr:postcode":"7101 gx",
    "addr:street":"Dingstraat;Gelderland",
    "iso:country":"NL",
    "sg:address":"Dingstraat 8",
    "sg:city":"Winterswijk",
    "sg:orig_category":"Vertaal- And Tolkenbureaus",
    "sg:phone":"+31 543 518 420",
    "sg:postcode":"7101 GX",
    "sg:province":"Gelderland",
    "wof:name":"Go British",
    "wof:placetype":"venue"
},
  "geometry": {"coordinates":[6.72077,51.969238],"type":"Point"}
}