{
  "type": "Feature",
  "properties": {
    "addr:full":"Industriewg 46 Staphorst Overijssel 7951 TA",
    "addr:housenumber":"46",
    "addr:postcode":"7951 ta",
    "addr:street":"Industriewg",
    "iso:country":"NL",
    "sg:address":"Industriewg 46",
    "sg:city":"Staphorst",
    "sg:orig_category":"Metaalbewerking",
    "sg:phone":"+31 522 462 775",
    "sg:postcode":"7951 TA",
    "sg:province":"Overijssel",
    "wof:name":"Veldman",
    "wof:placetype":"venue"
},
  "geometry": {"coordinates":[6.224199,52.637081],"type":"Point"}
}