{
  "type": "Feature",
  "properties": {
    "iso:country":"NL",
    "sg:address":"Schipperswal 19",
    "sg:city":"Roermond",
    "sg:classifiers":[
        {
            "category":"Home & Garden",
            "subcategory":"Garden Supply",
            "type":"Retail Goods"
        }
    ],
    "sg:phone":"+31 475 395 300",
    "sg:postcode":"6041 TC",
    "sg:province":"Limburg",
    "sg:tags":[
        "zand",
        "en",
        "grind"
    ],
    "wof:name":"Steenbrekerij Roermond",
    "wof:placetype":"venue"
},
  "geometry": {"coordinates":[5.991029,51.203045],"type":"Point"}
}