{
  "type": "Feature",
  "properties": {
    "iso:country":"NL",
    "sg:address":"De Hoge Kamp 6",
    "sg:city":"Rheden",
    "sg:orig_category":"Verzekeringen - Verzekeringskantoren",
    "sg:phone":"+31 26 327 1649",
    "sg:postcode":"6991 CX",
    "sg:province":"Gelderland",
    "wof:name":"Jansen, Dick",
    "wof:placetype":"venue"
},
  "geometry": {"coordinates":[6.03264,52.002544],"type":"Point"}
}