{
  "type": "Feature",
  "properties": {
    "iso:country":"NL",
    "sg:address":"Wilhelminapln 2",
    "sg:city":"Wassenaar",
    "sg:orig_category":"Juridische Adviseurs",
    "sg:phone":"+31 70 517 8514",
    "sg:postcode":"2243 HE",
    "sg:province":"Zuid-Holland",
    "sg:website":"http://www.uitvaart.nl/jurist",
    "wof:name":"Putten, Mr W G H M Van Der",
    "wof:placetype":"venue"
},
  "geometry": {"coordinates":[4.36264,52.123676],"type":"Point"}
}