{
  "type": "Feature",
  "properties": {
    "addr:full":"Kotkampwg 65 Enschede Overijssel 7531 AS",
    "addr:housenumber":"65",
    "addr:postcode":"7531 as",
    "addr:street":"Kotkampwg",
    "iso:country":"NL",
    "sg:address":"Kotkampwg 65",
    "sg:city":"Enschede",
    "sg:orig_category":"Nagelstudio'S",
    "sg:phone":"+31 6 23283398",
    "sg:postcode":"7531 AS",
    "sg:province":"Overijssel",
    "wof:name":"Alexandra",
    "wof:placetype":"venue"
},
  "geometry": {"coordinates":[6.910153,52.233524],"type":"Point"}
}