{
  "type": "Feature",
  "properties": {
    "addr:full":"Zuiderwg 1 Oude Niedorp Noord-Holland 1734 JK",
    "addr:housenumber":"1",
    "addr:postcode":"1734 jk",
    "addr:street":"Zuiderwg",
    "iso:country":"NL",
    "sg:address":"Zuiderwg 1",
    "sg:city":"Oude Niedorp",
    "sg:orig_category":"Keukens",
    "sg:phone":"+31 226 422 451",
    "sg:postcode":"1734 JK",
    "sg:province":"Noord-Holland",
    "wof:name":"Koopman",
    "wof:placetype":"venue"
},
  "geometry": {"coordinates":[4.876335,52.717461],"type":"Point"}
}