{
  "type": "Feature",
  "properties": {
    "iso:country":"NL",
    "sg:address":"K Fuitestr 23",
    "sg:city":"Genemuiden",
    "sg:classifiers":[
        {
            "category":"Farming",
            "subcategory":"Fish & Marine Products",
            "type":"Manufacturing & Wholesale Goods"
        }
    ],
    "sg:phone":"+31 38 385 5012",
    "sg:postcode":"8281 BX",
    "sg:province":"Overijssel",
    "sg:tags":[
        "vi"
    ],
    "wof:name":"Visscher, H J",
    "wof:placetype":"venue"
},
  "geometry": {"coordinates":[6.046037,52.624947],"type":"Point"}
}