{
  "type": "Feature",
  "properties": {
    "iso:country":"NL",
    "sg:address":"Postbus 63",
    "sg:city":"Rosmalen",
    "sg:orig_category":"Oppascentrales",
    "sg:phone":"+31 73 521 4362",
    "sg:postcode":"5240 AB",
    "sg:province":"Noord-Brabant",
    "wof:name":"Home Care",
    "wof:placetype":"venue"
},
  "geometry": {"coordinates":[5.3629798889,51.7173805237],"type":"Point"}
}