{
  "type": "Feature",
  "properties": {
    "addr:full":"Handelskade 2 Beverwijk North Holland 1948 NA",
    "addr:housenumber":"2",
    "addr:postcode":"1948 na",
    "addr:street":"Handelskade",
    "iso:country":"NL",
    "sg:address":"Handelskade 2",
    "sg:city":"Beverwijk",
    "sg:orig_category":"Meubels And Huishoudapparatuur Gh",
    "sg:phone":"+31 251 260 020",
    "sg:postcode":"1948 NA",
    "sg:province":"North Holland",
    "wof:name":"Bv Handel- En Verkoopmij Polypreen",
    "wof:placetype":"venue"
},
  "geometry": {"coordinates":[4.659644,52.47826],"type":"Point"}
}