{
  "type": "Feature",
  "properties": {
    "iso:country":"NL",
    "sg:address":"Aleyda Van Raephorstlaan 83",
    "sg:city":"Rotterdam",
    "sg:orig_category":"Verhuur Catering-, Feest- En Evenementbenodigdheden",
    "sg:phone":"+31 10 422 2317",
    "sg:postcode":"3054 CR",
    "sg:province":"Zuid-Holland",
    "wof:name":"Rickart Bv",
    "wof:placetype":"venue"
},
  "geometry": {"coordinates":[4.484697,51.95924],"type":"Point"}
}