{
  "type": "Feature",
  "properties": {
    "iso:country":"NL",
    "sg:address":"Postbus 2295",
    "sg:city":"Haarlem",
    "sg:orig_category":"Bedrijfsopleidingen",
    "sg:phone":"+31 23 548 2680",
    "sg:postcode":"2002 CG",
    "sg:province":"North Holland",
    "sg:website":"http://www.ncot.nl",
    "wof:name":"Nova College",
    "wof:placetype":"venue"
},
  "geometry": {"coordinates":[4.64225,52.380562],"type":"Point"}
}