{
  "type": "Feature",
  "properties": {
    "addr:full":"Larensteinseln 45 Velp Gld Gelderland 6882 CV",
    "addr:housenumber":"45",
    "addr:postcode":"6882 cv",
    "addr:street":"Larensteinseln;Gld Gelderland",
    "iso:country":"NL",
    "sg:address":"Larensteinseln 45",
    "sg:city":"Velp Gld",
    "sg:classifiers":[
        {
            "category":"Retail",
            "subcategory":"Auto Repair",
            "type":"Services"
        }
    ],
    "sg:phone":"+31 26 363 9677",
    "sg:postcode":"6882 CV",
    "sg:province":"Gelderland",
    "sg:tags":[
        "garage"
    ],
    "wof:name":"Delsink Bv",
    "wof:placetype":"venue"
},
  "geometry": {"coordinates":[5.963445,51.991268],"type":"Point"}
}