{
  "type": "Feature",
  "properties": {
    "iso:country":"NL",
    "sg:address":"Hoofdstr 20",
    "sg:city":"Borger",
    "sg:orig_category":"Opticiens",
    "sg:phone":"+31 599 235 284",
    "sg:postcode":"9531 AG",
    "sg:province":"Provincie Drenthe",
    "wof:name":"Heijer, Den",
    "wof:placetype":"venue"
},
  "geometry": {"coordinates":[6.7901749611,52.9255447388],"type":"Point"}
}