{
  "type": "Feature",
  "properties": {
    "addr:full":"Mulertstr 52/A Hasselt Overijssel 8061 CG",
    "addr:housenumber":"52 / a",
    "addr:postcode":"8061 cg",
    "addr:street":"Mulertstr",
    "iso:country":"NL",
    "sg:address":"Mulertstr 52/A",
    "sg:city":"Hasselt",
    "sg:orig_category":"Kinderopvang",
    "sg:phone":"+31 38 477 4002",
    "sg:postcode":"8061 CG",
    "sg:province":"Overijssel",
    "wof:name":"Pippeloentje",
    "wof:placetype":"venue"
},
  "geometry": {"coordinates":[6.098564,52.591072],"type":"Point"}
}