{
  "type": "Feature",
  "properties": {
    "iso:country":"NL",
    "sg:address":"Stadswerf 89",
    "sg:city":"Almere",
    "sg:orig_category":"Video - Faciliteiten En Producties",
    "sg:phone":"+31 36 531 4668",
    "sg:postcode":"1354 CJ",
    "sg:province":"Flevoland",
    "wof:name":"Geld, Dick Van Der",
    "wof:placetype":"venue"
},
  "geometry": {"coordinates":[5.219358,52.337616],"type":"Point"}
}