{
  "type": "Feature",
  "properties": {
    "addr:full":"Pr Hendrikln 386 Brunssum Limburg 6443 AE",
    "addr:housenumber":"386",
    "addr:postcode":"6443 ae",
    "addr:street":"Brunssum Limburg",
    "iso:country":"NL",
    "sg:address":"Pr Hendrikln 386",
    "sg:city":"Brunssum",
    "sg:orig_category":"Verenigingsgebouwen",
    "sg:phone":"+31 45 525 2858",
    "sg:postcode":"6443 AE",
    "sg:province":"Limburg",
    "wof:name":"Concordia",
    "wof:placetype":"venue"
},
  "geometry": {"coordinates":[5.975377,50.939861],"type":"Point"}
}