{
  "type": "Feature",
  "properties": {
    "addr:full":"Bark 25 , (Mobiele Telefoon) Kropswolde Groningen 9606 RB",
    "addr:housenumber":"25",
    "addr:postcode":"9606 rb",
    "addr:street":"Bark;Telefoon",
    "iso:country":"NL",
    "sg:address":"Bark 25 , (Mobiele Telefoon)",
    "sg:city":"Kropswolde",
    "sg:orig_category":"Keukens",
    "sg:phone":"+31 6 53927614",
    "sg:postcode":"9606 RB",
    "sg:province":"Groningen",
    "wof:name":"Remmerts, E W",
    "wof:placetype":"venue"
},
  "geometry": {"coordinates":[6.71257,53.146767],"type":"Point"}
}