{
  "type": "Feature",
  "properties": {
    "addr:full":"Bierkd 19 S Gravenhage Zuid-Holland 2512 AB",
    "addr:housenumber":"19;gravenhage",
    "addr:postcode":"2512 ab",
    "addr:street":"Bierkd;S",
    "iso:country":"NL",
    "sg:address":"Bierkd 19",
    "sg:city":"S Gravenhage",
    "sg:orig_category":"Wikkelinrichtingen",
    "sg:phone":"+31 70 360 5327",
    "sg:postcode":"2512 AB",
    "sg:province":"Zuid-Holland",
    "wof:name":"Looman Bv",
    "wof:placetype":"venue"
},
  "geometry": {"coordinates":[4.3061800003,52.0732116699],"type":"Point"}
}