{
  "type": "Feature",
  "properties": {
    "addr:full":"Continentenlaan 26 Veendam Groningen 9642 BG",
    "addr:housenumber":"26",
    "addr:postcode":"9642",
    "addr:street":"Continentenlaan",
    "iso:country":"NL",
    "sg:address":"Continentenlaan 26",
    "sg:city":"Veendam",
    "sg:classifiers":[
        {
            "category":"Professional",
            "subcategory":"Accounting & Tax Preparation",
            "type":"Services"
        }
    ],
    "sg:phone":"+31 598 624 917",
    "sg:postcode":"9642 BG",
    "sg:province":"Groningen",
    "sg:tags":[
        "accountant"
    ],
    "wof:name":"Accountantskantoor Hoogeboom",
    "wof:placetype":"venue"
},
  "geometry": {"coordinates":[6.864834,53.100315],"type":"Point"}
}