{
  "type": "Feature",
  "properties": {
    "iso:country":"NL",
    "sg:address":"W M Dudokwg 13",
    "sg:city":"Heerhugowaard",
    "sg:orig_category":"Fietsen En Bromfietsen",
    "sg:phone":"+31 72 571 2345",
    "sg:postcode":"1703 DA",
    "sg:province":"North Holland",
    "sg:website":"http://www.vittorio.nl",
    "wof:name":"Vittorio",
    "wof:placetype":"venue"
},
  "geometry": {"coordinates":[4.816921,52.666435],"type":"Point"}
}