{
  "type": "Feature",
  "properties": {
    "addr:full":"Voorzorgstraat 16 Haarlem Noord-Holland 2013 VP",
    "addr:housenumber":"16",
    "addr:postcode":"2013 vp",
    "addr:street":"Voorzorgstraat",
    "iso:country":"NL",
    "sg:address":"Voorzorgstraat 16",
    "sg:city":"Haarlem",
    "sg:orig_category":"Verzekeringen",
    "sg:phone":"+31 23 531 5448",
    "sg:postcode":"2013 VP",
    "sg:province":"Noord-Holland",
    "wof:name":"F.A. Bakker",
    "wof:placetype":"venue"
},
  "geometry": {"coordinates":[4.621117,52.38055],"type":"Point"}
}