{
  "type": "Feature",
  "properties": {
    "addr:full":"Terborchdreef 28 Oud Beyerland South Holland 3262 NB",
    "addr:housenumber":"28",
    "addr:postcode":"3262 nb",
    "addr:street":"Terborchdreef;Oud Beyerland",
    "iso:country":"NL",
    "sg:address":"Terborchdreef 28",
    "sg:city":"Oud Beyerland",
    "sg:orig_category":"Kunsthandel",
    "sg:phone":"+31 186 613 171",
    "sg:postcode":"3262 NB",
    "sg:province":"South Holland",
    "wof:name":"Bendek",
    "wof:placetype":"venue"
},
  "geometry": {"coordinates":[4.412397,51.817467],"type":"Point"}
}