{
  "type": "Feature",
  "properties": {
    "iso:country":"NL",
    "sg:address":"Vyverstr 1",
    "sg:city":"Prinsenbeek",
    "sg:orig_category":"Kinderopvang",
    "sg:phone":"+31 76 541 0328",
    "sg:postcode":"4841 AT",
    "sg:province":"Noord-Brabant",
    "sg:website":"http://www.kdv/bellefleur.nl",
    "wof:name":"Belle Fleur",
    "wof:placetype":"venue"
},
  "geometry": {"coordinates":[4.720438,51.598419],"type":"Point"}
}