{
  "type": "Feature",
  "properties": {
    "addr:full":"Mendelssohnstraat 1 Leeuwarden Friesland 8916 EV",
    "addr:housenumber":"1",
    "addr:street":"Mendelssohnstraat",
    "iso:country":"NL",
    "sg:address":"Mendelssohnstraat 1",
    "sg:city":"Leeuwarden",
    "sg:orig_category":"Fietshandelaren",
    "sg:phone":"+31 58 212 4643",
    "sg:postcode":"8916 EV",
    "sg:province":"Friesland",
    "wof:name":"Firma D. Hoogeveen",
    "wof:placetype":"venue"
},
  "geometry": {"coordinates":[5.781586,53.20776],"type":"Point"}
}