{
  "type": "Feature",
  "properties": {
    "iso:country":"NL",
    "sg:address":"Bevrydingstr 4",
    "sg:city":"Veldhoven",
    "sg:orig_category":"Autorijscholen",
    "sg:phone":"+31 40 253 0147",
    "sg:postcode":"5502 EL",
    "sg:province":"North Brabant",
    "wof:name":"Zuiden, Het",
    "wof:placetype":"venue"
},
  "geometry": {"coordinates":[5.414943,51.420872],"type":"Point"}
}