{
  "type": "Feature",
  "properties": {
    "addr:full":"Misterweg 180 Winterswijk Gelderland 7102 EP",
    "addr:housenumber":"180",
    "addr:postcode":"7102 ep",
    "addr:street":"Misterweg;Gelderland",
    "iso:country":"NL",
    "sg:address":"Misterweg 180",
    "sg:city":"Winterswijk",
    "sg:orig_category":"Wegen And Sportterreinen",
    "sg:phone":"+31 543 531 187",
    "sg:postcode":"7102 EP",
    "sg:province":"Gelderland",
    "wof:name":"R. Velders",
    "wof:placetype":"venue"
},
  "geometry": {"coordinates":[6.6868138313,51.9607124329],"type":"Point"}
}