{
  "type": "Feature",
  "properties": {
    "iso:country":"NL",
    "sg:address":"Wiltonstraat 1",
    "sg:city":"Veenendaal",
    "sg:orig_category":"Vaste And Vloeibare Brandstoffen",
    "sg:phone":"+31 318 511 428",
    "sg:postcode":"3905 KW",
    "sg:province":"Utrecht",
    "wof:name":"Schoorsteentechniek Midden Nederland Bv",
    "wof:placetype":"venue"
},
  "geometry": {"coordinates":[5.563857,52.037472],"type":"Point"}
}