{
  "type": "Feature",
  "properties": {
    "addr:full":"Oost Voorgors 1 Middelharnis South Holland 3241 KD",
    "addr:housenumber":"1",
    "addr:postcode":"3241 kd",
    "addr:street":"Oost Voorgors",
    "iso:country":"NL",
    "sg:address":"Oost Voorgors 1",
    "sg:city":"Middelharnis",
    "sg:orig_category":"Autokeuringen",
    "sg:phone":"+31 187 482 920",
    "sg:postcode":"3241 KD",
    "sg:province":"South Holland",
    "wof:name":"Garage Delta",
    "wof:placetype":"venue"
},
  "geometry": {"coordinates":[4.171187,51.75906],"type":"Point"}
}