{
  "type": "Feature",
  "properties": {
    "addr:full":"Hendrik Hamerstraat 165 'S Gravendeel Zuid-Holland 3295 CJ",
    "addr:housenumber":"165 ' s",
    "addr:postcode":"3295 cj",
    "addr:street":"Hendrik Hamerstraat",
    "iso:country":"NL",
    "sg:address":"Hendrik Hamerstraat 165",
    "sg:city":"'S Gravendeel",
    "sg:orig_category":"Goederenvervoer Over De Weg",
    "sg:phone":"+31 78 673 4001",
    "sg:postcode":"3295 CJ",
    "sg:province":"Zuid-Holland",
    "wof:name":"C. Van Der Linden",
    "wof:placetype":"venue"
},
  "geometry": {"coordinates":[4.61192,51.777225],"type":"Point"}
}