{
  "type": "Feature",
  "properties": {
    "addr:full":"Wesselinusstr 7 Beek Lb Limburg 6191 SM",
    "addr:housenumber":"7",
    "addr:postcode":"lb;6191 sm",
    "addr:street":"Wesselinusstr",
    "iso:country":"NL",
    "sg:address":"Wesselinusstr 7",
    "sg:city":"Beek Lb",
    "sg:orig_category":"Administratie- En Boekhoudkantoren",
    "sg:phone":"+31 46 437 4930",
    "sg:postcode":"6191 SM",
    "sg:province":"Limburg",
    "wof:name":"Bok",
    "wof:placetype":"venue"
},
  "geometry": {"coordinates":[-93.129936,36.705662],"type":"Point"}
}