{
  "type": "Feature",
  "properties": {
    "addr:full":"De Hg Akker 2 Geldrop Noord-Brabant 5661 NG",
    "addr:housenumber":"2",
    "addr:postcode":"5661 ng",
    "addr:street":"De Hg Akker",
    "iso:country":"NL",
    "sg:address":"De Hg Akker 2",
    "sg:city":"Geldrop",
    "sg:orig_category":"Metaalbewerking",
    "sg:phone":"+31 40 280 7100",
    "sg:postcode":"5661 NG",
    "sg:province":"Noord-Brabant",
    "wof:name":"Egb Bv",
    "wof:placetype":"venue"
},
  "geometry": {"coordinates":[5.53159,51.427753],"type":"Point"}
}