{
  "type": "Feature",
  "properties": {
    "addr:full":"Doddegraswg 39 Almere Flevoland 1313 AX",
    "addr:housenumber":"39",
    "addr:postcode":"1313 ax",
    "addr:street":"Doddegraswg;Flevoland",
    "iso:country":"NL",
    "sg:address":"Doddegraswg 39",
    "sg:city":"Almere",
    "sg:orig_category":"Artiesten/Gezelschappen",
    "sg:phone":"+31 6 51108415",
    "sg:postcode":"1313 AX",
    "sg:province":"Flevoland",
    "wof:name":"Parker, George",
    "wof:placetype":"venue"
},
  "geometry": {"coordinates":[5.200565,52.383926],"type":"Point"}
}