{
  "type": "Feature",
  "properties": {
    "addr:full":"Tynmuiden 5 Amsterdam Noord-Holland 1046 AK",
    "addr:housenumber":"5",
    "addr:postcode":"1046 ak",
    "addr:street":"Tynmuiden",
    "iso:country":"NL",
    "sg:address":"Tynmuiden 5",
    "sg:city":"Amsterdam",
    "sg:classifiers":[
        {
            "category":"Food & Beverages",
            "subcategory":"Candy",
            "type":"Retail Goods"
        }
    ],
    "sg:phone":"+31 900 4353638",
    "sg:postcode":"1046 AK",
    "sg:province":"Noord-Holland",
    "sg:tags":[
        "geld-",
        "en",
        "waardetransporten"
    ],
    "sg:website":"http://www.geldnet.nl",
    "wof:name":"Geldnet Amsterdam",
    "wof:placetype":"venue"
},
  "geometry": {"coordinates":[4.780632,52.390911],"type":"Point"}
}