{
  "type": "Feature",
  "properties": {
    "addr:full":"Eek 1 Huizen Noord-Holland 1274 GL",
    "addr:housenumber":"1",
    "addr:postcode":"1274 gl",
    "addr:street":"Eek",
    "iso:country":"NL",
    "sg:address":"Eek 1",
    "sg:city":"Huizen",
    "sg:orig_category":"Artsen And Specialisten",
    "sg:phone":"+31 35 525 4488",
    "sg:postcode":"1274 GL",
    "sg:province":"Noord-Holland",
    "wof:name":"J.J. Brasser",
    "wof:placetype":"venue"
},
  "geometry": {"coordinates":[5.268794,52.300156],"type":"Point"}
}