{
  "type": "Feature",
  "properties": {
    "addr:full":"De Eglantier 228 Apeldoorn Gelderland 7329 DG",
    "addr:housenumber":"228",
    "addr:postcode":"7329 dg",
    "addr:street":"De Eglantier;Gelderland",
    "iso:country":"NL",
    "sg:address":"De Eglantier 228",
    "sg:city":"Apeldoorn",
    "sg:orig_category":"Slagerijen",
    "sg:phone":"+31 55 533 7641",
    "sg:postcode":"7329 DG",
    "sg:province":"Gelderland",
    "wof:name":"Slagerij Jaap Oosterbeek",
    "wof:placetype":"venue"
},
  "geometry": {"coordinates":[6.006366,52.195919],"type":"Point"}
}