{
  "type": "Feature",
  "properties": {
    "addr:full":"Voorstr 53 Woudenberg Utrecht 3931 HC",
    "addr:housenumber":"53",
    "addr:postcode":"3931 hc",
    "addr:street":"Voorstr",
    "iso:country":"NL",
    "sg:address":"Voorstr 53",
    "sg:city":"Woudenberg",
    "sg:orig_category":"Fietsen En Bromfietsen",
    "sg:phone":"+31 33 286 3003",
    "sg:postcode":"3931 HC",
    "sg:province":"Utrecht",
    "wof:name":"Komen, C H",
    "wof:placetype":"venue"
},
  "geometry": {"coordinates":[5.409833,52.082581],"type":"Point"}
}