{
  "type": "Feature",
  "properties": {
    "addr:full":"Voorstad 5 Tiel Gelderland 4001 LS",
    "addr:housenumber":"5",
    "addr:postcode":"4001 ls",
    "addr:street":"Voorstad;Gelderland",
    "iso:country":"NL",
    "sg:address":"Voorstad 5",
    "sg:city":"Tiel",
    "sg:orig_category":"Opticiens",
    "sg:phone":"+31 344 618 047",
    "sg:postcode":"4001 LS",
    "sg:province":"Gelderland",
    "wof:name":"Intervisie",
    "wof:placetype":"venue"
},
  "geometry": {"coordinates":[5.4374198914,51.8881072998],"type":"Point"}
}