{
  "type": "Feature",
  "properties": {
    "addr:full":"Broeierdweg 71 Enschede Overijssel 7547 SG",
    "addr:housenumber":"71",
    "addr:postcode":"7547 sg",
    "addr:street":"Broeierdweg",
    "iso:country":"NL",
    "sg:address":"Broeierdweg 71",
    "sg:city":"Enschede",
    "sg:orig_category":"Bioscopen",
    "sg:phone":"+31 900 2463782",
    "sg:postcode":"7547 SG",
    "sg:province":"Overijssel",
    "wof:name":"Cinestar Enschede",
    "wof:placetype":"venue"
},
  "geometry": {"coordinates":[6.83083,52.239689],"type":"Point"}
}