{
  "type": "Feature",
  "properties": {
    "iso:country":"NL",
    "sg:address":"Ronde Hoek 8",
    "sg:city":"Ruinen",
    "sg:orig_category":"Huishoudapparatuur, Televisies And Radio'S",
    "sg:phone":"+31 522 471 801",
    "sg:postcode":"7963 SC",
    "sg:province":"South Carolina",
    "wof:name":"Bysky",
    "wof:placetype":"venue"
},
  "geometry": {"coordinates":[-80.947441,33.624981],"type":"Point"}
}