{
  "type": "Feature",
  "properties": {
    "iso:country":"NL",
    "sg:address":"Kerkstr 6",
    "sg:city":"Rinsumageest",
    "sg:orig_category":"Melktransporten",
    "sg:phone":"+31 511 421 406",
    "sg:postcode":"9105 LA",
    "sg:province":"Provincie Friesland",
    "wof:name":"Woude, Van Der",
    "wof:placetype":"venue"
},
  "geometry": {"coordinates":[5.949668,53.297329],"type":"Point"}
}