{
  "type": "Feature",
  "properties": {
    "iso:country":"NL",
    "sg:address":"Grootzand 76",
    "sg:city":"Sneek",
    "sg:orig_category":"Paramedische Behandelingen",
    "sg:phone":"+31 515 438 860",
    "sg:postcode":"8601 AZ",
    "sg:province":"Friesland",
    "wof:name":"Zorgbureau Jantine Slippens",
    "wof:placetype":"venue"
},
  "geometry": {"coordinates":[5.660631,53.0299],"type":"Point"}
}