{
  "type": "Feature",
  "properties": {
    "addr:full":"Boerhaavelaan 3 Zwolle Overijssel 8024 BE",
    "addr:housenumber":"3",
    "addr:postcode":"8024",
    "addr:street":"Boerhaavelaan",
    "iso:country":"NL",
    "sg:address":"Boerhaavelaan 3",
    "sg:city":"Zwolle",
    "sg:classifiers":[
        {
            "category":"Bakery",
            "type":"Food & Drink"
        }
    ],
    "sg:phone":"+31 38 454 9292",
    "sg:postcode":"8024 BE",
    "sg:province":"Overijssel",
    "sg:tags":[
        "brood",
        "banket"
    ],
    "wof:name":"Van Poorten Brood Banket En Zoetwaren",
    "wof:placetype":"venue"
},
  "geometry": {"coordinates":[6.136091,52.522579],"type":"Point"}
}