{
  "type": "Feature",
  "properties": {
    "addr:full":"Ruysdaelln 4 Muiderberg Noord-Holland 1399 GE",
    "addr:housenumber":"4;1399",
    "addr:street":"Ruysdaelln",
    "iso:country":"NL",
    "sg:address":"Ruysdaelln 4",
    "sg:city":"Muiderberg",
    "sg:orig_category":"Kappers",
    "sg:phone":"+31 294 263 536",
    "sg:postcode":"1399 GE",
    "sg:province":"Noord-Holland",
    "wof:name":"Hoofdzaak, De",
    "wof:placetype":"venue"
},
  "geometry": {"coordinates":[5.1160712242,52.327091217],"type":"Point"}
}