{
  "type": "Feature",
  "properties": {
    "addr:full":"Torenstr 77 Numansdorp Zuid-Holland 3281 XN",
    "addr:housenumber":"77",
    "addr:postcode":"3281 xn",
    "addr:street":"Torenstr",
    "iso:country":"NL",
    "sg:address":"Torenstr 77",
    "sg:city":"Numansdorp",
    "sg:orig_category":"Verzekeringen - Verzekeringskantoren",
    "sg:phone":"+31 186 636 666",
    "sg:postcode":"3281 XN",
    "sg:province":"Zuid-Holland",
    "wof:name":"Hoek, Van Der",
    "wof:placetype":"venue"
},
  "geometry": {"coordinates":[4.439176,51.729645],"type":"Point"}
}