{
  "type": "Feature",
  "properties": {
    "addr:full":"Verl Kazernestr 1 Deventer NL.08 7417 ZA",
    "addr:housenumber":"1;nl.08",
    "addr:postcode":"7417",
    "addr:street":"Kazernestr",
    "iso:country":"NL",
    "sg:address":"Verl Kazernestr 1",
    "sg:city":"Deventer",
    "sg:orig_category":"Bedrijfsopleidingen",
    "sg:phone":"+31 570 691 650",
    "sg:postcode":"7417 ZA",
    "sg:province":"NL.08",
    "wof:name":"Stavoor Groep",
    "wof:placetype":"venue"
},
  "geometry": {"coordinates":[6.166581,52.252491],"type":"Point"}
}