{
  "type": "Feature",
  "properties": {
    "iso:country":"NL",
    "sg:address":"Leenherenstr 13",
    "sg:city":"Mook",
    "sg:orig_category":"Kappers",
    "sg:phone":"+31 24 324 9970",
    "sg:postcode":"6585 VA",
    "sg:province":"Limburg",
    "wof:name":"Jozefien, Hairstyliste",
    "wof:placetype":"venue"
},
  "geometry": {"coordinates":[5.877409935,51.7552452087],"type":"Point"}
}