{
  "type": "Feature",
  "properties": {
    "addr:full":"Palenbergstraat 52 Heerlen Limburg 6415 RD",
    "addr:housenumber":"52",
    "addr:postcode":"6415 rd",
    "addr:street":"Palenbergstraat",
    "iso:country":"NL",
    "sg:address":"Palenbergstraat 52",
    "sg:city":"Heerlen",
    "sg:orig_category":"Zuivelproducten And Spijsoli?n Gh",
    "sg:phone":"+31 45 572 9348",
    "sg:postcode":"6415 RD",
    "sg:province":"Limburg",
    "wof:name":"Vof Vethandel Smeets",
    "wof:placetype":"venue"
},
  "geometry": {"coordinates":[5.983507,50.90358],"type":"Point"}
}