{
  "type": "Feature",
  "properties": {
    "addr:full":"Klarinetwg 4 Middelburg Zeeland 4337 RA",
    "addr:housenumber":"4",
    "addr:postcode":"4337 ra",
    "addr:street":"Klarinetwg",
    "iso:country":"NL",
    "sg:address":"Klarinetwg 4",
    "sg:city":"Middelburg",
    "sg:orig_category":"Autoschade- Herstelbedrijven",
    "sg:phone":"+31 118 613 564",
    "sg:postcode":"4337 RA",
    "sg:province":"Zeeland",
    "sg:website":"http://www.care-schadeservice.nl",
    "wof:name":"Care Schadeservice Middelburg Bv",
    "wof:placetype":"venue"
},
  "geometry": {"coordinates":[3.628235,51.485477],"type":"Point"}
}