{
  "type": "Feature",
  "properties": {
    "iso:country":"NL",
    "sg:address":"J Vd Bildtstr 15",
    "sg:city":"Eindhoven",
    "sg:orig_category":"Autoruiten",
    "sg:phone":"+31 40 236 9691",
    "sg:postcode":"5621 GN",
    "sg:province":"Noord-Brabant",
    "sg:website":"http://go.to/migocars",
    "wof:name":"Migo Cars",
    "wof:placetype":"venue"
},
  "geometry": {"coordinates":[5.454995,51.454014],"type":"Point"}
}