{
  "type": "Feature",
  "properties": {
    "addr:full":"Schepperbuurt 4 Termunterzijl Groningen 9948 PP",
    "addr:housenumber":"4",
    "addr:postcode":"9948 pp",
    "addr:street":"Schepperbuurt",
    "iso:country":"NL",
    "sg:address":"Schepperbuurt 4",
    "sg:city":"Termunterzijl",
    "sg:orig_category":"Kampeerterreinen",
    "sg:phone":"+31 596 601 443",
    "sg:postcode":"9948 PP",
    "sg:province":"Groningen",
    "wof:name":"Camping Zeestrand Eemsdollard",
    "wof:placetype":"venue"
},
  "geometry": {"coordinates":[7.0317292213,53.3009376526],"type":"Point"}
}