{
  "type": "Feature",
  "properties": {
    "addr:full":"Noordzyde 13Bis Noordeloos Zuid-Holland 4225 PG",
    "addr:housenumber":"13bis",
    "addr:postcode":"4225 pg",
    "iso:country":"NL",
    "sg:address":"Noordzyde 13Bis",
    "sg:city":"Noordeloos",
    "sg:orig_category":"Boekhandels",
    "sg:phone":"+31 183 588 215",
    "sg:postcode":"4225 PG",
    "sg:province":"Zuid-Holland",
    "wof:name":"Koetshuis, 'T",
    "wof:placetype":"venue"
},
  "geometry": {"coordinates":[4.942041,51.904411],"type":"Point"}
}