{
  "type": "Feature",
  "properties": {
    "iso:country":"NL",
    "sg:address":"Morsstraat 2",
    "sg:city":"Leiden",
    "sg:orig_category":"Boekbinden And Afwerken",
    "sg:phone":"+31 71 514 9103",
    "sg:postcode":"2312 BM",
    "sg:province":"South Holland",
    "sg:website":"http://www.printer.nl",
    "wof:name":"The Printer",
    "wof:placetype":"venue"
},
  "geometry": {"coordinates":[4.484558,52.161785],"type":"Point"}
}