{
  "type": "Feature",
  "properties": {
    "addr:full":"Vijzelgracht 37 Amsterdam North Holland 1017 HP",
    "addr:housenumber":"37",
    "addr:postcode":"1017 hp",
    "addr:street":"Vijzelgracht",
    "iso:country":"NL",
    "sg:address":"Vijzelgracht 37",
    "sg:city":"Amsterdam",
    "sg:classifiers":[
        {
            "category":"Food & Beverages",
            "subcategory":"Fruits & Vegetables",
            "type":"Retail Goods"
        }
    ],
    "sg:phone":"+31 20 623 4034",
    "sg:postcode":"1017 HP",
    "sg:province":"North Holland",
    "sg:tags":[
        "groenten"
    ],
    "wof:name":"Rogh Delicatessen",
    "wof:placetype":"venue"
},
  "geometry": {"coordinates":[4.891326,52.360821],"type":"Point"}
}