{
  "type": "Feature",
  "properties": {
    "iso:country":"NL",
    "sg:address":"Hoornwg 33A",
    "sg:city":"Rotterdam",
    "sg:orig_category":"Glazenwasserijen",
    "sg:phone":"+31 10 450 9797",
    "sg:postcode":"3042 BC",
    "sg:province":"South Holland",
    "sg:website":"http://www.xs4all.nl/~mholst/hogla/",
    "wof:name":"Holst",
    "wof:placetype":"venue"
},
  "geometry": {"coordinates":[4.427414,51.933014],"type":"Point"}
}