{
  "type": "Feature",
  "properties": {
    "addr:full":"Grote Markt 147 Almere Flevoland 1315 JD",
    "addr:housenumber":"147",
    "addr:postcode":"1315 jd",
    "addr:street":"Grote Markt;Flevoland",
    "iso:country":"NL",
    "sg:address":"Grote Markt 147",
    "sg:city":"Almere",
    "sg:orig_category":"Advocaten And Juridische Adviseurs",
    "sg:phone":"+31 36 533 6600",
    "sg:postcode":"1315 JD",
    "sg:province":"Flevoland",
    "wof:name":"Langelaar & Schepel Advocaten",
    "wof:placetype":"venue"
},
  "geometry": {"coordinates":[5.218199,52.372017],"type":"Point"}
}