{
  "type": "Feature",
  "properties": {
    "iso:country":"NL",
    "sg:address":"N Eswg 78",
    "sg:city":"Hengelo Ov",
    "sg:orig_category":"Hondenscholen",
    "sg:phone":"+31 74 277 7759",
    "sg:postcode":"7558 MG",
    "sg:province":"NL.08",
    "wof:name":"Hondenschool Hengelo",
    "wof:placetype":"venue"
},
  "geometry": {"coordinates":[6.78971,52.266331],"type":"Point"}
}