{
  "type": "Feature",
  "properties": {
    "addr:full":"Verlengde Hereweg 62 Groningen Groningen 9722 AG",
    "addr:housenumber":"62",
    "addr:postcode":"9722",
    "addr:street":"Verlengde Hereweg",
    "iso:country":"NL",
    "sg:address":"Verlengde Hereweg 62",
    "sg:city":"Groningen",
    "sg:classifiers":[
        {
            "category":"Communications",
            "subcategory":"Television Station",
            "type":"Services"
        }
    ],
    "sg:phone":"+31 50 527 0861",
    "sg:postcode":"9722 AG",
    "sg:province":"Groningen",
    "sg:tags":[
        "video",
        "audio",
        "verhuur"
    ],
    "wof:name":"Fun & Fantasy",
    "wof:placetype":"venue"
},
  "geometry": {"coordinates":[6.57949,53.199009],"type":"Point"}
}