{
  "type": "Feature",
  "properties": {
    "iso:country":"NL",
    "sg:address":"Smeepoortstraat 1",
    "sg:city":"Harderwijk",
    "sg:orig_category":"Banken And Kredietinstellingen",
    "sg:phone":"+31 341 436 411",
    "sg:postcode":"3841 EG",
    "sg:province":"Gelderland",
    "wof:name":"Sns Bank Gelderland Nv",
    "wof:placetype":"venue"
},
  "geometry": {"coordinates":[5.616093,52.346916],"type":"Point"}
}