{
  "type": "Feature",
  "properties": {
    "addr:full":"Arkelstein 33 Deventer Overijssel 7414 EP",
    "addr:housenumber":"33",
    "addr:postcode":"7414 ep",
    "addr:street":"Arkelstein",
    "iso:country":"NL",
    "sg:address":"Arkelstein 33",
    "sg:city":"Deventer",
    "sg:orig_category":"Horloges En Klokken - Reparatie En Onderhoud",
    "sg:phone":"+31 570 851 393",
    "sg:postcode":"7414 EP",
    "sg:province":"Overijssel",
    "wof:name":"Nieuwland Klokkenatelier",
    "wof:placetype":"venue"
},
  "geometry": {"coordinates":[6.15275,52.273254],"type":"Point"}
}