{
  "type": "Feature",
  "properties": {
    "addr:full":"Ganzevoortsingel 40 Groningen Groningen 9711 AN",
    "addr:housenumber":"40",
    "addr:postcode":"9711 an",
    "addr:street":"Ganzevoortsingel",
    "iso:country":"NL",
    "sg:address":"Ganzevoortsingel 40",
    "sg:city":"Groningen",
    "sg:orig_category":"Juridische Adviseurs",
    "sg:phone":"+31 50 318 8364",
    "sg:postcode":"9711 AN",
    "sg:province":"Groningen",
    "wof:name":"Bescherm Uw Idee Bv",
    "wof:placetype":"venue"
},
  "geometry": {"coordinates":[6.560431,53.214619],"type":"Point"}
}