{
  "type": "Feature",
  "properties": {
    "addr:full":"Heerenwg 40 Heiloo Noord-Holland 1851 KS",
    "addr:housenumber":"40",
    "addr:postcode":"1851 ks",
    "addr:street":"Heerenwg",
    "iso:country":"NL",
    "sg:address":"Heerenwg 40",
    "sg:city":"Heiloo",
    "sg:orig_category":"Huishoudelijke Apparaten En Artikelen",
    "sg:phone":"+31 72 532 0427",
    "sg:postcode":"1851 KS",
    "sg:province":"Noord-Holland",
    "wof:name":"Blokker Bv",
    "wof:placetype":"venue"
},
  "geometry": {"coordinates":[4.711705,52.604599],"type":"Point"}
}