{
  "type": "Feature",
  "properties": {
    "addr:full":"Handelsweg 26 Tynaarlo Drenthe 9482 WE",
    "addr:housenumber":"26",
    "addr:postcode":"9482 we",
    "addr:street":"Handelsweg",
    "iso:country":"NL",
    "sg:address":"Handelsweg 26",
    "sg:city":"Tynaarlo",
    "sg:orig_category":"Wegen And Sportterreinen",
    "sg:phone":"+31 592 530 630",
    "sg:postcode":"9482 WE",
    "sg:province":"Drenthe",
    "wof:name":"Snitjer",
    "wof:placetype":"venue"
},
  "geometry": {"coordinates":[6.6021208763,53.085395813],"type":"Point"}
}