{
  "type": "Feature",
  "properties": {
    "addr:full":"Sydneystr 3 Rotterdam Zuid-Holland 3047 BP",
    "addr:housenumber":"3",
    "addr:postcode":"3047 bp",
    "addr:street":"Sydneystr",
    "iso:country":"NL",
    "sg:address":"Sydneystr 3",
    "sg:city":"Rotterdam",
    "sg:orig_category":"Kantoor- En Bedrijfsmeubelen",
    "sg:phone":"+31 10 446 6600",
    "sg:postcode":"3047 BP",
    "sg:province":"Zuid-Holland",
    "wof:name":"Kmc",
    "wof:placetype":"venue"
},
  "geometry": {"coordinates":[4.4085130692,51.9416618347],"type":"Point"}
}