{
  "type": "Feature",
  "properties": {
    "addr:full":"Terminalwg 5-7 Amersfoort Utrecht 3821 AJ",
    "addr:housenumber":"5-7",
    "addr:postcode":"3821 aj",
    "addr:street":"Terminalwg",
    "iso:country":"NL",
    "sg:address":"Terminalwg 5-7",
    "sg:city":"Amersfoort",
    "sg:orig_category":"Kantoor- En Bedrijfsmeubelen - Fabrieken En Groothandel",
    "sg:phone":"+31 33 455 2561",
    "sg:postcode":"3821 AJ",
    "sg:province":"Utrecht",
    "sg:website":"http://www.wsm-framebouw.nl",
    "wof:name":"Wsm",
    "wof:placetype":"venue"
},
  "geometry": {"coordinates":[5.413795948,52.1773452759],"type":"Point"}
}