{
  "type": "Feature",
  "properties": {
    "addr:full":"Van Kesselplaats 2 Ravenstein Noord-Brabant 5371 AX",
    "addr:housenumber":"2",
    "addr:postcode":"5371 ax",
    "iso:country":"NL",
    "sg:address":"Van Kesselplaats 2",
    "sg:city":"Ravenstein",
    "sg:orig_category":"Overheidsdiensten",
    "sg:phone":"+31 486 411 778",
    "sg:postcode":"5371 AX",
    "sg:province":"Noord-Brabant",
    "wof:name":"Vidi-Reo",
    "wof:placetype":"venue"
},
  "geometry": {"coordinates":[5.6517748833,51.7956542969],"type":"Point"}
}