{
  "type": "Feature",
  "properties": {
    "addr:full":"Steenweg 94 Neerijnen Gelderland 4182 PB",
    "addr:housenumber":"94",
    "addr:postcode":"4182 pb",
    "addr:street":"Steenweg;Gelderland",
    "iso:country":"NL",
    "sg:address":"Steenweg 94",
    "sg:city":"Neerijnen",
    "sg:orig_category":"Wegen And Sportterreinen",
    "sg:phone":"+31 345 569 887",
    "sg:postcode":"4182 PB",
    "sg:province":"Gelderland",
    "wof:name":"Vof V.Z.B. Neerijnen",
    "wof:placetype":"venue"
},
  "geometry": {"coordinates":[5.2724971771,51.8512649536],"type":"Point"}
}