{
  "type": "Feature",
  "properties": {
    "iso:country":"NL",
    "sg:address":"Mathenesserln 336",
    "sg:city":"Rotterdam",
    "sg:orig_category":"Architecten En Architectenbureaus",
    "sg:phone":"+31 10 477 3707",
    "sg:postcode":"3021 HZ",
    "sg:province":"Zuid-Holland",
    "wof:name":"Vries, M F W De",
    "wof:placetype":"venue"
},
  "geometry": {"coordinates":[4.45709,51.913792],"type":"Point"}
}