{
  "type": "Feature",
  "properties": {
    "addr:full":"Nw Ryn 24 Leiden South Holland 2312 JD",
    "addr:housenumber":"24",
    "addr:postcode":"2312 jd",
    "addr:street":"Nw Ryn",
    "iso:country":"NL",
    "sg:address":"Nw Ryn 24",
    "sg:city":"Leiden",
    "sg:orig_category":"Woninginrichting",
    "sg:phone":"+31 71 513 4671",
    "sg:postcode":"2312 JD",
    "sg:province":"South Holland",
    "sg:website":"http://www.bentveldinterieur.nl",
    "wof:name":"Bentveld Interieur",
    "wof:placetype":"venue"
},
  "geometry": {"coordinates":[4.4946298599,52.1545715332],"type":"Point"}
}