{
  "type": "Feature",
  "properties": {
    "iso:country":"NL",
    "sg:address":"Rijnstraat 151",
    "sg:city":"Katwijk Zh",
    "sg:orig_category":"Begrafenisondernemers",
    "sg:phone":"+31 71 402 9610",
    "sg:postcode":"2223 EA",
    "sg:province":"Zuid-Holland",
    "wof:name":"Joodse Begraafplaats",
    "wof:placetype":"venue"
},
  "geometry": {"coordinates":[4.421504,52.197712],"type":"Point"}
}