{
  "type": "Feature",
  "properties": {
    "addr:full":"Columbusstraat 15 Rotterdam Albrands South Holland 3165 AC",
    "addr:housenumber":"15",
    "addr:postcode":"3165 ac",
    "addr:street":"Columbusstraat",
    "iso:country":"NL",
    "sg:address":"Columbusstraat 15",
    "sg:city":"Rotterdam Albrands",
    "sg:orig_category":"Goederenvervoer Over De Weg",
    "sg:phone":"+31 10 494 5777",
    "sg:postcode":"3165 AC",
    "sg:province":"South Holland",
    "wof:name":"Vitesse Transport Bv",
    "wof:placetype":"venue"
},
  "geometry": {"coordinates":[4.42053,51.869549],"type":"Point"}
}