{
  "type": "Feature",
  "properties": {
    "addr:full":"Akkerwg 3 , (Mobiele Telefoon) Riel Noord-Brabant 5133 NB",
    "addr:housenumber":"3",
    "addr:postcode":"5133 nb",
    "addr:street":"Akkerwg;Telefoon",
    "iso:country":"NL",
    "sg:address":"Akkerwg 3 , (Mobiele Telefoon)",
    "sg:city":"Riel",
    "sg:orig_category":"Hoefsmederijen",
    "sg:phone":"+31 6 53408812",
    "sg:postcode":"5133 NB",
    "sg:province":"Noord-Brabant",
    "wof:name":"Dries Boink",
    "wof:placetype":"venue"
},
  "geometry": {"coordinates":[5.009474,51.513935],"type":"Point"}
}