{
  "type": "Feature",
  "properties": {
    "addr:full":"Marnixkd 35 Amsterdam Noord-Holland 1015 XR",
    "addr:housenumber":"35",
    "addr:postcode":"1015 xr",
    "addr:street":"Marnixkd",
    "iso:country":"NL",
    "sg:address":"Marnixkd 35",
    "sg:city":"Amsterdam",
    "sg:orig_category":"Homeopathie",
    "sg:phone":"+31 20 626 4209",
    "sg:postcode":"1015 XR",
    "sg:province":"Noord-Holland",
    "wof:name":"A'Damse Samenwerkende Klassiek Homeopaten",
    "wof:placetype":"venue"
},
  "geometry": {"coordinates":[4.893195,52.373119],"type":"Point"}
}