{
  "type": "Feature",
  "properties": {
    "addr:full":"Marconistraat 30 Heerhugowaard North Holland 1704 RG",
    "addr:housenumber":"30",
    "addr:postcode":"1704 rg",
    "addr:street":"Marconistraat",
    "iso:country":"NL",
    "sg:address":"Marconistraat 30",
    "sg:city":"Heerhugowaard",
    "sg:orig_category":"Verhuur Bouwmachines",
    "sg:phone":"+31 72 574 4333",
    "sg:postcode":"1704 RG",
    "sg:province":"North Holland",
    "wof:name":"Meerestein Kraanbedrijf Bv",
    "wof:placetype":"venue"
},
  "geometry": {"coordinates":[4.834422,52.683102],"type":"Point"}
}