{
  "type": "Feature",
  "properties": {
    "addr:full":"Maaslandln 72 Weert Limburg 6004 GE",
    "addr:housenumber":"72",
    "addr:postcode":"6004",
    "addr:street":"Maaslandln",
    "iso:country":"NL",
    "sg:address":"Maaslandln 72",
    "sg:city":"Weert",
    "sg:orig_category":"Meubelen",
    "sg:phone":"+31 495 520 644",
    "sg:postcode":"6004 GE",
    "sg:province":"Limburg",
    "wof:name":"Lierop Bv, M Van",
    "wof:placetype":"venue"
},
  "geometry": {"coordinates":[5.723024,51.252773],"type":"Point"}
}