{
  "type": "Feature",
  "properties": {
    "addr:full":"Grt Gent 11 Vught Noord-Brabant 5261 BT",
    "addr:housenumber":"11",
    "addr:postcode":"5261 bt",
    "iso:country":"NL",
    "sg:address":"Grt Gent 11",
    "sg:city":"Vught",
    "sg:orig_category":"Meubelmakerijen",
    "sg:phone":"+31 73 656 5913",
    "sg:postcode":"5261 BT",
    "sg:province":"Noord-Brabant",
    "wof:name":"Maine, F Du",
    "wof:placetype":"venue"
},
  "geometry": {"coordinates":[5.301835,51.660637],"type":"Point"}
}