{
  "type": "Feature",
  "properties": {
    "addr:full":"Kerkstr 31 Ysselstein Ut Utrecht 3401 CM",
    "addr:housenumber":"31",
    "addr:postcode":"3401 cm",
    "addr:street":"Kerkstr",
    "iso:country":"NL",
    "sg:address":"Kerkstr 31",
    "sg:city":"Ysselstein Ut",
    "sg:orig_category":"Babyartikelen",
    "sg:phone":"+31 30 267 3494",
    "sg:postcode":"3401 CM",
    "sg:province":"Utrecht",
    "sg:website":"http://www.babytwinkel.nl",
    "wof:name":"Twinkel",
    "wof:placetype":"venue"
},
  "geometry": {"coordinates":[5.045617,52.020107],"type":"Point"}
}