{
  "type": "Feature",
  "properties": {
    "addr:full":"Raadhuispln 11 Oostburg Zeeland 4501 BG",
    "addr:housenumber":"11",
    "addr:postcode":"4501",
    "addr:street":"Raadhuispln",
    "iso:country":"NL",
    "sg:address":"Raadhuispln 11",
    "sg:city":"Oostburg",
    "sg:orig_category":"Webdesign Bureaus",
    "sg:phone":"+31 117 450 358",
    "sg:postcode":"4501 BG",
    "sg:province":"Zeeland",
    "sg:website":"http://www.annwebdesign.nl",
    "wof:name":"Ann Webdesign",
    "wof:placetype":"venue"
},
  "geometry": {"coordinates":[3.487126112,51.3267707825],"type":"Point"}
}