{
  "type": "Feature",
  "properties": {
    "addr:full":"Achterweg 65 Herwijnen Gelderland 4171 BB",
    "addr:housenumber":"65",
    "addr:postcode":"4171 bb",
    "addr:street":"Achterweg;Gelderland",
    "iso:country":"NL",
    "sg:address":"Achterweg 65",
    "sg:city":"Herwijnen",
    "sg:orig_category":"Landbouwmachines Gh",
    "sg:phone":"+31 418 582 328",
    "sg:postcode":"4171 BB",
    "sg:province":"Gelderland",
    "wof:name":"Wiltrac Landbouwmechanisatie Bv",
    "wof:placetype":"venue"
},
  "geometry": {"coordinates":[5.141897,51.824371],"type":"Point"}
}