{
  "type": "Feature",
  "properties": {
    "addr:full":"Kerkplein 36 Hoorn Nh Noord-Holland 1621 CZ",
    "addr:housenumber":"36",
    "addr:postcode":"1621",
    "addr:street":"Kerkplein",
    "iso:country":"NL",
    "sg:address":"Kerkplein 36",
    "sg:city":"Hoorn Nh",
    "sg:orig_category":"Verlichting And Huishoudartikelen",
    "sg:phone":"+31 229 218 162",
    "sg:postcode":"1621 CZ",
    "sg:province":"Noord-Holland",
    "wof:name":"Handelsonderneming K. & M. Haanstra",
    "wof:placetype":"venue"
},
  "geometry": {"coordinates":[5.059762,52.640263],"type":"Point"}
}