{
  "type": "Feature",
  "properties": {
    "addr:full":"Schaapsdijkweg 81 Venlo Limburg 5913 PB",
    "addr:housenumber":"81",
    "addr:postcode":"5913 pb",
    "addr:street":"Schaapsdijkweg",
    "iso:country":"NL",
    "sg:address":"Schaapsdijkweg 81",
    "sg:city":"Venlo",
    "sg:orig_category":"Autokeuringen",
    "sg:phone":"+31 77 351 2010",
    "sg:postcode":"5913 PB",
    "sg:province":"Limburg",
    "wof:name":"G T- Cars",
    "wof:placetype":"venue"
},
  "geometry": {"coordinates":[6.19108,51.374191],"type":"Point"}
}