{
  "type": "Feature",
  "properties": {
    "addr:full":"De Smalle Zijde 15 Veenendaal Utrecht 3903 LM",
    "addr:housenumber":"15",
    "addr:postcode":"3903 lm",
    "addr:street":"De Smalle Zijde",
    "iso:country":"NL",
    "sg:address":"De Smalle Zijde 15",
    "sg:city":"Veenendaal",
    "sg:orig_category":"Beveiliging",
    "sg:phone":"+31 318 500 090",
    "sg:postcode":"3903 LM",
    "sg:province":"Utrecht",
    "sg:website":"http://www.vanwakeren.nl",
    "wof:name":"Wakeren Beveiliging Bv, Van",
    "wof:placetype":"venue"
},
  "geometry": {"coordinates":[5.561892,52.008751],"type":"Point"}
}