{
  "type": "Feature",
  "properties": {
    "addr:full":"Rothenbacherweg 3 Vlodrop Limburg 6063 NJ",
    "addr:housenumber":"3",
    "addr:postcode":"6063 nj",
    "addr:street":"Rothenbacherweg",
    "iso:country":"NL",
    "sg:address":"Rothenbacherweg 3",
    "sg:city":"Vlodrop",
    "sg:orig_category":"Bloemen And Planten",
    "sg:phone":"+31 475 533 539",
    "sg:postcode":"6063 NJ",
    "sg:province":"Limburg",
    "wof:name":"J.F.A. Van Der Geer Bloemenhandel Vof",
    "wof:placetype":"venue"
},
  "geometry": {"coordinates":[-74.72672300000001,40.14278],"type":"Point"}
}