{
  "type": "Feature",
  "properties": {
    "iso:country":"NL",
    "sg:address":"Slesingerstr 2",
    "sg:city":"Brunssum",
    "sg:orig_category":"Houtgroothandel",
    "sg:phone":"+31 45 527 0585",
    "sg:postcode":"6442 PH",
    "sg:province":"Limburg",
    "sg:website":"http://www.houtzagerij.nl",
    "wof:name":"Windels, Houthandel-Zagerij",
    "wof:placetype":"venue"
},
  "geometry": {"coordinates":[5.990173,50.953838],"type":"Point"}
}