{
  "type": "Feature",
  "properties": {
    "addr:full":"Vlierstraat 25 Bergen Op Zoom Noord-Brabant 4621 GJ",
    "addr:housenumber":"25",
    "addr:postcode":"4621 gj",
    "addr:street":"Vlierstraat",
    "iso:country":"NL",
    "sg:address":"Vlierstraat 25",
    "sg:city":"Bergen Op Zoom",
    "sg:orig_category":"Metaalwerken",
    "sg:phone":"+31 164 261 545",
    "sg:postcode":"4621 GJ",
    "sg:province":"Noord-Brabant",
    "wof:name":"Double Top",
    "wof:placetype":"venue"
},
  "geometry": {"coordinates":[4.302792,51.494579],"type":"Point"}
}