{
  "type": "Feature",
  "properties": {
    "addr:full":"Kleine Veer 5 'S Hertogenbosch North Brabant 5236 EL",
    "addr:housenumber":"5 ' s",
    "addr:postcode":"5236 el",
    "addr:street":"Kleine Veer;Hertogenbosch",
    "iso:country":"NL",
    "sg:address":"Kleine Veer 5",
    "sg:city":"'S Hertogenbosch",
    "sg:orig_category":"Kappers",
    "sg:phone":"+31 73 641 4697",
    "sg:postcode":"5236 EL",
    "sg:province":"North Brabant",
    "wof:name":"Maison Helma",
    "wof:placetype":"venue"
},
  "geometry": {"coordinates":[5.327581,51.734676],"type":"Point"}
}