{
  "type": "Feature",
  "properties": {
    "addr:full":"Theresiastr 248 S Gravenhage Zuid-Holland 2593 AW",
    "addr:housenumber":"248;gravenhage",
    "addr:postcode":"2593 aw",
    "addr:street":"S",
    "iso:country":"NL",
    "sg:address":"Theresiastr 248",
    "sg:city":"S Gravenhage",
    "sg:orig_category":"Kaas",
    "sg:phone":"+31 70 385 8404",
    "sg:postcode":"2593 AW",
    "sg:province":"Zuid-Holland",
    "wof:name":"Zuivelland Bv",
    "wof:placetype":"venue"
},
  "geometry": {"coordinates":[4.3426599503,52.0861206055],"type":"Point"}
}