{
  "type": "Feature",
  "properties": {
    "addr:full":"Nijensteinheerd 4 Groningen Groningen 9736 TA",
    "addr:housenumber":"4",
    "addr:postcode":"9736 ta",
    "addr:street":"Nijensteinheerd",
    "iso:country":"NL",
    "sg:address":"Nijensteinheerd 4",
    "sg:city":"Groningen",
    "sg:classifiers":[
        {
            "category":"Fast Food",
            "type":"Food & Drink"
        }
    ],
    "sg:phone":"+31 50 542 1946",
    "sg:postcode":"9736 TA",
    "sg:province":"Groningen",
    "sg:tags":[
        "afhaal",
        "restaurant"
    ],
    "wof:name":"T Ta",
    "wof:placetype":"venue"
},
  "geometry": {"coordinates":[6.605101,53.247387],"type":"Point"}
}