{
  "type": "Feature",
  "properties": {
    "addr:full":"Ambachtswg 3 Ysselstein Ut Utrecht 3401 MK",
    "addr:housenumber":"3",
    "addr:postcode":"3401",
    "addr:street":"Ambachtswg",
    "iso:country":"NL",
    "sg:address":"Ambachtswg 3",
    "sg:city":"Ysselstein Ut",
    "sg:orig_category":"Beveiliging",
    "sg:phone":"+31 30 688 8100",
    "sg:postcode":"3401 MK",
    "sg:province":"Utrecht",
    "sg:website":"http://www.hg-beveiliging.nl",
    "wof:name":"Hg Beveiliging",
    "wof:placetype":"venue"
},
  "geometry": {"coordinates":[5.051988,52.012337],"type":"Point"}
}