{
  "type": "Feature",
  "properties": {
    "addr:full":"Dillenburgstr 27C Eindhoven Noord-Brabant 5652 AM",
    "addr:housenumber":"27c",
    "addr:postcode":"5652",
    "addr:street":"Dillenburgstr",
    "iso:country":"NL",
    "sg:address":"Dillenburgstr 27C",
    "sg:city":"Eindhoven",
    "sg:orig_category":"Onderwijsmateriaal",
    "sg:phone":"+31 40 201 4297",
    "sg:postcode":"5652 AM",
    "sg:province":"Noord-Brabant",
    "sg:website":"http://www.rijschoolservice.nl",
    "wof:name":"Smit",
    "wof:placetype":"venue"
},
  "geometry": {"coordinates":[5.437656,51.42701],"type":"Point"}
}