{
  "type": "Feature",
  "properties": {
    "addr:full":"Zandln 18 Ede Gld Gelderland 6717 LP",
    "addr:housenumber":"18",
    "addr:postcode":"6717 lp",
    "addr:street":"Zandln;Gld Gelderland",
    "iso:country":"NL",
    "sg:address":"Zandln 18",
    "sg:city":"Ede Gld",
    "sg:orig_category":"Bedrijfsorganisaties",
    "sg:phone":"+31 318 527 568",
    "sg:postcode":"6717 LP",
    "sg:province":"Gelderland",
    "sg:website":"http://www.vbw-groenplein.nl",
    "wof:name":"Vbw",
    "wof:placetype":"venue"
},
  "geometry": {"coordinates":[5.66767,52.044979],"type":"Point"}
}