{
  "type": "Feature",
  "properties": {
    "addr:full":"Burg. P. A. Rochefortstraat 9 Wehe Den Hoorn Groningen 9964 AJ",
    "addr:housenumber":"9",
    "addr:postcode":"9964 aj",
    "addr:street":"Burg. P. A. Rochefortstraat;Den Hoorn",
    "iso:country":"NL",
    "sg:address":"Burg. P. A. Rochefortstraat 9",
    "sg:city":"Wehe Den Hoorn",
    "sg:classifiers":[
        {
            "category":"Travel",
            "subcategory":"Hotels & Motels",
            "type":"Entertainment"
        }
    ],
    "sg:phone":"+31 595 577 070",
    "sg:postcode":"9964 AJ",
    "sg:province":"Groningen",
    "wof:name":"Wehestertil Hotel",
    "wof:placetype":"venue"
},
  "geometry": {"coordinates":[6.41901,53.357925],"type":"Point"}
}