{
  "type": "Feature",
  "properties": {
    "addr:full":"Bredewg 118H1 Zevenhuizen Zh Zuid-Holland 2761 KB",
    "addr:postcode":"2761 kb",
    "addr:street":"118H1",
    "iso:country":"NL",
    "sg:address":"Bredewg 118H1",
    "sg:city":"Zevenhuizen Zh",
    "sg:orig_category":"Keukens",
    "sg:phone":"+31 182 616 625",
    "sg:postcode":"2761 KB",
    "sg:province":"Zuid-Holland",
    "sg:website":"http://www.kebadesign.nl",
    "wof:name":"Keba Design",
    "wof:placetype":"venue"
},
  "geometry": {"coordinates":[4.617064,52.019104],"type":"Point"}
}