{
  "type": "Feature",
  "properties": {
    "addr:full":"Prins Hendriklaan 7 Bergen Nh Noord-Holland 1862 EK",
    "addr:housenumber":"7",
    "addr:postcode":"1862 ek",
    "addr:street":"Prins Hendriklaan",
    "iso:country":"NL",
    "sg:address":"Prins Hendriklaan 7",
    "sg:city":"Bergen Nh",
    "sg:orig_category":"Huishoudelijk Textiel Fab",
    "sg:phone":"+31 72 589 6841",
    "sg:postcode":"1862 EK",
    "sg:province":"Noord-Holland",
    "wof:name":"Holland Wolland Bv",
    "wof:placetype":"venue"
},
  "geometry": {"coordinates":[4.704197,52.670719],"type":"Point"}
}