{
  "type": "Feature",
  "properties": {
    "addr:full":"Jan Van Scorellaan 30 Heerhugowaard Noord-Holland 1701 VB",
    "addr:housenumber":"30",
    "addr:postcode":"1701 vb",
    "addr:street":"Jan Van Scorellaan",
    "iso:country":"NL",
    "sg:address":"Jan Van Scorellaan 30",
    "sg:city":"Heerhugowaard",
    "sg:orig_category":"Beautyfarms And Sauna'S",
    "sg:phone":"+31 72 571 9728",
    "sg:postcode":"1701 VB",
    "sg:province":"Noord-Holland",
    "wof:name":"H.J. Niks",
    "wof:placetype":"venue"
},
  "geometry": {"coordinates":[4.8514118195,52.675868988],"type":"Point"}
}