{
  "type": "Feature",
  "properties": {
    "addr:full":"Veerweg 11 Maasbracht Limburg 6051 AH",
    "addr:housenumber":"11",
    "addr:postcode":"6051 ah",
    "addr:street":"Veerweg",
    "iso:country":"NL",
    "sg:address":"Veerweg 11",
    "sg:city":"Maasbracht",
    "sg:orig_category":"Bouwmaterialen Gh",
    "sg:phone":"+31 475 463 444",
    "sg:postcode":"6051 AH",
    "sg:province":"Limburg",
    "wof:name":"Goudriaan Zand En Grint Bv",
    "wof:placetype":"venue"
},
  "geometry": {"coordinates":[5.8881,51.151859],"type":"Point"}
}