{
  "type": "Feature",
  "properties": {
    "addr:full":"Mozartln 18 Zwijndrecht Zuid-Holland 3335 AJ",
    "addr:housenumber":"18",
    "addr:postcode":"3335 aj",
    "addr:street":"Mozartln",
    "iso:country":"NL",
    "sg:address":"Mozartln 18",
    "sg:city":"Zwijndrecht",
    "sg:orig_category":"Mensendieck - Oefentherapeuten",
    "sg:phone":"+31 78 610 3667",
    "sg:postcode":"3335 AJ",
    "sg:province":"Zuid-Holland",
    "wof:name":"Engeland, N Van",
    "wof:placetype":"venue"
},
  "geometry": {"coordinates":[4.65647,51.822247],"type":"Point"}
}