{
  "type": "Feature",
  "properties": {
    "addr:full":"A Frankln 293 Purmerend Noord-Holland 1443 HH",
    "addr:housenumber":"293",
    "addr:postcode":"1443 hh",
    "iso:country":"NL",
    "sg:address":"A Frankln 293",
    "sg:city":"Purmerend",
    "sg:orig_category":"Koeriersdiensten",
    "sg:phone":"+31 6 23044292",
    "sg:postcode":"1443 HH",
    "sg:province":"Noord-Holland",
    "wof:name":"Meer, Van Der",
    "wof:placetype":"venue"
},
  "geometry": {"coordinates":[4.970748,52.508877],"type":"Point"}
}