{
  "type": "Feature",
  "properties": {
    "addr:full":"Eeg Str 4 Hulsberg Limburg 6336 BW",
    "addr:housenumber":"4",
    "addr:postcode":"6336 bw",
    "addr:street":"Str",
    "iso:country":"NL",
    "sg:address":"Eeg Str 4",
    "sg:city":"Hulsberg",
    "sg:orig_category":"Voetbalverenigingen",
    "sg:phone":"+31 45 405 1996",
    "sg:postcode":"6336 BW",
    "sg:province":"Limburg",
    "wof:name":"Hulsberg Vv",
    "wof:placetype":"venue"
},
  "geometry": {"coordinates":[5.85291,50.885757],"type":"Point"}
}