{
  "type": "Feature",
  "properties": {
    "addr:full":"Keenstr 25 Rotterdam Zuid-Holland 3044 CD",
    "addr:housenumber":"25",
    "addr:postcode":"3044 cd",
    "addr:street":"Keenstr",
    "iso:country":"NL",
    "sg:address":"Keenstr 25",
    "sg:city":"Rotterdam",
    "sg:orig_category":"Meubelen - Fabrieken En Groothandel",
    "sg:phone":"+31 10 415 9215",
    "sg:postcode":"3044 CD",
    "sg:province":"Zuid-Holland",
    "sg:website":"http://www.multifurn.nl",
    "wof:name":"Multifurn Bv",
    "wof:placetype":"venue"
},
  "geometry": {"coordinates":[4.419288,51.930809],"type":"Point"}
}