{
  "type": "Feature",
  "properties": {
    "addr:full":"Europawg 200 Apeldoorn Gelderland 7336 AR",
    "addr:housenumber":"200",
    "addr:postcode":"7336",
    "addr:street":"Gelderland",
    "iso:country":"NL",
    "sg:address":"Europawg 200",
    "sg:city":"Apeldoorn",
    "sg:orig_category":"Wasserijbenodigdheden",
    "sg:phone":"+31 55 533 2023",
    "sg:postcode":"7336 AR",
    "sg:province":"Gelderland",
    "wof:name":"Goudkuil",
    "wof:placetype":"venue"
},
  "geometry": {"coordinates":[5.9362969398,52.1936416626],"type":"Point"}
}