{
  "type": "Feature",
  "properties": {
    "addr:full":"Nieuwe Prinsengracht 39 Amsterdam North Holland 1018 EG",
    "addr:housenumber":"39",
    "addr:postcode":"1018 eg",
    "addr:street":"Nieuwe Prinsengracht",
    "iso:country":"NL",
    "sg:address":"Nieuwe Prinsengracht 39",
    "sg:city":"Amsterdam",
    "sg:orig_category":"Grafisch Ontwerpers",
    "sg:phone":"+31 20 626 1929",
    "sg:postcode":"1018 EG",
    "sg:province":"North Holland",
    "wof:name":"Formlab",
    "wof:placetype":"venue"
},
  "geometry": {"coordinates":[4.904972,52.363506],"type":"Point"}
}