{
  "type": "Feature",
  "properties": {
    "addr:full":"Graafland 17 Groot Ammers Zuid-Holland 2964 BH",
    "addr:housenumber":"17",
    "addr:postcode":"2964 bh",
    "addr:street":"Graafland;Groot Ammers",
    "iso:country":"NL",
    "sg:address":"Graafland 17",
    "sg:city":"Groot Ammers",
    "sg:orig_category":"Geluidshinderbestrijding",
    "sg:phone":"+31 184 661 700",
    "sg:postcode":"2964 BH",
    "sg:province":"Zuid-Holland",
    "sg:website":"http://www.lukagro.nl",
    "wof:name":"Lukagro",
    "wof:placetype":"venue"
},
  "geometry": {"coordinates":[4.825691,51.922188],"type":"Point"}
}