{
  "type": "Feature",
  "properties": {
    "iso:country":"NL",
    "sg:address":"Dreef 40",
    "sg:city":"Haarlem",
    "sg:orig_category":"Banken And Kredietinstellingen",
    "sg:phone":"+31 23 514 5811",
    "sg:postcode":"2012 HS",
    "sg:province":"Noord-Holland",
    "wof:name":"Rabobank",
    "wof:placetype":"venue"
},
  "geometry": {"coordinates":[4.62867,52.370476],"type":"Point"}
}