{
  "type": "Feature",
  "properties": {
    "addr:full":"Lekkerbeetjenln 150 Vught Noord-Brabant 5263 LB",
    "addr:housenumber":"150",
    "addr:postcode":"vught;5263 lb",
    "iso:country":"NL",
    "sg:address":"Lekkerbeetjenln 150",
    "sg:city":"Vught",
    "sg:orig_category":"Adviesbureaus Bedrijfsorganisatie",
    "sg:phone":"+31 6 51557639",
    "sg:postcode":"5263 LB",
    "sg:province":"Noord-Brabant",
    "wof:name":"Doorenbos Bv, H",
    "wof:placetype":"venue"
},
  "geometry": {"coordinates":[5.274416,51.656487],"type":"Point"}
}