{
  "type": "Feature",
  "properties": {
    "addr:full":"Westzanerdk 388 Zaandam North Holland 1507 AR",
    "addr:housenumber":"388",
    "addr:postcode":"1507",
    "iso:country":"NL",
    "sg:address":"Westzanerdk 388",
    "sg:city":"Zaandam",
    "sg:orig_category":"Verpakkingen En Verpakkingsmaterialen",
    "sg:phone":"+31 75 653 6353",
    "sg:postcode":"1507 AR",
    "sg:province":"North Holland",
    "sg:website":"http://www.hordijk.nl",
    "wof:name":"Hordijk Verpakkingsindustrie Bv",
    "wof:placetype":"venue"
},
  "geometry": {"coordinates":[4.794672,52.431404],"type":"Point"}
}