{
  "type": "Feature",
  "properties": {
    "addr:full":"Sandstromstraat 23 Oosterland Zeeland 4307 AW",
    "addr:housenumber":"23",
    "addr:postcode":"4307 aw",
    "addr:street":"Sandstromstraat",
    "iso:country":"NL",
    "sg:address":"Sandstromstraat 23",
    "sg:city":"Oosterland",
    "sg:orig_category":"Fitnesscentra",
    "sg:phone":"+31 111 642 876",
    "sg:postcode":"4307 AW",
    "sg:province":"Zeeland",
    "wof:name":"Sportschool Geelhoed",
    "wof:placetype":"venue"
},
  "geometry": {"coordinates":[4.040615,51.651196],"type":"Point"}
}