{
  "type": "Feature",
  "properties": {
    "addr:full":"Zilkerduinwg 114 De Zilk South Holland 2191 AP",
    "addr:housenumber":"114",
    "addr:postcode":"2191 ap",
    "iso:country":"NL",
    "sg:address":"Zilkerduinwg 114",
    "sg:city":"De Zilk",
    "sg:orig_category":"Montagebedrijven",
    "sg:phone":"+31 252 518 140",
    "sg:postcode":"2191 AP",
    "sg:province":"South Holland",
    "wof:name":"Wz",
    "wof:placetype":"venue"
},
  "geometry": {"coordinates":[4.54192,52.30331],"type":"Point"}
}