{
  "type": "Feature",
  "properties": {
    "addr:full":"Korhoenstr 58 Alkmaar Noord-Holland 1826 HW",
    "addr:housenumber":"58",
    "addr:postcode":"1826 hw",
    "addr:street":"Korhoenstr",
    "iso:country":"NL",
    "sg:address":"Korhoenstr 58",
    "sg:city":"Alkmaar",
    "sg:orig_category":"Verenigingen En Stichtingen",
    "sg:phone":"+31 72 562 5208",
    "sg:postcode":"1826 HW",
    "sg:province":"Noord-Holland",
    "wof:name":"Pcob Ouderenbond",
    "wof:placetype":"venue"
},
  "geometry": {"coordinates":[4.765298,52.662247],"type":"Point"}
}