{
  "type": "Feature",
  "properties": {
    "addr:full":"Burg Stramanwg 122 Amsterdam Zuidoost North Holland 1101 EN",
    "addr:housenumber":"122",
    "addr:postcode":"1101 en",
    "addr:street":"Burg",
    "iso:country":"NL",
    "sg:address":"Burg Stramanwg 122",
    "sg:city":"Amsterdam Zuidoost",
    "sg:orig_category":"Keuken- Inbouwapparatuur",
    "sg:phone":"+31 20 430 4500",
    "sg:postcode":"1101 EN",
    "sg:province":"North Holland",
    "sg:website":"http://www.bosch-huishoudelijke-apparaten.nl",
    "wof:name":"Willem Van Rijn Bv",
    "wof:placetype":"venue"
},
  "geometry": {"coordinates":[4.935923,52.310776],"type":"Point"}
}