{
  "type": "Feature",
  "properties": {
    "addr:full":"Korteweegje 11 Dirksland Zuid-Holland 3247 BH",
    "addr:housenumber":"11",
    "addr:postcode":"3247 bh",
    "addr:street":"Korteweegje",
    "iso:country":"NL",
    "sg:address":"Korteweegje 11",
    "sg:city":"Dirksland",
    "sg:orig_category":"Goederenvervoer Over De Weg",
    "sg:phone":"+31 187 603 130",
    "sg:postcode":"3247 BH",
    "sg:province":"Zuid-Holland",
    "wof:name":"P T H Hogerwerf-Transport",
    "wof:placetype":"venue"
},
  "geometry": {"coordinates":[4.107584,51.748394],"type":"Point"}
}