{
  "type": "Feature",
  "properties": {
    "addr:full":"Praam 55 Heerenveen Friesland 8447 CG",
    "addr:housenumber":"55",
    "addr:postcode":"8447 cg",
    "addr:street":"Praam",
    "iso:country":"NL",
    "sg:address":"Praam 55",
    "sg:city":"Heerenveen",
    "sg:orig_category":"Kappers",
    "sg:phone":"+31 513 628 682",
    "sg:postcode":"8447 CG",
    "sg:province":"Friesland",
    "wof:name":"Karin Haarsma Kapsalon",
    "wof:placetype":"venue"
},
  "geometry": {"coordinates":[5.9031090736,52.9632415771],"type":"Point"}
}