{
  "type": "Feature",
  "properties": {
    "iso:country":"NL",
    "sg:address":"D Nieuwenhuiswg 158",
    "sg:city":"Dordrecht",
    "sg:orig_category":"Vertalers",
    "sg:phone":"+31 78 617 6026",
    "sg:postcode":"3317 SH",
    "sg:province":"South Holland",
    "wof:name":"Wertheim, Drs J H",
    "wof:placetype":"venue"
},
  "geometry": {"coordinates":[4.661534,51.786972],"type":"Point"}
}