{
  "type": "Feature",
  "properties": {
    "addr:full":"Nijhoffgaarde 179 Deventer NL.08 7414 WN",
    "addr:housenumber":"179;nl.08",
    "addr:postcode":"7414 wn",
    "addr:street":"Nijhoffgaarde",
    "iso:country":"NL",
    "sg:address":"Nijhoffgaarde 179",
    "sg:city":"Deventer",
    "sg:orig_category":"Schoonheidssalons",
    "sg:phone":"+31 570 642 077",
    "sg:postcode":"7414 WN",
    "sg:province":"NL.08",
    "wof:name":"Massage- En Pedicurepraktijk P J Ranzijn",
    "wof:placetype":"venue"
},
  "geometry": {"coordinates":[6.136834,52.275692],"type":"Point"}
}