{
  "type": "Feature",
  "properties": {
    "addr:full":"Antoniushof 13 Utrecht Utrecht 3583 ZA",
    "addr:housenumber":"13",
    "addr:postcode":"3583",
    "addr:street":"Antoniushof",
    "iso:country":"NL",
    "sg:address":"Antoniushof 13",
    "sg:city":"Utrecht",
    "sg:orig_category":"Adviesbureaus Economie",
    "sg:phone":"+31 30 254 6575",
    "sg:postcode":"3583 ZA",
    "sg:province":"Utrecht",
    "wof:name":"Rietmusch Bv",
    "wof:placetype":"venue"
},
  "geometry": {"coordinates":[5.145234,52.086826],"type":"Point"}
}