{
  "type": "Feature",
  "properties": {
    "addr:full":"Laarwg 41 Velp Gld Gelderland 6882 AB",
    "addr:housenumber":"41",
    "addr:postcode":"6882 ab",
    "addr:street":"Laarwg;Gld Gelderland",
    "iso:country":"NL",
    "sg:address":"Laarwg 41",
    "sg:city":"Velp Gld",
    "sg:orig_category":"Geluidsinstallaties - Verhuur",
    "sg:phone":"+31 26 362 2800",
    "sg:postcode":"6882 AB",
    "sg:province":"Gelderland",
    "wof:name":"Hulswit",
    "wof:placetype":"venue"
},
  "geometry": {"coordinates":[5.963078,51.993023],"type":"Point"}
}