{
  "type": "Feature",
  "properties": {
    "addr:full":"Pretoriusstr 90E Amsterdam Noord-Holland 1092 GL",
    "addr:housenumber":"90e",
    "addr:postcode":"1092 gl",
    "addr:street":"Pretoriusstr",
    "iso:country":"NL",
    "sg:address":"Pretoriusstr 90E",
    "sg:city":"Amsterdam",
    "sg:classifiers":[
        {
            "category":"Food & Beverages",
            "subcategory":"Bakery",
            "type":"Retail Goods"
        }
    ],
    "sg:phone":"+31 20 693 6199",
    "sg:postcode":"1092 GL",
    "sg:province":"Noord-Holland",
    "sg:tags":[
        "brood",
        "en",
        "banket"
    ],
    "wof:name":"El Kasmi",
    "wof:placetype":"venue"
},
  "geometry": {"coordinates":[4.921077,52.354694],"type":"Point"}
}