{
  "type": "Feature",
  "properties": {
    "addr:full":"Herengracht 507 Amsterdam North Holland 1017 BV",
    "addr:housenumber":"507",
    "addr:postcode":"1017 bv",
    "addr:street":"Herengracht",
    "iso:country":"NL",
    "sg:address":"Herengracht 507",
    "sg:city":"Amsterdam",
    "sg:orig_category":"Boekenuitgeverijen",
    "sg:phone":"+31 20 556 6800",
    "sg:postcode":"1017 BV",
    "sg:province":"North Holland",
    "wof:name":"Thiememeulenhoff",
    "wof:placetype":"venue"
},
  "geometry": {"coordinates":[4.891909,52.365589],"type":"Point"}
}