{
  "type": "Feature",
  "properties": {
    "iso:country":"NL",
    "sg:address":"Herengracht 507",
    "sg:city":"Amsterdam",
    "sg:orig_category":"Boekenuitgeverijen",
    "sg:phone":"+31 20 556 6800",
    "sg:postcode":"1017 BV",
    "sg:province":"North Holland",
    "wof:name":"Thiememeulenhoff",
    "wof:placetype":"venue"
},
  "geometry": {"coordinates":[4.891909,52.365589],"type":"Point"}
}