{
  "type": "Feature",
  "properties": {
    "addr:full":"Leusderweg 246 Amersfoort Utrecht 3817 KH",
    "addr:housenumber":"246",
    "addr:postcode":"3817 kh",
    "addr:street":"Leusderweg",
    "iso:country":"NL",
    "sg:address":"Leusderweg 246",
    "sg:city":"Amersfoort",
    "sg:classifiers":[
        {
            "category":"Fast Food",
            "type":"Food & Drink"
        }
    ],
    "sg:phone":"+31 33 461 2103",
    "sg:postcode":"3817 KH",
    "sg:province":"Utrecht",
    "sg:tags":[
        "afhaal",
        "restaurant"
    ],
    "wof:name":"Vof Cafetaria Bolletje Van Polletje",
    "wof:placetype":"venue"
},
  "geometry": {"coordinates":[5.37836,52.140697],"type":"Point"}
}