{
  "type": "Feature",
  "properties": {
    "addr:full":"Buorren 21 Oudega Gem Small North Carolina 9216 WB",
    "addr:housenumber":"21",
    "addr:postcode":"9216 wb",
    "addr:street":"Buorren",
    "iso:country":"NL",
    "sg:address":"Buorren 21",
    "sg:city":"Oudega Gem Small",
    "sg:classifiers":[
        {
            "category":"Food & Beverages",
            "subcategory":"Bakery",
            "type":"Retail Goods"
        }
    ],
    "sg:phone":"+31 512 371 366",
    "sg:postcode":"9216 WB",
    "sg:province":"North Carolina",
    "sg:tags":[
        "brood",
        "en",
        "banket"
    ],
    "wof:name":"Vries, K W De",
    "wof:placetype":"venue"
},
  "geometry": {"coordinates":[-76.85424,35.284199],"type":"Point"}
}