{
  "type": "Feature",
  "properties": {
    "addr:full":"Burggravenlaan 40 Katwijk Zh South Holland 2223 GA",
    "addr:housenumber":"40",
    "addr:postcode":"zh;2223 ga",
    "addr:street":"Burggravenlaan",
    "iso:country":"NL",
    "sg:address":"Burggravenlaan 40",
    "sg:city":"Katwijk Zh",
    "sg:orig_category":"Verhuur Audiovisuele Apparatuur",
    "sg:phone":"+31 6 25021469",
    "sg:postcode":"2223 GA",
    "sg:province":"South Holland",
    "wof:name":"Prosound",
    "wof:placetype":"venue"
},
  "geometry": {"coordinates":[4.426853,52.191372],"type":"Point"}
}