{
  "type": "Feature",
  "properties": {
    "addr:full":"Paduaweg 5 Den Dolder Utrecht 3734 GG",
    "addr:housenumber":"5",
    "addr:postcode":"3734 gg",
    "addr:street":"Paduaweg",
    "iso:country":"NL",
    "sg:address":"Paduaweg 5",
    "sg:city":"Den Dolder",
    "sg:orig_category":"Banken And Kredietinstellingen",
    "sg:phone":"+31 30 228 2211",
    "sg:postcode":"3734 GG",
    "sg:province":"Utrecht",
    "wof:name":"Postkantoor",
    "wof:placetype":"venue"
},
  "geometry": {"coordinates":[5.240051,52.139069],"type":"Point"}
}