{
  "type": "Feature",
  "properties": {
    "addr:full":"Mauritsweg 48 Stein Lb Limburg 6171 AJ",
    "addr:housenumber":"48",
    "addr:postcode":"lb;6171 aj",
    "addr:street":"Mauritsweg",
    "iso:country":"NL",
    "sg:address":"Mauritsweg 48",
    "sg:city":"Stein Lb",
    "sg:orig_category":"Muziekinstrumenten",
    "sg:phone":"+31 46 433 3227",
    "sg:postcode":"6171 AJ",
    "sg:province":"Limburg",
    "wof:name":"Muziekhuis Lyana",
    "wof:placetype":"venue"
},
  "geometry": {"coordinates":[-93.129936,36.705662],"type":"Point"}
}