{
  "type": "Feature",
  "properties": {
    "addr:full":"Kreek 147 Lelystad Flevoland 8212 XJ",
    "addr:housenumber":"147",
    "addr:postcode":"8212 xj",
    "addr:street":"Kreek;Flevoland",
    "iso:country":"NL",
    "sg:address":"Kreek 147",
    "sg:city":"Lelystad",
    "sg:orig_category":"Autorijscholen",
    "sg:phone":"+31 320 242 179",
    "sg:postcode":"8212 XJ",
    "sg:province":"Flevoland",
    "wof:name":"Gerven, R Van",
    "wof:placetype":"venue"
},
  "geometry": {"coordinates":[5.496065,52.513165],"type":"Point"}
}