{
  "type": "Feature",
  "properties": {
    "addr:full":"Groenewg 6 S Gravenzande Zuid-Holland 2691 MP",
    "addr:housenumber":"6;gravenzande",
    "addr:postcode":"2691 mp",
    "addr:street":"Groenewg;S",
    "iso:country":"NL",
    "sg:address":"Groenewg 6",
    "sg:city":"S Gravenzande",
    "sg:orig_category":"Loonbedrijven",
    "sg:phone":"+31 174 625 832",
    "sg:postcode":"2691 MP",
    "sg:province":"Zuid-Holland",
    "wof:name":"Vos, L",
    "wof:placetype":"venue"
},
  "geometry": {"coordinates":[4.197625,51.984287],"type":"Point"}
}