{
  "type": "Feature",
  "properties": {
    "addr:full":"Hortensialaan 6 Waalre North Brabant 5582 CL",
    "addr:housenumber":"6",
    "addr:postcode":"5582",
    "addr:street":"Hortensialaan",
    "iso:country":"NL",
    "sg:address":"Hortensialaan 6",
    "sg:city":"Waalre",
    "sg:orig_category":"Kappers",
    "sg:phone":"+31 40 221 4955",
    "sg:postcode":"5582 CL",
    "sg:province":"North Brabant",
    "wof:name":"Hairteam",
    "wof:placetype":"venue"
},
  "geometry": {"coordinates":[5.4692549706,51.3997077942],"type":"Point"}
}