{
  "type": "Feature",
  "properties": {
    "addr:full":"Europaplein 19 Leerdam Zuid-Holland 4142 CC",
    "addr:housenumber":"19",
    "addr:postcode":"4142 cc",
    "addr:street":"Europaplein",
    "iso:country":"NL",
    "sg:address":"Europaplein 19",
    "sg:city":"Leerdam",
    "sg:orig_category":"Kappers",
    "sg:phone":"+31 345 614 966",
    "sg:postcode":"4142 CC",
    "sg:province":"Zuid-Holland",
    "wof:name":"Kapsalon De Kapper",
    "wof:placetype":"venue"
},
  "geometry": {"coordinates":[5.0808300972,51.8897972107],"type":"Point"}
}