{
  "type": "Feature",
  "properties": {
    "iso:country":"NL",
    "sg:address":"Vendelseweg 100",
    "sg:city":"Veenendaal",
    "sg:orig_category":"Goederenvervoer Over De Weg",
    "sg:phone":"+31 318 512 303",
    "sg:postcode":"3905 LD",
    "sg:province":"Utrecht",
    "wof:name":"J.A. Van Kessel Transport",
    "wof:placetype":"venue"
},
  "geometry": {"coordinates":[5.550957,52.033863],"type":"Point"}
}