{
  "type": "Feature",
  "properties": {
    "iso:country":"NL",
    "sg:address":"Hamingerwg 5",
    "sg:city":"Staphorst",
    "sg:orig_category":"Grondwerken",
    "sg:phone":"+31 522 254 055",
    "sg:postcode":"7951 KP",
    "sg:province":"Overijssel",
    "wof:name":"Dunnink",
    "wof:placetype":"venue"
},
  "geometry": {"coordinates":[6.1689,52.657757],"type":"Point"}
}