{
  "type": "Feature",
  "properties": {
    "addr:full":"Molenstr 46 Roosendaal Noord-Brabant 4701 JT",
    "addr:housenumber":"46",
    "addr:postcode":"4701 jt",
    "addr:street":"Molenstr",
    "iso:country":"NL",
    "sg:address":"Molenstr 46",
    "sg:city":"Roosendaal",
    "sg:orig_category":"Glas, Porselein En Aardewerk",
    "sg:phone":"+31 165 533 963",
    "sg:postcode":"4701 JT",
    "sg:province":"Noord-Brabant",
    "wof:name":"Ad Van Wesel Exclusief",
    "wof:placetype":"venue"
},
  "geometry": {"coordinates":[4.458579,51.534157],"type":"Point"}
}