{
  "type": "Feature",
  "properties": {
    "addr:full":"De Burght 252 Geldrop Noord-Brabant 5664 PT",
    "addr:housenumber":"252",
    "addr:postcode":"5664 pt",
    "addr:street":"De Burght",
    "iso:country":"NL",
    "sg:address":"De Burght 252",
    "sg:city":"Geldrop",
    "sg:orig_category":"Verenigingen En Stichtingen",
    "sg:phone":"+31 40 285 6906",
    "sg:postcode":"5664 PT",
    "sg:province":"Noord-Brabant",
    "wof:name":"Werken En Wonen, Sticht",
    "wof:placetype":"venue"
},
  "geometry": {"coordinates":[5.560632,51.420597],"type":"Point"}
}