{
  "type": "Feature",
  "properties": {
    "iso:country":"NL",
    "sg:address":"Dokter Van Deenweg 100",
    "sg:city":"Zwolle",
    "sg:classifiers":[
        {
            "category":"Professional",
            "subcategory":"Accounting & Tax Preparation",
            "type":"Services"
        }
    ],
    "sg:phone":"+31 38 456 4222",
    "sg:postcode":"8025 BJ",
    "sg:province":"Overijssel",
    "sg:tags":[
        "accountant"
    ],
    "wof:name":"Deloitte & Touche",
    "wof:placetype":"venue"
},
  "geometry": {"coordinates":[6.12344,52.509151],"type":"Point"}
}