{
  "type": "Feature",
  "properties": {
    "addr:full":"Voorstraat 2 Gramsbergen NL.08 7783 AM",
    "addr:housenumber":"2;nl.08",
    "addr:postcode":"7783",
    "addr:street":"Voorstraat",
    "iso:country":"NL",
    "sg:address":"Voorstraat 2",
    "sg:city":"Gramsbergen",
    "sg:orig_category":"Paramedische Behandelingen",
    "sg:phone":"+31 524 568 552",
    "sg:postcode":"7783 AM",
    "sg:province":"NL.08",
    "wof:name":"Logopediepraktijk R Verbeek",
    "wof:placetype":"venue"
},
  "geometry": {"coordinates":[6.669341,52.610428],"type":"Point"}
}