{
  "type": "Feature",
  "properties": {
    "addr:full":"Kruisbooglaan 46 Oostvoorne Zuid-Holland 3233 RE",
    "addr:housenumber":"46",
    "addr:postcode":"3233 re",
    "addr:street":"Kruisbooglaan",
    "iso:country":"NL",
    "sg:address":"Kruisbooglaan 46",
    "sg:city":"Oostvoorne",
    "sg:orig_category":"Vertaal- And Tolkenbureaus",
    "sg:phone":"+31 181 482 914",
    "sg:postcode":"3233 RE",
    "sg:province":"Zuid-Holland",
    "wof:name":"Truvi Taaladvies",
    "wof:placetype":"venue"
},
  "geometry": {"coordinates":[4.110948,51.911343],"type":"Point"}
}