{
  "type": "Feature",
  "properties": {
    "addr:full":"Aaltensewg 11 Hengelo Gld Gelderland 7255 PG",
    "addr:housenumber":"11",
    "addr:postcode":"7255 pg",
    "addr:street":"Aaltensewg",
    "iso:country":"NL",
    "sg:address":"Aaltensewg 11",
    "sg:city":"Hengelo Gld",
    "sg:orig_category":"Hoefsmederijen",
    "sg:phone":"+31 575 463 419",
    "sg:postcode":"7255 PG",
    "sg:province":"Gelderland",
    "wof:name":"Weijers, E J H",
    "wof:placetype":"venue"
},
  "geometry": {"coordinates":[6.326303,52.044239],"type":"Point"}
}