{
  "type": "Feature",
  "properties": {
    "addr:full":"Nedereindsewg 7 Nieuwegein Utrecht 3438 AA",
    "addr:housenumber":"7",
    "addr:postcode":"3438 aa",
    "addr:street":"Nedereindsewg",
    "iso:country":"NL",
    "sg:address":"Nedereindsewg 7",
    "sg:city":"Nieuwegein",
    "sg:classifiers":[
        {
            "category":"Food & Beverages",
            "subcategory":"Bakery",
            "type":"Retail Goods"
        }
    ],
    "sg:phone":"+31 30 607 2727",
    "sg:postcode":"3438 AA",
    "sg:province":"Utrecht",
    "sg:tags":[
        "pizza"
    ],
    "sg:website":"http://www.dominos.nl",
    "wof:name":"Domino",
    "wof:placetype":"venue"
},
  "geometry": {"coordinates":[5.093006,52.037727],"type":"Point"}
}