{
  "type": "Feature",
  "properties": {
    "addr:full":"Kalslagerring 636 Nieuw Vennep North Holland 2151 TN",
    "addr:housenumber":"636",
    "addr:postcode":"2151",
    "addr:street":"Kalslagerring;Nieuw Vennep North",
    "iso:country":"NL",
    "sg:address":"Kalslagerring 636",
    "sg:city":"Nieuw Vennep",
    "sg:orig_category":"Werving En Selectie",
    "sg:phone":"+31 252 686 256",
    "sg:postcode":"2151 TN",
    "sg:province":"North Holland",
    "wof:name":"Pesas, Beco",
    "wof:placetype":"venue"
},
  "geometry": {"coordinates":[4.6202578545,52.2642822266],"type":"Point"}
}