{
  "type": "Feature",
  "properties": {
    "addr:full":"Gentsestraat 36 Hulst Zeeland 4561 EK",
    "addr:housenumber":"36",
    "addr:postcode":"4561 ek",
    "addr:street":"Gentsestraat",
    "iso:country":"NL",
    "sg:address":"Gentsestraat 36",
    "sg:city":"Hulst",
    "sg:orig_category":"Schoenen",
    "sg:phone":"+31 114 312 621",
    "sg:postcode":"4561 EK",
    "sg:province":"Zeeland",
    "wof:name":"Firma Schoenwinkel Danny",
    "wof:placetype":"venue"
},
  "geometry": {"coordinates":[4.051359,51.279167],"type":"Point"}
}