{
  "type": "Feature",
  "properties": {
    "addr:full":"A Van Het Hartweg 54 Nieuwerkerk Ad Ijssel South Holland 2913 LG",
    "addr:housenumber":"54",
    "addr:postcode":"2913 lg",
    "addr:street":"A Van Het Hartweg;Ijssel",
    "iso:country":"NL",
    "sg:address":"A Van Het Hartweg 54",
    "sg:city":"Nieuwerkerk Ad Ijssel",
    "sg:orig_category":"Goederenvervoer Over De Weg",
    "sg:phone":"+31 180 312 889",
    "sg:postcode":"2913 LG",
    "sg:province":"South Holland",
    "wof:name":"Neleman Transport Bv",
    "wof:placetype":"venue"
},
  "geometry": {"coordinates":[4.598165,51.980465],"type":"Point"}
}