{
  "type": "Feature",
  "properties": {
    "iso:country":"NL",
    "sg:address":"Churchillsingel 483",
    "sg:city":"Vlaardingen",
    "sg:orig_category":"Bejaarden - Verzorgingstehuizen",
    "sg:phone":"+31 10 474 1755",
    "sg:postcode":"3137 XB",
    "sg:province":"Zuid-Holland",
    "wof:name":"Sgzzh Lok Uitzicht",
    "wof:placetype":"venue"
},
  "geometry": {"coordinates":[4.339855,51.93206],"type":"Point"}
}