{
  "type": "Feature",
  "properties": {
    "addr:full":"Bartenwg 5 Hillegom Zuid-Holland 2182 BV",
    "addr:housenumber":"5",
    "addr:postcode":"2182 bv",
    "addr:street":"Bartenwg",
    "iso:country":"NL",
    "sg:address":"Bartenwg 5",
    "sg:city":"Hillegom",
    "sg:orig_category":"Bloembollen - Groothandel",
    "sg:phone":"+31 23 584 6229",
    "sg:postcode":"2182 BV",
    "sg:province":"Zuid-Holland",
    "sg:website":"HTTP://www.hmvanhaaster.nl",
    "wof:name":"Haaster & Znn Bv, H M Van",
    "wof:placetype":"venue"
},
  "geometry": {"coordinates":[4.569185,52.314392],"type":"Point"}
}