{
  "type": "Feature",
  "properties": {
    "iso:country":"NL",
    "sg:address":"Utrechtsewg 351",
    "sg:city":"De Bilt",
    "sg:orig_category":"Autosloperijen En Autodemontagebedrijven",
    "sg:phone":"+31 30 220 2308",
    "sg:postcode":"3731 GB",
    "sg:province":"Utrecht",
    "wof:name":"Akkie Stomphorst Bv",
    "wof:placetype":"venue"
},
  "geometry": {"coordinates":[5.163073,52.099613],"type":"Point"}
}