{
  "type": "Feature",
  "properties": {
    "iso:country":"NL",
    "sg:address":"Harn 7",
    "sg:city":"Midwoud",
    "sg:orig_category":"Huisdierenfokkers",
    "sg:phone":"+31 229 202 485",
    "sg:postcode":"1679 VC",
    "sg:province":"North Holland",
    "wof:name":"Bia Von Sim",
    "wof:placetype":"venue"
},
  "geometry": {"coordinates":[5.073548,52.7197],"type":"Point"}
}