{
  "type": "Feature",
  "properties": {
    "addr:full":"Zoutmanstraat 39 'S Gravenhage Zuid-Holland 2518 GL",
    "addr:housenumber":"39",
    "addr:postcode":"2518 gl",
    "addr:street":"Zoutmanstraat;' S",
    "iso:country":"NL",
    "sg:address":"Zoutmanstraat 39",
    "sg:city":"'S Gravenhage",
    "sg:orig_category":"Farmaceutische Producten Gh",
    "sg:phone":"+31 70 356 0990",
    "sg:postcode":"2518 GL",
    "sg:province":"Zuid-Holland",
    "wof:name":"Esceha Bv",
    "wof:placetype":"venue"
},
  "geometry": {"coordinates":[4.295648,52.081764],"type":"Point"}
}