{
  "type": "Feature",
  "properties": {
    "addr:full":"Bocht V Guinea 19 S Gravenhage Zuid-Holland 2515 MA",
    "addr:housenumber":"19;gravenhage",
    "addr:postcode":"2515 ma",
    "addr:street":"Bocht V Guinea;S",
    "iso:country":"NL",
    "sg:address":"Bocht V Guinea 19",
    "sg:city":"S Gravenhage",
    "sg:orig_category":"Adviesbureaus Bedrijfsorganisatie",
    "sg:phone":"+31 70 364 6522",
    "sg:postcode":"2515 MA",
    "sg:province":"Zuid-Holland",
    "wof:name":"Hiemstra Bv",
    "wof:placetype":"venue"
},
  "geometry": {"coordinates":[4.31741,52.083988],"type":"Point"}
}