{
  "type": "Feature",
  "properties": {
    "addr:full":"Nieuwstraat 184 Spijkenisse Zuid-Holland 3201 EE",
    "addr:housenumber":"184",
    "addr:postcode":"3201 ee",
    "addr:street":"Nieuwstraat",
    "iso:country":"NL",
    "sg:address":"Nieuwstraat 184",
    "sg:city":"Spijkenisse",
    "sg:orig_category":"Baby- And Kinderkleding",
    "sg:phone":"+31 181 690 352",
    "sg:postcode":"3201 EE",
    "sg:province":"Zuid-Holland",
    "wof:name":"We Men",
    "wof:placetype":"venue"
},
  "geometry": {"coordinates":[4.325045,51.849525],"type":"Point"}
}