{
  "type": "Feature",
  "properties": {
    "addr:full":"Ringbaan Noord 85 Tilburg Noord-Brabant 5046 AA",
    "addr:housenumber":"85",
    "addr:postcode":"5046 aa",
    "addr:street":"Ringbaan Noord",
    "iso:country":"NL",
    "sg:address":"Ringbaan Noord 85",
    "sg:city":"Tilburg",
    "sg:orig_category":"Verzekeringen",
    "sg:phone":"+31 13 581 2920",
    "sg:postcode":"5046 AA",
    "sg:province":"Noord-Brabant",
    "wof:name":"Senior Service Vof",
    "wof:placetype":"venue"
},
  "geometry": {"coordinates":[5.087332,51.576023],"type":"Point"}
}