{
  "type": "Feature",
  "properties": {
    "iso:country":"NL",
    "sg:address":"Zuiderzeestrwg 254",
    "sg:city":"Oldebroek",
    "sg:orig_category":"Kunsthars - Fabrieken",
    "sg:phone":"+31 525 631 741",
    "sg:postcode":"8096 CJ",
    "sg:province":"Gelderland",
    "wof:name":"Hoop 1853 G Blaauw En Znn Bv, De",
    "wof:placetype":"venue"
},
  "geometry": {"coordinates":[5.8934,52.445419],"type":"Point"}
}