{
  "type": "Feature",
  "properties": {
    "iso:country":"NL",
    "sg:address":"Halle Heidewg 16",
    "sg:city":"Halle",
    "sg:orig_category":"Haarden En Kachels",
    "sg:phone":"+31 314 631 741",
    "sg:postcode":"7025 CL",
    "sg:province":"Gelderland",
    "sg:website":"http://www.heidesmid.nl",
    "wof:name":"Heide Smid Bv",
    "wof:placetype":"venue"
},
  "geometry": {"coordinates":[6.439146,52.006989],"type":"Point"}
}