{
  "type": "Feature",
  "properties": {
    "addr:full":"Melis Stokestraat 1 Utrecht Utrecht 3515 BN",
    "addr:housenumber":"1",
    "addr:postcode":"3515 bn",
    "addr:street":"Melis Stokestraat",
    "iso:country":"NL",
    "sg:address":"Melis Stokestraat 1",
    "sg:city":"Utrecht",
    "sg:orig_category":"Meubelreparatie And -Restauratie",
    "sg:phone":"+31 30 271 4486",
    "sg:postcode":"3515 BN",
    "sg:province":"Utrecht",
    "wof:name":"Meubelstoffeerderij Rovers",
    "wof:placetype":"venue"
},
  "geometry": {"coordinates":[5.120158,52.101795],"type":"Point"}
}