{
  "type": "Feature",
  "properties": {
    "addr:full":"Gedempte Zuiderdiep 50 Groningen Groningen 9711 HK",
    "addr:housenumber":"50",
    "addr:postcode":"9711 hk",
    "addr:street":"Gedempte Zuiderdiep",
    "iso:country":"NL",
    "sg:address":"Gedempte Zuiderdiep 50",
    "sg:city":"Groningen",
    "sg:orig_category":"Kappers",
    "sg:phone":"+31 50 314 2122",
    "sg:postcode":"9711 HK",
    "sg:province":"Groningen",
    "wof:name":"La Coupe",
    "wof:placetype":"venue"
},
  "geometry": {"coordinates":[6.567504,53.214561],"type":"Point"}
}