{
  "type": "Feature",
  "properties": {
    "addr:full":"Binnenkadk 459 Amsterdam Noord-Holland 1018 AX",
    "addr:housenumber":"459",
    "addr:postcode":"1018 ax",
    "iso:country":"NL",
    "sg:address":"Binnenkadk 459",
    "sg:city":"Amsterdam",
    "sg:orig_category":"Adviesbureaus Bedrijfsorganisatie",
    "sg:phone":"+31 20 423 3621",
    "sg:postcode":"1018 AX",
    "sg:province":"Noord-Holland",
    "wof:name":"Dynamika",
    "wof:placetype":"venue"
},
  "geometry": {"coordinates":[4.917146,52.367859],"type":"Point"}
}