{
  "type": "Feature",
  "properties": {
    "addr:full":"Amstelkd 70 Wilnis Utrecht 3648 KA",
    "addr:housenumber":"70",
    "addr:postcode":"3648 ka",
    "addr:street":"Amstelkd",
    "iso:country":"NL",
    "sg:address":"Amstelkd 70",
    "sg:city":"Wilnis",
    "sg:orig_category":"Opslag Inboedels",
    "sg:phone":"+31 172 409 433",
    "sg:postcode":"3648 KA",
    "sg:province":"Utrecht",
    "wof:name":"Roeleveld, B J",
    "wof:placetype":"venue"
},
  "geometry": {"coordinates":[4.8592710495,52.1771507263],"type":"Point"}
}