{
  "type": "Feature",
  "properties": {
    "addr:full":"Libellemeent 48 Hilversum North Holland 1218 CG",
    "addr:housenumber":"48",
    "addr:postcode":"1218 cg",
    "addr:street":"Libellemeent",
    "iso:country":"NL",
    "sg:address":"Libellemeent 48",
    "sg:city":"Hilversum",
    "sg:orig_category":"Fotoreportages",
    "sg:phone":"+31 6 22358178",
    "sg:postcode":"1218 CG",
    "sg:province":"North Holland",
    "sg:website":"http://www.members.ams.chello.nl/h.vd.roest",
    "wof:name":"Roest, H C Van De",
    "wof:placetype":"venue"
},
  "geometry": {"coordinates":[5.140203,52.270248],"type":"Point"}
}