{
  "type": "Feature",
  "properties": {
    "addr:full":"Hellegatsestraat 29 Moerstraten Noord-Brabant 4727 TA",
    "addr:housenumber":"29",
    "addr:postcode":"4727 ta",
    "addr:street":"Hellegatsestraat",
    "iso:country":"NL",
    "sg:address":"Hellegatsestraat 29",
    "sg:city":"Moerstraten",
    "sg:orig_category":"Bloemen- And Plantenteelt",
    "sg:phone":"+31 165 301 415",
    "sg:postcode":"4727 TA",
    "sg:province":"Noord-Brabant",
    "wof:name":"Rockx Graszodenkwekerij",
    "wof:placetype":"venue"
},
  "geometry": {"coordinates":[4.358857,51.538567],"type":"Point"}
}