{
  "type": "Feature",
  "properties": {
    "iso:country":"NL",
    "sg:address":"Rijnstraat 46",
    "sg:city":"Amsterdam",
    "sg:orig_category":"Slagerijen",
    "sg:phone":"+31 20 662 3454",
    "sg:postcode":"1078 RD",
    "sg:province":"Noord-Holland",
    "wof:name":"Slagerij J.J. Veldt",
    "wof:placetype":"venue"
},
  "geometry": {"coordinates":[4.90477,52.346905],"type":"Point"}
}