{
  "type": "Feature",
  "properties": {
    "iso:country":"NL",
    "sg:address":"Bachstr 6",
    "sg:city":"Hellevoetsluis",
    "sg:orig_category":"Juridische Adviseurs",
    "sg:phone":"+31 181 315 917",
    "sg:postcode":"3223 TA",
    "sg:province":"Zuid-Holland",
    "wof:name":"Berens En Van Den Besselaar",
    "wof:placetype":"venue"
},
  "geometry": {"coordinates":[4.158517,51.840813],"type":"Point"}
}