{
  "type": "Feature",
  "properties": {
    "addr:full":"Oostvoorneln 26 S Gravenhage Zuid-Holland 2554 BH",
    "addr:housenumber":"26;gravenhage",
    "addr:postcode":"2554 bh",
    "addr:street":"Oostvoorneln;S",
    "iso:country":"NL",
    "sg:address":"Oostvoorneln 26",
    "sg:city":"S Gravenhage",
    "sg:orig_category":"Administratie- En Boekhoudkantoren",
    "sg:phone":"+31 70 323 2197",
    "sg:postcode":"2554 BH",
    "sg:province":"Zuid-Holland",
    "wof:name":"Gvt",
    "wof:placetype":"venue"
},
  "geometry": {"coordinates":[4.22476,52.067989],"type":"Point"}
}