{
  "type": "Feature",
  "properties": {
    "addr:full":"Zaagmolen 28 Capelle Ad Yssel Zuid-Holland 2906 RK",
    "addr:housenumber":"28",
    "addr:postcode":"2906 rk",
    "addr:street":"Zaagmolen",
    "iso:country":"NL",
    "sg:address":"Zaagmolen 28",
    "sg:city":"Capelle Ad Yssel",
    "sg:orig_category":"Verenigingen En Stichtingen",
    "sg:phone":"+31 10 451 1004",
    "sg:postcode":"2906 RK",
    "sg:province":"Zuid-Holland",
    "sg:website":"http://www.dekoperwiek-capelle.nl",
    "wof:name":"Stadscentrum De Koperwiek, De",
    "wof:placetype":"venue"
},
  "geometry": {"coordinates":[4.567335,51.937546],"type":"Point"}
}