{
  "type": "Feature",
  "properties": {
    "addr:full":"Tulpstr 44 Zeist Utrecht 3702 VC",
    "addr:housenumber":"44",
    "addr:postcode":"3702 vc",
    "addr:street":"Tulpstr",
    "iso:country":"NL",
    "sg:address":"Tulpstr 44",
    "sg:city":"Zeist",
    "sg:orig_category":"Verhuizingen",
    "sg:phone":"+31 30 692 2386",
    "sg:postcode":"3702 VC",
    "sg:province":"Utrecht",
    "wof:name":"Greeven & Zonen Bv",
    "wof:placetype":"venue"
},
  "geometry": {"coordinates":[5.239004,52.090443],"type":"Point"}
}