{
  "type": "Feature",
  "properties": {
    "addr:full":"Kamilleveld 23 Doetinchem Gelderland 7006 VB",
    "addr:housenumber":"23",
    "addr:postcode":"7006 vb",
    "addr:street":"Kamilleveld;Gelderland",
    "iso:country":"NL",
    "sg:address":"Kamilleveld 23",
    "sg:city":"Doetinchem",
    "sg:orig_category":"Fotostudio'S And Fotografen",
    "sg:phone":"+31 314 360 952",
    "sg:postcode":"7006 VB",
    "sg:province":"Gelderland",
    "wof:name":"Benno Harwig Fotografie",
    "wof:placetype":"venue"
},
  "geometry": {"coordinates":[6.24982,51.961754],"type":"Point"}
}