{
  "type": "Feature",
  "properties": {
    "addr:full":"Bergstraat 33 Arnhem Gelderland 6811 LC",
    "addr:housenumber":"33",
    "addr:postcode":"6811 lc",
    "addr:street":"Bergstraat",
    "iso:country":"NL",
    "sg:address":"Bergstraat 33",
    "sg:city":"Arnhem",
    "sg:orig_category":"Kinderopvang Behalve Thuis",
    "sg:phone":"+31 26 443 4536",
    "sg:postcode":"6811 LC",
    "sg:province":"Gelderland",
    "wof:name":"Kinderdagverblijf Wonderberg",
    "wof:placetype":"venue"
},
  "geometry": {"coordinates":[5.901082,51.982426],"type":"Point"}
}