{
  "type": "Feature",
  "properties": {
    "addr:full":"Berkenln 238 Groningen Groningen 9741 JV",
    "addr:housenumber":"238",
    "addr:postcode":"9741 jv",
    "iso:country":"NL",
    "sg:address":"Berkenln 238",
    "sg:city":"Groningen",
    "sg:orig_category":"Verenigingsgebouwen",
    "sg:phone":"+31 50 577 0601",
    "sg:postcode":"9741 JV",
    "sg:province":"Groningen",
    "wof:name":"Berk, De",
    "wof:placetype":"venue"
},
  "geometry": {"coordinates":[6.553343,53.234779],"type":"Point"}
}