{
  "type": "Feature",
  "properties": {
    "iso:country":"NL",
    "sg:address":"Mackayln 7",
    "sg:city":"Naarden",
    "sg:classifiers":[
        {
            "category":"Utilities",
            "subcategory":"Cable",
            "type":"Services"
        }
    ],
    "sg:phone":"+31 35 695 1672",
    "sg:postcode":"1412 CN",
    "sg:province":"Noord-Holland",
    "sg:tags":[
        "masseur",
        "en",
        "heilgymnasten"
    ],
    "wof:name":"Bodde, Th",
    "wof:placetype":"venue"
},
  "geometry": {"coordinates":[5.160918,52.28624],"type":"Point"}
}