{
  "type": "Feature",
  "properties": {
    "addr:full":"Ongeleg 3 Marijenkampen Overijssel 8339 SK",
    "addr:housenumber":"3",
    "addr:street":"Ongeleg;8339",
    "iso:country":"NL",
    "sg:address":"Ongeleg 3",
    "sg:city":"Marijenkampen",
    "sg:orig_category":"Diverse Grafische Activiteiten",
    "sg:phone":"+31 521 589 159",
    "sg:postcode":"8339 SK",
    "sg:province":"Overijssel",
    "wof:name":"Bottenheft Vof",
    "wof:placetype":"venue"
},
  "geometry": {"coordinates":[6.057801,52.813583],"type":"Point"}
}