{
  "type": "Feature",
  "properties": {
    "addr:full":"A Philipswg 911 Uithoorn North Holland 1422 AL",
    "addr:housenumber":"911",
    "addr:postcode":"1422 al",
    "iso:country":"NL",
    "sg:address":"A Philipswg 911",
    "sg:city":"Uithoorn",
    "sg:orig_category":"Luchtbehandelings- Apparaten",
    "sg:phone":"+31 297 560 079",
    "sg:postcode":"1422 AL",
    "sg:province":"North Holland",
    "sg:website":"http://www.amcorex.com",
    "wof:name":"Amcorex Bv",
    "wof:placetype":"venue"
},
  "geometry": {"coordinates":[4.83469,52.240398],"type":"Point"}
}