{
  "type": "Feature",
  "properties": {
    "addr:full":"Kastanjelaan Oost 23 Lunteren Gelderland 6741 DT",
    "addr:housenumber":"23",
    "addr:postcode":"6741 dt",
    "addr:street":"Kastanjelaan Oost;Gelderland",
    "iso:country":"NL",
    "sg:address":"Kastanjelaan Oost 23",
    "sg:city":"Lunteren",
    "sg:classifiers":[
        {
            "category":"Professional",
            "subcategory":"Accounting & Tax Preparation",
            "type":"Services"
        }
    ],
    "sg:phone":"+31 318 484 441",
    "sg:postcode":"6741 DT",
    "sg:province":"Gelderland",
    "sg:tags":[
        "accountant"
    ],
    "wof:name":"Accountantskantoor J.H. De Groot Bv",
    "wof:placetype":"venue"
},
  "geometry": {"coordinates":[5.62646,52.083591],"type":"Point"}
}