{
  "type": "Feature",
  "properties": {
    "iso:country":"NL",
    "sg:address":"Binnenpad 16",
    "sg:city":"Giethoorn",
    "sg:orig_category":"Watersport-, Sport- And Kampeerbenodigdheden Verhuur",
    "sg:phone":"+31 521 361 337",
    "sg:postcode":"8355 BR",
    "sg:province":"NL.08",
    "sg:website":"http://www.broer-giethioorn.nl",
    "wof:name":"Botenverhuur Broer Giethoorn",
    "wof:placetype":"venue"
},
  "geometry": {"coordinates":[6.0898661613,52.7259101868],"type":"Point"}
}