{
  "type": "Feature",
  "properties": {
    "addr:full":"Dr H Mollerstr 41 Best Noord-Brabant 5683 HP",
    "addr:housenumber":"41",
    "addr:postcode":"5683 hp",
    "addr:street":"Dr",
    "iso:country":"NL",
    "sg:address":"Dr H Mollerstr 41",
    "sg:city":"Best",
    "sg:orig_category":"Glasdecoratie",
    "sg:phone":"+31 499 395 499",
    "sg:postcode":"5683 HP",
    "sg:province":"Noord-Brabant",
    "wof:name":"Kosco",
    "wof:placetype":"venue"
},
  "geometry": {"coordinates":[-101.618134,31.224251],"type":"Point"}
}