{
  "type": "Feature",
  "properties": {
    "addr:full":"O Heldringstr 43 Amsterdam North Holland 1066 XT",
    "addr:housenumber":"43",
    "addr:postcode":"1066 xt",
    "iso:country":"NL",
    "sg:address":"O Heldringstr 43",
    "sg:city":"Amsterdam",
    "sg:orig_category":"Beveiliging",
    "sg:phone":"+31 20 487 8484",
    "sg:postcode":"1066 XT",
    "sg:province":"North Holland",
    "wof:name":"Group 4 Falck",
    "wof:placetype":"venue"
},
  "geometry": {"coordinates":[4.83274,52.347645],"type":"Point"}
}