{
  "type": "Feature",
  "properties": {
    "addr:full":"Westeinde 159 'S Gravenhage South Holland 2512 GX",
    "addr:housenumber":"159 '",
    "addr:postcode":"2512 gx",
    "addr:street":"Westeinde",
    "iso:country":"NL",
    "sg:address":"Westeinde 159",
    "sg:city":"'S Gravenhage",
    "sg:orig_category":"Verhuur Catering-, Feest- En Evenementbenodigdheden",
    "sg:phone":"+31 70 364 6464",
    "sg:postcode":"2512 GX",
    "sg:province":"South Holland",
    "wof:name":"San Speelautomaten",
    "wof:placetype":"venue"
},
  "geometry": {"coordinates":[4.301699,52.075718],"type":"Point"}
}