{
  "type": "Feature",
  "properties": {
    "addr:full":"Dorpsstraat 300 Nijmegen Gelderland 6544 AH",
    "addr:housenumber":"300",
    "addr:postcode":"6544 ah",
    "addr:street":"Dorpsstraat;Gelderland",
    "iso:country":"NL",
    "sg:address":"Dorpsstraat 300",
    "sg:city":"Nijmegen",
    "sg:orig_category":"Autokeuringen",
    "sg:phone":"+31 24 373 1986",
    "sg:postcode":"6544 AH",
    "sg:province":"Gelderland",
    "wof:name":"Van Der Vaart Auto'S",
    "wof:placetype":"venue"
},
  "geometry": {"coordinates":[5.809214,51.834263],"type":"Point"}
}