{
  "type": "Feature",
  "properties": {
    "addr:full":"Platsmolenerf 11 Nuth Limburg 6361 DR",
    "addr:housenumber":"11",
    "addr:postcode":"6361 dr",
    "addr:street":"Platsmolenerf",
    "iso:country":"NL",
    "sg:address":"Platsmolenerf 11",
    "sg:city":"Nuth",
    "sg:orig_category":"Verhuur Bouwmachines",
    "sg:phone":"+31 45 561 0543",
    "sg:postcode":"6361 DR",
    "sg:province":"Limburg",
    "wof:name":"Paul Meertens",
    "wof:placetype":"venue"
},
  "geometry": {"coordinates":[5.881897,50.918209],"type":"Point"}
}