{
  "type": "Feature",
  "properties": {
    "addr:full":"Straatwg 176A Rotterdam South Holland 3054 AJ",
    "addr:housenumber":"176a",
    "addr:postcode":"3054 aj",
    "iso:country":"NL",
    "sg:address":"Straatwg 176A",
    "sg:city":"Rotterdam",
    "sg:orig_category":"Verenigingen En Stichtingen",
    "sg:phone":"+31 10 422 3202",
    "sg:postcode":"3054 AJ",
    "sg:province":"South Holland",
    "wof:name":"Rotterdam Jeugd Symfonie Orkest",
    "wof:placetype":"venue"
},
  "geometry": {"coordinates":[4.48727,51.949203],"type":"Point"}
}