{
  "type": "Feature",
  "properties": {
    "addr:full":"Ln V Klarenbeek 113 Arnhem Gelderland 6824 JN",
    "addr:housenumber":"113",
    "addr:postcode":"6824 jn",
    "addr:street":"Ln",
    "iso:country":"NL",
    "sg:address":"Ln V Klarenbeek 113",
    "sg:city":"Arnhem",
    "sg:orig_category":"Orthopedagogen",
    "sg:phone":"+31 26 383 0510",
    "sg:postcode":"6824 JN",
    "sg:province":"Gelderland",
    "wof:name":"Haan, De",
    "wof:placetype":"venue"
},
  "geometry": {"coordinates":[5.9374098778,51.9936714172],"type":"Point"}
}