{
  "type": "Feature",
  "properties": {
    "addr:full":"Meestoof 20 Middelburg Zeeland 4331 VC",
    "addr:housenumber":"20",
    "addr:postcode":"4331 vc",
    "addr:street":"Meestoof",
    "iso:country":"NL",
    "sg:address":"Meestoof 20",
    "sg:city":"Middelburg",
    "sg:orig_category":"Jachthavens - Jachtwerven",
    "sg:phone":"+31 118 626 241",
    "sg:postcode":"4331 VC",
    "sg:province":"Zeeland",
    "wof:name":"Berghoef",
    "wof:placetype":"venue"
},
  "geometry": {"coordinates":[3.621375,51.498207],"type":"Point"}
}