{
  "type": "Feature",
  "properties": {
    "addr:full":"Lynbaansgr 102 Amsterdam Noord-Holland 1016 KT",
    "addr:housenumber":"102",
    "addr:postcode":"1016 kt",
    "iso:country":"NL",
    "sg:address":"Lynbaansgr 102",
    "sg:city":"Amsterdam",
    "sg:orig_category":"Omroep",
    "sg:phone":"+31 20 528 7654",
    "sg:postcode":"1016 KT",
    "sg:province":"Noord-Holland",
    "sg:website":"http://www.radiotamara.com",
    "wof:name":"Awbc Tamara",
    "wof:placetype":"venue"
},
  "geometry": {"coordinates":[4.877094,52.373432],"type":"Point"}
}