{
  "type": "Feature",
  "properties": {
    "addr:full":"R Wagnerln 19 Voorschoten Zuid-Holland 2253 CA",
    "addr:housenumber":"19",
    "addr:postcode":"2253 ca",
    "iso:country":"NL",
    "sg:address":"R Wagnerln 19",
    "sg:city":"Voorschoten",
    "sg:orig_category":"Adviesbureaus Bedrijfsorganisatie",
    "sg:phone":"+31 71 561 4789",
    "sg:postcode":"2253 CA",
    "sg:province":"Zuid-Holland",
    "wof:name":"Bosch, C",
    "wof:placetype":"venue"
},
  "geometry": {"coordinates":[4.447024,52.133953],"type":"Point"}
}