{
  "type": "Feature",
  "properties": {
    "addr:full":"Op T Hovelke 34 Mheer Limburg 6261 PC",
    "addr:housenumber":"34",
    "addr:postcode":"6261 pc",
    "addr:street":"Op",
    "iso:country":"NL",
    "sg:address":"Op T Hovelke 34",
    "sg:city":"Mheer",
    "sg:classifiers":[
        {
            "category":"Personal",
            "subcategory":"Nail Salon",
            "type":"Services"
        }
    ],
    "sg:phone":"+31 43 457 2339",
    "sg:postcode":"6261 PC",
    "sg:province":"Limburg",
    "sg:tags":[
        "pedicure"
    ],
    "wof:name":"Stevens-Van Proemeren, J M L",
    "wof:placetype":"venue"
},
  "geometry": {"coordinates":[5.792355,50.783844],"type":"Point"}
}