{
  "type": "Feature",
  "properties": {
    "addr:full":"Rynln 79 Heemstede Noord-Holland 2105 XJ",
    "addr:housenumber":"79",
    "addr:postcode":"2105 xj",
    "addr:street":"Rynln",
    "iso:country":"NL",
    "sg:address":"Rynln 79",
    "sg:city":"Heemstede",
    "sg:orig_category":"Voetbalverenigingen",
    "sg:phone":"+31 23 528 5549",
    "sg:postcode":"2105 XJ",
    "sg:province":"Noord-Holland",
    "wof:name":"Hfc Heemstede",
    "wof:placetype":"venue"
},
  "geometry": {"coordinates":[4.621248,52.345287],"type":"Point"}
}