{
  "type": "Feature",
  "properties": {
    "iso:country":"NL",
    "sg:address":"Bultsweg 136",
    "sg:city":"Enschede",
    "sg:orig_category":"Fotostudio'S And Fotografen",
    "sg:phone":"+31 53 461 5173",
    "sg:postcode":"7532 XJ",
    "sg:province":"Overijssel",
    "wof:name":"Reinier Van Willigen",
    "wof:placetype":"venue"
},
  "geometry": {"coordinates":[6.967488,52.22068],"type":"Point"}
}