{
  "type": "Feature",
  "properties": {
    "addr:full":"Herbenusstr 121B Maastricht Limburg 6211 RC",
    "addr:housenumber":"121b",
    "addr:postcode":"6211 rc",
    "iso:country":"NL",
    "sg:address":"Herbenusstr 121B",
    "sg:city":"Maastricht",
    "sg:classifiers":[
        {
            "category":"Retail",
            "subcategory":"Auto Repair",
            "type":"Services"
        }
    ],
    "sg:phone":"+31 43 321 2913",
    "sg:postcode":"6211 RC",
    "sg:province":"Limburg",
    "sg:tags":[
        "garage"
    ],
    "wof:name":"Hafo Vof",
    "wof:placetype":"venue"
},
  "geometry": {"coordinates":[5.6795,50.849915],"type":"Point"}
}