{
  "type": "Feature",
  "properties": {
    "addr:full":"Willem De Merodestraat 64 Hengelo Ov Overijssel 7552 WZ",
    "addr:housenumber":"64",
    "addr:postcode":"7552 wz",
    "addr:street":"Willem De Merodestraat;Ov",
    "iso:country":"NL",
    "sg:address":"Willem De Merodestraat 64",
    "sg:city":"Hengelo Ov",
    "sg:orig_category":"Baby- And Kinderkleding",
    "sg:phone":"+31 74 243 0439",
    "sg:postcode":"7552 WZ",
    "sg:province":"Overijssel",
    "wof:name":"Reinders Mode Bv",
    "wof:placetype":"venue"
},
  "geometry": {"coordinates":[6.821811,52.262691],"type":"Point"}
}