{
  "type": "Feature",
  "properties": {
    "addr:full":"Hullenbergweg 357 Amsterdam Zuidoost Noord-Holland 1101 CP",
    "addr:housenumber":"357",
    "addr:postcode":"zuidoost;1101 cp",
    "addr:street":"Hullenbergweg",
    "iso:country":"NL",
    "sg:address":"Hullenbergweg 357",
    "sg:city":"Amsterdam Zuidoost",
    "sg:orig_category":"Public Relationbureaus",
    "sg:phone":"+31 20 609 0329",
    "sg:postcode":"1101 CP",
    "sg:province":"Noord-Holland",
    "wof:name":"Alexander K.F. Viazemsky Public Relations Bv",
    "wof:placetype":"venue"
},
  "geometry": {"coordinates":[4.951278,52.3041],"type":"Point"}
}