{
  "type": "Feature",
  "properties": {
    "addr:full":"Verl Herewg 113A Groningen Groningen 9721 AJ",
    "addr:housenumber":"113a",
    "addr:postcode":"9721 aj",
    "iso:country":"NL",
    "sg:address":"Verl Herewg 113A",
    "sg:city":"Groningen",
    "sg:orig_category":"Beeldende Kunstenaars",
    "sg:phone":"+31 50 527 0659",
    "sg:postcode":"9721 AJ",
    "sg:province":"Groningen",
    "wof:name":"Worst, Jan",
    "wof:placetype":"venue"
},
  "geometry": {"coordinates":[6.580603,53.19685],"type":"Point"}
}