{
  "type": "Feature",
  "properties": {
    "addr:full":"Schoolstr 7 Zaltbommel Gelderland 5301 NV",
    "addr:housenumber":"7",
    "addr:postcode":"5301 nv",
    "addr:street":"Schoolstr;Gelderland",
    "iso:country":"NL",
    "sg:address":"Schoolstr 7",
    "sg:city":"Zaltbommel",
    "sg:orig_category":"Schilders",
    "sg:phone":"+31 418 512 128",
    "sg:postcode":"5301 NV",
    "sg:province":"Gelderland",
    "wof:name":"Burnet, A",
    "wof:placetype":"venue"
},
  "geometry": {"coordinates":[5.24833,51.80275],"type":"Point"}
}