{
  "type": "Feature",
  "properties": {
    "addr:full":"Siriusstraat 43 Groningen Groningen 9742 KV",
    "addr:housenumber":"43",
    "addr:postcode":"9742 kv",
    "addr:street":"Siriusstraat",
    "iso:country":"NL",
    "sg:address":"Siriusstraat 43",
    "sg:city":"Groningen",
    "sg:orig_category":"Bloemen And Planten",
    "sg:phone":"+31 50 571 5855",
    "sg:postcode":"9742 KV",
    "sg:province":"Groningen",
    "wof:name":"Firma N J Boot & Zoon",
    "wof:placetype":"venue"
},
  "geometry": {"coordinates":[6.537002,53.229328],"type":"Point"}
}