{
  "type": "Feature",
  "properties": {
    "iso:country":"NL",
    "sg:address":"Morellenln 29",
    "sg:city":"Apeldoorn",
    "sg:orig_category":"Honden- En Kattentrimsalons",
    "sg:phone":"+31 55 366 7314",
    "sg:postcode":"7322 JS",
    "sg:province":"Gelderland",
    "sg:website":"http://www.trim-bianca.nl",
    "wof:name":"Bianca",
    "wof:placetype":"venue"
},
  "geometry": {"coordinates":[5.982565,52.216309],"type":"Point"}
}