{
  "type": "Feature",
  "properties": {
    "addr:full":"Terpstr 25 Wieringerwerf Noord-Holland 1771 AC",
    "addr:housenumber":"25",
    "addr:postcode":"1771 ac",
    "addr:street":"Terpstr",
    "iso:country":"NL",
    "sg:address":"Terpstr 25",
    "sg:city":"Wieringerwerf",
    "sg:classifiers":[
        {
            "category":"Food & Beverages",
            "subcategory":"Bakery",
            "type":"Retail Goods"
        }
    ],
    "sg:phone":"+31 227 601 202",
    "sg:postcode":"1771 AC",
    "sg:province":"Noord-Holland",
    "sg:tags":[
        "brood",
        "en",
        "banket"
    ],
    "wof:name":"Buwalda",
    "wof:placetype":"venue"
},
  "geometry": {"coordinates":[5.022956,52.852467],"type":"Point"}
}