{
  "type": "Feature",
  "properties": {
    "addr:full":"Katwykerbroek 13 Katwyk Zh South Holland 2223 XN",
    "addr:housenumber":"13;zh",
    "addr:postcode":"2223 xn",
    "addr:street":"Katwykerbroek",
    "iso:country":"NL",
    "sg:address":"Katwykerbroek 13",
    "sg:city":"Katwyk Zh",
    "sg:classifiers":[
        {
            "category":"Food & Beverages",
            "subcategory":"Fruits & Vegetables",
            "type":"Retail Goods"
        }
    ],
    "sg:phone":"+31 71 401 4497",
    "sg:postcode":"2223 XN",
    "sg:province":"South Holland",
    "sg:tags":[
        "en",
        "groenten"
    ],
    "wof:name":"Delft Bv, Leen Van",
    "wof:placetype":"venue"
},
  "geometry": {"coordinates":[4.41584,52.18483],"type":"Point"}
}