{
  "type": "Feature",
  "properties": {
    "addr:full":"Frederik Hendriklaan 273 'S Gravenhage South Holland 2582 CD",
    "addr:housenumber":"273 '",
    "addr:postcode":"2582 cd",
    "addr:street":"Frederik Hendriklaan",
    "iso:country":"NL",
    "sg:address":"Frederik Hendriklaan 273",
    "sg:city":"'S Gravenhage",
    "sg:classifiers":[
        {
            "category":"Shopping",
            "subcategory":"Clothing, Apparel, & Fashions",
            "type":"Retail Goods"
        }
    ],
    "sg:phone":"+31 70 350 5691",
    "sg:postcode":"2582 CD",
    "sg:province":"South Holland",
    "sg:tags":[
        "ondergoed",
        "lingerie"
    ],
    "wof:name":"Livera Laarhoven",
    "wof:placetype":"venue"
},
  "geometry": {"coordinates":[4.274591,52.089565],"type":"Point"}
}