{
  "type": "Feature",
  "properties": {
    "addr:full":"Weilustln 179 Breda Noord-Brabant 4817 TD",
    "addr:housenumber":"179",
    "addr:postcode":"4817 td",
    "iso:country":"NL",
    "sg:address":"Weilustln 179",
    "sg:city":"Breda",
    "sg:orig_category":"Beeldende Kunstenaars",
    "sg:phone":"+31 76 587 8757",
    "sg:postcode":"4817 TD",
    "sg:province":"Noord-Brabant",
    "wof:name":"Houtkamp, B",
    "wof:placetype":"venue"
},
  "geometry": {"coordinates":[4.812888,51.584934],"type":"Point"}
}