{
  "type": "Feature",
  "properties": {
    "iso:country":"NL",
    "sg:address":"A V Ostadeln 31",
    "sg:city":"Veenendaal",
    "sg:orig_category":"Zonnebank- En Solariumcentra",
    "sg:phone":"+31 318 523 076",
    "sg:postcode":"3904 TJ",
    "sg:province":"Utrecht",
    "wof:name":"Fanny",
    "wof:placetype":"venue"
},
  "geometry": {"coordinates":[5.55418,52.024902],"type":"Point"}
}