{
  "type": "Feature",
  "properties": {
    "iso:country":"NL",
    "sg:address":"Kerkstraat 19",
    "sg:city":"Roggel",
    "sg:orig_category":"Verlichting And Huishoudartikelen",
    "sg:phone":"+31 475 491 426",
    "sg:postcode":"6088 EG",
    "sg:province":"Limburg",
    "wof:name":"T Harlekijntje",
    "wof:placetype":"venue"
},
  "geometry": {"coordinates":[5.920109,51.26318],"type":"Point"}
}