{
  "type": "Feature",
  "properties": {
    "addr:full":"Hoofdweg 54 Amsterdam Noord-Holland 1058 BD",
    "addr:housenumber":"54",
    "addr:postcode":"1058 bd",
    "addr:street":"Hoofdweg",
    "iso:country":"NL",
    "sg:address":"Hoofdweg 54",
    "sg:city":"Amsterdam",
    "sg:orig_category":"Diverse Opleidingen And Onderwijs",
    "sg:phone":"+31 20 489 0054",
    "sg:postcode":"1058 BD",
    "sg:province":"Noord-Holland",
    "wof:name":"Ergoselect",
    "wof:placetype":"venue"
},
  "geometry": {"coordinates":[4.853556,52.360874],"type":"Point"}
}