{
  "type": "Feature",
  "properties": {
    "addr:full":"Marktpln 15 Broek Op Langedyk Noord-Holland 1721 CK",
    "addr:housenumber":"15",
    "addr:postcode":"1721 ck",
    "addr:street":"Marktpln;Op Langedyk",
    "iso:country":"NL",
    "sg:address":"Marktpln 15",
    "sg:city":"Broek Op Langedyk",
    "sg:orig_category":"Fotozaken",
    "sg:phone":"+31 226 317 259",
    "sg:postcode":"1721 CK",
    "sg:province":"Noord-Holland",
    "wof:name":"Flandria",
    "wof:placetype":"venue"
},
  "geometry": {"coordinates":[4.804239,52.678864],"type":"Point"}
}