{
  "type": "Feature",
  "properties": {
    "iso:country":"NL",
    "sg:address":"Walstr 17",
    "sg:city":"Yzendyke",
    "sg:orig_category":"Drukkerijen",
    "sg:phone":"+31 117 301 524",
    "sg:postcode":"4515 AJ",
    "sg:province":"Zeeland",
    "wof:name":"Elhape Bv",
    "wof:placetype":"venue"
},
  "geometry": {"coordinates":[3.617659,51.321983],"type":"Point"}
}