{
  "type": "Feature",
  "properties": {
    "iso:country":"NL",
    "sg:address":"Pergolesilaan 6",
    "sg:city":"Bergen Op Zoom",
    "sg:orig_category":"Farmaceutische Producten Gh",
    "sg:phone":"+31 164 290 000",
    "sg:postcode":"4614 VV",
    "sg:province":"North Brabant",
    "wof:name":"Meyvis En Co Bv",
    "wof:placetype":"venue"
},
  "geometry": {"coordinates":[4.298883,51.507156],"type":"Point"}
}