{
  "type": "Feature",
  "properties": {
    "addr:full":"De Rosmolen 123 Westervoort Gelderland 6932 NC",
    "addr:housenumber":"123;6932",
    "addr:street":"De Rosmolen;Gelderland",
    "iso:country":"NL",
    "sg:address":"De Rosmolen 123",
    "sg:city":"Westervoort",
    "sg:orig_category":"Voetverzorging",
    "sg:phone":"+31 26 311 4551",
    "sg:postcode":"6932 NC",
    "sg:province":"Gelderland",
    "wof:name":"Molenaar-Geubbels, J",
    "wof:placetype":"venue"
},
  "geometry": {"coordinates":[5.978062,51.943977],"type":"Point"}
}