{
  "type": "Feature",
  "properties": {
    "iso:country":"NL",
    "sg:address":"Berkenstraat 59",
    "sg:city":"Haarlem",
    "sg:orig_category":"Boekhouders",
    "sg:phone":"+31 23 526 0707",
    "sg:postcode":"2023 SX",
    "sg:province":"Noord-Holland",
    "wof:name":"Budget- En Begeleidingsbureau Kreule",
    "wof:placetype":"venue"
},
  "geometry": {"coordinates":[4.638476,52.401123],"type":"Point"}
}