{
  "type": "Feature",
  "properties": {
    "addr:full":"Cobbingstraat 16 Ootmarsum Overijssel 7631 JC",
    "addr:housenumber":"16",
    "addr:postcode":"7631 jc",
    "addr:street":"Cobbingstraat",
    "iso:country":"NL",
    "sg:address":"Cobbingstraat 16",
    "sg:city":"Ootmarsum",
    "sg:orig_category":"Fietshandelaren",
    "sg:phone":"+31 541 292 770",
    "sg:postcode":"7631 JC",
    "sg:province":"Overijssel",
    "wof:name":"Busscher Tweewielers",
    "wof:placetype":"venue"
},
  "geometry": {"coordinates":[6.909179,52.405449],"type":"Point"}
}