{
  "type": "Feature",
  "properties": {
    "addr:full":"Crayenesterln 47 Haarlem Noord-Holland 2012 TJ",
    "addr:housenumber":"47",
    "addr:postcode":"2012 tj",
    "addr:street":"Crayenesterln",
    "iso:country":"NL",
    "sg:address":"Crayenesterln 47",
    "sg:city":"Haarlem",
    "sg:orig_category":"Belastingconsulenten/ Belastingadviseurs",
    "sg:phone":"+31 23 528 7118",
    "sg:postcode":"2012 TJ",
    "sg:province":"Noord-Holland",
    "wof:name":"Janssen Aa/Fb, S H J",
    "wof:placetype":"venue"
},
  "geometry": {"coordinates":[4.631333,52.361336],"type":"Point"}
}