{
  "type": "Feature",
  "properties": {
    "addr:full":"Pastoor Bluemersplein 5 Silvolde Gelderland 7064 BK",
    "addr:housenumber":"5",
    "addr:postcode":"7064 bk",
    "addr:street":"Pastoor Bluemersplein;Gelderland",
    "iso:country":"NL",
    "sg:address":"Pastoor Bluemersplein 5",
    "sg:city":"Silvolde",
    "sg:classifiers":[
        {
            "category":"Education",
            "subcategory":"Preschool",
            "type":"Public Place"
        }
    ],
    "sg:phone":"+31 315 324 236",
    "sg:postcode":"7064 BK",
    "sg:province":"Gelderland",
    "sg:tags":[
        "kleuteronderwijs",
        "basis-"
    ],
    "wof:name":"Katholieke Basisschool De Plakkenberg",
    "wof:placetype":"venue"
},
  "geometry": {"coordinates":[6.383498,51.908909],"type":"Point"}
}