{
  "type": "Feature",
  "properties": {
    "addr:full":"Zuidermeent 6 Hilversum Noord-Holland 1218 GW",
    "addr:housenumber":"6",
    "addr:postcode":"1218 gw",
    "addr:street":"Zuidermeent",
    "iso:country":"NL",
    "sg:address":"Zuidermeent 6",
    "sg:city":"Hilversum",
    "sg:orig_category":"Cafetaria'S",
    "sg:phone":"+31 35 691 3162",
    "sg:postcode":"1218 GW",
    "sg:province":"Noord-Holland",
    "wof:name":"Meent, De",
    "wof:placetype":"venue"
},
  "geometry": {"coordinates":[5.1408948898,52.2664031982],"type":"Point"}
}