{
  "type": "Feature",
  "properties": {
    "iso:country":"NL",
    "sg:address":"J V Riebeekstr 391",
    "sg:city":"Den Haag",
    "sg:orig_category":"Fotojournalisten Freelance",
    "sg:phone":"+31 70 385 5497",
    "sg:postcode":"2595 TW",
    "sg:province":"Zuid-Holland",
    "wof:name":"Eijden, R Van",
    "wof:placetype":"venue"
},
  "geometry": {"coordinates":[4.317415,52.083992],"type":"Point"}
}