{
  "type": "Feature",
  "properties": {
    "addr:full":"Westdam 3K Woerden Utrecht 3441 GA",
    "addr:housenumber":"3k",
    "addr:postcode":"3441 ga",
    "addr:street":"Westdam",
    "iso:country":"NL",
    "sg:address":"Westdam 3K",
    "sg:city":"Woerden",
    "sg:orig_category":"Adviesbureaus Bedrijfsorganisatie",
    "sg:phone":"+31 348 435 959",
    "sg:postcode":"3441 GA",
    "sg:province":"Utrecht",
    "wof:name":"Typothese",
    "wof:placetype":"venue"
},
  "geometry": {"coordinates":[4.88106,52.087826],"type":"Point"}
}