{
  "type": "Feature",
  "properties": {
    "addr:full":"Spinel 19 'S Gravenzande Zuid-Holland 2691 TM",
    "addr:housenumber":"19",
    "addr:postcode":"2691 tm",
    "addr:street":"Spinel;' S",
    "iso:country":"NL",
    "sg:address":"Spinel 19",
    "sg:city":"'S Gravenzande",
    "sg:orig_category":"Kinderopvang Behalve Thuis",
    "sg:phone":"+31 174 420 250",
    "sg:postcode":"2691 TM",
    "sg:province":"Zuid-Holland",
    "wof:name":"Peuterspeelzaal Ukkenhonk",
    "wof:placetype":"venue"
},
  "geometry": {"coordinates":[4.168616,51.995178],"type":"Point"}
}