{
  "type": "Feature",
  "properties": {
    "addr:full":"Postbus 10274 S Gravenhage South Holland 2501 HG",
    "addr:housenumber":"10274",
    "addr:postcode":"2501 hg",
    "addr:street":"Postbus;S Gravenhage",
    "iso:country":"NL",
    "sg:address":"Postbus 10274",
    "sg:city":"S Gravenhage",
    "sg:orig_category":"Organisatiebureaus",
    "sg:phone":"+31 70 384 1199",
    "sg:postcode":"2501 HG",
    "sg:province":"South Holland",
    "wof:name":"Protocolbureau Bv, Het",
    "wof:placetype":"venue"
},
  "geometry": {"coordinates":[4.3136100769,52.0783195496],"type":"Point"}
}