{
  "type": "Feature",
  "properties": {
    "addr:full":"Aalsterweg 24 Eindhoven Noord-Brabant 5615 CG",
    "addr:housenumber":"24",
    "addr:postcode":"5615 cg",
    "addr:street":"Aalsterweg",
    "iso:country":"NL",
    "sg:address":"Aalsterweg 24",
    "sg:city":"Eindhoven",
    "sg:orig_category":"Makelaars In Onroerend Goed",
    "sg:phone":"+31 40 212 0164",
    "sg:postcode":"5615 CG",
    "sg:province":"Noord-Brabant",
    "wof:name":"Ed Willems Makelaardij",
    "wof:placetype":"venue"
},
  "geometry": {"coordinates":[5.486462,51.427872],"type":"Point"}
}