{
  "type": "Feature",
  "properties": {
    "addr:full":"Westzijde 39 Zaandam Noord-Holland 1506 EB",
    "addr:housenumber":"39",
    "addr:postcode":"1506 eb",
    "addr:street":"Westzijde",
    "iso:country":"NL",
    "sg:address":"Westzijde 39",
    "sg:city":"Zaandam",
    "sg:orig_category":"Organisaties And Verenigingen",
    "sg:phone":"+31 75 616 0599",
    "sg:postcode":"1506 EB",
    "sg:province":"Noord-Holland",
    "wof:name":"Kunstcentrum Zaanstad",
    "wof:placetype":"venue"
},
  "geometry": {"coordinates":[4.8215742111,52.4422569275],"type":"Point"}
}