{
  "type": "Feature",
  "properties": {
    "addr:full":"Vasteland 6 Rotterdam South Holland 3011 BK",
    "addr:housenumber":"6",
    "addr:postcode":"3011 bk",
    "addr:street":"Vasteland",
    "iso:country":"NL",
    "sg:address":"Vasteland 6",
    "sg:city":"Rotterdam",
    "sg:orig_category":"Olie - Exploratie",
    "sg:phone":"+31 10 400 0888",
    "sg:postcode":"3011 BK",
    "sg:province":"South Holland",
    "wof:name":"Oil Shipping Bv",
    "wof:placetype":"venue"
},
  "geometry": {"coordinates":[4.481297,51.912163],"type":"Point"}
}