{
  "type": "Feature",
  "properties": {
    "addr:full":"Schoolstr 25 Lent Gelderland 6663 CP",
    "addr:housenumber":"25",
    "addr:postcode":"6663 cp",
    "addr:street":"Schoolstr;Gelderland",
    "iso:country":"NL",
    "sg:address":"Schoolstr 25",
    "sg:city":"Lent",
    "sg:orig_category":"Artsen - Huisartsen",
    "sg:phone":"+31 24 322 1029",
    "sg:postcode":"6663 CP",
    "sg:province":"Gelderland",
    "wof:name":"Lent, Praktijk",
    "wof:placetype":"venue"
},
  "geometry": {"coordinates":[-77.241432,38.151344],"type":"Point"}
}