{
  "type": "Feature",
  "properties": {
    "addr:full":"Stationsstraat 51 Veenendaal Utrecht 3905 JH",
    "addr:housenumber":"51",
    "addr:postcode":"3905 jh",
    "addr:street":"Stationsstraat",
    "iso:country":"NL",
    "sg:address":"Stationsstraat 51",
    "sg:city":"Veenendaal",
    "sg:orig_category":"Begrafenisondernemers",
    "sg:phone":"+31 318 542 655",
    "sg:postcode":"3905 JH",
    "sg:province":"Utrecht",
    "wof:name":"Monuta Verzorging Nv",
    "wof:placetype":"venue"
},
  "geometry": {"coordinates":[5.565774,52.037437],"type":"Point"}
}