{
  "type": "Feature",
  "properties": {
    "addr:full":"Albert Plesmanweg 199 Rotterdam Zuid-Holland 3088 GC",
    "addr:housenumber":"199",
    "addr:postcode":"3088 gc",
    "addr:street":"Albert Plesmanweg",
    "iso:country":"NL",
    "sg:address":"Albert Plesmanweg 199",
    "sg:city":"Rotterdam",
    "sg:orig_category":"Autoverhuur",
    "sg:phone":"+31 10 429 7633",
    "sg:postcode":"3088 GC",
    "sg:province":"Zuid-Holland",
    "wof:name":"Tip Trailer Rental Bv",
    "wof:placetype":"venue"
},
  "geometry": {"coordinates":[4.432569,51.872257],"type":"Point"}
}