{
  "type": "Feature",
  "properties": {
    "addr:full":"De Beeklaan 25 Halsteren North Brabant 4661 EP",
    "addr:housenumber":"25",
    "addr:postcode":"4661 ep",
    "addr:street":"De Beeklaan",
    "iso:country":"NL",
    "sg:address":"De Beeklaan 25",
    "sg:city":"Halsteren",
    "sg:orig_category":"Psychotherapeuten",
    "sg:phone":"+31 164 687 983",
    "sg:postcode":"4661 EP",
    "sg:province":"North Brabant",
    "wof:name":"Pasveer, C",
    "wof:placetype":"venue"
},
  "geometry": {"coordinates":[4.272186,51.531445],"type":"Point"}
}