{
  "type": "Feature",
  "properties": {
    "addr:full":"Meander 30 Surhuisterveen Groningen 9231 DB",
    "addr:housenumber":"30",
    "addr:postcode":"9231 db",
    "addr:street":"Meander",
    "iso:country":"NL",
    "sg:address":"Meander 30",
    "sg:city":"Surhuisterveen",
    "sg:orig_category":"Verenigingen En Stichtingen",
    "sg:phone":"+31 512 360 691",
    "sg:postcode":"9231 DB",
    "sg:province":"Groningen",
    "wof:name":"Bca, Sticht",
    "wof:placetype":"venue"
},
  "geometry": {"coordinates":[6.184462,53.180859],"type":"Point"}
}