{
  "type": "Feature",
  "properties": {
    "addr:full":"Noordsngl 3 Rotterdam Zuid-Holland 3035 EG",
    "addr:housenumber":"3",
    "addr:postcode":"3035 eg",
    "addr:street":"Noordsngl",
    "iso:country":"NL",
    "sg:address":"Noordsngl 3",
    "sg:city":"Rotterdam",
    "sg:orig_category":"Fietsen En Bromfietsen",
    "sg:phone":"+31 10 466 2916",
    "sg:postcode":"3035 EG",
    "sg:province":"Zuid-Holland",
    "wof:name":"Bikers' Best",
    "wof:placetype":"venue"
},
  "geometry": {"coordinates":[4.48048,51.932461],"type":"Point"}
}