{
  "type": "Feature",
  "properties": {
    "addr:full":"De Brauwweg 80 Schiedam Zuid-Holland 3125 AE",
    "addr:housenumber":"80",
    "addr:postcode":"3125 ae",
    "addr:street":"De Brauwweg",
    "iso:country":"NL",
    "sg:address":"De Brauwweg 80",
    "sg:city":"Schiedam",
    "sg:orig_category":"Olie- And Gaswinning",
    "sg:phone":"+31 10 488 8911",
    "sg:postcode":"3125 AE",
    "sg:province":"Zuid-Holland",
    "wof:name":"Nederlandse Aardolie Maatschappij Bv",
    "wof:placetype":"venue"
},
  "geometry": {"coordinates":[4.408847,51.929073],"type":"Point"}
}