{
  "type": "Feature",
  "properties": {
    "iso:country":"NL",
    "sg:address":"Achter De Kerk 10",
    "sg:city":"Heerenveen",
    "sg:orig_category":"Kappers",
    "sg:phone":"+31 513 622 193",
    "sg:postcode":"8441 ET",
    "sg:province":"Friesland",
    "wof:name":"Jong, Haarmode De",
    "wof:placetype":"venue"
},
  "geometry": {"coordinates":[5.9214577675,52.9604988098],"type":"Point"}
}