{
  "type": "Feature",
  "properties": {
    "addr:full":"Mantelmeeuwstraat 3 Alkmaar North Holland 1826 GS",
    "addr:housenumber":"3",
    "addr:postcode":"1826 gs",
    "addr:street":"Mantelmeeuwstraat",
    "iso:country":"NL",
    "sg:address":"Mantelmeeuwstraat 3",
    "sg:city":"Alkmaar",
    "sg:orig_category":"Boekhouders",
    "sg:phone":"+31 72 561 1752",
    "sg:postcode":"1826 GS",
    "sg:province":"North Holland",
    "wof:name":"Adviesburo Busman",
    "wof:placetype":"venue"
},
  "geometry": {"coordinates":[4.761041,52.660053],"type":"Point"}
}