{
  "type": "Feature",
  "properties": {
    "addr:full":"Stadionstr 3B Breda Noord-Brabant 4815 NC",
    "addr:housenumber":"3b",
    "addr:postcode":"4815 nc",
    "addr:street":"Stadionstr",
    "iso:country":"NL",
    "sg:address":"Stadionstr 3B",
    "sg:city":"Breda",
    "sg:orig_category":"Werving En Selectie",
    "sg:phone":"+31 76 564 9536",
    "sg:postcode":"4815 NC",
    "sg:province":"Noord-Brabant",
    "wof:name":"Pas, Van Der",
    "wof:placetype":"venue"
},
  "geometry": {"coordinates":[4.7490367889,51.5950164795],"type":"Point"}
}