{
  "type": "Feature",
  "properties": {
    "addr:full":"Dr Nolensln 120 Sittard Limburg 6136 GV",
    "addr:housenumber":"120",
    "addr:postcode":"6136 gv",
    "addr:street":"Sittard Limburg",
    "iso:country":"NL",
    "sg:address":"Dr Nolensln 120",
    "sg:city":"Sittard",
    "sg:orig_category":"Verf En Lak - Fabrieken En Groothandel",
    "sg:phone":"+31 46 451 1351",
    "sg:postcode":"6136 GV",
    "sg:province":"Limburg",
    "wof:name":"Felix",
    "wof:placetype":"venue"
},
  "geometry": {"coordinates":[5.869686,51.019051],"type":"Point"}
}