{
  "type": "Feature",
  "properties": {
    "iso:country":"NL",
    "sg:address":"Vd Pekstr 72",
    "sg:city":"Utrecht",
    "sg:orig_category":"Fotojournalisten Freelance",
    "sg:phone":"+31 30 242 1256",
    "sg:postcode":"3555 AW",
    "sg:province":"Utrecht",
    "wof:name":"Stoops, Fotopersbureau Jeroen",
    "wof:placetype":"venue"
},
  "geometry": {"coordinates":[5.078888,52.116665],"type":"Point"}
}