{
  "type": "Feature",
  "properties": {
    "iso:country":"NL",
    "sg:address":"Hulk 3",
    "sg:city":"Franeker",
    "sg:orig_category":"Verzekeringen",
    "sg:phone":"+31 517 398 120",
    "sg:postcode":"8802 NJ",
    "sg:province":"Friesland",
    "wof:name":"L & R Verzekeringen",
    "wof:placetype":"venue"
},
  "geometry": {"coordinates":[5.541868,53.196838],"type":"Point"}
}