{
  "type": "Feature",
  "properties": {
    "addr:full":"Hoofdstraat 87 Kaatsheuvel North Brabant 5171 DK",
    "addr:housenumber":"87",
    "addr:postcode":"5171 dk",
    "addr:street":"Hoofdstraat",
    "iso:country":"NL",
    "sg:address":"Hoofdstraat 87",
    "sg:city":"Kaatsheuvel",
    "sg:orig_category":"Opticiens",
    "sg:phone":"+31 416 272 360",
    "sg:postcode":"5171 DK",
    "sg:province":"North Brabant",
    "wof:name":"Musters Optiek",
    "wof:placetype":"venue"
},
  "geometry": {"coordinates":[5.0323209763,51.6616249084],"type":"Point"}
}