{
  "type": "Feature",
  "properties": {
    "addr:full":"Burgemeester Colijnstr 22 Boskoop Zuid-Holland 2771 GD",
    "addr:housenumber":"22",
    "addr:postcode":"2771 gd",
    "addr:street":"Burgemeester Colijnstr",
    "iso:country":"NL",
    "sg:address":"Burgemeester Colijnstr 22",
    "sg:city":"Boskoop",
    "sg:orig_category":"Verzekeringen",
    "sg:phone":"+31 172 429 429",
    "sg:postcode":"2771 GD",
    "sg:province":"Zuid-Holland",
    "wof:name":"Rabobank",
    "wof:placetype":"venue"
},
  "geometry": {"coordinates":[4.659311,52.075279],"type":"Point"}
}