{
  "type": "Feature",
  "properties": {
    "addr:full":"Gibsonstraat 7 Steenbergen Nb Noord-Brabant 4651 SW",
    "addr:housenumber":"7",
    "addr:postcode":"4651 sw",
    "addr:street":"Gibsonstraat",
    "iso:country":"NL",
    "sg:address":"Gibsonstraat 7",
    "sg:city":"Steenbergen Nb",
    "sg:orig_category":"Wegen And Sportterreinen",
    "sg:phone":"+31 167 564 771",
    "sg:postcode":"4651 SW",
    "sg:province":"Noord-Brabant",
    "wof:name":"Jaartsveld Wegenbouw Bv",
    "wof:placetype":"venue"
},
  "geometry": {"coordinates":[4.305753231,51.590839386],"type":"Point"}
}