{
  "type": "Feature",
  "properties": {
    "iso:country":"NL",
    "sg:address":"Lemierserberg 27",
    "sg:city":"Vaals",
    "sg:orig_category":"Zonne-Energie",
    "sg:phone":"+31 43 308 0152",
    "sg:postcode":"6291 NM",
    "sg:province":"Limburg",
    "wof:name":"Ez Aupperle",
    "wof:placetype":"venue"
},
  "geometry": {"coordinates":[6.002722,50.780258],"type":"Point"}
}