{
  "type": "Feature",
  "properties": {
    "addr:full":"Herculesstr 51 Alkmaar North Holland 1812 PD",
    "addr:housenumber":"51",
    "addr:postcode":"1812 pd",
    "addr:street":"Herculesstr",
    "iso:country":"NL",
    "sg:address":"Herculesstr 51",
    "sg:city":"Alkmaar",
    "sg:orig_category":"Oud Metaal",
    "sg:phone":"+31 72 540 2926",
    "sg:postcode":"1812 PD",
    "sg:province":"North Holland",
    "wof:name":"Overdie Bv",
    "wof:placetype":"venue"
},
  "geometry": {"coordinates":[4.7670111656,52.6208190918],"type":"Point"}
}