{
  "type": "Feature",
  "properties": {
    "addr:full":"J Vd Doemstr 75 Utrecht Utrecht 3515 XP",
    "addr:housenumber":"75",
    "addr:postcode":"3515 xp",
    "iso:country":"NL",
    "sg:address":"J Vd Doemstr 75",
    "sg:city":"Utrecht",
    "sg:orig_category":"Fotoreportages",
    "sg:phone":"+31 30 271 9348",
    "sg:postcode":"3515 XP",
    "sg:province":"Utrecht",
    "wof:name":"Foto Utrecht",
    "wof:placetype":"venue"
},
  "geometry": {"coordinates":[5.122931,52.104485],"type":"Point"}
}