{
  "type": "Feature",
  "properties": {
    "iso:country":"NL",
    "sg:address":"Nyenrode 9",
    "sg:city":"Landsmeer",
    "sg:orig_category":"Adviesbureaus Bedrijfsorganisatie",
    "sg:phone":"+31 20 482 5834",
    "sg:postcode":"1121 HN",
    "sg:province":"Noord-Holland",
    "wof:name":"Koperdraat Advies",
    "wof:placetype":"venue"
},
  "geometry": {"coordinates":[4.91374,52.429974],"type":"Point"}
}