{
  "type": "Feature",
  "properties": {
    "iso:country":"NL",
    "sg:address":"Fideliolaan 10",
    "sg:city":"Oldenzaal",
    "sg:orig_category":"Verhuur Audiovisuele Apparatuur",
    "sg:phone":"+31 541 514 844",
    "sg:postcode":"7577 JD",
    "sg:province":"NL.08",
    "wof:name":"A. Schippers",
    "wof:placetype":"venue"
},
  "geometry": {"coordinates":[6.921059,52.320023],"type":"Point"}
}