{
  "type": "Feature",
  "properties": {
    "addr:full":"Fluiterswg 64 Wenum Wiesel Gelderland 7345 BJ",
    "addr:housenumber":"64",
    "addr:postcode":"7345 bj",
    "addr:street":"Fluiterswg",
    "iso:country":"NL",
    "sg:address":"Fluiterswg 64",
    "sg:city":"Wenum Wiesel",
    "sg:orig_category":"Kunststof Ramen",
    "sg:phone":"+31 55 506 4452",
    "sg:postcode":"7345 BJ",
    "sg:province":"Gelderland",
    "wof:name":"Klevering Kunststof Kozijnen Bv",
    "wof:placetype":"venue"
},
  "geometry": {"coordinates":[5.96548,52.244122],"type":"Point"}
}