{
  "type": "Feature",
  "properties": {
    "addr:full":"Looln 37 Apeldoorn Gelderland 7314 AB",
    "addr:housenumber":"37",
    "addr:postcode":"7314 ab",
    "addr:street":"Looln;Gelderland",
    "iso:country":"NL",
    "sg:address":"Looln 37",
    "sg:city":"Apeldoorn",
    "sg:orig_category":"Verenigingen En Stichtingen",
    "sg:phone":"+31 55 579 5503",
    "sg:postcode":"7314 AB",
    "sg:province":"Gelderland",
    "wof:name":"Euromicro",
    "wof:placetype":"venue"
},
  "geometry": {"coordinates":[5.96566,52.216518],"type":"Point"}
}