{
  "type": "Feature",
  "properties": {
    "addr:full":"M Ten Hovestr 9 Delft Zuid-Holland 2613 VX",
    "addr:housenumber":"9",
    "addr:postcode":"2613 vx",
    "addr:street":"M Ten Hovestr",
    "iso:country":"NL",
    "sg:address":"M Ten Hovestr 9",
    "sg:city":"Delft",
    "sg:orig_category":"Scholen Voor Basisonderwijs",
    "sg:phone":"+31 15 213 4615",
    "sg:postcode":"2613 VX",
    "sg:province":"Zuid-Holland",
    "sg:website":"http://www.dsdelft.nl/tildegabriel",
    "wof:name":"Gabri?lschool, De",
    "wof:placetype":"venue"
},
  "geometry": {"coordinates":[4.345418,52.007607],"type":"Point"}
}