{
  "type": "Feature",
  "properties": {
    "addr:full":"Postbus 2094 S Hertogenbosch 5202 CB",
    "addr:housenumber":"2094",
    "addr:postcode":"5202 cb",
    "addr:street":"Postbus;S Hertogenbosch",
    "iso:country":"NL",
    "sg:address":"Postbus 2094",
    "sg:city":"S Hertogenbosch",
    "sg:orig_category":"Administratie- En Boekhoudkantoren",
    "sg:phone":"+31 73 599 7017",
    "sg:postcode":"5202 CB",
    "wof:name":"Baak",
    "wof:placetype":"venue"
},
  "geometry": {"coordinates":[5.30421,51.68922],"type":"Point"}
}