{
  "type": "Feature",
  "properties": {
    "addr:full":"Jacob Catslaan 25 Woerden Utrecht 3445 XD",
    "addr:housenumber":"25",
    "addr:postcode":"3445 xd",
    "addr:street":"Jacob Catslaan",
    "iso:country":"NL",
    "sg:address":"Jacob Catslaan 25",
    "sg:city":"Woerden",
    "sg:orig_category":"Kantoor- En Bedrijfsmeubelen - Fabrieken En Groothandel",
    "sg:phone":"+31 348 420 904",
    "sg:postcode":"3445 XD",
    "sg:province":"Utrecht",
    "wof:name":"Flex Table",
    "wof:placetype":"venue"
},
  "geometry": {"coordinates":[4.8985590935,52.0918960571],"type":"Point"}
}