{
  "type": "Feature",
  "properties": {
    "addr:full":"Hocquart 8 Franeker Friesland 8801 KV",
    "addr:housenumber":"8",
    "addr:postcode":"8801 kv",
    "addr:street":"Hocquart",
    "iso:country":"NL",
    "sg:address":"Hocquart 8",
    "sg:city":"Franeker",
    "sg:orig_category":"Verzekeringen - Verzekeringskantoren",
    "sg:phone":"+31 517 390 022",
    "sg:postcode":"8801 KV",
    "sg:province":"Friesland",
    "wof:name":"Rodenhuis Assurantieservice",
    "wof:placetype":"venue"
},
  "geometry": {"coordinates":[5.540232,53.188347],"type":"Point"}
}