{
  "type": "Feature",
  "properties": {
    "addr:full":"Overtoom 140 Amsterdam Noord-Holland 1054 HN",
    "addr:housenumber":"140",
    "addr:postcode":"1054 hn",
    "addr:street":"Overtoom",
    "iso:country":"NL",
    "sg:address":"Overtoom 140",
    "sg:city":"Amsterdam",
    "sg:orig_category":"Gespecialiseerde Voeding",
    "sg:phone":"+31 20 685 1053",
    "sg:postcode":"1054 HN",
    "sg:province":"Noord-Holland",
    "wof:name":"Peperwortel",
    "wof:placetype":"venue"
},
  "geometry": {"coordinates":[4.873709,52.36253],"type":"Point"}
}