{
  "type": "Feature",
  "properties": {
    "addr:full":"Kralingse Plasln 98 Rotterdam South Holland 3061 DG",
    "addr:housenumber":"98",
    "addr:postcode":"3061 dg",
    "iso:country":"NL",
    "sg:address":"Kralingse Plasln 98",
    "sg:city":"Rotterdam",
    "sg:orig_category":"Verzekeringen - Verzekeringskantoren",
    "sg:phone":"+31 10 452 1100",
    "sg:postcode":"3061 DG",
    "sg:province":"South Holland",
    "sg:website":"http://www.braacx.nl",
    "wof:name":"Braacx Assuranti\u00ebn",
    "wof:placetype":"venue"
},
  "geometry": {"coordinates":[4.507567,51.932213],"type":"Point"}
}