{
  "type": "Feature",
  "properties": {
    "addr:full":"Hoogewaard 170 Koudekerk A/D Rijn South Holland 2396 AP",
    "addr:housenumber":"170;a / d",
    "addr:postcode":"2396 ap",
    "addr:street":"Hoogewaard;Rijn South",
    "iso:country":"NL",
    "sg:address":"Hoogewaard 170",
    "sg:city":"Koudekerk A/D Rijn",
    "sg:orig_category":"Bloemen And Planten",
    "sg:phone":"+31 71 341 2387",
    "sg:postcode":"2396 AP",
    "sg:province":"South Holland",
    "wof:name":"Firma M. Van Vliet En Zn",
    "wof:placetype":"venue"
},
  "geometry": {"coordinates":[4.614391,52.130241],"type":"Point"}
}