{
  "type": "Feature",
  "properties": {
    "iso:country":"NL",
    "sg:address":"Westwaarts 6",
    "sg:city":"Zoetermeer",
    "sg:orig_category":"Werving And Selectie Van Tijdelijk Personeel And Uitzendkantoren",
    "sg:phone":"+31 79 352 1100",
    "sg:postcode":"2711 AC",
    "sg:province":"South Holland",
    "wof:name":"Olympia Uitzendburo",
    "wof:placetype":"venue"
},
  "geometry": {"coordinates":[4.4875588417,52.0612716675],"type":"Point"}
}