{
  "type": "Feature",
  "properties": {
    "iso:country":"NL",
    "sg:address":"Schorpioen 20",
    "sg:city":"Lemmer",
    "sg:orig_category":"Zonnebank- En Solariumcentra",
    "sg:phone":"+31 514 562 606",
    "sg:postcode":"8531 NT",
    "sg:province":"Friesland",
    "wof:name":"Solaire",
    "wof:placetype":"venue"
},
  "geometry": {"coordinates":[5.701436,52.851295],"type":"Point"}
}