{
  "type": "Feature",
  "properties": {
    "addr:full":"Minervum 7487 Breda Noord-Brabant 4817 ZP",
    "addr:housenumber":"7487",
    "addr:postcode":"breda;4817 zp",
    "addr:street":"Minervum",
    "iso:country":"NL",
    "sg:address":"Minervum 7487",
    "sg:city":"Breda",
    "sg:orig_category":"Letters - Fabrieken En Groothandel",
    "sg:phone":"+31 76 571 1811",
    "sg:postcode":"4817 ZP",
    "sg:province":"Noord-Brabant",
    "sg:website":"http://www.fransluijkenreclame.nl",
    "wof:name":"Frans Luijken Reclame Bv",
    "wof:placetype":"venue"
},
  "geometry": {"coordinates":[4.833143,51.58997],"type":"Point"}
}