{
  "type": "Feature",
  "properties": {
    "addr:full":"Ohmstraat 121 Amsterdam Noord-Holland 1098 ST",
    "addr:housenumber":"121;1098",
    "addr:postcode":"st",
    "addr:street":"Ohmstraat",
    "iso:country":"NL",
    "sg:address":"Ohmstraat 121",
    "sg:city":"Amsterdam",
    "sg:orig_category":"Fotoreportages",
    "sg:phone":"+31 6 18472117",
    "sg:postcode":"1098 ST",
    "sg:province":"Noord-Holland",
    "sg:website":"http://www.twinq-fotografie.nl",
    "wof:name":"Scheerder, Margot",
    "wof:placetype":"venue"
},
  "geometry": {"coordinates":[4.94384,52.351391],"type":"Point"}
}