{
  "type": "Feature",
  "properties": {
    "addr:full":"Bastenakenstraat 121 Amsterdam North Holland 1066 JC",
    "addr:housenumber":"121",
    "addr:postcode":"1066 jc",
    "addr:street":"Bastenakenstraat",
    "iso:country":"NL",
    "sg:address":"Bastenakenstraat 121",
    "sg:city":"Amsterdam",
    "sg:orig_category":"Verzekeringen",
    "sg:phone":"+31 20 617 5896",
    "sg:postcode":"1066 JC",
    "sg:province":"North Holland",
    "wof:name":"Stijger Assurantien",
    "wof:placetype":"venue"
},
  "geometry": {"coordinates":[4.819734,52.3442],"type":"Point"}
}