{
  "type": "Feature",
  "properties": {
    "addr:full":"Schellingwouderdk 240 Amsterdam North Holland 1023 NL",
    "addr:housenumber":"240",
    "addr:postcode":"1023 nl",
    "iso:country":"NL",
    "sg:address":"Schellingwouderdk 240",
    "sg:city":"Amsterdam",
    "sg:orig_category":"Artsen - Huisartsen",
    "sg:phone":"+31 20 490 4231",
    "sg:postcode":"1023 NL",
    "sg:province":"North Holland",
    "wof:name":"Duyn & E Simons, M C",
    "wof:placetype":"venue"
},
  "geometry": {"coordinates":[4.962834,52.383846],"type":"Point"}
}