{
  "type": "Feature",
  "properties": {
    "iso:country":"NL",
    "sg:address":"Dampad 1",
    "sg:city":"Zaandam",
    "sg:classifiers":[
        {
            "category":"Fast Food",
            "type":"Food & Drink"
        }
    ],
    "sg:phone":"+31 75 612 5733",
    "sg:postcode":"1506 BK",
    "sg:province":"Noord-Holland",
    "sg:tags":[
        "afhaal",
        "restaurant"
    ],
    "wof:name":"Eethuis Derman",
    "wof:placetype":"venue"
},
  "geometry": {"coordinates":[4.82369,52.439377],"type":"Point"}
}