{
  "type": "Feature",
  "properties": {
    "addr:full":"Laanstraat 16A Baarn Utrecht 3743 BE",
    "addr:housenumber":"16a",
    "addr:postcode":"3743",
    "addr:street":"Laanstraat",
    "iso:country":"NL",
    "sg:address":"Laanstraat 16A",
    "sg:city":"Baarn",
    "sg:orig_category":"Bloemen En Planten",
    "sg:phone":"+31 35 543 0488",
    "sg:postcode":"3743 BE",
    "sg:province":"Utrecht",
    "wof:name":"Gooische Bloembinderij, De",
    "wof:placetype":"venue"
},
  "geometry": {"coordinates":[5.290395,52.211575],"type":"Point"}
}