{
  "type": "Feature",
  "properties": {
    "addr:full":"Hilvarenbeekse Wg 60 Tilburg Noord-Brabant 5022 GC",
    "addr:housenumber":"60",
    "addr:postcode":"5022 gc",
    "addr:street":"Wg",
    "iso:country":"NL",
    "sg:address":"Hilvarenbeekse Wg 60",
    "sg:city":"Tilburg",
    "sg:orig_category":"Ziekenhuizen, Sanatoria, Verpleeghuizen",
    "sg:phone":"+31 13 539 1313",
    "sg:postcode":"5022 GC",
    "sg:province":"Noord-Brabant",
    "wof:name":"St Elisabeth Ziekenhuis Tilburg",
    "wof:placetype":"venue"
},
  "geometry": {"coordinates":[5.103292,51.53896],"type":"Point"}
}