{
  "type": "Feature",
  "properties": {
    "addr:full":"Maasln 7 Arnhem Gelderland 6826 AC",
    "addr:housenumber":"7",
    "addr:postcode":"6826 ac",
    "addr:street":"Maasln",
    "iso:country":"NL",
    "sg:address":"Maasln 7",
    "sg:city":"Arnhem",
    "sg:orig_category":"Verenigingen En Stichtingen",
    "sg:phone":"+31 26 443 8098",
    "sg:postcode":"6826 AC",
    "sg:province":"Gelderland",
    "wof:name":"Turks Islam Ver",
    "wof:placetype":"venue"
},
  "geometry": {"coordinates":[5.94473,51.98209],"type":"Point"}
}