{
  "type": "Feature",
  "properties": {
    "addr:full":"Voorhaven 27/B Rotterdam Zuid-Holland 3025 HC",
    "addr:housenumber":"27 / b",
    "addr:postcode":"3025 hc",
    "addr:street":"Voorhaven",
    "iso:country":"NL",
    "sg:address":"Voorhaven 27/B",
    "sg:city":"Rotterdam",
    "sg:orig_category":"Grafisch Ontwerpers",
    "sg:phone":"+31 10 476 8521",
    "sg:postcode":"3025 HC",
    "sg:province":"Zuid-Holland",
    "wof:name":"Zee Rotterdam",
    "wof:placetype":"venue"
},
  "geometry": {"coordinates":[4.44788,51.90773],"type":"Point"}
}