{
  "type": "Feature",
  "properties": {
    "iso:country":"NL",
    "sg:address":"Duivenkamp 759",
    "sg:city":"Maarssen",
    "sg:orig_category":"Kantoor- En Secretariaatsservice",
    "sg:phone":"+31 346 565 608",
    "sg:postcode":"3607 VE",
    "sg:province":"Utrecht",
    "wof:name":"Secrenorm",
    "wof:placetype":"venue"
},
  "geometry": {"coordinates":[5.0238919258,52.1322937012],"type":"Point"}
}