{
  "type": "Feature",
  "properties": {
    "addr:full":"Duivenkamp 759 Maarssen Utrecht 3607 VE",
    "addr:housenumber":"759",
    "addr:postcode":"3607",
    "addr:street":"Duivenkamp",
    "iso:country":"NL",
    "sg:address":"Duivenkamp 759",
    "sg:city":"Maarssen",
    "sg:orig_category":"Kantoor- En Secretariaatsservice",
    "sg:phone":"+31 346 565 608",
    "sg:postcode":"3607 VE",
    "sg:province":"Utrecht",
    "wof:name":"Secrenorm",
    "wof:placetype":"venue"
},
  "geometry": {"coordinates":[5.0238919258,52.1322937012],"type":"Point"}
}