{
  "type": "Feature",
  "properties": {
    "iso:country":"NL",
    "sg:address":"Provincialewg 27",
    "sg:city":"Kornhorn",
    "sg:classifiers":[
        {
            "category":"Retail",
            "subcategory":"Auto Repair",
            "type":"Services"
        }
    ],
    "sg:phone":"+31 594 659 092",
    "sg:postcode":"9864 PA",
    "sg:province":"Groningen",
    "sg:tags":[
        "garage"
    ],
    "wof:name":"Kruizinga",
    "wof:placetype":"venue"
},
  "geometry": {"coordinates":[6.238663,53.180859],"type":"Point"}
}