{
  "type": "Feature",
  "properties": {
    "addr:full":"Goossenwg 4 Hellendoorn Overijssel 7447 SK",
    "addr:housenumber":"4",
    "addr:street":"Goossenwg;7447",
    "iso:country":"NL",
    "sg:address":"Goossenwg 4",
    "sg:city":"Hellendoorn",
    "sg:orig_category":"Hoefsmederijen",
    "sg:phone":"+31 548 681 624",
    "sg:postcode":"7447 SK",
    "sg:province":"Overijssel",
    "wof:name":"Bakhuis",
    "wof:placetype":"venue"
},
  "geometry": {"coordinates":[6.504612,52.417992],"type":"Point"}
}