{
  "type": "Feature",
  "properties": {
    "iso:country":"NL",
    "sg:address":"Handellaan 10",
    "sg:city":"'S Gravenhage",
    "sg:orig_category":"Boekhouders",
    "sg:phone":"+31 70 368 4405",
    "sg:postcode":"2555 WD",
    "sg:province":"Zuid-Holland",
    "wof:name":"Nel Vd Harst",
    "wof:placetype":"venue"
},
  "geometry": {"coordinates":[4.240895,52.065235],"type":"Point"}
}