{
  "type": "Feature",
  "properties": {
    "addr:full":"Eindhovensewg 3A Berkel Enschot Noord-Brabant 5056 RP",
    "addr:housenumber":"3a",
    "addr:postcode":"5056 rp",
    "addr:street":"Eindhovensewg",
    "iso:country":"NL",
    "sg:address":"Eindhovensewg 3A",
    "sg:city":"Berkel Enschot",
    "sg:orig_category":"Grondwerken",
    "sg:phone":"+31 13 544 0042",
    "sg:postcode":"5056 RP",
    "sg:province":"Noord-Brabant",
    "wof:name":"Brand, Van Den",
    "wof:placetype":"venue"
},
  "geometry": {"coordinates":[5.129068,51.54451],"type":"Point"}
}