{
  "type": "Feature",
  "properties": {
    "addr:full":"Karveel 4919 Lelystad Flevoland 8242 VS",
    "addr:postcode":"4919;8242",
    "addr:street":"Karveel;Flevoland",
    "iso:country":"NL",
    "sg:address":"Karveel 4919",
    "sg:city":"Lelystad",
    "sg:orig_category":"Scholen Voor Basisonderwijs",
    "sg:phone":"+31 320 222 178",
    "sg:postcode":"8242 VS",
    "sg:province":"Flevoland",
    "sg:website":"http://www.boeier.nl",
    "wof:name":"Boeier, De",
    "wof:placetype":"venue"
},
  "geometry": {"coordinates":[5.458682,52.523151],"type":"Point"}
}