{
  "type": "Feature",
  "properties": {
    "addr:full":"Vivaldistraat 206 Capelle A/D Ijssel South Holland 2901 HC",
    "addr:housenumber":"206;a / d",
    "addr:postcode":"2901 hc",
    "addr:street":"Vivaldistraat;Ijssel South",
    "iso:country":"NL",
    "sg:address":"Vivaldistraat 206",
    "sg:city":"Capelle A/D Ijssel",
    "sg:orig_category":"Verhuur Catering-, Feest- En Evenementbenodigdheden",
    "sg:phone":"+31 10 202 0234",
    "sg:postcode":"2901 HC",
    "sg:province":"South Holland",
    "wof:name":"Mega Therm Nederland",
    "wof:placetype":"venue"
},
  "geometry": {"coordinates":[4.563963,51.917423],"type":"Point"}
}