{
  "type": "Feature",
  "properties": {
    "iso:country":"NL",
    "sg:address":"Ln C Den Hoorn 102",
    "sg:city":"Groningen",
    "sg:classifiers":[
        {
            "category":"Professional",
            "subcategory":"Accounting & Tax Preparation",
            "type":"Services"
        }
    ],
    "sg:phone":"+31 50 520 4520",
    "sg:postcode":"9728 JR",
    "sg:province":"Groningen",
    "sg:tags":[
        "accountant",
        "en",
        "-kantoren",
        "register-"
    ],
    "sg:website":"http://www.deloitte.nl/",
    "wof:name":"Deloitte & Touche",
    "wof:placetype":"venue"
},
  "geometry": {"coordinates":[6.552897,53.194233],"type":"Point"}
}