{
  "type": "Feature",
  "properties": {
    "addr:full":"Verl Lodewykstr 15 Groningen Groningen 9724 EK",
    "addr:housenumber":"15",
    "addr:postcode":"9724 ek",
    "iso:country":"NL",
    "sg:address":"Verl Lodewykstr 15",
    "sg:city":"Groningen",
    "sg:orig_category":"Beveiliging",
    "sg:phone":"+31 50 368 6020",
    "sg:postcode":"9724 EK",
    "sg:province":"Groningen",
    "sg:website":"http://www.spn.nl",
    "wof:name":"Spn",
    "wof:placetype":"venue"
},
  "geometry": {"coordinates":[6.578387,53.20863],"type":"Point"}
}