{
  "type": "Feature",
  "properties": {
    "addr:full":"De Tinneweide 151 Veenendaal Utrecht 3901 KJ",
    "addr:housenumber":"151",
    "addr:postcode":"3901 kj",
    "addr:street":"De Tinneweide",
    "iso:country":"NL",
    "sg:address":"De Tinneweide 151",
    "sg:city":"Veenendaal",
    "sg:orig_category":"Kappers",
    "sg:phone":"+31 318 513 170",
    "sg:postcode":"3901 KJ",
    "sg:province":"Utrecht",
    "wof:name":"Kapsalon Silvester Bv",
    "wof:placetype":"venue"
},
  "geometry": {"coordinates":[5.563499,52.019615],"type":"Point"}
}