{
  "type": "Feature",
  "properties": {
    "iso:country":"NL",
    "sg:address":"De Tinneweide 151",
    "sg:city":"Veenendaal",
    "sg:orig_category":"Kappers",
    "sg:phone":"+31 318 513 170",
    "sg:postcode":"3901 KJ",
    "sg:province":"Utrecht",
    "wof:name":"Kapsalon Silvester Bv",
    "wof:placetype":"venue"
},
  "geometry": {"coordinates":[5.563499,52.019615],"type":"Point"}
}