{
  "type": "Feature",
  "properties": {
    "addr:full":"Verl Willemstr 12 Groningen Groningen 9725 AX",
    "addr:housenumber":"12",
    "addr:postcode":"9725 ax",
    "iso:country":"NL",
    "sg:address":"Verl Willemstr 12",
    "sg:city":"Groningen",
    "sg:orig_category":"Vertaalbureaus",
    "sg:phone":"+31 50 527 7088",
    "sg:postcode":"9725 AX",
    "sg:province":"Groningen",
    "sg:website":"http://www.yellowboxtranslations.com",
    "wof:name":"Yellow Box Translations",
    "wof:placetype":"venue"
},
  "geometry": {"coordinates":[6.578235,53.207981],"type":"Point"}
}