{
  "type": "Feature",
  "properties": {
    "addr:full":"P Vlamingstr 18Hs Amsterdam Noord-Holland 1093 AD",
    "addr:housenumber":"18hs",
    "addr:postcode":"1093 ad",
    "addr:street":"P",
    "iso:country":"NL",
    "sg:address":"P Vlamingstr 18Hs",
    "sg:city":"Amsterdam",
    "sg:orig_category":"Journalisten Freelance",
    "sg:phone":"+31 20 463 6283",
    "sg:postcode":"1093 AD",
    "sg:province":"Noord-Holland",
    "wof:name":"Schepel, Drs Selma",
    "wof:placetype":"venue"
},
  "geometry": {"coordinates":[4.925277,52.364613],"type":"Point"}
}