{
  "type": "Feature",
  "properties": {
    "addr:full":"Rododendronpln 2 Rotterdam South Holland 3053 ES",
    "addr:housenumber":"2",
    "addr:postcode":"3053 es",
    "addr:street":"Rododendronpln",
    "iso:country":"NL",
    "sg:address":"Rododendronpln 2",
    "sg:city":"Rotterdam",
    "sg:orig_category":"Drogisterijen",
    "sg:phone":"+31 10 418 4172",
    "sg:postcode":"3053 ES",
    "sg:province":"South Holland",
    "wof:name":"Da",
    "wof:placetype":"venue"
},
  "geometry": {"coordinates":[4.47238,51.95993],"type":"Point"}
}