{
  "type": "Feature",
  "properties": {
    "addr:full":"Binder 29 Eemnes Utrecht 3755 WP",
    "addr:housenumber":"29",
    "addr:postcode":"3755 wp",
    "addr:street":"Binder",
    "iso:country":"NL",
    "sg:address":"Binder 29",
    "sg:city":"Eemnes",
    "sg:orig_category":"Parketvloeren - Onderhoud En Reparatie",
    "sg:phone":"+31 6 51365444",
    "sg:postcode":"3755 WP",
    "sg:province":"Utrecht",
    "wof:name":"Beli",
    "wof:placetype":"venue"
},
  "geometry": {"coordinates":[5.257901,52.247463],"type":"Point"}
}