{
  "type": "Feature",
  "properties": {
    "addr:full":"Laan D Verenigde Naties 325 Dordrecht Zuid-Holland 3318 LA",
    "addr:housenumber":"325",
    "addr:postcode":"3318 la",
    "addr:street":"Laan D Verenigde Naties",
    "iso:country":"NL",
    "sg:address":"Laan D Verenigde Naties 325",
    "sg:city":"Dordrecht",
    "sg:orig_category":"Technische Studies And Onderzoek",
    "sg:phone":"+31 78 652 2522",
    "sg:postcode":"3318 LA",
    "sg:province":"Zuid-Holland",
    "wof:name":"Jgc Dordtse Engineering Bv",
    "wof:placetype":"venue"
},
  "geometry": {"coordinates":[4.676801,51.795151],"type":"Point"}
}