{
  "type": "Feature",
  "properties": {
    "iso:country":"NL",
    "sg:address":"Ulftseweg 85",
    "sg:city":"Silvolde",
    "sg:orig_category":"Meubelzaken, Woning- And Keukeninrichting",
    "sg:phone":"+31 315 340 189",
    "sg:postcode":"7064 BC",
    "sg:province":"Gelderland",
    "wof:name":"Ebenique Bv",
    "wof:placetype":"venue"
},
  "geometry": {"coordinates":[6.386707,51.904762],"type":"Point"}
}