{
  "type": "Feature",
  "properties": {
    "addr:full":"Jasmyn 19 Rhoon South Holland 3161 CM",
    "addr:housenumber":"19",
    "addr:postcode":"3161 cm",
    "addr:street":"Jasmyn",
    "iso:country":"NL",
    "sg:address":"Jasmyn 19",
    "sg:city":"Rhoon",
    "sg:orig_category":"Organisatiebureaus",
    "sg:phone":"+31 10 501 9019",
    "sg:postcode":"3161 CM",
    "sg:province":"South Holland",
    "wof:name":"Rijnmond Jazz Gala Bv",
    "wof:placetype":"venue"
},
  "geometry": {"coordinates":[4.4293198586,51.8550300598],"type":"Point"}
}