{
  "type": "Feature",
  "properties": {
    "iso:country":"NL",
    "sg:address":"A R Holststr 58",
    "sg:city":"Almere",
    "sg:orig_category":"Scholen Voor Basisonderwijs",
    "sg:phone":"+31 36 540 7387",
    "sg:postcode":"1321 RX",
    "sg:province":"NL.",
    "wof:name":"Omnibus 2, De",
    "wof:placetype":"venue"
},
  "geometry": {"coordinates":[5.18257,52.35714],"type":"Point"}
}