{
  "type": "Feature",
  "properties": {
    "iso:country":"NL",
    "sg:address":"Pluimenmeent 40",
    "sg:city":"Hilversum",
    "sg:orig_category":"Boekhouders",
    "sg:phone":"+31 35 698 0164",
    "sg:postcode":"1218 BL",
    "sg:province":"Noord-Holland",
    "wof:name":"Administratiekantoor Lisman",
    "wof:placetype":"venue"
},
  "geometry": {"coordinates":[5.139364,52.273659],"type":"Point"}
}