{
  "type": "Feature",
  "properties": {
    "addr:full":"In De Cramer 186 Heerlen Limburg 6412 PM",
    "addr:housenumber":"186",
    "addr:postcode":"6412 pm",
    "addr:street":"In De Cramer",
    "iso:country":"NL",
    "sg:address":"In De Cramer 186",
    "sg:city":"Heerlen",
    "sg:orig_category":"Bedden En Matrassen",
    "sg:phone":"+31 45 575 4100",
    "sg:postcode":"6412 PM",
    "sg:province":"Limburg",
    "wof:name":"Oase",
    "wof:placetype":"venue"
},
  "geometry": {"coordinates":[5.940083,50.900558],"type":"Point"}
}