{
  "type": "Feature",
  "properties": {
    "iso:country":"NL",
    "sg:address":"Ericaplein 27",
    "sg:city":"Kloosterzande",
    "sg:orig_category":"Schilderwerk",
    "sg:phone":"+31 114 682 131",
    "sg:postcode":"4587 AB",
    "sg:province":"Zeeland",
    "wof:name":"Goossen Schilderwerken",
    "wof:placetype":"venue"
},
  "geometry": {"coordinates":[4.009963,51.368214],"type":"Point"}
}