{
  "type": "Feature",
  "properties": {
    "addr:full":"Dorpsstr 12A Hellendoorn NL.08 7447 CR",
    "addr:housenumber":"12a;nl.08 7447",
    "addr:postcode":"cr",
    "addr:street":"Dorpsstr",
    "iso:country":"NL",
    "sg:address":"Dorpsstr 12A",
    "sg:city":"Hellendoorn",
    "sg:orig_category":"Kinderkleding",
    "sg:phone":"+31 548 619 746",
    "sg:postcode":"7447 CR",
    "sg:province":"NL.08",
    "wof:name":"Pardoes",
    "wof:placetype":"venue"
},
  "geometry": {"coordinates":[6.449605,52.388241],"type":"Point"}
}