{
  "type": "Feature",
  "properties": {
    "iso:country":"NL",
    "sg:address":"Dorpsstr 12A",
    "sg:city":"Hellendoorn",
    "sg:orig_category":"Kinderkleding",
    "sg:phone":"+31 548 619 746",
    "sg:postcode":"7447 CR",
    "sg:province":"NL.08",
    "wof:name":"Pardoes",
    "wof:placetype":"venue"
},
  "geometry": {"coordinates":[6.449605,52.388241],"type":"Point"}
}