{
  "type": "Feature",
  "properties": {
    "addr:full":"Rontgenln 5 Zoetermeer Zuid-Holland 2719 DX",
    "addr:housenumber":"5",
    "addr:postcode":"2719 dx",
    "addr:street":"Rontgenln",
    "iso:country":"NL",
    "sg:address":"Rontgenln 5",
    "sg:city":"Zoetermeer",
    "sg:orig_category":"Verzekeringen - Verzekeringskantoren",
    "sg:phone":"+31 79 316 0223",
    "sg:postcode":"2719 DX",
    "sg:province":"Zuid-Holland",
    "wof:name":"Stuut",
    "wof:placetype":"venue"
},
  "geometry": {"coordinates":[4.471654,52.044521],"type":"Point"}
}