{
  "type": "Feature",
  "properties": {
    "addr:full":"Fresiastr 12 Naaldwyk Zuid-Holland 2671 KS",
    "addr:housenumber":"12",
    "addr:postcode":"2671 ks",
    "addr:street":"Fresiastr",
    "iso:country":"NL",
    "sg:address":"Fresiastr 12",
    "sg:city":"Naaldwyk",
    "sg:orig_category":"Begrafenisverzorging",
    "sg:phone":"+31 174 629 946",
    "sg:postcode":"2671 KS",
    "sg:province":"Zuid-Holland",
    "wof:name":"Eijk, Van Der",
    "wof:placetype":"venue"
},
  "geometry": {"coordinates":[4.21267,51.990021],"type":"Point"}
}