{
  "type": "Feature",
  "properties": {
    "addr:full":"De Veluwse Heuvel 50 Nunspeet Gelderland 8071 GP",
    "addr:housenumber":"50",
    "addr:postcode":"8071 gp",
    "addr:street":"De Veluwse Heuvel;Gelderland",
    "iso:country":"NL",
    "sg:address":"De Veluwse Heuvel 50",
    "sg:city":"Nunspeet",
    "sg:orig_category":"Verenigingen En Stichtingen",
    "sg:phone":"+31 341 252 020",
    "sg:postcode":"8071 GP",
    "sg:province":"Gelderland",
    "wof:name":"Welzijn Ouderen Nunspeet, Sticht",
    "wof:placetype":"venue"
},
  "geometry": {"coordinates":[5.775204,52.374928],"type":"Point"}
}