{
  "type": "Feature",
  "properties": {
    "addr:full":"Plantynwg 2A Culemborg Gelderland 4104 BB",
    "addr:housenumber":"2a",
    "addr:postcode":"4104 bb",
    "addr:street":"Plantynwg;Gelderland",
    "iso:country":"NL",
    "sg:address":"Plantynwg 2A",
    "sg:city":"Culemborg",
    "sg:orig_category":"Verpakkingen En Verpakkingsmaterialen",
    "sg:phone":"+31 345 516 564",
    "sg:postcode":"4104 BB",
    "sg:province":"Gelderland",
    "wof:name":"Tromp Verpakking Partners Bv",
    "wof:placetype":"venue"
},
  "geometry": {"coordinates":[5.205341,51.941525],"type":"Point"}
}