{
  "type": "Feature",
  "properties": {
    "iso:country":"NL",
    "sg:address":"Fluitpolderpln 1A",
    "sg:city":"Leidschendam",
    "sg:orig_category":"Verenigingen En Stichtingen",
    "sg:phone":"+31 70 327 0239",
    "sg:postcode":"2262 ED",
    "sg:province":"Zuid-Holland",
    "wof:name":"Jeudwerk Noord",
    "wof:placetype":"venue"
},
  "geometry": {"coordinates":[4.393152,52.093689],"type":"Point"}
}