{
  "type": "Feature",
  "properties": {
    "addr:full":"Waldeck Pyrmontkade 1 'S Gravenhage Zuid-Holland 2518 RP",
    "addr:housenumber":"1 '",
    "addr:postcode":"2518 rp",
    "addr:street":"Waldeck Pyrmontkade",
    "iso:country":"NL",
    "sg:address":"Waldeck Pyrmontkade 1",
    "sg:city":"'S Gravenhage",
    "sg:classifiers":[
        {
            "category":"Retail",
            "subcategory":"Photofinishing",
            "type":"Services"
        }
    ],
    "sg:phone":"+31 70 365 4914",
    "sg:postcode":"2518 RP",
    "sg:province":"Zuid-Holland",
    "sg:tags":[
        "foto",
        "film"
    ],
    "wof:name":"Foto Elshout",
    "wof:placetype":"venue"
},
  "geometry": {"coordinates":[4.294639,52.076984],"type":"Point"}
}