{
  "type": "Feature",
  "properties": {
    "addr:full":"Den Brabanderhove 25 Zoetermeer South Holland 2717 WH",
    "addr:housenumber":"25",
    "addr:postcode":"2717 wh",
    "addr:street":"Den Brabanderhove",
    "iso:country":"NL",
    "sg:address":"Den Brabanderhove 25",
    "sg:city":"Zoetermeer",
    "sg:orig_category":"Administratie- En Boekhoudkantoren",
    "sg:phone":"+31 79 320 0092",
    "sg:postcode":"2717 WH",
    "sg:province":"South Holland",
    "wof:name":"Hummel, J",
    "wof:placetype":"venue"
},
  "geometry": {"coordinates":[4.477906,52.064407],"type":"Point"}
}