{
  "type": "Feature",
  "properties": {
    "iso:country":"NL",
    "sg:address":"Teeuwskamp 2A",
    "sg:city":"Alphen Gld",
    "sg:orig_category":"Onderhoudswerken",
    "sg:phone":"+31 487 562 253",
    "sg:postcode":"6626 CB",
    "sg:province":"Gelderland",
    "wof:name":"Kuijpers",
    "wof:placetype":"venue"
},
  "geometry": {"coordinates":[5.468605,51.823059],"type":"Point"}
}