{
  "type": "Feature",
  "properties": {
    "addr:full":"Ln D Zeven Linden 171 Delfgauw Zuid-Holland 2645 HV",
    "addr:housenumber":"171",
    "addr:postcode":"2645 hv",
    "addr:street":"Ln D Zeven Linden",
    "iso:country":"NL",
    "sg:address":"Ln D Zeven Linden 171",
    "sg:city":"Delfgauw",
    "sg:orig_category":"Logopedisten",
    "sg:phone":"+31 15 262 8865",
    "sg:postcode":"2645 HV",
    "sg:province":"Zuid-Holland",
    "wof:name":"Zeegers-Janssen, J C M",
    "wof:placetype":"venue"
},
  "geometry": {"coordinates":[4.391176,52.004574],"type":"Point"}
}