{
  "type": "Feature",
  "properties": {
    "addr:full":"Valkkooglaan 83 Heerhugowaard Noord-Holland 1705 AN",
    "addr:housenumber":"83",
    "addr:postcode":"1705 an",
    "addr:street":"Valkkooglaan",
    "iso:country":"NL",
    "sg:address":"Valkkooglaan 83",
    "sg:city":"Heerhugowaard",
    "sg:orig_category":"Boekhouders",
    "sg:phone":"+31 72 572 1851",
    "sg:postcode":"1705 AN",
    "sg:province":"Noord-Holland",
    "wof:name":"A.H. Telleman",
    "wof:placetype":"venue"
},
  "geometry": {"coordinates":[4.840059,52.6502],"type":"Point"}
}