{
  "type": "Feature",
  "properties": {
    "addr:full":"P Krugerstr 8A Arnhem Gelderland 6814 AS",
    "addr:housenumber":"8a",
    "addr:postcode":"6814 as",
    "iso:country":"NL",
    "sg:address":"P Krugerstr 8A",
    "sg:city":"Arnhem",
    "sg:orig_category":"Scholen Voor Basisonderwijs",
    "sg:phone":"+31 26 353 0830",
    "sg:postcode":"6814 AS",
    "sg:province":"Gelderland",
    "sg:website":"http://www.debasis.org",
    "wof:name":"Basis, De",
    "wof:placetype":"venue"
},
  "geometry": {"coordinates":[5.90795,51.987366],"type":"Point"}
}