{
  "type": "Feature",
  "properties": {
    "addr:full":"O Nassaustr 30 Noordwyk Zh Zuid-Holland 2202 TL",
    "addr:housenumber":"30",
    "addr:postcode":"2202 tl",
    "addr:street":"Noordwyk",
    "iso:country":"NL",
    "sg:address":"O Nassaustr 30",
    "sg:city":"Noordwyk Zh",
    "sg:orig_category":"Vertaalbureaus",
    "sg:phone":"+31 71 364 8997",
    "sg:postcode":"2202 TL",
    "sg:province":"Zuid-Holland",
    "wof:name":"Babylon Talen Service",
    "wof:placetype":"venue"
},
  "geometry": {"coordinates":[4.4477,52.234261],"type":"Point"}
}