{
  "type": "Feature",
  "properties": {
    "addr:full":"Stationsstraat 10 Assen Drenthe 9401 KX",
    "addr:housenumber":"10",
    "addr:postcode":"9401 kx",
    "addr:street":"Stationsstraat",
    "iso:country":"NL",
    "sg:address":"Stationsstraat 10",
    "sg:city":"Assen",
    "sg:orig_category":"Kappers",
    "sg:phone":"+31 592 318 585",
    "sg:postcode":"9401 KX",
    "sg:province":"Drenthe",
    "wof:name":"Kapsalon De Haarspecialisten Ed En Marja",
    "wof:placetype":"venue"
},
  "geometry": {"coordinates":[6.5663890839,52.9932136536],"type":"Point"}
}