{
  "type": "Feature",
  "properties": {
    "iso:country":"NL",
    "sg:address":"Huize D Vliedberg 18",
    "sg:city":"Rilland",
    "sg:orig_category":"Bejaarden - Verzorgingstehuizen",
    "sg:phone":"+31 113 551 487",
    "sg:postcode":"4411 AD",
    "sg:province":"Zeeland",
    "wof:name":"Vliedberg, St Huize De",
    "wof:placetype":"venue"
},
  "geometry": {"coordinates":[4.177888,51.415386],"type":"Point"}
}