{
  "type": "Feature",
  "properties": {
    "addr:full":"P C Hooftstr 85 Amsterdam North Holland 1071 BP",
    "addr:housenumber":"85",
    "addr:postcode":"1071 bp",
    "addr:street":"P C Hooftstr",
    "iso:country":"NL",
    "sg:address":"P C Hooftstr 85",
    "sg:city":"Amsterdam",
    "sg:orig_category":"Opticiens",
    "sg:phone":"+31 20 470 8217",
    "sg:postcode":"1071 BP",
    "sg:province":"North Holland",
    "wof:name":"Bi Occhi",
    "wof:placetype":"venue"
},
  "geometry": {"coordinates":[4.8802452087,52.3599853516],"type":"Point"}
}