{
  "type": "Feature",
  "properties": {
    "addr:full":"Randwg 21 Vaals Limburg 6291 DC",
    "addr:housenumber":"21",
    "addr:postcode":"6291",
    "addr:street":"Randwg",
    "iso:country":"NL",
    "sg:address":"Randwg 21",
    "sg:city":"Vaals",
    "sg:orig_category":"Golfbanen",
    "sg:phone":"+31 43 306 8345",
    "sg:postcode":"6291 DC",
    "sg:province":"Limburg",
    "wof:name":"Hoog Vaals",
    "wof:placetype":"venue"
},
  "geometry": {"coordinates":[6.005564,50.774529],"type":"Point"}
}