{
  "type": "Feature",
  "properties": {
    "addr:full":"Ryksstrwg 63 Hellevoetsluis South Holland 3222 KA",
    "addr:housenumber":"63",
    "addr:postcode":"3222 ka",
    "addr:street":"Ryksstrwg",
    "iso:country":"NL",
    "sg:address":"Ryksstrwg 63",
    "sg:city":"Hellevoetsluis",
    "sg:orig_category":"Autoradio'S",
    "sg:phone":"+31 181 414 625",
    "sg:postcode":"3222 KA",
    "sg:province":"South Holland",
    "wof:name":"Grand Prix",
    "wof:placetype":"venue"
},
  "geometry": {"coordinates":[4.143085,51.855431],"type":"Point"}
}