{
  "type": "Feature",
  "properties": {
    "addr:full":"Buitenkwartier 3 Zwartsluis Overijssel 8064 AB",
    "addr:housenumber":"3",
    "addr:postcode":"8064 ab",
    "addr:street":"Buitenkwartier",
    "iso:country":"NL",
    "sg:address":"Buitenkwartier 3",
    "sg:city":"Zwartsluis",
    "sg:classifiers":[
        {
            "category":"Retail",
            "subcategory":"Photofinishing",
            "type":"Services"
        }
    ],
    "sg:phone":"+31 38 386 6519",
    "sg:postcode":"8064 AB",
    "sg:province":"Overijssel",
    "sg:tags":[
        "foto",
        "film"
    ],
    "wof:name":"Foto-Grammo-Tuinman",
    "wof:placetype":"venue"
},
  "geometry": {"coordinates":[6.068415,52.639862],"type":"Point"}
}