{
  "type": "Feature",
  "properties": {
    "addr:full":"Zandvoortselaan 136 'S Gravenhage Zuid-Holland 2554 EM",
    "addr:housenumber":"136 '",
    "addr:postcode":"2554 em",
    "addr:street":"Zandvoortselaan",
    "iso:country":"NL",
    "sg:address":"Zandvoortselaan 136",
    "sg:city":"'S Gravenhage",
    "sg:orig_category":"Binnenhuisarchitecten",
    "sg:phone":"+31 70 323 2187",
    "sg:postcode":"2554 EM",
    "sg:province":"Zuid-Holland",
    "wof:name":"H. Van Dijk",
    "wof:placetype":"venue"
},
  "geometry": {"coordinates":[4.224049,52.068382],"type":"Point"}
}