{
  "type": "Feature",
  "properties": {
    "iso:country":"NL",
    "sg:address":"Zandvoortselaan 136",
    "sg:city":"'S Gravenhage",
    "sg:orig_category":"Binnenhuisarchitecten",
    "sg:phone":"+31 70 323 2187",
    "sg:postcode":"2554 EM",
    "sg:province":"Zuid-Holland",
    "wof:name":"H. Van Dijk",
    "wof:placetype":"venue"
},
  "geometry": {"coordinates":[4.224049,52.068382],"type":"Point"}
}