{
  "type": "Feature",
  "properties": {
    "addr:full":"Wenslauerstr 1 Amsterdam Noord-Holland 1053 AV",
    "addr:housenumber":"1",
    "addr:postcode":"1053 av",
    "addr:street":"Wenslauerstr",
    "iso:country":"NL",
    "sg:address":"Wenslauerstr 1",
    "sg:city":"Amsterdam",
    "sg:orig_category":"Beeldende Kunstenaars",
    "sg:phone":"+31 20 684 8217",
    "sg:postcode":"1053 AV",
    "sg:province":"Noord-Holland",
    "wof:name":"Benn Schr\u00f7Er",
    "wof:placetype":"venue"
},
  "geometry": {"coordinates":[4.866226,52.367592],"type":"Point"}
}