{
  "type": "Feature",
  "properties": {
    "addr:full":"Willem Ii Straat 1 Budel Noord-Brabant 6021 EA",
    "addr:housenumber":"1",
    "addr:postcode":"6021 ea",
    "addr:street":"Willem Ii Straat",
    "iso:country":"NL",
    "sg:address":"Willem Ii Straat 1",
    "sg:city":"Budel",
    "sg:orig_category":"Loodgieterswerk, Verwarming And Sanitaire Installaties",
    "sg:phone":"+31 495 491 267",
    "sg:postcode":"6021 EA",
    "sg:province":"Noord-Brabant",
    "wof:name":"F.G. Kosman",
    "wof:placetype":"venue"
},
  "geometry": {"coordinates":[5.576252,51.276093],"type":"Point"}
}