{
  "type": "Feature",
  "properties": {
    "iso:country":"NL",
    "sg:address":"Ginnekenstraat 76",
    "sg:city":"Breda",
    "sg:orig_category":"Huishoudapparatuur, Televisies And Radio'S",
    "sg:phone":"+31 76 521 1952",
    "sg:postcode":"4811 JJ",
    "sg:province":"North Brabant",
    "wof:name":"Handyman",
    "wof:placetype":"venue"
},
  "geometry": {"coordinates":[4.777009,51.58419],"type":"Point"}
}