{
  "type": "Feature",
  "properties": {
    "addr:full":"Raadhuisplein 30 Leeuwarden Friesland 8911 HK",
    "addr:housenumber":"30",
    "addr:postcode":"8911 hk",
    "addr:street":"Raadhuisplein",
    "iso:country":"NL",
    "sg:address":"Raadhuisplein 30",
    "sg:city":"Leeuwarden",
    "sg:orig_category":"Makelaars In Onroerend Goed",
    "sg:phone":"+31 58 215 5990",
    "sg:postcode":"8911 HK",
    "sg:province":"Friesland",
    "wof:name":"Hellema Makelaars",
    "wof:placetype":"venue"
},
  "geometry": {"coordinates":[5.795458,53.201801],"type":"Point"}
}