{
  "type": "Feature",
  "properties": {
    "addr:full":"Fazantpad 31 Soest Utrecht 3766 JH",
    "addr:housenumber":"31",
    "addr:postcode":"3766 jh",
    "addr:street":"Fazantpad",
    "iso:country":"NL",
    "sg:address":"Fazantpad 31",
    "sg:city":"Soest",
    "sg:orig_category":"Adviesbureaus",
    "sg:phone":"+31 35 609 0281",
    "sg:postcode":"3766 JH",
    "sg:province":"Utrecht",
    "wof:name":"Gelder",
    "wof:placetype":"venue"
},
  "geometry": {"coordinates":[5.277398,52.166252],"type":"Point"}
}