{
  "type": "Feature",
  "properties": {
    "addr:full":"Austerlitzsewg 5 Doorn Utrecht 3941 WJ",
    "addr:housenumber":"5",
    "addr:postcode":"3941 wj",
    "addr:street":"Austerlitzsewg",
    "iso:country":"NL",
    "sg:address":"Austerlitzsewg 5",
    "sg:city":"Doorn",
    "sg:orig_category":"Administratie- En Boekhoudkantoren",
    "sg:phone":"+31 343 420 521",
    "sg:postcode":"3941 WJ",
    "sg:province":"Utrecht",
    "wof:name":"Breugel Bv, Van",
    "wof:placetype":"venue"
},
  "geometry": {"coordinates":[5.339145,52.043644],"type":"Point"}
}