{
  "type": "Feature",
  "properties": {
    "addr:full":"Weidekervel 87 Duiven England 6922 GB",
    "addr:housenumber":"87",
    "addr:postcode":"6922 gb",
    "addr:street":"Weidekervel;England",
    "iso:country":"NL",
    "sg:address":"Weidekervel 87",
    "sg:city":"Duiven",
    "sg:orig_category":"Kinderopvang Behalve Thuis",
    "sg:phone":"+31 316 280 699",
    "sg:postcode":"6922 GB",
    "sg:province":"England",
    "wof:name":"Stichting Kinderopvang De Kangoeroe",
    "wof:placetype":"venue"
},
  "geometry": {"coordinates":[-2.23218,54.313919],"type":"Point"}
}