{
  "type": "Feature",
  "properties": {
    "addr:full":"Nieuwstr 9 Breda Noord-Brabant 4811 WX",
    "addr:housenumber":"9",
    "addr:postcode":"4811 wx",
    "addr:street":"Nieuwstr",
    "iso:country":"NL",
    "sg:address":"Nieuwstr 9",
    "sg:city":"Breda",
    "sg:orig_category":"Fietsen En Bromfietsen Stalling",
    "sg:phone":"+31 76 522 5498",
    "sg:postcode":"4811 WX",
    "sg:province":"Noord-Brabant",
    "wof:name":"Fietsenstalling",
    "wof:placetype":"venue"
},
  "geometry": {"coordinates":[4.775357,51.586903],"type":"Point"}
}