{
  "type": "Feature",
  "properties": {
    "addr:full":"Driftweg 51 Nunspeet Gelderland 8072 DN",
    "addr:housenumber":"51",
    "addr:postcode":"8072 dn",
    "addr:street":"Driftweg;Gelderland",
    "iso:country":"NL",
    "sg:address":"Driftweg 51",
    "sg:city":"Nunspeet",
    "sg:classifiers":[
        {
            "category":"Fast Food",
            "type":"Food & Drink"
        }
    ],
    "sg:phone":"+31 341 253 912",
    "sg:postcode":"8072 DN",
    "sg:province":"Gelderland",
    "sg:tags":[
        "afhaal",
        "restaurant"
    ],
    "wof:name":"Snackbar De Veluwse Jager",
    "wof:placetype":"venue"
},
  "geometry": {"coordinates":[5.793146,52.383381],"type":"Point"}
}