{
  "type": "Feature",
  "properties": {
    "iso:country":"NL",
    "sg:address":"Meeden 1",
    "sg:city":"Winsum Gn",
    "sg:orig_category":"Ziekenhuizen, Sanatoria, Verpleeghuizen",
    "sg:phone":"+31 595 442 525",
    "sg:postcode":"9951 HZ",
    "sg:province":"Groningen",
    "wof:name":"Twaalf Hoven, De",
    "wof:placetype":"venue"
},
  "geometry": {"coordinates":[6.526365,53.33033],"type":"Point"}
}