{
  "type": "Feature",
  "properties": {
    "iso:country":"NL",
    "sg:address":"Stoutenburg 24",
    "sg:city":"Landsmeer",
    "sg:classifiers":[
        {
            "category":"Professional",
            "subcategory":"Management & Consulting",
            "type":"Services"
        }
    ],
    "sg:phone":"+31 20 482 3685",
    "sg:postcode":"1121 GH",
    "sg:province":"Noord-Holland",
    "sg:tags":[
        "relation",
        "adviesbureaus",
        "public"
    ],
    "wof:name":"Overdiek",
    "wof:placetype":"venue"
},
  "geometry": {"coordinates":[4.920476,52.427982],"type":"Point"}
}