{
  "type": "Feature",
  "properties": {
    "addr:full":"Zwilbroekseweg 4 Winterswijk Meddo Gelderland 7104 BS",
    "addr:housenumber":"4",
    "addr:postcode":"7104 bs",
    "addr:street":"Zwilbroekseweg",
    "iso:country":"NL",
    "sg:address":"Zwilbroekseweg 4",
    "sg:city":"Winterswijk Meddo",
    "sg:orig_category":"Wegen And Sportterreinen",
    "sg:phone":"+31 543 569 328",
    "sg:postcode":"7104 BS",
    "sg:province":"Gelderland",
    "wof:name":"L. Smeenk",
    "wof:placetype":"venue"
},
  "geometry": {"coordinates":[6.6963739395,52.0326004028],"type":"Point"}
}