{
  "type": "Feature",
  "properties": {
    "addr:full":"Jachtln 81 Apeldoorn Gelderland 7313 CS",
    "addr:housenumber":"81",
    "addr:postcode":"7313 cs",
    "addr:street":"Jachtln;Gelderland",
    "iso:country":"NL",
    "sg:address":"Jachtln 81",
    "sg:city":"Apeldoorn",
    "sg:orig_category":"Verzekeringen - Verzekeringskantoren",
    "sg:phone":"+31 55 355 2222",
    "sg:postcode":"7313 CS",
    "sg:province":"Gelderland",
    "wof:name":"Janssen, Paul",
    "wof:placetype":"venue"
},
  "geometry": {"coordinates":[5.96566,52.216518],"type":"Point"}
}