{
  "type": "Feature",
  "properties": {
    "iso:country":"NL",
    "sg:address":"Tuinderij 5",
    "sg:city":"Harmelen",
    "sg:orig_category":"Bedrijfs- And Managementsconsultants",
    "sg:phone":"+31 348 441 504",
    "sg:postcode":"3481 TW",
    "sg:province":"Utrecht",
    "wof:name":"J.L.M. Van Vaalen",
    "wof:placetype":"venue"
},
  "geometry": {"coordinates":[4.960312,52.091827],"type":"Point"}
}