{
  "type": "Feature",
  "properties": {
    "addr:full":"Euterpeln 11 Oss Noord-Brabant 5344 CA",
    "addr:housenumber":"11",
    "addr:postcode":"5344 ca",
    "addr:street":"Euterpeln",
    "iso:country":"NL",
    "sg:address":"Euterpeln 11",
    "sg:city":"Oss",
    "sg:orig_category":"Verhuur",
    "sg:phone":"+31 412 656 231",
    "sg:postcode":"5344 CA",
    "sg:province":"Noord-Brabant",
    "wof:name":"A-Rent Munsters",
    "wof:placetype":"venue"
},
  "geometry": {"coordinates":[-77.235214,38.312599],"type":"Point"}
}