{
  "type": "Feature",
  "properties": {
    "addr:full":"M Louisestr 7 Sneek Friesland 8606 AV",
    "addr:housenumber":"7",
    "addr:postcode":"8606 av",
    "iso:country":"NL",
    "sg:address":"M Louisestr 7",
    "sg:city":"Sneek",
    "sg:orig_category":"Hulpverlening Sociaal",
    "sg:phone":"+31 515 436 040",
    "sg:postcode":"8606 AV",
    "sg:province":"Friesland",
    "sg:website":"http://www.hospicezwf.nl",
    "wof:name":"Hospice Zw Friesland",
    "wof:placetype":"venue"
},
  "geometry": {"coordinates":[5.66816,53.030819],"type":"Point"}
}