{
  "type": "Feature",
  "properties": {
    "addr:full":"Rozengr 97N Amsterdam Noord-Holland 1016 LT",
    "addr:housenumber":"97n",
    "addr:postcode":"1016 lt",
    "addr:street":"Rozengr",
    "iso:country":"NL",
    "sg:address":"Rozengr 97N",
    "sg:city":"Amsterdam",
    "sg:orig_category":"Adviesbureaus Bedrijfsorganisatie",
    "sg:phone":"+31 20 627 5886",
    "sg:postcode":"1016 LT",
    "sg:province":"Noord-Holland",
    "sg:website":"http://www.burer.nl",
    "wof:name":"O-Waza",
    "wof:placetype":"venue"
},
  "geometry": {"coordinates":[4.879752,52.373013],"type":"Point"}
}