{
  "type": "Feature",
  "properties": {
    "iso:country":"NL",
    "sg:address":"Kl Inez Erf 9",
    "sg:city":"Capelle Ad Yssel",
    "sg:orig_category":"Kantoormachines",
    "sg:phone":"+31 10 450 0252",
    "sg:postcode":"2907 ED",
    "sg:province":"Zuid-Holland",
    "wof:name":"Veeken",
    "wof:placetype":"venue"
},
  "geometry": {"coordinates":[4.5845999718,51.9234008789],"type":"Point"}
}