{
  "type": "Feature",
  "properties": {
    "addr:full":"Schathuis 12 Delfzyl Groningen 9932 CB",
    "addr:housenumber":"12",
    "addr:postcode":"9932 cb",
    "addr:street":"Schathuis",
    "iso:country":"NL",
    "sg:address":"Schathuis 12",
    "sg:city":"Delfzyl",
    "sg:orig_category":"Administratie- En Boekhoudkantoren",
    "sg:phone":"+31 596 681 010",
    "sg:postcode":"9932 CB",
    "sg:province":"Groningen",
    "wof:name":"Pallas",
    "wof:placetype":"venue"
},
  "geometry": {"coordinates":[6.891804,53.320004],"type":"Point"}
}