{
  "type": "Feature",
  "properties": {
    "addr:full":"Pasteurweg 93 Schoonhoven South Holland 2871 JM",
    "addr:housenumber":"93",
    "addr:postcode":"2871 jm",
    "addr:street":"Pasteurweg",
    "iso:country":"NL",
    "sg:address":"Pasteurweg 93",
    "sg:city":"Schoonhoven",
    "sg:classifiers":[
        {
            "category":"Education",
            "subcategory":"Preschool",
            "type":"Public Place"
        }
    ],
    "sg:phone":"+31 182 384 789",
    "sg:postcode":"2871 JM",
    "sg:province":"South Holland",
    "sg:tags":[
        "kleuteronderwijs",
        "basis-"
    ],
    "wof:name":"Prot Chr Basisschool De Rank",
    "wof:placetype":"venue"
},
  "geometry": {"coordinates":[4.842899,51.95155],"type":"Point"}
}