{
  "type": "Feature",
  "properties": {
    "addr:full":"Tolweg 18 Markelo Overijssel 7475 BJ",
    "addr:housenumber":"18",
    "addr:postcode":"7475 bj",
    "addr:street":"Tolweg",
    "iso:country":"NL",
    "sg:address":"Tolweg 18",
    "sg:city":"Markelo",
    "sg:orig_category":"Wegen And Sportterreinen",
    "sg:phone":"+31 547 362 772",
    "sg:postcode":"7475 BJ",
    "sg:province":"Overijssel",
    "wof:name":"Tempelman Vof Sierbestrating",
    "wof:placetype":"venue"
},
  "geometry": {"coordinates":[6.4919228554,52.2370147705],"type":"Point"}
}