{
  "type": "Feature",
  "properties": {
    "addr:full":"Schoener 26 Woerden Utrecht 3448 KP",
    "addr:housenumber":"26",
    "addr:postcode":"3448 kp",
    "addr:street":"Schoener",
    "iso:country":"NL",
    "sg:address":"Schoener 26",
    "sg:city":"Woerden",
    "sg:orig_category":"Kinderopvang",
    "sg:phone":"+31 348 434 275",
    "sg:postcode":"3448 KP",
    "sg:province":"Utrecht",
    "wof:name":"Clowntje, Het",
    "wof:placetype":"venue"
},
  "geometry": {"coordinates":[4.854046,52.080936],"type":"Point"}
}