{
  "type": "Feature",
  "properties": {
    "addr:full":"De Lopensaet 50 Dronten Flevoland 8252 KK",
    "addr:housenumber":"50",
    "addr:postcode":"8252 kk",
    "addr:street":"De Lopensaet;Flevoland",
    "iso:country":"NL",
    "sg:address":"De Lopensaet 50",
    "sg:city":"Dronten",
    "sg:orig_category":"Verenigingen En Stichtingen",
    "sg:phone":"+31 321 380 751",
    "sg:postcode":"8252 KK",
    "sg:province":"Flevoland",
    "wof:name":"Bond Van Ouderen, Kath",
    "wof:placetype":"venue"
},
  "geometry": {"coordinates":[5.69117,52.517662],"type":"Point"}
}