{
  "type": "Feature",
  "properties": {
    "iso:country":"NL",
    "sg:address":"Beekstraat 12",
    "sg:city":"Elburg",
    "sg:orig_category":"Warenhuizen",
    "sg:phone":"+31 525 681 320",
    "sg:postcode":"8081 EC",
    "sg:province":"Gelderland",
    "wof:name":"Hema",
    "wof:placetype":"venue"
},
  "geometry": {"coordinates":[5.8341369629,52.4490509033],"type":"Point"}
}