{
  "type": "Feature",
  "properties": {
    "addr:full":"Rotterd Airp Pln 20 Rotterdam Zuid-Holland 3045 AP",
    "addr:housenumber":"20",
    "addr:postcode":"3045 ap",
    "addr:street":"Pln",
    "iso:country":"NL",
    "sg:address":"Rotterd Airp Pln 20",
    "sg:city":"Rotterdam",
    "sg:orig_category":"Luchtvaart- Maatschappijen",
    "sg:phone":"+31 10 208 3650",
    "sg:postcode":"3045 AP",
    "sg:province":"Zuid-Holland",
    "wof:name":"Scotairways",
    "wof:placetype":"venue"
},
  "geometry": {"coordinates":[4.432258,51.949036],"type":"Point"}
}