{
  "type": "Feature",
  "properties": {
    "iso:country":"NL",
    "sg:address":"Lekdijk West 81",
    "sg:city":"Bergambacht",
    "sg:orig_category":"Levende Dieren Gh",
    "sg:phone":"+31 182 353 591",
    "sg:postcode":"2861 ET",
    "sg:province":"Zuid-Holland",
    "wof:name":"H. Jansen",
    "wof:placetype":"venue"
},
  "geometry": {"coordinates":[4.757604,51.915916],"type":"Point"}
}