{
  "type": "Feature",
  "properties": {
    "addr:full":"Burghoffweg 9 Roermond Limburg 6042 EX",
    "addr:housenumber":"9",
    "addr:postcode":"6042 ex",
    "addr:street":"Burghoffweg",
    "iso:country":"NL",
    "sg:address":"Burghoffweg 9",
    "sg:city":"Roermond",
    "sg:orig_category":"Autokeuringen",
    "sg:phone":"+31 475 345 500",
    "sg:postcode":"6042 EX",
    "sg:province":"Limburg",
    "wof:name":"Perfekta Autoschade Service",
    "wof:placetype":"venue"
},
  "geometry": {"coordinates":[6.015647,51.208683],"type":"Point"}
}