{
  "type": "Feature",
  "properties": {
    "iso:country":"NL",
    "sg:address":"Dokter Reilinghplein 3",
    "sg:city":"Leerdam",
    "sg:orig_category":"Bibliotheken And Openbare Archieven",
    "sg:phone":"+31 345 612 419",
    "sg:postcode":"4141 DA",
    "sg:province":"South Holland",
    "wof:name":"Stichting Openbare Uitleenbibl En Leesz",
    "wof:placetype":"venue"
},
  "geometry": {"coordinates":[5.092859,51.893093],"type":"Point"}
}