{
  "type": "Feature",
  "properties": {
    "addr:full":"Spiegelstr 13 Bussum Noord-Holland 1405 HV",
    "addr:housenumber":"13",
    "addr:postcode":"1405 hv",
    "addr:street":"Spiegelstr",
    "iso:country":"NL",
    "sg:address":"Spiegelstr 13",
    "sg:city":"Bussum",
    "sg:orig_category":"Binnenhuisarchitectuur",
    "sg:phone":"+31 35 693 4230",
    "sg:postcode":"1405 HV",
    "sg:province":"Noord-Holland",
    "wof:name":"Koldewey",
    "wof:placetype":"venue"
},
  "geometry": {"coordinates":[5.158866,52.274364],"type":"Point"}
}