{
  "type": "Feature",
  "properties": {
    "iso:country":"NL",
    "sg:address":"Spiegelstr 13",
    "sg:city":"Bussum",
    "sg:orig_category":"Binnenhuisarchitectuur",
    "sg:phone":"+31 35 693 4230",
    "sg:postcode":"1405 HV",
    "sg:province":"Noord-Holland",
    "wof:name":"Koldewey",
    "wof:placetype":"venue"
},
  "geometry": {"coordinates":[5.158866,52.274364],"type":"Point"}
}