{
  "type": "Feature",
  "properties": {
    "addr:full":"Langestraat 59 Winschoten Groningen 9671 PC",
    "addr:housenumber":"59",
    "addr:postcode":"9671 pc",
    "addr:street":"Langestraat",
    "iso:country":"NL",
    "sg:address":"Langestraat 59",
    "sg:city":"Winschoten",
    "sg:orig_category":"Verlichting And Huishoudartikelen",
    "sg:phone":"+31 597 431 409",
    "sg:postcode":"9671 PC",
    "sg:province":"Groningen",
    "wof:name":"Giraffe Bv",
    "wof:placetype":"venue"
},
  "geometry": {"coordinates":[7.036179,53.144905],"type":"Point"}
}