{
  "type": "Feature",
  "properties": {
    "addr:full":"Hilvertsweg 126 Hilversum North Holland 1214 JK",
    "addr:housenumber":"126",
    "addr:postcode":"1214 jk",
    "addr:street":"Hilvertsweg",
    "iso:country":"NL",
    "sg:address":"Hilvertsweg 126",
    "sg:city":"Hilversum",
    "sg:orig_category":"Discountwinkels",
    "sg:phone":"+31 35 624 8181",
    "sg:postcode":"1214 JK",
    "sg:province":"North Holland",
    "wof:name":"Fa H Ebes",
    "wof:placetype":"venue"
},
  "geometry": {"coordinates":[5.167625,52.213882],"type":"Point"}
}