{
  "type": "Feature",
  "properties": {
    "addr:full":"Brederolaan 73 Eindhoven North Brabant 5615 KH",
    "addr:housenumber":"73",
    "addr:postcode":"5615 kh",
    "addr:street":"Brederolaan",
    "iso:country":"NL",
    "sg:address":"Brederolaan 73",
    "sg:city":"Eindhoven",
    "sg:orig_category":"Metaalwerken",
    "sg:phone":"+31 40 252 3753",
    "sg:postcode":"5615 KH",
    "sg:province":"North Brabant",
    "wof:name":"Vof Vera",
    "wof:placetype":"venue"
},
  "geometry": {"coordinates":[5.469174,51.428543],"type":"Point"}
}