{
  "type": "Feature",
  "properties": {
    "iso:country":"NL",
    "sg:address":"Nw Mathenesserstr 5-7",
    "sg:city":"Schiedam",
    "sg:orig_category":"Wasserijen",
    "sg:phone":"+31 10 426 9681",
    "sg:postcode":"3113 AD",
    "sg:province":"South Holland",
    "sg:website":"http://www.deglans.nl",
    "wof:name":"Glans, De",
    "wof:placetype":"venue"
},
  "geometry": {"coordinates":[4.4089608192,51.9137878418],"type":"Point"}
}