{
  "type": "Feature",
  "properties": {
    "addr:full":"Westerpaauwenwg 7 Overschild Groningen 9625 TG",
    "addr:housenumber":"7",
    "addr:postcode":"9625 tg",
    "addr:street":"Westerpaauwenwg",
    "iso:country":"NL",
    "sg:address":"Westerpaauwenwg 7",
    "sg:city":"Overschild",
    "sg:orig_category":"Wasmachines En Wasdrogers - Onderhoud En Reparatie",
    "sg:phone":"+31 598 416 410",
    "sg:postcode":"9625 TG",
    "sg:province":"Groningen",
    "wof:name":"Lubbes Reparatiebedrijf",
    "wof:placetype":"venue"
},
  "geometry": {"coordinates":[6.7625432014,53.2495384216],"type":"Point"}
}