{
  "type": "Feature",
  "properties": {
    "addr:full":"Bolstr 28 Utrecht Utrecht 3581 WX",
    "addr:housenumber":"28",
    "addr:postcode":"3581 wx",
    "addr:street":"Bolstr",
    "iso:country":"NL",
    "sg:address":"Bolstr 28",
    "sg:city":"Utrecht",
    "sg:orig_category":"Fietsen En Bromfietsen",
    "sg:phone":"+31 30 251 7941",
    "sg:postcode":"3581 WX",
    "sg:province":"Utrecht",
    "wof:name":"Tegenwind, De",
    "wof:placetype":"venue"
},
  "geometry": {"coordinates":[5.134859,52.088135],"type":"Point"}
}