{
  "type": "Feature",
  "properties": {
    "addr:full":"De Passage 65 Mijdrecht Utrecht 3641 AK",
    "addr:housenumber":"65",
    "addr:postcode":"3641 ak",
    "addr:street":"De Passage",
    "iso:country":"NL",
    "sg:address":"De Passage 65",
    "sg:city":"Mijdrecht",
    "sg:orig_category":"Bedrijfs- And Managementsconsultants",
    "sg:phone":"+31 297 250 615",
    "sg:postcode":"3641 AK",
    "sg:province":"Utrecht",
    "wof:name":"Starters Support",
    "wof:placetype":"venue"
},
  "geometry": {"coordinates":[4.866465,52.207054],"type":"Point"}
}