{
  "type": "Feature",
  "properties": {
    "addr:full":"Bornerbroeksestr 19 De Kolk Almelo Overijssel 7607 KD",
    "addr:housenumber":"19",
    "addr:postcode":"7607 kd",
    "addr:street":"Bornerbroeksestr;De Kolk",
    "iso:country":"NL",
    "sg:address":"Bornerbroeksestr 19 De Kolk",
    "sg:city":"Almelo",
    "sg:orig_category":"Verenigingsgebouwen",
    "sg:phone":"+31 546 851 071",
    "sg:postcode":"7607 KD",
    "sg:province":"Overijssel",
    "wof:name":"Kolk, De",
    "wof:placetype":"venue"
},
  "geometry": {"coordinates":[6.664543,52.354954],"type":"Point"}
}