{
  "type": "Feature",
  "properties": {
    "addr:full":"E Verestr 9 Amstelveen North Holland 1183 KX",
    "addr:housenumber":"9",
    "addr:postcode":"1183 kx",
    "addr:street":"E Verestr",
    "iso:country":"NL",
    "sg:address":"E Verestr 9",
    "sg:city":"Amstelveen",
    "sg:orig_category":"Verenigingen En Stichtingen",
    "sg:phone":"+31 20 645 9900",
    "sg:postcode":"1183 KX",
    "sg:province":"North Holland",
    "wof:name":"Svenska Klubben Ned",
    "wof:placetype":"venue"
},
  "geometry": {"coordinates":[4.876074,52.30534],"type":"Point"}
}