{
  "type": "Feature",
  "properties": {
    "addr:full":"Dorpsstraat 13 Ouderkerk A/D Amstel Noord-Holland 1191 BH",
    "addr:housenumber":"13;a / d",
    "addr:postcode":"1191 bh",
    "addr:street":"Dorpsstraat",
    "iso:country":"NL",
    "sg:address":"Dorpsstraat 13",
    "sg:city":"Ouderkerk A/D Amstel",
    "sg:classifiers":[
        {
            "category":"Food & Beverages",
            "subcategory":"Fruits & Vegetables",
            "type":"Retail Goods"
        }
    ],
    "sg:phone":"+31 20 496 4392",
    "sg:postcode":"1191 BH",
    "sg:province":"Noord-Holland",
    "sg:tags":[
        "groenten"
    ],
    "wof:name":"Hans Uw Groenteman",
    "wof:placetype":"venue"
},
  "geometry": {"coordinates":[4.903238,52.296879],"type":"Point"}
}