{
  "type": "Feature",
  "properties": {
    "addr:full":"Valentynstr 30 Tilburg Noord-Brabant 5014 KG",
    "addr:housenumber":"30",
    "addr:postcode":"5014 kg",
    "addr:street":"Valentynstr",
    "iso:country":"NL",
    "sg:address":"Valentynstr 30",
    "sg:city":"Tilburg",
    "sg:orig_category":"Koffie-Automaten",
    "sg:phone":"+31 13 535 5446",
    "sg:postcode":"5014 KG",
    "sg:province":"Noord-Brabant",
    "wof:name":"Belkom, Ton Van",
    "wof:placetype":"venue"
},
  "geometry": {"coordinates":[5.096653,51.568348],"type":"Point"}
}