{
  "type": "Feature",
  "properties": {
    "iso:country":"NL",
    "sg:address":"Nieuwstraat 21",
    "sg:city":"Gemert",
    "sg:orig_category":"Meubelzaken, Woning- And Keukeninrichting",
    "sg:phone":"+31 6 53790901",
    "sg:postcode":"5421 KN",
    "sg:province":"Noord-Brabant",
    "wof:name":"Csa",
    "wof:placetype":"venue"
},
  "geometry": {"coordinates":[5.682248,51.556976],"type":"Point"}
}