{
  "type": "Feature",
  "properties": {
    "addr:full":"Amperestraat 2 Zandvoort Noord-Holland 2041 CL",
    "addr:housenumber":"2",
    "addr:postcode":"2041",
    "addr:street":"Amperestraat",
    "iso:country":"NL",
    "sg:address":"Amperestraat 2",
    "sg:city":"Zandvoort",
    "sg:orig_category":"Visspeciaalzaken",
    "sg:phone":"+31 23 571 7619",
    "sg:postcode":"2041 CL",
    "sg:province":"Noord-Holland",
    "wof:name":"J Kroon Vishandelaar",
    "wof:placetype":"venue"
},
  "geometry": {"coordinates":[4.555381,52.377979],"type":"Point"}
}