{
  "type": "Feature",
  "properties": {
    "addr:full":"Iepenlaan 64 Spijkenisse Zuid-Holland 3203 XH",
    "addr:housenumber":"64",
    "addr:postcode":"3203 xh",
    "addr:street":"Iepenlaan",
    "iso:country":"NL",
    "sg:address":"Iepenlaan 64",
    "sg:city":"Spijkenisse",
    "sg:orig_category":"Bouwnijverheidsmachines Gh",
    "sg:phone":"+31 181 619 206",
    "sg:postcode":"3203 XH",
    "sg:province":"Zuid-Holland",
    "wof:name":"Heffix",
    "wof:placetype":"venue"
},
  "geometry": {"coordinates":[4.343146,51.839733],"type":"Point"}
}