{
  "type": "Feature",
  "properties": {
    "addr:full":"Burgemeester Elkhuizenln 55 Halsteren Noord-Brabant 4661 CJ",
    "addr:housenumber":"55",
    "addr:postcode":"4661 cj",
    "addr:street":"Burgemeester Elkhuizenln",
    "iso:country":"NL",
    "sg:address":"Burgemeester Elkhuizenln 55",
    "sg:city":"Halsteren",
    "sg:classifiers":[
        {
            "category":"Education",
            "subcategory":"Preschool",
            "type":"Public Place"
        }
    ],
    "sg:phone":"+31 164 682 786",
    "sg:postcode":"4661 CJ",
    "sg:province":"Noord-Brabant",
    "sg:tags":[
        "kleuteronderwijs",
        "basis-"
    ],
    "wof:name":"Basisschool De Springplank",
    "wof:placetype":"venue"
},
  "geometry": {"coordinates":[4.271179,51.5369],"type":"Point"}
}