{
  "type": "Feature",
  "properties": {
    "addr:full":"Middenwg 453 Heerhugowaard Noord-Holland 1704 BB",
    "addr:housenumber":"453",
    "addr:postcode":"1704 bb",
    "iso:country":"NL",
    "sg:address":"Middenwg 453",
    "sg:city":"Heerhugowaard",
    "sg:orig_category":"Meubelen",
    "sg:phone":"+31 72 574 6147",
    "sg:postcode":"1704 BB",
    "sg:province":"Noord-Holland",
    "wof:name":"Supermeubel",
    "wof:placetype":"venue"
},
  "geometry": {"coordinates":[4.827522,52.665195],"type":"Point"}
}