{
  "type": "Feature",
  "properties": {
    "addr:full":"Voltastr 8 Purmerend Noord-Holland 1446 VC",
    "addr:housenumber":"8",
    "addr:postcode":"1446 vc",
    "addr:street":"Voltastr",
    "iso:country":"NL",
    "sg:address":"Voltastr 8",
    "sg:city":"Purmerend",
    "sg:orig_category":"Drukkerijen",
    "sg:phone":"+31 299 418 418",
    "sg:postcode":"1446 VC",
    "sg:province":"Noord-Holland",
    "sg:website":"http://www.henkessenefelder.nl",
    "wof:name":"Henkes Senefelder Bv",
    "wof:placetype":"venue"
},
  "geometry": {"coordinates":[5.001127,52.51532],"type":"Point"}
}