{
  "type": "Feature",
  "properties": {
    "addr:full":"Abbestederweg 29 Callantsoog North Holland 1759 NA",
    "addr:housenumber":"29",
    "addr:postcode":"1759 na",
    "addr:street":"Abbestederweg",
    "iso:country":"NL",
    "sg:address":"Abbestederweg 29",
    "sg:city":"Callantsoog",
    "sg:orig_category":"Kampeerterreinen",
    "sg:phone":"+31 224 581 972",
    "sg:postcode":"1759 NA",
    "sg:province":"North Holland",
    "wof:name":"Camping Trekkershonk",
    "wof:placetype":"venue"
},
  "geometry": {"coordinates":[4.6992669106,52.8415489197],"type":"Point"}
}