{
  "type": "Feature",
  "properties": {
    "addr:full":"Polln 54 Zutphen Gelderland 7202 BX",
    "addr:housenumber":"54",
    "addr:postcode":"7202 bx",
    "addr:street":"Polln;Gelderland",
    "iso:country":"NL",
    "sg:address":"Polln 54",
    "sg:city":"Zutphen",
    "sg:orig_category":"Cafetaria'S",
    "sg:phone":"+31 575 517 154",
    "sg:postcode":"7202 BX",
    "sg:province":"Gelderland",
    "wof:name":"Midi",
    "wof:placetype":"venue"
},
  "geometry": {"coordinates":[6.191525,52.140202],"type":"Point"}
}