{
  "type": "Feature",
  "properties": {
    "addr:full":"Canneshof 13 Eindhoven Noord-Brabant 5627 GZ",
    "addr:housenumber":"13",
    "addr:postcode":"5627 gz",
    "addr:street":"Canneshof",
    "iso:country":"NL",
    "sg:address":"Canneshof 13",
    "sg:city":"Eindhoven",
    "sg:orig_category":"Glazenwasserijen",
    "sg:phone":"+31 40 242 5623",
    "sg:postcode":"5627 GZ",
    "sg:province":"Noord-Brabant",
    "wof:name":"Peeters",
    "wof:placetype":"venue"
},
  "geometry": {"coordinates":[5.448804,51.480042],"type":"Point"}
}