{
  "type": "Feature",
  "properties": {
    "addr:full":"Galjoenweg 68 Maastricht Limburg 6222 NV",
    "addr:housenumber":"68",
    "addr:postcode":"6222 nv",
    "addr:street":"Galjoenweg",
    "iso:country":"NL",
    "sg:address":"Galjoenweg 68",
    "sg:city":"Maastricht",
    "sg:orig_category":"Goederenvervoer Over De Weg",
    "sg:phone":"+31 43 363 5885",
    "sg:postcode":"6222 NV",
    "sg:province":"Limburg",
    "wof:name":"Schavemaker Transport Bv",
    "wof:placetype":"venue"
},
  "geometry": {"coordinates":[5.70702,50.875732],"type":"Point"}
}