{
  "type": "Feature",
  "properties": {
    "iso:country":"NL",
    "sg:address":"Rijnlaan 33",
    "sg:city":"Zwolle",
    "sg:orig_category":"Fitnesscentra",
    "sg:phone":"+31 38 453 7960",
    "sg:postcode":"8032 JZ",
    "sg:province":"NL.08",
    "wof:name":"Fysio Fit Zwolle",
    "wof:placetype":"venue"
},
  "geometry": {"coordinates":[6.100294,52.52961],"type":"Point"}
}