{
  "type": "Feature",
  "properties": {
    "addr:full":"Kwartelstraat 29 Utrecht Utrecht 3514 ET",
    "addr:housenumber":"29",
    "addr:postcode":"3514 et",
    "addr:street":"Kwartelstraat",
    "iso:country":"NL",
    "sg:address":"Kwartelstraat 29",
    "sg:city":"Utrecht",
    "sg:orig_category":"Werving And Selectie Van Vast Personeel",
    "sg:phone":"+31 6 55748513",
    "sg:postcode":"3514 ET",
    "sg:province":"Utrecht",
    "wof:name":"Hekate",
    "wof:placetype":"venue"
},
  "geometry": {"coordinates":[5.1220231056,52.0983505249],"type":"Point"}
}