{
  "type": "Feature",
  "properties": {
    "addr:full":"Dorpsstraat 21 Helmond Noord-Brabant 5708 GC",
    "addr:housenumber":"21",
    "addr:postcode":"5708 gc",
    "addr:street":"Dorpsstraat",
    "iso:country":"NL",
    "sg:address":"Dorpsstraat 21",
    "sg:city":"Helmond",
    "sg:orig_category":"Architecten",
    "sg:phone":"+31 492 539 634",
    "sg:postcode":"5708 GC",
    "sg:province":"Noord-Brabant",
    "wof:name":"Architectenburo J.A.H. Van De Laar",
    "wof:placetype":"venue"
},
  "geometry": {"coordinates":[5.618063,51.486702],"type":"Point"}
}