{
  "type": "Feature",
  "properties": {
    "iso:country":"NL",
    "sg:address":"Bierens De Haanweg 71",
    "sg:city":"Rotterdam",
    "sg:classifiers":[
        {
            "category":"Communications",
            "subcategory":"Television Station",
            "type":"Services"
        }
    ],
    "sg:phone":"+31 10 419 4747",
    "sg:postcode":"3076 DA",
    "sg:province":"Zuid-Holland",
    "sg:tags":[
        "video",
        "audio",
        "verhuur"
    ],
    "wof:name":"Videotheek Lombardijen",
    "wof:placetype":"venue"
},
  "geometry": {"coordinates":[4.517031,51.878506],"type":"Point"}
}