{
  "type": "Feature",
  "properties": {
    "iso:country":"NL",
    "sg:address":"Plaswg 24",
    "sg:city":"Soest",
    "sg:orig_category":"Metselwerken",
    "sg:phone":"+31 35 601 9666",
    "sg:postcode":"3768 AM",
    "sg:province":"Utrecht",
    "wof:name":"Dijkman En Znn, H G",
    "wof:placetype":"venue"
},
  "geometry": {"coordinates":[5.300656,52.162041],"type":"Point"}
}