{
  "type": "Feature",
  "properties": {
    "addr:full":"Plaswg 24 Soest Utrecht 3768 AM",
    "addr:housenumber":"24",
    "addr:postcode":"3768",
    "addr:street":"Plaswg",
    "iso:country":"NL",
    "sg:address":"Plaswg 24",
    "sg:city":"Soest",
    "sg:orig_category":"Metselwerken",
    "sg:phone":"+31 35 601 9666",
    "sg:postcode":"3768 AM",
    "sg:province":"Utrecht",
    "wof:name":"Dijkman En Znn, H G",
    "wof:placetype":"venue"
},
  "geometry": {"coordinates":[5.300656,52.162041],"type":"Point"}
}