{
  "type": "Feature",
  "properties": {
    "addr:full":"Laan 1940 - 1945 48 Harderwijk Gelderland 3841 JD",
    "addr:housenumber":"48",
    "addr:postcode":"3841 jd",
    "addr:street":"Laan 1940 1945;Gelderland",
    "iso:country":"NL",
    "sg:address":"Laan 1940 - 1945 48",
    "sg:city":"Harderwijk",
    "sg:classifiers":[
        {
            "category":"Fast Food",
            "type":"Food & Drink"
        }
    ],
    "sg:phone":"+31 341 422 648",
    "sg:postcode":"3841 JD",
    "sg:province":"Gelderland",
    "sg:tags":[
        "afhaal",
        "restaurant"
    ],
    "wof:name":"Cafetaria Van Den Berg Vof",
    "wof:placetype":"venue"
},
  "geometry": {"coordinates":[5.627758,52.350548],"type":"Point"}
}