{
  "type": "Feature",
  "properties": {
    "addr:full":"Pr Pieter-Christiaanhof 5 Badhoevedorp Noord-Holland 1171 LL",
    "addr:housenumber":"5",
    "addr:postcode":"1171 ll",
    "addr:street":"Pieter-Christiaanhof",
    "iso:country":"NL",
    "sg:address":"Pr Pieter-Christiaanhof 5",
    "sg:city":"Badhoevedorp",
    "sg:orig_category":"Verzekeringen",
    "sg:phone":"+31 20 659 4481",
    "sg:postcode":"1171 LL",
    "sg:province":"Noord-Holland",
    "wof:name":"Ackema Assurantien",
    "wof:placetype":"venue"
},
  "geometry": {"coordinates":[4.765572,52.340221],"type":"Point"}
}