{
  "type": "Feature",
  "properties": {
    "addr:full":"Burg Cortenstr 20 Maastricht Limburg 6226 GV",
    "addr:housenumber":"20",
    "addr:postcode":"6226 gv",
    "addr:street":"Burg",
    "iso:country":"NL",
    "sg:address":"Burg Cortenstr 20",
    "sg:city":"Maastricht",
    "sg:orig_category":"Herenkleding",
    "sg:phone":"+31 43 362 9551",
    "sg:postcode":"6226 GV",
    "sg:province":"Limburg",
    "wof:name":"L'Uomo",
    "wof:placetype":"venue"
},
  "geometry": {"coordinates":[5.727727,50.845146],"type":"Point"}
}