{
  "type": "Feature",
  "properties": {
    "addr:full":"Noorddammerln 105A Amstelveen Noord-Holland 1187 AC",
    "addr:housenumber":"105a",
    "addr:postcode":"1187 ac",
    "iso:country":"NL",
    "sg:address":"Noorddammerln 105A",
    "sg:city":"Amstelveen",
    "sg:orig_category":"Fotografie Reclame En Mode",
    "sg:phone":"+31 20 645 3749",
    "sg:postcode":"1187 AC",
    "sg:province":"Noord-Holland",
    "wof:name":"Viehoff, Diek",
    "wof:placetype":"venue"
},
  "geometry": {"coordinates":[4.835744,52.29306],"type":"Point"}
}