{
  "type": "Feature",
  "properties": {
    "iso:country":"NL",
    "sg:address":"Zandweg 27",
    "sg:city":"Wijk Bij Duurstede",
    "sg:orig_category":"Autokeuringen",
    "sg:phone":"+31 343 572 585",
    "sg:postcode":"3962 EA",
    "sg:province":"Utrecht",
    "wof:name":"Gebr. J. En H. Oteman Bv",
    "wof:placetype":"venue"
},
  "geometry": {"coordinates":[5.318416,51.995358],"type":"Point"}
}