{
  "type": "Feature",
  "properties": {
    "addr:full":"Rechtestraat 6 Eindhoven Noord-Brabant 5611 GP",
    "addr:housenumber":"6",
    "addr:postcode":"5611 gp",
    "addr:street":"Rechtestraat",
    "iso:country":"NL",
    "sg:address":"Rechtestraat 6",
    "sg:city":"Eindhoven",
    "sg:classifiers":[
        {
            "category":"Retail",
            "subcategory":"Photofinishing",
            "type":"Services"
        }
    ],
    "sg:phone":"+31 40 245 3987",
    "sg:postcode":"5611 GP",
    "sg:province":"Noord-Brabant",
    "sg:tags":[
        "foto",
        "film"
    ],
    "wof:name":"Super Photo Snelservice Bv",
    "wof:placetype":"venue"
},
  "geometry": {"coordinates":[5.47743,51.439178],"type":"Point"}
}