{
  "type": "Feature",
  "properties": {
    "addr:full":"Vechtstr 82 Groningen Groningen 9725 CW",
    "addr:housenumber":"82",
    "addr:postcode":"9725 cw",
    "addr:street":"Vechtstr",
    "iso:country":"NL",
    "sg:address":"Vechtstr 82",
    "sg:city":"Groningen",
    "sg:orig_category":"Artsen - Manuele Geneeskunde",
    "sg:phone":"+31 50 526 9870",
    "sg:postcode":"9725 CW",
    "sg:province":"Groningen",
    "wof:name":"Tromp, Drs P J",
    "wof:placetype":"venue"
},
  "geometry": {"coordinates":[6.569138,53.20776],"type":"Point"}
}