{
  "type": "Feature",
  "properties": {
    "addr:full":"Boulevard 9 Breskens Zeeland 4511 AA",
    "addr:housenumber":"9",
    "addr:postcode":"4511 aa",
    "addr:street":"Boulevard",
    "iso:country":"NL",
    "sg:address":"Boulevard 9",
    "sg:city":"Breskens",
    "sg:orig_category":"Damesmodezaken",
    "sg:phone":"+31 117 382 590",
    "sg:postcode":"4511 AA",
    "sg:province":"Zeeland",
    "wof:name":"Boetiek Viviane",
    "wof:placetype":"venue"
},
  "geometry": {"coordinates":[3.556688,51.397366],"type":"Point"}
}