{
  "type": "Feature",
  "properties": {
    "addr:full":"Meeuwerderwg 45 Groningen Groningen 9724 EN",
    "addr:housenumber":"45",
    "addr:postcode":"9724 en",
    "addr:street":"Meeuwerderwg",
    "iso:country":"NL",
    "sg:address":"Meeuwerderwg 45",
    "sg:city":"Groningen",
    "sg:orig_category":"Linnenshops",
    "sg:phone":"+31 50 311 2454",
    "sg:postcode":"9724 EN",
    "sg:province":"Groningen",
    "wof:name":"Cotton Style",
    "wof:placetype":"venue"
},
  "geometry": {"coordinates":[6.578459,53.212864],"type":"Point"}
}