{
  "type": "Feature",
  "properties": {
    "addr:full":"Brahmsln 3-5 Leiden South Holland 2324 AC",
    "addr:housenumber":"3-5",
    "addr:postcode":"2324 ac",
    "addr:street":"Brahmsln",
    "iso:country":"NL",
    "sg:address":"Brahmsln 3-5",
    "sg:city":"Leiden",
    "sg:orig_category":"Metselwerken",
    "sg:phone":"+31 71 572 1884",
    "sg:postcode":"2324 AC",
    "sg:province":"South Holland",
    "wof:name":"D-Dan",
    "wof:placetype":"venue"
},
  "geometry": {"coordinates":[4.47026,52.144901],"type":"Point"}
}