{
  "type": "Feature",
  "properties": {
    "addr:full":"Reviusstraat 74 Hengelo Ov Overijssel 7552 GL",
    "addr:housenumber":"74",
    "addr:postcode":"7552 gl",
    "addr:street":"Reviusstraat;Ov",
    "iso:country":"NL",
    "sg:address":"Reviusstraat 74",
    "sg:city":"Hengelo Ov",
    "sg:orig_category":"Bedrijfs- And Managementsconsultants",
    "sg:phone":"+31 74 242 5429",
    "sg:postcode":"7552 GL",
    "sg:province":"Overijssel",
    "wof:name":"Van Oosten Consultancy",
    "wof:placetype":"venue"
},
  "geometry": {"coordinates":[6.824868,52.257538],"type":"Point"}
}