{
  "type": "Feature",
  "properties": {
    "addr:full":"Prof Holstln 4 Eindhoven Noord-Brabant 5656 AA",
    "addr:housenumber":"4",
    "addr:postcode":"5656 aa",
    "iso:country":"NL",
    "sg:address":"Prof Holstln 4",
    "sg:city":"Eindhoven",
    "sg:orig_category":"Arbo- En Bedrijfsgezondheids- Diensten",
    "sg:phone":"+31 40 274 2390",
    "sg:postcode":"5656 AA",
    "sg:province":"Noord-Brabant",
    "wof:name":"Achmea Arbo",
    "wof:placetype":"venue"
},
  "geometry": {"coordinates":[5.462565,51.411949],"type":"Point"}
}