{
  "type": "Feature",
  "properties": {
    "addr:full":"Marktstraat 10 Ootmarsum Overijssel 7631 BZ",
    "addr:housenumber":"10",
    "addr:postcode":"7631 bz",
    "addr:street":"Marktstraat",
    "iso:country":"NL",
    "sg:address":"Marktstraat 10",
    "sg:city":"Ootmarsum",
    "sg:orig_category":"Juweliers",
    "sg:phone":"+31 541 292 992",
    "sg:postcode":"7631 BZ",
    "sg:province":"Overijssel",
    "wof:name":"Juwelier A. Mensink",
    "wof:placetype":"venue"
},
  "geometry": {"coordinates":[6.897662,52.408585],"type":"Point"}
}