{
  "type": "Feature",
  "properties": {
    "iso:country":"NL",
    "sg:address":"Randstad 22127",
    "sg:city":"Almere",
    "sg:orig_category":"Medische Installaties En Instrumenten",
    "sg:phone":"+31 36 531 1624",
    "sg:postcode":"1316 BW",
    "sg:province":"NL.",
    "wof:name":"Kardia Bv",
    "wof:placetype":"venue"
},
  "geometry": {"coordinates":[5.228651,52.378948],"type":"Point"}
}