{
  "type": "Feature",
  "properties": {
    "addr:full":"W Voorstr 26 Oud Beyerland Zuid-Holland 3262 JP",
    "addr:housenumber":"26",
    "addr:postcode":"3262 jp",
    "addr:street":"W;Oud Beyerland",
    "iso:country":"NL",
    "sg:address":"W Voorstr 26",
    "sg:city":"Oud Beyerland",
    "sg:classifiers":[
        {
            "category":"Food & Beverages",
            "subcategory":"Candy",
            "type":"Retail Goods"
        }
    ],
    "sg:phone":"+31 186 616 469",
    "sg:postcode":"3262 JP",
    "sg:province":"Zuid-Holland",
    "sg:tags":[
        "sport-",
        "en",
        "spelartikelen"
    ],
    "wof:name":"Voorwinden Bv",
    "wof:placetype":"venue"
},
  "geometry": {"coordinates":[4.41701,51.823044],"type":"Point"}
}