{
  "type": "Feature",
  "properties": {
    "addr:full":"Zwaanstr 2 Enkhuizen North Holland 1601 KM",
    "addr:housenumber":"2",
    "addr:street":"Zwaanstr;1601 Km",
    "iso:country":"NL",
    "sg:address":"Zwaanstr 2",
    "sg:city":"Enkhuizen",
    "sg:orig_category":"Boeken En Tijdschriften",
    "sg:phone":"+31 228 314 208",
    "sg:postcode":"1601 KM",
    "sg:province":"North Holland",
    "wof:name":"Soneste",
    "wof:placetype":"venue"
},
  "geometry": {"coordinates":[5.295231,52.70369],"type":"Point"}
}