{
  "type": "Feature",
  "properties": {
    "iso:country":"NL",
    "sg:address":"Aarkd 63",
    "sg:city":"Alphen Aan Den Ryn",
    "sg:orig_category":"Lijstenmakerijen",
    "sg:phone":"+31 6 44402002",
    "sg:postcode":"2406 BW",
    "sg:province":"Zuid-Holland",
    "wof:name":"Alphrame",
    "wof:placetype":"venue"
},
  "geometry": {"coordinates":[4.67368,52.12981],"type":"Point"}
}