{
  "type": "Feature",
  "properties": {
    "iso:country":"NL",
    "sg:address":"Communicatiewg 18",
    "sg:city":"Mydrecht",
    "sg:orig_category":"Adviesbureaus",
    "sg:phone":"+31 297 256 111",
    "sg:postcode":"3641 SE",
    "sg:province":"Utrecht",
    "sg:website":"http://www.uniprox.com",
    "wof:name":"Uniprox Bv",
    "wof:placetype":"venue"
},
  "geometry": {"coordinates":[4.883645,52.212955],"type":"Point"}
}