{
  "type": "Feature",
  "properties": {
    "iso:country":"NL",
    "sg:address":"Benthuizerstr 25A",
    "sg:city":"Rotterdam",
    "sg:classifiers":[
        {
            "category":"Food & Beverages",
            "subcategory":"Fruits & Vegetables",
            "type":"Retail Goods"
        }
    ],
    "sg:phone":"+31 10 265 1049",
    "sg:postcode":"3036 CB",
    "sg:province":"South Holland",
    "sg:tags":[
        "en",
        "groenten"
    ],
    "wof:name":"Eser Market",
    "wof:placetype":"venue"
},
  "geometry": {"coordinates":[4.479501,51.937176],"type":"Point"}
}