{
  "type": "Feature",
  "properties": {
    "addr:full":"Oosterstr 36-37 Stadskanaal Groningen 9502 ED",
    "addr:housenumber":"36-37",
    "addr:postcode":"9502 ed",
    "addr:street":"Stadskanaal",
    "iso:country":"NL",
    "sg:address":"Oosterstr 36-37",
    "sg:city":"Stadskanaal",
    "sg:orig_category":"Machinefabrieken",
    "sg:phone":"+31 599 612 936",
    "sg:postcode":"9502 ED",
    "sg:province":"Groningen",
    "wof:name":"Pater Bv",
    "wof:placetype":"venue"
},
  "geometry": {"coordinates":[6.968922,52.976845],"type":"Point"}
}