{
  "type": "Feature",
  "properties": {
    "addr:full":"Tjalk 3052 Lelystad Flevoland 8232 NJ",
    "addr:postcode":"3052;8232",
    "addr:street":"Tjalk;Flevoland",
    "iso:country":"NL",
    "sg:address":"Tjalk 3052",
    "sg:city":"Lelystad",
    "sg:orig_category":"Onderhoudswerken",
    "sg:phone":"+31 320 235 374",
    "sg:postcode":"8232 NJ",
    "sg:province":"Flevoland",
    "wof:name":"Fokker, Fjc",
    "wof:placetype":"venue"
},
  "geometry": {"coordinates":[5.467906,52.499557],"type":"Point"}
}