{
  "type": "Feature",
  "properties": {
    "iso:country":"NL",
    "sg:address":"Postbus 5500",
    "sg:city":"Sittard",
    "sg:orig_category":"Ziekenhuizen, Sanatoria, Verpleeghuizen",
    "sg:phone":"+31 46 459 7777",
    "sg:postcode":"6130 MB",
    "sg:province":"Limburg",
    "sg:website":"http://www.orbisconcern.nl",
    "wof:name":"Orbis",
    "wof:placetype":"venue"
},
  "geometry": {"coordinates":[5.86292,50.998299],"type":"Point"}
}