{
  "type": "Feature",
  "properties": {
    "addr:full":"Kon Julianaln 15 Slootdorp Noord-Holland 1774 AZ",
    "addr:housenumber":"15",
    "addr:postcode":"1774 az",
    "addr:street":"Kon",
    "iso:country":"NL",
    "sg:address":"Kon Julianaln 15",
    "sg:city":"Slootdorp",
    "sg:orig_category":"Grondwerken",
    "sg:phone":"+31 227 581 435",
    "sg:postcode":"1774 AZ",
    "sg:province":"Noord-Holland",
    "wof:name":"Blokker",
    "wof:placetype":"venue"
},
  "geometry": {"coordinates":[4.972329,52.84486],"type":"Point"}
}