{
  "type": "Feature",
  "properties": {
    "iso:country":"NL",
    "sg:address":"Ronkenstr 8",
    "sg:city":"Roermond",
    "sg:orig_category":"Fietsen En Bromfietsen",
    "sg:phone":"+31 475 323 301",
    "sg:postcode":"6042 JM",
    "sg:province":"Limburg",
    "wof:name":"Jaspers",
    "wof:placetype":"venue"
},
  "geometry": {"coordinates":[6.012825,51.197426],"type":"Point"}
}