{
  "type": "Feature",
  "properties": {
    "addr:full":"Struytse Hoeck 57 Hellevoetsluis Zuid-Holland 3224 HA",
    "addr:housenumber":"57",
    "addr:postcode":"3224 ha",
    "addr:street":"Struytse Hoeck",
    "iso:country":"NL",
    "sg:address":"Struytse Hoeck 57",
    "sg:city":"Hellevoetsluis",
    "sg:orig_category":"Warenhuizen",
    "sg:phone":"+31 900 9800",
    "sg:postcode":"3224 HA",
    "sg:province":"Zuid-Holland",
    "wof:name":"Kijkshop",
    "wof:placetype":"venue"
},
  "geometry": {"coordinates":[4.1448521614,51.8299980164],"type":"Point"}
}