{
  "type": "Feature",
  "properties": {
    "addr:full":"Poststr 7A Amstenrade Limburg 6436 CJ",
    "addr:housenumber":"7a",
    "addr:postcode":"6436 cj",
    "addr:street":"Poststr",
    "iso:country":"NL",
    "sg:address":"Poststr 7A",
    "sg:city":"Amstenrade",
    "sg:orig_category":"Voetbalverenigingen",
    "sg:phone":"+31 46 442 1297",
    "sg:postcode":"6436 CJ",
    "sg:province":"Limburg",
    "wof:name":"Bende 92, In De",
    "wof:placetype":"venue"
},
  "geometry": {"coordinates":[5.924371,50.941711],"type":"Point"}
}