{
  "type": "Feature",
  "properties": {
    "iso:country":"NL",
    "sg:address":"Van Ruysdaellaan 55",
    "sg:city":"Leidschendam",
    "sg:classifiers":[
        {
            "category":"Professional",
            "subcategory":"Accounting & Tax Preparation",
            "type":"Services"
        }
    ],
    "sg:phone":"+31 70 320 2479",
    "sg:postcode":"2264 TK",
    "sg:province":"Zuid-Holland",
    "sg:tags":[
        "accountant"
    ],
    "wof:name":"Kramer Accountants",
    "wof:placetype":"venue"
},
  "geometry": {"coordinates":[4.389648,52.088062],"type":"Point"}
}