{
  "type": "Feature",
  "properties": {
    "addr:full":"Croonstadtln 1 Mydrecht Utrecht 3641 AL",
    "addr:housenumber":"1;3641",
    "addr:street":"Croonstadtln;Al",
    "iso:country":"NL",
    "sg:address":"Croonstadtln 1",
    "sg:city":"Mydrecht",
    "sg:orig_category":"Verloskundigen",
    "sg:phone":"+31 297 272 300",
    "sg:postcode":"3641 AL",
    "sg:province":"Utrecht",
    "wof:name":"Ronde Venen, Maatschap De",
    "wof:placetype":"venue"
},
  "geometry": {"coordinates":[4.86178,52.20578],"type":"Point"}
}