{
  "type": "Feature",
  "properties": {
    "addr:full":"Markt 13 Mill Noord-Brabant 5451 BS",
    "addr:housenumber":"13",
    "addr:postcode":"5451 bs",
    "addr:street":"Markt",
    "iso:country":"NL",
    "sg:address":"Markt 13",
    "sg:city":"Mill",
    "sg:orig_category":"Kappers",
    "sg:phone":"+31 485 451 955",
    "sg:postcode":"5451 BS",
    "sg:province":"Noord-Brabant",
    "wof:name":"Dames & Heren Haarverzorging Theo Slaats",
    "wof:placetype":"venue"
},
  "geometry": {"coordinates":[-77.7629394531,41.9040298462],"type":"Point"}
}