{
  "type": "Feature",
  "properties": {
    "iso:country":"NL",
    "sg:address":"Buitenwatersloot 71",
    "sg:city":"Delft",
    "sg:orig_category":"Wolartikelen En Breiwol - Fabrieken En Groothandel",
    "sg:phone":"+31 15 214 6342",
    "sg:postcode":"2613 TB",
    "sg:province":"Zuid-Holland",
    "sg:website":"http://www.wernekinck.com",
    "wof:name":"Wernekinck, Richard",
    "wof:placetype":"venue"
},
  "geometry": {"coordinates":[4.3532629013,52.0079994202],"type":"Point"}
}