{
  "type": "Feature",
  "properties": {
    "addr:full":"Buitenwatersloot 71 Delft Zuid-Holland 2613 TB",
    "addr:housenumber":"71",
    "addr:postcode":"2613 tb",
    "addr:street":"Buitenwatersloot",
    "iso:country":"NL",
    "sg:address":"Buitenwatersloot 71",
    "sg:city":"Delft",
    "sg:orig_category":"Wolartikelen En Breiwol - Fabrieken En Groothandel",
    "sg:phone":"+31 15 214 6342",
    "sg:postcode":"2613 TB",
    "sg:province":"Zuid-Holland",
    "sg:website":"http://www.wernekinck.com",
    "wof:name":"Wernekinck, Richard",
    "wof:placetype":"venue"
},
  "geometry": {"coordinates":[4.3532629013,52.0079994202],"type":"Point"}
}