{
  "type": "Feature",
  "properties": {
    "addr:full":"Van Grobbendoncklaan 101 'S Hertogenbosch Noord-Brabant 5213 AV",
    "addr:housenumber":"101 ' s",
    "addr:postcode":"5213 av",
    "addr:street":"Van Grobbendoncklaan",
    "iso:country":"NL",
    "sg:address":"Van Grobbendoncklaan 101",
    "sg:city":"'S Hertogenbosch",
    "sg:orig_category":"Meubelzaken, Woning- And Keukeninrichting",
    "sg:phone":"+31 73 613 8080",
    "sg:postcode":"5213 AV",
    "sg:province":"Noord-Brabant",
    "wof:name":"Apart Tridesign",
    "wof:placetype":"venue"
},
  "geometry": {"coordinates":[5.320104,51.698727],"type":"Point"}
}