{
  "type": "Feature",
  "properties": {
    "addr:full":"Wieringermeerstr 23 Enschede Overijssel 7543 XD",
    "addr:housenumber":"23",
    "addr:postcode":"7543 xd",
    "addr:street":"Wieringermeerstr",
    "iso:country":"NL",
    "sg:address":"Wieringermeerstr 23",
    "sg:city":"Enschede",
    "sg:orig_category":"Verenigingen En Stichtingen",
    "sg:phone":"+31 53 476 2588",
    "sg:postcode":"7543 XD",
    "sg:province":"Overijssel",
    "wof:name":"Scouting Nanne Zwiep",
    "wof:placetype":"venue"
},
  "geometry": {"coordinates":[6.878252,52.203011],"type":"Point"}
}