{
  "type": "Feature",
  "properties": {
    "addr:full":"Parallelweg 66 Geldrop Noord-Brabant 5664 AG",
    "addr:housenumber":"66",
    "addr:postcode":"5664",
    "addr:street":"Parallelweg",
    "iso:country":"NL",
    "sg:address":"Parallelweg 66",
    "sg:city":"Geldrop",
    "sg:orig_category":"Antiekzaken",
    "sg:phone":"+31 40 286 7047",
    "sg:postcode":"5664 AG",
    "sg:province":"Noord-Brabant",
    "wof:name":"Grootmoeders Snuffelhoek",
    "wof:placetype":"venue"
},
  "geometry": {"coordinates":[5.546189,51.423927],"type":"Point"}
}