{
  "type": "Feature",
  "properties": {
    "addr:full":"Wittewg 10A Langeveen Overijssel 7679 VV",
    "addr:housenumber":"10a",
    "addr:postcode":"7679 vv",
    "addr:street":"Wittewg",
    "iso:country":"NL",
    "sg:address":"Wittewg 10A",
    "sg:city":"Langeveen",
    "sg:orig_category":"Loonbedrijven",
    "sg:phone":"+31 546 681 286",
    "sg:postcode":"7679 VV",
    "sg:province":"Overijssel",
    "wof:name":"Oude Nijeweeme Bv",
    "wof:placetype":"venue"
},
  "geometry": {"coordinates":[6.734561,52.465862],"type":"Point"}
}