{
  "type": "Feature",
  "properties": {
    "iso:country":"NL",
    "sg:address":"Osdorpplein 621",
    "sg:city":"Amsterdam",
    "sg:orig_category":"Opticiens",
    "sg:phone":"+31 20 610 4253",
    "sg:postcode":"1068 TB",
    "sg:province":"Noord-Holland",
    "wof:name":"Pearle Opticiens",
    "wof:placetype":"venue"
},
  "geometry": {"coordinates":[4.8046197891,52.3583488464],"type":"Point"}
}