{
  "type": "Feature",
  "properties": {
    "addr:full":"Produktieweg 36 Zoeterwoude South Holland 2382 PC",
    "addr:housenumber":"36",
    "addr:postcode":"2382 pc",
    "addr:street":"Produktieweg",
    "iso:country":"NL",
    "sg:address":"Produktieweg 36",
    "sg:city":"Zoeterwoude",
    "sg:orig_category":"Verhuur Bouwmachines",
    "sg:phone":"+31 71 589 9344",
    "sg:postcode":"2382 PC",
    "sg:province":"South Holland",
    "wof:name":"Van Marwijk Kraanverhuur Bv",
    "wof:placetype":"venue"
},
  "geometry": {"coordinates":[4.515887,52.140305],"type":"Point"}
}