{
  "type": "Feature",
  "properties": {
    "iso:country":"NL",
    "sg:address":"Pythagorasstraat 9",
    "sg:city":"Arnhem",
    "sg:classifiers":[
        {
            "category":"Education",
            "subcategory":"Preschool",
            "type":"Public Place"
        }
    ],
    "sg:phone":"+31 26 327 2896",
    "sg:postcode":"6836 GA",
    "sg:province":"Gelderland",
    "sg:tags":[
        "kleuteronderwijs",
        "basis-"
    ],
    "wof:name":"Lea Dasberg School Voor Openbaar Basison",
    "wof:placetype":"venue"
},
  "geometry": {"coordinates":[5.890926,51.945934],"type":"Point"}
}