{
  "type": "Feature",
  "properties": {
    "addr:full":"Magelhaensstr 4 Breda Noord-Brabant 4812 RE",
    "addr:housenumber":"4",
    "addr:postcode":"4812 re",
    "addr:street":"Magelhaensstr",
    "iso:country":"NL",
    "sg:address":"Magelhaensstr 4",
    "sg:city":"Breda",
    "sg:orig_category":"Goudsmeden En Zilversmeden",
    "sg:phone":"+31 76 520 6170",
    "sg:postcode":"4812 RE",
    "sg:province":"Noord-Brabant",
    "wof:name":"Fiamma, Edelsmederij",
    "wof:placetype":"venue"
},
  "geometry": {"coordinates":[4.753958,51.576218],"type":"Point"}
}