{
  "type": "Feature",
  "properties": {
    "addr:full":"Westkadk 9 Nykerk Gld Gelderland 3861 MB",
    "addr:housenumber":"9",
    "addr:postcode":"3861 mb",
    "addr:street":"Westkadk;Gld Gelderland",
    "iso:country":"NL",
    "sg:address":"Westkadk 9",
    "sg:city":"Nykerk Gld",
    "sg:orig_category":"Makelaars En Adviseurs Onroerende Goederen",
    "sg:phone":"+31 33 245 0624",
    "sg:postcode":"3861 MB",
    "sg:province":"Gelderland",
    "sg:website":"http://www.vanderwerfvastgoed.nl",
    "wof:name":"Werf Nijkerk, Van Der",
    "wof:placetype":"venue"
},
  "geometry": {"coordinates":[5.480255,52.228008],"type":"Point"}
}