{
  "type": "Feature",
  "properties": {
    "addr:full":"Fluessenstraat 15 Lemmer Friesland 8531 RE",
    "addr:housenumber":"15",
    "addr:postcode":"8531 re",
    "addr:street":"Fluessenstraat",
    "iso:country":"NL",
    "sg:address":"Fluessenstraat 15",
    "sg:city":"Lemmer",
    "sg:orig_category":"Watersport-, Sport- And Kampeerbenodigdheden Verhuur",
    "sg:phone":"+31 514 565 363",
    "sg:postcode":"8531 RE",
    "sg:province":"Friesland",
    "wof:name":"Sail Charter Lemmer",
    "wof:placetype":"venue"
},
  "geometry": {"coordinates":[5.6972799301,52.8494300842],"type":"Point"}
}