{
  "type": "Feature",
  "properties": {
    "addr:full":"Olympiakd 55 Amsterdam North Holland 1076 XX",
    "addr:housenumber":"55",
    "addr:postcode":"1076 xx",
    "addr:street":"Olympiakd",
    "iso:country":"NL",
    "sg:address":"Olympiakd 55",
    "sg:city":"Amsterdam",
    "sg:orig_category":"Onderhoudswerken",
    "sg:phone":"+31 20 664 8069",
    "sg:postcode":"1076 XX",
    "sg:province":"North Holland",
    "wof:name":"Lelieveld, G",
    "wof:placetype":"venue"
},
  "geometry": {"coordinates":[4.858583,52.347115],"type":"Point"}
}