{
  "type": "Feature",
  "properties": {
    "addr:full":"Spoorlaan 1 Groesbeek Gelderland 6562 AL",
    "addr:housenumber":"1",
    "addr:postcode":"6562",
    "addr:street":"Spoorlaan;Gelderland",
    "iso:country":"NL",
    "sg:address":"Spoorlaan 1",
    "sg:city":"Groesbeek",
    "sg:orig_category":"Supermarkten",
    "sg:phone":"+31 24 397 1348",
    "sg:postcode":"6562 AL",
    "sg:province":"Gelderland",
    "wof:name":"Edah",
    "wof:placetype":"venue"
},
  "geometry": {"coordinates":[5.934151,51.777321],"type":"Point"}
}