{
  "type": "Feature",
  "properties": {
    "addr:full":"Burg Roosstr 24-26 Lekkerkerk Zuid-Holland 2941 AC",
    "addr:housenumber":"24-26",
    "addr:postcode":"2941 ac",
    "addr:street":"Burg",
    "iso:country":"NL",
    "sg:address":"Burg Roosstr 24-26",
    "sg:city":"Lekkerkerk",
    "sg:orig_category":"Huishoudelijke Apparaten En Artikelen",
    "sg:phone":"+31 180 661 869",
    "sg:postcode":"2941 AC",
    "sg:province":"Zuid-Holland",
    "sg:website":"http://www.ep-deridderelektronics.nl",
    "wof:name":"Ridder, H De",
    "wof:placetype":"venue"
},
  "geometry": {"coordinates":[4.684269,51.89592],"type":"Point"}
}