{
  "type": "Feature",
  "properties": {
    "addr:full":"Voorstraat 139 Egmond Aan Zee North Holland 1931 AK",
    "addr:housenumber":"139",
    "addr:postcode":"1931 ak",
    "addr:street":"Voorstraat",
    "iso:country":"NL",
    "sg:address":"Voorstraat 139",
    "sg:city":"Egmond Aan Zee",
    "sg:classifiers":[
        {
            "category":"Fast Food",
            "type":"Food & Drink"
        }
    ],
    "sg:phone":"+31 72 506 1382",
    "sg:postcode":"1931 AK",
    "sg:province":"North Holland",
    "sg:tags":[
        "afhaal",
        "restaurant"
    ],
    "wof:name":"Snack Inn",
    "wof:placetype":"venue"
},
  "geometry": {"coordinates":[4.622552,52.617725],"type":"Point"}
}