{
  "type": "Feature",
  "properties": {
    "iso:country":"NL",
    "sg:address":"Reekerkoogln 14A",
    "sg:city":"Heerhugowaard",
    "sg:orig_category":"Kappers",
    "sg:phone":"+31 72 572 9429",
    "sg:postcode":"1705 AK",
    "sg:province":"North Holland",
    "wof:name":"Image Line",
    "wof:placetype":"venue"
},
  "geometry": {"coordinates":[4.827521801,52.6651954651],"type":"Point"}
}