{
  "type": "Feature",
  "properties": {
    "iso:country":"NL",
    "sg:address":"Vondelstraat 47",
    "sg:city":"Amsterdam",
    "sg:orig_category":"Public Relationbureaus",
    "sg:phone":"+31 20 412 0327",
    "sg:postcode":"1054 GJ",
    "sg:province":"Noord-Holland",
    "wof:name":"Nicoline Teunissen Public Relations",
    "wof:placetype":"venue"
},
  "geometry": {"coordinates":[4.875687,52.361687],"type":"Point"}
}