{
  "type": "Feature",
  "properties": {
    "addr:full":"Kanaalstraat 22 Oosterhout Nb Noord-Brabant 4905 BJ",
    "addr:housenumber":"22",
    "addr:postcode":"4905 bj",
    "addr:street":"Kanaalstraat",
    "iso:country":"NL",
    "sg:address":"Kanaalstraat 22",
    "sg:city":"Oosterhout Nb",
    "sg:orig_category":"Autokeuringen",
    "sg:phone":"+31 162 454 134",
    "sg:postcode":"4905 BJ",
    "sg:province":"Noord-Brabant",
    "wof:name":"Mega Carwash Oosterhout",
    "wof:placetype":"venue"
},
  "geometry": {"coordinates":[4.85625,51.643051],"type":"Point"}
}