{
  "type": "Feature",
  "properties": {
    "addr:full":"Buitenkruierstraat 2 Almere Flevoland 1333 EB",
    "addr:housenumber":"2",
    "addr:postcode":"1333 eb",
    "addr:street":"Buitenkruierstraat;Flevoland",
    "iso:country":"NL",
    "sg:address":"Buitenkruierstraat 2",
    "sg:city":"Almere",
    "sg:classifiers":[
        {
            "category":"Education",
            "subcategory":"Preschool",
            "type":"Public Place"
        }
    ],
    "sg:phone":"+31 36 532 1041",
    "sg:postcode":"1333 EB",
    "sg:province":"Flevoland",
    "sg:tags":[
        "kleuteronderwijs",
        "basis-"
    ],
    "wof:name":"De Tjasker School",
    "wof:placetype":"venue"
},
  "geometry": {"coordinates":[5.271168,52.39978],"type":"Point"}
}