{
  "type": "Feature",
  "properties": {
    "addr:full":"Nieuwewg 1 Schelluinen Zuid-Holland 4209 BA",
    "addr:housenumber":"1",
    "addr:postcode":"4209 ba",
    "addr:street":"Nieuwewg",
    "iso:country":"NL",
    "sg:address":"Nieuwewg 1",
    "sg:city":"Schelluinen",
    "sg:orig_category":"Loonbedrijven",
    "sg:phone":"+31 183 623 382",
    "sg:postcode":"4209 BA",
    "sg:province":"Zuid-Holland",
    "wof:name":"Kreij, W H De",
    "wof:placetype":"venue"
},
  "geometry": {"coordinates":[4.941309,51.851578],"type":"Point"}
}