{
  "type": "Feature",
  "properties": {
    "addr:full":"Westeind 53 Papendrecht Zuid-Holland 3351 AL",
    "addr:housenumber":"53",
    "addr:postcode":"3351 al",
    "addr:street":"Westeind",
    "iso:country":"NL",
    "sg:address":"Westeind 53",
    "sg:city":"Papendrecht",
    "sg:orig_category":"Goederenvervoer Over De Weg",
    "sg:phone":"+31 78 615 0546",
    "sg:postcode":"3351 AL",
    "sg:province":"Zuid-Holland",
    "wof:name":"Firma Verdoorn",
    "wof:placetype":"venue"
},
  "geometry": {"coordinates":[4.679662,51.826038],"type":"Point"}
}