{
  "type": "Feature",
  "properties": {
    "addr:full":"Radboudtraverse 22 Utrecht Utrecht 3511 CP",
    "addr:housenumber":"22",
    "addr:postcode":"3511 cp",
    "addr:street":"Radboudtraverse",
    "iso:country":"NL",
    "sg:address":"Radboudtraverse 22",
    "sg:city":"Utrecht",
    "sg:orig_category":"Herenmodezaken",
    "sg:phone":"+31 30 231 9851",
    "sg:postcode":"3511 CP",
    "sg:province":"Utrecht",
    "wof:name":"Yank'S",
    "wof:placetype":"venue"
},
  "geometry": {"coordinates":[5.113517,52.091114],"type":"Point"}
}