{
  "type": "Feature",
  "properties": {
    "addr:full":"Landjuweel 11 Bergeyk Noord-Brabant 5571 ML",
    "addr:housenumber":"11",
    "addr:postcode":"5571 ml",
    "addr:street":"Landjuweel",
    "iso:country":"NL",
    "sg:address":"Landjuweel 11",
    "sg:city":"Bergeyk",
    "sg:orig_category":"Kappers",
    "sg:phone":"+31 497 512 331",
    "sg:postcode":"5571 ML",
    "sg:province":"Noord-Brabant",
    "wof:name":"Marieke",
    "wof:placetype":"venue"
},
  "geometry": {"coordinates":[5.374252,51.32502],"type":"Point"}
}