{
  "type": "Feature",
  "properties": {
    "addr:full":"Van Oldenbarneveldtstr 15 Arnhem Gelderland 6828 ZM",
    "addr:housenumber":"15",
    "addr:postcode":"6828 zm",
    "iso:country":"NL",
    "sg:address":"Van Oldenbarneveldtstr 15",
    "sg:city":"Arnhem",
    "sg:orig_category":"Hout Gh",
    "sg:phone":"+31 26 442 5904",
    "sg:postcode":"6828 ZM",
    "sg:province":"Gelderland",
    "wof:name":"Houthandel Klugkist Bv",
    "wof:placetype":"venue"
},
  "geometry": {"coordinates":[5.920862,51.977989],"type":"Point"}
}