{
  "type": "Feature",
  "properties": {
    "iso:country":"NL",
    "sg:address":"Overschiese Dorpsstraat 67",
    "sg:city":"Rotterdam",
    "sg:orig_category":"Bloemen En Planten - Decoratie",
    "sg:phone":"+31 10 415 8082",
    "sg:postcode":"3043 CN",
    "sg:province":"Zuid-Holland",
    "wof:name":"Es Stijl",
    "wof:placetype":"venue"
},
  "geometry": {"coordinates":[4.420534,51.939201],"type":"Point"}
}