{
  "type": "Feature",
  "properties": {
    "iso:country":"NL",
    "sg:address":"Nachtegaal 5",
    "sg:city":"Weert",
    "sg:orig_category":"Boekhouders",
    "sg:phone":"+31 495 534 123",
    "sg:postcode":"6005 KX",
    "sg:province":"Limburg",
    "wof:name":"Administratiekantoor J. Smeets",
    "wof:placetype":"venue"
},
  "geometry": {"coordinates":[5.721565,51.24197],"type":"Point"}
}