{
  "type": "Feature",
  "properties": {
    "addr:full":"Markt 6 Weert Limburg 6001 EK",
    "addr:housenumber":"6",
    "addr:postcode":"6001 ek",
    "addr:street":"Markt",
    "iso:country":"NL",
    "sg:address":"Markt 6",
    "sg:city":"Weert",
    "sg:orig_category":"Adviesbureaus Bouwkunde",
    "sg:phone":"+31 495 453 540",
    "sg:postcode":"6001 EK",
    "sg:province":"Limburg",
    "sg:website":"http://www.kg-bouwpro.nl",
    "wof:name":"K & G Bouwprojectmanagement Bv",
    "wof:placetype":"venue"
},
  "geometry": {"coordinates":[5.706399,51.253628],"type":"Point"}
}