{
  "type": "Feature",
  "properties": {
    "addr:full":"Griftpark 8 Woudenberg Utrecht 3931 XN",
    "addr:housenumber":"8",
    "addr:postcode":"3931 xn",
    "addr:street":"Griftpark",
    "iso:country":"NL",
    "sg:address":"Griftpark 8",
    "sg:city":"Woudenberg",
    "sg:orig_category":"Mensendieck - Oefentherapeuten",
    "sg:phone":"+31 33 286 2666",
    "sg:postcode":"3931 XN",
    "sg:province":"Utrecht",
    "wof:name":"Schuffel-Sleutel, P J",
    "wof:placetype":"venue"
},
  "geometry": {"coordinates":[5.403497,52.085907],"type":"Point"}
}