{
  "type": "Feature",
  "properties": {
    "addr:full":"Marktstraat 22 Uden Noord-Brabant 5401 GH",
    "addr:housenumber":"22",
    "addr:postcode":"5401 gh",
    "addr:street":"Marktstraat",
    "iso:country":"NL",
    "sg:address":"Marktstraat 22",
    "sg:city":"Uden",
    "sg:orig_category":"Drogisterijen",
    "sg:phone":"+31 413 262 146",
    "sg:postcode":"5401 GH",
    "sg:province":"Noord-Brabant",
    "wof:name":"Hema",
    "wof:placetype":"venue"
},
  "geometry": {"coordinates":[5.613817,51.657612],"type":"Point"}
}