{
  "type": "Feature",
  "properties": {
    "addr:full":"Bloemendaalwg 38 Waalwyk Noord-Brabant 5143 NB",
    "addr:housenumber":"38",
    "addr:postcode":"5143 nb",
    "addr:street":"Bloemendaalwg",
    "iso:country":"NL",
    "sg:address":"Bloemendaalwg 38",
    "sg:city":"Waalwyk",
    "sg:orig_category":"Begrafenisverzorging",
    "sg:phone":"+31 416 336 451",
    "sg:postcode":"5143 NB",
    "sg:province":"Noord-Brabant",
    "wof:name":"Bloemendaal",
    "wof:placetype":"venue"
},
  "geometry": {"coordinates":[5.098595,51.68858],"type":"Point"}
}