{
  "type": "Feature",
  "properties": {
    "iso:country":"NL",
    "sg:address":"Ophuijstraweg 3",
    "sg:city":"Driesum",
    "sg:orig_category":"Verlichting And Huishoudartikelen",
    "sg:phone":"+31 511 425 200",
    "sg:postcode":"9114 RC",
    "sg:province":"Provincie Friesland",
    "wof:name":"Stoffeerderij Haakma",
    "wof:placetype":"venue"
},
  "geometry": {"coordinates":[6.04257,53.294239],"type":"Point"}
}