{
  "type": "Feature",
  "properties": {
    "addr:full":"Heuvel 40 St Oedenrode North Brabant 5492 AD",
    "addr:housenumber":"40",
    "addr:postcode":"5492 ad",
    "addr:street":"Heuvel",
    "iso:country":"NL",
    "sg:address":"Heuvel 40",
    "sg:city":"St Oedenrode",
    "sg:orig_category":"Juweliers",
    "sg:phone":"+31 413 472 784",
    "sg:postcode":"5492 AD",
    "sg:province":"North Brabant",
    "wof:name":"Opaal",
    "wof:placetype":"venue"
},
  "geometry": {"coordinates":[5.459413,51.56242],"type":"Point"}
}