{
  "type": "Feature",
  "properties": {
    "addr:full":"Barrierweg 13 Eindhoven Noord-Brabant 5622 CL",
    "addr:housenumber":"13",
    "addr:postcode":"5622",
    "addr:street":"Barrierweg",
    "iso:country":"NL",
    "sg:address":"Barrierweg 13",
    "sg:city":"Eindhoven",
    "sg:orig_category":"Werving And Selectie Van Tijdelijk Personeel And Uitzendkantoren",
    "sg:phone":"+31 6 20636066",
    "sg:postcode":"5622 CL",
    "sg:province":"Noord-Brabant",
    "wof:name":"Dino'S Uitzendorganisatie",
    "wof:placetype":"venue"
},
  "geometry": {"coordinates":[5.4660010338,51.4612770081],"type":"Point"}
}