{
  "type": "Feature",
  "properties": {
    "addr:full":"Carolinenberg 41 Zoetermeer South Holland 2716 EP",
    "addr:housenumber":"41",
    "addr:postcode":"2716 ep",
    "addr:street":"Carolinenberg",
    "iso:country":"NL",
    "sg:address":"Carolinenberg 41",
    "sg:city":"Zoetermeer",
    "sg:orig_category":"Verzekeringen",
    "sg:phone":"+31 79 329 0986",
    "sg:postcode":"2716 EP",
    "sg:province":"South Holland",
    "wof:name":"Dykstra & Ter Avest Consultants Bv",
    "wof:placetype":"venue"
},
  "geometry": {"coordinates":[4.45994,52.054821],"type":"Point"}
}