{
  "type": "Feature",
  "properties": {
    "addr:full":"Postbus 59654 Amsterdam Drenthe 1040 LD",
    "addr:housenumber":"59654",
    "addr:postcode":"1040 ld",
    "addr:street":"Postbus",
    "iso:country":"NL",
    "sg:address":"Postbus 59654",
    "sg:city":"Amsterdam",
    "sg:orig_category":"Schilders",
    "sg:phone":"+31 6 22301153",
    "sg:postcode":"1040 LD",
    "sg:province":"Drenthe",
    "wof:name":"Djamal",
    "wof:placetype":"venue"
},
  "geometry": {"coordinates":[4.89205,52.37355],"type":"Point"}
}