{
  "type": "Feature",
  "properties": {
    "addr:full":"Dorpsstraat 105 Nibbixwoud Noord-Holland 1688 CD",
    "addr:housenumber":"105",
    "addr:postcode":"1688 cd",
    "addr:street":"Dorpsstraat",
    "iso:country":"NL",
    "sg:address":"Dorpsstraat 105",
    "sg:city":"Nibbixwoud",
    "sg:orig_category":"Meubelreparatie And -Restauratie",
    "sg:phone":"+31 229 573 052",
    "sg:postcode":"1688 CD",
    "sg:province":"Noord-Holland",
    "wof:name":"Meubelstoffeerderij Schavemaker",
    "wof:placetype":"venue"
},
  "geometry": {"coordinates":[5.069926,52.691216],"type":"Point"}
}