{
  "type": "Feature",
  "properties": {
    "addr:full":"Smeetswg 6A Waarland Montana 1738 DK",
    "addr:housenumber":"6a",
    "addr:postcode":"1738 dk",
    "addr:street":"Smeetswg;Montana",
    "iso:country":"NL",
    "sg:address":"Smeetswg 6A",
    "sg:city":"Waarland",
    "sg:orig_category":"Projectinrichting",
    "sg:phone":"+31 226 421 491",
    "sg:postcode":"1738 DK",
    "sg:province":"Montana",
    "sg:website":"http://www.drothenic.com",
    "wof:name":"Drothenic",
    "wof:placetype":"venue"
},
  "geometry": {"coordinates":[-115.30186500000001,48.500385],"type":"Point"}
}