{
  "type": "Feature",
  "properties": {
    "addr:full":"Algolweg 6 Amersfoort Utrecht 3821 BH",
    "addr:housenumber":"6",
    "addr:postcode":"3821 bh",
    "addr:street":"Algolweg",
    "iso:country":"NL",
    "sg:address":"Algolweg 6",
    "sg:city":"Amersfoort",
    "sg:orig_category":"Binnenhuisarchitecten",
    "sg:phone":"+31 33 455 6687",
    "sg:postcode":"3821 BH",
    "sg:province":"Utrecht",
    "wof:name":"Finitouch Interieurbouw Bv",
    "wof:placetype":"venue"
},
  "geometry": {"coordinates":[5.415372,52.175262],"type":"Point"}
}