{
  "type": "Feature",
  "properties": {
    "addr:full":"Veldhovenring 111 Tilburg North Brabant 5041 BB",
    "addr:housenumber":"111",
    "addr:postcode":"5041 bb",
    "addr:street":"Veldhovenring",
    "iso:country":"NL",
    "sg:address":"Veldhovenring 111",
    "sg:city":"Tilburg",
    "sg:orig_category":"Verzekeringen - Verzekeringskantoren",
    "sg:phone":"+31 13 535 1255",
    "sg:postcode":"5041 BB",
    "sg:province":"North Brabant",
    "wof:name":"Neggers Bv",
    "wof:placetype":"venue"
},
  "geometry": {"coordinates":[5.081954,51.567356],"type":"Point"}
}