{
  "type": "Feature",
  "properties": {
    "iso:country":"NL",
    "sg:address":"Richtersweg 22",
    "sg:city":"Enschede",
    "sg:orig_category":"Goederenvervoer Over De Weg",
    "sg:phone":"+31 53 435 9567",
    "sg:postcode":"7521 BW",
    "sg:province":"Overijssel",
    "wof:name":"Mark Lampe Internationaal Transport",
    "wof:placetype":"venue"
},
  "geometry": {"coordinates":[6.877702,52.223385],"type":"Point"}
}