{
  "type": "Feature",
  "properties": {
    "iso:country":"NL",
    "sg:address":"Minderbroed Sngl 17",
    "sg:city":"Roermond",
    "sg:orig_category":"Juridische Adviseurs",
    "sg:phone":"+31 475 339 902",
    "sg:postcode":"6041 KH",
    "sg:province":"Limburg",
    "sg:website":"http://www.quod.nl",
    "wof:name":"Quod",
    "wof:placetype":"venue"
},
  "geometry": {"coordinates":[5.985786,51.191071],"type":"Point"}
}