{
  "type": "Feature",
  "properties": {
    "addr:full":"Rijnzichtlaan 20 Bunnik Utrecht 3981 BT",
    "addr:housenumber":"20",
    "addr:postcode":"3981 bt",
    "addr:street":"Rijnzichtlaan",
    "iso:country":"NL",
    "sg:address":"Rijnzichtlaan 20",
    "sg:city":"Bunnik",
    "sg:orig_category":"Kinderopvang Behalve Thuis",
    "sg:phone":"+31 30 656 7232",
    "sg:postcode":"3981 BT",
    "sg:province":"Utrecht",
    "wof:name":"Het Hulstbosje",
    "wof:placetype":"venue"
},
  "geometry": {"coordinates":[5.207749,52.065033],"type":"Point"}
}