{
  "type": "Feature",
  "properties": {
    "addr:full":"Steenwykerveld 24A De Kwakel Noord-Holland 1424 RR",
    "addr:housenumber":"24a",
    "addr:postcode":"1424 rr",
    "addr:street":"Steenwykerveld",
    "iso:country":"NL",
    "sg:address":"Steenwykerveld 24A",
    "sg:city":"De Kwakel",
    "sg:orig_category":"Meubelen - Fabrieken En Groothandel",
    "sg:phone":"+31 297 581 070",
    "sg:postcode":"1424 RR",
    "sg:province":"Noord-Holland",
    "wof:name":"Rvr",
    "wof:placetype":"venue"
},
  "geometry": {"coordinates":[4.781389,52.231628],"type":"Point"}
}