{
  "type": "Feature",
  "properties": {
    "addr:full":"Hondsrug 15 Dronten Flevoland 8251 VP",
    "addr:housenumber":"15",
    "addr:postcode":"8251 vp",
    "addr:street":"Hondsrug;Flevoland",
    "iso:country":"NL",
    "sg:address":"Hondsrug 15",
    "sg:city":"Dronten",
    "sg:orig_category":"Kinderopvang Behalve Thuis",
    "sg:phone":"+31 321 316 543",
    "sg:postcode":"8251 VP",
    "sg:province":"Flevoland",
    "wof:name":"Pemari",
    "wof:placetype":"venue"
},
  "geometry": {"coordinates":[5.7252,52.51263],"type":"Point"}
}