{
  "type": "Feature",
  "properties": {
    "addr:full":"Delta Industriewg 9 Stellendam Zuid-Holland 3251 LX",
    "addr:housenumber":"9",
    "addr:postcode":"3251 lx",
    "addr:street":"Industriewg",
    "iso:country":"NL",
    "sg:address":"Delta Industriewg 9",
    "sg:city":"Stellendam",
    "sg:orig_category":"Kunststoffen - Fabrieken En Groothandel",
    "sg:phone":"+31 187 492 611",
    "sg:postcode":"3251 LX",
    "sg:province":"Zuid-Holland",
    "wof:name":"Brands Bv",
    "wof:placetype":"venue"
},
  "geometry": {"coordinates":[4.039299,51.817844],"type":"Point"}
}