{
  "type": "Feature",
  "properties": {
    "addr:full":"Vilstersestr 3A Lemelerveld Overijssel 8152 AA",
    "addr:housenumber":"3a",
    "addr:postcode":"8152 aa",
    "addr:street":"Vilstersestr",
    "iso:country":"NL",
    "sg:address":"Vilstersestr 3A",
    "sg:city":"Lemelerveld",
    "sg:classifiers":[
        {
            "category":"Retail",
            "subcategory":"Auto Repair",
            "type":"Services"
        }
    ],
    "sg:phone":"+31 572 372 400",
    "sg:postcode":"8152 AA",
    "sg:province":"Overijssel",
    "sg:tags":[
        "garage"
    ],
    "wof:name":"Duerink, Autobedrijf H",
    "wof:placetype":"venue"
},
  "geometry": {"coordinates":[6.341674,52.446518],"type":"Point"}
}