{
  "type": "Feature",
  "properties": {
    "addr:full":"Hogehilweg 8 Amsterdam Zuidoost North Holland 1101 CC",
    "addr:housenumber":"8",
    "addr:postcode":"1101 cc",
    "addr:street":"Hogehilweg",
    "iso:country":"NL",
    "sg:address":"Hogehilweg 8",
    "sg:city":"Amsterdam Zuidoost",
    "sg:classifiers":[
        {
            "category":"Professional",
            "subcategory":"Accounting & Tax Preparation",
            "type":"Services"
        }
    ],
    "sg:phone":"+31 20 451 5060",
    "sg:postcode":"1101 CC",
    "sg:province":"North Holland",
    "sg:tags":[
        "accountant"
    ],
    "wof:name":"De Keijzer Nipius & Co",
    "wof:placetype":"venue"
},
  "geometry": {"coordinates":[4.947948,52.305847],"type":"Point"}
}