{
  "type": "Feature",
  "properties": {
    "addr:full":"Bentinckstr 6 Nykerk Gld Gelderland 3861 KW",
    "addr:housenumber":"6",
    "addr:postcode":"3861 kw",
    "addr:street":"Bentinckstr;Gld Gelderland",
    "iso:country":"NL",
    "sg:address":"Bentinckstr 6",
    "sg:city":"Nykerk Gld",
    "sg:orig_category":"Architecten En Architectenbureaus",
    "sg:phone":"+31 33 245 0808",
    "sg:postcode":"3861 KW",
    "sg:province":"Gelderland",
    "sg:website":"http://www.frankvanhaarlem.nl",
    "wof:name":"Frank Van Haarlem Architect Bna",
    "wof:placetype":"venue"
},
  "geometry": {"coordinates":[5.484901,52.227097],"type":"Point"}
}