{
  "type": "Feature",
  "properties": {
    "addr:full":"B Edgarln 13 Amstelveen Noord-Holland 1187 HG",
    "addr:housenumber":"13",
    "addr:postcode":"1187 hg",
    "iso:country":"NL",
    "sg:address":"B Edgarln 13",
    "sg:city":"Amstelveen",
    "sg:orig_category":"Administratie- En Boekhoudkantoren",
    "sg:phone":"+31 20 453 5359",
    "sg:postcode":"1187 HG",
    "sg:province":"Noord-Holland",
    "wof:name":"B & D",
    "wof:placetype":"venue"
},
  "geometry": {"coordinates":[4.856945,52.303444],"type":"Point"}
}