{
  "type": "Feature",
  "properties": {
    "iso:country":"NL",
    "sg:address":"Wyksestr 39A",
    "sg:city":"Bergharen",
    "sg:orig_category":"Fotoreportages",
    "sg:phone":"+31 487 591 300",
    "sg:postcode":"6617 BZ",
    "sg:province":"Gelderland",
    "wof:name":"Bergharen",
    "wof:placetype":"venue"
},
  "geometry": {"coordinates":[5.67847,51.852596],"type":"Point"}
}