{
  "type": "Feature",
  "properties": {
    "addr:full":"Pr Bernhardstr 20 Landgraaf Limburg 6373 KK",
    "addr:housenumber":"20",
    "addr:postcode":"6373 kk",
    "iso:country":"NL",
    "sg:address":"Pr Bernhardstr 20",
    "sg:city":"Landgraaf",
    "sg:classifiers":[
        {
            "category":"Personal",
            "subcategory":"Nail Salon",
            "type":"Services"
        }
    ],
    "sg:phone":"+31 45 531 9139",
    "sg:postcode":"6373 KK",
    "sg:province":"Limburg",
    "sg:tags":[
        "pedicure"
    ],
    "wof:name":"Peters-Meijerhof, M",
    "wof:placetype":"venue"
},
  "geometry": {"coordinates":[6.034029,50.908886],"type":"Point"}
}