{
  "type": "Feature",
  "properties": {
    "addr:full":"Molenwg 10A Laren Nh North Holland 1251 LT",
    "addr:housenumber":"10a",
    "addr:postcode":"1251 lt",
    "addr:street":"Molenwg;Nh North",
    "iso:country":"NL",
    "sg:address":"Molenwg 10A",
    "sg:city":"Laren Nh",
    "sg:orig_category":"Meubelstoffering",
    "sg:phone":"+31 35 531 1473",
    "sg:postcode":"1251 LT",
    "sg:province":"North Holland",
    "wof:name":"Ederveen Meubelstoffering",
    "wof:placetype":"venue"
},
  "geometry": {"coordinates":[5.221861,52.253307],"type":"Point"}
}