{
  "type": "Feature",
  "properties": {
    "iso:country":"NL",
    "sg:address":"Postbus 27",
    "sg:city":"Overloon",
    "sg:orig_category":"Wasserijen",
    "sg:phone":"+31 478 642 728",
    "sg:postcode":"5825 ZG",
    "sg:province":"Noord-Brabant",
    "wof:name":"Duo Sal",
    "wof:placetype":"venue"
},
  "geometry": {"coordinates":[5.9463100433,51.5712547302],"type":"Point"}
}