{
  "type": "Feature",
  "properties": {
    "addr:full":"Biezen 49 Boskoop Zuid-Holland 2771 CR",
    "addr:housenumber":"49",
    "addr:postcode":"2771 cr",
    "addr:street":"Biezen",
    "iso:country":"NL",
    "sg:address":"Biezen 49",
    "sg:city":"Boskoop",
    "sg:orig_category":"Bloemen And Planten",
    "sg:phone":"+31 172 214 741",
    "sg:postcode":"2771 CR",
    "sg:province":"Zuid-Holland",
    "wof:name":"Gebroeders Boer Bv",
    "wof:placetype":"venue"
},
  "geometry": {"coordinates":[4.666604,52.078194],"type":"Point"}
}