{
  "type": "Feature",
  "properties": {
    "iso:country":"NL",
    "sg:address":"V Sytzamawg 39",
    "sg:city":"Driesum",
    "sg:orig_category":"Bedrijfskleding",
    "sg:phone":"+31 511 424 349",
    "sg:postcode":"9114 RV",
    "sg:province":"Friesland",
    "sg:website":"http://www.nofriesland.nl/agrohandel",
    "wof:name":"Wiersma, Agrarische Handel",
    "wof:placetype":"venue"
},
  "geometry": {"coordinates":[6.045774,53.297764],"type":"Point"}
}