{
  "type": "Feature",
  "properties": {
    "addr:full":"De Clercqstr 8 Amsterdam Noord-Holland 1052 NC",
    "addr:housenumber":"8",
    "addr:postcode":"1052 nc",
    "iso:country":"NL",
    "sg:address":"De Clercqstr 8",
    "sg:city":"Amsterdam",
    "sg:orig_category":"Muziekinstrumenten En Bladmuziek",
    "sg:phone":"+31 20 685 1045",
    "sg:postcode":"1052 NC",
    "sg:province":"Noord-Holland",
    "sg:website":"http://www.safesound.nl",
    "wof:name":"Safe Sound",
    "wof:placetype":"venue"
},
  "geometry": {"coordinates":[4.873586,52.371742],"type":"Point"}
}