{
  "type": "Feature",
  "properties": {
    "addr:full":"Boterveen 20 Dwingeloo Drenthe 7991 PV",
    "addr:housenumber":"20",
    "addr:postcode":"7991 pv",
    "addr:street":"Boterveen",
    "iso:country":"NL",
    "sg:address":"Boterveen 20",
    "sg:city":"Dwingeloo",
    "sg:orig_category":"Etiketten",
    "sg:phone":"+31 6 25135784",
    "sg:postcode":"7991 PV",
    "sg:province":"Drenthe",
    "wof:name":"Loki Reclame Dwingelo",
    "wof:placetype":"venue"
},
  "geometry": {"coordinates":[6.398284,52.867962],"type":"Point"}
}