{
  "type": "Feature",
  "properties": {
    "addr:full":"Eenhoornstraat 2 Voorburg South Holland 2271 GL",
    "addr:housenumber":"2",
    "addr:postcode":"2271 gl",
    "addr:street":"Eenhoornstraat",
    "iso:country":"NL",
    "sg:address":"Eenhoornstraat 2",
    "sg:city":"Voorburg",
    "sg:orig_category":"Binnenhuisarchitecten",
    "sg:phone":"+31 70 387 1578",
    "sg:postcode":"2271 GL",
    "sg:province":"South Holland",
    "wof:name":"H.J.M. Dungelmann",
    "wof:placetype":"venue"
},
  "geometry": {"coordinates":[4.373731,52.076946],"type":"Point"}
}