{
  "type": "Feature",
  "properties": {
    "addr:full":"Lindewg 3-C Emmeloord Flevoland 8305 AM",
    "addr:housenumber":"3-c",
    "addr:postcode":"8305",
    "addr:street":"Lindewg;Flevoland",
    "iso:country":"NL",
    "sg:address":"Lindewg 3-C",
    "sg:city":"Emmeloord",
    "sg:orig_category":"Woningstoffeerders",
    "sg:phone":"+31 527 614 499",
    "sg:postcode":"8305 AM",
    "sg:province":"Flevoland",
    "sg:website":"http://www.venema-stoffering.nl",
    "wof:name":"Venema, S",
    "wof:placetype":"venue"
},
  "geometry": {"coordinates":[5.8055357933,52.7122917175],"type":"Point"}
}