{
  "type": "Feature",
  "properties": {
    "addr:full":"Ln V Meerdervoort 162 S Gravenhage South Holland 2517 BG",
    "addr:housenumber":"162",
    "addr:postcode":"2517",
    "addr:street":"Ln;Meerdervoort;S Gravenhage",
    "iso:country":"NL",
    "sg:address":"Ln V Meerdervoort 162",
    "sg:city":"S Gravenhage",
    "sg:orig_category":"Koelkasten - Reparatie En Onderhoud",
    "sg:phone":"+31 70 363 5715",
    "sg:postcode":"2517 BG",
    "sg:province":"South Holland",
    "wof:name":"Klerk & Ten Bruggencate",
    "wof:placetype":"venue"
},
  "geometry": {"coordinates":[4.28708,52.08667],"type":"Point"}
}