{
  "type": "Feature",
  "properties": {
    "addr:full":"Waalstr 20 Andelst Gelderland 6673 MB",
    "addr:housenumber":"20",
    "addr:postcode":"6673 mb",
    "addr:street":"Waalstr;Gelderland",
    "iso:country":"NL",
    "sg:address":"Waalstr 20",
    "sg:city":"Andelst",
    "sg:orig_category":"Adviesbureaus Bedrijfsorganisatie",
    "sg:phone":"+31 488 420 727",
    "sg:postcode":"6673 MB",
    "sg:province":"Gelderland",
    "wof:name":"Fim Bv",
    "wof:placetype":"venue"
},
  "geometry": {"coordinates":[5.739102,51.891457],"type":"Point"}
}