{
  "type": "Feature",
  "properties": {
    "iso:country":"NL",
    "sg:address":"Kranenbroek 1",
    "sg:city":"Helmond",
    "sg:orig_category":"Pluimveehouderijen",
    "sg:phone":"+31 492 430 560",
    "sg:postcode":"5707 DC",
    "sg:province":"Noord-Brabant",
    "wof:name":"A. Manders",
    "wof:placetype":"venue"
},
  "geometry": {"coordinates":[5.5984458923,51.4605712891],"type":"Point"}
}