{
  "type": "Feature",
  "properties": {
    "iso:country":"NL",
    "sg:address":"Hagedis 2",
    "sg:city":"Huizen",
    "sg:orig_category":"Verzekeringen",
    "sg:phone":"+31 35 526 2712",
    "sg:postcode":"1275 BR",
    "sg:province":"Noord-Holland",
    "wof:name":"Assurantie- En Administratie- Kantoor C.",
    "wof:placetype":"venue"
},
  "geometry": {"coordinates":[5.265606,52.291882],"type":"Point"}
}