{
  "type": "Feature",
  "properties": {
    "addr:full":"Mendelssohnstr 78 Waalwyk Noord-Brabant 5144 GH",
    "addr:housenumber":"78",
    "addr:postcode":"5144 gh",
    "addr:street":"Mendelssohnstr",
    "iso:country":"NL",
    "sg:address":"Mendelssohnstr 78",
    "sg:city":"Waalwyk",
    "sg:orig_category":"Geluidsopnamestudio'S",
    "sg:phone":"+31 416 336 255",
    "sg:postcode":"5144 GH",
    "sg:province":"Noord-Brabant",
    "wof:name":"Arrow",
    "wof:placetype":"venue"
},
  "geometry": {"coordinates":[5.065323,51.680733],"type":"Point"}
}