{
  "type": "Feature",
  "properties": {
    "addr:full":"Roosjeswg 14 Domburg Zeeland 4357 ED",
    "addr:housenumber":"14",
    "addr:postcode":"4357 ed",
    "addr:street":"Roosjeswg",
    "iso:country":"NL",
    "sg:address":"Roosjeswg 14",
    "sg:city":"Domburg",
    "sg:classifiers":[
        {
            "category":"Home & Garden",
            "subcategory":"Building Materials",
            "type":"Retail Goods"
        }
    ],
    "sg:phone":"+31 118 582 749",
    "sg:postcode":"4357 ED",
    "sg:province":"Zeeland",
    "sg:tags":[
        "hout",
        "en",
        "board",
        "triplex"
    ],
    "wof:name":"Domburg Bv",
    "wof:placetype":"venue"
},
  "geometry": {"coordinates":[3.505819,51.556507],"type":"Point"}
}