{
  "type": "Feature",
  "properties": {
    "addr:full":"Storkstr 12 Cpe Zoetermeer Zuid-Holland 2722 NN",
    "addr:housenumber":"12",
    "addr:postcode":"2722 nn",
    "addr:street":"Storkstr",
    "iso:country":"NL",
    "sg:address":"Storkstr 12 Cpe",
    "sg:city":"Zoetermeer",
    "sg:orig_category":"Horecabenodigdheden",
    "sg:phone":"+31 79 330 4330",
    "sg:postcode":"2722 NN",
    "sg:province":"Zuid-Holland",
    "wof:name":"Deli Xl",
    "wof:placetype":"venue"
},
  "geometry": {"coordinates":[4.51464,52.053829],"type":"Point"}
}