{
  "type": "Feature",
  "properties": {
    "addr:full":"Waterman 18 Lisse Zuid-Holland 2163 BC",
    "addr:housenumber":"18",
    "addr:postcode":"2163 bc",
    "addr:street":"Waterman",
    "iso:country":"NL",
    "sg:address":"Waterman 18",
    "sg:city":"Lisse",
    "sg:orig_category":"Onderhoudswerken",
    "sg:phone":"+31 252 417 995",
    "sg:postcode":"2163 BC",
    "sg:province":"Zuid-Holland",
    "wof:name":"Tuan Klussenman",
    "wof:placetype":"venue"
},
  "geometry": {"coordinates":[4.563576,52.264576],"type":"Point"}
}