{
  "type": "Feature",
  "properties": {
    "addr:full":"Aalsmeerderwg 602 Rozenburg Nh Noord-Holland 1437 EJ",
    "addr:housenumber":"602",
    "addr:postcode":"1437 ej",
    "iso:country":"NL",
    "sg:address":"Aalsmeerderwg 602",
    "sg:city":"Rozenburg Nh",
    "sg:orig_category":"Onroerende Goederen",
    "sg:phone":"+31 20 653 5352",
    "sg:postcode":"1437 EJ",
    "sg:province":"Noord-Holland",
    "wof:name":"Team Bv",
    "wof:placetype":"venue"
},
  "geometry": {"coordinates":[4.738822,52.282356],"type":"Point"}
}