{
  "type": "Feature",
  "properties": {
    "addr:full":"Hengelosestr 102 Oldenzaal NL.08 7572 BS",
    "addr:housenumber":"102;nl.08",
    "addr:postcode":"7572 bs",
    "iso:country":"NL",
    "sg:address":"Hengelosestr 102",
    "sg:city":"Oldenzaal",
    "sg:orig_category":"Wasmachines En Wasdrogers - Onderhoud En Reparatie",
    "sg:phone":"+31 541 519 090",
    "sg:postcode":"7572 BS",
    "sg:province":"NL.08",
    "wof:name":"Plentyparts",
    "wof:placetype":"venue"
},
  "geometry": {"coordinates":[6.920331955,52.3097877502],"type":"Point"}
}