{
  "type": "Feature",
  "properties": {
    "addr:full":"Oregondreef 31 Utrecht Utrecht 3565 BE",
    "addr:housenumber":"31",
    "addr:postcode":"3565",
    "addr:street":"Oregondreef",
    "iso:country":"NL",
    "sg:address":"Oregondreef 31",
    "sg:city":"Utrecht",
    "sg:orig_category":"Kantoorartikelen",
    "sg:phone":"+31 30 260 2590",
    "sg:postcode":"3565 BE",
    "sg:province":"Utrecht",
    "wof:name":"Gispen Utrecht",
    "wof:placetype":"venue"
},
  "geometry": {"coordinates":[5.0880551338,52.126701355],"type":"Point"}
}