{
  "type": "Feature",
  "properties": {
    "addr:full":"Cissy Van Marxveldtstr 80 Almere Flevoland 1321 LP",
    "addr:housenumber":"80",
    "addr:postcode":"1321 lp",
    "addr:street":"Cissy Van Marxveldtstr;Flevoland",
    "iso:country":"NL",
    "sg:address":"Cissy Van Marxveldtstr 80",
    "sg:city":"Almere",
    "sg:orig_category":"Stukadoorsbedrijven",
    "sg:phone":"+31 36 537 4546",
    "sg:postcode":"1321 LP",
    "sg:province":"Flevoland",
    "wof:name":"Flevostuc",
    "wof:placetype":"venue"
},
  "geometry": {"coordinates":[5.183922,52.352524],"type":"Point"}
}