{
  "type": "Feature",
  "properties": {
    "addr:full":"Koninginnewg 83 Kortenhoef Noord-Holland 1241 CX",
    "addr:housenumber":"83",
    "addr:postcode":"1241 cx",
    "addr:street":"Koninginnewg",
    "iso:country":"NL",
    "sg:address":"Koninginnewg 83",
    "sg:city":"Kortenhoef",
    "sg:orig_category":"Elektronica - Ontwikkeling En Groothandel",
    "sg:phone":"+31 35 656 1299",
    "sg:postcode":"1241 CX",
    "sg:province":"Noord-Holland",
    "wof:name":"Abevo",
    "wof:placetype":"venue"
},
  "geometry": {"coordinates":[5.120469,52.24765],"type":"Point"}
}