{
  "type": "Feature",
  "properties": {
    "addr:full":"Donk 8 Breda Noord-Brabant 4824 CS",
    "addr:housenumber":"8",
    "addr:postcode":"4824 cs",
    "addr:street":"Donk",
    "iso:country":"NL",
    "sg:address":"Donk 8",
    "sg:city":"Breda",
    "sg:orig_category":"Drogisterijen",
    "sg:phone":"+31 76 541 0383",
    "sg:postcode":"4824 CS",
    "sg:province":"Noord-Brabant",
    "wof:name":"Kruidvat",
    "wof:placetype":"venue"
},
  "geometry": {"coordinates":[4.74723,51.607185],"type":"Point"}
}