{
  "type": "Feature",
  "properties": {
    "iso:country":"NL",
    "sg:address":"Donk 8",
    "sg:city":"Breda",
    "sg:orig_category":"Drogisterijen",
    "sg:phone":"+31 76 541 0383",
    "sg:postcode":"4824 CS",
    "sg:province":"Noord-Brabant",
    "wof:name":"Kruidvat",
    "wof:placetype":"venue"
},
  "geometry": {"coordinates":[4.74723,51.607185],"type":"Point"}
}