{
  "type": "Feature",
  "properties": {
    "iso:country":"NL",
    "sg:address":"Schuttehei 3",
    "sg:city":"Melick",
    "sg:orig_category":"Artsen And Specialisten",
    "sg:phone":"+31 475 537 841",
    "sg:postcode":"6074 DK",
    "sg:province":"Limburg",
    "wof:name":"J.H.F. Tenten",
    "wof:placetype":"venue"
},
  "geometry": {"coordinates":[9.51668,56.2757],"type":"Point"}
}