{
  "type": "Feature",
  "properties": {
    "addr:full":"Koningsplein 8 Tilburg North Brabant 5038 WG",
    "addr:housenumber":"8",
    "addr:postcode":"5038 wg",
    "addr:street":"Koningsplein",
    "iso:country":"NL",
    "sg:address":"Koningsplein 8",
    "sg:city":"Tilburg",
    "sg:orig_category":"Bedrijfs- And Managementsconsultants",
    "sg:phone":"+31 13 542 9303",
    "sg:postcode":"5038 WG",
    "sg:province":"North Brabant",
    "wof:name":"Buro Kleinschalig Werk",
    "wof:placetype":"venue"
},
  "geometry": {"coordinates":[5.086664,51.553879],"type":"Point"}
}