{
  "type": "Feature",
  "properties": {
    "iso:country":"NL",
    "sg:address":"Van Boetzelaerlaan 292",
    "sg:city":"'S Gravenhage",
    "sg:orig_category":"Begrafenisondernemers",
    "sg:phone":"+31 70 306 6030",
    "sg:postcode":"2581 BC",
    "sg:province":"Zuid-Holland",
    "wof:name":"Uitvaartverzorging Atropos Bv",
    "wof:placetype":"venue"
},
  "geometry": {"coordinates":[4.270192,52.095463],"type":"Point"}
}