{
  "type": "Feature",
  "properties": {
    "addr:full":"Jensemaheerd 71 Groningen Groningen 9736 CE",
    "addr:housenumber":"71",
    "addr:postcode":"9736 ce",
    "addr:street":"Jensemaheerd",
    "iso:country":"NL",
    "sg:address":"Jensemaheerd 71",
    "sg:city":"Groningen",
    "sg:orig_category":"Zalenexploitatie",
    "sg:phone":"+31 50 541 7740",
    "sg:postcode":"9736 CE",
    "sg:province":"Groningen",
    "wof:name":"Ger Bos",
    "wof:placetype":"venue"
},
  "geometry": {"coordinates":[6.603636,53.252975],"type":"Point"}
}