{
  "type": "Feature",
  "properties": {
    "addr:full":"Schoolstr 18 Bedum Groningen 9781 JN",
    "addr:housenumber":"18",
    "addr:postcode":"9781 jn",
    "addr:street":"Schoolstr",
    "iso:country":"NL",
    "sg:address":"Schoolstr 18",
    "sg:city":"Bedum",
    "sg:orig_category":"Verzekeringen - Verzekeringskantoren",
    "sg:phone":"+31 50 301 2651",
    "sg:postcode":"9781 JN",
    "sg:province":"Groningen",
    "wof:name":"Scholtens Zakelijke Assuranti\u00ebn Bv",
    "wof:placetype":"venue"
},
  "geometry": {"coordinates":[6.602069,53.299026],"type":"Point"}
}