{
  "type": "Feature",
  "properties": {
    "addr:full":"Gravenbos 79 Hoofddorp North Holland 2134 LG",
    "addr:housenumber":"79",
    "addr:postcode":"2134 lg",
    "addr:street":"Gravenbos",
    "iso:country":"NL",
    "sg:address":"Gravenbos 79",
    "sg:city":"Hoofddorp",
    "sg:orig_category":"Bestratingen",
    "sg:phone":"+31 23 563 6040",
    "sg:postcode":"2134 LG",
    "sg:province":"North Holland",
    "wof:name":"Hout Hoveniersbedr, Vd",
    "wof:placetype":"venue"
},
  "geometry": {"coordinates":[4.660835,52.312397],"type":"Point"}
}