{
  "type": "Feature",
  "properties": {
    "addr:full":"Kathage 22 Wenum Wiesel Gelderland 7345 DN",
    "addr:housenumber":"22",
    "addr:postcode":"7345 dn",
    "addr:street":"Kathage",
    "iso:country":"NL",
    "sg:address":"Kathage 22",
    "sg:city":"Wenum Wiesel",
    "sg:orig_category":"Verhuur",
    "sg:phone":"+31 55 522 3834",
    "sg:postcode":"7345 DN",
    "sg:province":"Gelderland",
    "wof:name":"Toi Bv",
    "wof:placetype":"venue"
},
  "geometry": {"coordinates":[5.966666,52.24313],"type":"Point"}
}