{
  "type": "Feature",
  "properties": {
    "addr:full":"Hertzstraat 1 Ede Gld Gelderland 6716 BS",
    "addr:housenumber":"1;6716",
    "addr:postcode":"bs",
    "addr:street":"Hertzstraat;Gld Gelderland",
    "iso:country":"NL",
    "sg:address":"Hertzstraat 1",
    "sg:city":"Ede Gld",
    "sg:orig_category":"Pluimveehouderijen",
    "sg:phone":"+31 318 638 522",
    "sg:postcode":"6716 BS",
    "sg:province":"Gelderland",
    "wof:name":"Meller Poultry Service Bv",
    "wof:placetype":"venue"
},
  "geometry": {"coordinates":[5.625926,52.029274],"type":"Point"}
}