{
  "type": "Feature",
  "properties": {
    "addr:full":"Gulberg 30-32 Nuenen North Brabant 5674 TE",
    "addr:housenumber":"30-32",
    "addr:postcode":"5674 te",
    "addr:street":"Gulberg",
    "iso:country":"NL",
    "sg:address":"Gulberg 30-32",
    "sg:city":"Nuenen",
    "sg:orig_category":"Bloemen En Planten",
    "sg:phone":"+31 40 283 6672",
    "sg:postcode":"5674 TE",
    "sg:province":"North Brabant",
    "wof:name":"Gulberg Bv",
    "wof:placetype":"venue"
},
  "geometry": {"coordinates":[5.559523,51.44706],"type":"Point"}
}