{
  "type": "Feature",
  "properties": {
    "iso:country":"NL",
    "sg:address":"Dorpsweg 40",
    "sg:city":"Rotterdam",
    "sg:orig_category":"Diverse Kredietdiensten",
    "sg:postcode":"3083 LC",
    "sg:province":"Zuid-Holland",
    "wof:name":"Rabobank Geldautomaat",
    "wof:placetype":"venue"
},
  "geometry": {"coordinates":[4.473278,51.890369],"type":"Point"}
}