{
  "type": "Feature",
  "properties": {
    "addr:full":"Weteringschans 145 Amsterdam Noord-Holland 1017 SE",
    "addr:housenumber":"145",
    "addr:postcode":"1017 se",
    "addr:street":"Weteringschans",
    "iso:country":"NL",
    "sg:address":"Weteringschans 145",
    "sg:city":"Amsterdam",
    "sg:orig_category":"Glaszetten",
    "sg:phone":"+31 20 623 7157",
    "sg:postcode":"1017 SE",
    "sg:province":"Noord-Holland",
    "wof:name":"Peter Scherpenzeel Studio",
    "wof:placetype":"venue"
},
  "geometry": {"coordinates":[4.889647,52.35994],"type":"Point"}
}