{
  "type": "Feature",
  "properties": {
    "addr:full":"St Hubertusplaats 33 Tollebeek Flevoland 8309 AA",
    "addr:housenumber":"33",
    "addr:postcode":"8309 aa",
    "addr:street":"St Hubertusplaats;Flevoland",
    "iso:country":"NL",
    "sg:address":"St Hubertusplaats 33",
    "sg:city":"Tollebeek",
    "sg:orig_category":"Kappers",
    "sg:phone":"+31 527 651 414",
    "sg:postcode":"8309 AA",
    "sg:province":"Flevoland",
    "wof:name":"Gerard Coiffeur",
    "wof:placetype":"venue"
},
  "geometry": {"coordinates":[5.6787080765,52.6772727966],"type":"Point"}
}