{
  "type": "Feature",
  "properties": {
    "addr:full":"Bruine Akkers 11 Maarheeze North Brabant 6026 DL",
    "addr:housenumber":"11",
    "addr:postcode":"6026 dl",
    "addr:street":"Bruine Akkers",
    "iso:country":"NL",
    "sg:address":"Bruine Akkers 11",
    "sg:city":"Maarheeze",
    "sg:orig_category":"Organisatiebureaus",
    "sg:phone":"+31 6 20036058",
    "sg:postcode":"6026 DL",
    "sg:province":"North Brabant",
    "sg:website":"http://www.harlekyn.nl",
    "wof:name":"Harlekyn Festival",
    "wof:placetype":"venue"
},
  "geometry": {"coordinates":[5.6175279617,51.3135375977],"type":"Point"}
}