{
  "type": "Feature",
  "properties": {
    "addr:full":"Sasdk 4 Genemuiden Overijssel 8281 BM",
    "addr:housenumber":"4",
    "addr:postcode":"8281 bm",
    "addr:street":"Sasdk",
    "iso:country":"NL",
    "sg:address":"Sasdk 4",
    "sg:city":"Genemuiden",
    "sg:orig_category":"Waterbouwkundige Werken",
    "sg:phone":"+31 38 385 4866",
    "sg:postcode":"8281 BM",
    "sg:province":"Overijssel",
    "wof:name":"Robusta Bv",
    "wof:placetype":"venue"
},
  "geometry": {"coordinates":[6.0429201126,52.6282501221],"type":"Point"}
}