{
  "type": "Feature",
  "properties": {
    "addr:full":"Tuinstraat 1 Veenendaal Utrecht 3901 RA",
    "addr:housenumber":"1",
    "addr:postcode":"3901 ra",
    "addr:street":"Tuinstraat",
    "iso:country":"NL",
    "sg:address":"Tuinstraat 1",
    "sg:city":"Veenendaal",
    "sg:orig_category":"Public Relationbureaus",
    "sg:phone":"+31 318 552 594",
    "sg:postcode":"3901 RA",
    "sg:province":"Utrecht",
    "wof:name":"Amna",
    "wof:placetype":"venue"
},
  "geometry": {"coordinates":[5.554255,52.023609],"type":"Point"}
}