{
  "type": "Feature",
  "properties": {
    "iso:country":"NL",
    "sg:address":"Tuinstraat 1",
    "sg:city":"Veenendaal",
    "sg:orig_category":"Public Relationbureaus",
    "sg:phone":"+31 318 552 594",
    "sg:postcode":"3901 RA",
    "sg:province":"Utrecht",
    "wof:name":"Amna",
    "wof:placetype":"venue"
},
  "geometry": {"coordinates":[5.554255,52.023609],"type":"Point"}
}