{
  "type": "Feature",
  "properties": {
    "iso:country":"NL",
    "sg:address":"Wedderstr 33",
    "sg:city":"Vlagtwedde",
    "sg:orig_category":"Adviesbureaus Bouwkunde",
    "sg:phone":"+31 599 312 940",
    "sg:postcode":"9541 ED",
    "sg:province":"Groningen",
    "wof:name":"Mondiri",
    "wof:placetype":"venue"
},
  "geometry": {"coordinates":[7.100192,53.03318],"type":"Point"}
}