{
  "type": "Feature",
  "properties": {
    "addr:full":"Patrijzenweg 26 Landsmeer Noord-Holland 1121 EZ",
    "addr:housenumber":"26",
    "addr:postcode":"1121 ez",
    "addr:street":"Patrijzenweg",
    "iso:country":"NL",
    "sg:address":"Patrijzenweg 26",
    "sg:city":"Landsmeer",
    "sg:orig_category":"Boekhouders",
    "sg:phone":"+31 20 482 1321",
    "sg:postcode":"1121 EZ",
    "sg:province":"Noord-Holland",
    "wof:name":"Buro Efficient +",
    "wof:placetype":"venue"
},
  "geometry": {"coordinates":[4.924393,52.432892],"type":"Point"}
}