{
  "type": "Feature",
  "properties": {
    "addr:full":"Sportln 2A Hellevoetsluis South Holland 3223 EV",
    "addr:housenumber":"2a",
    "addr:postcode":"3223 ev",
    "addr:street":"Sportln",
    "iso:country":"NL",
    "sg:address":"Sportln 2A",
    "sg:city":"Hellevoetsluis",
    "sg:orig_category":"Fitnesscentra",
    "sg:phone":"+31 181 399 501",
    "sg:postcode":"3223 EV",
    "sg:province":"South Holland",
    "sg:website":"http://www.ylifestyle.nl",
    "wof:name":"Yvonne'S Lifestyle Center",
    "wof:placetype":"venue"
},
  "geometry": {"coordinates":[4.14703,51.830406],"type":"Point"}
}