{
  "type": "Feature",
  "properties": {
    "addr:full":"Prof V Itersonstr 98 Heerlen Limburg 6419 SE",
    "addr:housenumber":"98",
    "addr:postcode":"6419 se",
    "addr:street":"Prof;Itersonstr",
    "iso:country":"NL",
    "sg:address":"Prof V Itersonstr 98",
    "sg:city":"Heerlen",
    "sg:orig_category":"Adviesbureaus",
    "sg:phone":"+31 45 574 0063",
    "sg:postcode":"6419 SE",
    "sg:province":"Limburg",
    "wof:name":"Tri-Angel",
    "wof:placetype":"venue"
},
  "geometry": {"coordinates":[5.9661,50.875561],"type":"Point"}
}