{
  "type": "Feature",
  "properties": {
    "addr:full":"Californiepln 16 Haarlem Noord-Holland 2037 AL",
    "addr:housenumber":"16",
    "addr:postcode":"2037 al",
    "addr:street":"Californiepln",
    "iso:country":"NL",
    "sg:address":"Californiepln 16",
    "sg:city":"Haarlem",
    "sg:orig_category":"Postkantoren",
    "sg:phone":"+31 23 533 6753",
    "sg:postcode":"2037 AL",
    "sg:province":"Noord-Holland",
    "sg:website":"http://www.postkantoor.nl",
    "wof:name":"Postkantoor",
    "wof:placetype":"venue"
},
  "geometry": {"coordinates":[4.655439,52.357368],"type":"Point"}
}