{
  "type": "Feature",
  "properties": {
    "addr:full":"Brinkweg 48 Zelhem Gelderland 7021 BW",
    "addr:housenumber":"48",
    "addr:postcode":"7021 bw",
    "addr:street":"Brinkweg;Gelderland",
    "iso:country":"NL",
    "sg:address":"Brinkweg 48",
    "sg:city":"Zelhem",
    "sg:orig_category":"Autokeuringen",
    "sg:phone":"+31 314 622 478",
    "sg:postcode":"7021 BW",
    "sg:province":"Gelderland",
    "wof:name":"Automobiel- En Garagebedrijf C H Dales",
    "wof:placetype":"venue"
},
  "geometry": {"coordinates":[6.355097,52.00367],"type":"Point"}
}