{
  "type": "Feature",
  "properties": {
    "addr:full":"Prins Hendrikstraat 39 Bodegraven South Holland 2411 CS",
    "addr:housenumber":"39",
    "addr:postcode":"2411 cs",
    "addr:street":"Prins Hendrikstraat",
    "iso:country":"NL",
    "sg:address":"Prins Hendrikstraat 39",
    "sg:city":"Bodegraven",
    "sg:orig_category":"Kappers",
    "sg:phone":"+31 172 615 050",
    "sg:postcode":"2411 CS",
    "sg:province":"South Holland",
    "wof:name":"Via Via",
    "wof:placetype":"venue"
},
  "geometry": {"coordinates":[4.745904,52.082657],"type":"Point"}
}