{
  "type": "Feature",
  "properties": {
    "addr:full":"Nummer 27 Deersum Provincie Friesland 8644 VS",
    "addr:postcode":"8644",
    "addr:street":"Provincie Friesland",
    "iso:country":"NL",
    "sg:address":"Nummer 27",
    "sg:city":"Deersum",
    "sg:orig_category":"Binnenvaart",
    "sg:phone":"+31 515 521 082",
    "sg:postcode":"8644 VS",
    "sg:province":"Provincie Friesland",
    "wof:name":"Rondvaartbedrijf De Oorden",
    "wof:placetype":"venue"
},
  "geometry": {"coordinates":[5.716242,53.086884],"type":"Point"}
}