{
  "type": "Feature",
  "properties": {
    "addr:full":"Waldwei 1 Elahuizen Provincie Friesland 8581 KA",
    "addr:housenumber":"1",
    "addr:postcode":"8581 ka",
    "addr:street":"Waldwei;Provincie Friesland",
    "iso:country":"NL",
    "sg:address":"Waldwei 1",
    "sg:city":"Elahuizen",
    "sg:orig_category":"Beeldende Kunstenaars",
    "sg:phone":"+31 514 602 909",
    "sg:postcode":"8581 KA",
    "sg:province":"Provincie Friesland",
    "wof:name":"Maaskant, J A",
    "wof:placetype":"venue"
},
  "geometry": {"coordinates":[5.542672,52.917442],"type":"Point"}
}