{
  "type": "Feature",
  "properties": {
    "iso:country":"NL",
    "sg:address":"Druyfplaats 62",
    "sg:city":"Abbekerk",
    "sg:orig_category":"Acupunctuur",
    "sg:phone":"+31 229 582 705",
    "sg:postcode":"1657 LZ",
    "sg:province":"Noord-Holland",
    "wof:name":"Kat, K",
    "wof:placetype":"venue"
},
  "geometry": {"coordinates":[5.012853,52.727627],"type":"Point"}
}