{
  "type": "Feature",
  "properties": {
    "addr:full":"Dorpspln 50 Duivendrecht North Holland 1115 CW",
    "addr:housenumber":"50",
    "addr:postcode":"1115 cw",
    "addr:street":"Dorpspln",
    "iso:country":"NL",
    "sg:address":"Dorpspln 50",
    "sg:city":"Duivendrecht",
    "sg:orig_category":"Bloemen En Planten",
    "sg:phone":"+31 20 699 0389",
    "sg:postcode":"1115 CW",
    "sg:province":"North Holland",
    "wof:name":"Ixora",
    "wof:placetype":"venue"
},
  "geometry": {"coordinates":[4.939556,52.33231],"type":"Point"}
}