{
  "type": "Feature",
  "properties": {
    "addr:full":"Langestraat 22 Nijkerk Gld Gelderland 3861 BN",
    "addr:housenumber":"22",
    "addr:postcode":"3861 bn",
    "addr:street":"Langestraat;Gld Gelderland",
    "iso:country":"NL",
    "sg:address":"Langestraat 22",
    "sg:city":"Nijkerk Gld",
    "sg:orig_category":"Fotostudio'S And Fotografen",
    "sg:phone":"+31 33 245 7020",
    "sg:postcode":"3861 BN",
    "sg:province":"Gelderland",
    "wof:name":"Foto Nispeling",
    "wof:placetype":"venue"
},
  "geometry": {"coordinates":[5.484694,52.222721],"type":"Point"}
}