{
  "type": "Feature",
  "properties": {
    "addr:full":"Brugstraat 9 Someren Noord-Brabant 5712 AX",
    "addr:housenumber":"9",
    "addr:postcode":"5712 ax",
    "addr:street":"Brugstraat",
    "iso:country":"NL",
    "sg:address":"Brugstraat 9",
    "sg:city":"Someren",
    "sg:orig_category":"Bloemen And Planten",
    "sg:phone":"+31 493 494 038",
    "sg:postcode":"5712 AX",
    "sg:province":"Noord-Brabant",
    "wof:name":"Ad Wijnen Rotsplanten",
    "wof:placetype":"venue"
},
  "geometry": {"coordinates":[5.733787,51.364693],"type":"Point"}
}