{
  "type": "Feature",
  "properties": {
    "addr:full":"Klein Schavernek 10 Leeuwarden Friesland 8911 BV",
    "addr:housenumber":"10",
    "addr:postcode":"8911 bv",
    "addr:street":"Klein Schavernek",
    "iso:country":"NL",
    "sg:address":"Klein Schavernek 10",
    "sg:city":"Leeuwarden",
    "sg:orig_category":"Kappers",
    "sg:phone":"+31 58 216 1684",
    "sg:postcode":"8911 BV",
    "sg:province":"Friesland",
    "wof:name":"Schoonheidssalon Diana",
    "wof:placetype":"venue"
},
  "geometry": {"coordinates":[5.78924,53.201378],"type":"Point"}
}