{
  "type": "Feature",
  "properties": {
    "addr:full":"Koningsweg 65 'S Hertogenbosch North Brabant 5211 BH",
    "addr:housenumber":"65",
    "addr:postcode":"5211 bh",
    "addr:street":"Koningsweg;' S Hertogenbosch",
    "iso:country":"NL",
    "sg:address":"Koningsweg 65",
    "sg:city":"'S Hertogenbosch",
    "sg:orig_category":"Vertaal- And Tolkenbureaus",
    "sg:phone":"+31 73 612 4326",
    "sg:postcode":"5211 BH",
    "sg:province":"North Brabant",
    "wof:name":"Todo Talenservice",
    "wof:placetype":"venue"
},
  "geometry": {"coordinates":[5.293522,51.686375],"type":"Point"}
}