{
  "type": "Feature",
  "properties": {
    "addr:full":"Jacob Van Lennepkade 332 Amsterdam Noord-Holland 1053 NJ",
    "addr:housenumber":"332",
    "addr:postcode":"1053 nj",
    "addr:street":"Jacob Van Lennepkade",
    "iso:country":"NL",
    "sg:address":"Jacob Van Lennepkade 332",
    "sg:city":"Amsterdam",
    "sg:orig_category":"Muziekinstrumenten Fab",
    "sg:phone":"+31 20 618 2440",
    "sg:postcode":"1053 NJ",
    "sg:province":"Noord-Holland",
    "wof:name":"D. Marcovich",
    "wof:placetype":"venue"
},
  "geometry": {"coordinates":[-94.58503,38.350479],"type":"Point"}
}