{
  "type": "Feature",
  "properties": {
    "addr:full":"Nieuwstr 44 Dordrecht Zuid-Holland 3311 XR",
    "addr:housenumber":"44",
    "addr:postcode":"3311 xr",
    "addr:street":"Nieuwstr",
    "iso:country":"NL",
    "sg:address":"Nieuwstr 44",
    "sg:city":"Dordrecht",
    "sg:orig_category":"Parketvloeren",
    "sg:phone":"+31 78 613 1686",
    "sg:postcode":"3311 XR",
    "sg:province":"Zuid-Holland",
    "wof:name":"Bevers",
    "wof:placetype":"venue"
},
  "geometry": {"coordinates":[4.669917,51.814644],"type":"Point"}
}