{
  "type": "Feature",
  "properties": {
    "addr:full":"Herenstr 9B Ryswyk Zh Zuid-Holland 2282 BN",
    "addr:housenumber":"9b",
    "addr:postcode":"2282 bn",
    "addr:street":"Herenstr",
    "iso:country":"NL",
    "sg:address":"Herenstr 9B",
    "sg:city":"Ryswyk Zh",
    "sg:orig_category":"Bijouterie?n",
    "sg:phone":"+31 70 390 4809",
    "sg:postcode":"2282 BN",
    "sg:province":"Zuid-Holland",
    "wof:name":"Gaby",
    "wof:placetype":"venue"
},
  "geometry": {"coordinates":[4.33694,52.056503],"type":"Point"}
}