{
  "type": "Feature",
  "properties": {
    "addr:full":"Alkmaarsestraat 6 Scheveningen Zuid-Holland 2587 RN",
    "addr:housenumber":"6",
    "addr:postcode":"2587 rn",
    "addr:street":"Alkmaarsestraat",
    "iso:country":"NL",
    "sg:address":"Alkmaarsestraat 6",
    "sg:city":"Scheveningen",
    "sg:classifiers":[
        {
            "category":"Travel",
            "subcategory":"Hotels & Motels",
            "type":"Entertainment"
        }
    ],
    "sg:phone":"+31 70 350 6999",
    "sg:postcode":"2587 RN",
    "sg:province":"Zuid-Holland",
    "wof:name":"Hotel Duinzicht / Duinhorst",
    "wof:placetype":"venue"
},
  "geometry": {"coordinates":[4.288053,52.115856],"type":"Point"}
}