{
  "type": "Feature",
  "properties": {
    "addr:full":"Smidswei 59 Drachtstercompagnie Friesland 9222 NB",
    "addr:housenumber":"59",
    "addr:postcode":"9222 nb",
    "addr:street":"Smidswei",
    "iso:country":"NL",
    "sg:address":"Smidswei 59",
    "sg:city":"Drachtstercompagnie",
    "sg:orig_category":"Hoefdierhouderijen",
    "sg:phone":"+31 512 342 565",
    "sg:postcode":"9222 NB",
    "sg:province":"Friesland",
    "wof:name":"Stal Zuidema",
    "wof:placetype":"venue"
},
  "geometry": {"coordinates":[6.134481,53.139618],"type":"Point"}
}