{
  "type": "Feature",
  "properties": {
    "addr:full":"Elftweg 17 Raamsdonksveer Noord-Brabant 4941 VR",
    "addr:housenumber":"17",
    "addr:postcode":"4941 vr",
    "addr:street":"Elftweg",
    "iso:country":"NL",
    "sg:address":"Elftweg 17",
    "sg:city":"Raamsdonksveer",
    "sg:orig_category":"Zuivelproducten And Spijsoli?n Gh",
    "sg:phone":"+31 162 586 700",
    "sg:postcode":"4941 VR",
    "sg:province":"Noord-Brabant",
    "wof:name":"Frico Slices",
    "wof:placetype":"venue"
},
  "geometry": {"coordinates":[4.879663,51.710941],"type":"Point"}
}