{
  "type": "Feature",
  "properties": {
    "addr:full":"Postbus 9393 Amsterdam Noord-Holland 1006 AJ",
    "addr:housenumber":"9393",
    "addr:postcode":"1006 aj",
    "addr:street":"Postbus",
    "iso:country":"NL",
    "sg:address":"Postbus 9393",
    "sg:city":"Amsterdam",
    "sg:orig_category":"Natuurvoeding En Reformartikelen",
    "sg:phone":"+31 20 411 2882",
    "sg:postcode":"1006 AJ",
    "sg:province":"Noord-Holland",
    "sg:website":"HTTP://www.perfectbody.nl",
    "wof:name":"Perfectbody Nl",
    "wof:placetype":"venue"
},
  "geometry": {"coordinates":[4.89205,52.37355],"type":"Point"}
}