{
  "type": "Feature",
  "properties": {
    "addr:full":"Benschopperstr 17 Ysselstein Ut Utrecht 3401 DG",
    "addr:housenumber":"17",
    "addr:postcode":"3401 dg",
    "addr:street":"Benschopperstr",
    "iso:country":"NL",
    "sg:address":"Benschopperstr 17",
    "sg:city":"Ysselstein Ut",
    "sg:orig_category":"Schoenen",
    "sg:phone":"+31 30 210 0124",
    "sg:postcode":"3401 DG",
    "sg:province":"Utrecht",
    "wof:name":"Schoenen & Zo",
    "wof:placetype":"venue"
},
  "geometry": {"coordinates":[5.041901,52.018856],"type":"Point"}
}