{
  "type": "Feature",
  "properties": {
    "addr:full":"Werenfriedstr 11 Waalre Noord-Brabant 5581 BB",
    "addr:housenumber":"11",
    "addr:postcode":"5581 bb",
    "addr:street":"Werenfriedstr",
    "iso:country":"NL",
    "sg:address":"Werenfriedstr 11",
    "sg:city":"Waalre",
    "sg:orig_category":"Psychotherapeuten",
    "sg:phone":"+31 40 221 8691",
    "sg:postcode":"5581 BB",
    "sg:province":"Noord-Brabant",
    "wof:name":"Auer, C",
    "wof:placetype":"venue"
},
  "geometry": {"coordinates":[5.441488,51.385773],"type":"Point"}
}