{
  "type": "Feature",
  "properties": {
    "addr:full":"J Deckersstr 9 Helenaveen Noord-Brabant 5759 PT",
    "addr:housenumber":"9",
    "addr:postcode":"5759 pt",
    "iso:country":"NL",
    "sg:address":"J Deckersstr 9",
    "sg:city":"Helenaveen",
    "sg:orig_category":"Beveiliging",
    "sg:phone":"+31 493 539 231",
    "sg:postcode":"5759 PT",
    "sg:province":"Noord-Brabant",
    "wof:name":"Swinkels Electronica Service",
    "wof:placetype":"venue"
},
  "geometry": {"coordinates":[5.922558,51.386047],"type":"Point"}
}