{
  "type": "Feature",
  "properties": {
    "addr:full":"Toereppel 15 Enkhuizen Noord-Holland 1602 KG",
    "addr:housenumber":"15",
    "addr:postcode":"1602 kg",
    "addr:street":"Toereppel",
    "iso:country":"NL",
    "sg:address":"Toereppel 15",
    "sg:city":"Enkhuizen",
    "sg:orig_category":"Administratie- En Boekhoudkantoren",
    "sg:phone":"+31 228 318 605",
    "sg:postcode":"1602 KG",
    "sg:province":"Noord-Holland",
    "wof:name":"Fima",
    "wof:placetype":"venue"
},
  "geometry": {"coordinates":[5.268532,52.712421],"type":"Point"}
}