{
  "type": "Feature",
  "properties": {
    "addr:full":"Kerkstr 27 Huizen Noord-Holland 1271 RJ",
    "addr:housenumber":"27",
    "addr:postcode":"1271 rj",
    "addr:street":"Kerkstr",
    "iso:country":"NL",
    "sg:address":"Kerkstr 27",
    "sg:city":"Huizen",
    "sg:orig_category":"Fietsen En Bromfietsen",
    "sg:phone":"+31 35 523 7048",
    "sg:postcode":"1271 RJ",
    "sg:province":"Noord-Holland",
    "sg:website":"http://www.biketotaal.nl",
    "wof:name":"Bike Totaal Huizen",
    "wof:placetype":"venue"
},
  "geometry": {"coordinates":[5.237483,52.298515],"type":"Point"}
}