{
  "type": "Feature",
  "properties": {
    "addr:full":"J V Vuchtstr 39 Rotterdam Zuid-Holland 3021 KB",
    "addr:housenumber":"39",
    "addr:postcode":"3021 kb",
    "addr:street":"J;Vuchtstr",
    "iso:country":"NL",
    "sg:address":"J V Vuchtstr 39",
    "sg:city":"Rotterdam",
    "sg:orig_category":"Verenigingen En Stichtingen",
    "sg:phone":"+31 10 476 3853",
    "sg:postcode":"3021 KB",
    "sg:province":"Zuid-Holland",
    "wof:name":"En Route, Sticht",
    "wof:placetype":"venue"
},
  "geometry": {"coordinates":[4.45925,51.916531],"type":"Point"}
}