{
  "type": "Feature",
  "properties": {
    "addr:full":"Dorpsstr 14 Beltrum Gelderland 7156 LL",
    "addr:housenumber":"14",
    "addr:postcode":"7156 ll",
    "addr:street":"Dorpsstr;Gelderland",
    "iso:country":"NL",
    "sg:address":"Dorpsstr 14",
    "sg:city":"Beltrum",
    "sg:orig_category":"Fietsen En Bromfietsen",
    "sg:phone":"+31 544 481 203",
    "sg:postcode":"7156 LL",
    "sg:province":"Gelderland",
    "wof:name":"Hofstede",
    "wof:placetype":"venue"
},
  "geometry": {"coordinates":[6.559574,52.066105],"type":"Point"}
}