{
  "type": "Feature",
  "properties": {
    "addr:full":"Smildestr 7 S Gravenhage South Holland 2545 WB",
    "addr:housenumber":"7 s",
    "addr:postcode":"2545 wb",
    "addr:street":"Smildestr",
    "iso:country":"NL",
    "sg:address":"Smildestr 7",
    "sg:city":"S Gravenhage",
    "sg:orig_category":"Webdesign Bureaus",
    "sg:phone":"+31 6 29512492",
    "sg:postcode":"2545 WB",
    "sg:province":"South Holland",
    "sg:website":"http://www.w3d-design.nl",
    "wof:name":"W3D-Design",
    "wof:placetype":"venue"
},
  "geometry": {"coordinates":[4.2704901695,52.0509300232],"type":"Point"}
}