{
  "type": "Feature",
  "properties": {
    "addr:full":"St Antoniusstr 40 Schyf Noord-Brabant 4721 AN",
    "addr:housenumber":"40",
    "addr:postcode":"4721 an",
    "addr:street":"Schyf",
    "iso:country":"NL",
    "sg:address":"St Antoniusstr 40",
    "sg:city":"Schyf",
    "sg:orig_category":"Zalenverhuur",
    "sg:phone":"+31 165 341 822",
    "sg:postcode":"4721 AN",
    "sg:province":"Noord-Brabant",
    "wof:name":"Sport",
    "wof:placetype":"venue"
},
  "geometry": {"coordinates":[4.560243,51.497471],"type":"Point"}
}