{
  "type": "Feature",
  "properties": {
    "addr:full":"Kraaijeveldstraat 2 Rotterdam South Holland 3078 PE",
    "addr:housenumber":"2",
    "addr:postcode":"3078 pe",
    "addr:street":"Kraaijeveldstraat",
    "iso:country":"NL",
    "sg:address":"Kraaijeveldstraat 2",
    "sg:city":"Rotterdam",
    "sg:classifiers":[
        {
            "category":"Education",
            "subcategory":"Preschool",
            "type":"Public Place"
        }
    ],
    "sg:phone":"+31 10 482 1088",
    "sg:postcode":"3078 PE",
    "sg:province":"South Holland",
    "sg:tags":[
        "kleuteronderwijs",
        "basis-"
    ],
    "wof:name":"Dr. F. Hogewindschool",
    "wof:placetype":"venue"
},
  "geometry": {"coordinates":[4.546075,51.893501],"type":"Point"}
}