{
  "type": "Feature",
  "properties": {
    "addr:full":"Helgoland 12 Zaandam Noord-Holland 1506 BW",
    "addr:housenumber":"12",
    "addr:postcode":"1506 bw",
    "addr:street":"Helgoland",
    "iso:country":"NL",
    "sg:address":"Helgoland 12",
    "sg:city":"Zaandam",
    "sg:orig_category":"Adviesbureaus Bedrijfsorganisatie",
    "sg:phone":"+31 75 614 1760",
    "sg:postcode":"1506 BW",
    "sg:province":"Noord-Holland",
    "sg:website":"http://www.beira.nl",
    "wof:name":"Beira Interim Services",
    "wof:placetype":"venue"
},
  "geometry": {"coordinates":[4.825472,52.433231],"type":"Point"}
}