{
  "type": "Feature",
  "properties": {
    "addr:full":"Nieuwe Uitleg 24 'S Gravenhage Zuid-Holland 2514 BR",
    "addr:housenumber":"24",
    "addr:postcode":"2514 br",
    "addr:street":"Nieuwe Uitleg;' S",
    "iso:country":"NL",
    "sg:address":"Nieuwe Uitleg 24",
    "sg:city":"'S Gravenhage",
    "sg:orig_category":"Werving And Selectie Van Tijdelijk Personeel And Uitzendkantoren",
    "sg:phone":"+31 70 364 6600",
    "sg:postcode":"2514 BR",
    "sg:province":"Zuid-Holland",
    "wof:name":"Exact Personeelsintermediair",
    "wof:placetype":"venue"
},
  "geometry": {"coordinates":[4.3146028519,52.0848045349],"type":"Point"}
}