{
  "type": "Feature",
  "properties": {
    "addr:full":"Arnhemsewg 49 Amersfoort Utrecht 3817 CA",
    "addr:housenumber":"49",
    "addr:postcode":"3817 ca",
    "addr:street":"Arnhemsewg",
    "iso:country":"NL",
    "sg:address":"Arnhemsewg 49",
    "sg:city":"Amersfoort",
    "sg:orig_category":"Verzekeringen - Verzekeringskantoren",
    "sg:phone":"+31 33 462 1919",
    "sg:postcode":"3817 CA",
    "sg:province":"Utrecht",
    "wof:name":"Vink, Jac",
    "wof:placetype":"venue"
},
  "geometry": {"coordinates":[5.385923,52.148983],"type":"Point"}
}