{
  "type": "Feature",
  "properties": {
    "iso:country":"NL",
    "sg:address":"Kroostweg-Noord 159",
    "sg:city":"Zeist",
    "sg:orig_category":"Verzekeringen",
    "sg:phone":"+31 30 696 1969",
    "sg:postcode":"3704 DW",
    "sg:province":"Utrecht",
    "wof:name":"Adviesburo F.J.J.M. Van Hemert",
    "wof:placetype":"venue"
},
  "geometry": {"coordinates":[5.212636,52.095905],"type":"Point"}
}