{
  "type": "Feature",
  "properties": {
    "addr:full":"Middelwaard 30 Zoetermeer Zuid-Holland 2716 CW",
    "addr:housenumber":"30",
    "addr:postcode":"2716 cw",
    "addr:street":"Middelwaard",
    "iso:country":"NL",
    "sg:address":"Middelwaard 30",
    "sg:city":"Zoetermeer",
    "sg:orig_category":"Zoetwaren - Winkels",
    "sg:phone":"+31 79 351 6733",
    "sg:postcode":"2716 CW",
    "sg:province":"Zuid-Holland",
    "wof:name":"Jamin",
    "wof:placetype":"venue"
},
  "geometry": {"coordinates":[4.469299,52.056293],"type":"Point"}
}