{
  "type": "Feature",
  "properties": {
    "iso:country":"NL",
    "sg:address":"De Vennen 17",
    "sg:city":"Delfzijl",
    "sg:classifiers":[
        {
            "category":"Food & Beverages",
            "subcategory":"Fruits & Vegetables",
            "type":"Retail Goods"
        }
    ],
    "sg:phone":"+31 596 614 505",
    "sg:postcode":"9934 AC",
    "sg:province":"Groningen",
    "sg:tags":[
        "groenten"
    ],
    "wof:name":"Lubbers Groenten En Fruit",
    "wof:placetype":"venue"
},
  "geometry": {"coordinates":[6.928554,53.333103],"type":"Point"}
}