{
  "type": "Feature",
  "properties": {
    "addr:full":"Locht 22 Veldhoven Noord-Brabant 5504 KD",
    "addr:housenumber":"22",
    "addr:postcode":"5504 kd",
    "addr:street":"Locht",
    "iso:country":"NL",
    "sg:address":"Locht 22",
    "sg:city":"Veldhoven",
    "sg:orig_category":"Schilders",
    "sg:phone":"+31 40 253 5964",
    "sg:postcode":"5504 KD",
    "sg:province":"Noord-Brabant",
    "wof:name":"Mol, Van",
    "wof:placetype":"venue"
},
  "geometry": {"coordinates":[5.394962,51.401344],"type":"Point"}
}