{
  "type": "Feature",
  "properties": {
    "addr:full":"Gen Cronjestr 22 Haarlem Noord-Holland 2021 JH",
    "addr:housenumber":"22",
    "addr:postcode":"2021 jh",
    "iso:country":"NL",
    "sg:address":"Gen Cronjestr 22",
    "sg:city":"Haarlem",
    "sg:orig_category":"Kaas",
    "sg:phone":"+31 23 527 6421",
    "sg:postcode":"2021 JH",
    "sg:province":"Noord-Holland",
    "wof:name":"Kaashoek, De",
    "wof:placetype":"venue"
},
  "geometry": {"coordinates":[4.6411371231,52.3927955627],"type":"Point"}
}