{
  "type": "Feature",
  "properties": {
    "addr:full":"Achterstraat 34 Putten Gelderland 3882 AG",
    "addr:housenumber":"34",
    "addr:postcode":"3882",
    "addr:street":"Achterstraat;Gelderland",
    "iso:country":"NL",
    "sg:address":"Achterstraat 34",
    "sg:city":"Putten",
    "sg:orig_category":"Boekenuitgeverijen",
    "sg:phone":"+31 341 352 899",
    "sg:postcode":"3882 AG",
    "sg:province":"Gelderland",
    "wof:name":"Boekhandel Van De Kamp Bv",
    "wof:placetype":"venue"
},
  "geometry": {"coordinates":[5.604181,52.260216],"type":"Point"}
}