{
  "type": "Feature",
  "properties": {
    "iso:country":"NL",
    "sg:address":"Q Matsyslaan 63",
    "sg:city":"Eindhoven",
    "sg:orig_category":"Loodgieterswerk, Verwarming And Sanitaire Installaties",
    "sg:phone":"+31 40 281 8105",
    "sg:postcode":"5642 JC",
    "sg:province":"Noord-Brabant",
    "wof:name":"Gas Service Team Eindhoven",
    "wof:placetype":"venue"
},
  "geometry": {"coordinates":[5.515856,51.435215],"type":"Point"}
}