{
  "type": "Feature",
  "properties": {
    "addr:full":"Jelsumerstraat 41A Leeuwarden Friesland 8917 EL",
    "addr:housenumber":"41a",
    "addr:postcode":"8917 el",
    "addr:street":"Jelsumerstraat",
    "iso:country":"NL",
    "sg:address":"Jelsumerstraat 41A",
    "sg:city":"Leeuwarden",
    "sg:orig_category":"Bloed- And Andere Donoren",
    "sg:phone":"+31 58 215 2015",
    "sg:postcode":"8917 EL",
    "sg:province":"Friesland",
    "wof:name":"Bloedbank Noord Nederland",
    "wof:placetype":"venue"
},
  "geometry": {"coordinates":[5.788534,53.209854],"type":"Point"}
}