{
  "type": "Feature",
  "properties": {
    "addr:full":"De Galery 6 Wyk En Aalburg Noord-Brabant 4261 DG",
    "addr:housenumber":"6",
    "addr:postcode":"4261 dg",
    "addr:street":"Wyk En",
    "iso:country":"NL",
    "sg:address":"De Galery 6",
    "sg:city":"Wyk En Aalburg",
    "sg:orig_category":"Kappers",
    "sg:phone":"+31 416 691 854",
    "sg:postcode":"4261 DG",
    "sg:province":"Noord-Brabant",
    "wof:name":"Verbeek, K",
    "wof:placetype":"venue"
},
  "geometry": {"coordinates":[5.13042,51.755196],"type":"Point"}
}