{
  "type": "Feature",
  "properties": {
    "addr:full":"Voorstr 128 Dordrecht Zuid-Holland 3311 ER",
    "addr:housenumber":"128",
    "addr:postcode":"3311 er",
    "iso:country":"NL",
    "sg:address":"Voorstr 128",
    "sg:city":"Dordrecht",
    "sg:orig_category":"Kunsthandel",
    "sg:phone":"+31 78 613 9902",
    "sg:postcode":"3311 ER",
    "sg:province":"Zuid-Holland",
    "wof:name":"Rode Deur, De",
    "wof:placetype":"venue"
},
  "geometry": {"coordinates":[4.670421,51.817699],"type":"Point"}
}