{
  "type": "Feature",
  "properties": {
    "addr:full":"Kajuit 322C Groningen Groningen 9733 CX",
    "addr:housenumber":"322c",
    "addr:postcode":"9733 cx",
    "addr:street":"Kajuit",
    "iso:country":"NL",
    "sg:address":"Kajuit 322C",
    "sg:city":"Groningen",
    "sg:orig_category":"Zuivelproducten",
    "sg:phone":"+31 50 542 2016",
    "sg:postcode":"9733 CX",
    "sg:province":"Groningen",
    "wof:name":"Kaasborg Van Der Leij",
    "wof:placetype":"venue"
},
  "geometry": {"coordinates":[6.624687,53.238197],"type":"Point"}
}