{
  "type": "Feature",
  "properties": {
    "addr:full":"Ptr. Van De Elsenstraat 25A Haarsteeg Noord-Brabant 5254 JG",
    "addr:housenumber":"25a",
    "addr:postcode":"5254 jg",
    "addr:street":"Ptr. Van De Elsenstraat",
    "iso:country":"NL",
    "sg:address":"Ptr. Van De Elsenstraat 25A",
    "sg:city":"Haarsteeg",
    "sg:orig_category":"Overheidsdiensten",
    "sg:phone":"+31 73 511 4600",
    "sg:postcode":"5254 JG",
    "sg:province":"Noord-Brabant",
    "wof:name":"Drieluik",
    "wof:placetype":"venue"
},
  "geometry": {"coordinates":[5.1973671913,51.7126846313],"type":"Point"}
}