{
  "type": "Feature",
  "properties": {
    "iso:country":"NL",
    "sg:address":"Pontanusstraat 26",
    "sg:city":"Nijmegen",
    "sg:orig_category":"Overheidsdiensten",
    "sg:phone":"+31 24 323 1423",
    "sg:postcode":"6524 HG",
    "sg:province":"Gelderland",
    "wof:name":"Joegoslavisch Ontmoetingscentrum",
    "wof:placetype":"venue"
},
  "geometry": {"coordinates":[5.8612279892,51.8390808105],"type":"Point"}
}