{
  "type": "Feature",
  "properties": {
    "iso:country":"NL",
    "sg:address":"Lucas Van Hauthemlaan 18",
    "sg:city":"Nuenen",
    "sg:orig_category":"Binnenhuisarchitecten",
    "sg:phone":"+31 40 295 1550",
    "sg:postcode":"5671 CJ",
    "sg:province":"North Brabant",
    "wof:name":"Total Interior Solutions",
    "wof:placetype":"venue"
},
  "geometry": {"coordinates":[5.558478,51.480125],"type":"Point"}
}