{
  "type": "Feature",
  "properties": {
    "addr:full":"Hofmeestery 17 Huissen Gelderland 6852 NA",
    "addr:housenumber":"17",
    "addr:postcode":"6852 na",
    "addr:street":"Hofmeestery;Gelderland",
    "iso:country":"NL",
    "sg:address":"Hofmeestery 17",
    "sg:city":"Huissen",
    "sg:orig_category":"Stukadoorsbedrijven",
    "sg:phone":"+31 26 325 5247",
    "sg:postcode":"6852 NA",
    "sg:province":"Gelderland",
    "wof:name":"Evers, H G J",
    "wof:placetype":"venue"
},
  "geometry": {"coordinates":[5.928282,51.93597],"type":"Point"}
}