{
  "type": "Feature",
  "properties": {
    "addr:full":"Aspergedreef 4 Spijkenisse South Holland 3204 HA",
    "addr:housenumber":"4",
    "addr:postcode":"3204 ha",
    "addr:street":"Aspergedreef",
    "iso:country":"NL",
    "sg:address":"Aspergedreef 4",
    "sg:city":"Spijkenisse",
    "sg:orig_category":"Onderhoud And Reparatie Kantoorapparatuur",
    "sg:phone":"+31 181 645 282",
    "sg:postcode":"3204 HA",
    "sg:province":"South Holland",
    "wof:name":"Rumach Automatisering",
    "wof:placetype":"venue"
},
  "geometry": {"coordinates":[4.331099,51.837597],"type":"Point"}
}