{
  "type": "Feature",
  "properties": {
    "addr:full":"Middelburgsngl 22 Arnhem Gelderland 6845 BR",
    "addr:housenumber":"22",
    "addr:postcode":"6845 br",
    "addr:street":"Middelburgsngl",
    "iso:country":"NL",
    "sg:address":"Middelburgsngl 22",
    "sg:city":"Arnhem",
    "sg:orig_category":"Glazenwasserijen",
    "sg:phone":"+31 6 14280674",
    "sg:postcode":"6845 BR",
    "sg:province":"Gelderland",
    "wof:name":"Robes",
    "wof:placetype":"venue"
},
  "geometry": {"coordinates":[5.868636,51.950214],"type":"Point"}
}