{
  "type": "Feature",
  "properties": {
    "addr:full":"Concoursln 1B Hoofddorp Noord-Holland 2132 DH",
    "addr:housenumber":"1b",
    "addr:postcode":"2132 dh",
    "addr:street":"Concoursln",
    "iso:country":"NL",
    "sg:address":"Concoursln 1B",
    "sg:city":"Hoofddorp",
    "sg:orig_category":"Horren",
    "sg:phone":"+31 23 563 5785",
    "sg:postcode":"2132 DH",
    "sg:province":"Noord-Holland",
    "sg:website":"http://www.randstadzonweringen.nl",
    "wof:name":"Randstad Zonweringen",
    "wof:placetype":"venue"
},
  "geometry": {"coordinates":[4.69296,52.305393],"type":"Point"}
}