{
  "type": "Feature",
  "properties": {
    "addr:full":"V Vollenhovenln 218 Utrecht Utrecht 3527 JX",
    "addr:housenumber":"218",
    "addr:postcode":"3527 jx",
    "iso:country":"NL",
    "sg:address":"V Vollenhovenln 218",
    "sg:city":"Utrecht",
    "sg:orig_category":"Adviesbureaus",
    "sg:phone":"+31 30 294 6993",
    "sg:postcode":"3527 JX",
    "sg:province":"Utrecht",
    "wof:name":"D' Apper",
    "wof:placetype":"venue"
},
  "geometry": {"coordinates":[5.09488,52.078011],"type":"Point"}
}