{
  "type": "Feature",
  "properties": {
    "addr:full":"Bertus Van Akenlaan 17 Voorschoten Zuid-Holland 2251 RA",
    "addr:housenumber":"17",
    "addr:postcode":"2251 ra",
    "addr:street":"Bertus Van Akenlaan",
    "iso:country":"NL",
    "sg:address":"Bertus Van Akenlaan 17",
    "sg:city":"Voorschoten",
    "sg:orig_category":"Binnenhuisarchitecten",
    "sg:phone":"+31 6 22336783",
    "sg:postcode":"2251 RA",
    "sg:province":"Zuid-Holland",
    "wof:name":"Dsd",
    "wof:placetype":"venue"
},
  "geometry": {"coordinates":[4.447677,52.118378],"type":"Point"}
}