{
  "type": "Feature",
  "properties": {
    "addr:full":"Schoenerstr 268 Den Helder Noord-Holland 1784 LL",
    "addr:housenumber":"268",
    "addr:postcode":"1784 ll",
    "iso:country":"NL",
    "sg:address":"Schoenerstr 268",
    "sg:city":"Den Helder",
    "sg:orig_category":"Glazenwasserijen",
    "sg:phone":"+31 6 11384798",
    "sg:postcode":"1784 LL",
    "sg:province":"Noord-Holland",
    "wof:name":"Koen",
    "wof:placetype":"venue"
},
  "geometry": {"coordinates":[4.741965,52.935253],"type":"Point"}
}