{
  "type": "Feature",
  "properties": {
    "addr:full":"Draaikolk 20 Hellevoetsluis Zuid-Holland 3224 SC",
    "addr:housenumber":"20",
    "addr:postcode":"3224 sc",
    "addr:street":"Draaikolk",
    "iso:country":"NL",
    "sg:address":"Draaikolk 20",
    "sg:city":"Hellevoetsluis",
    "sg:orig_category":"Vertalers",
    "sg:phone":"+31 181 324 757",
    "sg:postcode":"3224 SC",
    "sg:province":"Zuid-Holland",
    "wof:name":"Sitter-Houtkamp, P C",
    "wof:placetype":"venue"
},
  "geometry": {"coordinates":[4.146783,51.823853],"type":"Point"}
}