{
  "type": "Feature",
  "properties": {
    "addr:full":"1E C Huygensstr 61 Amsterdam Noord-Holland 1054 BT",
    "addr:housenumber":"61",
    "addr:postcode":"1054 bt",
    "addr:street":"1E C Huygensstr",
    "iso:country":"NL",
    "sg:address":"1E C Huygensstr 61",
    "sg:city":"Amsterdam",
    "sg:orig_category":"Beeldende Kunstenaars",
    "sg:phone":"+31 20 670 4575",
    "sg:postcode":"1054 BT",
    "sg:province":"Noord-Holland",
    "wof:name":"Knaapen Kazemier",
    "wof:placetype":"venue"
},
  "geometry": {"coordinates":[4.875217,52.363319],"type":"Point"}
}