{
  "type": "Feature",
  "properties": {
    "addr:full":"Molendk 11 Hoogezand Groningen 9601 LH",
    "addr:housenumber":"11",
    "addr:postcode":"9601 lh",
    "addr:street":"Molendk",
    "iso:country":"NL",
    "sg:address":"Molendk 11",
    "sg:city":"Hoogezand",
    "sg:orig_category":"Accountants - Administratie- Consulenten En -Kantoren",
    "sg:phone":"+31 598 351 707",
    "sg:postcode":"9601 LH",
    "sg:province":"Groningen",
    "wof:name":"Klatter, F",
    "wof:placetype":"venue"
},
  "geometry": {"coordinates":[6.74099,53.16328],"type":"Point"}
}