{
  "type": "Feature",
  "properties": {
    "addr:full":"Keyenbergsewg 5 Wageningen Gelderland 6704 PJ",
    "addr:housenumber":"5",
    "addr:postcode":"6704 pj",
    "addr:street":"Keyenbergsewg;Gelderland",
    "iso:country":"NL",
    "sg:address":"Keyenbergsewg 5",
    "sg:city":"Wageningen",
    "sg:orig_category":"Projectontwikkeling",
    "sg:phone":"+31 317 450 993",
    "sg:postcode":"6704 PJ",
    "sg:province":"Gelderland",
    "wof:name":"Nero Bv",
    "wof:placetype":"venue"
},
  "geometry": {"coordinates":[5.660976,51.964355],"type":"Point"}
}