{
  "type": "Feature",
  "properties": {
    "iso:country":"NL",
    "sg:address":"Voorland 5",
    "sg:city":"Zeewolde",
    "sg:orig_category":"Pensioenen",
    "sg:phone":"+31 36 522 7618",
    "sg:postcode":"3891 GM",
    "sg:province":"NL.",
    "wof:name":"Ruiterman Bv",
    "wof:placetype":"venue"
},
  "geometry": {"coordinates":[5.544617,52.333824],"type":"Point"}
}