{
  "type": "Feature",
  "properties": {
    "addr:full":"T Loo 22 Heiloo Noord-Holland 1851 HT",
    "addr:housenumber":"22",
    "addr:postcode":"1851 ht",
    "addr:street":"T Loo",
    "iso:country":"NL",
    "sg:address":"T Loo 22",
    "sg:city":"Heiloo",
    "sg:orig_category":"Zalenverhuur",
    "sg:phone":"+31 72 533 3368",
    "sg:postcode":"1851 HT",
    "sg:province":"Noord-Holland",
    "wof:name":"Open Huis, Sticht",
    "wof:placetype":"venue"
},
  "geometry": {"coordinates":[4.713702,52.604191],"type":"Point"}
}