{
  "type": "Feature",
  "properties": {
    "iso:country":"NL",
    "sg:address":"De Wulp 63",
    "sg:city":"Almelo",
    "sg:orig_category":"Landbouwmachines Gh",
    "sg:phone":"+31 546 829 799",
    "sg:postcode":"7609 LN",
    "sg:province":"Overijssel",
    "wof:name":"Bj Trading",
    "wof:placetype":"venue"
},
  "geometry": {"coordinates":[6.643216,52.334045],"type":"Point"}
}