{
  "type": "Feature",
  "properties": {
    "addr:full":"Wyk 2 14 Urk Flevoland 8321 EP",
    "addr:housenumber":"2 14",
    "addr:postcode":"8321 ep",
    "addr:street":"Wyk;Flevoland",
    "iso:country":"NL",
    "sg:address":"Wyk 2 14",
    "sg:city":"Urk",
    "sg:orig_category":"Binnenhuisarchitectuur",
    "sg:phone":"+31 527 651 987",
    "sg:postcode":"8321 EP",
    "sg:province":"Flevoland",
    "wof:name":"Presents",
    "wof:placetype":"venue"
},
  "geometry": {"coordinates":[5.597488,52.661499],"type":"Point"}
}