{
  "type": "Feature",
  "properties": {
    "addr:full":"Elshofwg 6 Groenlo Gelderland 7141 DH",
    "addr:housenumber":"6",
    "addr:postcode":"7141 dh",
    "addr:street":"Elshofwg;Gelderland",
    "iso:country":"NL",
    "sg:address":"Elshofwg 6",
    "sg:city":"Groenlo",
    "sg:orig_category":"Kappers",
    "sg:phone":"+31 544 462 526",
    "sg:postcode":"7141 DH",
    "sg:province":"Gelderland",
    "wof:name":"Coco",
    "wof:placetype":"venue"
},
  "geometry": {"coordinates":[6.6317958832,52.0361938477],"type":"Point"}
}