{
  "type": "Feature",
  "properties": {
    "iso:country":"NL",
    "sg:address":"Grachtweg 8",
    "sg:city":"Zierikzee",
    "sg:classifiers":[
        {
            "category":"Education",
            "subcategory":"Preschool",
            "type":"Public Place"
        }
    ],
    "sg:phone":"+31 111 412 762",
    "sg:postcode":"4301 KJ",
    "sg:province":"Zeeland",
    "sg:tags":[
        "kleuteronderwijs",
        "basis-"
    ],
    "wof:name":"Beatrixschool",
    "wof:placetype":"venue"
},
  "geometry": {"coordinates":[3.926014,51.650475],"type":"Point"}
}