{
  "type": "Feature",
  "properties": {
    "addr:full":"Rapenburg 24 Leiden Zuid-Holland 2311 EW",
    "addr:housenumber":"24",
    "addr:postcode":"2311 ew",
    "addr:street":"Rapenburg",
    "iso:country":"NL",
    "sg:address":"Rapenburg 24",
    "sg:city":"Leiden",
    "sg:orig_category":"Organisaties And Verenigingen",
    "sg:phone":"+31 71 514 2066",
    "sg:postcode":"2311 EW",
    "sg:province":"Zuid-Holland",
    "wof:name":"Augustinus Lvvs",
    "wof:placetype":"venue"
},
  "geometry": {"coordinates":[4.4856271744,52.1585502625],"type":"Point"}
}