{
  "type": "Feature",
  "properties": {
    "addr:full":"Herman Bavinckstraat 308 Rotterdam South Holland 3063 RP",
    "addr:housenumber":"308",
    "addr:postcode":"3063 rp",
    "addr:street":"Herman Bavinckstraat",
    "iso:country":"NL",
    "sg:address":"Herman Bavinckstraat 308",
    "sg:city":"Rotterdam",
    "sg:orig_category":"Fotostudio'S And Fotografen",
    "sg:phone":"+31 10 452 7243",
    "sg:postcode":"3063 RP",
    "sg:province":"South Holland",
    "wof:name":"J Reyngoud",
    "wof:placetype":"venue"
},
  "geometry": {"coordinates":[4.523598,51.913792],"type":"Point"}
}