{
  "type": "Feature",
  "properties": {
    "iso:country":"NL",
    "sg:address":"Weerdestein 98",
    "sg:city":"Dordrecht",
    "sg:orig_category":"Vertaal- And Tolkenbureaus",
    "sg:phone":"+31 78 631 5424",
    "sg:postcode":"3328 ML",
    "sg:province":"South Holland",
    "wof:name":"Portuguia",
    "wof:placetype":"venue"
},
  "geometry": {"coordinates":[4.669453,51.771038],"type":"Point"}
}