{
  "type": "Feature",
  "properties": {
    "addr:full":"Lavendelhof 75 Oosterhout Nb Noord-Brabant 4907 AS",
    "addr:housenumber":"75",
    "addr:postcode":"4907 as",
    "addr:street":"Lavendelhof",
    "iso:country":"NL",
    "sg:address":"Lavendelhof 75",
    "sg:city":"Oosterhout Nb",
    "sg:orig_category":"Vertaalbureaus",
    "sg:phone":"+31 162 437 294",
    "sg:postcode":"4907 AS",
    "sg:province":"Noord-Brabant",
    "sg:website":"http://www.bendito.nl",
    "wof:name":"Bendito",
    "wof:placetype":"venue"
},
  "geometry": {"coordinates":[4.874346,51.652313],"type":"Point"}
}