{
  "type": "Feature",
  "properties": {
    "addr:full":"F De Boerln 57 Amsterdam Noord-Holland 1019 KS",
    "addr:housenumber":"57",
    "addr:postcode":"1019 ks",
    "addr:street":"F",
    "iso:country":"NL",
    "sg:address":"F De Boerln 57",
    "sg:city":"Amsterdam",
    "sg:classifiers":[
        {
            "category":"Utilities",
            "subcategory":"Cable",
            "type":"Services"
        }
    ],
    "sg:phone":"+31 20 419 4559",
    "sg:postcode":"1019 KS",
    "sg:province":"Noord-Holland",
    "sg:tags":[
        "masseur",
        "en",
        "heilgymnasten"
    ],
    "wof:name":"Uit In Balans",
    "wof:placetype":"venue"
},
  "geometry": {"coordinates":[4.893195,52.373119],"type":"Point"}
}