{
  "type": "Feature",
  "properties": {
    "iso:country":"NL",
    "sg:address":"Duitslandln 23",
    "sg:city":"Hazerswoude Dorp",
    "sg:orig_category":"Land- En Tuinbouw - Loonbedrijven",
    "sg:phone":"+31 172 231 757",
    "sg:postcode":"2391 PC",
    "sg:province":"Zuid-Holland",
    "sg:website":"http://www.bedrijfsverzorging.nl",
    "wof:name":"Agrarische Bedrijfsverzorging",
    "wof:placetype":"venue"
},
  "geometry": {"coordinates":[4.625957,52.078224],"type":"Point"}
}