{
  "type": "Feature",
  "properties": {
    "addr:full":"Industrieweg 9 Druten Gelderland 6651 KR",
    "addr:housenumber":"9",
    "addr:postcode":"6651 kr",
    "addr:street":"Industrieweg",
    "iso:country":"NL",
    "sg:address":"Industrieweg 9",
    "sg:city":"Druten",
    "sg:orig_category":"Goederenvervoer Over De Weg",
    "sg:phone":"+31 487 515 529",
    "sg:postcode":"6651 KR",
    "sg:province":"Gelderland",
    "wof:name":"Th.H.J.M. Van Duijghuijzen",
    "wof:placetype":"venue"
},
  "geometry": {"coordinates":[5.583897,51.887791],"type":"Point"}
}