{
  "type": "Feature",
  "properties": {
    "addr:full":"Fred Hendriklaan 4 Leiderdorp Zuid-Holland 2351 GC",
    "addr:housenumber":"4",
    "addr:postcode":"2351 gc",
    "addr:street":"Hendriklaan",
    "iso:country":"NL",
    "sg:address":"Fred Hendriklaan 4",
    "sg:city":"Leiderdorp",
    "sg:classifiers":[
        {
            "category":"Communications",
            "subcategory":"Television Station",
            "type":"Services"
        }
    ],
    "sg:phone":"+31 71 542 1719",
    "sg:postcode":"2351 GC",
    "sg:province":"Zuid-Holland",
    "sg:tags":[
        "video",
        "audio",
        "verhuur"
    ],
    "wof:name":"Sky-Line",
    "wof:placetype":"venue"
},
  "geometry": {"coordinates":[4.527456,52.14669],"type":"Point"}
}