{
  "type": "Feature",
  "properties": {
    "iso:country":"NL",
    "sg:address":"Spuistr 102A",
    "sg:city":"Vlissingen",
    "sg:orig_category":"Warenhuizen",
    "sg:phone":"+31 900 9800",
    "sg:postcode":"4381 HT",
    "sg:province":"Zeeland",
    "wof:name":"Kijkshop",
    "wof:placetype":"venue"
},
  "geometry": {"coordinates":[3.5716819763,51.4438247681],"type":"Point"}
}