{
  "type": "Feature",
  "properties": {
    "addr:full":"Pruisische Veldwg 56 Hengelo Ov Overijssel 7552 AD",
    "addr:housenumber":"56",
    "addr:postcode":"7552 ad",
    "addr:street":"Ov",
    "iso:country":"NL",
    "sg:address":"Pruisische Veldwg 56",
    "sg:city":"Hengelo Ov",
    "sg:orig_category":"Meubelstoffering",
    "sg:phone":"+31 74 291 6079",
    "sg:postcode":"7552 AD",
    "sg:province":"Overijssel",
    "wof:name":"Stegehuis",
    "wof:placetype":"venue"
},
  "geometry": {"coordinates":[6.806349,52.250526],"type":"Point"}
}