{
  "type": "Feature",
  "properties": {
    "iso:country":"NL",
    "sg:address":"Venderstr 5B",
    "sg:city":"Kinrooi-Molenbeersel",
    "sg:orig_category":"Parketvloeren",
    "sg:phone":"+31 89701662",
    "sg:postcode":"B364 0",
    "wof:name":"Janssen, Gebr",
    "wof:placetype":"venue"
},
  "geometry": {"coordinates":[5.73907,51.16671],"type":"Point"}
}