{
  "type": "Feature",
  "properties": {
    "addr:full":"Kapittelweg 293-295 Hilversum North Holland 1216 HZ",
    "addr:housenumber":"293-295",
    "addr:postcode":"1216 hz",
    "addr:street":"Kapittelweg",
    "iso:country":"NL",
    "sg:address":"Kapittelweg 293-295",
    "sg:city":"Hilversum",
    "sg:orig_category":"Opticiens",
    "sg:phone":"+31 35 621 5026",
    "sg:postcode":"1216 HZ",
    "sg:province":"North Holland",
    "wof:name":"Oogzorg Briljant",
    "wof:placetype":"venue"
},
  "geometry": {"coordinates":[5.1404600143,52.2155342102],"type":"Point"}
}