{
  "type": "Feature",
  "properties": {
    "addr:full":"Raadhuisstraat 2 Koog Aan De Zaan North Holland 1541 JC",
    "addr:housenumber":"2",
    "addr:postcode":"1541 jc",
    "addr:street":"Raadhuisstraat",
    "iso:country":"NL",
    "sg:address":"Raadhuisstraat 2",
    "sg:city":"Koog Aan De Zaan",
    "sg:classifiers":[
        {
            "category":"Fast Food",
            "type":"Food & Drink"
        }
    ],
    "sg:phone":"+31 75 617 2590",
    "sg:postcode":"1541 JC",
    "sg:province":"North Holland",
    "sg:tags":[
        "afhaal",
        "restaurant"
    ],
    "wof:name":"Napoli Yam Yam",
    "wof:placetype":"venue"
},
  "geometry": {"coordinates":[4.811261,52.460781],"type":"Point"}
}