{
  "type": "Feature",
  "properties": {
    "iso:country":"NL",
    "sg:address":"Kraaivenstraat 7",
    "sg:city":"Tilburg",
    "sg:orig_category":"Vers Brood And Banket Fab",
    "sg:phone":"+31 13 595 1000",
    "sg:postcode":"5048 AB",
    "sg:province":"North Brabant",
    "wof:name":"Maitre Paul Bv",
    "wof:placetype":"venue"
},
  "geometry": {"coordinates":[5.065933,51.586212],"type":"Point"}
}