{
  "type": "Feature",
  "properties": {
    "addr:full":"Utrechtsestraatweg 6 Amerongen Utrecht 3958 BP",
    "addr:housenumber":"6",
    "addr:postcode":"3958 bp",
    "addr:street":"Utrechtsestraatweg",
    "iso:country":"NL",
    "sg:address":"Utrechtsestraatweg 6",
    "sg:city":"Amerongen",
    "sg:orig_category":"Kinderopvang Behalve Thuis",
    "sg:phone":"+31 343 461 504",
    "sg:postcode":"3958 BP",
    "sg:province":"Utrecht",
    "wof:name":"De Tuimelaar",
    "wof:placetype":"venue"
},
  "geometry": {"coordinates":[5.454271,51.999233],"type":"Point"}
}