{
  "type": "Feature",
  "properties": {
    "addr:full":"Vlier 8 Geldrop North Brabant 5662 TM",
    "addr:housenumber":"8",
    "addr:postcode":"5662 tm",
    "addr:street":"Vlier",
    "iso:country":"NL",
    "sg:address":"Vlier 8",
    "sg:city":"Geldrop",
    "sg:orig_category":"Goederenvervoer Over De Weg",
    "sg:phone":"+31 40 286 3343",
    "sg:postcode":"5662 TM",
    "sg:province":"North Brabant",
    "wof:name":"Transportbedrijf Van Den Boogaard Geldro",
    "wof:placetype":"venue"
},
  "geometry": {"coordinates":[5.544288,51.426414],"type":"Point"}
}