{
  "type": "Feature",
  "properties": {
    "addr:full":"Spoorstr 28 Ruurlo Gelderland 7261 AE",
    "addr:housenumber":"28",
    "addr:postcode":"7261 ae",
    "addr:street":"Spoorstr;Gelderland",
    "iso:country":"NL",
    "sg:address":"Spoorstr 28",
    "sg:city":"Ruurlo",
    "sg:orig_category":"Keukenspeciaalzaken",
    "sg:phone":"+31 573 452 000",
    "sg:postcode":"7261 AE",
    "sg:province":"Gelderland",
    "wof:name":"Holtslag Ruurlo Bv",
    "wof:placetype":"venue"
},
  "geometry": {"coordinates":[6.452383,52.080551],"type":"Point"}
}