{
  "type": "Feature",
  "properties": {
    "addr:full":"W Ten Catestr 1 Hengelo Ov Overijssel 7551 HW",
    "addr:housenumber":"1",
    "addr:postcode":"7551 hw",
    "addr:street":"W Ten Catestr;Ov",
    "iso:country":"NL",
    "sg:address":"W Ten Catestr 1",
    "sg:city":"Hengelo Ov",
    "sg:orig_category":"Makelaars En Adviseurs Onroerende Goederen",
    "sg:phone":"+31 74 256 7979",
    "sg:postcode":"7551 HW",
    "sg:province":"Overijssel",
    "sg:website":"http://www.kempersmakelaardij.com",
    "wof:name":"Kempers Bv",
    "wof:placetype":"venue"
},
  "geometry": {"coordinates":[6.789712,52.266361],"type":"Point"}
}