{
  "type": "Feature",
  "properties": {
    "iso:country":"NL",
    "sg:address":"Sumatraplnts 11A",
    "sg:city":"Amsterdam",
    "sg:orig_category":"Adviesbureaus Bedrijfsorganisatie",
    "sg:phone":"+31 20 463 8803",
    "sg:postcode":"1095 HW",
    "sg:province":"Noord-Holland",
    "wof:name":"Lavrijsen, Ria",
    "wof:placetype":"venue"
},
  "geometry": {"coordinates":[4.943247,52.360725],"type":"Point"}
}