{
  "type": "Feature",
  "properties": {
    "addr:full":"Postbus 200 Bilthoven Utrecht 3720 AE",
    "addr:housenumber":"200",
    "addr:postcode":"3720 ae",
    "addr:street":"Postbus",
    "iso:country":"NL",
    "sg:address":"Postbus 200",
    "sg:city":"Bilthoven",
    "sg:orig_category":"Naamplaten - Fabrieken",
    "sg:phone":"+31 30 229 2505",
    "sg:postcode":"3720 AE",
    "sg:province":"Utrecht",
    "sg:website":"http://www.bureau-indentificatie.nl",
    "wof:name":"Identificatie Bv, Bur",
    "wof:placetype":"venue"
},
  "geometry": {"coordinates":[5.20514,52.12949],"type":"Point"}
}