{
  "type": "Feature",
  "properties": {
    "addr:full":"Billitonkd 166 Utrecht Utrecht 3531 TN",
    "addr:housenumber":"166",
    "addr:postcode":"3531",
    "iso:country":"NL",
    "sg:address":"Billitonkd 166",
    "sg:city":"Utrecht",
    "sg:orig_category":"Beeldende Kunstenaars",
    "sg:phone":"+31 30 294 7098",
    "sg:postcode":"3531 TN",
    "sg:province":"Utrecht",
    "wof:name":"Toeba Design",
    "wof:placetype":"venue"
},
  "geometry": {"coordinates":[5.092754,52.09333],"type":"Point"}
}