{
  "type": "Feature",
  "properties": {
    "iso:country":"NL",
    "sg:address":"Pongastr 3",
    "sg:city":"Marrum",
    "sg:orig_category":"Drukkerijen",
    "sg:phone":"+31 518 412 336",
    "sg:postcode":"9073 LK",
    "sg:province":"Friesland",
    "wof:name":"Letter Studio, De",
    "wof:placetype":"venue"
},
  "geometry": {"coordinates":[5.80006,53.323303],"type":"Point"}
}