{
  "type": "Feature",
  "properties": {
    "iso:country":"NL",
    "sg:address":"Dorpsstr 66",
    "sg:city":"Hellendoorn",
    "sg:classifiers":[
        {
            "category":"Travel",
            "subcategory":"Hotels & Motels",
            "type":"Entertainment"
        }
    ],
    "sg:phone":"+31 548 654 265",
    "sg:postcode":"7447 CT",
    "sg:province":"Overijssel",
    "wof:name":"Tonne, In De",
    "wof:placetype":"venue"
},
  "geometry": {"coordinates":[6.449787,52.391953],"type":"Point"}
}