{
  "type": "Feature",
  "properties": {
    "iso:country":"NL",
    "sg:address":"Verwersstr 29",
    "sg:city":"S Hertogenbosch",
    "sg:orig_category":"Verzekeringen - Verzekeringskantoren",
    "sg:phone":"+31 73 548 1400",
    "sg:postcode":"5211 HT",
    "sg:province":"Noord-Brabant",
    "sg:website":"http://www.malherbe.nl",
    "wof:name":"Malherbe De Juvigny Assuranti\u00ebn Bv",
    "wof:placetype":"venue"
},
  "geometry": {"coordinates":[5.30478,51.687092],"type":"Point"}
}