{
  "type": "Feature",
  "properties": {
    "addr:full":"Begynenstr 1A Oss British Columbia 5341 BC",
    "addr:housenumber":"1a",
    "addr:postcode":"5341 bc",
    "addr:street":"Begynenstr",
    "iso:country":"NL",
    "sg:address":"Begynenstr 1A",
    "sg:city":"Oss",
    "sg:orig_category":"Verzekeringen - Verzekeringskantoren",
    "sg:phone":"+31 412 645 045",
    "sg:postcode":"5341 BC",
    "sg:province":"British Columbia",
    "wof:name":"Verbossen",
    "wof:placetype":"venue"
},
  "geometry": {"coordinates":[-126.555511,54.485668],"type":"Point"}
}