{
  "type": "Feature",
  "properties": {
    "addr:full":"Benedictusstr 13 Eindhoven Noord-Brabant 5612 GV",
    "addr:housenumber":"13",
    "addr:postcode":"5612 gv",
    "addr:street":"Benedictusstr",
    "iso:country":"NL",
    "sg:address":"Benedictusstr 13",
    "sg:city":"Eindhoven",
    "sg:orig_category":"Webdesign Bureaus",
    "sg:phone":"+31 40 295 0156",
    "sg:postcode":"5612 GV",
    "sg:province":"Noord-Brabant",
    "wof:name":"Bakx, Leo",
    "wof:placetype":"venue"
},
  "geometry": {"coordinates":[5.4683680534,51.4515266418],"type":"Point"}
}