{
  "type": "Feature",
  "properties": {
    "iso:country":"NL",
    "sg:address":"Jan Van Schaffelaarstr 42",
    "sg:city":"Barneveld",
    "sg:orig_category":"Juweliers",
    "sg:phone":"+31 342 412 297",
    "sg:postcode":"3771 BV",
    "sg:province":"Gelderland",
    "wof:name":"Kaasschieter Juweliers",
    "wof:placetype":"venue"
},
  "geometry": {"coordinates":[5.587021,52.140739],"type":"Point"}
}