{
  "type": "Feature",
  "properties": {
    "addr:full":"Tolberterstraat 1 Leek Groningen 9351 BA",
    "addr:housenumber":"1",
    "addr:postcode":"9351 ba",
    "addr:street":"Tolberterstraat",
    "iso:country":"NL",
    "sg:address":"Tolberterstraat 1",
    "sg:city":"Leek",
    "sg:orig_category":"Herenkleding",
    "sg:phone":"+31 594 510 800",
    "sg:postcode":"9351 BA",
    "sg:province":"Groningen",
    "wof:name":"Man, De",
    "wof:placetype":"venue"
},
  "geometry": {"coordinates":[6.388936,53.164536],"type":"Point"}
}