{
  "type": "Feature",
  "properties": {
    "iso:country":"NL",
    "sg:address":"Noorderdiep 476",
    "sg:city":"Nieuw Buinen",
    "sg:orig_category":"Woninginrichting",
    "sg:phone":"+31 599 613 928",
    "sg:postcode":"9521 BR",
    "sg:province":"Provincie Drenthe",
    "wof:name":"Hero Haak Hafa Bv",
    "wof:placetype":"venue"
},
  "geometry": {"coordinates":[6.954146862,52.966003418],"type":"Point"}
}