{
  "type": "Feature",
  "properties": {
    "addr:full":"Kralingseweg 360 Rotterdam South Holland 3066 RC",
    "addr:housenumber":"360",
    "addr:postcode":"3066 rc",
    "addr:street":"Kralingseweg",
    "iso:country":"NL",
    "sg:address":"Kralingseweg 360",
    "sg:city":"Rotterdam",
    "sg:orig_category":"Bedrijfs- And Managementsconsultants",
    "sg:phone":"+31 10 447 2544",
    "sg:postcode":"3066 RC",
    "sg:province":"South Holland",
    "wof:name":"Van Hasenbroek Consultancy",
    "wof:placetype":"venue"
},
  "geometry": {"coordinates":[4.553925,51.930424],"type":"Point"}
}