{
  "type": "Feature",
  "properties": {
    "addr:full":"Willem De Zwijgersingel 3 Gouda South Holland 2805 BP",
    "addr:housenumber":"3",
    "addr:postcode":"2805 bp",
    "addr:street":"Willem De Zwijgersingel",
    "iso:country":"NL",
    "sg:address":"Willem De Zwijgersingel 3",
    "sg:city":"Gouda",
    "sg:orig_category":"Verenigingen En Stichtingen",
    "sg:phone":"+31 182 585 770",
    "sg:postcode":"2805 BP",
    "sg:province":"South Holland",
    "wof:name":"Besturenraad Prot Chr Onderwijs",
    "wof:placetype":"venue"
},
  "geometry": {"coordinates":[4.711143,52.020943],"type":"Point"}
}