{
  "type": "Feature",
  "properties": {
    "addr:full":"Nyendal 42 Driebergen Rysenb Utrecht 3972 KC",
    "addr:housenumber":"42",
    "addr:postcode":"3972 kc",
    "addr:street":"Nyendal;Rysenb",
    "iso:country":"NL",
    "sg:address":"Nyendal 42",
    "sg:city":"Driebergen Rysenb",
    "sg:orig_category":"Elektronica - Ontwikkeling En Groothandel",
    "sg:phone":"+31 343 518 724",
    "sg:postcode":"3972 KC",
    "sg:province":"Utrecht",
    "sg:website":"http://www.elproma.nl",
    "wof:name":"Elproma Bv",
    "wof:placetype":"venue"
},
  "geometry": {"coordinates":[5.283655,52.051552],"type":"Point"}
}