{
  "type": "Feature",
  "properties": {
    "addr:full":"Melkmarkt 25 Zwolle Overijssel 8011 MA",
    "addr:housenumber":"25",
    "addr:postcode":"8011 ma",
    "addr:street":"Melkmarkt",
    "iso:country":"NL",
    "sg:address":"Melkmarkt 25",
    "sg:city":"Zwolle",
    "sg:orig_category":"Hypotheken",
    "sg:phone":"+31 38 423 6111",
    "sg:postcode":"8011 MA",
    "sg:province":"Overijssel",
    "wof:name":"Hypotheek Advies Centrum",
    "wof:placetype":"venue"
},
  "geometry": {"coordinates":[6.091268,52.512676],"type":"Point"}
}