{
  "type": "Feature",
  "properties": {
    "iso:country":"NL",
    "sg:address":"Mr V Kleffensstr 4",
    "sg:city":"Arnhem",
    "sg:orig_category":"Bedrijfshuisvesting",
    "sg:phone":"+31 26 400 1188",
    "sg:postcode":"6842 CV",
    "sg:province":"Gelderland",
    "sg:website":"http://www.engelsing.nl",
    "wof:name":"Engelsing Bedrijfsmakelaars",
    "wof:placetype":"venue"
},
  "geometry": {"coordinates":[5.881475,51.957588],"type":"Point"}
}