{
  "type": "Feature",
  "properties": {
    "addr:full":"Van Der Helstlaan 5 Bilthoven Utrecht 3723 EV",
    "addr:housenumber":"5",
    "addr:postcode":"3723 ev",
    "addr:street":"Van Der Helstlaan",
    "iso:country":"NL",
    "sg:address":"Van Der Helstlaan 5",
    "sg:city":"Bilthoven",
    "sg:orig_category":"Juridische Dienstverlening",
    "sg:phone":"+31 30 228 2417",
    "sg:postcode":"3723 EV",
    "sg:province":"Utrecht",
    "wof:name":"Arbeidsrechtelijk Adv. Bur. Boezeman-Hoy",
    "wof:placetype":"venue"
},
  "geometry": {"coordinates":[5.211924,52.140079],"type":"Point"}
}