{
  "type": "Feature",
  "properties": {
    "addr:full":"Beukelswg 73A Rotterdam Zuid-Holland 3022 GE",
    "addr:housenumber":"73a",
    "addr:postcode":"3022",
    "addr:street":"Beukelswg",
    "iso:country":"NL",
    "sg:address":"Beukelswg 73A",
    "sg:city":"Rotterdam",
    "sg:orig_category":"Architecten En Architectenbureaus",
    "sg:phone":"+31 10 425 7505",
    "sg:postcode":"3022 GE",
    "sg:province":"Zuid-Holland",
    "wof:name":"Tiemensma",
    "wof:placetype":"venue"
},
  "geometry": {"coordinates":[4.444019,51.920185],"type":"Point"}
}