{
  "type": "Feature",
  "properties": {
    "iso:country":"NL",
    "sg:address":"D Yserinckwg 27",
    "sg:city":"Vyfhuizen",
    "sg:orig_category":"Adviesbureaus Beroeps- En Schoolkeuze",
    "sg:phone":"+31 23 558 3644",
    "sg:postcode":"2141 AA",
    "sg:province":"Noord-Holland",
    "wof:name":"Hiq",
    "wof:placetype":"venue"
},
  "geometry": {"coordinates":[4.679693,52.351852],"type":"Point"}
}