{
  "type": "Feature",
  "properties": {
    "addr:full":"W Havendk 25 Roosendaal Noord-Brabant 4703 RA",
    "addr:housenumber":"25",
    "addr:postcode":"4703 ra",
    "addr:street":"W",
    "iso:country":"NL",
    "sg:address":"W Havendk 25",
    "sg:city":"Roosendaal",
    "sg:orig_category":"Airconditioning",
    "sg:phone":"+31 165 536 880",
    "sg:postcode":"4703 RA",
    "sg:province":"Noord-Brabant",
    "wof:name":"Cooltec",
    "wof:placetype":"venue"
},
  "geometry": {"coordinates":[4.45767,51.531403],"type":"Point"}
}