{
  "type": "Feature",
  "properties": {
    "addr:full":"Raamsingel 2 Haarlem North Holland 2012 DS",
    "addr:housenumber":"2",
    "addr:postcode":"2012 ds",
    "addr:street":"Raamsingel",
    "iso:country":"NL",
    "sg:address":"Raamsingel 2",
    "sg:city":"Haarlem",
    "sg:orig_category":"Boekenuitgeverijen",
    "sg:phone":"+31 23 532 4400",
    "sg:postcode":"2012 DS",
    "sg:province":"North Holland",
    "wof:name":"Volute",
    "wof:placetype":"venue"
},
  "geometry": {"coordinates":[4.626336,52.377102],"type":"Point"}
}