{
  "type": "Feature",
  "properties": {
    "addr:full":"Broersveld 127 Schiedam Zuid-Holland 3111 LG",
    "addr:housenumber":"127",
    "addr:postcode":"3111 lg",
    "addr:street":"Broersveld",
    "iso:country":"NL",
    "sg:address":"Broersveld 127",
    "sg:city":"Schiedam",
    "sg:orig_category":"Zonweringen",
    "sg:phone":"+31 10 473 3316",
    "sg:postcode":"3111 LG",
    "sg:province":"Zuid-Holland",
    "sg:website":"http://www.buitenzonwering.nl",
    "wof:name":"Villerius Vof",
    "wof:placetype":"venue"
},
  "geometry": {"coordinates":[4.401157,51.916939],"type":"Point"}
}