{
  "type": "Feature",
  "properties": {
    "addr:full":"Fransestraat 47 Nijmegen Gelderland 6524 HV",
    "addr:housenumber":"47",
    "addr:postcode":"6524 hv",
    "addr:street":"Fransestraat;Gelderland",
    "iso:country":"NL",
    "sg:address":"Fransestraat 47",
    "sg:city":"Nijmegen",
    "sg:classifiers":[
        {
            "category":"Fast Food",
            "type":"Food & Drink"
        }
    ],
    "sg:phone":"+31 24 322 1934",
    "sg:postcode":"6524 HV",
    "sg:province":"Gelderland",
    "sg:tags":[
        "afhaal",
        "restaurant"
    ],
    "wof:name":"Cafetaria St. Anna Family",
    "wof:placetype":"venue"
},
  "geometry": {"coordinates":[5.86222,51.838017],"type":"Point"}
}