{
  "type": "Feature",
  "properties": {
    "addr:full":"L J Costerstr 36 Venlo Limburg 5916 PS",
    "addr:housenumber":"36",
    "addr:postcode":"5916 ps",
    "addr:street":"L",
    "iso:country":"NL",
    "sg:address":"L J Costerstr 36",
    "sg:city":"Venlo",
    "sg:orig_category":"Verf En Lak - Fabrieken En Groothandel",
    "sg:phone":"+31 77 351 8048",
    "sg:postcode":"5916 PS",
    "sg:province":"Limburg",
    "wof:name":"Felix Bv",
    "wof:placetype":"venue"
},
  "geometry": {"coordinates":[6.183255,51.389519],"type":"Point"}
}