{
  "type": "Feature",
  "properties": {
    "addr:full":"Kovelaarstraat 13 Utrecht Utrecht 3582 GN",
    "addr:housenumber":"13",
    "addr:postcode":"3582 gn",
    "addr:street":"Kovelaarstraat",
    "iso:country":"NL",
    "sg:address":"Kovelaarstraat 13",
    "sg:city":"Utrecht",
    "sg:orig_category":"Loodgieterswerk, Verwarming And Sanitaire Installaties",
    "sg:phone":"+31 30 252 3477",
    "sg:postcode":"3582 GN",
    "sg:province":"Utrecht",
    "wof:name":"N Feddes",
    "wof:placetype":"venue"
},
  "geometry": {"coordinates":[5.134001,52.075947],"type":"Point"}
}