{
  "type": "Feature",
  "properties": {
    "addr:full":"Bosschewg 11 Drunen North Brabant 5151 BA",
    "addr:housenumber":"11",
    "addr:postcode":"5151 ba",
    "addr:street":"Bosschewg",
    "iso:country":"NL",
    "sg:address":"Bosschewg 11",
    "sg:city":"Drunen",
    "sg:orig_category":"Bedrijfsopleidingen",
    "sg:phone":"+31 416 322 899",
    "sg:postcode":"5151 BA",
    "sg:province":"North Brabant",
    "sg:website":"http://www.targettraining.nl",
    "wof:name":"Target Training",
    "wof:placetype":"venue"
},
  "geometry": {"coordinates":[5.147548,51.686623],"type":"Point"}
}