{
  "type": "Feature",
  "properties": {
    "addr:full":"Lindenstr 52 Abbekerk Noord-Holland 1657 AV",
    "addr:housenumber":"52",
    "addr:postcode":"1657 av",
    "addr:street":"Lindenstr",
    "iso:country":"NL",
    "sg:address":"Lindenstr 52",
    "sg:city":"Abbekerk",
    "sg:orig_category":"Administratie- En Boekhoudkantoren",
    "sg:phone":"+31 229 582 669",
    "sg:postcode":"1657 AV",
    "sg:province":"Noord-Holland",
    "wof:name":"Papenburg, Ben",
    "wof:placetype":"venue"
},
  "geometry": {"coordinates":[5.024588,52.730675],"type":"Point"}
}