{
  "type": "Feature",
  "properties": {
    "iso:country":"NL",
    "sg:address":"Korte Kerkstraat 3",
    "sg:city":"Schiedam",
    "sg:orig_category":"Film-, Tv- And Videoproductie",
    "sg:phone":"+31 10 473 5977",
    "sg:postcode":"3111 JE",
    "sg:province":"South Holland",
    "wof:name":"Jfk Productions (Multimedia Consultaties",
    "wof:placetype":"venue"
},
  "geometry": {"coordinates":[4.398177,51.917721],"type":"Point"}
}