{
  "type": "Feature",
  "properties": {
    "addr:full":"Transportbaan 12 Winschoten Groningen 9672 BK",
    "addr:housenumber":"12",
    "addr:postcode":"9672 bk",
    "addr:street":"Transportbaan",
    "iso:country":"NL",
    "sg:address":"Transportbaan 12",
    "sg:city":"Winschoten",
    "sg:orig_category":"Bibliotheken And Openbare Archieven",
    "sg:phone":"+31 597 431 433",
    "sg:postcode":"9672 BK",
    "sg:province":"Groningen",
    "wof:name":"Cas",
    "wof:placetype":"venue"
},
  "geometry": {"coordinates":[7.046988,53.145546],"type":"Point"}
}