{
  "type": "Feature",
  "properties": {
    "addr:full":"Pleyendal 6 Dalfsen Overijssel 7721 DE",
    "addr:housenumber":"6",
    "addr:postcode":"7721 de",
    "addr:street":"Pleyendal",
    "iso:country":"NL",
    "sg:address":"Pleyendal 6",
    "sg:city":"Dalfsen",
    "sg:orig_category":"Fietsen En Bromfietsen",
    "sg:phone":"+31 529 435 720",
    "sg:postcode":"7721 DE",
    "sg:province":"Overijssel",
    "wof:name":"Salland",
    "wof:placetype":"venue"
},
  "geometry": {"coordinates":[6.260303,52.505428],"type":"Point"}
}