{
  "type": "Feature",
  "properties": {
    "addr:full":"Molenstraat 22 Delft Zuid-Holland 2611 KA",
    "addr:housenumber":"22",
    "addr:postcode":"2611 ka",
    "addr:street":"Molenstraat",
    "iso:country":"NL",
    "sg:address":"Molenstraat 22",
    "sg:city":"Delft",
    "sg:orig_category":"Architecten",
    "sg:phone":"+31 15 212 2795",
    "sg:postcode":"2611 KA",
    "sg:province":"Zuid-Holland",
    "wof:name":"Bureau Bakker Delft",
    "wof:placetype":"venue"
},
  "geometry": {"coordinates":[4.35479,52.015846],"type":"Point"}
}