{
  "type": "Feature",
  "properties": {
    "addr:full":"Postbus 241 Lochem Gelderland 7240 AE",
    "addr:housenumber":"241",
    "addr:postcode":"7240 ae",
    "addr:street":"Postbus;Gelderland",
    "iso:country":"NL",
    "sg:address":"Postbus 241",
    "sg:city":"Lochem",
    "sg:orig_category":"Verf En Lak",
    "sg:phone":"+31 575 432 484",
    "sg:postcode":"7240 AE",
    "sg:province":"Gelderland",
    "sg:website":"http://www.trix-tekenremover.nl",
    "wof:name":"Coda Bv",
    "wof:placetype":"venue"
},
  "geometry": {"coordinates":[6.409836,52.162872],"type":"Point"}
}