{
  "type": "Feature",
  "properties": {
    "iso:country":"NL",
    "sg:address":"Lysterbeswg .",
    "sg:city":"Nunspeet",
    "sg:orig_category":"Peuterspeelzalen",
    "sg:phone":"+31 341 258 440",
    "sg:postcode":"8072 XV",
    "sg:province":"Gelderland",
    "wof:name":"Nijntje",
    "wof:placetype":"venue"
},
  "geometry": {"coordinates":[5.795552,52.384724],"type":"Point"}
}