{
  "type": "Feature",
  "properties": {
    "addr:full":"Nooitgedacht 12 Zeist Utrecht 3701 AN",
    "addr:housenumber":"12",
    "addr:postcode":"3701 an",
    "addr:street":"Nooitgedacht",
    "iso:country":"NL",
    "sg:address":"Nooitgedacht 12",
    "sg:city":"Zeist",
    "sg:orig_category":"Open Haarden",
    "sg:phone":"+31 30 692 2799",
    "sg:postcode":"3701 AN",
    "sg:province":"Utrecht",
    "wof:name":"Heleen Kienhuis",
    "wof:placetype":"venue"
},
  "geometry": {"coordinates":[5.241846,52.082142],"type":"Point"}
}