{
  "type": "Feature",
  "properties": {
    "addr:full":"V Vredenburchwg 67 Ryswyk Zh South Holland 2282 SE",
    "addr:housenumber":"67",
    "addr:postcode":"2282 se",
    "addr:street":"Ryswyk Zh",
    "iso:country":"NL",
    "sg:address":"V Vredenburchwg 67",
    "sg:city":"Ryswyk Zh",
    "sg:orig_category":"Begraafplaatsen",
    "sg:phone":"+31 70 395 2697",
    "sg:postcode":"2282 SE",
    "sg:province":"South Holland",
    "wof:name":"Bonifatius Rk, H",
    "wof:placetype":"venue"
},
  "geometry": {"coordinates":[4.33694,52.056503],"type":"Point"}
}