{
  "type": "Feature",
  "properties": {
    "addr:full":"Tinnegieter 9 Leiderdorp South Holland 2353 XB",
    "addr:housenumber":"9",
    "addr:postcode":"2353 xb",
    "addr:street":"Tinnegieter",
    "iso:country":"NL",
    "sg:address":"Tinnegieter 9",
    "sg:city":"Leiderdorp",
    "sg:orig_category":"Kappers",
    "sg:phone":"+31 6 24148431",
    "sg:postcode":"2353 XB",
    "sg:province":"South Holland",
    "wof:name":"Knipoog Haarstyling & Visagie",
    "wof:placetype":"venue"
},
  "geometry": {"coordinates":[4.522207,52.170265],"type":"Point"}
}