{
  "type": "Feature",
  "properties": {
    "iso:country":"NL",
    "sg:address":"D Klompwg 126",
    "sg:city":"Bergen Nh",
    "sg:orig_category":"Homeopathie",
    "sg:phone":"+31 72 581 8202",
    "sg:postcode":"1861 NG",
    "sg:province":"Noord-Holland",
    "wof:name":"Boon, R",
    "wof:placetype":"venue"
},
  "geometry": {"coordinates":[4.706596,52.662407],"type":"Point"}
}