{
  "type": "Feature",
  "properties": {
    "addr:full":"Noordpolderkade 498 'S Gravenhage Zuid-Holland 2516 JV",
    "addr:housenumber":"498 '",
    "addr:postcode":"2516 jv",
    "addr:street":"Noordpolderkade",
    "iso:country":"NL",
    "sg:address":"Noordpolderkade 498",
    "sg:city":"'S Gravenhage",
    "sg:orig_category":"Boekhouders",
    "sg:phone":"+31 70 399 0050",
    "sg:postcode":"2516 JV",
    "sg:province":"Zuid-Holland",
    "wof:name":"Gardenbroek Admin Kant",
    "wof:placetype":"venue"
},
  "geometry": {"coordinates":[4.336724,52.060673],"type":"Point"}
}