{
  "type": "Feature",
  "properties": {
    "addr:full":"Witpoel 2 Bavel Noord-Brabant 4854 RX",
    "addr:housenumber":"2",
    "addr:postcode":"4854 rx",
    "addr:street":"Witpoel",
    "iso:country":"NL",
    "sg:address":"Witpoel 2",
    "sg:city":"Bavel",
    "sg:orig_category":"Bloemen And Planten",
    "sg:phone":"+31 161 432 619",
    "sg:postcode":"4854 RX",
    "sg:province":"Noord-Brabant",
    "wof:name":"Present",
    "wof:placetype":"venue"
},
  "geometry": {"coordinates":[4.833608,51.561443],"type":"Point"}
}