{
  "type": "Feature",
  "properties": {
    "addr:full":"Pr Bernhardln 37 Ysselstein Ut Utrecht 3402 CD",
    "addr:housenumber":"37",
    "addr:postcode":"3402 cd",
    "addr:street":"Ysselstein",
    "iso:country":"NL",
    "sg:address":"Pr Bernhardln 37",
    "sg:city":"Ysselstein Ut",
    "sg:orig_category":"Gordijnen",
    "sg:phone":"+31 30 687 1410",
    "sg:postcode":"3402 CD",
    "sg:province":"Utrecht",
    "wof:name":"Lofr?",
    "wof:placetype":"venue"
},
  "geometry": {"coordinates":[5.0281,52.02663],"type":"Point"}
}