{
  "type": "Feature",
  "properties": {
    "addr:full":"C Huygensstr 12 Volendam Noord-Holland 1131 VC",
    "addr:housenumber":"12",
    "addr:postcode":"1131 vc",
    "iso:country":"NL",
    "sg:address":"C Huygensstr 12",
    "sg:city":"Volendam",
    "sg:orig_category":"Fotolaboratoria",
    "sg:phone":"+31 299 366 944",
    "sg:postcode":"1131 VC",
    "sg:province":"Noord-Holland",
    "wof:name":"Verbeelding, De",
    "wof:placetype":"venue"
},
  "geometry": {"coordinates":[5.07963,52.503662],"type":"Point"}
}