{
  "type": "Feature",
  "properties": {
    "addr:full":"Javastraat 9 Assen Provincie Drenthe 9401 KZ",
    "addr:housenumber":"9",
    "addr:postcode":"9401",
    "addr:street":"Javastraat;Provincie Drenthe",
    "iso:country":"NL",
    "sg:address":"Javastraat 9",
    "sg:city":"Assen",
    "sg:orig_category":"Werving And Selectie Van Tijdelijk Personeel And Uitzendkantoren",
    "sg:phone":"+31 592 301 023",
    "sg:postcode":"9401 KZ",
    "sg:province":"Provincie Drenthe",
    "wof:name":"Nlg Bv",
    "wof:placetype":"venue"
},
  "geometry": {"coordinates":[6.5666627884,52.9946365356],"type":"Point"}
}