{
  "type": "Feature",
  "properties": {
    "iso:country":"NL",
    "sg:address":"Ged Insteekhaven 85",
    "sg:city":"Amsterdam",
    "sg:orig_category":"Scholen Voor Basisonderwijs",
    "sg:phone":"+31 20 614 4951",
    "sg:postcode":"1021 RA",
    "sg:province":"Noord-Holland",
    "wof:name":"Elkadissia",
    "wof:placetype":"venue"
},
  "geometry": {"coordinates":[4.91567,52.383331],"type":"Point"}
}