{
  "type": "Feature",
  "properties": {
    "addr:full":"Janstr 3 Velp Gld Gelderland 6882 BS",
    "addr:housenumber":"3;6882",
    "addr:postcode":"bs",
    "addr:street":"Janstr;Gld Gelderland",
    "iso:country":"NL",
    "sg:address":"Janstr 3",
    "sg:city":"Velp Gld",
    "sg:orig_category":"Bloemen En Planten - Decoratie",
    "sg:phone":"+31 26 364 3514",
    "sg:postcode":"6882 BS",
    "sg:province":"Gelderland",
    "wof:name":"Flor ? Style",
    "wof:placetype":"venue"
},
  "geometry": {"coordinates":[5.9673,51.991516],"type":"Point"}
}