{
  "type": "Feature",
  "properties": {
    "addr:full":"Hofstraat 5 Winschoten Groningen 9671 KL",
    "addr:housenumber":"5",
    "addr:postcode":"9671 kl",
    "addr:street":"Hofstraat",
    "iso:country":"NL",
    "sg:address":"Hofstraat 5",
    "sg:city":"Winschoten",
    "sg:orig_category":"Goederenvervoer Over De Weg",
    "sg:phone":"+31 597 413 194",
    "sg:postcode":"9671 KL",
    "sg:province":"Groningen",
    "wof:name":"P J Bertus",
    "wof:placetype":"venue"
},
  "geometry": {"coordinates":[7.029727,53.145241],"type":"Point"}
}