{
  "type": "Feature",
  "properties": {
    "iso:country":"NL",
    "sg:address":"Postbus 15064",
    "sg:city":"Utrecht",
    "sg:orig_category":"Scholen Voor Basisonderwijs",
    "sg:phone":"+31 30 271 1395",
    "sg:postcode":"3501 BB",
    "sg:province":"Noord-Holland",
    "wof:name":"Paulus Rk",
    "wof:placetype":"venue"
},
  "geometry": {"coordinates":[5.12289,52.091],"type":"Point"}
}