{
  "type": "Feature",
  "properties": {
    "addr:full":"Oudenoord 170 Utrecht Utrecht 3513 EV",
    "addr:housenumber":"170",
    "addr:postcode":"3513 ev",
    "addr:street":"Oudenoord",
    "iso:country":"NL",
    "sg:address":"Oudenoord 170",
    "sg:city":"Utrecht",
    "sg:orig_category":"Vakorganisaties",
    "sg:phone":"+31 30 234 9666",
    "sg:postcode":"3513 EV",
    "sg:province":"Utrecht",
    "wof:name":"Abva-Kabo Fnv",
    "wof:placetype":"venue"
},
  "geometry": {"coordinates":[5.110532,52.098206],"type":"Point"}
}