{
  "type": "Feature",
  "properties": {
    "iso:country":"NL",
    "sg:address":"Blauwstr 69",
    "sg:city":"Steenbergen Nb",
    "sg:orig_category":"Schoenen",
    "sg:phone":"+31 167 561 870",
    "sg:postcode":"4651 GB",
    "sg:province":"Noord-Brabant",
    "wof:name":"Hoven, Van Den",
    "wof:placetype":"venue"
},
  "geometry": {"coordinates":[4.318945,51.586544],"type":"Point"}
}