{
  "type": "Feature",
  "properties": {
    "iso:country":"NL",
    "sg:address":"Vrijheidslaan 2",
    "sg:city":"Nijkerk Gld",
    "sg:orig_category":"Fietshandelaren",
    "sg:phone":"+31 33 245 1427",
    "sg:postcode":"3861 JA",
    "sg:province":"Gelderland",
    "wof:name":"Rijwielspeciaalzaak G. Flier",
    "wof:placetype":"venue"
},
  "geometry": {"coordinates":[5.483712,52.225594],"type":"Point"}
}