{
  "type": "Feature",
  "properties": {
    "addr:full":"Stuijvenburchstraat 22 Eerbeek Gelderland 6961 DR",
    "addr:housenumber":"22;6961",
    "addr:street":"Stuijvenburchstraat;Gelderland;Dr",
    "iso:country":"NL",
    "sg:address":"Stuijvenburchstraat 22",
    "sg:city":"Eerbeek",
    "sg:orig_category":"Opticiens",
    "sg:phone":"+31 313 651 383",
    "sg:postcode":"6961 DR",
    "sg:province":"Gelderland",
    "wof:name":"Fa Hendriks",
    "wof:placetype":"venue"
},
  "geometry": {"coordinates":[6.0677871704,52.1046981812],"type":"Point"}
}