{
  "type": "Feature",
  "properties": {
    "addr:full":"Dijkweg 163 Andijk North Holland 1619 HJ",
    "addr:housenumber":"163",
    "addr:postcode":"1619 hj",
    "addr:street":"Dijkweg",
    "iso:country":"NL",
    "sg:address":"Dijkweg 163",
    "sg:city":"Andijk",
    "sg:orig_category":"Bloemen And Planten Gh",
    "sg:phone":"+31 228 592 814",
    "sg:postcode":"1619 HJ",
    "sg:province":"North Holland",
    "wof:name":"Lico Export B.V.",
    "wof:placetype":"venue"
},
  "geometry": {"coordinates":[5.18707,52.746799],"type":"Point"}
}