{
  "type": "Feature",
  "properties": {
    "addr:full":"Zurinkstraat 4 Geesteren Ov Overijssel 7678 AC",
    "addr:housenumber":"4",
    "addr:postcode":"7678 ac",
    "addr:street":"Zurinkstraat;Ov",
    "iso:country":"NL",
    "sg:address":"Zurinkstraat 4",
    "sg:city":"Geesteren Ov",
    "sg:orig_category":"Paramedische Behandelingen",
    "sg:phone":"+31 546 631 997",
    "sg:postcode":"7678 AC",
    "sg:province":"Overijssel",
    "wof:name":"Logopedist J A Stam Masselink",
    "wof:placetype":"venue"
},
  "geometry": {"coordinates":[6.737532,52.420441],"type":"Point"}
}