{
  "type": "Feature",
  "properties": {
    "addr:full":"Goejanverwelledk 16 Gouda Zuid-Holland 2806 NZ",
    "addr:housenumber":"16",
    "addr:postcode":"2806 nz",
    "addr:street":"Goejanverwelledk",
    "iso:country":"NL",
    "sg:address":"Goejanverwelledk 16",
    "sg:city":"Gouda",
    "sg:orig_category":"Ministeries En Overheidsinstellingen",
    "sg:phone":"+31 182 513 691",
    "sg:postcode":"2806 NZ",
    "sg:province":"Zuid-Holland",
    "wof:name":"Rijkswaterstaat Waaiersluis",
    "wof:placetype":"venue"
},
  "geometry": {"coordinates":[4.731852,52.009403],"type":"Point"}
}