{
  "type": "Feature",
  "properties": {
    "iso:country":"NL",
    "sg:address":"Heydsewg 4",
    "sg:city":"Monster",
    "sg:orig_category":"Verhuur",
    "sg:phone":"+31 174 212 062",
    "sg:postcode":"2681 VN",
    "sg:province":"Zuid-Holland",
    "sg:website":"http://www.vanstraalen.com",
    "wof:name":"Straalen, Van",
    "wof:placetype":"venue"
},
  "geometry": {"coordinates":[4.167663,52.026871],"type":"Point"}
}