{
  "type": "Feature",
  "properties": {
    "addr:full":"Rupsklaver 112 Rotterdam Zuid-Holland 3069 DC",
    "addr:housenumber":"112",
    "addr:postcode":"3069",
    "addr:street":"Rupsklaver",
    "iso:country":"NL",
    "sg:address":"Rupsklaver 112",
    "sg:city":"Rotterdam",
    "sg:orig_category":"Fotostudio'S And Fotografen",
    "sg:phone":"+31 10 420 8032",
    "sg:postcode":"3069 DC",
    "sg:province":"Zuid-Holland",
    "wof:name":"Melchior Verheezen Mode- & Reclamefotografie",
    "wof:placetype":"venue"
},
  "geometry": {"coordinates":[4.532563,51.964359],"type":"Point"}
}