{
  "type": "Feature",
  "properties": {
    "addr:full":"Meent 100 Rotterdam Zuid-Holland 3011 JR",
    "addr:housenumber":"100",
    "addr:postcode":"3011 jr",
    "addr:street":"Meent",
    "iso:country":"NL",
    "sg:address":"Meent 100",
    "sg:city":"Rotterdam",
    "sg:orig_category":"Werving And Selectie Van Tijdelijk Personeel And Uitzendkantoren",
    "sg:phone":"+31 10 411 6392",
    "sg:postcode":"3011 JR",
    "sg:province":"Zuid-Holland",
    "wof:name":"Olympia Uitzendburo Bv",
    "wof:placetype":"venue"
},
  "geometry": {"coordinates":[4.4818410873,51.9217224121],"type":"Point"}
}