{
  "type": "Feature",
  "properties": {
    "iso:country":"NL",
    "sg:address":"De Paal 1-6",
    "sg:city":"Almere",
    "sg:classifiers":[
        {
            "category":"Fast Food",
            "type":"Food & Drink"
        }
    ],
    "sg:phone":"+31 36 538 6595",
    "sg:postcode":"1351 JA",
    "sg:province":"NL.",
    "sg:tags":[
        "afhaal",
        "restaurant"
    ],
    "wof:name":"Western Grill Nederland Nv",
    "wof:placetype":"venue"
},
  "geometry": {"coordinates":[5.219284,52.347095],"type":"Point"}
}