{
  "type": "Feature",
  "properties": {
    "addr:full":"Waalsewg 12A Tull En T Waal Utrecht 3999 NS",
    "addr:housenumber":"12a",
    "addr:postcode":"3999 ns",
    "addr:street":"Waalsewg;En T Waal",
    "iso:country":"NL",
    "sg:address":"Waalsewg 12A",
    "sg:city":"Tull En T Waal",
    "sg:orig_category":"Beveiliging",
    "sg:phone":"+31 30 601 1777",
    "sg:postcode":"3999 NS",
    "sg:province":"Utrecht",
    "wof:name":"Sba",
    "wof:placetype":"venue"
},
  "geometry": {"coordinates":[5.13201,52.001751],"type":"Point"}
}