{
  "type": "Feature",
  "properties": {
    "iso:country":"NL",
    "sg:address":"Oosterhof 1A",
    "sg:city":"Katwyk Zh",
    "sg:orig_category":"Parketvloeren",
    "sg:phone":"+31 71 401 6263",
    "sg:postcode":"2225 DW",
    "sg:province":"Zuid-Holland",
    "sg:website":"http://www.parketshop-katwijk.nl",
    "wof:name":"Parketshop Legservice Katwijk",
    "wof:placetype":"venue"
},
  "geometry": {"coordinates":[4.395763,52.20224],"type":"Point"}
}