{
  "type": "Feature",
  "properties": {
    "iso:country":"NL",
    "sg:address":"Boulevard 161",
    "sg:city":"Roosendaal",
    "sg:orig_category":"Verzekeringen - Verzekeringskantoren",
    "sg:phone":"+31 165 520 194",
    "sg:postcode":"4701 ET",
    "sg:province":"North Brabant",
    "wof:name":"Eekels",
    "wof:placetype":"venue"
},
  "geometry": {"coordinates":[4.465674,51.530979],"type":"Point"}
}