{
  "type": "Feature",
  "properties": {
    "addr:full":"P Cornelisz Hooftstr 47 Amsterdam North Holland 1071 BN",
    "addr:housenumber":"47",
    "addr:postcode":"1071 bn",
    "addr:street":"P Cornelisz Hooftstr",
    "iso:country":"NL",
    "sg:address":"P Cornelisz Hooftstr 47",
    "sg:city":"Amsterdam",
    "sg:orig_category":"Kappers",
    "sg:phone":"+31 20 662 8555",
    "sg:postcode":"1071 BN",
    "sg:province":"North Holland",
    "wof:name":"Joss Hair & Beauty",
    "wof:placetype":"venue"
},
  "geometry": {"coordinates":[4.8820028305,52.3604545593],"type":"Point"}
}