{
  "type": "Feature",
  "properties": {
    "iso:country":"NL",
    "sg:address":"Fluitekruid 15",
    "sg:city":"Schoonhoven",
    "sg:orig_category":"Gehandicapteninformatie",
    "sg:phone":"+31 182 320 376",
    "sg:postcode":"2871 NL",
    "sg:province":"Zuid-Holland",
    "wof:name":"Gemiva Svg Groep",
    "wof:placetype":"venue"
},
  "geometry": {"coordinates":[4.868415,51.947746],"type":"Point"}
}