{
  "type": "Feature",
  "properties": {
    "addr:full":"Heilooerdk 48S Alkmaar Noord-Holland 1814 LP",
    "addr:housenumber":"48s",
    "addr:postcode":"1814 lp",
    "addr:street":"Heilooerdk",
    "iso:country":"NL",
    "sg:address":"Heilooerdk 48S",
    "sg:city":"Alkmaar",
    "sg:orig_category":"Beeldende Kunstenaars",
    "sg:phone":"+31 72 512 5498",
    "sg:postcode":"1814 LP",
    "sg:province":"Noord-Holland",
    "sg:website":"http://www.proj.nl",
    "wof:name":"Werkmaatschappij, De",
    "wof:placetype":"venue"
},
  "geometry": {"coordinates":[4.738035,52.620811],"type":"Point"}
}