{
  "type": "Feature",
  "properties": {
    "addr:full":"Hoofdstr 109 Zuidwolde Dr Drenthe 7921 AG",
    "addr:housenumber":"109",
    "addr:postcode":"7921",
    "addr:street":"Zuidwolde Dr",
    "iso:country":"NL",
    "sg:address":"Hoofdstr 109",
    "sg:city":"Zuidwolde Dr",
    "sg:orig_category":"Bloemen En Planten",
    "sg:phone":"+31 528 370 632",
    "sg:postcode":"7921 AG",
    "sg:province":"Drenthe",
    "wof:name":"Alice",
    "wof:placetype":"venue"
},
  "geometry": {"coordinates":[6.42853,52.67675],"type":"Point"}
}