{
  "type": "Feature",
  "properties": {
    "addr:full":"Breedstraat 17 Hedel Gelderland 5321 VN",
    "addr:housenumber":"17",
    "addr:postcode":"5321 vn",
    "addr:street":"Breedstraat;Gelderland",
    "iso:country":"NL",
    "sg:address":"Breedstraat 17",
    "sg:city":"Hedel",
    "sg:orig_category":"Public Relationbureaus",
    "sg:phone":"+31 73 599 2832",
    "sg:postcode":"5321 VN",
    "sg:province":"Gelderland",
    "wof:name":"Alberts Communications",
    "wof:placetype":"venue"
},
  "geometry": {"coordinates":[5.264218,51.768635],"type":"Point"}
}