{
  "type": "Feature",
  "properties": {
    "addr:full":"Postbus 425 Capelle Ad Yssel 2900 AK",
    "addr:housenumber":"425",
    "addr:postcode":"2900 ak",
    "addr:street":"Postbus;Yssel",
    "iso:country":"NL",
    "sg:address":"Postbus 425",
    "sg:city":"Capelle Ad Yssel",
    "sg:orig_category":"Fotojournalisten Freelance",
    "sg:phone":"+31 6 54266702",
    "sg:postcode":"2900 AK",
    "wof:name":"Zeemeijer, Joop",
    "wof:placetype":"venue"
},
  "geometry": {"coordinates":[4.5897,51.932758],"type":"Point"}
}