{
  "type": "Feature",
  "properties": {
    "addr:full":"Putterweg 230 Ermelo Gelderland 3851 VG",
    "addr:housenumber":"230",
    "addr:postcode":"3851 vg",
    "addr:street":"Putterweg;Gelderland",
    "iso:country":"NL",
    "sg:address":"Putterweg 230",
    "sg:city":"Ermelo",
    "sg:orig_category":"Bedrijfs- And Managementsconsultants",
    "sg:phone":"+31 341 352 362",
    "sg:postcode":"3851 VG",
    "sg:province":"Gelderland",
    "wof:name":"Van Helsdingen Consultant",
    "wof:placetype":"venue"
},
  "geometry": {"coordinates":[5.627246,52.2906],"type":"Point"}
}