{
  "type": "Feature",
  "properties": {
    "addr:full":"Boslaan 1/K003 Vlieland Friesland 8899 BM",
    "addr:housenumber":"1 / k003",
    "addr:postcode":"8899 bm",
    "addr:street":"Boslaan;Vlieland",
    "iso:country":"NL",
    "sg:address":"Boslaan 1/K003",
    "sg:city":"Vlieland",
    "sg:orig_category":"Kinderopvang Behalve Thuis",
    "sg:phone":"+31 562 451 322",
    "sg:postcode":"8899 BM",
    "sg:province":"Friesland",
    "wof:name":"Kinderopvang Teddy Vlie",
    "wof:placetype":"venue"
},
  "geometry": {"coordinates":[5.063312,53.29615],"type":"Point"}
}