{
  "type": "Feature",
  "properties": {
    "addr:full":"P Potterstr 26 Kerkrade Limburg 6464 CB",
    "addr:housenumber":"26",
    "addr:postcode":"6464 cb",
    "addr:street":"P",
    "iso:country":"NL",
    "sg:address":"P Potterstr 26",
    "sg:city":"Kerkrade",
    "sg:classifiers":[
        {
            "category":"Personal",
            "subcategory":"Nail Salon",
            "type":"Services"
        }
    ],
    "sg:phone":"+31 45 545 2349",
    "sg:postcode":"6464 CB",
    "sg:province":"Limburg",
    "sg:tags":[
        "pedicure"
    ],
    "wof:name":"Lukassen-Kemmerling, I",
    "wof:placetype":"venue"
},
  "geometry": {"coordinates":[6.075343,50.879692],"type":"Point"}
}