{
  "type": "Feature",
  "properties": {
    "iso:country":"NL",
    "sg:address":"Bosserdk 39",
    "sg:city":"Hoogland",
    "sg:orig_category":"Administratie- En Boekhoudkantoren",
    "sg:phone":"+31 33 480 2475",
    "sg:postcode":"3828 CB",
    "sg:province":"Utrecht",
    "wof:name":"Heuvel, H M Van Den",
    "wof:placetype":"venue"
},
  "geometry": {"coordinates":[5.378046,52.185501],"type":"Point"}
}