{
  "type": "Feature",
  "properties": {
    "addr:full":"Multatulihof 18 Gendringen Gelderland 7081 AS",
    "addr:housenumber":"18",
    "addr:postcode":"7081 as",
    "addr:street":"Multatulihof;Gelderland",
    "iso:country":"NL",
    "sg:address":"Multatulihof 18",
    "sg:city":"Gendringen",
    "sg:orig_category":"Makelaars In Onroerend Goed",
    "sg:phone":"+31 315 632 736",
    "sg:postcode":"7081 AS",
    "sg:province":"Gelderland",
    "wof:name":"G. Heinen Og Assurantien",
    "wof:placetype":"venue"
},
  "geometry": {"coordinates":[6.379175,51.877083],"type":"Point"}
}