{
  "type": "Feature",
  "properties": {
    "addr:full":"Dam 73 Alblasserdam South Holland 2951 GA",
    "addr:housenumber":"73",
    "addr:postcode":"2951 ga",
    "addr:street":"Dam",
    "iso:country":"NL",
    "sg:address":"Dam 73",
    "sg:city":"Alblasserdam",
    "sg:classifiers":[
        {
            "category":"Fast Food",
            "type":"Food & Drink"
        }
    ],
    "sg:phone":"+31 78 691 3120",
    "sg:postcode":"2951 GA",
    "sg:province":"South Holland",
    "sg:tags":[
        "afhaal",
        "restaurant"
    ],
    "wof:name":"Shoarma Grill Room Jaffa",
    "wof:placetype":"venue"
},
  "geometry": {"coordinates":[4.660333,51.860977],"type":"Point"}
}