{
  "type": "Feature",
  "properties": {
    "addr:full":"D Oultremontweg 14 Elshout Noord-Brabant 5154 PD",
    "addr:housenumber":"14",
    "addr:postcode":"5154 pd",
    "addr:street":"Elshout",
    "iso:country":"NL",
    "sg:address":"D Oultremontweg 14",
    "sg:city":"Elshout",
    "sg:orig_category":"Fruit And Groenten Gh",
    "sg:phone":"+31 416 379 290",
    "sg:postcode":"5154 PD",
    "sg:province":"Noord-Brabant",
    "wof:name":"Em-Te A.G.F. Distributiecentrum",
    "wof:placetype":"venue"
},
  "geometry": {"coordinates":[5.162745,51.700245],"type":"Point"}
}