{
  "type": "Feature",
  "properties": {
    "addr:full":"De Kwinkelier 51 Bilthoven Utrecht 3722 AS",
    "addr:housenumber":"51",
    "addr:postcode":"3722 as",
    "addr:street":"De Kwinkelier",
    "iso:country":"NL",
    "sg:address":"De Kwinkelier 51",
    "sg:city":"Bilthoven",
    "sg:orig_category":"Broodjeszaken",
    "sg:phone":"+31 30 228 7771",
    "sg:postcode":"3722 AS",
    "sg:province":"Utrecht",
    "wof:name":"Portly",
    "wof:placetype":"venue"
},
  "geometry": {"coordinates":[5.21019,52.128693],"type":"Point"}
}