{
  "type": "Feature",
  "properties": {
    "addr:full":"Schiewg 15B Delft South Holland 2627 AN",
    "addr:housenumber":"15b",
    "addr:postcode":"2627 an",
    "addr:street":"Schiewg",
    "iso:country":"NL",
    "sg:address":"Schiewg 15B",
    "sg:city":"Delft",
    "sg:orig_category":"Fotoapparatuur En -Artikelen - Groothandel",
    "sg:phone":"+31 15 257 2817",
    "sg:postcode":"2627 AN",
    "sg:province":"South Holland",
    "wof:name":"Best Buy",
    "wof:placetype":"venue"
},
  "geometry": {"coordinates":[4.367686,51.994865],"type":"Point"}
}