{
  "type": "Feature",
  "properties": {
    "iso:country":"NL",
    "sg:address":"Nachtegaalstraat 21",
    "sg:city":"Eys",
    "sg:orig_category":"Kappers",
    "sg:phone":"+31 43 451 9095",
    "sg:postcode":"6287 AX",
    "sg:province":"Limburg",
    "wof:name":"Anita",
    "wof:placetype":"venue"
},
  "geometry": {"coordinates":[5.9400458336,50.8254890442],"type":"Point"}
}