{
  "type": "Feature",
  "properties": {
    "addr:full":"Duifpolder 11 Maasland South Holland 3155 CA",
    "addr:housenumber":"11",
    "addr:postcode":"3155 ca",
    "addr:street":"Duifpolder",
    "iso:country":"NL",
    "sg:address":"Duifpolder 11",
    "sg:city":"Maasland",
    "sg:orig_category":"Grondwerken",
    "sg:phone":"+31 10 591 9510",
    "sg:postcode":"3155 CA",
    "sg:province":"South Holland",
    "wof:name":"Nierop, H J Van",
    "wof:placetype":"venue"
},
  "geometry": {"coordinates":[4.313846,51.955635],"type":"Point"}
}