{
  "type": "Feature",
  "properties": {
    "addr:full":"Venkeldonk 53 Spijkenisse South Holland 3206 EK",
    "addr:housenumber":"53",
    "addr:postcode":"3206 ek",
    "addr:street":"Venkeldonk",
    "iso:country":"NL",
    "sg:address":"Venkeldonk 53",
    "sg:city":"Spijkenisse",
    "sg:orig_category":"Verhuur Bouwmachines",
    "sg:phone":"+31 181 639 555",
    "sg:postcode":"3206 EK",
    "sg:province":"South Holland",
    "wof:name":"Pss",
    "wof:placetype":"venue"
},
  "geometry": {"coordinates":[4.326134,51.830204],"type":"Point"}
}