{
  "type": "Feature",
  "properties": {
    "addr:full":"Adelastr 6 Weert Limburg 6004 HZ",
    "addr:housenumber":"6",
    "addr:postcode":"6004 hz",
    "addr:street":"Adelastr",
    "iso:country":"NL",
    "sg:address":"Adelastr 6",
    "sg:city":"Weert",
    "sg:orig_category":"Logopedisten",
    "sg:phone":"+31 495 541 123",
    "sg:postcode":"6004 HZ",
    "sg:province":"Limburg",
    "wof:name":"Bruekers-Caris, A",
    "wof:placetype":"venue"
},
  "geometry": {"coordinates":[5.719102,51.259258],"type":"Point"}
}