{
  "type": "Feature",
  "properties": {
    "addr:full":"Harmenjanswg 129 Haarlem North Holland 2031 WN",
    "addr:housenumber":"129",
    "addr:postcode":"2031 wn",
    "iso:country":"NL",
    "sg:address":"Harmenjanswg 129",
    "sg:city":"Haarlem",
    "sg:orig_category":"Zoetwaren - Fabrieken En Groothandel",
    "sg:phone":"+31 23 530 9309",
    "sg:postcode":"2031 WN",
    "sg:province":"North Holland",
    "sg:website":"http://www.dutchcocoa.nl",
    "wof:name":"Dutch Cocoa Bv",
    "wof:placetype":"venue"
},
  "geometry": {"coordinates":[4.64727,52.384838],"type":"Point"}
}