{
  "type": "Feature",
  "properties": {
    "addr:full":"F Vd Paltshof 33 Rhenen Utrecht 3911 LA",
    "addr:housenumber":"33",
    "addr:postcode":"3911 la",
    "iso:country":"NL",
    "sg:address":"F Vd Paltshof 33",
    "sg:city":"Rhenen",
    "sg:orig_category":"Woninginrichting",
    "sg:phone":"+31 317 612 564",
    "sg:postcode":"3911 LA",
    "sg:province":"Utrecht",
    "wof:name":"Quint",
    "wof:placetype":"venue"
},
  "geometry": {"coordinates":[5.5655641556,51.9580230713],"type":"Point"}
}