{
  "type": "Feature",
  "properties": {
    "iso:country":"NL",
    "sg:address":"Oostzeedijk Beneden 35",
    "sg:city":"Rotterdam",
    "sg:orig_category":"Binnenhuisarchitecten",
    "sg:phone":"+31 10 414 8159",
    "sg:postcode":"3062 VK",
    "sg:province":"Zuid-Holland",
    "wof:name":"Guus Van Riet Interieur-Ontwerp",
    "wof:placetype":"venue"
},
  "geometry": {"coordinates":[4.512002,51.920551],"type":"Point"}
}