{
  "type": "Feature",
  "properties": {
    "addr:full":"Fokkerstraat 489 Schiedam Zuid-Holland 3125 BD",
    "addr:housenumber":"489",
    "addr:postcode":"3125 bd",
    "addr:street":"Fokkerstraat",
    "iso:country":"NL",
    "sg:address":"Fokkerstraat 489",
    "sg:city":"Schiedam",
    "sg:orig_category":"Metaalbekleding And -Behandeling",
    "sg:phone":"+31 10 437 3622",
    "sg:postcode":"3125 BD",
    "sg:province":"Zuid-Holland",
    "wof:name":"Boers & Co Fijnmechanische Industrie Bv",
    "wof:placetype":"venue"
},
  "geometry": {"coordinates":[4.397325,51.933872],"type":"Point"}
}