{
  "type": "Feature",
  "properties": {
    "iso:country":"NL",
    "sg:address":"Mooierstr 8",
    "sg:city":"Amersfoort",
    "sg:orig_category":"Kinderkleding",
    "sg:phone":"+31 33 475 9111",
    "sg:postcode":"3811 EB",
    "sg:province":"Utrecht",
    "wof:name":"Zjerkala",
    "wof:placetype":"venue"
},
  "geometry": {"coordinates":[5.389195,52.154613],"type":"Point"}
}