{
  "type": "Feature",
  "properties": {
    "addr:full":"Kloetingsewg 47 Goes Zeeland 4462 AW",
    "addr:housenumber":"47",
    "addr:postcode":"4462 aw",
    "addr:street":"Kloetingsewg",
    "iso:country":"NL",
    "sg:address":"Kloetingsewg 47",
    "sg:city":"Goes",
    "sg:orig_category":"Woningbouw- Verenigingen En -Stichtingen",
    "sg:phone":"+31 113 215 256",
    "sg:postcode":"4462 AW",
    "sg:province":"Zeeland",
    "wof:name":"Wooncentr Joanna",
    "wof:placetype":"venue"
},
  "geometry": {"coordinates":[3.9033429623,51.4955749512],"type":"Point"}
}