{
  "type": "Feature",
  "properties": {
    "addr:full":"Achtergr 132 Weesp Noord-Holland 1381 BS",
    "addr:housenumber":"132",
    "addr:postcode":"1381 bs",
    "iso:country":"NL",
    "sg:address":"Achtergr 132",
    "sg:city":"Weesp",
    "sg:orig_category":"Verzekeringen - Verzekeringskantoren",
    "sg:phone":"+31 294 419 947",
    "sg:postcode":"1381 BS",
    "sg:province":"Noord-Holland",
    "wof:name":"Cvo",
    "wof:placetype":"venue"
},
  "geometry": {"coordinates":[5.04296,52.304825],"type":"Point"}
}