{
  "type": "Feature",
  "properties": {
    "addr:full":"Strawinskyln 15 Delft Zuid-Holland 2625 NC",
    "addr:housenumber":"15",
    "addr:postcode":"2625 nc",
    "addr:street":"Strawinskyln",
    "iso:country":"NL",
    "sg:address":"Strawinskyln 15",
    "sg:city":"Delft",
    "sg:orig_category":"Lasbedrijven",
    "sg:phone":"+31 15 261 9779",
    "sg:postcode":"2625 NC",
    "sg:province":"Zuid-Holland",
    "wof:name":"Mulhuyzen, L M",
    "wof:placetype":"venue"
},
  "geometry": {"coordinates":[4.33544,51.993931],"type":"Point"}
}