{
  "type": "Feature",
  "properties": {
    "addr:full":"Suderseewei 6 Makkum Fr Friesland 8754 GK",
    "addr:housenumber":"6",
    "addr:postcode":"8754 gk",
    "addr:street":"Suderseewei",
    "iso:country":"NL",
    "sg:address":"Suderseewei 6",
    "sg:city":"Makkum Fr",
    "sg:orig_category":"Recreatie- And Lunaparken",
    "sg:phone":"+31 515 231 091",
    "sg:postcode":"8754 GK",
    "sg:province":"Friesland",
    "wof:name":"Marina Makkum",
    "wof:placetype":"venue"
},
  "geometry": {"coordinates":[5.384757,53.054043],"type":"Point"}
}