{
  "type": "Feature",
  "properties": {
    "addr:full":"Langstr 39 Schimmert Limburg 6333 CC",
    "addr:housenumber":"39",
    "addr:postcode":"6333 cc",
    "addr:street":"Langstr",
    "iso:country":"NL",
    "sg:address":"Langstr 39",
    "sg:city":"Schimmert",
    "sg:classifiers":[
        {
            "category":"Sports & Exercise",
            "subcategory":"Stables",
            "type":"Entertainment"
        }
    ],
    "sg:phone":"+31 45 404 1986",
    "sg:postcode":"6333 CC",
    "sg:province":"Limburg",
    "sg:tags":[
        "maneges"
    ],
    "wof:name":"Hemij",
    "wof:placetype":"venue"
},
  "geometry": {"coordinates":[5.819707,50.907898],"type":"Point"}
}