{
  "type": "Feature",
  "properties": {
    "iso:country":"NL",
    "sg:address":"Middenweg 131",
    "sg:city":"Den Helder",
    "sg:orig_category":"Verlichting And Huishoudartikelen",
    "sg:phone":"+31 223 623 888",
    "sg:postcode":"1782 BD",
    "sg:province":"Noord-Holland",
    "wof:name":"Startapijt En Decorum",
    "wof:placetype":"venue"
},
  "geometry": {"coordinates":[4.756146,52.956242],"type":"Point"}
}