{
  "type": "Feature",
  "properties": {
    "iso:country":"NL",
    "sg:address":"Gr Sabinastr 52",
    "sg:city":"Zuid Beyerland",
    "sg:orig_category":"Postkantoren",
    "sg:phone":"+31 186 661 220",
    "sg:postcode":"3284 AP",
    "sg:province":"Zuid-Holland",
    "sg:website":"http://www.postkantoor.nl",
    "wof:name":"Postkantoor",
    "wof:placetype":"venue"
},
  "geometry": {"coordinates":[4.36709,51.74995],"type":"Point"}
}