{
  "type": "Feature",
  "properties": {
    "addr:full":"Z Schalkwykerwg 43A Haarlem Noord-Holland 2034 JH",
    "addr:housenumber":"43a",
    "addr:postcode":"2034 jh",
    "iso:country":"NL",
    "sg:address":"Z Schalkwykerwg 43A",
    "sg:city":"Haarlem",
    "sg:orig_category":"Exploitatie- Maatschappijen",
    "sg:phone":"+31 23 533 8649",
    "sg:postcode":"2034 JH",
    "sg:province":"Noord-Holland",
    "wof:name":"Amsterdam Bv",
    "wof:placetype":"venue"
},
  "geometry": {"coordinates":[4.64199,52.346939],"type":"Point"}
}