{
  "type": "Feature",
  "properties": {
    "addr:full":"Van Geenstraat 86 Putten Gelderland 3882 BJ",
    "addr:housenumber":"86",
    "addr:postcode":"3882 bj",
    "addr:street":"Van Geenstraat;Gelderland",
    "iso:country":"NL",
    "sg:address":"Van Geenstraat 86",
    "sg:city":"Putten",
    "sg:classifiers":[
        {
            "category":"Retail",
            "subcategory":"Storage",
            "type":"Services"
        }
    ],
    "sg:phone":"+31 341 351 756",
    "sg:postcode":"3882 BJ",
    "sg:province":"Gelderland",
    "sg:tags":[
        "opslag",
        "bewaring"
    ],
    "wof:name":"Firma Knoppert",
    "wof:placetype":"venue"
},
  "geometry": {"coordinates":[5.5944662094,52.2529754639],"type":"Point"}
}