{
  "type": "Feature",
  "properties": {
    "addr:full":"Industriestraat 3 Haaksbergen Overijssel 7482 EW",
    "addr:housenumber":"3",
    "addr:postcode":"7482 ew",
    "addr:street":"Industriestraat",
    "iso:country":"NL",
    "sg:address":"Industriestraat 3",
    "sg:city":"Haaksbergen",
    "sg:orig_category":"Huizensloop And Bouwrijp Maken",
    "sg:phone":"+31 53 573 5800",
    "sg:postcode":"7482 EW",
    "sg:province":"Overijssel",
    "wof:name":"Langezaal Grondverzet Bv",
    "wof:placetype":"venue"
},
  "geometry": {"coordinates":[6.724519,52.154587],"type":"Point"}
}