{
  "type": "Feature",
  "properties": {
    "addr:full":"Watergoorwg 68 Nykerk Gld Gelderland 3861 MA",
    "addr:housenumber":"68",
    "addr:postcode":"3861 ma",
    "addr:street":"Watergoorwg;Gld Gelderland",
    "iso:country":"NL",
    "sg:address":"Watergoorwg 68",
    "sg:city":"Nykerk Gld",
    "sg:orig_category":"Meubelstoffering",
    "sg:phone":"+31 33 245 9185",
    "sg:postcode":"3861 MA",
    "sg:province":"Gelderland",
    "wof:name":"Goudsmid, L",
    "wof:placetype":"venue"
},
  "geometry": {"coordinates":[5.472053,52.228683],"type":"Point"}
}