{
  "type": "Feature",
  "properties": {
    "addr:full":"Montgomerystr 40 Doetinchem Gelderland 7002 DT",
    "addr:housenumber":"40",
    "addr:postcode":"7002 dt",
    "addr:street":"Montgomerystr;Gelderland",
    "iso:country":"NL",
    "sg:address":"Montgomerystr 40",
    "sg:city":"Doetinchem",
    "sg:orig_category":"Pianostemmen En -Reparatie",
    "sg:phone":"+31 314 323 110",
    "sg:postcode":"7002 DT",
    "sg:province":"Gelderland",
    "wof:name":"Holleman, Joep",
    "wof:placetype":"venue"
},
  "geometry": {"coordinates":[6.313489,51.97509],"type":"Point"}
}