{
  "type": "Feature",
  "properties": {
    "addr:full":"Den Uylsingel 183 Rotterdam South Holland 3066 TC",
    "addr:housenumber":"183",
    "addr:postcode":"3066 tc",
    "addr:street":"Den Uylsingel",
    "iso:country":"NL",
    "sg:address":"Den Uylsingel 183",
    "sg:city":"Rotterdam",
    "sg:orig_category":"Public Relationbureaus",
    "sg:phone":"+31 10 261 9007",
    "sg:postcode":"3066 TC",
    "sg:province":"South Holland",
    "wof:name":"Henk Brejaart",
    "wof:placetype":"venue"
},
  "geometry": {"coordinates":[4.558098,51.935284],"type":"Point"}
}