{
  "type": "Feature",
  "properties": {
    "addr:full":"Geulenstraat 1 Purmerend Noord-Holland 1441 RX",
    "addr:housenumber":"1",
    "addr:postcode":"1441 rx",
    "addr:street":"Geulenstraat",
    "iso:country":"NL",
    "sg:address":"Geulenstraat 1",
    "sg:city":"Purmerend",
    "sg:orig_category":"Bioscopen",
    "sg:phone":"+31 299 436 188",
    "sg:postcode":"1441 RX",
    "sg:province":"Noord-Holland",
    "wof:name":"Metro 1-2-3 Bioscopen",
    "wof:placetype":"venue"
},
  "geometry": {"coordinates":[4.956472,52.503548],"type":"Point"}
}