{
  "type": "Feature",
  "properties": {
    "addr:full":"Marga Klompelaan 6 Arnhem Gelderland 6836 BH",
    "addr:housenumber":"6",
    "addr:postcode":"6836 bh",
    "addr:street":"Marga Klompelaan",
    "iso:country":"NL",
    "sg:address":"Marga Klompelaan 6",
    "sg:city":"Arnhem",
    "sg:orig_category":"Paramedische Behandelingen",
    "sg:phone":"+31 26 323 2323",
    "sg:postcode":"6836 BH",
    "sg:province":"Gelderland",
    "wof:name":"Hodes Thuiszorg Center",
    "wof:placetype":"venue"
},
  "geometry": {"coordinates":[5.884667,51.949417],"type":"Point"}
}