{
  "type": "Feature",
  "properties": {
    "iso:country":"NL",
    "sg:address":"Uiterdk 75A",
    "sg:city":"Appingedam",
    "sg:orig_category":"Grafisch Ontwerpers",
    "sg:phone":"+31 596 627 140",
    "sg:postcode":"9901 JG",
    "sg:province":"Groningen",
    "wof:name":"Boer, B De",
    "wof:placetype":"venue"
},
  "geometry": {"coordinates":[6.865191,53.321804],"type":"Point"}
}