{
  "type": "Feature",
  "properties": {
    "addr:full":"Schiekd 133 Unit 12 Rotterdam Zuid-Holland 3033 BL",
    "addr:housenumber":"133 unit 12",
    "addr:postcode":"3033 bl",
    "iso:country":"NL",
    "sg:address":"Schiekd 133 Unit 12",
    "sg:city":"Rotterdam",
    "sg:orig_category":"Projectontwikkeling",
    "sg:phone":"+31 10 467 8133",
    "sg:postcode":"3033 BL",
    "sg:province":"Zuid-Holland",
    "wof:name":"K & G",
    "wof:placetype":"venue"
},
  "geometry": {"coordinates":[4.46912,51.927521],"type":"Point"}
}