{
  "type": "Feature",
  "properties": {
    "addr:full":"Wijkplaats 54 Naarden Noord-Holland 1411 LT",
    "addr:housenumber":"54",
    "addr:postcode":"1411 lt",
    "addr:street":"Wijkplaats",
    "iso:country":"NL",
    "sg:address":"Wijkplaats 54",
    "sg:city":"Naarden",
    "sg:orig_category":"Adviesbureaus Bedrijfsorganisatie",
    "sg:phone":"+31 35 694 1702",
    "sg:postcode":"1411 LT",
    "sg:province":"Noord-Holland",
    "wof:name":"Euterpe Serv Bv",
    "wof:placetype":"venue"
},
  "geometry": {"coordinates":[5.150313,52.30896],"type":"Point"}
}