{
  "type": "Feature",
  "properties": {
    "addr:full":"Vredeln 8 Almere NL. 1318 AS",
    "addr:housenumber":"8",
    "addr:postcode":"1318 as",
    "addr:street":"Vredeln;Nl.",
    "iso:country":"NL",
    "sg:address":"Vredeln 8",
    "sg:city":"Almere",
    "sg:orig_category":"Verzekeringen - Verzekeringskantoren",
    "sg:phone":"+31 36 537 5968",
    "sg:postcode":"1318 AS",
    "sg:province":"NL.",
    "sg:website":"http://www.assurantieconcept.nl",
    "wof:name":"Assurantie Concept Almere Bv",
    "wof:placetype":"venue"
},
  "geometry": {"coordinates":[5.22223,52.376598],"type":"Point"}
}