{
  "type": "Feature",
  "properties": {
    "addr:full":"Haagweg 159 Breda North Brabant 4812 XC",
    "addr:housenumber":"159",
    "addr:postcode":"4812 xc",
    "addr:street":"Haagweg",
    "iso:country":"NL",
    "sg:address":"Haagweg 159",
    "sg:city":"Breda",
    "sg:orig_category":"Visspeciaalzaken",
    "sg:phone":"+31 76 521 0145",
    "sg:postcode":"4812 XC",
    "sg:province":"North Brabant",
    "wof:name":"Vishandel Van Nunen",
    "wof:placetype":"venue"
},
  "geometry": {"coordinates":[4.756442,51.581425],"type":"Point"}
}