{
  "type": "Feature",
  "properties": {
    "iso:country":"NL",
    "sg:address":"Bingleystr 61",
    "sg:city":"Rotterdam",
    "sg:classifiers":[
        {
            "category":"Personal",
            "subcategory":"Nail Salon",
            "type":"Services"
        }
    ],
    "sg:phone":"+31 10 477 7945",
    "sg:postcode":"3025 RD",
    "sg:province":"Zuid-Holland",
    "sg:tags":[
        "pedicure"
    ],
    "wof:name":"Willems-Martin, L A",
    "wof:placetype":"venue"
},
  "geometry": {"coordinates":[4.444679,51.907776],"type":"Point"}
}