{
  "type": "Feature",
  "properties": {
    "addr:full":"Vd D V Maasdamln 12 Woudenberg Utrecht 3931 HR",
    "addr:housenumber":"12",
    "addr:postcode":"3931 hr",
    "addr:street":"Maasdamln",
    "iso:country":"NL",
    "sg:address":"Vd D V Maasdamln 12",
    "sg:city":"Woudenberg",
    "sg:orig_category":"Schilders",
    "sg:phone":"+31 33 286 4276",
    "sg:postcode":"3931 HR",
    "sg:province":"Utrecht",
    "wof:name":"Labrie",
    "wof:placetype":"venue"
},
  "geometry": {"coordinates":[5.415759,52.08215],"type":"Point"}
}