{
  "type": "Feature",
  "properties": {
    "addr:full":"Zestienhovensekd 166 Rotterdam South Holland 3043 KV",
    "addr:housenumber":"166",
    "addr:postcode":"3043 kv",
    "iso:country":"NL",
    "sg:address":"Zestienhovensekd 166",
    "sg:city":"Rotterdam",
    "sg:orig_category":"Houtgroothandel",
    "sg:phone":"+31 10 462 0311",
    "sg:postcode":"3043 KV",
    "sg:province":"South Holland",
    "wof:name":"Leeuwen Bv, A S Van",
    "wof:placetype":"venue"
},
  "geometry": {"coordinates":[4.43046,51.941696],"type":"Point"}
}