{
  "type": "Feature",
  "properties": {
    "addr:full":"Muiderslotweg 2 Haarlem North Holland 2026 AP",
    "addr:housenumber":"2",
    "addr:postcode":"2026 ap",
    "addr:street":"Muiderslotweg",
    "iso:country":"NL",
    "sg:address":"Muiderslotweg 2",
    "sg:city":"Haarlem",
    "sg:orig_category":"Kappers",
    "sg:phone":"+31 23 537 4796",
    "sg:postcode":"2026 AP",
    "sg:province":"North Holland",
    "wof:name":"Salon Hans",
    "wof:placetype":"venue"
},
  "geometry": {"coordinates":[4.648435,52.419243],"type":"Point"}
}