{
  "type": "Feature",
  "properties": {
    "addr:full":"Tureluurweg 21 Diemen North Holland 1111 WL",
    "addr:housenumber":"21",
    "addr:postcode":"1111 wl",
    "addr:street":"Tureluurweg",
    "iso:country":"NL",
    "sg:address":"Tureluurweg 21",
    "sg:city":"Diemen",
    "sg:orig_category":"Metaalwerken",
    "sg:phone":"+31 20 695 1986",
    "sg:postcode":"1111 WL",
    "sg:province":"North Holland",
    "wof:name":"Van Ree'S Zonweringen En Rolluiken",
    "wof:placetype":"venue"
},
  "geometry": {"coordinates":[4.974233,52.349483],"type":"Point"}
}