{
  "type": "Feature",
  "properties": {
    "addr:full":"Nw Tyningen 115 Zaltbommel Gelderland 5301 DA",
    "addr:housenumber":"115",
    "addr:postcode":"5301 da",
    "addr:street":"Gelderland",
    "iso:country":"NL",
    "sg:address":"Nw Tyningen 115",
    "sg:city":"Zaltbommel",
    "sg:classifiers":[
        {
            "category":"Food & Beverages",
            "subcategory":"Fruits & Vegetables",
            "type":"Retail Goods"
        }
    ],
    "sg:phone":"+31 418 561 323",
    "sg:postcode":"5301 DA",
    "sg:province":"Gelderland",
    "sg:tags":[
        "en",
        "groenten"
    ],
    "wof:name":"Tuijl, Fa A Van",
    "wof:placetype":"venue"
},
  "geometry": {"coordinates":[5.228224,51.800987],"type":"Point"}
}