{
  "type": "Feature",
  "properties": {
    "addr:full":"Repelaerstr 18 S Gravenhage South Holland 2515 LZ",
    "addr:housenumber":"18",
    "addr:postcode":"2515 lz",
    "addr:street":"Repelaerstr;S Gravenhage",
    "iso:country":"NL",
    "sg:address":"Repelaerstr 18",
    "sg:city":"S Gravenhage",
    "sg:orig_category":"Modeontwerpen",
    "sg:phone":"+31 70 380 6164",
    "sg:postcode":"2515 LZ",
    "sg:province":"South Holland",
    "wof:name":"Vis \u00c0 Vis",
    "wof:placetype":"venue"
},
  "geometry": {"coordinates":[4.31741,52.083988],"type":"Point"}
}