{
  "type": "Feature",
  "properties": {
    "addr:full":"Wegalaan 35 Hoofddorp Noord-Holland 2132 JD",
    "addr:housenumber":"35",
    "addr:postcode":"2132 jd",
    "addr:street":"Wegalaan",
    "iso:country":"NL",
    "sg:address":"Wegalaan 35",
    "sg:city":"Hoofddorp",
    "sg:orig_category":"Luchtvaart",
    "sg:phone":"+31 20 470 1470",
    "sg:postcode":"2132 JD",
    "sg:province":"Noord-Holland",
    "wof:name":"Sabena",
    "wof:placetype":"venue"
},
  "geometry": {"coordinates":[4.707872,52.293987],"type":"Point"}
}