{
  "type": "Feature",
  "properties": {
    "addr:full":"O L Vrouwenstr 196 Zegge North Brabant 4735 RB",
    "addr:housenumber":"196",
    "addr:postcode":"4735 rb",
    "addr:street":"O;Zegge",
    "iso:country":"NL",
    "sg:address":"O L Vrouwenstr 196",
    "sg:city":"Zegge",
    "sg:orig_category":"Logopedisten",
    "sg:phone":"+31 165 560 782",
    "sg:postcode":"4735 RB",
    "sg:province":"North Brabant",
    "wof:name":"Elshout-De Rooy, W D G M",
    "wof:placetype":"venue"
},
  "geometry": {"coordinates":[4.516585,51.556709],"type":"Point"}
}