{
  "type": "Feature",
  "properties": {
    "addr:full":"R Visscherpln 15 Heemstede Noord-Holland 2106 AG",
    "addr:housenumber":"15",
    "addr:postcode":"2106",
    "iso:country":"NL",
    "sg:address":"R Visscherpln 15",
    "sg:city":"Heemstede",
    "sg:orig_category":"Adviesbureaus Bedrijfsorganisatie",
    "sg:phone":"+31 23 544 1599",
    "sg:postcode":"2106 AG",
    "sg:province":"Noord-Holland",
    "wof:name":"Geskes Bv",
    "wof:placetype":"venue"
},
  "geometry": {"coordinates":[4.60552,52.359371],"type":"Point"}
}