{
  "type": "Feature",
  "properties": {
    "addr:full":"Kerklaan 30 Haren Gn Groningen 9751 NN",
    "addr:housenumber":"30",
    "addr:postcode":"9751 nn",
    "addr:street":"Kerklaan",
    "iso:country":"NL",
    "sg:address":"Kerklaan 30",
    "sg:city":"Haren Gn",
    "sg:orig_category":"Overheidsdiensten",
    "sg:phone":"+31 50 533 0222",
    "sg:postcode":"9751 NN",
    "sg:province":"Groningen",
    "wof:name":"Belastingdienst Grote Ondernemingen Groningen",
    "wof:placetype":"venue"
},
  "geometry": {"coordinates":[6.6046500206,53.1786346436],"type":"Point"}
}