{
  "type": "Feature",
  "properties": {
    "iso:country":"NL",
    "sg:address":"Peperstr 14",
    "sg:city":"Godlinze",
    "sg:orig_category":"Bloemen En Planten",
    "sg:phone":"+31 596 581 422",
    "sg:postcode":"9908 PE",
    "sg:province":"Groningen",
    "wof:name":"Allersmaheerd, Van De",
    "wof:placetype":"venue"
},
  "geometry": {"coordinates":[6.81613,53.372623],"type":"Point"}
}