{
  "type": "Feature",
  "properties": {
    "addr:full":"Lorentzstr 4A Harderwyk Gelderland 3846 AW",
    "addr:housenumber":"4a",
    "addr:postcode":"3846 aw",
    "addr:street":"Lorentzstr;Gelderland",
    "iso:country":"NL",
    "sg:address":"Lorentzstr 4A",
    "sg:city":"Harderwyk",
    "sg:orig_category":"Automaterialen En Gereedschappen",
    "sg:phone":"+31 341 436 400",
    "sg:postcode":"3846 AW",
    "sg:province":"Gelderland",
    "wof:name":"Lasaulec Harderwijk",
    "wof:placetype":"venue"
},
  "geometry": {"coordinates":[5.633345,52.356239],"type":"Point"}
}