{
  "type": "Feature",
  "properties": {
    "addr:full":"Prinses Julianaplein 12 Amersfoort Utrecht 3817 CS",
    "addr:housenumber":"12",
    "addr:postcode":"3817 cs",
    "addr:street":"Prinses Julianaplein",
    "iso:country":"NL",
    "sg:address":"Prinses Julianaplein 12",
    "sg:city":"Amersfoort",
    "sg:orig_category":"Boekhouders",
    "sg:phone":"+31 33 463 7073",
    "sg:postcode":"3817 CS",
    "sg:province":"Utrecht",
    "wof:name":"Administratiekantoor De Vos Bv",
    "wof:placetype":"venue"
},
  "geometry": {"coordinates":[5.384932,52.150276],"type":"Point"}
}