{
  "type": "Feature",
  "properties": {
    "addr:full":"Eerbeekseweg 45 Loenen Gld Gelderland 7371 CC",
    "addr:housenumber":"45",
    "addr:postcode":"7371 cc",
    "addr:street":"Eerbeekseweg;Gld Gelderland",
    "iso:country":"NL",
    "sg:address":"Eerbeekseweg 45",
    "sg:city":"Loenen Gld",
    "sg:orig_category":"Metaalwerken",
    "sg:phone":"+31 55 505 1229",
    "sg:postcode":"7371 CC",
    "sg:province":"Gelderland",
    "wof:name":"H. Van Oorspronk Bv",
    "wof:placetype":"venue"
},
  "geometry": {"coordinates":[6.0221190453,52.1130714417],"type":"Point"}
}