{
  "type": "Feature",
  "properties": {
    "iso:country":"NL",
    "sg:address":"Eerbeekseweg 45",
    "sg:city":"Loenen Gld",
    "sg:orig_category":"Metaalwerken",
    "sg:phone":"+31 55 505 1229",
    "sg:postcode":"7371 CC",
    "sg:province":"Gelderland",
    "wof:name":"H. Van Oorspronk Bv",
    "wof:placetype":"venue"
},
  "geometry": {"coordinates":[6.0221190453,52.1130714417],"type":"Point"}
}