{
  "type": "Feature",
  "properties": {
    "addr:full":"Egstr 120 Heerlen Limburg 6418 JB",
    "addr:housenumber":"120",
    "addr:postcode":"6418 jb",
    "iso:country":"NL",
    "sg:address":"Egstr 120",
    "sg:city":"Heerlen",
    "sg:orig_category":"Webdesign Bureaus",
    "sg:phone":"+31 45 541 9885",
    "sg:postcode":"6418 JB",
    "sg:province":"Limburg",
    "sg:website":"http://www.phoenixwebdesign.nl",
    "wof:name":"Phoenix",
    "wof:placetype":"venue"
},
  "geometry": {"coordinates":[6.0143728256,50.8714065552],"type":"Point"}
}