{
  "type": "Feature",
  "properties": {
    "iso:country":"NL",
    "sg:address":"Dorpsstraat 46",
    "sg:city":"Halsteren",
    "sg:classifiers":[
        {
            "category":"Food & Beverages",
            "subcategory":"Fruits & Vegetables",
            "type":"Retail Goods"
        }
    ],
    "sg:phone":"+31 164 682 672",
    "sg:postcode":"4661 HP",
    "sg:province":"Noord-Brabant",
    "sg:tags":[
        "groenten"
    ],
    "wof:name":"Fa. Suykerbuyk - Matthijssen",
    "wof:placetype":"venue"
},
  "geometry": {"coordinates":[4.267881,51.527824],"type":"Point"}
}