{
  "type": "Feature",
  "properties": {
    "addr:full":"J C J V Speykstr 14 Hardenberg Overijssel 7772 ZC",
    "addr:housenumber":"14",
    "addr:postcode":"7772 zc",
    "addr:street":"J C J V Speykstr",
    "iso:country":"NL",
    "sg:address":"J C J V Speykstr 14",
    "sg:city":"Hardenberg",
    "sg:orig_category":"Bejaarden - Verzorgingstehuizen",
    "sg:phone":"+31 523 264 822",
    "sg:postcode":"7772 ZC",
    "sg:province":"Overijssel",
    "wof:name":"Oostloorn",
    "wof:placetype":"venue"
},
  "geometry": {"coordinates":[6.622884,52.57534],"type":"Point"}
}