{
  "type": "Feature",
  "properties": {
    "iso:country":"NL",
    "sg:address":"Wadden 34",
    "sg:city":"Huizen",
    "sg:orig_category":"Artsen - Huisartsen",
    "sg:phone":"+31 35 525 0777",
    "sg:postcode":"1274 GK",
    "sg:province":"Noord-Holland",
    "wof:name":"Gezondheidscentr Bovenmaat",
    "wof:placetype":"venue"
},
  "geometry": {"coordinates":[5.268189,52.301334],"type":"Point"}
}