{
  "type": "Feature",
  "properties": {
    "addr:full":"Buizerd 82 Blaricum Noord-Holland 1261 SV",
    "addr:housenumber":"82",
    "addr:postcode":"1261 sv",
    "addr:street":"Buizerd",
    "iso:country":"NL",
    "sg:address":"Buizerd 82",
    "sg:city":"Blaricum",
    "sg:orig_category":"Koeriersdiensten",
    "sg:phone":"+31 35 526 3472",
    "sg:postcode":"1261 SV",
    "sg:province":"Noord-Holland",
    "wof:name":"All Services Tyfoon Koerier",
    "wof:placetype":"venue"
},
  "geometry": {"coordinates":[5.2748231888,52.2870826721],"type":"Point"}
}