{
  "type": "Feature",
  "properties": {
    "addr:full":"Lange Dreef 14 Rijswijk Zh Zuid-Holland 2285 JN",
    "addr:housenumber":"14",
    "addr:postcode":"zh;2285 jn",
    "addr:street":"Lange Dreef",
    "iso:country":"NL",
    "sg:address":"Lange Dreef 14",
    "sg:city":"Rijswijk Zh",
    "sg:orig_category":"Boekenuitgeverijen",
    "sg:phone":"+31 70 336 1550",
    "sg:postcode":"2285 JN",
    "sg:province":"Zuid-Holland",
    "wof:name":"Graf. Ontwerpbureau- Uitgeverij-W. Groen",
    "wof:placetype":"venue"
},
  "geometry": {"coordinates":[4.298396,52.034138],"type":"Point"}
}