{
  "type": "Feature",
  "properties": {
    "addr:full":"Molenstraat 41 'S Gravenhage South Holland 2513 BJ",
    "addr:housenumber":"41",
    "addr:postcode":"2513 bj",
    "addr:street":"Molenstraat;' S Gravenhage",
    "iso:country":"NL",
    "sg:address":"Molenstraat 41",
    "sg:city":"'S Gravenhage",
    "sg:orig_category":"Diverse Grafische Activiteiten",
    "sg:phone":"+31 70 360 8930",
    "sg:postcode":"2513 BJ",
    "sg:province":"South Holland",
    "wof:name":"Wartna Lettering Bv",
    "wof:placetype":"venue"
},
  "geometry": {"coordinates":[4.306005,52.079838],"type":"Point"}
}