{
  "type": "Feature",
  "properties": {
    "addr:full":"Verl Talmaln 43 Soest Utrecht 3762 AB",
    "addr:housenumber":"43",
    "addr:postcode":"3762 ab",
    "addr:street":"Soest",
    "iso:country":"NL",
    "sg:address":"Verl Talmaln 43",
    "sg:city":"Soest",
    "sg:orig_category":"Meubelen - Fabrieken En Groothandel",
    "sg:phone":"+31 35 601 0091",
    "sg:postcode":"3762 AB",
    "sg:province":"Utrecht",
    "wof:name":"Stein",
    "wof:placetype":"venue"
},
  "geometry": {"coordinates":[5.300385,52.184044],"type":"Point"}
}