{
  "type": "Feature",
  "properties": {
    "iso:country":"NL",
    "sg:address":"R Schumanstr 31",
    "sg:city":"Groningen",
    "sg:orig_category":"Adviesbureaus",
    "sg:phone":"+31 50 526 4834",
    "sg:postcode":"9728 SM",
    "sg:province":"Groningen",
    "wof:name":"Davids, Bur",
    "wof:placetype":"venue"
},
  "geometry": {"coordinates":[6.559091,53.187389],"type":"Point"}
}