{
  "type": "Feature",
  "properties": {
    "addr:full":"Kerkpln 5 Heemskerk Noord-Holland 1961 EA",
    "addr:housenumber":"5",
    "addr:postcode":"1961 ea",
    "addr:street":"Kerkpln",
    "iso:country":"NL",
    "sg:address":"Kerkpln 5",
    "sg:city":"Heemskerk",
    "sg:orig_category":"Projectinrichting",
    "sg:phone":"+31 251 237 282",
    "sg:postcode":"1961 EA",
    "sg:province":"Noord-Holland",
    "wof:name":"Beermann Bv, Jos",
    "wof:placetype":"venue"
},
  "geometry": {"coordinates":[4.670682,52.511368],"type":"Point"}
}