{
  "type": "Feature",
  "properties": {
    "addr:full":"Erasmuspln 8-9 Breda North Brabant 4834 AD",
    "addr:housenumber":"8-9",
    "addr:postcode":"4834 ad",
    "addr:street":"Erasmuspln",
    "iso:country":"NL",
    "sg:address":"Erasmuspln 8-9",
    "sg:city":"Breda",
    "sg:orig_category":"Kappers",
    "sg:phone":"+31 76 565 7674",
    "sg:postcode":"4834 AD",
    "sg:province":"North Brabant",
    "wof:name":"Mondo",
    "wof:placetype":"venue"
},
  "geometry": {"coordinates":[4.795562,51.574818],"type":"Point"}
}