{
  "type": "Feature",
  "properties": {
    "addr:full":"Hoofdwg 60 Emst Gelderland 8166 AG",
    "addr:housenumber":"60",
    "addr:postcode":"8166",
    "addr:street":"Hoofdwg;Gelderland",
    "iso:country":"NL",
    "sg:address":"Hoofdwg 60",
    "sg:city":"Emst",
    "sg:orig_category":"Banken",
    "sg:phone":"+31 578 676 100",
    "sg:postcode":"8166 AG",
    "sg:province":"Gelderland",
    "sg:website":"http://www.rabobank.nl",
    "wof:name":"Rabobank",
    "wof:placetype":"venue"
},
  "geometry": {"coordinates":[5.976086,52.317654],"type":"Point"}
}