{
  "type": "Feature",
  "properties": {
    "addr:full":"Utrechtlaan 96 Enschede Overijssel 7543 BS",
    "addr:housenumber":"96",
    "addr:postcode":"7543 bs",
    "addr:street":"Utrechtlaan",
    "iso:country":"NL",
    "sg:address":"Utrechtlaan 96",
    "sg:city":"Enschede",
    "sg:classifiers":[
        {
            "category":"Education",
            "subcategory":"Preschool",
            "type":"Public Place"
        }
    ],
    "sg:phone":"+31 53 477 7048",
    "sg:postcode":"7543 BS",
    "sg:province":"Overijssel",
    "sg:tags":[
        "kleuteronderwijs",
        "basis-"
    ],
    "wof:name":"Nijntje Pluis",
    "wof:placetype":"venue"
},
  "geometry": {"coordinates":[6.884285,52.204346],"type":"Point"}
}