{
  "type": "Feature",
  "properties": {
    "addr:full":"F Halskd 118 Ryswyk Zh South Holland 2282 VC",
    "addr:housenumber":"118",
    "addr:postcode":"2282 vc",
    "addr:street":"Ryswyk Zh",
    "iso:country":"NL",
    "sg:address":"F Halskd 118",
    "sg:city":"Ryswyk Zh",
    "sg:orig_category":"Verenigingen En Stichtingen",
    "sg:phone":"+31 70 390 6191",
    "sg:postcode":"2282 VC",
    "sg:province":"South Holland",
    "wof:name":"Vervoer Gehandicapten, Sticht",
    "wof:placetype":"venue"
},
  "geometry": {"coordinates":[4.33694,52.056503],"type":"Point"}
}