{
  "type": "Feature",
  "properties": {
    "addr:full":"Gedempte Gracht 28 'S Gravenhage South Holland 2512 AL",
    "addr:housenumber":"28",
    "addr:postcode":"2512 al",
    "addr:street":"Gedempte Gracht;' S Gravenhage",
    "iso:country":"NL",
    "sg:address":"Gedempte Gracht 28",
    "sg:city":"'S Gravenhage",
    "sg:orig_category":"Fotolaboratoria",
    "sg:phone":"+31 70 365 9844",
    "sg:postcode":"2512 AL",
    "sg:province":"South Holland",
    "wof:name":"Hema",
    "wof:placetype":"venue"
},
  "geometry": {"coordinates":[4.313855,52.07642],"type":"Point"}
}