{
  "type": "Feature",
  "properties": {
    "addr:full":"Bermweg 282 Capelle A/D Ijssel South Holland 2906 LH",
    "addr:housenumber":"282;a / d",
    "addr:postcode":"2906 lh",
    "addr:street":"Bermweg;Ijssel South",
    "iso:country":"NL",
    "sg:address":"Bermweg 282",
    "sg:city":"Capelle A/D Ijssel",
    "sg:orig_category":"Verlichting And Huishoudartikelen",
    "sg:phone":"+31 10 450 7456",
    "sg:postcode":"2906 LH",
    "sg:province":"South Holland",
    "wof:name":"Firma J. De Waardt",
    "wof:placetype":"venue"
},
  "geometry": {"coordinates":[4.577721,51.936195],"type":"Point"}
}