{
  "type": "Feature",
  "properties": {
    "iso:country":"NL",
    "sg:address":"Borgercompagnie 101",
    "sg:city":"Borgercompagnie",
    "sg:orig_category":"Goederenvervoer Over De Weg",
    "sg:phone":"+31 598 627 186",
    "sg:postcode":"9631 TE",
    "sg:province":"Groningen",
    "wof:name":"J.M. Hamstra",
    "wof:placetype":"venue"
},
  "geometry": {"coordinates":[6.818363,53.118423],"type":"Point"}
}