{
  "type": "Feature",
  "properties": {
    "addr:full":"Weth Klerkstr 2A Beesd Gelderland 4153 VK",
    "addr:housenumber":"2a",
    "addr:postcode":"4153 vk",
    "addr:street":"Weth Klerkstr;Gelderland",
    "iso:country":"NL",
    "sg:address":"Weth Klerkstr 2A",
    "sg:city":"Beesd",
    "sg:classifiers":[
        {
            "category":"Food & Beverages",
            "subcategory":"Meat & Fish",
            "type":"Retail Goods"
        }
    ],
    "sg:phone":"+31 345 683 729",
    "sg:postcode":"4153 VK",
    "sg:province":"Gelderland",
    "sg:tags":[
        "bindsystemen",
        "en",
        "-machines"
    ],
    "sg:website":"http://www.bindingsystems.nl",
    "wof:name":"Binding Systems",
    "wof:placetype":"venue"
},
  "geometry": {"coordinates":[5.196452,51.888981],"type":"Point"}
}