{
  "type": "Feature",
  "properties": {
    "addr:full":"Hoofdstraat 35 Gorssel Gelderland 7213 CP",
    "addr:housenumber":"35",
    "addr:postcode":"7213 cp",
    "addr:street":"Hoofdstraat;Gelderland",
    "iso:country":"NL",
    "sg:address":"Hoofdstraat 35",
    "sg:city":"Gorssel",
    "sg:orig_category":"Verzekeringen",
    "sg:phone":"+31 575 491 525",
    "sg:postcode":"7213 CP",
    "sg:province":"Gelderland",
    "wof:name":"Assurantie- En Financieringskantoor Loman",
    "wof:placetype":"venue"
},
  "geometry": {"coordinates":[6.200189,52.198589],"type":"Point"}
}