{
  "type": "Feature",
  "properties": {
    "addr:full":"Kanaal N 216 Apeldoorn Gelderland 7322 AE",
    "addr:housenumber":"216",
    "addr:postcode":"7322 ae",
    "addr:street":"Kanaal N;Gelderland",
    "iso:country":"NL",
    "sg:address":"Kanaal N 216",
    "sg:city":"Apeldoorn",
    "sg:classifiers":[
        {
            "category":"Retail",
            "subcategory":"Auto Repair",
            "type":"Services"
        }
    ],
    "sg:phone":"+31 55 366 9210",
    "sg:postcode":"7322 AE",
    "sg:province":"Gelderland",
    "sg:tags":[
        "garage"
    ],
    "wof:name":"Marvo Plaatwerk/Autoservice",
    "wof:placetype":"venue"
},
  "geometry": {"coordinates":[5.974367,52.224735],"type":"Point"}
}