{
  "type": "Feature",
  "properties": {
    "addr:full":"Oostdk 12 Oud Beyerland Zuid-Holland 3261 KH",
    "addr:housenumber":"12",
    "addr:postcode":"3261 kh",
    "addr:street":"Oostdk;Oud Beyerland",
    "iso:country":"NL",
    "sg:address":"Oostdk 12",
    "sg:city":"Oud Beyerland",
    "sg:orig_category":"Kaas",
    "sg:phone":"+31 186 621 191",
    "sg:postcode":"3261 KH",
    "sg:province":"Zuid-Holland",
    "wof:name":"Kaesstolp, De",
    "wof:placetype":"venue"
},
  "geometry": {"coordinates":[4.4134941101,51.8262748718],"type":"Point"}
}