{
  "type": "Feature",
  "properties": {
    "addr:full":"Paalwerk 7 Emmen Provincie Drenthe 7823 VC",
    "addr:housenumber":"7",
    "addr:postcode":"7823 vc",
    "addr:street":"Paalwerk;Provincie Drenthe",
    "iso:country":"NL",
    "sg:address":"Paalwerk 7",
    "sg:city":"Emmen",
    "sg:orig_category":"Wasserettes, Stomerijen And Reiniging",
    "sg:phone":"+31 591 675 500",
    "sg:postcode":"7823 VC",
    "sg:province":"Provincie Drenthe",
    "wof:name":"Floortec/Tmr Henk De Boer",
    "wof:placetype":"venue"
},
  "geometry": {"coordinates":[6.9341669083,52.7996940613],"type":"Point"}
}