{
  "type": "Feature",
  "properties": {
    "addr:full":"Dorpstr 65 Linschoten Utrecht 3461 CR",
    "addr:housenumber":"65",
    "addr:postcode":"3461 cr",
    "addr:street":"Dorpstr",
    "iso:country":"NL",
    "sg:address":"Dorpstr 65",
    "sg:city":"Linschoten",
    "sg:orig_category":"Postkantoren",
    "sg:phone":"+31 348 412 790",
    "sg:postcode":"3461 CR",
    "sg:province":"Utrecht",
    "sg:website":"http://www.postkantoor.nl",
    "wof:name":"Postkantoor",
    "wof:placetype":"venue"
},
  "geometry": {"coordinates":[4.915297,52.060574],"type":"Point"}
}