{
  "type": "Feature",
  "properties": {
    "iso:country":"NL",
    "sg:address":"Ambachtsstraat 27",
    "sg:city":"Winterswijk",
    "sg:orig_category":"Bedrijfsinventaris Gh",
    "sg:phone":"+31 543 512 301",
    "sg:postcode":"7102 DW",
    "sg:province":"Gelderland",
    "wof:name":"Meijers Pan Glaze Vof",
    "wof:placetype":"venue"
},
  "geometry": {"coordinates":[6.71063,51.962811],"type":"Point"}
}