{
  "type": "Feature",
  "properties": {
    "addr:full":"C Petitwg 8 Breda Noord-Brabant 4827 HJ",
    "addr:housenumber":"8",
    "addr:postcode":"4827 hj",
    "iso:country":"NL",
    "sg:address":"C Petitwg 8",
    "sg:city":"Breda",
    "sg:orig_category":"Wegenbouw - Materialen",
    "sg:phone":"+31 76 587 6247",
    "sg:postcode":"4827 HJ",
    "sg:province":"Noord-Brabant",
    "wof:name":"Btn Bv",
    "wof:placetype":"venue"
},
  "geometry": {"coordinates":[4.8036432266,51.6043014526],"type":"Point"}
}