{
  "type": "Feature",
  "properties": {
    "addr:full":"Bremstr 19 St Willebrord Noord-Brabant 4711 CD",
    "addr:housenumber":"19",
    "addr:postcode":"4711 cd",
    "addr:street":"Bremstr",
    "iso:country":"NL",
    "sg:address":"Bremstr 19",
    "sg:city":"St Willebrord",
    "sg:orig_category":"Lasbedrijven",
    "sg:phone":"+31 165 386 698",
    "sg:postcode":"4711 CD",
    "sg:province":"Noord-Brabant",
    "wof:name":"Lbs",
    "wof:placetype":"venue"
},
  "geometry": {"coordinates":[4.588554,51.556984],"type":"Point"}
}