{
  "type": "Feature",
  "properties": {
    "addr:full":"Flevoln 41 Naarden North Holland 1411 KC",
    "addr:housenumber":"41",
    "addr:postcode":"1411 kc",
    "addr:street":"Flevoln",
    "iso:country":"NL",
    "sg:address":"Flevoln 41",
    "sg:city":"Naarden",
    "sg:orig_category":"Omroep",
    "sg:phone":"+31 35 695 8577",
    "sg:postcode":"1411 KC",
    "sg:province":"North Holland",
    "wof:name":"Body + Mind Multi Media",
    "wof:placetype":"venue"
},
  "geometry": {"coordinates":[5.161848,52.296371],"type":"Point"}
}