{
  "type": "Feature",
  "properties": {
    "addr:full":"Burg Slobln 14 Meerkerk Zuid-Holland 4231 AB",
    "addr:housenumber":"14",
    "addr:postcode":"4231 ab",
    "addr:street":"Burg",
    "iso:country":"NL",
    "sg:address":"Burg Slobln 14",
    "sg:city":"Meerkerk",
    "sg:orig_category":"Scholen Voor Basisonderwijs",
    "sg:phone":"+31 183 351 788",
    "sg:postcode":"4231 AB",
    "sg:province":"Zuid-Holland",
    "wof:name":"Springplank Openb, De",
    "wof:placetype":"venue"
},
  "geometry": {"coordinates":[4.99598,51.920277],"type":"Point"}
}