{
  "type": "Feature",
  "properties": {
    "addr:full":"Wethouder Vospad 24 Amsterdam Zuidoost North Holland 1107 DH",
    "addr:housenumber":"24",
    "addr:postcode":"1107 dh",
    "addr:street":"Wethouder Vospad",
    "iso:country":"NL",
    "sg:address":"Wethouder Vospad 24",
    "sg:city":"Amsterdam Zuidoost",
    "sg:classifiers":[
        {
            "category":"Professional",
            "subcategory":"Accounting & Tax Preparation",
            "type":"Services"
        }
    ],
    "sg:phone":"+31 20 696 1442",
    "sg:postcode":"1107 DH",
    "sg:province":"North Holland",
    "sg:tags":[
        "accountant"
    ],
    "wof:name":"Dacos",
    "wof:placetype":"venue"
},
  "geometry": {"coordinates":[4.992106,52.292423],"type":"Point"}
}