{
  "type": "Feature",
  "properties": {
    "addr:full":"Dorpsstr 59 Krabbendijke Zeeland 4413 BL",
    "addr:housenumber":"59",
    "addr:postcode":"4413 bl",
    "addr:street":"Dorpsstr",
    "iso:country":"NL",
    "sg:address":"Dorpsstr 59",
    "sg:city":"Krabbendijke",
    "sg:orig_category":"Drogisterijen",
    "sg:phone":"+31 113 501 259",
    "sg:postcode":"4413 BL",
    "sg:province":"Zeeland",
    "wof:name":"Looijen",
    "wof:placetype":"venue"
},
  "geometry": {"coordinates":[4.112655,51.430172],"type":"Point"}
}