{
  "type": "Feature",
  "properties": {
    "addr:full":"C Schadeweg 37 Oosterbeek Gelderland 6861 ER",
    "addr:housenumber":"37",
    "addr:postcode":"6861 er",
    "addr:street":"C Schadeweg;Gelderland",
    "iso:country":"NL",
    "sg:address":"C Schadeweg 37",
    "sg:city":"Oosterbeek",
    "sg:orig_category":"Diverse Bedrijfsinstallaties Gh",
    "sg:phone":"+31 26 333 4618",
    "sg:postcode":"6861 ER",
    "sg:province":"Gelderland",
    "wof:name":"Hpg",
    "wof:placetype":"venue"
},
  "geometry": {"coordinates":[5.845094,51.991978],"type":"Point"}
}