{
  "type": "Feature",
  "properties": {
    "addr:full":"Den Ilp 192 Den Ilp North Holland 1127 PV",
    "addr:housenumber":"192",
    "addr:postcode":"1127 pv",
    "addr:street":"Den Ilp",
    "iso:country":"NL",
    "sg:address":"Den Ilp 192",
    "sg:city":"Den Ilp",
    "sg:orig_category":"Verhuur Catering-, Feest- En Evenementbenodigdheden",
    "sg:phone":"+31 299 420 200",
    "sg:postcode":"1127 PV",
    "sg:province":"North Holland",
    "wof:name":"Cleem Rijnbeek Speelautomaten",
    "wof:placetype":"venue"
},
  "geometry": {"coordinates":[4.91404,52.46809],"type":"Point"}
}