{
  "type": "Feature",
  "properties": {
    "addr:full":"Koolmees 51 Breda Noord-Brabant 4822 PP",
    "addr:housenumber":"51",
    "addr:postcode":"4822 pp",
    "addr:street":"Koolmees",
    "iso:country":"NL",
    "sg:address":"Koolmees 51",
    "sg:city":"Breda",
    "sg:orig_category":"Koeriersdiensten",
    "sg:phone":"+31 76 544 0344",
    "sg:postcode":"4822 PP",
    "sg:province":"Noord-Brabant",
    "wof:name":"Aert, Van",
    "wof:placetype":"venue"
},
  "geometry": {"coordinates":[4.732374,51.617958],"type":"Point"}
}