{
  "type": "Feature",
  "properties": {
    "addr:full":"Prinses Marijkestraat 2 Stramproy Limburg 6039 BX",
    "addr:housenumber":"2",
    "addr:postcode":"6039 bx",
    "addr:street":"Prinses Marijkestraat",
    "iso:country":"NL",
    "sg:address":"Prinses Marijkestraat 2",
    "sg:city":"Stramproy",
    "sg:orig_category":"Verhuur Audiovisuele Apparatuur",
    "sg:phone":"+31 495 563 092",
    "sg:postcode":"6039 BX",
    "sg:province":"Limburg",
    "wof:name":"J.M.M. Geelen",
    "wof:placetype":"venue"
},
  "geometry": {"coordinates":[5.721265,51.196117],"type":"Point"}
}