{
  "type": "Feature",
  "properties": {
    "addr:full":"Spittaalstraat 28 Zutphen Gelderland 7201 ED",
    "addr:housenumber":"28",
    "addr:postcode":"7201 ed",
    "addr:street":"Spittaalstraat;Gelderland",
    "iso:country":"NL",
    "sg:address":"Spittaalstraat 28",
    "sg:city":"Zutphen",
    "sg:orig_category":"Bloemen And Planten",
    "sg:phone":"+31 575 546 301",
    "sg:postcode":"7201 ED",
    "sg:province":"Gelderland",
    "wof:name":"T Bloemenhuis",
    "wof:placetype":"venue"
},
  "geometry": {"coordinates":[6.199562,52.13813],"type":"Point"}
}