{
  "type": "Feature",
  "properties": {
    "addr:full":"Middelgraaf 63 Tilburg Noord-Brabant 5032 EH",
    "addr:housenumber":"63",
    "addr:postcode":"5032 eh",
    "addr:street":"Middelgraaf",
    "iso:country":"NL",
    "sg:address":"Middelgraaf 63",
    "sg:city":"Tilburg",
    "sg:orig_category":"Schoenen",
    "sg:phone":"+31 13 463 7806",
    "sg:postcode":"5032 EH",
    "sg:province":"Noord-Brabant",
    "wof:name":"Kerckhoven, Van",
    "wof:placetype":"venue"
},
  "geometry": {"coordinates":[5.043278,51.541958],"type":"Point"}
}