{
  "type": "Feature",
  "properties": {
    "addr:full":"Bovenpad 9 Oldebroek Gelderland 8096 RM",
    "addr:housenumber":"9",
    "addr:postcode":"8096 rm",
    "addr:street":"Bovenpad;Gelderland",
    "iso:country":"NL",
    "sg:address":"Bovenpad 9",
    "sg:city":"Oldebroek",
    "sg:orig_category":"Loonbedrijven",
    "sg:phone":"+31 525 630 963",
    "sg:postcode":"8096 RM",
    "sg:province":"Gelderland",
    "wof:name":"Hof, L Van 'T",
    "wof:placetype":"venue"
},
  "geometry": {"coordinates":[5.931711,52.448208],"type":"Point"}
}