{
  "type": "Feature",
  "properties": {
    "iso:country":"NL",
    "sg:address":"Braak En Bosch 20Hs",
    "sg:city":"Amsterdam",
    "sg:orig_category":"Loodgieterswerk, Verwarming And Sanitaire Installaties",
    "sg:phone":"+31 20 619 0730",
    "sg:postcode":"1068 DN",
    "sg:province":"North Holland",
    "wof:name":"C. Borst",
    "wof:placetype":"venue"
},
  "geometry": {"coordinates":[4.799092,52.361355],"type":"Point"}
}