{
  "type": "Feature",
  "properties": {
    "addr:full":"Rietveldseweg 21 Culemborg Gelderland 4107 LJ",
    "addr:housenumber":"21;lj",
    "addr:postcode":"4107",
    "addr:street":"Rietveldseweg;Gelderland",
    "iso:country":"NL",
    "sg:address":"Rietveldseweg 21",
    "sg:city":"Culemborg",
    "sg:orig_category":"Kampeerterreinen",
    "sg:phone":"+31 345 513 050",
    "sg:postcode":"4107 LJ",
    "sg:province":"Gelderland",
    "wof:name":"Campingwinkel De Welborn",
    "wof:placetype":"venue"
},
  "geometry": {"coordinates":[5.1850380898,51.9370079041],"type":"Point"}
}