{
  "type": "Feature",
  "properties": {
    "addr:full":"Pisuissestr 471 S Gravenhage Zuid-Holland 2553 BR",
    "addr:housenumber":"471;gravenhage",
    "addr:postcode":"2553 br",
    "addr:street":"S",
    "iso:country":"NL",
    "sg:address":"Pisuissestr 471",
    "sg:city":"S Gravenhage",
    "sg:classifiers":[
        {
            "category":"Recreation",
            "subcategory":"Dog Park",
            "type":"Entertainment"
        }
    ],
    "sg:phone":"+31 70 404 1824",
    "sg:postcode":"2553 BR",
    "sg:province":"Zuid-Holland",
    "sg:tags":[
        "chauffeur",
        "met",
        "autoverhuur"
    ],
    "wof:name":"Cosmo",
    "wof:placetype":"venue"
},
  "geometry": {"coordinates":[4.21987,52.046589],"type":"Point"}
}