{
  "type": "Feature",
  "properties": {
    "addr:full":"Spoorsngl 24 Rotterdam South Holland 3033 GL",
    "addr:housenumber":"24",
    "addr:postcode":"3033 gl",
    "addr:street":"Spoorsngl",
    "iso:country":"NL",
    "sg:address":"Spoorsngl 24",
    "sg:city":"Rotterdam",
    "sg:classifiers":[
        {
            "category":"Travel",
            "subcategory":"Hotels & Motels",
            "type":"Entertainment"
        }
    ],
    "sg:phone":"+31 10 466 9394",
    "sg:postcode":"3033 GL",
    "sg:province":"South Holland",
    "sg:website":"http://www.hotelbienvenue.nl",
    "wof:name":"Bienvenue Hotel",
    "wof:placetype":"venue"
},
  "geometry": {"coordinates":[4.46912,51.927521],"type":"Point"}
}