{
  "type": "Feature",
  "properties": {
    "addr:full":"F Hendrikstr 24Hs Amsterdam North Holland 1052 HV",
    "addr:postcode":"1052 hv",
    "iso:country":"NL",
    "sg:address":"F Hendrikstr 24Hs",
    "sg:city":"Amsterdam",
    "sg:orig_category":"Evenementenverzorging",
    "sg:phone":"+31 20 681 6669",
    "sg:postcode":"1052 HV",
    "sg:province":"North Holland",
    "sg:website":"http://www.doldramaoplocatie.nl",
    "wof:name":"Dol Drama Op Locatie",
    "wof:placetype":"venue"
},
  "geometry": {"coordinates":[4.874479,52.377728],"type":"Point"}
}