{
  "type": "Feature",
  "properties": {
    "addr:full":"Beukendreef 2 Putte North Brabant 4645 HV",
    "addr:housenumber":"2",
    "addr:postcode":"4645 hv",
    "addr:street":"Beukendreef",
    "iso:country":"NL",
    "sg:address":"Beukendreef 2",
    "sg:city":"Putte",
    "sg:orig_category":"Bejaarden - Verzorgingstehuizen",
    "sg:phone":"+31 164 603 020",
    "sg:postcode":"4645 HV",
    "sg:province":"North Brabant",
    "wof:name":"Beukenhof, De",
    "wof:placetype":"venue"
},
  "geometry": {"coordinates":[4.392063,51.360744],"type":"Point"}
}