{
  "type": "Feature",
  "properties": {
    "iso:country":"NL",
    "sg:address":"Dorpspln 32",
    "sg:city":"Koudekerke",
    "sg:orig_category":"Zoetwaren - Fabrieken En Groothandel",
    "sg:phone":"+31 118 552 710",
    "sg:postcode":"4371 AB",
    "sg:province":"Zeeland",
    "wof:name":"In Den Zoeten Inval, Fa",
    "wof:placetype":"venue"
},
  "geometry": {"coordinates":[3.554815,51.482426],"type":"Point"}
}