{
  "type": "Feature",
  "properties": {
    "iso:country":"NL",
    "sg:address":"Bagynhof 20",
    "sg:city":"Medemblik",
    "sg:orig_category":"Huishoudelijke Apparaten En Artikelen",
    "sg:phone":"+31 227 542 185",
    "sg:postcode":"1671 CD",
    "sg:province":"North Holland",
    "wof:name":"Expert Shop Everything",
    "wof:placetype":"venue"
},
  "geometry": {"coordinates":[5.104993,52.772465],"type":"Point"}
}