{
  "type": "Feature",
  "properties": {
    "addr:full":"Parkstr 32 Velp Gld Gelderland 6881 JG",
    "addr:housenumber":"32",
    "addr:postcode":"6881 jg",
    "addr:street":"Parkstr;Gld Gelderland",
    "iso:country":"NL",
    "sg:address":"Parkstr 32",
    "sg:city":"Velp Gld",
    "sg:orig_category":"Musea",
    "sg:phone":"+31 26 364 2996",
    "sg:postcode":"6881 JG",
    "sg:province":"Gelderland",
    "wof:name":"Gelders Geologisch Museum",
    "wof:placetype":"venue"
},
  "geometry": {"coordinates":[5.971482,51.998501],"type":"Point"}
}