{
  "type": "Feature",
  "properties": {
    "addr:full":"Oude Doetinchem Wg 61 Zeddam Gelderland 7038 BG",
    "addr:housenumber":"61",
    "addr:postcode":"7038",
    "addr:street":"Oude Doetinchem Wg;Gelderland",
    "iso:country":"NL",
    "sg:address":"Oude Doetinchem Wg 61",
    "sg:city":"Zeddam",
    "sg:orig_category":"Verenigingen En Stichtingen",
    "sg:phone":"+31 314 651 063",
    "sg:postcode":"7038 BG",
    "sg:province":"Gelderland",
    "wof:name":"Oswaldus, Sticht St",
    "wof:placetype":"venue"
},
  "geometry": {"coordinates":[6.26216,51.90379],"type":"Point"}
}