{
  "type": "Feature",
  "properties": {
    "addr:full":"Stationsweg 62 Budel Dorplein North Brabant 6024 BM",
    "addr:housenumber":"62",
    "addr:postcode":"6024 bm",
    "addr:street":"Stationsweg;Dorplein",
    "iso:country":"NL",
    "sg:address":"Stationsweg 62",
    "sg:city":"Budel Dorplein",
    "sg:classifiers":[
        {
            "category":"Fast Food",
            "type":"Food & Drink"
        }
    ],
    "sg:phone":"+31 495 495 069",
    "sg:postcode":"6024 BM",
    "sg:province":"North Brabant",
    "sg:tags":[
        "afhaal",
        "restaurant"
    ],
    "wof:name":"Cafetaria 'T Pandje",
    "wof:placetype":"venue"
},
  "geometry": {"coordinates":[5.569531,51.241074],"type":"Point"}
}