{
  "type": "Feature",
  "properties": {
    "iso:country":"NL",
    "sg:address":"Hoofdstraat 118",
    "sg:city":"Emmen",
    "sg:orig_category":"Bloemen And Planten",
    "sg:phone":"+31 591 615 856",
    "sg:postcode":"7811 ET",
    "sg:province":"Provincie Drenthe",
    "wof:name":"De Bloemenhut",
    "wof:placetype":"venue"
},
  "geometry": {"coordinates":[6.895032,52.78867],"type":"Point"}
}