{
  "type": "Feature",
  "properties": {
    "iso:country":"NL",
    "sg:address":"Hazenkoog 37B",
    "sg:city":"Alkmaar",
    "sg:orig_category":"Voegwerken",
    "sg:phone":"+31 72 564 6379",
    "sg:postcode":"1822 BS",
    "sg:province":"North Holland",
    "wof:name":"Nickro Bv",
    "wof:placetype":"venue"
},
  "geometry": {"coordinates":[4.794381,52.654999],"type":"Point"}
}