{
  "type": "Feature",
  "properties": {
    "addr:full":"Hazenkoog 37B Alkmaar North Holland 1822 BS",
    "addr:housenumber":"37b",
    "addr:postcode":"1822 bs",
    "addr:street":"Hazenkoog",
    "iso:country":"NL",
    "sg:address":"Hazenkoog 37B",
    "sg:city":"Alkmaar",
    "sg:orig_category":"Voegwerken",
    "sg:phone":"+31 72 564 6379",
    "sg:postcode":"1822 BS",
    "sg:province":"North Holland",
    "wof:name":"Nickro Bv",
    "wof:placetype":"venue"
},
  "geometry": {"coordinates":[4.794381,52.654999],"type":"Point"}
}