{
  "type": "Feature",
  "properties": {
    "iso:country":"NL",
    "sg:address":"Tolgaarder 10",
    "sg:city":"Nieuw Vennep",
    "sg:orig_category":"Loodgieterswerk, Verwarming And Sanitaire Installaties",
    "sg:phone":"+31 252 621 516",
    "sg:postcode":"2152 KA",
    "sg:province":"Noord-Holland",
    "wof:name":"Las- En Montagebedrijf M&P",
    "wof:placetype":"venue"
},
  "geometry": {"coordinates":[4.635941,52.272945],"type":"Point"}
}