{
  "type": "Feature",
  "properties": {
    "iso:country":"NL",
    "sg:address":"Troosterhof 17",
    "sg:city":"Utrecht",
    "sg:orig_category":"Hypotheken And Hypotheekbanken",
    "sg:phone":"+31 30 271 1300",
    "sg:postcode":"3571 NC",
    "sg:province":"Utrecht",
    "wof:name":"Mackaaij Assurantien Bv",
    "wof:placetype":"venue"
},
  "geometry": {"coordinates":[5.135794,52.106438],"type":"Point"}
}