{
  "type": "Feature",
  "properties": {
    "addr:full":"Schadijk 65 Veenendaal Utrecht 3905 XB",
    "addr:housenumber":"65",
    "addr:postcode":"3905 xb",
    "addr:street":"Schadijk",
    "iso:country":"NL",
    "sg:address":"Schadijk 65",
    "sg:city":"Veenendaal",
    "sg:orig_category":"Boekhouders",
    "sg:phone":"+31 318 526 072",
    "sg:postcode":"3905 XB",
    "sg:province":"Utrecht",
    "wof:name":"Admin. En Assurantiekantoor Van Laar Vof",
    "wof:placetype":"venue"
},
  "geometry": {"coordinates":[5.53897,52.035706],"type":"Point"}
}