{
  "type": "Feature",
  "properties": {
    "addr:full":"Kruisstr 8 Diever Drenthe 7981 AR",
    "addr:housenumber":"8",
    "addr:postcode":"7981",
    "addr:street":"Kruisstr",
    "iso:country":"NL",
    "sg:address":"Kruisstr 8",
    "sg:city":"Diever",
    "sg:orig_category":"Kappers",
    "sg:phone":"+31 521 592 772",
    "sg:postcode":"7981 AR",
    "sg:province":"Drenthe",
    "wof:name":"Kapper, De",
    "wof:placetype":"venue"
},
  "geometry": {"coordinates":[6.3200330734,52.8560028076],"type":"Point"}
}