{
  "type": "Feature",
  "properties": {
    "addr:full":"Blauwgras 9 Veenendaal Utrecht 3902 AB",
    "addr:housenumber":"9",
    "addr:postcode":"3902 ab",
    "addr:street":"Blauwgras",
    "iso:country":"NL",
    "sg:address":"Blauwgras 9",
    "sg:city":"Veenendaal",
    "sg:orig_category":"Autokeuringen",
    "sg:phone":"+31 318 514 494",
    "sg:postcode":"3902 AB",
    "sg:province":"Utrecht",
    "wof:name":"Gravendeel Auto'S Veenendaal",
    "wof:placetype":"venue"
},
  "geometry": {"coordinates":[5.565888,52.035053],"type":"Point"}
}