{
  "type": "Feature",
  "properties": {
    "iso:country":"NL",
    "sg:address":"Prinsengr 723",
    "sg:city":"Amsterdam",
    "sg:orig_category":"Fotojournalisten Freelance",
    "sg:phone":"+31 20 624 7356",
    "sg:postcode":"1017 JW",
    "sg:province":"North Holland",
    "wof:name":"Anema, T",
    "wof:placetype":"venue"
},
  "geometry": {"coordinates":[4.885667,52.364651],"type":"Point"}
}