{
  "type": "Feature",
  "properties": {
    "iso:country":"NL",
    "sg:address":"De Zelling 5",
    "sg:city":"Hendrik Ido Ambacht",
    "sg:orig_category":"Sportprijzen, Postzegels And Munten",
    "sg:phone":"+31 78 681 7060",
    "sg:postcode":"3342 GS",
    "sg:province":"South Holland",
    "wof:name":"Zijderveld Bv",
    "wof:placetype":"venue"
},
  "geometry": {"coordinates":[4.62292,51.837265],"type":"Point"}
}