{
  "type": "Feature",
  "properties": {
    "addr:full":"Koninginnewg 44 Amsterdam Noord-Holland 1075 EA",
    "addr:housenumber":"44",
    "addr:postcode":"1075 ea",
    "addr:street":"Koninginnewg",
    "iso:country":"NL",
    "sg:address":"Koninginnewg 44",
    "sg:city":"Amsterdam",
    "sg:orig_category":"Beeldende Kunstenaars",
    "sg:phone":"+31 20 676 7314",
    "sg:postcode":"1075 EA",
    "sg:province":"Noord-Holland",
    "wof:name":"Hack, E O T",
    "wof:placetype":"venue"
},
  "geometry": {"coordinates":[4.865395,52.353943],"type":"Point"}
}