{
  "type": "Feature",
  "properties": {
    "addr:full":"Emmastr 4 Naaldwyk Zuid-Holland 2671 ET",
    "addr:housenumber":"4",
    "addr:postcode":"2671 et",
    "addr:street":"Emmastr",
    "iso:country":"NL",
    "sg:address":"Emmastr 4",
    "sg:city":"Naaldwyk",
    "sg:orig_category":"Woninginrichting",
    "sg:phone":"+31 174 623 905",
    "sg:postcode":"2671 ET",
    "sg:province":"Zuid-Holland",
    "wof:name":"Eijk, Dirk Van Der",
    "wof:placetype":"venue"
},
  "geometry": {"coordinates":[4.2061700821,51.9946174622],"type":"Point"}
}