{
  "type": "Feature",
  "properties": {
    "iso:country":"NL",
    "sg:address":"De Hoefkens 15",
    "sg:city":"Moergestel",
    "sg:orig_category":"Verzekeringen",
    "sg:phone":"+31 13 513 2797",
    "sg:postcode":"5066 BX",
    "sg:province":"Noord-Brabant",
    "wof:name":"Guijt Pensioenadviesbureau",
    "wof:placetype":"venue"
},
  "geometry": {"coordinates":[5.171396,51.54731],"type":"Point"}
}