{
  "type": "Feature",
  "properties": {
    "iso:country":"NL",
    "sg:address":"Warmondstr 151",
    "sg:city":"Amsterdam",
    "sg:orig_category":"Webdesign Bureaus",
    "sg:phone":"+31 20 669 3377",
    "sg:postcode":"1058 KW",
    "sg:province":"North Holland",
    "wof:name":"Albrecht",
    "wof:placetype":"venue"
},
  "geometry": {"coordinates":[4.8496451378,52.3531761169],"type":"Point"}
}