{
  "type": "Feature",
  "properties": {
    "addr:full":"Damstraat 92 Dordrecht Zuid-Holland 3319 BE",
    "addr:housenumber":"92",
    "addr:postcode":"3319",
    "addr:street":"Damstraat",
    "iso:country":"NL",
    "sg:address":"Damstraat 92",
    "sg:city":"Dordrecht",
    "sg:orig_category":"Fietshandelaren",
    "sg:phone":"+31 78 616 0460",
    "sg:postcode":"3319 BE",
    "sg:province":"Zuid-Holland",
    "wof:name":"Rijwielhandel Goos Stam",
    "wof:placetype":"venue"
},
  "geometry": {"coordinates":[4.696877,51.79644],"type":"Point"}
}