{
  "type": "Feature",
  "properties": {
    "addr:full":"Middenweg 126 Haarlem Noord-Holland 2024 XG",
    "addr:housenumber":"126",
    "addr:postcode":"2024 xg",
    "addr:street":"Middenweg",
    "iso:country":"NL",
    "sg:address":"Middenweg 126",
    "sg:city":"Haarlem",
    "sg:orig_category":"Kappers",
    "sg:phone":"+31 23 525 2373",
    "sg:postcode":"2024 XG",
    "sg:province":"Noord-Holland",
    "wof:name":"Salon Hoffmann",
    "wof:placetype":"venue"
},
  "geometry": {"coordinates":[4.645547,52.405891],"type":"Point"}
}