{
  "type": "Feature",
  "properties": {
    "iso:country":"NL",
    "sg:address":"Middenweg 126",
    "sg:city":"Haarlem",
    "sg:orig_category":"Kappers",
    "sg:phone":"+31 23 525 2373",
    "sg:postcode":"2024 XG",
    "sg:province":"Noord-Holland",
    "wof:name":"Salon Hoffmann",
    "wof:placetype":"venue"
},
  "geometry": {"coordinates":[4.645547,52.405891],"type":"Point"}
}