{
  "type": "Feature",
  "properties": {
    "addr:full":"Zeghewg 6 Woudenberg Utrecht 3931 MR",
    "addr:housenumber":"6",
    "addr:postcode":"3931 mr",
    "addr:street":"Zeghewg",
    "iso:country":"NL",
    "sg:address":"Zeghewg 6",
    "sg:city":"Woudenberg",
    "sg:orig_category":"Sanitaire Artikelen",
    "sg:phone":"+31 33 286 3002",
    "sg:postcode":"3931 MR",
    "sg:province":"Utrecht",
    "wof:name":"Hek, G",
    "wof:placetype":"venue"
},
  "geometry": {"coordinates":[5.437975,52.079102],"type":"Point"}
}