{
  "type": "Feature",
  "properties": {
    "addr:full":"Schellingwouderdijk 337 Amsterdam Noord-Holland 1023 NK",
    "addr:housenumber":"337",
    "addr:postcode":"1023 nk",
    "addr:street":"Schellingwouderdijk",
    "iso:country":"NL",
    "sg:address":"Schellingwouderdijk 337",
    "sg:city":"Amsterdam",
    "sg:orig_category":"Binnenhuisarchitecten",
    "sg:phone":"+31 20 490 5160",
    "sg:postcode":"1023 NK",
    "sg:province":"Noord-Holland",
    "wof:name":"La Brocanteuse",
    "wof:placetype":"venue"
},
  "geometry": {"coordinates":[4.966997,52.381401],"type":"Point"}
}