{
  "type": "Feature",
  "properties": {
    "addr:full":"Terbregse Recht Rottekd 137 Rotterdam Zuid-Holland 3055 XC",
    "addr:housenumber":"137",
    "addr:postcode":"3055 xc",
    "addr:street":"Terbregse Recht Rottekd",
    "iso:country":"NL",
    "sg:address":"Terbregse Recht Rottekd 137",
    "sg:city":"Rotterdam",
    "sg:orig_category":"Kantoorartikelen",
    "sg:phone":"+31 10 422 9044",
    "sg:postcode":"3055 XC",
    "sg:province":"Zuid-Holland",
    "wof:name":"Sv Design Collection Bv",
    "wof:placetype":"venue"
},
  "geometry": {"coordinates":[4.51684618,51.954498291],"type":"Point"}
}