{
  "type": "Feature",
  "properties": {
    "iso:country":"NL",
    "sg:address":"Wilhelminastraat 2",
    "sg:city":"Dalfsen",
    "sg:orig_category":"Verlichting And Huishoudartikelen",
    "sg:phone":"+31 529 432 603",
    "sg:postcode":"7721 CH",
    "sg:province":"Overijssel",
    "wof:name":"C.J. Lindenburg",
    "wof:placetype":"venue"
},
  "geometry": {"coordinates":[6.260865,52.505329],"type":"Point"}
}