{
  "type": "Feature",
  "properties": {
    "addr:full":"Patryzenln 6 Oostvoorne South Holland 3233 BR",
    "addr:housenumber":"6",
    "addr:postcode":"3233 br",
    "addr:street":"Patryzenln",
    "iso:country":"NL",
    "sg:address":"Patryzenln 6",
    "sg:city":"Oostvoorne",
    "sg:orig_category":"Bejaarden - Verzorgingstehuizen",
    "sg:phone":"+31 181 489 999",
    "sg:postcode":"3233 BR",
    "sg:province":"South Holland",
    "wof:name":"Leemgaarde",
    "wof:placetype":"venue"
},
  "geometry": {"coordinates":[4.095612,51.912029],"type":"Point"}
}