{
  "type": "Feature",
  "properties": {
    "addr:full":"Lysterstr 62 Leeuwarden Friesland 8917 EB",
    "addr:housenumber":"62",
    "addr:postcode":"8917 eb",
    "addr:street":"Lysterstr",
    "iso:country":"NL",
    "sg:address":"Lysterstr 62",
    "sg:city":"Leeuwarden",
    "sg:orig_category":"Kaas",
    "sg:phone":"+31 58 212 5226",
    "sg:postcode":"8917 EB",
    "sg:province":"Friesland",
    "wof:name":"Dijk & Van Der Woude, Kaashandel Fa V",
    "wof:placetype":"venue"
},
  "geometry": {"coordinates":[5.7882351875,53.2089729309],"type":"Point"}
}