{
  "type": "Feature",
  "properties": {
    "addr:full":"Dorpsstraat 22 Rosmalen North Brabant 5241 EC",
    "addr:housenumber":"22",
    "addr:postcode":"5241 ec",
    "addr:street":"Dorpsstraat",
    "iso:country":"NL",
    "sg:address":"Dorpsstraat 22",
    "sg:city":"Rosmalen",
    "sg:orig_category":"Zuivelproducten",
    "sg:phone":"+31 73 521 5749",
    "sg:postcode":"5241 EC",
    "sg:province":"North Brabant",
    "wof:name":"De Kaaswaag Slegers",
    "wof:placetype":"venue"
},
  "geometry": {"coordinates":[5.362528,51.718117],"type":"Point"}
}