{
  "type": "Feature",
  "properties": {
    "addr:full":"Molenrak 19 Zeewolde Flevoland 3891 EK",
    "addr:housenumber":"19",
    "addr:postcode":"3891 ek",
    "addr:street":"Molenrak;Flevoland",
    "iso:country":"NL",
    "sg:address":"Molenrak 19",
    "sg:city":"Zeewolde",
    "sg:orig_category":"Adviesbureaus Financieringen",
    "sg:phone":"+31 36 522 2558",
    "sg:postcode":"3891 EK",
    "sg:province":"Flevoland",
    "wof:name":"Zevenboom",
    "wof:placetype":"venue"
},
  "geometry": {"coordinates":[5.541894,52.333775],"type":"Point"}
}