{
  "type": "Feature",
  "properties": {
    "iso:country":"NL",
    "sg:address":"Korenmarkt 5",
    "sg:city":"Weert",
    "sg:classifiers":[
        {
            "category":"Fast Food",
            "type":"Food & Drink"
        }
    ],
    "sg:phone":"+31 495 533 216",
    "sg:postcode":"6001 EM",
    "sg:province":"Limburg",
    "sg:tags":[
        "afhaal",
        "restaurant"
    ],
    "wof:name":"China",
    "wof:placetype":"venue"
},
  "geometry": {"coordinates":[5.7071590424,51.2539253235],"type":"Point"}
}