{
  "type": "Feature",
  "properties": {
    "addr:full":"Beerze 12 Someren Noord-Brabant 5711 KB",
    "addr:housenumber":"12",
    "addr:postcode":"5711 kb",
    "addr:street":"Beerze",
    "iso:country":"NL",
    "sg:address":"Beerze 12",
    "sg:city":"Someren",
    "sg:orig_category":"Kinderopvang Behalve Thuis",
    "sg:phone":"+31 493 495 974",
    "sg:postcode":"5711 KB",
    "sg:province":"Noord-Brabant",
    "wof:name":"Kinderdagverblijf De Speeldoos",
    "wof:placetype":"venue"
},
  "geometry": {"coordinates":[5.721237,51.389118],"type":"Point"}
}