{
  "type": "Feature",
  "properties": {
    "addr:full":"Marskramer 17 Rhoon Zuid-Holland 3161 ND",
    "addr:housenumber":"17",
    "addr:postcode":"3161 nd",
    "addr:street":"Marskramer",
    "iso:country":"NL",
    "sg:address":"Marskramer 17",
    "sg:city":"Rhoon",
    "sg:orig_category":"Geluidsopnamen",
    "sg:phone":"+31 10 501 5124",
    "sg:postcode":"3161 ND",
    "sg:province":"Zuid-Holland",
    "wof:name":"Audio Rhoon",
    "wof:placetype":"venue"
},
  "geometry": {"coordinates":[4.414363,51.861134],"type":"Point"}
}