{
  "type": "Feature",
  "properties": {
    "addr:full":"Cobaltstr 39 Zoetermeer Zuid-Holland 2718 RN",
    "addr:housenumber":"39",
    "addr:postcode":"2718 rn",
    "addr:street":"Cobaltstr",
    "iso:country":"NL",
    "sg:address":"Cobaltstr 39",
    "sg:city":"Zoetermeer",
    "sg:orig_category":"Verpakkingen En Verpakkingsmaterialen",
    "sg:phone":"+31 79 363 7070",
    "sg:postcode":"2718 RN",
    "sg:province":"Zuid-Holland",
    "wof:name":"Rowipack Bv",
    "wof:placetype":"venue"
},
  "geometry": {"coordinates":[4.515657,52.041279],"type":"Point"}
}