{
  "type": "Feature",
  "properties": {
    "iso:country":"NL",
    "sg:address":"Molengr 30",
    "sg:city":"Den Helder",
    "sg:orig_category":"Marktkramen",
    "sg:phone":"+31 223 613 231",
    "sg:postcode":"1781 NB",
    "sg:province":"North Holland",
    "wof:name":"Kroos, J H G",
    "wof:placetype":"venue"
},
  "geometry": {"coordinates":[4.766778,52.962589],"type":"Point"}
}