{
  "type": "Feature",
  "properties": {
    "addr:full":"Hekelstraat 28 Alkmaar North Holland 1811 BM",
    "addr:housenumber":"28",
    "addr:postcode":"1811 bm",
    "addr:street":"Hekelstraat",
    "iso:country":"NL",
    "sg:address":"Hekelstraat 28",
    "sg:city":"Alkmaar",
    "sg:orig_category":"Kunst And Kunstenaarsbenodigdheden",
    "sg:phone":"+31 72 515 0228",
    "sg:postcode":"1811 BM",
    "sg:province":"North Holland",
    "wof:name":"Galerie Fi Donc Animatie Kunsthandel",
    "wof:placetype":"venue"
},
  "geometry": {"coordinates":[4.750569,52.630077],"type":"Point"}
}