{
  "type": "Feature",
  "properties": {
    "addr:full":"Burg V Roijensngl 4 Zwolle Overijssel 8011 CS",
    "addr:housenumber":"4",
    "addr:postcode":"8011 cs",
    "addr:street":"Burg V Roijensngl",
    "iso:country":"NL",
    "sg:address":"Burg V Roijensngl 4",
    "sg:city":"Zwolle",
    "sg:orig_category":"Diverse Consumentenartikelen Gh",
    "sg:phone":"+31 38 421 3742",
    "sg:postcode":"8011 CS",
    "sg:province":"Overijssel",
    "wof:name":"Music Unlimited",
    "wof:placetype":"venue"
},
  "geometry": {"coordinates":[6.0887379646,52.5125656128],"type":"Point"}
}