{
  "type": "Feature",
  "properties": {
    "iso:country":"NL",
    "sg:address":"Aardbolhof 13",
    "sg:city":"Maarn",
    "sg:orig_category":"Adviesbureaus Bedrijfsorganisatie",
    "sg:phone":"+31 343 443 576",
    "sg:postcode":"3951 EB",
    "sg:province":"Utrecht",
    "wof:name":"Haaren, Van",
    "wof:placetype":"venue"
},
  "geometry": {"coordinates":[5.382091,52.065117],"type":"Point"}
}