{
  "type": "Feature",
  "properties": {
    "addr:full":"Nijverheidsstraat 3 Hardenberg Overijssel 7772 TP",
    "addr:housenumber":"3",
    "addr:postcode":"7772 tp",
    "addr:street":"Nijverheidsstraat",
    "iso:country":"NL",
    "sg:address":"Nijverheidsstraat 3",
    "sg:city":"Hardenberg",
    "sg:orig_category":"Metaalbekleding And -Behandeling",
    "sg:phone":"+31 523 263 260",
    "sg:postcode":"7772 TP",
    "sg:province":"Overijssel",
    "wof:name":"Strigl Metaal Bv",
    "wof:placetype":"venue"
},
  "geometry": {"coordinates":[6.630312,52.559284],"type":"Point"}
}