{
  "type": "Feature",
  "properties": {
    "addr:full":"Strandweg 1 'S Gravenhage Zuid-Holland 2586 JK",
    "addr:housenumber":"1 '",
    "addr:postcode":"2586 jk",
    "addr:street":"Strandweg",
    "iso:country":"NL",
    "sg:address":"Strandweg 1",
    "sg:city":"'S Gravenhage",
    "sg:classifiers":[
        {
            "category":"Fast Food",
            "type":"Food & Drink"
        }
    ],
    "sg:phone":"+31 70 358 5607",
    "sg:postcode":"2586 JK",
    "sg:province":"Zuid-Holland",
    "sg:tags":[
        "afhaal",
        "restaurant"
    ],
    "wof:name":"Strandpaviljoen De Peer",
    "wof:placetype":"venue"
},
  "geometry": {"coordinates":[4.278066,52.111904],"type":"Point"}
}