{
  "type": "Feature",
  "properties": {
    "addr:full":"Poststr 7 Zandvoort Noord-Holland 2042 HA",
    "addr:housenumber":"7",
    "addr:postcode":"2042 ha",
    "addr:street":"Poststr",
    "iso:country":"NL",
    "sg:address":"Poststr 7",
    "sg:city":"Zandvoort",
    "sg:orig_category":"Begrafenisverzorging",
    "sg:phone":"+31 23 571 3278",
    "sg:postcode":"2042 HA",
    "sg:province":"Noord-Holland",
    "wof:name":"Uitvaartcentr Van Onderling Hulpbetoon",
    "wof:placetype":"venue"
},
  "geometry": {"coordinates":[4.528562,52.371033],"type":"Point"}
}