{
  "type": "Feature",
  "properties": {
    "addr:full":"Verl Vaart Nz 90 Erica Drenthe 7887 EJ",
    "addr:housenumber":"90",
    "addr:postcode":"7887 ej",
    "addr:street":"Vaart Nz",
    "iso:country":"NL",
    "sg:address":"Verl Vaart Nz 90",
    "sg:city":"Erica",
    "sg:orig_category":"Postzegels",
    "sg:phone":"+31 591 303 730",
    "sg:postcode":"7887 EJ",
    "sg:province":"Drenthe",
    "wof:name":"Schorpioen, De",
    "wof:placetype":"venue"
},
  "geometry": {"coordinates":[8.50811,51.882469],"type":"Point"}
}