{
  "type": "Feature",
  "properties": {
    "addr:full":"Osseweg 36 Berghem North Brabant 5351 AE",
    "addr:housenumber":"36",
    "addr:postcode":"5351 ae",
    "addr:street":"Osseweg",
    "iso:country":"NL",
    "sg:address":"Osseweg 36",
    "sg:city":"Berghem",
    "sg:orig_category":"Kappers",
    "sg:phone":"+31 412 403 492",
    "sg:postcode":"5351 AE",
    "sg:province":"North Brabant",
    "wof:name":"Kapsalon Smits",
    "wof:placetype":"venue"
},
  "geometry": {"coordinates":[5.559773922,51.7696533203],"type":"Point"}
}