{
  "type": "Feature",
  "properties": {
    "addr:full":"Genneperwg 91 Eindhoven North Brabant 5654 AG",
    "addr:housenumber":"91",
    "addr:postcode":"5654",
    "addr:street":"Genneperwg",
    "iso:country":"NL",
    "sg:address":"Genneperwg 91",
    "sg:city":"Eindhoven",
    "sg:orig_category":"Verf En Lak",
    "sg:phone":"+31 40 251 6578",
    "sg:postcode":"5654 AG",
    "sg:province":"North Brabant",
    "wof:name":"Scheepers Bv",
    "wof:placetype":"venue"
},
  "geometry": {"coordinates":[5.465791,51.424656],"type":"Point"}
}