{
  "type": "Feature",
  "properties": {
    "addr:full":"Hemmerbuurt 83 Hem Noord-Holland 1607 CD",
    "addr:housenumber":"83",
    "addr:postcode":"1607 cd",
    "addr:street":"Hemmerbuurt",
    "iso:country":"NL",
    "sg:address":"Hemmerbuurt 83",
    "sg:city":"Hem",
    "sg:orig_category":"Timmerwerk Van Hout And Kunststof",
    "sg:phone":"+31 228 543 354",
    "sg:postcode":"1607 CD",
    "sg:province":"Noord-Holland",
    "wof:name":"Boon Karweiservice",
    "wof:placetype":"venue"
},
  "geometry": {"coordinates":[-84.171921,34.890556],"type":"Point"}
}