{
  "type": "Feature",
  "properties": {
    "addr:full":"Coenecoop 84 Waddinxveen South Holland 2741 PD",
    "addr:housenumber":"84",
    "addr:postcode":"2741 pd",
    "addr:street":"Coenecoop",
    "iso:country":"NL",
    "sg:address":"Coenecoop 84",
    "sg:city":"Waddinxveen",
    "sg:orig_category":"Fotostudio'S And Fotografen",
    "sg:phone":"+31 182 630 182",
    "sg:postcode":"2741 PD",
    "sg:province":"South Holland",
    "wof:name":"Studio Egbert D'Hamecourt Bv",
    "wof:placetype":"venue"
},
  "geometry": {"coordinates":[4.6542,52.027496],"type":"Point"}
}