{
  "type": "Feature",
  "properties": {
    "iso:country":"NL",
    "sg:address":"Keldermansstraat 92",
    "sg:city":"Tilburg",
    "sg:orig_category":"Loodgieterswerk, Verwarming And Sanitaire Installaties",
    "sg:phone":"+31 13 535 1041",
    "sg:postcode":"5041 KL",
    "sg:province":"Noord-Brabant",
    "wof:name":"W. Cuijpers",
    "wof:placetype":"venue"
},
  "geometry": {"coordinates":[5.066323,51.563976],"type":"Point"}
}