{
  "type": "Feature",
  "properties": {
    "addr:full":"Westeinde 157 Moordrecht Zuid-Holland 2841 BS",
    "addr:housenumber":"157",
    "addr:postcode":"2841 bs",
    "addr:street":"Westeinde",
    "iso:country":"NL",
    "sg:address":"Westeinde 157",
    "sg:city":"Moordrecht",
    "sg:classifiers":[
        {
            "category":"Personal",
            "subcategory":"Nail Salon",
            "type":"Services"
        }
    ],
    "sg:phone":"+31 182 374 398",
    "sg:postcode":"2841 BS",
    "sg:province":"Zuid-Holland",
    "sg:tags":[
        "pedicure"
    ],
    "wof:name":"Bruin, N De",
    "wof:placetype":"venue"
},
  "geometry": {"coordinates":[4.666156,51.980206],"type":"Point"}
}