{
  "type": "Feature",
  "properties": {
    "addr:full":"Voet Of Kraagweg 9 Rockanje Zuid-Holland 3235 LL",
    "addr:housenumber":"9",
    "addr:postcode":"3235 ll",
    "addr:street":"Voet Of Kraagweg",
    "iso:country":"NL",
    "sg:address":"Voet Of Kraagweg 9",
    "sg:city":"Rockanje",
    "sg:orig_category":"Kampeerterreinen",
    "sg:phone":"+31 181 404 179",
    "sg:postcode":"3235 LL",
    "sg:province":"Zuid-Holland",
    "wof:name":"Camping Van Der Burgh",
    "wof:placetype":"venue"
},
  "geometry": {"coordinates":[4.0973591805,51.858215332],"type":"Point"}
}