{
  "type": "Feature",
  "properties": {
    "addr:full":"Drimmelenseweg 32 Made Noord-Brabant 4921 SG",
    "addr:housenumber":"32",
    "addr:postcode":"4921 sg",
    "addr:street":"Drimmelenseweg",
    "iso:country":"NL",
    "sg:address":"Drimmelenseweg 32",
    "sg:city":"Made",
    "sg:orig_category":"Muziekinstrumenten",
    "sg:phone":"+31 162 686 483",
    "sg:postcode":"4921 SG",
    "sg:province":"Noord-Brabant",
    "wof:name":"Pianotechniek J. Van De Roer",
    "wof:placetype":"venue"
},
  "geometry": {"coordinates":[-119.955963,36.850494],"type":"Point"}
}