{
  "type": "Feature",
  "properties": {
    "addr:full":"M Michielshof 38 De Ryp Noord-Holland 1483 CD",
    "addr:housenumber":"38",
    "addr:postcode":"1483 cd",
    "addr:street":"M Michielshof;De Ryp",
    "iso:country":"NL",
    "sg:address":"M Michielshof 38",
    "sg:city":"De Ryp",
    "sg:orig_category":"Verbouwingen",
    "sg:phone":"+31 6 53454461",
    "sg:postcode":"1483 CD",
    "sg:province":"Noord-Holland",
    "wof:name":"Verhappen, J C",
    "wof:placetype":"venue"
},
  "geometry": {"coordinates":[4.846465,52.560177],"type":"Point"}
}