{
  "type": "Feature",
  "properties": {
    "addr:full":"Postbus 186 Sliedrecht Zuid-Holland 3360 AD",
    "addr:housenumber":"186",
    "addr:postcode":"3360 ad",
    "addr:street":"Postbus",
    "iso:country":"NL",
    "sg:address":"Postbus 186",
    "sg:city":"Sliedrecht",
    "sg:orig_category":"Beveiliging",
    "sg:phone":"+31 184 434 100",
    "sg:postcode":"3360 AD",
    "sg:province":"Zuid-Holland",
    "sg:website":"http://www.viewcontrol.nl",
    "wof:name":"Vieuw Control Bv",
    "wof:placetype":"venue"
},
  "geometry": {"coordinates":[4.772605,51.823555],"type":"Point"}
}