{
  "type": "Feature",
  "properties": {
    "addr:full":"Dr A Vd Horstln 48 Naarden North Holland 1411 DB",
    "addr:housenumber":"48",
    "addr:postcode":"1411 db",
    "addr:street":"Dr A",
    "iso:country":"NL",
    "sg:address":"Dr A Vd Horstln 48",
    "sg:city":"Naarden",
    "sg:classifiers":[
        {
            "category":"Professional",
            "subcategory":"Management & Consulting",
            "type":"Services"
        }
    ],
    "sg:phone":"+31 35 695 1275",
    "sg:postcode":"1411 DB",
    "sg:province":"North Holland",
    "sg:tags":[
        "relation",
        "adviesbureaus",
        "public"
    ],
    "sg:website":"http://www.bccboogaard.nl",
    "wof:name":"Boogaard Comm Consultancy",
    "wof:placetype":"venue"
},
  "geometry": {"coordinates":[5.177478,52.288654],"type":"Point"}
}