{
  "type": "Feature",
  "properties": {
    "addr:full":"Sint Antoniusstraat 55 Valkenswaard North Brabant 5552 LN",
    "addr:housenumber":"55",
    "addr:postcode":"5552 ln",
    "addr:street":"Sint Antoniusstraat",
    "iso:country":"NL",
    "sg:address":"Sint Antoniusstraat 55",
    "sg:city":"Valkenswaard",
    "sg:classifiers":[
        {
            "category":"Fast Food",
            "type":"Food & Drink"
        }
    ],
    "sg:phone":"+31 40 201 4388",
    "sg:postcode":"5552 LN",
    "sg:province":"North Brabant",
    "sg:tags":[
        "afhaal",
        "restaurant"
    ],
    "wof:name":"Den Haas 2 C.V.",
    "wof:placetype":"venue"
},
  "geometry": {"coordinates":[5.455448,51.357964],"type":"Point"}
}