{
  "type": "Feature",
  "properties": {
    "iso:country":"NL",
    "sg:address":"Vogelzankweg 228",
    "sg:city":"Landgraaf",
    "sg:orig_category":"Autokeuringen",
    "sg:phone":"+31 45 531 2044",
    "sg:postcode":"6374 AH",
    "sg:province":"Limburg",
    "wof:name":"Imex",
    "wof:placetype":"venue"
},
  "geometry": {"coordinates":[6.025251,50.921383],"type":"Point"}
}