{
  "type": "Feature",
  "properties": {
    "addr:full":"Nieuwstraat 55 Sint Michielsgestel North Brabant 5271 AC",
    "addr:housenumber":"55",
    "addr:postcode":"5271 ac",
    "addr:street":"Nieuwstraat;Sint Michielsgestel",
    "iso:country":"NL",
    "sg:address":"Nieuwstraat 55",
    "sg:city":"Sint Michielsgestel",
    "sg:orig_category":"Autokeuringen",
    "sg:phone":"+31 73 551 2252",
    "sg:postcode":"5271 AC",
    "sg:province":"North Brabant",
    "wof:name":"Servicestation Van Engelen Bv",
    "wof:placetype":"venue"
},
  "geometry": {"coordinates":[5.352419,51.642754],"type":"Point"}
}