{
  "type": "Feature",
  "properties": {
    "addr:full":"Achterweg 14 Nieuwveen Zuid-Holland 2441 GH",
    "addr:housenumber":"14",
    "addr:postcode":"2441 gh",
    "addr:street":"Achterweg",
    "iso:country":"NL",
    "sg:address":"Achterweg 14",
    "sg:city":"Nieuwveen",
    "sg:orig_category":"Keramische Producten Fab",
    "sg:phone":"+31 172 538 838",
    "sg:postcode":"2441 GH",
    "sg:province":"Zuid-Holland",
    "wof:name":"N.G. Trapman",
    "wof:placetype":"venue"
},
  "geometry": {"coordinates":[4.78013,52.207096],"type":"Point"}
}