{
  "type": "Feature",
  "properties": {
    "addr:full":"Zelhemseweg 35 Varsseveld Gelderland 7051 ZB",
    "addr:housenumber":"35",
    "addr:postcode":"7051 zb",
    "addr:street":"Zelhemseweg;Gelderland",
    "iso:country":"NL",
    "sg:address":"Zelhemseweg 35",
    "sg:city":"Varsseveld",
    "sg:orig_category":"Bouwnijverheidsmachines Gh",
    "sg:phone":"+31 315 242 243",
    "sg:postcode":"7051 ZB",
    "sg:province":"Gelderland",
    "wof:name":"Meca Bouwmachines",
    "wof:placetype":"venue"
},
  "geometry": {"coordinates":[6.45905,51.94746],"type":"Point"}
}