{
  "type": "Feature",
  "properties": {
    "addr:full":"Steenstr 36 Boxmeer North Brabant 5831 JE",
    "addr:housenumber":"36",
    "addr:postcode":"5831 je",
    "addr:street":"Steenstr",
    "iso:country":"NL",
    "sg:address":"Steenstr 36",
    "sg:city":"Boxmeer",
    "sg:orig_category":"Kappers",
    "sg:phone":"+31 485 520 991",
    "sg:postcode":"5831 JE",
    "sg:province":"North Brabant",
    "wof:name":"Hippe Knip, De",
    "wof:placetype":"venue"
},
  "geometry": {"coordinates":[5.9530878067,51.6463775635],"type":"Point"}
}