{
  "type": "Feature",
  "properties": {
    "addr:full":"Kapt Nemostr 64 Tilburg North Brabant 5015 AM",
    "addr:housenumber":"64",
    "addr:postcode":"5015",
    "iso:country":"NL",
    "sg:address":"Kapt Nemostr 64",
    "sg:city":"Tilburg",
    "sg:orig_category":"Elektronica - Ontwikkeling En Groothandel",
    "sg:phone":"+31 13 543 8487",
    "sg:postcode":"5015 AM",
    "sg:province":"North Brabant",
    "wof:name":"Riho",
    "wof:placetype":"venue"
},
  "geometry": {"coordinates":[5.109637,51.567421],"type":"Point"}
}