{
  "type": "Feature",
  "properties": {
    "iso:country":"NL",
    "sg:address":"Blyhamsterstr 40",
    "sg:city":"Winschoten",
    "sg:orig_category":"Kamerverhuur En -Bemiddeling",
    "sg:phone":"+31 597 414 290",
    "sg:postcode":"9671 AX",
    "sg:province":"Groningen",
    "wof:name":"Kamerverhuur Blijhamsterweg",
    "wof:placetype":"venue"
},
  "geometry": {"coordinates":[7.0402131081,53.1402015686],"type":"Point"}
}