{
  "type": "Feature",
  "properties": {
    "addr:full":"Plankstr 7 Maastricht Limburg 6211 GA",
    "addr:housenumber":"7",
    "addr:postcode":"6211 ga",
    "addr:street":"Plankstr",
    "iso:country":"NL",
    "sg:address":"Plankstr 7",
    "sg:city":"Maastricht",
    "sg:orig_category":"Herenkleding",
    "sg:phone":"+31 43 321 0069",
    "sg:postcode":"6211 GA",
    "sg:province":"Limburg",
    "wof:name":"Salet, Leon",
    "wof:placetype":"venue"
},
  "geometry": {"coordinates":[5.694073,50.847946],"type":"Point"}
}