{
  "type": "Feature",
  "properties": {
    "addr:full":"Molenstalweg 3 Rijssen Overijssel 7462 AE",
    "addr:housenumber":"3",
    "addr:postcode":"7462 ae",
    "addr:street":"Molenstalweg",
    "iso:country":"NL",
    "sg:address":"Molenstalweg 3",
    "sg:city":"Rijssen",
    "sg:orig_category":"Partycatering And -Organisatie",
    "sg:phone":"+31 548 516 694",
    "sg:postcode":"7462 AE",
    "sg:province":"Overijssel",
    "wof:name":"Partyservice De Molenstal",
    "wof:placetype":"venue"
},
  "geometry": {"coordinates":[6.519293,52.310966],"type":"Point"}
}