{
  "type": "Feature",
  "properties": {
    "iso:country":"NL",
    "sg:address":"Kudelstaartsewg 192",
    "sg:city":"Kudelstaart",
    "sg:orig_category":"Architecten En Architectenbureaus",
    "sg:phone":"+31 297 326 709",
    "sg:postcode":"1433 GP",
    "sg:province":"Noord-Holland",
    "wof:name":"Houwelingen, L J Van",
    "wof:placetype":"venue"
},
  "geometry": {"coordinates":[4.750309,52.238625],"type":"Point"}
}