{
  "type": "Feature",
  "properties": {
    "iso:country":"NL",
    "sg:address":"Kruisln 54",
    "sg:city":"Hoofddorp",
    "sg:orig_category":"Bejaarden - Verzorgingstehuizen",
    "sg:phone":"+31 23 561 6000",
    "sg:postcode":"2131 WE",
    "sg:province":"North Holland",
    "wof:name":"Horizon Prot Chr",
    "wof:placetype":"venue"
},
  "geometry": {"coordinates":[4.70066,52.322971],"type":"Point"}
}