{
  "type": "Feature",
  "properties": {
    "iso:country":"NL",
    "sg:address":"Mr F J Haarmanwg 19",
    "sg:city":"Terneuzen",
    "sg:classifiers":[
        {
            "category":"Retail",
            "subcategory":"Auto Repair",
            "type":"Services"
        }
    ],
    "sg:phone":"+31 115 612 210",
    "sg:postcode":"4538 AM",
    "sg:province":"Zeeland",
    "sg:tags":[
        "garage"
    ],
    "wof:name":"Zegers",
    "wof:placetype":"venue"
},
  "geometry": {"coordinates":[3.830336,51.326378],"type":"Point"}
}