{
  "type": "Feature",
  "properties": {
    "addr:full":"Wolga 11 S Gravenhage 2491 BK",
    "addr:housenumber":"11",
    "addr:postcode":"2491 bk",
    "addr:street":"Wolga;S Gravenhage",
    "iso:country":"NL",
    "sg:address":"Wolga 11",
    "sg:city":"S Gravenhage",
    "sg:orig_category":"Mode Artikelen Dames En Heren - Fabrieken En Groothandel",
    "sg:phone":"+31 70 320 1130",
    "sg:postcode":"2491 BK",
    "wof:name":"Oscar Bv",
    "wof:placetype":"venue"
},
  "geometry": {"coordinates":[4.38382,52.065289],"type":"Point"}
}