{
  "type": "Feature",
  "properties": {
    "iso:country":"NL",
    "sg:address":"Amsterdamsestraatweg 697",
    "sg:city":"Utrecht",
    "sg:orig_category":"Huishoudapparatuur, Televisies And Radio'S",
    "sg:phone":"+31 30 244 6840",
    "sg:postcode":"3555 HD",
    "sg:province":"Utrecht",
    "wof:name":"Miele Speciaalzaak G & D Service Bv",
    "wof:placetype":"venue"
},
  "geometry": {"coordinates":[5.07997,52.112446],"type":"Point"}
}