{
  "type": "Feature",
  "properties": {
    "addr:full":"De Dennen 7B Delden Overijssel 7491 HH",
    "addr:housenumber":"7b",
    "addr:postcode":"7491 hh",
    "addr:street":"De Dennen",
    "iso:country":"NL",
    "sg:address":"De Dennen 7B",
    "sg:city":"Delden",
    "sg:orig_category":"Autoschade- Herstelbedrijven",
    "sg:phone":"+31 74 349 4084",
    "sg:postcode":"7491 HH",
    "sg:province":"Overijssel",
    "wof:name":"Geerlings",
    "wof:placetype":"venue"
},
  "geometry": {"coordinates":[6.694236,52.254677],"type":"Point"}
}