{
  "type": "Feature",
  "properties": {
    "addr:full":"Nieuwstad 44 Zutphen Gelderland 7201 NR",
    "addr:housenumber":"44",
    "addr:postcode":"7201",
    "addr:street":"Nieuwstad;Gelderland;Nr",
    "iso:country":"NL",
    "sg:address":"Nieuwstad 44",
    "sg:city":"Zutphen",
    "sg:orig_category":"Bedden En Matrassen",
    "sg:phone":"+31 575 512 816",
    "sg:postcode":"7201 NR",
    "sg:province":"Gelderland",
    "sg:website":"http://www.bedshop.nl",
    "wof:name":"Duif Zutphen Bv, De",
    "wof:placetype":"venue"
},
  "geometry": {"coordinates":[6.197319,52.144169],"type":"Point"}
}