{
  "type": "Feature",
  "properties": {
    "addr:full":"Stadspln 101 Amstelveen Noord-Holland 1181 ZM",
    "addr:housenumber":"101",
    "addr:postcode":"1181 zm",
    "iso:country":"NL",
    "sg:address":"Stadspln 101",
    "sg:city":"Amstelveen",
    "sg:orig_category":"Autoruiten",
    "sg:phone":"+31 20 445 9833",
    "sg:postcode":"1181 ZM",
    "sg:province":"Noord-Holland",
    "wof:name":"Ster",
    "wof:placetype":"venue"
},
  "geometry": {"coordinates":[4.859919,52.302757],"type":"Point"}
}