{
  "type": "Feature",
  "properties": {
    "addr:full":"Appelaarsewg 8A Fynaart Noord-Brabant 4793 EK",
    "addr:housenumber":"8a",
    "addr:postcode":"4793 ek",
    "addr:street":"Appelaarsewg",
    "iso:country":"NL",
    "sg:address":"Appelaarsewg 8A",
    "sg:city":"Fynaart",
    "sg:orig_category":"Onroerende Goederen",
    "sg:phone":"+31 168 462 353",
    "sg:postcode":"4793 EK",
    "sg:province":"Noord-Brabant",
    "wof:name":"Sighem-Bras Bv, Van",
    "wof:placetype":"venue"
},
  "geometry": {"coordinates":[4.46088,51.635265],"type":"Point"}
}