{
  "type": "Feature",
  "properties": {
    "addr:full":"Kerkstraat 15 Hattem Gelderland 8051 GJ",
    "addr:housenumber":"15",
    "addr:postcode":"8051 gj",
    "addr:street":"Kerkstraat;Gelderland",
    "iso:country":"NL",
    "sg:address":"Kerkstraat 15",
    "sg:city":"Hattem",
    "sg:orig_category":"Damesmodezaken",
    "sg:phone":"+31 38 444 6231",
    "sg:postcode":"8051 GJ",
    "sg:province":"Gelderland",
    "wof:name":"Boutique Albert",
    "wof:placetype":"venue"
},
  "geometry": {"coordinates":[6.068733,52.474453],"type":"Point"}
}