{
  "type": "Feature",
  "properties": {
    "addr:full":"Kerkstr 13B Oud Beyerland South Holland 3262 PG",
    "addr:housenumber":"13b",
    "addr:postcode":"3262 pg",
    "addr:street":"Kerkstr;Oud Beyerland",
    "iso:country":"NL",
    "sg:address":"Kerkstr 13B",
    "sg:city":"Oud Beyerland",
    "sg:classifiers":[
        {
            "category":"Shopping",
            "subcategory":"Adult",
            "type":"Retail Goods"
        }
    ],
    "sg:phone":"+31 186 649 634",
    "sg:postcode":"3262 PG",
    "sg:province":"South Holland",
    "sg:tags":[
        "lingerie",
        "en",
        "tricotage"
    ],
    "wof:name":"Miss Sylly",
    "wof:placetype":"venue"
},
  "geometry": {"coordinates":[4.410383,51.826363],"type":"Point"}
}