{
  "type": "Feature",
  "properties": {
    "addr:full":"Wekeromseweg 41 Ede Gld Gelderland 6718 SC",
    "addr:housenumber":"41",
    "addr:postcode":"6718",
    "addr:street":"Wekeromseweg;Gld Gelderland",
    "iso:country":"NL",
    "sg:address":"Wekeromseweg 41",
    "sg:city":"Ede Gld",
    "sg:orig_category":"Hoefdierhouderijen",
    "sg:phone":"+31 318 616 978",
    "sg:postcode":"6718 SC",
    "sg:province":"Gelderland",
    "wof:name":"De Oscarhoeve",
    "wof:placetype":"venue"
},
  "geometry": {"coordinates":[5.691563,52.073364],"type":"Point"}
}