{
  "type": "Feature",
  "properties": {
    "iso:country":"NL",
    "sg:address":"Grundelstr 1",
    "sg:city":"Raalte",
    "sg:orig_category":"Automaterialen En Gereedschappen",
    "sg:phone":"+31 572 345 959",
    "sg:postcode":"8102 HT",
    "sg:province":"NL.08",
    "wof:name":"Oosterlaar Raalte Bv",
    "wof:placetype":"venue"
},
  "geometry": {"coordinates":[6.29205513,52.3817825317],"type":"Point"}
}