{
  "type": "Feature",
  "properties": {
    "addr:full":"Schaalsmeerdk 2 Oostknollendam Noord-Holland 1534 NA",
    "addr:housenumber":"2",
    "addr:postcode":"1534 na",
    "addr:street":"Schaalsmeerdk",
    "iso:country":"NL",
    "sg:address":"Schaalsmeerdk 2",
    "sg:city":"Oostknollendam",
    "sg:orig_category":"Timmerwerken",
    "sg:phone":"+31 75 642 5969",
    "sg:postcode":"1534 NA",
    "sg:province":"Noord-Holland",
    "wof:name":"Soolingen, Rick Van",
    "wof:placetype":"venue"
},
  "geometry": {"coordinates":[4.796964,52.514042],"type":"Point"}
}