{
  "type": "Feature",
  "properties": {
    "addr:full":"Oude Veerwg 5 Lewedorp Zeeland 4456 NW",
    "addr:housenumber":"5",
    "addr:postcode":"4456 nw",
    "addr:street":"Oude Veerwg",
    "iso:country":"NL",
    "sg:address":"Oude Veerwg 5",
    "sg:city":"Lewedorp",
    "sg:orig_category":"Beeldende Kunstenaars",
    "sg:phone":"+31 113 612 303",
    "sg:postcode":"4456 NW",
    "sg:province":"Zeeland",
    "wof:name":"Nieuwenhuijzen, Nelly Van",
    "wof:placetype":"venue"
},
  "geometry": {"coordinates":[3.725301,51.49511],"type":"Point"}
}