{
  "type": "Feature",
  "properties": {
    "addr:full":"Kobaltstr 26 S Gravenhage Zuid-Holland 2544 EV",
    "addr:housenumber":"26;gravenhage",
    "addr:street":"Kobaltstr;S",
    "iso:country":"NL",
    "sg:address":"Kobaltstr 26",
    "sg:city":"S Gravenhage",
    "sg:classifiers":[
        {
            "category":"Retail",
            "subcategory":"Auto Repair",
            "type":"Services"
        }
    ],
    "sg:phone":"+31 70 321 0523",
    "sg:postcode":"2544 EV",
    "sg:province":"Zuid-Holland",
    "sg:tags":[
        "garage"
    ],
    "wof:name":"Assendelft Bv",
    "wof:placetype":"venue"
},
  "geometry": {"coordinates":[4.25157,52.039551],"type":"Point"}
}