{
  "type": "Feature",
  "properties": {
    "iso:country":"NL",
    "sg:address":"Jan Van Goyenkade 28",
    "sg:city":"Amsterdam",
    "sg:orig_category":"Marktonderzoekbureaus",
    "sg:phone":"+31 20 679 6496",
    "sg:postcode":"1075 HS",
    "sg:province":"North Holland",
    "wof:name":"Sociomart Bv",
    "wof:placetype":"venue"
},
  "geometry": {"coordinates":[4.866455,52.351498],"type":"Point"}
}