{
  "type": "Feature",
  "properties": {
    "addr:full":"Hoofdstr 5 Veenendaal Utrecht 3901 AA",
    "addr:housenumber":"5",
    "addr:postcode":"3901 aa",
    "addr:street":"Hoofdstr",
    "iso:country":"NL",
    "sg:address":"Hoofdstr 5",
    "sg:city":"Veenendaal",
    "sg:orig_category":"Herenkleding",
    "sg:phone":"+31 318 512 037",
    "sg:postcode":"3901 AA",
    "sg:province":"Utrecht",
    "wof:name":"Ravenhorst Bv, Van",
    "wof:placetype":"venue"
},
  "geometry": {"coordinates":[5.554707,52.025944],"type":"Point"}
}