{
  "type": "Feature",
  "properties": {
    "addr:full":"Banneweg 61 Gorinchem Zuid-Holland 4204 AA",
    "addr:housenumber":"61",
    "addr:postcode":"4204 aa",
    "addr:street":"Banneweg",
    "iso:country":"NL",
    "sg:address":"Banneweg 61",
    "sg:city":"Gorinchem",
    "sg:orig_category":"Paramedische Behandelingen",
    "sg:phone":"+31 183 648 003",
    "sg:postcode":"4204 AA",
    "sg:province":"Zuid-Holland",
    "wof:name":"Podotherapeute M.B. Oudijk",
    "wof:placetype":"venue"
},
  "geometry": {"coordinates":[4.95904,51.838982],"type":"Point"}
}