{
  "type": "Feature",
  "properties": {
    "addr:full":"Stad En Landschap 19 Krimpen A/D Ijssel South Holland 2923 BK",
    "addr:housenumber":"19;a / d",
    "addr:postcode":"2923 bk",
    "addr:street":"Stad En Landschap;Ijssel South",
    "iso:country":"NL",
    "sg:address":"Stad En Landschap 19",
    "sg:city":"Krimpen A/D Ijssel",
    "sg:classifiers":[
        {
            "category":"Fast Food",
            "type":"Food & Drink"
        }
    ],
    "sg:phone":"+31 180 518 446",
    "sg:postcode":"2923 BK",
    "sg:province":"South Holland",
    "sg:tags":[
        "afhaal",
        "restaurant"
    ],
    "wof:name":"Chin-Ind Rest New City",
    "wof:placetype":"venue"
},
  "geometry": {"coordinates":[4.601185,51.915405],"type":"Point"}
}