{
  "type": "Feature",
  "properties": {
    "iso:country":"NL",
    "sg:address":"Nijverheidsweg 5",
    "sg:city":"Oudenbosch",
    "sg:classifiers":[
        {
            "category":"Bakery",
            "type":"Food & Drink"
        }
    ],
    "sg:phone":"+31 165 312 550",
    "sg:postcode":"4731 CZ",
    "sg:province":"Noord-Brabant",
    "sg:tags":[
        "brood",
        "banket"
    ],
    "wof:name":"De Rooy Bakkerijen Bv",
    "wof:placetype":"venue"
},
  "geometry": {"coordinates":[4.551736,51.590691],"type":"Point"}
}