{
  "type": "Feature",
  "properties": {
    "iso:country":"NL",
    "sg:address":"Hoogstraat 10",
    "sg:city":"Gouda",
    "sg:orig_category":"Damesmodezaken",
    "sg:phone":"+31 182 520 256",
    "sg:postcode":"2801 HH",
    "sg:province":"South Holland",
    "wof:name":"Modehuis Henri Reedijk Vof",
    "wof:placetype":"venue"
},
  "geometry": {"coordinates":[4.710065,52.012432],"type":"Point"}
}