{
  "type": "Feature",
  "properties": {
    "addr:full":"Esdoornstr 17 Driebruggen South Holland 3465 JL",
    "addr:housenumber":"17",
    "addr:postcode":"3465 jl",
    "addr:street":"Esdoornstr",
    "iso:country":"NL",
    "sg:address":"Esdoornstr 17",
    "sg:city":"Driebruggen",
    "sg:orig_category":"Drukkerijen",
    "sg:phone":"+31 348 501 844",
    "sg:postcode":"3465 JL",
    "sg:province":"South Holland",
    "wof:name":"M & R Bv",
    "wof:placetype":"venue"
},
  "geometry": {"coordinates":[4.800187,52.042049],"type":"Point"}
}