{
  "type": "Feature",
  "properties": {
    "addr:full":"Herendijk 11 Beek En Donk North Brabant 5741 RA",
    "addr:housenumber":"11",
    "addr:postcode":"5741 ra",
    "addr:street":"Herendijk",
    "iso:country":"NL",
    "sg:address":"Herendijk 11",
    "sg:city":"Beek En Donk",
    "sg:orig_category":"Diverse Dierenfokkers",
    "sg:phone":"+31 492 463 363",
    "sg:postcode":"5741 RA",
    "sg:province":"North Brabant",
    "wof:name":"Nertsenfarm Van Den Broek Bv",
    "wof:placetype":"venue"
},
  "geometry": {"coordinates":[5.61164,51.53738],"type":"Point"}
}