{
  "type": "Feature",
  "properties": {
    "addr:full":"Krayenhoffln 10 Nymegen Gelderland 6541 BG",
    "addr:housenumber":"10",
    "addr:postcode":"6541",
    "addr:street":"Krayenhoffln;Gelderland",
    "iso:country":"NL",
    "sg:address":"Krayenhoffln 10",
    "sg:city":"Nymegen",
    "sg:orig_category":"Zonweringen",
    "sg:phone":"+31 24 372 6262",
    "sg:postcode":"6541 BG",
    "sg:province":"Gelderland",
    "wof:name":"Hansa Bv",
    "wof:placetype":"venue"
},
  "geometry": {"coordinates":[26.304199,41.93145],"type":"Point"}
}