{
  "type": "Feature",
  "properties": {
    "addr:full":"Dorpsstr 95 Zoetermeer Zuid-Holland 2712 AE",
    "addr:housenumber":"95",
    "addr:postcode":"2712 ae",
    "addr:street":"Dorpsstr",
    "iso:country":"NL",
    "sg:address":"Dorpsstr 95",
    "sg:city":"Zoetermeer",
    "sg:orig_category":"Juweliers",
    "sg:phone":"+31 79 316 9411",
    "sg:postcode":"2712 AE",
    "sg:province":"Zuid-Holland",
    "wof:name":"Es, Van",
    "wof:placetype":"venue"
},
  "geometry": {"coordinates":[4.497486,52.055908],"type":"Point"}
}