{
  "type": "Feature",
  "properties": {
    "addr:full":"Burgemeester Van Kuikstr 4 Mierlo North Brabant 5731 WB",
    "addr:housenumber":"4",
    "addr:postcode":"5731 wb",
    "addr:street":"Burgemeester Van Kuikstr",
    "iso:country":"NL",
    "sg:address":"Burgemeester Van Kuikstr 4",
    "sg:city":"Mierlo",
    "sg:orig_category":"Kappers",
    "sg:phone":"+31 492 662 745",
    "sg:postcode":"5731 WB",
    "sg:province":"North Brabant",
    "wof:name":"Vogels Coiffures",
    "wof:placetype":"venue"
},
  "geometry": {"coordinates":[5.622104,51.438221],"type":"Point"}
}