{
  "type": "Feature",
  "properties": {
    "addr:full":"Dreef 10 Breda North Brabant 4813 EG",
    "addr:housenumber":"10",
    "addr:postcode":"4813 eg",
    "addr:street":"Dreef",
    "iso:country":"NL",
    "sg:address":"Dreef 10",
    "sg:city":"Breda",
    "sg:orig_category":"Paramedische Behandelingen",
    "sg:phone":"+31 76 520 0265",
    "sg:postcode":"4813 EG",
    "sg:province":"North Brabant",
    "wof:name":"N.T.N. Thuiszorg Regiobureau Breda Eo",
    "wof:placetype":"venue"
},
  "geometry": {"coordinates":[4.740089,51.576714],"type":"Point"}
}