{
  "type": "Feature",
  "properties": {
    "addr:full":"A Bynsring 201 Apeldoorn Gelderland 7321 HG",
    "addr:housenumber":"201",
    "addr:postcode":"7321 hg",
    "addr:street":"Gelderland",
    "iso:country":"NL",
    "sg:address":"A Bynsring 201",
    "sg:city":"Apeldoorn",
    "sg:orig_category":"Scholen Voor Basisonderwijs",
    "sg:phone":"+31 55 366 1644",
    "sg:postcode":"7321 HG",
    "sg:province":"Gelderland",
    "sg:website":"http://home.wxs.nl/~bunde005/",
    "wof:name":"Bundel Openb, De",
    "wof:placetype":"venue"
},
  "geometry": {"coordinates":[5.99548,52.215286],"type":"Point"}
}