{
  "type": "Feature",
  "properties": {
    "iso:country":"NL",
    "sg:address":"Brielsedreef 23",
    "sg:city":"Prinsenbeek",
    "sg:orig_category":"Parketvloeren",
    "sg:phone":"+31 76 581 1724",
    "sg:postcode":"4841 KR",
    "sg:province":"Noord-Brabant",
    "wof:name":"Bliek Hout",
    "wof:placetype":"venue"
},
  "geometry": {"coordinates":[4.706378,51.604771],"type":"Point"}
}