{
  "type": "Feature",
  "properties": {
    "iso:country":"NL",
    "sg:address":"Looweg 18",
    "sg:city":"Bathmen",
    "sg:orig_category":"Kappers",
    "sg:phone":"+31 570 542 138",
    "sg:postcode":"7437 RR",
    "sg:province":"Overijssel",
    "wof:name":"Will'S Kapsalon",
    "wof:placetype":"venue"
},
  "geometry": {"coordinates":[6.290647,52.251205],"type":"Point"}
}