{
  "type": "Feature",
  "properties": {
    "addr:full":"Helmstraat 3 Maastricht Limburg 6211 TA",
    "addr:housenumber":"3",
    "addr:postcode":"6211 ta",
    "addr:street":"Helmstraat",
    "iso:country":"NL",
    "sg:address":"Helmstraat 3",
    "sg:city":"Maastricht",
    "sg:orig_category":"Discountwinkels",
    "sg:phone":"+31 43 350 0310",
    "sg:postcode":"6211 TA",
    "sg:province":"Limburg",
    "wof:name":"Zeeman Textielsupers",
    "wof:placetype":"venue"
},
  "geometry": {"coordinates":[5.68933,50.850376],"type":"Point"}
}