{
  "type": "Feature",
  "properties": {
    "addr:full":"Slochterenwg 2 Arnhem Gelderland 6835 CB",
    "addr:housenumber":"2",
    "addr:postcode":"6835 cb",
    "addr:street":"Slochterenwg",
    "iso:country":"NL",
    "sg:address":"Slochterenwg 2",
    "sg:city":"Arnhem",
    "sg:orig_category":"Ziekenhuizen, Sanatoria, Verpleeghuizen",
    "sg:phone":"+31 26 320 9200",
    "sg:postcode":"6835 CB",
    "sg:province":"Gelderland",
    "sg:website":"http://www.alysis.nl",
    "wof:name":"Martinushof",
    "wof:placetype":"venue"
},
  "geometry": {"coordinates":[5.900465,51.956825],"type":"Point"}
}