{
  "type": "Feature",
  "properties": {
    "addr:full":"Terborgseweg 31 A Doetinchem Gelderland 7001 GM",
    "addr:housenumber":"31 a",
    "addr:postcode":"7001 gm",
    "addr:street":"Terborgseweg;Gelderland",
    "iso:country":"NL",
    "sg:address":"Terborgseweg 31 A",
    "sg:city":"Doetinchem",
    "sg:classifiers":[
        {
            "category":"Fast Food",
            "type":"Food & Drink"
        }
    ],
    "sg:phone":"+31 314 334 267",
    "sg:postcode":"7001 GM",
    "sg:province":"Gelderland",
    "sg:tags":[
        "afhaal",
        "restaurant"
    ],
    "wof:name":"Naturo Vloeren Doetinchem",
    "wof:placetype":"venue"
},
  "geometry": {"coordinates":[6.29423,51.960747],"type":"Point"}
}