{
  "type": "Feature",
  "properties": {
    "addr:full":"Urkersingel 8 A Rotterdam South Holland 3083 SV",
    "addr:housenumber":"8 a",
    "addr:postcode":"3083 sv",
    "addr:street":"Urkersingel",
    "iso:country":"NL",
    "sg:address":"Urkersingel 8 A",
    "sg:city":"Rotterdam",
    "sg:orig_category":"Elektronische Bedrijfsinstallaties",
    "sg:phone":"+31 10 480 8745",
    "sg:postcode":"3083 SV",
    "sg:province":"South Holland",
    "wof:name":"Fai Home Security",
    "wof:placetype":"venue"
},
  "geometry": {"coordinates":[4.483658,51.886932],"type":"Point"}
}