{
  "type": "Feature",
  "properties": {
    "iso:country":"NL",
    "sg:address":"Kempweg 15",
    "sg:city":"Horst",
    "sg:orig_category":"Fruitteelt",
    "sg:phone":"+31 77 398 2430",
    "sg:postcode":"5964 ND",
    "sg:province":"North Dakota",
    "wof:name":"Plantenkwekerij De Kemp Bv",
    "wof:placetype":"venue"
},
  "geometry": {"coordinates":[-100.30171199999999,47.467731],"type":"Point"}
}