{
  "type": "Feature",
  "properties": {
    "addr:full":"Vaartweg 58G Lelystad Flevoland 8243 PP",
    "addr:housenumber":"58g",
    "addr:postcode":"8243 pp",
    "addr:street":"Vaartweg;Flevoland",
    "iso:country":"NL",
    "sg:address":"Vaartweg 58G",
    "sg:city":"Lelystad",
    "sg:orig_category":"Bloemen En Planten - Groothandel",
    "sg:phone":"+31 320 212 000",
    "sg:postcode":"8243 PP",
    "sg:province":"Flevoland",
    "wof:name":"Lops Bv, Leo",
    "wof:placetype":"venue"
},
  "geometry": {"coordinates":[5.439447,52.501019],"type":"Point"}
}