{
  "type": "Feature",
  "properties": {
    "addr:full":"Oude Steiger 3 Nes Ameland Provincie Friesland 9163 GV",
    "addr:housenumber":"3",
    "addr:postcode":"9163 gv",
    "addr:street":"Oude Steiger;Friesland",
    "iso:country":"NL",
    "sg:address":"Oude Steiger 3",
    "sg:city":"Nes Ameland",
    "sg:orig_category":"Jachthavens - Jachtwerven",
    "sg:phone":"+31 519 542 159",
    "sg:postcode":"9163 GV",
    "sg:province":"Provincie Friesland",
    "wof:name":"Leije Gat Ameland, Sticht 'T",
    "wof:placetype":"venue"
},
  "geometry": {"coordinates":[5.775919,53.437656],"type":"Point"}
}