{
  "type": "Feature",
  "properties": {
    "addr:full":"Felland 7 Haren Gn Groningen 9753 TA",
    "addr:housenumber":"7",
    "addr:postcode":"9753 ta",
    "addr:street":"Felland",
    "iso:country":"NL",
    "sg:address":"Felland 7",
    "sg:city":"Haren Gn",
    "sg:orig_category":"Autokeuringen",
    "sg:phone":"+31 50 534 0612",
    "sg:postcode":"9753 TA",
    "sg:province":"Groningen",
    "wof:name":"Hvh Autotechniek",
    "wof:placetype":"venue"
},
  "geometry": {"coordinates":[6.625052,53.164783],"type":"Point"}
}