{
  "type": "Feature",
  "properties": {
    "addr:full":"Majoorswg 6 Amerongen Utrecht 3958 GW",
    "addr:housenumber":"6",
    "addr:postcode":"3958 gw",
    "addr:street":"Majoorswg",
    "iso:country":"NL",
    "sg:address":"Majoorswg 6",
    "sg:city":"Amerongen",
    "sg:orig_category":"Verenigingen En Stichtingen",
    "sg:phone":"+31 343 461 200",
    "sg:postcode":"3958 GW",
    "sg:province":"Utrecht",
    "wof:name":"Ons Genoegen",
    "wof:placetype":"venue"
},
  "geometry": {"coordinates":[5.457312,52.005302],"type":"Point"}
}