{
  "type": "Feature",
  "properties": {
    "addr:full":"Misterstraat 78 Winterswijk Gelderland 7101 EZ",
    "addr:housenumber":"78",
    "addr:postcode":"7101 ez",
    "addr:street":"Misterstraat;Gelderland",
    "iso:country":"NL",
    "sg:address":"Misterstraat 78",
    "sg:city":"Winterswijk",
    "sg:orig_category":"Werving And Selectie Van Tijdelijk Personeel And Uitzendkantoren",
    "sg:phone":"+31 543 517 575",
    "sg:postcode":"7101 EZ",
    "sg:province":"Gelderland",
    "wof:name":"Vedior",
    "wof:placetype":"venue"
},
  "geometry": {"coordinates":[6.7154359818,51.9704704285],"type":"Point"}
}