{
  "type": "Feature",
  "properties": {
    "iso:country":"NL",
    "sg:address":"Maasdijk 78",
    "sg:city":"Rossum Gld",
    "sg:orig_category":"Reclamebureaus",
    "sg:phone":"+31 418 540 015",
    "sg:postcode":"5328 BH",
    "sg:province":"Gelderland",
    "wof:name":"Vincent Wibier, Art & Copy",
    "wof:placetype":"venue"
},
  "geometry": {"coordinates":[5.338216,51.799721],"type":"Point"}
}