{
  "type": "Feature",
  "properties": {
    "addr:full":"Berkenwg 14 Amersfoort Utrecht 3818 LB",
    "addr:housenumber":"14",
    "addr:postcode":"3818 lb",
    "addr:street":"Berkenwg",
    "iso:country":"NL",
    "sg:address":"Berkenwg 14",
    "sg:city":"Amersfoort",
    "sg:orig_category":"Adviesbureaus Bedrijfsorganisatie",
    "sg:phone":"+31 33 258 1639",
    "sg:postcode":"3818 LB",
    "sg:province":"Utrecht",
    "sg:website":"http://www.berkenbosch.com",
    "wof:name":"Berkenbosch, Bas",
    "wof:placetype":"venue"
},
  "geometry": {"coordinates":[5.379028,52.150906],"type":"Point"}
}