{
  "type": "Feature",
  "properties": {
    "addr:full":"Valkhof 115 Leidschendam Zuid-Holland 2261 HW",
    "addr:housenumber":"115",
    "addr:postcode":"2261 hw",
    "addr:street":"Valkhof",
    "iso:country":"NL",
    "sg:address":"Valkhof 115",
    "sg:city":"Leidschendam",
    "sg:orig_category":"Adviesbureaus Elektronica",
    "sg:phone":"+31 70 327 1159",
    "sg:postcode":"2261 HW",
    "sg:province":"Zuid-Holland",
    "wof:name":"Fartree Advise",
    "wof:placetype":"venue"
},
  "geometry": {"coordinates":[4.397672,52.100449],"type":"Point"}
}