{
  "type": "Feature",
  "properties": {
    "iso:country":"NL",
    "sg:address":"Hertenrade 460",
    "sg:city":"'S Gravenhage",
    "sg:orig_category":"Kappers",
    "sg:phone":"+31 70 367 3862",
    "sg:postcode":"2544 HT",
    "sg:province":"Zuid-Holland",
    "wof:name":"Kapsalon Double Masque",
    "wof:placetype":"venue"
},
  "geometry": {"coordinates":[4.2631878853,52.046207428],"type":"Point"}
}