{
  "type": "Feature",
  "properties": {
    "iso:country":"NL",
    "sg:address":"Spinozawg 407",
    "sg:city":"Rotterdam",
    "sg:orig_category":"Postkantoren",
    "sg:phone":"+31 10 419 4522",
    "sg:postcode":"3076 ET",
    "sg:province":"South Holland",
    "sg:website":"http://www.postkantoor.nl",
    "wof:name":"Postkantoor",
    "wof:placetype":"venue"
},
  "geometry": {"coordinates":[4.517456,51.877148],"type":"Point"}
}