{
  "type": "Feature",
  "properties": {
    "addr:full":"Rykswg 50 Limmen Noord-Holland 1906 BJ",
    "addr:housenumber":"50",
    "addr:postcode":"1906 bj",
    "addr:street":"Rykswg",
    "iso:country":"NL",
    "sg:address":"Rykswg 50",
    "sg:city":"Limmen",
    "sg:classifiers":[
        {
            "category":"Retail",
            "subcategory":"Auto Repair",
            "type":"Services"
        }
    ],
    "sg:phone":"+31 72 505 3066",
    "sg:postcode":"1906 BJ",
    "sg:province":"Noord-Holland",
    "sg:tags":[
        "garage"
    ],
    "wof:name":"Kaandorp, G",
    "wof:placetype":"venue"
},
  "geometry": {"coordinates":[4.690966,52.566494],"type":"Point"}
}