{
  "type": "Feature",
  "properties": {
    "addr:full":"Noordstr 72 Terneuzen Zeeland 4531 GJ",
    "addr:housenumber":"72",
    "addr:postcode":"4531 gj",
    "addr:street":"Noordstr",
    "iso:country":"NL",
    "sg:address":"Noordstr 72",
    "sg:city":"Terneuzen",
    "sg:orig_category":"Sportschoenen - Winkels",
    "sg:phone":"+31 115 648 366",
    "sg:postcode":"4531 GJ",
    "sg:province":"Zeeland",
    "wof:name":"Aktiesport",
    "wof:placetype":"venue"
},
  "geometry": {"coordinates":[3.826646,51.337368],"type":"Point"}
}