{
  "type": "Feature",
  "properties": {
    "addr:full":"Sterkenburg 67 Oosterhout Nb Noord-Brabant 4901 WC",
    "addr:housenumber":"67",
    "addr:postcode":"4901 wc",
    "addr:street":"Sterkenburg",
    "iso:country":"NL",
    "sg:address":"Sterkenburg 67",
    "sg:city":"Oosterhout Nb",
    "sg:orig_category":"Projectinrichting",
    "sg:phone":"+31 162 453 892",
    "sg:postcode":"4901 WC",
    "sg:province":"Noord-Brabant",
    "wof:name":"Brokx Bv, Hans",
    "wof:placetype":"venue"
},
  "geometry": {"coordinates":[4.867063,51.650848],"type":"Point"}
}