{
  "type": "Feature",
  "properties": {
    "addr:full":"Zevenpelsen 25 Ijlst Friesland 8651 BT",
    "addr:housenumber":"25",
    "addr:postcode":"8651 bt",
    "addr:street":"Zevenpelsen",
    "iso:country":"NL",
    "sg:address":"Zevenpelsen 25",
    "sg:city":"Ijlst",
    "sg:orig_category":"Pleziervaartuigen And Reparatie",
    "sg:phone":"+31 515 531 253",
    "sg:postcode":"8651 BT",
    "sg:province":"Friesland",
    "wof:name":"Technisch Bedrijf Bakker Ijlst",
    "wof:placetype":"venue"
},
  "geometry": {"coordinates":[5.618603,53.010513],"type":"Point"}
}