{
  "type": "Feature",
  "properties": {
    "iso:country":"NL",
    "sg:address":"De Els 13",
    "sg:city":"Beek En Donk",
    "sg:orig_category":"Autorijscholen",
    "sg:phone":"+31 492 468 985",
    "sg:postcode":"5741 DN",
    "sg:province":"North Brabant",
    "wof:name":"Laarbeek",
    "wof:placetype":"venue"
},
  "geometry": {"coordinates":[5.621071,51.541084],"type":"Point"}
}