{
  "type": "Feature",
  "properties": {
    "addr:full":"Clinckenburgh 13 Oegstgeest South Holland 2343 JG",
    "addr:housenumber":"13",
    "addr:postcode":"2343 jg",
    "addr:street":"Clinckenburgh",
    "iso:country":"NL",
    "sg:address":"Clinckenburgh 13",
    "sg:city":"Oegstgeest",
    "sg:classifiers":[
        {
            "category":"Professional",
            "subcategory":"Accounting & Tax Preparation",
            "type":"Services"
        }
    ],
    "sg:phone":"+31 71 301 2921",
    "sg:postcode":"2343 JG",
    "sg:province":"South Holland",
    "sg:tags":[
        "accountant"
    ],
    "wof:name":"W.J. Laman Accountancy Bv",
    "wof:placetype":"venue"
},
  "geometry": {"coordinates":[4.488279,52.192459],"type":"Point"}
}