{
  "type": "Feature",
  "properties": {
    "addr:full":"Calagneweg 3 Ovezande Zeeland 4441 SM",
    "addr:housenumber":"3",
    "addr:postcode":"4441 sm",
    "addr:street":"Calagneweg",
    "iso:country":"NL",
    "sg:address":"Calagneweg 3",
    "sg:city":"Ovezande",
    "sg:orig_category":"Schilderwerk",
    "sg:phone":"+31 113 655 901",
    "sg:postcode":"4441 SM",
    "sg:province":"Zeeland",
    "wof:name":"C Van Sprang Schildersbedrijf",
    "wof:placetype":"venue"
},
  "geometry": {"coordinates":[3.813484,51.434795],"type":"Point"}
}