{
  "type": "Feature",
  "properties": {
    "addr:full":"Overheicop 31 Leerdam Zuid-Holland 4143 KW",
    "addr:housenumber":"31",
    "addr:postcode":"4143 kw",
    "addr:street":"Overheicop",
    "iso:country":"NL",
    "sg:address":"Overheicop 31",
    "sg:city":"Leerdam",
    "sg:orig_category":"Werving En Selectie",
    "sg:phone":"+31 345 514 451",
    "sg:postcode":"4143 KW",
    "sg:province":"Zuid-Holland",
    "wof:name":"Q-Search",
    "wof:placetype":"venue"
},
  "geometry": {"coordinates":[5.109577179,51.9210662842],"type":"Point"}
}