{
  "type": "Feature",
  "properties": {
    "addr:full":"De Star 15 Leidschendam Zuid-Holland 2266 NA",
    "addr:housenumber":"15",
    "addr:postcode":"2266 na",
    "addr:street":"De Star",
    "iso:country":"NL",
    "sg:address":"De Star 15",
    "sg:city":"Leidschendam",
    "sg:orig_category":"Autoschade- Herstelbedrijven",
    "sg:phone":"+31 70 320 4044",
    "sg:postcode":"2266 NA",
    "sg:province":"Zuid-Holland",
    "wof:name":"Beukers Bv",
    "wof:placetype":"venue"
},
  "geometry": {"coordinates":[4.406684,52.084038],"type":"Point"}
}