{
  "type": "Feature",
  "properties": {
    "iso:country":"NL",
    "sg:address":"Peppelhorst 110",
    "sg:city":"Waddinxveen",
    "sg:orig_category":"Beeldende Kunstenaars",
    "sg:phone":"+31 182 615 551",
    "sg:postcode":"2742 DA",
    "sg:province":"Zuid-Holland",
    "wof:name":"Mensink, A",
    "wof:placetype":"venue"
},
  "geometry": {"coordinates":[4.64742,52.05209],"type":"Point"}
}