{
  "type": "Feature",
  "properties": {
    "addr:full":"Voorhaakdk 8 Woerdense Verlaat Zuid-Holland 3651 MB",
    "addr:housenumber":"8",
    "addr:postcode":"verlaat;3651 mb",
    "addr:street":"Voorhaakdk",
    "iso:country":"NL",
    "sg:address":"Voorhaakdk 8",
    "sg:city":"Woerdense Verlaat",
    "sg:orig_category":"Heiwerken En Funderingstechniek",
    "sg:phone":"+31 172 408 332",
    "sg:postcode":"3651 MB",
    "sg:province":"Zuid-Holland",
    "wof:name":"Voorend, G B",
    "wof:placetype":"venue"
},
  "geometry": {"coordinates":[4.861585,52.147682],"type":"Point"}
}