{
  "type": "Feature",
  "properties": {
    "addr:full":"Zwembadwg 15 Geldrop North Brabant 5663 PL",
    "addr:housenumber":"15",
    "addr:postcode":"5663 pl",
    "addr:street":"Zwembadwg",
    "iso:country":"NL",
    "sg:address":"Zwembadwg 15",
    "sg:city":"Geldrop",
    "sg:orig_category":"Cafetaria'S",
    "sg:phone":"+31 40 286 8046",
    "sg:postcode":"5663 PL",
    "sg:province":"North Brabant",
    "sg:website":"http://www.cocody.nl",
    "wof:name":"Cocody Geldrop",
    "wof:placetype":"venue"
},
  "geometry": {"coordinates":[5.55169,51.408905],"type":"Point"}
}