{
  "type": "Feature",
  "properties": {
    "addr:full":"Ankerplaats 18 Amsterdam Noord-Holland 1034 KC",
    "addr:housenumber":"18",
    "addr:postcode":"1034 kc",
    "addr:street":"Ankerplaats",
    "iso:country":"NL",
    "sg:address":"Ankerplaats 18",
    "sg:city":"Amsterdam",
    "sg:orig_category":"Bibliotheken And Openbare Archieven",
    "sg:phone":"+31 20 631 4132",
    "sg:postcode":"1034 KC",
    "sg:province":"Noord-Holland",
    "wof:name":"Openbare Bibliotheek En Leeszaal",
    "wof:placetype":"venue"
},
  "geometry": {"coordinates":[4.916767,52.406349],"type":"Point"}
}