{
  "type": "Feature",
  "properties": {
    "addr:full":"Industrieweg 9 Heerjansdam Zuid-Holland 2995 BE",
    "addr:housenumber":"9",
    "addr:postcode":"2995",
    "addr:street":"Industrieweg",
    "iso:country":"NL",
    "sg:address":"Industrieweg 9",
    "sg:city":"Heerjansdam",
    "sg:classifiers":[
        {
            "category":"Parking",
            "subcategory":"Lot",
            "type":"Transportation"
        }
    ],
    "sg:phone":"+31 78 677 1166",
    "sg:postcode":"2995 BE",
    "sg:province":"Zuid-Holland",
    "sg:tags":[
        "fab",
        "metalen",
        "tank"
    ],
    "wof:name":"Leemberg Pijpleidingen En Apparatenbouw Bv",
    "wof:placetype":"venue"
},
  "geometry": {"coordinates":[4.558929,51.834145],"type":"Point"}
}