{
  "type": "Feature",
  "properties": {
    "iso:country":"NL",
    "sg:address":"Dorpsstr 127-131",
    "sg:city":"Wervershoof",
    "sg:orig_category":"Woninginrichting",
    "sg:phone":"+31 228 581 294",
    "sg:postcode":"1693 AD",
    "sg:province":"Noord-Holland",
    "wof:name":"Bot",
    "wof:placetype":"venue"
},
  "geometry": {"coordinates":[5.1635408401,52.7305603027],"type":"Point"}
}