{
  "type": "Feature",
  "properties": {
    "iso:country":"NL",
    "sg:address":"Drift 2",
    "sg:city":"Doorn",
    "sg:orig_category":"Verhuur Audiovisuele Apparatuur",
    "sg:phone":"+31 343 420 040",
    "sg:postcode":"3941 DC",
    "sg:province":"Utrecht",
    "wof:name":"Key Systems",
    "wof:placetype":"venue"
},
  "geometry": {"coordinates":[5.338319,52.039692],"type":"Point"}
}