{
  "type": "Feature",
  "properties": {
    "addr:full":"Herman Colleniusstraat 13 Groningen Groningen 9718 KP",
    "addr:housenumber":"13",
    "addr:postcode":"9718 kp",
    "addr:street":"Herman Colleniusstraat",
    "iso:country":"NL",
    "sg:address":"Herman Colleniusstraat 13",
    "sg:city":"Groningen",
    "sg:orig_category":"Zalenexploitatie",
    "sg:phone":"+31 50 313 7643",
    "sg:postcode":"9718 KP",
    "sg:province":"Groningen",
    "wof:name":"Artrias",
    "wof:placetype":"venue"
},
  "geometry": {"coordinates":[6.55031,53.217422],"type":"Point"}
}