{
  "type": "Feature",
  "properties": {
    "addr:full":"F Mullerstr 301 Hoofddorp Noord-Holland 2135 ML",
    "addr:housenumber":"301",
    "addr:postcode":"2135 ml",
    "iso:country":"NL",
    "sg:address":"F Mullerstr 301",
    "sg:city":"Hoofddorp",
    "sg:orig_category":"Administratie- En Boekhoudkantoren",
    "sg:phone":"+31 23 562 8932",
    "sg:postcode":"2135 ML",
    "sg:province":"Noord-Holland",
    "wof:name":"Goedings",
    "wof:placetype":"venue"
},
  "geometry": {"coordinates":[4.668529,52.295345],"type":"Point"}
}