{
  "type": "Feature",
  "properties": {
    "addr:full":"Vetkamp 6 Nijkerk Gld Gelderland 3861 JP",
    "addr:housenumber":"6",
    "addr:postcode":"3861 jp",
    "addr:street":"Vetkamp;Gld Gelderland",
    "iso:country":"NL",
    "sg:address":"Vetkamp 6",
    "sg:city":"Nijkerk Gld",
    "sg:classifiers":[
        {
            "category":"Fast Food",
            "type":"Food & Drink"
        }
    ],
    "sg:phone":"+31 33 245 4387",
    "sg:postcode":"3861 JP",
    "sg:province":"Gelderland",
    "sg:tags":[
        "afhaal",
        "restaurant"
    ],
    "wof:name":"Snack Resto O Retto",
    "wof:placetype":"venue"
},
  "geometry": {"coordinates":[5.48956,52.224529],"type":"Point"}
}