{
  "type": "Feature",
  "properties": {
    "addr:full":"Omdraai 7 Wieringerwerf Noord-Holland 1771 HH",
    "addr:housenumber":"7",
    "addr:postcode":"1771 hh",
    "addr:street":"Omdraai",
    "iso:country":"NL",
    "sg:address":"Omdraai 7",
    "sg:city":"Wieringerwerf",
    "sg:orig_category":"Schilders",
    "sg:phone":"+31 227 601 459",
    "sg:postcode":"1771 HH",
    "sg:province":"Noord-Holland",
    "wof:name":"Boltjes",
    "wof:placetype":"venue"
},
  "geometry": {"coordinates":[5.036985,52.855309],"type":"Point"}
}