{
  "type": "Feature",
  "properties": {
    "addr:full":"Oostsingel 39 Venray Limburg 5802 AM",
    "addr:housenumber":"39",
    "addr:postcode":"5802",
    "addr:street":"Oostsingel",
    "iso:country":"NL",
    "sg:address":"Oostsingel 39",
    "sg:city":"Venray",
    "sg:classifiers":[
        {
            "category":"Education",
            "subcategory":"Preschool",
            "type":"Public Place"
        }
    ],
    "sg:phone":"+31 478 550 222",
    "sg:postcode":"5802 AM",
    "sg:province":"Limburg",
    "sg:tags":[
        "kleuteronderwijs",
        "basis-"
    ],
    "wof:name":"De Hommel",
    "wof:placetype":"venue"
},
  "geometry": {"coordinates":[5.986209,51.522945],"type":"Point"}
}