{
  "type": "Feature",
  "properties": {
    "addr:full":"Thorbeckestr 152 Wageningen Gelderland 6702 BW",
    "addr:housenumber":"152",
    "addr:postcode":"6702 bw",
    "addr:street":"Gelderland",
    "iso:country":"NL",
    "sg:address":"Thorbeckestr 152",
    "sg:city":"Wageningen",
    "sg:orig_category":"Voegwerken",
    "sg:phone":"+31 317 421 981",
    "sg:postcode":"6702 BW",
    "sg:province":"Gelderland",
    "wof:name":"Steenhuis",
    "wof:placetype":"venue"
},
  "geometry": {"coordinates":[5.653055,51.966099],"type":"Point"}
}