{
  "type": "Feature",
  "properties": {
    "iso:country":"NL",
    "sg:address":"Stationswg 13",
    "sg:city":"Winsum Gn",
    "sg:orig_category":"Banken",
    "sg:phone":"+31 595 490 101",
    "sg:postcode":"9951 BA",
    "sg:province":"Groningen",
    "wof:name":"Rabobank",
    "wof:placetype":"venue"
},
  "geometry": {"coordinates":[6.517395,53.334412],"type":"Point"}
}