{
  "type": "Feature",
  "properties": {
    "addr:full":"Rotterdamseweg 51 Delft Zuid-Holland 2628 AJ",
    "addr:housenumber":"51",
    "addr:postcode":"2628 aj",
    "addr:street":"Rotterdamseweg",
    "iso:country":"NL",
    "sg:address":"Rotterdamseweg 51",
    "sg:city":"Delft",
    "sg:classifiers":[
        {
            "category":"Education",
            "subcategory":"Preschool",
            "type":"Public Place"
        }
    ],
    "sg:phone":"+31 15 257 5556",
    "sg:postcode":"2628 AJ",
    "sg:province":"Zuid-Holland",
    "sg:tags":[
        "kleuteronderwijs",
        "basis-"
    ],
    "wof:name":"Hummelhof",
    "wof:placetype":"venue"
},
  "geometry": {"coordinates":[4.363821,52.005028],"type":"Point"}
}