{
  "type": "Feature",
  "properties": {
    "addr:full":"Hoofdstr 56 Stadskanaal Groningen 9501 CN",
    "addr:housenumber":"56",
    "addr:postcode":"9501 cn",
    "addr:street":"Hoofdstr",
    "iso:country":"NL",
    "sg:address":"Hoofdstr 56",
    "sg:city":"Stadskanaal",
    "sg:orig_category":"Kappers",
    "sg:phone":"+31 599 650 515",
    "sg:postcode":"9501 CN",
    "sg:province":"Groningen",
    "wof:name":"Experience",
    "wof:placetype":"venue"
},
  "geometry": {"coordinates":[6.9538788795,52.9864807129],"type":"Point"}
}