{
  "type": "Feature",
  "properties": {
    "iso:country":"NL",
    "sg:address":"Hoofdstr 56",
    "sg:city":"Stadskanaal",
    "sg:orig_category":"Kappers",
    "sg:phone":"+31 599 650 515",
    "sg:postcode":"9501 CN",
    "sg:province":"Groningen",
    "wof:name":"Experience",
    "wof:placetype":"venue"
},
  "geometry": {"coordinates":[6.9538788795,52.9864807129],"type":"Point"}
}