{
  "type": "Feature",
  "properties": {
    "addr:full":"Park 13 Nuenen Noord-Brabant 5671 GB",
    "addr:housenumber":"13",
    "addr:postcode":"5671 gb",
    "addr:street":"Park",
    "iso:country":"NL",
    "sg:address":"Park 13",
    "sg:city":"Nuenen",
    "sg:orig_category":"Kappers",
    "sg:phone":"+31 40 283 8348",
    "sg:postcode":"5671 GB",
    "sg:province":"Noord-Brabant",
    "wof:name":"Werner",
    "wof:placetype":"venue"
},
  "geometry": {"coordinates":[5.548421,51.474438],"type":"Point"}
}