{
  "type": "Feature",
  "properties": {
    "iso:country":"NL",
    "sg:address":"Hertshooi 25",
    "sg:city":"Mierlo",
    "sg:orig_category":"Adviesbureaus Marketing",
    "sg:phone":"+31 492 664 514",
    "sg:postcode":"5731 TK",
    "sg:province":"Noord-Brabant",
    "wof:name":"Mierlo Advies Bv",
    "wof:placetype":"venue"
},
  "geometry": {"coordinates":[5.625039,51.440964],"type":"Point"}
}