{
  "type": "Feature",
  "properties": {
    "iso:country":"NL",
    "sg:address":"Orthenstraat 42",
    "sg:city":"'S Hertogenbosch",
    "sg:orig_category":"Werving And Selectie Van Tijdelijk Personeel And Uitzendkantoren",
    "sg:phone":"+31 73 614 8228",
    "sg:postcode":"5211 SX",
    "sg:province":"North Brabant",
    "wof:name":"Start",
    "wof:placetype":"venue"
},
  "geometry": {"coordinates":[5.3009791374,51.6912231445],"type":"Point"}
}