{
  "type": "Feature",
  "properties": {
    "addr:full":"Middenmolenplein 34 Gouda South Holland 2807 GZ",
    "addr:housenumber":"34",
    "addr:postcode":"2807 gz",
    "addr:street":"Middenmolenplein",
    "iso:country":"NL",
    "sg:address":"Middenmolenplein 34",
    "sg:city":"Gouda",
    "sg:orig_category":"Bloemen And Planten",
    "sg:phone":"+31 182 585 070",
    "sg:postcode":"2807 GZ",
    "sg:province":"South Holland",
    "wof:name":"Wim Jansen Bv",
    "wof:placetype":"venue"
},
  "geometry": {"coordinates":[4.74225,52.011425],"type":"Point"}
}