{
  "type": "Feature",
  "properties": {
    "addr:full":"Nw Binnenwg 20H Rotterdam Zuid-Holland 3015 BA",
    "addr:postcode":"3015 ba",
    "iso:country":"NL",
    "sg:address":"Nw Binnenwg 20H",
    "sg:city":"Rotterdam",
    "sg:orig_category":"Opticiens",
    "sg:phone":"+31 10 436 4475",
    "sg:postcode":"3015 BA",
    "sg:province":"Zuid-Holland",
    "wof:name":"Kievit, De",
    "wof:placetype":"venue"
},
  "geometry": {"coordinates":[4.471367836,51.9165382385],"type":"Point"}
}