{
  "type": "Feature",
  "properties": {
    "iso:country":"NL",
    "sg:address":"Deken Van Baarsstraat 42",
    "sg:city":"Budel",
    "sg:orig_category":"Schoonheidssalons",
    "sg:phone":"+31 495 492 898",
    "sg:postcode":"6021 BH",
    "sg:province":"Noord-Brabant",
    "wof:name":"Annie Voetverzorging",
    "wof:placetype":"venue"
},
  "geometry": {"coordinates":[5.580214,51.271858],"type":"Point"}
}