{
  "type": "Feature",
  "properties": {
    "addr:full":"Oost-Voorstraat 32 Oud Beijerland Zuid-Holland 3262 JE",
    "addr:housenumber":"32",
    "addr:postcode":"3262 je",
    "addr:street":"Oost-Voorstraat;Oud Beijerland",
    "iso:country":"NL",
    "sg:address":"Oost-Voorstraat 32",
    "sg:city":"Oud Beijerland",
    "sg:orig_category":"Herenmodezaken",
    "sg:phone":"+31 186 615 671",
    "sg:postcode":"3262 JE",
    "sg:province":"Zuid-Holland",
    "wof:name":"Kruyswijk Mannenmode",
    "wof:placetype":"venue"
},
  "geometry": {"coordinates":[4.412285,51.825066],"type":"Point"}
}