{
  "type": "Feature",
  "properties": {
    "addr:full":"Piraeuspln 3 Amsterdam North Holland 1019 NL",
    "addr:housenumber":"3",
    "addr:postcode":"1019 nl",
    "addr:street":"Piraeuspln",
    "iso:country":"NL",
    "sg:address":"Piraeuspln 3",
    "sg:city":"Amsterdam",
    "sg:orig_category":"Adviesbureaus Elektronica",
    "sg:phone":"+31 20 419 6928",
    "sg:postcode":"1019 NL",
    "sg:province":"North Holland",
    "wof:name":"Boer, F W N De",
    "wof:placetype":"venue"
},
  "geometry": {"coordinates":[4.940721,52.37693],"type":"Point"}
}