{
  "type": "Feature",
  "properties": {
    "addr:full":"Rotterd Airp Pln 54 Rotterdam South Holland 3045 AP",
    "addr:housenumber":"54",
    "addr:postcode":"3045 ap",
    "addr:street":"Pln",
    "iso:country":"NL",
    "sg:address":"Rotterd Airp Pln 54",
    "sg:city":"Rotterdam",
    "sg:orig_category":"Luchtvaart- Maatschappijen",
    "sg:phone":"+31 10 437 8122",
    "sg:postcode":"3045 AP",
    "sg:province":"South Holland",
    "sg:website":"http://www.dynamic-airlines.nl",
    "wof:name":"Dynamic Airlines",
    "wof:placetype":"venue"
},
  "geometry": {"coordinates":[4.433426,51.94923],"type":"Point"}
}