{
  "type": "Feature",
  "properties": {
    "addr:full":"V Brienenoord 17 Rotterdam Zuid-Holland 3077 AE",
    "addr:housenumber":"17",
    "addr:postcode":"3077 ae",
    "addr:street":"Brienenoord",
    "iso:country":"NL",
    "sg:address":"V Brienenoord 17",
    "sg:city":"Rotterdam",
    "sg:orig_category":"Verenigingen En Stichtingen",
    "sg:phone":"+31 10 482 1434",
    "sg:postcode":"3077 AE",
    "sg:province":"Zuid-Holland",
    "wof:name":"Brienenoord Volkstuinver, Van",
    "wof:placetype":"venue"
},
  "geometry": {"coordinates":[4.5496,51.900501],"type":"Point"}
}