{
  "type": "Feature",
  "properties": {
    "addr:full":"Raadhuisstr 86 Heemstede North Holland 2101 HJ",
    "addr:housenumber":"86",
    "addr:postcode":"2101 hj",
    "addr:street":"Raadhuisstr",
    "iso:country":"NL",
    "sg:address":"Raadhuisstr 86",
    "sg:city":"Heemstede",
    "sg:orig_category":"Keukens",
    "sg:phone":"+31 23 547 6320",
    "sg:postcode":"2101 HJ",
    "sg:province":"North Holland",
    "wof:name":"Schutter",
    "wof:placetype":"venue"
},
  "geometry": {"coordinates":[4.621328,52.349403],"type":"Point"}
}