{
  "type": "Feature",
  "properties": {
    "addr:full":"Prinsenhil 13 Breda Noord-Brabant 4825 AX",
    "addr:housenumber":"13",
    "addr:postcode":"4825 ax",
    "addr:street":"Prinsenhil",
    "iso:country":"NL",
    "sg:address":"Prinsenhil 13",
    "sg:city":"Breda",
    "sg:orig_category":"Glasindustrie?n",
    "sg:phone":"+31 76 587 7771",
    "sg:postcode":"4825 AX",
    "sg:province":"Noord-Brabant",
    "sg:website":"http://www.artiglas.nl",
    "wof:name":"Theulings Glasslijperij Bv",
    "wof:placetype":"venue"
},
  "geometry": {"coordinates":[4.766537,51.615101],"type":"Point"}
}