{
  "type": "Feature",
  "properties": {
    "addr:full":"Oranjeplnts 88 Diemen Noord-Holland 1111 CH",
    "addr:housenumber":"88",
    "addr:postcode":"1111",
    "addr:street":"Oranjeplnts",
    "iso:country":"NL",
    "sg:address":"Oranjeplnts 88",
    "sg:city":"Diemen",
    "sg:orig_category":"Accountants - Administratie- Consulenten En -Kantoren",
    "sg:phone":"+31 20 690 3770",
    "sg:postcode":"1111 CH",
    "sg:province":"Noord-Holland",
    "wof:name":"Abako Bv",
    "wof:placetype":"venue"
},
  "geometry": {"coordinates":[4.958399,52.342892],"type":"Point"}
}