{
  "type": "Feature",
  "properties": {
    "iso:country":"NL",
    "sg:address":"Nes 116",
    "sg:city":"Amsterdam",
    "sg:orig_category":"Makelaars In Onroerend Goed",
    "sg:phone":"+31 20 623 9225",
    "sg:postcode":"1012 KE",
    "sg:province":"Noord-Holland",
    "wof:name":"Smit Boelen & Co Bv",
    "wof:placetype":"venue"
},
  "geometry": {"coordinates":[4.893101,52.369774],"type":"Point"}
}