{
  "type": "Feature",
  "properties": {
    "addr:full":"Kerkstr 9 Giesbeek Gelderland 6987 AA",
    "addr:housenumber":"9",
    "addr:postcode":"6987 aa",
    "addr:street":"Kerkstr;Gelderland",
    "iso:country":"NL",
    "sg:address":"Kerkstr 9",
    "sg:city":"Giesbeek",
    "sg:orig_category":"Kaarsen - Fabrieken En Groothandel",
    "sg:phone":"+31 313 632 128",
    "sg:postcode":"6987 AA",
    "sg:province":"Gelderland",
    "wof:name":"Zwalm, De",
    "wof:placetype":"venue"
},
  "geometry": {"coordinates":[6.0747551918,51.9971847534],"type":"Point"}
}