{
  "type": "Feature",
  "properties": {
    "addr:full":"Nieuwstr 9 Deventer Overijssel 7411 LE",
    "addr:housenumber":"9",
    "addr:postcode":"7411 le",
    "addr:street":"Nieuwstr",
    "iso:country":"NL",
    "sg:address":"Nieuwstr 9",
    "sg:city":"Deventer",
    "sg:orig_category":"Bloemen En Planten - Decoratie",
    "sg:phone":"+31 570 613 125",
    "sg:postcode":"7411 LE",
    "sg:province":"Overijssel",
    "wof:name":"Michiel",
    "wof:placetype":"venue"
},
  "geometry": {"coordinates":[6.159899,52.251034],"type":"Point"}
}