{
  "type": "Feature",
  "properties": {
    "addr:full":"Lorentzstr 15B Groningen Groningen 9727 HW",
    "addr:housenumber":"15b",
    "addr:postcode":"9727 hw",
    "addr:street":"Lorentzstr",
    "iso:country":"NL",
    "sg:address":"Lorentzstr 15B",
    "sg:city":"Groningen",
    "sg:orig_category":"Vertalers",
    "sg:phone":"+31 50 526 3444",
    "sg:postcode":"9727 HW",
    "sg:province":"Groningen",
    "wof:name":"Schedler, M M J",
    "wof:placetype":"venue"
},
  "geometry": {"coordinates":[6.558488,53.206131],"type":"Point"}
}