{
  "type": "Feature",
  "properties": {
    "addr:full":"Stationsstr 15-17 Twello Gelderland 7391 EG",
    "addr:housenumber":"15-17",
    "addr:postcode":"7391 eg",
    "addr:street":"Gelderland",
    "iso:country":"NL",
    "sg:address":"Stationsstr 15-17",
    "sg:city":"Twello",
    "sg:orig_category":"Kappers",
    "sg:phone":"+31 571 276 734",
    "sg:postcode":"7391 EG",
    "sg:province":"Gelderland",
    "wof:name":"E & E Hair En Beauty",
    "wof:placetype":"venue"
},
  "geometry": {"coordinates":[6.1026678085,52.2371711731],"type":"Point"}
}