{
  "type": "Feature",
  "properties": {
    "iso:country":"NL",
    "sg:address":"Brakkeveldweg 57",
    "sg:city":"Den Helder",
    "sg:orig_category":"Feestartikelen",
    "sg:phone":"+31 223 624 260",
    "sg:postcode":"1782 AE",
    "sg:province":"Noord-Holland",
    "wof:name":"T Snabbeltje",
    "wof:placetype":"venue"
},
  "geometry": {"coordinates":[4.759946,52.950241],"type":"Point"}
}