{
  "type": "Feature",
  "properties": {
    "addr:full":"Bieslandstraat 52 Rotterdam Zuid-Holland 3037 LD",
    "addr:housenumber":"52",
    "addr:postcode":"3037 ld",
    "addr:street":"Bieslandstraat",
    "iso:country":"NL",
    "sg:address":"Bieslandstraat 52",
    "sg:city":"Rotterdam",
    "sg:orig_category":"Wasserettes And Stomerijen",
    "sg:phone":"+31 10 465 7770",
    "sg:postcode":"3037 LD",
    "sg:province":"Zuid-Holland",
    "wof:name":"Wassalon Biesland Bv",
    "wof:placetype":"venue"
},
  "geometry": {"coordinates":[4.4733920097,51.9388923645],"type":"Point"}
}