{
  "type": "Feature",
  "properties": {
    "iso:country":"NL",
    "sg:address":"Vierakkerstraat 5",
    "sg:city":"Huissen",
    "sg:orig_category":"Kappers",
    "sg:phone":"+31 26 388 6847",
    "sg:postcode":"6851 BA",
    "sg:province":"Gelderland",
    "wof:name":"Harmony Of Hair",
    "wof:placetype":"venue"
},
  "geometry": {"coordinates":[5.9412879944,51.9355888367],"type":"Point"}
}