{
  "type": "Feature",
  "properties": {
    "iso:country":"NL",
    "sg:address":"Plein 1902 4-6",
    "sg:city":"Leerdam",
    "sg:orig_category":"Geluidsinstallaties",
    "sg:phone":"+31 345 612 967",
    "sg:postcode":"4141 DD",
    "sg:province":"Noord-Holland",
    "wof:name":"Premo",
    "wof:placetype":"venue"
},
  "geometry": {"coordinates":[5.091345,51.893051],"type":"Point"}
}