{
  "type": "Feature",
  "properties": {
    "addr:full":"Vredewg 32B Zaandam North Holland 1505 HH",
    "addr:housenumber":"32b",
    "addr:postcode":"1505 hh",
    "addr:street":"Vredewg",
    "iso:country":"NL",
    "sg:address":"Vredewg 32B",
    "sg:city":"Zaandam",
    "sg:orig_category":"Jachthavens - Jachtwerven",
    "sg:phone":"+31 75 614 9133",
    "sg:postcode":"1505 HH",
    "sg:province":"North Holland",
    "sg:website":"http://www.hollandjachtbouw.nl",
    "wof:name":"Holland Bv",
    "wof:placetype":"venue"
},
  "geometry": {"coordinates":[4.846794,52.425293],"type":"Point"}
}