{
  "type": "Feature",
  "properties": {
    "iso:country":"NL",
    "sg:address":"Haydnln 14",
    "sg:city":"Hoogezand",
    "sg:orig_category":"Adviesbureaus Financieel",
    "sg:phone":"+31 598 327 091",
    "sg:postcode":"9603 AS",
    "sg:province":"Groningen",
    "wof:name":"Finan-Econ",
    "wof:placetype":"venue"
},
  "geometry": {"coordinates":[6.759265,53.155895],"type":"Point"}
}