{
  "type": "Feature",
  "properties": {
    "addr:full":"Ambachtswg 4 Lexmond Zuid-Holland 4128 LC",
    "addr:housenumber":"4",
    "addr:postcode":"4128 lc",
    "addr:street":"Ambachtswg",
    "iso:country":"NL",
    "sg:address":"Ambachtswg 4",
    "sg:city":"Lexmond",
    "sg:orig_category":"Bodemonderzoek",
    "sg:phone":"+31 347 342 188",
    "sg:postcode":"4128 LC",
    "sg:province":"Zuid-Holland",
    "sg:website":"http://www.econsultancy.nl",
    "wof:name":"Econsultancy Bv",
    "wof:placetype":"venue"
},
  "geometry": {"coordinates":[5.046914,51.968975],"type":"Point"}
}