{
  "type": "Feature",
  "properties": {
    "addr:full":"Liesselseweg 112 Deurne North Brabant 5753 PP",
    "addr:housenumber":"112",
    "addr:postcode":"5753 pp",
    "addr:street":"Liesselseweg",
    "iso:country":"NL",
    "sg:address":"Liesselseweg 112",
    "sg:city":"Deurne",
    "sg:orig_category":"Autokeuringen",
    "sg:phone":"+31 493 313 307",
    "sg:postcode":"5753 PP",
    "sg:province":"North Brabant",
    "wof:name":"Van Der Schoot Auto'S",
    "wof:placetype":"venue"
},
  "geometry": {"coordinates":[5.796562,51.453964],"type":"Point"}
}