{
  "type": "Feature",
  "properties": {
    "addr:full":"Polstr 77 Wyk En Aalburg North Brabant 4261 BR",
    "addr:housenumber":"77",
    "addr:postcode":"4261 br",
    "addr:street":"Polstr",
    "iso:country":"NL",
    "sg:address":"Polstr 77",
    "sg:city":"Wyk En Aalburg",
    "sg:orig_category":"Bloemen En Planten - Groothandel",
    "sg:phone":"+31 416 691 523",
    "sg:postcode":"4261 BR",
    "sg:province":"North Brabant",
    "wof:name":"Bouman, C M",
    "wof:placetype":"venue"
},
  "geometry": {"coordinates":[5.124319,51.750381],"type":"Point"}
}