{
  "type": "Feature",
  "properties": {
    "addr:full":"Postbus 24 Dokkum Provincie Friesland 9100 AA",
    "addr:housenumber":"24",
    "addr:postcode":"9100 aa",
    "addr:street":"Postbus;Provincie Friesland",
    "iso:country":"NL",
    "sg:address":"Postbus 24",
    "sg:city":"Dokkum",
    "sg:orig_category":"Kabelexploitanten",
    "sg:phone":"+31 519 298 233",
    "sg:postcode":"9100 AA",
    "sg:province":"Provincie Friesland",
    "wof:name":"Kabel Noord",
    "wof:placetype":"venue"
},
  "geometry": {"coordinates":[5.9988498688,53.328289032],"type":"Point"}
}