{
  "type": "Feature",
  "properties": {
    "addr:full":"Stengelinstraat 1 Katwijk Zh Zuid-Holland 2225 EE",
    "addr:housenumber":"1",
    "addr:postcode":"2225 ee",
    "addr:street":"Stengelinstraat",
    "iso:country":"NL",
    "sg:address":"Stengelinstraat 1",
    "sg:city":"Katwijk Zh",
    "sg:orig_category":"Loodgieterswerk, Verwarming And Sanitaire Installaties",
    "sg:phone":"+31 71 407 2880",
    "sg:postcode":"2225 EE",
    "sg:province":"Zuid-Holland",
    "wof:name":"Van Duijn'S Loodgietersbedrijf",
    "wof:placetype":"venue"
},
  "geometry": {"coordinates":[4.403788,52.202965],"type":"Point"}
}