{
  "type": "Feature",
  "properties": {
    "addr:full":"Zuukerwg 32 Epe Gelderland 8161 XT",
    "addr:housenumber":"32",
    "addr:postcode":"8161 xt",
    "addr:street":"Zuukerwg;Gelderland",
    "iso:country":"NL",
    "sg:address":"Zuukerwg 32",
    "sg:city":"Epe",
    "sg:orig_category":"Autorijscholen",
    "sg:phone":"+31 578 627 876",
    "sg:postcode":"8161 XT",
    "sg:province":"Gelderland",
    "sg:website":"http://www.oscarpalm.nl",
    "wof:name":"Oscar Palm, Verkeersschool",
    "wof:placetype":"venue"
},
  "geometry": {"coordinates":[5.991656,52.340683],"type":"Point"}
}