{
  "type": "Feature",
  "properties": {
    "addr:full":"Harderwijkerweg 13 Eerbeek Gelderland 6961 GG",
    "addr:housenumber":"13",
    "addr:postcode":"6961 gg",
    "addr:street":"Harderwijkerweg;Gelderland",
    "iso:country":"NL",
    "sg:address":"Harderwijkerweg 13",
    "sg:city":"Eerbeek",
    "sg:orig_category":"Public Relationbureaus",
    "sg:phone":"+31 313 652 869",
    "sg:postcode":"6961 GG",
    "sg:province":"Gelderland",
    "wof:name":"Agri Relations",
    "wof:placetype":"venue"
},
  "geometry": {"coordinates":[6.040762,52.103722],"type":"Point"}
}