{
  "type": "Feature",
  "properties": {
    "addr:full":"Dickenslaan 24 Utrecht Utrecht 3533 BW",
    "addr:housenumber":"24",
    "addr:postcode":"3533 bw",
    "addr:street":"Dickenslaan",
    "iso:country":"NL",
    "sg:address":"Dickenslaan 24",
    "sg:city":"Utrecht",
    "sg:orig_category":"Boekhouders",
    "sg:phone":"+31 30 296 1047",
    "sg:postcode":"3533 BW",
    "sg:province":"Utrecht",
    "wof:name":"M.J.A. Van Den Ende",
    "wof:placetype":"venue"
},
  "geometry": {"coordinates":[5.080674,52.09119],"type":"Point"}
}