{
  "type": "Feature",
  "properties": {
    "addr:full":"Katwijkerbroek 51 Katwijk Zh South Holland 2223 XN",
    "addr:housenumber":"51",
    "addr:postcode":"zh;2223 xn",
    "addr:street":"Katwijkerbroek",
    "iso:country":"NL",
    "sg:address":"Katwijkerbroek 51",
    "sg:city":"Katwijk Zh",
    "sg:orig_category":"Houten Verpakkingen Fab",
    "sg:phone":"+31 71 407 4544",
    "sg:postcode":"2223 XN",
    "sg:province":"South Holland",
    "wof:name":"Kisten- Palletsfabriek Guldemond Bv",
    "wof:placetype":"venue"
},
  "geometry": {"coordinates":[4.42442,52.184059],"type":"Point"}
}