{
  "type": "Feature",
  "properties": {
    "addr:full":"Oudewg 105 Haarlem Noord-Holland 2031 CC",
    "addr:housenumber":"105",
    "addr:postcode":"2031 cc",
    "iso:country":"NL",
    "sg:address":"Oudewg 105",
    "sg:city":"Haarlem",
    "sg:orig_category":"Parketvloeren",
    "sg:phone":"+31 23 542 1864",
    "sg:postcode":"2031 CC",
    "sg:province":"Noord-Holland",
    "sg:website":"http://www.certus.nl",
    "wof:name":"Certus Haarlem Bv",
    "wof:placetype":"venue"
},
  "geometry": {"coordinates":[4.659426,52.385334],"type":"Point"}
}