{
  "type": "Feature",
  "properties": {
    "addr:full":"Daendelsstraat 78 Tilburg North Brabant 5018 ET",
    "addr:housenumber":"78",
    "addr:postcode":"5018 et",
    "addr:street":"Daendelsstraat",
    "iso:country":"NL",
    "sg:address":"Daendelsstraat 78",
    "sg:city":"Tilburg",
    "sg:orig_category":"Grafologen, Handlezers And Helderzienden",
    "sg:phone":"+31 13 580 0668",
    "sg:postcode":"5018 ET",
    "sg:province":"North Brabant",
    "wof:name":"M Bujdoso",
    "wof:placetype":"venue"
},
  "geometry": {"coordinates":[5.105222,51.558884],"type":"Point"}
}