{
  "type": "Feature",
  "properties": {
    "addr:full":"Cornelis Troostplein 15 Amsterdam North Holland 1072 JJ",
    "addr:housenumber":"15",
    "addr:postcode":"1072 jj",
    "addr:street":"Cornelis Troostplein",
    "iso:country":"NL",
    "sg:address":"Cornelis Troostplein 15",
    "sg:city":"Amsterdam",
    "sg:orig_category":"Kappers",
    "sg:phone":"+31 20 671 5542",
    "sg:postcode":"1072 JJ",
    "sg:province":"North Holland",
    "wof:name":"Koppers Kapsalon",
    "wof:placetype":"venue"
},
  "geometry": {"coordinates":[4.89138,52.35096],"type":"Point"}
}