{
  "type": "Feature",
  "properties": {
    "addr:full":"Saelde 16 Goirle Noord-Brabant 5051 WL",
    "addr:housenumber":"16",
    "addr:postcode":"5051 wl",
    "addr:street":"Saelde",
    "iso:country":"NL",
    "sg:address":"Saelde 16",
    "sg:city":"Goirle",
    "sg:orig_category":"Adviesbureaus Bedrijfsorganisatie",
    "sg:phone":"+31 13 534 6768",
    "sg:postcode":"5051 WL",
    "sg:province":"Noord-Brabant",
    "wof:name":"Fazant Bv",
    "wof:placetype":"venue"
},
  "geometry": {"coordinates":[5.069532,51.518112],"type":"Point"}
}