{
  "type": "Feature",
  "properties": {
    "addr:full":"Damln 46 Leidschendam Zuid-Holland 2265 AP",
    "addr:housenumber":"46",
    "addr:postcode":"2265 ap",
    "addr:street":"Damln",
    "iso:country":"NL",
    "sg:address":"Damln 46",
    "sg:city":"Leidschendam",
    "sg:orig_category":"Goudsmeden En Zilversmeden",
    "sg:phone":"+31 70 327 9112",
    "sg:postcode":"2265 AP",
    "sg:province":"Zuid-Holland",
    "wof:name":"Verduin, C J F",
    "wof:placetype":"venue"
},
  "geometry": {"coordinates":[4.395579,52.082401],"type":"Point"}
}