{
  "type": "Feature",
  "properties": {
    "addr:full":"Landstraat 35 Aalten Gelderland 7121 CN",
    "addr:housenumber":"35",
    "addr:postcode":"7121 cn",
    "addr:street":"Landstraat;Gelderland",
    "iso:country":"NL",
    "sg:address":"Landstraat 35",
    "sg:city":"Aalten",
    "sg:orig_category":"Kappers",
    "sg:phone":"+31 543 472 319",
    "sg:postcode":"7121 CN",
    "sg:province":"Gelderland",
    "wof:name":"Lelou Haarmode",
    "wof:placetype":"venue"
},
  "geometry": {"coordinates":[6.581215,51.915882],"type":"Point"}
}