{
  "type": "Feature",
  "properties": {
    "addr:full":"Weyland 19 Nieuwerbrug South Holland 2415 BB",
    "addr:housenumber":"19",
    "addr:postcode":"2415 bb",
    "addr:street":"Weyland;Nieuwerbrug South",
    "iso:country":"NL",
    "sg:address":"Weyland 19",
    "sg:city":"Nieuwerbrug",
    "sg:orig_category":"Pluimveebedrijven En -Handelaren",
    "sg:phone":"+31 348 688 422",
    "sg:postcode":"2415 BB",
    "sg:province":"South Holland",
    "wof:name":"Wil De Wit Groothandel",
    "wof:placetype":"venue"
},
  "geometry": {"coordinates":[4.8125009537,52.0775108337],"type":"Point"}
}