{
  "type": "Feature",
  "properties": {
    "addr:full":"Sportln 16 Roelofarendsveen Zuid-Holland 2371 XB",
    "addr:housenumber":"16",
    "addr:postcode":"2371 xb",
    "addr:street":"Sportln",
    "iso:country":"NL",
    "sg:address":"Sportln 16",
    "sg:city":"Roelofarendsveen",
    "sg:orig_category":"Sportverenigingen En Ontspannings- Verenigingen",
    "sg:phone":"+31 71 331 3527",
    "sg:postcode":"2371 XB",
    "sg:province":"Zuid-Holland",
    "wof:name":"Alkemade Tennisver",
    "wof:placetype":"venue"
},
  "geometry": {"coordinates":[4.632897,52.204285],"type":"Point"}
}