{
  "type": "Feature",
  "properties": {
    "iso:country":"NL",
    "sg:address":"Nieuwe Ebbingestraat 34",
    "sg:city":"Groningen",
    "sg:orig_category":"Boekhandels",
    "sg:phone":"+31 50 313 4939",
    "sg:postcode":"9712 NL",
    "sg:province":"Groningen",
    "wof:name":"Stichting Bijbel & Boekencentrum Kruispunt",
    "wof:placetype":"venue"
},
  "geometry": {"coordinates":[6.563749,53.223164],"type":"Point"}
}