{
  "type": "Feature",
  "properties": {
    "iso:country":"NL",
    "sg:address":"Prinsengracht 1113",
    "sg:city":"Amsterdam",
    "sg:orig_category":"Marktonderzoekbureaus",
    "sg:phone":"+31 20 622 9001",
    "sg:postcode":"1017 JJ",
    "sg:province":"North Holland",
    "wof:name":"Advic Group Bv",
    "wof:placetype":"venue"
},
  "geometry": {"coordinates":[4.900983,52.362782],"type":"Point"}
}