{
  "type": "Feature",
  "properties": {
    "addr:full":"Wieenpassage 31 Venlo Limburg 5921 GD",
    "addr:housenumber":"31",
    "addr:postcode":"5921 gd",
    "addr:street":"Wieenpassage",
    "iso:country":"NL",
    "sg:address":"Wieenpassage 31",
    "sg:city":"Venlo",
    "sg:orig_category":"Bloemen En Planten",
    "sg:phone":"+31 77 382 7816",
    "sg:postcode":"5921 GD",
    "sg:province":"Limburg",
    "wof:name":"Dings",
    "wof:placetype":"venue"
},
  "geometry": {"coordinates":[6.149108,51.369453],"type":"Point"}
}