{
  "type": "Feature",
  "properties": {
    "addr:full":"Clara Zetkinweg 2 Tilburg Noord-Brabant 5032 ML",
    "addr:housenumber":"2",
    "addr:postcode":"5032 ml",
    "addr:street":"Clara Zetkinweg",
    "iso:country":"NL",
    "sg:address":"Clara Zetkinweg 2",
    "sg:city":"Tilburg",
    "sg:orig_category":"Fruit And Groenten Gh",
    "sg:phone":"+31 13 467 5775",
    "sg:postcode":"5032 ML",
    "sg:province":"Noord-Brabant",
    "wof:name":"Frank Verhaaren Bv",
    "wof:placetype":"venue"
},
  "geometry": {"coordinates":[5.038752,51.534184],"type":"Point"}
}