{
  "type": "Feature",
  "properties": {
    "iso:country":"NL",
    "sg:address":"Velperwg 15",
    "sg:city":"Arnhem",
    "sg:orig_category":"Verzekeringen - Verzekeringskantoren",
    "sg:phone":"+31 26 443 5555",
    "sg:postcode":"6824 BC",
    "sg:province":"Gelderland",
    "sg:website":"http://www.gaba.nl",
    "wof:name":"Gaba Verzekeringen",
    "wof:placetype":"venue"
},
  "geometry": {"coordinates":[5.92224,51.985622],"type":"Point"}
}