{
  "type": "Feature",
  "properties": {
    "addr:full":"Kleine Haven 13 Haastrecht Zuid-Holland 2851 BP",
    "addr:housenumber":"13",
    "addr:postcode":"2851 bp",
    "addr:street":"Kleine Haven",
    "iso:country":"NL",
    "sg:address":"Kleine Haven 13",
    "sg:city":"Haastrecht",
    "sg:orig_category":"Damesmodezaken",
    "sg:phone":"+31 182 502 422",
    "sg:postcode":"2851 BP",
    "sg:province":"Zuid-Holland",
    "wof:name":"Boetiek De Egel",
    "wof:placetype":"venue"
},
  "geometry": {"coordinates":[4.775092,52.00185],"type":"Point"}
}