{
  "type": "Feature",
  "properties": {
    "addr:full":"Piusplein 71 Tilburg Noord-Brabant 5038 WP",
    "addr:housenumber":"71",
    "addr:postcode":"5038 wp",
    "addr:street":"Piusplein",
    "iso:country":"NL",
    "sg:address":"Piusplein 71",
    "sg:city":"Tilburg",
    "sg:orig_category":"Kappers",
    "sg:phone":"+31 13 542 0686",
    "sg:postcode":"5038 WP",
    "sg:province":"Noord-Brabant",
    "wof:name":"Kapsalon Le Changement",
    "wof:placetype":"venue"
},
  "geometry": {"coordinates":[5.0911397934,51.5557823181],"type":"Point"}
}