{
  "type": "Feature",
  "properties": {
    "addr:full":"Stationswg 38 Aalsmeer Noord-Holland 1431 EG",
    "addr:housenumber":"38",
    "addr:postcode":"1431 eg",
    "addr:street":"Stationswg",
    "iso:country":"NL",
    "sg:address":"Stationswg 38",
    "sg:city":"Aalsmeer",
    "sg:orig_category":"Administratie- En Boekhoudkantoren",
    "sg:phone":"+31 297 345 093",
    "sg:postcode":"1431 EG",
    "sg:province":"Noord-Holland",
    "wof:name":"Mas Bv",
    "wof:placetype":"venue"
},
  "geometry": {"coordinates":[4.750392,52.2649],"type":"Point"}
}