{
  "type": "Feature",
  "properties": {
    "addr:full":"Wiekermaatwg 1 Rossum Ov Overijssel 7596 JA",
    "addr:housenumber":"1",
    "addr:postcode":"7596 ja",
    "addr:street":"Wiekermaatwg;Ov",
    "iso:country":"NL",
    "sg:address":"Wiekermaatwg 1",
    "sg:city":"Rossum Ov",
    "sg:orig_category":"Verbouwingen",
    "sg:phone":"+31 541 625 661",
    "sg:postcode":"7596 JA",
    "sg:province":"Overijssel",
    "wof:name":"Groote Punt, Jos",
    "wof:placetype":"venue"
},
  "geometry": {"coordinates":[6.924828,52.356422],"type":"Point"}
}