{
  "type": "Feature",
  "properties": {
    "addr:full":"Burg Mooystr 19 Castricum Noord-Holland 1901 EP",
    "addr:housenumber":"19",
    "addr:postcode":"1901 ep",
    "addr:street":"Burg",
    "iso:country":"NL",
    "sg:address":"Burg Mooystr 19",
    "sg:city":"Castricum",
    "sg:orig_category":"Boeken En Tijdschriften",
    "sg:phone":"+31 251 652 255",
    "sg:postcode":"1901 EP",
    "sg:province":"Noord-Holland",
    "sg:website":"http://www.boekhandellaan.nl",
    "wof:name":"Laan Libris",
    "wof:placetype":"venue"
},
  "geometry": {"coordinates":[4.663725,52.546844],"type":"Point"}
}