{
  "type": "Feature",
  "properties": {
    "iso:country":"NL",
    "sg:address":"Schweibergerweg 54",
    "sg:city":"Mechelen",
    "sg:classifiers":[
        {
            "category":"Food & Beverages",
            "subcategory":"Fruits & Vegetables",
            "type":"Retail Goods"
        }
    ],
    "sg:phone":"+31 43 455 1237",
    "sg:postcode":"6281 NH",
    "sg:province":"Limburg",
    "sg:tags":[
        "groenten"
    ],
    "wof:name":"J J H Wetzels",
    "wof:placetype":"venue"
},
  "geometry": {"coordinates":[5.901945,50.783047],"type":"Point"}
}