{
  "type": "Feature",
  "properties": {
    "addr:full":"Suyderbon 38 Rynsaterwoude Zuid-Holland 2465 BR",
    "addr:housenumber":"38",
    "addr:postcode":"2465 br",
    "addr:street":"Suyderbon",
    "iso:country":"NL",
    "sg:address":"Suyderbon 38",
    "sg:city":"Rynsaterwoude",
    "sg:orig_category":"Administratie- En Boekhoudkantoren",
    "sg:phone":"+31 172 508 626",
    "sg:postcode":"2465 BR",
    "sg:province":"Zuid-Holland",
    "wof:name":"Geest, C B Van Der",
    "wof:placetype":"venue"
},
  "geometry": {"coordinates":[4.669061,52.196091],"type":"Point"}
}