{
  "type": "Feature",
  "properties": {
    "addr:full":"A Huynstr 3 Venlo Limburg 5914 PE",
    "addr:housenumber":"3",
    "addr:postcode":"5914 pe",
    "iso:country":"NL",
    "sg:address":"A Huynstr 3",
    "sg:city":"Venlo",
    "sg:orig_category":"Verenigingen En Stichtingen",
    "sg:phone":"+31 77 324 0299",
    "sg:postcode":"5914 PE",
    "sg:province":"Limburg",
    "wof:name":"Witte Kerk, Sticht De",
    "wof:placetype":"venue"
},
  "geometry": {"coordinates":[6.17286,51.372421],"type":"Point"}
}