{
  "type": "Feature",
  "properties": {
    "addr:full":"Industriewg 9A Woerden Utrecht 3442 AE",
    "addr:housenumber":"9a",
    "addr:postcode":"3442 ae",
    "addr:street":"Industriewg",
    "iso:country":"NL",
    "sg:address":"Industriewg 9A",
    "sg:city":"Woerden",
    "sg:orig_category":"Kaasgroothandel",
    "sg:phone":"+31 348 413 568",
    "sg:postcode":"3442 AE",
    "sg:province":"Utrecht",
    "wof:name":"Nell, A",
    "wof:placetype":"venue"
},
  "geometry": {"coordinates":[4.8800578117,52.0809860229],"type":"Point"}
}