{
  "type": "Feature",
  "properties": {
    "addr:full":"Wilhelminastr 3 Boekel Noord-Brabant 5427 CC",
    "addr:housenumber":"3",
    "addr:postcode":"5427 cc",
    "addr:street":"Wilhelminastr",
    "iso:country":"NL",
    "sg:address":"Wilhelminastr 3",
    "sg:city":"Boekel",
    "sg:orig_category":"Schilders",
    "sg:phone":"+31 492 321 727",
    "sg:postcode":"5427 CC",
    "sg:province":"Noord-Brabant",
    "wof:name":"Delst, A H M Van",
    "wof:placetype":"venue"
},
  "geometry": {"coordinates":[5.671423,51.605221],"type":"Point"}
}