{
  "type": "Feature",
  "properties": {
    "addr:full":"Torenln 27A Laren Nh Noord-Holland 1251 HG",
    "addr:housenumber":"27a",
    "addr:postcode":"1251 hg",
    "addr:street":"Torenln",
    "iso:country":"NL",
    "sg:address":"Torenln 27A",
    "sg:city":"Laren Nh",
    "sg:orig_category":"Pensioenen",
    "sg:phone":"+31 35 538 7660",
    "sg:postcode":"1251 HG",
    "sg:province":"Noord-Holland",
    "sg:website":"http://www.leeuwerke-finance.nl",
    "wof:name":"Leeuwerke Finance Bv",
    "wof:placetype":"venue"
},
  "geometry": {"coordinates":[5.22387,52.256741],"type":"Point"}
}