{
  "type": "Feature",
  "properties": {
    "addr:full":"Hoofdstraat 88 Diever Drenthe 7981 AV",
    "addr:housenumber":"88",
    "addr:postcode":"7981 av",
    "addr:street":"Hoofdstraat",
    "iso:country":"NL",
    "sg:address":"Hoofdstraat 88",
    "sg:city":"Diever",
    "sg:orig_category":"Bibliotheken And Openbare Archieven",
    "sg:phone":"+31 521 592 915",
    "sg:postcode":"7981 AV",
    "sg:province":"Drenthe",
    "wof:name":"Openbare Bibliotheek",
    "wof:placetype":"venue"
},
  "geometry": {"coordinates":[6.321749,52.853436],"type":"Point"}
}