{
  "type": "Feature",
  "properties": {
    "addr:full":"Ankerkd 12 , (Blerick) Venlo Limburg 5928 PL",
    "addr:housenumber":"12",
    "addr:postcode":"5928 pl",
    "addr:street":"Ankerkd",
    "iso:country":"NL",
    "sg:address":"Ankerkd 12 , (Blerick)",
    "sg:city":"Venlo",
    "sg:orig_category":"Pijpleidingen - Installatie En Onderhoud",
    "sg:phone":"+31 77 382 0870",
    "sg:postcode":"5928 PL",
    "sg:province":"Limburg",
    "wof:name":"Hogenboom Spijkenisse Bv",
    "wof:placetype":"venue"
},
  "geometry": {"coordinates":[6.11955,51.395309],"type":"Point"}
}