{
  "type": "Feature",
  "properties": {
    "addr:full":"Duindoorn 24 Emmen Drenthe 7822 AL",
    "addr:housenumber":"24",
    "addr:postcode":"7822 al",
    "addr:street":"Duindoorn",
    "iso:country":"NL",
    "sg:address":"Duindoorn 24",
    "sg:city":"Emmen",
    "sg:orig_category":"Geluidsinstallaties",
    "sg:phone":"+31 591 658 806",
    "sg:postcode":"7822 AL",
    "sg:province":"Drenthe",
    "sg:website":"http://www.dj-store.nl",
    "wof:name":"Profilight",
    "wof:placetype":"venue"
},
  "geometry": {"coordinates":[6.905552,52.798237],"type":"Point"}
}