{
  "type": "Feature",
  "properties": {
    "addr:full":"L Spaanderln 30 Volendam Noord-Holland 1132 BR",
    "addr:housenumber":"30",
    "addr:postcode":"1132 br",
    "iso:country":"NL",
    "sg:address":"L Spaanderln 30",
    "sg:city":"Volendam",
    "sg:orig_category":"Scholen Voor Basisonderwijs",
    "sg:phone":"+31 299 363 029",
    "sg:postcode":"1132 BR",
    "sg:province":"Noord-Holland",
    "wof:name":"Springplank Rk, De",
    "wof:placetype":"venue"
},
  "geometry": {"coordinates":[5.04978,52.495243],"type":"Point"}
}