{
  "type": "Feature",
  "properties": {
    "iso:country":"NL",
    "sg:address":"Westbroeksebinnenweg 68C-31",
    "sg:city":"Tienhoven Ut",
    "sg:orig_category":"Verhuur Bouwmachines",
    "sg:phone":"+31 6 55765923",
    "sg:postcode":"3612 AJ",
    "sg:province":"Utrecht",
    "wof:name":"Front Stage",
    "wof:placetype":"venue"
},
  "geometry": {"coordinates":[5.09943,52.141529],"type":"Point"}
}