{
  "type": "Feature",
  "properties": {
    "addr:full":"L Nieuwstr 171 Schiedam South Holland 3111 AJ",
    "addr:housenumber":"171",
    "addr:postcode":"3111 aj",
    "iso:country":"NL",
    "sg:address":"L Nieuwstr 171",
    "sg:city":"Schiedam",
    "sg:classifiers":[
        {
            "category":"Professional",
            "subcategory":"Accounting & Tax Preparation",
            "type":"Services"
        }
    ],
    "sg:phone":"+31 10 426 3479",
    "sg:postcode":"3111 AJ",
    "sg:province":"South Holland",
    "sg:tags":[
        "accountant",
        "en",
        "-kantoren",
        "register-"
    ],
    "wof:name":"Oranje, J",
    "wof:placetype":"venue"
},
  "geometry": {"coordinates":[4.401754,51.912182],"type":"Point"}
}