{
  "type": "Feature",
  "properties": {
    "iso:country":"NL",
    "sg:address":"Ravenswade 98A",
    "sg:city":"Nieuwegein",
    "sg:orig_category":"Medische Installaties En Instrumenten",
    "sg:phone":"+31 30 284 9177",
    "sg:postcode":"3439 LD",
    "sg:province":"Utrecht",
    "wof:name":"Medical Dynamics",
    "wof:placetype":"venue"
},
  "geometry": {"coordinates":[5.115413,52.050537],"type":"Point"}
}