{
  "type": "Feature",
  "properties": {
    "addr:full":"Watermolen 15 Tholen Zeeland 4691 LH",
    "addr:housenumber":"15",
    "addr:postcode":"4691 lh",
    "addr:street":"Watermolen",
    "iso:country":"NL",
    "sg:address":"Watermolen 15",
    "sg:city":"Tholen",
    "sg:orig_category":"Binnenvaart",
    "sg:phone":"+31 166 604 547",
    "sg:postcode":"4691 LH",
    "sg:province":"Zeeland",
    "wof:name":"Jan Molenaar",
    "wof:placetype":"venue"
},
  "geometry": {"coordinates":[4.218683,51.53566],"type":"Point"}
}