{
  "type": "Feature",
  "properties": {
    "addr:full":"Apolloln 138 Reservations - Toll Free Amsterdam Noord-Holland 1077 BG",
    "addr:housenumber":"138",
    "addr:postcode":"1077",
    "addr:street":"Reservations Toll Free",
    "iso:country":"NL",
    "sg:address":"Apolloln 138 Reservations - Toll Free",
    "sg:city":"Amsterdam",
    "sg:classifiers":[
        {
            "category":"Travel",
            "subcategory":"Hotels & Motels",
            "type":"Entertainment"
        }
    ],
    "sg:phone":"+31 800 0223346",
    "sg:postcode":"1077 BG",
    "sg:province":"Noord-Holland",
    "wof:name":"Hilton Reservations Worldwide",
    "wof:placetype":"venue"
},
  "geometry": {"coordinates":[4.87585,52.345482],"type":"Point"}
}