{
  "type": "Feature",
  "properties": {
    "addr:full":"Norbertynenstr 12 Assendelft Noord-Holland 1566 LK",
    "addr:housenumber":"12",
    "addr:postcode":"1566 lk",
    "addr:street":"Norbertynenstr",
    "iso:country":"NL",
    "sg:address":"Norbertynenstr 12",
    "sg:city":"Assendelft",
    "sg:orig_category":"Fotografie Reclame En Mode",
    "sg:phone":"+31 75 687 7783",
    "sg:postcode":"1566 LK",
    "sg:province":"Noord-Holland",
    "sg:website":"http://www.zellererfotografie.nl",
    "wof:name":"Yvette Zellerer",
    "wof:placetype":"venue"
},
  "geometry": {"coordinates":[4.74064,52.466629],"type":"Point"}
}