{
  "type": "Feature",
  "properties": {
    "addr:full":"Kraaivenstr 19 Tilburg Noord-Brabant 5048 AB",
    "addr:housenumber":"19",
    "addr:postcode":"5048 ab",
    "addr:street":"Kraaivenstr",
    "iso:country":"NL",
    "sg:address":"Kraaivenstr 19",
    "sg:city":"Tilburg",
    "sg:orig_category":"Directmail",
    "sg:phone":"+31 13 595 3500",
    "sg:postcode":"5048 AB",
    "sg:province":"Noord-Brabant",
    "wof:name":"Pondres Bv",
    "wof:placetype":"venue"
},
  "geometry": {"coordinates":[5.066056,51.585102],"type":"Point"}
}