{
  "type": "Feature",
  "properties": {
    "addr:full":"Cruquiuswg 48 Amsterdam North Holland 1019 AT",
    "addr:housenumber":"48",
    "addr:postcode":"1019",
    "addr:street":"Cruquiuswg",
    "iso:country":"NL",
    "sg:address":"Cruquiuswg 48",
    "sg:city":"Amsterdam",
    "sg:orig_category":"Onderhoudswerken",
    "sg:phone":"+31 20 463 1030",
    "sg:postcode":"1019 AT",
    "sg:province":"North Holland",
    "sg:website":"http://www.elbuc.nl",
    "wof:name":"Elbuc Onderhoudsbedrijf Vof",
    "wof:placetype":"venue"
},
  "geometry": {"coordinates":[4.937503,52.368458],"type":"Point"}
}