{
  "type": "Feature",
  "properties": {
    "addr:full":"Rijndijk 216 Hazerswoude Rijndijk South Holland 2394 AM",
    "addr:housenumber":"216",
    "addr:postcode":"2394",
    "addr:street":"Rijndijk;Hazerswoude Rijndijk",
    "iso:country":"NL",
    "sg:address":"Rijndijk 216",
    "sg:city":"Hazerswoude Rijndijk",
    "sg:orig_category":"Elektriciens",
    "sg:phone":"+31 71 341 3020",
    "sg:postcode":"2394 AM",
    "sg:province":"South Holland",
    "wof:name":"C. Cok Electrisch Installatiebedrijf Bv",
    "wof:placetype":"venue"
},
  "geometry": {"coordinates":[4.58323,52.128239],"type":"Point"}
}