{
  "type": "Feature",
  "properties": {
    "iso:country":"NL",
    "sg:address":"Pascalwg 10",
    "sg:city":"Nunspeet",
    "sg:orig_category":"Elektronica - Ontwikkeling En Groothandel",
    "sg:phone":"+31 341 251 899",
    "sg:postcode":"8071 SE",
    "sg:province":"Gelderland",
    "sg:website":"HTTP://www.opticom.nl",
    "wof:name":"Opticom Bv",
    "wof:placetype":"venue"
},
  "geometry": {"coordinates":[5.764269,52.373966],"type":"Point"}
}