{
  "type": "Feature",
  "properties": {
    "addr:full":"Thuishaven 6 Huissen Gelderland 6852 DH",
    "addr:housenumber":"6",
    "addr:postcode":"6852 dh",
    "addr:street":"Thuishaven;Gelderland",
    "iso:country":"NL",
    "sg:address":"Thuishaven 6",
    "sg:city":"Huissen",
    "sg:orig_category":"Adviesbureaus Bedrijfsorganisatie",
    "sg:phone":"+31 26 325 2868",
    "sg:postcode":"6852 DH",
    "sg:province":"Gelderland",
    "sg:website":"http://www.the-wok.com",
    "wof:name":"Wheel Of Knowledge Cv, The",
    "wof:placetype":"venue"
},
  "geometry": {"coordinates":[5.929014,51.943321],"type":"Point"}
}