{
  "type": "Feature",
  "properties": {
    "addr:full":"Steenovenwg 5 Werkhoven Utrecht 3985 SJ",
    "addr:housenumber":"5",
    "addr:postcode":"3985",
    "addr:street":"Steenovenwg",
    "iso:country":"NL",
    "sg:address":"Steenovenwg 5",
    "sg:city":"Werkhoven",
    "sg:orig_category":"Grondwerken",
    "sg:phone":"+31 343 551 331",
    "sg:postcode":"3985 SJ",
    "sg:province":"Utrecht",
    "wof:name":"Bos Bv, C J",
    "wof:placetype":"venue"
},
  "geometry": {"coordinates":[5.264048,52.020508],"type":"Point"}
}