{
  "type": "Feature",
  "properties": {
    "iso:country":"NL",
    "sg:address":"Heiligerweg 1",
    "sg:city":"Margraten",
    "sg:orig_category":"Bloemen And Planten",
    "sg:phone":"+31 43 458 1234",
    "sg:postcode":"6269 NM",
    "sg:province":"Limburg",
    "wof:name":"De Bloemkwekerij Margraten",
    "wof:placetype":"venue"
},
  "geometry": {"coordinates":[5.830051899,50.8250808716],"type":"Point"}
}