{
  "type": "Feature",
  "properties": {
    "addr:full":"Schouwpad 11 Lopik Utrecht 3411 WB",
    "addr:housenumber":"11",
    "addr:postcode":"3411 wb",
    "addr:street":"Schouwpad",
    "iso:country":"NL",
    "sg:address":"Schouwpad 11",
    "sg:city":"Lopik",
    "sg:orig_category":"Metaalbewerking",
    "sg:phone":"+31 348 551 956",
    "sg:postcode":"3411 WB",
    "sg:province":"Utrecht",
    "wof:name":"Hacotec, Lopik",
    "wof:placetype":"venue"
},
  "geometry": {"coordinates":[4.935936,51.974117],"type":"Point"}
}