{
  "type": "Feature",
  "properties": {
    "addr:full":"Zonneplein 11 Amsterdam Noord-Holland 1033 EJ",
    "addr:housenumber":"11",
    "addr:postcode":"1033 ej",
    "addr:street":"Zonneplein",
    "iso:country":"NL",
    "sg:address":"Zonneplein 11",
    "sg:city":"Amsterdam",
    "sg:orig_category":"Zuivelproducten",
    "sg:phone":"+31 20 631 5380",
    "sg:postcode":"1033 EJ",
    "sg:province":"Noord-Holland",
    "wof:name":"Kaashuis De Reuver",
    "wof:placetype":"venue"
},
  "geometry": {"coordinates":[4.890652,52.413132],"type":"Point"}
}