{
  "type": "Feature",
  "properties": {
    "addr:full":"Zoggelstr 6 Uden North Carolina 5404 NC",
    "addr:housenumber":"6",
    "addr:postcode":"5404 nc",
    "addr:street":"Zoggelstr",
    "iso:country":"NL",
    "sg:address":"Zoggelstr 6",
    "sg:city":"Uden",
    "sg:orig_category":"Betonijzervlechten",
    "sg:phone":"+31 6 22153606",
    "sg:postcode":"5404 NC",
    "sg:province":"North Carolina",
    "wof:name":"Raaijmakers",
    "wof:placetype":"venue"
},
  "geometry": {"coordinates":[-80.018333,35.21941],"type":"Point"}
}