{
  "type": "Feature",
  "properties": {
    "iso:country":"NL",
    "sg:address":"Veenweg 10",
    "sg:city":"Bathmen",
    "sg:orig_category":"Artsen And Specialisten",
    "sg:phone":"+31 573 221 491",
    "sg:postcode":"7437 SG",
    "sg:province":"Overijssel",
    "wof:name":"H.J. De Heer",
    "wof:placetype":"venue"
},
  "geometry": {"coordinates":[6.373826,52.249634],"type":"Point"}
}