{
  "type": "Feature",
  "properties": {
    "addr:full":"Bocholterwg 150 Weert Limburg 6006 TP",
    "addr:housenumber":"150",
    "addr:postcode":"6006",
    "addr:street":"Weert Limburg",
    "iso:country":"NL",
    "sg:address":"Bocholterwg 150",
    "sg:city":"Weert",
    "sg:orig_category":"Homeopathie",
    "sg:phone":"+31 495 522 250",
    "sg:postcode":"6006 TP",
    "sg:province":"Limburg",
    "wof:name":"Jongebreur, M",
    "wof:placetype":"venue"
},
  "geometry": {"coordinates":[5.662923,51.212589],"type":"Point"}
}