{
  "type": "Feature",
  "properties": {
    "addr:full":"V Linschotenstr 4B Valkenswaard Noord-Brabant 5554 PM",
    "addr:housenumber":"4b",
    "addr:postcode":"5554 pm",
    "addr:street":"Linschotenstr",
    "iso:country":"NL",
    "sg:address":"V Linschotenstr 4B",
    "sg:city":"Valkenswaard",
    "sg:orig_category":"Antiquiteiten",
    "sg:phone":"+31 40 204 5456",
    "sg:postcode":"5554 PM",
    "sg:province":"Noord-Brabant",
    "wof:name":"Meubeldroom, De",
    "wof:placetype":"venue"
},
  "geometry": {"coordinates":[5.45897,51.35051],"type":"Point"}
}