{
  "type": "Feature",
  "properties": {
    "iso:country":"NL",
    "sg:address":"Raadhuisplein 25",
    "sg:city":"Nieuwerkerk Ad Ijssel",
    "sg:orig_category":"Verzekeringen",
    "sg:phone":"+31 180 319 926",
    "sg:postcode":"2914 KM",
    "sg:province":"Zuid-Holland",
    "wof:name":"Carinac Assurantien Bv",
    "wof:placetype":"venue"
},
  "geometry": {"coordinates":[4.616937,51.966934],"type":"Point"}
}