{
  "type": "Feature",
  "properties": {
    "addr:full":"Dorpsstraat 32 Wijngaarden Zh South Holland 3366 BD",
    "addr:housenumber":"32",
    "addr:postcode":"zh;3366 bd",
    "addr:street":"Dorpsstraat",
    "iso:country":"NL",
    "sg:address":"Dorpsstraat 32",
    "sg:city":"Wijngaarden Zh",
    "sg:classifiers":[
        {
            "category":"Education",
            "subcategory":"Preschool",
            "type":"Public Place"
        }
    ],
    "sg:phone":"+31 184 410 139",
    "sg:postcode":"3366 BD",
    "sg:province":"South Holland",
    "sg:tags":[
        "kleuteronderwijs",
        "basis-"
    ],
    "wof:name":"Christelijke Basisschool De Zaaier",
    "wof:placetype":"venue"
},
  "geometry": {"coordinates":[4.761737,51.844685],"type":"Point"}
}