{
  "type": "Feature",
  "properties": {
    "iso:country":"NL",
    "sg:address":"Oudkerkseweg 3 A",
    "sg:city":"Giessenburg",
    "sg:orig_category":"Fotostudio'S And Fotografen",
    "sg:phone":"+31 184 652 140",
    "sg:postcode":"3381 KP",
    "sg:province":"Zuid-Holland",
    "wof:name":"Atelier Leo Lanser",
    "wof:placetype":"venue"
},
  "geometry": {"coordinates":[4.87001,51.843922],"type":"Point"}
}