{
  "type": "Feature",
  "properties": {
    "iso:country":"NL",
    "sg:address":"Hoofdstraat 176",
    "sg:city":"Apeldoorn",
    "sg:classifiers":[
        {
            "category":"Bars & Pubs",
            "type":"Food & Drink"
        }
    ],
    "sg:phone":"+31 55 576 8630",
    "sg:postcode":"7311 BD",
    "sg:province":"Gelderland",
    "wof:name":"Finnegan'S Pub",
    "wof:placetype":"venue"
},
  "geometry": {"coordinates":[5.958449,52.216599],"type":"Point"}
}