{
  "type": "Feature",
  "properties": {
    "iso:country":"NL",
    "sg:address":"Parnassuswg 206",
    "sg:city":"Amsterdam",
    "sg:orig_category":"Fotoapparatuur En -Artikelen - Groothandel",
    "sg:phone":"+31 20 676 7569",
    "sg:postcode":"1076 AV",
    "sg:province":"Noord-Holland",
    "wof:name":"Fimex Bv",
    "wof:placetype":"venue"
},
  "geometry": {"coordinates":[4.867921,52.342205],"type":"Point"}
}