{
  "type": "Feature",
  "properties": {
    "addr:full":"Boslaan 12 Bussum North Holland 1405 CB",
    "addr:housenumber":"12",
    "addr:postcode":"1405 cb",
    "addr:street":"Boslaan",
    "iso:country":"NL",
    "sg:address":"Boslaan 12",
    "sg:city":"Bussum",
    "sg:orig_category":"Diverse Grafische Activiteiten",
    "sg:phone":"+31 35 691 4325",
    "sg:postcode":"1405 CB",
    "sg:province":"North Holland",
    "wof:name":"Hermaion",
    "wof:placetype":"venue"
},
  "geometry": {"coordinates":[5.147627,52.275951],"type":"Point"}
}