{
  "type": "Feature",
  "properties": {
    "addr:full":"Verenwei 39 Arnhem Gelderland 6843 ZV",
    "addr:housenumber":"39",
    "addr:postcode":"6843 zv",
    "addr:street":"Verenwei",
    "iso:country":"NL",
    "sg:address":"Verenwei 39",
    "sg:city":"Arnhem",
    "sg:orig_category":"Fotostudio'S And Fotografen",
    "sg:phone":"+31 26 381 2278",
    "sg:postcode":"6843 ZV",
    "sg:province":"Gelderland",
    "wof:name":"Fotografie Split Second Arnhem",
    "wof:placetype":"venue"
},
  "geometry": {"coordinates":[5.866197,51.96471],"type":"Point"}
}