{
  "type": "Feature",
  "properties": {
    "addr:full":"Postbus 464 Houten Utrecht 3990 GG",
    "addr:housenumber":"464",
    "addr:postcode":"3990 gg",
    "addr:street":"Postbus",
    "iso:country":"NL",
    "sg:address":"Postbus 464",
    "sg:city":"Houten",
    "sg:orig_category":"Adviesbureaus Bedrijfsorganisatie",
    "sg:phone":"+31 30 635 0546",
    "sg:postcode":"3990 GG",
    "sg:province":"Utrecht",
    "sg:website":"http://www.fwaarde.nl",
    "wof:name":"F-Waarde",
    "wof:placetype":"venue"
},
  "geometry": {"coordinates":[5.169435,52.036541],"type":"Point"}
}