{
  "type": "Feature",
  "properties": {
    "addr:full":"Patrys 1 Ursem North Holland 1645 TL",
    "addr:housenumber":"1",
    "addr:postcode":"1645 tl",
    "addr:street":"Patrys",
    "iso:country":"NL",
    "sg:address":"Patrys 1",
    "sg:city":"Ursem",
    "sg:orig_category":"Homeopathie",
    "sg:phone":"+31 72 502 2950",
    "sg:postcode":"1645 TL",
    "sg:province":"North Holland",
    "wof:name":"Stam, Anita",
    "wof:placetype":"venue"
},
  "geometry": {"coordinates":[4.88878,52.629314],"type":"Point"}
}