{
  "type": "Feature",
  "properties": {
    "addr:full":"Elzenbroek 15 Breda Noord-Brabant 4822 XE",
    "addr:housenumber":"15",
    "addr:postcode":"4822 xe",
    "addr:street":"Elzenbroek",
    "iso:country":"NL",
    "sg:address":"Elzenbroek 15",
    "sg:city":"Breda",
    "sg:orig_category":"Verhuur Audiovisuele Apparatuur",
    "sg:phone":"+31 76 542 2368",
    "sg:postcode":"4822 XE",
    "sg:province":"Noord-Brabant",
    "wof:name":"G.J. Sound Service",
    "wof:placetype":"venue"
},
  "geometry": {"coordinates":[4.731749,51.60535],"type":"Point"}
}