{
  "type": "Feature",
  "properties": {
    "addr:full":"Minden 26 Apeldoorn Gelderland 7327 AW",
    "addr:housenumber":"26",
    "addr:postcode":"7327 aw",
    "addr:street":"Minden;Gelderland",
    "iso:country":"NL",
    "sg:address":"Minden 26",
    "sg:city":"Apeldoorn",
    "sg:orig_category":"Adviesbureaus Beveiliging",
    "sg:phone":"+31 55 541 5416",
    "sg:postcode":"7327 AW",
    "sg:province":"Gelderland",
    "wof:name":"Dongen En Partn Bv, P Van",
    "wof:placetype":"venue"
},
  "geometry": {"coordinates":[5.992463,52.187057],"type":"Point"}
}