{
  "type": "Feature",
  "properties": {
    "iso:country":"NL",
    "sg:address":"Olympiapln 152",
    "sg:city":"Amsterdam",
    "sg:orig_category":"Verzekeringen - Verzekeringskantoren",
    "sg:phone":"+31 20 679 6162",
    "sg:postcode":"1076 AL",
    "sg:province":"Noord-Holland",
    "wof:name":"Een In Al",
    "wof:placetype":"venue"
},
  "geometry": {"coordinates":[4.866301,52.346027],"type":"Point"}
}