{
  "type": "Feature",
  "properties": {
    "addr:full":"Meijgraaf 43 Schijndel Noord-Brabant 5481 GA",
    "addr:housenumber":"43",
    "addr:postcode":"5481 ga",
    "addr:street":"Meijgraaf",
    "iso:country":"NL",
    "sg:address":"Meijgraaf 43",
    "sg:city":"Schijndel",
    "sg:orig_category":"Geluidsopnamen",
    "sg:phone":"+31 73 547 4759",
    "sg:postcode":"5481 GA",
    "sg:province":"Noord-Brabant",
    "wof:name":"Kees Buenen Produktions",
    "wof:placetype":"venue"
},
  "geometry": {"coordinates":[-83.222931,32.678131],"type":"Point"}
}