{
  "type": "Feature",
  "properties": {
    "iso:country":"NL",
    "sg:address":"Stationspln 14A",
    "sg:city":"Zevenaar",
    "sg:orig_category":"Logopedisten",
    "sg:phone":"+31 316 524 904",
    "sg:postcode":"6901 BE",
    "sg:province":"Gelderland",
    "wof:name":"Logopedie Op Scholen",
    "wof:placetype":"venue"
},
  "geometry": {"coordinates":[6.076878,51.931618],"type":"Point"}
}