{
  "type": "Feature",
  "properties": {
    "addr:full":"Linnerweg 31 Montfort Limburg 6065 EM",
    "addr:housenumber":"31",
    "addr:postcode":"6065 em",
    "addr:street":"Linnerweg",
    "iso:country":"NL",
    "sg:address":"Linnerweg 31",
    "sg:city":"Montfort",
    "sg:orig_category":"Kunst And Kunstenaarsbenodigdheden",
    "sg:phone":"+31 475 541 826",
    "sg:postcode":"6065 EM",
    "sg:province":"Limburg",
    "wof:name":"Keramiek Roos Van Heel",
    "wof:placetype":"venue"
},
  "geometry": {"coordinates":[5.94582,51.131618],"type":"Point"}
}