{
  "type": "Feature",
  "properties": {
    "addr:full":"Sint Oedenrodeseweg 5 Best Noord-Brabant 5681 PH",
    "addr:housenumber":"5",
    "addr:postcode":"5681",
    "addr:street":"Oedenrodeseweg",
    "iso:country":"NL",
    "sg:address":"Sint Oedenrodeseweg 5",
    "sg:city":"Best",
    "sg:orig_category":"Algemene Werktuigbouw",
    "sg:phone":"+31 499 393 781",
    "sg:postcode":"5681 PH",
    "sg:province":"Noord-Brabant",
    "wof:name":"R.L.B.",
    "wof:placetype":"venue"
},
  "geometry": {"coordinates":[-101.46472199999999,31.19459],"type":"Point"}
}