{
  "type": "Feature",
  "properties": {
    "addr:full":"Lage Bothofstraat 322 Enschede Overijssel 7533 AT",
    "addr:housenumber":"322",
    "addr:postcode":"7533",
    "addr:street":"Lage Bothofstraat",
    "iso:country":"NL",
    "sg:address":"Lage Bothofstraat 322",
    "sg:city":"Enschede",
    "sg:orig_category":"Meubelreparatie And -Restauratie",
    "sg:phone":"+31 53 431 6547",
    "sg:postcode":"7533 AT",
    "sg:province":"Overijssel",
    "wof:name":"G.J.L. Steffens",
    "wof:placetype":"venue"
},
  "geometry": {"coordinates":[6.914674,52.223942],"type":"Point"}
}