{
  "type": "Feature",
  "properties": {
    "addr:full":"Cornelis Blaauwstraat 17 West Graftdijk North Holland 1486 MR",
    "addr:housenumber":"17",
    "addr:postcode":"1486 mr",
    "addr:street":"Cornelis Blaauwstraat;West Graftdijk North",
    "iso:country":"NL",
    "sg:address":"Cornelis Blaauwstraat 17",
    "sg:city":"West Graftdijk",
    "sg:orig_category":"Meubelreparatie And -Restauratie",
    "sg:phone":"+31 75 641 1563",
    "sg:postcode":"1486 MR",
    "sg:province":"North Holland",
    "wof:name":"Van Driel Meubelstoffering",
    "wof:placetype":"venue"
},
  "geometry": {"coordinates":[4.796781,52.554653],"type":"Point"}
}