{
  "type": "Feature",
  "properties": {
    "addr:full":"Prins Bernhardstraat 11 Raamsdonksveer Noord-Brabant 4941 GH",
    "addr:housenumber":"11",
    "addr:postcode":"4941 gh",
    "addr:street":"Prins Bernhardstraat",
    "iso:country":"NL",
    "sg:address":"Prins Bernhardstraat 11",
    "sg:city":"Raamsdonksveer",
    "sg:orig_category":"Artsen And Specialisten",
    "sg:phone":"+31 162 512 444",
    "sg:postcode":"4941 GH",
    "sg:province":"Noord-Brabant",
    "wof:name":"Artspraktijk Maas Bv",
    "wof:placetype":"venue"
},
  "geometry": {"coordinates":[4.874919,51.695328],"type":"Point"}
}