{
  "type": "Feature",
  "properties": {
    "addr:full":"Grote Kerk 12 Vlijmen North Brabant 5251 AA",
    "addr:housenumber":"12",
    "addr:postcode":"5251 aa",
    "addr:street":"Grote Kerk",
    "iso:country":"NL",
    "sg:address":"Grote Kerk 12",
    "sg:city":"Vlijmen",
    "sg:orig_category":"Loodgieterswerk, Verwarming And Sanitaire Installaties",
    "sg:phone":"+31 73 511 3345",
    "sg:postcode":"5251 AA",
    "sg:province":"North Brabant",
    "wof:name":"Gebroeders Libregts",
    "wof:placetype":"venue"
},
  "geometry": {"coordinates":[5.225762,51.693962],"type":"Point"}
}