{
  "type": "Feature",
  "properties": {
    "addr:full":"Domstraat 60 Nijkerkerveen Gelderland 3864 PR",
    "addr:housenumber":"60",
    "addr:postcode":"3864 pr",
    "addr:street":"Domstraat;Gelderland",
    "iso:country":"NL",
    "sg:address":"Domstraat 60",
    "sg:city":"Nijkerkerveen",
    "sg:orig_category":"Goederenvervoer Over De Weg",
    "sg:phone":"+31 33 257 1459",
    "sg:postcode":"3864 PR",
    "sg:province":"Gelderland",
    "wof:name":"Handels- En Transportbedrijf Mostert & Van De Weg",
    "wof:placetype":"venue"
},
  "geometry": {"coordinates":[5.448618,52.199543],"type":"Point"}
}