{
  "type": "Feature",
  "properties": {
    "addr:full":"St Jorisstr 58 Beesel Limburg 5954 AP",
    "addr:housenumber":"58",
    "addr:postcode":"5954 ap",
    "iso:country":"NL",
    "sg:address":"St Jorisstr 58",
    "sg:city":"Beesel",
    "sg:orig_category":"Veiligheidsuitrusting En -Kleding",
    "sg:phone":"+31 77 476 9500",
    "sg:postcode":"5954 AP",
    "sg:province":"Limburg",
    "wof:name":"Forto Bv",
    "wof:placetype":"venue"
},
  "geometry": {"coordinates":[6.047567,51.280125],"type":"Point"}
}