{
  "type": "Feature",
  "properties": {
    "addr:full":"Jan Tinbergenlaan 105 Berkel-Enschot Noord-Brabant 5056 WE",
    "addr:housenumber":"105",
    "addr:postcode":"5056 we",
    "addr:street":"Jan Tinbergenlaan",
    "iso:country":"NL",
    "sg:address":"Jan Tinbergenlaan 105",
    "sg:city":"Berkel-Enschot",
    "sg:orig_category":"Bedrijfs- And Managementsconsultants",
    "sg:phone":"+31 13 533 5357",
    "sg:postcode":"5056 WE",
    "sg:province":"Noord-Brabant",
    "wof:name":"Hoes En Associes Bv",
    "wof:placetype":"venue"
},
  "geometry": {"coordinates":[5.151184,51.585266],"type":"Point"}
}