{
  "type": "Feature",
  "properties": {
    "iso:country":"NL",
    "sg:address":"Duitslandlaan 9",
    "sg:city":"Heemskerk",
    "sg:orig_category":"Bloemen And Planten",
    "sg:phone":"+31 251 233 244",
    "sg:postcode":"1965 BC",
    "sg:province":"British Columbia",
    "wof:name":"Bloemisterij-Siertuincentrum Olaf De Ruyter",
    "wof:placetype":"venue"
},
  "geometry": {"coordinates":[-126.555511,54.485668],"type":"Point"}
}