{
  "type": "Feature",
  "properties": {
    "addr:full":"Gevers Deynootweg 990/63 'S Gravenhage Zuid-Holland 2586 BZ",
    "addr:housenumber":"990 / 63",
    "addr:postcode":"2586 bz",
    "addr:street":"Gevers Deynootweg;' S",
    "iso:country":"NL",
    "sg:address":"Gevers Deynootweg 990/63",
    "sg:city":"'S Gravenhage",
    "sg:classifiers":[
        {
            "category":"Shopping",
            "subcategory":"Gifts & Souvenirs",
            "type":"Retail Goods"
        }
    ],
    "sg:phone":"+31 70 354 6128",
    "sg:postcode":"2586 BZ",
    "sg:province":"Zuid-Holland",
    "sg:tags":[
        "geschenken"
    ],
    "wof:name":"Limetree And Hamilton",
    "wof:placetype":"venue"
},
  "geometry": {"coordinates":[4.284147,52.114307],"type":"Point"}
}