{
  "type": "Feature",
  "properties": {
    "addr:full":"Cardanuslaan 33 Doorwerth Gelderland 6865 HJ",
    "addr:housenumber":"33",
    "addr:postcode":"6865 hj",
    "addr:street":"Cardanuslaan;Gelderland",
    "iso:country":"NL",
    "sg:address":"Cardanuslaan 33",
    "sg:city":"Doorwerth",
    "sg:orig_category":"Architecten",
    "sg:phone":"+31 26 339 0606",
    "sg:postcode":"6865 HJ",
    "sg:province":"Gelderland",
    "wof:name":"De Noord Architekten Bv",
    "wof:placetype":"venue"
},
  "geometry": {"coordinates":[5.811587,51.974442],"type":"Point"}
}