{
  "type": "Feature",
  "properties": {
    "iso:country":"NL",
    "sg:address":"Galliersweg 59",
    "sg:city":"Oss",
    "sg:orig_category":"Glaszetten",
    "sg:phone":"+31 412 627 701",
    "sg:postcode":"5342 PN",
    "sg:province":"Noord-Brabant",
    "wof:name":"Beekmans Glasko",
    "wof:placetype":"venue"
},
  "geometry": {"coordinates":[-77.235214,38.312599],"type":"Point"}
}