{
  "type": "Feature",
  "properties": {
    "addr:full":"Eikepage 21 Meppel Drenthe 7943 RV",
    "addr:housenumber":"21",
    "addr:postcode":"7943 rv",
    "addr:street":"Eikepage",
    "iso:country":"NL",
    "sg:address":"Eikepage 21",
    "sg:city":"Meppel",
    "sg:orig_category":"Fotoreportages",
    "sg:phone":"+31 522 443 675",
    "sg:postcode":"7943 RV",
    "sg:province":"Drenthe",
    "wof:name":"Hagedoorn, Anja",
    "wof:placetype":"venue"
},
  "geometry": {"coordinates":[6.224495,52.698471],"type":"Point"}
}