{
  "type": "Feature",
  "properties": {
    "iso:country":"NL",
    "sg:address":"Flevowg 72",
    "sg:city":"Zeewolde",
    "sg:orig_category":"Peuterspeelzalen",
    "sg:phone":"+31 36 522 1761",
    "sg:postcode":"3891 CB",
    "sg:province":"NL.",
    "wof:name":"Klodderpot, De",
    "wof:placetype":"venue"
},
  "geometry": {"coordinates":[5.539454,52.33168],"type":"Point"}
}