{
  "type": "Feature",
  "properties": {
    "addr:full":"Fazantenhof 11 Schagen Noord-Holland 1742 AG",
    "addr:housenumber":"11",
    "addr:postcode":"1742",
    "addr:street":"Fazantenhof",
    "iso:country":"NL",
    "sg:address":"Fazantenhof 11",
    "sg:city":"Schagen",
    "sg:orig_category":"Public Relationbureaus",
    "sg:phone":"+31 224 214 199",
    "sg:postcode":"1742 AG",
    "sg:province":"Noord-Holland",
    "wof:name":"Pharmail",
    "wof:placetype":"venue"
},
  "geometry": {"coordinates":[4.788343,52.785591],"type":"Point"}
}