{
  "type": "Feature",
  "properties": {
    "addr:full":"J C V Hattumwg 5 Amstelveen North Holland 1187 ZN",
    "addr:housenumber":"5",
    "addr:postcode":"1187 zn",
    "addr:street":"J;V Hattumwg",
    "iso:country":"NL",
    "sg:address":"J C V Hattumwg 5",
    "sg:city":"Amstelveen",
    "sg:orig_category":"Bloemen En Planten",
    "sg:phone":"+31 20 640 9347",
    "sg:postcode":"1187 ZN",
    "sg:province":"North Holland",
    "wof:name":"Verhoef Bv",
    "wof:placetype":"venue"
},
  "geometry": {"coordinates":[4.856945,52.303444],"type":"Point"}
}