{
  "type": "Feature",
  "properties": {
    "iso:country":"NL",
    "sg:address":"Haven 4",
    "sg:city":"Goor",
    "sg:orig_category":"Kunstmest - Fabrieken En Groothandel",
    "sg:phone":"+31 547 283 338",
    "sg:postcode":"7471 LV",
    "sg:province":"Overijssel",
    "sg:website":"http://www.triferto.org",
    "wof:name":"Triferto",
    "wof:placetype":"venue"
},
  "geometry": {"coordinates":[6.597822,52.227024],"type":"Point"}
}