{
  "type": "Feature",
  "properties": {
    "addr:full":"Kerkbuurt 151 Sliedrecht Zuid-Holland 3361 BG",
    "addr:housenumber":"151",
    "addr:postcode":"3361",
    "addr:street":"Kerkbuurt",
    "iso:country":"NL",
    "sg:address":"Kerkbuurt 151",
    "sg:city":"Sliedrecht",
    "sg:orig_category":"Makelaars En Adviseurs Onroerende Goederen",
    "sg:phone":"+31 184 412 711",
    "sg:postcode":"3361 BG",
    "sg:province":"Zuid-Holland",
    "sg:website":"http://www.vanderaa.nl",
    "wof:name":"Aa Bv, Van Der",
    "wof:placetype":"venue"
},
  "geometry": {"coordinates":[4.770486,51.823063],"type":"Point"}
}