{
  "type": "Feature",
  "properties": {
    "addr:full":"Min Talmaln 1 Ryswyk Zh South Holland 2285 EB",
    "addr:housenumber":"1;zh",
    "addr:postcode":"2285 eb",
    "addr:street":"Talmaln",
    "iso:country":"NL",
    "sg:address":"Min Talmaln 1",
    "sg:city":"Ryswyk Zh",
    "sg:orig_category":"Fietsen En Bromfietsen",
    "sg:phone":"+31 70 394 1470",
    "sg:postcode":"2285 EB",
    "sg:province":"South Holland",
    "wof:name":"Ruiten Fietsen, Van",
    "wof:placetype":"venue"
},
  "geometry": {"coordinates":[4.32436,52.037251],"type":"Point"}
}