{
  "type": "Feature",
  "properties": {
    "addr:full":"Oldenzaalsestr 60 Losser Overijssel 7581 AW",
    "addr:housenumber":"60",
    "addr:postcode":"7581 aw",
    "addr:street":"Oldenzaalsestr",
    "iso:country":"NL",
    "sg:address":"Oldenzaalsestr 60",
    "sg:city":"Losser",
    "sg:orig_category":"Verzekeringen - Verzekeringskantoren",
    "sg:phone":"+31 53 538 1853",
    "sg:postcode":"7581 AW",
    "sg:province":"Overijssel",
    "wof:name":"Mulder",
    "wof:placetype":"venue"
},
  "geometry": {"coordinates":[6.998935,52.265762],"type":"Point"}
}