{
  "type": "Feature",
  "properties": {
    "iso:country":"NL",
    "sg:address":"Terwoldseweg 6",
    "sg:city":"Apeldoorn",
    "sg:orig_category":"Bloemen And Planten",
    "sg:phone":"+31 55 366 5936",
    "sg:postcode":"7323 RB",
    "sg:province":"Gelderland",
    "wof:name":"Vof H. Albers",
    "wof:placetype":"venue"
},
  "geometry": {"coordinates":[6.001571,52.228432],"type":"Point"}
}