{
  "type": "Feature",
  "properties": {
    "addr:full":"Windmolen 104 Wateringen Zuid-Holland 2291 KT",
    "addr:housenumber":"104",
    "addr:postcode":"2291 kt",
    "addr:street":"Windmolen",
    "iso:country":"NL",
    "sg:address":"Windmolen 104",
    "sg:city":"Wateringen",
    "sg:orig_category":"Metaalwerken",
    "sg:phone":"+31 174 297 848",
    "sg:postcode":"2291 KT",
    "sg:province":"Zuid-Holland",
    "wof:name":"F.G. Van Der Scheer",
    "wof:placetype":"venue"
},
  "geometry": {"coordinates":[4.27274,52.020088],"type":"Point"}
}