{
  "type": "Feature",
  "properties": {
    "iso:country":"NL",
    "sg:address":"Lindengracht 95",
    "sg:city":"Amsterdam",
    "sg:classifiers":[
        {
            "category":"Bars & Pubs",
            "type":"Food & Drink"
        }
    ],
    "sg:phone":"+31 20 622 2716",
    "sg:postcode":"1015 KD",
    "sg:province":"Noord-Holland",
    "wof:name":"Restaurant Vandenberg",
    "wof:placetype":"venue"
},
  "geometry": {"coordinates":[4.884658,52.380009],"type":"Point"}
}