{
  "type": "Feature",
  "properties": {
    "addr:full":"Beekstr 52 Geleen Limburg 6166 CC",
    "addr:housenumber":"52",
    "addr:postcode":"6166 cc",
    "addr:street":"Beekstr",
    "iso:country":"NL",
    "sg:address":"Beekstr 52",
    "sg:city":"Geleen",
    "sg:orig_category":"Antiquiteiten",
    "sg:phone":"+31 46 474 4486",
    "sg:postcode":"6166 CC",
    "sg:province":"Limburg",
    "wof:name":"Antiek Galerie",
    "wof:placetype":"venue"
},
  "geometry": {"coordinates":[5.845991,50.970722],"type":"Point"}
}