{
  "type": "Feature",
  "properties": {
    "iso:country":"NL",
    "sg:address":"Herderinnenpad 22",
    "sg:city":"Amersfoort",
    "sg:orig_category":"Adviesbureaus Bedrijfsorganisatie",
    "sg:phone":"+31 33 489 0413",
    "sg:postcode":"3813 NK",
    "sg:province":"Utrecht",
    "wof:name":"Pamacee",
    "wof:placetype":"venue"
},
  "geometry": {"coordinates":[5.39436,52.172668],"type":"Point"}
}