{
  "type": "Feature",
  "properties": {
    "addr:full":"Hazenstr 3 Amsterdam North Holland 1016 SM",
    "addr:housenumber":"3",
    "addr:postcode":"1016 sm",
    "addr:street":"Hazenstr",
    "iso:country":"NL",
    "sg:address":"Hazenstr 3",
    "sg:city":"Amsterdam",
    "sg:orig_category":"Hoeden",
    "sg:phone":"+31 20 624 7385",
    "sg:postcode":"1016 SM",
    "sg:province":"North Holland",
    "wof:name":"Ans Wesseling",
    "wof:placetype":"venue"
},
  "geometry": {"coordinates":[4.879862,52.370945],"type":"Point"}
}