{
  "type": "Feature",
  "properties": {
    "addr:full":"Burg De Boerstr 25 Assendelft Noord-Holland 1566 KB",
    "addr:housenumber":"25",
    "addr:postcode":"1566 kb",
    "iso:country":"NL",
    "sg:address":"Burg De Boerstr 25",
    "sg:city":"Assendelft",
    "sg:orig_category":"Vertalers",
    "sg:phone":"+31 75 622 4455",
    "sg:postcode":"1566 KB",
    "sg:province":"Noord-Holland",
    "wof:name":"Jagtman-Leegwater, Y",
    "wof:placetype":"venue"
},
  "geometry": {"coordinates":[4.761157,52.492413],"type":"Point"}
}