{
  "type": "Feature",
  "properties": {
    "addr:full":"Baanhoek 182 Sliedrecht Zuid-Holland 3361 GN",
    "addr:housenumber":"182",
    "addr:postcode":"3361 gn",
    "addr:street":"Baanhoek",
    "iso:country":"NL",
    "sg:address":"Baanhoek 182",
    "sg:city":"Sliedrecht",
    "sg:orig_category":"Autokeuringen",
    "sg:phone":"+31 184 493 888",
    "sg:postcode":"3361 GN",
    "sg:province":"Zuid-Holland",
    "wof:name":"Teus Vlot Diesel Marine Bv",
    "wof:placetype":"venue"
},
  "geometry": {"coordinates":[4.748025,51.823677],"type":"Point"}
}