{
  "type": "Feature",
  "properties": {
    "iso:country":"NL",
    "sg:address":"Weverij 7",
    "sg:city":"Amstelveen",
    "sg:orig_category":"Loodgieterswerk, Verwarming And Sanitaire Installaties",
    "sg:phone":"+31 20 647 0081",
    "sg:postcode":"1185 ZE",
    "sg:province":"Noord-Holland",
    "wof:name":"Abb Flakt Service Bv",
    "wof:placetype":"venue"
},
  "geometry": {"coordinates":[4.83992,52.290218],"type":"Point"}
}