{
  "type": "Feature",
  "properties": {
    "addr:full":"Copernicusstraat 35 Amsterdam Noord-Holland 1098 JD",
    "addr:housenumber":"35",
    "addr:postcode":"1098 jd",
    "addr:street":"Copernicusstraat",
    "iso:country":"NL",
    "sg:address":"Copernicusstraat 35",
    "sg:city":"Amsterdam",
    "sg:orig_category":"Partycatering And -Organisatie",
    "sg:phone":"+31 20 665 9919",
    "sg:postcode":"1098 JD",
    "sg:province":"Noord-Holland",
    "wof:name":"Kaatje",
    "wof:placetype":"venue"
},
  "geometry": {"coordinates":[4.936769,52.35479],"type":"Point"}
}