{
  "type": "Feature",
  "properties": {
    "addr:full":"Voorstr 222 Dordrecht Zuid-Holland 3311 ET",
    "addr:housenumber":"222",
    "addr:postcode":"3311 et",
    "iso:country":"NL",
    "sg:address":"Voorstr 222",
    "sg:city":"Dordrecht",
    "sg:orig_category":"Schoenen",
    "sg:phone":"+31 78 613 5400",
    "sg:postcode":"3311 ET",
    "sg:province":"Zuid-Holland",
    "wof:name":"Govers",
    "wof:placetype":"venue"
},
  "geometry": {"coordinates":[4.669135,51.815449],"type":"Point"}
}