{
  "type": "Feature",
  "properties": {
    "addr:full":"Besterdring 163A Tilburg Noord-Brabant 5014 HK",
    "addr:housenumber":"163a",
    "addr:postcode":"5014 hk",
    "addr:street":"Besterdring",
    "iso:country":"NL",
    "sg:address":"Besterdring 163A",
    "sg:city":"Tilburg",
    "sg:orig_category":"Juweliers",
    "sg:phone":"+31 13 536 2430",
    "sg:postcode":"5014 HK",
    "sg:province":"Noord-Brabant",
    "wof:name":"Adrie Pasztjerik",
    "wof:placetype":"venue"
},
  "geometry": {"coordinates":[5.090648,51.563461],"type":"Point"}
}