{
  "type": "Feature",
  "properties": {
    "addr:full":"De Werken 2 Steenbergen Nb Noord-Brabant 4651 CE",
    "addr:housenumber":"2",
    "addr:postcode":"4651 ce",
    "addr:street":"De Werken",
    "iso:country":"NL",
    "sg:address":"De Werken 2",
    "sg:city":"Steenbergen Nb",
    "sg:orig_category":"Artsen And Specialisten",
    "sg:phone":"+31 167 563 060",
    "sg:postcode":"4651 CE",
    "sg:province":"Noord-Brabant",
    "wof:name":"A.J.H.M. Mannaerts",
    "wof:placetype":"venue"
},
  "geometry": {"coordinates":[4.314628,51.584534],"type":"Point"}
}