{
  "type": "Feature",
  "properties": {
    "iso:country":"NL",
    "sg:address":"Wulpstr 14",
    "sg:city":"Maurik",
    "sg:orig_category":"Administratie- En Boekhoudkantoren",
    "sg:phone":"+31 344 693 070",
    "sg:postcode":"4021 EW",
    "sg:province":"Gelderland",
    "wof:name":"As",
    "wof:placetype":"venue"
},
  "geometry": {"coordinates":[5.427046,51.959423],"type":"Point"}
}