{
  "type": "Feature",
  "properties": {
    "addr:full":"Pioentuin 15 Bergschenhoek South Holland 2662 DB",
    "addr:housenumber":"15",
    "addr:postcode":"2662 db",
    "addr:street":"Pioentuin",
    "iso:country":"NL",
    "sg:address":"Pioentuin 15",
    "sg:city":"Bergschenhoek",
    "sg:orig_category":"Kappers",
    "sg:phone":"+31 10 524 8769",
    "sg:postcode":"2662 DB",
    "sg:province":"South Holland",
    "wof:name":"Kappersvisie",
    "wof:placetype":"venue"
},
  "geometry": {"coordinates":[4.4884090424,51.9860992432],"type":"Point"}
}