{
  "type": "Feature",
  "properties": {
    "addr:full":"Jonker Fransstraat 69A Rotterdam Zuid-Holland 3031 AN",
    "addr:housenumber":"69a",
    "addr:postcode":"3031 an",
    "addr:street":"Jonker Fransstraat",
    "iso:country":"NL",
    "sg:address":"Jonker Fransstraat 69A",
    "sg:city":"Rotterdam",
    "sg:orig_category":"Gespecialiseerde Voeding",
    "sg:phone":"+31 10 280 9080",
    "sg:postcode":"3031 AN",
    "sg:province":"Zuid-Holland",
    "wof:name":"Novianti",
    "wof:placetype":"venue"
},
  "geometry": {"coordinates":[4.486472,51.926804],"type":"Point"}
}