{
  "type": "Feature",
  "properties": {
    "iso:country":"NL",
    "sg:address":"Jonker Fransstraat 69A",
    "sg:city":"Rotterdam",
    "sg:orig_category":"Gespecialiseerde Voeding",
    "sg:phone":"+31 10 280 9080",
    "sg:postcode":"3031 AN",
    "sg:province":"Zuid-Holland",
    "wof:name":"Novianti",
    "wof:placetype":"venue"
},
  "geometry": {"coordinates":[4.486472,51.926804],"type":"Point"}
}