{
  "type": "Feature",
  "properties": {
    "iso:country":"NL",
    "sg:address":"1E Oosterparkstr 97Hs",
    "sg:city":"Amsterdam",
    "sg:orig_category":"Fotojournalisten Freelance",
    "sg:phone":"+31 20 692 1922",
    "sg:postcode":"1091 GW",
    "sg:province":"North Holland",
    "wof:name":"Wallrafen, Hannes",
    "wof:placetype":"venue"
},
  "geometry": {"coordinates":[4.910262,52.356365],"type":"Point"}
}