{
  "type": "Feature",
  "properties": {
    "addr:full":"Knsm Ln 240 Amsterdam Noord-Holland 1019 LM",
    "addr:housenumber":"240",
    "addr:postcode":"1019 lm",
    "addr:street":"Knsm Ln",
    "iso:country":"NL",
    "sg:address":"Knsm Ln 240",
    "sg:city":"Amsterdam",
    "sg:orig_category":"Goudsmeden En Zilversmeden",
    "sg:phone":"+31 20 420 4604",
    "sg:postcode":"1019 LM",
    "sg:province":"Noord-Holland",
    "wof:name":"Phool Chand",
    "wof:placetype":"venue"
},
  "geometry": {"coordinates":[4.939354,52.376839],"type":"Point"}
}