{
  "type": "Feature",
  "properties": {
    "iso:country":"NL",
    "sg:address":"Mentanaln 4",
    "sg:city":"Oudenbosch",
    "sg:orig_category":"Verzekeringen - Verzekeringskantoren",
    "sg:phone":"+31 165 330 535",
    "sg:postcode":"4731 DV",
    "sg:province":"North Brabant",
    "wof:name":"Rademakers",
    "wof:placetype":"venue"
},
  "geometry": {"coordinates":[4.547747,51.590508],"type":"Point"}
}