{
  "type": "Feature",
  "properties": {
    "addr:full":"M. Van Heemskerckstraat 41 Heemskerk Noord-Holland 1964 EC",
    "addr:housenumber":"41",
    "addr:postcode":"1964 ec",
    "addr:street":"M. Van Heemskerckstraat",
    "iso:country":"NL",
    "sg:address":"M. Van Heemskerckstraat 41",
    "sg:city":"Heemskerk",
    "sg:orig_category":"Politie",
    "sg:phone":"+31 900 8844",
    "sg:postcode":"1964 EC",
    "sg:province":"Noord-Holland",
    "wof:name":"Politie Kennemerland",
    "wof:placetype":"venue"
},
  "geometry": {"coordinates":[4.66925,52.506588],"type":"Point"}
}