{
  "type": "Feature",
  "properties": {
    "iso:country":"NL",
    "sg:address":"Teteringsedk 89H",
    "sg:city":"Breda",
    "sg:orig_category":"Grafisch Ontwerpers",
    "sg:phone":"+31 76 515 4400",
    "sg:postcode":"4817 MB",
    "sg:province":"North Brabant",
    "wof:name":"Frames Eleven Int Bv",
    "wof:placetype":"venue"
},
  "geometry": {"coordinates":[4.796399,51.593719],"type":"Point"}
}