{
  "type": "Feature",
  "properties": {
    "addr:full":"Stationsplein 2 D Leeuwarden Friesland 8911  A",
    "addr:housenumber":"2 d;8911 a",
    "addr:street":"Stationsplein",
    "iso:country":"NL",
    "sg:address":"Stationsplein 2 D",
    "sg:city":"Leeuwarden",
    "sg:orig_category":"Boekenuitgeverijen",
    "sg:phone":"+31 58 212 8256",
    "sg:postcode":"8911  A",
    "sg:province":"Friesland",
    "wof:name":"Bruna",
    "wof:placetype":"venue"
},
  "geometry": {"coordinates":[5.7932100296,53.1964988708],"type":"Point"}
}