{
  "type": "Feature",
  "properties": {
    "addr:full":"Frans Halsstraat 28 Vlijmen North Brabant 5251 NL",
    "addr:housenumber":"28",
    "addr:postcode":"5251 nl",
    "addr:street":"Frans Halsstraat",
    "iso:country":"NL",
    "sg:address":"Frans Halsstraat 28",
    "sg:city":"Vlijmen",
    "sg:orig_category":"Metaalwerken",
    "sg:phone":"+31 73 511 7062",
    "sg:postcode":"5251 NL",
    "sg:province":"North Brabant",
    "wof:name":"R.C.H. Stok",
    "wof:placetype":"venue"
},
  "geometry": {"coordinates":[5.199169,51.690212],"type":"Point"}
}