{
  "type": "Feature",
  "properties": {
    "addr:full":"Dammerkd 8 Ankeveen Noord-Holland 1244 NS",
    "addr:housenumber":"8",
    "addr:postcode":"1244 ns",
    "addr:street":"Dammerkd",
    "iso:country":"NL",
    "sg:address":"Dammerkd 8",
    "sg:city":"Ankeveen",
    "sg:orig_category":"Onderwijsmateriaal",
    "sg:phone":"+31 35 656 2856",
    "sg:postcode":"1244 NS",
    "sg:province":"Noord-Holland",
    "wof:name":"Ankersmit",
    "wof:placetype":"venue"
},
  "geometry": {"coordinates":[5.098394,52.265591],"type":"Point"}
}