{
  "type": "Feature",
  "properties": {
    "addr:full":"Nieuwenhuysstraat 57 Hulsberg Limburg 6336 XV",
    "addr:housenumber":"57",
    "addr:postcode":"6336 xv",
    "addr:street":"Nieuwenhuysstraat",
    "iso:country":"NL",
    "sg:address":"Nieuwenhuysstraat 57",
    "sg:city":"Hulsberg",
    "sg:orig_category":"Verhuur Voertuigen Behalve Auto'S",
    "sg:phone":"+31 45 405 1644",
    "sg:postcode":"6336 XV",
    "sg:province":"Limburg",
    "wof:name":"G.C.L. Orbons",
    "wof:placetype":"venue"
},
  "geometry": {"coordinates":[5.844087,50.904572],"type":"Point"}
}