{
  "type": "Feature",
  "properties": {
    "iso:country":"NL",
    "sg:address":"Lange Groenendaal 49",
    "sg:city":"Gouda",
    "sg:orig_category":"Verlichting And Huishoudartikelen",
    "sg:phone":"+31 182 514 089",
    "sg:postcode":"2801 LR",
    "sg:province":"Zuid-Holland",
    "wof:name":"Prik Interieur Verlichting",
    "wof:placetype":"venue"
},
  "geometry": {"coordinates":[4.708681,52.01088],"type":"Point"}
}