{
  "type": "Feature",
  "properties": {
    "addr:full":"Gasthuisstraat 1 C Barneveld Gelderland 3771 HE",
    "addr:housenumber":"1 c",
    "addr:postcode":"3771 he",
    "addr:street":"Gasthuisstraat;Gelderland",
    "iso:country":"NL",
    "sg:address":"Gasthuisstraat 1 C",
    "sg:city":"Barneveld",
    "sg:orig_category":"Werving And Selectie Van Tijdelijk Personeel And Uitzendkantoren",
    "sg:phone":"+31 342 421 882",
    "sg:postcode":"3771 HE",
    "sg:province":"Gelderland",
    "wof:name":"Interim Personnel",
    "wof:placetype":"venue"
},
  "geometry": {"coordinates":[5.5834431648,52.1405906677],"type":"Point"}
}