{
  "type": "Feature",
  "properties": {
    "addr:full":"Leptonenwg 6 Utrecht Utrecht 3542 CJ",
    "addr:housenumber":"6",
    "addr:postcode":"3542 cj",
    "addr:street":"Leptonenwg",
    "iso:country":"NL",
    "sg:address":"Leptonenwg 6",
    "sg:city":"Utrecht",
    "sg:orig_category":"Autosloperijen En Autodemontagebedrijven",
    "sg:phone":"+31 30 241 4428",
    "sg:postcode":"3542 CJ",
    "sg:province":"Utrecht",
    "wof:name":"Utrecht",
    "wof:placetype":"venue"
},
  "geometry": {"coordinates":[5.061827,52.117687],"type":"Point"}
}