{
  "type": "Feature",
  "properties": {
    "addr:full":"Merseywg 10 Botlek Rt Zuid-Holland 3197 KG",
    "addr:housenumber":"10",
    "addr:postcode":"rt;3197 kg",
    "addr:street":"Merseywg",
    "iso:country":"NL",
    "sg:address":"Merseywg 10",
    "sg:city":"Botlek Rt",
    "sg:orig_category":"Onderhoudswerken",
    "sg:phone":"+31 181 292 683",
    "sg:postcode":"3197 KG",
    "sg:province":"Zuid-Holland",
    "wof:name":"Pro-I Vof",
    "wof:placetype":"venue"
},
  "geometry": {"coordinates":[4.257352,51.886299],"type":"Point"}
}