{
  "type": "Feature",
  "properties": {
    "addr:full":"Vroomshoopseweg 14 Den Ham Ov Overijssel 7683 RL",
    "addr:housenumber":"14",
    "addr:postcode":"ov;7683 rl",
    "addr:street":"Vroomshoopseweg",
    "iso:country":"NL",
    "sg:address":"Vroomshoopseweg 14",
    "sg:city":"Den Ham Ov",
    "sg:classifiers":[
        {
            "category":"Bakery",
            "type":"Food & Drink"
        }
    ],
    "sg:phone":"+31 546 671 397",
    "sg:postcode":"7683 RL",
    "sg:province":"Overijssel",
    "sg:tags":[
        "brood",
        "banket"
    ],
    "wof:name":"Vof Jansen",
    "wof:placetype":"venue"
},
  "geometry": {"coordinates":[6.496274,52.462387],"type":"Point"}
}