{
  "type": "Feature",
  "properties": {
    "iso:country":"NL",
    "sg:address":"Hoogstr 38",
    "sg:city":"Harlingen",
    "sg:orig_category":"Loodgieters",
    "sg:phone":"+31 517 412 936",
    "sg:postcode":"8861 AH",
    "sg:province":"Provincie Friesland",
    "wof:name":"Boersma",
    "wof:placetype":"venue"
},
  "geometry": {"coordinates":[5.423233,53.17635],"type":"Point"}
}