{
  "type": "Feature",
  "properties": {
    "addr:full":"Van Diemenstraat 308 Amsterdam Noord-Holland 1013 CR",
    "addr:housenumber":"308;1013",
    "addr:postcode":"cr",
    "addr:street":"Van Diemenstraat",
    "iso:country":"NL",
    "sg:address":"Van Diemenstraat 308",
    "sg:city":"Amsterdam",
    "sg:orig_category":"Diverse Grafische Activiteiten",
    "sg:phone":"+31 20 626 2416",
    "sg:postcode":"1013 CR",
    "sg:province":"Noord-Holland",
    "wof:name":"Dpplus Digital Prepress Bv",
    "wof:placetype":"venue"
},
  "geometry": {"coordinates":[4.887043,52.390285],"type":"Point"}
}