{
  "type": "Feature",
  "properties": {
    "addr:full":"Ladonkseweg 4 Boxtel North Brabant 5281 RN",
    "addr:housenumber":"4",
    "addr:postcode":"5281 rn",
    "addr:street":"Ladonkseweg",
    "iso:country":"NL",
    "sg:address":"Ladonkseweg 4",
    "sg:city":"Boxtel",
    "sg:orig_category":"Metaalbekleding And -Behandeling",
    "sg:phone":"+31 411 682 980",
    "sg:postcode":"5281 RN",
    "sg:province":"North Brabant",
    "wof:name":"Vdl Technics Bv",
    "wof:placetype":"venue"
},
  "geometry": {"coordinates":[5.31242,51.584892],"type":"Point"}
}