{
  "type": "Feature",
  "properties": {
    "addr:full":"F De Veyestr 3 Maastricht Limburg 6221 AB",
    "addr:housenumber":"3",
    "addr:postcode":"6221 ab",
    "addr:street":"F;Veyestr",
    "iso:country":"NL",
    "sg:address":"F De Veyestr 3",
    "sg:city":"Maastricht",
    "sg:orig_category":"Makelaars En Adviseurs Onroerende Goederen",
    "sg:phone":"+31 43 321 1025",
    "sg:postcode":"6221 AB",
    "sg:province":"Limburg",
    "wof:name":"Kan, M Van",
    "wof:placetype":"venue"
},
  "geometry": {"coordinates":[5.70527,50.850399],"type":"Point"}
}