{
  "type": "Feature",
  "properties": {
    "addr:full":"Langestraat 52 'S Gravenzande Zuid-Holland 2691 BH",
    "addr:housenumber":"52",
    "addr:postcode":"2691 bh",
    "addr:street":"Langestraat;' S",
    "iso:country":"NL",
    "sg:address":"Langestraat 52",
    "sg:city":"'S Gravenzande",
    "sg:orig_category":"Meubelzaken, Woning- And Keukeninrichting",
    "sg:phone":"+31 174 422 335",
    "sg:postcode":"2691 BH",
    "sg:province":"Zuid-Holland",
    "wof:name":"W. Verheij Woning- & Projektinrichting",
    "wof:placetype":"venue"
},
  "geometry": {"coordinates":[4.160997,52.003471],"type":"Point"}
}