{
  "type": "Feature",
  "properties": {
    "iso:country":"NL",
    "sg:address":"C Huygensstr 11",
    "sg:city":"Deventer",
    "sg:orig_category":"Kappers",
    "sg:phone":"+31 570 611 857",
    "sg:postcode":"7412 MD",
    "sg:province":"NL.08",
    "wof:name":"Liz",
    "wof:placetype":"venue"
},
  "geometry": {"coordinates":[6.142105,52.266937],"type":"Point"}
}