{
  "type": "Feature",
  "properties": {
    "iso:country":"NL",
    "sg:address":"Kreeftstr 1",
    "sg:city":"Zaandijk",
    "sg:orig_category":"Margarine, Olie En Vet - Industrie",
    "sg:phone":"+31 75 627 8400",
    "sg:postcode":"1544 CK",
    "sg:province":"Noord-Holland",
    "sg:website":"http://www.karlshamns.com",
    "wof:name":"Karlshamns",
    "wof:placetype":"venue"
},
  "geometry": {"coordinates":[4.807245,52.477245],"type":"Point"}
}