{
  "type": "Feature",
  "properties": {
    "addr:full":"De Kluis 20 Heeze Noord-Brabant 5591 KE",
    "addr:housenumber":"20",
    "addr:postcode":"5591 ke",
    "addr:street":"De Kluis",
    "iso:country":"NL",
    "sg:address":"De Kluis 20",
    "sg:city":"Heeze",
    "sg:orig_category":"Kampeerterreinen",
    "sg:phone":"+31 40 226 4900",
    "sg:postcode":"5591 KE",
    "sg:province":"Noord-Brabant",
    "wof:name":"De Kluis",
    "wof:placetype":"venue"
},
  "geometry": {"coordinates":[5.5886697769,51.3692779541],"type":"Point"}
}