{
  "type": "Feature",
  "properties": {
    "addr:full":"Loopuytpark 1 Den Helder North Holland 1786 AD",
    "addr:housenumber":"1",
    "addr:postcode":"1786 ad",
    "addr:street":"Loopuytpark",
    "iso:country":"NL",
    "sg:address":"Loopuytpark 1",
    "sg:city":"Den Helder",
    "sg:orig_category":"Zuivelproducten",
    "sg:phone":"+31 223 641 596",
    "sg:postcode":"1786 AD",
    "sg:province":"North Holland",
    "wof:name":"R J Groet Kaasshop 'T Hoekje",
    "wof:placetype":"venue"
},
  "geometry": {"coordinates":[4.753605,52.897358],"type":"Point"}
}