{
  "type": "Feature",
  "properties": {
    "addr:full":"Archimedesbaan 7 Nieuwegein Utrecht 3439 ME",
    "addr:housenumber":"7",
    "addr:postcode":"3439",
    "addr:street":"Archimedesbaan",
    "iso:country":"NL",
    "sg:address":"Archimedesbaan 7",
    "sg:city":"Nieuwegein",
    "sg:orig_category":"Ingenieursbureaus",
    "sg:phone":"+31 30 602 8175",
    "sg:postcode":"3439 ME",
    "sg:province":"Utrecht",
    "wof:name":"Fugro Bv",
    "wof:placetype":"venue"
},
  "geometry": {"coordinates":[5.104774,52.035583],"type":"Point"}
}