{
  "type": "Feature",
  "properties": {
    "addr:full":"Lange Putstraat 15 'S Hertogenbosch Noord-Brabant 5211 KN",
    "addr:housenumber":"15",
    "addr:postcode":"5211 kn",
    "addr:street":"Lange Putstraat;' S",
    "iso:country":"NL",
    "sg:address":"Lange Putstraat 15",
    "sg:city":"'S Hertogenbosch",
    "sg:orig_category":"Kunst And Kunstenaarsbenodigdheden",
    "sg:phone":"+31 73 612 8581",
    "sg:postcode":"5211 KN",
    "sg:province":"Noord-Brabant",
    "wof:name":"In Druk",
    "wof:placetype":"venue"
},
  "geometry": {"coordinates":[5.306067,51.686935],"type":"Point"}
}