{
  "type": "Feature",
  "properties": {
    "addr:full":"Gele Rijders Plein 29/2 Arnhem Gelderland 6811 AP",
    "addr:housenumber":"29 / 2",
    "addr:postcode":"6811 ap",
    "addr:street":"Gele Rijders Plein",
    "iso:country":"NL",
    "sg:address":"Gele Rijders Plein 29/2",
    "sg:city":"Arnhem",
    "sg:orig_category":"Loodgieterswerk, Verwarming And Sanitaire Installaties",
    "sg:phone":"+31 26 446 2463",
    "sg:postcode":"6811 AP",
    "sg:province":"Gelderland",
    "wof:name":"Joop Reinders Onderhoud",
    "wof:placetype":"venue"
},
  "geometry": {"coordinates":[5.908239,51.983742],"type":"Point"}
}