{
  "type": "Feature",
  "properties": {
    "addr:full":"V Ostadestr 45E Amsterdam North Holland 1072 SN",
    "addr:housenumber":"45e",
    "addr:postcode":"1072 sn",
    "addr:street":"Ostadestr",
    "iso:country":"NL",
    "sg:address":"V Ostadestr 45E",
    "sg:city":"Amsterdam",
    "sg:orig_category":"Verenigingen En Stichtingen",
    "sg:phone":"+31 20 670 4062",
    "sg:postcode":"1072 SN",
    "sg:province":"North Holland",
    "wof:name":"Komitee Marokkanen Voor Mensenrechten",
    "wof:placetype":"venue"
},
  "geometry": {"coordinates":[4.89067,52.354012],"type":"Point"}
}