{
  "type": "Feature",
  "properties": {
    "addr:full":"Parallelweg Zuid 33 Boxtel North Brabant 5281 LB",
    "addr:housenumber":"33",
    "addr:postcode":"5281 lb",
    "addr:street":"Parallelweg Zuid",
    "iso:country":"NL",
    "sg:address":"Parallelweg Zuid 33",
    "sg:city":"Boxtel",
    "sg:orig_category":"Makelaars In Onroerend Goed",
    "sg:phone":"+31 411 686 201",
    "sg:postcode":"5281 LB",
    "sg:province":"North Brabant",
    "wof:name":"Bedrijvencentrum De Baanderije",
    "wof:placetype":"venue"
},
  "geometry": {"coordinates":[5.327142,51.578468],"type":"Point"}
}