{
  "type": "Feature",
  "properties": {
    "addr:full":"St Adriaanstr 12 Goes Ohio 4461 JC",
    "addr:housenumber":"12",
    "addr:postcode":"4461 jc",
    "iso:country":"NL",
    "sg:address":"St Adriaanstr 12",
    "sg:city":"Goes",
    "sg:classifiers":[
        {
            "category":"Shopping",
            "subcategory":"Adult",
            "type":"Retail Goods"
        }
    ],
    "sg:phone":"+31 113 214 152",
    "sg:postcode":"4461 JC",
    "sg:province":"Ohio",
    "sg:tags":[
        "lingerie",
        "en",
        "tricotage"
    ],
    "wof:name":"Weele, I Van De",
    "wof:placetype":"venue"
},
  "geometry": {"coordinates":[-83.914169,39.768833],"type":"Point"}
}