{
  "type": "Feature",
  "properties": {
    "addr:full":"Rosmolen 4 Wijk Bij Duurstede Utrecht 3961 LJ",
    "addr:housenumber":"4",
    "addr:postcode":"3961 lj",
    "addr:street":"Rosmolen",
    "iso:country":"NL",
    "sg:address":"Rosmolen 4",
    "sg:city":"Wijk Bij Duurstede",
    "sg:orig_category":"Autokeuringen",
    "sg:phone":"+31 343 579 096",
    "sg:postcode":"3961 LJ",
    "sg:province":"Utrecht",
    "wof:name":"Steef Ebbers Vof",
    "wof:placetype":"venue"
},
  "geometry": {"coordinates":[5.329522,51.973206],"type":"Point"}
}