{
  "type": "Feature",
  "properties": {
    "addr:full":"Heemradenlaan 101 Apeldoorn Gelderland 7329 BZ",
    "addr:housenumber":"101",
    "addr:postcode":"7329 bz",
    "addr:street":"Heemradenlaan;Gelderland",
    "iso:country":"NL",
    "sg:address":"Heemradenlaan 101",
    "sg:city":"Apeldoorn",
    "sg:orig_category":"Fitnesscentra",
    "sg:phone":"+31 55 543 3265",
    "sg:postcode":"7329 BZ",
    "sg:province":"Gelderland",
    "wof:name":"Ten Tije Fitnesscentra Nederland",
    "wof:placetype":"venue"
},
  "geometry": {"coordinates":[5.991893,52.195744],"type":"Point"}
}