{
  "type": "Feature",
  "properties": {
    "addr:full":"Hooghuisstraat 32 Oss Noord-Brabant 5341 CE",
    "addr:housenumber":"32",
    "addr:postcode":"5341 ce",
    "addr:street":"Hooghuisstraat",
    "iso:country":"NL",
    "sg:address":"Hooghuisstraat 32",
    "sg:city":"Oss",
    "sg:classifiers":[
        {
            "category":"Fast Food",
            "type":"Food & Drink"
        }
    ],
    "sg:phone":"+31 412 634 093",
    "sg:postcode":"5341 CE",
    "sg:province":"Noord-Brabant",
    "sg:tags":[
        "afhaal",
        "restaurant"
    ],
    "wof:name":"Pizzeria Restaurant Piccola",
    "wof:placetype":"venue"
},
  "geometry": {"coordinates":[-77.235214,38.312599],"type":"Point"}
}