{
  "type": "Feature",
  "properties": {
    "addr:full":"Divertimentostr 5 Almere Flevoland 1312 EA",
    "addr:housenumber":"5",
    "addr:postcode":"1312 ea",
    "addr:street":"Divertimentostr;Flevoland",
    "iso:country":"NL",
    "sg:address":"Divertimentostr 5",
    "sg:city":"Almere",
    "sg:orig_category":"Administratie- En Boekhoudkantoren",
    "sg:phone":"+31 36 536 6079",
    "sg:postcode":"1312 EA",
    "sg:province":"Flevoland",
    "wof:name":"Blank",
    "wof:placetype":"venue"
},
  "geometry": {"coordinates":[5.190826,52.374809],"type":"Point"}
}