{
  "type": "Feature",
  "properties": {
    "addr:full":"Gerard Van Dintherstraat 30 Rosmalen Noord-Brabant 5246 EK",
    "addr:housenumber":"30",
    "addr:postcode":"5246 ek",
    "addr:street":"Gerard Van Dintherstraat",
    "iso:country":"NL",
    "sg:address":"Gerard Van Dintherstraat 30",
    "sg:city":"Rosmalen",
    "sg:orig_category":"Bedrijfsinventaris Gh",
    "sg:phone":"+31 73 641 5141",
    "sg:postcode":"5246 EK",
    "sg:province":"Noord-Brabant",
    "wof:name":"Cees Van Roosmalen",
    "wof:placetype":"venue"
},
  "geometry": {"coordinates":[5.345089,51.697403],"type":"Point"}
}