{
  "type": "Feature",
  "properties": {
    "addr:full":"Pr Bernhardstr 67 Asten North Brabant 5721 GB",
    "addr:housenumber":"67",
    "addr:postcode":"5721 gb",
    "iso:country":"NL",
    "sg:address":"Pr Bernhardstr 67",
    "sg:city":"Asten",
    "sg:orig_category":"Meubelen",
    "sg:phone":"+31 493 699 404",
    "sg:postcode":"5721 GB",
    "sg:province":"North Brabant",
    "sg:website":"http://www.dominiowonen.nl",
    "wof:name":"Domo, Il",
    "wof:placetype":"venue"
},
  "geometry": {"coordinates":[5.746616,51.408737],"type":"Point"}
}