{
  "type": "Feature",
  "properties": {
    "addr:full":"Pannenbakkersstr 12 Holten Overijssel 7451 AX",
    "addr:housenumber":"12",
    "addr:postcode":"7451 ax",
    "addr:street":"Pannenbakkersstr",
    "iso:country":"NL",
    "sg:address":"Pannenbakkersstr 12",
    "sg:city":"Holten",
    "sg:orig_category":"Kinderactiviteiten",
    "sg:phone":"+31 548 361 843",
    "sg:postcode":"7451 AX",
    "sg:province":"Overijssel",
    "sg:website":"http://www.theaterfiets.nl",
    "wof:name":"Theaterfiets",
    "wof:placetype":"venue"
},
  "geometry": {"coordinates":[6.429228,52.283401],"type":"Point"}
}