{
  "type": "Feature",
  "properties": {
    "iso:country":"NL",
    "sg:address":"Westeresweg 31",
    "sg:city":"Exloo",
    "sg:orig_category":"Architecten",
    "sg:phone":"+31 591 549 564",
    "sg:postcode":"7875 BC",
    "sg:province":"Drenthe",
    "wof:name":"Adviesbur. Loon- En Aannemingsbedr. H. H",
    "wof:placetype":"venue"
},
  "geometry": {"coordinates":[6.857915,52.880035],"type":"Point"}
}