{
  "type": "Feature",
  "properties": {
    "addr:full":"Scholeksterstr 30 Landsmeer Noord-Holland 1121 EG",
    "addr:housenumber":"30",
    "addr:postcode":"1121 eg",
    "addr:street":"Scholeksterstr",
    "iso:country":"NL",
    "sg:address":"Scholeksterstr 30",
    "sg:city":"Landsmeer",
    "sg:orig_category":"Beeldende Kunstenaars",
    "sg:phone":"+31 20 482 5270",
    "sg:postcode":"1121 EG",
    "sg:province":"Noord-Holland",
    "wof:name":"Oudejans, A",
    "wof:placetype":"venue"
},
  "geometry": {"coordinates":[4.920012,52.430759],"type":"Point"}
}