{
  "type": "Feature",
  "properties": {
    "addr:full":"Wendtsteinwg 16A Marum Groningen 9363 AN",
    "addr:housenumber":"16a",
    "addr:postcode":"9363 an",
    "addr:street":"Wendtsteinwg",
    "iso:country":"NL",
    "sg:address":"Wendtsteinwg 16A",
    "sg:city":"Marum",
    "sg:orig_category":"Makelaars En Adviseurs Onroerende Goederen",
    "sg:phone":"+31 594 643 034",
    "sg:postcode":"9363 AN",
    "sg:province":"Groningen",
    "wof:name":"Laan Vof, Th Van Der",
    "wof:placetype":"venue"
},
  "geometry": {"coordinates":[6.274015,53.146507],"type":"Point"}
}