{
  "type": "Feature",
  "properties": {
    "addr:full":"Serliowg 39 Eindhoven North Brabant 5624 KB",
    "addr:housenumber":"39",
    "addr:postcode":"5624 kb",
    "addr:street":"Serliowg",
    "iso:country":"NL",
    "sg:address":"Serliowg 39",
    "sg:city":"Eindhoven",
    "sg:orig_category":"Verenigingen En Stichtingen",
    "sg:phone":"+31 40 245 0137",
    "sg:postcode":"5624 KB",
    "sg:province":"North Brabant",
    "wof:name":"Nvvh Afd Geldrop-Heeze-Leende",
    "wof:placetype":"venue"
},
  "geometry": {"coordinates":[5.458707,51.467304],"type":"Point"}
}