{
  "type": "Feature",
  "properties": {
    "addr:full":"Oude Molenweg 137 Nijmegen Gelderland 6533 WH",
    "addr:housenumber":"137",
    "addr:postcode":"6533 wh",
    "addr:street":"Oude Molenweg;Gelderland",
    "iso:country":"NL",
    "sg:address":"Oude Molenweg 137",
    "sg:city":"Nijmegen",
    "sg:orig_category":"Antiekzaken",
    "sg:phone":"+31 24 355 5849",
    "sg:postcode":"6533 WH",
    "sg:province":"Gelderland",
    "wof:name":"Gerard Deco",
    "wof:placetype":"venue"
},
  "geometry": {"coordinates":[5.849899,51.817711],"type":"Point"}
}