{
  "type": "Feature",
  "properties": {
    "iso:country":"NL",
    "sg:address":"Langelermaatwg 131",
    "sg:city":"Hengelo Ov",
    "sg:orig_category":"Koffie- En Theehuizen",
    "sg:phone":"+31 74 291 9939",
    "sg:postcode":"7553 JG",
    "sg:province":"Overijssel",
    "wof:name":"Dostlar",
    "wof:placetype":"venue"
},
  "geometry": {"coordinates":[6.792829,52.254982],"type":"Point"}
}