{
  "type": "Feature",
  "properties": {
    "addr:full":"Goudenregenstraat 241 'S Gravenhage South Holland 2565 ET",
    "addr:housenumber":"241 '",
    "addr:postcode":"2565 et",
    "addr:street":"Goudenregenstraat",
    "iso:country":"NL",
    "sg:address":"Goudenregenstraat 241",
    "sg:city":"'S Gravenhage",
    "sg:classifiers":[
        {
            "category":"Fast Food",
            "type":"Food & Drink"
        }
    ],
    "sg:phone":"+31 70 360 6732",
    "sg:postcode":"2565 ET",
    "sg:province":"South Holland",
    "sg:tags":[
        "afhaal",
        "restaurant"
    ],
    "wof:name":"Chinees Indonesisch Restaurant Gouden Bloemen",
    "wof:placetype":"venue"
},
  "geometry": {"coordinates":[4.263018,52.07777],"type":"Point"}
}