{
  "type": "Feature",
  "properties": {
    "addr:full":"F Halshage 20 Nieuwegein Utrecht 3438 JG",
    "addr:housenumber":"20",
    "addr:postcode":"3438 jg",
    "addr:street":"F Halshage",
    "iso:country":"NL",
    "sg:address":"F Halshage 20",
    "sg:city":"Nieuwegein",
    "sg:orig_category":"Onderhoudswerken",
    "sg:phone":"+31 6 53942505",
    "sg:postcode":"3438 JG",
    "sg:province":"Utrecht",
    "wof:name":"Os, R Van",
    "wof:placetype":"venue"
},
  "geometry": {"coordinates":[5.084753,52.049316],"type":"Point"}
}