{
  "type": "Feature",
  "properties": {
    "addr:full":"Deventerstr 176 Apeldoorn Gelderland 7321 CE",
    "addr:housenumber":"176",
    "addr:postcode":"7321 ce",
    "addr:street":"Gelderland",
    "iso:country":"NL",
    "sg:address":"Deventerstr 176",
    "sg:city":"Apeldoorn",
    "sg:orig_category":"Loodgieters",
    "sg:phone":"+31 55 366 7641",
    "sg:postcode":"7321 CE",
    "sg:province":"Gelderland",
    "wof:name":"Schut Bv, Installatieburo",
    "wof:placetype":"venue"
},
  "geometry": {"coordinates":[5.983609,52.214081],"type":"Point"}
}