{
  "type": "Feature",
  "properties": {
    "iso:country":"NL",
    "sg:address":"Tuinstraat 14",
    "sg:city":"Waalwijk",
    "sg:orig_category":"Diverse Bedrijfsinstallaties Gh",
    "sg:phone":"+31 416 334 677",
    "sg:postcode":"5144 NT",
    "sg:province":"Noord-Brabant",
    "wof:name":"S.T.A. Luchtbehandeling Vof",
    "wof:placetype":"venue"
},
  "geometry": {"coordinates":[5.051545,51.681049],"type":"Point"}
}