{
  "type": "Feature",
  "properties": {
    "addr:full":"Diessenseweg 15 Hilvarenbeek Noord-Brabant 5081 AE",
    "addr:housenumber":"15",
    "addr:postcode":"5081 ae",
    "addr:street":"Diessenseweg",
    "iso:country":"NL",
    "sg:address":"Diessenseweg 15",
    "sg:city":"Hilvarenbeek",
    "sg:orig_category":"Schoenen Fab",
    "sg:phone":"+31 13 505 1348",
    "sg:postcode":"5081 AE",
    "sg:province":"Noord-Brabant",
    "wof:name":"Schoenfabriek Jawo",
    "wof:placetype":"venue"
},
  "geometry": {"coordinates":[5.138758,51.484528],"type":"Point"}
}