{
  "type": "Feature",
  "properties": {
    "addr:full":"De Schoof 15 Hendrik Ido Ambacht Zuid-Holland 3341 EA",
    "addr:housenumber":"15",
    "addr:postcode":"ido ambacht;3341 ea",
    "addr:street":"De Schoof",
    "iso:country":"NL",
    "sg:address":"De Schoof 15",
    "sg:city":"Hendrik Ido Ambacht",
    "sg:orig_category":"Zuivelproducten",
    "sg:phone":"+31 78 681 8353",
    "sg:postcode":"3341 EA",
    "sg:province":"Zuid-Holland",
    "wof:name":"Kaasbest Muilwijk",
    "wof:placetype":"venue"
},
  "geometry": {"coordinates":[4.645003,51.849522],"type":"Point"}
}