{
  "type": "Feature",
  "properties": {
    "addr:full":"Amsterdamsestraatweg 418 Utrecht Utrecht 3551 CX",
    "addr:housenumber":"418",
    "addr:postcode":"3551 cx",
    "addr:street":"Amsterdamsestraatweg",
    "iso:country":"NL",
    "sg:address":"Amsterdamsestraatweg 418",
    "sg:city":"Utrecht",
    "sg:orig_category":"Opticiens",
    "sg:phone":"+31 30 243 1583",
    "sg:postcode":"3551 CX",
    "sg:province":"Utrecht",
    "wof:name":"Miedema Brillen Vof",
    "wof:placetype":"venue"
},
  "geometry": {"coordinates":[5.0935211182,52.1042633057],"type":"Point"}
}