{
  "type": "Feature",
  "properties": {
    "iso:country":"NL",
    "sg:address":"Kerkstr 10",
    "sg:city":"Ravenstein",
    "sg:orig_category":"Autorijscholen",
    "sg:phone":"+31 486 416 059",
    "sg:postcode":"5371 PW",
    "sg:province":"North Brabant",
    "wof:name":"Summeren, Willy Van",
    "wof:placetype":"venue"
},
  "geometry": {"coordinates":[5.672083,51.774361],"type":"Point"}
}