{
  "type": "Feature",
  "properties": {
    "addr:full":"Watersnip 64 Berkel En Rodenrys Zuid-Holland 2651 ZB",
    "addr:housenumber":"64",
    "addr:postcode":"2651 zb",
    "addr:street":"Watersnip;Berkel",
    "iso:country":"NL",
    "sg:address":"Watersnip 64",
    "sg:city":"Berkel En Rodenrys",
    "sg:orig_category":"Huishoudelijke Apparaten En Artikelen",
    "sg:phone":"+31 10 511 2216",
    "sg:postcode":"2651 ZB",
    "sg:province":"Zuid-Holland",
    "wof:name":"Az",
    "wof:placetype":"venue"
},
  "geometry": {"coordinates":[4.469221,51.98666],"type":"Point"}
}