{
  "type": "Feature",
  "properties": {
    "addr:full":"Muiderslotweg 10 Haarlem Noord-Holland 2026 AP",
    "addr:housenumber":"10",
    "addr:postcode":"2026 ap",
    "addr:street":"Muiderslotweg",
    "iso:country":"NL",
    "sg:address":"Muiderslotweg 10",
    "sg:city":"Haarlem",
    "sg:orig_category":"Kinderopvang Behalve Thuis",
    "sg:phone":"+31 23 537 0240",
    "sg:postcode":"2026 AP",
    "sg:province":"Noord-Holland",
    "wof:name":"Kinderdagverblijf Het Vosje",
    "wof:placetype":"venue"
},
  "geometry": {"coordinates":[4.649036,52.419338],"type":"Point"}
}