{
  "type": "Feature",
  "properties": {
    "addr:full":"De Greverije 2 Noordwolde Fr Friesland 8391 LM",
    "addr:housenumber":"2",
    "addr:postcode":"8391 lm",
    "addr:street":"De Greverije",
    "iso:country":"NL",
    "sg:address":"De Greverije 2",
    "sg:city":"Noordwolde Fr",
    "sg:orig_category":"Opticiens",
    "sg:phone":"+31 561 431 100",
    "sg:postcode":"8391 LM",
    "sg:province":"Friesland",
    "wof:name":"Optiek De Brillenkoker",
    "wof:placetype":"venue"
},
  "geometry": {"coordinates":[6.1352138519,52.8898658752],"type":"Point"}
}