{
  "type": "Feature",
  "properties": {
    "iso:country":"NL",
    "sg:address":"Laan Van Vollenhove 1457",
    "sg:city":"Zeist",
    "sg:classifiers":[
        {
            "category":"Education",
            "subcategory":"Preschool",
            "type":"Public Place"
        }
    ],
    "sg:phone":"+31 30 695 9033",
    "sg:postcode":"3706 EW",
    "sg:province":"Utrecht",
    "sg:tags":[
        "kleuteronderwijs",
        "basis-"
    ],
    "wof:name":"Openbare Basisschool Op Dreef",
    "wof:placetype":"venue"
},
  "geometry": {"coordinates":[5.23188,52.102402],"type":"Point"}
}