{
  "type": "Feature",
  "properties": {
    "addr:full":"Bredaseweg 385 Tilburg North Brabant 5037 LD",
    "addr:housenumber":"385",
    "addr:postcode":"5037 ld",
    "addr:street":"Bredaseweg",
    "iso:country":"NL",
    "sg:address":"Bredaseweg 385",
    "sg:city":"Tilburg",
    "sg:orig_category":"Diverse Grafische Activiteiten",
    "sg:phone":"+31 13 468 0257",
    "sg:postcode":"5037 LD",
    "sg:province":"North Brabant",
    "wof:name":"Beelenkamp Media Bv",
    "wof:placetype":"venue"
},
  "geometry": {"coordinates":[5.047767,51.557602],"type":"Point"}
}