{
  "type": "Feature",
  "properties": {
    "iso:country":"NL",
    "sg:address":"L Wal 72",
    "sg:city":"Arnhem",
    "sg:orig_category":"Voetbalverenigingen",
    "sg:phone":"+31 26 361 5803",
    "sg:postcode":"6826 NE",
    "sg:province":"Gelderland",
    "wof:name":"Elsweide",
    "wof:placetype":"venue"
},
  "geometry": {"coordinates":[5.94306,51.98344],"type":"Point"}
}