{
  "type": "Feature",
  "properties": {
    "iso:country":"NL",
    "sg:address":"Dokter W Nijestraat 75",
    "sg:city":"Spaarndam",
    "sg:classifiers":[
        {
            "category":"Fast Food",
            "type":"Food & Drink"
        }
    ],
    "sg:phone":"+31 23 539 1571",
    "sg:postcode":"2064 XB",
    "sg:province":"Noord-Holland",
    "sg:tags":[
        "afhaal",
        "restaurant"
    ],
    "wof:name":"Afhaalcentrum Nieuw Azie",
    "wof:placetype":"venue"
},
  "geometry": {"coordinates":[4.687825,52.414383],"type":"Point"}
}