{
  "type": "Feature",
  "properties": {
    "addr:full":"Molenstraat 134 Roosendaal Noord-Brabant 4701 JW",
    "addr:housenumber":"134",
    "addr:postcode":"4701 jw",
    "addr:street":"Molenstraat",
    "iso:country":"NL",
    "sg:address":"Molenstraat 134",
    "sg:city":"Roosendaal",
    "sg:orig_category":"Verzekeringen",
    "sg:phone":"+31 165 523 939",
    "sg:postcode":"4701 JW",
    "sg:province":"Noord-Brabant",
    "wof:name":"Hertoghs & Lute Assurantien",
    "wof:placetype":"venue"
},
  "geometry": {"coordinates":[4.459481,51.534386],"type":"Point"}
}