{
  "type": "Feature",
  "properties": {
    "iso:country":"NL",
    "sg:address":"Zijp 3",
    "sg:city":"Boekel",
    "sg:orig_category":"Houten Verpakkingen Fab",
    "sg:phone":"+31 492 326 129",
    "sg:postcode":"5427 HK",
    "sg:province":"Noord-Brabant",
    "wof:name":"J. V.D. Aa",
    "wof:placetype":"venue"
},
  "geometry": {"coordinates":[5.693766,51.608334],"type":"Point"}
}