{
  "type": "Feature",
  "properties": {
    "addr:full":"Ryksstrwg 26 Twello Gelderland 7391 MR",
    "addr:housenumber":"26",
    "addr:postcode":"7391 mr",
    "addr:street":"Ryksstrwg;Gelderland",
    "iso:country":"NL",
    "sg:address":"Ryksstrwg 26",
    "sg:city":"Twello",
    "sg:orig_category":"Verenigingen En Stichtingen",
    "sg:phone":"+31 571 273 453",
    "sg:postcode":"7391 MR",
    "sg:province":"Gelderland",
    "wof:name":"Bewonersver Twello",
    "wof:placetype":"venue"
},
  "geometry": {"coordinates":[6.106505,52.238346],"type":"Point"}
}