{
  "type": "Feature",
  "properties": {
    "iso:country":"NL",
    "sg:address":"Molslaan 43",
    "sg:city":"Delft",
    "sg:orig_category":"Werving And Selectie Van Tijdelijk Personeel And Uitzendkantoren",
    "sg:phone":"+31 15 214 0043",
    "sg:postcode":"2611 RJ",
    "sg:province":"South Holland",
    "wof:name":"Barendse Bv",
    "wof:placetype":"venue"
},
  "geometry": {"coordinates":[4.3627309799,52.0106582642],"type":"Point"}
}