{
  "type": "Feature",
  "properties": {
    "addr:full":"Bedryvenwg 9 Oirschot North Brabant 5688 XH",
    "addr:housenumber":"9",
    "addr:postcode":"5688 xh",
    "addr:street":"Bedryvenwg",
    "iso:country":"NL",
    "sg:address":"Bedryvenwg 9",
    "sg:city":"Oirschot",
    "sg:orig_category":"Pijpleidingen - Installatie En Onderhoud",
    "sg:phone":"+31 499 578 147",
    "sg:postcode":"5688 XH",
    "sg:province":"North Brabant",
    "sg:website":"http://www.bjservices.com",
    "wof:name":"Bj Services",
    "wof:placetype":"venue"
},
  "geometry": {"coordinates":[5.331207,51.502773],"type":"Point"}
}