{
  "type": "Feature",
  "properties": {
    "iso:country":"NL",
    "sg:address":"Stetse 6",
    "sg:city":"Grootebroek",
    "sg:orig_category":"Loodgieterswerk, Verwarming And Sanitaire Installaties",
    "sg:phone":"+31 228 512 211",
    "sg:postcode":"1613 BV",
    "sg:province":"North Holland",
    "wof:name":"G.H. Van Cappelleveen",
    "wof:placetype":"venue"
},
  "geometry": {"coordinates":[5.229545,52.687668],"type":"Point"}
}