{
  "type": "Feature",
  "properties": {
    "iso:country":"NL",
    "sg:address":"Molenstr 30",
    "sg:city":"Groede",
    "sg:orig_category":"On- Offshore",
    "sg:phone":"+31 117 372 207",
    "sg:postcode":"4503 BB",
    "sg:province":"Zeeland",
    "wof:name":"Drilltec",
    "wof:placetype":"venue"
},
  "geometry": {"coordinates":[3.503908,51.379364],"type":"Point"}
}