{
  "type": "Feature",
  "properties": {
    "addr:full":"Leembaan 39 Deurne North Brabant 5753 CW",
    "addr:housenumber":"39",
    "addr:postcode":"5753 cw",
    "addr:street":"Leembaan",
    "iso:country":"NL",
    "sg:address":"Leembaan 39",
    "sg:city":"Deurne",
    "sg:orig_category":"Loodgieterswerk, Verwarming And Sanitaire Installaties",
    "sg:phone":"+31 493 310 769",
    "sg:postcode":"5753 CW",
    "sg:province":"North Brabant",
    "wof:name":"Vof Giesbers-Poels",
    "wof:placetype":"venue"
},
  "geometry": {"coordinates":[5.795959,51.44994],"type":"Point"}
}