{
  "type": "Feature",
  "properties": {
    "addr:full":"Dorpsstr 170 Scherpenzeel Gld Utrecht 3925 KG",
    "addr:housenumber":"170",
    "addr:postcode":"3925 kg",
    "addr:street":"Gld",
    "iso:country":"NL",
    "sg:address":"Dorpsstr 170",
    "sg:city":"Scherpenzeel Gld",
    "sg:orig_category":"Kappers",
    "sg:phone":"+31 33 277 2979",
    "sg:postcode":"3925 KG",
    "sg:province":"Utrecht",
    "wof:name":"Hooge Huys, 'T",
    "wof:placetype":"venue"
},
  "geometry": {"coordinates":[5.4903278351,52.0793838501],"type":"Point"}
}