{
  "type": "Feature",
  "properties": {
    "iso:country":"NL",
    "sg:address":"A Plesmanln 11",
    "sg:city":"Sassenheim",
    "sg:classifiers":[
        {
            "category":"Professional",
            "subcategory":"Accounting & Tax Preparation",
            "type":"Services"
        }
    ],
    "sg:phone":"+31 252 220 825",
    "sg:postcode":"2171 RE",
    "sg:province":"Zuid-Holland",
    "sg:tags":[
        "accountant",
        "en",
        "-kantoren",
        "register-"
    ],
    "wof:name":"Pias",
    "wof:placetype":"venue"
},
  "geometry": {"coordinates":[4.507912,52.219517],"type":"Point"}
}