{
  "type": "Feature",
  "properties": {
    "addr:full":"De Lasso Z 3F Roelofarendsveen South Holland 2371 EV",
    "addr:housenumber":"3f",
    "addr:postcode":"2371 ev",
    "addr:street":"De Lasso Z",
    "iso:country":"NL",
    "sg:address":"De Lasso Z 3F",
    "sg:city":"Roelofarendsveen",
    "sg:orig_category":"Elektrotechnische Installatiebureaus",
    "sg:phone":"+31 71 331 1140",
    "sg:postcode":"2371 EV",
    "sg:province":"South Holland",
    "wof:name":"Berge Henegouwen Bv, Van",
    "wof:placetype":"venue"
},
  "geometry": {"coordinates":[4.622066,52.203625],"type":"Point"}
}