{
  "type": "Feature",
  "properties": {
    "addr:full":"Beulakerweg 55 Giethoorn Overijssel 8355 AB",
    "addr:housenumber":"55",
    "addr:postcode":"8355 ab",
    "addr:street":"Beulakerweg",
    "iso:country":"NL",
    "sg:address":"Beulakerweg 55",
    "sg:city":"Giethoorn",
    "sg:orig_category":"Binnenvaart",
    "sg:phone":"+31 521 361 372",
    "sg:postcode":"8355 AB",
    "sg:province":"Overijssel",
    "wof:name":"Hotel De Harmonie",
    "wof:placetype":"venue"
},
  "geometry": {"coordinates":[6.081577,52.751724],"type":"Point"}
}