{
  "type": "Feature",
  "properties": {
    "addr:full":"L Noordstr 4 Middelburg Zeeland 4331 CD",
    "addr:housenumber":"4",
    "addr:postcode":"4331 cd",
    "iso:country":"NL",
    "sg:address":"L Noordstr 4",
    "sg:city":"Middelburg",
    "sg:orig_category":"Bruidskleding",
    "sg:phone":"+31 118 611 174",
    "sg:postcode":"4331 CD",
    "sg:province":"Zeeland",
    "wof:name":"Bbk",
    "wof:placetype":"venue"
},
  "geometry": {"coordinates":[3.610909,51.499561],"type":"Point"}
}