{
  "type": "Feature",
  "properties": {
    "addr:full":"Raadhuispln 31 Soest Utrecht 3762 AV",
    "addr:housenumber":"31",
    "addr:postcode":"3762 av",
    "addr:street":"Raadhuispln",
    "iso:country":"NL",
    "sg:address":"Raadhuispln 31",
    "sg:city":"Soest",
    "sg:orig_category":"Politie",
    "sg:phone":"+31 900 8844",
    "sg:postcode":"3762 AV",
    "sg:province":"Utrecht",
    "wof:name":"Politie",
    "wof:placetype":"venue"
},
  "geometry": {"coordinates":[5.29316,52.176445],"type":"Point"}
}