{
  "type": "Feature",
  "properties": {
    "addr:full":"Rondstaai 16 Grevenbicht BE.05 6127 AD",
    "addr:housenumber":"16;be.05",
    "addr:postcode":"6127 ad",
    "addr:street":"Rondstaai",
    "iso:country":"NL",
    "sg:address":"Rondstaai 16",
    "sg:city":"Grevenbicht",
    "sg:orig_category":"Juweliers",
    "sg:phone":"+31 46 485 8455",
    "sg:postcode":"6127 AD",
    "sg:province":"BE.05",
    "wof:name":"A. Ruber Sieraden",
    "wof:placetype":"venue"
},
  "geometry": {"coordinates":[5.773059,51.040405],"type":"Point"}
}