{
  "type": "Feature",
  "properties": {
    "addr:full":"Torenstr 19 Scheemda Groningen 9679 BN",
    "addr:housenumber":"19",
    "addr:postcode":"9679 bn",
    "addr:street":"Torenstr",
    "iso:country":"NL",
    "sg:address":"Torenstr 19",
    "sg:city":"Scheemda",
    "sg:orig_category":"Schilders",
    "sg:phone":"+31 597 594 256",
    "sg:postcode":"9679 BN",
    "sg:province":"Groningen",
    "wof:name":"Vastgoed Schilderwerken",
    "wof:placetype":"venue"
},
  "geometry": {"coordinates":[6.971502,53.177059],"type":"Point"}
}