{
  "type": "Feature",
  "properties": {
    "addr:full":"Plesmanstr 32 Veenendaal Utrecht 3905 KZ",
    "addr:housenumber":"32",
    "addr:postcode":"3905",
    "addr:street":"Plesmanstr",
    "iso:country":"NL",
    "sg:address":"Plesmanstr 32",
    "sg:city":"Veenendaal",
    "sg:classifiers":[
        {
            "category":"Home & Garden",
            "subcategory":"Hardware",
            "type":"Retail Goods"
        }
    ],
    "sg:phone":"+31 318 550 200",
    "sg:postcode":"3905 KZ",
    "sg:province":"Utrecht",
    "sg:tags":[
        "machine",
        "-",
        "metaalbewerking"
    ],
    "wof:name":"Bendertechn Bv",
    "wof:placetype":"venue"
},
  "geometry": {"coordinates":[5.558249,52.041626],"type":"Point"}
}