{
  "type": "Feature",
  "properties": {
    "iso:country":"NL",
    "sg:address":"De Smalle Zyde 9",
    "sg:city":"Veenendaal",
    "sg:orig_category":"Kunststoffen - Fabrieken En Groothandel",
    "sg:phone":"+31 318 610 500",
    "sg:postcode":"3903 LL",
    "sg:province":"Utrecht",
    "sg:website":"http://www.hidrosystems.nl",
    "wof:name":"Hidrosystems Nederland",
    "wof:placetype":"venue"
},
  "geometry": {"coordinates":[5.559694,52.00967],"type":"Point"}
}