{
  "type": "Feature",
  "properties": {
    "iso:country":"NL",
    "sg:address":"Hoofdstr 263",
    "sg:city":"Sassenheim",
    "sg:orig_category":"Glas, Porselein En Aardewerk",
    "sg:phone":"+31 252 224 500",
    "sg:postcode":"2171 BD",
    "sg:province":"South Holland",
    "sg:website":"http://www.dekoffiekenner.nl",
    "wof:name":"Nieuwkoop Sassenheim, Van",
    "wof:placetype":"venue"
},
  "geometry": {"coordinates":[4.524386,52.228073],"type":"Point"}
}