{
  "type": "Feature",
  "properties": {
    "addr:full":"Radboudwg 23 Rhenen Utrecht 3911 BE",
    "addr:housenumber":"23",
    "addr:postcode":"3911",
    "addr:street":"Radboudwg",
    "iso:country":"NL",
    "sg:address":"Radboudwg 23",
    "sg:city":"Rhenen",
    "sg:orig_category":"Sportverenigingen En Ontspannings- Verenigingen",
    "sg:phone":"+31 317 617 490",
    "sg:postcode":"3911 BE",
    "sg:province":"Utrecht",
    "sg:website":"http://www.aikido-arnhem-jks.nl",
    "wof:name":"Aikido Arnhem, Sticht",
    "wof:placetype":"venue"
},
  "geometry": {"coordinates":[5.581042,51.961246],"type":"Point"}
}