{
  "type": "Feature",
  "properties": {
    "iso:country":"NL",
    "sg:address":"Fagelstr 85",
    "sg:city":"Amsterdam",
    "sg:orig_category":"Beeldende Kunstenaars",
    "sg:phone":"+31 20 684 6317",
    "sg:postcode":"1052 GA",
    "sg:province":"Noord-Holland",
    "wof:name":"Stansfield, E A",
    "wof:placetype":"venue"
},
  "geometry": {"coordinates":[-94.58503,38.350479],"type":"Point"}
}