{
  "type": "Feature",
  "properties": {
    "addr:full":"Nijkerkerkweg 64A Ermelo Gelderland 3853 NX",
    "addr:housenumber":"64a",
    "addr:postcode":"3853 nx",
    "addr:street":"Nijkerkerkweg;Gelderland",
    "iso:country":"NL",
    "sg:address":"Nijkerkerkweg 64A",
    "sg:city":"Ermelo",
    "sg:orig_category":"Kappers",
    "sg:phone":"+31 341 559 058",
    "sg:postcode":"3853 NX",
    "sg:province":"Gelderland",
    "wof:name":"Kapsalon Leyla",
    "wof:placetype":"venue"
},
  "geometry": {"coordinates":[5.5759267807,52.2889595032],"type":"Point"}
}