{
  "type": "Feature",
  "properties": {
    "iso:country":"NL",
    "sg:address":"Burgemeester Smitsstraat 14",
    "sg:city":"Utrecht",
    "sg:orig_category":"Paramedische Behandelingen",
    "sg:phone":"+31 30 289 9498",
    "sg:postcode":"3523 KL",
    "sg:province":"Utrecht",
    "wof:name":"B.W.J.J.La Croix Podotherapie",
    "wof:placetype":"venue"
},
  "geometry": {"coordinates":[5.119501,52.068611],"type":"Point"}
}