{
  "type": "Feature",
  "properties": {
    "addr:full":"Engelbertsstr 8 Zandvoort Noord-Holland 2042 KN",
    "addr:housenumber":"8",
    "addr:postcode":"2042 kn",
    "addr:street":"Engelbertsstr",
    "iso:country":"NL",
    "sg:address":"Engelbertsstr 8",
    "sg:city":"Zandvoort",
    "sg:orig_category":"Administratie- En Boekhoudkantoren",
    "sg:phone":"+31 23 573 6028",
    "sg:postcode":"2042 KN",
    "sg:province":"Noord-Holland",
    "wof:name":"Ham Admn Kantoor, Van Der",
    "wof:placetype":"venue"
},
  "geometry": {"coordinates":[4.526812,52.373032],"type":"Point"}
}