{
  "type": "Feature",
  "properties": {
    "addr:full":"Schiedamsedijk 126 Vlaardingen Zuid-Holland 3134 KK",
    "addr:housenumber":"126",
    "addr:postcode":"3134 kk",
    "addr:street":"Schiedamsedijk",
    "iso:country":"NL",
    "sg:address":"Schiedamsedijk 126",
    "sg:city":"Vlaardingen",
    "sg:orig_category":"Boekhouders",
    "sg:phone":"+31 10 435 7170",
    "sg:postcode":"3134 KK",
    "sg:province":"Zuid-Holland",
    "wof:name":"Administratiekantoor Steenbergen",
    "wof:placetype":"venue"
},
  "geometry": {"coordinates":[4.368622,51.908001],"type":"Point"}
}