{
  "type": "Feature",
  "properties": {
    "addr:full":"Plompertstr 20 Rotterdam Zuid-Holland 3087 BD",
    "addr:housenumber":"20",
    "addr:postcode":"3087 bd",
    "addr:street":"Plompertstr",
    "iso:country":"NL",
    "sg:address":"Plompertstr 20",
    "sg:city":"Rotterdam",
    "sg:orig_category":"Verkoopautomaten",
    "sg:phone":"+31 10 262 1033",
    "sg:postcode":"3087 BD",
    "sg:province":"Zuid-Holland",
    "wof:name":"Acr Automatenexploitatie Bv",
    "wof:placetype":"venue"
},
  "geometry": {"coordinates":[4.462232,51.891396],"type":"Point"}
}