{
  "type": "Feature",
  "properties": {
    "addr:full":"Weerdingerkan Nz 80 Nieuw Weerdinge Drenthe 7831 HG",
    "addr:housenumber":"80",
    "addr:postcode":"7831 hg",
    "addr:street":"Nz;Nieuw Weerdinge",
    "iso:country":"NL",
    "sg:address":"Weerdingerkan Nz 80",
    "sg:city":"Nieuw Weerdinge",
    "sg:orig_category":"Drukkerijen",
    "sg:phone":"+31 591 522 784",
    "sg:postcode":"7831 HG",
    "sg:province":"Drenthe",
    "wof:name":"Abbes Hummel",
    "wof:placetype":"venue"
},
  "geometry": {"coordinates":[6.970731,52.851387],"type":"Point"}
}