{
  "type": "Feature",
  "properties": {
    "addr:full":"Bisschopstr 38 Oldenzaal NL.08 7571 CZ",
    "addr:housenumber":"38;nl.08",
    "addr:postcode":"7571",
    "addr:street":"Bisschopstr",
    "iso:country":"NL",
    "sg:address":"Bisschopstr 38",
    "sg:city":"Oldenzaal",
    "sg:orig_category":"Schoenen",
    "sg:phone":"+31 541 511 498",
    "sg:postcode":"7571 CZ",
    "sg:province":"NL.08",
    "wof:name":"Brummelhuis, Fa H Ten",
    "wof:placetype":"venue"
},
  "geometry": {"coordinates":[6.930481,52.314926],"type":"Point"}
}