{
  "type": "Feature",
  "properties": {
    "addr:full":"Singel 15 Hillegom Zuid-Holland 2182 LS",
    "addr:housenumber":"15",
    "addr:postcode":"2182 ls",
    "addr:street":"Singel",
    "iso:country":"NL",
    "sg:address":"Singel 15",
    "sg:city":"Hillegom",
    "sg:orig_category":"Handelsbemiddeling Textiel And Lederwaren",
    "sg:phone":"+31 252 520 261",
    "sg:postcode":"2182 LS",
    "sg:province":"Zuid-Holland",
    "wof:name":"T. Janssen Agenturen In Betere Woningtex",
    "wof:placetype":"venue"
},
  "geometry": {"coordinates":[4.575619,52.282131],"type":"Point"}
}