{
  "type": "Feature",
  "properties": {
    "addr:full":"Schoterweg 12 Haarlem Noord-Holland 2021 HM",
    "addr:housenumber":"12",
    "addr:postcode":"2021 hm",
    "addr:street":"Schoterweg",
    "iso:country":"NL",
    "sg:address":"Schoterweg 12",
    "sg:city":"Haarlem",
    "sg:orig_category":"Advocaten And Juridische Adviseurs",
    "sg:phone":"+31 23 525 3686",
    "sg:postcode":"2021 HM",
    "sg:province":"Noord-Holland",
    "wof:name":"M.S. Tissingh",
    "wof:placetype":"venue"
},
  "geometry": {"coordinates":[4.640857,52.390442],"type":"Point"}
}