{
  "type": "Feature",
  "properties": {
    "addr:full":"Oude Naarderweg 1 Laren Nh North Holland 1251 BJ",
    "addr:housenumber":"1",
    "addr:postcode":"1251 bj",
    "addr:street":"Oude Naarderweg;Nh North",
    "iso:country":"NL",
    "sg:address":"Oude Naarderweg 1",
    "sg:city":"Laren Nh",
    "sg:orig_category":"Werving And Selectie Van Vast Personeel",
    "sg:phone":"+31 35 531 7382",
    "sg:postcode":"1251 BJ",
    "sg:province":"North Holland",
    "wof:name":"Landman En Partners",
    "wof:placetype":"venue"
},
  "geometry": {"coordinates":[5.2233271599,52.2603111267],"type":"Point"}
}