{
  "type": "Feature",
  "properties": {
    "addr:full":"Nieuwe Tielseweg 189 Tiel Gelderland 4006 BH",
    "addr:housenumber":"189",
    "addr:postcode":"4006 bh",
    "addr:street":"Nieuwe Tielseweg;Gelderland",
    "iso:country":"NL",
    "sg:address":"Nieuwe Tielseweg 189",
    "sg:city":"Tiel",
    "sg:orig_category":"Bloemen And Planten",
    "sg:phone":"+31 344 618 238",
    "sg:postcode":"4006 BH",
    "sg:province":"Gelderland",
    "wof:name":"Floriant",
    "wof:placetype":"venue"
},
  "geometry": {"coordinates":[5.41678,51.879189],"type":"Point"}
}