{
  "type": "Feature",
  "properties": {
    "addr:full":"Meyerspln N 25-27 Rotterdam Zuid-Holland 3053 TE",
    "addr:housenumber":"25-27",
    "addr:postcode":"3053 te",
    "addr:street":"N",
    "iso:country":"NL",
    "sg:address":"Meyerspln N 25-27",
    "sg:city":"Rotterdam",
    "sg:orig_category":"Artsen - Huisartsen",
    "sg:phone":"+31 10 418 4056",
    "sg:postcode":"3053 TE",
    "sg:province":"Zuid-Holland",
    "wof:name":"Hoeven & P Verbruggen-Van Iperen, J C Van Der",
    "wof:placetype":"venue"
},
  "geometry": {"coordinates":[4.466463,51.956417],"type":"Point"}
}