{
  "type": "Feature",
  "properties": {
    "addr:full":"Reymerwg 59 Renkum Gelderland 6871 HB",
    "addr:housenumber":"59",
    "addr:postcode":"6871 hb",
    "addr:street":"Reymerwg;Gelderland",
    "iso:country":"NL",
    "sg:address":"Reymerwg 59",
    "sg:city":"Renkum",
    "sg:orig_category":"Onderhoudswerken",
    "sg:phone":"+31 317 310 126",
    "sg:postcode":"6871 HB",
    "sg:province":"Gelderland",
    "wof:name":"Cees Van Geffen Onderhoudsbedrijf",
    "wof:placetype":"venue"
},
  "geometry": {"coordinates":[5.735993,51.978104],"type":"Point"}
}