{
  "type": "Feature",
  "properties": {
    "addr:full":"Floresstr 15 Haarlem Noord-Holland 2022 BB",
    "addr:housenumber":"15",
    "addr:postcode":"2022 bb",
    "addr:street":"Floresstr",
    "iso:country":"NL",
    "sg:address":"Floresstr 15",
    "sg:city":"Haarlem",
    "sg:orig_category":"Zoetwaren - Fabrieken En Groothandel",
    "sg:phone":"+31 23 525 1738",
    "sg:postcode":"2022 BB",
    "sg:province":"Noord-Holland",
    "wof:name":"Kollerie Bv",
    "wof:placetype":"venue"
},
  "geometry": {"coordinates":[4.645317,52.399166],"type":"Point"}
}