{
  "type": "Feature",
  "properties": {
    "addr:full":"Wilhelminasngl 259 Weert Limburg 6001 GS",
    "addr:housenumber":"259",
    "addr:postcode":"6001 gs",
    "addr:street":"Weert Limburg",
    "iso:country":"NL",
    "sg:address":"Wilhelminasngl 259",
    "sg:city":"Weert",
    "sg:orig_category":"Bedrijfsopleidingen",
    "sg:phone":"+31 495 542 324",
    "sg:postcode":"6001 GS",
    "sg:province":"Limburg",
    "sg:website":"http://www.tryact.nl",
    "wof:name":"Tryact",
    "wof:placetype":"venue"
},
  "geometry": {"coordinates":[5.703781,51.255016],"type":"Point"}
}