{
  "type": "Feature",
  "properties": {
    "addr:full":"Woldstraat 20 Meppel Drenthe 7941 LJ",
    "addr:housenumber":"20",
    "addr:postcode":"7941 lj",
    "addr:street":"Woldstraat",
    "iso:country":"NL",
    "sg:address":"Woldstraat 20",
    "sg:city":"Meppel",
    "sg:classifiers":[
        {
            "category":"Shopping",
            "subcategory":"Gifts & Souvenirs",
            "type":"Retail Goods"
        }
    ],
    "sg:phone":"+31 522 240 942",
    "sg:postcode":"7941 LJ",
    "sg:province":"Drenthe",
    "sg:tags":[
        "geschenken"
    ],
    "wof:name":"Kadoshop Jojo",
    "wof:placetype":"venue"
},
  "geometry": {"coordinates":[6.191996,52.697872],"type":"Point"}
}