{
  "type": "Feature",
  "properties": {
    "addr:full":"Waalbandk 64 Gameren Gelderland 5311 AH",
    "addr:housenumber":"64",
    "addr:postcode":"5311 ah",
    "addr:street":"Waalbandk;Gelderland",
    "iso:country":"NL",
    "sg:address":"Waalbandk 64",
    "sg:city":"Gameren",
    "sg:orig_category":"Bloemen En Planten",
    "sg:phone":"+31 418 561 007",
    "sg:postcode":"5311 AH",
    "sg:province":"Gelderland",
    "wof:name":"Flowers For You",
    "wof:placetype":"venue"
},
  "geometry": {"coordinates":[5.198675,51.803112],"type":"Point"}
}