{
  "type": "Feature",
  "properties": {
    "addr:full":"Paterswg 24 Beverwyk North Holland 1941 BV",
    "addr:housenumber":"24",
    "addr:postcode":"1941 bv",
    "addr:street":"Paterswg;North",
    "iso:country":"NL",
    "sg:address":"Paterswg 24",
    "sg:city":"Beverwyk",
    "sg:orig_category":"Zuivel - Groothandel",
    "sg:phone":"+31 251 211 124",
    "sg:postcode":"1941 BV",
    "sg:province":"North Holland",
    "wof:name":"Dekker, G",
    "wof:placetype":"venue"
},
  "geometry": {"coordinates":[4.656049,52.483383],"type":"Point"}
}