{
  "type": "Feature",
  "properties": {
    "iso:country":"NL",
    "sg:address":"Oudebildtdijk 828",
    "sg:city":"Sint Jacobiparochie",
    "sg:orig_category":"Metaalwerken",
    "sg:phone":"+31 518 491 229",
    "sg:postcode":"9079 ND",
    "sg:province":"Provincie Friesland",
    "wof:name":"F. De Vries",
    "wof:placetype":"venue"
},
  "geometry": {"coordinates":[5.605765,53.288654],"type":"Point"}
}