{
  "type": "Feature",
  "properties": {
    "addr:full":"Hoofschestr 16 Grave Noord-Brabant 5361 EV",
    "addr:housenumber":"16",
    "addr:postcode":"5361 ev",
    "addr:street":"Hoofschestr",
    "iso:country":"NL",
    "sg:address":"Hoofschestr 16",
    "sg:city":"Grave",
    "sg:orig_category":"Juweliers",
    "sg:phone":"+31 486 473 058",
    "sg:postcode":"5361 EV",
    "sg:province":"Noord-Brabant",
    "sg:website":"http://www.degoudenluifel.nl",
    "wof:name":"Gouden Luifel Bv, De",
    "wof:placetype":"venue"
},
  "geometry": {"coordinates":[-92.151741,32.929253],"type":"Point"}
}