{
  "type": "Feature",
  "properties": {
    "addr:full":"Polderwg 28 Oostwold Scheemda Groningen 9682 XS",
    "addr:housenumber":"28",
    "addr:postcode":"9682 xs",
    "addr:street":"Polderwg",
    "iso:country":"NL",
    "sg:address":"Polderwg 28",
    "sg:city":"Oostwold Scheemda",
    "sg:orig_category":"Luchthavens En Vliegvelden",
    "sg:phone":"+31 597 551 490",
    "sg:postcode":"9682 XS",
    "sg:province":"Groningen",
    "wof:name":"Vliegveld Oostwold",
    "wof:placetype":"venue"
},
  "geometry": {"coordinates":[7.049479,53.209351],"type":"Point"}
}