{
  "type": "Feature",
  "properties": {
    "addr:full":"Oranjelaan 6 Harderwijk Gelderland 3844 AA",
    "addr:housenumber":"6",
    "addr:postcode":"3844 aa",
    "addr:street":"Oranjelaan;Gelderland",
    "iso:country":"NL",
    "sg:address":"Oranjelaan 6",
    "sg:city":"Harderwijk",
    "sg:orig_category":"Artsen And Specialisten",
    "sg:phone":"+31 341 416 625",
    "sg:postcode":"3844 AA",
    "sg:province":"Gelderland",
    "wof:name":"J. Slaa",
    "wof:placetype":"venue"
},
  "geometry": {"coordinates":[5.620348,52.334461],"type":"Point"}
}