{
  "type": "Feature",
  "properties": {
    "iso:country":"NL",
    "sg:address":"Middenwg 13",
    "sg:city":"Hoogerheide",
    "sg:orig_category":"Grondboringen En Bronbemalingen",
    "sg:phone":"+31 164 620 334",
    "sg:postcode":"4631 ST",
    "sg:province":"North Brabant",
    "wof:name":"Smet Groundwater Technics Bv",
    "wof:placetype":"venue"
},
  "geometry": {"coordinates":[4.349408,51.42865],"type":"Point"}
}