{
  "type": "Feature",
  "properties": {
    "addr:full":"Castenrayseweg 2 Oirlo Limburg 5808 AG",
    "addr:housenumber":"2",
    "addr:postcode":"5808",
    "addr:street":"Castenrayseweg",
    "iso:country":"NL",
    "sg:address":"Castenrayseweg 2",
    "sg:city":"Oirlo",
    "sg:orig_category":"Pluimveehouderijen",
    "sg:phone":"+31 478 578 600",
    "sg:postcode":"5808 AG",
    "sg:province":"Limburg",
    "wof:name":"P.M.M. Classens",
    "wof:placetype":"venue"
},
  "geometry": {"coordinates":[6.039142,51.505482],"type":"Point"}
}