{
  "type": "Feature",
  "properties": {
    "addr:full":"Vlietskant 43 Leerdam South Holland 4141 CK",
    "addr:housenumber":"43",
    "addr:postcode":"4141 ck",
    "addr:street":"Vlietskant",
    "iso:country":"NL",
    "sg:address":"Vlietskant 43",
    "sg:city":"Leerdam",
    "sg:orig_category":"Herenmodezaken",
    "sg:phone":"+31 345 612 054",
    "sg:postcode":"4141 CK",
    "sg:province":"South Holland",
    "wof:name":"Van Meeuwen Exclusieve Mode",
    "wof:placetype":"venue"
},
  "geometry": {"coordinates":[5.095697,51.892754],"type":"Point"}
}