{
  "type": "Feature",
  "properties": {
    "iso:country":"NL",
    "sg:address":"Aengwirderweg 300",
    "sg:city":"Tjalleberd",
    "sg:orig_category":"Meubelzaken, Woning- And Keukeninrichting",
    "sg:phone":"+31 513 529 477",
    "sg:postcode":"8458 CK",
    "sg:province":"Friesland",
    "wof:name":"Vof Carina Interdecor",
    "wof:placetype":"venue"
},
  "geometry": {"coordinates":[5.94809,52.999481],"type":"Point"}
}