{
  "type": "Feature",
  "properties": {
    "addr:full":"Ryksstrwg 270 Haren Gn Groningen 9752 CL",
    "addr:housenumber":"270",
    "addr:postcode":"9752",
    "iso:country":"NL",
    "sg:address":"Ryksstrwg 270",
    "sg:city":"Haren Gn",
    "sg:orig_category":"Beeldende Kunstenaars",
    "sg:phone":"+31 50 534 3224",
    "sg:postcode":"9752 CL",
    "sg:province":"Groningen",
    "wof:name":"Bert Van Der Wal",
    "wof:placetype":"venue"
},
  "geometry": {"coordinates":[6.60632,53.170658],"type":"Point"}
}