{
  "type": "Feature",
  "properties": {
    "addr:full":"Kerkstraat 9 Doesburg Gelderland 6981 CK",
    "addr:housenumber":"9",
    "addr:postcode":"6981 ck",
    "addr:street":"Kerkstraat;Gelderland",
    "iso:country":"NL",
    "sg:address":"Kerkstraat 9",
    "sg:city":"Doesburg",
    "sg:orig_category":"Opticiens",
    "sg:phone":"+31 313 476 765",
    "sg:postcode":"6981 CK",
    "sg:province":"Gelderland",
    "wof:name":"Hillenaar Optiek",
    "wof:placetype":"venue"
},
  "geometry": {"coordinates":[6.1345968246,52.0146827698],"type":"Point"}
}