{
  "type": "Feature",
  "properties": {
    "addr:full":"Penitentenstr 9C Weert Limburg 6001 VX",
    "addr:housenumber":"9c",
    "addr:postcode":"6001 vx",
    "addr:street":"Penitentenstr",
    "iso:country":"NL",
    "sg:address":"Penitentenstr 9C",
    "sg:city":"Weert",
    "sg:orig_category":"Ziekenvervoer",
    "sg:phone":"+31 495 547 403",
    "sg:postcode":"6001 VX",
    "sg:province":"Limburg",
    "wof:name":"Meldpost Weert Bv",
    "wof:placetype":"venue"
},
  "geometry": {"coordinates":[5.698237,51.255108],"type":"Point"}
}