{
  "type": "Feature",
  "properties": {
    "addr:full":"J Bottemastr 11 Bussum Noord-Holland 1403 TG",
    "addr:housenumber":"11",
    "addr:postcode":"1403 tg",
    "iso:country":"NL",
    "sg:address":"J Bottemastr 11",
    "sg:city":"Bussum",
    "sg:orig_category":"Schilders",
    "sg:phone":"+31 35 694 0431",
    "sg:postcode":"1403 TG",
    "sg:province":"Noord-Holland",
    "wof:name":"Eisenga Meesterschilders Bv",
    "wof:placetype":"venue"
},
  "geometry": {"coordinates":[5.177559,52.266499],"type":"Point"}
}