{
  "type": "Feature",
  "properties": {
    "iso:country":"NL",
    "sg:address":"Zeewg 168",
    "sg:city":"Ymuiden",
    "sg:orig_category":"Mensendieck - Oefentherapeuten",
    "sg:phone":"+31 23 525 1290",
    "sg:postcode":"1971 HG",
    "sg:province":"Noord-Holland",
    "wof:name":"Annelies Van Der Linden",
    "wof:placetype":"venue"
},
  "geometry": {"coordinates":[4.627276,52.455997],"type":"Point"}
}