{
  "type": "Feature",
  "properties": {
    "addr:full":"Wildforsterweg 14 Putten Gelderland 3881 NJ",
    "addr:housenumber":"14",
    "addr:postcode":"3881",
    "addr:street":"Wildforsterweg;Gelderland",
    "iso:country":"NL",
    "sg:address":"Wildforsterweg 14",
    "sg:city":"Putten",
    "sg:orig_category":"Diverse Bedrijfsinstallaties Gh",
    "sg:phone":"+31 577 461 697",
    "sg:postcode":"3881 NJ",
    "sg:province":"Gelderland",
    "wof:name":"M3 Impact Group",
    "wof:placetype":"venue"
},
  "geometry": {"coordinates":[5.660088,52.230953],"type":"Point"}
}