{
  "type": "Feature",
  "properties": {
    "addr:full":"Halve Morgensstraat 15 Berghem North Brabant 5351 NT",
    "addr:housenumber":"15",
    "addr:postcode":"5351 nt",
    "addr:street":"Halve Morgensstraat",
    "iso:country":"NL",
    "sg:address":"Halve Morgensstraat 15",
    "sg:city":"Berghem",
    "sg:orig_category":"Levende Dieren Gh",
    "sg:phone":"+31 412 401 186",
    "sg:postcode":"5351 NT",
    "sg:province":"North Brabant",
    "wof:name":"J. Nelissen Veehandel Export",
    "wof:placetype":"venue"
},
  "geometry": {"coordinates":[5.589625,51.774368],"type":"Point"}
}