{
  "type": "Feature",
  "properties": {
    "addr:full":"Pr Beatrixln 357 Ryswyk Zh Zuid-Holland 2284 AM",
    "addr:housenumber":"357",
    "addr:postcode":"2284",
    "addr:street":"Ryswyk",
    "iso:country":"NL",
    "sg:address":"Pr Beatrixln 357",
    "sg:city":"Ryswyk Zh",
    "sg:orig_category":"Onroerende Goederen",
    "sg:phone":"+31 70 396 3366",
    "sg:postcode":"2284 AM",
    "sg:province":"Zuid-Holland",
    "wof:name":"Mit Group Bv",
    "wof:placetype":"venue"
},
  "geometry": {"coordinates":[4.32436,52.037251],"type":"Point"}
}