{
  "type": "Feature",
  "properties": {
    "addr:full":"P Krugerstr 145-147 Rotterdam Zuid-Holland 3072 GJ",
    "addr:housenumber":"145-147",
    "addr:postcode":"3072 gj",
    "iso:country":"NL",
    "sg:address":"P Krugerstr 145-147",
    "sg:city":"Rotterdam",
    "sg:orig_category":"Wasmachines En Wasdrogers",
    "sg:phone":"+31 10 484 7067",
    "sg:postcode":"3072 GJ",
    "sg:province":"Zuid-Holland",
    "wof:name":"Andr? Witgoed Superstore",
    "wof:placetype":"venue"
},
  "geometry": {"coordinates":[4.497631073,51.8996696472],"type":"Point"}
}