{
  "type": "Feature",
  "properties": {
    "addr:full":"Konynenberg 57A Breda Noord-Brabant 4825 BC",
    "addr:housenumber":"57a",
    "addr:postcode":"4825 bc",
    "addr:street":"Konynenberg",
    "iso:country":"NL",
    "sg:address":"Konynenberg 57A",
    "sg:city":"Breda",
    "sg:classifiers":[
        {
            "category":"Professional",
            "type":"Services"
        }
    ],
    "sg:phone":"+31 76 571 1888",
    "sg:postcode":"4825 BC",
    "sg:province":"Noord-Brabant",
    "sg:tags":[
        "leasing"
    ],
    "wof:name":"Continental Bv",
    "wof:placetype":"venue"
},
  "geometry": {"coordinates":[4.76852,51.611752],"type":"Point"}
}