{
  "type": "Feature",
  "properties": {
    "addr:full":"Rochussenstr 33 Rotterdam Zuid-Holland 3015 EB",
    "addr:housenumber":"33",
    "addr:postcode":"3015 eb",
    "addr:street":"Rochussenstr",
    "iso:country":"NL",
    "sg:address":"Rochussenstr 33",
    "sg:city":"Rotterdam",
    "sg:orig_category":"Journalisten Freelance",
    "sg:phone":"+31 10 436 5798",
    "sg:postcode":"3015 EB",
    "sg:province":"Zuid-Holland",
    "wof:name":"Rusp",
    "wof:placetype":"venue"
},
  "geometry": {"coordinates":[4.470019,51.915436],"type":"Point"}
}