{
  "type": "Feature",
  "properties": {
    "iso:country":"NL",
    "sg:address":"Turfland 58",
    "sg:city":"Lemmer",
    "sg:orig_category":"Fietsen En Bromfietsen",
    "sg:phone":"+31 514 563 664",
    "sg:postcode":"8531 JL",
    "sg:province":"Provincie Friesland",
    "sg:website":"http://www.profile.nl",
    "wof:name":"Profile",
    "wof:placetype":"venue"
},
  "geometry": {"coordinates":[5.706928,52.845833],"type":"Point"}
}