{
  "type": "Feature",
  "properties": {
    "addr:full":"Havenstraat 30 Hilversum Noord-Holland 1211 KM",
    "addr:housenumber":"30",
    "addr:postcode":"1211 km",
    "addr:street":"Havenstraat",
    "iso:country":"NL",
    "sg:address":"Havenstraat 30",
    "sg:city":"Hilversum",
    "sg:orig_category":"Naai- And Breimachines",
    "sg:phone":"+31 35 621 5798",
    "sg:postcode":"1211 KM",
    "sg:province":"Noord-Holland",
    "wof:name":"L G Venecourt",
    "wof:placetype":"venue"
},
  "geometry": {"coordinates":[5.1695,52.228565],"type":"Point"}
}