{
  "type": "Feature",
  "properties": {
    "iso:country":"NL",
    "sg:address":"Eewg 2",
    "sg:city":"Tholen",
    "sg:orig_category":"Bloemen En Planten - Groothandel",
    "sg:phone":"+31 166 604 039",
    "sg:postcode":"4691 PC",
    "sg:province":"Zeeland",
    "wof:name":"Rietkerk Van Broekhoven",
    "wof:placetype":"venue"
},
  "geometry": {"coordinates":[4.218683,51.53566],"type":"Point"}
}