{
  "type": "Feature",
  "properties": {
    "addr:full":"Eeltsjebaes 5 Joure Friesland 8501 RA",
    "addr:housenumber":"5",
    "addr:postcode":"8501 ra",
    "addr:street":"Eeltsjebaes",
    "iso:country":"NL",
    "sg:address":"Eeltsjebaes 5",
    "sg:city":"Joure",
    "sg:orig_category":"Fotopersbureaus",
    "sg:phone":"+31 513 414 068",
    "sg:postcode":"8501 RA",
    "sg:province":"Friesland",
    "wof:name":"Verton, D A",
    "wof:placetype":"venue"
},
  "geometry": {"coordinates":[5.79831,52.972443],"type":"Point"}
}