{
  "type": "Feature",
  "properties": {
    "iso:country":"NL",
    "sg:address":"Herenwg 145",
    "sg:city":"Rynsaterwoude",
    "sg:orig_category":"Kinderopvang",
    "sg:phone":"+31 172 508 391",
    "sg:postcode":"2465 AG",
    "sg:province":"South Holland",
    "wof:name":"Baloe",
    "wof:placetype":"venue"
},
  "geometry": {"coordinates":[4.671006,52.195419],"type":"Point"}
}