{
  "type": "Feature",
  "properties": {
    "addr:full":"Ommelanderwyk 145 Veendam Groningen 9644 TD",
    "addr:housenumber":"145",
    "addr:postcode":"9644 td",
    "addr:street":"Veendam",
    "iso:country":"NL",
    "sg:address":"Ommelanderwyk 145",
    "sg:city":"Veendam",
    "sg:orig_category":"Meubelen",
    "sg:phone":"+31 598 612 476",
    "sg:postcode":"9644 TD",
    "sg:province":"Groningen",
    "wof:name":"Meertens Meubelen",
    "wof:placetype":"venue"
},
  "geometry": {"coordinates":[6.901332,53.091217],"type":"Point"}
}