{
  "type": "Feature",
  "properties": {
    "iso:country":"NL",
    "sg:address":"Loswal 2",
    "sg:city":"Hardenberg",
    "sg:classifiers":[
        {
            "category":"Bus Charters",
            "type":"Transportation"
        }
    ],
    "sg:phone":"+31 523 260 398",
    "sg:postcode":"7772 TT",
    "sg:province":"Overijssel",
    "sg:tags":[
        "caravan"
    ],
    "wof:name":"Reiling",
    "wof:placetype":"venue"
},
  "geometry": {"coordinates":[6.632297,52.558533],"type":"Point"}
}