{
  "type": "Feature",
  "properties": {
    "addr:full":"E D Boer-Van Rijkstr 56 Amsterdam Noord-Holland 1065 GP",
    "addr:housenumber":"56",
    "addr:postcode":"1065 gp",
    "addr:street":"E D Boer-Van Rijkstr",
    "iso:country":"NL",
    "sg:address":"E D Boer-Van Rijkstr 56",
    "sg:city":"Amsterdam",
    "sg:orig_category":"Vertaal- And Tolkenbureaus",
    "sg:phone":"+31 20 615 4207",
    "sg:postcode":"1065 GP",
    "sg:province":"Noord-Holland",
    "wof:name":"Indonesian Translation Service",
    "wof:placetype":"venue"
},
  "geometry": {"coordinates":[4.825785,52.353661],"type":"Point"}
}