{
  "type": "Feature",
  "properties": {
    "addr:full":"Elkerzeesewg 36 Scharendyke Zeeland 4322 NB",
    "addr:housenumber":"36",
    "addr:postcode":"4322 nb",
    "addr:street":"Elkerzeesewg;Zeeland",
    "iso:country":"NL",
    "sg:address":"Elkerzeesewg 36",
    "sg:city":"Scharendyke",
    "sg:orig_category":"Administratie- En Boekhoudkantoren",
    "sg:phone":"+31 111 676 073",
    "sg:postcode":"4322 NB",
    "sg:province":"Zeeland",
    "wof:name":"Docwell",
    "wof:placetype":"venue"
},
  "geometry": {"coordinates":[3.841708,51.731544],"type":"Point"}
}