{
  "type": "Feature",
  "properties": {
    "iso:country":"NL",
    "sg:address":"A J Duymaer Van Twiststr 20",
    "sg:city":"Deventer",
    "sg:orig_category":"Verenigingen En Stichtingen",
    "sg:phone":"+31 570 631 153",
    "sg:postcode":"7413 VX",
    "sg:province":"Overijssel",
    "wof:name":"Atalaya Spaans Cult Genootsch",
    "wof:placetype":"venue"
},
  "geometry": {"coordinates":[6.166227,52.261063],"type":"Point"}
}