{
  "type": "Feature",
  "properties": {
    "iso:country":"NL",
    "sg:address":"Mozartplaats 15",
    "sg:city":"Bergschenhoek",
    "sg:orig_category":"Organisatiebureaus",
    "sg:phone":"+31 10 522 1113",
    "sg:postcode":"2661 HG",
    "sg:province":"Zuid-Holland",
    "wof:name":"Vlug & Partners",
    "wof:placetype":"venue"
},
  "geometry": {"coordinates":[4.501103878,51.9866714478],"type":"Point"}
}