{
  "type": "Feature",
  "properties": {
    "addr:full":"Baarlosestraat 342 Venlo Limburg 5926 PN",
    "addr:housenumber":"342",
    "addr:postcode":"5926 pn",
    "addr:street":"Baarlosestraat",
    "iso:country":"NL",
    "sg:address":"Baarlosestraat 342",
    "sg:city":"Venlo",
    "sg:orig_category":"Partycatering And -Organisatie",
    "sg:phone":"+31 77 382 6830",
    "sg:postcode":"5926 PN",
    "sg:province":"Limburg",
    "wof:name":"Party-Service Rob Kaneman",
    "wof:placetype":"venue"
},
  "geometry": {"coordinates":[6.121066,51.353024],"type":"Point"}
}