{
  "type": "Feature",
  "properties": {
    "iso:country":"NL",
    "sg:address":"Kruisbroeksestr 21",
    "sg:city":"Boxtel",
    "sg:orig_category":"Autopoetsbedrijven",
    "sg:phone":"+31 6 53661583",
    "sg:postcode":"5281 RV",
    "sg:province":"Noord-Brabant",
    "wof:name":"Troeyen",
    "wof:placetype":"venue"
},
  "geometry": {"coordinates":[5.312962,51.578873],"type":"Point"}
}