{
  "type": "Feature",
  "properties": {
    "addr:full":"Jachthavenweg 4 Amsterdam North Holland 1076 CZ",
    "addr:housenumber":"4",
    "addr:postcode":"1076",
    "addr:street":"Jachthavenweg",
    "iso:country":"NL",
    "sg:address":"Jachthavenweg 4",
    "sg:city":"Amsterdam",
    "sg:orig_category":"Paramedische Behandelingen",
    "sg:phone":"+31 20 679 3722",
    "sg:postcode":"1076 CZ",
    "sg:province":"North Holland",
    "wof:name":"J J M Geytenbeek",
    "wof:placetype":"venue"
},
  "geometry": {"coordinates":[4.848769,52.340141],"type":"Point"}
}