{
  "type": "Feature",
  "properties": {
    "iso:country":"NL",
    "sg:address":"Laan Van Snelrewaard 63",
    "sg:city":"Snelrewaard",
    "sg:orig_category":"Fitnesscentra",
    "sg:phone":"+31 348 565 125",
    "sg:postcode":"3425 ES",
    "sg:province":"Utrecht",
    "wof:name":"You Too",
    "wof:placetype":"venue"
},
  "geometry": {"coordinates":[4.88013,52.02129],"type":"Point"}
}