{
  "type": "Feature",
  "properties": {
    "addr:full":"Raadhuispln 17 Haren Gn Groningen 9751 AN",
    "addr:housenumber":"17",
    "addr:postcode":"9751 an",
    "addr:street":"Raadhuispln",
    "iso:country":"NL",
    "sg:address":"Raadhuispln 17",
    "sg:city":"Haren Gn",
    "sg:classifiers":[
        {
            "category":"Education",
            "subcategory":"Special Training",
            "type":"Public Place"
        }
    ],
    "sg:phone":"+31 50 534 8080",
    "sg:postcode":"9751 AN",
    "sg:province":"Groningen",
    "sg:tags":[
        "expertise"
    ],
    "sg:website":"http://www.touw.nl",
    "wof:name":"Touw Bv",
    "wof:placetype":"venue"
},
  "geometry": {"coordinates":[6.603678,53.173321],"type":"Point"}
}