{
  "type": "Feature",
  "properties": {
    "addr:full":"Sandtlaan 36 G-11 Katwijk Zh Zuid-Holland 2333 GG",
    "addr:housenumber":"36",
    "addr:postcode":"zh;2333 gg",
    "addr:street":"Sandtlaan",
    "iso:country":"NL",
    "sg:address":"Sandtlaan 36 G-11",
    "sg:city":"Katwijk Zh",
    "sg:orig_category":"Beveiligingsdiensten And Bewakingsbedrijven",
    "sg:phone":"+31 71 401 0055",
    "sg:postcode":"2333 GG",
    "sg:province":"Zuid-Holland",
    "wof:name":"Smart Security",
    "wof:placetype":"venue"
},
  "geometry": {"coordinates":[4.39656,52.205101],"type":"Point"}
}