{
  "type": "Feature",
  "properties": {
    "iso:country":"NL",
    "sg:address":"Johannes Vermeerstraat 43",
    "sg:city":"Amsterdam",
    "sg:orig_category":"Werving And Selectie Van Vast Personeel",
    "sg:phone":"+31 20 471 0147",
    "sg:postcode":"1071 DL",
    "sg:province":"North Holland",
    "wof:name":"Prins En Partners",
    "wof:placetype":"venue"
},
  "geometry": {"coordinates":[4.8842630386,52.3562965393],"type":"Point"}
}