{
  "type": "Feature",
  "properties": {
    "addr:full":"Heemraadssngl 36 Rotterdam Zuid-Holland 3021 DB",
    "addr:housenumber":"36",
    "addr:postcode":"3021 db",
    "addr:street":"Heemraadssngl",
    "iso:country":"NL",
    "sg:address":"Heemraadssngl 36",
    "sg:city":"Rotterdam",
    "sg:orig_category":"Adviesbureaus Bedrijfsorganisatie",
    "sg:phone":"+31 10 425 9855",
    "sg:postcode":"3021 DB",
    "sg:province":"Zuid-Holland",
    "wof:name":"Graaff",
    "wof:placetype":"venue"
},
  "geometry": {"coordinates":[4.456189,51.920509],"type":"Point"}
}