{
  "type": "Feature",
  "properties": {
    "addr:full":"Weijland 70 Nieuwerbrug Zuid-Holland 2415 BD",
    "addr:housenumber":"70",
    "addr:postcode":"2415 bd",
    "addr:street":"Weijland",
    "iso:country":"NL",
    "sg:address":"Weijland 70",
    "sg:city":"Nieuwerbrug",
    "sg:orig_category":"Diverse Bedrijfsinstallaties Gh",
    "sg:phone":"+31 348 688 684",
    "sg:postcode":"2415 BD",
    "sg:province":"Zuid-Holland",
    "wof:name":"G & K Groothandel Bv",
    "wof:placetype":"venue"
},
  "geometry": {"coordinates":[4.815026,52.079502],"type":"Point"}
}