{
  "type": "Feature",
  "properties": {
    "addr:full":"Dukaton 17 Volendam Noord-Holland 1132 RA",
    "addr:housenumber":"17",
    "addr:postcode":"1132 ra",
    "addr:street":"Dukaton",
    "iso:country":"NL",
    "sg:address":"Dukaton 17",
    "sg:city":"Volendam",
    "sg:orig_category":"Manueel Therapeuten",
    "sg:phone":"+31 299 351 663",
    "sg:postcode":"1132 RA",
    "sg:province":"Noord-Holland",
    "wof:name":"Segaar, B K",
    "wof:placetype":"venue"
},
  "geometry": {"coordinates":[5.062448,52.505421],"type":"Point"}
}