{
  "type": "Feature",
  "properties": {
    "iso:country":"NL",
    "sg:address":"Hoofdwg 1318",
    "sg:city":"Nieuw Vennep",
    "sg:orig_category":"Zalenverhuur",
    "sg:phone":"+31 252 672 476",
    "sg:postcode":"2153 LS",
    "sg:province":"Flevoland",
    "wof:name":"Trefpunt, Het",
    "wof:placetype":"venue"
},
  "geometry": {"coordinates":[4.634819,52.264717],"type":"Point"}
}