{
  "type": "Feature",
  "properties": {
    "iso:country":"NL",
    "sg:address":"M Raymakersstr 21",
    "sg:city":"Best",
    "sg:orig_category":"Verzekeringen - Verzekeringskantoren",
    "sg:phone":"+31 499 373 141",
    "sg:postcode":"5683 EH",
    "sg:province":"North Brabant",
    "wof:name":"Saris Bos",
    "wof:placetype":"venue"
},
  "geometry": {"coordinates":[5.401066,51.513828],"type":"Point"}
}