{
  "type": "Feature",
  "properties": {
    "iso:country":"NL",
    "sg:address":"Elzenbos 29",
    "sg:city":"Geldermalsen",
    "sg:orig_category":"Bedrijfs- And Managementsconsultants",
    "sg:phone":"+31 345 576 732",
    "sg:postcode":"4191 MR",
    "sg:province":"Gelderland",
    "wof:name":"Borrowwoods",
    "wof:placetype":"venue"
},
  "geometry": {"coordinates":[5.294084,51.874599],"type":"Point"}
}