{
  "type": "Feature",
  "properties": {
    "addr:full":"Van Goorstraat 1/A Breda Noord-Brabant 4811 HH",
    "addr:housenumber":"1 / a",
    "addr:postcode":"4811 hh",
    "addr:street":"Van Goorstraat",
    "iso:country":"NL",
    "sg:address":"Van Goorstraat 1/A",
    "sg:city":"Breda",
    "sg:orig_category":"Huishoudapparatuur, Televisies And Radio'S",
    "sg:phone":"+31 76 522 4334",
    "sg:postcode":"4811 HH",
    "sg:province":"Noord-Brabant",
    "wof:name":"Electro-Comfort",
    "wof:placetype":"venue"
},
  "geometry": {"coordinates":[4.777523,51.582005],"type":"Point"}
}