{
  "type": "Feature",
  "properties": {
    "iso:country":"NL",
    "sg:address":"Plevier 56",
    "sg:city":"Hoorn Nh",
    "sg:orig_category":"Administratie- En Boekhoudkantoren",
    "sg:phone":"+31 6 18555053",
    "sg:postcode":"1628 EV",
    "sg:province":"Noord-Holland",
    "wof:name":"Ms Consultancy",
    "wof:placetype":"venue"
},
  "geometry": {"coordinates":[5.092344,52.65786],"type":"Point"}
}