{
  "type": "Feature",
  "properties": {
    "addr:full":"Javalaan 15 Baarn Utrecht 3742 CN",
    "addr:housenumber":"15",
    "addr:postcode":"3742 cn",
    "addr:street":"Javalaan",
    "iso:country":"NL",
    "sg:address":"Javalaan 15",
    "sg:city":"Baarn",
    "sg:orig_category":"Technische Studies And Onderzoek",
    "sg:phone":"+31 35 541 4868",
    "sg:postcode":"3742 CN",
    "sg:province":"Utrecht",
    "wof:name":"Little Video Consultancy",
    "wof:placetype":"venue"
},
  "geometry": {"coordinates":[5.296836,52.208595],"type":"Point"}
}