{
  "type": "Feature",
  "properties": {
    "addr:full":"Herenweg 39 Warmond Zuid-Holland 2361 EC",
    "addr:housenumber":"39",
    "addr:postcode":"2361 ec",
    "addr:street":"Herenweg",
    "iso:country":"NL",
    "sg:address":"Herenweg 39",
    "sg:city":"Warmond",
    "sg:classifiers":[
        {
            "category":"Food & Beverages",
            "subcategory":"Fruits & Vegetables",
            "type":"Retail Goods"
        }
    ],
    "sg:phone":"+31 71 301 0252",
    "sg:postcode":"2361 EC",
    "sg:province":"Zuid-Holland",
    "sg:tags":[
        "groenten"
    ],
    "wof:name":"Jos Van Dam Groente En Fruithandel",
    "wof:placetype":"venue"
},
  "geometry": {"coordinates":[4.499207,52.194309],"type":"Point"}
}