{
  "type": "Feature",
  "properties": {
    "addr:full":"Narcislaan 34 Leende Noord-Brabant 5595 EG",
    "addr:housenumber":"34",
    "addr:postcode":"5595 eg",
    "addr:street":"Narcislaan",
    "iso:country":"NL",
    "sg:address":"Narcislaan 34",
    "sg:city":"Leende",
    "sg:orig_category":"Diverse Consumentenartikelen Gh",
    "sg:phone":"+31 40 206 1413",
    "sg:postcode":"5595 EG",
    "sg:province":"Noord-Brabant",
    "wof:name":"H.A. Floris International Trading",
    "wof:placetype":"venue"
},
  "geometry": {"coordinates":[5.547247,51.349609],"type":"Point"}
}