{
  "type": "Feature",
  "properties": {
    "addr:full":"Weth. Beversstraat 140 Enschede Overijssel 7543 BN",
    "addr:housenumber":"140",
    "addr:postcode":"7543 bn",
    "addr:street":"Weth. Beversstraat",
    "iso:country":"NL",
    "sg:address":"Weth. Beversstraat 140",
    "sg:city":"Enschede",
    "sg:orig_category":"Bloemen And Planten",
    "sg:phone":"+31 53 477 7122",
    "sg:postcode":"7543 BN",
    "sg:province":"Overijssel",
    "wof:name":"Marcel Huiskes",
    "wof:placetype":"venue"
},
  "geometry": {"coordinates":[6.876819,52.207672],"type":"Point"}
}