{
  "type": "Feature",
  "properties": {
    "addr:full":"Postbus 9853 Amsterdam Friesland 1006 AN",
    "addr:housenumber":"9853",
    "addr:postcode":"1006 an",
    "addr:street":"Postbus",
    "iso:country":"NL",
    "sg:address":"Postbus 9853",
    "sg:city":"Amsterdam",
    "sg:orig_category":"Adviesbureaus Bedrijfsorganisatie",
    "sg:phone":"+31 20 640 0982",
    "sg:postcode":"1006 AN",
    "sg:province":"Friesland",
    "wof:name":"Oog",
    "wof:placetype":"venue"
},
  "geometry": {"coordinates":[4.89205,52.37355],"type":"Point"}
}