{
  "type": "Feature",
  "properties": {
    "addr:full":"Postbus 3 Maarn Utrecht 3950 AA",
    "addr:housenumber":"3",
    "addr:postcode":"3950 aa",
    "addr:street":"Postbus",
    "iso:country":"NL",
    "sg:address":"Postbus 3",
    "sg:city":"Maarn",
    "sg:orig_category":"Adviesbureaus Gezondheidszorg",
    "sg:phone":"+31 343 442 674",
    "sg:postcode":"3950 AA",
    "sg:province":"Utrecht",
    "wof:name":"Advies En Management Gezondheidszorg",
    "wof:placetype":"venue"
},
  "geometry": {"coordinates":[5.3719,52.064388],"type":"Point"}
}