{
  "type": "Feature",
  "properties": {
    "addr:full":"Diepenhorstlaan 8 Rijswijk Zh South Holland 2288 EW",
    "addr:housenumber":"8",
    "addr:postcode":"2288 ew",
    "addr:street":"Diepenhorstlaan",
    "iso:country":"NL",
    "sg:address":"Diepenhorstlaan 8",
    "sg:city":"Rijswijk Zh",
    "sg:orig_category":"Boekhouders",
    "sg:phone":"+31 70 399 3538",
    "sg:postcode":"2288 EW",
    "sg:province":"South Holland",
    "wof:name":"Adm Beslat Adv Bur R S Ladi",
    "wof:placetype":"venue"
},
  "geometry": {"coordinates":[4.331969,52.040661],"type":"Point"}
}