{
  "type": "Feature",
  "properties": {
    "iso:country":"NL",
    "sg:address":"Het Haagje 109",
    "sg:city":"Hoogeveen",
    "sg:orig_category":"Accountants - Administratie- Consulenten En -Kantoren",
    "sg:phone":"+31 528 262 231",
    "sg:postcode":"7902 LD",
    "sg:province":"Drenthe",
    "wof:name":"Alfa Bv",
    "wof:placetype":"venue"
},
  "geometry": {"coordinates":[6.4825358391,52.7209663391],"type":"Point"}
}