{
  "type": "Feature",
  "properties": {
    "addr:full":"Televisiewg 58 Almere Flevoland 1322 AM",
    "addr:housenumber":"58",
    "addr:postcode":"1322",
    "addr:street":"Televisiewg;Flevoland",
    "iso:country":"NL",
    "sg:address":"Televisiewg 58",
    "sg:city":"Almere",
    "sg:orig_category":"Hydrocultuur",
    "sg:phone":"+31 36 546 8600",
    "sg:postcode":"1322 AM",
    "sg:province":"Flevoland",
    "sg:website":"http://www.hygros.nl",
    "wof:name":"Hygros",
    "wof:placetype":"venue"
},
  "geometry": {"coordinates":[5.181451,52.350266],"type":"Point"}
}