{
  "type": "Feature",
  "properties": {
    "addr:full":"Schoterlandsewg 84 Nieuwehorne Friesland 8414 LZ",
    "addr:housenumber":"84",
    "addr:postcode":"8414 lz",
    "addr:street":"Schoterlandsewg",
    "iso:country":"NL",
    "sg:address":"Schoterlandsewg 84",
    "sg:city":"Nieuwehorne",
    "sg:orig_category":"Dumpgoederen",
    "sg:phone":"+31 513 541 398",
    "sg:postcode":"8414 LZ",
    "sg:province":"Friesland",
    "wof:name":"Molenhoek, De",
    "wof:placetype":"venue"
},
  "geometry": {"coordinates":[6.061215,52.95224],"type":"Point"}
}