{
  "type": "Feature",
  "properties": {
    "addr:full":"Schoonoord 43 Westervoort Gelderland 6931 BS",
    "addr:housenumber":"43",
    "addr:postcode":"6931 bs",
    "addr:street":"Schoonoord;Gelderland",
    "iso:country":"NL",
    "sg:address":"Schoonoord 43",
    "sg:city":"Westervoort",
    "sg:orig_category":"Verhuur Catering-, Feest- En Evenementbenodigdheden",
    "sg:phone":"+31 26 311 2483",
    "sg:postcode":"6931 BS",
    "sg:province":"Gelderland",
    "wof:name":"A.J.C. Buys",
    "wof:placetype":"venue"
},
  "geometry": {"coordinates":[5.961825,51.962261],"type":"Point"}
}