{
  "type": "Feature",
  "properties": {
    "addr:full":"Noorderstraat 9 Emmen Drenthe 7811 AK",
    "addr:housenumber":"9",
    "addr:postcode":"7811 ak",
    "addr:street":"Noorderstraat",
    "iso:country":"NL",
    "sg:address":"Noorderstraat 9",
    "sg:city":"Emmen",
    "sg:orig_category":"Wasserettes And Stomerijen",
    "sg:phone":"+31 591 612 298",
    "sg:postcode":"7811 AK",
    "sg:province":"Drenthe",
    "wof:name":"E.E.R. Chemische Reiniging",
    "wof:placetype":"venue"
},
  "geometry": {"coordinates":[6.8938012123,52.7868766785],"type":"Point"}
}