{
  "type": "Feature",
  "properties": {
    "addr:full":"Voorstr 3A Katwyk Zh South Holland 2225 EJ",
    "addr:housenumber":"3a;zh",
    "addr:postcode":"2225 ej",
    "addr:street":"Voorstr",
    "iso:country":"NL",
    "sg:address":"Voorstr 3A",
    "sg:city":"Katwyk Zh",
    "sg:classifiers":[
        {
            "category":"Travel",
            "subcategory":"Hotels & Motels",
            "type":"Entertainment"
        }
    ],
    "sg:phone":"+31 71 401 7683",
    "sg:postcode":"2225 EJ",
    "sg:province":"South Holland",
    "wof:name":"Nicolette",
    "wof:placetype":"venue"
},
  "geometry": {"coordinates":[4.396585,52.205109],"type":"Point"}
}