{
  "type": "Feature",
  "properties": {
    "addr:full":"Regentesseln 243 S Gravenhage South Holland 2562 EA",
    "addr:housenumber":"243",
    "addr:postcode":"2562 ea",
    "addr:street":"S Gravenhage",
    "iso:country":"NL",
    "sg:address":"Regentesseln 243",
    "sg:city":"S Gravenhage",
    "sg:orig_category":"Verenigingen En Stichtingen",
    "sg:phone":"+31 70 346 8706",
    "sg:postcode":"2562 EA",
    "sg:province":"South Holland",
    "wof:name":"Schaakgenootschap Dd",
    "wof:placetype":"venue"
},
  "geometry": {"coordinates":[4.28326,52.075001],"type":"Point"}
}