{
  "type": "Feature",
  "properties": {
    "addr:full":"Olympiaplein 1 Hengelo Ov Overijssel 7552 BK",
    "addr:housenumber":"1",
    "addr:postcode":"7552 bk",
    "addr:street":"Olympiaplein;Ov",
    "iso:country":"NL",
    "sg:address":"Olympiaplein 1",
    "sg:city":"Hengelo Ov",
    "sg:orig_category":"Verlichting And Huishoudartikelen",
    "sg:phone":"+31 74 291 8324",
    "sg:postcode":"7552 BK",
    "sg:province":"Overijssel",
    "wof:name":"Bedden Boxsprings Matrassen De Jong",
    "wof:placetype":"venue"
},
  "geometry": {"coordinates":[6.803714,52.253448],"type":"Point"}
}