{
  "type": "Feature",
  "properties": {
    "addr:full":"Sieboldstr 34 Leiden Zuid-Holland 2315 HN",
    "addr:housenumber":"34",
    "addr:postcode":"2315 hn",
    "addr:street":"Sieboldstr",
    "iso:country":"NL",
    "sg:address":"Sieboldstr 34",
    "sg:city":"Leiden",
    "sg:orig_category":"Kappers",
    "sg:phone":"+31 71 521 8777",
    "sg:postcode":"2315 HN",
    "sg:province":"Zuid-Holland",
    "wof:name":"Vink, Jeroen De",
    "wof:placetype":"venue"
},
  "geometry": {"coordinates":[4.508465,52.162495],"type":"Point"}
}