{
  "type": "Feature",
  "properties": {
    "iso:country":"NL",
    "sg:address":"Egelantiersgr 390",
    "sg:city":"Amsterdam",
    "sg:orig_category":"Fotolaboratoria",
    "sg:phone":"+31 20 625 3789",
    "sg:postcode":"1015 RR",
    "sg:province":"Noord-Holland",
    "wof:name":"John Kingma Bv Mpp",
    "wof:placetype":"venue"
},
  "geometry": {"coordinates":[4.880802,52.376095],"type":"Point"}
}