{
  "type": "Feature",
  "properties": {
    "addr:full":"Zuideinde 9 Koog A/D Zaan North Holland 1541 CA",
    "addr:housenumber":"9;a / d",
    "addr:postcode":"1541 ca",
    "addr:street":"Zuideinde;Zaan North",
    "iso:country":"NL",
    "sg:address":"Zuideinde 9",
    "sg:city":"Koog A/D Zaan",
    "sg:orig_category":"Metaalwerken",
    "sg:phone":"+31 75 616 2406",
    "sg:postcode":"1541 CA",
    "sg:province":"North Holland",
    "wof:name":"Handelsonderneming Pennekamp Systeemplaf",
    "wof:placetype":"venue"
},
  "geometry": {"coordinates":[4.810564,52.45623],"type":"Point"}
}