{
  "type": "Feature",
  "properties": {
    "iso:country":"NL",
    "sg:address":"Kerkdam 5",
    "sg:city":"Warmond",
    "sg:orig_category":"Zalenexploitatie",
    "sg:phone":"+31 71 301 0700",
    "sg:postcode":"2361 GK",
    "sg:province":"South Holland",
    "wof:name":"Art Intercession",
    "wof:placetype":"venue"
},
  "geometry": {"coordinates":[4.503817,52.196987],"type":"Point"}
}