{
  "type": "Feature",
  "properties": {
    "addr:full":"Molendreef 79 Ossendrecht Noord-Brabant 4641 CT",
    "addr:housenumber":"79",
    "addr:postcode":"4641 ct",
    "addr:street":"Molendreef",
    "iso:country":"NL",
    "sg:address":"Molendreef 79",
    "sg:city":"Ossendrecht",
    "sg:orig_category":"Bloemen And Planten",
    "sg:phone":"+31 164 673 518",
    "sg:postcode":"4641 CT",
    "sg:province":"Noord-Brabant",
    "wof:name":"Tuincentrum De Molen",
    "wof:placetype":"venue"
},
  "geometry": {"coordinates":[4.335771,51.394688],"type":"Point"}
}