{
  "type": "Feature",
  "properties": {
    "addr:full":"Crooswijkseweg 90/B Rotterdam South Holland 3034 HM",
    "addr:housenumber":"90 / b",
    "addr:postcode":"3034 hm",
    "addr:street":"Crooswijkseweg",
    "iso:country":"NL",
    "sg:address":"Crooswijkseweg 90/B",
    "sg:city":"Rotterdam",
    "sg:classifiers":[
        {
            "category":"Fast Food",
            "type":"Food & Drink"
        }
    ],
    "sg:phone":"+31 10 213 2477",
    "sg:postcode":"3034 HM",
    "sg:province":"South Holland",
    "sg:tags":[
        "afhaal",
        "restaurant"
    ],
    "wof:name":"Snack En Vishandel M. Verbeek-Looyen",
    "wof:placetype":"venue"
},
  "geometry": {"coordinates":[4.493429,51.931511],"type":"Point"}
}