{
  "type": "Feature",
  "properties": {
    "addr:full":"Spui 188 S Gravenhage Zuid-Holland 2511 BW",
    "addr:housenumber":"188;gravenhage",
    "addr:postcode":"2511 bw",
    "addr:street":"Spui;S",
    "iso:country":"NL",
    "sg:address":"Spui 188",
    "sg:city":"S Gravenhage",
    "sg:orig_category":"Vakorganisaties",
    "sg:phone":"+31 70 375 1751",
    "sg:postcode":"2511 BW",
    "sg:province":"Zuid-Holland",
    "wof:name":"Knv Kon Ned Vervoer",
    "wof:placetype":"venue"
},
  "geometry": {"coordinates":[4.31627,52.07896],"type":"Point"}
}