{
  "type": "Feature",
  "properties": {
    "addr:full":"Grebbewg 85 Rhenen Utrecht 3911 AV",
    "addr:housenumber":"85",
    "addr:postcode":"3911 av",
    "addr:street":"Grebbewg",
    "iso:country":"NL",
    "sg:address":"Grebbewg 85",
    "sg:city":"Rhenen",
    "sg:orig_category":"Voetbalverenigingen",
    "sg:phone":"+31 317 612 708",
    "sg:postcode":"3911 AV",
    "sg:province":"Utrecht",
    "wof:name":"Clubhuis Candia 66",
    "wof:placetype":"venue"
},
  "geometry": {"coordinates":[5.586095,51.956318],"type":"Point"}
}