{
  "type": "Feature",
  "properties": {
    "addr:full":"Essenburgstr 27 Rotterdam Zuid-Holland 3022 MB",
    "addr:housenumber":"27",
    "addr:postcode":"3022 mb",
    "addr:street":"Essenburgstr",
    "iso:country":"NL",
    "sg:address":"Essenburgstr 27",
    "sg:city":"Rotterdam",
    "sg:orig_category":"Begrafenisverzorging",
    "sg:phone":"+31 10 276 2743",
    "sg:postcode":"3022 MB",
    "sg:province":"Zuid-Holland",
    "wof:name":"Pakistan Welfare",
    "wof:placetype":"venue"
},
  "geometry": {"coordinates":[4.451086,51.921623],"type":"Point"}
}