{
  "type": "Feature",
  "properties": {
    "addr:full":"Noordmark 26 Almere NL. 1351 GB",
    "addr:housenumber":"26",
    "addr:postcode":"1351 gb",
    "addr:street":"Noordmark;Nl.",
    "iso:country":"NL",
    "sg:address":"Noordmark 26",
    "sg:city":"Almere",
    "sg:orig_category":"Hijswerktuigen",
    "sg:phone":"+31 36 547 0578",
    "sg:postcode":"1351 GB",
    "sg:province":"NL.",
    "wof:name":"Wit, Firma A",
    "wof:placetype":"venue"
},
  "geometry": {"coordinates":[5.222788,52.34713],"type":"Point"}
}