{
  "type": "Feature",
  "properties": {
    "iso:country":"NL",
    "sg:address":"Kruisbalk 9",
    "sg:city":"Wateringen",
    "sg:orig_category":"Loodgieterswerk, Verwarming And Sanitaire Installaties",
    "sg:phone":"+31 174 297 048",
    "sg:postcode":"2291 ME",
    "sg:province":"South Holland",
    "wof:name":"Reigeda",
    "wof:placetype":"venue"
},
  "geometry": {"coordinates":[4.27377,52.019142],"type":"Point"}
}