{
  "type": "Feature",
  "properties": {
    "addr:full":"Heemraadssngl 299 Rotterdam South Holland 3023 BG",
    "addr:housenumber":"299",
    "addr:postcode":"3023",
    "iso:country":"NL",
    "sg:address":"Heemraadssngl 299",
    "sg:city":"Rotterdam",
    "sg:orig_category":"Adviesbureaus Bedrijfsorganisatie",
    "sg:phone":"+31 10 425 5111",
    "sg:postcode":"3023 BG",
    "sg:province":"South Holland",
    "wof:name":"Dijkstra",
    "wof:placetype":"venue"
},
  "geometry": {"coordinates":[4.455986,51.910877],"type":"Point"}
}