{
  "type": "Feature",
  "properties": {
    "iso:country":"NL",
    "sg:address":"G Majellastr 7",
    "sg:city":"Dongen",
    "sg:orig_category":"Fietsen En Bromfietsen",
    "sg:phone":"+31 162 312 468",
    "sg:postcode":"5101 BE",
    "sg:province":"BE.07",
    "wof:name":"Kimenai Vof, Jan",
    "wof:placetype":"venue"
},
  "geometry": {"coordinates":[4.904815,50.448189],"type":"Point"}
}