{
  "type": "Feature",
  "properties": {
    "iso:country":"NL",
    "sg:address":"Passage Molenpoort 23",
    "sg:city":"Nijmegen",
    "sg:classifiers":[
        {
            "category":"Bakery",
            "type":"Food & Drink"
        }
    ],
    "sg:phone":"+31 24 360 0693",
    "sg:postcode":"6511 HS",
    "sg:province":"Gelderland",
    "sg:tags":[
        "brood",
        "banket"
    ],
    "wof:name":"Drop-Inn",
    "wof:placetype":"venue"
},
  "geometry": {"coordinates":[5.863803,51.844055],"type":"Point"}
}