{
  "type": "Feature",
  "properties": {
    "addr:full":"Julianastr 13 Rucphen Noord-Brabant 4715 AT",
    "addr:housenumber":"13",
    "addr:postcode":"4715",
    "addr:street":"Julianastr",
    "iso:country":"NL",
    "sg:address":"Julianastr 13",
    "sg:city":"Rucphen",
    "sg:orig_category":"Kinderkleding",
    "sg:phone":"+31 165 343 145",
    "sg:postcode":"4715 AT",
    "sg:province":"Noord-Brabant",
    "wof:name":"Bengeltje, 'T",
    "wof:placetype":"venue"
},
  "geometry": {"coordinates":[4.558275,51.534229],"type":"Point"}
}