{
  "type": "Feature",
  "properties": {
    "addr:full":"Bredholm 17 Hoofddorp Noord-Holland 2133 JL",
    "addr:housenumber":"17",
    "addr:postcode":"2133 jl",
    "addr:street":"Bredholm",
    "iso:country":"NL",
    "sg:address":"Bredholm 17",
    "sg:city":"Hoofddorp",
    "sg:orig_category":"Onroerende Goederen",
    "sg:phone":"+31 6 54365004",
    "sg:postcode":"2133 JL",
    "sg:province":"Noord-Holland",
    "wof:name":"Coiffures Vof, Christiaan",
    "wof:placetype":"venue"
},
  "geometry": {"coordinates":[4.661968,52.308453],"type":"Point"}
}