{
  "type": "Feature",
  "properties": {
    "addr:full":"Beatrixstr 103 Enschede NL.08 7511 KR",
    "addr:housenumber":"103",
    "addr:postcode":"7511 kr",
    "iso:country":"NL",
    "sg:address":"Beatrixstr 103",
    "sg:city":"Enschede",
    "sg:orig_category":"Beeldende Kunstenaars",
    "sg:phone":"+31 53 430 0263",
    "sg:postcode":"7511 KR",
    "sg:province":"NL.08",
    "wof:name":"Schouman, M",
    "wof:placetype":"venue"
},
  "geometry": {"coordinates":[6.90294,52.221977],"type":"Point"}
}