{
  "type": "Feature",
  "properties": {
    "addr:full":"Wijnpeerstraat 17 Eindhoven Noord-Brabant 5632 ME",
    "addr:housenumber":"17",
    "addr:postcode":"5632 me",
    "addr:street":"Wijnpeerstraat",
    "iso:country":"NL",
    "sg:address":"Wijnpeerstraat 17",
    "sg:city":"Eindhoven",
    "sg:orig_category":"Kappers",
    "sg:phone":"+31 40 241 4371",
    "sg:postcode":"5632 ME",
    "sg:province":"Noord-Brabant",
    "wof:name":"Caro'S Kapperszaak",
    "wof:placetype":"venue"
},
  "geometry": {"coordinates":[5.4926600456,51.4777565002],"type":"Point"}
}