{
  "type": "Feature",
  "properties": {
    "iso:country":"NL",
    "sg:address":"Edisonweg 11B",
    "sg:city":"Woerden",
    "sg:orig_category":"Veilingen",
    "sg:phone":"+31 348 431 953",
    "sg:postcode":"3442 AC",
    "sg:province":"Utrecht",
    "wof:name":"Veilinghuis Olthof Woerden",
    "wof:placetype":"venue"
},
  "geometry": {"coordinates":[4.881957,52.080379],"type":"Point"}
}