{
  "type": "Feature",
  "properties": {
    "addr:full":"Hoofdstr 110 Zuidwolde Dr Drenthe 7921 AR",
    "addr:housenumber":"110",
    "addr:postcode":"7921",
    "addr:street":"Zuidwolde Dr",
    "iso:country":"NL",
    "sg:address":"Hoofdstr 110",
    "sg:city":"Zuidwolde Dr",
    "sg:orig_category":"Bibliotheken En Leeszalen Openbare",
    "sg:phone":"+31 528 371 644",
    "sg:postcode":"7921 AR",
    "sg:province":"Drenthe",
    "sg:website":"http://www.pbc-drenthe.nl",
    "wof:name":"Openb Bibliotheek",
    "wof:placetype":"venue"
},
  "geometry": {"coordinates":[6.42853,52.67675],"type":"Point"}
}