{
  "type": "Feature",
  "properties": {
    "addr:full":"Bolsterstr 6 Slagharen Overijssel 7776 BC",
    "addr:housenumber":"6",
    "addr:postcode":"7776 bc",
    "addr:street":"Bolsterstr",
    "iso:country":"NL",
    "sg:address":"Bolsterstr 6",
    "sg:city":"Slagharen",
    "sg:orig_category":"Loodgieters",
    "sg:phone":"+31 523 682 655",
    "sg:postcode":"7776 BC",
    "sg:province":"Overijssel",
    "wof:name":"Weide, F",
    "wof:placetype":"venue"
},
  "geometry": {"coordinates":[6.554936,52.628136],"type":"Point"}
}