{
  "type": "Feature",
  "properties": {
    "addr:full":"Weissenbruchstraat 25 'S Gravenhage Zuid-Holland 2596 GB",
    "addr:housenumber":"25",
    "addr:postcode":"2596 gb",
    "addr:street":"Weissenbruchstraat;' S",
    "iso:country":"NL",
    "sg:address":"Weissenbruchstraat 25",
    "sg:city":"'S Gravenhage",
    "sg:orig_category":"Wasserettes And Stomerijen",
    "sg:phone":"+31 70 324 8316",
    "sg:postcode":"2596 GB",
    "sg:province":"Zuid-Holland",
    "wof:name":"Wassalon Weissenbruch",
    "wof:placetype":"venue"
},
  "geometry": {"coordinates":[4.3181247711,52.0895233154],"type":"Point"}
}