{
  "type": "Feature",
  "properties": {
    "addr:full":"Ln V Meerdervoort 492-B S Gravenhage Zuid-Holland 2563 BJ",
    "addr:housenumber":"492-b;gravenhage",
    "addr:postcode":"2563 bj",
    "addr:street":"Ln;Meerdervoort;S",
    "iso:country":"NL",
    "sg:address":"Ln V Meerdervoort 492-B",
    "sg:city":"S Gravenhage",
    "sg:orig_category":"Administratie- En Boekhoudkantoren",
    "sg:phone":"+31 70 363 0413",
    "sg:postcode":"2563 BJ",
    "sg:province":"Zuid-Holland",
    "wof:name":"Kleef, T J Van",
    "wof:placetype":"venue"
},
  "geometry": {"coordinates":[4.270956,52.072578],"type":"Point"}
}