{
  "type": "Feature",
  "properties": {
    "addr:full":"Falckstr 14 Amsterdam Noord-Holland 1017 VW",
    "addr:housenumber":"14",
    "addr:postcode":"1017 vw",
    "addr:street":"Falckstr",
    "iso:country":"NL",
    "sg:address":"Falckstr 14",
    "sg:city":"Amsterdam",
    "sg:orig_category":"Tekstschrijversters",
    "sg:phone":"+31 20 626 1216",
    "sg:postcode":"1017 VW",
    "sg:province":"Noord-Holland",
    "sg:website":"http://www.tekstsupport.nl",
    "wof:name":"Tekst/Support",
    "wof:placetype":"venue"
},
  "geometry": {"coordinates":[4.897932,52.36034],"type":"Point"}
}