{
  "type": "Feature",
  "properties": {
    "addr:full":"Zandhoekln 8 Westerbork Drenthe 9431 BL",
    "addr:housenumber":"8",
    "addr:postcode":"9431 bl",
    "addr:street":"Zandhoekln",
    "iso:country":"NL",
    "sg:address":"Zandhoekln 8",
    "sg:city":"Westerbork",
    "sg:orig_category":"Homeopathie",
    "sg:phone":"+31 593 331 938",
    "sg:postcode":"9431 BL",
    "sg:province":"Drenthe",
    "wof:name":"Weyzen, J A W M Arts",
    "wof:placetype":"venue"
},
  "geometry": {"coordinates":[6.61223,52.850124],"type":"Point"}
}