{
  "type": "Feature",
  "properties": {
    "addr:full":"Markenland 96 Etten-Leur North Brabant 4871 AV",
    "addr:housenumber":"96",
    "addr:postcode":"4871 av",
    "addr:street":"Markenland",
    "iso:country":"NL",
    "sg:address":"Markenland 96",
    "sg:city":"Etten-Leur",
    "sg:orig_category":"Kinderopvang Behalve Thuis",
    "sg:phone":"+31 76 503 7994",
    "sg:postcode":"4871 AV",
    "sg:province":"North Brabant",
    "wof:name":"Kinderdagverblijf Markenland",
    "wof:placetype":"venue"
},
  "geometry": {"coordinates":[4.642791,51.582298],"type":"Point"}
}