{
  "type": "Feature",
  "properties": {
    "iso:country":"NL",
    "sg:address":"Biltstr 87",
    "sg:city":"Utrecht",
    "sg:orig_category":"Meubelen",
    "sg:phone":"+31 30 231 7255",
    "sg:postcode":"3572 AK",
    "sg:province":"Utrecht",
    "wof:name":"Meubelhome",
    "wof:placetype":"venue"
},
  "geometry": {"coordinates":[5.130409,52.095139],"type":"Point"}
}