{
  "type": "Feature",
  "properties": {
    "addr:full":"Pompenmaker 1 Beuningen Gld Gelderland 6641 GH",
    "addr:housenumber":"1",
    "addr:postcode":"6641 gh",
    "addr:street":"Pompenmaker",
    "iso:country":"NL",
    "sg:address":"Pompenmaker 1",
    "sg:city":"Beuningen Gld",
    "sg:orig_category":"Technische Studies And Onderzoek",
    "sg:phone":"+31 24 677 9921",
    "sg:postcode":"6641 GH",
    "sg:province":"Gelderland",
    "wof:name":"Tricert Support",
    "wof:placetype":"venue"
},
  "geometry": {"coordinates":[5.761602,51.859287],"type":"Point"}
}