{
  "type": "Feature",
  "properties": {
    "addr:full":"Nassaustr 94 Rotterdam South Holland 3071 JN",
    "addr:housenumber":"94",
    "addr:postcode":"3071 jn",
    "addr:street":"Nassaustr",
    "iso:country":"NL",
    "sg:address":"Nassaustr 94",
    "sg:city":"Rotterdam",
    "sg:orig_category":"Meubelstoffering",
    "sg:phone":"+31 10 423 1620",
    "sg:postcode":"3071 JN",
    "sg:province":"South Holland",
    "sg:website":"http://www.stoffeerder.nl",
    "wof:name":"Capiton-Hessel",
    "wof:placetype":"venue"
},
  "geometry": {"coordinates":[4.504907,51.912582],"type":"Point"}
}