{
  "type": "Feature",
  "properties": {
    "addr:full":"Noordeinde 116 Oostzaan Noord-Holland 1511 AG",
    "addr:housenumber":"116",
    "addr:postcode":"1511",
    "addr:street":"Noordeinde",
    "iso:country":"NL",
    "sg:address":"Noordeinde 116",
    "sg:city":"Oostzaan",
    "sg:orig_category":"Houtplaatmaterialen",
    "sg:phone":"+31 75 684 1393",
    "sg:postcode":"1511 AG",
    "sg:province":"Noord-Holland",
    "wof:name":"Vonk",
    "wof:placetype":"venue"
},
  "geometry": {"coordinates":[4.869571,52.452232],"type":"Point"}
}