{
  "type": "Feature",
  "properties": {
    "addr:full":"Wilhelminapk 38 Tilburg North Brabant 5041 EC",
    "addr:housenumber":"38",
    "addr:postcode":"5041 ec",
    "addr:street":"Wilhelminapk",
    "iso:country":"NL",
    "sg:address":"Wilhelminapk 38",
    "sg:city":"Tilburg",
    "sg:orig_category":"Beeldende Kunstenaars",
    "sg:phone":"+31 13 543 5539",
    "sg:postcode":"5041 EC",
    "sg:province":"North Brabant",
    "sg:website":"http://www.janspit.nl",
    "wof:name":"Spit, Jan",
    "wof:placetype":"venue"
},
  "geometry": {"coordinates":[5.0786,51.56432],"type":"Point"}
}