{
  "type": "Feature",
  "properties": {
    "iso:country":"NL",
    "sg:address":"Kievitstr 26",
    "sg:city":"Hilversum",
    "sg:orig_category":"Onderhoudswerken",
    "sg:phone":"+31 35 685 0232",
    "sg:postcode":"1221 KZ",
    "sg:province":"North Holland",
    "wof:name":"Essen, D J Van",
    "wof:placetype":"venue"
},
  "geometry": {"coordinates":[5.190036,52.223801],"type":"Point"}
}