{
  "type": "Feature",
  "properties": {
    "addr:full":"Industriewg 25D Hoogeveen Drenthe 7903 AH",
    "addr:housenumber":"25d",
    "addr:postcode":"7903 ah",
    "addr:street":"Industriewg",
    "iso:country":"NL",
    "sg:address":"Industriewg 25D",
    "sg:city":"Hoogeveen",
    "sg:orig_category":"Hengelsportartikelen - Fabrieken En Groothandel",
    "sg:phone":"+31 528 220 408",
    "sg:postcode":"7903 AH",
    "sg:province":"Drenthe",
    "sg:website":"http://www.leonardsports.nl",
    "wof:name":"Leonard",
    "wof:placetype":"venue"
},
  "geometry": {"coordinates":[6.484359,52.731976],"type":"Point"}
}