{
  "type": "Feature",
  "properties": {
    "addr:full":"Vensestraat 27 Ottersum Limburg 6595 MT",
    "addr:housenumber":"27",
    "addr:postcode":"6595",
    "addr:street":"Vensestraat;Mt",
    "iso:country":"NL",
    "sg:address":"Vensestraat 27",
    "sg:city":"Ottersum",
    "sg:classifiers":[
        {
            "category":"Fast Food",
            "type":"Food & Drink"
        }
    ],
    "sg:phone":"+31 485 518 174",
    "sg:postcode":"6595 MT",
    "sg:province":"Limburg",
    "sg:tags":[
        "afhaal",
        "restaurant"
    ],
    "wof:name":"Cafetaria Joep",
    "wof:placetype":"venue"
},
  "geometry": {"coordinates":[6.024971,51.714935],"type":"Point"}
}