{
  "type": "Feature",
  "properties": {
    "iso:country":"NL",
    "sg:address":"Eendrachtsstraat 30",
    "sg:city":"Velsen-Noord",
    "sg:orig_category":"Papier And Karton Fab",
    "sg:phone":"+31 251 262 233",
    "sg:postcode":"1951 AZ",
    "sg:province":"Noord-Holland",
    "wof:name":"Crown Van Gelder Papierfabrieken Nv",
    "wof:placetype":"venue"
},
  "geometry": {"coordinates":[4.638404,52.46703],"type":"Point"}
}