{
  "type": "Feature",
  "properties": {
    "addr:full":"Verl Trambaanwg 4 Rhenen Utrecht 3911 AJ",
    "addr:housenumber":"4",
    "addr:postcode":"3911 aj",
    "addr:street":"Trambaanwg",
    "iso:country":"NL",
    "sg:address":"Verl Trambaanwg 4",
    "sg:city":"Rhenen",
    "sg:classifiers":[
        {
            "category":"Retail",
            "subcategory":"Auto Repair",
            "type":"Services"
        }
    ],
    "sg:phone":"+31 317 619 107",
    "sg:postcode":"3911 AJ",
    "sg:province":"Utrecht",
    "sg:tags":[
        "garage"
    ],
    "wof:name":"Tsn",
    "wof:placetype":"venue"
},
  "geometry": {"coordinates":[5.578643,51.955139],"type":"Point"}
}