{
  "type": "Feature",
  "properties": {
    "addr:full":"Oude Langstraat 65 Tilburg North Brabant 5041 CD",
    "addr:housenumber":"65",
    "addr:postcode":"5041 cd",
    "addr:street":"Oude Langstraat",
    "iso:country":"NL",
    "sg:address":"Oude Langstraat 65",
    "sg:city":"Tilburg",
    "sg:orig_category":"Fotostudio'S And Fotografen",
    "sg:phone":"+31 13 580 2222",
    "sg:postcode":"5041 CD",
    "sg:province":"North Brabant",
    "wof:name":"Style Pictorial Art",
    "wof:placetype":"venue"
},
  "geometry": {"coordinates":[5.084708,51.565647],"type":"Point"}
}