{
  "type": "Feature",
  "properties": {
    "iso:country":"NL",
    "sg:address":"Ring 3",
    "sg:city":"Zuidland",
    "sg:orig_category":"Poppen En Poppenhuismaterialen",
    "sg:phone":"+31 181 451 556",
    "sg:postcode":"3214 AT",
    "sg:province":"South Holland",
    "wof:name":"Porceleyne Pop, De",
    "wof:placetype":"venue"
},
  "geometry": {"coordinates":[4.262028,51.822166],"type":"Point"}
}