{
  "type": "Feature",
  "properties": {
    "addr:full":"Hei En Boeicopseweg 168 Hei En Boeicop Zuid-Holland 4126 RM",
    "addr:housenumber":"168",
    "addr:postcode":"4126 rm",
    "addr:street":"Hei En Boeicopseweg",
    "iso:country":"NL",
    "sg:address":"Hei En Boeicopseweg 168",
    "sg:city":"Hei En Boeicop",
    "sg:orig_category":"Goederenvervoer Over De Weg",
    "sg:phone":"+31 347 342 361",
    "sg:postcode":"4126 RM",
    "sg:province":"Zuid-Holland",
    "wof:name":"Johannes De Jong",
    "wof:placetype":"venue"
},
  "geometry": {"coordinates":[5.054283,51.949154],"type":"Point"}
}