{
  "type": "Feature",
  "properties": {
    "addr:full":"Leeuwenhoekweg 16 Veghel Noord-Brabant 5466 AL",
    "addr:housenumber":"16",
    "addr:postcode":"5466 al",
    "addr:street":"Leeuwenhoekweg",
    "iso:country":"NL",
    "sg:address":"Leeuwenhoekweg 16",
    "sg:city":"Veghel",
    "sg:orig_category":"Diverse Grafische Activiteiten",
    "sg:phone":"+31 413 350 010",
    "sg:postcode":"5466 AL",
    "sg:province":"Noord-Brabant",
    "wof:name":"Mark Vormgeving En Reclameprodukties",
    "wof:placetype":"venue"
},
  "geometry": {"coordinates":[5.508815,51.617325],"type":"Point"}
}