{
  "type": "Feature",
  "properties": {
    "iso:country":"NL",
    "sg:address":"Schermerhornpk 81",
    "sg:city":"Nieuwegein",
    "sg:orig_category":"Offsetdrukkerijen",
    "sg:phone":"+31 30 687 2240",
    "sg:postcode":"3437 PX",
    "sg:province":"Utrecht",
    "wof:name":"Vogelpoel, J M Van",
    "wof:placetype":"venue"
},
  "geometry": {"coordinates":[5.082954,52.052593],"type":"Point"}
}