{
  "type": "Feature",
  "properties": {
    "addr:full":"Leembaan 13 Deurne Noord-Brabant 5753 CW",
    "addr:housenumber":"13",
    "addr:postcode":"5753 cw",
    "addr:street":"Leembaan",
    "iso:country":"NL",
    "sg:address":"Leembaan 13",
    "sg:city":"Deurne",
    "sg:orig_category":"Land- En Tuinbouw - Mechanisatie",
    "sg:phone":"+31 493 312 595",
    "sg:postcode":"5753 CW",
    "sg:province":"Noord-Brabant",
    "sg:website":"http://www.munckhof.com/",
    "wof:name":"Munckhof Deurne",
    "wof:placetype":"venue"
},
  "geometry": {"coordinates":[5.792143,51.452644],"type":"Point"}
}