{
  "type": "Feature",
  "properties": {
    "addr:full":"V Zompelstr 1Zw Haarlem Noord-Holland 2012 XK",
    "addr:housenumber":"1zw",
    "addr:postcode":"2012 xk",
    "addr:street":"Zompelstr",
    "iso:country":"NL",
    "sg:address":"V Zompelstr 1Zw",
    "sg:city":"Haarlem",
    "sg:classifiers":[
        {
            "category":"Retail",
            "subcategory":"Auto Repair",
            "type":"Services"
        }
    ],
    "sg:phone":"+31 23 531 2417",
    "sg:postcode":"2012 XK",
    "sg:province":"Noord-Holland",
    "sg:tags":[
        "garage"
    ],
    "wof:name":"Schipper",
    "wof:placetype":"venue"
},
  "geometry": {"coordinates":[4.642253,52.380562],"type":"Point"}
}