{
  "type": "Feature",
  "properties": {
    "addr:full":"Ln V De Eekharst 307 Emmen Provincie Drenthe 7823 AH",
    "addr:housenumber":"307",
    "addr:postcode":"7823 ah",
    "addr:street":"Ln V De Eekharst;Provincie Drenthe",
    "iso:country":"NL",
    "sg:address":"Ln V De Eekharst 307",
    "sg:city":"Emmen",
    "sg:orig_category":"Webdesign Bureaus",
    "sg:phone":"+31 591 625 706",
    "sg:postcode":"7823 AH",
    "sg:province":"Provincie Drenthe",
    "sg:website":"http://www.graffito.nl",
    "wof:name":"Graffito Internet Design",
    "wof:placetype":"venue"
},
  "geometry": {"coordinates":[6.9313941002,52.7879295349],"type":"Point"}
}