{
  "type": "Feature",
  "properties": {
    "addr:full":"Moostdijk 1 Neerkant Noord-Brabant 5758 PV",
    "addr:housenumber":"1",
    "addr:postcode":"5758 pv",
    "addr:street":"Moostdijk",
    "iso:country":"NL",
    "sg:address":"Moostdijk 1",
    "sg:city":"Neerkant",
    "sg:orig_category":"Artsen And Specialisten",
    "sg:phone":"+31 77 466 2285",
    "sg:postcode":"5758 PV",
    "sg:province":"Noord-Brabant",
    "wof:name":"J.A.W. Schepman Huisarts",
    "wof:placetype":"venue"
},
  "geometry": {"coordinates":[5.859509,51.370556],"type":"Point"}
}