{
  "type": "Feature",
  "properties": {
    "iso:country":"NL",
    "sg:address":"De Hoogjens 16",
    "sg:city":"Sleeuwyk",
    "sg:orig_category":"Fietsen En Bromfietsen",
    "sg:phone":"+31 183 600 630",
    "sg:postcode":"4254 XW",
    "sg:province":"Noord-Brabant",
    "wof:name":"Obisk",
    "wof:placetype":"venue"
},
  "geometry": {"coordinates":[4.956705,51.810997],"type":"Point"}
}