{
  "type": "Feature",
  "properties": {
    "addr:full":"Hamburgerstr 3 Utrecht Utrecht 3512 NN",
    "addr:housenumber":"3",
    "addr:postcode":"3512 nn",
    "addr:street":"Hamburgerstr",
    "iso:country":"NL",
    "sg:address":"Hamburgerstr 3",
    "sg:city":"Utrecht",
    "sg:orig_category":"Handwerkartikelen",
    "sg:phone":"+31 30 231 0063",
    "sg:postcode":"3512 NN",
    "sg:province":"Utrecht",
    "wof:name":"In De Nijvere Conste",
    "wof:placetype":"venue"
},
  "geometry": {"coordinates":[5.121976,52.088326],"type":"Point"}
}