{
  "type": "Feature",
  "properties": {
    "iso:country":"NL",
    "sg:address":"Julianapln 13",
    "sg:city":"Sittard",
    "sg:orig_category":"Kunsthandel",
    "sg:phone":"+31 46 475 8732",
    "sg:postcode":"6131 JS",
    "sg:province":"Limburg",
    "wof:name":"Gruner Art",
    "wof:placetype":"venue"
},
  "geometry": {"coordinates":[5.865797,50.993675],"type":"Point"}
}