{
  "type": "Feature",
  "properties": {
    "addr:full":"Hazenkamp 15 Arnhem Gelderland 6836 BA",
    "addr:housenumber":"15",
    "addr:postcode":"6836 ba",
    "addr:street":"Hazenkamp",
    "iso:country":"NL",
    "sg:address":"Hazenkamp 15",
    "sg:city":"Arnhem",
    "sg:orig_category":"Autoverhuur",
    "sg:phone":"+31 26 320 1182",
    "sg:postcode":"6836 BA",
    "sg:province":"Gelderland",
    "wof:name":"Bogane",
    "wof:placetype":"venue"
},
  "geometry": {"coordinates":[5.882461,51.947273],"type":"Point"}
}