{
  "type": "Feature",
  "properties": {
    "iso:country":"NL",
    "sg:address":"Wirostr 3",
    "sg:city":"Echt",
    "sg:orig_category":"Autorijscholen",
    "sg:phone":"+31 475 484 252",
    "sg:postcode":"6102 BC",
    "sg:province":"Limburg",
    "wof:name":"Graus",
    "wof:placetype":"venue"
},
  "geometry": {"coordinates":[-126.555511,54.485668],"type":"Point"}
}