{
  "type": "Feature",
  "properties": {
    "addr:full":"Wirostr 3 Echt Limburg 6102 BC",
    "addr:housenumber":"3",
    "addr:postcode":"6102 bc",
    "addr:street":"Wirostr",
    "iso:country":"NL",
    "sg:address":"Wirostr 3",
    "sg:city":"Echt",
    "sg:orig_category":"Autorijscholen",
    "sg:phone":"+31 475 484 252",
    "sg:postcode":"6102 BC",
    "sg:province":"Limburg",
    "wof:name":"Graus",
    "wof:placetype":"venue"
},
  "geometry": {"coordinates":[-126.555511,54.485668],"type":"Point"}
}