{
  "type": "Feature",
  "properties": {
    "iso:country":"NL",
    "sg:address":"Brede Steeg 19",
    "sg:city":"Oisterwijk",
    "sg:orig_category":"Fotografische And Optische Artikelen Gh",
    "sg:phone":"+31 13 528 8122",
    "sg:postcode":"5062 KG",
    "sg:province":"North Brabant",
    "wof:name":"Lunettes Ava Brillen",
    "wof:placetype":"venue"
},
  "geometry": {"coordinates":[5.186723,51.571438],"type":"Point"}
}