{
  "type": "Feature",
  "properties": {
    "addr:full":"Kerkstr 15A Schoonhoven South Holland 2871 EE",
    "addr:housenumber":"15a",
    "addr:postcode":"2871 ee",
    "addr:street":"Kerkstr",
    "iso:country":"NL",
    "sg:address":"Kerkstr 15A",
    "sg:city":"Schoonhoven",
    "sg:orig_category":"Kappers",
    "sg:phone":"+31 182 385 109",
    "sg:postcode":"2871 EE",
    "sg:province":"South Holland",
    "wof:name":"Contour",
    "wof:placetype":"venue"
},
  "geometry": {"coordinates":[4.8505802155,51.9464492798],"type":"Point"}
}