{
  "type": "Feature",
  "properties": {
    "addr:full":"Dorpsstraat 170 Halsteren Noord-Brabant 4661 HV",
    "addr:housenumber":"170",
    "addr:postcode":"4661 hv",
    "addr:street":"Dorpsstraat",
    "iso:country":"NL",
    "sg:address":"Dorpsstraat 170",
    "sg:city":"Halsteren",
    "sg:classifiers":[
        {
            "category":"Food & Beverages",
            "subcategory":"Fruits & Vegetables",
            "type":"Retail Goods"
        }
    ],
    "sg:phone":"+31 164 685 638",
    "sg:postcode":"4661 HV",
    "sg:province":"Noord-Brabant",
    "sg:tags":[
        "groenten"
    ],
    "wof:name":"Doewin Bv",
    "wof:placetype":"venue"
},
  "geometry": {"coordinates":[4.272145,51.522526],"type":"Point"}
}