{
  "type": "Feature",
  "properties": {
    "iso:country":"NL",
    "sg:address":"Roerdomphoek 7",
    "sg:city":"Spijkenisse",
    "sg:orig_category":"Airconditioning And Ventilatie",
    "sg:phone":"+31 181 622 985",
    "sg:postcode":"3201 HM",
    "sg:province":"Zuid-Holland",
    "wof:name":"Dh",
    "wof:placetype":"venue"
},
  "geometry": {"coordinates":[4.3169,51.844814],"type":"Point"}
}