{
  "type": "Feature",
  "properties": {
    "addr:full":"Secretariestraat 32 Rotterdam South Holland 3052 XL",
    "addr:housenumber":"32",
    "addr:postcode":"3052 xl",
    "addr:street":"Secretariestraat",
    "iso:country":"NL",
    "sg:address":"Secretariestraat 32",
    "sg:city":"Rotterdam",
    "sg:orig_category":"Verhuur Catering-, Feest- En Evenementbenodigdheden",
    "sg:phone":"+31 10 422 0489",
    "sg:postcode":"3052 XL",
    "sg:province":"South Holland",
    "wof:name":"A.R.B. Automaten Bv",
    "wof:placetype":"venue"
},
  "geometry": {"coordinates":[4.476857,51.954807],"type":"Point"}
}