{
  "type": "Feature",
  "properties": {
    "addr:full":"Lorentzpln T/O 78 S Gravenhage Zuid-Holland 2522 EH",
    "addr:housenumber":"78;gravenhage",
    "addr:postcode":"2522 eh",
    "addr:street":"S",
    "iso:country":"NL",
    "sg:address":"Lorentzpln T/O 78",
    "sg:city":"S Gravenhage",
    "sg:classifiers":[
        {
            "category":"Farming",
            "subcategory":"Fish & Marine Products",
            "type":"Manufacturing & Wholesale Goods"
        }
    ],
    "sg:phone":"+31 70 358 5761",
    "sg:postcode":"2522 EH",
    "sg:province":"Zuid-Holland",
    "sg:tags":[
        "vi"
    ],
    "wof:name":"Lorentzplein",
    "wof:placetype":"venue"
},
  "geometry": {"coordinates":[4.32729,52.060848],"type":"Point"}
}