{
  "type": "Feature",
  "properties": {
    "addr:full":"Verzetslaan 1 Purmerend Noord-Holland 1447 XX",
    "addr:housenumber":"1",
    "addr:postcode":"1447 xx",
    "addr:street":"Verzetslaan",
    "iso:country":"NL",
    "sg:address":"Verzetslaan 1",
    "sg:city":"Purmerend",
    "sg:orig_category":"Benzinestations And Brandstoffen",
    "sg:phone":"+31 299 648 336",
    "sg:postcode":"1447 XX",
    "sg:province":"Noord-Holland",
    "wof:name":"Total Selfservicestation Purmer Zuid",
    "wof:placetype":"venue"
},
  "geometry": {"coordinates":[4.960855,52.484859],"type":"Point"}
}