{
  "type": "Feature",
  "properties": {
    "addr:full":"Julianalaan 7-11 Baarn Utrecht 3743 JG",
    "addr:housenumber":"7-11",
    "addr:postcode":"3743 jg",
    "addr:street":"Julianalaan",
    "iso:country":"NL",
    "sg:address":"Julianalaan 7-11",
    "sg:city":"Baarn",
    "sg:orig_category":"Meubelzaken, Woning- And Keukeninrichting",
    "sg:phone":"+31 35 543 0214",
    "sg:postcode":"3743 JG",
    "sg:province":"Utrecht",
    "wof:name":"M. Van Praag",
    "wof:placetype":"venue"
},
  "geometry": {"coordinates":[5.277732,52.206497],"type":"Point"}
}