{
  "type": "Feature",
  "properties": {
    "addr:full":"Vilstersedk 9 Lemelerveld NL.08 8152 EB",
    "addr:housenumber":"9;nl.08",
    "addr:postcode":"8152 eb",
    "addr:street":"Vilstersedk",
    "iso:country":"NL",
    "sg:address":"Vilstersedk 9",
    "sg:city":"Lemelerveld",
    "sg:orig_category":"Begrafenisverzorging",
    "sg:phone":"+31 572 371 466",
    "sg:postcode":"8152 EB",
    "sg:province":"NL.08",
    "wof:name":"Laatste Eer Lemelerveld",
    "wof:placetype":"venue"
},
  "geometry": {"coordinates":[6.341295,52.452915],"type":"Point"}
}