{
  "type": "Feature",
  "properties": {
    "addr:full":"Renssenstraat 13 Arnhem Gelderland 6811 MC",
    "addr:housenumber":"13",
    "addr:postcode":"6811 mc",
    "addr:street":"Renssenstraat",
    "iso:country":"NL",
    "sg:address":"Renssenstraat 13",
    "sg:city":"Arnhem",
    "sg:orig_category":"Timmerwerk Van Hout And Kunststof",
    "sg:phone":"+31 26 442 6493",
    "sg:postcode":"6811 MC",
    "sg:province":"Gelderland",
    "wof:name":"Fa. Jan",
    "wof:placetype":"venue"
},
  "geometry": {"coordinates":[5.898095,51.984669],"type":"Point"}
}