{
  "type": "Feature",
  "properties": {
    "iso:country":"NL",
    "sg:address":"Haarlemmerwg 55",
    "sg:city":"Amsterdam",
    "sg:orig_category":"Banden",
    "sg:phone":"+31 20 682 9784",
    "sg:postcode":"1051 KP",
    "sg:province":"Noord-Holland",
    "wof:name":"Ouasim",
    "wof:placetype":"venue"
},
  "geometry": {"coordinates":[4.877278,52.385357],"type":"Point"}
}