{
  "type": "Feature",
  "properties": {
    "iso:country":"NL",
    "sg:address":"Weststr 43",
    "sg:city":"Axel",
    "sg:orig_category":"Adviesbureaus Bedrijfsorganisatie",
    "sg:phone":"+31 115 564 675",
    "sg:postcode":"4571 HK",
    "sg:province":"Zeeland",
    "wof:name":"Q-Design Fiume",
    "wof:placetype":"venue"
},
  "geometry": {"coordinates":[114.153542,22.411249],"type":"Point"}
}