{
  "type": "Feature",
  "properties": {
    "addr:full":"Koornlaan 2 Alkmaar Noord-Holland 1815 GE",
    "addr:housenumber":"2",
    "addr:postcode":"1815",
    "addr:street":"Koornlaan",
    "iso:country":"NL",
    "sg:address":"Koornlaan 2",
    "sg:city":"Alkmaar",
    "sg:classifiers":[
        {
            "category":"Education",
            "subcategory":"Preschool",
            "type":"Public Place"
        }
    ],
    "sg:phone":"+31 72 511 7973",
    "sg:postcode":"1815 GE",
    "sg:province":"Noord-Holland",
    "sg:tags":[
        "kleuteronderwijs",
        "basis-"
    ],
    "wof:name":"Katholieke Basisschool De Kring",
    "wof:placetype":"venue"
},
  "geometry": {"coordinates":[4.739106,52.632431],"type":"Point"}
}