{
  "type": "Feature",
  "properties": {
    "addr:full":"Draadbaan 49 Leiderdorp South Holland 2352 BM",
    "addr:housenumber":"49",
    "addr:postcode":"2352 bm",
    "addr:street":"Draadbaan",
    "iso:country":"NL",
    "sg:address":"Draadbaan 49",
    "sg:city":"Leiderdorp",
    "sg:orig_category":"Goederenvervoer Over De Weg",
    "sg:phone":"+31 71 589 0094",
    "sg:postcode":"2352 BM",
    "sg:province":"South Holland",
    "wof:name":"Transportbedrijf P. Van Der Meer Bv",
    "wof:placetype":"venue"
},
  "geometry": {"coordinates":[4.518882,52.164047],"type":"Point"}
}