{
  "type": "Feature",
  "properties": {
    "iso:country":"NL",
    "sg:address":"Hogehuisstraat 7",
    "sg:city":"Ijsselmuiden",
    "sg:orig_category":"Medische Apparatuur And Prothesen Fab",
    "sg:phone":"+31 38 332 9513",
    "sg:postcode":"8271 BR",
    "sg:province":"NL.08",
    "wof:name":"Tandtechnisch Lab Prima Dent",
    "wof:placetype":"venue"
},
  "geometry": {"coordinates":[5.929401,52.565018],"type":"Point"}
}