{
  "type": "Feature",
  "properties": {
    "addr:full":"Kneuterdijk 3 'S Gravenhage Zuid-Holland 2514 EM",
    "addr:housenumber":"3 '",
    "addr:postcode":"2514 em",
    "addr:street":"Kneuterdijk",
    "iso:country":"NL",
    "sg:address":"Kneuterdijk 3",
    "sg:city":"'S Gravenhage",
    "sg:orig_category":"Binnenhuisarchitecten",
    "sg:phone":"+31 70 369 7110",
    "sg:postcode":"2514 EM",
    "sg:province":"Zuid-Holland",
    "wof:name":"Interior Collection Bv",
    "wof:placetype":"venue"
},
  "geometry": {"coordinates":[4.30978,52.080425],"type":"Point"}
}