{
  "type": "Feature",
  "properties": {
    "iso:country":"NL",
    "sg:address":"Poggenbeekstr 5",
    "sg:city":"Eindhoven",
    "sg:orig_category":"Webdesign Bureaus",
    "sg:phone":"+31 40 251 6420",
    "sg:postcode":"5645 JL",
    "sg:province":"Noord-Brabant",
    "sg:website":"http://www.catchmedia.nl",
    "wof:name":"Catchmedia",
    "wof:placetype":"venue"
},
  "geometry": {"coordinates":[5.5135269165,51.4272232056],"type":"Point"}
}