{
  "type": "Feature",
  "properties": {
    "iso:country":"NL",
    "sg:address":"Prinsenlaan 64",
    "sg:city":"Emmen",
    "sg:orig_category":"Vertaal- And Tolkenbureaus",
    "sg:phone":"+31 591 640 870",
    "sg:postcode":"7822 GJ",
    "sg:province":"Provincie Drenthe",
    "wof:name":"Bakker Conversation & Translation",
    "wof:placetype":"venue"
},
  "geometry": {"coordinates":[6.903071,52.784847],"type":"Point"}
}