{
  "type": "Feature",
  "properties": {
    "addr:full":"Loowg 20 T Loo Oldebroek Gelderland 8095 PT",
    "addr:housenumber":"20 t",
    "addr:postcode":"8095",
    "addr:street":"Loowg;Loo;Gelderland;Pt",
    "iso:country":"NL",
    "sg:address":"Loowg 20",
    "sg:city":"T Loo Oldebroek",
    "sg:orig_category":"Grondwerken",
    "sg:phone":"+31 525 631 920",
    "sg:postcode":"8095 PT",
    "sg:province":"Gelderland",
    "wof:name":"Evink, W",
    "wof:placetype":"venue"
},
  "geometry": {"coordinates":[5.95043,52.444698],"type":"Point"}
}