{
  "type": "Feature",
  "properties": {
    "addr:full":"Werktuigenwg 22 Emmeloord Flevoland 8304 AP",
    "addr:housenumber":"22",
    "addr:postcode":"8304 ap",
    "addr:street":"Werktuigenwg;Flevoland",
    "iso:country":"NL",
    "sg:address":"Werktuigenwg 22",
    "sg:city":"Emmeloord",
    "sg:orig_category":"Scheepsstofferingen",
    "sg:phone":"+31 527 615 417",
    "sg:postcode":"8304 AP",
    "sg:province":"Flevoland",
    "wof:name":"Huisjes, Fa",
    "wof:placetype":"venue"
},
  "geometry": {"coordinates":[5.755162,52.695786],"type":"Point"}
}