{
  "type": "Feature",
  "properties": {
    "iso:country":"NL",
    "sg:address":"Lokbossen 3",
    "sg:city":"Reusel",
    "sg:orig_category":"Voegwerken",
    "sg:phone":"+31 497 644 007",
    "sg:postcode":"5541 TJ",
    "sg:province":"North Brabant",
    "wof:name":"Patrick Rens",
    "wof:placetype":"venue"
},
  "geometry": {"coordinates":[5.165353,51.358135],"type":"Point"}
}