{
  "type": "Feature",
  "properties": {
    "addr:full":"Pr Mauritsstr 1 Bredevoort Gelderland 7126 AC",
    "addr:housenumber":"1",
    "addr:postcode":"7126 ac",
    "addr:street":"Gelderland",
    "iso:country":"NL",
    "sg:address":"Pr Mauritsstr 1",
    "sg:city":"Bredevoort",
    "sg:orig_category":"Mobiele- En Autotelefoons",
    "sg:phone":"+31 543 451 754",
    "sg:postcode":"7126 AC",
    "sg:province":"Gelderland",
    "sg:website":"http://www.wrtolkamp.nl",
    "wof:name":"Tolkamp, W R",
    "wof:placetype":"venue"
},
  "geometry": {"coordinates":[6.615741,51.941235],"type":"Point"}
}