{
  "type": "Feature",
  "properties": {
    "addr:full":"Haaksbergerstr 526 Enschede Overijssel 7545 GC",
    "addr:housenumber":"526",
    "addr:postcode":"7545 gc",
    "iso:country":"NL",
    "sg:address":"Haaksbergerstr 526",
    "sg:city":"Enschede",
    "sg:orig_category":"Administratie- En Boekhoudkantoren",
    "sg:phone":"+31 53 431 5000",
    "sg:postcode":"7545 GC",
    "sg:province":"Overijssel",
    "wof:name":"Apro Bv",
    "wof:placetype":"venue"
},
  "geometry": {"coordinates":[6.872036,52.208256],"type":"Point"}
}