{
  "type": "Feature",
  "properties": {
    "iso:country":"NL",
    "sg:address":"Nw Waalresewg 39",
    "sg:city":"Valkenswaard",
    "sg:orig_category":"Nagelstudio'S",
    "sg:phone":"+31 40 204 1534",
    "sg:postcode":"5552 ED",
    "sg:province":"Noord-Brabant",
    "sg:website":"http://www.nagelstudiojannie.nl",
    "wof:name":"Jannie Westra Nagelstudio",
    "wof:placetype":"venue"
},
  "geometry": {"coordinates":[5.447327,51.359264],"type":"Point"}
}