{
  "type": "Feature",
  "properties": {
    "iso:country":"NL",
    "sg:address":"Blesboklaan 6",
    "sg:city":"Hilversum",
    "sg:orig_category":"Marktonderzoekbureaus",
    "sg:phone":"+31 35 621 6226",
    "sg:postcode":"1217 GJ",
    "sg:province":"Noord-Holland",
    "wof:name":"Drs.C.J.Ruitenberg",
    "wof:placetype":"venue"
},
  "geometry": {"coordinates":[5.144835,52.235741],"type":"Point"}
}