{
  "type": "Feature",
  "properties": {
    "addr:full":"Brab Turfmarkt 73 Delft Zuid-Holland 2611 CM",
    "addr:housenumber":"73",
    "addr:postcode":"2611 cm",
    "addr:street":"Turfmarkt",
    "iso:country":"NL",
    "sg:address":"Brab Turfmarkt 73",
    "sg:city":"Delft",
    "sg:orig_category":"Opticiens",
    "sg:phone":"+31 15 213 6336",
    "sg:postcode":"2611 CM",
    "sg:province":"Zuid-Holland",
    "sg:website":"http://www.hansanders.nl",
    "wof:name":"Hans Anders",
    "wof:placetype":"venue"
},
  "geometry": {"coordinates":[4.3602018356,52.0102615356],"type":"Point"}
}