{
  "type": "Feature",
  "properties": {
    "iso:country":"NL",
    "sg:address":"Postbus 509",
    "sg:city":"Bleiswyk",
    "sg:orig_category":"Bloemen En Planten - Groothandel",
    "sg:phone":"+31 10 522 4696",
    "sg:postcode":"2665 ZM",
    "sg:province":"South Holland",
    "wof:name":"Tulp",
    "wof:placetype":"venue"
},
  "geometry": {"coordinates":[4.531235,52.012997],"type":"Point"}
}