{
  "type": "Feature",
  "properties": {
    "addr:full":"Postbus 333 Groningen Groningen 9700 AH",
    "addr:housenumber":"333",
    "addr:postcode":"9700 ah",
    "addr:street":"Postbus",
    "iso:country":"NL",
    "sg:address":"Postbus 333",
    "sg:city":"Groningen",
    "sg:orig_category":"Woningbureaus",
    "sg:phone":"+31 50 366 3645",
    "sg:postcode":"9700 AH",
    "sg:province":"Groningen",
    "sg:website":"http://www.woonnetwerk-noord.nl",
    "wof:name":"Woonnetwerk-Noord",
    "wof:placetype":"venue"
},
  "geometry": {"coordinates":[6.5650200844,53.2164497375],"type":"Point"}
}