{
  "type": "Feature",
  "properties": {
    "addr:full":"Hakgriend 44 Hardinxveld Giessend Zuid-Holland 3371 KA",
    "addr:housenumber":"44;giessend",
    "addr:postcode":"3371 ka",
    "addr:street":"Hakgriend",
    "iso:country":"NL",
    "sg:address":"Hakgriend 44",
    "sg:city":"Hardinxveld Giessend",
    "sg:orig_category":"Boekhouders",
    "sg:phone":"+31 184 676 115",
    "sg:postcode":"3371 KA",
    "sg:province":"Zuid-Holland",
    "wof:name":"Quirinus St Administratie Kantoor",
    "wof:placetype":"venue"
},
  "geometry": {"coordinates":[4.852199,51.825329],"type":"Point"}
}