{
  "type": "Feature",
  "properties": {
    "addr:full":"De Hofvoogd 11 Borculo Gelderland 7271 ZP",
    "addr:housenumber":"11",
    "addr:postcode":"7271 zp",
    "addr:street":"De Hofvoogd;Gelderland",
    "iso:country":"NL",
    "sg:address":"De Hofvoogd 11",
    "sg:city":"Borculo",
    "sg:orig_category":"Adviesbureaus Bedrijfsorganisatie",
    "sg:phone":"+31 545 274 761",
    "sg:postcode":"7271 ZP",
    "sg:province":"Gelderland",
    "wof:name":"Mac Quality",
    "wof:placetype":"venue"
},
  "geometry": {"coordinates":[6.510614,52.120605],"type":"Point"}
}