{
  "type": "Feature",
  "properties": {
    "addr:full":"L Kerkstr 7 Goes Zeeland 4461 JG",
    "addr:housenumber":"7",
    "addr:postcode":"4461 jg",
    "iso:country":"NL",
    "sg:address":"L Kerkstr 7",
    "sg:city":"Goes",
    "sg:orig_category":"Kappers",
    "sg:phone":"+31 113 216 873",
    "sg:postcode":"4461 JG",
    "sg:province":"Zeeland",
    "wof:name":"Michelle",
    "wof:placetype":"venue"
},
  "geometry": {"coordinates":[-83.914169,39.768833],"type":"Point"}
}