{
  "type": "Feature",
  "properties": {
    "addr:full":"Aronskelk 82 Venray Limburg 5803 BK",
    "addr:housenumber":"82",
    "addr:postcode":"5803 bk",
    "addr:street":"Aronskelk",
    "iso:country":"NL",
    "sg:address":"Aronskelk 82",
    "sg:city":"Venray",
    "sg:orig_category":"Fitnesscentra",
    "sg:phone":"+31 478 587 630",
    "sg:postcode":"5803 BK",
    "sg:province":"Limburg",
    "wof:name":"Tong-Il",
    "wof:placetype":"venue"
},
  "geometry": {"coordinates":[5.987691,51.529652],"type":"Point"}
}