{
  "type": "Feature",
  "properties": {
    "addr:full":"Langestraat 30 'S Gravenzande South Holland 2691 BH",
    "addr:housenumber":"30",
    "addr:postcode":"2691 bh",
    "addr:street":"Langestraat;' S Gravenzande",
    "iso:country":"NL",
    "sg:address":"Langestraat 30",
    "sg:city":"'S Gravenzande",
    "sg:orig_category":"Kappers",
    "sg:phone":"+31 174 420 202",
    "sg:postcode":"2691 BH",
    "sg:province":"South Holland",
    "wof:name":"Reflex",
    "wof:placetype":"venue"
},
  "geometry": {"coordinates":[4.1601,52.004673],"type":"Point"}
}