{
  "type": "Feature",
  "properties": {
    "iso:country":"NL",
    "sg:address":"Haaskoul 12",
    "sg:city":"Born",
    "sg:orig_category":"Fotolaboratoria",
    "sg:phone":"+31 46 485 1759",
    "sg:postcode":"6121 JN",
    "sg:province":"Limburg",
    "wof:name":"Pieters Photo Finishing Bv",
    "wof:placetype":"venue"
},
  "geometry": {"coordinates":[-156.93781999999999,67.060463],"type":"Point"}
}