{
  "type": "Feature",
  "properties": {
    "addr:full":"Koningin Julianalaan 9 Leusden Utrecht 3832 BA",
    "addr:housenumber":"9",
    "addr:postcode":"3832 ba",
    "addr:street":"Koningin Julianalaan",
    "iso:country":"NL",
    "sg:address":"Koningin Julianalaan 9",
    "sg:city":"Leusden",
    "sg:orig_category":"Loodgieterswerk, Verwarming And Sanitaire Installaties",
    "sg:phone":"+31 33 494 5453",
    "sg:postcode":"3832 BA",
    "sg:province":"Utrecht",
    "wof:name":"R. Rijnders",
    "wof:placetype":"venue"
},
  "geometry": {"coordinates":[5.406398,52.112904],"type":"Point"}
}