{
  "type": "Feature",
  "properties": {
    "addr:full":"St Franciscuswg 21 Heerlen Limburg 6411 GH",
    "addr:housenumber":"21",
    "addr:postcode":"6411 gh",
    "iso:country":"NL",
    "sg:address":"St Franciscuswg 21",
    "sg:city":"Heerlen",
    "sg:orig_category":"Verzekeringen - Verzekeringskantoren",
    "sg:phone":"+31 45 574 3595",
    "sg:postcode":"6411 GH",
    "sg:province":"Limburg",
    "wof:name":"Eva",
    "wof:placetype":"venue"
},
  "geometry": {"coordinates":[5.985665,50.883148],"type":"Point"}
}