{
  "type": "Feature",
  "properties": {
    "addr:full":"Postbus 1086 Eindhoven Noord-Brabant 5602 BB",
    "addr:housenumber":"1086",
    "addr:postcode":"5602 bb",
    "addr:street":"Postbus",
    "iso:country":"NL",
    "sg:address":"Postbus 1086",
    "sg:city":"Eindhoven",
    "sg:orig_category":"Werving En Selectie",
    "sg:phone":"+31 40 291 2796",
    "sg:postcode":"5602 BB",
    "sg:province":"Noord-Brabant",
    "wof:name":"Anma Connection",
    "wof:placetype":"venue"
},
  "geometry": {"coordinates":[5.4841098785,51.4344711304],"type":"Point"}
}