{
  "type": "Feature",
  "properties": {
    "iso:country":"NL",
    "sg:address":"Breezijde 9",
    "sg:city":"Nieuwland",
    "sg:orig_category":"Verzekeringen",
    "sg:phone":"+31 183 351 483",
    "sg:postcode":"4243 JM",
    "sg:province":"South Holland",
    "wof:name":"Assurantiekantoor A Van Rossem",
    "wof:placetype":"venue"
},
  "geometry": {"coordinates":[5.013803,51.898098],"type":"Point"}
}