{
  "type": "Feature",
  "properties": {
    "iso:country":"NL",
    "sg:address":"Koningin Emmakade 4",
    "sg:city":"'S Gravenhage",
    "sg:orig_category":"Autokeuringen",
    "sg:phone":"+31 70 364 5857",
    "sg:postcode":"2518 RJ",
    "sg:province":"South Holland",
    "wof:name":"R En S Automobielen",
    "wof:placetype":"venue"
},
  "geometry": {"coordinates":[4.293996,52.076832],"type":"Point"}
}