{
  "type": "Feature",
  "properties": {
    "addr:full":"Hofsln 119 Berlikum Fr Friesland 9041 AN",
    "addr:housenumber":"119",
    "addr:postcode":"9041 an",
    "iso:country":"NL",
    "sg:address":"Hofsln 119",
    "sg:city":"Berlikum Fr",
    "sg:classifiers":[
        {
            "category":"Arena",
            "subcategory":"Auto Racetrack",
            "type":"Entertainment"
        }
    ],
    "sg:phone":"+31 518 461 900",
    "sg:postcode":"9041 AN",
    "sg:province":"Friesland",
    "sg:tags":[
        "en",
        "racebanen",
        "kart-"
    ],
    "wof:name":"Berlikum Bv",
    "wof:placetype":"venue"
},
  "geometry": {"coordinates":[5.653159,53.244648],"type":"Point"}
}