{
  "type": "Feature",
  "properties": {
    "addr:full":"Schinkelstr 11B Heerlen Limburg 6411 LN",
    "addr:housenumber":"11b",
    "addr:postcode":"6411 ln",
    "addr:street":"Schinkelstr",
    "iso:country":"NL",
    "sg:address":"Schinkelstr 11B",
    "sg:city":"Heerlen",
    "sg:orig_category":"Woningbouw- Verenigingen En -Stichtingen",
    "sg:phone":"+31 495 454 650",
    "sg:postcode":"6411 LN",
    "sg:province":"Limburg",
    "sg:website":"http://www.balanswonen.nl",
    "wof:name":"Balans",
    "wof:placetype":"venue"
},
  "geometry": {"coordinates":[5.9748969078,50.8881225586],"type":"Point"}
}