{
  "type": "Feature",
  "properties": {
    "addr:full":"Kamillestr 2 Purmerend Noord-Holland 1441 NZ",
    "addr:housenumber":"2",
    "addr:postcode":"1441 nz",
    "addr:street":"Kamillestr",
    "iso:country":"NL",
    "sg:address":"Kamillestr 2",
    "sg:city":"Purmerend",
    "sg:orig_category":"Administratie- En Boekhoudkantoren",
    "sg:phone":"+31 299 472 452",
    "sg:postcode":"1441 NZ",
    "sg:province":"Noord-Holland",
    "wof:name":"Geerling, R P",
    "wof:placetype":"venue"
},
  "geometry": {"coordinates":[4.957899,52.495441],"type":"Point"}
}