{
  "type": "Feature",
  "properties": {
    "addr:full":"Peperstr 3 S Hertogenbosch North Brabant 5211 KM",
    "addr:housenumber":"3",
    "addr:postcode":"5211 km",
    "addr:street":"Peperstr",
    "iso:country":"NL",
    "sg:address":"Peperstr 3",
    "sg:city":"S Hertogenbosch",
    "sg:orig_category":"Projectontwikkeling",
    "sg:phone":"+31 73 614 2211",
    "sg:postcode":"5211 KM",
    "sg:province":"North Brabant",
    "wof:name":"Crescendo Bv",
    "wof:placetype":"venue"
},
  "geometry": {"coordinates":[5.306954,51.686539],"type":"Point"}
}