{
  "type": "Feature",
  "properties": {
    "iso:country":"NL",
    "sg:address":"1E J V Campenstr 12",
    "sg:city":"Amsterdam",
    "sg:orig_category":"Webdesign Bureaus",
    "sg:phone":"+31 20 771 4595",
    "sg:postcode":"1072 BE",
    "sg:province":"Noord-Holland",
    "sg:website":"http://www.site-division.nl",
    "wof:name":"Site Division",
    "wof:placetype":"venue"
},
  "geometry": {"coordinates":[4.8875861168,52.3574066162],"type":"Point"}
}