{
  "type": "Feature",
  "properties": {
    "addr:full":"Kerkstr 22 Rossum Gld Gelderland 5328 AB",
    "addr:housenumber":"22",
    "addr:postcode":"5328 ab",
    "addr:street":"Kerkstr;Gld Gelderland",
    "iso:country":"NL",
    "sg:address":"Kerkstr 22",
    "sg:city":"Rossum Gld",
    "sg:orig_category":"Afslankinstituten",
    "sg:phone":"+31 418 662 113",
    "sg:postcode":"5328 AB",
    "sg:province":"Gelderland",
    "wof:name":"Wetering-Van Heusden, S Van De",
    "wof:placetype":"venue"
},
  "geometry": {"coordinates":[5.33725,51.802029],"type":"Point"}
}