{
  "type": "Feature",
  "properties": {
    "iso:country":"NL",
    "sg:address":"Gorechtkd 44B",
    "sg:city":"Groningen",
    "sg:orig_category":"Schilders",
    "sg:phone":"+31 50 312 6240",
    "sg:postcode":"9713 CC",
    "sg:province":"Groningen",
    "wof:name":"Erich Schildersbedrijf",
    "wof:placetype":"venue"
},
  "geometry": {"coordinates":[6.579774,53.223312],"type":"Point"}
}