{
  "type": "Feature",
  "properties": {
    "addr:full":"Koningin Julianalaan 11 Maartensdijk Utrecht 3738 VA",
    "addr:housenumber":"11",
    "addr:postcode":"3738",
    "addr:street":"Koningin Julianalaan",
    "iso:country":"NL",
    "sg:address":"Koningin Julianalaan 11",
    "sg:city":"Maartensdijk",
    "sg:orig_category":"Verzekeringen",
    "sg:phone":"+31 346 213 676",
    "sg:postcode":"3738 VA",
    "sg:province":"Utrecht",
    "wof:name":"Stichting Kolibri",
    "wof:placetype":"venue"
},
  "geometry": {"coordinates":[5.182998,52.156799],"type":"Point"}
}