{
  "type": "Feature",
  "properties": {
    "addr:full":"Klinkerstr 9 Grave Louisiana 5361 GV",
    "addr:housenumber":"9",
    "addr:postcode":"5361 gv",
    "addr:street":"Klinkerstr;Louisiana",
    "iso:country":"NL",
    "sg:address":"Klinkerstr 9",
    "sg:city":"Grave",
    "sg:orig_category":"Behangselpapier En Wandbekleding",
    "sg:phone":"+31 486 472 186",
    "sg:postcode":"5361 GV",
    "sg:province":"Louisiana",
    "wof:name":"Derks",
    "wof:placetype":"venue"
},
  "geometry": {"coordinates":[-92.1517410278,32.9292526245],"type":"Point"}
}