{
  "type": "Feature",
  "properties": {
    "addr:full":"Utrechtsewg 109C Utrecht Utrecht 3544 NA",
    "addr:housenumber":"109c",
    "addr:postcode":"3544 na",
    "addr:street":"Utrechtsewg",
    "iso:country":"NL",
    "sg:address":"Utrechtsewg 109C",
    "sg:city":"Utrecht",
    "sg:classifiers":[
        {
            "category":"Professional",
            "type":"Services"
        }
    ],
    "sg:phone":"+31 30 677 9891",
    "sg:postcode":"3544 NA",
    "sg:province":"Utrecht",
    "sg:tags":[
        "leasing"
    ],
    "wof:name":"Taxi Lease Int",
    "wof:placetype":"venue"
},
  "geometry": {"coordinates":[5.049783,52.098232],"type":"Point"}
}