{
  "type": "Feature",
  "properties": {
    "addr:full":"De Sterke Arm 3 Veenendaal Utrecht 3901 EK",
    "addr:housenumber":"3",
    "addr:postcode":"3901 ek",
    "addr:street":"De Sterke Arm",
    "iso:country":"NL",
    "sg:address":"De Sterke Arm 3",
    "sg:city":"Veenendaal",
    "sg:orig_category":"Bibliotheken And Openbare Archieven",
    "sg:phone":"+31 318 523 950",
    "sg:postcode":"3901 EK",
    "sg:province":"Utrecht",
    "wof:name":"Speelotheek De Bolderwagen",
    "wof:placetype":"venue"
},
  "geometry": {"coordinates":[5.554947,52.022694],"type":"Point"}
}