{
  "type": "Feature",
  "properties": {
    "addr:full":"Weteringsdk 4 Odyk Utrecht 3984 LL",
    "addr:housenumber":"4",
    "addr:postcode":"3984 ll",
    "addr:street":"Weteringsdk",
    "iso:country":"NL",
    "sg:address":"Weteringsdk 4",
    "sg:city":"Odyk",
    "sg:orig_category":"Verzekeringen - Verzekeringskantoren",
    "sg:phone":"+31 30 657 1547",
    "sg:postcode":"3984 LL",
    "sg:province":"Utrecht",
    "wof:name":"Bomenrijck",
    "wof:placetype":"venue"
},
  "geometry": {"coordinates":[5.23238,52.050835],"type":"Point"}
}