{
  "type": "Feature",
  "properties": {
    "addr:full":"Parnassusweg 8 Amsterdam Noord-Holland 1076 AN",
    "addr:housenumber":"8",
    "addr:postcode":"1076 an",
    "addr:street":"Parnassusweg",
    "iso:country":"NL",
    "sg:address":"Parnassusweg 8",
    "sg:city":"Amsterdam",
    "sg:orig_category":"Makelaars In Onroerend Goed",
    "sg:phone":"+31 20 671 3303",
    "sg:postcode":"1076 AN",
    "sg:province":"Noord-Holland",
    "wof:name":"Bakkenist & Van Lonkhuizen Makelaars",
    "wof:placetype":"venue"
},
  "geometry": {"coordinates":[4.866971,52.346001],"type":"Point"}
}