{
  "type": "Feature",
  "properties": {
    "iso:country":"NL",
    "sg:address":"Thuvinestr 38",
    "sg:city":"Duiven",
    "sg:orig_category":"Fietsen - Fabrieken En Groothandel",
    "sg:phone":"+31 316 265 511",
    "sg:postcode":"6921 BC",
    "sg:province":"Gelderland",
    "wof:name":"Eurocycles",
    "wof:placetype":"venue"
},
  "geometry": {"coordinates":[-126.555511,54.485668],"type":"Point"}
}