{
  "type": "Feature",
  "properties": {
    "addr:full":"Dwarssplitting 2 Stadskanaal Groningen 9502 CA",
    "addr:housenumber":"2",
    "addr:postcode":"9502 ca",
    "addr:street":"Dwarssplitting",
    "iso:country":"NL",
    "sg:address":"Dwarssplitting 2",
    "sg:city":"Stadskanaal",
    "sg:orig_category":"Verzekeringen",
    "sg:phone":"+31 599 615 705",
    "sg:postcode":"9502 CA",
    "sg:province":"Groningen",
    "wof:name":"Assurantiekantoor Wolters En Renkema",
    "wof:placetype":"venue"
},
  "geometry": {"coordinates":[6.964968,52.99548],"type":"Point"}
}