{
  "type": "Feature",
  "properties": {
    "addr:full":"Vaartpln 4 S Gravenzande Zuid-Holland 2691 AJ",
    "addr:housenumber":"4;gravenzande",
    "addr:postcode":"2691 aj",
    "addr:street":"Vaartpln;S",
    "iso:country":"NL",
    "sg:address":"Vaartpln 4",
    "sg:city":"S Gravenzande",
    "sg:orig_category":"Woninginrichting",
    "sg:phone":"+31 174 412 364",
    "sg:postcode":"2691 AJ",
    "sg:province":"Zuid-Holland",
    "wof:name":"Tebbenhoff",
    "wof:placetype":"venue"
},
  "geometry": {"coordinates":[4.161965847,52.0035324097],"type":"Point"}
}