{
  "type": "Feature",
  "properties": {
    "addr:full":"Kloveniersburgwal 65Hs Amsterdam North Holland 1011 JZ",
    "addr:housenumber":"65hs",
    "addr:postcode":"1011 jz",
    "addr:street":"Kloveniersburgwal",
    "iso:country":"NL",
    "sg:address":"Kloveniersburgwal 65Hs",
    "sg:city":"Amsterdam",
    "sg:orig_category":"Diverse Grafische Activiteiten",
    "sg:phone":"+31 20 625 8950",
    "sg:postcode":"1011 JZ",
    "sg:province":"North Holland",
    "wof:name":"Bunder Brordus Studio",
    "wof:placetype":"venue"
},
  "geometry": {"coordinates":[4.898361,52.370049],"type":"Point"}
}