{
  "type": "Feature",
  "properties": {
    "iso:country":"NL",
    "sg:address":"Dennenln 2",
    "sg:city":"Ermelo",
    "sg:orig_category":"Bejaarden - Verzorgingstehuizen",
    "sg:phone":"+31 341 556 854",
    "sg:postcode":"3851 PW",
    "sg:province":"Gelderland",
    "wof:name":"Rehoboth, Stich",
    "wof:placetype":"venue"
},
  "geometry": {"coordinates":[5.62714,52.302895],"type":"Point"}
}