{
  "type": "Feature",
  "properties": {
    "iso:country":"NL",
    "sg:address":"Boterzwin 1212",
    "sg:city":"Den Helder",
    "sg:orig_category":"Adviesbureaus Bedrijfsorganisatie",
    "sg:phone":"+31 223 647 226",
    "sg:postcode":"1788 VV",
    "sg:province":"Noord-Holland",
    "wof:name":"Kadix",
    "wof:placetype":"venue"
},
  "geometry": {"coordinates":[4.736788,52.88475],"type":"Point"}
}