{
  "type": "Feature",
  "properties": {
    "addr:full":"Lynbaan 16 Heemskerk North Holland 1969 NE",
    "addr:housenumber":"16",
    "addr:postcode":"1969 ne",
    "addr:street":"Lynbaan",
    "iso:country":"NL",
    "sg:address":"Lynbaan 16",
    "sg:city":"Heemskerk",
    "sg:orig_category":"Automaterialen En Gereedschappen",
    "sg:phone":"+31 251 252 244",
    "sg:postcode":"1969 NE",
    "sg:province":"North Holland",
    "wof:name":"Velu Bv",
    "wof:placetype":"venue"
},
  "geometry": {"coordinates":[4.62565,52.513199],"type":"Point"}
}