{
  "type": "Feature",
  "properties": {
    "addr:full":"Vierakkerstr 7A Huissen Gelderland 6851 BA",
    "addr:housenumber":"7a",
    "addr:postcode":"6851 ba",
    "addr:street":"Vierakkerstr;Gelderland",
    "iso:country":"NL",
    "sg:address":"Vierakkerstr 7A",
    "sg:city":"Huissen",
    "sg:orig_category":"Kinderopvang",
    "sg:phone":"+31 26 442 1880",
    "sg:postcode":"6851 BA",
    "sg:province":"Gelderland",
    "wof:name":"Centrum, 'T",
    "wof:placetype":"venue"
},
  "geometry": {"coordinates":[5.941263,51.93568],"type":"Point"}
}