{
  "type": "Feature",
  "properties": {
    "addr:full":"Stationswg 54 Eindhoven North Brabant 5611 BZ",
    "addr:housenumber":"54",
    "addr:postcode":"5611 bz",
    "addr:street":"Stationswg",
    "iso:country":"NL",
    "sg:address":"Stationswg 54",
    "sg:city":"Eindhoven",
    "sg:orig_category":"Werving En Selectie",
    "sg:phone":"+31 40 264 9090",
    "sg:postcode":"5611 BZ",
    "sg:province":"North Brabant",
    "sg:website":"http://www.gegarandeerd.nl",
    "wof:name":"Avance Eindhoven Bv",
    "wof:placetype":"venue"
},
  "geometry": {"coordinates":[5.4841051102,51.4344711304],"type":"Point"}
}