{
  "type": "Feature",
  "properties": {
    "addr:full":"Haarstraat 6 Tuil Gelderland 4176 BL",
    "addr:housenumber":"6",
    "addr:postcode":"4176 bl",
    "addr:street":"Haarstraat;Gelderland",
    "iso:country":"NL",
    "sg:address":"Haarstraat 6",
    "sg:city":"Tuil",
    "sg:orig_category":"Kampeerterreinen",
    "sg:phone":"+31 418 591 297",
    "sg:postcode":"4176 BL",
    "sg:province":"Gelderland",
    "wof:name":"Camping Klingelenberg",
    "wof:placetype":"venue"
},
  "geometry": {"coordinates":[5.2438960075,51.8235092163],"type":"Point"}
}