{
  "type": "Feature",
  "properties": {
    "iso:country":"NL",
    "sg:address":"Hilleniussingel 23",
    "sg:city":"Rotterdam",
    "sg:classifiers":[
        {
            "category":"Education",
            "subcategory":"Preschool",
            "type":"Public Place"
        }
    ],
    "sg:phone":"+31 10 418 9053",
    "sg:postcode":"3054 EX",
    "sg:province":"Zuid-Holland",
    "sg:tags":[
        "kleuteronderwijs",
        "basis-"
    ],
    "wof:name":"Emma School",
    "wof:placetype":"venue"
},
  "geometry": {"coordinates":[4.492844,51.956856],"type":"Point"}
}