{
  "type": "Feature",
  "properties": {
    "addr:full":"A Brietstr 3 Nunspeet Gelderland 8072 GW",
    "addr:housenumber":"3",
    "addr:postcode":"8072 gw",
    "addr:street":"Gelderland",
    "iso:country":"NL",
    "sg:address":"A Brietstr 3",
    "sg:city":"Nunspeet",
    "sg:orig_category":"Artsen - Huisartsen",
    "sg:phone":"+31 341 251 777",
    "sg:postcode":"8072 GW",
    "sg:province":"Gelderland",
    "wof:name":"Oudega, R",
    "wof:placetype":"venue"
},
  "geometry": {"coordinates":[5.796341,52.38905],"type":"Point"}
}