{
  "type": "Feature",
  "properties": {
    "addr:full":"Frankeneng 55 Ede Gld Gelderland 6716 AA",
    "addr:housenumber":"55",
    "addr:postcode":"6716 aa",
    "addr:street":"Frankeneng;Gld Gelderland",
    "iso:country":"NL",
    "sg:address":"Frankeneng 55",
    "sg:city":"Ede Gld",
    "sg:orig_category":"Bouwnijverheidsmachines Gh",
    "sg:phone":"+31 318 660 500",
    "sg:postcode":"6716 AA",
    "sg:province":"Gelderland",
    "wof:name":"Bt Nederland Bv",
    "wof:placetype":"venue"
},
  "geometry": {"coordinates":[5.626254,52.034054],"type":"Point"}
}