{
  "type": "Feature",
  "properties": {
    "iso:country":"NL",
    "sg:address":"Woonboulev 22",
    "sg:city":"Almelo",
    "sg:orig_category":"Bedden En Matrassen",
    "sg:phone":"+31 546 853 239",
    "sg:postcode":"7606 JA",
    "sg:province":"Overijssel",
    "sg:website":"http://www.beterbed.nl",
    "wof:name":"Beter Bed",
    "wof:placetype":"venue"
},
  "geometry": {"coordinates":[6.64343,52.340309],"type":"Point"}
}