{
  "type": "Feature",
  "properties": {
    "addr:full":"Engelandlaan 390 Zoetermeer South Holland 2711 DZ",
    "addr:housenumber":"390",
    "addr:postcode":"2711 dz",
    "addr:street":"Engelandlaan",
    "iso:country":"NL",
    "sg:address":"Engelandlaan 390",
    "sg:city":"Zoetermeer",
    "sg:orig_category":"Diverse Bedrijfsinstallaties Gh",
    "sg:phone":"+31 79 345 1111",
    "sg:postcode":"2711 DZ",
    "sg:province":"South Holland",
    "wof:name":"Sulzer Nederland Bv",
    "wof:placetype":"venue"
},
  "geometry": {"coordinates":[4.49191,52.060398],"type":"Point"}
}