{
  "type": "Feature",
  "properties": {
    "addr:full":"Kempenaar 144 Lelystad Flevoland 8242 BA",
    "addr:housenumber":"144",
    "addr:postcode":"8242 ba",
    "addr:street":"Kempenaar;Flevoland",
    "iso:country":"NL",
    "sg:address":"Kempenaar 144",
    "sg:city":"Lelystad",
    "sg:orig_category":"Schilderwerk",
    "sg:phone":"+31 320 230 779",
    "sg:postcode":"8242 BA",
    "sg:province":"Flevoland",
    "wof:name":"Grival Bv",
    "wof:placetype":"venue"
},
  "geometry": {"coordinates":[5.460443,52.518105],"type":"Point"}
}