{
  "type": "Feature",
  "properties": {
    "addr:full":"Stadserf 62 Schiedam South Holland 3112 DX",
    "addr:housenumber":"62",
    "addr:postcode":"3112 dx",
    "addr:street":"Stadserf",
    "iso:country":"NL",
    "sg:address":"Stadserf 62",
    "sg:city":"Schiedam",
    "sg:orig_category":"Werving And Selectie Van Tijdelijk Personeel And Uitzendkantoren",
    "sg:phone":"+31 10 426 9449",
    "sg:postcode":"3112 DX",
    "sg:province":"South Holland",
    "wof:name":"Start",
    "wof:placetype":"venue"
},
  "geometry": {"coordinates":[4.4034810066,51.9175796509],"type":"Point"}
}