{
  "type": "Feature",
  "properties": {
    "addr:full":"Schreurswg 61 Enschede Overijssel 7531 AK",
    "addr:housenumber":"61",
    "addr:postcode":"7531 ak",
    "addr:street":"Schreurswg",
    "iso:country":"NL",
    "sg:address":"Schreurswg 61",
    "sg:city":"Enschede",
    "sg:orig_category":"Fotografie Reclame En Mode",
    "sg:phone":"+31 53 431 9621",
    "sg:postcode":"7531 AK",
    "sg:province":"Overijssel",
    "wof:name":"Haverkort",
    "wof:placetype":"venue"
},
  "geometry": {"coordinates":[6.908154,52.230785],"type":"Point"}
}