{
  "type": "Feature",
  "properties": {
    "addr:full":"Bosberg 22 Borculo Gelderland 7271 LG",
    "addr:housenumber":"22",
    "addr:postcode":"7271 lg",
    "addr:street":"Bosberg;Gelderland",
    "iso:country":"NL",
    "sg:address":"Bosberg 22",
    "sg:city":"Borculo",
    "sg:orig_category":"Verhuur",
    "sg:phone":"+31 545 273 476",
    "sg:postcode":"7271 LG",
    "sg:province":"Gelderland",
    "wof:name":"Crossroads",
    "wof:placetype":"venue"
},
  "geometry": {"coordinates":[6.52329,52.116772],"type":"Point"}
}