{
  "type": "Feature",
  "properties": {
    "addr:full":"Exelseweg 10 Laren Gld Gelderland 7245 VE",
    "addr:housenumber":"10",
    "addr:postcode":"7245",
    "addr:street":"Exelseweg;Gld Gelderland;Ve",
    "iso:country":"NL",
    "sg:address":"Exelseweg 10",
    "sg:city":"Laren Gld",
    "sg:orig_category":"Fotostudio'S And Fotografen",
    "sg:phone":"+31 573 421 270",
    "sg:postcode":"7245 VE",
    "sg:province":"Gelderland",
    "wof:name":"Alex Arkink Fotografie",
    "wof:placetype":"venue"
},
  "geometry": {"coordinates":[6.413148,52.182774],"type":"Point"}
}