{
  "type": "Feature",
  "properties": {
    "addr:full":"Populierenlaan 9 Boxtel North Brabant 5283 CZ",
    "addr:housenumber":"9",
    "addr:postcode":"5283",
    "addr:street":"Populierenlaan",
    "iso:country":"NL",
    "sg:address":"Populierenlaan 9",
    "sg:city":"Boxtel",
    "sg:classifiers":[
        {
            "category":"Education",
            "subcategory":"Preschool",
            "type":"Public Place"
        }
    ],
    "sg:phone":"+31 411 672 459",
    "sg:postcode":"5283 CZ",
    "sg:province":"North Brabant",
    "sg:tags":[
        "kleuteronderwijs",
        "basis-"
    ],
    "wof:name":"Openbare Basisschool De Oosterpoort",
    "wof:placetype":"venue"
},
  "geometry": {"coordinates":[5.34091,51.58844],"type":"Point"}
}