{
  "type": "Feature",
  "properties": {
    "addr:full":"Starwg 22 Heemskerk Noord-Holland 1964 PZ",
    "addr:housenumber":"22",
    "addr:postcode":"1964 pz",
    "addr:street":"Starwg",
    "iso:country":"NL",
    "sg:address":"Starwg 22",
    "sg:city":"Heemskerk",
    "sg:orig_category":"Bloemen En Planten - Groothandel",
    "sg:phone":"+31 251 250 076",
    "sg:postcode":"1964 PZ",
    "sg:province":"Noord-Holland",
    "wof:name":"Maruwa",
    "wof:placetype":"venue"
},
  "geometry": {"coordinates":[4.654769,52.507576],"type":"Point"}
}