{
  "type": "Feature",
  "properties": {
    "iso:country":"NL",
    "sg:address":"Kantstraat 35",
    "sg:city":"Landgraaf",
    "sg:orig_category":"Meubelreparatie And -Restauratie",
    "sg:phone":"+31 45 531 4522",
    "sg:postcode":"6374 EE",
    "sg:province":"Limburg",
    "wof:name":"J V.D. Zwaag",
    "wof:placetype":"venue"
},
  "geometry": {"coordinates":[6.042217,50.915672],"type":"Point"}
}