{
  "type": "Feature",
  "properties": {
    "iso:country":"NL",
    "sg:address":"Gestelsestraat 7A",
    "sg:city":"Waalre",
    "sg:orig_category":"Verbouwingen",
    "sg:phone":"+31 40 222 1460",
    "sg:postcode":"5582 HE",
    "sg:province":"North Brabant",
    "wof:name":"Vhvb",
    "wof:placetype":"venue"
},
  "geometry": {"coordinates":[5.476404,51.398029],"type":"Point"}
}