{
  "type": "Feature",
  "properties": {
    "addr:full":"Gestelsestraat 7A Waalre North Brabant 5582 HE",
    "addr:housenumber":"7a",
    "addr:postcode":"5582 he",
    "addr:street":"Gestelsestraat",
    "iso:country":"NL",
    "sg:address":"Gestelsestraat 7A",
    "sg:city":"Waalre",
    "sg:orig_category":"Verbouwingen",
    "sg:phone":"+31 40 222 1460",
    "sg:postcode":"5582 HE",
    "sg:province":"North Brabant",
    "wof:name":"Vhvb",
    "wof:placetype":"venue"
},
  "geometry": {"coordinates":[5.476404,51.398029],"type":"Point"}
}