{
  "type": "Feature",
  "properties": {
    "addr:full":"Nieuwe Gr 116 Haarlem Noord-Holland 2011 NM",
    "addr:housenumber":"116",
    "addr:postcode":"2011",
    "addr:street":"Nieuwe Gr",
    "iso:country":"NL",
    "sg:address":"Nieuwe Gr 116",
    "sg:city":"Haarlem",
    "sg:orig_category":"Onroerende Goederen",
    "sg:phone":"+31 23 531 0504",
    "sg:postcode":"2011 NM",
    "sg:province":"Noord-Holland",
    "wof:name":"Muller En Van De Lande Bv",
    "wof:placetype":"venue"
},
  "geometry": {"coordinates":[4.63374,52.385532],"type":"Point"}
}