{
  "type": "Feature",
  "properties": {
    "iso:country":"NL",
    "sg:address":"Oostdorperwg 49",
    "sg:city":"Wassenaar",
    "sg:orig_category":"Wereldwinkels",
    "sg:phone":"+31 70 517 0909",
    "sg:postcode":"2242 NE",
    "sg:province":"Zuid-Holland",
    "sg:website":"http://www.wereldwinkelwassenaar.nl",
    "wof:name":"Wereldwinkel",
    "wof:placetype":"venue"
},
  "geometry": {"coordinates":[4.3963360786,52.1485595703],"type":"Point"}
}