{
  "type": "Feature",
  "properties": {
    "addr:full":"Okeghemstr 31 Amsterdam Noord-Holland 1075 PL",
    "addr:housenumber":"31",
    "addr:postcode":"1075 pl",
    "addr:street":"Okeghemstr",
    "iso:country":"NL",
    "sg:address":"Okeghemstr 31",
    "sg:city":"Amsterdam",
    "sg:orig_category":"Filmstudio'S En -Productie",
    "sg:phone":"+31 20 662 7453",
    "sg:postcode":"1075 PL",
    "sg:province":"Noord-Holland",
    "wof:name":"Richters, A W",
    "wof:placetype":"venue"
},
  "geometry": {"coordinates":[4.863216,52.351151],"type":"Point"}
}