{
  "type": "Feature",
  "properties": {
    "iso:country":"NL",
    "sg:address":"Burgemeester V Leeuwenln 49",
    "sg:city":"Amsterdam",
    "sg:orig_category":"Kappers",
    "sg:phone":"+31 20 613 4917",
    "sg:postcode":"1064 KK",
    "sg:province":"Noord-Holland",
    "wof:name":"Kapsalon Tiffany'S",
    "wof:placetype":"venue"
},
  "geometry": {"coordinates":[4.8120861053,52.3760147095],"type":"Point"}
}