{
  "type": "Feature",
  "properties": {
    "addr:full":"Sonneveld 14 'S Hertogenbosch North Brabant 5211 GS",
    "addr:housenumber":"14",
    "addr:postcode":"5211 gs",
    "addr:street":"Sonneveld;' S Hertogenbosch",
    "iso:country":"NL",
    "sg:address":"Sonneveld 14",
    "sg:city":"'S Hertogenbosch",
    "sg:orig_category":"Bedrijfs- And Managementsconsultants",
    "sg:phone":"+31 73 613 6161",
    "sg:postcode":"5211 GS",
    "sg:province":"North Brabant",
    "wof:name":"Industrie- En Handelsmaatschappij Pieke Bv",
    "wof:placetype":"venue"
},
  "geometry": {"coordinates":[5.295296,51.683735],"type":"Point"}
}