{
  "type": "Feature",
  "properties": {
    "addr:full":"Zaanstr 156 Amsterdam North Holland 1013 RW",
    "addr:housenumber":"156",
    "addr:postcode":"1013 rw",
    "iso:country":"NL",
    "sg:address":"Zaanstr 156",
    "sg:city":"Amsterdam",
    "sg:orig_category":"Kappers",
    "sg:phone":"+31 20 682 6723",
    "sg:postcode":"1013 RW",
    "sg:province":"North Holland",
    "wof:name":"Dungen, C M Van",
    "wof:placetype":"venue"
},
  "geometry": {"coordinates":[4.8761777878,52.3889579773],"type":"Point"}
}