{
  "type": "Feature",
  "properties": {
    "addr:full":"Watermanwg 17 Rotterdam South Holland 3067 GA",
    "addr:housenumber":"17",
    "addr:postcode":"3067 ga",
    "addr:street":"Watermanwg",
    "iso:country":"NL",
    "sg:address":"Watermanwg 17",
    "sg:city":"Rotterdam",
    "sg:orig_category":"Meubelen",
    "sg:phone":"+31 10 421 9985",
    "sg:postcode":"3067 GA",
    "sg:province":"South Holland",
    "wof:name":"Lagerwaard Classic Bv",
    "wof:placetype":"venue"
},
  "geometry": {"coordinates":[4.560056,51.951443],"type":"Point"}
}