{
  "type": "Feature",
  "properties": {
    "addr:full":"De Middend 232 Bovenkarspel Noord-Holland 1611 KM",
    "addr:housenumber":"232",
    "addr:postcode":"1611 km",
    "addr:street":"De Middend",
    "iso:country":"NL",
    "sg:address":"De Middend 232",
    "sg:city":"Bovenkarspel",
    "sg:orig_category":"Dameskleding",
    "sg:phone":"+31 228 522 775",
    "sg:postcode":"1611 KM",
    "sg:province":"Noord-Holland",
    "wof:name":"Feminin Fashion",
    "wof:placetype":"venue"
},
  "geometry": {"coordinates":[5.235211,52.696655],"type":"Point"}
}