{
  "type": "Feature",
  "properties": {
    "addr:full":"Boulevard 70 Zeist Utrecht 3707 BN",
    "addr:housenumber":"70",
    "addr:postcode":"3707 bn",
    "addr:street":"Boulevard",
    "iso:country":"NL",
    "sg:address":"Boulevard 70",
    "sg:city":"Zeist",
    "sg:orig_category":"Autokeuringen",
    "sg:phone":"+31 30 691 8982",
    "sg:postcode":"3707 BN",
    "sg:province":"Utrecht",
    "wof:name":"Shell",
    "wof:placetype":"venue"
},
  "geometry": {"coordinates":[5.259775,52.103638],"type":"Point"}
}