{
  "type": "Feature",
  "properties": {
    "iso:country":"NL",
    "sg:address":"Boulevard 70",
    "sg:city":"Zeist",
    "sg:orig_category":"Autokeuringen",
    "sg:phone":"+31 30 691 8982",
    "sg:postcode":"3707 BN",
    "sg:province":"Utrecht",
    "wof:name":"Shell",
    "wof:placetype":"venue"
},
  "geometry": {"coordinates":[5.259775,52.103638],"type":"Point"}
}