{
  "type": "Feature",
  "properties": {
    "iso:country":"NL",
    "sg:address":"Rykswg Z 18A , (Ind Terr Pannenwg)",
    "sg:city":"Nederweert",
    "sg:orig_category":"Plafonds",
    "sg:phone":"+31 495 460 133",
    "sg:postcode":"6031 RL",
    "sg:province":"Limburg",
    "wof:name":"Multi-Fix Interieurafbouw",
    "wof:placetype":"venue"
},
  "geometry": {"coordinates":[5.746135,51.28743],"type":"Point"}
}