{
  "type": "Feature",
  "properties": {
    "addr:full":"Rykswg Z 18A , (Ind Terr Pannenwg) Nederweert Limburg 6031 RL",
    "addr:housenumber":"18a",
    "addr:postcode":"6031 rl",
    "addr:street":"Terr Pannenwg",
    "iso:country":"NL",
    "sg:address":"Rykswg Z 18A , (Ind Terr Pannenwg)",
    "sg:city":"Nederweert",
    "sg:orig_category":"Plafonds",
    "sg:phone":"+31 495 460 133",
    "sg:postcode":"6031 RL",
    "sg:province":"Limburg",
    "wof:name":"Multi-Fix Interieurafbouw",
    "wof:placetype":"venue"
},
  "geometry": {"coordinates":[5.746135,51.28743],"type":"Point"}
}