{
  "type": "Feature",
  "properties": {
    "iso:country":"NL",
    "sg:address":"Kloosterstraat 11",
    "sg:city":"Bavel",
    "sg:orig_category":"Opticiens",
    "sg:phone":"+31 161 437 028",
    "sg:postcode":"4854 CL",
    "sg:province":"Noord-Brabant",
    "wof:name":"Optiek Arnold Bavel/Ulvenhout",
    "wof:placetype":"venue"
},
  "geometry": {"coordinates":[4.8308110237,51.5654335022],"type":"Point"}
}