{
  "type": "Feature",
  "properties": {
    "addr:full":"Brede Beek 11 Nykerk Gld Gelderland 3861 BC",
    "addr:housenumber":"11",
    "addr:postcode":"3861 bc",
    "addr:street":"Brede Beek;Gld Gelderland",
    "iso:country":"NL",
    "sg:address":"Brede Beek 11",
    "sg:city":"Nykerk Gld",
    "sg:orig_category":"Kappers",
    "sg:phone":"+31 33 246 1050",
    "sg:postcode":"3861 BC",
    "sg:province":"Gelderland",
    "sg:website":"http://www.ownlook.nl",
    "wof:name":"Own Look",
    "wof:placetype":"venue"
},
  "geometry": {"coordinates":[5.4831,52.221569],"type":"Point"}
}