{
  "type": "Feature",
  "properties": {
    "addr:full":"Rijksstraatweg 14 Geldermalsen Gelderland 4191 SE",
    "addr:housenumber":"14",
    "addr:postcode":"4191",
    "addr:street":"Rijksstraatweg;Gelderland;Se",
    "iso:country":"NL",
    "sg:address":"Rijksstraatweg 14",
    "sg:city":"Geldermalsen",
    "sg:classifiers":[
        {
            "category":"Food & Beverages",
            "subcategory":"Fruits & Vegetables",
            "type":"Retail Goods"
        }
    ],
    "sg:phone":"+31 345 580 052",
    "sg:postcode":"4191 SE",
    "sg:province":"Gelderland",
    "sg:tags":[
        "groenten"
    ],
    "wof:name":"Groente- En Fruitspeciaalzaak Buunders",
    "wof:placetype":"venue"
},
  "geometry": {"coordinates":[5.290115,51.882862],"type":"Point"}
}