{
  "type": "Feature",
  "properties": {
    "addr:full":"Bolspil 3 Geldermalsen Gelderland 4191 TG",
    "addr:housenumber":"3",
    "addr:postcode":"4191 tg",
    "addr:street":"Bolspil;Gelderland",
    "iso:country":"NL",
    "sg:address":"Bolspil 3",
    "sg:city":"Geldermalsen",
    "sg:orig_category":"Goudsmeden En Zilversmeden",
    "sg:phone":"+31 345 572 026",
    "sg:postcode":"4191 TG",
    "sg:province":"Gelderland",
    "wof:name":"Timmer, M",
    "wof:placetype":"venue"
},
  "geometry": {"coordinates":[5.281711,51.879391],"type":"Point"}
}