{
  "type": "Feature",
  "properties": {
    "addr:full":"Imkerberg 60 Roosendaal North Brabant 4708 JC",
    "addr:housenumber":"60",
    "addr:postcode":"4708 jc",
    "addr:street":"Imkerberg",
    "iso:country":"NL",
    "sg:address":"Imkerberg 60",
    "sg:city":"Roosendaal",
    "sg:orig_category":"Film-, Tv- And Videoproductie",
    "sg:phone":"+31 165 570 532",
    "sg:postcode":"4708 JC",
    "sg:province":"North Brabant",
    "wof:name":"Digivid",
    "wof:placetype":"venue"
},
  "geometry": {"coordinates":[4.435654,51.517742],"type":"Point"}
}