{
  "type": "Feature",
  "properties": {
    "addr:full":"Stationsstraat 32 Deurne Noord-Brabant 5751 HE",
    "addr:housenumber":"32",
    "addr:postcode":"5751 he",
    "addr:street":"Stationsstraat",
    "iso:country":"NL",
    "sg:address":"Stationsstraat 32",
    "sg:city":"Deurne",
    "sg:orig_category":"Werving And Selectie Van Tijdelijk Personeel And Uitzendkantoren",
    "sg:phone":"+31 493 320 492",
    "sg:postcode":"5751 HE",
    "sg:province":"Noord-Brabant",
    "wof:name":"Itproject",
    "wof:placetype":"venue"
},
  "geometry": {"coordinates":[5.792757988,51.462272644],"type":"Point"}
}