{
  "type": "Feature",
  "properties": {
    "iso:country":"NL",
    "sg:address":"Europalaan 6",
    "sg:city":"Utrecht Zuid",
    "sg:orig_category":"Autokeuringen",
    "sg:phone":"+31 30 289 5252",
    "sg:postcode":"3526 KS",
    "sg:province":"Utrecht",
    "wof:name":"R.K.A. Koch Carwash",
    "wof:placetype":"venue"
},
  "geometry": {"coordinates":[5.105534,52.074337],"type":"Point"}
}