{
  "type": "Feature",
  "properties": {
    "addr:full":"Zeelsterstraat 156 Eindhoven Noord-Brabant 5652 EN",
    "addr:housenumber":"156",
    "addr:postcode":"5652 en",
    "addr:street":"Zeelsterstraat",
    "iso:country":"NL",
    "sg:address":"Zeelsterstraat 156",
    "sg:city":"Eindhoven",
    "sg:orig_category":"Onderhoud And Reparatie Kantoorapparatuur",
    "sg:phone":"+31 40 257 3471",
    "sg:postcode":"5652 EN",
    "sg:province":"Noord-Brabant",
    "wof:name":"Sit Smans",
    "wof:placetype":"venue"
},
  "geometry": {"coordinates":[5.437555,51.43771],"type":"Point"}
}