{
  "type": "Feature",
  "properties": {
    "addr:full":"Laan 22 Schagen Noord-Holland 1741 EB",
    "addr:housenumber":"22",
    "addr:postcode":"1741 eb",
    "addr:street":"Laan",
    "iso:country":"NL",
    "sg:address":"Laan 22",
    "sg:city":"Schagen",
    "sg:orig_category":"Grafisch Ontwerpers",
    "sg:phone":"+31 224 216 633",
    "sg:postcode":"1741 EB",
    "sg:province":"Noord-Holland",
    "sg:website":"http://www.studiokolkman.nl",
    "wof:name":"Kolkman, Studio",
    "wof:placetype":"venue"
},
  "geometry": {"coordinates":[4.800047,52.785545],"type":"Point"}
}