{
  "type": "Feature",
  "properties": {
    "iso:country":"NL",
    "sg:address":"Nieuwstraat 9",
    "sg:city":"Helden",
    "sg:orig_category":"Overheidsdiensten",
    "sg:phone":"+31 77 307 3969",
    "sg:postcode":"5988 CE",
    "sg:province":"Illinois",
    "wof:name":"T Zaelke",
    "wof:placetype":"venue"
},
  "geometry": {"coordinates":[-89.4168395996,41.772731781],"type":"Point"}
}