{
  "type": "Feature",
  "properties": {
    "addr:full":"Erasmusplein 22 Papendrecht Zuid-Holland 3351 GG",
    "addr:housenumber":"22",
    "addr:postcode":"3351 gg",
    "addr:street":"Erasmusplein",
    "iso:country":"NL",
    "sg:address":"Erasmusplein 22",
    "sg:city":"Papendrecht",
    "sg:orig_category":"Kappers",
    "sg:phone":"+31 78 615 1551",
    "sg:postcode":"3351 GG",
    "sg:province":"Zuid-Holland",
    "wof:name":"Kapsalon Andre",
    "wof:placetype":"venue"
},
  "geometry": {"coordinates":[4.6826229095,51.8300743103],"type":"Point"}
}