{
  "type": "Feature",
  "properties": {
    "addr:full":"Ryndk 99A Hazerswoude Ryndyk Zuid-Holland 2394 AE",
    "addr:housenumber":"99a",
    "addr:postcode":"ryndyk;2394 ae",
    "addr:street":"Ryndk",
    "iso:country":"NL",
    "sg:address":"Ryndk 99A",
    "sg:city":"Hazerswoude Ryndyk",
    "sg:orig_category":"Adviesbureaus Bouwkunde",
    "sg:phone":"+31 71 341 9166",
    "sg:postcode":"2394 AE",
    "sg:province":"Zuid-Holland",
    "sg:website":"http://www.benbouw.nl",
    "wof:name":"Benbouw",
    "wof:placetype":"venue"
},
  "geometry": {"coordinates":[4.595154,52.131054],"type":"Point"}
}