{
  "type": "Feature",
  "properties": {
    "addr:full":"Rijksweg 39 Kessel Lb Limburg 5995 NT",
    "addr:housenumber":"39",
    "addr:postcode":"lb;5995 nt",
    "addr:street":"Rijksweg",
    "iso:country":"NL",
    "sg:address":"Rijksweg 39",
    "sg:city":"Kessel Lb",
    "sg:classifiers":[
        {
            "category":"Food & Beverages",
            "subcategory":"Fruits & Vegetables",
            "type":"Retail Goods"
        }
    ],
    "sg:phone":"+31 77 462 3037",
    "sg:postcode":"5995 NT",
    "sg:province":"Limburg",
    "sg:tags":[
        "groenten"
    ],
    "wof:name":"R.W.P. V/D Beuken-Stroucken",
    "wof:placetype":"venue"
},
  "geometry": {"coordinates":[6.0217,51.282181],"type":"Point"}
}