{
  "type": "Feature",
  "properties": {
    "iso:country":"NL",
    "sg:address":"Lyzyde 21",
    "sg:city":"Amersfoort",
    "sg:orig_category":"Grafisch Ontwerpers",
    "sg:phone":"+31 33 455 1676",
    "sg:postcode":"3823 TE",
    "sg:province":"Utrecht",
    "wof:name":"Giffel, J Te",
    "wof:placetype":"venue"
},
  "geometry": {"coordinates":[5.39682,52.189159],"type":"Point"}
}