{
  "type": "Feature",
  "properties": {
    "iso:country":"NL",
    "sg:address":"Fregat 82",
    "sg:city":"Lemmer",
    "sg:orig_category":"Goederenvervoer Over De Weg",
    "sg:phone":"+31 514 562 748",
    "sg:postcode":"8531 AK",
    "sg:province":"Provincie Friesland",
    "wof:name":"R.J.F. Postma",
    "wof:placetype":"venue"
},
  "geometry": {"coordinates":[5.717695,52.839859],"type":"Point"}
}