{
  "type": "Feature",
  "properties": {
    "addr:full":"Westerstraat 230 Enkhuizen Noord-Holland 1601 AR",
    "addr:housenumber":"230",
    "addr:postcode":"1601",
    "addr:street":"Westerstraat",
    "iso:country":"NL",
    "sg:address":"Westerstraat 230",
    "sg:city":"Enkhuizen",
    "sg:orig_category":"Bloemen And Planten",
    "sg:phone":"+31 228 322 401",
    "sg:postcode":"1601 AR",
    "sg:province":"Noord-Holland",
    "wof:name":"Bloemendaal Advies Groep",
    "wof:placetype":"venue"
},
  "geometry": {"coordinates":[5.280835,52.702343],"type":"Point"}
}