{
  "type": "Feature",
  "properties": {
    "addr:full":"Binnenhavenstraat 91 Hengelo Ov NL.08 7553 GH",
    "addr:housenumber":"91",
    "addr:postcode":"7553 gh",
    "addr:street":"Binnenhavenstraat;Ov",
    "iso:country":"NL",
    "sg:address":"Binnenhavenstraat 91",
    "sg:city":"Hengelo Ov",
    "sg:classifiers":[
        {
            "category":"Parking",
            "subcategory":"Lot",
            "type":"Transportation"
        }
    ],
    "sg:phone":"+31 74 290 9713",
    "sg:postcode":"7553 GH",
    "sg:province":"NL.08",
    "sg:tags":[
        "fab",
        "metalen",
        "tank"
    ],
    "wof:name":"Vidra Rolcontainers Bv",
    "wof:placetype":"venue"
},
  "geometry": {"coordinates":[6.772793,52.252129],"type":"Point"}
}