{
  "type": "Feature",
  "properties": {
    "iso:country":"NL",
    "sg:address":"Nicolaas Ruychaverstraat 26",
    "sg:city":"Amsterdam",
    "sg:orig_category":"Kappers",
    "sg:phone":"+31 20 613 4886",
    "sg:postcode":"1067 NH",
    "sg:province":"North Holland",
    "wof:name":"Gemma'S Hairstyling",
    "wof:placetype":"venue"
},
  "geometry": {"coordinates":[4.8044228554,52.3768196106],"type":"Point"}
}