{
  "type": "Feature",
  "properties": {
    "iso:country":"NL",
    "sg:address":"V W Poelmanwg 5",
    "sg:city":"Almelo",
    "sg:orig_category":"Koel- En Vrieshuizen",
    "sg:phone":"+31 546 866 163",
    "sg:postcode":"7602 PC",
    "sg:province":"Overijssel",
    "wof:name":"Bussink",
    "wof:placetype":"venue"
},
  "geometry": {"coordinates":[6.664543,52.354954],"type":"Point"}
}