{
  "type": "Feature",
  "properties": {
    "addr:full":"Ameidepark 21 Helmond Noord-Brabant 5701 ZZ",
    "addr:housenumber":"21",
    "addr:postcode":"5701 zz",
    "addr:street":"Ameidepark",
    "iso:country":"NL",
    "sg:address":"Ameidepark 21",
    "sg:city":"Helmond",
    "sg:orig_category":"Artsen And Specialisten",
    "sg:phone":"+31 492 522 500",
    "sg:postcode":"5701 ZZ",
    "sg:province":"Noord-Brabant",
    "wof:name":"G. Bekkers Huisarts",
    "wof:placetype":"venue"
},
  "geometry": {"coordinates":[5.659152,51.481033],"type":"Point"}
}