{
  "type": "Feature",
  "properties": {
    "addr:full":"Franciscushof 155 Vianen Zh South Holland 4133 BD",
    "addr:housenumber":"155",
    "addr:postcode":"zh;4133 bd",
    "addr:street":"Franciscushof",
    "iso:country":"NL",
    "sg:address":"Franciscushof 155",
    "sg:city":"Vianen Zh",
    "sg:orig_category":"Kappers",
    "sg:phone":"+31 347 377 108",
    "sg:postcode":"4133 BD",
    "sg:province":"South Holland",
    "wof:name":"Betsie Van Lent",
    "wof:placetype":"venue"
},
  "geometry": {"coordinates":[5.0842652321,51.9812583923],"type":"Point"}
}