{
  "type": "Feature",
  "properties": {
    "addr:full":"Kostverlorenhof 149 Amstelveen North Holland 1183 HK",
    "addr:housenumber":"149",
    "addr:postcode":"1183 hk",
    "addr:street":"Kostverlorenhof",
    "iso:country":"NL",
    "sg:address":"Kostverlorenhof 149",
    "sg:city":"Amstelveen",
    "sg:classifiers":[
        {
            "category":"Communications",
            "subcategory":"Television Station",
            "type":"Services"
        }
    ],
    "sg:phone":"+31 20 643 9655",
    "sg:postcode":"1183 HK",
    "sg:province":"North Holland",
    "sg:tags":[
        "video",
        "audio",
        "verhuur"
    ],
    "wof:name":"Videotheek Kostverlorenhof",
    "wof:placetype":"venue"
},
  "geometry": {"coordinates":[4.875771,52.313183],"type":"Point"}
}