{
  "type": "Feature",
  "properties": {
    "addr:full":"Kleyn Proffijtlaan 29 Oegstgeest Zuid-Holland 2343 DB",
    "addr:housenumber":"29",
    "addr:postcode":"2343 db",
    "addr:street":"Kleyn Proffijtlaan",
    "iso:country":"NL",
    "sg:address":"Kleyn Proffijtlaan 29",
    "sg:city":"Oegstgeest",
    "sg:orig_category":"Schilderwerk",
    "sg:phone":"+31 71 515 4197",
    "sg:postcode":"2343 DB",
    "sg:province":"Zuid-Holland",
    "wof:name":"Schildersbedrijf J Petiet Bv",
    "wof:placetype":"venue"
},
  "geometry": {"coordinates":[4.4794,52.191917],"type":"Point"}
}