{
  "type": "Feature",
  "properties": {
    "addr:full":"G V Dort Kroonwg 6 Waddinxveen Zuid-Holland 2742 KG",
    "addr:housenumber":"6",
    "addr:postcode":"2742 kg",
    "addr:street":"V Dort Kroonwg",
    "iso:country":"NL",
    "sg:address":"G V Dort Kroonwg 6",
    "sg:city":"Waddinxveen",
    "sg:orig_category":"Bloemen En Planten - Groothandel",
    "sg:phone":"+31 182 617 667",
    "sg:postcode":"2742 KG",
    "sg:province":"Zuid-Holland",
    "wof:name":"Stolk Vof En Zn, P J",
    "wof:placetype":"venue"
},
  "geometry": {"coordinates":[4.65507,52.044601],"type":"Point"}
}