{
  "type": "Feature",
  "properties": {
    "iso:country":"NL",
    "sg:address":"Harddraverstraat 7",
    "sg:city":"Rotterdam",
    "sg:classifiers":[
        {
            "category":"Education",
            "subcategory":"Preschool",
            "type":"Public Place"
        }
    ],
    "sg:phone":"+31 10 465 8308",
    "sg:postcode":"3033 XG",
    "sg:province":"South Holland",
    "sg:tags":[
        "kleuteronderwijs",
        "basis-"
    ],
    "wof:name":"Basisschool De Provenier",
    "wof:placetype":"venue"
},
  "geometry": {"coordinates":[4.467324,51.926533],"type":"Point"}
}