{
  "type": "Feature",
  "properties": {
    "iso:country":"NL",
    "sg:address":"Logger 16",
    "sg:city":"Huizen",
    "sg:orig_category":"Fotografie Reclame En Mode",
    "sg:phone":"+31 35 526 2060",
    "sg:postcode":"1276 BR",
    "sg:province":"Noord-Holland",
    "wof:name":"Oerlemans, Robert",
    "wof:placetype":"venue"
},
  "geometry": {"coordinates":[5.25593,52.294888],"type":"Point"}
}