{
  "type": "Feature",
  "properties": {
    "iso:country":"NL",
    "sg:address":"Smeepoortenbrink 10",
    "sg:city":"Harderwijk",
    "sg:classifiers":[
        {
            "category":"Shopping",
            "subcategory":"Gifts & Souvenirs",
            "type":"Retail Goods"
        }
    ],
    "sg:phone":"+31 341 427 646",
    "sg:postcode":"3841 EM",
    "sg:province":"Gelderland",
    "sg:tags":[
        "geschenken"
    ],
    "wof:name":"Wereldwinkel",
    "wof:placetype":"venue"
},
  "geometry": {"coordinates":[5.616276,52.347366],"type":"Point"}
}