{
  "type": "Feature",
  "properties": {
    "iso:country":"NL",
    "sg:address":"Klyne Meer 64",
    "sg:city":"Vinkeveen",
    "sg:orig_category":"Hypnotherapeuten",
    "sg:phone":"+31 297 266 761",
    "sg:postcode":"3645 WS",
    "sg:province":"Utrecht",
    "wof:name":"Labins",
    "wof:placetype":"venue"
},
  "geometry": {"coordinates":[4.926218,52.207424],"type":"Point"}
}