{
  "type": "Feature",
  "properties": {
    "iso:country":"NL",
    "sg:address":"Kwartelweg 16",
    "sg:city":"Epe",
    "sg:orig_category":"Loodgieterswerk, Verwarming And Sanitaire Installaties",
    "sg:phone":"+31 578 612 204",
    "sg:postcode":"8161 VE",
    "sg:province":"Gelderland",
    "wof:name":"E.J. Visser",
    "wof:placetype":"venue"
},
  "geometry": {"coordinates":[5.987363,52.342125],"type":"Point"}
}