{
  "type": "Feature",
  "properties": {
    "addr:full":"Oudedk 56A Tienhoven Ut Utrecht 3612 AC",
    "addr:housenumber":"56a",
    "addr:postcode":"3612 ac",
    "addr:street":"Oudedk",
    "iso:country":"NL",
    "sg:address":"Oudedk 56A",
    "sg:city":"Tienhoven Ut",
    "sg:classifiers":[
        {
            "category":"Retail",
            "subcategory":"Auto Repair",
            "type":"Services"
        }
    ],
    "sg:phone":"+31 346 281 001",
    "sg:postcode":"3612 AC",
    "sg:province":"Utrecht",
    "sg:tags":[
        "garage"
    ],
    "wof:name":"Schouten, Jaco",
    "wof:placetype":"venue"
},
  "geometry": {"coordinates":[5.081879,52.148914],"type":"Point"}
}