{
  "type": "Feature",
  "properties": {
    "addr:full":"Ootmarsumsestr 230 Almelo Overijssel 7603 AN",
    "addr:housenumber":"230",
    "addr:postcode":"7603 an",
    "iso:country":"NL",
    "sg:address":"Ootmarsumsestr 230",
    "sg:city":"Almelo",
    "sg:orig_category":"Artsen - Huisartsen",
    "sg:phone":"+31 546 861 752",
    "sg:postcode":"7603 AN",
    "sg:province":"Overijssel",
    "wof:name":"Boonstra En J H A Teeuw-Schaap, K P",
    "wof:placetype":"venue"
},
  "geometry": {"coordinates":[6.67699,52.366058],"type":"Point"}
}