{
  "type": "Feature",
  "properties": {
    "iso:country":"NL",
    "sg:address":"Frans L Blomlaan 67",
    "sg:city":"Leerdam",
    "sg:orig_category":"Loodgieterswerk, Verwarming And Sanitaire Installaties",
    "sg:phone":"+31 345 617 726",
    "sg:postcode":"4143 CW",
    "sg:province":"Zuid-Holland",
    "wof:name":"Aawee",
    "wof:placetype":"venue"
},
  "geometry": {"coordinates":[5.083065,51.899998],"type":"Point"}
}