{
  "type": "Feature",
  "properties": {
    "addr:full":"Wilhelminalaan 27 Delft South Holland 2625 LE",
    "addr:housenumber":"27",
    "addr:postcode":"2625 le",
    "addr:street":"Wilhelminalaan",
    "iso:country":"NL",
    "sg:address":"Wilhelminalaan 27",
    "sg:city":"Delft",
    "sg:orig_category":"Verhuur Catering-, Feest- En Evenementbenodigdheden",
    "sg:phone":"+31 15 262 0278",
    "sg:postcode":"2625 LE",
    "sg:province":"South Holland",
    "wof:name":"Idevo Video",
    "wof:placetype":"venue"
},
  "geometry": {"coordinates":[4.342685,51.987312],"type":"Point"}
}