{
  "type": "Feature",
  "properties": {
    "addr:full":"Molenwijk 33 Amsterdam North Holland 1035 EG",
    "addr:housenumber":"33",
    "addr:postcode":"1035 eg",
    "addr:street":"Molenwijk",
    "iso:country":"NL",
    "sg:address":"Molenwijk 33",
    "sg:city":"Amsterdam",
    "sg:classifiers":[
        {
            "category":"Fast Food",
            "type":"Food & Drink"
        }
    ],
    "sg:phone":"+31 20 631 1756",
    "sg:postcode":"1035 EG",
    "sg:province":"North Holland",
    "sg:tags":[
        "afhaal",
        "restaurant"
    ],
    "wof:name":"Snackbar & Coffeeshop De Wieken",
    "wof:placetype":"venue"
},
  "geometry": {"coordinates":[4.887819,52.419659],"type":"Point"}
}