{
  "type": "Feature",
  "properties": {
    "addr:full":"T Holthuis 4 Twello Gelderland 7391 TV",
    "addr:housenumber":"4",
    "addr:postcode":"7391 tv",
    "addr:street":"T Holthuis;Gelderland",
    "iso:country":"NL",
    "sg:address":"T Holthuis 4",
    "sg:city":"Twello",
    "sg:orig_category":"Bloemen En Planten",
    "sg:phone":"+31 571 270 886",
    "sg:postcode":"7391 TV",
    "sg:province":"Gelderland",
    "wof:name":"Kruidentuin, De",
    "wof:placetype":"venue"
},
  "geometry": {"coordinates":[6.116572,52.238781],"type":"Point"}
}