{
  "type": "Feature",
  "properties": {
    "iso:country":"NL",
    "sg:address":"Einsteinstr 67",
    "sg:city":"Kudelstaart",
    "sg:orig_category":"Sportverenigingen En Ontspannings- Verenigingen",
    "sg:phone":"+31 6 21670558",
    "sg:postcode":"1433 BD",
    "sg:province":"North Holland",
    "wof:name":"Aalsmeer Waterskiver",
    "wof:placetype":"venue"
},
  "geometry": {"coordinates":[4.750256,52.234837],"type":"Point"}
}