{
  "type": "Feature",
  "properties": {
    "iso:country":"NL",
    "sg:address":"Spaandonk 39",
    "sg:city":"Oosterhout Nb",
    "sg:orig_category":"Adviesbureaus Automatisering",
    "sg:phone":"+31 162 439 793",
    "sg:postcode":"4907 ZK",
    "sg:province":"Noord-Brabant",
    "sg:website":"http://www.taalsupport.nl",
    "wof:name":"Coach Bv",
    "wof:placetype":"venue"
},
  "geometry": {"coordinates":[4.86389,51.659325],"type":"Point"}
}