{
  "type": "Feature",
  "properties": {
    "addr:full":"Vd Asdonckstr 25 Gemert North Brabant 5421 VB",
    "addr:housenumber":"25",
    "addr:postcode":"5421 vb",
    "iso:country":"NL",
    "sg:address":"Vd Asdonckstr 25",
    "sg:city":"Gemert",
    "sg:orig_category":"Fitnesscentra",
    "sg:phone":"+31 492 361 751",
    "sg:postcode":"5421 VB",
    "sg:province":"North Brabant",
    "wof:name":"Fitland",
    "wof:placetype":"venue"
},
  "geometry": {"coordinates":[5.681675,51.556126],"type":"Point"}
}