{
  "type": "Feature",
  "properties": {
    "addr:full":"Tuindorpwg 5 Maarsbergen Utrecht 3953 BB",
    "addr:housenumber":"5",
    "addr:postcode":"3953 bb",
    "addr:street":"Tuindorpwg",
    "iso:country":"NL",
    "sg:address":"Tuindorpwg 5",
    "sg:city":"Maarsbergen",
    "sg:orig_category":"Adviesbureaus Bedrijfsorganisatie",
    "sg:phone":"+31 343 431 664",
    "sg:postcode":"3953 BB",
    "sg:province":"Utrecht",
    "wof:name":"Merlijn Vof",
    "wof:placetype":"venue"
},
  "geometry": {"coordinates":[5.40323,52.057564],"type":"Point"}
}