{
  "type": "Feature",
  "properties": {
    "addr:full":"Jephtastraat 67 Amsterdam Noord-Holland 1055 JS",
    "addr:housenumber":"67",
    "addr:postcode":"1055 js",
    "addr:street":"Jephtastraat",
    "iso:country":"NL",
    "sg:address":"Jephtastraat 67",
    "sg:city":"Amsterdam",
    "sg:orig_category":"Fotostudio'S And Fotografen",
    "sg:phone":"+31 20 682 2109",
    "sg:postcode":"1055 JS",
    "sg:province":"Noord-Holland",
    "wof:name":"Fotografie Niels Van Iperen",
    "wof:placetype":"venue"
},
  "geometry": {"coordinates":[4.845308,52.381218],"type":"Point"}
}