{
  "type": "Feature",
  "properties": {
    "addr:full":"Houtstraat 25A Klimmen Limburg 6343 BJ",
    "addr:housenumber":"25a",
    "addr:postcode":"6343 bj",
    "addr:street":"Houtstraat",
    "iso:country":"NL",
    "sg:address":"Houtstraat 25A",
    "sg:city":"Klimmen",
    "sg:orig_category":"Bibliotheken And Openbare Archieven",
    "sg:phone":"+31 45 405 3376",
    "sg:postcode":"6343 BJ",
    "sg:province":"Limburg",
    "wof:name":"Openbare Bibliotheek Klimmen",
    "wof:placetype":"venue"
},
  "geometry": {"coordinates":[5.882016,50.875877],"type":"Point"}
}