{
  "type": "Feature",
  "properties": {
    "addr:full":"Harmonielaan 146 Diemen Noord-Holland 1111 RB",
    "addr:housenumber":"146",
    "addr:postcode":"1111 rb",
    "addr:street":"Harmonielaan",
    "iso:country":"NL",
    "sg:address":"Harmonielaan 146",
    "sg:city":"Diemen",
    "sg:orig_category":"Diverse Grafische Activiteiten",
    "sg:phone":"+31 20 695 9996",
    "sg:postcode":"1111 RB",
    "sg:province":"Noord-Holland",
    "wof:name":"T.R. Flaherty",
    "wof:placetype":"venue"
},
  "geometry": {"coordinates":[4.968335,52.34642],"type":"Point"}
}