{
  "type": "Feature",
  "properties": {
    "addr:full":"Meridiaan 22-24 Amersfoort Utrecht 3813 AV",
    "addr:housenumber":"22-24",
    "addr:postcode":"3813 av",
    "addr:street":"Meridiaan",
    "iso:country":"NL",
    "sg:address":"Meridiaan 22-24",
    "sg:city":"Amersfoort",
    "sg:orig_category":"Onroerende Goederen",
    "sg:phone":"+31 33 470 1900",
    "sg:postcode":"3813 AV",
    "sg:province":"Utrecht",
    "wof:name":"Mostert Holding Bv, A.",
    "wof:placetype":"venue"
},
  "geometry": {"coordinates":[5.385757,52.164555],"type":"Point"}
}