{
  "type": "Feature",
  "properties": {
    "addr:full":"W Barentszstr 17 Barneveld Gelderland 3772 KZ",
    "addr:housenumber":"17",
    "addr:postcode":"3772",
    "addr:street":"W;Gelderland",
    "iso:country":"NL",
    "sg:address":"W Barentszstr 17",
    "sg:city":"Barneveld",
    "sg:orig_category":"Kinderkleding - Fabrieken En Groothandel",
    "sg:phone":"+31 342 408 490",
    "sg:postcode":"3772 KZ",
    "sg:province":"Gelderland",
    "wof:name":"Native Company",
    "wof:placetype":"venue"
},
  "geometry": {"coordinates":[5.573391,52.131344],"type":"Point"}
}