{
  "type": "Feature",
  "properties": {
    "addr:full":"Parallelweg 5 Wijlre Limburg 6321 BA",
    "addr:housenumber":"5",
    "addr:postcode":"6321 ba",
    "addr:street":"Parallelweg",
    "iso:country":"NL",
    "sg:address":"Parallelweg 5",
    "sg:city":"Wijlre",
    "sg:orig_category":"Houten Verpakkingen Fab",
    "sg:phone":"+31 43 450 1695",
    "sg:postcode":"6321 BA",
    "sg:province":"Limburg",
    "wof:name":"Bv Houthandel W.E. Boumans",
    "wof:placetype":"venue"
},
  "geometry": {"coordinates":[5.899111,50.83131],"type":"Point"}
}