{
  "type": "Feature",
  "properties": {
    "addr:full":"Veldhofstr 24 Eygelshoven Limburg 6471 CK",
    "addr:housenumber":"24",
    "addr:postcode":"6471 ck",
    "addr:street":"Veldhofstr",
    "iso:country":"NL",
    "sg:address":"Veldhofstr 24",
    "sg:city":"Eygelshoven",
    "sg:classifiers":[
        {
            "category":"Food & Beverages",
            "subcategory":"Bakery",
            "type":"Retail Goods"
        }
    ],
    "sg:phone":"+31 45 535 1262",
    "sg:postcode":"6471 CK",
    "sg:province":"Limburg",
    "sg:tags":[
        "brood",
        "en",
        "banket"
    ],
    "wof:name":"Eeghem Bv, Van",
    "wof:placetype":"venue"
},
  "geometry": {"coordinates":[6.060134,50.893784],"type":"Point"}
}