{
  "type": "Feature",
  "properties": {
    "addr:full":"Van Daatselaarhof 14 Leusden Utrecht 3833 HV",
    "addr:housenumber":"14",
    "addr:postcode":"3833 hv",
    "addr:street":"Van Daatselaarhof",
    "iso:country":"NL",
    "sg:address":"Van Daatselaarhof 14",
    "sg:city":"Leusden",
    "sg:orig_category":"Boekhouders",
    "sg:phone":"+31 33 494 3038",
    "sg:postcode":"3833 HV",
    "sg:province":"Utrecht",
    "wof:name":"J.M.I. Berg-Van Den Berg",
    "wof:placetype":"venue"
},
  "geometry": {"coordinates":[5.413946,52.125294],"type":"Point"}
}