{
  "type": "Feature",
  "properties": {
    "addr:full":"Brugstraat 12 Hengelo Ov Overijssel 7551 BZ",
    "addr:housenumber":"12",
    "addr:postcode":"7551 bz",
    "addr:street":"Brugstraat;Ov",
    "iso:country":"NL",
    "sg:address":"Brugstraat 12",
    "sg:city":"Hengelo Ov",
    "sg:orig_category":"Onderhoud And Reparatie Kantoorapparatuur",
    "sg:phone":"+31 74 243 5143",
    "sg:postcode":"7551 BZ",
    "sg:province":"Overijssel",
    "wof:name":"Multi Cat",
    "wof:placetype":"venue"
},
  "geometry": {"coordinates":[6.789866,52.264565],"type":"Point"}
}