{
  "type": "Feature",
  "properties": {
    "addr:full":"Nieuwstr 2 Woerden South Holland 3441 EB",
    "addr:housenumber":"2",
    "addr:postcode":"3441 eb",
    "addr:street":"Nieuwstr",
    "iso:country":"NL",
    "sg:address":"Nieuwstr 2",
    "sg:city":"Woerden",
    "sg:orig_category":"Bloemen En Planten",
    "sg:phone":"+31 348 418 111",
    "sg:postcode":"3441 EB",
    "sg:province":"South Holland",
    "wof:name":"Jong, G C F L De",
    "wof:placetype":"venue"
},
  "geometry": {"coordinates":[4.835266,52.114002],"type":"Point"}
}