{
  "type": "Feature",
  "properties": {
    "addr:full":"Geerdinkhof 598 Amsterdam Zuidoost Noord-Holland 1103 RL",
    "addr:housenumber":"598",
    "addr:postcode":"zuidoost;1103 rl",
    "addr:street":"Geerdinkhof",
    "iso:country":"NL",
    "sg:address":"Geerdinkhof 598",
    "sg:city":"Amsterdam Zuidoost",
    "sg:orig_category":"Schoonheidsinstituten",
    "sg:phone":"+31 20 699 4041",
    "sg:postcode":"1103 RL",
    "sg:province":"Noord-Holland",
    "sg:website":"http://www.weswereld.nl",
    "wof:name":"Wes-Wereld Estheticienne Salon",
    "wof:placetype":"venue"
},
  "geometry": {"coordinates":[4.980029,52.326447],"type":"Point"}
}