{
  "type": "Feature",
  "properties": {
    "addr:full":"Torenstr 10 Amersfoort Utrecht 3811 DJ",
    "addr:housenumber":"10",
    "addr:postcode":"3811 dj",
    "addr:street":"Torenstr",
    "iso:country":"NL",
    "sg:address":"Torenstr 10",
    "sg:city":"Amersfoort",
    "sg:orig_category":"Binnenhuisarchitectuur",
    "sg:phone":"+31 33 465 8618",
    "sg:postcode":"3811 DJ",
    "sg:province":"Utrecht",
    "wof:name":"Klaren & Tromp",
    "wof:placetype":"venue"
},
  "geometry": {"coordinates":[5.388705,52.155945],"type":"Point"}
}