{
  "type": "Feature",
  "properties": {
    "iso:country":"NL",
    "sg:address":"Koningshoek 92335",
    "sg:city":"Maassluis",
    "sg:orig_category":"Poeliers",
    "sg:phone":"+31 10 591 0556",
    "sg:postcode":"3144 BA",
    "sg:province":"South Holland",
    "wof:name":"Krijgsman",
    "wof:placetype":"venue"
},
  "geometry": {"coordinates":[4.239938,51.927902],"type":"Point"}
}