{
  "type": "Feature",
  "properties": {
    "addr:full":"Markt 1 Silvolde Gelderland 7064 AZ",
    "addr:housenumber":"1",
    "addr:postcode":"7064",
    "addr:street":"Markt;Gelderland",
    "iso:country":"NL",
    "sg:address":"Markt 1",
    "sg:city":"Silvolde",
    "sg:classifiers":[
        {
            "category":"Travel",
            "subcategory":"Hotels & Motels",
            "type":"Entertainment"
        }
    ],
    "sg:phone":"+31 315 324 567",
    "sg:postcode":"7064 AZ",
    "sg:province":"Gelderland",
    "sg:website":"http://www.herbergjan.nl",
    "wof:name":"Herberg Jan",
    "wof:placetype":"venue"
},
  "geometry": {"coordinates":[6.37984,51.910843],"type":"Point"}
}