{
  "type": "Feature",
  "properties": {
    "iso:country":"NL",
    "sg:address":"Keizersgr 117",
    "sg:city":"Amsterdam",
    "sg:orig_category":"Architecten En Architectenbureaus",
    "sg:phone":"+31 20 627 2627",
    "sg:postcode":"1015 CJ",
    "sg:province":"Noord-Holland",
    "wof:name":"Reintjens Bna Architecten Bv, Jef",
    "wof:placetype":"venue"
},
  "geometry": {"coordinates":[4.887614,52.376575],"type":"Point"}
}