{
  "type": "Feature",
  "properties": {
    "iso:country":"NL",
    "sg:address":"In De Cramer 188",
    "sg:city":"Heerlen",
    "sg:orig_category":"Woninginrichting",
    "sg:phone":"+31 45 575 4200",
    "sg:postcode":"6412 PM",
    "sg:province":"Limburg",
    "sg:website":"http://www.designhouse.nl",
    "wof:name":"Design House",
    "wof:placetype":"venue"
},
  "geometry": {"coordinates":[5.9401788712,50.900177002],"type":"Point"}
}