{
  "type": "Feature",
  "properties": {
    "addr:full":"Eikenln 15 Ochten Gelderland 4051 EP",
    "addr:housenumber":"15",
    "addr:postcode":"4051 ep",
    "addr:street":"Eikenln;Gelderland",
    "iso:country":"NL",
    "sg:address":"Eikenln 15",
    "sg:city":"Ochten",
    "sg:orig_category":"Wegenbouw",
    "sg:phone":"+31 344 643 033",
    "sg:postcode":"4051 EP",
    "sg:province":"Gelderland",
    "wof:name":"Nijhoff",
    "wof:placetype":"venue"
},
  "geometry": {"coordinates":[5.5700821877,51.9116821289],"type":"Point"}
}