{
  "type": "Feature",
  "properties": {
    "addr:full":"Schellingwouderdk 243 Amsterdam North Holland 1023 NG",
    "addr:housenumber":"243",
    "addr:postcode":"1023 ng",
    "iso:country":"NL",
    "sg:address":"Schellingwouderdk 243",
    "sg:city":"Amsterdam",
    "sg:orig_category":"Pottenbakkerijen",
    "sg:phone":"+31 20 490 4936",
    "sg:postcode":"1023 NG",
    "sg:province":"North Holland",
    "wof:name":"Marjoke De Heer",
    "wof:placetype":"venue"
},
  "geometry": {"coordinates":[4.962331,52.384346],"type":"Point"}
}