{
  "type": "Feature",
  "properties": {
    "addr:full":"Oudkerkhof 38 Utrecht Utrecht 3512 GL",
    "addr:housenumber":"38",
    "addr:postcode":"3512 gl",
    "addr:street":"Oudkerkhof",
    "iso:country":"NL",
    "sg:address":"Oudkerkhof 38",
    "sg:city":"Utrecht",
    "sg:orig_category":"Meubelzaken, Woning- And Keukeninrichting",
    "sg:phone":"+31 30 231 3242",
    "sg:postcode":"3512 GL",
    "sg:province":"Utrecht",
    "wof:name":"Lifestyle",
    "wof:placetype":"venue"
},
  "geometry": {"coordinates":[5.121643,52.092014],"type":"Point"}
}