{
  "type": "Feature",
  "properties": {
    "addr:full":"V Wynbergenln 37 Barneveld Gelderland 3771 JG",
    "addr:housenumber":"37",
    "addr:postcode":"3771 jg",
    "addr:street":"Gelderland",
    "iso:country":"NL",
    "sg:address":"V Wynbergenln 37",
    "sg:city":"Barneveld",
    "sg:orig_category":"Onderhoudswerken",
    "sg:phone":"+31 342 412 602",
    "sg:postcode":"3771 JG",
    "sg:province":"Gelderland",
    "wof:name":"Pul, J D",
    "wof:placetype":"venue"
},
  "geometry": {"coordinates":[5.588843,52.141216],"type":"Point"}
}