{
  "type": "Feature",
  "properties": {
    "iso:country":"NL",
    "sg:address":"Bolstraschans 17",
    "sg:city":"Zoetermeer",
    "sg:classifiers":[
        {
            "category":"Personal",
            "subcategory":"Nail Salon",
            "type":"Services"
        }
    ],
    "sg:phone":"+31 79 343 2911",
    "sg:postcode":"2728 ER",
    "sg:province":"South Holland",
    "sg:tags":[
        "pedicure"
    ],
    "wof:name":"Schuur-Adegeest, A J",
    "wof:placetype":"venue"
},
  "geometry": {"coordinates":[4.528577,52.07793],"type":"Point"}
}