{
  "type": "Feature",
  "properties": {
    "addr:full":"Citadellaan 53 'S Hertogenbosch Noord-Brabant 5212 VA",
    "addr:housenumber":"53",
    "addr:postcode":"5212",
    "addr:street":"Citadellaan;' S",
    "iso:country":"NL",
    "sg:address":"Citadellaan 53",
    "sg:city":"'S Hertogenbosch",
    "sg:orig_category":"Werving And Selectie Van Tijdelijk Personeel And Uitzendkantoren",
    "sg:phone":"+31 73 614 0745",
    "sg:postcode":"5212 VA",
    "sg:province":"Noord-Brabant",
    "wof:name":"Ruvo Bv",
    "wof:placetype":"venue"
},
  "geometry": {"coordinates":[5.3057441711,51.6955108643],"type":"Point"}
}