{
  "type": "Feature",
  "properties": {
    "iso:country":"NL",
    "sg:address":"Korteveldswg 3",
    "sg:city":"Lemele",
    "sg:orig_category":"Discotheken",
    "sg:phone":"+31 572 331 215",
    "sg:postcode":"8148 RD",
    "sg:province":"Overijssel",
    "sg:website":"http://www.zaaldijk.nl",
    "wof:name":"Dijk, Zaal",
    "wof:placetype":"venue"
},
  "geometry": {"coordinates":[6.413937,52.45126],"type":"Point"}
}