{
  "type": "Feature",
  "properties": {
    "addr:full":"Vliethof 94 Wateringen Zuid-Holland 2291 RZ",
    "addr:housenumber":"94",
    "addr:postcode":"2291 rz",
    "addr:street":"Vliethof",
    "iso:country":"NL",
    "sg:address":"Vliethof 94",
    "sg:city":"Wateringen",
    "sg:orig_category":"Bloemen En Planten",
    "sg:phone":"+31 174 292 961",
    "sg:postcode":"2291 RZ",
    "sg:province":"Zuid-Holland",
    "wof:name":"Veldhoven",
    "wof:placetype":"venue"
},
  "geometry": {"coordinates":[4.274524,52.025703],"type":"Point"}
}