{
  "type": "Feature",
  "properties": {
    "addr:full":"Kloosterhoekwg 7A Welsum Overijssel 8196 KM",
    "addr:housenumber":"7a",
    "addr:postcode":"8196 km",
    "addr:street":"Kloosterhoekwg",
    "iso:country":"NL",
    "sg:address":"Kloosterhoekwg 7A",
    "sg:city":"Welsum",
    "sg:orig_category":"Grondwerken",
    "sg:phone":"+31 570 562 999",
    "sg:postcode":"8196 KM",
    "sg:province":"Overijssel",
    "wof:name":"Bouman Welsum",
    "wof:placetype":"venue"
},
  "geometry": {"coordinates":[6.085982,52.325966],"type":"Point"}
}