{
  "type": "Feature",
  "properties": {
    "iso:country":"NL",
    "sg:address":"Kleine Belt 3",
    "sg:city":"Zutphen",
    "sg:orig_category":"Loodgieterswerk, Verwarming And Sanitaire Installaties",
    "sg:phone":"+31 575 546 986",
    "sg:postcode":"7202 CS",
    "sg:province":"Gelderland",
    "wof:name":"Oldenhave Personeelsdiensten Bv",
    "wof:placetype":"venue"
},
  "geometry": {"coordinates":[6.196935,52.15237],"type":"Point"}
}