{
  "type": "Feature",
  "properties": {
    "addr:full":"Koningin Sophiastraat 18 Zwolle NL.08 8019 XZ",
    "addr:housenumber":"18",
    "addr:postcode":"8019 xz",
    "addr:street":"Koningin Sophiastraat",
    "iso:country":"NL",
    "sg:address":"Koningin Sophiastraat 18",
    "sg:city":"Zwolle",
    "sg:orig_category":"Boekhouders",
    "sg:phone":"+31 38 421 8824",
    "sg:postcode":"8019 XZ",
    "sg:province":"NL.08",
    "wof:name":"K. Van Hoffen",
    "wof:placetype":"venue"
},
  "geometry": {"coordinates":[6.075257,52.506245],"type":"Point"}
}