{
  "type": "Feature",
  "properties": {
    "addr:full":"V Deelenstr 39 Heusden Gem Heusd Noord-Brabant 5256 JA",
    "addr:housenumber":"39",
    "addr:postcode":"heusd;5256 ja",
    "addr:street":"V Deelenstr",
    "iso:country":"NL",
    "sg:address":"V Deelenstr 39",
    "sg:city":"Heusden Gem Heusd",
    "sg:orig_category":"Verzekeringen - Verzekeringskantoren",
    "sg:phone":"+31 416 665 197",
    "sg:postcode":"5256 JA",
    "sg:province":"Noord-Brabant",
    "wof:name":"Fidias",
    "wof:placetype":"venue"
},
  "geometry": {"coordinates":[5.13727,51.733074],"type":"Point"}
}