{
  "type": "Feature",
  "properties": {
    "addr:full":"Lylantse Baan 2B Capelle Ad Yssel Zuid-Holland 2908 LG",
    "addr:housenumber":"2b",
    "addr:postcode":"2908 lg",
    "addr:street":"Lylantse Baan",
    "iso:country":"NL",
    "sg:address":"Lylantse Baan 2B",
    "sg:city":"Capelle Ad Yssel",
    "sg:orig_category":"Parketvloeren",
    "sg:phone":"+31 10 227 1568",
    "sg:postcode":"2908 LG",
    "sg:province":"Zuid-Holland",
    "wof:name":"Santana",
    "wof:placetype":"venue"
},
  "geometry": {"coordinates":[4.564409,51.95332],"type":"Point"}
}