{
  "type": "Feature",
  "properties": {
    "addr:full":"Boothstr 2A Utrecht Utrecht 3512 BW",
    "addr:housenumber":"2a",
    "addr:postcode":"3512 bw",
    "addr:street":"Boothstr",
    "iso:country":"NL",
    "sg:address":"Boothstr 2A",
    "sg:city":"Utrecht",
    "sg:orig_category":"Grafisch Ontwerpers",
    "sg:phone":"+31 30 231 6420",
    "sg:postcode":"3512 BW",
    "sg:province":"Utrecht",
    "sg:website":"http://www.wrik.com",
    "wof:name":"Wrik Ontwerpbureau",
    "wof:placetype":"venue"
},
  "geometry": {"coordinates":[5.121812,52.093998],"type":"Point"}
}