{
  "type": "Feature",
  "properties": {
    "addr:full":"Lisdodde 8 Genemuiden Overijssel 8281 KD",
    "addr:housenumber":"8",
    "addr:postcode":"8281 kd",
    "addr:street":"Lisdodde",
    "iso:country":"NL",
    "sg:address":"Lisdodde 8",
    "sg:city":"Genemuiden",
    "sg:orig_category":"Woninginrichting",
    "sg:phone":"+31 38 385 6370",
    "sg:postcode":"8281 KD",
    "sg:province":"Overijssel",
    "wof:name":"Beens",
    "wof:placetype":"venue"
},
  "geometry": {"coordinates":[6.0351629257,52.625125885],"type":"Point"}
}