{
  "type": "Feature",
  "properties": {
    "addr:full":"Van Alphenstraat 24 Heerlen Limburg 6416 EE",
    "addr:housenumber":"24",
    "addr:postcode":"6416 ee",
    "addr:street":"Van Alphenstraat",
    "iso:country":"NL",
    "sg:address":"Van Alphenstraat 24",
    "sg:city":"Heerlen",
    "sg:orig_category":"Kappers",
    "sg:phone":"+31 45 541 5011",
    "sg:postcode":"6416 EE",
    "sg:province":"Limburg",
    "wof:name":"L A H Schaeks",
    "wof:placetype":"venue"
},
  "geometry": {"coordinates":[5.994493,50.883091],"type":"Point"}
}