{
  "type": "Feature",
  "properties": {
    "addr:full":"Bennekomseweg 110 Renkum Gelderland 6871 KH",
    "addr:housenumber":"110",
    "addr:postcode":"6871 kh",
    "addr:street":"Bennekomseweg;Gelderland",
    "iso:country":"NL",
    "sg:address":"Bennekomseweg 110",
    "sg:city":"Renkum",
    "sg:orig_category":"Verzekeringen",
    "sg:phone":"+31 317 314 671",
    "sg:postcode":"6871 KH",
    "sg:province":"Gelderland",
    "wof:name":"J. Stoel Assurantien",
    "wof:placetype":"venue"
},
  "geometry": {"coordinates":[5.745892,51.986107],"type":"Point"}
}