{
  "type": "Feature",
  "properties": {
    "addr:full":"Stationsstr 72 Maarheeze Noord-Brabant 6026 CW",
    "addr:housenumber":"72",
    "addr:postcode":"6026 cw",
    "addr:street":"Stationsstr",
    "iso:country":"NL",
    "sg:address":"Stationsstr 72",
    "sg:city":"Maarheeze",
    "sg:orig_category":"Adviesbureaus Beveiliging",
    "sg:phone":"+31 495 592 215",
    "sg:postcode":"6026 CW",
    "sg:province":"Noord-Brabant",
    "wof:name":"Kirkels",
    "wof:placetype":"venue"
},
  "geometry": {"coordinates":[5.619477,51.313282],"type":"Point"}
}