{
  "type": "Feature",
  "properties": {
    "addr:full":"F Ruysstr 53 Rotterdam Zuid-Holland 3061 MD",
    "addr:housenumber":"53",
    "addr:postcode":"3061",
    "iso:country":"NL",
    "sg:address":"F Ruysstr 53",
    "sg:city":"Rotterdam",
    "sg:orig_category":"Kappers",
    "sg:phone":"+31 10 452 3567",
    "sg:postcode":"3061 MD",
    "sg:province":"Zuid-Holland",
    "wof:name":"Briljant",
    "wof:placetype":"venue"
},
  "geometry": {"coordinates":[4.5016732216,51.9268493652],"type":"Point"}
}