{
  "type": "Feature",
  "properties": {
    "addr:full":"Belterwiede 4 Lelystad Flevoland 8244 EH",
    "addr:housenumber":"4",
    "addr:postcode":"8244 eh",
    "addr:street":"Belterwiede;Flevoland",
    "iso:country":"NL",
    "sg:address":"Belterwiede 4",
    "sg:city":"Lelystad",
    "sg:orig_category":"Werving En Selectie",
    "sg:phone":"+31 320 212 626",
    "sg:postcode":"8244 EH",
    "sg:province":"Flevoland",
    "wof:name":"Interface",
    "wof:placetype":"venue"
},
  "geometry": {"coordinates":[5.4161028862,52.4969177246],"type":"Point"}
}