{
  "type": "Feature",
  "properties": {
    "addr:full":"Oostheullaan 10 Honselersdijk South Holland 2675 KR",
    "addr:housenumber":"10",
    "addr:postcode":"2675 kr",
    "addr:street":"Oostheullaan",
    "iso:country":"NL",
    "sg:address":"Oostheullaan 10",
    "sg:city":"Honselersdijk",
    "sg:orig_category":"Bloemen And Planten",
    "sg:phone":"+31 174 640 224",
    "sg:postcode":"2675 KR",
    "sg:province":"South Holland",
    "wof:name":"Richplant Bv",
    "wof:placetype":"venue"
},
  "geometry": {"coordinates":[4.242668,52.000011],"type":"Point"}
}