{
  "type": "Feature",
  "properties": {
    "iso:country":"NL",
    "sg:address":"Nyverheidswg 7",
    "sg:city":"Mydrecht",
    "sg:orig_category":"Grafische Machines",
    "sg:phone":"+31 297 289 691",
    "sg:postcode":"3641 RP",
    "sg:province":"Utrecht",
    "sg:website":"http://www.wifac.nl",
    "wof:name":"Wifac Bv",
    "wof:placetype":"venue"
},
  "geometry": {"coordinates":[4.86178,52.20578],"type":"Point"}
}