{
  "type": "Feature",
  "properties": {
    "addr:full":"Veerweg 107 Rheden Gelderland 6991 GM",
    "addr:housenumber":"107",
    "addr:postcode":"6991 gm",
    "addr:street":"Veerweg;Gelderland",
    "iso:country":"NL",
    "sg:address":"Veerweg 107",
    "sg:city":"Rheden",
    "sg:classifiers":[
        {
            "category":"Food & Beverages",
            "subcategory":"Fruits & Vegetables",
            "type":"Retail Goods"
        }
    ],
    "sg:phone":"+31 26 495 1610",
    "sg:postcode":"6991 GM",
    "sg:province":"Gelderland",
    "sg:tags":[
        "groenten"
    ],
    "wof:name":"H Nijhof",
    "wof:placetype":"venue"
},
  "geometry": {"coordinates":[6.034996,52.006535],"type":"Point"}
}