{
  "type": "Feature",
  "properties": {
    "addr:full":"Kerkstr 32 Putten Gelderland 3882 BS",
    "addr:housenumber":"32",
    "addr:postcode":"3882 bs",
    "addr:street":"Kerkstr;Gelderland",
    "iso:country":"NL",
    "sg:address":"Kerkstr 32",
    "sg:city":"Putten",
    "sg:orig_category":"Horloges En Klokken",
    "sg:phone":"+31 341 352 370",
    "sg:postcode":"3882 BS",
    "sg:province":"Gelderland",
    "wof:name":"Kaasschieter",
    "wof:placetype":"venue"
},
  "geometry": {"coordinates":[5.607451,52.259468],"type":"Point"}
}