{
  "type": "Feature",
  "properties": {
    "iso:country":"NL",
    "sg:address":"Bergerhof 100",
    "sg:city":"Renkum",
    "sg:orig_category":"Autorijscholen",
    "sg:phone":"+31 317 316 939",
    "sg:postcode":"6871 ZM",
    "sg:province":"Gelderland",
    "wof:name":"Aad Deventer Verkeersschool",
    "wof:placetype":"venue"
},
  "geometry": {"coordinates":[5.724721,51.97699],"type":"Point"}
}