{
  "type": "Feature",
  "properties": {
    "addr:full":"Velperwg 31 Arnhem Gelderland 6824 BD",
    "addr:housenumber":"31",
    "addr:postcode":"6824 bd",
    "addr:street":"Velperwg",
    "iso:country":"NL",
    "sg:address":"Velperwg 31",
    "sg:city":"Arnhem",
    "sg:orig_category":"Mensendieck - Oefentherapeuten",
    "sg:phone":"+31 26 351 8400",
    "sg:postcode":"6824 BD",
    "sg:province":"Gelderland",
    "wof:name":"Engel-Vletter, A J Van Den",
    "wof:placetype":"venue"
},
  "geometry": {"coordinates":[5.925189,51.986912],"type":"Point"}
}