{
  "type": "Feature",
  "properties": {
    "addr:full":"Snipln 45 Ryswyk Zh South Holland 2289 EK",
    "addr:housenumber":"45;zh",
    "addr:postcode":"2289 ek",
    "addr:street":"Snipln",
    "iso:country":"NL",
    "sg:address":"Snipln 45",
    "sg:city":"Ryswyk Zh",
    "sg:orig_category":"Elektronica - Ontwikkeling En Groothandel",
    "sg:phone":"+31 70 399 5762",
    "sg:postcode":"2289 EK",
    "sg:province":"South Holland",
    "wof:name":"Hollander, T J Den",
    "wof:placetype":"venue"
},
  "geometry": {"coordinates":[4.32436,52.037251],"type":"Point"}
}