{
  "type": "Feature",
  "properties": {
    "iso:country":"NL",
    "sg:address":"Engwg 77",
    "sg:city":"Putten",
    "sg:orig_category":"Bloemen En Planten - Groothandel",
    "sg:phone":"+31 341 360 377",
    "sg:postcode":"3882 AK",
    "sg:province":"Gelderland",
    "wof:name":"Tinctoria",
    "wof:placetype":"venue"
},
  "geometry": {"coordinates":[5.607686,52.256233],"type":"Point"}
}