{
  "type": "Feature",
  "properties": {
    "addr:full":"Bussumergrintwg 5 Hilversum Noord-Holland 1217 BM",
    "addr:housenumber":"5",
    "addr:postcode":"1217 bm",
    "addr:street":"Bussumergrintwg",
    "iso:country":"NL",
    "sg:address":"Bussumergrintwg 5",
    "sg:city":"Hilversum",
    "sg:orig_category":"Juridische Adviseurs",
    "sg:phone":"+31 35 624 1198",
    "sg:postcode":"1217 BM",
    "sg:province":"Noord-Holland",
    "wof:name":"Scheltema, F J",
    "wof:placetype":"venue"
},
  "geometry": {"coordinates":[5.160352,52.234852],"type":"Point"}
}