{
  "type": "Feature",
  "properties": {
    "addr:full":"Dorpsstraat 62 Capelle A/D Ijssel South Holland 2902 BD",
    "addr:housenumber":"62;a / d",
    "addr:postcode":"2902 bd",
    "addr:street":"Dorpsstraat;Ijssel South",
    "iso:country":"NL",
    "sg:address":"Dorpsstraat 62",
    "sg:city":"Capelle A/D Ijssel",
    "sg:orig_category":"Verzekeringen",
    "sg:phone":"+31 10 458 5562",
    "sg:postcode":"2902 BD",
    "sg:province":"South Holland",
    "wof:name":"Assurantiekantoor Van Galen",
    "wof:placetype":"venue"
},
  "geometry": {"coordinates":[4.58717,51.922192],"type":"Point"}
}