{
  "type": "Feature",
  "properties": {
    "addr:full":"Middenwg 127A Den Helder North Holland 1782 BD",
    "addr:housenumber":"127a",
    "addr:postcode":"1782 bd",
    "iso:country":"NL",
    "sg:address":"Middenwg 127A",
    "sg:city":"Den Helder",
    "sg:orig_category":"Verzekeringen - Verzekeringskantoren",
    "sg:phone":"+31 223 642 234",
    "sg:postcode":"1782 BD",
    "sg:province":"North Holland",
    "sg:website":"http://www.leeuwestein.nl",
    "wof:name":"Baaren & Leeuwestein, Van",
    "wof:placetype":"venue"
},
  "geometry": {"coordinates":[4.756028,52.956184],"type":"Point"}
}