{
  "type": "Feature",
  "properties": {
    "addr:full":"Polarisavenue 150 Hoofddorp Noord-Holland 2132 JX",
    "addr:housenumber":"150",
    "addr:postcode":"2132 jx",
    "addr:street":"Polarisavenue",
    "iso:country":"NL",
    "sg:address":"Polarisavenue 150",
    "sg:city":"Hoofddorp",
    "sg:classifiers":[
        {
            "category":"Professional",
            "subcategory":"Management & Consulting",
            "type":"Services"
        }
    ],
    "sg:phone":"+31 23 554 2030",
    "sg:postcode":"2132 JX",
    "sg:province":"Noord-Holland",
    "sg:tags":[
        "relation",
        "adviesbureaus",
        "public"
    ],
    "sg:website":"http://www.edelman-dlvpr.nl",
    "wof:name":"Edelma Dlv",
    "wof:placetype":"venue"
},
  "geometry": {"coordinates":[4.70922,52.292259],"type":"Point"}
}