{
  "type": "Feature",
  "properties": {
    "addr:full":"Diepenveensewg 5 Deventer Overijssel 7413 AK",
    "addr:housenumber":"5",
    "addr:postcode":"7413 ak",
    "addr:street":"Diepenveensewg",
    "iso:country":"NL",
    "sg:address":"Diepenveensewg 5",
    "sg:city":"Deventer",
    "sg:orig_category":"Kantoor- En Secretariaatsservice",
    "sg:phone":"+31 570 620 699",
    "sg:postcode":"7413 AK",
    "sg:province":"Overijssel",
    "wof:name":"Dieperink, R",
    "wof:placetype":"venue"
},
  "geometry": {"coordinates":[6.1571631432,52.2601089478],"type":"Point"}
}