{
  "type": "Feature",
  "properties": {
    "addr:full":"Forelkolk 134 Zwolle Overijssel 8017 PK",
    "addr:housenumber":"134",
    "addr:postcode":"8017 pk",
    "addr:street":"Forelkolk",
    "iso:country":"NL",
    "sg:address":"Forelkolk 134",
    "sg:city":"Zwolle",
    "sg:classifiers":[
        {
            "category":"Food & Beverages",
            "subcategory":"Bakery",
            "type":"Retail Goods"
        }
    ],
    "sg:phone":"+31 38 465 4454",
    "sg:postcode":"8017 PK",
    "sg:province":"Overijssel",
    "sg:tags":[
        "pizza"
    ],
    "wof:name":"A Bella Vita",
    "wof:placetype":"venue"
},
  "geometry": {"coordinates":[6.093322,52.497318],"type":"Point"}
}