{
  "type": "Feature",
  "properties": {
    "iso:country":"NL",
    "sg:address":"Oldenzaalsestr 131",
    "sg:city":"Enschede",
    "sg:orig_category":"Artsen - Huisartsen",
    "sg:phone":"+31 53 435 8620",
    "sg:postcode":"7514 DR",
    "sg:province":"Overijssel",
    "wof:name":"Wegman, J H",
    "wof:placetype":"venue"
},
  "geometry": {"coordinates":[6.900097847,52.2261199951],"type":"Point"}
}