{
  "type": "Feature",
  "properties": {
    "addr:full":"Speenkruid 74 Diemen Noord-Holland 1112 NC",
    "addr:housenumber":"74",
    "addr:postcode":"1112 nc",
    "addr:street":"Speenkruid",
    "iso:country":"NL",
    "sg:address":"Speenkruid 74",
    "sg:city":"Diemen",
    "sg:orig_category":"Glazenwasserijen",
    "sg:phone":"+31 20 695 3424",
    "sg:postcode":"1112 NC",
    "sg:province":"Noord-Holland",
    "wof:name":"Plas, R J R",
    "wof:placetype":"venue"
},
  "geometry": {"coordinates":[4.956678,52.335842],"type":"Point"}
}