{
  "type": "Feature",
  "properties": {
    "addr:full":"Korvelsewg 173 Tilburg Noord-Brabant 5025 JD",
    "addr:housenumber":"173",
    "addr:postcode":"5025 jd",
    "addr:street":"Tilburg",
    "iso:country":"NL",
    "sg:address":"Korvelsewg 173",
    "sg:city":"Tilburg",
    "sg:orig_category":"Orthopedische Artikelen",
    "sg:phone":"+31 13 536 6701",
    "sg:postcode":"5025 JD",
    "sg:province":"Noord-Brabant",
    "wof:name":"Dinter, Fa Van",
    "wof:placetype":"venue"
},
  "geometry": {"coordinates":[5.0732369423,51.550907135],"type":"Point"}
}