{
  "type": "Feature",
  "properties": {
    "addr:full":"Tinstr 13 Breda North Brabant 4823 AA",
    "addr:housenumber":"13",
    "addr:postcode":"4823 aa",
    "addr:street":"Tinstr",
    "iso:country":"NL",
    "sg:address":"Tinstr 13",
    "sg:city":"Breda",
    "sg:orig_category":"Bedrijfshuisvesting",
    "sg:phone":"+31 76 548 1378",
    "sg:postcode":"4823 AA",
    "sg:province":"North Brabant",
    "wof:name":"Sawi",
    "wof:placetype":"venue"
},
  "geometry": {"coordinates":[4.71928,51.610378],"type":"Point"}
}