{
  "type": "Feature",
  "properties": {
    "addr:full":"Arkelstraat 108 Gorinchem Zuid-Holland 4201 KH",
    "addr:housenumber":"108",
    "addr:postcode":"4201 kh",
    "addr:street":"Arkelstraat",
    "iso:country":"NL",
    "sg:address":"Arkelstraat 108",
    "sg:city":"Gorinchem",
    "sg:orig_category":"Werving And Selectie Van Vast Personeel",
    "sg:phone":"+31 900 7002404",
    "sg:postcode":"4201 KH",
    "sg:province":"Zuid-Holland",
    "wof:name":"Employment Vision, W & S Bureau",
    "wof:placetype":"venue"
},
  "geometry": {"coordinates":[4.9754037857,51.8321075439],"type":"Point"}
}