{
  "type": "Feature",
  "properties": {
    "addr:full":"Sophialaan 39 Amsterdam Noord-Holland 1075 BM",
    "addr:housenumber":"39",
    "addr:postcode":"1075 bm",
    "addr:street":"Sophialaan",
    "iso:country":"NL",
    "sg:address":"Sophialaan 39",
    "sg:city":"Amsterdam",
    "sg:orig_category":"Advocaten And Juridische Adviseurs",
    "sg:phone":"+31 20 471 0805",
    "sg:postcode":"1075 BM",
    "sg:province":"Noord-Holland",
    "wof:name":"B M C Pouw",
    "wof:placetype":"venue"
},
  "geometry": {"coordinates":[4.85812,52.352421],"type":"Point"}
}