{
  "type": "Feature",
  "properties": {
    "addr:full":"Fazantenkamp 768 Maarssen Utrecht 3607 DT",
    "addr:housenumber":"768",
    "addr:postcode":"3607 dt",
    "addr:street":"Fazantenkamp",
    "iso:country":"NL",
    "sg:address":"Fazantenkamp 768",
    "sg:city":"Maarssen",
    "sg:orig_category":"Werving And Selectie Van Vast Personeel",
    "sg:phone":"+31 346 567 571",
    "sg:postcode":"3607 DT",
    "sg:province":"Utrecht",
    "wof:name":"Va Vl",
    "wof:placetype":"venue"
},
  "geometry": {"coordinates":[5.0248222351,52.129699707],"type":"Point"}
}