{
  "type": "Feature",
  "properties": {
    "addr:full":"Dorpsstraat 7 Noord Sleen Drenthe 7846 AS",
    "addr:housenumber":"7",
    "addr:postcode":"7846 as",
    "addr:street":"Dorpsstraat",
    "iso:country":"NL",
    "sg:address":"Dorpsstraat 7",
    "sg:city":"Noord Sleen",
    "sg:orig_category":"Fruit And Groenten Gh",
    "sg:phone":"+31 591 362 370",
    "sg:postcode":"7846 AS",
    "sg:province":"Drenthe",
    "wof:name":"Beckering'S Exploitatie Maatschappij Bv",
    "wof:placetype":"venue"
},
  "geometry": {"coordinates":[6.797401,52.793476],"type":"Point"}
}