{
  "type": "Feature",
  "properties": {
    "iso:country":"NL",
    "sg:address":"Kerkstraat 33",
    "sg:city":"Enschede",
    "sg:orig_category":"Kappers",
    "sg:phone":"+31 53 461 3602",
    "sg:postcode":"7532 AP",
    "sg:province":"NL.08",
    "wof:name":"Hairstyling Salon Bertine",
    "wof:placetype":"venue"
},
  "geometry": {"coordinates":[6.9734010696,52.2168312073],"type":"Point"}
}