{
  "type": "Feature",
  "properties": {
    "addr:full":"Ruys De Beerenbroucklaan 36 Heerlen Limburg 6411 GB",
    "addr:housenumber":"36",
    "addr:postcode":"6411 gb",
    "addr:street":"Ruys De Beerenbroucklaan",
    "iso:country":"NL",
    "sg:address":"Ruys De Beerenbroucklaan 36",
    "sg:city":"Heerlen",
    "sg:orig_category":"Kinderopvang Behalve Thuis",
    "sg:phone":"+31 45 571 0407",
    "sg:postcode":"6411 GB",
    "sg:province":"Limburg",
    "wof:name":"Kinderdagverblijf Beerengoed",
    "wof:placetype":"venue"
},
  "geometry": {"coordinates":[5.981654,50.882713],"type":"Point"}
}