{
  "type": "Feature",
  "properties": {
    "addr:full":"Mennewg 163 Sassenheim Zuid-Holland 2172 HC",
    "addr:housenumber":"163",
    "addr:postcode":"sassenheim;2172 hc",
    "iso:country":"NL",
    "sg:address":"Mennewg 163",
    "sg:city":"Sassenheim",
    "sg:orig_category":"Baggerwerken",
    "sg:phone":"+31 252 211 975",
    "sg:postcode":"2172 HC",
    "sg:province":"Zuid-Holland",
    "wof:name":"Reuser, A J M",
    "wof:placetype":"venue"
},
  "geometry": {"coordinates":[4.528177,52.218994],"type":"Point"}
}