{
  "type": "Feature",
  "properties": {
    "addr:full":"R Luxemburgstr 15 Almelo Overijssel 7607 SM",
    "addr:housenumber":"15",
    "addr:postcode":"7607 sm",
    "iso:country":"NL",
    "sg:address":"R Luxemburgstr 15",
    "sg:city":"Almelo",
    "sg:orig_category":"Verlichting",
    "sg:phone":"+31 546 821 185",
    "sg:postcode":"7607 SM",
    "sg:province":"Overijssel",
    "wof:name":"Lampenier",
    "wof:placetype":"venue"
},
  "geometry": {"coordinates":[6.662385,52.356674],"type":"Point"}
}