{
  "type": "Feature",
  "properties": {
    "addr:full":"Zonnebergerdijk 42-46 Heeten Overijssel 8111 ND",
    "addr:housenumber":"42-46",
    "addr:postcode":"8111 nd",
    "iso:country":"NL",
    "sg:address":"Zonnebergerdijk 42-46",
    "sg:city":"Heeten",
    "sg:orig_category":"Zonnebanken En Solaria - Fabrieken En Groothandel",
    "sg:phone":"+31 6 13530405",
    "sg:postcode":"8111 ND",
    "sg:province":"Overijssel",
    "wof:name":"Sundance Zonnehemel Verhuur",
    "wof:placetype":"venue"
},
  "geometry": {"coordinates":[-100.30171199999999,47.467731],"type":"Point"}
}