{
  "type": "Feature",
  "properties": {
    "addr:full":"H Hindersstr 54 Oude Pekela Groningen 9665 RC",
    "addr:housenumber":"54",
    "addr:postcode":"pekela;9665 rc",
    "addr:street":"Oude",
    "iso:country":"NL",
    "sg:address":"H Hindersstr 54",
    "sg:city":"Oude Pekela",
    "sg:orig_category":"Scholen Voor Basisonderwijs",
    "sg:phone":"+31 597 613 720",
    "sg:postcode":"9665 RC",
    "sg:province":"Groningen",
    "wof:name":"Hendrik Wester",
    "wof:placetype":"venue"
},
  "geometry": {"coordinates":[6.989617,53.093548],"type":"Point"}
}