{
  "type": "Feature",
  "properties": {
    "addr:full":"Berckheideln 30 Heerhugowaard Noord-Holland 1701 VG",
    "addr:housenumber":"30",
    "addr:postcode":"1701 vg",
    "addr:street":"Berckheideln",
    "iso:country":"NL",
    "sg:address":"Berckheideln 30",
    "sg:city":"Heerhugowaard",
    "sg:orig_category":"Kappers",
    "sg:phone":"+31 72 571 0988",
    "sg:postcode":"1701 VG",
    "sg:province":"Noord-Holland",
    "wof:name":"Vitu",
    "wof:placetype":"venue"
},
  "geometry": {"coordinates":[4.827522,52.665195],"type":"Point"}
}