{
  "type": "Feature",
  "properties": {
    "addr:full":"Dr Nolenslaan 157 Sittard Limburg 6136 GM",
    "addr:housenumber":"157",
    "addr:postcode":"6136 gm",
    "addr:street":"Dr Nolenslaan",
    "iso:country":"NL",
    "sg:address":"Dr Nolenslaan 157",
    "sg:city":"Sittard",
    "sg:orig_category":"Juridische Dienstverlening",
    "sg:phone":"+31 46 420 0420",
    "sg:postcode":"6136 GM",
    "sg:province":"Limburg",
    "wof:name":"Algemeen Octrooibureau",
    "wof:placetype":"venue"
},
  "geometry": {"coordinates":[5.860406,51.018322],"type":"Point"}
}