{
  "type": "Feature",
  "properties": {
    "addr:full":"Kerkstr 17 St Oedenrode Noord-Brabant 5492 AH",
    "addr:housenumber":"17",
    "addr:postcode":"5492 ah",
    "addr:street":"Kerkstr",
    "iso:country":"NL",
    "sg:address":"Kerkstr 17",
    "sg:city":"St Oedenrode",
    "sg:orig_category":"Advocaten En Advocatenkantoren",
    "sg:phone":"+31 413 477 996",
    "sg:postcode":"5492 AH",
    "sg:province":"Noord-Brabant",
    "wof:name":"Bouwman",
    "wof:placetype":"venue"
},
  "geometry": {"coordinates":[5.459725,51.562397],"type":"Point"}
}