{
  "type": "Feature",
  "properties": {
    "addr:full":"Jacobsheul 3 Nieuwerkerk Zeeland 4306 EC",
    "addr:housenumber":"3",
    "addr:postcode":"4306 ec",
    "addr:street":"Jacobsheul",
    "iso:country":"NL",
    "sg:address":"Jacobsheul 3",
    "sg:city":"Nieuwerkerk",
    "sg:classifiers":[
        {
            "category":"Personal",
            "subcategory":"Nail Salon",
            "type":"Services"
        }
    ],
    "sg:phone":"+31 111 641 370",
    "sg:postcode":"4306 EC",
    "sg:province":"Zeeland",
    "sg:tags":[
        "pedicure"
    ],
    "wof:name":"Jessica",
    "wof:placetype":"venue"
},
  "geometry": {"coordinates":[4.000664,51.649048],"type":"Point"}
}