{
  "type": "Feature",
  "properties": {
    "addr:full":"Nijverheidsweg 25 Tynaarlo Drenthe 9482 WB",
    "addr:housenumber":"25",
    "addr:postcode":"9482 wb",
    "addr:street":"Nijverheidsweg",
    "iso:country":"NL",
    "sg:address":"Nijverheidsweg 25",
    "sg:city":"Tynaarlo",
    "sg:orig_category":"Airconditioning And Ventilatie",
    "sg:phone":"+31 592 461 100",
    "sg:postcode":"9482 WB",
    "sg:province":"Drenthe",
    "wof:name":"Joco Benelux Bv",
    "wof:placetype":"venue"
},
  "geometry": {"coordinates":[6.597786,53.082981],"type":"Point"}
}