{
  "type": "Feature",
  "properties": {
    "addr:full":"Nieuwe Huizen 43 Breda Noord-Brabant 4811 TL",
    "addr:housenumber":"43",
    "addr:postcode":"4811 tl",
    "addr:street":"Nieuwe Huizen",
    "iso:country":"NL",
    "sg:address":"Nieuwe Huizen 43",
    "sg:city":"Breda",
    "sg:orig_category":"Kinderopvang Behalve Thuis",
    "sg:phone":"+31 76 522 4426",
    "sg:postcode":"4811 TL",
    "sg:province":"Noord-Brabant",
    "wof:name":"Pino",
    "wof:placetype":"venue"
},
  "geometry": {"coordinates":[4.764548,51.586094],"type":"Point"}
}