{
  "type": "Feature",
  "properties": {
    "addr:full":"Wederik 1 Zeewolde Flevoland 3892 AH",
    "addr:housenumber":"1",
    "addr:postcode":"3892 ah",
    "addr:street":"Wederik;Flevoland",
    "iso:country":"NL",
    "sg:address":"Wederik 1",
    "sg:city":"Zeewolde",
    "sg:classifiers":[
        {
            "category":"Shopping",
            "subcategory":"News",
            "type":"Retail Goods"
        }
    ],
    "sg:phone":"+31 36 522 2640",
    "sg:postcode":"3892 AH",
    "sg:province":"Flevoland",
    "sg:tags":[
        "maandbladen",
        "en",
        "week-"
    ],
    "wof:name":"Zeewolde Aktueel",
    "wof:placetype":"venue"
},
  "geometry": {"coordinates":[5.5414118767,52.3271446228],"type":"Point"}
}