{
  "type": "Feature",
  "properties": {
    "addr:full":"Adamshofstr 129A Rotterdam South Holland 3061 ZD",
    "addr:housenumber":"129a",
    "addr:postcode":"3061 zd",
    "iso:country":"NL",
    "sg:address":"Adamshofstr 129A",
    "sg:city":"Rotterdam",
    "sg:classifiers":[
        {
            "category":"Government",
            "subcategory":"Post Office",
            "type":"Public Place"
        }
    ],
    "sg:phone":"+31 10 414 2305",
    "sg:postcode":"3061 ZD",
    "sg:province":"South Holland",
    "sg:tags":[
        "poster"
    ],
    "wof:name":"Photovision Photography",
    "wof:placetype":"venue"
},
  "geometry": {"coordinates":[4.50907,51.922848],"type":"Point"}
}