{
  "type": "Feature",
  "properties": {
    "iso:country":"NL",
    "sg:address":"Kerkstr 43",
    "sg:city":"Monnickendam",
    "sg:orig_category":"Zonnebank- En Solariumcentra",
    "sg:phone":"+31 299 655 231",
    "sg:postcode":"1141 BG",
    "sg:province":"North Holland",
    "wof:name":"Mallorca",
    "wof:placetype":"venue"
},
  "geometry": {"coordinates":[5.034766,52.45879],"type":"Point"}
}