{
  "type": "Feature",
  "properties": {
    "addr:full":"Stationsstr 116 Putten Gelderland 3881 AG",
    "addr:housenumber":"116",
    "addr:postcode":"3881",
    "addr:street":"Gelderland",
    "iso:country":"NL",
    "sg:address":"Stationsstr 116",
    "sg:city":"Putten",
    "sg:orig_category":"Autoreclame",
    "sg:phone":"+31 341 354 897",
    "sg:postcode":"3881 AG",
    "sg:province":"Gelderland",
    "sg:website":"http://www.cdm-belettering.nl",
    "wof:name":"Cdm Belettering",
    "wof:placetype":"venue"
},
  "geometry": {"coordinates":[5.580017,52.265274],"type":"Point"}
}