{
  "type": "Feature",
  "properties": {
    "addr:full":"Breedstr 47 Enkhuizen North Holland 1601 KA",
    "addr:housenumber":"47",
    "addr:postcode":"1601 ka",
    "addr:street":"Breedstr",
    "iso:country":"NL",
    "sg:address":"Breedstr 47",
    "sg:city":"Enkhuizen",
    "sg:orig_category":"Verenigingsgebouwen",
    "sg:phone":"+31 228 312 634",
    "sg:postcode":"1601 KA",
    "sg:province":"North Holland",
    "wof:name":"Hervormd Centr",
    "wof:placetype":"venue"
},
  "geometry": {"coordinates":[5.294854,52.704357],"type":"Point"}
}