{
  "type": "Feature",
  "properties": {
    "addr:full":"Eelerbergstr 74 Almere NL. 1333 ZX",
    "addr:housenumber":"74",
    "addr:postcode":"1333 zx",
    "addr:street":"Eelerbergstr;Nl.",
    "iso:country":"NL",
    "sg:address":"Eelerbergstr 74",
    "sg:city":"Almere",
    "sg:orig_category":"Administratie- En Boekhoudkantoren",
    "sg:phone":"+31 36 532 4757",
    "sg:postcode":"1333 ZX",
    "sg:province":"NL.",
    "wof:name":"Hg",
    "wof:placetype":"venue"
},
  "geometry": {"coordinates":[5.265445,52.384399],"type":"Point"}
}