{
  "type": "Feature",
  "properties": {
    "iso:country":"NL",
    "sg:address":"Pr Florispln 13",
    "sg:city":"Bathmen",
    "sg:orig_category":"Verzekerings- Maatschappijen",
    "sg:phone":"+31 570 541 368",
    "sg:postcode":"7437 XR",
    "sg:province":"Overijssel",
    "wof:name":"Onderlinge Paardenverz",
    "wof:placetype":"venue"
},
  "geometry": {"coordinates":[6.297912,52.248756],"type":"Point"}
}