{
  "type": "Feature",
  "properties": {
    "addr:full":"Schout Janszpad 22 Hoogvliet Rt South Holland 3191 HD",
    "addr:housenumber":"22",
    "addr:postcode":"3191 hd",
    "addr:street":"Schout Janszpad;Rt South",
    "iso:country":"NL",
    "sg:address":"Schout Janszpad 22",
    "sg:city":"Hoogvliet Rt",
    "sg:orig_category":"Goederenvervoer Over De Weg",
    "sg:phone":"+31 10 438 1737",
    "sg:postcode":"3191 HD",
    "sg:province":"South Holland",
    "wof:name":"G.C. Locker",
    "wof:placetype":"venue"
},
  "geometry": {"coordinates":[4.366844,51.859604],"type":"Point"}
}