{
  "type": "Feature",
  "properties": {
    "iso:country":"NL",
    "sg:address":"Schout Janszpad 22",
    "sg:city":"Hoogvliet Rt",
    "sg:orig_category":"Goederenvervoer Over De Weg",
    "sg:phone":"+31 10 438 1737",
    "sg:postcode":"3191 HD",
    "sg:province":"South Holland",
    "wof:name":"G.C. Locker",
    "wof:placetype":"venue"
},
  "geometry": {"coordinates":[4.366844,51.859604],"type":"Point"}
}