{
  "type": "Feature",
  "properties": {
    "addr:full":"Drechterland 41 Zoetermeer Zuid-Holland 2716 CE",
    "addr:housenumber":"41",
    "addr:postcode":"2716 ce",
    "addr:street":"Drechterland",
    "iso:country":"NL",
    "sg:address":"Drechterland 41",
    "sg:city":"Zoetermeer",
    "sg:orig_category":"Autoreclame",
    "sg:phone":"+31 79 352 1331",
    "sg:postcode":"2716 CE",
    "sg:province":"Zuid-Holland",
    "wof:name":"Root Art Design",
    "wof:placetype":"venue"
},
  "geometry": {"coordinates":[4.462128,52.053421],"type":"Point"}
}