{
  "type": "Feature",
  "properties": {
    "iso:country":"NL",
    "sg:address":"Eoceenstraat 45",
    "sg:city":"Heerlen",
    "sg:orig_category":"Beautyfarms And Sauna'S",
    "sg:phone":"+31 45 572 8319",
    "sg:postcode":"6412 DC",
    "sg:province":"Limburg",
    "wof:name":"H. Smit",
    "wof:placetype":"venue"
},
  "geometry": {"coordinates":[5.964998,50.898674],"type":"Point"}
}