{
  "type": "Feature",
  "properties": {
    "addr:full":"Huisdreef 1 Alphen Nb Noord-Brabant 5131 NH",
    "addr:housenumber":"1",
    "addr:postcode":"5131 nh",
    "addr:street":"Huisdreef",
    "iso:country":"NL",
    "sg:address":"Huisdreef 1",
    "sg:city":"Alphen Nb",
    "sg:orig_category":"Kampeerterreinen",
    "sg:phone":"+31 13 508 1480",
    "sg:postcode":"5131 NH",
    "sg:province":"Noord-Brabant",
    "wof:name":"Camping Buitenlust Bv",
    "wof:placetype":"venue"
},
  "geometry": {"coordinates":[4.9107580185,51.5010490417],"type":"Point"}
}