{
  "type": "Feature",
  "properties": {
    "addr:full":"Charles Vos Cour 22 Maastricht Limburg 6211 XR",
    "addr:housenumber":"22",
    "addr:postcode":"6211 xr",
    "addr:street":"Cour",
    "iso:country":"NL",
    "sg:address":"Charles Vos Cour 22",
    "sg:city":"Maastricht",
    "sg:orig_category":"Architecten",
    "sg:phone":"+31 43 325 3507",
    "sg:postcode":"6211 XR",
    "sg:province":"Limburg",
    "wof:name":"Architectenbureau Joop Slangen",
    "wof:placetype":"venue"
},
  "geometry": {"coordinates":[5.684521,50.852753],"type":"Point"}
}