{
  "type": "Feature",
  "properties": {
    "addr:full":"Notel 12 Oirschot Noord-Brabant 5688 NB",
    "addr:housenumber":"12",
    "addr:postcode":"5688 nb",
    "addr:street":"Notel",
    "iso:country":"NL",
    "sg:address":"Notel 12",
    "sg:city":"Oirschot",
    "sg:orig_category":"Adviesbureaus Bedrijfsorganisatie",
    "sg:phone":"+31 40 263 1123",
    "sg:postcode":"5688 NB",
    "sg:province":"Noord-Brabant",
    "wof:name":"Nijenhuis Bv",
    "wof:placetype":"venue"
},
  "geometry": {"coordinates":[5.325532,51.507599],"type":"Point"}
}