{
  "type": "Feature",
  "properties": {
    "iso:country":"NL",
    "sg:address":"Kasteel Neubourgweg 92",
    "sg:city":"Maastricht",
    "sg:orig_category":"Fotostudio'S And Fotografen",
    "sg:phone":"+31 43 363 7419",
    "sg:postcode":"6222 SH",
    "sg:province":"Limburg",
    "wof:name":"Bert Janssen Fotografie",
    "wof:placetype":"venue"
},
  "geometry": {"coordinates":[5.719224,50.865673],"type":"Point"}
}