{
  "type": "Feature",
  "properties": {
    "addr:full":"V Pomerenstr 26 Hippolytushoef North Holland 1777 BE",
    "addr:housenumber":"26",
    "addr:postcode":"1777",
    "iso:country":"NL",
    "sg:address":"V Pomerenstr 26",
    "sg:city":"Hippolytushoef",
    "sg:orig_category":"On- Offshore",
    "sg:phone":"+31 227 592 074",
    "sg:postcode":"1777 BE",
    "sg:province":"North Holland",
    "wof:name":"Hunter Cv",
    "wof:placetype":"venue"
},
  "geometry": {"coordinates":[4.960445,52.905769],"type":"Point"}
}