{
  "type": "Feature",
  "properties": {
    "addr:full":"Ramstr 22 Leeuwarden Friesland 8921 PZ",
    "addr:housenumber":"22",
    "addr:postcode":"8921 pz",
    "addr:street":"Ramstr",
    "iso:country":"NL",
    "sg:address":"Ramstr 22",
    "sg:city":"Leeuwarden",
    "sg:orig_category":"Kermisexploitatie",
    "sg:phone":"+31 58 213 9478",
    "sg:postcode":"8921 PZ",
    "sg:province":"Friesland",
    "wof:name":"Tichelaar En Zoon, J",
    "wof:placetype":"venue"
},
  "geometry": {"coordinates":[5.809453,53.20853],"type":"Point"}
}