{
  "type": "Feature",
  "properties": {
    "addr:full":"Besterdring 151 Tilburg Noord-Brabant 5014 HK",
    "addr:housenumber":"151",
    "addr:postcode":"5014 hk",
    "addr:street":"Besterdring",
    "iso:country":"NL",
    "sg:address":"Besterdring 151",
    "sg:city":"Tilburg",
    "sg:orig_category":"Opticiens",
    "sg:phone":"+31 13 542 5197",
    "sg:postcode":"5014 HK",
    "sg:province":"Noord-Brabant",
    "wof:name":"Van Gijzen Optiek Bv",
    "wof:placetype":"venue"
},
  "geometry": {"coordinates":[5.0905542374,51.5638694763],"type":"Point"}
}