{
  "type": "Feature",
  "properties": {
    "iso:country":"NL",
    "sg:address":"Boerenstr 54",
    "sg:city":"Gorinchem",
    "sg:orig_category":"Beveiliging",
    "sg:phone":"+31 183 660 003",
    "sg:postcode":"4201 GB",
    "sg:province":"Zuid-Holland",
    "sg:website":"http://www.veilighuisnederland.nl",
    "wof:name":"Veilig Huis Nederland",
    "wof:placetype":"venue"
},
  "geometry": {"coordinates":[4.972637,51.828045],"type":"Point"}
}