{
  "type": "Feature",
  "properties": {
    "addr:full":"Strawinskyln 3111 Amsterdam Noord-Holland 1077 ZX",
    "addr:housenumber":"3111",
    "addr:postcode":"1077 zx",
    "iso:country":"NL",
    "sg:address":"Strawinskyln 3111",
    "sg:city":"Amsterdam",
    "sg:orig_category":"Adviesbureaus Financieel",
    "sg:phone":"+31 20 442 0245",
    "sg:postcode":"1077 ZX",
    "sg:province":"Noord-Holland",
    "wof:name":"Schickedanz Bv",
    "wof:placetype":"venue"
},
  "geometry": {"coordinates":[4.869382,52.340435],"type":"Point"}
}