{
  "type": "Feature",
  "properties": {
    "addr:full":"Kloosterstr 3 Beuningen Gld Gelderland 6641 KW",
    "addr:housenumber":"3",
    "addr:postcode":"6641 kw",
    "addr:street":"Kloosterstr",
    "iso:country":"NL",
    "sg:address":"Kloosterstr 3",
    "sg:city":"Beuningen Gld",
    "sg:orig_category":"Psychotherapeuten",
    "sg:phone":"+31 24 677 4885",
    "sg:postcode":"6641 KW",
    "sg:province":"Gelderland",
    "wof:name":"Baartmans, Elfry",
    "wof:placetype":"venue"
},
  "geometry": {"coordinates":[5.772531,51.865761],"type":"Point"}
}