{
  "type": "Feature",
  "properties": {
    "addr:full":"Wg-Plein 553 Amsterdam Noord-Holland 1054 SJ",
    "addr:housenumber":"553",
    "addr:postcode":"1054",
    "addr:street":"Wg-Plein",
    "iso:country":"NL",
    "sg:address":"Wg-Plein 553",
    "sg:city":"Amsterdam",
    "sg:orig_category":"Public Relationbureaus",
    "sg:phone":"+31 20 616 3453",
    "sg:postcode":"1054 SJ",
    "sg:province":"Noord-Holland",
    "wof:name":"Movement",
    "wof:placetype":"venue"
},
  "geometry": {"coordinates":[4.871848,52.364388],"type":"Point"}
}