{
  "type": "Feature",
  "properties": {
    "addr:full":"Sluiskade 32 Almere Flevoland 1353 BV",
    "addr:housenumber":"32",
    "addr:postcode":"1353 bv",
    "addr:street":"Sluiskade;Flevoland",
    "iso:country":"NL",
    "sg:address":"Sluiskade 32",
    "sg:city":"Almere",
    "sg:orig_category":"Kansspelen",
    "sg:phone":"+31 36 534 8444",
    "sg:postcode":"1353 BV",
    "sg:province":"Flevoland",
    "wof:name":"Fair Play",
    "wof:placetype":"venue"
},
  "geometry": {"coordinates":[5.2185931206,52.3335533142],"type":"Point"}
}