{
  "type": "Feature",
  "properties": {
    "addr:full":"Glorieuxln 2 Vught Noord-Brabant 5261 SJ",
    "addr:housenumber":"2",
    "addr:postcode":"5261",
    "addr:street":"Glorieuxln",
    "iso:country":"NL",
    "sg:address":"Glorieuxln 2",
    "sg:city":"Vught",
    "sg:orig_category":"Bedrijfskleding",
    "sg:phone":"+31 73 656 5723",
    "sg:postcode":"5261 SJ",
    "sg:province":"Noord-Brabant",
    "sg:website":"http://www.fashionforbusiness.nl",
    "wof:name":"Fashion For Business",
    "wof:placetype":"venue"
},
  "geometry": {"coordinates":[5.300947,51.651112],"type":"Point"}
}