{
  "type": "Feature",
  "properties": {
    "addr:full":"Kon Wilhelminastr 54 Dordrecht South Holland 3311 LN",
    "addr:housenumber":"54",
    "addr:postcode":"3311 ln",
    "addr:street":"Kon Wilhelminastr",
    "iso:country":"NL",
    "sg:address":"Kon Wilhelminastr 54",
    "sg:city":"Dordrecht",
    "sg:orig_category":"Grafisch Ontwerpers",
    "sg:phone":"+31 78 631 0493",
    "sg:postcode":"3311 LN",
    "sg:province":"South Holland",
    "sg:website":"http://www.zock.nl",
    "wof:name":"Zock Design",
    "wof:placetype":"venue"
},
  "geometry": {"coordinates":[4.669183,51.810112],"type":"Point"}
}