{
  "type": "Feature",
  "properties": {
    "addr:full":"Kastanjeln 20 Alkmaar North Holland 1815 EC",
    "addr:housenumber":"20",
    "addr:postcode":"1815 ec",
    "addr:street":"Kastanjeln",
    "iso:country":"NL",
    "sg:address":"Kastanjeln 20",
    "sg:city":"Alkmaar",
    "sg:orig_category":"Voetbalverenigingen",
    "sg:phone":"+31 72 515 1176",
    "sg:postcode":"1815 EC",
    "sg:province":"North Holland",
    "wof:name":"Canisius United",
    "wof:placetype":"venue"
},
  "geometry": {"coordinates":[4.746258,52.634361],"type":"Point"}
}