{
  "type": "Feature",
  "properties": {
    "addr:full":"V Stuartln 17F Ryswyk Zh South Holland 2288 EK",
    "addr:housenumber":"17f",
    "addr:postcode":"2288 ek",
    "addr:street":"Ryswyk Zh",
    "iso:country":"NL",
    "sg:address":"V Stuartln 17F",
    "sg:city":"Ryswyk Zh",
    "sg:orig_category":"Onderzoekbureaus",
    "sg:phone":"+31 70 319 3045",
    "sg:postcode":"2288 EK",
    "sg:province":"South Holland",
    "sg:website":"http://www.comparison.nl",
    "wof:name":"Comparison",
    "wof:placetype":"venue"
},
  "geometry": {"coordinates":[4.32436,52.037251],"type":"Point"}
}