{
  "type": "Feature",
  "properties": {
    "addr:full":"De Grutto 11 Hoogeveen Provincie Drenthe 7905 BA",
    "addr:housenumber":"11",
    "addr:postcode":"7905 ba",
    "addr:street":"De Grutto;Provincie",
    "iso:country":"NL",
    "sg:address":"De Grutto 11",
    "sg:city":"Hoogeveen",
    "sg:orig_category":"Verlichting And Huishoudartikelen",
    "sg:phone":"+31 528 279 186",
    "sg:postcode":"7905 BA",
    "sg:province":"Provincie Drenthe",
    "wof:name":"Vd Weide Advisering En Serviceburo",
    "wof:placetype":"venue"
},
  "geometry": {"coordinates":[6.497497,52.713589],"type":"Point"}
}