{
  "type": "Feature",
  "properties": {
    "addr:full":"Feestdans 101 Capelle Ad Yssel Zuid-Holland 2907 TH",
    "addr:housenumber":"101;2907",
    "addr:postcode":"th",
    "addr:street":"Feestdans",
    "iso:country":"NL",
    "sg:address":"Feestdans 101",
    "sg:city":"Capelle Ad Yssel",
    "sg:orig_category":"Autorijscholen",
    "sg:phone":"+31 10 458 2788",
    "sg:postcode":"2907 TH",
    "sg:province":"Zuid-Holland",
    "wof:name":"Bruijn, G De",
    "wof:placetype":"venue"
},
  "geometry": {"coordinates":[4.571012,51.950199],"type":"Point"}
}