{
  "type": "Feature",
  "properties": {
    "addr:full":"Kruisvaardersstraat 28D Tilburg Noord-Brabant 5021 BD",
    "addr:housenumber":"28d",
    "addr:postcode":"5021 bd",
    "addr:street":"Kruisvaardersstraat",
    "iso:country":"NL",
    "sg:address":"Kruisvaardersstraat 28D",
    "sg:city":"Tilburg",
    "sg:orig_category":"Artsen And Specialisten",
    "sg:phone":"+31 13 542 4982",
    "sg:postcode":"5021 BD",
    "sg:province":"Noord-Brabant",
    "wof:name":"A.M.M. Kouwenhoven",
    "wof:placetype":"venue"
},
  "geometry": {"coordinates":[5.099228,51.550678],"type":"Point"}
}