{
  "type": "Feature",
  "properties": {
    "addr:full":"Hofstr 44 Hillegom Zuid-Holland 2181 AX",
    "addr:housenumber":"44",
    "addr:postcode":"2181 ax",
    "addr:street":"Hofstr",
    "iso:country":"NL",
    "sg:address":"Hofstr 44",
    "sg:city":"Hillegom",
    "sg:orig_category":"Verzekeringen - Verzekeringskantoren",
    "sg:phone":"+31 252 530 542",
    "sg:postcode":"2181 AX",
    "sg:province":"Zuid-Holland",
    "wof:name":"Attentiv Bv",
    "wof:placetype":"venue"
},
  "geometry": {"coordinates":[4.582016,52.29105],"type":"Point"}
}