{
  "type": "Feature",
  "properties": {
    "iso:country":"NL",
    "sg:address":"Aan De Fremme 5",
    "sg:city":"Margraten",
    "sg:orig_category":"Autokeuringen",
    "sg:phone":"+31 43 458 1892",
    "sg:postcode":"6269 BK",
    "sg:province":"Limburg",
    "wof:name":"Vakgarage Oto Margraten",
    "wof:placetype":"venue"
},
  "geometry": {"coordinates":[5.82968,50.822025],"type":"Point"}
}