{
  "type": "Feature",
  "properties": {
    "addr:full":"Prins Willem-Alexanderln 1423 Apeldoorn Gelderland 7312 GB",
    "addr:housenumber":"1423",
    "addr:postcode":"7312 gb",
    "addr:street":"Prins Willem-Alexanderln;Gelderland",
    "iso:country":"NL",
    "sg:address":"Prins Willem-Alexanderln 1423",
    "sg:city":"Apeldoorn",
    "sg:orig_category":"Kantoorapparatuur Gh",
    "sg:phone":"+31 55 355 4444",
    "sg:postcode":"7312 GB",
    "sg:province":"Gelderland",
    "wof:name":"Dijkgraaf Rijsdorp Bv",
    "wof:placetype":"venue"
},
  "geometry": {"coordinates":[5.9483571053,52.2061309814],"type":"Point"}
}