{
  "type": "Feature",
  "properties": {
    "addr:full":"Hooftstraat 116 Alphen A/D Rijn Zuid-Holland 2406 GM",
    "addr:housenumber":"116",
    "addr:postcode":"2406 gm",
    "addr:street":"Hooftstraat",
    "iso:country":"NL",
    "sg:address":"Hooftstraat 116",
    "sg:city":"Alphen A/D Rijn",
    "sg:orig_category":"Kappers",
    "sg:phone":"+31 172 475 576",
    "sg:postcode":"2406 GM",
    "sg:province":"Zuid-Holland",
    "wof:name":"Face It Hair Design",
    "wof:placetype":"venue"
},
  "geometry": {"coordinates":[4.6636929512,52.133392334],"type":"Point"}
}