{
  "type": "Feature",
  "properties": {
    "iso:country":"NL",
    "sg:address":"Lange Zuiderweg 130",
    "sg:city":"Voorthuizen",
    "sg:orig_category":"Kampeerterreinen",
    "sg:phone":"+31 342 472 590",
    "sg:postcode":"3781 PL",
    "sg:province":"Gelderland",
    "wof:name":"Camping De Tussenlanding",
    "wof:placetype":"venue"
},
  "geometry": {"coordinates":[5.6534771919,52.1931381226],"type":"Point"}
}