{
  "type": "Feature",
  "properties": {
    "addr:full":"Valeriusstr 218 Amsterdam Noord-Holland 1075 GK",
    "addr:housenumber":"218",
    "addr:postcode":"1075 gk",
    "iso:country":"NL",
    "sg:address":"Valeriusstr 218",
    "sg:city":"Amsterdam",
    "sg:orig_category":"Video - Faciliteiten En Producties",
    "sg:phone":"+31 20 676 8603",
    "sg:postcode":"1075 GK",
    "sg:province":"Noord-Holland",
    "sg:website":"http://www.doctoredit.nl",
    "wof:name":"Doctor Edit",
    "wof:placetype":"venue"
},
  "geometry": {"coordinates":[4.861255,52.352287],"type":"Point"}
}