{
  "type": "Feature",
  "properties": {
    "addr:full":"Celsiusstraat 27 Terneuzen Zeeland 4532 KV",
    "addr:housenumber":"27",
    "addr:postcode":"4532 kv",
    "addr:street":"Celsiusstraat",
    "iso:country":"NL",
    "sg:address":"Celsiusstraat 27",
    "sg:city":"Terneuzen",
    "sg:orig_category":"Autokeuringen",
    "sg:phone":"+31 115 620 136",
    "sg:postcode":"4532 KV",
    "sg:province":"Zeeland",
    "wof:name":"K.H.U. Guthe Bv",
    "wof:placetype":"venue"
},
  "geometry": {"coordinates":[3.851895,51.331249],"type":"Point"}
}