{
  "type": "Feature",
  "properties": {
    "iso:country":"NL",
    "sg:address":"Byrdstraat 15",
    "sg:city":"Eindhoven",
    "sg:orig_category":"Fruit And Groenten Gh",
    "sg:phone":"+31 40 243 0733",
    "sg:postcode":"5623 PL",
    "sg:province":"North Brabant",
    "wof:name":"J.A.C. Roubos. Eindhovense Aardappelhand",
    "wof:placetype":"venue"
},
  "geometry": {"coordinates":[5.480046,51.454288],"type":"Point"}
}