{
  "type": "Feature",
  "properties": {
    "addr:full":"Boxbergerwg 82 Deventer NL.08 7412 BG",
    "addr:housenumber":"82;nl.08",
    "addr:postcode":"7412",
    "addr:street":"Boxbergerwg",
    "iso:country":"NL",
    "sg:address":"Boxbergerwg 82",
    "sg:city":"Deventer",
    "sg:orig_category":"Verf En Lak",
    "sg:phone":"+31 570 613 730",
    "sg:postcode":"7412 BG",
    "sg:province":"NL.08",
    "wof:name":"Mourik Bv, Van",
    "wof:placetype":"venue"
},
  "geometry": {"coordinates":[6.150587,52.259945],"type":"Point"}
}