{
  "type": "Feature",
  "properties": {
    "iso:country":"NL",
    "sg:address":"Piet Heinstraat 2",
    "sg:city":"Haastrecht",
    "sg:orig_category":"Hang- And Sluitwerk Fab",
    "sg:phone":"+31 182 502 198",
    "sg:postcode":"2851 TG",
    "sg:province":"Zuid-Holland",
    "wof:name":"Hkc (Haastrechtse Klus Centrale)",
    "wof:placetype":"venue"
},
  "geometry": {"coordinates":[4.7711048126,52.0022697449],"type":"Point"}
}