{
  "type": "Feature",
  "properties": {
    "addr:full":"Bellamystraat 28 Terneuzen Zeeland 4532 CP",
    "addr:housenumber":"28",
    "addr:postcode":"4532 cp",
    "addr:street":"Bellamystraat",
    "iso:country":"NL",
    "sg:address":"Bellamystraat 28",
    "sg:city":"Terneuzen",
    "sg:orig_category":"Begrafenisondernemers",
    "sg:phone":"+31 115 615 400",
    "sg:postcode":"4532 CP",
    "sg:province":"Zeeland",
    "wof:name":"Crematorium Terneuzen Bv",
    "wof:placetype":"venue"
},
  "geometry": {"coordinates":[3.842822,51.325993],"type":"Point"}
}