{
  "type": "Feature",
  "properties": {
    "iso:country":"NL",
    "sg:address":"Nyverheidswg 1",
    "sg:city":"Harmelen",
    "sg:orig_category":"Loodgieters",
    "sg:phone":"+31 348 443 422",
    "sg:postcode":"3481 MA",
    "sg:province":"Utrecht",
    "wof:name":"Spruit Harmelen",
    "wof:placetype":"venue"
},
  "geometry": {"coordinates":[4.945248,52.100697],"type":"Point"}
}