{
  "type": "Feature",
  "properties": {
    "addr:full":"Lindtstr 14 Rotterdam Zuid-Holland 3073 SH",
    "addr:housenumber":"14",
    "addr:postcode":"3073 sh",
    "addr:street":"Lindtstr",
    "iso:country":"NL",
    "sg:address":"Lindtstr 14",
    "sg:city":"Rotterdam",
    "sg:orig_category":"Onderhoudswerken",
    "sg:phone":"+31 6 15083926",
    "sg:postcode":"3073 SH",
    "sg:province":"Zuid-Holland",
    "wof:name":"Oudeland",
    "wof:placetype":"venue"
},
  "geometry": {"coordinates":[4.505928,51.893883],"type":"Point"}
}