{
  "type": "Feature",
  "properties": {
    "addr:full":"Sparrenln 6 Baarn Utrecht 3742 WG",
    "addr:housenumber":"6",
    "addr:postcode":"3742 wg",
    "addr:street":"Sparrenln",
    "iso:country":"NL",
    "sg:address":"Sparrenln 6",
    "sg:city":"Baarn",
    "sg:orig_category":"Orgels",
    "sg:phone":"+31 35 541 1109",
    "sg:postcode":"3742 WG",
    "sg:province":"Utrecht",
    "sg:website":"http://www.elrecom.nl",
    "wof:name":"Elrecom Muziek",
    "wof:placetype":"venue"
},
  "geometry": {"coordinates":[5.2942080498,52.207157135],"type":"Point"}
}