{
  "type": "Feature",
  "properties": {
    "iso:country":"NL",
    "sg:address":"Kleis 117",
    "sg:city":"Uitgeest",
    "sg:orig_category":"Adviesbureaus Bedrijfsorganisatie",
    "sg:phone":"+31 251 318 155",
    "sg:postcode":"1911 ME",
    "sg:province":"Noord-Holland",
    "wof:name":"Nebu Sales",
    "wof:placetype":"venue"
},
  "geometry": {"coordinates":[4.700765,52.515732],"type":"Point"}
}