{
  "type": "Feature",
  "properties": {
    "iso:country":"NL",
    "sg:address":"Hooigr 98A",
    "sg:city":"Leiden",
    "sg:orig_category":"Psychologen",
    "sg:phone":"+31 71 514 6789",
    "sg:postcode":"2312 KX",
    "sg:province":"South Holland",
    "wof:name":"Verkooijen, Drs Jan",
    "wof:placetype":"venue"
},
  "geometry": {"coordinates":[4.496606,52.159794],"type":"Point"}
}