{
  "type": "Feature",
  "properties": {
    "addr:full":"Ryswykstr 183 Amsterdam Noord-Holland 1062 EV",
    "addr:housenumber":"183",
    "iso:country":"NL",
    "sg:address":"Ryswykstr 183",
    "sg:city":"Amsterdam",
    "sg:orig_category":"Mode-Artikelen Dames En Heren",
    "sg:phone":"+31 20 669 7238",
    "sg:postcode":"1062 EV",
    "sg:province":"Noord-Holland",
    "wof:name":"Br\u00fctek",
    "wof:placetype":"venue"
},
  "geometry": {"coordinates":[4.83975,52.351082],"type":"Point"}
}