{
  "type": "Feature",
  "properties": {
    "addr:full":"Schiedamsedijk 77 Vlaardingen Zuid-Holland 3134 KK",
    "addr:housenumber":"77",
    "addr:postcode":"3134 kk",
    "addr:street":"Schiedamsedijk",
    "iso:country":"NL",
    "sg:address":"Schiedamsedijk 77",
    "sg:city":"Vlaardingen",
    "sg:orig_category":"Gebouwenafwerking, Renovaties And Reiniging",
    "sg:phone":"+31 10 470 4999",
    "sg:postcode":"3134 KK",
    "sg:province":"Zuid-Holland",
    "wof:name":"J. Klarenbeek Bv",
    "wof:placetype":"venue"
},
  "geometry": {"coordinates":[4.369267,51.90398],"type":"Point"}
}