{
  "type": "Feature",
  "properties": {
    "iso:country":"NL",
    "sg:address":"Zwaluwstr 7",
    "sg:city":"Badhoevedorp",
    "sg:classifiers":[
        {
            "category":"Shopping",
            "subcategory":"Gifts & Souvenirs",
            "type":"Retail Goods"
        }
    ],
    "sg:phone":"+31 20 659 4421",
    "sg:postcode":"1171 SM",
    "sg:province":"North Holland",
    "sg:tags":[
        "wens-",
        "en",
        "prentbriefkaarten"
    ],
    "wof:name":"Kaartenwinkeltje, Het",
    "wof:placetype":"venue"
},
  "geometry": {"coordinates":[4.7900371552,52.3381996155],"type":"Point"}
}