{
  "type": "Feature",
  "properties": {
    "addr:full":"Dr Molewaterpln 50 Rotterdam South Holland 3015 GE",
    "addr:housenumber":"50",
    "addr:postcode":"3015",
    "iso:country":"NL",
    "sg:address":"Dr Molewaterpln 50",
    "sg:city":"Rotterdam",
    "sg:orig_category":"Verenigingen En Stichtingen",
    "sg:phone":"+31 10 408 7707",
    "sg:postcode":"3015 GE",
    "sg:province":"South Holland",
    "wof:name":"Mfvr Medische Faculteits Ver Rotterdam",
    "wof:placetype":"venue"
},
  "geometry": {"coordinates":[4.468492,51.910751],"type":"Point"}
}