{
  "type": "Feature",
  "properties": {
    "addr:full":"Hillevliet 118A Rotterdam Zuid-Holland 3074 KD",
    "addr:housenumber":"118a",
    "addr:postcode":"3074 kd",
    "addr:street":"Hillevliet",
    "iso:country":"NL",
    "sg:address":"Hillevliet 118A",
    "sg:city":"Rotterdam",
    "sg:orig_category":"Onderzoekbureaus",
    "sg:phone":"+31 10 486 0112",
    "sg:postcode":"3074 KD",
    "sg:province":"Zuid-Holland",
    "wof:name":"Bridge Commercial Counselor",
    "wof:placetype":"venue"
},
  "geometry": {"coordinates":[4.507882,51.894859],"type":"Point"}
}