{
  "type": "Feature",
  "properties": {
    "addr:full":"Zomerhofstr 60 Rotterdam South Holland 3032 CM",
    "addr:housenumber":"60",
    "addr:postcode":"3032 cm",
    "addr:street":"Zomerhofstr",
    "iso:country":"NL",
    "sg:address":"Zomerhofstr 60",
    "sg:city":"Rotterdam",
    "sg:orig_category":"Offsetdrukkerijen",
    "sg:phone":"+31 10 467 3033",
    "sg:postcode":"3032 CM",
    "sg:province":"South Holland",
    "sg:website":"http://www.drukkerij-dekruijff.nl",
    "wof:name":"Kruijff, Drukkerij De",
    "wof:placetype":"venue"
},
  "geometry": {"coordinates":[4.479245,51.92889],"type":"Point"}
}