{
  "type": "Feature",
  "properties": {
    "addr:full":"Kooikerweg 15 Rotterdam South Holland 3069 WP",
    "addr:housenumber":"15",
    "addr:postcode":"3069 wp",
    "addr:street":"Kooikerweg",
    "iso:country":"NL",
    "sg:address":"Kooikerweg 15",
    "sg:city":"Rotterdam",
    "sg:orig_category":"Kinderopvang Behalve Thuis",
    "sg:phone":"+31 10 420 3162",
    "sg:postcode":"3069 WP",
    "sg:province":"South Holland",
    "wof:name":"Kinderdagverblijf Pino",
    "wof:placetype":"venue"
},
  "geometry": {"coordinates":[4.571065,51.966194],"type":"Point"}
}