{
  "type": "Feature",
  "properties": {
    "addr:full":"Donizettistraat 55 Capelle A/D Ijssel Zuid-Holland 2901 KD",
    "addr:housenumber":"55;a / d",
    "addr:postcode":"2901 kd",
    "addr:street":"Donizettistraat",
    "iso:country":"NL",
    "sg:address":"Donizettistraat 55",
    "sg:city":"Capelle A/D Ijssel",
    "sg:orig_category":"Boekhouders",
    "sg:phone":"+31 10 202 2696",
    "sg:postcode":"2901 KD",
    "sg:province":"Zuid-Holland",
    "wof:name":"G.T. Bergshoeff & R.F. Breda",
    "wof:placetype":"venue"
},
  "geometry": {"coordinates":[4.571969,51.919094],"type":"Point"}
}