{
  "type": "Feature",
  "properties": {
    "addr:full":"Kerkstraat Zuid 6-8 Helmond North Brabant 5701 PM",
    "addr:housenumber":"6-8",
    "addr:postcode":"5701 pm",
    "addr:street":"Kerkstraat Zuid",
    "iso:country":"NL",
    "sg:address":"Kerkstraat Zuid 6-8",
    "sg:city":"Helmond",
    "sg:orig_category":"Meubelzaken, Woning- And Keukeninrichting",
    "sg:phone":"+31 492 522 681",
    "sg:postcode":"5701 PM",
    "sg:province":"North Brabant",
    "wof:name":"Roelofs",
    "wof:placetype":"venue"
},
  "geometry": {"coordinates":[5.6559882164,51.4774551392],"type":"Point"}
}