{
  "type": "Feature",
  "properties": {
    "iso:country":"NL",
    "sg:address":"Ryksstrwg 213",
    "sg:city":"Beek Ubbergen",
    "sg:orig_category":"Boeken Antiquarische En Gebruikte",
    "sg:phone":"+31 24 324 0054",
    "sg:postcode":"6573 CS",
    "sg:province":"Gelderland",
    "wof:name":"Supplement",
    "wof:placetype":"venue"
},
  "geometry": {"coordinates":[5.92779,51.831219],"type":"Point"}
}