{
  "type": "Feature",
  "properties": {
    "addr:full":"Hendrik Soeteboomstraat 5 Amsterdam Noord-Holland 1035  N",
    "addr:housenumber":"5;1035",
    "addr:street":"Hendrik Soeteboomstraat;N",
    "iso:country":"NL",
    "sg:address":"Hendrik Soeteboomstraat 5",
    "sg:city":"Amsterdam",
    "sg:orig_category":"Loodgieterswerk, Verwarming And Sanitaire Installaties",
    "sg:phone":"+31 20 493 3192",
    "sg:postcode":"1035  N",
    "sg:province":"Noord-Holland",
    "wof:name":"Loodgietersbedrijf Sanou",
    "wof:placetype":"venue"
},
  "geometry": {"coordinates":[4.895688,52.417877],"type":"Point"}
}