{
  "type": "Feature",
  "properties": {
    "addr:full":"Postbus 14 De Wijk Drenthe 7957 ZG",
    "addr:housenumber":"14",
    "addr:postcode":"7957 zg",
    "addr:street":"Postbus",
    "iso:country":"NL",
    "sg:address":"Postbus 14",
    "sg:city":"De Wijk",
    "sg:orig_category":"Organisaties And Verenigingen",
    "sg:phone":"+31 522 443 252",
    "sg:postcode":"7957 ZG",
    "sg:province":"Drenthe",
    "wof:name":"Dutch Landrover Register",
    "wof:placetype":"venue"
},
  "geometry": {"coordinates":[8.5479898453,47.1645584106],"type":"Point"}
}