{
  "type": "Feature",
  "properties": {
    "addr:full":"Botlek 56 Zwolle Overijssel 8032 CG",
    "addr:housenumber":"56",
    "addr:postcode":"8032 cg",
    "addr:street":"Botlek",
    "iso:country":"NL",
    "sg:address":"Botlek 56",
    "sg:city":"Zwolle",
    "sg:orig_category":"Scholen Voor Basisonderwijs",
    "sg:phone":"+31 38 453 3619",
    "sg:postcode":"8032 CG",
    "sg:province":"Overijssel",
    "wof:name":"Stroomdal Chr, Het",
    "wof:placetype":"venue"
},
  "geometry": {"coordinates":[6.107976,52.528362],"type":"Point"}
}