{
  "type": "Feature",
  "properties": {
    "addr:full":"Alphensebaan 2 Chaam Noord-Brabant 4861 RA",
    "addr:housenumber":"2",
    "addr:postcode":"4861 ra",
    "addr:street":"Alphensebaan",
    "iso:country":"NL",
    "sg:address":"Alphensebaan 2",
    "sg:city":"Chaam",
    "sg:orig_category":"Bloemen En Planten",
    "sg:phone":"+31 161 492 000",
    "sg:postcode":"4861 RA",
    "sg:province":"Noord-Brabant",
    "wof:name":"Fleurs 2000",
    "wof:placetype":"venue"
},
  "geometry": {"coordinates":[4.871675,51.500328],"type":"Point"}
}