{
  "type": "Feature",
  "properties": {
    "iso:country":"NL",
    "sg:address":"Winkelsestr 33",
    "sg:city":"Biezenmortel",
    "sg:orig_category":"Bloemen En Planten - Groothandel",
    "sg:phone":"+31 13 511 6150",
    "sg:postcode":"5074 ND",
    "sg:province":"Noord-Brabant",
    "wof:name":"Roessel, W Van",
    "wof:placetype":"venue"
},
  "geometry": {"coordinates":[-100.30171199999999,47.467731],"type":"Point"}
}