{
  "type": "Feature",
  "properties": {
    "addr:full":"De Aanstee 19 Diessen Noord-Brabant 5087 LK",
    "addr:housenumber":"19",
    "addr:postcode":"5087 lk",
    "addr:street":"De Aanstee",
    "iso:country":"NL",
    "sg:address":"De Aanstee 19",
    "sg:city":"Diessen",
    "sg:orig_category":"Dierenvoeder - Fabrieken",
    "sg:phone":"+31 13 504 3155",
    "sg:postcode":"5087 LK",
    "sg:province":"Noord-Brabant",
    "wof:name":"Jan Beekmans",
    "wof:placetype":"venue"
},
  "geometry": {"coordinates":[5.174791,51.469791],"type":"Point"}
}