{
  "type": "Feature",
  "properties": {
    "addr:full":"Industriewg 7 Pynacker South Holland 2641 RM",
    "addr:housenumber":"7",
    "addr:postcode":"2641 rm",
    "addr:street":"Industriewg;Pynacker South",
    "iso:country":"NL",
    "sg:address":"Industriewg 7",
    "sg:city":"Pynacker",
    "sg:orig_category":"Postzegels",
    "sg:phone":"+31 15 369 9010",
    "sg:postcode":"2641 RM",
    "sg:province":"South Holland",
    "wof:name":"Klomp",
    "wof:placetype":"venue"
},
  "geometry": {"coordinates":[4.440878,52.01371],"type":"Point"}
}