{
  "type": "Feature",
  "properties": {
    "addr:full":"Mozartstr 102 Almelo NL.08 7604 GS",
    "addr:housenumber":"102;nl.08",
    "addr:postcode":"7604 gs",
    "iso:country":"NL",
    "sg:address":"Mozartstr 102",
    "sg:city":"Almelo",
    "sg:orig_category":"Meubelstoffering",
    "sg:phone":"+31 546 817 409",
    "sg:postcode":"7604 GS",
    "sg:province":"NL.08",
    "wof:name":"Steenbergen Meubelstoffeerder, H",
    "wof:placetype":"venue"
},
  "geometry": {"coordinates":[6.634766,52.356525],"type":"Point"}
}