{
  "type": "Feature",
  "properties": {
    "addr:full":"Lovense Kanaaldk 1A Tilburg Noord-Brabant 5046 AV",
    "addr:housenumber":"1a",
    "addr:postcode":"5046 av",
    "addr:street":"Kanaaldk",
    "iso:country":"NL",
    "sg:address":"Lovense Kanaaldk 1A",
    "sg:city":"Tilburg",
    "sg:orig_category":"Oldtimers",
    "sg:phone":"+31 13 542 5466",
    "sg:postcode":"5046 AV",
    "sg:province":"Noord-Brabant",
    "wof:name":"O'Prinsen, Cees",
    "wof:placetype":"venue"
},
  "geometry": {"coordinates":[5.085152,51.578548],"type":"Point"}
}