{
  "type": "Feature",
  "properties": {
    "addr:full":"Dorpstraat 152 Luyksgestel Noord-Brabant 5575 AH",
    "addr:housenumber":"152",
    "addr:postcode":"5575 ah",
    "addr:street":"Dorpstraat",
    "iso:country":"NL",
    "sg:address":"Dorpstraat 152",
    "sg:city":"Luyksgestel",
    "sg:orig_category":"Metaalbekleding And -Behandeling",
    "sg:phone":"+31 497 542 276",
    "sg:postcode":"5575 AH",
    "sg:province":"Noord-Brabant",
    "wof:name":"Houbraken",
    "wof:placetype":"venue"
},
  "geometry": {"coordinates":[5.314527,51.284397],"type":"Point"}
}