{
  "type": "Feature",
  "properties": {
    "addr:full":"J Provostln 79 Bilthoven Utrecht 3723 RC",
    "addr:housenumber":"79",
    "addr:postcode":"3723 rc",
    "iso:country":"NL",
    "sg:address":"J Provostln 79",
    "sg:city":"Bilthoven",
    "sg:orig_category":"Kantoorinstallaties",
    "sg:phone":"+31 30 228 8090",
    "sg:postcode":"3723 RC",
    "sg:province":"Utrecht",
    "wof:name":"Ergo-2000",
    "wof:placetype":"venue"
},
  "geometry": {"coordinates":[5.1957650185,52.1313667297],"type":"Point"}
}