{
  "type": "Feature",
  "properties": {
    "iso:country":"NL",
    "sg:address":"Dorpsstraat 22",
    "sg:city":"Kloosterhaar",
    "sg:orig_category":"Banken And Kredietinstellingen",
    "sg:phone":"+31 523 241 250",
    "sg:postcode":"7694 AC",
    "sg:province":"Overijssel",
    "wof:name":"Rabobank",
    "wof:placetype":"venue"
},
  "geometry": {"coordinates":[6.667983,52.494839],"type":"Point"}
}