{
  "type": "Feature",
  "properties": {
    "addr:full":"Hoevelakerveenweg 8 Hoevelaken Gelderland 3871 KK",
    "addr:housenumber":"8",
    "addr:postcode":"3871 kk",
    "addr:street":"Hoevelakerveenweg;Gelderland",
    "iso:country":"NL",
    "sg:address":"Hoevelakerveenweg 8",
    "sg:city":"Hoevelaken",
    "sg:orig_category":"Verzekeringen",
    "sg:phone":"+31 33 257 1295",
    "sg:postcode":"3871 KK",
    "sg:province":"Gelderland",
    "wof:name":"Collignon & Partners",
    "wof:placetype":"venue"
},
  "geometry": {"coordinates":[5.457162,52.184895],"type":"Point"}
}