{
  "type": "Feature",
  "properties": {
    "iso:country":"NL",
    "sg:address":"Melkmarkt 1",
    "sg:city":"Zwolle",
    "sg:orig_category":"Banken And Kredietinstellingen",
    "sg:phone":"+31 38 428 5185",
    "sg:postcode":"8011 MA",
    "sg:province":"NL.08",
    "wof:name":"Abn Amro",
    "wof:placetype":"venue"
},
  "geometry": {"coordinates":[6.09235,52.512314],"type":"Point"}
}