{
  "type": "Feature",
  "properties": {
    "addr:full":"Bizetstr 3 Almelo Overijssel 7604 HT",
    "addr:housenumber":"3",
    "addr:postcode":"7604 ht",
    "addr:street":"Bizetstr",
    "iso:country":"NL",
    "sg:address":"Bizetstr 3",
    "sg:city":"Almelo",
    "sg:orig_category":"Grafisch Ontwerpers",
    "sg:phone":"+31 546 813 283",
    "sg:postcode":"7604 HT",
    "sg:province":"Overijssel",
    "wof:name":"Antara, D'",
    "wof:placetype":"venue"
},
  "geometry": {"coordinates":[6.636411,52.361935],"type":"Point"}
}