{
  "type": "Feature",
  "properties": {
    "addr:full":"Marktstraat 14 Sneek Friesland 8601 CV",
    "addr:housenumber":"14",
    "addr:postcode":"8601 cv",
    "addr:street":"Marktstraat",
    "iso:country":"NL",
    "sg:address":"Marktstraat 14",
    "sg:city":"Sneek",
    "sg:orig_category":"Werving And Selectie Van Tijdelijk Personeel And Uitzendkantoren",
    "sg:phone":"+31 515 419 400",
    "sg:postcode":"8601 CV",
    "sg:province":"Friesland",
    "wof:name":"Uitzendbureau Start",
    "wof:placetype":"venue"
},
  "geometry": {"coordinates":[5.6591310501,53.0323181152],"type":"Point"}
}