{
  "type": "Feature",
  "properties": {
    "iso:country":"NL",
    "sg:address":"Langsstraat 7",
    "sg:city":"Rijswijk Gld",
    "sg:orig_category":"Juridische Dienstverlening",
    "sg:phone":"+31 345 558 231",
    "sg:postcode":"4023 AE",
    "sg:province":"Gelderland",
    "wof:name":"Smits Bouw- En Interieurprojekten Bv",
    "wof:placetype":"venue"
},
  "geometry": {"coordinates":[5.360697,51.95612],"type":"Point"}
}