{
  "type": "Feature",
  "properties": {
    "addr:full":"Geminisngl 18 Assen Provincie Drenthe 9405 RA",
    "addr:housenumber":"18",
    "addr:postcode":"9405 ra",
    "addr:street":"Geminisngl;Provincie Drenthe",
    "iso:country":"NL",
    "sg:address":"Geminisngl 18",
    "sg:city":"Assen",
    "sg:orig_category":"Kappers",
    "sg:phone":"+31 6 12055851",
    "sg:postcode":"9405 RA",
    "sg:province":"Provincie Drenthe",
    "wof:name":"Zwanet",
    "wof:placetype":"venue"
},
  "geometry": {"coordinates":[6.517757,52.981911],"type":"Point"}
}