{
  "type": "Feature",
  "properties": {
    "addr:full":"H W Iordenswg 75 Twello Gelderland 7391 KD",
    "addr:housenumber":"75",
    "addr:postcode":"7391 kd",
    "addr:street":"H W Iordenswg;Gelderland",
    "iso:country":"NL",
    "sg:address":"H W Iordenswg 75",
    "sg:city":"Twello",
    "sg:orig_category":"Loodgieters",
    "sg:phone":"+31 571 274 802",
    "sg:postcode":"7391 KD",
    "sg:province":"Gelderland",
    "wof:name":"Hutten",
    "wof:placetype":"venue"
},
  "geometry": {"coordinates":[6.106505,52.238346],"type":"Point"}
}