{
  "type": "Feature",
  "properties": {
    "iso:country":"NL",
    "sg:address":"Reeshofdk 27",
    "sg:city":"Tilburg",
    "sg:classifiers":[
        {
            "category":"Professional",
            "subcategory":"Accounting & Tax Preparation",
            "type":"Services"
        }
    ],
    "sg:phone":"+31 13 570 0762",
    "sg:postcode":"5044 VB",
    "sg:province":"North Brabant",
    "sg:tags":[
        "accountant",
        "en",
        "-kantoren",
        "register-"
    ],
    "wof:name":"Matabadal Bv",
    "wof:placetype":"venue"
},
  "geometry": {"coordinates":[5.02033,51.572926],"type":"Point"}
}