{
  "type": "Feature",
  "properties": {
    "addr:full":"Rengersln 2 Leeuwarden Friesland 8917 DD",
    "addr:housenumber":"2",
    "addr:postcode":"8917 dd",
    "addr:street":"Rengersln",
    "iso:country":"NL",
    "sg:address":"Rengersln 2",
    "sg:city":"Leeuwarden",
    "sg:orig_category":"Begrafenisverzorging",
    "sg:phone":"+31 58 212 3990",
    "sg:postcode":"8917 DD",
    "sg:province":"Friesland",
    "wof:name":"Nuva",
    "wof:placetype":"venue"
},
  "geometry": {"coordinates":[5.79257,53.197319],"type":"Point"}
}