{
  "type": "Feature",
  "properties": {
    "addr:full":"Spinozawg 195 Rotterdam South Holland 3076 EL",
    "addr:housenumber":"195",
    "addr:postcode":"3076 el",
    "iso:country":"NL",
    "sg:address":"Spinozawg 195",
    "sg:city":"Rotterdam",
    "sg:orig_category":"Bloemen En Planten",
    "sg:phone":"+31 10 419 5108",
    "sg:postcode":"3076 EL",
    "sg:province":"South Holland",
    "wof:name":"Flower Drive-Inn",
    "wof:placetype":"venue"
},
  "geometry": {"coordinates":[4.520482,51.877254],"type":"Point"}
}