{
  "type": "Feature",
  "properties": {
    "addr:full":"Bredasewg 5 Baarle Nassau North Brabant 5111 GC",
    "addr:housenumber":"5",
    "addr:postcode":"5111 gc",
    "addr:street":"Bredasewg",
    "iso:country":"NL",
    "sg:address":"Bredasewg 5",
    "sg:city":"Baarle Nassau",
    "sg:orig_category":"Midgetgolf",
    "sg:phone":"+31 13 507 8282",
    "sg:postcode":"5111 GC",
    "sg:province":"North Brabant",
    "wof:name":"Bosrand, De",
    "wof:placetype":"venue"
},
  "geometry": {"coordinates":[4.915194,51.452923],"type":"Point"}
}