{
  "type": "Feature",
  "properties": {
    "iso:country":"NL",
    "sg:address":"Arnhemsebovenweg 293",
    "sg:city":"Driebergen-Rijsenburg",
    "sg:classifiers":[
        {
            "category":"Professional",
            "subcategory":"Accounting & Tax Preparation",
            "type":"Services"
        }
    ],
    "sg:phone":"+31 343 516 921",
    "sg:postcode":"3971 MJ",
    "sg:province":"Utrecht",
    "sg:tags":[
        "accountant"
    ],
    "wof:name":"Accountantskantoor Drs. F.G. Van Der Werf",
    "wof:placetype":"venue"
},
  "geometry": {"coordinates":[5.301938,52.055161],"type":"Point"}
}