{
  "type": "Feature",
  "properties": {
    "addr:full":"Daltonstr 17A Dordrecht Zuid-Holland 3316 GD",
    "addr:housenumber":"17a",
    "addr:postcode":"3316 gd",
    "addr:street":"Daltonstr",
    "iso:country":"NL",
    "sg:address":"Daltonstr 17A",
    "sg:city":"Dordrecht",
    "sg:orig_category":"Parketvloeren",
    "sg:phone":"+31 78 631 6646",
    "sg:postcode":"3316 GD",
    "sg:province":"Zuid-Holland",
    "wof:name":"Ab & Partn",
    "wof:placetype":"venue"
},
  "geometry": {"coordinates":[4.637843,51.77787],"type":"Point"}
}