{
  "type": "Feature",
  "properties": {
    "iso:country":"NL",
    "sg:address":"Mertensstr 106",
    "sg:city":"Rotterdam",
    "sg:classifiers":[
        {
            "category":"Personal",
            "subcategory":"Nail Salon",
            "type":"Services"
        }
    ],
    "sg:phone":"+31 10 420 0687",
    "sg:postcode":"3067 CM",
    "sg:province":"Zuid-Holland",
    "sg:tags":[
        "pedicure"
    ],
    "wof:name":"Pijpe-Van Den Bosch, M C J",
    "wof:placetype":"venue"
},
  "geometry": {"coordinates":[4.553266,51.945141],"type":"Point"}
}