{
  "type": "Feature",
  "properties": {
    "addr:full":"Oudelandsedijk 4 Abbenbroek Zuid-Holland 3216 AP",
    "addr:housenumber":"4",
    "addr:postcode":"3216 ap",
    "addr:street":"Oudelandsedijk",
    "iso:country":"NL",
    "sg:address":"Oudelandsedijk 4",
    "sg:city":"Abbenbroek",
    "sg:orig_category":"Diverse Bedrijfsinstallaties Gh",
    "sg:phone":"+31 181 661 686",
    "sg:postcode":"3216 AP",
    "sg:province":"Zuid-Holland",
    "wof:name":"L T Van Rooijen Machineservice",
    "wof:placetype":"venue"
},
  "geometry": {"coordinates":[4.244659,51.842579],"type":"Point"}
}