{
  "type": "Feature",
  "properties": {
    "addr:full":"Groenmarkt 25 Den Haag South Holland 2513 AL",
    "addr:housenumber":"25",
    "addr:postcode":"2513 al",
    "addr:street":"Groenmarkt",
    "iso:country":"NL",
    "sg:address":"Groenmarkt 25",
    "sg:city":"Den Haag",
    "sg:orig_category":"Verlichting And Huishoudartikelen",
    "sg:phone":"+31 70 365 7748",
    "sg:postcode":"2513 AL",
    "sg:province":"South Holland",
    "wof:name":"Zwilling J.A. Henckels",
    "wof:placetype":"venue"
},
  "geometry": {"coordinates":[4.298437,52.025181],"type":"Point"}
}