{
  "type": "Feature",
  "properties": {
    "addr:full":"Delftechpk 25 Delft Zuid-Holland 2628 XJ",
    "addr:housenumber":"25",
    "addr:postcode":"2628 xj",
    "addr:street":"Delftechpk",
    "iso:country":"NL",
    "sg:address":"Delftechpk 25",
    "sg:city":"Delft",
    "sg:orig_category":"Afzuiginstallaties",
    "sg:phone":"+31 15 257 2796",
    "sg:postcode":"2628 XJ",
    "sg:province":"Zuid-Holland",
    "sg:website":"http://www.joa.nl",
    "wof:name":"Joa",
    "wof:placetype":"venue"
},
  "geometry": {"coordinates":[4.383785,51.997303],"type":"Point"}
}