{
  "type": "Feature",
  "properties": {
    "addr:full":"S Groeneweg Erf 372 Dordrecht Zuid-Holland 3315 XK",
    "addr:housenumber":"372",
    "addr:postcode":"3315 xk",
    "addr:street":"S Groeneweg Erf",
    "iso:country":"NL",
    "sg:address":"S Groeneweg Erf 372",
    "sg:city":"Dordrecht",
    "sg:orig_category":"Micrografie / Microfilm",
    "sg:phone":"+31 78 621 4720",
    "sg:postcode":"3315 XK",
    "sg:province":"Zuid-Holland",
    "wof:name":"Abdis",
    "wof:placetype":"venue"
},
  "geometry": {"coordinates":[4.718112,51.799736],"type":"Point"}
}