{
  "type": "Feature",
  "properties": {
    "addr:full":"Oude Binnenwg 89A Rotterdam Zuid-Holland 3012 JA",
    "addr:housenumber":"89a",
    "addr:postcode":"3012 ja",
    "addr:street":"Oude Binnenwg",
    "iso:country":"NL",
    "sg:address":"Oude Binnenwg 89A",
    "sg:city":"Rotterdam",
    "sg:orig_category":"Bloemen En Planten",
    "sg:phone":"+31 10 413 2608",
    "sg:postcode":"3012 JA",
    "sg:province":"Zuid-Holland",
    "wof:name":"Hoogerwerf",
    "wof:placetype":"venue"
},
  "geometry": {"coordinates":[4.475495,51.917782],"type":"Point"}
}