{
  "type": "Feature",
  "properties": {
    "iso:country":"NL",
    "sg:address":"Oudeweg 92",
    "sg:city":"Siddeburen",
    "sg:orig_category":"Kappers",
    "sg:phone":"+31 598 431 238",
    "sg:postcode":"9628 CG",
    "sg:province":"Groningen",
    "wof:name":"P Tuinema",
    "wof:placetype":"venue"
},
  "geometry": {"coordinates":[6.869438,53.249641],"type":"Point"}
}