{
  "type": "Feature",
  "properties": {
    "iso:country":"NL",
    "sg:address":"Tielerwaard 45",
    "sg:city":"Rotterdam",
    "sg:orig_category":"Schoonheidsinstituten",
    "sg:phone":"+31 10 482 6636",
    "sg:postcode":"3079 PV",
    "sg:province":"South Holland",
    "wof:name":"Rijswijk, Y Van",
    "wof:placetype":"venue"
},
  "geometry": {"coordinates":[4.54237,51.885151],"type":"Point"}
}