{
  "type": "Feature",
  "properties": {
    "iso:country":"NL",
    "sg:address":"Windmolenven 11",
    "sg:city":"Haelen",
    "sg:orig_category":"Ventilatiesystemen",
    "sg:phone":"+31 475 593 397",
    "sg:postcode":"6081 PJ",
    "sg:province":"Limburg",
    "wof:name":"Rob\u00e9",
    "wof:placetype":"venue"
},
  "geometry": {"coordinates":[5.956641,51.222713],"type":"Point"}
}