{
  "type": "Feature",
  "properties": {
    "addr:full":"Klipper 79 Veenendaal Utrecht 3904 SL",
    "addr:housenumber":"79",
    "addr:postcode":"3904 sl",
    "addr:street":"Klipper",
    "iso:country":"NL",
    "sg:address":"Klipper 79",
    "sg:city":"Veenendaal",
    "sg:orig_category":"Grafisch Ontwerpers",
    "sg:phone":"+31 318 502 366",
    "sg:postcode":"3904 SL",
    "sg:province":"Utrecht",
    "wof:name":"Kaya Design Veenendaal",
    "wof:placetype":"venue"
},
  "geometry": {"coordinates":[5.534204,52.025349],"type":"Point"}
}