{
  "type": "Feature",
  "properties": {
    "addr:full":"Kerkpolderwg 1 Delft South Holland 2625 EB",
    "addr:housenumber":"1",
    "addr:postcode":"2625 eb",
    "addr:street":"Kerkpolderwg",
    "iso:country":"NL",
    "sg:address":"Kerkpolderwg 1",
    "sg:city":"Delft",
    "sg:orig_category":"Sportverenigingen En Ontspannings- Verenigingen",
    "sg:phone":"+31 15 256 7907",
    "sg:postcode":"2625 EB",
    "sg:province":"South Holland",
    "wof:name":"Dzv Zwemver",
    "wof:placetype":"venue"
},
  "geometry": {"coordinates":[4.335315,51.984428],"type":"Point"}
}