{
  "type": "Feature",
  "properties": {
    "iso:country":"NL",
    "sg:address":"Tiendweg 4",
    "sg:city":"Naaldwijk",
    "sg:classifiers":[
        {
            "category":"Professional",
            "subcategory":"Accounting & Tax Preparation",
            "type":"Services"
        }
    ],
    "sg:phone":"+31 174 637 100",
    "sg:postcode":"2671 SB",
    "sg:province":"Zuid-Holland",
    "sg:tags":[
        "accountant"
    ],
    "wof:name":"Ltb Adviseurs En` Accountants Bv",
    "wof:placetype":"venue"
},
  "geometry": {"coordinates":[4.220598,51.989613],"type":"Point"}
}