{
  "type": "Feature",
  "properties": {
    "addr:full":"Haverkamp 3 Beek En Donk Noord-Brabant 5741 PN",
    "addr:housenumber":"3",
    "addr:postcode":"5741 pn",
    "addr:street":"Haverkamp",
    "iso:country":"NL",
    "sg:address":"Haverkamp 3",
    "sg:city":"Beek En Donk",
    "sg:orig_category":"Meubelmakerijen",
    "sg:phone":"+31 492 465 640",
    "sg:postcode":"5741 PN",
    "sg:province":"Noord-Brabant",
    "wof:name":"Hurk, Dirk-Jan Van Den",
    "wof:placetype":"venue"
},
  "geometry": {"coordinates":[5.63792,51.546947],"type":"Point"}
}