{
  "type": "Feature",
  "properties": {
    "addr:full":"Klokstg 103 Utrecht Utrecht 3512 EZ",
    "addr:housenumber":"103",
    "addr:postcode":"3512 ez",
    "iso:country":"NL",
    "sg:address":"Klokstg 103",
    "sg:city":"Utrecht",
    "sg:orig_category":"Vertaalbureaus",
    "sg:phone":"+31 30 231 4116",
    "sg:postcode":"3512 EZ",
    "sg:province":"Utrecht",
    "wof:name":"Bochove, Drs M M H Van",
    "wof:placetype":"venue"
},
  "geometry": {"coordinates":[5.125316,52.094593],"type":"Point"}
}