{
  "type": "Feature",
  "properties": {
    "iso:country":"NL",
    "sg:address":"Nw Ryn 22",
    "sg:city":"Leiden",
    "sg:orig_category":"Kopieerservice",
    "sg:phone":"+31 71 512 6706",
    "sg:postcode":"2312 JC",
    "sg:province":"Zuid-Holland",
    "wof:name":"Lifo",
    "wof:placetype":"venue"
},
  "geometry": {"coordinates":[4.49463,52.154572],"type":"Point"}
}