{
  "type": "Feature",
  "properties": {
    "addr:full":"Ungerplein 2 Rotterdam Zuid-Holland 3033 BR",
    "addr:housenumber":"2",
    "addr:postcode":"3033 br",
    "addr:street":"Ungerplein",
    "iso:country":"NL",
    "sg:address":"Ungerplein 2",
    "sg:city":"Rotterdam",
    "sg:orig_category":"Makelaars In Onroerend Goed",
    "sg:phone":"+31 10 466 1000",
    "sg:postcode":"3033 BR",
    "sg:province":"Zuid-Holland",
    "wof:name":"Ipm Vastgoed",
    "wof:placetype":"venue"
},
  "geometry": {"coordinates":[4.471573,51.929523],"type":"Point"}
}