{
  "type": "Feature",
  "properties": {
    "addr:full":"Willem Ii Singel 1 Roermond Limburg 6041 HP",
    "addr:housenumber":"1",
    "addr:postcode":"6041 hp",
    "addr:street":"Willem Ii Singel",
    "iso:country":"NL",
    "sg:address":"Willem Ii Singel 1",
    "sg:city":"Roermond",
    "sg:orig_category":"Banken And Kredietinstellingen",
    "sg:phone":"+31 475 396 262",
    "sg:postcode":"6041 HP",
    "sg:province":"Limburg",
    "wof:name":"Ing Bank",
    "wof:placetype":"venue"
},
  "geometry": {"coordinates":[5.992587,51.192036],"type":"Point"}
}