{
  "type": "Feature",
  "properties": {
    "iso:country":"NL",
    "sg:address":"Winkelcentrum 36",
    "sg:city":"Malden",
    "sg:orig_category":"Opticiens",
    "sg:phone":"+31 24 358 2482",
    "sg:postcode":"6581 BW",
    "sg:province":"Gelderland",
    "sg:website":"http://www.optiekhoose.com",
    "wof:name":"Hoose",
    "wof:placetype":"venue"
},
  "geometry": {"coordinates":[5.8532657623,51.7824363708],"type":"Point"}
}