{
  "type": "Feature",
  "properties": {
    "addr:full":"V Weedestr 8 Soest Utrecht 3761 CE",
    "addr:housenumber":"8",
    "addr:postcode":"3761 ce",
    "addr:street":"Weedestr",
    "iso:country":"NL",
    "sg:address":"V Weedestr 8",
    "sg:city":"Soest",
    "sg:orig_category":"Herenkleding",
    "sg:phone":"+31 35 602 3324",
    "sg:postcode":"3761 CE",
    "sg:province":"Utrecht",
    "wof:name":"Hil-Ton",
    "wof:placetype":"venue"
},
  "geometry": {"coordinates":[5.300385,52.184044],"type":"Point"}
}