{
  "type": "Feature",
  "properties": {
    "addr:full":"Saksenhorst 3 Sassenheim South Holland 2171 VN",
    "addr:housenumber":"3",
    "addr:postcode":"2171 vn",
    "addr:street":"Saksenhorst",
    "iso:country":"NL",
    "sg:address":"Saksenhorst 3",
    "sg:city":"Sassenheim",
    "sg:orig_category":"Boekhandels",
    "sg:phone":"+31 252 212 472",
    "sg:postcode":"2171 VN",
    "sg:province":"South Holland",
    "wof:name":"Lokaal Boek",
    "wof:placetype":"venue"
},
  "geometry": {"coordinates":[4.515157,52.226677],"type":"Point"}
}