{
  "type": "Feature",
  "properties": {
    "iso:country":"NL",
    "sg:address":"Veldstraat 30",
    "sg:city":"Zundert",
    "sg:orig_category":"Binnenhuisarchitecten",
    "sg:phone":"+31 76 597 4086",
    "sg:postcode":"4881 BC",
    "sg:province":"Noord-Brabant",
    "wof:name":"Heuvel Interieur Zundert",
    "wof:placetype":"venue"
},
  "geometry": {"coordinates":[4.658274,51.47414],"type":"Point"}
}