{
  "type": "Feature",
  "properties": {
    "addr:full":"Ophoven 28A Roggel Limburg 6088 AD",
    "addr:housenumber":"28a",
    "addr:postcode":"6088 ad",
    "addr:street":"Ophoven",
    "iso:country":"NL",
    "sg:address":"Ophoven 28A",
    "sg:city":"Roggel",
    "sg:orig_category":"Loodgieters",
    "sg:phone":"+31 475 491 559",
    "sg:postcode":"6088 AD",
    "sg:province":"Limburg",
    "wof:name":"Beerens Roggel Bv",
    "wof:placetype":"venue"
},
  "geometry": {"coordinates":[5.94344,51.265469],"type":"Point"}
}