{
  "type": "Feature",
  "properties": {
    "addr:full":"Leliegr 47 Amsterdam Noord-Holland 1016 GT",
    "addr:housenumber":"47",
    "addr:postcode":"1016 gt",
    "addr:street":"Leliegr",
    "iso:country":"NL",
    "sg:address":"Leliegr 47",
    "sg:city":"Amsterdam",
    "sg:orig_category":"Galeries",
    "sg:phone":"+31 20 620 4758",
    "sg:postcode":"1016 GT",
    "sg:province":"Noord-Holland",
    "wof:name":"Expeditie, De",
    "wof:placetype":"venue"
},
  "geometry": {"coordinates":[4.884704,52.375557],"type":"Point"}
}