{
  "type": "Feature",
  "properties": {
    "addr:full":"Veemarkt 100 Amsterdam Noord-Holland 1019 DE",
    "addr:housenumber":"100;1019",
    "addr:postcode":"de",
    "addr:street":"Veemarkt",
    "iso:country":"NL",
    "sg:address":"Veemarkt 100",
    "sg:city":"Amsterdam",
    "sg:orig_category":"Loodgieterswerk, Verwarming And Sanitaire Installaties",
    "sg:phone":"+31 20 668 5725",
    "sg:postcode":"1019 DE",
    "sg:province":"Noord-Holland",
    "wof:name":"A.W.B.O.-Amsterdam",
    "wof:placetype":"venue"
},
  "geometry": {"coordinates":[4.938383,52.367531],"type":"Point"}
}