{
  "type": "Feature",
  "properties": {
    "addr:full":"Hanzestraat 86 Arnhem Gelderland 6826 MP",
    "addr:housenumber":"86",
    "addr:postcode":"6826 mp",
    "addr:street":"Hanzestraat",
    "iso:country":"NL",
    "sg:address":"Hanzestraat 86",
    "sg:city":"Arnhem",
    "sg:classifiers":[
        {
            "category":"Shopping",
            "subcategory":"Gifts & Souvenirs",
            "type":"Retail Goods"
        }
    ],
    "sg:phone":"+31 26 361 2203",
    "sg:postcode":"6826 MP",
    "sg:province":"Gelderland",
    "sg:tags":[
        "geschenken"
    ],
    "wof:name":"Stijl",
    "wof:placetype":"venue"
},
  "geometry": {"coordinates":[5.950915,51.982971],"type":"Point"}
}