{
  "type": "Feature",
  "properties": {
    "addr:full":"J Huizingaln 174A Amsterdam Noord-Holland 1065 JH",
    "addr:housenumber":"174a",
    "addr:postcode":"1065 jh",
    "iso:country":"NL",
    "sg:address":"J Huizingaln 174A",
    "sg:city":"Amsterdam",
    "sg:orig_category":"Bloemen En Planten",
    "sg:phone":"+31 20 615 1701",
    "sg:postcode":"1065 JH",
    "sg:province":"Noord-Holland",
    "wof:name":"Floriade",
    "wof:placetype":"venue"
},
  "geometry": {"coordinates":[4.826875,52.358482],"type":"Point"}
}