{
  "type": "Feature",
  "properties": {
    "addr:full":"Holleblok 46 Huizen Noord-Holland 1273 EG",
    "addr:housenumber":"46",
    "addr:postcode":"1273 eg",
    "addr:street":"Holleblok",
    "iso:country":"NL",
    "sg:address":"Holleblok 46",
    "sg:city":"Huizen",
    "sg:orig_category":"Schoenen - Reparaties",
    "sg:phone":"+31 35 525 9885",
    "sg:postcode":"1273 EG",
    "sg:province":"Noord-Holland",
    "wof:name":"Boerhout-De Weert Vof",
    "wof:placetype":"venue"
},
  "geometry": {"coordinates":[5.252736,52.30209],"type":"Point"}
}