{
  "type": "Feature",
  "properties": {
    "addr:full":"Maandereind 7 Ede Gld Gelderland 6711 AA",
    "addr:housenumber":"7",
    "addr:postcode":"6711 aa",
    "addr:street":"Maandereind;Gld Gelderland",
    "iso:country":"NL",
    "sg:address":"Maandereind 7",
    "sg:city":"Ede Gld",
    "sg:orig_category":"Verlichting",
    "sg:phone":"+31 318 616 588",
    "sg:postcode":"6711 AA",
    "sg:province":"Gelderland",
    "wof:name":"Lampenier",
    "wof:placetype":"venue"
},
  "geometry": {"coordinates":[5.6697368622,52.0431976318],"type":"Point"}
}