{
  "type": "Feature",
  "properties": {
    "addr:full":"Wagenmaker 8 Beuningen Gld Gelderland 6641 EW",
    "addr:housenumber":"8",
    "addr:postcode":"6641 ew",
    "addr:street":"Wagenmaker",
    "iso:country":"NL",
    "sg:address":"Wagenmaker 8",
    "sg:city":"Beuningen Gld",
    "sg:orig_category":"Projectinrichting",
    "sg:phone":"+31 24 675 0777",
    "sg:postcode":"6641 EW",
    "sg:province":"Gelderland",
    "wof:name":"Cann Bv",
    "wof:placetype":"venue"
},
  "geometry": {"coordinates":[5.760394,51.858009],"type":"Point"}
}