{
  "type": "Feature",
  "properties": {
    "addr:full":"Vossenbeemd 90C Helmond Noord-Brabant 5705 CL",
    "addr:housenumber":"90c",
    "addr:postcode":"5705",
    "addr:street":"Vossenbeemd",
    "iso:country":"NL",
    "sg:address":"Vossenbeemd 90C",
    "sg:city":"Helmond",
    "sg:orig_category":"Bewakingsdiensten",
    "sg:phone":"+31 492 564 256",
    "sg:postcode":"5705 CL",
    "sg:province":"Noord-Brabant",
    "sg:website":"http://www.networkprotection.nl",
    "wof:name":"Network Protection Bv",
    "wof:placetype":"venue"
},
  "geometry": {"coordinates":[5.668532,51.466572],"type":"Point"}
}