{
  "type": "Feature",
  "properties": {
    "addr:full":"Staringstraat 36 Nieuw Vennep Noord-Holland 2152 CX",
    "addr:housenumber":"36",
    "addr:postcode":"2152 cx",
    "addr:street":"Staringstraat;Nieuw Vennep",
    "iso:country":"NL",
    "sg:address":"Staringstraat 36",
    "sg:city":"Nieuw Vennep",
    "sg:orig_category":"Autokeuringen",
    "sg:phone":"+31 252 621 911",
    "sg:postcode":"2152 CX",
    "sg:province":"Noord-Holland",
    "wof:name":"Garage Roeleveld",
    "wof:placetype":"venue"
},
  "geometry": {"coordinates":[4.628032,52.271881],"type":"Point"}
}