{
  "type": "Feature",
  "properties": {
    "addr:full":"Bermerstraat 16 Ommen Overijssel 7731 CZ",
    "addr:housenumber":"16",
    "addr:postcode":"7731",
    "addr:street":"Bermerstraat",
    "iso:country":"NL",
    "sg:address":"Bermerstraat 16",
    "sg:city":"Ommen",
    "sg:orig_category":"Verzekeringen",
    "sg:phone":"+31 529 451 139",
    "sg:postcode":"7731 CZ",
    "sg:province":"Overijssel",
    "wof:name":"Assurantiekantoor M Bouwman Bv",
    "wof:placetype":"venue"
},
  "geometry": {"coordinates":[6.422438,52.51881],"type":"Point"}
}