{
  "type": "Feature",
  "properties": {
    "addr:full":"Kapellerln 168 Roermond Limburg 6045 AJ",
    "addr:housenumber":"168",
    "addr:postcode":"6045 aj",
    "iso:country":"NL",
    "sg:address":"Kapellerln 168",
    "sg:city":"Roermond",
    "sg:orig_category":"Adviesbureaus Bedrijfsorganisatie",
    "sg:phone":"+31 475 337 460",
    "sg:postcode":"6045 AJ",
    "sg:province":"Limburg",
    "wof:name":"Gras, K",
    "wof:placetype":"venue"
},
  "geometry": {"coordinates":[5.991103,51.189888],"type":"Point"}
}