{
  "type": "Feature",
  "properties": {
    "addr:full":"Bellwg 2 Culemborg Gelderland 4104 BJ",
    "addr:housenumber":"2",
    "addr:postcode":"4104 bj",
    "addr:street":"Bellwg;Gelderland",
    "iso:country":"NL",
    "sg:address":"Bellwg 2",
    "sg:city":"Culemborg",
    "sg:orig_category":"Verpakkingsmachines - Fabrieken",
    "sg:phone":"+31 345 630 444",
    "sg:postcode":"4104 BJ",
    "sg:province":"Gelderland",
    "wof:name":"Racupack Bv",
    "wof:placetype":"venue"
},
  "geometry": {"coordinates":[5.19964,51.941681],"type":"Point"}
}