{
  "type": "Feature",
  "properties": {
    "addr:full":"Oude Bredaseweg 36 Etten-Leur Noord-Brabant 4872 AE",
    "addr:housenumber":"36",
    "addr:postcode":"4872 ae",
    "addr:street":"Oude Bredaseweg",
    "iso:country":"NL",
    "sg:address":"Oude Bredaseweg 36",
    "sg:city":"Etten-Leur",
    "sg:orig_category":"Fitnesscentra",
    "sg:phone":"+31 76 501 8528",
    "sg:postcode":"4872 AE",
    "sg:province":"Noord-Brabant",
    "wof:name":"Valeovita Health- & Beautycenter",
    "wof:placetype":"venue"
},
  "geometry": {"coordinates":[4.638461,51.570152],"type":"Point"}
}