{
  "type": "Feature",
  "properties": {
    "addr:full":"Louis Pasteurstraat 9 Oud Beijerland Zuid-Holland 3261 LZ",
    "addr:housenumber":"9",
    "addr:postcode":"3261 lz",
    "addr:street":"Louis Pasteurstraat;Oud Beijerland",
    "iso:country":"NL",
    "sg:address":"Louis Pasteurstraat 9",
    "sg:city":"Oud Beijerland",
    "sg:orig_category":"Airconditioning And Ventilatie",
    "sg:phone":"+31 186 619 288",
    "sg:postcode":"3261 LZ",
    "sg:province":"Zuid-Holland",
    "wof:name":"Abb Bv",
    "wof:placetype":"venue"
},
  "geometry": {"coordinates":[4.441943,51.826248],"type":"Point"}
}