{
  "type": "Feature",
  "properties": {
    "addr:full":"1E Oosterkade 6 Sneek Provincie Friesland 8605 AA",
    "addr:housenumber":"6",
    "addr:postcode":"8605 aa",
    "addr:street":"1E Oosterkade;Provincie Friesland",
    "iso:country":"NL",
    "sg:address":"1E Oosterkade 6",
    "sg:city":"Sneek",
    "sg:orig_category":"Binnenvaart",
    "sg:phone":"+31 515 417 314",
    "sg:postcode":"8605 AA",
    "sg:province":"Provincie Friesland",
    "wof:name":"M. Harder",
    "wof:placetype":"venue"
},
  "geometry": {"coordinates":[5.666315,53.033764],"type":"Point"}
}