{
  "type": "Feature",
  "properties": {
    "addr:full":"M Rutgers-Hoitsemastr 2 Spijkenisse Zuid-Holland 3207 EJ",
    "addr:housenumber":"2",
    "addr:postcode":"3207 ej",
    "iso:country":"NL",
    "sg:address":"M Rutgers-Hoitsemastr 2",
    "sg:city":"Spijkenisse",
    "sg:orig_category":"Overheidsdiensten",
    "sg:phone":"+31 181 634 125",
    "sg:postcode":"3207 EJ",
    "sg:province":"Zuid-Holland",
    "wof:name":"Wijkcentrum Maaswijk",
    "wof:placetype":"venue"
},
  "geometry": {"coordinates":[4.3588519096,51.8368301392],"type":"Point"}
}