{
  "type": "Feature",
  "properties": {
    "addr:full":"Klarendalseweg 132 Arnhem Gelderland 6822 GE",
    "addr:housenumber":"132",
    "addr:postcode":"6822",
    "addr:street":"Klarendalseweg",
    "iso:country":"NL",
    "sg:address":"Klarendalseweg 132",
    "sg:city":"Arnhem",
    "sg:orig_category":"Binnenhuisarchitecten",
    "sg:phone":"+31 26 370 0214",
    "sg:postcode":"6822 GE",
    "sg:province":"Gelderland",
    "wof:name":"Bos, Drikus J M",
    "wof:placetype":"venue"
},
  "geometry": {"coordinates":[5.921537,51.988644],"type":"Point"}
}