{
  "type": "Feature",
  "properties": {
    "addr:full":"Hanzestr 153 Arnhem Gelderland 6826 MJ",
    "addr:housenumber":"153",
    "addr:postcode":"6826 mj",
    "iso:country":"NL",
    "sg:address":"Hanzestr 153",
    "sg:city":"Arnhem",
    "sg:orig_category":"Opticiens",
    "sg:phone":"+31 26 388 2902",
    "sg:postcode":"6826 MJ",
    "sg:province":"Gelderland",
    "sg:website":"http://www.hansanders.nl",
    "wof:name":"Hans Anders",
    "wof:placetype":"venue"
},
  "geometry": {"coordinates":[5.9514021873,51.9834060669],"type":"Point"}
}