{
  "type": "Feature",
  "properties": {
    "addr:full":"Noorderklamp 2 Nuenen Noord-Brabant 5673 BH",
    "addr:housenumber":"2",
    "addr:postcode":"5673 bh",
    "addr:street":"Noorderklamp",
    "iso:country":"NL",
    "sg:address":"Noorderklamp 2",
    "sg:city":"Nuenen",
    "sg:orig_category":"Vertalers",
    "sg:phone":"+31 40 252 7366",
    "sg:postcode":"5673 BH",
    "sg:province":"Noord-Brabant",
    "wof:name":"Vanherf, Drs Ing S",
    "wof:placetype":"venue"
},
  "geometry": {"coordinates":[5.567921,51.478153],"type":"Point"}
}