{
  "type": "Feature",
  "properties": {
    "iso:country":"NL",
    "sg:address":"Schokkerweg 32",
    "sg:city":"'S Gravenhage",
    "sg:orig_category":"Diverse Consumentenartikelen Gh",
    "sg:phone":"+31 70 350 0918",
    "sg:postcode":"2583 BH",
    "sg:province":"Zuid-Holland",
    "wof:name":"Handelsonderneming En Opslagbedrijf Jan Thysse",
    "wof:placetype":"venue"
},
  "geometry": {"coordinates":[4.271179,52.100697],"type":"Point"}
}