{
  "type": "Feature",
  "properties": {
    "iso:country":"NL",
    "sg:address":"Zomerwg 31",
    "sg:city":"Burgum",
    "sg:orig_category":"Voetbalverenigingen",
    "sg:phone":"+31 511 461 994",
    "sg:postcode":"9251 MG",
    "sg:province":"Minas Gerais",
    "wof:name":"Herauten, De",
    "wof:placetype":"venue"
},
  "geometry": {"coordinates":[-45.451351,-18.57752],"type":"Point"}
}