{
  "type": "Feature",
  "properties": {
    "addr:full":"Stationspln 10 Bussum Noord-Holland 1404 AM",
    "addr:housenumber":"10",
    "addr:postcode":"1404",
    "addr:street":"Stationspln",
    "iso:country":"NL",
    "sg:address":"Stationspln 10",
    "sg:city":"Bussum",
    "sg:orig_category":"Advocaten En Advocatenkantoren",
    "sg:phone":"+31 35 694 4833",
    "sg:postcode":"1404 AM",
    "sg:province":"Noord-Holland",
    "wof:name":"Hamer & Smit",
    "wof:placetype":"venue"
},
  "geometry": {"coordinates":[5.158252,52.280895],"type":"Point"}
}