{
  "type": "Feature",
  "properties": {
    "addr:full":"Noorderwg 10 Hilversum North Holland 1221 AA",
    "addr:housenumber":"10",
    "addr:postcode":"1221 aa",
    "addr:street":"Noorderwg",
    "iso:country":"NL",
    "sg:address":"Noorderwg 10",
    "sg:city":"Hilversum",
    "sg:orig_category":"Webdesign Bureaus",
    "sg:phone":"+31 35 683 4366",
    "sg:postcode":"1221 AA",
    "sg:province":"North Holland",
    "sg:website":"http://www.studio79.nl",
    "wof:name":"Studio 79",
    "wof:placetype":"venue"
},
  "geometry": {"coordinates":[5.1860799789,52.226600647],"type":"Point"}
}