{
  "type": "Feature",
  "properties": {
    "addr:full":"Kasteelseplaats 7 Ravenstein Noord-Brabant 5371 AR",
    "addr:housenumber":"7",
    "addr:postcode":"5371",
    "addr:street":"Kasteelseplaats",
    "iso:country":"NL",
    "sg:address":"Kasteelseplaats 7",
    "sg:city":"Ravenstein",
    "sg:orig_category":"Scholen Voor Basisonderwijs",
    "sg:phone":"+31 486 411 581",
    "sg:postcode":"5371 AR",
    "sg:province":"Noord-Brabant",
    "wof:name":"Bogaard Rk, De",
    "wof:placetype":"venue"
},
  "geometry": {"coordinates":[5.650106,51.797737],"type":"Point"}
}