{
  "type": "Feature",
  "properties": {
    "addr:full":"Verlengde Middenraai 45 Nieuw Balinge Drenthe 7938 PA",
    "addr:housenumber":"45",
    "addr:postcode":"balinge;7938 pa",
    "addr:street":"Verlengde Middenraai",
    "iso:country":"NL",
    "sg:address":"Verlengde Middenraai 45",
    "sg:city":"Nieuw Balinge",
    "sg:orig_category":"Loodgieterswerk, Verwarming And Sanitaire Installaties",
    "sg:phone":"+31 528 321 286",
    "sg:postcode":"7938 PA",
    "sg:province":"Drenthe",
    "wof:name":"A Wanninge",
    "wof:placetype":"venue"
},
  "geometry": {"coordinates":[6.608906,52.766479],"type":"Point"}
}