{
  "type": "Feature",
  "properties": {
    "addr:full":"Drentestraat 5 Amsterdam Noord-Holland 1083 HK",
    "addr:housenumber":"5",
    "addr:postcode":"1083 hk",
    "addr:street":"Drentestraat",
    "iso:country":"NL",
    "sg:address":"Drentestraat 5",
    "sg:city":"Amsterdam",
    "sg:orig_category":"Verzekeringen",
    "sg:phone":"+31 20 549 0101",
    "sg:postcode":"1083 HK",
    "sg:province":"Noord-Holland",
    "wof:name":"Eickhoff De Lorme Van Rossem Bv",
    "wof:placetype":"venue"
},
  "geometry": {"coordinates":[4.887054,52.335922],"type":"Point"}
}