{
  "type": "Feature",
  "properties": {
    "addr:full":"Velserstraat 19 Haarlem North Holland 2023 EA",
    "addr:housenumber":"19",
    "addr:postcode":"2023 ea",
    "addr:street":"Velserstraat",
    "iso:country":"NL",
    "sg:address":"Velserstraat 19",
    "sg:city":"Haarlem",
    "sg:orig_category":"Bloemen And Planten",
    "sg:phone":"+31 23 525 1985",
    "sg:postcode":"2023 EA",
    "sg:province":"North Holland",
    "wof:name":"Bloemenboetiek De Deo",
    "wof:placetype":"venue"
},
  "geometry": {"coordinates":[4.631935,52.392403],"type":"Point"}
}