{
  "type": "Feature",
  "properties": {
    "addr:full":"Purperbeer 34 Oss Michigan 5345 ET",
    "addr:housenumber":"34",
    "addr:postcode":"5345 et",
    "addr:street":"Purperbeer",
    "iso:country":"NL",
    "sg:address":"Purperbeer 34",
    "sg:city":"Oss",
    "sg:orig_category":"Autorijscholen",
    "sg:phone":"+31 412 640 913",
    "sg:postcode":"5345 ET",
    "sg:province":"Michigan",
    "wof:name":"Reuvers",
    "wof:placetype":"venue"
},
  "geometry": {"coordinates":[-84.54444100000001,41.88448],"type":"Point"}
}