{
  "type": "Feature",
  "properties": {
    "addr:full":"Olympus 15 Hellevoetsluis South Holland 3225 TS",
    "addr:housenumber":"15",
    "addr:postcode":"3225 ts",
    "addr:street":"Olympus",
    "iso:country":"NL",
    "sg:address":"Olympus 15",
    "sg:city":"Hellevoetsluis",
    "sg:orig_category":"Meubelen",
    "sg:phone":"+31 6 29596761",
    "sg:postcode":"3225 TS",
    "sg:province":"South Holland",
    "wof:name":"Bt",
    "wof:placetype":"venue"
},
  "geometry": {"coordinates":[4.160361,51.836353],"type":"Point"}
}