{
  "type": "Feature",
  "properties": {
    "addr:full":"Dusseldorperwg 105A Limmen Noord-Holland 1906 AJ",
    "addr:housenumber":"105a",
    "addr:postcode":"1906 aj",
    "iso:country":"NL",
    "sg:address":"Dusseldorperwg 105A",
    "sg:city":"Limmen",
    "sg:orig_category":"Bloemen En Planten",
    "sg:phone":"+31 72 505 3316",
    "sg:postcode":"1906 AJ",
    "sg:province":"Noord-Holland",
    "wof:name":"Suus",
    "wof:placetype":"venue"
},
  "geometry": {"coordinates":[4.699824,52.572147],"type":"Point"}
}