{
  "type": "Feature",
  "properties": {
    "addr:full":"Bogelscamplaan 1 Denekamp Overijssel 7591 GH",
    "addr:housenumber":"1",
    "addr:postcode":"7591 gh",
    "addr:street":"Bogelscamplaan",
    "iso:country":"NL",
    "sg:address":"Bogelscamplaan 1",
    "sg:city":"Denekamp",
    "sg:orig_category":"Verzekeringen",
    "sg:phone":"+31 541 351 681",
    "sg:postcode":"7591 GH",
    "sg:province":"Overijssel",
    "wof:name":"Assurantie- En Administratie- Kantoor G.J.J. Struy",
    "wof:placetype":"venue"
},
  "geometry": {"coordinates":[6.998545,52.372742],"type":"Point"}
}