{
  "type": "Feature",
  "properties": {
    "addr:full":"A V Hogendorpland 3 Heerhugowaard Noord-Holland 1705 JK",
    "addr:housenumber":"3",
    "addr:postcode":"1705 jk",
    "addr:street":"A;Hogendorpland",
    "iso:country":"NL",
    "sg:address":"A V Hogendorpland 3",
    "sg:city":"Heerhugowaard",
    "sg:orig_category":"Scheidingswanden - Fabrieken",
    "sg:phone":"+31 72 574 0198",
    "sg:postcode":"1705 JK",
    "sg:province":"Noord-Holland",
    "wof:name":"Ed De La Porte",
    "wof:placetype":"venue"
},
  "geometry": {"coordinates":[4.827522,52.665195],"type":"Point"}
}