{
  "type": "Feature",
  "properties": {
    "iso:country":"NL",
    "sg:address":"Burg Patynln 1900",
    "sg:city":"S Gravenhage",
    "sg:orig_category":"Bejaarden - Verzorgingstehuizen",
    "sg:phone":"+31 70 354 3927",
    "sg:postcode":"2585 CB",
    "sg:province":"South Holland",
    "wof:name":"Schakelpunt, Het",
    "wof:placetype":"venue"
},
  "geometry": {"coordinates":[4.29777,52.094799],"type":"Point"}
}