{
  "type": "Feature",
  "properties": {
    "addr:full":"Oranjestraat 6 Dalerpeel Drenthe 7753 TK",
    "addr:housenumber":"6",
    "addr:postcode":"7753 tk",
    "addr:street":"Oranjestraat",
    "iso:country":"NL",
    "sg:address":"Oranjestraat 6",
    "sg:city":"Dalerpeel",
    "sg:orig_category":"Overheidsdiensten",
    "sg:phone":"+31 524 571 305",
    "sg:postcode":"7753 TK",
    "sg:province":"Drenthe",
    "wof:name":"Dorpshuis De Breiberg",
    "wof:placetype":"venue"
},
  "geometry": {"coordinates":[6.6632070541,52.6793746948],"type":"Point"}
}