{
  "type": "Feature",
  "properties": {
    "addr:full":"Dennenbosweg 92 Hengelo Ov NL.08 7556 CJ",
    "addr:housenumber":"92",
    "addr:postcode":"7556",
    "addr:street":"Dennenbosweg;Ov;Cj",
    "iso:country":"NL",
    "sg:address":"Dennenbosweg 92",
    "sg:city":"Hengelo Ov",
    "sg:classifiers":[
        {
            "category":"Fast Food",
            "type":"Food & Drink"
        }
    ],
    "sg:phone":"+31 74 243 1084",
    "sg:postcode":"7556 CJ",
    "sg:province":"NL.08",
    "sg:tags":[
        "afhaal",
        "restaurant"
    ],
    "wof:name":"Snackcorner P.W. Aalbers",
    "wof:placetype":"venue"
},
  "geometry": {"coordinates":[6.795331,52.270992],"type":"Point"}
}