{
  "type": "Feature",
  "properties": {
    "iso:country":"NL",
    "sg:address":"R Vd Hamkd 95",
    "sg:city":"Utrecht",
    "sg:orig_category":"Hengelsportartikelen",
    "sg:phone":"+31 30 243 3696",
    "sg:postcode":"3552 CL",
    "sg:province":"Utrecht",
    "wof:name":"Temming Ton Traditional Hengelsport",
    "wof:placetype":"venue"
},
  "geometry": {"coordinates":[5.10422,52.107819],"type":"Point"}
}