{
  "type": "Feature",
  "properties": {
    "addr:full":"Frederik Hendrikstraat 115 Utrecht Utrecht 3583 VJ",
    "addr:housenumber":"115",
    "addr:postcode":"3583 vj",
    "addr:street":"Frederik Hendrikstraat",
    "iso:country":"NL",
    "sg:address":"Frederik Hendrikstraat 115",
    "sg:city":"Utrecht",
    "sg:orig_category":"Werving And Selectie Van Vast Personeel",
    "sg:phone":"+31 6 22449535",
    "sg:postcode":"3583 VJ",
    "sg:province":"Utrecht",
    "wof:name":"Mathilde Van Den Berg",
    "wof:placetype":"venue"
},
  "geometry": {"coordinates":[5.1451439857,52.0883331299],"type":"Point"}
}