{
  "type": "Feature",
  "properties": {
    "addr:full":"Maarsseveensevaart 80 Maarssen Utrecht 3601 CG",
    "addr:housenumber":"80",
    "addr:postcode":"3601 cg",
    "addr:street":"Maarsseveensevaart",
    "iso:country":"NL",
    "sg:address":"Maarsseveensevaart 80",
    "sg:city":"Maarssen",
    "sg:classifiers":[
        {
            "category":"Food & Beverages",
            "subcategory":"Fruits & Vegetables",
            "type":"Retail Goods"
        }
    ],
    "sg:phone":"+31 346 561 020",
    "sg:postcode":"3601 CG",
    "sg:province":"Utrecht",
    "sg:tags":[
        "groenten"
    ],
    "wof:name":"Firma De Groot Groente En Fruit",
    "wof:placetype":"venue"
},
  "geometry": {"coordinates":[5.054436,52.143005],"type":"Point"}
}