{
  "type": "Feature",
  "properties": {
    "addr:full":"Pr Frederikln 203 Leidschendam South Holland 2263 HA",
    "addr:housenumber":"203",
    "addr:postcode":"2263 ha",
    "iso:country":"NL",
    "sg:address":"Pr Frederikln 203",
    "sg:city":"Leidschendam",
    "sg:orig_category":"Postkantoren",
    "sg:phone":"+31 70 327 9983",
    "sg:postcode":"2263 HA",
    "sg:province":"South Holland",
    "sg:website":"http://www.postkantoor.nl",
    "wof:name":"Postkantoor",
    "wof:placetype":"venue"
},
  "geometry": {"coordinates":[4.401683,52.097965],"type":"Point"}
}