{
  "type": "Feature",
  "properties": {
    "addr:full":"Weiersloop 6 Assen Provincie Drenthe 9401 DZ",
    "addr:housenumber":"6",
    "addr:postcode":"9401 dz",
    "addr:street":"Weiersloop;Provincie Drenthe",
    "iso:country":"NL",
    "sg:address":"Weiersloop 6",
    "sg:city":"Assen",
    "sg:orig_category":"Juweliers",
    "sg:phone":"+31 592 311 390",
    "sg:postcode":"9401 DZ",
    "sg:province":"Provincie Drenthe",
    "wof:name":"Jan Ten Hoor Juwelier",
    "wof:placetype":"venue"
},
  "geometry": {"coordinates":[6.560417,52.994343],"type":"Point"}
}