{
  "type": "Feature",
  "properties": {
    "iso:country":"NL",
    "sg:address":"Kruisakkers 12",
    "sg:city":"Bergen Op Zoom",
    "sg:orig_category":"Automaterialen En Gereedschappen",
    "sg:phone":"+31 164 233 550",
    "sg:postcode":"4613 BV",
    "sg:province":"Noord-Brabant",
    "wof:name":"Aps",
    "wof:placetype":"venue"
},
  "geometry": {"coordinates":[4.277245,51.504551],"type":"Point"}
}