{
  "type": "Feature",
  "properties": {
    "addr:full":"D Brouwerln 9 Hooglanderveen Utrecht 3829 CD",
    "addr:housenumber":"9",
    "addr:postcode":"3829 cd",
    "iso:country":"NL",
    "sg:address":"D Brouwerln 9",
    "sg:city":"Hooglanderveen",
    "sg:orig_category":"Onderhoudswerken",
    "sg:phone":"+31 33 258 0503",
    "sg:postcode":"3829 CD",
    "sg:province":"Utrecht",
    "wof:name":"Vlasakker, Van De",
    "wof:placetype":"venue"
},
  "geometry": {"coordinates":[5.431815,52.188042],"type":"Point"}
}