{
  "type": "Feature",
  "properties": {
    "addr:full":"Anklaarsewg 97 Apeldoorn Gelderland 7317 AS",
    "addr:housenumber":"97",
    "addr:postcode":"7317 as",
    "addr:street":"Anklaarsewg;Gelderland",
    "iso:country":"NL",
    "sg:address":"Anklaarsewg 97",
    "sg:city":"Apeldoorn",
    "sg:orig_category":"Parketvloeren",
    "sg:phone":"+31 55 576 7767",
    "sg:postcode":"7317 AS",
    "sg:province":"Gelderland",
    "wof:name":"Royal",
    "wof:placetype":"venue"
},
  "geometry": {"coordinates":[5.9708,52.235088],"type":"Point"}
}