{
  "type": "Feature",
  "properties": {
    "addr:full":"Spaarnwouderstraat 29 Haarlem North Holland 2011 AA",
    "addr:housenumber":"29",
    "addr:postcode":"2011 aa",
    "addr:street":"Spaarnwouderstraat",
    "iso:country":"NL",
    "sg:address":"Spaarnwouderstraat 29",
    "sg:city":"Haarlem",
    "sg:orig_category":"Kappers",
    "sg:phone":"+31 23 535 3794",
    "sg:postcode":"2011 AA",
    "sg:province":"North Holland",
    "wof:name":"Do Bartels",
    "wof:placetype":"venue"
},
  "geometry": {"coordinates":[4.6428079605,52.3798599243],"type":"Point"}
}