{
  "type": "Feature",
  "properties": {
    "iso:country":"NL",
    "sg:address":"Ebstroom 15",
    "sg:city":"Katwijk Zh",
    "sg:orig_category":"Bloemen And Planten Gh",
    "sg:phone":"+31 71 408 4236",
    "sg:postcode":"2221 WC",
    "sg:province":"South Holland",
    "wof:name":"M A Ravensbergen",
    "wof:placetype":"venue"
},
  "geometry": {"coordinates":[4.429523,52.207771],"type":"Point"}
}