{
  "type": "Feature",
  "properties": {
    "addr:full":"Scharnerweg 67 Maastricht Limburg 6224 JB",
    "addr:housenumber":"67",
    "addr:postcode":"6224 jb",
    "addr:street":"Scharnerweg",
    "iso:country":"NL",
    "sg:address":"Scharnerweg 67",
    "sg:city":"Maastricht",
    "sg:classifiers":[
        {
            "category":"Communications",
            "subcategory":"Television Station",
            "type":"Services"
        }
    ],
    "sg:phone":"+31 43 363 3733",
    "sg:postcode":"6224 JB",
    "sg:province":"Limburg",
    "sg:tags":[
        "video",
        "audio",
        "verhuur"
    ],
    "wof:name":"Euro Video",
    "wof:placetype":"venue"
},
  "geometry": {"coordinates":[5.716413,50.848728],"type":"Point"}
}