{
  "type": "Feature",
  "properties": {
    "addr:full":"Mr F J Haarmanwg 28 Terneuzen Zeeland 4538 AR",
    "addr:housenumber":"28",
    "addr:postcode":"4538",
    "addr:street":"Mr F J Haarmanwg",
    "iso:country":"NL",
    "sg:address":"Mr F J Haarmanwg 28",
    "sg:city":"Terneuzen",
    "sg:orig_category":"Verf En Lak - Fabrieken En Groothandel",
    "sg:phone":"+31 115 617 564",
    "sg:postcode":"4538 AR",
    "sg:province":"Zeeland",
    "wof:name":"Verf Verkoop Zeeland Bv",
    "wof:placetype":"venue"
},
  "geometry": {"coordinates":[3.843189,51.30994],"type":"Point"}
}