{
  "type": "Feature",
  "properties": {
    "addr:full":"Nobelstraat 117-119 Utrecht Utrecht 3512 EM",
    "addr:housenumber":"117-119",
    "addr:postcode":"3512 em",
    "addr:street":"Nobelstraat",
    "iso:country":"NL",
    "sg:address":"Nobelstraat 117-119",
    "sg:city":"Utrecht",
    "sg:orig_category":"Huishoudapparatuur, Televisies And Radio'S",
    "sg:phone":"+31 30 233 4090",
    "sg:postcode":"3512 EM",
    "sg:province":"Utrecht",
    "wof:name":"Audio Design",
    "wof:placetype":"venue"
},
  "geometry": {"coordinates":[5.124194,52.092968],"type":"Point"}
}