{
  "type": "Feature",
  "properties": {
    "addr:full":"Holkerweg 101 Amersfoort Utrecht 3813 KG",
    "addr:housenumber":"101",
    "addr:postcode":"3813 kg",
    "addr:street":"Holkerweg",
    "iso:country":"NL",
    "sg:address":"Holkerweg 101",
    "sg:city":"Amersfoort",
    "sg:orig_category":"Marktonderzoekbureaus",
    "sg:phone":"+31 33 433 0070",
    "sg:postcode":"3813 KG",
    "sg:province":"Utrecht",
    "wof:name":"Metselaar Consultancy",
    "wof:placetype":"venue"
},
  "geometry": {"coordinates":[5.391287,52.173538],"type":"Point"}
}