{
  "type": "Feature",
  "properties": {
    "iso:country":"NL",
    "sg:address":"Timorstr 15",
    "sg:city":"Leiden",
    "sg:orig_category":"Scholen Voor Basisonderwijs",
    "sg:phone":"+31 71 522 1127",
    "sg:postcode":"2315 BL",
    "sg:province":"South Holland",
    "wof:name":"Viersprong Openb, De",
    "wof:placetype":"venue"
},
  "geometry": {"coordinates":[4.510208,52.166088],"type":"Point"}
}