{
  "type": "Feature",
  "properties": {
    "addr:full":"Waterloowg 33 Austerlitz Utrecht 3711 BB",
    "addr:housenumber":"33",
    "addr:postcode":"3711 bb",
    "addr:street":"Waterloowg",
    "iso:country":"NL",
    "sg:address":"Waterloowg 33",
    "sg:city":"Austerlitz",
    "sg:orig_category":"Kunstenaars- Benodigdheden",
    "sg:phone":"+31 343 491 354",
    "sg:postcode":"3711 BB",
    "sg:province":"Utrecht",
    "wof:name":"Vliet, R Van Der",
    "wof:placetype":"venue"
},
  "geometry": {"coordinates":[5.31225,52.077431],"type":"Point"}
}