{
  "type": "Feature",
  "properties": {
    "addr:full":"Van Ghentstraat 5 Twello Gelderland 7391 CR",
    "addr:housenumber":"5",
    "addr:postcode":"7391 cr",
    "addr:street":"Van Ghentstraat;Gelderland",
    "iso:country":"NL",
    "sg:address":"Van Ghentstraat 5",
    "sg:city":"Twello",
    "sg:orig_category":"Schoenen",
    "sg:phone":"+31 571 271 395",
    "sg:postcode":"7391 CR",
    "sg:province":"Gelderland",
    "wof:name":"Hulsebos Schoen En Mode",
    "wof:placetype":"venue"
},
  "geometry": {"coordinates":[6.103835,52.236519],"type":"Point"}
}