{
  "type": "Feature",
  "properties": {
    "iso:country":"NL",
    "sg:address":"Stationspln 2",
    "sg:city":"Heerenveen",
    "sg:orig_category":"Begrafenisverzorging",
    "sg:phone":"+31 512 514 489",
    "sg:postcode":"8441 AT",
    "sg:province":"Friesland",
    "wof:name":"Helpt Elkander",
    "wof:placetype":"venue"
},
  "geometry": {"coordinates":[5.915029,52.961926],"type":"Point"}
}