{
  "type": "Feature",
  "properties": {
    "iso:country":"NL",
    "sg:address":"Van Der Palmstraat 37C",
    "sg:city":"Rotterdam",
    "sg:classifiers":[
        {
            "category":"Wholesale",
            "subcategory":"Motor Vehicles",
            "type":"Manufacturing & Wholesale Goods"
        }
    ],
    "sg:phone":"+31 10 425 9024",
    "sg:postcode":"3022 VV",
    "sg:province":"South Holland",
    "sg:tags":[
        "scooter",
        "en"
    ],
    "wof:name":"Pee, De",
    "wof:placetype":"venue"
},
  "geometry": {"coordinates":[4.451421,51.91721],"type":"Point"}
}