{
  "type": "Feature",
  "properties": {
    "iso:country":"NL",
    "sg:address":"Sibeliusstraat 50",
    "sg:city":"Bergen Op Zoom",
    "sg:orig_category":"Kappers",
    "sg:phone":"+31 164 237 860",
    "sg:postcode":"4614 VD",
    "sg:province":"North Brabant",
    "wof:name":"Tendenz Kappers",
    "wof:placetype":"venue"
},
  "geometry": {"coordinates":[4.295999,51.50507],"type":"Point"}
}