{
  "type": "Feature",
  "properties": {
    "addr:full":"Herenstr 87 Voorhout South Holland 2215 KG",
    "addr:housenumber":"87",
    "addr:postcode":"2215 kg",
    "addr:street":"Herenstr",
    "iso:country":"NL",
    "sg:address":"Herenstr 87",
    "sg:city":"Voorhout",
    "sg:orig_category":"Kinderkleding",
    "sg:phone":"+31 252 229 619",
    "sg:postcode":"2215 KG",
    "sg:province":"South Holland",
    "wof:name":"Minou",
    "wof:placetype":"venue"
},
  "geometry": {"coordinates":[4.48416,52.222443],"type":"Point"}
}