{
  "type": "Feature",
  "properties": {
    "addr:full":"Koningsln 37 Utrecht Utrecht 3583 GH",
    "addr:housenumber":"37",
    "addr:postcode":"3583 gh",
    "addr:street":"Koningsln",
    "iso:country":"NL",
    "sg:address":"Koningsln 37",
    "sg:city":"Utrecht",
    "sg:orig_category":"Galeries",
    "sg:phone":"+31 30 251 5395",
    "sg:postcode":"3583 GH",
    "sg:province":"Utrecht",
    "wof:name":"Huis Voor Beeldende Kunst",
    "wof:placetype":"venue"
},
  "geometry": {"coordinates":[5.142643,52.088501],"type":"Point"}
}