{
  "type": "Feature",
  "properties": {
    "addr:full":"Zeven Eikenln 37 Veghel North Brabant 5461 EC",
    "addr:housenumber":"37",
    "addr:postcode":"5461 ec",
    "iso:country":"NL",
    "sg:address":"Zeven Eikenln 37",
    "sg:city":"Veghel",
    "sg:orig_category":"Woningstoffeerders",
    "sg:phone":"+31 413 351 451",
    "sg:postcode":"5461 EC",
    "sg:province":"North Brabant",
    "wof:name":"Prowoon",
    "wof:placetype":"venue"
},
  "geometry": {"coordinates":[5.550306797,51.6177139282],"type":"Point"}
}