{
  "type": "Feature",
  "properties": {
    "iso:country":"NL",
    "sg:address":"Industriewg 29",
    "sg:city":"Mydrecht",
    "sg:classifiers":[
        {
            "category":"Arena",
            "subcategory":"Auto Racetrack",
            "type":"Entertainment"
        }
    ],
    "sg:phone":"+31 297 241 856",
    "sg:postcode":"3641 RK",
    "sg:province":"Utrecht",
    "sg:tags":[
        "en",
        "racebanen",
        "kart-"
    ],
    "wof:name":"Bleekemolens",
    "wof:placetype":"venue"
},
  "geometry": {"coordinates":[4.875515,52.206757],"type":"Point"}
}