{
  "type": "Feature",
  "properties": {
    "addr:full":"Dekkersweg 3 Lewedorp Zeeland 4456 NT",
    "addr:housenumber":"3",
    "addr:postcode":"4456 nt",
    "addr:street":"Dekkersweg",
    "iso:country":"NL",
    "sg:address":"Dekkersweg 3",
    "sg:city":"Lewedorp",
    "sg:orig_category":"Kampeerterreinen",
    "sg:phone":"+31 113 612 305",
    "sg:postcode":"4456 NT",
    "sg:province":"Zeeland",
    "wof:name":"Buitenhof",
    "wof:placetype":"venue"
},
  "geometry": {"coordinates":[3.735886097,51.4923553467],"type":"Point"}
}