{
  "type": "Feature",
  "properties": {
    "addr:full":"Galileistr 63C Heerhugowaard Noord-Holland 1704 SE",
    "addr:housenumber":"63c",
    "addr:postcode":"1704 se",
    "addr:street":"Galileistr",
    "iso:country":"NL",
    "sg:address":"Galileistr 63C",
    "sg:city":"Heerhugowaard",
    "sg:orig_category":"Gordijnen",
    "sg:phone":"+31 72 534 6897",
    "sg:postcode":"1704 SE",
    "sg:province":"Noord-Holland",
    "wof:name":"Vries & Volbeda, De",
    "wof:placetype":"venue"
},
  "geometry": {"coordinates":[4.828562,52.690826],"type":"Point"}
}