{
  "type": "Feature",
  "properties": {
    "addr:full":"Spaarbekkenkade 22 Purmerend Noord-Holland 1441 WT",
    "addr:housenumber":"22",
    "addr:postcode":"1441 wt",
    "addr:street":"Spaarbekkenkade",
    "iso:country":"NL",
    "sg:address":"Spaarbekkenkade 22",
    "sg:city":"Purmerend",
    "sg:orig_category":"Fotostudio'S And Fotografen",
    "sg:phone":"+31 299 438 571",
    "sg:postcode":"1441 WT",
    "sg:province":"Noord-Holland",
    "wof:name":"Fotografie De Kat Edwoud",
    "wof:placetype":"venue"
},
  "geometry": {"coordinates":[4.958353,52.502476],"type":"Point"}
}