{
  "type": "Feature",
  "properties": {
    "addr:full":"Putterweg 4 Ermelo Gelderland 3851 GD",
    "addr:housenumber":"4",
    "addr:postcode":"3851 gd",
    "addr:street":"Putterweg;Gelderland",
    "iso:country":"NL",
    "sg:address":"Putterweg 4",
    "sg:city":"Ermelo",
    "sg:classifiers":[
        {
            "category":"Fast Food",
            "type":"Food & Drink"
        }
    ],
    "sg:phone":"+31 341 552 333",
    "sg:postcode":"3851 GD",
    "sg:province":"Gelderland",
    "sg:tags":[
        "afhaal",
        "restaurant"
    ],
    "wof:name":"Cafetaria 'T Weitje",
    "wof:placetype":"venue"
},
  "geometry": {"coordinates":[5.63161,52.30019],"type":"Point"}
}