{
  "type": "Feature",
  "properties": {
    "addr:full":"Oude Bredaseweg 40 Etten Leur Noord-Brabant 4872 AE",
    "addr:housenumber":"40",
    "addr:postcode":"4872 ae",
    "addr:street":"Oude Bredaseweg",
    "iso:country":"NL",
    "sg:address":"Oude Bredaseweg 40",
    "sg:city":"Etten Leur",
    "sg:orig_category":"Bloemen And Planten",
    "sg:phone":"+31 76 501 6543",
    "sg:postcode":"4872 AE",
    "sg:province":"Noord-Brabant",
    "wof:name":"Bloemenatelier De Blauwe Iris",
    "wof:placetype":"venue"
},
  "geometry": {"coordinates":[4.638723,51.57021],"type":"Point"}
}