{
  "type": "Feature",
  "properties": {
    "addr:full":"Dorpsstr 35 Vught Noord-Brabant 5261 CJ",
    "addr:housenumber":"35",
    "addr:postcode":"5261 cj",
    "addr:street":"Dorpsstr",
    "iso:country":"NL",
    "sg:address":"Dorpsstr 35",
    "sg:city":"Vught",
    "sg:orig_category":"Verlichting",
    "sg:phone":"+31 73 656 2544",
    "sg:postcode":"5261 CJ",
    "sg:province":"Noord-Brabant",
    "wof:name":"Pijnenburg Verlichting, Jac",
    "wof:placetype":"venue"
},
  "geometry": {"coordinates":[5.297663,51.660519],"type":"Point"}
}