{
  "type": "Feature",
  "properties": {
    "addr:full":"Eeuwigeln 1 Bergen Nh North Holland 1861 CL",
    "addr:housenumber":"1",
    "addr:postcode":"1861",
    "addr:street":"Eeuwigeln",
    "iso:country":"NL",
    "sg:address":"Eeuwigeln 1",
    "sg:city":"Bergen Nh",
    "sg:orig_category":"Bioscopen",
    "sg:phone":"+31 72 581 3312",
    "sg:postcode":"1861 CL",
    "sg:province":"North Holland",
    "wof:name":"Cinebergen",
    "wof:placetype":"venue"
},
  "geometry": {"coordinates":[4.701395,52.669979],"type":"Point"}
}