{
  "type": "Feature",
  "properties": {
    "addr:full":"Stadhouderswg 4 St Annaparochie Friesland 9076 AC",
    "addr:housenumber":"4",
    "addr:postcode":"9076 ac",
    "addr:street":"Stadhouderswg",
    "iso:country":"NL",
    "sg:address":"Stadhouderswg 4",
    "sg:city":"St Annaparochie",
    "sg:orig_category":"Elektrotechnische Installatiebureaus",
    "sg:phone":"+31 518 401 883",
    "sg:postcode":"9076 AC",
    "sg:province":"Friesland",
    "wof:name":"Brouwer, Sieb",
    "wof:placetype":"venue"
},
  "geometry": {"coordinates":[5.657249,53.276863],"type":"Point"}
}