{
  "type": "Feature",
  "properties": {
    "addr:full":"Voorstad 79 Goes Zeeland 4461 KM",
    "addr:housenumber":"79",
    "addr:postcode":"4461 km",
    "addr:street":"Voorstad",
    "iso:country":"NL",
    "sg:address":"Voorstad 79",
    "sg:city":"Goes",
    "sg:classifiers":[
        {
            "category":"Retail",
            "subcategory":"Auto Repair",
            "type":"Services"
        }
    ],
    "sg:phone":"+31 113 227 353",
    "sg:postcode":"4461 KM",
    "sg:province":"Zeeland",
    "sg:tags":[
        "garage"
    ],
    "sg:website":"http://www.vanfraassen.nl",
    "wof:name":"Fraassen Bv, Van",
    "wof:placetype":"venue"
},
  "geometry": {"coordinates":[-83.914169,39.768833],"type":"Point"}
}