{
  "type": "Feature",
  "properties": {
    "addr:full":"Kerkweg 1 Zeddam Gelderland 7038 CE",
    "addr:housenumber":"1",
    "addr:postcode":"7038 ce",
    "addr:street":"Kerkweg;Gelderland",
    "iso:country":"NL",
    "sg:address":"Kerkweg 1",
    "sg:city":"Zeddam",
    "sg:orig_category":"Paramedische Behandelingen",
    "sg:phone":"+31 314 651 992",
    "sg:postcode":"7038 CE",
    "sg:province":"Gelderland",
    "wof:name":"G.M.F. Heijting",
    "wof:placetype":"venue"
},
  "geometry": {"coordinates":[6.256583,51.899529],"type":"Point"}
}