{
  "type": "Feature",
  "properties": {
    "addr:full":"Tegelseweg 49 Belfeld Limburg 5951 GL",
    "addr:housenumber":"49",
    "addr:postcode":"5951 gl",
    "addr:street":"Tegelseweg",
    "iso:country":"NL",
    "sg:address":"Tegelseweg 49",
    "sg:city":"Belfeld",
    "sg:orig_category":"Verhuur Voertuigen Behalve Auto'S",
    "sg:phone":"+31 77 373 1279",
    "sg:postcode":"5951 GL",
    "sg:province":"Limburg",
    "wof:name":"A. Op Het Veld",
    "wof:placetype":"venue"
},
  "geometry": {"coordinates":[6.13449,51.323891],"type":"Point"}
}