{
  "type": "Feature",
  "properties": {
    "iso:country":"NL",
    "sg:address":"Monseigneur Hanssenstr 2",
    "sg:city":"Broekhuizenvorst",
    "sg:orig_category":"Kappers",
    "sg:phone":"+31 77 463 1379",
    "sg:postcode":"5871 AN",
    "sg:province":"Limburg",
    "wof:name":"Kapsalon Jacqueline",
    "wof:placetype":"venue"
},
  "geometry": {"coordinates":[6.1564478874,51.4945755005],"type":"Point"}
}