{
  "type": "Feature",
  "properties": {
    "addr:full":"Monseigneur Hanssenstr 2 Broekhuizenvorst Limburg 5871 AN",
    "addr:housenumber":"2",
    "addr:postcode":"5871 an",
    "addr:street":"Monseigneur Hanssenstr",
    "iso:country":"NL",
    "sg:address":"Monseigneur Hanssenstr 2",
    "sg:city":"Broekhuizenvorst",
    "sg:orig_category":"Kappers",
    "sg:phone":"+31 77 463 1379",
    "sg:postcode":"5871 AN",
    "sg:province":"Limburg",
    "wof:name":"Kapsalon Jacqueline",
    "wof:placetype":"venue"
},
  "geometry": {"coordinates":[6.1564478874,51.4945755005],"type":"Point"}
}