{
  "type": "Feature",
  "properties": {
    "iso:country":"NL",
    "sg:address":"Aletta Jacobskade 50",
    "sg:city":"Vlaardingen",
    "sg:orig_category":"Vertaal- And Tolkenbureaus",
    "sg:phone":"+31 10 474 8494",
    "sg:postcode":"3137 TB",
    "sg:province":"South Holland",
    "wof:name":"Vertaalbureau Mr Ellen Smits",
    "wof:placetype":"venue"
},
  "geometry": {"coordinates":[4.336732,51.931694],"type":"Point"}
}