{
  "type": "Feature",
  "properties": {
    "addr:full":"Bongerswg 6 T Loo Oldebroek Gelderland 8095 PH",
    "addr:housenumber":"6 t",
    "addr:postcode":"8095",
    "addr:street":"Bongerswg;Loo;Gelderland",
    "iso:country":"NL",
    "sg:address":"Bongerswg 6",
    "sg:city":"T Loo Oldebroek",
    "sg:orig_category":"Hek- En Rasterwerken",
    "sg:phone":"+31 525 653 913",
    "sg:postcode":"8095 PH",
    "sg:province":"Gelderland",
    "wof:name":"Focus 4+, Montagebedrijf",
    "wof:placetype":"venue"
},
  "geometry": {"coordinates":[5.933234,52.439434],"type":"Point"}
}