{
  "type": "Feature",
  "properties": {
    "addr:full":"Ln V Chartroise 166 Utrecht Utrecht 3552 EZ",
    "addr:housenumber":"166",
    "addr:postcode":"3552 ez",
    "addr:street":"Ln;Chartroise",
    "iso:country":"NL",
    "sg:address":"Ln V Chartroise 166",
    "sg:city":"Utrecht",
    "sg:orig_category":"Verenigingsgebouwen",
    "sg:phone":"+31 30 244 7595",
    "sg:postcode":"3552 EZ",
    "sg:province":"Utrecht",
    "wof:name":"Geuzenkwartier, Het",
    "wof:placetype":"venue"
},
  "geometry": {"coordinates":[5.099053,52.108089],"type":"Point"}
}