{
  "type": "Feature",
  "properties": {
    "iso:country":"NL",
    "sg:address":"Timmereind 5",
    "sg:city":"Waalre",
    "sg:orig_category":"Grondwerken",
    "sg:phone":"+31 40 221 7366",
    "sg:postcode":"5581 VJ",
    "sg:province":"Noord-Brabant",
    "wof:name":"Wijlaars Grond- & Cultuurtechnische Werken",
    "wof:placetype":"venue"
},
  "geometry": {"coordinates":[5.43661,51.379242],"type":"Point"}
}