{
  "type": "Feature",
  "properties": {
    "addr:full":"Grotestr 80A Vierlingsbeek North Brabant 5821 AH",
    "addr:housenumber":"80a",
    "addr:postcode":"5821 ah",
    "addr:street":"Grotestr",
    "iso:country":"NL",
    "sg:address":"Grotestr 80A",
    "sg:city":"Vierlingsbeek",
    "sg:orig_category":"Kappers",
    "sg:phone":"+31 478 632 282",
    "sg:postcode":"5821 AH",
    "sg:province":"North Brabant",
    "wof:name":"Jos?",
    "wof:placetype":"venue"
},
  "geometry": {"coordinates":[6.013133049,51.5959358215],"type":"Point"}
}