{
  "type": "Feature",
  "properties": {
    "addr:full":"Middenweg 17 Hoenderloo Gelderland 7351 BA",
    "addr:housenumber":"17",
    "addr:postcode":"7351 ba",
    "addr:street":"Middenweg;Gelderland",
    "iso:country":"NL",
    "sg:address":"Middenweg 17",
    "sg:city":"Hoenderloo",
    "sg:orig_category":"Kappers",
    "sg:phone":"+31 55 378 1269",
    "sg:postcode":"7351 BA",
    "sg:province":"Gelderland",
    "wof:name":"Kapsalon Haarstudio Papillot",
    "wof:placetype":"venue"
},
  "geometry": {"coordinates":[5.8754329681,52.1196022034],"type":"Point"}
}