{
  "type": "Feature",
  "properties": {
    "iso:country":"NL",
    "sg:address":"De Vest 22",
    "sg:city":"Valkenswaard",
    "sg:orig_category":"Houten Verpakkingen Fab",
    "sg:phone":"+31 40 204 4935",
    "sg:postcode":"5555 XL",
    "sg:province":"Noord-Brabant",
    "wof:name":"Spaninks Pallets Vof",
    "wof:placetype":"venue"
},
  "geometry": {"coordinates":[5.487741,51.34811],"type":"Point"}
}