{
  "type": "Feature",
  "properties": {
    "addr:full":"Industriewg 62B Rotterdam South Holland 3044 CC",
    "addr:housenumber":"62b",
    "addr:postcode":"3044 cc",
    "addr:street":"Industriewg",
    "iso:country":"NL",
    "sg:address":"Industriewg 62B",
    "sg:city":"Rotterdam",
    "sg:orig_category":"Autorijscholen",
    "sg:phone":"+31 10 462 1547",
    "sg:postcode":"3044 CC",
    "sg:province":"South Holland",
    "wof:name":"Monique",
    "wof:placetype":"venue"
},
  "geometry": {"coordinates":[4.416903,51.931488],"type":"Point"}
}