{
  "type": "Feature",
  "properties": {
    "addr:full":"Mondriaanstraat 17 Ede Gld Gelderland 6717 SC",
    "addr:housenumber":"17",
    "addr:postcode":"6717",
    "addr:street":"Mondriaanstraat;Gld Gelderland",
    "iso:country":"NL",
    "sg:address":"Mondriaanstraat 17",
    "sg:city":"Ede Gld",
    "sg:orig_category":"Artsen And Specialisten",
    "sg:phone":"+31 318 636 369",
    "sg:postcode":"6717 SC",
    "sg:province":"Gelderland",
    "wof:name":"Huisartsenpraktijk E.E. Bouman",
    "wof:placetype":"venue"
},
  "geometry": {"coordinates":[5.654081,52.019115],"type":"Point"}
}