{
  "type": "Feature",
  "properties": {
    "addr:full":"Pannenweg 313 Nederweert Limburg 6031 RK",
    "addr:housenumber":"313",
    "addr:postcode":"6031 rk",
    "addr:street":"Pannenweg",
    "iso:country":"NL",
    "sg:address":"Pannenweg 313",
    "sg:city":"Nederweert",
    "sg:orig_category":"Werving And Selectie Van Tijdelijk Personeel And Uitzendkantoren",
    "sg:phone":"+31 495 461 571",
    "sg:postcode":"6031 RK",
    "sg:province":"Limburg",
    "wof:name":"Work-Team Uitzendbureau Bv",
    "wof:placetype":"venue"
},
  "geometry": {"coordinates":[5.7518758774,51.2762260437],"type":"Point"}
}