{
  "type": "Feature",
  "properties": {
    "addr:full":"Geestakker 46 Eindhoven Noord-Brabant 5625 XA",
    "addr:housenumber":"46",
    "addr:postcode":"5625 xa",
    "addr:street":"Geestakker",
    "iso:country":"NL",
    "sg:address":"Geestakker 46",
    "sg:city":"Eindhoven",
    "sg:orig_category":"Woningbouwverenigingen",
    "sg:phone":"+31 40 241 9160",
    "sg:postcode":"5625 XA",
    "sg:province":"Noord-Brabant",
    "wof:name":"Jurriaan Pels Wooncentrum",
    "wof:placetype":"venue"
},
  "geometry": {"coordinates":[5.4796991348,51.4683647156],"type":"Point"}
}