{
  "type": "Feature",
  "properties": {
    "iso:country":"NL",
    "sg:address":"Dorpsstr 63",
    "sg:city":"Vriescheloo",
    "sg:orig_category":"Loonbedrijven",
    "sg:phone":"+31 597 541 201",
    "sg:postcode":"9699 PB",
    "sg:province":"Groningen",
    "wof:name":"Meijer, B J",
    "wof:placetype":"venue"
},
  "geometry": {"coordinates":[7.130429,53.084797],"type":"Point"}
}