{
  "type": "Feature",
  "properties": {
    "addr:full":"Brouwerywg 6 Domburg Zeeland 4357 CE",
    "addr:housenumber":"6",
    "addr:postcode":"4357 ce",
    "addr:street":"Brouwerywg",
    "iso:country":"NL",
    "sg:address":"Brouwerywg 6",
    "sg:city":"Domburg",
    "sg:classifiers":[
        {
            "category":"Travel",
            "subcategory":"Hotels & Motels",
            "type":"Entertainment"
        }
    ],
    "sg:phone":"+31 118 581 285",
    "sg:postcode":"4357 CE",
    "sg:province":"Zeeland",
    "wof:name":"Brouwerij, De",
    "wof:placetype":"venue"
},
  "geometry": {"coordinates":[3.496668,51.561401],"type":"Point"}
}