{
  "type": "Feature",
  "properties": {
    "iso:country":"NL",
    "sg:address":"Kostverlorenkd 9",
    "sg:city":"Geldermalsen",
    "sg:orig_category":"Accountants - Administratie- Consulenten En -Kantoren",
    "sg:phone":"+31 345 575 933",
    "sg:postcode":"4191 CG",
    "sg:province":"Gelderland",
    "wof:name":"Alfa",
    "wof:placetype":"venue"
},
  "geometry": {"coordinates":[5.291876,51.884632],"type":"Point"}
}