{
  "type": "Feature",
  "properties": {
    "iso:country":"NL",
    "sg:address":"Prinses Mariannelaan 45",
    "sg:city":"Voorburg",
    "sg:orig_category":"Wegen And Sportterreinen",
    "sg:phone":"+31 70 386 0942",
    "sg:postcode":"2275 BA",
    "sg:province":"Zuid-Holland",
    "wof:name":"H P Tetteroo Wegenbouw Bv",
    "wof:placetype":"venue"
},
  "geometry": {"coordinates":[4.3539018631,52.0646324158],"type":"Point"}
}