{
  "type": "Feature",
  "properties": {
    "addr:full":"Klein Holtum 25 Buchten Limburg 6122 EG",
    "addr:housenumber":"25",
    "addr:postcode":"6122 eg",
    "addr:street":"Klein Holtum",
    "iso:country":"NL",
    "sg:address":"Klein Holtum 25",
    "sg:city":"Buchten",
    "sg:orig_category":"Verhuur Audiovisuele Apparatuur",
    "sg:phone":"+31 46 481 0288",
    "sg:postcode":"6122 EG",
    "sg:province":"Limburg",
    "wof:name":"J.W. Music Power",
    "wof:placetype":"venue"
},
  "geometry": {"coordinates":[5.814649,51.039604],"type":"Point"}
}