{
  "type": "Feature",
  "properties": {
    "addr:full":"Wibautstr 3 Amsterdam Noord-Holland 1091 GH",
    "addr:housenumber":"3",
    "addr:postcode":"1091 gh",
    "addr:street":"Wibautstr",
    "iso:country":"NL",
    "sg:address":"Wibautstr 3",
    "sg:city":"Amsterdam",
    "sg:orig_category":"Adviesbureaus",
    "sg:phone":"+31 20 851 3500",
    "sg:postcode":"1091 GH",
    "sg:province":"Noord-Holland",
    "wof:name":"Groundwater Bv",
    "wof:placetype":"venue"
},
  "geometry": {"coordinates":[4.909481,52.359039],"type":"Point"}
}