{
  "type": "Feature",
  "properties": {
    "iso:country":"NL",
    "sg:address":"Westerkd 19",
    "sg:city":"Utrecht",
    "sg:orig_category":"Verf En Lak",
    "sg:phone":"+31 30 234 0615",
    "sg:postcode":"3511 HB",
    "sg:province":"Utrecht",
    "wof:name":"Vergulde Kwast, De",
    "wof:placetype":"venue"
},
  "geometry": {"coordinates":[5.115405,52.088932],"type":"Point"}
}