{
  "type": "Feature",
  "properties": {
    "iso:country":"NL",
    "sg:address":"Middenweg 109-113 A",
    "sg:city":"Amsterdam",
    "sg:orig_category":"Meubelzaken, Woning- And Keukeninrichting",
    "sg:phone":"+31 20 663 1161",
    "sg:postcode":"1098 AH",
    "sg:province":"North Holland",
    "wof:name":"Easy Living Bv",
    "wof:placetype":"venue"
},
  "geometry": {"coordinates":[4.933281,52.3522],"type":"Point"}
}