{
  "type": "Feature",
  "properties": {
    "addr:full":"Brucknerplein 5 Eindhoven Noord-Brabant 5653 ER",
    "addr:housenumber":"5",
    "addr:postcode":"5653 er",
    "addr:street":"Brucknerplein",
    "iso:country":"NL",
    "sg:address":"Brucknerplein 5",
    "sg:city":"Eindhoven",
    "sg:orig_category":"Kappers",
    "sg:phone":"+31 40 251 1342",
    "sg:postcode":"5653 ER",
    "sg:province":"Noord-Brabant",
    "wof:name":"Kapsalon Judith & Erik",
    "wof:placetype":"venue"
},
  "geometry": {"coordinates":[5.451895237,51.4237480164],"type":"Point"}
}