{
  "type": "Feature",
  "properties": {
    "addr:full":"Meester Slootsweg 1 Waalre North Brabant 5581 AS",
    "addr:housenumber":"1",
    "addr:postcode":"5581 as",
    "addr:street":"Meester Slootsweg",
    "iso:country":"NL",
    "sg:address":"Meester Slootsweg 1",
    "sg:city":"Waalre",
    "sg:classifiers":[
        {
            "category":"Education",
            "subcategory":"Preschool",
            "type":"Public Place"
        }
    ],
    "sg:phone":"+31 40 221 3535",
    "sg:postcode":"5581 AS",
    "sg:province":"North Brabant",
    "sg:tags":[
        "kleuteronderwijs",
        "basis-"
    ],
    "wof:name":"Basisschool De Wilderen",
    "wof:placetype":"venue"
},
  "geometry": {"coordinates":[5.439698,51.387623],"type":"Point"}
}