{
  "type": "Feature",
  "properties": {
    "addr:full":"Vd B V Heems Wg 21 Voorhout Zuid-Holland 2215 RK",
    "addr:housenumber":"21",
    "addr:postcode":"2215 rk",
    "addr:street":"V;Wg",
    "iso:country":"NL",
    "sg:address":"Vd B V Heems Wg 21",
    "sg:city":"Voorhout",
    "sg:orig_category":"Kunststoffen - Fabrieken En Groothandel",
    "sg:phone":"+31 252 213 400",
    "sg:postcode":"2215 RK",
    "sg:province":"Zuid-Holland",
    "wof:name":"Moonen Bv",
    "wof:placetype":"venue"
},
  "geometry": {"coordinates":[4.48252,52.221874],"type":"Point"}
}