{
  "type": "Feature",
  "properties": {
    "addr:full":"Postbus 8 Rypwetering Zuid-Holland 2375 ZG",
    "addr:housenumber":"8",
    "addr:postcode":"2375 zg",
    "addr:street":"Postbus",
    "iso:country":"NL",
    "sg:address":"Postbus 8",
    "sg:city":"Rypwetering",
    "sg:orig_category":"Adviesbureaus",
    "sg:phone":"+31 71 501 3379",
    "sg:postcode":"2375 ZG",
    "sg:province":"Zuid-Holland",
    "wof:name":"Eyecatchers",
    "wof:placetype":"venue"
},
  "geometry": {"coordinates":[4.585019,52.190571],"type":"Point"}
}