{
  "type": "Feature",
  "properties": {
    "addr:full":"Prof Poelsstr 14 Hilversum North Holland 1221 HS",
    "addr:housenumber":"14",
    "addr:postcode":"1221 hs",
    "iso:country":"NL",
    "sg:address":"Prof Poelsstr 14",
    "sg:city":"Hilversum",
    "sg:orig_category":"Voetbalverenigingen",
    "sg:phone":"+31 35 685 2029",
    "sg:postcode":"1221 HS",
    "sg:province":"North Holland",
    "wof:name":"Fc Husky",
    "wof:placetype":"venue"
},
  "geometry": {"coordinates":[5.18388,52.225433],"type":"Point"}
}