{
  "type": "Feature",
  "properties": {
    "addr:full":"Beekstraat 17 Schinveld Limburg 6451 CA",
    "addr:housenumber":"17",
    "addr:postcode":"6451 ca",
    "addr:street":"Beekstraat",
    "iso:country":"NL",
    "sg:address":"Beekstraat 17",
    "sg:city":"Schinveld",
    "sg:orig_category":"Kappers",
    "sg:phone":"+31 45 525 5778",
    "sg:postcode":"6451 CA",
    "sg:province":"Limburg",
    "wof:name":"Lugin Schinveld Dames- En Herenkapsalon",
    "wof:placetype":"venue"
},
  "geometry": {"coordinates":[5.978224,50.969513],"type":"Point"}
}