{
  "type": "Feature",
  "properties": {
    "addr:full":"J F Kennedypln 29 Purmerend Noord-Holland 1443 EA",
    "addr:housenumber":"29",
    "addr:postcode":"1443 ea",
    "addr:street":"J F Kennedypln",
    "iso:country":"NL",
    "sg:address":"J F Kennedypln 29",
    "sg:city":"Purmerend",
    "sg:classifiers":[
        {
            "category":"Food & Beverages",
            "subcategory":"Bakery",
            "type":"Retail Goods"
        }
    ],
    "sg:phone":"+31 299 428 391",
    "sg:postcode":"1443 EA",
    "sg:province":"Noord-Holland",
    "sg:tags":[
        "brood",
        "en",
        "banket"
    ],
    "wof:name":"Kaandorp, S",
    "wof:placetype":"venue"
},
  "geometry": {"coordinates":[4.969733,52.509106],"type":"Point"}
}