{
  "type": "Feature",
  "properties": {
    "addr:full":"Eikenwg 14 Hoensbroek Limburg 6431 VZ",
    "addr:housenumber":"14",
    "addr:postcode":"6431 vz",
    "addr:street":"Eikenwg",
    "iso:country":"NL",
    "sg:address":"Eikenwg 14",
    "sg:city":"Hoensbroek",
    "sg:orig_category":"Woninginrichting",
    "sg:phone":"+31 45 521 5903",
    "sg:postcode":"6431 VZ",
    "sg:province":"Limburg",
    "wof:name":"Leurs Bv",
    "wof:placetype":"venue"
},
  "geometry": {"coordinates":[5.9327178001,50.9223747253],"type":"Point"}
}