{
  "type": "Feature",
  "properties": {
    "iso:country":"NL",
    "sg:address":"Weigelia 6",
    "sg:city":"Leidschendam",
    "sg:orig_category":"Woninginrichting",
    "sg:phone":"+31 70 327 2169",
    "sg:postcode":"2262 AB",
    "sg:province":"Zuid-Holland",
    "wof:name":"Ankerman",
    "wof:placetype":"venue"
},
  "geometry": {"coordinates":[4.3830289841,52.0878105164],"type":"Point"}
}