{
  "type": "Feature",
  "properties": {
    "addr:full":"Cesar Franckstraat 2 Delft South Holland 2625 BX",
    "addr:housenumber":"2",
    "addr:postcode":"2625 bx",
    "addr:street":"Cesar Franckstraat",
    "iso:country":"NL",
    "sg:address":"Cesar Franckstraat 2",
    "sg:city":"Delft",
    "sg:orig_category":"Verhuur Catering-, Feest- En Evenementbenodigdheden",
    "sg:phone":"+31 15 261 1599",
    "sg:postcode":"2625 BX",
    "sg:province":"South Holland",
    "wof:name":"W. Noordam",
    "wof:placetype":"venue"
},
  "geometry": {"coordinates":[4.336269,51.995068],"type":"Point"}
}