{
  "type": "Feature",
  "properties": {
    "addr:full":"S-Gravelandsevaartweg 9 Loosdrecht Noord-Holland 1231 NL",
    "addr:housenumber":"9",
    "addr:postcode":"1231 nl",
    "addr:street":"S-Gravelandsevaartweg",
    "iso:country":"NL",
    "sg:address":"S-Gravelandsevaartweg 9",
    "sg:city":"Loosdrecht",
    "sg:orig_category":"Bloemen And Planten",
    "sg:phone":"+31 35 656 4632",
    "sg:postcode":"1231 NL",
    "sg:province":"Noord-Holland",
    "wof:name":"Tomin Kwekerij Kerkelanden",
    "wof:placetype":"venue"
},
  "geometry": {"coordinates":[5.116663,52.213085],"type":"Point"}
}