{
  "type": "Feature",
  "properties": {
    "iso:country":"NL",
    "sg:address":"Marieken Van Nimwegenstr 11Hs",
    "sg:city":"Amsterdam",
    "sg:orig_category":"Artsen And Specialisten",
    "sg:phone":"+31 20 682 8078",
    "sg:postcode":"1055 BK",
    "sg:province":"North Holland",
    "wof:name":"Drs. L.M. Suij",
    "wof:placetype":"venue"
},
  "geometry": {"coordinates":[4.850201,52.376842],"type":"Point"}
}