{
  "type": "Feature",
  "properties": {
    "addr:full":"Stationswg 5 Anna Paulowna North Holland 1761 EB",
    "addr:housenumber":"5",
    "addr:postcode":"1761 eb",
    "addr:street":"Stationswg",
    "iso:country":"NL",
    "sg:address":"Stationswg 5",
    "sg:city":"Anna Paulowna",
    "sg:orig_category":"Verenigingen En Stichtingen",
    "sg:phone":"+31 223 532 147",
    "sg:postcode":"1761 EB",
    "sg:province":"North Holland",
    "wof:name":"Spoorbuurt",
    "wof:placetype":"venue"
},
  "geometry": {"coordinates":[4.83282,52.86256],"type":"Point"}
}