{
  "type": "Feature",
  "properties": {
    "iso:country":"NL",
    "sg:address":"Weisestraat 17",
    "sg:city":"Lithoijen",
    "sg:orig_category":"Landbouwmachines Gh",
    "sg:phone":"+31 412 481 301",
    "sg:postcode":"5396 NL",
    "sg:province":"Noord-Brabant",
    "wof:name":"V.D. Goor Machinehandel",
    "wof:placetype":"venue"
},
  "geometry": {"coordinates":[5.454038,51.788349],"type":"Point"}
}