{
  "type": "Feature",
  "properties": {
    "addr:full":"Oldebertwg 66 Tolbert Groningen 9356 AE",
    "addr:housenumber":"66",
    "addr:postcode":"9356 ae",
    "addr:street":"Oldebertwg",
    "iso:country":"NL",
    "sg:address":"Oldebertwg 66",
    "sg:city":"Tolbert",
    "sg:orig_category":"Beveiliging",
    "sg:phone":"+31 594 548 000",
    "sg:postcode":"9356 AE",
    "sg:province":"Groningen",
    "sg:website":"http://www.btn-beveiliging.nl",
    "wof:name":"Btn Beveiliging",
    "wof:placetype":"venue"
},
  "geometry": {"coordinates":[-99.414536,34.226662],"type":"Point"}
}