{
  "type": "Feature",
  "properties": {
    "addr:full":"Vondelstr 49 Son Noord-Brabant 5691 XB",
    "addr:housenumber":"49",
    "addr:postcode":"5691 xb",
    "addr:street":"Vondelstr",
    "iso:country":"NL",
    "sg:address":"Vondelstr 49",
    "sg:city":"Son",
    "sg:orig_category":"Orthopedagogen",
    "sg:phone":"+31 499 474 800",
    "sg:postcode":"5691 XB",
    "sg:province":"Noord-Brabant",
    "wof:name":"Boosten, J F G M",
    "wof:placetype":"venue"
},
  "geometry": {"coordinates":[-101.93762207029999,35.1896209717],"type":"Point"}
}