{
  "type": "Feature",
  "properties": {
    "addr:full":"Kaap Hoorndreef 56E Utrecht Utrecht 3563 AV",
    "addr:housenumber":"56e",
    "addr:postcode":"3563 av",
    "addr:street":"Kaap Hoorndreef",
    "iso:country":"NL",
    "sg:address":"Kaap Hoorndreef 56E",
    "sg:city":"Utrecht",
    "sg:orig_category":"Psychotherapeuten",
    "sg:phone":"+31 30 262 1487",
    "sg:postcode":"3563 AV",
    "sg:province":"Utrecht",
    "wof:name":"Centrum Voor Zijnsori\u00ebntatie",
    "wof:placetype":"venue"
},
  "geometry": {"coordinates":[5.105934,52.114738],"type":"Point"}
}