{
  "type": "Feature",
  "properties": {
    "addr:full":"V Ysendykstr 82 Purmerend Noord-Holland 1442 CR",
    "addr:housenumber":"82;1442",
    "addr:postcode":"cr",
    "iso:country":"NL",
    "sg:address":"V Ysendykstr 82",
    "sg:city":"Purmerend",
    "sg:orig_category":"Fotoapparatuur En -Artikelen - Groothandel",
    "sg:phone":"+31 299 432 287",
    "sg:postcode":"1442 CR",
    "sg:province":"Noord-Holland",
    "sg:website":"http://www.pwiersma.nl",
    "wof:name":"Wiersma-Techniek Bv",
    "wof:placetype":"venue"
},
  "geometry": {"coordinates":[4.94793,52.507607],"type":"Point"}
}