{
  "type": "Feature",
  "properties": {
    "addr:full":"Buitendk 10 Helmond North Brabant 5705 CD",
    "addr:housenumber":"10",
    "addr:postcode":"5705 cd",
    "addr:street":"Buitendk",
    "iso:country":"NL",
    "sg:address":"Buitendk 10",
    "sg:city":"Helmond",
    "sg:orig_category":"Verpakkingsbedrijven",
    "sg:phone":"+31 492 536 405",
    "sg:postcode":"5705 CD",
    "sg:province":"North Brabant",
    "wof:name":"Profi Pack Bv",
    "wof:placetype":"venue"
},
  "geometry": {"coordinates":[5.683401,51.469189],"type":"Point"}
}