{
  "type": "Feature",
  "properties": {
    "addr:full":"Veltumse Kleffen 52 Venray Limburg 5801 SH",
    "addr:housenumber":"52;5801",
    "addr:postcode":"sh",
    "addr:street":"Veltumse Kleffen",
    "iso:country":"NL",
    "sg:address":"Veltumse Kleffen 52",
    "sg:city":"Venray",
    "sg:orig_category":"Sportverenigingen En Ontspannings- Verenigingen",
    "sg:phone":"+31 478 587 620",
    "sg:postcode":"5801 SH",
    "sg:province":"Limburg",
    "wof:name":"Dynamic",
    "wof:placetype":"venue"
},
  "geometry": {"coordinates":[5.964971,51.51926],"type":"Point"}
}