{
  "type": "Feature",
  "properties": {
    "addr:full":"Bremerheide 10 Wynjewoude Friesland 9241 EJ",
    "addr:housenumber":"10",
    "addr:postcode":"9241 ej",
    "addr:street":"Bremerheide",
    "iso:country":"NL",
    "sg:address":"Bremerheide 10",
    "sg:city":"Wynjewoude",
    "sg:orig_category":"Autopoetsbedrijven",
    "sg:phone":"+31 516 481 195",
    "sg:postcode":"9241 EJ",
    "sg:province":"Friesland",
    "wof:name":"Nutterts, H",
    "wof:placetype":"venue"
},
  "geometry": {"coordinates":[6.207635,53.055248],"type":"Point"}
}