{
  "type": "Feature",
  "properties": {
    "addr:full":"Barwoutswaarder 30 Woerden South Holland 3449 HM",
    "addr:housenumber":"30",
    "addr:postcode":"3449 hm",
    "addr:street":"Barwoutswaarder",
    "iso:country":"NL",
    "sg:address":"Barwoutswaarder 30",
    "sg:city":"Woerden",
    "sg:orig_category":"Horecabenodigdheden",
    "sg:phone":"+31 348 480 861",
    "sg:postcode":"3449 HM",
    "sg:province":"South Holland",
    "wof:name":"Setten, M F Van",
    "wof:placetype":"venue"
},
  "geometry": {"coordinates":[4.864609,52.085606],"type":"Point"}
}