{
  "type": "Feature",
  "properties": {
    "addr:full":"Einderstr 29 Wittem Limburg 6286 BJ",
    "addr:housenumber":"29",
    "addr:postcode":"6286 bj",
    "addr:street":"Einderstr",
    "iso:country":"NL",
    "sg:address":"Einderstr 29",
    "sg:city":"Wittem",
    "sg:orig_category":"Adviesbureaus Bedrijfsorganisatie",
    "sg:phone":"+31 43 451 1322",
    "sg:postcode":"6286 BJ",
    "sg:province":"Limburg",
    "wof:name":"Corten",
    "wof:placetype":"venue"
},
  "geometry": {"coordinates":[5.939902,50.810894],"type":"Point"}
}