{
  "type": "Feature",
  "properties": {
    "addr:full":"Buitenkade 14 Nieuwendijk Nb Noord-Brabant 4255 GW",
    "addr:housenumber":"14",
    "addr:postcode":"4255 gw",
    "addr:street":"Buitenkade",
    "iso:country":"NL",
    "sg:address":"Buitenkade 14",
    "sg:city":"Nieuwendijk Nb",
    "sg:orig_category":"Verhuur Bouwmachines",
    "sg:phone":"+31 183 403 953",
    "sg:postcode":"4255 GW",
    "sg:province":"Noord-Brabant",
    "wof:name":"A.C.E. Nieuwendijk Bv",
    "wof:placetype":"venue"
},
  "geometry": {"coordinates":[4.926717,51.769127],"type":"Point"}
}