{
  "type": "Feature",
  "properties": {
    "addr:full":"De Ruyterstr 86 Oudeschild Noord-Holland 1792 AM",
    "addr:housenumber":"86",
    "addr:postcode":"1792",
    "iso:country":"NL",
    "sg:address":"De Ruyterstr 86",
    "sg:city":"Oudeschild",
    "sg:orig_category":"Verloskundigen",
    "sg:phone":"+31 222 313 090",
    "sg:postcode":"1792 AM",
    "sg:province":"Noord-Holland",
    "wof:name":"Verloskundigen Praktijk Texel",
    "wof:placetype":"venue"
},
  "geometry": {"coordinates":[4.841892,53.033932],"type":"Point"}
}