{
  "type": "Feature",
  "properties": {
    "addr:full":"Oudestr 73 Kampen Overijssel 8261 CG",
    "addr:housenumber":"73",
    "addr:postcode":"8261 cg",
    "addr:street":"Oudestr",
    "iso:country":"NL",
    "sg:address":"Oudestr 73",
    "sg:city":"Kampen",
    "sg:orig_category":"Kinderkleding",
    "sg:phone":"+31 38 333 2426",
    "sg:postcode":"8261 CG",
    "sg:province":"Overijssel",
    "wof:name":"Color For Kids Kampen",
    "wof:placetype":"venue"
},
  "geometry": {"coordinates":[5.918229,52.557152],"type":"Point"}
}