{
  "type": "Feature",
  "properties": {
    "addr:full":"Grebbe 40 Tilburg North Brabant 5032 RT",
    "addr:housenumber":"40",
    "addr:postcode":"5032 rt",
    "addr:street":"Grebbe",
    "iso:country":"NL",
    "sg:address":"Grebbe 40",
    "sg:city":"Tilburg",
    "sg:classifiers":[
        {
            "category":"Education",
            "subcategory":"Preschool",
            "type":"Public Place"
        }
    ],
    "sg:phone":"+31 13 467 5632",
    "sg:postcode":"5032 RT",
    "sg:province":"North Brabant",
    "sg:tags":[
        "kleuteronderwijs",
        "basis-"
    ],
    "wof:name":"Basisschool De Borne",
    "wof:placetype":"venue"
},
  "geometry": {"coordinates":[5.045417,51.545876],"type":"Point"}
}