{
  "type": "Feature",
  "properties": {
    "addr:full":"Veldstr 26 Ulft Gelderland 7071 CC",
    "addr:housenumber":"26",
    "addr:postcode":"7071 cc",
    "addr:street":"Veldstr;Gelderland",
    "iso:country":"NL",
    "sg:address":"Veldstr 26",
    "sg:city":"Ulft",
    "sg:orig_category":"Geluidsinstallaties - Verhuur",
    "sg:phone":"+31 315 683 000",
    "sg:postcode":"7071 CC",
    "sg:province":"Gelderland",
    "wof:name":"Overbeek",
    "wof:placetype":"venue"
},
  "geometry": {"coordinates":[6.383795,51.889641],"type":"Point"}
}