{
  "type": "Feature",
  "properties": {
    "addr:full":"Min Lelyln 1F Ryswyk Zh Zuid-Holland 2285 HG",
    "addr:housenumber":"1f",
    "addr:postcode":"2285 hg",
    "addr:street":"Ryswyk",
    "iso:country":"NL",
    "sg:address":"Min Lelyln 1F",
    "sg:city":"Ryswyk Zh",
    "sg:orig_category":"Machineonderhoud En -Reparatie",
    "sg:phone":"+31 70 335 9787",
    "sg:postcode":"2285 HG",
    "sg:province":"Zuid-Holland",
    "wof:name":"Artsencrafts Bv",
    "wof:placetype":"venue"
},
  "geometry": {"coordinates":[4.32436,52.037251],"type":"Point"}
}