{
  "type": "Feature",
  "properties": {
    "iso:country":"NL",
    "sg:address":"Coltermanln 28",
    "sg:city":"Heerhugowaard",
    "sg:orig_category":"Vertalers",
    "sg:phone":"+31 72 571 0161",
    "sg:postcode":"1701 AD",
    "sg:province":"Noord-Holland",
    "wof:name":"Graaf, C L M De",
    "wof:placetype":"venue"
},
  "geometry": {"coordinates":[4.847981,52.67527],"type":"Point"}
}