{
  "type": "Feature",
  "properties": {
    "addr:full":"Ged Oude Gr 100 Haarlem Noord-Holland 2011 GW",
    "addr:housenumber":"100",
    "addr:postcode":"2011 gw",
    "addr:street":"Oude Gr",
    "iso:country":"NL",
    "sg:address":"Ged Oude Gr 100",
    "sg:city":"Haarlem",
    "sg:orig_category":"Woninginrichting",
    "sg:phone":"+31 23 531 5402",
    "sg:postcode":"2011 GW",
    "sg:province":"Noord-Holland",
    "wof:name":"Dubo",
    "wof:placetype":"venue"
},
  "geometry": {"coordinates":[4.6345157623,52.3785247803],"type":"Point"}
}