{
  "type": "Feature",
  "properties": {
    "addr:full":"Schoenmakersstraat 24 Roermond Limburg 6041 EZ",
    "addr:housenumber":"24",
    "addr:postcode":"6041 ez",
    "addr:street":"Schoenmakersstraat",
    "iso:country":"NL",
    "sg:address":"Schoenmakersstraat 24",
    "sg:city":"Roermond",
    "sg:orig_category":"Verlichting And Huishoudartikelen",
    "sg:phone":"+31 475 311 128",
    "sg:postcode":"6041 EZ",
    "sg:province":"Limburg",
    "wof:name":"Joosten Verlichtingsspeciaalzaak",
    "wof:placetype":"venue"
},
  "geometry": {"coordinates":[5.987541,51.194851],"type":"Point"}
}