{
  "type": "Feature",
  "properties": {
    "addr:full":"Zevenkampse Ring 400 Rotterdam Zuid-Holland 3068 HG",
    "addr:housenumber":"400",
    "addr:postcode":"3068 hg",
    "addr:street":"Zevenkampse Ring",
    "iso:country":"NL",
    "sg:address":"Zevenkampse Ring 400",
    "sg:city":"Rotterdam",
    "sg:orig_category":"Gehandicapten - Hulpmiddelen",
    "sg:phone":"+31 10 286 2620",
    "sg:postcode":"3068 HG",
    "sg:province":"Zuid-Holland",
    "wof:name":"Steinmetz",
    "wof:placetype":"venue"
},
  "geometry": {"coordinates":[4.571843,51.963619],"type":"Point"}
}