{
  "type": "Feature",
  "properties": {
    "addr:full":"Kraan 6 Nederweert Limburg 6031 RX",
    "addr:housenumber":"6",
    "addr:postcode":"6031 rx",
    "addr:street":"Kraan",
    "iso:country":"NL",
    "sg:address":"Kraan 6",
    "sg:city":"Nederweert",
    "sg:orig_category":"Zalenverhuur",
    "sg:phone":"+31 495 632 151",
    "sg:postcode":"6031 RX",
    "sg:province":"Limburg",
    "wof:name":"Briels",
    "wof:placetype":"venue"
},
  "geometry": {"coordinates":[5.75805,51.260761],"type":"Point"}
}