{
  "type": "Feature",
  "properties": {
    "addr:full":"Losplaatsweg 8 Noordwijk Zh Zuid-Holland 2201 CV",
    "addr:housenumber":"8",
    "addr:postcode":"2201 cv",
    "addr:street":"Losplaatsweg",
    "iso:country":"NL",
    "sg:address":"Losplaatsweg 8",
    "sg:city":"Noordwijk Zh",
    "sg:orig_category":"Metaalwerken",
    "sg:phone":"+31 71 364 6994",
    "sg:postcode":"2201 CV",
    "sg:province":"Zuid-Holland",
    "wof:name":"Progenta Projektservices Bv",
    "wof:placetype":"venue"
},
  "geometry": {"coordinates":[4.441899,52.233307],"type":"Point"}
}