{
  "type": "Feature",
  "properties": {
    "addr:full":"De Kempenaerstr 59 Oegstgeest Zuid-Holland 2341 GH",
    "addr:housenumber":"59",
    "addr:postcode":"2341 gh",
    "iso:country":"NL",
    "sg:address":"De Kempenaerstr 59",
    "sg:city":"Oegstgeest",
    "sg:orig_category":"Woninginrichting",
    "sg:phone":"+31 71 523 7251",
    "sg:postcode":"2341 GH",
    "sg:province":"Zuid-Holland",
    "wof:name":"Binnenhuys, 'T",
    "wof:placetype":"venue"
},
  "geometry": {"coordinates":[4.4712018967,52.1777000427],"type":"Point"}
}