{
  "type": "Feature",
  "properties": {
    "addr:full":"Oorgat 110 Edam North Holland 1135 CT",
    "addr:housenumber":"110",
    "addr:postcode":"1135 ct",
    "addr:street":"Oorgat",
    "iso:country":"NL",
    "sg:address":"Oorgat 110",
    "sg:city":"Edam",
    "sg:orig_category":"Technische Studies And Onderzoek",
    "sg:phone":"+31 299 373 169",
    "sg:postcode":"1135 CT",
    "sg:province":"North Holland",
    "wof:name":"Thermografisch Adviesbureau Van Den Hove Bv",
    "wof:placetype":"venue"
},
  "geometry": {"coordinates":[5.058707,52.51405],"type":"Point"}
}