{
  "type": "Feature",
  "properties": {
    "addr:full":"Exloerkyl Z 49 Tweede Exloermond Drenthe 9571 AC",
    "addr:postcode":"9571 ac",
    "addr:street":"Tweede Exloermond",
    "iso:country":"NL",
    "sg:address":"Exloerkyl Z 49",
    "sg:city":"Tweede Exloermond",
    "sg:orig_category":"Kappers",
    "sg:phone":"+31 599 671 420",
    "sg:postcode":"9571 AC",
    "sg:province":"Drenthe",
    "wof:name":"Trea",
    "wof:placetype":"venue"
},
  "geometry": {"coordinates":[6.923037,52.895828],"type":"Point"}
}