{
  "type": "Feature",
  "properties": {
    "addr:full":"Tweede Oosterparkstraat 33 Amsterdam North Holland 1091 HV",
    "addr:housenumber":"33",
    "addr:postcode":"1091 hv",
    "addr:street":"Tweede Oosterparkstraat",
    "iso:country":"NL",
    "sg:address":"Tweede Oosterparkstraat 33",
    "sg:city":"Amsterdam",
    "sg:classifiers":[
        {
            "category":"Education",
            "subcategory":"Preschool",
            "type":"Public Place"
        }
    ],
    "sg:phone":"+31 20 694 0708",
    "sg:postcode":"1091 HV",
    "sg:province":"North Holland",
    "sg:tags":[
        "kleuteronderwijs",
        "basis-"
    ],
    "wof:name":"Louise De Colignyschool",
    "wof:placetype":"venue"
},
  "geometry": {"coordinates":[4.9131,52.356205],"type":"Point"}
}