{
  "type": "Feature",
  "properties": {
    "iso:country":"NL",
    "sg:address":"Prins Mauritsplein 36",
    "sg:city":"Hoogeveen",
    "sg:orig_category":"Metaalwerken",
    "sg:phone":"+31 528 234 450",
    "sg:postcode":"7902 AG",
    "sg:province":"Drenthe",
    "wof:name":"Damen Projectinrichting Bv",
    "wof:placetype":"venue"
},
  "geometry": {"coordinates":[6.478172,52.730343],"type":"Point"}
}