{
  "type": "Feature",
  "properties": {
    "addr:full":"Dammolen 94 Harmelen Utrecht 3481 AP",
    "addr:housenumber":"94",
    "addr:postcode":"3481 ap",
    "addr:street":"Dammolen",
    "iso:country":"NL",
    "sg:address":"Dammolen 94",
    "sg:city":"Harmelen",
    "sg:orig_category":"Adviesbureaus Waterbouwkunde",
    "sg:phone":"+31 348 442 198",
    "sg:postcode":"3481 AP",
    "sg:province":"Utrecht",
    "wof:name":"Gering",
    "wof:placetype":"venue"
},
  "geometry": {"coordinates":[4.968952,52.085968],"type":"Point"}
}