{
  "type": "Feature",
  "properties": {
    "addr:full":"Duinkerkenstr 14 Groningen Groningen 9723 BR",
    "addr:housenumber":"14",
    "addr:postcode":"9723 br",
    "addr:street":"Duinkerkenstr",
    "iso:country":"NL",
    "sg:address":"Duinkerkenstr 14",
    "sg:city":"Groningen",
    "sg:orig_category":"Verbouwingen",
    "sg:phone":"+31 50 313 6565",
    "sg:postcode":"9723 BR",
    "sg:province":"Groningen",
    "wof:name":"Kooi Bouwbedrijf Bv, B",
    "wof:placetype":"venue"
},
  "geometry": {"coordinates":[6.597564,53.201477],"type":"Point"}
}