{
  "type": "Feature",
  "properties": {
    "addr:full":"Grote Dk 26 Breda Noord-Brabant 4823 EG",
    "addr:housenumber":"26",
    "addr:postcode":"4823 eg",
    "addr:street":"Grote Dk",
    "iso:country":"NL",
    "sg:address":"Grote Dk 26",
    "sg:city":"Breda",
    "sg:orig_category":"Koeriersdiensten",
    "sg:phone":"+31 76 542 9347",
    "sg:postcode":"4823 EG",
    "sg:province":"Noord-Brabant",
    "wof:name":"Kbl",
    "wof:placetype":"venue"
},
  "geometry": {"coordinates":[4.749161,51.623924],"type":"Point"}
}