{
  "type": "Feature",
  "properties": {
    "addr:full":"De Hulk 4 Berkhout North Holland 1647 DR",
    "addr:housenumber":"4",
    "addr:postcode":"1647 dr",
    "addr:street":"De Hulk",
    "iso:country":"NL",
    "sg:address":"De Hulk 4",
    "sg:city":"Berkhout",
    "sg:orig_category":"Koeltechniek",
    "sg:phone":"+31 229 553 381",
    "sg:postcode":"1647 DR",
    "sg:province":"North Holland",
    "wof:name":"Grenco Transportkoeling Bv",
    "wof:placetype":"venue"
},
  "geometry": {"coordinates":[5.008891,52.62981],"type":"Point"}
}