{
  "type": "Feature",
  "properties": {
    "addr:full":"Disselvoorde 13 Spijkenisse Zuid-Holland 3204 SE",
    "addr:housenumber":"13",
    "addr:postcode":"3204 se",
    "addr:street":"Disselvoorde",
    "iso:country":"NL",
    "sg:address":"Disselvoorde 13",
    "sg:city":"Spijkenisse",
    "sg:orig_category":"Kledingaccessoires",
    "sg:phone":"+31 181 649 004",
    "sg:postcode":"3204 SE",
    "sg:province":"Zuid-Holland",
    "wof:name":"Mar-Soer Vof",
    "wof:placetype":"venue"
},
  "geometry": {"coordinates":[4.3223,51.834064],"type":"Point"}
}