{
  "type": "Feature",
  "properties": {
    "iso:country":"NL",
    "sg:address":"Herengr 104",
    "sg:city":"Amsterdam",
    "sg:orig_category":"Mode-Artikelen Dames En Heren",
    "sg:phone":"+31 20 422 1187",
    "sg:postcode":"1015 BS",
    "sg:province":"North Holland",
    "wof:name":"Ferragamo Int Bv",
    "wof:placetype":"venue"
},
  "geometry": {"coordinates":[4.888722,52.376236],"type":"Point"}
}