{
  "type": "Feature",
  "properties": {
    "addr:full":"Graaf Hendrikstraat 2 Steenbergen Nb North Brabant 4651 TB",
    "addr:housenumber":"2;nb",
    "addr:postcode":"4651 tb",
    "addr:street":"Graaf Hendrikstraat",
    "iso:country":"NL",
    "sg:address":"Graaf Hendrikstraat 2",
    "sg:city":"Steenbergen Nb",
    "sg:orig_category":"Hout Gh",
    "sg:phone":"+31 167 563 850",
    "sg:postcode":"4651 TB",
    "sg:province":"North Brabant",
    "wof:name":"Pontmeyer Steenbergen Bv",
    "wof:placetype":"venue"
},
  "geometry": {"coordinates":[4.347091,51.591],"type":"Point"}
}