{
  "type": "Feature",
  "properties": {
    "addr:full":"Arnhemseweg 45 Amersfoort Utrecht 3817 CA",
    "addr:housenumber":"45",
    "addr:postcode":"3817 ca",
    "addr:street":"Arnhemseweg",
    "iso:country":"NL",
    "sg:address":"Arnhemseweg 45",
    "sg:city":"Amersfoort",
    "sg:orig_category":"Kappers",
    "sg:phone":"+31 33 461 9809",
    "sg:postcode":"3817 CA",
    "sg:province":"Utrecht",
    "wof:name":"Salon Jeunesse",
    "wof:placetype":"venue"
},
  "geometry": {"coordinates":[5.385736,52.149246],"type":"Point"}
}