{
  "type": "Feature",
  "properties": {
    "addr:full":"V Hogendorpstr 105 Schiedam Zuid-Holland 3118 LG",
    "addr:housenumber":"105",
    "addr:postcode":"3118 lg",
    "iso:country":"NL",
    "sg:address":"V Hogendorpstr 105",
    "sg:city":"Schiedam",
    "sg:orig_category":"Scholen Voor Basisonderwijs",
    "sg:phone":"+31 10 273 2506",
    "sg:postcode":"3118 LG",
    "sg:province":"Zuid-Holland",
    "wof:name":"Centrale Opvang Neveninstromers",
    "wof:placetype":"venue"
},
  "geometry": {"coordinates":[4.3981599808,51.91847229],"type":"Point"}
}