{
  "type": "Feature",
  "properties": {
    "addr:full":"Slotln 18 Capelle Ad Yssel Zuid-Holland 2902 AM",
    "addr:housenumber":"18",
    "addr:postcode":"2902",
    "addr:street":"Slotln",
    "iso:country":"NL",
    "sg:address":"Slotln 18",
    "sg:city":"Capelle Ad Yssel",
    "sg:orig_category":"Adviesbureaus Bedrijfsorganisatie",
    "sg:phone":"+31 10 451 0222",
    "sg:postcode":"2902 AM",
    "sg:province":"Zuid-Holland",
    "wof:name":"Craig, Duncan",
    "wof:placetype":"venue"
},
  "geometry": {"coordinates":[4.57697,51.926311],"type":"Point"}
}