{
  "type": "Feature",
  "properties": {
    "addr:full":"Dorpsstraat 14 Vlieland Provincie Friesland 8899 AH",
    "addr:housenumber":"14",
    "addr:postcode":"8899 ah",
    "addr:street":"Dorpsstraat;Provincie Friesland",
    "iso:country":"NL",
    "sg:address":"Dorpsstraat 14",
    "sg:city":"Vlieland",
    "sg:orig_category":"Visspeciaalzaken",
    "sg:phone":"+31 562 451 692",
    "sg:postcode":"8899 AH",
    "sg:province":"Provincie Friesland",
    "wof:name":"Viswinkel Het Anker",
    "wof:placetype":"venue"
},
  "geometry": {"coordinates":[5.074077,53.29652],"type":"Point"}
}