{
  "type": "Feature",
  "properties": {
    "addr:full":"Mercuriusstr 9 Spykenisse South Holland 3204 BM",
    "addr:housenumber":"9",
    "addr:postcode":"3204 bm",
    "addr:street":"Mercuriusstr",
    "iso:country":"NL",
    "sg:address":"Mercuriusstr 9",
    "sg:city":"Spykenisse",
    "sg:orig_category":"Montagebedrijven",
    "sg:phone":"+31 181 615 935",
    "sg:postcode":"3204 BM",
    "sg:province":"South Holland",
    "wof:name":"Spoel, Van Der",
    "wof:placetype":"venue"
},
  "geometry": {"coordinates":[4.3231,51.838711],"type":"Point"}
}