{
  "type": "Feature",
  "properties": {
    "addr:full":"Vondelln 124 Utrecht Utrecht 3521 GH",
    "addr:housenumber":"124",
    "addr:postcode":"3521 gh",
    "iso:country":"NL",
    "sg:address":"Vondelln 124",
    "sg:city":"Utrecht",
    "sg:orig_category":"Adviesbureaus Bouwkunde",
    "sg:phone":"+31 30 281 9880",
    "sg:postcode":"3521 GH",
    "sg:province":"Utrecht",
    "sg:website":"http://www.gpzadvies.nl",
    "wof:name":"Gpz",
    "wof:placetype":"venue"
},
  "geometry": {"coordinates":[5.11037,52.084572],"type":"Point"}
}