{
  "type": "Feature",
  "properties": {
    "addr:full":"Loerikseweg 17 Houten Utrecht 3991 AA",
    "addr:housenumber":"17",
    "addr:postcode":"3991 aa",
    "addr:street":"Loerikseweg",
    "iso:country":"NL",
    "sg:address":"Loerikseweg 17",
    "sg:city":"Houten",
    "sg:orig_category":"Architecten",
    "sg:phone":"+31 30 637 2332",
    "sg:postcode":"3991 AA",
    "sg:province":"Utrecht",
    "wof:name":"Architectenbureau Huub Van Der Zee",
    "wof:placetype":"venue"
},
  "geometry": {"coordinates":[5.165074,52.02607],"type":"Point"}
}