{
  "type": "Feature",
  "properties": {
    "iso:country":"NL",
    "sg:address":"Heer Halewynburg 9",
    "sg:city":"Capelle Ad Yssel",
    "sg:orig_category":"Begrafenisverzorging",
    "sg:phone":"+31 800 0231010",
    "sg:postcode":"2907 HA",
    "sg:province":"Zuid-Holland",
    "wof:name":"Memoriam",
    "wof:placetype":"venue"
},
  "geometry": {"coordinates":[4.580174,51.948826],"type":"Point"}
}