{
  "type": "Feature",
  "properties": {
    "iso:country":"NL",
    "sg:address":"Batjanstr 3",
    "sg:city":"S Gravenhage",
    "sg:orig_category":"Fotografie Reclame En Mode",
    "sg:phone":"+31 70 306 3458",
    "sg:postcode":"2585 VR",
    "sg:province":"South Holland",
    "wof:name":"Ruud Visser",
    "wof:placetype":"venue"
},
  "geometry": {"coordinates":[4.29777,52.094799],"type":"Point"}
}