{
  "type": "Feature",
  "properties": {
    "iso:country":"NL",
    "sg:address":"Kennemerstrwg 116",
    "sg:city":"Alkmaar",
    "sg:orig_category":"Muziekinstrumenten En Bladmuziek",
    "sg:phone":"+31 72 511 0879",
    "sg:postcode":"1815 LD",
    "sg:province":"North Holland",
    "sg:website":"http://www.alfredverhoef.nl",
    "wof:name":"Alfred Verhoef Houtblaasinstr",
    "wof:placetype":"venue"
},
  "geometry": {"coordinates":[4.746258,52.634361],"type":"Point"}
}