{
  "type": "Feature",
  "properties": {
    "addr:full":"Langstraat 61 Wijhe Overijssel 8131 BB",
    "addr:housenumber":"61",
    "addr:postcode":"8131 bb",
    "addr:street":"Langstraat",
    "iso:country":"NL",
    "sg:address":"Langstraat 61",
    "sg:city":"Wijhe",
    "sg:orig_category":"Damesmodezaken",
    "sg:phone":"+31 570 521 253",
    "sg:postcode":"8131 BB",
    "sg:province":"Overijssel",
    "wof:name":"Modehuis Elferink Vof",
    "wof:placetype":"venue"
},
  "geometry": {"coordinates":[6.13596,52.387089],"type":"Point"}
}