{
  "type": "Feature",
  "properties": {
    "addr:full":"Aduarderdieps Wg 14-2 Groningen Groningen 9745 EM",
    "addr:housenumber":"14-2",
    "addr:postcode":"9745 em",
    "addr:street":"Wg",
    "iso:country":"NL",
    "sg:address":"Aduarderdieps Wg 14-2",
    "sg:city":"Groningen",
    "sg:orig_category":"Wegenbouw",
    "sg:phone":"+31 50 551 5455",
    "sg:postcode":"9745 EM",
    "sg:province":"Groningen",
    "wof:name":"Westerman Bv, K",
    "wof:placetype":"venue"
},
  "geometry": {"coordinates":[6.4843201637,53.2209091187],"type":"Point"}
}