{
  "type": "Feature",
  "properties": {
    "addr:full":"Nobelstraat 24 Heerlen Limburg 6411 EN",
    "addr:housenumber":"24",
    "addr:postcode":"6411 en",
    "addr:street":"Nobelstraat",
    "iso:country":"NL",
    "sg:address":"Nobelstraat 24",
    "sg:city":"Heerlen",
    "sg:orig_category":"Boekhouders",
    "sg:phone":"+31 45 571 7650",
    "sg:postcode":"6411 EN",
    "sg:province":"Limburg",
    "wof:name":"Administratiekantoor Wigman",
    "wof:placetype":"venue"
},
  "geometry": {"coordinates":[5.979419,50.884789],"type":"Point"}
}