{
  "type": "Feature",
  "properties": {
    "iso:country":"NL",
    "sg:address":"Hoofschestraat 12",
    "sg:city":"Grave",
    "sg:orig_category":"Kappers",
    "sg:phone":"+31 486 473 540",
    "sg:postcode":"5361 EV",
    "sg:province":"Louisiana",
    "wof:name":"Dames- En Herensalon De Kapperij",
    "wof:placetype":"venue"
},
  "geometry": {"coordinates":[-92.1517410278,32.9292526245],"type":"Point"}
}