{
  "type": "Feature",
  "properties": {
    "addr:full":"Merwedestraat 8 Maasdam Zuid-Holland 3299 XD",
    "addr:housenumber":"8",
    "addr:postcode":"3299 xd",
    "addr:street":"Merwedestraat",
    "iso:country":"NL",
    "sg:address":"Merwedestraat 8",
    "sg:city":"Maasdam",
    "sg:orig_category":"Boekhouders",
    "sg:phone":"+31 78 676 4818",
    "sg:postcode":"3299 XD",
    "sg:province":"Zuid-Holland",
    "wof:name":"Administratiekantoor Kwikkers",
    "wof:placetype":"venue"
},
  "geometry": {"coordinates":[4.553237,51.791893],"type":"Point"}
}