{
  "type": "Feature",
  "properties": {
    "iso:country":"NL",
    "sg:address":"Vierhuysen 30",
    "sg:city":"Diemen",
    "sg:orig_category":"Merkenbureaus",
    "sg:phone":"+31 20 695 3201",
    "sg:postcode":"1111 SC",
    "sg:province":"Noord-Holland",
    "wof:name":"Pinpoint",
    "wof:placetype":"venue"
},
  "geometry": {"coordinates":[-80.947441,33.624981],"type":"Point"}
}