{
  "type": "Feature",
  "properties": {
    "addr:full":"Wynkamp 3 Goor Ov NL.08 7471 CA",
    "addr:housenumber":"3",
    "addr:postcode":"7471 ca",
    "addr:street":"Wynkamp;Ov",
    "iso:country":"NL",
    "sg:address":"Wynkamp 3",
    "sg:city":"Goor Ov",
    "sg:orig_category":"Paramedische Behandelingen",
    "sg:phone":"+31 547 261 303",
    "sg:postcode":"7471 CA",
    "sg:province":"NL.08",
    "wof:name":"Podosupplies",
    "wof:placetype":"venue"
},
  "geometry": {"coordinates":[6.587045,52.234573],"type":"Point"}
}