{
  "type": "Feature",
  "properties": {
    "addr:full":"Karveel 2230 Lelystad Flevoland 8231 BG",
    "addr:postcode":"2230;8231",
    "addr:street":"Karveel;Flevoland",
    "iso:country":"NL",
    "sg:address":"Karveel 2230",
    "sg:city":"Lelystad",
    "sg:orig_category":"Verenigingen En Stichtingen",
    "sg:phone":"+31 320 282 152",
    "sg:postcode":"8231 BG",
    "sg:province":"Flevoland",
    "wof:name":"Fauna",
    "wof:placetype":"venue"
},
  "geometry": {"coordinates":[5.46658,52.523251],"type":"Point"}
}