{
  "type": "Feature",
  "properties": {
    "iso:country":"NL",
    "sg:address":"Voorstr 17",
    "sg:city":"Makkum Fr",
    "sg:orig_category":"Watersportartikelen",
    "sg:phone":"+31 515 230 333",
    "sg:postcode":"8754 EV",
    "sg:province":"Friesland",
    "wof:name":"Silerswaar",
    "wof:placetype":"venue"
},
  "geometry": {"coordinates":[5.403386116,53.0549812317],"type":"Point"}
}