{
  "type": "Feature",
  "properties": {
    "iso:country":"NL",
    "sg:address":"Piet Van Thielplein 30",
    "sg:city":"Beek En Donk",
    "sg:orig_category":"Supermarkten",
    "sg:phone":"+31 492 461 655",
    "sg:postcode":"5741 CP",
    "sg:province":"Noord-Brabant",
    "wof:name":"Edah",
    "wof:placetype":"venue"
},
  "geometry": {"coordinates":[5.628791,51.538437],"type":"Point"}
}