{
  "type": "Feature",
  "properties": {
    "addr:full":"Jan Pieter Heijestraat 77 Amsterdam Noord-Holland 1053 GM",
    "addr:housenumber":"77",
    "addr:postcode":"1053 gm",
    "addr:street":"Jan Pieter Heijestraat",
    "iso:country":"NL",
    "sg:address":"Jan Pieter Heijestraat 77",
    "sg:city":"Amsterdam",
    "sg:orig_category":"Boekhandels",
    "sg:phone":"+31 20 612 6007",
    "sg:postcode":"1053 GM",
    "sg:province":"Noord-Holland",
    "wof:name":"M.C. Beumer",
    "wof:placetype":"venue"
},
  "geometry": {"coordinates":[4.863123,52.364208],"type":"Point"}
}