{
  "type": "Feature",
  "properties": {
    "addr:full":"Pr Mauritsln 8 S Gravenhage South Holland 2582 LR",
    "addr:housenumber":"8",
    "addr:postcode":"2582 lr",
    "addr:street":"S Gravenhage",
    "iso:country":"NL",
    "sg:address":"Pr Mauritsln 8",
    "sg:city":"S Gravenhage",
    "sg:orig_category":"Scholen Voor Basisonderwijs",
    "sg:phone":"+31 70 354 4323",
    "sg:postcode":"2582 LR",
    "sg:province":"South Holland",
    "wof:name":"Duinoord, Pr Chr",
    "wof:placetype":"venue"
},
  "geometry": {"coordinates":[4.27852,52.092411],"type":"Point"}
}