{
  "type": "Feature",
  "properties": {
    "addr:full":"Bennebroekweg 1 Zoeterwoude South Holland 2381 BS",
    "addr:housenumber":"1",
    "addr:postcode":"2381 bs",
    "addr:street":"Bennebroekweg",
    "iso:country":"NL",
    "sg:address":"Bennebroekweg 1",
    "sg:city":"Zoeterwoude",
    "sg:orig_category":"Bejaardeninstellingen And Serviceflats",
    "sg:phone":"+31 71 580 9203",
    "sg:postcode":"2381 BS",
    "sg:province":"South Holland",
    "wof:name":"Stichting Zorgnet Groenwoude Locatie Emmaus",
    "wof:placetype":"venue"
},
  "geometry": {"coordinates":[4.494874,52.119095],"type":"Point"}
}