{
  "type": "Feature",
  "properties": {
    "addr:full":"Lycklamavaart 3 Ravenswoud Friesland 8427 RM",
    "addr:housenumber":"3",
    "addr:postcode":"8427 rm",
    "addr:street":"Lycklamavaart",
    "iso:country":"NL",
    "sg:address":"Lycklamavaart 3",
    "sg:city":"Ravenswoud",
    "sg:orig_category":"Autokeuringen",
    "sg:phone":"+31 516 432 436",
    "sg:postcode":"8427 RM",
    "sg:province":"Friesland",
    "wof:name":"Montagebedrijf Dorenbos",
    "wof:placetype":"venue"
},
  "geometry": {"coordinates":[6.405834,52.978905],"type":"Point"}
}