{
  "type": "Feature",
  "properties": {
    "addr:full":"J F Kennedyplein 2 Ulft Gelderland 7071 BT",
    "addr:housenumber":"2",
    "addr:postcode":"7071 bt",
    "addr:street":"J F Kennedyplein;Gelderland",
    "iso:country":"NL",
    "sg:address":"J F Kennedyplein 2",
    "sg:city":"Ulft",
    "sg:orig_category":"Kappers",
    "sg:phone":"+31 315 686 769",
    "sg:postcode":"7071 BT",
    "sg:province":"Gelderland",
    "wof:name":"Haarmode Wendy",
    "wof:placetype":"venue"
},
  "geometry": {"coordinates":[6.3837351799,51.8915176392],"type":"Point"}
}