{
  "type": "Feature",
  "properties": {
    "addr:full":"Dorpsstr 1A Goirle Noord-Brabant 5051 CH",
    "addr:housenumber":"1a",
    "addr:postcode":"5051",
    "addr:street":"Dorpsstr",
    "iso:country":"NL",
    "sg:address":"Dorpsstr 1A",
    "sg:city":"Goirle",
    "sg:orig_category":"Herenkleding",
    "sg:phone":"+31 13 534 9072",
    "sg:postcode":"5051 CH",
    "sg:province":"Noord-Brabant",
    "wof:name":"Milano",
    "wof:placetype":"venue"
},
  "geometry": {"coordinates":[5.066049,51.523182],"type":"Point"}
}