{
  "type": "Feature",
  "properties": {
    "addr:full":"Vlytstr 6A Utrecht Utrecht 3513 SV",
    "addr:housenumber":"6a",
    "addr:postcode":"3513 sv",
    "addr:street":"Vlytstr",
    "iso:country":"NL",
    "sg:address":"Vlytstr 6A",
    "sg:city":"Utrecht",
    "sg:orig_category":"Antiquiteiten - Restauratie",
    "sg:phone":"+31 30 231 3170",
    "sg:postcode":"3513 SV",
    "sg:province":"Utrecht",
    "wof:name":"Hijman Meubelrestauratie",
    "wof:placetype":"venue"
},
  "geometry": {"coordinates":[5.106885,52.095448],"type":"Point"}
}