{
  "type": "Feature",
  "properties": {
    "addr:full":"Oude Rynsburgerwg 19 Oegstgeest Zuid-Holland 2342 BA",
    "addr:housenumber":"19",
    "addr:postcode":"2342 ba",
    "addr:street":"Oude Rynsburgerwg",
    "iso:country":"NL",
    "sg:address":"Oude Rynsburgerwg 19",
    "sg:city":"Oegstgeest",
    "sg:orig_category":"Bloemen En Planten - Groothandel",
    "sg:phone":"+31 71 517 6716",
    "sg:postcode":"2342 BA",
    "sg:province":"Zuid-Holland",
    "wof:name":"Verhaar, P",
    "wof:placetype":"venue"
},
  "geometry": {"coordinates":[4.453298,52.175983],"type":"Point"}
}