{
  "type": "Feature",
  "properties": {
    "iso:country":"NL",
    "sg:address":"Peppelweg 77",
    "sg:city":"Rotterdam",
    "sg:classifiers":[
        {
            "category":"Food & Beverages",
            "subcategory":"Fruits & Vegetables",
            "type":"Retail Goods"
        }
    ],
    "sg:phone":"+31 10 418 5725",
    "sg:postcode":"3053 GD",
    "sg:province":"South Holland",
    "sg:tags":[
        "groenten"
    ],
    "wof:name":"Groenteboxer",
    "wof:placetype":"venue"
},
  "geometry": {"coordinates":[4.472057,51.959957],"type":"Point"}
}