{
  "type": "Feature",
  "properties": {
    "addr:full":"Oude Arnhemsew 77 Zeist Utrecht 3702 BB",
    "addr:housenumber":"77",
    "addr:postcode":"3702 bb",
    "addr:street":"Oude Arnhemsew",
    "iso:country":"NL",
    "sg:address":"Oude Arnhemsew 77",
    "sg:city":"Zeist",
    "sg:classifiers":[
        {
            "category":"Personal",
            "subcategory":"Nail Salon",
            "type":"Services"
        }
    ],
    "sg:phone":"+31 30 691 4715",
    "sg:postcode":"3702 BB",
    "sg:province":"Utrecht",
    "sg:tags":[
        "pedicure"
    ],
    "wof:name":"Helling-Femer, E C",
    "wof:placetype":"venue"
},
  "geometry": {"coordinates":[5.24387,52.08548],"type":"Point"}
}