{
  "type": "Feature",
  "properties": {
    "addr:full":"Breestraat 128 Leiden South Holland 2311 CX",
    "addr:housenumber":"128",
    "addr:postcode":"2311 cx",
    "addr:street":"Breestraat",
    "iso:country":"NL",
    "sg:address":"Breestraat 128",
    "sg:city":"Leiden",
    "sg:orig_category":"Wasserettes And Stomerijen",
    "sg:phone":"+31 71 512 5885",
    "sg:postcode":"2311 CX",
    "sg:province":"South Holland",
    "wof:name":"Palthe Stomerijen Bv",
    "wof:placetype":"venue"
},
  "geometry": {"coordinates":[4.4920339584,52.157081604],"type":"Point"}
}