{
  "type": "Feature",
  "properties": {
    "addr:full":"Prins Hendriklaan 90 Utrecht Utrecht 3584 ES",
    "addr:housenumber":"90",
    "addr:postcode":"3584 es",
    "addr:street":"Prins Hendriklaan",
    "iso:country":"NL",
    "sg:address":"Prins Hendriklaan 90",
    "sg:city":"Utrecht",
    "sg:orig_category":"Vertaal- And Tolkenbureaus",
    "sg:phone":"+31 30 252 2018",
    "sg:postcode":"3584 ES",
    "sg:province":"Utrecht",
    "wof:name":"Anglo-File",
    "wof:placetype":"venue"
},
  "geometry": {"coordinates":[5.150043,52.084473],"type":"Point"}
}