{
  "type": "Feature",
  "properties": {
    "addr:full":"G Bomansln 3 Hilvarenbeek Noord-Brabant 5081 SP",
    "addr:housenumber":"3",
    "addr:postcode":"5081 sp",
    "iso:country":"NL",
    "sg:address":"G Bomansln 3",
    "sg:city":"Hilvarenbeek",
    "sg:orig_category":"Administratie- En Boekhoudkantoren",
    "sg:phone":"+31 13 505 4415",
    "sg:postcode":"5081 SP",
    "sg:province":"Noord-Brabant",
    "wof:name":"Mengerink, J H H",
    "wof:placetype":"venue"
},
  "geometry": {"coordinates":[5.136008,51.485294],"type":"Point"}
}