{
  "type": "Feature",
  "properties": {
    "addr:full":"In Den Daal 30 Oirsbeek Limburg 6438 JM",
    "addr:housenumber":"30",
    "addr:postcode":"6438 jm",
    "addr:street":"In Den Daal",
    "iso:country":"NL",
    "sg:address":"In Den Daal 30",
    "sg:city":"Oirsbeek",
    "sg:orig_category":"Diverse Consumentenartikelen Gh",
    "sg:phone":"+31 46 442 2235",
    "sg:postcode":"6438 JM",
    "sg:province":"Limburg",
    "wof:name":"Visser Elektro",
    "wof:placetype":"venue"
},
  "geometry": {"coordinates":[5.913278,50.949993],"type":"Point"}
}