{
  "type": "Feature",
  "properties": {
    "iso:country":"NL",
    "sg:address":"Stationsstr 99",
    "sg:city":"Deurne",
    "sg:orig_category":"Schoenen",
    "sg:phone":"+31 493 316 839",
    "sg:postcode":"5751 HD",
    "sg:province":"North Brabant",
    "wof:name":"Baloe Kinderschoenen",
    "wof:placetype":"venue"
},
  "geometry": {"coordinates":[5.786237,51.457886],"type":"Point"}
}