{
  "type": "Feature",
  "properties": {
    "addr:full":"Edisonstr 22 Franeker Friesland 8801 PN",
    "addr:housenumber":"22",
    "addr:postcode":"8801 pn",
    "addr:street":"Edisonstr",
    "iso:country":"NL",
    "sg:address":"Edisonstr 22",
    "sg:city":"Franeker",
    "sg:orig_category":"Straalbedrijven",
    "sg:phone":"+31 517 383 220",
    "sg:postcode":"8801 PN",
    "sg:province":"Friesland",
    "wof:name":"Hoeksma Bv",
    "wof:placetype":"venue"
},
  "geometry": {"coordinates":[5.518963,53.183163],"type":"Point"}
}