{
  "type": "Feature",
  "properties": {
    "addr:full":"Herengracht 121 Amsterdam North Holland 1015 BG",
    "addr:housenumber":"121",
    "addr:postcode":"1015",
    "addr:street":"Herengracht",
    "iso:country":"NL",
    "sg:address":"Herengracht 121",
    "sg:city":"Amsterdam",
    "sg:orig_category":"Zalenexploitatie",
    "sg:phone":"+31 20 626 0807",
    "sg:postcode":"1015 BG",
    "sg:province":"North Holland",
    "wof:name":"Art Nouveau International Bv",
    "wof:placetype":"venue"
},
  "geometry": {"coordinates":[4.889649,52.376076],"type":"Point"}
}