{
  "type": "Feature",
  "properties": {
    "addr:full":"Eemslandwg 29 Zwartemeer Drenthe 7894 AB",
    "addr:housenumber":"29",
    "addr:postcode":"7894 ab",
    "addr:street":"Eemslandwg",
    "iso:country":"NL",
    "sg:address":"Eemslandwg 29",
    "sg:city":"Zwartemeer",
    "sg:orig_category":"Lpg-Installaties",
    "sg:phone":"+31 591 312 229",
    "sg:postcode":"7894 AB",
    "sg:province":"Drenthe",
    "wof:name":"Luth-Tangenberg",
    "wof:placetype":"venue"
},
  "geometry": {"coordinates":[7.032947,52.722721],"type":"Point"}
}