{
  "type": "Feature",
  "properties": {
    "addr:full":"Garonnedal 7 Doetinchem Gelderland 7007 HM",
    "addr:housenumber":"7",
    "addr:postcode":"7007 hm",
    "addr:street":"Garonnedal;Gelderland",
    "iso:country":"NL",
    "sg:address":"Garonnedal 7",
    "sg:city":"Doetinchem",
    "sg:orig_category":"Paramedische Behandelingen",
    "sg:phone":"+31 314 324 817",
    "sg:postcode":"7007 HM",
    "sg:province":"Gelderland",
    "wof:name":"B.L. Brus",
    "wof:placetype":"venue"
},
  "geometry": {"coordinates":[6.254507,51.956909],"type":"Point"}
}