{
  "type": "Feature",
  "properties": {
    "iso:country":"NL",
    "sg:address":"Hassinkweg 22",
    "sg:city":"Hengelo Ov",
    "sg:orig_category":"Autokeuringen",
    "sg:phone":"+31 74 250 0174",
    "sg:postcode":"7556 BV",
    "sg:province":"Overijssel",
    "wof:name":"Autopoets En Antiroeststation Hengelo",
    "wof:placetype":"venue"
},
  "geometry": {"coordinates":[6.773017,52.280514],"type":"Point"}
}