{
  "type": "Feature",
  "properties": {
    "iso:country":"NL",
    "sg:address":"Westdk 8",
    "sg:city":"Dirksland",
    "sg:orig_category":"Loonbedrijven",
    "sg:phone":"+31 187 669 253",
    "sg:postcode":"3247 LM",
    "sg:province":"Zuid-Holland",
    "wof:name":"Av",
    "wof:placetype":"venue"
},
  "geometry": {"coordinates":[4.105012,51.748753],"type":"Point"}
}