{
  "type": "Feature",
  "properties": {
    "addr:full":"Postbus 79 Hilversum Noord-Holland 1200 AB",
    "addr:housenumber":"79",
    "addr:postcode":"1200 ab",
    "addr:street":"Postbus",
    "iso:country":"NL",
    "sg:address":"Postbus 79",
    "sg:city":"Hilversum",
    "sg:orig_category":"Webdesign Bureaus",
    "sg:phone":"+31 35 642 0554",
    "sg:postcode":"1200 AB",
    "sg:province":"Noord-Holland",
    "sg:website":"http://www.branche.net",
    "wof:name":"Branchenet",
    "wof:placetype":"venue"
},
  "geometry": {"coordinates":[5.1710000038,52.223991394],"type":"Point"}
}