{
  "type": "Feature",
  "properties": {
    "addr:full":"Gedempte Zuiderdiep 115 Groningen Groningen 9711 HE",
    "addr:housenumber":"115",
    "addr:postcode":"9711 he",
    "addr:street":"Gedempte Zuiderdiep",
    "iso:country":"NL",
    "sg:address":"Gedempte Zuiderdiep 115",
    "sg:city":"Groningen",
    "sg:classifiers":[
        {
            "category":"Fast Food",
            "type":"Food & Drink"
        }
    ],
    "sg:phone":"+31 50 312 6168",
    "sg:postcode":"9711 HE",
    "sg:province":"Groningen",
    "sg:tags":[
        "afhaal",
        "restaurant"
    ],
    "wof:name":"Adanus",
    "wof:placetype":"venue"
},
  "geometry": {"coordinates":[6.563658,53.21476],"type":"Point"}
}