{
  "type": "Feature",
  "properties": {
    "iso:country":"NL",
    "sg:address":"Postbus 38265",
    "sg:city":"Nymegen",
    "sg:orig_category":"Vertaalbureaus",
    "sg:phone":"+31 24 645 4870",
    "sg:postcode":"6503 AG",
    "sg:province":"Guanajuato",
    "wof:name":"Nefa",
    "wof:placetype":"venue"
},
  "geometry": {"coordinates":[-100.866539,20.66522],"type":"Point"}
}