{
  "type": "Feature",
  "properties": {
    "addr:full":"Haven 45 Volendam Noord-Holland 1131 EP",
    "addr:housenumber":"45",
    "addr:postcode":"1131 ep",
    "addr:street":"Haven",
    "iso:country":"NL",
    "sg:address":"Haven 45",
    "sg:city":"Volendam",
    "sg:orig_category":"Meubeltextiel Fab",
    "sg:phone":"+31 299 363 666",
    "sg:postcode":"1131 EP",
    "sg:province":"Noord-Holland",
    "wof:name":"Jan Schokker'S Zeilmakerij Ijsselmeer Bv",
    "wof:placetype":"venue"
},
  "geometry": {"coordinates":[5.076072,52.493809],"type":"Point"}
}