{
  "type": "Feature",
  "properties": {
    "addr:full":"Willem Van Noortstraat 16 Arnhem Gelderland 6828 XW",
    "addr:housenumber":"16",
    "addr:postcode":"6828 xw",
    "addr:street":"Willem Van Noortstraat",
    "iso:country":"NL",
    "sg:address":"Willem Van Noortstraat 16",
    "sg:city":"Arnhem",
    "sg:orig_category":"Film-, Tv- And Videoproductie",
    "sg:phone":"+31 6 51111088",
    "sg:postcode":"6828 XW",
    "sg:province":"Gelderland",
    "wof:name":"Ferdinand Van Dam",
    "wof:placetype":"venue"
},
  "geometry": {"coordinates":[5.926469,51.977684],"type":"Point"}
}