{
  "type": "Feature",
  "properties": {
    "addr:full":"Goudplevier 51 Leusden Utrecht 3831 GR",
    "addr:housenumber":"51",
    "addr:postcode":"3831",
    "addr:street":"Goudplevier",
    "iso:country":"NL",
    "sg:address":"Goudplevier 51",
    "sg:city":"Leusden",
    "sg:orig_category":"Loopbaanbegeleiding",
    "sg:phone":"+31 33 494 7706",
    "sg:postcode":"3831 GR",
    "sg:province":"Utrecht",
    "wof:name":"Dreier",
    "wof:placetype":"venue"
},
  "geometry": {"coordinates":[5.444819,52.134838],"type":"Point"}
}