{
  "type": "Feature",
  "properties": {
    "addr:full":"M L Kingln 168 Hellevoetsluis South Holland 3223 RE",
    "addr:housenumber":"168",
    "addr:postcode":"3223 re",
    "addr:street":"M",
    "iso:country":"NL",
    "sg:address":"M L Kingln 168",
    "sg:city":"Hellevoetsluis",
    "sg:orig_category":"Huidtherapeuten",
    "sg:phone":"+31 181 325 373",
    "sg:postcode":"3223 RE",
    "sg:province":"South Holland",
    "wof:name":"Nederlof-Schneider, M",
    "wof:placetype":"venue"
},
  "geometry": {"coordinates":[4.14703,51.830406],"type":"Point"}
}