{
  "type": "Feature",
  "properties": {
    "iso:country":"NL",
    "sg:address":"Zandbergwg 13",
    "sg:city":"Breda",
    "sg:orig_category":"Vertaalbureaus",
    "sg:phone":"+31 76 521 8361",
    "sg:postcode":"4818 LJ",
    "sg:province":"Noord-Brabant",
    "wof:name":"Hart-Waslicka, Drs H 'T",
    "wof:placetype":"venue"
},
  "geometry": {"coordinates":[4.779408,51.577503],"type":"Point"}
}