{
  "type": "Feature",
  "properties": {
    "addr:full":"Hofsngl 11 Arnhem Gelderland 6834 GA",
    "addr:housenumber":"11",
    "addr:postcode":"6834 ga",
    "addr:street":"Hofsngl",
    "iso:country":"NL",
    "sg:address":"Hofsngl 11",
    "sg:city":"Arnhem",
    "sg:orig_category":"Verenigingen En Stichtingen",
    "sg:phone":"+31 26 321 2661",
    "sg:postcode":"6834 GA",
    "sg:province":"Gelderland",
    "wof:name":"Klarendal",
    "wof:placetype":"venue"
},
  "geometry": {"coordinates":[5.924674,51.955982],"type":"Point"}
}