{
  "type": "Feature",
  "properties": {
    "addr:full":"Hessenwg 57 Hattem Gelderland 8051 LB",
    "addr:housenumber":"57",
    "addr:postcode":"8051 lb",
    "addr:street":"Hessenwg;Gelderland",
    "iso:country":"NL",
    "sg:address":"Hessenwg 57",
    "sg:city":"Hattem",
    "sg:orig_category":"Schoonheidsinstituten",
    "sg:phone":"+31 38 444 8877",
    "sg:postcode":"8051 LB",
    "sg:province":"Gelderland",
    "wof:name":"Wilma",
    "wof:placetype":"venue"
},
  "geometry": {"coordinates":[6.052686,52.471992],"type":"Point"}
}