{
  "type": "Feature",
  "properties": {
    "addr:full":"Heimolen 17 Bergen Op Zoom Noord-Brabant 4625 DC",
    "addr:housenumber":"17",
    "addr:postcode":"4625",
    "addr:street":"Heimolen",
    "iso:country":"NL",
    "sg:address":"Heimolen 17",
    "sg:city":"Bergen Op Zoom",
    "sg:orig_category":"Groententeelt",
    "sg:phone":"+31 164 237 089",
    "sg:postcode":"4625 DC",
    "sg:province":"Noord-Brabant",
    "wof:name":"Landbouwbedrijf Govers Bv",
    "wof:placetype":"venue"
},
  "geometry": {"coordinates":[4.314577,51.468086],"type":"Point"}
}