{
  "type": "Feature",
  "properties": {
    "addr:full":"Zeeltpln 16 Hoogvliet Rt Zuid-Holland 3192 AJ",
    "addr:housenumber":"16",
    "addr:postcode":"rt;3192 aj",
    "addr:street":"Zeeltpln",
    "iso:country":"NL",
    "sg:address":"Zeeltpln 16",
    "sg:city":"Hoogvliet Rt",
    "sg:classifiers":[
        {
            "category":"Food & Beverages",
            "subcategory":"Bakery",
            "type":"Retail Goods"
        }
    ],
    "sg:phone":"+31 10 472 0033",
    "sg:postcode":"3192 AJ",
    "sg:province":"Zuid-Holland",
    "sg:tags":[
        "pizza"
    ],
    "wof:name":"Strada Hoogvliet, La",
    "wof:placetype":"venue"
},
  "geometry": {"coordinates":[4.351198,51.857368],"type":"Point"}
}