{
  "type": "Feature",
  "properties": {
    "iso:country":"NL",
    "sg:address":"Jan Van Scorelstraat 15",
    "sg:city":"Leeuwarden",
    "sg:orig_category":"Verzekeringen",
    "sg:phone":"+31 58 213 9937",
    "sg:postcode":"8932 CW",
    "sg:province":"Provincie Friesland",
    "wof:name":"Bemiddelingskantoor De Vaf",
    "wof:placetype":"venue"
},
  "geometry": {"coordinates":[5.785815,53.192623],"type":"Point"}
}