{
  "type": "Feature",
  "properties": {
    "addr:full":"Grt Wade 46 Nieuwegein Utrecht 3439 NS",
    "addr:housenumber":"46",
    "addr:postcode":"3439 ns",
    "addr:street":"Wade",
    "iso:country":"NL",
    "sg:address":"Grt Wade 46",
    "sg:city":"Nieuwegein",
    "sg:orig_category":"Administratie- En Boekhoudkantoren",
    "sg:phone":"+31 30 601 8899",
    "sg:postcode":"3439 NS",
    "sg:province":"Utrecht",
    "wof:name":"Bonheem Bv",
    "wof:placetype":"venue"
},
  "geometry": {"coordinates":[5.111648,52.04594],"type":"Point"}
}