{
  "type": "Feature",
  "properties": {
    "addr:full":"Industriewg 1 Veendam Groningen 9641 HM",
    "addr:housenumber":"1",
    "addr:postcode":"9641 hm",
    "addr:street":"Industriewg",
    "iso:country":"NL",
    "sg:address":"Industriewg 1",
    "sg:city":"Veendam",
    "sg:orig_category":"Machinefabrieken",
    "sg:phone":"+31 598 619 456",
    "sg:postcode":"9641 HM",
    "sg:province":"Groningen",
    "wof:name":"Nivoba Bv",
    "wof:placetype":"venue"
},
  "geometry": {"coordinates":[6.881828,53.099762],"type":"Point"}
}