{
  "type": "Feature",
  "properties": {
    "iso:country":"NL",
    "sg:address":"Bilderdijkstraat 25",
    "sg:city":"Heemskerk",
    "sg:orig_category":"Alternatieve Geneeskunde",
    "sg:phone":"+31 251 243 329",
    "sg:postcode":"1962 SJ",
    "sg:province":"Noord-Holland",
    "wof:name":"Huidtherapie Maria Pardo Estetica",
    "wof:placetype":"venue"
},
  "geometry": {"coordinates":[4.676699,52.511238],"type":"Point"}
}