{
  "type": "Feature",
  "properties": {
    "addr:full":"Laanstraat 21 Baarn Utrecht 3743 BA",
    "addr:housenumber":"21",
    "addr:postcode":"3743 ba",
    "addr:street":"Laanstraat",
    "iso:country":"NL",
    "sg:address":"Laanstraat 21",
    "sg:city":"Baarn",
    "sg:orig_category":"Kappers",
    "sg:phone":"+31 35 542 3749",
    "sg:postcode":"3743 BA",
    "sg:province":"Utrecht",
    "wof:name":"Hw Hairstyling",
    "wof:placetype":"venue"
},
  "geometry": {"coordinates":[5.2906489372,52.2114143372],"type":"Point"}
}