{
  "type": "Feature",
  "properties": {
    "addr:full":"Witte De Withstraat 27 'S Gravenhage Zuid-Holland 2518 CP",
    "addr:housenumber":"27",
    "addr:postcode":"2518 cp",
    "addr:street":"Witte De Withstraat;' S",
    "iso:country":"NL",
    "sg:address":"Witte De Withstraat 27",
    "sg:city":"'S Gravenhage",
    "sg:orig_category":"Overheidsdiensten",
    "sg:phone":"+31 70 362 1007",
    "sg:postcode":"2518 CP",
    "sg:province":"Zuid-Holland",
    "wof:name":"Centrum De Ruimte",
    "wof:placetype":"venue"
},
  "geometry": {"coordinates":[4.2947740555,52.0802955627],"type":"Point"}
}