{
  "type": "Feature",
  "properties": {
    "addr:full":"Roosendaalse Baan 17 Wouw Noord-Brabant 4724  S",
    "addr:housenumber":"17;4724",
    "addr:street":"Roosendaalse Baan;S",
    "iso:country":"NL",
    "sg:address":"Roosendaalse Baan 17",
    "sg:city":"Wouw",
    "sg:classifiers":[
        {
            "category":"Fast Food",
            "type":"Food & Drink"
        }
    ],
    "sg:phone":"+31 165 301 643",
    "sg:postcode":"4724  S",
    "sg:province":"Noord-Brabant",
    "sg:tags":[
        "afhaal",
        "restaurant"
    ],
    "wof:name":"Cafetaria De Baan",
    "wof:placetype":"venue"
},
  "geometry": {"coordinates":[4.398038,51.526321],"type":"Point"}
}