{
  "type": "Feature",
  "properties": {
    "addr:full":"Haarlemmerwg 21 Leiden Zuid-Holland 2316 AB",
    "addr:housenumber":"21",
    "addr:postcode":"2316 ab",
    "addr:street":"Haarlemmerwg",
    "iso:country":"NL",
    "sg:address":"Haarlemmerwg 21",
    "sg:city":"Leiden",
    "sg:orig_category":"Webdesign Bureaus",
    "sg:phone":"+31 71 522 4500",
    "sg:postcode":"2316 AB",
    "sg:province":"Zuid-Holland",
    "sg:website":"http://www.infofilm.nl",
    "wof:name":"Infofilm",
    "wof:placetype":"venue"
},
  "geometry": {"coordinates":[4.4900708199,52.1663589478],"type":"Point"}
}