{
  "type": "Feature",
  "properties": {
    "addr:full":"Johan V Oldenbarneveltln 103 Zeist Utrecht 3705 HD",
    "addr:housenumber":"103",
    "addr:postcode":"3705 hd",
    "addr:street":"Johan V Oldenbarneveltln",
    "iso:country":"NL",
    "sg:address":"Johan V Oldenbarneveltln 103",
    "sg:city":"Zeist",
    "sg:orig_category":"Overheidsdiensten",
    "sg:phone":"+31 30 695 1152",
    "sg:postcode":"3705 HD",
    "sg:province":"Utrecht",
    "wof:name":"Hebron",
    "wof:placetype":"venue"
},
  "geometry": {"coordinates":[5.2388348579,52.0984535217],"type":"Point"}
}