{
  "type": "Feature",
  "properties": {
    "addr:full":"Gasthuisstr 22 Heukelum Gelderland 4161 CC",
    "addr:housenumber":"22",
    "addr:postcode":"4161 cc",
    "addr:street":"Gasthuisstr;Gelderland",
    "iso:country":"NL",
    "sg:address":"Gasthuisstr 22",
    "sg:city":"Heukelum",
    "sg:orig_category":"Loopbaanbegeleiding",
    "sg:phone":"+31 345 632 112",
    "sg:postcode":"4161 CC",
    "sg:province":"Gelderland",
    "wof:name":"Aurora",
    "wof:placetype":"venue"
},
  "geometry": {"coordinates":[5.076858,51.87421],"type":"Point"}
}