{
  "type": "Feature",
  "properties": {
    "addr:full":"Hegge 24 Schinnen Limburg 6365 ED",
    "addr:housenumber":"24",
    "addr:postcode":"6365 ed",
    "addr:street":"Hegge",
    "iso:country":"NL",
    "sg:address":"Hegge 24",
    "sg:city":"Schinnen",
    "sg:orig_category":"Goederenvervoer Over De Weg",
    "sg:phone":"+31 46 443 1922",
    "sg:postcode":"6365 ED",
    "sg:province":"Limburg",
    "wof:name":"Transportonderneming C M R Vd Elzen Vof",
    "wof:placetype":"venue"
},
  "geometry": {"coordinates":[5.871058,50.938477],"type":"Point"}
}