{
  "type": "Feature",
  "properties": {
    "addr:full":"Latyrusstraat 14 Dedemsvaart Overijssel 7701 CX",
    "addr:housenumber":"14",
    "addr:postcode":"7701 cx",
    "addr:street":"Latyrusstraat",
    "iso:country":"NL",
    "sg:address":"Latyrusstraat 14",
    "sg:city":"Dedemsvaart",
    "sg:orig_category":"Medische Apparatuur And Prothesen Fab",
    "sg:phone":"+31 523 615 295",
    "sg:postcode":"7701 CX",
    "sg:province":"Overijssel",
    "wof:name":"Tandtechnisch Laboratorium Avereest Vof",
    "wof:placetype":"venue"
},
  "geometry": {"coordinates":[6.461928,52.601265],"type":"Point"}
}