{
  "type": "Feature",
  "properties": {
    "iso:country":"NL",
    "sg:address":"Het Kleine Loo 308",
    "sg:city":"'S Gravenhage",
    "sg:orig_category":"Zuivelproducten",
    "sg:phone":"+31 70 385 3628",
    "sg:postcode":"2592 CK",
    "sg:province":"Zuid-Holland",
    "wof:name":"De Kaasspecialist Bv",
    "wof:placetype":"venue"
},
  "geometry": {"coordinates":[4.356483,52.091297],"type":"Point"}
}