{
  "type": "Feature",
  "properties": {
    "addr:full":"De Banier 9 Swifterbant Flevoland 8255 GJ",
    "addr:housenumber":"9",
    "addr:postcode":"8255 gj",
    "addr:street":"De Banier;Flevoland",
    "iso:country":"NL",
    "sg:address":"De Banier 9",
    "sg:city":"Swifterbant",
    "sg:orig_category":"Adviesbureaus Bouwkunde",
    "sg:phone":"+31 321 321 893",
    "sg:postcode":"8255 GJ",
    "sg:province":"Flevoland",
    "wof:name":"Abovinis",
    "wof:placetype":"venue"
},
  "geometry": {"coordinates":[5.642882,52.565784],"type":"Point"}
}