{
  "type": "Feature",
  "properties": {
    "iso:country":"NL",
    "sg:address":"Oranjesingel 25",
    "sg:city":"Nijmegen",
    "sg:orig_category":"Advocaten And Juridische Adviseurs",
    "sg:phone":"+31 24 322 9203",
    "sg:postcode":"6511 NM",
    "sg:province":"Gelderland",
    "wof:name":"Smits & Vermeulen Advocaten",
    "wof:placetype":"venue"
},
  "geometry": {"coordinates":[5.864353,51.841904],"type":"Point"}
}