{
  "type": "Feature",
  "properties": {
    "addr:full":"Albrandswaardsedk 188 Poortugaal South Holland 3172 XB",
    "addr:housenumber":"188",
    "addr:postcode":"3172 xb",
    "iso:country":"NL",
    "sg:address":"Albrandswaardsedk 188",
    "sg:city":"Poortugaal",
    "sg:orig_category":"Fitnesscentra",
    "sg:phone":"+31 10 501 3115",
    "sg:postcode":"3172 XB",
    "sg:province":"South Holland",
    "wof:name":"Carla Van Gameren Sportcentrum",
    "wof:placetype":"venue"
},
  "geometry": {"coordinates":[4.420245,51.846622],"type":"Point"}
}