{
  "type": "Feature",
  "properties": {
    "addr:full":"Gelkingestr 25 Groningen Groningen 9711 NA",
    "addr:housenumber":"25",
    "addr:postcode":"9711 na",
    "addr:street":"Gelkingestr",
    "iso:country":"NL",
    "sg:address":"Gelkingestr 25",
    "sg:city":"Groningen",
    "sg:classifiers":[
        {
            "category":"Food & Beverages",
            "subcategory":"Bakery",
            "type":"Retail Goods"
        }
    ],
    "sg:phone":"+31 50 312 4871",
    "sg:postcode":"9711 NA",
    "sg:province":"Groningen",
    "sg:tags":[
        "pizza"
    ],
    "wof:name":"Costa Rei",
    "wof:placetype":"venue"
},
  "geometry": {"coordinates":[6.568652,53.216759],"type":"Point"}
}