{
  "type": "Feature",
  "properties": {
    "addr:full":"Burgemeesterpark 29 Driebergen-Rijsenburg Utrecht 3971 CV",
    "addr:housenumber":"29",
    "addr:postcode":"3971 cv",
    "addr:street":"Burgemeesterpark",
    "iso:country":"NL",
    "sg:address":"Burgemeesterpark 29",
    "sg:city":"Driebergen-Rijsenburg",
    "sg:classifiers":[
        {
            "category":"Education",
            "subcategory":"Preschool",
            "type":"Public Place"
        }
    ],
    "sg:phone":"+31 343 513 290",
    "sg:postcode":"3971 CV",
    "sg:province":"Utrecht",
    "sg:tags":[
        "kleuteronderwijs",
        "basis-"
    ],
    "wof:name":"Christelijke Basisschool De Zonheuvel",
    "wof:placetype":"venue"
},
  "geometry": {"coordinates":[5.290073,52.056614],"type":"Point"}
}