{
  "type": "Feature",
  "properties": {
    "addr:full":"Staatssecretar Ln 252 Zwolle Overijssel 8015 DC",
    "addr:housenumber":"252",
    "addr:postcode":"8015",
    "addr:street":"Staatssecretar Ln",
    "iso:country":"NL",
    "sg:address":"Staatssecretar Ln 252",
    "sg:city":"Zwolle",
    "sg:orig_category":"Administratie- En Boekhoudkantoren",
    "sg:phone":"+31 38 460 1620",
    "sg:postcode":"8015 DC",
    "sg:province":"Overijssel",
    "wof:name":"Counting House",
    "wof:placetype":"venue"
},
  "geometry": {"coordinates":[6.117357,52.474388],"type":"Point"}
}