{
  "type": "Feature",
  "properties": {
    "iso:country":"NL",
    "sg:address":"Stationsstr 4",
    "sg:city":"Zuidbroek",
    "sg:classifiers":[
        {
            "category":"Travel",
            "subcategory":"Hotels & Motels",
            "type":"Entertainment"
        }
    ],
    "sg:phone":"+31 598 451 559",
    "sg:postcode":"9636 BA",
    "sg:province":"Groningen",
    "wof:name":"Hulsebos",
    "wof:placetype":"venue"
},
  "geometry": {"coordinates":[6.867237,53.159737],"type":"Point"}
}