{
  "type": "Feature",
  "properties": {
    "addr:full":"Korhoenstraat 24 Gennep Limburg 6591 VH",
    "addr:housenumber":"24",
    "addr:postcode":"6591 vh",
    "addr:street":"Korhoenstraat",
    "iso:country":"NL",
    "sg:address":"Korhoenstraat 24",
    "sg:city":"Gennep",
    "sg:orig_category":"Farmaceutische Producten Gh",
    "sg:phone":"+31 485 512 438",
    "sg:postcode":"6591 VH",
    "sg:province":"Limburg",
    "wof:name":"L.H.W.J. Dodemont",
    "wof:placetype":"venue"
},
  "geometry": {"coordinates":[5.988214,51.696514],"type":"Point"}
}