{
  "type": "Feature",
  "properties": {
    "iso:country":"NL",
    "sg:address":"Groothandelsmarkt 25",
    "sg:city":"Zwaagdijk",
    "sg:orig_category":"Boekhouders",
    "sg:phone":"+31 228 581 549",
    "sg:postcode":"1681 NN",
    "sg:province":"North Holland",
    "wof:name":"Administratie Lat",
    "wof:placetype":"venue"
},
  "geometry": {"coordinates":[5.154388,52.702408],"type":"Point"}
}