{
  "type": "Feature",
  "properties": {
    "addr:full":"Fazantenkamp 482 Maarssen Utrecht 3607 DB",
    "addr:housenumber":"482",
    "addr:postcode":"3607 db",
    "addr:street":"Fazantenkamp",
    "iso:country":"NL",
    "sg:address":"Fazantenkamp 482",
    "sg:city":"Maarssen",
    "sg:orig_category":"Binnenhuisarchitecten",
    "sg:phone":"+31 6 53512276",
    "sg:postcode":"3607 DB",
    "sg:province":"Utrecht",
    "wof:name":"Studio Is",
    "wof:placetype":"venue"
},
  "geometry": {"coordinates":[5.020564,52.127033],"type":"Point"}
}