{
  "type": "Feature",
  "properties": {
    "iso:country":"NL",
    "sg:address":"Landbouwpln 1-2",
    "sg:city":"Noordwykerhout",
    "sg:orig_category":"Kaasgroothandel",
    "sg:phone":"+31 252 373 316",
    "sg:postcode":"2211 GE",
    "sg:province":"Zuid-Holland",
    "wof:name":"Elzen Bv, B Den",
    "wof:placetype":"venue"
},
  "geometry": {"coordinates":[4.4923839569,52.2613754272],"type":"Point"}
}