{
  "type": "Feature",
  "properties": {
    "addr:full":"Hanzestr 14 Hindeloopen Provincie Friesland 8713 JZ",
    "addr:housenumber":"14",
    "addr:postcode":"8713 jz",
    "addr:street":"Hanzestr;Provincie Friesland",
    "iso:country":"NL",
    "sg:address":"Hanzestr 14",
    "sg:city":"Hindeloopen",
    "sg:classifiers":[
        {
            "category":"Farming",
            "subcategory":"Fish & Marine Products",
            "type":"Manufacturing & Wholesale Goods"
        }
    ],
    "sg:phone":"+31 514 522 296",
    "sg:postcode":"8713 JZ",
    "sg:province":"Provincie Friesland",
    "sg:tags":[
        "vi"
    ],
    "wof:name":"Visser",
    "wof:placetype":"venue"
},
  "geometry": {"coordinates":[5.403691,52.938408],"type":"Point"}
}