{
  "type": "Feature",
  "properties": {
    "iso:country":"NL",
    "sg:address":"Rochussenstr 385",
    "sg:city":"Rotterdam",
    "sg:orig_category":"Fotografie Reclame En Mode",
    "sg:phone":"+31 10 425 7902",
    "sg:postcode":"3023 DK",
    "sg:province":"Zuid-Holland",
    "wof:name":"Steenhoven",
    "wof:placetype":"venue"
},
  "geometry": {"coordinates":[4.451661,51.909428],"type":"Point"}
}