{
  "type": "Feature",
  "properties": {
    "addr:full":"Kasteel Ter Aalaan 9 Berlicum Nb Noord-Brabant 5258 CH",
    "addr:housenumber":"9",
    "addr:postcode":"5258",
    "addr:street":"Kasteel Ter Aalaan",
    "iso:country":"NL",
    "sg:address":"Kasteel Ter Aalaan 9",
    "sg:city":"Berlicum Nb",
    "sg:classifiers":[
        {
            "category":"Professional",
            "subcategory":"Accounting & Tax Preparation",
            "type":"Services"
        }
    ],
    "sg:phone":"+31 73 503 1503",
    "sg:postcode":"5258 CH",
    "sg:province":"Noord-Brabant",
    "sg:tags":[
        "accountant"
    ],
    "wof:name":"Zwanenberg Advies Bv",
    "wof:placetype":"venue"
},
  "geometry": {"coordinates":[5.389463,51.686005],"type":"Point"}
}