{
  "type": "Feature",
  "properties": {
    "iso:country":"NL",
    "sg:address":"Alteveerstr 32-34",
    "sg:city":"Hoogeveen",
    "sg:orig_category":"Wasmachines En Wasdrogers - Onderhoud En Reparatie",
    "sg:phone":"+31 528 344 677",
    "sg:postcode":"7907 AA",
    "sg:province":"Provincie Drenthe",
    "sg:website":"http://www.plentyparts.net",
    "wof:name":"Plentyparts",
    "wof:placetype":"venue"
},
  "geometry": {"coordinates":[6.4772310257,52.7191467285],"type":"Point"}
}