{
  "type": "Feature",
  "properties": {
    "iso:country":"NL",
    "sg:address":"Spanjaardslaan 81",
    "sg:city":"Leeuwarden",
    "sg:orig_category":"Verzekeringen",
    "sg:phone":"+31 58 213 0750",
    "sg:postcode":"8917 AM",
    "sg:province":"Friesland",
    "wof:name":"Assurantiekantoor B. Van Keulen",
    "wof:placetype":"venue"
},
  "geometry": {"coordinates":[5.79032,53.208092],"type":"Point"}
}