{
  "type": "Feature",
  "properties": {
    "iso:country":"NL",
    "sg:address":"Vinkenlaan 47",
    "sg:city":"Bilthoven",
    "sg:classifiers":[
        {
            "category":"Fast Food",
            "type":"Food & Drink"
        }
    ],
    "sg:phone":"+31 30 228 0288",
    "sg:postcode":"3722 AH",
    "sg:province":"Utrecht",
    "sg:tags":[
        "afhaal",
        "restaurant"
    ],
    "wof:name":"La Terrazza",
    "wof:placetype":"venue"
},
  "geometry": {"coordinates":[5.206132,52.12851],"type":"Point"}
}