{
  "type": "Feature",
  "properties": {
    "addr:full":"Heerenwg 5 Yhorst Provincie Drenthe 7955 PA",
    "addr:housenumber":"5",
    "addr:postcode":"7955",
    "addr:street":"Heerenwg;Provincie Drenthe",
    "iso:country":"NL",
    "sg:address":"Heerenwg 5",
    "sg:city":"Yhorst",
    "sg:orig_category":"Ballonvaarten En -Reclame",
    "sg:phone":"+31 522 442 921",
    "sg:postcode":"7955 PA",
    "sg:province":"Provincie Drenthe",
    "wof:name":"Hulsbergen Hot-Air Balloons",
    "wof:placetype":"venue"
},
  "geometry": {"coordinates":[6.274545,52.661301],"type":"Point"}
}