{
  "type": "Feature",
  "properties": {
    "addr:full":"Havenpln 20 Zierikzee Zeeland 4301 CB",
    "addr:housenumber":"20",
    "addr:postcode":"4301 cb",
    "addr:street":"Havenpln",
    "iso:country":"NL",
    "sg:address":"Havenpln 20",
    "sg:city":"Zierikzee",
    "sg:orig_category":"Bloemen En Planten",
    "sg:phone":"+31 111 417 768",
    "sg:postcode":"4301 CB",
    "sg:province":"Zeeland",
    "wof:name":"Harlekijn, Bloemsierkunst De",
    "wof:placetype":"venue"
},
  "geometry": {"coordinates":[3.920752,51.649456],"type":"Point"}
}