{
  "type": "Feature",
  "properties": {
    "addr:full":"Collardslaan 2A Assen Provincie Drenthe 9401 GZ",
    "addr:housenumber":"2a",
    "addr:postcode":"9401 gz",
    "addr:street":"Collardslaan;Provincie Drenthe",
    "iso:country":"NL",
    "sg:address":"Collardslaan 2A",
    "sg:city":"Assen",
    "sg:orig_category":"Begrafenisondernemers",
    "sg:phone":"+31 592 300 487",
    "sg:postcode":"9401 GZ",
    "sg:province":"Provincie Drenthe",
    "wof:name":"Hervormde Diakonale Begrafenis Verz Nv",
    "wof:placetype":"venue"
},
  "geometry": {"coordinates":[6.559737,52.992519],"type":"Point"}
}