{
  "type": "Feature",
  "properties": {
    "addr:full":"Zandstraat 122 Beneden Leeuwen Gelderland 6658 CX",
    "addr:housenumber":"122",
    "addr:postcode":"6658 cx",
    "addr:street":"Zandstraat",
    "iso:country":"NL",
    "sg:address":"Zandstraat 122",
    "sg:city":"Beneden Leeuwen",
    "sg:orig_category":"Beursorganisaties And Standbouw",
    "sg:phone":"+31 487 594 140",
    "sg:postcode":"6658 CX",
    "sg:province":"Gelderland",
    "wof:name":"Interex (Interieur En Exterieur Afbouw)",
    "wof:placetype":"venue"
},
  "geometry": {"coordinates":[5.509795,51.881134],"type":"Point"}
}