{
  "type": "Feature",
  "properties": {
    "addr:full":"P Krugerstr 8 Katwyk Zh South Holland 2225 ZK",
    "addr:housenumber":"8;zh",
    "addr:postcode":"2225",
    "addr:street":"Krugerstr;Zk",
    "iso:country":"NL",
    "sg:address":"P Krugerstr 8",
    "sg:city":"Katwyk Zh",
    "sg:orig_category":"Kappers",
    "sg:phone":"+31 71 407 2225",
    "sg:postcode":"2225 ZK",
    "sg:province":"South Holland",
    "wof:name":"Dijkhuizen, J",
    "wof:placetype":"venue"
},
  "geometry": {"coordinates":[4.3965849876,52.2051086426],"type":"Point"}
}