{
  "type": "Feature",
  "properties": {
    "addr:full":"Kerkwg 94 Ridderkerk Zuid-Holland 2985 AV",
    "addr:housenumber":"94",
    "addr:postcode":"2985 av",
    "addr:street":"Kerkwg",
    "iso:country":"NL",
    "sg:address":"Kerkwg 94",
    "sg:city":"Ridderkerk",
    "sg:orig_category":"Kappers",
    "sg:phone":"+31 180 424 357",
    "sg:postcode":"2985 AV",
    "sg:province":"Zuid-Holland",
    "wof:name":"Meijer, H",
    "wof:placetype":"venue"
},
  "geometry": {"coordinates":[4.599115,51.865627],"type":"Point"}
}