{
  "type": "Feature",
  "properties": {
    "iso:country":"NL",
    "sg:address":"Laanstr 104",
    "sg:city":"Baarn",
    "sg:classifiers":[
        {
            "category":"Food & Beverages",
            "subcategory":"Fruits & Vegetables",
            "type":"Retail Goods"
        }
    ],
    "sg:phone":"+31 35 541 2465",
    "sg:postcode":"3743 BJ",
    "sg:province":"Utrecht",
    "sg:tags":[
        "en",
        "groenten"
    ],
    "wof:name":"Kraay & Zn",
    "wof:placetype":"venue"
},
  "geometry": {"coordinates":[5.284851,52.212357],"type":"Point"}
}