{
  "type": "Feature",
  "properties": {
    "iso:country":"NL",
    "sg:address":"Pilootwg 5",
    "sg:city":"Stavenisse",
    "sg:orig_category":"Grondwerken",
    "sg:phone":"+31 166 692 977",
    "sg:postcode":"4696 RJ",
    "sg:province":"Zeeland",
    "wof:name":"Haaften Bv, Aannemersbedrijf Van",
    "wof:placetype":"venue"
},
  "geometry": {"coordinates":[4.00688,51.586891],"type":"Point"}
}