{
  "type": "Feature",
  "properties": {
    "addr:full":"Zuideinde 26 Meppel Provincie Drenthe 7941 GH",
    "addr:housenumber":"26",
    "addr:postcode":"7941 gh",
    "addr:street":"Zuideinde;Provincie Drenthe",
    "iso:country":"NL",
    "sg:address":"Zuideinde 26",
    "sg:city":"Meppel",
    "sg:orig_category":"Werving And Selectie Van Tijdelijk Personeel And Uitzendkantoren",
    "sg:phone":"+31 522 252 622",
    "sg:postcode":"7941 GH",
    "sg:province":"Provincie Drenthe",
    "wof:name":"Adecco",
    "wof:placetype":"venue"
},
  "geometry": {"coordinates":[6.1962947845,52.6996154785],"type":"Point"}
}