{
  "type": "Feature",
  "properties": {
    "addr:full":"Sloterweg 358 Badhoevedorp Noord-Holland 1171 VK",
    "addr:housenumber":"358",
    "addr:postcode":"1171 vk",
    "addr:street":"Sloterweg",
    "iso:country":"NL",
    "sg:address":"Sloterweg 358",
    "sg:city":"Badhoevedorp",
    "sg:orig_category":"Goederenvervoer Over De Weg",
    "sg:phone":"+31 20 585 8800",
    "sg:postcode":"1171 VK",
    "sg:province":"Noord-Holland",
    "wof:name":"Abbink International",
    "wof:placetype":"venue"
},
  "geometry": {"coordinates":[4.762952,52.326485],"type":"Point"}
}