{
  "type": "Feature",
  "properties": {
    "addr:full":"Haverblok 11 Wouw North Brabant 4724 GB",
    "addr:housenumber":"11",
    "addr:postcode":"4724 gb",
    "addr:street":"Haverblok",
    "iso:country":"NL",
    "sg:address":"Haverblok 11",
    "sg:city":"Wouw",
    "sg:orig_category":"Meubelreparatie And -Restauratie",
    "sg:phone":"+31 165 303 150",
    "sg:postcode":"4724 GB",
    "sg:province":"North Brabant",
    "wof:name":"Huijbrechts Meubelmaker Meubel- & Woning",
    "wof:placetype":"venue"
},
  "geometry": {"coordinates":[4.391973,51.523586],"type":"Point"}
}