{
  "type": "Feature",
  "properties": {
    "addr:full":"Botshol 8 Abcoude North Holland 1391 HN",
    "addr:housenumber":"8",
    "addr:postcode":"1391 hn",
    "addr:street":"Botshol",
    "iso:country":"NL",
    "sg:address":"Botshol 8",
    "sg:city":"Abcoude",
    "sg:orig_category":"Loonbedrijven",
    "sg:phone":"+31 294 284 238",
    "sg:postcode":"1391 HN",
    "sg:province":"North Holland",
    "wof:name":"Groot & Zn, G J De",
    "wof:placetype":"venue"
},
  "geometry": {"coordinates":[4.932487,52.268341],"type":"Point"}
}