{
  "type": "Feature",
  "properties": {
    "addr:full":"Leugemorswg 1 Eibergen Gelderland 7151 ML",
    "addr:housenumber":"1",
    "addr:postcode":"7151 ml",
    "addr:street":"Leugemorswg;Gelderland",
    "iso:country":"NL",
    "sg:address":"Leugemorswg 1",
    "sg:city":"Eibergen",
    "sg:orig_category":"Psychologen",
    "sg:phone":"+31 545 431 969",
    "sg:postcode":"7151 ML",
    "sg:province":"Gelderland",
    "wof:name":"Wijga, S",
    "wof:placetype":"venue"
},
  "geometry": {"coordinates":[6.646672,52.108932],"type":"Point"}
}