{
  "type": "Feature",
  "properties": {
    "addr:full":"Henegouwerpln 4 Rotterdam Zuid-Holland 3021 PL",
    "addr:housenumber":"4",
    "addr:postcode":"3021 pl",
    "addr:street":"Henegouwerpln",
    "iso:country":"NL",
    "sg:address":"Henegouwerpln 4",
    "sg:city":"Rotterdam",
    "sg:orig_category":"Advocaten En Advocatenkantoren",
    "sg:phone":"+31 10 425 4004",
    "sg:postcode":"3021 PL",
    "sg:province":"Zuid-Holland",
    "wof:name":"Lo A Foe, M A",
    "wof:placetype":"venue"
},
  "geometry": {"coordinates":[4.462702,51.921185],"type":"Point"}
}