{
  "type": "Feature",
  "properties": {
    "iso:country":"NL",
    "sg:address":"Kl Houtstr 25",
    "sg:city":"Haarlem",
    "sg:orig_category":"Antiquiteiten",
    "sg:phone":"+31 23 532 8228",
    "sg:postcode":"2011 DD",
    "sg:province":"Noord-Holland",
    "wof:name":"Haarlem Antiek",
    "wof:placetype":"venue"
},
  "geometry": {"coordinates":[4.636588,52.378845],"type":"Point"}
}