{
  "type": "Feature",
  "properties": {
    "addr:full":"Schuitendiep 56 Groningen Groningen 9711 RE",
    "addr:housenumber":"56",
    "addr:postcode":"9711 re",
    "addr:street":"Schuitendiep",
    "iso:country":"NL",
    "sg:address":"Schuitendiep 56",
    "sg:city":"Groningen",
    "sg:orig_category":"Broodjeszaken",
    "sg:phone":"+31 50 589 1200",
    "sg:postcode":"9711 RE",
    "sg:province":"Groningen",
    "wof:name":"Petit Grande, Le",
    "wof:placetype":"venue"
},
  "geometry": {"coordinates":[6.57318,53.218388],"type":"Point"}
}