{
  "type": "Feature",
  "properties": {
    "addr:full":"Boeierln 55 Zaandam Noord-Holland 1503 JT",
    "addr:housenumber":"55",
    "addr:postcode":"1503 jt",
    "addr:street":"Boeierln",
    "iso:country":"NL",
    "sg:address":"Boeierln 55",
    "sg:city":"Zaandam",
    "sg:orig_category":"Verzekeringen - Verzekeringskantoren",
    "sg:phone":"+31 75 631 3850",
    "sg:postcode":"1503 JT",
    "sg:province":"Noord-Holland",
    "wof:name":"Broek, P G Ten",
    "wof:placetype":"venue"
},
  "geometry": {"coordinates":[4.84081,52.447651],"type":"Point"}
}