{
  "type": "Feature",
  "properties": {
    "addr:full":"Oranjekanaal Zuidzijde 17 Hijken Drenthe 9415 PR",
    "addr:housenumber":"17",
    "addr:postcode":"9415 pr",
    "addr:street":"Oranjekanaal Zuidzijde",
    "iso:country":"NL",
    "sg:address":"Oranjekanaal Zuidzijde 17",
    "sg:city":"Hijken",
    "sg:orig_category":"Verhuur Landbouwmachines",
    "sg:phone":"+31 593 524 066",
    "sg:postcode":"9415 PR",
    "sg:province":"Drenthe",
    "wof:name":"Wasse Bv",
    "wof:placetype":"venue"
},
  "geometry": {"coordinates":[6.499354,52.897312],"type":"Point"}
}