{
  "type": "Feature",
  "properties": {
    "addr:full":"Jisperwg 105A Westbeemster Noord-Holland 1464 NJ",
    "addr:housenumber":"105a",
    "addr:postcode":"1464 nj",
    "iso:country":"NL",
    "sg:address":"Jisperwg 105A",
    "sg:city":"Westbeemster",
    "sg:classifiers":[
        {
            "category":"Retail",
            "subcategory":"Auto Repair",
            "type":"Services"
        }
    ],
    "sg:phone":"+31 299 683 602",
    "sg:postcode":"1464 NJ",
    "sg:province":"Noord-Holland",
    "sg:tags":[
        "garage"
    ],
    "wof:name":"Tiesken",
    "wof:placetype":"venue"
},
  "geometry": {"coordinates":[4.889942,52.559418],"type":"Point"}
}