{
  "type": "Feature",
  "properties": {
    "addr:full":"Postbus 322 Nieuwegein Utrecht 3430 AH",
    "addr:housenumber":"322",
    "addr:postcode":"3430 ah",
    "addr:street":"Postbus",
    "iso:country":"NL",
    "sg:address":"Postbus 322",
    "sg:city":"Nieuwegein",
    "sg:orig_category":"Adviesbureaus Bouwkunde",
    "sg:phone":"+31 30 696 1581",
    "sg:postcode":"3430 AH",
    "sg:province":"Utrecht",
    "sg:website":"http://www.acabennu.nl",
    "wof:name":"B & U Advies Centrum Aanbestedingen",
    "wof:placetype":"venue"
},
  "geometry": {"coordinates":[5.082197,52.027325],"type":"Point"}
}