{
  "type": "Feature",
  "properties": {
    "addr:full":"Surinamewg 15 Apeldoorn Gelderland 7333 PC",
    "addr:housenumber":"15",
    "addr:postcode":"7333 pc",
    "addr:street":"Surinamewg;Gelderland",
    "iso:country":"NL",
    "sg:address":"Surinamewg 15",
    "sg:city":"Apeldoorn",
    "sg:orig_category":"Oud Metaal",
    "sg:phone":"+31 55 542 0086",
    "sg:postcode":"7333 PC",
    "sg:province":"Gelderland",
    "wof:name":"Rometa",
    "wof:placetype":"venue"
},
  "geometry": {"coordinates":[5.9720759392,52.1761054993],"type":"Point"}
}