{
  "type": "Feature",
  "properties": {
    "addr:full":"Postbus 16672 S Gravenhage Gelderland 2500 BR",
    "addr:housenumber":"16672",
    "addr:postcode":"2500 br",
    "addr:street":"Postbus;S Gravenhage Gelderland",
    "iso:country":"NL",
    "sg:address":"Postbus 16672",
    "sg:city":"S Gravenhage",
    "sg:orig_category":"Glazenwasserijen",
    "sg:phone":"+31 6 55788520",
    "sg:postcode":"2500 BR",
    "sg:province":"Gelderland",
    "wof:name":"Schmits, M",
    "wof:placetype":"venue"
},
  "geometry": {"coordinates":[4.31741,52.083988],"type":"Point"}
}