{
  "type": "Feature",
  "properties": {
    "addr:full":"Prinsengracht 81 Amsterdam North Holland 1015 DN",
    "addr:housenumber":"81",
    "addr:postcode":"1015 dn",
    "addr:street":"Prinsengracht",
    "iso:country":"NL",
    "sg:address":"Prinsengracht 81",
    "sg:city":"Amsterdam",
    "sg:orig_category":"Kappers",
    "sg:phone":"+31 20 627 4184",
    "sg:postcode":"1015 DN",
    "sg:province":"North Holland",
    "wof:name":"De Kapperij",
    "wof:placetype":"venue"
},
  "geometry": {"coordinates":[4.8877158165,52.3791618347],"type":"Point"}
}