{
  "type": "Feature",
  "properties": {
    "addr:full":"Kooltuin 8 Alkmaar Noord-Holland 1811 MG",
    "addr:housenumber":"8",
    "addr:postcode":"1811 mg",
    "addr:street":"Kooltuin",
    "iso:country":"NL",
    "sg:address":"Kooltuin 8",
    "sg:city":"Alkmaar",
    "sg:orig_category":"Architecten",
    "sg:phone":"+31 72 511 6421",
    "sg:postcode":"1811 MG",
    "sg:province":"Noord-Holland",
    "wof:name":"Architectenbureau Lody Trap Hbo Bna",
    "wof:placetype":"venue"
},
  "geometry": {"coordinates":[4.752639,52.631699],"type":"Point"}
}