{
  "type": "Feature",
  "properties": {
    "addr:full":"Cornelis Krusemanstraat 17 Amsterdam Noord-Holland 1075 NC",
    "addr:housenumber":"17;1075",
    "addr:postcode":"nc",
    "addr:street":"Cornelis Krusemanstraat",
    "iso:country":"NL",
    "sg:address":"Cornelis Krusemanstraat 17",
    "sg:city":"Amsterdam",
    "sg:orig_category":"Loodgieterswerk, Verwarming And Sanitaire Installaties",
    "sg:phone":"+31 20 679 5029",
    "sg:postcode":"1075 NC",
    "sg:province":"Noord-Holland",
    "wof:name":"Tom Janssen",
    "wof:placetype":"venue"
},
  "geometry": {"coordinates":[4.862707,52.351086],"type":"Point"}
}