{
  "type": "Feature",
  "properties": {
    "addr:full":"De Els 18 Didam Gelderland 6942 TK",
    "addr:housenumber":"18",
    "addr:postcode":"6942 tk",
    "addr:street":"De Els;Gelderland",
    "iso:country":"NL",
    "sg:address":"De Els 18",
    "sg:city":"Didam",
    "sg:orig_category":"Koeriersdiensten",
    "sg:phone":"+31 6 22777332",
    "sg:postcode":"6942 TK",
    "sg:province":"Gelderland",
    "wof:name":"Jordi",
    "wof:placetype":"venue"
},
  "geometry": {"coordinates":[6.138927,51.945885],"type":"Point"}
}