{
  "type": "Feature",
  "properties": {
    "iso:country":"NL",
    "sg:address":"Kerkstr 5",
    "sg:city":"Rynsburg",
    "sg:orig_category":"Zalenverhuur",
    "sg:phone":"+31 71 402 1038",
    "sg:postcode":"2231 CW",
    "sg:province":"South Holland",
    "wof:name":"Centrum, 'T",
    "wof:placetype":"venue"
},
  "geometry": {"coordinates":[4.442628,52.190884],"type":"Point"}
}