{
  "type": "Feature",
  "properties": {
    "addr:full":"Fazantenlaan 1 Hellevoetsluis Zuid-Holland 3222 AM",
    "addr:housenumber":"1",
    "addr:postcode":"3222",
    "addr:street":"Fazantenlaan",
    "iso:country":"NL",
    "sg:address":"Fazantenlaan 1",
    "sg:city":"Hellevoetsluis",
    "sg:orig_category":"Volwassenenonderwijs",
    "sg:phone":"+31 181 316 488",
    "sg:postcode":"3222 AM",
    "sg:province":"Zuid-Holland",
    "wof:name":"Gem Scholengemeenschap Helinium",
    "wof:placetype":"venue"
},
  "geometry": {"coordinates":[4.120158,51.835155],"type":"Point"}
}