{
  "type": "Feature",
  "properties": {
    "iso:country":"NL",
    "sg:address":"Werfkd 30",
    "sg:city":"Ridderkerk",
    "sg:orig_category":"Homeopathie",
    "sg:phone":"+31 6 23939555",
    "sg:postcode":"2987 RH",
    "sg:province":"Zuid-Holland",
    "sg:website":"http://www.vitaalinbalans.com",
    "wof:name":"Vitaal In Balans",
    "wof:placetype":"venue"
},
  "geometry": {"coordinates":[4.58259,51.890572],"type":"Point"}
}