{
  "type": "Feature",
  "properties": {
    "addr:full":"Innsbruckwg 226 Rotterdam Zuid-Holland 3047 AH",
    "addr:housenumber":"226",
    "addr:postcode":"3047 ah",
    "iso:country":"NL",
    "sg:address":"Innsbruckwg 226",
    "sg:city":"Rotterdam",
    "sg:orig_category":"Adviesbureaus",
    "sg:phone":"+31 10 415 1754",
    "sg:postcode":"3047 AH",
    "sg:province":"Zuid-Holland",
    "wof:name":"Utc",
    "wof:placetype":"venue"
},
  "geometry": {"coordinates":[4.414001,51.941528],"type":"Point"}
}