{
  "type": "Feature",
  "properties": {
    "iso:country":"NL",
    "sg:address":"Schriksestraat 26",
    "sg:city":"Afferden Gld",
    "sg:orig_category":"Pluimveehouderijen",
    "sg:phone":"+31 487 512 415",
    "sg:postcode":"6654 AN",
    "sg:province":"Gelderland",
    "wof:name":"A. De Jong-Litjens",
    "wof:placetype":"venue"
},
  "geometry": {"coordinates":[5.635854,51.878498],"type":"Point"}
}