{
  "type": "Feature",
  "properties": {
    "addr:full":"Schriksestraat 26 Afferden Gld Gelderland 6654 AN",
    "addr:housenumber":"26",
    "addr:postcode":"6654 an",
    "addr:street":"Schriksestraat;Gld Gelderland",
    "iso:country":"NL",
    "sg:address":"Schriksestraat 26",
    "sg:city":"Afferden Gld",
    "sg:orig_category":"Pluimveehouderijen",
    "sg:phone":"+31 487 512 415",
    "sg:postcode":"6654 AN",
    "sg:province":"Gelderland",
    "wof:name":"A. De Jong-Litjens",
    "wof:placetype":"venue"
},
  "geometry": {"coordinates":[5.635854,51.878498],"type":"Point"}
}