{
  "type": "Feature",
  "properties": {
    "addr:full":"De Brink 3 Rhenoy Gelderland 4152 GA",
    "addr:housenumber":"3",
    "addr:postcode":"4152 ga",
    "addr:street":"De Brink;Gelderland",
    "iso:country":"NL",
    "sg:address":"De Brink 3",
    "sg:city":"Rhenoy",
    "sg:orig_category":"Adviesbureaus Bouwkunde",
    "sg:phone":"+31 345 682 526",
    "sg:postcode":"4152 GA",
    "sg:province":"Gelderland",
    "sg:website":"http://www.baasbouwadviezen.nl",
    "wof:name":"Baas",
    "wof:placetype":"venue"
},
  "geometry": {"coordinates":[-83.222931,32.678131],"type":"Point"}
}