{
  "type": "Feature",
  "properties": {
    "addr:full":"Pastoor Van Muijenweg 12 Heiloo Noord-Holland 1852 EH",
    "addr:housenumber":"12",
    "addr:postcode":"1852 eh",
    "addr:street":"Pastoor Van Muijenweg",
    "iso:country":"NL",
    "sg:address":"Pastoor Van Muijenweg 12",
    "sg:city":"Heiloo",
    "sg:orig_category":"Overheidsdiensten",
    "sg:phone":"+31 72 532 1048",
    "sg:postcode":"1852 EH",
    "sg:province":"Noord-Holland",
    "wof:name":"Buk Buk Jongerencentrum",
    "wof:placetype":"venue"
},
  "geometry": {"coordinates":[4.6980128288,52.6011199951],"type":"Point"}
}