{
  "type": "Feature",
  "properties": {
    "addr:full":"Zuiderdiep 187 Drouwenermond Provincie Drenthe 9523 TE",
    "addr:housenumber":"187;9523",
    "addr:postcode":"te",
    "addr:street":"Zuiderdiep;Provincie Drenthe",
    "iso:country":"NL",
    "sg:address":"Zuiderdiep 187",
    "sg:city":"Drouwenermond",
    "sg:orig_category":"Granen, Zaden And Diervoeders Gh",
    "sg:phone":"+31 599 617 386",
    "sg:postcode":"9523 TE",
    "sg:province":"Provincie Drenthe",
    "wof:name":"Groothandel Kramer-Mensinga",
    "wof:placetype":"venue"
},
  "geometry": {"coordinates":[6.921523,52.982712],"type":"Point"}
}