{
  "type": "Feature",
  "properties": {
    "iso:country":"NL",
    "sg:address":"Zuiderdiep 187",
    "sg:city":"Drouwenermond",
    "sg:orig_category":"Granen, Zaden And Diervoeders Gh",
    "sg:phone":"+31 599 617 386",
    "sg:postcode":"9523 TE",
    "sg:province":"Provincie Drenthe",
    "wof:name":"Groothandel Kramer-Mensinga",
    "wof:placetype":"venue"
},
  "geometry": {"coordinates":[6.921523,52.982712],"type":"Point"}
}