{
  "type": "Feature",
  "properties": {
    "addr:full":"Rumpsterwg 12 Bunnik Utrecht 3981 AK",
    "addr:housenumber":"12",
    "addr:postcode":"3981 ak",
    "addr:street":"Rumpsterwg",
    "iso:country":"NL",
    "sg:address":"Rumpsterwg 12",
    "sg:city":"Bunnik",
    "sg:classifiers":[
        {
            "category":"Home & Garden",
            "subcategory":"Hardware",
            "type":"Retail Goods"
        }
    ],
    "sg:phone":"+31 30 657 2006",
    "sg:postcode":"3981 AK",
    "sg:province":"Utrecht",
    "sg:tags":[
        "machine",
        "-",
        "metaalbewerking"
    ],
    "wof:name":"Gadellaa Edm Bv",
    "wof:placetype":"venue"
},
  "geometry": {"coordinates":[5.21769,52.063179],"type":"Point"}
}