{
  "type": "Feature",
  "properties": {
    "addr:full":"Hermelijnkwartier 43 Cuijk Noord-Brabant 5431 KJ",
    "addr:housenumber":"43",
    "addr:postcode":"5431 kj",
    "addr:street":"Hermelijnkwartier",
    "iso:country":"NL",
    "sg:address":"Hermelijnkwartier 43",
    "sg:city":"Cuijk",
    "sg:classifiers":[
        {
            "category":"Education",
            "subcategory":"Preschool",
            "type":"Public Place"
        }
    ],
    "sg:phone":"+31 485 315 163",
    "sg:postcode":"5431 KJ",
    "sg:province":"Noord-Brabant",
    "sg:tags":[
        "kleuteronderwijs",
        "basis-"
    ],
    "wof:name":"Openbare Basisschool Harlekijn",
    "wof:placetype":"venue"
},
  "geometry": {"coordinates":[5.8878011703,51.7149505615],"type":"Point"}
}