{
  "type": "Feature",
  "properties": {
    "addr:full":"Chopinln 10 Apeldoorn Gelderland 7333 GD",
    "addr:housenumber":"10",
    "addr:postcode":"7333 gd",
    "addr:street":"Chopinln;Gelderland",
    "iso:country":"NL",
    "sg:address":"Chopinln 10",
    "sg:city":"Apeldoorn",
    "sg:orig_category":"Kinderactiviteiten",
    "sg:phone":"+31 55 844 1210",
    "sg:postcode":"7333 GD",
    "sg:province":"Gelderland",
    "sg:website":"http://www.karoesel.nl",
    "wof:name":"Karoesel",
    "wof:placetype":"venue"
},
  "geometry": {"coordinates":[5.963933,52.186432],"type":"Point"}
}