{
  "type": "Feature",
  "properties": {
    "addr:full":"Gr Adolfstr 33 Ridderkerk South Holland 2983 HA",
    "addr:housenumber":"33",
    "addr:postcode":"2983 ha",
    "iso:country":"NL",
    "sg:address":"Gr Adolfstr 33",
    "sg:city":"Ridderkerk",
    "sg:orig_category":"Onderhoudswerken",
    "sg:phone":"+31 6 48230222",
    "sg:postcode":"2983 HA",
    "sg:province":"South Holland",
    "wof:name":"Amapa",
    "wof:placetype":"venue"
},
  "geometry": {"coordinates":[4.610469,51.884495],"type":"Point"}
}