{
  "type": "Feature",
  "properties": {
    "addr:full":"Duindoornstr 15 Grootegast Groningen 9861 CX",
    "addr:housenumber":"15",
    "addr:postcode":"9861 cx",
    "addr:street":"Duindoornstr",
    "iso:country":"NL",
    "sg:address":"Duindoornstr 15",
    "sg:city":"Grootegast",
    "sg:orig_category":"Boeken En Tijdschriften - Groothandel",
    "sg:phone":"+31 594 612 760",
    "sg:postcode":"9861 CX",
    "sg:province":"Groningen",
    "wof:name":"Sitra",
    "wof:placetype":"venue"
},
  "geometry": {"coordinates":[6.272321,53.209103],"type":"Point"}
}