{
  "type": "Feature",
  "properties": {
    "addr:full":"Talmastraat 20 Nijkerkerveen Gelderland 3864 DE",
    "addr:housenumber":"20",
    "addr:postcode":"3864 de",
    "addr:street":"Talmastraat;Gelderland",
    "iso:country":"NL",
    "sg:address":"Talmastraat 20",
    "sg:city":"Nijkerkerveen",
    "sg:orig_category":"Autokeuringen",
    "sg:phone":"+31 33 253 8383",
    "sg:postcode":"3864 DE",
    "sg:province":"Gelderland",
    "wof:name":"Habo Nijkerk Bv",
    "wof:placetype":"venue"
},
  "geometry": {"coordinates":[5.471193,52.195992],"type":"Point"}
}