{
  "type": "Feature",
  "properties": {
    "iso:country":"NL",
    "sg:address":"Kalverstraat 26-28",
    "sg:city":"Veghel",
    "sg:classifiers":[
        {
            "category":"Food & Beverages",
            "subcategory":"Fruits & Vegetables",
            "type":"Retail Goods"
        }
    ],
    "sg:phone":"+31 413 363 690",
    "sg:postcode":"5461 JL",
    "sg:province":"North Brabant",
    "sg:tags":[
        "groenten"
    ],
    "wof:name":"Van Lankveld Groente En Fruit",
    "wof:placetype":"venue"
},
  "geometry": {"coordinates":[5.544058,51.616844],"type":"Point"}
}