{
  "type": "Feature",
  "properties": {
    "addr:full":"Zoomstede 16 Nieuwegein Utrecht 3431 HL",
    "addr:housenumber":"16",
    "addr:postcode":"3431 hl",
    "addr:street":"Zoomstede",
    "iso:country":"NL",
    "sg:address":"Zoomstede 16",
    "sg:city":"Nieuwegein",
    "sg:orig_category":"Filters - Fabrieken En Groothandel",
    "sg:phone":"+31 30 603 0049",
    "sg:postcode":"3431 HL",
    "sg:province":"Utrecht",
    "wof:name":"Ultrafilter Bv",
    "wof:placetype":"venue"
},
  "geometry": {"coordinates":[5.082595,52.027229],"type":"Point"}
}