{
  "type": "Feature",
  "properties": {
    "addr:full":"Saeftinge 83 Haarlem North Holland 2036 GZ",
    "addr:housenumber":"83",
    "addr:postcode":"2036 gz",
    "addr:street":"Saeftinge",
    "iso:country":"NL",
    "sg:address":"Saeftinge 83",
    "sg:city":"Haarlem",
    "sg:orig_category":"Pianostemmen En -Reparatie",
    "sg:phone":"+31 23 535 2333",
    "sg:postcode":"2036 GZ",
    "sg:province":"North Holland",
    "wof:name":"Laan, H B Van Der",
    "wof:placetype":"venue"
},
  "geometry": {"coordinates":[4.650638,52.34697],"type":"Point"}
}