{
  "type": "Feature",
  "properties": {
    "addr:full":"Kronehoefstr 85 Eindhoven North Brabant 5612 HL",
    "addr:housenumber":"85",
    "addr:postcode":"5612 hl",
    "addr:street":"Kronehoefstr",
    "iso:country":"NL",
    "sg:address":"Kronehoefstr 85",
    "sg:city":"Eindhoven",
    "sg:orig_category":"Woningbouw- Verenigingen En -Stichtingen",
    "sg:phone":"+31 40 296 8222",
    "sg:postcode":"5612 HL",
    "sg:province":"North Brabant",
    "wof:name":"Domein",
    "wof:placetype":"venue"
},
  "geometry": {"coordinates":[5.4651618004,51.4517250061],"type":"Point"}
}