{
  "type": "Feature",
  "properties": {
    "addr:full":"Leidschestraatweg 14A Woerden Utrecht 3443 BV",
    "addr:housenumber":"14a",
    "addr:postcode":"3443 bv",
    "addr:street":"Leidschestraatweg",
    "iso:country":"NL",
    "sg:address":"Leidschestraatweg 14A",
    "sg:city":"Woerden",
    "sg:orig_category":"Metaalwerken",
    "sg:phone":"+31 348 413 702",
    "sg:postcode":"3443 BV",
    "sg:province":"Utrecht",
    "wof:name":"Hoogenboom Systeemplafonds",
    "wof:placetype":"venue"
},
  "geometry": {"coordinates":[4.879732,52.088066],"type":"Point"}
}