{
  "type": "Feature",
  "properties": {
    "addr:full":"Heer Oudelandsln 2 Zwyndrecht Zuid-Holland 3335 LC",
    "addr:housenumber":"2",
    "addr:postcode":"3335 lc",
    "addr:street":"Heer Oudelandsln",
    "iso:country":"NL",
    "sg:address":"Heer Oudelandsln 2",
    "sg:city":"Zwyndrecht",
    "sg:classifiers":[
        {
            "category":"Retail",
            "subcategory":"Auto Repair",
            "type":"Services"
        }
    ],
    "sg:phone":"+31 78 610 1679",
    "sg:postcode":"3335 LC",
    "sg:province":"Zuid-Holland",
    "sg:tags":[
        "garage"
    ],
    "wof:name":"Deelen, J Van",
    "wof:placetype":"venue"
},
  "geometry": {"coordinates":[4.60712,51.827839],"type":"Point"}
}