{
  "type": "Feature",
  "properties": {
    "addr:full":"Amersfoortsestr 17 Barneveld Gelderland 3772 CE",
    "addr:housenumber":"17",
    "addr:postcode":"3772 ce",
    "addr:street":"Amersfoortsestr;Gelderland",
    "iso:country":"NL",
    "sg:address":"Amersfoortsestr 17",
    "sg:city":"Barneveld",
    "sg:orig_category":"Accountants - Administratie- Consulenten En -Kantoren",
    "sg:phone":"+31 342 421 100",
    "sg:postcode":"3772 CE",
    "sg:province":"Gelderland",
    "wof:name":"Houting, Den",
    "wof:placetype":"venue"
},
  "geometry": {"coordinates":[5.582614,52.138901],"type":"Point"}
}