{
  "type": "Feature",
  "properties": {
    "iso:country":"NL",
    "sg:address":"Kennemerlaan 167",
    "sg:city":"Ijmuiden",
    "sg:orig_category":"Metaalwerken",
    "sg:phone":"+31 255 536 565",
    "sg:postcode":"1972 EM",
    "sg:province":"Noord-Holland",
    "wof:name":"Rene Meijer Speciaalvloeren",
    "wof:placetype":"venue"
},
  "geometry": {"coordinates":[4.612508,52.459896],"type":"Point"}
}