{
  "type": "Feature",
  "properties": {
    "addr:full":"Oosterblokker 78 Oosterblokker Noord-Holland 1696 BJ",
    "addr:housenumber":"78",
    "addr:postcode":"1696 bj",
    "addr:street":"Oosterblokker",
    "iso:country":"NL",
    "sg:address":"Oosterblokker 78",
    "sg:city":"Oosterblokker",
    "sg:orig_category":"Binnenhuisarchitectuur",
    "sg:phone":"+31 229 263 937",
    "sg:postcode":"1696 BJ",
    "sg:province":"Noord-Holland",
    "sg:website":"http://www.waitandsee.nl",
    "wof:name":"Wait & See",
    "wof:placetype":"venue"
},
  "geometry": {"coordinates":[5.117354,52.668621],"type":"Point"}
}