{
  "type": "Feature",
  "properties": {
    "addr:full":"Saelberngenplantsoen 12 Panningen Limburg 5981 EN",
    "addr:housenumber":"12",
    "addr:postcode":"5981 en",
    "addr:street":"Saelberngenplantsoen",
    "iso:country":"NL",
    "sg:address":"Saelberngenplantsoen 12",
    "sg:city":"Panningen",
    "sg:orig_category":"Artsen And Specialisten",
    "sg:phone":"+31 77 307 4914",
    "sg:postcode":"5981 EN",
    "sg:province":"Limburg",
    "wof:name":"G. Beckers",
    "wof:placetype":"venue"
},
  "geometry": {"coordinates":[5.984664,51.325287],"type":"Point"}
}