{
  "type": "Feature",
  "properties": {
    "addr:full":"Herestr 17 Grypskerk Groningen 9843 AH",
    "addr:housenumber":"17",
    "addr:postcode":"9843 ah",
    "addr:street":"Herestr",
    "iso:country":"NL",
    "sg:address":"Herestr 17",
    "sg:city":"Grypskerk",
    "sg:orig_category":"Juweliers",
    "sg:phone":"+31 594 213 290",
    "sg:postcode":"9843 AH",
    "sg:province":"Groningen",
    "wof:name":"Gardenier, Nynke",
    "wof:placetype":"venue"
},
  "geometry": {"coordinates":[6.308585,53.263828],"type":"Point"}
}