{
  "type": "Feature",
  "properties": {
    "addr:full":"Borkeldwg 1 Markelo NL.08 7475 RV",
    "addr:housenumber":"1;nl.08",
    "addr:postcode":"7475 rv",
    "addr:street":"Borkeldwg",
    "iso:country":"NL",
    "sg:address":"Borkeldwg 1",
    "sg:city":"Markelo",
    "sg:classifiers":[
        {
            "category":"Sports & Exercise",
            "subcategory":"Stables",
            "type":"Entertainment"
        }
    ],
    "sg:phone":"+31 547 361 471",
    "sg:postcode":"7475 RV",
    "sg:province":"NL.08",
    "sg:tags":[
        "maneges"
    ],
    "wof:name":"Snorrewind Markelo, Manege",
    "wof:placetype":"venue"
},
  "geometry": {"coordinates":[6.461199,52.260925],"type":"Point"}
}