{
  "type": "Feature",
  "properties": {
    "addr:full":"Industriestraat 63 Haaksbergen Overijssel 7482 EW",
    "addr:housenumber":"63",
    "addr:postcode":"7482 ew",
    "addr:street":"Industriestraat",
    "iso:country":"NL",
    "sg:address":"Industriestraat 63",
    "sg:city":"Haaksbergen",
    "sg:orig_category":"Drukkerijen And Copyshops",
    "sg:phone":"+31 53 572 1609",
    "sg:postcode":"7482 EW",
    "sg:province":"Overijssel",
    "wof:name":"Hatefa Bv",
    "wof:placetype":"venue"
},
  "geometry": {"coordinates":[6.721509,52.151974],"type":"Point"}
}