{
  "type": "Feature",
  "properties": {
    "addr:full":"Reeenspoor 1 Hoevelaken Gelderland 3871 JR",
    "addr:housenumber":"1",
    "addr:postcode":"3871 jr",
    "addr:street":"Reeenspoor;Gelderland",
    "iso:country":"NL",
    "sg:address":"Reeenspoor 1",
    "sg:city":"Hoevelaken",
    "sg:orig_category":"Adviesbureaus Bedrijfsorganisatie",
    "sg:phone":"+31 33 494 8667",
    "sg:postcode":"3871 JR",
    "sg:province":"Gelderland",
    "sg:website":"http://www.pythagoras-advies.nl",
    "wof:name":"Pythagoras",
    "wof:placetype":"venue"
},
  "geometry": {"coordinates":[5.463266,52.169571],"type":"Point"}
}