{
  "type": "Feature",
  "properties": {
    "addr:full":"Marconistr 38 Landgraaf Limburg 6372 PN",
    "addr:housenumber":"38",
    "addr:postcode":"6372 pn",
    "addr:street":"Marconistr",
    "iso:country":"NL",
    "sg:address":"Marconistr 38",
    "sg:city":"Landgraaf",
    "sg:orig_category":"Beveiliging",
    "sg:phone":"+31 45 531 1923",
    "sg:postcode":"6372 PN",
    "sg:province":"Limburg",
    "sg:website":"http://www.detec.nl",
    "wof:name":"Detec Beveiligingstechniek",
    "wof:placetype":"venue"
},
  "geometry": {"coordinates":[6.026755,50.890434],"type":"Point"}
}