{
  "type": "Feature",
  "properties": {
    "addr:full":"Rembrandtln 202 Papendrecht Zuid-Holland 3351 RL",
    "addr:housenumber":"202",
    "addr:postcode":"papendrecht;3351 rl",
    "iso:country":"NL",
    "sg:address":"Rembrandtln 202",
    "sg:city":"Papendrecht",
    "sg:orig_category":"Sportverenigingen En Ontspannings- Verenigingen",
    "sg:phone":"+31 78 615 9336",
    "sg:postcode":"3351 RL",
    "sg:province":"Zuid-Holland",
    "sg:website":"http://www.eteha.nl/zvv",
    "wof:name":"Eteha Zaalvoetbalver",
    "wof:placetype":"venue"
},
  "geometry": {"coordinates":[4.680385,51.834534],"type":"Point"}
}