{
  "type": "Feature",
  "properties": {
    "addr:full":"Postbus 60 Gennep Limburg 6590 AB",
    "addr:housenumber":"60",
    "addr:postcode":"6590 ab",
    "addr:street":"Postbus",
    "iso:country":"NL",
    "sg:address":"Postbus 60",
    "sg:city":"Gennep",
    "sg:classifiers":[
        {
            "category":"Shopping",
            "subcategory":"News",
            "type":"Retail Goods"
        }
    ],
    "sg:phone":"+31 485 512 216",
    "sg:postcode":"6590 AB",
    "sg:province":"Limburg",
    "sg:tags":[
        "maandbladen",
        "en",
        "week-"
    ],
    "wof:name":"Brug Venlo, De",
    "wof:placetype":"venue"
},
  "geometry": {"coordinates":[5.9711899757,51.6992988586],"type":"Point"}
}