{
  "type": "Feature",
  "properties": {
    "iso:country":"NL",
    "sg:address":"Hoge Veld 26",
    "sg:city":"Aalten",
    "sg:orig_category":"Bejaardeninstellingen And Serviceflats",
    "sg:phone":"+31 543 473 661",
    "sg:postcode":"7122 ZR",
    "sg:province":"Gelderland",
    "wof:name":"St Zorgcombinatie Marga Klompe 'T Hoge Veld",
    "wof:placetype":"venue"
},
  "geometry": {"coordinates":[6.575307,51.930729],"type":"Point"}
}