{
  "type": "Feature",
  "properties": {
    "iso:country":"NL",
    "sg:address":"Rucphensebaan 58",
    "sg:city":"Roosendaal",
    "sg:orig_category":"Fruitteelt",
    "sg:phone":"+31 165 542 942",
    "sg:postcode":"4706 PJ",
    "sg:province":"North Brabant",
    "wof:name":"Rapo Bv",
    "wof:placetype":"venue"
},
  "geometry": {"coordinates":[4.49782,51.535728],"type":"Point"}
}