{
  "type": "Feature",
  "properties": {
    "iso:country":"NL",
    "sg:address":"Kd V Ras 6",
    "sg:city":"De Lier",
    "sg:orig_category":"Exploitatie- Maatschappijen",
    "sg:phone":"+31 174 513 127",
    "sg:postcode":"2678 LZ",
    "sg:province":"South Holland",
    "sg:website":"http://www.okplant.nl",
    "wof:name":"Ok Plant",
    "wof:placetype":"venue"
},
  "geometry": {"coordinates":[4.25138,51.975086],"type":"Point"}
}