{
  "type": "Feature",
  "properties": {
    "addr:full":"Stadsring 141 Amersfoort Utrecht 3817 BA",
    "addr:housenumber":"141",
    "addr:postcode":"3817 ba",
    "addr:street":"Stadsring",
    "iso:country":"NL",
    "sg:address":"Stadsring 141",
    "sg:city":"Amersfoort",
    "sg:orig_category":"Verzekeringen",
    "sg:phone":"+31 33 463 8888",
    "sg:postcode":"3817 BA",
    "sg:province":"Utrecht",
    "wof:name":"Lagerwij & Potter Bv",
    "wof:placetype":"venue"
},
  "geometry": {"coordinates":[5.391378,52.152508],"type":"Point"}
}