{
  "type": "Feature",
  "properties": {
    "addr:full":"Ds V Dorpstr 3 Gendringen Gelderland 7081 BD",
    "addr:housenumber":"3",
    "addr:postcode":"7081 bd",
    "addr:street":"Ds V Dorpstr;Gelderland",
    "iso:country":"NL",
    "sg:address":"Ds V Dorpstr 3",
    "sg:city":"Gendringen",
    "sg:orig_category":"Kinderopvang",
    "sg:phone":"+31 315 632 035",
    "sg:postcode":"7081 BD",
    "sg:province":"Gelderland",
    "wof:name":"Berend Botje",
    "wof:placetype":"venue"
},
  "geometry": {"coordinates":[6.3795,51.870861],"type":"Point"}
}