{
  "type": "Feature",
  "properties": {
    "addr:full":"Stuijvezandeweg 51 Callantsoog North Holland 1759 GB",
    "addr:housenumber":"51",
    "addr:postcode":"1759 gb",
    "addr:street":"Stuijvezandeweg",
    "iso:country":"NL",
    "sg:address":"Stuijvezandeweg 51",
    "sg:city":"Callantsoog",
    "sg:orig_category":"Boekhouders",
    "sg:phone":"+31 224 581 860",
    "sg:postcode":"1759 GB",
    "sg:province":"North Holland",
    "wof:name":"J.F. De Bakker",
    "wof:placetype":"venue"
},
  "geometry": {"coordinates":[4.696424,52.839642],"type":"Point"}
}