{
  "type": "Feature",
  "properties": {
    "addr:full":"Ambachtsstr 2 Poortugaal Zuid-Holland 3176 PR",
    "addr:housenumber":"2",
    "addr:postcode":"3176 pr",
    "addr:street":"Ambachtsstr",
    "iso:country":"NL",
    "sg:address":"Ambachtsstr 2",
    "sg:city":"Poortugaal",
    "sg:orig_category":"Meubelstoffering",
    "sg:phone":"+31 10 501 6566",
    "sg:postcode":"3176 PR",
    "sg:province":"Zuid-Holland",
    "wof:name":"Stoffeerderij Rhoon",
    "wof:placetype":"venue"
},
  "geometry": {"coordinates":[4.40617,51.85976],"type":"Point"}
}