{
  "type": "Feature",
  "properties": {
    "addr:full":"Willaertpln 9 Eindhoven Noord-Brabant 5654 LN",
    "addr:housenumber":"9",
    "addr:postcode":"5654 ln",
    "addr:street":"Willaertpln",
    "iso:country":"NL",
    "sg:address":"Willaertpln 9",
    "sg:city":"Eindhoven",
    "sg:orig_category":"Medische Installaties En Instrumenten",
    "sg:phone":"+31 40 251 4955",
    "sg:postcode":"5654 LN",
    "sg:province":"Noord-Brabant",
    "wof:name":"Xaratax Bv",
    "wof:placetype":"venue"
},
  "geometry": {"coordinates":[5.461013,51.422646],"type":"Point"}
}