{
  "type": "Feature",
  "properties": {
    "addr:full":"Vorstengrafln 1A Oss Virginia 5342 LM",
    "addr:housenumber":"1a",
    "addr:postcode":"5342 lm",
    "addr:street":"Vorstengrafln",
    "iso:country":"NL",
    "sg:address":"Vorstengrafln 1A",
    "sg:city":"Oss",
    "sg:orig_category":"Verzekeringen - Verzekeringskantoren",
    "sg:phone":"+31 412 457 406",
    "sg:postcode":"5342 LM",
    "sg:province":"Virginia",
    "wof:name":"Bens & Van Der Hall",
    "wof:placetype":"venue"
},
  "geometry": {"coordinates":[-77.235214,38.312599],"type":"Point"}
}