{
  "type": "Feature",
  "properties": {
    "addr:full":"Tandwielstr 20 Rotterdam Zuid-Holland 3083 AV",
    "addr:housenumber":"20",
    "addr:postcode":"3083 av",
    "addr:street":"Tandwielstr",
    "iso:country":"NL",
    "sg:address":"Tandwielstr 20",
    "sg:city":"Rotterdam",
    "sg:classifiers":[
        {
            "category":"Retail",
            "subcategory":"Auto Repair",
            "type":"Services"
        }
    ],
    "sg:phone":"+31 10 485 2361",
    "sg:postcode":"3083 AV",
    "sg:province":"Zuid-Holland",
    "sg:tags":[
        "garage"
    ],
    "sg:website":"http://www.swarttouw.demon.nl",
    "wof:name":"Swarttouw & Znn, J A",
    "wof:placetype":"venue"
},
  "geometry": {"coordinates":[4.496186,51.886116],"type":"Point"}
}