{
  "type": "Feature",
  "properties": {
    "addr:full":"T Mannplaats 158 Rotterdam Zuid-Holland 3069 NG",
    "addr:housenumber":"158",
    "addr:postcode":"3069 ng",
    "addr:street":"T Mannplaats",
    "iso:country":"NL",
    "sg:address":"T Mannplaats 158",
    "sg:city":"Rotterdam",
    "sg:orig_category":"Kappers",
    "sg:phone":"+31 10 251 1775",
    "sg:postcode":"3069 NG",
    "sg:province":"Zuid-Holland",
    "wof:name":"Vivi Kapsalon",
    "wof:placetype":"venue"
},
  "geometry": {"coordinates":[4.553776,51.964249],"type":"Point"}
}