{
  "type": "Feature",
  "properties": {
    "addr:full":"Zwanestr 41 Groningen Groningen 9712 CK",
    "addr:housenumber":"41",
    "addr:postcode":"9712 ck",
    "addr:street":"Zwanestr",
    "iso:country":"NL",
    "sg:address":"Zwanestr 41",
    "sg:city":"Groningen",
    "sg:orig_category":"Boeken En Tijdschriften",
    "sg:phone":"+31 50 312 6749",
    "sg:postcode":"9712 CK",
    "sg:province":"Groningen",
    "wof:name":"Boomker & Savenije",
    "wof:placetype":"venue"
},
  "geometry": {"coordinates":[6.563389,53.218288],"type":"Point"}
}