{
  "type": "Feature",
  "properties": {
    "addr:full":"Spinnerstraat 17G Rijssen Overijssel 7461 TV",
    "addr:housenumber":"17g",
    "addr:postcode":"7461 tv",
    "addr:street":"Spinnerstraat",
    "iso:country":"NL",
    "sg:address":"Spinnerstraat 17G",
    "sg:city":"Rijssen",
    "sg:orig_category":"Autokeuringen",
    "sg:phone":"+31 548 522 314",
    "sg:postcode":"7461 TV",
    "sg:province":"Overijssel",
    "wof:name":"Van Heek Motorsport",
    "wof:placetype":"venue"
},
  "geometry": {"coordinates":[6.506696,52.316551],"type":"Point"}
}