{
  "type": "Feature",
  "properties": {
    "addr:full":"Provincialeweg West 7 Haastrecht South Holland 2851 EH",
    "addr:housenumber":"7",
    "addr:postcode":"2851 eh",
    "addr:street":"Provincialeweg West",
    "iso:country":"NL",
    "sg:address":"Provincialeweg West 7",
    "sg:city":"Haastrecht",
    "sg:orig_category":"Public Relationbureaus",
    "sg:phone":"+31 182 509 238",
    "sg:postcode":"2851 EH",
    "sg:province":"South Holland",
    "wof:name":"Merla",
    "wof:placetype":"venue"
},
  "geometry": {"coordinates":[4.76809,52.000568],"type":"Point"}
}