{
  "type": "Feature",
  "properties": {
    "addr:full":"Kotterkd 113 Ymuiden North Holland 1976 DL",
    "addr:housenumber":"113",
    "addr:postcode":"1976 dl",
    "addr:street":"Ymuiden North",
    "iso:country":"NL",
    "sg:address":"Kotterkd 113",
    "sg:city":"Ymuiden",
    "sg:orig_category":"Koel- En Vriestransporten",
    "sg:phone":"+31 255 523 840",
    "sg:postcode":"1976 DL",
    "sg:province":"North Holland",
    "wof:name":"Kloos Holland Bv, J",
    "wof:placetype":"venue"
},
  "geometry": {"coordinates":[4.61762,52.458302],"type":"Point"}
}