{
  "type": "Feature",
  "properties": {
    "addr:full":"Dorpsstr 28 Wilnis Utrecht 3648 AH",
    "addr:housenumber":"28",
    "addr:postcode":"3648 ah",
    "addr:street":"Dorpsstr",
    "iso:country":"NL",
    "sg:address":"Dorpsstr 28",
    "sg:city":"Wilnis",
    "sg:orig_category":"Banken",
    "sg:phone":"+31 297 292 600",
    "sg:postcode":"3648 AH",
    "sg:province":"Utrecht",
    "sg:website":"http://www.rabobank.nl",
    "wof:name":"Rabobank",
    "wof:placetype":"venue"
},
  "geometry": {"coordinates":[4.903706,52.195187],"type":"Point"}
}