{
  "type": "Feature",
  "properties": {
    "addr:full":"Schoolakkerpln 54 Breda Noord-Brabant 4835 EJ",
    "addr:housenumber":"54",
    "addr:postcode":"4835 ej",
    "addr:street":"Schoolakkerpln",
    "iso:country":"NL",
    "sg:address":"Schoolakkerpln 54",
    "sg:city":"Breda",
    "sg:orig_category":"Loopbaanbegeleiding",
    "sg:phone":"+31 76 565 7460",
    "sg:postcode":"4835 EJ",
    "sg:province":"Noord-Brabant",
    "wof:name":"Edeladvies",
    "wof:placetype":"venue"
},
  "geometry": {"coordinates":[4.788572,51.567623],"type":"Point"}
}