{
  "type": "Feature",
  "properties": {
    "addr:full":"Zwaan 1 Harmelen Utrecht 3481 TN",
    "addr:housenumber":"1",
    "addr:postcode":"3481",
    "addr:street":"Zwaan",
    "iso:country":"NL",
    "sg:address":"Zwaan 1",
    "sg:city":"Harmelen",
    "sg:orig_category":"Farmaceutische Producten Gh",
    "sg:phone":"+31 348 442 504",
    "sg:postcode":"3481 TN",
    "sg:province":"Utrecht",
    "wof:name":"M.R. Groeneveld",
    "wof:placetype":"venue"
},
  "geometry": {"coordinates":[4.956051,52.093559],"type":"Point"}
}