{
  "type": "Feature",
  "properties": {
    "addr:full":"Maasdk 79 Wyk En Aalburg Noord-Brabant 4261 AE",
    "addr:housenumber":"79",
    "addr:postcode":"4261 ae",
    "addr:street":"Maasdk",
    "iso:country":"NL",
    "sg:address":"Maasdk 79",
    "sg:city":"Wyk En Aalburg",
    "sg:orig_category":"Plafonds",
    "sg:phone":"+31 416 694 870",
    "sg:postcode":"4261 AE",
    "sg:province":"Noord-Brabant",
    "sg:website":"http://www.plameco.nl",
    "wof:name":"Vrw",
    "wof:placetype":"venue"
},
  "geometry": {"coordinates":[5.134482,51.755215],"type":"Point"}
}