{
  "type": "Feature",
  "properties": {
    "addr:full":"Oranjepln 223 Weert Limburg 6006 CX",
    "addr:housenumber":"223",
    "addr:postcode":"6006 cx",
    "addr:street":"Weert Limburg",
    "iso:country":"NL",
    "sg:address":"Oranjepln 223",
    "sg:city":"Weert",
    "sg:orig_category":"Bloemen En Planten",
    "sg:phone":"+31 495 535 311",
    "sg:postcode":"6006 CX",
    "sg:province":"Limburg",
    "wof:name":"Meewis, B",
    "wof:placetype":"venue"
},
  "geometry": {"coordinates":[5.707654,51.243202],"type":"Point"}
}