{
  "type": "Feature",
  "properties": {
    "addr:full":"Radboudtraverse 12 Utrecht Utrecht 3511 CP",
    "addr:housenumber":"12",
    "addr:postcode":"3511 cp",
    "addr:street":"Radboudtraverse",
    "iso:country":"NL",
    "sg:address":"Radboudtraverse 12",
    "sg:city":"Utrecht",
    "sg:orig_category":"Schoenen",
    "sg:phone":"+31 30 231 2830",
    "sg:postcode":"3511 CP",
    "sg:province":"Utrecht",
    "wof:name":"Manfield Bv",
    "wof:placetype":"venue"
},
  "geometry": {"coordinates":[5.113431,52.091106],"type":"Point"}
}