{
  "type": "Feature",
  "properties": {
    "addr:full":"Hoogstraat 34 Purmerend Noord-Holland 1441 BC",
    "addr:housenumber":"34",
    "addr:postcode":"1441 bc",
    "addr:street":"Hoogstraat",
    "iso:country":"NL",
    "sg:address":"Hoogstraat 34",
    "sg:city":"Purmerend",
    "sg:orig_category":"Damesmodezaken",
    "sg:phone":"+31 299 432 681",
    "sg:postcode":"1441 BC",
    "sg:province":"Noord-Holland",
    "wof:name":"Modehuis Claudette",
    "wof:placetype":"venue"
},
  "geometry": {"coordinates":[4.944792,52.508854],"type":"Point"}
}