{
  "type": "Feature",
  "properties": {
    "addr:full":"Ginderover 9 Heeze Noord-Brabant 5591 JM",
    "addr:housenumber":"9",
    "addr:postcode":"5591 jm",
    "addr:street":"Ginderover",
    "iso:country":"NL",
    "sg:address":"Ginderover 9",
    "sg:city":"Heeze",
    "sg:orig_category":"Automaterialen En Gereedschappen",
    "sg:phone":"+31 40 226 4172",
    "sg:postcode":"5591 JM",
    "sg:province":"Noord-Brabant",
    "wof:name":"V & V",
    "wof:placetype":"venue"
},
  "geometry": {"coordinates":[5.581204,51.374321],"type":"Point"}
}