{
  "type": "Feature",
  "properties": {
    "addr:full":"Dorpsstr 15 Bunnik Utrecht 3981 EA",
    "addr:housenumber":"15",
    "addr:postcode":"3981 ea",
    "addr:street":"Dorpsstr",
    "iso:country":"NL",
    "sg:address":"Dorpsstr 15",
    "sg:city":"Bunnik",
    "sg:orig_category":"Goudsmeden En Zilversmeden",
    "sg:phone":"+31 30 656 7752",
    "sg:postcode":"3981 EA",
    "sg:province":"Utrecht",
    "wof:name":"Jumelle Goudsmid & Juwelier",
    "wof:placetype":"venue"
},
  "geometry": {"coordinates":[5.202149,52.067715],"type":"Point"}
}