{
  "type": "Feature",
  "properties": {
    "addr:full":"Beresteinlaan 499 'S Gravenhage South Holland 2542 JM",
    "addr:housenumber":"499 '",
    "addr:postcode":"2542 jm",
    "addr:street":"Beresteinlaan",
    "iso:country":"NL",
    "sg:address":"Beresteinlaan 499",
    "sg:city":"'S Gravenhage",
    "sg:orig_category":"Werving And Selectie Van Tijdelijk Personeel And Uitzendkantoren",
    "sg:phone":"+31 6 22422249",
    "sg:postcode":"2542 JM",
    "sg:province":"South Holland",
    "wof:name":"M Ozmen",
    "wof:placetype":"venue"
},
  "geometry": {"coordinates":[4.2573428154,52.0395889282],"type":"Point"}
}