{
  "type": "Feature",
  "properties": {
    "addr:full":"Populierwg 108 Maastricht Limburg 6222 CS",
    "addr:housenumber":"108",
    "addr:postcode":"6222 cs",
    "iso:country":"NL",
    "sg:address":"Populierwg 108",
    "sg:city":"Maastricht",
    "sg:orig_category":"Kappers",
    "sg:phone":"+31 43 363 2837",
    "sg:postcode":"6222 CS",
    "sg:province":"Limburg",
    "wof:name":"Mar\u00e9",
    "wof:placetype":"venue"
},
  "geometry": {"coordinates":[5.708299,50.864479],"type":"Point"}
}