{
  "type": "Feature",
  "properties": {
    "addr:full":"Zevenkampse Ring 985 Rotterdam Zuid-Holland 3069 MD",
    "addr:housenumber":"985",
    "addr:postcode":"3069",
    "addr:street":"Zevenkampse Ring",
    "iso:country":"NL",
    "sg:address":"Zevenkampse Ring 985",
    "sg:city":"Rotterdam",
    "sg:classifiers":[
        {
            "category":"Building & Trades",
            "subcategory":"Electrical",
            "type":"Services"
        }
    ],
    "sg:phone":"+31 10 456 0119",
    "sg:postcode":"3069 MD",
    "sg:province":"Zuid-Holland",
    "sg:tags":[
        "distributor"
    ],
    "wof:name":"Roxanto",
    "wof:placetype":"venue"
},
  "geometry": {"coordinates":[4.561984,51.966625],"type":"Point"}
}