{
  "type": "Feature",
  "properties": {
    "iso:country":"NL",
    "sg:address":"Veldln 26",
    "sg:city":"Boskoop",
    "sg:orig_category":"Administratie- En Boekhoudkantoren",
    "sg:phone":"+31 172 231 033",
    "sg:postcode":"2771 LX",
    "sg:province":"Zuid-Holland",
    "wof:name":"Jaarsveld, A M Van",
    "wof:placetype":"venue"
},
  "geometry": {"coordinates":[4.65922,52.074268],"type":"Point"}
}