{
  "type": "Feature",
  "properties": {
    "addr:full":"Het Bijvank 75 Enschede Overijssel 7544 DA",
    "addr:housenumber":"75",
    "addr:postcode":"7544 da",
    "addr:street":"Het Bijvank",
    "iso:country":"NL",
    "sg:address":"Het Bijvank 75",
    "sg:city":"Enschede",
    "sg:orig_category":"Partycatering And -Organisatie",
    "sg:phone":"+31 53 477 9619",
    "sg:postcode":"7544 DA",
    "sg:province":"Overijssel",
    "wof:name":"Food Service Sebastian",
    "wof:placetype":"venue"
},
  "geometry": {"coordinates":[6.876287,52.195396],"type":"Point"}
}