{
  "type": "Feature",
  "properties": {
    "addr:full":"Rubenslaan 13 Bilthoven Utrecht 3723 BN",
    "addr:housenumber":"13",
    "addr:postcode":"3723 bn",
    "addr:street":"Rubenslaan",
    "iso:country":"NL",
    "sg:address":"Rubenslaan 13",
    "sg:city":"Bilthoven",
    "sg:orig_category":"Verzekeringen",
    "sg:phone":"+31 30 229 2977",
    "sg:postcode":"3723 BN",
    "sg:province":"Utrecht",
    "wof:name":"Het Assurantieadvieshuis",
    "wof:placetype":"venue"
},
  "geometry": {"coordinates":[5.200661,52.131199],"type":"Point"}
}