{
  "type": "Feature",
  "properties": {
    "iso:country":"NL",
    "sg:address":"Oudestraat 74",
    "sg:city":"Neede",
    "sg:classifiers":[
        {
            "category":"Communications",
            "subcategory":"Television Station",
            "type":"Services"
        }
    ],
    "sg:phone":"+31 545 296 116",
    "sg:postcode":"7161 DZ",
    "sg:province":"Gelderland",
    "sg:tags":[
        "video",
        "audio",
        "verhuur"
    ],
    "wof:name":"The Video Connection",
    "wof:placetype":"venue"
},
  "geometry": {"coordinates":[-121.31706200000001,38.299633],"type":"Point"}
}