{
  "type": "Feature",
  "properties": {
    "iso:country":"NL",
    "sg:address":"Portugalweg 20",
    "sg:city":"Bodegraven",
    "sg:orig_category":"Goederenvervoer Over De Weg",
    "sg:phone":"+31 172 631 631",
    "sg:postcode":"2411 PR",
    "sg:province":"Zuid-Holland",
    "wof:name":"Transportonderneming D. Broersma & Zn Bv",
    "wof:placetype":"venue"
},
  "geometry": {"coordinates":[4.764777,52.070782],"type":"Point"}
}