{
  "type": "Feature",
  "properties": {
    "addr:full":"1E Lageveldsweg 1 Wierden NL.08 7641 RM",
    "addr:housenumber":"1;nl.08",
    "addr:postcode":"7641 rm",
    "addr:street":"1E Lageveldsweg",
    "iso:country":"NL",
    "sg:address":"1E Lageveldsweg 1",
    "sg:city":"Wierden",
    "sg:orig_category":"Gebouwenafwerking, Renovaties And Reiniging",
    "sg:phone":"+31 546 573 392",
    "sg:postcode":"7641 RM",
    "sg:province":"NL.08",
    "wof:name":"Lubbers Betonreparatie",
    "wof:placetype":"venue"
},
  "geometry": {"coordinates":[6.584041,52.370434],"type":"Point"}
}