{
  "type": "Feature",
  "properties": {
    "addr:full":"Leeuwerikhof 20 Weert Limburg 6005 JS",
    "addr:housenumber":"20",
    "addr:postcode":"6005 js",
    "addr:street":"Leeuwerikhof",
    "iso:country":"NL",
    "sg:address":"Leeuwerikhof 20",
    "sg:city":"Weert",
    "sg:orig_category":"Verzekeringen",
    "sg:phone":"+31 495 531 661",
    "sg:postcode":"6005 JS",
    "sg:province":"Limburg",
    "wof:name":"Alfred V Leeuwaarden Assurantien",
    "wof:placetype":"venue"
},
  "geometry": {"coordinates":[5.720198,51.245193],"type":"Point"}
}