{
  "type": "Feature",
  "properties": {
    "addr:full":"Bakenessergr 65 Haarlem North Holland 2011 JT",
    "addr:housenumber":"65",
    "addr:postcode":"2011 jt",
    "addr:street":"Bakenessergr",
    "iso:country":"NL",
    "sg:address":"Bakenessergr 65",
    "sg:city":"Haarlem",
    "sg:orig_category":"Beeldende Kunstenaars",
    "sg:phone":"+31 23 532 5608",
    "sg:postcode":"2011 JT",
    "sg:province":"North Holland",
    "wof:name":"Overbeeke, M F Van",
    "wof:placetype":"venue"
},
  "geometry": {"coordinates":[4.640724,52.381931],"type":"Point"}
}