{
  "type": "Feature",
  "properties": {
    "addr:full":"Zandveldstraat 1 'S Hertogenbosch North Brabant 5223 JX",
    "addr:housenumber":"1 ' s",
    "addr:postcode":"5223 jx",
    "addr:street":"Zandveldstraat;Hertogenbosch",
    "iso:country":"NL",
    "sg:address":"Zandveldstraat 1",
    "sg:city":"'S Hertogenbosch",
    "sg:classifiers":[
        {
            "category":"Education",
            "subcategory":"Preschool",
            "type":"Public Place"
        }
    ],
    "sg:phone":"+31 73 621 6949",
    "sg:postcode":"5223 JX",
    "sg:province":"North Brabant",
    "sg:tags":[
        "kleuteronderwijs",
        "basis-"
    ],
    "wof:name":"Basisschool Mgr. Bekkers",
    "wof:placetype":"venue"
},
  "geometry": {"coordinates":[5.268062,51.694557],"type":"Point"}
}