{
  "type": "Feature",
  "properties": {
    "addr:full":"Grootzand 14 Sneek Provincie Friesland 8601 AW",
    "addr:housenumber":"14",
    "addr:postcode":"8601 aw",
    "addr:street":"Grootzand;Provincie Friesland",
    "iso:country":"NL",
    "sg:address":"Grootzand 14",
    "sg:city":"Sneek",
    "sg:orig_category":"Bedden En Matrassen",
    "sg:phone":"+31 515 412 920",
    "sg:postcode":"8601 AW",
    "sg:province":"Provincie Friesland",
    "sg:website":"http://www.slaapkenner.nl",
    "wof:name":"Metz Slaapkenner",
    "wof:placetype":"venue"
},
  "geometry": {"coordinates":[5.661694,53.031685],"type":"Point"}
}