{
  "type": "Feature",
  "properties": {
    "addr:full":"Zanddk 36 S Gravenzande Zuid-Holland 2691 PH",
    "addr:housenumber":"36;gravenzande",
    "addr:postcode":"2691",
    "addr:street":"Zanddk;S",
    "iso:country":"NL",
    "sg:address":"Zanddk 36",
    "sg:city":"S Gravenzande",
    "sg:classifiers":[
        {
            "category":"Professional",
            "subcategory":"Management & Consulting",
            "type":"Services"
        }
    ],
    "sg:phone":"+31 174 420 305",
    "sg:postcode":"2691 PH",
    "sg:province":"Zuid-Holland",
    "sg:tags":[
        "relation",
        "adviesbureaus",
        "public"
    ],
    "wof:name":"Enthoven, Bur",
    "wof:placetype":"venue"
},
  "geometry": {"coordinates":[4.15236,52.002651],"type":"Point"}
}