{
  "type": "Feature",
  "properties": {
    "addr:full":"Schepersstr 4 Dalfsen NL.08 7722 TC",
    "addr:housenumber":"4;nl.08",
    "addr:postcode":"7722 tc",
    "addr:street":"Schepersstr",
    "iso:country":"NL",
    "sg:address":"Schepersstr 4",
    "sg:city":"Dalfsen",
    "sg:orig_category":"Bibliotheken En Leeszalen Openbare",
    "sg:phone":"+31 529 471 567",
    "sg:postcode":"7722 TC",
    "sg:province":"NL.08",
    "wof:name":"Openb Bibliotheek",
    "wof:placetype":"venue"
},
  "geometry": {"coordinates":[6.312621,52.532444],"type":"Point"}
}