{
  "type": "Feature",
  "properties": {
    "iso:country":"NL",
    "sg:address":"Klapbrugweg 4",
    "sg:city":"Almere",
    "sg:orig_category":"Kantoorapparatuur Gh",
    "sg:phone":"+31 36 549 1030",
    "sg:postcode":"1332 AK",
    "sg:province":"NL.",
    "wof:name":"Timmermans Lammers Bv",
    "wof:placetype":"venue"
},
  "geometry": {"coordinates":[5.2546410561,52.4057273865],"type":"Point"}
}