{
  "type": "Feature",
  "properties": {
    "addr:full":"Gieterij 50 Noordwijkerhout South Holland 2211 XK",
    "addr:housenumber":"50",
    "addr:postcode":"2211 xk",
    "addr:street":"Gieterij",
    "iso:country":"NL",
    "sg:address":"Gieterij 50",
    "sg:city":"Noordwijkerhout",
    "sg:orig_category":"Werving And Selectie Van Tijdelijk Personeel And Uitzendkantoren",
    "sg:phone":"+31 252 370 888",
    "sg:postcode":"2211 XK",
    "sg:province":"South Holland",
    "wof:name":"Start",
    "wof:placetype":"venue"
},
  "geometry": {"coordinates":[4.492975235,52.2495040894],"type":"Point"}
}