{
  "type": "Feature",
  "properties": {
    "addr:full":"Postbus 123 Bunnik Utrecht 3980 CC",
    "addr:housenumber":"123",
    "addr:postcode":"3980 cc",
    "addr:street":"Postbus",
    "iso:country":"NL",
    "sg:address":"Postbus 123",
    "sg:city":"Bunnik",
    "sg:orig_category":"Verenigingen En Stichtingen",
    "sg:phone":"+31 70 387 3406",
    "sg:postcode":"3980 CC",
    "sg:province":"Utrecht",
    "wof:name":"Marfan",
    "wof:placetype":"venue"
},
  "geometry": {"coordinates":[5.19958,52.067097],"type":"Point"}
}