{
  "type": "Feature",
  "properties": {
    "iso:country":"NL",
    "sg:address":"Elkshove 3",
    "sg:city":"Bergen Nh",
    "sg:orig_category":"Paramedische Behandelingen",
    "sg:phone":"+31 72 589 7191",
    "sg:postcode":"1862 ED",
    "sg:province":"Noord-Holland",
    "wof:name":"Logopedie V Boer-Hendriks De/Weide Praktijk",
    "wof:placetype":"venue"
},
  "geometry": {"coordinates":[4.704177,52.672482],"type":"Point"}
}