{
  "type": "Feature",
  "properties": {
    "addr:full":"Kroonpassage 22 Den Helder North Holland 1781 JT",
    "addr:housenumber":"22",
    "addr:postcode":"1781 jt",
    "addr:street":"Kroonpassage",
    "iso:country":"NL",
    "sg:address":"Kroonpassage 22",
    "sg:city":"Den Helder",
    "sg:orig_category":"Juweliers",
    "sg:phone":"+31 223 612 233",
    "sg:postcode":"1781 JT",
    "sg:province":"North Holland",
    "wof:name":"Goudschakel Juwelier",
    "wof:placetype":"venue"
},
  "geometry": {"coordinates":[4.761567,52.957867],"type":"Point"}
}