{
  "type": "Feature",
  "properties": {
    "addr:full":"Leidsegr 76 Amsterdam Noord-Holland 1016 CR",
    "addr:housenumber":"76;1016",
    "addr:postcode":"cr",
    "addr:street":"Leidsegr",
    "iso:country":"NL",
    "sg:address":"Leidsegr 76",
    "sg:city":"Amsterdam",
    "sg:orig_category":"Galeries",
    "sg:phone":"+31 20 572 2722",
    "sg:postcode":"1016 CR",
    "sg:province":"Noord-Holland",
    "sg:website":"http://www.donkersloot.nl",
    "wof:name":"Donkersloot The Gallery",
    "wof:placetype":"venue"
},
  "geometry": {"coordinates":[4.88194,52.36615],"type":"Point"}
}