{
  "type": "Feature",
  "properties": {
    "addr:full":"Martinusgaarde 33 Nieuwegein Utrecht 3436 RC",
    "addr:housenumber":"33",
    "addr:postcode":"3436 rc",
    "addr:street":"Martinusgaarde",
    "iso:country":"NL",
    "sg:address":"Martinusgaarde 33",
    "sg:city":"Nieuwegein",
    "sg:orig_category":"Bedrijfsinventaris Gh",
    "sg:phone":"+31 30 604 8850",
    "sg:postcode":"3436 RC",
    "sg:province":"Utrecht",
    "wof:name":"M.J. Van Der Heyden Bv",
    "wof:placetype":"venue"
},
  "geometry": {"coordinates":[5.069832,52.037758],"type":"Point"}
}