{
  "type": "Feature",
  "properties": {
    "addr:full":"Waldastrjitte 26 Scharnegoutum Provincie Friesland 8629 PH",
    "addr:housenumber":"26",
    "addr:postcode":"8629",
    "addr:street":"Waldastrjitte;Provincie Friesland",
    "iso:country":"NL",
    "sg:address":"Waldastrjitte 26",
    "sg:city":"Scharnegoutum",
    "sg:orig_category":"Goederenvervoer Over De Weg",
    "sg:phone":"+31 515 419 894",
    "sg:postcode":"8629 PH",
    "sg:province":"Provincie Friesland",
    "wof:name":"Vof P. Bremer Transport Bemiddeling",
    "wof:placetype":"venue"
},
  "geometry": {"coordinates":[5.678786,53.061375],"type":"Point"}
}