{
  "type": "Feature",
  "properties": {
    "addr:full":"John F. Kennedylaan 83 Woudenberg Utrecht 3931 XH",
    "addr:housenumber":"83",
    "addr:postcode":"3931 xh",
    "addr:street":"John F. Kennedylaan",
    "iso:country":"NL",
    "sg:address":"John F. Kennedylaan 83",
    "sg:city":"Woudenberg",
    "sg:orig_category":"Schilderwerk",
    "sg:phone":"+31 33 286 2464",
    "sg:postcode":"3931 XH",
    "sg:province":"Utrecht",
    "wof:name":"Schildersbedrijf Bouw",
    "wof:placetype":"venue"
},
  "geometry": {"coordinates":[5.405914,52.08522],"type":"Point"}
}