{
  "type": "Feature",
  "properties": {
    "iso:country":"NL",
    "sg:address":"J Coltranestr 19",
    "sg:city":"Almere",
    "sg:orig_category":"Webdesign Bureaus",
    "sg:phone":"+31 36 546 4720",
    "sg:postcode":"1311 SH",
    "sg:province":"Flevoland",
    "sg:website":"http://www.ebwebs.com",
    "wof:name":"Eb",
    "wof:placetype":"venue"
},
  "geometry": {"coordinates":[5.1831650734,52.3663864136],"type":"Point"}
}