{
  "type": "Feature",
  "properties": {
    "addr:full":"Oude Waal 34C Amsterdam Noord-Holland 1011 CC",
    "addr:housenumber":"34c",
    "addr:postcode":"1011 cc",
    "addr:street":"Oude Waal",
    "iso:country":"NL",
    "sg:address":"Oude Waal 34C",
    "sg:city":"Amsterdam",
    "sg:orig_category":"Beeldende Kunstenaars",
    "sg:phone":"+31 20 622 6993",
    "sg:postcode":"1011 CC",
    "sg:province":"Noord-Holland",
    "wof:name":"Gorter, Willem",
    "wof:placetype":"venue"
},
  "geometry": {"coordinates":[4.904767,52.37236],"type":"Point"}
}