{
  "type": "Feature",
  "properties": {
    "addr:full":"J Pennwg 44 Hilversum Noord-Holland 1217 JH",
    "addr:housenumber":"44",
    "addr:postcode":"1217 jh",
    "iso:country":"NL",
    "sg:address":"J Pennwg 44",
    "sg:city":"Hilversum",
    "sg:orig_category":"Beeldende Kunstenaars",
    "sg:phone":"+31 35 623 1243",
    "sg:postcode":"1217 JH",
    "sg:province":"Noord-Holland",
    "wof:name":"Leene Charlotte",
    "wof:placetype":"venue"
},
  "geometry": {"coordinates":[5.163261,52.236374],"type":"Point"}
}