{
  "type": "Feature",
  "properties": {
    "addr:full":"Marktstraat 19 Zevenaar Gelderland 6901 AK",
    "addr:housenumber":"19",
    "addr:postcode":"6901 ak",
    "addr:street":"Marktstraat",
    "iso:country":"NL",
    "sg:address":"Marktstraat 19",
    "sg:city":"Zevenaar",
    "sg:classifiers":[
        {
            "category":"Retail",
            "subcategory":"Photofinishing",
            "type":"Services"
        }
    ],
    "sg:phone":"+31 316 524 290",
    "sg:postcode":"6901 AK",
    "sg:province":"Gelderland",
    "sg:tags":[
        "foto",
        "film"
    ],
    "wof:name":"Foto Film Botvliet Bv",
    "wof:placetype":"venue"
},
  "geometry": {"coordinates":[6.076344,51.927605],"type":"Point"}
}