{
  "type": "Feature",
  "properties": {
    "addr:full":"Burgemeester Van Esstr 34 Pernis Rt Zuid-Holland 3195 AG",
    "addr:housenumber":"34",
    "addr:postcode":"rt;3195",
    "addr:street":"Burgemeester Van Esstr",
    "iso:country":"NL",
    "sg:address":"Burgemeester Van Esstr 34",
    "sg:city":"Pernis Rt",
    "sg:orig_category":"Paramedische Behandelingen",
    "sg:phone":"+31 10 416 7002",
    "sg:postcode":"3195 AG",
    "sg:province":"Zuid-Holland",
    "wof:name":"E M F De Bruijn",
    "wof:placetype":"venue"
},
  "geometry": {"coordinates":[4.387126,51.891228],"type":"Point"}
}