{
  "type": "Feature",
  "properties": {
    "iso:country":"NL",
    "sg:address":"Bramenberg 17",
    "sg:city":"Eemnes",
    "sg:orig_category":"Woninginrichting- Fournituren - Fabrieken En Groothandel",
    "sg:phone":"+31 35 531 6360",
    "sg:postcode":"3755 BV",
    "sg:province":"Utrecht",
    "wof:name":"Vicam",
    "wof:placetype":"venue"
},
  "geometry": {"coordinates":[5.2500200272,52.2480278015],"type":"Point"}
}