{
  "type": "Feature",
  "properties": {
    "addr:full":"Kl Bredeplaats 20/A Harlingen Provincie Friesland 8861 BV",
    "addr:housenumber":"20 / a",
    "addr:postcode":"8861 bv",
    "addr:street":"Bredeplaats;Provincie Friesland",
    "iso:country":"NL",
    "sg:address":"Kl Bredeplaats 20/A",
    "sg:city":"Harlingen",
    "sg:orig_category":"Honden- En Kattentrimsalons",
    "sg:phone":"+31 517 413 846",
    "sg:postcode":"8861 BV",
    "sg:province":"Provincie Friesland",
    "wof:name":"Houwelingen, E Van",
    "wof:placetype":"venue"
},
  "geometry": {"coordinates":[5.415724,53.174191],"type":"Point"}
}