{
  "type": "Feature",
  "properties": {
    "addr:full":"Kanaalwg 5/B Blokzyl Idaho 8356 VS",
    "addr:housenumber":"5 / b",
    "addr:postcode":"8356",
    "addr:street":"Kanaalwg;Blokzyl Idaho",
    "iso:country":"NL",
    "sg:address":"Kanaalwg 5/B",
    "sg:city":"Blokzyl",
    "sg:orig_category":"Metaalbewerking",
    "sg:phone":"+31 527 291 281",
    "sg:postcode":"8356 VS",
    "sg:province":"Idaho",
    "wof:name":"Winter, Constructie",
    "wof:placetype":"venue"
},
  "geometry": {"coordinates":[-116.982178,48.890652],"type":"Point"}
}