{
  "type": "Feature",
  "properties": {
    "addr:full":"Delflandpln 17 Amsterdam North Holland 1062 HP",
    "addr:housenumber":"17",
    "addr:postcode":"1062 hp",
    "addr:street":"Delflandpln",
    "iso:country":"NL",
    "sg:address":"Delflandpln 17",
    "sg:city":"Amsterdam",
    "sg:orig_category":"Postkantoren",
    "sg:phone":"+31 20 614 2126",
    "sg:postcode":"1062 HP",
    "sg:province":"North Holland",
    "sg:website":"http://www.postkantoor.nl",
    "wof:name":"Postkantoor",
    "wof:placetype":"venue"
},
  "geometry": {"coordinates":[4.840303,52.348946],"type":"Point"}
}