{
  "type": "Feature",
  "properties": {
    "iso:country":"NL",
    "sg:address":"Vlaardingwg 4",
    "sg:city":"Rotterdam",
    "sg:orig_category":"Luchtvrachtexpediteurs",
    "sg:phone":"+31 10 208 2150",
    "sg:postcode":"3044 CK",
    "sg:province":"Zuid-Holland",
    "sg:website":"http://www.flaircargo.nl",
    "wof:name":"Flair Cargo Bv",
    "wof:placetype":"venue"
},
  "geometry": {"coordinates":[4.421215,51.933491],"type":"Point"}
}