{
  "type": "Feature",
  "properties": {
    "iso:country":"NL",
    "sg:address":"Klapperdk 14A",
    "sg:city":"Wapenveld",
    "sg:orig_category":"Warenhuizen",
    "sg:phone":"+31 38 447 8143",
    "sg:postcode":"8191 AD",
    "sg:province":"Gelderland",
    "wof:name":"Warenhuis Wapenveld",
    "wof:placetype":"venue"
},
  "geometry": {"coordinates":[6.0717701912,52.4326324463],"type":"Point"}
}