{
  "type": "Feature",
  "properties": {
    "addr:full":"Accumulatorstr 3 Eindhoven Noord-Brabant 5641 TK",
    "addr:housenumber":"3",
    "addr:postcode":"5641 tk",
    "addr:street":"Accumulatorstr",
    "iso:country":"NL",
    "sg:address":"Accumulatorstr 3",
    "sg:city":"Eindhoven",
    "sg:orig_category":"Meubelen - Fabrieken En Groothandel",
    "sg:phone":"+31 40 246 8034",
    "sg:postcode":"5641 TK",
    "sg:province":"Noord-Brabant",
    "wof:name":"Steengoed, Projektstoffering",
    "wof:placetype":"venue"
},
  "geometry": {"coordinates":[5.513176,51.444908],"type":"Point"}
}