{
  "type": "Feature",
  "properties": {
    "addr:full":"Oenenburgweg 314 Nunspeet Gelderland 8072 GT",
    "addr:housenumber":"314",
    "addr:postcode":"8072 gt",
    "addr:street":"Oenenburgweg;Gelderland",
    "iso:country":"NL",
    "sg:address":"Oenenburgweg 314",
    "sg:city":"Nunspeet",
    "sg:orig_category":"Paramedische Behandelingen",
    "sg:phone":"+31 341 254 792",
    "sg:postcode":"8072 GT",
    "sg:province":"Gelderland",
    "wof:name":"C C M Van Schubert",
    "wof:placetype":"venue"
},
  "geometry": {"coordinates":[5.796102,52.388798],"type":"Point"}
}