{
  "type": "Feature",
  "properties": {
    "iso:country":"NL",
    "sg:address":"Vierhavensstr 59",
    "sg:city":"Rotterdam",
    "sg:orig_category":"Woninginrichting",
    "sg:phone":"+31 10 462 2694",
    "sg:postcode":"3029 BB",
    "sg:province":"South Holland",
    "wof:name":"Westen, 'T",
    "wof:placetype":"venue"
},
  "geometry": {"coordinates":[4.4382429123,51.9078025818],"type":"Point"}
}