{
  "type": "Feature",
  "properties": {
    "addr:full":"Emmalaan 4 Bergen Nh Noord-Holland 1862 ET",
    "addr:housenumber":"4",
    "addr:postcode":"1862 et",
    "addr:street":"Emmalaan",
    "iso:country":"NL",
    "sg:address":"Emmalaan 4",
    "sg:city":"Bergen Nh",
    "sg:orig_category":"Architecten",
    "sg:phone":"+31 72 589 5745",
    "sg:postcode":"1862 ET",
    "sg:province":"Noord-Holland",
    "wof:name":"Architectenburo Admiraal-Stoute",
    "wof:placetype":"venue"
},
  "geometry": {"coordinates":[4.707539,52.669441],"type":"Point"}
}