{
  "type": "Feature",
  "properties": {
    "addr:full":"Weberstraat 1 Purmerend Noord-Holland 1446 VV",
    "addr:housenumber":"1",
    "addr:postcode":"1446 vv",
    "addr:street":"Weberstraat",
    "iso:country":"NL",
    "sg:address":"Weberstraat 1",
    "sg:city":"Purmerend",
    "sg:orig_category":"Verhuisdiensten",
    "sg:phone":"+31 299 642 642",
    "sg:postcode":"1446 VV",
    "sg:province":"Noord-Holland",
    "wof:name":"Bert Ooms Verhuizingen",
    "wof:placetype":"venue"
},
  "geometry": {"coordinates":[4.998567,52.511574],"type":"Point"}
}