{
  "type": "Feature",
  "properties": {
    "iso:country":"NL",
    "sg:address":"De Genestetstr 8",
    "sg:city":"Enschede",
    "sg:classifiers":[
        {
            "category":"Retail",
            "subcategory":"Auto Repair",
            "type":"Services"
        }
    ],
    "sg:phone":"+31 53 431 0488",
    "sg:postcode":"7514 CR",
    "sg:province":"Overijssel",
    "sg:tags":[
        "garage"
    ],
    "wof:name":"Crietee",
    "wof:placetype":"venue"
},
  "geometry": {"coordinates":[6.893578,52.226631],"type":"Point"}
}