{
  "type": "Feature",
  "properties": {
    "addr:full":"Burg Jasln 56 Dordrecht South Holland 3319 AC",
    "addr:housenumber":"56",
    "addr:postcode":"3319 ac",
    "addr:street":"Burg",
    "iso:country":"NL",
    "sg:address":"Burg Jasln 56",
    "sg:city":"Dordrecht",
    "sg:classifiers":[
        {
            "category":"Personal",
            "subcategory":"Nail Salon",
            "type":"Services"
        }
    ],
    "sg:phone":"+31 78 616 6466",
    "sg:postcode":"3319 AC",
    "sg:province":"South Holland",
    "sg:tags":[
        "pedicure"
    ],
    "wof:name":"Kok, W S",
    "wof:placetype":"venue"
},
  "geometry": {"coordinates":[4.656506,51.811916],"type":"Point"}
}