{
  "type": "Feature",
  "properties": {
    "addr:full":"Westringdijk 29 Nieuwerkerk Ad Ijssel Zuid-Holland 2913 LK",
    "addr:housenumber":"29",
    "addr:postcode":"ijssel;2913 lk",
    "addr:street":"Westringdijk",
    "iso:country":"NL",
    "sg:address":"Westringdijk 29",
    "sg:city":"Nieuwerkerk Ad Ijssel",
    "sg:orig_category":"Bloemen And Planten",
    "sg:phone":"+31 180 312 480",
    "sg:postcode":"2913 LK",
    "sg:province":"Zuid-Holland",
    "wof:name":"Kwekerij J. Oudijk",
    "wof:placetype":"venue"
},
  "geometry": {"coordinates":[4.595142,51.978916],"type":"Point"}
}