{
  "type": "Feature",
  "properties": {
    "addr:full":"Borneoplein 21 Amersfoort Utrecht 3818 AH",
    "addr:housenumber":"21",
    "addr:postcode":"3818 ah",
    "addr:street":"Borneoplein",
    "iso:country":"NL",
    "sg:address":"Borneoplein 21",
    "sg:city":"Amersfoort",
    "sg:orig_category":"Artiesten",
    "sg:phone":"+31 33 462 1122",
    "sg:postcode":"3818 AH",
    "sg:province":"Utrecht",
    "wof:name":"Van Der Hoeven - De Heer Kloots",
    "wof:placetype":"venue"
},
  "geometry": {"coordinates":[5.375273,52.1394],"type":"Point"}
}