{
  "type": "Feature",
  "properties": {
    "addr:full":"Bloemenmarkt 35 Geleen Limburg 6163  C",
    "addr:housenumber":"35;6163 c",
    "addr:street":"Bloemenmarkt",
    "iso:country":"NL",
    "sg:address":"Bloemenmarkt 35",
    "sg:city":"Geleen",
    "sg:orig_category":"Boekenuitgeverijen",
    "sg:phone":"+31 46 474 2947",
    "sg:postcode":"6163  C",
    "sg:province":"Limburg",
    "wof:name":"Bruna",
    "wof:placetype":"venue"
},
  "geometry": {"coordinates":[5.814673,50.984722],"type":"Point"}
}