{
  "type": "Feature",
  "properties": {
    "addr:full":"Achterdk 2 Hellevoetsluis South Holland 3223 LA",
    "addr:housenumber":"2",
    "addr:postcode":"3223 la",
    "addr:street":"Achterdk",
    "iso:country":"NL",
    "sg:address":"Achterdk 2",
    "sg:city":"Hellevoetsluis",
    "sg:orig_category":"Oldtimers",
    "sg:phone":"+31 181 320 901",
    "sg:postcode":"3223 LA",
    "sg:province":"South Holland",
    "wof:name":"Jack-Leg'S",
    "wof:placetype":"venue"
},
  "geometry": {"coordinates":[4.161019,51.866909],"type":"Point"}
}