{
  "type": "Feature",
  "properties": {
    "iso:country":"NL",
    "sg:address":"Merodeln 62",
    "sg:city":"Breda",
    "sg:orig_category":"Pensioenen",
    "sg:phone":"+31 76 544 0200",
    "sg:postcode":"4824 BN",
    "sg:province":"North Brabant",
    "wof:name":"Brabant",
    "wof:placetype":"venue"
},
  "geometry": {"coordinates":[4.74994,51.612591],"type":"Point"}
}