{
  "type": "Feature",
  "properties": {
    "addr:full":"Merodeln 62 Breda North Brabant 4824 BN",
    "addr:housenumber":"62",
    "addr:postcode":"4824 bn",
    "addr:street":"Merodeln",
    "iso:country":"NL",
    "sg:address":"Merodeln 62",
    "sg:city":"Breda",
    "sg:orig_category":"Pensioenen",
    "sg:phone":"+31 76 544 0200",
    "sg:postcode":"4824 BN",
    "sg:province":"North Brabant",
    "wof:name":"Brabant",
    "wof:placetype":"venue"
},
  "geometry": {"coordinates":[4.74994,51.612591],"type":"Point"}
}