{
  "type": "Feature",
  "properties": {
    "iso:country":"NL",
    "sg:address":"Walderstraat 23",
    "sg:city":"Lochem",
    "sg:orig_category":"Schoenen",
    "sg:phone":"+31 573 251 631",
    "sg:postcode":"7241 BH",
    "sg:province":"Gelderland",
    "wof:name":"Beumer Schoenmode",
    "wof:placetype":"venue"
},
  "geometry": {"coordinates":[6.413111,52.162075],"type":"Point"}
}