{
  "type": "Feature",
  "properties": {
    "addr:full":"Havenstraat 3 Volendam Noord-Holland 1131  B",
    "addr:housenumber":"3;1131 b",
    "addr:street":"Havenstraat",
    "iso:country":"NL",
    "sg:address":"Havenstraat 3",
    "sg:city":"Volendam",
    "sg:orig_category":"Boekenuitgeverijen",
    "sg:phone":"+31 299 364 140",
    "sg:postcode":"1131  B",
    "sg:province":"Noord-Holland",
    "wof:name":"Bruna",
    "wof:placetype":"venue"
},
  "geometry": {"coordinates":[5.074197,52.493202],"type":"Point"}
}