{
  "type": "Feature",
  "properties": {
    "iso:country":"NL",
    "sg:address":"Hg Einde Z 23",
    "sg:city":"Ouderkerk Amstel",
    "sg:orig_category":"Fietsen En Bromfietsen",
    "sg:phone":"+31 20 496 1216",
    "sg:postcode":"1191 AH",
    "sg:province":"North Holland",
    "sg:website":"http://www.gerritdehaan.nl",
    "wof:name":"Haan Bv, De",
    "wof:placetype":"venue"
},
  "geometry": {"coordinates":[4.904776,52.296631],"type":"Point"}
}