{
  "type": "Feature",
  "properties": {
    "addr:full":"Arendstr 37 Oosterhout Nb Noord-Brabant 4901 JJ",
    "addr:housenumber":"37",
    "addr:postcode":"4901 jj",
    "addr:street":"Arendstr",
    "iso:country":"NL",
    "sg:address":"Arendstr 37",
    "sg:city":"Oosterhout Nb",
    "sg:orig_category":"Opticiens",
    "sg:phone":"+31 162 454 639",
    "sg:postcode":"4901 JJ",
    "sg:province":"Noord-Brabant",
    "wof:name":"Loonen Brillenmakers",
    "wof:placetype":"venue"
},
  "geometry": {"coordinates":[4.8572201729,51.6431503296],"type":"Point"}
}