{
  "type": "Feature",
  "properties": {
    "iso:country":"NL",
    "sg:address":"Burg Meineszln 43/A",
    "sg:city":"Rotterdam",
    "sg:orig_category":"Grafisch Ontwerpers",
    "sg:phone":"+31 10 477 5239",
    "sg:postcode":"3022 BB",
    "sg:province":"Zuid-Holland",
    "wof:name":"Zeevat, C",
    "wof:placetype":"venue"
},
  "geometry": {"coordinates":[4.452623,51.91827],"type":"Point"}
}