{
  "type": "Feature",
  "properties": {
    "addr:full":"Burg Meineszln 43/A Rotterdam Zuid-Holland 3022 BB",
    "addr:housenumber":"43 / a",
    "addr:postcode":"3022 bb",
    "addr:street":"Burg",
    "iso:country":"NL",
    "sg:address":"Burg Meineszln 43/A",
    "sg:city":"Rotterdam",
    "sg:orig_category":"Grafisch Ontwerpers",
    "sg:phone":"+31 10 477 5239",
    "sg:postcode":"3022 BB",
    "sg:province":"Zuid-Holland",
    "wof:name":"Zeevat, C",
    "wof:placetype":"venue"
},
  "geometry": {"coordinates":[4.452623,51.91827],"type":"Point"}
}