{
  "type": "Feature",
  "properties": {
    "addr:full":"S Reimerstr 45 Enschede Overijssel 7524 CR",
    "addr:housenumber":"45",
    "addr:postcode":"7524 cr",
    "iso:country":"NL",
    "sg:address":"S Reimerstr 45",
    "sg:city":"Enschede",
    "sg:orig_category":"Kappers",
    "sg:phone":"+31 53 435 5954",
    "sg:postcode":"7524 CR",
    "sg:province":"Overijssel",
    "wof:name":"Eshuis-Schopman",
    "wof:placetype":"venue"
},
  "geometry": {"coordinates":[6.911356926,52.2499961853],"type":"Point"}
}