{
  "type": "Feature",
  "properties": {
    "addr:full":"Kastanjelaan 14 Molenhoek Lb Limburg 6584 CP",
    "addr:housenumber":"14",
    "addr:postcode":"lb;6584 cp",
    "addr:street":"Kastanjelaan",
    "iso:country":"NL",
    "sg:address":"Kastanjelaan 14",
    "sg:city":"Molenhoek Lb",
    "sg:orig_category":"Meubelzaken, Woning- And Keukeninrichting",
    "sg:phone":"+31 24 388 1290",
    "sg:postcode":"6584 CP",
    "sg:province":"Limburg",
    "wof:name":"R.B. Leijn",
    "wof:placetype":"venue"
},
  "geometry": {"coordinates":[5.880789,51.772221],"type":"Point"}
}