{
  "type": "Feature",
  "properties": {
    "addr:full":"Novaliewg 4 Hattem Gelderland 8051 AH",
    "addr:housenumber":"4",
    "addr:postcode":"8051 ah",
    "addr:street":"Novaliewg;Gelderland",
    "iso:country":"NL",
    "sg:address":"Novaliewg 4",
    "sg:city":"Hattem",
    "sg:orig_category":"Psychologen",
    "sg:phone":"+31 38 444 1110",
    "sg:postcode":"8051 AH",
    "sg:province":"Gelderland",
    "wof:name":"Hof, Drs G R",
    "wof:placetype":"venue"
},
  "geometry": {"coordinates":[6.065331,52.465122],"type":"Point"}
}