{
  "type": "Feature",
  "properties": {
    "addr:full":"Voorstr 52 Voorschoten Zuid-Holland 2251 BP",
    "addr:housenumber":"52",
    "addr:postcode":"2251 bp",
    "addr:street":"Voorstr",
    "iso:country":"NL",
    "sg:address":"Voorstr 52",
    "sg:city":"Voorschoten",
    "sg:orig_category":"Organisatiebureaus",
    "sg:phone":"+31 71 561 1934",
    "sg:postcode":"2251 BP",
    "sg:province":"Zuid-Holland",
    "sg:website":"http://www.paraview.nl",
    "wof:name":"View Vof, Bureau",
    "wof:placetype":"venue"
},
  "geometry": {"coordinates":[4.4443669319,52.1234931946],"type":"Point"}
}