{
  "type": "Feature",
  "properties": {
    "addr:full":"Sluisjesdk 122 Rotterdam South Holland 3087 AK",
    "addr:housenumber":"122",
    "addr:postcode":"3087 ak",
    "iso:country":"NL",
    "sg:address":"Sluisjesdk 122",
    "sg:city":"Rotterdam",
    "sg:orig_category":"Lijsten - Fabrieken En Groothandel",
    "sg:phone":"+31 10 428 1433",
    "sg:postcode":"3087 AK",
    "sg:province":"South Holland",
    "wof:name":"Lijstenfabriek Rotterdam Bv",
    "wof:placetype":"venue"
},
  "geometry": {"coordinates":[4.450307,51.89658],"type":"Point"}
}