{
  "type": "Feature",
  "properties": {
    "iso:country":"NL",
    "sg:address":"Lijnbaan 150",
    "sg:city":"Rotterdam",
    "sg:orig_category":"Boekenuitgeverijen",
    "sg:phone":"+31 10 413 2070",
    "sg:postcode":"3012 ER",
    "sg:province":"Zuid-Holland",
    "wof:name":"Donner Boeken Bv",
    "wof:placetype":"venue"
},
  "geometry": {"coordinates":[4.478382,51.918518],"type":"Point"}
}