{
  "type": "Feature",
  "properties": {
    "iso:country":"NL",
    "sg:address":"Nettenboetsterstr 11",
    "sg:city":"Vlaardingen",
    "sg:orig_category":"Gehandicapteninformatie",
    "sg:phone":"+31 10 234 2889",
    "sg:postcode":"3133 EP",
    "sg:province":"Zuid-Holland",
    "wof:name":"Arbeidscentr De Boei",
    "wof:placetype":"venue"
},
  "geometry": {"coordinates":[4.332825,51.907326],"type":"Point"}
}