{
  "type": "Feature",
  "properties": {
    "addr:full":"Lagoswg 25 Delft Zuid-Holland 2622 CZ",
    "addr:housenumber":"25",
    "addr:postcode":"2622",
    "addr:street":"Lagoswg",
    "iso:country":"NL",
    "sg:address":"Lagoswg 25",
    "sg:city":"Delft",
    "sg:orig_category":"Geluidsinstallaties - Verhuur",
    "sg:phone":"+31 15 261 5010",
    "sg:postcode":"2622 CZ",
    "sg:province":"Zuid-Holland",
    "sg:website":"http://www.westamp.nl",
    "wof:name":"Westamp",
    "wof:placetype":"venue"
},
  "geometry": {"coordinates":[4.340684,51.984489],"type":"Point"}
}