{
  "type": "Feature",
  "properties": {
    "iso:country":"NL",
    "sg:address":"Kalkoenstraat 11B",
    "sg:city":"Amsterdam",
    "sg:orig_category":"Binnenhuisarchitecten",
    "sg:phone":"+31 20 636 0642",
    "sg:postcode":"1022 BA",
    "sg:province":"Noord-Holland",
    "wof:name":"Beelden Op Textiel",
    "wof:placetype":"venue"
},
  "geometry": {"coordinates":[4.923049,52.389149],"type":"Point"}
}