{
  "type": "Feature",
  "properties": {
    "addr:full":"Mauritswg 31 Rotterdam Zuid-Holland 3012 JT",
    "addr:housenumber":"31",
    "addr:postcode":"3012 jt",
    "addr:street":"Mauritswg",
    "iso:country":"NL",
    "sg:address":"Mauritswg 31",
    "sg:city":"Rotterdam",
    "sg:orig_category":"Offsetdrukkerijen",
    "sg:phone":"+31 10 404 5042",
    "sg:postcode":"3012 JT",
    "sg:province":"Zuid-Holland",
    "wof:name":"Skyland Vof",
    "wof:placetype":"venue"
},
  "geometry": {"coordinates":[4.472582,51.919224],"type":"Point"}
}