{
  "type": "Feature",
  "properties": {
    "addr:full":"Westendorperh Wg 18 Emst Gelderland 8166 HX",
    "addr:housenumber":"18",
    "addr:postcode":"8166 hx",
    "addr:street":"Wg;Gelderland",
    "iso:country":"NL",
    "sg:address":"Westendorperh Wg 18",
    "sg:city":"Emst",
    "sg:orig_category":"Bedrijfsopleidingen",
    "sg:phone":"+31 317 427 830",
    "sg:postcode":"8166 HX",
    "sg:province":"Gelderland",
    "wof:name":"Ask",
    "wof:placetype":"venue"
},
  "geometry": {"coordinates":[5.9948,52.327679],"type":"Point"}
}