{
  "type": "Feature",
  "properties": {
    "addr:full":"Kolkstraat 2 Nijkerk Gld Gelderland 3861 AK",
    "addr:housenumber":"2",
    "addr:postcode":"3861 ak",
    "addr:street":"Kolkstraat;Gld Gelderland",
    "iso:country":"NL",
    "sg:address":"Kolkstraat 2",
    "sg:city":"Nijkerk Gld",
    "sg:orig_category":"Kappers",
    "sg:phone":"+31 33 245 3226",
    "sg:postcode":"3861 AK",
    "sg:province":"Gelderland",
    "wof:name":"Hairstyling Bert",
    "wof:placetype":"venue"
},
  "geometry": {"coordinates":[5.484295845,52.2244262695],"type":"Point"}
}