{
  "type": "Feature",
  "properties": {
    "addr:full":"Rondeel 116 Leusden Utrecht 3831 SZ",
    "addr:housenumber":"116",
    "addr:postcode":"3831 sz",
    "addr:street":"Rondeel",
    "iso:country":"NL",
    "sg:address":"Rondeel 116",
    "sg:city":"Leusden",
    "sg:orig_category":"Podotherapeuten",
    "sg:phone":"+31 33 494 1669",
    "sg:postcode":"3831 SZ",
    "sg:province":"Utrecht",
    "wof:name":"Praktijk Podotherapie Leusden",
    "wof:placetype":"venue"
},
  "geometry": {"coordinates":[5.42794,52.142921],"type":"Point"}
}