{
  "type": "Feature",
  "properties": {
    "addr:full":"Frederikstr 967D S Gravenhage Zuid-Holland 2514 LJ",
    "addr:housenumber":"967d;gravenhage",
    "addr:postcode":"2514 lj",
    "addr:street":"Frederikstr;S",
    "iso:country":"NL",
    "sg:address":"Frederikstr 967D",
    "sg:city":"S Gravenhage",
    "sg:orig_category":"Galeries",
    "sg:phone":"+31 70 427 7977",
    "sg:postcode":"2514 LJ",
    "sg:province":"Zuid-Holland",
    "sg:website":"http://www.portret.nl",
    "wof:name":"Ermine",
    "wof:placetype":"venue"
},
  "geometry": {"coordinates":[4.30935,52.084148],"type":"Point"}
}