{
  "type": "Feature",
  "properties": {
    "iso:country":"NL",
    "sg:address":"Steege 12",
    "sg:city":"Marienheem",
    "sg:orig_category":"Horecabenodigdheden",
    "sg:phone":"+31 572 351 654",
    "sg:postcode":"8106 PD",
    "sg:province":"Overijssel",
    "wof:name":"Velderman Eierhandel",
    "wof:placetype":"venue"
},
  "geometry": {"coordinates":[6.303421,52.395378],"type":"Point"}
}