{
  "type": "Feature",
  "properties": {
    "iso:country":"NL",
    "sg:address":"Scheepmakershaven 32B",
    "sg:city":"Rotterdam",
    "sg:orig_category":"Scheepvaartservice- Bureaus",
    "sg:phone":"+31 10 240 0095",
    "sg:postcode":"3011 VB",
    "sg:province":"Zuid-Holland",
    "wof:name":"T & D",
    "wof:placetype":"venue"
},
  "geometry": {"coordinates":[4.487712,51.916317],"type":"Point"}
}