{
  "type": "Feature",
  "properties": {
    "addr:full":"Scheepmakershaven 32B Rotterdam Zuid-Holland 3011 VB",
    "addr:housenumber":"32b",
    "addr:postcode":"3011 vb",
    "addr:street":"Scheepmakershaven",
    "iso:country":"NL",
    "sg:address":"Scheepmakershaven 32B",
    "sg:city":"Rotterdam",
    "sg:orig_category":"Scheepvaartservice- Bureaus",
    "sg:phone":"+31 10 240 0095",
    "sg:postcode":"3011 VB",
    "sg:province":"Zuid-Holland",
    "wof:name":"T & D",
    "wof:placetype":"venue"
},
  "geometry": {"coordinates":[4.487712,51.916317],"type":"Point"}
}