{
  "type": "Feature",
  "properties": {
    "addr:full":"Achterwg Z 66 Lisse Zuid-Holland 2161 DZ",
    "addr:housenumber":"66",
    "addr:postcode":"2161 dz",
    "iso:country":"NL",
    "sg:address":"Achterwg Z 66",
    "sg:city":"Lisse",
    "sg:orig_category":"Bloembollen - Groothandel",
    "sg:phone":"+31 252 423 588",
    "sg:postcode":"2161 DZ",
    "sg:province":"Zuid-Holland",
    "wof:name":"Wit & Zoon Vof, G De",
    "wof:placetype":"venue"
},
  "geometry": {"coordinates":[4.536166,52.246849],"type":"Point"}
}