{
  "type": "Feature",
  "properties": {
    "iso:country":"NL",
    "sg:address":"Enkweg 45",
    "sg:city":"Harderwijk",
    "sg:orig_category":"Kappers",
    "sg:phone":"+31 341 412 016",
    "sg:postcode":"3841 GG",
    "sg:province":"Gelderland",
    "wof:name":"Kapsalon Hans Lubbers",
    "wof:placetype":"venue"
},
  "geometry": {"coordinates":[5.6304411888,52.3486213684],"type":"Point"}
}