{
  "type": "Feature",
  "properties": {
    "addr:full":"Haasweg 9 Almere NL. 1338 AW",
    "addr:housenumber":"9",
    "addr:postcode":"1338 aw",
    "addr:street":"Haasweg;Nl.",
    "iso:country":"NL",
    "sg:address":"Haasweg 9",
    "sg:city":"Almere",
    "sg:orig_category":"Paramedische Behandelingen",
    "sg:phone":"+31 36 532 2777",
    "sg:postcode":"1338 AW",
    "sg:province":"NL.",
    "wof:name":"Logopediepraktijk Toom",
    "wof:placetype":"venue"
},
  "geometry": {"coordinates":[5.274253,52.388947],"type":"Point"}
}