{
  "type": "Feature",
  "properties": {
    "addr:full":"Kleine G Plnts 7-9 I Amsterdam North Holland 1017 RP",
    "addr:housenumber":"7-9 i",
    "addr:postcode":"1017 rp",
    "addr:street":"Kleine G Plnts",
    "iso:country":"NL",
    "sg:address":"Kleine G Plnts 7-9 I",
    "sg:city":"Amsterdam",
    "sg:orig_category":"Verenigingen En Stichtingen",
    "sg:phone":"+31 20 623 6985",
    "sg:postcode":"1017 RP",
    "sg:province":"North Holland",
    "wof:name":"Kring, Societeit De",
    "wof:placetype":"venue"
},
  "geometry": {"coordinates":[4.893195,52.373119],"type":"Point"}
}