{
  "type": "Feature",
  "properties": {
    "iso:country":"NL",
    "sg:address":"Woonboulevard 22",
    "sg:city":"Almelo",
    "sg:orig_category":"Meubelzaken, Woning- And Keukeninrichting",
    "sg:phone":"+31 546 853 239",
    "sg:postcode":"7606 JA",
    "sg:province":"Overijssel",
    "wof:name":"Beter Bed",
    "wof:placetype":"venue"
},
  "geometry": {"coordinates":[6.64343,52.340309],"type":"Point"}
}