{
  "type": "Feature",
  "properties": {
    "addr:full":"Mariendk 7 Honselersdyk South Holland 2675 SV",
    "addr:housenumber":"7",
    "addr:postcode":"2675 sv",
    "addr:street":"Mariendk",
    "iso:country":"NL",
    "sg:address":"Mariendk 7",
    "sg:city":"Honselersdyk",
    "sg:orig_category":"Ketelmakerijen",
    "sg:phone":"+31 174 626 081",
    "sg:postcode":"2675 SV",
    "sg:province":"South Holland",
    "wof:name":"Bkc",
    "wof:placetype":"venue"
},
  "geometry": {"coordinates":[4.236498,52.011223],"type":"Point"}
}