{
  "type": "Feature",
  "properties": {
    "addr:full":"Past Versterpln 1 Kloosterzande Zeeland 4587 CW",
    "addr:housenumber":"1",
    "addr:postcode":"4587 cw",
    "iso:country":"NL",
    "sg:address":"Past Versterpln 1",
    "sg:city":"Kloosterzande",
    "sg:orig_category":"Bejaarden - Verzorgingstehuizen",
    "sg:phone":"+31 114 682 230",
    "sg:postcode":"4587 CW",
    "sg:province":"Zeeland",
    "wof:name":"Antonius",
    "wof:placetype":"venue"
},
  "geometry": {"coordinates":[4.007975,51.370934],"type":"Point"}
}