{
  "type": "Feature",
  "properties": {
    "addr:full":"Hasselterdk 37 Zwartsluis Overijssel 8064 PL",
    "addr:housenumber":"37",
    "addr:postcode":"8064 pl",
    "addr:street":"Hasselterdk",
    "iso:country":"NL",
    "sg:address":"Hasselterdk 37",
    "sg:city":"Zwartsluis",
    "sg:orig_category":"Verzekeringen - Verzekeringskantoren",
    "sg:phone":"+31 38 386 7065",
    "sg:postcode":"8064 PL",
    "sg:province":"Overijssel",
    "wof:name":"Napel, K Ten",
    "wof:placetype":"venue"
},
  "geometry": {"coordinates":[6.077925,52.638222],"type":"Point"}
}