{
  "type": "Feature",
  "properties": {
    "addr:full":"Zichtenburglaan 94 'S Gravenhage Zuid-Holland 2544 EB",
    "addr:housenumber":"94",
    "addr:postcode":"2544 eb",
    "addr:street":"Zichtenburglaan;' S",
    "iso:country":"NL",
    "sg:address":"Zichtenburglaan 94",
    "sg:city":"'S Gravenhage",
    "sg:orig_category":"Verhuur Bouwmachines",
    "sg:phone":"+31 70 329 6463",
    "sg:postcode":"2544 EB",
    "sg:province":"Zuid-Holland",
    "wof:name":"J.N.J. Moerland",
    "wof:placetype":"venue"
},
  "geometry": {"coordinates":[4.25077,52.047832],"type":"Point"}
}