{
  "type": "Feature",
  "properties": {
    "iso:country":"NL",
    "sg:address":"Croy 7E",
    "sg:city":"Eindhoven",
    "sg:orig_category":"Adviesbureaus Bedrijfsorganisatie",
    "sg:phone":"+31 40 291 6700",
    "sg:postcode":"5653 LC",
    "sg:province":"Noord-Brabant",
    "sg:website":"http://www.dbassociates.com",
    "wof:name":"Dbassociates Nederland Nv",
    "wof:placetype":"venue"
},
  "geometry": {"coordinates":[5.432251,51.418507],"type":"Point"}
}