{
  "type": "Feature",
  "properties": {
    "addr:full":"Foarwei 23 Oudwoude Friesland 9294 KC",
    "addr:housenumber":"23",
    "addr:postcode":"9294 kc",
    "addr:street":"Foarwei",
    "iso:country":"NL",
    "sg:address":"Foarwei 23",
    "sg:city":"Oudwoude",
    "sg:classifiers":[
        {
            "category":"Fast Food",
            "type":"Food & Drink"
        }
    ],
    "sg:phone":"+31 511 451 286",
    "sg:postcode":"9294 KC",
    "sg:province":"Friesland",
    "sg:tags":[
        "afhaal",
        "restaurant"
    ],
    "wof:name":"It Earrebarrenest",
    "wof:placetype":"venue"
},
  "geometry": {"coordinates":[6.118029,53.279316],"type":"Point"}
}