{
  "type": "Feature",
  "properties": {
    "addr:full":"De Nachtegaal 8 Surhuisterveen Friesland 9231 JN",
    "addr:housenumber":"8",
    "addr:postcode":"9231 jn",
    "addr:street":"De Nachtegaal",
    "iso:country":"NL",
    "sg:address":"De Nachtegaal 8",
    "sg:city":"Surhuisterveen",
    "sg:orig_category":"Verzekeringen - Verzekeringskantoren",
    "sg:phone":"+31 512 362 688",
    "sg:postcode":"9231 JN",
    "sg:province":"Friesland",
    "wof:name":"Akker, B E Van Den",
    "wof:placetype":"venue"
},
  "geometry": {"coordinates":[6.169438,53.187943],"type":"Point"}
}