{
  "type": "Feature",
  "properties": {
    "iso:country":"NL",
    "sg:address":"J Bildersstr 77",
    "sg:city":"S Gravenhage",
    "sg:classifiers":[
        {
            "category":"Shopping",
            "subcategory":"Adult",
            "type":"Retail Goods"
        }
    ],
    "sg:phone":"+31 70 324 8998",
    "sg:postcode":"2596 EG",
    "sg:province":"Zuid-Holland",
    "sg:tags":[
        "lingerie",
        "en",
        "tricotage"
    ],
    "wof:name":"Pink & Lie",
    "wof:placetype":"venue"
},
  "geometry": {"coordinates":[4.31846,52.093311],"type":"Point"}
}