{
  "type": "Feature",
  "properties": {
    "iso:country":"NL",
    "sg:address":"Dorpsstr 44",
    "sg:city":"Jisp",
    "sg:orig_category":"Grafische Bedrijven",
    "sg:phone":"+31 75 642 5720",
    "sg:postcode":"1546 LK",
    "sg:province":"North Holland",
    "wof:name":"Tekstra Grafische Producties",
    "wof:placetype":"venue"
},
  "geometry": {"coordinates":[4.854348,52.507214],"type":"Point"}
}