{
  "type": "Feature",
  "properties": {
    "iso:country":"NL",
    "sg:address":"Prinsenstraat 14",
    "sg:city":"Dalfsen",
    "sg:orig_category":"Kappers",
    "sg:phone":"+31 529 431 302",
    "sg:postcode":"7721 AJ",
    "sg:province":"Overijssel",
    "wof:name":"Haarmode Vrielink Voor Dames En Heren",
    "wof:placetype":"venue"
},
  "geometry": {"coordinates":[6.2600288391,52.5039253235],"type":"Point"}
}