{
  "type": "Feature",
  "properties": {
    "addr:full":"Pieter Zeemanweg 36 Dordrecht Zuid-Holland 3316 GZ",
    "addr:housenumber":"36",
    "addr:postcode":"3316 gz",
    "addr:street":"Pieter Zeemanweg",
    "iso:country":"NL",
    "sg:address":"Pieter Zeemanweg 36",
    "sg:city":"Dordrecht",
    "sg:orig_category":"Autokeuringen",
    "sg:phone":"+31 78 618 7718",
    "sg:postcode":"3316 GZ",
    "sg:province":"Zuid-Holland",
    "wof:name":"Herrebrugh Occasion Center Bv",
    "wof:placetype":"venue"
},
  "geometry": {"coordinates":[4.641357,51.776493],"type":"Point"}
}