{
  "type": "Feature",
  "properties": {
    "addr:full":"H Viottahof 12A Hoofddorp Noord-Holland 2132 KN",
    "addr:housenumber":"12a",
    "addr:postcode":"2132 kn",
    "addr:street":"Viottahof",
    "iso:country":"NL",
    "sg:address":"H Viottahof 12A",
    "sg:city":"Hoofddorp",
    "sg:orig_category":"Artsen - Huisartsen",
    "sg:phone":"+31 23 561 6135",
    "sg:postcode":"2132 KN",
    "sg:province":"Noord-Holland",
    "sg:website":"http://www.vdvinne.praktijkinfo.nl",
    "wof:name":"Vinne, A J H Van Der",
    "wof:placetype":"venue"
},
  "geometry": {"coordinates":[4.707022,52.304276],"type":"Point"}
}