{
  "type": "Feature",
  "properties": {
    "addr:full":"Segbroekln 308 S Gravenhage Zuid-Holland 2565 DW",
    "addr:housenumber":"308;gravenhage",
    "addr:postcode":"2565 dw",
    "addr:street":"S",
    "iso:country":"NL",
    "sg:address":"Segbroekln 308",
    "sg:city":"S Gravenhage",
    "sg:orig_category":"Administratie- En Boekhoudkantoren",
    "sg:phone":"+31 70 364 4759",
    "sg:postcode":"2565 DW",
    "sg:province":"Zuid-Holland",
    "wof:name":"Mpk",
    "wof:placetype":"venue"
},
  "geometry": {"coordinates":[4.26129,52.076382],"type":"Point"}
}