{
  "type": "Feature",
  "properties": {
    "iso:country":"NL",
    "sg:address":"Schaapdijkstraat 2",
    "sg:city":"Zuiddorpe",
    "sg:orig_category":"Verhuur Audiovisuele Apparatuur",
    "sg:phone":"+31 115 608 682",
    "sg:postcode":"4574 SZ",
    "sg:province":"Zeeland",
    "wof:name":"Sanrobi",
    "wof:placetype":"venue"
},
  "geometry": {"coordinates":[3.908861,51.238171],"type":"Point"}
}