{
  "type": "Feature",
  "properties": {
    "addr:full":"Schaapdijkstraat 2 Zuiddorpe Zeeland 4574 SZ",
    "addr:housenumber":"2",
    "addr:postcode":"4574 sz",
    "addr:street":"Schaapdijkstraat",
    "iso:country":"NL",
    "sg:address":"Schaapdijkstraat 2",
    "sg:city":"Zuiddorpe",
    "sg:orig_category":"Verhuur Audiovisuele Apparatuur",
    "sg:phone":"+31 115 608 682",
    "sg:postcode":"4574 SZ",
    "sg:province":"Zeeland",
    "wof:name":"Sanrobi",
    "wof:placetype":"venue"
},
  "geometry": {"coordinates":[3.908861,51.238171],"type":"Point"}
}