{
  "type": "Feature",
  "properties": {
    "addr:full":"Venraysewg 44 Venlo Limburg 5928 NZ",
    "addr:housenumber":"44",
    "addr:postcode":"5928 nz",
    "addr:street":"Venraysewg",
    "iso:country":"NL",
    "sg:address":"Venraysewg 44",
    "sg:city":"Venlo",
    "sg:orig_category":"Horeca-Inrichtingen En -Uitrustingen",
    "sg:phone":"+31 77 387 4242",
    "sg:postcode":"5928 NZ",
    "sg:province":"Limburg",
    "wof:name":"Hakvoort Zuid Bv",
    "wof:placetype":"venue"
},
  "geometry": {"coordinates":[6.151342,51.380646],"type":"Point"}
}