{
  "type": "Feature",
  "properties": {
    "addr:full":"Schotsbossenstr 1 Roosendaal Noord-Brabant 4705 AE",
    "addr:housenumber":"1",
    "addr:postcode":"4705 ae",
    "addr:street":"Schotsbossenstr",
    "iso:country":"NL",
    "sg:address":"Schotsbossenstr 1",
    "sg:city":"Roosendaal",
    "sg:classifiers":[
        {
            "category":"Wholesale",
            "subcategory":"Meat",
            "type":"Manufacturing & Wholesale Goods"
        }
    ],
    "sg:phone":"+31 165 597 070",
    "sg:postcode":"4705 AE",
    "sg:province":"Noord-Brabant",
    "sg:tags":[
        "abattoir"
    ],
    "wof:name":"Slachthuis Roosendaal Bv",
    "wof:placetype":"venue"
},
  "geometry": {"coordinates":[4.4849,51.544281],"type":"Point"}
}