{
  "type": "Feature",
  "properties": {
    "addr:full":"F Elsingastr 5 Rotterdam South Holland 3067 NW",
    "addr:housenumber":"5",
    "addr:postcode":"3067 nw",
    "addr:street":"Elsingastr",
    "iso:country":"NL",
    "sg:address":"F Elsingastr 5",
    "sg:city":"Rotterdam",
    "sg:orig_category":"Verzekeringen - Verzekeringskantoren",
    "sg:phone":"+31 10 421 5512",
    "sg:postcode":"3067 NW",
    "sg:province":"South Holland",
    "sg:website":"http://www.asro.nl",
    "wof:name":"Asro Adviesgroep",
    "wof:placetype":"venue"
},
  "geometry": {"coordinates":[4.545796,51.940395],"type":"Point"}
}