{
  "type": "Feature",
  "properties": {
    "addr:full":"Westsngl 46 Borssele Zeeland 4454 AK",
    "addr:housenumber":"46",
    "addr:postcode":"4454 ak",
    "addr:street":"Westsngl",
    "iso:country":"NL",
    "sg:address":"Westsngl 46",
    "sg:city":"Borssele",
    "sg:orig_category":"Verf En Lak",
    "sg:phone":"+31 113 351 954",
    "sg:postcode":"4454 AK",
    "sg:province":"Zeeland",
    "wof:name":"Muynck, De",
    "wof:placetype":"venue"
},
  "geometry": {"coordinates":[3.737395,51.420727],"type":"Point"}
}