{
  "type": "Feature",
  "properties": {
    "addr:full":"Schutstraat 91 Hoogeveen Provincie Drenthe 7907 CB",
    "addr:housenumber":"91;7907",
    "addr:postcode":"cb",
    "addr:street":"Schutstraat;Provincie",
    "iso:country":"NL",
    "sg:address":"Schutstraat 91",
    "sg:city":"Hoogeveen",
    "sg:orig_category":"Kantoorapparatuur Gh",
    "sg:phone":"+31 528 343 433",
    "sg:postcode":"7907 CB",
    "sg:province":"Provincie Drenthe",
    "wof:name":"Wemmenhove Hoogeveen",
    "wof:placetype":"venue"
},
  "geometry": {"coordinates":[6.4740099907,52.7198562622],"type":"Point"}
}