{
  "type": "Feature",
  "properties": {
    "addr:full":"Rynaakkd 3 Venlo Limburg 5928 PT",
    "addr:housenumber":"3",
    "addr:postcode":"5928 pt",
    "addr:street":"Rynaakkd",
    "iso:country":"NL",
    "sg:address":"Rynaakkd 3",
    "sg:city":"Venlo",
    "sg:orig_category":"Elektrotechnische Installatiebureaus",
    "sg:phone":"+31 77 387 0447",
    "sg:postcode":"5928 PT",
    "sg:province":"Limburg",
    "wof:name":"Gti Venlo Bv",
    "wof:placetype":"venue"
},
  "geometry": {"coordinates":[6.11955,51.395309],"type":"Point"}
}