{
  "type": "Feature",
  "properties": {
    "addr:full":"Nieuwendijk 2 Someren North Brabant 5712 EM",
    "addr:housenumber":"2",
    "addr:postcode":"5712 em",
    "addr:street":"Nieuwendijk",
    "iso:country":"NL",
    "sg:address":"Nieuwendijk 2",
    "sg:city":"Someren",
    "sg:orig_category":"Warenhuizen",
    "sg:phone":"+31 493 491 973",
    "sg:postcode":"5712 EM",
    "sg:province":"North Brabant",
    "wof:name":"Riant Warenhuis Someren Bv",
    "wof:placetype":"venue"
},
  "geometry": {"coordinates":[5.72976017,51.3534202576],"type":"Point"}
}