{
  "type": "Feature",
  "properties": {
    "addr:full":"Van Heuven Goedhartlaan 159 Utrecht Utrecht 3527 CJ",
    "addr:housenumber":"159",
    "addr:postcode":"3527 cj",
    "addr:street":"Van Heuven Goedhartlaan",
    "iso:country":"NL",
    "sg:address":"Van Heuven Goedhartlaan 159",
    "sg:city":"Utrecht",
    "sg:classifiers":[
        {
            "category":"Food & Beverages",
            "subcategory":"Fruits & Vegetables",
            "type":"Retail Goods"
        }
    ],
    "sg:phone":"+31 30 294 0159",
    "sg:postcode":"3527 CJ",
    "sg:province":"Utrecht",
    "sg:tags":[
        "groenten"
    ],
    "wof:name":"Gulec Gida Pazari",
    "wof:placetype":"venue"
},
  "geometry": {"coordinates":[5.086834,52.077621],"type":"Point"}
}