{
  "type": "Feature",
  "properties": {
    "addr:full":"Spreeuwstr 13 Leerdam Zuid-Holland 4143 AH",
    "addr:housenumber":"13",
    "addr:postcode":"4143 ah",
    "addr:street":"Spreeuwstr",
    "iso:country":"NL",
    "sg:address":"Spreeuwstr 13",
    "sg:city":"Leerdam",
    "sg:orig_category":"Webdesign Bureaus",
    "sg:phone":"+31 6 18157891",
    "sg:postcode":"4143 AH",
    "sg:province":"Zuid-Holland",
    "sg:website":"http://www.web-creation.nl",
    "wof:name":"Web-Creation",
    "wof:placetype":"venue"
},
  "geometry": {"coordinates":[5.0893888474,51.8966331482],"type":"Point"}
}