{
  "type": "Feature",
  "properties": {
    "iso:country":"NL",
    "sg:address":"Schaverystr 30",
    "sg:city":"Utrecht",
    "sg:orig_category":"Drukkerijen",
    "sg:phone":"+31 30 244 7427",
    "sg:postcode":"3534 AS",
    "sg:province":"Utrecht",
    "wof:name":"Palm",
    "wof:placetype":"venue"
},
  "geometry": {"coordinates":[5.081801,52.10601],"type":"Point"}
}