{
  "type": "Feature",
  "properties": {
    "addr:full":"Havenweg 6 Amersfoort Utrecht 3812 PR",
    "addr:housenumber":"6",
    "addr:postcode":"3812 pr",
    "addr:street":"Havenweg",
    "iso:country":"NL",
    "sg:address":"Havenweg 6",
    "sg:city":"Amersfoort",
    "sg:orig_category":"Airconditioning And Ventilatie",
    "sg:phone":"+31 33 465 2391",
    "sg:postcode":"3812 PR",
    "sg:province":"Utrecht",
    "wof:name":"Zwankhuizen Instalatiebedrijf",
    "wof:placetype":"venue"
},
  "geometry": {"coordinates":[5.372334,52.165699],"type":"Point"}
}