{
  "type": "Feature",
  "properties": {
    "addr:full":"Margrietstraat 49 Mierlo North Brabant 5731 BN",
    "addr:housenumber":"49",
    "addr:postcode":"5731 bn",
    "addr:street":"Margrietstraat",
    "iso:country":"NL",
    "sg:address":"Margrietstraat 49",
    "sg:city":"Mierlo",
    "sg:orig_category":"Kappers",
    "sg:phone":"+31 492 664 433",
    "sg:postcode":"5731 BN",
    "sg:province":"North Brabant",
    "wof:name":"Ben Goede Coiffure",
    "wof:placetype":"venue"
},
  "geometry": {"coordinates":[5.6189699173,51.4423751831],"type":"Point"}
}