{
  "type": "Feature",
  "properties": {
    "addr:full":"Vermeerstr 9 Eerbeek Gelderland 6961 ZC",
    "addr:housenumber":"9",
    "addr:postcode":"6961 zc",
    "addr:street":"Vermeerstr;Gelderland",
    "iso:country":"NL",
    "sg:address":"Vermeerstr 9",
    "sg:city":"Eerbeek",
    "sg:orig_category":"Zonnebank- En Solariumcentra",
    "sg:phone":"+31 313 651 717",
    "sg:postcode":"6961 ZC",
    "sg:province":"Gelderland",
    "wof:name":"Liesbeth",
    "wof:placetype":"venue"
},
  "geometry": {"coordinates":[6.052511,52.10408],"type":"Point"}
}