{
  "type": "Feature",
  "properties": {
    "addr:full":"H Jurgensln 28 Berkel Enschot Noord-Brabant 5056 VT",
    "addr:housenumber":"28",
    "addr:postcode":"5056",
    "addr:street":"Berkel",
    "iso:country":"NL",
    "sg:address":"H Jurgensln 28",
    "sg:city":"Berkel Enschot",
    "sg:orig_category":"Adviesbureaus Economie",
    "sg:phone":"+31 13 533 1614",
    "sg:postcode":"5056 VT",
    "sg:province":"Noord-Brabant",
    "wof:name":"Sr Investments Bv",
    "wof:placetype":"venue"
},
  "geometry": {"coordinates":[5.136945,51.57674],"type":"Point"}
}