{
  "type": "Feature",
  "properties": {
    "addr:full":"Terpstr 9A Wieringerwerf North Holland 1771 AC",
    "addr:housenumber":"9a",
    "addr:postcode":"1771 ac",
    "addr:street":"Terpstr",
    "iso:country":"NL",
    "sg:address":"Terpstr 9A",
    "sg:city":"Wieringerwerf",
    "sg:orig_category":"Kappers",
    "sg:phone":"+31 227 603 008",
    "sg:postcode":"1771 AC",
    "sg:province":"North Holland",
    "wof:name":"Mariska'S",
    "wof:placetype":"venue"
},
  "geometry": {"coordinates":[5.023198,52.851479],"type":"Point"}
}