{
  "type": "Feature",
  "properties": {
    "addr:full":"Tapirstraat 14 Eindhoven Noord-Brabant 5646 BV",
    "addr:housenumber":"14",
    "addr:postcode":"5646 bv",
    "addr:street":"Tapirstraat",
    "iso:country":"NL",
    "sg:address":"Tapirstraat 14",
    "sg:city":"Eindhoven",
    "sg:classifiers":[
        {
            "category":"Food & Beverages",
            "subcategory":"Fruits & Vegetables",
            "type":"Retail Goods"
        }
    ],
    "sg:phone":"+31 40 211 8543",
    "sg:postcode":"5646 BV",
    "sg:province":"Noord-Brabant",
    "sg:tags":[
        "groenten"
    ],
    "wof:name":"A.J. Stratman",
    "wof:placetype":"venue"
},
  "geometry": {"coordinates":[5.50872,51.41898],"type":"Point"}
}