{
  "type": "Feature",
  "properties": {
    "iso:country":"NL",
    "sg:address":"Kerkstr 24",
    "sg:city":"Zandvoort",
    "sg:orig_category":"Woninginrichting",
    "sg:phone":"+31 23 573 0059",
    "sg:postcode":"2042 JG",
    "sg:province":"Noord-Holland",
    "wof:name":"Judy",
    "wof:placetype":"venue"
},
  "geometry": {"coordinates":[4.5278749466,52.3718223572],"type":"Point"}
}