{
  "type": "Feature",
  "properties": {
    "addr:full":"Z Om 45 Gemert North Brabant 5421 WS",
    "addr:housenumber":"45",
    "addr:postcode":"5421 ws",
    "iso:country":"NL",
    "sg:address":"Z Om 45",
    "sg:city":"Gemert",
    "sg:orig_category":"Benzine En Olie - Groothandel",
    "sg:phone":"+31 492 362 055",
    "sg:postcode":"5421 WS",
    "sg:province":"North Brabant",
    "wof:name":"Maas, J G",
    "wof:placetype":"venue"
},
  "geometry": {"coordinates":[5.681675,51.556126],"type":"Point"}
}