{
  "type": "Feature",
  "properties": {
    "addr:full":"W Diemerstr 7 Musselkanaal Groningen 9581 AG",
    "addr:housenumber":"7",
    "addr:postcode":"9581",
    "addr:street":"W;Musselkanaal",
    "iso:country":"NL",
    "sg:address":"W Diemerstr 7",
    "sg:city":"Musselkanaal",
    "sg:orig_category":"Bejaarden - Verzorgingstehuizen",
    "sg:phone":"+31 599 483 535",
    "sg:postcode":"9581 AG",
    "sg:province":"Groningen",
    "wof:name":"Heggerank, De",
    "wof:placetype":"venue"
},
  "geometry": {"coordinates":[7.016255,52.929642],"type":"Point"}
}