{
  "type": "Feature",
  "properties": {
    "addr:full":"Kinkerstraat 142A1 Amsterdam North Holland 1053 EG",
    "addr:housenumber":"142a1",
    "addr:postcode":"1053 eg",
    "addr:street":"Kinkerstraat",
    "iso:country":"NL",
    "sg:address":"Kinkerstraat 142A1",
    "sg:city":"Amsterdam",
    "sg:orig_category":"Grafisch Ontwerpers",
    "sg:phone":"+31 20 412 5072",
    "sg:postcode":"1053 EG",
    "sg:province":"North Holland",
    "sg:website":"http://www.sandor.nl",
    "wof:name":"Sandor",
    "wof:placetype":"venue"
},
  "geometry": {"coordinates":[4.869046,52.366528],"type":"Point"}
}