{
  "type": "Feature",
  "properties": {
    "addr:full":"Burg Weertsplnts 58 Santpoort Noord Noord-Holland 2071 PJ",
    "addr:housenumber":"58",
    "addr:postcode":"2071 pj",
    "addr:street":"Burg;Santpoort",
    "iso:country":"NL",
    "sg:address":"Burg Weertsplnts 58",
    "sg:city":"Santpoort Noord",
    "sg:orig_category":"Journalisten Freelance",
    "sg:phone":"+31 23 538 4620",
    "sg:postcode":"2071 PJ",
    "sg:province":"Noord-Holland",
    "wof:name":"Jan Van Den Berg",
    "wof:placetype":"venue"
},
  "geometry": {"coordinates":[-121.95871,39.780125],"type":"Point"}
}