{
  "type": "Feature",
  "properties": {
    "addr:full":"P J Noel Bakerstraat 40 Groningen Groningen 9728 WC",
    "addr:housenumber":"p j;40",
    "addr:postcode":"9728 wc",
    "addr:street":"Bakerstraat",
    "iso:country":"NL",
    "sg:address":"P J Noel Bakerstraat 40",
    "sg:city":"Groningen",
    "sg:orig_category":"Goederenvervoer Over De Weg",
    "sg:phone":"+31 50 525 7756",
    "sg:postcode":"9728 WC",
    "sg:province":"Groningen",
    "wof:name":"B. Oldenburger",
    "wof:placetype":"venue"
},
  "geometry": {"coordinates":[6.554689,53.187],"type":"Point"}
}