{
  "type": "Feature",
  "properties": {
    "iso:country":"NL",
    "sg:address":"Laanstraat 105",
    "sg:city":"Baarn",
    "sg:orig_category":"Bloemen And Planten",
    "sg:phone":"+31 35 541 2673",
    "sg:postcode":"3743 BD",
    "sg:province":"Utrecht",
    "wof:name":"Bloemisterij De Mengerij",
    "wof:placetype":"venue"
},
  "geometry": {"coordinates":[5.284427,52.212147],"type":"Point"}
}