{
  "type": "Feature",
  "properties": {
    "addr:full":"Wouwsestr 5 Steenbergen Nb North Brabant 4651 DV",
    "addr:housenumber":"5;nb",
    "addr:postcode":"4651 dv",
    "addr:street":"Wouwsestr",
    "iso:country":"NL",
    "sg:address":"Wouwsestr 5",
    "sg:city":"Steenbergen Nb",
    "sg:orig_category":"Land- En Tuinbouw - Loonbedrijven",
    "sg:phone":"+31 167 565 555",
    "sg:postcode":"4651 DV",
    "sg:province":"North Brabant",
    "wof:name":"Roge",
    "wof:placetype":"venue"
},
  "geometry": {"coordinates":[4.322931,51.58276],"type":"Point"}
}