{
  "type": "Feature",
  "properties": {
    "addr:full":"Fokkerstraat 12 Veenendaal Utrecht 3905 KV",
    "addr:housenumber":"12",
    "addr:postcode":"3905 kv",
    "addr:street":"Fokkerstraat",
    "iso:country":"NL",
    "sg:address":"Fokkerstraat 12",
    "sg:city":"Veenendaal",
    "sg:orig_category":"Kantoorartikelen",
    "sg:phone":"+31 318 553 440",
    "sg:postcode":"3905 KV",
    "sg:province":"Utrecht",
    "wof:name":"Zevenbergen Kantoorefficiency Bv",
    "wof:placetype":"venue"
},
  "geometry": {"coordinates":[5.5591540337,52.0387382507],"type":"Point"}
}