{
  "type": "Feature",
  "properties": {
    "addr:full":"Min Talmaln 155 Ryswyk Zh South Holland 2285 EE",
    "addr:housenumber":"155",
    "addr:postcode":"2285 ee",
    "addr:street":"Ryswyk Zh",
    "iso:country":"NL",
    "sg:address":"Min Talmaln 155",
    "sg:city":"Ryswyk Zh",
    "sg:orig_category":"Administratie- En Boekhoudkantoren",
    "sg:phone":"+31 70 393 4686",
    "sg:postcode":"2285 EE",
    "sg:province":"South Holland",
    "wof:name":"Bba",
    "wof:placetype":"venue"
},
  "geometry": {"coordinates":[4.32436,52.037251],"type":"Point"}
}