{
  "type": "Feature",
  "properties": {
    "addr:full":"Murenepad 11 Almere NL. 1317 RT",
    "addr:housenumber":"11",
    "addr:postcode":"1317 rt",
    "addr:street":"Murenepad;Nl.",
    "iso:country":"NL",
    "sg:address":"Murenepad 11",
    "sg:city":"Almere",
    "sg:orig_category":"Beeldende Kunstenaars",
    "sg:phone":"+31 36 530 1015",
    "sg:postcode":"1317 RT",
    "sg:province":"NL.",
    "wof:name":"Jong, Rineke De",
    "wof:placetype":"venue"
},
  "geometry": {"coordinates":[5.233401,52.389763],"type":"Point"}
}