{
  "type": "Feature",
  "properties": {
    "iso:country":"NL",
    "sg:address":"Nyverheidswg 10",
    "sg:city":"Giessenburg",
    "sg:orig_category":"Loonbedrijven",
    "sg:phone":"+31 184 651 036",
    "sg:postcode":"3381 LM",
    "sg:province":"South Holland",
    "wof:name":"Kreij, Gebr De",
    "wof:placetype":"venue"
},
  "geometry": {"coordinates":[4.896502,51.843922],"type":"Point"}
}