{
  "type": "Feature",
  "properties": {
    "iso:country":"NL",
    "sg:address":"Piet Heinstraat 51",
    "sg:city":"'S Gravenhage",
    "sg:orig_category":"Kappers",
    "sg:phone":"+31 70 360 7202",
    "sg:postcode":"2518 CB",
    "sg:province":"South Holland",
    "wof:name":"Haarzuiver",
    "wof:placetype":"venue"
},
  "geometry": {"coordinates":[4.2993149757,52.0822944641],"type":"Point"}
}