{
  "type": "Feature",
  "properties": {
    "iso:country":"NL",
    "sg:address":"Burgemeester Rietmanstr 8",
    "sg:city":"Gemert",
    "sg:orig_category":"Kappers",
    "sg:phone":"+31 492 362 330",
    "sg:postcode":"5421 JX",
    "sg:province":"Noord-Brabant",
    "wof:name":"Kapsalon Will Ploegmakers",
    "wof:placetype":"venue"
},
  "geometry": {"coordinates":[5.6924700737,51.5545272827],"type":"Point"}
}