{
  "type": "Feature",
  "properties": {
    "addr:full":"Malrove 25 Apeldoorn Gelderland 7322 GA",
    "addr:housenumber":"25",
    "addr:postcode":"7322 ga",
    "addr:street":"Malrove;Gelderland",
    "iso:country":"NL",
    "sg:address":"Malrove 25",
    "sg:city":"Apeldoorn",
    "sg:classifiers":[
        {
            "category":"Personal",
            "subcategory":"Nail Salon",
            "type":"Services"
        }
    ],
    "sg:phone":"+31 55 366 4639",
    "sg:postcode":"7322 GA",
    "sg:province":"Gelderland",
    "sg:tags":[
        "pedicure"
    ],
    "wof:name":"Knobbe-Hooghiemstra, T C M",
    "wof:placetype":"venue"
},
  "geometry": {"coordinates":[5.986151,52.225018],"type":"Point"}
}