{
  "type": "Feature",
  "properties": {
    "addr:full":"Mariastraat 1 Stramproy Limburg 6039 AW",
    "addr:housenumber":"1",
    "addr:postcode":"6039 aw",
    "addr:street":"Mariastraat",
    "iso:country":"NL",
    "sg:address":"Mariastraat 1",
    "sg:city":"Stramproy",
    "sg:orig_category":"Overheidsdiensten",
    "sg:phone":"+31 495 561 768",
    "sg:postcode":"6039 AW",
    "sg:province":"Limburg",
    "wof:name":"Gemeenschapscentrum",
    "wof:placetype":"venue"
},
  "geometry": {"coordinates":[5.7177119255,51.1972389221],"type":"Point"}
}