{
  "type": "Feature",
  "properties": {
    "addr:full":"Leeuwerikpln 19 Purmerend Noord-Holland 1444 HW",
    "addr:housenumber":"19",
    "addr:postcode":"1444 hw",
    "addr:street":"Leeuwerikpln",
    "iso:country":"NL",
    "sg:address":"Leeuwerikpln 19",
    "sg:city":"Purmerend",
    "sg:orig_category":"Opticiens",
    "sg:phone":"+31 299 660 277",
    "sg:postcode":"1444 HW",
    "sg:province":"Noord-Holland",
    "wof:name":"Cornea",
    "wof:placetype":"venue"
},
  "geometry": {"coordinates":[4.9619340897,52.520980835],"type":"Point"}
}