{
  "type": "Feature",
  "properties": {
    "addr:full":"Beekestein 9 Leiderdorp South Holland 2352 KL",
    "addr:housenumber":"9",
    "addr:postcode":"2352 kl",
    "addr:street":"Beekestein",
    "iso:country":"NL",
    "sg:address":"Beekestein 9",
    "sg:city":"Leiderdorp",
    "sg:orig_category":"Kinderkleding - Fabrieken En Groothandel",
    "sg:phone":"+31 71 541 8388",
    "sg:postcode":"2352 KL",
    "sg:province":"South Holland",
    "wof:name":"Den-Hol Trading",
    "wof:placetype":"venue"
},
  "geometry": {"coordinates":[4.530307,52.156075],"type":"Point"}
}