{
  "type": "Feature",
  "properties": {
    "addr:full":"Radio Oranjeln 19 Almere NL. 1318 AW",
    "addr:housenumber":"19",
    "addr:postcode":"1318 aw",
    "addr:street":"Nl.",
    "iso:country":"NL",
    "sg:address":"Radio Oranjeln 19",
    "sg:city":"Almere",
    "sg:orig_category":"Licentiebemiddeling",
    "sg:phone":"+31 36 535 3181",
    "sg:postcode":"1318 AW",
    "sg:province":"NL.",
    "wof:name":"Dutch Courage",
    "wof:placetype":"venue"
},
  "geometry": {"coordinates":[5.239677,52.379856],"type":"Point"}
}