{
  "type": "Feature",
  "properties": {
    "addr:full":"Herenwerf 18 Maasland South Holland 3155 DK",
    "addr:housenumber":"18",
    "addr:postcode":"3155 dk",
    "addr:street":"Herenwerf",
    "iso:country":"NL",
    "sg:address":"Herenwerf 18",
    "sg:city":"Maasland",
    "sg:classifiers":[
        {
            "category":"Food & Beverages",
            "subcategory":"Fruits & Vegetables",
            "type":"Retail Goods"
        }
    ],
    "sg:phone":"+31 174 520 780",
    "sg:postcode":"3155 DK",
    "sg:province":"South Holland",
    "sg:tags":[
        "en",
        "groenten"
    ],
    "wof:name":"Pamako",
    "wof:placetype":"venue"
},
  "geometry": {"coordinates":[4.247785,51.955093],"type":"Point"}
}