{
  "type": "Feature",
  "properties": {
    "addr:full":"Oude Engelensewg 22A S Hertogenbosch North Brabant 5223 KC",
    "addr:housenumber":"22a",
    "addr:postcode":"5223 kc",
    "addr:street":"Oude Engelensewg;S Hertogenbosch",
    "iso:country":"NL",
    "sg:address":"Oude Engelensewg 22A",
    "sg:city":"S Hertogenbosch",
    "sg:classifiers":[
        {
            "category":"Travel",
            "subcategory":"Hotels & Motels",
            "type":"Entertainment"
        }
    ],
    "sg:phone":"+31 73 621 8277",
    "sg:postcode":"5223 KC",
    "sg:province":"North Brabant",
    "wof:name":"Marktzicht, Hotel",
    "wof:placetype":"venue"
},
  "geometry": {"coordinates":[5.292591,51.698132],"type":"Point"}
}