{
  "type": "Feature",
  "properties": {
    "addr:full":"Hoogerheijdestraat 102 Ter Aar South Holland 2461 XG",
    "addr:housenumber":"102",
    "addr:postcode":"2461 xg",
    "addr:street":"Hoogerheijdestraat",
    "iso:country":"NL",
    "sg:address":"Hoogerheijdestraat 102",
    "sg:city":"Ter Aar",
    "sg:orig_category":"Bloemen And Planten",
    "sg:phone":"+31 172 605 769",
    "sg:postcode":"2461 XG",
    "sg:province":"South Holland",
    "wof:name":"G. Groen",
    "wof:placetype":"venue"
},
  "geometry": {"coordinates":[4.703967,52.162735],"type":"Point"}
}