{
  "type": "Feature",
  "properties": {
    "addr:full":"Aert De Gelderlaan 148 Alkmaar North Holland 1816 NC",
    "addr:housenumber":"148",
    "addr:postcode":"1816 nc",
    "addr:street":"Aert De Gelderlaan",
    "iso:country":"NL",
    "sg:address":"Aert De Gelderlaan 148",
    "sg:city":"Alkmaar",
    "sg:orig_category":"Boekhouders",
    "sg:phone":"+31 72 512 8661",
    "sg:postcode":"1816 NC",
    "sg:province":"North Holland",
    "wof:name":"S H E Koelewijn-Backer",
    "wof:placetype":"venue"
},
  "geometry": {"coordinates":[4.721585,52.630123],"type":"Point"}
}