{
  "type": "Feature",
  "properties": {
    "addr:full":"Admiraliteitskd 81C Rotterdam Zuid-Holland 3063 EG",
    "addr:housenumber":"81c",
    "addr:postcode":"3063 eg",
    "addr:street":"Admiraliteitskd",
    "iso:country":"NL",
    "sg:address":"Admiraliteitskd 81C",
    "sg:city":"Rotterdam",
    "sg:classifiers":[
        {
            "category":"Shopping",
            "subcategory":"Adult",
            "type":"Retail Goods"
        }
    ],
    "sg:phone":"+31 10 214 3500",
    "sg:postcode":"3063 EG",
    "sg:province":"Zuid-Holland",
    "sg:tags":[
        "lingerie",
        "en",
        "tricotage"
    ],
    "sg:website":"http://www.louisana.nl",
    "wof:name":"Louisana",
    "wof:placetype":"venue"
},
  "geometry": {"coordinates":[4.500111,51.922279],"type":"Point"}
}