{
  "type": "Feature",
  "properties": {
    "addr:full":"Rode Kruislaan 73 Groningen Groningen 9728 CT",
    "addr:housenumber":"73",
    "addr:postcode":"9728 ct",
    "addr:street":"Rode Kruislaan",
    "iso:country":"NL",
    "sg:address":"Rode Kruislaan 73",
    "sg:city":"Groningen",
    "sg:orig_category":"Kinderopvang Behalve Thuis",
    "sg:phone":"+31 50 527 2198",
    "sg:postcode":"9728 CT",
    "sg:province":"Groningen",
    "wof:name":"Kinderdagverblijf Rakkerbak",
    "wof:placetype":"venue"
},
  "geometry": {"coordinates":[6.558562,53.200451],"type":"Point"}
}