{
  "type": "Feature",
  "properties": {
    "addr:full":"Liniestr 121 Breda Noord-Brabant 4816 BG",
    "addr:housenumber":"121",
    "addr:postcode":"4816",
    "iso:country":"NL",
    "sg:address":"Liniestr 121",
    "sg:city":"Breda",
    "sg:classifiers":[
        {
            "category":"Wholesale",
            "subcategory":"Motor Vehicles",
            "type":"Manufacturing & Wholesale Goods"
        }
    ],
    "sg:phone":"+31 76 571 0719",
    "sg:postcode":"4816 BG",
    "sg:province":"Noord-Brabant",
    "sg:tags":[
        "scooter",
        "en"
    ],
    "sg:website":"http://www.oit-harley-davidson.com",
    "wof:name":"Harley-Davidson Oit",
    "wof:placetype":"venue"
},
  "geometry": {"coordinates":[4.787299,51.597031],"type":"Point"}
}