{
  "type": "Feature",
  "properties": {
    "addr:full":"Hoofdstr 33 Kerkrade Limburg 6461 CM",
    "addr:housenumber":"33",
    "addr:postcode":"6461 cm",
    "addr:street":"Hoofdstr",
    "iso:country":"NL",
    "sg:address":"Hoofdstr 33",
    "sg:city":"Kerkrade",
    "sg:orig_category":"Opticiens",
    "sg:phone":"+31 45 545 3707",
    "sg:postcode":"6461 CM",
    "sg:province":"Limburg",
    "wof:name":"Romijn, H",
    "wof:placetype":"venue"
},
  "geometry": {"coordinates":[6.0663528442,50.8644790649],"type":"Point"}
}