{
  "type": "Feature",
  "properties": {
    "addr:full":"Spuistr 12 Amsterdam Noord-Holland 1012 TS",
    "addr:housenumber":"12",
    "addr:postcode":"1012 ts",
    "addr:street":"Spuistr",
    "iso:country":"NL",
    "sg:address":"Spuistr 12",
    "sg:city":"Amsterdam",
    "sg:orig_category":"Verenigingen En Stichtingen",
    "sg:phone":"+31 20 624 2183",
    "sg:postcode":"1012 TS",
    "sg:province":"Noord-Holland",
    "wof:name":"Dominicus Gem",
    "wof:placetype":"venue"
},
  "geometry": {"coordinates":[4.893485,52.377045],"type":"Point"}
}