{
  "type": "Feature",
  "properties": {
    "addr:full":"Zaaijerplein 13 Oosterbeek Gelderland 6861 ZP",
    "addr:housenumber":"13",
    "addr:postcode":"6861 zp",
    "addr:street":"Zaaijerplein;Gelderland",
    "iso:country":"NL",
    "sg:address":"Zaaijerplein 13",
    "sg:city":"Oosterbeek",
    "sg:orig_category":"Fruit And Groenten Gh",
    "sg:phone":"+31 26 333 2388",
    "sg:postcode":"6861 ZP",
    "sg:province":"Gelderland",
    "wof:name":"C. Wenting",
    "wof:placetype":"venue"
},
  "geometry": {"coordinates":[5.847382,51.989647],"type":"Point"}
}