{
  "type": "Feature",
  "properties": {
    "addr:full":"Tiendhof 4 Harmelen Utrecht 3481 GS",
    "addr:housenumber":"4",
    "addr:postcode":"3481 gs",
    "addr:street":"Tiendhof",
    "iso:country":"NL",
    "sg:address":"Tiendhof 4",
    "sg:city":"Harmelen",
    "sg:orig_category":"Metselwerken",
    "sg:phone":"+31 348 443 197",
    "sg:postcode":"3481 GS",
    "sg:province":"Utrecht",
    "wof:name":"Berg, H C Van Den",
    "wof:placetype":"venue"
},
  "geometry": {"coordinates":[4.966069,52.097141],"type":"Point"}
}