{
  "type": "Feature",
  "properties": {
    "iso:country":"NL",
    "sg:address":"Gentianenln 11",
    "sg:city":"Oostvoorne",
    "sg:orig_category":"Adviesbureaus Financieel",
    "sg:phone":"+31 6 51811946",
    "sg:postcode":"3233 VC",
    "sg:province":"Zuid-Holland",
    "wof:name":"New Xchange Bv",
    "wof:placetype":"venue"
},
  "geometry": {"coordinates":[4.08623,51.903519],"type":"Point"}
}