{
  "type": "Feature",
  "properties": {
    "addr:full":"Gentianenln 11 Oostvoorne Zuid-Holland 3233 VC",
    "addr:housenumber":"11",
    "addr:postcode":"3233 vc",
    "addr:street":"Gentianenln",
    "iso:country":"NL",
    "sg:address":"Gentianenln 11",
    "sg:city":"Oostvoorne",
    "sg:orig_category":"Adviesbureaus Financieel",
    "sg:phone":"+31 6 51811946",
    "sg:postcode":"3233 VC",
    "sg:province":"Zuid-Holland",
    "wof:name":"New Xchange Bv",
    "wof:placetype":"venue"
},
  "geometry": {"coordinates":[4.08623,51.903519],"type":"Point"}
}