{
  "type": "Feature",
  "properties": {
    "addr:full":"Kerkbuurt 6 Westzaan North Holland 1551 AD",
    "addr:housenumber":"6",
    "addr:postcode":"1551 ad",
    "addr:street":"Kerkbuurt",
    "iso:country":"NL",
    "sg:address":"Kerkbuurt 6",
    "sg:city":"Westzaan",
    "sg:orig_category":"Beeldende Kunstenaars",
    "sg:phone":"+31 75 628 3287",
    "sg:postcode":"1551 AD",
    "sg:province":"North Holland",
    "wof:name":"Poelmeijer Bv",
    "wof:placetype":"venue"
},
  "geometry": {"coordinates":[4.772493,52.462456],"type":"Point"}
}