{
  "type": "Feature",
  "properties": {
    "addr:full":"Spuistraat 49 Amsterdam Noord-Holland 1012 SR",
    "addr:housenumber":"49",
    "addr:postcode":"1012 sr",
    "addr:street":"Spuistraat",
    "iso:country":"NL",
    "sg:address":"Spuistraat 49",
    "sg:city":"Amsterdam",
    "sg:orig_category":"Kantoorartikelen",
    "sg:phone":"+31 20 624 2806",
    "sg:postcode":"1012 SR",
    "sg:province":"Noord-Holland",
    "wof:name":"Ros Kantoorvakhandel",
    "wof:placetype":"venue"
},
  "geometry": {"coordinates":[4.892619133,52.3760528564],"type":"Point"}
}