{
  "type": "Feature",
  "properties": {
    "addr:full":"Menadostraat 47 Vlaardingen Zuid-Holland 3131 JK",
    "addr:housenumber":"47",
    "addr:postcode":"3131 jk",
    "addr:street":"Menadostraat",
    "iso:country":"NL",
    "sg:address":"Menadostraat 47",
    "sg:city":"Vlaardingen",
    "sg:orig_category":"Goederenvervoer Over De Weg",
    "sg:phone":"+31 10 435 3163",
    "sg:postcode":"3131 JK",
    "sg:province":"Zuid-Holland",
    "wof:name":"Vof T. Dangerman & Zoon",
    "wof:placetype":"venue"
},
  "geometry": {"coordinates":[4.332982,51.913364],"type":"Point"}
}