{
  "type": "Feature",
  "properties": {
    "addr:full":"Rompertpassage 53 'S Hertogenbosch North Brabant 5233 AP",
    "addr:housenumber":"53",
    "addr:postcode":"5233 ap",
    "addr:street":"Rompertpassage;' S Hertogenbosch",
    "iso:country":"NL",
    "sg:address":"Rompertpassage 53",
    "sg:city":"'S Hertogenbosch",
    "sg:orig_category":"Fotolaboratoria",
    "sg:phone":"+31 73 641 8248",
    "sg:postcode":"5233 AP",
    "sg:province":"North Brabant",
    "wof:name":"Fotolaboratorium G. Verstappen Bv",
    "wof:placetype":"venue"
},
  "geometry": {"coordinates":[5.314799,51.712414],"type":"Point"}
}