{
  "type": "Feature",
  "properties": {
    "addr:full":"C De Vriesweg 29 Dirkshorn Noord-Holland 1746 CM",
    "addr:housenumber":"29",
    "addr:postcode":"1746 cm",
    "addr:street":"C De Vriesweg",
    "iso:country":"NL",
    "sg:address":"C De Vriesweg 29",
    "sg:city":"Dirkshorn",
    "sg:orig_category":"Organisaties And Verenigingen",
    "sg:phone":"+31 224 551 753",
    "sg:postcode":"1746 CM",
    "sg:province":"Noord-Holland",
    "wof:name":"Jb Fiat 500",
    "wof:placetype":"venue"
},
  "geometry": {"coordinates":[4.7782402039,52.7332038879],"type":"Point"}
}