{
  "type": "Feature",
  "properties": {
    "addr:full":"Rijsdijk 146 Rhoon Zuid-Holland 3161 EW",
    "addr:housenumber":"146",
    "addr:postcode":"3161 ew",
    "addr:street":"Rijsdijk",
    "iso:country":"NL",
    "sg:address":"Rijsdijk 146",
    "sg:city":"Rhoon",
    "sg:orig_category":"Glaszetten",
    "sg:phone":"+31 10 501 6695",
    "sg:postcode":"3161 EW",
    "sg:province":"Zuid-Holland",
    "wof:name":"Schildersbedrijf J. Berkelaar Bv",
    "wof:placetype":"venue"
},
  "geometry": {"coordinates":[4.443261,51.863739],"type":"Point"}
}