{
  "type": "Feature",
  "properties": {
    "addr:full":"Pastorieln 2 Joure Friesland 8501 EZ",
    "addr:housenumber":"2",
    "addr:postcode":"8501 ez",
    "addr:street":"Pastorieln",
    "iso:country":"NL",
    "sg:address":"Pastorieln 2",
    "sg:city":"Joure",
    "sg:orig_category":"Amusementshallen",
    "sg:phone":"+31 513 416 959",
    "sg:postcode":"8501 EZ",
    "sg:province":"Friesland",
    "wof:name":"Paradiso",
    "wof:placetype":"venue"
},
  "geometry": {"coordinates":[5.796723,52.966557],"type":"Point"}
}