{
  "type": "Feature",
  "properties": {
    "iso:country":"NL",
    "sg:address":"Handwerkerszijde 110",
    "sg:city":"Drachten",
    "sg:orig_category":"Kappers",
    "sg:phone":"+31 512 524 215",
    "sg:postcode":"9201 CP",
    "sg:province":"Friesland",
    "wof:name":"Kapsalon Alie'S Haarsalon",
    "wof:placetype":"venue"
},
  "geometry": {"coordinates":[6.0913767815,53.1145057678],"type":"Point"}
}