{
  "type": "Feature",
  "properties": {
    "addr:full":"Blaak 22 Rotterdam Zuid-Holland 3011 TA",
    "addr:housenumber":"22",
    "addr:postcode":"3011 ta",
    "addr:street":"Blaak",
    "iso:country":"NL",
    "sg:address":"Blaak 22",
    "sg:city":"Rotterdam",
    "sg:orig_category":"Verenigingen En Stichtingen",
    "sg:phone":"+31 10 217 7640",
    "sg:postcode":"3011 TA",
    "sg:province":"Zuid-Holland",
    "wof:name":"Vervangingsfonds, Sticht",
    "wof:placetype":"venue"
},
  "geometry": {"coordinates":[4.486958,51.918682],"type":"Point"}
}