{
  "type": "Feature",
  "properties": {
    "addr:full":"Beatrixln 31 Dirksland Zuid-Holland 3247 AA",
    "addr:housenumber":"31",
    "addr:postcode":"3247 aa",
    "addr:street":"Beatrixln",
    "iso:country":"NL",
    "sg:address":"Beatrixln 31",
    "sg:city":"Dirksland",
    "sg:orig_category":"Verenigingsgebouwen",
    "sg:phone":"+31 187 601 777",
    "sg:postcode":"3247 AA",
    "sg:province":"Zuid-Holland",
    "wof:name":"Schakel, De",
    "wof:placetype":"venue"
},
  "geometry": {"coordinates":[4.100241,51.747036],"type":"Point"}
}