{
  "type": "Feature",
  "properties": {
    "addr:full":"Karnemelkstr 26 Ommen Overijssel 7731 JB",
    "addr:housenumber":"26",
    "addr:postcode":"7731 jb",
    "addr:street":"Karnemelkstr",
    "iso:country":"NL",
    "sg:address":"Karnemelkstr 26",
    "sg:city":"Ommen",
    "sg:orig_category":"Adviesbureaus Bedrijfsorganisatie",
    "sg:phone":"+31 529 462 334",
    "sg:postcode":"7731 JB",
    "sg:province":"Overijssel",
    "wof:name":"G2 Guide & Guard",
    "wof:placetype":"venue"
},
  "geometry": {"coordinates":[6.423257,52.519485],"type":"Point"}
}