{
  "type": "Feature",
  "properties": {
    "iso:country":"NL",
    "sg:address":"Zuiderhavenwg 46",
    "sg:city":"Tiel",
    "sg:classifiers":[
        {
            "category":"Home & Garden",
            "subcategory":"Garden Supply",
            "type":"Retail Goods"
        }
    ],
    "sg:phone":"+31 344 618 323",
    "sg:postcode":"4004 JJ",
    "sg:province":"Gelderland",
    "sg:tags":[
        "zand",
        "en",
        "grind"
    ],
    "wof:name":"Tlc Tielse Loswal Combinatie Vof",
    "wof:placetype":"venue"
},
  "geometry": {"coordinates":[5.435611,51.913929],"type":"Point"}
}