{
  "type": "Feature",
  "properties": {
    "addr:full":"Lutswei 2 Workum Friesland 8711 JG",
    "addr:housenumber":"2",
    "addr:postcode":"8711 jg",
    "addr:street":"Lutswei",
    "iso:country":"NL",
    "sg:address":"Lutswei 2",
    "sg:city":"Workum",
    "sg:classifiers":[
        {
            "category":"Retail",
            "subcategory":"Auto Repair",
            "type":"Services"
        }
    ],
    "sg:phone":"+31 515 540 558",
    "sg:postcode":"8711 JG",
    "sg:province":"Friesland",
    "sg:tags":[
        "garage"
    ],
    "sg:website":"http://www.jsb4x4.nl",
    "wof:name":"Jsb",
    "wof:placetype":"venue"
},
  "geometry": {"coordinates":[5.454999,52.971668],"type":"Point"}
}