{
  "type": "Feature",
  "properties": {
    "addr:full":"Noltheniusstr 47 Utrecht Utrecht 3533 SG",
    "addr:housenumber":"47",
    "addr:postcode":"3533 sg",
    "addr:street":"Noltheniusstr",
    "iso:country":"NL",
    "sg:address":"Noltheniusstr 47",
    "sg:city":"Utrecht",
    "sg:orig_category":"Adviesbureaus Gezondheidszorg",
    "sg:phone":"+31 30 294 7193",
    "sg:postcode":"3533 SG",
    "sg:province":"Utrecht",
    "wof:name":"Baas, M T G",
    "wof:placetype":"venue"
},
  "geometry": {"coordinates":[5.082515,52.086456],"type":"Point"}
}