{
  "type": "Feature",
  "properties": {
    "iso:country":"NL",
    "sg:address":"Brasem 38",
    "sg:city":"Raamsdonksveer",
    "sg:orig_category":"Kabels",
    "sg:phone":"+31 162 515 256",
    "sg:postcode":"4941 SE",
    "sg:province":"North Brabant",
    "sg:website":"http://www.12assemble.com",
    "wof:name":"12 Assemble",
    "wof:placetype":"venue"
},
  "geometry": {"coordinates":[4.8665571213,51.7086486816],"type":"Point"}
}