{
  "type": "Feature",
  "properties": {
    "addr:full":"Nieuwveensewg 102 Zevenhoven South Holland 2435 NW",
    "addr:housenumber":"102",
    "addr:postcode":"2435 nw",
    "iso:country":"NL",
    "sg:address":"Nieuwveensewg 102",
    "sg:city":"Zevenhoven",
    "sg:orig_category":"Kaas",
    "sg:phone":"+31 172 538 616",
    "sg:postcode":"2435 NW",
    "sg:province":"South Holland",
    "wof:name":"Nieuwenhuizen, Jan",
    "wof:placetype":"venue"
},
  "geometry": {"coordinates":[4.7821221352,52.1814346313],"type":"Point"}
}