{
  "type": "Feature",
  "properties": {
    "addr:full":"Willem De Zwijgerlaan 38 'S Gravenhage Zuid-Holland 2582 ER",
    "addr:housenumber":"38",
    "addr:postcode":"2582 er",
    "addr:street":"Willem De Zwijgerlaan;' S",
    "iso:country":"NL",
    "sg:address":"Willem De Zwijgerlaan 38",
    "sg:city":"'S Gravenhage",
    "sg:orig_category":"Kappers",
    "sg:phone":"+31 70 355 0724",
    "sg:postcode":"2582 ER",
    "sg:province":"Zuid-Holland",
    "wof:name":"H. Meysen",
    "wof:placetype":"venue"
},
  "geometry": {"coordinates":[4.2744321823,52.0905036926],"type":"Point"}
}