{
  "type": "Feature",
  "properties": {
    "iso:country":"NL",
    "sg:address":"Vilgert 16",
    "sg:city":"Neer",
    "sg:orig_category":"Technische Studies And Onderzoek",
    "sg:phone":"+31 475 597 542",
    "sg:postcode":"6086 NM",
    "sg:province":"Limburg",
    "wof:name":"Noten Design",
    "wof:placetype":"venue"
},
  "geometry": {"coordinates":[-106.026123,34.166161],"type":"Point"}
}