{
  "type": "Feature",
  "properties": {
    "iso:country":"NL",
    "sg:address":"Zwanenburgwal 300",
    "sg:city":"Amsterdam",
    "sg:orig_category":"Architecten",
    "sg:phone":"+31 20 626 5811",
    "sg:postcode":"1011 JH",
    "sg:province":"Noord-Holland",
    "wof:name":"Peter Hakkenberg Van Gaasbeek Architecten",
    "wof:placetype":"venue"
},
  "geometry": {"coordinates":[4.898478,52.367725],"type":"Point"}
}