{
  "type": "Feature",
  "properties": {
    "addr:full":"Herikkruid 7 Purmerend Noord-Holland 1441 XE",
    "addr:housenumber":"7",
    "addr:postcode":"1441 xe",
    "addr:street":"Herikkruid",
    "iso:country":"NL",
    "sg:address":"Herikkruid 7",
    "sg:city":"Purmerend",
    "sg:orig_category":"Administratie- En Boekhoudkantoren",
    "sg:phone":"+31 299 424 614",
    "sg:postcode":"1441 XE",
    "sg:province":"Noord-Holland",
    "wof:name":"Administrateur, De",
    "wof:placetype":"venue"
},
  "geometry": {"coordinates":[4.951911,52.489506],"type":"Point"}
}