{
  "type": "Feature",
  "properties": {
    "iso:country":"NL",
    "sg:address":"Eenlandswg 52",
    "sg:city":"Halsteren",
    "sg:orig_category":"Begraafplaatsen",
    "sg:phone":"+31 164 680 519",
    "sg:postcode":"4661 LK",
    "sg:province":"North Brabant",
    "wof:name":"Memodes",
    "wof:placetype":"venue"
},
  "geometry": {"coordinates":[4.276771,51.524921],"type":"Point"}
}