{
  "type": "Feature",
  "properties": {
    "addr:full":"G Meirstr 15 Groningen Groningen 9728 TB",
    "addr:housenumber":"15",
    "addr:postcode":"9728 tb",
    "iso:country":"NL",
    "sg:address":"G Meirstr 15",
    "sg:city":"Groningen",
    "sg:orig_category":"Adviesbureaus Bedrijfsorganisatie",
    "sg:phone":"+31 50 528 0411",
    "sg:postcode":"9728 TB",
    "sg:province":"Groningen",
    "wof:name":"K'S Concern Bv",
    "wof:placetype":"venue"
},
  "geometry": {"coordinates":[6.557444,53.188141],"type":"Point"}
}