{
  "type": "Feature",
  "properties": {
    "iso:country":"NL",
    "sg:address":"De Heurne 4",
    "sg:city":"Enschede",
    "sg:orig_category":"Boekenuitgeverijen",
    "sg:phone":"+31 53 434 6553",
    "sg:postcode":"7511 GX",
    "sg:province":"NL.08",
    "wof:name":"Boekenvoordeel Bv",
    "wof:placetype":"venue"
},
  "geometry": {"coordinates":[6.898985,52.21981],"type":"Point"}
}