{
  "type": "Feature",
  "properties": {
    "iso:country":"NL",
    "sg:address":"Koepas 8",
    "sg:city":"Oirlo",
    "sg:orig_category":"Groepsaccommodaties",
    "sg:phone":"+31 478 571 581",
    "sg:postcode":"5808 AB",
    "sg:province":"Limburg",
    "wof:name":"Walnoot, Camping De",
    "wof:placetype":"venue"
},
  "geometry": {"coordinates":[6.007192,51.503513],"type":"Point"}
}