{
  "type": "Feature",
  "properties": {
    "addr:full":"Kokswijk 1A Zevenhuizen Gn Groningen 9354 BV",
    "addr:housenumber":"1a;gn",
    "addr:postcode":"9354 bv",
    "addr:street":"Kokswijk",
    "iso:country":"NL",
    "sg:address":"Kokswijk 1A",
    "sg:city":"Zevenhuizen Gn",
    "sg:orig_category":"Huishoudapparatuur, Televisies And Radio'S",
    "sg:phone":"+31 594 631 217",
    "sg:postcode":"9354 BV",
    "sg:province":"Groningen",
    "wof:name":"Poeder & Prins Vof",
    "wof:placetype":"venue"
},
  "geometry": {"coordinates":[6.350362,53.123405],"type":"Point"}
}