{
  "type": "Feature",
  "properties": {
    "iso:country":"NL",
    "sg:address":"Norbertplein 3",
    "sg:city":"Gennep",
    "sg:orig_category":"Overheidsdiensten",
    "sg:phone":"+31 485 512 923",
    "sg:postcode":"6591 XA",
    "sg:province":"Limburg",
    "wof:name":"Van Ons",
    "wof:placetype":"venue"
},
  "geometry": {"coordinates":[5.9808812141,51.6898002625],"type":"Point"}
}