{
  "type": "Feature",
  "properties": {
    "addr:full":"Bergweg 297 Rotterdam South Holland 3037 EN",
    "addr:housenumber":"297",
    "addr:postcode":"3037 en",
    "addr:street":"Bergweg",
    "iso:country":"NL",
    "sg:address":"Bergweg 297",
    "sg:city":"Rotterdam",
    "sg:orig_category":"Metalen And Ertsen Gh",
    "sg:phone":"+31 10 466 0564",
    "sg:postcode":"3037 EN",
    "sg:province":"South Holland",
    "wof:name":"Staalhandel De Giessen Bv",
    "wof:placetype":"venue"
},
  "geometry": {"coordinates":[4.473181,51.933563],"type":"Point"}
}