{
  "type": "Feature",
  "properties": {
    "addr:full":"Wolfstr 28 Maastricht Limburg 6211 GN",
    "addr:housenumber":"28",
    "addr:postcode":"6211 gn",
    "addr:street":"Wolfstr",
    "iso:country":"NL",
    "sg:address":"Wolfstr 28",
    "sg:city":"Maastricht",
    "sg:orig_category":"Koffiebranderijen",
    "sg:phone":"+31 43 321 3475",
    "sg:postcode":"6211 GN",
    "sg:province":"Limburg",
    "wof:name":"Blanche Dael, Maison",
    "wof:placetype":"venue"
},
  "geometry": {"coordinates":[5.692434,50.848083],"type":"Point"}
}