{
  "type": "Feature",
  "properties": {
    "iso:country":"NL",
    "sg:address":"Bartoklaan 1",
    "sg:city":"Heemstede",
    "sg:classifiers":[
        {
            "category":"Fast Food",
            "type":"Food & Drink"
        }
    ],
    "sg:phone":"+31 23 528 6090",
    "sg:postcode":"2102 ZA",
    "sg:province":"Noord-Holland",
    "sg:tags":[
        "afhaal",
        "restaurant"
    ],
    "wof:name":"Chinees Indisch Restaurant China Palace",
    "wof:placetype":"venue"
},
  "geometry": {"coordinates":[4.633485,52.353439],"type":"Point"}
}