{
  "type": "Feature",
  "properties": {
    "addr:full":"Van Haestrechtstraat 66 Goirle Noord-Brabant 5051 VE",
    "addr:housenumber":"66",
    "addr:postcode":"5051",
    "addr:street":"Van Haestrechtstraat;Ve",
    "iso:country":"NL",
    "sg:address":"Van Haestrechtstraat 66",
    "sg:city":"Goirle",
    "sg:orig_category":"Artsen And Specialisten",
    "sg:phone":"+31 13 534 1799",
    "sg:postcode":"5051 VE",
    "sg:province":"Noord-Brabant",
    "wof:name":"J.H.L. Van Doorn",
    "wof:placetype":"venue"
},
  "geometry": {"coordinates":[5.074879,51.524155],"type":"Point"}
}