{
  "type": "Feature",
  "properties": {
    "addr:full":"Shannonwg 27A Luchth Schiphol Noord-Holland 1118 LA",
    "addr:housenumber":"27a",
    "addr:postcode":"1118 la",
    "addr:street":"Shannonwg",
    "iso:country":"NL",
    "sg:address":"Shannonwg 27A",
    "sg:city":"Luchth Schiphol",
    "sg:orig_category":"Luchtvaart- Agentschappen",
    "sg:phone":"+31 20 446 0982",
    "sg:postcode":"1118 LA",
    "sg:province":"Noord-Holland",
    "sg:website":"http://www.eurocargoaviation.com",
    "wof:name":"Euro Cargo Aviation Bv",
    "wof:placetype":"venue"
},
  "geometry": {"coordinates":[4.765048,52.290504],"type":"Point"}
}