{
  "type": "Feature",
  "properties": {
    "addr:full":"Meridiaan 1315 Gouda Flevoland 2801 DA",
    "addr:housenumber":"1315;2801",
    "addr:postcode":"da",
    "addr:street":"Meridiaan;Flevoland",
    "iso:country":"NL",
    "sg:address":"Meridiaan 1315",
    "sg:city":"Gouda",
    "sg:orig_category":"Meubelstoffering",
    "sg:phone":"+31 182 514 505",
    "sg:postcode":"2801 DA",
    "sg:province":"Flevoland",
    "wof:name":"Koemans",
    "wof:placetype":"venue"
},
  "geometry": {"coordinates":[4.68576,52.016891],"type":"Point"}
}