{
  "type": "Feature",
  "properties": {
    "addr:full":"Opaalstr 22 Hengelo Ov Overijssel 7554 TS",
    "addr:housenumber":"22",
    "addr:postcode":"7554 ts",
    "addr:street":"Opaalstr;Ov",
    "iso:country":"NL",
    "sg:address":"Opaalstr 22",
    "sg:city":"Hengelo Ov",
    "sg:orig_category":"Waterbehandeling En Waterzuiverings- Systemen",
    "sg:phone":"+31 74 242 2009",
    "sg:postcode":"7554 TS",
    "sg:province":"Overijssel",
    "wof:name":"Norit Bv",
    "wof:placetype":"venue"
},
  "geometry": {"coordinates":[6.7768311501,52.2439498901],"type":"Point"}
}