{
  "type": "Feature",
  "properties": {
    "addr:full":"Lindeboom 169 Mook Limburg 6585 BL",
    "addr:housenumber":"169",
    "addr:postcode":"6585 bl",
    "addr:street":"Lindeboom",
    "iso:country":"NL",
    "sg:address":"Lindeboom 169",
    "sg:city":"Mook",
    "sg:classifiers":[
        {
            "category":"Personal",
            "subcategory":"Nail Salon",
            "type":"Services"
        }
    ],
    "sg:phone":"+31 24 696 2478",
    "sg:postcode":"6585 BL",
    "sg:province":"Limburg",
    "sg:tags":[
        "pedicure"
    ],
    "wof:name":"Zuylen-De Jonge, G F C Van",
    "wof:placetype":"venue"
},
  "geometry": {"coordinates":[5.888306,51.747684],"type":"Point"}
}