{
  "type": "Feature",
  "properties": {
    "iso:country":"NL",
    "sg:address":"Haringhuizerwg 1",
    "sg:city":"Schagen",
    "sg:orig_category":"Adviesbureaus Bouwkosten",
    "sg:phone":"+31 224 292 828",
    "sg:postcode":"1742 NS",
    "sg:province":"Noord-Holland",
    "wof:name":"Wijnker",
    "wof:placetype":"venue"
},
  "geometry": {"coordinates":[4.816689,52.773937],"type":"Point"}
}