{
  "type": "Feature",
  "properties": {
    "iso:country":"NL",
    "sg:address":"Teylerplein 79",
    "sg:city":"Haarlem",
    "sg:orig_category":"Apotheken",
    "sg:phone":"+31 23 535 3431",
    "sg:postcode":"2032 NB",
    "sg:province":"Noord-Holland",
    "sg:website":"http://www.teylerapotheek.nl",
    "wof:name":"Teyler Apotheek",
    "wof:placetype":"venue"
},
  "geometry": {"coordinates":[4.649767,52.378437],"type":"Point"}
}