{
  "type": "Feature",
  "properties": {
    "iso:country":"NL",
    "sg:address":"J F Kennedyln 51",
    "sg:city":"Valkenswaard",
    "sg:orig_category":"Kantoor- En Bedrijfsmeubelen",
    "sg:phone":"+31 40 208 4222",
    "sg:postcode":"5555 XC",
    "sg:province":"North Brabant",
    "sg:website":"http://www.ercogroep.nl",
    "wof:name":"Erco Groep",
    "wof:placetype":"venue"
},
  "geometry": {"coordinates":[5.4589700699,51.3505096436],"type":"Point"}
}