{
  "type": "Feature",
  "properties": {
    "iso:country":"NL",
    "sg:address":"Kalverstr 8",
    "sg:city":"Ouderkerk Ad Yssel",
    "sg:orig_category":"Kappers",
    "sg:phone":"+31 180 682 196",
    "sg:postcode":"2935 AE",
    "sg:province":"Zuid-Holland",
    "wof:name":"Marijke",
    "wof:placetype":"venue"
},
  "geometry": {"coordinates":[4.634619,51.934837],"type":"Point"}
}