{
  "type": "Feature",
  "properties": {
    "addr:full":"Mgr Poelsstr 46 Hoogerheide Noord-Brabant 4631 CB",
    "addr:housenumber":"46",
    "addr:postcode":"4631 cb",
    "addr:street":"Poelsstr",
    "iso:country":"NL",
    "sg:address":"Mgr Poelsstr 46",
    "sg:city":"Hoogerheide",
    "sg:orig_category":"Grafisch Ontwerpers",
    "sg:phone":"+31 164 616 858",
    "sg:postcode":"4631 CB",
    "sg:province":"Noord-Brabant",
    "wof:name":"In-Vorm Communicatie",
    "wof:placetype":"venue"
},
  "geometry": {"coordinates":[4.323843,51.419769],"type":"Point"}
}