{
  "type": "Feature",
  "properties": {
    "addr:full":"Engelenkampstraat 6 Sittard Limburg 6131 JG",
    "addr:housenumber":"6",
    "addr:postcode":"6131 jg",
    "addr:street":"Engelenkampstraat",
    "iso:country":"NL",
    "sg:address":"Engelenkampstraat 6",
    "sg:city":"Sittard",
    "sg:orig_category":"Boekhouders",
    "sg:phone":"+31 46 411 1866",
    "sg:postcode":"6131 JG",
    "sg:province":"Limburg",
    "wof:name":"Administratiekantoor Adservo",
    "wof:placetype":"venue"
},
  "geometry": {"coordinates":[5.870955,50.994743],"type":"Point"}
}