{
  "type": "Feature",
  "properties": {
    "addr:full":"Lichtenvoordsestraatweg 99 Aalten Gelderland 7121 RE",
    "addr:housenumber":"99",
    "addr:postcode":"7121",
    "addr:street":"Lichtenvoordsestraatweg;Gelderland",
    "iso:country":"NL",
    "sg:address":"Lichtenvoordsestraatweg 99",
    "sg:city":"Aalten",
    "sg:orig_category":"Vertaal- And Tolkenbureaus",
    "sg:phone":"+31 543 451 393",
    "sg:postcode":"7121 RE",
    "sg:province":"Gelderland",
    "wof:name":"J.W. Tolkamp",
    "wof:placetype":"venue"
},
  "geometry": {"coordinates":[6.592184,51.970871],"type":"Point"}
}