{
  "type": "Feature",
  "properties": {
    "iso:country":"NL",
    "sg:address":"Reiger 28",
    "sg:city":"Sprang Capelle",
    "sg:classifiers":[
        {
            "category":"Personal",
            "subcategory":"Nail Salon",
            "type":"Services"
        }
    ],
    "sg:phone":"+31 416 279 097",
    "sg:postcode":"5161 TZ",
    "sg:province":"North Brabant",
    "sg:tags":[
        "pedicure"
    ],
    "wof:name":"Dungen-Van Laarhoven, A E M Van Den",
    "wof:placetype":"venue"
},
  "geometry": {"coordinates":[5.019456,51.678284],"type":"Point"}
}