{
  "type": "Feature",
  "properties": {
    "addr:full":"Boonswg 8A Heinenoord Zuid-Holland 3274 LH",
    "addr:housenumber":"8a",
    "addr:postcode":"3274 lh",
    "addr:street":"Boonswg",
    "iso:country":"NL",
    "sg:address":"Boonswg 8A",
    "sg:city":"Heinenoord",
    "sg:classifiers":[
        {
            "category":"Retail",
            "subcategory":"Auto Repair",
            "type":"Services"
        }
    ],
    "sg:phone":"+31 10 462 5888",
    "sg:postcode":"3274 LH",
    "sg:province":"Zuid-Holland",
    "sg:tags":[
        "garage"
    ],
    "wof:name":"D & S",
    "wof:placetype":"venue"
},
  "geometry": {"coordinates":[4.521974,51.814999],"type":"Point"}
}