{
  "type": "Feature",
  "properties": {
    "addr:full":"Zuiderwg 58 Wydewormer Noord-Holland 1456 NG",
    "addr:housenumber":"58",
    "addr:postcode":"1456 ng",
    "addr:street":"Zuiderwg",
    "iso:country":"NL",
    "sg:address":"Zuiderwg 58",
    "sg:city":"Wydewormer",
    "sg:orig_category":"Zuivel - Groothandel",
    "sg:phone":"+31 299 421 912",
    "sg:postcode":"1456 NG",
    "sg:province":"Noord-Holland",
    "wof:name":"Dam & Zn, C Van",
    "wof:placetype":"venue"
},
  "geometry": {"coordinates":[4.873412,52.477688],"type":"Point"}
}