{
  "type": "Feature",
  "properties": {
    "iso:country":"NL",
    "sg:address":"Burgemeester Meslaan 68",
    "sg:city":"Tiel",
    "sg:orig_category":"Apothekers",
    "sg:phone":"+31 344 615 383",
    "sg:postcode":"4003 CC",
    "sg:province":"Gelderland",
    "wof:name":"Apotheek Drumpt",
    "wof:placetype":"venue"
},
  "geometry": {"coordinates":[5.412927,51.895058],"type":"Point"}
}