{
  "type": "Feature",
  "properties": {
    "addr:full":"Bosrand 42 Ens NL. 8307 AH",
    "addr:housenumber":"42",
    "addr:postcode":"8307 ah",
    "addr:street":"Bosrand;Nl.",
    "iso:country":"NL",
    "sg:address":"Bosrand 42",
    "sg:city":"Ens",
    "sg:orig_category":"Montagebedrijven",
    "sg:phone":"+31 527 251 607",
    "sg:postcode":"8307 AH",
    "sg:province":"NL.",
    "wof:name":"Jonkers",
    "wof:placetype":"venue"
},
  "geometry": {"coordinates":[5.825327,52.639046],"type":"Point"}
}