{
  "type": "Feature",
  "properties": {
    "addr:full":"Haersoltewg 23 Dalfsen NL.08 7722 SE",
    "addr:housenumber":"23;nl.08",
    "addr:postcode":"7722 se",
    "addr:street":"Haersoltewg",
    "iso:country":"NL",
    "sg:address":"Haersoltewg 23",
    "sg:city":"Dalfsen",
    "sg:orig_category":"Fitnesscentra",
    "sg:phone":"+31 529 434 447",
    "sg:postcode":"7722 SE",
    "sg:province":"NL.08",
    "wof:name":"Kontrast Sportstudio",
    "wof:placetype":"venue"
},
  "geometry": {"coordinates":[6.267739,52.519852],"type":"Point"}
}