{
  "type": "Feature",
  "properties": {
    "addr:full":"Hasseltstraat 175 Tilburg North Brabant 5046 LK",
    "addr:housenumber":"175",
    "addr:postcode":"5046 lk",
    "addr:street":"Hasseltstraat",
    "iso:country":"NL",
    "sg:address":"Hasseltstraat 175",
    "sg:city":"Tilburg",
    "sg:orig_category":"Elektriciens",
    "sg:phone":"+31 13 542 4518",
    "sg:postcode":"5046 LK",
    "sg:province":"North Brabant",
    "wof:name":"Bv Electrotechnisch Installatiebureau Veti",
    "wof:placetype":"venue"
},
  "geometry": {"coordinates":[5.07308,51.571442],"type":"Point"}
}