{
  "type": "Feature",
  "properties": {
    "addr:full":"Nassau Dillenburgstr 4 Den Haag Zuid-Holland 2596 AD",
    "addr:housenumber":"4",
    "addr:postcode":"2596 ad",
    "addr:street":"Dillenburgstr",
    "iso:country":"NL",
    "sg:address":"Nassau Dillenburgstr 4",
    "sg:city":"Den Haag",
    "sg:orig_category":"Balletscholen",
    "sg:phone":"+31 70 328 0566",
    "sg:postcode":"2596 AD",
    "sg:province":"Zuid-Holland",
    "wof:name":"Jean Heesbeen",
    "wof:placetype":"venue"
},
  "geometry": {"coordinates":[4.313538,52.089249],"type":"Point"}
}