{
  "type": "Feature",
  "properties": {
    "addr:full":"Fluitenbergstr 23 S Gravenhage Zuid-Holland 2545 NK",
    "addr:housenumber":"23;gravenhage",
    "addr:postcode":"2545 nk",
    "addr:street":"Fluitenbergstr;S",
    "iso:country":"NL",
    "sg:address":"Fluitenbergstr 23",
    "sg:city":"S Gravenhage",
    "sg:orig_category":"Onderhoudswerken",
    "sg:phone":"+31 70 329 4377",
    "sg:postcode":"2545 NK",
    "sg:province":"Zuid-Holland",
    "wof:name":"Heuvel, J Van Den",
    "wof:placetype":"venue"
},
  "geometry": {"coordinates":[4.27049,52.05093],"type":"Point"}
}