{
  "type": "Feature",
  "properties": {
    "addr:full":"Torenstr 50 Helvoirt Noord-Brabant 5268 AV",
    "addr:housenumber":"50",
    "addr:postcode":"5268 av",
    "addr:street":"Torenstr",
    "iso:country":"NL",
    "sg:address":"Torenstr 50",
    "sg:city":"Helvoirt",
    "sg:orig_category":"Fietsen En Bromfietsen",
    "sg:phone":"+31 411 642 313",
    "sg:postcode":"5268 AV",
    "sg:province":"Noord-Brabant",
    "wof:name":"Rijwielcentrale, De",
    "wof:placetype":"venue"
},
  "geometry": {"coordinates":[5.23742,51.63065],"type":"Point"}
}