{
  "type": "Feature",
  "properties": {
    "addr:full":"R De Beerenb Str 3 Venlo Limburg 5911 BC",
    "addr:housenumber":"3",
    "addr:postcode":"5911 bc",
    "addr:street":"Str",
    "iso:country":"NL",
    "sg:address":"R De Beerenb Str 3",
    "sg:city":"Venlo",
    "sg:orig_category":"Mode Artikelen Dames En Heren - Fabrieken En Groothandel",
    "sg:phone":"+31 77 354 2939",
    "sg:postcode":"5911 BC",
    "sg:province":"Limburg",
    "wof:name":"Haanen, H",
    "wof:placetype":"venue"
},
  "geometry": {"coordinates":[6.17286,51.372421],"type":"Point"}
}