{
  "type": "Feature",
  "properties": {
    "addr:full":"Keizersgracht 209 Amsterdam Noord-Holland 1016 DT",
    "addr:housenumber":"209",
    "addr:postcode":"1016 dt",
    "addr:street":"Keizersgracht",
    "iso:country":"NL",
    "sg:address":"Keizersgracht 209",
    "sg:city":"Amsterdam",
    "sg:orig_category":"Public Relationbureaus",
    "sg:phone":"+31 20 624 8119",
    "sg:postcode":"1016 DT",
    "sg:province":"Noord-Holland",
    "wof:name":"Strike",
    "wof:placetype":"venue"
},
  "geometry": {"coordinates":[4.88547,52.373333],"type":"Point"}
}