{
  "type": "Feature",
  "properties": {
    "addr:full":"Burg Vd Elzenln 41 Oss Virginia 5348 JN",
    "addr:housenumber":"41",
    "addr:postcode":"5348 jn",
    "addr:street":"Burg",
    "iso:country":"NL",
    "sg:address":"Burg Vd Elzenln 41",
    "sg:city":"Oss",
    "sg:orig_category":"Accountants - Administratie- Consulenten En -Kantoren",
    "sg:phone":"+31 412 632 905",
    "sg:postcode":"5348 JN",
    "sg:province":"Virginia",
    "sg:website":"http://www.toncman-kappen.nl",
    "wof:name":"Toncman & Kappen Bv Accountants",
    "wof:placetype":"venue"
},
  "geometry": {"coordinates":[-77.235214,38.312599],"type":"Point"}
}