{
  "type": "Feature",
  "properties": {
    "addr:full":"Erfstr 10 Uden Noord-Brabant 5405 BE",
    "addr:housenumber":"10",
    "addr:postcode":"5405",
    "addr:street":"Erfstr",
    "iso:country":"NL",
    "sg:address":"Erfstr 10",
    "sg:city":"Uden",
    "sg:orig_category":"Medische Installaties En Instrumenten",
    "sg:phone":"+31 413 335 144",
    "sg:postcode":"5405 BE",
    "sg:province":"Noord-Brabant",
    "wof:name":"Task Bv",
    "wof:placetype":"venue"
},
  "geometry": {"coordinates":[4.47677,50.500992],"type":"Point"}
}