{
  "type": "Feature",
  "properties": {
    "addr:full":"Willeskop 139A Oudewater Utrecht 3421 GV",
    "addr:housenumber":"139a",
    "addr:postcode":"3421 gv",
    "addr:street":"Willeskop",
    "iso:country":"NL",
    "sg:address":"Willeskop 139A",
    "sg:city":"Oudewater",
    "sg:orig_category":"Verbouwingen",
    "sg:phone":"+31 348 565 121",
    "sg:postcode":"3421 GV",
    "sg:province":"Utrecht",
    "sg:website":"http://www.sgbouw.nl",
    "wof:name":"S G Bouw, Aannemersbedrijf",
    "wof:placetype":"venue"
},
  "geometry": {"coordinates":[4.882842,52.019238],"type":"Point"}
}