{
  "type": "Feature",
  "properties": {
    "addr:full":"Utrechtsestr 9 Amersfoort Utrecht 3811 LA",
    "addr:housenumber":"9",
    "addr:postcode":"3811 la",
    "addr:street":"Utrechtsestr",
    "iso:country":"NL",
    "sg:address":"Utrechtsestr 9",
    "sg:city":"Amersfoort",
    "sg:orig_category":"Wijnkoperijen En -Groothandel",
    "sg:phone":"+31 33 461 3371",
    "sg:postcode":"3811 LA",
    "sg:province":"Utrecht",
    "sg:website":"http://www.wijnimport.org",
    "wof:name":"Zoete Vreugde, Genootschap Van De",
    "wof:placetype":"venue"
},
  "geometry": {"coordinates":[5.3867001534,52.1543998718],"type":"Point"}
}