{
  "type": "Feature",
  "properties": {
    "iso:country":"NL",
    "sg:address":"Boomgaard 3",
    "sg:city":"Drimmelen",
    "sg:orig_category":"Autokeuringen",
    "sg:phone":"+31 162 681 050",
    "sg:postcode":"4924 BZ",
    "sg:province":"Noord-Brabant",
    "wof:name":"Vema Bv",
    "wof:placetype":"venue"
},
  "geometry": {"coordinates":[4.80643,51.707001],"type":"Point"}
}