{
  "type": "Feature",
  "properties": {
    "addr:full":"Hamstraat 29 Roermond Limburg 6041 HA",
    "addr:housenumber":"29",
    "addr:postcode":"6041 ha",
    "addr:street":"Hamstraat",
    "iso:country":"NL",
    "sg:address":"Hamstraat 29",
    "sg:city":"Roermond",
    "sg:orig_category":"Herenmodezaken",
    "sg:phone":"+31 475 332 237",
    "sg:postcode":"6041 HA",
    "sg:province":"Limburg",
    "wof:name":"Elgozo Bv",
    "wof:placetype":"venue"
},
  "geometry": {"coordinates":[5.989874,51.19339],"type":"Point"}
}