{
  "type": "Feature",
  "properties": {
    "addr:full":"Bergstr 90 Goirle Noord-Brabant 5051 HD",
    "addr:housenumber":"90",
    "addr:postcode":"5051 hd",
    "addr:street":"Bergstr",
    "iso:country":"NL",
    "sg:address":"Bergstr 90",
    "sg:city":"Goirle",
    "sg:orig_category":"Plafonds",
    "sg:phone":"+31 13 534 0189",
    "sg:postcode":"5051 HD",
    "sg:province":"Noord-Brabant",
    "wof:name":"Dun Plafonds & Wanden Vof, Van",
    "wof:placetype":"venue"
},
  "geometry": {"coordinates":[5.062898,51.515991],"type":"Point"}
}