{
  "type": "Feature",
  "properties": {
    "iso:country":"NL",
    "sg:address":"Nieuwstraat 38",
    "sg:city":"Westmaas",
    "sg:orig_category":"Elektriciens",
    "sg:phone":"+31 186 572 658",
    "sg:postcode":"3273 AR",
    "sg:province":"Zuid-Holland",
    "wof:name":"Van Der Giesen Bv",
    "wof:placetype":"venue"
},
  "geometry": {"coordinates":[4.473611,51.790321],"type":"Point"}
}