{
  "type": "Feature",
  "properties": {
    "addr:full":"Meeuwerderweg 103 Groningen Groningen 9724 ER",
    "addr:housenumber":"103",
    "addr:postcode":"9724 er",
    "addr:street":"Meeuwerderweg",
    "iso:country":"NL",
    "sg:address":"Meeuwerderweg 103",
    "sg:city":"Groningen",
    "sg:classifiers":[
        {
            "category":"Food & Beverages",
            "subcategory":"Fruits & Vegetables",
            "type":"Retail Goods"
        }
    ],
    "sg:phone":"+31 50 313 2039",
    "sg:postcode":"9724 ER",
    "sg:province":"Groningen",
    "sg:tags":[
        "groenten"
    ],
    "wof:name":"H Mulder",
    "wof:placetype":"venue"
},
  "geometry": {"coordinates":[6.57885,53.211166],"type":"Point"}
}