{
  "type": "Feature",
  "properties": {
    "addr:full":"Helderse Duinen 54 Overloon North Brabant 5825 JM",
    "addr:housenumber":"54",
    "addr:postcode":"5825 jm",
    "addr:street":"Helderse Duinen",
    "iso:country":"NL",
    "sg:address":"Helderse Duinen 54",
    "sg:city":"Overloon",
    "sg:orig_category":"Glazenwasserijen",
    "sg:phone":"+31 478 640 036",
    "sg:postcode":"5825 JM",
    "sg:province":"North Brabant",
    "wof:name":"Glazenwasserij Overloon",
    "wof:placetype":"venue"
},
  "geometry": {"coordinates":[5.931714,51.564163],"type":"Point"}
}