{
  "type": "Feature",
  "properties": {
    "addr:full":"Zwynsbergen 51 Elst Ut Utrecht 3921 DW",
    "addr:housenumber":"51",
    "addr:postcode":"ut;3921 dw",
    "addr:street":"Zwynsbergen",
    "iso:country":"NL",
    "sg:address":"Zwynsbergen 51",
    "sg:city":"Elst Ut",
    "sg:orig_category":"Goudsmeden En Zilversmeden",
    "sg:phone":"+31 318 471 568",
    "sg:postcode":"3921 DW",
    "sg:province":"Utrecht",
    "wof:name":"Steilen, S Van Der",
    "wof:placetype":"venue"
},
  "geometry": {"coordinates":[5.500553,51.983845],"type":"Point"}
}