{
  "type": "Feature",
  "properties": {
    "iso:country":"NL",
    "sg:address":"Kruisweg 652",
    "sg:city":"Hoofddorp",
    "sg:orig_category":"Verzekeringen",
    "sg:phone":"+31 23 556 0016",
    "sg:postcode":"2132 CJ",
    "sg:province":"North Holland",
    "wof:name":"De Pensioendesk",
    "wof:placetype":"venue"
},
  "geometry": {"coordinates":[4.696118,52.303566],"type":"Point"}
}