{
  "type": "Feature",
  "properties": {
    "iso:country":"NL",
    "sg:address":"Waterwerk 70",
    "sg:city":"Rotterdam",
    "sg:orig_category":"Marktonderzoekbureaus",
    "sg:phone":"+31 10 452 3788",
    "sg:postcode":"3063 HB",
    "sg:province":"Zuid-Holland",
    "wof:name":"Coen Van Doorn / Strategie",
    "wof:placetype":"venue"
},
  "geometry": {"coordinates":[4.519663,51.913586],"type":"Point"}
}