{
  "type": "Feature",
  "properties": {
    "addr:full":"Tesselschadelaan 75A Muiderberg North Holland 1399 HX",
    "addr:housenumber":"75a",
    "addr:postcode":"1399 hx",
    "addr:street":"Tesselschadelaan",
    "iso:country":"NL",
    "sg:address":"Tesselschadelaan 75A",
    "sg:city":"Muiderberg",
    "sg:classifiers":[
        {
            "category":"Education",
            "subcategory":"Preschool",
            "type":"Public Place"
        }
    ],
    "sg:phone":"+31 294 261 828",
    "sg:postcode":"1399 HX",
    "sg:province":"North Holland",
    "sg:tags":[
        "kleuteronderwijs",
        "basis-"
    ],
    "wof:name":"Peuterspeelzaal De Krullevaar",
    "wof:placetype":"venue"
},
  "geometry": {"coordinates":[5.122873,52.324394],"type":"Point"}
}