{
  "type": "Feature",
  "properties": {
    "addr:full":"Elandsgr 101 Amsterdam North Holland 1016 TS",
    "addr:housenumber":"101",
    "addr:postcode":"1016 ts",
    "iso:country":"NL",
    "sg:address":"Elandsgr 101",
    "sg:city":"Amsterdam",
    "sg:orig_category":"Accountants - Administratie- Consulenten En -Kantoren",
    "sg:phone":"+31 20 625 7893",
    "sg:postcode":"1016 TS",
    "sg:province":"North Holland",
    "wof:name":"Thomas, B J",
    "wof:placetype":"venue"
},
  "geometry": {"coordinates":[4.879222,52.368958],"type":"Point"}
}