{
  "type": "Feature",
  "properties": {
    "addr:full":"De Oeverloper 433 Dronten NL. 8251 HS",
    "addr:housenumber":"433",
    "addr:postcode":"8251 hs",
    "addr:street":"De Oeverloper;Nl.",
    "iso:country":"NL",
    "sg:address":"De Oeverloper 433",
    "sg:city":"Dronten",
    "sg:orig_category":"Verenigingen En Stichtingen",
    "sg:phone":"+31 321 312 279",
    "sg:postcode":"8251 HS",
    "sg:province":"NL.",
    "wof:name":"Oosterlicht Zwolseloge",
    "wof:placetype":"venue"
},
  "geometry": {"coordinates":[5.729569,52.528885],"type":"Point"}
}