{
  "type": "Feature",
  "properties": {
    "addr:full":"J V Nassaustr 17 S Gravenhage Zuid-Holland 2596 BL",
    "addr:housenumber":"17;gravenhage",
    "addr:postcode":"2596 bl",
    "addr:street":"J;Nassaustr;S",
    "iso:country":"NL",
    "sg:address":"J V Nassaustr 17",
    "sg:city":"S Gravenhage",
    "sg:orig_category":"Kunsthandel",
    "sg:phone":"+31 70 328 0020",
    "sg:postcode":"2596 BL",
    "sg:province":"Zuid-Holland",
    "sg:website":"http://www.polak-gallery.nl",
    "wof:name":"Polak, Kunsthandel R",
    "wof:placetype":"venue"
},
  "geometry": {"coordinates":[4.31846,52.093311],"type":"Point"}
}