{
  "type": "Feature",
  "properties": {
    "addr:full":"Burgemeester Smeelelaan 21 Waalwijk North Brabant 5144 AP",
    "addr:housenumber":"21",
    "addr:postcode":"5144 ap",
    "addr:street":"Burgemeester Smeelelaan",
    "iso:country":"NL",
    "sg:address":"Burgemeester Smeelelaan 21",
    "sg:city":"Waalwijk",
    "sg:orig_category":"Meubelreparatie And -Restauratie",
    "sg:phone":"+31 416 339 865",
    "sg:postcode":"5144 AP",
    "sg:province":"North Brabant",
    "wof:name":"C.H.L. Schuurmans",
    "wof:placetype":"venue"
},
  "geometry": {"coordinates":[5.076189,51.684574],"type":"Point"}
}