{
  "type": "Feature",
  "properties": {
    "addr:full":"Albert Cuypstraat 128/1 Amsterdam North Holland 1072 EA",
    "addr:housenumber":"128 / 1",
    "addr:postcode":"1072 ea",
    "addr:street":"Albert Cuypstraat",
    "iso:country":"NL",
    "sg:address":"Albert Cuypstraat 128/1",
    "sg:city":"Amsterdam",
    "sg:orig_category":"Fotostudio'S And Fotografen",
    "sg:phone":"+31 20 671 2822",
    "sg:postcode":"1072 EA",
    "sg:province":"North Holland",
    "wof:name":"P. Van Roon",
    "wof:placetype":"venue"
},
  "geometry": {"coordinates":[4.893002,52.355412],"type":"Point"}
}