{
  "type": "Feature",
  "properties": {
    "addr:full":"Molenkade 45 Duivendrecht Noord-Holland 1115 AC",
    "addr:housenumber":"45",
    "addr:postcode":"1115 ac",
    "addr:street":"Molenkade",
    "iso:country":"NL",
    "sg:address":"Molenkade 45",
    "sg:city":"Duivendrecht",
    "sg:orig_category":"Wegen And Sportterreinen",
    "sg:phone":"+31 20 698 2231",
    "sg:postcode":"1115 AC",
    "sg:province":"Noord-Holland",
    "wof:name":"Koninklijke Wegenbouw Stevin Noord Holland Kws",
    "wof:placetype":"venue"
},
  "geometry": {"coordinates":[4.9500460625,52.3371810913],"type":"Point"}
}