{
  "type": "Feature",
  "properties": {
    "addr:full":"Westerstr 3 Amsterdam North Holland 1015 LT",
    "addr:housenumber":"3",
    "addr:postcode":"1015 lt",
    "addr:street":"Westerstr",
    "iso:country":"NL",
    "sg:address":"Westerstr 3",
    "sg:city":"Amsterdam",
    "sg:orig_category":"Meubelstoffen",
    "sg:phone":"+31 20 622 8561",
    "sg:postcode":"1015 LT",
    "sg:province":"North Holland",
    "sg:website":"http://www.hofstedestoffen.nl",
    "wof:name":"Hofstede, Interieurstoffen",
    "wof:placetype":"venue"
},
  "geometry": {"coordinates":[4.886176,52.37888],"type":"Point"}
}