{
  "type": "Feature",
  "properties": {
    "addr:full":"Westerkade 3 Rotterdam Zuid-Holland 3016 CL",
    "addr:housenumber":"3",
    "addr:postcode":"3016",
    "addr:street":"Westerkade",
    "iso:country":"NL",
    "sg:address":"Westerkade 3",
    "sg:city":"Rotterdam",
    "sg:orig_category":"Reclamebureaus",
    "sg:phone":"+31 10 241 2111",
    "sg:postcode":"3016 CL",
    "sg:province":"Zuid-Holland",
    "wof:name":"Via Reclame Adviesburo Bv",
    "wof:placetype":"venue"
},
  "geometry": {"coordinates":[4.478147,51.906532],"type":"Point"}
}