{
  "type": "Feature",
  "properties": {
    "iso:country":"NL",
    "sg:address":"Drijverslaan 2",
    "sg:city":"Bilthoven",
    "sg:orig_category":"Autorijscholen",
    "sg:phone":"+31 30 220 5007",
    "sg:postcode":"3721 CE",
    "sg:province":"Utrecht",
    "wof:name":"Smits, B A",
    "wof:placetype":"venue"
},
  "geometry": {"coordinates":[5.196724,52.124508],"type":"Point"}
}