{
  "type": "Feature",
  "properties": {
    "iso:country":"NL",
    "sg:address":"Kleine Noord 33",
    "sg:city":"Hoorn Nh",
    "sg:orig_category":"Kappers",
    "sg:phone":"+31 229 272 152",
    "sg:postcode":"1621 JE",
    "sg:province":"North Holland",
    "wof:name":"Kapsalon Emel",
    "wof:placetype":"venue"
},
  "geometry": {"coordinates":[5.0531592369,52.6431655884],"type":"Point"}
}