{
  "type": "Feature",
  "properties": {
    "addr:full":"Nieuwe Strwg 31 Giekerk Provincie Friesland 9061 CK",
    "addr:housenumber":"31",
    "addr:postcode":"9061 ck",
    "addr:street":"Nieuwe Strwg;Provincie Friesland",
    "iso:country":"NL",
    "sg:address":"Nieuwe Strwg 31",
    "sg:city":"Giekerk",
    "sg:orig_category":"Onderhoudswerken",
    "sg:phone":"+31 58 256 1117",
    "sg:postcode":"9061 CK",
    "sg:province":"Provincie Friesland",
    "wof:name":"Radomile, G",
    "wof:placetype":"venue"
},
  "geometry": {"coordinates":[5.891692,53.242096],"type":"Point"}
}