{
  "type": "Feature",
  "properties": {
    "addr:full":"Jonker 11 Spijk Gn Groningen 9909 CB",
    "addr:housenumber":"11",
    "addr:postcode":"gn;9909 cb",
    "addr:street":"Jonker",
    "iso:country":"NL",
    "sg:address":"Jonker 11",
    "sg:city":"Spijk Gn",
    "sg:orig_category":"Schilderwerk",
    "sg:phone":"+31 596 592 056",
    "sg:postcode":"9909 CB",
    "sg:province":"Groningen",
    "wof:name":"H. Pijper",
    "wof:placetype":"venue"
},
  "geometry": {"coordinates":[6.850264,53.406044],"type":"Point"}
}