{
  "type": "Feature",
  "properties": {
    "addr:full":"Mozartln 188 Enschede NL.08 7522 HS",
    "addr:housenumber":"188",
    "addr:postcode":"7522 hs",
    "iso:country":"NL",
    "sg:address":"Mozartln 188",
    "sg:city":"Enschede",
    "sg:orig_category":"Vertaalbureaus",
    "sg:phone":"+31 53 431 2657",
    "sg:postcode":"7522 HS",
    "sg:province":"NL.08",
    "wof:name":"Powell-Hobart",
    "wof:placetype":"venue"
},
  "geometry": {"coordinates":[6.85852,52.25145],"type":"Point"}
}