{
  "type": "Feature",
  "properties": {
    "addr:full":"Coolsngl 60D Rotterdam Zuid-Holland 3011 AE",
    "addr:housenumber":"60d",
    "addr:postcode":"3011 ae",
    "addr:street":"Coolsngl",
    "iso:country":"NL",
    "sg:address":"Coolsngl 60D",
    "sg:city":"Rotterdam",
    "sg:orig_category":"Herenkleding",
    "sg:phone":"+31 10 413 9176",
    "sg:postcode":"3011 AE",
    "sg:province":"Zuid-Holland",
    "wof:name":"Eduard Pelger Rotterdam",
    "wof:placetype":"venue"
},
  "geometry": {"coordinates":[4.478455,51.922836],"type":"Point"}
}