{
  "type": "Feature",
  "properties": {
    "addr:full":"Hilsestraat 47 Kaatsheuvel Noord-Brabant 5171 AA",
    "addr:housenumber":"47",
    "addr:postcode":"5171 aa",
    "addr:street":"Hilsestraat",
    "iso:country":"NL",
    "sg:address":"Hilsestraat 47",
    "sg:city":"Kaatsheuvel",
    "sg:orig_category":"Bloemen And Planten",
    "sg:phone":"+31 416 274 421",
    "sg:postcode":"5171 AA",
    "sg:province":"Noord-Brabant",
    "wof:name":"W.J. Haarbosch",
    "wof:placetype":"venue"
},
  "geometry": {"coordinates":[5.0273,51.656696],"type":"Point"}
}