{
  "type": "Feature",
  "properties": {
    "iso:country":"NL",
    "sg:address":"Yspolderwg 29",
    "sg:city":"Papendrecht",
    "sg:orig_category":"Onderhoudswerken",
    "sg:phone":"+31 78 615 3341",
    "sg:postcode":"3353 SM",
    "sg:province":"South Holland",
    "wof:name":"Multiklus",
    "wof:placetype":"venue"
},
  "geometry": {"coordinates":[4.688338,51.823631],"type":"Point"}
}