{
  "type": "Feature",
  "properties": {
    "addr:full":"Graafs Horneln 136N Weert Limburg 6004 HT",
    "addr:housenumber":"136n",
    "addr:postcode":"6004 ht",
    "addr:street":"Horneln",
    "iso:country":"NL",
    "sg:address":"Graafs Horneln 136N",
    "sg:city":"Weert",
    "sg:orig_category":"Oldtimers",
    "sg:phone":"+31 495 555 074",
    "sg:postcode":"6004 HT",
    "sg:province":"Limburg",
    "sg:website":"http://www.classico-italiano.nl",
    "wof:name":"Classico Italiano",
    "wof:placetype":"venue"
},
  "geometry": {"coordinates":[5.703781,51.255016],"type":"Point"}
}