{
  "type": "Feature",
  "properties": {
    "addr:full":"Hoekenrode 8 Amsterdam Zuidoost Noord-Holland 1102 BR",
    "addr:housenumber":"8",
    "addr:postcode":"zuidoost;1102 br",
    "addr:street":"Hoekenrode",
    "iso:country":"NL",
    "sg:address":"Hoekenrode 8",
    "sg:city":"Amsterdam Zuidoost",
    "sg:orig_category":"Banken",
    "sg:phone":"+31 20 565 5111",
    "sg:postcode":"1102 BR",
    "sg:province":"Noord-Holland",
    "sg:website":"http://www.postbank.nl",
    "wof:name":"Postbank Nv, (Zakelijke Markt)",
    "wof:placetype":"venue"
},
  "geometry": {"coordinates":[4.949827,52.312084],"type":"Point"}
}