{
  "type": "Feature",
  "properties": {
    "iso:country":"NL",
    "sg:address":"T De Boerstr 3",
    "sg:city":"Bakhuizen",
    "sg:orig_category":"Montagebedrijven",
    "sg:phone":"+31 514 582 163",
    "sg:postcode":"8574 SB",
    "sg:province":"Provincie Friesland",
    "wof:name":"Lente, Van",
    "wof:placetype":"venue"
},
  "geometry": {"coordinates":[5.460585,52.869709],"type":"Point"}
}