{
  "type": "Feature",
  "properties": {
    "addr:full":"Rijssenseweg 38 Markelo NL.08 7475 VB",
    "addr:housenumber":"38;nl.08",
    "addr:postcode":"7475 vb",
    "addr:street":"Rijssenseweg",
    "iso:country":"NL",
    "sg:address":"Rijssenseweg 38",
    "sg:city":"Markelo",
    "sg:orig_category":"Verhuur Catering-, Feest- En Evenementbenodigdheden",
    "sg:phone":"+31 548 514 190",
    "sg:postcode":"7475 VB",
    "sg:province":"NL.08",
    "wof:name":"Klebo Technics Bv",
    "wof:placetype":"venue"
},
  "geometry": {"coordinates":[6.535408,52.269009],"type":"Point"}
}