{
  "type": "Feature",
  "properties": {
    "addr:full":"Saturnusstr 59 S Gravenhage Zuid-Holland 2516 AE",
    "addr:housenumber":"59;gravenhage",
    "addr:postcode":"2516 ae",
    "addr:street":"Saturnusstr;S",
    "iso:country":"NL",
    "sg:address":"Saturnusstr 59",
    "sg:city":"S Gravenhage",
    "sg:orig_category":"Horecabenodigdheden",
    "sg:phone":"+31 70 385 9076",
    "sg:postcode":"2516 AE",
    "sg:province":"Zuid-Holland",
    "wof:name":"Krekogroep Bv",
    "wof:placetype":"venue"
},
  "geometry": {"coordinates":[4.33931,52.06786],"type":"Point"}
}