{
  "type": "Feature",
  "properties": {
    "addr:full":"Karveelstr 46 Alkmaar Noord-Holland 1826 EG",
    "addr:housenumber":"46",
    "addr:postcode":"1826 eg",
    "addr:street":"Karveelstr",
    "iso:country":"NL",
    "sg:address":"Karveelstr 46",
    "sg:city":"Alkmaar",
    "sg:orig_category":"Adviesbureaus Bedrijfsorganisatie",
    "sg:phone":"+31 72 564 3941",
    "sg:postcode":"1826 EG",
    "sg:province":"Noord-Holland",
    "wof:name":"Astrant Bv",
    "wof:placetype":"venue"
},
  "geometry": {"coordinates":[4.761086,52.657391],"type":"Point"}
}