{
  "type": "Feature",
  "properties": {
    "iso:country":"NL",
    "sg:address":"Bergweg 76",
    "sg:city":"Baars",
    "sg:orig_category":"Kampeerterreinen",
    "sg:phone":"+31 521 588 575",
    "sg:postcode":"8336 MC",
    "sg:province":"Overijssel",
    "wof:name":"Camping 'T Kappie Vof",
    "wof:placetype":"venue"
},
  "geometry": {"coordinates":[6.1057529449,52.8133201599],"type":"Point"}
}