{
  "type": "Feature",
  "properties": {
    "addr:full":"Nw Purmerwg 24 Amsterdam New York 1025 VS",
    "addr:housenumber":"24;1025",
    "addr:postcode":"vs",
    "iso:country":"NL",
    "sg:address":"Nw Purmerwg 24",
    "sg:city":"Amsterdam",
    "sg:orig_category":"Voetbalverenigingen",
    "sg:phone":"+31 20 637 0755",
    "sg:postcode":"1025 VS",
    "sg:province":"New York",
    "wof:name":"Dwv",
    "wof:placetype":"venue"
},
  "geometry": {"coordinates":[-74.287521,42.981632],"type":"Point"}
}