{
  "type": "Feature",
  "properties": {
    "addr:full":"Naarderstr 45 Hilversum Noord-Holland 1211 AJ",
    "addr:housenumber":"45",
    "addr:postcode":"1211 aj",
    "addr:street":"Naarderstr",
    "iso:country":"NL",
    "sg:address":"Naarderstr 45",
    "sg:city":"Hilversum",
    "sg:orig_category":"Meubelstoffering",
    "sg:phone":"+31 6 53535526",
    "sg:postcode":"1211 AJ",
    "sg:province":"Noord-Holland",
    "wof:name":"K & Zo",
    "wof:placetype":"venue"
},
  "geometry": {"coordinates":[5.176171,52.228313],"type":"Point"}
}