{
  "type": "Feature",
  "properties": {
    "addr:full":"Osloweg 124 Groningen Groningen 9723 BX",
    "addr:housenumber":"124",
    "addr:postcode":"9723 bx",
    "addr:street":"Osloweg",
    "iso:country":"NL",
    "sg:address":"Osloweg 124",
    "sg:city":"Groningen",
    "sg:orig_category":"Elektronische Bedrijfsinstallaties",
    "sg:phone":"+31 50 542 6666",
    "sg:postcode":"9723 BX",
    "sg:province":"Groningen",
    "wof:name":"Uniglas Bv",
    "wof:placetype":"venue"
},
  "geometry": {"coordinates":[6.606903,53.21759],"type":"Point"}
}