{
  "type": "Feature",
  "properties": {
    "addr:full":"Jan Vermeerstraat 26 Deurne Noord-Brabant 5753 BP",
    "addr:housenumber":"26",
    "addr:postcode":"5753 bp",
    "addr:street":"Jan Vermeerstraat",
    "iso:country":"NL",
    "sg:address":"Jan Vermeerstraat 26",
    "sg:city":"Deurne",
    "sg:orig_category":"Paramedische Behandelingen",
    "sg:phone":"+31 493 313 322",
    "sg:postcode":"5753 BP",
    "sg:province":"Noord-Brabant",
    "wof:name":"Logopedische Praktijk F. Otten-Van De Kerkhof",
    "wof:placetype":"venue"
},
  "geometry": {"coordinates":[5.79063,51.449879],"type":"Point"}
}