{
  "type": "Feature",
  "properties": {
    "addr:full":"Zwaanshals 337A Rotterdam South Holland 3035 KK",
    "addr:housenumber":"337a",
    "addr:postcode":"3035 kk",
    "addr:street":"Zwaanshals",
    "iso:country":"NL",
    "sg:address":"Zwaanshals 337A",
    "sg:city":"Rotterdam",
    "sg:orig_category":"Koffie- En Theehuizen",
    "sg:phone":"+31 10 465 3445",
    "sg:postcode":"3035 KK",
    "sg:province":"South Holland",
    "wof:name":"Baris",
    "wof:placetype":"venue"
},
  "geometry": {"coordinates":[4.485084,51.931892],"type":"Point"}
}