{
  "type": "Feature",
  "properties": {
    "iso:country":"NL",
    "sg:address":"Handelstr 27",
    "sg:city":"Hellevoetsluis",
    "sg:orig_category":"Medische Keuringen",
    "sg:phone":"+31 181 322 448",
    "sg:postcode":"3223 TH",
    "sg:province":"Zuid-Holland",
    "wof:name":"D E S C Bv",
    "wof:placetype":"venue"
},
  "geometry": {"coordinates":[4.156998,51.840683],"type":"Point"}
}