{
  "type": "Feature",
  "properties": {
    "addr:full":"Handelstr 27 Hellevoetsluis Zuid-Holland 3223 TH",
    "addr:housenumber":"27",
    "addr:postcode":"3223 th",
    "addr:street":"Handelstr",
    "iso:country":"NL",
    "sg:address":"Handelstr 27",
    "sg:city":"Hellevoetsluis",
    "sg:orig_category":"Medische Keuringen",
    "sg:phone":"+31 181 322 448",
    "sg:postcode":"3223 TH",
    "sg:province":"Zuid-Holland",
    "wof:name":"D E S C Bv",
    "wof:placetype":"venue"
},
  "geometry": {"coordinates":[4.156998,51.840683],"type":"Point"}
}