{
  "type": "Feature",
  "properties": {
    "iso:country":"NL",
    "sg:address":"Kerklaan 98",
    "sg:city":"Nieuwerkerk Ad Ijssel",
    "sg:orig_category":"Bloemen And Planten",
    "sg:phone":"+31 180 320 544",
    "sg:postcode":"2912 CL",
    "sg:province":"South Holland",
    "wof:name":"Vof Groene Vingers Nieuwerkerk Aan Den I",
    "wof:placetype":"venue"
},
  "geometry": {"coordinates":[4.606126,51.970112],"type":"Point"}
}