{
  "type": "Feature",
  "properties": {
    "addr:full":"Postbus 285 Goes Zeeland 4460 AR",
    "addr:housenumber":"285",
    "addr:postcode":"4460",
    "addr:street":"Postbus",
    "iso:country":"NL",
    "sg:address":"Postbus 285",
    "sg:city":"Goes",
    "sg:orig_category":"Gehandicapteninformatie",
    "sg:phone":"+31 113 246 502",
    "sg:postcode":"4460 AR",
    "sg:province":"Zeeland",
    "sg:website":"http://www.arduin.nl",
    "wof:name":"Arduin, Sticht",
    "wof:placetype":"venue"
},
  "geometry": {"coordinates":[-83.914169,39.768833],"type":"Point"}
}