{
  "type": "Feature",
  "properties": {
    "addr:full":"Elandsgracht 142 Amsterdam North Holland 1016 VC",
    "addr:housenumber":"142",
    "addr:postcode":"1016 vc",
    "addr:street":"Elandsgracht",
    "iso:country":"NL",
    "sg:address":"Elandsgracht 142",
    "sg:city":"Amsterdam",
    "sg:orig_category":"Opticiens",
    "sg:phone":"+31 20 623 9783",
    "sg:postcode":"1016 VC",
    "sg:province":"North Holland",
    "wof:name":"Vroom & Nobbe Speciaal Optiek",
    "wof:placetype":"venue"
},
  "geometry": {"coordinates":[4.8786802292,52.3691864014],"type":"Point"}
}