{
  "type": "Feature",
  "properties": {
    "iso:country":"NL",
    "sg:address":"Noorderhaven 25",
    "sg:city":"Groningen",
    "sg:orig_category":"Veilingen En Venduhuizen",
    "sg:phone":"+31 50 318 9725",
    "sg:postcode":"9712 VG",
    "sg:province":"Groningen",
    "wof:name":"Postma Veilinghuis, G",
    "wof:placetype":"venue"
},
  "geometry": {"coordinates":[6.55917,53.220631],"type":"Point"}
}