{
  "type": "Feature",
  "properties": {
    "addr:full":"Henseniuspln 9A Venray Limburg 5801 BB",
    "addr:housenumber":"9a",
    "addr:postcode":"5801 bb",
    "addr:street":"Henseniuspln",
    "iso:country":"NL",
    "sg:address":"Henseniuspln 9A",
    "sg:city":"Venray",
    "sg:orig_category":"Bloemen En Planten",
    "sg:phone":"+31 478 588 198",
    "sg:postcode":"5801 BB",
    "sg:province":"Limburg",
    "wof:name":"September",
    "wof:placetype":"venue"
},
  "geometry": {"coordinates":[5.973793,51.524521],"type":"Point"}
}