{
  "type": "Feature",
  "properties": {
    "addr:full":"Wertsteeg 29 Kerkdriel Gelderland 5331 PE",
    "addr:housenumber":"29",
    "addr:postcode":"5331 pe",
    "addr:street":"Wertsteeg;Gelderland",
    "iso:country":"NL",
    "sg:address":"Wertsteeg 29",
    "sg:city":"Kerkdriel",
    "sg:orig_category":"Groententeelt",
    "sg:phone":"+31 418 632 025",
    "sg:postcode":"5331 PE",
    "sg:province":"Gelderland",
    "wof:name":"Champignonkwekerij G. Baars Bv",
    "wof:placetype":"venue"
},
  "geometry": {"coordinates":[5.327964,51.760284],"type":"Point"}
}