{
  "type": "Feature",
  "properties": {
    "addr:full":"Egstr 66 Dordrecht Zuid-Holland 3319 LA",
    "addr:housenumber":"66",
    "addr:postcode":"3319 la",
    "addr:street":"Egstr",
    "iso:country":"NL",
    "sg:address":"Egstr 66",
    "sg:city":"Dordrecht",
    "sg:orig_category":"Hydraulische Apparaten En Installaties",
    "sg:phone":"+31 78 616 1133",
    "sg:postcode":"3319 LA",
    "sg:province":"Zuid-Holland",
    "wof:name":"Looman Olie Bv, Joost",
    "wof:placetype":"venue"
},
  "geometry": {"coordinates":[4.714885,51.79697],"type":"Point"}
}