{
  "type": "Feature",
  "properties": {
    "addr:full":"Prinses Beatrixlaan 4 Alphen A/D Rijn Zuid-Holland 2404 XC",
    "addr:housenumber":"4",
    "addr:postcode":"2404 xc",
    "addr:street":"Prinses Beatrixlaan",
    "iso:country":"NL",
    "sg:address":"Prinses Beatrixlaan 4",
    "sg:city":"Alphen A/D Rijn",
    "sg:orig_category":"Volwassenenonderwijs",
    "sg:phone":"+31 172 449 500",
    "sg:postcode":"2404 XC",
    "sg:province":"Zuid-Holland",
    "wof:name":"Chr Scholengemeenschap Groene Hart Lyceum",
    "wof:placetype":"venue"
},
  "geometry": {"coordinates":[4.651199,52.131165],"type":"Point"}
}