{
  "type": "Feature",
  "properties": {
    "iso:country":"NL",
    "sg:address":"Gravinnestraat 3",
    "sg:city":"Wageningen",
    "sg:orig_category":"Organisaties And Verenigingen",
    "sg:phone":"+31 317 421 158",
    "sg:postcode":"6707 EW",
    "sg:province":"Gelderland",
    "wof:name":"Nicolas Maillard Studentenverenigingen",
    "wof:placetype":"venue"
},
  "geometry": {"coordinates":[5.6667151451,51.9725723267],"type":"Point"}
}