{
  "type": "Feature",
  "properties": {
    "addr:full":"Koestr 26 Geertruidenberg Noord-Brabant 4931 CS",
    "addr:housenumber":"26",
    "addr:postcode":"4931 cs",
    "addr:street":"Koestr",
    "iso:country":"NL",
    "sg:address":"Koestr 26",
    "sg:city":"Geertruidenberg",
    "sg:orig_category":"Natuurvoeding En Reformartikelen",
    "sg:phone":"+31 162 515 623",
    "sg:postcode":"4931 CS",
    "sg:province":"Noord-Brabant",
    "sg:website":"http://www.shop-around-the-clock.nl",
    "wof:name":"E-Net-Commerce",
    "wof:placetype":"venue"
},
  "geometry": {"coordinates":[4.858335,51.701351],"type":"Point"}
}