{
  "type": "Feature",
  "properties": {
    "addr:full":"Sallandstr 12 Zwolle Overijssel 8012 XB",
    "addr:housenumber":"12",
    "addr:postcode":"8012 xb",
    "addr:street":"Sallandstr",
    "iso:country":"NL",
    "sg:address":"Sallandstr 12",
    "sg:city":"Zwolle",
    "sg:orig_category":"Grafisch Ontwerpers",
    "sg:phone":"+31 38 422 1813",
    "sg:postcode":"8012 XB",
    "sg:province":"Overijssel",
    "wof:name":"Brandie Oosterwold",
    "wof:placetype":"venue"
},
  "geometry": {"coordinates":[6.105675,52.50502],"type":"Point"}
}