{
  "type": "Feature",
  "properties": {
    "iso:country":"NL",
    "sg:address":"Holterswg 7",
    "sg:city":"Hengelo Ov",
    "sg:orig_category":"Verf En Lak - Fabrieken En Groothandel",
    "sg:phone":"+31 74 242 0044",
    "sg:postcode":"7556 BS",
    "sg:province":"Overijssel",
    "wof:name":"Sikkens Verkoop",
    "wof:placetype":"venue"
},
  "geometry": {"coordinates":[6.777378,52.278133],"type":"Point"}
}