{
  "type": "Feature",
  "properties": {
    "addr:full":"Holterswg 7 Hengelo Ov Overijssel 7556 BS",
    "addr:housenumber":"7",
    "addr:postcode":"7556 bs",
    "addr:street":"Holterswg;Ov",
    "iso:country":"NL",
    "sg:address":"Holterswg 7",
    "sg:city":"Hengelo Ov",
    "sg:orig_category":"Verf En Lak - Fabrieken En Groothandel",
    "sg:phone":"+31 74 242 0044",
    "sg:postcode":"7556 BS",
    "sg:province":"Overijssel",
    "wof:name":"Sikkens Verkoop",
    "wof:placetype":"venue"
},
  "geometry": {"coordinates":[6.777378,52.278133],"type":"Point"}
}