{
  "type": "Feature",
  "properties": {
    "addr:full":"Westblaak 196 Rotterdam Zuid-Holland 3012 KN",
    "addr:housenumber":"196",
    "addr:postcode":"3012 kn",
    "addr:street":"Westblaak",
    "iso:country":"NL",
    "sg:address":"Westblaak 196",
    "sg:city":"Rotterdam",
    "sg:orig_category":"Verzekeringen - Verzekeringskantoren",
    "sg:phone":"+31 10 401 8501",
    "sg:postcode":"3012 KN",
    "sg:province":"Zuid-Holland",
    "sg:website":"http://www.assurantien.com",
    "wof:name":"Kok Bv",
    "wof:placetype":"venue"
},
  "geometry": {"coordinates":[4.474988,51.916294],"type":"Point"}
}