{
  "type": "Feature",
  "properties": {
    "addr:full":"Visstraat 13 Zierikzee Zeeland 4301 CC",
    "addr:housenumber":"13",
    "addr:postcode":"4301 cc",
    "addr:street":"Visstraat",
    "iso:country":"NL",
    "sg:address":"Visstraat 13",
    "sg:city":"Zierikzee",
    "sg:orig_category":"Visspeciaalzaken",
    "sg:phone":"+31 111 413 296",
    "sg:postcode":"4301 CC",
    "sg:province":"Zeeland",
    "wof:name":"Saman Vis- En Palinghandel",
    "wof:placetype":"venue"
},
  "geometry": {"coordinates":[3.921078,51.648914],"type":"Point"}
}