{
  "type": "Feature",
  "properties": {
    "addr:full":"De Schelp 104 Zandvoort Noord-Holland 2042 DX",
    "addr:housenumber":"104",
    "addr:postcode":"zandvoort;2042 dx",
    "addr:street":"De Schelp",
    "iso:country":"NL",
    "sg:address":"De Schelp 104",
    "sg:city":"Zandvoort",
    "sg:orig_category":"Kunststoffen - Fabrieken En Groothandel",
    "sg:phone":"+31 23 571 2420",
    "sg:postcode":"2042 DX",
    "sg:province":"Noord-Holland",
    "wof:name":"Al Kunststoffen",
    "wof:placetype":"venue"
},
  "geometry": {"coordinates":[4.535972,52.36898],"type":"Point"}
}