{
  "type": "Feature",
  "properties": {
    "iso:country":"NL",
    "sg:address":"Van Diemenstraat 302",
    "sg:city":"Amsterdam",
    "sg:orig_category":"Diverse Grafische Activiteiten",
    "sg:phone":"+31 20 428 4777",
    "sg:postcode":"1013 CR",
    "sg:province":"Noord-Holland",
    "wof:name":"Def",
    "wof:placetype":"venue"
},
  "geometry": {"coordinates":[4.88708,52.390282],"type":"Point"}
}