{
  "type": "Feature",
  "properties": {
    "addr:full":"Spykerln 11 Arnhem Gelderland 6828 EB",
    "addr:housenumber":"11",
    "addr:postcode":"6828 eb",
    "addr:street":"Spykerln",
    "iso:country":"NL",
    "sg:address":"Spykerln 11",
    "sg:city":"Arnhem",
    "sg:orig_category":"Kappers",
    "sg:phone":"+31 26 351 9733",
    "sg:postcode":"6828 EB",
    "sg:province":"Gelderland",
    "wof:name":"Via Via",
    "wof:placetype":"venue"
},
  "geometry": {"coordinates":[5.92598,51.98053],"type":"Point"}
}