{
  "type": "Feature",
  "properties": {
    "addr:full":"Gruttostr 2 Rozenburg Zh Zuid-Holland 3181 TC",
    "addr:housenumber":"2",
    "addr:postcode":"zh;3181 tc",
    "addr:street":"Gruttostr",
    "iso:country":"NL",
    "sg:address":"Gruttostr 2",
    "sg:city":"Rozenburg Zh",
    "sg:orig_category":"Kinderopvang",
    "sg:phone":"+31 181 276 100",
    "sg:postcode":"3181 TC",
    "sg:province":"Zuid-Holland",
    "wof:name":"Doerak, Sticht",
    "wof:placetype":"venue"
},
  "geometry": {"coordinates":[4.237773,51.908604],"type":"Point"}
}