{
  "type": "Feature",
  "properties": {
    "addr:full":"Jansstr 41 Arnhem Gelderland 6811 GH",
    "addr:housenumber":"41",
    "addr:postcode":"6811 gh",
    "addr:street":"Jansstr",
    "iso:country":"NL",
    "sg:address":"Jansstr 41",
    "sg:city":"Arnhem",
    "sg:orig_category":"Kappers",
    "sg:phone":"+31 26 442 5043",
    "sg:postcode":"6811 GH",
    "sg:province":"Gelderland",
    "wof:name":"Welkom",
    "wof:placetype":"venue"
},
  "geometry": {"coordinates":[5.906206,51.98241],"type":"Point"}
}