{
  "type": "Feature",
  "properties": {
    "iso:country":"NL",
    "sg:address":"Amsterdamstr 15-17",
    "sg:city":"Haarlem",
    "sg:orig_category":"Boeken En Tijdschriften",
    "sg:phone":"+31 23 540 9366",
    "sg:postcode":"2032 PM",
    "sg:province":"Noord-Holland",
    "wof:name":"Bruna",
    "wof:placetype":"venue"
},
  "geometry": {"coordinates":[4.647415,52.380035],"type":"Point"}
}