{
  "type": "Feature",
  "properties": {
    "iso:country":"NL",
    "sg:address":"Herenstraat 4",
    "sg:city":"Rijswijk Zh",
    "sg:orig_category":"Biljart- And Snookerzalen",
    "sg:phone":"+31 70 399 6404",
    "sg:postcode":"2282 BT",
    "sg:province":"Zuid-Holland",
    "wof:name":"Cafebiljart Witsenburch",
    "wof:placetype":"venue"
},
  "geometry": {"coordinates":[4.337116,52.056625],"type":"Point"}
}