{
  "type": "Feature",
  "properties": {
    "addr:full":"Venraysewg 53A Venlo Limburg 5921 KJ",
    "addr:housenumber":"53a",
    "addr:postcode":"5921 kj",
    "addr:street":"Venraysewg",
    "iso:country":"NL",
    "sg:address":"Venraysewg 53A",
    "sg:city":"Venlo",
    "sg:orig_category":"Hypotheken",
    "sg:phone":"+31 800 1600",
    "sg:postcode":"5921 KJ",
    "sg:province":"Limburg",
    "sg:website":"http://www.vanbruggen.nl",
    "wof:name":"Bruggen Adviesgroep, Van",
    "wof:placetype":"venue"
},
  "geometry": {"coordinates":[6.151845,51.376129],"type":"Point"}
}