{
  "type": "Feature",
  "properties": {
    "addr:full":"Begynhofstr 28 Roermond Limburg 6041 GX",
    "addr:housenumber":"28",
    "addr:postcode":"6041 gx",
    "addr:street":"Begynhofstr",
    "iso:country":"NL",
    "sg:address":"Begynhofstr 28",
    "sg:city":"Roermond",
    "sg:orig_category":"Scholen Voor Algemeen Voortgezet Onderwijs",
    "sg:phone":"+31 475 347 347",
    "sg:postcode":"6041 GX",
    "sg:province":"Limburg",
    "wof:name":"Stedelijk Lyceum",
    "wof:placetype":"venue"
},
  "geometry": {"coordinates":[5.992392,51.194984],"type":"Point"}
}