{
  "type": "Feature",
  "properties": {
    "addr:full":"Oosterburen 45 Terschelling West Friesland 8891 GB",
    "addr:housenumber":"45",
    "addr:postcode":"8891 gb",
    "addr:street":"Oosterburen",
    "iso:country":"NL",
    "sg:address":"Oosterburen 45",
    "sg:city":"Terschelling West",
    "sg:orig_category":"Boekhandels",
    "sg:phone":"+31 562 448 971",
    "sg:postcode":"8891 GB",
    "sg:province":"Friesland",
    "wof:name":"Bruna",
    "wof:placetype":"venue"
},
  "geometry": {"coordinates":[5.288857,53.383423],"type":"Point"}
}