{
  "type": "Feature",
  "properties": {
    "iso:country":"NL",
    "sg:address":"Hoofdstr 16",
    "sg:city":"Oostwold Scheemda",
    "sg:orig_category":"Kegelbanen",
    "sg:phone":"+31 597 551 601",
    "sg:postcode":"9682 PK",
    "sg:province":"Groningen",
    "wof:name":"Jachthoorn, De",
    "wof:placetype":"venue"
},
  "geometry": {"coordinates":[7.044147,53.203705],"type":"Point"}
}