{
  "type": "Feature",
  "properties": {
    "addr:full":"J. Van Der Heydenstraat 7 Numansdorp Zuid-Holland 3281 NE",
    "addr:housenumber":"7;3281",
    "addr:postcode":"ne",
    "addr:street":"J. Van Der Heydenstraat",
    "iso:country":"NL",
    "sg:address":"J. Van Der Heydenstraat 7",
    "sg:city":"Numansdorp",
    "sg:orig_category":"Woningbouwverenigingen",
    "sg:phone":"+31 186 651 013",
    "sg:postcode":"3281 NE",
    "sg:province":"Zuid-Holland",
    "wof:name":"Woningstoffeerbedrijf J. Buitelaar",
    "wof:placetype":"venue"
},
  "geometry": {"coordinates":[4.448469162,51.7465324402],"type":"Point"}
}