{
  "type": "Feature",
  "properties": {
    "iso:country":"NL",
    "sg:address":"L Leidsedwstr 42",
    "sg:city":"Amsterdam",
    "sg:orig_category":"Vertalers",
    "sg:phone":"+31 20 320 2051",
    "sg:postcode":"1017 NL",
    "sg:province":"Noord-Holland",
    "sg:website":"http://www.sprachgitter.com",
    "wof:name":"Spachgitter",
    "wof:placetype":"venue"
},
  "geometry": {"coordinates":[4.886016,52.365845],"type":"Point"}
}