{
  "type": "Feature",
  "properties": {
    "addr:full":"Oudegr 108 Utrecht Utrecht 3511 AV",
    "addr:housenumber":"108",
    "addr:postcode":"3511 av",
    "iso:country":"NL",
    "sg:address":"Oudegr 108",
    "sg:city":"Utrecht",
    "sg:orig_category":"Werving En Selectie",
    "sg:phone":"+31 30 234 1454",
    "sg:postcode":"3511 AV",
    "sg:province":"Utrecht",
    "wof:name":"Facility Talents",
    "wof:placetype":"venue"
},
  "geometry": {"coordinates":[5.1154050827,52.0889320374],"type":"Point"}
}