{
  "type": "Feature",
  "properties": {
    "addr:full":"Ruyghwg 1 Den Helder Noord-Holland 1781 DA",
    "addr:housenumber":"1",
    "addr:postcode":"1781 da",
    "addr:street":"Ruyghwg",
    "iso:country":"NL",
    "sg:address":"Ruyghwg 1",
    "sg:city":"Den Helder",
    "sg:orig_category":"Bloemen En Planten",
    "sg:phone":"+31 223 612 104",
    "sg:postcode":"1781 DA",
    "sg:province":"Noord-Holland",
    "wof:name":"Amesfoort, Van",
    "wof:placetype":"venue"
},
  "geometry": {"coordinates":[4.763219,52.954151],"type":"Point"}
}