{
  "type": "Feature",
  "properties": {
    "addr:full":"Smaragdstoep 5 Assen Drenthe 9403 SE",
    "addr:housenumber":"5",
    "addr:postcode":"9403 se",
    "addr:street":"Smaragdstoep",
    "iso:country":"NL",
    "sg:address":"Smaragdstoep 5",
    "sg:city":"Assen",
    "sg:orig_category":"Kinderopvang Behalve Thuis",
    "sg:phone":"+31 592 373 919",
    "sg:postcode":"9403 SE",
    "sg:province":"Drenthe",
    "wof:name":"Kinderopvang De Kubus",
    "wof:placetype":"venue"
},
  "geometry": {"coordinates":[6.596535,53.016376],"type":"Point"}
}