{
  "type": "Feature",
  "properties": {
    "iso:country":"NL",
    "sg:address":"Electronwg 15",
    "sg:city":"Hoorn Nh",
    "sg:orig_category":"Verpakkingsbedrijven",
    "sg:phone":"+31 251 313 658",
    "sg:postcode":"1627 LB",
    "sg:province":"Noord-Holland",
    "wof:name":"Castricumpak Bv",
    "wof:placetype":"venue"
},
  "geometry": {"coordinates":[5.101347,52.643505],"type":"Point"}
}