{
  "type": "Feature",
  "properties": {
    "addr:full":"Koelmansstraat 77 Dalfsen Overijssel 7722 LW",
    "addr:housenumber":"77",
    "addr:postcode":"7722 lw",
    "addr:street":"Koelmansstraat",
    "iso:country":"NL",
    "sg:address":"Koelmansstraat 77",
    "sg:city":"Dalfsen",
    "sg:orig_category":"Landbouwmachines Gh",
    "sg:phone":"+31 529 401 276",
    "sg:postcode":"7722 LW",
    "sg:province":"Overijssel",
    "wof:name":"J Veldhuis",
    "wof:placetype":"venue"
},
  "geometry": {"coordinates":[6.200293,52.480904],"type":"Point"}
}