{
  "type": "Feature",
  "properties": {
    "addr:full":"Vd Giessenwg 30 Krimpen Ad Yssel Zuid-Holland 2921 LP",
    "addr:housenumber":"30",
    "addr:postcode":"2921 lp",
    "addr:street":"Krimpen",
    "iso:country":"NL",
    "sg:address":"Vd Giessenwg 30",
    "sg:city":"Krimpen Ad Yssel",
    "sg:orig_category":"Oldtimers",
    "sg:phone":"+31 180 552 147",
    "sg:postcode":"2921 LP",
    "sg:province":"Zuid-Holland",
    "sg:website":"http://www.xs4all.nl/~hk/",
    "wof:name":"Buijs Bv, D",
    "wof:placetype":"venue"
},
  "geometry": {"coordinates":[4.5731,51.909908],"type":"Point"}
}