{
  "type": "Feature",
  "properties": {
    "iso:country":"NL",
    "sg:address":"Jane Addamsstraat 35",
    "sg:city":"Hoofddorp",
    "sg:orig_category":"Autokeuringen",
    "sg:phone":"+31 23 561 1304",
    "sg:postcode":"2131 VR",
    "sg:province":"North Holland",
    "wof:name":"Collection Cars Bv",
    "wof:placetype":"venue"
},
  "geometry": {"coordinates":[4.673772,52.301929],"type":"Point"}
}