{
  "type": "Feature",
  "properties": {
    "addr:full":"Dr Schaepmanstr 9 Halfweg Nh Noord-Holland 1165 GP",
    "addr:housenumber":"9",
    "addr:postcode":"1165 gp",
    "iso:country":"NL",
    "sg:address":"Dr Schaepmanstr 9",
    "sg:city":"Halfweg Nh",
    "sg:orig_category":"Adviesbureaus",
    "sg:phone":"+31 20 497 0595",
    "sg:postcode":"1165 GP",
    "sg:province":"Noord-Holland",
    "wof:name":"Headline Bv",
    "wof:placetype":"venue"
},
  "geometry": {"coordinates":[4.75446,52.383404],"type":"Point"}
}