{
  "type": "Feature",
  "properties": {
    "addr:full":"De Genestetwg 16 Bloemendaal Noord-Holland 2061 VC",
    "addr:housenumber":"16",
    "addr:postcode":"2061 vc",
    "iso:country":"NL",
    "sg:address":"De Genestetwg 16",
    "sg:city":"Bloemendaal",
    "sg:orig_category":"Adviesbureaus Personeel",
    "sg:phone":"+31 23 526 5945",
    "sg:postcode":"2061 VC",
    "sg:province":"Noord-Holland",
    "wof:name":"Coaching Company",
    "wof:placetype":"venue"
},
  "geometry": {"coordinates":[4.620086,52.405254],"type":"Point"}
}