{
  "type": "Feature",
  "properties": {
    "iso:country":"NL",
    "sg:address":"L Nering 15",
    "sg:city":"Emmeloord",
    "sg:orig_category":"Schoenen",
    "sg:phone":"+31 527 612 282",
    "sg:postcode":"8302 EH",
    "sg:province":"Flevoland",
    "wof:name":"Bruin, C J",
    "wof:placetype":"venue"
},
  "geometry": {"coordinates":[5.754972,52.711357],"type":"Point"}
}