{
  "type": "Feature",
  "properties": {
    "addr:full":"Wagenstr 137 S Gravenhage Zuid-Holland 2512 AT",
    "addr:housenumber":"137;gravenhage",
    "addr:postcode":"2512",
    "addr:street":"S",
    "iso:country":"NL",
    "sg:address":"Wagenstr 137",
    "sg:city":"S Gravenhage",
    "sg:classifiers":[
        {
            "category":"Food & Beverages",
            "subcategory":"Bakery",
            "type":"Retail Goods"
        }
    ],
    "sg:phone":"+31 70 363 8807",
    "sg:postcode":"2512 AT",
    "sg:province":"Zuid-Holland",
    "sg:tags":[
        "brood",
        "en",
        "banket"
    ],
    "wof:name":"Brouwers, A",
    "wof:placetype":"venue"
},
  "geometry": {"coordinates":[4.30618,52.073212],"type":"Point"}
}