{
  "type": "Feature",
  "properties": {
    "addr:full":"Hub Dassenplein 1 Sittard Limburg 6131 LB",
    "addr:housenumber":"1",
    "addr:postcode":"6131 lb",
    "addr:street":"Hub Dassenplein",
    "iso:country":"NL",
    "sg:address":"Hub Dassenplein 1",
    "sg:city":"Sittard",
    "sg:orig_category":"Overheidsdiensten",
    "sg:phone":"+31 46 459 6666",
    "sg:postcode":"6131 LB",
    "sg:province":"Limburg",
    "wof:name":"Gemeente Sittard Geleen",
    "wof:placetype":"venue"
},
  "geometry": {"coordinates":[5.8682169914,50.9956588745],"type":"Point"}
}