{
  "type": "Feature",
  "properties": {
    "iso:country":"NL",
    "sg:address":"Pk Reeburg 28",
    "sg:city":"Vught",
    "sg:orig_category":"Kinderopvang",
    "sg:phone":"+31 73 657 9012",
    "sg:postcode":"5261 GC",
    "sg:province":"North Brabant",
    "wof:name":"Kasteeltje, 'T",
    "wof:placetype":"venue"
},
  "geometry": {"coordinates":[5.298247,51.653503],"type":"Point"}
}