{
  "type": "Feature",
  "properties": {
    "iso:country":"NL",
    "sg:address":"Snellingerdk 1",
    "sg:city":"Oosterwolde Fr",
    "sg:orig_category":"Verzekeringen - Verzekeringskantoren",
    "sg:phone":"+31 516 512 534",
    "sg:postcode":"8431 EH",
    "sg:province":"Friesland",
    "wof:name":"Brouwers",
    "wof:placetype":"venue"
},
  "geometry": {"coordinates":[6.291716,52.988529],"type":"Point"}
}