{
  "type": "Feature",
  "properties": {
    "addr:full":"Hinthamerstr 64 S Hertogenbosch Noord-Brabant 5211 MR",
    "addr:housenumber":"64",
    "addr:postcode":"5211 mr",
    "addr:street":"Hinthamerstr;S Hertogenbosch",
    "iso:country":"NL",
    "sg:address":"Hinthamerstr 64",
    "sg:city":"S Hertogenbosch",
    "sg:orig_category":"Kinderkleding",
    "sg:phone":"+31 73 613 6130",
    "sg:postcode":"5211 MR",
    "sg:province":"Noord-Brabant",
    "wof:name":"Ot & Sien",
    "wof:placetype":"venue"
},
  "geometry": {"coordinates":[5.307349,51.688965],"type":"Point"}
}