{
  "type": "Feature",
  "properties": {
    "addr:full":"Gedempte Nieuwesloot 16 Alkmaar North Holland 1811 KT",
    "addr:housenumber":"16",
    "addr:postcode":"1811 kt",
    "addr:street":"Gedempte Nieuwesloot",
    "iso:country":"NL",
    "sg:address":"Gedempte Nieuwesloot 16",
    "sg:city":"Alkmaar",
    "sg:orig_category":"Discountwinkels",
    "sg:phone":"+31 72 512 1860",
    "sg:postcode":"1811 KT",
    "sg:province":"North Holland",
    "wof:name":"Dumpstore B. Sietsma",
    "wof:placetype":"venue"
},
  "geometry": {"coordinates":[4.749158,52.632607],"type":"Point"}
}