{
  "type": "Feature",
  "properties": {
    "addr:full":"Overtuinen 13 Zuidhorn Groningen 9801 BR",
    "addr:housenumber":"13",
    "addr:postcode":"9801 br",
    "addr:street":"Overtuinen",
    "iso:country":"NL",
    "sg:address":"Overtuinen 13",
    "sg:city":"Zuidhorn",
    "sg:orig_category":"Schoenen",
    "sg:phone":"+31 594 500 630",
    "sg:postcode":"9801 BR",
    "sg:province":"Groningen",
    "wof:name":"Botermans",
    "wof:placetype":"venue"
},
  "geometry": {"coordinates":[6.408416,53.243782],"type":"Point"}
}