{
  "type": "Feature",
  "properties": {
    "addr:full":"Carnegiepln 2 Den Haag Zuid-Holland 2517 KJ",
    "addr:housenumber":"2",
    "addr:postcode":"2517 kj",
    "addr:street":"Carnegiepln",
    "iso:country":"NL",
    "sg:address":"Carnegiepln 2",
    "sg:city":"Den Haag",
    "sg:orig_category":"Postkantoren",
    "sg:phone":"+31 70 302 4145",
    "sg:postcode":"2517 KJ",
    "sg:province":"Zuid-Holland",
    "sg:website":"http://www.postkantoor.nl",
    "wof:name":"Postkantoor",
    "wof:placetype":"venue"
},
  "geometry": {"coordinates":[4.297372,52.087162],"type":"Point"}
}