{
  "type": "Feature",
  "properties": {
    "iso:country":"NL",
    "sg:address":"Pelikaanwg 18",
    "sg:city":"De Koog",
    "sg:classifiers":[
        {
            "category":"Travel",
            "subcategory":"Hotels & Motels",
            "type":"Entertainment"
        }
    ],
    "sg:phone":"+31 222 317 202",
    "sg:postcode":"1796 NR",
    "sg:province":"North Holland",
    "sg:website":"http://www.depelikaan.nl",
    "wof:name":"Pelikaan Texel, De",
    "wof:placetype":"venue"
},
  "geometry": {"coordinates":[4.764032,53.08147],"type":"Point"}
}