{
  "type": "Feature",
  "properties": {
    "iso:country":"NL",
    "sg:address":"Harderwykerwg 134A",
    "sg:city":"Ermelo",
    "sg:orig_category":"Boeken En Tijdschriften",
    "sg:phone":"+31 341 563 310",
    "sg:postcode":"3852 AH",
    "sg:province":"Gelderland",
    "wof:name":"Lezer, De",
    "wof:placetype":"venue"
},
  "geometry": {"coordinates":[5.629139,52.316708],"type":"Point"}
}