{
  "type": "Feature",
  "properties": {
    "addr:full":"Tramweg 4 Rossum Ov NL.08 7596 NA",
    "addr:housenumber":"4",
    "addr:postcode":"7596 na",
    "addr:street":"Tramweg;Ov",
    "iso:country":"NL",
    "sg:address":"Tramweg 4",
    "sg:city":"Rossum Ov",
    "sg:orig_category":"Overheidsdiensten",
    "sg:phone":"+31 541 625 550",
    "sg:postcode":"7596 NA",
    "sg:province":"NL.08",
    "wof:name":"Blokhut",
    "wof:placetype":"venue"
},
  "geometry": {"coordinates":[6.9362092018,52.343208313],"type":"Point"}
}