{
  "type": "Feature",
  "properties": {
    "iso:country":"NL",
    "sg:address":"Morsstr 10",
    "sg:city":"Leiden",
    "sg:orig_category":"Kappers",
    "sg:phone":"+31 71 514 3383",
    "sg:postcode":"2312 BM",
    "sg:province":"Zuid-Holland",
    "wof:name":"Heek, Ed Van",
    "wof:placetype":"venue"
},
  "geometry": {"coordinates":[4.4842500687,52.1617431641],"type":"Point"}
}