{
  "type": "Feature",
  "properties": {
    "iso:country":"NL",
    "sg:address":"S V Oyenln 2C",
    "sg:city":"Maarheeze",
    "sg:orig_category":"Kinderkleding",
    "sg:phone":"+31 495 594 610",
    "sg:postcode":"6026 CP",
    "sg:province":"Noord-Brabant",
    "wof:name":"Kunst & Kids",
    "wof:placetype":"venue"
},
  "geometry": {"coordinates":[5.615365,51.312126],"type":"Point"}
}