{
  "type": "Feature",
  "properties": {
    "addr:full":"Postbus 187 De Meern Utrecht 3454 ZK",
    "addr:housenumber":"187",
    "addr:postcode":"3454",
    "addr:street":"Postbus",
    "iso:country":"NL",
    "sg:address":"Postbus 187",
    "sg:city":"De Meern",
    "sg:orig_category":"Facilitaire Dienstverlening",
    "sg:phone":"+31 30 666 3642",
    "sg:postcode":"3454 ZK",
    "sg:province":"Utrecht",
    "wof:name":"Inter Steba",
    "wof:placetype":"venue"
},
  "geometry": {"coordinates":[5.03752,52.078983],"type":"Point"}
}