{
  "type": "Feature",
  "properties": {
    "addr:full":"Veelerveensterwg 109 Veelerveen Groningen 9566 PK",
    "addr:housenumber":"109",
    "addr:postcode":"9566 pk",
    "addr:street":"Veelerveen",
    "iso:country":"NL",
    "sg:address":"Veelerveensterwg 109",
    "sg:city":"Veelerveen",
    "sg:orig_category":"Peuterspeelzalen",
    "sg:phone":"+31 597 541 705",
    "sg:postcode":"9566 PK",
    "sg:province":"Groningen",
    "wof:name":"Peuterspeelzaal Veelerveen",
    "wof:placetype":"venue"
},
  "geometry": {"coordinates":[7.125837,53.056622],"type":"Point"}
}