{
  "type": "Feature",
  "properties": {
    "addr:full":"Walstr 2 , (Bij Sassenpoort) Zwolle Overijssel 8011 NT",
    "addr:housenumber":"2",
    "addr:postcode":"8011 nt",
    "addr:street":"Walstr;Overijssel",
    "iso:country":"NL",
    "sg:address":"Walstr 2 , (Bij Sassenpoort)",
    "sg:city":"Zwolle",
    "sg:orig_category":"Fietsen En Bromfietsen",
    "sg:phone":"+31 38 421 3203",
    "sg:postcode":"8011 NT",
    "sg:province":"Overijssel",
    "wof:name":"Bob Korpershoek Tweewielers",
    "wof:placetype":"venue"
},
  "geometry": {"coordinates":[6.049578,52.517258],"type":"Point"}
}