{
  "type": "Feature",
  "properties": {
    "addr:full":"Rijksstraatweg 205 Leersum Utrecht 3956 CM",
    "addr:housenumber":"205",
    "addr:postcode":"3956 cm",
    "addr:street":"Rijksstraatweg",
    "iso:country":"NL",
    "sg:address":"Rijksstraatweg 205",
    "sg:city":"Leersum",
    "sg:orig_category":"Diverse Grafische Activiteiten",
    "sg:phone":"+31 343 451 394",
    "sg:postcode":"3956 CM",
    "sg:province":"Utrecht",
    "wof:name":"Wcp Filmdruk Bv",
    "wof:placetype":"venue"
},
  "geometry": {"coordinates":[5.425999,52.012589],"type":"Point"}
}