{
  "type": "Feature",
  "properties": {
    "iso:country":"NL",
    "sg:address":"Volleringweg 2",
    "sg:city":"Waarland",
    "sg:orig_category":"Boekhouders",
    "sg:phone":"+31 226 422 202",
    "sg:postcode":"1738 BT",
    "sg:province":"North Holland",
    "wof:name":"G V M Houtenbos",
    "wof:placetype":"venue"
},
  "geometry": {"coordinates":[4.828252,52.727081],"type":"Point"}
}