{
  "type": "Feature",
  "properties": {
    "iso:country":"NL",
    "sg:address":"De Noord 21",
    "sg:city":"Weert",
    "sg:orig_category":"Plaatmateriaal",
    "sg:phone":"+31 495 551 866",
    "sg:postcode":"6001 DA",
    "sg:province":"Limburg",
    "sg:website":"http://www.wpi-panelen.nl",
    "wof:name":"Weerter Paneel Bv",
    "wof:placetype":"venue"
},
  "geometry": {"coordinates":[5.72827,51.263931],"type":"Point"}
}