{
  "type": "Feature",
  "properties": {
    "addr:full":"Gezandebaan 52 Heusden Gem Asten North Brabant 5725 TN",
    "addr:housenumber":"52",
    "addr:postcode":"5725",
    "addr:street":"Gezandebaan",
    "iso:country":"NL",
    "sg:address":"Gezandebaan 52",
    "sg:city":"Heusden Gem Asten",
    "sg:orig_category":"Hengelsportartikelen - Fabrieken En Groothandel",
    "sg:phone":"+31 493 560 253",
    "sg:postcode":"5725 TN",
    "sg:province":"North Brabant",
    "wof:name":"Pro Line",
    "wof:placetype":"venue"
},
  "geometry": {"coordinates":[5.774447,51.370907],"type":"Point"}
}