{
  "type": "Feature",
  "properties": {
    "addr:full":"Koningin Julianaweg 106 'S Gravenzande South Holland 2691 GG",
    "addr:housenumber":"106 '",
    "addr:postcode":"2691 gg",
    "addr:street":"Koningin Julianaweg",
    "iso:country":"NL",
    "sg:address":"Koningin Julianaweg 106",
    "sg:city":"'S Gravenzande",
    "sg:orig_category":"Werving And Selectie Van Tijdelijk Personeel And Uitzendkantoren",
    "sg:phone":"+31 174 421 882",
    "sg:postcode":"2691 GG",
    "sg:province":"South Holland",
    "wof:name":"Viawerk",
    "wof:placetype":"venue"
},
  "geometry": {"coordinates":[4.1723480225,52.0003700256],"type":"Point"}
}