{
  "type": "Feature",
  "properties": {
    "addr:full":"Saffier 42 Hoorn Nh North Holland 1625 RB",
    "addr:housenumber":"42",
    "addr:postcode":"1625 rb",
    "addr:street":"Saffier;Nh North",
    "iso:country":"NL",
    "sg:address":"Saffier 42",
    "sg:city":"Hoorn Nh",
    "sg:orig_category":"Boekhouders",
    "sg:phone":"+31 229 231 770",
    "sg:postcode":"1625 RB",
    "sg:province":"North Holland",
    "wof:name":"Boekhoud- En Belastingadviesbureau Herba",
    "wof:placetype":"venue"
},
  "geometry": {"coordinates":[5.065719,52.658001],"type":"Point"}
}