{
  "type": "Feature",
  "properties": {
    "addr:full":"Almeloseweg 69A Vriezenveen Overijssel 7671 RC",
    "addr:housenumber":"69a",
    "addr:postcode":"7671 rc",
    "addr:street":"Almeloseweg",
    "iso:country":"NL",
    "sg:address":"Almeloseweg 69A",
    "sg:city":"Vriezenveen",
    "sg:orig_category":"Bloemen And Planten",
    "sg:phone":"+31 546 566 161",
    "sg:postcode":"7671 RC",
    "sg:province":"Overijssel",
    "wof:name":"Tuincentrum Alco",
    "wof:placetype":"venue"
},
  "geometry": {"coordinates":[6.632965,52.405022],"type":"Point"}
}