{
  "type": "Feature",
  "properties": {
    "iso:country":"NL",
    "sg:address":"Burg Groenev D Katerstr 7",
    "sg:city":"Maasdam",
    "sg:orig_category":"Fotostudio'S And Fotografen",
    "sg:phone":"+31 78 676 3533",
    "sg:postcode":"3299 AA",
    "sg:province":"South Holland",
    "wof:name":"Multivision Photography",
    "wof:placetype":"venue"
},
  "geometry": {"coordinates":[4.552983,51.789246],"type":"Point"}
}