{
  "type": "Feature",
  "properties": {
    "addr:full":"Arena 174 S Hertogenbosch Noord-Brabant 5211 XT",
    "addr:housenumber":"174",
    "addr:postcode":"5211 xt",
    "addr:street":"Arena;S",
    "iso:country":"NL",
    "sg:address":"Arena 174",
    "sg:city":"S Hertogenbosch",
    "sg:classifiers":[
        {
            "category":"Government",
            "subcategory":"Post Office",
            "type":"Public Place"
        }
    ],
    "sg:phone":"+31 73 613 3382",
    "sg:postcode":"5211 XT",
    "sg:province":"Noord-Brabant",
    "sg:tags":[
        "poster"
    ],
    "wof:name":"Expo",
    "wof:placetype":"venue"
},
  "geometry": {"coordinates":[5.3038,51.690269],"type":"Point"}
}