{
  "type": "Feature",
  "properties": {
    "iso:country":"NL",
    "sg:address":"Europaln 65-67",
    "sg:city":"Bladel",
    "sg:orig_category":"Discotheken",
    "sg:phone":"+31 497 387 509",
    "sg:postcode":"5531 BE",
    "sg:province":"North Brabant",
    "wof:name":"Ambiani",
    "wof:placetype":"venue"
},
  "geometry": {"coordinates":[5.21485,51.366089],"type":"Point"}
}