{
  "type": "Feature",
  "properties": {
    "addr:full":"Ravelijnstraat 1 Hellevoetsluis Zuid-Holland 3221 XP",
    "addr:housenumber":"1",
    "addr:postcode":"3221 xp",
    "addr:street":"Ravelijnstraat",
    "iso:country":"NL",
    "sg:address":"Ravelijnstraat 1",
    "sg:city":"Hellevoetsluis",
    "sg:orig_category":"Makelaars In Onroerend Goed",
    "sg:phone":"+31 181 318 133",
    "sg:postcode":"3221 XP",
    "sg:province":"Zuid-Holland",
    "wof:name":"Voogt Assurantie & Makelaardij Bv",
    "wof:placetype":"venue"
},
  "geometry": {"coordinates":[4.135607,51.827129],"type":"Point"}
}