{
  "type": "Feature",
  "properties": {
    "addr:full":"Nw Achtergr 67 Amsterdam Noord-Holland 1018 WL",
    "addr:housenumber":"67",
    "addr:postcode":"1018 wl",
    "iso:country":"NL",
    "sg:address":"Nw Achtergr 67",
    "sg:city":"Amsterdam",
    "sg:classifiers":[
        {
            "category":"Travel",
            "subcategory":"Hotels & Motels",
            "type":"Entertainment"
        }
    ],
    "sg:phone":"+31 20 625 7238",
    "sg:postcode":"1018 WL",
    "sg:province":"Noord-Holland",
    "wof:name":"Canal Apartments",
    "wof:placetype":"venue"
},
  "geometry": {"coordinates":[4.908137,52.362858],"type":"Point"}
}