{
  "type": "Feature",
  "properties": {
    "addr:full":"Oudedijk 2 Odiliapeel Noord-Brabant 5409 AC",
    "addr:housenumber":"2",
    "addr:postcode":"5409 ac",
    "addr:street":"Oudedijk",
    "iso:country":"NL",
    "sg:address":"Oudedijk 2",
    "sg:city":"Odiliapeel",
    "sg:orig_category":"Bloemen And Planten",
    "sg:phone":"+31 413 272 653",
    "sg:postcode":"5409 AC",
    "sg:province":"Noord-Brabant",
    "wof:name":"Tuincentrum De Zwaan Vof",
    "wof:placetype":"venue"
},
  "geometry": {"coordinates":[5.694593,51.646172],"type":"Point"}
}