{
  "type": "Feature",
  "properties": {
    "iso:country":"NL",
    "sg:address":"Breguetln 10",
    "sg:city":"Oude Meer",
    "sg:orig_category":"Kantoor- En Bedrijfsmeubelen",
    "sg:phone":"+31 20 653 0390",
    "sg:postcode":"1438 BC",
    "sg:province":"British Columbia",
    "sg:website":"http://www.horas.be",
    "wof:name":"Office Pavilion Benelux, Herman Miller",
    "wof:placetype":"venue"
},
  "geometry": {"coordinates":[-126.5555114746,54.4856681824],"type":"Point"}
}