{
  "type": "Feature",
  "properties": {
    "addr:full":"Badhoevelaan 12 Badhoevedorp North Holland 1171 DD",
    "addr:housenumber":"12",
    "addr:postcode":"1171 dd",
    "addr:street":"Badhoevelaan",
    "iso:country":"NL",
    "sg:address":"Badhoevelaan 12",
    "sg:city":"Badhoevedorp",
    "sg:orig_category":"Kappers",
    "sg:phone":"+31 20 659 2343",
    "sg:postcode":"1171 DD",
    "sg:province":"North Holland",
    "wof:name":"Kapsalon Carla",
    "wof:placetype":"venue"
},
  "geometry": {"coordinates":[4.7897019386,52.3409805298],"type":"Point"}
}