{
  "type": "Feature",
  "properties": {
    "addr:full":"Voorstr 27 Woudenberg Utrecht 3931 HB",
    "addr:housenumber":"27",
    "addr:postcode":"3931 hb",
    "addr:street":"Voorstr",
    "iso:country":"NL",
    "sg:address":"Voorstr 27",
    "sg:city":"Woudenberg",
    "sg:orig_category":"Banket",
    "sg:phone":"+31 33 286 1352",
    "sg:postcode":"3931 HB",
    "sg:province":"Utrecht",
    "wof:name":"Pol, Bakkerij Jan Van Den",
    "wof:placetype":"venue"
},
  "geometry": {"coordinates":[5.412344,52.082371],"type":"Point"}
}