{
  "type": "Feature",
  "properties": {
    "iso:country":"NL",
    "sg:address":"Anninksweg 4",
    "sg:city":"Hengelo Ov",
    "sg:orig_category":"Bloemen And Planten",
    "sg:phone":"+31 74 243 6161",
    "sg:postcode":"7557 AG",
    "sg:province":"Overijssel",
    "wof:name":"Fleur 2000",
    "wof:placetype":"venue"
},
  "geometry": {"coordinates":[6.801106,52.264973],"type":"Point"}
}