{
  "type": "Feature",
  "properties": {
    "addr:full":"Grotel 4 Bakel Noord-Brabant 5761 RA",
    "addr:housenumber":"4",
    "addr:postcode":"5761 ra",
    "addr:street":"Grotel",
    "iso:country":"NL",
    "sg:address":"Grotel 4",
    "sg:city":"Bakel",
    "sg:orig_category":"Natuurvoeding En Reformartikelen - Fabrieken En Groothandel",
    "sg:phone":"+31 492 464 826",
    "sg:postcode":"5761 RA",
    "sg:province":"Noord-Brabant",
    "wof:name":"Jonkers, Ank",
    "wof:placetype":"venue"
},
  "geometry": {"coordinates":[5.691664,51.520828],"type":"Point"}
}