{
  "type": "Feature",
  "properties": {
    "addr:full":"Bosrand 102 Geldrop Noord-Brabant 5665 ES",
    "addr:housenumber":"102",
    "addr:postcode":"5665 es",
    "addr:street":"Bosrand",
    "iso:country":"NL",
    "sg:address":"Bosrand 102",
    "sg:city":"Geldrop",
    "sg:orig_category":"Verenigingen En Stichtingen",
    "sg:phone":"+31 40 285 0148",
    "sg:postcode":"5665 ES",
    "sg:province":"Noord-Brabant",
    "wof:name":"Ned Jeugdbond V Natuurstudie",
    "wof:placetype":"venue"
},
  "geometry": {"coordinates":[5.577658,51.416229],"type":"Point"}
}