{
  "type": "Feature",
  "properties": {
    "addr:full":"Sint Cornelisstraat 44 Vortum Mullem Noord-Brabant 5827 AM",
    "addr:housenumber":"44",
    "addr:postcode":"5827",
    "addr:street":"Sint Cornelisstraat",
    "iso:country":"NL",
    "sg:address":"Sint Cornelisstraat 44",
    "sg:city":"Vortum Mullem",
    "sg:orig_category":"Autokeuringen",
    "sg:phone":"+31 485 520 556",
    "sg:postcode":"5827 AM",
    "sg:province":"Noord-Brabant",
    "wof:name":"Hennie Lamers",
    "wof:placetype":"venue"
},
  "geometry": {"coordinates":[5.9731,51.617676],"type":"Point"}
}