{
  "type": "Feature",
  "properties": {
    "addr:full":"Troubadourln 250 Hoogvliet Rt South Holland 3194 HL",
    "addr:housenumber":"250",
    "addr:postcode":"3194 hl",
    "addr:street":"Rt South",
    "iso:country":"NL",
    "sg:address":"Troubadourln 250",
    "sg:city":"Hoogvliet Rt",
    "sg:orig_category":"Peuterspeelzalen",
    "sg:phone":"+31 10 416 2635",
    "sg:postcode":"3194 HL",
    "sg:province":"South Holland",
    "wof:name":"Blokkendoos, De",
    "wof:placetype":"venue"
},
  "geometry": {"coordinates":[4.359904,51.869682],"type":"Point"}
}