{
  "type": "Feature",
  "properties": {
    "addr:full":"Vivaldistr 7 Lisse Zuid-Holland 2162 AA",
    "addr:housenumber":"7",
    "addr:postcode":"2162 aa",
    "addr:street":"Vivaldistr",
    "iso:country":"NL",
    "sg:address":"Vivaldistr 7",
    "sg:city":"Lisse",
    "sg:classifiers":[
        {
            "category":"Food & Beverages",
            "subcategory":"Bakery",
            "type":"Retail Goods"
        }
    ],
    "sg:phone":"+31 252 415 324",
    "sg:postcode":"2162 AA",
    "sg:province":"Zuid-Holland",
    "sg:tags":[
        "brood",
        "en",
        "banket"
    ],
    "wof:name":"Rhijnsburger",
    "wof:placetype":"venue"
},
  "geometry": {"coordinates":[4.561126,52.249325],"type":"Point"}
}