{
  "type": "Feature",
  "properties": {
    "addr:full":"Lies 8 Terschelling Lies Friesland 8895 KT",
    "addr:housenumber":"8",
    "addr:postcode":"8895 kt",
    "addr:street":"Lies",
    "iso:country":"NL",
    "sg:address":"Lies 8",
    "sg:city":"Terschelling Lies",
    "sg:orig_category":"Fietsen En Bromfietsen Verhuur",
    "sg:phone":"+31 562 448 442",
    "sg:postcode":"8895 KT",
    "sg:province":"Friesland",
    "wof:name":"Bakker",
    "wof:placetype":"venue"
},
  "geometry": {"coordinates":[5.323672,53.393333],"type":"Point"}
}