{
  "type": "Feature",
  "properties": {
    "iso:country":"NL",
    "sg:address":"Enschedepad 101",
    "sg:city":"Almere",
    "sg:orig_category":"Verzekeringen - Verzekeringskantoren",
    "sg:phone":"+31 36 530 3967",
    "sg:postcode":"1324 GE",
    "sg:province":"NL.",
    "wof:name":"Hoorn Vof, Van",
    "wof:placetype":"venue"
},
  "geometry": {"coordinates":[5.210819,52.366627],"type":"Point"}
}