{
  "type": "Feature",
  "properties": {
    "iso:country":"NL",
    "sg:address":"Stationsstr 12-16",
    "sg:city":"Zelhem",
    "sg:orig_category":"Postkantoren",
    "sg:phone":"+31 314 621 230",
    "sg:postcode":"7021 CK",
    "sg:province":"Gelderland",
    "sg:website":"http://www.postkantoor.nl",
    "wof:name":"Postkantoor",
    "wof:placetype":"venue"
},
  "geometry": {"coordinates":[6.350054,52.005951],"type":"Point"}
}