{
  "type": "Feature",
  "properties": {
    "addr:full":"Oudemanhuispoort 1 Amsterdam Noord-Holland 1012 CN",
    "addr:housenumber":"1",
    "addr:postcode":"1012 cn",
    "addr:street":"Oudemanhuispoort",
    "iso:country":"NL",
    "sg:address":"Oudemanhuispoort 1",
    "sg:city":"Amsterdam",
    "sg:orig_category":"Fotografie Reclame En Mode",
    "sg:phone":"+31 20 624 8017",
    "sg:postcode":"1012 CN",
    "sg:province":"Noord-Holland",
    "wof:name":"Photo Graphic Design",
    "wof:placetype":"venue"
},
  "geometry": {"coordinates":[-94.605186,38.381996],"type":"Point"}
}