{
  "type": "Feature",
  "properties": {
    "addr:full":"Kerkstr 52/C Veendam Groningen 9641 AT",
    "addr:housenumber":"52 / c",
    "addr:postcode":"9641",
    "addr:street":"Kerkstr",
    "iso:country":"NL",
    "sg:address":"Kerkstr 52/C",
    "sg:city":"Veendam",
    "sg:orig_category":"Bijouterie?n",
    "sg:phone":"+31 598 616 942",
    "sg:postcode":"9641 AT",
    "sg:province":"Groningen",
    "wof:name":"Le Byou",
    "wof:placetype":"venue"
},
  "geometry": {"coordinates":[6.876348,53.106167],"type":"Point"}
}