{
  "type": "Feature",
  "properties": {
    "addr:full":"Spinmeesterstr 5 Tilburg Noord-Brabant 5046 TG",
    "addr:housenumber":"5",
    "addr:postcode":"5046 tg",
    "addr:street":"Spinmeesterstr",
    "iso:country":"NL",
    "sg:address":"Spinmeesterstr 5",
    "sg:city":"Tilburg",
    "sg:orig_category":"Ventilatiesystemen",
    "sg:phone":"+31 13 535 8011",
    "sg:postcode":"5046 TG",
    "sg:province":"Noord-Brabant",
    "wof:name":"T & D",
    "wof:placetype":"venue"
},
  "geometry": {"coordinates":[5.071997,51.574955],"type":"Point"}
}