{
  "type": "Feature",
  "properties": {
    "addr:full":"Luitenant Klopwg 19 Venlo Limburg 5916 LC",
    "addr:housenumber":"19",
    "addr:postcode":"5916 lc",
    "addr:street":"Luitenant Klopwg",
    "iso:country":"NL",
    "sg:address":"Luitenant Klopwg 19",
    "sg:city":"Venlo",
    "sg:orig_category":"Organisatiebureaus",
    "sg:phone":"+31 77 354 8393",
    "sg:postcode":"5916 LC",
    "sg:province":"Limburg",
    "wof:name":"Pm3 Bv",
    "wof:placetype":"venue"
},
  "geometry": {"coordinates":[6.2101979256,51.3820495605],"type":"Point"}
}