{
  "type": "Feature",
  "properties": {
    "addr:full":"Terworm 72 Haarlem Noord-Holland 2036 CR",
    "addr:housenumber":"72",
    "addr:postcode":"2036 cr",
    "addr:street":"Terworm",
    "iso:country":"NL",
    "sg:address":"Terworm 72",
    "sg:city":"Haarlem",
    "sg:orig_category":"Verhuur",
    "sg:phone":"+31 23 533 0395",
    "sg:postcode":"2036 CR",
    "sg:province":"Noord-Holland",
    "wof:name":"Nso",
    "wof:placetype":"venue"
},
  "geometry": {"coordinates":[4.659818,52.349743],"type":"Point"}
}