{
  "type": "Feature",
  "properties": {
    "addr:full":"De Corantyn 39F Zwaag Noord-Holland 1689 AN",
    "addr:housenumber":"39f",
    "addr:postcode":"1689 an",
    "iso:country":"NL",
    "sg:address":"De Corantyn 39F",
    "sg:city":"Zwaag",
    "sg:orig_category":"Meubelstoffering",
    "sg:phone":"+31 72 502 2896",
    "sg:postcode":"1689 AN",
    "sg:province":"Noord-Holland",
    "wof:name":"Schaft & Vanans",
    "wof:placetype":"venue"
},
  "geometry": {"coordinates":[5.070436,52.671902],"type":"Point"}
}