{
  "type": "Feature",
  "properties": {
    "addr:full":"V W Poelmanstr 17 Heerlen Limburg 6417 EJ",
    "addr:housenumber":"17",
    "addr:postcode":"6417 ej",
    "iso:country":"NL",
    "sg:address":"V W Poelmanstr 17",
    "sg:city":"Heerlen",
    "sg:orig_category":"Wassalons",
    "sg:phone":"+31 45 541 3311",
    "sg:postcode":"6417 EJ",
    "sg:province":"Limburg",
    "wof:name":"Gijsbers",
    "wof:placetype":"venue"
},
  "geometry": {"coordinates":[5.9809799194,50.8855056763],"type":"Point"}
}