{
  "type": "Feature",
  "properties": {
    "addr:full":"Janspoort 2 Arnhem Gelderland 6811 GE",
    "addr:housenumber":"2",
    "addr:postcode":"6811",
    "addr:street":"Janspoort",
    "iso:country":"NL",
    "sg:address":"Janspoort 2",
    "sg:city":"Arnhem",
    "sg:orig_category":"Ministeries En Overheidsinstellingen",
    "sg:phone":"+31 26 355 7111",
    "sg:postcode":"6811 GE",
    "sg:province":"Gelderland",
    "wof:name":"Arbeidsinspectie Regio Oost",
    "wof:placetype":"venue"
},
  "geometry": {"coordinates":[5.90719,51.98315],"type":"Point"}
}