{
  "type": "Feature",
  "properties": {
    "addr:full":"Bevrijdingsweg 99 Venlo Limburg 5915 PJ",
    "addr:housenumber":"99",
    "addr:postcode":"5915 pj",
    "addr:street":"Bevrijdingsweg",
    "iso:country":"NL",
    "sg:address":"Bevrijdingsweg 99",
    "sg:city":"Venlo",
    "sg:orig_category":"Goederenvervoer Over De Weg",
    "sg:phone":"+31 77 354 4488",
    "sg:postcode":"5915 PJ",
    "sg:province":"Limburg",
    "wof:name":"Van Zwamen Bv",
    "wof:placetype":"venue"
},
  "geometry": {"coordinates":[6.190372,51.342274],"type":"Point"}
}