{
  "type": "Feature",
  "properties": {
    "iso:country":"NL",
    "sg:address":"Duinweg 38",
    "sg:city":"Schoorl",
    "sg:orig_category":"Artsen And Specialisten",
    "sg:phone":"+31 72 509 3336",
    "sg:postcode":"1871 AG",
    "sg:province":"Noord-Holland",
    "wof:name":"J.J.M. V.D. Heijden",
    "wof:placetype":"venue"
},
  "geometry": {"coordinates":[4.700871,52.690151],"type":"Point"}
}