{
  "type": "Feature",
  "properties": {
    "addr:full":"V Duivenvoordeln 2 Geertruidenberg North Brabant 4931 HS",
    "addr:housenumber":"2",
    "addr:postcode":"4931 hs",
    "addr:street":"V Duivenvoordeln",
    "iso:country":"NL",
    "sg:address":"V Duivenvoordeln 2",
    "sg:city":"Geertruidenberg",
    "sg:orig_category":"Bejaarden - Verzorgingstehuizen",
    "sg:phone":"+31 162 513 555",
    "sg:postcode":"4931 HS",
    "sg:province":"North Brabant",
    "wof:name":"Riethorst, De",
    "wof:placetype":"venue"
},
  "geometry": {"coordinates":[4.848223,51.702312],"type":"Point"}
}