{
  "type": "Feature",
  "properties": {
    "addr:full":"Soetendaalln 20 Utrecht Utrecht 3554 HS",
    "addr:housenumber":"20",
    "addr:postcode":"3554 hs",
    "addr:street":"Soetendaalln",
    "iso:country":"NL",
    "sg:address":"Soetendaalln 20",
    "sg:city":"Utrecht",
    "sg:orig_category":"Fotoreportages",
    "sg:phone":"+31 6 50602136",
    "sg:postcode":"3554 HS",
    "sg:province":"Utrecht",
    "wof:name":"Alofs, Gerian",
    "wof:placetype":"venue"
},
  "geometry": {"coordinates":[5.09225,52.112808],"type":"Point"}
}