{
  "type": "Feature",
  "properties": {
    "addr:full":"Loowg 47B Bathmen NL.08 7437 RP",
    "addr:housenumber":"47b;nl.08",
    "addr:postcode":"7437",
    "addr:street":"Loowg",
    "iso:country":"NL",
    "sg:address":"Loowg 47B",
    "sg:city":"Bathmen",
    "sg:orig_category":"Kermisexploitatie",
    "sg:phone":"+31 570 543 070",
    "sg:postcode":"7437 RP",
    "sg:province":"NL.08",
    "wof:name":"Souilljee-Dauphin, M C P",
    "wof:placetype":"venue"
},
  "geometry": {"coordinates":[6.33772,52.253151],"type":"Point"}
}