{
  "type": "Feature",
  "properties": {
    "addr:full":"Hoogstr 21 Nieuwpoort South Holland 2965 AJ",
    "addr:housenumber":"21",
    "addr:postcode":"2965 aj",
    "addr:street":"Hoogstr",
    "iso:country":"NL",
    "sg:address":"Hoogstr 21",
    "sg:city":"Nieuwpoort",
    "sg:orig_category":"Bloemen En Planten",
    "sg:phone":"+31 184 602 645",
    "sg:postcode":"2965 AJ",
    "sg:province":"South Holland",
    "wof:name":"Korenschoof, De",
    "wof:placetype":"venue"
},
  "geometry": {"coordinates":[4.8703,51.935169],"type":"Point"}
}