{
  "type": "Feature",
  "properties": {
    "addr:full":"Drakenburgerweg 51 Baarn Utrecht 3741 GK",
    "addr:housenumber":"51",
    "addr:postcode":"3741 gk",
    "addr:street":"Drakenburgerweg",
    "iso:country":"NL",
    "sg:address":"Drakenburgerweg 51",
    "sg:city":"Baarn",
    "sg:orig_category":"Fotostudio'S And Fotografen",
    "sg:phone":"+31 35 541 4530",
    "sg:postcode":"3741 GK",
    "sg:province":"Utrecht",
    "wof:name":"Arnold Meine Jansen",
    "wof:placetype":"venue"
},
  "geometry": {"coordinates":[5.273447,52.221737],"type":"Point"}
}