{
  "type": "Feature",
  "properties": {
    "addr:full":"Helenaveenseweg 13 Grashoek Limburg 5985 NK",
    "addr:housenumber":"13",
    "addr:postcode":"5985 nk",
    "addr:street":"Helenaveenseweg",
    "iso:country":"NL",
    "sg:address":"Helenaveenseweg 13",
    "sg:city":"Grashoek",
    "sg:orig_category":"Landbouwmachines Gh",
    "sg:phone":"+31 77 307 2070",
    "sg:postcode":"5985 NK",
    "sg:province":"Limburg",
    "wof:name":"Maessen Import En Handel Bv",
    "wof:placetype":"venue"
},
  "geometry": {"coordinates":[5.938511,51.363506],"type":"Point"}
}