{
  "type": "Feature",
  "properties": {
    "addr:full":"Moorselaar 24 Nykerk Gld Gelderland 3862 VA",
    "addr:housenumber":"24",
    "addr:postcode":"3862",
    "addr:street":"Moorselaar;Gld Gelderland",
    "iso:country":"NL",
    "sg:address":"Moorselaar 24",
    "sg:city":"Nykerk Gld",
    "sg:orig_category":"Projectontwikkeling",
    "sg:phone":"+31 33 246 0324",
    "sg:postcode":"3862 VA",
    "sg:province":"Gelderland",
    "wof:name":"Anva",
    "wof:placetype":"venue"
},
  "geometry": {"coordinates":[5.51415,52.21376],"type":"Point"}
}