{
  "type": "Feature",
  "properties": {
    "addr:full":"Prinsengr 574 Amsterdam Noord-Holland 1017 KR",
    "addr:housenumber":"574",
    "addr:postcode":"1017 kr",
    "iso:country":"NL",
    "sg:address":"Prinsengr 574",
    "sg:city":"Amsterdam",
    "sg:orig_category":"Antiquiteiten",
    "sg:phone":"+31 20 625 2355",
    "sg:postcode":"1017 KR",
    "sg:province":"Noord-Holland",
    "wof:name":"Ria Jong",
    "wof:placetype":"venue"
},
  "geometry": {"coordinates":[4.888186,52.362358],"type":"Point"}
}