{
  "type": "Feature",
  "properties": {
    "addr:full":"Vermeerln 8 Naarden North Holland 1412 JX",
    "addr:housenumber":"8",
    "addr:postcode":"1412 jx",
    "addr:street":"Vermeerln",
    "iso:country":"NL",
    "sg:address":"Vermeerln 8",
    "sg:city":"Naarden",
    "sg:orig_category":"Bedrijfsopleidingen",
    "sg:phone":"+31 35 694 5572",
    "sg:postcode":"1412 JX",
    "sg:province":"North Holland",
    "sg:website":"http://www.helman.nl",
    "wof:name":"Helman & Partners",
    "wof:placetype":"venue"
},
  "geometry": {"coordinates":[5.175227,52.283562],"type":"Point"}
}