{
  "type": "Feature",
  "properties": {
    "addr:full":"Albistr 24 Hengelo Ov Overijssel 7559 KJ",
    "addr:housenumber":"24",
    "addr:postcode":"7559 kj",
    "addr:street":"Albistr;Ov",
    "iso:country":"NL",
    "sg:address":"Albistr 24",
    "sg:city":"Hengelo Ov",
    "sg:orig_category":"Adviesbureaus Automatisering",
    "sg:phone":"+31 74 278 0955",
    "sg:postcode":"7559 KJ",
    "sg:province":"Overijssel",
    "wof:name":"Zeilstra",
    "wof:placetype":"venue"
},
  "geometry": {"coordinates":[6.80222,52.296124],"type":"Point"}
}