{
  "type": "Feature",
  "properties": {
    "addr:full":"Koninginnewg 11 Hilversum Noord-Holland 1217 KP",
    "addr:housenumber":"11",
    "addr:postcode":"1217 kp",
    "addr:street":"Koninginnewg",
    "iso:country":"NL",
    "sg:address":"Koninginnewg 11",
    "sg:city":"Hilversum",
    "sg:orig_category":"Adviesbureaus Bedrijfsorganisatie",
    "sg:phone":"+31 35 625 0630",
    "sg:postcode":"1217 KP",
    "sg:province":"Noord-Holland",
    "wof:name":"Morvenna Bv",
    "wof:placetype":"venue"
},
  "geometry": {"coordinates":[5.167174,52.229546],"type":"Point"}
}