{
  "type": "Feature",
  "properties": {
    "addr:full":"Leemansstraat 2 Werkendam Noord-Brabant 4251 LD",
    "addr:housenumber":"2",
    "addr:postcode":"4251 ld",
    "addr:street":"Leemansstraat",
    "iso:country":"NL",
    "sg:address":"Leemansstraat 2",
    "sg:city":"Werkendam",
    "sg:orig_category":"Hout Gh",
    "sg:phone":"+31 183 505 666",
    "sg:postcode":"4251 LD",
    "sg:province":"Noord-Brabant",
    "wof:name":"Distelberg Bv",
    "wof:placetype":"venue"
},
  "geometry": {"coordinates":[4.881435,51.801579],"type":"Point"}
}