{
  "type": "Feature",
  "properties": {
    "addr:full":"Kraaivenstraat 36-01 Tilburg Noord-Brabant 5048 AB",
    "addr:housenumber":"36-01",
    "addr:postcode":"5048 ab",
    "addr:street":"Kraaivenstraat",
    "iso:country":"NL",
    "sg:address":"Kraaivenstraat 36-01",
    "sg:city":"Tilburg",
    "sg:orig_category":"Kantoorartikelen",
    "sg:phone":"+31 13 591 0565",
    "sg:postcode":"5048 AB",
    "sg:province":"Noord-Brabant",
    "wof:name":"Pfs Tilburg Bv",
    "wof:placetype":"venue"
},
  "geometry": {"coordinates":[5.0645580292,51.579750061],"type":"Point"}
}