{
  "type": "Feature",
  "properties": {
    "addr:full":"Olden Eibergsedk 1C Eibergen Gelderland 7151 NB",
    "addr:housenumber":"1c",
    "addr:postcode":"7151 nb",
    "addr:street":"Eibergsedk;Gelderland",
    "iso:country":"NL",
    "sg:address":"Olden Eibergsedk 1C",
    "sg:city":"Eibergen",
    "sg:orig_category":"Metaalbewerking",
    "sg:phone":"+31 545 474 759",
    "sg:postcode":"7151 NB",
    "sg:province":"Gelderland",
    "wof:name":"Jwf",
    "wof:placetype":"venue"
},
  "geometry": {"coordinates":[6.633587,52.09549],"type":"Point"}
}