{
  "type": "Feature",
  "properties": {
    "iso:country":"NL",
    "sg:address":"Hazendk 112",
    "sg:city":"Enschede",
    "sg:orig_category":"Autorijscholen",
    "sg:phone":"+31 53 476 0182",
    "sg:postcode":"7544 ZL",
    "sg:province":"Overijssel",
    "sg:website":"http://www.jansnuverink.myweb.nl",
    "wof:name":"Snuverink, Autorijschool Jan",
    "wof:placetype":"venue"
},
  "geometry": {"coordinates":[6.884968,52.188835],"type":"Point"}
}