{
  "type": "Feature",
  "properties": {
    "addr:full":"Oosterparallelweg 3 Staphorst Overijssel 7951 DD",
    "addr:housenumber":"3",
    "addr:postcode":"7951 dd",
    "addr:street":"Oosterparallelweg",
    "iso:country":"NL",
    "sg:address":"Oosterparallelweg 3",
    "sg:city":"Staphorst",
    "sg:orig_category":"Huishoudapparatuur, Televisies And Radio'S",
    "sg:phone":"+31 522 461 575",
    "sg:postcode":"7951 DD",
    "sg:province":"Overijssel",
    "wof:name":"Handelsonderneming J. Faber",
    "wof:placetype":"venue"
},
  "geometry": {"coordinates":[6.217493,52.648525],"type":"Point"}
}