{
  "type": "Feature",
  "properties": {
    "iso:country":"NL",
    "sg:address":"Houbenln 13",
    "sg:city":"Stramproy",
    "sg:orig_category":"Metaalbewerking",
    "sg:phone":"+31 495 563 723",
    "sg:postcode":"6039 CM",
    "sg:province":"BE.05",
    "wof:name":"Caris, R",
    "wof:placetype":"venue"
},
  "geometry": {"coordinates":[5.72462,51.192799],"type":"Point"}
}