{
  "type": "Feature",
  "properties": {
    "iso:country":"NL",
    "sg:address":"Kl Vosstr 34",
    "sg:city":"Brummen",
    "sg:orig_category":"Natuurvoeding En Reformartikelen",
    "sg:phone":"+31 575 562 979",
    "sg:postcode":"6971 KK",
    "sg:province":"Gelderland",
    "sg:website":"http://www.sunpower.nl",
    "wof:name":"Sunpower",
    "wof:placetype":"venue"
},
  "geometry": {"coordinates":[101.707611,3.1501],"type":"Point"}
}