{
  "type": "Feature",
  "properties": {
    "addr:full":"Noordse Bosje 43 Voorz Ouderen En Gehand Hilversum North Holland 1211 BE",
    "addr:housenumber":"43",
    "addr:postcode":"1211",
    "addr:street":"Noordse Bosje",
    "iso:country":"NL",
    "sg:address":"Noordse Bosje 43 Voorz Ouderen En Gehand",
    "sg:city":"Hilversum",
    "sg:orig_category":"Verenigingen En Stichtingen",
    "sg:phone":"+31 35 629 2934",
    "sg:postcode":"1211 BE",
    "sg:province":"North Holland",
    "wof:name":"Ouderenwerk Hilversum, Sticht",
    "wof:placetype":"venue"
},
  "geometry": {"coordinates":[5.1695,52.228565],"type":"Point"}
}