{
  "type": "Feature",
  "properties": {
    "addr:full":"1E Wormensewg 65 Apeldoorn Gelderland 7331 DB",
    "addr:housenumber":"65",
    "addr:postcode":"7331 db",
    "addr:street":"1E Wormensewg;Gelderland",
    "iso:country":"NL",
    "sg:address":"1E Wormensewg 65",
    "sg:city":"Apeldoorn",
    "sg:orig_category":"Kunststof Ramen",
    "sg:phone":"+31 6 50916887",
    "sg:postcode":"7331 DB",
    "sg:province":"Gelderland",
    "wof:name":"M S A",
    "wof:placetype":"venue"
},
  "geometry": {"coordinates":[5.969139,52.206059],"type":"Point"}
}