{
  "type": "Feature",
  "properties": {
    "addr:full":"Nieuwstraat 8 Brakel Gelderland 5306 AT",
    "addr:housenumber":"8",
    "addr:postcode":"5306",
    "addr:street":"Nieuwstraat;Gelderland",
    "iso:country":"NL",
    "sg:address":"Nieuwstraat 8",
    "sg:city":"Brakel",
    "sg:orig_category":"Autokeuringen",
    "sg:phone":"+31 418 671 349",
    "sg:postcode":"5306 AT",
    "sg:province":"Gelderland",
    "wof:name":"Garage Jan Van Beek",
    "wof:placetype":"venue"
},
  "geometry": {"coordinates":[5.097513,51.820305],"type":"Point"}
}