{
  "type": "Feature",
  "properties": {
    "addr:full":"Saenredamstr 49 Amsterdam Noord-Holland 1072 CC",
    "addr:housenumber":"49",
    "addr:postcode":"1072 cc",
    "addr:street":"Saenredamstr",
    "iso:country":"NL",
    "sg:address":"Saenredamstr 49",
    "sg:city":"Amsterdam",
    "sg:orig_category":"Loopbaanbegeleiding",
    "sg:phone":"+31 20 672 2000",
    "sg:postcode":"1072 CC",
    "sg:province":"Noord-Holland",
    "sg:website":"http://www.movente.nl",
    "wof:name":"Movente",
    "wof:placetype":"venue"
},
  "geometry": {"coordinates":[4.889308,52.355839],"type":"Point"}
}