{
  "type": "Feature",
  "properties": {
    "iso:country":"NL",
    "sg:address":"Gierstraat 45",
    "sg:city":"Haarlem",
    "sg:classifiers":[
        {
            "category":"Food & Beverages",
            "subcategory":"Fruits & Vegetables",
            "type":"Retail Goods"
        }
    ],
    "sg:phone":"+31 23 532 0817",
    "sg:postcode":"2011 GA",
    "sg:province":"Noord-Holland",
    "sg:tags":[
        "groenten"
    ],
    "wof:name":"Groenten & Fruitspecialist J.N. Kuyper",
    "wof:placetype":"venue"
},
  "geometry": {"coordinates":[4.632131,52.378769],"type":"Point"}
}