{
  "type": "Feature",
  "properties": {
    "addr:full":"Sint Jeroensweg 4 Noordwijk Zh Zuid-Holland 2201 NW",
    "addr:housenumber":"4;2201",
    "addr:postcode":"nw",
    "addr:street":"Sint Jeroensweg",
    "iso:country":"NL",
    "sg:address":"Sint Jeroensweg 4",
    "sg:city":"Noordwijk Zh",
    "sg:classifiers":[
        {
            "category":"Retail",
            "subcategory":"Photofinishing",
            "type":"Services"
        }
    ],
    "sg:phone":"+31 71 361 2176",
    "sg:postcode":"2201 NW",
    "sg:province":"Zuid-Holland",
    "sg:tags":[
        "foto",
        "film"
    ],
    "wof:name":"Foto Van Kampen",
    "wof:placetype":"venue"
},
  "geometry": {"coordinates":[4.447159,52.237125],"type":"Point"}
}