{
  "type": "Feature",
  "properties": {
    "addr:full":"Uhlenbeckstr 55 Voorburg South Holland 2273 CG",
    "addr:housenumber":"55",
    "addr:postcode":"2273 cg",
    "addr:street":"Uhlenbeckstr",
    "iso:country":"NL",
    "sg:address":"Uhlenbeckstr 55",
    "sg:city":"Voorburg",
    "sg:orig_category":"Verzekeringen - Verzekeringskantoren",
    "sg:phone":"+31 70 386 5293",
    "sg:postcode":"2273 CG",
    "sg:province":"South Holland",
    "wof:name":"Matthijssen",
    "wof:placetype":"venue"
},
  "geometry": {"coordinates":[4.357925,52.077484],"type":"Point"}
}