{
  "type": "Feature",
  "properties": {
    "addr:full":"Graafseweg 618 Wijchen Gelderland 6603 CM",
    "addr:housenumber":"618",
    "addr:postcode":"6603 cm",
    "addr:street":"Graafseweg;Gelderland",
    "iso:country":"NL",
    "sg:address":"Graafseweg 618",
    "sg:city":"Wijchen",
    "sg:orig_category":"Fotostudio'S And Fotografen",
    "sg:phone":"+31 24 642 1141",
    "sg:postcode":"6603 CM",
    "sg:province":"Gelderland",
    "wof:name":"Jos Migo Vakfotografie",
    "wof:placetype":"venue"
},
  "geometry": {"coordinates":[5.75954,51.807911],"type":"Point"}
}