{
  "type": "Feature",
  "properties": {
    "addr:full":"Mercuriusplein 2 Grubbenvorst Limburg 5971 LW",
    "addr:housenumber":"2",
    "addr:postcode":"5971 lw",
    "addr:street":"Mercuriusplein",
    "iso:country":"NL",
    "sg:address":"Mercuriusplein 2",
    "sg:city":"Grubbenvorst",
    "sg:orig_category":"Meubelreparatie And -Restauratie",
    "sg:phone":"+31 77 398 8090",
    "sg:postcode":"5971 LW",
    "sg:province":"Limburg",
    "wof:name":"Firma Fresco H.D.",
    "wof:placetype":"venue"
},
  "geometry": {"coordinates":[6.144904,51.425747],"type":"Point"}
}