{
  "type": "Feature",
  "properties": {
    "iso:country":"NL",
    "sg:address":"Postbus 5083",
    "sg:city":"Venray",
    "sg:orig_category":"Verzekeringen - Verzekeringskantoren",
    "sg:phone":"+31 475 578 171",
    "sg:postcode":"5800 GB",
    "sg:province":"Limburg",
    "sg:website":"http://www.vegio.nl",
    "wof:name":"V\u00e9gio Verzekeringsgroep",
    "wof:placetype":"venue"
},
  "geometry": {"coordinates":[5.977073,51.527157],"type":"Point"}
}