{
  "type": "Feature",
  "properties": {
    "addr:full":"Roestenbergstraat 64 Kaatsheuvel Noord-Brabant 5171 JD",
    "addr:housenumber":"64",
    "addr:postcode":"5171 jd",
    "addr:street":"Roestenbergstraat",
    "iso:country":"NL",
    "sg:address":"Roestenbergstraat 64",
    "sg:city":"Kaatsheuvel",
    "sg:orig_category":"Schoenen",
    "sg:phone":"+31 416 272 323",
    "sg:postcode":"5171 JD",
    "sg:province":"Noord-Brabant",
    "wof:name":"Schoenfabriek W.J. Sulsters",
    "wof:placetype":"venue"
},
  "geometry": {"coordinates":[5.042872,51.662521],"type":"Point"}
}