{
  "type": "Feature",
  "properties": {
    "addr:full":"Vd Capellenstr 246 Zwolle NL.08 8014 VZ",
    "addr:housenumber":"246",
    "addr:postcode":"8014 vz",
    "iso:country":"NL",
    "sg:address":"Vd Capellenstr 246",
    "sg:city":"Zwolle",
    "sg:orig_category":"Juweliers",
    "sg:phone":"+31 38 460 0076",
    "sg:postcode":"8014 VZ",
    "sg:province":"NL.08",
    "wof:name":"Luna, Juwelier",
    "wof:placetype":"venue"
},
  "geometry": {"coordinates":[6.1122,52.483448],"type":"Point"}
}