{
  "type": "Feature",
  "properties": {
    "addr:full":"Mimosaln 10 Waalre North Brabant 5582 AG",
    "addr:housenumber":"10",
    "addr:postcode":"5582",
    "addr:street":"Mimosaln",
    "iso:country":"NL",
    "sg:address":"Mimosaln 10",
    "sg:city":"Waalre",
    "sg:orig_category":"Marktonderzoekbureaus",
    "sg:phone":"+31 40 221 2725",
    "sg:postcode":"5582 AG",
    "sg:province":"North Brabant",
    "wof:name":"Rie Schouten Bv",
    "wof:placetype":"venue"
},
  "geometry": {"coordinates":[5.443459,51.386463],"type":"Point"}
}