{
  "type": "Feature",
  "properties": {
    "addr:full":"Lindenlaan 5 Kerkrade Limburg 6463 GG",
    "addr:housenumber":"5",
    "addr:postcode":"6463 gg",
    "addr:street":"Lindenlaan",
    "iso:country":"NL",
    "sg:address":"Lindenlaan 5",
    "sg:city":"Kerkrade",
    "sg:orig_category":"Boekhouders",
    "sg:phone":"+31 45 546 0812",
    "sg:postcode":"6463 GG",
    "sg:province":"Limburg",
    "wof:name":"Assurantie- En Administratiekantoor Wil",
    "wof:placetype":"venue"
},
  "geometry": {"coordinates":[6.067561,50.873989],"type":"Point"}
}