{
  "type": "Feature",
  "properties": {
    "addr:full":"Waverveensepad 23 Vinkeveen Utrecht 3645 CL",
    "addr:housenumber":"23",
    "addr:postcode":"3645",
    "addr:street":"Waverveensepad",
    "iso:country":"NL",
    "sg:address":"Waverveensepad 23",
    "sg:city":"Vinkeveen",
    "sg:orig_category":"Kappers",
    "sg:phone":"+31 297 261 345",
    "sg:postcode":"3645 CL",
    "sg:province":"Utrecht",
    "wof:name":"Brenda",
    "wof:placetype":"venue"
},
  "geometry": {"coordinates":[4.908768177,52.2244415283],"type":"Point"}
}