{
  "type": "Feature",
  "properties": {
    "addr:full":"Reigerln 3 St Pancras Noord-Holland 1834 VK",
    "addr:housenumber":"3",
    "addr:postcode":"1834 vk",
    "addr:street":"Reigerln",
    "iso:country":"NL",
    "sg:address":"Reigerln 3",
    "sg:city":"St Pancras",
    "sg:orig_category":"Loodgieters",
    "sg:phone":"+31 72 562 5536",
    "sg:postcode":"1834 VK",
    "sg:province":"Noord-Holland",
    "wof:name":"Tih",
    "wof:placetype":"venue"
},
  "geometry": {"coordinates":[4.781905,52.659256],"type":"Point"}
}