{
  "type": "Feature",
  "properties": {
    "addr:full":"Kievitstr 2 Zierikzee Zeeland 4302 WC",
    "addr:housenumber":"2",
    "addr:postcode":"4302 wc",
    "addr:street":"Kievitstr",
    "iso:country":"NL",
    "sg:address":"Kievitstr 2",
    "sg:city":"Zierikzee",
    "sg:orig_category":"Artsen - Huisartsen",
    "sg:phone":"+31 111 413 410",
    "sg:postcode":"4302 WC",
    "sg:province":"Zeeland",
    "wof:name":"Daniels, C H G",
    "wof:placetype":"venue"
},
  "geometry": {"coordinates":[3.907306,51.646839],"type":"Point"}
}