{
  "type": "Feature",
  "properties": {
    "addr:full":"Tichelkuilen 127 Zutphen Gelderland 7206 BJ",
    "addr:housenumber":"127",
    "addr:postcode":"7206 bj",
    "addr:street":"Tichelkuilen;Gelderland",
    "iso:country":"NL",
    "sg:address":"Tichelkuilen 127",
    "sg:city":"Zutphen",
    "sg:orig_category":"Adviesbureaus Bouwkunde",
    "sg:phone":"+31 575 520 649",
    "sg:postcode":"7206 BJ",
    "sg:province":"Gelderland",
    "wof:name":"Claessens, W M A",
    "wof:placetype":"venue"
},
  "geometry": {"coordinates":[6.206168,52.12632],"type":"Point"}
}