{
  "type": "Feature",
  "properties": {
    "addr:full":"Marathon 136 Krimpen A/D Ijssel Zuid-Holland 2924 XG",
    "addr:housenumber":"136;a / d",
    "addr:postcode":"2924 xg",
    "addr:street":"Marathon;Krimpen",
    "iso:country":"NL",
    "sg:address":"Marathon 136",
    "sg:city":"Krimpen A/D Ijssel",
    "sg:orig_category":"Kappers",
    "sg:phone":"+31 180 510 406",
    "sg:postcode":"2924 XG",
    "sg:province":"Zuid-Holland",
    "wof:name":"P J L Van Der Meer",
    "wof:placetype":"venue"
},
  "geometry": {"coordinates":[4.615494,51.921196],"type":"Point"}
}