{
  "type": "Feature",
  "properties": {
    "addr:full":"Spoorln 33 Zwammerdam Zuid-Holland 2471 PC",
    "addr:housenumber":"33",
    "addr:postcode":"2471 pc",
    "addr:street":"Spoorln",
    "iso:country":"NL",
    "sg:address":"Spoorln 33",
    "sg:city":"Zwammerdam",
    "sg:orig_category":"Kinderopvang",
    "sg:phone":"+31 172 650 446",
    "sg:postcode":"2471 PC",
    "sg:province":"Zuid-Holland",
    "wof:name":"Beertjes Burch",
    "wof:placetype":"venue"
},
  "geometry": {"coordinates":[4.730431,52.104767],"type":"Point"}
}