{
  "type": "Feature",
  "properties": {
    "addr:full":"Berlagestr 2 Lekkerkerk Zuid-Holland 2941 GC",
    "addr:housenumber":"2",
    "addr:postcode":"2941 gc",
    "addr:street":"Berlagestr",
    "iso:country":"NL",
    "sg:address":"Berlagestr 2",
    "sg:city":"Lekkerkerk",
    "sg:orig_category":"Scholen Voor Algemeen Voortgezet Onderwijs",
    "sg:phone":"+31 180 669 044",
    "sg:postcode":"2941 GC",
    "sg:province":"Zuid-Holland",
    "sg:website":"http://www.driestarcollege.nl",
    "wof:name":"Driestar College",
    "wof:placetype":"venue"
},
  "geometry": {"coordinates":[4.683374,51.896568],"type":"Point"}
}