{
  "type": "Feature",
  "properties": {
    "iso:country":"NL",
    "sg:address":"Peperstraat 24",
    "sg:city":"Sevenum",
    "sg:orig_category":"Verzekeringen",
    "sg:phone":"+31 77 467 3172",
    "sg:postcode":"5975 BV",
    "sg:province":"Limburg",
    "wof:name":"Jan Lucassen Assurantien",
    "wof:placetype":"venue"
},
  "geometry": {"coordinates":[6.033469,51.411228],"type":"Point"}
}