{
  "type": "Feature",
  "properties": {
    "iso:country":"NL",
    "sg:address":"Adelaarswg 92Hs",
    "sg:city":"Amsterdam",
    "sg:orig_category":"Beeldende Kunstenaars",
    "sg:phone":"+31 20 638 5137",
    "sg:postcode":"1021 BX",
    "sg:province":"North Holland",
    "wof:name":"Krone, U",
    "wof:placetype":"venue"
},
  "geometry": {"coordinates":[4.918159,52.387737],"type":"Point"}
}