{
  "type": "Feature",
  "properties": {
    "addr:full":"Vd Poelstr 13 Raamsdonksveer Noord-Brabant 4941 AL",
    "addr:housenumber":"13",
    "addr:postcode":"4941 al",
    "iso:country":"NL",
    "sg:address":"Vd Poelstr 13",
    "sg:city":"Raamsdonksveer",
    "sg:orig_category":"Betonijzervlechten",
    "sg:phone":"+31 162 512 230",
    "sg:postcode":"4941 AL",
    "sg:province":"Noord-Brabant",
    "wof:name":"Berg?, A W",
    "wof:placetype":"venue"
},
  "geometry": {"coordinates":[4.880079,51.694283],"type":"Point"}
}