{
  "type": "Feature",
  "properties": {
    "addr:full":"Markt 61 S Hertogenbosch Noord-Brabant 5211 JW",
    "addr:housenumber":"61",
    "addr:postcode":"5211 jw",
    "addr:street":"Markt;S Hertogenbosch",
    "iso:country":"NL",
    "sg:address":"Markt 61",
    "sg:city":"S Hertogenbosch",
    "sg:orig_category":"Schoenen",
    "sg:phone":"+31 73 614 6714",
    "sg:postcode":"5211 JW",
    "sg:province":"Noord-Brabant",
    "wof:name":"Invito",
    "wof:placetype":"venue"
},
  "geometry": {"coordinates":[5.303728,51.689484],"type":"Point"}
}