{
  "type": "Feature",
  "properties": {
    "iso:country":"NL",
    "sg:address":"K De Boerwg 16",
    "sg:city":"Woltersum",
    "sg:classifiers":[
        {
            "category":"Food & Beverages",
            "subcategory":"Bakery",
            "type":"Retail Goods"
        }
    ],
    "sg:phone":"+31 50 302 1518",
    "sg:postcode":"9795 PH",
    "sg:province":"Groningen",
    "sg:tags":[
        "brood",
        "en",
        "banket"
    ],
    "wof:name":"Kiel, J",
    "wof:placetype":"venue"
},
  "geometry": {"coordinates":[6.732886,53.271893],"type":"Point"}
}