{
  "type": "Feature",
  "properties": {
    "addr:full":"Horsterwg 5 Beek Lb Missouri 6191 RX",
    "addr:housenumber":"5",
    "addr:postcode":"6191 rx",
    "addr:street":"Horsterwg",
    "iso:country":"NL",
    "sg:address":"Horsterwg 5",
    "sg:city":"Beek Lb",
    "sg:orig_category":"Projectinrichting",
    "sg:phone":"+31 43 364 8686",
    "sg:postcode":"6191 RX",
    "sg:province":"Missouri",
    "wof:name":"Pan Brasilia Nederland Bv",
    "wof:placetype":"venue"
},
  "geometry": {"coordinates":[-93.129936,36.705662],"type":"Point"}
}