{
  "type": "Feature",
  "properties": {
    "iso:country":"NL",
    "sg:address":"Ypesteinerlaan 44",
    "sg:city":"Heiloo",
    "sg:orig_category":"Mode-, Juwelen- And Meubelontwerpers",
    "sg:phone":"+31 72 533 7761",
    "sg:postcode":"1851 WG",
    "sg:province":"North Holland",
    "wof:name":"Meijering Maquettebouw",
    "wof:placetype":"venue"
},
  "geometry": {"coordinates":[4.711883,52.593243],"type":"Point"}
}