{
  "type": "Feature",
  "properties": {
    "addr:full":"Sinj Semeynsstr 32 Amstelveen Noord-Holland 1183 LE",
    "addr:housenumber":"32",
    "addr:postcode":"1183 le",
    "iso:country":"NL",
    "sg:address":"Sinj Semeynsstr 32",
    "sg:city":"Amstelveen",
    "sg:orig_category":"Journalisten Freelance",
    "sg:phone":"+31 20 453 8042",
    "sg:postcode":"1183 LE",
    "sg:province":"Noord-Holland",
    "wof:name":"Dutchmedia",
    "wof:placetype":"venue"
},
  "geometry": {"coordinates":[4.876048,52.304649],"type":"Point"}
}