{
  "type": "Feature",
  "properties": {
    "addr:full":"Bergerothwg 63 Stramproy Limburg 6039 AL",
    "addr:housenumber":"63",
    "addr:postcode":"6039 al",
    "addr:street":"Bergerothwg",
    "iso:country":"NL",
    "sg:address":"Bergerothwg 63",
    "sg:city":"Stramproy",
    "sg:orig_category":"Adviesbureaus Bedrijfsorganisatie",
    "sg:phone":"+31 495 564 658",
    "sg:postcode":"6039 AL",
    "sg:province":"Limburg",
    "wof:name":"Eggelen, E",
    "wof:placetype":"venue"
},
  "geometry": {"coordinates":[5.711254,51.198605],"type":"Point"}
}