{
  "type": "Feature",
  "properties": {
    "addr:full":"Korteraarsewg 130 Ter Aar Zuid-Holland 2461 GP",
    "addr:housenumber":"130",
    "addr:postcode":"aar;2461 gp",
    "addr:street":"Ter",
    "iso:country":"NL",
    "sg:address":"Korteraarsewg 130",
    "sg:city":"Ter Aar",
    "sg:orig_category":"Verzekeringen - Verzekeringskantoren",
    "sg:phone":"+31 172 602 532",
    "sg:postcode":"2461 GP",
    "sg:province":"Zuid-Holland",
    "wof:name":"Baak",
    "wof:placetype":"venue"
},
  "geometry": {"coordinates":[4.727026,52.162933],"type":"Point"}
}