{
  "type": "Feature",
  "properties": {
    "addr:full":"Spoorstraat 30 Den Helder Noord-Holland 1781 JG",
    "addr:housenumber":"30",
    "addr:postcode":"1781 jg",
    "addr:street":"Spoorstraat",
    "iso:country":"NL",
    "sg:address":"Spoorstraat 30",
    "sg:city":"Den Helder",
    "sg:orig_category":"Baby- And Kinderkleding",
    "sg:phone":"+31 223 612 035",
    "sg:postcode":"1781 JG",
    "sg:province":"Noord-Holland",
    "wof:name":"We Men",
    "wof:placetype":"venue"
},
  "geometry": {"coordinates":[4.762475,52.959133],"type":"Point"}
}