{
  "type": "Feature",
  "properties": {
    "iso:country":"NL",
    "sg:address":"Lombardkd 28",
    "sg:city":"Rotterdam",
    "sg:orig_category":"Verenigingen En Stichtingen",
    "sg:phone":"+31 10 414 3915",
    "sg:postcode":"3031 AH",
    "sg:province":"South Holland",
    "wof:name":"Lombard, De",
    "wof:placetype":"venue"
},
  "geometry": {"coordinates":[4.485534,51.925278],"type":"Point"}
}