{
  "type": "Feature",
  "properties": {
    "addr:full":"Vierkante Bos 28 Ijmuiden North Holland 1974 LN",
    "addr:housenumber":"28",
    "addr:postcode":"1974 ln",
    "addr:street":"Vierkante Bos",
    "iso:country":"NL",
    "sg:address":"Vierkante Bos 28",
    "sg:city":"Ijmuiden",
    "sg:orig_category":"Goederenvervoer Over De Weg",
    "sg:phone":"+31 255 532 401",
    "sg:postcode":"1974 LN",
    "sg:province":"North Holland",
    "wof:name":"P.J.J. Venema",
    "wof:placetype":"venue"
},
  "geometry": {"coordinates":[4.59899,52.448578],"type":"Point"}
}