{
  "type": "Feature",
  "properties": {
    "addr:full":"Valeriusstr 296 Amsterdam Noord-Holland 1075 GP",
    "addr:housenumber":"296",
    "addr:postcode":"1075 gp",
    "iso:country":"NL",
    "sg:address":"Valeriusstr 296",
    "sg:city":"Amsterdam",
    "sg:orig_category":"Adviesbureaus Bedrijfsorganisatie",
    "sg:phone":"+31 20 670 7965",
    "sg:postcode":"1075 GP",
    "sg:province":"Noord-Holland",
    "sg:website":"http://www.kpc.nl",
    "wof:name":"Keizer",
    "wof:placetype":"venue"
},
  "geometry": {"coordinates":[4.857341,52.351288],"type":"Point"}
}