{
  "type": "Feature",
  "properties": {
    "addr:full":"Tt Vasumwg 18 Amsterdam North Holland 1033 SC",
    "addr:housenumber":"18",
    "addr:postcode":"1033 sc",
    "iso:country":"NL",
    "sg:address":"Tt Vasumwg 18",
    "sg:city":"Amsterdam",
    "sg:orig_category":"Kindermeubelen",
    "sg:phone":"+31 20 633 7331",
    "sg:postcode":"1033 SC",
    "sg:province":"North Holland",
    "wof:name":"Fakkeldij Groep",
    "wof:placetype":"venue"
},
  "geometry": {"coordinates":[4.897025,52.402687],"type":"Point"}
}