{
  "type": "Feature",
  "properties": {
    "iso:country":"NL",
    "sg:address":"Europalaan 6B",
    "sg:city":"Eindhoven",
    "sg:orig_category":"Makelaars In Onroerend Goed",
    "sg:phone":"+31 40 246 6363",
    "sg:postcode":"5623 LJ",
    "sg:province":"Noord-Brabant",
    "wof:name":"Kats & Waalwijk Vastgoedmanagement Bv",
    "wof:placetype":"venue"
},
  "geometry": {"coordinates":[5.482099,51.457623],"type":"Point"}
}