{
  "type": "Feature",
  "properties": {
    "addr:full":"Meervensedijk 4 Lierop Noord-Brabant 5715 PZ",
    "addr:housenumber":"4",
    "addr:postcode":"5715 pz",
    "addr:street":"Meervensedijk",
    "iso:country":"NL",
    "sg:address":"Meervensedijk 4",
    "sg:city":"Lierop",
    "sg:orig_category":"Overheidsdiensten",
    "sg:phone":"+31 492 331 779",
    "sg:postcode":"5715 PZ",
    "sg:province":"Noord-Brabant",
    "wof:name":"Nirwana Ojc",
    "wof:placetype":"venue"
},
  "geometry": {"coordinates":[5.6719350815,51.4164924622],"type":"Point"}
}