{
  "type": "Feature",
  "properties": {
    "iso:country":"NL",
    "sg:address":"Handelln 2 Lok He",
    "sg:city":"Heemstede",
    "sg:orig_category":"Ziekenhuizen, Sanatoria, Verpleeghuizen",
    "sg:phone":"+31 23 514 1566",
    "sg:postcode":"2102 CW",
    "sg:province":"North Holland",
    "wof:name":"Spaarne Zks",
    "wof:placetype":"venue"
},
  "geometry": {"coordinates":[4.621248,52.345287],"type":"Point"}
}