{
  "type": "Feature",
  "properties": {
    "iso:country":"NL",
    "sg:address":"Phoenixstr 33",
    "sg:city":"Alkmaar",
    "sg:orig_category":"Weegwerktuigen - Fabrieken En Groothandel",
    "sg:phone":"+31 72 533 7044",
    "sg:postcode":"1812 PP",
    "sg:province":"Noord-Holland",
    "wof:name":"Leguit & Noordman",
    "wof:placetype":"venue"
},
  "geometry": {"coordinates":[4.7641768456,52.6191482544],"type":"Point"}
}