{
  "type": "Feature",
  "properties": {
    "addr:full":"Johan Modastraat 6 Winschoten Groningen 9671 CD",
    "addr:housenumber":"6",
    "addr:postcode":"9671 cd",
    "addr:street":"Johan Modastraat",
    "iso:country":"NL",
    "sg:address":"Johan Modastraat 6",
    "sg:city":"Winschoten",
    "sg:orig_category":"Overheidsdiensten",
    "sg:phone":"+31 597 481 111",
    "sg:postcode":"9671 CD",
    "sg:province":"Groningen",
    "wof:name":"Gemeente Winschoten",
    "wof:placetype":"venue"
},
  "geometry": {"coordinates":[7.0389590263,53.1440315247],"type":"Point"}
}