{
  "type": "Feature",
  "properties": {
    "addr:full":"Heesweg 9 Raalte Overijssel 8102 HJ",
    "addr:housenumber":"9",
    "addr:postcode":"8102 hj",
    "addr:street":"Heesweg",
    "iso:country":"NL",
    "sg:address":"Heesweg 9",
    "sg:city":"Raalte",
    "sg:orig_category":"Autokeuringen",
    "sg:phone":"+31 572 357 971",
    "sg:postcode":"8102 HJ",
    "sg:province":"Overijssel",
    "wof:name":"Euromaster Vulcano Bv",
    "wof:placetype":"venue"
},
  "geometry": {"coordinates":[6.281906,52.382801],"type":"Point"}
}