{
  "type": "Feature",
  "properties": {
    "addr:full":"Zijde 62 Boskoop Zuid-Holland 2771 EP",
    "addr:housenumber":"62",
    "addr:postcode":"2771 ep",
    "addr:street":"Zijde",
    "iso:country":"NL",
    "sg:address":"Zijde 62",
    "sg:city":"Boskoop",
    "sg:orig_category":"Huishoudapparatuur, Televisies And Radio'S",
    "sg:phone":"+31 172 213 435",
    "sg:postcode":"2771 EP",
    "sg:province":"Zuid-Holland",
    "wof:name":"Windhorst-Techniek",
    "wof:placetype":"venue"
},
  "geometry": {"coordinates":[4.655658,52.074394],"type":"Point"}
}