{
  "type": "Feature",
  "properties": {
    "addr:full":"Waarbekenwg 19 Hengelo Ov Overijssel 7553 KH",
    "addr:housenumber":"19",
    "addr:postcode":"7553 kh",
    "addr:street":"Waarbekenwg;Ov",
    "iso:country":"NL",
    "sg:address":"Waarbekenwg 19",
    "sg:city":"Hengelo Ov",
    "sg:orig_category":"Levensmiddelen - Fabrieken En Groothandel",
    "sg:phone":"+31 74 242 7821",
    "sg:postcode":"7553 KH",
    "sg:province":"Overijssel",
    "wof:name":"Ipek",
    "wof:placetype":"venue"
},
  "geometry": {"coordinates":[6.797618,52.254086],"type":"Point"}
}