{
  "type": "Feature",
  "properties": {
    "addr:full":"Citroenstraat 33 'S Gravenhage South Holland 2564 PJ",
    "addr:housenumber":"33",
    "addr:postcode":"2564 pj",
    "addr:street":"Citroenstraat;' S Gravenhage",
    "iso:country":"NL",
    "sg:address":"Citroenstraat 33",
    "sg:city":"'S Gravenhage",
    "sg:orig_category":"Marktonderzoekbureaus",
    "sg:phone":"+31 70 368 2469",
    "sg:postcode":"2564 PJ",
    "sg:province":"South Holland",
    "wof:name":"Adviesburo Delta Plus",
    "wof:placetype":"venue"
},
  "geometry": {"coordinates":[4.258601,52.065453],"type":"Point"}
}