{
  "type": "Feature",
  "properties": {
    "addr:full":"Oude Baan 9 Rosmalen Noord-Brabant 5242 HT",
    "addr:housenumber":"9",
    "addr:postcode":"5242 ht",
    "addr:street":"Oude Baan",
    "iso:country":"NL",
    "sg:address":"Oude Baan 9",
    "sg:city":"Rosmalen",
    "sg:orig_category":"Apothekers",
    "sg:phone":"+31 73 521 4459",
    "sg:postcode":"5242 HT",
    "sg:province":"Noord-Brabant",
    "wof:name":"Apotheek Rosmalen-Berlicum Bv",
    "wof:placetype":"venue"
},
  "geometry": {"coordinates":[5.364048,51.708279],"type":"Point"}
}