{
  "type": "Feature",
  "properties": {
    "addr:full":"Eilandsewg 16 Nederhorst D Berg California 1394 JE",
    "addr:housenumber":"16",
    "addr:postcode":"1394 je",
    "addr:street":"Eilandsewg;Nederhorst D Berg",
    "iso:country":"NL",
    "sg:address":"Eilandsewg 16",
    "sg:city":"Nederhorst D Berg",
    "sg:orig_category":"Loonbedrijven",
    "sg:phone":"+31 294 252 405",
    "sg:postcode":"1394 JE",
    "sg:province":"California",
    "wof:name":"Ploegstra, C",
    "wof:placetype":"venue"
},
  "geometry": {"coordinates":[-121.624138,39.182121],"type":"Point"}
}