{
  "type": "Feature",
  "properties": {
    "addr:full":"De Meeuwse Acker 2006 Nymegen Gelderland 6546 DZ",
    "addr:housenumber":"2006",
    "addr:postcode":"6546 dz",
    "addr:street":"De Meeuwse Acker;Gelderland",
    "iso:country":"NL",
    "sg:address":"De Meeuwse Acker 2006",
    "sg:city":"Nymegen",
    "sg:orig_category":"Verzekeringen - Verzekeringskantoren",
    "sg:phone":"+31 24 373 4258",
    "sg:postcode":"6546 DZ",
    "sg:province":"Gelderland",
    "wof:name":"Thiele, N J",
    "wof:placetype":"venue"
},
  "geometry": {"coordinates":[5.799751,51.835812],"type":"Point"}
}