{
  "type": "Feature",
  "properties": {
    "addr:full":"Lindenlaan 6 Baarn Utrecht 3741 WP",
    "addr:housenumber":"6",
    "addr:postcode":"3741 wp",
    "addr:street":"Lindenlaan",
    "iso:country":"NL",
    "sg:address":"Lindenlaan 6",
    "sg:city":"Baarn",
    "sg:orig_category":"Metaalwerken",
    "sg:phone":"+31 35 541 5195",
    "sg:postcode":"3741 WP",
    "sg:province":"Utrecht",
    "wof:name":"Intermontage Baarn Bv",
    "wof:placetype":"venue"
},
  "geometry": {"coordinates":[5.282607,52.217129],"type":"Point"}
}