{
  "type": "Feature",
  "properties": {
    "addr:full":"Zandstraat 56 Gennep Limburg 6591 DD",
    "addr:housenumber":"56",
    "addr:postcode":"6591 dd",
    "addr:street":"Zandstraat",
    "iso:country":"NL",
    "sg:address":"Zandstraat 56",
    "sg:city":"Gennep",
    "sg:orig_category":"Banken And Kredietinstellingen",
    "sg:phone":"+31 485 550 550",
    "sg:postcode":"6591 DD",
    "sg:province":"Limburg",
    "wof:name":"Rabobank",
    "wof:placetype":"venue"
},
  "geometry": {"coordinates":[5.97119,51.699299],"type":"Point"}
}