{
  "type": "Feature",
  "properties": {
    "addr:full":"Gerardus Majellastraat 9 Dongen BE.07 5101 BE",
    "addr:housenumber":"9;be.07",
    "addr:postcode":"5101",
    "addr:street":"Gerardus Majellastraat",
    "iso:country":"NL",
    "sg:address":"Gerardus Majellastraat 9",
    "sg:city":"Dongen",
    "sg:orig_category":"Bloemen And Planten",
    "sg:phone":"+31 162 312 446",
    "sg:postcode":"5101 BE",
    "sg:province":"BE.07",
    "wof:name":"Brattinga Bloemen",
    "wof:placetype":"venue"
},
  "geometry": {"coordinates":[4.904815,50.448189],"type":"Point"}
}