{
  "type": "Feature",
  "properties": {
    "addr:full":"Hoofdwg 143 Rotterdam South Holland 3067 GE",
    "addr:housenumber":"143",
    "addr:postcode":"3067",
    "iso:country":"NL",
    "sg:address":"Hoofdwg 143",
    "sg:city":"Rotterdam",
    "sg:orig_category":"Banden",
    "sg:phone":"+31 6 51557856",
    "sg:postcode":"3067 GE",
    "sg:province":"South Holland",
    "wof:name":"Huijbregtse & Van Der Hoeven Bv",
    "wof:placetype":"venue"
},
  "geometry": {"coordinates":[4.539139,51.947136],"type":"Point"}
}