{
  "type": "Feature",
  "properties": {
    "iso:country":"NL",
    "sg:address":"Lievelderstraat 15",
    "sg:city":"Groenlo",
    "sg:orig_category":"Makelaars In Onroerend Goed",
    "sg:phone":"+31 544 467 471",
    "sg:postcode":"7141 BJ",
    "sg:province":"Gelderland",
    "wof:name":"De Vesting",
    "wof:placetype":"venue"
},
  "geometry": {"coordinates":[6.617784,52.041203],"type":"Point"}
}