{
  "type": "Feature",
  "properties": {
    "addr:full":"Bothastraat 3 Ridderkerk Zuid-Holland 2987 BH",
    "addr:housenumber":"3",
    "addr:postcode":"2987 bh",
    "addr:street":"Bothastraat",
    "iso:country":"NL",
    "sg:address":"Bothastraat 3",
    "sg:city":"Ridderkerk",
    "sg:orig_category":"Koeriersdiensten",
    "sg:phone":"+31 6 53915474",
    "sg:postcode":"2987 BH",
    "sg:province":"Zuid-Holland",
    "wof:name":"Portservices",
    "wof:placetype":"venue"
},
  "geometry": {"coordinates":[4.579959,51.898525],"type":"Point"}
}