{
  "type": "Feature",
  "properties": {
    "addr:full":"Stadhuisplein 320 Tilburg North Brabant 5038 TH",
    "addr:housenumber":"320",
    "addr:postcode":"5038 th",
    "addr:street":"Stadhuisplein",
    "iso:country":"NL",
    "sg:address":"Stadhuisplein 320",
    "sg:city":"Tilburg",
    "sg:classifiers":[
        {
            "category":"Fast Food",
            "type":"Food & Drink"
        }
    ],
    "sg:phone":"+31 13 536 5643",
    "sg:postcode":"5038 TH",
    "sg:province":"North Brabant",
    "sg:tags":[
        "afhaal",
        "restaurant"
    ],
    "wof:name":"Cafetaria Grillhouse Le Marche",
    "wof:placetype":"venue"
},
  "geometry": {"coordinates":[5.087303,51.556095],"type":"Point"}
}