{
  "type": "Feature",
  "properties": {
    "addr:full":"Cockeveld 8 Nuenen Noord-Brabant 5672 AE",
    "addr:housenumber":"8",
    "addr:postcode":"5672 ae",
    "addr:street":"Cockeveld",
    "iso:country":"NL",
    "sg:address":"Cockeveld 8",
    "sg:city":"Nuenen",
    "sg:orig_category":"Autopoetsbedrijven",
    "sg:phone":"+31 40 284 2294",
    "sg:postcode":"5672 AE",
    "sg:province":"Noord-Brabant",
    "sg:website":"http://www.allroundsnel.com",
    "wof:name":"Allround Carcleaning",
    "wof:placetype":"venue"
},
  "geometry": {"coordinates":[5.537592,51.466595],"type":"Point"}
}