{
  "type": "Feature",
  "properties": {
    "iso:country":"NL",
    "sg:address":"Concordialaan 5",
    "sg:city":"Ede Gld",
    "sg:orig_category":"Handwerkartikelen",
    "sg:phone":"+31 318 612 862",
    "sg:postcode":"6712 GL",
    "sg:province":"Gelderland",
    "wof:name":"Karels, Wilma",
    "wof:placetype":"venue"
},
  "geometry": {"coordinates":[5.665142,52.050186],"type":"Point"}
}