{
  "type": "Feature",
  "properties": {
    "addr:full":"Leydeckerstr 19 Arnhem Gelderland 6831 KE",
    "addr:housenumber":"19",
    "addr:postcode":"6831 ke",
    "addr:street":"Leydeckerstr",
    "iso:country":"NL",
    "sg:address":"Leydeckerstr 19",
    "sg:city":"Arnhem",
    "sg:orig_category":"Autorijscholen",
    "sg:phone":"+31 26 323 6679",
    "sg:postcode":"6831 KE",
    "sg:province":"Gelderland",
    "wof:name":"Joosten, Dick",
    "wof:placetype":"venue"
},
  "geometry": {"coordinates":[5.8905,51.956558],"type":"Point"}
}