{
  "type": "Feature",
  "properties": {
    "iso:country":"NL",
    "sg:address":"Krimwg 22",
    "sg:city":"Hoenderloo",
    "sg:orig_category":"Fietsen En Bromfietsen Verhuur",
    "sg:phone":"+31 55 378 1318",
    "sg:postcode":"7351 AX",
    "sg:province":"Gelderland",
    "wof:name":"Buitenhuis",
    "wof:placetype":"venue"
},
  "geometry": {"coordinates":[5.87877,52.117973],"type":"Point"}
}