{
  "type": "Feature",
  "properties": {
    "iso:country":"NL",
    "sg:address":"Vermeerstr 16",
    "sg:city":"Ommen",
    "sg:orig_category":"Mobiele- En Autotelefoons",
    "sg:phone":"+31 529 454 774",
    "sg:postcode":"7731 SM",
    "sg:province":"Overijssel",
    "wof:name":"Kelder",
    "wof:placetype":"venue"
},
  "geometry": {"coordinates":[6.425073,52.532257],"type":"Point"}
}