{
  "type": "Feature",
  "properties": {
    "iso:country":"NL",
    "sg:address":"Singel 93",
    "sg:city":"Amsterdam",
    "sg:orig_category":"Wijnkoperijen En -Groothandel",
    "sg:phone":"+31 20 420 0022",
    "sg:postcode":"1012 VG",
    "sg:province":"North Holland",
    "wof:name":"Perelada Int Bv",
    "wof:placetype":"venue"
},
  "geometry": {"coordinates":[4.8915119171,52.3759536743],"type":"Point"}
}