{
  "type": "Feature",
  "properties": {
    "addr:full":"Maarsbergenstraat 30 'S Gravenhage Zuid-Holland 2546 SR",
    "addr:housenumber":"30",
    "addr:postcode":"2546 sr",
    "addr:street":"Maarsbergenstraat;' S",
    "iso:country":"NL",
    "sg:address":"Maarsbergenstraat 30",
    "sg:city":"'S Gravenhage",
    "sg:classifiers":[
        {
            "category":"Education",
            "subcategory":"Preschool",
            "type":"Public Place"
        }
    ],
    "sg:phone":"+31 70 367 3080",
    "sg:postcode":"2546 SR",
    "sg:province":"Zuid-Holland",
    "sg:tags":[
        "kleuteronderwijs",
        "basis-"
    ],
    "wof:name":"Eben Haezer",
    "wof:placetype":"venue"
},
  "geometry": {"coordinates":[4.272843,52.059887],"type":"Point"}
}