{
  "type": "Feature",
  "properties": {
    "addr:full":"Nieuwstraat 10 Heesch Noord-Brabant 5384 TC",
    "addr:housenumber":"10",
    "addr:postcode":"5384 tc",
    "addr:street":"Nieuwstraat",
    "iso:country":"NL",
    "sg:address":"Nieuwstraat 10",
    "sg:city":"Heesch",
    "sg:orig_category":"Fruit And Groenten Gh",
    "sg:phone":"+31 412 454 647",
    "sg:postcode":"5384 TC",
    "sg:province":"Noord-Brabant",
    "wof:name":"Van Weerdenburg Bv",
    "wof:placetype":"venue"
},
  "geometry": {"coordinates":[5.513191,51.724117],"type":"Point"}
}