{
  "type": "Feature",
  "properties": {
    "iso:country":"NL",
    "sg:address":"Industrieweg 91",
    "sg:city":"Waalwijk",
    "sg:orig_category":"Pleziervaartuigen And Reparatie",
    "sg:phone":"+31 416 337 848",
    "sg:postcode":"5145 PD",
    "sg:province":"North Brabant",
    "wof:name":"Moverbo Watersport Bv",
    "wof:placetype":"venue"
},
  "geometry": {"coordinates":[5.059115,51.705997],"type":"Point"}
}