{
  "type": "Feature",
  "properties": {
    "addr:full":"Broekermolenweg 3 A Putten Gelderland 3882 MG",
    "addr:housenumber":"3 a",
    "addr:postcode":"3882 mg",
    "addr:street":"Broekermolenweg;Gelderland",
    "iso:country":"NL",
    "sg:address":"Broekermolenweg 3 A",
    "sg:city":"Putten",
    "sg:orig_category":"Metaalafval, Schrootrecycling And Sloperijen",
    "sg:phone":"+31 341 360 300",
    "sg:postcode":"3882 MG",
    "sg:province":"Gelderland",
    "wof:name":"Autosloperij G. Pieper",
    "wof:placetype":"venue"
},
  "geometry": {"coordinates":[5.549912,52.249069],"type":"Point"}
}