{
  "type": "Feature",
  "properties": {
    "addr:full":"Julialn 24 Ryswyk Zh South Holland 2283 TB",
    "addr:housenumber":"24;zh",
    "addr:postcode":"2283 tb",
    "addr:street":"Julialn",
    "iso:country":"NL",
    "sg:address":"Julialn 24",
    "sg:city":"Ryswyk Zh",
    "sg:orig_category":"Verenigingsgebouwen",
    "sg:phone":"+31 70 390 4431",
    "sg:postcode":"2283 TB",
    "sg:province":"South Holland",
    "wof:name":"Don Bosco Jeugdcentr",
    "wof:placetype":"venue"
},
  "geometry": {"coordinates":[4.32436,52.037251],"type":"Point"}
}