{
  "type": "Feature",
  "properties": {
    "addr:full":"Achter St Pieter 136 Utrecht Utrecht 3512 HT",
    "addr:housenumber":"136",
    "addr:postcode":"3512 ht",
    "addr:street":"Achter St Pieter",
    "iso:country":"NL",
    "sg:address":"Achter St Pieter 136",
    "sg:city":"Utrecht",
    "sg:orig_category":"Adviesbureaus",
    "sg:phone":"+31 30 233 1037",
    "sg:postcode":"3512 HT",
    "sg:province":"Utrecht",
    "wof:name":"Groebel Bv",
    "wof:placetype":"venue"
},
  "geometry": {"coordinates":[5.12342,52.0914],"type":"Point"}
}