{
  "type": "Feature",
  "properties": {
    "addr:full":"Ruysdaelstraat 1 Haarlem Noord-Holland 2021 EM",
    "addr:housenumber":"1",
    "addr:postcode":"2021 em",
    "addr:street":"Ruysdaelstraat",
    "iso:country":"NL",
    "sg:address":"Ruysdaelstraat 1",
    "sg:city":"Haarlem",
    "sg:orig_category":"Hoger Onderwijs",
    "sg:phone":"+31 23 526 0990",
    "sg:postcode":"2021 EM",
    "sg:province":"Noord-Holland",
    "wof:name":"A.M.F. Van Ruiten",
    "wof:placetype":"venue"
},
  "geometry": {"coordinates":[4.637853,52.391491],"type":"Point"}
}