{
  "type": "Feature",
  "properties": {
    "addr:full":"J Ter Laanplaats 49 Rotterdam Zuid-Holland 3063 RS",
    "addr:housenumber":"49",
    "addr:postcode":"3063 rs",
    "addr:street":"J Ter Laanplaats",
    "iso:country":"NL",
    "sg:address":"J Ter Laanplaats 49",
    "sg:city":"Rotterdam",
    "sg:orig_category":"Adviesbureaus Bedrijfsorganisatie",
    "sg:phone":"+31 10 452 1952",
    "sg:postcode":"3063 RS",
    "sg:province":"Zuid-Holland",
    "wof:name":"Mic-Punt",
    "wof:placetype":"venue"
},
  "geometry": {"coordinates":[4.5217,51.914608],"type":"Point"}
}