{
  "type": "Feature",
  "properties": {
    "addr:full":"Derde Oosterparkstraat 360 Amsterdam Noord-Holland 1092 SE",
    "addr:housenumber":"360",
    "addr:postcode":"1092 se",
    "addr:street":"Derde Oosterparkstraat",
    "iso:country":"NL",
    "sg:address":"Derde Oosterparkstraat 360",
    "sg:city":"Amsterdam",
    "sg:classifiers":[
        {
            "category":"Education",
            "subcategory":"Preschool",
            "type":"Public Place"
        }
    ],
    "sg:phone":"+31 20 665 5394",
    "sg:postcode":"1092 SE",
    "sg:province":"Noord-Holland",
    "sg:tags":[
        "kleuteronderwijs",
        "basis-"
    ],
    "wof:name":"Openbare Basisschool Linnaeus",
    "wof:placetype":"venue"
},
  "geometry": {"coordinates":[4.925731,52.358753],"type":"Point"}
}