{
  "type": "Feature",
  "properties": {
    "addr:full":"Kon Lodewykln 748 Apeldoorn Gelderland 7314 GX",
    "addr:housenumber":"748",
    "addr:postcode":"7314 gx",
    "addr:street":"Kon;Gelderland",
    "iso:country":"NL",
    "sg:address":"Kon Lodewykln 748",
    "sg:city":"Apeldoorn",
    "sg:orig_category":"Organisatiebureaus",
    "sg:phone":"+31 55 534 4071",
    "sg:postcode":"7314 GX",
    "sg:province":"Gelderland",
    "wof:name":"Discovery-It",
    "wof:placetype":"venue"
},
  "geometry": {"coordinates":[5.9467592239,52.2154846191],"type":"Point"}
}