{
  "type": "Feature",
  "properties": {
    "iso:country":"NL",
    "sg:address":"Nieuwstraat 29",
    "sg:city":"Purmerend",
    "sg:orig_category":"Juweliers",
    "sg:phone":"+31 299 423 579",
    "sg:postcode":"1441 CK",
    "sg:province":"North Holland",
    "wof:name":"Firma Juwelier Muis",
    "wof:placetype":"venue"
},
  "geometry": {"coordinates":[4.944689,52.508614],"type":"Point"}
}