{
  "type": "Feature",
  "properties": {
    "addr:full":"Van Busselstraat 9 Mierlo Noord-Brabant 5731 NA",
    "addr:housenumber":"9",
    "addr:postcode":"5731 na",
    "addr:street":"Van Busselstraat",
    "iso:country":"NL",
    "sg:address":"Van Busselstraat 9",
    "sg:city":"Mierlo",
    "sg:orig_category":"Medische And Orthopedische Artikelen",
    "sg:phone":"+31 492 666 077",
    "sg:postcode":"5731 NA",
    "sg:province":"Noord-Brabant",
    "wof:name":"Mubarik",
    "wof:placetype":"venue"
},
  "geometry": {"coordinates":[5.627212,51.440041],"type":"Point"}
}