{
  "type": "Feature",
  "properties": {
    "addr:full":"Amsterdamsewg 45-47 Amersfoort Utrecht 3812 RP",
    "addr:housenumber":"45-47",
    "addr:postcode":"3812 rp",
    "iso:country":"NL",
    "sg:address":"Amsterdamsewg 45-47",
    "sg:city":"Amersfoort",
    "sg:orig_category":"Woninginrichting",
    "sg:phone":"+31 33 462 7782",
    "sg:postcode":"3812 RP",
    "sg:province":"Utrecht",
    "wof:name":"Kwantum",
    "wof:placetype":"venue"
},
  "geometry": {"coordinates":[5.3673820496,52.1636924744],"type":"Point"}
}