{
  "type": "Feature",
  "properties": {
    "addr:full":"Diedenwg 92 Ede Gld Gelderland 6717 KV",
    "addr:housenumber":"92",
    "addr:postcode":"6717 kv",
    "addr:street":"Diedenwg;Gld Gelderland",
    "iso:country":"NL",
    "sg:address":"Diedenwg 92",
    "sg:city":"Ede Gld",
    "sg:orig_category":"Verbouwingen",
    "sg:phone":"+31 318 620 818",
    "sg:postcode":"6717 KV",
    "sg:province":"Gelderland",
    "sg:website":"http://www.hsvandenbrink.nl",
    "wof:name":"Brink Bv, Aannemersbedr H S V/D",
    "wof:placetype":"venue"
},
  "geometry": {"coordinates":[5.668924,52.021439],"type":"Point"}
}