{
  "type": "Feature",
  "properties": {
    "iso:country":"NL",
    "sg:address":"Diedenwg 92",
    "sg:city":"Ede Gld",
    "sg:orig_category":"Verbouwingen",
    "sg:phone":"+31 318 620 818",
    "sg:postcode":"6717 KV",
    "sg:province":"Gelderland",
    "sg:website":"http://www.hsvandenbrink.nl",
    "wof:name":"Brink Bv, Aannemersbedr H S V/D",
    "wof:placetype":"venue"
},
  "geometry": {"coordinates":[5.668924,52.021439],"type":"Point"}
}