{
  "type": "Feature",
  "properties": {
    "addr:full":"C Stulemeyerwg 3 Tilburg Noord-Brabant 5026 RS",
    "addr:housenumber":"3",
    "addr:postcode":"5026 rs",
    "iso:country":"NL",
    "sg:address":"C Stulemeyerwg 3",
    "sg:city":"Tilburg",
    "sg:orig_category":"Kantoorbenodigdheden - Fabrieken En Groothandel",
    "sg:phone":"+31 13 467 0270",
    "sg:postcode":"5026 RS",
    "sg:province":"Noord-Brabant",
    "wof:name":"Office Centre",
    "wof:placetype":"venue"
},
  "geometry": {"coordinates":[5.0574650764,51.5430412292],"type":"Point"}
}