{
  "type": "Feature",
  "properties": {
    "addr:full":"Oude Hollewg 5 Berg En Dal Gelderland 6572 AA",
    "addr:housenumber":"5",
    "addr:postcode":"6572 aa",
    "addr:street":"Oude Hollewg",
    "iso:country":"NL",
    "sg:address":"Oude Hollewg 5",
    "sg:city":"Berg En Dal",
    "sg:classifiers":[
        {
            "category":"Travel",
            "subcategory":"Hotels & Motels",
            "type":"Entertainment"
        }
    ],
    "sg:phone":"+31 24 684 2000",
    "sg:postcode":"6572 AA",
    "sg:province":"Gelderland",
    "sg:website":"http://www.gtvalmonte.nl",
    "wof:name":"Golden Tulip Hotel Val-Monte",
    "wof:placetype":"venue"
},
  "geometry": {"coordinates":[5.915589,51.824684],"type":"Point"}
}