{
  "type": "Feature",
  "properties": {
    "addr:full":"Oranjelaan 32 Wijhe Overijssel 8131 DD",
    "addr:housenumber":"32",
    "addr:postcode":"8131 dd",
    "addr:street":"Oranjelaan",
    "iso:country":"NL",
    "sg:address":"Oranjelaan 32",
    "sg:city":"Wijhe",
    "sg:orig_category":"Diverse Grafische Activiteiten",
    "sg:phone":"+31 570 524 760",
    "sg:postcode":"8131 DD",
    "sg:province":"Overijssel",
    "wof:name":"I.C.B. Nieuwenhuis",
    "wof:placetype":"venue"
},
  "geometry": {"coordinates":[6.135354,52.392841],"type":"Point"}
}