{
  "type": "Feature",
  "properties": {
    "addr:full":"Postbus 561 Oss Noord-Brabant 5340 AN",
    "addr:housenumber":"561",
    "addr:postcode":"5340 an",
    "addr:street":"Postbus",
    "iso:country":"NL",
    "sg:address":"Postbus 561",
    "sg:city":"Oss",
    "sg:orig_category":"Scholen Voor Basisonderwijs",
    "sg:phone":"+31 412 633 625",
    "sg:postcode":"5340 AN",
    "sg:province":"Noord-Brabant",
    "wof:name":"Bolster Openb, De",
    "wof:placetype":"venue"
},
  "geometry": {"coordinates":[-77.235214,38.312599],"type":"Point"}
}