{
  "type": "Feature",
  "properties": {
    "addr:full":"Grevingaheerd 6 Groningen Groningen 9737 SB",
    "addr:housenumber":"6",
    "addr:postcode":"9737 sb",
    "addr:street":"Grevingaheerd",
    "iso:country":"NL",
    "sg:address":"Grevingaheerd 6",
    "sg:city":"Groningen",
    "sg:orig_category":"Psychologen",
    "sg:phone":"+31 50 549 1543",
    "sg:postcode":"9737 SB",
    "sg:province":"Groningen",
    "wof:name":"Egmond, Drs A W",
    "wof:placetype":"venue"
},
  "geometry": {"coordinates":[6.591753,53.247276],"type":"Point"}
}