{
  "type": "Feature",
  "properties": {
    "addr:full":"Muurhuizen 47B Amersfoort Utrecht 3811 ED",
    "addr:housenumber":"47b",
    "addr:postcode":"3811 ed",
    "addr:street":"Muurhuizen",
    "iso:country":"NL",
    "sg:address":"Muurhuizen 47B",
    "sg:city":"Amersfoort",
    "sg:orig_category":"Adviesbureaus Bedrijfsorganisatie",
    "sg:phone":"+31 33 465 3960",
    "sg:postcode":"3811 ED",
    "sg:province":"Utrecht",
    "wof:name":"Leidraad",
    "wof:placetype":"venue"
},
  "geometry": {"coordinates":[5.392578,52.155556],"type":"Point"}
}