{
  "type": "Feature",
  "properties": {
    "iso:country":"NL",
    "sg:address":"Denekamperwg 40C",
    "sg:city":"Geesteren Ov",
    "sg:orig_category":"Autoschade- Herstelbedrijven",
    "sg:phone":"+31 546 631 795",
    "sg:postcode":"7678 SZ",
    "sg:province":"Overijssel",
    "wof:name":"Twentheland",
    "wof:placetype":"venue"
},
  "geometry": {"coordinates":[6.756144,52.42535],"type":"Point"}
}