{
  "type": "Feature",
  "properties": {
    "iso:country":"NL",
    "sg:address":"Postbus 7005",
    "sg:city":"Klaaswaal",
    "sg:orig_category":"Notarissen",
    "sg:phone":"+31 186 571 166",
    "sg:postcode":"3286 ZG",
    "sg:province":"Gelderland",
    "wof:name":"Notaris Mr. H. Borgers",
    "wof:placetype":"venue"
},
  "geometry": {"coordinates":[4.447235,51.768005],"type":"Point"}
}