{
  "type": "Feature",
  "properties": {
    "addr:full":"Grafterbaan 29 Graft North Holland 1484 EC",
    "addr:housenumber":"29",
    "addr:postcode":"1484 ec",
    "addr:street":"Grafterbaan",
    "iso:country":"NL",
    "sg:address":"Grafterbaan 29",
    "sg:city":"Graft",
    "sg:orig_category":"Scholen Voor Basisonderwijs",
    "sg:phone":"+31 299 673 148",
    "sg:postcode":"1484 EC",
    "sg:province":"North Holland",
    "wof:name":"Baanbreker Kath, De",
    "wof:placetype":"venue"
},
  "geometry": {"coordinates":[4.838089,52.560398],"type":"Point"}
}