{
  "type": "Feature",
  "properties": {
    "addr:full":"Burg Knappertln 154 Schiedam Zuid-Holland 3117 BE",
    "addr:housenumber":"154",
    "addr:postcode":"3117",
    "addr:street":"Burg",
    "iso:country":"NL",
    "sg:address":"Burg Knappertln 154",
    "sg:city":"Schiedam",
    "sg:orig_category":"Artsen - Huisartsen",
    "sg:phone":"+31 10 426 9880",
    "sg:postcode":"3117 BE",
    "sg:province":"Zuid-Holland",
    "wof:name":"Valk, P V",
    "wof:placetype":"venue"
},
  "geometry": {"coordinates":[4.39816,51.918472],"type":"Point"}
}