{
  "type": "Feature",
  "properties": {
    "addr:full":"Schaepmanlaan 16 Vlijmen North Brabant 5252 AV",
    "addr:housenumber":"16",
    "addr:postcode":"5252 av",
    "addr:street":"Schaepmanlaan",
    "iso:country":"NL",
    "sg:address":"Schaepmanlaan 16",
    "sg:city":"Vlijmen",
    "sg:orig_category":"Bedrijfs- And Managementsconsultants",
    "sg:phone":"+31 73 511 7292",
    "sg:postcode":"5252 AV",
    "sg:province":"North Brabant",
    "wof:name":"Tops Bouwplanontwikkeling Vof",
    "wof:placetype":"venue"
},
  "geometry": {"coordinates":[5.206474,51.698879],"type":"Point"}
}