{
  "type": "Feature",
  "properties": {
    "addr:full":"Hindersteinstr 65 Rotterdam Zuid-Holland 3077 DA",
    "addr:housenumber":"65",
    "addr:postcode":"3077 da",
    "addr:street":"Hindersteinstr",
    "iso:country":"NL",
    "sg:address":"Hindersteinstr 65",
    "sg:city":"Rotterdam",
    "sg:orig_category":"Hondenscholen",
    "sg:phone":"+31 10 482 2194",
    "sg:postcode":"3077 DA",
    "sg:province":"Zuid-Holland",
    "wof:name":"Oase, De",
    "wof:placetype":"venue"
},
  "geometry": {"coordinates":[4.567075,51.886311],"type":"Point"}
}