{
  "type": "Feature",
  "properties": {
    "iso:country":"NL",
    "sg:address":"Phebensstr 1",
    "sg:city":"Groningen",
    "sg:orig_category":"Waterleidingbedrijven",
    "sg:phone":"+31 50 368 8688",
    "sg:postcode":"9711 BL",
    "sg:province":"Groningen",
    "wof:name":"Waterbedrijf Groningen",
    "wof:placetype":"venue"
},
  "geometry": {"coordinates":[6.5679750443,53.2136955261],"type":"Point"}
}