{
  "type": "Feature",
  "properties": {
    "addr:full":"Bemuurde Weerd Oz 67Bis Utrecht Utrecht 3514 AT",
    "addr:housenumber":"67bis",
    "addr:postcode":"3514",
    "addr:street":"Bemuurde Weerd Oz",
    "iso:country":"NL",
    "sg:address":"Bemuurde Weerd Oz 67Bis",
    "sg:city":"Utrecht",
    "sg:orig_category":"Adviesbureaus Bedrijfsorganisatie",
    "sg:phone":"+31 30 272 2341",
    "sg:postcode":"3514 AT",
    "sg:province":"Utrecht",
    "wof:name":"Elementary",
    "wof:placetype":"venue"
},
  "geometry": {"coordinates":[5.113354,52.099609],"type":"Point"}
}