{
  "type": "Feature",
  "properties": {
    "iso:country":"NL",
    "sg:address":"Van Der Hoopstraat 129",
    "sg:city":"Amsterdam",
    "sg:classifiers":[
        {
            "category":"Fast Food",
            "type":"Food & Drink"
        }
    ],
    "sg:phone":"+31 20 684 0065",
    "sg:postcode":"1051 VE",
    "sg:province":"Noord-Holland",
    "sg:tags":[
        "afhaal",
        "restaurant"
    ],
    "wof:name":"Snackbar Hanny",
    "wof:placetype":"venue"
},
  "geometry": {"coordinates":[4.870324,52.383945],"type":"Point"}
}