{
  "type": "Feature",
  "properties": {
    "addr:full":"Dorpsstraat 75 Putten Gelderland 3881 BB",
    "addr:housenumber":"75",
    "addr:postcode":"3881 bb",
    "addr:street":"Dorpsstraat;Gelderland",
    "iso:country":"NL",
    "sg:address":"Dorpsstraat 75",
    "sg:city":"Putten",
    "sg:orig_category":"Kappers",
    "sg:phone":"+31 341 360 100",
    "sg:postcode":"3881 BB",
    "sg:province":"Gelderland",
    "wof:name":"Bert Reuvers",
    "wof:placetype":"venue"
},
  "geometry": {"coordinates":[5.6025261879,52.260055542],"type":"Point"}
}