{
  "type": "Feature",
  "properties": {
    "iso:country":"NL",
    "sg:address":"Molenweg 22",
    "sg:city":"Oosterbeek",
    "sg:orig_category":"Loodgieterswerk, Verwarming And Sanitaire Installaties",
    "sg:phone":"+31 26 334 0095",
    "sg:postcode":"6862 HP",
    "sg:province":"Gelderland",
    "wof:name":"T.J. Ooms",
    "wof:placetype":"venue"
},
  "geometry": {"coordinates":[5.849961,51.984951],"type":"Point"}
}