{
  "type": "Feature",
  "properties": {
    "addr:full":"Jacob Grootstraat 26 Middenbeemster Noord-Holland 1462 XH",
    "addr:housenumber":"26",
    "addr:postcode":"1462 xh",
    "addr:street":"Jacob Grootstraat",
    "iso:country":"NL",
    "sg:address":"Jacob Grootstraat 26",
    "sg:city":"Middenbeemster",
    "sg:orig_category":"Drukkerijen And Copyshops",
    "sg:phone":"+31 299 684 540",
    "sg:postcode":"1462 XH",
    "sg:province":"Noord-Holland",
    "wof:name":"Duplo Druk Van Braam",
    "wof:placetype":"venue"
},
  "geometry": {"coordinates":[4.908859,52.551334],"type":"Point"}
}