{
  "type": "Feature",
  "properties": {
    "addr:full":"Vrijzicht 81 Amsterdam Noord-Holland 1068 CG",
    "addr:housenumber":"81",
    "addr:postcode":"1068 cg",
    "addr:street":"Vrijzicht",
    "iso:country":"NL",
    "sg:address":"Vrijzicht 81",
    "sg:city":"Amsterdam",
    "sg:orig_category":"Autokeuringen",
    "sg:phone":"+31 20 610 4555",
    "sg:postcode":"1068 CG",
    "sg:province":"Noord-Holland",
    "wof:name":"European Truck Brokers",
    "wof:placetype":"venue"
},
  "geometry": {"coordinates":[4.808134,52.362663],"type":"Point"}
}