{
  "type": "Feature",
  "properties": {
    "addr:full":"Jekerschans 10 Maastricht Limburg 6212 GJ",
    "addr:housenumber":"10",
    "addr:postcode":"6212 gj",
    "addr:street":"Jekerschans",
    "iso:country":"NL",
    "sg:address":"Jekerschans 10",
    "sg:city":"Maastricht",
    "sg:orig_category":"Paramedische Behandelingen",
    "sg:phone":"+31 43 321 8290",
    "sg:postcode":"6212 GJ",
    "sg:province":"Limburg",
    "wof:name":"H.M.G. Jongen",
    "wof:placetype":"venue"
},
  "geometry": {"coordinates":[5.685536,50.839558],"type":"Point"}
}