{
  "type": "Feature",
  "properties": {
    "iso:country":"NL",
    "sg:address":"Achter De Hoven 23",
    "sg:city":"Leeuwarden",
    "sg:orig_category":"Boekenuitgeverijen",
    "sg:phone":"+31 58 213 3048",
    "sg:postcode":"8933 AG",
    "sg:province":"Provincie Friesland",
    "wof:name":"Stichting It Fryske Boek",
    "wof:placetype":"venue"
},
  "geometry": {"coordinates":[5.801198,53.198231],"type":"Point"}
}