{
  "type": "Feature",
  "properties": {
    "addr:full":"Gorechtkd 8 Groningen Groningen 9713 CA",
    "addr:housenumber":"8",
    "addr:postcode":"9713 ca",
    "addr:street":"Gorechtkd",
    "iso:country":"NL",
    "sg:address":"Gorechtkd 8",
    "sg:city":"Groningen",
    "sg:orig_category":"Psychologen",
    "sg:phone":"+31 50 309 3944",
    "sg:postcode":"9713 CA",
    "sg:province":"Groningen",
    "wof:name":"Veldman, Mw Drs I C M",
    "wof:placetype":"venue"
},
  "geometry": {"coordinates":[6.580731,53.222385],"type":"Point"}
}