{
  "type": "Feature",
  "properties": {
    "addr:full":"Prof E M Meyersln 5 Amstelveen North Holland 1183 AV",
    "addr:housenumber":"5",
    "addr:postcode":"1183 av",
    "addr:street":"Prof",
    "iso:country":"NL",
    "sg:address":"Prof E M Meyersln 5",
    "sg:city":"Amstelveen",
    "sg:orig_category":"Adviesbureaus Automatisering",
    "sg:phone":"+31 20 543 3001",
    "sg:postcode":"1183 AV",
    "sg:province":"North Holland",
    "sg:website":"http://www.innovact.nl",
    "wof:name":"Wwb Innovact Bv",
    "wof:placetype":"venue"
},
  "geometry": {"coordinates":[4.875262,52.317711],"type":"Point"}
}