{
  "type": "Feature",
  "properties": {
    "iso:country":"NL",
    "sg:address":"Vt Hoffstr 12",
    "sg:city":"Barendrecht",
    "sg:orig_category":"Woninginrichting",
    "sg:phone":"+31 10 479 7992",
    "sg:postcode":"2991 XP",
    "sg:province":"South Holland",
    "wof:name":"Kwantum",
    "wof:placetype":"venue"
},
  "geometry": {"coordinates":[4.5460429192,51.8704414368],"type":"Point"}
}