{
  "type": "Feature",
  "properties": {
    "addr:full":"Overysselhaven 20 Nieuwegein Utrecht 3433 PH",
    "addr:housenumber":"20",
    "addr:postcode":"3433",
    "addr:street":"Overysselhaven",
    "iso:country":"NL",
    "sg:address":"Overysselhaven 20",
    "sg:city":"Nieuwegein",
    "sg:orig_category":"Drukkerijen",
    "sg:phone":"+31 30 608 1737",
    "sg:postcode":"3433 PH",
    "sg:province":"Utrecht",
    "sg:website":"http://www.hentenaar-boek.nl",
    "wof:name":"Hentenaar Boek Bv",
    "wof:placetype":"venue"
},
  "geometry": {"coordinates":[5.104565,52.020672],"type":"Point"}
}