{
  "type": "Feature",
  "properties": {
    "addr:full":"Bloemstr 128 Amsterdam Noord-Holland 1016 LH",
    "addr:housenumber":"128",
    "addr:postcode":"1016 lh",
    "iso:country":"NL",
    "sg:address":"Bloemstr 128",
    "sg:city":"Amsterdam",
    "sg:orig_category":"Beeldende Kunstenaars",
    "sg:phone":"+31 20 624 4825",
    "sg:postcode":"1016 LH",
    "sg:province":"Noord-Holland",
    "wof:name":"Roodenburg-Slagter",
    "wof:placetype":"venue"
},
  "geometry": {"coordinates":[4.879141,52.373795],"type":"Point"}
}