{
  "type": "Feature",
  "properties": {
    "addr:full":"Gendringsewg 19 Aalten Gelderland 7122 MJ",
    "addr:housenumber":"19",
    "addr:postcode":"7122 mj",
    "addr:street":"Gendringsewg;Gelderland",
    "iso:country":"NL",
    "sg:address":"Gendringsewg 19",
    "sg:city":"Aalten",
    "sg:orig_category":"Heftrucks",
    "sg:phone":"+31 543 461 508",
    "sg:postcode":"7122 MJ",
    "sg:province":"Gelderland",
    "wof:name":"Geven",
    "wof:placetype":"venue"
},
  "geometry": {"coordinates":[6.525844,51.923035],"type":"Point"}
}