{
  "type": "Feature",
  "properties": {
    "iso:country":"NL",
    "sg:address":"Abelenlaan 6",
    "sg:city":"Ouderkerk A/D Ijssel",
    "sg:orig_category":"Banken And Kredietinstellingen",
    "sg:phone":"+31 180 682 155",
    "sg:postcode":"2935 SB",
    "sg:province":"South Holland",
    "wof:name":"Rabobank",
    "wof:placetype":"venue"
},
  "geometry": {"coordinates":[4.634057,51.933838],"type":"Point"}
}