{
  "type": "Feature",
  "properties": {
    "addr:full":"Akerstr 53 Kerkrade Limburg 6466 HB",
    "addr:housenumber":"53",
    "addr:postcode":"6466 hb",
    "addr:street":"Akerstr",
    "iso:country":"NL",
    "sg:address":"Akerstr 53",
    "sg:city":"Kerkrade",
    "sg:orig_category":"Honden- En Kattentrimsalons",
    "sg:phone":"+31 45 542 1590",
    "sg:postcode":"6466 HB",
    "sg:province":"Limburg",
    "wof:name":"Doggie'S Paradise",
    "wof:placetype":"venue"
},
  "geometry": {"coordinates":[6.026004,50.857269],"type":"Point"}
}