{
  "type": "Feature",
  "properties": {
    "iso:country":"NL",
    "sg:address":"Korteweide 19",
    "sg:city":"Zuid-Scharwoude",
    "sg:orig_category":"Parfum And Cosmetica Gh",
    "sg:phone":"+31 226 314 107",
    "sg:postcode":"1722 VA",
    "sg:province":"Noord-Holland",
    "wof:name":"Reflex De Graaf",
    "wof:placetype":"venue"
},
  "geometry": {"coordinates":[-79.771446,38.003349],"type":"Point"}
}