{
  "type": "Feature",
  "properties": {
    "addr:full":"Patersstr 13 Venray Limburg 5801 AT",
    "addr:housenumber":"13",
    "addr:postcode":"5801",
    "addr:street":"Patersstr",
    "iso:country":"NL",
    "sg:address":"Patersstr 13",
    "sg:city":"Venray",
    "sg:orig_category":"Banken",
    "sg:phone":"+31 478 559 500",
    "sg:postcode":"5801 AT",
    "sg:province":"Limburg",
    "wof:name":"Fortis",
    "wof:placetype":"venue"
},
  "geometry": {"coordinates":[5.97585,51.523666],"type":"Point"}
}