{
  "type": "Feature",
  "properties": {
    "addr:full":"Data 12 Coevorden Drenthe 7741 MG",
    "addr:housenumber":"12",
    "addr:postcode":"7741 mg",
    "addr:street":"Data",
    "iso:country":"NL",
    "sg:address":"Data 12",
    "sg:city":"Coevorden",
    "sg:orig_category":"Oud Metaal",
    "sg:phone":"+31 524 511 664",
    "sg:postcode":"7741 MG",
    "sg:province":"Drenthe",
    "wof:name":"Mereco Vof",
    "wof:placetype":"venue"
},
  "geometry": {"coordinates":[6.7291121483,52.6626663208],"type":"Point"}
}