{
  "type": "Feature",
  "properties": {
    "addr:full":"Nieuwkuijksestraat 97 Nieuwkuijk Noord-Brabant 5253 AE",
    "addr:housenumber":"97",
    "addr:postcode":"5253 ae",
    "addr:street":"Nieuwkuijksestraat",
    "iso:country":"NL",
    "sg:address":"Nieuwkuijksestraat 97",
    "sg:city":"Nieuwkuijk",
    "sg:orig_category":"Sportprijzen, Postzegels And Munten",
    "sg:phone":"+31 73 511 4293",
    "sg:postcode":"5253 AE",
    "sg:province":"Noord-Brabant",
    "wof:name":"Sportprijzen Nieuwkuijk",
    "wof:placetype":"venue"
},
  "geometry": {"coordinates":[5.177778,51.690441],"type":"Point"}
}