{
  "type": "Feature",
  "properties": {
    "addr:full":"Piccolostr 2 Duiven Gelderland 6922 KP",
    "addr:housenumber":"2",
    "addr:postcode":"6922 kp",
    "addr:street":"Piccolostr;Gelderland",
    "iso:country":"NL",
    "sg:address":"Piccolostr 2",
    "sg:city":"Duiven",
    "sg:orig_category":"Kantoor- En Secretariaatsservice",
    "sg:phone":"+31 316 281 523",
    "sg:postcode":"6922 KP",
    "sg:province":"Gelderland",
    "wof:name":"Prodesse",
    "wof:placetype":"venue"
},
  "geometry": {"coordinates":[5.9970850945,51.9437408447],"type":"Point"}
}