{
  "type": "Feature",
  "properties": {
    "iso:country":"NL",
    "sg:address":"P Heinstr 14",
    "sg:city":"Alphen Aan Den Ryn",
    "sg:classifiers":[
        {
            "category":"Building & Trades",
            "subcategory":"Electrical",
            "type":"Services"
        }
    ],
    "sg:phone":"+31 172 492 594",
    "sg:postcode":"2404 AK",
    "sg:province":"Zuid-Holland",
    "sg:tags":[
        "distributor"
    ],
    "wof:name":"Redegeld",
    "wof:placetype":"venue"
},
  "geometry": {"coordinates":[4.658921,52.12719],"type":"Point"}
}