{
  "type": "Feature",
  "properties": {
    "iso:country":"NL",
    "sg:address":"De Wierst 160",
    "sg:city":"Emmen",
    "sg:orig_category":"Verplichte Sociale Verzekeringen",
    "sg:phone":"+31 33 465 4545",
    "sg:postcode":"7811 BV",
    "sg:province":"Drenthe",
    "wof:name":"Anova Winkel Emmen",
    "wof:placetype":"venue"
},
  "geometry": {"coordinates":[6.8964,52.782017],"type":"Point"}
}