{
  "type": "Feature",
  "properties": {
    "addr:full":"Westerwijk 62 Dalen Drenthe 7751 CP",
    "addr:housenumber":"62",
    "addr:postcode":"7751 cp",
    "addr:street":"Westerwijk",
    "iso:country":"NL",
    "sg:address":"Westerwijk 62",
    "sg:city":"Dalen",
    "sg:orig_category":"Alternatieve Geneeskunde",
    "sg:phone":"+31 524 552 742",
    "sg:postcode":"7751 CP",
    "sg:province":"Drenthe",
    "wof:name":"Dreamline (N.F.E. Wiebing-Wagtendonk)",
    "wof:placetype":"venue"
},
  "geometry": {"coordinates":[6.751452,52.701874],"type":"Point"}
}