{
  "type": "Feature",
  "properties": {
    "iso:country":"NL",
    "sg:address":"Pandora 8",
    "sg:city":"Amstelveen",
    "sg:classifiers":[
        {
            "category":"Education",
            "subcategory":"Preschool",
            "type":"Public Place"
        }
    ],
    "sg:phone":"+31 20 641 9271",
    "sg:postcode":"1183 KK",
    "sg:province":"Noord-Holland",
    "sg:tags":[
        "kleuteronderwijs",
        "basis-"
    ],
    "wof:name":"Joost Van Den Vondelschool",
    "wof:placetype":"venue"
},
  "geometry": {"coordinates":[4.878849,52.302437],"type":"Point"}
}