{
  "type": "Feature",
  "properties": {
    "addr:full":"Bedryvenpk Twente 144 Almelo Overijssel 7602 KE",
    "addr:housenumber":"144",
    "addr:postcode":"7602 ke",
    "addr:street":"Twente",
    "iso:country":"NL",
    "sg:address":"Bedryvenpk Twente 144",
    "sg:city":"Almelo",
    "sg:orig_category":"Plafonds",
    "sg:phone":"+31 546 578 292",
    "sg:postcode":"7602 KE",
    "sg:province":"Overijssel",
    "wof:name":"Gerrit Smit Systeemplafonds Bv",
    "wof:placetype":"venue"
},
  "geometry": {"coordinates":[6.620747,52.379948],"type":"Point"}
}