{
  "type": "Feature",
  "properties": {
    "addr:full":"Simpsonstr 16 Sittard Limburg 6135 CT",
    "addr:housenumber":"16",
    "addr:postcode":"6135 ct",
    "addr:street":"Simpsonstr",
    "iso:country":"NL",
    "sg:address":"Simpsonstr 16",
    "sg:city":"Sittard",
    "sg:orig_category":"Beveiliging",
    "sg:phone":"+31 46 451 8833",
    "sg:postcode":"6135 CT",
    "sg:province":"Limburg",
    "wof:name":"Rongen Project Montage Dienst",
    "wof:placetype":"venue"
},
  "geometry": {"coordinates":[5.850994,51.008236],"type":"Point"}
}