{
  "type": "Feature",
  "properties": {
    "addr:full":"Visstraat 57 'S Hertogenbosch North Brabant 5211 DM",
    "addr:housenumber":"57",
    "addr:postcode":"5211 dm",
    "addr:street":"Visstraat;' S Hertogenbosch",
    "iso:country":"NL",
    "sg:address":"Visstraat 57",
    "sg:city":"'S Hertogenbosch",
    "sg:orig_category":"Werving And Selectie Van Tijdelijk Personeel And Uitzendkantoren",
    "sg:phone":"+31 73 691 9100",
    "sg:postcode":"5211 DM",
    "sg:province":"North Brabant",
    "wof:name":"Ad Rem",
    "wof:placetype":"venue"
},
  "geometry": {"coordinates":[5.2993268967,51.6904830933],"type":"Point"}
}