{
  "type": "Feature",
  "properties": {
    "iso:country":"NL",
    "sg:address":"Baarsjeswg 283",
    "sg:city":"Amsterdam",
    "sg:classifiers":[
        {
            "category":"Retail",
            "subcategory":"Auto Repair",
            "type":"Services"
        }
    ],
    "sg:phone":"+31 20 685 4087",
    "sg:postcode":"1058 AE",
    "sg:province":"North Holland",
    "sg:tags":[
        "garage"
    ],
    "wof:name":"Kemmer, L",
    "wof:placetype":"venue"
},
  "geometry": {"coordinates":[4.855928,52.359959],"type":"Point"}
}