{
  "type": "Feature",
  "properties": {
    "addr:full":"Operaplein 17 Apeldoorn Gelderland 7323 EK",
    "addr:housenumber":"17",
    "addr:postcode":"7323 ek",
    "addr:street":"Operaplein;Gelderland",
    "iso:country":"NL",
    "sg:address":"Operaplein 17",
    "sg:city":"Apeldoorn",
    "sg:orig_category":"Supermarkten",
    "sg:phone":"+31 55 366 7758",
    "sg:postcode":"7323 EK",
    "sg:province":"Gelderland",
    "wof:name":"Edah",
    "wof:placetype":"venue"
},
  "geometry": {"coordinates":[5.98576,52.228767],"type":"Point"}
}