{
  "type": "Feature",
  "properties": {
    "iso:country":"NL",
    "sg:address":"Mandenmakerstr 17A",
    "sg:city":"Ridderkerk",
    "sg:classifiers":[
        {
            "category":"Shopping",
            "subcategory":"Gifts & Souvenirs",
            "type":"Retail Goods"
        }
    ],
    "sg:phone":"+31 180 487 275",
    "sg:postcode":"2984 AS",
    "sg:province":"South Holland",
    "sg:tags":[
        "wens-",
        "en",
        "prentbriefkaarten"
    ],
    "sg:website":"http://www.marant-cards.com",
    "wof:name":"Marant Cards Distribution",
    "wof:placetype":"venue"
},
  "geometry": {"coordinates":[4.6115407944,51.8779830933],"type":"Point"}
}