{
  "type": "Feature",
  "properties": {
    "iso:country":"NL",
    "sg:address":"Nunspeterwg 17",
    "sg:city":"Elburg",
    "sg:orig_category":"Adviesbureaus Verzekeringen",
    "sg:phone":"+31 525 686 468",
    "sg:postcode":"8081 BV",
    "sg:province":"Gelderland",
    "wof:name":"Diamant",
    "wof:placetype":"venue"
},
  "geometry": {"coordinates":[5.832172,52.444416],"type":"Point"}
}