{
  "type": "Feature",
  "properties": {
    "addr:full":"Hendrik Van Viandenstraat 37 Amersfoort Utrecht 3817 AA",
    "addr:housenumber":"37",
    "addr:postcode":"3817 aa",
    "addr:street":"Hendrik Van Viandenstraat",
    "iso:country":"NL",
    "sg:address":"Hendrik Van Viandenstraat 37",
    "sg:city":"Amersfoort",
    "sg:orig_category":"Verzekeringen",
    "sg:phone":"+31 33 461 4545",
    "sg:postcode":"3817 AA",
    "sg:province":"Utrecht",
    "wof:name":"Assurantiekantoor Visser",
    "wof:placetype":"venue"
},
  "geometry": {"coordinates":[5.391547,52.151169],"type":"Point"}
}