{
  "type": "Feature",
  "properties": {
    "addr:full":"Plein 1945 5 Ymuiden Georgia 1971 GA",
    "addr:housenumber":"5",
    "addr:postcode":"1971 ga",
    "addr:street":"Plein 1945;Georgia",
    "iso:country":"NL",
    "sg:address":"Plein 1945 5",
    "sg:city":"Ymuiden",
    "sg:orig_category":"Opticiens",
    "sg:phone":"+31 255 510 062",
    "sg:postcode":"1971 GA",
    "sg:province":"Georgia",
    "sg:website":"http://www.kosterbrillen.nl",
    "wof:name":"Koster Brillen Rvo",
    "wof:placetype":"venue"
},
  "geometry": {"coordinates":[-83.2229309082,32.6781311035],"type":"Point"}
}