{
  "type": "Feature",
  "properties": {
    "addr:full":"Heerenweg 212 Heiloo Noord-Holland 1851 KZ",
    "addr:housenumber":"212",
    "addr:postcode":"1851 kz",
    "addr:street":"Heerenweg",
    "iso:country":"NL",
    "sg:address":"Heerenweg 212",
    "sg:city":"Heiloo",
    "sg:orig_category":"Boekhouders",
    "sg:phone":"+31 72 533 9419",
    "sg:postcode":"1851 KZ",
    "sg:province":"Noord-Holland",
    "wof:name":"Administratiekantoor B. Bosma",
    "wof:placetype":"venue"
},
  "geometry": {"coordinates":[4.698915,52.597099],"type":"Point"}
}