{
  "type": "Feature",
  "properties": {
    "addr:full":"Mezenln 19 Bussum Noord-Holland 1403 BR",
    "addr:housenumber":"19",
    "addr:postcode":"1403 br",
    "addr:street":"Mezenln",
    "iso:country":"NL",
    "sg:address":"Mezenln 19",
    "sg:city":"Bussum",
    "sg:classifiers":[
        {
            "category":"Real Estate",
            "subcategory":"Real Estate Operator",
            "type":"Services"
        }
    ],
    "sg:phone":"+31 35 691 2153",
    "sg:postcode":"1403 BR",
    "sg:province":"Noord-Holland",
    "sg:tags":[
        "appartementen",
        "en",
        "flat"
    ],
    "wof:name":"Gooise Warande Ua, De",
    "wof:placetype":"venue"
},
  "geometry": {"coordinates":[5.191611,52.271751],"type":"Point"}
}