{
  "type": "Feature",
  "properties": {
    "addr:full":"Axelsestraat 23 Terneuzen Zeeland 4537 AB",
    "addr:housenumber":"23",
    "addr:postcode":"4537 ab",
    "addr:street":"Axelsestraat",
    "iso:country":"NL",
    "sg:address":"Axelsestraat 23",
    "sg:city":"Terneuzen",
    "sg:classifiers":[
        {
            "category":"Retail",
            "subcategory":"Photofinishing",
            "type":"Services"
        }
    ],
    "sg:phone":"+31 115 618 184",
    "sg:postcode":"4537 AB",
    "sg:province":"Zeeland",
    "sg:tags":[
        "foto",
        "film"
    ],
    "wof:name":"Fotostudio Mark Neelemans",
    "wof:placetype":"venue"
},
  "geometry": {"coordinates":[3.830567,51.333382],"type":"Point"}
}