{
  "type": "Feature",
  "properties": {
    "addr:full":"Liemersweg 2 Doetinchem Gelderland 7006 GG",
    "addr:housenumber":"2",
    "addr:postcode":"7006 gg",
    "addr:street":"Liemersweg;Gelderland",
    "iso:country":"NL",
    "sg:address":"Liemersweg 2",
    "sg:city":"Doetinchem",
    "sg:orig_category":"Overheidsdiensten",
    "sg:phone":"+31 314 369 369",
    "sg:postcode":"7006 GG",
    "sg:province":"Gelderland",
    "wof:name":"Waterschap Rijn En Ijssel",
    "wof:placetype":"venue"
},
  "geometry": {"coordinates":[6.2484211922,51.9698944092],"type":"Point"}
}