{
  "type": "Feature",
  "properties": {
    "iso:country":"NL",
    "sg:address":"Telefoonstr 6",
    "sg:city":"Tilburg",
    "sg:orig_category":"Meubelstoffering",
    "sg:phone":"+31 13 535 1728",
    "sg:postcode":"5038 DM",
    "sg:province":"North Brabant",
    "wof:name":"Knop Meubelstoffeerderij Vof, De",
    "wof:placetype":"venue"
},
  "geometry": {"coordinates":[5.08499,51.557259],"type":"Point"}
}