{
  "type": "Feature",
  "properties": {
    "addr:full":"Ambachtsstr 12/A Nykerk Gld Gelderland 3861 RH",
    "addr:housenumber":"12 / a",
    "addr:postcode":"3861 rh",
    "addr:street":"Ambachtsstr;Nykerk Gld Gelderland",
    "iso:country":"NL",
    "sg:address":"Ambachtsstr 12/A",
    "sg:city":"Nykerk Gld",
    "sg:orig_category":"Verlichting",
    "sg:phone":"+31 33 247 0341",
    "sg:postcode":"3861 RH",
    "sg:province":"Gelderland",
    "wof:name":"Unifit",
    "wof:placetype":"venue"
},
  "geometry": {"coordinates":[5.481241,52.234081],"type":"Point"}
}