{
  "type": "Feature",
  "properties": {
    "addr:full":"V Heemstrastr 12B Driebergen Rysenb Utrecht 3971 VR",
    "addr:housenumber":"12b",
    "addr:postcode":"3971 vr",
    "addr:street":"Heemstrastr;Rysenb",
    "iso:country":"NL",
    "sg:address":"V Heemstrastr 12B",
    "sg:city":"Driebergen Rysenb",
    "sg:orig_category":"Horecabenodigdheden",
    "sg:phone":"+31 343 513 361",
    "sg:postcode":"3971 VR",
    "sg:province":"Utrecht",
    "wof:name":"Woudri Bv",
    "wof:placetype":"venue"
},
  "geometry": {"coordinates":[5.30052,52.065571],"type":"Point"}
}