{
  "type": "Feature",
  "properties": {
    "addr:full":"Velserhof 111 Ijmuiden Noord-Holland 1972 JH",
    "addr:housenumber":"111",
    "addr:postcode":"1972 jh",
    "addr:street":"Velserhof",
    "iso:country":"NL",
    "sg:address":"Velserhof 111",
    "sg:city":"Ijmuiden",
    "sg:orig_category":"Kappers",
    "sg:phone":"+31 255 513 832",
    "sg:postcode":"1972 JH",
    "sg:province":"Noord-Holland",
    "wof:name":"Hairshop Van Westerop",
    "wof:placetype":"venue"
},
  "geometry": {"coordinates":[4.6160650253,52.4586639404],"type":"Point"}
}