{
  "type": "Feature",
  "properties": {
    "addr:full":"Sluiskd 24 Hoogezand Groningen 9601 LC",
    "addr:housenumber":"24",
    "addr:postcode":"9601 lc",
    "addr:street":"Sluiskd",
    "iso:country":"NL",
    "sg:address":"Sluiskd 24",
    "sg:city":"Hoogezand",
    "sg:orig_category":"Kappers",
    "sg:phone":"+31 598 395 402",
    "sg:postcode":"9601 LC",
    "sg:province":"Groningen",
    "wof:name":"Monique",
    "wof:placetype":"venue"
},
  "geometry": {"coordinates":[6.74858,53.165501],"type":"Point"}
}