{
  "type": "Feature",
  "properties": {
    "addr:full":"Sophialn 7 Amsterdam North Holland 1075 BL",
    "addr:housenumber":"7",
    "addr:postcode":"1075 bl",
    "addr:street":"Sophialn",
    "iso:country":"NL",
    "sg:address":"Sophialn 7",
    "sg:city":"Amsterdam",
    "sg:orig_category":"Verzekeringen - Verzekeringskantoren",
    "sg:phone":"+31 20 572 1111",
    "sg:postcode":"1075 BL",
    "sg:province":"North Holland",
    "wof:name":"Vimars Bv",
    "wof:placetype":"venue"
},
  "geometry": {"coordinates":[4.85933,52.35051],"type":"Point"}
}