{
  "type": "Feature",
  "properties": {
    "addr:full":"Prins Clausstraat 2 Houten Utrecht 3991 BX",
    "addr:housenumber":"2",
    "addr:postcode":"3991 bx",
    "addr:street":"Prins Clausstraat",
    "iso:country":"NL",
    "sg:address":"Prins Clausstraat 2",
    "sg:city":"Houten",
    "sg:orig_category":"Fietshandelaren",
    "sg:phone":"+31 30 634 2511",
    "sg:postcode":"3991 BX",
    "sg:province":"Utrecht",
    "wof:name":"Hei Bike Bv",
    "wof:placetype":"venue"
},
  "geometry": {"coordinates":[5.163777,52.027576],"type":"Point"}
}