{
  "type": "Feature",
  "properties": {
    "addr:full":"Het Veer 6 Avenhorn Noord-Holland 1633 HE",
    "addr:housenumber":"6",
    "addr:postcode":"1633 he",
    "addr:street":"Het Veer",
    "iso:country":"NL",
    "sg:address":"Het Veer 6",
    "sg:city":"Avenhorn",
    "sg:classifiers":[
        {
            "category":"Fast Food",
            "type":"Food & Drink"
        }
    ],
    "sg:phone":"+31 229 542 139",
    "sg:postcode":"1633 HE",
    "sg:province":"Noord-Holland",
    "sg:tags":[
        "afhaal",
        "restaurant"
    ],
    "wof:name":"Snackbar Piet",
    "wof:placetype":"venue"
},
  "geometry": {"coordinates":[4.952644,52.615978],"type":"Point"}
}