{
  "type": "Feature",
  "properties": {
    "addr:full":"Nunspeetln 416 S Gravenhage Zuid-Holland 2573 GT",
    "addr:housenumber":"416;gravenhage",
    "addr:postcode":"2573 gt",
    "addr:street":"S",
    "iso:country":"NL",
    "sg:address":"Nunspeetln 416",
    "sg:city":"S Gravenhage",
    "sg:orig_category":"Fotoreportages",
    "sg:phone":"+31 70 345 9740",
    "sg:postcode":"2573 GT",
    "sg:province":"Zuid-Holland",
    "sg:website":"http://www.fotocavo.nl",
    "wof:name":"Cavo Foto",
    "wof:placetype":"venue"
},
  "geometry": {"coordinates":[4.2844,52.064911],"type":"Point"}
}