{
  "type": "Feature",
  "properties": {
    "addr:full":"Molenln 229 Rotterdam South Holland 3055 GD",
    "addr:housenumber":"229",
    "addr:postcode":"3055 gd",
    "iso:country":"NL",
    "sg:address":"Molenln 229",
    "sg:city":"Rotterdam",
    "sg:orig_category":"Binnenhuisarchitectuur",
    "sg:phone":"+31 10 418 0891",
    "sg:postcode":"3055 GD",
    "sg:province":"South Holland",
    "wof:name":"Valk, Van Der",
    "wof:placetype":"venue"
},
  "geometry": {"coordinates":[4.507748,51.957726],"type":"Point"}
}