{
  "type": "Feature",
  "properties": {
    "addr:full":"Citerstraat 22 Rijswijk Zh Zuid-Holland 2287 EN",
    "addr:housenumber":"22",
    "addr:postcode":"zh;2287 en",
    "addr:street":"Citerstraat",
    "iso:country":"NL",
    "sg:address":"Citerstraat 22",
    "sg:city":"Rijswijk Zh",
    "sg:orig_category":"Diverse Bedrijfsinstallaties Gh",
    "sg:phone":"+31 70 394 4517",
    "sg:postcode":"2287 EN",
    "sg:province":"Zuid-Holland",
    "wof:name":"A Vocaturo",
    "wof:placetype":"venue"
},
  "geometry": {"coordinates":[4.321873,52.032692],"type":"Point"}
}