{
  "type": "Feature",
  "properties": {
    "addr:full":"Lagedijk 64A Koog A/D Zaan Noord-Holland 1541 KC",
    "addr:housenumber":"64a;a / d",
    "addr:postcode":"1541 kc",
    "addr:street":"Lagedijk",
    "iso:country":"NL",
    "sg:address":"Lagedijk 64A",
    "sg:city":"Koog A/D Zaan",
    "sg:orig_category":"Gebouwenafwerking, Renovaties And Reiniging",
    "sg:phone":"+31 75 612 1539",
    "sg:postcode":"1541 KC",
    "sg:province":"Noord-Holland",
    "wof:name":"Wilko Bv",
    "wof:placetype":"venue"
},
  "geometry": {"coordinates":[4.81305,52.467735],"type":"Point"}
}