{
  "type": "Feature",
  "properties": {
    "addr:full":"Wagenweg 208 Haarlem Noord-Holland 2012 NM",
    "addr:housenumber":"208",
    "addr:postcode":"2012",
    "addr:street":"Wagenweg",
    "iso:country":"NL",
    "sg:address":"Wagenweg 208",
    "sg:city":"Haarlem",
    "sg:classifiers":[
        {
            "category":"Professional",
            "subcategory":"Accounting & Tax Preparation",
            "type":"Services"
        }
    ],
    "sg:phone":"+31 23 531 9381",
    "sg:postcode":"2012 NM",
    "sg:province":"Noord-Holland",
    "sg:tags":[
        "accountant"
    ],
    "wof:name":"Coenen Heunen Van De Ven",
    "wof:placetype":"venue"
},
  "geometry": {"coordinates":[4.620694,52.367786],"type":"Point"}
}