{
  "type": "Feature",
  "properties": {
    "addr:full":"Spoorven 601 Veghel Noord-Brabant 5464 PA",
    "addr:housenumber":"601",
    "addr:postcode":"veghel;5464 pa",
    "addr:street":"Spoorven",
    "iso:country":"NL",
    "sg:address":"Spoorven 601",
    "sg:city":"Veghel",
    "sg:orig_category":"Meubelreparatie And -Restauratie",
    "sg:phone":"+31 413 343 998",
    "sg:postcode":"5464 PA",
    "sg:province":"Noord-Brabant",
    "wof:name":"Pemoht Jf",
    "wof:placetype":"venue"
},
  "geometry": {"coordinates":[5.54851,51.629402],"type":"Point"}
}