{
  "type": "Feature",
  "properties": {
    "addr:full":"De Lindeboom 11 Mijdrecht Utrecht 3641 EX",
    "addr:housenumber":"11",
    "addr:postcode":"3641 ex",
    "addr:street":"De Lindeboom",
    "iso:country":"NL",
    "sg:address":"De Lindeboom 11",
    "sg:city":"Mijdrecht",
    "sg:orig_category":"Boekenuitgeverijen",
    "sg:phone":"+31 297 281 855",
    "sg:postcode":"3641 EX",
    "sg:province":"Utrecht",
    "wof:name":"Boekhandel Mondria Bv",
    "wof:placetype":"venue"
},
  "geometry": {"coordinates":[4.866595,52.208328],"type":"Point"}
}