{
  "type": "Feature",
  "properties": {
    "iso:country":"NL",
    "sg:address":"Spittaalstr 92",
    "sg:city":"Zutphen",
    "sg:orig_category":"Kunstnijverheidsateliers",
    "sg:phone":"+31 575 547 343",
    "sg:postcode":"7201 EG",
    "sg:province":"Gelderland",
    "wof:name":"Soet, Dorine De",
    "wof:placetype":"venue"
},
  "geometry": {"coordinates":[6.201011,52.13752],"type":"Point"}
}