{
  "type": "Feature",
  "properties": {
    "iso:country":"NL",
    "sg:address":"Havenstr 73",
    "sg:city":"Ridderkerk",
    "sg:orig_category":"Omroep",
    "sg:phone":"+31 180 426 700",
    "sg:postcode":"2984 AC",
    "sg:province":"Zuid-Holland",
    "wof:name":"Ridderkerk Fm",
    "wof:placetype":"venue"
},
  "geometry": {"coordinates":[4.606498,51.872135],"type":"Point"}
}