{
  "type": "Feature",
  "properties": {
    "iso:country":"NL",
    "sg:address":"1E Brandenburg Wg 53",
    "sg:city":"Bilthoven",
    "sg:orig_category":"Grafische Bedrijven",
    "sg:phone":"+31 30 220 2835",
    "sg:postcode":"3721 MC",
    "sg:province":"Utrecht",
    "wof:name":"Cartodoc",
    "wof:placetype":"venue"
},
  "geometry": {"coordinates":[5.184766,52.116783],"type":"Point"}
}