{
  "type": "Feature",
  "properties": {
    "addr:full":"Industriestraat 50A Tegelen Limburg 5931 PJ",
    "addr:housenumber":"50a",
    "addr:postcode":"5931 pj",
    "addr:street":"Industriestraat",
    "iso:country":"NL",
    "sg:address":"Industriestraat 50A",
    "sg:city":"Tegelen",
    "sg:orig_category":"Partycatering And -Organisatie",
    "sg:phone":"+31 77 374 0350",
    "sg:postcode":"5931 PJ",
    "sg:province":"Limburg",
    "wof:name":"De Graaf Indonesische Catering",
    "wof:placetype":"venue"
},
  "geometry": {"coordinates":[6.139155,51.338631],"type":"Point"}
}