{
  "type": "Feature",
  "properties": {
    "addr:full":"Huis Te Landelaan 490 Rijswijk Zh Zuid-Holland 2283 VJ",
    "addr:housenumber":"490",
    "addr:postcode":"zh;2283 vj",
    "addr:street":"Huis Te Landelaan",
    "iso:country":"NL",
    "sg:address":"Huis Te Landelaan 490",
    "sg:city":"Rijswijk Zh",
    "sg:orig_category":"Huishoudapparatuur, Televisies And Radio'S",
    "sg:phone":"+31 70 393 4411",
    "sg:postcode":"2283 VJ",
    "sg:province":"Zuid-Holland",
    "wof:name":"Joh Kock",
    "wof:placetype":"venue"
},
  "geometry": {"coordinates":[4.322814,52.040863],"type":"Point"}
}