{
  "type": "Feature",
  "properties": {
    "addr:full":"Veilingweg 2 Gronsveld Limburg 6247 EP",
    "addr:housenumber":"2",
    "addr:postcode":"6247 ep",
    "addr:street":"Veilingweg",
    "iso:country":"NL",
    "sg:address":"Veilingweg 2",
    "sg:city":"Gronsveld",
    "sg:classifiers":[
        {
            "category":"Retail",
            "subcategory":"Storage",
            "type":"Services"
        }
    ],
    "sg:phone":"+31 43 408 1628",
    "sg:postcode":"6247 EP",
    "sg:province":"Limburg",
    "sg:tags":[
        "opslag",
        "bewaring"
    ],
    "wof:name":"Curfs Transport En Overslagbedrijf Bv",
    "wof:placetype":"venue"
},
  "geometry": {"coordinates":[5.7317252159,50.8098106384],"type":"Point"}
}