{
  "type": "Feature",
  "properties": {
    "addr:full":"Rooseindsestraat 45 Helmond North Brabant 5705 BP",
    "addr:housenumber":"45",
    "addr:postcode":"5705 bp",
    "addr:street":"Rooseindsestraat",
    "iso:country":"NL",
    "sg:address":"Rooseindsestraat 45",
    "sg:city":"Helmond",
    "sg:orig_category":"Gespecialiseerde Bouw",
    "sg:phone":"+31 492 523 957",
    "sg:postcode":"5705 BP",
    "sg:province":"North Brabant",
    "wof:name":"Arts Constructiebedrijf Bv",
    "wof:placetype":"venue"
},
  "geometry": {"coordinates":[5.680854,51.47356],"type":"Point"}
}