{
  "type": "Feature",
  "properties": {
    "addr:full":"Postbaan 33 Prinsenbeek North Brabant 4841 KK",
    "addr:housenumber":"33",
    "addr:postcode":"4841 kk",
    "addr:street":"Postbaan",
    "iso:country":"NL",
    "sg:address":"Postbaan 33",
    "sg:city":"Prinsenbeek",
    "sg:orig_category":"Zuivelproducten",
    "sg:phone":"+31 76 541 2413",
    "sg:postcode":"4841 KK",
    "sg:province":"North Brabant",
    "wof:name":"Kaasboerderij Schalk",
    "wof:placetype":"venue"
},
  "geometry": {"coordinates":[4.709455,51.612347],"type":"Point"}
}