{
  "type": "Feature",
  "properties": {
    "addr:full":"Langeraarsewg 2 Ter Aar South Holland 2461 CK",
    "addr:housenumber":"2",
    "addr:postcode":"2461 ck",
    "addr:street":"Langeraarsewg",
    "iso:country":"NL",
    "sg:address":"Langeraarsewg 2",
    "sg:city":"Ter Aar",
    "sg:orig_category":"Webdesign Bureaus",
    "sg:phone":"+31 172 605 945",
    "sg:postcode":"2461 CK",
    "sg:province":"South Holland",
    "wof:name":"Frednet",
    "wof:placetype":"venue"
},
  "geometry": {"coordinates":[4.7221851349,52.1994819641],"type":"Point"}
}