{
  "type": "Feature",
  "properties": {
    "addr:full":"Troelstraln 96 Delft Zuid-Holland 2624 EX",
    "addr:housenumber":"96",
    "addr:postcode":"2624 ex",
    "addr:street":"Troelstraln",
    "iso:country":"NL",
    "sg:address":"Troelstraln 96",
    "sg:city":"Delft",
    "sg:orig_category":"Werving En Selectie",
    "sg:phone":"+31 15 285 2368",
    "sg:postcode":"2624 EX",
    "sg:province":"Zuid-Holland",
    "wof:name":"Working Together",
    "wof:placetype":"venue"
},
  "geometry": {"coordinates":[4.3529191017,51.9979896545],"type":"Point"}
}