{
  "type": "Feature",
  "properties": {
    "addr:full":"A Fokkerstr 25 Barneveld Gelderland 3772 MP",
    "addr:housenumber":"25",
    "addr:postcode":"3772 mp",
    "addr:street":"Gelderland",
    "iso:country":"NL",
    "sg:address":"A Fokkerstr 25",
    "sg:city":"Barneveld",
    "sg:orig_category":"Meubelen",
    "sg:phone":"+31 342 421 731",
    "sg:postcode":"3772 MP",
    "sg:province":"Gelderland",
    "wof:name":"Pauline'S Woonwinkel",
    "wof:placetype":"venue"
},
  "geometry": {"coordinates":[5.564629,52.127861],"type":"Point"}
}