{
  "type": "Feature",
  "properties": {
    "addr:full":"Voltastr 7A Leeuwarden Provincie Friesland 8912 AE",
    "addr:housenumber":"7a",
    "addr:postcode":"8912 ae",
    "addr:street":"Voltastr;Provincie Friesland",
    "iso:country":"NL",
    "sg:address":"Voltastr 7A",
    "sg:city":"Leeuwarden",
    "sg:classifiers":[
        {
            "category":"Shopping",
            "subcategory":"News",
            "type":"Retail Goods"
        }
    ],
    "sg:phone":"+31 58 298 7781",
    "sg:postcode":"8912 AE",
    "sg:province":"Provincie Friesland",
    "sg:tags":[
        "maandbladen",
        "en",
        "week-"
    ],
    "wof:name":"Centraal Weekblad",
    "wof:placetype":"venue"
},
  "geometry": {"coordinates":[5.7719359398,53.1964302063],"type":"Point"}
}