{
  "type": "Feature",
  "properties": {
    "addr:full":"Htg V Brabantpln 65 Eindhoven Noord-Brabant 5611 PJ",
    "addr:housenumber":"65",
    "addr:postcode":"5611 pj",
    "addr:street":"Brabantpln",
    "iso:country":"NL",
    "sg:address":"Htg V Brabantpln 65",
    "sg:city":"Eindhoven",
    "sg:orig_category":"Adviesbureaus Bedrijfsorganisatie",
    "sg:phone":"+31 40 212 1385",
    "sg:postcode":"5611 PJ",
    "sg:province":"Noord-Brabant",
    "wof:name":"Kap Int",
    "wof:placetype":"venue"
},
  "geometry": {"coordinates":[5.484105,51.434471],"type":"Point"}
}