{
  "type": "Feature",
  "properties": {
    "iso:country":"NL",
    "sg:address":"Moerstraatsewg 25",
    "sg:city":"Moerstraten",
    "sg:orig_category":"Voetbalverenigingen",
    "sg:phone":"+31 165 302 189",
    "sg:postcode":"4727 SZ",
    "sg:province":"Noord-Brabant",
    "wof:name":"Fc Moerstraten",
    "wof:placetype":"venue"
},
  "geometry": {"coordinates":[4.349113,51.528904],"type":"Point"}
}