{
  "type": "Feature",
  "properties": {
    "addr:full":"Pr Margrietstr 40 Ridderkerk Zuid-Holland 2983 EH",
    "addr:housenumber":"40",
    "addr:postcode":"2983 eh",
    "iso:country":"NL",
    "sg:address":"Pr Margrietstr 40",
    "sg:city":"Ridderkerk",
    "sg:orig_category":"Kappers",
    "sg:phone":"+31 180 410 333",
    "sg:postcode":"2983 EH",
    "sg:province":"Zuid-Holland",
    "wof:name":"Subliem",
    "wof:placetype":"venue"
},
  "geometry": {"coordinates":[4.604729,51.878597],"type":"Point"}
}