{
  "type": "Feature",
  "properties": {
    "iso:country":"NL",
    "sg:address":"Mgr Zwysenstr 9",
    "sg:city":"Waalwyk",
    "sg:orig_category":"Cafetaria'S",
    "sg:phone":"+31 416 342 074",
    "sg:postcode":"5142 SM",
    "sg:province":"Noord-Brabant",
    "wof:name":"Mot, De",
    "wof:placetype":"venue"
},
  "geometry": {"coordinates":[5.0872,51.689838],"type":"Point"}
}