{
  "type": "Feature",
  "properties": {
    "addr:full":"Joost Van Den Vondelstr 161 Winterswijk Gelderland 7103 XT",
    "addr:housenumber":"161",
    "addr:postcode":"7103 xt",
    "addr:street":"Joost Van Den Vondelstr;Gelderland",
    "iso:country":"NL",
    "sg:address":"Joost Van Den Vondelstr 161",
    "sg:city":"Winterswijk",
    "sg:orig_category":"Kinderopvang Behalve Thuis",
    "sg:phone":"+31 543 524 221",
    "sg:postcode":"7103 XT",
    "sg:province":"Gelderland",
    "wof:name":"Kinderdagverblijf Jodokus",
    "wof:placetype":"venue"
},
  "geometry": {"coordinates":[6.728381,51.97789],"type":"Point"}
}