{
  "type": "Feature",
  "properties": {
    "addr:full":"Schiedamsedk 48 Rotterdam Zuid-Holland 3011 ED",
    "addr:housenumber":"48",
    "addr:postcode":"3011 ed",
    "addr:street":"Schiedamsedk",
    "iso:country":"NL",
    "sg:address":"Schiedamsedk 48",
    "sg:city":"Rotterdam",
    "sg:orig_category":"Adviesbureaus Bouwkunde",
    "sg:phone":"+31 10 201 0044",
    "sg:postcode":"3011 ED",
    "sg:province":"Zuid-Holland",
    "sg:website":"http://www.pkb.nl",
    "wof:name":"Pkb",
    "wof:placetype":"venue"
},
  "geometry": {"coordinates":[4.481488,51.916634],"type":"Point"}
}