{
  "type": "Feature",
  "properties": {
    "addr:full":"Lottumsewg 2A Broekhuizen Lb Missouri 5872 AB",
    "addr:housenumber":"2a",
    "addr:postcode":"5872 ab",
    "addr:street":"Lottumsewg",
    "iso:country":"NL",
    "sg:address":"Lottumsewg 2A",
    "sg:city":"Broekhuizen Lb",
    "sg:orig_category":"Adviesbureaus Bouwkunde",
    "sg:phone":"+31 77 463 8080",
    "sg:postcode":"5872 AB",
    "sg:province":"Missouri",
    "wof:name":"Loo, S Van",
    "wof:placetype":"venue"
},
  "geometry": {"coordinates":[-93.129936,36.705662],"type":"Point"}
}