{
  "type": "Feature",
  "properties": {
    "addr:full":"St Catharinastr 1 D-E Eindhoven Noord-Brabant 5611 JA",
    "addr:housenumber":"1",
    "addr:postcode":"5611 ja",
    "addr:street":"D-E Eindhoven",
    "iso:country":"NL",
    "sg:address":"St Catharinastr 1 D-E",
    "sg:city":"Eindhoven",
    "sg:orig_category":"Biljartzalen",
    "sg:phone":"+31 40 245 0372",
    "sg:postcode":"5611 JA",
    "sg:province":"Noord-Brabant",
    "sg:website":"http://www.johnbull.nl",
    "wof:name":"John Bull Snookerclub",
    "wof:placetype":"venue"
},
  "geometry": {"coordinates":[5.484105,51.434471],"type":"Point"}
}