{
  "type": "Feature",
  "properties": {
    "addr:full":"Vrouwenhuiswaard 6 Zoetermeer Zuid-Holland 2716 DP",
    "addr:housenumber":"6",
    "addr:postcode":"2716 dp",
    "addr:street":"Vrouwenhuiswaard",
    "iso:country":"NL",
    "sg:address":"Vrouwenhuiswaard 6",
    "sg:city":"Zoetermeer",
    "sg:orig_category":"Adviesbureaus Economie",
    "sg:phone":"+31 79 351 0391",
    "sg:postcode":"2716 DP",
    "sg:province":"Zuid-Holland",
    "wof:name":"Bfb",
    "wof:placetype":"venue"
},
  "geometry": {"coordinates":[4.466752,52.05669],"type":"Point"}
}