{
  "type": "Feature",
  "properties": {
    "iso:country":"NL",
    "sg:address":"Marinus Naefflaan 3",
    "sg:city":"Lochem",
    "sg:orig_category":"Artsen And Specialisten",
    "sg:phone":"+31 573 253 138",
    "sg:postcode":"7241 GC",
    "sg:province":"Gelderland",
    "wof:name":"Artsenpraktijk Hoogendoorn Bv",
    "wof:placetype":"venue"
},
  "geometry": {"coordinates":[6.42716,52.156452],"type":"Point"}
}