{
  "type": "Feature",
  "properties": {
    "addr:full":"Einderstr 59 Kerkrade Limburg 6461 EM",
    "addr:housenumber":"59",
    "addr:postcode":"6461 em",
    "addr:street":"Einderstr",
    "iso:country":"NL",
    "sg:address":"Einderstr 59",
    "sg:city":"Kerkrade",
    "sg:orig_category":"Boeken En Tijdschriften",
    "sg:phone":"+31 45 567 1698",
    "sg:postcode":"6461 EM",
    "sg:province":"Limburg",
    "wof:name":"Plantage, Boekhandel",
    "wof:placetype":"venue"
},
  "geometry": {"coordinates":[6.063179,50.863575],"type":"Point"}
}