{
  "type": "Feature",
  "properties": {
    "addr:full":"Nispensestraat 72 Roosendaal North Brabant 4701 CX",
    "addr:housenumber":"72",
    "addr:postcode":"4701 cx",
    "addr:street":"Nispensestraat",
    "iso:country":"NL",
    "sg:address":"Nispensestraat 72",
    "sg:city":"Roosendaal",
    "sg:orig_category":"Motoren",
    "sg:phone":"+31 165 564 241",
    "sg:postcode":"4701 CX",
    "sg:province":"North Brabant",
    "wof:name":"Card Benelux Bv",
    "wof:placetype":"venue"
},
  "geometry": {"coordinates":[4.459355,51.528469],"type":"Point"}
}