{
  "type": "Feature",
  "properties": {
    "addr:full":"Grt Hoogstr 19 Leeuwarden Provincie Friesland 8911 GZ",
    "addr:housenumber":"19",
    "addr:postcode":"8911 gz",
    "addr:street":"Provincie Friesland",
    "iso:country":"NL",
    "sg:address":"Grt Hoogstr 19",
    "sg:city":"Leeuwarden",
    "sg:orig_category":"Boekbinderijen",
    "sg:phone":"+31 58 212 2593",
    "sg:postcode":"8911 GZ",
    "sg:province":"Provincie Friesland",
    "wof:name":"Schonenberg, H",
    "wof:placetype":"venue"
},
  "geometry": {"coordinates":[5.79691,53.202209],"type":"Point"}
}