{
  "type": "Feature",
  "properties": {
    "addr:full":"K Onnesstr 3 Haarlem Noord-Holland 2014 EJ",
    "addr:housenumber":"3",
    "addr:postcode":"2014 ej",
    "addr:street":"Onnesstr",
    "iso:country":"NL",
    "sg:address":"K Onnesstr 3",
    "sg:city":"Haarlem",
    "sg:orig_category":"Wijnkoperijen En -Groothandel",
    "sg:phone":"+31 23 544 3418",
    "sg:postcode":"2014 EJ",
    "sg:province":"Noord-Holland",
    "wof:name":"Haarlems Wijnhuis, Het",
    "wof:placetype":"venue"
},
  "geometry": {"coordinates":[4.6422529221,52.3805618286],"type":"Point"}
}