{
  "type": "Feature",
  "properties": {
    "addr:full":"De Neerheide 6 Waalre Noord-Brabant 5581 TP",
    "addr:housenumber":"6",
    "addr:postcode":"5581 tp",
    "addr:street":"De Neerheide",
    "iso:country":"NL",
    "sg:address":"De Neerheide 6",
    "sg:city":"Waalre",
    "sg:orig_category":"Autorijscholen",
    "sg:phone":"+31 40 222 0605",
    "sg:postcode":"5581 TP",
    "sg:province":"Noord-Brabant",
    "wof:name":"Meerakker, Verkeersschool Van De",
    "wof:placetype":"venue"
},
  "geometry": {"coordinates":[5.443377,51.391949],"type":"Point"}
}