{
  "type": "Feature",
  "properties": {
    "addr:full":"Zuidervaart 3 A Zuidschermer North Holland 1846 LE",
    "addr:housenumber":"3 a",
    "addr:postcode":"1846 le",
    "addr:street":"Zuidervaart",
    "iso:country":"NL",
    "sg:address":"Zuidervaart 3 A",
    "sg:city":"Zuidschermer",
    "sg:orig_category":"Kantoor- En Secretariaatsservice",
    "sg:phone":"+31 72 564 9096",
    "sg:postcode":"1846 LE",
    "sg:province":"North Holland",
    "sg:website":"http://www.easily.nl",
    "wof:name":"Easily",
    "wof:placetype":"venue"
},
  "geometry": {"coordinates":[4.7674508095,52.5641059875],"type":"Point"}
}