{
  "type": "Feature",
  "properties": {
    "addr:full":"Wilhelminastr 114 Egmond Aan Zee Noord-Holland 1931 BT",
    "addr:housenumber":"114",
    "addr:postcode":"1931 bt",
    "addr:street":"Wilhelminastr",
    "iso:country":"NL",
    "sg:address":"Wilhelminastr 114",
    "sg:city":"Egmond Aan Zee",
    "sg:classifiers":[
        {
            "category":"Travel",
            "subcategory":"Hotels & Motels",
            "type":"Entertainment"
        }
    ],
    "sg:phone":"+31 72 506 1589",
    "sg:postcode":"1931 BT",
    "sg:province":"Noord-Holland",
    "wof:name":"Sonnevanck",
    "wof:placetype":"venue"
},
  "geometry": {"coordinates":[4.623843,52.621033],"type":"Point"}
}