{
  "type": "Feature",
  "properties": {
    "addr:full":"Houtduifstr 14 Delft Zuid-Holland 2623 ES",
    "addr:housenumber":"14",
    "addr:postcode":"2623 es",
    "addr:street":"Houtduifstr",
    "iso:country":"NL",
    "sg:address":"Houtduifstr 14",
    "sg:city":"Delft",
    "sg:orig_category":"Bedrijfsopleidingen",
    "sg:phone":"+31 15 251 0669",
    "sg:postcode":"2623 ES",
    "sg:province":"Zuid-Holland",
    "wof:name":"Door Training",
    "wof:placetype":"venue"
},
  "geometry": {"coordinates":[4.363829,51.985199],"type":"Point"}
}