{
  "type": "Feature",
  "properties": {
    "addr:full":"Kast Heysterumstr 25 Roermond Limburg 6043 HP",
    "addr:housenumber":"25",
    "addr:postcode":"6043 hp",
    "iso:country":"NL",
    "sg:address":"Kast Heysterumstr 25",
    "sg:city":"Roermond",
    "sg:orig_category":"Wijnkoperijen En -Groothandel",
    "sg:phone":"+31 475 325 979",
    "sg:postcode":"6043 HP",
    "sg:province":"Limburg",
    "wof:name":"Rutten, Peter",
    "wof:placetype":"venue"
},
  "geometry": {"coordinates":[6.0079379082,51.1903114319],"type":"Point"}
}