{
  "type": "Feature",
  "properties": {
    "addr:full":"Postbus 44 Twello Gelderland 7390 AA",
    "addr:housenumber":"44",
    "addr:postcode":"7390 aa",
    "addr:street":"Postbus;Gelderland",
    "iso:country":"NL",
    "sg:address":"Postbus 44",
    "sg:city":"Twello",
    "sg:orig_category":"Scholen Voor Basisonderwijs",
    "sg:phone":"+31 55 323 1369",
    "sg:postcode":"7390 AA",
    "sg:province":"Gelderland",
    "wof:name":"Antonius Rk, St",
    "wof:placetype":"venue"
},
  "geometry": {"coordinates":[6.10329,52.237049],"type":"Point"}
}