{
  "type": "Feature",
  "properties": {
    "iso:country":"NL",
    "sg:address":"Amsterdamsestrwg 41A",
    "sg:city":"Baarn",
    "sg:orig_category":"Muziekdrukkerijen En -Uitgeverijen",
    "sg:phone":"+31 35 623 9611",
    "sg:postcode":"3744 MA",
    "sg:province":"Utrecht",
    "sg:website":"http://www.alabianca.nl",
    "wof:name":"Ala Bianca Benelux Bv",
    "wof:placetype":"venue"
},
  "geometry": {"coordinates":[5.268625,52.211006],"type":"Point"}
}