{
  "type": "Feature",
  "properties": {
    "addr:full":"Vrijthof 49 Maastricht Limburg 6211 LE",
    "addr:housenumber":"49",
    "addr:postcode":"6211 le",
    "addr:street":"Vrijthof",
    "iso:country":"NL",
    "sg:address":"Vrijthof 49",
    "sg:city":"Maastricht",
    "sg:orig_category":"Kunsthandel",
    "sg:phone":"+31 43 321 6745",
    "sg:postcode":"6211 LE",
    "sg:province":"Limburg",
    "wof:name":"Noortman Bv",
    "wof:placetype":"venue"
},
  "geometry": {"coordinates":[5.687752,50.849983],"type":"Point"}
}