{
  "type": "Feature",
  "properties": {
    "addr:full":"Van Pallandtstraat 9 Arnhem Gelderland 6814 GM",
    "addr:housenumber":"9",
    "addr:postcode":"6814 gm",
    "addr:street":"Van Pallandtstraat",
    "iso:country":"NL",
    "sg:address":"Van Pallandtstraat 9",
    "sg:city":"Arnhem",
    "sg:orig_category":"Boekhouders",
    "sg:phone":"+31 26 442 8904",
    "sg:postcode":"6814 GM",
    "sg:province":"Gelderland",
    "wof:name":"Administratiekantoor Bewima Bv",
    "wof:placetype":"venue"
},
  "geometry": {"coordinates":[5.899342,51.988956],"type":"Point"}
}