{
  "type": "Feature",
  "properties": {
    "addr:full":"Karveel 3917 Dep Lelystad Flevoland 8231 DN",
    "addr:postcode":"3917 dep;8231 dn",
    "addr:street":"Karveel;Flevoland",
    "iso:country":"NL",
    "sg:address":"Karveel 3917 Dep",
    "sg:city":"Lelystad",
    "sg:orig_category":"Ziekenhuizen, Sanatoria, Verpleeghuizen",
    "sg:phone":"+31 320 280 980",
    "sg:postcode":"8231 DN",
    "sg:province":"Flevoland",
    "wof:name":"Riethorst, De",
    "wof:placetype":"venue"
},
  "geometry": {"coordinates":[5.474038,52.505688],"type":"Point"}
}