{
  "type": "Feature",
  "properties": {
    "iso:country":"NL",
    "sg:address":"Wilhelminaln 53D",
    "sg:city":"Alphen Aan Den Ryn",
    "sg:orig_category":"Autorijscholen",
    "sg:phone":"+31 172 474 076",
    "sg:postcode":"2405 EC",
    "sg:province":"South Holland",
    "wof:name":"Promise",
    "wof:placetype":"venue"
},
  "geometry": {"coordinates":[4.661781,52.133389],"type":"Point"}
}