{
  "type": "Feature",
  "properties": {
    "addr:full":"Jericholaan 13 Rotterdam Zuid-Holland 3061 HA",
    "addr:housenumber":"13",
    "addr:postcode":"3061 ha",
    "addr:street":"Jericholaan",
    "iso:country":"NL",
    "sg:address":"Jericholaan 13",
    "sg:city":"Rotterdam",
    "sg:orig_category":"Fotostudio'S And Fotografen",
    "sg:phone":"+31 10 452 1007",
    "sg:postcode":"3061 HA",
    "sg:province":"Zuid-Holland",
    "wof:name":"Ruud Van Bueren Fotografie",
    "wof:placetype":"venue"
},
  "geometry": {"coordinates":[4.507194,51.931862],"type":"Point"}
}