{
  "type": "Feature",
  "properties": {
    "iso:country":"NL",
    "sg:address":"Rykswg Centrum 103 , (Hk Kummenaedestr)",
    "sg:city":"Geleen",
    "sg:orig_category":"Homeopathie",
    "sg:phone":"+31 46 475 9003",
    "sg:postcode":"6161 ED",
    "sg:province":"Limburg",
    "wof:name":"Buysen Homeopathie Bio-Estetiek",
    "wof:placetype":"venue"
},
  "geometry": {"coordinates":[5.828038,50.967319],"type":"Point"}
}