{
  "type": "Feature",
  "properties": {
    "addr:full":"Elandsgracht 101 Amsterdam North Holland 1016 TS",
    "addr:housenumber":"101",
    "addr:postcode":"1016 ts",
    "addr:street":"Elandsgracht",
    "iso:country":"NL",
    "sg:address":"Elandsgracht 101",
    "sg:city":"Amsterdam",
    "sg:classifiers":[
        {
            "category":"Professional",
            "subcategory":"Accounting & Tax Preparation",
            "type":"Services"
        }
    ],
    "sg:phone":"+31 20 625 7893",
    "sg:postcode":"1016 TS",
    "sg:province":"North Holland",
    "sg:tags":[
        "accountant"
    ],
    "wof:name":"Accountantskantoor B.J. Thomas",
    "wof:placetype":"venue"
},
  "geometry": {"coordinates":[4.879222,52.368958],"type":"Point"}
}