{
  "type": "Feature",
  "properties": {
    "addr:full":"Zaaierswg 15 Amsterdam Noord-Holland 1097 SM",
    "addr:housenumber":"15",
    "addr:postcode":"1097 sm",
    "addr:street":"Zaaierswg",
    "iso:country":"NL",
    "sg:address":"Zaaierswg 15",
    "sg:city":"Amsterdam",
    "sg:orig_category":"Scholen Voor Basisonderwijs",
    "sg:phone":"+31 20 694 7160",
    "sg:postcode":"1097 SM",
    "sg:province":"Noord-Holland",
    "wof:name":"Vijfde Montessori Watergraafsmeer",
    "wof:placetype":"venue"
},
  "geometry": {"coordinates":[4.944258,52.34351],"type":"Point"}
}