{
  "type": "Feature",
  "properties": {
    "iso:country":"NL",
    "sg:address":"Peperstr 11",
    "sg:city":"Valkenswaard",
    "sg:orig_category":"Plafonds",
    "sg:phone":"+31 40 204 6796",
    "sg:postcode":"5554 EG",
    "sg:province":"Noord-Brabant",
    "wof:name":"Hds, Hooff/Dielis Van",
    "wof:placetype":"venue"
},
  "geometry": {"coordinates":[5.459802,51.349239],"type":"Point"}
}