{
  "type": "Feature",
  "properties": {
    "iso:country":"NL",
    "sg:address":"Frans Van Mierisstraat 48",
    "sg:city":"Apeldoorn",
    "sg:orig_category":"Schoonheidssalons",
    "sg:phone":"+31 55 355 6706",
    "sg:postcode":"7312 LE",
    "sg:province":"Gelderland",
    "wof:name":"Salon Voor Huidverzorging M.A. De Beer-P",
    "wof:placetype":"venue"
},
  "geometry": {"coordinates":[5.935069,52.202614],"type":"Point"}
}