{
  "type": "Feature",
  "properties": {
    "addr:full":"Dorpstr 122 Maastricht Limburg 6227 BR",
    "addr:housenumber":"122",
    "addr:postcode":"6227 br",
    "iso:country":"NL",
    "sg:address":"Dorpstr 122",
    "sg:city":"Maastricht",
    "sg:orig_category":"Onderhoudswerken",
    "sg:phone":"+31 43 347 2272",
    "sg:postcode":"6227 BR",
    "sg:province":"Limburg",
    "wof:name":"Lumpens",
    "wof:placetype":"venue"
},
  "geometry": {"coordinates":[5.726221,50.838207],"type":"Point"}
}