{
  "type": "Feature",
  "properties": {
    "addr:full":"Beersewg 52 Mill Pennsylvania 5451 NR",
    "addr:housenumber":"52",
    "addr:postcode":"5451 nr",
    "addr:street":"Beersewg",
    "iso:country":"NL",
    "sg:address":"Beersewg 52",
    "sg:city":"Mill",
    "sg:orig_category":"Bedrijfsopleidingen",
    "sg:phone":"+31 485 452 525",
    "sg:postcode":"5451 NR",
    "sg:province":"Pennsylvania",
    "wof:name":"Lange, Toos",
    "wof:placetype":"venue"
},
  "geometry": {"coordinates":[-77.762939,41.90403],"type":"Point"}
}