{
  "type": "Feature",
  "properties": {
    "iso:country":"NL",
    "sg:address":"Beukenln 77",
    "sg:city":"Eindhoven",
    "sg:orig_category":"Accountants - Administratie- Consulenten En -Kantoren",
    "sg:phone":"+31 40 250 0600",
    "sg:postcode":"5616 VC",
    "sg:province":"North Brabant",
    "sg:website":"http://www.pwcglobal.com/nl",
    "wof:name":"Pricewaterhousecoopers",
    "wof:placetype":"venue"
},
  "geometry": {"coordinates":[5.484105,51.434471],"type":"Point"}
}