{
  "type": "Feature",
  "properties": {
    "addr:full":"N Bohrwg 123 Utrecht Utrecht 3542 CA",
    "addr:housenumber":"123",
    "addr:postcode":"3542 ca",
    "addr:street":"N",
    "iso:country":"NL",
    "sg:address":"N Bohrwg 123",
    "sg:city":"Utrecht",
    "sg:orig_category":"Directmail",
    "sg:phone":"+31 30 241 7020",
    "sg:postcode":"3542 CA",
    "sg:province":"Utrecht",
    "wof:name":"Edg",
    "wof:placetype":"venue"
},
  "geometry": {"coordinates":[5.04821,52.121658],"type":"Point"}
}