{
  "type": "Feature",
  "properties": {
    "addr:full":"Het Zuid 26 Drachten Provincie Friesland 9203 TD",
    "addr:housenumber":"26",
    "addr:postcode":"9203 td",
    "addr:street":"Het Zuid;Provincie Friesland",
    "iso:country":"NL",
    "sg:address":"Het Zuid 26",
    "sg:city":"Drachten",
    "sg:orig_category":"Bloemen And Planten",
    "sg:phone":"+31 512 525 121",
    "sg:postcode":"9203 TD",
    "sg:province":"Provincie Friesland",
    "wof:name":"Tuindorado Drachten",
    "wof:placetype":"venue"
},
  "geometry": {"coordinates":[6.099582,53.085754],"type":"Point"}
}