{
  "type": "Feature",
  "properties": {
    "addr:full":"Oisterwijksebaan 163 Tilburg Noord-Brabant 5018 CB",
    "addr:housenumber":"163",
    "addr:postcode":"5018 cb",
    "addr:street":"Oisterwijksebaan",
    "iso:country":"NL",
    "sg:address":"Oisterwijksebaan 163",
    "sg:city":"Tilburg",
    "sg:orig_category":"Glaszetten",
    "sg:phone":"+31 13 535 2917",
    "sg:postcode":"5018 CB",
    "sg:province":"Noord-Brabant",
    "wof:name":"M.A.C. Sikkers",
    "wof:placetype":"venue"
},
  "geometry": {"coordinates":[5.106529,51.556656],"type":"Point"}
}