{
  "type": "Feature",
  "properties": {
    "iso:country":"NL",
    "sg:address":"Akerkhof 41",
    "sg:city":"Groningen",
    "sg:orig_category":"Juweliers",
    "sg:phone":"+31 50 312 1607",
    "sg:postcode":"9712 BC",
    "sg:province":"Groningen",
    "wof:name":"Hazekamp Juweliers",
    "wof:placetype":"venue"
},
  "geometry": {"coordinates":[6.561807,53.216713],"type":"Point"}
}