{
  "type": "Feature",
  "properties": {
    "addr:full":"Rijckerveld 1 Gulpen Limburg 6271 CL",
    "addr:housenumber":"1",
    "addr:postcode":"6271",
    "addr:street":"Rijckerveld",
    "iso:country":"NL",
    "sg:address":"Rijckerveld 1",
    "sg:city":"Gulpen",
    "sg:orig_category":"Verhuur Diversen",
    "sg:phone":"+31 43 450 1338",
    "sg:postcode":"6271 CL",
    "sg:province":"Limburg",
    "wof:name":"Marktkramenverhuurbedrijf M. Van Der Sangen",
    "wof:placetype":"venue"
},
  "geometry": {"coordinates":[5.885996,50.815102],"type":"Point"}
}