{
  "type": "Feature",
  "properties": {
    "addr:full":"Grt Fok 16 Urk Flevoland 8321 VW",
    "addr:housenumber":"16",
    "addr:postcode":"8321",
    "addr:street":"Fok;Flevoland;Vw",
    "iso:country":"NL",
    "sg:address":"Grt Fok 16",
    "sg:city":"Urk",
    "sg:orig_category":"Loonbedrijven",
    "sg:phone":"+31 6 22697523",
    "sg:postcode":"8321 VW",
    "sg:province":"Flevoland",
    "wof:name":"Boer'S Agri Service, De",
    "wof:placetype":"venue"
},
  "geometry": {"coordinates":[5.609606,52.665928],"type":"Point"}
}