{
  "type": "Feature",
  "properties": {
    "addr:full":"Kreeftstraat 18 Rotterdam Centrum Zuid-Holland 3067 JV",
    "addr:housenumber":"18",
    "addr:postcode":"3067 jv",
    "addr:street":"Kreeftstraat",
    "iso:country":"NL",
    "sg:address":"Kreeftstraat 18",
    "sg:city":"Rotterdam Centrum",
    "sg:orig_category":"Apothekers",
    "sg:phone":"+31 10 455 9344",
    "sg:postcode":"3067 JV",
    "sg:province":"Zuid-Holland",
    "wof:name":"Apotheek De Schorpioen",
    "wof:placetype":"venue"
},
  "geometry": {"coordinates":[4.556767,51.946926],"type":"Point"}
}