{
  "type": "Feature",
  "properties": {
    "iso:country":"NL",
    "sg:address":"Statenlaan 26",
    "sg:city":"'S Gravenhage",
    "sg:orig_category":"Werving And Selectie Van Vast Personeel",
    "sg:phone":"+31 6 53155331",
    "sg:postcode":"2582 GM",
    "sg:province":"South Holland",
    "wof:name":"Talentmatch",
    "wof:placetype":"venue"
},
  "geometry": {"coordinates":[4.2766489983,52.0919761658],"type":"Point"}
}