{
  "type": "Feature",
  "properties": {
    "addr:full":"De Wiekstr 1 Wormer Noord-Holland 1531 NV",
    "addr:housenumber":"1",
    "addr:postcode":"1531 nv",
    "addr:street":"Wormer",
    "iso:country":"NL",
    "sg:address":"De Wiekstr 1",
    "sg:city":"Wormer",
    "sg:orig_category":"Woningbouw- Verenigingen En -Stichtingen",
    "sg:phone":"+31 75 642 5291",
    "sg:postcode":"1531 NV",
    "sg:province":"Noord-Holland",
    "wof:name":"Lorzie, De",
    "wof:placetype":"venue"
},
  "geometry": {"coordinates":[4.8112850189,52.4980545044],"type":"Point"}
}