{
  "type": "Feature",
  "properties": {
    "addr:full":"De J De Jongstr 84 Rosmalen Noord-Brabant 5246 ED",
    "addr:housenumber":"84",
    "addr:postcode":"5246 ed",
    "addr:street":"De J De Jongstr",
    "iso:country":"NL",
    "sg:address":"De J De Jongstr 84",
    "sg:city":"Rosmalen",
    "sg:orig_category":"Administratie- En Boekhoudkantoren",
    "sg:phone":"+31 73 642 2618",
    "sg:postcode":"5246 ED",
    "sg:province":"Noord-Brabant",
    "wof:name":"Diebels",
    "wof:placetype":"venue"
},
  "geometry": {"coordinates":[5.34528,51.697468],"type":"Point"}
}