{
  "type": "Feature",
  "properties": {
    "addr:full":"De Appelboomstraat 11 Westzaan Noord-Holland 1551 BS",
    "addr:housenumber":"11;1551",
    "addr:postcode":"bs",
    "addr:street":"De Appelboomstraat",
    "iso:country":"NL",
    "sg:address":"De Appelboomstraat 11",
    "sg:city":"Westzaan",
    "sg:orig_category":"Schilderwerk",
    "sg:phone":"+31 75 771 3643",
    "sg:postcode":"1551 BS",
    "sg:province":"Noord-Holland",
    "wof:name":"K Visser",
    "wof:placetype":"venue"
},
  "geometry": {"coordinates":[4.769922,52.464882],"type":"Point"}
}