{
  "type": "Feature",
  "properties": {
    "addr:full":"Botlekwg 115 Botlek Rt South Holland 3197 KA",
    "addr:housenumber":"115",
    "addr:postcode":"3197 ka",
    "addr:street":"Botlek Rt South",
    "iso:country":"NL",
    "sg:address":"Botlekwg 115",
    "sg:city":"Botlek Rt",
    "sg:orig_category":"Warenhuizen",
    "sg:phone":"+31 10 416 1133",
    "sg:postcode":"3197 KA",
    "sg:province":"South Holland",
    "wof:name":"Botlek Stores Bv",
    "wof:placetype":"venue"
},
  "geometry": {"coordinates":[4.3074440956,51.8697814941],"type":"Point"}
}