{
  "type": "Feature",
  "properties": {
    "iso:country":"NL",
    "sg:address":"Witherenstraat 48",
    "sg:city":"Venlo",
    "sg:orig_category":"Bibliotheken And Openbare Archieven",
    "sg:phone":"+31 77 382 1071",
    "sg:postcode":"5921 GC",
    "sg:province":"Limburg",
    "wof:name":"Rk Openbare Leeszaal En Bibliotheek",
    "wof:placetype":"venue"
},
  "geometry": {"coordinates":[6.149041,51.366959],"type":"Point"}
}