{
  "type": "Feature",
  "properties": {
    "iso:country":"NL",
    "sg:address":"Heumenseweg 6",
    "sg:city":"Wijchen",
    "sg:orig_category":"Geluidsopnamen",
    "sg:phone":"+31 24 641 4260",
    "sg:postcode":"6603 CZ",
    "sg:province":"Gelderland",
    "wof:name":"F. Janssen Muziek",
    "wof:placetype":"venue"
},
  "geometry": {"coordinates":[5.762985,51.79892],"type":"Point"}
}