{
  "type": "Feature",
  "properties": {
    "iso:country":"NL",
    "sg:address":"Kempenaar 1502",
    "sg:city":"Lelystad",
    "sg:orig_category":"Kinderopvang",
    "sg:phone":"+31 320 242 542",
    "sg:postcode":"8231 EG",
    "sg:province":"Flevoland",
    "wof:name":"Pompoen Bso, De",
    "wof:placetype":"venue"
},
  "geometry": {"coordinates":[5.466745,52.520184],"type":"Point"}
}