{
  "type": "Feature",
  "properties": {
    "iso:country":"NL",
    "sg:address":"Hoofdweg 10",
    "sg:city":"Wedde",
    "sg:orig_category":"Musea And Historische Gebouwen",
    "sg:phone":"+31 597 562 652",
    "sg:postcode":"9698 AE",
    "sg:province":"Groningen",
    "wof:name":"Museum Grootmoeders Keuken",
    "wof:placetype":"venue"
},
  "geometry": {"coordinates":[7.07257,53.068581],"type":"Point"}
}