{
  "type": "Feature",
  "properties": {
    "addr:full":"Vd Bylstr 13 Roelofarendsveen Zuid-Holland 2371 VN",
    "addr:housenumber":"13",
    "addr:postcode":"2371 vn",
    "iso:country":"NL",
    "sg:address":"Vd Bylstr 13",
    "sg:city":"Roelofarendsveen",
    "sg:orig_category":"Montagebedrijven",
    "sg:phone":"+31 71 331 6991",
    "sg:postcode":"2371 VN",
    "sg:province":"Zuid-Holland",
    "wof:name":"Amsterdam, Fred Van",
    "wof:placetype":"venue"
},
  "geometry": {"coordinates":[4.632897,52.204285],"type":"Point"}
}