{
  "type": "Feature",
  "properties": {
    "addr:full":"V Eckstr 59 Arnhem Gelderland 6814 HW",
    "addr:housenumber":"59",
    "addr:postcode":"6814 hw",
    "iso:country":"NL",
    "sg:address":"V Eckstr 59",
    "sg:city":"Arnhem",
    "sg:orig_category":"Mensendieck - Oefentherapeuten",
    "sg:phone":"+31 26 445 1707",
    "sg:postcode":"6814 HW",
    "sg:province":"Gelderland",
    "wof:name":"Kouwenberg-Duijnhouwer, J H",
    "wof:placetype":"venue"
},
  "geometry": {"coordinates":[5.904585,51.985519],"type":"Point"}
}