{
  "type": "Feature",
  "properties": {
    "iso:country":"NL",
    "sg:address":"Kadeplein 2",
    "sg:city":"Roosendaal",
    "sg:orig_category":"Banken And Kredietinstellingen",
    "sg:phone":"+31 165 534 064",
    "sg:postcode":"4703 GB",
    "sg:province":"North Brabant",
    "wof:name":"Postkantoor",
    "wof:placetype":"venue"
},
  "geometry": {"coordinates":[4.451571,51.534737],"type":"Point"}
}