{
  "type": "Feature",
  "properties": {
    "addr:full":"Dotingastate 6 Leeuwarden Friesland 8926 MP",
    "addr:housenumber":"6",
    "addr:postcode":"8926 mp",
    "addr:street":"Dotingastate",
    "iso:country":"NL",
    "sg:address":"Dotingastate 6",
    "sg:city":"Leeuwarden",
    "sg:orig_category":"Architecten",
    "sg:phone":"+31 58 266 0022",
    "sg:postcode":"8926 MP",
    "sg:province":"Friesland",
    "wof:name":"Architectenbureau Ir. Meine Gerbenzon",
    "wof:placetype":"venue"
},
  "geometry": {"coordinates":[5.845662,53.215439],"type":"Point"}
}