{
  "type": "Feature",
  "properties": {
    "addr:full":"Nieuwestraat 27-29 Strijen Zuid-Holland 3291 AN",
    "addr:housenumber":"27-29",
    "addr:postcode":"3291 an",
    "addr:street":"Nieuwestraat",
    "iso:country":"NL",
    "sg:address":"Nieuwestraat 27-29",
    "sg:city":"Strijen",
    "sg:orig_category":"Goederenvervoer Over De Weg",
    "sg:phone":"+31 78 674 4063",
    "sg:postcode":"3291 AN",
    "sg:province":"Zuid-Holland",
    "wof:name":"Transportbedrijf E. Dorst",
    "wof:placetype":"venue"
},
  "geometry": {"coordinates":[4.549143,51.746857],"type":"Point"}
}