{
  "type": "Feature",
  "properties": {
    "addr:full":"De Kolk 30 Surhuisterveen Provincie Friesland 9231 CX",
    "addr:housenumber":"30",
    "addr:postcode":"9231 cx",
    "addr:street":"De Kolk;Provincie Friesland",
    "iso:country":"NL",
    "sg:address":"De Kolk 30",
    "sg:city":"Surhuisterveen",
    "sg:orig_category":"Woninginrichting",
    "sg:phone":"+31 512 365 650",
    "sg:postcode":"9231 CX",
    "sg:province":"Provincie Friesland",
    "wof:name":"Excesse",
    "wof:placetype":"venue"
},
  "geometry": {"coordinates":[6.165802002,53.1822395325],"type":"Point"}
}