{
  "type": "Feature",
  "properties": {
    "addr:full":"Piuspln 62-25 Tilburg Noord-Brabant 5038 WP",
    "addr:housenumber":"62-25",
    "addr:postcode":"5038 wp",
    "addr:street":"Tilburg",
    "iso:country":"NL",
    "sg:address":"Piuspln 62-25",
    "sg:city":"Tilburg",
    "sg:orig_category":"Verzekeringen - Verzekeringskantoren",
    "sg:phone":"+31 13 581 1177",
    "sg:postcode":"5038 WP",
    "sg:province":"Noord-Brabant",
    "wof:name":"Zakenbeheer Bv",
    "wof:placetype":"venue"
},
  "geometry": {"coordinates":[5.09105,51.555367],"type":"Point"}
}