{
  "type": "Feature",
  "properties": {
    "addr:full":"Staringln 60 Veenendaal Utrecht 3906 WJ",
    "addr:housenumber":"60",
    "addr:postcode":"3906 wj",
    "addr:street":"Staringln",
    "iso:country":"NL",
    "sg:address":"Staringln 60",
    "sg:city":"Veenendaal",
    "sg:orig_category":"Webdesign Bureaus",
    "sg:phone":"+31 318 526 269",
    "sg:postcode":"3906 WJ",
    "sg:province":"Utrecht",
    "sg:website":"http://www.wd60.nl",
    "wof:name":"Wd60",
    "wof:placetype":"venue"
},
  "geometry": {"coordinates":[5.5213451385,52.0251121521],"type":"Point"}
}