{
  "type": "Feature",
  "properties": {
    "addr:full":"G E C Ribbiuslaan 11 Rhoon Zuid-Holland 3161 HB",
    "addr:housenumber":"11",
    "addr:postcode":"3161 hb",
    "addr:street":"Ribbiuslaan",
    "iso:country":"NL",
    "sg:address":"G E C Ribbiuslaan 11",
    "sg:city":"Rhoon",
    "sg:orig_category":"Technische Studies And Onderzoek",
    "sg:phone":"+31 10 501 5928",
    "sg:postcode":"3161 HB",
    "sg:province":"Zuid-Holland",
    "wof:name":"J F E Ten Brink - Consulting Engineer",
    "wof:placetype":"venue"
},
  "geometry": {"coordinates":[4.427178,51.859737],"type":"Point"}
}