{
  "type": "Feature",
  "properties": {
    "addr:full":"Grutto 69 Bodegraven Zuid-Holland 2411 LR",
    "addr:housenumber":"69",
    "addr:postcode":"2411 lr",
    "addr:street":"Grutto",
    "iso:country":"NL",
    "sg:address":"Grutto 69",
    "sg:city":"Bodegraven",
    "sg:orig_category":"Verzekeringen - Verzekeringskantoren",
    "sg:phone":"+31 172 613 847",
    "sg:postcode":"2411 LR",
    "sg:province":"Zuid-Holland",
    "wof:name":"Onderlinge De Meije",
    "wof:placetype":"venue"
},
  "geometry": {"coordinates":[4.748922,52.074863],"type":"Point"}
}