{
  "type": "Feature",
  "properties": {
    "addr:full":"Burg Ter Veerstr 15 Moergestel Noord-Brabant 5066 GK",
    "addr:housenumber":"15",
    "addr:postcode":"5066 gk",
    "addr:street":"Burg Ter Veerstr",
    "iso:country":"NL",
    "sg:address":"Burg Ter Veerstr 15",
    "sg:city":"Moergestel",
    "sg:orig_category":"Onderhoudswerken",
    "sg:phone":"+31 13 513 3096",
    "sg:postcode":"5066 GK",
    "sg:province":"Noord-Brabant",
    "wof:name":"Frank Van Esch",
    "wof:placetype":"venue"
},
  "geometry": {"coordinates":[5.17774,51.538982],"type":"Point"}
}