{
  "type": "Feature",
  "properties": {
    "addr:full":"Hoofdstr 7 Kesteren Gelderland 4041 AA",
    "addr:housenumber":"7",
    "addr:postcode":"4041 aa",
    "addr:street":"Hoofdstr;Gelderland",
    "iso:country":"NL",
    "sg:address":"Hoofdstr 7",
    "sg:city":"Kesteren",
    "sg:orig_category":"Bloemen En Planten",
    "sg:phone":"+31 488 481 503",
    "sg:postcode":"4041 AA",
    "sg:province":"Gelderland",
    "wof:name":"Korenschoof, De",
    "wof:placetype":"venue"
},
  "geometry": {"coordinates":[5.574098,51.934513],"type":"Point"}
}