{
  "type": "Feature",
  "properties": {
    "addr:full":"Economiestr 39 Hoensbroek Limburg 6433 KC",
    "addr:housenumber":"39",
    "addr:postcode":"6433 kc",
    "addr:street":"Economiestr",
    "iso:country":"NL",
    "sg:address":"Economiestr 39",
    "sg:city":"Hoensbroek",
    "sg:orig_category":"Verpakkingsbedrijven",
    "sg:phone":"+31 45 533 1547",
    "sg:postcode":"6433 KC",
    "sg:province":"Limburg",
    "sg:website":"http://www.clip-lok.com",
    "wof:name":"Clip-Lok Simpak",
    "wof:placetype":"venue"
},
  "geometry": {"coordinates":[5.933451,50.90498],"type":"Point"}
}