{
  "type": "Feature",
  "properties": {
    "addr:full":"Zandstraat 2 Terneuzen Zeeland 4531 ES",
    "addr:housenumber":"2",
    "addr:postcode":"4531 es",
    "addr:street":"Zandstraat",
    "iso:country":"NL",
    "sg:address":"Zandstraat 2",
    "sg:city":"Terneuzen",
    "sg:orig_category":"Kinderopvang Behalve Thuis",
    "sg:phone":"+31 115 630 463",
    "sg:postcode":"4531 ES",
    "sg:province":"Zeeland",
    "wof:name":"Kinderdagverblijf 'T Hummeltje",
    "wof:placetype":"venue"
},
  "geometry": {"coordinates":[3.859698,51.30706],"type":"Point"}
}