{
  "type": "Feature",
  "properties": {
    "addr:full":"Picassopassage 74 Emmen Provincie Drenthe 7811 DP",
    "addr:housenumber":"74",
    "addr:postcode":"7811 dp",
    "addr:street":"Picassopassage;Provincie Drenthe",
    "iso:country":"NL",
    "sg:address":"Picassopassage 74",
    "sg:city":"Emmen",
    "sg:orig_category":"Opticiens",
    "sg:phone":"+31 591 670 850",
    "sg:postcode":"7811 DP",
    "sg:province":"Provincie Drenthe",
    "wof:name":"Fielmann",
    "wof:placetype":"venue"
},
  "geometry": {"coordinates":[6.8947300911,52.7830085754],"type":"Point"}
}