{
  "type": "Feature",
  "properties": {
    "addr:full":"Teslastr 72 Haarlem North Holland 2014 KN",
    "addr:housenumber":"72",
    "addr:postcode":"2014 kn",
    "addr:street":"Teslastr",
    "iso:country":"NL",
    "sg:address":"Teslastr 72",
    "sg:city":"Haarlem",
    "sg:orig_category":"Muziekinstrumenten En Bladmuziek",
    "sg:phone":"+31 23 544 1637",
    "sg:postcode":"2014 KN",
    "sg:province":"North Holland",
    "wof:name":"Tune-Up / Dikke Wanden",
    "wof:placetype":"venue"
},
  "geometry": {"coordinates":[4.614262,52.368156],"type":"Point"}
}