{
  "type": "Feature",
  "properties": {
    "addr:full":"Skagerrak 296 Hoofddorp Noord-Holland 2133 DW",
    "addr:housenumber":"296",
    "addr:postcode":"2133 dw",
    "addr:street":"Skagerrak",
    "iso:country":"NL",
    "sg:address":"Skagerrak 296",
    "sg:city":"Hoofddorp",
    "sg:classifiers":[
        {
            "category":"Education",
            "subcategory":"Preschool",
            "type":"Public Place"
        }
    ],
    "sg:phone":"+31 23 561 1499",
    "sg:postcode":"2133 DW",
    "sg:province":"Noord-Holland",
    "sg:tags":[
        "kleuteronderwijs",
        "basis-"
    ],
    "wof:name":"Openbare Basisschool Bikube",
    "wof:placetype":"venue"
},
  "geometry": {"coordinates":[4.671266,52.310036],"type":"Point"}
}