{
  "type": "Feature",
  "properties": {
    "addr:full":"Hoofdwg 4 Slochteren Groningen 9621 AL",
    "addr:housenumber":"4",
    "addr:postcode":"9621 al",
    "addr:street":"Hoofdwg",
    "iso:country":"NL",
    "sg:address":"Hoofdwg 4",
    "sg:city":"Slochteren",
    "sg:classifiers":[
        {
            "category":"Shopping",
            "subcategory":"News",
            "type":"Retail Goods"
        }
    ],
    "sg:phone":"+31 598 422 070",
    "sg:postcode":"9621 AL",
    "sg:province":"Groningen",
    "sg:tags":[
        "maandbladen",
        "en",
        "week-"
    ],
    "wof:name":"Bokkeblad, 'T",
    "wof:placetype":"venue"
},
  "geometry": {"coordinates":[6.805659771,53.2206573486],"type":"Point"}
}