{
  "type": "Feature",
  "properties": {
    "addr:full":"Rumpenerstraat 95 Brunssum Limburg 6443 CC",
    "addr:housenumber":"95",
    "addr:postcode":"6443 cc",
    "addr:street":"Rumpenerstraat",
    "iso:country":"NL",
    "sg:address":"Rumpenerstraat 95",
    "sg:city":"Brunssum",
    "sg:orig_category":"Fotostudio'S And Fotografen",
    "sg:phone":"+31 45 525 6159",
    "sg:postcode":"6443 CC",
    "sg:province":"Limburg",
    "wof:name":"P Craenen",
    "wof:placetype":"venue"
},
  "geometry": {"coordinates":[5.96935,50.940174],"type":"Point"}
}