{
  "type": "Feature",
  "properties": {
    "addr:full":"Rijnstraat 181 Amsterdam North Holland 1079 HD",
    "addr:housenumber":"181",
    "addr:postcode":"1079 hd",
    "addr:street":"Rijnstraat",
    "iso:country":"NL",
    "sg:address":"Rijnstraat 181",
    "sg:city":"Amsterdam",
    "sg:orig_category":"Boekhouders",
    "sg:phone":"+31 20 646 2629",
    "sg:postcode":"1079 HD",
    "sg:province":"North Holland",
    "wof:name":"Tosh Contracting Bv",
    "wof:placetype":"venue"
},
  "geometry": {"coordinates":[4.906994,52.342159],"type":"Point"}
}