{
  "type": "Feature",
  "properties": {
    "addr:full":"Kleiwegstraat 32 Gouda Zuid-Holland 2801 GM",
    "addr:housenumber":"32",
    "addr:postcode":"2801 gm",
    "addr:street":"Kleiwegstraat",
    "iso:country":"NL",
    "sg:address":"Kleiwegstraat 32",
    "sg:city":"Gouda",
    "sg:orig_category":"Herenmodezaken",
    "sg:phone":"+31 182 583 869",
    "sg:postcode":"2801 GM",
    "sg:province":"Zuid-Holland",
    "wof:name":"El Hombre",
    "wof:placetype":"venue"
},
  "geometry": {"coordinates":[4.708593,52.01387],"type":"Point"}
}