{
  "type": "Feature",
  "properties": {
    "addr:full":"Lagewg 27 Burgh Haamstede Zeeland 4328 RR",
    "addr:housenumber":"27",
    "addr:postcode":"4328 rr",
    "addr:street":"Lagewg;Haamstede",
    "iso:country":"NL",
    "sg:address":"Lagewg 27",
    "sg:city":"Burgh Haamstede",
    "sg:orig_category":"Vakantieverblijven",
    "sg:phone":"+31 111 653 448",
    "sg:postcode":"4328 RR",
    "sg:province":"Zeeland",
    "wof:name":"Meijpacht, De",
    "wof:placetype":"venue"
},
  "geometry": {"coordinates":[3.709795,51.673737],"type":"Point"}
}