{
  "type": "Feature",
  "properties": {
    "addr:full":"Middelwg 32 Leiden Zuid-Holland 2312 KJ",
    "addr:housenumber":"32",
    "addr:postcode":"2312 kj",
    "addr:street":"Middelwg",
    "iso:country":"NL",
    "sg:address":"Middelwg 32",
    "sg:city":"Leiden",
    "sg:orig_category":"Zeilmakerijen",
    "sg:phone":"+31 71 512 5307",
    "sg:postcode":"2312 KJ",
    "sg:province":"Zuid-Holland",
    "wof:name":"Bruss?, L B",
    "wof:placetype":"venue"
},
  "geometry": {"coordinates":[4.495145,52.158794],"type":"Point"}
}