{
  "type": "Feature",
  "properties": {
    "iso:country":"NL",
    "sg:address":"Beekenkampwg 33",
    "sg:city":"Doornspyk",
    "sg:orig_category":"Kappers",
    "sg:phone":"+31 6 23817621",
    "sg:postcode":"8085 BR",
    "sg:province":"Gelderland",
    "wof:name":"Boven, Anita Van",
    "wof:placetype":"venue"
},
  "geometry": {"coordinates":[5.8185300827,52.4216804504],"type":"Point"}
}