{
  "type": "Feature",
  "properties": {
    "addr:full":"Vyzelstr 17 Leeuwarden Friesland 8911 EW",
    "addr:housenumber":"17",
    "addr:postcode":"8911 ew",
    "addr:street":"Vyzelstr",
    "iso:country":"NL",
    "sg:address":"Vyzelstr 17",
    "sg:city":"Leeuwarden",
    "sg:orig_category":"Verlichting",
    "sg:phone":"+31 58 213 3961",
    "sg:postcode":"8911 EW",
    "sg:province":"Friesland",
    "wof:name":"Lampada",
    "wof:placetype":"venue"
},
  "geometry": {"coordinates":[5.798309,53.205135],"type":"Point"}
}