{
  "type": "Feature",
  "properties": {
    "addr:full":"Coppenolstraat 10 Alkmaar Noord-Holland 1827 JP",
    "addr:housenumber":"10",
    "addr:postcode":"1827 jp",
    "addr:street":"Coppenolstraat",
    "iso:country":"NL",
    "sg:address":"Coppenolstraat 10",
    "sg:city":"Alkmaar",
    "sg:orig_category":"Bloemen And Planten",
    "sg:phone":"+31 72 562 4643",
    "sg:postcode":"1827 JP",
    "sg:province":"Noord-Holland",
    "wof:name":"Jarlin Zijdebloemen",
    "wof:placetype":"venue"
},
  "geometry": {"coordinates":[4.761265,52.672832],"type":"Point"}
}