{
  "type": "Feature",
  "properties": {
    "addr:full":"Hogenendseweg 2 Didam Gelderland 6942 DV",
    "addr:housenumber":"2",
    "addr:postcode":"6942",
    "addr:street":"Hogenendseweg;Gelderland",
    "iso:country":"NL",
    "sg:address":"Hogenendseweg 2",
    "sg:city":"Didam",
    "sg:orig_category":"Verzekeringen",
    "sg:phone":"+31 316 225 941",
    "sg:postcode":"6942 DV",
    "sg:province":"Gelderland",
    "wof:name":"Eijmans Assurantien",
    "wof:placetype":"venue"
},
  "geometry": {"coordinates":[6.13044,51.933926],"type":"Point"}
}