{
  "type": "Feature",
  "properties": {
    "addr:full":"R Boelemastr 24 Stiens Friesland 9051 CH",
    "addr:housenumber":"24",
    "addr:postcode":"9051",
    "iso:country":"NL",
    "sg:address":"R Boelemastr 24",
    "sg:city":"Stiens",
    "sg:orig_category":"Plafonds",
    "sg:phone":"+31 58 257 3289",
    "sg:postcode":"9051 CH",
    "sg:province":"Friesland",
    "wof:name":"Bks",
    "wof:placetype":"venue"
},
  "geometry": {"coordinates":[5.762418,53.261799],"type":"Point"}
}