{
  "type": "Feature",
  "properties": {
    "addr:full":"Nijverheidsstraat 30 'S Heer Arendskerke Zeeland 4458 AV",
    "addr:housenumber":"30",
    "addr:postcode":"4458 av",
    "addr:street":"Nijverheidsstraat;' S Heer Arendskerke",
    "iso:country":"NL",
    "sg:address":"Nijverheidsstraat 30",
    "sg:city":"'S Heer Arendskerke",
    "sg:orig_category":"Autokeuringen",
    "sg:phone":"+31 113 561 871",
    "sg:postcode":"4458 AV",
    "sg:province":"Zeeland",
    "wof:name":"Garage Auto De Laat",
    "wof:placetype":"venue"
},
  "geometry": {"coordinates":[3.824743,51.498947],"type":"Point"}
}