{
  "type": "Feature",
  "properties": {
    "addr:full":"Zevenend 33 Laren Nh Noord-Holland 1251 RL",
    "addr:housenumber":"33",
    "addr:postcode":"1251 rl",
    "addr:street":"Zevenend",
    "iso:country":"NL",
    "sg:address":"Zevenend 33",
    "sg:city":"Laren Nh",
    "sg:orig_category":"Kunst And Kunstenaarsbenodigdheden",
    "sg:phone":"+31 35 531 9121",
    "sg:postcode":"1251 RL",
    "sg:province":"Noord-Holland",
    "wof:name":"Kessel",
    "wof:placetype":"venue"
},
  "geometry": {"coordinates":[5.228328,52.253239],"type":"Point"}
}