{
  "type": "Feature",
  "properties": {
    "addr:full":"Nijverheidsweg 17D Mijdrecht Utrecht 3641 RP",
    "addr:housenumber":"17d",
    "addr:postcode":"3641 rp",
    "addr:street":"Nijverheidsweg",
    "iso:country":"NL",
    "sg:address":"Nijverheidsweg 17D",
    "sg:city":"Mijdrecht",
    "sg:orig_category":"Marketingbureaus",
    "sg:phone":"+31 297 286 963",
    "sg:postcode":"3641 RP",
    "sg:province":"Utrecht",
    "wof:name":"Data Mail Bv",
    "wof:placetype":"venue"
},
  "geometry": {"coordinates":[4.874938,52.20322],"type":"Point"}
}