{
  "type": "Feature",
  "properties": {
    "iso:country":"NL",
    "sg:address":"Kruisstr 16",
    "sg:city":"Slootdorp",
    "sg:orig_category":"Betonwerken",
    "sg:phone":"+31 227 581 976",
    "sg:postcode":"1774 AG",
    "sg:province":"Noord-Holland",
    "wof:name":"Jervin'S Bouwchemie",
    "wof:placetype":"venue"
},
  "geometry": {"coordinates":[4.972539,52.841949],"type":"Point"}
}