{
  "type": "Feature",
  "properties": {
    "addr:full":"Sint Jansstraat 77 Hoensbroek Limburg 6431 ND",
    "addr:housenumber":"77",
    "addr:postcode":"6431 nd",
    "addr:street":"Sint Jansstraat",
    "iso:country":"NL",
    "sg:address":"Sint Jansstraat 77",
    "sg:city":"Hoensbroek",
    "sg:orig_category":"Metaalbekleding And -Behandeling",
    "sg:phone":"+31 45 521 6393",
    "sg:postcode":"6431 ND",
    "sg:province":"Limburg",
    "wof:name":"Repol",
    "wof:placetype":"venue"
},
  "geometry": {"coordinates":[5.92649,50.92086],"type":"Point"}
}