{
  "type": "Feature",
  "properties": {
    "addr:full":"Oosterwg M 35 Purmer North Holland 1482 AK",
    "addr:housenumber":"35",
    "addr:postcode":"1482 ak",
    "iso:country":"NL",
    "sg:address":"Oosterwg M 35",
    "sg:city":"Purmer",
    "sg:orig_category":"Zoetwaren - Fabrieken En Groothandel",
    "sg:phone":"+31 299 645 751",
    "sg:postcode":"1482 AK",
    "sg:province":"North Holland",
    "wof:name":"Huyser M\u00f7Ller Bv",
    "wof:placetype":"venue"
},
  "geometry": {"coordinates":[5.007471,52.488876],"type":"Point"}
}