{
  "type": "Feature",
  "properties": {
    "addr:full":"Industriewg 10 Assendelft North Holland 1566 JP",
    "addr:housenumber":"10",
    "addr:postcode":"1566 jp",
    "addr:street":"Industriewg",
    "iso:country":"NL",
    "sg:address":"Industriewg 10",
    "sg:city":"Assendelft",
    "sg:orig_category":"Woninginrichting",
    "sg:phone":"+31 75 657 1214",
    "sg:postcode":"1566 JP",
    "sg:province":"North Holland",
    "wof:name":"Gooijer",
    "wof:placetype":"venue"
},
  "geometry": {"coordinates":[4.7651438713,52.4923782349],"type":"Point"}
}