{
  "type": "Feature",
  "properties": {
    "addr:full":"Julianawg 8 Utrecht Utrecht 3525 VG",
    "addr:housenumber":"8",
    "addr:postcode":"3525 vg",
    "addr:street":"Julianawg",
    "iso:country":"NL",
    "sg:address":"Julianawg 8",
    "sg:city":"Utrecht",
    "sg:orig_category":"Administratie- En Boekhoudkantoren",
    "sg:phone":"+31 30 288 6917",
    "sg:postcode":"3525 VG",
    "sg:province":"Utrecht",
    "wof:name":"Koster, M U L",
    "wof:placetype":"venue"
},
  "geometry": {"coordinates":[5.116649,52.06097],"type":"Point"}
}