{
  "type": "Feature",
  "properties": {
    "addr:full":"Galileistraat 17 Heerhugowaard North Holland 1704 SE",
    "addr:housenumber":"17",
    "addr:postcode":"1704 se",
    "addr:street":"Galileistraat",
    "iso:country":"NL",
    "sg:address":"Galileistraat 17",
    "sg:city":"Heerhugowaard",
    "sg:orig_category":"Verhuur Bouwmachines",
    "sg:phone":"+31 72 571 4956",
    "sg:postcode":"1704 SE",
    "sg:province":"North Holland",
    "wof:name":"Stammis Verhuur Bv",
    "wof:placetype":"venue"
},
  "geometry": {"coordinates":[4.827896,52.687679],"type":"Point"}
}