{
  "type": "Feature",
  "properties": {
    "addr:full":"Schans 26 Blaricum Noord-Holland 1261 MK",
    "addr:housenumber":"26",
    "addr:postcode":"1261",
    "addr:street":"Schans",
    "iso:country":"NL",
    "sg:address":"Schans 26",
    "sg:city":"Blaricum",
    "sg:orig_category":"Bedrijfsopleidingen",
    "sg:phone":"+31 35 523 5247",
    "sg:postcode":"1261 MK",
    "sg:province":"Noord-Holland",
    "wof:name":"Wb-Adv",
    "wof:placetype":"venue"
},
  "geometry": {"coordinates":[5.271785,52.285069],"type":"Point"}
}