{
  "type": "Feature",
  "properties": {
    "addr:full":"Spui 4 Edam Noord-Holland 1135 BA",
    "addr:housenumber":"4",
    "addr:postcode":"1135 ba",
    "addr:street":"Spui",
    "iso:country":"NL",
    "sg:address":"Spui 4",
    "sg:city":"Edam",
    "sg:orig_category":"Zoetwaren - Winkels",
    "sg:phone":"+31 299 371 389",
    "sg:postcode":"1135 BA",
    "sg:province":"Noord-Holland",
    "wof:name":"Snoepwinkeltje, 'T",
    "wof:placetype":"venue"
},
  "geometry": {"coordinates":[5.048415,52.512657],"type":"Point"}
}