{
  "type": "Feature",
  "properties": {
    "addr:full":"Langstraat 69 Wijhe NL.08 8131 BB",
    "addr:housenumber":"69;nl.08",
    "addr:postcode":"8131 bb",
    "addr:street":"Langstraat",
    "iso:country":"NL",
    "sg:address":"Langstraat 69",
    "sg:city":"Wijhe",
    "sg:orig_category":"Meubelzaken, Woning- And Keukeninrichting",
    "sg:phone":"+31 570 524 268",
    "sg:postcode":"8131 BB",
    "sg:province":"NL.08",
    "wof:name":"Akkerman Wonen",
    "wof:placetype":"venue"
},
  "geometry": {"coordinates":[6.1359,52.38678],"type":"Point"}
}