{
  "type": "Feature",
  "properties": {
    "iso:country":"NL",
    "sg:address":"Pannekoekstr 55",
    "sg:city":"Rotterdam",
    "sg:orig_category":"Kinderactiviteiten",
    "sg:phone":"+31 10 414 3103",
    "sg:postcode":"3011 LC",
    "sg:province":"South Holland",
    "sg:website":"http://www.ontdekhoek.nl",
    "wof:name":"Ontdekhoek, De",
    "wof:placetype":"venue"
},
  "geometry": {"coordinates":[4.487935,51.923035],"type":"Point"}
}