{
  "type": "Feature",
  "properties": {
    "addr:full":"Venedie 23 Enkhuizen Noord-Holland 1601 HA",
    "addr:housenumber":"23",
    "addr:postcode":"1601 ha",
    "addr:street":"Venedie",
    "iso:country":"NL",
    "sg:address":"Venedie 23",
    "sg:city":"Enkhuizen",
    "sg:orig_category":"Makelaars In Onroerend Goed",
    "sg:phone":"+31 228 313 816",
    "sg:postcode":"1601 HA",
    "sg:province":"Noord-Holland",
    "wof:name":"De Wit Makelaars",
    "wof:placetype":"venue"
},
  "geometry": {"coordinates":[5.290285,52.702587],"type":"Point"}
}