{
  "type": "Feature",
  "properties": {
    "addr:full":"Multatulistraat 96 'S Gravenhage South Holland 2524 KL",
    "addr:housenumber":"96",
    "addr:postcode":"2524 kl",
    "addr:street":"Multatulistraat;' S Gravenhage",
    "iso:country":"NL",
    "sg:address":"Multatulistraat 96",
    "sg:city":"'S Gravenhage",
    "sg:orig_category":"Verlichting And Huishoudartikelen",
    "sg:phone":"+31 70 396 0819",
    "sg:postcode":"2524 KL",
    "sg:province":"South Holland",
    "wof:name":"Firma Talen",
    "wof:placetype":"venue"
},
  "geometry": {"coordinates":[4.313496,52.0518],"type":"Point"}
}