{
  "type": "Feature",
  "properties": {
    "iso:country":"NL",
    "sg:address":"Oude Haagsewg 59",
    "sg:city":"Amsterdam",
    "sg:orig_category":"Grafmonumenten",
    "sg:phone":"+31 20 676 2668",
    "sg:postcode":"1066 DC",
    "sg:province":"North Holland",
    "wof:name":"Mieke Folgering",
    "wof:placetype":"venue"
},
  "geometry": {"coordinates":[4.810971,52.330727],"type":"Point"}
}