{
  "type": "Feature",
  "properties": {
    "addr:full":"Hogewaard 11 Ameide Zuid-Holland 4233 VX",
    "addr:housenumber":"11",
    "addr:postcode":"4233 vx",
    "addr:street":"Hogewaard",
    "iso:country":"NL",
    "sg:address":"Hogewaard 11",
    "sg:city":"Ameide",
    "sg:orig_category":"Schilders",
    "sg:phone":"+31 183 601 447",
    "sg:postcode":"4233 VX",
    "sg:province":"Zuid-Holland",
    "wof:name":"Weeda Schildersbedrijf, A",
    "wof:placetype":"venue"
},
  "geometry": {"coordinates":[4.957861,51.95409],"type":"Point"}
}