{
  "type": "Feature",
  "properties": {
    "addr:full":"Europaln 79A Bladel Noord-Brabant 5531 BG",
    "addr:housenumber":"79a",
    "addr:postcode":"5531",
    "addr:street":"Europaln",
    "iso:country":"NL",
    "sg:address":"Europaln 79A",
    "sg:city":"Bladel",
    "sg:orig_category":"Makelaars En Adviseurs Onroerende Goederen",
    "sg:phone":"+31 497 330 806",
    "sg:postcode":"5531 BG",
    "sg:province":"Noord-Brabant",
    "wof:name":"Verhagen Invest",
    "wof:placetype":"venue"
},
  "geometry": {"coordinates":[5.21485,51.366089],"type":"Point"}
}