{
  "type": "Feature",
  "properties": {
    "addr:full":"Engweg 3 Elst Ut Utrecht 3921 DN",
    "addr:housenumber":"3",
    "addr:postcode":"ut;3921 dn",
    "addr:street":"Engweg",
    "iso:country":"NL",
    "sg:address":"Engweg 3",
    "sg:city":"Elst Ut",
    "sg:orig_category":"Metaalbekleding And -Behandeling",
    "sg:phone":"+31 318 471 296",
    "sg:postcode":"3921 DN",
    "sg:province":"Utrecht",
    "wof:name":"Veenhof'S Slijperij",
    "wof:placetype":"venue"
},
  "geometry": {"coordinates":[5.506,51.98962],"type":"Point"}
}