{
  "type": "Feature",
  "properties": {
    "addr:full":"Prinsengr 473H Amsterdam Noord-Holland 1016 HP",
    "addr:housenumber":"473h",
    "addr:postcode":"1016 hp",
    "addr:street":"Prinsengr",
    "iso:country":"NL",
    "sg:address":"Prinsengr 473H",
    "sg:city":"Amsterdam",
    "sg:orig_category":"Grafologen",
    "sg:phone":"+31 20 627 8222",
    "sg:postcode":"1016 HP",
    "sg:province":"Noord-Holland",
    "wof:name":"Ellemers, C",
    "wof:placetype":"venue"
},
  "geometry": {"coordinates":[4.883161,52.369507],"type":"Point"}
}