{
  "type": "Feature",
  "properties": {
    "addr:full":"Helene Swarthlaan 37 Uithoorn Noord-Holland 1422 KG",
    "addr:housenumber":"37",
    "addr:postcode":"1422 kg",
    "addr:street":"Helene Swarthlaan",
    "iso:country":"NL",
    "sg:address":"Helene Swarthlaan 37",
    "sg:city":"Uithoorn",
    "sg:orig_category":"Scheepsmotoren - Reparatie",
    "sg:phone":"+31 297 523 981",
    "sg:postcode":"1422 KG",
    "sg:province":"Noord-Holland",
    "wof:name":"Haes Bv",
    "wof:placetype":"venue"
},
  "geometry": {"coordinates":[4.827837,52.251236],"type":"Point"}
}