{
  "type": "Feature",
  "properties": {
    "addr:full":"Rynstr 7 Wyk By Duurstede Utrecht 3961 CD",
    "addr:housenumber":"7",
    "addr:postcode":"duurstede;3961 cd",
    "addr:street":"Rynstr",
    "iso:country":"NL",
    "sg:address":"Rynstr 7",
    "sg:city":"Wyk By Duurstede",
    "sg:orig_category":"Glazenwasserijen",
    "sg:phone":"+31 343 577 689",
    "sg:postcode":"3961 CD",
    "sg:province":"Utrecht",
    "wof:name":"Glashelder",
    "wof:placetype":"venue"
},
  "geometry": {"coordinates":[5.345255,51.972858],"type":"Point"}
}