{
  "type": "Feature",
  "properties": {
    "addr:full":"Molenstraat 85 Tubbergen Overijssel 7651 AV",
    "addr:housenumber":"85",
    "addr:postcode":"7651 av",
    "addr:street":"Molenstraat",
    "iso:country":"NL",
    "sg:address":"Molenstraat 85",
    "sg:city":"Tubbergen",
    "sg:orig_category":"Diverse Consumentenartikelen Gh",
    "sg:phone":"+31 546 621 738",
    "sg:postcode":"7651 AV",
    "sg:province":"Overijssel",
    "wof:name":"B.H. Wispelwey-Geerdink",
    "wof:placetype":"venue"
},
  "geometry": {"coordinates":[6.787857,52.407696],"type":"Point"}
}