{
  "type": "Feature",
  "properties": {
    "addr:full":"Wondklaver 1 Rotterdam Zuid-Holland 3069 DR",
    "addr:housenumber":"1",
    "addr:postcode":"3069 dr",
    "addr:street":"Wondklaver",
    "iso:country":"NL",
    "sg:address":"Wondklaver 1",
    "sg:city":"Rotterdam",
    "sg:orig_category":"Glazenwasserijen",
    "sg:phone":"+31 10 421 9642",
    "sg:postcode":"3069 DR",
    "sg:province":"Zuid-Holland",
    "wof:name":"Waterstad",
    "wof:placetype":"venue"
},
  "geometry": {"coordinates":[4.531989,51.965363],"type":"Point"}
}