{
  "type": "Feature",
  "properties": {
    "addr:full":"Pr Bernhardln 24 Amerongen Utrecht 3958 VM",
    "addr:housenumber":"24",
    "addr:postcode":"3958 vm",
    "addr:street":"Amerongen",
    "iso:country":"NL",
    "sg:address":"Pr Bernhardln 24",
    "sg:city":"Amerongen",
    "sg:orig_category":"Kappers",
    "sg:phone":"+31 343 451 961",
    "sg:postcode":"3958 VM",
    "sg:province":"Utrecht",
    "wof:name":"Anja",
    "wof:placetype":"venue"
},
  "geometry": {"coordinates":[5.4602298737,52.0007019043],"type":"Point"}
}