{
  "type": "Feature",
  "properties": {
    "addr:full":"Addenshoeve 12 Rhenen Utrecht 3911 TG",
    "addr:housenumber":"12",
    "addr:postcode":"3911 tg",
    "addr:street":"Addenshoeve",
    "iso:country":"NL",
    "sg:address":"Addenshoeve 12",
    "sg:city":"Rhenen",
    "sg:orig_category":"Schilders",
    "sg:phone":"+31 317 612 001",
    "sg:postcode":"3911 TG",
    "sg:province":"Utrecht",
    "wof:name":"Grift Rhenen Bv, Van Der",
    "wof:placetype":"venue"
},
  "geometry": {"coordinates":[5.534634,51.971272],"type":"Point"}
}