{
  "type": "Feature",
  "properties": {
    "iso:country":"NL",
    "sg:address":"Koningsvaren 5",
    "sg:city":"Bergschenhoek",
    "sg:orig_category":"Kantoor- En Secretariaatsservice",
    "sg:phone":"+31 10 522 5111",
    "sg:postcode":"2661 PB",
    "sg:province":"Zuid-Holland",
    "wof:name":"Wolff, De",
    "wof:placetype":"venue"
},
  "geometry": {"coordinates":[4.5001521111,51.9925537109],"type":"Point"}
}