{
  "type": "Feature",
  "properties": {
    "addr:full":"Ocarinalaan 414 Rijswijk Zh South Holland 2287 RN",
    "addr:housenumber":"414",
    "addr:postcode":"2287 rn",
    "addr:street":"Ocarinalaan",
    "iso:country":"NL",
    "sg:address":"Ocarinalaan 414",
    "sg:city":"Rijswijk Zh",
    "sg:orig_category":"Bedrijfs- And Managementsconsultants",
    "sg:phone":"+31 70 396 3288",
    "sg:postcode":"2287 RN",
    "sg:province":"South Holland",
    "wof:name":"Antrovista",
    "wof:placetype":"venue"
},
  "geometry": {"coordinates":[4.319569,52.031971],"type":"Point"}
}