{
  "type": "Feature",
  "properties": {
    "addr:full":"Akersingel 230 Amsterdam Noord-Holland 1060 NK",
    "addr:housenumber":"230",
    "addr:postcode":"1060 nk",
    "addr:street":"Akersingel",
    "iso:country":"NL",
    "sg:address":"Akersingel 230",
    "sg:city":"Amsterdam",
    "sg:orig_category":"Alternatieve Geneeskunde",
    "sg:phone":"+31 20 410 0177",
    "sg:postcode":"1060 NK",
    "sg:province":"Noord-Holland",
    "wof:name":"Apotheek De Vaart",
    "wof:placetype":"venue"
},
  "geometry": {"coordinates":[4.774239,52.35376],"type":"Point"}
}