{
  "type": "Feature",
  "properties": {
    "addr:full":"Past Wynenwg 16 Maastricht Limburg 6214 RD",
    "addr:housenumber":"16",
    "addr:postcode":"6214 rd",
    "iso:country":"NL",
    "sg:address":"Past Wynenwg 16",
    "sg:city":"Maastricht",
    "sg:orig_category":"Verhuur",
    "sg:phone":"+31 43 325 8867",
    "sg:postcode":"6214 RD",
    "sg:province":"Limburg",
    "wof:name":"Taterstein Bv, De",
    "wof:placetype":"venue"
},
  "geometry": {"coordinates":[5.675106,50.84576],"type":"Point"}
}