{
  "type": "Feature",
  "properties": {
    "addr:full":"J Campertstr 28 Westkapelle Zeeland 4361 DE",
    "addr:housenumber":"28",
    "addr:postcode":"4361 de",
    "iso:country":"NL",
    "sg:address":"J Campertstr 28",
    "sg:city":"Westkapelle",
    "sg:orig_category":"Wasmachines En Wasdrogers - Onderhoud En Reparatie",
    "sg:phone":"+31 118 572 427",
    "sg:postcode":"4361 DE",
    "sg:province":"Zeeland",
    "wof:name":"Aangeenbrug",
    "wof:placetype":"venue"
},
  "geometry": {"coordinates":[3.4421429634,51.5334320068],"type":"Point"}
}