{
  "type": "Feature",
  "properties": {
    "iso:country":"NL",
    "sg:address":"Kleiwg 84B",
    "sg:city":"Gouda",
    "sg:orig_category":"Adviesbureaus Bedrijfsorganisatie",
    "sg:phone":"+31 182 586 273",
    "sg:postcode":"2801 GJ",
    "sg:province":"South Holland",
    "wof:name":"Commforte",
    "wof:placetype":"venue"
},
  "geometry": {"coordinates":[4.709743,52.014244],"type":"Point"}
}