{
  "type": "Feature",
  "properties": {
    "addr:full":"Konnetln 4 Rysenhout North Holland 1435 HW",
    "addr:housenumber":"4",
    "addr:postcode":"1435 hw",
    "addr:street":"Konnetln;North",
    "iso:country":"NL",
    "sg:address":"Konnetln 4",
    "sg:city":"Rysenhout",
    "sg:orig_category":"Kantoor- En Bedrijfsmeubelen",
    "sg:phone":"+31 297 368 230",
    "sg:postcode":"1435 HW",
    "sg:province":"North Holland",
    "wof:name":"Dol",
    "wof:placetype":"venue"
},
  "geometry": {"coordinates":[4.7146539688,52.2575302124],"type":"Point"}
}