{
  "type": "Feature",
  "properties": {
    "addr:full":"Blokland 32 Sch. Nieuwveen Zuid-Holland 2441 GG",
    "addr:housenumber":"32",
    "addr:postcode":"2441 gg",
    "addr:street":"Blokland;Sch.",
    "iso:country":"NL",
    "sg:address":"Blokland 32 Sch.",
    "sg:city":"Nieuwveen",
    "sg:orig_category":"Sanitaire Artikelen",
    "sg:phone":"+31 172 537 018",
    "sg:postcode":"2441 GG",
    "sg:province":"Zuid-Holland",
    "wof:name":"Mansion House",
    "wof:placetype":"venue"
},
  "geometry": {"coordinates":[4.75722,52.196278],"type":"Point"}
}