{
  "type": "Feature",
  "properties": {
    "addr:full":"Balsa 158 Dordrecht South Holland 3315 NK",
    "addr:housenumber":"158",
    "addr:postcode":"3315 nk",
    "addr:street":"Balsa",
    "iso:country":"NL",
    "sg:address":"Balsa 158",
    "sg:city":"Dordrecht",
    "sg:orig_category":"Binnenhuisarchitecten",
    "sg:phone":"+31 78 621 0957",
    "sg:postcode":"3315 NK",
    "sg:province":"South Holland",
    "wof:name":"123Dii",
    "wof:placetype":"venue"
},
  "geometry": {"coordinates":[4.71359,51.81152],"type":"Point"}
}