{
  "type": "Feature",
  "properties": {
    "addr:full":"Paulinastraat 46 Sint Oedenrode North Brabant 5491 JH",
    "addr:housenumber":"46",
    "addr:postcode":"5491 jh",
    "addr:street":"Paulinastraat;Sint Oedenrode",
    "iso:country":"NL",
    "sg:address":"Paulinastraat 46",
    "sg:city":"Sint Oedenrode",
    "sg:orig_category":"Elektronische Bedrijfsinstallaties",
    "sg:phone":"+31 413 477 693",
    "sg:postcode":"5491 JH",
    "sg:province":"North Brabant",
    "wof:name":"B. Van Ravenstein",
    "wof:placetype":"venue"
},
  "geometry": {"coordinates":[5.45803,51.575039],"type":"Point"}
}