{
  "type": "Feature",
  "properties": {
    "iso:country":"NL",
    "sg:address":"Schapenmarkt 5",
    "sg:city":"S Hertogenbosch",
    "sg:orig_category":"Opticiens",
    "sg:phone":"+31 73 613 2555",
    "sg:postcode":"5211 ES",
    "sg:province":"North Brabant",
    "wof:name":"Maaren, Carl Van",
    "wof:placetype":"venue"
},
  "geometry": {"coordinates":[5.3024787903,51.6885223389],"type":"Point"}
}