{
  "type": "Feature",
  "properties": {
    "addr:full":"Breezandpad 5 Arnhem Gelderland 6843 JM",
    "addr:housenumber":"5",
    "addr:postcode":"6843 jm",
    "addr:street":"Breezandpad",
    "iso:country":"NL",
    "sg:address":"Breezandpad 5",
    "sg:city":"Arnhem",
    "sg:orig_category":"Kinderopvang",
    "sg:phone":"+31 26 321 8164",
    "sg:postcode":"6843 JM",
    "sg:province":"Gelderland",
    "wof:name":"Klavertje, Het",
    "wof:placetype":"venue"
},
  "geometry": {"coordinates":[5.863987,51.961643],"type":"Point"}
}