{
  "type": "Feature",
  "properties": {
    "addr:full":"Vordenseweg 6 Lochem Gelderland 7241 SB",
    "addr:housenumber":"6",
    "addr:postcode":"7241 sb",
    "addr:street":"Vordenseweg;Gelderland",
    "iso:country":"NL",
    "sg:address":"Vordenseweg 6",
    "sg:city":"Lochem",
    "sg:orig_category":"Levende Dieren Gh",
    "sg:phone":"+31 573 257 299",
    "sg:postcode":"7241 SB",
    "sg:province":"Gelderland",
    "wof:name":"Veehandel G.J. Kok",
    "wof:placetype":"venue"
},
  "geometry": {"coordinates":[6.388534,52.147335],"type":"Point"}
}