{
  "type": "Feature",
  "properties": {
    "addr:full":"Reijnier Vinkeleskade 64 Amsterdam Noord-Holland 1071 SX",
    "addr:housenumber":"64",
    "addr:postcode":"1071 sx",
    "addr:street":"Reijnier Vinkeleskade",
    "iso:country":"NL",
    "sg:address":"Reijnier Vinkeleskade 64",
    "sg:city":"Amsterdam",
    "sg:orig_category":"Advocaten And Juridische Adviseurs",
    "sg:phone":"+31 20 664 4313",
    "sg:postcode":"1071 SX",
    "sg:province":"Noord-Holland",
    "wof:name":"Van Driem Advocatenkantoor",
    "wof:placetype":"venue"
},
  "geometry": {"coordinates":[4.87618,52.352146],"type":"Point"}
}