{
  "type": "Feature",
  "properties": {
    "addr:full":"Bocholtzerwg 18 Simpelveld Limburg 6369 TG",
    "addr:housenumber":"18",
    "addr:postcode":"6369 tg",
    "addr:street":"Bocholtzerwg",
    "iso:country":"NL",
    "sg:address":"Bocholtzerwg 18",
    "sg:city":"Simpelveld",
    "sg:orig_category":"Boekbinderijen",
    "sg:phone":"+31 45 544 0645",
    "sg:postcode":"6369 TG",
    "sg:province":"Limburg",
    "wof:name":"Berg, M Van Den",
    "wof:placetype":"venue"
},
  "geometry": {"coordinates":[5.989372,50.829807],"type":"Point"}
}