{
  "type": "Feature",
  "properties": {
    "addr:full":"Parallelstr 41 Nuth Limburg 6361 XK",
    "addr:housenumber":"41",
    "addr:postcode":"6361 xk",
    "addr:street":"Parallelstr",
    "iso:country":"NL",
    "sg:address":"Parallelstr 41",
    "sg:city":"Nuth",
    "sg:orig_category":"Scholen Voor Basisonderwijs",
    "sg:phone":"+31 45 524 2242",
    "sg:postcode":"6361 XK",
    "sg:province":"Limburg",
    "wof:name":"Elckerlyceum",
    "wof:placetype":"venue"
},
  "geometry": {"coordinates":[5.889676,50.916664],"type":"Point"}
}