{
  "type": "Feature",
  "properties": {
    "addr:full":"Harry Hoekstraat 86 Wateringen Zuid-Holland 2291 SR",
    "addr:housenumber":"86",
    "addr:postcode":"2291 sr",
    "addr:street":"Harry Hoekstraat",
    "iso:country":"NL",
    "sg:address":"Harry Hoekstraat 86",
    "sg:city":"Wateringen",
    "sg:orig_category":"Overheidsdiensten",
    "sg:phone":"+31 174 294 484",
    "sg:postcode":"2291 SR",
    "sg:province":"Zuid-Holland",
    "wof:name":"De Eendenburcht",
    "wof:placetype":"venue"
},
  "geometry": {"coordinates":[4.2661910057,52.0253448486],"type":"Point"}
}