{
  "type": "Feature",
  "properties": {
    "addr:full":"Dorpsstr 50 Nunspeet Gelderland 8071 BZ",
    "addr:housenumber":"50",
    "addr:postcode":"8071 bz",
    "addr:street":"Dorpsstr;Gelderland",
    "iso:country":"NL",
    "sg:address":"Dorpsstr 50",
    "sg:city":"Nunspeet",
    "sg:orig_category":"Huishoudelijke Apparaten En Artikelen",
    "sg:phone":"+31 341 258 162",
    "sg:postcode":"8071 BZ",
    "sg:province":"Gelderland",
    "wof:name":"Blokker Bv",
    "wof:placetype":"venue"
},
  "geometry": {"coordinates":[5.782757,52.376183],"type":"Point"}
}