{
  "type": "Feature",
  "properties": {
    "addr:full":"Dorpsstraat 13 Oisterwijk Noord-Brabant 5061 HH",
    "addr:housenumber":"13",
    "addr:postcode":"5061 hh",
    "addr:street":"Dorpsstraat",
    "iso:country":"NL",
    "sg:address":"Dorpsstraat 13",
    "sg:city":"Oisterwijk",
    "sg:classifiers":[
        {
            "category":"Communications",
            "subcategory":"Television Station",
            "type":"Services"
        }
    ],
    "sg:phone":"+31 13 521 9321",
    "sg:postcode":"5061 HH",
    "sg:province":"Noord-Brabant",
    "sg:tags":[
        "video",
        "audio",
        "verhuur"
    ],
    "wof:name":"Videoland Oisterwijk",
    "wof:placetype":"venue"
},
  "geometry": {"coordinates":[5.192637,51.580513],"type":"Point"}
}