{
  "type": "Feature",
  "properties": {
    "addr:full":"Toon Dupuisstraat 4 'S Gravenhage South Holland 2552 SB",
    "addr:housenumber":"4 '",
    "addr:postcode":"2552 sb",
    "addr:street":"Toon Dupuisstraat",
    "iso:country":"NL",
    "sg:address":"Toon Dupuisstraat 4",
    "sg:city":"'S Gravenhage",
    "sg:orig_category":"Banken And Kredietinstellingen",
    "sg:phone":"+31 70 397 6991",
    "sg:postcode":"2552 SB",
    "sg:province":"South Holland",
    "wof:name":"Postkantoor",
    "wof:placetype":"venue"
},
  "geometry": {"coordinates":[4.251112,52.055302],"type":"Point"}
}