{
  "type": "Feature",
  "properties": {
    "iso:country":"NL",
    "sg:address":"Bredehof 37",
    "sg:city":"Rotterdam",
    "sg:orig_category":"Fotostudio'S And Fotografen",
    "sg:phone":"+31 10 419 2326",
    "sg:postcode":"3075 DE",
    "sg:province":"Zuid-Holland",
    "wof:name":"Antonio Videoreportages",
    "wof:placetype":"venue"
},
  "geometry": {"coordinates":[4.505582,51.878624],"type":"Point"}
}