{
  "type": "Feature",
  "properties": {
    "addr:full":"Havenweg 18 Spijk Gn Groningen 9909 AZ",
    "addr:housenumber":"18",
    "addr:postcode":"gn;9909",
    "addr:street":"Havenweg",
    "iso:country":"NL",
    "sg:address":"Havenweg 18",
    "sg:city":"Spijk Gn",
    "sg:orig_category":"Huizensloop And Bouwrijp Maken",
    "sg:phone":"+31 596 591 360",
    "sg:postcode":"9909 AZ",
    "sg:province":"Groningen",
    "wof:name":"Draineerbedrijf Eemsmond Bv",
    "wof:placetype":"venue"
},
  "geometry": {"coordinates":[6.838553,53.388546],"type":"Point"}
}