{
  "type": "Feature",
  "properties": {
    "addr:full":"Dennenln 77 Dorst North Brabant 4849 BD",
    "addr:housenumber":"77",
    "addr:postcode":"4849 bd",
    "addr:street":"Dennenln",
    "iso:country":"NL",
    "sg:address":"Dennenln 77",
    "sg:city":"Dorst",
    "sg:orig_category":"Beeldende Kunstenaars",
    "sg:phone":"+31 161 411 378",
    "sg:postcode":"4849 BD",
    "sg:province":"North Brabant",
    "wof:name":"Lansdaal & Verhoeven Vof",
    "wof:placetype":"venue"
},
  "geometry": {"coordinates":[4.855211,51.591747],"type":"Point"}
}