{
  "type": "Feature",
  "properties": {
    "iso:country":"NL",
    "sg:address":"Groningerwg 39",
    "sg:city":"Groningen",
    "sg:orig_category":"Veren - Fabrieken En Groothandel",
    "sg:phone":"+31 50 577 2754",
    "sg:postcode":"9738 AB",
    "sg:province":"Groningen",
    "sg:website":"http://www.bakkergroup.com",
    "wof:name":"Bakker Bv",
    "wof:placetype":"venue"
},
  "geometry": {"coordinates":[6.574105,53.244198],"type":"Point"}
}