{
  "type": "Feature",
  "properties": {
    "addr:full":"Ariawg 374 Amersfoort Utrecht 3816 HT",
    "addr:housenumber":"374",
    "addr:postcode":"3816 ht",
    "iso:country":"NL",
    "sg:address":"Ariawg 374",
    "sg:city":"Amersfoort",
    "sg:orig_category":"Fotoreportages",
    "sg:phone":"+31 6 15216374",
    "sg:postcode":"3816 HT",
    "sg:province":"Utrecht",
    "sg:website":"http://www.jgfotografie.nl",
    "wof:name":"Gelderloos Fotografie, Johan",
    "wof:placetype":"venue"
},
  "geometry": {"coordinates":[5.414616,52.156883],"type":"Point"}
}