{
  "type": "Feature",
  "properties": {
    "addr:full":"Sandenburgerlaan 3 Langbroek Utrecht 3947 CS",
    "addr:housenumber":"3",
    "addr:postcode":"3947 cs",
    "addr:street":"Sandenburgerlaan",
    "iso:country":"NL",
    "sg:address":"Sandenburgerlaan 3",
    "sg:city":"Langbroek",
    "sg:orig_category":"Zuivelproducten And Spijsoli?n Gh",
    "sg:phone":"+31 343 562 656",
    "sg:postcode":"3947 CS",
    "sg:province":"Utrecht",
    "wof:name":"Kaasmakerij Van Cooten",
    "wof:placetype":"venue"
},
  "geometry": {"coordinates":[5.347676,52.007801],"type":"Point"}
}