{
  "type": "Feature",
  "properties": {
    "addr:full":"Woolderbeekwg 11 Hengelo Ov NL.08 7553 BZ",
    "addr:housenumber":"11",
    "addr:postcode":"7553 bz",
    "addr:street":"Woolderbeekwg;Ov",
    "iso:country":"NL",
    "sg:address":"Woolderbeekwg 11",
    "sg:city":"Hengelo Ov",
    "sg:orig_category":"Verlichting",
    "sg:phone":"+31 74 250 1736",
    "sg:postcode":"7553 BZ",
    "sg:province":"NL.08",
    "wof:name":"Dbl",
    "wof:placetype":"venue"
},
  "geometry": {"coordinates":[6.774947,52.256149],"type":"Point"}
}