{
  "type": "Feature",
  "properties": {
    "addr:full":"Damsterdiep 16 Groningen Groningen 9711 SK",
    "addr:housenumber":"16",
    "addr:street":"Damsterdiep;9711",
    "iso:country":"NL",
    "sg:address":"Damsterdiep 16",
    "sg:city":"Groningen",
    "sg:orig_category":"Kappers",
    "sg:phone":"+31 50 314 4290",
    "sg:postcode":"9711 SK",
    "sg:province":"Groningen",
    "wof:name":"Jasper",
    "wof:placetype":"venue"
},
  "geometry": {"coordinates":[6.5750989914,53.2174186707],"type":"Point"}
}