{
  "type": "Feature",
  "properties": {
    "iso:country":"NL",
    "sg:address":"Koninginnewg 11",
    "sg:city":"Hilversum",
    "sg:orig_category":"Adviesbureaus Bedrijfsorganisatie",
    "sg:phone":"+31 35 625 0699",
    "sg:postcode":"1217 KP",
    "sg:province":"Noord-Holland",
    "wof:name":"Kyber Van Dijk Maatschap Voor Org Advies",
    "wof:placetype":"venue"
},
  "geometry": {"coordinates":[5.167174,52.229546],"type":"Point"}
}