{
  "type": "Feature",
  "properties": {
    "addr:full":"2E Tochtwg 61 Nieuwerkerk Yssel Zuid-Holland 2914 LM",
    "addr:housenumber":"61",
    "addr:postcode":"2914 lm",
    "addr:street":"2E Tochtwg",
    "iso:country":"NL",
    "sg:address":"2E Tochtwg 61",
    "sg:city":"Nieuwerkerk Yssel",
    "sg:orig_category":"Metselwerken",
    "sg:phone":"+31 180 317 023",
    "sg:postcode":"2914 LM",
    "sg:province":"Zuid-Holland",
    "wof:name":"Mst",
    "wof:placetype":"venue"
},
  "geometry": {"coordinates":[4.62855,51.982075],"type":"Point"}
}