{
  "type": "Feature",
  "properties": {
    "addr:full":"Montferlandstr 6 Amsterdam Noord-Holland 1079 PJ",
    "addr:housenumber":"6",
    "addr:postcode":"1079 pj",
    "addr:street":"Montferlandstr",
    "iso:country":"NL",
    "sg:address":"Montferlandstr 6",
    "sg:city":"Amsterdam",
    "sg:orig_category":"Administratie- En Boekhoudkantoren",
    "sg:phone":"+31 20 642 9345",
    "sg:postcode":"1079 PJ",
    "sg:province":"Noord-Holland",
    "wof:name":"Kool Vof, H W",
    "wof:placetype":"venue"
},
  "geometry": {"coordinates":[4.895046,52.339989],"type":"Point"}
}