{
  "type": "Feature",
  "properties": {
    "iso:country":"NL",
    "sg:address":"Nieuwstraat 63",
    "sg:city":"Nijverdal",
    "sg:orig_category":"Werving And Selectie Van Vast Personeel",
    "sg:phone":"+31 548 623 174",
    "sg:postcode":"7443 XN",
    "sg:province":"Overijssel",
    "wof:name":"Bvv",
    "wof:placetype":"venue"
},
  "geometry": {"coordinates":[6.4537210464,52.3711051941],"type":"Point"}
}