{
  "type": "Feature",
  "properties": {
    "addr:full":"Griendwg 1A S Gravendeel Zuid-Holland 3295 KV",
    "addr:housenumber":"1a",
    "addr:postcode":"3295 kv",
    "addr:street":"Griendwg;S Gravendeel",
    "iso:country":"NL",
    "sg:address":"Griendwg 1A",
    "sg:city":"S Gravendeel",
    "sg:classifiers":[
        {
            "category":"Retail",
            "subcategory":"Auto Repair",
            "type":"Services"
        }
    ],
    "sg:phone":"+31 78 673 1246",
    "sg:postcode":"3295 KV",
    "sg:province":"Zuid-Holland",
    "sg:tags":[
        "garage"
    ],
    "wof:name":"Ren? Moreel, Autoservice",
    "wof:placetype":"venue"
},
  "geometry": {"coordinates":[4.616294,51.788528],"type":"Point"}
}