{
  "type": "Feature",
  "properties": {
    "iso:country":"NL",
    "sg:address":"Den Ham 36",
    "sg:city":"Boskoop",
    "sg:orig_category":"Accountants - Administratie- Consulenten En -Kantoren",
    "sg:phone":"+31 172 216 489",
    "sg:postcode":"2771 WV",
    "sg:province":"Zuid-Holland",
    "wof:name":"Middelkoop En Partners",
    "wof:placetype":"venue"
},
  "geometry": {"coordinates":[4.659965,52.069149],"type":"Point"}
}