{
  "type": "Feature",
  "properties": {
    "addr:full":"Frankrijkstraat 7 Kaatsheuvel North Brabant 5171 PR",
    "addr:housenumber":"7",
    "addr:postcode":"5171 pr",
    "addr:street":"Frankrijkstraat",
    "iso:country":"NL",
    "sg:address":"Frankrijkstraat 7",
    "sg:city":"Kaatsheuvel",
    "sg:classifiers":[
        {
            "category":"Retail",
            "subcategory":"Storage",
            "type":"Services"
        }
    ],
    "sg:phone":"+31 416 540 691",
    "sg:postcode":"5171 PR",
    "sg:province":"North Brabant",
    "sg:tags":[
        "opslag",
        "bewaring"
    ],
    "wof:name":"Esap Systems",
    "wof:placetype":"venue"
},
  "geometry": {"coordinates":[5.0285549164,51.6640663147],"type":"Point"}
}