{
  "type": "Feature",
  "properties": {
    "addr:full":"Veluweweg 60 Kootwijkerbroek Gelderland 3774 BN",
    "addr:housenumber":"60",
    "addr:postcode":"3774 bn",
    "addr:street":"Veluweweg;Gelderland",
    "iso:country":"NL",
    "sg:address":"Veluweweg 60",
    "sg:city":"Kootwijkerbroek",
    "sg:orig_category":"Autokeuringen",
    "sg:phone":"+31 342 441 219",
    "sg:postcode":"3774 BN",
    "sg:province":"Gelderland",
    "wof:name":"Van Kooten Kootwijkerbroek Bv",
    "wof:placetype":"venue"
},
  "geometry": {"coordinates":[5.668659,52.152664],"type":"Point"}
}