{
  "type": "Feature",
  "properties": {
    "iso:country":"NL",
    "sg:address":"Bombardonln 19",
    "sg:city":"Nieuwegein",
    "sg:orig_category":"Vertaalbureaus",
    "sg:phone":"+31 30 603 3276",
    "sg:postcode":"3438 RN",
    "sg:province":"Utrecht",
    "wof:name":"Mw",
    "wof:placetype":"venue"
},
  "geometry": {"coordinates":[5.08505,52.045273],"type":"Point"}
}