{
  "type": "Feature",
  "properties": {
    "addr:full":"Blerckwg 49 T Harde Gelderland 8084 EX",
    "addr:housenumber":"49",
    "addr:postcode":"8084 ex",
    "addr:street":"Blerckwg",
    "iso:country":"NL",
    "sg:address":"Blerckwg 49",
    "sg:city":"T Harde",
    "sg:orig_category":"Leesportefeuilles",
    "sg:phone":"+31 525 651 507",
    "sg:postcode":"8084 EX",
    "sg:province":"Gelderland",
    "wof:name":"Pater, Stef",
    "wof:placetype":"venue"
},
  "geometry": {"coordinates":[5.877227,52.418842],"type":"Point"}
}