{
  "type": "Feature",
  "properties": {
    "iso:country":"NL",
    "sg:address":"Blerckwg 49",
    "sg:city":"T Harde",
    "sg:orig_category":"Leesportefeuilles",
    "sg:phone":"+31 525 651 507",
    "sg:postcode":"8084 EX",
    "sg:province":"Gelderland",
    "wof:name":"Pater, Stef",
    "wof:placetype":"venue"
},
  "geometry": {"coordinates":[5.877227,52.418842],"type":"Point"}
}