{
  "type": "Feature",
  "properties": {
    "iso:country":"NL",
    "sg:address":"Dietsveld 5",
    "sg:city":"Haarlem",
    "sg:orig_category":"Adviesbureaus Elektrotechniek",
    "sg:phone":"+31 23 539 8044",
    "sg:postcode":"2025 BG",
    "sg:province":"Noord-Holland",
    "wof:name":"Koene",
    "wof:placetype":"venue"
},
  "geometry": {"coordinates":[23.3997,42.356701],"type":"Point"}
}