{
  "type": "Feature",
  "properties": {
    "addr:full":"M V Wyhewg 29 Hoenderloo Gelderland 7351 AL",
    "addr:housenumber":"29",
    "addr:postcode":"7351",
    "addr:street":"Wyhewg;Gelderland",
    "iso:country":"NL",
    "sg:address":"M V Wyhewg 29",
    "sg:city":"Hoenderloo",
    "sg:orig_category":"Voetbalverenigingen",
    "sg:phone":"+31 55 378 1749",
    "sg:postcode":"7351 AL",
    "sg:province":"Gelderland",
    "wof:name":"Beatrix",
    "wof:placetype":"venue"
},
  "geometry": {"coordinates":[5.878067,52.118149],"type":"Point"}
}