{
  "type": "Feature",
  "properties": {
    "iso:country":"NL",
    "sg:address":"Spoorln 12",
    "sg:city":"Bilthoven",
    "sg:orig_category":"Metaaldraaierijen",
    "sg:phone":"+31 30 228 5521",
    "sg:postcode":"3721 PB",
    "sg:province":"Utrecht",
    "wof:name":"Loffeld",
    "wof:placetype":"venue"
},
  "geometry": {"coordinates":[5.18986,52.12133],"type":"Point"}
}