{
  "type": "Feature",
  "properties": {
    "addr:full":"Tuinfluiterstr 136 Sliedrecht Zuid-Holland 3362 PS",
    "addr:housenumber":"136",
    "addr:postcode":"3362 ps",
    "iso:country":"NL",
    "sg:address":"Tuinfluiterstr 136",
    "sg:city":"Sliedrecht",
    "sg:orig_category":"Accountants - Administratie- Consulenten En -Kantoren",
    "sg:phone":"+31 184 449 333",
    "sg:postcode":"3362 PS",
    "sg:province":"Zuid-Holland",
    "wof:name":"Jongh, De",
    "wof:placetype":"venue"
},
  "geometry": {"coordinates":[4.785426,51.821033],"type":"Point"}
}