{
  "type": "Feature",
  "properties": {
    "addr:full":"Boterberg 30 Tilburg Noord-Brabant 5047 ST",
    "addr:housenumber":"30",
    "addr:postcode":"5047 st",
    "addr:street":"Boterberg",
    "iso:country":"NL",
    "sg:address":"Boterberg 30",
    "sg:city":"Tilburg",
    "sg:orig_category":"Metaalbekleding And -Behandeling",
    "sg:phone":"+31 13 570 3370",
    "sg:postcode":"5047 ST",
    "sg:province":"Noord-Brabant",
    "wof:name":"Czl Tilburg Bv",
    "wof:placetype":"venue"
},
  "geometry": {"coordinates":[5.02526,51.587688],"type":"Point"}
}