{
  "type": "Feature",
  "properties": {
    "addr:full":"Ligusterstr 24 S Gravenhage South Holland 2563 VD",
    "addr:housenumber":"24",
    "addr:postcode":"2563 vd",
    "addr:street":"Ligusterstr;S Gravenhage",
    "iso:country":"NL",
    "sg:address":"Ligusterstr 24",
    "sg:city":"S Gravenhage",
    "sg:orig_category":"Belastingconsulenten/ Belastingadviseurs",
    "sg:phone":"+31 70 360 0587",
    "sg:postcode":"2563 VD",
    "sg:province":"South Holland",
    "wof:name":"Haghe, Die",
    "wof:placetype":"venue"
},
  "geometry": {"coordinates":[4.270956,52.072578],"type":"Point"}
}