{
  "type": "Feature",
  "properties": {
    "addr:full":"Nijverheidsstraat 11 Gorssel Gelderland 7213 DA",
    "addr:housenumber":"11",
    "addr:postcode":"7213 da",
    "addr:street":"Nijverheidsstraat;Gelderland",
    "iso:country":"NL",
    "sg:address":"Nijverheidsstraat 11",
    "sg:city":"Gorssel",
    "sg:orig_category":"Kappers",
    "sg:phone":"+31 575 491 362",
    "sg:postcode":"7213 DA",
    "sg:province":"Gelderland",
    "wof:name":"Flair Haarmode",
    "wof:placetype":"venue"
},
  "geometry": {"coordinates":[6.2008919716,52.2006454468],"type":"Point"}
}