{
  "type": "Feature",
  "properties": {
    "addr:full":"Verrekamppln 25 Venlo Limburg 5912 TH",
    "addr:housenumber":"25",
    "addr:postcode":"5912 th",
    "addr:street":"Verrekamppln",
    "iso:country":"NL",
    "sg:address":"Verrekamppln 25",
    "sg:city":"Venlo",
    "sg:orig_category":"Beeldende Kunstenaars",
    "sg:phone":"+31 77 352 0530",
    "sg:postcode":"5912 TH",
    "sg:province":"Limburg",
    "wof:name":"Simons, R",
    "wof:placetype":"venue"
},
  "geometry": {"coordinates":[6.170906,51.361198],"type":"Point"}
}