{
  "type": "Feature",
  "properties": {
    "addr:full":"Zutphensestr 101 Brummen Gelderland 6971 EJ",
    "addr:housenumber":"101",
    "addr:postcode":"6971 ej",
    "addr:street":"Gelderland",
    "iso:country":"NL",
    "sg:address":"Zutphensestr 101",
    "sg:city":"Brummen",
    "sg:orig_category":"Bloemen En Planten",
    "sg:phone":"+31 575 564 746",
    "sg:postcode":"6971 EJ",
    "sg:province":"Gelderland",
    "wof:name":"Bloemenshop, De",
    "wof:placetype":"venue"
},
  "geometry": {"coordinates":[6.152417,52.094715],"type":"Point"}
}