{
  "type": "Feature",
  "properties": {
    "addr:full":"St Hubertusholt 27 Bedum Groningen 9781 KA",
    "addr:housenumber":"27",
    "addr:postcode":"9781 ka",
    "addr:street":"St Hubertusholt",
    "iso:country":"NL",
    "sg:address":"St Hubertusholt 27",
    "sg:city":"Bedum",
    "sg:orig_category":"Metaalwerken",
    "sg:phone":"+31 50 301 4309",
    "sg:postcode":"9781 KA",
    "sg:province":"Groningen",
    "wof:name":"Makkes Systeembouw Bv",
    "wof:placetype":"venue"
},
  "geometry": {"coordinates":[6.605314,53.294922],"type":"Point"}
}