{
  "type": "Feature",
  "properties": {
    "addr:full":"Bructerenln 3 Apeldoorn Gelderland 7312 HL",
    "addr:housenumber":"3",
    "addr:postcode":"7312 hl",
    "addr:street":"Bructerenln;Gelderland",
    "iso:country":"NL",
    "sg:address":"Bructerenln 3",
    "sg:city":"Apeldoorn",
    "sg:orig_category":"Kappers",
    "sg:phone":"+31 55 355 3430",
    "sg:postcode":"7312 HL",
    "sg:province":"Gelderland",
    "wof:name":"Kwant, B J",
    "wof:placetype":"venue"
},
  "geometry": {"coordinates":[5.931744,52.206512],"type":"Point"}
}