{
  "type": "Feature",
  "properties": {
    "addr:full":"Canadastr 76 Heino Minnesota 8141 AE",
    "addr:housenumber":"76",
    "addr:postcode":"8141 ae",
    "addr:street":"Canadastr;Minnesota",
    "iso:country":"NL",
    "sg:address":"Canadastr 76",
    "sg:city":"Heino",
    "sg:classifiers":[
        {
            "category":"Banks & Credit Unions",
            "subcategory":"Investment Brokerage",
            "type":"Services"
        }
    ],
    "sg:phone":"+31 572 393 779",
    "sg:postcode":"8141 AE",
    "sg:province":"Minnesota",
    "sg:tags":[
        "pension"
    ],
    "wof:name":"Salouwe",
    "wof:placetype":"venue"
},
  "geometry": {"coordinates":[-95.398735,46.498905],"type":"Point"}
}