{
  "type": "Feature",
  "properties": {
    "addr:full":"Meerpaal 318 Groningen Groningen 9732 AT",
    "addr:housenumber":"318",
    "addr:postcode":"9732",
    "addr:street":"Meerpaal",
    "iso:country":"NL",
    "sg:address":"Meerpaal 318",
    "sg:city":"Groningen",
    "sg:orig_category":"Diverse Grafische Activiteiten",
    "sg:phone":"+31 50 542 4672",
    "sg:postcode":"9732 AT",
    "sg:province":"Groningen",
    "wof:name":"K Koopman Design",
    "wof:placetype":"venue"
},
  "geometry": {"coordinates":[6.628601,53.234043],"type":"Point"}
}