{
  "type": "Feature",
  "properties": {
    "iso:country":"NL",
    "sg:address":"De Bus 42B",
    "sg:city":"Waalre",
    "sg:orig_category":"Bedrijfsorganisaties",
    "sg:phone":"+31 40 223 3126",
    "sg:postcode":"5581 GP",
    "sg:province":"Noord-Brabant",
    "wof:name":"Systrain Bv",
    "wof:placetype":"venue"
},
  "geometry": {"coordinates":[5.445686,51.387203],"type":"Point"}
}