{
  "type": "Feature",
  "properties": {
    "addr:full":"Stalpln 1 Haarzuilens Utrecht 3455 RS",
    "addr:housenumber":"1",
    "addr:postcode":"3455 rs",
    "addr:street":"Stalpln",
    "iso:country":"NL",
    "sg:address":"Stalpln 1",
    "sg:city":"Haarzuilens",
    "sg:orig_category":"Adviesbureaus Bouwkunde",
    "sg:phone":"+31 30 677 2780",
    "sg:postcode":"3455 RS",
    "sg:province":"Utrecht",
    "wof:name":"Griffioen, P",
    "wof:placetype":"venue"
},
  "geometry": {"coordinates":[4.983188,52.119556],"type":"Point"}
}