{
  "type": "Feature",
  "properties": {
    "addr:full":"Nieuwe Binnenweg 89 Rotterdam Zuid-Holland 3014 GE",
    "addr:housenumber":"89",
    "addr:postcode":"3014",
    "addr:street":"Nieuwe Binnenweg",
    "iso:country":"NL",
    "sg:address":"Nieuwe Binnenweg 89",
    "sg:city":"Rotterdam",
    "sg:orig_category":"Damesmodezaken",
    "sg:phone":"+31 10 436 1508",
    "sg:postcode":"3014 GE",
    "sg:province":"Zuid-Holland",
    "wof:name":"Boetiek Sister Moon",
    "wof:placetype":"venue"
},
  "geometry": {"coordinates":[4.468574,51.916157],"type":"Point"}
}