{
  "type": "Feature",
  "properties": {
    "addr:full":"Amstelveenseweg 880 Amsterdam Noord-Holland 1081 JM",
    "addr:housenumber":"880",
    "addr:postcode":"1081 jm",
    "addr:street":"Amstelveenseweg",
    "iso:country":"NL",
    "sg:address":"Amstelveenseweg 880",
    "sg:city":"Amsterdam",
    "sg:orig_category":"Watersport-, Sport- And Kampeerbenodigdheden Verhuur",
    "sg:phone":"+31 20 644 5473",
    "sg:postcode":"1081 JM",
    "sg:province":"Noord-Holland",
    "wof:name":"Amsterdamse Bos",
    "wof:placetype":"venue"
},
  "geometry": {"coordinates":[4.8572092056,52.3292007446],"type":"Point"}
}