{
  "type": "Feature",
  "properties": {
    "addr:full":"Brandersmolenstraat 31 Almere Flevoland 1333 BX",
    "addr:housenumber":"31",
    "addr:postcode":"1333 bx",
    "addr:street":"Brandersmolenstraat;Flevoland",
    "iso:country":"NL",
    "sg:address":"Brandersmolenstraat 31",
    "sg:city":"Almere",
    "sg:orig_category":"Bedrijfs- And Managementsconsultants",
    "sg:phone":"+31 36 532 8460",
    "sg:postcode":"1333 BX",
    "sg:province":"Flevoland",
    "wof:name":"Concept Innovatie",
    "wof:placetype":"venue"
},
  "geometry": {"coordinates":[5.26515,52.398769],"type":"Point"}
}