{
  "type": "Feature",
  "properties": {
    "iso:country":"NL",
    "sg:address":"Topaasdk 43",
    "sg:city":"Roosendaal",
    "sg:orig_category":"Maquettes",
    "sg:phone":"+31 165 570 255",
    "sg:postcode":"4706 TL",
    "sg:province":"North Brabant",
    "wof:name":"Terlaak",
    "wof:placetype":"venue"
},
  "geometry": {"coordinates":[4.500143,51.51886],"type":"Point"}
}