{
  "type": "Feature",
  "properties": {
    "addr:full":"S Robertsonstr 8 Venray Limburg 5803 GM",
    "addr:housenumber":"8",
    "addr:postcode":"5803 gm",
    "iso:country":"NL",
    "sg:address":"S Robertsonstr 8",
    "sg:city":"Venray",
    "sg:orig_category":"Homeopathie",
    "sg:phone":"+31 478 516 638",
    "sg:postcode":"5803 GM",
    "sg:province":"Limburg",
    "wof:name":"Valks-Smits, J M H E",
    "wof:placetype":"venue"
},
  "geometry": {"coordinates":[5.998556,51.526203],"type":"Point"}
}