{
  "type": "Feature",
  "properties": {
    "addr:full":"Huigbrouwerstraat 24 Alkmaar North Holland 1811 BJ",
    "addr:housenumber":"24",
    "addr:postcode":"1811 bj",
    "addr:street":"Huigbrouwerstraat",
    "iso:country":"NL",
    "sg:address":"Huigbrouwerstraat 24",
    "sg:city":"Alkmaar",
    "sg:orig_category":"Kunst And Kunstenaarsbenodigdheden",
    "sg:phone":"+31 72 512 7384",
    "sg:postcode":"1811 BJ",
    "sg:province":"North Holland",
    "wof:name":"Kunsthandel Wim De Boer",
    "wof:placetype":"venue"
},
  "geometry": {"coordinates":[4.748962,52.629852],"type":"Point"}
}