{
  "type": "Feature",
  "properties": {
    "addr:full":"Grotestr 48 ,(City Promenade) Almelo Overijssel 7607 CR",
    "addr:housenumber":"48",
    "addr:postcode":"7607 cr",
    "addr:street":"Grotestr;Promenade",
    "iso:country":"NL",
    "sg:address":"Grotestr 48 ,(City Promenade)",
    "sg:city":"Almelo",
    "sg:orig_category":"Glas, Porselein En Aardewerk",
    "sg:phone":"+31 546 826 555",
    "sg:postcode":"7607 CR",
    "sg:province":"Overijssel",
    "wof:name":"Joldersma",
    "wof:placetype":"venue"
},
  "geometry": {"coordinates":[6.664971,52.357273],"type":"Point"}
}