{
  "type": "Feature",
  "properties": {
    "iso:country":"NL",
    "sg:address":"A Brouwerln 32",
    "sg:city":"Oosterhout Nb",
    "sg:orig_category":"Woningstoffeerders",
    "sg:phone":"+31 162 428 483",
    "sg:postcode":"4907 MJ",
    "sg:province":"Noord-Brabant",
    "wof:name":"Boerhof",
    "wof:placetype":"venue"
},
  "geometry": {"coordinates":[4.8677802086,51.6565589905],"type":"Point"}
}