{
  "type": "Feature",
  "properties": {
    "addr:full":"Doornenkampseweg 101 Heelsum Gelderland 6866 BC",
    "addr:housenumber":"101",
    "addr:postcode":"6866 bc",
    "addr:street":"Doornenkampseweg;Gelderland",
    "iso:country":"NL",
    "sg:address":"Doornenkampseweg 101",
    "sg:city":"Heelsum",
    "sg:classifiers":[
        {
            "category":"Fast Food",
            "type":"Food & Drink"
        }
    ],
    "sg:phone":"+31 317 313 382",
    "sg:postcode":"6866 BC",
    "sg:province":"Gelderland",
    "sg:tags":[
        "afhaal",
        "restaurant"
    ],
    "wof:name":"Cafetaria Petit Restaurant De Doornenkam",
    "wof:placetype":"venue"
},
  "geometry": {"coordinates":[5.748046,51.982037],"type":"Point"}
}