{
  "type": "Feature",
  "properties": {
    "addr:full":"Westervoortsedijk 124 Arnhem Gelderland 6827 AX",
    "addr:housenumber":"124",
    "addr:postcode":"6827 ax",
    "addr:street":"Westervoortsedijk",
    "iso:country":"NL",
    "sg:address":"Westervoortsedijk 124",
    "sg:city":"Arnhem",
    "sg:orig_category":"Zuivelproducten And Spijsoli?n Gh",
    "sg:phone":"+31 26 353 5111",
    "sg:postcode":"6827 AX",
    "sg:province":"Gelderland",
    "wof:name":"Coberco Zuivel",
    "wof:placetype":"venue"
},
  "geometry": {"coordinates":[5.91603,51.975391],"type":"Point"}
}