{
  "type": "Feature",
  "properties": {
    "addr:full":"Spaarndamsewg 120K Haarlem Noord-Holland 2021 KA",
    "addr:housenumber":"120k",
    "addr:postcode":"2021 ka",
    "addr:street":"Spaarndamsewg",
    "iso:country":"NL",
    "sg:address":"Spaarndamsewg 120K",
    "sg:city":"Haarlem",
    "sg:orig_category":"Beurzen",
    "sg:phone":"+31 23 525 8500",
    "sg:postcode":"2021 KA",
    "sg:province":"Noord-Holland",
    "wof:name":"Ekeris Bv, Van",
    "wof:placetype":"venue"
},
  "geometry": {"coordinates":[4.649291,52.390614],"type":"Point"}
}