{
  "type": "Feature",
  "properties": {
    "addr:full":"Vanadiumwg 5 Amersfoort Utrecht 3812 PX",
    "addr:housenumber":"5",
    "addr:postcode":"3812 px",
    "addr:street":"Vanadiumwg",
    "iso:country":"NL",
    "sg:address":"Vanadiumwg 5",
    "sg:city":"Amersfoort",
    "sg:orig_category":"Vervoercentra",
    "sg:phone":"+31 33 461 0845",
    "sg:postcode":"3812 PX",
    "sg:province":"Utrecht",
    "wof:name":"Pakketdienst Bv, Ned",
    "wof:placetype":"venue"
},
  "geometry": {"coordinates":[5.361907,52.169868],"type":"Point"}
}