{
  "type": "Feature",
  "properties": {
    "addr:full":"Geerde 31 Waalwyk North Brabant 5142 NN",
    "addr:housenumber":"31",
    "addr:postcode":"5142 nn",
    "addr:street":"Geerde",
    "iso:country":"NL",
    "sg:address":"Geerde 31",
    "sg:city":"Waalwyk",
    "sg:orig_category":"Luchtbehandelings- Apparaten",
    "sg:phone":"+31 416 561 991",
    "sg:postcode":"5142 NN",
    "sg:province":"North Brabant",
    "wof:name":"Vandelaar Trading Bv",
    "wof:placetype":"venue"
},
  "geometry": {"coordinates":[5.093696,51.688873],"type":"Point"}
}