{
  "type": "Feature",
  "properties": {
    "iso:country":"NL",
    "sg:address":"Dirk Huizingastraat 11",
    "sg:city":"Groningen",
    "sg:classifiers":[
        {
            "category":"Fast Food",
            "type":"Food & Drink"
        }
    ],
    "sg:phone":"+31 50 312 7312",
    "sg:postcode":"9713 GL",
    "sg:province":"Groningen",
    "sg:tags":[
        "afhaal",
        "restaurant"
    ],
    "wof:name":"Snackcentrum",
    "wof:placetype":"venue"
},
  "geometry": {"coordinates":[6.580438,53.2216],"type":"Point"}
}