{
  "type": "Feature",
  "properties": {
    "addr:full":"Pelikaanhof 91 Leidschendam Zuid-Holland 2264 JH",
    "addr:housenumber":"91",
    "addr:postcode":"2264 jh",
    "addr:street":"Pelikaanhof",
    "iso:country":"NL",
    "sg:address":"Pelikaanhof 91",
    "sg:city":"Leidschendam",
    "sg:orig_category":"Boekhouders",
    "sg:phone":"+31 70 320 3780",
    "sg:postcode":"2264 JH",
    "sg:province":"Zuid-Holland",
    "wof:name":"Administratiekantoor J. Van Grootel",
    "wof:placetype":"venue"
},
  "geometry": {"coordinates":[4.407554,52.094627],"type":"Point"}
}