{
  "type": "Feature",
  "properties": {
    "addr:full":"Heeleind 98 Bladel North Brabant 5531 CD",
    "addr:housenumber":"98",
    "addr:postcode":"5531 cd",
    "addr:street":"Heeleind",
    "iso:country":"NL",
    "sg:address":"Heeleind 98",
    "sg:city":"Bladel",
    "sg:orig_category":"Loodgieterswerk, Verwarming And Sanitaire Installaties",
    "sg:phone":"+31 497 385 132",
    "sg:postcode":"5531 CD",
    "sg:province":"North Brabant",
    "wof:name":"A.J. Sol Klussenbedrijf",
    "wof:placetype":"venue"
},
  "geometry": {"coordinates":[5.229242,51.368591],"type":"Point"}
}