{
  "type": "Feature",
  "properties": {
    "addr:full":"Heesbergstr 41 Heerlen Limburg 6417 AA",
    "addr:housenumber":"41",
    "addr:postcode":"6417 aa",
    "addr:street":"Heesbergstr",
    "iso:country":"NL",
    "sg:address":"Heesbergstr 41",
    "sg:city":"Heerlen",
    "sg:orig_category":"Verzekeringen - Verzekeringskantoren",
    "sg:phone":"+31 45 542 1440",
    "sg:postcode":"6417 AA",
    "sg:province":"Limburg",
    "wof:name":"Heerlerbaan",
    "wof:placetype":"venue"
},
  "geometry": {"coordinates":[5.989805,50.875568],"type":"Point"}
}