{
  "type": "Feature",
  "properties": {
    "addr:full":"Boschstraat 24 Breda Noord-Brabant 4811 GH",
    "addr:housenumber":"24",
    "addr:postcode":"4811 gh",
    "addr:street":"Boschstraat",
    "iso:country":"NL",
    "sg:address":"Boschstraat 24",
    "sg:city":"Breda",
    "sg:orig_category":"Diverse Grafische Activiteiten",
    "sg:phone":"+31 76 520 4163",
    "sg:postcode":"4811 GH",
    "sg:province":"Noord-Brabant",
    "wof:name":"Studio Wr",
    "wof:placetype":"venue"
},
  "geometry": {"coordinates":[4.781402,51.589787],"type":"Point"}
}