{
  "type": "Feature",
  "properties": {
    "iso:country":"NL",
    "sg:address":"Heinsbergerweg 12",
    "sg:city":"Melick",
    "sg:classifiers":[
        {
            "category":"Travel",
            "subcategory":"Hotels & Motels",
            "type":"Entertainment"
        }
    ],
    "sg:phone":"+31 475 532 095",
    "sg:postcode":"6074 AD",
    "sg:province":"Limburg",
    "wof:name":"Hofstee De Roerdalhoeve",
    "wof:placetype":"venue"
},
  "geometry": {"coordinates":[6.006048,51.153957],"type":"Point"}
}