{
  "type": "Feature",
  "properties": {
    "addr:full":"Vlymenwg 25 Arnhem Gelderland 6844 GC",
    "addr:housenumber":"25",
    "addr:postcode":"6844 gc",
    "addr:street":"Vlymenwg",
    "iso:country":"NL",
    "sg:address":"Vlymenwg 25",
    "sg:city":"Arnhem",
    "sg:orig_category":"Verhuizingen",
    "sg:phone":"+31 26 389 0795",
    "sg:postcode":"6844 GC",
    "sg:province":"Gelderland",
    "wof:name":"Willem",
    "wof:placetype":"venue"
},
  "geometry": {"coordinates":[5.858574,51.949612],"type":"Point"}
}