{
  "type": "Feature",
  "properties": {
    "addr:full":"Industriestr 8 Numansdorp Zuid-Holland 3281 LB",
    "addr:housenumber":"8",
    "addr:postcode":"3281 lb",
    "addr:street":"Industriestr",
    "iso:country":"NL",
    "sg:address":"Industriestr 8",
    "sg:city":"Numansdorp",
    "sg:orig_category":"Afvalverwerkings- Apparatuur",
    "sg:phone":"+31 186 650 000",
    "sg:postcode":"3281 LB",
    "sg:province":"Zuid-Holland",
    "wof:name":"Gibros Pec Bv",
    "wof:placetype":"venue"
},
  "geometry": {"coordinates":[4.447691,51.743496],"type":"Point"}
}