{
  "type": "Feature",
  "properties": {
    "addr:full":"Haspel 22 Veenendaal Utrecht 3906 NB",
    "addr:housenumber":"22",
    "addr:postcode":"3906 nb",
    "addr:street":"Haspel",
    "iso:country":"NL",
    "sg:address":"Haspel 22",
    "sg:city":"Veenendaal",
    "sg:orig_category":"Adviesbureaus Bedrijfsorganisatie",
    "sg:phone":"+31 318 517 079",
    "sg:postcode":"3906 NB",
    "sg:province":"Utrecht",
    "wof:name":"Buddels",
    "wof:placetype":"venue"
},
  "geometry": {"coordinates":[5.523903,52.032566],"type":"Point"}
}