{
  "type": "Feature",
  "properties": {
    "addr:full":"Bozenhoven 105 Mijdrecht Utrecht 3641 AD",
    "addr:housenumber":"105",
    "addr:postcode":"3641 ad",
    "addr:street":"Bozenhoven",
    "iso:country":"NL",
    "sg:address":"Bozenhoven 105",
    "sg:city":"Mijdrecht",
    "sg:orig_category":"Bloemen En Planten",
    "sg:phone":"+31 297 281 576",
    "sg:postcode":"3641 AD",
    "sg:province":"Utrecht",
    "wof:name":"Wiegmans",
    "wof:placetype":"venue"
},
  "geometry": {"coordinates":[4.86766,52.203812],"type":"Point"}
}