{
  "type": "Feature",
  "properties": {
    "addr:full":"Vreeswijkpad 11 Amsterdam Zuidoost North Holland 1106 DV",
    "addr:housenumber":"11",
    "addr:postcode":"1106 dv",
    "addr:street":"Vreeswijkpad",
    "iso:country":"NL",
    "sg:address":"Vreeswijkpad 11",
    "sg:city":"Amsterdam Zuidoost",
    "sg:orig_category":"Kinderopvang Behalve Thuis",
    "sg:phone":"+31 20 696 8961",
    "sg:postcode":"1106 DV",
    "sg:province":"North Holland",
    "wof:name":"Het Gein Naschoolse Opvang",
    "wof:placetype":"venue"
},
  "geometry": {"coordinates":[4.984128,52.296593],"type":"Point"}
}