{
  "type": "Feature",
  "properties": {
    "iso:country":"NL",
    "sg:address":"Dorpsstraat 34C",
    "sg:city":"Noordwijkerhout",
    "sg:orig_category":"Kappers",
    "sg:phone":"+31 252 371 254",
    "sg:postcode":"2211 GD",
    "sg:province":"South Holland",
    "wof:name":"Bourgondi?n, Van",
    "wof:placetype":"venue"
},
  "geometry": {"coordinates":[4.4917907715,52.2620735168],"type":"Point"}
}