{
  "type": "Feature",
  "properties": {
    "addr:full":"Nobelstraat 36 Heerlen Limburg 6411 EP",
    "addr:housenumber":"36",
    "addr:postcode":"6411 ep",
    "addr:street":"Nobelstraat",
    "iso:country":"NL",
    "sg:address":"Nobelstraat 36",
    "sg:city":"Heerlen",
    "sg:orig_category":"Onderhoud And Reparatie Kantoorapparatuur",
    "sg:phone":"+31 45 571 4727",
    "sg:postcode":"6411 EP",
    "sg:province":"Limburg",
    "wof:name":"Mic Automatisering",
    "wof:placetype":"venue"
},
  "geometry": {"coordinates":[5.979029,50.88406],"type":"Point"}
}