{
  "type": "Feature",
  "properties": {
    "addr:full":"Lomstraat 8 Venlo Limburg 5911 GN",
    "addr:housenumber":"8",
    "addr:postcode":"5911 gn",
    "addr:street":"Lomstraat",
    "iso:country":"NL",
    "sg:address":"Lomstraat 8",
    "sg:city":"Venlo",
    "sg:classifiers":[
        {
            "category":"Shopping",
            "subcategory":"Gifts & Souvenirs",
            "type":"Retail Goods"
        }
    ],
    "sg:phone":"+31 77 354 8092",
    "sg:postcode":"5911 GN",
    "sg:province":"Limburg",
    "sg:tags":[
        "geschenken"
    ],
    "wof:name":"Pivera Bv",
    "wof:placetype":"venue"
},
  "geometry": {"coordinates":[6.169745,51.370747],"type":"Point"}
}