{
  "type": "Feature",
  "properties": {
    "addr:full":"Slootsestr 23 Puiflyk Gelderland 6655 AJ",
    "addr:housenumber":"23",
    "addr:postcode":"6655 aj",
    "addr:street":"Slootsestr;Gelderland",
    "iso:country":"NL",
    "sg:address":"Slootsestr 23",
    "sg:city":"Puiflyk",
    "sg:orig_category":"Verloskundigen",
    "sg:phone":"+31 487 516 464",
    "sg:postcode":"6655 AJ",
    "sg:province":"Gelderland",
    "wof:name":"Druten En West Maas & Waal",
    "wof:placetype":"venue"
},
  "geometry": {"coordinates":[5.593923,51.880199],"type":"Point"}
}