{
  "type": "Feature",
  "properties": {
    "iso:country":"NL",
    "sg:address":"V Heemstrawg 58",
    "sg:city":"Winssen",
    "sg:orig_category":"Logerijen",
    "sg:phone":"+31 487 522 080",
    "sg:postcode":"6645 KH",
    "sg:province":"Gelderland",
    "wof:name":"B. Loeffen",
    "wof:placetype":"venue"
},
  "geometry": {"coordinates":[5.708412,51.882339],"type":"Point"}
}