{
  "type": "Feature",
  "properties": {
    "addr:full":"Markt 75 Gouda South Holland 2801 JM",
    "addr:housenumber":"75",
    "addr:postcode":"2801 jm",
    "addr:street":"Markt",
    "iso:country":"NL",
    "sg:address":"Markt 75",
    "sg:city":"Gouda",
    "sg:classifiers":[
        {
            "category":"Retail",
            "subcategory":"Photofinishing",
            "type":"Services"
        }
    ],
    "sg:phone":"+31 182 580 241",
    "sg:postcode":"2801 JM",
    "sg:province":"South Holland",
    "sg:tags":[
        "foto",
        "film"
    ],
    "wof:name":"Super Photo Snelservice",
    "wof:placetype":"venue"
},
  "geometry": {"coordinates":[4.71002,52.011215],"type":"Point"}
}