{
  "type": "Feature",
  "properties": {
    "addr:full":"De Valuwe 3 Cuijk Noord-Brabant 5431 AV",
    "addr:housenumber":"3",
    "addr:postcode":"5431 av",
    "addr:street":"De Valuwe",
    "iso:country":"NL",
    "sg:address":"De Valuwe 3",
    "sg:city":"Cuijk",
    "sg:orig_category":"Kappers",
    "sg:phone":"+31 485 321 777",
    "sg:postcode":"5431 AV",
    "sg:province":"Noord-Brabant",
    "wof:name":"Vof J.P.M. Geboers En G.L.W. Luypen",
    "wof:placetype":"venue"
},
  "geometry": {"coordinates":[5.87245,51.73756],"type":"Point"}
}