{
  "type": "Feature",
  "properties": {
    "iso:country":"NL",
    "sg:address":"Verspronckweg 63C",
    "sg:city":"Haarlem",
    "sg:orig_category":"Wasserettes, Stomerijen And Reiniging",
    "sg:phone":"+31 23 526 4050",
    "sg:postcode":"2023 BB",
    "sg:province":"Noord-Holland",
    "wof:name":"Chemdry",
    "wof:placetype":"venue"
},
  "geometry": {"coordinates":[4.6280550957,52.389629364],"type":"Point"}
}