{
  "type": "Feature",
  "properties": {
    "addr:full":"V Ysendykstr 373 Purmerend Noord-Holland 1442 LB",
    "addr:housenumber":"373",
    "addr:postcode":"1442 lb",
    "iso:country":"NL",
    "sg:address":"V Ysendykstr 373",
    "sg:city":"Purmerend",
    "sg:orig_category":"Administratie- En Boekhoudkantoren",
    "sg:phone":"+31 299 404 604",
    "sg:postcode":"1442 LB",
    "sg:province":"Noord-Holland",
    "sg:website":"http://www.vanderkuytgroep.nl",
    "wof:name":"Kuyt Administratie & Fiscale Dienstverlening, Van Der",
    "wof:placetype":"venue"
},
  "geometry": {"coordinates":[4.94793,52.507607],"type":"Point"}
}