{
  "type": "Feature",
  "properties": {
    "addr:full":"Blokhuis 55 Lisse Zuid-Holland 2161 EV",
    "addr:housenumber":"55",
    "addr:street":"Blokhuis",
    "iso:country":"NL",
    "sg:address":"Blokhuis 55",
    "sg:city":"Lisse",
    "sg:orig_category":"Huishoudelijke Apparaten En Artikelen",
    "sg:phone":"+31 252 411 446",
    "sg:postcode":"2161 EV",
    "sg:province":"Zuid-Holland",
    "wof:name":"Blokker Bv",
    "wof:placetype":"venue"
},
  "geometry": {"coordinates":[4.558946,52.261189],"type":"Point"}
}