{
  "type": "Feature",
  "properties": {
    "addr:full":"Calandhof 66 Tilburg Noord-Brabant 5025 DJ",
    "addr:housenumber":"66",
    "addr:postcode":"5025 dj",
    "addr:street":"Calandhof",
    "iso:country":"NL",
    "sg:address":"Calandhof 66",
    "sg:city":"Tilburg",
    "sg:orig_category":"Verhuur Audiovisuele Apparatuur",
    "sg:phone":"+31 13 544 4287",
    "sg:postcode":"5025 DJ",
    "sg:province":"Noord-Brabant",
    "wof:name":"Technisch Bureau Boonstra",
    "wof:placetype":"venue"
},
  "geometry": {"coordinates":[5.071396,51.549568],"type":"Point"}
}