{
  "type": "Feature",
  "properties": {
    "addr:full":"Zuukerweg 21 Epe Gelderland 8161 XW",
    "addr:housenumber":"21",
    "addr:postcode":"8161 xw",
    "addr:street":"Zuukerweg;Gelderland",
    "iso:country":"NL",
    "sg:address":"Zuukerweg 21",
    "sg:city":"Epe",
    "sg:classifiers":[
        {
            "category":"Professional",
            "subcategory":"Accounting & Tax Preparation",
            "type":"Services"
        }
    ],
    "sg:phone":"+31 578 614 537",
    "sg:postcode":"8161 XW",
    "sg:province":"Gelderland",
    "sg:tags":[
        "accountant"
    ],
    "wof:name":"Kieskamp Accountants",
    "wof:placetype":"venue"
},
  "geometry": {"coordinates":[6.00216,52.33588],"type":"Point"}
}