{
  "type": "Feature",
  "properties": {
    "iso:country":"NL",
    "sg:address":"Dampoortwg 29 A",
    "sg:city":"Middelburg",
    "sg:orig_category":"Meubelstoffering",
    "sg:phone":"+31 118 615 271",
    "sg:postcode":"4332 AW",
    "sg:province":"Zeeland",
    "wof:name":"Bies, De",
    "wof:placetype":"venue"
},
  "geometry": {"coordinates":[3.628659,51.503258],"type":"Point"}
}