{
  "type": "Feature",
  "properties": {
    "addr:full":"Nieuwstraat 23 Son Noord-Brabant 5691 AA",
    "addr:housenumber":"23",
    "addr:postcode":"5691 aa",
    "addr:street":"Nieuwstraat",
    "iso:country":"NL",
    "sg:address":"Nieuwstraat 23",
    "sg:city":"Son",
    "sg:classifiers":[
        {
            "category":"Fast Food",
            "type":"Food & Drink"
        }
    ],
    "sg:phone":"+31 499 471 533",
    "sg:postcode":"5691 AA",
    "sg:province":"Noord-Brabant",
    "sg:tags":[
        "afhaal",
        "restaurant"
    ],
    "wof:name":"Shoarma Sphinx",
    "wof:placetype":"venue"
},
  "geometry": {"coordinates":[-101.937622,35.189621],"type":"Point"}
}