{
  "type": "Feature",
  "properties": {
    "addr:full":"Postbus 327 Nuenen Noord-Brabant 5670 AH",
    "addr:housenumber":"327",
    "addr:postcode":"5670 ah",
    "addr:street":"Postbus",
    "iso:country":"NL",
    "sg:address":"Postbus 327",
    "sg:city":"Nuenen",
    "sg:orig_category":"Lpg-Installaties",
    "sg:phone":"+31 40 295 1428",
    "sg:postcode":"5670 AH",
    "sg:province":"Noord-Brabant",
    "sg:website":"http://www.dimaautogas.nl",
    "wof:name":"Dima Autogas",
    "wof:placetype":"venue"
},
  "geometry": {"coordinates":[5.54893,51.473518],"type":"Point"}
}