{
  "type": "Feature",
  "properties": {
    "iso:country":"NL",
    "sg:address":"Kloosterstraat 13",
    "sg:city":"Roosendaal",
    "sg:classifiers":[
        {
            "category":"Education",
            "subcategory":"Preschool",
            "type":"Public Place"
        }
    ],
    "sg:phone":"+31 165 537 091",
    "sg:postcode":"4701 KH",
    "sg:province":"Noord-Brabant",
    "sg:tags":[
        "kleuteronderwijs",
        "basis-"
    ],
    "wof:name":"Basisschool Jeroen Bosch",
    "wof:placetype":"venue"
},
  "geometry": {"coordinates":[4.458765,51.53561],"type":"Point"}
}