{
  "type": "Feature",
  "properties": {
    "addr:full":"De Smalle Zyde 50 Veenendaal Utrecht 3903 LP",
    "addr:housenumber":"50",
    "addr:postcode":"3903 lp",
    "addr:street":"De Smalle Zyde",
    "iso:country":"NL",
    "sg:address":"De Smalle Zyde 50",
    "sg:city":"Veenendaal",
    "sg:orig_category":"Verpakkingen En Verpakkingsmaterialen",
    "sg:phone":"+31 318 514 021",
    "sg:postcode":"3903 LP",
    "sg:province":"Utrecht",
    "sg:website":"http://www.barneveld-verpakkingen.nl",
    "wof:name":"Barneveld Bv, Van",
    "wof:placetype":"venue"
},
  "geometry": {"coordinates":[5.568697,52.00568],"type":"Point"}
}