{
  "type": "Feature",
  "properties": {
    "addr:full":"Raadhuislaan 49 Eemnes Utrecht 3755 HB",
    "addr:housenumber":"49",
    "addr:postcode":"3755 hb",
    "addr:street":"Raadhuislaan",
    "iso:country":"NL",
    "sg:address":"Raadhuislaan 49",
    "sg:city":"Eemnes",
    "sg:orig_category":"Banken And Kredietinstellingen",
    "sg:phone":"+31 35 538 0118",
    "sg:postcode":"3755 HB",
    "sg:province":"Utrecht",
    "wof:name":"Postkantoor",
    "wof:placetype":"venue"
},
  "geometry": {"coordinates":[5.261692,52.250652],"type":"Point"}
}