{
  "type": "Feature",
  "properties": {
    "iso:country":"NL",
    "sg:address":"Neptunusstraat 44",
    "sg:city":"Berlicum Nb",
    "sg:orig_category":"Grafisch Ontwerpers",
    "sg:phone":"+31 73 503 2222",
    "sg:postcode":"5258 AP",
    "sg:province":"North Brabant",
    "sg:website":"http://www.studiok2.nl",
    "wof:name":"K2, Studio",
    "wof:placetype":"venue"
},
  "geometry": {"coordinates":[5.394586,51.682617],"type":"Point"}
}