{
  "type": "Feature",
  "properties": {
    "addr:full":"Kerkstr 23 Nuland Noord-Brabant 5392 CA",
    "addr:housenumber":"23",
    "addr:postcode":"5392 ca",
    "addr:street":"Kerkstr",
    "iso:country":"NL",
    "sg:address":"Kerkstr 23",
    "sg:city":"Nuland",
    "sg:orig_category":"Kappers",
    "sg:phone":"+31 73 532 2116",
    "sg:postcode":"5392 CA",
    "sg:province":"Noord-Brabant",
    "wof:name":"Simone & Hair",
    "wof:placetype":"venue"
},
  "geometry": {"coordinates":[5.43212,51.730747],"type":"Point"}
}