{
  "type": "Feature",
  "properties": {
    "addr:full":"Stevinstraat 8D Heerhugowaard Noord-Holland 1704 RN",
    "addr:housenumber":"8d",
    "addr:postcode":"1704 rn",
    "addr:street":"Stevinstraat",
    "iso:country":"NL",
    "sg:address":"Stevinstraat 8D",
    "sg:city":"Heerhugowaard",
    "sg:orig_category":"Metaalwerken",
    "sg:phone":"+31 72 574 7427",
    "sg:postcode":"1704 RN",
    "sg:province":"Noord-Holland",
    "wof:name":"Alphera Vouwwandenfabriek",
    "wof:placetype":"venue"
},
  "geometry": {"coordinates":[4.832239,52.678993],"type":"Point"}
}