{
  "type": "Feature",
  "properties": {
    "iso:country":"NL",
    "sg:address":"Molenkampstg 10",
    "sg:city":"Haren Gn",
    "sg:orig_category":"Kappers",
    "sg:phone":"+31 50 534 4303",
    "sg:postcode":"9751 TT",
    "sg:province":"Groningen",
    "wof:name":"Marco & Miranda",
    "wof:placetype":"venue"
},
  "geometry": {"coordinates":[6.620924,53.168488],"type":"Point"}
}