{
  "type": "Feature",
  "properties": {
    "addr:full":"Hof V Zevenbergen 1 S Hertogenbosch Noord-Brabant 5211 HB",
    "addr:housenumber":"1",
    "addr:postcode":"5211 hb",
    "addr:street":"Zevenbergen",
    "iso:country":"NL",
    "sg:address":"Hof V Zevenbergen 1",
    "sg:city":"S Hertogenbosch",
    "sg:orig_category":"Projectontwikkeling",
    "sg:phone":"+31 73 657 0129",
    "sg:postcode":"5211 HB",
    "sg:province":"Noord-Brabant",
    "wof:name":"Bouwconsulting Bv",
    "wof:placetype":"venue"
},
  "geometry": {"coordinates":[5.29824,51.69075],"type":"Point"}
}