{
  "type": "Feature",
  "properties": {
    "addr:full":"Purmerplein 2 Amsterdam North Holland 1023 BD",
    "addr:housenumber":"2",
    "addr:postcode":"1023 bd",
    "addr:street":"Purmerplein",
    "iso:country":"NL",
    "sg:address":"Purmerplein 2",
    "sg:city":"Amsterdam",
    "sg:orig_category":"Verzekeringen",
    "sg:phone":"+31 20 632 5858",
    "sg:postcode":"1023 BD",
    "sg:province":"North Holland",
    "wof:name":"Mr. A. Langelaar Assurantien Bv",
    "wof:placetype":"venue"
},
  "geometry": {"coordinates":[4.943229,52.391144],"type":"Point"}
}