{
  "type": "Feature",
  "properties": {
    "iso:country":"NL",
    "sg:address":"Stadswg 11",
    "sg:city":"Sittard",
    "sg:orig_category":"Woningbouw- Verenigingen En -Stichtingen",
    "sg:phone":"+31 46 459 8888",
    "sg:postcode":"6131 AG",
    "sg:province":"Limburg",
    "sg:website":"http://www.stichtingwvs.nl",
    "wof:name":"Wvs, Sticht",
    "wof:placetype":"venue"
},
  "geometry": {"coordinates":[5.8596901894,50.9985275269],"type":"Point"}
}