{
  "type": "Feature",
  "properties": {
    "addr:full":"Honthorststr 15 Eindhoven North Brabant 5643 VG",
    "addr:housenumber":"15",
    "addr:postcode":"5643 vg",
    "addr:street":"Honthorststr",
    "iso:country":"NL",
    "sg:address":"Honthorststr 15",
    "sg:city":"Eindhoven",
    "sg:orig_category":"Journalisten Freelance",
    "sg:phone":"+31 40 212 8556",
    "sg:postcode":"5643 VG",
    "sg:province":"North Brabant",
    "wof:name":"Lunter, Marlene",
    "wof:placetype":"venue"
},
  "geometry": {"coordinates":[5.508766,51.429146],"type":"Point"}
}