{
  "type": "Feature",
  "properties": {
    "addr:full":"Fornheseln 118 Den Dolder Utrecht 3734 GE",
    "addr:housenumber":"118",
    "addr:postcode":"3734",
    "iso:country":"NL",
    "sg:address":"Fornheseln 118",
    "sg:city":"Den Dolder",
    "sg:orig_category":"Projectontwikkeling",
    "sg:phone":"+31 30 228 1952",
    "sg:postcode":"3734 GE",
    "sg:province":"Utrecht",
    "wof:name":"Melbosch Bv",
    "wof:placetype":"venue"
},
  "geometry": {"coordinates":[5.241445,52.139938],"type":"Point"}
}