{
  "type": "Feature",
  "properties": {
    "addr:full":"Broekwegzijde 114 Zoetermeer Zuid-Holland 2725 PE",
    "addr:housenumber":"114",
    "addr:postcode":"2725 pe",
    "addr:street":"Broekwegzijde",
    "iso:country":"NL",
    "sg:address":"Broekwegzijde 114",
    "sg:city":"Zoetermeer",
    "sg:classifiers":[
        {
            "category":"Fast Food",
            "type":"Food & Drink"
        }
    ],
    "sg:phone":"+31 79 341 5710",
    "sg:postcode":"2725 PE",
    "sg:province":"Zuid-Holland",
    "sg:tags":[
        "afhaal",
        "restaurant"
    ],
    "wof:name":"Aziatisch Spec Rest Asian Garden",
    "wof:placetype":"venue"
},
  "geometry": {"coordinates":[4.494364,52.071793],"type":"Point"}
}