{
  "type": "Feature",
  "properties": {
    "iso:country":"NL",
    "sg:address":"Meeuwerderwg 67",
    "sg:city":"Groningen",
    "sg:orig_category":"Natuurvoeding En Reformartikelen",
    "sg:phone":"+31 50 318 1422",
    "sg:postcode":"9724 EN",
    "sg:province":"Groningen",
    "wof:name":"Terp Natuurdesembakkerij, De",
    "wof:placetype":"venue"
},
  "geometry": {"coordinates":[6.578524,53.212135],"type":"Point"}
}