{
  "type": "Feature",
  "properties": {
    "iso:country":"NL",
    "sg:address":"Thull 12B",
    "sg:city":"Schinnen",
    "sg:orig_category":"Wijnkoperijen En -Groothandel",
    "sg:phone":"+31 46 443 4003",
    "sg:postcode":"6365 AC",
    "sg:province":"Limburg",
    "sg:website":"http://www.goedewijn.nl",
    "wof:name":"Thuller Gaard, De",
    "wof:placetype":"venue"
},
  "geometry": {"coordinates":[5.8961000443,50.938205719],"type":"Point"}
}