{
  "type": "Feature",
  "properties": {
    "addr:full":"Slotlaan 38 Zeist Utrecht 3701 GM",
    "addr:housenumber":"38",
    "addr:postcode":"3701 gm",
    "addr:street":"Slotlaan",
    "iso:country":"NL",
    "sg:address":"Slotlaan 38",
    "sg:city":"Zeist",
    "sg:orig_category":"Kappers",
    "sg:phone":"+31 30 691 6639",
    "sg:postcode":"3701 GM",
    "sg:province":"Utrecht",
    "wof:name":"Herenkapsalon Joli Bv",
    "wof:placetype":"venue"
},
  "geometry": {"coordinates":[5.2411789894,52.0829963684],"type":"Point"}
}