{
  "type": "Feature",
  "properties": {
    "addr:full":"Boterdiep 58 Groningen Groningen 9712 LR",
    "addr:housenumber":"58",
    "addr:postcode":"9712 lr",
    "addr:street":"Boterdiep",
    "iso:country":"NL",
    "sg:address":"Boterdiep 58",
    "sg:city":"Groningen",
    "sg:classifiers":[
        {
            "category":"Communications",
            "subcategory":"Television Station",
            "type":"Services"
        }
    ],
    "sg:phone":"+31 50 311 2737",
    "sg:postcode":"9712 LR",
    "sg:province":"Groningen",
    "sg:tags":[
        "video",
        "audio",
        "verhuur"
    ],
    "wof:name":"King Long Videotheek",
    "wof:placetype":"venue"
},
  "geometry": {"coordinates":[6.563702,53.224266],"type":"Point"}
}