{
  "type": "Feature",
  "properties": {
    "addr:full":"Lindenln 44A Kerkrade Limburg 6463 GK",
    "addr:housenumber":"44a",
    "addr:postcode":"6463 gk",
    "addr:street":"Lindenln",
    "iso:country":"NL",
    "sg:address":"Lindenln 44A",
    "sg:city":"Kerkrade",
    "sg:orig_category":"Gehandicapteninformatie",
    "sg:phone":"+31 45 535 4792",
    "sg:postcode":"6463 GK",
    "sg:province":"Limburg",
    "wof:name":"Fokus",
    "wof:placetype":"venue"
},
  "geometry": {"coordinates":[6.059685,50.863773],"type":"Point"}
}