{
  "type": "Feature",
  "properties": {
    "addr:full":"Weelwg 4C Waarde Zeeland 4414 AW",
    "addr:housenumber":"4c",
    "addr:postcode":"4414 aw",
    "addr:street":"Weelwg",
    "iso:country":"NL",
    "sg:address":"Weelwg 4C",
    "sg:city":"Waarde",
    "sg:orig_category":"Grondwerken",
    "sg:phone":"+31 113 501 310",
    "sg:postcode":"4414 AW",
    "sg:province":"Zeeland",
    "sg:website":"http://www.materieelpagina.nl",
    "wof:name":"Goud, Grondverzet",
    "wof:placetype":"venue"
},
  "geometry": {"coordinates":[4.071406,51.415859],"type":"Point"}
}