{
  "type": "Feature",
  "properties": {
    "addr:full":"Reilinkswg 8 Holten Overijssel 7451 CR",
    "addr:housenumber":"8",
    "addr:postcode":"7451 cr",
    "addr:street":"Reilinkswg",
    "iso:country":"NL",
    "sg:address":"Reilinkswg 8",
    "sg:city":"Holten",
    "sg:orig_category":"Begrafenisverzorging",
    "sg:phone":"+31 548 363 237",
    "sg:postcode":"7451 CR",
    "sg:province":"Overijssel",
    "sg:website":"http://www.monuta.nl",
    "wof:name":"Monuta",
    "wof:placetype":"venue"
},
  "geometry": {"coordinates":[6.415073,52.28204],"type":"Point"}
}