{
  "type": "Feature",
  "properties": {
    "addr:full":"Hanzeplein 121 Groningen Groningen 9713 GW",
    "addr:housenumber":"121",
    "addr:postcode":"9713 gw",
    "addr:street":"Hanzeplein",
    "iso:country":"NL",
    "sg:address":"Hanzeplein 121",
    "sg:city":"Groningen",
    "sg:orig_category":"Banken And Kredietinstellingen",
    "sg:phone":"+31 50 313 6959",
    "sg:postcode":"9713 GW",
    "sg:province":"Groningen",
    "wof:name":"Abn Amro",
    "wof:placetype":"venue"
},
  "geometry": {"coordinates":[6.576861,53.220219],"type":"Point"}
}