{
  "type": "Feature",
  "properties": {
    "iso:country":"NL",
    "sg:address":"Haagdk 1",
    "sg:city":"S Gravenpolder",
    "sg:orig_category":"Sportverenigingen En Ontspannings- Verenigingen",
    "sg:phone":"+31 113 312 267",
    "sg:postcode":"4431 NG",
    "sg:province":"Zeeland",
    "wof:name":"Goblin Tennisver",
    "wof:placetype":"venue"
},
  "geometry": {"coordinates":[3.900693,51.456345],"type":"Point"}
}