{
  "type": "Feature",
  "properties": {
    "iso:country":"NL",
    "sg:address":"Herenstraat 138",
    "sg:city":"Voorburg",
    "sg:orig_category":"Glaszetten",
    "sg:phone":"+31 70 386 4421",
    "sg:postcode":"2271 CL",
    "sg:province":"Zuid-Holland",
    "wof:name":"Voorburgse Glashandel",
    "wof:placetype":"venue"
},
  "geometry": {"coordinates":[4.362283,52.066391],"type":"Point"}
}