{
  "type": "Feature",
  "properties": {
    "iso:country":"NL",
    "sg:address":"Molenstr 109",
    "sg:city":"Clinge",
    "sg:orig_category":"Metaalbewerking",
    "sg:phone":"+31 114 314 623",
    "sg:postcode":"4567 BC",
    "sg:province":"Zeeland",
    "wof:name":"Steycon",
    "wof:placetype":"venue"
},
  "geometry": {"coordinates":[4.070797,51.26281],"type":"Point"}
}