{
  "type": "Feature",
  "properties": {
    "addr:full":"Gildenwg 131 Gorinchem South Holland 4204 GG",
    "addr:housenumber":"131",
    "addr:postcode":"4204 gg",
    "iso:country":"NL",
    "sg:address":"Gildenwg 131",
    "sg:city":"Gorinchem",
    "sg:orig_category":"Kappers",
    "sg:phone":"+31 183 632 487",
    "sg:postcode":"4204 GG",
    "sg:province":"South Holland",
    "wof:name":"Hairwear Team",
    "wof:placetype":"venue"
},
  "geometry": {"coordinates":[4.9504680634,51.8374176025],"type":"Point"}
}