{
  "type": "Feature",
  "properties": {
    "addr:full":"Breitnerhof 106 Meppel Drenthe 7944 LC",
    "addr:housenumber":"106",
    "addr:postcode":"7944 lc",
    "addr:street":"Breitnerhof",
    "iso:country":"NL",
    "sg:address":"Breitnerhof 106",
    "sg:city":"Meppel",
    "sg:orig_category":"Handelsbemiddeling Textiel And Lederwaren",
    "sg:phone":"+31 522 251 464",
    "sg:postcode":"7944 LC",
    "sg:province":"Drenthe",
    "wof:name":"Kreuze",
    "wof:placetype":"venue"
},
  "geometry": {"coordinates":[6.181817,52.691235],"type":"Point"}
}