{
  "type": "Feature",
  "properties": {
    "iso:country":"NL",
    "sg:address":"Postbus 38036",
    "sg:city":"Nymegen",
    "sg:orig_category":"Psychologen",
    "sg:phone":"+31 24 344 5801",
    "sg:postcode":"6503 AA",
    "sg:website":"http://www.psyline.nl",
    "wof:name":"B\u00f6gels, Drs T J P M",
    "wof:placetype":"venue"
},
  "geometry": {"coordinates":[-89.616074,35.32584],"type":"Point"}
}