{
  "type": "Feature",
  "properties": {
    "addr:full":"Nyverheidswg 10A Giessenburg South Holland 3381 LM",
    "addr:housenumber":"10a",
    "addr:postcode":"3381 lm",
    "addr:street":"Nyverheidswg",
    "iso:country":"NL",
    "sg:address":"Nyverheidswg 10A",
    "sg:city":"Giessenburg",
    "sg:orig_category":"Land- En Tuinbouw - Mechanisatie",
    "sg:phone":"+31 184 651 453",
    "sg:postcode":"3381 LM",
    "sg:province":"South Holland",
    "sg:website":"http://www.hdeleeuw.nl",
    "wof:name":"Leeuw, H De",
    "wof:placetype":"venue"
},
  "geometry": {"coordinates":[4.896502,51.843922],"type":"Point"}
}