{
  "type": "Feature",
  "properties": {
    "addr:full":"Postweg 2 Leersum Utrecht 3956 RZ",
    "addr:housenumber":"2",
    "addr:postcode":"3956 rz",
    "addr:street":"Postweg",
    "iso:country":"NL",
    "sg:address":"Postweg 2",
    "sg:city":"Leersum",
    "sg:orig_category":"Boekhouders",
    "sg:phone":"+31 343 454 809",
    "sg:postcode":"3956 RZ",
    "sg:province":"Utrecht",
    "wof:name":"G.A. Van Schaik",
    "wof:placetype":"venue"
},
  "geometry": {"coordinates":[5.41551,52.01107],"type":"Point"}
}