{
  "type": "Feature",
  "properties": {
    "iso:country":"NL",
    "sg:address":"Sjungadijk 14",
    "sg:city":"Burgwerd",
    "sg:orig_category":"Kampeerterreinen",
    "sg:phone":"+31 515 575 167",
    "sg:postcode":"8742 KL",
    "sg:province":"Friesland",
    "wof:name":"Aylvapolder Skieppebuorkerij",
    "wof:placetype":"venue"
},
  "geometry": {"coordinates":[5.539247036,53.091796875],"type":"Point"}
}