{
  "type": "Feature",
  "properties": {
    "addr:full":"Produktiewg 6 Roermond Limburg 6045 JC",
    "addr:housenumber":"6",
    "addr:postcode":"6045 jc",
    "addr:street":"Produktiewg",
    "iso:country":"NL",
    "sg:address":"Produktiewg 6",
    "sg:city":"Roermond",
    "sg:orig_category":"Kunststoffen- Verwerkende Industrie",
    "sg:phone":"+31 475 370 270",
    "sg:postcode":"6045 JC",
    "sg:province":"Limburg",
    "wof:name":"Schmitz Bv",
    "wof:placetype":"venue"
},
  "geometry": {"coordinates":[6.051839,51.167629],"type":"Point"}
}