{
  "type": "Feature",
  "properties": {
    "iso:country":"NL",
    "sg:address":"Burg Stramanwg 102J",
    "sg:city":"Amsterdam Zuidoost",
    "sg:classifiers":[
        {
            "category":"Professional",
            "subcategory":"Management & Consulting",
            "type":"Services"
        }
    ],
    "sg:phone":"+31 20 363 1152",
    "sg:postcode":"1101 AA",
    "sg:province":"Noord-Holland",
    "sg:tags":[
        "relation",
        "adviesbureaus",
        "public"
    ],
    "sg:website":"http://www.workinprogress.nl",
    "wof:name":"Work In Progress",
    "wof:placetype":"venue"
},
  "geometry": {"coordinates":[4.934398,52.31152],"type":"Point"}
}