{
  "type": "Feature",
  "properties": {
    "addr:full":"Wilhelminastraat 27 Mijnsheerenland Zuid-Holland 3271 BX",
    "addr:housenumber":"27",
    "addr:postcode":"3271 bx",
    "addr:street":"Wilhelminastraat",
    "iso:country":"NL",
    "sg:address":"Wilhelminastraat 27",
    "sg:city":"Mijnsheerenland",
    "sg:orig_category":"Verlichting And Huishoudartikelen",
    "sg:phone":"+31 186 601 396",
    "sg:postcode":"3271 BX",
    "sg:province":"Zuid-Holland",
    "wof:name":"L.E.Van Der Sluys",
    "wof:placetype":"venue"
},
  "geometry": {"coordinates":[4.49302,51.797466],"type":"Point"}
}