{
  "type": "Feature",
  "properties": {
    "iso:country":"NL",
    "sg:address":"Nyverheidswg 18",
    "sg:city":"Purmerend",
    "sg:orig_category":"Naamplaten - Fabrieken",
    "sg:phone":"+31 299 431 977",
    "sg:postcode":"1442 LD",
    "sg:province":"Noord-Holland",
    "sg:website":"http://www.ospla.com",
    "wof:name":"Ospla",
    "wof:placetype":"venue"
},
  "geometry": {"coordinates":[4.977,52.516994],"type":"Point"}
}