{
  "type": "Feature",
  "properties": {
    "iso:country":"NL",
    "sg:address":"Koopvaardijweg 7",
    "sg:city":"Oosterhout Nb",
    "sg:classifiers":[
        {
            "category":"Retail",
            "subcategory":"Storage",
            "type":"Services"
        }
    ],
    "sg:phone":"+31 162 454 437",
    "sg:postcode":"4906 CV",
    "sg:province":"North Brabant",
    "sg:tags":[
        "opslag",
        "bewaring"
    ],
    "wof:name":"Opslag- En Logistiek Van Wanrooy Bv",
    "wof:placetype":"venue"
},
  "geometry": {"coordinates":[4.8372120857,51.6659698486],"type":"Point"}
}