{
  "type": "Feature",
  "properties": {
    "iso:country":"NL",
    "sg:address":"Einsteinweg 27",
    "sg:city":"Bunschoten Spakenburg",
    "sg:orig_category":"Autokeuringen",
    "sg:phone":"+31 33 298 3990",
    "sg:postcode":"3752 LW",
    "sg:province":"Utrecht",
    "wof:name":"Tijra",
    "wof:placetype":"venue"
},
  "geometry": {"coordinates":[5.368503,52.229141],"type":"Point"}
}