{
  "type": "Feature",
  "properties": {
    "iso:country":"NL",
    "sg:address":"Dorsvloer 3",
    "sg:city":"Drachten",
    "sg:classifiers":[
        {
            "category":"Education",
            "subcategory":"Preschool",
            "type":"Public Place"
        }
    ],
    "sg:phone":"+31 512 530 405",
    "sg:postcode":"9205 BN",
    "sg:province":"Friesland",
    "sg:tags":[
        "kleuteronderwijs",
        "basis-"
    ],
    "wof:name":"T Foarhus Prot Chr",
    "wof:placetype":"venue"
},
  "geometry": {"coordinates":[6.056673,53.093697],"type":"Point"}
}