{
  "type": "Feature",
  "properties": {
    "addr:full":"Poelgeeststr 24-24A Leiden South Holland 2316 XL",
    "addr:housenumber":"24-24a",
    "addr:postcode":"2316 xl",
    "iso:country":"NL",
    "sg:address":"Poelgeeststr 24-24A",
    "sg:city":"Leiden",
    "sg:orig_category":"Beeldende Kunstenaars",
    "sg:phone":"+31 71 522 0657",
    "sg:postcode":"2316 XL",
    "sg:province":"South Holland",
    "wof:name":"Gerard De Reus",
    "wof:placetype":"venue"
},
  "geometry": {"coordinates":[4.488862,52.167004],"type":"Point"}
}