{
  "type": "Feature",
  "properties": {
    "addr:full":"Postbus 2 Emst Gelderland 8166 ZG",
    "addr:housenumber":"2",
    "addr:postcode":"8166 zg",
    "addr:street":"Postbus;Gelderland",
    "iso:country":"NL",
    "sg:address":"Postbus 2",
    "sg:city":"Emst",
    "sg:orig_category":"Voetbalverenigingen",
    "sg:phone":"+31 55 312 1432",
    "sg:postcode":"8166 ZG",
    "sg:province":"Gelderland",
    "wof:name":"Emst Vv",
    "wof:placetype":"venue"
},
  "geometry": {"coordinates":[5.975392,52.315819],"type":"Point"}
}