{
  "type": "Feature",
  "properties": {
    "addr:full":"Ootmarsumsestraat 29 Oldenzaal NL.08 7572 AB",
    "addr:housenumber":"29;nl.08",
    "addr:postcode":"7572 ab",
    "addr:street":"Ootmarsumsestraat",
    "iso:country":"NL",
    "sg:address":"Ootmarsumsestraat 29",
    "sg:city":"Oldenzaal",
    "sg:orig_category":"Overheidsdiensten",
    "sg:phone":"+31 541 514 090",
    "sg:postcode":"7572 AB",
    "sg:province":"NL.08",
    "wof:name":"Gak Groep",
    "wof:placetype":"venue"
},
  "geometry": {"coordinates":[6.9312000275,52.3176689148],"type":"Point"}
}