{
  "type": "Feature",
  "properties": {
    "addr:full":"Boulev De Wieling 39 Cadzand Zeeland 4506 JK",
    "addr:housenumber":"39",
    "addr:postcode":"4506 jk",
    "addr:street":"Boulev De Wieling",
    "iso:country":"NL",
    "sg:address":"Boulev De Wieling 39",
    "sg:city":"Cadzand",
    "sg:orig_category":"Schelpenhandel",
    "sg:phone":"+31 117 391 469",
    "sg:postcode":"4506 JK",
    "sg:province":"Zeeland",
    "wof:name":"Reuzenschelp, De",
    "wof:placetype":"venue"
},
  "geometry": {"coordinates":[3.391363,51.37888],"type":"Point"}
}