{
  "type": "Feature",
  "properties": {
    "addr:full":"Spoordwarsstraat 9 Ijsselmuiden Overijssel 8271 RD",
    "addr:housenumber":"9",
    "addr:postcode":"8271 rd",
    "addr:street":"Spoordwarsstraat",
    "iso:country":"NL",
    "sg:address":"Spoordwarsstraat 9",
    "sg:city":"Ijsselmuiden",
    "sg:orig_category":"Diverse Bedrijfsinstallaties Gh",
    "sg:phone":"+31 38 333 0348",
    "sg:postcode":"8271 RD",
    "sg:province":"Overijssel",
    "wof:name":"Lubbers Machinefabriek",
    "wof:placetype":"venue"
},
  "geometry": {"coordinates":[5.929104,52.555878],"type":"Point"}
}