{
  "type": "Feature",
  "properties": {
    "iso:country":"NL",
    "sg:address":"Roermondsewg 28",
    "sg:city":"Haelen",
    "sg:orig_category":"Verf En Lak - Fabrieken En Groothandel",
    "sg:phone":"+31 475 594 777",
    "sg:postcode":"6081 NV",
    "sg:province":"Limburg",
    "sg:website":"http://www.prinsses.net",
    "wof:name":"Prinssen Sierpleisters",
    "wof:placetype":"venue"
},
  "geometry": {"coordinates":[5.963329,51.229237],"type":"Point"}
}