{
  "type": "Feature",
  "properties": {
    "addr:full":"V Oldenbarnev Ln 87 S Gravenhage South Holland 2582 NK",
    "addr:housenumber":"87",
    "addr:postcode":"2582 nk",
    "addr:street":"Oldenbarnev Ln;S Gravenhage",
    "iso:country":"NL",
    "sg:address":"V Oldenbarnev Ln 87",
    "sg:city":"S Gravenhage",
    "sg:orig_category":"Juridische Adviseurs",
    "sg:phone":"+31 70 416 1919",
    "sg:postcode":"2582 NK",
    "sg:province":"South Holland",
    "wof:name":"Quaedvlieg Bv",
    "wof:placetype":"venue"
},
  "geometry": {"coordinates":[4.27852,52.092411],"type":"Point"}
}