{
  "type": "Feature",
  "properties": {
    "addr:full":"Westersngl 12 Rotterdam Zuid-Holland 3014 GN",
    "addr:housenumber":"12",
    "addr:postcode":"3014 gn",
    "addr:street":"Westersngl",
    "iso:country":"NL",
    "sg:address":"Westersngl 12",
    "sg:city":"Rotterdam",
    "sg:orig_category":"Verzekerings- Maatschappijen",
    "sg:phone":"+31 10 424 5711",
    "sg:postcode":"3014 GN",
    "sg:province":"Zuid-Holland",
    "wof:name":"Optas Nv",
    "wof:placetype":"venue"
},
  "geometry": {"coordinates":[4.478455,51.922836],"type":"Point"}
}