{
  "type": "Feature",
  "properties": {
    "iso:country":"NL",
    "sg:address":"De Houtmanstr 36",
    "sg:city":"Hoogezand",
    "sg:orig_category":"Watersportartikelen",
    "sg:phone":"+31 598 391 143",
    "sg:postcode":"9601 GJ",
    "sg:province":"Groningen",
    "wof:name":"Aqua Sports",
    "wof:placetype":"venue"
},
  "geometry": {"coordinates":[6.7590198517,53.1669998169],"type":"Point"}
}