{
  "type": "Feature",
  "properties": {
    "iso:country":"NL",
    "sg:address":"Fluweelboomln 245",
    "sg:city":"Amstelveen",
    "sg:orig_category":"Metaalbewerking",
    "sg:phone":"+31 20 647 0322",
    "sg:postcode":"1185 PS",
    "sg:province":"North Holland",
    "sg:website":"http://www.Metaldesign.nl",
    "wof:name":"Cor Van Kuijk",
    "wof:placetype":"venue"
},
  "geometry": {"coordinates":[4.852631,52.291046],"type":"Point"}
}