{
  "type": "Feature",
  "properties": {
    "addr:full":"Zundertseweg 100 Schijf North Brabant 4722 SJ",
    "addr:housenumber":"100",
    "addr:postcode":"4722",
    "addr:street":"Zundertseweg",
    "iso:country":"NL",
    "sg:address":"Zundertseweg 100",
    "sg:city":"Schijf",
    "sg:orig_category":"Binnenvaart",
    "sg:phone":"+31 165 348 104",
    "sg:postcode":"4722 SJ",
    "sg:province":"North Brabant",
    "wof:name":"Rondvaartbedrijf Avontuur",
    "wof:placetype":"venue"
},
  "geometry": {"coordinates":[4.580413,51.509285],"type":"Point"}
}