{
  "type": "Feature",
  "properties": {
    "iso:country":"NL",
    "sg:address":"Elzenstr 36",
    "sg:city":"Den Helder",
    "sg:orig_category":"Verenigingen En Stichtingen",
    "sg:phone":"+31 223 621 029",
    "sg:postcode":"1783 HX",
    "sg:province":"North Holland",
    "wof:name":"Winnubst",
    "wof:placetype":"venue"
},
  "geometry": {"coordinates":[4.731632,52.941612],"type":"Point"}
}