{
  "type": "Feature",
  "properties": {
    "iso:country":"NL",
    "sg:address":"Den Achterhof 5",
    "sg:city":"Liempde",
    "sg:orig_category":"Chemische Producten Gh",
    "sg:phone":"+31 411 632 074",
    "sg:postcode":"5298 BG",
    "sg:province":"Noord-Brabant",
    "wof:name":"H.P. V.D. Wildenberg",
    "wof:placetype":"venue"
},
  "geometry": {"coordinates":[5.375202,51.567768],"type":"Point"}
}