{
  "type": "Feature",
  "properties": {
    "iso:country":"NL",
    "sg:address":"Noordhollandstr 80",
    "sg:city":"Amsterdam",
    "sg:orig_category":"Horloges - Groothandel",
    "sg:phone":"+31 20 644 5369",
    "sg:postcode":"1081 AV",
    "sg:province":"Noord-Holland",
    "wof:name":"Europe Watches",
    "wof:placetype":"venue"
},
  "geometry": {"coordinates":[4.865384,52.323841],"type":"Point"}
}