{
  "type": "Feature",
  "properties": {
    "addr:full":"De Hagen 2 Eibergen Gelderland 7151 CA",
    "addr:housenumber":"2",
    "addr:postcode":"7151 ca",
    "addr:street":"De Hagen;Gelderland",
    "iso:country":"NL",
    "sg:address":"De Hagen 2",
    "sg:city":"Eibergen",
    "sg:orig_category":"Baby- And Kinderkleding",
    "sg:phone":"+31 545 474 458",
    "sg:postcode":"7151 CA",
    "sg:province":"Gelderland",
    "wof:name":"Reinders Mode",
    "wof:placetype":"venue"
},
  "geometry": {"coordinates":[6.647932,52.102184],"type":"Point"}
}