{
  "type": "Feature",
  "properties": {
    "addr:full":"Westerplein 10 Berkel En Rodenrijs South Holland 2651 JM",
    "addr:housenumber":"10",
    "addr:postcode":"2651 jm",
    "addr:street":"Westerplein",
    "iso:country":"NL",
    "sg:address":"Westerplein 10",
    "sg:city":"Berkel En Rodenrijs",
    "sg:orig_category":"Banken And Kredietinstellingen",
    "sg:phone":"+31 10 519 2233",
    "sg:postcode":"2651 JM",
    "sg:province":"South Holland",
    "wof:name":"Ing Bank",
    "wof:placetype":"venue"
},
  "geometry": {"coordinates":[4.474056,51.993874],"type":"Point"}
}