{
  "type": "Feature",
  "properties": {
    "addr:full":"President Kennedylaan 299 Velp Gld Gelderland 6883 AK",
    "addr:housenumber":"299",
    "addr:postcode":"6883 ak",
    "addr:street":"President Kennedylaan;Gld Gelderland",
    "iso:country":"NL",
    "sg:address":"President Kennedylaan 299",
    "sg:city":"Velp Gld",
    "sg:orig_category":"Drukkerijen And Copyshops",
    "sg:phone":"+31 26 362 2485",
    "sg:postcode":"6883 AK",
    "sg:province":"Gelderland",
    "wof:name":"Vof Velpprint",
    "wof:placetype":"venue"
},
  "geometry": {"coordinates":[5.979779,51.987297],"type":"Point"}
}