{
  "type": "Feature",
  "properties": {
    "iso:country":"NL",
    "sg:address":"Nieuwstr 15",
    "sg:city":"Budel",
    "sg:orig_category":"Opticiens",
    "sg:phone":"+31 495 494 363",
    "sg:postcode":"6021 HP",
    "sg:province":"North Brabant",
    "sg:website":"http://www.phillipoptiek.nl",
    "wof:name":"Phillip",
    "wof:placetype":"venue"
},
  "geometry": {"coordinates":[5.5737228394,51.2728538513],"type":"Point"}
}