{
  "type": "Feature",
  "properties": {
    "iso:country":"NL",
    "sg:address":"Voorthuizerstraat 202",
    "sg:city":"Putten",
    "sg:classifiers":[
        {
            "category":"Fast Food",
            "type":"Food & Drink"
        }
    ],
    "sg:phone":"+31 341 358 771",
    "sg:postcode":"3881 SM",
    "sg:province":"Gelderland",
    "sg:tags":[
        "afhaal",
        "restaurant"
    ],
    "wof:name":"Vof 'T Melkmeisje",
    "wof:placetype":"venue"
},
  "geometry": {"coordinates":[5.609606,52.22765],"type":"Point"}
}