{
  "type": "Feature",
  "properties": {
    "iso:country":"NL",
    "sg:address":"Nw Achtergr 17",
    "sg:city":"Amsterdam",
    "sg:orig_category":"Architecten En Architectenbureaus",
    "sg:phone":"+31 20 420 8890",
    "sg:postcode":"1018 XV",
    "sg:province":"Noord-Holland",
    "wof:name":"Kossmann En De Jong",
    "wof:placetype":"venue"
},
  "geometry": {"coordinates":[4.906109,52.362457],"type":"Point"}
}