{
  "type": "Feature",
  "properties": {
    "addr:full":"T Dorp 124 Heesch North Brabant 5384 MD",
    "addr:housenumber":"124",
    "addr:postcode":"5384",
    "addr:street":"T Dorp",
    "iso:country":"NL",
    "sg:address":"T Dorp 124",
    "sg:city":"Heesch",
    "sg:orig_category":"Woninginrichting",
    "sg:phone":"+31 412 456 106",
    "sg:postcode":"5384 MD",
    "sg:province":"North Brabant",
    "wof:name":"Interiors",
    "wof:placetype":"venue"
},
  "geometry": {"coordinates":[5.5217981339,51.7341003418],"type":"Point"}
}