{
  "type": "Feature",
  "properties": {
    "addr:full":"Plesmanstraat 2 Assen Drenthe 9403 AL",
    "addr:housenumber":"2",
    "addr:postcode":"9403 al",
    "addr:street":"Plesmanstraat",
    "iso:country":"NL",
    "sg:address":"Plesmanstraat 2",
    "sg:city":"Assen",
    "sg:orig_category":"Metaalafval, Schrootrecycling And Sloperijen",
    "sg:phone":"+31 592 343 672",
    "sg:postcode":"9403 AL",
    "sg:province":"Drenthe",
    "wof:name":"Autosloperij Doldersum",
    "wof:placetype":"venue"
},
  "geometry": {"coordinates":[6.578145,53.002647],"type":"Point"}
}