{
  "type": "Feature",
  "properties": {
    "addr:full":"Wielemakersbaan 4 Koudekerke Zeeland 4371 PM",
    "addr:housenumber":"4",
    "addr:postcode":"4371 pm",
    "addr:street":"Wielemakersbaan",
    "iso:country":"NL",
    "sg:address":"Wielemakersbaan 4",
    "sg:city":"Koudekerke",
    "sg:orig_category":"Schilders",
    "sg:phone":"+31 118 551 121",
    "sg:postcode":"4371 PM",
    "sg:province":"Zeeland",
    "wof:name":"Walraven, B",
    "wof:placetype":"venue"
},
  "geometry": {"coordinates":[3.535767,51.479027],"type":"Point"}
}