{
  "type": "Feature",
  "properties": {
    "addr:full":"De Volmer 132 Haaksbergen NL.08 7482 HB",
    "addr:housenumber":"132;nl.08",
    "addr:postcode":"7482 hb",
    "addr:street":"De Volmer",
    "iso:country":"NL",
    "sg:address":"De Volmer 132",
    "sg:city":"Haaksbergen",
    "sg:orig_category":"Loonbedrijven",
    "sg:phone":"+31 6 10798692",
    "sg:postcode":"7482 HB",
    "sg:province":"NL.08",
    "wof:name":"Extrapak",
    "wof:placetype":"venue"
},
  "geometry": {"coordinates":[6.717462,52.161587],"type":"Point"}
}