{
  "type": "Feature",
  "properties": {
    "iso:country":"NL",
    "sg:address":"De Volmer 132",
    "sg:city":"Haaksbergen",
    "sg:orig_category":"Loonbedrijven",
    "sg:phone":"+31 6 10798692",
    "sg:postcode":"7482 HB",
    "sg:province":"NL.08",
    "wof:name":"Extrapak",
    "wof:placetype":"venue"
},
  "geometry": {"coordinates":[6.717462,52.161587],"type":"Point"}
}