{
  "type": "Feature",
  "properties": {
    "addr:full":"V Reenenwg 80 Zeist Utrecht 3702 SM",
    "addr:housenumber":"80",
    "addr:postcode":"3702 sm",
    "iso:country":"NL",
    "sg:address":"V Reenenwg 80",
    "sg:city":"Zeist",
    "sg:orig_category":"Bedrijfsmechanisatie En -Automatisering",
    "sg:phone":"+31 30 692 4480",
    "sg:postcode":"3702 SM",
    "sg:province":"Utrecht",
    "wof:name":"Geha Vof",
    "wof:placetype":"venue"
},
  "geometry": {"coordinates":[5.24387,52.08548],"type":"Point"}
}