{
  "type": "Feature",
  "properties": {
    "iso:country":"NL",
    "sg:address":"L Brugstr 63",
    "sg:city":"Etten Leur",
    "sg:orig_category":"Zalenverhuur",
    "sg:phone":"+31 76 501 3145",
    "sg:postcode":"4871 CM",
    "sg:province":"North Brabant",
    "sg:website":"http://www.turfschip.nl",
    "wof:name":"Turfschip, 'T",
    "wof:placetype":"venue"
},
  "geometry": {"coordinates":[4.66156,51.586948],"type":"Point"}
}