{
  "type": "Feature",
  "properties": {
    "iso:country":"NL",
    "sg:address":"Piet Heinstraat 59",
    "sg:city":"Helmond",
    "sg:classifiers":[
        {
            "category":"Bakery",
            "type":"Food & Drink"
        }
    ],
    "sg:phone":"+31 492 523 150",
    "sg:postcode":"5703 AK",
    "sg:province":"Noord-Brabant",
    "sg:tags":[
        "brood",
        "banket"
    ],
    "wof:name":"Van Duynhoven Bv",
    "wof:placetype":"venue"
},
  "geometry": {"coordinates":[5.682064,51.476303],"type":"Point"}
}