{
  "type": "Feature",
  "properties": {
    "addr:full":"Noordkd 183 Waddinxveen South Holland 2741 GA",
    "addr:housenumber":"183",
    "addr:postcode":"2741 ga",
    "iso:country":"NL",
    "sg:address":"Noordkd 183",
    "sg:city":"Waddinxveen",
    "sg:orig_category":"Verzekeringen - Verzekeringskantoren",
    "sg:phone":"+31 182 614 630",
    "sg:postcode":"2741 GA",
    "sg:province":"South Holland",
    "wof:name":"Rooy Van Der Loo, De",
    "wof:placetype":"venue"
},
  "geometry": {"coordinates":[4.65507,52.044601],"type":"Point"}
}