{
  "type": "Feature",
  "properties": {
    "addr:full":"Dekkershof 3 Gorssel Gelderland 7213 XJ",
    "addr:housenumber":"3",
    "addr:postcode":"7213 xj",
    "addr:street":"Dekkershof;Gelderland",
    "iso:country":"NL",
    "sg:address":"Dekkershof 3",
    "sg:city":"Gorssel",
    "sg:orig_category":"Vertaalbureaus",
    "sg:phone":"+31 575 544 841",
    "sg:postcode":"7213 XJ",
    "sg:province":"Gelderland",
    "sg:website":"http://home.planet.nl/~taalhuis",
    "wof:name":"Baukje Van Bruggen",
    "wof:placetype":"venue"
},
  "geometry": {"coordinates":[6.204556,52.203484],"type":"Point"}
}