{
  "type": "Feature",
  "properties": {
    "addr:full":"Neerveldstraat 41 Oss Noord-Brabant 5348 LB",
    "addr:housenumber":"41",
    "addr:postcode":"5348 lb",
    "addr:street":"Neerveldstraat",
    "iso:country":"NL",
    "sg:address":"Neerveldstraat 41",
    "sg:city":"Oss",
    "sg:orig_category":"Vertaal- And Tolkenbureaus",
    "sg:phone":"+31 412 634 119",
    "sg:postcode":"5348 LB",
    "sg:province":"Noord-Brabant",
    "wof:name":"M.Heesen Beedigd Vertaalster",
    "wof:placetype":"venue"
},
  "geometry": {"coordinates":[-77.235214,38.312599],"type":"Point"}
}