{
  "type": "Feature",
  "properties": {
    "addr:full":"Postbus 5051 Arnhem Noord-Brabant 6802 EB",
    "addr:housenumber":"5051",
    "addr:postcode":"6802 eb",
    "addr:street":"Postbus",
    "iso:country":"NL",
    "sg:address":"Postbus 5051",
    "sg:city":"Arnhem",
    "sg:orig_category":"Accountants - Administratie- Consulenten En -Kantoren",
    "sg:phone":"+31 26 351 7820",
    "sg:postcode":"6802 EB",
    "sg:province":"Noord-Brabant",
    "sg:website":"http://www.administratiekantoor.org",
    "wof:name":"Administratiekantoor.Org",
    "wof:placetype":"venue"
},
  "geometry": {"coordinates":[5.9124,51.979729],"type":"Point"}
}