{
  "type": "Feature",
  "properties": {
    "addr:full":"J C Wilslaan 21 Apeldoorn Gelderland 7313 HK",
    "addr:housenumber":"21",
    "addr:postcode":"7313 hk",
    "addr:street":"J C Wilslaan;Gelderland",
    "iso:country":"NL",
    "sg:address":"J C Wilslaan 21",
    "sg:city":"Apeldoorn",
    "sg:classifiers":[
        {
            "category":"Shopping",
            "subcategory":"Gifts & Souvenirs",
            "type":"Retail Goods"
        }
    ],
    "sg:phone":"+31 55 355 5200",
    "sg:postcode":"7313 HK",
    "sg:province":"Gelderland",
    "sg:tags":[
        "geschenken"
    ],
    "wof:name":"Souvenierswinkel Arends",
    "wof:placetype":"venue"
},
  "geometry": {"coordinates":[5.92586,52.214008],"type":"Point"}
}