{
  "type": "Feature",
  "properties": {
    "addr:full":"Arent Krijtsstraat 1 Diemen Noord-Holland 1111 AG",
    "addr:housenumber":"1",
    "addr:postcode":"1111",
    "addr:street":"Arent Krijtsstraat",
    "iso:country":"NL",
    "sg:address":"Arent Krijtsstraat 1",
    "sg:city":"Diemen",
    "sg:orig_category":"Begrafenisondernemers",
    "sg:phone":"+31 20 398 6800",
    "sg:postcode":"1111 AG",
    "sg:province":"Noord-Holland",
    "wof:name":"Cvn Crematoria Nederland Bv",
    "wof:placetype":"venue"
},
  "geometry": {"coordinates":[4.955117,52.339809],"type":"Point"}
}