{
  "type": "Feature",
  "properties": {
    "addr:full":"Akkerweg 79 Moerkapelle Zuid-Holland 2751 CJ",
    "addr:housenumber":"79",
    "addr:postcode":"2751 cj",
    "addr:street":"Akkerweg",
    "iso:country":"NL",
    "sg:address":"Akkerweg 79",
    "sg:city":"Moerkapelle",
    "sg:orig_category":"Elektriciens",
    "sg:phone":"+31 79 593 6191",
    "sg:postcode":"2751 CJ",
    "sg:province":"Zuid-Holland",
    "wof:name":"Cock Hoogendoorn Elektro & Besturingstechn",
    "wof:placetype":"venue"
},
  "geometry": {"coordinates":[4.570406,52.045155],"type":"Point"}
}