{
  "type": "Feature",
  "properties": {
    "addr:full":"Schaapswg 36 Ede Gld Gelderland 6713 BD",
    "addr:housenumber":"36",
    "addr:postcode":"6713 bd",
    "addr:street":"Schaapswg;Gld Gelderland",
    "iso:country":"NL",
    "sg:address":"Schaapswg 36",
    "sg:city":"Ede Gld",
    "sg:classifiers":[
        {
            "category":"Retail",
            "subcategory":"Auto Repair",
            "type":"Services"
        }
    ],
    "sg:phone":"+31 318 614 864",
    "sg:postcode":"6713 BD",
    "sg:province":"Gelderland",
    "sg:tags":[
        "garage"
    ],
    "wof:name":"Vreugdenhil, J",
    "wof:placetype":"venue"
},
  "geometry": {"coordinates":[5.661635,52.042866],"type":"Point"}
}