{
  "type": "Feature",
  "properties": {
    "addr:full":"Duizendblad 3 Ijsselstein Utrecht 3401 LX",
    "addr:housenumber":"3",
    "addr:postcode":"3401 lx",
    "addr:street":"Duizendblad",
    "iso:country":"NL",
    "sg:address":"Duizendblad 3",
    "sg:city":"Ijsselstein",
    "sg:orig_category":"Verzekeringen - Verzekeringskantoren",
    "sg:phone":"+31 30 688 4174",
    "sg:postcode":"3401 LX",
    "sg:province":"Utrecht",
    "wof:name":"Barlo, P",
    "wof:placetype":"venue"
},
  "geometry": {"coordinates":[5.032963,52.020493],"type":"Point"}
}