{
  "type": "Feature",
  "properties": {
    "addr:full":"Bilderdykstr 141 Amsterdam Noord-Holland 1053 KN",
    "addr:housenumber":"141",
    "addr:postcode":"1053 kn",
    "iso:country":"NL",
    "sg:address":"Bilderdykstr 141",
    "sg:city":"Amsterdam",
    "sg:orig_category":"Verlichting",
    "sg:phone":"+31 20 683 2960",
    "sg:postcode":"1053 KN",
    "sg:province":"Noord-Holland",
    "wof:name":"Nolting",
    "wof:placetype":"venue"
},
  "geometry": {"coordinates":[4.871718,52.368134],"type":"Point"}
}