{
  "type": "Feature",
  "properties": {
    "addr:full":"Kolverniershof/Lange Kerkstraat Goes Zeeland 4461 HC",
    "addr:postcode":"4461 hc",
    "addr:street":"Kerkstraat",
    "iso:country":"NL",
    "sg:address":"Kolverniershof/Lange Kerkstraat",
    "sg:city":"Goes",
    "sg:orig_category":"Winkelcentra",
    "sg:phone":"+31 141",
    "sg:postcode":"4461 HC",
    "sg:province":"Zeeland",
    "wof:name":"Goes Winkelcentrum",
    "wof:placetype":"venue"
},
  "geometry": {"coordinates":[-83.9141693115,39.7688331604],"type":"Point"}
}