{
  "type": "Feature",
  "properties": {
    "addr:full":"Balkweiterhoek 22 Zwaagdijk Noord-Holland 1685 PK",
    "addr:housenumber":"22",
    "addr:postcode":"1685 pk",
    "addr:street":"Balkweiterhoek",
    "iso:country":"NL",
    "sg:address":"Balkweiterhoek 22",
    "sg:city":"Zwaagdijk",
    "sg:orig_category":"Autorijscholen",
    "sg:phone":"+31 229 572 178",
    "sg:postcode":"1685 PK",
    "sg:province":"Noord-Holland",
    "wof:name":"Aalten, Van",
    "wof:placetype":"venue"
},
  "geometry": {"coordinates":[5.05716,52.675896],"type":"Point"}
}