{
  "type": "Feature",
  "properties": {
    "addr:full":"Rietdekkerswg 16 Woerden Utrecht 3449 JC",
    "addr:housenumber":"16",
    "addr:postcode":"3449 jc",
    "addr:street":"Rietdekkerswg",
    "iso:country":"NL",
    "sg:address":"Rietdekkerswg 16",
    "sg:city":"Woerden",
    "sg:orig_category":"Verzekeringen - Verzekeringskantoren",
    "sg:phone":"+31 348 430 010",
    "sg:postcode":"3449 JC",
    "sg:province":"Utrecht",
    "sg:website":"http://www.vekoadvies.nl",
    "wof:name":"Veko",
    "wof:placetype":"venue"
},
  "geometry": {"coordinates":[4.855041,52.084881],"type":"Point"}
}