{
  "type": "Feature",
  "properties": {
    "addr:full":"Langeboomsestraat 4 Vethuizen Gelderland 7046 AA",
    "addr:housenumber":"4",
    "addr:postcode":"7046 aa",
    "addr:street":"Langeboomsestraat;Gelderland",
    "iso:country":"NL",
    "sg:address":"Langeboomsestraat 4",
    "sg:city":"Vethuizen",
    "sg:orig_category":"Diverse Bedrijfsinstallaties Gh",
    "sg:phone":"+31 314 653 045",
    "sg:postcode":"7046 AA",
    "sg:province":"Gelderland",
    "wof:name":"Matec",
    "wof:placetype":"venue"
},
  "geometry": {"coordinates":[6.297569,51.909592],"type":"Point"}
}