{
  "type": "Feature",
  "properties": {
    "addr:full":"Dorpsstraat 114 Gouderak Zuid-Holland 2831 AT",
    "addr:housenumber":"114",
    "addr:postcode":"2831",
    "addr:street":"Dorpsstraat",
    "iso:country":"NL",
    "sg:address":"Dorpsstraat 114",
    "sg:city":"Gouderak",
    "sg:orig_category":"Levende Dieren Gh",
    "sg:phone":"+31 182 374 190",
    "sg:postcode":"2831 AT",
    "sg:province":"Zuid-Holland",
    "wof:name":"Deve Foods Bv",
    "wof:placetype":"venue"
},
  "geometry": {"coordinates":[4.676182,51.986137],"type":"Point"}
}