{
  "type": "Feature",
  "properties": {
    "addr:full":"J V Scorelstr 62 Utrecht Utrecht 3583 CR",
    "addr:housenumber":"62",
    "addr:postcode":"3583 cr",
    "addr:street":"J;Scorelstr",
    "iso:country":"NL",
    "sg:address":"J V Scorelstr 62",
    "sg:city":"Utrecht",
    "sg:classifiers":[
        {
            "category":"Food & Beverages",
            "subcategory":"Bakery",
            "type":"Retail Goods"
        }
    ],
    "sg:phone":"+31 30 254 5775",
    "sg:postcode":"3583 CR",
    "sg:province":"Utrecht",
    "sg:tags":[
        "pizza"
    ],
    "wof:name":"Forno, Il",
    "wof:placetype":"venue"
},
  "geometry": {"coordinates":[5.14371,52.086601],"type":"Point"}
}