{
  "type": "Feature",
  "properties": {
    "addr:full":"Montaubanstraat 251 Zeist Utrecht 3701 HN",
    "addr:housenumber":"251",
    "addr:postcode":"3701 hn",
    "addr:street":"Montaubanstraat",
    "iso:country":"NL",
    "sg:address":"Montaubanstraat 251",
    "sg:city":"Zeist",
    "sg:classifiers":[
        {
            "category":"Fast Food",
            "type":"Food & Drink"
        }
    ],
    "sg:phone":"+31 30 692 1707",
    "sg:postcode":"3701 HN",
    "sg:province":"Utrecht",
    "sg:tags":[
        "afhaal",
        "restaurant"
    ],
    "sg:website":"http://www.alcapones.nl",
    "wof:name":"Al Capone`S",
    "wof:placetype":"venue"
},
  "geometry": {"coordinates":[5.238516,52.086025],"type":"Point"}
}