{
  "type": "Feature",
  "properties": {
    "iso:country":"NL",
    "sg:address":"Statenlaan 21",
    "sg:city":"Bussum",
    "sg:orig_category":"Public Relationbureaus",
    "sg:phone":"+31 35 693 1479",
    "sg:postcode":"1405 EV",
    "sg:province":"North Holland",
    "wof:name":"Drs. W.A.M. Van Waes",
    "wof:placetype":"venue"
},
  "geometry": {"coordinates":[5.145728,52.273823],"type":"Point"}
}