{
  "type": "Feature",
  "properties": {
    "addr:full":"Pr Julianaln 84 Rotterdam South Holland 3062 DL",
    "addr:housenumber":"84",
    "addr:postcode":"3062 dl",
    "iso:country":"NL",
    "sg:address":"Pr Julianaln 84",
    "sg:city":"Rotterdam",
    "sg:orig_category":"Artsen - Huisartsen",
    "sg:phone":"+31 10 452 7878",
    "sg:postcode":"3062 DL",
    "sg:province":"South Holland",
    "wof:name":"Jansen En C G M Jansen-Van Amen, C J",
    "wof:placetype":"venue"
},
  "geometry": {"coordinates":[4.515273,51.925636],"type":"Point"}
}