{
  "type": "Feature",
  "properties": {
    "addr:full":"Hoofdstr 63 Kaatsheuvel Noord-Brabant 5171 DK",
    "addr:housenumber":"63",
    "addr:postcode":"5171 dk",
    "addr:street":"Hoofdstr",
    "iso:country":"NL",
    "sg:address":"Hoofdstr 63",
    "sg:city":"Kaatsheuvel",
    "sg:orig_category":"Juweliers",
    "sg:phone":"+31 416 277 913",
    "sg:postcode":"5171 DK",
    "sg:province":"Noord-Brabant",
    "wof:name":"Grinsven Juwelier G Van",
    "wof:placetype":"venue"
},
  "geometry": {"coordinates":[5.034054,51.661495],"type":"Point"}
}