{
  "type": "Feature",
  "properties": {
    "addr:full":"Wiemanstr 25 Emst Gelderland 8166 GA",
    "addr:housenumber":"25",
    "addr:postcode":"8166 ga",
    "addr:street":"Wiemanstr;Gelderland",
    "iso:country":"NL",
    "sg:address":"Wiemanstr 25",
    "sg:city":"Emst",
    "sg:orig_category":"Loonbedrijven",
    "sg:phone":"+31 578 614 469",
    "sg:postcode":"8166 GA",
    "sg:province":"Gelderland",
    "wof:name":"Foks, G",
    "wof:placetype":"venue"
},
  "geometry": {"coordinates":[5.997288,52.325035],"type":"Point"}
}