{
  "type": "Feature",
  "properties": {
    "iso:country":"NL",
    "sg:address":"Buizerdstr 13",
    "sg:city":"Leerdam",
    "sg:orig_category":"Adviesbureaus Bouwkosten",
    "sg:phone":"+31 345 633 878",
    "sg:postcode":"4143 BA",
    "sg:province":"Zuid-Holland",
    "wof:name":"Twigt",
    "wof:placetype":"venue"
},
  "geometry": {"coordinates":[5.08678,51.897137],"type":"Point"}
}