{
  "type": "Feature",
  "properties": {
    "addr:full":"De Stuwdijk 4 Hardenberg Overijssel 7772 AW",
    "addr:housenumber":"4",
    "addr:postcode":"7772 aw",
    "addr:street":"De Stuwdijk",
    "iso:country":"NL",
    "sg:address":"De Stuwdijk 4",
    "sg:city":"Hardenberg",
    "sg:orig_category":"Woningbouwverenigingen",
    "sg:phone":"+31 523 261 385",
    "sg:postcode":"7772 AW",
    "sg:province":"Overijssel",
    "wof:name":"Woningstichting Beter Wonen",
    "wof:placetype":"venue"
},
  "geometry": {"coordinates":[6.6178398132,52.5684051514],"type":"Point"}
}