{
  "type": "Feature",
  "properties": {
    "iso:country":"NL",
    "sg:address":"Noorderweg 162",
    "sg:city":"Wijdewormer",
    "sg:classifiers":[
        {
            "category":"Education",
            "subcategory":"Preschool",
            "type":"Public Place"
        }
    ],
    "sg:phone":"+31 299 425 477",
    "sg:postcode":"1456 NP",
    "sg:province":"North Holland",
    "sg:tags":[
        "kleuteronderwijs",
        "basis-"
    ],
    "wof:name":"Openbare Basisschool Wijdewormer",
    "wof:placetype":"venue"
},
  "geometry": {"coordinates":[4.917302,52.507652],"type":"Point"}
}