{
  "type": "Feature",
  "properties": {
    "iso:country":"NL",
    "sg:address":"Noordplein 249",
    "sg:city":"Rotterdam",
    "sg:orig_category":"Verhuisdiensten",
    "sg:phone":"+31 10 466 3657",
    "sg:postcode":"3035 EE",
    "sg:province":"Zuid-Holland",
    "wof:name":"Jan Buijs Verhuizingen Bv",
    "wof:placetype":"venue"
},
  "geometry": {"coordinates":[4.482635,51.929844],"type":"Point"}
}