{
  "type": "Feature",
  "properties": {
    "iso:country":"NL",
    "sg:address":"Koppeldk 35",
    "sg:city":"Abcoude",
    "sg:orig_category":"Parketvloeren",
    "sg:phone":"+31 294 284 156",
    "sg:postcode":"1391 CX",
    "sg:province":"North Holland",
    "wof:name":"Albers Abcoude Parket",
    "wof:placetype":"venue"
},
  "geometry": {"coordinates":[4.974741,52.268097],"type":"Point"}
}