{
  "type": "Feature",
  "properties": {
    "addr:full":"Brugakker 6527 Zeist Utrecht 3704 RK",
    "addr:housenumber":"6527",
    "addr:postcode":"3704 rk",
    "addr:street":"Brugakker",
    "iso:country":"NL",
    "sg:address":"Brugakker 6527",
    "sg:city":"Zeist",
    "sg:orig_category":"Public Relationbureaus",
    "sg:phone":"+31 30 699 1863",
    "sg:postcode":"3704 RK",
    "sg:province":"Utrecht",
    "wof:name":"Thijssen Public Relations Bv",
    "wof:placetype":"venue"
},
  "geometry": {"coordinates":[5.206235,52.084583],"type":"Point"}
}