{
  "type": "Feature",
  "properties": {
    "iso:country":"NL",
    "sg:address":"Zwettestr 1",
    "sg:city":"Leeuwarden",
    "sg:classifiers":[
        {
            "category":"Retail",
            "subcategory":"Auto Repair",
            "type":"Services"
        }
    ],
    "sg:phone":"+31 58 213 1275",
    "sg:postcode":"8912 AH",
    "sg:province":"Friesland",
    "sg:tags":[
        "garage"
    ],
    "wof:name":"John Silvius, Vakgarage",
    "wof:placetype":"venue"
},
  "geometry": {"coordinates":[5.770239,53.196686],"type":"Point"}
}