{
  "type": "Feature",
  "properties": {
    "iso:country":"NL",
    "sg:address":"Van Goghlaan 162",
    "sg:city":"Roosendaal",
    "sg:orig_category":"Boekhouders",
    "sg:phone":"+31 165 549 178",
    "sg:postcode":"4703 JE",
    "sg:province":"North Brabant",
    "wof:name":"Administratie Belastingadviesburo Testers",
    "wof:placetype":"venue"
},
  "geometry": {"coordinates":[4.445562,51.539288],"type":"Point"}
}