{
  "type": "Feature",
  "properties": {
    "addr:full":"Jacob Ruijsdaellaan 9 Schagen Noord-Holland 1741 KT",
    "addr:housenumber":"9",
    "addr:postcode":"1741 kt",
    "addr:street":"Jacob Ruijsdaellaan",
    "iso:country":"NL",
    "sg:address":"Jacob Ruijsdaellaan 9",
    "sg:city":"Schagen",
    "sg:orig_category":"Kappers",
    "sg:phone":"+31 224 218 064",
    "sg:postcode":"1741 KT",
    "sg:province":"Noord-Holland",
    "wof:name":"Papillot Haarverzorging",
    "wof:placetype":"venue"
},
  "geometry": {"coordinates":[4.802691,52.791622],"type":"Point"}
}