{
  "type": "Feature",
  "properties": {
    "addr:full":"Zuidendk 169 Dordrecht Zuid-Holland 3314 CT",
    "addr:housenumber":"169",
    "addr:postcode":"3314 ct",
    "iso:country":"NL",
    "sg:address":"Zuidendk 169",
    "sg:city":"Dordrecht",
    "sg:orig_category":"Koeriersdiensten",
    "sg:phone":"+31 78 618 2825",
    "sg:postcode":"3314 CT",
    "sg:province":"Zuid-Holland",
    "sg:website":"http://www.pekoerier.nl",
    "wof:name":"Pe Koerier",
    "wof:placetype":"venue"
},
  "geometry": {"coordinates":[4.656168,51.79702],"type":"Point"}
}