{
  "type": "Feature",
  "properties": {
    "addr:full":"Hooftstr 208 Alphen Aan Den Ryn Zuid-Holland 2406 GR",
    "addr:housenumber":"208",
    "addr:postcode":"2406",
    "addr:street":"Aan Den Ryn",
    "iso:country":"NL",
    "sg:address":"Hooftstr 208",
    "sg:city":"Alphen Aan Den Ryn",
    "sg:orig_category":"Sportverenigingen En Ontspannings- Verenigingen",
    "sg:phone":"+31 172 470 840",
    "sg:postcode":"2406 GR",
    "sg:province":"Zuid-Holland",
    "wof:name":"Alphense Schaakcl",
    "wof:placetype":"venue"
},
  "geometry": {"coordinates":[4.663789,52.137577],"type":"Point"}
}