{
  "type": "Feature",
  "properties": {
    "iso:country":"NL",
    "sg:address":"Edisonstr 2",
    "sg:city":"Dedemsvaart",
    "sg:orig_category":"Reclame",
    "sg:phone":"+31 523 628 911",
    "sg:postcode":"7701 BT",
    "sg:province":"Overijssel",
    "sg:website":"http://www.marquage.nl",
    "wof:name":"Marquage Bergslot Bv",
    "wof:placetype":"venue"
},
  "geometry": {"coordinates":[6.483775,52.604301],"type":"Point"}
}