{
  "type": "Feature",
  "properties": {
    "addr:full":"Schoffelstr 32 Alkmaar North Holland 1825 MB",
    "addr:housenumber":"32",
    "addr:postcode":"1825 mb",
    "addr:street":"Schoffelstr",
    "iso:country":"NL",
    "sg:address":"Schoffelstr 32",
    "sg:city":"Alkmaar",
    "sg:orig_category":"Adviesbureaus Bouwkunde",
    "sg:phone":"+31 72 561 9095",
    "sg:postcode":"1825 MB",
    "sg:province":"North Holland",
    "wof:name":"Keijer, W S J M",
    "wof:placetype":"venue"
},
  "geometry": {"coordinates":[4.759235,52.663685],"type":"Point"}
}