{
  "type": "Feature",
  "properties": {
    "addr:full":"Marsstr 11 Culemborg Gelderland 4105 JK",
    "addr:housenumber":"11",
    "addr:postcode":"4105 jk",
    "addr:street":"Marsstr;Gelderland",
    "iso:country":"NL",
    "sg:address":"Marsstr 11",
    "sg:city":"Culemborg",
    "sg:orig_category":"Leesportefeuilles",
    "sg:phone":"+31 345 510 204",
    "sg:postcode":"4105 JK",
    "sg:province":"Gelderland",
    "wof:name":"Sales Inc",
    "wof:placetype":"venue"
},
  "geometry": {"coordinates":[5.206746,51.945129],"type":"Point"}
}