{
  "type": "Feature",
  "properties": {
    "iso:country":"NL",
    "sg:address":"A De Kompln 4-10",
    "sg:city":"Amsterdam Zuidoost",
    "sg:orig_category":"Mobiele- En Autotelefoons",
    "sg:phone":"+31 20 451 0423",
    "sg:postcode":"1102 DR",
    "sg:province":"Noord-Holland",
    "wof:name":"Mobi Shop",
    "wof:placetype":"venue"
},
  "geometry": {"coordinates":[4.957479,52.316833],"type":"Point"}
}