{
  "type": "Feature",
  "properties": {
    "addr:full":"Pk Hoornwyck 36 Ryswyk Zh Zuid-Holland 2289 CZ",
    "addr:housenumber":"36",
    "addr:postcode":"2289",
    "addr:street":"Ryswyk",
    "iso:country":"NL",
    "sg:address":"Pk Hoornwyck 36",
    "sg:city":"Ryswyk Zh",
    "sg:orig_category":"Loopbaanbegeleiding",
    "sg:phone":"+31 70 415 9248",
    "sg:postcode":"2289 CZ",
    "sg:province":"Zuid-Holland",
    "sg:website":"http://www.loopbaangeluk.nl",
    "wof:name":"Neven Loopbaanmanagement Bv",
    "wof:placetype":"venue"
},
  "geometry": {"coordinates":[4.32436,52.037251],"type":"Point"}
}