{
  "type": "Feature",
  "properties": {
    "addr:full":"Vendelstr 47 Liempde Noord-Brabant 5298 CX",
    "addr:housenumber":"47",
    "addr:postcode":"5298 cx",
    "addr:street":"Vendelstr",
    "iso:country":"NL",
    "sg:address":"Vendelstr 47",
    "sg:city":"Liempde",
    "sg:orig_category":"Schilders",
    "sg:phone":"+31 411 631 549",
    "sg:postcode":"5298 CX",
    "sg:province":"Noord-Brabant",
    "wof:name":"Abeelen, Schilderwerken Van",
    "wof:placetype":"venue"
},
  "geometry": {"coordinates":[5.379093,51.571278],"type":"Point"}
}