{
  "type": "Feature",
  "properties": {
    "iso:country":"NL",
    "sg:address":"Grotestraat 7",
    "sg:city":"Ede Gld",
    "sg:orig_category":"Juweliers",
    "sg:phone":"+31 318 693 069",
    "sg:postcode":"6711 AH",
    "sg:province":"Gelderland",
    "wof:name":"Kreek Juwelier Bv",
    "wof:placetype":"venue"
},
  "geometry": {"coordinates":[5.669735,52.044109],"type":"Point"}
}