{
  "type": "Feature",
  "properties": {
    "addr:full":"Waterlandlaan 39 Purmerend Noord-Holland 1441 RS",
    "addr:housenumber":"39",
    "addr:postcode":"1441 rs",
    "addr:street":"Waterlandlaan",
    "iso:country":"NL",
    "sg:address":"Waterlandlaan 39",
    "sg:city":"Purmerend",
    "sg:orig_category":"Boekhouders",
    "sg:phone":"+31 299 438 428",
    "sg:postcode":"1441 RS",
    "sg:province":"Noord-Holland",
    "wof:name":"Administratiekantoor Vreeman",
    "wof:placetype":"venue"
},
  "geometry": {"coordinates":[4.958282,52.50494],"type":"Point"}
}