{
  "type": "Feature",
  "properties": {
    "iso:country":"NL",
    "sg:address":"Stationsstraat 22",
    "sg:city":"Waalwijk",
    "sg:orig_category":"Herenmodezaken",
    "sg:phone":"+31 416 335 512",
    "sg:postcode":"5141 GE",
    "sg:province":"Noord-Brabant",
    "wof:name":"Van Dijk Herenmode Bv",
    "wof:placetype":"venue"
},
  "geometry": {"coordinates":[5.066675,51.688908],"type":"Point"}
}