{
  "type": "Feature",
  "properties": {
    "addr:full":"Overstichtln 2 Deventer NL.08 7414 AP",
    "addr:housenumber":"2;nl.08",
    "addr:postcode":"7414 ap",
    "addr:street":"Overstichtln",
    "iso:country":"NL",
    "sg:address":"Overstichtln 2",
    "sg:city":"Deventer",
    "sg:orig_category":"Woningbouw- Verenigingen En -Stichtingen",
    "sg:phone":"+31 570 858 610",
    "sg:postcode":"7414 AP",
    "sg:province":"NL.08",
    "sg:website":"http://www.woonunie.nl",
    "wof:name":"Woonunie",
    "wof:placetype":"venue"
},
  "geometry": {"coordinates":[6.1509289742,52.2713661194],"type":"Point"}
}