{
  "type": "Feature",
  "properties": {
    "iso:country":"NL",
    "sg:address":"J A Wentelstr 6",
    "sg:city":"Den Helder",
    "sg:orig_category":"Orthopedische Artikelen",
    "sg:phone":"+31 223 633 477",
    "sg:postcode":"1785 HH",
    "sg:province":"Noord-Holland",
    "wof:name":"Pedifit",
    "wof:placetype":"venue"
},
  "geometry": {"coordinates":[4.7675619125,52.9317131042],"type":"Point"}
}