{
  "type": "Feature",
  "properties": {
    "iso:country":"NL",
    "sg:address":"Plasticslaan 1",
    "sg:city":"Bergen Op Zoom",
    "sg:orig_category":"Pijpleidingen - Installatie En Onderhoud",
    "sg:phone":"+31 164 251 891",
    "sg:postcode":"4612 PX",
    "sg:province":"North Brabant",
    "wof:name":"Rmh Bv",
    "wof:placetype":"venue"
},
  "geometry": {"coordinates":[4.253059,51.507637],"type":"Point"}
}