{
  "type": "Feature",
  "properties": {
    "iso:country":"NL",
    "sg:address":"Julianastraat 10",
    "sg:city":"Moerkapelle",
    "sg:orig_category":"Pompen And Compressoren Fab",
    "sg:phone":"+31 79 593 1329",
    "sg:postcode":"2751 GD",
    "sg:province":"South Holland",
    "wof:name":"Hertog Polderbemalingen Bv",
    "wof:placetype":"venue"
},
  "geometry": {"coordinates":[4.57916,52.042995],"type":"Point"}
}