{
  "type": "Feature",
  "properties": {
    "addr:full":"Wollefoppenwg 17 Rotterdam Zuid-Holland 3059 LG",
    "addr:housenumber":"17",
    "addr:postcode":"3059 lg",
    "addr:street":"Wollefoppenwg",
    "iso:country":"NL",
    "sg:address":"Wollefoppenwg 17",
    "sg:city":"Rotterdam",
    "sg:orig_category":"Boekhandels",
    "sg:phone":"+31 180 313 643",
    "sg:postcode":"3059 LG",
    "sg:province":"Zuid-Holland",
    "wof:name":"Media Expresse",
    "wof:placetype":"venue"
},
  "geometry": {"coordinates":[4.59524,51.981709],"type":"Point"}
}