{
  "type": "Feature",
  "properties": {
    "addr:full":"Dominepad 6B Hoogeloon Noord-Brabant 5528 NC",
    "addr:housenumber":"6b",
    "addr:postcode":"5528 nc",
    "addr:street":"Dominepad",
    "iso:country":"NL",
    "sg:address":"Dominepad 6B",
    "sg:city":"Hoogeloon",
    "sg:orig_category":"Landbouwmachines Gh",
    "sg:phone":"+31 497 682 646",
    "sg:postcode":"5528 NC",
    "sg:province":"Noord-Brabant",
    "wof:name":"Agrarische Bedrijfsuitrusting Abemec Bv",
    "wof:placetype":"venue"
},
  "geometry": {"coordinates":[5.278252,51.381413],"type":"Point"}
}