{
  "type": "Feature",
  "properties": {
    "addr:full":"Van Woustraat 154 Amsterdam Noord-Holland 1073 LW",
    "addr:housenumber":"154",
    "addr:postcode":"1073 lw",
    "addr:street":"Van Woustraat",
    "iso:country":"NL",
    "sg:address":"Van Woustraat 154",
    "sg:city":"Amsterdam",
    "sg:classifiers":[
        {
            "category":"Communications",
            "subcategory":"Television Station",
            "type":"Services"
        }
    ],
    "sg:phone":"+31 20 679 9045",
    "sg:postcode":"1073 LW",
    "sg:province":"Noord-Holland",
    "sg:tags":[
        "video",
        "audio",
        "verhuur"
    ],
    "wof:name":"Videoland Van Wou",
    "wof:placetype":"venue"
},
  "geometry": {"coordinates":[4.902744,52.352562],"type":"Point"}
}