{
  "type": "Feature",
  "properties": {
    "addr:full":"Raadhuisplein 7 Arcen Limburg 5944 AH",
    "addr:housenumber":"7",
    "addr:postcode":"5944 ah",
    "addr:street":"Raadhuisplein",
    "iso:country":"NL",
    "sg:address":"Raadhuisplein 7",
    "sg:city":"Arcen",
    "sg:orig_category":"Kappers",
    "sg:phone":"+31 77 473 1781",
    "sg:postcode":"5944 AH",
    "sg:province":"Limburg",
    "wof:name":"J. Arts-Verhaegh",
    "wof:placetype":"venue"
},
  "geometry": {"coordinates":[6.179599762,51.4738235474],"type":"Point"}
}