{
  "type": "Feature",
  "properties": {
    "iso:country":"NL",
    "sg:address":"Goede Hoopstr 40B",
    "sg:city":"Rotterdam",
    "sg:orig_category":"Kappersbenodigdheden",
    "sg:phone":"+31 10 485 6604",
    "sg:postcode":"3072 BC",
    "sg:province":"South Holland",
    "wof:name":"Gondal",
    "wof:placetype":"venue"
},
  "geometry": {"coordinates":[4.49729,51.898193],"type":"Point"}
}