{
  "type": "Feature",
  "properties": {
    "iso:country":"NL",
    "sg:address":"Langelermaatweg 41",
    "sg:city":"Hengelo Ov",
    "sg:orig_category":"Meubelzaken, Woning- And Keukeninrichting",
    "sg:phone":"+31 74 291 4912",
    "sg:postcode":"7553 JE",
    "sg:province":"NL.08",
    "wof:name":"Vof Valkenaar",
    "wof:placetype":"venue"
},
  "geometry": {"coordinates":[6.793248,52.258682],"type":"Point"}
}