{
  "type": "Feature",
  "properties": {
    "addr:full":"Regentesseln 6 Appingedam Groningen 9901 HM",
    "addr:housenumber":"6",
    "addr:postcode":"9901 hm",
    "addr:street":"Regentesseln",
    "iso:country":"NL",
    "sg:address":"Regentesseln 6",
    "sg:city":"Appingedam",
    "sg:orig_category":"Adviesbureaus Bedrijfsorganisatie",
    "sg:phone":"+31 596 624 094",
    "sg:postcode":"9901 HM",
    "sg:province":"Groningen",
    "wof:name":"Zwart",
    "wof:placetype":"venue"
},
  "geometry": {"coordinates":[6.836911,53.320995],"type":"Point"}
}