{
  "type": "Feature",
  "properties": {
    "iso:country":"NL",
    "sg:address":"Goeman Borgesiuslaan 4",
    "sg:city":"Sneek",
    "sg:classifiers":[
        {
            "category":"Travel",
            "subcategory":"Hotels & Motels",
            "type":"Entertainment"
        }
    ],
    "sg:phone":"+31 515 417 742",
    "sg:postcode":"8603 BJ",
    "sg:province":"Friesland",
    "wof:name":"Swettestate",
    "wof:placetype":"venue"
},
  "geometry": {"coordinates":[5.666509,53.039871],"type":"Point"}
}