{
  "type": "Feature",
  "properties": {
    "addr:full":"Hoofdweg 303 Amsterdam Noord-Holland 1057 CZ",
    "addr:housenumber":"303;1057",
    "addr:street":"Hoofdweg",
    "iso:country":"NL",
    "sg:address":"Hoofdweg 303",
    "sg:city":"Amsterdam",
    "sg:orig_category":"Kappers",
    "sg:phone":"+31 20 618 0789",
    "sg:postcode":"1057 CZ",
    "sg:province":"Noord-Holland",
    "wof:name":"Kapsalon Greta",
    "wof:placetype":"venue"
},
  "geometry": {"coordinates":[4.8513889313,52.3686447144],"type":"Point"}
}