{
  "type": "Feature",
  "properties": {
    "addr:full":"Zocherstraat 50 Amsterdam Noord-Holland 1054 LZ",
    "addr:housenumber":"50",
    "addr:postcode":"1054 lz",
    "addr:street":"Zocherstraat",
    "iso:country":"NL",
    "sg:address":"Zocherstraat 50",
    "sg:city":"Amsterdam",
    "sg:orig_category":"Vertaal- And Tolkenbureaus",
    "sg:phone":"+31 20 689 2040",
    "sg:postcode":"1054 LZ",
    "sg:province":"Noord-Holland",
    "wof:name":"Marjo Severs Productions",
    "wof:placetype":"venue"
},
  "geometry": {"coordinates":[4.855603,52.356964],"type":"Point"}
}