{
  "type": "Feature",
  "properties": {
    "addr:full":"Zwichtstr 4 Wolvega Provincie Friesland 8471 HM",
    "addr:housenumber":"4",
    "addr:postcode":"8471 hm",
    "addr:street":"Zwichtstr;Provincie Friesland",
    "iso:country":"NL",
    "sg:address":"Zwichtstr 4",
    "sg:city":"Wolvega",
    "sg:orig_category":"Adviesbureaus Bedrijfsorganisatie",
    "sg:phone":"+31 561 614 871",
    "sg:postcode":"8471 HM",
    "sg:province":"Provincie Friesland",
    "wof:name":"Maatman Bv",
    "wof:placetype":"venue"
},
  "geometry": {"coordinates":[5.989568,52.871964],"type":"Point"}
}