{
  "type": "Feature",
  "properties": {
    "addr:full":"Meijersweg 9 Hengelo Ov NL.08 7553 AX",
    "addr:housenumber":"9",
    "addr:postcode":"7553 ax",
    "addr:street":"Meijersweg;Ov",
    "iso:country":"NL",
    "sg:address":"Meijersweg 9",
    "sg:city":"Hengelo Ov",
    "sg:orig_category":"Meubelzaken, Woning- And Keukeninrichting",
    "sg:phone":"+31 74 242 2614",
    "sg:postcode":"7553 AX",
    "sg:province":"NL.08",
    "wof:name":"P. Van Der Berg",
    "wof:placetype":"venue"
},
  "geometry": {"coordinates":[6.783834,52.256222],"type":"Point"}
}