{
  "type": "Feature",
  "properties": {
    "iso:country":"NL",
    "sg:address":"Willem Alexanderlaan 1",
    "sg:city":"Harmelen",
    "sg:orig_category":"Bibliotheken And Openbare Archieven",
    "sg:phone":"+31 348 443 145",
    "sg:postcode":"3481 VA",
    "sg:province":"Utrecht",
    "wof:name":"Openbare Bibliotheek",
    "wof:placetype":"venue"
},
  "geometry": {"coordinates":[4.963678,52.088062],"type":"Point"}
}