{
  "type": "Feature",
  "properties": {
    "addr:full":"Batterijlaan 18 Bussum North Holland 1402 SN",
    "addr:housenumber":"18",
    "addr:postcode":"1402 sn",
    "addr:street":"Batterijlaan",
    "iso:country":"NL",
    "sg:address":"Batterijlaan 18",
    "sg:city":"Bussum",
    "sg:orig_category":"Loodgieterswerk, Verwarming And Sanitaire Installaties",
    "sg:phone":"+31 35 693 7150",
    "sg:postcode":"1402 SN",
    "sg:province":"North Holland",
    "wof:name":"Gasservice Sigo",
    "wof:placetype":"venue"
},
  "geometry": {"coordinates":[5.172857,52.27335],"type":"Point"}
}