{
  "type": "Feature",
  "properties": {
    "addr:full":"Karveel 8 Oosterhout Nb Noord-Brabant 4902 CP",
    "addr:housenumber":"8",
    "addr:postcode":"4902 cp",
    "addr:street":"Karveel",
    "iso:country":"NL",
    "sg:address":"Karveel 8",
    "sg:city":"Oosterhout Nb",
    "sg:orig_category":"Adviesbureaus Economie",
    "sg:phone":"+31 162 425 085",
    "sg:postcode":"4902 CP",
    "sg:province":"Noord-Brabant",
    "wof:name":"Knispel & Co",
    "wof:placetype":"venue"
},
  "geometry": {"coordinates":[4.841909,51.641205],"type":"Point"}
}