{
  "type": "Feature",
  "properties": {
    "iso:country":"NL",
    "sg:address":"Liedeweg 37",
    "sg:city":"Haarlemmerliede",
    "sg:orig_category":"Loodgieterswerk, Verwarming And Sanitaire Installaties",
    "sg:phone":"+31 23 532 5513",
    "sg:postcode":"2065 AJ",
    "sg:province":"Noord-Holland",
    "wof:name":"Onderhouds Bedrijf Van Warmerdam",
    "wof:placetype":"venue"
},
  "geometry": {"coordinates":[4.689475,52.388603],"type":"Point"}
}