{
  "type": "Feature",
  "properties": {
    "addr:full":"Grt Wielen 113 Rotterdam Zuid-Holland 3068 PT",
    "addr:housenumber":"113",
    "addr:postcode":"3068 pt",
    "addr:street":"Grt Wielen",
    "iso:country":"NL",
    "sg:address":"Grt Wielen 113",
    "sg:city":"Rotterdam",
    "sg:orig_category":"Administratie- En Boekhoudkantoren",
    "sg:phone":"+31 10 420 1134",
    "sg:postcode":"3068 PT",
    "sg:province":"Zuid-Holland",
    "wof:name":"Abaco Int Bv",
    "wof:placetype":"venue"
},
  "geometry": {"coordinates":[4.577979,51.964268],"type":"Point"}
}