{
  "type": "Feature",
  "properties": {
    "iso:country":"NL",
    "sg:address":"Essenburgsingel 139",
    "sg:city":"Rotterdam",
    "sg:orig_category":"Opvangtehuizen",
    "sg:phone":"+31 10 477 6264",
    "sg:postcode":"3022 EM",
    "sg:province":"Zuid-Holland",
    "wof:name":"Somik",
    "wof:placetype":"venue"
},
  "geometry": {"coordinates":[4.4443001747,51.9207229614],"type":"Point"}
}