{
  "type": "Feature",
  "properties": {
    "addr:full":"Essenburgsingel 139 Rotterdam Zuid-Holland 3022 EM",
    "addr:housenumber":"139",
    "addr:postcode":"3022 em",
    "addr:street":"Essenburgsingel",
    "iso:country":"NL",
    "sg:address":"Essenburgsingel 139",
    "sg:city":"Rotterdam",
    "sg:orig_category":"Opvangtehuizen",
    "sg:phone":"+31 10 477 6264",
    "sg:postcode":"3022 EM",
    "sg:province":"Zuid-Holland",
    "wof:name":"Somik",
    "wof:placetype":"venue"
},
  "geometry": {"coordinates":[4.4443001747,51.9207229614],"type":"Point"}
}