{
  "type": "Feature",
  "properties": {
    "addr:full":"Bohrwg 38 Spykenisse Zuid-Holland 3208 KR",
    "addr:housenumber":"38",
    "addr:postcode":"3208 kr",
    "addr:street":"Bohrwg",
    "iso:country":"NL",
    "sg:address":"Bohrwg 38",
    "sg:city":"Spykenisse",
    "sg:orig_category":"Meubelen - Fabrieken En Groothandel",
    "sg:phone":"+31 181 610 635",
    "sg:postcode":"3208 KR",
    "sg:province":"Zuid-Holland",
    "wof:name":"Seuren Trading",
    "wof:placetype":"venue"
},
  "geometry": {"coordinates":[4.3029,51.84264],"type":"Point"}
}