{
  "type": "Feature",
  "properties": {
    "addr:full":"V Heekstr 15 Schiedam South Holland 3125 BN",
    "addr:housenumber":"15",
    "addr:postcode":"3125 bn",
    "iso:country":"NL",
    "sg:address":"V Heekstr 15",
    "sg:city":"Schiedam",
    "sg:orig_category":"Ongediertebestrijding En Ontsmetting",
    "sg:phone":"+31 10 631 5060",
    "sg:postcode":"3125 BN",
    "sg:province":"South Holland",
    "sg:website":"http://www.onsgroep.nl",
    "wof:name":"Irado",
    "wof:placetype":"venue"
},
  "geometry": {"coordinates":[4.40341,51.934971],"type":"Point"}
}