{
  "type": "Feature",
  "properties": {
    "addr:full":"Soeverein 57 Leiderdorp Zuid-Holland 2353 TP",
    "addr:housenumber":"57",
    "addr:postcode":"2353 tp",
    "addr:street":"Soeverein",
    "iso:country":"NL",
    "sg:address":"Soeverein 57",
    "sg:city":"Leiderdorp",
    "sg:orig_category":"Kappers",
    "sg:phone":"+31 71 542 3717",
    "sg:postcode":"2353 TP",
    "sg:province":"Zuid-Holland",
    "wof:name":"Meulen, M F W Van Der",
    "wof:placetype":"venue"
},
  "geometry": {"coordinates":[4.530576,52.163704],"type":"Point"}
}