{
  "type": "Feature",
  "properties": {
    "addr:full":"Korte Leidsedwarsstraat 74 Amsterdam Noord-Holland 1017 RD",
    "addr:housenumber":"74",
    "addr:postcode":"1017 rd",
    "addr:street":"Korte Leidsedwarsstraat",
    "iso:country":"NL",
    "sg:address":"Korte Leidsedwarsstraat 74",
    "sg:city":"Amsterdam",
    "sg:orig_category":"Kappers",
    "sg:phone":"+31 20 624 6881",
    "sg:postcode":"1017 RD",
    "sg:province":"Noord-Holland",
    "wof:name":"Cuts And Curls Hairstyling",
    "wof:placetype":"venue"
},
  "geometry": {"coordinates":[4.8840808868,52.363494873],"type":"Point"}
}