{
  "type": "Feature",
  "properties": {
    "addr:full":"Utrechtseweg 373 De Bilt Utrecht 3731 GB",
    "addr:housenumber":"373",
    "addr:postcode":"3731 gb",
    "addr:street":"Utrechtseweg",
    "iso:country":"NL",
    "sg:address":"Utrechtseweg 373",
    "sg:city":"De Bilt",
    "sg:orig_category":"Fotostudio'S And Fotografen",
    "sg:phone":"+31 30 220 4460",
    "sg:postcode":"3731 GB",
    "sg:province":"Utrecht",
    "wof:name":"L.G. Huiskes",
    "wof:placetype":"venue"
},
  "geometry": {"coordinates":[5.160227,52.097851],"type":"Point"}
}