{
  "type": "Feature",
  "properties": {
    "addr:full":"Industriewg Z 13 Westdorpe Zeeland 4554 LL",
    "addr:housenumber":"13",
    "addr:postcode":"4554 ll",
    "iso:country":"NL",
    "sg:address":"Industriewg Z 13",
    "sg:city":"Westdorpe",
    "sg:orig_category":"Kunstmest",
    "sg:phone":"+31 115 472 945",
    "sg:postcode":"4554 LL",
    "sg:province":"Zeeland",
    "wof:name":"Moor-Vlaeminck, Firma De",
    "wof:placetype":"venue"
},
  "geometry": {"coordinates":[3.871498,51.267574],"type":"Point"}
}