{
  "type": "Feature",
  "properties": {
    "iso:country":"NL",
    "sg:address":"Hortensiastraat 74",
    "sg:city":"Ridderkerk",
    "sg:orig_category":"Geluidsopnamen",
    "sg:phone":"+31 180 432 533",
    "sg:postcode":"2985 AK",
    "sg:province":"South Holland",
    "wof:name":"General Noise",
    "wof:placetype":"venue"
},
  "geometry": {"coordinates":[4.5965,51.862934],"type":"Point"}
}