{
  "type": "Feature",
  "properties": {
    "addr:full":"Beemstraat 100 Gameren Gelderland 5311 AE",
    "addr:housenumber":"100",
    "addr:postcode":"5311 ae",
    "addr:street":"Beemstraat;Gelderland",
    "iso:country":"NL",
    "sg:address":"Beemstraat 100",
    "sg:city":"Gameren",
    "sg:orig_category":"Goederenvervoer Over De Weg",
    "sg:phone":"+31 418 562 248",
    "sg:postcode":"5311 AE",
    "sg:province":"Gelderland",
    "wof:name":"Dinant Van Iterson Vof",
    "wof:placetype":"venue"
},
  "geometry": {"coordinates":[5.221597,51.806084],"type":"Point"}
}