{
  "type": "Feature",
  "properties": {
    "addr:full":"Groenedk 3 T Goy Utrecht 3997 MZ",
    "addr:housenumber":"3 t",
    "addr:postcode":"3997 mz",
    "addr:street":"Groenedk;Goy",
    "iso:country":"NL",
    "sg:address":"Groenedk 3",
    "sg:city":"T Goy",
    "sg:orig_category":"Kantoor- En Secretariaatsservice",
    "sg:phone":"+31 30 228 4680",
    "sg:postcode":"3997 MZ",
    "sg:province":"Utrecht",
    "wof:name":"Tos",
    "wof:placetype":"venue"
},
  "geometry": {"coordinates":[5.2114801407,52.0025787354],"type":"Point"}
}