{
  "type": "Feature",
  "properties": {
    "addr:full":"Prinsestraat 10 Enschede Overijssel 7513 AL",
    "addr:housenumber":"10",
    "addr:postcode":"7513 al",
    "addr:street":"Prinsestraat",
    "iso:country":"NL",
    "sg:address":"Prinsestraat 10",
    "sg:city":"Enschede",
    "sg:classifiers":[
        {
            "category":"Education",
            "subcategory":"Preschool",
            "type":"Public Place"
        }
    ],
    "sg:phone":"+31 53 431 9652",
    "sg:postcode":"7513 AL",
    "sg:province":"Overijssel",
    "sg:tags":[
        "kleuteronderwijs",
        "basis-"
    ],
    "wof:name":"Openbare Basisschool De Stadsweide",
    "wof:placetype":"venue"
},
  "geometry": {"coordinates":[6.886085,52.218979],"type":"Point"}
}