{
  "type": "Feature",
  "properties": {
    "addr:full":"Schoolstr 1/A St Philipsland Zeeland 4675 BL",
    "addr:housenumber":"1 / a",
    "addr:postcode":"4675 bl",
    "addr:street":"Schoolstr;St Philipsland",
    "iso:country":"NL",
    "sg:address":"Schoolstr 1/A",
    "sg:city":"St Philipsland",
    "sg:orig_category":"Postkantoren",
    "sg:phone":"+31 167 572 320",
    "sg:postcode":"4675 BL",
    "sg:province":"Zeeland",
    "sg:website":"http://www.postkantoor.nl",
    "wof:name":"Postkantoor",
    "wof:placetype":"venue"
},
  "geometry": {"coordinates":[4.166989,51.617294],"type":"Point"}
}