{
  "type": "Feature",
  "properties": {
    "iso:country":"NL",
    "sg:address":"Zirkoon 51",
    "sg:city":"Heerhugowaard",
    "sg:orig_category":"Orthopedagogen",
    "sg:phone":"+31 72 571 6601",
    "sg:postcode":"1703 CR",
    "sg:province":"Noord-Holland",
    "wof:name":"Gehem, Drs J P",
    "wof:placetype":"venue"
},
  "geometry": {"coordinates":[4.8210802078,52.659160614],"type":"Point"}
}