{
  "type": "Feature",
  "properties": {
    "iso:country":"NL",
    "sg:address":"Heereweg 40",
    "sg:city":"Castricum",
    "sg:orig_category":"Autokeuringen",
    "sg:phone":"+31 251 651 925",
    "sg:postcode":"1901 ME",
    "sg:province":"North Holland",
    "wof:name":"Fons Fakkeldij Autobedrijf",
    "wof:placetype":"venue"
},
  "geometry": {"coordinates":[4.654782,52.56459],"type":"Point"}
}