{
  "type": "Feature",
  "properties": {
    "addr:full":"Maasstr 37 Amsterdam Noord-Holland 1078 HC",
    "addr:housenumber":"37",
    "addr:postcode":"1078 hc",
    "addr:street":"Maasstr",
    "iso:country":"NL",
    "sg:address":"Maasstr 37",
    "sg:city":"Amsterdam",
    "sg:orig_category":"Huishoudelijke Apparaten En Artikelen",
    "sg:phone":"+31 20 675 0709",
    "sg:postcode":"1078 HC",
    "sg:province":"Noord-Holland",
    "wof:name":"Blokker Bv",
    "wof:placetype":"venue"
},
  "geometry": {"coordinates":[4.895212,52.346336],"type":"Point"}
}