{
  "type": "Feature",
  "properties": {
    "addr:full":"Polstr 72 Wyk En Aalburg Noord-Brabant 4261 BV",
    "addr:housenumber":"72",
    "addr:postcode":"4261 bv",
    "addr:street":"Polstr",
    "iso:country":"NL",
    "sg:address":"Polstr 72",
    "sg:city":"Wyk En Aalburg",
    "sg:orig_category":"Banden",
    "sg:phone":"+31 416 691 550",
    "sg:postcode":"4261 BV",
    "sg:province":"Noord-Brabant",
    "wof:name":"Altena Profile Tyre Center",
    "wof:placetype":"venue"
},
  "geometry": {"coordinates":[5.118166,51.748398],"type":"Point"}
}