{
  "type": "Feature",
  "properties": {
    "addr:full":"Dokter Pinxterplantsoen 61 Wervershoof North Holland 1693 EW",
    "addr:housenumber":"61",
    "addr:postcode":"1693 ew",
    "addr:street":"Dokter Pinxterplantsoen",
    "iso:country":"NL",
    "sg:address":"Dokter Pinxterplantsoen 61",
    "sg:city":"Wervershoof",
    "sg:orig_category":"Autokeuringen",
    "sg:phone":"+31 228 582 815",
    "sg:postcode":"1693 EW",
    "sg:province":"North Holland",
    "wof:name":"Huisman Import Export",
    "wof:placetype":"venue"
},
  "geometry": {"coordinates":[5.151381,52.730404],"type":"Point"}
}