{
  "type": "Feature",
  "properties": {
    "addr:full":"Salvatorplein 1 Arnhem Gelderland 6832 AB",
    "addr:housenumber":"1",
    "addr:postcode":"6832 ab",
    "addr:street":"Salvatorplein",
    "iso:country":"NL",
    "sg:address":"Salvatorplein 1",
    "sg:city":"Arnhem",
    "sg:orig_category":"Autokeuringen",
    "sg:phone":"+31 26 321 1177",
    "sg:postcode":"6832 AB",
    "sg:province":"Gelderland",
    "wof:name":"Th.A. Hegeman Bv",
    "wof:placetype":"venue"
},
  "geometry": {"coordinates":[5.906987,51.967815],"type":"Point"}
}