{
  "type": "Feature",
  "properties": {
    "iso:country":"NL",
    "sg:address":"Brusselseweg 241",
    "sg:city":"Maastricht",
    "sg:orig_category":"Film-, Tv- And Videoproductie",
    "sg:phone":"+31 43 347 4489",
    "sg:postcode":"6217 GV",
    "sg:province":"Limburg",
    "wof:name":"241 Productions",
    "wof:placetype":"venue"
},
  "geometry": {"coordinates":[5.671303,50.856991],"type":"Point"}
}