{
  "type": "Feature",
  "properties": {
    "addr:full":"Burg Elkhuizenln 57 Halsteren Noord-Brabant 4661 CJ",
    "addr:housenumber":"57",
    "addr:postcode":"4661 cj",
    "addr:street":"Burg",
    "iso:country":"NL",
    "sg:address":"Burg Elkhuizenln 57",
    "sg:city":"Halsteren",
    "sg:orig_category":"Artsen - Huisartsen",
    "sg:phone":"+31 164 682 858",
    "sg:postcode":"4661 CJ",
    "sg:province":"Noord-Brabant",
    "wof:name":"Leeuwen, M H Van",
    "wof:placetype":"venue"
},
  "geometry": {"coordinates":[4.271159,51.537884],"type":"Point"}
}