{
  "type": "Feature",
  "properties": {
    "addr:full":"Streekweg 68 Hoogkarspel Noord-Holland 1616 AL",
    "addr:housenumber":"68",
    "addr:postcode":"1616 al",
    "addr:street":"Streekweg",
    "iso:country":"NL",
    "sg:address":"Streekweg 68",
    "sg:city":"Hoogkarspel",
    "sg:orig_category":"Diverse Consumentenartikelen Gh",
    "sg:phone":"+31 228 562 545",
    "sg:postcode":"1616 AL",
    "sg:province":"Noord-Holland",
    "wof:name":"Wsv International",
    "wof:placetype":"venue"
},
  "geometry": {"coordinates":[5.166131,52.69252],"type":"Point"}
}