{
  "type": "Feature",
  "properties": {
    "addr:full":"Wagnerln 30 Enschede NL.08 7522 KJ",
    "addr:housenumber":"30",
    "addr:postcode":"7522 kj",
    "addr:street":"Wagnerln",
    "iso:country":"NL",
    "sg:address":"Wagnerln 30",
    "sg:city":"Enschede",
    "sg:orig_category":"Kunsthandel",
    "sg:phone":"+31 53 435 7205",
    "sg:postcode":"7522 KJ",
    "sg:province":"NL.08",
    "wof:name":"Rijkeboer, W",
    "wof:placetype":"venue"
},
  "geometry": {"coordinates":[6.877402,52.240345],"type":"Point"}
}