{
  "type": "Feature",
  "properties": {
    "addr:full":"S Gravelandsewg 131A Hilversum Noord-Holland 1217 ER",
    "addr:housenumber":"131a",
    "addr:postcode":"1217 er",
    "iso:country":"NL",
    "sg:address":"S Gravelandsewg 131A",
    "sg:city":"Hilversum",
    "sg:orig_category":"Adviesbureaus Bedrijfsorganisatie",
    "sg:phone":"+31 35 621 1312",
    "sg:postcode":"1217 ER",
    "sg:province":"Noord-Holland",
    "wof:name":"Meijnik Bv",
    "wof:placetype":"venue"
},
  "geometry": {"coordinates":[5.148439,52.235699],"type":"Point"}
}