{
  "type": "Feature",
  "properties": {
    "iso:country":"NL",
    "sg:address":"S M Loncquestraat 2",
    "sg:city":"Oosterland",
    "sg:orig_category":"Verhuur Bouwmachines",
    "sg:phone":"+31 111 647 220",
    "sg:postcode":"4307 BH",
    "sg:province":"Zeeland",
    "wof:name":"S & D",
    "wof:placetype":"venue"
},
  "geometry": {"coordinates":[4.033226,51.651379],"type":"Point"}
}