{
  "type": "Feature",
  "properties": {
    "addr:full":"Frans Halslaan 17 Waalwijk North Brabant 5143 GJ",
    "addr:housenumber":"17",
    "addr:postcode":"5143 gj",
    "addr:street":"Frans Halslaan",
    "iso:country":"NL",
    "sg:address":"Frans Halslaan 17",
    "sg:city":"Waalwijk",
    "sg:classifiers":[
        {
            "category":"Education",
            "subcategory":"Preschool",
            "type":"Public Place"
        }
    ],
    "sg:phone":"+31 416 331 188",
    "sg:postcode":"5143 GJ",
    "sg:province":"North Brabant",
    "sg:tags":[
        "kleuteronderwijs",
        "basis-"
    ],
    "wof:name":"Basisschool Meerdijk",
    "wof:placetype":"venue"
},
  "geometry": {"coordinates":[5.080668,51.67601],"type":"Point"}
}