{
  "type": "Feature",
  "properties": {
    "iso:country":"NL",
    "sg:address":"Voorheuvel 68",
    "sg:city":"Zeist",
    "sg:orig_category":"Juweliers",
    "sg:phone":"+31 30 691 6652",
    "sg:postcode":"3701 JG",
    "sg:province":"Utrecht",
    "wof:name":"Blinken",
    "wof:placetype":"venue"
},
  "geometry": {"coordinates":[5.241474,52.088581],"type":"Point"}
}