{
  "type": "Feature",
  "properties": {
    "iso:country":"NL",
    "sg:address":"Dorpsstraat 18",
    "sg:city":"Rosmalen",
    "sg:orig_category":"Damesmodezaken",
    "sg:phone":"+31 73 521 3174",
    "sg:postcode":"5241 EC",
    "sg:province":"Noord-Brabant",
    "wof:name":"Modehuis Van Den Oetelaar Vof",
    "wof:placetype":"venue"
},
  "geometry": {"coordinates":[5.362529,51.718254],"type":"Point"}
}