{
  "type": "Feature",
  "properties": {
    "addr:full":"Nachtegaalstraat 64 Utrecht Utrecht 3581 AM",
    "addr:housenumber":"64",
    "addr:postcode":"3581",
    "addr:street":"Nachtegaalstraat",
    "iso:country":"NL",
    "sg:address":"Nachtegaalstraat 64",
    "sg:city":"Utrecht",
    "sg:classifiers":[
        {
            "category":"Shopping",
            "subcategory":"Gifts & Souvenirs",
            "type":"Retail Goods"
        }
    ],
    "sg:phone":"+31 30 231 0030",
    "sg:postcode":"3581 AM",
    "sg:province":"Utrecht",
    "sg:tags":[
        "geschenken"
    ],
    "wof:name":"Winesong",
    "wof:placetype":"venue"
},
  "geometry": {"coordinates":[5.13153,52.091801],"type":"Point"}
}