{
  "type": "Feature",
  "properties": {
    "iso:country":"NL",
    "sg:address":"Heimolendreef 12",
    "sg:city":"Rucphen",
    "sg:orig_category":"Goederenvervoer Over De Weg",
    "sg:phone":"+31 165 341 748",
    "sg:postcode":"4715 TC",
    "sg:province":"Noord-Brabant",
    "wof:name":"P. De Rijk En Zonen Transport Bv",
    "wof:placetype":"venue"
},
  "geometry": {"coordinates":[4.536931,51.541721],"type":"Point"}
}