{
  "type": "Feature",
  "properties": {
    "addr:full":"Heimolendreef 12 Rucphen Noord-Brabant 4715 TC",
    "addr:housenumber":"12",
    "addr:postcode":"4715 tc",
    "addr:street":"Heimolendreef",
    "iso:country":"NL",
    "sg:address":"Heimolendreef 12",
    "sg:city":"Rucphen",
    "sg:orig_category":"Goederenvervoer Over De Weg",
    "sg:phone":"+31 165 341 748",
    "sg:postcode":"4715 TC",
    "sg:province":"Noord-Brabant",
    "wof:name":"P. De Rijk En Zonen Transport Bv",
    "wof:placetype":"venue"
},
  "geometry": {"coordinates":[4.536931,51.541721],"type":"Point"}
}