{
  "type": "Feature",
  "properties": {
    "addr:full":"Emmastraat 18 Lekkerkerk Zuid-Holland 2941 XD",
    "addr:housenumber":"18",
    "addr:postcode":"2941 xd",
    "addr:street":"Emmastraat",
    "iso:country":"NL",
    "sg:address":"Emmastraat 18",
    "sg:city":"Lekkerkerk",
    "sg:orig_category":"Diverse Bedrijfsinstallaties Gh",
    "sg:phone":"+31 180 662 429",
    "sg:postcode":"2941 XD",
    "sg:province":"Zuid-Holland",
    "wof:name":"Meijer Brandbeveiliging Vof",
    "wof:placetype":"venue"
},
  "geometry": {"coordinates":[4.687988,51.897251],"type":"Point"}
}