{
  "type": "Feature",
  "properties": {
    "addr:full":"Hofstad 38 Bladel North Brabant 5531 GD",
    "addr:housenumber":"38",
    "addr:postcode":"5531 gd",
    "addr:street":"Hofstad",
    "iso:country":"NL",
    "sg:address":"Hofstad 38",
    "sg:city":"Bladel",
    "sg:orig_category":"Medische And Orthopedische Artikelen",
    "sg:phone":"+31 497 382 787",
    "sg:postcode":"5531 GD",
    "sg:province":"North Brabant",
    "wof:name":"Linders En Lieberwirth Vof",
    "wof:placetype":"venue"
},
  "geometry": {"coordinates":[5.223538,51.372093],"type":"Point"}
}