{
  "type": "Feature",
  "properties": {
    "addr:full":"J Vernewg 7A Tilburg North Brabant 5015 BD",
    "addr:housenumber":"7a",
    "addr:postcode":"5015 bd",
    "iso:country":"NL",
    "sg:address":"J Vernewg 7A",
    "sg:city":"Tilburg",
    "sg:orig_category":"Bloemisterijartikelen - Fabrieken En Groothandel",
    "sg:phone":"+31 13 535 6281",
    "sg:postcode":"5015 BD",
    "sg:province":"North Brabant",
    "wof:name":"Items Decorations",
    "wof:placetype":"venue"
},
  "geometry": {"coordinates":[5.11067,51.565338],"type":"Point"}
}