{
  "type": "Feature",
  "properties": {
    "addr:full":"Draaiwg 35 Utrecht Utrecht 3515 EJ",
    "addr:housenumber":"35",
    "addr:postcode":"3515 ej",
    "addr:street":"Draaiwg",
    "iso:country":"NL",
    "sg:address":"Draaiwg 35",
    "sg:city":"Utrecht",
    "sg:orig_category":"Webdesign Bureaus",
    "sg:phone":"+31 30 254 0822",
    "sg:postcode":"3515 EJ",
    "sg:province":"Utrecht",
    "sg:website":"http://www.elfling.nl",
    "wof:name":"Elfling",
    "wof:placetype":"venue"
},
  "geometry": {"coordinates":[5.1145119667,52.1010017395],"type":"Point"}
}