{
  "type": "Feature",
  "properties": {
    "iso:country":"NL",
    "sg:address":"Databankweg 18",
    "sg:city":"Amersfoort",
    "sg:orig_category":"Verhuisdiensten",
    "sg:phone":"+31 33 450 8210",
    "sg:postcode":"3821 AL",
    "sg:province":"Utrecht",
    "wof:name":"Pot Verhuizingen En Logistiek",
    "wof:placetype":"venue"
},
  "geometry": {"coordinates":[5.416917,52.181835],"type":"Point"}
}