{
  "type": "Feature",
  "properties": {
    "addr:full":"Davidspln 6 Veenendaal Utrecht 3905 AZ",
    "addr:housenumber":"6",
    "addr:postcode":"3905",
    "addr:street":"Davidspln",
    "iso:country":"NL",
    "sg:address":"Davidspln 6",
    "sg:city":"Veenendaal",
    "sg:orig_category":"Podotherapeuten",
    "sg:phone":"+31 318 512 596",
    "sg:postcode":"3905 AZ",
    "sg:province":"Utrecht",
    "wof:name":"Erp, M Van",
    "wof:placetype":"venue"
},
  "geometry": {"coordinates":[5.547326,52.029884],"type":"Point"}
}