{
  "type": "Feature",
  "properties": {
    "addr:full":"Doctor Van Beurdenstraat 29 Kaatsheuvel North Brabant 5171 GA",
    "addr:housenumber":"29",
    "addr:postcode":"5171 ga",
    "addr:street":"Doctor Van Beurdenstraat",
    "iso:country":"NL",
    "sg:address":"Doctor Van Beurdenstraat 29",
    "sg:city":"Kaatsheuvel",
    "sg:orig_category":"Schoenen Fab",
    "sg:phone":"+31 416 274 434",
    "sg:postcode":"5171 GA",
    "sg:province":"North Brabant",
    "wof:name":"Leon Parc Bv",
    "wof:placetype":"venue"
},
  "geometry": {"coordinates":[5.036314,51.65995],"type":"Point"}
}