{
  "type": "Feature",
  "properties": {
    "addr:full":"H Figeewg 1-1 Haarlem Noord-Holland 2031 BJ",
    "addr:housenumber":"1-1",
    "addr:postcode":"2031 bj",
    "iso:country":"NL",
    "sg:address":"H Figeewg 1-1",
    "sg:city":"Haarlem",
    "sg:orig_category":"Displays, Showcards En Toonmaterialen",
    "sg:phone":"+31 23 551 9610",
    "sg:postcode":"2031 BJ",
    "sg:province":"Noord-Holland",
    "wof:name":"Display Corner Bv",
    "wof:placetype":"venue"
},
  "geometry": {"coordinates":[4.651705,52.389973],"type":"Point"}
}