{
  "type": "Feature",
  "properties": {
    "iso:country":"NL",
    "sg:address":"Rietdekkerstraat 1",
    "sg:city":"Uden",
    "sg:orig_category":"Metaalbekleding And -Behandeling",
    "sg:phone":"+31 413 255 451",
    "sg:postcode":"5405 AX",
    "sg:province":"\u00c5land",
    "wof:name":"Vovu Metaalbewerking",
    "wof:placetype":"venue"
},
  "geometry": {"coordinates":[20.217291,60.19825],"type":"Point"}
}