{
  "type": "Feature",
  "properties": {
    "addr:full":"Einsteinstr 32 Maastricht Limburg 6227 BZ",
    "addr:housenumber":"32",
    "addr:postcode":"6227 bz",
    "addr:street":"Einsteinstr",
    "iso:country":"NL",
    "sg:address":"Einsteinstr 32",
    "sg:city":"Maastricht",
    "sg:orig_category":"Verenigingsgebouwen",
    "sg:phone":"+31 43 361 2246",
    "sg:postcode":"6227 BZ",
    "sg:province":"Limburg",
    "wof:name":"Wan, Aen De",
    "wof:placetype":"venue"
},
  "geometry": {"coordinates":[5.732277,50.840698],"type":"Point"}
}