{
  "type": "Feature",
  "properties": {
    "addr:full":"Breelaan 16 Bergen Nh North Holland 1861 GE",
    "addr:housenumber":"16",
    "addr:postcode":"1861",
    "addr:street":"Breelaan",
    "iso:country":"NL",
    "sg:address":"Breelaan 16",
    "sg:city":"Bergen Nh",
    "sg:orig_category":"Banken And Kredietinstellingen",
    "sg:phone":"+31 72 509 6500",
    "sg:postcode":"1861 GE",
    "sg:province":"North Holland",
    "wof:name":"Rabobank",
    "wof:placetype":"venue"
},
  "geometry": {"coordinates":[4.700557,52.671326],"type":"Point"}
}