{
  "type": "Feature",
  "properties": {
    "iso:country":"NL",
    "sg:address":"Munnikenhof 6",
    "sg:city":"Heino",
    "sg:orig_category":"Opticiens",
    "sg:phone":"+31 572 391 206",
    "sg:postcode":"8141 GL",
    "sg:province":"Overijssel",
    "wof:name":"Boerdijk Opticien-Juwelier",
    "wof:placetype":"venue"
},
  "geometry": {"coordinates":[-95.39873504640001,46.4989051819],"type":"Point"}
}