{
  "type": "Feature",
  "properties": {
    "addr:full":"Rootven 30 Bladel Noord-Brabant 5531 MB",
    "addr:housenumber":"30",
    "addr:postcode":"5531 mb",
    "addr:street":"Rootven",
    "iso:country":"NL",
    "sg:address":"Rootven 30",
    "sg:city":"Bladel",
    "sg:orig_category":"Verhuur Catering-, Feest- En Evenementbenodigdheden",
    "sg:phone":"+31 497 383 990",
    "sg:postcode":"5531 MB",
    "sg:province":"Noord-Brabant",
    "wof:name":"Van Ham Tenten",
    "wof:placetype":"venue"
},
  "geometry": {"coordinates":[5.201403,51.355202],"type":"Point"}
}