{
  "type": "Feature",
  "properties": {
    "addr:full":"Hoofdstr 32 Zwiggelte Drenthe 9433 PC",
    "addr:housenumber":"32",
    "addr:postcode":"9433 pc",
    "addr:street":"Hoofdstr",
    "iso:country":"NL",
    "sg:address":"Hoofdstr 32",
    "sg:city":"Zwiggelte",
    "sg:orig_category":"Kinderopvang",
    "sg:phone":"+31 593 331 430",
    "sg:postcode":"9433 PC",
    "sg:province":"Drenthe",
    "wof:name":"Speulhoes, 'T",
    "wof:placetype":"venue"
},
  "geometry": {"coordinates":[6.587563,52.874523],"type":"Point"}
}