{
  "type": "Feature",
  "properties": {
    "iso:country":"NL",
    "sg:address":"Schiphorsterweg 36",
    "sg:city":"De Wijk",
    "sg:orig_category":"Binnenhuisarchitecten",
    "sg:phone":"+31 522 441 448",
    "sg:postcode":"7957 NV",
    "sg:province":"Drenthe",
    "wof:name":"Klinkenberg Styling & Ontwerp",
    "wof:placetype":"venue"
},
  "geometry": {"coordinates":[6.270876,52.673401],"type":"Point"}
}