{
  "type": "Feature",
  "properties": {
    "addr:full":"Libellestr 3 Hengelo Ov Overijssel 7559 BR",
    "addr:housenumber":"3",
    "addr:postcode":"7559 br",
    "addr:street":"Libellestr;Ov",
    "iso:country":"NL",
    "sg:address":"Libellestr 3",
    "sg:city":"Hengelo Ov",
    "sg:orig_category":"Vakorganisaties",
    "sg:phone":"+31 74 277 7143",
    "sg:postcode":"7559 BR",
    "sg:province":"Overijssel",
    "wof:name":"A O B",
    "wof:placetype":"venue"
},
  "geometry": {"coordinates":[6.813032,52.285004],"type":"Point"}
}