{
  "type": "Feature",
  "properties": {
    "addr:full":"Langstraat 31 Zoutelande Zeeland 4374 AN",
    "addr:housenumber":"31",
    "addr:postcode":"4374 an",
    "addr:street":"Langstraat",
    "iso:country":"NL",
    "sg:address":"Langstraat 31",
    "sg:city":"Zoutelande",
    "sg:orig_category":"Visspeciaalzaken",
    "sg:phone":"+31 118 562 287",
    "sg:postcode":"4374 AN",
    "sg:province":"Zeeland",
    "wof:name":"Vistaria 'T Harinkje",
    "wof:placetype":"venue"
},
  "geometry": {"coordinates":[3.484509,51.500099],"type":"Point"}
}