{
  "type": "Feature",
  "properties": {
    "addr:full":"G Flinckstr 4 Papendrecht Zuid-Holland 3351 VH",
    "addr:housenumber":"4",
    "addr:postcode":"3351 vh",
    "iso:country":"NL",
    "sg:address":"G Flinckstr 4",
    "sg:city":"Papendrecht",
    "sg:orig_category":"Meditatietechnieken",
    "sg:phone":"+31 78 615 3665",
    "sg:postcode":"3351 VH",
    "sg:province":"Zuid-Holland",
    "wof:name":"Transcendente Meditatie",
    "wof:placetype":"venue"
},
  "geometry": {"coordinates":[4.683512,51.834831],"type":"Point"}
}