{
  "type": "Feature",
  "properties": {
    "iso:country":"NL",
    "sg:address":"Philips Van Wassenaerln 8",
    "sg:city":"Nederhorst Den Berg",
    "sg:orig_category":"Keramische Producten Fab",
    "sg:phone":"+31 294 253 104",
    "sg:postcode":"1394 GZ",
    "sg:province":"Noord-Holland",
    "wof:name":"A. Masselman",
    "wof:placetype":"venue"
},
  "geometry": {"coordinates":[5.046851,52.26725],"type":"Point"}
}