{
  "type": "Feature",
  "properties": {
    "addr:full":"Middelwg 130 Deventer Overijssel 7413 PZ",
    "addr:housenumber":"130",
    "addr:postcode":"7413 pz",
    "iso:country":"NL",
    "sg:address":"Middelwg 130",
    "sg:city":"Deventer",
    "sg:orig_category":"Adviesbureaus Bedrijfsorganisatie",
    "sg:phone":"+31 570 625 266",
    "sg:postcode":"7413 PZ",
    "sg:province":"Overijssel",
    "wof:name":"Astrad",
    "wof:placetype":"venue"
},
  "geometry": {"coordinates":[6.148771,52.263988],"type":"Point"}
}