{
  "type": "Feature",
  "properties": {
    "addr:full":"Baanstraat 99 Landgraaf Limburg 6372 AE",
    "addr:housenumber":"99",
    "addr:postcode":"6372 ae",
    "addr:street":"Baanstraat",
    "iso:country":"NL",
    "sg:address":"Baanstraat 99",
    "sg:city":"Landgraaf",
    "sg:orig_category":"Elektronische Bedrijfsinstallaties",
    "sg:phone":"+31 45 532 3944",
    "sg:postcode":"6372 AE",
    "sg:province":"Limburg",
    "wof:name":"Begra Beveiligingen",
    "wof:placetype":"venue"
},
  "geometry": {"coordinates":[6.019069,50.889107],"type":"Point"}
}