{
  "type": "Feature",
  "properties": {
    "iso:country":"NL",
    "sg:address":"Dennendk 7",
    "sg:city":"Warnsveld",
    "sg:orig_category":"Pluimveebedrijven En -Handelaren",
    "sg:phone":"+31 575 521 895",
    "sg:postcode":"7231 RB",
    "sg:province":"Gelderland",
    "wof:name":"Derksen, W",
    "wof:placetype":"venue"
},
  "geometry": {"coordinates":[6.262065,52.124062],"type":"Point"}
}