{
  "type": "Feature",
  "properties": {
    "iso:country":"NL",
    "sg:address":"Kromhoutstraat 44",
    "sg:city":"Groningen",
    "sg:orig_category":"Boekhouders",
    "sg:phone":"+31 50 542 6339",
    "sg:postcode":"9731 MT",
    "sg:province":"Groningen",
    "wof:name":"Administratiekantoor Waanders",
    "wof:placetype":"venue"
},
  "geometry": {"coordinates":[6.574234,53.241058],"type":"Point"}
}