{
  "type": "Feature",
  "properties": {
    "addr:full":"V Harenstr 126 St Annaparochie Friesland 9076 BZ",
    "addr:housenumber":"126",
    "addr:postcode":"9076 bz",
    "addr:street":"St",
    "iso:country":"NL",
    "sg:address":"V Harenstr 126",
    "sg:city":"St Annaparochie",
    "sg:orig_category":"Meubelstoffering",
    "sg:phone":"+31 518 401 533",
    "sg:postcode":"9076 BZ",
    "sg:province":"Friesland",
    "wof:name":"Cuperus, Meubelstoffeerderij",
    "wof:placetype":"venue"
},
  "geometry": {"coordinates":[5.65766,53.27393],"type":"Point"}
}