{
  "type": "Feature",
  "properties": {
    "addr:full":"Vliet 20 Leiden Zuid-Holland 2311 RE",
    "addr:housenumber":"20",
    "addr:postcode":"2311 re",
    "addr:street":"Vliet",
    "iso:country":"NL",
    "sg:address":"Vliet 20",
    "sg:city":"Leiden",
    "sg:classifiers":[
        {
            "category":"Education",
            "subcategory":"Preschool",
            "type":"Public Place"
        }
    ],
    "sg:phone":"+31 71 512 1675",
    "sg:postcode":"2311 RE",
    "sg:province":"Zuid-Holland",
    "sg:tags":[
        "kleuteronderwijs",
        "basis-"
    ],
    "wof:name":"Openbare Basisschool Lucas Van Leijden",
    "wof:placetype":"venue"
},
  "geometry": {"coordinates":[4.487954,52.155182],"type":"Point"}
}