{
  "type": "Feature",
  "properties": {
    "addr:full":"Jekerstr 112 Amsterdam Noord-Holland 1078 MJ",
    "addr:housenumber":"112",
    "addr:postcode":"1078 mj",
    "iso:country":"NL",
    "sg:address":"Jekerstr 112",
    "sg:city":"Amsterdam",
    "sg:orig_category":"Kappers",
    "sg:phone":"+31 20 470 6477",
    "sg:postcode":"1078 MJ",
    "sg:province":"Noord-Holland",
    "wof:name":"Oggi",
    "wof:placetype":"venue"
},
  "geometry": {"coordinates":[4.89557,52.345642],"type":"Point"}
}