{
  "type": "Feature",
  "properties": {
    "addr:full":"W Pyperln 5 Rotterdam South Holland 3055 WL",
    "addr:housenumber":"5",
    "addr:postcode":"3055 wl",
    "addr:street":"W",
    "iso:country":"NL",
    "sg:address":"W Pyperln 5",
    "sg:city":"Rotterdam",
    "sg:orig_category":"Adviesbureaus Bedrijfsorganisatie",
    "sg:phone":"+31 10 218 0904",
    "sg:postcode":"3055 WL",
    "sg:province":"South Holland",
    "wof:name":"Lourens, G H",
    "wof:placetype":"venue"
},
  "geometry": {"coordinates":[4.50689,51.961319],"type":"Point"}
}