{
  "type": "Feature",
  "properties": {
    "addr:full":"Klinkerwg 45 Amsterdam Noord-Holland 1033 PJ",
    "addr:housenumber":"45",
    "addr:postcode":"1033 pj",
    "addr:street":"Klinkerwg",
    "iso:country":"NL",
    "sg:address":"Klinkerwg 45",
    "sg:city":"Amsterdam",
    "sg:orig_category":"Autorijscholen",
    "sg:phone":"+31 20 633 2388",
    "sg:postcode":"1033 PJ",
    "sg:province":"Noord-Holland",
    "wof:name":"Alegria",
    "wof:placetype":"venue"
},
  "geometry": {"coordinates":[4.89785,52.406933],"type":"Point"}
}