{
  "type": "Feature",
  "properties": {
    "addr:full":"Europawg 131 Nieuw Schoonebeek Drenthe 7766 AD",
    "addr:housenumber":"131",
    "addr:postcode":"7766 ad",
    "addr:street":"Nieuw Schoonebeek",
    "iso:country":"NL",
    "sg:address":"Europawg 131",
    "sg:city":"Nieuw Schoonebeek",
    "sg:orig_category":"Touringcars",
    "sg:phone":"+31 524 541 300",
    "sg:postcode":"7766 AD",
    "sg:province":"Drenthe",
    "wof:name":"Pieper En Zn, Fa",
    "wof:placetype":"venue"
},
  "geometry": {"coordinates":[6.983405,52.647293],"type":"Point"}
}