{
  "type": "Feature",
  "properties": {
    "iso:country":"NL",
    "sg:address":"Eco Eckiusstrjitte 25",
    "sg:city":"Stiens",
    "sg:orig_category":"Goederenvervoer Over De Weg",
    "sg:phone":"+31 58 257 1216",
    "sg:postcode":"9051 CB",
    "sg:province":"Provincie Friesland",
    "wof:name":"Firma B. De Vries",
    "wof:placetype":"venue"
},
  "geometry": {"coordinates":[5.761757,53.261791],"type":"Point"}
}