{
  "type": "Feature",
  "properties": {
    "addr:full":"Zandvoortwijk 4 Abbekerk Noord-Holland 1657 LT",
    "addr:housenumber":"4",
    "addr:postcode":"1657 lt",
    "addr:street":"Zandvoortwijk",
    "iso:country":"NL",
    "sg:address":"Zandvoortwijk 4",
    "sg:city":"Abbekerk",
    "sg:orig_category":"Boekhouders",
    "sg:phone":"+31 229 582 548",
    "sg:postcode":"1657 LT",
    "sg:province":"Noord-Holland",
    "wof:name":"Hoogeboom Admin En Fiscale Dienstverlening",
    "wof:placetype":"venue"
},
  "geometry": {"coordinates":[5.014979,52.731007],"type":"Point"}
}