{
  "type": "Feature",
  "properties": {
    "iso:country":"NL",
    "sg:address":"Hoofddorpwg 9",
    "sg:city":"Amsterdam",
    "sg:orig_category":"Broodjeszaken",
    "sg:phone":"+31 20 617 1683",
    "sg:postcode":"1059 CS",
    "sg:province":"Noord-Holland",
    "wof:name":"Diwi",
    "wof:placetype":"venue"
},
  "geometry": {"coordinates":[4.851533,52.35088],"type":"Point"}
}