{
  "type": "Feature",
  "properties": {
    "iso:country":"NL",
    "sg:address":"Elektronweg 10",
    "sg:city":"Utrecht",
    "sg:orig_category":"Gespecialiseerde Bouw",
    "sg:phone":"+31 30 241 1754",
    "sg:postcode":"3542 AC",
    "sg:province":"Utrecht",
    "wof:name":"De Graaf Constructie & Apparatenfabr Bv",
    "wof:placetype":"venue"
},
  "geometry": {"coordinates":[5.070482,52.099438],"type":"Point"}
}