{
  "type": "Feature",
  "properties": {
    "addr:full":"Boschstr 38A Breda Noord-Brabant 4811 GH",
    "addr:housenumber":"38a",
    "addr:postcode":"4811 gh",
    "addr:street":"Boschstr",
    "iso:country":"NL",
    "sg:address":"Boschstr 38A",
    "sg:city":"Breda",
    "sg:orig_category":"Kappers",
    "sg:phone":"+31 76 522 9621",
    "sg:postcode":"4811 GH",
    "sg:province":"Noord-Brabant",
    "wof:name":"Kosa",
    "wof:placetype":"venue"
},
  "geometry": {"coordinates":[4.781929,51.590008],"type":"Point"}
}