{
  "type": "Feature",
  "properties": {
    "addr:full":"Lindenhof 3 Woerden Utrecht 3442 GT",
    "addr:housenumber":"3",
    "addr:postcode":"3442 gt",
    "addr:street":"Lindenhof",
    "iso:country":"NL",
    "sg:address":"Lindenhof 3",
    "sg:city":"Woerden",
    "sg:orig_category":"Boekhouders",
    "sg:phone":"+31 348 415 175",
    "sg:postcode":"3442 GT",
    "sg:province":"Utrecht",
    "wof:name":"Administratiekantoor Schoe Bv",
    "wof:placetype":"venue"
},
  "geometry": {"coordinates":[4.870599,52.083878],"type":"Point"}
}