{
  "type": "Feature",
  "properties": {
    "addr:full":"Jan Steenlaan 130 Papendrecht Zuid-Holland 3351 RD",
    "addr:housenumber":"130",
    "addr:postcode":"3351 rd",
    "addr:street":"Jan Steenlaan",
    "iso:country":"NL",
    "sg:address":"Jan Steenlaan 130",
    "sg:city":"Papendrecht",
    "sg:orig_category":"Kappers",
    "sg:phone":"+31 78 615 5524",
    "sg:postcode":"3351 RD",
    "sg:province":"Zuid-Holland",
    "wof:name":"L.C.M. V.D. Hout-Wouters",
    "wof:placetype":"venue"
},
  "geometry": {"coordinates":[4.682269,51.835407],"type":"Point"}
}