{
  "type": "Feature",
  "properties": {
    "addr:full":"Zakkendragersstg 7 Utrecht Utrecht 3511 AA",
    "addr:housenumber":"7",
    "addr:postcode":"3511 aa",
    "addr:street":"Zakkendragersstg",
    "iso:country":"NL",
    "sg:address":"Zakkendragersstg 7",
    "sg:city":"Utrecht",
    "sg:orig_category":"Woninginrichting",
    "sg:phone":"+31 30 262 0929",
    "sg:postcode":"3511 AA",
    "sg:province":"Utrecht",
    "wof:name":"Hill Design",
    "wof:placetype":"venue"
},
  "geometry": {"coordinates":[5.1161031723,52.0926971436],"type":"Point"}
}