{
  "type": "Feature",
  "properties": {
    "addr:full":"Tramstr 23-25 Deurne Noord-Brabant 5751 JK",
    "addr:housenumber":"23-25",
    "addr:postcode":"5751 jk",
    "iso:country":"NL",
    "sg:address":"Tramstr 23-25",
    "sg:city":"Deurne",
    "sg:orig_category":"Administratie- En Boekhoudkantoren",
    "sg:phone":"+31 493 316 028",
    "sg:postcode":"5751 JK",
    "sg:province":"Noord-Brabant",
    "wof:name":"Kuijten",
    "wof:placetype":"venue"
},
  "geometry": {"coordinates":[5.790587,51.456097],"type":"Point"}
}