{
  "type": "Feature",
  "properties": {
    "addr:full":"Industriewg 13A Assendelft North Holland 1566 JN",
    "addr:housenumber":"13a",
    "addr:postcode":"1566 jn",
    "addr:street":"Industriewg",
    "iso:country":"NL",
    "sg:address":"Industriewg 13A",
    "sg:city":"Assendelft",
    "sg:orig_category":"Verpakkingsbedrijven",
    "sg:phone":"+31 75 640 0961",
    "sg:postcode":"1566 JN",
    "sg:province":"North Holland",
    "wof:name":"Inpako Med",
    "wof:placetype":"venue"
},
  "geometry": {"coordinates":[4.766312,52.490623],"type":"Point"}
}