{
  "type": "Feature",
  "properties": {
    "addr:full":"Dorpstraat 58 Luyksgestel Noord-Brabant 5575 AE",
    "addr:housenumber":"58",
    "addr:postcode":"5575 ae",
    "addr:street":"Dorpstraat",
    "iso:country":"NL",
    "sg:address":"Dorpstraat 58",
    "sg:city":"Luyksgestel",
    "sg:classifiers":[
        {
            "category":"Bakery",
            "type":"Food & Drink"
        }
    ],
    "sg:phone":"+31 497 541 294",
    "sg:postcode":"5575 AE",
    "sg:province":"Noord-Brabant",
    "sg:tags":[
        "brood",
        "banket"
    ],
    "wof:name":"Van Heeswijk Vof",
    "wof:placetype":"venue"
},
  "geometry": {"coordinates":[5.325892,51.287838],"type":"Point"}
}