{
  "type": "Feature",
  "properties": {
    "iso:country":"NL",
    "sg:address":"Anjerstr 1",
    "sg:city":"Papendrecht",
    "sg:orig_category":"Verenigingen En Stichtingen",
    "sg:phone":"+31 78 615 8648",
    "sg:postcode":"3353 AB",
    "sg:province":"Zuid-Holland",
    "wof:name":"Excelsior Muziekvereniging",
    "wof:placetype":"venue"
},
  "geometry": {"coordinates":[4.692919,51.828625],"type":"Point"}
}