{
  "type": "Feature",
  "properties": {
    "addr:full":"S Stevinstr 4 Wychen Gelderland 6603 BD",
    "addr:housenumber":"4",
    "addr:postcode":"6603 bd",
    "addr:street":"Wychen Gelderland",
    "iso:country":"NL",
    "sg:address":"S Stevinstr 4",
    "sg:city":"Wychen",
    "sg:orig_category":"Bakkerijmachines En -Gereedschappen",
    "sg:phone":"+31 24 648 6288",
    "sg:postcode":"6603 BD",
    "sg:province":"Gelderland",
    "wof:name":"Beko",
    "wof:placetype":"venue"
},
  "geometry": {"coordinates":[5.69934,51.820381],"type":"Point"}
}