{
  "type": "Feature",
  "properties": {
    "iso:country":"NL",
    "sg:address":"Centrumpassage 124",
    "sg:city":"Capelle Ad Yssel",
    "sg:orig_category":"Kaas",
    "sg:phone":"+31 10 442 4903",
    "sg:postcode":"2903 HE",
    "sg:province":"Zuid-Holland",
    "wof:name":"Kaasspecialist, De",
    "wof:placetype":"venue"
},
  "geometry": {"coordinates":[4.5886659622,51.931804657],"type":"Point"}
}