{
  "type": "Feature",
  "properties": {
    "addr:full":"Gelderlantln 4 Utrecht Utrecht 3526 KZ",
    "addr:housenumber":"4",
    "addr:postcode":"3526",
    "addr:street":"Gelderlantln",
    "iso:country":"NL",
    "sg:address":"Gelderlantln 4",
    "sg:city":"Utrecht",
    "sg:orig_category":"Administratie- En Boekhoudkantoren",
    "sg:phone":"+31 30 298 8200",
    "sg:postcode":"3526 KZ",
    "sg:province":"Utrecht",
    "wof:name":"Fiditem Bv",
    "wof:placetype":"venue"
},
  "geometry": {"coordinates":[5.106713,52.054649],"type":"Point"}
}