{
  "type": "Feature",
  "properties": {
    "addr:full":"Fregat 205 Diemen Noord-Holland 1113 EG",
    "addr:housenumber":"205",
    "addr:postcode":"1113 eg",
    "addr:street":"Fregat",
    "iso:country":"NL",
    "sg:address":"Fregat 205",
    "sg:city":"Diemen",
    "sg:orig_category":"Modellenbureaus",
    "sg:phone":"+31 20 402 0715",
    "sg:postcode":"1113 EG",
    "sg:province":"Noord-Holland",
    "wof:name":"Publiekszaken Tv En Figuratie",
    "wof:placetype":"venue"
},
  "geometry": {"coordinates":[4.980871,52.350166],"type":"Point"}
}