{
  "type": "Feature",
  "properties": {
    "addr:full":"Hooghiemstraplein 128 Utrecht Utrecht 3514 AZ",
    "addr:housenumber":"128",
    "addr:postcode":"3514",
    "addr:street":"Hooghiemstraplein",
    "iso:country":"NL",
    "sg:address":"Hooghiemstraplein 128",
    "sg:city":"Utrecht",
    "sg:orig_category":"Bedrijfs- And Managementsconsultants",
    "sg:phone":"+31 30 276 9262",
    "sg:postcode":"3514 AZ",
    "sg:province":"Utrecht",
    "wof:name":"Pro Found",
    "wof:placetype":"venue"
},
  "geometry": {"coordinates":[5.125095,52.098335],"type":"Point"}
}