{
  "type": "Feature",
  "properties": {
    "addr:full":"Dorpsstraat 308 Assendelft North Holland 1566 BP",
    "addr:housenumber":"308",
    "addr:postcode":"1566 bp",
    "addr:street":"Dorpsstraat",
    "iso:country":"NL",
    "sg:address":"Dorpsstraat 308",
    "sg:city":"Assendelft",
    "sg:orig_category":"Verhuur Gereedschapsmachines And Gereedschappen",
    "sg:phone":"+31 75 687 3210",
    "sg:postcode":"1566 BP",
    "sg:province":"North Holland",
    "wof:name":"Fa. R. Meijer & Zn",
    "wof:placetype":"venue"
},
  "geometry": {"coordinates":[4.737803,52.46273],"type":"Point"}
}