{
  "type": "Feature",
  "properties": {
    "addr:full":"Prof Scholtenstr 13 Nykerkerveen Gelderland 3864 GL",
    "addr:housenumber":"13",
    "addr:postcode":"3864 gl",
    "addr:street":"Nykerkerveen Gelderland",
    "iso:country":"NL",
    "sg:address":"Prof Scholtenstr 13",
    "sg:city":"Nykerkerveen",
    "sg:orig_category":"Woningstoffeerders",
    "sg:phone":"+31 33 253 4090",
    "sg:postcode":"3864 GL",
    "sg:province":"Gelderland",
    "wof:name":"Berge, H Van Den",
    "wof:placetype":"venue"
},
  "geometry": {"coordinates":[5.4633851051,52.1927223206],"type":"Point"}
}