{
  "type": "Feature",
  "properties": {
    "addr:full":"Baaneweer 35 Sliedrecht Zuid-Holland 3363 XB",
    "addr:housenumber":"35",
    "addr:postcode":"3363 xb",
    "addr:street":"Baaneweer",
    "iso:country":"NL",
    "sg:address":"Baaneweer 35",
    "sg:city":"Sliedrecht",
    "sg:orig_category":"Administratie- En Boekhoudkantoren",
    "sg:phone":"+31 184 417 110",
    "sg:postcode":"3363 XB",
    "sg:province":"Zuid-Holland",
    "wof:name":"Jager, De",
    "wof:placetype":"venue"
},
  "geometry": {"coordinates":[4.751612,51.827915],"type":"Point"}
}