{
  "type": "Feature",
  "properties": {
    "addr:full":"Arendshof 75 Oosterhout Nb North Brabant 4901 LK",
    "addr:housenumber":"75;nb",
    "addr:postcode":"4901 lk",
    "addr:street":"Arendshof",
    "iso:country":"NL",
    "sg:address":"Arendshof 75",
    "sg:city":"Oosterhout Nb",
    "sg:orig_category":"Schoenen",
    "sg:phone":"+31 162 453 478",
    "sg:postcode":"4901 LK",
    "sg:province":"North Brabant",
    "wof:name":"2000 Voetjes",
    "wof:placetype":"venue"
},
  "geometry": {"coordinates":[4.854784,51.643478],"type":"Point"}
}