{
  "type": "Feature",
  "properties": {
    "iso:country":"NL",
    "sg:address":"Nieuweweg 61",
    "sg:city":"Hoofddorp",
    "sg:orig_category":"Kantoorartikelen",
    "sg:phone":"+31 23 563 8481",
    "sg:postcode":"2132 CM",
    "sg:province":"North Holland",
    "wof:name":"Jager Kantoorshop",
    "wof:placetype":"venue"
},
  "geometry": {"coordinates":[4.6967248917,52.3030281067],"type":"Point"}
}