{
  "type": "Feature",
  "properties": {
    "addr:full":"Teilingerstraat 85 Rotterdam Zuid-Holland 3032 AV",
    "addr:housenumber":"85",
    "addr:postcode":"3032 av",
    "addr:street":"Teilingerstraat",
    "iso:country":"NL",
    "sg:address":"Teilingerstraat 85",
    "sg:city":"Rotterdam",
    "sg:classifiers":[
        {
            "category":"Fast Food",
            "type":"Food & Drink"
        }
    ],
    "sg:phone":"+31 10 466 2397",
    "sg:postcode":"3032 AV",
    "sg:province":"Zuid-Holland",
    "sg:tags":[
        "afhaal",
        "restaurant"
    ],
    "wof:name":"Afhaalrestaurant Silvia",
    "wof:placetype":"venue"
},
  "geometry": {"coordinates":[4.474461,51.928452],"type":"Point"}
}