{
  "type": "Feature",
  "properties": {
    "addr:full":"George Gershwinstr 207 Zaandijk North Holland 1544 NX",
    "addr:housenumber":"207",
    "addr:postcode":"1544 nx",
    "iso:country":"NL",
    "sg:address":"George Gershwinstr 207",
    "sg:city":"Zaandijk",
    "sg:orig_category":"Overheidsdiensten",
    "sg:phone":"+31 75 628 1253",
    "sg:postcode":"1544 NX",
    "sg:province":"North Holland",
    "wof:name":"Buurtcentrum Guishuis Het",
    "wof:placetype":"venue"
},
  "geometry": {"coordinates":[4.8008890152,52.4771575928],"type":"Point"}
}