{
  "type": "Feature",
  "properties": {
    "iso:country":"NL",
    "sg:address":"Edisonwg 8",
    "sg:city":"Bunschoten Spakenb",
    "sg:orig_category":"Banket",
    "sg:phone":"+31 33 299 2990",
    "sg:postcode":"3752 LV",
    "sg:province":"Utrecht",
    "wof:name":"Neerlandia Bv",
    "wof:placetype":"venue"
},
  "geometry": {"coordinates":[5.366961,52.230358],"type":"Point"}
}