{
  "type": "Feature",
  "properties": {
    "addr:full":"Amersfoortsewg 11D Doorn Utrecht 3941 EJ",
    "addr:housenumber":"11d",
    "addr:postcode":"3941 ej",
    "addr:street":"Amersfoortsewg",
    "iso:country":"NL",
    "sg:address":"Amersfoortsewg 11D",
    "sg:city":"Doorn",
    "sg:orig_category":"Goudsmeden En Zilversmeden",
    "sg:phone":"+31 343 415 049",
    "sg:postcode":"3941 EJ",
    "sg:province":"Utrecht",
    "sg:website":"http://www.goudsnip.nl",
    "wof:name":"Goudsnip, De",
    "wof:placetype":"venue"
},
  "geometry": {"coordinates":[5.345485,52.033768],"type":"Point"}
}