{
  "type": "Feature",
  "properties": {
    "addr:full":"F Hendrikstr 67 Sneek Provincie Friesland 8606 EH",
    "addr:housenumber":"67",
    "addr:postcode":"provincie;8606 eh",
    "iso:country":"NL",
    "sg:address":"F Hendrikstr 67",
    "sg:city":"Sneek",
    "sg:orig_category":"Verbouwingen",
    "sg:phone":"+31 515 422 778",
    "sg:postcode":"8606 EH",
    "sg:province":"Provincie Friesland",
    "wof:name":"Horst, Ter",
    "wof:placetype":"venue"
},
  "geometry": {"coordinates":[5.66197,53.033459],"type":"Point"}
}