{
  "type": "Feature",
  "properties": {
    "addr:full":"Heereweg 23 Lisse North Holland 2161 AC",
    "addr:housenumber":"23",
    "addr:postcode":"2161 ac",
    "addr:street":"Heereweg",
    "iso:country":"NL",
    "sg:address":"Heereweg 23",
    "sg:city":"Lisse",
    "sg:orig_category":"Loodgieters- And Verwarmingsmateriaal Gh",
    "sg:phone":"+31 252 466 400",
    "sg:postcode":"2161 AC",
    "sg:province":"North Holland",
    "wof:name":"Technische Handelsonderneming Nivola Bv",
    "wof:placetype":"venue"
},
  "geometry": {"coordinates":[4.561938,52.269981],"type":"Point"}
}