{
  "type": "Feature",
  "properties": {
    "iso:country":"NL",
    "sg:address":"Kees Boekelaan 1",
    "sg:city":"Bilthoven",
    "sg:orig_category":"Sportclubs",
    "sg:phone":"+31 30 228 2700",
    "sg:postcode":"3723 BA",
    "sg:province":"Utrecht",
    "wof:name":"Stichtse Cricket & Hockeyclub",
    "wof:placetype":"venue"
},
  "geometry": {"coordinates":[5.197243,52.135452],"type":"Point"}
}