{
  "type": "Feature",
  "properties": {
    "addr:full":"Einsteinstr 67 Dordrecht Zuid-Holland 3316 GG",
    "addr:housenumber":"67",
    "addr:postcode":"3316 gg",
    "addr:street":"Einsteinstr",
    "iso:country":"NL",
    "sg:address":"Einsteinstr 67",
    "sg:city":"Dordrecht",
    "sg:orig_category":"Beveiliging",
    "sg:phone":"+31 78 652 1199",
    "sg:postcode":"3316 GG",
    "sg:province":"Zuid-Holland",
    "sg:website":"http://www.casystems.nl",
    "wof:name":"Ca Systems",
    "wof:placetype":"venue"
},
  "geometry": {"coordinates":[4.636215,51.775417],"type":"Point"}
}