{
  "type": "Feature",
  "properties": {
    "addr:full":"Lynbaan 76 Rotterdam Zuid-Holland 3012 ER",
    "addr:housenumber":"76",
    "addr:postcode":"3012 er",
    "addr:street":"Lynbaan",
    "iso:country":"NL",
    "sg:address":"Lynbaan 76",
    "sg:city":"Rotterdam",
    "sg:orig_category":"Schoenen",
    "sg:phone":"+31 10 413 7983",
    "sg:postcode":"3012 ER",
    "sg:province":"Zuid-Holland",
    "sg:website":"http://www.dolcis.nl",
    "wof:name":"Dolcis",
    "wof:placetype":"venue"
},
  "geometry": {"coordinates":[4.478455,51.922836],"type":"Point"}
}