{
  "type": "Feature",
  "properties": {
    "addr:full":"Middenwaard 12 Heerhugowaard North Holland 1703 SE",
    "addr:housenumber":"12",
    "addr:postcode":"1703 se",
    "addr:street":"Middenwaard",
    "iso:country":"NL",
    "sg:address":"Middenwaard 12",
    "sg:city":"Heerhugowaard",
    "sg:orig_category":"Kaas",
    "sg:phone":"+31 72 571 7245",
    "sg:postcode":"1703 SE",
    "sg:province":"North Holland",
    "wof:name":"Fromagerie, De",
    "wof:placetype":"venue"
},
  "geometry": {"coordinates":[4.8309121132,52.6623191833],"type":"Point"}
}