{
  "type": "Feature",
  "properties": {
    "iso:country":"NL",
    "sg:address":"Vijf Eikenweg 5",
    "sg:city":"Oosterhout Nb",
    "sg:orig_category":"Sportclubs",
    "sg:phone":"+31 162 458 406",
    "sg:postcode":"4903 RK",
    "sg:province":"Noord-Brabant",
    "wof:name":"Voetbalvereniging Wvo",
    "wof:placetype":"venue"
},
  "geometry": {"coordinates":[4.877478,51.620842],"type":"Point"}
}