{
  "type": "Feature",
  "properties": {
    "addr:full":"De Huufkes 66 Nuenen Noord-Brabant 5674 TM",
    "addr:housenumber":"66",
    "addr:postcode":"5674 tm",
    "addr:street":"De Huufkes",
    "iso:country":"NL",
    "sg:address":"De Huufkes 66",
    "sg:city":"Nuenen",
    "sg:orig_category":"Diverse Grafische Activiteiten",
    "sg:phone":"+31 40 283 9531",
    "sg:postcode":"5674 TM",
    "sg:province":"Noord-Brabant",
    "wof:name":"Industrial Printing Services Bv",
    "wof:placetype":"venue"
},
  "geometry": {"coordinates":[5.555886,51.447075],"type":"Point"}
}