{
  "type": "Feature",
  "properties": {
    "iso:country":"NL",
    "sg:address":"Rykswg 12",
    "sg:city":"Schoorl",
    "sg:classifiers":[
        {
            "category":"Travel",
            "subcategory":"Hotels & Motels",
            "type":"Entertainment"
        }
    ],
    "sg:phone":"+31 72 509 1287",
    "sg:postcode":"1871 PD",
    "sg:province":"Noord-Holland",
    "wof:name":"Hof Van Schoorl",
    "wof:placetype":"venue"
},
  "geometry": {"coordinates":[4.715696,52.706772],"type":"Point"}
}