{
  "type": "Feature",
  "properties": {
    "addr:full":"Damstraat 44 Amsterdam Noord-Holland 1012 JM",
    "addr:housenumber":"44",
    "addr:postcode":"1012 jm",
    "addr:street":"Damstraat",
    "iso:country":"NL",
    "sg:address":"Damstraat 44",
    "sg:city":"Amsterdam",
    "sg:classifiers":[
        {
            "category":"Fast Food",
            "type":"Food & Drink"
        }
    ],
    "sg:phone":"+31 20 627 1937",
    "sg:postcode":"1012 JM",
    "sg:province":"Noord-Holland",
    "sg:tags":[
        "afhaal",
        "restaurant"
    ],
    "wof:name":"Grillroom The Middle East",
    "wof:placetype":"venue"
},
  "geometry": {"coordinates":[4.8954257965,52.371887207],"type":"Point"}
}