{
  "type": "Feature",
  "properties": {
    "iso:country":"NL",
    "sg:address":"Abeelstr 2",
    "sg:city":"Dordrecht",
    "sg:orig_category":"Beveiliging",
    "sg:phone":"+31 78 622 7551",
    "sg:postcode":"3329 AD",
    "sg:province":"Zuid-Holland",
    "wof:name":"Multech, Beveiligingstechniek",
    "wof:placetype":"venue"
},
  "geometry": {"coordinates":[4.707014,51.788013],"type":"Point"}
}