{
  "type": "Feature",
  "properties": {
    "addr:full":"Pluvierstraat 435 'S Gravenhage Zuid-Holland 2583 GX",
    "addr:housenumber":"435 '",
    "addr:postcode":"2583 gx",
    "addr:street":"Pluvierstraat",
    "iso:country":"NL",
    "sg:address":"Pluvierstraat 435",
    "sg:city":"'S Gravenhage",
    "sg:orig_category":"Kappers",
    "sg:phone":"+31 70 354 5508",
    "sg:postcode":"2583 GX",
    "sg:province":"Zuid-Holland",
    "wof:name":"Dameskapsalon Natasja",
    "wof:placetype":"venue"
},
  "geometry": {"coordinates":[4.2549090385,52.0880470276],"type":"Point"}
}