{
  "type": "Feature",
  "properties": {
    "addr:full":"Eikenburglaan 7 Rosmalen Noord-Brabant 5248 BJ",
    "addr:housenumber":"7",
    "addr:postcode":"5248 bj",
    "addr:street":"Eikenburglaan",
    "iso:country":"NL",
    "sg:address":"Eikenburglaan 7",
    "sg:city":"Rosmalen",
    "sg:orig_category":"Metaalbekleding And -Behandeling",
    "sg:phone":"+31 73 521 9200",
    "sg:postcode":"5248 BJ",
    "sg:province":"Noord-Brabant",
    "wof:name":"L.P.S. Benelux Bv",
    "wof:placetype":"venue"
},
  "geometry": {"coordinates":[5.387331,51.708755],"type":"Point"}
}