{
  "type": "Feature",
  "properties": {
    "addr:full":"Dorpsstraat 103 Vlieland Friesland 8899 AE",
    "addr:housenumber":"103",
    "addr:postcode":"8899 ae",
    "addr:street":"Dorpsstraat",
    "iso:country":"NL",
    "sg:address":"Dorpsstraat 103",
    "sg:city":"Vlieland",
    "sg:classifiers":[
        {
            "category":"Fast Food",
            "type":"Food & Drink"
        }
    ],
    "sg:phone":"+31 562 451 580",
    "sg:postcode":"8899 AE",
    "sg:province":"Friesland",
    "sg:tags":[
        "afhaal",
        "restaurant"
    ],
    "wof:name":"Cafetaria 'T Veerhuys",
    "wof:placetype":"venue"
},
  "geometry": {"coordinates":[5.067016,53.295353],"type":"Point"}
}