{
  "type": "Feature",
  "properties": {
    "iso:country":"NL",
    "sg:address":"Carbasiusstraat 21",
    "sg:city":"Purmerend",
    "sg:orig_category":"Film-, Tv- And Videoproductie",
    "sg:phone":"+31 299 642 370",
    "sg:postcode":"1447 PG",
    "sg:province":"Noord-Holland",
    "wof:name":"Disclosure",
    "wof:placetype":"venue"
},
  "geometry": {"coordinates":[4.974245,52.489117],"type":"Point"}
}