{
  "type": "Feature",
  "properties": {
    "addr:full":"Koningsln 33 Amsterdam North Holland 1075 AB",
    "addr:housenumber":"33",
    "addr:postcode":"1075 ab",
    "addr:street":"Koningsln",
    "iso:country":"NL",
    "sg:address":"Koningsln 33",
    "sg:city":"Amsterdam",
    "sg:orig_category":"Banken",
    "sg:phone":"+31 20 664 4141",
    "sg:postcode":"1075 AB",
    "sg:province":"North Holland",
    "wof:name":"Fgh Nv",
    "wof:placetype":"venue"
},
  "geometry": {"coordinates":[4.862321,52.355255],"type":"Point"}
}