{
  "type": "Feature",
  "properties": {
    "iso:country":"NL",
    "sg:address":"Lichte Gaard 4",
    "sg:city":"Utrecht",
    "sg:orig_category":"Vertaalbureaus",
    "sg:phone":"+31 30 233 1498",
    "sg:postcode":"3511 KT",
    "sg:province":"Utrecht",
    "sg:website":"http://www.atalanta.nl",
    "wof:name":"Atalanta",
    "wof:placetype":"venue"
},
  "geometry": {"coordinates":[5.120761,52.090321],"type":"Point"}
}