{
  "type": "Feature",
  "properties": {
    "addr:full":"Spuiboulevard 334 Dordrecht Zuid-Holland 3311 GR",
    "addr:housenumber":"334",
    "addr:postcode":"3311",
    "addr:street":"Spuiboulevard",
    "iso:country":"NL",
    "sg:address":"Spuiboulevard 334",
    "sg:city":"Dordrecht",
    "sg:orig_category":"Chemische Producten Gh",
    "sg:phone":"+31 78 635 0720",
    "sg:postcode":"3311 GR",
    "sg:province":"Zuid-Holland",
    "wof:name":"Hoetmer Bv",
    "wof:placetype":"venue"
},
  "geometry": {"coordinates":[4.661295,51.812038],"type":"Point"}
}