{
  "type": "Feature",
  "properties": {
    "addr:full":"Vrouwenhuiswaard 46 Zoetermeer Zuid-Holland 2716 DP",
    "addr:housenumber":"46",
    "addr:postcode":"2716 dp",
    "addr:street":"Vrouwenhuiswaard",
    "iso:country":"NL",
    "sg:address":"Vrouwenhuiswaard 46",
    "sg:city":"Zoetermeer",
    "sg:orig_category":"Vaste And Vloeibare Brandstoffen",
    "sg:phone":"+31 79 352 2145",
    "sg:postcode":"2716 DP",
    "sg:province":"Zuid-Holland",
    "wof:name":"L.A. Bakker",
    "wof:placetype":"venue"
},
  "geometry": {"coordinates":[4.466811,52.05632],"type":"Point"}
}