{
  "type": "Feature",
  "properties": {
    "iso:country":"NL",
    "sg:address":"J V Galenstr 72",
    "sg:city":"Schiedam",
    "sg:orig_category":"Ballonnen - Fabrieken En Groothandel",
    "sg:phone":"+31 10 273 4795",
    "sg:postcode":"3115 JG",
    "sg:province":"South Holland",
    "sg:website":"http://www.amazingballoons.nl",
    "wof:name":"Amazing Balloons",
    "wof:placetype":"venue"
},
  "geometry": {"coordinates":[4.39816,51.918472],"type":"Point"}
}