{
  "type": "Feature",
  "properties": {
    "addr:full":"Distelmeent 44 Hilversum North Holland 1218 AJ",
    "addr:housenumber":"44",
    "addr:postcode":"1218 aj",
    "addr:street":"Distelmeent",
    "iso:country":"NL",
    "sg:address":"Distelmeent 44",
    "sg:city":"Hilversum",
    "sg:orig_category":"Sportverenigingen En Ontspannings- Verenigingen",
    "sg:phone":"+31 35 693 0001",
    "sg:postcode":"1218 AJ",
    "sg:province":"North Holland",
    "sg:website":"http://www.de5dorpen.ontheweb.nl",
    "wof:name":"5 Dorpen Schaats & Hardrijdersver, De",
    "wof:placetype":"venue"
},
  "geometry": {"coordinates":[5.136374,52.275715],"type":"Point"}
}