{
  "type": "Feature",
  "properties": {
    "iso:country":"NL",
    "sg:address":"Schipholwg 925",
    "sg:city":"Boesingheliede",
    "sg:orig_category":"Kantoor- En Bedrijfsmeubelen",
    "sg:phone":"+31 23 555 2555",
    "sg:postcode":"2143 CE",
    "sg:province":"North Holland",
    "wof:name":"Euro Stoel 2000 Bv",
    "wof:placetype":"venue"
},
  "geometry": {"coordinates":[4.7231030464,52.3617591858],"type":"Point"}
}