{
  "type": "Feature",
  "properties": {
    "iso:country":"NL",
    "sg:address":"Edisonweg 6",
    "sg:city":"Vlissingen",
    "sg:orig_category":"Autokeuringen",
    "sg:phone":"+31 118 472 598",
    "sg:postcode":"4382 NW",
    "sg:province":"Zeeland",
    "wof:name":"Doe Het Zelf Garage Colijn",
    "wof:placetype":"venue"
},
  "geometry": {"coordinates":[3.589968,51.453026],"type":"Point"}
}