{
  "type": "Feature",
  "properties": {
    "iso:country":"NL",
    "sg:address":"Kleine Looiersstraat 35",
    "sg:city":"Maastricht",
    "sg:orig_category":"Binnenhuisarchitecten",
    "sg:phone":"+31 43 325 3539",
    "sg:postcode":"6211 JL",
    "sg:province":"Limburg",
    "wof:name":"Felix Interieurs Adv Bureau",
    "wof:placetype":"venue"
},
  "geometry": {"coordinates":[5.691779,50.845005],"type":"Point"}
}