{
  "type": "Feature",
  "properties": {
    "addr:full":"Ds Bleekerstr 9 Marknesse Flevoland 8316 CV",
    "addr:housenumber":"9",
    "addr:postcode":"8316 cv",
    "addr:street":"Ds Bleekerstr;Flevoland",
    "iso:country":"NL",
    "sg:address":"Ds Bleekerstr 9",
    "sg:city":"Marknesse",
    "sg:orig_category":"Ventilatiesystemen",
    "sg:phone":"+31 527 201 342",
    "sg:postcode":"8316 CV",
    "sg:province":"Flevoland",
    "sg:website":"http://www.becom.nl",
    "wof:name":"Becom Marknesse",
    "wof:placetype":"venue"
},
  "geometry": {"coordinates":[5.868624,52.711201],"type":"Point"}
}