{
  "type": "Feature",
  "properties": {
    "addr:full":"Herengr 414 Amsterdam North Holland 1017 BZ",
    "addr:housenumber":"414",
    "addr:postcode":"1017 bz",
    "iso:country":"NL",
    "sg:address":"Herengr 414",
    "sg:city":"Amsterdam",
    "sg:orig_category":"Beeldende Kunstenaars",
    "sg:phone":"+31 20 639 0147",
    "sg:postcode":"1017 BZ",
    "sg:province":"North Holland",
    "wof:name":"Hessels, Rob",
    "wof:placetype":"venue"
},
  "geometry": {"coordinates":[4.887367,52.366894],"type":"Point"}
}