{
  "type": "Feature",
  "properties": {
    "addr:full":"Hessenwg 2 Stoutenburg Utrecht 3835 PJ",
    "addr:housenumber":"2",
    "addr:postcode":"3835 pj",
    "addr:street":"Hessenwg",
    "iso:country":"NL",
    "sg:address":"Hessenwg 2",
    "sg:city":"Stoutenburg",
    "sg:orig_category":"Geluidsopnamestudio'S",
    "sg:phone":"+31 33 480 1665",
    "sg:postcode":"3835 PJ",
    "sg:province":"Utrecht",
    "wof:name":"Bombastic Productions",
    "wof:placetype":"venue"
},
  "geometry": {"coordinates":[5.426778,52.157623],"type":"Point"}
}