{
  "type": "Feature",
  "properties": {
    "addr:full":"B Buyspk 6 Deventer Overijssel 7425 GD",
    "addr:housenumber":"6",
    "addr:postcode":"7425 gd",
    "iso:country":"NL",
    "sg:address":"B Buyspk 6",
    "sg:city":"Deventer",
    "sg:orig_category":"Bedrijfsopleidingen",
    "sg:phone":"+31 570 513 724",
    "sg:postcode":"7425 GD",
    "sg:province":"Overijssel",
    "wof:name":"Nieuwkompas",
    "wof:placetype":"venue"
},
  "geometry": {"coordinates":[6.224849,52.262039],"type":"Point"}
}