{
  "type": "Feature",
  "properties": {
    "iso:country":"NL",
    "sg:address":"Oude Doetinch Wg 3",
    "sg:city":"Varsseveld",
    "sg:classifiers":[
        {
            "category":"Food & Beverages",
            "subcategory":"Fruits & Vegetables",
            "type":"Retail Goods"
        }
    ],
    "sg:phone":"+31 315 242 991",
    "sg:postcode":"7051 DZ",
    "sg:province":"Gelderland",
    "sg:tags":[
        "en",
        "groenten"
    ],
    "wof:name":"Diersen, H J",
    "wof:placetype":"venue"
},
  "geometry": {"coordinates":[6.447292,51.946831],"type":"Point"}
}