{
  "type": "Feature",
  "properties": {
    "addr:full":"Oude Doetinch Wg 3 Varsseveld Gelderland 7051 DZ",
    "addr:housenumber":"3",
    "addr:postcode":"7051 dz",
    "addr:street":"Oude;Wg;Gelderland",
    "iso:country":"NL",
    "sg:address":"Oude Doetinch Wg 3",
    "sg:city":"Varsseveld",
    "sg:classifiers":[
        {
            "category":"Food & Beverages",
            "subcategory":"Fruits & Vegetables",
            "type":"Retail Goods"
        }
    ],
    "sg:phone":"+31 315 242 991",
    "sg:postcode":"7051 DZ",
    "sg:province":"Gelderland",
    "sg:tags":[
        "en",
        "groenten"
    ],
    "wof:name":"Diersen, H J",
    "wof:placetype":"venue"
},
  "geometry": {"coordinates":[6.447292,51.946831],"type":"Point"}
}