{
  "type": "Feature",
  "properties": {
    "addr:full":"Dorpsstraat 25 Oosterhout Gld Gelderland 6678 BE",
    "addr:housenumber":"25",
    "addr:postcode":"6678",
    "addr:street":"Dorpsstraat;Gld Gelderland",
    "iso:country":"NL",
    "sg:address":"Dorpsstraat 25",
    "sg:city":"Oosterhout Gld",
    "sg:orig_category":"Kappers",
    "sg:phone":"+31 481 481 282",
    "sg:postcode":"6678 BE",
    "sg:province":"Gelderland",
    "wof:name":"Vof Dames- En Herenkapsalon A.Th.L. Van",
    "wof:placetype":"venue"
},
  "geometry": {"coordinates":[5.825294,51.878181],"type":"Point"}
}