{
  "type": "Feature",
  "properties": {
    "addr:full":"Vd Wyckpln 3B Bergen Aan Zee North Holland 1865 AN",
    "addr:housenumber":"3b",
    "addr:postcode":"1865 an",
    "iso:country":"NL",
    "sg:address":"Vd Wyckpln 3B",
    "sg:city":"Bergen Aan Zee",
    "sg:orig_category":"Vakantieverblijven",
    "sg:phone":"+31 251 658 460",
    "sg:postcode":"1865 AN",
    "sg:province":"North Holland",
    "wof:name":"Albatros",
    "wof:placetype":"venue"
},
  "geometry": {"coordinates":[4.631065,52.660343],"type":"Point"}
}