{
  "type": "Feature",
  "properties": {
    "addr:full":"De Kempenaerstraat 11 Vlissingen Zeeland 4384 KA",
    "addr:housenumber":"11",
    "addr:postcode":"4384 ka",
    "addr:street":"De Kempenaerstraat",
    "iso:country":"NL",
    "sg:address":"De Kempenaerstraat 11",
    "sg:city":"Vlissingen",
    "sg:orig_category":"Verzekeringen",
    "sg:phone":"+31 118 476 112",
    "sg:postcode":"4384 KA",
    "sg:province":"Zeeland",
    "wof:name":"K & P Cons",
    "wof:placetype":"venue"
},
  "geometry": {"coordinates":[3.550547,51.460457],"type":"Point"}
}