{
  "type": "Feature",
  "properties": {
    "addr:full":"Herculespln 353 Utrecht Utrecht 3584 AA",
    "addr:housenumber":"353",
    "addr:postcode":"3584 aa",
    "iso:country":"NL",
    "sg:address":"Herculespln 353",
    "sg:city":"Utrecht",
    "sg:orig_category":"Adviesbureaus Economie",
    "sg:phone":"+31 30 251 6163",
    "sg:postcode":"3584 AA",
    "sg:province":"Utrecht",
    "wof:name":"Landstad Bv",
    "wof:placetype":"venue"
},
  "geometry": {"coordinates":[5.14708,52.077888],"type":"Point"}
}