{
  "type": "Feature",
  "properties": {
    "addr:full":"Mozartstr 33 Groningen Groningen 9722 EB",
    "addr:housenumber":"33",
    "addr:postcode":"9722 eb",
    "addr:street":"Mozartstr",
    "iso:country":"NL",
    "sg:address":"Mozartstr 33",
    "sg:city":"Groningen",
    "sg:orig_category":"Psychotherapeuten",
    "sg:phone":"+31 50 526 7166",
    "sg:postcode":"9722 EB",
    "sg:province":"Groningen",
    "wof:name":"Gerrits, R J H",
    "wof:placetype":"venue"
},
  "geometry": {"coordinates":[6.583255,53.200619],"type":"Point"}
}