{
  "type": "Feature",
  "properties": {
    "addr:full":"St Gerlach 30A Valkenburg Lb Limburg 6301 JC",
    "addr:housenumber":"30a",
    "addr:postcode":"lb;6301 jc",
    "addr:street":"St Gerlach",
    "iso:country":"NL",
    "sg:address":"St Gerlach 30A",
    "sg:city":"Valkenburg Lb",
    "sg:orig_category":"Balletscholen",
    "sg:phone":"+31 43 459 2052",
    "sg:postcode":"6301 JC",
    "sg:province":"Limburg",
    "wof:name":"Backer, Joke De",
    "wof:placetype":"venue"
},
  "geometry": {"coordinates":[5.799388,50.871891],"type":"Point"}
}