{
  "type": "Feature",
  "properties": {
    "addr:full":"Steenbakkerswg 25 Hengelo Ov Overijssel 7553 EH",
    "addr:housenumber":"25",
    "addr:postcode":"7553 eh",
    "addr:street":"Steenbakkerswg;Ov",
    "iso:country":"NL",
    "sg:address":"Steenbakkerswg 25",
    "sg:city":"Hengelo Ov",
    "sg:orig_category":"Adviesbureaus Bedrijfsorganisatie",
    "sg:phone":"+31 74 291 1113",
    "sg:postcode":"7553 EH",
    "sg:province":"Overijssel",
    "wof:name":"Pas",
    "wof:placetype":"venue"
},
  "geometry": {"coordinates":[6.785261,52.255184],"type":"Point"}
}