{
  "type": "Feature",
  "properties": {
    "iso:country":"NL",
    "sg:address":"Delving 102",
    "sg:city":"Akersloot",
    "sg:orig_category":"Autokeuringen",
    "sg:phone":"+31 251 316 385",
    "sg:postcode":"1921 VG",
    "sg:province":"Noord-Holland",
    "wof:name":"Karst Automobielen Bv",
    "wof:placetype":"venue"
},
  "geometry": {"coordinates":[4.725598,52.555317],"type":"Point"}
}