{
  "type": "Feature",
  "properties": {
    "addr:full":"Ridderspoor 3 Elburg Gelderland 8081 DR",
    "addr:housenumber":"3",
    "addr:postcode":"8081 dr",
    "addr:street":"Ridderspoor;Gelderland",
    "iso:country":"NL",
    "sg:address":"Ridderspoor 3",
    "sg:city":"Elburg",
    "sg:orig_category":"Boekhouders",
    "sg:phone":"+31 525 685 005",
    "sg:postcode":"8081 DR",
    "sg:province":"Gelderland",
    "wof:name":"Administratie- En Adviescentrum Nagelhout B.V",
    "wof:placetype":"venue"
},
  "geometry": {"coordinates":[5.854237,52.447117],"type":"Point"}
}