{
  "type": "Feature",
  "properties": {
    "addr:full":"Henry Dunantstraat 8 Nijmegen Gelderland 6543 KR",
    "addr:housenumber":"8",
    "addr:postcode":"6543 kr",
    "addr:street":"Henry Dunantstraat;Gelderland",
    "iso:country":"NL",
    "sg:address":"Henry Dunantstraat 8",
    "sg:city":"Nijmegen",
    "sg:classifiers":[
        {
            "category":"Education",
            "subcategory":"Preschool",
            "type":"Public Place"
        }
    ],
    "sg:phone":"+31 24 377 1573",
    "sg:postcode":"6543 KR",
    "sg:province":"Gelderland",
    "sg:tags":[
        "kleuteronderwijs",
        "basis-"
    ],
    "wof:name":"Jenaplanschool De Lanteerne",
    "wof:placetype":"venue"
},
  "geometry": {"coordinates":[5.823278,51.835991],"type":"Point"}
}