{
  "type": "Feature",
  "properties": {
    "addr:full":"Droogbloem 41 Rotterdam South Holland 3068 AW",
    "addr:housenumber":"41",
    "addr:postcode":"3068 aw",
    "addr:street":"Droogbloem",
    "iso:country":"NL",
    "sg:address":"Droogbloem 41",
    "sg:city":"Rotterdam",
    "sg:orig_category":"Boekbinderijen",
    "sg:phone":"+31 10 455 5350",
    "sg:postcode":"3068 AW",
    "sg:province":"South Holland",
    "sg:website":"http://www.boekbinderij-rietveld.nl",
    "wof:name":"Rietveld Boekbinderij",
    "wof:placetype":"venue"
},
  "geometry": {"coordinates":[4.532992,51.954384],"type":"Point"}
}