{
  "type": "Feature",
  "properties": {
    "iso:country":"NL",
    "sg:address":"Castor 56",
    "sg:city":"Berkel En Rodenrijs",
    "sg:orig_category":"Kantoorartikelen",
    "sg:phone":"+31 10 511 0500",
    "sg:postcode":"2651 GW",
    "sg:province":"Zuid-Holland",
    "wof:name":"De Beer",
    "wof:placetype":"venue"
},
  "geometry": {"coordinates":[4.4856820107,52.0032424927],"type":"Point"}
}