{
  "type": "Feature",
  "properties": {
    "addr:full":"J Vd Heydenstr 50 Bleiswyk Zuid-Holland 2665 JA",
    "addr:housenumber":"50",
    "addr:postcode":"2665 ja",
    "iso:country":"NL",
    "sg:address":"J Vd Heydenstr 50",
    "sg:city":"Bleiswyk",
    "sg:orig_category":"Gasapparaten En -Artikelen",
    "sg:phone":"+31 10 521 7344",
    "sg:postcode":"2665 JA",
    "sg:province":"Zuid-Holland",
    "sg:website":"http://www.buveco.com",
    "wof:name":"Buveco Bv",
    "wof:placetype":"venue"
},
  "geometry": {"coordinates":[4.531235,52.012997],"type":"Point"}
}