{
  "type": "Feature",
  "properties": {
    "addr:full":"Van Der Capellenstraat 101 Zwolle Overijssel 8014 VW",
    "addr:housenumber":"101",
    "addr:postcode":"8014 vw",
    "addr:street":"Van Der Capellenstraat",
    "iso:country":"NL",
    "sg:address":"Van Der Capellenstraat 101",
    "sg:city":"Zwolle",
    "sg:orig_category":"Dierenspeciaalzaken",
    "sg:phone":"+31 38 465 7814",
    "sg:postcode":"8014 VW",
    "sg:province":"Overijssel",
    "wof:name":"Dierenspeciaalzaak Hilbert Jonkman",
    "wof:placetype":"venue"
},
  "geometry": {"coordinates":[6.111733,52.483074],"type":"Point"}
}