{
  "type": "Feature",
  "properties": {
    "addr:full":"Baldershof 11 Brakel Gelderland 5306 CC",
    "addr:housenumber":"11",
    "addr:postcode":"5306 cc",
    "addr:street":"Baldershof;Gelderland",
    "iso:country":"NL",
    "sg:address":"Baldershof 11",
    "sg:city":"Brakel",
    "sg:orig_category":"Banden",
    "sg:phone":"+31 418 673 952",
    "sg:postcode":"5306 CC",
    "sg:province":"Gelderland",
    "sg:website":"http://www.wieltechniek.com",
    "wof:name":"Luites Wieltechniek Vof",
    "wof:placetype":"venue"
},
  "geometry": {"coordinates":[5.090569,51.819691],"type":"Point"}
}