{
  "type": "Feature",
  "properties": {
    "addr:full":"Laveringsveen 22 Dalen Drenthe 7751 DN",
    "addr:housenumber":"22",
    "addr:postcode":"7751 dn",
    "addr:street":"Laveringsveen",
    "iso:country":"NL",
    "sg:address":"Laveringsveen 22",
    "sg:city":"Dalen",
    "sg:classifiers":[
        {
            "category":"Personal",
            "subcategory":"Nail Salon",
            "type":"Services"
        }
    ],
    "sg:phone":"+31 524 552 942",
    "sg:postcode":"7751 DN",
    "sg:province":"Drenthe",
    "sg:tags":[
        "pedicure"
    ],
    "wof:name":"Kamphuijs, Carolien",
    "wof:placetype":"venue"
},
  "geometry": {"coordinates":[6.749219,52.698753],"type":"Point"}
}