{
  "type": "Feature",
  "properties": {
    "iso:country":"NL",
    "sg:address":"Laan V Nieuw-Oost-Indie 38",
    "sg:city":"'S Gravenhage",
    "sg:orig_category":"Bloemen And Planten",
    "sg:phone":"+31 70 347 7483",
    "sg:postcode":"2593 BV",
    "sg:province":"South Holland",
    "wof:name":"Regina Decoratie",
    "wof:placetype":"venue"
},
  "geometry": {"coordinates":[4.336815,52.086769],"type":"Point"}
}