{
  "type": "Feature",
  "properties": {
    "addr:full":"Rondven 9 Maarheeze Noord-Brabant 6026 PX",
    "addr:housenumber":"9",
    "addr:postcode":"6026 px",
    "addr:street":"Rondven",
    "iso:country":"NL",
    "sg:address":"Rondven 9",
    "sg:city":"Maarheeze",
    "sg:orig_category":"Verpakkingsbedrijven",
    "sg:phone":"+31 495 599 999",
    "sg:postcode":"6026 PX",
    "sg:province":"Noord-Brabant",
    "wof:name":"Gopak Bv",
    "wof:placetype":"venue"
},
  "geometry": {"coordinates":[5.629987,51.31068],"type":"Point"}
}