{
  "type": "Feature",
  "properties": {
    "addr:full":"Mercuriusstraat 2 Sas Van Gent Zeeland 4551 LB",
    "addr:housenumber":"2",
    "addr:postcode":"4551 lb",
    "addr:street":"Mercuriusstraat",
    "iso:country":"NL",
    "sg:address":"Mercuriusstraat 2",
    "sg:city":"Sas Van Gent",
    "sg:orig_category":"Goederenvervoer Over De Weg",
    "sg:phone":"+31 115 471 751",
    "sg:postcode":"4551 LB",
    "sg:province":"Zeeland",
    "wof:name":"Bv Internationaal Transportbedrijf De Rijke",
    "wof:placetype":"venue"
},
  "geometry": {"coordinates":[3.828253,51.269344],"type":"Point"}
}