{
  "type": "Feature",
  "properties": {
    "iso:country":"NL",
    "sg:address":"De Kemphaan 25",
    "sg:city":"Sneek",
    "sg:orig_category":"Juridische Adviseurs",
    "sg:phone":"+31 515 432 222",
    "sg:postcode":"8601 ZG",
    "sg:province":"Friesland",
    "wof:name":"Roding, Dr Mr T J",
    "wof:placetype":"venue"
},
  "geometry": {"coordinates":[5.640406,53.028065],"type":"Point"}
}