{
  "type": "Feature",
  "properties": {
    "addr:full":"Nassauln 18 Delft Zuid-Holland 2628 GH",
    "addr:housenumber":"18",
    "addr:postcode":"2628 gh",
    "addr:street":"Nassauln",
    "iso:country":"NL",
    "sg:address":"Nassauln 18",
    "sg:city":"Delft",
    "sg:orig_category":"Banken",
    "sg:phone":"+31 15 270 0600",
    "sg:postcode":"2628 GH",
    "sg:province":"Zuid-Holland",
    "sg:website":"http://www.rabobank.nl",
    "wof:name":"Rabobank",
    "wof:placetype":"venue"
},
  "geometry": {"coordinates":[4.37537,52.001652],"type":"Point"}
}