{
  "type": "Feature",
  "properties": {
    "iso:country":"NL",
    "sg:address":"Lijnbaan 44",
    "sg:city":"Heemskerk",
    "sg:orig_category":"Kantoorartikelen",
    "sg:phone":"+31 251 240 434",
    "sg:postcode":"1969 NE",
    "sg:province":"Noord-Holland",
    "wof:name":"Wesjon Kantoorinrichtingen",
    "wof:placetype":"venue"
},
  "geometry": {"coordinates":[4.6536188126,52.5057029724],"type":"Point"}
}