{
  "type": "Feature",
  "properties": {
    "addr:full":"Leywg 1208 S Gravenhage South Holland 2545 HJ",
    "addr:housenumber":"1208",
    "addr:postcode":"2545 hj",
    "addr:street":"S Gravenhage",
    "iso:country":"NL",
    "sg:address":"Leywg 1208",
    "sg:city":"S Gravenhage",
    "sg:classifiers":[
        {
            "category":"Food & Beverages",
            "subcategory":"Fruits & Vegetables",
            "type":"Retail Goods"
        }
    ],
    "sg:phone":"+31 70 366 2088",
    "sg:postcode":"2545 HJ",
    "sg:province":"South Holland",
    "sg:tags":[
        "en",
        "groenten"
    ],
    "wof:name":"Derya",
    "wof:placetype":"venue"
},
  "geometry": {"coordinates":[4.27049,52.05093],"type":"Point"}
}