{
  "type": "Feature",
  "properties": {
    "addr:full":"St Jorisstr 17 Oost W Middelbeers Noord-Brabant 5091 SC",
    "addr:housenumber":"17",
    "addr:postcode":"5091 sc",
    "addr:street":"Oost W Middelbeers",
    "iso:country":"NL",
    "sg:address":"St Jorisstr 17",
    "sg:city":"Oost W Middelbeers",
    "sg:orig_category":"Meubelmakerijen",
    "sg:phone":"+31 13 514 1810",
    "sg:postcode":"5091 SC",
    "sg:province":"Noord-Brabant",
    "wof:name":"Heuvel, M Van Den",
    "wof:placetype":"venue"
},
  "geometry": {"coordinates":[-80.947441,33.624981],"type":"Point"}
}