{
  "type": "Feature",
  "properties": {
    "iso:country":"NL",
    "sg:address":"Lijster 64",
    "sg:city":"Sprang-Capelle",
    "sg:orig_category":"Goederenvervoer Over De Weg",
    "sg:phone":"+31 416 543 004",
    "sg:postcode":"5161 ST",
    "sg:province":"North Brabant",
    "wof:name":"C. Riedijk Transport",
    "wof:placetype":"venue"
},
  "geometry": {"coordinates":[5.019893,51.676491],"type":"Point"}
}