{
  "type": "Feature",
  "properties": {
    "addr:full":"Lijster 64 Sprang-Capelle North Brabant 5161 ST",
    "addr:housenumber":"64",
    "addr:postcode":"5161 st",
    "addr:street":"Lijster",
    "iso:country":"NL",
    "sg:address":"Lijster 64",
    "sg:city":"Sprang-Capelle",
    "sg:orig_category":"Goederenvervoer Over De Weg",
    "sg:phone":"+31 416 543 004",
    "sg:postcode":"5161 ST",
    "sg:province":"North Brabant",
    "wof:name":"C. Riedijk Transport",
    "wof:placetype":"venue"
},
  "geometry": {"coordinates":[5.019893,51.676491],"type":"Point"}
}