{
  "type": "Feature",
  "properties": {
    "addr:full":"N Beetsstr 84-86 Amsterdam North Holland 1053 RP",
    "addr:housenumber":"84-86",
    "addr:postcode":"1053 rp",
    "addr:street":"N",
    "iso:country":"NL",
    "sg:address":"N Beetsstr 84-86",
    "sg:city":"Amsterdam",
    "sg:orig_category":"Peuterspeelzalen",
    "sg:phone":"+31 20 618 1811",
    "sg:postcode":"1053 RP",
    "sg:province":"North Holland",
    "wof:name":"Vierhoek, De",
    "wof:placetype":"venue"
},
  "geometry": {"coordinates":[4.865793,52.364788],"type":"Point"}
}