{
  "type": "Feature",
  "properties": {
    "iso:country":"NL",
    "sg:address":"Leemskuilen 6",
    "sg:city":"Bladel",
    "sg:orig_category":"Bedrijfswagenaccessoires",
    "sg:phone":"+31 497 386 600",
    "sg:postcode":"5531 NL",
    "sg:province":"Noord-Brabant",
    "sg:website":"http://www.vingerhoets.trucks.nl",
    "wof:name":"Vingerhoets Vof, J",
    "wof:placetype":"venue"
},
  "geometry": {"coordinates":[5.211656,51.362312],"type":"Point"}
}