{
  "type": "Feature",
  "properties": {
    "iso:country":"NL",
    "sg:address":"Catharinaland 15",
    "sg:city":"S Gravenhage",
    "sg:classifiers":[
        {
            "category":"Restaurant",
            "type":"Food & Drink"
        }
    ],
    "sg:phone":"+31 70 347 4625",
    "sg:postcode":"2591 CE",
    "sg:province":"South Holland",
    "wof:name":"Lay Garden",
    "wof:placetype":"venue"
},
  "geometry": {"coordinates":[4.3639,52.09351],"type":"Point"}
}