{
  "type": "Feature",
  "properties": {
    "addr:full":"S M H V Gynwg 305 Dordrecht South Holland 3317 JL",
    "addr:housenumber":"305",
    "addr:postcode":"3317 jl",
    "addr:street":"H;Gynwg",
    "iso:country":"NL",
    "sg:address":"S M H V Gynwg 305",
    "sg:city":"Dordrecht",
    "sg:orig_category":"Voetbalverenigingen",
    "sg:phone":"+31 78 617 9946",
    "sg:postcode":"3317 JL",
    "sg:province":"South Holland",
    "wof:name":"Fluks",
    "wof:placetype":"venue"
},
  "geometry": {"coordinates":[4.656506,51.811916],"type":"Point"}
}