{
  "type": "Feature",
  "properties": {
    "addr:full":"Barendstr 13B Boskoop Zuid-Holland 2771 DJ",
    "addr:housenumber":"13b",
    "addr:postcode":"2771 dj",
    "addr:street":"Barendstr",
    "iso:country":"NL",
    "sg:address":"Barendstr 13B",
    "sg:city":"Boskoop",
    "sg:orig_category":"Bloemen En Planten - Groothandel",
    "sg:phone":"+31 172 213 252",
    "sg:postcode":"2771 DJ",
    "sg:province":"Zuid-Holland",
    "wof:name":"Teylingen, G C Van",
    "wof:placetype":"venue"
},
  "geometry": {"coordinates":[4.65976,52.07338],"type":"Point"}
}