{
  "type": "Feature",
  "properties": {
    "addr:full":"Frankestr 13 Haarlem Noord-Holland 2011 HT",
    "addr:housenumber":"13",
    "addr:postcode":"2011 ht",
    "addr:street":"Frankestr",
    "iso:country":"NL",
    "sg:address":"Frankestr 13",
    "sg:city":"Haarlem",
    "sg:orig_category":"Onderhoudswerken",
    "sg:phone":"+31 23 531 8331",
    "sg:postcode":"2011 HT",
    "sg:province":"Noord-Holland",
    "wof:name":"Herter Vof, J C",
    "wof:placetype":"venue"
},
  "geometry": {"coordinates":[4.635796,52.379642],"type":"Point"}
}