{
  "type": "Feature",
  "properties": {
    "addr:full":"Raadhuisstr 25 Berkel Enschot North Brabant 5056 HC",
    "addr:housenumber":"25",
    "addr:postcode":"5056 hc",
    "addr:street":"Raadhuisstr;Enschot",
    "iso:country":"NL",
    "sg:address":"Raadhuisstr 25",
    "sg:city":"Berkel Enschot",
    "sg:classifiers":[
        {
            "category":"Shopping",
            "subcategory":"News",
            "type":"Retail Goods"
        }
    ],
    "sg:phone":"+31 13 533 2137",
    "sg:postcode":"5056 HC",
    "sg:province":"North Brabant",
    "sg:tags":[
        "maandbladen",
        "en",
        "week-"
    ],
    "wof:name":"Zijwind, Sticht",
    "wof:placetype":"venue"
},
  "geometry": {"coordinates":[5.1394181252,51.5875549316],"type":"Point"}
}