{
  "type": "Feature",
  "properties": {
    "iso:country":"NL",
    "sg:address":"Hilsebaan 125",
    "sg:city":"Etten Leur",
    "sg:orig_category":"Melktransporten",
    "sg:phone":"+31 76 501 3417",
    "sg:postcode":"4873 LH",
    "sg:province":"North Brabant",
    "wof:name":"Buijnsters, J",
    "wof:placetype":"venue"
},
  "geometry": {"coordinates":[4.66899,51.560616],"type":"Point"}
}