{
  "type": "Feature",
  "properties": {
    "iso:country":"NL",
    "sg:address":"St Hubertus 342",
    "sg:city":"Ede Gld",
    "sg:orig_category":"Glazenwasserijen",
    "sg:phone":"+31 318 630 207",
    "sg:postcode":"6713 JK",
    "sg:province":"Gelderland",
    "wof:name":"Excellent",
    "wof:placetype":"venue"
},
  "geometry": {"coordinates":[5.64601,52.036812],"type":"Point"}
}