{
  "type": "Feature",
  "properties": {
    "addr:full":"Flintenwg 4-6 Orvelte Drenthe 9441 PC",
    "addr:housenumber":"4-6",
    "addr:postcode":"9441 pc",
    "addr:street":"Flintenwg",
    "iso:country":"NL",
    "sg:address":"Flintenwg 4-6",
    "sg:city":"Orvelte",
    "sg:orig_category":"Vakantieverblijven",
    "sg:phone":"+31 593 322 351",
    "sg:postcode":"9441 PC",
    "sg:province":"Drenthe",
    "sg:website":"http://www.borckerhof.nl",
    "wof:name":"Borckerhof Buitenverblijven, De",
    "wof:placetype":"venue"
},
  "geometry": {"coordinates":[6.657573,52.843761],"type":"Point"}
}