{
  "type": "Feature",
  "properties": {
    "iso:country":"NL",
    "sg:address":"Pr Bernhardpln 51",
    "sg:city":"Utrecht",
    "sg:orig_category":"Postkantoren",
    "sg:phone":"+31 30 244 2111",
    "sg:postcode":"3555 AL",
    "sg:province":"Utrecht",
    "sg:website":"http://www.postkantoor.nl",
    "wof:name":"Postkantoor",
    "wof:placetype":"venue"
},
  "geometry": {"coordinates":[5.08264,52.114986],"type":"Point"}
}