{
  "type": "Feature",
  "properties": {
    "addr:full":"Heienlangdonk 69 Breda North Brabant 4824 EB",
    "addr:housenumber":"69",
    "addr:postcode":"4824 eb",
    "addr:street":"Heienlangdonk",
    "iso:country":"NL",
    "sg:address":"Heienlangdonk 69",
    "sg:city":"Breda",
    "sg:orig_category":"Bedrijfsopleidingen",
    "sg:phone":"+31 76 543 9615",
    "sg:postcode":"4824 EB",
    "sg:province":"North Brabant",
    "sg:website":"http://www.imkopleidingen.nl",
    "wof:name":"Imk Bv",
    "wof:placetype":"venue"
},
  "geometry": {"coordinates":[4.750432,51.610664],"type":"Point"}
}