{
  "type": "Feature",
  "properties": {
    "iso:country":"NL",
    "sg:address":"Torenstr 31",
    "sg:city":"Joure",
    "sg:orig_category":"Kappers",
    "sg:phone":"+31 513 417 733",
    "sg:postcode":"8501 BV",
    "sg:province":"Friesland",
    "wof:name":"Headroom Kappers Joure",
    "wof:placetype":"venue"
},
  "geometry": {"coordinates":[5.7957468033,52.9692649841],"type":"Point"}
}