{
  "type": "Feature",
  "properties": {
    "addr:full":"Kade 11 Steenbergen Nb Noord-Brabant 4651 BS",
    "addr:housenumber":"11",
    "addr:postcode":"4651 bs",
    "addr:street":"Kade",
    "iso:country":"NL",
    "sg:address":"Kade 11",
    "sg:city":"Steenbergen Nb",
    "sg:orig_category":"Hypotheken",
    "sg:phone":"+31 167 561 713",
    "sg:postcode":"4651 BS",
    "sg:province":"Noord-Brabant",
    "wof:name":"Franken & Groffen",
    "wof:placetype":"venue"
},
  "geometry": {"coordinates":[4.314115,51.586311],"type":"Point"}
}