{
  "type": "Feature",
  "properties": {
    "addr:full":"Bethlehemkerkpln 38 Zwolle Overijssel 8011 PH",
    "addr:housenumber":"38",
    "addr:postcode":"8011",
    "addr:street":"Bethlehemkerkpln",
    "iso:country":"NL",
    "sg:address":"Bethlehemkerkpln 38",
    "sg:city":"Zwolle",
    "sg:orig_category":"Verenigingen En Stichtingen",
    "sg:phone":"+31 38 421 2900",
    "sg:postcode":"8011 PH",
    "sg:province":"Overijssel",
    "wof:name":"City Centr Winkeliersver",
    "wof:placetype":"venue"
},
  "geometry": {"coordinates":[6.094076,52.510777],"type":"Point"}
}