{
  "type": "Feature",
  "properties": {
    "iso:country":"NL",
    "sg:address":"Havenstr 110B",
    "sg:city":"Doetinchem",
    "sg:orig_category":"Verpakkingsbedrijven",
    "sg:phone":"+31 314 346 773",
    "sg:postcode":"7005 AG",
    "sg:province":"Gelderland",
    "wof:name":"Martens Folie Verpakker",
    "wof:placetype":"venue"
},
  "geometry": {"coordinates":[6.301159,51.948162],"type":"Point"}
}