{
  "type": "Feature",
  "properties": {
    "iso:country":"NL",
    "sg:address":"Vorsenpoel 20",
    "sg:city":"Boxtel",
    "sg:classifiers":[
        {
            "category":"Retail",
            "subcategory":"Photofinishing",
            "type":"Services"
        }
    ],
    "sg:phone":"+31 411 616 080",
    "sg:postcode":"5283 ZK",
    "sg:province":"North Brabant",
    "sg:tags":[
        "foto",
        "film"
    ],
    "wof:name":"V.C.I.",
    "wof:placetype":"venue"
},
  "geometry": {"coordinates":[5.352635,51.584534],"type":"Point"}
}