{
  "type": "Feature",
  "properties": {
    "addr:full":"Koperstr 45 Zoetermeer South Holland 2718 RG",
    "addr:housenumber":"45",
    "addr:postcode":"2718 rg",
    "addr:street":"Koperstr",
    "iso:country":"NL",
    "sg:address":"Koperstr 45",
    "sg:city":"Zoetermeer",
    "sg:orig_category":"Poeliers",
    "sg:phone":"+31 79 361 4004",
    "sg:postcode":"2718 RG",
    "sg:province":"South Holland",
    "wof:name":"Leeuwen Bv, Van",
    "wof:placetype":"venue"
},
  "geometry": {"coordinates":[4.509134,52.036751],"type":"Point"}
}