{
  "type": "Feature",
  "properties": {
    "addr:full":"Veerseveste 12 Nieuwegein Utrecht 3432 RE",
    "addr:housenumber":"12",
    "addr:postcode":"3432",
    "addr:street":"Veerseveste",
    "iso:country":"NL",
    "sg:address":"Veerseveste 12",
    "sg:city":"Nieuwegein",
    "sg:orig_category":"Schoonheidssalons",
    "sg:phone":"+31 30 604 0134",
    "sg:postcode":"3432 RE",
    "sg:province":"Utrecht",
    "wof:name":"Schoonheidssalon 'T Geintje",
    "wof:placetype":"venue"
},
  "geometry": {"coordinates":[5.096102,52.024773],"type":"Point"}
}