{
  "type": "Feature",
  "properties": {
    "addr:full":"Prof Asserstr 4 Hoensbroek Limburg 6431 TR",
    "addr:housenumber":"4",
    "addr:postcode":"6431 tr",
    "iso:country":"NL",
    "sg:address":"Prof Asserstr 4",
    "sg:city":"Hoensbroek",
    "sg:orig_category":"Verenigingsgebouwen",
    "sg:phone":"+31 45 522 6031",
    "sg:postcode":"6431 TR",
    "sg:province":"Limburg",
    "wof:name":"Biese Gatz, D'R",
    "wof:placetype":"venue"
},
  "geometry": {"coordinates":[5.940505,50.922794],"type":"Point"}
}