{
  "type": "Feature",
  "properties": {
    "addr:full":"Primulastr 25 Almelo Overijssel 7601 AS",
    "addr:housenumber":"25",
    "addr:postcode":"7601 as",
    "addr:street":"Primulastr",
    "iso:country":"NL",
    "sg:address":"Primulastr 25",
    "sg:city":"Almelo",
    "sg:orig_category":"Stukadoorsbedrijven",
    "sg:phone":"+31 6 54783747",
    "sg:postcode":"7601 AS",
    "sg:province":"Overijssel",
    "wof:name":"Ezinga, M A",
    "wof:placetype":"venue"
},
  "geometry": {"coordinates":[6.665056,52.34758],"type":"Point"}
}