{
  "type": "Feature",
  "properties": {
    "addr:full":"V Polanenpk 147 Wassenaar South Holland 2241 SJ",
    "addr:housenumber":"147",
    "addr:postcode":"2241",
    "iso:country":"NL",
    "sg:address":"V Polanenpk 147",
    "sg:city":"Wassenaar",
    "sg:orig_category":"Bloemen En Planten - Groothandel",
    "sg:phone":"+31 70 511 6271",
    "sg:postcode":"2241 SJ",
    "sg:province":"South Holland",
    "wof:name":"Horticept Bv",
    "wof:placetype":"venue"
},
  "geometry": {"coordinates":[4.393863,52.14307],"type":"Point"}
}