{
  "type": "Feature",
  "properties": {
    "addr:full":"Haarbrug 11 Bunschoten Spakenburg Utrecht 3751 LM",
    "addr:housenumber":"11",
    "addr:postcode":"3751 lm",
    "addr:street":"Haarbrug",
    "iso:country":"NL",
    "sg:address":"Haarbrug 11",
    "sg:city":"Bunschoten Spakenburg",
    "sg:orig_category":"Drukkerijen And Copyshops",
    "sg:phone":"+31 33 299 6642",
    "sg:postcode":"3751 LM",
    "sg:province":"Utrecht",
    "wof:name":"Vof Combi Offset",
    "wof:placetype":"venue"
},
  "geometry": {"coordinates":[5.378677,52.230179],"type":"Point"}
}