{
  "type": "Feature",
  "properties": {
    "iso:country":"NL",
    "sg:address":"Heugemerwg 2D",
    "sg:city":"Maastricht",
    "sg:orig_category":"Vertaalbureaus",
    "sg:phone":"+31 43 325 1269",
    "sg:postcode":"6221 GJ",
    "sg:province":"Limburg",
    "wof:name":"Avoc",
    "wof:placetype":"venue"
},
  "geometry": {"coordinates":[5.705266,50.847073],"type":"Point"}
}