{
  "type": "Feature",
  "properties": {
    "addr:full":"Zandstraat 139 Beneden Leeuwen Gelderland 6658 CS",
    "addr:housenumber":"139",
    "addr:postcode":"6658 cs",
    "addr:street":"Zandstraat",
    "iso:country":"NL",
    "sg:address":"Zandstraat 139",
    "sg:city":"Beneden Leeuwen",
    "sg:orig_category":"Bloemen And Planten",
    "sg:phone":"+31 487 591 597",
    "sg:postcode":"6658 CS",
    "sg:province":"Gelderland",
    "wof:name":"De Agave",
    "wof:placetype":"venue"
},
  "geometry": {"coordinates":[5.506868,51.880444],"type":"Point"}
}