{
  "type": "Feature",
  "properties": {
    "iso:country":"NL",
    "sg:address":"Middenwg 9",
    "sg:city":"Huizen",
    "sg:orig_category":"Opslag Inboedels",
    "sg:phone":"+31 6 50280525",
    "sg:postcode":"1271 AS",
    "sg:province":"North Holland",
    "wof:name":"Mini",
    "wof:placetype":"venue"
},
  "geometry": {"coordinates":[5.2361989021,52.298740387],"type":"Point"}
}