{
  "type": "Feature",
  "properties": {
    "addr:full":"Hengeloln 158 S Gravenhage South Holland 2545 JS",
    "addr:housenumber":"158",
    "addr:postcode":"2545 js",
    "addr:street":"S Gravenhage",
    "iso:country":"NL",
    "sg:address":"Hengeloln 158",
    "sg:city":"S Gravenhage",
    "sg:orig_category":"Bestratingen",
    "sg:phone":"+31 6 26546873",
    "sg:postcode":"2545 JS",
    "sg:province":"South Holland",
    "wof:name":"Leeuw D P Van Der",
    "wof:placetype":"venue"
},
  "geometry": {"coordinates":[4.27049,52.05093],"type":"Point"}
}