{
  "type": "Feature",
  "properties": {
    "addr:full":"Daalseweg 5 Nijmegen Gelderland 6521 GE",
    "addr:housenumber":"5",
    "addr:postcode":"6521",
    "addr:street":"Daalseweg;Gelderland",
    "iso:country":"NL",
    "sg:address":"Daalseweg 5",
    "sg:city":"Nijmegen",
    "sg:classifiers":[
        {
            "category":"Fast Food",
            "type":"Food & Drink"
        }
    ],
    "sg:phone":"+31 24 322 9771",
    "sg:postcode":"6521 GE",
    "sg:province":"Gelderland",
    "sg:tags":[
        "afhaal",
        "restaurant"
    ],
    "wof:name":"Chinees-Indisch Afhaalcentrum Diamant",
    "wof:placetype":"venue"
},
  "geometry": {"coordinates":[5.87085,51.841476],"type":"Point"}
}