{
  "type": "Feature",
  "properties": {
    "addr:full":"G Bidloostr 27 S Gravenhage Zuid-Holland 2563 XC",
    "addr:housenumber":"27;gravenhage",
    "addr:postcode":"2563 xc",
    "addr:street":"S",
    "iso:country":"NL",
    "sg:address":"G Bidloostr 27",
    "sg:city":"S Gravenhage",
    "sg:orig_category":"Architecten En Architectenbureaus",
    "sg:phone":"+31 70 365 0864",
    "sg:postcode":"2563 XC",
    "sg:province":"Zuid-Holland",
    "sg:website":"http://www.mama-architecten.nl",
    "wof:name":"Mama",
    "wof:placetype":"venue"
},
  "geometry": {"coordinates":[4.270956,52.072578],"type":"Point"}
}