{
  "type": "Feature",
  "properties": {
    "iso:country":"NL",
    "sg:address":"Baanhoek 425",
    "sg:city":"Sliedrecht",
    "sg:classifiers":[
        {
            "category":"Retail",
            "subcategory":"Storage",
            "type":"Services"
        }
    ],
    "sg:phone":"+31 6 27051532",
    "sg:postcode":"3361 GH",
    "sg:province":"South Holland",
    "sg:tags":[
        "op-",
        "en",
        "overslagbedrijven"
    ],
    "wof:name":"Independent Survey And Assistance",
    "wof:placetype":"venue"
},
  "geometry": {"coordinates":[4.737946,51.824406],"type":"Point"}
}