{
  "type": "Feature",
  "properties": {
    "iso:country":"NL",
    "sg:address":"Dorpsstraat 15",
    "sg:city":"Heerde",
    "sg:classifiers":[
        {
            "category":"Bakery",
            "type":"Food & Drink"
        }
    ],
    "sg:phone":"+31 578 691 562",
    "sg:postcode":"8181 HL",
    "sg:province":"Gelderland",
    "sg:tags":[
        "brood",
        "banket"
    ],
    "wof:name":"Banketbakkerij Tearoom Kamphorst",
    "wof:placetype":"venue"
},
  "geometry": {"coordinates":[6.041916,52.387486],"type":"Point"}
}