{
  "type": "Feature",
  "properties": {
    "addr:full":"A. Roland Holstlaan 13 Raamsdonksveer Noord-Brabant 4942 ED",
    "addr:housenumber":"13",
    "addr:postcode":"4942 ed",
    "addr:street":"A. Roland Holstlaan",
    "iso:country":"NL",
    "sg:address":"A. Roland Holstlaan 13",
    "sg:city":"Raamsdonksveer",
    "sg:classifiers":[
        {
            "category":"Retail",
            "subcategory":"Storage",
            "type":"Services"
        }
    ],
    "sg:phone":"+31 162 519 657",
    "sg:postcode":"4942 ED",
    "sg:province":"Noord-Brabant",
    "sg:tags":[
        "opslag",
        "bewaring"
    ],
    "wof:name":"Peters En Van Lopik Overslag Bv",
    "wof:placetype":"venue"
},
  "geometry": {"coordinates":[4.8758101463,51.7016639709],"type":"Point"}
}