{
  "type": "Feature",
  "properties": {
    "addr:full":"Burg Rothestr 102 Wyk Aan Zee Noord-Holland 1949 CG",
    "addr:housenumber":"102",
    "addr:postcode":"1949 cg",
    "addr:street":"Burg;Wyk Aan Zee",
    "iso:country":"NL",
    "sg:address":"Burg Rothestr 102",
    "sg:city":"Wyk Aan Zee",
    "sg:orig_category":"Administratie- En Boekhoudkantoren",
    "sg:phone":"+31 251 375 530",
    "sg:postcode":"1949 CG",
    "sg:province":"Noord-Holland",
    "wof:name":"Bodewes, C J M",
    "wof:placetype":"venue"
},
  "geometry": {"coordinates":[4.594696,52.491993],"type":"Point"}
}