{
  "type": "Feature",
  "properties": {
    "iso:country":"NL",
    "sg:address":"Van Iddekingeweg 110",
    "sg:city":"Groningen",
    "sg:orig_category":"Diverse Bedrijfsinstallaties Gh",
    "sg:phone":"+31 50 525 0952",
    "sg:postcode":"9721 CK",
    "sg:province":"Groningen",
    "wof:name":"A Mekkering",
    "wof:placetype":"venue"
},
  "geometry": {"coordinates":[6.576494,53.198078],"type":"Point"}
}