{
  "type": "Feature",
  "properties": {
    "addr:full":"Van Iddekingeweg 110 Groningen Groningen 9721 CK",
    "addr:housenumber":"110",
    "addr:postcode":"9721 ck",
    "addr:street":"Van Iddekingeweg",
    "iso:country":"NL",
    "sg:address":"Van Iddekingeweg 110",
    "sg:city":"Groningen",
    "sg:orig_category":"Diverse Bedrijfsinstallaties Gh",
    "sg:phone":"+31 50 525 0952",
    "sg:postcode":"9721 CK",
    "sg:province":"Groningen",
    "wof:name":"A Mekkering",
    "wof:placetype":"venue"
},
  "geometry": {"coordinates":[6.576494,53.198078],"type":"Point"}
}