{
  "type": "Feature",
  "properties": {
    "iso:country":"NL",
    "sg:address":"Gruttostraat 3",
    "sg:city":"Ilpendam",
    "sg:classifiers":[
        {
            "category":"Education",
            "subcategory":"Preschool",
            "type":"Public Place"
        }
    ],
    "sg:phone":"+31 20 436 1817",
    "sg:postcode":"1452 XH",
    "sg:province":"North Holland",
    "sg:tags":[
        "kleuteronderwijs",
        "basis-"
    ],
    "wof:name":"H.M. Van Randwijkschool",
    "wof:placetype":"venue"
},
  "geometry": {"coordinates":[4.951264,52.465942],"type":"Point"}
}