{
  "type": "Feature",
  "properties": {
    "iso:country":"NL",
    "sg:address":"Hamseweg 18",
    "sg:city":"Hoogland",
    "sg:orig_category":"Meubelzaken, Woning- And Keukeninrichting",
    "sg:phone":"+31 33 480 3808",
    "sg:postcode":"3828 AD",
    "sg:province":"Utrecht",
    "wof:name":"Trendhopper Hoogland Vof",
    "wof:placetype":"venue"
},
  "geometry": {"coordinates":[5.373754,52.179966],"type":"Point"}
}