{
  "type": "Feature",
  "properties": {
    "addr:full":"Horsterweg 17 Sevenum Limburg 5975 NA",
    "addr:housenumber":"17",
    "addr:postcode":"5975 na",
    "addr:street":"Horsterweg",
    "iso:country":"NL",
    "sg:address":"Horsterweg 17",
    "sg:city":"Sevenum",
    "sg:orig_category":"Autokeuringen",
    "sg:phone":"+31 77 467 1350",
    "sg:postcode":"5975 NA",
    "sg:province":"Limburg",
    "wof:name":"Garage Marcel Philipsen",
    "wof:placetype":"venue"
},
  "geometry": {"coordinates":[6.035621,51.419296],"type":"Point"}
}