{
  "type": "Feature",
  "properties": {
    "addr:full":"Levantkd 105 Amsterdam Noord-Holland 1019 MJ",
    "addr:housenumber":"105",
    "addr:postcode":"1019 mj",
    "iso:country":"NL",
    "sg:address":"Levantkd 105",
    "sg:city":"Amsterdam",
    "sg:orig_category":"Evenementenverzorging",
    "sg:phone":"+31 20 419 3737",
    "sg:postcode":"1019 MJ",
    "sg:province":"Noord-Holland",
    "wof:name":"Action Work",
    "wof:placetype":"venue"
},
  "geometry": {"coordinates":[4.939715,52.376431],"type":"Point"}
}