{
  "type": "Feature",
  "properties": {
    "addr:full":"Westeinde 13 Roelofarendsveen Zuid-Holland 2371 AS",
    "addr:housenumber":"13",
    "addr:postcode":"2371 as",
    "addr:street":"Westeinde",
    "iso:country":"NL",
    "sg:address":"Westeinde 13",
    "sg:city":"Roelofarendsveen",
    "sg:orig_category":"Zuivelproducten",
    "sg:phone":"+31 71 331 2550",
    "sg:postcode":"2371 AS",
    "sg:province":"Zuid-Holland",
    "wof:name":"Van Der Poel",
    "wof:placetype":"venue"
},
  "geometry": {"coordinates":[4.629596,52.202354],"type":"Point"}
}