{
  "type": "Feature",
  "properties": {
    "addr:full":"Gerrit Van De Lindestr 32 Rotterdam South Holland 3022 TL",
    "addr:housenumber":"32",
    "addr:postcode":"3022 tl",
    "addr:street":"Gerrit Van De Lindestr",
    "iso:country":"NL",
    "sg:address":"Gerrit Van De Lindestr 32",
    "sg:city":"Rotterdam",
    "sg:orig_category":"Fruit And Groenten Gh",
    "sg:phone":"+31 10 477 8863",
    "sg:postcode":"3022 TL",
    "sg:province":"South Holland",
    "wof:name":"H. Ozdemir Import",
    "wof:placetype":"venue"
},
  "geometry": {"coordinates":[4.451874,51.91745],"type":"Point"}
}