{
  "type": "Feature",
  "properties": {
    "addr:full":"Kerkstr 7 Ryswyk Zh Zuid-Holland 2282 BL",
    "addr:housenumber":"7",
    "addr:postcode":"2282 bl",
    "addr:street":"Kerkstr",
    "iso:country":"NL",
    "sg:address":"Kerkstr 7",
    "sg:city":"Ryswyk Zh",
    "sg:orig_category":"Sanitaire Artikelen",
    "sg:phone":"+31 70 390 2575",
    "sg:postcode":"2282 BL",
    "sg:province":"Zuid-Holland",
    "wof:name":"Mooyman",
    "wof:placetype":"venue"
},
  "geometry": {"coordinates":[4.33694,52.056503],"type":"Point"}
}