{
  "type": "Feature",
  "properties": {
    "addr:full":"Sirius 52 Klazienaveen Provincie Drenthe 7891 VG",
    "addr:housenumber":"52",
    "addr:postcode":"7891 vg",
    "addr:street":"Sirius;Provincie Drenthe",
    "iso:country":"NL",
    "sg:address":"Sirius 52",
    "sg:city":"Klazienaveen",
    "sg:orig_category":"Metaalwerken",
    "sg:phone":"+31 591 318 141",
    "sg:postcode":"7891 VG",
    "sg:province":"Provincie Drenthe",
    "wof:name":"Brands Systeemplafonds En Scheidingswand",
    "wof:placetype":"venue"
},
  "geometry": {"coordinates":[6.982375,52.732491],"type":"Point"}
}