{
  "type": "Feature",
  "properties": {
    "addr:full":"Ziel 1 Roosendaal Noord-Brabant 4704 RS",
    "addr:housenumber":"1",
    "addr:postcode":"4704 rs",
    "addr:street":"Ziel",
    "iso:country":"NL",
    "sg:address":"Ziel 1",
    "sg:city":"Roosendaal",
    "sg:orig_category":"Kabels",
    "sg:phone":"+31 165 563 300",
    "sg:postcode":"4704 RS",
    "sg:province":"Noord-Brabant",
    "wof:name":"Hof Bv, Van Der",
    "wof:placetype":"venue"
},
  "geometry": {"coordinates":[4.4578008652,51.5457191467],"type":"Point"}
}