{
  "type": "Feature",
  "properties": {
    "addr:full":"Prins Hendrikstraat 30 Egmond Aan Zee Noord-Holland 1931 BK",
    "addr:housenumber":"30",
    "addr:postcode":"1931 bk",
    "addr:street":"Prins Hendrikstraat",
    "iso:country":"NL",
    "sg:address":"Prins Hendrikstraat 30",
    "sg:city":"Egmond Aan Zee",
    "sg:orig_category":"Loodgieterswerk, Verwarming And Sanitaire Installaties",
    "sg:phone":"+31 72 506 7149",
    "sg:postcode":"1931 BK",
    "sg:province":"Noord-Holland",
    "wof:name":"J Hosmus",
    "wof:placetype":"venue"
},
  "geometry": {"coordinates":[4.630143,52.619827],"type":"Point"}
}