{
  "type": "Feature",
  "properties": {
    "addr:full":"Verlengde Hereweg 124 Groningen Groningen 9722 AJ",
    "addr:housenumber":"124",
    "addr:postcode":"9722 aj",
    "addr:street":"Verlengde Hereweg",
    "iso:country":"NL",
    "sg:address":"Verlengde Hereweg 124",
    "sg:city":"Groningen",
    "sg:orig_category":"Notarissen",
    "sg:phone":"+31 50 527 0110",
    "sg:postcode":"9722 AJ",
    "sg:province":"Groningen",
    "wof:name":"Mr. J. Cohen Notaris",
    "wof:placetype":"venue"
},
  "geometry": {"coordinates":[6.582098,53.195595],"type":"Point"}
}