{
  "type": "Feature",
  "properties": {
    "addr:full":"Postbus 116 Ede Gld Gelderland 6710 BC",
    "addr:housenumber":"116",
    "addr:postcode":"6710 bc",
    "addr:street":"Postbus;Gld Gelderland",
    "iso:country":"NL",
    "sg:address":"Postbus 116",
    "sg:city":"Ede Gld",
    "sg:orig_category":"Persoonlijke Leningen",
    "sg:phone":"+31 318 680 111",
    "sg:postcode":"6710 BC",
    "sg:province":"Gelderland",
    "wof:name":"Kredietbank Ede",
    "wof:placetype":"venue"
},
  "geometry": {"coordinates":[5.66767,52.044979],"type":"Point"}
}