{
  "type": "Feature",
  "properties": {
    "addr:full":"Fraamwg 6 Middelstum Groningen 9991 TE",
    "addr:housenumber":"6",
    "addr:postcode":"9991 te",
    "addr:street":"Fraamwg",
    "iso:country":"NL",
    "sg:address":"Fraamwg 6",
    "sg:city":"Middelstum",
    "sg:classifiers":[
        {
            "category":"Banks & Credit Unions",
            "subcategory":"Investment Brokerage",
            "type":"Services"
        }
    ],
    "sg:phone":"+31 595 551 823",
    "sg:postcode":"9991 TE",
    "sg:province":"Groningen",
    "sg:tags":[
        "pension"
    ],
    "wof:name":"Fraam",
    "wof:placetype":"venue"
},
  "geometry": {"coordinates":[6.618838,53.330208],"type":"Point"}
}