{
  "type": "Feature",
  "properties": {
    "addr:full":"Veerstr 2 Gennep Limburg 6591 BK",
    "addr:housenumber":"2",
    "addr:postcode":"6591 bk",
    "addr:street":"Veerstr",
    "iso:country":"NL",
    "sg:address":"Veerstr 2",
    "sg:city":"Gennep",
    "sg:orig_category":"Waterschappen",
    "sg:phone":"+31 485 518 162",
    "sg:postcode":"6591 BK",
    "sg:province":"Limburg",
    "wof:name":"Zuiveringschap",
    "wof:placetype":"venue"
},
  "geometry": {"coordinates":[5.9642429352,51.7043952942],"type":"Point"}
}