{
  "type": "Feature",
  "properties": {
    "addr:full":"Grotestraat 78 Drunen Noord-Brabant 5151 JG",
    "addr:housenumber":"78",
    "addr:postcode":"5151 jg",
    "addr:street":"Grotestraat",
    "iso:country":"NL",
    "sg:address":"Grotestraat 78",
    "sg:city":"Drunen",
    "sg:orig_category":"Houten Verpakkingen Fab",
    "sg:phone":"+31 416 373 758",
    "sg:postcode":"5151 JG",
    "sg:province":"Noord-Brabant",
    "wof:name":"H. Van Heeswijk",
    "wof:placetype":"venue"
},
  "geometry": {"coordinates":[5.128185,51.686539],"type":"Point"}
}