{
  "type": "Feature",
  "properties": {
    "iso:country":"NL",
    "sg:address":"Eendendonk 20",
    "sg:city":"Oosterhout Nb",
    "sg:orig_category":"Schilders",
    "sg:phone":"+31 162 464 753",
    "sg:postcode":"4907 XS",
    "sg:province":"Noord-Brabant",
    "wof:name":"Krol",
    "wof:placetype":"venue"
},
  "geometry": {"coordinates":[4.865683,51.65807],"type":"Point"}
}