{
  "type": "Feature",
  "properties": {
    "addr:full":"Eendendonk 20 Oosterhout Nb Noord-Brabant 4907 XS",
    "addr:housenumber":"20",
    "addr:postcode":"4907 xs",
    "addr:street":"Eendendonk",
    "iso:country":"NL",
    "sg:address":"Eendendonk 20",
    "sg:city":"Oosterhout Nb",
    "sg:orig_category":"Schilders",
    "sg:phone":"+31 162 464 753",
    "sg:postcode":"4907 XS",
    "sg:province":"Noord-Brabant",
    "wof:name":"Krol",
    "wof:placetype":"venue"
},
  "geometry": {"coordinates":[4.865683,51.65807],"type":"Point"}
}