{
  "type": "Feature",
  "properties": {
    "iso:country":"NL",
    "sg:address":"Voorstr 60",
    "sg:city":"Franeker",
    "sg:orig_category":"Bloemen En Planten",
    "sg:phone":"+31 517 395 657",
    "sg:postcode":"8801 LE",
    "sg:province":"Friesland",
    "wof:name":"Butterfly",
    "wof:placetype":"venue"
},
  "geometry": {"coordinates":[5.540349,53.186775],"type":"Point"}
}