{
  "type": "Feature",
  "properties": {
    "addr:full":"Engelstilstraat 3 Winschoten Groningen 9671 JE",
    "addr:housenumber":"3",
    "addr:postcode":"9671 je",
    "addr:street":"Engelstilstraat",
    "iso:country":"NL",
    "sg:address":"Engelstilstraat 3",
    "sg:city":"Winschoten",
    "sg:classifiers":[
        {
            "category":"Fast Food",
            "type":"Food & Drink"
        }
    ],
    "sg:phone":"+31 597 414 787",
    "sg:postcode":"9671 JE",
    "sg:province":"Groningen",
    "sg:tags":[
        "afhaal",
        "restaurant"
    ],
    "wof:name":"Cafe Thijs",
    "wof:placetype":"venue"
},
  "geometry": {"coordinates":[7.032723,53.146328],"type":"Point"}
}