{
  "type": "Feature",
  "properties": {
    "addr:full":"Beverveen 492 Spijkenisse Zuid-Holland 3205 AN",
    "addr:housenumber":"492",
    "addr:postcode":"3205 an",
    "addr:street":"Beverveen",
    "iso:country":"NL",
    "sg:address":"Beverveen 492",
    "sg:city":"Spijkenisse",
    "sg:orig_category":"Verhuur Catering-, Feest- En Evenementbenodigdheden",
    "sg:phone":"+31 181 641 095",
    "sg:postcode":"3205 AN",
    "sg:province":"Zuid-Holland",
    "wof:name":"H.W. Verheij Horeca Installatie Techniek",
    "wof:placetype":"venue"
},
  "geometry": {"coordinates":[4.334179,51.835335],"type":"Point"}
}