{
  "type": "Feature",
  "properties": {
    "addr:full":"Westzyde 72 Zaandam North Holland 1506 EG",
    "addr:housenumber":"72",
    "addr:postcode":"1506 eg",
    "addr:street":"Westzyde",
    "iso:country":"NL",
    "sg:address":"Westzyde 72",
    "sg:city":"Zaandam",
    "sg:orig_category":"Juweliers",
    "sg:phone":"+31 75 616 3117",
    "sg:postcode":"1506 EG",
    "sg:province":"North Holland",
    "wof:name":"Strego Bv",
    "wof:placetype":"venue"
},
  "geometry": {"coordinates":[4.808925,52.44944],"type":"Point"}
}