{
  "type": "Feature",
  "properties": {
    "addr:full":"Reigersvoortsewg 16 Toldyk Gelderland 7227 NK",
    "addr:housenumber":"16",
    "addr:postcode":"7227 nk",
    "addr:street":"Reigersvoortsewg;Gelderland",
    "iso:country":"NL",
    "sg:address":"Reigersvoortsewg 16",
    "sg:city":"Toldyk",
    "sg:orig_category":"Hoefsmederijen",
    "sg:phone":"+31 575 461 687",
    "sg:postcode":"7227 NK",
    "sg:province":"Gelderland",
    "wof:name":"Schiphorst",
    "wof:placetype":"venue"
},
  "geometry": {"coordinates":[6.258724,52.034771],"type":"Point"}
}