{
  "type": "Feature",
  "properties": {
    "addr:full":"Kerkstr 3 Ouderkerk Amstel Noord-Holland 1191 JB",
    "addr:housenumber":"3",
    "addr:postcode":"1191 jb",
    "addr:street":"Kerkstr;Ouderkerk Amstel",
    "iso:country":"NL",
    "sg:address":"Kerkstr 3",
    "sg:city":"Ouderkerk Amstel",
    "sg:orig_category":"Wereldwinkels",
    "sg:phone":"+31 20 496 5388",
    "sg:postcode":"1191 JB",
    "sg:province":"Noord-Holland",
    "wof:name":"Wereldwinkel, Sticht",
    "wof:placetype":"venue"
},
  "geometry": {"coordinates":[4.9021787643,52.2953910828],"type":"Point"}
}