{
  "type": "Feature",
  "properties": {
    "addr:full":"De Kolonie 23 Balkbrug NL.08 7707 SB",
    "addr:housenumber":"23;nl.08",
    "addr:postcode":"7707 sb",
    "addr:street":"De Kolonie",
    "iso:country":"NL",
    "sg:address":"De Kolonie 23",
    "sg:city":"Balkbrug",
    "sg:orig_category":"Bloemen And Planten",
    "sg:phone":"+31 523 612 822",
    "sg:postcode":"7707 SB",
    "sg:province":"NL.08",
    "wof:name":"De Beeksterhof",
    "wof:placetype":"venue"
},
  "geometry": {"coordinates":[6.413856,52.589577],"type":"Point"}
}