{
  "type": "Feature",
  "properties": {
    "iso:country":"NL",
    "sg:address":"Huizerweg 44",
    "sg:city":"Bussum",
    "sg:orig_category":"Werving And Selectie Van Tijdelijk Personeel And Uitzendkantoren",
    "sg:phone":"+31 35 692 2928",
    "sg:postcode":"1402 AC",
    "sg:province":"Noord-Holland",
    "wof:name":"Senior Uitzendbureau",
    "wof:placetype":"venue"
},
  "geometry": {"coordinates":[5.1699471474,52.2742424011],"type":"Point"}
}