{
  "type": "Feature",
  "properties": {
    "iso:country":"NL",
    "sg:address":"Kreijel 15",
    "sg:city":"Nederweert",
    "sg:orig_category":"Boekhouders",
    "sg:phone":"+31 495 625 435",
    "sg:postcode":"6031 AA",
    "sg:province":"Limburg",
    "wof:name":"Administratiekantoor H.M. Janssen",
    "wof:placetype":"venue"
},
  "geometry": {"coordinates":[5.76255,51.29808],"type":"Point"}
}