{
  "type": "Feature",
  "properties": {
    "addr:full":"Nw Meer 16 Zaandam Noord-Holland 1509 JJ",
    "addr:housenumber":"16",
    "addr:postcode":"1509 jj",
    "addr:street":"Nw Meer",
    "iso:country":"NL",
    "sg:address":"Nw Meer 16",
    "sg:city":"Zaandam",
    "sg:orig_category":"Autorijscholen",
    "sg:phone":"+31 75 612 2258",
    "sg:postcode":"1509 JJ",
    "sg:province":"Noord-Holland",
    "wof:name":"Marcel",
    "wof:placetype":"venue"
},
  "geometry": {"coordinates":[4.83236,52.468361],"type":"Point"}
}