{
  "type": "Feature",
  "properties": {
    "addr:full":"Zijperstraat 27-29 Alkmaar North Holland 1823 CX",
    "addr:housenumber":"27-29",
    "addr:postcode":"1823 cx",
    "addr:street":"Zijperstraat",
    "iso:country":"NL",
    "sg:address":"Zijperstraat 27-29",
    "sg:city":"Alkmaar",
    "sg:orig_category":"Onderhoud And Reparatie Kantoorapparatuur",
    "sg:phone":"+31 72 515 1611",
    "sg:postcode":"1823 CX",
    "sg:province":"North Holland",
    "wof:name":"Audio Video Service Center",
    "wof:placetype":"venue"
},
  "geometry": {"coordinates":[4.749685,52.638748],"type":"Point"}
}