{
  "type": "Feature",
  "properties": {
    "addr:full":"Liesveld 141 Vlaardingen Zuid-Holland 3131 CK",
    "addr:housenumber":"141",
    "addr:postcode":"3131 ck",
    "addr:street":"Liesveld",
    "iso:country":"NL",
    "sg:address":"Liesveld 141",
    "sg:city":"Vlaardingen",
    "sg:orig_category":"Boekenuitgeverijen",
    "sg:phone":"+31 10 434 5068",
    "sg:postcode":"3131 CK",
    "sg:province":"Zuid-Holland",
    "wof:name":"Boekenvoordeel Bv",
    "wof:placetype":"venue"
},
  "geometry": {"coordinates":[4.341625,51.91],"type":"Point"}
}