{
  "type": "Feature",
  "properties": {
    "addr:full":"Langenakker 101 Mierlo Noord-Brabant 5731 JZ",
    "addr:housenumber":"101",
    "addr:postcode":"5731 jz",
    "addr:street":"Langenakker",
    "iso:country":"NL",
    "sg:address":"Langenakker 101",
    "sg:city":"Mierlo",
    "sg:orig_category":"Verbouwingen",
    "sg:phone":"+31 492 381 044",
    "sg:postcode":"5731 JZ",
    "sg:province":"Noord-Brabant",
    "wof:name":"Bouwexact",
    "wof:placetype":"venue"
},
  "geometry": {"coordinates":[5.610235,51.43882],"type":"Point"}
}