{
  "type": "Feature",
  "properties": {
    "addr:full":"Prof Meyersln 54 Baarn Utrecht 3741 XJ",
    "addr:housenumber":"54",
    "addr:postcode":"3741 xj",
    "iso:country":"NL",
    "sg:address":"Prof Meyersln 54",
    "sg:city":"Baarn",
    "sg:orig_category":"Autopoetsbedrijven",
    "sg:phone":"+31 35 541 6913",
    "sg:postcode":"3741 XJ",
    "sg:province":"Utrecht",
    "wof:name":"Moolenaar",
    "wof:placetype":"venue"
},
  "geometry": {"coordinates":[5.276576,52.220795],"type":"Point"}
}