{
  "type": "Feature",
  "properties": {
    "iso:country":"NL",
    "sg:address":"Bergstr 45",
    "sg:city":"Deventer",
    "sg:orig_category":"Hulpverlening Sociaal",
    "sg:phone":"+31 570 615 116",
    "sg:postcode":"7411 ES",
    "sg:province":"NL.08",
    "wof:name":"Coach Deventer",
    "wof:placetype":"venue"
},
  "geometry": {"coordinates":[6.162308,52.252037],"type":"Point"}
}