{
  "type": "Feature",
  "properties": {
    "iso:country":"NL",
    "sg:address":"Simon Stevinweg 1",
    "sg:city":"Zwolle",
    "sg:orig_category":"Autokeuringen",
    "sg:phone":"+31 38 465 3153",
    "sg:postcode":"8013 NA",
    "sg:province":"NL.08",
    "wof:name":"Schadenet Rothuijsen",
    "wof:placetype":"venue"
},
  "geometry": {"coordinates":[6.127233,52.489281],"type":"Point"}
}