{
  "type": "Feature",
  "properties": {
    "addr:full":"Voordijk 39 Vlijmen North Brabant 5251 VE",
    "addr:housenumber":"39",
    "addr:postcode":"5251",
    "addr:street":"Voordijk;Ve",
    "iso:country":"NL",
    "sg:address":"Voordijk 39",
    "sg:city":"Vlijmen",
    "sg:orig_category":"Medische And Orthopedische Artikelen",
    "sg:phone":"+31 73 511 4634",
    "sg:postcode":"5251 VE",
    "sg:province":"North Brabant",
    "wof:name":"Van Den Borne Orthopedie",
    "wof:placetype":"venue"
},
  "geometry": {"coordinates":[5.225918,51.707588],"type":"Point"}
}