{
  "type": "Feature",
  "properties": {
    "addr:full":"Sperwerln 22 Bilthoven Utrecht 3722 XB",
    "addr:housenumber":"22",
    "addr:postcode":"3722 xb",
    "addr:street":"Sperwerln",
    "iso:country":"NL",
    "sg:address":"Sperwerln 22",
    "sg:city":"Bilthoven",
    "sg:orig_category":"Zonweringen",
    "sg:phone":"+31 30 228 5906",
    "sg:postcode":"3722 XB",
    "sg:province":"Utrecht",
    "wof:name":"Deka",
    "wof:placetype":"venue"
},
  "geometry": {"coordinates":[5.21093,52.121498],"type":"Point"}
}