{
  "type": "Feature",
  "properties": {
    "iso:country":"NL",
    "sg:address":"Ryksstrwg 269",
    "sg:city":"Leersum",
    "sg:orig_category":"Adviesbureaus",
    "sg:phone":"+31 343 469 929",
    "sg:postcode":"3956 CP",
    "sg:province":"Utrecht",
    "sg:website":"http://www.v2bo.nl",
    "wof:name":"V2Bo",
    "wof:placetype":"venue"
},
  "geometry": {"coordinates":[5.43237,52.010792],"type":"Point"}
}