{
  "type": "Feature",
  "properties": {
    "addr:full":"Nijbroekseweg 9 Apeldoorn Gelderland 7323 RE",
    "addr:housenumber":"9",
    "addr:postcode":"7323",
    "addr:street":"Nijbroekseweg;Gelderland",
    "iso:country":"NL",
    "sg:address":"Nijbroekseweg 9",
    "sg:city":"Apeldoorn",
    "sg:orig_category":"Bloemen And Planten",
    "sg:phone":"+31 55 366 0629",
    "sg:postcode":"7323 RE",
    "sg:province":"Gelderland",
    "wof:name":"Vof Kwekerij Jos Albers",
    "wof:placetype":"venue"
},
  "geometry": {"coordinates":[5.995126,52.233513],"type":"Point"}
}