{
  "type": "Feature",
  "properties": {
    "addr:full":"Ankerstr 17 Dronten Flevoland 8251 XE",
    "addr:housenumber":"17",
    "addr:postcode":"8251 xe",
    "addr:street":"Ankerstr;Flevoland",
    "iso:country":"NL",
    "sg:address":"Ankerstr 17",
    "sg:city":"Dronten",
    "sg:orig_category":"Wasmachines En Wasdrogers - Onderhoud En Reparatie",
    "sg:phone":"+31 321 315 683",
    "sg:postcode":"8251 XE",
    "sg:province":"Flevoland",
    "wof:name":"A Class Witgoedsnelservice",
    "wof:placetype":"venue"
},
  "geometry": {"coordinates":[5.7212929726,52.5198783875],"type":"Point"}
}