{
  "type": "Feature",
  "properties": {
    "addr:full":"Hogeweg 7 Zaltbommel Gelderland 5301 LB",
    "addr:housenumber":"7",
    "addr:postcode":"5301 lb",
    "addr:street":"Hogeweg;Gelderland",
    "iso:country":"NL",
    "sg:address":"Hogeweg 7",
    "sg:city":"Zaltbommel",
    "sg:orig_category":"Kantoorapparatuur Gh",
    "sg:phone":"+31 418 682 222",
    "sg:postcode":"5301 LB",
    "sg:province":"Gelderland",
    "wof:name":"Holland Office Group",
    "wof:placetype":"venue"
},
  "geometry": {"coordinates":[5.2562999725,51.8010101318],"type":"Point"}
}