{
  "type": "Feature",
  "properties": {
    "addr:full":"Koningin Wilhelminalaan 2 Ouderkerk A/D Amstel North Holland 1191 BT",
    "addr:housenumber":"2;a / d",
    "addr:postcode":"1191 bt",
    "addr:street":"Koningin Wilhelminalaan;Amstel North",
    "iso:country":"NL",
    "sg:address":"Koningin Wilhelminalaan 2",
    "sg:city":"Ouderkerk A/D Amstel",
    "sg:classifiers":[
        {
            "category":"Education",
            "subcategory":"Preschool",
            "type":"Public Place"
        }
    ],
    "sg:phone":"+31 20 496 3476",
    "sg:postcode":"1191 BT",
    "sg:province":"North Holland",
    "sg:tags":[
        "kleuteronderwijs",
        "basis-"
    ],
    "wof:name":"Jan Hekmanschool",
    "wof:placetype":"venue"
},
  "geometry": {"coordinates":[4.905707,52.296673],"type":"Point"}
}