{
  "type": "Feature",
  "properties": {
    "iso:country":"NL",
    "sg:address":"Mouterspad 70",
    "sg:city":"Weesp",
    "sg:orig_category":"Autorijscholen",
    "sg:phone":"+31 294 418 240",
    "sg:postcode":"1383 DL",
    "sg:province":"North Holland",
    "wof:name":"Rijst, Guus",
    "wof:placetype":"venue"
},
  "geometry": {"coordinates":[5.039745,52.297771],"type":"Point"}
}