{
  "type": "Feature",
  "properties": {
    "addr:full":"Kanaaldk Z 1 Eindhoven North Brabant 5643 TZ",
    "addr:housenumber":"1",
    "addr:postcode":"5643 tz",
    "iso:country":"NL",
    "sg:address":"Kanaaldk Z 1",
    "sg:city":"Eindhoven",
    "sg:orig_category":"Autoschade- Herstelbedrijven",
    "sg:phone":"+31 40 214 6444",
    "sg:postcode":"5643 TZ",
    "sg:province":"North Brabant",
    "wof:name":"Kade, De",
    "wof:placetype":"venue"
},
  "geometry": {"coordinates":[5.501986,51.434875],"type":"Point"}
}