{
  "type": "Feature",
  "properties": {
    "iso:country":"NL",
    "sg:address":"Anton De Haenstraat 6",
    "sg:city":"'S Gravenhage",
    "sg:orig_category":"Beveiligingsdiensten And Bewakingsbedrijven",
    "sg:phone":"+31 70 361 7498",
    "sg:postcode":"2563 BS",
    "sg:province":"South Holland",
    "wof:name":"Pendawa",
    "wof:placetype":"venue"
},
  "geometry": {"coordinates":[4.271636,52.074951],"type":"Point"}
}