{
  "type": "Feature",
  "properties": {
    "addr:full":"Holtien 6 Dwingeloo Drenthe 7991 PN",
    "addr:housenumber":"6",
    "addr:postcode":"7991 pn",
    "addr:street":"Holtien",
    "iso:country":"NL",
    "sg:address":"Holtien 6",
    "sg:city":"Dwingeloo",
    "sg:orig_category":"Verenigingen En Stichtingen",
    "sg:phone":"+31 521 591 133",
    "sg:postcode":"7991 PN",
    "sg:province":"Drenthe",
    "sg:website":"http://www.mascotte.nl",
    "wof:name":"Mascotte, De",
    "wof:placetype":"venue"
},
  "geometry": {"coordinates":[6.398201,52.852489],"type":"Point"}
}