{
  "type": "Feature",
  "properties": {
    "addr:full":"Allendeln 8 , (Mobiele Telefoon) Epe Gelderland 8161 DA",
    "addr:housenumber":"8",
    "addr:postcode":"8161 da",
    "addr:street":"Allendeln;Telefoon;Gelderland",
    "iso:country":"NL",
    "sg:address":"Allendeln 8 , (Mobiele Telefoon)",
    "sg:city":"Epe",
    "sg:orig_category":"Adviesbureaus Bedrijfsorganisatie",
    "sg:phone":"+31 6 53731582",
    "sg:postcode":"8161 DA",
    "sg:province":"Gelderland",
    "wof:name":"Shem Bv",
    "wof:placetype":"venue"
},
  "geometry": {"coordinates":[5.983639,52.339256],"type":"Point"}
}