{
  "type": "Feature",
  "properties": {
    "addr:full":"Oostdk 37A Hellevoetsluis South Holland 3224 AK",
    "addr:housenumber":"37a",
    "addr:postcode":"3224 ak",
    "addr:street":"Oostdk",
    "iso:country":"NL",
    "sg:address":"Oostdk 37A",
    "sg:city":"Hellevoetsluis",
    "sg:orig_category":"Meubelstoffering",
    "sg:phone":"+31 181 320 867",
    "sg:postcode":"3224 AK",
    "sg:province":"South Holland",
    "wof:name":"Hazelbag",
    "wof:placetype":"venue"
},
  "geometry": {"coordinates":[4.152125,51.831684],"type":"Point"}
}