{
  "type": "Feature",
  "properties": {
    "addr:full":"T Rietlandt 2 Westervoort Gelderland 6932 JB",
    "addr:housenumber":"2",
    "addr:postcode":"6932 jb",
    "addr:street":"T Rietlandt;Gelderland",
    "iso:country":"NL",
    "sg:address":"T Rietlandt 2",
    "sg:city":"Westervoort",
    "sg:orig_category":"Gehandicapteninformatie",
    "sg:phone":"+31 26 312 0165",
    "sg:postcode":"6932 JB",
    "sg:province":"Gelderland",
    "wof:name":"Dovenpastoraat Teksttelefoon",
    "wof:placetype":"venue"
},
  "geometry": {"coordinates":[5.972004,51.949738],"type":"Point"}
}