{
  "type": "Feature",
  "properties": {
    "addr:full":"Postbus 218 Heerhugowaard Noord-Holland 1700 AE",
    "addr:housenumber":"218",
    "addr:postcode":"1700 ae",
    "addr:street":"Postbus",
    "iso:country":"NL",
    "sg:address":"Postbus 218",
    "sg:city":"Heerhugowaard",
    "sg:orig_category":"Verenigingen En Stichtingen",
    "sg:phone":"+31 72 574 6857",
    "sg:postcode":"1700 AE",
    "sg:province":"Noord-Holland",
    "wof:name":"Facit/Sigin",
    "wof:placetype":"venue"
},
  "geometry": {"coordinates":[4.827522,52.665195],"type":"Point"}
}