{
  "type": "Feature",
  "properties": {
    "addr:full":"Schiedamsedk 77 Rotterdam Zuid-Holland 3011 EM",
    "addr:housenumber":"77",
    "addr:postcode":"3011 em",
    "addr:street":"Schiedamsedk",
    "iso:country":"NL",
    "sg:address":"Schiedamsedk 77",
    "sg:city":"Rotterdam",
    "sg:orig_category":"Geluidsbanden - Fabrieken En Groothandel",
    "sg:phone":"+31 10 214 1220",
    "sg:postcode":"3011 EM",
    "sg:province":"Zuid-Holland",
    "sg:website":"http://www.tapes.nl",
    "wof:name":"Tapes",
    "wof:placetype":"venue"
},
  "geometry": {"coordinates":[4.481646,51.914597],"type":"Point"}
}