{
  "type": "Feature",
  "properties": {
    "iso:country":"NL",
    "sg:address":"Ringersstraat 11",
    "sg:city":"Schiedam",
    "sg:orig_category":"Goederenvervoer Over De Weg",
    "sg:phone":"+31 10 262 2080",
    "sg:postcode":"3125 BP",
    "sg:province":"Zuid-Holland",
    "wof:name":"Van De Water Transport Bv",
    "wof:placetype":"venue"
},
  "geometry": {"coordinates":[4.404446,51.932697],"type":"Point"}
}