{
  "type": "Feature",
  "properties": {
    "addr:full":"Adrianusplein 2 Sint Michielsgestel Noord-Brabant 5271 BN",
    "addr:housenumber":"2;michielsgestel",
    "addr:postcode":"5271 bn",
    "addr:street":"Adrianusplein",
    "iso:country":"NL",
    "sg:address":"Adrianusplein 2",
    "sg:city":"Sint Michielsgestel",
    "sg:orig_category":"Binnenhuisarchitecten",
    "sg:phone":"+31 73 551 3953",
    "sg:postcode":"5271 BN",
    "sg:province":"Noord-Brabant",
    "wof:name":"Int. Adviesburo Lathouwers St.Michielsgestel",
    "wof:placetype":"venue"
},
  "geometry": {"coordinates":[5.349791,51.637787],"type":"Point"}
}