{
  "type": "Feature",
  "properties": {
    "addr:full":"Brinkln 7 Bussum North Holland 1404 EP",
    "addr:housenumber":"7",
    "addr:postcode":"1404 ep",
    "addr:street":"Brinkln",
    "iso:country":"NL",
    "sg:address":"Brinkln 7",
    "sg:city":"Bussum",
    "sg:orig_category":"Verenigingen En Stichtingen",
    "sg:phone":"+31 35 691 9191",
    "sg:postcode":"1404 EP",
    "sg:province":"North Holland",
    "wof:name":"Ssig, Sticht",
    "wof:placetype":"venue"
},
  "geometry": {"coordinates":[5.1625847816,52.2819824219],"type":"Point"}
}