{
  "type": "Feature",
  "properties": {
    "addr:full":"Bagynestr 16 Ochten Gelderland 4051 AL",
    "addr:housenumber":"16",
    "addr:postcode":"4051",
    "addr:street":"Bagynestr;Gelderland",
    "iso:country":"NL",
    "sg:address":"Bagynestr 16",
    "sg:city":"Ochten",
    "sg:orig_category":"Loodgieters",
    "sg:phone":"+31 344 642 884",
    "sg:postcode":"4051 AL",
    "sg:province":"Gelderland",
    "wof:name":"Laar Installatiebedrijf, Van",
    "wof:placetype":"venue"
},
  "geometry": {"coordinates":[5.563937,51.90757],"type":"Point"}
}