{
  "type": "Feature",
  "properties": {
    "addr:full":"Kolfbaanstr 42 Breda Noord-Brabant 4814 CM",
    "addr:housenumber":"42",
    "addr:postcode":"4814 cm",
    "addr:street":"Kolfbaanstr",
    "iso:country":"NL",
    "sg:address":"Kolfbaanstr 42",
    "sg:city":"Breda",
    "sg:orig_category":"Webdesign Bureaus",
    "sg:phone":"+31 6 29478385",
    "sg:postcode":"4814 CM",
    "sg:province":"Noord-Brabant",
    "sg:website":"http://www.tobeontheweb.nl",
    "wof:name":"To Be On The Web",
    "wof:placetype":"venue"
},
  "geometry": {"coordinates":[4.7586460114,51.5849494934],"type":"Point"}
}