{
  "type": "Feature",
  "properties": {
    "addr:full":"Bonnwg 131 Vlaardingen Zuid-Holland 3137 NH",
    "addr:housenumber":"131",
    "addr:postcode":"3137 nh",
    "iso:country":"NL",
    "sg:address":"Bonnwg 131",
    "sg:city":"Vlaardingen",
    "sg:orig_category":"Kappers",
    "sg:phone":"+31 10 460 3103",
    "sg:postcode":"3137 NH",
    "sg:province":"Zuid-Holland",
    "wof:name":"Mo",
    "wof:placetype":"venue"
},
  "geometry": {"coordinates":[4.353489,51.936798],"type":"Point"}
}