{
  "type": "Feature",
  "properties": {
    "addr:full":"Boomkamp 16 Rijssen NL.08 7461 AX",
    "addr:housenumber":"16;nl.08",
    "addr:postcode":"7461 ax",
    "addr:street":"Boomkamp",
    "iso:country":"NL",
    "sg:address":"Boomkamp 16",
    "sg:city":"Rijssen",
    "sg:orig_category":"Woningbouwverenigingen",
    "sg:phone":"+31 548 513 612",
    "sg:postcode":"7461 AX",
    "sg:province":"NL.08",
    "wof:name":"Christelijke Woningb.Ver. De Goede Wonin",
    "wof:placetype":"venue"
},
  "geometry": {"coordinates":[6.5202260017,52.3095588684],"type":"Point"}
}