{
  "type": "Feature",
  "properties": {
    "addr:full":"Hoofdstraat 211 Hoogeveen Drenthe 7902 EH",
    "addr:housenumber":"211",
    "addr:postcode":"7902 eh",
    "addr:street":"Hoofdstraat",
    "iso:country":"NL",
    "sg:address":"Hoofdstraat 211",
    "sg:city":"Hoogeveen",
    "sg:orig_category":"Fotolaboratoria",
    "sg:phone":"+31 528 227 027",
    "sg:postcode":"7902 EH",
    "sg:province":"Drenthe",
    "wof:name":"Hema",
    "wof:placetype":"venue"
},
  "geometry": {"coordinates":[6.477841,52.721619],"type":"Point"}
}