{
  "type": "Feature",
  "properties": {
    "addr:full":"Oosterduinwg 211 Aerdenhout North Holland 2111 XG",
    "addr:housenumber":"211",
    "addr:postcode":"2111 xg",
    "iso:country":"NL",
    "sg:address":"Oosterduinwg 211",
    "sg:city":"Aerdenhout",
    "sg:orig_category":"Kantoor- En Secretariaatsservice",
    "sg:phone":"+31 23 524 1047",
    "sg:postcode":"2111 XG",
    "sg:province":"North Holland",
    "wof:name":"Patell",
    "wof:placetype":"venue"
},
  "geometry": {"coordinates":[4.6036348343,52.3667755127],"type":"Point"}
}