{
  "type": "Feature",
  "properties": {
    "addr:full":"Breikom 23 Oosterwolde Fr Friesland 8431 BM",
    "addr:housenumber":"23",
    "addr:postcode":"8431 bm",
    "addr:street":"Breikom",
    "iso:country":"NL",
    "sg:address":"Breikom 23",
    "sg:city":"Oosterwolde Fr",
    "sg:orig_category":"Modelbouw",
    "sg:phone":"+31 516 520 755",
    "sg:postcode":"8431 BM",
    "sg:province":"Friesland",
    "sg:website":"http://mypage.goplay.com/spoorhobby/",
    "wof:name":"Huisman",
    "wof:placetype":"venue"
},
  "geometry": {"coordinates":[6.284268,52.985474],"type":"Point"}
}