{
  "type": "Feature",
  "properties": {
    "addr:full":"T Nyhof 47 Enschede NL.08 7522 AD",
    "addr:housenumber":"47",
    "addr:postcode":"7522 ad",
    "iso:country":"NL",
    "sg:address":"T Nyhof 47",
    "sg:city":"Enschede",
    "sg:orig_category":"Bedrijfsopleidingen",
    "sg:phone":"+31 53 436 4721",
    "sg:postcode":"7522 AD",
    "sg:province":"NL.08",
    "sg:website":"http://www.zoezi.nl",
    "wof:name":"Zo?zi",
    "wof:placetype":"venue"
},
  "geometry": {"coordinates":[6.875887,52.229279],"type":"Point"}
}