{
  "type": "Feature",
  "properties": {
    "addr:full":"Walstraat 24 Ravenstein Noord-Brabant 5371 AM",
    "addr:housenumber":"24",
    "addr:postcode":"5371",
    "addr:street":"Walstraat",
    "iso:country":"NL",
    "sg:address":"Walstraat 24",
    "sg:city":"Ravenstein",
    "sg:orig_category":"Paramedische Behandelingen",
    "sg:phone":"+31 486 412 767",
    "sg:postcode":"5371 AM",
    "sg:province":"Noord-Brabant",
    "wof:name":"6M. Oosterbaan",
    "wof:placetype":"venue"
},
  "geometry": {"coordinates":[5.65251,51.795937],"type":"Point"}
}