{
  "type": "Feature",
  "properties": {
    "iso:country":"NL",
    "sg:address":"Gravenhof 2",
    "sg:city":"Raamsdonk",
    "sg:orig_category":"Metaalbekleding And -Behandeling",
    "sg:phone":"+31 162 521 161",
    "sg:postcode":"4944 VM",
    "sg:province":"Noord-Brabant",
    "wof:name":"Joosen Techniek",
    "wof:placetype":"venue"
},
  "geometry": {"coordinates":[4.904265,51.690262],"type":"Point"}
}