{
  "type": "Feature",
  "properties": {
    "iso:country":"NL",
    "sg:address":"Groot Wezenland 12",
    "sg:city":"Zwolle",
    "sg:orig_category":"Bruidskleding",
    "sg:phone":"+31 38 422 9684",
    "sg:postcode":"8011 JV",
    "sg:province":"Overijssel",
    "wof:name":"Atelier Baris Design",
    "wof:placetype":"venue"
},
  "geometry": {"coordinates":[6.097057,52.508457],"type":"Point"}
}