{
  "type": "Feature",
  "properties": {
    "iso:country":"NL",
    "sg:address":"Soestdyksewg Z 87 B6",
    "sg:city":"De Bilt",
    "sg:orig_category":"Journalisten Freelance",
    "sg:phone":"+31 30 220 4940",
    "sg:postcode":"3732 HE",
    "sg:province":"Utrecht",
    "wof:name":"Goos",
    "wof:placetype":"venue"
},
  "geometry": {"coordinates":[5.179905,52.108021],"type":"Point"}
}