{
  "type": "Feature",
  "properties": {
    "addr:full":"Rugbystr 26 Rotterdam South Holland 3078 ZH",
    "addr:housenumber":"26",
    "addr:postcode":"3078 zh",
    "addr:street":"Rugbystr",
    "iso:country":"NL",
    "sg:address":"Rugbystr 26",
    "sg:city":"Rotterdam",
    "sg:orig_category":"Woningstoffeerders",
    "sg:phone":"+31 10 483 4751",
    "sg:postcode":"3078 ZH",
    "sg:province":"South Holland",
    "wof:name":"Duerings",
    "wof:placetype":"venue"
},
  "geometry": {"coordinates":[4.5342140198,51.8937606812],"type":"Point"}
}