{
  "type": "Feature",
  "properties": {
    "addr:full":"Amer 23 Gemert North Brabant 5422 VP",
    "addr:housenumber":"23",
    "addr:postcode":"5422 vp",
    "addr:street":"Amer",
    "iso:country":"NL",
    "sg:address":"Amer 23",
    "sg:city":"Gemert",
    "sg:orig_category":"Metaalbewerking",
    "sg:phone":"+31 492 366 503",
    "sg:postcode":"5422 VP",
    "sg:province":"North Brabant",
    "wof:name":"Kanters",
    "wof:placetype":"venue"
},
  "geometry": {"coordinates":[5.706564,51.563896],"type":"Point"}
}