{
  "type": "Feature",
  "properties": {
    "iso:country":"NL",
    "sg:address":"Heisteeg 4",
    "sg:city":"Amsterdam",
    "sg:orig_category":"Antiekzaken",
    "sg:phone":"+31 20 626 5462",
    "sg:postcode":"1012 WC",
    "sg:province":"Noord-Holland",
    "wof:name":"May Antiekhandel",
    "wof:placetype":"venue"
},
  "geometry": {"coordinates":[4.888435,52.368938],"type":"Point"}
}