{
  "type": "Feature",
  "properties": {
    "iso:country":"NL",
    "sg:address":"Rembrandtln 51",
    "sg:city":"Ryen",
    "sg:orig_category":"Fitnesscentra",
    "sg:phone":"+31 161 224 739",
    "sg:postcode":"5121 WK",
    "sg:province":"Noord-Brabant",
    "wof:name":"Jan Smeekens",
    "wof:placetype":"venue"
},
  "geometry": {"coordinates":[4.9197,51.588017],"type":"Point"}
}