{
  "type": "Feature",
  "properties": {
    "addr:full":"Rembrandtln 51 Ryen Noord-Brabant 5121 WK",
    "addr:housenumber":"51",
    "addr:postcode":"5121 wk",
    "addr:street":"Rembrandtln",
    "iso:country":"NL",
    "sg:address":"Rembrandtln 51",
    "sg:city":"Ryen",
    "sg:orig_category":"Fitnesscentra",
    "sg:phone":"+31 161 224 739",
    "sg:postcode":"5121 WK",
    "sg:province":"Noord-Brabant",
    "wof:name":"Jan Smeekens",
    "wof:placetype":"venue"
},
  "geometry": {"coordinates":[4.9197,51.588017],"type":"Point"}
}