{
  "type": "Feature",
  "properties": {
    "iso:country":"NL",
    "sg:address":"Zeisterwg 44",
    "sg:city":"Odyk",
    "sg:orig_category":"Verenigingsgebouwen",
    "sg:phone":"+31 30 656 2769",
    "sg:postcode":"3984 NM",
    "sg:province":"Utrecht",
    "wof:name":"Sticht Dorpshuis De Nieuwe Haven",
    "wof:placetype":"venue"
},
  "geometry": {"coordinates":[5.236023,52.049305],"type":"Point"}
}