{
  "type": "Feature",
  "properties": {
    "addr:full":"Coolwyksewg 10 Heenvliet Zuid-Holland 3218 VC",
    "addr:housenumber":"10",
    "addr:postcode":"3218 vc",
    "addr:street":"Coolwyksewg",
    "iso:country":"NL",
    "sg:address":"Coolwyksewg 10",
    "sg:city":"Heenvliet",
    "sg:orig_category":"Kunstnijverheid",
    "sg:phone":"+31 181 661 690",
    "sg:postcode":"3218 VC",
    "sg:province":"Zuid-Holland",
    "wof:name":"Santh\u00e9",
    "wof:placetype":"venue"
},
  "geometry": {"coordinates":[4.244195,51.86858],"type":"Point"}
}