{
  "type": "Feature",
  "properties": {
    "iso:country":"NL",
    "sg:address":"Lindeln 8B",
    "sg:city":"Bussum",
    "sg:orig_category":"Manueel Therapeuten",
    "sg:phone":"+31 35 655 0997",
    "sg:postcode":"1405 AJ",
    "sg:province":"Noord-Holland",
    "wof:name":"Saane, F Van",
    "wof:placetype":"venue"
},
  "geometry": {"coordinates":[5.158211,52.276634],"type":"Point"}
}