{
  "type": "Feature",
  "properties": {
    "addr:full":"Vliet 17 Gemert North Brabant 5422 VV",
    "addr:housenumber":"17",
    "addr:postcode":"5422 vv",
    "addr:street":"Vliet",
    "iso:country":"NL",
    "sg:address":"Vliet 17",
    "sg:city":"Gemert",
    "sg:orig_category":"Milieu",
    "sg:phone":"+31 492 322 437",
    "sg:postcode":"5422 VV",
    "sg:province":"North Brabant",
    "sg:website":"http://www.r-r-systems.nl",
    "wof:name":"R & R Systems Bv",
    "wof:placetype":"venue"
},
  "geometry": {"coordinates":[5.709203,51.567307],"type":"Point"}
}