{
  "type": "Feature",
  "properties": {
    "addr:full":"Kolkstg 8 Amsterdam North Holland 1012 PT",
    "addr:housenumber":"8",
    "addr:postcode":"1012 pt",
    "addr:street":"Kolkstg",
    "iso:country":"NL",
    "sg:address":"Kolkstg 8",
    "sg:city":"Amsterdam",
    "sg:orig_category":"Fotojournalisten Freelance",
    "sg:phone":"+31 20 320 6666",
    "sg:postcode":"1012 PT",
    "sg:province":"North Holland",
    "sg:website":"http://www.photofactory.nl",
    "wof:name":"Hommel, R De",
    "wof:placetype":"venue"
},
  "geometry": {"coordinates":[4.895392,52.376305],"type":"Point"}
}