{
  "type": "Feature",
  "properties": {
    "addr:full":"Stationsplein 1 Dordrecht South Holland 3311 JV",
    "addr:housenumber":"1",
    "addr:postcode":"3311 jv",
    "addr:street":"Stationsplein",
    "iso:country":"NL",
    "sg:address":"Stationsplein 1",
    "sg:city":"Dordrecht",
    "sg:orig_category":"Bloemen And Planten",
    "sg:phone":"+31 78 613 2739",
    "sg:postcode":"3311 JV",
    "sg:province":"South Holland",
    "wof:name":"Bloemenboetiek Tisserand",
    "wof:placetype":"venue"
},
  "geometry": {"coordinates":[4.668351,51.807392],"type":"Point"}
}