{
  "type": "Feature",
  "properties": {
    "iso:country":"NL",
    "sg:address":"Mariahoek 1",
    "sg:city":"Utrecht",
    "sg:orig_category":"Vakorganisaties",
    "sg:phone":"+31 30 233 6000",
    "sg:postcode":"3511 LD",
    "sg:province":"Utrecht",
    "wof:name":"Fnv",
    "wof:placetype":"venue"
},
  "geometry": {"coordinates":[5.115696,52.089458],"type":"Point"}
}