{
  "type": "Feature",
  "properties": {
    "iso:country":"NL",
    "sg:address":"Karskamp 2",
    "sg:city":"Warnsveld",
    "sg:classifiers":[
        {
            "category":"Education",
            "subcategory":"Preschool",
            "type":"Public Place"
        }
    ],
    "sg:phone":"+31 575 526 541",
    "sg:postcode":"7232 BD",
    "sg:province":"Gelderland",
    "sg:tags":[
        "kleuteronderwijs",
        "basis-"
    ],
    "wof:name":"Openbare Basisschool Het Forum",
    "wof:placetype":"venue"
},
  "geometry": {"coordinates":[6.231991,52.130543],"type":"Point"}
}