{
  "type": "Feature",
  "properties": {
    "addr:full":"Ryksstrwg 105 Haren Gn Groningen 9752 BA",
    "addr:housenumber":"105",
    "addr:postcode":"9752 ba",
    "iso:country":"NL",
    "sg:address":"Ryksstrwg 105",
    "sg:city":"Haren Gn",
    "sg:orig_category":"Fietsen En Bromfietsen",
    "sg:phone":"+31 50 534 4657",
    "sg:postcode":"9752 BA",
    "sg:province":"Groningen",
    "wof:name":"Cycle Shop",
    "wof:placetype":"venue"
},
  "geometry": {"coordinates":[6.60632,53.170658],"type":"Point"}
}