{
  "type": "Feature",
  "properties": {
    "addr:full":"Leidsestraat 12 Amsterdam Noord-Holland 1017 PA",
    "addr:housenumber":"12",
    "addr:postcode":"1017 pa",
    "addr:street":"Leidsestraat",
    "iso:country":"NL",
    "sg:address":"Leidsestraat 12",
    "sg:city":"Amsterdam",
    "sg:classifiers":[
        {
            "category":"Shopping",
            "subcategory":"Gifts & Souvenirs",
            "type":"Retail Goods"
        }
    ],
    "sg:phone":"+31 20 422 6314",
    "sg:postcode":"1017 PA",
    "sg:province":"Noord-Holland",
    "sg:tags":[
        "geschenken"
    ],
    "wof:name":"Regalo Gallery",
    "wof:placetype":"venue"
},
  "geometry": {"coordinates":[-74.11232800000001,42.977543],"type":"Point"}
}