{
  "type": "Feature",
  "properties": {
    "addr:full":"Beekpark 28 Apeldoorn Gelderland 7311 BZ",
    "addr:housenumber":"28",
    "addr:postcode":"7311 bz",
    "addr:street":"Beekpark;Gelderland",
    "iso:country":"NL",
    "sg:address":"Beekpark 28",
    "sg:city":"Apeldoorn",
    "sg:orig_category":"Makelaars In Onroerend Goed",
    "sg:phone":"+31 55 578 9444",
    "sg:postcode":"7311 BZ",
    "sg:province":"Gelderland",
    "wof:name":"De Kamerbank",
    "wof:placetype":"venue"
},
  "geometry": {"coordinates":[5.957432,52.21669],"type":"Point"}
}