{
  "type": "Feature",
  "properties": {
    "addr:full":"Burg Burgerhof 36 Harmelen Utrecht 3481 CZ",
    "addr:housenumber":"36",
    "addr:postcode":"3481",
    "addr:street":"Burg Burgerhof",
    "iso:country":"NL",
    "sg:address":"Burg Burgerhof 36",
    "sg:city":"Harmelen",
    "sg:orig_category":"Handelscentra",
    "sg:phone":"+31 348 443 195",
    "sg:postcode":"3481 CZ",
    "sg:province":"Utrecht",
    "wof:name":"Griffid Bv",
    "wof:placetype":"venue"
},
  "geometry": {"coordinates":[4.956917,52.088779],"type":"Point"}
}