{
  "type": "Feature",
  "properties": {
    "addr:full":"Noordwal 38 Huizen North Holland 1274 AG",
    "addr:housenumber":"38",
    "addr:postcode":"1274",
    "addr:street":"Noordwal",
    "iso:country":"NL",
    "sg:address":"Noordwal 38",
    "sg:city":"Huizen",
    "sg:orig_category":"Fotolitho- En Reprografie - Inrichtingen",
    "sg:phone":"+31 6 53279295",
    "sg:postcode":"1274 AG",
    "sg:province":"North Holland",
    "wof:name":"Berg Bv, Gerard Van Den",
    "wof:placetype":"venue"
},
  "geometry": {"coordinates":[5.265298,52.304726],"type":"Point"}
}