{
  "type": "Feature",
  "properties": {
    "iso:country":"NL",
    "sg:address":"Burg Molln 38",
    "sg:city":"Waalre",
    "sg:orig_category":"Meubelen",
    "sg:phone":"+31 40 221 2215",
    "sg:postcode":"5582 CK",
    "sg:province":"North Brabant",
    "wof:name":"Meubelgalerie, De",
    "wof:placetype":"venue"
},
  "geometry": {"coordinates":[5.477007,51.396118],"type":"Point"}
}