{
  "type": "Feature",
  "properties": {
    "addr:full":"Heulenslag 13 Bleskensgraaf Ca Zuid-Holland 2971 VE",
    "addr:housenumber":"13",
    "addr:postcode":"ca;2971",
    "addr:street":"Heulenslag;Ve",
    "iso:country":"NL",
    "sg:address":"Heulenslag 13",
    "sg:city":"Bleskensgraaf Ca",
    "sg:orig_category":"Gezondheidszorg Geestelijke -",
    "sg:phone":"+31 184 692 001",
    "sg:postcode":"2971 VE",
    "sg:province":"Zuid-Holland",
    "sg:website":"HTTP://www.tooga.nl",
    "wof:name":"Tooga",
    "wof:placetype":"venue"
},
  "geometry": {"coordinates":[4.769137,51.869713],"type":"Point"}
}