{
  "type": "Feature",
  "properties": {
    "addr:full":"Moorsterwg 6 Woudenberg Utrecht 3931 NC",
    "addr:housenumber":"6",
    "addr:postcode":"3931 nc",
    "addr:street":"Moorsterwg",
    "iso:country":"NL",
    "sg:address":"Moorsterwg 6",
    "sg:city":"Woudenberg",
    "sg:orig_category":"Metselwerken",
    "sg:phone":"+31 33 277 1969",
    "sg:postcode":"3931 NC",
    "sg:province":"Utrecht",
    "wof:name":"Liefting, W",
    "wof:placetype":"venue"
},
  "geometry": {"coordinates":[5.482511,52.099461],"type":"Point"}
}