{
  "type": "Feature",
  "properties": {
    "iso:country":"NL",
    "sg:address":"Koningswg 1D",
    "sg:city":"Groningen",
    "sg:orig_category":"Geluidsinstallaties - Verhuur",
    "sg:phone":"+31 50 549 6127",
    "sg:postcode":"9731 AM",
    "sg:province":"Groningen",
    "sg:website":"http://www.entertainment-factory.nl",
    "wof:name":"Entertainment Factory",
    "wof:placetype":"venue"
},
  "geometry": {"coordinates":[6.600247,53.225273],"type":"Point"}
}