{
  "type": "Feature",
  "properties": {
    "addr:full":"Operettewg 4A Almere Flevoland 1323 VA",
    "addr:housenumber":"4a",
    "addr:postcode":"1323",
    "addr:street":"Operettewg;Flevoland",
    "iso:country":"NL",
    "sg:address":"Operettewg 4A",
    "sg:city":"Almere",
    "sg:orig_category":"Verlichtingsartikelen - Groothandel",
    "sg:phone":"+31 36 536 7157",
    "sg:postcode":"1323 VA",
    "sg:province":"Flevoland",
    "wof:name":"Manelco Bv",
    "wof:placetype":"venue"
},
  "geometry": {"coordinates":[5.186678,52.363384],"type":"Point"}
}