{
  "type": "Feature",
  "properties": {
    "addr:full":"Lockhorststr 2 Didam Gelderland 6942 AC",
    "addr:housenumber":"2",
    "addr:postcode":"6942 ac",
    "addr:street":"Lockhorststr;Gelderland",
    "iso:country":"NL",
    "sg:address":"Lockhorststr 2",
    "sg:city":"Didam",
    "sg:orig_category":"Fietsen En Bromfietsen",
    "sg:phone":"+31 316 220 212",
    "sg:postcode":"6942 AC",
    "sg:province":"Gelderland",
    "wof:name":"Fiets-Inn",
    "wof:placetype":"venue"
},
  "geometry": {"coordinates":[6.129336,51.94035],"type":"Point"}
}