{
  "type": "Feature",
  "properties": {
    "iso:country":"NL",
    "sg:address":"Lockhorststr 2",
    "sg:city":"Didam",
    "sg:orig_category":"Fietsen En Bromfietsen",
    "sg:phone":"+31 316 220 212",
    "sg:postcode":"6942 AC",
    "sg:province":"Gelderland",
    "wof:name":"Fiets-Inn",
    "wof:placetype":"venue"
},
  "geometry": {"coordinates":[6.129336,51.94035],"type":"Point"}
}