{
  "type": "Feature",
  "properties": {
    "iso:country":"NL",
    "sg:address":"Mr. Ulrichweg 14",
    "sg:city":"Maastricht",
    "sg:orig_category":"Drukkerijen And Copyshops",
    "sg:phone":"+31 43 321 2265",
    "sg:postcode":"6214 PX",
    "sg:province":"Limburg",
    "wof:name":"Stegen Grafisch Produktie Bureau",
    "wof:placetype":"venue"
},
  "geometry": {"coordinates":[5.67657,50.846973],"type":"Point"}
}