{
  "type": "Feature",
  "properties": {
    "addr:full":"Wildeman 2 Veenendaal Utrecht 3905 TL",
    "addr:housenumber":"2",
    "addr:postcode":"3905 tl",
    "addr:street":"Wildeman",
    "iso:country":"NL",
    "sg:address":"Wildeman 2",
    "sg:city":"Veenendaal",
    "sg:classifiers":[
        {
            "category":"Wholesale",
            "subcategory":"Meat",
            "type":"Manufacturing & Wholesale Goods"
        }
    ],
    "sg:phone":"+31 318 541 700",
    "sg:postcode":"3905 TL",
    "sg:province":"Utrecht",
    "sg:tags":[
        "hang-",
        "sluitwerk",
        "en"
    ],
    "sg:website":"http://www.jobe-international.nl",
    "wof:name":"Jobe Int",
    "wof:placetype":"venue"
},
  "geometry": {"coordinates":[5.534006,52.039707],"type":"Point"}
}