{
  "type": "Feature",
  "properties": {
    "addr:full":"Stationswg 38B Aalsmeer North Holland 1431 EG",
    "addr:housenumber":"38b",
    "addr:postcode":"1431 eg",
    "addr:street":"Stationswg",
    "iso:country":"NL",
    "sg:address":"Stationswg 38B",
    "sg:city":"Aalsmeer",
    "sg:orig_category":"Kantoor- En Bedrijfsmeubelen",
    "sg:phone":"+31 297 368 020",
    "sg:postcode":"1431 EG",
    "sg:province":"North Holland",
    "sg:website":"http://www.vaalofficesupport.nl",
    "wof:name":"Vaal Office Support Bv",
    "wof:placetype":"venue"
},
  "geometry": {"coordinates":[4.7503919601,52.2649002075],"type":"Point"}
}