{
  "type": "Feature",
  "properties": {
    "iso:country":"NL",
    "sg:address":"Kentgenspln 14",
    "sg:city":"Zoetermeer",
    "sg:orig_category":"Drogisterijen",
    "sg:phone":"+31 79 351 4666",
    "sg:postcode":"2717 HS",
    "sg:province":"Zuid-Holland",
    "wof:name":"Da",
    "wof:placetype":"venue"
},
  "geometry": {"coordinates":[4.478383,52.066101],"type":"Point"}
}