{
  "type": "Feature",
  "properties": {
    "addr:full":"Bierbrouwerswg 14 Woerden Utrecht 3449 HW",
    "addr:housenumber":"14",
    "addr:postcode":"3449 hw",
    "addr:street":"Bierbrouwerswg",
    "iso:country":"NL",
    "sg:address":"Bierbrouwerswg 14",
    "sg:city":"Woerden",
    "sg:orig_category":"Fotostudio'S",
    "sg:phone":"+31 348 415 122",
    "sg:postcode":"3449 HW",
    "sg:province":"Utrecht",
    "wof:name":"Hans Van Ommeren Bv",
    "wof:placetype":"venue"
},
  "geometry": {"coordinates":[4.859752,52.08374],"type":"Point"}
}