{
  "type": "Feature",
  "properties": {
    "iso:country":"NL",
    "sg:address":"Alpen Rondweg 56",
    "sg:city":"Amstelveen",
    "sg:orig_category":"Tandartsen",
    "sg:phone":"+31 20 645 2413",
    "sg:postcode":"1186 EA",
    "sg:province":"Noord-Holland",
    "wof:name":"J.B. Hoogstraten",
    "wof:placetype":"venue"
},
  "geometry": {"coordinates":[4.865447,52.291443],"type":"Point"}
}