{
  "type": "Feature",
  "properties": {
    "iso:country":"NL",
    "sg:address":"Margarethastr 71",
    "sg:city":"Ittervoort",
    "sg:orig_category":"Banken",
    "sg:phone":"+31 495 459 591",
    "sg:postcode":"6014 AD",
    "sg:province":"Limburg",
    "sg:website":"http://www.rabobank.nl",
    "wof:name":"Rabobank",
    "wof:placetype":"venue"
},
  "geometry": {"coordinates":[5.814575,51.16843],"type":"Point"}
}