{
  "type": "Feature",
  "properties": {
    "addr:full":"Bilderdykstr 74 Amsterdam Noord-Holland 1053 KW",
    "addr:housenumber":"74",
    "addr:postcode":"1053 kw",
    "addr:street":"Bilderdykstr",
    "iso:country":"NL",
    "sg:address":"Bilderdykstr 74",
    "sg:city":"Amsterdam",
    "sg:classifiers":[
        {
            "category":"Restaurant",
            "type":"Food & Drink"
        }
    ],
    "sg:phone":"+31 20 618 2043",
    "sg:postcode":"1053 KW",
    "sg:province":"Noord-Holland",
    "wof:name":"Pagode",
    "wof:placetype":"venue"
},
  "geometry": {"coordinates":[4.870293,52.369843],"type":"Point"}
}