{
  "type": "Feature",
  "properties": {
    "addr:full":"Purmerwg 39A Purmerend North Holland 1441 RA",
    "addr:housenumber":"39a",
    "addr:postcode":"1441 ra",
    "addr:street":"Purmerwg",
    "iso:country":"NL",
    "sg:address":"Purmerwg 39A",
    "sg:city":"Purmerend",
    "sg:orig_category":"Lasbedrijven",
    "sg:phone":"+31 299 437 408",
    "sg:postcode":"1441 RA",
    "sg:province":"North Holland",
    "wof:name":"Lason",
    "wof:placetype":"venue"
},
  "geometry": {"coordinates":[4.968597,52.503777],"type":"Point"}
}