{
  "type": "Feature",
  "properties": {
    "addr:full":"Crouwelstraat 17 Groningen Groningen 9731 MG",
    "addr:housenumber":"17",
    "addr:postcode":"9731 mg",
    "addr:street":"Crouwelstraat",
    "iso:country":"NL",
    "sg:address":"Crouwelstraat 17",
    "sg:city":"Groningen",
    "sg:orig_category":"Kappers",
    "sg:phone":"+31 50 541 0463",
    "sg:postcode":"9731 MG",
    "sg:province":"Groningen",
    "wof:name":"Kapsalon Antoinette",
    "wof:placetype":"venue"
},
  "geometry": {"coordinates":[6.5802798271,53.2408638],"type":"Point"}
}