{
  "type": "Feature",
  "properties": {
    "addr:full":"Ammunitiehaven 19-21 Den Haag South Holland 2511 HT",
    "addr:housenumber":"19-21",
    "addr:postcode":"2511 ht",
    "addr:street":"Ammunitiehaven",
    "iso:country":"NL",
    "sg:address":"Ammunitiehaven 19-21",
    "sg:city":"Den Haag",
    "sg:orig_category":"Werving And Selectie Van Tijdelijk Personeel And Uitzendkantoren",
    "sg:phone":"+31 70 356 0563",
    "sg:postcode":"2511 HT",
    "sg:province":"South Holland",
    "wof:name":"Start",
    "wof:placetype":"venue"
},
  "geometry": {"coordinates":[4.318418026,52.0760498047],"type":"Point"}
}