{
  "type": "Feature",
  "properties": {
    "addr:full":"Akkermansstr 1A Zelhem Gelderland 7021 LW",
    "addr:housenumber":"1a",
    "addr:postcode":"7021 lw",
    "addr:street":"Akkermansstr;Gelderland",
    "iso:country":"NL",
    "sg:address":"Akkermansstr 1A",
    "sg:city":"Zelhem",
    "sg:orig_category":"Betonwerken",
    "sg:phone":"+31 314 641 777",
    "sg:postcode":"7021 LW",
    "sg:province":"Gelderland",
    "wof:name":"Kleve",
    "wof:placetype":"venue"
},
  "geometry": {"coordinates":[6.286595,52.020855],"type":"Point"}
}