{
  "type": "Feature",
  "properties": {
    "addr:full":"A Dekenpln 23 Hoorn Nh North Holland 1628 NX",
    "addr:housenumber":"23",
    "addr:postcode":"1628 nx",
    "addr:street":"Nh North",
    "iso:country":"NL",
    "sg:address":"A Dekenpln 23",
    "sg:city":"Hoorn Nh",
    "sg:orig_category":"Opticiens",
    "sg:phone":"+31 229 247 165",
    "sg:postcode":"1628 NX",
    "sg:province":"North Holland",
    "sg:website":"http://www.ruttenberg.nl",
    "wof:name":"Huis Ruttenberg, Het",
    "wof:placetype":"venue"
},
  "geometry": {"coordinates":[5.0942602158,52.6542015076],"type":"Point"}
}