{
  "type": "Feature",
  "properties": {
    "addr:full":"Wouwsestraat 40 Bergen Op Zoom North Brabant 4611 PM",
    "addr:housenumber":"40",
    "addr:postcode":"4611 pm",
    "addr:street":"Wouwsestraat",
    "iso:country":"NL",
    "sg:address":"Wouwsestraat 40",
    "sg:city":"Bergen Op Zoom",
    "sg:classifiers":[
        {
            "category":"Shopping",
            "subcategory":"Clothing, Apparel, & Fashions",
            "type":"Retail Goods"
        }
    ],
    "sg:phone":"+31 164 233 537",
    "sg:postcode":"4611 PM",
    "sg:province":"North Brabant",
    "sg:tags":[
        "ondergoed",
        "lingerie"
    ],
    "wof:name":"P.C. Dekkers",
    "wof:placetype":"venue"
},
  "geometry": {"coordinates":[4.291876,51.495117],"type":"Point"}
}