{
  "type": "Feature",
  "properties": {
    "addr:full":"Entrepotdok 78A Amsterdam Noord-Holland 1018 AD",
    "addr:housenumber":"78a",
    "addr:postcode":"1018 ad",
    "addr:street":"Entrepotdok",
    "iso:country":"NL",
    "sg:address":"Entrepotdok 78A",
    "sg:city":"Amsterdam",
    "sg:orig_category":"Artiestenbureaus",
    "sg:phone":"+31 20 620 6556",
    "sg:postcode":"1018 AD",
    "sg:province":"Noord-Holland",
    "wof:name":"Euro Stage",
    "wof:placetype":"venue"
},
  "geometry": {"coordinates":[4.917193,52.367867],"type":"Point"}
}