{
  "type": "Feature",
  "properties": {
    "addr:full":"Hobbemastraat 3 Hardinxveld Giessend Zuid-Holland 3372 XG",
    "addr:housenumber":"3;giessend",
    "addr:postcode":"3372 xg",
    "addr:street":"Hobbemastraat",
    "iso:country":"NL",
    "sg:address":"Hobbemastraat 3",
    "sg:city":"Hardinxveld Giessend",
    "sg:classifiers":[
        {
            "category":"Education",
            "subcategory":"Preschool",
            "type":"Public Place"
        }
    ],
    "sg:phone":"+31 184 613 942",
    "sg:postcode":"3372 XG",
    "sg:province":"Zuid-Holland",
    "sg:tags":[
        "kleuteronderwijs",
        "basis-"
    ],
    "wof:name":"Openbare Basisschool Merwedeschool",
    "wof:placetype":"venue"
},
  "geometry": {"coordinates":[4.886599,51.823845],"type":"Point"}
}