{
  "type": "Feature",
  "properties": {
    "addr:full":"Keizersgr 323 Amsterdam Noord-Holland 1016 EE",
    "addr:housenumber":"323",
    "addr:postcode":"1016 ee",
    "iso:country":"NL",
    "sg:address":"Keizersgr 323",
    "sg:city":"Amsterdam",
    "sg:orig_category":"Verenigingen En Stichtingen",
    "sg:phone":"+31 20 624 7768",
    "sg:postcode":"1016 EE",
    "sg:province":"Noord-Holland",
    "wof:name":"Beetshuis",
    "wof:placetype":"venue"
},
  "geometry": {"coordinates":[4.885154,52.369812],"type":"Point"}
}