{
  "type": "Feature",
  "properties": {
    "iso:country":"NL",
    "sg:address":"De Jagerstraat 17",
    "sg:city":"Alkmaar",
    "sg:orig_category":"Autokeuringen",
    "sg:phone":"+31 72 511 9908",
    "sg:postcode":"1823 CV",
    "sg:province":"Noord-Holland",
    "wof:name":"Garage Dave Kuys",
    "wof:placetype":"venue"
},
  "geometry": {"coordinates":[4.747981,52.636677],"type":"Point"}
}