{
  "type": "Feature",
  "properties": {
    "addr:full":"Gravenmade 20 Pijnacker South Holland 2641 LM",
    "addr:housenumber":"20",
    "addr:postcode":"2641 lm",
    "addr:street":"Gravenmade",
    "iso:country":"NL",
    "sg:address":"Gravenmade 20",
    "sg:city":"Pijnacker",
    "sg:orig_category":"Vertaalbureaus",
    "sg:phone":"+31 15 261 6370",
    "sg:postcode":"2641 LM",
    "sg:province":"South Holland",
    "wof:name":"Europahuis",
    "wof:placetype":"venue"
},
  "geometry": {"coordinates":[4.440529,52.012363],"type":"Point"}
}