{
  "type": "Feature",
  "properties": {
    "addr:full":"Oudebrugwg 8 Gouda Zuid-Holland 2808 NP",
    "addr:housenumber":"8",
    "addr:postcode":"2808 np",
    "addr:street":"Oudebrugwg",
    "iso:country":"NL",
    "sg:address":"Oudebrugwg 8",
    "sg:city":"Gouda",
    "sg:orig_category":"Machineonderhoud En -Reparatie",
    "sg:phone":"+31 182 541 885",
    "sg:postcode":"2808 NP",
    "sg:province":"Zuid-Holland",
    "wof:name":"Wijngo Techno Service",
    "wof:placetype":"venue"
},
  "geometry": {"coordinates":[4.720329,52.00573],"type":"Point"}
}