{
  "type": "Feature",
  "properties": {
    "iso:country":"NL",
    "sg:address":"De Koppele 295",
    "sg:city":"Eindhoven",
    "sg:orig_category":"Voetbalverenigingen",
    "sg:phone":"+31 40 241 1740",
    "sg:postcode":"5632 LK",
    "sg:province":"Noord-Brabant",
    "wof:name":"Eindhoven Av",
    "wof:placetype":"venue"
},
  "geometry": {"coordinates":[5.490425,51.478828],"type":"Point"}
}