{
  "type": "Feature",
  "properties": {
    "addr:full":"Dorpsstr 256 St Willebrord Noord-Brabant 4711 EP",
    "addr:housenumber":"256",
    "addr:postcode":"4711 ep",
    "addr:street":"St",
    "iso:country":"NL",
    "sg:address":"Dorpsstr 256",
    "sg:city":"St Willebrord",
    "sg:orig_category":"Gordijnen",
    "sg:phone":"+31 165 387 161",
    "sg:postcode":"4711 EP",
    "sg:province":"Noord-Brabant",
    "wof:name":"Ella",
    "wof:placetype":"venue"
},
  "geometry": {"coordinates":[4.590552,51.557484],"type":"Point"}
}