{
  "type": "Feature",
  "properties": {
    "addr:full":"Gaardenstr 37 Holten NL.08 7451 CV",
    "addr:housenumber":"37;nl.08",
    "addr:postcode":"7451 cv",
    "addr:street":"Gaardenstr",
    "iso:country":"NL",
    "sg:address":"Gaardenstr 37",
    "sg:city":"Holten",
    "sg:orig_category":"Postkantoren",
    "sg:phone":"+31 548 365 069",
    "sg:postcode":"7451 CV",
    "sg:province":"NL.08",
    "sg:website":"http://www.postkantoor.nl",
    "wof:name":"Postkantoor",
    "wof:placetype":"venue"
},
  "geometry": {"coordinates":[6.418303,52.281639],"type":"Point"}
}