{
  "type": "Feature",
  "properties": {
    "iso:country":"NL",
    "sg:address":"Stationsweg 22",
    "sg:city":"Bergentheim",
    "sg:classifiers":[
        {
            "category":"Education",
            "subcategory":"Preschool",
            "type":"Public Place"
        }
    ],
    "sg:phone":"+31 523 231 958",
    "sg:postcode":"7691 AR",
    "sg:province":"Arkansas",
    "sg:tags":[
        "kleuteronderwijs",
        "basis-"
    ],
    "wof:name":"Openbare Basisschool Prins Bernhard",
    "wof:placetype":"venue"
},
  "geometry": {"coordinates":[-92.131348,34.751888],"type":"Point"}
}