{
  "type": "Feature",
  "properties": {
    "addr:full":"Wolvenhoek 14 S Hertogenbosch Noord-Brabant 5211 HH",
    "addr:housenumber":"14",
    "addr:postcode":"5211 hh",
    "addr:street":"Wolvenhoek;S",
    "iso:country":"NL",
    "sg:address":"Wolvenhoek 14",
    "sg:city":"S Hertogenbosch",
    "sg:orig_category":"Zonnebank- En Solariumcentra",
    "sg:phone":"+31 73 614 9808",
    "sg:postcode":"5211 HH",
    "sg:province":"Noord-Brabant",
    "wof:name":"Summertan",
    "wof:placetype":"venue"
},
  "geometry": {"coordinates":[5.30331,51.68652],"type":"Point"}
}