{
  "type": "Feature",
  "properties": {
    "addr:full":"Ootmarsumsestr 132 Almelo Overijssel 7603 AL",
    "addr:housenumber":"132",
    "addr:postcode":"7603 al",
    "iso:country":"NL",
    "sg:address":"Ootmarsumsestr 132",
    "sg:city":"Almelo",
    "sg:orig_category":"Levensmiddelen - Fabrieken En Groothandel",
    "sg:phone":"+31 546 872 920",
    "sg:postcode":"7603 AL",
    "sg:province":"Overijssel",
    "wof:name":"Aydin",
    "wof:placetype":"venue"
},
  "geometry": {"coordinates":[6.67273,52.365334],"type":"Point"}
}