{
  "type": "Feature",
  "properties": {
    "addr:full":"Noordkade 64 Waddinxveen South Holland 2741 EZ",
    "addr:housenumber":"64",
    "addr:postcode":"2741 ez",
    "addr:street":"Noordkade",
    "iso:country":"NL",
    "sg:address":"Noordkade 64",
    "sg:city":"Waddinxveen",
    "sg:orig_category":"Technische Studies And Onderzoek",
    "sg:phone":"+31 182 633 336",
    "sg:postcode":"2741 EZ",
    "sg:province":"South Holland",
    "wof:name":"Quintessence Technical Support Bv",
    "wof:placetype":"venue"
},
  "geometry": {"coordinates":[4.661049,52.052486],"type":"Point"}
}