{
  "type": "Feature",
  "properties": {
    "addr:full":"Troelstrawg 281 Vlissingen Zeeland 4384 GP",
    "addr:housenumber":"281",
    "addr:postcode":"4384 gp",
    "iso:country":"NL",
    "sg:address":"Troelstrawg 281",
    "sg:city":"Vlissingen",
    "sg:orig_category":"Keuken- Groot-Installaties",
    "sg:phone":"+31 118 463 589",
    "sg:postcode":"4384 GP",
    "sg:province":"Zeeland",
    "wof:name":"Cbestra",
    "wof:placetype":"venue"
},
  "geometry": {"coordinates":[3.57262,51.442684],"type":"Point"}
}