{
  "type": "Feature",
  "properties": {
    "addr:full":"Schieweg 96 Rotterdam Zuid-Holland 3038 BB",
    "addr:housenumber":"96",
    "addr:postcode":"3038 bb",
    "addr:street":"Schieweg",
    "iso:country":"NL",
    "sg:address":"Schieweg 96",
    "sg:city":"Rotterdam",
    "sg:orig_category":"Kappers",
    "sg:phone":"+31 10 466 3904",
    "sg:postcode":"3038 BB",
    "sg:province":"Zuid-Holland",
    "wof:name":"Hairstudio 91",
    "wof:placetype":"venue"
},
  "geometry": {"coordinates":[4.466023922,51.9324874878],"type":"Point"}
}