{
  "type": "Feature",
  "properties": {
    "addr:full":"Litscherveldw 13 Heerlen Limburg 6413 BA",
    "addr:housenumber":"13",
    "addr:postcode":"6413 ba",
    "addr:street":"Litscherveldw",
    "iso:country":"NL",
    "sg:address":"Litscherveldw 13",
    "sg:city":"Heerlen",
    "sg:orig_category":"Kermisexploitatie",
    "sg:phone":"+31 45 522 3843",
    "sg:postcode":"6413 BA",
    "sg:province":"Limburg",
    "wof:name":"Lutjens, S",
    "wof:placetype":"venue"
},
  "geometry": {"coordinates":[5.959146,50.912983],"type":"Point"}
}