{
  "type": "Feature",
  "properties": {
    "iso:country":"NL",
    "sg:address":"Schoolstraat 11",
    "sg:city":"Moergestel",
    "sg:orig_category":"Hypotheken And Hypotheekbanken",
    "sg:phone":"+31 13 513 2218",
    "sg:postcode":"5066 EC",
    "sg:province":"Noord-Brabant",
    "wof:name":"Joost Kwinten Assurantien",
    "wof:placetype":"venue"
},
  "geometry": {"coordinates":[5.182929,51.543514],"type":"Point"}
}