{
  "type": "Feature",
  "properties": {
    "addr:full":"De Regge 16 Eindhoven Noord-Brabant 5626 GZ",
    "addr:housenumber":"16",
    "addr:postcode":"5626 gz",
    "addr:street":"De Regge",
    "iso:country":"NL",
    "sg:address":"De Regge 16",
    "sg:city":"Eindhoven",
    "sg:orig_category":"Voegwerken",
    "sg:phone":"+31 40 262 3212",
    "sg:postcode":"5626 GZ",
    "sg:province":"Noord-Brabant",
    "wof:name":"Ven & Zn, J L Van De",
    "wof:placetype":"venue"
},
  "geometry": {"coordinates":[5.430483,51.476559],"type":"Point"}
}