{
  "type": "Feature",
  "properties": {
    "addr:full":"O Handelskd 12K Amsterdam Noord-Holland 1019 BM",
    "addr:housenumber":"12k",
    "addr:postcode":"1019 bm",
    "addr:street":"Handelskd",
    "iso:country":"NL",
    "sg:address":"O Handelskd 12K",
    "sg:city":"Amsterdam",
    "sg:orig_category":"Webdesign Bureaus",
    "sg:phone":"+31 20 419 5628",
    "sg:postcode":"1019 BM",
    "sg:province":"Noord-Holland",
    "wof:name":"Alias",
    "wof:placetype":"venue"
},
  "geometry": {"coordinates":[4.8931951523,52.3731193542],"type":"Point"}
}