{
  "type": "Feature",
  "properties": {
    "addr:full":"Van Voorststraat 4 Huissen Gelderland 6851 LV",
    "addr:housenumber":"4",
    "addr:postcode":"6851",
    "addr:street":"Van Voorststraat;Gelderland",
    "iso:country":"NL",
    "sg:address":"Van Voorststraat 4",
    "sg:city":"Huissen",
    "sg:orig_category":"Metaalwerken",
    "sg:phone":"+31 26 325 6203",
    "sg:postcode":"6851 LV",
    "sg:province":"Gelderland",
    "wof:name":"Bouwman Zonwering",
    "wof:placetype":"venue"
},
  "geometry": {"coordinates":[5.938773,51.938519],"type":"Point"}
}