{
  "type": "Feature",
  "properties": {
    "addr:full":"Lange Marktstraat 5 Leeuwarden Provincie Friesland 8911 AD",
    "addr:housenumber":"5",
    "addr:postcode":"8911 ad",
    "addr:street":"Lange Marktstraat;Provincie Friesland",
    "iso:country":"NL",
    "sg:address":"Lange Marktstraat 5",
    "sg:city":"Leeuwarden",
    "sg:classifiers":[
        {
            "category":"Professional",
            "subcategory":"Accounting & Tax Preparation",
            "type":"Services"
        }
    ],
    "sg:phone":"+31 58 212 2646",
    "sg:postcode":"8911 AD",
    "sg:province":"Provincie Friesland",
    "sg:tags":[
        "accountant"
    ],
    "wof:name":"Deloitte & Touche Accountants Belastingadviseurs C",
    "wof:placetype":"venue"
},
  "geometry": {"coordinates":[5.791814,53.197441],"type":"Point"}
}