{
  "type": "Feature",
  "properties": {
    "addr:full":"Gortstraat 44 Middelburg Zeeland 4331 LC",
    "addr:housenumber":"44",
    "addr:postcode":"4331 lc",
    "addr:street":"Gortstraat",
    "iso:country":"NL",
    "sg:address":"Gortstraat 44",
    "sg:city":"Middelburg",
    "sg:orig_category":"Wasserettes And Stomerijen",
    "sg:phone":"+31 118 639 164",
    "sg:postcode":"4331 LC",
    "sg:province":"Zeeland",
    "wof:name":"Stomerij Veldman",
    "wof:placetype":"venue"
},
  "geometry": {"coordinates":[3.6105918884,51.4967765808],"type":"Point"}
}