{
  "type": "Feature",
  "properties": {
    "addr:full":"De Dars 8 Schagerbrug Noord-Holland 1751 PD",
    "addr:housenumber":"8",
    "addr:postcode":"1751 pd",
    "addr:street":"De Dars",
    "iso:country":"NL",
    "sg:address":"De Dars 8",
    "sg:city":"Schagerbrug",
    "sg:orig_category":"Loodgieterswerk, Verwarming And Sanitaire Installaties",
    "sg:phone":"+31 224 571 553",
    "sg:postcode":"1751 PD",
    "sg:province":"Noord-Holland",
    "wof:name":"Timmerbedrijf Kuit",
    "wof:placetype":"venue"
},
  "geometry": {"coordinates":[4.763138,52.801319],"type":"Point"}
}