{
  "type": "Feature",
  "properties": {
    "addr:full":"Valkenburgstraat 10 Meliskerke Zeeland 4365 AC",
    "addr:housenumber":"10",
    "addr:postcode":"4365 ac",
    "addr:street":"Valkenburgstraat",
    "iso:country":"NL",
    "sg:address":"Valkenburgstraat 10",
    "sg:city":"Meliskerke",
    "sg:classifiers":[
        {
            "category":"Education",
            "subcategory":"Preschool",
            "type":"Public Place"
        }
    ],
    "sg:phone":"+31 118 561 649",
    "sg:postcode":"4365 AC",
    "sg:province":"Zeeland",
    "sg:tags":[
        "kleuteronderwijs",
        "basis-"
    ],
    "wof:name":"Gereformeerde Basisschool Boaz",
    "wof:placetype":"venue"
},
  "geometry": {"coordinates":[3.51246,51.514954],"type":"Point"}
}