{
  "type": "Feature",
  "properties": {
    "addr:full":"Nyverheidswg N 55A Amersfoort Utrecht 3812 PK",
    "addr:housenumber":"55a",
    "addr:postcode":"3812 pk",
    "addr:street":"N",
    "iso:country":"NL",
    "sg:address":"Nyverheidswg N 55A",
    "sg:city":"Amersfoort",
    "sg:orig_category":"Keukens",
    "sg:phone":"+31 33 455 7699",
    "sg:postcode":"3812 PK",
    "sg:province":"Utrecht",
    "sg:website":"http://www.brilliantkeukens.nl",
    "wof:name":"Brilliant, Keuken Arch",
    "wof:placetype":"venue"
},
  "geometry": {"coordinates":[5.378292,52.159302],"type":"Point"}
}