{
  "type": "Feature",
  "properties": {
    "addr:full":"Plantsoenlaan 2 Zwanenburg North Holland 1161 VW",
    "addr:housenumber":"2",
    "addr:postcode":"1161 vw",
    "addr:street":"Plantsoenlaan",
    "iso:country":"NL",
    "sg:address":"Plantsoenlaan 2",
    "sg:city":"Zwanenburg",
    "sg:orig_category":"Kinderopvang Behalve Thuis",
    "sg:phone":"+31 20 497 2416",
    "sg:postcode":"1161 VW",
    "sg:province":"North Holland",
    "wof:name":"Kinderdagverblijf De Hoek",
    "wof:placetype":"venue"
},
  "geometry": {"coordinates":[4.74548,52.377644],"type":"Point"}
}