{
  "type": "Feature",
  "properties": {
    "iso:country":"NL",
    "sg:address":"Lange Mosten 4",
    "sg:city":"Breda",
    "sg:classifiers":[
        {
            "category":"Travel",
            "subcategory":"Hotels & Motels",
            "type":"Entertainment"
        }
    ],
    "sg:phone":"+31 76 542 0403",
    "sg:postcode":"4822 NJ",
    "sg:province":"Noord-Brabant",
    "wof:name":"Bastion Hotel",
    "wof:placetype":"venue"
},
  "geometry": {"coordinates":[4.724681,51.603451],"type":"Point"}
}