{
  "type": "Feature",
  "properties": {
    "addr:full":"Belgieln 33 Beverwyk Noord-Holland 1946 TJ",
    "addr:housenumber":"33",
    "addr:postcode":"1946 tj",
    "addr:street":"Belgieln",
    "iso:country":"NL",
    "sg:address":"Belgieln 33",
    "sg:city":"Beverwyk",
    "sg:classifiers":[
        {
            "category":"Retail",
            "subcategory":"Auto Repair",
            "type":"Services"
        }
    ],
    "sg:phone":"+31 251 245 091",
    "sg:postcode":"1946 TJ",
    "sg:province":"Noord-Holland",
    "sg:tags":[
        "garage"
    ],
    "wof:name":"Oosterwijk Autobedrijf",
    "wof:placetype":"venue"
},
  "geometry": {"coordinates":[4.67626,52.491581],"type":"Point"}
}