{
  "type": "Feature",
  "properties": {
    "addr:full":"J Vermeerln 251 Roosendaal Noord-Brabant 4703 KW",
    "addr:housenumber":"251",
    "addr:postcode":"4703 kw",
    "iso:country":"NL",
    "sg:address":"J Vermeerln 251",
    "sg:city":"Roosendaal",
    "sg:orig_category":"Autolakken",
    "sg:phone":"+31 165 555 030",
    "sg:postcode":"4703 KW",
    "sg:province":"Noord-Brabant",
    "wof:name":"Jp Carcolour",
    "wof:placetype":"venue"
},
  "geometry": {"coordinates":[4.447368,51.541206],"type":"Point"}
}