{
  "type": "Feature",
  "properties": {
    "iso:country":"NL",
    "sg:address":"De Amert 130",
    "sg:city":"Veghel",
    "sg:orig_category":"Pijpleidingen - Apparatuur En Benodigdheden",
    "sg:phone":"+31 413 377 466",
    "sg:postcode":"5462 GH",
    "sg:province":"Noord-Brabant",
    "wof:name":"Buisklem Bv",
    "wof:placetype":"venue"
},
  "geometry": {"coordinates":[5.517824,51.623516],"type":"Point"}
}