{
  "type": "Feature",
  "properties": {
    "iso:country":"NL",
    "sg:address":"Looiersdreef 671",
    "sg:city":"Apeldoorn",
    "sg:orig_category":"Administratie- En Boekhoudkantoren",
    "sg:phone":"+31 55 541 5384",
    "sg:postcode":"7328 HV",
    "sg:province":"Gelderland",
    "wof:name":"Messemaker",
    "wof:placetype":"venue"
},
  "geometry": {"coordinates":[5.98537,52.202],"type":"Point"}
}