{
  "type": "Feature",
  "properties": {
    "addr:full":"Engelsewg 210 Helmond North Brabant 5705 AJ",
    "addr:housenumber":"210",
    "addr:postcode":"5705 aj",
    "iso:country":"NL",
    "sg:address":"Engelsewg 210",
    "sg:city":"Helmond",
    "sg:orig_category":"Automaterialen En Gereedschappen",
    "sg:phone":"+31 492 537 825",
    "sg:postcode":"5705 AJ",
    "sg:province":"North Brabant",
    "wof:name":"Zuiden Bv, Het",
    "wof:placetype":"venue"
},
  "geometry": {"coordinates":[5.676265,51.473042],"type":"Point"}
}