{
  "type": "Feature",
  "properties": {
    "iso:country":"NL",
    "sg:address":"Smidstr 3",
    "sg:city":"Gaanderen",
    "sg:orig_category":"Adviesbureaus Bedrijfsorganisatie",
    "sg:phone":"+31 315 329 723",
    "sg:postcode":"7011 JK",
    "sg:province":"Gelderland",
    "wof:name":"Bussink",
    "wof:placetype":"venue"
},
  "geometry": {"coordinates":[6.36972,51.935459],"type":"Point"}
}