{
  "type": "Feature",
  "properties": {
    "addr:full":"V Clermontpln 30 Vaals North Rhine-Westphalia 6291 AV",
    "addr:housenumber":"30",
    "addr:postcode":"6291 av",
    "iso:country":"NL",
    "sg:address":"V Clermontpln 30",
    "sg:city":"Vaals",
    "sg:orig_category":"Perzische En Oosterse Tapijten",
    "sg:phone":"+31 43 306 2771",
    "sg:postcode":"6291 AV",
    "sg:province":"North Rhine-Westphalia",
    "wof:name":"Dastmaltschi Snijders",
    "wof:placetype":"venue"
},
  "geometry": {"coordinates":[6.017875,50.77298],"type":"Point"}
}