{
  "type": "Feature",
  "properties": {
    "iso:country":"NL",
    "sg:address":"Marenseweg 2",
    "sg:city":"Maren Kessel",
    "sg:orig_category":"Bloemen And Planten",
    "sg:phone":"+31 412 479 333",
    "sg:postcode":"5398 JE",
    "sg:province":"Noord-Brabant",
    "wof:name":"G.M.W. Verhallen-P.J.H.M. Verhallen-V.D.",
    "wof:placetype":"venue"
},
  "geometry": {"coordinates":[5.378966,51.793541],"type":"Point"}
}