{
  "type": "Feature",
  "properties": {
    "iso:country":"NL",
    "sg:address":"Chemiewg 25",
    "sg:city":"Moerdyk",
    "sg:orig_category":"Betonindustrie",
    "sg:phone":"+31 168 324 480",
    "sg:postcode":"4782 SJ",
    "sg:province":"Noord-Brabant",
    "wof:name":"Ahak Ned Bv",
    "wof:placetype":"venue"
},
  "geometry": {"coordinates":[4.57194,51.682499],"type":"Point"}
}