{
  "type": "Feature",
  "properties": {
    "iso:country":"NL",
    "sg:address":"Julianastraat 1",
    "sg:city":"Brunssum",
    "sg:orig_category":"Administratie- En Boekhoudkantoren",
    "sg:phone":"+31 45 525 1100",
    "sg:postcode":"6441 BR",
    "sg:province":"Limburg",
    "wof:name":"Garde, Bureau La",
    "wof:placetype":"venue"
},
  "geometry": {"coordinates":[5.97285,50.951012],"type":"Point"}
}