{
  "type": "Feature",
  "properties": {
    "addr:full":"Westerstr 123 Enkhuizen Noord-Holland 1601 AE",
    "addr:housenumber":"123",
    "addr:postcode":"1601 ae",
    "iso:country":"NL",
    "sg:address":"Westerstr 123",
    "sg:city":"Enkhuizen",
    "sg:orig_category":"Warenhuizen",
    "sg:phone":"+31 228 321 163",
    "sg:postcode":"1601 AE",
    "sg:province":"Noord-Holland",
    "wof:name":"Hema",
    "wof:placetype":"venue"
},
  "geometry": {"coordinates":[5.2869749069,52.7031097412],"type":"Point"}
}