{
  "type": "Feature",
  "properties": {
    "addr:full":"Laaressingel 138 Enschede Overijssel 7514 ET",
    "addr:housenumber":"138",
    "addr:postcode":"7514 et",
    "addr:street":"Laaressingel",
    "iso:country":"NL",
    "sg:address":"Laaressingel 138",
    "sg:city":"Enschede",
    "sg:orig_category":"Hypotheken And Hypotheekbanken",
    "sg:phone":"+31 53 433 8220",
    "sg:postcode":"7514 ET",
    "sg:province":"Overijssel",
    "wof:name":"Hofman-Assurantien",
    "wof:placetype":"venue"
},
  "geometry": {"coordinates":[6.90908,52.226856],"type":"Point"}
}