{
  "type": "Feature",
  "properties": {
    "addr:full":"Zuider Es 18 Appelscha Provincie Friesland 8426 KA",
    "addr:housenumber":"18",
    "addr:postcode":"8426 ka",
    "addr:street":"Zuider Es;Provincie Friesland",
    "iso:country":"NL",
    "sg:address":"Zuider Es 18",
    "sg:city":"Appelscha",
    "sg:orig_category":"Kinderactiviteiten",
    "sg:phone":"+31 516 433 114",
    "sg:postcode":"8426 KA",
    "sg:province":"Provincie Friesland",
    "wof:name":"Dewia",
    "wof:placetype":"venue"
},
  "geometry": {"coordinates":[6.360008,52.950554],"type":"Point"}
}