{
  "type": "Feature",
  "properties": {
    "addr:full":"Wagenwg 194 Haarlem Noord-Holland 2012 NM",
    "addr:housenumber":"194",
    "addr:postcode":"2012",
    "iso:country":"NL",
    "sg:address":"Wagenwg 194",
    "sg:city":"Haarlem",
    "sg:orig_category":"Juridische Adviseurs",
    "sg:phone":"+31 23 531 8266",
    "sg:postcode":"2012 NM",
    "sg:province":"Noord-Holland",
    "wof:name":"Schrijvers Bv",
    "wof:placetype":"venue"
},
  "geometry": {"coordinates":[4.621069,52.368408],"type":"Point"}
}