{
  "type": "Feature",
  "properties": {
    "addr:full":"Oude Baan 103 Dongen Pennsylvania 5104 PA",
    "addr:housenumber":"103",
    "addr:postcode":"5104 pa",
    "addr:street":"Oude Baan",
    "iso:country":"NL",
    "sg:address":"Oude Baan 103",
    "sg:city":"Dongen",
    "sg:orig_category":"Bedrijfskleding",
    "sg:phone":"+31 162 318 757",
    "sg:postcode":"5104 PA",
    "sg:province":"Pennsylvania",
    "sg:website":"http://www.schipper - handel.nl",
    "wof:name":"Schipper Handelsonderneming",
    "wof:placetype":"venue"
},
  "geometry": {"coordinates":[-77.604507,40.99464],"type":"Point"}
}