{
  "type": "Feature",
  "properties": {
    "addr:full":"Lemelerbergwg 42 Amsterdam Zuidoost Noord-Holland 1101 AM",
    "addr:housenumber":"42",
    "addr:postcode":"zuidoost;1101",
    "addr:street":"Lemelerbergwg",
    "iso:country":"NL",
    "sg:address":"Lemelerbergwg 42",
    "sg:city":"Amsterdam Zuidoost",
    "sg:orig_category":"Juwelen - Groothandel",
    "sg:phone":"+31 20 342 8080",
    "sg:postcode":"1101 AM",
    "sg:province":"Noord-Holland",
    "wof:name":"Ibb Amsterdam Bv",
    "wof:placetype":"venue"
},
  "geometry": {"coordinates":[4.941179,52.303154],"type":"Point"}
}