{
  "type": "Feature",
  "properties": {
    "addr:full":"Schuitevaarstraat 2 Oudenbosch Noord-Brabant 4731 LH",
    "addr:housenumber":"2",
    "addr:postcode":"4731 lh",
    "addr:street":"Schuitevaarstraat",
    "iso:country":"NL",
    "sg:address":"Schuitevaarstraat 2",
    "sg:city":"Oudenbosch",
    "sg:orig_category":"Meubelzaken, Woning- And Keukeninrichting",
    "sg:phone":"+31 165 312 868",
    "sg:postcode":"4731 LH",
    "sg:province":"Noord-Brabant",
    "wof:name":"Complete Woninginrichting Carel Bv",
    "wof:placetype":"venue"
},
  "geometry": {"coordinates":[4.525029,51.594913],"type":"Point"}
}