{
  "type": "Feature",
  "properties": {
    "addr:full":"Van Ruysdaellaan 94 Leidschendam Zuid-Holland 2264 TM",
    "addr:housenumber":"94",
    "addr:postcode":"2264 tm",
    "addr:street":"Van Ruysdaellaan",
    "iso:country":"NL",
    "sg:address":"Van Ruysdaellaan 94",
    "sg:city":"Leidschendam",
    "sg:orig_category":"Elektronische Bedrijfsinstallaties",
    "sg:phone":"+31 70 320 2224",
    "sg:postcode":"2264 TM",
    "sg:province":"Zuid-Holland",
    "wof:name":"H Wassen",
    "wof:placetype":"venue"
},
  "geometry": {"coordinates":[4.39309,52.090199],"type":"Point"}
}