{
  "type": "Feature",
  "properties": {
    "iso:country":"NL",
    "sg:address":"Postbus 1090",
    "sg:city":"Almere",
    "sg:orig_category":"Kunststofcoating",
    "sg:phone":"+31 36 532 6540",
    "sg:postcode":"1300 BB",
    "sg:website":"http://www.cocoon-holland.nl",
    "wof:name":"Cocoon Holland Bv",
    "wof:placetype":"venue"
},
  "geometry": {"coordinates":[5.22223,52.376591],"type":"Point"}
}