{
  "type": "Feature",
  "properties": {
    "iso:country":"NL",
    "sg:address":"Bladderswijk Oz 101",
    "sg:city":"Nieuw Dordrecht",
    "sg:orig_category":"Metaalbekleding And -Behandeling",
    "sg:phone":"+31 591 316 753",
    "sg:postcode":"7885 TK",
    "sg:province":"Drenthe",
    "wof:name":"Gereedschapslijperij Oranjedorp",
    "wof:placetype":"venue"
},
  "geometry": {"coordinates":[6.953506,52.734535],"type":"Point"}
}