{
  "type": "Feature",
  "properties": {
    "addr:full":"Van Panhuysstraat 16 Noordwijk Zh South Holland 2203 JR",
    "addr:housenumber":"16",
    "addr:postcode":"zh;2203 jr",
    "addr:street":"Van Panhuysstraat",
    "iso:country":"NL",
    "sg:address":"Van Panhuysstraat 16",
    "sg:city":"Noordwijk Zh",
    "sg:orig_category":"Woningbouwverenigingen",
    "sg:phone":"+31 71 361 1376",
    "sg:postcode":"2203 JR",
    "sg:province":"South Holland",
    "wof:name":"Noordwijkse Woningstichting",
    "wof:placetype":"venue"
},
  "geometry": {"coordinates":[4.4458031654,52.2415504456],"type":"Point"}
}