{
  "type": "Feature",
  "properties": {
    "iso:country":"NL",
    "sg:address":"Langestr 31",
    "sg:city":"S Gravenzande",
    "sg:classifiers":[
        {
            "category":"Professional",
            "subcategory":"Accounting & Tax Preparation",
            "type":"Services"
        }
    ],
    "sg:phone":"+31 174 445 464",
    "sg:postcode":"2691 BB",
    "sg:province":"South Holland",
    "sg:tags":[
        "accountant",
        "en",
        "-kantoren",
        "register-"
    ],
    "wof:name":"Veldhoven, Van",
    "wof:placetype":"venue"
},
  "geometry": {"coordinates":[4.159742,52.004517],"type":"Point"}
}