{
  "type": "Feature",
  "properties": {
    "addr:full":"Beerseweg 11 Oirschot Noord-Brabant 5688 HD",
    "addr:housenumber":"11",
    "addr:postcode":"5688 hd",
    "addr:street":"Beerseweg",
    "iso:country":"NL",
    "sg:address":"Beerseweg 11",
    "sg:city":"Oirschot",
    "sg:orig_category":"Fruit And Groenten Gh",
    "sg:phone":"+31 499 571 430",
    "sg:postcode":"5688 HD",
    "sg:province":"Noord-Brabant",
    "wof:name":"Quick Orange Oirschot Bv",
    "wof:placetype":"venue"
},
  "geometry": {"coordinates":[5.29681,51.495556],"type":"Point"}
}