{
  "type": "Feature",
  "properties": {
    "addr:full":"Markerstraat 9 Lemmer Provincie Friesland 8531 KM",
    "addr:housenumber":"9;8531",
    "addr:street":"Markerstraat;Provincie Friesland;Km",
    "iso:country":"NL",
    "sg:address":"Markerstraat 9",
    "sg:city":"Lemmer",
    "sg:classifiers":[
        {
            "category":"Education",
            "subcategory":"Preschool",
            "type":"Public Place"
        }
    ],
    "sg:phone":"+31 514 560 563",
    "sg:postcode":"8531 KM",
    "sg:province":"Provincie Friesland",
    "sg:tags":[
        "kleuteronderwijs",
        "basis-"
    ],
    "wof:name":"Daltonschool Sint Jozef",
    "wof:placetype":"venue"
},
  "geometry": {"coordinates":[5.71163,52.847321],"type":"Point"}
}