{
  "type": "Feature",
  "properties": {
    "iso:country":"NL",
    "sg:address":"Energiestr 6",
    "sg:city":"Geesbrug",
    "sg:orig_category":"Onderhoudswerken",
    "sg:phone":"+31 524 291 255",
    "sg:postcode":"7917 RA",
    "sg:province":"Drenthe",
    "wof:name":"Lowijs Vof",
    "wof:placetype":"venue"
},
  "geometry": {"coordinates":[6.611495,52.717289],"type":"Point"}
}