{
  "type": "Feature",
  "properties": {
    "addr:full":"Pylkruid 24 Kockengen Utrecht 3628 NP",
    "addr:housenumber":"24",
    "addr:postcode":"3628 np",
    "addr:street":"Pylkruid",
    "iso:country":"NL",
    "sg:address":"Pylkruid 24",
    "sg:city":"Kockengen",
    "sg:orig_category":"Autopoetsbedrijven",
    "sg:phone":"+31 346 250 277",
    "sg:postcode":"3628 NP",
    "sg:province":"Utrecht",
    "wof:name":"Dissel",
    "wof:placetype":"venue"
},
  "geometry": {"coordinates":[4.94939,52.148819],"type":"Point"}
}