{
  "type": "Feature",
  "properties": {
    "addr:full":"Sweilandstr 7A Warmond South Holland 2361 JA",
    "addr:housenumber":"7a",
    "addr:postcode":"2361 ja",
    "addr:street":"Sweilandstr",
    "iso:country":"NL",
    "sg:address":"Sweilandstr 7A",
    "sg:city":"Warmond",
    "sg:orig_category":"Jachthavens - Jachtwerven",
    "sg:phone":"+31 71 301 0378",
    "sg:postcode":"2361 JA",
    "sg:province":"South Holland",
    "wof:name":"Lockhorst Bv",
    "wof:placetype":"venue"
},
  "geometry": {"coordinates":[4.496819,52.191906],"type":"Point"}
}