{
  "type": "Feature",
  "properties": {
    "addr:full":"Tuinderstraat 11 Weert Limburg 6004 LD",
    "addr:housenumber":"11",
    "addr:postcode":"6004 ld",
    "addr:street":"Tuinderstraat",
    "iso:country":"NL",
    "sg:address":"Tuinderstraat 11",
    "sg:city":"Weert",
    "sg:orig_category":"Kappers",
    "sg:phone":"+31 495 541 313",
    "sg:postcode":"6004 LD",
    "sg:province":"Limburg",
    "wof:name":"H.G.L. Slenders",
    "wof:placetype":"venue"
},
  "geometry": {"coordinates":[5.7200331688,51.2508964539],"type":"Point"}
}