{
  "type": "Feature",
  "properties": {
    "addr:full":"Billitonstraat 10 Amersfoort Utrecht 3818 CN",
    "addr:housenumber":"10",
    "addr:postcode":"3818 cn",
    "addr:street":"Billitonstraat",
    "iso:country":"NL",
    "sg:address":"Billitonstraat 10",
    "sg:city":"Amersfoort",
    "sg:orig_category":"Boekhouders",
    "sg:phone":"+31 33 461 1366",
    "sg:postcode":"3818 CN",
    "sg:province":"Utrecht",
    "wof:name":"J. Zuydendorp",
    "wof:placetype":"venue"
},
  "geometry": {"coordinates":[5.372944,52.1367],"type":"Point"}
}