{
  "type": "Feature",
  "properties": {
    "addr:full":"Beltrumseweg 9 Groenlo Gelderland 7141 VJ",
    "addr:housenumber":"9",
    "addr:postcode":"7141 vj",
    "addr:street":"Beltrumseweg;Gelderland",
    "iso:country":"NL",
    "sg:address":"Beltrumseweg 9",
    "sg:city":"Groenlo",
    "sg:orig_category":"Landbouwmachines Gh",
    "sg:phone":"+31 544 461 949",
    "sg:postcode":"7141 VJ",
    "sg:province":"Gelderland",
    "wof:name":"Handelsonderneming Bumatrac",
    "wof:placetype":"venue"
},
  "geometry": {"coordinates":[6.601519,52.049465],"type":"Point"}
}