{
  "type": "Feature",
  "properties": {
    "iso:country":"NL",
    "sg:address":"Beltrumseweg 9",
    "sg:city":"Groenlo",
    "sg:orig_category":"Landbouwmachines Gh",
    "sg:phone":"+31 544 461 949",
    "sg:postcode":"7141 VJ",
    "sg:province":"Gelderland",
    "wof:name":"Handelsonderneming Bumatrac",
    "wof:placetype":"venue"
},
  "geometry": {"coordinates":[6.601519,52.049465],"type":"Point"}
}