{
  "type": "Feature",
  "properties": {
    "iso:country":"NL",
    "sg:address":"Oude Amersf Wg 114",
    "sg:city":"Hilversum",
    "sg:orig_category":"Psychologen",
    "sg:phone":"+31 35 772 0490",
    "sg:postcode":"1212 AJ",
    "sg:province":"North Holland",
    "wof:name":"Til, Drs R Van",
    "wof:placetype":"venue"
},
  "geometry": {"coordinates":[5.191318,52.218971],"type":"Point"}
}