{
  "type": "Feature",
  "properties": {
    "addr:full":"De Boelelaan 873 Amsterdam North Holland 1082 RW",
    "addr:housenumber":"873",
    "addr:postcode":"1082 rw",
    "addr:street":"De Boelelaan",
    "iso:country":"NL",
    "sg:address":"De Boelelaan 873",
    "sg:city":"Amsterdam",
    "sg:orig_category":"Bedrijfs- And Managementsconsultants",
    "sg:phone":"+31 20 301 1919",
    "sg:postcode":"1082 RW",
    "sg:province":"North Holland",
    "wof:name":"Publicis Consultants Bv",
    "wof:placetype":"venue"
},
  "geometry": {"coordinates":[4.871974,52.334599],"type":"Point"}
}