{
  "type": "Feature",
  "properties": {
    "addr:full":"Onderdk 189 Wervershoof Noord-Holland 1693 CE",
    "addr:housenumber":"189",
    "addr:postcode":"1693 ce",
    "iso:country":"NL",
    "sg:address":"Onderdk 189",
    "sg:city":"Wervershoof",
    "sg:classifiers":[
        {
            "category":"Travel",
            "subcategory":"Hotels & Motels",
            "type":"Entertainment"
        }
    ],
    "sg:phone":"+31 228 583 838",
    "sg:postcode":"1693 CE",
    "sg:province":"Noord-Holland",
    "wof:name":"Hart Van Onderdijk, 'T",
    "wof:placetype":"venue"
},
  "geometry": {"coordinates":[-39.34277,-5.32226],"type":"Point"}
}