{
  "type": "Feature",
  "properties": {
    "addr:full":"Paddeweg 39 Barendrecht South Holland 2992 CK",
    "addr:housenumber":"39",
    "addr:postcode":"2992 ck",
    "addr:street":"Paddeweg",
    "iso:country":"NL",
    "sg:address":"Paddeweg 39",
    "sg:city":"Barendrecht",
    "sg:orig_category":"Medische Apparatuur And Prothesen Fab",
    "sg:phone":"+31 180 618 780",
    "sg:postcode":"2992 CK",
    "sg:province":"South Holland",
    "wof:name":"T R Lodge Tandprothetische Praktijk",
    "wof:placetype":"venue"
},
  "geometry": {"coordinates":[4.531898,51.855122],"type":"Point"}
}