{
  "type": "Feature",
  "properties": {
    "addr:full":"Molenweg 1 Heerjansdam South Holland 2995 BK",
    "addr:housenumber":"1",
    "addr:postcode":"2995 bk",
    "addr:street":"Molenweg",
    "iso:country":"NL",
    "sg:address":"Molenweg 1",
    "sg:city":"Heerjansdam",
    "sg:orig_category":"Autokeuringen",
    "sg:phone":"+31 78 677 1506",
    "sg:postcode":"2995 BK",
    "sg:province":"South Holland",
    "wof:name":"Van Der Krans Auto'S",
    "wof:placetype":"venue"
},
  "geometry": {"coordinates":[4.56932,51.839878],"type":"Point"}
}