{
  "type": "Feature",
  "properties": {
    "iso:country":"NL",
    "sg:address":"Klinkstr 6A",
    "sg:city":"Oudenbosch",
    "sg:orig_category":"Keuringsdiensten",
    "sg:phone":"+31 165 305 070",
    "sg:postcode":"4731 DM",
    "sg:province":"North Brabant",
    "wof:name":"Rvv",
    "wof:placetype":"venue"
},
  "geometry": {"coordinates":[4.55237,51.592789],"type":"Point"}
}