{
  "type": "Feature",
  "properties": {
    "addr:full":"Pr Bernhardln 345 Voorburg South Holland 2273 DP",
    "addr:housenumber":"345",
    "addr:postcode":"2273 dp",
    "iso:country":"NL",
    "sg:address":"Pr Bernhardln 345",
    "sg:city":"Voorburg",
    "sg:classifiers":[
        {
            "category":"Personal",
            "subcategory":"Nail Salon",
            "type":"Services"
        }
    ],
    "sg:phone":"+31 70 383 3959",
    "sg:postcode":"2273 DP",
    "sg:province":"South Holland",
    "sg:tags":[
        "pedicure"
    ],
    "wof:name":"Graaf, De",
    "wof:placetype":"venue"
},
  "geometry": {"coordinates":[4.35977,52.07848],"type":"Point"}
}