{
  "type": "Feature",
  "properties": {
    "addr:full":"Virmundtstr 20 Gemert Noord-Brabant 5421 BW",
    "addr:housenumber":"20",
    "addr:postcode":"5421 bw",
    "addr:street":"Virmundtstr",
    "iso:country":"NL",
    "sg:address":"Virmundtstr 20",
    "sg:city":"Gemert",
    "sg:orig_category":"Manueel Therapeuten",
    "sg:phone":"+31 492 366 694",
    "sg:postcode":"5421 BW",
    "sg:province":"Noord-Brabant",
    "wof:name":"Erp, J M M Van",
    "wof:placetype":"venue"
},
  "geometry": {"coordinates":[5.683958,51.556122],"type":"Point"}
}