{
  "type": "Feature",
  "properties": {
    "addr:full":"Rynstr 52 Enschede Overijssel 7523 GG",
    "addr:housenumber":"52",
    "addr:postcode":"7523 gg",
    "addr:street":"Rynstr",
    "iso:country":"NL",
    "sg:address":"Rynstr 52",
    "sg:city":"Enschede",
    "sg:orig_category":"Drogisterijen",
    "sg:phone":"+31 53 436 2622",
    "sg:postcode":"7523 GG",
    "sg:province":"Overijssel",
    "wof:name":"Kruitvat",
    "wof:placetype":"venue"
},
  "geometry": {"coordinates":[6.89691,52.235901],"type":"Point"}
}