{
  "type": "Feature",
  "properties": {
    "iso:country":"NL",
    "sg:address":"Zwaluwenburg 10",
    "sg:city":"Deventer",
    "sg:classifiers":[
        {
            "category":"Education",
            "subcategory":"Preschool",
            "type":"Public Place"
        }
    ],
    "sg:phone":"+31 570 651 270",
    "sg:postcode":"7423 DS",
    "sg:province":"Overijssel",
    "sg:tags":[
        "kleuteronderwijs",
        "basis-"
    ],
    "wof:name":"Prins Mauritsschool",
    "wof:placetype":"venue"
},
  "geometry": {"coordinates":[6.207876,52.253948],"type":"Point"}
}