{
  "type": "Feature",
  "properties": {
    "addr:full":"Marktplein 3 'S Gravenzande Zuid-Holland 2691 BV",
    "addr:housenumber":"3 '",
    "addr:postcode":"2691 bv",
    "addr:street":"Marktplein",
    "iso:country":"NL",
    "sg:address":"Marktplein 3",
    "sg:city":"'S Gravenzande",
    "sg:orig_category":"Damesmodezaken",
    "sg:phone":"+31 174 417 800",
    "sg:postcode":"2691 BV",
    "sg:province":"Zuid-Holland",
    "wof:name":"Boetiek 'T Haantje 'S Gravenzande Bv",
    "wof:placetype":"venue"
},
  "geometry": {"coordinates":[4.161728,52.002632],"type":"Point"}
}