{
  "type": "Feature",
  "properties": {
    "addr:full":"Rooimond 7 Buurmalsen Gelderland 4197 BS",
    "addr:housenumber":"7",
    "addr:postcode":"4197 bs",
    "addr:street":"Rooimond;Gelderland",
    "iso:country":"NL",
    "sg:address":"Rooimond 7",
    "sg:city":"Buurmalsen",
    "sg:orig_category":"Architecten",
    "sg:phone":"+31 345 572 562",
    "sg:postcode":"4197 BS",
    "sg:province":"Gelderland",
    "wof:name":"Bolak",
    "wof:placetype":"venue"
},
  "geometry": {"coordinates":[5.294982,51.8936],"type":"Point"}
}