{
  "type": "Feature",
  "properties": {
    "addr:full":"Uijlenbroeklaan 37 Doetinchem Gelderland 7006 PM",
    "addr:housenumber":"37",
    "addr:postcode":"7006 pm",
    "addr:street":"Uijlenbroeklaan;Gelderland",
    "iso:country":"NL",
    "sg:address":"Uijlenbroeklaan 37",
    "sg:city":"Doetinchem",
    "sg:orig_category":"Boekhouders",
    "sg:phone":"+31 314 323 954",
    "sg:postcode":"7006 PM",
    "sg:province":"Gelderland",
    "wof:name":"G. Van Hattum",
    "wof:placetype":"venue"
},
  "geometry": {"coordinates":[6.267855,51.959892],"type":"Point"}
}