{
  "type": "Feature",
  "properties": {
    "iso:country":"NL",
    "sg:address":"Witterstraat 23",
    "sg:city":"Assen",
    "sg:orig_category":"Partycatering And -Organisatie",
    "sg:phone":"+31 592 354 581",
    "sg:postcode":"9401 SE",
    "sg:province":"Drenthe",
    "wof:name":"Pieke'S Catering",
    "wof:placetype":"venue"
},
  "geometry": {"coordinates":[6.549236,52.993221],"type":"Point"}
}