{
  "type": "Feature",
  "properties": {
    "addr:full":"Molenstr 59A Twello Gelderland 7391 AC",
    "addr:housenumber":"59a",
    "addr:postcode":"7391 ac",
    "addr:street":"Molenstr;Gelderland",
    "iso:country":"NL",
    "sg:address":"Molenstr 59A",
    "sg:city":"Twello",
    "sg:orig_category":"Machinehandel",
    "sg:phone":"+31 571 275 545",
    "sg:postcode":"7391 AC",
    "sg:province":"Gelderland",
    "wof:name":"Maarschalkerwaart & Co Bv, A V",
    "wof:placetype":"venue"
},
  "geometry": {"coordinates":[6.08446,52.233437],"type":"Point"}
}