{
  "type": "Feature",
  "properties": {
    "addr:full":"L Bisschopstr 37 Deventer NL.08 7411 KH",
    "addr:housenumber":"37;nl.08",
    "addr:postcode":"7411 kh",
    "iso:country":"NL",
    "sg:address":"L Bisschopstr 37",
    "sg:city":"Deventer",
    "sg:orig_category":"Juweliers",
    "sg:phone":"+31 570 641 889",
    "sg:postcode":"7411 KH",
    "sg:province":"NL.08",
    "wof:name":"Lucardi",
    "wof:placetype":"venue"
},
  "geometry": {"coordinates":[6.157307,52.253361],"type":"Point"}
}