{
  "type": "Feature",
  "properties": {
    "addr:full":"Middenweg 12 Leidschendam Zuid-Holland 2266 EZ",
    "addr:housenumber":"12",
    "addr:postcode":"2266 ez",
    "addr:street":"Middenweg",
    "iso:country":"NL",
    "sg:address":"Middenweg 12",
    "sg:city":"Leidschendam",
    "sg:orig_category":"Metaalwerken",
    "sg:phone":"+31 70 320 3459",
    "sg:postcode":"2266 EZ",
    "sg:province":"Zuid-Holland",
    "wof:name":"Andre Vd Loos Handelsonderneming",
    "wof:placetype":"venue"
},
  "geometry": {"coordinates":[4.465135,52.09568],"type":"Point"}
}