{
  "type": "Feature",
  "properties": {
    "addr:full":"Hamstr 50 Roermond Limburg 6041 HC",
    "addr:housenumber":"50",
    "addr:postcode":"6041 hc",
    "addr:street":"Hamstr",
    "iso:country":"NL",
    "sg:address":"Hamstr 50",
    "sg:city":"Roermond",
    "sg:orig_category":"Juweliers",
    "sg:phone":"+31 475 332 085",
    "sg:postcode":"6041 HC",
    "sg:province":"Limburg",
    "wof:name":"Engels Vof, H J J",
    "wof:placetype":"venue"
},
  "geometry": {"coordinates":[5.990111,51.193657],"type":"Point"}
}