{
  "type": "Feature",
  "properties": {
    "addr:full":"Zutphenseweg 8 Deventer Overijssel 7418 AJ",
    "addr:housenumber":"8",
    "addr:postcode":"7418 aj",
    "addr:street":"Zutphenseweg",
    "iso:country":"NL",
    "sg:address":"Zutphenseweg 8",
    "sg:city":"Deventer",
    "sg:classifiers":[
        {
            "category":"Travel",
            "subcategory":"Hotels & Motels",
            "type":"Entertainment"
        }
    ],
    "sg:phone":"+31 570 606 264",
    "sg:postcode":"7418 AJ",
    "sg:province":"Overijssel",
    "wof:name":"Kakelbont, Villa",
    "wof:placetype":"venue"
},
  "geometry": {"coordinates":[6.170046,52.24305],"type":"Point"}
}