{
  "type": "Feature",
  "properties": {
    "addr:full":"Het Ruim 11 Amersfoort Utrecht 3823 SG",
    "addr:housenumber":"11",
    "addr:postcode":"3823 sg",
    "addr:street":"Het Ruim",
    "iso:country":"NL",
    "sg:address":"Het Ruim 11",
    "sg:city":"Amersfoort",
    "sg:orig_category":"Vertalers",
    "sg:phone":"+31 33 455 4134",
    "sg:postcode":"3823 SG",
    "sg:province":"Utrecht",
    "wof:name":"Fasoglio, Drs Daniela",
    "wof:placetype":"venue"
},
  "geometry": {"coordinates":[5.387695,52.193916],"type":"Point"}
}