{
  "type": "Feature",
  "properties": {
    "addr:full":"Oeverlandenweg 1 Meppel Provincie Drenthe 7944 HZ",
    "addr:housenumber":"1",
    "addr:postcode":"7944 hz",
    "addr:street":"Oeverlandenweg;Provincie Drenthe",
    "iso:country":"NL",
    "sg:address":"Oeverlandenweg 1",
    "sg:city":"Meppel",
    "sg:orig_category":"Kantoorartikelen",
    "sg:phone":"+31 522 270 645",
    "sg:postcode":"7944 HZ",
    "sg:province":"Provincie Drenthe",
    "wof:name":"Huisman Bv",
    "wof:placetype":"venue"
},
  "geometry": {"coordinates":[6.1696748734,52.6898574829],"type":"Point"}
}