{
  "type": "Feature",
  "properties": {
    "addr:full":"Ryksstrwg 140 Haren Gn Groningen 9752 BL",
    "addr:housenumber":"140",
    "addr:postcode":"9752 bl",
    "iso:country":"NL",
    "sg:address":"Ryksstrwg 140",
    "sg:city":"Haren Gn",
    "sg:orig_category":"Kappers",
    "sg:phone":"+31 50 534 5266",
    "sg:postcode":"9752 BL",
    "sg:province":"Groningen",
    "wof:name":"Kraaima, H",
    "wof:placetype":"venue"
},
  "geometry": {"coordinates":[6.60632,53.170658],"type":"Point"}
}