{
  "type": "Feature",
  "properties": {
    "addr:full":"Korte Bunder 4 Hoeven Etten-Leur North Brabant 4741 PA",
    "addr:housenumber":"4",
    "addr:postcode":"4741 pa",
    "addr:street":"Korte Bunder",
    "iso:country":"NL",
    "sg:address":"Korte Bunder 4",
    "sg:city":"Hoeven Etten-Leur",
    "sg:orig_category":"Verhuur Bouwmachines",
    "sg:phone":"+31 165 504 646",
    "sg:postcode":"4741 PA",
    "sg:province":"North Brabant",
    "wof:name":"Luijkx",
    "wof:placetype":"venue"
},
  "geometry": {"coordinates":[4.587614,51.575447],"type":"Point"}
}