{
  "type": "Feature",
  "properties": {
    "addr:full":"Postbus 83016 Amsterdam Flevoland 1080 AA",
    "addr:postcode":"83016;1080 aa",
    "addr:street":"Postbus;Flevoland",
    "iso:country":"NL",
    "sg:address":"Postbus 83016",
    "sg:city":"Amsterdam",
    "sg:orig_category":"Grafisch Ontwerpers",
    "sg:phone":"+31 20 679 9668",
    "sg:postcode":"1080 AA",
    "sg:province":"Flevoland",
    "wof:name":"Bekkers",
    "wof:placetype":"venue"
},
  "geometry": {"coordinates":[4.89319,52.373119],"type":"Point"}
}