{
  "type": "Feature",
  "properties": {
    "iso:country":"NL",
    "sg:address":"Bedrijfsweg 6",
    "sg:city":"Vriezenveen",
    "sg:orig_category":"Verhuur Voertuigen Behalve Auto'S",
    "sg:phone":"+31 546 579 054",
    "sg:postcode":"7671 EG",
    "sg:province":"Overijssel",
    "wof:name":"Top Bv",
    "wof:placetype":"venue"
},
  "geometry": {"coordinates":[6.602487,52.4081],"type":"Point"}
}