{
  "type": "Feature",
  "properties": {
    "addr:full":"Dijk 129 Broek Op Langedijk Noord-Holland 1721 AD",
    "addr:housenumber":"129",
    "addr:postcode":"1721 ad",
    "addr:street":"Dijk",
    "iso:country":"NL",
    "sg:address":"Dijk 129",
    "sg:city":"Broek Op Langedijk",
    "sg:orig_category":"Autokeuringen",
    "sg:phone":"+31 226 316 178",
    "sg:postcode":"1721 AD",
    "sg:province":"Noord-Holland",
    "wof:name":"Vriend'S Garagebedrijf",
    "wof:placetype":"venue"
},
  "geometry": {"coordinates":[4.805615,52.67395],"type":"Point"}
}