{
  "type": "Feature",
  "properties": {
    "addr:full":"Industriewg 42 Middenmeer Noord-Holland 1775 PV",
    "addr:housenumber":"42",
    "addr:postcode":"1775 pv",
    "addr:street":"Industriewg",
    "iso:country":"NL",
    "sg:address":"Industriewg 42",
    "sg:city":"Middenmeer",
    "sg:orig_category":"Jachthavens - Jachtwerven",
    "sg:phone":"+31 227 501 771",
    "sg:postcode":"1775 PV",
    "sg:province":"Noord-Holland",
    "wof:name":"Klok",
    "wof:placetype":"venue"
},
  "geometry": {"coordinates":[4.998078,52.81905],"type":"Point"}
}