{
  "type": "Feature",
  "properties": {
    "addr:full":"Wg Naar Rhynauwen 10 Utrecht Utrecht 3584 AD",
    "addr:housenumber":"10",
    "addr:postcode":"3584 ad",
    "addr:street":"Wg",
    "iso:country":"NL",
    "sg:address":"Wg Naar Rhynauwen 10",
    "sg:city":"Utrecht",
    "sg:orig_category":"Bloemen En Planten",
    "sg:phone":"+31 30 251 2507",
    "sg:postcode":"3584 AD",
    "sg:province":"Utrecht",
    "wof:name":"Veronique",
    "wof:placetype":"venue"
},
  "geometry": {"coordinates":[5.158885,52.081451],"type":"Point"}
}