{
  "type": "Feature",
  "properties": {
    "addr:full":"Kofferen 19 St Oedenrode North Brabant 5492 BL",
    "addr:housenumber":"19",
    "addr:postcode":"5492 bl",
    "addr:street":"Kofferen",
    "iso:country":"NL",
    "sg:address":"Kofferen 19",
    "sg:city":"St Oedenrode",
    "sg:orig_category":"Fietsen En Bromfietsen",
    "sg:phone":"+31 413 477 722",
    "sg:postcode":"5492 BL",
    "sg:province":"North Brabant",
    "wof:name":"Goliat",
    "wof:placetype":"venue"
},
  "geometry": {"coordinates":[5.458122,51.561749],"type":"Point"}
}