{
  "type": "Feature",
  "properties": {
    "iso:country":"NL",
    "sg:address":"Emmastraat 2",
    "sg:city":"Hilversum",
    "sg:classifiers":[
        {
            "category":"Fast Food",
            "type":"Food & Drink"
        }
    ],
    "sg:phone":"+31 35 624 9580",
    "sg:postcode":"1211 NG",
    "sg:province":"Noord-Holland",
    "sg:tags":[
        "afhaal",
        "restaurant"
    ],
    "wof:name":"Mr Moto Japanese & Oriental",
    "wof:placetype":"venue"
},
  "geometry": {"coordinates":[5.177724,52.22187],"type":"Point"}
}