{
  "type": "Feature",
  "properties": {
    "addr:full":"Koolhovenstr 9-11 Schiedam South Holland 3125 BT",
    "addr:housenumber":"9-11",
    "addr:postcode":"3125 bt",
    "iso:country":"NL",
    "sg:address":"Koolhovenstr 9-11",
    "sg:city":"Schiedam",
    "sg:orig_category":"Machinefabrieken",
    "sg:phone":"+31 10 437 4888",
    "sg:postcode":"3125 BT",
    "sg:province":"South Holland",
    "wof:name":"Spraying Syst Ned Bv",
    "wof:placetype":"venue"
},
  "geometry": {"coordinates":[4.399523,51.93359],"type":"Point"}
}