{
  "type": "Feature",
  "properties": {
    "iso:country":"NL",
    "sg:address":"James Wattstraat 114",
    "sg:city":"Amsterdam",
    "sg:orig_category":"Autokeuringen",
    "sg:phone":"+31 20 694 3416",
    "sg:postcode":"1097 DM",
    "sg:province":"North Holland",
    "wof:name":"Landring Bv",
    "wof:placetype":"venue"
},
  "geometry": {"coordinates":[4.919086,52.349239],"type":"Point"}
}