{
  "type": "Feature",
  "properties": {
    "addr:full":"Lynmarkt 32-34 Utrecht Utrecht 3511 KJ",
    "addr:housenumber":"32-34",
    "addr:postcode":"3511 kj",
    "iso:country":"NL",
    "sg:address":"Lynmarkt 32-34",
    "sg:city":"Utrecht",
    "sg:orig_category":"Woninginrichting",
    "sg:phone":"+31 30 233 3307",
    "sg:postcode":"3511 KJ",
    "sg:province":"Utrecht",
    "wof:name":"Aba-I Bv",
    "wof:placetype":"venue"
},
  "geometry": {"coordinates":[5.1154050827,52.0889320374],"type":"Point"}
}