{
  "type": "Feature",
  "properties": {
    "iso:country":"NL",
    "sg:address":"Begoniastr 2",
    "sg:city":"Rotterdam",
    "sg:orig_category":"Schoenen - Reparaties",
    "sg:phone":"+31 10 418 2369",
    "sg:postcode":"3051 LC",
    "sg:province":"Zuid-Holland",
    "wof:name":"Zee & Zn Schoenherstelbedrijf, A",
    "wof:placetype":"venue"
},
  "geometry": {"coordinates":[4.473289,51.945026],"type":"Point"}
}