{
  "type": "Feature",
  "properties": {
    "addr:full":"Maaskd 76C Rotterdam South Holland 3071 ND",
    "addr:housenumber":"76c",
    "addr:postcode":"3071 nd",
    "addr:street":"Maaskd",
    "iso:country":"NL",
    "sg:address":"Maaskd 76C",
    "sg:city":"Rotterdam",
    "sg:orig_category":"Grafisch Ontwerpers",
    "sg:phone":"+31 10 413 7755",
    "sg:postcode":"3071 ND",
    "sg:province":"South Holland",
    "wof:name":"Stoute, Paul",
    "wof:placetype":"venue"
},
  "geometry": {"coordinates":[4.50327,51.910591],"type":"Point"}
}