{
  "type": "Feature",
  "properties": {
    "addr:full":"T Plein 38 Leusden Utrecht 3831 CR",
    "addr:housenumber":"38",
    "addr:postcode":"3831 cr",
    "addr:street":"T Plein",
    "iso:country":"NL",
    "sg:address":"T Plein 38",
    "sg:city":"Leusden",
    "sg:classifiers":[
        {
            "category":"Shopping",
            "subcategory":"Clothing, Apparel, & Fashions",
            "type":"Retail Goods"
        }
    ],
    "sg:phone":"+31 33 495 3343",
    "sg:postcode":"3831 CR",
    "sg:province":"Utrecht",
    "sg:tags":[
        "ondergoed",
        "lingerie"
    ],
    "wof:name":"Lincherie",
    "wof:placetype":"venue"
},
  "geometry": {"coordinates":[5.427393,52.128948],"type":"Point"}
}