{
  "type": "Feature",
  "properties": {
    "iso:country":"NL",
    "sg:address":"Nobelstraat 12",
    "sg:city":"Brielle",
    "sg:orig_category":"Kappers",
    "sg:phone":"+31 181 412 338",
    "sg:postcode":"3231 BC",
    "sg:province":"Zuid-Holland",
    "wof:name":"Haarmode Bisschops",
    "wof:placetype":"venue"
},
  "geometry": {"coordinates":[4.1644001007,51.9019241333],"type":"Point"}
}