{
  "type": "Feature",
  "properties": {
    "addr:full":"Gildenstraat 10 Nijkerk Gld Gelderland 3861 RG",
    "addr:housenumber":"10",
    "addr:postcode":"3861 rg",
    "addr:street":"Gildenstraat;Gld Gelderland",
    "iso:country":"NL",
    "sg:address":"Gildenstraat 10",
    "sg:city":"Nijkerk Gld",
    "sg:orig_category":"Metaalbekleding And -Behandeling",
    "sg:phone":"+31 33 245 2846",
    "sg:postcode":"3861 RG",
    "sg:province":"Gelderland",
    "wof:name":"Hardchroom Nijkerk Bv",
    "wof:placetype":"venue"
},
  "geometry": {"coordinates":[5.482962,52.232407],"type":"Point"}
}