{
  "type": "Feature",
  "properties": {
    "iso:country":"NL",
    "sg:address":"Merk 15",
    "sg:city":"Workum",
    "sg:classifiers":[
        {
            "category":"Food & Beverages",
            "subcategory":"Bakery",
            "type":"Retail Goods"
        }
    ],
    "sg:phone":"+31 515 541 208",
    "sg:postcode":"8711 CL",
    "sg:province":"Friesland",
    "sg:tags":[
        "brood",
        "en",
        "banket"
    ],
    "wof:name":"Keuning",
    "wof:placetype":"venue"
},
  "geometry": {"coordinates":[5.442352,52.979389],"type":"Point"}
}