{
  "type": "Feature",
  "properties": {
    "addr:full":"De Miede 1 Schagen North Holland 1741 DD",
    "addr:housenumber":"1",
    "addr:postcode":"1741 dd",
    "addr:street":"De Miede",
    "iso:country":"NL",
    "sg:address":"De Miede 1",
    "sg:city":"Schagen",
    "sg:orig_category":"Verenigingen En Stichtingen",
    "sg:phone":"+31 224 272 880",
    "sg:postcode":"1741 DD",
    "sg:province":"North Holland",
    "wof:name":"Welzijn Ouderen Schagen, Sticht",
    "wof:placetype":"venue"
},
  "geometry": {"coordinates":[4.808348,52.789124],"type":"Point"}
}