{
  "type": "Feature",
  "properties": {
    "addr:full":"Robijnweg 10 Amersfoort Utrecht 3817 GE",
    "addr:housenumber":"10",
    "addr:postcode":"3817",
    "addr:street":"Robijnweg",
    "iso:country":"NL",
    "sg:address":"Robijnweg 10",
    "sg:city":"Amersfoort",
    "sg:orig_category":"Makelaars In Onroerend Goed",
    "sg:phone":"+31 33 463 5294",
    "sg:postcode":"3817 GE",
    "sg:province":"Utrecht",
    "wof:name":"E.G.J. Scheerder",
    "wof:placetype":"venue"
},
  "geometry": {"coordinates":[5.400577,52.138725],"type":"Point"}
}