{
  "type": "Feature",
  "properties": {
    "addr:full":"Jonenstraat 10 Winterswijk Gelderland 7101 GA",
    "addr:housenumber":"10",
    "addr:postcode":"7101 ga",
    "addr:street":"Jonenstraat;Gelderland",
    "iso:country":"NL",
    "sg:address":"Jonenstraat 10",
    "sg:city":"Winterswijk",
    "sg:orig_category":"Fitnesscentra",
    "sg:phone":"+31 6 22205827",
    "sg:postcode":"7101 GA",
    "sg:province":"Gelderland",
    "wof:name":"Skate & Smile",
    "wof:placetype":"venue"
},
  "geometry": {"coordinates":[6.715469,51.97097],"type":"Point"}
}