{
  "type": "Feature",
  "properties": {
    "addr:full":"Floralaan 8 Lent Virginia 6663 BK",
    "addr:housenumber":"8",
    "addr:postcode":"6663 bk",
    "addr:street":"Floralaan",
    "iso:country":"NL",
    "sg:address":"Floralaan 8",
    "sg:city":"Lent",
    "sg:orig_category":"Vertaal- And Tolkenbureaus",
    "sg:phone":"+31 24 360 1923",
    "sg:postcode":"6663 BK",
    "sg:province":"Virginia",
    "wof:name":"Reversie Vertaal En Tolkbureau",
    "wof:placetype":"venue"
},
  "geometry": {"coordinates":[-77.241432,38.151344],"type":"Point"}
}