{
  "type": "Feature",
  "properties": {
    "iso:country":"NL",
    "sg:address":"Tolhusln 11-15",
    "sg:city":"Gorredyk",
    "sg:orig_category":"Verpakkingen En Verpakkingsmaterialen",
    "sg:phone":"+31 513 469 369",
    "sg:postcode":"8401 GA",
    "sg:province":"Friesland",
    "wof:name":"Medi-Pack Bv",
    "wof:placetype":"venue"
},
  "geometry": {"coordinates":[6.06447,53.00478],"type":"Point"}
}