{
  "type": "Feature",
  "properties": {
    "addr:full":"Utrechtsestr 38 Arnhem Gelderland 6811 LZ",
    "addr:housenumber":"38",
    "addr:postcode":"6811 lz",
    "addr:street":"Utrechtsestr",
    "iso:country":"NL",
    "sg:address":"Utrechtsestr 38",
    "sg:city":"Arnhem",
    "sg:orig_category":"Loopbaanbegeleiding",
    "sg:phone":"+31 26 389 2656",
    "sg:postcode":"6811 LZ",
    "sg:province":"Gelderland",
    "sg:website":"http://www.tempo-team.nl",
    "wof:name":"Tempo-Team Traject",
    "wof:placetype":"venue"
},
  "geometry": {"coordinates":[5.899159,51.983543],"type":"Point"}
}