{
  "type": "Feature",
  "properties": {
    "iso:country":"NL",
    "sg:address":"Steenwg 59",
    "sg:city":"Utrecht",
    "sg:orig_category":"Warenhuizen",
    "sg:phone":"+31 30 231 2507",
    "sg:postcode":"3511 JN",
    "sg:province":"Utrecht",
    "wof:name":"Hema",
    "wof:placetype":"venue"
},
  "geometry": {"coordinates":[5.1174678802,52.0908126831],"type":"Point"}
}