{
  "type": "Feature",
  "properties": {
    "addr:full":"Catsheuvel 6B S Gravenhage Zuid-Holland 2517 JZ",
    "addr:housenumber":"6b;gravenhage",
    "addr:postcode":"2517 jz",
    "addr:street":"Catsheuvel;S",
    "iso:country":"NL",
    "sg:address":"Catsheuvel 6B",
    "sg:city":"S Gravenhage",
    "sg:orig_category":"Organisatiebureaus",
    "sg:phone":"+31 70 350 6998",
    "sg:postcode":"2517 JZ",
    "sg:province":"Zuid-Holland",
    "sg:website":"http://www.benrutteman.nl",
    "wof:name":"Ben Rutteman Bv",
    "wof:placetype":"venue"
},
  "geometry": {"coordinates":[4.2870798111,52.0866699219],"type":"Point"}
}