{
  "type": "Feature",
  "properties": {
    "addr:full":"Elzenweike 5 Heibloem Limburg 6089 NR",
    "addr:housenumber":"5",
    "addr:postcode":"6089 nr",
    "addr:street":"Elzenweike",
    "iso:country":"NL",
    "sg:address":"Elzenweike 5",
    "sg:city":"Heibloem",
    "sg:orig_category":"Kantoorartikelen",
    "sg:phone":"+31 475 492 383",
    "sg:postcode":"6089 NR",
    "sg:province":"Limburg",
    "wof:name":"Boek En Kantoorboekhandel W.G.M.O. Caenen",
    "wof:placetype":"venue"
},
  "geometry": {"coordinates":[5.8986458778,51.3021316528],"type":"Point"}
}