{
  "type": "Feature",
  "properties": {
    "addr:full":"Bisonspoor 3006 Maarssen Utrecht 3605 LW",
    "addr:housenumber":"3006",
    "addr:postcode":"3605 lw",
    "addr:street":"Bisonspoor",
    "iso:country":"NL",
    "sg:address":"Bisonspoor 3006",
    "sg:city":"Maarssen",
    "sg:orig_category":"Verzekeringen",
    "sg:phone":"+31 346 553 370",
    "sg:postcode":"3605 LW",
    "sg:province":"Utrecht",
    "wof:name":"Rassurantien",
    "wof:placetype":"venue"
},
  "geometry": {"coordinates":[5.030646,52.135536],"type":"Point"}
}