{
  "type": "Feature",
  "properties": {
    "addr:full":"Stadhuisstr 62 Lelystad Flevoland 8232 VC",
    "addr:housenumber":"62",
    "addr:postcode":"8232 vc",
    "addr:street":"Stadhuisstr;Flevoland",
    "iso:country":"NL",
    "sg:address":"Stadhuisstr 62",
    "sg:city":"Lelystad",
    "sg:orig_category":"Bloemen En Planten",
    "sg:phone":"+31 320 232 639",
    "sg:postcode":"8232 VC",
    "sg:province":"Flevoland",
    "wof:name":"Kamphuis, Bloembinderij",
    "wof:placetype":"venue"
},
  "geometry": {"coordinates":[5.476396,52.506435],"type":"Point"}
}