{
  "type": "Feature",
  "properties": {
    "addr:full":"Duyvesteynstr 11 Rotterdam South Holland 3042 BA",
    "addr:housenumber":"11",
    "addr:postcode":"3042 ba",
    "addr:street":"Duyvesteynstr",
    "iso:country":"NL",
    "sg:address":"Duyvesteynstr 11",
    "sg:city":"Rotterdam",
    "sg:orig_category":"Juweliers",
    "sg:phone":"+31 10 415 7160",
    "sg:postcode":"3042 BA",
    "sg:province":"South Holland",
    "wof:name":"Sativar",
    "wof:placetype":"venue"
},
  "geometry": {"coordinates":[4.428244,51.933197],"type":"Point"}
}