{
  "type": "Feature",
  "properties": {
    "addr:full":"Nieuwstr 6 Koewacht Zeeland 4576 AL",
    "addr:housenumber":"6",
    "addr:postcode":"4576 al",
    "addr:street":"Nieuwstr",
    "iso:country":"NL",
    "sg:address":"Nieuwstr 6",
    "sg:city":"Koewacht",
    "sg:orig_category":"Koeriersdiensten",
    "sg:phone":"+31 114 361 369",
    "sg:postcode":"4576 AL",
    "sg:province":"Zeeland",
    "wof:name":"M & J Vof",
    "wof:placetype":"venue"
},
  "geometry": {"coordinates":[3.977129,51.225838],"type":"Point"}
}