{
  "type": "Feature",
  "properties": {
    "iso:country":"NL",
    "sg:address":"Oosterhof 3",
    "sg:city":"Katwijk Zh",
    "sg:orig_category":"Metaalafval, Schrootrecycling And Sloperijen",
    "sg:phone":"+31 71 407 3395",
    "sg:postcode":"2225 DW",
    "sg:province":"Zuid-Holland",
    "wof:name":"J Van Rijn Oud Ijzer & Metaal",
    "wof:placetype":"venue"
},
  "geometry": {"coordinates":[4.395798,52.202278],"type":"Point"}
}