{
  "type": "Feature",
  "properties": {
    "addr:full":"Dorpsstraat 35 Zieuwent Gelderland 7136 LE",
    "addr:housenumber":"35",
    "addr:postcode":"7136 le",
    "addr:street":"Dorpsstraat;Gelderland",
    "iso:country":"NL",
    "sg:address":"Dorpsstraat 35",
    "sg:city":"Zieuwent",
    "sg:orig_category":"Fietshandelaren",
    "sg:phone":"+31 544 352 254",
    "sg:postcode":"7136 LE",
    "sg:province":"Gelderland",
    "wof:name":"P Knippenborg",
    "wof:placetype":"venue"
},
  "geometry": {"coordinates":[6.520759,52.001972],"type":"Point"}
}