{
  "type": "Feature",
  "properties": {
    "iso:country":"NL",
    "sg:address":"Dorpsstr 46-48",
    "sg:city":"Nieuwegein",
    "sg:orig_category":"Woninginrichting",
    "sg:phone":"+31 30 606 2837",
    "sg:postcode":"3433 CL",
    "sg:province":"Utrecht",
    "wof:name":"Sluys Bv",
    "wof:placetype":"venue"
},
  "geometry": {"coordinates":[5.0949068069,52.0042915344],"type":"Point"}
}