{
  "type": "Feature",
  "properties": {
    "iso:country":"NL",
    "sg:address":"Van Der Driftstraat 73",
    "sg:city":"Vlaardingen",
    "sg:orig_category":"Kappers",
    "sg:phone":"+31 10 434 6207",
    "sg:postcode":"3131 JG",
    "sg:province":"South Holland",
    "wof:name":"Haarmode Louise",
    "wof:placetype":"venue"
},
  "geometry": {"coordinates":[4.3361649513,51.9129905701],"type":"Point"}
}