{
  "type": "Feature",
  "properties": {
    "iso:country":"NL",
    "sg:address":"Jan Rebelstraat 18B",
    "sg:city":"Amsterdam",
    "sg:orig_category":"Keramische Producten Fab",
    "sg:phone":"+31 20 669 6360",
    "sg:postcode":"1069 CC",
    "sg:province":"Noord-Holland",
    "wof:name":"Pottenbakkerij 'T Spinnewiel",
    "wof:placetype":"venue"
},
  "geometry": {"coordinates":[4.78598,52.361336],"type":"Point"}
}