{
  "type": "Feature",
  "properties": {
    "addr:full":"Maasdijk 52 Poederoijen Gelderland 5307 HR",
    "addr:housenumber":"52",
    "addr:postcode":"5307 hr",
    "addr:street":"Maasdijk;Gelderland",
    "iso:country":"NL",
    "sg:address":"Maasdijk 52",
    "sg:city":"Poederoijen",
    "sg:orig_category":"Goederenvervoer Over De Weg",
    "sg:phone":"+31 418 671 341",
    "sg:postcode":"5307 HR",
    "sg:province":"Gelderland",
    "wof:name":"J. Bok Bloemenexpresse",
    "wof:placetype":"venue"
},
  "geometry": {"coordinates":[5.078781,51.784439],"type":"Point"}
}