{
  "type": "Feature",
  "properties": {
    "addr:full":"Liendenhof 71 Amsterdam Zuidoost North Holland 1108 HC",
    "addr:housenumber":"71",
    "addr:postcode":"1108 hc",
    "addr:street":"Liendenhof",
    "iso:country":"NL",
    "sg:address":"Liendenhof 71",
    "sg:city":"Amsterdam Zuidoost",
    "sg:orig_category":"Journalisten Freelance",
    "sg:phone":"+31 20 451 1000",
    "sg:postcode":"1108 HC",
    "sg:province":"North Holland",
    "wof:name":"Nation, Fitzroy",
    "wof:placetype":"venue"
},
  "geometry": {"coordinates":[4.984389,52.308666],"type":"Point"}
}