{
  "type": "Feature",
  "properties": {
    "addr:full":"Gr Sabinastr 16 Zuid Beyerland South Holland 3284 AP",
    "addr:housenumber":"16",
    "addr:postcode":"3284 ap",
    "addr:street":"Beyerland",
    "iso:country":"NL",
    "sg:address":"Gr Sabinastr 16",
    "sg:city":"Zuid Beyerland",
    "sg:orig_category":"Verzekeringen - Verzekeringskantoren",
    "sg:phone":"+31 186 662 010",
    "sg:postcode":"3284 AP",
    "sg:province":"South Holland",
    "wof:name":"Wfd",
    "wof:placetype":"venue"
},
  "geometry": {"coordinates":[4.32028,51.754093],"type":"Point"}
}