{
  "type": "Feature",
  "properties": {
    "addr:full":"Kloosterln 51 Bergen Nh North Holland 1861 SC",
    "addr:housenumber":"51",
    "addr:postcode":"1861 sc",
    "addr:street":"Kloosterln",
    "iso:country":"NL",
    "sg:address":"Kloosterln 51",
    "sg:city":"Bergen Nh",
    "sg:orig_category":"Webdesign Bureaus",
    "sg:phone":"+31 72 589 9604",
    "sg:postcode":"1861 SC",
    "sg:province":"North Holland",
    "wof:name":"Proruit",
    "wof:placetype":"venue"
},
  "geometry": {"coordinates":[4.7055840492,52.6638145447],"type":"Point"}
}