{
  "type": "Feature",
  "properties": {
    "addr:full":"Laat 187 Alkmaar North Holland 1811 EG",
    "addr:housenumber":"187",
    "addr:postcode":"1811 eg",
    "addr:street":"Laat",
    "iso:country":"NL",
    "sg:address":"Laat 187",
    "sg:city":"Alkmaar",
    "sg:orig_category":"Juweliers",
    "sg:phone":"+31 72 511 4320",
    "sg:postcode":"1811 EG",
    "sg:province":"North Holland",
    "sg:website":"http://www.ibink.nl",
    "wof:name":"Ibink Bv",
    "wof:placetype":"venue"
},
  "geometry": {"coordinates":[4.746401,52.630554],"type":"Point"}
}