{
  "type": "Feature",
  "properties": {
    "addr:full":"Telingstr 9 Utrecht Utrecht 3512 GV",
    "addr:housenumber":"9",
    "addr:postcode":"3512 gv",
    "addr:street":"Telingstr",
    "iso:country":"NL",
    "sg:address":"Telingstr 9",
    "sg:city":"Utrecht",
    "sg:orig_category":"Woninginrichting",
    "sg:phone":"+31 30 276 7203",
    "sg:postcode":"3512 GV",
    "sg:province":"Utrecht",
    "sg:website":"http://www.bartletts.nl",
    "wof:name":"Bartlett'S",
    "wof:placetype":"venue"
},
  "geometry": {"coordinates":[5.1200041771,52.0927696228],"type":"Point"}
}