{
  "type": "Feature",
  "properties": {
    "addr:full":"Westkapelsewg 1 Zoutelande Zeeland 4374 BA",
    "addr:housenumber":"1",
    "addr:postcode":"4374 ba",
    "addr:street":"Westkapelsewg",
    "iso:country":"NL",
    "sg:address":"Westkapelsewg 1",
    "sg:city":"Zoutelande",
    "sg:classifiers":[
        {
            "category":"Travel",
            "subcategory":"Hotels & Motels",
            "type":"Entertainment"
        }
    ],
    "sg:phone":"+31 118 562 040",
    "sg:postcode":"4374 BA",
    "sg:province":"Zeeland",
    "wof:name":"Distel, De",
    "wof:placetype":"venue"
},
  "geometry": {"coordinates":[3.478543,51.501888],"type":"Point"}
}