{
  "type": "Feature",
  "properties": {
    "addr:full":"Ruysln 65 De Koog North Holland 1796 AC",
    "addr:housenumber":"65",
    "addr:postcode":"1796 ac",
    "addr:street":"Ruysln",
    "iso:country":"NL",
    "sg:address":"Ruysln 65",
    "sg:city":"De Koog",
    "sg:orig_category":"Verenigingen En Stichtingen",
    "sg:phone":"+31 222 317 662",
    "sg:postcode":"1796 AC",
    "sg:province":"North Holland",
    "wof:name":"Texel Vakantie Gehandicapten, Sticht",
    "wof:placetype":"venue"
},
  "geometry": {"coordinates":[4.764149,53.09808],"type":"Point"}
}