{
  "type": "Feature",
  "properties": {
    "addr:full":"Benedenstr 3 S Heerenhoek Zeeland 4453 CG",
    "addr:housenumber":"3",
    "addr:postcode":"4453 cg",
    "addr:street":"Benedenstr;S Heerenhoek Zeeland",
    "iso:country":"NL",
    "sg:address":"Benedenstr 3",
    "sg:city":"S Heerenhoek",
    "sg:orig_category":"Huidtherapeuten",
    "sg:phone":"+31 113 350 702",
    "sg:postcode":"4453 CG",
    "sg:province":"Zeeland",
    "wof:name":"Verton-Steggerda, G",
    "wof:placetype":"venue"
},
  "geometry": {"coordinates":[3.768581,51.451859],"type":"Point"}
}