{
  "type": "Feature",
  "properties": {
    "iso:country":"NL",
    "sg:address":"Jan Steenstraat 102",
    "sg:city":"Woerden",
    "sg:classifiers":[
        {
            "category":"Education",
            "subcategory":"Preschool",
            "type":"Public Place"
        }
    ],
    "sg:phone":"+31 348 414 691",
    "sg:postcode":"3443 GZ",
    "sg:province":"Utrecht",
    "sg:tags":[
        "kleuteronderwijs",
        "basis-"
    ],
    "wof:name":"De Kring Jenaplanschool",
    "wof:placetype":"venue"
},
  "geometry": {"coordinates":[4.864667,52.088745],"type":"Point"}
}