{
  "type": "Feature",
  "properties": {
    "addr:full":"Reeuwykse Poort 311B Reeuwyk Zuid-Holland 2811 NV",
    "addr:housenumber":"311b",
    "addr:postcode":"2811 nv",
    "addr:street":"Poort",
    "iso:country":"NL",
    "sg:address":"Reeuwykse Poort 311B",
    "sg:city":"Reeuwyk",
    "sg:orig_category":"Adviesbureaus Bedrijfsorganisatie",
    "sg:phone":"+31 182 300 297",
    "sg:postcode":"2811 NV",
    "sg:province":"Zuid-Holland",
    "wof:name":"Key Information Bv",
    "wof:placetype":"venue"
},
  "geometry": {"coordinates":[4.728349,52.056152],"type":"Point"}
}