{
  "type": "Feature",
  "properties": {
    "addr:full":"Kerkewyk 27 Veenendaal Utrecht 3901 EB",
    "addr:housenumber":"27",
    "addr:postcode":"3901 eb",
    "addr:street":"Kerkewyk",
    "iso:country":"NL",
    "sg:address":"Kerkewyk 27",
    "sg:city":"Veenendaal",
    "sg:orig_category":"Bloemen En Planten",
    "sg:phone":"+31 318 519 479",
    "sg:postcode":"3901 EB",
    "sg:province":"Utrecht",
    "wof:name":"Manen, Wout Van",
    "wof:placetype":"venue"
},
  "geometry": {"coordinates":[5.554009,52.02433],"type":"Point"}
}