{
  "type": "Feature",
  "properties": {
    "addr:full":"Lorentzweg 21 Lekkerkerk South Holland 2941 VC",
    "addr:housenumber":"21",
    "addr:postcode":"2941 vc",
    "addr:street":"Lorentzweg",
    "iso:country":"NL",
    "sg:address":"Lorentzweg 21",
    "sg:city":"Lekkerkerk",
    "sg:orig_category":"Granen, Zaden And Diervoeders Gh",
    "sg:phone":"+31 180 661 353",
    "sg:postcode":"2941 VC",
    "sg:province":"South Holland",
    "wof:name":"Fa C Van Limborgh & Zn",
    "wof:placetype":"venue"
},
  "geometry": {"coordinates":[4.681458,51.898289],"type":"Point"}
}