{
  "type": "Feature",
  "properties": {
    "iso:country":"NL",
    "sg:address":"Lierwg 65",
    "sg:city":"De Lier",
    "sg:orig_category":"Loodgieters",
    "sg:phone":"+31 174 518 070",
    "sg:postcode":"2678 CT",
    "sg:province":"Zuid-Holland",
    "wof:name":"Vis Bv",
    "wof:placetype":"venue"
},
  "geometry": {"coordinates":[4.260898,51.977097],"type":"Point"}
}