{
  "type": "Feature",
  "properties": {
    "addr:full":"B Ingenhoesln 134 Voorburg Zuid-Holland 2273 KT",
    "addr:housenumber":"134",
    "addr:postcode":"2273 kt",
    "iso:country":"NL",
    "sg:address":"B Ingenhoesln 134",
    "sg:city":"Voorburg",
    "sg:orig_category":"Administratie- En Boekhoudkantoren",
    "sg:phone":"+31 70 387 6571",
    "sg:postcode":"2273 KT",
    "sg:province":"Zuid-Holland",
    "wof:name":"Burg, P L Van Der",
    "wof:placetype":"venue"
},
  "geometry": {"coordinates":[4.35977,52.07848],"type":"Point"}
}