{
  "type": "Feature",
  "properties": {
    "addr:full":"Venewg 155 Wanneperveen Overijssel 7946 LL",
    "addr:housenumber":"155",
    "addr:postcode":"7946 ll",
    "iso:country":"NL",
    "sg:address":"Venewg 155",
    "sg:city":"Wanneperveen",
    "sg:orig_category":"Bloemen En Planten",
    "sg:phone":"+31 522 281 158",
    "sg:postcode":"7946 LL",
    "sg:province":"Overijssel",
    "wof:name":"Seco",
    "wof:placetype":"venue"
},
  "geometry": {"coordinates":[6.104725,52.697342],"type":"Point"}
}