{
  "type": "Feature",
  "properties": {
    "iso:country":"NL",
    "sg:address":"Utrechtsestr 38F",
    "sg:city":"Arnhem",
    "sg:orig_category":"Werving En Selectie",
    "sg:phone":"+31 26 443 3333",
    "sg:postcode":"6811 LZ",
    "sg:province":"Gelderland",
    "sg:website":"http://www.pci.nl",
    "wof:name":"Pci Consultants",
    "wof:placetype":"venue"
},
  "geometry": {"coordinates":[5.8991589546,51.983543396],"type":"Point"}
}