{
  "type": "Feature",
  "properties": {
    "addr:full":"Dekkerswg 7 Lewedorp Zeeland 4456 NT",
    "addr:housenumber":"7",
    "addr:postcode":"4456 nt",
    "addr:street":"Dekkerswg",
    "iso:country":"NL",
    "sg:address":"Dekkerswg 7",
    "sg:city":"Lewedorp",
    "sg:orig_category":"Pluimveebedrijven En -Handelaren",
    "sg:phone":"+31 113 613 306",
    "sg:postcode":"4456 NT",
    "sg:province":"Zeeland",
    "wof:name":"Fokke, A J",
    "wof:placetype":"venue"
},
  "geometry": {"coordinates":[3.735389,51.484085],"type":"Point"}
}