{
  "type": "Feature",
  "properties": {
    "addr:full":"Nieuwestreek 21 Ezinge Groningen 9891 AA",
    "addr:housenumber":"21",
    "addr:postcode":"9891 aa",
    "addr:street":"Nieuwestreek",
    "iso:country":"NL",
    "sg:address":"Nieuwestreek 21",
    "sg:city":"Ezinge",
    "sg:orig_category":"Autokeuringen",
    "sg:phone":"+31 594 621 209",
    "sg:postcode":"9891 AA",
    "sg:province":"Groningen",
    "wof:name":"Garage Molenheem",
    "wof:placetype":"venue"
},
  "geometry": {"coordinates":[6.44357,53.307407],"type":"Point"}
}