{
  "type": "Feature",
  "properties": {
    "addr:full":"Noordstraat 12 Sas Van Gent Zeeland 4551 BJ",
    "addr:housenumber":"12",
    "addr:postcode":"4551 bj",
    "addr:street":"Noordstraat",
    "iso:country":"NL",
    "sg:address":"Noordstraat 12",
    "sg:city":"Sas Van Gent",
    "sg:orig_category":"Zuivelproducten",
    "sg:phone":"+31 115 454 485",
    "sg:postcode":"4551 BJ",
    "sg:province":"Zeeland",
    "wof:name":"Fromagerie Jalex",
    "wof:placetype":"venue"
},
  "geometry": {"coordinates":[3.799765,51.228584],"type":"Point"}
}