{
  "type": "Feature",
  "properties": {
    "addr:full":"De Zanden 17A Teuge Gelderland 7395 PA",
    "addr:housenumber":"17a",
    "addr:postcode":"7395",
    "addr:street":"De Zanden;Gelderland",
    "iso:country":"NL",
    "sg:address":"De Zanden 17A",
    "sg:city":"Teuge",
    "sg:orig_category":"Luchtvaart Zonder Dienstregeling",
    "sg:phone":"+31 55 323 2808",
    "sg:postcode":"7395 PA",
    "sg:province":"Gelderland",
    "wof:name":"Air Center Teuge Bv",
    "wof:placetype":"venue"
},
  "geometry": {"coordinates":[6.046359,52.240784],"type":"Point"}
}