{
  "type": "Feature",
  "properties": {
    "addr:full":"Eduard Van Wegbergplein 7 Heythuysen Limburg 6093  E",
    "addr:housenumber":"7;6093",
    "addr:street":"Eduard Van Wegbergplein;E",
    "iso:country":"NL",
    "sg:address":"Eduard Van Wegbergplein 7",
    "sg:city":"Heythuysen",
    "sg:orig_category":"Boekenuitgeverijen",
    "sg:phone":"+31 475 440 115",
    "sg:postcode":"6093  E",
    "sg:province":"Limburg",
    "wof:name":"Bruna",
    "wof:placetype":"venue"
},
  "geometry": {"coordinates":[5.894743,51.249462],"type":"Point"}
}