{
  "type": "Feature",
  "properties": {
    "iso:country":"NL",
    "sg:address":"Eduard Van Wegbergplein 7",
    "sg:city":"Heythuysen",
    "sg:orig_category":"Boekenuitgeverijen",
    "sg:phone":"+31 475 440 115",
    "sg:postcode":"6093  E",
    "sg:province":"Limburg",
    "wof:name":"Bruna",
    "wof:placetype":"venue"
},
  "geometry": {"coordinates":[5.894743,51.249462],"type":"Point"}
}