{
  "type": "Feature",
  "properties": {
    "addr:full":"Vivaldistr 11 Twello Gelderland 7391 ST",
    "addr:housenumber":"11",
    "addr:postcode":"7391 st",
    "addr:street":"Vivaldistr;Gelderland",
    "iso:country":"NL",
    "sg:address":"Vivaldistr 11",
    "sg:city":"Twello",
    "sg:orig_category":"Beeldende Kunstenaars",
    "sg:phone":"+31 571 273 695",
    "sg:postcode":"7391 ST",
    "sg:province":"Gelderland",
    "wof:name":"Bos, J",
    "wof:placetype":"venue"
},
  "geometry": {"coordinates":[6.102225,52.228561],"type":"Point"}
}