{
  "type": "Feature",
  "properties": {
    "iso:country":"NL",
    "sg:address":"Groenedk 41",
    "sg:city":"Utrecht",
    "sg:orig_category":"Boekhandels",
    "sg:phone":"+31 30 662 2055",
    "sg:postcode":"3544 AB",
    "sg:province":"Utrecht",
    "wof:name":"Media Expresse",
    "wof:placetype":"venue"
},
  "geometry": {"coordinates":[5.061068,52.086918],"type":"Point"}
}