{
  "type": "Feature",
  "properties": {
    "addr:full":"Nieuwe Binnenweg 277 Rotterdam South Holland 3021 GE",
    "addr:housenumber":"277",
    "addr:postcode":"3021",
    "addr:street":"Nieuwe Binnenweg",
    "iso:country":"NL",
    "sg:address":"Nieuwe Binnenweg 277",
    "sg:city":"Rotterdam",
    "sg:classifiers":[
        {
            "category":"Fast Food",
            "type":"Food & Drink"
        }
    ],
    "sg:phone":"+31 10 477 6626",
    "sg:postcode":"3021 GE",
    "sg:province":"South Holland",
    "sg:tags":[
        "afhaal",
        "restaurant"
    ],
    "wof:name":"Cafetaria Welkom",
    "wof:placetype":"venue"
},
  "geometry": {"coordinates":[4.459,51.913136],"type":"Point"}
}