{
  "type": "Feature",
  "properties": {
    "addr:full":"De Ambachten 106 Heeze Noord-Brabant 5591 NK",
    "addr:housenumber":"106",
    "addr:postcode":"5591 nk",
    "addr:street":"De Ambachten",
    "iso:country":"NL",
    "sg:address":"De Ambachten 106",
    "sg:city":"Heeze",
    "sg:orig_category":"Goederenvervoer Over De Weg",
    "sg:phone":"+31 40 226 2500",
    "sg:postcode":"5591 NK",
    "sg:province":"Noord-Brabant",
    "wof:name":"Internationaal Transportbedrijf Guitjens",
    "wof:placetype":"venue"
},
  "geometry": {"coordinates":[5.562032,51.384132],"type":"Point"}
}