{
  "type": "Feature",
  "properties": {
    "iso:country":"NL",
    "sg:address":"Canterstate 69",
    "sg:city":"Leeuwarden",
    "sg:orig_category":"Bedrijfsopleidingen",
    "sg:phone":"+31 58 844 5003",
    "sg:postcode":"8925 BG",
    "sg:province":"Friesland",
    "wof:name":"Squaw Peak",
    "wof:placetype":"venue"
},
  "geometry": {"coordinates":[5.835303,53.208401],"type":"Point"}
}