{
  "type": "Feature",
  "properties": {
    "iso:country":"NL",
    "sg:address":"Houtensewg 6",
    "sg:city":"Odyk",
    "sg:orig_category":"Loonbedrijven",
    "sg:phone":"+31 30 657 1021",
    "sg:postcode":"3984 LJ",
    "sg:province":"Utrecht",
    "wof:name":"Sturkenboom Vof",
    "wof:placetype":"venue"
},
  "geometry": {"coordinates":[5.23238,52.050835],"type":"Point"}
}