{
  "type": "Feature",
  "properties": {
    "addr:full":"Mathenesserlaan 540 Rotterdam Zuid-Holland 3023 HL",
    "addr:housenumber":"540",
    "addr:postcode":"3023 hl",
    "addr:street":"Mathenesserlaan",
    "iso:country":"NL",
    "sg:address":"Mathenesserlaan 540",
    "sg:city":"Rotterdam",
    "sg:orig_category":"Werving And Selectie Van Vast Personeel",
    "sg:phone":"+31 10 403 9500",
    "sg:postcode":"3023 HL",
    "sg:province":"Zuid-Holland",
    "wof:name":"Gewestelijk Arbeidsbureau",
    "wof:placetype":"venue"
},
  "geometry": {"coordinates":[4.4461421967,51.9164123535],"type":"Point"}
}