{
  "type": "Feature",
  "properties": {
    "addr:full":"Wilhelminastraat 46 Eijsden Limburg 6245 AX",
    "addr:housenumber":"46",
    "addr:postcode":"6245 ax",
    "addr:street":"Wilhelminastraat",
    "iso:country":"NL",
    "sg:address":"Wilhelminastraat 46",
    "sg:city":"Eijsden",
    "sg:orig_category":"Bedrijfsinventaris Gh",
    "sg:phone":"+31 43 409 1243",
    "sg:postcode":"6245 AX",
    "sg:province":"Limburg",
    "wof:name":"J.H.M. Liegeois-V.D. Heuvel",
    "wof:placetype":"venue"
},
  "geometry": {"coordinates":[5.705845,50.773857],"type":"Point"}
}