{
  "type": "Feature",
  "properties": {
    "addr:full":"Hoofdstr 120 Stadskanaal Groningen 9501 CR",
    "addr:housenumber":"120",
    "addr:postcode":"9501 cr",
    "addr:street":"Stadskanaal",
    "iso:country":"NL",
    "sg:address":"Hoofdstr 120",
    "sg:city":"Stadskanaal",
    "sg:orig_category":"Koffie- En Theehuizen",
    "sg:phone":"+31 599 610 852",
    "sg:postcode":"9501 CR",
    "sg:province":"Groningen",
    "wof:name":"Wiz Art",
    "wof:placetype":"venue"
},
  "geometry": {"coordinates":[6.962967,52.980728],"type":"Point"}
}