{
  "type": "Feature",
  "properties": {
    "addr:full":"Westerse Drift 17 Haren Gn Groningen 9752 LA",
    "addr:housenumber":"17",
    "addr:postcode":"9752 la",
    "addr:street":"Westerse Drift",
    "iso:country":"NL",
    "sg:address":"Westerse Drift 17",
    "sg:city":"Haren Gn",
    "sg:orig_category":"Architecten",
    "sg:phone":"+31 50 534 6923",
    "sg:postcode":"9752 LA",
    "sg:province":"Groningen",
    "wof:name":"B H Boersma Advisering Verkeer En Vervoe",
    "wof:placetype":"venue"
},
  "geometry": {"coordinates":[6.600257,53.170532],"type":"Point"}
}