{
  "type": "Feature",
  "properties": {
    "addr:full":"Veneweg 264 Wanneperveen Overijssel 7946 LW",
    "addr:housenumber":"264",
    "addr:postcode":"7946 lw",
    "addr:street":"Veneweg",
    "iso:country":"NL",
    "sg:address":"Veneweg 264",
    "sg:city":"Wanneperveen",
    "sg:orig_category":"Kampeerterreinen",
    "sg:phone":"+31 522 281 393",
    "sg:postcode":"7946 LW",
    "sg:province":"Overijssel",
    "wof:name":"Watersport Camping De Bolder",
    "wof:placetype":"venue"
},
  "geometry": {"coordinates":[6.0894198418,52.6950454712],"type":"Point"}
}