{
  "type": "Feature",
  "properties": {
    "addr:full":"Operawg 77 Amersfoort Utrecht 3816 EC",
    "addr:housenumber":"77",
    "addr:postcode":"3816 ec",
    "addr:street":"Operawg",
    "iso:country":"NL",
    "sg:address":"Operawg 77",
    "sg:city":"Amersfoort",
    "sg:orig_category":"Kinderopvang",
    "sg:phone":"+31 33 472 5684",
    "sg:postcode":"3816 EC",
    "sg:province":"Utrecht",
    "wof:name":"Anthea",
    "wof:placetype":"venue"
},
  "geometry": {"coordinates":[5.413018,52.156925],"type":"Point"}
}