{
  "type": "Feature",
  "properties": {
    "addr:full":"Sasput 11 Schoondijke Zeeland 4507 JV",
    "addr:housenumber":"11",
    "addr:postcode":"4507 jv",
    "addr:street":"Sasput",
    "iso:country":"NL",
    "sg:address":"Sasput 11",
    "sg:city":"Schoondijke",
    "sg:orig_category":"Vakantieverblijven",
    "sg:phone":"+31 117 348 278",
    "sg:postcode":"4507 JV",
    "sg:province":"Zeeland",
    "wof:name":"Cvjm",
    "wof:placetype":"venue"
},
  "geometry": {"coordinates":[3.602491,51.373104],"type":"Point"}
}