{
  "type": "Feature",
  "properties": {
    "addr:full":"Markt 16 Makkum Fr Friesland 8754 ES",
    "addr:housenumber":"16",
    "addr:postcode":"8754 es",
    "addr:street":"Markt",
    "iso:country":"NL",
    "sg:address":"Markt 16",
    "sg:city":"Makkum Fr",
    "sg:orig_category":"Kinderkleding",
    "sg:phone":"+31 515 232 156",
    "sg:postcode":"8754 ES",
    "sg:province":"Friesland",
    "wof:name":"Roos",
    "wof:placetype":"venue"
},
  "geometry": {"coordinates":[5.403231,53.055241],"type":"Point"}
}