{
  "type": "Feature",
  "properties": {
    "addr:full":"Zomerdijk 90 Zwartsluis Overijssel 8064 XH",
    "addr:housenumber":"90",
    "addr:postcode":"8064 xh",
    "addr:street":"Zomerdijk",
    "iso:country":"NL",
    "sg:address":"Zomerdijk 90",
    "sg:city":"Zwartsluis",
    "sg:orig_category":"Autokeuringen",
    "sg:phone":"+31 38 386 7977",
    "sg:postcode":"8064 XH",
    "sg:province":"Overijssel",
    "wof:name":"Autobedrijf John De Rijk",
    "wof:placetype":"venue"
},
  "geometry": {"coordinates":[6.084056,52.64579],"type":"Point"}
}