{
  "type": "Feature",
  "properties": {
    "iso:country":"NL",
    "sg:address":"Dijkhuizenweg 5",
    "sg:city":"Appingedam",
    "sg:classifiers":[
        {
            "category":"Education",
            "subcategory":"Preschool",
            "type":"Public Place"
        }
    ],
    "sg:phone":"+31 596 680 003",
    "sg:postcode":"9903 AA",
    "sg:province":"Groningen",
    "sg:tags":[
        "kleuteronderwijs",
        "basis-"
    ],
    "wof:name":"Christelijke Basisschool De Citer",
    "wof:placetype":"venue"
},
  "geometry": {"coordinates":[6.85216,53.319599],"type":"Point"}
}