{
  "type": "Feature",
  "properties": {
    "iso:country":"NL",
    "sg:address":"Het Kleine Loo 12",
    "sg:city":"'S Gravenhage",
    "sg:orig_category":"Sportcentra",
    "sg:phone":"+31 70 385 5838",
    "sg:postcode":"2592 CE",
    "sg:province":"Zuid-Holland",
    "wof:name":"Sporthand Het Kleine Loo Bv",
    "wof:placetype":"venue"
},
  "geometry": {"coordinates":[4.350848,52.088493],"type":"Point"}
}