{
  "type": "Feature",
  "properties": {
    "iso:country":"NL",
    "sg:address":"De Ness 7",
    "sg:city":"Linschoten",
    "sg:orig_category":"Verzekeringen",
    "sg:phone":"+31 348 412 935",
    "sg:postcode":"3461 GC",
    "sg:province":"Utrecht",
    "wof:name":"Assurantiekantoor Possel",
    "wof:placetype":"venue"
},
  "geometry": {"coordinates":[4.91766,52.061455],"type":"Point"}
}