{
  "type": "Feature",
  "properties": {
    "addr:full":"Damlaan 36 Leidschendam South Holland 2265 AN",
    "addr:housenumber":"36",
    "addr:postcode":"2265 an",
    "addr:street":"Damlaan",
    "iso:country":"NL",
    "sg:address":"Damlaan 36",
    "sg:city":"Leidschendam",
    "sg:orig_category":"Werving And Selectie Van Tijdelijk Personeel And Uitzendkantoren",
    "sg:phone":"+31 70 357 5780",
    "sg:postcode":"2265 AN",
    "sg:province":"South Holland",
    "wof:name":"Randstad Uitzendbureau Bv",
    "wof:placetype":"venue"
},
  "geometry": {"coordinates":[4.3959078789,52.0822143555],"type":"Point"}
}