{
  "type": "Feature",
  "properties": {
    "addr:full":"Gerstakker 53 Waddinxveen Zuid-Holland 2743 ES",
    "addr:housenumber":"53",
    "addr:postcode":"2743 es",
    "addr:street":"Gerstakker",
    "iso:country":"NL",
    "sg:address":"Gerstakker 53",
    "sg:city":"Waddinxveen",
    "sg:orig_category":"Fitnesscentra",
    "sg:phone":"+31 182 619 477",
    "sg:postcode":"2743 ES",
    "sg:province":"Zuid-Holland",
    "wof:name":"Sportinstituut Timmers",
    "wof:placetype":"venue"
},
  "geometry": {"coordinates":[4.639079,52.035728],"type":"Point"}
}