{
  "type": "Feature",
  "properties": {
    "addr:full":"De La Reyweg 807 'S Gravenhage Zuid-Holland 2571 EW",
    "addr:housenumber":"807 '",
    "addr:postcode":"2571 ew",
    "addr:street":"De La Reyweg",
    "iso:country":"NL",
    "sg:address":"De La Reyweg 807",
    "sg:city":"'S Gravenhage",
    "sg:orig_category":"Metaalwerken",
    "sg:phone":"+31 6 53129101",
    "sg:postcode":"2571 EW",
    "sg:province":"Zuid-Holland",
    "wof:name":"Neijts & Paul Vof",
    "wof:placetype":"venue"
},
  "geometry": {"coordinates":[4.291885,52.060093],"type":"Point"}
}