{
  "type": "Feature",
  "properties": {
    "addr:full":"F Kortlangln 140 Ermelo Gelderland 3853 KJ",
    "addr:housenumber":"140",
    "addr:postcode":"3853 kj",
    "addr:street":"Gelderland",
    "iso:country":"NL",
    "sg:address":"F Kortlangln 140",
    "sg:city":"Ermelo",
    "sg:orig_category":"Meubelmakerijen",
    "sg:phone":"+31 341 415 743",
    "sg:postcode":"3853 KJ",
    "sg:province":"Gelderland",
    "wof:name":"Vries, Meubelmakerij De",
    "wof:placetype":"venue"
},
  "geometry": {"coordinates":[5.610595,52.319958],"type":"Point"}
}