{
  "type": "Feature",
  "properties": {
    "addr:full":"Langestraat 21 Amersfoort Utrecht 3811 AA",
    "addr:housenumber":"21",
    "addr:postcode":"3811 aa",
    "addr:street":"Langestraat",
    "iso:country":"NL",
    "sg:address":"Langestraat 21",
    "sg:city":"Amersfoort",
    "sg:orig_category":"Opticiens",
    "sg:phone":"+31 33 461 3887",
    "sg:postcode":"3811 AA",
    "sg:province":"Utrecht",
    "wof:name":"Pearle Opticiens",
    "wof:placetype":"venue"
},
  "geometry": {"coordinates":[5.3860850334,52.1523246765],"type":"Point"}
}