{
  "type": "Feature",
  "properties": {
    "addr:full":"Treubstr 13B Ryswyk Zh Zuid-Holland 2288 EG",
    "addr:housenumber":"13b ryswyk",
    "addr:postcode":"2288 eg",
    "addr:street":"Treubstr",
    "iso:country":"NL",
    "sg:address":"Treubstr 13B",
    "sg:city":"Ryswyk Zh",
    "sg:orig_category":"Bedrijfshuisvesting",
    "sg:phone":"+31 70 319 1519",
    "sg:postcode":"2288 EG",
    "sg:province":"Zuid-Holland",
    "sg:website":"http://www.bedrijfhuisvesting.net",
    "wof:name":"Evion Bv",
    "wof:placetype":"venue"
},
  "geometry": {"coordinates":[4.32436,52.037251],"type":"Point"}
}