{
  "type": "Feature",
  "properties": {
    "addr:full":"Essenln 44A Sassenheim Zuid-Holland 2172 BX",
    "addr:housenumber":"44a",
    "addr:postcode":"2172 bx",
    "addr:street":"Essenln",
    "iso:country":"NL",
    "sg:address":"Essenln 44A",
    "sg:city":"Sassenheim",
    "sg:orig_category":"Verzekeringen - Verzekeringskantoren",
    "sg:phone":"+31 252 241 222",
    "sg:postcode":"2172 BX",
    "sg:province":"Zuid-Holland",
    "wof:name":"Faber",
    "wof:placetype":"venue"
},
  "geometry": {"coordinates":[4.528609,52.222134],"type":"Point"}
}