{
  "type": "Feature",
  "properties": {
    "addr:full":"Dorpstr 90 Westervoort Gelderland 6931 BM",
    "addr:housenumber":"90",
    "addr:postcode":"6931 bm",
    "addr:street":"Dorpstr;Gelderland",
    "iso:country":"NL",
    "sg:address":"Dorpstr 90",
    "sg:city":"Westervoort",
    "sg:orig_category":"Fietsen En Bromfietsen",
    "sg:phone":"+31 26 311 6743",
    "sg:postcode":"6931 BM",
    "sg:province":"Gelderland",
    "sg:website":"http://www.reerinkrijwielen.nl",
    "wof:name":"Reerink Rijwielen",
    "wof:placetype":"venue"
},
  "geometry": {"coordinates":[5.969097,51.963608],"type":"Point"}
}