{
  "type": "Feature",
  "properties": {
    "addr:full":"Zadelmakersln 3 Heythuysen Limburg 6093 GN",
    "addr:housenumber":"3",
    "addr:postcode":"6093 gn",
    "addr:street":"Zadelmakersln",
    "iso:country":"NL",
    "sg:address":"Zadelmakersln 3",
    "sg:city":"Heythuysen",
    "sg:orig_category":"Koel- En Vriestransporten",
    "sg:phone":"+31 475 492 112",
    "sg:postcode":"6093 GN",
    "sg:province":"Limburg",
    "wof:name":"Pouls, A",
    "wof:placetype":"venue"
},
  "geometry": {"coordinates":[5.90106,51.251026],"type":"Point"}
}