{
  "type": "Feature",
  "properties": {
    "iso:country":"NL",
    "sg:address":"Aploniastraat 11",
    "sg:city":"Rotterdam",
    "sg:orig_category":"Metaalwerken",
    "sg:phone":"+31 10 480 4465",
    "sg:postcode":"3084 CC",
    "sg:province":"Zuid-Holland",
    "wof:name":"Stardac Bv",
    "wof:placetype":"venue"
},
  "geometry": {"coordinates":[4.455426,51.867126],"type":"Point"}
}