{
  "type": "Feature",
  "properties": {
    "addr:full":"Maasstr 6 Amsterdam North Holland 1078 HJ",
    "addr:housenumber":"6",
    "addr:postcode":"1078 hj",
    "addr:street":"Maasstr",
    "iso:country":"NL",
    "sg:address":"Maasstr 6",
    "sg:city":"Amsterdam",
    "sg:orig_category":"Kappers",
    "sg:phone":"+31 20 679 9575",
    "sg:postcode":"1078 HJ",
    "sg:province":"North Holland",
    "wof:name":"Ligne S",
    "wof:placetype":"venue"
},
  "geometry": {"coordinates":[4.894959,52.347569],"type":"Point"}
}