{
  "type": "Feature",
  "properties": {
    "iso:country":"NL",
    "sg:address":"Oostermeent-Oost 22",
    "sg:city":"Huizen",
    "sg:orig_category":"Verlichting And Huishoudartikelen",
    "sg:phone":"+31 35 526 7781",
    "sg:postcode":"1274 SM",
    "sg:province":"Noord-Holland",
    "wof:name":"B & C Electronic Services",
    "wof:placetype":"venue"
},
  "geometry": {"coordinates":[5.263944,52.294277],"type":"Point"}
}