{
  "type": "Feature",
  "properties": {
    "addr:full":"Zeewg 75 Ermelo Gelderland 3853 LK",
    "addr:housenumber":"75",
    "addr:postcode":"3853 lk",
    "addr:street":"Zeewg;Gelderland",
    "iso:country":"NL",
    "sg:address":"Zeewg 75",
    "sg:city":"Ermelo",
    "sg:orig_category":"Poeliers",
    "sg:phone":"+31 341 561 977",
    "sg:postcode":"3853 LK",
    "sg:province":"Gelderland",
    "sg:website":"http://www.bloemendaal-kipworstproducten.nl",
    "wof:name":"Bloemendaal Vof, Van",
    "wof:placetype":"venue"
},
  "geometry": {"coordinates":[5.583327,52.304611],"type":"Point"}
}