{
  "type": "Feature",
  "properties": {
    "addr:full":"Kastanjewg 7 Hoogezand Groningen 9603 DE",
    "addr:housenumber":"7",
    "addr:postcode":"9603 de",
    "addr:street":"Kastanjewg",
    "iso:country":"NL",
    "sg:address":"Kastanjewg 7",
    "sg:city":"Hoogezand",
    "sg:orig_category":"Grondwerken",
    "sg:phone":"+31 598 326 642",
    "sg:postcode":"9603 DE",
    "sg:province":"Groningen",
    "wof:name":"Kroon, J",
    "wof:placetype":"venue"
},
  "geometry": {"coordinates":[6.757008,53.149632],"type":"Point"}
}