{
  "type": "Feature",
  "properties": {
    "addr:full":"Grotestraat 218 Waalwijk North Brabant 5141 HE",
    "addr:housenumber":"218",
    "addr:postcode":"5141 he",
    "addr:street":"Grotestraat",
    "iso:country":"NL",
    "sg:address":"Grotestraat 218",
    "sg:city":"Waalwijk",
    "sg:orig_category":"Kappers",
    "sg:phone":"+31 416 650 589",
    "sg:postcode":"5141 HE",
    "sg:province":"North Brabant",
    "wof:name":"Walter De Rooij Coiffures",
    "wof:placetype":"venue"
},
  "geometry": {"coordinates":[5.067086,51.690407],"type":"Point"}
}