{
  "type": "Feature",
  "properties": {
    "iso:country":"NL",
    "sg:address":"Handelswg 7",
    "sg:city":"Vlissingen",
    "sg:orig_category":"Zonweringen",
    "sg:phone":"+31 118 616 334",
    "sg:postcode":"4387 PC",
    "sg:province":"Zeeland",
    "wof:name":"Hiwako",
    "wof:placetype":"venue"
},
  "geometry": {"coordinates":[3.593087,51.471973],"type":"Point"}
}