{
  "type": "Feature",
  "properties": {
    "iso:country":"NL",
    "sg:address":"Rhoneweg 28",
    "sg:city":"Amsterdam",
    "sg:orig_category":"Loodgieterswerk, Verwarming And Sanitaire Installaties",
    "sg:phone":"+31 20 616 6464",
    "sg:postcode":"1043 AH",
    "sg:province":"North Holland",
    "wof:name":"E.S.C. Totaaltechniek Bv",
    "wof:placetype":"venue"
},
  "geometry": {"coordinates":[4.828062,52.390362],"type":"Point"}
}