{
  "type": "Feature",
  "properties": {
    "addr:full":"Lorentzkd 56 Haarlem Noord-Holland 2014 CB",
    "addr:housenumber":"56",
    "addr:postcode":"2014 cb",
    "addr:street":"Lorentzkd",
    "iso:country":"NL",
    "sg:address":"Lorentzkd 56",
    "sg:city":"Haarlem",
    "sg:orig_category":"Balletscholen",
    "sg:phone":"+31 23 529 0019",
    "sg:postcode":"2014 CB",
    "sg:province":"Noord-Holland",
    "wof:name":"Arabesque",
    "wof:placetype":"venue"
},
  "geometry": {"coordinates":[4.60983,52.370762],"type":"Point"}
}