{
  "type": "Feature",
  "properties": {
    "addr:full":"Stadhoudersln 32 Veenendaal Utrecht 3905 HD",
    "addr:housenumber":"32",
    "addr:postcode":"3905 hd",
    "addr:street":"Stadhoudersln",
    "iso:country":"NL",
    "sg:address":"Stadhoudersln 32",
    "sg:city":"Veenendaal",
    "sg:orig_category":"Adviesbureaus Bouwkunde",
    "sg:phone":"+31 318 520 116",
    "sg:postcode":"3905 HD",
    "sg:province":"Utrecht",
    "wof:name":"Vermeulen Bv",
    "wof:placetype":"venue"
},
  "geometry": {"coordinates":[5.55418,52.024902],"type":"Point"}
}