{
  "type": "Feature",
  "properties": {
    "addr:full":"Weverstr 25 Oosterbeek Gelderland 6862 DJ",
    "addr:housenumber":"25",
    "addr:postcode":"6862 dj",
    "addr:street":"Weverstr;Gelderland",
    "iso:country":"NL",
    "sg:address":"Weverstr 25",
    "sg:city":"Oosterbeek",
    "sg:classifiers":[
        {
            "category":"Farming",
            "subcategory":"Fish & Marine Products",
            "type":"Manufacturing & Wholesale Goods"
        }
    ],
    "sg:phone":"+31 26 333 2517",
    "sg:postcode":"6862 DJ",
    "sg:province":"Gelderland",
    "sg:tags":[
        "vi"
    ],
    "wof:name":"Vos",
    "wof:placetype":"venue"
},
  "geometry": {"coordinates":[5.843943,51.986305],"type":"Point"}
}