{
  "type": "Feature",
  "properties": {
    "addr:full":"De Els 21 Waalwijk Noord-Brabant 5141 HH",
    "addr:housenumber":"21",
    "addr:postcode":"5141 hh",
    "addr:street":"De Els",
    "iso:country":"NL",
    "sg:address":"De Els 21",
    "sg:city":"Waalwijk",
    "sg:orig_category":"Boekenuitgeverijen",
    "sg:phone":"+31 416 337 409",
    "sg:postcode":"5141 HH",
    "sg:province":"Noord-Brabant",
    "wof:name":"De Boekelier",
    "wof:placetype":"venue"
},
  "geometry": {"coordinates":[5.065067,51.690182],"type":"Point"}
}