{
  "type": "Feature",
  "properties": {
    "addr:full":"Gildeplein 96 Purmerend North Holland 1445  B",
    "addr:housenumber":"96;1445 b",
    "addr:street":"Gildeplein",
    "iso:country":"NL",
    "sg:address":"Gildeplein 96",
    "sg:city":"Purmerend",
    "sg:orig_category":"Visspeciaalzaken",
    "sg:phone":"+31 299 645 500",
    "sg:postcode":"1445  B",
    "sg:province":"North Holland",
    "wof:name":"Volendammer Vishandel De Boer",
    "wof:placetype":"venue"
},
  "geometry": {"coordinates":[4.985187,52.505997],"type":"Point"}
}