{
  "type": "Feature",
  "properties": {
    "addr:full":"Dracht 32 Heerenveen Provincie Friesland 8442 BR",
    "addr:housenumber":"32",
    "addr:postcode":"8442 br",
    "addr:street":"Dracht;Provincie Friesland",
    "iso:country":"NL",
    "sg:address":"Dracht 32",
    "sg:city":"Heerenveen",
    "sg:classifiers":[
        {
            "category":"Food & Beverages",
            "subcategory":"Candy",
            "type":"Retail Goods"
        }
    ],
    "sg:phone":"+31 513 624 969",
    "sg:postcode":"8442 BR",
    "sg:province":"Provincie Friesland",
    "sg:tags":[
        "sport-",
        "en",
        "spelartikelen"
    ],
    "wof:name":"Vries, Jac De",
    "wof:placetype":"venue"
},
  "geometry": {"coordinates":[5.924322,52.958717],"type":"Point"}
}