{
  "type": "Feature",
  "properties": {
    "iso:country":"NL",
    "sg:address":"Baan 29",
    "sg:city":"Haarlem",
    "sg:orig_category":"Architecten",
    "sg:phone":"+31 23 534 6109",
    "sg:postcode":"2012 DC",
    "sg:province":"Noord-Holland",
    "wof:name":"Ir Thijs Asselbergs Architect Bna Bv",
    "wof:placetype":"venue"
},
  "geometry": {"coordinates":[4.632796,52.374271],"type":"Point"}
}