{
  "type": "Feature",
  "properties": {
    "addr:full":"Spoorstr 5 Amersfoort Utrecht 3811 MN",
    "addr:housenumber":"5",
    "addr:postcode":"3811 mn",
    "addr:street":"Spoorstr",
    "iso:country":"NL",
    "sg:address":"Spoorstr 5",
    "sg:city":"Amersfoort",
    "sg:classifiers":[
        {
            "category":"Professional",
            "subcategory":"Accounting & Tax Preparation",
            "type":"Services"
        }
    ],
    "sg:phone":"+31 33 461 4898",
    "sg:postcode":"3811 MN",
    "sg:province":"Utrecht",
    "sg:tags":[
        "accountant",
        "en",
        "-kantoren",
        "register-"
    ],
    "wof:name":"Kuiter En Partn, B G M",
    "wof:placetype":"venue"
},
  "geometry": {"coordinates":[5.38021,52.153606],"type":"Point"}
}