{
  "type": "Feature",
  "properties": {
    "iso:country":"NL",
    "sg:address":"De Savornin Lohmanstraat 58",
    "sg:city":"Veenendaal",
    "sg:orig_category":"Visspeciaalzaken",
    "sg:phone":"+31 318 512 877",
    "sg:postcode":"3904 AT",
    "sg:province":"Utrecht",
    "wof:name":"Vishandel Rosendaal",
    "wof:placetype":"venue"
},
  "geometry": {"coordinates":[5.544269,52.017723],"type":"Point"}
}