{
  "type": "Feature",
  "properties": {
    "addr:full":"Langestr 127 Klazienaveen Provincie Drenthe 7891 GH",
    "addr:housenumber":"127",
    "addr:postcode":"7891 gh",
    "addr:street":"Provincie Drenthe",
    "iso:country":"NL",
    "sg:address":"Langestr 127",
    "sg:city":"Klazienaveen",
    "sg:orig_category":"Opticiens",
    "sg:phone":"+31 591 311 823",
    "sg:postcode":"7891 GH",
    "sg:province":"Provincie Drenthe",
    "wof:name":"Guido",
    "wof:placetype":"venue"
},
  "geometry": {"coordinates":[6.991092205,52.7245941162],"type":"Point"}
}