{
  "type": "Feature",
  "properties": {
    "iso:country":"NL",
    "sg:address":"Ticheldobben 7",
    "sg:city":"Ten Boer",
    "sg:orig_category":"Banken And Kredietinstellingen",
    "sg:phone":"+31 50 302 1340",
    "sg:postcode":"9791 CZ",
    "sg:province":"Groningen",
    "wof:name":"Postkantoor",
    "wof:placetype":"venue"
},
  "geometry": {"coordinates":[6.691104,53.274445],"type":"Point"}
}