{
  "type": "Feature",
  "properties": {
    "addr:full":"De Bongerd 69 Doetinchem Gelderland 7006 NH",
    "addr:housenumber":"69",
    "addr:postcode":"7006 nh",
    "addr:street":"De Bongerd;Gelderland",
    "iso:country":"NL",
    "sg:address":"De Bongerd 69",
    "sg:city":"Doetinchem",
    "sg:orig_category":"Postkantoren",
    "sg:phone":"+31 314 345 655",
    "sg:postcode":"7006 NH",
    "sg:province":"Gelderland",
    "sg:website":"http://www.postkantoor.nl",
    "wof:name":"Postkantoor",
    "wof:placetype":"venue"
},
  "geometry": {"coordinates":[6.257434,51.961189],"type":"Point"}
}