{
  "type": "Feature",
  "properties": {
    "iso:country":"NL",
    "sg:address":"Het Horseler 1",
    "sg:city":"Warnsveld",
    "sg:classifiers":[
        {
            "category":"Education",
            "subcategory":"Preschool",
            "type":"Public Place"
        }
    ],
    "sg:phone":"+31 575 528 011",
    "sg:postcode":"7232 GA",
    "sg:province":"Gelderland",
    "sg:tags":[
        "kleuteronderwijs",
        "basis-"
    ],
    "wof:name":"Christelijke Basisschool Arcade",
    "wof:placetype":"venue"
},
  "geometry": {"coordinates":[6.234415,52.129501],"type":"Point"}
}