{
  "type": "Feature",
  "properties": {
    "addr:full":"Baliendijk 10 Breda Noord-Brabant 4816 GD",
    "addr:housenumber":"10",
    "addr:postcode":"4816 gd",
    "addr:street":"Baliendijk",
    "iso:country":"NL",
    "sg:address":"Baliendijk 10",
    "sg:city":"Breda",
    "sg:orig_category":"Medische Apparatuur And Prothesen Fab",
    "sg:phone":"+31 76 572 9800",
    "sg:postcode":"4816 GD",
    "sg:province":"Noord-Brabant",
    "wof:name":"Tandtechnisch Laboratorium Van Der Wal",
    "wof:placetype":"venue"
},
  "geometry": {"coordinates":[4.792596817,51.5986595154],"type":"Point"}
}