{
  "type": "Feature",
  "properties": {
    "addr:full":"Servetstraat 3 Rhenen Utrecht 3911 KW",
    "addr:housenumber":"3",
    "addr:postcode":"3911 kw",
    "addr:street":"Servetstraat",
    "iso:country":"NL",
    "sg:address":"Servetstraat 3",
    "sg:city":"Rhenen",
    "sg:orig_category":"Fitnesscentra",
    "sg:phone":"+31 317 612 592",
    "sg:postcode":"3911 KW",
    "sg:province":"Utrecht",
    "wof:name":"Sport Studio Hasselaar",
    "wof:placetype":"venue"
},
  "geometry": {"coordinates":[5.564585,51.958122],"type":"Point"}
}