{
  "type": "Feature",
  "properties": {
    "addr:full":"Tamboerynstr 15 Amersfoort Utrecht 3822 DG",
    "addr:housenumber":"15",
    "addr:postcode":"3822 dg",
    "addr:street":"Tamboerynstr",
    "iso:country":"NL",
    "sg:address":"Tamboerynstr 15",
    "sg:city":"Amersfoort",
    "sg:orig_category":"Plafonds",
    "sg:phone":"+31 33 465 7598",
    "sg:postcode":"3822 DG",
    "sg:province":"Utrecht",
    "wof:name":"Burgt, S Van De",
    "wof:placetype":"venue"
},
  "geometry": {"coordinates":[5.402758,52.18541],"type":"Point"}
}