{
  "type": "Feature",
  "properties": {
    "addr:full":"Christinastraat 1 Mierlo North Brabant 5731 BL",
    "addr:housenumber":"1",
    "addr:postcode":"5731 bl",
    "addr:street":"Christinastraat",
    "iso:country":"NL",
    "sg:address":"Christinastraat 1",
    "sg:city":"Mierlo",
    "sg:classifiers":[
        {
            "category":"Fast Food",
            "type":"Food & Drink"
        }
    ],
    "sg:phone":"+31 492 662 450",
    "sg:postcode":"5731 BL",
    "sg:province":"North Brabant",
    "sg:tags":[
        "afhaal",
        "restaurant"
    ],
    "wof:name":"Vof Cafetaria 'T Huukske",
    "wof:placetype":"venue"
},
  "geometry": {"coordinates":[5.617074,51.441147],"type":"Point"}
}