{
  "type": "Feature",
  "properties": {
    "addr:full":"Ln V Westroyen 2A Tiel Gelderland 4003 AZ",
    "addr:housenumber":"2a",
    "addr:postcode":"4003",
    "addr:street":"Ln;Westroyen;Gelderland",
    "iso:country":"NL",
    "sg:address":"Ln V Westroyen 2A",
    "sg:city":"Tiel",
    "sg:classifiers":[
        {
            "category":"Wholesale",
            "subcategory":"Meat",
            "type":"Manufacturing & Wholesale Goods"
        }
    ],
    "sg:phone":"+31 344 631 130",
    "sg:postcode":"4003 AZ",
    "sg:province":"Gelderland",
    "sg:tags":[
        "regeltechniek",
        "en",
        "meet-"
    ],
    "sg:website":"http://www.langegroep.nl",
    "wof:name":"Lange Group Benelux, Dr",
    "wof:placetype":"venue"
},
  "geometry": {"coordinates":[5.430696,51.888096],"type":"Point"}
}