{
  "type": "Feature",
  "properties": {
    "iso:country":"NL",
    "sg:address":"De Hemmen 28",
    "sg:city":"Drachten",
    "sg:orig_category":"Puien",
    "sg:phone":"+31 512 586 958",
    "sg:postcode":"9206 AG",
    "sg:province":"Friesland",
    "sg:website":"http://www.polyprofiel.nl",
    "wof:name":"Variso Fa\u00e7ade",
    "wof:placetype":"venue"
},
  "geometry": {"coordinates":[6.075029,53.112312],"type":"Point"}
}