{
  "type": "Feature",
  "properties": {
    "addr:full":"Anjerstr 33 Rotterdam Zuid-Holland 3071 VA",
    "addr:housenumber":"33",
    "addr:postcode":"3071",
    "addr:street":"Anjerstr",
    "iso:country":"NL",
    "sg:address":"Anjerstr 33",
    "sg:city":"Rotterdam",
    "sg:orig_category":"Video - Faciliteiten En Producties",
    "sg:phone":"+31 10 433 2151",
    "sg:postcode":"3071 VA",
    "sg:province":"Zuid-Holland",
    "wof:name":"Bolek",
    "wof:placetype":"venue"
},
  "geometry": {"coordinates":[4.494847,51.912407],"type":"Point"}
}