{
  "type": "Feature",
  "properties": {
    "addr:full":"Steenpoortestr 34 Andyk Noord-Holland 1619 CV",
    "addr:housenumber":"34",
    "addr:postcode":"1619 cv",
    "addr:street":"Steenpoortestr",
    "iso:country":"NL",
    "sg:address":"Steenpoortestr 34",
    "sg:city":"Andyk",
    "sg:orig_category":"Grafisch Ontwerpers",
    "sg:phone":"+31 228 592 430",
    "sg:postcode":"1619 CV",
    "sg:province":"Noord-Holland",
    "wof:name":"Karin Venekamp",
    "wof:placetype":"venue"
},
  "geometry": {"coordinates":[5.183362,52.739063],"type":"Point"}
}