{
  "type": "Feature",
  "properties": {
    "addr:full":"Romeinenstr 14 Sittard North Rhine-Westphalia 6132 GN",
    "addr:housenumber":"14",
    "addr:postcode":"6132 gn",
    "addr:street":"Romeinenstr",
    "iso:country":"NL",
    "sg:address":"Romeinenstr 14",
    "sg:city":"Sittard",
    "sg:orig_category":"Kaas",
    "sg:phone":"+31 46 451 6181",
    "sg:postcode":"6132 GN",
    "sg:province":"North Rhine-Westphalia",
    "wof:name":"Yvonne",
    "wof:placetype":"venue"
},
  "geometry": {"coordinates":[5.8939571381,50.9959754944],"type":"Point"}
}