{
  "type": "Feature",
  "properties": {
    "addr:full":"Westerkim 22 Prinsenbeek Noord-Brabant 4841 BR",
    "addr:housenumber":"22",
    "addr:postcode":"4841 br",
    "addr:street":"Westerkim",
    "iso:country":"NL",
    "sg:address":"Westerkim 22",
    "sg:city":"Prinsenbeek",
    "sg:orig_category":"Adviesbureaus",
    "sg:phone":"+31 76 549 7220",
    "sg:postcode":"4841 BR",
    "sg:province":"Noord-Brabant",
    "wof:name":"Euroscope, Sticht",
    "wof:placetype":"venue"
},
  "geometry": {"coordinates":[4.710288,51.595341],"type":"Point"}
}