{
  "type": "Feature",
  "properties": {
    "addr:full":"Stationsplein 5 Arnhem Gelderland 6811 KG",
    "addr:housenumber":"5",
    "addr:postcode":"6811 kg",
    "addr:street":"Stationsplein",
    "iso:country":"NL",
    "sg:address":"Stationsplein 5",
    "sg:city":"Arnhem",
    "sg:orig_category":"Verhuur Catering-, Feest- En Evenementbenodigdheden",
    "sg:phone":"+31 26 351 5558",
    "sg:postcode":"6811 KG",
    "sg:province":"Gelderland",
    "wof:name":"Eurolink Holding",
    "wof:placetype":"venue"
},
  "geometry": {"coordinates":[5.901949,51.983242],"type":"Point"}
}