{
  "type": "Feature",
  "properties": {
    "addr:full":"Eisenhowerln 115 Delft Zuid-Holland 2625 GH",
    "addr:housenumber":"115",
    "addr:postcode":"delft;2625 gh",
    "iso:country":"NL",
    "sg:address":"Eisenhowerln 115",
    "sg:city":"Delft",
    "sg:orig_category":"Kassenonderhoud",
    "sg:phone":"+31 15 262 0203",
    "sg:postcode":"2625 GH",
    "sg:province":"Zuid-Holland",
    "wof:name":"Rijk, Jack De",
    "wof:placetype":"venue"
},
  "geometry": {"coordinates":[4.349092,51.990593],"type":"Point"}
}