{
  "type": "Feature",
  "properties": {
    "addr:full":"O L Vrouwestr 47 Ospel Limburg 6035 AN",
    "addr:housenumber":"47",
    "addr:postcode":"6035 an",
    "addr:street":"O",
    "iso:country":"NL",
    "sg:address":"O L Vrouwestr 47",
    "sg:city":"Ospel",
    "sg:orig_category":"Begrafenisverzorging",
    "sg:phone":"+31 495 625 356",
    "sg:postcode":"6035 AN",
    "sg:province":"Limburg",
    "wof:name":"Ospel",
    "wof:placetype":"venue"
},
  "geometry": {"coordinates":[-86.165451,34.620892],"type":"Point"}
}