{
  "type": "Feature",
  "properties": {
    "addr:full":"Postbus 3044 Groningen Zuid-Holland 9701 DA",
    "addr:housenumber":"3044",
    "addr:postcode":"9701 da",
    "addr:street":"Postbus",
    "iso:country":"NL",
    "sg:address":"Postbus 3044",
    "sg:city":"Groningen",
    "sg:classifiers":[
        {
            "category":"Shopping",
            "subcategory":"News",
            "type":"Retail Goods"
        }
    ],
    "sg:phone":"+31 50 311 1661",
    "sg:postcode":"9701 DA",
    "sg:province":"Zuid-Holland",
    "sg:tags":[
        "maandbladen",
        "en",
        "week-"
    ],
    "sg:website":"http://www2.iway.nl/interdatavac/abonnementen.html",
    "wof:name":"Datavac Bv",
    "wof:placetype":"venue"
},
  "geometry": {"coordinates":[6.5650200844,53.2164497375],"type":"Point"}
}