{
  "type": "Feature",
  "properties": {
    "addr:full":"Z Midslandwg 12 Terschelling Midld Provincie Friesland 8891 GH",
    "addr:housenumber":"12;midld",
    "addr:postcode":"8891 gh",
    "addr:street":"Terschelling;Friesland",
    "iso:country":"NL",
    "sg:address":"Z Midslandwg 12",
    "sg:city":"Terschelling Midld",
    "sg:orig_category":"Vakantieverblijven",
    "sg:phone":"+31 562 448 158",
    "sg:postcode":"8891 GH",
    "sg:province":"Provincie Friesland",
    "wof:name":"Schroo-Ligelijn Vof",
    "wof:placetype":"venue"
},
  "geometry": {"coordinates":[5.286301,53.381443],"type":"Point"}
}