{
  "type": "Feature",
  "properties": {
    "addr:full":"Oostvlietweg 51 Leidschendam South Holland 2266 GN",
    "addr:housenumber":"51",
    "addr:postcode":"2266 gn",
    "addr:street":"Oostvlietweg",
    "iso:country":"NL",
    "sg:address":"Oostvlietweg 51",
    "sg:city":"Leidschendam",
    "sg:orig_category":"Wegen And Sportterreinen",
    "sg:phone":"+31 70 327 4375",
    "sg:postcode":"2266 GN",
    "sg:province":"South Holland",
    "wof:name":"Aannemingsbedrijf Oostvliet Bv",
    "wof:placetype":"venue"
},
  "geometry": {"coordinates":[4.4387359619,52.1092796326],"type":"Point"}
}