{
  "type": "Feature",
  "properties": {
    "iso:country":"NL",
    "sg:address":"Kalffstraat 39",
    "sg:city":"Erica",
    "sg:orig_category":"Autokeuringen",
    "sg:phone":"+31 591 301 814",
    "sg:postcode":"7887 AG",
    "sg:province":"Provincie Drenthe",
    "wof:name":"Joh. Vos",
    "wof:placetype":"venue"
},
  "geometry": {"coordinates":[6.921784,52.712582],"type":"Point"}
}