{
  "type": "Feature",
  "properties": {
    "addr:full":"Hendrikus Avelinghstraat 3 Velp Gld Gelderland 6881 VP",
    "addr:housenumber":"3",
    "addr:postcode":"6881 vp",
    "addr:street":"Hendrikus Avelinghstraat;Gld Gelderland",
    "iso:country":"NL",
    "sg:address":"Hendrikus Avelinghstraat 3",
    "sg:city":"Velp Gld",
    "sg:orig_category":"Binnenhuisarchitecten",
    "sg:phone":"+31 26 362 9626",
    "sg:postcode":"6881 VP",
    "sg:province":"Gelderland",
    "wof:name":"Acd Salvage Techniek",
    "wof:placetype":"venue"
},
  "geometry": {"coordinates":[5.97685,51.994968],"type":"Point"}
}