{
  "type": "Feature",
  "properties": {
    "addr:full":"Martenswg 56 Nunspeet Gelderland 8071 KK",
    "addr:housenumber":"56",
    "addr:postcode":"8071 kk",
    "addr:street":"Martenswg;Gelderland",
    "iso:country":"NL",
    "sg:address":"Martenswg 56",
    "sg:city":"Nunspeet",
    "sg:orig_category":"Machinehandel",
    "sg:phone":"+31 341 254 388",
    "sg:postcode":"8071 KK",
    "sg:province":"Gelderland",
    "wof:name":"Dammers Vof",
    "wof:placetype":"venue"
},
  "geometry": {"coordinates":[5.764199,52.37191],"type":"Point"}
}