{
  "type": "Feature",
  "properties": {
    "iso:country":"NL",
    "sg:address":"Kleiwg 14",
    "sg:city":"Gouda",
    "sg:orig_category":"Opticiens",
    "sg:phone":"+31 182 523 992",
    "sg:postcode":"2801 GG",
    "sg:province":"South Holland",
    "wof:name":"Pearle",
    "wof:placetype":"venue"
},
  "geometry": {"coordinates":[4.7098689079,52.0132255554],"type":"Point"}
}