{
  "type": "Feature",
  "properties": {
    "addr:full":"V Schaikwg 60 Emmen Provincie Drenthe 7811 KK",
    "addr:housenumber":"60",
    "addr:postcode":"7811 kk",
    "addr:street":"Provincie Drenthe",
    "iso:country":"NL",
    "sg:address":"V Schaikwg 60",
    "sg:city":"Emmen",
    "sg:orig_category":"Verzekeringen - Verzekeringskantoren",
    "sg:phone":"+31 591 650 690",
    "sg:postcode":"7811 KK",
    "sg:province":"Provincie Drenthe",
    "wof:name":"Census",
    "wof:placetype":"venue"
},
  "geometry": {"coordinates":[6.8964,52.782017],"type":"Point"}
}