{
  "type": "Feature",
  "properties": {
    "iso:country":"NL",
    "sg:address":"Gouwe 4",
    "sg:city":"Hoogwoud",
    "sg:orig_category":"Paramedische Behandelingen",
    "sg:phone":"+31 229 581 441",
    "sg:postcode":"1718 LJ",
    "sg:province":"North Holland",
    "wof:name":"K. V.D. Wijk",
    "wof:placetype":"venue"
},
  "geometry": {"coordinates":[4.964348,52.719948],"type":"Point"}
}