{
  "type": "Feature",
  "properties": {
    "addr:full":"Plantage Middenln 40 Amsterdam Noord-Holland 1018 DG",
    "addr:housenumber":"40",
    "addr:postcode":"1018 dg",
    "addr:street":"Plantage Middenln",
    "iso:country":"NL",
    "sg:address":"Plantage Middenln 40",
    "sg:city":"Amsterdam",
    "sg:classifiers":[
        {
            "category":"Travel",
            "subcategory":"Hotels & Motels",
            "type":"Entertainment"
        }
    ],
    "sg:phone":"+31 20 622 6819",
    "sg:postcode":"1018 DG",
    "sg:province":"Noord-Holland",
    "wof:name":"Kitty",
    "wof:placetype":"venue"
},
  "geometry": {"coordinates":[4.9124,52.365971],"type":"Point"}
}