{
  "type": "Feature",
  "properties": {
    "addr:full":"Puntmosstr 42 Purmerend Noord-Holland 1441 LJ",
    "addr:housenumber":"42",
    "addr:postcode":"1441 lj",
    "addr:street":"Puntmosstr",
    "iso:country":"NL",
    "sg:address":"Puntmosstr 42",
    "sg:city":"Purmerend",
    "sg:orig_category":"Kappers",
    "sg:phone":"+31 299 660 376",
    "sg:postcode":"1441 LJ",
    "sg:province":"Noord-Holland",
    "wof:name":"Studio Smc",
    "wof:placetype":"venue"
},
  "geometry": {"coordinates":[4.952542,52.500717],"type":"Point"}
}