{
  "type": "Feature",
  "properties": {
    "iso:country":"NL",
    "sg:address":"Floryn 2",
    "sg:city":"Deurne",
    "sg:orig_category":"Sanitaire Artikelen",
    "sg:phone":"+31 493 321 166",
    "sg:postcode":"5751 PC",
    "sg:province":"Noord-Brabant",
    "sg:website":"http://www.sanidrome.nl",
    "wof:name":"Thijssen",
    "wof:placetype":"venue"
},
  "geometry": {"coordinates":[5.790711,51.461773],"type":"Point"}
}