{
  "type": "Feature",
  "properties": {
    "addr:full":"Laurierhof 36 Amsterdam Noord-Holland 1016 MB",
    "addr:housenumber":"36",
    "addr:postcode":"1016 mb",
    "addr:street":"Laurierhof",
    "iso:country":"NL",
    "sg:address":"Laurierhof 36",
    "sg:city":"Amsterdam",
    "sg:orig_category":"Vertaalbureaus",
    "sg:phone":"+31 20 620 9032",
    "sg:postcode":"1016 MB",
    "sg:province":"Noord-Holland",
    "wof:name":"Wright, Annie",
    "wof:placetype":"venue"
},
  "geometry": {"coordinates":[4.879931,52.372086],"type":"Point"}
}