{
  "type": "Feature",
  "properties": {
    "addr:full":"Verspronckwg 68 Haarlem Noord-Holland 2023 BM",
    "addr:housenumber":"68",
    "addr:postcode":"2023 bm",
    "addr:street":"Verspronckwg",
    "iso:country":"NL",
    "sg:address":"Verspronckwg 68",
    "sg:city":"Haarlem",
    "sg:orig_category":"Kinderhuizen",
    "sg:phone":"+31 23 526 1431",
    "sg:postcode":"2023 BM",
    "sg:province":"Noord-Holland",
    "wof:name":"Spalier, Het",
    "wof:placetype":"venue"
},
  "geometry": {"coordinates":[4.627296,52.390354],"type":"Point"}
}