{
  "type": "Feature",
  "properties": {
    "iso:country":"NL",
    "sg:address":"2E Sluiswg 16",
    "sg:city":"Tilburg",
    "sg:orig_category":"Bloemen En Planten - Groothandel",
    "sg:phone":"+31 13 515 9284",
    "sg:postcode":"5047 TH",
    "sg:province":"Noord-Brabant",
    "wof:name":"Arendse Bv, A",
    "wof:placetype":"venue"
},
  "geometry": {"coordinates":[4.991275,51.602142],"type":"Point"}
}