{
  "type": "Feature",
  "properties": {
    "iso:country":"NL",
    "sg:address":"Postbus 239",
    "sg:city":"Heemstede",
    "sg:orig_category":"Juwelen - Groothandel",
    "sg:phone":"+31 23 565 5155",
    "sg:postcode":"2100 AE",
    "sg:province":"Noord-Holland",
    "wof:name":"Gruijl, Y De",
    "wof:placetype":"venue"
},
  "geometry": {"coordinates":[4.621248,52.345287],"type":"Point"}
}