{
  "type": "Feature",
  "properties": {
    "iso:country":"NL",
    "sg:address":"N Ottostr 20",
    "sg:city":"Zwolle",
    "sg:orig_category":"Automaterialen En Gereedschappen",
    "sg:phone":"+31 38 453 1039",
    "sg:postcode":"8013 NG",
    "sg:province":"Overijssel",
    "sg:website":"http://www.schaftenaar.nl",
    "wof:name":"Schaftenaar Bv",
    "wof:placetype":"venue"
},
  "geometry": {"coordinates":[6.12343,52.49432],"type":"Point"}
}