{
  "type": "Feature",
  "properties": {
    "addr:full":"Nicolaas Beetsstraat 2 Vlaardingen Zuid-Holland 3131 GP",
    "addr:housenumber":"2",
    "addr:postcode":"3131 gp",
    "addr:street":"Nicolaas Beetsstraat",
    "iso:country":"NL",
    "sg:address":"Nicolaas Beetsstraat 2",
    "sg:city":"Vlaardingen",
    "sg:orig_category":"Platenmaatschappijen",
    "sg:phone":"+31 10 460 4316",
    "sg:postcode":"3131 GP",
    "sg:province":"Zuid-Holland",
    "wof:name":"Ultimate Dance Productions",
    "wof:placetype":"venue"
},
  "geometry": {"coordinates":[4.339491,51.912769],"type":"Point"}
}