{
  "type": "Feature",
  "properties": {
    "addr:full":"Wesselmanln 25 Helmond Noord-Brabant 5707 HA",
    "addr:housenumber":"25",
    "addr:postcode":"5707 ha",
    "addr:street":"Wesselmanln",
    "iso:country":"NL",
    "sg:address":"Wesselmanln 25",
    "sg:city":"Helmond",
    "sg:orig_category":"Kappers",
    "sg:phone":"+31 492 595 726",
    "sg:postcode":"5707 HA",
    "sg:province":"Noord-Brabant",
    "wof:name":"Desiree",
    "wof:placetype":"venue"
},
  "geometry": {"coordinates":[5.6440429688,51.4822311401],"type":"Point"}
}