{
  "type": "Feature",
  "properties": {
    "addr:full":"Oude Kerkstr 83 Standdaarbuiten North Brabant 4758 BD",
    "addr:housenumber":"83",
    "addr:postcode":"4758 bd",
    "addr:street":"Oude Kerkstr",
    "iso:country":"NL",
    "sg:address":"Oude Kerkstr 83",
    "sg:city":"Standdaarbuiten",
    "sg:classifiers":[
        {
            "category":"Retail",
            "subcategory":"Auto Repair",
            "type":"Services"
        }
    ],
    "sg:phone":"+31 165 312 129",
    "sg:postcode":"4758 BD",
    "sg:province":"North Brabant",
    "sg:tags":[
        "garage"
    ],
    "wof:name":"Vlimmeren Autobedrijf, Rom Van",
    "wof:placetype":"venue"
},
  "geometry": {"coordinates":[4.506409,51.614429],"type":"Point"}
}