{
  "type": "Feature",
  "properties": {
    "addr:full":"Paletpln 15 Tilburg Noord-Brabant 5044 JB",
    "addr:housenumber":"15",
    "addr:postcode":"5044 jb",
    "addr:street":"Paletpln",
    "iso:country":"NL",
    "sg:address":"Paletpln 15",
    "sg:city":"Tilburg",
    "sg:orig_category":"Schoenen - Reparaties",
    "sg:phone":"+31 13 467 3284",
    "sg:postcode":"5044 JB",
    "sg:province":"Noord-Brabant",
    "wof:name":"Klink",
    "wof:placetype":"venue"
},
  "geometry": {"coordinates":[5.039266,51.576115],"type":"Point"}
}