{
  "type": "Feature",
  "properties": {
    "addr:full":"Kerkstraat 10 Nieuwe Pekela Groningen 9663 CB",
    "addr:housenumber":"10",
    "addr:postcode":"9663 cb",
    "addr:street":"Kerkstraat",
    "iso:country":"NL",
    "sg:address":"Kerkstraat 10",
    "sg:city":"Nieuwe Pekela",
    "sg:classifiers":[
        {
            "category":"Fast Food",
            "type":"Food & Drink"
        }
    ],
    "sg:phone":"+31 597 646 989",
    "sg:postcode":"9663 CB",
    "sg:province":"Groningen",
    "sg:tags":[
        "afhaal",
        "restaurant"
    ],
    "wof:name":"Het Smulpaleis",
    "wof:placetype":"venue"
},
  "geometry": {"coordinates":[6.967866,53.078884],"type":"Point"}
}