{
  "type": "Feature",
  "properties": {
    "addr:full":"Vrijheidslaan 14 Delft Zuid-Holland 2625 RD",
    "addr:housenumber":"14",
    "addr:postcode":"2625 rd",
    "addr:street":"Vrijheidslaan",
    "iso:country":"NL",
    "sg:address":"Vrijheidslaan 14",
    "sg:city":"Delft",
    "sg:orig_category":"Bloemen And Planten",
    "sg:phone":"+31 15 257 2192",
    "sg:postcode":"2625 RD",
    "sg:province":"Zuid-Holland",
    "wof:name":"Bloemenboetieks F.A.M. Karlas",
    "wof:placetype":"venue"
},
  "geometry": {"coordinates":[4.346082,51.987888],"type":"Point"}
}