{
  "type": "Feature",
  "properties": {
    "addr:full":"Holstraat 43 Margraten Limburg 6269 AW",
    "addr:housenumber":"43",
    "addr:postcode":"6269 aw",
    "addr:street":"Holstraat",
    "iso:country":"NL",
    "sg:address":"Holstraat 43",
    "sg:city":"Margraten",
    "sg:orig_category":"Hout Gh",
    "sg:phone":"+31 43 458 1982",
    "sg:postcode":"6269 AW",
    "sg:province":"Limburg",
    "wof:name":"Rondhouthandel En Impregneerbedrijf J. Kuijpers",
    "wof:placetype":"venue"
},
  "geometry": {"coordinates":[5.821216,50.819908],"type":"Point"}
}