{
  "type": "Feature",
  "properties": {
    "addr:full":"Boswg 8A T Zand Nh Noord-Holland 1756 CG",
    "addr:housenumber":"8a",
    "addr:postcode":"1756 cg",
    "addr:street":"Boswg",
    "iso:country":"NL",
    "sg:address":"Boswg 8A",
    "sg:city":"T Zand Nh",
    "sg:orig_category":"Metselwerken",
    "sg:phone":"+31 224 591 995",
    "sg:postcode":"1756 CG",
    "sg:province":"Noord-Holland",
    "wof:name":"Smit En De Moel",
    "wof:placetype":"venue"
},
  "geometry": {"coordinates":[4.74427,52.830402],"type":"Point"}
}