{
  "type": "Feature",
  "properties": {
    "addr:full":"Ginnekenstr 16 Arnhem Gelderland 6843 RV",
    "addr:housenumber":"16",
    "addr:postcode":"6843 rv",
    "addr:street":"Ginnekenstr",
    "iso:country":"NL",
    "sg:address":"Ginnekenstr 16",
    "sg:city":"Arnhem",
    "sg:orig_category":"Artsen - Huisartsen",
    "sg:phone":"+31 26 381 0500",
    "sg:postcode":"6843 RV",
    "sg:province":"Gelderland",
    "wof:name":"Haenen, L",
    "wof:placetype":"venue"
},
  "geometry": {"coordinates":[5.863773,51.950111],"type":"Point"}
}