{
  "type": "Feature",
  "properties": {
    "addr:full":"Welbergsedk 20A Steenbergen Nb Noord-Brabant 4651 TE",
    "addr:housenumber":"20a",
    "addr:postcode":"4651 te",
    "addr:street":"Welbergsedk",
    "iso:country":"NL",
    "sg:address":"Welbergsedk 20A",
    "sg:city":"Steenbergen Nb",
    "sg:classifiers":[
        {
            "category":"Retail",
            "subcategory":"Auto Repair",
            "type":"Services"
        }
    ],
    "sg:phone":"+31 167 563 156",
    "sg:postcode":"4651 TE",
    "sg:province":"Noord-Brabant",
    "sg:tags":[
        "garage"
    ],
    "wof:name":"Rooy, H P Van",
    "wof:placetype":"venue"
},
  "geometry": {"coordinates":[4.33771,51.578335],"type":"Point"}
}