{
  "type": "Feature",
  "properties": {
    "addr:full":"Hendrik Ter Kuilestraat 146 Enschede Overijssel 7547 BE",
    "addr:housenumber":"146",
    "addr:postcode":"7547",
    "addr:street":"Hendrik Ter Kuilestraat",
    "iso:country":"NL",
    "sg:address":"Hendrik Ter Kuilestraat 146",
    "sg:city":"Enschede",
    "sg:orig_category":"Metaalwerken",
    "sg:phone":"+31 53 432 0368",
    "sg:postcode":"7547 BE",
    "sg:province":"Overijssel",
    "wof:name":"Wagener Bv",
    "wof:placetype":"venue"
},
  "geometry": {"coordinates":[6.853422,52.219898],"type":"Point"}
}