{
  "type": "Feature",
  "properties": {
    "iso:country":"NL",
    "sg:address":"Hendrik Ter Kuilestraat 146",
    "sg:city":"Enschede",
    "sg:orig_category":"Metaalwerken",
    "sg:phone":"+31 53 432 0368",
    "sg:postcode":"7547 BE",
    "sg:province":"Overijssel",
    "wof:name":"Wagener Bv",
    "wof:placetype":"venue"
},
  "geometry": {"coordinates":[6.853422,52.219898],"type":"Point"}
}