{
  "type": "Feature",
  "properties": {
    "addr:full":"Liniestr 19 Breda Noord-Brabant 4816 BG",
    "addr:housenumber":"19",
    "addr:postcode":"4816",
    "addr:street":"Liniestr",
    "iso:country":"NL",
    "sg:address":"Liniestr 19",
    "sg:city":"Breda",
    "sg:orig_category":"Zoetwaren - Fabrieken En Groothandel",
    "sg:phone":"+31 76 572 8433",
    "sg:postcode":"4816 BG",
    "sg:province":"Noord-Brabant",
    "wof:name":"Astra Faam Bv",
    "wof:placetype":"venue"
},
  "geometry": {"coordinates":[4.782885,51.596977],"type":"Point"}
}