{
  "type": "Feature",
  "properties": {
    "addr:full":"Gaelstr 1F Haarlem North Holland 2013 CE",
    "addr:housenumber":"1f",
    "addr:postcode":"2013 ce",
    "iso:country":"NL",
    "sg:address":"Gaelstr 1F",
    "sg:city":"Haarlem",
    "sg:orig_category":"Liften - Onderhoud En Reparatie",
    "sg:phone":"+31 23 551 0021",
    "sg:postcode":"2013 CE",
    "sg:province":"North Holland",
    "wof:name":"Ascent Bv",
    "wof:placetype":"venue"
},
  "geometry": {"coordinates":[4.624584,52.385941],"type":"Point"}
}