{
  "type": "Feature",
  "properties": {
    "addr:full":"St Jorispln 3 Gorinchem South Holland 4205 JA",
    "addr:housenumber":"3",
    "addr:postcode":"4205 ja",
    "iso:country":"NL",
    "sg:address":"St Jorispln 3",
    "sg:city":"Gorinchem",
    "sg:orig_category":"Psychotherapeuten",
    "sg:phone":"+31 183 626 614",
    "sg:postcode":"4205 JA",
    "sg:province":"South Holland",
    "wof:name":"Mayenburg, Drs J E",
    "wof:placetype":"venue"
},
  "geometry": {"coordinates":[4.963432,51.83955],"type":"Point"}
}