{
  "type": "Feature",
  "properties": {
    "addr:full":"Eikenlaan 5 Sint Michielsgestel North Brabant 5271 RR",
    "addr:housenumber":"5;michielsgestel",
    "addr:postcode":"5271 rr",
    "addr:street":"Eikenlaan",
    "iso:country":"NL",
    "sg:address":"Eikenlaan 5",
    "sg:city":"Sint Michielsgestel",
    "sg:orig_category":"Sportcentra",
    "sg:phone":"+31 73 551 3103",
    "sg:postcode":"5271 RR",
    "sg:province":"North Brabant",
    "wof:name":"Sporthal",
    "wof:placetype":"venue"
},
  "geometry": {"coordinates":[5.336706,51.633621],"type":"Point"}
}