{
  "type": "Feature",
  "properties": {
    "addr:full":"Spoorstraat 49 Alkmaar North Holland 1815 BH",
    "addr:housenumber":"49",
    "addr:postcode":"1815 bh",
    "addr:street":"Spoorstraat",
    "iso:country":"NL",
    "sg:address":"Spoorstraat 49",
    "sg:city":"Alkmaar",
    "sg:orig_category":"Fruit And Groenten Gh",
    "sg:phone":"+31 72 515 8114",
    "sg:postcode":"1815 BH",
    "sg:province":"North Holland",
    "wof:name":"Conny'S Enterprise",
    "wof:placetype":"venue"
},
  "geometry": {"coordinates":[4.742646,52.636421],"type":"Point"}
}