{
  "type": "Feature",
  "properties": {
    "addr:full":"Koningshoeven 83 Tilburg North Brabant 5018 AA",
    "addr:housenumber":"83",
    "addr:postcode":"5018 aa",
    "addr:street":"Koningshoeven",
    "iso:country":"NL",
    "sg:address":"Koningshoeven 83",
    "sg:city":"Tilburg",
    "sg:orig_category":"Beeldende Kunstenaars",
    "sg:phone":"+31 13 543 1859",
    "sg:postcode":"5018 AA",
    "sg:province":"North Brabant",
    "wof:name":"Mols, Th En H",
    "wof:placetype":"venue"
},
  "geometry": {"coordinates":[5.115606,51.546989],"type":"Point"}
}