{
  "type": "Feature",
  "properties": {
    "addr:full":"H Loonstrastr 15 Eestrum Provincie Friesland 9258 CZ",
    "addr:housenumber":"15;9258",
    "addr:street":"Eestrum Provincie Friesland",
    "iso:country":"NL",
    "sg:address":"H Loonstrastr 15",
    "sg:city":"Eestrum",
    "sg:orig_category":"Scheepssleep- En Duwvaart",
    "sg:phone":"+31 512 471 624",
    "sg:postcode":"9258 CZ",
    "sg:province":"Provincie Friesland",
    "wof:name":"Bouius, G S",
    "wof:placetype":"venue"
},
  "geometry": {"coordinates":[6.065328,53.212421],"type":"Point"}
}