{
  "type": "Feature",
  "properties": {
    "addr:full":"Havenstr 45 Woerden Utrecht 3441 BH",
    "addr:housenumber":"45",
    "addr:postcode":"3441 bh",
    "addr:street":"Havenstr",
    "iso:country":"NL",
    "sg:address":"Havenstr 45",
    "sg:city":"Woerden",
    "sg:orig_category":"Woninginrichting",
    "sg:phone":"+31 348 499 913",
    "sg:postcode":"3441 BH",
    "sg:province":"Utrecht",
    "wof:name":"Way Of Life",
    "wof:placetype":"venue"
},
  "geometry": {"coordinates":[4.8848757744,52.0851249695],"type":"Point"}
}