{
  "type": "Feature",
  "properties": {
    "addr:full":"Buorren 38 Tietjerk Friesland 9255 KL",
    "addr:housenumber":"38",
    "addr:postcode":"9255 kl",
    "addr:street":"Buorren",
    "iso:country":"NL",
    "sg:address":"Buorren 38",
    "sg:city":"Tietjerk",
    "sg:orig_category":"Huisbrand- En Industrieolie",
    "sg:phone":"+31 511 431 400",
    "sg:postcode":"9255 KL",
    "sg:province":"Friesland",
    "wof:name":"Venema, A M",
    "wof:placetype":"venue"
},
  "geometry": {"coordinates":[5.896325,53.197521],"type":"Point"}
}