{
  "type": "Feature",
  "properties": {
    "iso:country":"NL",
    "sg:address":"Wesselsewg 110/A",
    "sg:city":"Kootwykerbroek",
    "sg:orig_category":"Meubelstoffering",
    "sg:phone":"+31 342 421 519",
    "sg:postcode":"3774 RL",
    "sg:province":"Gelderland",
    "wof:name":"Beek, G J Van",
    "wof:placetype":"venue"
},
  "geometry": {"coordinates":[5.639913,52.14941],"type":"Point"}
}