{
  "type": "Feature",
  "properties": {
    "addr:full":"Postbus 43 Roelofarendsveen South Holland 2370 AA",
    "addr:housenumber":"43",
    "addr:postcode":"2370 aa",
    "addr:street":"Postbus",
    "iso:country":"NL",
    "sg:address":"Postbus 43",
    "sg:city":"Roelofarendsveen",
    "sg:orig_category":"Verenigingen En Stichtingen",
    "sg:phone":"+31 71 331 2957",
    "sg:postcode":"2370 AA",
    "sg:province":"South Holland",
    "wof:name":"Dosr Voetbalver",
    "wof:placetype":"venue"
},
  "geometry": {"coordinates":[4.6314,52.203491],"type":"Point"}
}