{
  "type": "Feature",
  "properties": {
    "addr:full":"De Lepelaar 24 Vriezenveen Overijssel 7671 WK",
    "addr:housenumber":"24",
    "addr:postcode":"7671 wk",
    "addr:street":"De Lepelaar",
    "iso:country":"NL",
    "sg:address":"De Lepelaar 24",
    "sg:city":"Vriezenveen",
    "sg:orig_category":"Adviesbureaus Bouwkunde",
    "sg:phone":"+31 546 569 710",
    "sg:postcode":"7671 WK",
    "sg:province":"Overijssel",
    "wof:name":"Wasser Bouwmanagement",
    "wof:placetype":"venue"
},
  "geometry": {"coordinates":[6.610886,52.398899],"type":"Point"}
}