{
  "type": "Feature",
  "properties": {
    "addr:full":"Laan Van Westroijen 4 Tiel Gelderland 4003 AZ",
    "addr:housenumber":"4",
    "addr:postcode":"4003",
    "addr:street":"Laan Van Westroijen;Gelderland",
    "iso:country":"NL",
    "sg:address":"Laan Van Westroijen 4",
    "sg:city":"Tiel",
    "sg:orig_category":"Bedrijfs- And Werkgeversorganisaties",
    "sg:phone":"+31 344 637 700",
    "sg:postcode":"4003 AZ",
    "sg:province":"Gelderland",
    "wof:name":"Kamer Van Koophandel Voor Rivierenland",
    "wof:placetype":"venue"
},
  "geometry": {"coordinates":[5.438436,51.899986],"type":"Point"}
}