{
  "type": "Feature",
  "properties": {
    "addr:full":"Busselseweg 7 Asten Noord-Brabant 5721 PB",
    "addr:housenumber":"7",
    "addr:postcode":"5721 pb",
    "addr:street":"Busselseweg",
    "iso:country":"NL",
    "sg:address":"Busselseweg 7",
    "sg:city":"Asten",
    "sg:orig_category":"Kampeerterreinen",
    "sg:phone":"+31 493 694 342",
    "sg:postcode":"5721 PB",
    "sg:province":"Noord-Brabant",
    "wof:name":"Minicamping Van Den Boer",
    "wof:placetype":"venue"
},
  "geometry": {"coordinates":[5.7175879478,51.4182548523],"type":"Point"}
}