{
  "type": "Feature",
  "properties": {
    "iso:country":"NL",
    "sg:address":"H Goeman Borgesiusstraat 52",
    "sg:city":"Schildwolde",
    "sg:classifiers":[
        {
            "category":"Education",
            "subcategory":"Preschool",
            "type":"Public Place"
        }
    ],
    "sg:phone":"+31 598 421 434",
    "sg:postcode":"9626 AX",
    "sg:province":"Groningen",
    "sg:tags":[
        "kleuteronderwijs",
        "basis-"
    ],
    "wof:name":"Obs De Meent",
    "wof:placetype":"venue"
},
  "geometry": {"coordinates":[6.812066,53.234371],"type":"Point"}
}