{
  "type": "Feature",
  "properties": {
    "iso:country":"NL",
    "sg:address":"Boterzwin 3615",
    "sg:city":"Den Helder",
    "sg:orig_category":"Vertaal- And Tolkenbureaus",
    "sg:phone":"+31 223 642 970",
    "sg:postcode":"1788 WL",
    "sg:province":"North Holland",
    "wof:name":"Backer Vertaalbureau Th",
    "wof:placetype":"venue"
},
  "geometry": {"coordinates":[4.739326,52.881783],"type":"Point"}
}