{
  "type": "Feature",
  "properties": {
    "addr:full":"Theresiastr 93 S Gravenhage Zuid-Holland 2593 AC",
    "addr:housenumber":"93;gravenhage",
    "addr:postcode":"2593 ac",
    "addr:street":"Theresiastr;S",
    "iso:country":"NL",
    "sg:address":"Theresiastr 93",
    "sg:city":"S Gravenhage",
    "sg:orig_category":"Boekhandels",
    "sg:phone":"+31 70 383 3729",
    "sg:postcode":"2593 AC",
    "sg:province":"Zuid-Holland",
    "wof:name":"Boekelier, De",
    "wof:placetype":"venue"
},
  "geometry": {"coordinates":[4.34266,52.086121],"type":"Point"}
}