{
  "type": "Feature",
  "properties": {
    "addr:full":"Kerkstr 14 Bussum North Holland 1404 HH",
    "addr:housenumber":"14",
    "addr:postcode":"1404 hh",
    "addr:street":"Kerkstr",
    "iso:country":"NL",
    "sg:address":"Kerkstr 14",
    "sg:city":"Bussum",
    "sg:orig_category":"Kappers",
    "sg:phone":"+31 35 692 1684",
    "sg:postcode":"1404 HH",
    "sg:province":"North Holland",
    "wof:name":"Beauty Boulevard",
    "wof:placetype":"venue"
},
  "geometry": {"coordinates":[5.1642141342,52.2733879089],"type":"Point"}
}