{
  "type": "Feature",
  "properties": {
    "addr:full":"Grote Houtstraat 132 Haarlem North Holland 2011 SV",
    "addr:housenumber":"132",
    "addr:postcode":"2011 sv",
    "addr:street":"Grote Houtstraat",
    "iso:country":"NL",
    "sg:address":"Grote Houtstraat 132",
    "sg:city":"Haarlem",
    "sg:orig_category":"Herenmodezaken",
    "sg:phone":"+31 23 532 9451",
    "sg:postcode":"2011 SV",
    "sg:province":"North Holland",
    "wof:name":"Mcgregor Shop",
    "wof:placetype":"venue"
},
  "geometry": {"coordinates":[4.631717,52.377682],"type":"Point"}
}