{
  "type": "Feature",
  "properties": {
    "addr:full":"Nw Steen 2E F Hoorn Nh North Holland 1625 HV",
    "addr:housenumber":"2e f",
    "addr:postcode":"1625 hv",
    "addr:street":"Nw Steen;Nh North",
    "iso:country":"NL",
    "sg:address":"Nw Steen 2E F",
    "sg:city":"Hoorn Nh",
    "sg:orig_category":"Verzekeringen - Verzekeringskantoren",
    "sg:phone":"+31 229 287 888",
    "sg:postcode":"1625 HV",
    "sg:province":"North Holland",
    "sg:website":"http://www.vkg.com",
    "wof:name":"Kampen Groep, Van",
    "wof:placetype":"venue"
},
  "geometry": {"coordinates":[5.05321,52.655369],"type":"Point"}
}