{
  "type": "Feature",
  "properties": {
    "addr:full":"Eiber 2 Grootegast Groningen 9861 HL",
    "addr:housenumber":"2",
    "addr:postcode":"9861 hl",
    "addr:street":"Eiber",
    "iso:country":"NL",
    "sg:address":"Eiber 2",
    "sg:city":"Grootegast",
    "sg:orig_category":"Beeldende Kunstenaars",
    "sg:phone":"+31 594 612 290",
    "sg:postcode":"9861 HL",
    "sg:province":"Groningen",
    "wof:name":"Joop Klompien",
    "wof:placetype":"venue"
},
  "geometry": {"coordinates":[6.272846,53.216],"type":"Point"}
}