{
  "type": "Feature",
  "properties": {
    "iso:country":"NL",
    "sg:address":"Nolenslaan 22",
    "sg:city":"Utrecht",
    "sg:orig_category":"Onderhoud And Reparatie Kantoorapparatuur",
    "sg:phone":"+31 30 273 4848",
    "sg:postcode":"3515 VG",
    "sg:province":"Utrecht",
    "wof:name":"Utrechtse Pc Klusjesman",
    "wof:placetype":"venue"
},
  "geometry": {"coordinates":[5.116166,52.102161],"type":"Point"}
}