{
  "type": "Feature",
  "properties": {
    "addr:full":"Fuutlaan 14 Eindhoven Noord-Brabant 5613 AB",
    "addr:housenumber":"14",
    "addr:postcode":"5613 ab",
    "addr:street":"Fuutlaan",
    "iso:country":"NL",
    "sg:address":"Fuutlaan 14",
    "sg:city":"Eindhoven",
    "sg:orig_category":"Bloemen And Planten Gh",
    "sg:phone":"+31 40 246 6145",
    "sg:postcode":"5613 AB",
    "sg:province":"Noord-Brabant",
    "wof:name":"Falcon Gardens Agenturen",
    "wof:placetype":"venue"
},
  "geometry": {"coordinates":[5.492836,51.443436],"type":"Point"}
}