{
  "type": "Feature",
  "properties": {
    "iso:country":"NL",
    "sg:address":"Statenpln 43",
    "sg:city":"Dordrecht",
    "sg:orig_category":"Herenkleding",
    "sg:phone":"+31 78 639 9197",
    "sg:postcode":"3311 NG",
    "sg:province":"South Holland",
    "sg:website":"http://www.wefashion.com",
    "wof:name":"We",
    "wof:placetype":"venue"
},
  "geometry": {"coordinates":[4.668882,51.813801],"type":"Point"}
}