{
  "type": "Feature",
  "properties": {
    "addr:full":"Royermarke 1 Zwolle NL.08 8016 CZ",
    "addr:housenumber":"1",
    "addr:postcode":"8016",
    "addr:street":"Royermarke",
    "iso:country":"NL",
    "sg:address":"Royermarke 1",
    "sg:city":"Zwolle",
    "sg:orig_category":"Bedrijfsopleidingen",
    "sg:phone":"+31 38 466 1165",
    "sg:postcode":"8016 CZ",
    "sg:province":"NL.08",
    "wof:name":"It Supervisiebureau",
    "wof:placetype":"venue"
},
  "geometry": {"coordinates":[6.088738,52.512566],"type":"Point"}
}