{
  "type": "Feature",
  "properties": {
    "addr:full":"Rembrandtstr 5G Oud Beyerland Zuid-Holland 3262 HN",
    "addr:housenumber":"5g",
    "addr:postcode":"3262 hn",
    "addr:street":"Rembrandtstr;Oud Beyerland",
    "iso:country":"NL",
    "sg:address":"Rembrandtstr 5G",
    "sg:city":"Oud Beyerland",
    "sg:orig_category":"Autopoetsbedrijven",
    "sg:phone":"+31 186 617 270",
    "sg:postcode":"3262 HN",
    "sg:province":"Zuid-Holland",
    "wof:name":"Quick",
    "wof:placetype":"venue"
},
  "geometry": {"coordinates":[4.412757,51.815445],"type":"Point"}
}