{
  "type": "Feature",
  "properties": {
    "addr:full":"Oudedk 62 Rotterdam Zuid-Holland 3062 AE",
    "addr:housenumber":"62",
    "addr:postcode":"3062 ae",
    "addr:street":"Oudedk",
    "iso:country":"NL",
    "sg:address":"Oudedk 62",
    "sg:city":"Rotterdam",
    "sg:orig_category":"Bloemen En Planten",
    "sg:phone":"+31 10 411 8237",
    "sg:postcode":"3062 AE",
    "sg:province":"Zuid-Holland",
    "wof:name":"Euroflower",
    "wof:placetype":"venue"
},
  "geometry": {"coordinates":[4.513388,51.925362],"type":"Point"}
}