{
  "type": "Feature",
  "properties": {
    "addr:full":"Vrouw Juttenland 8 Delft Zuid-Holland 2611 LC",
    "addr:housenumber":"8",
    "addr:postcode":"2611 lc",
    "addr:street":"Delft",
    "iso:country":"NL",
    "sg:address":"Vrouw Juttenland 8",
    "sg:city":"Delft",
    "sg:orig_category":"Motoren",
    "sg:phone":"+31 15 212 1417",
    "sg:postcode":"2611 LC",
    "sg:province":"Zuid-Holland",
    "wof:name":"De Fietsenreus",
    "wof:placetype":"venue"
},
  "geometry": {"coordinates":[4.360383,52.013092],"type":"Point"}
}