{
  "type": "Feature",
  "properties": {
    "addr:full":"Curiewg 9A Alphen Aan Den Ryn South Holland 2408 BZ",
    "addr:housenumber":"9a",
    "addr:postcode":"2408 bz",
    "addr:street":"Curiewg;Aan Den Ryn",
    "iso:country":"NL",
    "sg:address":"Curiewg 9A",
    "sg:city":"Alphen Aan Den Ryn",
    "sg:orig_category":"Autoschade- Herstelbedrijven",
    "sg:phone":"+31 172 460 950",
    "sg:postcode":"2408 BZ",
    "sg:province":"South Holland",
    "wof:name":"Autoschadehuis, Het",
    "wof:placetype":"venue"
},
  "geometry": {"coordinates":[4.630656,52.125858],"type":"Point"}
}