{
  "type": "Feature",
  "properties": {
    "addr:full":"Nederwaard 10 Capelle Ad Yssel Zuid-Holland 2904 SH",
    "addr:housenumber":"10;2904",
    "addr:postcode":"sh",
    "addr:street":"Nederwaard",
    "iso:country":"NL",
    "sg:address":"Nederwaard 10",
    "sg:city":"Capelle Ad Yssel",
    "sg:orig_category":"Kantoor- En Secretariaatsservice",
    "sg:phone":"+31 10 458 4015",
    "sg:postcode":"2904 SH",
    "sg:province":"Zuid-Holland",
    "sg:website":"http://www.dcondersteuning.nl",
    "wof:name":"Dc Ondersteuning",
    "wof:placetype":"venue"
},
  "geometry": {"coordinates":[4.6156201363,51.9345741272],"type":"Point"}
}