{
  "type": "Feature",
  "properties": {
    "addr:full":"Niftrikhof 1 Amsterdam Zuidoost North Holland 1106 SB",
    "addr:housenumber":"1",
    "addr:postcode":"1106 sb",
    "addr:street":"Niftrikhof",
    "iso:country":"NL",
    "sg:address":"Niftrikhof 1",
    "sg:city":"Amsterdam Zuidoost",
    "sg:orig_category":"Bejaarden - Verzorgingstehuizen",
    "sg:phone":"+31 20 696 5451",
    "sg:postcode":"1106 SB",
    "sg:province":"North Holland",
    "wof:name":"Drecht, De",
    "wof:placetype":"venue"
},
  "geometry": {"coordinates":[4.961711,52.299278],"type":"Point"}
}