{
  "type": "Feature",
  "properties": {
    "addr:full":"Kwadk 143 Kwadyk Noord-Holland 1471 CJ",
    "addr:housenumber":"143;1471",
    "addr:postcode":"cj",
    "addr:street":"Kwadyk Noord-Holland",
    "iso:country":"NL",
    "sg:address":"Kwadk 143",
    "sg:city":"Kwadyk",
    "sg:orig_category":"Hoefsmederijen",
    "sg:phone":"+31 299 623 624",
    "sg:postcode":"1471 CJ",
    "sg:province":"Noord-Holland",
    "wof:name":"Hooijer Vof, A",
    "wof:placetype":"venue"
},
  "geometry": {"coordinates":[4.991258,52.5243],"type":"Point"}
}