{
  "type": "Feature",
  "properties": {
    "addr:full":"Westeinde 231 Vriezenveen NL.08 7671 ER",
    "addr:housenumber":"231;nl.08",
    "addr:postcode":"7671 er",
    "addr:street":"Westeinde",
    "iso:country":"NL",
    "sg:address":"Westeinde 231",
    "sg:city":"Vriezenveen",
    "sg:classifiers":[
        {
            "category":"Retail",
            "subcategory":"Photofinishing",
            "type":"Services"
        }
    ],
    "sg:phone":"+31 546 561 204",
    "sg:postcode":"7671 ER",
    "sg:province":"NL.08",
    "sg:tags":[
        "foto",
        "film"
    ],
    "wof:name":"Joop Lamberts Vriezenveen Bv",
    "wof:placetype":"venue"
},
  "geometry": {"coordinates":[6.6157751083,52.4087142944],"type":"Point"}
}