{
  "type": "Feature",
  "properties": {
    "addr:full":"Bennebroekerwg 307 Hoofddorp Noord-Holland 2132 MD",
    "addr:housenumber":"307",
    "addr:postcode":"2132",
    "iso:country":"NL",
    "sg:address":"Bennebroekerwg 307",
    "sg:city":"Hoofddorp",
    "sg:orig_category":"Hek- En Rasterwerken",
    "sg:phone":"+31 23 555 6267",
    "sg:postcode":"2132 MD",
    "sg:province":"Noord-Holland",
    "wof:name":"Roubos Bv",
    "wof:placetype":"venue"
},
  "geometry": {"coordinates":[4.693801,52.268745],"type":"Point"}
}