{
  "type": "Feature",
  "properties": {
    "addr:full":"Laan Van Hilbelink 73 Winterswijk Gelderland 7101 WK",
    "addr:housenumber":"73",
    "addr:postcode":"7101 wk",
    "addr:street":"Laan Van Hilbelink;Gelderland",
    "iso:country":"NL",
    "sg:address":"Laan Van Hilbelink 73",
    "sg:city":"Winterswijk",
    "sg:classifiers":[
        {
            "category":"Education",
            "subcategory":"Preschool",
            "type":"Public Place"
        }
    ],
    "sg:phone":"+31 543 514 744",
    "sg:postcode":"7101 WK",
    "sg:province":"Gelderland",
    "sg:tags":[
        "kleuteronderwijs",
        "basis-"
    ],
    "wof:name":"Chr Basisschool Prins Willem Alexander",
    "wof:placetype":"venue"
},
  "geometry": {"coordinates":[6.732532,51.96841],"type":"Point"}
}