{
  "type": "Feature",
  "properties": {
    "addr:full":"Winkelhof 85 Leiderdorp Zuid-Holland 2353 TZ",
    "addr:housenumber":"85",
    "addr:postcode":"2353 tz",
    "addr:street":"Winkelhof",
    "iso:country":"NL",
    "sg:address":"Winkelhof 85",
    "sg:city":"Leiderdorp",
    "sg:orig_category":"Warenhuizen",
    "sg:phone":"+31 71 542 2875",
    "sg:postcode":"2353 TZ",
    "sg:province":"Zuid-Holland",
    "wof:name":"Hema",
    "wof:placetype":"venue"
},
  "geometry": {"coordinates":[4.5318198204,52.1623954773],"type":"Point"}
}