{
  "type": "Feature",
  "properties": {
    "addr:full":"Traay 84 Driebergen-Rijsenburg Utrecht 3971 GR",
    "addr:housenumber":"84",
    "addr:postcode":"3971",
    "addr:street":"Traay",
    "iso:country":"NL",
    "sg:address":"Traay 84",
    "sg:city":"Driebergen-Rijsenburg",
    "sg:orig_category":"Huishoudapparatuur, Televisies And Radio'S",
    "sg:phone":"+31 343 512 954",
    "sg:postcode":"3971 GR",
    "sg:province":"Utrecht",
    "wof:name":"Hora-Lensink Bv",
    "wof:placetype":"venue"
},
  "geometry": {"coordinates":[5.288177,52.054024],"type":"Point"}
}