{
  "type": "Feature",
  "properties": {
    "addr:full":"Hobbemaln 24 Bilthoven Utrecht 3723 ES",
    "addr:housenumber":"24",
    "addr:postcode":"3723 es",
    "addr:street":"Hobbemaln",
    "iso:country":"NL",
    "sg:address":"Hobbemaln 24",
    "sg:city":"Bilthoven",
    "sg:classifiers":[
        {
            "category":"Real Estate",
            "subcategory":"Real Estate Operator",
            "type":"Services"
        }
    ],
    "sg:phone":"+31 30 229 2424",
    "sg:postcode":"3723 ES",
    "sg:province":"Utrecht",
    "sg:tags":[
        "appartementen",
        "en",
        "flat"
    ],
    "wof:name":"Hobbemaflat, De",
    "wof:placetype":"venue"
},
  "geometry": {"coordinates":[5.21242,52.142529],"type":"Point"}
}