{
  "type": "Feature",
  "properties": {
    "addr:full":"Brediusweg 20 Bussum Noord-Holland 1401 AG",
    "addr:housenumber":"20",
    "addr:postcode":"1401",
    "addr:street":"Brediusweg",
    "iso:country":"NL",
    "sg:address":"Brediusweg 20",
    "sg:city":"Bussum",
    "sg:orig_category":"Verzekeringen",
    "sg:phone":"+31 35 692 5600",
    "sg:postcode":"1401 AG",
    "sg:province":"Noord-Holland",
    "wof:name":"Kuperus Zakelijke Diensten Bv",
    "wof:placetype":"venue"
},
  "geometry": {"coordinates":[5.166294,52.280518],"type":"Point"}
}