{
  "type": "Feature",
  "properties": {
    "addr:full":"Aelderstr 50 Aalden Drenthe 7854 RS",
    "addr:housenumber":"50",
    "addr:postcode":"7854 rs",
    "addr:street":"Aelderstr",
    "iso:country":"NL",
    "sg:address":"Aelderstr 50",
    "sg:city":"Aalden",
    "sg:orig_category":"Bloemen En Planten",
    "sg:phone":"+31 591 372 321",
    "sg:postcode":"7854 RS",
    "sg:province":"Drenthe",
    "wof:name":"Fleurie Vof",
    "wof:placetype":"venue"
},
  "geometry": {"coordinates":[6.720204,52.789009],"type":"Point"}
}