{
  "type": "Feature",
  "properties": {
    "addr:full":"Jansbinnensingel 2 Arnhem Gelderland 6811 AJ",
    "addr:housenumber":"2",
    "addr:postcode":"6811 aj",
    "addr:street":"Jansbinnensingel",
    "iso:country":"NL",
    "sg:address":"Jansbinnensingel 2",
    "sg:city":"Arnhem",
    "sg:orig_category":"Damesmodezaken",
    "sg:phone":"+31 26 370 5666",
    "sg:postcode":"6811 AJ",
    "sg:province":"Gelderland",
    "wof:name":"Monique Barree",
    "wof:placetype":"venue"
},
  "geometry": {"coordinates":[5.907536,51.984108],"type":"Point"}
}