{
  "type": "Feature",
  "properties": {
    "iso:country":"NL",
    "sg:address":"Zuiddijk 16",
    "sg:city":"Nieuwe Tonge",
    "sg:orig_category":"Kappers",
    "sg:phone":"+31 187 652 566",
    "sg:postcode":"3244 AZ",
    "sg:province":"South Holland",
    "wof:name":"Bellissimo Hairstudio Vof",
    "wof:placetype":"venue"
},
  "geometry": {"coordinates":[4.1635699272,51.7137718201],"type":"Point"}
}