{
  "type": "Feature",
  "properties": {
    "addr:full":"Kerkstraat 19 Veendam Groningen 9641 AM",
    "addr:housenumber":"19",
    "addr:postcode":"9641",
    "addr:street":"Kerkstraat",
    "iso:country":"NL",
    "sg:address":"Kerkstraat 19",
    "sg:city":"Veendam",
    "sg:orig_category":"Kappers",
    "sg:phone":"+31 598 617 042",
    "sg:postcode":"9641 AM",
    "sg:province":"Groningen",
    "wof:name":"Haarstudio Nauta",
    "wof:placetype":"venue"
},
  "geometry": {"coordinates":[6.8782129288,53.1047973633],"type":"Point"}
}