{
  "type": "Feature",
  "properties": {
    "addr:full":"Mathaakveld 15 Houten Utrecht 3993 SP",
    "addr:housenumber":"15",
    "addr:postcode":"3993 sp",
    "addr:street":"Mathaakveld",
    "iso:country":"NL",
    "sg:address":"Mathaakveld 15",
    "sg:city":"Houten",
    "sg:orig_category":"Public Relationbureaus",
    "sg:phone":"+31 30 635 3975",
    "sg:postcode":"3993 SP",
    "sg:province":"Utrecht",
    "wof:name":"To The Point",
    "wof:placetype":"venue"
},
  "geometry": {"coordinates":[5.177826,52.04192],"type":"Point"}
}