{
  "type": "Feature",
  "properties": {
    "iso:country":"NL",
    "sg:address":"Meerkoet 3",
    "sg:city":"Spanbroek",
    "sg:orig_category":"Pensioenen",
    "sg:phone":"+31 72 533 9917",
    "sg:postcode":"1715 HH",
    "sg:province":"Noord-Holland",
    "wof:name":"Pennywise",
    "wof:placetype":"venue"
},
  "geometry": {"coordinates":[4.954133,52.703457],"type":"Point"}
}