{
  "type": "Feature",
  "properties": {
    "iso:country":"NL",
    "sg:address":"Croesestr 132",
    "sg:city":"Utrecht",
    "sg:orig_category":"Vakantieverblijven",
    "sg:phone":"+31 30 214 8944",
    "sg:postcode":"3522 AJ",
    "sg:province":"Utrecht",
    "sg:website":"http://www.hungariahuizen.nl",
    "wof:name":"Hungaria Huizen",
    "wof:placetype":"venue"
},
  "geometry": {"coordinates":[5.115332,52.077709],"type":"Point"}
}