{
  "type": "Feature",
  "properties": {
    "addr:full":"Biltstr 449 Utrecht Utrecht 3572 AW",
    "addr:housenumber":"449",
    "addr:postcode":"3572 aw",
    "iso:country":"NL",
    "sg:address":"Biltstr 449",
    "sg:city":"Utrecht",
    "sg:orig_category":"Adviesbureaus Bedrijfsorganisatie",
    "sg:phone":"+31 30 238 1003",
    "sg:postcode":"3572 AW",
    "sg:province":"Utrecht",
    "wof:name":"Vooruit Bv",
    "wof:placetype":"venue"
},
  "geometry": {"coordinates":[5.136113,52.095428],"type":"Point"}
}