{
  "type": "Feature",
  "properties": {
    "iso:country":"NL",
    "sg:address":"Hoebigerweg 63",
    "sg:city":"Eys",
    "sg:orig_category":"Schoonheidssalons",
    "sg:phone":"+31 43 451 2467",
    "sg:postcode":"6287 AS",
    "sg:province":"Limburg",
    "wof:name":"Alice Den Heijer",
    "wof:placetype":"venue"
},
  "geometry": {"coordinates":[5.942247,50.823788],"type":"Point"}
}