{
  "type": "Feature",
  "properties": {
    "addr:full":"Provincialewg 73 Sebaldeburen Groningen 9862 PC",
    "addr:housenumber":"73",
    "addr:postcode":"9862 pc",
    "addr:street":"Provincialewg",
    "iso:country":"NL",
    "sg:address":"Provincialewg 73",
    "sg:city":"Sebaldeburen",
    "sg:orig_category":"Meubelstoffering",
    "sg:phone":"+31 594 613 742",
    "sg:postcode":"9862 PC",
    "sg:province":"Groningen",
    "wof:name":"Abm Meubelstoffering",
    "wof:placetype":"venue"
},
  "geometry": {"coordinates":[6.307789,53.220562],"type":"Point"}
}