{
  "type": "Feature",
  "properties": {
    "addr:full":"Leliegracht 16 Amsterdam North Holland 1015 DE",
    "addr:housenumber":"16",
    "addr:postcode":"1015 de",
    "addr:street":"Leliegracht",
    "iso:country":"NL",
    "sg:address":"Leliegracht 16",
    "sg:city":"Amsterdam",
    "sg:orig_category":"Meubels And Huishoudapparatuur Gh",
    "sg:phone":"+31 20 627 1622",
    "sg:postcode":"1015 DE",
    "sg:province":"North Holland",
    "wof:name":"Object Art Deco",
    "wof:placetype":"venue"
},
  "geometry": {"coordinates":[4.88718,52.375229],"type":"Point"}
}