{
  "type": "Feature",
  "properties": {
    "addr:full":"Assendorperstr 179 Zwolle Overijssel 8012 DM",
    "addr:housenumber":"179",
    "addr:postcode":"8012 dm",
    "iso:country":"NL",
    "sg:address":"Assendorperstr 179",
    "sg:city":"Zwolle",
    "sg:orig_category":"Afslankinstituten",
    "sg:phone":"+31 38 421 1073",
    "sg:postcode":"8012 DM",
    "sg:province":"Overijssel",
    "wof:name":"Slender Vital",
    "wof:placetype":"venue"
},
  "geometry": {"coordinates":[6.105816,52.502804],"type":"Point"}
}