{
  "type": "Feature",
  "properties": {
    "addr:full":"De Wielewaal 4 Surhuisterveen Provincie Friesland 9231 JL",
    "addr:housenumber":"4",
    "addr:postcode":"9231 jl",
    "addr:street":"De Wielewaal;Provincie Friesland",
    "iso:country":"NL",
    "sg:address":"De Wielewaal 4",
    "sg:city":"Surhuisterveen",
    "sg:orig_category":"Zonnebank- En Solariumcentra",
    "sg:phone":"+31 512 363 869",
    "sg:postcode":"9231 JL",
    "sg:province":"Provincie Friesland",
    "wof:name":"Bauk",
    "wof:placetype":"venue"
},
  "geometry": {"coordinates":[6.173413,53.185162],"type":"Point"}
}