{
  "type": "Feature",
  "properties": {
    "addr:full":"Pr J Frisostr 19 Everdingen Utrecht 4121 EX",
    "addr:housenumber":"19",
    "addr:postcode":"4121 ex",
    "iso:country":"NL",
    "sg:address":"Pr J Frisostr 19",
    "sg:city":"Everdingen",
    "sg:orig_category":"Hoefsmederijen",
    "sg:phone":"+31 6 51513818",
    "sg:postcode":"4121 EX",
    "sg:province":"Utrecht",
    "wof:name":"Rooij, Dennis De",
    "wof:placetype":"venue"
},
  "geometry": {"coordinates":[5.157621,51.963108],"type":"Point"}
}