{
  "type": "Feature",
  "properties": {
    "iso:country":"NL",
    "sg:address":"Groenewoudseweg 1",
    "sg:city":"Nijmegen",
    "sg:orig_category":"Hoger Onderwijs",
    "sg:phone":"+31 24 323 3778",
    "sg:postcode":"6524 TM",
    "sg:province":"Gelderland",
    "wof:name":"Pabo Groenewoud-Nijmegen",
    "wof:placetype":"venue"
},
  "geometry": {"coordinates":[5.873877,51.82988],"type":"Point"}
}