{
  "type": "Feature",
  "properties": {
    "iso:country":"NL",
    "sg:address":"Watersnip 11",
    "sg:city":"Eemnes",
    "sg:orig_category":"Beeldende Kunstenaars",
    "sg:phone":"+31 35 531 4555",
    "sg:postcode":"3755 GK",
    "sg:province":"Utrecht",
    "wof:name":"Spronsen, Cecile Van",
    "wof:placetype":"venue"
},
  "geometry": {"coordinates":[5.262049,52.259274],"type":"Point"}
}