{
  "type": "Feature",
  "properties": {
    "iso:country":"NL",
    "sg:address":"Catharinadal 13",
    "sg:city":"'S Hertogenbosch",
    "sg:orig_category":"Marktonderzoekbureaus",
    "sg:phone":"+31 73 642 3771",
    "sg:postcode":"5235 BJ",
    "sg:province":"North Brabant",
    "wof:name":"Marketing Adviesbureau Rooderkerk Bv",
    "wof:placetype":"venue"
},
  "geometry": {"coordinates":[5.3155708313,51.725353241],"type":"Point"}
}