{
  "type": "Feature",
  "properties": {
    "addr:full":"De Amstel 50 Dronten Flevoland 8253 PC",
    "addr:housenumber":"50",
    "addr:postcode":"8253 pc",
    "addr:street":"De Amstel;Flevoland",
    "iso:country":"NL",
    "sg:address":"De Amstel 50",
    "sg:city":"Dronten",
    "sg:orig_category":"Zonnebank- En Solariumcentra",
    "sg:phone":"+31 321 380 339",
    "sg:postcode":"8253 PC",
    "sg:province":"Flevoland",
    "wof:name":"Wendy",
    "wof:placetype":"venue"
},
  "geometry": {"coordinates":[5.70101,52.541512],"type":"Point"}
}