{
  "type": "Feature",
  "properties": {
    "addr:full":"Wilhelminaln 2E Hoorn Nh Noord-Holland 1623 MA",
    "addr:housenumber":"2e",
    "addr:postcode":"1623 ma",
    "addr:street":"Wilhelminaln",
    "iso:country":"NL",
    "sg:address":"Wilhelminaln 2E",
    "sg:city":"Hoorn Nh",
    "sg:orig_category":"Verenigingen En Stichtingen",
    "sg:phone":"+31 229 210 948",
    "sg:postcode":"1623 MA",
    "sg:province":"Noord-Holland",
    "wof:name":"Vakantiespelen, Sticht",
    "wof:placetype":"venue"
},
  "geometry": {"coordinates":[5.067433,52.64534],"type":"Point"}
}