{
  "type": "Feature",
  "properties": {
    "addr:full":"Baarsjeswg 289 Amsterdam North Holland 1058 AG",
    "addr:housenumber":"289",
    "addr:postcode":"1058",
    "iso:country":"NL",
    "sg:address":"Baarsjeswg 289",
    "sg:city":"Amsterdam",
    "sg:orig_category":"Verf En Lak - Fabrieken En Groothandel",
    "sg:phone":"+31 20 683 0573",
    "sg:postcode":"1058 AG",
    "sg:province":"North Holland",
    "wof:name":"Herfst En Helder Bv",
    "wof:placetype":"venue"
},
  "geometry": {"coordinates":[4.855734,52.359718],"type":"Point"}
}