{
  "type": "Feature",
  "properties": {
    "addr:full":"Oudegracht 193 Utrecht Utrecht 3511 NG",
    "addr:housenumber":"193",
    "addr:postcode":"3511 ng",
    "addr:street":"Oudegracht",
    "iso:country":"NL",
    "sg:address":"Oudegracht 193",
    "sg:city":"Utrecht",
    "sg:orig_category":"Drukkerijen And Copyshops",
    "sg:phone":"+31 30 231 1346",
    "sg:postcode":"3511 NG",
    "sg:province":"Utrecht",
    "wof:name":"Drukkerij Abels Bv",
    "wof:placetype":"venue"
},
  "geometry": {"coordinates":[5.115405,52.088932],"type":"Point"}
}