{
  "type": "Feature",
  "properties": {
    "addr:full":"Langstr 40 Wyhe Overijssel 8131 BC",
    "addr:housenumber":"40",
    "addr:postcode":"8131 bc",
    "addr:street":"Langstr;Overijssel",
    "iso:country":"NL",
    "sg:address":"Langstr 40",
    "sg:city":"Wyhe",
    "sg:orig_category":"Babyartikelen",
    "sg:phone":"+31 570 521 221",
    "sg:postcode":"8131 BC",
    "sg:province":"Overijssel",
    "wof:name":"Kleinsorge",
    "wof:placetype":"venue"
},
  "geometry": {"coordinates":[-126.555511,54.485668],"type":"Point"}
}