{
  "type": "Feature",
  "properties": {
    "addr:full":"D Beyenszln 68 Poortugaal South Holland 3176 XA",
    "addr:housenumber":"68",
    "addr:postcode":"3176 xa",
    "iso:country":"NL",
    "sg:address":"D Beyenszln 68",
    "sg:city":"Poortugaal",
    "sg:orig_category":"Verhuur",
    "sg:phone":"+31 6 55897220",
    "sg:postcode":"3176 XA",
    "sg:province":"South Holland",
    "wof:name":"Ronde Jr, J C De",
    "wof:placetype":"venue"
},
  "geometry": {"coordinates":[4.39884,51.865608],"type":"Point"}
}