{
  "type": "Feature",
  "properties": {
    "addr:full":"Zandhofsestr 41 Utrecht Utrecht 3572 GB",
    "addr:housenumber":"41",
    "addr:postcode":"3572 gb",
    "addr:street":"Zandhofsestr",
    "iso:country":"NL",
    "sg:address":"Zandhofsestr 41",
    "sg:city":"Utrecht",
    "sg:classifiers":[
        {
            "category":"Professional",
            "type":"Services"
        }
    ],
    "sg:phone":"+31 30 276 1796",
    "sg:postcode":"3572 GB",
    "sg:province":"Utrecht",
    "sg:tags":[
        "leasing"
    ],
    "wof:name":"Fleet Knowledge Bv",
    "wof:placetype":"venue"
},
  "geometry": {"coordinates":[5.130971,52.098438],"type":"Point"}
}