{
  "type": "Feature",
  "properties": {
    "iso:country":"NL",
    "sg:address":"V Tuyll V Serooskerkenwg 21",
    "sg:city":"Amsterdam",
    "sg:orig_category":"Koeriersdiensten",
    "sg:phone":"+31 6 53101535",
    "sg:postcode":"1076 JA",
    "sg:province":"Noord-Holland",
    "wof:name":"T.G.P. Koeriers",
    "wof:placetype":"venue"
},
  "geometry": {"coordinates":[4.85812,52.344231],"type":"Point"}
}