{
  "type": "Feature",
  "properties": {
    "addr:full":"St Annastr 60 Gemert Noord-Brabant 5421 KC",
    "addr:housenumber":"60",
    "addr:postcode":"5421 kc",
    "iso:country":"NL",
    "sg:address":"St Annastr 60",
    "sg:city":"Gemert",
    "sg:orig_category":"Verenigingen En Stichtingen",
    "sg:phone":"+31 492 365 442",
    "sg:postcode":"5421 KC",
    "sg:province":"Noord-Brabant",
    "sg:website":"http://www.jcdebunker.nl",
    "wof:name":"Bunker, Jc De",
    "wof:placetype":"venue"
},
  "geometry": {"coordinates":[5.691103,51.5578],"type":"Point"}
}