{
  "type": "Feature",
  "properties": {
    "iso:country":"NL",
    "sg:address":"Postbus 36",
    "sg:city":"Gulpen",
    "sg:orig_category":"Vertaalbureaus",
    "sg:phone":"+31 43 457 3384",
    "sg:postcode":"6270 AA",
    "sg:province":"Limburg",
    "wof:name":"Bogaert, Van",
    "wof:placetype":"venue"
},
  "geometry": {"coordinates":[5.88998,50.817322],"type":"Point"}
}