{
  "type": "Feature",
  "properties": {
    "addr:full":"Dr A Kuyperweg 73 Beesd Gelderland 4153 XA",
    "addr:housenumber":"73",
    "addr:postcode":"4153 xa",
    "addr:street":"Dr A Kuyperweg;Gelderland",
    "iso:country":"NL",
    "sg:address":"Dr A Kuyperweg 73",
    "sg:city":"Beesd",
    "sg:orig_category":"Bloemen And Planten",
    "sg:phone":"+31 345 683 030",
    "sg:postcode":"4153 XA",
    "sg:province":"Gelderland",
    "wof:name":"Firma M.W. Kroeze En Zonen",
    "wof:placetype":"venue"
},
  "geometry": {"coordinates":[5.17919,51.892094],"type":"Point"}
}