{
  "type": "Feature",
  "properties": {
    "addr:full":"Meerlaan 1 Uithoorn North Holland 1421 TM",
    "addr:housenumber":"1",
    "addr:postcode":"1421 tm",
    "addr:street":"Meerlaan",
    "iso:country":"NL",
    "sg:address":"Meerlaan 1",
    "sg:city":"Uithoorn",
    "sg:orig_category":"Verzekeringen",
    "sg:phone":"+31 297 540 419",
    "sg:postcode":"1421 TM",
    "sg:province":"North Holland",
    "wof:name":"Bohnenn & Van Santen Assurantien",
    "wof:placetype":"venue"
},
  "geometry": {"coordinates":[4.827551,52.23317],"type":"Point"}
}