{
  "type": "Feature",
  "properties": {
    "iso:country":"NL",
    "sg:address":"H De Grootstr 25",
    "sg:city":"Geldermalsen",
    "sg:orig_category":"Kappers",
    "sg:phone":"+31 345 577 610",
    "sg:postcode":"4191 ZN",
    "sg:province":"Gelderland",
    "wof:name":"Maxim",
    "wof:placetype":"venue"
},
  "geometry": {"coordinates":[5.305252,51.887596],"type":"Point"}
}