{
  "type": "Feature",
  "properties": {
    "addr:full":"Amstelveensewg 760 Amsterdam Noord-Holland 1081 JK",
    "addr:housenumber":"760",
    "addr:postcode":"1081 jk",
    "iso:country":"NL",
    "sg:address":"Amstelveensewg 760",
    "sg:city":"Amsterdam",
    "sg:orig_category":"Adviesbureaus Bedrijfsorganisatie",
    "sg:phone":"+31 20 301 4000",
    "sg:postcode":"1081 JK",
    "sg:province":"Noord-Holland",
    "sg:website":"http://www.boercroon.nl",
    "wof:name":"Boer & Croon Strategy And Management Group",
    "wof:placetype":"venue"
},
  "geometry": {"coordinates":[4.857175,52.331425],"type":"Point"}
}