{
  "type": "Feature",
  "properties": {
    "iso:country":"NL",
    "sg:address":"Lokkerdreef 37C",
    "sg:city":"Etten Leur",
    "sg:orig_category":"Koffiebranderijen",
    "sg:phone":"+31 76 503 0116",
    "sg:postcode":"4879 ND",
    "sg:province":"Noord-Brabant",
    "wof:name":"Mocca Mecca",
    "wof:placetype":"venue"
},
  "geometry": {"coordinates":[4.616724,51.558346],"type":"Point"}
}