{
  "type": "Feature",
  "properties": {
    "addr:full":"Lokkerdreef 37C Etten Leur Noord-Brabant 4879 ND",
    "addr:housenumber":"37c",
    "addr:postcode":"4879 nd",
    "addr:street":"Lokkerdreef",
    "iso:country":"NL",
    "sg:address":"Lokkerdreef 37C",
    "sg:city":"Etten Leur",
    "sg:orig_category":"Koffiebranderijen",
    "sg:phone":"+31 76 503 0116",
    "sg:postcode":"4879 ND",
    "sg:province":"Noord-Brabant",
    "wof:name":"Mocca Mecca",
    "wof:placetype":"venue"
},
  "geometry": {"coordinates":[4.616724,51.558346],"type":"Point"}
}