{
  "type": "Feature",
  "properties": {
    "addr:full":"Banjostraat 1 Rijswijk Zh Zuid-Holland 2287 EJ",
    "addr:housenumber":"1",
    "addr:postcode":"zh;2287 ej",
    "addr:street":"Banjostraat",
    "iso:country":"NL",
    "sg:address":"Banjostraat 1",
    "sg:city":"Rijswijk Zh",
    "sg:orig_category":"Wasserettes And Stomerijen",
    "sg:phone":"+31 70 393 9583",
    "sg:postcode":"2287 EJ",
    "sg:province":"Zuid-Holland",
    "wof:name":"Stomery Verhoeve",
    "wof:placetype":"venue"
},
  "geometry": {"coordinates":[4.3209037781,52.0330924988],"type":"Point"}
}