{
  "type": "Feature",
  "properties": {
    "addr:full":"Midstraat 151 Joure Provincie Friesland 8501 AK",
    "addr:housenumber":"151",
    "addr:postcode":"8501 ak",
    "addr:street":"Midstraat;Provincie Friesland",
    "iso:country":"NL",
    "sg:address":"Midstraat 151",
    "sg:city":"Joure",
    "sg:orig_category":"Opticiens",
    "sg:phone":"+31 513 418 651",
    "sg:postcode":"8501 AK",
    "sg:province":"Provincie Friesland",
    "wof:name":"Hans Anders Opticiens",
    "wof:placetype":"venue"
},
  "geometry": {"coordinates":[5.7979989052,52.9663925171],"type":"Point"}
}