{
  "type": "Feature",
  "properties": {
    "addr:full":"Nieuwe Kerkstraat 29 Nijkerkerveen Gelderland 3864 EA",
    "addr:housenumber":"29",
    "addr:postcode":"3864 ea",
    "addr:street":"Nieuwe Kerkstraat;Gelderland",
    "iso:country":"NL",
    "sg:address":"Nieuwe Kerkstraat 29",
    "sg:city":"Nijkerkerveen",
    "sg:orig_category":"Levende Dieren Gh",
    "sg:phone":"+31 33 257 2851",
    "sg:postcode":"3864 EA",
    "sg:province":"Gelderland",
    "wof:name":"Poeliersbedrijf Nico Van De Bunt Bv",
    "wof:placetype":"venue"
},
  "geometry": {"coordinates":[5.459754,52.195339],"type":"Point"}
}