{
  "type": "Feature",
  "properties": {
    "addr:full":"Vlasmarkt 53 Middelburg Zeeland 4331 PD",
    "addr:housenumber":"53",
    "addr:postcode":"4331 pd",
    "addr:street":"Vlasmarkt",
    "iso:country":"NL",
    "sg:address":"Vlasmarkt 53",
    "sg:city":"Middelburg",
    "sg:orig_category":"Schoonheidssalons",
    "sg:phone":"+31 118 614 865",
    "sg:postcode":"4331 PD",
    "sg:province":"Zeeland",
    "wof:name":"Marnel Jeras",
    "wof:placetype":"venue"
},
  "geometry": {"coordinates":[3.608816,51.498543],"type":"Point"}
}