{
  "type": "Feature",
  "properties": {
    "addr:full":"Kerkstraat 8 Roermond Limburg 6042 LL",
    "addr:housenumber":"8",
    "addr:postcode":"6042 ll",
    "addr:street":"Kerkstraat",
    "iso:country":"NL",
    "sg:address":"Kerkstraat 8",
    "sg:city":"Roermond",
    "sg:orig_category":"Autokeuringen",
    "sg:phone":"+31 475 326 713",
    "sg:postcode":"6042 LL",
    "sg:province":"Limburg",
    "wof:name":"Garage Paul Verheggen",
    "wof:placetype":"venue"
},
  "geometry": {"coordinates":[6.047468,51.192333],"type":"Point"}
}