{
  "type": "Feature",
  "properties": {
    "addr:full":"Wamberg 65 Amsterdam Noord-Holland 1083 CX",
    "addr:housenumber":"65",
    "addr:postcode":"1083 cx",
    "addr:street":"Wamberg",
    "iso:country":"NL",
    "sg:address":"Wamberg 65",
    "sg:city":"Amsterdam",
    "sg:orig_category":"Houtgroothandel",
    "sg:phone":"+31 20 404 3256",
    "sg:postcode":"1083 CX",
    "sg:province":"Noord-Holland",
    "wof:name":"Wellwood Nederland Bv",
    "wof:placetype":"venue"
},
  "geometry": {"coordinates":[4.885829,52.327377],"type":"Point"}
}