{
  "type": "Feature",
  "properties": {
    "addr:full":"Prof De Jongstr 18 Hilversum Noord-Holland 1221 HZ",
    "addr:housenumber":"18",
    "addr:postcode":"1221 hz",
    "addr:street":"Prof",
    "iso:country":"NL",
    "sg:address":"Prof De Jongstr 18",
    "sg:city":"Hilversum",
    "sg:orig_category":"Kappers",
    "sg:phone":"+31 35 685 4580",
    "sg:postcode":"1221 HZ",
    "sg:province":"Noord-Holland",
    "wof:name":"Dolle, R Ten",
    "wof:placetype":"venue"
},
  "geometry": {"coordinates":[5.1853961945,52.224609375],"type":"Point"}
}