{
  "type": "Feature",
  "properties": {
    "addr:full":"Palenbergstr 57 Heerlen Limburg 6415 RB",
    "addr:housenumber":"57",
    "addr:postcode":"6415 rb",
    "addr:street":"Palenbergstr",
    "iso:country":"NL",
    "sg:address":"Palenbergstr 57",
    "sg:city":"Heerlen",
    "sg:orig_category":"Verbouwingen",
    "sg:phone":"+31 45 572 3308",
    "sg:postcode":"6415 RB",
    "sg:province":"Limburg",
    "wof:name":"Mija Vof",
    "wof:placetype":"venue"
},
  "geometry": {"coordinates":[5.983171,50.903351],"type":"Point"}
}