{
  "type": "Feature",
  "properties": {
    "addr:full":"Van Limburg Stirumstraat 69 Amsterdam Noord-Holland 1051 BA",
    "addr:housenumber":"69",
    "addr:postcode":"1051 ba",
    "addr:street":"Van Limburg Stirumstraat",
    "iso:country":"NL",
    "sg:address":"Van Limburg Stirumstraat 69",
    "sg:city":"Amsterdam",
    "sg:classifiers":[
        {
            "category":"Fast Food",
            "type":"Food & Drink"
        }
    ],
    "sg:phone":"+31 20 684 1444",
    "sg:postcode":"1051 BA",
    "sg:province":"Noord-Holland",
    "sg:tags":[
        "afhaal",
        "restaurant"
    ],
    "wof:name":"Stomy'S Snackbar",
    "wof:placetype":"venue"
},
  "geometry": {"coordinates":[4.875371,52.384247],"type":"Point"}
}