{
  "type": "Feature",
  "properties": {
    "addr:full":"Esschestraat 1 Vught Noord-Brabant 5262 BA",
    "addr:housenumber":"1",
    "addr:postcode":"5262 ba",
    "addr:street":"Esschestraat",
    "iso:country":"NL",
    "sg:address":"Esschestraat 1",
    "sg:city":"Vught",
    "sg:orig_category":"Overheidsdiensten",
    "sg:phone":"+31 73 656 6232",
    "sg:postcode":"5262 BA",
    "sg:province":"Noord-Brabant",
    "wof:name":"Gouden Zonne",
    "wof:placetype":"venue"
},
  "geometry": {"coordinates":[5.2922420502,51.6525268555],"type":"Point"}
}