{
  "type": "Feature",
  "properties": {
    "addr:full":"Binnenweide 3 Veghel Noord-Brabant 5467 ML",
    "addr:housenumber":"3",
    "addr:postcode":"5467 ml",
    "addr:street":"Binnenweide",
    "iso:country":"NL",
    "sg:address":"Binnenweide 3",
    "sg:city":"Veghel",
    "sg:orig_category":"Projectontwikkeling",
    "sg:phone":"+31 6 51563239",
    "sg:postcode":"5467 ML",
    "sg:province":"Noord-Brabant",
    "wof:name":"Tiemstra, Ir J S",
    "wof:placetype":"venue"
},
  "geometry": {"coordinates":[5.565879,51.622303],"type":"Point"}
}