{
  "type": "Feature",
  "properties": {
    "addr:full":"Van Merlenlaan 7 Heemstede North Holland 2103 GA",
    "addr:housenumber":"7",
    "addr:postcode":"2103 ga",
    "addr:street":"Van Merlenlaan",
    "iso:country":"NL",
    "sg:address":"Van Merlenlaan 7",
    "sg:city":"Heemstede",
    "sg:orig_category":"Vertaal- And Tolkenbureaus",
    "sg:phone":"+31 23 528 4411",
    "sg:postcode":"2103 GA",
    "sg:province":"North Holland",
    "wof:name":"J Vd Weiden",
    "wof:placetype":"venue"
},
  "geometry": {"coordinates":[4.618731,52.345837],"type":"Point"}
}