{
  "type": "Feature",
  "properties": {
    "addr:full":"Fellenoordstraat 1 Breda Noord-Brabant 4811 TG",
    "addr:housenumber":"1",
    "addr:postcode":"4811 tg",
    "addr:street":"Fellenoordstraat",
    "iso:country":"NL",
    "sg:address":"Fellenoordstraat 1",
    "sg:city":"Breda",
    "sg:orig_category":"Kappers",
    "sg:phone":"+31 76 520 1955",
    "sg:postcode":"4811 TG",
    "sg:province":"Noord-Brabant",
    "wof:name":"Dames- En Herenkapsalon Cabello",
    "wof:placetype":"venue"
},
  "geometry": {"coordinates":[4.7657608986,51.5867080688],"type":"Point"}
}