{
  "type": "Feature",
  "properties": {
    "addr:full":"Zinkweg 283 Oud Beijerland South Holland 3262 BH",
    "addr:housenumber":"283",
    "addr:postcode":"3262 bh",
    "addr:street":"Zinkweg;Oud Beijerland",
    "iso:country":"NL",
    "sg:address":"Zinkweg 283",
    "sg:city":"Oud Beijerland",
    "sg:orig_category":"Landbouwmachines Gh",
    "sg:phone":"+31 186 613 384",
    "sg:postcode":"3262 BH",
    "sg:province":"South Holland",
    "wof:name":"Dijkstra Tractorenbedrijf",
    "wof:placetype":"venue"
},
  "geometry": {"coordinates":[4.393118,51.814564],"type":"Point"}
}