{
  "type": "Feature",
  "properties": {
    "addr:full":"Beekseweg 7 Lieshout Noord-Brabant 5737 RC",
    "addr:housenumber":"7",
    "addr:postcode":"5737 rc",
    "addr:street":"Beekseweg",
    "iso:country":"NL",
    "sg:address":"Beekseweg 7",
    "sg:city":"Lieshout",
    "sg:orig_category":"Landbouwmachines Gh",
    "sg:phone":"+31 499 422 435",
    "sg:postcode":"5737 RC",
    "sg:province":"Noord-Brabant",
    "wof:name":"S.J. Staadegaard & Zonen Bv",
    "wof:placetype":"venue"
},
  "geometry": {"coordinates":[5.612998,51.521301],"type":"Point"}
}