{
  "type": "Feature",
  "properties": {
    "addr:full":"Deutzstraat 19 Oegstgeest South Holland 2342 AC",
    "addr:housenumber":"19",
    "addr:postcode":"2342 ac",
    "addr:street":"Deutzstraat",
    "iso:country":"NL",
    "sg:address":"Deutzstraat 19",
    "sg:city":"Oegstgeest",
    "sg:orig_category":"Kinderopvang Behalve Thuis",
    "sg:phone":"+31 71 517 4930",
    "sg:postcode":"2342 AC",
    "sg:province":"South Holland",
    "wof:name":"Peuterspeelzaal Juliana",
    "wof:placetype":"venue"
},
  "geometry": {"coordinates":[4.464622,52.178764],"type":"Point"}
}