{
  "type": "Feature",
  "properties": {
    "addr:full":"Postbus 68 Dordrecht Zuid-Holland 3300 AB",
    "addr:housenumber":"68",
    "addr:postcode":"3300 ab",
    "addr:street":"Postbus",
    "iso:country":"NL",
    "sg:address":"Postbus 68",
    "sg:city":"Dordrecht",
    "sg:orig_category":"Koffiebranderijen",
    "sg:phone":"+31 78 654 6111",
    "sg:postcode":"3300 AB",
    "sg:province":"Zuid-Holland",
    "sg:website":"http://www.ics-vending.com",
    "wof:name":"Ics Int Bv",
    "wof:placetype":"venue"
},
  "geometry": {"coordinates":[4.66837,51.811199],"type":"Point"}
}