{
  "type": "Feature",
  "properties": {
    "addr:full":"Kerkweg 60 Vaassen Gelderland 8171 VP",
    "addr:housenumber":"60",
    "addr:postcode":"8171 vp",
    "addr:street":"Kerkweg;Gelderland",
    "iso:country":"NL",
    "sg:address":"Kerkweg 60",
    "sg:city":"Vaassen",
    "sg:orig_category":"Loodgieterswerk, Verwarming And Sanitaire Installaties",
    "sg:phone":"+31 578 572 311",
    "sg:postcode":"8171 VP",
    "sg:province":"Gelderland",
    "wof:name":"J.J. Brummelkamp",
    "wof:placetype":"venue"
},
  "geometry": {"coordinates":[5.960833,52.28854],"type":"Point"}
}