{
  "type": "Feature",
  "properties": {
    "addr:full":"St Jansgildestr 14 Beek Gem Bergh Gelderland 7037 DM",
    "addr:housenumber":"14",
    "addr:postcode":"7037 dm",
    "iso:country":"NL",
    "sg:address":"St Jansgildestr 14",
    "sg:city":"Beek Gem Bergh",
    "sg:orig_category":"Bodemonderzoek",
    "sg:phone":"+31 316 532 256",
    "sg:postcode":"7037 DM",
    "sg:province":"Gelderland",
    "sg:website":"http://www.vcmi.nl",
    "wof:name":"Vcmi",
    "wof:placetype":"venue"
},
  "geometry": {"coordinates":[6.195673,51.916553],"type":"Point"}
}