{
  "type": "Feature",
  "properties": {
    "addr:full":"Raadhuisstraat 52 Terheijden North Brabant 4844 AE",
    "addr:housenumber":"52",
    "addr:postcode":"4844 ae",
    "addr:street":"Raadhuisstraat",
    "iso:country":"NL",
    "sg:address":"Raadhuisstraat 52",
    "sg:city":"Terheijden",
    "sg:orig_category":"Verlichting And Huishoudartikelen",
    "sg:phone":"+31 76 593 2317",
    "sg:postcode":"4844 AE",
    "sg:province":"North Brabant",
    "wof:name":"Whistling Jack",
    "wof:placetype":"venue"
},
  "geometry": {"coordinates":[4.749305,51.644642],"type":"Point"}
}