{
  "type": "Feature",
  "properties": {
    "iso:country":"NL",
    "sg:address":"Kennemerstraat 30",
    "sg:city":"Haarlem",
    "sg:orig_category":"Huishoudapparatuur, Televisies And Radio'S",
    "sg:phone":"+31 23 527 6830",
    "sg:postcode":"2021 ED",
    "sg:province":"Noord-Holland",
    "wof:name":"Firma Elmo",
    "wof:placetype":"venue"
},
  "geometry": {"coordinates":[4.639144,52.391872],"type":"Point"}
}