{
  "type": "Feature",
  "properties": {
    "addr:full":"2E De Carpentierstraat 244 'S Gravenhage Zuid-Holland 2595 HN",
    "addr:housenumber":"244 '",
    "addr:postcode":"2595 hn",
    "addr:street":"2E De Carpentierstraat",
    "iso:country":"NL",
    "sg:address":"2E De Carpentierstraat 244",
    "sg:city":"'S Gravenhage",
    "sg:orig_category":"Hout Gh",
    "sg:phone":"+31 70 385 2271",
    "sg:postcode":"2595 HN",
    "sg:province":"Zuid-Holland",
    "wof:name":"Kleuskens Fijnhouthandel",
    "wof:placetype":"venue"
},
  "geometry": {"coordinates":[4.340071,52.082771],"type":"Point"}
}