{
  "type": "Feature",
  "properties": {
    "addr:full":"Kastanjeln 5 Leusden Utrecht 3833 AN",
    "addr:housenumber":"5",
    "addr:postcode":"3833 an",
    "addr:street":"Kastanjeln",
    "iso:country":"NL",
    "sg:address":"Kastanjeln 5",
    "sg:city":"Leusden",
    "sg:orig_category":"Adviesbureaus",
    "sg:phone":"+31 33 432 6000",
    "sg:postcode":"3833 AN",
    "sg:province":"Utrecht",
    "sg:website":"HTTP://www.etcint.org",
    "wof:name":"Etc Ned Bv",
    "wof:placetype":"venue"
},
  "geometry": {"coordinates":[5.42959,52.131248],"type":"Point"}
}