{
  "type": "Feature",
  "properties": {
    "addr:full":"Berenkoog 6-8 Alkmaar North Holland 1822 BJ",
    "addr:housenumber":"6-8",
    "addr:postcode":"1822 bj",
    "addr:street":"Berenkoog",
    "iso:country":"NL",
    "sg:address":"Berenkoog 6-8",
    "sg:city":"Alkmaar",
    "sg:orig_category":"Banden",
    "sg:phone":"+31 72 512 6124",
    "sg:postcode":"1822 BJ",
    "sg:province":"North Holland",
    "sg:website":"http://www.noorderkade.alkmaar.nl",
    "wof:name":"Bandenservice Noorderkade Bv",
    "wof:placetype":"venue"
},
  "geometry": {"coordinates":[4.780981,52.643238],"type":"Point"}
}