{
  "type": "Feature",
  "properties": {
    "addr:full":"Van Woustraat 38 Amsterdam Noord-Holland 1073 LM",
    "addr:housenumber":"38",
    "addr:postcode":"1073 lm",
    "addr:street":"Van Woustraat",
    "iso:country":"NL",
    "sg:address":"Van Woustraat 38",
    "sg:city":"Amsterdam",
    "sg:orig_category":"Parfum And Cosmetica Gh",
    "sg:phone":"+31 20 662 0738",
    "sg:postcode":"1073 LM",
    "sg:province":"Noord-Holland",
    "wof:name":"Parfumella Bv",
    "wof:placetype":"venue"
},
  "geometry": {"coordinates":[4.899714,52.356426],"type":"Point"}
}