{
  "type": "Feature",
  "properties": {
    "addr:full":"Kerkring 7 Standdaarbuiten North Brabant 4758 SZ",
    "addr:housenumber":"7",
    "addr:postcode":"4758 sz",
    "addr:street":"Kerkring",
    "iso:country":"NL",
    "sg:address":"Kerkring 7",
    "sg:city":"Standdaarbuiten",
    "sg:orig_category":"Oldtimers",
    "sg:phone":"+31 168 412 994",
    "sg:postcode":"4758 SZ",
    "sg:province":"North Brabant",
    "wof:name":"Moerdijkse Oldtimer Vrienden",
    "wof:placetype":"venue"
},
  "geometry": {"coordinates":[4.533649,51.641483],"type":"Point"}
}