{
  "type": "Feature",
  "properties": {
    "addr:full":"Kelperweg 7 Leveroy Limburg 6091 NC",
    "addr:housenumber":"7",
    "addr:postcode":"6091 nc",
    "addr:street":"Kelperweg",
    "iso:country":"NL",
    "sg:address":"Kelperweg 7",
    "sg:city":"Leveroy",
    "sg:orig_category":"Partycatering And -Organisatie",
    "sg:phone":"+31 495 652 213",
    "sg:postcode":"6091 NC",
    "sg:province":"Limburg",
    "wof:name":"Banziger Kamphuis Partycatering",
    "wof:placetype":"venue"
},
  "geometry": {"coordinates":[5.818702,51.245384],"type":"Point"}
}