{
  "type": "Feature",
  "properties": {
    "addr:full":"Nw Kerkhof 6 Groningen Groningen 9712 PT",
    "addr:housenumber":"6",
    "addr:postcode":"9712 pt",
    "addr:street":"Nw Kerkhof",
    "iso:country":"NL",
    "sg:address":"Nw Kerkhof 6",
    "sg:city":"Groningen",
    "sg:orig_category":"Accountants - Administratie- Consulenten En -Kantoren",
    "sg:phone":"+31 50 503 5919",
    "sg:postcode":"9712 PT",
    "sg:province":"Groningen",
    "wof:name":"Koops Accountancy",
    "wof:placetype":"venue"
},
  "geometry": {"coordinates":[6.562167,53.222736],"type":"Point"}
}