{
  "type": "Feature",
  "properties": {
    "iso:country":"NL",
    "sg:address":"Middenwg 8",
    "sg:city":"Opheusden",
    "sg:orig_category":"Bloemen En Planten",
    "sg:phone":"+31 488 442 506",
    "sg:postcode":"4043 MD",
    "sg:province":"Gelderland",
    "wof:name":"Steen, Van Der",
    "wof:placetype":"venue"
},
  "geometry": {"coordinates":[5.631051,51.934353],"type":"Point"}
}