{
  "type": "Feature",
  "properties": {
    "addr:full":"Maastrichtsewg 18A S Hertogenbosch Noord-Brabant 5215 AB",
    "addr:housenumber":"18a",
    "addr:postcode":"5215 ab",
    "addr:street":"Maastrichtsewg;S Hertogenbosch",
    "iso:country":"NL",
    "sg:address":"Maastrichtsewg 18A",
    "sg:city":"S Hertogenbosch",
    "sg:orig_category":"Beeldende Kunstenaars",
    "sg:phone":"+31 6 53660386",
    "sg:postcode":"5215 AB",
    "sg:province":"Noord-Brabant",
    "wof:name":"Spierings",
    "wof:placetype":"venue"
},
  "geometry": {"coordinates":[5.318596,51.688602],"type":"Point"}
}