{
  "type": "Feature",
  "properties": {
    "iso:country":"NL",
    "sg:address":"Galvanistraat 126",
    "sg:city":"Rotterdam",
    "sg:orig_category":"Farmaceutische Producten Gh",
    "sg:phone":"+31 10 420 9155",
    "sg:postcode":"3029 AD",
    "sg:province":"South Holland",
    "wof:name":"Van Der Laan Mediscore",
    "wof:placetype":"venue"
},
  "geometry": {"coordinates":[4.428868,51.911018],"type":"Point"}
}