{
  "type": "Feature",
  "properties": {
    "addr:full":"Schiedamsewg 53 Schiedam Zuid-Holland 3121 JE",
    "addr:housenumber":"53",
    "addr:postcode":"3121 je",
    "addr:street":"Schiedamsewg",
    "iso:country":"NL",
    "sg:address":"Schiedamsewg 53",
    "sg:city":"Schiedam",
    "sg:orig_category":"Behangers",
    "sg:phone":"+31 10 471 7505",
    "sg:postcode":"3121 JE",
    "sg:province":"Zuid-Holland",
    "wof:name":"Boelhouwers Schiedam Vof, A",
    "wof:placetype":"venue"
},
  "geometry": {"coordinates":[4.378801,51.934124],"type":"Point"}
}