{
  "type": "Feature",
  "properties": {
    "addr:full":"Tweemolentjeskd 18 Delft Zuid-Holland 2612 XW",
    "addr:housenumber":"18",
    "addr:postcode":"2612 xw",
    "addr:street":"Tweemolentjeskd",
    "iso:country":"NL",
    "sg:address":"Tweemolentjeskd 18",
    "sg:city":"Delft",
    "sg:orig_category":"Kappers",
    "sg:phone":"+31 15 212 5440",
    "sg:postcode":"2612 XW",
    "sg:province":"Zuid-Holland",
    "wof:name":"Knipsels",
    "wof:placetype":"venue"
},
  "geometry": {"coordinates":[4.361891,52.018776],"type":"Point"}
}