{
  "type": "Feature",
  "properties": {
    "addr:full":"Nyverheidswg 47 Zeewolde Flevoland 3899 AE",
    "addr:housenumber":"47",
    "addr:postcode":"3899 ae",
    "addr:street":"Nyverheidswg;Flevoland",
    "iso:country":"NL",
    "sg:address":"Nyverheidswg 47",
    "sg:city":"Zeewolde",
    "sg:orig_category":"Verhuur",
    "sg:phone":"+31 36 521 9900",
    "sg:postcode":"3899 AE",
    "sg:province":"Flevoland",
    "wof:name":"Holland Bv",
    "wof:placetype":"venue"
},
  "geometry": {"coordinates":[5.503059,52.357849],"type":"Point"}
}