{
  "type": "Feature",
  "properties": {
    "addr:full":"Oosterwg 77 Haren Gn Groningen 9751 PC",
    "addr:housenumber":"77",
    "addr:postcode":"9751 pc",
    "addr:street":"Oosterwg",
    "iso:country":"NL",
    "sg:address":"Oosterwg 77",
    "sg:city":"Haren Gn",
    "sg:orig_category":"Psychotherapeuten",
    "sg:phone":"+31 50 549 1240",
    "sg:postcode":"9751 PC",
    "sg:province":"Groningen",
    "wof:name":"Wolff, J J",
    "wof:placetype":"venue"
},
  "geometry": {"coordinates":[6.611278,53.177433],"type":"Point"}
}