{
  "type": "Feature",
  "properties": {
    "addr:full":"L Majoorln 48 Bussum North Holland 1401 RP",
    "addr:housenumber":"48",
    "addr:postcode":"1401 rp",
    "iso:country":"NL",
    "sg:address":"L Majoorln 48",
    "sg:city":"Bussum",
    "sg:orig_category":"Verpakkingen En Verpakkingsmaterialen",
    "sg:phone":"+31 35 691 6790",
    "sg:postcode":"1401 RP",
    "sg:province":"North Holland",
    "wof:name":"Ippel",
    "wof:placetype":"venue"
},
  "geometry": {"coordinates":[5.162605,52.276829],"type":"Point"}
}