{
  "type": "Feature",
  "properties": {
    "addr:full":"Ryksstrwg 284 Haren Gn Groningen 9752 CL",
    "addr:housenumber":"284",
    "addr:postcode":"9752",
    "iso:country":"NL",
    "sg:address":"Ryksstrwg 284",
    "sg:city":"Haren Gn",
    "sg:orig_category":"Scholen Voor Basisonderwijs",
    "sg:phone":"+31 50 534 9569",
    "sg:postcode":"9752 CL",
    "sg:province":"Groningen",
    "wof:name":"Visio Noord, Onderwijsinst",
    "wof:placetype":"venue"
},
  "geometry": {"coordinates":[6.60632,53.170658],"type":"Point"}
}