{
  "type": "Feature",
  "properties": {
    "iso:country":"NL",
    "sg:address":"Anton Brucknersingel 16",
    "sg:city":"Waalwijk",
    "sg:orig_category":"Boekhouders",
    "sg:phone":"+31 416 335 894",
    "sg:postcode":"5144 HC",
    "sg:province":"Noord-Brabant",
    "wof:name":"S. Mateijsen Vof",
    "wof:placetype":"venue"
},
  "geometry": {"coordinates":[5.060657,51.681728],"type":"Point"}
}