{
  "type": "Feature",
  "properties": {
    "iso:country":"NL",
    "sg:address":"Ringbaan N 101",
    "sg:city":"Tilburg",
    "sg:orig_category":"Accountants - Administratie- Consulenten En -Kantoren",
    "sg:phone":"+31 13 536 4350",
    "sg:postcode":"5046 AA",
    "sg:province":"Noord-Brabant",
    "wof:name":"Nbc/Oprins,Jansen & Partn Bv",
    "wof:placetype":"venue"
},
  "geometry": {"coordinates":[5.086838,51.576172],"type":"Point"}
}