{
  "type": "Feature",
  "properties": {
    "addr:full":"Bellstr 4B-D Sneek Friesland 8606 JH",
    "addr:housenumber":"4b-d",
    "addr:postcode":"8606 jh",
    "addr:street":"Bellstr",
    "iso:country":"NL",
    "sg:address":"Bellstr 4B-D",
    "sg:city":"Sneek",
    "sg:orig_category":"Jachthavens - Jachtwerven",
    "sg:phone":"+31 515 462 433",
    "sg:postcode":"8606 JH",
    "sg:province":"Friesland",
    "sg:website":"http://www.jachtbouwsulver.nl",
    "wof:name":"Sulver Jachtbouw Bv",
    "wof:placetype":"venue"
},
  "geometry": {"coordinates":[5.66197,53.033459],"type":"Point"}
}