{
  "type": "Feature",
  "properties": {
    "addr:full":"Engelandlaan 395 Haarlem North Holland 2034 PS",
    "addr:housenumber":"395",
    "addr:postcode":"2034 ps",
    "addr:street":"Engelandlaan",
    "iso:country":"NL",
    "sg:address":"Engelandlaan 395",
    "sg:city":"Haarlem",
    "sg:orig_category":"Loodgieterswerk, Verwarming And Sanitaire Installaties",
    "sg:phone":"+31 23 533 8023",
    "sg:postcode":"2034 PS",
    "sg:province":"North Holland",
    "wof:name":"Hooglugt Klussenbus Bv",
    "wof:placetype":"venue"
},
  "geometry": {"coordinates":[4.644347,52.356449],"type":"Point"}
}