{
  "type": "Feature",
  "properties": {
    "addr:full":"Arena Boulev 72 Amsterdam Zuidoost Noord-Holland 1101 DJ",
    "addr:housenumber":"72",
    "addr:postcode":"zuidoost;1101 dj",
    "addr:street":"Boulev",
    "iso:country":"NL",
    "sg:address":"Arena Boulev 72",
    "sg:city":"Amsterdam Zuidoost",
    "sg:orig_category":"Meubelen",
    "sg:phone":"+31 20 365 9036",
    "sg:postcode":"1101 DJ",
    "sg:province":"Noord-Holland",
    "wof:name":"Leef Bv",
    "wof:placetype":"venue"
},
  "geometry": {"coordinates":[4.941983,52.312881],"type":"Point"}
}