{
  "type": "Feature",
  "properties": {
    "addr:full":"Sportlaan 1 Voorhout Zuid-Holland 2215 NA",
    "addr:housenumber":"1",
    "addr:postcode":"2215 na",
    "addr:street":"Sportlaan",
    "iso:country":"NL",
    "sg:address":"Sportlaan 1",
    "sg:city":"Voorhout",
    "sg:orig_category":"Kinderopvang",
    "sg:phone":"+31 252 215 585",
    "sg:postcode":"2215 NA",
    "sg:province":"Zuid-Holland",
    "wof:name":"Speelbrug Bso, De",
    "wof:placetype":"venue"
},
  "geometry": {"coordinates":[4.478508,52.217072],"type":"Point"}
}