{
  "type": "Feature",
  "properties": {
    "addr:full":"Korte Hoogstraat 20 Vlaardingen South Holland 3131 BK",
    "addr:housenumber":"20",
    "addr:postcode":"3131 bk",
    "addr:street":"Korte Hoogstraat",
    "iso:country":"NL",
    "sg:address":"Korte Hoogstraat 20",
    "sg:city":"Vlaardingen",
    "sg:orig_category":"Meubelzaken, Woning- And Keukeninrichting",
    "sg:phone":"+31 10 434 5685",
    "sg:postcode":"3131 BK",
    "sg:province":"South Holland",
    "wof:name":"Schnitzler Woonkomfort",
    "wof:placetype":"venue"
},
  "geometry": {"coordinates":[4.342471,51.910912],"type":"Point"}
}