{
  "type": "Feature",
  "properties": {
    "addr:full":"Burg Gielenstr 20 Grubbenvorst Limburg 5971 VP",
    "addr:housenumber":"20",
    "addr:postcode":"5971 vp",
    "addr:street":"Burg",
    "iso:country":"NL",
    "sg:address":"Burg Gielenstr 20",
    "sg:city":"Grubbenvorst",
    "sg:orig_category":"Plafonds",
    "sg:phone":"+31 77 366 1698",
    "sg:postcode":"5971 VP",
    "sg:province":"Limburg",
    "wof:name":"Thijssen",
    "wof:placetype":"venue"
},
  "geometry": {"coordinates":[6.144034,51.41861],"type":"Point"}
}