{
  "type": "Feature",
  "properties": {
    "addr:full":"Mauvestr 8 Arnhem Gelderland 6813 JL",
    "addr:housenumber":"8",
    "addr:postcode":"6813 jl",
    "addr:street":"Mauvestr",
    "iso:country":"NL",
    "sg:address":"Mauvestr 8",
    "sg:city":"Arnhem",
    "sg:orig_category":"Adviesbureaus Bouwkunde",
    "sg:phone":"+31 26 443 5632",
    "sg:postcode":"6813 JL",
    "sg:province":"Gelderland",
    "wof:name":"Roelofs",
    "wof:placetype":"venue"
},
  "geometry": {"coordinates":[5.883151,51.995991],"type":"Point"}
}