{
  "type": "Feature",
  "properties": {
    "addr:full":"Geesterduin 64 Castricum Noord-Holland 1902 EL",
    "addr:housenumber":"64;1902",
    "addr:postcode":"el",
    "addr:street":"Geesterduin",
    "iso:country":"NL",
    "sg:address":"Geesterduin 64",
    "sg:city":"Castricum",
    "sg:orig_category":"Huishoudapparatuur, Televisies And Radio'S",
    "sg:phone":"+31 251 671 480",
    "sg:postcode":"1902 EL",
    "sg:province":"Noord-Holland",
    "wof:name":"Homeparts Shop",
    "wof:placetype":"venue"
},
  "geometry": {"coordinates":[4.673034,52.549515],"type":"Point"}
}