{
  "type": "Feature",
  "properties": {
    "addr:full":"Schwartzenberglaan 3 Broeksterwoude Provincie Friesland 9108 AL",
    "addr:housenumber":"3",
    "addr:postcode":"9108",
    "addr:street":"Schwartzenberglaan;Provincie Friesland",
    "iso:country":"NL",
    "sg:address":"Schwartzenberglaan 3",
    "sg:city":"Broeksterwoude",
    "sg:orig_category":"Verzekeringen",
    "sg:phone":"+31 511 421 529",
    "sg:postcode":"9108 AL",
    "sg:province":"Provincie Friesland",
    "wof:name":"H. Loonstra-Dijkstra",
    "wof:placetype":"venue"
},
  "geometry": {"coordinates":[5.980234,53.27198],"type":"Point"}
}