{
  "type": "Feature",
  "properties": {
    "iso:country":"NL",
    "sg:address":"Schwartzenberglaan 3",
    "sg:city":"Broeksterwoude",
    "sg:orig_category":"Verzekeringen",
    "sg:phone":"+31 511 421 529",
    "sg:postcode":"9108 AL",
    "sg:province":"Provincie Friesland",
    "wof:name":"H. Loonstra-Dijkstra",
    "wof:placetype":"venue"
},
  "geometry": {"coordinates":[5.980234,53.27198],"type":"Point"}
}