{
  "type": "Feature",
  "properties": {
    "addr:full":"Koopmanspln 1 Assen Drenthe 9401 EL",
    "addr:housenumber":"1",
    "addr:postcode":"9401 el",
    "addr:street":"Koopmanspln",
    "iso:country":"NL",
    "sg:address":"Koopmanspln 1",
    "sg:city":"Assen",
    "sg:orig_category":"Warenhuizen",
    "sg:phone":"+31 592 317 055",
    "sg:postcode":"9401 EL",
    "sg:province":"Drenthe",
    "wof:name":"Hema",
    "wof:placetype":"venue"
},
  "geometry": {"coordinates":[6.5598487854,52.9950408936],"type":"Point"}
}