{
  "type": "Feature",
  "properties": {
    "addr:full":"Koningin Emmastraat 29 Kaatsheuvel Noord-Brabant 5171 GS",
    "addr:housenumber":"29",
    "addr:postcode":"5171 gs",
    "addr:street":"Koningin Emmastraat",
    "iso:country":"NL",
    "sg:address":"Koningin Emmastraat 29",
    "sg:city":"Kaatsheuvel",
    "sg:orig_category":"Schoenen Fab",
    "sg:phone":"+31 416 275 207",
    "sg:postcode":"5171 GS",
    "sg:province":"Noord-Brabant",
    "wof:name":"Jure (Van Riel)",
    "wof:placetype":"venue"
},
  "geometry": {"coordinates":[5.041743,51.658527],"type":"Point"}
}