{
  "type": "Feature",
  "properties": {
    "iso:country":"NL",
    "sg:address":"Hazelaarstr 40",
    "sg:city":"Breda",
    "sg:orig_category":"Glazenwasserijen",
    "sg:phone":"+31 6 29556516",
    "sg:postcode":"4814 BD",
    "sg:province":"North Brabant",
    "wof:name":"Goorbergh, Remon Van De",
    "wof:placetype":"venue"
},
  "geometry": {"coordinates":[4.760595,51.588112],"type":"Point"}
}