{
  "type": "Feature",
  "properties": {
    "addr:full":"Schildmeer 35 Zaandam North Holland 1509 JL",
    "addr:housenumber":"35",
    "addr:postcode":"1509 jl",
    "addr:street":"Schildmeer",
    "iso:country":"NL",
    "sg:address":"Schildmeer 35",
    "sg:city":"Zaandam",
    "sg:orig_category":"Bedrijfsopleidingen",
    "sg:phone":"+31 75 615 6589",
    "sg:postcode":"1509 JL",
    "sg:province":"North Holland",
    "wof:name":"Leap Frog Communications",
    "wof:placetype":"venue"
},
  "geometry": {"coordinates":[4.841559,52.467861],"type":"Point"}
}