{
  "type": "Feature",
  "properties": {
    "addr:full":"Stetwg 41/A Castricum Noord-Holland 1901 JD",
    "addr:housenumber":"41 / a",
    "addr:postcode":"1901 jd",
    "addr:street":"Stetwg",
    "iso:country":"NL",
    "sg:address":"Stetwg 41/A",
    "sg:city":"Castricum",
    "sg:orig_category":"Biljartzalen",
    "sg:phone":"+31 251 658 384",
    "sg:postcode":"1901 JD",
    "sg:province":"Noord-Holland",
    "wof:name":"Biljart En Bridge Centrum, Sticht",
    "wof:placetype":"venue"
},
  "geometry": {"coordinates":[4.663007,52.559052],"type":"Point"}
}