{
  "type": "Feature",
  "properties": {
    "addr:full":"Lakerveld 49 Lexmond Zuid-Holland 4128 LE",
    "addr:housenumber":"49",
    "addr:postcode":"4128 le",
    "addr:street":"Lakerveld",
    "iso:country":"NL",
    "sg:address":"Lakerveld 49",
    "sg:city":"Lexmond",
    "sg:orig_category":"Marketingbureaus",
    "sg:phone":"+31 347 341 629",
    "sg:postcode":"4128 LE",
    "sg:province":"Zuid-Holland",
    "wof:name":"A & W",
    "wof:placetype":"venue"
},
  "geometry": {"coordinates":[5.025091,51.951321],"type":"Point"}
}