{
  "type": "Feature",
  "properties": {
    "iso:country":"NL",
    "sg:address":"Oosterdwarsstraat 18",
    "sg:city":"Leiden",
    "sg:orig_category":"Wegen And Sportterreinen",
    "sg:phone":"+31 71 522 3730",
    "sg:postcode":"2315 LS",
    "sg:province":"South Holland",
    "wof:name":"Grond- En Straatwerk Blankestein",
    "wof:placetype":"venue"
},
  "geometry": {"coordinates":[4.5065097809,52.1568450928],"type":"Point"}
}