{
  "type": "Feature",
  "properties": {
    "iso:country":"NL",
    "sg:address":"I Kooistrawg 50",
    "sg:city":"Apeldoorn",
    "sg:orig_category":"Adviesbureaus Bedrijfsorganisatie",
    "sg:phone":"+31 55 578 5285",
    "sg:postcode":"7311 GZ",
    "sg:province":"Gelderland",
    "sg:website":"http://www.training-coaching.nl",
    "wof:name":"I & O Balans",
    "wof:placetype":"venue"
},
  "geometry": {"coordinates":[5.96566,52.216518],"type":"Point"}
}