{
  "type": "Feature",
  "properties": {
    "addr:full":"Lagebeldsweg 37 Almelo NL.08 7607 WE",
    "addr:housenumber":"37;nl.08",
    "addr:postcode":"7607 we",
    "addr:street":"Lagebeldsweg",
    "iso:country":"NL",
    "sg:address":"Lagebeldsweg 37",
    "sg:city":"Almelo",
    "sg:orig_category":"Huishoudelijk Textiel Fab",
    "sg:phone":"+31 546 821 401",
    "sg:postcode":"7607 WE",
    "sg:province":"NL.08",
    "wof:name":"Hendrik Wanschers",
    "wof:placetype":"venue"
},
  "geometry": {"coordinates":[6.667292,52.361012],"type":"Point"}
}