{
  "type": "Feature",
  "properties": {
    "iso:country":"NL",
    "sg:address":"Antonie Van Der Kolkstr 34",
    "sg:city":"Eethen",
    "sg:orig_category":"Warenhuizen",
    "sg:phone":"+31 416 351 475",
    "sg:postcode":"4266 EP",
    "sg:province":"Noord-Brabant",
    "wof:name":"Kleinwarenhuis N. Van Den Berg",
    "wof:placetype":"venue"
},
  "geometry": {"coordinates":[5.0510411263,51.7328491211],"type":"Point"}
}