{
  "type": "Feature",
  "properties": {
    "addr:full":"Menneweg 9 Sassenheim Zuid-Holland 2171 JA",
    "addr:housenumber":"9",
    "addr:postcode":"2171 ja",
    "addr:street":"Menneweg",
    "iso:country":"NL",
    "sg:address":"Menneweg 9",
    "sg:city":"Sassenheim",
    "sg:orig_category":"Verzekeringen",
    "sg:phone":"+31 252 210 536",
    "sg:postcode":"2171 JA",
    "sg:province":"Zuid-Holland",
    "wof:name":"Mr. R.A.F. Van Der Kraan",
    "wof:placetype":"venue"
},
  "geometry": {"coordinates":[4.523994,52.223091],"type":"Point"}
}