{
  "type": "Feature",
  "properties": {
    "addr:full":"Getymolen 6 Maassluis South Holland 3146 CA",
    "addr:housenumber":"6",
    "addr:postcode":"3146 ca",
    "addr:street":"Getymolen",
    "iso:country":"NL",
    "sg:address":"Getymolen 6",
    "sg:city":"Maassluis",
    "sg:orig_category":"Verzekeringen - Verzekeringskantoren",
    "sg:phone":"+31 10 592 6368",
    "sg:postcode":"3146 CA",
    "sg:province":"South Holland",
    "wof:name":"Molen",
    "wof:placetype":"venue"
},
  "geometry": {"coordinates":[4.228828,51.938839],"type":"Point"}
}