{
  "type": "Feature",
  "properties": {
    "addr:full":"Heymansln 49 Groningen Groningen 9714 GJ",
    "addr:housenumber":"49",
    "addr:postcode":"9714 gj",
    "addr:street":"Heymansln",
    "iso:country":"NL",
    "sg:address":"Heymansln 49",
    "sg:city":"Groningen",
    "sg:orig_category":"Vertalers",
    "sg:phone":"+31 50 577 2393",
    "sg:postcode":"9714 GJ",
    "sg:province":"Groningen",
    "wof:name":"Thuss, A",
    "wof:placetype":"venue"
},
  "geometry": {"coordinates":[6.571465,53.231075],"type":"Point"}
}