{
  "type": "Feature",
  "properties": {
    "iso:country":"NL",
    "sg:address":"Vossenkamp 14",
    "sg:city":"Driebergen Rysenb",
    "sg:orig_category":"Adviesbureaus Personeel",
    "sg:phone":"+31 343 521 644",
    "sg:postcode":"3972 VJ",
    "sg:province":"Utrecht",
    "sg:website":"http://www.nedconsult.nl",
    "wof:name":"Nedconsult",
    "wof:placetype":"venue"
},
  "geometry": {"coordinates":[5.275556,52.048573],"type":"Point"}
}