{
  "type": "Feature",
  "properties": {
    "addr:full":"Het Gangwerk 37 Hoorn Nh Noord-Holland 1622 HB",
    "addr:housenumber":"37",
    "addr:postcode":"1622 hb",
    "addr:street":"Het Gangwerk",
    "iso:country":"NL",
    "sg:address":"Het Gangwerk 37",
    "sg:city":"Hoorn Nh",
    "sg:orig_category":"Adviesbureaus Economie",
    "sg:phone":"+31 229 237 057",
    "sg:postcode":"1622 HB",
    "sg:province":"Noord-Holland",
    "wof:name":"Beljij",
    "wof:placetype":"venue"
},
  "geometry": {"coordinates":[5.03126,52.639229],"type":"Point"}
}