{
  "type": "Feature",
  "properties": {
    "iso:country":"NL",
    "sg:address":"Erasmuspln 2",
    "sg:city":"Vlaardingen",
    "sg:orig_category":"Kinderopvang",
    "sg:phone":"+31 10 434 1724",
    "sg:postcode":"3132 EL",
    "sg:province":"Zuid-Holland",
    "sg:website":"http://www.skv.nl",
    "wof:name":"Bibelebons",
    "wof:placetype":"venue"
},
  "geometry": {"coordinates":[4.31594,51.910629],"type":"Point"}
}