{
  "type": "Feature",
  "properties": {
    "iso:country":"NL",
    "sg:address":"Drie Decembersingel 42",
    "sg:city":"Venlo",
    "sg:orig_category":"Loodgieterswerk, Verwarming And Sanitaire Installaties",
    "sg:phone":"+31 77 396 8300",
    "sg:postcode":"5921 AC",
    "sg:province":"Limburg",
    "wof:name":"Axis Installatiegroep Bv",
    "wof:placetype":"venue"
},
  "geometry": {"coordinates":[6.13766,51.370323],"type":"Point"}
}