{
  "type": "Feature",
  "properties": {
    "addr:full":"De Merret 10 St Anthonis North Brabant 5845 DA",
    "addr:housenumber":"10",
    "addr:postcode":"5845 da",
    "addr:street":"De Merret",
    "iso:country":"NL",
    "sg:address":"De Merret 10",
    "sg:city":"St Anthonis",
    "sg:classifiers":[
        {
            "category":"Food & Beverages",
            "subcategory":"Fruits & Vegetables",
            "type":"Retail Goods"
        }
    ],
    "sg:phone":"+31 485 383 200",
    "sg:postcode":"5845 DA",
    "sg:province":"North Brabant",
    "sg:tags":[
        "en",
        "groenten"
    ],
    "wof:name":"Dam, J Van",
    "wof:placetype":"venue"
},
  "geometry": {"coordinates":[5.88176,51.627167],"type":"Point"}
}