{
  "type": "Feature",
  "properties": {
    "addr:full":"Julianastr 27 Gronsveld Limburg 6247 CD",
    "addr:housenumber":"27",
    "addr:postcode":"6247 cd",
    "addr:street":"Julianastr",
    "iso:country":"NL",
    "sg:address":"Julianastr 27",
    "sg:city":"Gronsveld",
    "sg:orig_category":"Kappers",
    "sg:phone":"+31 43 408 5890",
    "sg:postcode":"6247 CD",
    "sg:province":"Limburg",
    "wof:name":"Maurice",
    "wof:placetype":"venue"
},
  "geometry": {"coordinates":[5.729701,50.807095],"type":"Point"}
}