{
  "type": "Feature",
  "properties": {
    "iso:country":"NL",
    "sg:address":"Hoofdstr 118",
    "sg:city":"Epe",
    "sg:orig_category":"Warenhuizen",
    "sg:phone":"+31 578 621 548",
    "sg:postcode":"8162 AN",
    "sg:province":"Gelderland",
    "wof:name":"Action",
    "wof:placetype":"venue"
},
  "geometry": {"coordinates":[5.9836649895,52.3463821411],"type":"Point"}
}