{
  "type": "Feature",
  "properties": {
    "addr:full":"Ywg 1670 Nieuw Vennep North Holland 2151 MN",
    "addr:housenumber":"1670",
    "addr:postcode":"2151 mn",
    "addr:street":"Nieuw Vennep North",
    "iso:country":"NL",
    "sg:address":"Ywg 1670",
    "sg:city":"Nieuw Vennep",
    "sg:orig_category":"Open Haard Houtblokken",
    "sg:phone":"+31 252 674 892",
    "sg:postcode":"2151 MN",
    "sg:province":"North Holland",
    "wof:name":"Menco",
    "wof:placetype":"venue"
},
  "geometry": {"coordinates":[4.631055,52.264744],"type":"Point"}
}