{
  "type": "Feature",
  "properties": {
    "iso:country":"NL",
    "sg:address":"L Heynricsstr 26G",
    "sg:city":"Amersfoort",
    "sg:orig_category":"Beeldende Kunstenaars",
    "sg:phone":"+31 33 465 5734",
    "sg:postcode":"3817 ES",
    "sg:province":"Utrecht",
    "wof:name":"Oijen, Bart Van",
    "wof:placetype":"venue"
},
  "geometry": {"coordinates":[5.397399,52.14566],"type":"Point"}
}