{
  "type": "Feature",
  "properties": {
    "addr:full":"Henri Dunantweg 133 Lochem Gelderland 7242 HH",
    "addr:housenumber":"133",
    "addr:postcode":"7242 hh",
    "addr:street":"Henri Dunantweg;Gelderland",
    "iso:country":"NL",
    "sg:address":"Henri Dunantweg 133",
    "sg:city":"Lochem",
    "sg:orig_category":"Modevakscholen",
    "sg:phone":"+31 573 254 376",
    "sg:postcode":"7242 HH",
    "sg:province":"Gelderland",
    "wof:name":"Ensaid",
    "wof:placetype":"venue"
},
  "geometry": {"coordinates":[6.40347,52.153709],"type":"Point"}
}