{
  "type": "Feature",
  "properties": {
    "iso:country":"NL",
    "sg:address":"Amersfoortseweg 241",
    "sg:city":"Uddel",
    "sg:orig_category":"Diverse Consumentenartikelen Gh",
    "sg:phone":"+31 577 456 155",
    "sg:postcode":"3888 NM",
    "sg:province":"Gelderland",
    "wof:name":"Trade Unlimited Vof",
    "wof:placetype":"venue"
},
  "geometry": {"coordinates":[5.791356,52.221432],"type":"Point"}
}