{
  "type": "Feature",
  "properties": {
    "iso:country":"NL",
    "sg:address":"Sint Cathrijnestraat 4",
    "sg:city":"Zaandam",
    "sg:orig_category":"Kappers",
    "sg:phone":"+31 75 617 7383",
    "sg:postcode":"1501 NN",
    "sg:province":"Noord-Holland",
    "wof:name":"Kapsalon Monique",
    "wof:placetype":"venue"
},
  "geometry": {"coordinates":[4.8303451538,52.438659668],"type":"Point"}
}