{
  "type": "Feature",
  "properties": {
    "iso:country":"NL",
    "sg:address":"Burg V Erpstr 58",
    "sg:city":"Berghem",
    "sg:orig_category":"Fitnesscentra",
    "sg:phone":"+31 412 401 081",
    "sg:postcode":"5351 AX",
    "sg:province":"Noord-Brabant",
    "wof:name":"Do-It",
    "wof:placetype":"venue"
},
  "geometry": {"coordinates":[5.565603,51.774323],"type":"Point"}
}