{
  "type": "Feature",
  "properties": {
    "addr:full":"Burg V Erpstr 58 Berghem Noord-Brabant 5351 AX",
    "addr:housenumber":"58",
    "addr:postcode":"5351 ax",
    "addr:street":"Burg V Erpstr",
    "iso:country":"NL",
    "sg:address":"Burg V Erpstr 58",
    "sg:city":"Berghem",
    "sg:orig_category":"Fitnesscentra",
    "sg:phone":"+31 412 401 081",
    "sg:postcode":"5351 AX",
    "sg:province":"Noord-Brabant",
    "wof:name":"Do-It",
    "wof:placetype":"venue"
},
  "geometry": {"coordinates":[5.565603,51.774323],"type":"Point"}
}