{
  "type": "Feature",
  "properties": {
    "iso:country":"NL",
    "sg:address":"St Martinusstr 74",
    "sg:city":"Venlo",
    "sg:orig_category":"Grafisch Ontwerpers",
    "sg:phone":"+31 77 351 5124",
    "sg:postcode":"5911 CK",
    "sg:province":"Limburg",
    "wof:name":"Prinsen & Co Grafisch Ontwerp",
    "wof:placetype":"venue"
},
  "geometry": {"coordinates":[6.173741,51.372196],"type":"Point"}
}