{
  "type": "Feature",
  "properties": {
    "iso:country":"NL",
    "sg:address":"Dorpsstraat 92",
    "sg:city":"Mierlo",
    "sg:orig_category":"Meubelzaken, Woning- And Keukeninrichting",
    "sg:phone":"+31 492 661 819",
    "sg:postcode":"5731 JK",
    "sg:province":"Noord-Brabant",
    "wof:name":"Branten Woninginrichting",
    "wof:placetype":"venue"
},
  "geometry": {"coordinates":[5.612199,51.443077],"type":"Point"}
}