{
  "type": "Feature",
  "properties": {
    "addr:full":"Rietmolenweg 20 Haaksbergen Overijssel 7482 NX",
    "addr:housenumber":"20",
    "addr:postcode":"7482 nx",
    "addr:street":"Rietmolenweg",
    "iso:country":"NL",
    "sg:address":"Rietmolenweg 20",
    "sg:city":"Haaksbergen",
    "sg:orig_category":"Hout Gh",
    "sg:phone":"+31 74 357 5822",
    "sg:postcode":"7482 NX",
    "sg:province":"Overijssel",
    "wof:name":"Houthal De Perik Bv",
    "wof:placetype":"venue"
},
  "geometry": {"coordinates":[6.698825,52.170998],"type":"Point"}
}