{
  "type": "Feature",
  "properties": {
    "addr:full":"Raadhuisstr 45 Blyham Groningen 9697 PP",
    "addr:housenumber":"45",
    "addr:postcode":"9697 pp",
    "addr:street":"Raadhuisstr",
    "iso:country":"NL",
    "sg:address":"Raadhuisstr 45",
    "sg:city":"Blyham",
    "sg:orig_category":"Arbo- En Bedrijfsgezondheids- Diensten",
    "sg:phone":"+31 597 562 418",
    "sg:postcode":"9697 PP",
    "sg:province":"Groningen",
    "sg:website":"http://www.klatetas.nl",
    "wof:name":"Klatetas",
    "wof:placetype":"venue"
},
  "geometry": {"coordinates":[7.082377,53.106037],"type":"Point"}
}