{
  "type": "Feature",
  "properties": {
    "iso:country":"NL",
    "sg:address":"Ranonkelstr 4C",
    "sg:city":"Rotterdam",
    "sg:orig_category":"Autorijscholen",
    "sg:phone":"+31 6 24218843",
    "sg:postcode":"3073 ES",
    "sg:province":"Zuid-Holland",
    "wof:name":"Osman",
    "wof:placetype":"venue"
},
  "geometry": {"coordinates":[4.500641,51.895489],"type":"Point"}
}