{
  "type": "Feature",
  "properties": {
    "addr:full":"Leeuwerikstr 3 Middelburg Zeeland 4335 CH",
    "addr:housenumber":"3",
    "addr:postcode":"4335",
    "addr:street":"Leeuwerikstr",
    "iso:country":"NL",
    "sg:address":"Leeuwerikstr 3",
    "sg:city":"Middelburg",
    "sg:orig_category":"Scholen Voor Basisonderwijs",
    "sg:phone":"+31 118 626 325",
    "sg:postcode":"4335 CH",
    "sg:province":"Zeeland",
    "wof:name":"Herman Faukeliusschool Reform",
    "wof:placetype":"venue"
},
  "geometry": {"coordinates":[3.600097,51.494022],"type":"Point"}
}