{
  "type": "Feature",
  "properties": {
    "iso:country":"NL",
    "sg:address":"Vliegveldstraat 12",
    "sg:city":"Hengelo Ov",
    "sg:orig_category":"Goederenvervoer Over De Weg",
    "sg:phone":"+31 74 277 2210",
    "sg:postcode":"7558 PT",
    "sg:province":"Overijssel",
    "wof:name":"Transportbedrijf Hofste Bv",
    "wof:placetype":"venue"
},
  "geometry": {"coordinates":[6.849513,52.287151],"type":"Point"}
}