{
  "type": "Feature",
  "properties": {
    "addr:full":"Pleinweg 216 Rotterdam Zuid-Holland 3083 EW",
    "addr:housenumber":"216",
    "addr:postcode":"3083 ew",
    "addr:street":"Pleinweg",
    "iso:country":"NL",
    "sg:address":"Pleinweg 216",
    "sg:city":"Rotterdam",
    "sg:orig_category":"Kinderopvang Behalve Thuis",
    "sg:phone":"+31 10 290 6500",
    "sg:postcode":"3083 EW",
    "sg:province":"Zuid-Holland",
    "wof:name":"Stichting Kinderopvang Charlois",
    "wof:placetype":"venue"
},
  "geometry": {"coordinates":[4.477818,51.891453],"type":"Point"}
}