{
  "type": "Feature",
  "properties": {
    "addr:full":"A Petershof 31 Amsterdam Noord-Holland 1065 SL",
    "addr:housenumber":"31",
    "addr:postcode":"1065 sl",
    "addr:street":"A Petershof",
    "iso:country":"NL",
    "sg:address":"A Petershof 31",
    "sg:city":"Amsterdam",
    "sg:orig_category":"Sportverenigingen En Ontspannings- Verenigingen",
    "sg:phone":"+31 20 669 3921",
    "sg:postcode":"1065 SL",
    "sg:province":"Noord-Holland",
    "wof:name":"Easv Sjoelver",
    "wof:placetype":"venue"
},
  "geometry": {"coordinates":[4.830517,52.352661],"type":"Point"}
}