{
  "type": "Feature",
  "properties": {
    "addr:full":"St Maartensln 26 Maastricht Limburg 6221 AX",
    "addr:housenumber":"26",
    "addr:postcode":"6221 ax",
    "iso:country":"NL",
    "sg:address":"St Maartensln 26",
    "sg:city":"Maastricht",
    "sg:orig_category":"Organisatiebureaus",
    "sg:phone":"+31 43 356 1718",
    "sg:postcode":"6221 AX",
    "sg:province":"Limburg",
    "sg:website":"http://www.treat.nl",
    "wof:name":"Treat",
    "wof:placetype":"venue"
},
  "geometry": {"coordinates":[5.7016620636,50.8512840271],"type":"Point"}
}