{
  "type": "Feature",
  "properties": {
    "addr:full":"Neptunusplein 21 Amersfoort Utrecht 3814 BB",
    "addr:housenumber":"21",
    "addr:postcode":"3814 bb",
    "addr:street":"Neptunusplein",
    "iso:country":"NL",
    "sg:address":"Neptunusplein 21",
    "sg:city":"Amersfoort",
    "sg:classifiers":[
        {
            "category":"Food & Beverages",
            "subcategory":"Fruits & Vegetables",
            "type":"Retail Goods"
        }
    ],
    "sg:phone":"+31 33 472 0589",
    "sg:postcode":"3814 BB",
    "sg:province":"Utrecht",
    "sg:tags":[
        "groenten"
    ],
    "wof:name":"Groentehal De Goudreinet Bv",
    "wof:placetype":"venue"
},
  "geometry": {"coordinates":[5.399613,52.162216],"type":"Point"}
}