{
  "type": "Feature",
  "properties": {
    "addr:full":"Lagedijk 15 Helmond North Brabant 5705 BX",
    "addr:housenumber":"15",
    "addr:postcode":"5705 bx",
    "addr:street":"Lagedijk",
    "iso:country":"NL",
    "sg:address":"Lagedijk 15",
    "sg:city":"Helmond",
    "sg:classifiers":[
        {
            "category":"Fast Food",
            "type":"Food & Drink"
        }
    ],
    "sg:phone":"+31 492 553 888",
    "sg:postcode":"5705 BX",
    "sg:province":"North Brabant",
    "sg:tags":[
        "afhaal",
        "restaurant"
    ],
    "wof:name":"Bocken Frituur",
    "wof:placetype":"venue"
},
  "geometry": {"coordinates":[5.678346,51.468342],"type":"Point"}
}