{
  "type": "Feature",
  "properties": {
    "iso:country":"NL",
    "sg:address":"Reguliersgracht 31",
    "sg:city":"Amsterdam",
    "sg:classifiers":[
        {
            "category":"Travel",
            "subcategory":"Hotels & Motels",
            "type":"Entertainment"
        }
    ],
    "sg:phone":"+31 20 623 1329",
    "sg:postcode":"1017 LK",
    "sg:province":"North Holland",
    "wof:name":"Hotel 7 Bridges Bv",
    "wof:placetype":"venue"
},
  "geometry": {"coordinates":[4.896308,52.36388],"type":"Point"}
}