{
  "type": "Feature",
  "properties": {
    "iso:country":"NL",
    "sg:address":"Buizerdhorst 33",
    "sg:city":"Cuijk",
    "sg:orig_category":"Elektronische Bedrijfsinstallaties",
    "sg:phone":"+31 485 317 921",
    "sg:postcode":"5431 LX",
    "sg:province":"North Brabant",
    "wof:name":"J.E.M. Brugman",
    "wof:placetype":"venue"
},
  "geometry": {"coordinates":[5.888143,51.71323],"type":"Point"}
}