{
  "type": "Feature",
  "properties": {
    "addr:full":"Kroonsingel 128 Malden Gelderland 6581 BP",
    "addr:housenumber":"128",
    "addr:postcode":"6581 bp",
    "addr:street":"Kroonsingel;Gelderland",
    "iso:country":"NL",
    "sg:address":"Kroonsingel 128",
    "sg:city":"Malden",
    "sg:orig_category":"Artsen And Specialisten",
    "sg:phone":"+31 24 358 1485",
    "sg:postcode":"6581 BP",
    "sg:province":"Gelderland",
    "wof:name":"J. Atema",
    "wof:placetype":"venue"
},
  "geometry": {"coordinates":[5.858735,51.782604],"type":"Point"}
}