{
  "type": "Feature",
  "properties": {
    "iso:country":"NL",
    "sg:address":"Struisvaren 2",
    "sg:city":"Bergschenhoek",
    "sg:orig_category":"Artsen - Huisartsen",
    "sg:phone":"+31 10 522 5255",
    "sg:postcode":"2661 PW",
    "sg:province":"Zuid-Holland",
    "wof:name":"Huijsman, A",
    "wof:placetype":"venue"
},
  "geometry": {"coordinates":[4.503739,51.991505],"type":"Point"}
}