{
  "type": "Feature",
  "properties": {
    "iso:country":"NL",
    "sg:address":"Stationswg 1",
    "sg:city":"Appingedam",
    "sg:orig_category":"Verbouwingen",
    "sg:phone":"+31 596 620 142",
    "sg:postcode":"9901 CP",
    "sg:province":"Groningen",
    "wof:name":"Tent Vof, Erik",
    "wof:placetype":"venue"
},
  "geometry": {"coordinates":[6.857888,53.322594],"type":"Point"}
}