{
  "type": "Feature",
  "properties": {
    "addr:full":"Hellingweg 198 'S Gravenhage Zuid-Holland 2583 DX",
    "addr:housenumber":"198 '",
    "addr:postcode":"2583 dx",
    "addr:street":"Hellingweg",
    "iso:country":"NL",
    "sg:address":"Hellingweg 198",
    "sg:city":"'S Gravenhage",
    "sg:orig_category":"Technische Studies And Onderzoek",
    "sg:phone":"+31 70 306 0691",
    "sg:postcode":"2583 DX",
    "sg:province":"Zuid-Holland",
    "wof:name":"Medusa Bv",
    "wof:placetype":"venue"
},
  "geometry": {"coordinates":[4.2617,52.095238],"type":"Point"}
}