{
  "type": "Feature",
  "properties": {
    "addr:full":"Tjalkstraat 2 Nieuw Lekkerland Zuid-Holland 2957 GB",
    "addr:housenumber":"2",
    "addr:postcode":"2957 gb",
    "addr:street":"Tjalkstraat",
    "iso:country":"NL",
    "sg:address":"Tjalkstraat 2",
    "sg:city":"Nieuw Lekkerland",
    "sg:classifiers":[
        {
            "category":"Education",
            "subcategory":"Preschool",
            "type":"Public Place"
        }
    ],
    "sg:phone":"+31 184 682 818",
    "sg:postcode":"2957 GB",
    "sg:province":"Zuid-Holland",
    "sg:tags":[
        "kleuteronderwijs",
        "basis-"
    ],
    "wof:name":"Peuterspeelzaal 'T Winkeltje",
    "wof:placetype":"venue"
},
  "geometry": {"coordinates":[4.662084,51.884724],"type":"Point"}
}