{
  "type": "Feature",
  "properties": {
    "addr:full":"Postbus 397 Brunssum Limburg 6440 AJ",
    "addr:housenumber":"397",
    "addr:postcode":"6440 aj",
    "addr:street":"Postbus",
    "iso:country":"NL",
    "sg:address":"Postbus 397",
    "sg:city":"Brunssum",
    "sg:orig_category":"Peuterspeelzalen",
    "sg:phone":"+31 6 41722994",
    "sg:postcode":"6440 AJ",
    "sg:province":"Limburg",
    "wof:name":"Hummelhoek",
    "wof:placetype":"venue"
},
  "geometry": {"coordinates":[5.970233,50.943302],"type":"Point"}
}