{
  "type": "Feature",
  "properties": {
    "iso:country":"NL",
    "sg:address":"Oosthaven 52",
    "sg:city":"Gouda",
    "sg:orig_category":"Adviesbureaus Bouwkunde",
    "sg:phone":"+31 182 300 774",
    "sg:postcode":"2801 PE",
    "sg:province":"South Holland",
    "sg:website":"http://www.archibald.info",
    "wof:name":"Archibald",
    "wof:placetype":"venue"
},
  "geometry": {"coordinates":[4.713123,52.008202],"type":"Point"}
}