{
  "type": "Feature",
  "properties": {
    "addr:full":"Van Eedenstraat 18 Haarlem Noord-Holland 2012 EM",
    "addr:housenumber":"18",
    "addr:postcode":"2012 em",
    "addr:street":"Van Eedenstraat",
    "iso:country":"NL",
    "sg:address":"Van Eedenstraat 18",
    "sg:city":"Haarlem",
    "sg:orig_category":"Verzekeringen",
    "sg:phone":"+31 23 534 5023",
    "sg:postcode":"2012 EM",
    "sg:province":"Noord-Holland",
    "wof:name":"Standaert Verzekeringen",
    "wof:placetype":"venue"
},
  "geometry": {"coordinates":[4.626932,52.37542],"type":"Point"}
}