{
  "type": "Feature",
  "properties": {
    "addr:full":"Hamermolen 7 Dinteloord Noord-Brabant 4671 JG",
    "addr:housenumber":"7",
    "addr:postcode":"4671 jg",
    "addr:street":"Hamermolen",
    "iso:country":"NL",
    "sg:address":"Hamermolen 7",
    "sg:city":"Dinteloord",
    "sg:orig_category":"Public Relationbureaus",
    "sg:phone":"+31 167 522 342",
    "sg:postcode":"4671 JG",
    "sg:province":"Noord-Brabant",
    "wof:name":"Natascha De Vos",
    "wof:placetype":"venue"
},
  "geometry": {"coordinates":[4.376536,51.632515],"type":"Point"}
}