{
  "type": "Feature",
  "properties": {
    "addr:full":"Melkmarkt 10 Zwolle Overijssel 8011 MC",
    "addr:housenumber":"10",
    "addr:postcode":"8011 mc",
    "addr:street":"Melkmarkt",
    "iso:country":"NL",
    "sg:address":"Melkmarkt 10",
    "sg:city":"Zwolle",
    "sg:orig_category":"Boeken Antiquarische En Gebruikte",
    "sg:phone":"+31 38 421 4408",
    "sg:postcode":"8011 MC",
    "sg:province":"Overijssel",
    "sg:website":"http://www.deslegte.nl",
    "wof:name":"Slegte Bv, J De",
    "wof:placetype":"venue"
},
  "geometry": {"coordinates":[6.092208,52.512753],"type":"Point"}
}