{
  "type": "Feature",
  "properties": {
    "addr:full":"Schoolstraat 4 Uffelte Provincie Drenthe 7975 AC",
    "addr:housenumber":"4",
    "addr:postcode":"7975 ac",
    "addr:street":"Schoolstraat;Provincie Drenthe",
    "iso:country":"NL",
    "sg:address":"Schoolstraat 4",
    "sg:city":"Uffelte",
    "sg:classifiers":[
        {
            "category":"Education",
            "subcategory":"Preschool",
            "type":"Public Place"
        }
    ],
    "sg:phone":"+31 521 351 307",
    "sg:postcode":"7975 AC",
    "sg:province":"Provincie Drenthe",
    "sg:tags":[
        "kleuteronderwijs",
        "basis-"
    ],
    "wof:name":"Openbare Basisschool Oosterveld",
    "wof:placetype":"venue"
},
  "geometry": {"coordinates":[6.27846,52.787582],"type":"Point"}
}