{
  "type": "Feature",
  "properties": {
    "iso:country":"NL",
    "sg:address":"Kerkstraat 54",
    "sg:city":"Katwijk Zh",
    "sg:orig_category":"Boekhouders",
    "sg:phone":"+31 71 402 2300",
    "sg:postcode":"2223 AK",
    "sg:province":"South Holland",
    "wof:name":"Gibo Accountants En Adviseurs",
    "wof:placetype":"venue"
},
  "geometry": {"coordinates":[4.42222,52.196396],"type":"Point"}
}