{
  "type": "Feature",
  "properties": {
    "iso:country":"NL",
    "sg:address":"Biss Schrynenstr 16E",
    "sg:city":"Venlo",
    "sg:orig_category":"Fotoreportages",
    "sg:phone":"+31 77 351 8124",
    "sg:postcode":"5914 RZ",
    "sg:province":"Limburg",
    "wof:name":"Derckx, Hans",
    "wof:placetype":"venue"
},
  "geometry": {"coordinates":[6.176658,51.377674],"type":"Point"}
}