{
  "type": "Feature",
  "properties": {
    "addr:full":"De Beerebijt 16 Amstelveen North Holland 1181 MN",
    "addr:housenumber":"16",
    "addr:postcode":"1181 mn",
    "addr:street":"De Beerebijt",
    "iso:country":"NL",
    "sg:address":"De Beerebijt 16",
    "sg:city":"Amstelveen",
    "sg:orig_category":"Kappers",
    "sg:phone":"+31 20 641 6292",
    "sg:postcode":"1181 MN",
    "sg:province":"North Holland",
    "wof:name":"Kapsalon Eston",
    "wof:placetype":"venue"
},
  "geometry": {"coordinates":[4.8700342178,52.3101196289],"type":"Point"}
}