{
  "type": "Feature",
  "properties": {
    "addr:full":"Eekmolenweg 2 Lochem Gelderland 7241 CM",
    "addr:housenumber":"2",
    "addr:postcode":"7241 cm",
    "addr:street":"Eekmolenweg;Gelderland",
    "iso:country":"NL",
    "sg:address":"Eekmolenweg 2",
    "sg:city":"Lochem",
    "sg:orig_category":"Auto'S And Voertuigen",
    "sg:phone":"+31 573 251 480",
    "sg:postcode":"7241 CM",
    "sg:province":"Gelderland",
    "wof:name":"Autobedrijf Teger Lochem Bv",
    "wof:placetype":"venue"
},
  "geometry": {"coordinates":[6.39987,52.16407],"type":"Point"}
}