{
  "type": "Feature",
  "properties": {
    "addr:full":"Hogedijken 6 Dokkum Friesland 9101 WV",
    "addr:housenumber":"6",
    "addr:postcode":"9101 wv",
    "addr:street":"Hogedijken",
    "iso:country":"NL",
    "sg:address":"Hogedijken 6",
    "sg:city":"Dokkum",
    "sg:orig_category":"Glaszetten",
    "sg:phone":"+31 519 293 458",
    "sg:postcode":"9101 WV",
    "sg:province":"Friesland",
    "wof:name":"Schilders- En Afwerkingsbedrijf Loonstra",
    "wof:placetype":"venue"
},
  "geometry": {"coordinates":[6.011017,53.321808],"type":"Point"}
}