{
  "type": "Feature",
  "properties": {
    "addr:full":"Bremen 1 Barendrecht South Holland 2993 LJ",
    "addr:housenumber":"1",
    "addr:postcode":"2993 lj",
    "addr:street":"Bremen",
    "iso:country":"NL",
    "sg:address":"Bremen 1",
    "sg:city":"Barendrecht",
    "sg:orig_category":"Gespecialiseerde Bouw",
    "sg:phone":"+31 180 643 950",
    "sg:postcode":"2993 LJ",
    "sg:province":"South Holland",
    "wof:name":"Alprokon Aluminium Development Bv",
    "wof:placetype":"venue"
},
  "geometry": {"coordinates":[4.512032,51.853497],"type":"Point"}
}