{
  "type": "Feature",
  "properties": {
    "addr:full":"Alkmaarseweg 114 Beverwijk Noord-Holland 1941 DR",
    "addr:housenumber":"114;1941",
    "addr:postcode":"dr",
    "addr:street":"Alkmaarseweg",
    "iso:country":"NL",
    "sg:address":"Alkmaarseweg 114",
    "sg:city":"Beverwijk",
    "sg:orig_category":"Makelaars In Onroerend Goed",
    "sg:phone":"+31 251 214 840",
    "sg:postcode":"1941 DR",
    "sg:province":"Noord-Holland",
    "wof:name":"Eck",
    "wof:placetype":"venue"
},
  "geometry": {"coordinates":[4.660085,52.487972],"type":"Point"}
}