{
  "type": "Feature",
  "properties": {
    "addr:full":"2E Wormenseweg 86 Apeldoorn Gelderland 7331 VH",
    "addr:housenumber":"86",
    "addr:postcode":"7331 vh",
    "addr:street":"2E Wormenseweg;Gelderland",
    "iso:country":"NL",
    "sg:address":"2E Wormenseweg 86",
    "sg:city":"Apeldoorn",
    "sg:orig_category":"Huishoudelijk Textiel Fab",
    "sg:phone":"+31 55 533 1139",
    "sg:postcode":"7331 VH",
    "sg:province":"Gelderland",
    "wof:name":"Gordijnenatelier De Plooi",
    "wof:placetype":"venue"
},
  "geometry": {"coordinates":[5.973034,52.205612],"type":"Point"}
}