{
  "type": "Feature",
  "properties": {
    "addr:full":"Lagedijk 10 Ijsselstein Ut Utrecht 3401 RG",
    "addr:housenumber":"10",
    "addr:postcode":"3401 rg",
    "addr:street":"Lagedijk",
    "iso:country":"NL",
    "sg:address":"Lagedijk 10",
    "sg:city":"Ijsselstein Ut",
    "sg:orig_category":"Diverse Grafische Activiteiten",
    "sg:phone":"+31 30 688 8077",
    "sg:postcode":"3401 RG",
    "sg:province":"Utrecht",
    "wof:name":"Lithoma Grafisch Productieburo",
    "wof:placetype":"venue"
},
  "geometry": {"coordinates":[5.058213,52.013233],"type":"Point"}
}