{
  "type": "Feature",
  "properties": {
    "addr:full":"Nye Tikewei 10 Nyega Friesland 9217 RS",
    "addr:housenumber":"10",
    "addr:postcode":"9217 rs",
    "addr:street":"Nye Tikewei",
    "iso:country":"NL",
    "sg:address":"Nye Tikewei 10",
    "sg:city":"Nyega",
    "sg:classifiers":[
        {
            "category":"Retail",
            "subcategory":"Auto Repair",
            "type":"Services"
        }
    ],
    "sg:phone":"+31 512 371 457",
    "sg:postcode":"9217 RS",
    "sg:province":"Friesland",
    "sg:tags":[
        "garage"
    ],
    "wof:name":"Haarsma",
    "wof:placetype":"venue"
},
  "geometry": {"coordinates":[6.02533,53.14098],"type":"Point"}
}