{
  "type": "Feature",
  "properties": {
    "iso:country":"NL",
    "sg:address":"Graaf Van Lohnstraat 31",
    "sg:city":"Varsseveld",
    "sg:orig_category":"Metalen And Ertsen Gh",
    "sg:phone":"+31 315 244 221",
    "sg:postcode":"7051 CB",
    "sg:province":"Gelderland",
    "wof:name":"Barmentloo Tribunes",
    "wof:placetype":"venue"
},
  "geometry": {"coordinates":[6.452089,51.93932],"type":"Point"}
}