{
  "type": "Feature",
  "properties": {
    "iso:country":"NL",
    "sg:address":"Buurmeesterslaan 14",
    "sg:city":"Muiderberg",
    "sg:orig_category":"Loodgieterswerk, Verwarming And Sanitaire Installaties",
    "sg:phone":"+31 294 264 946",
    "sg:postcode":"1399 JL",
    "sg:province":"Noord-Holland",
    "wof:name":"Peter Slokker",
    "wof:placetype":"venue"
},
  "geometry": {"coordinates":[5.121406,52.324478],"type":"Point"}
}