{
  "type": "Feature",
  "properties": {
    "addr:full":"Molenweg 12 Oosterbeek Gelderland 6862 HP",
    "addr:housenumber":"12",
    "addr:postcode":"6862 hp",
    "addr:street":"Molenweg;Gelderland",
    "iso:country":"NL",
    "sg:address":"Molenweg 12",
    "sg:city":"Oosterbeek",
    "sg:orig_category":"Metaalwerken",
    "sg:phone":"+31 26 333 3077",
    "sg:postcode":"6862 HP",
    "sg:province":"Gelderland",
    "wof:name":"Moller Oosterbeek Bv",
    "wof:placetype":"venue"
},
  "geometry": {"coordinates":[5.849708,51.985573],"type":"Point"}
}