{
  "type": "Feature",
  "properties": {
    "addr:full":"Nilantstraat 64 Deventer Overijssel 7415 TG",
    "addr:housenumber":"64",
    "addr:postcode":"7415 tg",
    "addr:street":"Nilantstraat",
    "iso:country":"NL",
    "sg:address":"Nilantstraat 64",
    "sg:city":"Deventer",
    "sg:orig_category":"Kledingaccessoires",
    "sg:phone":"+31 570 676 009",
    "sg:postcode":"7415 TG",
    "sg:province":"Overijssel",
    "wof:name":"Josh Country En Western Artikelen",
    "wof:placetype":"venue"
},
  "geometry": {"coordinates":[6.162803,52.265919],"type":"Point"}
}