{
  "type": "Feature",
  "properties": {
    "iso:country":"NL",
    "sg:address":"Marsstukken 61",
    "sg:city":"Aalden",
    "sg:orig_category":"Antiekzaken",
    "sg:phone":"+31 591 372 517",
    "sg:postcode":"7854 PS",
    "sg:province":"Drenthe",
    "wof:name":"Antiekhandel Oosting",
    "wof:placetype":"venue"
},
  "geometry": {"coordinates":[6.714683,52.796158],"type":"Point"}
}