{
  "type": "Feature",
  "properties": {
    "addr:full":"Tesselschadestraat 35 Leeuwarden Friesland 8913 HA",
    "addr:housenumber":"35",
    "addr:postcode":"8913 ha",
    "addr:street":"Tesselschadestraat",
    "iso:country":"NL",
    "sg:address":"Tesselschadestraat 35",
    "sg:city":"Leeuwarden",
    "sg:orig_category":"Werving And Selectie Van Vast Personeel",
    "sg:phone":"+31 58 297 7777",
    "sg:postcode":"8913 HA",
    "sg:province":"Friesland",
    "wof:name":"Arbeidsbureau Leeuwarden",
    "wof:placetype":"venue"
},
  "geometry": {"coordinates":[5.7788538933,53.1991958618],"type":"Point"}
}