{
  "type": "Feature",
  "properties": {
    "addr:full":"Rozenhof 101 Epe Gelderland 8161 BE",
    "addr:housenumber":"101",
    "addr:postcode":"8161",
    "addr:street":"Rozenhof;Gelderland",
    "iso:country":"NL",
    "sg:address":"Rozenhof 101",
    "sg:city":"Epe",
    "sg:classifiers":[
        {
            "category":"Real Estate",
            "subcategory":"Real Estate Operator",
            "type":"Services"
        }
    ],
    "sg:phone":"+31 578 613 006",
    "sg:postcode":"8161 BE",
    "sg:province":"Gelderland",
    "sg:tags":[
        "appartementen",
        "en",
        "flat"
    ],
    "wof:name":"Rozenhof Ua",
    "wof:placetype":"venue"
},
  "geometry": {"coordinates":[5.990682,52.354877],"type":"Point"}
}