{
  "type": "Feature",
  "properties": {
    "addr:full":"Geerdinkhof 18 Amsterdam Zuidoost Noord-Holland 1103 PP",
    "addr:housenumber":"18",
    "addr:postcode":"zuidoost;1103 pp",
    "addr:street":"Geerdinkhof",
    "iso:country":"NL",
    "sg:address":"Geerdinkhof 18",
    "sg:city":"Amsterdam Zuidoost",
    "sg:orig_category":"Verzekeringen",
    "sg:phone":"+31 20 690 6566",
    "sg:postcode":"1103 PP",
    "sg:province":"Noord-Holland",
    "wof:name":"Spaan Assurantien",
    "wof:placetype":"venue"
},
  "geometry": {"coordinates":[4.981847,52.323223],"type":"Point"}
}