{
  "type": "Feature",
  "properties": {
    "iso:country":"NL",
    "sg:address":"Geerdinkhof 18",
    "sg:city":"Amsterdam Zuidoost",
    "sg:orig_category":"Verzekeringen",
    "sg:phone":"+31 20 690 6566",
    "sg:postcode":"1103 PP",
    "sg:province":"Noord-Holland",
    "wof:name":"Spaan Assurantien",
    "wof:placetype":"venue"
},
  "geometry": {"coordinates":[4.981847,52.323223],"type":"Point"}
}