{
  "type": "Feature",
  "properties": {
    "iso:country":"NL",
    "sg:address":"Laan Van Meerdervoort 264",
    "sg:city":"'S Gravenhage",
    "sg:classifiers":[
        {
            "category":"Shopping",
            "subcategory":"Clothing, Apparel, & Fashions",
            "type":"Retail Goods"
        }
    ],
    "sg:phone":"+31 70 363 6682",
    "sg:postcode":"2563 AJ",
    "sg:province":"Zuid-Holland",
    "sg:tags":[
        "ondergoed",
        "lingerie"
    ],
    "wof:name":"Mariken V/H Van Stuivenberg",
    "wof:placetype":"venue"
},
  "geometry": {"coordinates":[4.280397,52.079628],"type":"Point"}
}