{
  "type": "Feature",
  "properties": {
    "addr:full":"Doornstraat 1 'S Gravenhage Zuid-Holland 2584 AL",
    "addr:housenumber":"1 '",
    "addr:postcode":"2584 al",
    "addr:street":"Doornstraat",
    "iso:country":"NL",
    "sg:address":"Doornstraat 1",
    "sg:city":"'S Gravenhage",
    "sg:orig_category":"Zalenexploitatie",
    "sg:phone":"+31 70 354 4094",
    "sg:postcode":"2584 AL",
    "sg:province":"Zuid-Holland",
    "wof:name":"Artbank",
    "wof:placetype":"venue"
},
  "geometry": {"coordinates":[4.276059,52.101498],"type":"Point"}
}