{
  "type": "Feature",
  "properties": {
    "addr:full":"Piriet 8 Heerhugowaard Noord-Holland 1703 BL",
    "addr:housenumber":"8",
    "addr:postcode":"1703 bl",
    "addr:street":"Piriet",
    "iso:country":"NL",
    "sg:address":"Piriet 8",
    "sg:city":"Heerhugowaard",
    "sg:orig_category":"Aannemers Woningbouw",
    "sg:phone":"+31 72 571 0091",
    "sg:postcode":"1703 BL",
    "sg:province":"Noord-Holland",
    "wof:name":"Promo",
    "wof:placetype":"venue"
},
  "geometry": {"coordinates":[4.81465,52.660912],"type":"Point"}
}