{
  "type": "Feature",
  "properties": {
    "iso:country":"NL",
    "sg:address":"Piriet 8",
    "sg:city":"Heerhugowaard",
    "sg:orig_category":"Aannemers Woningbouw",
    "sg:phone":"+31 72 571 0091",
    "sg:postcode":"1703 BL",
    "sg:province":"Noord-Holland",
    "wof:name":"Promo",
    "wof:placetype":"venue"
},
  "geometry": {"coordinates":[4.81465,52.660912],"type":"Point"}
}