{
  "type": "Feature",
  "properties": {
    "addr:full":"De Bruynestraat 42 'S Gravenhage South Holland 2597 RH",
    "addr:housenumber":"42",
    "addr:postcode":"2597 rh",
    "addr:street":"De Bruynestraat;' S Gravenhage",
    "iso:country":"NL",
    "sg:address":"De Bruynestraat 42",
    "sg:city":"'S Gravenhage",
    "sg:orig_category":"Public Relationbureaus",
    "sg:phone":"+31 70 362 4776",
    "sg:postcode":"2597 RH",
    "sg:province":"South Holland",
    "wof:name":"I. Teekens",
    "wof:placetype":"venue"
},
  "geometry": {"coordinates":[4.314729,52.099998],"type":"Point"}
}