{
  "type": "Feature",
  "properties": {
    "addr:full":"Elftweg 54 Raamsdonksveer North Brabant 4941 VP",
    "addr:housenumber":"54",
    "addr:postcode":"4941 vp",
    "addr:street":"Elftweg",
    "iso:country":"NL",
    "sg:address":"Elftweg 54",
    "sg:city":"Raamsdonksveer",
    "sg:orig_category":"Veiligheidsuitrusting En -Kleding",
    "sg:phone":"+31 162 511 578",
    "sg:postcode":"4941 VP",
    "sg:province":"North Brabant",
    "wof:name":"Dianne",
    "wof:placetype":"venue"
},
  "geometry": {"coordinates":[4.880781,51.711426],"type":"Point"}
}