{
  "type": "Feature",
  "properties": {
    "addr:full":"Ossenkolkweg 3 Terwolde Gelderland 7396 NH",
    "addr:housenumber":"3",
    "addr:postcode":"7396 nh",
    "addr:street":"Ossenkolkweg;Gelderland",
    "iso:country":"NL",
    "sg:address":"Ossenkolkweg 3",
    "sg:city":"Terwolde",
    "sg:orig_category":"Zuivelproducten",
    "sg:phone":"+31 571 292 208",
    "sg:postcode":"7396 NH",
    "sg:province":"Gelderland",
    "wof:name":"De Wolf",
    "wof:placetype":"venue"
},
  "geometry": {"coordinates":[-71.632828,44.001301],"type":"Point"}
}