{
  "type": "Feature",
  "properties": {
    "addr:full":"De Akker 9 Waddinxveen Zuid-Holland 2743 DR",
    "addr:housenumber":"9",
    "addr:postcode":"2743 dr",
    "addr:street":"De Akker",
    "iso:country":"NL",
    "sg:address":"De Akker 9",
    "sg:city":"Waddinxveen",
    "sg:orig_category":"Adviesbureaus",
    "sg:phone":"+31 182 632 775",
    "sg:postcode":"2743 DR",
    "sg:province":"Zuid-Holland",
    "wof:name":"Haircare",
    "wof:placetype":"venue"
},
  "geometry": {"coordinates":[4.642346,52.036961],"type":"Point"}
}