{
  "type": "Feature",
  "properties": {
    "addr:full":"Achterwg 5 Tiel Gelderland 4001 MV",
    "addr:housenumber":"5",
    "addr:postcode":"4001 mv",
    "addr:street":"Achterwg;Gelderland",
    "iso:country":"NL",
    "sg:address":"Achterwg 5",
    "sg:city":"Tiel",
    "sg:orig_category":"Accountants - Administratie- Consulenten En -Kantoren",
    "sg:phone":"+31 344 613 797",
    "sg:postcode":"4001 MV",
    "sg:province":"Gelderland",
    "wof:name":"Lith, Van",
    "wof:placetype":"venue"
},
  "geometry": {"coordinates":[5.430696,51.888096],"type":"Point"}
}