{
  "type": "Feature",
  "properties": {
    "iso:country":"NL",
    "sg:address":"Valkenierslaan 67",
    "sg:city":"Breda",
    "sg:orig_category":"Algemene Werktuigbouw",
    "sg:phone":"+31 76 565 3743",
    "sg:postcode":"4834 CA",
    "sg:province":"Noord-Brabant",
    "wof:name":"Quality Projects Int.",
    "wof:placetype":"venue"
},
  "geometry": {"coordinates":[4.795733,51.57185],"type":"Point"}
}