{
  "type": "Feature",
  "properties": {
    "addr:full":"Lekstr 27-37-39 S Gravenhage Zuid-Holland 2515 XA",
    "addr:housenumber":"27-37-39;gravenhage",
    "addr:postcode":"2515 xa",
    "addr:street":"S",
    "iso:country":"NL",
    "sg:address":"Lekstr 27-37-39",
    "sg:city":"S Gravenhage",
    "sg:orig_category":"Automaterialen En Gereedschappen",
    "sg:phone":"+31 70 347 4644",
    "sg:postcode":"2515 XA",
    "sg:province":"Zuid-Holland",
    "sg:website":"http://www.automateriaal.com",
    "wof:name":"Keijzer, De",
    "wof:placetype":"venue"
},
  "geometry": {"coordinates":[4.31741,52.083988],"type":"Point"}
}