{
  "type": "Feature",
  "properties": {
    "addr:full":"Rugbystr 23 Rotterdam South Holland 3078 ZG",
    "addr:housenumber":"23",
    "addr:postcode":"3078 zg",
    "addr:street":"Rugbystr",
    "iso:country":"NL",
    "sg:address":"Rugbystr 23",
    "sg:city":"Rotterdam",
    "sg:orig_category":"Kunststof Ramen",
    "sg:phone":"+31 10 479 7301",
    "sg:postcode":"3078 ZG",
    "sg:province":"South Holland",
    "wof:name":"Thermax Kozijnen",
    "wof:placetype":"venue"
},
  "geometry": {"coordinates":[4.533776,51.89373],"type":"Point"}
}