{
  "type": "Feature",
  "properties": {
    "iso:country":"NL",
    "sg:address":"Rugbystr 23",
    "sg:city":"Rotterdam",
    "sg:orig_category":"Kunststof Ramen",
    "sg:phone":"+31 10 479 7301",
    "sg:postcode":"3078 ZG",
    "sg:province":"South Holland",
    "wof:name":"Thermax Kozijnen",
    "wof:placetype":"venue"
},
  "geometry": {"coordinates":[4.533776,51.89373],"type":"Point"}
}