{
  "type": "Feature",
  "properties": {
    "iso:country":"NL",
    "sg:address":"Bree 45-47",
    "sg:city":"Rotterdam",
    "sg:orig_category":"Autorijscholen",
    "sg:phone":"+31 10 419 4166",
    "sg:postcode":"3074 BC",
    "sg:province":"Zuid-Holland",
    "sg:website":"http://www.verkeersschool-blad.nl",
    "wof:name":"Blad, Verkeersschool",
    "wof:placetype":"venue"
},
  "geometry": {"coordinates":[4.511278,51.890224],"type":"Point"}
}