{
  "type": "Feature",
  "properties": {
    "addr:full":"Zegveldse Uitwg 5 Woerden Utrecht 3443 JE",
    "addr:housenumber":"5",
    "addr:postcode":"3443 je",
    "addr:street":"Uitwg",
    "iso:country":"NL",
    "sg:address":"Zegveldse Uitwg 5",
    "sg:city":"Woerden",
    "sg:orig_category":"Glasdecoratie",
    "sg:phone":"+31 348 434 141",
    "sg:postcode":"3443 JE",
    "sg:province":"Utrecht",
    "wof:name":"Vooren, Van Der",
    "wof:placetype":"venue"
},
  "geometry": {"coordinates":[4.861695,52.087799],"type":"Point"}
}