{
  "type": "Feature",
  "properties": {
    "iso:country":"NL",
    "sg:address":"Westerzicht 494",
    "sg:city":"Vlissingen",
    "sg:classifiers":[
        {
            "category":"Travel",
            "subcategory":"Hotels & Motels",
            "type":"Entertainment"
        }
    ],
    "sg:phone":"+31 118 465 946",
    "sg:postcode":"4385 BS",
    "sg:province":"Zeeland",
    "wof:name":"M.A.J. Hogerheide",
    "wof:placetype":"venue"
},
  "geometry": {"coordinates":[3.58548,51.461586],"type":"Point"}
}