{
  "type": "Feature",
  "properties": {
    "addr:full":"Nyverheidswg 33 Etten Leur Noord-Brabant 4879 AP",
    "addr:housenumber":"33",
    "addr:postcode":"4879 ap",
    "addr:street":"Nyverheidswg",
    "iso:country":"NL",
    "sg:address":"Nyverheidswg 33",
    "sg:city":"Etten Leur",
    "sg:classifiers":[
        {
            "category":"Retail",
            "subcategory":"Auto Repair",
            "type":"Services"
        }
    ],
    "sg:phone":"+31 76 503 3888",
    "sg:postcode":"4879 AP",
    "sg:province":"Noord-Brabant",
    "sg:tags":[
        "garage"
    ],
    "wof:name":"Tilburg-Bastianen Bv, P Van",
    "wof:placetype":"venue"
},
  "geometry": {"coordinates":[4.608494,51.56337],"type":"Point"}
}