{
  "type": "Feature",
  "properties": {
    "addr:full":"L Brinkwg 94 Soest Utrecht 3764 AG",
    "addr:housenumber":"94",
    "addr:postcode":"3764",
    "addr:street":"Soest",
    "iso:country":"NL",
    "sg:address":"L Brinkwg 94",
    "sg:city":"Soest",
    "sg:orig_category":"Schilders",
    "sg:phone":"+31 35 601 2234",
    "sg:postcode":"3764 AG",
    "sg:province":"Utrecht",
    "wof:name":"Steeg & Zoon, Fa H Van Der",
    "wof:placetype":"venue"
},
  "geometry": {"coordinates":[5.313065,52.175671],"type":"Point"}
}