{
  "type": "Feature",
  "properties": {
    "addr:full":"Leurschans 34 Steenbergen Nb Noord-Brabant 4651 WJ",
    "addr:housenumber":"34",
    "addr:postcode":"4651 wj",
    "addr:street":"Leurschans",
    "iso:country":"NL",
    "sg:address":"Leurschans 34",
    "sg:city":"Steenbergen Nb",
    "sg:orig_category":"Machinehandel",
    "sg:phone":"+31 167 563 552",
    "sg:postcode":"4651 WJ",
    "sg:province":"Noord-Brabant",
    "wof:name":"Ocmg",
    "wof:placetype":"venue"
},
  "geometry": {"coordinates":[4.325426,51.593655],"type":"Point"}
}