{
  "type": "Feature",
  "properties": {
    "iso:country":"NL",
    "sg:address":"Breepln 2A",
    "sg:city":"Rotterdam",
    "sg:orig_category":"Homeopathie",
    "sg:phone":"+31 10 419 0197",
    "sg:postcode":"3075 KC",
    "sg:province":"Zuid-Holland",
    "wof:name":"Promy Bv",
    "wof:placetype":"venue"
},
  "geometry": {"coordinates":[4.513923,51.890221],"type":"Point"}
}