{
  "type": "Feature",
  "properties": {
    "iso:country":"NL",
    "sg:address":"Charley Tooropstraat 2",
    "sg:city":"Hilversum",
    "sg:orig_category":"Muziekinstrumenten En Bladmuziek",
    "sg:phone":"+31 35 623 9663",
    "sg:postcode":"1213 LH",
    "sg:province":"North Holland",
    "wof:name":"Music Mail",
    "wof:placetype":"venue"
},
  "geometry": {"coordinates":[5.176722,52.210911],"type":"Point"}
}