{
  "type": "Feature",
  "properties": {
    "addr:full":"Hoefweg 204 Bleiswijk Zuid-Holland 2665 LE",
    "addr:housenumber":"204",
    "addr:postcode":"2665 le",
    "addr:street":"Hoefweg",
    "iso:country":"NL",
    "sg:address":"Hoefweg 204",
    "sg:city":"Bleiswijk",
    "sg:orig_category":"Bedrijfs- And Managementsconsultants",
    "sg:phone":"+31 10 521 4024",
    "sg:postcode":"2665 LE",
    "sg:province":"Zuid-Holland",
    "wof:name":"A.J. Brons",
    "wof:placetype":"venue"
},
  "geometry": {"coordinates":[4.538893,52.031002],"type":"Point"}
}