{
  "type": "Feature",
  "properties": {
    "addr:full":"Anjerstr 2 Alblasserdam South Holland 2951 BA",
    "addr:housenumber":"2",
    "addr:postcode":"2951 ba",
    "addr:street":"Anjerstr",
    "iso:country":"NL",
    "sg:address":"Anjerstr 2",
    "sg:city":"Alblasserdam",
    "sg:orig_category":"Verenigingen En Stichtingen",
    "sg:phone":"+31 78 691 6844",
    "sg:postcode":"2951 BA",
    "sg:province":"South Holland",
    "wof:name":"Wao Belangengroep",
    "wof:placetype":"venue"
},
  "geometry": {"coordinates":[4.661856,51.868839],"type":"Point"}
}