{
  "type": "Feature",
  "properties": {
    "addr:full":"Westkerksewg 5 Scherpenisse Zeeland 4694 CW",
    "addr:housenumber":"5",
    "addr:postcode":"4694 cw",
    "addr:street":"Westkerksewg",
    "iso:country":"NL",
    "sg:address":"Westkerksewg 5",
    "sg:city":"Scherpenisse",
    "sg:orig_category":"Kasregisters",
    "sg:phone":"+31 166 661 763",
    "sg:postcode":"4694 CW",
    "sg:province":"Zeeland",
    "sg:website":"http://www.boskassa.nl",
    "wof:name":"Bos Kassasystemen",
    "wof:placetype":"venue"
},
  "geometry": {"coordinates":[4.101968,51.54723],"type":"Point"}
}