{
  "type": "Feature",
  "properties": {
    "addr:full":"S V Oyenwg 17 Oyen Noord-Brabant 5394 AR",
    "addr:housenumber":"17",
    "addr:postcode":"5394",
    "addr:street":"Oyenwg",
    "iso:country":"NL",
    "sg:address":"S V Oyenwg 17",
    "sg:city":"Oyen",
    "sg:orig_category":"Kappers",
    "sg:phone":"+31 412 492 407",
    "sg:postcode":"5394 AR",
    "sg:province":"Noord-Brabant",
    "wof:name":"Hannie",
    "wof:placetype":"venue"
},
  "geometry": {"coordinates":[-96.0559387207,42.8205337524],"type":"Point"}
}