{
  "type": "Feature",
  "properties": {
    "addr:full":"Lekdk W 1 Schoonhoven Zuid-Holland 2871 MK",
    "addr:housenumber":"1",
    "addr:postcode":"2871",
    "addr:street":"W",
    "iso:country":"NL",
    "sg:address":"Lekdk W 1",
    "sg:city":"Schoonhoven",
    "sg:orig_category":"Goudsmeden En Zilversmeden",
    "sg:phone":"+31 182 382 331",
    "sg:postcode":"2871 MK",
    "sg:province":"Zuid-Holland",
    "wof:name":"Oudsten, Fa Den",
    "wof:placetype":"venue"
},
  "geometry": {"coordinates":[4.849568,51.94318],"type":"Point"}
}