{
  "type": "Feature",
  "properties": {
    "addr:full":"Muiderweg 4 Zeewolde Flevoland 3891 DB",
    "addr:housenumber":"4",
    "addr:postcode":"3891 db",
    "addr:street":"Muiderweg;Flevoland",
    "iso:country":"NL",
    "sg:address":"Muiderweg 4",
    "sg:city":"Zeewolde",
    "sg:orig_category":"Boekenuitgeverijen",
    "sg:phone":"+31 36 522 4976",
    "sg:postcode":"3891 DB",
    "sg:province":"Flevoland",
    "wof:name":"Publikatieburo/Uitgeverij De Tolboom",
    "wof:placetype":"venue"
},
  "geometry": {"coordinates":[5.529272,52.33519],"type":"Point"}
}