{
  "type": "Feature",
  "properties": {
    "addr:full":"Klokkendijk 4 Lochem Gelderland 7241 SP",
    "addr:housenumber":"4",
    "addr:postcode":"7241 sp",
    "addr:street":"Klokkendijk;Gelderland",
    "iso:country":"NL",
    "sg:address":"Klokkendijk 4",
    "sg:city":"Lochem",
    "sg:orig_category":"Kappers",
    "sg:phone":"+31 573 255 662",
    "sg:postcode":"7241 SP",
    "sg:province":"Gelderland",
    "wof:name":"Salon Maurien",
    "wof:placetype":"venue"
},
  "geometry": {"coordinates":[6.377525,52.154202],"type":"Point"}
}