{
  "type": "Feature",
  "properties": {
    "addr:full":"Rode Kruisstraat 79 Amsterdam Noord-Holland 1025 KM",
    "addr:housenumber":"79",
    "addr:postcode":"1025 km",
    "addr:street":"Rode Kruisstraat",
    "iso:country":"NL",
    "sg:address":"Rode Kruisstraat 79",
    "sg:city":"Amsterdam",
    "sg:orig_category":"Politie",
    "sg:phone":"+31 900 8844",
    "sg:postcode":"1025 KM",
    "sg:province":"Noord-Holland",
    "wof:name":"Politie District Amsterdam-Noord",
    "wof:placetype":"venue"
},
  "geometry": {"coordinates":[4.928242,52.395115],"type":"Point"}
}