{
  "type": "Feature",
  "properties": {
    "iso:country":"NL",
    "sg:address":"Meerkoetweg 9A",
    "sg:city":"Heerenveen",
    "sg:orig_category":"Kinderopvang Behalve Thuis",
    "sg:phone":"+31 513 625 331",
    "sg:postcode":"8446 JT",
    "sg:province":"Provincie Friesland",
    "wof:name":"Kinderdagcentrum Us Greide",
    "wof:placetype":"venue"
},
  "geometry": {"coordinates":[5.924365,52.946629],"type":"Point"}
}