{
  "type": "Feature",
  "properties": {
    "addr:full":"Achterweg 57 Herwijnen Gelderland 4171 BA",
    "addr:housenumber":"57",
    "addr:postcode":"4171 ba",
    "addr:street":"Achterweg;Gelderland",
    "iso:country":"NL",
    "sg:address":"Achterweg 57",
    "sg:city":"Herwijnen",
    "sg:orig_category":"Goederenvervoer Over De Weg",
    "sg:phone":"+31 418 581 405",
    "sg:postcode":"4171 BA",
    "sg:province":"Gelderland",
    "wof:name":"Firma Van Arendonk",
    "wof:placetype":"venue"
},
  "geometry": {"coordinates":[5.136904,51.825005],"type":"Point"}
}