{
  "type": "Feature",
  "properties": {
    "iso:country":"NL",
    "sg:address":"Beekstraat 41",
    "sg:city":"Epe",
    "sg:orig_category":"Verzekeringen",
    "sg:phone":"+31 578 612 349",
    "sg:postcode":"8162 HA",
    "sg:province":"Gelderland",
    "wof:name":"Unive Noord Veluwe",
    "wof:placetype":"venue"
},
  "geometry": {"coordinates":[5.97796,52.346882],"type":"Point"}
}