{
  "type": "Feature",
  "properties": {
    "addr:full":"Stationsstr 7 Bergen Nh North Holland 1861 GA",
    "addr:housenumber":"7",
    "addr:postcode":"1861 ga",
    "addr:street":"Stationsstr",
    "iso:country":"NL",
    "sg:address":"Stationsstr 7",
    "sg:city":"Bergen Nh",
    "sg:orig_category":"Boeken En Tijdschriften",
    "sg:phone":"+31 72 581 2763",
    "sg:postcode":"1861 GA",
    "sg:province":"North Holland",
    "sg:website":"http://www.boekhandelthomas.nl",
    "wof:name":"Thomas Bv",
    "wof:placetype":"venue"
},
  "geometry": {"coordinates":[4.700338,52.67054],"type":"Point"}
}