{
  "type": "Feature",
  "properties": {
    "iso:country":"NL",
    "sg:address":"Plotterweg 14",
    "sg:city":"Amersfoort",
    "sg:orig_category":"Verzekeringen",
    "sg:phone":"+31 33 453 8453",
    "sg:postcode":"3821 BB",
    "sg:province":"Utrecht",
    "wof:name":"Qua Raad Advies Bv",
    "wof:placetype":"venue"
},
  "geometry": {"coordinates":[5.408478,52.173599],"type":"Point"}
}