{
  "type": "Feature",
  "properties": {
    "addr:full":"P Schreurswg 46 Haelen Limburg 6081 NX",
    "addr:housenumber":"46",
    "addr:postcode":"6081 nx",
    "addr:street":"P",
    "iso:country":"NL",
    "sg:address":"P Schreurswg 46",
    "sg:city":"Haelen",
    "sg:orig_category":"Loodgieters",
    "sg:phone":"+31 475 593 096",
    "sg:postcode":"6081 NX",
    "sg:province":"Limburg",
    "wof:name":"Boots Haelen Bv",
    "wof:placetype":"venue"
},
  "geometry": {"coordinates":[5.956777,51.221764],"type":"Point"}
}