{
  "type": "Feature",
  "properties": {
    "addr:full":"Loskd 6 Zutphen Gelderland 7202 CZ",
    "addr:housenumber":"6;7202",
    "addr:street":"Loskd;Gelderland",
    "iso:country":"NL",
    "sg:address":"Loskd 6",
    "sg:city":"Zutphen",
    "sg:orig_category":"Land- En Tuinbouw - Mechanisatie",
    "sg:phone":"+31 575 599 999",
    "sg:postcode":"7202 CZ",
    "sg:province":"Gelderland",
    "wof:name":"Stierman",
    "wof:placetype":"venue"
},
  "geometry": {"coordinates":[6.191525,52.140202],"type":"Point"}
}