{
  "type": "Feature",
  "properties": {
    "addr:full":"Graaf Waltgerlaan 15 Tiel Gelderland 4001 KE",
    "addr:housenumber":"15",
    "addr:postcode":"4001 ke",
    "addr:street":"Graaf Waltgerlaan;Gelderland",
    "iso:country":"NL",
    "sg:address":"Graaf Waltgerlaan 15",
    "sg:city":"Tiel",
    "sg:orig_category":"Werving And Selectie Van Tijdelijk Personeel And Uitzendkantoren",
    "sg:phone":"+31 344 634 399",
    "sg:postcode":"4001 KE",
    "sg:province":"Gelderland",
    "wof:name":"Nlc",
    "wof:placetype":"venue"
},
  "geometry": {"coordinates":[5.4313502312,51.8822441101],"type":"Point"}
}