{
  "type": "Feature",
  "properties": {
    "addr:full":"Dorpsstr 35 Ouderkerk Amstel North Holland 1191 BH",
    "addr:housenumber":"35",
    "addr:postcode":"1191 bh",
    "addr:street":"Dorpsstr;Amstel",
    "iso:country":"NL",
    "sg:address":"Dorpsstr 35",
    "sg:city":"Ouderkerk Amstel",
    "sg:orig_category":"Vertaalbureaus",
    "sg:phone":"+31 20 496 5271",
    "sg:postcode":"1191 BH",
    "sg:province":"North Holland",
    "sg:website":"http://www.isp.nl",
    "wof:name":"Isp",
    "wof:placetype":"venue"
},
  "geometry": {"coordinates":[4.902158,52.297146],"type":"Point"}
}