{
  "type": "Feature",
  "properties": {
    "addr:full":"Karpatenlaan 72 Tilburg Noord-Brabant 5022 GJ",
    "addr:housenumber":"72",
    "addr:postcode":"5022 gj",
    "addr:street":"Karpatenlaan",
    "iso:country":"NL",
    "sg:address":"Karpatenlaan 72",
    "sg:city":"Tilburg",
    "sg:orig_category":"Bloemen And Planten",
    "sg:phone":"+31 13 543 4628",
    "sg:postcode":"5022 GJ",
    "sg:province":"Noord-Brabant",
    "wof:name":"Van Geloven",
    "wof:placetype":"venue"
},
  "geometry": {"coordinates":[5.082915,51.539513],"type":"Point"}
}