{
  "type": "Feature",
  "properties": {
    "addr:full":"Midden Eng 34 Bennekom Gelderland 6721 GX",
    "addr:housenumber":"34",
    "addr:postcode":"6721 gx",
    "addr:street":"Midden Eng;Gelderland",
    "iso:country":"NL",
    "sg:address":"Midden Eng 34",
    "sg:city":"Bennekom",
    "sg:classifiers":[
        {
            "category":"Personal",
            "subcategory":"Nail Salon",
            "type":"Services"
        }
    ],
    "sg:phone":"+31 318 418 997",
    "sg:postcode":"6721 GX",
    "sg:province":"Gelderland",
    "sg:tags":[
        "pedicure"
    ],
    "wof:name":"Veraa, C",
    "wof:placetype":"venue"
},
  "geometry": {"coordinates":[5.681241,51.995373],"type":"Point"}
}