{
  "type": "Feature",
  "properties": {
    "addr:full":"Oosterhoutstr 116 Arnhem Gelderland 6843 RP",
    "addr:housenumber":"116",
    "addr:postcode":"6843 rp",
    "iso:country":"NL",
    "sg:address":"Oosterhoutstr 116",
    "sg:city":"Arnhem",
    "sg:orig_category":"Schilders",
    "sg:phone":"+31 26 443 2128",
    "sg:postcode":"6843 RP",
    "sg:province":"Gelderland",
    "wof:name":"Mission Schilderwerken",
    "wof:placetype":"venue"
},
  "geometry": {"coordinates":[5.862824,51.950577],"type":"Point"}
}