{
  "type": "Feature",
  "properties": {
    "addr:full":"Nicolaas Beetsstraat 18 Papendrecht Zuid-Holland 3351 EC",
    "addr:housenumber":"18",
    "addr:postcode":"3351 ec",
    "addr:street":"Nicolaas Beetsstraat",
    "iso:country":"NL",
    "sg:address":"Nicolaas Beetsstraat 18",
    "sg:city":"Papendrecht",
    "sg:orig_category":"Technische Studies And Onderzoek",
    "sg:phone":"+31 78 615 4566",
    "sg:postcode":"3351 EC",
    "sg:province":"Zuid-Holland",
    "wof:name":"Navcon Maritime Projects Bv",
    "wof:placetype":"venue"
},
  "geometry": {"coordinates":[4.673856,51.832378],"type":"Point"}
}