{
  "type": "Feature",
  "properties": {
    "addr:full":"Hagerhofwg 9 Venlo Limburg 5912 PN",
    "addr:housenumber":"9",
    "addr:postcode":"5912 pn",
    "addr:street":"Hagerhofwg",
    "iso:country":"NL",
    "sg:address":"Hagerhofwg 9",
    "sg:city":"Venlo",
    "sg:orig_category":"Banden",
    "sg:phone":"+31 77 320 0532",
    "sg:postcode":"5912 PN",
    "sg:province":"Limburg",
    "sg:website":"http://www.kwik-fit.nl",
    "wof:name":"Kwik-Fit",
    "wof:placetype":"venue"
},
  "geometry": {"coordinates":[6.162944,51.356152],"type":"Point"}
}