{
  "type": "Feature",
  "properties": {
    "addr:full":"Kralingsewg 233-1 Rotterdam Zuid-Holland 3062 CE",
    "addr:housenumber":"233-1",
    "addr:postcode":"rotterdam;3062 ce",
    "iso:country":"NL",
    "sg:address":"Kralingsewg 233-1",
    "sg:city":"Rotterdam",
    "sg:orig_category":"Loopbaanbegeleiding",
    "sg:phone":"+31 10 452 4922",
    "sg:postcode":"3062 CE",
    "sg:province":"Zuid-Holland",
    "sg:website":"http://www.joosten-partners.nl",
    "wof:name":"Joosten & Partners Bv",
    "wof:placetype":"venue"
},
  "geometry": {"coordinates":[4.536688,51.927639],"type":"Point"}
}