{
  "type": "Feature",
  "properties": {
    "iso:country":"NL",
    "sg:address":"Grotestr 59",
    "sg:city":"Gendringen",
    "sg:orig_category":"Fietsen En Bromfietsen",
    "sg:phone":"+31 315 681 750",
    "sg:postcode":"7081 CC",
    "sg:province":"Gelderland",
    "wof:name":"Mekers",
    "wof:placetype":"venue"
},
  "geometry": {"coordinates":[6.375791,51.872017],"type":"Point"}
}