{
  "type": "Feature",
  "properties": {
    "addr:full":"Barbarastraat 28 Helden Limburg 5988 BC",
    "addr:housenumber":"28",
    "addr:postcode":"5988 bc",
    "addr:street":"Barbarastraat",
    "iso:country":"NL",
    "sg:address":"Barbarastraat 28",
    "sg:city":"Helden",
    "sg:orig_category":"Architecten",
    "sg:phone":"+31 77 307 4364",
    "sg:postcode":"5988 BC",
    "sg:province":"Limburg",
    "wof:name":"Oac Simwerk-Design",
    "wof:placetype":"venue"
},
  "geometry": {"coordinates":[-126.555511,54.485668],"type":"Point"}
}