{
  "type": "Feature",
  "properties": {
    "iso:country":"NL",
    "sg:address":"Stationsweg 38",
    "sg:city":"Aalsmeer",
    "sg:orig_category":"Werving And Selectie Van Vast Personeel",
    "sg:phone":"+31 297 342 354",
    "sg:postcode":"1431 EG",
    "sg:province":"Noord-Holland",
    "wof:name":"Koeleman Consultancy Nederland",
    "wof:placetype":"venue"
},
  "geometry": {"coordinates":[4.7503919601,52.2649002075],"type":"Point"}
}