{
  "type": "Feature",
  "properties": {
    "addr:full":"Van Kanstraat 1A Eindhoven Noord-Brabant 5652 GA",
    "addr:housenumber":"1a",
    "addr:postcode":"5652 ga",
    "addr:street":"Van Kanstraat",
    "iso:country":"NL",
    "sg:address":"Van Kanstraat 1A",
    "sg:city":"Eindhoven",
    "sg:orig_category":"Verhuur Catering-, Feest- En Evenementbenodigdheden",
    "sg:phone":"+31 40 255 1860",
    "sg:postcode":"5652 GA",
    "sg:province":"Noord-Brabant",
    "wof:name":"Linders Horeca Inrichting En Uitrusting",
    "wof:placetype":"venue"
},
  "geometry": {"coordinates":[5.447609,51.439728],"type":"Point"}
}