{
  "type": "Feature",
  "properties": {
    "iso:country":"NL",
    "sg:address":"Marconiwg 11C",
    "sg:city":"Delft",
    "sg:classifiers":[
        {
            "category":"Food & Beverages",
            "subcategory":"Bakery",
            "type":"Retail Goods"
        }
    ],
    "sg:phone":"+31 15 257 8054",
    "sg:postcode":"2627 BA",
    "sg:province":"Zuid-Holland",
    "sg:tags":[
        "pizza"
    ],
    "wof:name":"Domino",
    "wof:placetype":"venue"
},
  "geometry": {"coordinates":[4.3718,51.985016],"type":"Point"}
}