{
  "type": "Feature",
  "properties": {
    "iso:country":"NL",
    "sg:address":"Charley Tooropstraat 35",
    "sg:city":"Hendrik Ido Ambacht",
    "sg:orig_category":"Boekhouders",
    "sg:phone":"+31 78 681 7031",
    "sg:postcode":"3343 RE",
    "sg:province":"Zuid-Holland",
    "wof:name":"D.M. Van Der Giessen, Administraties",
    "wof:placetype":"venue"
},
  "geometry": {"coordinates":[4.638288,51.840645],"type":"Point"}
}