{
  "type": "Feature",
  "properties": {
    "addr:full":"Prinsengr 405 Amsterdam Noord-Holland 1016 HM",
    "addr:housenumber":"405",
    "addr:postcode":"1016 hm",
    "iso:country":"NL",
    "sg:address":"Prinsengr 405",
    "sg:city":"Amsterdam",
    "sg:orig_category":"Kopieerservice",
    "sg:phone":"+31 20 624 1190",
    "sg:postcode":"1016 HM",
    "sg:province":"Noord-Holland",
    "sg:website":"http://www.cito-repro.nl",
    "wof:name":"Cito Repro Bv",
    "wof:placetype":"venue"
},
  "geometry": {"coordinates":[4.883201,52.370022],"type":"Point"}
}