{
  "type": "Feature",
  "properties": {
    "addr:full":"Vogelenzang 5 Ossendrecht Noord-Brabant 4641 JK",
    "addr:housenumber":"5",
    "addr:postcode":"4641 jk",
    "addr:street":"Vogelenzang",
    "iso:country":"NL",
    "sg:address":"Vogelenzang 5",
    "sg:city":"Ossendrecht",
    "sg:orig_category":"Loodgieterswerk, Verwarming And Sanitaire Installaties",
    "sg:phone":"+31 164 672 267",
    "sg:postcode":"4641 JK",
    "sg:province":"Noord-Brabant",
    "wof:name":"V & P",
    "wof:placetype":"venue"
},
  "geometry": {"coordinates":[4.326611,51.394451],"type":"Point"}
}