{
  "type": "Feature",
  "properties": {
    "addr:full":"Wagnerplein 14 Tilburg North Brabant 5011 LP",
    "addr:housenumber":"14",
    "addr:postcode":"5011 lp",
    "addr:street":"Wagnerplein",
    "iso:country":"NL",
    "sg:address":"Wagnerplein 14",
    "sg:city":"Tilburg",
    "sg:orig_category":"Bloemen And Planten",
    "sg:phone":"+31 13 455 4744",
    "sg:postcode":"5011 LP",
    "sg:province":"North Brabant",
    "wof:name":"Florado",
    "wof:placetype":"venue"
},
  "geometry": {"coordinates":[5.084827,51.584385],"type":"Point"}
}