{
  "type": "Feature",
  "properties": {
    "addr:full":"Nieuwegr 16 Soest Utrecht 3763 LB",
    "addr:housenumber":"16",
    "addr:postcode":"3763 lb",
    "addr:street":"Nieuwegr",
    "iso:country":"NL",
    "sg:address":"Nieuwegr 16",
    "sg:city":"Soest",
    "sg:orig_category":"Weegwerktuigen - Fabrieken En Groothandel",
    "sg:phone":"+31 35 601 2734",
    "sg:postcode":"3763 LB",
    "sg:province":"Utrecht",
    "wof:name":"Dosco Bv",
    "wof:placetype":"venue"
},
  "geometry": {"coordinates":[5.3003849983,52.1840438843],"type":"Point"}
}