{
  "type": "Feature",
  "properties": {
    "addr:full":"Wijchenseweg 172 Nijmegen Gelderland 6538 SX",
    "addr:housenumber":"172",
    "addr:postcode":"6538 sx",
    "addr:street":"Wijchenseweg;Gelderland",
    "iso:country":"NL",
    "sg:address":"Wijchenseweg 172",
    "sg:city":"Nijmegen",
    "sg:orig_category":"Meubelzaken, Woning- And Keukeninrichting",
    "sg:phone":"+31 24 343 0333",
    "sg:postcode":"6538 SX",
    "sg:province":"Gelderland",
    "wof:name":"Woontrend",
    "wof:placetype":"venue"
},
  "geometry": {"coordinates":[5.800398,51.825047],"type":"Point"}
}