{
  "type": "Feature",
  "properties": {
    "addr:full":"Mr W M O V Veenwg 20 Bergum Friesland 9251 GA",
    "addr:housenumber":"20",
    "addr:postcode":"9251 ga",
    "addr:street":"W;Veenwg",
    "iso:country":"NL",
    "sg:address":"Mr W M O V Veenwg 20",
    "sg:city":"Bergum",
    "sg:orig_category":"Verenigingen En Stichtingen",
    "sg:phone":"+31 511 461 621",
    "sg:postcode":"9251 GA",
    "sg:province":"Friesland",
    "wof:name":"Dobbe Ua, De",
    "wof:placetype":"venue"
},
  "geometry": {"coordinates":[5.986921,53.19529],"type":"Point"}
}