{
  "type": "Feature",
  "properties": {
    "addr:full":"Tiggeltsebergstraat 60 Rijsbergen North Brabant 4891 TD",
    "addr:housenumber":"60",
    "addr:postcode":"4891 td",
    "addr:street":"Tiggeltsebergstraat",
    "iso:country":"NL",
    "sg:address":"Tiggeltsebergstraat 60",
    "sg:city":"Rijsbergen",
    "sg:orig_category":"Bloemen And Planten",
    "sg:phone":"+31 76 596 3859",
    "sg:postcode":"4891 TD",
    "sg:province":"North Brabant",
    "wof:name":"Jolanda Wouters",
    "wof:placetype":"venue"
},
  "geometry": {"coordinates":[4.664946,51.522106],"type":"Point"}
}