{
  "type": "Feature",
  "properties": {
    "addr:full":"Weidebloemenwg 69 Roden Drenthe 9302 AC",
    "addr:housenumber":"69",
    "addr:postcode":"9302 ac",
    "addr:street":"Weidebloemenwg",
    "iso:country":"NL",
    "sg:address":"Weidebloemenwg 69",
    "sg:city":"Roden",
    "sg:orig_category":"Haptotherapeuten",
    "sg:phone":"+31 50 501 5055",
    "sg:postcode":"9302 AC",
    "sg:province":"Drenthe",
    "sg:website":"http://www.haptotherapeuten-vvh.nl",
    "wof:name":"Douma, G J",
    "wof:placetype":"venue"
},
  "geometry": {"coordinates":[6.406532,53.12875],"type":"Point"}
}