{
  "type": "Feature",
  "properties": {
    "addr:full":"Muntpassage 43 Weert Limburg 6001 GL",
    "addr:housenumber":"43",
    "addr:postcode":"6001 gl",
    "addr:street":"Muntpassage",
    "iso:country":"NL",
    "sg:address":"Muntpassage 43",
    "sg:city":"Weert",
    "sg:orig_category":"Bijouterie?n",
    "sg:phone":"+31 495 520 970",
    "sg:postcode":"6001 GL",
    "sg:province":"Limburg",
    "wof:name":"Bijoux Bijoux",
    "wof:placetype":"venue"
},
  "geometry": {"coordinates":[5.704745,51.254463],"type":"Point"}
}