{
  "type": "Feature",
  "properties": {
    "addr:full":"Dorp 87 Benschop Utrecht 3405 BA",
    "addr:housenumber":"87",
    "addr:postcode":"3405 ba",
    "addr:street":"Dorp",
    "iso:country":"NL",
    "sg:address":"Dorp 87",
    "sg:city":"Benschop",
    "sg:orig_category":"Boekhouders",
    "sg:phone":"+31 348 451 304",
    "sg:postcode":"3405 BA",
    "sg:province":"Utrecht",
    "wof:name":"Administratie- & Assurantie- Kantoor Zuid-Utrecht",
    "wof:placetype":"venue"
},
  "geometry": {"coordinates":[4.990781,52.00983],"type":"Point"}
}