{
  "type": "Feature",
  "properties": {
    "addr:full":"Rozenstraat 1 'S Gravenhage South Holland 2565 SG",
    "addr:housenumber":"1 '",
    "addr:postcode":"2565 sg",
    "addr:street":"Rozenstraat",
    "iso:country":"NL",
    "sg:address":"Rozenstraat 1",
    "sg:city":"'S Gravenhage",
    "sg:orig_category":"Kappers",
    "sg:phone":"+31 70 345 8598",
    "sg:postcode":"2565 SG",
    "sg:province":"South Holland",
    "wof:name":"Hair Affair",
    "wof:placetype":"venue"
},
  "geometry": {"coordinates":[4.2576479912,52.0747375488],"type":"Point"}
}