{
  "type": "Feature",
  "properties": {
    "iso:country":"NL",
    "sg:address":"Willem 2 Str 19",
    "sg:city":"Tilburg",
    "sg:orig_category":"Verzekeringen - Verzekeringskantoren",
    "sg:phone":"+31 13 543 2907",
    "sg:postcode":"5038 BA",
    "sg:province":"North Brabant",
    "wof:name":"Timmermans",
    "wof:placetype":"venue"
},
  "geometry": {"coordinates":[5.086512,51.55891],"type":"Point"}
}