{
  "type": "Feature",
  "properties": {
    "addr:full":"Homme Hettingastraat 7 Amsterdam Noord-Holland 1067 PK",
    "addr:housenumber":"7",
    "addr:postcode":"1067 pk",
    "addr:street":"Homme Hettingastraat",
    "iso:country":"NL",
    "sg:address":"Homme Hettingastraat 7",
    "sg:city":"Amsterdam",
    "sg:classifiers":[
        {
            "category":"Fast Food",
            "type":"Food & Drink"
        }
    ],
    "sg:phone":"+31 20 613 2398",
    "sg:postcode":"1067 PK",
    "sg:province":"Noord-Holland",
    "sg:tags":[
        "afhaal",
        "restaurant"
    ],
    "wof:name":"Patat Frite Bakkery Graanstra En Zoon",
    "wof:placetype":"venue"
},
  "geometry": {"coordinates":[4.804646,52.373512],"type":"Point"}
}