{
  "type": "Feature",
  "properties": {
    "iso:country":"NL",
    "sg:address":"A Jacobsstr 25",
    "sg:city":"Coevorden",
    "sg:orig_category":"Administratie- En Boekhoudkantoren",
    "sg:phone":"+31 524 515 210",
    "sg:postcode":"7741 RS",
    "sg:province":"Drenthe",
    "wof:name":"Beukers",
    "wof:placetype":"venue"
},
  "geometry": {"coordinates":[6.731735,52.67149],"type":"Point"}
}