{
  "type": "Feature",
  "properties": {
    "iso:country":"NL",
    "sg:address":"Leidsegr 9",
    "sg:city":"Amsterdam",
    "sg:orig_category":"Makelaars En Adviseurs Onroerende Goederen",
    "sg:phone":"+31 20 420 0411",
    "sg:postcode":"1017 NA",
    "sg:province":"Noord-Holland",
    "wof:name":"Zanten, Van",
    "wof:placetype":"venue"
},
  "geometry": {"coordinates":[4.886283,52.367126],"type":"Point"}
}