{
  "type": "Feature",
  "properties": {
    "addr:full":"Wildervanckstraat 15 Wildervank Groningen 9648 LC",
    "addr:housenumber":"15",
    "addr:postcode":"9648 lc",
    "addr:street":"Wildervanckstraat",
    "iso:country":"NL",
    "sg:address":"Wildervanckstraat 15",
    "sg:city":"Wildervank",
    "sg:orig_category":"Pluimveehouderijen",
    "sg:phone":"+31 598 612 219",
    "sg:postcode":"9648 LC",
    "sg:province":"Groningen",
    "wof:name":"E.P. Oldenziel",
    "wof:placetype":"venue"
},
  "geometry": {"coordinates":[6.869049,53.083866],"type":"Point"}
}