{
  "type": "Feature",
  "properties": {
    "addr:full":"Nieuwstraat 4 Bruinisse Zeeland 4311 AN",
    "addr:housenumber":"4",
    "addr:postcode":"4311 an",
    "addr:street":"Nieuwstraat",
    "iso:country":"NL",
    "sg:address":"Nieuwstraat 4",
    "sg:city":"Bruinisse",
    "sg:classifiers":[
        {
            "category":"Travel",
            "subcategory":"Hotels & Motels",
            "type":"Entertainment"
        }
    ],
    "sg:phone":"+31 111 482 201",
    "sg:postcode":"4311 AN",
    "sg:province":"Zeeland",
    "wof:name":"Pension Neele",
    "wof:placetype":"venue"
},
  "geometry": {"coordinates":[4.094973,51.661648],"type":"Point"}
}