{
  "type": "Feature",
  "properties": {
    "addr:full":"Bentheimerstraat 8 Coevorden Drenthe 7741 JK",
    "addr:housenumber":"8",
    "addr:postcode":"7741 jk",
    "addr:street":"Bentheimerstraat",
    "iso:country":"NL",
    "sg:address":"Bentheimerstraat 8",
    "sg:city":"Coevorden",
    "sg:orig_category":"Boekenuitgeverijen",
    "sg:phone":"+31 524 516 186",
    "sg:postcode":"7741 JK",
    "sg:province":"Drenthe",
    "wof:name":"Boekhandel Heijink",
    "wof:placetype":"venue"
},
  "geometry": {"coordinates":[6.740488,52.660694],"type":"Point"}
}