{
  "type": "Feature",
  "properties": {
    "iso:country":"NL",
    "sg:address":"Het Wed 39",
    "sg:city":"Houten",
    "sg:orig_category":"Loodgieterswerk, Verwarming And Sanitaire Installaties",
    "sg:phone":"+31 30 637 6997",
    "sg:postcode":"3995 DS",
    "sg:province":"Utrecht",
    "wof:name":"B.E. Schrijvers",
    "wof:placetype":"venue"
},
  "geometry": {"coordinates":[5.168281,52.036213],"type":"Point"}
}