{
  "type": "Feature",
  "properties": {
    "addr:full":"Raadhuisstr 1A Beverwyk Noord-Holland 1941 EB",
    "addr:housenumber":"1a",
    "addr:postcode":"1941 eb",
    "addr:street":"Raadhuisstr",
    "iso:country":"NL",
    "sg:address":"Raadhuisstr 1A",
    "sg:city":"Beverwyk",
    "sg:orig_category":"Bloemen En Planten",
    "sg:phone":"+31 251 225 495",
    "sg:postcode":"1941 EB",
    "sg:province":"Noord-Holland",
    "wof:name":"Eeuwige Lente, De",
    "wof:placetype":"venue"
},
  "geometry": {"coordinates":[4.65626,52.480339],"type":"Point"}
}