{
  "type": "Feature",
  "properties": {
    "iso:country":"NL",
    "sg:address":"Katendrechtse Lagedijk 194",
    "sg:city":"Rotterdam",
    "sg:orig_category":"Kappers",
    "sg:phone":"+31 10 423 3579",
    "sg:postcode":"3081 ZE",
    "sg:province":"Zuid-Holland",
    "wof:name":"Kapsalon The Golden Hair",
    "wof:placetype":"venue"
},
  "geometry": {"coordinates":[4.48107481,51.8918571472],"type":"Point"}
}