{
  "type": "Feature",
  "properties": {
    "addr:full":"Noordmolenstraat 74 Rotterdam Zuid-Holland 3035 RM",
    "addr:housenumber":"74",
    "addr:postcode":"3035 rm",
    "addr:street":"Noordmolenstraat",
    "iso:country":"NL",
    "sg:address":"Noordmolenstraat 74",
    "sg:city":"Rotterdam",
    "sg:orig_category":"Discountwinkels",
    "sg:phone":"+31 10 243 0095",
    "sg:postcode":"3035 RM",
    "sg:province":"Zuid-Holland",
    "wof:name":"Zeeman Textielsupers Bv",
    "wof:placetype":"venue"
},
  "geometry": {"coordinates":[4.481303,51.931995],"type":"Point"}
}