{
  "type": "Feature",
  "properties": {
    "addr:full":"Antwerpsestrwg 174 Hoogerheide North Brabant 4631 RC",
    "addr:housenumber":"174",
    "addr:postcode":"4631 rc",
    "iso:country":"NL",
    "sg:address":"Antwerpsestrwg 174",
    "sg:city":"Hoogerheide",
    "sg:orig_category":"Banden - Fabrieken En Groothandel",
    "sg:phone":"+31 164 616 542",
    "sg:postcode":"4631 RC",
    "sg:province":"North Brabant",
    "wof:name":"Merband",
    "wof:placetype":"venue"
},
  "geometry": {"coordinates":[4.325936,51.421288],"type":"Point"}
}