{
  "type": "Feature",
  "properties": {
    "addr:full":"Postbus 414 Zeist Utrecht 3700 AK",
    "addr:housenumber":"414",
    "addr:postcode":"3700 ak",
    "addr:street":"Postbus",
    "iso:country":"NL",
    "sg:address":"Postbus 414",
    "sg:city":"Zeist",
    "sg:orig_category":"Voetbalverenigingen",
    "sg:phone":"+31 30 691 2286",
    "sg:postcode":"3700 AK",
    "sg:province":"Utrecht",
    "wof:name":"Saestum",
    "wof:placetype":"venue"
},
  "geometry": {"coordinates":[5.24387,52.08548],"type":"Point"}
}