{
  "type": "Feature",
  "properties": {
    "addr:full":"Duinroosln 1 Bentveld Noord-Holland 2116 TG",
    "addr:housenumber":"1",
    "addr:postcode":"2116 tg",
    "addr:street":"Duinroosln",
    "iso:country":"NL",
    "sg:address":"Duinroosln 1",
    "sg:city":"Bentveld",
    "sg:classifiers":[
        {
            "category":"Sports & Exercise",
            "subcategory":"Stables",
            "type":"Entertainment"
        }
    ],
    "sg:phone":"+31 23 524 3959",
    "sg:postcode":"2116 TG",
    "sg:province":"Noord-Holland",
    "sg:tags":[
        "maneges"
    ],
    "wof:name":"Naaldenhof, De",
    "wof:placetype":"venue"
},
  "geometry": {"coordinates":[4.575445,52.36541],"type":"Point"}
}