{
  "type": "Feature",
  "properties": {
    "addr:full":"Beukenstr 69 Goor Overijssel 7471 WC",
    "addr:housenumber":"69",
    "addr:postcode":"7471 wc",
    "addr:street":"Beukenstr",
    "iso:country":"NL",
    "sg:address":"Beukenstr 69",
    "sg:city":"Goor",
    "sg:orig_category":"Beeldende Kunstenaars",
    "sg:phone":"+31 547 273 112",
    "sg:postcode":"7471 WC",
    "sg:province":"Overijssel",
    "sg:website":"http://www.members.home.nl/robtenberge",
    "wof:name":"Berge, Rob Ten",
    "wof:placetype":"venue"
},
  "geometry": {"coordinates":[6.602378,52.235012],"type":"Point"}
}