{
  "type": "Feature",
  "properties": {
    "addr:full":"1213 Laan 1 Landgraaf Limburg 6373 EJ",
    "addr:housenumber":"1",
    "addr:postcode":"6373 ej",
    "addr:street":"Laan",
    "iso:country":"NL",
    "sg:address":"1213 Laan 1",
    "sg:city":"Landgraaf",
    "sg:orig_category":"Kinderopvang",
    "sg:phone":"+31 45 532 7961",
    "sg:postcode":"6373 EJ",
    "sg:province":"Limburg",
    "wof:name":"Humanitas, Sticht",
    "wof:placetype":"venue"
},
  "geometry": {"coordinates":[6.02683,50.91048],"type":"Point"}
}