{
  "type": "Feature",
  "properties": {
    "iso:country":"NL",
    "sg:address":"Duizendblad 15",
    "sg:city":"Culemborg",
    "sg:orig_category":"Verenigingen En Stichtingen",
    "sg:phone":"+31 345 518 569",
    "sg:postcode":"4102 KP",
    "sg:province":"Gelderland",
    "wof:name":"Ouders Van Meerlingen, Ned Ver Voor",
    "wof:placetype":"venue"
},
  "geometry": {"coordinates":[5.250369,51.956593],"type":"Point"}
}