{
  "type": "Feature",
  "properties": {
    "iso:country":"NL",
    "sg:address":"Oploostr 12",
    "sg:city":"Tilburg",
    "sg:orig_category":"Organisatiebureaus",
    "sg:phone":"+31 13 571 1259",
    "sg:postcode":"5045 SN",
    "sg:province":"Noord-Brabant",
    "wof:name":"Hutten, Leon",
    "wof:placetype":"venue"
},
  "geometry": {"coordinates":[4.9940881729,51.5824661255],"type":"Point"}
}