{
  "type": "Feature",
  "properties": {
    "addr:full":"Dr H J V Mookln 1 Ryswyk Zh Zuid-Holland 2286 BA",
    "addr:housenumber":"1",
    "addr:postcode":"2286 ba",
    "addr:street":"Dr;J;Mookln",
    "iso:country":"NL",
    "sg:address":"Dr H J V Mookln 1",
    "sg:city":"Ryswyk Zh",
    "sg:orig_category":"Peuterspeelzalen",
    "sg:phone":"+31 70 394 5074",
    "sg:postcode":"2286 BA",
    "sg:province":"Zuid-Holland",
    "wof:name":"Pinkeltje",
    "wof:placetype":"venue"
},
  "geometry": {"coordinates":[4.32436,52.037251],"type":"Point"}
}