{
  "type": "Feature",
  "properties": {
    "iso:country":"NL",
    "sg:address":"Burg Geuljansln 19",
    "sg:city":"Roermond",
    "sg:orig_category":"Adviesbureaus Bedrijfsorganisatie",
    "sg:phone":"+31 475 318 454",
    "sg:postcode":"6041 NA",
    "sg:province":"Limburg",
    "wof:name":"Marx",
    "wof:placetype":"venue"
},
  "geometry": {"coordinates":[5.9788999557,51.1824493408],"type":"Point"}
}