{
  "type": "Feature",
  "properties": {
    "addr:full":"Burg Geuljansln 19 Roermond Limburg 6041 NA",
    "addr:housenumber":"19",
    "addr:postcode":"6041 na",
    "addr:street":"Burg",
    "iso:country":"NL",
    "sg:address":"Burg Geuljansln 19",
    "sg:city":"Roermond",
    "sg:orig_category":"Adviesbureaus Bedrijfsorganisatie",
    "sg:phone":"+31 475 318 454",
    "sg:postcode":"6041 NA",
    "sg:province":"Limburg",
    "wof:name":"Marx",
    "wof:placetype":"venue"
},
  "geometry": {"coordinates":[5.9788999557,51.1824493408],"type":"Point"}
}