{
  "type": "Feature",
  "properties": {
    "addr:full":"Willemsparkweg 31 Amsterdam Noord-Holland 1071 GP",
    "addr:housenumber":"31",
    "addr:postcode":"1071 gp",
    "addr:street":"Willemsparkweg",
    "iso:country":"NL",
    "sg:address":"Willemsparkweg 31",
    "sg:city":"Amsterdam",
    "sg:orig_category":"Advocaten And Juridische Adviseurs",
    "sg:phone":"+31 20 676 6690",
    "sg:postcode":"1071 GP",
    "sg:province":"Noord-Holland",
    "wof:name":"Van De Woude De Graaf Advocaten",
    "wof:placetype":"venue"
},
  "geometry": {"coordinates":[4.876883,52.357536],"type":"Point"}
}