{
  "type": "Feature",
  "properties": {
    "addr:full":"Ruysstr 31 Panningen Limburg 5981 CL",
    "addr:housenumber":"31",
    "addr:postcode":"5981",
    "addr:street":"Ruysstr",
    "iso:country":"NL",
    "sg:address":"Ruysstr 31",
    "sg:city":"Panningen",
    "sg:orig_category":"Werving En Selectie",
    "sg:phone":"+31 77 307 5669",
    "sg:postcode":"5981 CL",
    "sg:province":"Limburg",
    "wof:name":"Wetsteyn",
    "wof:placetype":"venue"
},
  "geometry": {"coordinates":[5.9851341248,51.3275604248],"type":"Point"}
}