{
  "type": "Feature",
  "properties": {
    "addr:full":"Vaart Zz 61 Appelscha Provincie Friesland 8426 AG",
    "addr:housenumber":"61",
    "addr:postcode":"8426",
    "addr:street":"Vaart Zz;Provincie Friesland",
    "iso:country":"NL",
    "sg:address":"Vaart Zz 61",
    "sg:city":"Appelscha",
    "sg:orig_category":"Kaas",
    "sg:phone":"+31 516 431 276",
    "sg:postcode":"8426 AG",
    "sg:province":"Provincie Friesland",
    "wof:name":"Markdammer Bv",
    "wof:placetype":"venue"
},
  "geometry": {"coordinates":[6.3564138412,52.954158783],"type":"Point"}
}