{
  "type": "Feature",
  "properties": {
    "iso:country":"NL",
    "sg:address":"Hommelstr 73",
    "sg:city":"Arnhem",
    "sg:orig_category":"Satellietontvangst- En Antenne-Installaties",
    "sg:phone":"+31 26 351 7956",
    "sg:postcode":"6828 AJ",
    "sg:province":"Gelderland",
    "wof:name":"Hupra Int Bv",
    "wof:placetype":"venue"
},
  "geometry": {"coordinates":[5.914039,51.985409],"type":"Point"}
}