{
  "type": "Feature",
  "properties": {
    "addr:full":"Voorzoom 6 Wateringen Zuid-Holland 2291 MV",
    "addr:housenumber":"6",
    "addr:postcode":"2291 mv",
    "addr:street":"Voorzoom",
    "iso:country":"NL",
    "sg:address":"Voorzoom 6",
    "sg:city":"Wateringen",
    "sg:orig_category":"Kappers",
    "sg:phone":"+31 6 26176367",
    "sg:postcode":"2291 MV",
    "sg:province":"Zuid-Holland",
    "wof:name":"2 Sizzers",
    "wof:placetype":"venue"
},
  "geometry": {"coordinates":[4.2730908394,52.0219154358],"type":"Point"}
}