{
  "type": "Feature",
  "properties": {
    "addr:full":"Hoofdstrata 41 Noordwijk Zh Zuid-Holland 2202 ET",
    "addr:housenumber":"41",
    "addr:postcode":"2202 et",
    "addr:street":"Hoofdstrata",
    "iso:country":"NL",
    "sg:address":"Hoofdstrata 41",
    "sg:city":"Noordwijk Zh",
    "sg:orig_category":"Fotolaboratoria",
    "sg:phone":"+31 71 367 2222",
    "sg:postcode":"2202 ET",
    "sg:province":"Zuid-Holland",
    "wof:name":"Hema",
    "wof:placetype":"venue"
},
  "geometry": {"coordinates":[4.435614,52.248837],"type":"Point"}
}