{
  "type": "Feature",
  "properties": {
    "addr:full":"Eendrachtswg 10 Tholen Zeeland 4691 EK",
    "addr:housenumber":"10",
    "addr:postcode":"4691 ek",
    "addr:street":"Eendrachtswg",
    "iso:country":"NL",
    "sg:address":"Eendrachtswg 10",
    "sg:city":"Tholen",
    "sg:orig_category":"Bloemen En Planten",
    "sg:phone":"+31 166 602 662",
    "sg:postcode":"4691 EK",
    "sg:province":"Zeeland",
    "wof:name":"Berge Vof, Van De",
    "wof:placetype":"venue"
},
  "geometry": {"coordinates":[4.223721,51.533295],"type":"Point"}
}