{
  "type": "Feature",
  "properties": {
    "addr:full":"Westpln 9 Rotterdam Zuid-Holland 3016 BM",
    "addr:housenumber":"9",
    "addr:postcode":"3016 bm",
    "addr:street":"Westpln",
    "iso:country":"NL",
    "sg:address":"Westpln 9",
    "sg:city":"Rotterdam",
    "sg:orig_category":"Ambassades/Consulaten",
    "sg:phone":"+31 10 436 5600",
    "sg:postcode":"3016 BM",
    "sg:province":"Zuid-Holland",
    "wof:name":"Griekenland Consulaat Van",
    "wof:placetype":"venue"
},
  "geometry": {"coordinates":[4.478059,51.908882],"type":"Point"}
}