{
  "type": "Feature",
  "properties": {
    "addr:full":"De Bloemen 71A Castricum North Holland 1902 GT",
    "addr:housenumber":"71a",
    "addr:postcode":"1902 gt",
    "addr:street":"De Bloemen",
    "iso:country":"NL",
    "sg:address":"De Bloemen 71A",
    "sg:city":"Castricum",
    "sg:orig_category":"Sportverenigingen En Ontspannings- Verenigingen",
    "sg:phone":"+31 251 652 804",
    "sg:postcode":"1902 GT",
    "sg:province":"North Holland",
    "wof:name":"Footballclub Castricum",
    "wof:placetype":"venue"
},
  "geometry": {"coordinates":[4.684238,52.551228],"type":"Point"}
}