{
  "type": "Feature",
  "properties": {
    "addr:full":"Scharlo 11 Waspik North Brabant 5165 NG",
    "addr:housenumber":"11",
    "addr:postcode":"5165 ng",
    "addr:street":"Scharlo",
    "iso:country":"NL",
    "sg:address":"Scharlo 11",
    "sg:city":"Waspik",
    "sg:orig_category":"Parketvloeren",
    "sg:phone":"+31 416 316 170",
    "sg:postcode":"5165 NG",
    "sg:province":"North Brabant",
    "wof:name":"Pardio",
    "wof:placetype":"venue"
},
  "geometry": {"coordinates":[4.943649,51.69545],"type":"Point"}
}