{
  "type": "Feature",
  "properties": {
    "addr:full":"Binnenban 42 Hoogvliet Rt South Holland 3191 CH",
    "addr:housenumber":"42",
    "addr:postcode":"3191",
    "addr:street":"Binnenban;Rt South",
    "iso:country":"NL",
    "sg:address":"Binnenban 42",
    "sg:city":"Hoogvliet Rt",
    "sg:orig_category":"Zoetwaren - Winkels",
    "sg:phone":"+31 10 416 6114",
    "sg:postcode":"3191 CH",
    "sg:province":"South Holland",
    "wof:name":"Jamin Bv",
    "wof:placetype":"venue"
},
  "geometry": {"coordinates":[4.354575,51.866177],"type":"Point"}
}