{
  "type": "Feature",
  "properties": {
    "iso:country":"NL",
    "sg:address":"Molenstraat 17",
    "sg:city":"Oosterhout Nb",
    "sg:orig_category":"Huizensloop And Bouwrijp Maken",
    "sg:phone":"+31 162 437 529",
    "sg:postcode":"4902 NM",
    "sg:province":"Noord-Brabant",
    "wof:name":"E.J. De Wijs",
    "wof:placetype":"venue"
},
  "geometry": {"coordinates":[4.848458,51.6409],"type":"Point"}
}