{
  "type": "Feature",
  "properties": {
    "addr:full":"Roerdompwg 30 Oud Beijerland Zuid-Holland 3263 AJ",
    "addr:housenumber":"30",
    "addr:postcode":"3263 aj",
    "addr:street":"Roerdompwg;Oud Beijerland",
    "iso:country":"NL",
    "sg:address":"Roerdompwg 30",
    "sg:city":"Oud Beijerland",
    "sg:orig_category":"Fotojournalisten Freelance",
    "sg:phone":"+31 186 612 437",
    "sg:postcode":"3263 AJ",
    "sg:province":"Zuid-Holland",
    "wof:name":"Geleijnse, R",
    "wof:placetype":"venue"
},
  "geometry": {"coordinates":[4.393584,51.82349],"type":"Point"}
}