{
  "type": "Feature",
  "properties": {
    "addr:full":"De Lairessestr 154 Amsterdam Noord-Holland 1075 HL",
    "addr:housenumber":"154",
    "addr:postcode":"1075 hl",
    "iso:country":"NL",
    "sg:address":"De Lairessestr 154",
    "sg:city":"Amsterdam",
    "sg:orig_category":"Verzekeringen - Verzekeringskantoren",
    "sg:phone":"+31 20 645 3755",
    "sg:postcode":"1075 HL",
    "sg:province":"Noord-Holland",
    "wof:name":"Donkervoort Bv, F",
    "wof:placetype":"venue"
},
  "geometry": {"coordinates":[4.86758,52.352623],"type":"Point"}
}