{
  "type": "Feature",
  "properties": {
    "iso:country":"NL",
    "sg:address":"Gertrudisstr 41",
    "sg:city":"Breda",
    "sg:classifiers":[
        {
            "category":"Personal",
            "subcategory":"Nail Salon",
            "type":"Services"
        }
    ],
    "sg:phone":"+31 76 565 0922",
    "sg:postcode":"4834 VE",
    "sg:province":"North Brabant",
    "sg:tags":[
        "pedicure"
    ],
    "wof:name":"Pauwels, M",
    "wof:placetype":"venue"
},
  "geometry": {"coordinates":[4.796333,51.566196],"type":"Point"}
}