{
  "type": "Feature",
  "properties": {
    "addr:full":"V Oeststr 29 Swalmen Limburg 6071 EA",
    "addr:housenumber":"29",
    "addr:postcode":"6071 ea",
    "iso:country":"NL",
    "sg:address":"V Oeststr 29",
    "sg:city":"Swalmen",
    "sg:orig_category":"Geluidsinstallaties - Verhuur",
    "sg:phone":"+31 475 504 210",
    "sg:postcode":"6071 EA",
    "sg:province":"Limburg",
    "wof:name":"Tjs",
    "wof:placetype":"venue"
},
  "geometry": {"coordinates":[6.045765,51.213768],"type":"Point"}
}