{
  "type": "Feature",
  "properties": {
    "iso:country":"NL",
    "sg:address":"Marktplein 69",
    "sg:city":"Broek Op Langedijk",
    "sg:orig_category":"Schoenen",
    "sg:phone":"+31 226 341 371",
    "sg:postcode":"1721 CK",
    "sg:province":"Noord-Holland",
    "wof:name":"Nelson Schoenen Bv",
    "wof:placetype":"venue"
},
  "geometry": {"coordinates":[4.803623,52.678841],"type":"Point"}
}