{
  "type": "Feature",
  "properties": {
    "addr:full":"Bostonweg 47 Almere NL. 1334  K",
    "addr:housenumber":"47;1334 k",
    "addr:street":"Bostonweg;Nl.",
    "iso:country":"NL",
    "sg:address":"Bostonweg 47",
    "sg:city":"Almere",
    "sg:orig_category":"Meubelzaken, Woning- And Keukeninrichting",
    "sg:phone":"+31 36 532 3628",
    "sg:postcode":"1334  K",
    "sg:province":"NL.",
    "wof:name":"N.T.U. Almere",
    "wof:placetype":"venue"
},
  "geometry": {"coordinates":[5.273294,52.393917],"type":"Point"}
}