{
  "type": "Feature",
  "properties": {
    "addr:full":"Vliexstraat 28 Simpelveld Limburg 6369 HH",
    "addr:housenumber":"28",
    "addr:postcode":"6369 hh",
    "addr:street":"Vliexstraat",
    "iso:country":"NL",
    "sg:address":"Vliexstraat 28",
    "sg:city":"Simpelveld",
    "sg:orig_category":"Paramedische Behandelingen",
    "sg:phone":"+31 45 544 4259",
    "sg:postcode":"6369 HH",
    "sg:province":"Limburg",
    "wof:name":"J Hollands",
    "wof:placetype":"venue"
},
  "geometry": {"coordinates":[5.993062,50.839836],"type":"Point"}
}