{
  "type": "Feature",
  "properties": {
    "addr:full":"Rondwg 7 Leermens Groningen 9912 PA",
    "addr:housenumber":"7",
    "addr:postcode":"9912 pa",
    "addr:street":"Rondwg",
    "iso:country":"NL",
    "sg:address":"Rondwg 7",
    "sg:city":"Leermens",
    "sg:orig_category":"Administratie- En Boekhoudkantoren",
    "sg:phone":"+31 596 581 937",
    "sg:postcode":"9912 PA",
    "sg:province":"Groningen",
    "wof:name":"Kwadraat, M",
    "wof:placetype":"venue"
},
  "geometry": {"coordinates":[6.795344,53.346691],"type":"Point"}
}