{
  "type": "Feature",
  "properties": {
    "addr:full":"Waalresewg 17 Valkenswaard Noord-Brabant 5554 HA",
    "addr:housenumber":"17",
    "addr:postcode":"5554 ha",
    "addr:street":"Waalresewg",
    "iso:country":"NL",
    "sg:address":"Waalresewg 17",
    "sg:city":"Valkenswaard",
    "sg:orig_category":"Koeltechniek",
    "sg:phone":"+31 40 208 9373",
    "sg:postcode":"5554 HA",
    "sg:province":"Noord-Brabant",
    "sg:website":"http://www.yorkref.com",
    "wof:name":"York",
    "wof:placetype":"venue"
},
  "geometry": {"coordinates":[5.457215,51.351959],"type":"Point"}
}