{
  "type": "Feature",
  "properties": {
    "addr:full":"Gerststraat 42 Enschede Overijssel 7545 GS",
    "addr:housenumber":"42",
    "addr:postcode":"7545 gs",
    "addr:street":"Gerststraat",
    "iso:country":"NL",
    "sg:address":"Gerststraat 42",
    "sg:city":"Enschede",
    "sg:orig_category":"Diverse Opleidingen And Onderwijs",
    "sg:phone":"+31 53 434 1385",
    "sg:postcode":"7545 GS",
    "sg:province":"Overijssel",
    "wof:name":"First Aid Team Enschede (Fate)",
    "wof:placetype":"venue"
},
  "geometry": {"coordinates":[6.870114,52.208836],"type":"Point"}
}