{
  "type": "Feature",
  "properties": {
    "addr:full":"Den Deel 5 Made Noord-Brabant 4921 JH",
    "addr:housenumber":"5",
    "addr:postcode":"4921 jh",
    "addr:street":"Den Deel",
    "iso:country":"NL",
    "sg:address":"Den Deel 5",
    "sg:city":"Made",
    "sg:classifiers":[
        {
            "category":"Fast Food",
            "type":"Food & Drink"
        }
    ],
    "sg:phone":"+31 162 682 196",
    "sg:postcode":"4921 JH",
    "sg:province":"Noord-Brabant",
    "sg:tags":[
        "afhaal",
        "restaurant"
    ],
    "wof:name":"Chin Ind Restaurant Lin Wah",
    "wof:placetype":"venue"
},
  "geometry": {"coordinates":[-120.101364,36.829536],"type":"Point"}
}