{
  "type": "Feature",
  "properties": {
    "addr:full":"St Rochuspln 9 Berg En Terblyt Limburg 6325 AZ",
    "addr:housenumber":"9",
    "addr:postcode":"6325",
    "addr:street":"Berg",
    "iso:country":"NL",
    "sg:address":"St Rochuspln 9",
    "sg:city":"Berg En Terblyt",
    "sg:orig_category":"Kappers",
    "sg:phone":"+31 43 604 0400",
    "sg:postcode":"6325 AZ",
    "sg:province":"Limburg",
    "wof:name":"Hub",
    "wof:placetype":"venue"
},
  "geometry": {"coordinates":[5.8093819618,50.8580093384],"type":"Point"}
}