{
  "type": "Feature",
  "properties": {
    "iso:country":"NL",
    "sg:address":"President Kennedystraat 40",
    "sg:city":"Margraten",
    "sg:orig_category":"Sportcentra",
    "sg:phone":"+31 43 458 1795",
    "sg:postcode":"6269 CC",
    "sg:province":"Limburg",
    "wof:name":"Sportpark Margraten",
    "wof:placetype":"venue"
},
  "geometry": {"coordinates":[5.818375,50.824142],"type":"Point"}
}