{
  "type": "Feature",
  "properties": {
    "addr:full":"Ooststraat 15 Kortgene Zeeland 4484 CN",
    "addr:housenumber":"15",
    "addr:postcode":"4484 cn",
    "addr:street":"Ooststraat",
    "iso:country":"NL",
    "sg:address":"Ooststraat 15",
    "sg:city":"Kortgene",
    "sg:orig_category":"Artsen And Specialisten",
    "sg:phone":"+31 113 301 319",
    "sg:postcode":"4484 CN",
    "sg:province":"Zeeland",
    "wof:name":"J.A. Kersseboom Huisarts",
    "wof:placetype":"venue"
},
  "geometry": {"coordinates":[3.803284,51.557499],"type":"Point"}
}