{
  "type": "Feature",
  "properties": {
    "addr:full":"Anklaarsewg 95 Apeldoorn Gelderland 7317 AS",
    "addr:housenumber":"95",
    "addr:postcode":"7317 as",
    "addr:street":"Anklaarsewg;Gelderland",
    "iso:country":"NL",
    "sg:address":"Anklaarsewg 95",
    "sg:city":"Apeldoorn",
    "sg:orig_category":"Scholen: Hoger Beroepsonderwijs",
    "sg:phone":"+31 55 578 6960",
    "sg:postcode":"7317 AS",
    "sg:province":"Gelderland",
    "sg:website":"http://www.vapa.nl",
    "wof:name":"Vapa",
    "wof:placetype":"venue"
},
  "geometry": {"coordinates":[5.9708,52.235088],"type":"Point"}
}