{
  "type": "Feature",
  "properties": {
    "addr:full":"Westerstr 26 Amsterdam Noord-Holland 1015 MK",
    "addr:housenumber":"26",
    "addr:postcode":"1015",
    "addr:street":"Westerstr",
    "iso:country":"NL",
    "sg:address":"Westerstr 26",
    "sg:city":"Amsterdam",
    "sg:orig_category":"Wasserijen",
    "sg:phone":"+31 20 627 9888",
    "sg:postcode":"1015 MK",
    "sg:province":"Noord-Holland",
    "wof:name":"Clean Brothers",
    "wof:placetype":"venue"
},
  "geometry": {"coordinates":[4.8854689598,52.378993988],"type":"Point"}
}