{
  "type": "Feature",
  "properties": {
    "addr:full":"Pastoorstraat 10 Naarden Noord-Holland 1411 SE",
    "addr:housenumber":"10;1411",
    "addr:street":"Pastoorstraat;Se",
    "iso:country":"NL",
    "sg:address":"Pastoorstraat 10",
    "sg:city":"Naarden",
    "sg:orig_category":"Fotostudio'S And Fotografen",
    "sg:phone":"+31 35 695 3154",
    "sg:postcode":"1411 SE",
    "sg:province":"Noord-Holland",
    "wof:name":"E.J. Geniets",
    "wof:placetype":"venue"
},
  "geometry": {"coordinates":[5.16122,52.295757],"type":"Point"}
}