{
  "type": "Feature",
  "properties": {
    "iso:country":"NL",
    "sg:address":"Meuleveldweg 2",
    "sg:city":"Zandhuizen",
    "sg:orig_category":"Goederenvervoer Over De Weg",
    "sg:phone":"+31 561 433 204",
    "sg:postcode":"8389 TD",
    "sg:province":"Friesland",
    "wof:name":"Dako Olderberkoop Bv",
    "wof:placetype":"venue"
},
  "geometry": {"coordinates":[6.164261,52.913631],"type":"Point"}
}