{
  "type": "Feature",
  "properties": {
    "addr:full":"Houtenend 34 Dordrecht Zuid-Holland 3317 MK",
    "addr:housenumber":"34",
    "addr:postcode":"3317",
    "addr:street":"Houtenend",
    "iso:country":"NL",
    "sg:address":"Houtenend 34",
    "sg:city":"Dordrecht",
    "sg:orig_category":"Onderhoudswerken",
    "sg:phone":"+31 6 27533849",
    "sg:postcode":"3317 MK",
    "sg:province":"Zuid-Holland",
    "wof:name":"Kooijman",
    "wof:placetype":"venue"
},
  "geometry": {"coordinates":[4.655328,51.783848],"type":"Point"}
}