{
  "type": "Feature",
  "properties": {
    "iso:country":"NL",
    "sg:address":"Houtenend 34",
    "sg:city":"Dordrecht",
    "sg:orig_category":"Onderhoudswerken",
    "sg:phone":"+31 6 27533849",
    "sg:postcode":"3317 MK",
    "sg:province":"Zuid-Holland",
    "wof:name":"Kooijman",
    "wof:placetype":"venue"
},
  "geometry": {"coordinates":[4.655328,51.783848],"type":"Point"}
}