{
  "type": "Feature",
  "properties": {
    "addr:full":"Herenweg 22 Warmond Zuid-Holland 2361 ER",
    "addr:housenumber":"22",
    "addr:postcode":"2361 er",
    "addr:street":"Herenweg",
    "iso:country":"NL",
    "sg:address":"Herenweg 22",
    "sg:city":"Warmond",
    "sg:orig_category":"Bloemen And Planten Gh",
    "sg:phone":"+31 71 301 0339",
    "sg:postcode":"2361 ER",
    "sg:province":"Zuid-Holland",
    "wof:name":"M.G. Van Winsen",
    "wof:placetype":"venue"
},
  "geometry": {"coordinates":[4.497423,52.193607],"type":"Point"}
}