{
  "type": "Feature",
  "properties": {
    "addr:full":"Linnaeusparkwg 142 Amsterdam North Holland 1098 EL",
    "addr:housenumber":"142;1098",
    "addr:postcode":"el",
    "iso:country":"NL",
    "sg:address":"Linnaeusparkwg 142",
    "sg:city":"Amsterdam",
    "sg:orig_category":"Fietsen En Bromfietsen",
    "sg:phone":"+31 20 692 8166",
    "sg:postcode":"1098 EL",
    "sg:province":"North Holland",
    "wof:name":"Bvd",
    "wof:placetype":"venue"
},
  "geometry": {"coordinates":[4.936911,52.352043],"type":"Point"}
}