{
  "type": "Feature",
  "properties": {
    "addr:full":"Hoeksekade 64 Bergschenhoek Zuid-Holland 2661 GL",
    "addr:housenumber":"64",
    "addr:postcode":"2661 gl",
    "addr:street":"Hoeksekade",
    "iso:country":"NL",
    "sg:address":"Hoeksekade 64",
    "sg:city":"Bergschenhoek",
    "sg:orig_category":"Schilderwerk",
    "sg:phone":"+31 79 316 5196",
    "sg:postcode":"2661 GL",
    "sg:province":"Zuid-Holland",
    "wof:name":"Wandafwerkingsbedrijf P J De Wit",
    "wof:placetype":"venue"
},
  "geometry": {"coordinates":[4.510291,51.984768],"type":"Point"}
}