{
  "type": "Feature",
  "properties": {
    "addr:full":"Rivium 2E Str 11 Capelle Ad Yssel Zuid-Holland 2909 LG",
    "addr:housenumber":"11",
    "addr:postcode":"2909 lg",
    "addr:street":"Rivium 2E Str",
    "iso:country":"NL",
    "sg:address":"Rivium 2E Str 11",
    "sg:city":"Capelle Ad Yssel",
    "sg:orig_category":"Werving En Selectie",
    "sg:phone":"+31 10 501 1867",
    "sg:postcode":"2909 LG",
    "sg:province":"Zuid-Holland",
    "wof:name":"Dsg Network",
    "wof:placetype":"venue"
},
  "geometry": {"coordinates":[4.5454740524,51.9113311768],"type":"Point"}
}