{
  "type": "Feature",
  "properties": {
    "iso:country":"NL",
    "sg:address":"Molenvaart 261",
    "sg:city":"Anna Paulowna",
    "sg:orig_category":"Verzekeringen - Verzekeringskantoren",
    "sg:phone":"+31 223 521 750",
    "sg:postcode":"1761 AE",
    "sg:province":"Noord-Holland",
    "sg:website":"http://www.phverheul.nl",
    "wof:name":"Verheul Bv, P H",
    "wof:placetype":"venue"
},
  "geometry": {"coordinates":[4.811359,52.869621],"type":"Point"}
}