{
  "type": "Feature",
  "properties": {
    "addr:full":"Voltastr 32 Doetinchem Gelderland 7006 RV",
    "addr:housenumber":"32",
    "addr:postcode":"7006 rv",
    "addr:street":"Voltastr;Gelderland",
    "iso:country":"NL",
    "sg:address":"Voltastr 32",
    "sg:city":"Doetinchem",
    "sg:orig_category":"Autoschade- Herstelbedrijven",
    "sg:phone":"+31 314 340 238",
    "sg:postcode":"7006 RV",
    "sg:province":"Gelderland",
    "wof:name":"Holtkamp Bv",
    "wof:placetype":"venue"
},
  "geometry": {"coordinates":[6.259911,51.971825],"type":"Point"}
}