{
  "type": "Feature",
  "properties": {
    "addr:full":"Terborgseweg 25 Doetinchem Gelderland 7001 GM",
    "addr:housenumber":"25",
    "addr:postcode":"7001 gm",
    "addr:street":"Terborgseweg;Gelderland",
    "iso:country":"NL",
    "sg:address":"Terborgseweg 25",
    "sg:city":"Doetinchem",
    "sg:classifiers":[
        {
            "category":"Professional",
            "subcategory":"Accounting & Tax Preparation",
            "type":"Services"
        }
    ],
    "sg:phone":"+31 314 369 111",
    "sg:postcode":"7001 GM",
    "sg:province":"Gelderland",
    "sg:tags":[
        "accountant"
    ],
    "wof:name":"Stolwijk Van De Rakt",
    "wof:placetype":"venue"
},
  "geometry": {"coordinates":[6.293132,51.961742],"type":"Point"}
}