{
  "type": "Feature",
  "properties": {
    "iso:country":"NL",
    "sg:address":"Hoofdweg 155",
    "sg:city":"De Kwakel",
    "sg:orig_category":"Bloemen And Planten",
    "sg:phone":"+31 297 344 641",
    "sg:postcode":"1424 PE",
    "sg:province":"North Holland",
    "wof:name":"Toon Kuipers Bv",
    "wof:placetype":"venue"
},
  "geometry": {"coordinates":[4.773697,52.241154],"type":"Point"}
}