{
  "type": "Feature",
  "properties": {
    "addr:full":"Hoofdweg 155 De Kwakel North Holland 1424 PE",
    "addr:housenumber":"155",
    "addr:postcode":"1424 pe",
    "addr:street":"Hoofdweg",
    "iso:country":"NL",
    "sg:address":"Hoofdweg 155",
    "sg:city":"De Kwakel",
    "sg:orig_category":"Bloemen And Planten",
    "sg:phone":"+31 297 344 641",
    "sg:postcode":"1424 PE",
    "sg:province":"North Holland",
    "wof:name":"Toon Kuipers Bv",
    "wof:placetype":"venue"
},
  "geometry": {"coordinates":[4.773697,52.241154],"type":"Point"}
}