{
  "type": "Feature",
  "properties": {
    "iso:country":"NL",
    "sg:address":"Dokter Van Stratenweg 752",
    "sg:city":"Gorinchem",
    "sg:orig_category":"Onderhoud And Reparatie Kantoorapparatuur",
    "sg:phone":"+31 183 628 349",
    "sg:postcode":"4205 LZ",
    "sg:province":"South Holland",
    "wof:name":"Megaworks",
    "wof:placetype":"venue"
},
  "geometry": {"coordinates":[4.953323,51.8438],"type":"Point"}
}