{
  "type": "Feature",
  "properties": {
    "addr:full":"Laat 88+119 , (Centrum) Alkmaar North Holland 1811 EK",
    "addr:housenumber":"88 + 119",
    "addr:postcode":"1811 ek",
    "addr:street":"Laat",
    "iso:country":"NL",
    "sg:address":"Laat 88+119 , (Centrum)",
    "sg:city":"Alkmaar",
    "sg:orig_category":"Kampeerartikelen",
    "sg:phone":"+31 72 511 2278",
    "sg:postcode":"1811 EK",
    "sg:province":"North Holland",
    "wof:name":"Roobeek",
    "wof:placetype":"venue"
},
  "geometry": {"coordinates":[4.7495961189,52.6296806335],"type":"Point"}
}