{
  "type": "Feature",
  "properties": {
    "addr:full":"Veerwg 14 Beesd Gelderland 4153 AS",
    "addr:housenumber":"14",
    "addr:postcode":"4153 as",
    "addr:street":"Veerwg;Gelderland",
    "iso:country":"NL",
    "sg:address":"Veerwg 14",
    "sg:city":"Beesd",
    "sg:orig_category":"Muziekinstrumenten - Reparatie En Onderhoud",
    "sg:phone":"+31 345 684 868",
    "sg:postcode":"4153 AS",
    "sg:province":"Gelderland",
    "wof:name":"Stolk Bv",
    "wof:placetype":"venue"
},
  "geometry": {"coordinates":[5.186788,51.882732],"type":"Point"}
}