{
  "type": "Feature",
  "properties": {
    "addr:full":"Guishof 1 Zaandijk Noord-Holland 1544 TA",
    "addr:housenumber":"1",
    "addr:postcode":"1544 ta",
    "addr:street":"Guishof",
    "iso:country":"NL",
    "sg:address":"Guishof 1",
    "sg:city":"Zaandijk",
    "sg:orig_category":"Politie",
    "sg:phone":"+31 900 8844",
    "sg:postcode":"1544 TA",
    "sg:province":"Noord-Holland",
    "wof:name":"Regiopolitie Zaanstreek Waterland",
    "wof:placetype":"venue"
},
  "geometry": {"coordinates":[4.796681,52.469204],"type":"Point"}
}