{
  "type": "Feature",
  "properties": {
    "iso:country":"NL",
    "sg:address":"Dorpsstraat 43",
    "sg:city":"Renswoude",
    "sg:orig_category":"Metaalbekleding And -Behandeling",
    "sg:phone":"+31 318 573 591",
    "sg:postcode":"3927 BB",
    "sg:province":"Utrecht",
    "wof:name":"D.J. Ten Voorde",
    "wof:placetype":"venue"
},
  "geometry": {"coordinates":[5.541418,52.073196],"type":"Point"}
}