{
  "type": "Feature",
  "properties": {
    "addr:full":"Langbroekerdk 7B Driebergen Rysenb Utrecht 3972 NB",
    "addr:housenumber":"7b",
    "addr:postcode":"3972 nb",
    "addr:street":"Langbroekerdk;Rysenb",
    "iso:country":"NL",
    "sg:address":"Langbroekerdk 7B",
    "sg:city":"Driebergen Rysenb",
    "sg:classifiers":[
        {
            "category":"Home & Garden",
            "subcategory":"Garden Supply",
            "type":"Retail Goods"
        }
    ],
    "sg:phone":"+31 343 516 735",
    "sg:postcode":"3972 NB",
    "sg:province":"Utrecht",
    "sg:tags":[
        "zand",
        "en",
        "grind"
    ],
    "wof:name":"Baaren Transport Bv, Van",
    "wof:placetype":"venue"
},
  "geometry": {"coordinates":[5.252016,52.045338],"type":"Point"}
}