{
  "type": "Feature",
  "properties": {
    "iso:country":"NL",
    "sg:address":"Vliertwyksestr 38A",
    "sg:city":"Rosmalen",
    "sg:orig_category":"Honden- En Kattentrimsalons",
    "sg:phone":"+31 73 521 8323",
    "sg:postcode":"5249 RJ",
    "sg:province":"Noord-Brabant",
    "wof:name":"Kwispel",
    "wof:placetype":"venue"
},
  "geometry": {"coordinates":[5.402438,51.729393],"type":"Point"}
}