{
  "type": "Feature",
  "properties": {
    "addr:full":"Emsterwg 90 Vaassen Gelderland 8171 PK",
    "addr:housenumber":"90",
    "addr:postcode":"8171 pk",
    "addr:street":"Emsterwg;Gelderland",
    "iso:country":"NL",
    "sg:address":"Emsterwg 90",
    "sg:city":"Vaassen",
    "sg:orig_category":"Woningstoffeerders",
    "sg:phone":"+31 578 571 296",
    "sg:postcode":"8171 PK",
    "sg:province":"Gelderland",
    "wof:name":"Ruite, Frits",
    "wof:placetype":"venue"
},
  "geometry": {"coordinates":[5.9748940468,52.2977790833],"type":"Point"}
}