{
  "type": "Feature",
  "properties": {
    "iso:country":"NL",
    "sg:address":"Emsterwg 90",
    "sg:city":"Vaassen",
    "sg:orig_category":"Woningstoffeerders",
    "sg:phone":"+31 578 571 296",
    "sg:postcode":"8171 PK",
    "sg:province":"Gelderland",
    "wof:name":"Ruite, Frits",
    "wof:placetype":"venue"
},
  "geometry": {"coordinates":[5.9748940468,52.2977790833],"type":"Point"}
}