{
  "type": "Feature",
  "properties": {
    "iso:country":"NL",
    "sg:address":"Ullerberglaan 23",
    "sg:city":"Eindhoven",
    "sg:orig_category":"Metaalwerken",
    "sg:phone":"+31 40 241 6232",
    "sg:postcode":"5628 EG",
    "sg:province":"North Brabant",
    "wof:name":"Muller",
    "wof:placetype":"venue"
},
  "geometry": {"coordinates":[5.466744,51.482876],"type":"Point"}
}