{
  "type": "Feature",
  "properties": {
    "addr:full":"Erasstr 73 Kaatsheuvel Noord-Brabant 5171 VG",
    "addr:housenumber":"73",
    "addr:postcode":"5171 vg",
    "addr:street":"Erasstr",
    "iso:country":"NL",
    "sg:address":"Erasstr 73",
    "sg:city":"Kaatsheuvel",
    "sg:orig_category":"Zonweringen",
    "sg:phone":"+31 416 274 495",
    "sg:postcode":"5171 VG",
    "sg:province":"Noord-Brabant",
    "wof:name":"Wanrooy Vof Zonwering, Van",
    "wof:placetype":"venue"
},
  "geometry": {"coordinates":[5.008526,51.656277],"type":"Point"}
}