{
  "type": "Feature",
  "properties": {
    "addr:full":"Spaarpotstraat 11 Deventer Overijssel 7419 AX",
    "addr:housenumber":"11",
    "addr:postcode":"7419 ax",
    "addr:street":"Spaarpotstraat",
    "iso:country":"NL",
    "sg:address":"Spaarpotstraat 11",
    "sg:city":"Deventer",
    "sg:orig_category":"Kappers",
    "sg:phone":"+31 570 611 180",
    "sg:postcode":"7419 AX",
    "sg:province":"Overijssel",
    "wof:name":"Fa W J Timmerman",
    "wof:placetype":"venue"
},
  "geometry": {"coordinates":[6.1435761452,52.2478294373],"type":"Point"}
}