{
  "type": "Feature",
  "properties": {
    "iso:country":"NL",
    "sg:address":"Veenselangweg 8",
    "sg:city":"Den Burg",
    "sg:orig_category":"Goederenvervoer Over De Weg",
    "sg:phone":"+31 222 312 118",
    "sg:postcode":"1791 LS",
    "sg:province":"North Holland",
    "wof:name":"Firma Leen Eelman En Zonen",
    "wof:placetype":"venue"
},
  "geometry": {"coordinates":[4.831185,53.055103],"type":"Point"}
}