{
  "type": "Feature",
  "properties": {
    "addr:full":"Maaskantlaan 3 Groningen Groningen 9731 LV",
    "addr:housenumber":"3",
    "addr:postcode":"9731",
    "addr:street":"Maaskantlaan",
    "iso:country":"NL",
    "sg:address":"Maaskantlaan 3",
    "sg:city":"Groningen",
    "sg:orig_category":"Schoonheidssalons",
    "sg:phone":"+31 50 542 1679",
    "sg:postcode":"9731 LV",
    "sg:province":"Groningen",
    "wof:name":"Schoonheidssalon Alida Venema",
    "wof:placetype":"venue"
},
  "geometry": {"coordinates":[6.581282,53.241894],"type":"Point"}
}