{
  "type": "Feature",
  "properties": {
    "addr:full":"Eerselsedk 51 Bergeyk Noord-Brabant 5571 TM",
    "addr:housenumber":"51",
    "addr:postcode":"5571 tm",
    "addr:street":"Eerselsedk",
    "iso:country":"NL",
    "sg:address":"Eerselsedk 51",
    "sg:city":"Bergeyk",
    "sg:orig_category":"Natuur- En Milieuorganisaties",
    "sg:phone":"+31 497 571 218",
    "sg:postcode":"5571 TM",
    "sg:province":"Noord-Brabant",
    "wof:name":"Milieuwerkgroep Kempenland, Sticht",
    "wof:placetype":"venue"
},
  "geometry": {"coordinates":[5.354706,51.329056],"type":"Point"}
}