{
  "type": "Feature",
  "properties": {
    "addr:full":"Brink Oz 4 Zuidlaren Drenthe 9471 AE",
    "addr:housenumber":"4",
    "addr:postcode":"9471 ae",
    "addr:street":"Brink Oz",
    "iso:country":"NL",
    "sg:address":"Brink Oz 4",
    "sg:city":"Zuidlaren",
    "sg:orig_category":"Discotheken",
    "sg:phone":"+31 50 409 4076",
    "sg:postcode":"9471 AE",
    "sg:province":"Drenthe",
    "wof:name":"Paris, Caf? De",
    "wof:placetype":"venue"
},
  "geometry": {"coordinates":[6.687982,53.093792],"type":"Point"}
}