{
  "type": "Feature",
  "properties": {
    "iso:country":"NL",
    "sg:address":"Lindenln 20",
    "sg:city":"Heerhugowaard",
    "sg:orig_category":"Artsen - Huisartsen",
    "sg:phone":"+31 72 571 1212",
    "sg:postcode":"1701 GV",
    "sg:province":"Noord-Holland",
    "wof:name":"Odijk En A Visser, C T M",
    "wof:placetype":"venue"
},
  "geometry": {"coordinates":[4.827522,52.665195],"type":"Point"}
}