{
  "type": "Feature",
  "properties": {
    "iso:country":"NL",
    "sg:address":"Nw Hilversumsewg 17",
    "sg:city":"Bussum",
    "sg:orig_category":"Bedrijfsopleidingen",
    "sg:phone":"+31 35 691 0861",
    "sg:postcode":"1406 TB",
    "sg:province":"Noord-Holland",
    "wof:name":"Hart & Pol, De",
    "wof:placetype":"venue"
},
  "geometry": {"coordinates":[5.159583,52.271172],"type":"Point"}
}