{
  "type": "Feature",
  "properties": {
    "addr:full":"Buinerstraat 1 Borger Drenthe 9531 TH",
    "addr:housenumber":"1",
    "addr:postcode":"9531 th",
    "addr:street":"Buinerstraat",
    "iso:country":"NL",
    "sg:address":"Buinerstraat 1",
    "sg:city":"Borger",
    "sg:orig_category":"Autokeuringen",
    "sg:phone":"+31 599 234 457",
    "sg:postcode":"9531 TH",
    "sg:province":"Drenthe",
    "wof:name":"Autocentrum Borger",
    "wof:placetype":"venue"
},
  "geometry": {"coordinates":[6.79816,52.924629],"type":"Point"}
}