{
  "type": "Feature",
  "properties": {
    "addr:full":"Den Hof 104 Waalre North Brabant 5582 JZ",
    "addr:housenumber":"104",
    "addr:postcode":"5582 jz",
    "addr:street":"Den Hof",
    "iso:country":"NL",
    "sg:address":"Den Hof 104",
    "sg:city":"Waalre",
    "sg:orig_category":"Kappers",
    "sg:phone":"+31 40 221 4955",
    "sg:postcode":"5582 JZ",
    "sg:province":"North Brabant",
    "wof:name":"Hairteam Kappers",
    "wof:placetype":"venue"
},
  "geometry": {"coordinates":[5.476336956,51.3953819275],"type":"Point"}
}