{
  "type": "Feature",
  "properties": {
    "addr:full":"Zeesluisweg 55 Scheveningen South Holland 2583 DP",
    "addr:housenumber":"55",
    "addr:postcode":"2583 dp",
    "addr:street":"Zeesluisweg",
    "iso:country":"NL",
    "sg:address":"Zeesluisweg 55",
    "sg:city":"Scheveningen",
    "sg:orig_category":"Fitnesscentra",
    "sg:phone":"+31 70 355 7045",
    "sg:postcode":"2583 DP",
    "sg:province":"South Holland",
    "wof:name":"Body Basics For Women",
    "wof:placetype":"venue"
},
  "geometry": {"coordinates":[4.269466,52.100182],"type":"Point"}
}