{
  "type": "Feature",
  "properties": {
    "addr:full":"Overpeltstraat 23 Amsterdam Noord-Holland 1066 PR",
    "addr:housenumber":"23",
    "addr:postcode":"1066 pr",
    "addr:street":"Overpeltstraat",
    "iso:country":"NL",
    "sg:address":"Overpeltstraat 23",
    "sg:city":"Amsterdam",
    "sg:classifiers":[
        {
            "category":"Fast Food",
            "type":"Food & Drink"
        }
    ],
    "sg:phone":"+31 20 617 5123",
    "sg:postcode":"1066 PR",
    "sg:province":"Noord-Holland",
    "sg:tags":[
        "afhaal",
        "restaurant"
    ],
    "wof:name":"J N Bloemberg",
    "wof:placetype":"venue"
},
  "geometry": {"coordinates":[4.806318,52.348045],"type":"Point"}
}