{
  "type": "Feature",
  "properties": {
    "iso:country":"NL",
    "sg:address":"Malkenschoten 5A",
    "sg:city":"Apeldoorn",
    "sg:orig_category":"Kampeerauto'S",
    "sg:phone":"+31 55 541 1525",
    "sg:postcode":"7333 NL",
    "sg:province":"Gelderland",
    "sg:website":"http://www.koldenhofcampers.nl",
    "wof:name":"Koldenhof Campers",
    "wof:placetype":"venue"
},
  "geometry": {"coordinates":[5.9660129547,52.1816482544],"type":"Point"}
}