{
  "type": "Feature",
  "properties": {
    "addr:full":"Hertoginneln 2 Appingedam Groningen 9901 HV",
    "addr:housenumber":"2",
    "addr:postcode":"9901 hv",
    "addr:street":"Hertoginneln",
    "iso:country":"NL",
    "sg:address":"Hertoginneln 2",
    "sg:city":"Appingedam",
    "sg:orig_category":"Scheepvaartmijen",
    "sg:phone":"+31 596 629 835",
    "sg:postcode":"9901 HV",
    "sg:province":"Groningen",
    "wof:name":"Ice Star",
    "wof:placetype":"venue"
},
  "geometry": {"coordinates":[6.841751,53.321281],"type":"Point"}
}