{
  "type": "Feature",
  "properties": {
    "iso:country":"NL",
    "sg:address":"Handelswg 12",
    "sg:city":"S Heerenberg",
    "sg:orig_category":"Kunststoffen - Fabrieken En Groothandel",
    "sg:phone":"+31 314 675 110",
    "sg:postcode":"7041 GX",
    "sg:province":"Gelderland",
    "sg:website":"http://www.comex-projects.com",
    "wof:name":"Comex Projects Bv",
    "wof:placetype":"venue"
},
  "geometry": {"coordinates":[6.262405,51.870789],"type":"Point"}
}