{
  "type": "Feature",
  "properties": {
    "iso:country":"NL",
    "sg:address":"Broeksewg 107",
    "sg:city":"Ameide",
    "sg:orig_category":"Kaas",
    "sg:phone":"+31 183 601 563",
    "sg:postcode":"4233 CV",
    "sg:province":"Zuid-Holland",
    "wof:name":"Vermaat, P C",
    "wof:placetype":"venue"
},
  "geometry": {"coordinates":[4.9701142311,51.9430160522],"type":"Point"}
}