{
  "type": "Feature",
  "properties": {
    "addr:full":"Vissersburen 62 Lemmer Provincie Friesland 8531 ED",
    "addr:housenumber":"62;8531",
    "addr:postcode":"ed",
    "addr:street":"Vissersburen;Provincie Friesland",
    "iso:country":"NL",
    "sg:address":"Vissersburen 62",
    "sg:city":"Lemmer",
    "sg:orig_category":"Kaas",
    "sg:phone":"+31 514 564 793",
    "sg:postcode":"8531 ED",
    "sg:province":"Provincie Friesland",
    "wof:name":"Kaaswinkel, De",
    "wof:placetype":"venue"
},
  "geometry": {"coordinates":[5.7128548622,52.8441009521],"type":"Point"}
}