{
  "type": "Feature",
  "properties": {
    "addr:full":"Businesspk Frl W 413 Nyehaske Friesland 8466 SL",
    "addr:postcode":"8466 sl",
    "addr:street":"W 413",
    "iso:country":"NL",
    "sg:address":"Businesspk Frl W 413",
    "sg:city":"Nyehaske",
    "sg:orig_category":"Adviesbureaus Bedrijfsorganisatie",
    "sg:phone":"+31 513 640 797",
    "sg:postcode":"8466 SL",
    "sg:province":"Friesland",
    "sg:website":"http://www.maatconsult.nl",
    "wof:name":"Maat Consult Bv",
    "wof:placetype":"venue"
},
  "geometry": {"coordinates":[5.893304,52.961056],"type":"Point"}
}