{
  "type": "Feature",
  "properties": {
    "addr:full":"Treubstr 5 Ryswyk Zh Zuid-Holland 2288 EG",
    "addr:housenumber":"5",
    "addr:postcode":"2288 eg",
    "addr:street":"Treubstr",
    "iso:country":"NL",
    "sg:address":"Treubstr 5",
    "sg:city":"Ryswyk Zh",
    "sg:orig_category":"Elektrotechnische Apparatuur - Fabrieken En Groothandel",
    "sg:phone":"+31 70 319 9199",
    "sg:postcode":"2288 EG",
    "sg:province":"Zuid-Holland",
    "sg:website":"http://www.rexel-electrometaal.nl",
    "wof:name":"Rexel",
    "wof:placetype":"venue"
},
  "geometry": {"coordinates":[4.32436,52.037251],"type":"Point"}
}