{
  "type": "Feature",
  "properties": {
    "addr:full":"Rijsdijk 43 Krimpen A/D Lek Zuid-Holland 2931 AW",
    "addr:housenumber":"43;a / d",
    "addr:postcode":"2931 aw",
    "addr:street":"Rijsdijk",
    "iso:country":"NL",
    "sg:address":"Rijsdijk 43",
    "sg:city":"Krimpen A/D Lek",
    "sg:classifiers":[
        {
            "category":"Shopping",
            "subcategory":"Gifts & Souvenirs",
            "type":"Retail Goods"
        }
    ],
    "sg:phone":"+31 180 512 101",
    "sg:postcode":"2931 AW",
    "sg:province":"Zuid-Holland",
    "sg:tags":[
        "geschenken"
    ],
    "wof:name":"A C P Van Der Graaf Hepico",
    "wof:placetype":"venue"
},
  "geometry": {"coordinates":[4.630247,51.892666],"type":"Point"}
}