{
  "type": "Feature",
  "properties": {
    "addr:full":"Beckerwg 25 Groningen Groningen 9731 AX",
    "addr:housenumber":"25",
    "addr:postcode":"9731 ax",
    "addr:street":"Beckerwg",
    "iso:country":"NL",
    "sg:address":"Beckerwg 25",
    "sg:city":"Groningen",
    "sg:orig_category":"Waterkoelers En Drinkwaterinstallaties",
    "sg:phone":"+31 50 549 4512",
    "sg:postcode":"9731 AX",
    "sg:province":"Groningen",
    "wof:name":"Culligan",
    "wof:placetype":"venue"
},
  "geometry": {"coordinates":[6.5838689804,53.2362594604],"type":"Point"}
}