{
  "type": "Feature",
  "properties": {
    "iso:country":"NL",
    "sg:address":"K Schaft 9",
    "sg:city":"Houten",
    "sg:orig_category":"Metaalwaren",
    "sg:phone":"+31 30 637 2060",
    "sg:postcode":"3991 AT",
    "sg:province":"Utrecht",
    "wof:name":"Wijngaarden Bv, Van",
    "wof:placetype":"venue"
},
  "geometry": {"coordinates":[5.172499,52.022278],"type":"Point"}
}