{
  "type": "Feature",
  "properties": {
    "iso:country":"NL",
    "sg:address":"Prinsesseweg 33",
    "sg:city":"Groningen",
    "sg:orig_category":"Diverse Grafische Activiteiten",
    "sg:phone":"+31 50 313 4880",
    "sg:postcode":"9717 BB",
    "sg:province":"Groningen",
    "wof:name":"Marsman",
    "wof:placetype":"venue"
},
  "geometry": {"coordinates":[6.548156,53.220715],"type":"Point"}
}