{
  "type": "Feature",
  "properties": {
    "addr:full":"Operapln 15 Apeldoorn Gelderland 7323 EJ",
    "addr:housenumber":"15",
    "addr:postcode":"7323 ej",
    "addr:street":"Operapln;Gelderland",
    "iso:country":"NL",
    "sg:address":"Operapln 15",
    "sg:city":"Apeldoorn",
    "sg:orig_category":"Banken",
    "sg:phone":"+31 55 578 4911",
    "sg:postcode":"7323 EJ",
    "sg:province":"Gelderland",
    "sg:website":"http://www.rabobank.nl",
    "wof:name":"Rabobank",
    "wof:placetype":"venue"
},
  "geometry": {"coordinates":[5.985541,52.228714],"type":"Point"}
}