{
  "type": "Feature",
  "properties": {
    "addr:full":"Z Eswg 19 Hellendoorn Overijssel 7447 HE",
    "addr:housenumber":"19",
    "addr:postcode":"7447 he",
    "iso:country":"NL",
    "sg:address":"Z Eswg 19",
    "sg:city":"Hellendoorn",
    "sg:orig_category":"Adviesbureaus",
    "sg:phone":"+31 548 654 208",
    "sg:postcode":"7447 HE",
    "sg:province":"Overijssel",
    "wof:name":"Strada",
    "wof:placetype":"venue"
},
  "geometry": {"coordinates":[6.447976,52.390255],"type":"Point"}
}