{
  "type": "Feature",
  "properties": {
    "iso:country":"NL",
    "sg:address":"O Zeedk 2",
    "sg:city":"Colynsplaat",
    "sg:orig_category":"Jachthavens - Jachtwerven",
    "sg:phone":"+31 113 695 349",
    "sg:postcode":"4486 PN",
    "sg:province":"Zeeland",
    "wof:name":"Thm",
    "wof:placetype":"venue"
},
  "geometry": {"coordinates":[3.84761,51.599251],"type":"Point"}
}