{
  "type": "Feature",
  "properties": {
    "addr:full":"Soendastr 26-2 Amsterdam North Holland 1094 BH",
    "addr:housenumber":"26-2",
    "addr:postcode":"1094 bh",
    "iso:country":"NL",
    "sg:address":"Soendastr 26-2",
    "sg:city":"Amsterdam",
    "sg:orig_category":"Verenigingen En Stichtingen",
    "sg:phone":"+31 20 693 7296",
    "sg:postcode":"1094 BH",
    "sg:province":"North Holland",
    "wof:name":"Madison",
    "wof:placetype":"venue"
},
  "geometry": {"coordinates":[4.938459,52.364876],"type":"Point"}
}