{
  "type": "Feature",
  "properties": {
    "addr:full":"Havenstraat 30 Schiedam Zuid-Holland 3115 HD",
    "addr:housenumber":"30",
    "addr:postcode":"3115 hd",
    "addr:street":"Havenstraat",
    "iso:country":"NL",
    "sg:address":"Havenstraat 30",
    "sg:city":"Schiedam",
    "sg:orig_category":"Farmaceutische Producten Gh",
    "sg:phone":"+31 10 246 2646",
    "sg:postcode":"3115 HD",
    "sg:province":"Zuid-Holland",
    "wof:name":"Farmamed Bv",
    "wof:placetype":"venue"
},
  "geometry": {"coordinates":[4.398202,51.900864],"type":"Point"}
}