{
  "type": "Feature",
  "properties": {
    "addr:full":"Dwarskade 35 Nootdorp South Holland 2631 NA",
    "addr:housenumber":"35",
    "addr:postcode":"2631 na",
    "addr:street":"Dwarskade",
    "iso:country":"NL",
    "sg:address":"Dwarskade 35",
    "sg:city":"Nootdorp",
    "sg:orig_category":"Bloemen- And Plantenteelt",
    "sg:phone":"+31 15 310 9288",
    "sg:postcode":"2631 NA",
    "sg:province":"South Holland",
    "wof:name":"J.J. Kooi Rozenkwekerij",
    "wof:placetype":"venue"
},
  "geometry": {"coordinates":[4.391232,52.035599],"type":"Point"}
}