{
  "type": "Feature",
  "properties": {
    "addr:full":"Charley Tooroplaan 16 Pijnacker South Holland 2642 CK",
    "addr:housenumber":"16",
    "addr:postcode":"2642 ck",
    "addr:street":"Charley Tooroplaan",
    "iso:country":"NL",
    "sg:address":"Charley Tooroplaan 16",
    "sg:city":"Pijnacker",
    "sg:orig_category":"Metaalwerken",
    "sg:phone":"+31 15 369 2272",
    "sg:postcode":"2642 CK",
    "sg:province":"South Holland",
    "wof:name":"Windeko",
    "wof:placetype":"venue"
},
  "geometry": {"coordinates":[4.445607,52.011715],"type":"Point"}
}