{
  "type": "Feature",
  "properties": {
    "addr:full":"Grt Kerkstr 73-75 Hoogeveen Drenthe 7902 CG",
    "addr:housenumber":"73-75",
    "addr:postcode":"hoogeveen;7902 cg",
    "iso:country":"NL",
    "sg:address":"Grt Kerkstr 73-75",
    "sg:city":"Hoogeveen",
    "sg:orig_category":"Cafetaria'S",
    "sg:phone":"+31 528 264 155",
    "sg:postcode":"7902 CG",
    "sg:province":"Drenthe",
    "wof:name":"City",
    "wof:placetype":"venue"
},
  "geometry": {"coordinates":[6.483364,52.726143],"type":"Point"}
}