{
  "type": "Feature",
  "properties": {
    "addr:full":"Oorsprongpark 12 Utrecht Utrecht 3581 ET",
    "addr:housenumber":"12",
    "addr:postcode":"3581 et",
    "addr:street":"Oorsprongpark",
    "iso:country":"NL",
    "sg:address":"Oorsprongpark 12",
    "sg:city":"Utrecht",
    "sg:orig_category":"Makelaars In Onroerend Goed",
    "sg:phone":"+31 30 233 2552",
    "sg:postcode":"3581 ET",
    "sg:province":"Utrecht",
    "wof:name":"Dtz Zadelhoff Vof",
    "wof:placetype":"venue"
},
  "geometry": {"coordinates":[5.137745,52.095043],"type":"Point"}
}