{
  "type": "Feature",
  "properties": {
    "iso:country":"NL",
    "sg:address":"T V Amerongenstr 17",
    "sg:city":"Markelo",
    "sg:orig_category":"Autoreclame",
    "sg:phone":"+31 547 363 535",
    "sg:postcode":"7475 BT",
    "sg:province":"Overijssel",
    "wof:name":"Veen, Pieter Ten",
    "wof:placetype":"venue"
},
  "geometry": {"coordinates":[6.4959869385,52.2342033386],"type":"Point"}
}