{
  "type": "Feature",
  "properties": {
    "iso:country":"NL",
    "sg:address":"Boijlerweg 116",
    "sg:city":"Boijl",
    "sg:orig_category":"Boekhouders",
    "sg:phone":"+31 561 421 144",
    "sg:postcode":"8392 NL",
    "sg:province":"Provincie Friesland",
    "wof:name":"Slot & Knorren Adm En Reclamebureau",
    "wof:placetype":"venue"
},
  "geometry": {"coordinates":[6.213838,52.915791],"type":"Point"}
}