{
  "type": "Feature",
  "properties": {
    "addr:full":"Verdistraat 79 Oss Virginia 5343 VC",
    "addr:housenumber":"79",
    "addr:postcode":"5343 vc",
    "addr:street":"Verdistraat",
    "iso:country":"NL",
    "sg:address":"Verdistraat 79",
    "sg:city":"Oss",
    "sg:orig_category":"Kinderopvang Behalve Thuis",
    "sg:phone":"+31 412 645 479",
    "sg:postcode":"5343 VC",
    "sg:province":"Virginia",
    "wof:name":"Kinderdagverblijf De Vriendjes",
    "wof:placetype":"venue"
},
  "geometry": {"coordinates":[-77.235214,38.312599],"type":"Point"}
}