{
  "type": "Feature",
  "properties": {
    "addr:full":"Hoofdbrug 6 Heerenveen Friesland 8442 PA",
    "addr:housenumber":"6",
    "addr:postcode":"8442 pa",
    "addr:street":"Hoofdbrug",
    "iso:country":"NL",
    "sg:address":"Hoofdbrug 6",
    "sg:city":"Heerenveen",
    "sg:classifiers":[
        {
            "category":"Shopping",
            "subcategory":"Adult",
            "type":"Retail Goods"
        }
    ],
    "sg:phone":"+31 513 651 881",
    "sg:postcode":"8442 PA",
    "sg:province":"Friesland",
    "sg:tags":[
        "lingerie",
        "en",
        "tricotage"
    ],
    "wof:name":"Melanie",
    "wof:placetype":"venue"
},
  "geometry": {"coordinates":[5.923108,52.959869],"type":"Point"}
}