{
  "type": "Feature",
  "properties": {
    "addr:full":"Dorpsstr 98A Amstelveen North Holland 1182 JH",
    "addr:housenumber":"98a",
    "addr:postcode":"1182 jh",
    "addr:street":"Dorpsstr",
    "iso:country":"NL",
    "sg:address":"Dorpsstr 98A",
    "sg:city":"Amstelveen",
    "sg:orig_category":"Kappers",
    "sg:phone":"+31 20 643 6187",
    "sg:postcode":"1182 JH",
    "sg:province":"North Holland",
    "wof:name":"Nadeni",
    "wof:placetype":"venue"
},
  "geometry": {"coordinates":[4.846509,52.301975],"type":"Point"}
}