{
  "type": "Feature",
  "properties": {
    "iso:country":"NL",
    "sg:address":"James Wattstraat 19",
    "sg:city":"Alkmaar",
    "sg:classifiers":[
        {
            "category":"Professional",
            "subcategory":"Accounting & Tax Preparation",
            "type":"Services"
        }
    ],
    "sg:phone":"+31 72 512 2142",
    "sg:postcode":"1817 DC",
    "sg:province":"North Holland",
    "sg:tags":[
        "accountant"
    ],
    "wof:name":"Accountants Schippers En Co",
    "wof:placetype":"venue"
},
  "geometry": {"coordinates":[4.740044,52.649429],"type":"Point"}
}