{
  "type": "Feature",
  "properties": {
    "addr:full":"Hoornweg 61 Marum Groningen 9363 EE",
    "addr:housenumber":"61",
    "addr:postcode":"9363 ee",
    "addr:street":"Hoornweg",
    "iso:country":"NL",
    "sg:address":"Hoornweg 61",
    "sg:city":"Marum",
    "sg:orig_category":"Fietshandelaren",
    "sg:phone":"+31 594 643 683",
    "sg:postcode":"9363 EE",
    "sg:province":"Groningen",
    "wof:name":"Tweewielercentrum Jan En Pietsje",
    "wof:placetype":"venue"
},
  "geometry": {"coordinates":[6.250278,53.141666],"type":"Point"}
}