{
  "type": "Feature",
  "properties": {
    "addr:full":"Kanaalstr 53 Roden Drenthe 9301 LR",
    "addr:housenumber":"53",
    "addr:postcode":"9301 lr",
    "addr:street":"Kanaalstr",
    "iso:country":"NL",
    "sg:address":"Kanaalstr 53",
    "sg:city":"Roden",
    "sg:orig_category":"Kinderkleding",
    "sg:phone":"+31 50 409 4404",
    "sg:postcode":"9301 LR",
    "sg:province":"Drenthe",
    "wof:name":"Okiedokie",
    "wof:placetype":"venue"
},
  "geometry": {"coordinates":[6.432771,53.141003],"type":"Point"}
}