{
  "type": "Feature",
  "properties": {
    "addr:full":"Cyclamenstr 1 Eindhoven Noord-Brabant 5644 KH",
    "addr:housenumber":"1",
    "addr:postcode":"5644 kh",
    "addr:street":"Cyclamenstr",
    "iso:country":"NL",
    "sg:address":"Cyclamenstr 1",
    "sg:city":"Eindhoven",
    "sg:orig_category":"Verenigingen En Stichtingen",
    "sg:phone":"+31 40 212 6241",
    "sg:postcode":"5644 KH",
    "sg:province":"Noord-Brabant",
    "wof:name":"Sarah Yasmine, Sticht",
    "wof:placetype":"venue"
},
  "geometry": {"coordinates":[5.490373,51.419991],"type":"Point"}
}