{
  "type": "Feature",
  "properties": {
    "addr:full":"Folkertsstr 19 Arkel South Holland 4241 BE",
    "addr:housenumber":"19",
    "addr:postcode":"4241",
    "addr:street":"Folkertsstr",
    "iso:country":"NL",
    "sg:address":"Folkertsstr 19",
    "sg:city":"Arkel",
    "sg:classifiers":[
        {
            "category":"Utilities",
            "subcategory":"Cable",
            "type":"Services"
        }
    ],
    "sg:phone":"+31 183 561 183",
    "sg:postcode":"4241 BE",
    "sg:province":"South Holland",
    "sg:tags":[
        "masseur",
        "en",
        "heilgymnasten"
    ],
    "wof:name":"Daalen, Paul Van",
    "wof:placetype":"venue"
},
  "geometry": {"coordinates":[4.994451,51.864487],"type":"Point"}
}