{
  "type": "Feature",
  "properties": {
    "addr:full":"Gentiaan 28 Wolvega Provincie Friesland 8471 WG",
    "addr:housenumber":"28",
    "addr:postcode":"8471 wg",
    "addr:street":"Gentiaan;Provincie Friesland",
    "iso:country":"NL",
    "sg:address":"Gentiaan 28",
    "sg:city":"Wolvega",
    "sg:orig_category":"Voetbalverenigingen",
    "sg:phone":"+31 561 614 244",
    "sg:postcode":"8471 WG",
    "sg:province":"Provincie Friesland",
    "wof:name":"Fc Wolvega",
    "wof:placetype":"venue"
},
  "geometry": {"coordinates":[5.983299,52.867825],"type":"Point"}
}