{
  "type": "Feature",
  "properties": {
    "addr:full":"Dr P Rinsemastraat 2 Vlagtwedde Groningen 9541 AL",
    "addr:housenumber":"2",
    "addr:postcode":"9541 al",
    "addr:street":"P Rinsemastraat",
    "iso:country":"NL",
    "sg:address":"Dr P Rinsemastraat 2",
    "sg:city":"Vlagtwedde",
    "sg:orig_category":"Woningbouwverenigingen",
    "sg:phone":"+31 599 345 670",
    "sg:postcode":"9541 AL",
    "sg:province":"Groningen",
    "wof:name":"Woonstichting Oosterkim",
    "wof:placetype":"venue"
},
  "geometry": {"coordinates":[7.1060380936,53.0260658264],"type":"Point"}
}