{
  "type": "Feature",
  "properties": {
    "iso:country":"NL",
    "sg:address":"Hunnenwg 10/9",
    "sg:city":"Voorthuizen",
    "sg:orig_category":"Kantoor- En Secretariaatsservice",
    "sg:phone":"+31 342 478 450",
    "sg:postcode":"3781 NN",
    "sg:province":"Gelderland",
    "wof:name":"Assisting Hands",
    "wof:placetype":"venue"
},
  "geometry": {"coordinates":[5.6053438187,52.1868209839],"type":"Point"}
}