{
  "type": "Feature",
  "properties": {
    "addr:full":"Hoofdstr 88 Diever Provincie Drenthe 7981 AV",
    "addr:housenumber":"88;7981",
    "addr:postcode":"av",
    "addr:street":"Hoofdstr;Provincie Drenthe",
    "iso:country":"NL",
    "sg:address":"Hoofdstr 88",
    "sg:city":"Diever",
    "sg:orig_category":"Zalenverhuur",
    "sg:phone":"+31 521 592 072",
    "sg:postcode":"7981 AV",
    "sg:province":"Provincie Drenthe",
    "wof:name":"Dingspilhuus",
    "wof:placetype":"venue"
},
  "geometry": {"coordinates":[6.321749,52.853436],"type":"Point"}
}