{
  "type": "Feature",
  "properties": {
    "addr:full":"Hoofdstr 57 Veenendaal Utrecht 3901 AE",
    "addr:housenumber":"57",
    "addr:postcode":"3901 ae",
    "addr:street":"Hoofdstr",
    "iso:country":"NL",
    "sg:address":"Hoofdstr 57",
    "sg:city":"Veenendaal",
    "sg:orig_category":"Opticiens",
    "sg:phone":"+31 318 526 500",
    "sg:postcode":"3901 AE",
    "sg:province":"Utrecht",
    "wof:name":"Pearle",
    "wof:placetype":"venue"
},
  "geometry": {"coordinates":[5.5559048653,52.0275001526],"type":"Point"}
}