{
  "type": "Feature",
  "properties": {
    "iso:country":"NL",
    "sg:address":"Broekhem 95",
    "sg:city":"Valkenburg Lb",
    "sg:orig_category":"Verenigingen En Stichtingen",
    "sg:phone":"+31 43 609 8200",
    "sg:postcode":"6301 HE",
    "sg:province":"Limburg",
    "wof:name":"Zonnewende Huisvesting, Sticht",
    "wof:placetype":"venue"
},
  "geometry": {"coordinates":[5.820535,50.871445],"type":"Point"}
}