{
  "type": "Feature",
  "properties": {
    "addr:full":"Broekhem 95 Valkenburg Lb Limburg 6301 HE",
    "addr:housenumber":"95",
    "addr:postcode":"lb;6301 he",
    "addr:street":"Broekhem",
    "iso:country":"NL",
    "sg:address":"Broekhem 95",
    "sg:city":"Valkenburg Lb",
    "sg:orig_category":"Verenigingen En Stichtingen",
    "sg:phone":"+31 43 609 8200",
    "sg:postcode":"6301 HE",
    "sg:province":"Limburg",
    "wof:name":"Zonnewende Huisvesting, Sticht",
    "wof:placetype":"venue"
},
  "geometry": {"coordinates":[5.820535,50.871445],"type":"Point"}
}