{
  "type": "Feature",
  "properties": {
    "addr:full":"Hermesweg 3 Zutphen Gelderland 7202 BR",
    "addr:housenumber":"3",
    "addr:postcode":"7202 br",
    "addr:street":"Hermesweg;Gelderland",
    "iso:country":"NL",
    "sg:address":"Hermesweg 3",
    "sg:city":"Zutphen",
    "sg:orig_category":"Diverse Bedrijfsinstallaties Gh",
    "sg:phone":"+31 575 515 243",
    "sg:postcode":"7202 BR",
    "sg:province":"Gelderland",
    "wof:name":"Netam Service Bv",
    "wof:placetype":"venue"
},
  "geometry": {"coordinates":[6.192238,52.14846],"type":"Point"}
}