{
  "type": "Feature",
  "properties": {
    "addr:full":"Jhr Hoeufftln 10B Vianen Zh South Holland 4132 EB",
    "addr:housenumber":"10b",
    "addr:postcode":"zh;4132 eb",
    "addr:street":"Jhr Hoeufftln",
    "iso:country":"NL",
    "sg:address":"Jhr Hoeufftln 10B",
    "sg:city":"Vianen Zh",
    "sg:orig_category":"Woninginrichting",
    "sg:phone":"+31 347 372 391",
    "sg:postcode":"4132 EB",
    "sg:province":"South Holland",
    "sg:website":"http://www.denbesten-woninginrichting.nl",
    "wof:name":"Besten, Den",
    "wof:placetype":"venue"
},
  "geometry": {"coordinates":[5.0961518288,51.9924163818],"type":"Point"}
}