{
  "type": "Feature",
  "properties": {
    "addr:full":"Broekstraat 3 Nederasselt Gelderland 6612 AA",
    "addr:housenumber":"3",
    "addr:postcode":"6612 aa",
    "addr:street":"Broekstraat;Gelderland",
    "iso:country":"NL",
    "sg:address":"Broekstraat 3",
    "sg:city":"Nederasselt",
    "sg:classifiers":[
        {
            "category":"Food & Beverages",
            "subcategory":"Fruits & Vegetables",
            "type":"Retail Goods"
        }
    ],
    "sg:phone":"+31 24 622 1973",
    "sg:postcode":"6612 AA",
    "sg:province":"Gelderland",
    "sg:tags":[
        "groenten"
    ],
    "wof:name":"P.J. Broekman",
    "wof:placetype":"venue"
},
  "geometry": {"coordinates":[5.748917,51.774231],"type":"Point"}
}