{
  "type": "Feature",
  "properties": {
    "addr:full":"Dukdalfwg 55 Almere NL. 1332 BK",
    "addr:housenumber":"55",
    "addr:postcode":"1332 bk",
    "addr:street":"Dukdalfwg;Nl.",
    "iso:country":"NL",
    "sg:address":"Dukdalfwg 55",
    "sg:city":"Almere",
    "sg:orig_category":"Machinehandel",
    "sg:phone":"+31 36 532 2140",
    "sg:postcode":"1332 BK",
    "sg:province":"NL.",
    "wof:name":"Rode Loper, De",
    "wof:placetype":"venue"
},
  "geometry": {"coordinates":[5.258068,52.410439],"type":"Point"}
}