{
  "type": "Feature",
  "properties": {
    "iso:country":"NL",
    "sg:address":"Stationsstr 51",
    "sg:city":"Rhoon",
    "sg:orig_category":"Voorlichtingsbureaus",
    "sg:phone":"+31 10 506 1931",
    "sg:postcode":"3161 GH",
    "sg:province":"South Holland",
    "sg:website":"http://www.shortsea.nl",
    "wof:name":"Shortsea Shipping",
    "wof:placetype":"venue"
},
  "geometry": {"coordinates":[4.421779,51.859806],"type":"Point"}
}