{
  "type": "Feature",
  "properties": {
    "addr:full":"Dr Kuyperkade 29 Maassluis Zuid-Holland 3142 GC",
    "addr:housenumber":"29",
    "addr:postcode":"3142 gc",
    "addr:street":"Dr Kuyperkade",
    "iso:country":"NL",
    "sg:address":"Dr Kuyperkade 29",
    "sg:city":"Maassluis",
    "sg:orig_category":"Verzekeringen",
    "sg:phone":"+31 10 591 5383",
    "sg:postcode":"3142 GC",
    "sg:province":"Zuid-Holland",
    "wof:name":"W. Renzen Assurantiebedrijf",
    "wof:placetype":"venue"
},
  "geometry": {"coordinates":[4.256566,51.922623],"type":"Point"}
}