{
  "type": "Feature",
  "properties": {
    "addr:full":"Ratelaar 35 Krimpen Ad Yssel Zuid-Holland 2923 GE",
    "addr:housenumber":"35",
    "addr:postcode":"2923",
    "addr:street":"Ratelaar",
    "iso:country":"NL",
    "sg:address":"Ratelaar 35",
    "sg:city":"Krimpen Ad Yssel",
    "sg:orig_category":"Administratie- En Boekhoudkantoren",
    "sg:phone":"+31 180 511 124",
    "sg:postcode":"2923 GE",
    "sg:province":"Zuid-Holland",
    "wof:name":"Bestman",
    "wof:placetype":"venue"
},
  "geometry": {"coordinates":[4.60838,51.913986],"type":"Point"}
}