{
  "type": "Feature",
  "properties": {
    "addr:full":"Dorpsweg 92 Wilsum Overijssel 8274 AH",
    "addr:housenumber":"92",
    "addr:postcode":"8274 ah",
    "addr:street":"Dorpsweg",
    "iso:country":"NL",
    "sg:address":"Dorpsweg 92",
    "sg:city":"Wilsum",
    "sg:orig_category":"Autokeuringen",
    "sg:phone":"+31 38 355 7256",
    "sg:postcode":"8274 AH",
    "sg:province":"Overijssel",
    "wof:name":"Garage H Roetman",
    "wof:placetype":"venue"
},
  "geometry": {"coordinates":[5.966081,52.52705],"type":"Point"}
}