{
  "type": "Feature",
  "properties": {
    "addr:full":"Markenburg 95 Hoofddorp Noord-Holland 2135 DS",
    "addr:housenumber":"95",
    "addr:postcode":"2135 ds",
    "addr:street":"Markenburg",
    "iso:country":"NL",
    "sg:address":"Markenburg 95",
    "sg:city":"Hoofddorp",
    "sg:classifiers":[
        {
            "category":"Bakery",
            "type":"Food & Drink"
        }
    ],
    "sg:phone":"+31 23 562 6553",
    "sg:postcode":"2135 DS",
    "sg:province":"Noord-Holland",
    "sg:tags":[
        "brood",
        "banket"
    ],
    "wof:name":"J.P.M. Van Der Voorn",
    "wof:placetype":"venue"
},
  "geometry": {"coordinates":[4.663085,52.30183],"type":"Point"}
}