{
  "type": "Feature",
  "properties": {
    "iso:country":"NL",
    "sg:address":"Koevoetstraat 51",
    "sg:city":"Bergen Op Zoom",
    "sg:orig_category":"Werving And Selectie Van Tijdelijk Personeel And Uitzendkantoren",
    "sg:phone":"+31 164 239 300",
    "sg:postcode":"4611 PB",
    "sg:province":"Noord-Brabant",
    "wof:name":"Tence Uitzendbureau",
    "wof:placetype":"venue"
},
  "geometry": {"coordinates":[4.2899980545,51.4939155579],"type":"Point"}
}