{
  "type": "Feature",
  "properties": {
    "addr:full":"Koenenkd 24 Amsterdam North Holland 1081 KG",
    "addr:housenumber":"24",
    "addr:postcode":"1081 kg",
    "addr:street":"Koenenkd",
    "iso:country":"NL",
    "sg:address":"Koenenkd 24",
    "sg:city":"Amsterdam",
    "sg:orig_category":"Jachthavens - Jachtwerven",
    "sg:phone":"+31 20 644 9801",
    "sg:postcode":"1081 KG",
    "sg:province":"North Holland",
    "wof:name":"Koenen/Bibo, De",
    "wof:placetype":"venue"
},
  "geometry": {"coordinates":[4.84344,52.330189],"type":"Point"}
}