{
  "type": "Feature",
  "properties": {
    "iso:country":"NL",
    "sg:address":"L Linden 24",
    "sg:city":"Katwyk Nb",
    "sg:orig_category":"Olie - Exploratie",
    "sg:phone":"+31 485 314 004",
    "sg:postcode":"5433 NC",
    "sg:province":"Noord-Brabant",
    "wof:name":"Snijders Bv",
    "wof:placetype":"venue"
},
  "geometry": {"coordinates":[5.871582,51.750683],"type":"Point"}
}