{
  "type": "Feature",
  "properties": {
    "addr:full":"De Meeten 20A Roosendaal North Brabant 4706 NG",
    "addr:housenumber":"20a",
    "addr:postcode":"4706 ng",
    "addr:street":"De Meeten",
    "iso:country":"NL",
    "sg:address":"De Meeten 20A",
    "sg:city":"Roosendaal",
    "sg:classifiers":[
        {
            "category":"Retail",
            "subcategory":"Auto Repair",
            "type":"Services"
        }
    ],
    "sg:phone":"+31 165 537 687",
    "sg:postcode":"4706 NG",
    "sg:province":"North Brabant",
    "sg:tags":[
        "garage"
    ],
    "wof:name":"Meeten, De",
    "wof:placetype":"venue"
},
  "geometry": {"coordinates":[4.489289,51.535038],"type":"Point"}
}