{
  "type": "Feature",
  "properties": {
    "addr:full":"Oude Liesbosln 154 Breda Noord-Brabant 4839 AD",
    "addr:housenumber":"154",
    "addr:postcode":"4839 ad",
    "addr:street":"Oude Liesbosln",
    "iso:country":"NL",
    "sg:address":"Oude Liesbosln 154",
    "sg:city":"Breda",
    "sg:orig_category":"Adviesbureaus Financieel",
    "sg:phone":"+31 76 522 2895",
    "sg:postcode":"4839 AD",
    "sg:province":"Noord-Brabant",
    "wof:name":"Varen, De",
    "wof:placetype":"venue"
},
  "geometry": {"coordinates":[4.70606,51.582649],"type":"Point"}
}