{
  "type": "Feature",
  "properties": {
    "addr:full":"Looierslaan 26 Leidschendam Zuid-Holland 2264 AA",
    "addr:housenumber":"26",
    "addr:postcode":"2264 aa",
    "addr:street":"Looierslaan",
    "iso:country":"NL",
    "sg:address":"Looierslaan 26",
    "sg:city":"Leidschendam",
    "sg:orig_category":"Autokeuringen",
    "sg:phone":"+31 70 327 7207",
    "sg:postcode":"2264 AA",
    "sg:province":"Zuid-Holland",
    "wof:name":"Bandenservicebedrijf Superband Bv",
    "wof:placetype":"venue"
},
  "geometry": {"coordinates":[4.387135,52.082539],"type":"Point"}
}