{
  "type": "Feature",
  "properties": {
    "iso:country":"NL",
    "sg:address":"Vreeswijkstraat 737",
    "sg:city":"'S Gravenhage",
    "sg:orig_category":"Kappers",
    "sg:phone":"+31 70 366 5410",
    "sg:postcode":"2546 AT",
    "sg:province":"Zuid-Holland",
    "wof:name":"P.J. Baan & Zn",
    "wof:placetype":"venue"
},
  "geometry": {"coordinates":[4.271014,52.055061],"type":"Point"}
}