{
  "type": "Feature",
  "properties": {
    "addr:full":"F Erensstr 53 Voerendaal Limburg 6367 SK",
    "addr:housenumber":"53",
    "addr:street":"6367",
    "iso:country":"NL",
    "sg:address":"F Erensstr 53",
    "sg:city":"Voerendaal",
    "sg:orig_category":"Keukens",
    "sg:phone":"+31 45 562 0233",
    "sg:postcode":"6367 SK",
    "sg:province":"Limburg",
    "wof:name":"Notten",
    "wof:placetype":"venue"
},
  "geometry": {"coordinates":[5.931765,50.879032],"type":"Point"}
}