{
  "type": "Feature",
  "properties": {
    "addr:full":"Frankendaal 10 Rotterdam South Holland 3075 XS",
    "addr:housenumber":"10",
    "addr:postcode":"3075 xs",
    "addr:street":"Frankendaal",
    "iso:country":"NL",
    "sg:address":"Frankendaal 10",
    "sg:city":"Rotterdam",
    "sg:orig_category":"Organisatiebureaus",
    "sg:phone":"+31 10 419 5876",
    "sg:postcode":"3075 XS",
    "sg:province":"South Holland",
    "wof:name":"P M O Ondersteuning",
    "wof:placetype":"venue"
},
  "geometry": {"coordinates":[4.5180487633,51.8885116577],"type":"Point"}
}