{
  "type": "Feature",
  "properties": {
    "addr:full":"K Doormanwg 10E Breukelen Ut Utrecht 3621 JX",
    "addr:housenumber":"10e",
    "addr:postcode":"3621 jx",
    "addr:street":"Doormanwg",
    "iso:country":"NL",
    "sg:address":"K Doormanwg 10E",
    "sg:city":"Breukelen Ut",
    "sg:orig_category":"Kappers",
    "sg:phone":"+31 346 262 722",
    "sg:postcode":"3621 JX",
    "sg:province":"Utrecht",
    "wof:name":"Kox, Barbershop",
    "wof:placetype":"venue"
},
  "geometry": {"coordinates":[5.001585,52.172958],"type":"Point"}
}