{
  "type": "Feature",
  "properties": {
    "addr:full":"Noordeinde 23 Monnickendam North Holland 1141 AE",
    "addr:housenumber":"23",
    "addr:postcode":"1141 ae",
    "addr:street":"Noordeinde",
    "iso:country":"NL",
    "sg:address":"Noordeinde 23",
    "sg:city":"Monnickendam",
    "sg:orig_category":"Alternatieve Geneeskunde",
    "sg:phone":"+31 299 655 788",
    "sg:postcode":"1141 AE",
    "sg:province":"North Holland",
    "wof:name":"Esperlind Beauty",
    "wof:placetype":"venue"
},
  "geometry": {"coordinates":[5.035147,52.460209],"type":"Point"}
}