{
  "type": "Feature",
  "properties": {
    "iso:country":"NL",
    "sg:address":"Duivenwaardsedk 18",
    "sg:city":"Nieuwe Tonge",
    "sg:orig_category":"Adviesbureaus Land- En Tuinbouw",
    "sg:phone":"+31 187 651 519",
    "sg:postcode":"3244 LG",
    "sg:province":"Zuid-Holland",
    "wof:name":"Brooshoofd, J M P",
    "wof:placetype":"venue"
},
  "geometry": {"coordinates":[4.147854,51.71661],"type":"Point"}
}