{
  "type": "Feature",
  "properties": {
    "addr:full":"Nieuwe Havenweg 53 Hilversum Noord-Holland 1216 BL",
    "addr:housenumber":"53",
    "addr:postcode":"1216 bl",
    "addr:street":"Nieuwe Havenweg",
    "iso:country":"NL",
    "sg:address":"Nieuwe Havenweg 53",
    "sg:city":"Hilversum",
    "sg:orig_category":"Goederenvervoer Over De Weg",
    "sg:phone":"+31 35 625 5000",
    "sg:postcode":"1216 BL",
    "sg:province":"Noord-Holland",
    "wof:name":"Transport- En Expeditiebedrijf G.W.J. Van Straaten",
    "wof:placetype":"venue"
},
  "geometry": {"coordinates":[5.141106,52.224133],"type":"Point"}
}