{
  "type": "Feature",
  "properties": {
    "addr:full":"Zuidwend 21 Bant Flevoland 8314 AA",
    "addr:housenumber":"21",
    "addr:postcode":"8314 aa",
    "addr:street":"Zuidwend;Flevoland",
    "iso:country":"NL",
    "sg:address":"Zuidwend 21",
    "sg:city":"Bant",
    "sg:orig_category":"Loodgieterswerk, Verwarming And Sanitaire Installaties",
    "sg:phone":"+31 527 261 627",
    "sg:postcode":"8314 AA",
    "sg:province":"Flevoland",
    "wof:name":"J G Schonewille Klussenbedrijf",
    "wof:placetype":"venue"
},
  "geometry": {"coordinates":[-86.249771,39.524075],"type":"Point"}
}