{
  "type": "Feature",
  "properties": {
    "iso:country":"NL",
    "sg:address":"H Dunantln 93",
    "sg:city":"Delft",
    "sg:orig_category":"Adviesbureaus Bedrijfsorganisatie",
    "sg:phone":"+31 6 15030570",
    "sg:postcode":"2614 GL",
    "sg:province":"Zuid-Holland",
    "wof:name":"Parr\u00e8sia",
    "wof:placetype":"venue"
},
  "geometry": {"coordinates":[4.341895,52.003979],"type":"Point"}
}