{
  "type": "Feature",
  "properties": {
    "addr:full":"Noordzijde 28 Goudriaan Zuid-Holland 2977 AD",
    "addr:housenumber":"28",
    "addr:postcode":"2977 ad",
    "addr:street":"Noordzijde",
    "iso:country":"NL",
    "sg:address":"Noordzijde 28",
    "sg:city":"Goudriaan",
    "sg:orig_category":"Heiwerken En Funderingstechniek",
    "sg:phone":"+31 183 582 787",
    "sg:postcode":"2977 AD",
    "sg:province":"Zuid-Holland",
    "wof:name":"Vos, J De",
    "wof:placetype":"venue"
},
  "geometry": {"coordinates":[4.889593,51.903416],"type":"Point"}
}