{
  "type": "Feature",
  "properties": {
    "iso:country":"NL",
    "sg:address":"De Akkeren 18",
    "sg:city":"Soest",
    "sg:orig_category":"Boekhouders",
    "sg:phone":"+31 35 601 2671",
    "sg:postcode":"3762 AS",
    "sg:province":"Utrecht",
    "wof:name":"Adm.-Assurantie-En Financ.Kantoor N.J.Ko",
    "wof:placetype":"venue"
},
  "geometry": {"coordinates":[5.287571,52.173492],"type":"Point"}
}