{
  "type": "Feature",
  "properties": {
    "addr:full":"Erasmusweg 68 'S Gravenhage Zuid-Holland 2532 CR",
    "addr:housenumber":"68",
    "addr:postcode":"2532 cr",
    "addr:street":"Erasmusweg;' S",
    "iso:country":"NL",
    "sg:address":"Erasmusweg 68",
    "sg:city":"'S Gravenhage",
    "sg:classifiers":[
        {
            "category":"Education",
            "subcategory":"Preschool",
            "type":"Public Place"
        }
    ],
    "sg:phone":"+31 70 394 8687",
    "sg:postcode":"2532 CR",
    "sg:province":"Zuid-Holland",
    "sg:tags":[
        "kleuteronderwijs",
        "basis-"
    ],
    "wof:name":"Ds. D.A. Van Den Boschschool",
    "wof:placetype":"venue"
},
  "geometry": {"coordinates":[4.30405,52.052193],"type":"Point"}
}