{
  "type": "Feature",
  "properties": {
    "addr:full":"Doelstr 2A Maasland Zuid-Holland 3155 AH",
    "addr:housenumber":"2a",
    "addr:postcode":"3155 ah",
    "addr:street":"Doelstr",
    "iso:country":"NL",
    "sg:address":"Doelstr 2A",
    "sg:city":"Maasland",
    "sg:orig_category":"Bloemen En Planten",
    "sg:phone":"+31 10 599 0599",
    "sg:postcode":"3155 AH",
    "sg:province":"Zuid-Holland",
    "wof:name":"Carlton, De",
    "wof:placetype":"venue"
},
  "geometry": {"coordinates":[4.272247,51.935879],"type":"Point"}
}