{
  "type": "Feature",
  "properties": {
    "addr:full":"Van Swinderenstraat 8 Balk Friesland 8561 AP",
    "addr:housenumber":"8",
    "addr:postcode":"8561 ap",
    "addr:street":"Van Swinderenstraat",
    "iso:country":"NL",
    "sg:address":"Van Swinderenstraat 8",
    "sg:city":"Balk",
    "sg:orig_category":"Kansspelen",
    "sg:phone":"+31 514 602 767",
    "sg:postcode":"8561 AP",
    "sg:province":"Friesland",
    "wof:name":"Pinball Wizzard Amusementenhal S. Kooyst",
    "wof:placetype":"venue"
},
  "geometry": {"coordinates":[-100.8285827637,36.6088294983],"type":"Point"}
}