{
  "type": "Feature",
  "properties": {
    "addr:full":"Frisostr 17 S Gravendeel Zuid-Holland 3295 CE",
    "addr:housenumber":"17",
    "addr:postcode":"3295 ce",
    "addr:street":"Frisostr;S",
    "iso:country":"NL",
    "sg:address":"Frisostr 17",
    "sg:city":"S Gravendeel",
    "sg:orig_category":"Elektrotechnische Installatiebureaus",
    "sg:phone":"+31 78 673 1100",
    "sg:postcode":"3295 CE",
    "sg:province":"Zuid-Holland",
    "wof:name":"Barth Bv",
    "wof:placetype":"venue"
},
  "geometry": {"coordinates":[4.617353,51.775745],"type":"Point"}
}