{
  "type": "Feature",
  "properties": {
    "iso:country":"NL",
    "sg:address":"Houtkampweg 11A",
    "sg:city":"Hoenderloo",
    "sg:orig_category":"Kampeerterreinen",
    "sg:phone":"+31 55 378 2232",
    "sg:postcode":"7352 TC",
    "sg:province":"Gelderland",
    "wof:name":"Kampeerterrein De Hoge Veluwe",
    "wof:placetype":"venue"
},
  "geometry": {"coordinates":[5.8835601807,52.1062812805],"type":"Point"}
}