{
  "type": "Feature",
  "properties": {
    "addr:full":"Koningsvaren 95 Abcoude North Holland 1391 AG",
    "addr:housenumber":"95",
    "addr:postcode":"1391",
    "addr:street":"Koningsvaren",
    "iso:country":"NL",
    "sg:address":"Koningsvaren 95",
    "sg:city":"Abcoude",
    "sg:orig_category":"Autorijscholen",
    "sg:phone":"+31 294 283 542",
    "sg:postcode":"1391 AG",
    "sg:province":"North Holland",
    "sg:website":"http://www.autorijschoolgriffioen.nl",
    "wof:name":"Griffioen, G W",
    "wof:placetype":"venue"
},
  "geometry": {"coordinates":[4.968802,52.277611],"type":"Point"}
}