{
  "type": "Feature",
  "properties": {
    "addr:full":"Vendelierstraat 11 Asten North Brabant 5721 MG",
    "addr:housenumber":"11",
    "addr:postcode":"5721 mg",
    "addr:street":"Vendelierstraat",
    "iso:country":"NL",
    "sg:address":"Vendelierstraat 11",
    "sg:city":"Asten",
    "sg:orig_category":"Diverse Bedrijfsinstallaties Gh",
    "sg:phone":"+31 493 699 595",
    "sg:postcode":"5721 MG",
    "sg:province":"North Brabant",
    "wof:name":"F. Koot",
    "wof:placetype":"venue"
},
  "geometry": {"coordinates":[5.757399,51.397243],"type":"Point"}
}