{
  "type": "Feature",
  "properties": {
    "addr:full":"Kleibultwg 90-92 Oldenzaal Overijssel 7575 BX",
    "addr:housenumber":"90-92",
    "addr:postcode":"7575 bx",
    "iso:country":"NL",
    "sg:address":"Kleibultwg 90-92",
    "sg:city":"Oldenzaal",
    "sg:orig_category":"Modelmakerijen",
    "sg:phone":"+31 541 570 300",
    "sg:postcode":"7575 BX",
    "sg:province":"Overijssel",
    "wof:name":"Twente Bv",
    "wof:placetype":"venue"
},
  "geometry": {"coordinates":[6.917445,52.297371],"type":"Point"}
}