{
  "type": "Feature",
  "properties": {
    "iso:country":"NL",
    "sg:address":"Vd Wateringeln 153",
    "sg:city":"Voorburg",
    "sg:orig_category":"Architecten En Architectenbureaus",
    "sg:phone":"+31 70 347 9277",
    "sg:postcode":"2274 CE",
    "sg:province":"Zuid-Holland",
    "wof:name":"Inter A70",
    "wof:placetype":"venue"
},
  "geometry": {"coordinates":[4.345164,52.077431],"type":"Point"}
}