{
  "type": "Feature",
  "properties": {
    "addr:full":"Oosteinde 11 Broek In Waterland Noord-Holland 1151 BT",
    "addr:housenumber":"11",
    "addr:postcode":"1151 bt",
    "addr:street":"Oosteinde",
    "iso:country":"NL",
    "sg:address":"Oosteinde 11",
    "sg:city":"Broek In Waterland",
    "sg:orig_category":"Grafisch Ontwerpers",
    "sg:phone":"+31 20 403 3487",
    "sg:postcode":"1151 BT",
    "sg:province":"Noord-Holland",
    "wof:name":"Mulder, H",
    "wof:placetype":"venue"
},
  "geometry": {"coordinates":[4.998372,52.436756],"type":"Point"}
}