{
  "type": "Feature",
  "properties": {
    "addr:full":"Noordeinde 249 Almere Flevoland 1334 BN",
    "addr:housenumber":"249",
    "addr:postcode":"1334 bn",
    "addr:street":"Noordeinde;Flevoland",
    "iso:country":"NL",
    "sg:address":"Noordeinde 249",
    "sg:city":"Almere",
    "sg:orig_category":"Kappers",
    "sg:phone":"+31 36 537 2488",
    "sg:postcode":"1334 BN",
    "sg:province":"Flevoland",
    "wof:name":"Haarmode 2000",
    "wof:placetype":"venue"
},
  "geometry": {"coordinates":[5.2779798508,52.3944892883],"type":"Point"}
}