{
  "type": "Feature",
  "properties": {
    "iso:country":"NL",
    "sg:address":"Kloosterstraat 6-8",
    "sg:city":"Helmond",
    "sg:classifiers":[
        {
            "category":"Professional",
            "subcategory":"Accounting & Tax Preparation",
            "type":"Services"
        }
    ],
    "sg:phone":"+31 492 540 770",
    "sg:postcode":"5708 GM",
    "sg:province":"North Brabant",
    "sg:tags":[
        "accountant"
    ],
    "wof:name":"Vullings & Partners Accountants & Consul",
    "wof:placetype":"venue"
},
  "geometry": {"coordinates":[5.618426,51.485756],"type":"Point"}
}