{
  "type": "Feature",
  "properties": {
    "addr:full":"Voorstr 142 Lekkerkerk South Holland 2941 EW",
    "addr:housenumber":"142",
    "addr:postcode":"2941 ew",
    "iso:country":"NL",
    "sg:address":"Voorstr 142",
    "sg:city":"Lekkerkerk",
    "sg:orig_category":"Kinderkleding",
    "sg:phone":"+31 180 662 322",
    "sg:postcode":"2941 EW",
    "sg:province":"South Holland",
    "wof:name":"Bofleur",
    "wof:placetype":"venue"
},
  "geometry": {"coordinates":[4.682791,51.894829],"type":"Point"}
}