{
  "type": "Feature",
  "properties": {
    "addr:full":"Oringerbrink 174 Emmen Drenthe 7812 JZ",
    "addr:housenumber":"174",
    "addr:postcode":"7812 jz",
    "addr:street":"Oringerbrink",
    "iso:country":"NL",
    "sg:address":"Oringerbrink 174",
    "sg:city":"Emmen",
    "sg:orig_category":"Boekhouders",
    "sg:phone":"+31 591 610 347",
    "sg:postcode":"7812 JZ",
    "sg:province":"Drenthe",
    "wof:name":"Admiraad / Emmen",
    "wof:placetype":"venue"
},
  "geometry": {"coordinates":[6.89068,52.763084],"type":"Point"}
}