{
  "type": "Feature",
  "properties": {
    "iso:country":"NL",
    "sg:address":"Vogelwg 16",
    "sg:city":"Alkmaar",
    "sg:classifiers":[
        {
            "category":"Personal",
            "subcategory":"Nail Salon",
            "type":"Services"
        }
    ],
    "sg:phone":"+31 72 561 5959",
    "sg:postcode":"1826 HA",
    "sg:province":"Noord-Holland",
    "sg:tags":[
        "pedicure"
    ],
    "wof:name":"Voortman, W G",
    "wof:placetype":"venue"
},
  "geometry": {"coordinates":[4.763368,52.658607],"type":"Point"}
}