{
  "type": "Feature",
  "properties": {
    "iso:country":"NL",
    "sg:address":"Rabatstraat 11",
    "sg:city":"Hengelo Ov",
    "sg:orig_category":"Glaszetten",
    "sg:phone":"+31 74 277 1851",
    "sg:postcode":"7559 CW",
    "sg:province":"Overijssel",
    "wof:name":"Glas- En Schilderwerken Ten Brummelhuis Bv",
    "wof:placetype":"venue"
},
  "geometry": {"coordinates":[6.811043,52.28997],"type":"Point"}
}