{
  "type": "Feature",
  "properties": {
    "addr:full":"De Houtmanstr 18 Hoek Van Holland Zuid-Holland 3151 TD",
    "addr:housenumber":"18",
    "addr:postcode":"3151 td",
    "addr:street":"De Houtmanstr",
    "iso:country":"NL",
    "sg:address":"De Houtmanstr 18",
    "sg:city":"Hoek Van Holland",
    "sg:classifiers":[
        {
            "category":"Personal",
            "subcategory":"Nail Salon",
            "type":"Services"
        }
    ],
    "sg:phone":"+31 174 386 408",
    "sg:postcode":"3151 TD",
    "sg:province":"Zuid-Holland",
    "sg:tags":[
        "pedicure"
    ],
    "wof:name":"Karsdorp, Cobie",
    "wof:placetype":"venue"
},
  "geometry": {"coordinates":[4.139496,51.973305],"type":"Point"}
}