{
  "type": "Feature",
  "properties": {
    "addr:full":"Dorpsstraat 203 Lunteren Gelderland 6741 AH",
    "addr:housenumber":"203",
    "addr:postcode":"6741 ah",
    "addr:street":"Dorpsstraat;Gelderland",
    "iso:country":"NL",
    "sg:address":"Dorpsstraat 203",
    "sg:city":"Lunteren",
    "sg:orig_category":"Loodgieterswerk, Verwarming And Sanitaire Installaties",
    "sg:phone":"+31 318 483 083",
    "sg:postcode":"6741 AH",
    "sg:province":"Gelderland",
    "wof:name":"T.H. Jongbloed",
    "wof:placetype":"venue"
},
  "geometry": {"coordinates":[5.618666,52.088627],"type":"Point"}
}