{
  "type": "Feature",
  "properties": {
    "iso:country":"NL",
    "sg:address":"Statenplein 21",
    "sg:city":"'S Gravenhage",
    "sg:orig_category":"Verzekeringen",
    "sg:phone":"+31 70 351 2281",
    "sg:postcode":"2582 EZ",
    "sg:province":"Zuid-Holland",
    "wof:name":"Van De Bosch & Looman Bv",
    "wof:placetype":"venue"
},
  "geometry": {"coordinates":[4.278281,52.090385],"type":"Point"}
}