{
  "type": "Feature",
  "properties": {
    "addr:full":"Kaldenkerkerweg 197 Tegelen Limburg 5932 DB",
    "addr:housenumber":"197",
    "addr:postcode":"5932 db",
    "addr:street":"Kaldenkerkerweg",
    "iso:country":"NL",
    "sg:address":"Kaldenkerkerweg 197",
    "sg:city":"Tegelen",
    "sg:orig_category":"Boomkwekerijen",
    "sg:phone":"+31 77 373 0808",
    "sg:postcode":"5932 DB",
    "sg:province":"Limburg",
    "wof:name":"M. Leenders & Co Bv",
    "wof:placetype":"venue"
},
  "geometry": {"coordinates":[6.16716,51.33091],"type":"Point"}
}