{
  "type": "Feature",
  "properties": {
    "addr:full":"M Hobbemastr 14 Veenendaal Utrecht 3904 XG",
    "addr:housenumber":"14",
    "addr:postcode":"3904 xg",
    "iso:country":"NL",
    "sg:address":"M Hobbemastr 14",
    "sg:city":"Veenendaal",
    "sg:orig_category":"Koeriersdiensten",
    "sg:phone":"+31 6 18681096",
    "sg:postcode":"3904 XG",
    "sg:province":"Utrecht",
    "wof:name":"Chv",
    "wof:placetype":"venue"
},
  "geometry": {"coordinates":[5.543872,52.021523],"type":"Point"}
}