{
  "type": "Feature",
  "properties": {
    "iso:country":"NL",
    "sg:address":"Aesculaapstraat 6",
    "sg:city":"Maastricht",
    "sg:orig_category":"Begrafenisondernemers",
    "sg:phone":"+31 43 343 2555",
    "sg:postcode":"6216 CM",
    "sg:province":"Limburg",
    "wof:name":"Uitvaartcentrum Dielemans",
    "wof:placetype":"venue"
},
  "geometry": {"coordinates":[5.664086,50.851219],"type":"Point"}
}