{
  "type": "Feature",
  "properties": {
    "addr:full":"Langedaal 19 Dordrecht South Holland 3317 MA",
    "addr:housenumber":"19",
    "addr:postcode":"3317 ma",
    "addr:street":"Langedaal",
    "iso:country":"NL",
    "sg:address":"Langedaal 19",
    "sg:city":"Dordrecht",
    "sg:orig_category":"Zonweringen",
    "sg:phone":"+31 78 617 7656",
    "sg:postcode":"3317 MA",
    "sg:province":"South Holland",
    "sg:website":"http://www.dekal.nl",
    "wof:name":"Faas Zonwering",
    "wof:placetype":"venue"
},
  "geometry": {"coordinates":[4.656634,51.782074],"type":"Point"}
}