{
  "type": "Feature",
  "properties": {
    "addr:full":"Insulindeln 113 Eindhoven Noord-Brabant 5642 CV",
    "addr:housenumber":"113",
    "addr:postcode":"5642 cv",
    "iso:country":"NL",
    "sg:address":"Insulindeln 113",
    "sg:city":"Eindhoven",
    "sg:orig_category":"Adviesbureaus Bouwkunde",
    "sg:phone":"+31 40 281 4455",
    "sg:postcode":"5642 CV",
    "sg:province":"Noord-Brabant",
    "wof:name":"Tielemans Bv",
    "wof:placetype":"venue"
},
  "geometry": {"coordinates":[5.504168,51.442406],"type":"Point"}
}