{
  "type": "Feature",
  "properties": {
    "addr:full":"Kerkstr 249 Oostzaan North Holland 1511 EG",
    "addr:housenumber":"249",
    "addr:postcode":"1511 eg",
    "iso:country":"NL",
    "sg:address":"Kerkstr 249",
    "sg:city":"Oostzaan",
    "sg:classifiers":[
        {
            "category":"Personal",
            "subcategory":"Nail Salon",
            "type":"Services"
        }
    ],
    "sg:phone":"+31 75 684 1561",
    "sg:postcode":"1511 EG",
    "sg:province":"North Holland",
    "sg:tags":[
        "pedicure"
    ],
    "wof:name":"Brink-Dral, A C Van Den",
    "wof:placetype":"venue"
},
  "geometry": {"coordinates":[4.874871,52.440029],"type":"Point"}
}