{
  "type": "Feature",
  "properties": {
    "iso:country":"NL",
    "sg:address":"De Til 1",
    "sg:city":"Koudekerk A/D Rijn",
    "sg:orig_category":"Loodgieterswerk, Verwarming And Sanitaire Installaties",
    "sg:phone":"+31 71 341 6348",
    "sg:postcode":"2396 DA",
    "sg:province":"Zuid-Holland",
    "wof:name":"Technisch Installatie Bedrijf Rijnland Vof",
    "wof:placetype":"venue"
},
  "geometry": {"coordinates":[4.606476,52.131176],"type":"Point"}
}