{
  "type": "Feature",
  "properties": {
    "addr:full":"Beckummerweg 10 Haaksbergen NL.08 7482 ST",
    "addr:housenumber":"10;nl.08",
    "addr:postcode":"7482",
    "addr:street":"Beckummerweg",
    "iso:country":"NL",
    "sg:address":"Beckummerweg 10",
    "sg:city":"Haaksbergen",
    "sg:orig_category":"Kappers",
    "sg:phone":"+31 74 357 5534",
    "sg:postcode":"7482 ST",
    "sg:province":"NL.08",
    "wof:name":"Kapsalon Wilma",
    "wof:placetype":"venue"
},
  "geometry": {"coordinates":[6.7116599083,52.192741394],"type":"Point"}
}