{
  "type": "Feature",
  "properties": {
    "iso:country":"NL",
    "sg:address":"De Maten 23",
    "sg:city":"Schoonebeek",
    "sg:orig_category":"Voegwerken",
    "sg:phone":"+31 524 532 119",
    "sg:postcode":"7761 DJ",
    "sg:province":"Drenthe",
    "wof:name":"Hoop, De",
    "wof:placetype":"venue"
},
  "geometry": {"coordinates":[6.884418,52.664829],"type":"Point"}
}