{
  "type": "Feature",
  "properties": {
    "iso:country":"NL",
    "sg:address":"Elandstraat 78",
    "sg:city":"Rotterdam",
    "sg:orig_category":"Diverse Bedrijfsinstallaties Gh",
    "sg:phone":"+31 10 450 3337",
    "sg:postcode":"3064 AH",
    "sg:province":"Zuid-Holland",
    "wof:name":"Erlas Bv",
    "wof:placetype":"venue"
},
  "geometry": {"coordinates":[4.555674,51.911179],"type":"Point"}
}