{
  "type": "Feature",
  "properties": {
    "iso:country":"NL",
    "sg:address":"Zylstr 71",
    "sg:city":"Haarlem",
    "sg:orig_category":"Bedrijfskleding",
    "sg:phone":"+31 23 531 0791",
    "sg:postcode":"2011 TL",
    "sg:province":"Noord-Holland",
    "wof:name":"Smit & Van Rijsbergen",
    "wof:placetype":"venue"
},
  "geometry": {"coordinates":[4.642253,52.380562],"type":"Point"}
}