{
  "type": "Feature",
  "properties": {
    "addr:full":"Passage Zuidpoort 1-3 Breda North Brabant 4811 NT",
    "addr:housenumber":"1-3",
    "addr:postcode":"4811 nt",
    "addr:street":"Passage Zuidpoort",
    "iso:country":"NL",
    "sg:address":"Passage Zuidpoort 1-3",
    "sg:city":"Breda",
    "sg:orig_category":"Meubelzaken, Woning- And Keukeninrichting",
    "sg:phone":"+31 76 531 0282",
    "sg:postcode":"4811 NT",
    "sg:province":"North Brabant",
    "wof:name":"Sleep And Health",
    "wof:placetype":"venue"
},
  "geometry": {"coordinates":[4.7779831886,51.582359314],"type":"Point"}
}