{
  "type": "Feature",
  "properties": {
    "addr:full":"Bosschewg 11 Berkel Enschot North Brabant 5056 PP",
    "addr:housenumber":"11",
    "addr:postcode":"5056 pp",
    "addr:street":"Bosschewg;Enschot",
    "iso:country":"NL",
    "sg:address":"Bosschewg 11",
    "sg:city":"Berkel Enschot",
    "sg:orig_category":"Beurzen",
    "sg:phone":"+31 13 533 4114",
    "sg:postcode":"5056 PP",
    "sg:province":"North Brabant",
    "wof:name":"Horeca Vakbeurs",
    "wof:placetype":"venue"
},
  "geometry": {"coordinates":[5.145004,51.576469],"type":"Point"}
}