{
  "type": "Feature",
  "properties": {
    "addr:full":"Haydnstr 32 Deurne North Brabant 5751 ES",
    "addr:housenumber":"32",
    "addr:postcode":"5751 es",
    "addr:street":"Haydnstr",
    "iso:country":"NL",
    "sg:address":"Haydnstr 32",
    "sg:city":"Deurne",
    "sg:orig_category":"Verenigingen En Stichtingen",
    "sg:phone":"+31 493 310 844",
    "sg:postcode":"5751 ES",
    "sg:province":"North Brabant",
    "wof:name":"Hobbycl Soos",
    "wof:placetype":"venue"
},
  "geometry": {"coordinates":[5.784874,51.46431],"type":"Point"}
}