{
  "type": "Feature",
  "properties": {
    "addr:full":"Nieuwe Havenweg 29 Arnhem Gelderland 6827 BA",
    "addr:housenumber":"29",
    "addr:postcode":"6827 ba",
    "addr:street":"Nieuwe Havenweg",
    "iso:country":"NL",
    "sg:address":"Nieuwe Havenweg 29",
    "sg:city":"Arnhem",
    "sg:orig_category":"Metaalbekleding And -Behandeling",
    "sg:phone":"+31 26 369 9611",
    "sg:postcode":"6827 BA",
    "sg:province":"Gelderland",
    "wof:name":"Wilke Carbide Bv",
    "wof:placetype":"venue"
},
  "geometry": {"coordinates":[5.937974,51.965847],"type":"Point"}
}