{
  "type": "Feature",
  "properties": {
    "addr:full":"Hornwg 5A Aalsmeer Noord-Holland 1432 GD",
    "addr:housenumber":"5a",
    "addr:postcode":"1432 gd",
    "addr:street":"Hornwg",
    "iso:country":"NL",
    "sg:address":"Hornwg 5A",
    "sg:city":"Aalsmeer",
    "sg:orig_category":"Beveiliging",
    "sg:phone":"+31 297 368 350",
    "sg:postcode":"1432 GD",
    "sg:province":"Noord-Holland",
    "sg:website":"http://www.ritom.nl",
    "wof:name":"Ritom",
    "wof:placetype":"venue"
},
  "geometry": {"coordinates":[4.779993,52.265987],"type":"Point"}
}