{
  "type": "Feature",
  "properties": {
    "addr:full":"Donkerstraat 34 Ravenswaaij Gelderland 4119 LZ",
    "addr:housenumber":"34",
    "addr:postcode":"4119 lz",
    "addr:street":"Donkerstraat;Gelderland",
    "iso:country":"NL",
    "sg:address":"Donkerstraat 34",
    "sg:city":"Ravenswaaij",
    "sg:orig_category":"Autokeuringen",
    "sg:phone":"+31 345 501 440",
    "sg:postcode":"4119 LZ",
    "sg:province":"Gelderland",
    "wof:name":"Stroband",
    "wof:placetype":"venue"
},
  "geometry": {"coordinates":[5.317613,51.946125],"type":"Point"}
}