{
  "type": "Feature",
  "properties": {
    "addr:full":"Meerlosewg 9 Oirlo Limburg 5808 AM",
    "addr:housenumber":"9",
    "addr:postcode":"5808",
    "addr:street":"Meerlosewg",
    "iso:country":"NL",
    "sg:address":"Meerlosewg 9",
    "sg:city":"Oirlo",
    "sg:orig_category":"Pluimveebedrijven En -Handelaren",
    "sg:phone":"+31 478 578 800",
    "sg:postcode":"5808 AM",
    "sg:province":"Limburg",
    "wof:name":"Zanders Bv",
    "wof:placetype":"venue"
},
  "geometry": {"coordinates":[6.03806,51.511135],"type":"Point"}
}