{
  "type": "Feature",
  "properties": {
    "addr:full":"Frits Kruitstraat 4 Schagen North Holland 1742 SZ",
    "addr:housenumber":"4",
    "addr:postcode":"1742 sz",
    "addr:street":"Frits Kruitstraat",
    "iso:country":"NL",
    "sg:address":"Frits Kruitstraat 4",
    "sg:city":"Schagen",
    "sg:orig_category":"Paramedische Behandelingen",
    "sg:phone":"+31 224 298 055",
    "sg:postcode":"1742 SZ",
    "sg:province":"North Holland",
    "wof:name":"Praktijk Bouma",
    "wof:placetype":"venue"
},
  "geometry": {"coordinates":[4.80331,52.777267],"type":"Point"}
}