{
  "type": "Feature",
  "properties": {
    "addr:full":"Van Homberghlaan 13 Sint Oedenrode North Brabant 5491 GM",
    "addr:housenumber":"13",
    "addr:postcode":"5491 gm",
    "addr:street":"Van Homberghlaan;Oedenrode",
    "iso:country":"NL",
    "sg:address":"Van Homberghlaan 13",
    "sg:city":"Sint Oedenrode",
    "sg:orig_category":"Verpakkingsmachines Fab",
    "sg:phone":"+31 413 477 440",
    "sg:postcode":"5491 GM",
    "sg:province":"North Brabant",
    "wof:name":"Th.A.M. Vermeltfoort",
    "wof:placetype":"venue"
},
  "geometry": {"coordinates":[5.461689,51.569771],"type":"Point"}
}