{
  "type": "Feature",
  "properties": {
    "iso:country":"NL",
    "sg:address":"Haagwinde 9",
    "sg:city":"Puttershoek",
    "sg:orig_category":"Bedrijfsmechanisatie En -Automatisering",
    "sg:phone":"+31 78 676 7211",
    "sg:postcode":"3297 WJ",
    "sg:province":"South Holland",
    "sg:website":"http://www.listo.nl",
    "wof:name":"Listo",
    "wof:placetype":"venue"
},
  "geometry": {"coordinates":[4.558787,51.799519],"type":"Point"}
}