{
  "type": "Feature",
  "properties": {
    "addr:full":"Neringpassage 16 Lelystad NL. 8224 JC",
    "addr:housenumber":"16",
    "addr:postcode":"8224 jc",
    "addr:street":"Neringpassage;Nl.",
    "iso:country":"NL",
    "sg:address":"Neringpassage 16",
    "sg:city":"Lelystad",
    "sg:orig_category":"Gespecialiseerde Voeding",
    "sg:phone":"+31 320 249 989",
    "sg:postcode":"8224 JC",
    "sg:province":"NL.",
    "wof:name":"Vof Rozemarijn De Vries Lelystad",
    "wof:placetype":"venue"
},
  "geometry": {"coordinates":[5.476778,52.509781],"type":"Point"}
}