{
  "type": "Feature",
  "properties": {
    "addr:full":"Oude Kijk In 'T Jatstr 32 Groningen Groningen 9712 EK",
    "addr:housenumber":"32",
    "addr:postcode":"9712 ek",
    "addr:street":"Oude Kijk In ' T Jatstr",
    "iso:country":"NL",
    "sg:address":"Oude Kijk In 'T Jatstr 32",
    "sg:city":"Groningen",
    "sg:orig_category":"Boekenuitgeverijen",
    "sg:phone":"+31 50 312 6950",
    "sg:postcode":"9712 EK",
    "sg:province":"Groningen",
    "wof:name":"Reisboekwinkel De Zwerver",
    "wof:placetype":"venue"
},
  "geometry": {"coordinates":[6.56368,53.221481],"type":"Point"}
}