{
  "type": "Feature",
  "properties": {
    "addr:full":"K Doormanln 28 Zoetermeer Zuid-Holland 2712 JK",
    "addr:housenumber":"28",
    "addr:postcode":"2712 jk",
    "addr:street":"Doormanln",
    "iso:country":"NL",
    "sg:address":"K Doormanln 28",
    "sg:city":"Zoetermeer",
    "sg:orig_category":"Webdesign Bureaus",
    "sg:phone":"+31 6 15465489",
    "sg:postcode":"2712 JK",
    "sg:province":"Zuid-Holland",
    "sg:website":"http://www.westhoek-solutions.nl",
    "wof:name":"Westhoek Solutions",
    "wof:placetype":"venue"
},
  "geometry": {"coordinates":[4.4992518425,52.0510292053],"type":"Point"}
}