{
  "type": "Feature",
  "properties": {
    "iso:country":"NL",
    "sg:address":"Hoofdwg 81",
    "sg:city":"De Kwakel",
    "sg:orig_category":"Bloemen En Planten - Groothandel",
    "sg:phone":"+31 297 383 444",
    "sg:postcode":"1424 PD",
    "sg:province":"Noord-Holland",
    "sg:website":"http://www.schreurs.nl",
    "wof:name":"Schreurs De Kwakel Bv, Piet",
    "wof:placetype":"venue"
},
  "geometry": {"coordinates":[4.774323,52.241459],"type":"Point"}
}