{
  "type": "Feature",
  "properties": {
    "iso:country":"NL",
    "sg:address":"Schiermonnikoogerf 3",
    "sg:city":"Tilburg",
    "sg:orig_category":"Bloemen And Planten",
    "sg:phone":"+31 13 468 3180",
    "sg:postcode":"5035 JH",
    "sg:province":"Noord-Brabant",
    "wof:name":"Alpina Bloemsierkunst",
    "wof:placetype":"venue"
},
  "geometry": {"coordinates":[4.977036,51.581982],"type":"Point"}
}