{
  "type": "Feature",
  "properties": {
    "addr:full":"Koningsplein 1 Asten North Brabant 5721 GJ",
    "addr:housenumber":"1",
    "addr:postcode":"5721 gj",
    "addr:street":"Koningsplein",
    "iso:country":"NL",
    "sg:address":"Koningsplein 1",
    "sg:city":"Asten",
    "sg:orig_category":"Bejaarden - Verzorgingstehuizen",
    "sg:phone":"+31 493 692 333",
    "sg:postcode":"5721 GJ",
    "sg:province":"North Brabant",
    "wof:name":"Bartholomeus",
    "wof:placetype":"venue"
},
  "geometry": {"coordinates":[5.744698,51.4034],"type":"Point"}
}