{
  "type": "Feature",
  "properties": {
    "addr:full":"Zandweg 2 Sirjansland Zeeland 4308 AA",
    "addr:housenumber":"2",
    "addr:postcode":"4308 aa",
    "addr:street":"Zandweg",
    "iso:country":"NL",
    "sg:address":"Zandweg 2",
    "sg:city":"Sirjansland",
    "sg:orig_category":"Kampeerterreinen",
    "sg:phone":"+31 111 643 294",
    "sg:postcode":"4308 AA",
    "sg:province":"Zeeland",
    "wof:name":"J.W. 'T Hart",
    "wof:placetype":"venue"
},
  "geometry": {"coordinates":[4.0343742371,51.6738891602],"type":"Point"}
}