{
  "type": "Feature",
  "properties": {
    "iso:country":"NL",
    "sg:address":"J Catsstr 17",
    "sg:city":"Katwyk Zh",
    "sg:orig_category":"Adviesbureaus Bedrijfsorganisatie",
    "sg:phone":"+31 71 402 3730",
    "sg:postcode":"2221 JA",
    "sg:province":"Zuid-Holland",
    "wof:name":"Male, Joop Van",
    "wof:placetype":"venue"
},
  "geometry": {"coordinates":[4.42057,52.187599],"type":"Point"}
}