{
  "type": "Feature",
  "properties": {
    "iso:country":"NL",
    "sg:address":"Kronenburggalery 1",
    "sg:city":"Arnhem",
    "sg:classifiers":[
        {
            "category":"Shopping",
            "subcategory":"Adult",
            "type":"Retail Goods"
        }
    ],
    "sg:phone":"+31 26 327 0031",
    "sg:postcode":"6831 ET",
    "sg:province":"Gelderland",
    "sg:tags":[
        "lingerie",
        "en",
        "tricotage"
    ],
    "sg:website":"http://www.xllingerie.nl",
    "wof:name":"Xl Lingerie & Women'S Wear",
    "wof:placetype":"venue"
},
  "geometry": {"coordinates":[5.897119,51.958076],"type":"Point"}
}