{
  "type": "Feature",
  "properties": {
    "addr:full":"Achillesstr 118 Amsterdam North Holland 1076 RJ",
    "addr:housenumber":"118",
    "addr:postcode":"1076 rj",
    "iso:country":"NL",
    "sg:address":"Achillesstr 118",
    "sg:city":"Amsterdam",
    "sg:orig_category":"Koeriersdiensten",
    "sg:phone":"+31 20 779 9606",
    "sg:postcode":"1076 RJ",
    "sg:province":"North Holland",
    "wof:name":"En Route",
    "wof:placetype":"venue"
},
  "geometry": {"coordinates":[4.864354,52.344421],"type":"Point"}
}