{
  "type": "Feature",
  "properties": {
    "addr:full":"Reiger 13 Hoorn Nh North Holland 1628 BA",
    "addr:housenumber":"13",
    "addr:postcode":"1628 ba",
    "addr:street":"Reiger;Nh North",
    "iso:country":"NL",
    "sg:address":"Reiger 13",
    "sg:city":"Hoorn Nh",
    "sg:orig_category":"Miniaturen",
    "sg:phone":"+31 229 297 032",
    "sg:postcode":"1628 BA",
    "sg:province":"North Holland",
    "wof:name":"Fantastic Cars",
    "wof:placetype":"venue"
},
  "geometry": {"coordinates":[5.080147,52.654385],"type":"Point"}
}