{
  "type": "Feature",
  "properties": {
    "iso:country":"NL",
    "sg:address":"Pieter Lastmankade 7",
    "sg:city":"Amsterdam",
    "sg:orig_category":"Verlichting And Huishoudartikelen",
    "sg:phone":"+31 20 470 9556",
    "sg:postcode":"1075 KJ",
    "sg:province":"North Holland",
    "wof:name":"Cocoon",
    "wof:placetype":"venue"
},
  "geometry": {"coordinates":[4.863568,52.350704],"type":"Point"}
}