{
  "type": "Feature",
  "properties": {
    "addr:full":"Franz-Lisztplantsoen 200 Utrecht Utrecht 3533 JG",
    "addr:housenumber":"200",
    "addr:postcode":"3533 jg",
    "addr:street":"Franz-Lisztplantsoen",
    "iso:country":"NL",
    "sg:address":"Franz-Lisztplantsoen 200",
    "sg:city":"Utrecht",
    "sg:orig_category":"Banken And Kredietinstellingen",
    "sg:phone":"+31 30 293 0700",
    "sg:postcode":"3533 JG",
    "sg:province":"Utrecht",
    "wof:name":"Kredietbank Nederland Nv",
    "wof:placetype":"venue"
},
  "geometry": {"coordinates":[5.095744,52.084164],"type":"Point"}
}