{
  "type": "Feature",
  "properties": {
    "addr:full":"Grootdorp 38 Merselo Limburg 5815 AE",
    "addr:housenumber":"38",
    "addr:postcode":"5815 ae",
    "addr:street":"Grootdorp",
    "iso:country":"NL",
    "sg:address":"Grootdorp 38",
    "sg:city":"Merselo",
    "sg:orig_category":"Kappers",
    "sg:phone":"+31 478 546 560",
    "sg:postcode":"5815 AE",
    "sg:province":"Limburg",
    "wof:name":"Engels Haarmode",
    "wof:placetype":"venue"
},
  "geometry": {"coordinates":[5.9282541275,51.5287132263],"type":"Point"}
}