{
  "type": "Feature",
  "properties": {
    "addr:full":"Pr Bernhardstr 12A Venray Limburg 5802 BM",
    "addr:housenumber":"12a",
    "addr:postcode":"5802 bm",
    "iso:country":"NL",
    "sg:address":"Pr Bernhardstr 12A",
    "sg:city":"Venray",
    "sg:orig_category":"Verenigingen En Stichtingen",
    "sg:phone":"+31 478 512 139",
    "sg:postcode":"5802 BM",
    "sg:province":"Limburg",
    "wof:name":"Senior Service Gilde Venray",
    "wof:placetype":"venue"
},
  "geometry": {"coordinates":[5.978555,51.524147],"type":"Point"}
}