{
  "type": "Feature",
  "properties": {
    "addr:full":"Schiethoek 34 Bergen Op Zoom North Brabant 4614 CR",
    "addr:housenumber":"34",
    "addr:postcode":"4614 cr",
    "addr:street":"Schiethoek",
    "iso:country":"NL",
    "sg:address":"Schiethoek 34",
    "sg:city":"Bergen Op Zoom",
    "sg:orig_category":"Boekhouders",
    "sg:phone":"+31 164 252 647",
    "sg:postcode":"4614 CR",
    "sg:province":"North Brabant",
    "wof:name":"Administratiekantoor De Meulder",
    "wof:placetype":"venue"
},
  "geometry": {"coordinates":[4.292913,51.504906],"type":"Point"}
}