{
  "type": "Feature",
  "properties": {
    "addr:full":"Het Leunenberg 570 Enschede NL.08 7544 JM",
    "addr:housenumber":"570",
    "addr:postcode":"7544 jm",
    "addr:street":"Het Leunenberg",
    "iso:country":"NL",
    "sg:address":"Het Leunenberg 570",
    "sg:city":"Enschede",
    "sg:orig_category":"Kinderopvang",
    "sg:phone":"+31 53 476 7821",
    "sg:postcode":"7544 JM",
    "sg:province":"NL.08",
    "wof:name":"Windroos, De",
    "wof:placetype":"venue"
},
  "geometry": {"coordinates":[6.880634,52.193062],"type":"Point"}
}