{
  "type": "Feature",
  "properties": {
    "iso:country":"NL",
    "sg:address":"Het Leunenberg 570",
    "sg:city":"Enschede",
    "sg:orig_category":"Kinderopvang",
    "sg:phone":"+31 53 476 7821",
    "sg:postcode":"7544 JM",
    "sg:province":"NL.08",
    "wof:name":"Windroos, De",
    "wof:placetype":"venue"
},
  "geometry": {"coordinates":[6.880634,52.193062],"type":"Point"}
}