{
  "type": "Feature",
  "properties": {
    "addr:full":"Vale Hen 1 Hoorn Nh Noord-Holland 1621 JX",
    "addr:housenumber":"1",
    "addr:postcode":"1621 jx",
    "addr:street":"Vale Hen",
    "iso:country":"NL",
    "sg:address":"Vale Hen 1",
    "sg:city":"Hoorn Nh",
    "sg:orig_category":"Werving And Selectie Van Tijdelijk Personeel And Uitzendkantoren",
    "sg:phone":"+31 229 273 700",
    "sg:postcode":"1621 JX",
    "sg:province":"Noord-Holland",
    "wof:name":"Content",
    "wof:placetype":"venue"
},
  "geometry": {"coordinates":[5.0523428917,52.6421127319],"type":"Point"}
}