{
  "type": "Feature",
  "properties": {
    "addr:full":"Paviljoenwg 2 Oostburg Zeeland 4501 NJ",
    "addr:housenumber":"2",
    "addr:postcode":"4501 nj",
    "addr:street":"Paviljoenwg",
    "iso:country":"NL",
    "sg:address":"Paviljoenwg 2",
    "sg:city":"Oostburg",
    "sg:orig_category":"Paardensport",
    "sg:phone":"+31 117 450 420",
    "sg:postcode":"4501 NJ",
    "sg:province":"Zeeland",
    "sg:website":"http://www.parelli.nl",
    "wof:name":"Eddy Modde",
    "wof:placetype":"venue"
},
  "geometry": {"coordinates":[3.451836,51.312122],"type":"Point"}
}