{
  "type": "Feature",
  "properties": {
    "addr:full":"Varkensmarkt 26 Vianen Zh Utrecht 4132 BB",
    "addr:housenumber":"26",
    "addr:postcode":"zh;4132 bb",
    "addr:street":"Varkensmarkt",
    "iso:country":"NL",
    "sg:address":"Varkensmarkt 26",
    "sg:city":"Vianen Zh",
    "sg:orig_category":"Onroerende Goederen",
    "sg:phone":"+31 347 376 126",
    "sg:postcode":"4132 BB",
    "sg:province":"Utrecht",
    "wof:name":"Ouwerkerk Bv",
    "wof:placetype":"venue"
},
  "geometry": {"coordinates":[5.094457,51.995365],"type":"Point"}
}