{
  "type": "Feature",
  "properties": {
    "addr:full":"Wethouder Theunissenhof 11 Milsbeek Limburg 6596 EA",
    "addr:housenumber":"11",
    "addr:postcode":"6596 ea",
    "addr:street":"Wethouder Theunissenhof",
    "iso:country":"NL",
    "sg:address":"Wethouder Theunissenhof 11",
    "sg:city":"Milsbeek",
    "sg:orig_category":"Loodgieterswerk, Verwarming And Sanitaire Installaties",
    "sg:phone":"+31 485 515 857",
    "sg:postcode":"6596 EA",
    "sg:province":"Limburg",
    "wof:name":"H.J. Kaus Eikholt",
    "wof:placetype":"venue"
},
  "geometry": {"coordinates":[5.94956,51.72438],"type":"Point"}
}