{
  "type": "Feature",
  "properties": {
    "addr:full":"Nieuwewg N 312A Veenendaal Utrecht 3905 LX",
    "addr:housenumber":"312a",
    "addr:postcode":"3905 lx",
    "addr:street":"N",
    "iso:country":"NL",
    "sg:address":"Nieuwewg N 312A",
    "sg:city":"Veenendaal",
    "sg:classifiers":[
        {
            "category":"Home & Garden",
            "subcategory":"Building Materials",
            "type":"Retail Goods"
        }
    ],
    "sg:phone":"+31 318 524 084",
    "sg:postcode":"3905 LX",
    "sg:province":"Utrecht",
    "sg:tags":[
        "hout",
        "en",
        "board",
        "triplex"
    ],
    "sg:website":"http://www.menpvandoorn.nl",
    "wof:name":"Doorn, M En P Van",
    "wof:placetype":"venue"
},
  "geometry": {"coordinates":[5.557169,52.04306],"type":"Point"}
}