{
  "type": "Feature",
  "properties": {
    "addr:full":"Vaart Zz 17 Assen Provincie Drenthe 9401 GE",
    "addr:housenumber":"17",
    "addr:postcode":"9401",
    "addr:street":"Vaart Zz;Provincie Drenthe",
    "iso:country":"NL",
    "sg:address":"Vaart Zz 17",
    "sg:city":"Assen",
    "sg:orig_category":"Onroerende Goederen",
    "sg:phone":"+31 592 309 457",
    "sg:postcode":"9401 GE",
    "sg:province":"Provincie Drenthe",
    "wof:name":"Steenhoeve Bv",
    "wof:placetype":"venue"
},
  "geometry": {"coordinates":[6.557207,52.993568],"type":"Point"}
}