{
  "type": "Feature",
  "properties": {
    "addr:full":"Prinseneiland 59 Amsterdam Noord-Holland 1013 LM",
    "addr:housenumber":"59",
    "addr:postcode":"1013 lm",
    "addr:street":"Prinseneiland",
    "iso:country":"NL",
    "sg:address":"Prinseneiland 59",
    "sg:city":"Amsterdam",
    "sg:orig_category":"Fotografie Reclame En Mode",
    "sg:phone":"+31 20 639 1455",
    "sg:postcode":"1013 LM",
    "sg:province":"Noord-Holland",
    "wof:name":"Swinkels, K S",
    "wof:placetype":"venue"
},
  "geometry": {"coordinates":[4.886869,52.386333],"type":"Point"}
}