{
  "type": "Feature",
  "properties": {
    "addr:full":"Sandery 15 Delden Overijssel 7491 GX",
    "addr:housenumber":"15",
    "addr:postcode":"7491 gx",
    "addr:street":"Sandery",
    "iso:country":"NL",
    "sg:address":"Sandery 15",
    "sg:city":"Delden",
    "sg:orig_category":"Adviesbureaus Bedrijfsorganisatie",
    "sg:phone":"+31 74 376 7191",
    "sg:postcode":"7491 GX",
    "sg:province":"Overijssel",
    "wof:name":"Buro 5",
    "wof:placetype":"venue"
},
  "geometry": {"coordinates":[6.695981,52.256336],"type":"Point"}
}