{
  "type": "Feature",
  "properties": {
    "addr:full":"Petuniatuin 10 Zoetermeer South Holland 2724 NA",
    "addr:housenumber":"10",
    "addr:postcode":"2724 na",
    "addr:street":"Petuniatuin",
    "iso:country":"NL",
    "sg:address":"Petuniatuin 10",
    "sg:city":"Zoetermeer",
    "sg:classifiers":[
        {
            "category":"Fast Food",
            "type":"Food & Drink"
        }
    ],
    "sg:phone":"+31 79 342 0078",
    "sg:postcode":"2724 NA",
    "sg:province":"South Holland",
    "sg:tags":[
        "afhaal",
        "restaurant"
    ],
    "wof:name":"Snackbarry",
    "wof:placetype":"venue"
},
  "geometry": {"coordinates":[4.514046,52.064121],"type":"Point"}
}