{
  "type": "Feature",
  "properties": {
    "iso:country":"NL",
    "sg:address":"Burghoffwg 14",
    "sg:city":"Roermond",
    "sg:orig_category":"Automaterialen En Gereedschappen",
    "sg:phone":"+31 475 326 394",
    "sg:postcode":"6042 EX",
    "sg:province":"Limburg",
    "wof:name":"Autoparts Roermond",
    "wof:placetype":"venue"
},
  "geometry": {"coordinates":[6.01485,51.209187],"type":"Point"}
}