{
  "type": "Feature",
  "properties": {
    "addr:full":"Postbus 5060 Venray Limburg 5800 GB",
    "addr:postcode":"5060 venray;5800 gb",
    "addr:street":"Postbus",
    "iso:country":"NL",
    "sg:address":"Postbus 5060",
    "sg:city":"Venray",
    "sg:orig_category":"Ventilatiesystemen",
    "sg:phone":"+31 478 515 252",
    "sg:postcode":"5800 GB",
    "sg:province":"Limburg",
    "sg:website":"http://www.bovema-sair.nl",
    "wof:name":"Bovema S-Air Bv",
    "wof:placetype":"venue"
},
  "geometry": {"coordinates":[5.977073,51.527157],"type":"Point"}
}