{
  "type": "Feature",
  "properties": {
    "iso:country":"NL",
    "sg:address":"Johanna Naber-Erf 222",
    "sg:city":"Dordrecht",
    "sg:orig_category":"Architecten",
    "sg:phone":"+31 78 621 3075",
    "sg:postcode":"3315 HG",
    "sg:province":"Zuid-Holland",
    "wof:name":"Architectenbureau K. Dekker",
    "wof:placetype":"venue"
},
  "geometry": {"coordinates":[4.734905,51.801247],"type":"Point"}
}