{
  "type": "Feature",
  "properties": {
    "addr:full":"Valkenburgerweg 17 Oegstgeest South Holland 2342 BZ",
    "addr:housenumber":"17",
    "addr:postcode":"2342 bz",
    "addr:street":"Valkenburgerweg",
    "iso:country":"NL",
    "sg:address":"Valkenburgerweg 17",
    "sg:city":"Oegstgeest",
    "sg:orig_category":"Bloemen And Planten",
    "sg:phone":"+31 71 402 3628",
    "sg:postcode":"2342 BZ",
    "sg:province":"South Holland",
    "wof:name":"Fa. D.C. Kromhout En Zn.",
    "wof:placetype":"venue"
},
  "geometry": {"coordinates":[4.442359,52.180798],"type":"Point"}
}