{
  "type": "Feature",
  "properties": {
    "addr:full":"Grotestr 257 Drunen Noord-Brabant 5151 BM",
    "addr:housenumber":"257",
    "addr:postcode":"5151 bm",
    "iso:country":"NL",
    "sg:address":"Grotestr 257",
    "sg:city":"Drunen",
    "sg:orig_category":"Fotojournalisten Freelance",
    "sg:phone":"+31 416 374 530",
    "sg:postcode":"5151 BM",
    "sg:province":"Noord-Brabant",
    "wof:name":"Chris Van Cromvoirt Fotografie",
    "wof:placetype":"venue"
},
  "geometry": {"coordinates":[5.14477,51.686462],"type":"Point"}
}