{
  "type": "Feature",
  "properties": {
    "addr:full":"H De Ruiterstr 1 Assen Drenthe 9401 KT",
    "addr:housenumber":"1",
    "addr:postcode":"9401 kt",
    "iso:country":"NL",
    "sg:address":"H De Ruiterstr 1",
    "sg:city":"Assen",
    "sg:orig_category":"Ziekenhuizen, Sanatoria, Verpleeghuizen",
    "sg:phone":"+31 592 381 900",
    "sg:postcode":"9401 KT",
    "sg:province":"Drenthe",
    "wof:name":"Ipd",
    "wof:placetype":"venue"
},
  "geometry": {"coordinates":[6.570505,52.993168],"type":"Point"}
}