{
  "type": "Feature",
  "properties": {
    "iso:country":"NL",
    "sg:address":"Valkweg 6",
    "sg:city":"Sliedrecht",
    "sg:orig_category":"Fitnesscentra",
    "sg:phone":"+31 184 410 206",
    "sg:postcode":"3362 GH",
    "sg:province":"South Holland",
    "wof:name":"Fitness & Beauty Palace",
    "wof:placetype":"venue"
},
  "geometry": {"coordinates":[4.789244,51.824535],"type":"Point"}
}