{
  "type": "Feature",
  "properties": {
    "addr:full":"Ellertsveld 26 Huizen Noord-Holland 1274 KD",
    "addr:housenumber":"26",
    "addr:postcode":"1274 kd",
    "addr:street":"Ellertsveld",
    "iso:country":"NL",
    "sg:address":"Ellertsveld 26",
    "sg:city":"Huizen",
    "sg:orig_category":"Glazenwasserijen",
    "sg:phone":"+31 35 525 4681",
    "sg:postcode":"1274 KD",
    "sg:province":"Noord-Holland",
    "wof:name":"Eijpen, P J J",
    "wof:placetype":"venue"
},
  "geometry": {"coordinates":[5.27326,52.297253],"type":"Point"}
}