{
  "type": "Feature",
  "properties": {
    "addr:full":"Maarnse Grindweg 18 Maarn Utrecht 3951 LK",
    "addr:housenumber":"18",
    "addr:postcode":"3951 lk",
    "addr:street":"Maarnse Grindweg",
    "iso:country":"NL",
    "sg:address":"Maarnse Grindweg 18",
    "sg:city":"Maarn",
    "sg:orig_category":"Bloemen And Planten",
    "sg:phone":"+31 343 441 492",
    "sg:postcode":"3951 LK",
    "sg:province":"Utrecht",
    "wof:name":"Tuincentrum & Hoveniers De Bremstee R. Vd Heuvel",
    "wof:placetype":"venue"
},
  "geometry": {"coordinates":[5.359952,52.062103],"type":"Point"}
}