{
  "type": "Feature",
  "properties": {
    "addr:full":"Arthur Van Schendelstr 612 Utrecht Utrecht 3511 MJ",
    "addr:housenumber":"612",
    "addr:postcode":"3511 mj",
    "addr:street":"Arthur Van Schendelstr",
    "iso:country":"NL",
    "sg:address":"Arthur Van Schendelstr 612",
    "sg:city":"Utrecht",
    "sg:orig_category":"Diverse Opleidingen And Onderwijs",
    "sg:phone":"+31 30 232 9555",
    "sg:postcode":"3511 MJ",
    "sg:province":"Utrecht",
    "wof:name":"Shl Nederland Bv",
    "wof:placetype":"venue"
},
  "geometry": {"coordinates":[5.117909,52.081985],"type":"Point"}
}