{
  "type": "Feature",
  "properties": {
    "addr:full":"Hoornsediep 147 Groningen Groningen 9727 GH",
    "addr:housenumber":"147",
    "addr:postcode":"9727 gh",
    "addr:street":"Hoornsediep",
    "iso:country":"NL",
    "sg:address":"Hoornsediep 147",
    "sg:city":"Groningen",
    "sg:orig_category":"Meubelzaken, Woning- And Keukeninrichting",
    "sg:phone":"+31 50 527 5888",
    "sg:postcode":"9727 GH",
    "sg:province":"Groningen",
    "wof:name":"Meubelhuis Hoornsediep",
    "wof:placetype":"venue"
},
  "geometry": {"coordinates":[6.562528,53.204357],"type":"Point"}
}