{
  "type": "Feature",
  "properties": {
    "addr:full":"Singelweg 11 Winterswijk Gelderland 7101 MH",
    "addr:housenumber":"11",
    "addr:postcode":"7101 mh",
    "addr:street":"Singelweg;Gelderland",
    "iso:country":"NL",
    "sg:address":"Singelweg 11",
    "sg:city":"Winterswijk",
    "sg:orig_category":"Vertaal- And Tolkenbureaus",
    "sg:phone":"+31 543 517 452",
    "sg:postcode":"7101 MH",
    "sg:province":"Gelderland",
    "wof:name":"G.W. Tolkamp",
    "wof:placetype":"venue"
},
  "geometry": {"coordinates":[6.721637,51.974659],"type":"Point"}
}