{
  "type": "Feature",
  "properties": {
    "addr:full":"Noorderbreedte 93 Amsterdam North Holland 1034 PL",
    "addr:housenumber":"93",
    "addr:postcode":"1034 pl",
    "addr:street":"Noorderbreedte",
    "iso:country":"NL",
    "sg:address":"Noorderbreedte 93",
    "sg:city":"Amsterdam",
    "sg:orig_category":"Technische Studies And Onderzoek",
    "sg:phone":"+31 20 631 6486",
    "sg:postcode":"1034 PL",
    "sg:province":"North Holland",
    "wof:name":"R.B. Research",
    "wof:placetype":"venue"
},
  "geometry": {"coordinates":[4.924211,52.412407],"type":"Point"}
}