{
  "type": "Feature",
  "properties": {
    "addr:full":"St. Maartensloop 58 Tilburg Noord-Brabant 5032 CX",
    "addr:housenumber":"58",
    "addr:postcode":"5032 cx",
    "iso:country":"NL",
    "sg:address":"St. Maartensloop 58",
    "sg:city":"Tilburg",
    "sg:orig_category":"Binnenhuisarchitecten",
    "sg:phone":"+31 13 463 4674",
    "sg:postcode":"5032 CX",
    "sg:province":"Noord-Brabant",
    "wof:name":"Kuipersprojectadvies",
    "wof:placetype":"venue"
},
  "geometry": {"coordinates":[5.03464,51.542831],"type":"Point"}
}