{
  "type": "Feature",
  "properties": {
    "iso:country":"NL",
    "sg:address":"Slot Loeves Str 37",
    "sg:city":"Tilburg",
    "sg:orig_category":"Adviesbureaus Personeel",
    "sg:phone":"+31 13 468 9271",
    "sg:postcode":"5037 HV",
    "sg:province":"Noord-Brabant",
    "wof:name":"Elsen Bv, Van Den",
    "wof:placetype":"venue"
},
  "geometry": {"coordinates":[5.053875,51.558468],"type":"Point"}
}