{
  "type": "Feature",
  "properties": {
    "addr:full":"Wymerswg 43 Loppersum Groningen 9919 BJ",
    "addr:housenumber":"43",
    "addr:postcode":"9919 bj",
    "addr:street":"Wymerswg",
    "iso:country":"NL",
    "sg:address":"Wymerswg 43",
    "sg:city":"Loppersum",
    "sg:orig_category":"Verzekeringen - Verzekeringskantoren",
    "sg:phone":"+31 596 572 211",
    "sg:postcode":"9919 BJ",
    "sg:province":"Groningen",
    "sg:website":"http://www.accesnet.nl/univehgv",
    "wof:name":"Univ\u00e9",
    "wof:placetype":"venue"
},
  "geometry": {"coordinates":[6.746046,53.328606],"type":"Point"}
}