{
  "type": "Feature",
  "properties": {
    "addr:full":"Heezerweg 294 Eindhoven Noord-Brabant 5643 KM",
    "addr:housenumber":"294",
    "addr:postcode":"5643 km",
    "addr:street":"Heezerweg",
    "iso:country":"NL",
    "sg:address":"Heezerweg 294",
    "sg:city":"Eindhoven",
    "sg:orig_category":"Juweliers",
    "sg:phone":"+31 40 211 3489",
    "sg:postcode":"5643 KM",
    "sg:province":"Noord-Brabant",
    "wof:name":"Juwelier Goldtime",
    "wof:placetype":"venue"
},
  "geometry": {"coordinates":[5.498765,51.423363],"type":"Point"}
}