{
  "type": "Feature",
  "properties": {
    "addr:full":"Energiewg 12-18 Barneveld Gelderland 3771 NA",
    "addr:housenumber":"12-18",
    "addr:postcode":"3771 na",
    "addr:street":"Gelderland",
    "iso:country":"NL",
    "sg:address":"Energiewg 12-18",
    "sg:city":"Barneveld",
    "sg:orig_category":"Banden",
    "sg:phone":"+31 342 415 468",
    "sg:postcode":"3771 NA",
    "sg:province":"Gelderland",
    "sg:website":"http://www.profile.nl",
    "wof:name":"Profile Tyrecenter Carservice",
    "wof:placetype":"venue"
},
  "geometry": {"coordinates":[5.603509,52.165806],"type":"Point"}
}