{
  "type": "Feature",
  "properties": {
    "addr:full":"Sorbonneln 195 Maastricht Limburg 6229 HD",
    "addr:housenumber":"195",
    "addr:postcode":"6229 hd",
    "iso:country":"NL",
    "sg:address":"Sorbonneln 195",
    "sg:city":"Maastricht",
    "sg:orig_category":"Kinderopvang",
    "sg:phone":"+31 43 367 1984",
    "sg:postcode":"6229 HD",
    "sg:province":"Limburg",
    "wof:name":"Rataplan",
    "wof:placetype":"venue"
},
  "geometry": {"coordinates":[5.709856,50.833508],"type":"Point"}
}