{
  "type": "Feature",
  "properties": {
    "addr:full":"Verbreepark 27 Benthuizen South Holland 2731 BR",
    "addr:housenumber":"27",
    "addr:postcode":"2731 br",
    "addr:street":"Verbreepark",
    "iso:country":"NL",
    "sg:address":"Verbreepark 27",
    "sg:city":"Benthuizen",
    "sg:orig_category":"Meubelen",
    "sg:phone":"+31 79 331 1200",
    "sg:postcode":"2731 BR",
    "sg:province":"South Holland",
    "sg:website":"http://www.vanwaayinterieurs.com",
    "wof:name":"Waay Interieurs, Van",
    "wof:placetype":"venue"
},
  "geometry": {"coordinates":[4.555155,52.074451],"type":"Point"}
}