{
  "type": "Feature",
  "properties": {
    "addr:full":"Operastr 48 Barendrecht South Holland 2992 GA",
    "addr:housenumber":"48",
    "addr:postcode":"2992 ga",
    "addr:street":"Operastr",
    "iso:country":"NL",
    "sg:address":"Operastr 48",
    "sg:city":"Barendrecht",
    "sg:orig_category":"Onderhoudswerken",
    "sg:phone":"+31 180 620 056",
    "sg:postcode":"2992 GA",
    "sg:province":"South Holland",
    "wof:name":"Noordijk",
    "wof:placetype":"venue"
},
  "geometry": {"coordinates":[4.524711,51.856258],"type":"Point"}
}