{
  "type": "Feature",
  "properties": {
    "addr:full":"Deltasingel 46 Deurne Noord-Brabant 5751 SM",
    "addr:housenumber":"46",
    "addr:postcode":"5751 sm",
    "addr:street":"Deltasingel",
    "iso:country":"NL",
    "sg:address":"Deltasingel 46",
    "sg:city":"Deurne",
    "sg:orig_category":"Vertaal- And Tolkenbureaus",
    "sg:phone":"+31 493 310 502",
    "sg:postcode":"5751 SM",
    "sg:province":"Noord-Brabant",
    "wof:name":"Double Write Vertaalburo",
    "wof:placetype":"venue"
},
  "geometry": {"coordinates":[5.809968,51.457756],"type":"Point"}
}