{
  "type": "Feature",
  "properties": {
    "addr:full":"Richterinkstr 7 Aalten Gelderland 7122 ZA",
    "addr:housenumber":"7",
    "addr:postcode":"7122",
    "addr:street":"Richterinkstr;Gelderland",
    "iso:country":"NL",
    "sg:address":"Richterinkstr 7",
    "sg:city":"Aalten",
    "sg:orig_category":"Kappers",
    "sg:phone":"+31 543 474 223",
    "sg:postcode":"7122 ZA",
    "sg:province":"Gelderland",
    "wof:name":"Marja",
    "wof:placetype":"venue"
},
  "geometry": {"coordinates":[6.569679,51.927162],"type":"Point"}
}