{
  "type": "Feature",
  "properties": {
    "iso:country":"NL",
    "sg:address":"Goudln 31",
    "sg:city":"S Gravenhage",
    "sg:orig_category":"Bloemen En Planten",
    "sg:phone":"+31 70 359 5478",
    "sg:postcode":"2544 EG",
    "sg:province":"Zuid-Holland",
    "sg:website":"http://www.groenplein.nl",
    "wof:name":"Bloemenbode Den Haag Bv",
    "wof:placetype":"venue"
},
  "geometry": {"coordinates":[4.25157,52.039551],"type":"Point"}
}