{
  "type": "Feature",
  "properties": {
    "addr:full":"Lupine Oord 65 Houten Utrecht 3991 VH",
    "addr:housenumber":"65",
    "addr:postcode":"3991 vh",
    "addr:street":"Lupine Oord",
    "iso:country":"NL",
    "sg:address":"Lupine Oord 65",
    "sg:city":"Houten",
    "sg:classifiers":[
        {
            "category":"Home & Garden",
            "subcategory":"Building Materials",
            "type":"Retail Goods"
        }
    ],
    "sg:phone":"+31 30 634 1666",
    "sg:postcode":"3991 VH",
    "sg:province":"Utrecht",
    "sg:tags":[
        "hout",
        "en",
        "board",
        "triplex"
    ],
    "wof:name":"Monsjou & Van Der Vlugt Bv",
    "wof:placetype":"venue"
},
  "geometry": {"coordinates":[5.156175,52.031788],"type":"Point"}
}