{
  "type": "Feature",
  "properties": {
    "addr:full":"B V Meursstr 33 Oldenzaal Overijssel 7576 BL",
    "addr:housenumber":"33",
    "addr:postcode":"7576 bl",
    "addr:street":"V Meursstr",
    "iso:country":"NL",
    "sg:address":"B V Meursstr 33",
    "sg:city":"Oldenzaal",
    "sg:classifiers":[
        {
            "category":"Personal",
            "subcategory":"Nail Salon",
            "type":"Services"
        }
    ],
    "sg:phone":"+31 541 513 371",
    "sg:postcode":"7576 BL",
    "sg:province":"Overijssel",
    "sg:tags":[
        "pedicure"
    ],
    "wof:name":"Koning, Lucie",
    "wof:placetype":"venue"
},
  "geometry": {"coordinates":[6.927277,52.309284],"type":"Point"}
}