{
  "type": "Feature",
  "properties": {
    "addr:full":"Ampereln 4D Ryswyk Zh South Holland 2289 CD",
    "addr:postcode":"2289 cd",
    "iso:country":"NL",
    "sg:address":"Ampereln 4D",
    "sg:city":"Ryswyk Zh",
    "sg:orig_category":"Bedrijfsorganisaties",
    "sg:phone":"+31 70 319 5195",
    "sg:postcode":"2289 CD",
    "sg:province":"South Holland",
    "wof:name":"Produktschap Margarine Vetten & Oli?n",
    "wof:placetype":"venue"
},
  "geometry": {"coordinates":[4.32436,52.037251],"type":"Point"}
}