{
  "type": "Feature",
  "properties": {
    "addr:full":"Raadhuispln 34 Nieuwerkerk Yssel Zuid-Holland 2914 KM",
    "addr:housenumber":"34",
    "addr:postcode":"2914 km",
    "addr:street":"Raadhuispln",
    "iso:country":"NL",
    "sg:address":"Raadhuispln 34",
    "sg:city":"Nieuwerkerk Yssel",
    "sg:orig_category":"Makelaars En Adviseurs Onroerende Goederen",
    "sg:phone":"+31 180 315 544",
    "sg:postcode":"2914 KM",
    "sg:province":"Zuid-Holland",
    "sg:website":"http://www.scheele.nl",
    "wof:name":"Scheele, M",
    "wof:placetype":"venue"
},
  "geometry": {"coordinates":[4.616295,51.967411],"type":"Point"}
}