{
  "type": "Feature",
  "properties": {
    "iso:country":"NL",
    "sg:address":"Industriewg 6",
    "sg:city":"Oostburg",
    "sg:orig_category":"Autoschade- Herstelbedrijven",
    "sg:phone":"+31 117 454 520",
    "sg:postcode":"4501 PM",
    "sg:province":"Zeeland",
    "wof:name":"Dekker Oostburg Bv",
    "wof:placetype":"venue"
},
  "geometry": {"coordinates":[3.498644,51.333195],"type":"Point"}
}