{
  "type": "Feature",
  "properties": {
    "iso:country":"NL",
    "sg:address":"Julianaln 74",
    "sg:city":"Ermelo",
    "sg:orig_category":"Fotoreportages",
    "sg:phone":"+31 341 454 376",
    "sg:postcode":"3853 KK",
    "sg:province":"Gelderland",
    "wof:name":"Dis",
    "wof:placetype":"venue"
},
  "geometry": {"coordinates":[5.615449,52.312588],"type":"Point"}
}