{
  "type": "Feature",
  "properties": {
    "iso:country":"NL",
    "sg:address":"Hoofdweg 10",
    "sg:city":"Capelle A/D Ijssel",
    "sg:orig_category":"Goederenvervoer Over De Weg",
    "sg:phone":"+31 10 442 6939",
    "sg:postcode":"2908 LC",
    "sg:province":"Zuid-Holland",
    "wof:name":"Weber Transport Bv",
    "wof:placetype":"venue"
},
  "geometry": {"coordinates":[4.57233,51.954182],"type":"Point"}
}