{
  "type": "Feature",
  "properties": {
    "addr:full":"Raadhuisstraat 1 Venray Limburg 5801 MB",
    "addr:housenumber":"1",
    "addr:postcode":"5801 mb",
    "addr:street":"Raadhuisstraat",
    "iso:country":"NL",
    "sg:address":"Raadhuisstraat 1",
    "sg:city":"Venray",
    "sg:orig_category":"Overheidsdiensten",
    "sg:phone":"+31 478 523 333",
    "sg:postcode":"5801 MB",
    "sg:province":"Limburg",
    "wof:name":"Gemeente Venray",
    "wof:placetype":"venue"
},
  "geometry": {"coordinates":[5.9765958786,51.5288543701],"type":"Point"}
}