{
  "type": "Feature",
  "properties": {
    "iso:country":"NL",
    "sg:address":"Kastanjeln 22",
    "sg:city":"Malden",
    "sg:orig_category":"Adviesbureaus Bedrijfsorganisatie",
    "sg:phone":"+31 24 388 0266",
    "sg:postcode":"6581 PX",
    "sg:province":"Gelderland",
    "wof:name":"Blanjaar, Ir J A",
    "wof:placetype":"venue"
},
  "geometry": {"coordinates":[5.867382,51.780434],"type":"Point"}
}