{
  "type": "Feature",
  "properties": {
    "addr:full":"Kastanjeln 22 Malden Gelderland 6581 PX",
    "addr:housenumber":"22",
    "addr:postcode":"6581 px",
    "addr:street":"Kastanjeln;Gelderland",
    "iso:country":"NL",
    "sg:address":"Kastanjeln 22",
    "sg:city":"Malden",
    "sg:orig_category":"Adviesbureaus Bedrijfsorganisatie",
    "sg:phone":"+31 24 388 0266",
    "sg:postcode":"6581 PX",
    "sg:province":"Gelderland",
    "wof:name":"Blanjaar, Ir J A",
    "wof:placetype":"venue"
},
  "geometry": {"coordinates":[5.867382,51.780434],"type":"Point"}
}