{
  "type": "Feature",
  "properties": {
    "addr:full":"Patrijslaan 1 Boekel Noord-Brabant 5427 VM",
    "addr:housenumber":"1",
    "addr:postcode":"5427 vm",
    "addr:street":"Patrijslaan",
    "iso:country":"NL",
    "sg:address":"Patrijslaan 1",
    "sg:city":"Boekel",
    "sg:orig_category":"Diverse Bedrijfsinstallaties Gh",
    "sg:phone":"+31 492 322 244",
    "sg:postcode":"5427 VM",
    "sg:province":"Noord-Brabant",
    "wof:name":"J.M. Van Alebeek",
    "wof:placetype":"venue"
},
  "geometry": {"coordinates":[5.680969,51.600208],"type":"Point"}
}