{
  "type": "Feature",
  "properties": {
    "iso:country":"NL",
    "sg:address":"Spuiwg 14",
    "sg:city":"Waalwyk",
    "sg:orig_category":"Plaatwerk",
    "sg:phone":"+31 416 341 665",
    "sg:postcode":"5145 NE",
    "sg:province":"Noord-Brabant",
    "sg:website":"http://www.alucet.nl",
    "wof:name":"Alu-Cet Bv",
    "wof:placetype":"venue"
},
  "geometry": {"coordinates":[5.048011,51.695698],"type":"Point"}
}