{
  "type": "Feature",
  "properties": {
    "addr:full":"Hamelandroute 72 Aalten Gelderland 7121 GZ",
    "addr:housenumber":"72",
    "addr:postcode":"7121 gz",
    "addr:street":"Hamelandroute;Gelderland",
    "iso:country":"NL",
    "sg:address":"Hamelandroute 72",
    "sg:city":"Aalten",
    "sg:orig_category":"Verenigingen En Stichtingen",
    "sg:phone":"+31 543 475 708",
    "sg:postcode":"7121 GZ",
    "sg:province":"Gelderland",
    "wof:name":"Slaa, Sticht 'T",
    "wof:placetype":"venue"
},
  "geometry": {"coordinates":[6.593911,51.915039],"type":"Point"}
}