{
  "type": "Feature",
  "properties": {
    "addr:full":"Mercuriuswg 9 S Gravenhage Zuid-Holland 2516 AW",
    "addr:housenumber":"9 s",
    "addr:postcode":"2516 aw",
    "addr:street":"Mercuriuswg",
    "iso:country":"NL",
    "sg:address":"Mercuriuswg 9",
    "sg:city":"S Gravenhage",
    "sg:orig_category":"Verzekeringen - Verzekeringskantoren",
    "sg:phone":"+31 70 304 1473",
    "sg:postcode":"2516 AW",
    "sg:province":"Zuid-Holland",
    "wof:name":"Wilton Assuranti\u00ebn Bv",
    "wof:placetype":"venue"
},
  "geometry": {"coordinates":[4.33931,52.06786],"type":"Point"}
}