{
  "type": "Feature",
  "properties": {
    "iso:country":"NL",
    "sg:address":"Lamoen 6",
    "sg:city":"Barendrecht",
    "sg:orig_category":"Waterbouwkundige Werken",
    "sg:phone":"+31 180 558 374",
    "sg:postcode":"2993 AM",
    "sg:province":"South Holland",
    "wof:name":"Meijden, Van Der",
    "wof:placetype":"venue"
},
  "geometry": {"coordinates":[4.4818601608,51.8555984497],"type":"Point"}
}