{
  "type": "Feature",
  "properties": {
    "iso:country":"NL",
    "sg:address":"Jupiter 71",
    "sg:city":"Poeldyk",
    "sg:orig_category":"Administratie- En Boekhoudkantoren",
    "sg:phone":"+31 174 244 937",
    "sg:postcode":"2685 LV",
    "sg:province":"Zuid-Holland",
    "sg:website":"http://www.imedia.nl/biesot",
    "wof:name":"Biesot",
    "wof:placetype":"venue"
},
  "geometry": {"coordinates":[4.208591,52.019436],"type":"Point"}
}