{
  "type": "Feature",
  "properties": {
    "addr:full":"Wilthuisstr 2 Deurningen Overijssel 7561 AH",
    "addr:housenumber":"2",
    "addr:postcode":"7561 ah",
    "addr:street":"Wilthuisstr",
    "iso:country":"NL",
    "sg:address":"Wilthuisstr 2",
    "sg:city":"Deurningen",
    "sg:orig_category":"Woninginrichting",
    "sg:phone":"+31 74 277 2269",
    "sg:postcode":"7561 AH",
    "sg:province":"Overijssel",
    "wof:name":"Eshuis",
    "wof:placetype":"venue"
},
  "geometry": {"coordinates":[6.8354578018,52.3002281189],"type":"Point"}
}