{
  "type": "Feature",
  "properties": {
    "iso:country":"NL",
    "sg:address":"Ryn En Schiekd 25",
    "sg:city":"Leiden",
    "sg:orig_category":"Psychologen",
    "sg:phone":"+31 71 513 2128",
    "sg:postcode":"2311 AK",
    "sg:province":"South Holland",
    "wof:name":"Lamers & C M Grondel, G A",
    "wof:placetype":"venue"
},
  "geometry": {"coordinates":[4.49463,52.154572],"type":"Point"}
}