{
  "type": "Feature",
  "properties": {
    "iso:country":"NL",
    "sg:address":"Kwartelweg 4",
    "sg:city":"Wapenveld",
    "sg:orig_category":"Juweliers",
    "sg:phone":"+31 38 447 8997",
    "sg:postcode":"8191 AS",
    "sg:province":"Gelderland",
    "wof:name":"Firma Kamphuis",
    "wof:placetype":"venue"
},
  "geometry": {"coordinates":[6.070037,52.429287],"type":"Point"}
}