{
  "type": "Feature",
  "properties": {
    "addr:full":"Kwartelweg 4 Wapenveld Gelderland 8191 AS",
    "addr:housenumber":"4",
    "addr:postcode":"8191 as",
    "addr:street":"Kwartelweg;Gelderland",
    "iso:country":"NL",
    "sg:address":"Kwartelweg 4",
    "sg:city":"Wapenveld",
    "sg:orig_category":"Juweliers",
    "sg:phone":"+31 38 447 8997",
    "sg:postcode":"8191 AS",
    "sg:province":"Gelderland",
    "wof:name":"Firma Kamphuis",
    "wof:placetype":"venue"
},
  "geometry": {"coordinates":[6.070037,52.429287],"type":"Point"}
}