{
  "type": "Feature",
  "properties": {
    "iso:country":"NL",
    "sg:address":"Haverkampsweg 4",
    "sg:city":"Epe",
    "sg:orig_category":"Autokeuringen",
    "sg:phone":"+31 578 612 756",
    "sg:postcode":"8161 VN",
    "sg:province":"Gelderland",
    "wof:name":"Automobielbedrijf Auto Jaap",
    "wof:placetype":"venue"
},
  "geometry": {"coordinates":[5.983142,52.343185],"type":"Point"}
}