{
  "type": "Feature",
  "properties": {
    "addr:full":"Ysselmondestr 9 Sittard Limburg 6137 KD",
    "addr:housenumber":"9",
    "addr:postcode":"6137 kd",
    "addr:street":"Ysselmondestr",
    "iso:country":"NL",
    "sg:address":"Ysselmondestr 9",
    "sg:city":"Sittard",
    "sg:orig_category":"Luchtbehandelings- Apparaten",
    "sg:phone":"+31 6 41478870",
    "sg:postcode":"6137 KD",
    "sg:province":"Limburg",
    "wof:name":"Salair",
    "wof:placetype":"venue"
},
  "geometry": {"coordinates":[5.90019,51.001411],"type":"Point"}
}