{
  "type": "Feature",
  "properties": {
    "addr:full":"Mildert 10-11 Nederweert Limburg 6031 SM",
    "addr:housenumber":"10-11",
    "addr:postcode":"6031 sm",
    "addr:street":"Mildert",
    "iso:country":"NL",
    "sg:address":"Mildert 10-11",
    "sg:city":"Nederweert",
    "sg:orig_category":"Boeken En Tijdschriften",
    "sg:phone":"+31 495 651 543",
    "sg:postcode":"6031 SM",
    "sg:province":"Limburg",
    "wof:name":"Avesta Ned Bv",
    "wof:placetype":"venue"
},
  "geometry": {"coordinates":[5.746135,51.28743],"type":"Point"}
}