{
  "type": "Feature",
  "properties": {
    "addr:full":"Ganserd 7 Eindhoven Noord-Brabant 5641 LX",
    "addr:housenumber":"7",
    "addr:postcode":"5641 lx",
    "addr:street":"Ganserd",
    "iso:country":"NL",
    "sg:address":"Ganserd 7",
    "sg:city":"Eindhoven",
    "sg:orig_category":"Boekhouders",
    "sg:phone":"+31 40 281 5853",
    "sg:postcode":"5641 LX",
    "sg:province":"Noord-Brabant",
    "wof:name":"Administratie Praktijk Eindhoven",
    "wof:placetype":"venue"
},
  "geometry": {"coordinates":[5.529667,51.443306],"type":"Point"}
}