{
  "type": "Feature",
  "properties": {
    "addr:full":"Marconistraat 9 Hillegom North Holland 2181 AK",
    "addr:housenumber":"9",
    "addr:postcode":"2181 ak",
    "addr:street":"Marconistraat",
    "iso:country":"NL",
    "sg:address":"Marconistraat 9",
    "sg:city":"Hillegom",
    "sg:orig_category":"Autokeuringen",
    "sg:phone":"+31 252 530 051",
    "sg:postcode":"2181 AK",
    "sg:province":"North Holland",
    "wof:name":"Van Saase",
    "wof:placetype":"venue"
},
  "geometry": {"coordinates":[4.585241,52.288944],"type":"Point"}
}