{
  "type": "Feature",
  "properties": {
    "addr:full":"Dollard 26 Zwijndrecht Zuid-Holland 3332 EE",
    "addr:housenumber":"26",
    "addr:postcode":"3332 ee",
    "addr:street":"Dollard",
    "iso:country":"NL",
    "sg:address":"Dollard 26",
    "sg:city":"Zwijndrecht",
    "sg:orig_category":"Fotolaboratoria",
    "sg:phone":"+31 78 619 2377",
    "sg:postcode":"3332 EE",
    "sg:province":"Zuid-Holland",
    "wof:name":"Hema",
    "wof:placetype":"venue"
},
  "geometry": {"coordinates":[4.652943,51.822968],"type":"Point"}
}