{
  "type": "Feature",
  "properties": {
    "addr:full":"Waterigewg 12 Zeist Utrecht 3703 CN",
    "addr:housenumber":"12",
    "addr:postcode":"3703 cn",
    "addr:street":"Waterigewg",
    "iso:country":"NL",
    "sg:address":"Waterigewg 12",
    "sg:city":"Zeist",
    "sg:orig_category":"Adviesbureaus Bedrijfsorganisatie",
    "sg:phone":"+31 30 692 3414",
    "sg:postcode":"3703 CN",
    "sg:province":"Utrecht",
    "sg:website":"http://www.business-wise.nl",
    "wof:name":"Business Wise",
    "wof:placetype":"venue"
},
  "geometry": {"coordinates":[5.234796,52.081825],"type":"Point"}
}