{
  "type": "Feature",
  "properties": {
    "iso:country":"NL",
    "sg:address":"Besterdring 49",
    "sg:city":"Tilburg",
    "sg:classifiers":[
        {
            "category":"Fast Food",
            "type":"Food & Drink"
        }
    ],
    "sg:phone":"+31 13 543 0113",
    "sg:postcode":"5014 HH",
    "sg:province":"Noord-Brabant",
    "sg:tags":[
        "afhaal",
        "restaurant"
    ],
    "wof:name":"Pizza Uno",
    "wof:placetype":"venue"
},
  "geometry": {"coordinates":[5.08884,51.566341],"type":"Point"}
}