{
  "type": "Feature",
  "properties": {
    "iso:country":"NL",
    "sg:address":"Past Spieringsln 4",
    "sg:city":"Heeze",
    "sg:orig_category":"Verzekeringen - Verzekeringskantoren",
    "sg:phone":"+31 40 226 2929",
    "sg:postcode":"5591 CT",
    "sg:province":"Noord-Brabant",
    "wof:name":"Leeuw Bv, De",
    "wof:placetype":"venue"
},
  "geometry": {"coordinates":[5.576401,51.386711],"type":"Point"}
}