{
  "type": "Feature",
  "properties": {
    "addr:full":"Mynsherenwg 32A Kudelstaart Noord-Holland 1433 AS",
    "addr:housenumber":"32a",
    "addr:postcode":"1433 as",
    "addr:street":"Mynsherenwg",
    "iso:country":"NL",
    "sg:address":"Mynsherenwg 32A",
    "sg:city":"Kudelstaart",
    "sg:orig_category":"Grondwerken",
    "sg:phone":"+31 297 341 989",
    "sg:postcode":"1433 AS",
    "sg:province":"Noord-Holland",
    "wof:name":"Bon, Fa A",
    "wof:placetype":"venue"
},
  "geometry": {"coordinates":[4.760979,52.241199],"type":"Point"}
}