{
  "type": "Feature",
  "properties": {
    "addr:full":"Hobrederweg 42 Middenbeemster Noord-Holland 1462 LK",
    "addr:housenumber":"42",
    "addr:postcode":"1462 lk",
    "addr:street":"Hobrederweg",
    "iso:country":"NL",
    "sg:address":"Hobrederweg 42",
    "sg:city":"Middenbeemster",
    "sg:orig_category":"Meubelzaken, Woning- And Keukeninrichting",
    "sg:phone":"+31 299 681 517",
    "sg:postcode":"1462 LK",
    "sg:province":"Noord-Holland",
    "wof:name":"Groen'S Grenen Meubelen",
    "wof:placetype":"venue"
},
  "geometry": {"coordinates":[4.960131,52.555614],"type":"Point"}
}