{
  "type": "Feature",
  "properties": {
    "addr:full":"Kubus 11 Sliedrecht South Holland 3364 DG",
    "addr:housenumber":"11",
    "addr:postcode":"3364 dg",
    "addr:street":"Kubus",
    "iso:country":"NL",
    "sg:address":"Kubus 11",
    "sg:city":"Sliedrecht",
    "sg:orig_category":"Landmeetkundige Bureaus",
    "sg:phone":"+31 184 671 830",
    "sg:postcode":"3364 DG",
    "sg:province":"South Holland",
    "sg:website":"http://www.facto.info",
    "wof:name":"Facto Bv",
    "wof:placetype":"venue"
},
  "geometry": {"coordinates":[4.795001,51.826965],"type":"Point"}
}