{
  "type": "Feature",
  "properties": {
    "iso:country":"NL",
    "sg:address":"Cesar Francklaan 37",
    "sg:city":"Waalwijk",
    "sg:orig_category":"Paramedische Behandelingen",
    "sg:phone":"+31 416 341 220",
    "sg:postcode":"5144 WD",
    "sg:province":"North Brabant",
    "wof:name":"Verloskundigenpraktijk Waalwijk En Waspik",
    "wof:placetype":"venue"
},
  "geometry": {"coordinates":[5.064124,51.674149],"type":"Point"}
}