{
  "type": "Feature",
  "properties": {
    "addr:full":"Lobbendijk 4 Houten Utrecht 3991 EC",
    "addr:housenumber":"4",
    "addr:postcode":"3991 ec",
    "addr:street":"Lobbendijk",
    "iso:country":"NL",
    "sg:address":"Lobbendijk 4",
    "sg:city":"Houten",
    "sg:orig_category":"Notarissen",
    "sg:phone":"+31 30 637 1213",
    "sg:postcode":"3991 EC",
    "sg:province":"Utrecht",
    "wof:name":"Mr. J.G. De Boer Notaris",
    "wof:placetype":"venue"
},
  "geometry": {"coordinates":[5.161293,52.027924],"type":"Point"}
}