{
  "type": "Feature",
  "properties": {
    "addr:full":"Ambachtstraat 1 Almelo Overijssel 7609 RA",
    "addr:housenumber":"1",
    "addr:postcode":"7609 ra",
    "addr:street":"Ambachtstraat",
    "iso:country":"NL",
    "sg:address":"Ambachtstraat 1",
    "sg:city":"Almelo",
    "sg:orig_category":"Verhuur Huishoudartikelen",
    "sg:phone":"+31 546 824 257",
    "sg:postcode":"7609 RA",
    "sg:province":"Overijssel",
    "wof:name":"Westerhuis Verhuur",
    "wof:placetype":"venue"
},
  "geometry": {"coordinates":[6.65715,52.335278],"type":"Point"}
}