{
  "type": "Feature",
  "properties": {
    "addr:full":"M Klompewg 2 Tilburg Noord-Brabant 5032 MP",
    "addr:housenumber":"2",
    "addr:postcode":"5032 mp",
    "iso:country":"NL",
    "sg:address":"M Klompewg 2",
    "sg:city":"Tilburg",
    "sg:orig_category":"Luchtvrachtexpediteurs",
    "sg:phone":"+31 13 595 2560",
    "sg:postcode":"5032 MP",
    "sg:province":"Noord-Brabant",
    "wof:name":"Fritz Companies Ned Bv",
    "wof:placetype":"venue"
},
  "geometry": {"coordinates":[5.036206,51.535851],"type":"Point"}
}