{
  "type": "Feature",
  "properties": {
    "iso:country":"NL",
    "sg:address":"Wilhelminastraat 28",
    "sg:city":"Emmen",
    "sg:orig_category":"Visspeciaalzaken",
    "sg:phone":"+31 591 612 881",
    "sg:postcode":"7811 JC",
    "sg:province":"Drenthe",
    "wof:name":"Vishandel Hollands Glorie",
    "wof:placetype":"venue"
},
  "geometry": {"coordinates":[6.896836,52.780422],"type":"Point"}
}