{
  "type": "Feature",
  "properties": {
    "addr:full":"Wilhelminastraat 28 Emmen Drenthe 7811 JC",
    "addr:housenumber":"28",
    "addr:postcode":"7811 jc",
    "addr:street":"Wilhelminastraat",
    "iso:country":"NL",
    "sg:address":"Wilhelminastraat 28",
    "sg:city":"Emmen",
    "sg:orig_category":"Visspeciaalzaken",
    "sg:phone":"+31 591 612 881",
    "sg:postcode":"7811 JC",
    "sg:province":"Drenthe",
    "wof:name":"Vishandel Hollands Glorie",
    "wof:placetype":"venue"
},
  "geometry": {"coordinates":[6.896836,52.780422],"type":"Point"}
}