{
  "type": "Feature",
  "properties": {
    "addr:full":"Agniesestraat 41 Rotterdam Zuid-Holland 3032 TC",
    "addr:housenumber":"41",
    "addr:postcode":"3032 tc",
    "addr:street":"Agniesestraat",
    "iso:country":"NL",
    "sg:address":"Agniesestraat 41",
    "sg:city":"Rotterdam",
    "sg:orig_category":"Fotostudio'S And Fotografen",
    "sg:phone":"+31 10 467 2600",
    "sg:postcode":"3032 TC",
    "sg:province":"Zuid-Holland",
    "wof:name":"Arnoud Verhey Fotografie",
    "wof:placetype":"venue"
},
  "geometry": {"coordinates":[4.475631,51.930866],"type":"Point"}
}