{
  "type": "Feature",
  "properties": {
    "addr:full":"Pijlakker 4 Kaatsheuvel Noord-Brabant 5171 SZ",
    "addr:housenumber":"4",
    "addr:postcode":"5171 sz",
    "addr:street":"Pijlakker",
    "iso:country":"NL",
    "sg:address":"Pijlakker 4",
    "sg:city":"Kaatsheuvel",
    "sg:orig_category":"Sportverenigingen En Ontspannings- Verenigingen",
    "sg:phone":"+31 416 540 377",
    "sg:postcode":"5171 SZ",
    "sg:province":"Noord-Brabant",
    "wof:name":"Cornu Copiae Muziekkorps",
    "wof:placetype":"venue"
},
  "geometry": {"coordinates":[5.033833,51.652382],"type":"Point"}
}