{
  "type": "Feature",
  "properties": {
    "addr:full":"Oeverstr 5 Wyk By Duurstede Utrecht 3961 AM",
    "addr:housenumber":"5",
    "addr:postcode":"duurstede;3961",
    "addr:street":"Oeverstr",
    "iso:country":"NL",
    "sg:address":"Oeverstr 5",
    "sg:city":"Wyk By Duurstede",
    "sg:orig_category":"Architecten En Architectenbureaus",
    "sg:phone":"+31 343 577 358",
    "sg:postcode":"3961 AM",
    "sg:province":"Utrecht",
    "wof:name":"Ton Van Der Woude",
    "wof:placetype":"venue"
},
  "geometry": {"coordinates":[5.347934,51.971813],"type":"Point"}
}