{
  "type": "Feature",
  "properties": {
    "addr:full":"Wilhelminapark 18 Venlo Limburg 5911 ED",
    "addr:housenumber":"18",
    "addr:postcode":"5911 ed",
    "addr:street":"Wilhelminapark",
    "iso:country":"NL",
    "sg:address":"Wilhelminapark 18",
    "sg:city":"Venlo",
    "sg:orig_category":"Vertaal- And Tolkenbureaus",
    "sg:phone":"+31 77 352 2612",
    "sg:postcode":"5911 ED",
    "sg:province":"Limburg",
    "wof:name":"Global Translation Services",
    "wof:placetype":"venue"
},
  "geometry": {"coordinates":[6.172487,51.375153],"type":"Point"}
}