{
  "type": "Feature",
  "properties": {
    "addr:full":"Kipstr 53H Rotterdam South Holland 3011 ZX",
    "addr:postcode":"3011 zx",
    "iso:country":"NL",
    "sg:address":"Kipstr 53H",
    "sg:city":"Rotterdam",
    "sg:orig_category":"Verhuizingen",
    "sg:phone":"+31 10 413 1454",
    "sg:postcode":"3011 ZX",
    "sg:province":"South Holland",
    "wof:name":"Scholte, G",
    "wof:placetype":"venue"
},
  "geometry": {"coordinates":[4.492597,51.922066],"type":"Point"}
}