{
  "type": "Feature",
  "properties": {
    "addr:full":"Noordweegseweg 21 'S Heer Arendskerke Zeeland 4458 AT",
    "addr:housenumber":"21",
    "addr:postcode":"4458",
    "addr:street":"Noordweegseweg;' S Heer Arendskerke",
    "iso:country":"NL",
    "sg:address":"Noordweegseweg 21",
    "sg:city":"'S Heer Arendskerke",
    "sg:orig_category":"Goederenvervoer Over De Weg",
    "sg:phone":"+31 113 562 134",
    "sg:postcode":"4458 AT",
    "sg:province":"Zeeland",
    "wof:name":"Transportbedrijf Joka Bv",
    "wof:placetype":"venue"
},
  "geometry": {"coordinates":[3.818966,51.498428],"type":"Point"}
}