{
  "type": "Feature",
  "properties": {
    "addr:full":"Admiralengr 53 Amsterdam Noord-Holland 1057 EN",
    "addr:housenumber":"53",
    "addr:postcode":"1057 en",
    "addr:street":"Admiralengr",
    "iso:country":"NL",
    "sg:address":"Admiralengr 53",
    "sg:city":"Amsterdam",
    "sg:orig_category":"Horloges En Klokken - Reparatie En Onderhoud",
    "sg:phone":"+31 20 683 4076",
    "sg:postcode":"1057 EN",
    "sg:province":"Noord-Holland",
    "wof:name":"Hollander, N H",
    "wof:placetype":"venue"
},
  "geometry": {"coordinates":[4.857136,52.366604],"type":"Point"}
}