{
  "type": "Feature",
  "properties": {
    "addr:full":"Oudelandseweg 54 Ouddorp Zh Zuid-Holland 3253 LP",
    "addr:housenumber":"54",
    "addr:postcode":"3253 lp",
    "addr:street":"Oudelandseweg",
    "iso:country":"NL",
    "sg:address":"Oudelandseweg 54",
    "sg:city":"Ouddorp Zh",
    "sg:orig_category":"Technische Studies And Onderzoek",
    "sg:phone":"+31 187 681 959",
    "sg:postcode":"3253 LP",
    "sg:province":"Zuid-Holland",
    "wof:name":"Jantec Bv",
    "wof:placetype":"venue"
},
  "geometry": {"coordinates":[3.911378,51.802635],"type":"Point"}
}