{
  "type": "Feature",
  "properties": {
    "addr:full":"Erasmusw 24 Breda Noord-Brabant 4834 AA",
    "addr:housenumber":"24",
    "addr:postcode":"4834 aa",
    "addr:street":"Erasmusw",
    "iso:country":"NL",
    "sg:address":"Erasmusw 24",
    "sg:city":"Breda",
    "sg:orig_category":"Verenigingsgebouwen",
    "sg:phone":"+31 76 565 7873",
    "sg:postcode":"4834 AA",
    "sg:province":"Noord-Brabant",
    "wof:name":"Erasmus Gemeenschapshuis",
    "wof:placetype":"venue"
},
  "geometry": {"coordinates":[4.79333,51.575691],"type":"Point"}
}