{
  "type": "Feature",
  "properties": {
    "iso:country":"NL",
    "sg:address":"J Luykenstr 12",
    "sg:city":"Amsterdam",
    "sg:orig_category":"Luchtvaart- Maatschappijen",
    "sg:phone":"+31 20 675 1411",
    "sg:postcode":"1071 CM",
    "sg:province":"North Holland",
    "wof:name":"Jap",
    "wof:placetype":"venue"
},
  "geometry": {"coordinates":[4.88412,52.360634],"type":"Point"}
}