{
  "type": "Feature",
  "properties": {
    "addr:full":"Haverterstr 23 Koningsbosch Limburg 6104 AM",
    "addr:housenumber":"23",
    "addr:postcode":"6104",
    "addr:street":"Haverterstr",
    "iso:country":"NL",
    "sg:address":"Haverterstr 23",
    "sg:city":"Koningsbosch",
    "sg:orig_category":"Journalisten Freelance",
    "sg:phone":"+31 475 301 232",
    "sg:postcode":"6104 AM",
    "sg:province":"Limburg",
    "wof:name":"Pol, J P M Van",
    "wof:placetype":"venue"
},
  "geometry": {"coordinates":[5.953421,51.052704],"type":"Point"}
}