{
  "type": "Feature",
  "properties": {
    "iso:country":"NL",
    "sg:address":"Munsterstr 9",
    "sg:city":"Deventer",
    "sg:orig_category":"Onroerende Goederen",
    "sg:phone":"+31 570 662 966",
    "sg:postcode":"7418 EV",
    "sg:province":"NL.08",
    "wof:name":"Uni-Invest Beheer Bv",
    "wof:placetype":"venue"
},
  "geometry": {"coordinates":[6.185918,52.238407],"type":"Point"}
}