{
  "type": "Feature",
  "properties": {
    "iso:country":"NL",
    "sg:address":"Prinses Marijkestraat 5",
    "sg:city":"'S Gravenhage",
    "sg:orig_category":"Autokeuringen",
    "sg:phone":"+31 70 381 1800",
    "sg:postcode":"2595 TL",
    "sg:province":"South Holland",
    "wof:name":"Achilles Diensten Bv",
    "wof:placetype":"venue"
},
  "geometry": {"coordinates":[4.335219,52.079952],"type":"Point"}
}