{
  "type": "Feature",
  "properties": {
    "addr:full":"Hoofdland 2 Zwijndrecht Zuid-Holland 3332 RG",
    "addr:housenumber":"2",
    "addr:postcode":"3332 rg",
    "addr:street":"Hoofdland",
    "iso:country":"NL",
    "sg:address":"Hoofdland 2",
    "sg:city":"Zwijndrecht",
    "sg:classifiers":[
        {
            "category":"Education",
            "subcategory":"Preschool",
            "type":"Public Place"
        }
    ],
    "sg:phone":"+31 78 612 9393",
    "sg:postcode":"3332 RG",
    "sg:province":"Zuid-Holland",
    "sg:tags":[
        "kleuteronderwijs",
        "basis-"
    ],
    "wof:name":"Gereformeerde Basisschool De Wegwijzer",
    "wof:placetype":"venue"
},
  "geometry": {"coordinates":[4.65647,51.822247],"type":"Point"}
}