{
  "type": "Feature",
  "properties": {
    "addr:full":"Hoofdstraat West 69 Noordwolde Fr Friesland 8391 AM",
    "addr:housenumber":"69",
    "addr:postcode":"8391",
    "addr:street":"Hoofdstraat West",
    "iso:country":"NL",
    "sg:address":"Hoofdstraat West 69",
    "sg:city":"Noordwolde Fr",
    "sg:orig_category":"Autokeuringen",
    "sg:phone":"+31 561 431 644",
    "sg:postcode":"8391 AM",
    "sg:province":"Friesland",
    "wof:name":"Expertisebureau G De Vries",
    "wof:placetype":"venue"
},
  "geometry": {"coordinates":[6.134593,52.886475],"type":"Point"}
}