{
  "type": "Feature",
  "properties": {
    "iso:country":"NL",
    "sg:address":"Kleasterdk 16",
    "sg:city":"Winsum Fr",
    "sg:orig_category":"Verf En Lak - Fabrieken En Groothandel",
    "sg:phone":"+31 517 341 835",
    "sg:postcode":"8831 XB",
    "sg:province":"Friesland",
    "wof:name":"Hempel Ned Bv",
    "wof:placetype":"venue"
},
  "geometry": {"coordinates":[5.629913,53.154137],"type":"Point"}
}