{
  "type": "Feature",
  "properties": {
    "iso:country":"NL",
    "sg:address":"Markt 40",
    "sg:city":"S Hertogenbosch",
    "sg:orig_category":"Voetbalverenigingen",
    "sg:phone":"+31 73 614 7407",
    "sg:postcode":"5211 JX",
    "sg:province":"Noord-Brabant",
    "wof:name":"Dvo Princen",
    "wof:placetype":"venue"
},
  "geometry": {"coordinates":[5.302555,51.689491],"type":"Point"}
}