{
  "type": "Feature",
  "properties": {
    "iso:country":"NL",
    "sg:address":"Wildenborg 38",
    "sg:city":"Barneveld",
    "sg:orig_category":"Adviesbureaus Bedrijfsorganisatie",
    "sg:phone":"+31 6 53697249",
    "sg:postcode":"3772 ZB",
    "sg:province":"Gelderland",
    "wof:name":"Dulken Interim Management, Van",
    "wof:placetype":"venue"
},
  "geometry": {"coordinates":[5.574092,52.130329],"type":"Point"}
}