{
  "type": "Feature",
  "properties": {
    "addr:full":"Grensweg 7 Emst Gelderland 8166 HC",
    "addr:housenumber":"7",
    "addr:postcode":"8166 hc",
    "addr:street":"Grensweg;Gelderland",
    "iso:country":"NL",
    "sg:address":"Grensweg 7",
    "sg:city":"Emst",
    "sg:orig_category":"Kappers",
    "sg:phone":"+31 578 615 552",
    "sg:postcode":"8166 HC",
    "sg:province":"Gelderland",
    "wof:name":"Elite",
    "wof:placetype":"venue"
},
  "geometry": {"coordinates":[5.9753918648,52.3158187866],"type":"Point"}
}