{
  "type": "Feature",
  "properties": {
    "iso:country":"NL",
    "sg:address":"Wulverhorst 53",
    "sg:city":"Montfoort",
    "sg:orig_category":"Bedrijfsopleidingen",
    "sg:phone":"+31 348 473 171",
    "sg:postcode":"3417 TH",
    "sg:province":"Utrecht",
    "wof:name":"Vos",
    "wof:placetype":"venue"
},
  "geometry": {"coordinates":[4.947639,52.040298],"type":"Point"}
}