{
  "type": "Feature",
  "properties": {
    "addr:full":"Wulverhorst 53 Montfoort Utrecht 3417 TH",
    "addr:housenumber":"53",
    "addr:postcode":"3417 th",
    "addr:street":"Wulverhorst",
    "iso:country":"NL",
    "sg:address":"Wulverhorst 53",
    "sg:city":"Montfoort",
    "sg:orig_category":"Bedrijfsopleidingen",
    "sg:phone":"+31 348 473 171",
    "sg:postcode":"3417 TH",
    "sg:province":"Utrecht",
    "wof:name":"Vos",
    "wof:placetype":"venue"
},
  "geometry": {"coordinates":[4.947639,52.040298],"type":"Point"}
}