{
  "type": "Feature",
  "properties": {
    "addr:full":"Drostln 67 Asperen Gelderland 4147 GG",
    "addr:housenumber":"67",
    "addr:postcode":"4147 gg",
    "addr:street":"Drostln;Gelderland",
    "iso:country":"NL",
    "sg:address":"Drostln 67",
    "sg:city":"Asperen",
    "sg:orig_category":"Montagebedrijven",
    "sg:phone":"+31 6 53326354",
    "sg:postcode":"4147 GG",
    "sg:province":"Gelderland",
    "wof:name":"Mkkm",
    "wof:placetype":"venue"
},
  "geometry": {"coordinates":[5.103023,51.880913],"type":"Point"}
}