{
  "type": "Feature",
  "properties": {
    "addr:full":"Zuidkd 21 Veghel North Brabant 5462 CD",
    "addr:housenumber":"21",
    "addr:postcode":"5462 cd",
    "addr:street":"Zuidkd",
    "iso:country":"NL",
    "sg:address":"Zuidkd 21",
    "sg:city":"Veghel",
    "sg:orig_category":"Keukens",
    "sg:phone":"+31 413 351 006",
    "sg:postcode":"5462 CD",
    "sg:province":"North Brabant",
    "sg:website":"http://www.hiddokk.nl",
    "wof:name":"Gas Onder Glas",
    "wof:placetype":"venue"
},
  "geometry": {"coordinates":[5.528348,51.61729],"type":"Point"}
}