{
  "type": "Feature",
  "properties": {
    "iso:country":"NL",
    "sg:address":"De Boskamp 5",
    "sg:city":"Tolbert",
    "sg:orig_category":"Keramische Producten Fab",
    "sg:phone":"+31 594 517 915",
    "sg:postcode":"9356 CE",
    "sg:province":"Texas",
    "wof:name":"Margariette Fijnkeramiek",
    "wof:placetype":"venue"
},
  "geometry": {"coordinates":[-99.414536,34.226662],"type":"Point"}
}