{
  "type": "Feature",
  "properties": {
    "addr:full":"Eisenhowerln 118 Beek Lb Limburg 6191 VW",
    "addr:housenumber":"118",
    "addr:postcode":"lb;6191 vw",
    "iso:country":"NL",
    "sg:address":"Eisenhowerln 118",
    "sg:city":"Beek Lb",
    "sg:orig_category":"Webdesign Bureaus",
    "sg:phone":"+31 46 449 0750",
    "sg:postcode":"6191 VW",
    "sg:province":"Limburg",
    "wof:name":"Inter Media",
    "wof:placetype":"venue"
},
  "geometry": {"coordinates":[-93.1299362183,36.7056617737],"type":"Point"}
}