{
  "type": "Feature",
  "properties": {
    "iso:country":"NL",
    "sg:address":"Zwenkgrasstr 5",
    "sg:city":"Almere",
    "sg:orig_category":"Automaterialen En Gereedschappen",
    "sg:phone":"+31 36 548 2555",
    "sg:postcode":"1313 LC",
    "sg:province":"Flevoland",
    "wof:name":"Lasaulec Almere",
    "wof:placetype":"venue"
},
  "geometry": {"coordinates":[5.203991,52.386189],"type":"Point"}
}