{
  "type": "Feature",
  "properties": {
    "iso:country":"NL",
    "sg:address":"Mendelssohnstraat 12",
    "sg:city":"Alkmaar",
    "sg:orig_category":"Vertaal- And Tolkenbureaus",
    "sg:phone":"+31 72 512 6524",
    "sg:postcode":"1817 HG",
    "sg:province":"Noord-Holland",
    "wof:name":"Elekes Vertaalbureau",
    "wof:placetype":"venue"
},
  "geometry": {"coordinates":[4.733322,52.6427],"type":"Point"}
}