{
  "type": "Feature",
  "properties": {
    "addr:full":"Kinkerstraat 279 Amsterdam North Holland 1053 ES",
    "addr:housenumber":"279",
    "addr:postcode":"1053 es",
    "addr:street":"Kinkerstraat",
    "iso:country":"NL",
    "sg:address":"Kinkerstraat 279",
    "sg:city":"Amsterdam",
    "sg:orig_category":"Verlichting And Huishoudartikelen",
    "sg:phone":"+31 20 689 7735",
    "sg:postcode":"1053 ES",
    "sg:province":"North Holland",
    "wof:name":"Knaakland",
    "wof:placetype":"venue"
},
  "geometry": {"coordinates":[4.863977,52.364971],"type":"Point"}
}