{
  "type": "Feature",
  "properties": {
    "iso:country":"NL",
    "sg:address":"Lucas Gasselstraat 12",
    "sg:city":"Helmond",
    "sg:orig_category":"Kappers",
    "sg:phone":"+31 492 522 838",
    "sg:postcode":"5701 BP",
    "sg:province":"North Brabant",
    "wof:name":"Ronald Vullings Coiffures",
    "wof:placetype":"venue"
},
  "geometry": {"coordinates":[5.670651,51.484768],"type":"Point"}
}