{
  "type": "Feature",
  "properties": {
    "addr:full":"De Jagerwg 278 Dordrecht South Holland 3328 AA",
    "addr:housenumber":"278",
    "addr:postcode":"3328 aa",
    "iso:country":"NL",
    "sg:address":"De Jagerwg 278",
    "sg:city":"Dordrecht",
    "sg:orig_category":"Kappers",
    "sg:phone":"+31 78 618 2165",
    "sg:postcode":"3328 AA",
    "sg:province":"South Holland",
    "wof:name":"Hair Maxx",
    "wof:placetype":"venue"
},
  "geometry": {"coordinates":[4.681043148,51.7747077942],"type":"Point"}
}