{
  "type": "Feature",
  "properties": {
    "addr:full":"Spalstr 31 Hengelo Gld Gelderland 7255 AB",
    "addr:housenumber":"31",
    "addr:postcode":"7255 ab",
    "addr:street":"Spalstr",
    "iso:country":"NL",
    "sg:address":"Spalstr 31",
    "sg:city":"Hengelo Gld",
    "sg:orig_category":"Hypotheken",
    "sg:phone":"+31 575 468 846",
    "sg:postcode":"7255 AB",
    "sg:province":"Gelderland",
    "wof:name":"Gerrits Lammers",
    "wof:placetype":"venue"
},
  "geometry": {"coordinates":[6.310242,52.04961],"type":"Point"}
}