{
  "type": "Feature",
  "properties": {
    "addr:full":"Raadhuislaan 6 Rockanje Zuid-Holland 3235 AP",
    "addr:housenumber":"6",
    "addr:postcode":"3235 ap",
    "addr:street":"Raadhuislaan",
    "iso:country":"NL",
    "sg:address":"Raadhuislaan 6",
    "sg:city":"Rockanje",
    "sg:orig_category":"Overheidsdiensten",
    "sg:phone":"+31 181 408 000",
    "sg:postcode":"3235 AP",
    "sg:province":"Zuid-Holland",
    "wof:name":"Gemeente Westvoorne",
    "wof:placetype":"venue"
},
  "geometry": {"coordinates":[4.064207077,51.8743209839],"type":"Point"}
}