{
  "type": "Feature",
  "properties": {
    "addr:full":"Volkersweg 27 Zwaagdijk Noord-Holland 1684 NV",
    "addr:housenumber":"27",
    "addr:postcode":"1684 nv",
    "addr:street":"Volkersweg",
    "iso:country":"NL",
    "sg:address":"Volkersweg 27",
    "sg:city":"Zwaagdijk",
    "sg:orig_category":"Boekhouders",
    "sg:phone":"+31 228 582 103",
    "sg:postcode":"1684 NV",
    "sg:province":"Noord-Holland",
    "wof:name":"Administratiekantoor Linzell",
    "wof:placetype":"venue"
},
  "geometry": {"coordinates":[5.127294,52.702076],"type":"Point"}
}