{
  "type": "Feature",
  "properties": {
    "addr:full":"Conradstr 4 Schiedam Zuid-Holland 3125 BC",
    "addr:housenumber":"4",
    "addr:postcode":"3125 bc",
    "addr:street":"Conradstr",
    "iso:country":"NL",
    "sg:address":"Conradstr 4",
    "sg:city":"Schiedam",
    "sg:orig_category":"Verpakkingsmachines",
    "sg:phone":"+31 10 488 5899",
    "sg:postcode":"3125 BC",
    "sg:province":"Zuid-Holland",
    "sg:website":"http://www.tevo.nl",
    "wof:name":"Kl\u00f6ckner H\u00e4nsel Tevopharm Bv",
    "wof:placetype":"venue"
},
  "geometry": {"coordinates":[4.406189,51.929977],"type":"Point"}
}