{
  "type": "Feature",
  "properties": {
    "addr:full":"L Berchmakerstr 12 Utrecht Utrecht 3512 TD",
    "addr:housenumber":"12",
    "addr:postcode":"3512 td",
    "iso:country":"NL",
    "sg:address":"L Berchmakerstr 12",
    "sg:city":"Utrecht",
    "sg:orig_category":"Kaarsen - Fabrieken En Groothandel",
    "sg:phone":"+31 30 238 0956",
    "sg:postcode":"3512 TD",
    "sg:province":"Utrecht",
    "wof:name":"Loeff Atelier, De",
    "wof:placetype":"venue"
},
  "geometry": {"coordinates":[5.1180381775,52.0938644409],"type":"Point"}
}