{
  "type": "Feature",
  "properties": {
    "addr:full":"Lutterveldsestr 19 Kapel Avezaath Bur Gelderland 4016 DD",
    "addr:housenumber":"19",
    "addr:postcode":"4016 dd",
    "addr:street":"Lutterveldsestr",
    "iso:country":"NL",
    "sg:address":"Lutterveldsestr 19",
    "sg:city":"Kapel Avezaath Bur",
    "sg:orig_category":"Makelaars En Adviseurs Overnames",
    "sg:phone":"+31 344 661 407",
    "sg:postcode":"4016 DD",
    "sg:province":"Gelderland",
    "wof:name":"Avestaete Bv",
    "wof:placetype":"venue"
},
  "geometry": {"coordinates":[5.35171,51.882],"type":"Point"}
}