{
  "type": "Feature",
  "properties": {
    "addr:full":"Zocherstr 1 Leiden Zuid-Holland 2321 EE",
    "addr:housenumber":"1",
    "addr:postcode":"2321 ee",
    "addr:street":"Zocherstr",
    "iso:country":"NL",
    "sg:address":"Zocherstr 1",
    "sg:city":"Leiden",
    "sg:orig_category":"Artsen - Huisartsen",
    "sg:phone":"+31 71 576 6123",
    "sg:postcode":"2321 EE",
    "sg:province":"Zuid-Holland",
    "wof:name":"Horn, M P C",
    "wof:placetype":"venue"
},
  "geometry": {"coordinates":[4.477691,52.142807],"type":"Point"}
}