{
  "type": "Feature",
  "properties": {
    "iso:country":"NL",
    "sg:address":"Dorpsweg 43",
    "sg:city":"Zijderveld",
    "sg:orig_category":"Goederenvervoer Over De Weg",
    "sg:phone":"+31 345 642 244",
    "sg:postcode":"4122 GE",
    "sg:province":"Utrecht",
    "wof:name":"L.C. Van Meeteren Transport Bv",
    "wof:placetype":"venue"
},
  "geometry": {"coordinates":[5.13519,51.939186],"type":"Point"}
}