{
  "type": "Feature",
  "properties": {
    "addr:full":"Parallelwg 13A Bergambacht Zuid-Holland 2861 EC",
    "addr:housenumber":"13a",
    "addr:postcode":"2861 ec",
    "addr:street":"Parallelwg",
    "iso:country":"NL",
    "sg:address":"Parallelwg 13A",
    "sg:city":"Bergambacht",
    "sg:orig_category":"Autoreclame",
    "sg:phone":"+31 182 357 171",
    "sg:postcode":"2861 EC",
    "sg:province":"Zuid-Holland",
    "wof:name":"Id Bv",
    "wof:placetype":"venue"
},
  "geometry": {"coordinates":[4.783497,51.930958],"type":"Point"}
}