{
  "type": "Feature",
  "properties": {
    "addr:full":"Berlynstr 135 Zoetermeer Zuid-Holland 2711 PR",
    "addr:housenumber":"135",
    "addr:postcode":"2711 pr",
    "iso:country":"NL",
    "sg:address":"Berlynstr 135",
    "sg:city":"Zoetermeer",
    "sg:orig_category":"Webdesign Bureaus",
    "sg:phone":"+31 79 343 1576",
    "sg:postcode":"2711 PR",
    "sg:province":"Zuid-Holland",
    "wof:name":"Pebedesign",
    "wof:placetype":"venue"
},
  "geometry": {"coordinates":[4.4940500259,52.0629844666],"type":"Point"}
}