{
  "type": "Feature",
  "properties": {
    "addr:full":"Dahliasingel 33 Oostzaan Noord-Holland 1511 EV",
    "addr:housenumber":"33",
    "addr:street":"Dahliasingel",
    "iso:country":"NL",
    "sg:address":"Dahliasingel 33",
    "sg:city":"Oostzaan",
    "sg:orig_category":"Geluidsopnamen",
    "sg:phone":"+31 75 684 3841",
    "sg:postcode":"1511 EV",
    "sg:province":"Noord-Holland",
    "wof:name":"Romano",
    "wof:placetype":"venue"
},
  "geometry": {"coordinates":[4.879143,52.439838],"type":"Point"}
}