{
  "type": "Feature",
  "properties": {
    "iso:country":"NL",
    "sg:address":"Amsterdamsewg 175",
    "sg:city":"Amstelveen",
    "sg:orig_category":"Verzekeringen - Verzekeringskantoren",
    "sg:phone":"+31 20 547 0111",
    "sg:postcode":"1182 GV",
    "sg:province":"North Holland",
    "sg:website":"http://www.penp.nl",
    "wof:name":"P & P",
    "wof:placetype":"venue"
},
  "geometry": {"coordinates":[4.846551,52.310658],"type":"Point"}
}