{
  "type": "Feature",
  "properties": {
    "addr:full":"Wikke 3 Uithoorn Noord-Holland 1422 MZ",
    "addr:housenumber":"3",
    "addr:postcode":"1422 mz",
    "addr:street":"Wikke",
    "iso:country":"NL",
    "sg:address":"Wikke 3",
    "sg:city":"Uithoorn",
    "sg:orig_category":"Logopedisten",
    "sg:phone":"+31 297 569 916",
    "sg:postcode":"1422 MZ",
    "sg:province":"Noord-Holland",
    "wof:name":"Anke Van Niele-Knaap, Logopediepraktijk",
    "wof:placetype":"venue"
},
  "geometry": {"coordinates":[4.817013,52.246693],"type":"Point"}
}