{
  "type": "Feature",
  "properties": {
    "addr:full":"Glaciswg 45 Maastricht Limburg 6212 BM",
    "addr:housenumber":"45",
    "addr:postcode":"6212 bm",
    "addr:street":"Glaciswg",
    "iso:country":"NL",
    "sg:address":"Glaciswg 45",
    "sg:city":"Maastricht",
    "sg:orig_category":"Beeldende Kunstenaars",
    "sg:phone":"+31 43 325 2894",
    "sg:postcode":"6212 BM",
    "sg:province":"Limburg",
    "wof:name":"Reynders, Math",
    "wof:placetype":"venue"
},
  "geometry": {"coordinates":[5.690249,50.839653],"type":"Point"}
}