{
  "type": "Feature",
  "properties": {
    "addr:full":"Klothal 1 Sint Oedenrode Noord-Brabant 5491 KA",
    "addr:housenumber":"1;oedenrode",
    "addr:postcode":"5491 ka",
    "addr:street":"Klothal",
    "iso:country":"NL",
    "sg:address":"Klothal 1",
    "sg:city":"Sint Oedenrode",
    "sg:orig_category":"Kinderactiviteiten",
    "sg:phone":"+31 413 478 912",
    "sg:postcode":"5491 KA",
    "sg:province":"Noord-Brabant",
    "wof:name":"Kienehoeve",
    "wof:placetype":"venue"
},
  "geometry": {"coordinates":[5.452045,51.575264],"type":"Point"}
}