{
  "type": "Feature",
  "properties": {
    "iso:country":"NL",
    "sg:address":"Ranonkelstraat 35",
    "sg:city":"Alkmaar",
    "sg:orig_category":"Vertaal- And Tolkenbureaus",
    "sg:phone":"+31 72 515 7551",
    "sg:postcode":"1817 CC",
    "sg:province":"Noord-Holland",
    "wof:name":"Mw. I. Kalf",
    "wof:placetype":"venue"
},
  "geometry": {"coordinates":[4.741382,52.64072],"type":"Point"}
}