{
  "type": "Feature",
  "properties": {
    "addr:full":"Schenkelse Dreef 1 Capelle Ad Yssel Zuid-Holland 2906 VM",
    "addr:housenumber":"1",
    "addr:postcode":"2906 vm",
    "addr:street":"Dreef",
    "iso:country":"NL",
    "sg:address":"Schenkelse Dreef 1",
    "sg:city":"Capelle Ad Yssel",
    "sg:orig_category":"Verenigingen En Stichtingen",
    "sg:phone":"+31 10 450 6572",
    "sg:postcode":"2906 VM",
    "sg:province":"Zuid-Holland",
    "wof:name":"Dagcentr Noord Oost",
    "wof:placetype":"venue"
},
  "geometry": {"coordinates":[4.573106,51.931671],"type":"Point"}
}