{
  "type": "Feature",
  "properties": {
    "iso:country":"NL",
    "sg:address":"Pastoor Pottersplein 17",
    "sg:city":"Breda",
    "sg:orig_category":"Boekhouders",
    "sg:phone":"+31 76 571 9716",
    "sg:postcode":"4815 BA",
    "sg:province":"Noord-Brabant",
    "wof:name":"A.M. Bastiaansen",
    "wof:placetype":"venue"
},
  "geometry": {"coordinates":[4.777419,51.599255],"type":"Point"}
}