{
  "type": "Feature",
  "properties": {
    "addr:full":"Stationsstraat 5 Middelburg Zeeland 4331 JA",
    "addr:housenumber":"5",
    "addr:postcode":"4331 ja",
    "addr:street":"Stationsstraat",
    "iso:country":"NL",
    "sg:address":"Stationsstraat 5",
    "sg:city":"Middelburg",
    "sg:classifiers":[
        {
            "category":"Retail",
            "subcategory":"Photofinishing",
            "type":"Services"
        }
    ],
    "sg:phone":"+31 118 612 633",
    "sg:postcode":"4331 JA",
    "sg:province":"Zeeland",
    "sg:tags":[
        "foto",
        "film"
    ],
    "wof:name":"De Pas Fotoboetiek",
    "wof:placetype":"venue"
},
  "geometry": {"coordinates":[3.617452,51.49612],"type":"Point"}
}