{
  "type": "Feature",
  "properties": {
    "iso:country":"NL",
    "sg:address":"Deltaweg 185",
    "sg:city":"Helmond",
    "sg:orig_category":"Politie",
    "sg:phone":"+31 492 561 490",
    "sg:postcode":"5709 AA",
    "sg:province":"Noord-Brabant",
    "wof:name":"Politie Brabant Zuid-Oost District Helmond Oost",
    "wof:placetype":"venue"
},
  "geometry": {"coordinates":[5.701883,51.471024],"type":"Point"}
}