{
  "type": "Feature",
  "properties": {
    "iso:country":"NL",
    "sg:address":"Oude Raadhuisln 27",
    "sg:city":"Rotterdam",
    "sg:orig_category":"Adviesbureaus Bouwkunde",
    "sg:phone":"+31 10 418 9841",
    "sg:postcode":"3054 NM",
    "sg:province":"Zuid-Holland",
    "wof:name":"Bmr",
    "wof:placetype":"venue"
},
  "geometry": {"coordinates":[4.492862,51.957928],"type":"Point"}
}