{
  "type": "Feature",
  "properties": {
    "addr:full":"Doctor Cuyperslaan 47 Eindhoven North Brabant 5622 MA",
    "addr:housenumber":"47",
    "addr:postcode":"5622 ma",
    "addr:street":"Doctor Cuyperslaan",
    "iso:country":"NL",
    "sg:address":"Doctor Cuyperslaan 47",
    "sg:city":"Eindhoven",
    "sg:orig_category":"Beroepsorganisaties",
    "sg:phone":"+31 40 244 2433",
    "sg:postcode":"5622 MA",
    "sg:province":"North Brabant",
    "wof:name":"Bouw- En Houtbond Fnv",
    "wof:placetype":"venue"
},
  "geometry": {"coordinates":[5.470849,51.457706],"type":"Point"}
}