{
  "type": "Feature",
  "properties": {
    "iso:country":"NL",
    "sg:address":"J V Kanrede 57",
    "sg:city":"Capelle Ad Yssel",
    "sg:orig_category":"Verenigingen En Stichtingen",
    "sg:phone":"+31 10 451 7644",
    "sg:postcode":"2901 TA",
    "sg:province":"Zuid-Holland",
    "wof:name":"Buurtgroep Capelle West, Sticht",
    "wof:placetype":"venue"
},
  "geometry": {"coordinates":[4.56426,51.916981],"type":"Point"}
}