{
  "type": "Feature",
  "properties": {
    "addr:full":"Markendaalsewg 2A Breda Noord-Brabant 4811 KC",
    "addr:housenumber":"2a",
    "addr:postcode":"4811 kc",
    "addr:street":"Markendaalsewg",
    "iso:country":"NL",
    "sg:address":"Markendaalsewg 2A",
    "sg:city":"Breda",
    "sg:orig_category":"Meubelen",
    "sg:phone":"+31 76 520 5517",
    "sg:postcode":"4811 KC",
    "sg:province":"Noord-Brabant",
    "wof:name":"Lamers & Lamers",
    "wof:placetype":"venue"
},
  "geometry": {"coordinates":[4.771169,51.588272],"type":"Point"}
}