{
  "type": "Feature",
  "properties": {
    "addr:full":"Jansveld 24 Utrecht Utrecht 3512 BG",
    "addr:housenumber":"24",
    "addr:postcode":"3512",
    "addr:street":"Jansveld",
    "iso:country":"NL",
    "sg:address":"Jansveld 24",
    "sg:city":"Utrecht",
    "sg:orig_category":"Psychotherapeuten",
    "sg:phone":"+31 30 231 6307",
    "sg:postcode":"3512 BG",
    "sg:province":"Utrecht",
    "wof:name":"Koper, P A J M",
    "wof:placetype":"venue"
},
  "geometry": {"coordinates":[5.119692,52.09407],"type":"Point"}
}