{
  "type": "Feature",
  "properties": {
    "iso:country":"NL",
    "sg:address":"Jan Olieslagersstraat 51",
    "sg:city":"'S Hertogenbosch",
    "sg:orig_category":"Fitnesscentra",
    "sg:phone":"+31 73 642 9651",
    "sg:postcode":"5224 BD",
    "sg:province":"Noord-Brabant",
    "wof:name":"Sportschool Ellen'S Aerobic Centre",
    "wof:placetype":"venue"
},
  "geometry": {"coordinates":[5.262867,51.698532],"type":"Point"}
}