{
  "type": "Feature",
  "properties": {
    "addr:full":"Generaal Cronjestraat 126 Haarlem Noord-Holland 2021 JM",
    "addr:housenumber":"126",
    "addr:postcode":"2021 jm",
    "addr:street":"Generaal Cronjestraat",
    "iso:country":"NL",
    "sg:address":"Generaal Cronjestraat 126",
    "sg:city":"Haarlem",
    "sg:orig_category":"Meubelzaken, Woning- And Keukeninrichting",
    "sg:phone":"+31 23 527 7125",
    "sg:postcode":"2021 JM",
    "sg:province":"Noord-Holland",
    "wof:name":"Het Beddencentrum Afd Bedtextiel",
    "wof:placetype":"venue"
},
  "geometry": {"coordinates":[4.642385,52.395226],"type":"Point"}
}