{
  "type": "Feature",
  "properties": {
    "addr:full":"Zevenbergseweg 12 Plasmolen Limburg 6586 AJ",
    "addr:housenumber":"12",
    "addr:postcode":"6586 aj",
    "addr:street":"Zevenbergseweg",
    "iso:country":"NL",
    "sg:address":"Zevenbergseweg 12",
    "sg:city":"Plasmolen",
    "sg:orig_category":"Zalenexploitatie",
    "sg:phone":"+31 24 696 2176",
    "sg:postcode":"6586 AJ",
    "sg:province":"Limburg",
    "wof:name":"Galerie De Vierde Dimensie",
    "wof:placetype":"venue"
},
  "geometry": {"coordinates":[5.924845,51.733898],"type":"Point"}
}