{
  "type": "Feature",
  "properties": {
    "addr:full":"Bierwischstr 5-14 Arnhem Gelderland 6831 HZ",
    "addr:housenumber":"5-14",
    "addr:postcode":"6831 hz",
    "iso:country":"NL",
    "sg:address":"Bierwischstr 5-14",
    "sg:city":"Arnhem",
    "sg:orig_category":"Accountants - Administratie- Consulenten En -Kantoren",
    "sg:phone":"+31 26 323 3343",
    "sg:postcode":"6831 HZ",
    "sg:province":"Gelderland",
    "wof:name":"Mulder Accountantskantoor",
    "wof:placetype":"venue"
},
  "geometry": {"coordinates":[5.897418,51.959881],"type":"Point"}
}