{
  "type": "Feature",
  "properties": {
    "iso:country":"NL",
    "sg:address":"Nijverheidstraat 11",
    "sg:city":"Katwijk Zh",
    "sg:classifiers":[
        {
            "category":"Retail",
            "subcategory":"Storage",
            "type":"Services"
        }
    ],
    "sg:phone":"+31 71 403 0773",
    "sg:postcode":"2222 AV",
    "sg:province":"South Holland",
    "sg:tags":[
        "opslag",
        "bewaring"
    ],
    "wof:name":"Firma Gebroeders De Jong",
    "wof:placetype":"venue"
},
  "geometry": {"coordinates":[4.4361329079,52.2037811279],"type":"Point"}
}