{
  "type": "Feature",
  "properties": {
    "addr:full":"Sarphatipk 106 Amsterdam Noord-Holland 1073 EC",
    "addr:housenumber":"106",
    "addr:postcode":"1073 ec",
    "iso:country":"NL",
    "sg:address":"Sarphatipk 106",
    "sg:city":"Amsterdam",
    "sg:classifiers":[
        {
            "category":"Travel",
            "subcategory":"Hotels & Motels",
            "type":"Entertainment"
        }
    ],
    "sg:phone":"+31 20 676 0310",
    "sg:postcode":"1073 EC",
    "sg:province":"Noord-Holland",
    "wof:name":"Aalborg",
    "wof:placetype":"venue"
},
  "geometry": {"coordinates":[4.897509,52.35371],"type":"Point"}
}