{
  "type": "Feature",
  "properties": {
    "addr:full":"Vlasakker 2 Losser Overijssel 7582 AS",
    "addr:housenumber":"2",
    "addr:postcode":"7582 as",
    "addr:street":"Vlasakker",
    "iso:country":"NL",
    "sg:address":"Vlasakker 2",
    "sg:city":"Losser",
    "sg:orig_category":"Verenigingsgebouwen",
    "sg:phone":"+31 53 536 9400",
    "sg:postcode":"7582 AS",
    "sg:province":"Overijssel",
    "wof:name":"Muchte, De",
    "wof:placetype":"venue"
},
  "geometry": {"coordinates":[7.002753,52.260647],"type":"Point"}
}