{
  "type": "Feature",
  "properties": {
    "addr:full":"Eerbeekseweg 8 Loenen Gld Gelderland 7371 CG",
    "addr:housenumber":"8",
    "addr:postcode":"7371 cg",
    "addr:street":"Eerbeekseweg;Gld Gelderland",
    "iso:country":"NL",
    "sg:address":"Eerbeekseweg 8",
    "sg:city":"Loenen Gld",
    "sg:orig_category":"Kappers",
    "sg:phone":"+31 55 505 1934",
    "sg:postcode":"7371 CG",
    "sg:province":"Gelderland",
    "wof:name":"Drogisterij En Kapsalon Bosman",
    "wof:placetype":"venue"
},
  "geometry": {"coordinates":[6.0180668831,52.1153945923],"type":"Point"}
}