{
  "type": "Feature",
  "properties": {
    "addr:full":"Waterloweg 49 Ede Gld Gelderland 6713 AR",
    "addr:housenumber":"49",
    "addr:postcode":"6713",
    "addr:street":"Waterloweg;Gld Gelderland",
    "iso:country":"NL",
    "sg:address":"Waterloweg 49",
    "sg:city":"Ede Gld",
    "sg:orig_category":"Landbouwmachines Gh",
    "sg:phone":"+31 318 651 617",
    "sg:postcode":"6713 AR",
    "sg:province":"Gelderland",
    "wof:name":"Handelsonderneming En Servicebedrijf A.",
    "wof:placetype":"venue"
},
  "geometry": {"coordinates":[5.663021,52.042431],"type":"Point"}
}