{
  "type": "Feature",
  "properties": {
    "iso:country":"NL",
    "sg:address":"Dalweg 115",
    "sg:city":"Soest",
    "sg:orig_category":"Wegen And Sportterreinen",
    "sg:phone":"+31 35 603 0712",
    "sg:postcode":"3764 BV",
    "sg:province":"Utrecht",
    "wof:name":"E. Van Roest",
    "wof:placetype":"venue"
},
  "geometry": {"coordinates":[5.2999930382,52.1793632507],"type":"Point"}
}