{
  "type": "Feature",
  "properties": {
    "addr:full":"Waddenwg 4 Amsterdam Noord-Holland 1025 PV",
    "addr:housenumber":"4",
    "addr:postcode":"1025 pv",
    "addr:street":"Waddenwg",
    "iso:country":"NL",
    "sg:address":"Waddenwg 4",
    "sg:city":"Amsterdam",
    "sg:orig_category":"Kappers",
    "sg:phone":"+31 20 636 1164",
    "sg:postcode":"1025 PV",
    "sg:province":"Noord-Holland",
    "wof:name":"Hofman, Nico",
    "wof:placetype":"venue"
},
  "geometry": {"coordinates":[4.9256029129,52.3912353516],"type":"Point"}
}