{
  "type": "Feature",
  "properties": {
    "addr:full":"Tyssenvoort 11 Helmond Noord-Brabant 5706 KK",
    "addr:housenumber":"11",
    "addr:postcode":"5706 kk",
    "addr:street":"Tyssenvoort",
    "iso:country":"NL",
    "sg:address":"Tyssenvoort 11",
    "sg:city":"Helmond",
    "sg:orig_category":"Boekhandels",
    "sg:phone":"+31 492 574 826",
    "sg:postcode":"5706 KK",
    "sg:province":"Noord-Brabant",
    "wof:name":"Media Expresse",
    "wof:placetype":"venue"
},
  "geometry": {"coordinates":[5.62382,51.461117],"type":"Point"}
}