{
  "type": "Feature",
  "properties": {
    "addr:full":"Muurzwaluw 55 Veenendaal Utrecht 3905 RW",
    "addr:housenumber":"55",
    "addr:postcode":"3905 rw",
    "addr:street":"Muurzwaluw",
    "iso:country":"NL",
    "sg:address":"Muurzwaluw 55",
    "sg:city":"Veenendaal",
    "sg:orig_category":"Webdesign Bureaus",
    "sg:phone":"+31 318 517 955",
    "sg:postcode":"3905 RW",
    "sg:province":"Utrecht",
    "sg:website":"http://www.twoface.nl",
    "wof:name":"Two Face",
    "wof:placetype":"venue"
},
  "geometry": {"coordinates":[5.5345830917,52.0305099487],"type":"Point"}
}