{
  "type": "Feature",
  "properties": {
    "addr:full":"Venusstr 15 Sittard Limburg 6133 WJ",
    "addr:housenumber":"15",
    "addr:postcode":"6133 wj",
    "addr:street":"Venusstr",
    "iso:country":"NL",
    "sg:address":"Venusstr 15",
    "sg:city":"Sittard",
    "sg:orig_category":"Adviesbureaus Bedrijfsorganisatie",
    "sg:phone":"+31 46 452 9776",
    "sg:postcode":"6133 WJ",
    "sg:province":"Limburg",
    "wof:name":"Qualitas",
    "wof:placetype":"venue"
},
  "geometry": {"coordinates":[5.860288,50.98497],"type":"Point"}
}