{
  "type": "Feature",
  "properties": {
    "addr:full":"Trippaardstr 23 Thorn Limburg 6017 AM",
    "addr:housenumber":"23",
    "addr:postcode":"6017",
    "addr:street":"Trippaardstr",
    "iso:country":"NL",
    "sg:address":"Trippaardstr 23",
    "sg:city":"Thorn",
    "sg:orig_category":"Advocaten En Advocatenkantoren",
    "sg:phone":"+31 475 565 820",
    "sg:postcode":"6017 AM",
    "sg:province":"Limburg",
    "wof:name":"Kemme, Mr M",
    "wof:placetype":"venue"
},
  "geometry": {"coordinates":[5.844045,51.161186],"type":"Point"}
}