{
  "type": "Feature",
  "properties": {
    "addr:full":"Burg Godschalxstr 41 'S Hertogenbosch North Brabant 5236 AA",
    "addr:housenumber":"41",
    "addr:postcode":"5236 aa",
    "addr:street":"Burg;' S Hertogenbosch",
    "iso:country":"NL",
    "sg:address":"Burg Godschalxstr 41",
    "sg:city":"'S Hertogenbosch",
    "sg:orig_category":"Goederenvervoer Over De Weg",
    "sg:phone":"+31 73 642 2371",
    "sg:postcode":"5236 AA",
    "sg:province":"North Brabant",
    "wof:name":"Transportbedrijf Kooijmans Bv",
    "wof:placetype":"venue"
},
  "geometry": {"coordinates":[5.324621,51.729195],"type":"Point"}
}