{
  "type": "Feature",
  "properties": {
    "addr:full":"Florynstr 4 A Etten Leur Noord-Brabant 4879 AH",
    "addr:housenumber":"4 a",
    "addr:postcode":"4879 ah",
    "addr:street":"Florynstr",
    "iso:country":"NL",
    "sg:address":"Florynstr 4 A",
    "sg:city":"Etten Leur",
    "sg:orig_category":"Elektrotechnische Installatiebureaus",
    "sg:phone":"+31 76 504 1501",
    "sg:postcode":"4879 AH",
    "sg:province":"Noord-Brabant",
    "wof:name":"Broeders, Elektrotechniek",
    "wof:placetype":"venue"
},
  "geometry": {"coordinates":[4.61451,51.561871],"type":"Point"}
}