{
  "type": "Feature",
  "properties": {
    "addr:full":"Langestraat 59 Genemuiden Overijssel 8281 AG",
    "addr:housenumber":"59",
    "addr:postcode":"8281",
    "addr:street":"Langestraat",
    "iso:country":"NL",
    "sg:address":"Langestraat 59",
    "sg:city":"Genemuiden",
    "sg:classifiers":[
        {
            "category":"Fast Food",
            "type":"Food & Drink"
        }
    ],
    "sg:phone":"+31 38 385 5074",
    "sg:postcode":"8281 AG",
    "sg:province":"Overijssel",
    "sg:tags":[
        "afhaal",
        "restaurant"
    ],
    "wof:name":"Fa Snackbar Henk Bos",
    "wof:placetype":"venue"
},
  "geometry": {"coordinates":[6.041208,52.62241],"type":"Point"}
}