{
  "type": "Feature",
  "properties": {
    "iso:country":"NL",
    "sg:address":"Lookertstraat 8",
    "sg:city":"Sint Michielsgestel",
    "sg:orig_category":"Hoefdierhouderijen",
    "sg:phone":"+31 73 551 3485",
    "sg:postcode":"5271 VC",
    "sg:province":"Noord-Brabant",
    "wof:name":"Manegebedrijf De Krom",
    "wof:placetype":"venue"
},
  "geometry": {"coordinates":[5.3466,51.65387],"type":"Point"}
}