{
  "type": "Feature",
  "properties": {
    "addr:full":"Lookertstraat 8 Sint Michielsgestel Noord-Brabant 5271 VC",
    "addr:housenumber":"8;michielsgestel",
    "addr:postcode":"5271 vc",
    "addr:street":"Lookertstraat",
    "iso:country":"NL",
    "sg:address":"Lookertstraat 8",
    "sg:city":"Sint Michielsgestel",
    "sg:orig_category":"Hoefdierhouderijen",
    "sg:phone":"+31 73 551 3485",
    "sg:postcode":"5271 VC",
    "sg:province":"Noord-Brabant",
    "wof:name":"Manegebedrijf De Krom",
    "wof:placetype":"venue"
},
  "geometry": {"coordinates":[5.3466,51.65387],"type":"Point"}
}