{
  "type": "Feature",
  "properties": {
    "addr:full":"Waalsdorperln 29 Wassenaar Zuid-Holland 2244 BN",
    "addr:housenumber":"29",
    "addr:postcode":"2244 bn",
    "addr:street":"Waalsdorperln",
    "iso:country":"NL",
    "sg:address":"Waalsdorperln 29",
    "sg:city":"Wassenaar",
    "sg:orig_category":"Paardensport",
    "sg:phone":"+31 70 314 8740",
    "sg:postcode":"2244 BN",
    "sg:province":"Zuid-Holland",
    "sg:website":"http://www.renbaanduindigt.nl",
    "wof:name":"Duindigt",
    "wof:placetype":"venue"
},
  "geometry": {"coordinates":[4.339981,52.105637],"type":"Point"}
}