{
  "type": "Feature",
  "properties": {
    "addr:full":"Langevaart 22 Rynsburg Zuid-Holland 2231 GC",
    "addr:housenumber":"22",
    "addr:postcode":"2231 gc",
    "addr:street":"Langevaart",
    "iso:country":"NL",
    "sg:address":"Langevaart 22",
    "sg:city":"Rynsburg",
    "sg:orig_category":"Bloemen En Planten - Groothandel",
    "sg:phone":"+31 71 402 2076",
    "sg:postcode":"2231 GC",
    "sg:province":"Zuid-Holland",
    "wof:name":"Kralt & Zn Bv, Nico",
    "wof:placetype":"venue"
},
  "geometry": {"coordinates":[4.43887,52.190571],"type":"Point"}
}