{
  "type": "Feature",
  "properties": {
    "addr:full":"Groenelaan 1 Woldendorp Groningen 9946 RG",
    "addr:housenumber":"1",
    "addr:postcode":"9946 rg",
    "addr:street":"Groenelaan",
    "iso:country":"NL",
    "sg:address":"Groenelaan 1",
    "sg:city":"Woldendorp",
    "sg:orig_category":"Verzekeringen",
    "sg:phone":"+31 596 601 500",
    "sg:postcode":"9946 RG",
    "sg:province":"Groningen",
    "wof:name":"Plas Algemeen Assurantiekantoor",
    "wof:placetype":"venue"
},
  "geometry": {"coordinates":[7.029098,53.272041],"type":"Point"}
}