{
  "type": "Feature",
  "properties": {
    "iso:country":"NL",
    "sg:address":"Tuinstraat 34",
    "sg:city":"Tilburg",
    "sg:orig_category":"Werving And Selectie Van Tijdelijk Personeel And Uitzendkantoren",
    "sg:phone":"+31 13 536 2930",
    "sg:postcode":"5038 DC",
    "sg:province":"North Brabant",
    "wof:name":"Eksakt",
    "wof:placetype":"venue"
},
  "geometry": {"coordinates":[5.0857701302,51.5574417114],"type":"Point"}
}