{
  "type": "Feature",
  "properties": {
    "iso:country":"NL",
    "sg:address":"Atalantaberm 15",
    "sg:city":"Houten",
    "sg:orig_category":"Marktonderzoekbureaus",
    "sg:phone":"+31 30 635 1540",
    "sg:postcode":"3994 WB",
    "sg:province":"Utrecht",
    "wof:name":"Marketing- En Org.Adv.Bur. H. Ter Steege",
    "wof:placetype":"venue"
},
  "geometry": {"coordinates":[5.183378,52.037075],"type":"Point"}
}