{
  "type": "Feature",
  "properties": {
    "addr:full":"Keesomstraat 4 Ede Gld Gelderland 6716 AB",
    "addr:housenumber":"4",
    "addr:postcode":"6716 ab",
    "addr:street":"Keesomstraat;Gld Gelderland",
    "iso:country":"NL",
    "sg:address":"Keesomstraat 4",
    "sg:city":"Ede Gld",
    "sg:orig_category":"Huishoudapparatuur, Televisies And Radio'S",
    "sg:phone":"+31 318 676 111",
    "sg:postcode":"6716 AB",
    "sg:province":"Gelderland",
    "wof:name":"De Drie Electronics Bv",
    "wof:placetype":"venue"
},
  "geometry": {"coordinates":[5.645575,52.031937],"type":"Point"}
}