{
  "type": "Feature",
  "properties": {
    "addr:full":"Helmondsestr 68 Bakel Noord-Brabant 5761 CT",
    "addr:housenumber":"68",
    "addr:postcode":"5761 ct",
    "addr:street":"Helmondsestr",
    "iso:country":"NL",
    "sg:address":"Helmondsestr 68",
    "sg:city":"Bakel",
    "sg:orig_category":"Verpakkingsmachines - Fabrieken",
    "sg:phone":"+31 492 343 529",
    "sg:postcode":"5761 CT",
    "sg:province":"Noord-Brabant",
    "sg:website":"http://www.ibw.nl/hurkmans",
    "wof:name":"Hurkmans",
    "wof:placetype":"venue"
},
  "geometry": {"coordinates":[81.811279,19.351259],"type":"Point"}
}