{
  "type": "Feature",
  "properties": {
    "addr:full":"Baden-Powellstraat 231 Haarlem Noord-Holland 2037 SR",
    "addr:housenumber":"231",
    "addr:postcode":"2037 sr",
    "addr:street":"Baden-Powellstraat",
    "iso:country":"NL",
    "sg:address":"Baden-Powellstraat 231",
    "sg:city":"Haarlem",
    "sg:orig_category":"Verhuur Audiovisuele Apparatuur",
    "sg:phone":"+31 23 535 9577",
    "sg:postcode":"2037 SR",
    "sg:province":"Noord-Holland",
    "wof:name":"First Step Studio",
    "wof:placetype":"venue"
},
  "geometry": {"coordinates":[4.660844,52.356335],"type":"Point"}
}