{
  "type": "Feature",
  "properties": {
    "addr:full":"Koeweitdreef 20 Utrecht Utrecht 3564 HC",
    "addr:housenumber":"20",
    "addr:postcode":"3564 hc",
    "addr:street":"Koeweitdreef",
    "iso:country":"NL",
    "sg:address":"Koeweitdreef 20",
    "sg:city":"Utrecht",
    "sg:orig_category":"Verhuizingen",
    "sg:phone":"+31 30 261 3035",
    "sg:postcode":"3564 HC",
    "sg:province":"Utrecht",
    "wof:name":"Haarlem Bv, W Van",
    "wof:placetype":"venue"
},
  "geometry": {"coordinates":[5.104542,52.12524],"type":"Point"}
}