{
  "type": "Feature",
  "properties": {
    "iso:country":"NL",
    "sg:address":"Frombergstraat 60",
    "sg:city":"Arnhem",
    "sg:orig_category":"Bloemen And Planten",
    "sg:phone":"+31 26 351 6824",
    "sg:postcode":"6814 EC",
    "sg:province":"Gelderland",
    "wof:name":"Bloemenhal Maassen & Co",
    "wof:placetype":"venue"
},
  "geometry": {"coordinates":[5.895015,51.987003],"type":"Point"}
}