{
  "type": "Feature",
  "properties": {
    "iso:country":"NL",
    "sg:address":"Pr Hendrikstr 4",
    "sg:city":"Wierden",
    "sg:orig_category":"Accountants - Administratie- Consulenten En -Kantoren",
    "sg:phone":"+31 546 577 373",
    "sg:postcode":"7642 BT",
    "sg:province":"Overijssel",
    "wof:name":"Dijk & Meinen, Van",
    "wof:placetype":"venue"
},
  "geometry": {"coordinates":[6.590784,52.356815],"type":"Point"}
}