{
  "type": "Feature",
  "properties": {
    "addr:full":"Auxiliatrixwg 35 Venlo Limburg 5915 PN",
    "addr:housenumber":"35",
    "addr:postcode":"5915 pn",
    "addr:street":"Auxiliatrixwg",
    "iso:country":"NL",
    "sg:address":"Auxiliatrixwg 35",
    "sg:city":"Venlo",
    "sg:orig_category":"Ziekenhuizen, Sanatoria, Verpleeghuizen",
    "sg:phone":"+31 77 355 9555",
    "sg:postcode":"5915 PN",
    "sg:province":"Limburg",
    "sg:website":"http://www.zorggroep-noord-limburg.nl",
    "wof:name":"Horstgraaf, D'N",
    "wof:placetype":"venue"
},
  "geometry": {"coordinates":[6.185188,51.340225],"type":"Point"}
}