{
  "type": "Feature",
  "properties": {
    "addr:full":"Noormannenstr 1 Haarlem Noord-Holland 2033 LG",
    "addr:housenumber":"1",
    "addr:postcode":"2033 lg",
    "addr:street":"Noormannenstr",
    "iso:country":"NL",
    "sg:address":"Noormannenstr 1",
    "sg:city":"Haarlem",
    "sg:orig_category":"Peuterspeelzalen",
    "sg:phone":"+31 23 533 7715",
    "sg:postcode":"2033 LG",
    "sg:province":"Noord-Holland",
    "wof:name":"Hummeltje, 'T",
    "wof:placetype":"venue"
},
  "geometry": {"coordinates":[4.64591,52.370918],"type":"Point"}
}