{
  "type": "Feature",
  "properties": {
    "addr:full":"Magnoliastr 36 Vlaardingen South Holland 3135 VS",
    "addr:housenumber":"36",
    "addr:postcode":"3135 vs",
    "addr:street":"Magnoliastr",
    "iso:country":"NL",
    "sg:address":"Magnoliastr 36",
    "sg:city":"Vlaardingen",
    "sg:orig_category":"Wassalons",
    "sg:phone":"+31 10 471 0060",
    "sg:postcode":"3135 VS",
    "sg:province":"South Holland",
    "wof:name":"Wassalon, De",
    "wof:placetype":"venue"
},
  "geometry": {"coordinates":[4.3591208458,51.9168281555],"type":"Point"}
}