{
  "type": "Feature",
  "properties": {
    "iso:country":"NL",
    "sg:address":"S I Zwartzstraat 6",
    "sg:city":"Oldenzaal",
    "sg:orig_category":"Schoonheidssalons",
    "sg:phone":"+31 541 518 653",
    "sg:postcode":"7574 XK",
    "sg:province":"Overijssel",
    "wof:name":"B. Grundel",
    "wof:placetype":"venue"
},
  "geometry": {"coordinates":[6.933025,52.297337],"type":"Point"}
}