{
  "type": "Feature",
  "properties": {
    "addr:full":"S I Zwartzstraat 6 Oldenzaal Overijssel 7574 XK",
    "addr:housenumber":"6",
    "addr:postcode":"7574 xk",
    "addr:street":"S I Zwartzstraat",
    "iso:country":"NL",
    "sg:address":"S I Zwartzstraat 6",
    "sg:city":"Oldenzaal",
    "sg:orig_category":"Schoonheidssalons",
    "sg:phone":"+31 541 518 653",
    "sg:postcode":"7574 XK",
    "sg:province":"Overijssel",
    "wof:name":"B. Grundel",
    "wof:placetype":"venue"
},
  "geometry": {"coordinates":[6.933025,52.297337],"type":"Point"}
}