{
  "type": "Feature",
  "properties": {
    "addr:full":"De Groendijck 20 Driebruggen Zuid-Holland 3465 JB",
    "addr:housenumber":"20",
    "addr:postcode":"3465 jb",
    "addr:street":"De Groendijck",
    "iso:country":"NL",
    "sg:address":"De Groendijck 20",
    "sg:city":"Driebruggen",
    "sg:orig_category":"Diverse Bedrijfsinstallaties Gh",
    "sg:phone":"+31 348 501 578",
    "sg:postcode":"3465 JB",
    "sg:province":"Zuid-Holland",
    "wof:name":"Leen Van De Berg Werkplaatsuitrustingen Vof",
    "wof:placetype":"venue"
},
  "geometry": {"coordinates":[4.802941,52.044712],"type":"Point"}
}