{
  "type": "Feature",
  "properties": {
    "addr:full":"Newtonstr 19 Heerhugowaard Noord-Holland 1704 SB",
    "addr:housenumber":"19",
    "addr:postcode":"1704 sb",
    "addr:street":"Newtonstr",
    "iso:country":"NL",
    "sg:address":"Newtonstr 19",
    "sg:city":"Heerhugowaard",
    "sg:orig_category":"Fotostudio'S",
    "sg:phone":"+31 72 571 0761",
    "sg:postcode":"1704 SB",
    "sg:province":"Noord-Holland",
    "wof:name":"Harpenau, Rob",
    "wof:placetype":"venue"
},
  "geometry": {"coordinates":[4.834408,52.689434],"type":"Point"}
}