{
  "type": "Feature",
  "properties": {
    "iso:country":"NL",
    "sg:address":"Zwanenpln 10",
    "sg:city":"Amsterdam",
    "sg:orig_category":"Adviesbureaus",
    "sg:phone":"+31 6 14439232",
    "sg:postcode":"1021 CL",
    "sg:province":"Noord-Holland",
    "wof:name":"Omega Dienstverlening",
    "wof:placetype":"venue"
},
  "geometry": {"coordinates":[4.918603,52.386688],"type":"Point"}
}