{
  "type": "Feature",
  "properties": {
    "iso:country":"NL",
    "sg:address":"Stadionwg 254",
    "sg:city":"Amsterdam",
    "sg:orig_category":"Zonweringen",
    "sg:phone":"+31 20 675 2835",
    "sg:postcode":"1076 PC",
    "sg:province":"North Holland",
    "wof:name":"Olympus",
    "wof:placetype":"venue"
},
  "geometry": {"coordinates":[4.863677,52.346092],"type":"Point"}
}