{
  "type": "Feature",
  "properties": {
    "iso:country":"NL",
    "sg:address":"Ginnekenweg 90",
    "sg:city":"Breda",
    "sg:orig_category":"Kappers",
    "sg:phone":"+31 76 522 9573",
    "sg:postcode":"4818 JH",
    "sg:province":"Noord-Brabant",
    "wof:name":"T Knipcafe",
    "wof:placetype":"venue"
},
  "geometry": {"coordinates":[4.7818908691,51.5759010315],"type":"Point"}
}