{
  "type": "Feature",
  "properties": {
    "addr:full":"Zonnebloemstr 13 Almelo Overijssel 7601 BV",
    "addr:housenumber":"13",
    "addr:postcode":"7601 bv",
    "addr:street":"Zonnebloemstr",
    "iso:country":"NL",
    "sg:address":"Zonnebloemstr 13",
    "sg:city":"Almelo",
    "sg:orig_category":"Wegenbouw",
    "sg:phone":"+31 546 810 304",
    "sg:postcode":"7601 BV",
    "sg:province":"Overijssel",
    "wof:name":"Kuipers",
    "wof:placetype":"venue"
},
  "geometry": {"coordinates":[6.6631650925,52.3453216553],"type":"Point"}
}