{
  "type": "Feature",
  "properties": {
    "addr:full":"Dr. Kuyperstraat 14 'S Gravenhage South Holland 2514 BB",
    "addr:housenumber":"14",
    "addr:postcode":"2514 bb",
    "addr:street":"Dr. Kuyperstraat;' S Gravenhage",
    "iso:country":"NL",
    "sg:address":"Dr. Kuyperstraat 14",
    "sg:city":"'S Gravenhage",
    "sg:orig_category":"Werving And Selectie Van Vast Personeel",
    "sg:phone":"+31 70 365 2306",
    "sg:postcode":"2514 BB",
    "sg:province":"South Holland",
    "wof:name":"Business Creation Result Bv",
    "wof:placetype":"venue"
},
  "geometry": {"coordinates":[4.313601017,52.087310791],"type":"Point"}
}