{
  "type": "Feature",
  "properties": {
    "addr:full":"Kerkstr 119 Brunssum Limburg 6441 BD",
    "addr:housenumber":"119",
    "addr:postcode":"6441 bd",
    "addr:street":"Brunssum Limburg",
    "iso:country":"NL",
    "sg:address":"Kerkstr 119",
    "sg:city":"Brunssum",
    "sg:orig_category":"Verzekeringen - Verzekeringskantoren",
    "sg:phone":"+31 45 525 3346",
    "sg:postcode":"6441 BD",
    "sg:province":"Limburg",
    "wof:name":"Heco Adviesgroep",
    "wof:placetype":"venue"
},
  "geometry": {"coordinates":[5.971814,50.949177],"type":"Point"}
}