{
  "type": "Feature",
  "properties": {
    "addr:full":"Rootven 20 Bladel North Brabant 5531 MB",
    "addr:housenumber":"20",
    "addr:postcode":"5531 mb",
    "addr:street":"Rootven",
    "iso:country":"NL",
    "sg:address":"Rootven 20",
    "sg:city":"Bladel",
    "sg:orig_category":"Verpakkingsmachines Fab",
    "sg:phone":"+31 497 362 500",
    "sg:postcode":"5531 MB",
    "sg:province":"North Brabant",
    "wof:name":"Amse Bv",
    "wof:placetype":"venue"
},
  "geometry": {"coordinates":[5.204859,51.355427],"type":"Point"}
}