{
  "type": "Feature",
  "properties": {
    "addr:full":"G V Amstelstr 184 Hilversum North Holland 1214 BE",
    "addr:housenumber":"184",
    "addr:postcode":"1214",
    "addr:street":"V Amstelstr",
    "iso:country":"NL",
    "sg:address":"G V Amstelstr 184",
    "sg:city":"Hilversum",
    "sg:orig_category":"Bloemen En Planten",
    "sg:phone":"+31 35 624 4326",
    "sg:postcode":"1214 BE",
    "sg:province":"North Holland",
    "wof:name":"Binderij, De",
    "wof:placetype":"venue"
},
  "geometry": {"coordinates":[5.1695,52.228565],"type":"Point"}
}