{
  "type": "Feature",
  "properties": {
    "addr:full":"Nedereindsestr 5 Kesteren Gelderland 4041 XE",
    "addr:housenumber":"5",
    "addr:postcode":"4041 xe",
    "addr:street":"Nedereindsestr;Gelderland",
    "iso:country":"NL",
    "sg:address":"Nedereindsestr 5",
    "sg:city":"Kesteren",
    "sg:classifiers":[
        {
            "category":"Food & Beverages",
            "subcategory":"Bakery",
            "type":"Retail Goods"
        }
    ],
    "sg:phone":"+31 488 483 591",
    "sg:postcode":"4041 XE",
    "sg:province":"Gelderland",
    "sg:tags":[
        "brood",
        "en",
        "banket"
    ],
    "wof:name":"Voorthuizen, A J Van",
    "wof:placetype":"venue"
},
  "geometry": {"coordinates":[5.573928,51.932838],"type":"Point"}
}