{
  "type": "Feature",
  "properties": {
    "addr:full":"J Corneliszstr 5 Oostzaan Noord-Holland 1511 BM",
    "addr:housenumber":"5",
    "addr:postcode":"1511 bm",
    "iso:country":"NL",
    "sg:address":"J Corneliszstr 5",
    "sg:city":"Oostzaan",
    "sg:orig_category":"Woningbouw- Verenigingen En -Stichtingen",
    "sg:phone":"+31 75 684 5215",
    "sg:postcode":"1511 BM",
    "sg:province":"Noord-Holland",
    "wof:name":"Oostzaanse Volkshuisvesting",
    "wof:placetype":"venue"
},
  "geometry": {"coordinates":[4.8729000092,52.4419441223],"type":"Point"}
}