{
  "type": "Feature",
  "properties": {
    "addr:full":"Tuinstr 35 Tilburg North Brabant 5038 DA",
    "addr:housenumber":"35",
    "addr:postcode":"5038 da",
    "addr:street":"Tuinstr",
    "iso:country":"NL",
    "sg:address":"Tuinstr 35",
    "sg:city":"Tilburg",
    "sg:orig_category":"Boeken En Tijdschriften",
    "sg:phone":"+31 13 544 3781",
    "sg:postcode":"5038 DA",
    "sg:province":"North Brabant",
    "wof:name":"Zevensprong, De",
    "wof:placetype":"venue"
},
  "geometry": {"coordinates":[5.086322,51.557549],"type":"Point"}
}