{
  "type": "Feature",
  "properties": {
    "addr:full":"Kildersewg 17 Zeddam Gelderland 7038 EH",
    "addr:housenumber":"17",
    "addr:postcode":"7038 eh",
    "addr:street":"Kildersewg;Gelderland",
    "iso:country":"NL",
    "sg:address":"Kildersewg 17",
    "sg:city":"Zeddam",
    "sg:classifiers":[
        {
            "category":"Restaurant",
            "type":"Food & Drink"
        }
    ],
    "sg:phone":"+31 314 651 128",
    "sg:postcode":"7038 EH",
    "sg:province":"Gelderland",
    "sg:website":"http://www.dinersite.nl",
    "wof:name":"Palissade",
    "wof:placetype":"venue"
},
  "geometry": {"coordinates":[6.25651,51.907333],"type":"Point"}
}