{
  "type": "Feature",
  "properties": {
    "addr:full":"Tussendiepen 47 Drachten Provincie Friesland 9206 AB",
    "addr:housenumber":"47",
    "addr:postcode":"9206 ab",
    "addr:street":"Tussendiepen;Provincie Friesland",
    "iso:country":"NL",
    "sg:address":"Tussendiepen 47",
    "sg:city":"Drachten",
    "sg:orig_category":"Oud Metaal",
    "sg:phone":"+31 512 531 721",
    "sg:postcode":"9206 AB",
    "sg:province":"Provincie Friesland",
    "wof:name":"Veen Ijzer & Metaalhandel",
    "wof:placetype":"venue"
},
  "geometry": {"coordinates":[6.0679450035,53.1059875488],"type":"Point"}
}