{
  "type": "Feature",
  "properties": {
    "addr:full":"Waterstraat 14 Zaltbommel Gelderland 5301  A",
    "addr:housenumber":"14;5301 a",
    "addr:street":"Waterstraat;Gelderland",
    "iso:country":"NL",
    "sg:address":"Waterstraat 14",
    "sg:city":"Zaltbommel",
    "sg:orig_category":"Boekenuitgeverijen",
    "sg:phone":"+31 418 514 353",
    "sg:postcode":"5301  A",
    "sg:province":"Gelderland",
    "wof:name":"Bruna",
    "wof:placetype":"venue"
},
  "geometry": {"coordinates":[5.247739,51.81398],"type":"Point"}
}