{
  "type": "Feature",
  "properties": {
    "addr:full":"Valkenswaardseweg 29 Leende Noord-Brabant 5595 XB",
    "addr:housenumber":"29",
    "addr:postcode":"5595 xb",
    "addr:street":"Valkenswaardseweg",
    "iso:country":"NL",
    "sg:address":"Valkenswaardseweg 29",
    "sg:city":"Leende",
    "sg:orig_category":"Hoefdierhouderijen",
    "sg:phone":"+31 40 206 1812",
    "sg:postcode":"5595 XB",
    "sg:province":"Noord-Brabant",
    "wof:name":"Handelsstal Frans Van Herten",
    "wof:placetype":"venue"
},
  "geometry": {"coordinates":[5.540677,51.348022],"type":"Point"}
}