{
  "type": "Feature",
  "properties": {
    "addr:full":"Garderensewg 102 Uddel Gelderland 3888 LD",
    "addr:housenumber":"102",
    "addr:postcode":"3888 ld",
    "addr:street":"Gelderland",
    "iso:country":"NL",
    "sg:address":"Garderensewg 102",
    "sg:city":"Uddel",
    "sg:orig_category":"Acupunctuur",
    "sg:phone":"+31 577 401 460",
    "sg:postcode":"3888 LD",
    "sg:province":"Gelderland",
    "wof:name":"Stoltenborgh",
    "wof:placetype":"venue"
},
  "geometry": {"coordinates":[5.770315,52.253399],"type":"Point"}
}