{
  "type": "Feature",
  "properties": {
    "addr:full":"Brusselselaan 2 Scheveningen Zuid-Holland 2587 AH",
    "addr:housenumber":"2",
    "addr:postcode":"2587 ah",
    "addr:street":"Brusselselaan",
    "iso:country":"NL",
    "sg:address":"Brusselselaan 2",
    "sg:city":"Scheveningen",
    "sg:orig_category":"Fitnesscentra",
    "sg:phone":"+31 70 350 3016",
    "sg:postcode":"2587 AH",
    "sg:province":"Zuid-Holland",
    "wof:name":"High Five Health Club",
    "wof:placetype":"venue"
},
  "geometry": {"coordinates":[4.292938,52.107716],"type":"Point"}
}