{
  "type": "Feature",
  "properties": {
    "addr:full":"Waalresewg 124 Valkenswaard North Brabant 5552 HR",
    "addr:housenumber":"124",
    "addr:postcode":"5552 hr",
    "iso:country":"NL",
    "sg:address":"Waalresewg 124",
    "sg:city":"Valkenswaard",
    "sg:orig_category":"Kappers",
    "sg:phone":"+31 40 201 5571",
    "sg:postcode":"5552 HR",
    "sg:province":"North Brabant",
    "wof:name":"Hairline",
    "wof:placetype":"venue"
},
  "geometry": {"coordinates":[5.452026844,51.3569374084],"type":"Point"}
}