{
  "type": "Feature",
  "properties": {
    "addr:full":"V Echtenskan Nz 143A Klazienaveen Drenthe 7891 AH",
    "addr:housenumber":"143a",
    "addr:postcode":"7891 ah",
    "addr:street":"Nz",
    "iso:country":"NL",
    "sg:address":"V Echtenskan Nz 143A",
    "sg:city":"Klazienaveen",
    "sg:orig_category":"Wolartikelen En Breiwol",
    "sg:phone":"+31 591 317 990",
    "sg:postcode":"7891 AH",
    "sg:province":"Drenthe",
    "wof:name":"Alise",
    "wof:placetype":"venue"
},
  "geometry": {"coordinates":[6.988506794,52.7249908447],"type":"Point"}
}