{
  "type": "Feature",
  "properties": {
    "iso:country":"NL",
    "sg:address":"Baron Van Nagellstraat 158",
    "sg:city":"Barneveld",
    "sg:orig_category":"Personenvervoer Zonder Dienstregeling",
    "sg:phone":"+31 342 420 102",
    "sg:postcode":"3771 LL",
    "sg:province":"Gelderland",
    "wof:name":"Autobedrijf Van Delen En Zoon Bv",
    "wof:placetype":"venue"
},
  "geometry": {"coordinates":[5.599183,52.164135],"type":"Point"}
}