{
  "type": "Feature",
  "properties": {
    "addr:full":"Weltertuijnstraat 44 Heerlen Limburg 6419 CV",
    "addr:housenumber":"44",
    "addr:postcode":"6419 cv",
    "addr:street":"Weltertuijnstraat",
    "iso:country":"NL",
    "sg:address":"Weltertuijnstraat 44",
    "sg:city":"Heerlen",
    "sg:orig_category":"Overheidsdiensten",
    "sg:phone":"+31 45 571 4386",
    "sg:postcode":"6419 CV",
    "sg:province":"Limburg",
    "wof:name":"Gemeenschapshuis",
    "wof:placetype":"venue"
},
  "geometry": {"coordinates":[5.9679141045,50.8759040833],"type":"Point"}
}