{
  "type": "Feature",
  "properties": {
    "iso:country":"NL",
    "sg:address":"Leusderwg 6",
    "sg:city":"Amersfoort",
    "sg:orig_category":"Bloemen En Planten - Decoratie",
    "sg:phone":"+31 33 445 1621",
    "sg:postcode":"3817 KA",
    "sg:province":"Utrecht",
    "wof:name":"Blauwe Regen, De",
    "wof:placetype":"venue"
},
  "geometry": {"coordinates":[5.384556,52.149673],"type":"Point"}
}