{
  "type": "Feature",
  "properties": {
    "addr:full":"Groningensingel 955 Arnhem Gelderland 6835 GL",
    "addr:housenumber":"955",
    "addr:postcode":"6835 gl",
    "addr:street":"Groningensingel",
    "iso:country":"NL",
    "sg:address":"Groningensingel 955",
    "sg:city":"Arnhem",
    "sg:orig_category":"Bloemen And Planten",
    "sg:phone":"+31 26 321 2418",
    "sg:postcode":"6835 GL",
    "sg:province":"Gelderland",
    "wof:name":"Jan Lehmann Bloemen En Planten Vof",
    "wof:placetype":"venue"
},
  "geometry": {"coordinates":[5.905591,51.952591],"type":"Point"}
}