{
  "type": "Feature",
  "properties": {
    "iso:country":"NL",
    "sg:address":"Burgemeester Van Hooffln 75",
    "sg:city":"Veldhoven",
    "sg:classifiers":[
        {
            "category":"Communications",
            "subcategory":"Television Station",
            "type":"Services"
        }
    ],
    "sg:phone":"+31 40 254 4277",
    "sg:postcode":"5503 BK",
    "sg:province":"North Brabant",
    "sg:tags":[
        "video",
        "audio",
        "verhuur"
    ],
    "wof:name":"Bakker Videotheken Deurne Veldhoven",
    "wof:placetype":"venue"
},
  "geometry": {"coordinates":[5.407642,51.413116],"type":"Point"}
}