{
  "type": "Feature",
  "properties": {
    "addr:full":"Logtenbergwg 13 Vaassen Gelderland 8171 PA",
    "addr:housenumber":"13",
    "addr:postcode":"8171",
    "addr:street":"Logtenbergwg;Gelderland",
    "iso:country":"NL",
    "sg:address":"Logtenbergwg 13",
    "sg:city":"Vaassen",
    "sg:orig_category":"Machinehandel",
    "sg:phone":"+31 578 574 925",
    "sg:postcode":"8171 PA",
    "sg:province":"Gelderland",
    "wof:name":"Rodijk",
    "wof:placetype":"venue"
},
  "geometry": {"coordinates":[5.981646,52.298302],"type":"Point"}
}