{
  "type": "Feature",
  "properties": {
    "addr:full":"Dillenburgstr 28 Eindhoven North Brabant 5652 AP",
    "addr:housenumber":"28",
    "addr:postcode":"5652 ap",
    "addr:street":"Dillenburgstr",
    "iso:country":"NL",
    "sg:address":"Dillenburgstr 28",
    "sg:city":"Eindhoven",
    "sg:orig_category":"Verhuizingen",
    "sg:phone":"+31 40 251 7403",
    "sg:postcode":"5652 AP",
    "sg:province":"North Brabant",
    "wof:name":"Vroonhoven, J Van",
    "wof:placetype":"venue"
},
  "geometry": {"coordinates":[5.434112,51.425526],"type":"Point"}
}