{
  "type": "Feature",
  "properties": {
    "addr:full":"Noorder Markweg 1 Loerbeek Gelderland 7036 AN",
    "addr:housenumber":"1",
    "addr:postcode":"7036 an",
    "addr:street":"Noorder Markweg;Gelderland",
    "iso:country":"NL",
    "sg:address":"Noorder Markweg 1",
    "sg:city":"Loerbeek",
    "sg:orig_category":"Meubelreparatie And -Restauratie",
    "sg:phone":"+31 316 531 147",
    "sg:postcode":"7036 AN",
    "sg:province":"Gelderland",
    "wof:name":"Sinan Meubelfabriek",
    "wof:placetype":"venue"
},
  "geometry": {"coordinates":[6.191861,51.923649],"type":"Point"}
}