{
  "type": "Feature",
  "properties": {
    "addr:full":"Prins Hendrikkade 12 Zaandam Noord-Holland 1501 AB",
    "addr:housenumber":"12",
    "addr:postcode":"1501 ab",
    "addr:street":"Prins Hendrikkade",
    "iso:country":"NL",
    "sg:address":"Prins Hendrikkade 12",
    "sg:city":"Zaandam",
    "sg:orig_category":"Marktonderzoekbureaus",
    "sg:phone":"+31 75 616 9611",
    "sg:postcode":"1501 AB",
    "sg:province":"Noord-Holland",
    "wof:name":"Saffier",
    "wof:placetype":"venue"
},
  "geometry": {"coordinates":[4.828914,52.437374],"type":"Point"}
}