{
  "type": "Feature",
  "properties": {
    "addr:full":"Industrieweg 30 Middenmeer Noord-Holland 1775 PV",
    "addr:housenumber":"30",
    "addr:postcode":"1775 pv",
    "addr:street":"Industrieweg",
    "iso:country":"NL",
    "sg:address":"Industrieweg 30",
    "sg:city":"Middenmeer",
    "sg:orig_category":"Huishoudapparatuur, Televisies And Radio'S",
    "sg:phone":"+31 227 502 332",
    "sg:postcode":"1775 PV",
    "sg:province":"Noord-Holland",
    "wof:name":"P.K.F. Satellite Ltd.",
    "wof:placetype":"venue"
},
  "geometry": {"coordinates":[4.995976,52.81702],"type":"Point"}
}