{
  "type": "Feature",
  "properties": {
    "addr:full":"Breezyde 29 Nieuwland Zuid-Holland 4243 JN",
    "addr:housenumber":"29",
    "addr:postcode":"4243 jn",
    "addr:street":"Breezyde",
    "iso:country":"NL",
    "sg:address":"Breezyde 29",
    "sg:city":"Nieuwland",
    "sg:orig_category":"Kaas",
    "sg:phone":"+31 183 561 278",
    "sg:postcode":"4243 JN",
    "sg:province":"Zuid-Holland",
    "wof:name":"Hee, M Van Der",
    "wof:placetype":"venue"
},
  "geometry": {"coordinates":[5.0139279366,51.9019126892],"type":"Point"}
}