{
  "type": "Feature",
  "properties": {
    "iso:country":"NL",
    "sg:address":"Rotterdamsewg 107",
    "sg:city":"Delft",
    "sg:orig_category":"Projectontwikkeling",
    "sg:phone":"+31 15 257 6420",
    "sg:postcode":"2628 AK",
    "sg:province":"Zuid-Holland",
    "wof:name":"Transblue",
    "wof:placetype":"venue"
},
  "geometry": {"coordinates":[4.365321,52.003643],"type":"Point"}
}