{
  "type": "Feature",
  "properties": {
    "iso:country":"NL",
    "sg:address":"Grotestraat 278",
    "sg:city":"Drunen",
    "sg:orig_category":"Verlichting And Huishoudartikelen",
    "sg:phone":"+31 416 378 469",
    "sg:postcode":"5151 BS",
    "sg:province":"Noord-Brabant",
    "wof:name":"Willem Kampen Tapijten",
    "wof:placetype":"venue"
},
  "geometry": {"coordinates":[5.145254,51.68676],"type":"Point"}
}