{
  "type": "Feature",
  "properties": {
    "addr:full":"Vuurplaat 393 Rotterdam New York 3071 AR",
    "addr:housenumber":"393;3071",
    "addr:street":"Vuurplaat",
    "iso:country":"NL",
    "sg:address":"Vuurplaat 393",
    "sg:city":"Rotterdam",
    "sg:orig_category":"Makelaars En Adviseurs Verzekeringen",
    "sg:phone":"+31 10 419 8077",
    "sg:postcode":"3071 AR",
    "sg:province":"New York",
    "wof:name":"Weijers, N T",
    "wof:placetype":"venue"
},
  "geometry": {"coordinates":[-73.97154999999999,42.786839],"type":"Point"}
}