{
  "type": "Feature",
  "properties": {
    "addr:full":"Hekven 13 Breda Noord-Brabant 4824 AD",
    "addr:housenumber":"13",
    "addr:postcode":"4824 ad",
    "addr:street":"Hekven",
    "iso:country":"NL",
    "sg:address":"Hekven 13",
    "sg:city":"Breda",
    "sg:orig_category":"Geluidsopnamestudio'S",
    "sg:phone":"+31 76 541 5733",
    "sg:postcode":"4824 AD",
    "sg:province":"Noord-Brabant",
    "sg:website":"http://www.muziekmaken.nl",
    "wof:name":"Boom! Music, The",
    "wof:placetype":"venue"
},
  "geometry": {"coordinates":[4.75637,51.604256],"type":"Point"}
}