{
  "type": "Feature",
  "properties": {
    "iso:country":"NL",
    "sg:address":"Lohrpad 2",
    "sg:city":"Voorst Gem Gendringen",
    "sg:orig_category":"Loodgieterswerk, Verwarming And Sanitaire Installaties",
    "sg:phone":"+31 315 631 697",
    "sg:postcode":"7083 AX",
    "sg:province":"Gelderland",
    "wof:name":"J.J.M. Schieven",
    "wof:placetype":"venue"
},
  "geometry": {"coordinates":[6.411339,51.872978],"type":"Point"}
}