{
  "type": "Feature",
  "properties": {
    "iso:country":"NL",
    "sg:address":"Ambachtswg 56",
    "sg:city":"Utrecht",
    "sg:orig_category":"Wegenbouw",
    "sg:phone":"+31 30 214 2170",
    "sg:postcode":"3542 DH",
    "sg:province":"Utrecht",
    "wof:name":"Vermeer Bv",
    "wof:placetype":"venue"
},
  "geometry": {"coordinates":[5.0467839241,52.1227416992],"type":"Point"}
}