{
  "type": "Feature",
  "properties": {
    "addr:full":"Burgerhoutsestr 22 Roosendaal Noord-Brabant 4701 EM",
    "addr:housenumber":"22",
    "addr:postcode":"4701 em",
    "addr:street":"Burgerhoutsestr",
    "iso:country":"NL",
    "sg:address":"Burgerhoutsestr 22",
    "sg:city":"Roosendaal",
    "sg:orig_category":"Accountants - Administratie- Consulenten En -Kantoren",
    "sg:phone":"+31 165 543 747",
    "sg:postcode":"4701 EM",
    "sg:province":"Noord-Brabant",
    "wof:name":"Horians",
    "wof:placetype":"venue"
},
  "geometry": {"coordinates":[4.463297,51.530251],"type":"Point"}
}