{
  "type": "Feature",
  "properties": {
    "addr:full":"Van Spilbergenstraat 14 Hoek Van Holland Zuid-Holland 3151 BZ",
    "addr:housenumber":"14",
    "addr:postcode":"3151 bz",
    "addr:street":"Van Spilbergenstraat",
    "iso:country":"NL",
    "sg:address":"Van Spilbergenstraat 14",
    "sg:city":"Hoek Van Holland",
    "sg:orig_category":"Kinderopvang Behalve Thuis",
    "sg:phone":"+31 174 384 634",
    "sg:postcode":"3151 BZ",
    "sg:province":"Zuid-Holland",
    "wof:name":"Kinderdagverblijf De Duinpieper",
    "wof:placetype":"venue"
},
  "geometry": {"coordinates":[4.132843,51.980957],"type":"Point"}
}