{
  "type": "Feature",
  "properties": {
    "addr:full":"Julianastr 2 Stramproy Limburg 6039 AJ",
    "addr:housenumber":"2",
    "addr:postcode":"6039 aj",
    "addr:street":"Julianastr",
    "iso:country":"NL",
    "sg:address":"Julianastr 2",
    "sg:city":"Stramproy",
    "sg:orig_category":"Zalenverhuur",
    "sg:phone":"+31 495 561 630",
    "sg:postcode":"6039 AJ",
    "sg:province":"Limburg",
    "wof:name":"Luifel, De",
    "wof:placetype":"venue"
},
  "geometry": {"coordinates":[5.72304,51.19426],"type":"Point"}
}