{
  "type": "Feature",
  "properties": {
    "addr:full":"Burg Brinkmanhof 2 Driebruggen Zuid-Holland 3465 KR",
    "addr:housenumber":"2",
    "addr:postcode":"3465 kr",
    "addr:street":"Burg Brinkmanhof",
    "iso:country":"NL",
    "sg:address":"Burg Brinkmanhof 2",
    "sg:city":"Driebruggen",
    "sg:orig_category":"Ziekenvervoer",
    "sg:phone":"+31 348 501 621",
    "sg:postcode":"3465 KR",
    "sg:province":"Zuid-Holland",
    "wof:name":"Boerefijn, W",
    "wof:placetype":"venue"
},
  "geometry": {"coordinates":[4.804542,52.045109],"type":"Point"}
}