{
  "type": "Feature",
  "properties": {
    "addr:full":"Grevenswg 9A Doornspyk Gelderland 8085 PZ",
    "addr:housenumber":"9a",
    "addr:postcode":"8085 pz",
    "addr:street":"Grevenswg;Gelderland",
    "iso:country":"NL",
    "sg:address":"Grevenswg 9A",
    "sg:city":"Doornspyk",
    "sg:orig_category":"Adviesbureaus Bedrijfsorganisatie",
    "sg:phone":"+31 525 662 059",
    "sg:postcode":"8085 PZ",
    "sg:province":"Gelderland",
    "wof:name":"Ich Bv",
    "wof:placetype":"venue"
},
  "geometry": {"coordinates":[5.828338,52.410259],"type":"Point"}
}