{
  "type": "Feature",
  "properties": {
    "addr:full":"V Galenstr 16 Bergeyk North Brabant 5571 BN",
    "addr:housenumber":"16",
    "addr:postcode":"5571 bn",
    "addr:street":"Bergeyk North",
    "iso:country":"NL",
    "sg:address":"V Galenstr 16",
    "sg:city":"Bergeyk",
    "sg:orig_category":"Adviesbureaus Bouwkunde",
    "sg:phone":"+31 497 575 927",
    "sg:postcode":"5571 BN",
    "sg:province":"North Brabant",
    "wof:name":"Zweers, D J K",
    "wof:placetype":"venue"
},
  "geometry": {"coordinates":[5.360135,51.323326],"type":"Point"}
}