{
  "type": "Feature",
  "properties": {
    "addr:full":"Noord Voorstraat 29 'S Gravendeel South Holland 3295 BL",
    "addr:housenumber":"29",
    "addr:postcode":"3295 bl",
    "addr:street":"Noord Voorstraat;' S Gravendeel",
    "iso:country":"NL",
    "sg:address":"Noord Voorstraat 29",
    "sg:city":"'S Gravendeel",
    "sg:orig_category":"Werving And Selectie Van Tijdelijk Personeel And Uitzendkantoren",
    "sg:phone":"+31 78 673 6600",
    "sg:postcode":"3295 BL",
    "sg:province":"South Holland",
    "wof:name":"Randstad",
    "wof:placetype":"venue"
},
  "geometry": {"coordinates":[4.6175589561,51.7801475525],"type":"Point"}
}