{
  "type": "Feature",
  "properties": {
    "addr:full":"Hoeverveldweg 1 Schinnen Limburg 6365 CZ",
    "addr:housenumber":"1",
    "addr:postcode":"6365",
    "addr:street":"Hoeverveldweg",
    "iso:country":"NL",
    "sg:address":"Hoeverveldweg 1",
    "sg:city":"Schinnen",
    "sg:orig_category":"Goederenvervoer Over De Weg",
    "sg:phone":"+31 46 443 2775",
    "sg:postcode":"6365 CZ",
    "sg:province":"Limburg",
    "wof:name":"Transportbedrijf Fa. Jongen",
    "wof:placetype":"venue"
},
  "geometry": {"coordinates":[5.879416,50.938171],"type":"Point"}
}