{
  "type": "Feature",
  "properties": {
    "iso:country":"NL",
    "sg:address":"Lunenburg 11",
    "sg:city":"Veenendaal",
    "sg:orig_category":"Adviesbureaus Bedrijfsorganisatie",
    "sg:phone":"+31 318 548 735",
    "sg:postcode":"3904 JN",
    "sg:province":"Utrecht",
    "wof:name":"Lsi Bv",
    "wof:placetype":"venue"
},
  "geometry": {"coordinates":[5.540837,52.0116],"type":"Point"}
}