{
  "type": "Feature",
  "properties": {
    "iso:country":"NL",
    "sg:address":"Kanaalstraat 40",
    "sg:city":"Rijnsburg",
    "sg:orig_category":"Bloemen And Planten Gh",
    "sg:phone":"+31 71 402 0170",
    "sg:postcode":"2231 KD",
    "sg:province":"Zuid-Holland",
    "wof:name":"K Van Klaveren",
    "wof:placetype":"venue"
},
  "geometry": {"coordinates":[4.438997,52.194462],"type":"Point"}
}