{
  "type": "Feature",
  "properties": {
    "addr:full":"Terraswg 60 Santpoort Noord Noord-Holland 2071 BE",
    "addr:housenumber":"60",
    "addr:postcode":"2071",
    "addr:street":"Terraswg",
    "iso:country":"NL",
    "sg:address":"Terraswg 60",
    "sg:city":"Santpoort Noord",
    "sg:orig_category":"Adviesbureaus Bedrijfsorganisatie",
    "sg:phone":"+31 23 537 7204",
    "sg:postcode":"2071 BE",
    "sg:province":"Noord-Holland",
    "wof:name":"Bmvo Bv",
    "wof:placetype":"venue"
},
  "geometry": {"coordinates":[-121.95871,39.780125],"type":"Point"}
}