{
  "type": "Feature",
  "properties": {
    "addr:full":"De Zwaaikom 8 Veendam Groningen 9641 KV",
    "addr:housenumber":"8",
    "addr:postcode":"9641 kv",
    "addr:street":"De Zwaaikom",
    "iso:country":"NL",
    "sg:address":"De Zwaaikom 8",
    "sg:city":"Veendam",
    "sg:orig_category":"Kantoor- En Bedrijfsmeubelen - Fabrieken En Groothandel",
    "sg:phone":"+31 598 632 224",
    "sg:postcode":"9641 KV",
    "sg:province":"Groningen",
    "sg:website":"http://www.trilogy.nl",
    "wof:name":"Triumph",
    "wof:placetype":"venue"
},
  "geometry": {"coordinates":[6.8948431015,53.1028518677],"type":"Point"}
}