{
  "type": "Feature",
  "properties": {
    "addr:full":"Nieuwstr 3C Maassluis Zuid-Holland 3141 AA",
    "addr:housenumber":"3c",
    "addr:postcode":"3141 aa",
    "addr:street":"Nieuwstr",
    "iso:country":"NL",
    "sg:address":"Nieuwstr 3C",
    "sg:city":"Maassluis",
    "sg:orig_category":"Kinderkleding",
    "sg:phone":"+31 10 592 3497",
    "sg:postcode":"3141 AA",
    "sg:province":"Zuid-Holland",
    "wof:name":"Funny Kiddy Store",
    "wof:placetype":"venue"
},
  "geometry": {"coordinates":[4.254383,51.921574],"type":"Point"}
}