{
  "type": "Feature",
  "properties": {
    "iso:country":"NL",
    "sg:address":"Mient 16",
    "sg:city":"Alkmaar",
    "sg:orig_category":"Fietsen En Bromfietsen",
    "sg:phone":"+31 72 511 2216",
    "sg:postcode":"1811 NC",
    "sg:province":"Noord-Holland",
    "wof:name":"Nl Zaak",
    "wof:placetype":"venue"
},
  "geometry": {"coordinates":[4.749829,52.630775],"type":"Point"}
}