{
  "type": "Feature",
  "properties": {
    "addr:full":"Mient 16 Alkmaar Noord-Holland 1811 NC",
    "addr:housenumber":"16",
    "addr:postcode":"1811 nc",
    "addr:street":"Mient",
    "iso:country":"NL",
    "sg:address":"Mient 16",
    "sg:city":"Alkmaar",
    "sg:orig_category":"Fietsen En Bromfietsen",
    "sg:phone":"+31 72 511 2216",
    "sg:postcode":"1811 NC",
    "sg:province":"Noord-Holland",
    "wof:name":"Nl Zaak",
    "wof:placetype":"venue"
},
  "geometry": {"coordinates":[4.749829,52.630775],"type":"Point"}
}