{
  "type": "Feature",
  "properties": {
    "addr:full":"Avinkwg 2 Haarlo Gelderland 7273 PT",
    "addr:housenumber":"2",
    "addr:postcode":"7273",
    "addr:street":"Avinkwg;Gelderland;Pt",
    "iso:country":"NL",
    "sg:address":"Avinkwg 2",
    "sg:city":"Haarlo",
    "sg:orig_category":"Waterschappen",
    "sg:phone":"+31 545 261 512",
    "sg:postcode":"7273 PT",
    "sg:province":"Gelderland",
    "wof:name":"Waterschap Rijn En Ijssel",
    "wof:placetype":"venue"
},
  "geometry": {"coordinates":[6.5914011002,52.1179237366],"type":"Point"}
}