{
  "type": "Feature",
  "properties": {
    "iso:country":"NL",
    "sg:address":"Grevelingen 46",
    "sg:city":"Tilburg",
    "sg:orig_category":"Adviesbureaus Bedrijfsorganisatie",
    "sg:phone":"+31 13 590 0867",
    "sg:postcode":"5032 TG",
    "sg:province":"Noord-Brabant",
    "wof:name":"Kamphuis Bv",
    "wof:placetype":"venue"
},
  "geometry": {"coordinates":[5.046851,51.552685],"type":"Point"}
}