{
  "type": "Feature",
  "properties": {
    "addr:full":"Stadsbrink 3/C Wageningen Gelderland 6707 AA",
    "addr:housenumber":"3 / c",
    "addr:postcode":"6707 aa",
    "addr:street":"Stadsbrink;Gelderland",
    "iso:country":"NL",
    "sg:address":"Stadsbrink 3/C",
    "sg:city":"Wageningen",
    "sg:orig_category":"Notarissen En Notariskantoren",
    "sg:phone":"+31 317 427 000",
    "sg:postcode":"6707 AA",
    "sg:province":"Gelderland",
    "wof:name":"Hoek, Mr D G",
    "wof:placetype":"venue"
},
  "geometry": {"coordinates":[5.666448,51.969791],"type":"Point"}
}