{
  "type": "Feature",
  "properties": {
    "addr:full":"Molendwarsstraat 47 Apeldoorn Gelderland 7311 MX",
    "addr:housenumber":"47",
    "addr:postcode":"7311 mx",
    "addr:street":"Molendwarsstraat;Gelderland",
    "iso:country":"NL",
    "sg:address":"Molendwarsstraat 47",
    "sg:city":"Apeldoorn",
    "sg:orig_category":"Erotische Etablissementen",
    "sg:phone":"+31 55 579 0338",
    "sg:postcode":"7311 MX",
    "sg:province":"Gelderland",
    "wof:name":"Jan Bik",
    "wof:placetype":"venue"
},
  "geometry": {"coordinates":[5.970438,52.211704],"type":"Point"}
}