{
  "type": "Feature",
  "properties": {
    "iso:country":"NL",
    "sg:address":"Overtoom 2",
    "sg:city":"Westzaan",
    "sg:orig_category":"Huizensloop And Bouwrijp Maken",
    "sg:phone":"+31 75 616 4223",
    "sg:postcode":"1551 PA",
    "sg:province":"Noord-Holland",
    "wof:name":"K. Zwikker",
    "wof:placetype":"venue"
},
  "geometry": {"coordinates":[4.790086,52.431591],"type":"Point"}
}