{
  "type": "Feature",
  "properties": {
    "addr:full":"Drooghe Bol 1035 Den Helder Noord-Holland 1788 VB",
    "addr:housenumber":"1035",
    "addr:postcode":"1788 vb",
    "addr:street":"Drooghe Bol",
    "iso:country":"NL",
    "sg:address":"Drooghe Bol 1035",
    "sg:city":"Den Helder",
    "sg:orig_category":"Postkantoren",
    "sg:phone":"+31 223 641 210",
    "sg:postcode":"1788 VB",
    "sg:province":"Noord-Holland",
    "sg:website":"http://www.postkantoor.nl",
    "wof:name":"Postkantoor",
    "wof:placetype":"venue"
},
  "geometry": {"coordinates":[4.740369,52.884804],"type":"Point"}
}