{
  "type": "Feature",
  "properties": {
    "addr:full":"Standerdmolen 21 Harmelen Utrecht 3481 AE",
    "addr:housenumber":"21",
    "addr:postcode":"3481 ae",
    "addr:street":"Standerdmolen",
    "iso:country":"NL",
    "sg:address":"Standerdmolen 21",
    "sg:city":"Harmelen",
    "sg:orig_category":"Marktonderzoekbureaus",
    "sg:phone":"+31 348 442 016",
    "sg:postcode":"3481 AE",
    "sg:province":"Utrecht",
    "wof:name":"Comm Adviesbureau Positioning Management",
    "wof:placetype":"venue"
},
  "geometry": {"coordinates":[4.967363,52.088318],"type":"Point"}
}