{
  "type": "Feature",
  "properties": {
    "addr:full":"Kerkebuurt 160 Berkhout North Holland 1647 ME",
    "addr:housenumber":"160",
    "addr:postcode":"1647 me",
    "addr:street":"Kerkebuurt",
    "iso:country":"NL",
    "sg:address":"Kerkebuurt 160",
    "sg:city":"Berkhout",
    "sg:orig_category":"Kappers",
    "sg:phone":"+31 229 551 485",
    "sg:postcode":"1647 ME",
    "sg:province":"North Holland",
    "wof:name":"Kapsalon Boulangier",
    "wof:placetype":"venue"
},
  "geometry": {"coordinates":[4.9979782104,52.6402626038],"type":"Point"}
}