{
  "type": "Feature",
  "properties": {
    "addr:full":"Westkanaalwg 72 Ter Aar South Holland 2461 EH",
    "addr:housenumber":"72",
    "addr:postcode":"2461 eh",
    "addr:street":"Westkanaalwg",
    "iso:country":"NL",
    "sg:address":"Westkanaalwg 72",
    "sg:city":"Ter Aar",
    "sg:orig_category":"Touringcars",
    "sg:phone":"+31 172 602 333",
    "sg:postcode":"2461 EH",
    "sg:province":"South Holland",
    "wof:name":"Langhout",
    "wof:placetype":"venue"
},
  "geometry": {"coordinates":[4.71474,52.174515],"type":"Point"}
}