{
  "type": "Feature",
  "properties": {
    "addr:full":"Mitchamplein 1A Hengelo Ov Overijssel 7556 SC",
    "addr:housenumber":"1a",
    "addr:postcode":"7556 sc",
    "addr:street":"Mitchamplein;Ov",
    "iso:country":"NL",
    "sg:address":"Mitchamplein 1A",
    "sg:city":"Hengelo Ov",
    "sg:orig_category":"Psychologen",
    "sg:phone":"+31 74 250 9181",
    "sg:postcode":"7556 SC",
    "sg:province":"Overijssel",
    "sg:website":"http://www.rid.nl",
    "wof:name":"Regionaal Instituut Voor Dyslexie",
    "wof:placetype":"venue"
},
  "geometry": {"coordinates":[6.786474,52.266548],"type":"Point"}
}