{
  "type": "Feature",
  "properties": {
    "iso:country":"NL",
    "sg:address":"17 Oktoberplein 6",
    "sg:city":"Ijzendijke",
    "sg:orig_category":"Kinderopvang Behalve Thuis",
    "sg:phone":"+31 117 302 790",
    "sg:postcode":"4515 CP",
    "sg:province":"Zeeland",
    "wof:name":"Het Gabbertje",
    "wof:placetype":"venue"
},
  "geometry": {"coordinates":[3.618829,51.318932],"type":"Point"}
}