{
  "type": "Feature",
  "properties": {
    "addr:full":"Ottengas 29 Nijmegen Gelderland 6511 TS",
    "addr:housenumber":"29",
    "addr:postcode":"6511 ts",
    "addr:street":"Ottengas;Gelderland",
    "iso:country":"NL",
    "sg:address":"Ottengas 29",
    "sg:city":"Nijmegen",
    "sg:orig_category":"Verenigingen En Stichtingen",
    "sg:phone":"+31 24 322 3434",
    "sg:postcode":"6511 TS",
    "sg:province":"Gelderland",
    "wof:name":"Nutopia",
    "wof:placetype":"venue"
},
  "geometry": {"coordinates":[5.867249,51.847935],"type":"Point"}
}