{
  "type": "Feature",
  "properties": {
    "addr:full":"Nieuwstr 87 Deventer Overijssel 7411 LK",
    "addr:housenumber":"87",
    "addr:postcode":"7411 lk",
    "addr:street":"Nieuwstr",
    "iso:country":"NL",
    "sg:address":"Nieuwstr 87",
    "sg:city":"Deventer",
    "sg:orig_category":"Woninginrichting",
    "sg:phone":"+31 570 612 564",
    "sg:postcode":"7411 LK",
    "sg:province":"Overijssel",
    "wof:name":"Hardon",
    "wof:placetype":"venue"
},
  "geometry": {"coordinates":[6.1598992348,52.251033783],"type":"Point"}
}