{
  "type": "Feature",
  "properties": {
    "addr:full":"Riederln 91 Rotterdam Zuid-Holland 3074 CE",
    "addr:housenumber":"91",
    "addr:postcode":"3074 ce",
    "addr:street":"Riederln",
    "iso:country":"NL",
    "sg:address":"Riederln 91",
    "sg:city":"Rotterdam",
    "sg:orig_category":"Dumpgoederen",
    "sg:phone":"+31 10 492 0060",
    "sg:postcode":"3074 CE",
    "sg:province":"Zuid-Holland",
    "wof:name":"Dumpshop Zuid",
    "wof:placetype":"venue"
},
  "geometry": {"coordinates":[4.51149,51.89608],"type":"Point"}
}