{
  "type": "Feature",
  "properties": {
    "iso:country":"NL",
    "sg:address":"Baangr 75",
    "sg:city":"Alkmaar",
    "sg:orig_category":"Fotoreportages",
    "sg:phone":"+31 72 511 2173",
    "sg:postcode":"1811 DR",
    "sg:province":"Noord-Holland",
    "wof:name":"Beemster, Erwin",
    "wof:placetype":"venue"
},
  "geometry": {"coordinates":[4.74758,52.62804],"type":"Point"}
}