{
  "type": "Feature",
  "properties": {
    "addr:full":"Vestaplein 48 Wormerveer North Holland 1521 AN",
    "addr:housenumber":"48",
    "addr:postcode":"1521 an",
    "addr:street":"Vestaplein",
    "iso:country":"NL",
    "sg:address":"Vestaplein 48",
    "sg:city":"Wormerveer",
    "sg:orig_category":"Loodgieterswerk, Verwarming And Sanitaire Installaties",
    "sg:phone":"+31 6 55812798",
    "sg:postcode":"1521 AN",
    "sg:province":"North Holland",
    "wof:name":"Allround",
    "wof:placetype":"venue"
},
  "geometry": {"coordinates":[4.800788,52.486897],"type":"Point"}
}