{
  "type": "Feature",
  "properties": {
    "addr:full":"Amsterdamseweg 40 Ede Gld Gelderland 6712 GJ",
    "addr:housenumber":"40",
    "addr:postcode":"6712 gj",
    "addr:street":"Amsterdamseweg;Gld Gelderland",
    "iso:country":"NL",
    "sg:address":"Amsterdamseweg 40",
    "sg:city":"Ede Gld",
    "sg:orig_category":"Vertaal- And Tolkenbureaus",
    "sg:phone":"+31 318 693 140",
    "sg:postcode":"6712 GJ",
    "sg:province":"Gelderland",
    "wof:name":"M.G. Van Andel - Boswijk",
    "wof:placetype":"venue"
},
  "geometry": {"coordinates":[5.664847,52.04961],"type":"Point"}
}