{
  "type": "Feature",
  "properties": {
    "iso:country":"NL",
    "sg:address":"Van Der Lelijstraat 20",
    "sg:city":"Delft",
    "sg:classifiers":[
        {
            "category":"Education",
            "subcategory":"Preschool",
            "type":"Public Place"
        }
    ],
    "sg:phone":"+31 15 213 4609",
    "sg:postcode":"2614 EM",
    "sg:province":"Zuid-Holland",
    "sg:tags":[
        "kleuteronderwijs",
        "basis-"
    ],
    "wof:name":"Openbare Basisschool De Omnibus",
    "wof:placetype":"venue"
},
  "geometry": {"coordinates":[4.337483,52.010525],"type":"Point"}
}