{
  "type": "Feature",
  "properties": {
    "addr:full":"Crooswyksesngl 2A Rotterdam Zuid-Holland 3034 CE",
    "addr:housenumber":"2a",
    "addr:postcode":"3034 ce",
    "addr:street":"Crooswyksesngl",
    "iso:country":"NL",
    "sg:address":"Crooswyksesngl 2A",
    "sg:city":"Rotterdam",
    "sg:orig_category":"Postkantoren",
    "sg:phone":"+31 10 413 6689",
    "sg:postcode":"3034 CE",
    "sg:province":"Zuid-Holland",
    "sg:website":"http://www.postkantoor.nl",
    "wof:name":"Postkantoor",
    "wof:placetype":"venue"
},
  "geometry": {"coordinates":[4.49123,51.93848],"type":"Point"}
}