{
  "type": "Feature",
  "properties": {
    "iso:country":"NL",
    "sg:address":"Ter Borghstr 146",
    "sg:city":"Geldrop",
    "sg:orig_category":"Hek- En Rasterwerken",
    "sg:phone":"+31 40 280 1414",
    "sg:postcode":"5666 RE",
    "sg:province":"Noord-Brabant",
    "wof:name":"Roma",
    "wof:placetype":"venue"
},
  "geometry": {"coordinates":[5.565993,51.425976],"type":"Point"}
}