{
  "type": "Feature",
  "properties": {
    "addr:full":"Kelvinstr 24 Didam Gelderland 6942 RD",
    "addr:housenumber":"24",
    "addr:postcode":"6942",
    "addr:street":"Kelvinstr;Gelderland;Rd",
    "iso:country":"NL",
    "sg:address":"Kelvinstr 24",
    "sg:city":"Didam",
    "sg:orig_category":"Kunststoffen - Fabrieken En Groothandel",
    "sg:phone":"+31 316 526 979",
    "sg:postcode":"6942 RD",
    "sg:province":"Gelderland",
    "wof:name":"Dufor Resins Bv",
    "wof:placetype":"venue"
},
  "geometry": {"coordinates":[6.128348,51.936817],"type":"Point"}
}