{
  "type": "Feature",
  "properties": {
    "addr:full":"Lekdk 106 Ammerstol Zuid-Holland 2865 LE",
    "addr:housenumber":"106",
    "addr:postcode":"2865 le",
    "iso:country":"NL",
    "sg:address":"Lekdk 106",
    "sg:city":"Ammerstol",
    "sg:orig_category":"Accountants - Administratie- Consulenten En -Kantoren",
    "sg:phone":"+31 182 351 146",
    "sg:postcode":"2865 LE",
    "sg:province":"Zuid-Holland",
    "wof:name":"Tak, E",
    "wof:placetype":"venue"
},
  "geometry": {"coordinates":[4.807948,51.925457],"type":"Point"}
}