{
  "type": "Feature",
  "properties": {
    "addr:full":"Catharinastr 47 Wellerlooi Limburg 5856 AS",
    "addr:housenumber":"47",
    "addr:postcode":"5856 as",
    "addr:street":"Catharinastr",
    "iso:country":"NL",
    "sg:address":"Catharinastr 47",
    "sg:city":"Wellerlooi",
    "sg:orig_category":"Scholen Voor Basisonderwijs",
    "sg:phone":"+31 478 501 876",
    "sg:postcode":"5856 AS",
    "sg:province":"Limburg",
    "wof:name":"Catharina Rk",
    "wof:placetype":"venue"
},
  "geometry": {"coordinates":[6.14062,51.536198],"type":"Point"}
}