{
  "type": "Feature",
  "properties": {
    "addr:full":"Sportcentrumln 1 Sittard North Rhine-Westphalia 6136 KX",
    "addr:housenumber":"1",
    "addr:postcode":"6136 kx",
    "addr:street":"Sportcentrumln",
    "iso:country":"NL",
    "sg:address":"Sportcentrumln 1",
    "sg:city":"Sittard",
    "sg:orig_category":"Sportverenigingen En Ontspannings- Verenigingen",
    "sg:phone":"+31 46 452 3693",
    "sg:postcode":"6136 KX",
    "sg:province":"North Rhine-Westphalia",
    "wof:name":"Alpenjagers Handboogschutt, De",
    "wof:placetype":"venue"
},
  "geometry": {"coordinates":[5.881888,51.008259],"type":"Point"}
}