{
  "type": "Feature",
  "properties": {
    "addr:full":"V Galenstr 7 Eindhoven North Brabant 5612 GZ",
    "addr:housenumber":"7",
    "addr:postcode":"5612 gz",
    "addr:street":"Galenstr",
    "iso:country":"NL",
    "sg:address":"V Galenstr 7",
    "sg:city":"Eindhoven",
    "sg:orig_category":"Autorijscholen",
    "sg:phone":"+31 40 243 4862",
    "sg:postcode":"5612 GZ",
    "sg:province":"North Brabant",
    "wof:name":"Dennis, Autorijschool",
    "wof:placetype":"venue"
},
  "geometry": {"coordinates":[5.484105,51.434471],"type":"Point"}
}