{
  "type": "Feature",
  "properties": {
    "addr:full":"Veenslag 3 Veenendaal Utrecht 3905 SH",
    "addr:housenumber":"3",
    "addr:postcode":"3905 sh",
    "addr:street":"Veenslag",
    "iso:country":"NL",
    "sg:address":"Veenslag 3",
    "sg:city":"Veenendaal",
    "sg:classifiers":[
        {
            "category":"Shopping",
            "subcategory":"Gifts & Souvenirs",
            "type":"Retail Goods"
        }
    ],
    "sg:phone":"+31 318 511 136",
    "sg:postcode":"3905 SH",
    "sg:province":"Utrecht",
    "sg:tags":[
        "geschenken"
    ],
    "wof:name":"Vof Geschenkenhuis Ad Quint",
    "wof:placetype":"venue"
},
  "geometry": {"coordinates":[5.532448,52.028534],"type":"Point"}
}