{
  "type": "Feature",
  "properties": {
    "iso:country":"NL",
    "sg:address":"Handelsweg 9",
    "sg:city":"Hapert",
    "sg:orig_category":"Metaalbekleding And -Behandeling",
    "sg:phone":"+31 497 384 215",
    "sg:postcode":"5527 AL",
    "sg:province":"Noord-Brabant",
    "wof:name":"Swabo",
    "wof:placetype":"venue"
},
  "geometry": {"coordinates":[5.275748,51.371941],"type":"Point"}
}