{
  "type": "Feature",
  "properties": {
    "addr:full":"Stadhouderskd 67 Amsterdam Noord-Holland 1072 AD",
    "addr:housenumber":"67",
    "addr:postcode":"1072 ad",
    "addr:street":"Stadhouderskd",
    "iso:country":"NL",
    "sg:address":"Stadhouderskd 67",
    "sg:city":"Amsterdam",
    "sg:orig_category":"Binnenhuisarchitectuur",
    "sg:phone":"+31 20 664 5639",
    "sg:postcode":"1072 AD",
    "sg:province":"Noord-Holland",
    "wof:name":"Coenen, Studio",
    "wof:placetype":"venue"
},
  "geometry": {"coordinates":[4.89067,52.354012],"type":"Point"}
}