{
  "type": "Feature",
  "properties": {
    "addr:full":"Jansstr 31 Haarlem North Holland 2011 RT",
    "addr:housenumber":"31",
    "addr:postcode":"2011 rt",
    "addr:street":"Jansstr",
    "iso:country":"NL",
    "sg:address":"Jansstr 31",
    "sg:city":"Haarlem",
    "sg:orig_category":"Boeken En Tijdschriften",
    "sg:phone":"+31 23 534 0871",
    "sg:postcode":"2011 RT",
    "sg:province":"North Holland",
    "sg:website":"http://www.allaboutart.nl",
    "wof:name":"All About Art",
    "wof:placetype":"venue"
},
  "geometry": {"coordinates":[4.638497,52.383686],"type":"Point"}
}