{
  "type": "Feature",
  "properties": {
    "addr:full":"Morsestraat 1-3 Hoogeveen Drenthe 7903 BK",
    "addr:housenumber":"1-3",
    "addr:postcode":"7903 bk",
    "addr:street":"Morsestraat",
    "iso:country":"NL",
    "sg:address":"Morsestraat 1-3",
    "sg:city":"Hoogeveen",
    "sg:orig_category":"Bedrijfsinventaris Gh",
    "sg:phone":"+31 528 274 899",
    "sg:postcode":"7903 BK",
    "sg:province":"Drenthe",
    "sg:website":"http://www.mirpra.nl",
    "wof:name":"Mirpra",
    "wof:placetype":"venue"
},
  "geometry": {"coordinates":[6.498963,52.734894],"type":"Point"}
}