{
  "type": "Feature",
  "properties": {
    "addr:full":"Zamenhofdreef 19 Utrecht Utrecht 3562 JT",
    "addr:housenumber":"19",
    "addr:postcode":"3562 jt",
    "addr:street":"Zamenhofdreef",
    "iso:country":"NL",
    "sg:address":"Zamenhofdreef 19",
    "sg:city":"Utrecht",
    "sg:classifiers":[
        {
            "category":"Bakery",
            "type":"Food & Drink"
        }
    ],
    "sg:phone":"+31 30 261 0287",
    "sg:postcode":"3562 JT",
    "sg:province":"Utrecht",
    "sg:tags":[
        "brood",
        "banket"
    ],
    "wof:name":"Van Kooten Banket Brood",
    "wof:placetype":"venue"
},
  "geometry": {"coordinates":[5.111948,52.11454],"type":"Point"}
}