{
  "type": "Feature",
  "properties": {
    "addr:full":"Noordeinde 116 Roelofarendsveen Zuid-Holland 2371 CW",
    "addr:housenumber":"116",
    "addr:postcode":"2371 cw",
    "addr:street":"Noordeinde",
    "iso:country":"NL",
    "sg:address":"Noordeinde 116",
    "sg:city":"Roelofarendsveen",
    "sg:orig_category":"Marktonderzoekbureaus",
    "sg:phone":"+31 71 331 2397",
    "sg:postcode":"2371 CW",
    "sg:province":"Zuid-Holland",
    "sg:website":"http://www.testsystems.nl",
    "wof:name":"Test Systems Nederland",
    "wof:placetype":"venue"
},
  "geometry": {"coordinates":[4.629187,52.197502],"type":"Point"}
}