{
  "type": "Feature",
  "properties": {
    "addr:full":"Kruisbessengaard 26 Wyk By Duurstede Utrecht 3962 JK",
    "addr:housenumber":"26",
    "addr:postcode":"duurstede;3962 jk",
    "addr:street":"Kruisbessengaard",
    "iso:country":"NL",
    "sg:address":"Kruisbessengaard 26",
    "sg:city":"Wyk By Duurstede",
    "sg:orig_category":"Administratie- En Boekhoudkantoren",
    "sg:phone":"+31 343 573 800",
    "sg:postcode":"3962 JK",
    "sg:province":"Utrecht",
    "wof:name":"Beekes, F J",
    "wof:placetype":"venue"
},
  "geometry": {"coordinates":[5.345877,51.983673],"type":"Point"}
}