{
  "type": "Feature",
  "properties": {
    "addr:full":"Meginhardweg 35 Arnhem Gelderland 6841 HB",
    "addr:housenumber":"35",
    "addr:postcode":"6841 hb",
    "addr:street":"Meginhardweg",
    "iso:country":"NL",
    "sg:address":"Meginhardweg 35",
    "sg:city":"Arnhem",
    "sg:orig_category":"Architecten",
    "sg:phone":"+31 26 321 5375",
    "sg:postcode":"6841 HB",
    "sg:province":"Gelderland",
    "wof:name":"Adviesburo G. Litjens",
    "wof:placetype":"venue"
},
  "geometry": {"coordinates":[5.874608,51.976341],"type":"Point"}
}