{
  "type": "Feature",
  "properties": {
    "addr:full":"Boschstr 23 Brunssum Limburg 6442 PB",
    "addr:housenumber":"23",
    "addr:postcode":"6442 pb",
    "addr:street":"Boschstr",
    "iso:country":"NL",
    "sg:address":"Boschstr 23",
    "sg:city":"Brunssum",
    "sg:orig_category":"Kunststoffen- Verwerkende Industrie",
    "sg:phone":"+31 45 526 1261",
    "sg:postcode":"6442 PB",
    "sg:province":"Limburg",
    "wof:name":"Curver Bv",
    "wof:placetype":"venue"
},
  "geometry": {"coordinates":[5.992225,50.956131],"type":"Point"}
}