{
  "type": "Feature",
  "properties": {
    "addr:full":"Misericordepln 3 Maastricht Limburg 6211 XK",
    "addr:housenumber":"3",
    "addr:postcode":"6211 xk",
    "addr:street":"Misericordepln",
    "iso:country":"NL",
    "sg:address":"Misericordepln 3",
    "sg:city":"Maastricht",
    "sg:orig_category":"Administratie- En Boekhoudkantoren",
    "sg:phone":"+31 43 321 9802",
    "sg:postcode":"6211 XK",
    "sg:province":"Limburg",
    "wof:name":"Nelissen, J",
    "wof:placetype":"venue"
},
  "geometry": {"coordinates":[5.687024,50.852158],"type":"Point"}
}