{
  "type": "Feature",
  "properties": {
    "addr:full":"Haagwindelaan 33 Oosthuizen Noord-Holland 1474 RC",
    "addr:housenumber":"33",
    "addr:postcode":"1474 rc",
    "addr:street":"Haagwindelaan",
    "iso:country":"NL",
    "sg:address":"Haagwindelaan 33",
    "sg:city":"Oosthuizen",
    "sg:orig_category":"Begrafenisondernemers",
    "sg:phone":"+31 299 403 501",
    "sg:postcode":"1474 RC",
    "sg:province":"Noord-Holland",
    "wof:name":"Uitvaartvereniging De Laatste Eer",
    "wof:placetype":"venue"
},
  "geometry": {"coordinates":[4.996741,52.569866],"type":"Point"}
}