{
  "type": "Feature",
  "properties": {
    "iso:country":"NL",
    "sg:address":"Zytwende 11",
    "sg:city":"Schipluiden",
    "sg:classifiers":[
        {
            "category":"Personal",
            "subcategory":"Nail Salon",
            "type":"Services"
        }
    ],
    "sg:phone":"+31 15 380 7523",
    "sg:postcode":"2636 GX",
    "sg:province":"South Holland",
    "sg:tags":[
        "pedicure"
    ],
    "wof:name":"Jolanda Van Leeuwen",
    "wof:placetype":"venue"
},
  "geometry": {"coordinates":[4.31591,51.97718],"type":"Point"}
}