{
  "type": "Feature",
  "properties": {
    "addr:full":"Singelpassage 10 Assen Drenthe 9401 JC",
    "addr:housenumber":"10",
    "addr:postcode":"9401 jc",
    "addr:street":"Singelpassage",
    "iso:country":"NL",
    "sg:address":"Singelpassage 10",
    "sg:city":"Assen",
    "sg:orig_category":"Kunst And Kunstenaarsbenodigdheden",
    "sg:phone":"+31 592 310 389",
    "sg:postcode":"9401 JC",
    "sg:province":"Drenthe",
    "wof:name":"Lijstenmakerij Magnolia",
    "wof:placetype":"venue"
},
  "geometry": {"coordinates":[6.562749,52.994492],"type":"Point"}
}