{
  "type": "Feature",
  "properties": {
    "addr:full":"Overschiestr 55 Amsterdam North Holland 1062 HN",
    "addr:housenumber":"55",
    "addr:postcode":"1062 hn",
    "addr:street":"Overschiestr",
    "iso:country":"NL",
    "sg:address":"Overschiestr 55",
    "sg:city":"Amsterdam",
    "sg:orig_category":"Juridische Adviseurs",
    "sg:phone":"+31 20 669 2069",
    "sg:postcode":"1062 HN",
    "sg:province":"North Holland",
    "wof:name":"Koelman, Bureau",
    "wof:placetype":"venue"
},
  "geometry": {"coordinates":[4.839681,52.347782],"type":"Point"}
}