{
  "type": "Feature",
  "properties": {
    "iso:country":"NL",
    "sg:address":"Kraaijerdijk 5",
    "sg:city":"Melissant",
    "sg:orig_category":"Verhuur Landbouwmachines",
    "sg:phone":"+31 187 601 408",
    "sg:postcode":"3248 LC",
    "sg:province":"South Holland",
    "wof:name":"R. Kort",
    "wof:placetype":"venue"
},
  "geometry": {"coordinates":[4.088016,51.775871],"type":"Point"}
}