{
  "type": "Feature",
  "properties": {
    "addr:full":"Springwg 91E Utrecht Utrecht 3511 VL",
    "addr:housenumber":"91e",
    "addr:postcode":"3511 vl",
    "addr:street":"Springwg",
    "iso:country":"NL",
    "sg:address":"Springwg 91E",
    "sg:city":"Utrecht",
    "sg:orig_category":"Artiesten/Gezelschappen",
    "sg:phone":"+31 30 230 4090",
    "sg:postcode":"3511 VL",
    "sg:province":"Utrecht",
    "wof:name":"Perfume De Salsa",
    "wof:placetype":"venue"
},
  "geometry": {"coordinates":[5.119937,52.086525],"type":"Point"}
}