{
  "type": "Feature",
  "properties": {
    "iso:country":"NL",
    "sg:address":"Marconistr 10A",
    "sg:city":"Kudelstaart",
    "sg:orig_category":"Kinderopvang",
    "sg:phone":"+31 297 325 320",
    "sg:postcode":"1433 KK",
    "sg:province":"Noord-Holland",
    "wof:name":"Stempel, De",
    "wof:placetype":"venue"
},
  "geometry": {"coordinates":[4.753292,52.231956],"type":"Point"}
}