{
  "type": "Feature",
  "properties": {
    "addr:full":"M J Bultenastr 6 Uithuizen Groningen 9981 JB",
    "addr:housenumber":"6",
    "addr:postcode":"9981 jb",
    "addr:street":"M;Bultenastr",
    "iso:country":"NL",
    "sg:address":"M J Bultenastr 6",
    "sg:city":"Uithuizen",
    "sg:orig_category":"Makelaars En Adviseurs Onroerende Goederen",
    "sg:phone":"+31 595 431 455",
    "sg:postcode":"9981 JB",
    "sg:province":"Groningen",
    "wof:name":"Poort Sienot & Woltjer Vof",
    "wof:placetype":"venue"
},
  "geometry": {"coordinates":[6.672033,53.406368],"type":"Point"}
}