{
  "type": "Feature",
  "properties": {
    "iso:country":"NL",
    "sg:address":"Talmastr 90B",
    "sg:city":"Rotterdam",
    "sg:orig_category":"Koeriersdiensten",
    "sg:phone":"+31 10 467 2524",
    "sg:postcode":"3038 SV",
    "sg:province":"Zuid-Holland",
    "wof:name":"K & L",
    "wof:placetype":"venue"
},
  "geometry": {"coordinates":[4.460883,51.935642],"type":"Point"}
}