{
  "type": "Feature",
  "properties": {
    "addr:full":"Grt Kerkstr 2 Steenbergen Nb North Brabant 4651 BB",
    "addr:housenumber":"2;nb",
    "addr:postcode":"4651 bb",
    "addr:street":"Kerkstr",
    "iso:country":"NL",
    "sg:address":"Grt Kerkstr 2",
    "sg:city":"Steenbergen Nb",
    "sg:orig_category":"Wasmachines En Wasdrogers",
    "sg:phone":"+31 167 563 795",
    "sg:postcode":"4651 BB",
    "sg:province":"North Brabant",
    "sg:website":"http://www.expert.nl",
    "wof:name":"Vliet, Van",
    "wof:placetype":"venue"
},
  "geometry": {"coordinates":[4.3145551682,51.5855941772],"type":"Point"}
}