{
  "type": "Feature",
  "properties": {
    "addr:full":"Molenveld 15 Koog Aan De Zaan Noord-Holland 1541 SJ",
    "addr:housenumber":"15",
    "addr:postcode":"1541",
    "addr:street":"Molenveld",
    "iso:country":"NL",
    "sg:address":"Molenveld 15",
    "sg:city":"Koog Aan De Zaan",
    "sg:orig_category":"Kappers",
    "sg:phone":"+31 75 615 8304",
    "sg:postcode":"1541 SJ",
    "sg:province":"Noord-Holland",
    "wof:name":"Knipsalon, De",
    "wof:placetype":"venue"
},
  "geometry": {"coordinates":[4.800116,52.462971],"type":"Point"}
}