{
  "type": "Feature",
  "properties": {
    "addr:full":"Industrieweg 10 Paterswolde Basel-Landschaft 9765 BL",
    "addr:housenumber":"10",
    "addr:postcode":"9765 bl",
    "addr:street":"Industrieweg",
    "iso:country":"NL",
    "sg:address":"Industrieweg 10",
    "sg:city":"Paterswolde",
    "sg:orig_category":"Kansspelen",
    "sg:phone":"+31 50 309 3532",
    "sg:postcode":"9765 BL",
    "sg:province":"Basel-Landschaft",
    "wof:name":"Cooperatieve Vereniging D.O.A.C. Ua",
    "wof:placetype":"venue"
},
  "geometry": {"coordinates":[7.822450161,47.4510498047],"type":"Point"}
}