{
  "type": "Feature",
  "properties": {
    "iso:country":"NL",
    "sg:address":"1E Hogewg 77",
    "sg:city":"Zeist",
    "sg:orig_category":"Schoenen",
    "sg:phone":"+31 30 692 4127",
    "sg:postcode":"3701 HJ",
    "sg:province":"Utrecht",
    "wof:name":"Bitter Bv",
    "wof:placetype":"venue"
},
  "geometry": {"coordinates":[5.24269,52.084648],"type":"Point"}
}