{
  "type": "Feature",
  "properties": {
    "addr:full":"Kraaienveld 16 Emmen Drenthe 7827 JM",
    "addr:housenumber":"16",
    "addr:postcode":"7827 jm",
    "addr:street":"Kraaienveld",
    "iso:country":"NL",
    "sg:address":"Kraaienveld 16",
    "sg:city":"Emmen",
    "sg:orig_category":"Psychologen",
    "sg:phone":"+31 591 676 114",
    "sg:postcode":"7827 JM",
    "sg:province":"Drenthe",
    "wof:name":"Gritter, G",
    "wof:placetype":"venue"
},
  "geometry": {"coordinates":[6.891756,52.746685],"type":"Point"}
}