{
  "type": "Feature",
  "properties": {
    "addr:full":"Koperstraat 4 Vaals Limburg 6291 AJ",
    "addr:housenumber":"4",
    "addr:postcode":"6291 aj",
    "addr:street":"Koperstraat",
    "iso:country":"NL",
    "sg:address":"Koperstraat 4",
    "sg:city":"Vaals",
    "sg:orig_category":"Diverse Grafische Activiteiten",
    "sg:phone":"+31 43 306 4078",
    "sg:postcode":"6291 AJ",
    "sg:province":"Limburg",
    "wof:name":"A. Michels",
    "wof:placetype":"venue"
},
  "geometry": {"coordinates":[6.021225,50.771797],"type":"Point"}
}