{
  "type": "Feature",
  "properties": {
    "addr:full":"Sylspaed 27 Workum Provincie Friesland 8711 EB",
    "addr:housenumber":"27",
    "addr:postcode":"8711 eb",
    "addr:street":"Sylspaed;Provincie Friesland",
    "iso:country":"NL",
    "sg:address":"Sylspaed 27",
    "sg:city":"Workum",
    "sg:orig_category":"Fitnesscentra",
    "sg:phone":"+31 515 542 072",
    "sg:postcode":"8711 EB",
    "sg:province":"Provincie Friesland",
    "wof:name":"Het Smidsvuur",
    "wof:placetype":"venue"
},
  "geometry": {"coordinates":[5.436295,52.974205],"type":"Point"}
}