{
  "type": "Feature",
  "properties": {
    "addr:full":"Graaf Zeppelinlaan 2 Amstelveen Noord-Holland 1185 HD",
    "addr:housenumber":"2",
    "addr:postcode":"1185 hd",
    "addr:street":"Graaf Zeppelinlaan",
    "iso:country":"NL",
    "sg:address":"Graaf Zeppelinlaan 2",
    "sg:city":"Amstelveen",
    "sg:orig_category":"Paramedische Behandelingen",
    "sg:phone":"+31 20 641 7138",
    "sg:postcode":"1185 HD",
    "sg:province":"Noord-Holland",
    "wof:name":"Logopediepraktijk Keizer Karelpark",
    "wof:placetype":"venue"
},
  "geometry": {"coordinates":[4.84985,52.298771],"type":"Point"}
}