{
  "type": "Feature",
  "properties": {
    "addr:full":"Spyksedk 16A Gorinchem South Holland 4207 GN",
    "addr:housenumber":"16a",
    "addr:postcode":"4207 gn",
    "addr:street":"Spyksedk",
    "iso:country":"NL",
    "sg:address":"Spyksedk 16A",
    "sg:city":"Gorinchem",
    "sg:orig_category":"Wegenbouw",
    "sg:phone":"+31 183 623 033",
    "sg:postcode":"4207 GN",
    "sg:province":"South Holland",
    "wof:name":"Hbg Bv",
    "wof:placetype":"venue"
},
  "geometry": {"coordinates":[4.9823651314,51.8356056213],"type":"Point"}
}