{
  "type": "Feature",
  "properties": {
    "addr:full":"Ryksstrwg 237 Hellevoetsluis Zuid-Holland 3222 KD",
    "addr:housenumber":"237",
    "addr:postcode":"3222 kd",
    "iso:country":"NL",
    "sg:address":"Ryksstrwg 237",
    "sg:city":"Hellevoetsluis",
    "sg:orig_category":"Sportverenigingen En Ontspannings- Verenigingen",
    "sg:phone":"+31 181 310 517",
    "sg:postcode":"3222 KD",
    "sg:province":"Zuid-Holland",
    "wof:name":"Hellevoetsluis Schietver",
    "wof:placetype":"venue"
},
  "geometry": {"coordinates":[4.143085,51.855431],"type":"Point"}
}