{
  "type": "Feature",
  "properties": {
    "addr:full":"Haagdijk 260 Breda North Brabant 4811 TX",
    "addr:housenumber":"260",
    "addr:postcode":"4811 tx",
    "addr:street":"Haagdijk",
    "iso:country":"NL",
    "sg:address":"Haagdijk 260",
    "sg:city":"Breda",
    "sg:orig_category":"Juweliers",
    "sg:phone":"+31 76 521 3744",
    "sg:postcode":"4811 TX",
    "sg:province":"North Brabant",
    "wof:name":"F. Heesters-Tegenbosch Juweliers-Horloge",
    "wof:placetype":"venue"
},
  "geometry": {"coordinates":[4.766106,51.587158],"type":"Point"}
}