{
  "type": "Feature",
  "properties": {
    "addr:full":"E Strouvenln 5 Maastricht Limburg 6214 AW",
    "addr:housenumber":"5",
    "addr:postcode":"6214 aw",
    "iso:country":"NL",
    "sg:address":"E Strouvenln 5",
    "sg:city":"Maastricht",
    "sg:orig_category":"Beeldende Kunstenaars",
    "sg:phone":"+31 43 321 5238",
    "sg:postcode":"6214 AW",
    "sg:province":"Limburg",
    "wof:name":"Kranen",
    "wof:placetype":"venue"
},
  "geometry": {"coordinates":[5.679382,50.846333],"type":"Point"}
}