{
  "type": "Feature",
  "properties": {
    "addr:full":"Voswinkelstg 13 Losser Overijssel 7582 PK",
    "addr:housenumber":"13",
    "addr:postcode":"7582 pk",
    "addr:street":"Voswinkelstg",
    "iso:country":"NL",
    "sg:address":"Voswinkelstg 13",
    "sg:city":"Losser",
    "sg:orig_category":"Verhuur",
    "sg:phone":"+31 53 538 4810",
    "sg:postcode":"7582 PK",
    "sg:province":"Overijssel",
    "wof:name":"Kentucky",
    "wof:placetype":"venue"
},
  "geometry": {"coordinates":[6.995187,52.264381],"type":"Point"}
}