{
  "type": "Feature",
  "properties": {
    "addr:full":"Oosterstraat 90 Vlaardingen Zuid-Holland 3134 NT",
    "addr:housenumber":"90",
    "addr:postcode":"3134 nt",
    "addr:street":"Oosterstraat",
    "iso:country":"NL",
    "sg:address":"Oosterstraat 90",
    "sg:city":"Vlaardingen",
    "sg:orig_category":"Beautyfarms And Sauna'S",
    "sg:phone":"+31 10 234 1367",
    "sg:postcode":"3134 NT",
    "sg:province":"Zuid-Holland",
    "wof:name":"Jeannette Stout",
    "wof:placetype":"venue"
},
  "geometry": {"coordinates":[4.351372,51.907082],"type":"Point"}
}