{
  "type": "Feature",
  "properties": {
    "addr:full":"Bruggestraat 9 Oude Wetering Zuid-Holland 2377 BC",
    "addr:housenumber":"9",
    "addr:postcode":"wetering;2377 bc",
    "addr:street":"Bruggestraat",
    "iso:country":"NL",
    "sg:address":"Bruggestraat 9",
    "sg:city":"Oude Wetering",
    "sg:orig_category":"Loodgieterswerk, Verwarming And Sanitaire Installaties",
    "sg:phone":"+31 71 331 5584",
    "sg:postcode":"2377 BC",
    "sg:province":"Zuid-Holland",
    "wof:name":"A.H. Van Heek",
    "wof:placetype":"venue"
},
  "geometry": {"coordinates":[4.643217,52.218838],"type":"Point"}
}