{
  "type": "Feature",
  "properties": {
    "addr:full":"Weststraat 83 Den Helder Noord-Holland 1781 BX",
    "addr:housenumber":"83",
    "addr:postcode":"1781 bx",
    "addr:street":"Weststraat",
    "iso:country":"NL",
    "sg:address":"Weststraat 83",
    "sg:city":"Den Helder",
    "sg:classifiers":[
        {
            "category":"Travel",
            "subcategory":"Hotels & Motels",
            "type":"Entertainment"
        }
    ],
    "sg:phone":"+31 223 610 212",
    "sg:postcode":"1781 BX",
    "sg:province":"Noord-Holland",
    "wof:name":"Le Saillant",
    "wof:placetype":"venue"
},
  "geometry": {"coordinates":[4.76736,52.959351],"type":"Point"}
}