{
  "type": "Feature",
  "properties": {
    "iso:country":"NL",
    "sg:address":"Oranjeln 39",
    "sg:city":"Rijswijk",
    "sg:orig_category":"Verenigingsgebouwen",
    "sg:phone":"+31 70 399 2023",
    "sg:postcode":"2281 GA",
    "sg:province":"South Holland",
    "wof:name":"Amicitia",
    "wof:placetype":"venue"
},
  "geometry": {"coordinates":[4.340776,52.056229],"type":"Point"}
}