{
  "type": "Feature",
  "properties": {
    "iso:country":"NL",
    "sg:address":"Esborgstraat 54",
    "sg:city":"Scheemda",
    "sg:orig_category":"Mobiele Service Aan Motorvoertuigen",
    "sg:phone":"+31 597 591 734",
    "sg:postcode":"9679 BV",
    "sg:province":"Groningen",
    "wof:name":"Internationaal Bergings- En Sleepdienst Weering",
    "wof:placetype":"venue"
},
  "geometry": {"coordinates":[6.978496,53.173599],"type":"Point"}
}