{
  "type": "Feature",
  "properties": {
    "addr:full":"Jacques Veltmanstraat 21B Amsterdam Noord-Holland 1065 EG",
    "addr:housenumber":"21b",
    "addr:postcode":"1065 eg",
    "addr:street":"Jacques Veltmanstraat",
    "iso:country":"NL",
    "sg:address":"Jacques Veltmanstraat 21B",
    "sg:city":"Amsterdam",
    "sg:orig_category":"Overheidsdiensten",
    "sg:phone":"+31 20 617 2721",
    "sg:postcode":"1065 EG",
    "sg:province":"Noord-Holland",
    "wof:name":"Buurtcentrum Het Anker",
    "wof:placetype":"venue"
},
  "geometry": {"coordinates":[4.8326449394,52.3533859253],"type":"Point"}
}