{
  "type": "Feature",
  "properties": {
    "addr:full":"Jaarbeursplein 6 Utrecht Utrecht 3521 AL",
    "addr:housenumber":"6",
    "addr:postcode":"3521 al",
    "addr:street":"Jaarbeursplein",
    "iso:country":"NL",
    "sg:address":"Jaarbeursplein 6",
    "sg:city":"Utrecht",
    "sg:classifiers":[
        {
            "category":"Fast Food",
            "type":"Food & Drink"
        }
    ],
    "sg:phone":"+31 30 293 5127",
    "sg:postcode":"3521 AL",
    "sg:province":"Utrecht",
    "sg:tags":[
        "afhaal",
        "restaurant"
    ],
    "wof:name":"Mcdonald'S Restaurant Jaarbeurs",
    "wof:placetype":"venue"
},
  "geometry": {"coordinates":[5.107294,52.088722],"type":"Point"}
}