{
  "type": "Feature",
  "properties": {
    "addr:full":"W Pyrmontkd 409 S Gravenhage South Holland 2518 KE",
    "addr:housenumber":"409",
    "addr:postcode":"2518 ke",
    "addr:street":"W;S Gravenhage",
    "iso:country":"NL",
    "sg:address":"W Pyrmontkd 409",
    "sg:city":"S Gravenhage",
    "sg:orig_category":"Kappers",
    "sg:phone":"+31 70 427 4343",
    "sg:postcode":"2518 KE",
    "sg:province":"South Holland",
    "wof:name":"Manolita",
    "wof:placetype":"venue"
},
  "geometry": {"coordinates":[4.29348,52.080318],"type":"Point"}
}