{
  "type": "Feature",
  "properties": {
    "addr:full":"Beukenln 1 Heesch Noord-Brabant 5384 BE",
    "addr:housenumber":"1",
    "addr:postcode":"5384",
    "addr:street":"Beukenln",
    "iso:country":"NL",
    "sg:address":"Beukenln 1",
    "sg:city":"Heesch",
    "sg:orig_category":"Administratie- En Boekhoudkantoren",
    "sg:phone":"+31 412 452 146",
    "sg:postcode":"5384 BE",
    "sg:province":"Noord-Brabant",
    "wof:name":"Fridal Bv",
    "wof:placetype":"venue"
},
  "geometry": {"coordinates":[5.536976,51.735111],"type":"Point"}
}