{
  "type": "Feature",
  "properties": {
    "addr:full":"Theresiastr 32 S Gravenhage Zuid-Holland 2593 AP",
    "addr:housenumber":"32;gravenhage",
    "addr:postcode":"2593 ap",
    "addr:street":"Theresiastr;S",
    "iso:country":"NL",
    "sg:address":"Theresiastr 32",
    "sg:city":"S Gravenhage",
    "sg:orig_category":"Bloemen En Planten",
    "sg:phone":"+31 70 383 8489",
    "sg:postcode":"2593 AP",
    "sg:province":"Zuid-Holland",
    "wof:name":"Melvin",
    "wof:placetype":"venue"
},
  "geometry": {"coordinates":[4.34266,52.086121],"type":"Point"}
}