{
  "type": "Feature",
  "properties": {
    "iso:country":"NL",
    "sg:address":"V Mussenbroekbaan 14-16",
    "sg:city":"Nieuwegein",
    "sg:orig_category":"Oud Papier",
    "sg:phone":"+31 30 603 6821",
    "sg:postcode":"3439 MX",
    "sg:province":"Utrecht",
    "wof:name":"Ap Vianen Recycling Bv",
    "wof:placetype":"venue"
},
  "geometry": {"coordinates":[5.1025471687,52.0263900757],"type":"Point"}
}