{
  "type": "Feature",
  "properties": {
    "addr:full":"Industrieterrein 4A Panningen Limburg 5981 NK",
    "addr:housenumber":"4a",
    "addr:postcode":"5981 nk",
    "addr:street":"Industrieterrein",
    "iso:country":"NL",
    "sg:address":"Industrieterrein 4A",
    "sg:city":"Panningen",
    "sg:orig_category":"Metaalbekleding And -Behandeling",
    "sg:phone":"+31 77 306 0194",
    "sg:postcode":"5981 NK",
    "sg:province":"Limburg",
    "wof:name":"Snijcentrum Zuid Nederland Bv",
    "wof:placetype":"venue"
},
  "geometry": {"coordinates":[5.988276,51.335415],"type":"Point"}
}