{
  "type": "Feature",
  "properties": {
    "addr:full":"Bloemendaalsewg 5 Waddinxveen South Holland 2741 LD",
    "addr:housenumber":"5",
    "addr:postcode":"2741 ld",
    "addr:street":"Bloemendaalsewg",
    "iso:country":"NL",
    "sg:address":"Bloemendaalsewg 5",
    "sg:city":"Waddinxveen",
    "sg:orig_category":"Bloemen En Planten - Groothandel",
    "sg:phone":"+31 182 393 191",
    "sg:postcode":"2741 LD",
    "sg:province":"South Holland",
    "wof:name":"Bloemendaal, Fa",
    "wof:placetype":"venue"
},
  "geometry": {"coordinates":[4.687357,52.042194],"type":"Point"}
}