{
  "type": "Feature",
  "properties": {
    "addr:full":"Kersenbongerd 20 Huissen Gelderland 6852 BK",
    "addr:housenumber":"20",
    "addr:postcode":"6852 bk",
    "addr:street":"Kersenbongerd;Gelderland",
    "iso:country":"NL",
    "sg:address":"Kersenbongerd 20",
    "sg:city":"Huissen",
    "sg:orig_category":"Fotojournalisten Freelance",
    "sg:phone":"+31 26 325 7407",
    "sg:postcode":"6852 BK",
    "sg:province":"Gelderland",
    "wof:name":"Sluiter, Fons",
    "wof:placetype":"venue"
},
  "geometry": {"coordinates":[5.933039,51.94054],"type":"Point"}
}