{
  "type": "Feature",
  "properties": {
    "addr:full":"Populierendreef 980 Voorburg Zuid-Holland 2272 HW",
    "addr:housenumber":"980",
    "addr:postcode":"2272 hw",
    "addr:street":"Populierendreef",
    "iso:country":"NL",
    "sg:address":"Populierendreef 980",
    "sg:city":"Voorburg",
    "sg:orig_category":"Loodgieters",
    "sg:phone":"+31 70 386 1418",
    "sg:postcode":"2272 HW",
    "sg:province":"Zuid-Holland",
    "wof:name":"Leeuwen Voorburg, Van",
    "wof:placetype":"venue"
},
  "geometry": {"coordinates":[4.361408,52.08456],"type":"Point"}
}