{
  "type": "Feature",
  "properties": {
    "addr:full":"Hongkongstraat 82 Rotterdam Zuid-Holland 3047 BS",
    "addr:housenumber":"82",
    "addr:postcode":"3047 bs",
    "addr:street":"Hongkongstraat",
    "iso:country":"NL",
    "sg:address":"Hongkongstraat 82",
    "sg:city":"Rotterdam",
    "sg:orig_category":"Meubels And Huishoudapparatuur Gh",
    "sg:phone":"+31 10 415 9215",
    "sg:postcode":"3047 BS",
    "sg:province":"Zuid-Holland",
    "wof:name":"Multifurn Bv",
    "wof:placetype":"venue"
},
  "geometry": {"coordinates":[4.400587,51.941723],"type":"Point"}
}