{
  "type": "Feature",
  "properties": {
    "iso:country":"NL",
    "sg:address":"Tjalk 3722",
    "sg:city":"Lelystad",
    "sg:orig_category":"Montagebedrijven",
    "sg:phone":"+31 320 218 177",
    "sg:postcode":"8232 MN",
    "sg:province":"NL.",
    "wof:name":"Vmb",
    "wof:placetype":"venue"
},
  "geometry": {"coordinates":[5.463602,52.502323],"type":"Point"}
}