{
  "type": "Feature",
  "properties": {
    "addr:full":"Wachthoevestraat 26 Hekelingen Zuid-Holland 3209 BK",
    "addr:housenumber":"26",
    "addr:postcode":"3209 bk",
    "addr:street":"Wachthoevestraat",
    "iso:country":"NL",
    "sg:address":"Wachthoevestraat 26",
    "sg:city":"Hekelingen",
    "sg:orig_category":"Binnenhuisarchitecten",
    "sg:phone":"+31 181 631 489",
    "sg:postcode":"3209 BK",
    "sg:province":"Zuid-Holland",
    "wof:name":"De Verbeelders",
    "wof:placetype":"venue"
},
  "geometry": {"coordinates":[4.343945,51.826447],"type":"Point"}
}