{
  "type": "Feature",
  "properties": {
    "addr:full":"2E Oosterparkstr 72 Amsterdam Noord-Holland 1091 JG",
    "addr:housenumber":"72",
    "addr:postcode":"1091 jg",
    "addr:street":"2E Oosterparkstr",
    "iso:country":"NL",
    "sg:address":"2E Oosterparkstr 72",
    "sg:city":"Amsterdam",
    "sg:orig_category":"Beveiliging",
    "sg:phone":"+31 20 663 0075",
    "sg:postcode":"1091 JG",
    "sg:province":"Noord-Holland",
    "wof:name":"Ipc",
    "wof:placetype":"venue"
},
  "geometry": {"coordinates":[4.915526,52.356564],"type":"Point"}
}