{
  "type": "Feature",
  "properties": {
    "addr:full":"J V Nassaustr 97 S Gravenhage Zuid-Holland 2596 BR",
    "addr:housenumber":"97;gravenhage",
    "addr:postcode":"2596 br",
    "addr:street":"J;Nassaustr;S",
    "iso:country":"NL",
    "sg:address":"J V Nassaustr 97",
    "sg:city":"S Gravenhage",
    "sg:orig_category":"Organisatiebureaus",
    "sg:phone":"+31 70 324 5335",
    "sg:postcode":"2596 BR",
    "sg:province":"Zuid-Holland",
    "wof:name":"Senf Pr-Organizers",
    "wof:placetype":"venue"
},
  "geometry": {"coordinates":[4.3184599876,52.0933113098],"type":"Point"}
}