{
  "type": "Feature",
  "properties": {
    "addr:full":"Bunderstr 22 Purmerend Noord-Holland 1445 ED",
    "addr:housenumber":"22",
    "addr:postcode":"1445 ed",
    "addr:street":"Bunderstr",
    "iso:country":"NL",
    "sg:address":"Bunderstr 22",
    "sg:city":"Purmerend",
    "sg:orig_category":"Adviesbureaus Economie",
    "sg:phone":"+31 299 476 916",
    "sg:postcode":"1445 ED",
    "sg:province":"Noord-Holland",
    "wof:name":"Mediterranean Energy Political Risk Consultancy",
    "wof:placetype":"venue"
},
  "geometry": {"coordinates":[4.987197,52.502663],"type":"Point"}
}