{
  "type": "Feature",
  "properties": {
    "iso:country":"NL",
    "sg:address":"Wilgenroos 17",
    "sg:city":"Gieten",
    "sg:orig_category":"Ongediertebestrijding En Ontsmetting",
    "sg:phone":"+31 592 262 185",
    "sg:postcode":"9461 LD",
    "sg:province":"Drenthe",
    "wof:name":"Hoekstra Ongediertebestrijding",
    "wof:placetype":"venue"
},
  "geometry": {"coordinates":[6.770242,52.999325],"type":"Point"}
}