{
  "type": "Feature",
  "properties": {
    "addr:full":"Burg Vd Stadtstr 135 Zaandam North Holland 1501 SE",
    "addr:housenumber":"135;1501",
    "addr:street":"Burg;Se",
    "iso:country":"NL",
    "sg:address":"Burg Vd Stadtstr 135",
    "sg:city":"Zaandam",
    "sg:orig_category":"Verenigingen En Stichtingen",
    "sg:phone":"+31 75 616 2734",
    "sg:postcode":"1501 SE",
    "sg:province":"North Holland",
    "wof:name":"Alevitischeen Cult Ver",
    "wof:placetype":"venue"
},
  "geometry": {"coordinates":[4.836609,52.436523],"type":"Point"}
}