{
  "type": "Feature",
  "properties": {
    "iso:country":"NL",
    "sg:address":"Oranjestraat 6",
    "sg:city":"Velp Gld",
    "sg:orig_category":"Bloemen And Planten",
    "sg:phone":"+31 26 361 6618",
    "sg:postcode":"6881 SE",
    "sg:province":"Gelderland",
    "wof:name":"Bloemsierkunst Karel",
    "wof:placetype":"venue"
},
  "geometry": {"coordinates":[5.969588,51.995617],"type":"Point"}
}