{
  "type": "Feature",
  "properties": {
    "addr:full":"Weteringwg 2B Pynacker Zuid-Holland 2641 KM",
    "addr:housenumber":"2b",
    "addr:postcode":"2641 km",
    "addr:street":"Weteringwg",
    "iso:country":"NL",
    "sg:address":"Weteringwg 2B",
    "sg:city":"Pynacker",
    "sg:orig_category":"Organisatiebureaus",
    "sg:phone":"+31 15 362 0500",
    "sg:postcode":"2641 KM",
    "sg:province":"Zuid-Holland",
    "wof:name":"Star Bv",
    "wof:placetype":"venue"
},
  "geometry": {"coordinates":[4.4389538765,52.0251541138],"type":"Point"}
}