{
  "type": "Feature",
  "properties": {
    "addr:full":"Sint Pieterstraat 7 Maastricht Limburg 6211 JM",
    "addr:housenumber":"7",
    "addr:postcode":"6211 jm",
    "addr:street":"Sint Pieterstraat",
    "iso:country":"NL",
    "sg:address":"Sint Pieterstraat 7",
    "sg:city":"Maastricht",
    "sg:orig_category":"Bibliotheken And Openbare Archieven",
    "sg:phone":"+31 43 321 7051",
    "sg:postcode":"6211 JM",
    "sg:province":"Limburg",
    "wof:name":"Rijksarchief In Limburg",
    "wof:placetype":"venue"
},
  "geometry": {"coordinates":[5.692555,50.845753],"type":"Point"}
}