{
  "type": "Feature",
  "properties": {
    "iso:country":"NL",
    "sg:address":"Albert Van Cuijckstraat 19",
    "sg:city":"Asten",
    "sg:orig_category":"Verhuur Audiovisuele Apparatuur",
    "sg:phone":"+31 493 691 665",
    "sg:postcode":"5721 JL",
    "sg:province":"Noord-Brabant",
    "wof:name":"Manders Geluidstechniek",
    "wof:placetype":"venue"
},
  "geometry": {"coordinates":[5.743072,51.399612],"type":"Point"}
}