{
  "type": "Feature",
  "properties": {
    "addr:full":"Zuidplein 10 Amsterdam Noord-Holland 1077 XV",
    "addr:housenumber":"10",
    "addr:postcode":"1077 xv",
    "addr:street":"Zuidplein",
    "iso:country":"NL",
    "sg:address":"Zuidplein 10",
    "sg:city":"Amsterdam",
    "sg:orig_category":"Boekenuitgeverijen",
    "sg:phone":"+31 20 661 3598",
    "sg:postcode":"1077 XV",
    "sg:province":"Noord-Holland",
    "wof:name":"Ako Zuid",
    "wof:placetype":"venue"
},
  "geometry": {"coordinates":[4.87304,52.339943],"type":"Point"}
}