{
  "type": "Feature",
  "properties": {
    "addr:full":"Feddemawg 3 Kloosterburen Groningen 9977 TG",
    "addr:housenumber":"3",
    "addr:postcode":"9977 tg",
    "addr:street":"Feddemawg",
    "iso:country":"NL",
    "sg:address":"Feddemawg 3",
    "sg:city":"Kloosterburen",
    "sg:orig_category":"Bedrijfsopleidingen",
    "sg:phone":"+31 595 481 672",
    "sg:postcode":"9977 TG",
    "sg:province":"Groningen",
    "sg:website":"http://www.bhv.stuive.demon.nl",
    "wof:name":"Stuive, P",
    "wof:placetype":"venue"
},
  "geometry": {"coordinates":[6.414056,53.405724],"type":"Point"}
}