{
  "type": "Feature",
  "properties": {
    "addr:full":"Rijksweg 39 Sint Maartensvlotbrug Noord-Holland 1753 EC",
    "addr:housenumber":"39",
    "addr:postcode":"1753 ec",
    "addr:street":"Rijksweg",
    "iso:country":"NL",
    "sg:address":"Rijksweg 39",
    "sg:city":"Sint Maartensvlotbrug",
    "sg:classifiers":[
        {
            "category":"Travel",
            "subcategory":"Hotels & Motels",
            "type":"Entertainment"
        }
    ],
    "sg:phone":"+31 224 561 237",
    "sg:postcode":"1753 EC",
    "sg:province":"Noord-Holland",
    "wof:name":"T Karrespoor",
    "wof:placetype":"venue"
},
  "geometry": {"coordinates":[4.706645,52.786392],"type":"Point"}
}