{
  "type": "Feature",
  "properties": {
    "addr:full":"Hoogstraat 47 Nieuwpoort South Holland 2965 AK",
    "addr:housenumber":"47",
    "addr:postcode":"2965 ak",
    "addr:street":"Hoogstraat",
    "iso:country":"NL",
    "sg:address":"Hoogstraat 47",
    "sg:city":"Nieuwpoort",
    "sg:orig_category":"Kappers",
    "sg:phone":"+31 184 601 368",
    "sg:postcode":"2965 AK",
    "sg:province":"South Holland",
    "wof:name":"Kapsalon Modern",
    "wof:placetype":"venue"
},
  "geometry": {"coordinates":[4.8689208031,51.9351997375],"type":"Point"}
}