{
  "type": "Feature",
  "properties": {
    "addr:full":"Lijnbaan 30 Rotterdam Zuid-Holland 3012 EP",
    "addr:housenumber":"30",
    "addr:postcode":"3012 ep",
    "addr:street":"Lijnbaan",
    "iso:country":"NL",
    "sg:address":"Lijnbaan 30",
    "sg:city":"Rotterdam",
    "sg:orig_category":"Gespecialiseerde Voeding",
    "sg:phone":"+31 10 214 1808",
    "sg:postcode":"3012 EP",
    "sg:province":"Zuid-Holland",
    "wof:name":"Java House",
    "wof:placetype":"venue"
},
  "geometry": {"coordinates":[4.475603,51.923359],"type":"Point"}
}