{
  "type": "Feature",
  "properties": {
    "addr:full":"Simplonbaan 41 Utrecht Utrecht 3524 GB",
    "addr:housenumber":"41",
    "addr:postcode":"3524 gb",
    "addr:street":"Simplonbaan",
    "iso:country":"NL",
    "sg:address":"Simplonbaan 41",
    "sg:city":"Utrecht",
    "sg:orig_category":"Vertalers",
    "sg:phone":"+31 30 280 1358",
    "sg:postcode":"3524 GB",
    "sg:province":"Utrecht",
    "wof:name":"Eekhout, D",
    "wof:placetype":"venue"
},
  "geometry": {"coordinates":[5.131918,52.063599],"type":"Point"}
}