{
  "type": "Feature",
  "properties": {
    "addr:full":"Industrieweg 56 Staphorst Overijssel 7951 TA",
    "addr:housenumber":"56",
    "addr:postcode":"7951 ta",
    "addr:street":"Industrieweg",
    "iso:country":"NL",
    "sg:address":"Industrieweg 56",
    "sg:city":"Staphorst",
    "sg:orig_category":"Algemene Werktuigbouw",
    "sg:phone":"+31 522 461 103",
    "sg:postcode":"7951 TA",
    "sg:province":"Overijssel",
    "wof:name":"Smit Snij- En Lastechniek Bv",
    "wof:placetype":"venue"
},
  "geometry": {"coordinates":[6.225324,52.636063],"type":"Point"}
}