{
  "type": "Feature",
  "properties": {
    "addr:full":"Engelseweg 233 Helmond North Brabant 5705 AE",
    "addr:housenumber":"233",
    "addr:postcode":"5705 ae",
    "addr:street":"Engelseweg",
    "iso:country":"NL",
    "sg:address":"Engelseweg 233",
    "sg:city":"Helmond",
    "sg:orig_category":"Metaalvrije Afvalrecycling",
    "sg:phone":"+31 492 526 669",
    "sg:postcode":"5705 AE",
    "sg:province":"North Brabant",
    "wof:name":"Papierhandel Van Heck Bv",
    "wof:placetype":"venue"
},
  "geometry": {"coordinates":[5.683715,51.471443],"type":"Point"}
}