{
  "type": "Feature",
  "properties": {
    "iso:country":"NL",
    "sg:address":"Noorderstationsstraat 77",
    "sg:city":"Zwaagwesteinde",
    "sg:orig_category":"Verzekeringen",
    "sg:phone":"+31 511 444 340",
    "sg:postcode":"9271 CJ",
    "sg:province":"Provincie Friesland",
    "wof:name":"Peter Van Zutphen Verzekeringen",
    "wof:placetype":"venue"
},
  "geometry": {"coordinates":[6.036835,53.249138],"type":"Point"}
}