{
  "type": "Feature",
  "properties": {
    "addr:full":"Hoofdstraat 138 Epe Gelderland 8162 AP",
    "addr:housenumber":"138",
    "addr:postcode":"8162 ap",
    "addr:street":"Hoofdstraat;Gelderland",
    "iso:country":"NL",
    "sg:address":"Hoofdstraat 138",
    "sg:city":"Epe",
    "sg:orig_category":"Werving And Selectie Van Tijdelijk Personeel And Uitzendkantoren",
    "sg:phone":"+31 578 629 155",
    "sg:postcode":"8162 AP",
    "sg:province":"Gelderland",
    "wof:name":"Intermediar Uitzendbureau",
    "wof:placetype":"venue"
},
  "geometry": {"coordinates":[5.9836750031,52.345790863],"type":"Point"}
}