{
  "type": "Feature",
  "properties": {
    "addr:full":"V Schermbeekln 7 Ulvenhout Noord-Brabant 4851 AV",
    "addr:housenumber":"7",
    "addr:postcode":"4851 av",
    "addr:street":"Schermbeekln",
    "iso:country":"NL",
    "sg:address":"V Schermbeekln 7",
    "sg:city":"Ulvenhout",
    "sg:orig_category":"Adviesbureaus Bedrijfsorganisatie",
    "sg:phone":"+31 76 564 0248",
    "sg:postcode":"4851 AV",
    "sg:province":"Noord-Brabant",
    "wof:name":"Coserco Bv",
    "wof:placetype":"venue"
},
  "geometry": {"coordinates":[4.797003,51.552074],"type":"Point"}
}