{
  "type": "Feature",
  "properties": {
    "addr:full":"Stoepveldsngl 43 Assen Drenthe 9403 SM",
    "addr:housenumber":"43",
    "addr:postcode":"9403 sm",
    "addr:street":"Stoepveldsngl",
    "iso:country":"NL",
    "sg:address":"Stoepveldsngl 43",
    "sg:city":"Assen",
    "sg:orig_category":"Elektrotechnische Apparatuur - Fabrieken En Groothandel",
    "sg:phone":"+31 592 343 360",
    "sg:postcode":"9403 SM",
    "sg:province":"Drenthe",
    "wof:name":"Intercraft",
    "wof:placetype":"venue"
},
  "geometry": {"coordinates":[6.595336,53.013416],"type":"Point"}
}