{
  "type": "Feature",
  "properties": {
    "addr:full":"Postbus 399 Schiedam Zuid-Holland 3100 AJ",
    "addr:housenumber":"399",
    "addr:postcode":"3100 aj",
    "addr:street":"Postbus",
    "iso:country":"NL",
    "sg:address":"Postbus 399",
    "sg:city":"Schiedam",
    "sg:orig_category":"Begrafenisverzorging",
    "sg:phone":"+31 10 273 2424",
    "sg:postcode":"3100 AJ",
    "sg:province":"Zuid-Holland",
    "wof:name":"Matrice",
    "wof:placetype":"venue"
},
  "geometry": {"coordinates":[4.39816,51.918449],"type":"Point"}
}