{
  "type": "Feature",
  "properties": {
    "iso:country":"NL",
    "sg:address":"Molenstraat 96A",
    "sg:city":"Kruisland",
    "sg:orig_category":"Goederenvervoer Over De Weg",
    "sg:phone":"+31 167 533 259",
    "sg:postcode":"4756 BH",
    "sg:province":"Noord-Brabant",
    "wof:name":"Kop En Zn. Int.",
    "wof:placetype":"venue"
},
  "geometry": {"coordinates":[50.5485,26.02475],"type":"Point"}
}