{
  "type": "Feature",
  "properties": {
    "addr:full":"Middelwg 59 Asperen Gelderland 4147 AT",
    "addr:housenumber":"59",
    "addr:postcode":"4147",
    "addr:street":"Middelwg;Gelderland",
    "iso:country":"NL",
    "sg:address":"Middelwg 59",
    "sg:city":"Asperen",
    "sg:orig_category":"Kappers",
    "sg:phone":"+31 345 632 309",
    "sg:postcode":"4147 AT",
    "sg:province":"Gelderland",
    "wof:name":"Gerrit, De Jong",
    "wof:placetype":"venue"
},
  "geometry": {"coordinates":[5.116271019,51.8798789978],"type":"Point"}
}