{
  "type": "Feature",
  "properties": {
    "addr:full":"Vredehofln 63 Vlissingen Zeeland 4383 AB",
    "addr:housenumber":"63",
    "addr:postcode":"4383 ab",
    "addr:street":"Vredehofln",
    "iso:country":"NL",
    "sg:address":"Vredehofln 63",
    "sg:city":"Vlissingen",
    "sg:orig_category":"Kappers",
    "sg:phone":"+31 118 467 722",
    "sg:postcode":"4383 AB",
    "sg:province":"Zeeland",
    "wof:name":"Mystic",
    "wof:placetype":"venue"
},
  "geometry": {"coordinates":[3.559239,51.454723],"type":"Point"}
}