{
  "type": "Feature",
  "properties": {
    "iso:country":"NL",
    "sg:address":"Leuvensestraat 56",
    "sg:city":"Scheveningen",
    "sg:classifiers":[
        {
            "category":"Travel",
            "subcategory":"Hotels & Motels",
            "type":"Entertainment"
        }
    ],
    "sg:phone":"+31 70 355 2118",
    "sg:postcode":"2587 GJ",
    "sg:province":"South Holland",
    "wof:name":"Hotel Danny",
    "wof:placetype":"venue"
},
  "geometry": {"coordinates":[4.293779,52.11005],"type":"Point"}
}