{
  "type": "Feature",
  "properties": {
    "iso:country":"NL",
    "sg:address":"Gaastmeer 8",
    "sg:city":"Uithoorn",
    "sg:orig_category":"Kappers",
    "sg:phone":"+31 297 531 080",
    "sg:postcode":"1423 DD",
    "sg:province":"Noord-Holland",
    "wof:name":"Janine Thuiskappersservice",
    "wof:placetype":"venue"
},
  "geometry": {"coordinates":[4.8205947876,52.2306022644],"type":"Point"}
}