{
  "type": "Feature",
  "properties": {
    "addr:full":"Amelandln 1 Heerenveen Friesland 8443 BT",
    "addr:housenumber":"1",
    "addr:postcode":"8443 bt",
    "addr:street":"Amelandln",
    "iso:country":"NL",
    "sg:address":"Amelandln 1",
    "sg:city":"Heerenveen",
    "sg:orig_category":"Scholen Voor Algemeen Voortgezet Onderwijs",
    "sg:phone":"+31 513 636 572",
    "sg:postcode":"8443 BT",
    "sg:province":"Friesland",
    "wof:name":"Osg Sevenwolden",
    "wof:placetype":"venue"
},
  "geometry": {"coordinates":[5.936188,52.945034],"type":"Point"}
}