{
  "type": "Feature",
  "properties": {
    "addr:full":"Europaln 26C Eindhoven Noord-Brabant 5623 LJ",
    "addr:housenumber":"26c",
    "addr:postcode":"5623 lj",
    "addr:street":"Europaln",
    "iso:country":"NL",
    "sg:address":"Europaln 26C",
    "sg:city":"Eindhoven",
    "sg:orig_category":"Belastingconsulenten/ Belastingadviseurs",
    "sg:phone":"+31 40 244 4288",
    "sg:postcode":"5623 LJ",
    "sg:province":"Noord-Brabant",
    "sg:website":"http://www.dewert.nl",
    "wof:name":"Wert Accountants/Belastingadv, De",
    "wof:placetype":"venue"
},
  "geometry": {"coordinates":[5.47708,51.460041],"type":"Point"}
}