{
  "type": "Feature",
  "properties": {
    "addr:full":"Laat 46 Alkmaar Noord-Holland 1811 EJ",
    "addr:housenumber":"46",
    "addr:postcode":"1811 ej",
    "addr:street":"Laat",
    "iso:country":"NL",
    "sg:address":"Laat 46",
    "sg:city":"Alkmaar",
    "sg:orig_category":"Meubelzaken, Woning- And Keukeninrichting",
    "sg:phone":"+31 72 515 4882",
    "sg:postcode":"1811 EJ",
    "sg:province":"Noord-Holland",
    "wof:name":"Burgers",
    "wof:placetype":"venue"
},
  "geometry": {"coordinates":[4.75143,52.628941],"type":"Point"}
}