{
  "type": "Feature",
  "properties": {
    "addr:full":"Shannonwg 1 Luchth Schiphol Noord-Holland 1118 LA",
    "addr:housenumber":"1",
    "addr:postcode":"1118 la",
    "addr:street":"Shannonwg",
    "iso:country":"NL",
    "sg:address":"Shannonwg 1",
    "sg:city":"Luchth Schiphol",
    "sg:orig_category":"Luchtvrachtexpediteurs",
    "sg:phone":"+31 20 446 7111",
    "sg:postcode":"1118 LA",
    "sg:province":"Noord-Holland",
    "wof:name":"Kds Cargo Bv",
    "wof:placetype":"venue"
},
  "geometry": {"coordinates":[4.763394,52.292164],"type":"Point"}
}