{
  "type": "Feature",
  "properties": {
    "addr:full":"Hulstweg 16 Kootwijkerbroek Gelderland 3774 TM",
    "addr:housenumber":"16",
    "addr:postcode":"3774 tm",
    "addr:street":"Hulstweg;Gelderland",
    "iso:country":"NL",
    "sg:address":"Hulstweg 16",
    "sg:city":"Kootwijkerbroek",
    "sg:orig_category":"Chemische Producten Gh",
    "sg:phone":"+31 342 441 311",
    "sg:postcode":"3774 TM",
    "sg:province":"Gelderland",
    "wof:name":"Loonbedrijf Gebr.Goorhuis",
    "wof:placetype":"venue"
},
  "geometry": {"coordinates":[5.701565,52.142616],"type":"Point"}
}