{
  "type": "Feature",
  "properties": {
    "addr:full":"Anemoonstraat 16 Katwijk Zh South Holland 2223 JC",
    "addr:housenumber":"16",
    "addr:postcode":"zh;2223 jc",
    "addr:street":"Anemoonstraat",
    "iso:country":"NL",
    "sg:address":"Anemoonstraat 16",
    "sg:city":"Katwijk Zh",
    "sg:orig_category":"Glaszetten",
    "sg:phone":"+31 71 401 2021",
    "sg:postcode":"2223 JC",
    "sg:province":"South Holland",
    "wof:name":"Glashandel Van Tricht",
    "wof:placetype":"venue"
},
  "geometry": {"coordinates":[4.420642,52.187901],"type":"Point"}
}