{
  "type": "Feature",
  "properties": {
    "addr:full":"De Vennen 1 Peize Drenthe 9321 HR",
    "addr:housenumber":"1",
    "addr:postcode":"9321 hr",
    "addr:street":"De Vennen",
    "iso:country":"NL",
    "sg:address":"De Vennen 1",
    "sg:city":"Peize",
    "sg:orig_category":"Koel- En Vriestransporten",
    "sg:phone":"+31 50 503 3025",
    "sg:postcode":"9321 HR",
    "sg:province":"Drenthe",
    "wof:name":"Fellinger",
    "wof:placetype":"venue"
},
  "geometry": {"coordinates":[6.489145,53.147141],"type":"Point"}
}