{
  "type": "Feature",
  "properties": {
    "addr:full":"Spreeuwenlaan 49 Schagen Noord-Holland 1742 GA",
    "addr:housenumber":"49",
    "addr:postcode":"1742 ga",
    "addr:street":"Spreeuwenlaan",
    "iso:country":"NL",
    "sg:address":"Spreeuwenlaan 49",
    "sg:city":"Schagen",
    "sg:orig_category":"Marktonderzoekbureaus",
    "sg:phone":"+31 224 298 646",
    "sg:postcode":"1742 GA",
    "sg:province":"Noord-Holland",
    "wof:name":"C.M. Zomerdijk",
    "wof:placetype":"venue"
},
  "geometry": {"coordinates":[4.784898,52.780865],"type":"Point"}
}