{
  "type": "Feature",
  "properties": {
    "iso:country":"NL",
    "sg:address":"Bleijerheiderstraat 93",
    "sg:city":"Kerkrade",
    "sg:orig_category":"Artsen And Specialisten",
    "sg:phone":"+31 45 545 2913",
    "sg:postcode":"6462 AG",
    "sg:province":"Limburg",
    "wof:name":"A.J.M. Vluggen",
    "wof:placetype":"venue"
},
  "geometry": {"coordinates":[6.068041,50.85519],"type":"Point"}
}