{
  "type": "Feature",
  "properties": {
    "iso:country":"NL",
    "sg:address":"Johan De Wittstraat 33",
    "sg:city":"Dordrecht",
    "sg:orig_category":"Notarissen",
    "sg:phone":"+31 78 613 8100",
    "sg:postcode":"3311 KG",
    "sg:province":"Zuid-Holland",
    "wof:name":"Mr. J. Van Der Veen Notaris",
    "wof:placetype":"venue"
},
  "geometry": {"coordinates":[4.667844,51.810226],"type":"Point"}
}