{
  "type": "Feature",
  "properties": {
    "addr:full":"Nw Oostenburg Str 16 Amsterdam Noord-Holland 1018 MK",
    "addr:housenumber":"16",
    "addr:postcode":"1018",
    "addr:street":"Nw Oostenburg Str",
    "iso:country":"NL",
    "sg:address":"Nw Oostenburg Str 16",
    "sg:city":"Amsterdam",
    "sg:orig_category":"Beeldende Kunstenaars",
    "sg:phone":"+31 20 625 6814",
    "sg:postcode":"1018 MK",
    "sg:province":"Noord-Holland",
    "wof:name":"Lemaire, D",
    "wof:placetype":"venue"
},
  "geometry": {"coordinates":[4.924232,52.369041],"type":"Point"}
}