{
  "type": "Feature",
  "properties": {
    "addr:full":"Smitstr 27 Amsterdam North Holland 1092 XP",
    "addr:housenumber":"27",
    "addr:postcode":"1092 xp",
    "addr:street":"Smitstr",
    "iso:country":"NL",
    "sg:address":"Smitstr 27",
    "sg:city":"Amsterdam",
    "sg:orig_category":"Onderzoekbureaus",
    "sg:phone":"+31 20 525 2238",
    "sg:postcode":"1092 XP",
    "sg:province":"North Holland",
    "wof:name":"Br\u00f7Er",
    "wof:placetype":"venue"
},
  "geometry": {"coordinates":[4.922103,52.354713],"type":"Point"}
}