{
  "type": "Feature",
  "properties": {
    "addr:full":"Kattenb Kruisstr 5 Amsterdam Noord-Holland 1018 JR",
    "addr:housenumber":"5",
    "addr:postcode":"1018 jr",
    "addr:street":"Kruisstr",
    "iso:country":"NL",
    "sg:address":"Kattenb Kruisstr 5",
    "sg:city":"Amsterdam",
    "sg:orig_category":"Peuterspeelzalen",
    "sg:phone":"+31 20 626 6602",
    "sg:postcode":"1018 JR",
    "sg:province":"Noord-Holland",
    "wof:name":"Bon Bini",
    "wof:placetype":"venue"
},
  "geometry": {"coordinates":[4.920136,52.372353],"type":"Point"}
}