{
  "type": "Feature",
  "properties": {
    "iso:country":"NL",
    "sg:address":"Klaverkamp 19",
    "sg:city":"Hattem",
    "sg:orig_category":"Boekhouders",
    "sg:phone":"+31 38 444 1713",
    "sg:postcode":"8051 SZ",
    "sg:province":"Gelderland",
    "wof:name":"Eska",
    "wof:placetype":"venue"
},
  "geometry": {"coordinates":[6.053555,52.471786],"type":"Point"}
}