{
  "type": "Feature",
  "properties": {
    "addr:full":"Industriewg 15B Assendelft Noord-Holland 1566 JN",
    "addr:housenumber":"15b",
    "addr:postcode":"1566 jn",
    "addr:street":"Industriewg",
    "iso:country":"NL",
    "sg:address":"Industriewg 15B",
    "sg:city":"Assendelft",
    "sg:orig_category":"Keukens",
    "sg:phone":"+31 75 622 9387",
    "sg:postcode":"1566 JN",
    "sg:province":"Noord-Holland",
    "sg:website":"http://www.totaalinterieur.nl",
    "wof:name":"Totaal Interieur Bv",
    "wof:placetype":"venue"
},
  "geometry": {"coordinates":[4.766752,52.491924],"type":"Point"}
}