{
  "type": "Feature",
  "properties": {
    "addr:full":"De Molen 10 Houten Utrecht 3994 DB",
    "addr:housenumber":"10",
    "addr:postcode":"3994 db",
    "addr:street":"De Molen",
    "iso:country":"NL",
    "sg:address":"De Molen 10",
    "sg:city":"Houten",
    "sg:orig_category":"Diverse Grafische Activiteiten",
    "sg:phone":"+31 30 637 5011",
    "sg:postcode":"3994 DB",
    "sg:province":"Utrecht",
    "wof:name":"Color Design Grafische Vormgeving",
    "wof:placetype":"venue"
},
  "geometry": {"coordinates":[5.176225,52.028255],"type":"Point"}
}