{
  "type": "Feature",
  "properties": {
    "addr:full":"Bosmanskamp 61 Geldermalsen Gelderland 4191 MT",
    "addr:housenumber":"61",
    "addr:postcode":"4191",
    "addr:street":"Bosmanskamp;Gelderland;Mt",
    "iso:country":"NL",
    "sg:address":"Bosmanskamp 61",
    "sg:city":"Geldermalsen",
    "sg:orig_category":"Arbo- En Bedrijfsgezondheids- Diensten",
    "sg:phone":"+31 345 589 444",
    "sg:postcode":"4191 MT",
    "sg:province":"Gelderland",
    "wof:name":"Aon Verzuim Management",
    "wof:placetype":"venue"
},
  "geometry": {"coordinates":[5.303961,51.874279],"type":"Point"}
}