{
  "type": "Feature",
  "properties": {
    "iso:country":"NL",
    "sg:address":"Dorpsstr 4",
    "sg:city":"Nunspeet",
    "sg:orig_category":"Kinderkleding",
    "sg:phone":"+31 341 254 204",
    "sg:postcode":"8071 BZ",
    "sg:province":"Gelderland",
    "wof:name":"Kameleon",
    "wof:placetype":"venue"
},
  "geometry": {"coordinates":[5.786342,52.376377],"type":"Point"}
}