{
  "type": "Feature",
  "properties": {
    "iso:country":"NL",
    "sg:address":"Zuilenburg 68",
    "sg:city":"Dordrecht",
    "sg:orig_category":"Kinderopvang",
    "sg:phone":"+31 78 617 7776",
    "sg:postcode":"3328 VC",
    "sg:province":"Zuid-Holland",
    "wof:name":"Bengels, De",
    "wof:placetype":"venue"
},
  "geometry": {"coordinates":[4.678301,51.776066],"type":"Point"}
}