{
  "type": "Feature",
  "properties": {
    "addr:full":"Asselsestraat 139 Apeldoorn Gelderland 7311 EJ",
    "addr:housenumber":"139",
    "addr:postcode":"7311 ej",
    "addr:street":"Asselsestraat;Gelderland",
    "iso:country":"NL",
    "sg:address":"Asselsestraat 139",
    "sg:city":"Apeldoorn",
    "sg:orig_category":"Kinderopvang Behalve Thuis",
    "sg:phone":"+31 55 522 6409",
    "sg:postcode":"7311 EJ",
    "sg:province":"Gelderland",
    "wof:name":"Stichting Dagverblijven Apeldoorn",
    "wof:placetype":"venue"
},
  "geometry": {"coordinates":[5.951497,52.211426],"type":"Point"}
}