{
  "type": "Feature",
  "properties": {
    "addr:full":"Prinsengracht 803 Amsterdam Noord-Holland 1017 KA",
    "addr:housenumber":"803",
    "addr:postcode":"1017 ka",
    "addr:street":"Prinsengracht",
    "iso:country":"NL",
    "sg:address":"Prinsengracht 803",
    "sg:city":"Amsterdam",
    "sg:orig_category":"Verzekeringen",
    "sg:phone":"+31 20 626 9116",
    "sg:postcode":"1017 KA",
    "sg:province":"Noord-Holland",
    "wof:name":"R.B. De Waal",
    "wof:placetype":"venue"
},
  "geometry": {"coordinates":[4.887882,52.363186],"type":"Point"}
}