{
  "type": "Feature",
  "properties": {
    "addr:full":"Marconistraat 2 Bleiswijk Zuid-Holland 2665 JE",
    "addr:housenumber":"2",
    "addr:postcode":"2665 je",
    "addr:street":"Marconistraat",
    "iso:country":"NL",
    "sg:address":"Marconistraat 2",
    "sg:city":"Bleiswijk",
    "sg:orig_category":"Fitnesscentra",
    "sg:phone":"+31 10 522 0221",
    "sg:postcode":"2665 JE",
    "sg:province":"Zuid-Holland",
    "wof:name":"Fitness Center Body Blitzz",
    "wof:placetype":"venue"
},
  "geometry": {"coordinates":[4.543889,52.014496],"type":"Point"}
}