{
  "type": "Feature",
  "properties": {
    "addr:full":"Molenstraat 1 Meijel Limburg 5768 EA",
    "addr:housenumber":"1",
    "addr:postcode":"5768 ea",
    "addr:street":"Molenstraat",
    "iso:country":"NL",
    "sg:address":"Molenstraat 1",
    "sg:city":"Meijel",
    "sg:orig_category":"Schilderwerk",
    "sg:phone":"+31 77 466 1930",
    "sg:postcode":"5768 EA",
    "sg:province":"Limburg",
    "wof:name":"H G Doensen",
    "wof:placetype":"venue"
},
  "geometry": {"coordinates":[5.882023,51.346424],"type":"Point"}
}