{
  "type": "Feature",
  "properties": {
    "addr:full":"Johanniterlaan 3 Harderwijk Gelderland 3841 DS",
    "addr:housenumber":"3",
    "addr:postcode":"3841 ds",
    "addr:street":"Johanniterlaan;Gelderland",
    "iso:country":"NL",
    "sg:address":"Johanniterlaan 3",
    "sg:city":"Harderwijk",
    "sg:orig_category":"Banken And Kredietinstellingen",
    "sg:phone":"+31 341 465 511",
    "sg:postcode":"3841 DS",
    "sg:province":"Gelderland",
    "wof:name":"Ing Bank",
    "wof:placetype":"venue"
},
  "geometry": {"coordinates":[5.624306,52.344978],"type":"Point"}
}