{
  "type": "Feature",
  "properties": {
    "addr:full":"Ferdinand Bolstraat 1 Deventer Overijssel 7412 GL",
    "addr:housenumber":"1",
    "addr:postcode":"7412 gl",
    "addr:street":"Ferdinand Bolstraat",
    "iso:country":"NL",
    "sg:address":"Ferdinand Bolstraat 1",
    "sg:city":"Deventer",
    "sg:orig_category":"Bloemen And Planten",
    "sg:phone":"+31 570 672 811",
    "sg:postcode":"7412 GL",
    "sg:province":"Overijssel",
    "wof:name":"Marleen De Boer-Pors",
    "wof:placetype":"venue"
},
  "geometry": {"coordinates":[6.139835,52.262978],"type":"Point"}
}