{
  "type": "Feature",
  "properties": {
    "addr:full":"Frederiksstraat 19 Amsterdam Noord-Holland 1054 LA",
    "addr:housenumber":"19",
    "addr:postcode":"1054 la",
    "addr:street":"Frederiksstraat",
    "iso:country":"NL",
    "sg:address":"Frederiksstraat 19",
    "sg:city":"Amsterdam",
    "sg:orig_category":"Meubelzaken, Woning- And Keukeninrichting",
    "sg:phone":"+31 20 683 7300",
    "sg:postcode":"1054 LA",
    "sg:province":"Noord-Holland",
    "wof:name":"T.P. Ebbink",
    "wof:placetype":"venue"
},
  "geometry": {"coordinates":[4.85938,52.358124],"type":"Point"}
}