{
  "type": "Feature",
  "properties": {
    "addr:full":"T Dorp 69 Heesch Noord-Brabant 5384 MB",
    "addr:housenumber":"69",
    "addr:postcode":"5384 mb",
    "addr:street":"T Dorp",
    "iso:country":"NL",
    "sg:address":"T Dorp 69",
    "sg:city":"Heesch",
    "sg:orig_category":"Kaas",
    "sg:phone":"+31 412 453 759",
    "sg:postcode":"5384 MB",
    "sg:province":"Noord-Brabant",
    "wof:name":"Bon Fromage",
    "wof:placetype":"venue"
},
  "geometry": {"coordinates":[5.5267810822,51.7351303101],"type":"Point"}
}