{
  "type": "Feature",
  "properties": {
    "addr:full":"Zylbaan 2 Leiderdorp Zuid-Holland 2352 BN",
    "addr:housenumber":"2",
    "addr:postcode":"2352 bn",
    "addr:street":"Zylbaan",
    "iso:country":"NL",
    "sg:address":"Zylbaan 2",
    "sg:city":"Leiderdorp",
    "sg:orig_category":"Houtgroothandel",
    "sg:phone":"+31 71 581 5100",
    "sg:postcode":"2352 BN",
    "sg:province":"Zuid-Holland",
    "wof:name":"Klinkenberg Bv",
    "wof:placetype":"venue"
},
  "geometry": {"coordinates":[4.534218,52.156174],"type":"Point"}
}