{
  "type": "Feature",
  "properties": {
    "addr:full":"Valkenburgerstr 74/D Berg En Terblyt Limburg 6325 BP",
    "addr:housenumber":"74 / d",
    "addr:postcode":"6325 bp",
    "addr:street":"Valkenburgerstr;Berg",
    "iso:country":"NL",
    "sg:address":"Valkenburgerstr 74/D",
    "sg:city":"Berg En Terblyt",
    "sg:orig_category":"Wegenbouw",
    "sg:phone":"+31 43 604 1110",
    "sg:postcode":"6325 BP",
    "sg:province":"Limburg",
    "wof:name":"Haveco Bv",
    "wof:placetype":"venue"
},
  "geometry": {"coordinates":[5.7853770256,50.8607711792],"type":"Point"}
}