{
  "type": "Feature",
  "properties": {
    "addr:full":"Ryksstrwg 41/B Elst Ut Utrecht 3921 AB",
    "addr:housenumber":"41 / b",
    "addr:postcode":"3921 ab",
    "addr:street":"Ryksstrwg",
    "iso:country":"NL",
    "sg:address":"Ryksstrwg 41/B",
    "sg:city":"Elst Ut",
    "sg:orig_category":"Kappers",
    "sg:phone":"+31 318 471 407",
    "sg:postcode":"3921 AB",
    "sg:province":"Utrecht",
    "wof:name":"Budding, A",
    "wof:placetype":"venue"
},
  "geometry": {"coordinates":[5.5005531311,51.9838447571],"type":"Point"}
}