{
  "type": "Feature",
  "properties": {
    "iso:country":"NL",
    "sg:address":"Bosschendk 82",
    "sg:city":"Oudenbosch",
    "sg:orig_category":"Artsen - Huisartsen",
    "sg:phone":"+31 165 313 446",
    "sg:postcode":"4731 DH",
    "sg:province":"North Brabant",
    "wof:name":"Philips-Cr\u00e9bolder & M Valster, C A M L",
    "wof:placetype":"venue"
},
  "geometry": {"coordinates":[4.545459,51.589825],"type":"Point"}
}