{
  "type": "Feature",
  "properties": {
    "addr:full":"Raadhuispln 5 Nieuwerkerk Yssel Zuid-Holland 2914 KM",
    "addr:housenumber":"5",
    "addr:postcode":"2914 km",
    "addr:street":"Raadhuispln",
    "iso:country":"NL",
    "sg:address":"Raadhuispln 5",
    "sg:city":"Nieuwerkerk Yssel",
    "sg:orig_category":"Hypotheken",
    "sg:phone":"+31 180 317 139",
    "sg:postcode":"2914 KM",
    "sg:province":"Zuid-Holland",
    "wof:name":"Hypotheken Meester Bv, De",
    "wof:placetype":"venue"
},
  "geometry": {"coordinates":[4.616235,51.967773],"type":"Point"}
}