{
  "type": "Feature",
  "properties": {
    "addr:full":"Rattinkstr 1 Deventer Overijssel 7413 AJ",
    "addr:housenumber":"1",
    "addr:postcode":"7413 aj",
    "addr:street":"Rattinkstr",
    "iso:country":"NL",
    "sg:address":"Rattinkstr 1",
    "sg:city":"Deventer",
    "sg:orig_category":"Agenturen En Commissiehandel",
    "sg:phone":"+31 570 606 725",
    "sg:postcode":"7413 AJ",
    "sg:province":"Overijssel",
    "wof:name":"T4T Holland",
    "wof:placetype":"venue"
},
  "geometry": {"coordinates":[6.161911,52.257507],"type":"Point"}
}