{
  "type": "Feature",
  "properties": {
    "addr:full":"Grensstr 4 S Heerenberg North Rhine-Westphalia 7041 GZ",
    "addr:housenumber":"4",
    "addr:postcode":"7041 gz",
    "addr:street":"Grensstr",
    "iso:country":"NL",
    "sg:address":"Grensstr 4",
    "sg:city":"S Heerenberg",
    "sg:orig_category":"Elektronica - Ontwikkeling En Groothandel",
    "sg:phone":"+31 314 675 070",
    "sg:postcode":"7041 GZ",
    "sg:province":"North Rhine-Westphalia",
    "wof:name":"Betronic Hyberd Circuits Bv",
    "wof:placetype":"venue"
},
  "geometry": {"coordinates":[6.262443,51.869545],"type":"Point"}
}