{
  "type": "Feature",
  "properties": {
    "addr:full":"Molenpoort 17 Weert Limburg 6001 HB",
    "addr:housenumber":"17",
    "addr:postcode":"6001 hb",
    "addr:street":"Molenpoort",
    "iso:country":"NL",
    "sg:address":"Molenpoort 17",
    "sg:city":"Weert",
    "sg:orig_category":"Homeopathie",
    "sg:phone":"+31 495 451 192",
    "sg:postcode":"6001 HB",
    "sg:province":"Limburg",
    "wof:name":"Herman Philipsen",
    "wof:placetype":"venue"
},
  "geometry": {"coordinates":[5.70194,51.254208],"type":"Point"}
}