{
  "type": "Feature",
  "properties": {
    "addr:full":"Nieuwstad 15 Burgum Friesland 9251 LN",
    "addr:housenumber":"15",
    "addr:postcode":"9251 ln",
    "addr:street":"Nieuwstad",
    "iso:country":"NL",
    "sg:address":"Nieuwstad 15",
    "sg:city":"Burgum",
    "sg:orig_category":"Bloemen And Planten Gh",
    "sg:phone":"+31 511 461 213",
    "sg:postcode":"9251 LN",
    "sg:province":"Friesland",
    "wof:name":"Firma J.R. Douma",
    "wof:placetype":"venue"
},
  "geometry": {"coordinates":[6.006621,53.197845],"type":"Point"}
}