{
  "type": "Feature",
  "properties": {
    "addr:full":"Stockholm 1 Barendrecht Zuid-Holland 2993 LM",
    "addr:housenumber":"1",
    "addr:postcode":"2993 lm",
    "addr:street":"Stockholm",
    "iso:country":"NL",
    "sg:address":"Stockholm 1",
    "sg:city":"Barendrecht",
    "sg:orig_category":"Kantoor- En Bedrijfsmeubelen",
    "sg:phone":"+31 180 695 555",
    "sg:postcode":"2993 LM",
    "sg:province":"Zuid-Holland",
    "sg:website":"http://www.kantoortotaal.nl",
    "wof:name":"Kantoortotaal Groep",
    "wof:placetype":"venue"
},
  "geometry": {"coordinates":[4.5102128983,51.8500976562],"type":"Point"}
}