{
  "type": "Feature",
  "properties": {
    "addr:full":"Jelgersmastr 6 Haarlem Noord-Holland 2023 EP",
    "addr:housenumber":"6",
    "addr:postcode":"2023 ep",
    "addr:street":"Jelgersmastr",
    "iso:country":"NL",
    "sg:address":"Jelgersmastr 6",
    "sg:city":"Haarlem",
    "sg:orig_category":"Beeldende Kunstenaars",
    "sg:phone":"+31 23 526 2465",
    "sg:postcode":"2023 EP",
    "sg:province":"Noord-Holland",
    "wof:name":"Timmerman, Karel",
    "wof:placetype":"venue"
},
  "geometry": {"coordinates":[4.631742,52.393856],"type":"Point"}
}