{
  "type": "Feature",
  "properties": {
    "addr:full":"Fie Carelsenstraat 44 Hengelo Ov NL.08 7558 WB",
    "addr:housenumber":"44",
    "addr:postcode":"7558 wb",
    "addr:street":"Fie Carelsenstraat;Ov",
    "iso:country":"NL",
    "sg:address":"Fie Carelsenstraat 44",
    "sg:city":"Hengelo Ov",
    "sg:orig_category":"Glaszetten",
    "sg:phone":"+31 74 277 1310",
    "sg:postcode":"7558 WB",
    "sg:province":"NL.08",
    "wof:name":"J.H.M. Altena",
    "wof:placetype":"venue"
},
  "geometry": {"coordinates":[6.844075,52.28569],"type":"Point"}
}