{
  "type": "Feature",
  "properties": {
    "iso:country":"NL",
    "sg:address":"Gemeenlandsedk Z 12A",
    "sg:city":"Abbenbroek",
    "sg:orig_category":"Woningbouw- Verenigingen En -Stichtingen",
    "sg:phone":"+31 181 668 222",
    "sg:postcode":"3216 AH",
    "sg:province":"Zuid-Holland",
    "wof:name":"Zes Kernen, De",
    "wof:placetype":"venue"
},
  "geometry": {"coordinates":[4.2420048714,51.850402832],"type":"Point"}
}