{
  "type": "Feature",
  "properties": {
    "addr:full":"Ceintuurbaan 153 Amsterdam North Holland 1072 GB",
    "addr:housenumber":"153",
    "addr:postcode":"1072 gb",
    "addr:street":"Ceintuurbaan",
    "iso:country":"NL",
    "sg:address":"Ceintuurbaan 153",
    "sg:city":"Amsterdam",
    "sg:orig_category":"Meubelen",
    "sg:phone":"+31 20 673 7206",
    "sg:postcode":"1072 GB",
    "sg:province":"North Holland",
    "wof:name":"Mc",
    "wof:placetype":"venue"
},
  "geometry": {"coordinates":[4.894096,52.353325],"type":"Point"}
}