{
  "type": "Feature",
  "properties": {
    "addr:full":"Brugstraat 8 Enkhuizen Noord-Holland 1601 GC",
    "addr:housenumber":"8",
    "addr:postcode":"1601 gc",
    "addr:street":"Brugstraat",
    "iso:country":"NL",
    "sg:address":"Brugstraat 8",
    "sg:city":"Enkhuizen",
    "sg:orig_category":"Pleziervaartuigen And Reparatie",
    "sg:phone":"+31 228 321 551",
    "sg:postcode":"1601 GC",
    "sg:province":"Noord-Holland",
    "wof:name":"Zilver En Staal / Govert De Bruijn",
    "wof:placetype":"venue"
},
  "geometry": {"coordinates":[5.291725,52.70079],"type":"Point"}
}