{
  "type": "Feature",
  "properties": {
    "addr:full":"Valeriusstraat 121Hs Amsterdam North Holland 1075 ER",
    "addr:housenumber":"121hs",
    "addr:postcode":"1075 er",
    "addr:street":"Valeriusstraat",
    "iso:country":"NL",
    "sg:address":"Valeriusstraat 121Hs",
    "sg:city":"Amsterdam",
    "sg:orig_category":"Diverse Grafische Activiteiten",
    "sg:phone":"+31 20 662 4196",
    "sg:postcode":"1075 ER",
    "sg:province":"North Holland",
    "wof:name":"M. Dinkelberg",
    "wof:placetype":"venue"
},
  "geometry": {"coordinates":[4.866413,52.353374],"type":"Point"}
}