{
  "type": "Feature",
  "properties": {
    "addr:full":"Spaarne 10Zw Haarlem North Holland 2011 CH",
    "addr:housenumber":"10zw",
    "addr:postcode":"2011",
    "addr:street":"Spaarne",
    "iso:country":"NL",
    "sg:address":"Spaarne 10Zw",
    "sg:city":"Haarlem",
    "sg:orig_category":"Boeken En Tijdschriften",
    "sg:phone":"+31 23 532 7834",
    "sg:postcode":"2011 CH",
    "sg:province":"North Holland",
    "wof:name":"Automobilia Collection",
    "wof:placetype":"venue"
},
  "geometry": {"coordinates":[4.640603,52.380405],"type":"Point"}
}