{
  "type": "Feature",
  "properties": {
    "iso:country":"NL",
    "sg:address":"Zr Meyboomstr 1A",
    "sg:city":"Zutphen",
    "sg:orig_category":"Artsen - Huisartsen",
    "sg:phone":"+31 575 574 414",
    "sg:postcode":"7207 GZ",
    "sg:province":"Gelderland",
    "wof:name":"Verhoef, S",
    "wof:placetype":"venue"
},
  "geometry": {"coordinates":[6.226529,52.126659],"type":"Point"}
}