{
  "type": "Feature",
  "properties": {
    "addr:full":"Rozemaryn 16 Leidschendam Zuid-Holland 2262 AH",
    "addr:housenumber":"16",
    "addr:postcode":"2262 ah",
    "addr:street":"Rozemaryn",
    "iso:country":"NL",
    "sg:address":"Rozemaryn 16",
    "sg:city":"Leidschendam",
    "sg:orig_category":"Juweliers",
    "sg:phone":"+31 70 327 8676",
    "sg:postcode":"2262 AH",
    "sg:province":"Zuid-Holland",
    "sg:website":"http://www.siebel.nl",
    "wof:name":"Siebel",
    "wof:placetype":"venue"
},
  "geometry": {"coordinates":[4.38396,52.088451],"type":"Point"}
}