{
  "type": "Feature",
  "properties": {
    "addr:full":"Kraaierslaan 17 Noordwijk Zh South Holland 2204 AN",
    "addr:housenumber":"17",
    "addr:postcode":"zh;2204 an",
    "addr:street":"Kraaierslaan",
    "iso:country":"NL",
    "sg:address":"Kraaierslaan 17",
    "sg:city":"Noordwijk Zh",
    "sg:orig_category":"Kampeerterreinen",
    "sg:phone":"+31 252 373 930",
    "sg:postcode":"2204 AN",
    "sg:province":"South Holland",
    "wof:name":"Samoa",
    "wof:placetype":"venue"
},
  "geometry": {"coordinates":[4.4773521423,52.2715568542],"type":"Point"}
}