{
  "type": "Feature",
  "properties": {
    "addr:full":"Kerkstraat 42 Geldermalsen Gelderland 4191 AB",
    "addr:housenumber":"42",
    "addr:postcode":"4191 ab",
    "addr:street":"Kerkstraat;Gelderland",
    "iso:country":"NL",
    "sg:address":"Kerkstraat 42",
    "sg:city":"Geldermalsen",
    "sg:orig_category":"Verlichting And Huishoudartikelen",
    "sg:phone":"+31 345 581 940",
    "sg:postcode":"4191 AB",
    "sg:province":"Gelderland",
    "wof:name":"Blokker",
    "wof:placetype":"venue"
},
  "geometry": {"coordinates":[5.288158,51.883308],"type":"Point"}
}