{
  "type": "Feature",
  "properties": {
    "addr:full":"Nieuweweg 26 Roden Provincie Drenthe 9301 GS",
    "addr:housenumber":"26",
    "addr:postcode":"9301 gs",
    "addr:street":"Nieuweweg;Provincie Drenthe",
    "iso:country":"NL",
    "sg:address":"Nieuweweg 26",
    "sg:city":"Roden",
    "sg:orig_category":"Autokeuringen",
    "sg:phone":"+31 50 501 7612",
    "sg:postcode":"9301 GS",
    "sg:province":"Provincie Drenthe",
    "wof:name":"Roona - Wiechers",
    "wof:placetype":"venue"
},
  "geometry": {"coordinates":[6.423983,53.135994],"type":"Point"}
}