{
  "type": "Feature",
  "properties": {
    "iso:country":"NL",
    "sg:address":"Larixlaan 7",
    "sg:city":"Soest",
    "sg:orig_category":"Vertaal- And Tolkenbureaus",
    "sg:phone":"+31 35 601 8971",
    "sg:postcode":"3768 BD",
    "sg:province":"Utrecht",
    "wof:name":"Markers Tolken Vertalers",
    "wof:placetype":"venue"
},
  "geometry": {"coordinates":[5.298046,52.15836],"type":"Point"}
}