{
  "type": "Feature",
  "properties": {
    "addr:full":"Maasdijk 63 Hedel Gelderland 5321 NG",
    "addr:housenumber":"63",
    "addr:postcode":"5321 ng",
    "addr:street":"Maasdijk;Gelderland",
    "iso:country":"NL",
    "sg:address":"Maasdijk 63",
    "sg:city":"Hedel",
    "sg:orig_category":"Huizensloop And Bouwrijp Maken",
    "sg:phone":"+31 73 599 1244",
    "sg:postcode":"5321 NG",
    "sg:province":"Gelderland",
    "wof:name":"Zand En Grondhandel Hofmans",
    "wof:placetype":"venue"
},
  "geometry": {"coordinates":[5.274071,51.748745],"type":"Point"}
}