{
  "type": "Feature",
  "properties": {
    "addr:full":"Neptunuspln 29 Amersfoort Utrecht 3814 BB",
    "addr:housenumber":"29",
    "addr:postcode":"3814 bb",
    "addr:street":"Neptunuspln",
    "iso:country":"NL",
    "sg:address":"Neptunuspln 29",
    "sg:city":"Amersfoort",
    "sg:classifiers":[
        {
            "category":"Food & Beverages",
            "subcategory":"Bakery",
            "type":"Retail Goods"
        }
    ],
    "sg:phone":"+31 33 475 0449",
    "sg:postcode":"3814 BB",
    "sg:province":"Utrecht",
    "sg:tags":[
        "pizza"
    ],
    "wof:name":"Pulcinella 2000",
    "wof:placetype":"venue"
},
  "geometry": {"coordinates":[5.399525,52.162148],"type":"Point"}
}