{
  "type": "Feature",
  "properties": {
    "addr:full":"Noordstr 22A Bodegraven Zuid-Holland 2411 BJ",
    "addr:housenumber":"22a",
    "addr:postcode":"2411 bj",
    "addr:street":"Noordstr",
    "iso:country":"NL",
    "sg:address":"Noordstr 22A",
    "sg:city":"Bodegraven",
    "sg:orig_category":"Gordijnenateliers",
    "sg:phone":"+31 172 618 385",
    "sg:postcode":"2411 BJ",
    "sg:province":"Zuid-Holland",
    "wof:name":"Veen, Seri Van",
    "wof:placetype":"venue"
},
  "geometry": {"coordinates":[4.747547,52.085552],"type":"Point"}
}