{
  "type": "Feature",
  "properties": {
    "addr:full":"De Bloemendaal 3 S Hertogenbosch Noord-Brabant 5221 EB",
    "addr:housenumber":"3",
    "addr:postcode":"5221 eb",
    "addr:street":"De Bloemendaal",
    "iso:country":"NL",
    "sg:address":"De Bloemendaal 3",
    "sg:city":"S Hertogenbosch",
    "sg:orig_category":"Elektrotechnische Apparatuur - Fabrieken En Groothandel",
    "sg:phone":"+31 73 633 9633",
    "sg:postcode":"5221 EB",
    "sg:province":"Noord-Brabant",
    "wof:name":"Bernard Bv",
    "wof:placetype":"venue"
},
  "geometry": {"coordinates":[5.263097,51.713673],"type":"Point"}
}