{
  "type": "Feature",
  "properties": {
    "addr:full":"H Zwaardemakerstr 18 Bussum North Holland 1402 VE",
    "addr:housenumber":"18",
    "addr:postcode":"1402",
    "addr:street":"Ve",
    "iso:country":"NL",
    "sg:address":"H Zwaardemakerstr 18",
    "sg:city":"Bussum",
    "sg:orig_category":"Bloemen En Planten - Decoratie",
    "sg:phone":"+31 35 692 2102",
    "sg:postcode":"1402 VE",
    "sg:province":"North Holland",
    "wof:name":"Verhage, L",
    "wof:placetype":"venue"
},
  "geometry": {"coordinates":[5.179148,52.272793],"type":"Point"}
}