{
  "type": "Feature",
  "properties": {
    "iso:country":"NL",
    "sg:address":"Randweg 6",
    "sg:city":"Noordwijk Zh",
    "sg:orig_category":"Kampeerterreinen",
    "sg:phone":"+31 252 372 425",
    "sg:postcode":"2204 AL",
    "sg:province":"Zuid-Holland",
    "wof:name":"Duinrust",
    "wof:placetype":"venue"
},
  "geometry": {"coordinates":[4.4717731476,52.2731399536],"type":"Point"}
}