{
  "type": "Feature",
  "properties": {
    "iso:country":"NL",
    "sg:address":"Mijdrechtstraat 93",
    "sg:city":"Utrecht",
    "sg:orig_category":"Onderhoud And Reparatie Kantoorapparatuur",
    "sg:phone":"+31 30 289 5095",
    "sg:postcode":"3522 HV",
    "sg:province":"Utrecht",
    "wof:name":"H.P. Hammelburg",
    "wof:placetype":"venue"
},
  "geometry": {"coordinates":[5.116931,52.075665],"type":"Point"}
}