{
  "type": "Feature",
  "properties": {
    "iso:country":"NL",
    "sg:address":"Bob Marleystraat 1",
    "sg:city":"Almere",
    "sg:orig_category":"Vertaal- And Tolkenbureaus",
    "sg:phone":"+31 36 536 3758",
    "sg:postcode":"1311 JC",
    "sg:province":"Flevoland",
    "wof:name":"Hamdy Mighawry",
    "wof:placetype":"venue"
},
  "geometry": {"coordinates":[5.176391,52.366543],"type":"Point"}
}