{
  "type": "Feature",
  "properties": {
    "addr:full":"Leidseweg 41 Utrecht Utrecht 3531 BB",
    "addr:housenumber":"41",
    "addr:postcode":"3531 bb",
    "addr:street":"Leidseweg",
    "iso:country":"NL",
    "sg:address":"Leidseweg 41",
    "sg:city":"Utrecht",
    "sg:orig_category":"Metalen And Ertsen Gh",
    "sg:phone":"+31 30 294 2872",
    "sg:postcode":"3531 BB",
    "sg:province":"Utrecht",
    "wof:name":"Kopier G.E.",
    "wof:placetype":"venue"
},
  "geometry": {"coordinates":[5.10077,52.089077],"type":"Point"}
}