{
  "type": "Feature",
  "properties": {
    "iso:country":"NL",
    "sg:address":"N Beetsstr 8",
    "sg:city":"Sommelsdyk",
    "sg:orig_category":"Etiketten",
    "sg:phone":"+31 187 470 111",
    "sg:postcode":"3245 RD",
    "sg:province":"Zuid-Holland",
    "sg:website":"http://www.heattransfers.nl",
    "wof:name":"Pds",
    "wof:placetype":"venue"
},
  "geometry": {"coordinates":[4.15478,51.760239],"type":"Point"}
}