{
  "type": "Feature",
  "properties": {
    "iso:country":"NL",
    "sg:address":"Atoomweg 27",
    "sg:city":"Hoorn Nh",
    "sg:orig_category":"Pompen And Compressoren Fab",
    "sg:phone":"+31 229 247 258",
    "sg:postcode":"1627 LE",
    "sg:province":"Noord-Holland",
    "wof:name":"Hypec",
    "wof:placetype":"venue"
},
  "geometry": {"coordinates":[5.093796,52.641315],"type":"Point"}
}