{
  "type": "Feature",
  "properties": {
    "addr:full":"Wilhelminakan Z 110 Oosterhout Nb Noord-Brabant 4903 RA",
    "addr:housenumber":"110",
    "addr:postcode":"4903 ra",
    "iso:country":"NL",
    "sg:address":"Wilhelminakan Z 110",
    "sg:city":"Oosterhout Nb",
    "sg:orig_category":"Werving En Selectie",
    "sg:phone":"+31 162 484 114",
    "sg:postcode":"4903 RA",
    "sg:province":"Noord-Brabant",
    "wof:name":"Wijngaart & Partners, Van Der",
    "wof:placetype":"venue"
},
  "geometry": {"coordinates":[4.8562498093,51.6430511475],"type":"Point"}
}