{
  "type": "Feature",
  "properties": {
    "iso:country":"NL",
    "sg:address":"Lokerenpassage 3",
    "sg:city":"'S Hertogenbosch",
    "sg:orig_category":"Kappers",
    "sg:phone":"+31 73 641 2078",
    "sg:postcode":"5235 KR",
    "sg:province":"Noord-Brabant",
    "wof:name":"Kapsalon Jansen",
    "wof:placetype":"venue"
},
  "geometry": {"coordinates":[5.3085451126,51.7260437012],"type":"Point"}
}