{
  "type": "Feature",
  "properties": {
    "addr:full":"Jupiterweg 4 Zevenbergen Noord-Brabant 4761 RW",
    "addr:housenumber":"4",
    "addr:postcode":"4761 rw",
    "addr:street":"Jupiterweg",
    "iso:country":"NL",
    "sg:address":"Jupiterweg 4",
    "sg:city":"Zevenbergen",
    "sg:orig_category":"Goederenvervoer Over De Weg",
    "sg:phone":"+31 168 388 388",
    "sg:postcode":"4761 RW",
    "sg:province":"Noord-Brabant",
    "wof:name":"Rinnen Gmbh & Co Kg",
    "wof:placetype":"venue"
},
  "geometry": {"coordinates":[4.610105,51.644798],"type":"Point"}
}