{
  "type": "Feature",
  "properties": {
    "iso:country":"NL",
    "sg:address":"Dorpsstraat 65",
    "sg:city":"Halsteren",
    "sg:orig_category":"Banken And Kredietinstellingen",
    "sg:phone":"+31 164 650 500",
    "sg:postcode":"4661 HM",
    "sg:province":"North Brabant",
    "wof:name":"Rabobank",
    "wof:placetype":"venue"
},
  "geometry": {"coordinates":[4.269392,51.526215],"type":"Point"}
}