{
  "type": "Feature",
  "properties": {
    "addr:full":"Beringstr 5 Amersfoort Utrecht 3814 XW",
    "addr:housenumber":"5",
    "addr:postcode":"3814 xw",
    "addr:street":"Beringstr",
    "iso:country":"NL",
    "sg:address":"Beringstr 5",
    "sg:city":"Amersfoort",
    "sg:orig_category":"Biljartzalen",
    "sg:phone":"+31 33 475 1145",
    "sg:postcode":"3814 XW",
    "sg:province":"Utrecht",
    "wof:name":"Koster, H",
    "wof:placetype":"venue"
},
  "geometry": {"coordinates":[5.403195,52.159344],"type":"Point"}
}