{
  "type": "Feature",
  "properties": {
    "addr:full":"De Hagen 5 Vollenhove Overijssel 8325 DB",
    "addr:housenumber":"5",
    "addr:postcode":"8325 db",
    "addr:street":"De Hagen",
    "iso:country":"NL",
    "sg:address":"De Hagen 5",
    "sg:city":"Vollenhove",
    "sg:orig_category":"Fietsen En Bromfietsen",
    "sg:phone":"+31 527 241 654",
    "sg:postcode":"8325 DB",
    "sg:province":"Overijssel",
    "sg:website":"http://www.logtmeijer-tweewielers.nl",
    "wof:name":"Logtmeijer",
    "wof:placetype":"venue"
},
  "geometry": {"coordinates":[5.967676,52.682041],"type":"Point"}
}