{
  "type": "Feature",
  "properties": {
    "addr:full":"Castricummer Werf 99A Castricum North Holland 1901 RS",
    "addr:housenumber":"99a",
    "addr:postcode":"1901 rs",
    "addr:street":"Castricummer Werf",
    "iso:country":"NL",
    "sg:address":"Castricummer Werf 99A",
    "sg:city":"Castricum",
    "sg:orig_category":"Medische Installaties En Instrumenten",
    "sg:phone":"+31 251 662 066",
    "sg:postcode":"1901 RS",
    "sg:province":"North Holland",
    "wof:name":"Tromp",
    "wof:placetype":"venue"
},
  "geometry": {"coordinates":[4.663692,52.540813],"type":"Point"}
}