{
  "type": "Feature",
  "properties": {
    "iso:country":"NL",
    "sg:address":"Balsebaan 55",
    "sg:city":"Bergen Op Zoom",
    "sg:orig_category":"Loodgieterswerk, Verwarming And Sanitaire Installaties",
    "sg:phone":"+31 164 234 980",
    "sg:postcode":"4621 AL",
    "sg:province":"Noord-Brabant",
    "wof:name":"Loodgietersbedrijf Franken",
    "wof:placetype":"venue"
},
  "geometry": {"coordinates":[4.298656,51.490135],"type":"Point"}
}