{
  "type": "Feature",
  "properties": {
    "iso:country":"NL",
    "sg:address":"Ringweg 27",
    "sg:city":"Zaandam",
    "sg:orig_category":"Artiesten",
    "sg:phone":"+31 75 670 0842",
    "sg:postcode":"1507 BG",
    "sg:province":"Noord-Holland",
    "wof:name":"S Timmerman",
    "wof:placetype":"venue"
},
  "geometry": {"coordinates":[4.810699,52.43322],"type":"Point"}
}