{
  "type": "Feature",
  "properties": {
    "addr:full":"Schiedamseweg 84 Schiedam South Holland 3121 JK",
    "addr:housenumber":"84",
    "addr:postcode":"3121 jk",
    "addr:street":"Schiedamseweg",
    "iso:country":"NL",
    "sg:address":"Schiedamseweg 84",
    "sg:city":"Schiedam",
    "sg:orig_category":"Kappers",
    "sg:phone":"+31 10 470 3253",
    "sg:postcode":"3121 JK",
    "sg:province":"South Holland",
    "wof:name":"Dames- En Herenkapsalon Bianca Van Steenis",
    "wof:placetype":"venue"
},
  "geometry": {"coordinates":[4.3796668053,51.9309005737],"type":"Point"}
}