{
  "type": "Feature",
  "properties": {
    "iso:country":"NL",
    "sg:address":"St. Bavostraat 72",
    "sg:city":"Rijsbergen",
    "sg:orig_category":"Film-, Tv- And Videoproductie",
    "sg:phone":"+31 76 596 3370",
    "sg:postcode":"4891 CK",
    "sg:province":"Noord-Brabant",
    "wof:name":"Dig (I'Vent)",
    "wof:placetype":"venue"
},
  "geometry": {"coordinates":[4.702655,51.517067],"type":"Point"}
}