{
  "type": "Feature",
  "properties": {
    "iso:country":"NL",
    "sg:address":"Voordijk 26",
    "sg:city":"Schelluinen",
    "sg:orig_category":"Paramedische Behandelingen",
    "sg:phone":"+31 183 623 577",
    "sg:postcode":"4209 SC",
    "sg:province":"Zuid-Holland",
    "wof:name":"H M Bol",
    "wof:placetype":"venue"
},
  "geometry": {"coordinates":[4.924035,51.848213],"type":"Point"}
}