{
  "type": "Feature",
  "properties": {
    "addr:full":"Rietdreef 5 Papendrecht South Holland 3355 ED",
    "addr:housenumber":"5",
    "addr:postcode":"3355 ed",
    "addr:street":"Rietdreef",
    "iso:country":"NL",
    "sg:address":"Rietdreef 5",
    "sg:city":"Papendrecht",
    "sg:orig_category":"Goederenvervoer Over De Weg",
    "sg:phone":"+31 78 642 8181",
    "sg:postcode":"3355 ED",
    "sg:province":"South Holland",
    "wof:name":"T.J. Van Den Heuvel",
    "wof:placetype":"venue"
},
  "geometry": {"coordinates":[4.706356,51.839359],"type":"Point"}
}