{
  "type": "Feature",
  "properties": {
    "addr:full":"Einsteinstraat 13 Vlierden Noord-Brabant 5756 AX",
    "addr:housenumber":"13",
    "addr:postcode":"5756 ax",
    "addr:street":"Einsteinstraat",
    "iso:country":"NL",
    "sg:address":"Einsteinstraat 13",
    "sg:city":"Vlierden",
    "sg:orig_category":"Kappers",
    "sg:phone":"+31 493 316 312",
    "sg:postcode":"5756 AX",
    "sg:province":"Noord-Brabant",
    "wof:name":"Kapsalon Marjon",
    "wof:placetype":"venue"
},
  "geometry": {"coordinates":[5.7578239441,51.4458465576],"type":"Point"}
}