{
  "type": "Feature",
  "properties": {
    "addr:full":"Minderbroed Sngl 13A Roermond Limburg 6041 KG",
    "addr:housenumber":"13a",
    "addr:postcode":"6041 kg",
    "addr:street":"Sngl",
    "iso:country":"NL",
    "sg:address":"Minderbroed Sngl 13A",
    "sg:city":"Roermond",
    "sg:orig_category":"Makelaars En Adviseurs Hypotheken",
    "sg:phone":"+31 475 336 778",
    "sg:postcode":"6041 KG",
    "sg:province":"Limburg",
    "wof:name":"George Vossen Groep Bv",
    "wof:placetype":"venue"
},
  "geometry": {"coordinates":[5.985333,51.192055],"type":"Point"}
}