{
  "type": "Feature",
  "properties": {
    "addr:full":"Emmastr 16 Alkmaar North Holland 1814 DR",
    "addr:housenumber":"16",
    "addr:postcode":"1814 dr",
    "addr:street":"Emmastr",
    "iso:country":"NL",
    "sg:address":"Emmastr 16",
    "sg:city":"Alkmaar",
    "sg:orig_category":"Verzekeringen - Verzekeringskantoren",
    "sg:phone":"+31 72 512 5531",
    "sg:postcode":"1814 DR",
    "sg:province":"North Holland",
    "wof:name":"Betu\u00e9, H P S De",
    "wof:placetype":"venue"
},
  "geometry": {"coordinates":[4.742059,52.626324],"type":"Point"}
}