{
  "type": "Feature",
  "properties": {
    "addr:full":"Eisenhowerstr 19 Hoogeveen Drenthe 7901 AG",
    "addr:housenumber":"19",
    "addr:postcode":"7901",
    "addr:street":"Eisenhowerstr",
    "iso:country":"NL",
    "sg:address":"Eisenhowerstr 19",
    "sg:city":"Hoogeveen",
    "sg:classifiers":[
        {
            "category":"Professional",
            "subcategory":"Accounting & Tax Preparation",
            "type":"Services"
        }
    ],
    "sg:phone":"+31 528 268 325",
    "sg:postcode":"7901 AG",
    "sg:province":"Drenthe",
    "sg:tags":[
        "accountant",
        "en",
        "-kantoren",
        "register-"
    ],
    "wof:name":"Boersma Bv, T J",
    "wof:placetype":"venue"
},
  "geometry": {"coordinates":[6.474397,52.73167],"type":"Point"}
}