{
  "type": "Feature",
  "properties": {
    "iso:country":"NL",
    "sg:address":"Kanaalstr 247",
    "sg:city":"Lisse",
    "sg:orig_category":"Kerkorgels - Bouw En Reparatie",
    "sg:phone":"+31 252 413 924",
    "sg:postcode":"2161 JK",
    "sg:province":"North Holland",
    "wof:name":"Jongh, W N De",
    "wof:placetype":"venue"
},
  "geometry": {"coordinates":[4.56753,52.256378],"type":"Point"}
}