{
  "type": "Feature",
  "properties": {
    "addr:full":"Kalverstr 176 Amsterdam North Holland 1012 XG",
    "addr:housenumber":"176",
    "addr:postcode":"1012 xg",
    "iso:country":"NL",
    "sg:address":"Kalverstr 176",
    "sg:city":"Amsterdam",
    "sg:orig_category":"Herenkleding",
    "sg:phone":"+31 20 623 5809",
    "sg:postcode":"1012 XG",
    "sg:province":"North Holland",
    "wof:name":"Bendorff",
    "wof:placetype":"venue"
},
  "geometry": {"coordinates":[4.89116,52.368301],"type":"Point"}
}