{
  "type": "Feature",
  "properties": {
    "addr:full":"Vosseln 36 Hillegom Zuid-Holland 2181 CD",
    "addr:housenumber":"36",
    "addr:postcode":"2181 cd",
    "addr:street":"Vosseln",
    "iso:country":"NL",
    "sg:address":"Vosseln 36",
    "sg:city":"Hillegom",
    "sg:orig_category":"Onderhoudswerken",
    "sg:phone":"+31 252 521 642",
    "sg:postcode":"2181 CD",
    "sg:province":"Zuid-Holland",
    "wof:name":"Bakker, E P M",
    "wof:placetype":"venue"
},
  "geometry": {"coordinates":[4.578603,52.290993],"type":"Point"}
}