{
  "type": "Feature",
  "properties": {
    "addr:full":"Pettelaarsewg 9 S Hertogenbosch Noord-Brabant 5216 BG",
    "addr:housenumber":"9",
    "addr:postcode":"5216",
    "addr:street":"Pettelaarsewg",
    "iso:country":"NL",
    "sg:address":"Pettelaarsewg 9",
    "sg:city":"S Hertogenbosch",
    "sg:orig_category":"Binnenhuisarchitectuur",
    "sg:phone":"+31 73613240",
    "sg:postcode":"5216 BG",
    "sg:province":"Noord-Brabant",
    "wof:name":"Du Sable",
    "wof:placetype":"venue"
},
  "geometry": {"coordinates":[5.311409,51.683033],"type":"Point"}
}