{
  "type": "Feature",
  "properties": {
    "addr:full":"Alvarezlaan 64 Terneuzen Zeeland 4536  B",
    "addr:housenumber":"64;b",
    "addr:postcode":"4536",
    "addr:street":"Alvarezlaan",
    "iso:country":"NL",
    "sg:address":"Alvarezlaan 64",
    "sg:city":"Terneuzen",
    "sg:orig_category":"Boekenuitgeverijen",
    "sg:phone":"+31 115 611 696",
    "sg:postcode":"4536  B",
    "sg:province":"Zeeland",
    "wof:name":"Bruna",
    "wof:placetype":"venue"
},
  "geometry": {"coordinates":[3.84625,51.319672],"type":"Point"}
}