{
  "type": "Feature",
  "properties": {
    "iso:country":"NL",
    "sg:address":"Reactorweg 259",
    "sg:city":"Utrecht",
    "sg:orig_category":"Diverse Bedrijfsinstallaties Gh",
    "sg:phone":"+31 30 241 3888",
    "sg:postcode":"3542 AD",
    "sg:province":"Utrecht",
    "wof:name":"Satchwell Bv",
    "wof:placetype":"venue"
},
  "geometry": {"coordinates":[5.047916,52.11525],"type":"Point"}
}