{
  "type": "Feature",
  "properties": {
    "addr:full":"Ohmweg 41 Alblasserdam Zuid-Holland 2952 BD",
    "addr:housenumber":"41",
    "addr:postcode":"2952 bd",
    "addr:street":"Ohmweg",
    "iso:country":"NL",
    "sg:address":"Ohmweg 41",
    "sg:city":"Alblasserdam",
    "sg:orig_category":"Kantoorartikelen",
    "sg:phone":"+31 78 654 0718",
    "sg:postcode":"2952 BD",
    "sg:province":"Zuid-Holland",
    "wof:name":"Pavimento Projektinrichting",
    "wof:placetype":"venue"
},
  "geometry": {"coordinates":[4.6736907959,51.856628418],"type":"Point"}
}