{
  "type": "Feature",
  "properties": {
    "iso:country":"NL",
    "sg:address":"Julianastr 17A",
    "sg:city":"Ewyk",
    "sg:orig_category":"Kappers",
    "sg:phone":"+31 487 522 962",
    "sg:postcode":"6644 BN",
    "sg:province":"Gelderland",
    "wof:name":"Sam Sam",
    "wof:placetype":"venue"
},
  "geometry": {"coordinates":[114.598969,4.52513],"type":"Point"}
}