{
  "type": "Feature",
  "properties": {
    "addr:full":"Verl Badwg 1 Meeden North Rhine-Westphalia 9651 BR",
    "addr:housenumber":"1",
    "addr:postcode":"9651 br",
    "addr:street":"Badwg",
    "iso:country":"NL",
    "sg:address":"Verl Badwg 1",
    "sg:city":"Meeden",
    "sg:orig_category":"Filters - Fabrieken En Groothandel",
    "sg:phone":"+31 598 621 317",
    "sg:postcode":"9651 BR",
    "sg:province":"North Rhine-Westphalia",
    "wof:name":"Holt, Van Der",
    "wof:placetype":"venue"
},
  "geometry": {"coordinates":[8.50811,51.882469],"type":"Point"}
}