{
  "type": "Feature",
  "properties": {
    "addr:full":"Descartesstr 29 Amsterdam North Holland 1064 XM",
    "addr:housenumber":"29",
    "addr:postcode":"1064 xm",
    "addr:street":"Descartesstr",
    "iso:country":"NL",
    "sg:address":"Descartesstr 29",
    "sg:city":"Amsterdam",
    "sg:orig_category":"Autorijscholen",
    "sg:phone":"+31 6 14675234",
    "sg:postcode":"1064 XM",
    "sg:province":"North Holland",
    "wof:name":"Loutfi, Z",
    "wof:placetype":"venue"
},
  "geometry": {"coordinates":[4.816379,52.374466],"type":"Point"}
}