{
  "type": "Feature",
  "properties": {
    "addr:full":"Ceresstraat 23 Wageningen Gelderland 6706 AL",
    "addr:housenumber":"23",
    "addr:postcode":"6706",
    "addr:street":"Ceresstraat;Gelderland",
    "iso:country":"NL",
    "sg:address":"Ceresstraat 23",
    "sg:city":"Wageningen",
    "sg:orig_category":"Schilderwerk",
    "sg:phone":"+31 317 412 372",
    "sg:postcode":"6706 AL",
    "sg:province":"Gelderland",
    "wof:name":"A.T. Zaayer",
    "wof:placetype":"venue"
},
  "geometry": {"coordinates":[5.671966,51.970074],"type":"Point"}
}