{
  "type": "Feature",
  "properties": {
    "iso:country":"NL",
    "sg:address":"Titiaanstraat 13",
    "sg:city":"Amsterdam",
    "sg:orig_category":"Architecten",
    "sg:phone":"+31 20 676 1755",
    "sg:postcode":"1077 RC",
    "sg:province":"Noord-Holland",
    "wof:name":"Tangram Architekten Bv",
    "wof:placetype":"venue"
},
  "geometry": {"coordinates":[4.869978,52.349602],"type":"Point"}
}