{
  "type": "Feature",
  "properties": {
    "iso:country":"NL",
    "sg:address":"Vogelzankwg 20",
    "sg:city":"Landgraaf",
    "sg:orig_category":"Kappers",
    "sg:phone":"+31 45 531 2944",
    "sg:postcode":"6374 AH",
    "sg:province":"Limburg",
    "wof:name":"Miranka",
    "wof:placetype":"venue"
},
  "geometry": {"coordinates":[6.037652,50.913265],"type":"Point"}
}