{
  "type": "Feature",
  "properties": {
    "addr:full":"Vogelzankwg 20 Landgraaf Limburg 6374 AH",
    "addr:housenumber":"20",
    "addr:postcode":"6374 ah",
    "addr:street":"Vogelzankwg",
    "iso:country":"NL",
    "sg:address":"Vogelzankwg 20",
    "sg:city":"Landgraaf",
    "sg:orig_category":"Kappers",
    "sg:phone":"+31 45 531 2944",
    "sg:postcode":"6374 AH",
    "sg:province":"Limburg",
    "wof:name":"Miranka",
    "wof:placetype":"venue"
},
  "geometry": {"coordinates":[6.037652,50.913265],"type":"Point"}
}