{
  "type": "Feature",
  "properties": {
    "addr:full":"Dkn Hennissenstr 6 Gulpen Limburg 6271 GA",
    "addr:housenumber":"6",
    "addr:postcode":"6271 ga",
    "addr:street":"Hennissenstr",
    "iso:country":"NL",
    "sg:address":"Dkn Hennissenstr 6",
    "sg:city":"Gulpen",
    "sg:orig_category":"Autorijscholen",
    "sg:phone":"+31 43 450 4062",
    "sg:postcode":"6271 GA",
    "sg:province":"Limburg",
    "wof:name":"Huijnen Autorijschool Marcel",
    "wof:placetype":"venue"
},
  "geometry": {"coordinates":[5.889586,50.817989],"type":"Point"}
}