{
  "type": "Feature",
  "properties": {
    "addr:full":"J F Kennedyln 10 Vught Noord-Brabant 5263 AJ",
    "addr:housenumber":"10",
    "addr:postcode":"5263 aj",
    "addr:street":"J F Kennedyln",
    "iso:country":"NL",
    "sg:address":"J F Kennedyln 10",
    "sg:city":"Vught",
    "sg:orig_category":"Agenturen En Commissiehandel",
    "sg:phone":"+31 73 656 6861",
    "sg:postcode":"5263 AJ",
    "sg:province":"Noord-Brabant",
    "wof:name":"Wouw, Van De",
    "wof:placetype":"venue"
},
  "geometry": {"coordinates":[5.297663,51.660519],"type":"Point"}
}