{
  "type": "Feature",
  "properties": {
    "addr:full":"Borculoseweg 23 Ruurlo Gelderland 7261 BH",
    "addr:housenumber":"23",
    "addr:postcode":"7261 bh",
    "addr:street":"Borculoseweg;Gelderland",
    "iso:country":"NL",
    "sg:address":"Borculoseweg 23",
    "sg:city":"Ruurlo",
    "sg:orig_category":"Apothekers",
    "sg:phone":"+31 573 453 400",
    "sg:postcode":"7261 BH",
    "sg:province":"Gelderland",
    "wof:name":"Apotheek Ruurlo",
    "wof:placetype":"venue"
},
  "geometry": {"coordinates":[6.453097,52.088543],"type":"Point"}
}