{
  "type": "Feature",
  "properties": {
    "iso:country":"NL",
    "sg:address":"Brouwersstraat 30",
    "sg:city":"Maasbracht",
    "sg:orig_category":"Diverse Bedrijfsinstallaties Gh",
    "sg:phone":"+31 475 468 122",
    "sg:postcode":"6051 AA",
    "sg:province":"Limburg",
    "wof:name":"Reef Mechatronica Bv",
    "wof:placetype":"venue"
},
  "geometry": {"coordinates":[5.89362,51.15276],"type":"Point"}
}