{
  "type": "Feature",
  "properties": {
    "addr:full":"Knoppersweg 12 Randwijk Gelderland 6668 AT",
    "addr:housenumber":"12",
    "addr:postcode":"6668",
    "addr:street":"Knoppersweg;Gelderland",
    "iso:country":"NL",
    "sg:address":"Knoppersweg 12",
    "sg:city":"Randwijk",
    "sg:orig_category":"Bloemen And Planten",
    "sg:phone":"+31 488 491 702",
    "sg:postcode":"6668 AT",
    "sg:province":"Gelderland",
    "wof:name":"Vof Gebr. Van Voorthuijsen",
    "wof:placetype":"venue"
},
  "geometry": {"coordinates":[5.712427,51.943653],"type":"Point"}
}