{
  "type": "Feature",
  "properties": {
    "iso:country":"NL",
    "sg:address":"Caroliewg 29",
    "sg:city":"Groningen",
    "sg:orig_category":"Schoenen",
    "sg:phone":"+31 50 311 6275",
    "sg:postcode":"9711 LR",
    "sg:province":"Groningen",
    "wof:name":"Ara-Geox",
    "wof:placetype":"venue"
},
  "geometry": {"coordinates":[6.570141,53.216385],"type":"Point"}
}