{
  "type": "Feature",
  "properties": {
    "addr:full":"Winkelc Coevering 29 Geldrop North Brabant 5665 GA",
    "addr:housenumber":"29",
    "addr:postcode":"5665 ga",
    "addr:street":"Winkelc Coevering",
    "iso:country":"NL",
    "sg:address":"Winkelc Coevering 29",
    "sg:city":"Geldrop",
    "sg:orig_category":"Cafetaria'S",
    "sg:phone":"+31 40 286 2403",
    "sg:postcode":"5665 GA",
    "sg:province":"North Brabant",
    "wof:name":"Coevering, De",
    "wof:placetype":"venue"
},
  "geometry": {"coordinates":[5.572993,51.417782],"type":"Point"}
}