{
  "type": "Feature",
  "properties": {
    "addr:full":"Het Ambacht 67 Brunssum Limburg 6444 KZ",
    "addr:housenumber":"67",
    "addr:postcode":"6444 kz",
    "addr:street":"Het Ambacht",
    "iso:country":"NL",
    "sg:address":"Het Ambacht 67",
    "sg:city":"Brunssum",
    "sg:orig_category":"Accountants - Administratie- Consulenten En -Kantoren",
    "sg:phone":"+31 6 40085151",
    "sg:postcode":"6444 KZ",
    "sg:province":"Limburg",
    "wof:name":"Apora",
    "wof:placetype":"venue"
},
  "geometry": {"coordinates":[5.948906,50.941498],"type":"Point"}
}