{
  "type": "Feature",
  "properties": {
    "addr:full":"Schurenstraat 8 Deventer Overijssel 7413 RA",
    "addr:housenumber":"8",
    "addr:postcode":"7413 ra",
    "addr:street":"Schurenstraat",
    "iso:country":"NL",
    "sg:address":"Schurenstraat 8",
    "sg:city":"Deventer",
    "sg:orig_category":"Bouwnijverheidsmachines Gh",
    "sg:phone":"+31 575 432 218",
    "sg:postcode":"7413 RA",
    "sg:province":"Overijssel",
    "wof:name":"Occasion Centrum Van Lindenberg Bv",
    "wof:placetype":"venue"
},
  "geometry": {"coordinates":[6.154228,52.260342],"type":"Point"}
}