{
  "type": "Feature",
  "properties": {
    "addr:full":"Spoorlaan Noord 171 Roermond Limburg 6042  A",
    "addr:housenumber":"171;6042 a",
    "addr:street":"Spoorlaan Noord",
    "iso:country":"NL",
    "sg:address":"Spoorlaan Noord 171",
    "sg:city":"Roermond",
    "sg:orig_category":"Glaszetten",
    "sg:phone":"+31 475 357 247",
    "sg:postcode":"6042  A",
    "sg:province":"Limburg",
    "wof:name":"Kersten",
    "wof:placetype":"venue"
},
  "geometry": {"coordinates":[5.997627,51.197899],"type":"Point"}
}