{
  "type": "Feature",
  "properties": {
    "addr:full":"Raadhuisstraat 3 Gilze Noord-Brabant 5126 CK",
    "addr:housenumber":"3",
    "addr:postcode":"5126 ck",
    "addr:street":"Raadhuisstraat",
    "iso:country":"NL",
    "sg:address":"Raadhuisstraat 3",
    "sg:city":"Gilze",
    "sg:classifiers":[
        {
            "category":"Education",
            "subcategory":"Preschool",
            "type":"Public Place"
        }
    ],
    "sg:phone":"+31 161 455 838",
    "sg:postcode":"5126 CK",
    "sg:province":"Noord-Brabant",
    "sg:tags":[
        "kleuteronderwijs",
        "basis-"
    ],
    "wof:name":"De Wildschut",
    "wof:placetype":"venue"
},
  "geometry": {"coordinates":[4.944012,51.541634],"type":"Point"}
}