{
  "type": "Feature",
  "properties": {
    "addr:full":"Spierdykerwg 105 Spierdyk Noord-Holland 1641 LW",
    "addr:housenumber":"105;1641",
    "addr:postcode":"lw",
    "addr:street":"Spierdyk Noord-Holland",
    "iso:country":"NL",
    "sg:address":"Spierdykerwg 105",
    "sg:city":"Spierdyk",
    "sg:orig_category":"Kantoor- En Interieurbeplanting",
    "sg:phone":"+31 229 563 535",
    "sg:postcode":"1641 LW",
    "sg:province":"Noord-Holland",
    "wof:name":"Zonnetje, 'T",
    "wof:placetype":"venue"
},
  "geometry": {"coordinates":[4.94145298,52.6489181519],"type":"Point"}
}