{
  "type": "Feature",
  "properties": {
    "addr:full":"Hamerstr 22S Edam North Holland 1135 GA",
    "addr:housenumber":"22s",
    "addr:postcode":"1135 ga",
    "addr:street":"Hamerstr",
    "iso:country":"NL",
    "sg:address":"Hamerstr 22S",
    "sg:city":"Edam",
    "sg:orig_category":"Meubelstoffering",
    "sg:phone":"+31 299 372 404",
    "sg:postcode":"1135 GA",
    "sg:province":"North Holland",
    "wof:name":"Onna, Van",
    "wof:placetype":"venue"
},
  "geometry": {"coordinates":[5.038444,52.516041],"type":"Point"}
}