{
  "type": "Feature",
  "properties": {
    "addr:full":"Langeleegte 186 Veendam Groningen 9641 GX",
    "addr:housenumber":"186",
    "addr:postcode":"9641 gx",
    "addr:street":"Langeleegte",
    "iso:country":"NL",
    "sg:address":"Langeleegte 186",
    "sg:city":"Veendam",
    "sg:orig_category":"Fotostudio'S And Fotografen",
    "sg:phone":"+31 598 623 904",
    "sg:postcode":"9641 GX",
    "sg:province":"Groningen",
    "wof:name":"M. Werkman",
    "wof:placetype":"venue"
},
  "geometry": {"coordinates":[6.844931,53.107849],"type":"Point"}
}