{
  "type": "Feature",
  "properties": {
    "addr:full":"Kinkerstr 53 Amsterdam Noord-Holland 1053 DE",
    "addr:housenumber":"53",
    "addr:postcode":"1053 de",
    "addr:street":"Kinkerstr",
    "iso:country":"NL",
    "sg:address":"Kinkerstr 53",
    "sg:city":"Amsterdam",
    "sg:orig_category":"Meubelmakerijen",
    "sg:phone":"+31 20 616 7699",
    "sg:postcode":"1053 DE",
    "sg:province":"Noord-Holland",
    "wof:name":"Koet, M",
    "wof:placetype":"venue"
},
  "geometry": {"coordinates":[4.873004,52.367344],"type":"Point"}
}