{
  "type": "Feature",
  "properties": {
    "addr:full":"Gerritsenwg 3 Zutphen Gelderland 7202 BP",
    "addr:housenumber":"3",
    "addr:postcode":"7202 bp",
    "addr:street":"Gerritsenwg;Gelderland",
    "iso:country":"NL",
    "sg:address":"Gerritsenwg 3",
    "sg:city":"Zutphen",
    "sg:orig_category":"Meubelen",
    "sg:phone":"+31 575 518 166",
    "sg:postcode":"7202 BP",
    "sg:province":"Gelderland",
    "sg:website":"http://www.runnermeubel.nl",
    "wof:name":"Runner",
    "wof:placetype":"venue"
},
  "geometry": {"coordinates":[6.194943,52.150696],"type":"Point"}
}