{
  "type": "Feature",
  "properties": {
    "addr:full":"Koningsweg 2 Alkmaar Noord-Holland 1811 LM",
    "addr:housenumber":"2",
    "addr:postcode":"1811 lm",
    "addr:street":"Koningsweg",
    "iso:country":"NL",
    "sg:address":"Koningsweg 2",
    "sg:city":"Alkmaar",
    "sg:orig_category":"Overheidsdiensten",
    "sg:phone":"+31 72 511 6761",
    "sg:postcode":"1811 LM",
    "sg:province":"Noord-Holland",
    "wof:name":"Stichting Eigen Gebouw",
    "wof:placetype":"venue"
},
  "geometry": {"coordinates":[4.7494587898,52.6328735352],"type":"Point"}
}