{
  "type": "Feature",
  "properties": {
    "addr:full":"Quellijnstraat 117 Amsterdam Noord-Holland 1073 XH",
    "addr:housenumber":"117",
    "addr:postcode":"1073 xh",
    "addr:street":"Quellijnstraat",
    "iso:country":"NL",
    "sg:address":"Quellijnstraat 117",
    "sg:city":"Amsterdam",
    "sg:orig_category":"Diverse Consumentenartikelen Gh",
    "sg:phone":"+31 20 679 9567",
    "sg:postcode":"1073 XH",
    "sg:province":"Noord-Holland",
    "wof:name":"Daheico Bv",
    "wof:placetype":"venue"
},
  "geometry": {"coordinates":[4.893548,52.356743],"type":"Point"}
}