{
  "type": "Feature",
  "properties": {
    "iso:country":"NL",
    "sg:address":"Evertsenstraat 16",
    "sg:city":"Bleiswijk",
    "sg:orig_category":"Bedrijfs- And Managementsconsultants",
    "sg:phone":"+31 10 522 2245",
    "sg:postcode":"2665 AE",
    "sg:province":"South Holland",
    "wof:name":"Stassen O & I Management Bv",
    "wof:placetype":"venue"
},
  "geometry": {"coordinates":[4.528041,52.012947],"type":"Point"}
}