{
  "type": "Feature",
  "properties": {
    "addr:full":"Weteringstraat 42 Valkenswaard North Brabant 5555 KN",
    "addr:housenumber":"42",
    "addr:postcode":"5555 kn",
    "addr:street":"Weteringstraat",
    "iso:country":"NL",
    "sg:address":"Weteringstraat 42",
    "sg:city":"Valkenswaard",
    "sg:orig_category":"Schoonheidssalons",
    "sg:phone":"+31 40 201 7528",
    "sg:postcode":"5555 KN",
    "sg:province":"North Brabant",
    "wof:name":"Schoonheidssalon Camelia",
    "wof:placetype":"venue"
},
  "geometry": {"coordinates":[5.473465,51.351192],"type":"Point"}
}