{
  "type": "Feature",
  "properties": {
    "addr:full":"Cannerwg 60 Maastricht Limburg 6213 BH",
    "addr:housenumber":"60",
    "addr:postcode":"6213 bh",
    "addr:street":"Cannerwg",
    "iso:country":"NL",
    "sg:address":"Cannerwg 60",
    "sg:city":"Maastricht",
    "sg:orig_category":"Administratie- En Boekhoudkantoren",
    "sg:phone":"+31 43 327 0204",
    "sg:postcode":"6213 BH",
    "sg:province":"Limburg",
    "wof:name":"Campus Bv",
    "wof:placetype":"venue"
},
  "geometry": {"coordinates":[5.678319,50.84214],"type":"Point"}
}