{
  "type": "Feature",
  "properties": {
    "addr:full":"K Doormanln 75 Huizen Noord-Holland 1271 CB",
    "addr:housenumber":"75",
    "addr:postcode":"1271 cb",
    "addr:street":"Doormanln",
    "iso:country":"NL",
    "sg:address":"K Doormanln 75",
    "sg:city":"Huizen",
    "sg:orig_category":"Schilders",
    "sg:phone":"+31 35 525 1870",
    "sg:postcode":"1271 CB",
    "sg:province":"Noord-Holland",
    "wof:name":"Boer, W De",
    "wof:placetype":"venue"
},
  "geometry": {"coordinates":[5.226589,52.30048],"type":"Point"}
}