{
  "type": "Feature",
  "properties": {
    "iso:country":"NL",
    "sg:address":"Vooronder 50",
    "sg:city":"Elburg",
    "sg:orig_category":"Apothekers",
    "sg:phone":"+31 525 683 751",
    "sg:postcode":"8081 NM",
    "sg:province":"Gelderland",
    "wof:name":"Apotheek Elburg",
    "wof:placetype":"venue"
},
  "geometry": {"coordinates":[5.854876,52.451122],"type":"Point"}
}