{
  "type": "Feature",
  "properties": {
    "addr:full":"Ringbaan Noord 185 Tilburg Noord-Brabant 5046 AB",
    "addr:housenumber":"185",
    "addr:postcode":"5046 ab",
    "addr:street":"Ringbaan Noord",
    "iso:country":"NL",
    "sg:address":"Ringbaan Noord 185",
    "sg:city":"Tilburg",
    "sg:orig_category":"Boekhouders",
    "sg:phone":"+31 13 460 9999",
    "sg:postcode":"5046 AB",
    "sg:province":"Noord-Brabant",
    "wof:name":"Stichting Onderwijsbureau Midden Brabant",
    "wof:placetype":"venue"
},
  "geometry": {"coordinates":[5.076852,51.576557],"type":"Point"}
}