{
  "type": "Feature",
  "properties": {
    "addr:full":"Plein 1945 50 Ymuiden Noord-Holland 1971 GC",
    "addr:housenumber":"50",
    "addr:postcode":"1971 gc",
    "addr:street":"Plein 1945",
    "iso:country":"NL",
    "sg:address":"Plein 1945 50",
    "sg:city":"Ymuiden",
    "sg:classifiers":[
        {
            "category":"Food & Beverages",
            "subcategory":"Bakery",
            "type":"Retail Goods"
        }
    ],
    "sg:phone":"+31 255 540 049",
    "sg:postcode":"1971 GC",
    "sg:province":"Noord-Holland",
    "sg:tags":[
        "brood",
        "en",
        "banket"
    ],
    "wof:name":"Bastmeijer, W",
    "wof:placetype":"venue"
},
  "geometry": {"coordinates":[4.617625,52.458279],"type":"Point"}
}