{
  "type": "Feature",
  "properties": {
    "iso:country":"NL",
    "sg:address":"Herengr 493",
    "sg:city":"Amsterdam",
    "sg:orig_category":"Bibliotheken Weten- Schappelijke",
    "sg:phone":"+31 20 422 9652",
    "sg:postcode":"1017 BT",
    "sg:province":"North Holland",
    "sg:website":"http://www.ccf.nl",
    "wof:name":"Japanese Library Of Art",
    "wof:placetype":"venue"
},
  "geometry": {"coordinates":[4.891161,52.365688],"type":"Point"}
}