{
  "type": "Feature",
  "properties": {
    "addr:full":"Noordeinde 2B Leiden Zuid-Holland 2311 CD",
    "addr:housenumber":"2b",
    "addr:postcode":"2311 cd",
    "addr:street":"Noordeinde",
    "iso:country":"NL",
    "sg:address":"Noordeinde 2B",
    "sg:city":"Leiden",
    "sg:orig_category":"Bloemen And Planten",
    "sg:phone":"+31 71 514 4074",
    "sg:postcode":"2311 CD",
    "sg:province":"Zuid-Holland",
    "wof:name":"Bloemenkiosk Hans Kanbier",
    "wof:placetype":"venue"
},
  "geometry": {"coordinates":[4.48128,52.160149],"type":"Point"}
}