{
  "type": "Feature",
  "properties": {
    "addr:full":"Oude Leedeweg 193 Pijnacker South Holland 2641 SE",
    "addr:housenumber":"193",
    "addr:postcode":"2641 se",
    "addr:street":"Oude Leedeweg",
    "iso:country":"NL",
    "sg:address":"Oude Leedeweg 193",
    "sg:city":"Pijnacker",
    "sg:orig_category":"Bloemen And Planten",
    "sg:phone":"+31 15 369 3153",
    "sg:postcode":"2641 SE",
    "sg:province":"South Holland",
    "wof:name":"G. De Hoog",
    "wof:placetype":"venue"
},
  "geometry": {"coordinates":[4.41585,51.984455],"type":"Point"}
}