{
  "type": "Feature",
  "properties": {
    "addr:full":"Griegstraat 287 Delft South Holland 2625 AN",
    "addr:housenumber":"287",
    "addr:postcode":"2625 an",
    "addr:street":"Griegstraat",
    "iso:country":"NL",
    "sg:address":"Griegstraat 287",
    "sg:city":"Delft",
    "sg:orig_category":"Kappers",
    "sg:phone":"+31 15 256 6373",
    "sg:postcode":"2625 AN",
    "sg:province":"South Holland",
    "wof:name":"Coiffeur Tom Molier",
    "wof:placetype":"venue"
},
  "geometry": {"coordinates":[4.3414168358,51.9958229065],"type":"Point"}
}