{
  "type": "Feature",
  "properties": {
    "addr:full":"H De Grootln 28 Lochem Gelderland 7241 HM",
    "addr:housenumber":"28",
    "addr:postcode":"7241 hm",
    "addr:street":"Gelderland",
    "iso:country":"NL",
    "sg:address":"H De Grootln 28",
    "sg:city":"Lochem",
    "sg:orig_category":"Juridische Adviseurs",
    "sg:phone":"+31 573 257 006",
    "sg:postcode":"7241 HM",
    "sg:province":"Gelderland",
    "wof:name":"B & L",
    "wof:placetype":"venue"
},
  "geometry": {"coordinates":[6.409836,52.162872],"type":"Point"}
}