{
  "type": "Feature",
  "properties": {
    "addr:full":"Handelsweg 7 Schagerbrug North Holland 1751 HE",
    "addr:housenumber":"7",
    "addr:postcode":"1751 he",
    "addr:street":"Handelsweg",
    "iso:country":"NL",
    "sg:address":"Handelsweg 7",
    "sg:city":"Schagerbrug",
    "sg:orig_category":"Goederenvervoer Over De Weg",
    "sg:phone":"+31 224 571 232",
    "sg:postcode":"1751 HE",
    "sg:province":"North Holland",
    "wof:name":"Containertransport Cok Nierop & Zoon",
    "wof:placetype":"venue"
},
  "geometry": {"coordinates":[4.752462,52.802883],"type":"Point"}
}