{
  "type": "Feature",
  "properties": {
    "iso:country":"NL",
    "sg:address":"Kloosterhof 6",
    "sg:city":"Blaricum",
    "sg:orig_category":"Artsen - Huisartsen",
    "sg:phone":"+31 35 531 4177",
    "sg:postcode":"1261 WK",
    "sg:province":"North Holland",
    "wof:name":"Beltman, M L A",
    "wof:placetype":"venue"
},
  "geometry": {"coordinates":[5.250554,52.270649],"type":"Point"}
}