{
  "type": "Feature",
  "properties": {
    "iso:country":"NL",
    "sg:address":"Kipstr 37",
    "sg:city":"Rotterdam",
    "sg:orig_category":"Verenigingen En Stichtingen",
    "sg:phone":"+31 10 413 0839",
    "sg:postcode":"3011 RS",
    "sg:province":"South Holland",
    "sg:website":"http://www.alzheimer-ned.nl",
    "wof:name":"Alzheimer Ned Afd Rotterdam",
    "wof:placetype":"venue"
},
  "geometry": {"coordinates":[4.491497,51.922943],"type":"Point"}
}