{
  "type": "Feature",
  "properties": {
    "iso:country":"NL",
    "sg:address":"P Lastmankd 2",
    "sg:city":"Amsterdam",
    "sg:orig_category":"Drukkerijen",
    "sg:phone":"+31 20 679 0792",
    "sg:postcode":"1075 KJ",
    "sg:province":"Noord-Holland",
    "wof:name":"Papyro",
    "wof:placetype":"venue"
},
  "geometry": {"coordinates":[4.864008,52.350815],"type":"Point"}
}