{
  "type": "Feature",
  "properties": {
    "addr:full":"Populierenlaan 227 Krimpen A/D Ijssel Zuid-Holland 2925 CS",
    "addr:housenumber":"227;a / d",
    "addr:postcode":"2925 cs",
    "addr:street":"Populierenlaan;Krimpen",
    "iso:country":"NL",
    "sg:address":"Populierenlaan 227",
    "sg:city":"Krimpen A/D Ijssel",
    "sg:orig_category":"Overheidsdiensten",
    "sg:phone":"+31 180 520 435",
    "sg:postcode":"2925 CS",
    "sg:province":"Zuid-Holland",
    "wof:name":"De Amateur Volkstuinvereniging",
    "wof:placetype":"venue"
},
  "geometry": {"coordinates":[4.6214461327,51.9140968323],"type":"Point"}
}