{
  "type": "Feature",
  "properties": {
    "iso:country":"NL",
    "sg:address":"Zilverstraat 95",
    "sg:city":"'S Gravenhage",
    "sg:orig_category":"Diverse Grafische Activiteiten",
    "sg:phone":"+31 70 308 0150",
    "sg:postcode":"2544 EJ",
    "sg:province":"Zuid-Holland",
    "wof:name":"Boekbinderij Bosboom Bv",
    "wof:placetype":"venue"
},
  "geometry": {"coordinates":[4.254614,52.047939],"type":"Point"}
}