{
  "type": "Feature",
  "properties": {
    "addr:full":"Obliehoren 21 Noordwyk Zh Zuid-Holland 2201 VA",
    "addr:housenumber":"21",
    "addr:postcode":"2201",
    "addr:street":"Obliehoren",
    "iso:country":"NL",
    "sg:address":"Obliehoren 21",
    "sg:city":"Noordwyk Zh",
    "sg:classifiers":[
        {
            "category":"Professional",
            "subcategory":"Management & Consulting",
            "type":"Services"
        }
    ],
    "sg:phone":"+31 71 362 3305",
    "sg:postcode":"2201 VA",
    "sg:province":"Zuid-Holland",
    "sg:tags":[
        "relation",
        "adviesbureaus",
        "public"
    ],
    "wof:name":"E-Linkx",
    "wof:placetype":"venue"
},
  "geometry": {"coordinates":[4.443107,52.226665],"type":"Point"}
}