{
  "type": "Feature",
  "properties": {
    "addr:full":"Floresstraat 1 Haarlem Noord-Holland 2022 BB",
    "addr:housenumber":"1",
    "addr:postcode":"2022 bb",
    "addr:street":"Floresstraat",
    "iso:country":"NL",
    "sg:address":"Floresstraat 1",
    "sg:city":"Haarlem",
    "sg:orig_category":"Hypotheken And Hypotheekbanken",
    "sg:phone":"+31 23 525 8884",
    "sg:postcode":"2022 BB",
    "sg:province":"Noord-Holland",
    "wof:name":"De Hypotheker Haarlem Noord",
    "wof:placetype":"venue"
},
  "geometry": {"coordinates":[4.644706,52.399284],"type":"Point"}
}