{
  "type": "Feature",
  "properties": {
    "addr:full":"De Ploeg 16 Berlicum Nb Noord-Brabant 5258 EZ",
    "addr:housenumber":"16",
    "addr:postcode":"5258 ez",
    "addr:street":"De Ploeg",
    "iso:country":"NL",
    "sg:address":"De Ploeg 16",
    "sg:city":"Berlicum Nb",
    "sg:orig_category":"Wegen And Sportterreinen",
    "sg:phone":"+31 73 503 1410",
    "sg:postcode":"5258 EZ",
    "sg:province":"Noord-Brabant",
    "wof:name":"Electrotechn Install & Montage Bedrijf Gebr. Van D",
    "wof:placetype":"venue"
},
  "geometry": {"coordinates":[5.4105100632,51.6735115051],"type":"Point"}
}