{
  "type": "Feature",
  "properties": {
    "addr:full":"Postbus 1012 Alphen Aan Den Ryn Noord-Holland 2400 BA",
    "addr:housenumber":"1012",
    "addr:postcode":"2400 ba",
    "addr:street":"Postbus;Aan Den Ryn",
    "iso:country":"NL",
    "sg:address":"Postbus 1012",
    "sg:city":"Alphen Aan Den Ryn",
    "sg:orig_category":"Adviesbureaus Financieringen",
    "sg:phone":"+31 172 417 502",
    "sg:postcode":"2400 BA",
    "sg:province":"Noord-Holland",
    "wof:name":"Linden, Van Der",
    "wof:placetype":"venue"
},
  "geometry": {"coordinates":[4.68895,52.131088],"type":"Point"}
}