{
  "type": "Feature",
  "properties": {
    "addr:full":"Havenstraat 193 Rotterdam Zuid-Holland 3024 SK",
    "addr:housenumber":"193",
    "addr:street":"Havenstraat;3024",
    "iso:country":"NL",
    "sg:address":"Havenstraat 193",
    "sg:city":"Rotterdam",
    "sg:orig_category":"Diverse Bedrijfsinstallaties Gh",
    "sg:phone":"+31 10 476 5776",
    "sg:postcode":"3024 SK",
    "sg:province":"Zuid-Holland",
    "wof:name":"P.C. De Leeuw",
    "wof:placetype":"venue"
},
  "geometry": {"coordinates":[4.452139,51.905869],"type":"Point"}
}