{
  "type": "Feature",
  "properties": {
    "addr:full":"F Halspln 1B Schiedam South Holland 3117 WD",
    "addr:housenumber":"1b",
    "addr:postcode":"3117 wd",
    "addr:street":"Halspln",
    "iso:country":"NL",
    "sg:address":"F Halspln 1B",
    "sg:city":"Schiedam",
    "sg:orig_category":"Onroerende Goederen",
    "sg:phone":"+31 10 473 3888",
    "sg:postcode":"3117 WD",
    "sg:province":"South Holland",
    "wof:name":"Interstore",
    "wof:placetype":"venue"
},
  "geometry": {"coordinates":[4.38293,51.91304],"type":"Point"}
}