{
  "type": "Feature",
  "properties": {
    "addr:full":"Strypkd 33 S Gravenhage South Holland 2548 AG",
    "addr:housenumber":"33",
    "addr:postcode":"2548",
    "addr:street":"Strypkd;S Gravenhage",
    "iso:country":"NL",
    "sg:address":"Strypkd 33",
    "sg:city":"S Gravenhage",
    "sg:orig_category":"Bejaarden - Verzorgingstehuizen",
    "sg:phone":"+31 70 321 2141",
    "sg:postcode":"2548 AG",
    "sg:province":"South Holland",
    "wof:name":"Waterhof",
    "wof:placetype":"venue"
},
  "geometry": {"coordinates":[4.2901,52.029888],"type":"Point"}
}