{
  "type": "Feature",
  "properties": {
    "addr:full":"Gasthuislaan 10 Winschoten Groningen 9671 JD",
    "addr:housenumber":"10",
    "addr:postcode":"9671 jd",
    "addr:street":"Gasthuislaan",
    "iso:country":"NL",
    "sg:address":"Gasthuislaan 10",
    "sg:city":"Winschoten",
    "sg:orig_category":"Chemische Producten Gh",
    "sg:phone":"+31 597 434 155",
    "sg:postcode":"9671 JD",
    "sg:province":"Groningen",
    "wof:name":"Okayproducts",
    "wof:placetype":"venue"
},
  "geometry": {"coordinates":[7.029386,53.143768],"type":"Point"}
}