{
  "type": "Feature",
  "properties": {
    "iso:country":"NL",
    "sg:address":"Hoefslag 26",
    "sg:city":"Den Burg",
    "sg:orig_category":"Schilders",
    "sg:phone":"+31 222 312 230",
    "sg:postcode":"1791 SC",
    "sg:province":"Noord-Holland",
    "wof:name":"Banda, Guido",
    "wof:placetype":"venue"
},
  "geometry": {"coordinates":[-94.071686,34.232082],"type":"Point"}
}