{
  "type": "Feature",
  "properties": {
    "addr:full":"Kloosterweg 32 Sint Jansklooster Overijssel 8326 CE",
    "addr:housenumber":"32",
    "addr:postcode":"8326 ce",
    "addr:street":"Kloosterweg",
    "iso:country":"NL",
    "sg:address":"Kloosterweg 32",
    "sg:city":"Sint Jansklooster",
    "sg:classifiers":[
        {
            "category":"Education",
            "subcategory":"Preschool",
            "type":"Public Place"
        }
    ],
    "sg:phone":"+31 527 246 431",
    "sg:postcode":"8326 CE",
    "sg:province":"Overijssel",
    "sg:tags":[
        "kleuteronderwijs",
        "basis-"
    ],
    "wof:name":"De Wiedekieker",
    "wof:placetype":"venue"
},
  "geometry": {"coordinates":[6.007061,52.678665],"type":"Point"}
}