{
  "type": "Feature",
  "properties": {
    "addr:full":"Loosterwg 2 Voorhout Zuid-Holland 2215 TL",
    "addr:housenumber":"2",
    "addr:postcode":"2215 tl",
    "addr:street":"Loosterwg",
    "iso:country":"NL",
    "sg:address":"Loosterwg 2",
    "sg:city":"Voorhout",
    "sg:classifiers":[
        {
            "category":"Retail",
            "subcategory":"Auto Repair",
            "type":"Services"
        }
    ],
    "sg:phone":"+31 252 232 010",
    "sg:postcode":"2215 TL",
    "sg:province":"Zuid-Holland",
    "sg:tags":[
        "garage"
    ],
    "wof:name":"Cors",
    "wof:placetype":"venue"
},
  "geometry": {"coordinates":[4.511889,52.242943],"type":"Point"}
}