{
  "type": "Feature",
  "properties": {
    "addr:full":"Zuiderpln 7 Leeuwarden Friesland 8911 AM",
    "addr:housenumber":"7",
    "addr:postcode":"8911",
    "addr:street":"Zuiderpln",
    "iso:country":"NL",
    "sg:address":"Zuiderpln 7",
    "sg:city":"Leeuwarden",
    "sg:orig_category":"Kampeerartikelen",
    "sg:phone":"+31 58 213 4440",
    "sg:postcode":"8911 AM",
    "sg:province":"Friesland",
    "wof:name":"Luxen Adventure",
    "wof:placetype":"venue"
},
  "geometry": {"coordinates":[5.7974538803,53.198135376],"type":"Point"}
}