{
  "type": "Feature",
  "properties": {
    "iso:country":"NL",
    "sg:address":"Jan Van Nassaustraat 62",
    "sg:city":"'S Gravenhage",
    "sg:orig_category":"Zalenexploitatie",
    "sg:phone":"+31 70 328 3644",
    "sg:postcode":"2596 BV",
    "sg:province":"South Holland",
    "wof:name":"Kunstgallery Balance",
    "wof:placetype":"venue"
},
  "geometry": {"coordinates":[4.317469,52.088654],"type":"Point"}
}