{
  "type": "Feature",
  "properties": {
    "iso:country":"NL",
    "sg:address":"De Looijakker 60",
    "sg:city":"Moergestel",
    "sg:orig_category":"Boekhouders",
    "sg:phone":"+31 13 513 3305",
    "sg:postcode":"5066 MT",
    "sg:province":"Noord-Brabant",
    "wof:name":"Administratiekantoor Sprengers",
    "wof:placetype":"venue"
},
  "geometry": {"coordinates":[5.191975,51.546295],"type":"Point"}
}