{
  "type": "Feature",
  "properties": {
    "addr:full":"Beelstr 26 Rotterdam Zuid-Holland 3066 TL",
    "addr:housenumber":"26",
    "addr:postcode":"3066 tl",
    "addr:street":"Beelstr",
    "iso:country":"NL",
    "sg:address":"Beelstr 26",
    "sg:city":"Rotterdam",
    "sg:orig_category":"Verzekeringen - Verzekeringskantoren",
    "sg:phone":"+31 10 455 6933",
    "sg:postcode":"3066 TL",
    "sg:province":"Zuid-Holland",
    "wof:name":"Eureka",
    "wof:placetype":"venue"
},
  "geometry": {"coordinates":[4.554162,51.933361],"type":"Point"}
}