{
  "type": "Feature",
  "properties": {
    "addr:full":"Waagpassage 132 , De Gordiaan Lelystad NL. 8232 DW",
    "addr:housenumber":"132",
    "addr:postcode":"8232 dw",
    "addr:street":"Waagpassage;De Gordiaan;Nl.",
    "iso:country":"NL",
    "sg:address":"Waagpassage 132 , De Gordiaan",
    "sg:city":"Lelystad",
    "sg:orig_category":"Kappers",
    "sg:phone":"+31 320 240 031",
    "sg:postcode":"8232 DW",
    "sg:province":"NL.",
    "wof:name":"Rob'S Knipcorner",
    "wof:placetype":"venue"
},
  "geometry": {"coordinates":[5.474038,52.505688],"type":"Point"}
}