{
  "type": "Feature",
  "properties": {
    "iso:country":"NL",
    "sg:address":"Duin En Dal 1A",
    "sg:city":"Noordwykerhout",
    "sg:orig_category":"Kinderopvang",
    "sg:phone":"+31 252 432 800",
    "sg:postcode":"2211 JP",
    "sg:province":"South Holland",
    "wof:name":"Kinderopvangcentra Noordwijkerhout Skn, St",
    "wof:placetype":"venue"
},
  "geometry": {"coordinates":[4.495063,52.258629],"type":"Point"}
}