{
  "type": "Feature",
  "properties": {
    "addr:full":"Vredenrustlaan 100 Veendam Groningen 9645 NL",
    "addr:housenumber":"100",
    "addr:postcode":"9645 nl",
    "addr:street":"Vredenrustlaan",
    "iso:country":"NL",
    "sg:address":"Vredenrustlaan 100",
    "sg:city":"Veendam",
    "sg:classifiers":[
        {
            "category":"Education",
            "subcategory":"Preschool",
            "type":"Public Place"
        }
    ],
    "sg:phone":"+31 598 613 970",
    "sg:postcode":"9645 NL",
    "sg:province":"Groningen",
    "sg:tags":[
        "kleuteronderwijs",
        "basis-"
    ],
    "wof:name":"Obs Noorderbreedte",
    "wof:placetype":"venue"
},
  "geometry": {"coordinates":[6.875249,53.113018],"type":"Point"}
}