{
  "type": "Feature",
  "properties": {
    "addr:full":"Mgr Boermansstr 29 Venlo Limburg 5911 BA",
    "addr:housenumber":"29",
    "addr:postcode":"5911 ba",
    "addr:street":"Boermansstr",
    "iso:country":"NL",
    "sg:address":"Mgr Boermansstr 29",
    "sg:city":"Venlo",
    "sg:orig_category":"Video - Faciliteiten En Producties",
    "sg:phone":"+31 6 25550284",
    "sg:postcode":"5911 BA",
    "sg:province":"Limburg",
    "wof:name":"Rene",
    "wof:placetype":"venue"
},
  "geometry": {"coordinates":[6.175224,51.370453],"type":"Point"}
}