{
  "type": "Feature",
  "properties": {
    "addr:full":"Papenbeek 2 Well Lb Limburg 5855 BD",
    "addr:housenumber":"2",
    "addr:postcode":"lb;5855 bd",
    "addr:street":"Papenbeek",
    "iso:country":"NL",
    "sg:address":"Papenbeek 2",
    "sg:city":"Well Lb",
    "sg:orig_category":"Banken",
    "sg:phone":"+31 485 550 550",
    "sg:postcode":"5855 BD",
    "sg:province":"Limburg",
    "sg:website":"http://www.rabobank.nl",
    "wof:name":"Rabobank",
    "wof:placetype":"venue"
},
  "geometry": {"coordinates":[-93.129936,36.705662],"type":"Point"}
}