{
  "type": "Feature",
  "properties": {
    "iso:country":"NL",
    "sg:address":"Halstersewg 183",
    "sg:city":"Bergen Op Zoom",
    "sg:orig_category":"Zoetwaren - Fabrieken En Groothandel",
    "sg:phone":"+31 164 211 192",
    "sg:postcode":"4613 AM",
    "sg:province":"Noord-Brabant",
    "wof:name":"Badis Bv",
    "wof:placetype":"venue"
},
  "geometry": {"coordinates":[4.279737,51.507675],"type":"Point"}
}