{
  "type": "Feature",
  "properties": {
    "addr:full":"Tweebosstr 33 Rotterdam South Holland 3072 BL",
    "addr:housenumber":"33",
    "addr:postcode":"3072 bl",
    "addr:street":"Tweebosstr",
    "iso:country":"NL",
    "sg:address":"Tweebosstr 33",
    "sg:city":"Rotterdam",
    "sg:orig_category":"Verenigingen En Stichtingen",
    "sg:phone":"+31 10 484 6497",
    "sg:postcode":"3072 BL",
    "sg:province":"South Holland",
    "wof:name":"Buurtver Tweebosstraat",
    "wof:placetype":"venue"
},
  "geometry": {"coordinates":[4.505461,51.900928],"type":"Point"}
}