{
  "type": "Feature",
  "properties": {
    "addr:full":"Op Den Bosch 5 Baarlo Lb Limburg 5991 NE",
    "addr:housenumber":"5;5991",
    "addr:postcode":"lb;ne",
    "addr:street":"Op Den Bosch",
    "iso:country":"NL",
    "sg:address":"Op Den Bosch 5",
    "sg:city":"Baarlo Lb",
    "sg:orig_category":"Levende Dieren Gh",
    "sg:phone":"+31 77 477 2803",
    "sg:postcode":"5991 NE",
    "sg:province":"Limburg",
    "wof:name":"L.J.G. Thijssen",
    "wof:placetype":"venue"
},
  "geometry": {"coordinates":[6.067409,51.316868],"type":"Point"}
}