{
  "type": "Feature",
  "properties": {
    "addr:full":"Langeland 4 S Gravenhage South Holland 2548 WE",
    "addr:housenumber":"4",
    "addr:postcode":"2548 we",
    "addr:street":"Langeland;S Gravenhage",
    "iso:country":"NL",
    "sg:address":"Langeland 4",
    "sg:city":"S Gravenhage",
    "sg:orig_category":"Plafonds",
    "sg:phone":"+31 6 24676120",
    "sg:postcode":"2548 WE",
    "sg:province":"South Holland",
    "wof:name":"Gulzaar",
    "wof:placetype":"venue"
},
  "geometry": {"coordinates":[4.2901,52.029888],"type":"Point"}
}