{
  "type": "Feature",
  "properties": {
    "iso:country":"NL",
    "sg:address":"Bakenbergsewg 20",
    "sg:city":"Arnhem",
    "sg:orig_category":"Verenigingen En Stichtingen",
    "sg:phone":"+31 26 442 0600",
    "sg:postcode":"6814 MJ",
    "sg:province":"Gelderland",
    "sg:website":"http://www.anbo.nl",
    "wof:name":"Anbo",
    "wof:placetype":"venue"
},
  "geometry": {"coordinates":[5.891018,51.989807],"type":"Point"}
}