{
  "type": "Feature",
  "properties": {
    "iso:country":"NL",
    "sg:address":"Markt 9",
    "sg:city":"Kruiningen",
    "sg:classifiers":[
        {
            "category":"Food & Beverages",
            "subcategory":"Bakery",
            "type":"Retail Goods"
        }
    ],
    "sg:phone":"+31 113 320 303",
    "sg:postcode":"4416 AG",
    "sg:province":"Zeeland",
    "sg:tags":[
        "pizza"
    ],
    "wof:name":"Mem'S",
    "wof:placetype":"venue"
},
  "geometry": {"coordinates":[4.033346,51.449188],"type":"Point"}
}