{
  "type": "Feature",
  "properties": {
    "addr:full":"V Ruysdaelstr 5 Sprang Capelle Noord-Brabant 5161 VJ",
    "addr:housenumber":"5",
    "addr:postcode":"5161 vj",
    "addr:street":"Ruysdaelstr",
    "iso:country":"NL",
    "sg:address":"V Ruysdaelstr 5",
    "sg:city":"Sprang Capelle",
    "sg:orig_category":"Adviesbureaus Bedrijfsorganisatie",
    "sg:phone":"+31 416 334 736",
    "sg:postcode":"5161 VJ",
    "sg:province":"Noord-Brabant",
    "sg:website":"http://www.blace.nl",
    "wof:name":"Blace Bv",
    "wof:placetype":"venue"
},
  "geometry": {"coordinates":[5.02336,51.670841],"type":"Point"}
}