{
  "type": "Feature",
  "properties": {
    "iso:country":"NL",
    "sg:address":"Biggelaar 24",
    "sg:city":"Roosendaal",
    "sg:orig_category":"Zuivelproducten",
    "sg:phone":"+31 165 565 973",
    "sg:postcode":"4701 RA",
    "sg:province":"North Brabant",
    "wof:name":"Jan Bruijns",
    "wof:placetype":"venue"
},
  "geometry": {"coordinates":[4.45782,51.533283],"type":"Point"}
}