{
  "type": "Feature",
  "properties": {
    "addr:full":"Croeseln 295 Utrecht Utrecht 3521 BT",
    "addr:housenumber":"295",
    "addr:postcode":"3521 bt",
    "iso:country":"NL",
    "sg:address":"Croeseln 295",
    "sg:city":"Utrecht",
    "sg:orig_category":"Parketvloeren",
    "sg:phone":"+31 30 293 7545",
    "sg:postcode":"3521 BT",
    "sg:province":"Utrecht",
    "wof:name":"Floorstore",
    "wof:placetype":"venue"
},
  "geometry": {"coordinates":[5.11037,52.084572],"type":"Point"}
}