{
  "type": "Feature",
  "properties": {
    "iso:country":"NL",
    "sg:address":"Pr J W Frisoln 542",
    "sg:city":"Leidschendam",
    "sg:orig_category":"Facilitaire Dienstverlening",
    "sg:phone":"+31 70 327 0086",
    "sg:postcode":"2263 ER",
    "sg:province":"Zuid-Holland",
    "sg:website":"http://www.extrahands.nl",
    "wof:name":"Extra Hands Den Haag",
    "wof:placetype":"venue"
},
  "geometry": {"coordinates":[4.41042,52.10218],"type":"Point"}
}