{
  "type": "Feature",
  "properties": {
    "iso:country":"NL",
    "sg:address":"Slotmakersstraat 24",
    "sg:city":"Makkum Fr",
    "sg:orig_category":"Geluidsopnamen",
    "sg:phone":"+31 515 232 085",
    "sg:postcode":"8754 EM",
    "sg:province":"Friesland",
    "wof:name":"Arie Kuipers Music Productions",
    "wof:placetype":"venue"
},
  "geometry": {"coordinates":[5.401663,53.056316],"type":"Point"}
}