{
  "type": "Feature",
  "properties": {
    "addr:full":"Molenpoort 12 Weert Limburg 6001 HC",
    "addr:housenumber":"12",
    "addr:postcode":"6001 hc",
    "addr:street":"Molenpoort",
    "iso:country":"NL",
    "sg:address":"Molenpoort 12",
    "sg:city":"Weert",
    "sg:orig_category":"Drukkerijen",
    "sg:phone":"+31 495 532 146",
    "sg:postcode":"6001 HC",
    "sg:province":"Limburg",
    "sg:website":"http://www.art-is.nl",
    "wof:name":"Maes",
    "wof:placetype":"venue"
},
  "geometry": {"coordinates":[5.701698,51.25449],"type":"Point"}
}