{
  "type": "Feature",
  "properties": {
    "addr:full":"Industriewg 61 Nunspeet Gelderland 8071 CS",
    "addr:housenumber":"61",
    "addr:postcode":"8071 cs",
    "addr:street":"Industriewg;Gelderland",
    "iso:country":"NL",
    "sg:address":"Industriewg 61",
    "sg:city":"Nunspeet",
    "sg:orig_category":"Machinefabrieken",
    "sg:phone":"+31 341 253 744",
    "sg:postcode":"8071 CS",
    "sg:province":"Gelderland",
    "sg:website":"http://www.aarding.nl",
    "wof:name":"Aarding Special Products Bv",
    "wof:placetype":"venue"
},
  "geometry": {"coordinates":[5.769695,52.368618],"type":"Point"}
}