{
  "type": "Feature",
  "properties": {
    "addr:full":"Lange Dreef 49 Veenendaal Utrecht 3902 AG",
    "addr:housenumber":"49",
    "addr:postcode":"3902",
    "addr:street":"Lange Dreef",
    "iso:country":"NL",
    "sg:address":"Lange Dreef 49",
    "sg:city":"Veenendaal",
    "sg:orig_category":"Bedrijfs- And Managementsconsultants",
    "sg:phone":"+31 318 526 525",
    "sg:postcode":"3902 AG",
    "sg:province":"Utrecht",
    "wof:name":"Strafin",
    "wof:placetype":"venue"
},
  "geometry": {"coordinates":[5.568025,52.034416],"type":"Point"}
}