{
  "type": "Feature",
  "properties": {
    "iso:country":"NL",
    "sg:address":"M V Hongaryedreef 38",
    "sg:city":"Utrecht",
    "sg:orig_category":"Psychologen",
    "sg:phone":"+31 30 266 1848",
    "sg:postcode":"3561 TJ",
    "sg:province":"Utrecht",
    "wof:name":"Laar, A Van",
    "wof:placetype":"venue"
},
  "geometry": {"coordinates":[5.12395,52.11272],"type":"Point"}
}