{
  "type": "Feature",
  "properties": {
    "addr:full":"Theda Mansholtstraat 7H Leiden Zuid-Holland 2331 JE",
    "addr:housenumber":"7h",
    "addr:postcode":"2331 je",
    "addr:street":"Theda Mansholtstraat",
    "iso:country":"NL",
    "sg:address":"Theda Mansholtstraat 7H",
    "sg:city":"Leiden",
    "sg:orig_category":"Paramedische Behandelingen",
    "sg:phone":"+31 71 656 1411",
    "sg:postcode":"2331 JE",
    "sg:province":"Zuid-Holland",
    "wof:name":"Baby Vision",
    "wof:placetype":"venue"
},
  "geometry": {"coordinates":[4.455241,52.150242],"type":"Point"}
}