{
  "type": "Feature",
  "properties": {
    "addr:full":"Tramweg 2 Winschoten Groningen 9672 AT",
    "addr:housenumber":"2",
    "addr:postcode":"9672",
    "addr:street":"Tramweg",
    "iso:country":"NL",
    "sg:address":"Tramweg 2",
    "sg:city":"Winschoten",
    "sg:orig_category":"Keukens",
    "sg:phone":"+31 597 430 268",
    "sg:postcode":"9672 AT",
    "sg:province":"Groningen",
    "sg:website":"http://www.studiotk.nl",
    "wof:name":"Studio Tk",
    "wof:placetype":"venue"
},
  "geometry": {"coordinates":[7.045398,53.140366],"type":"Point"}
}