{
  "type": "Feature",
  "properties": {
    "addr:full":"Folkingestraat 22 Groningen Groningen 9711 JW",
    "addr:housenumber":"22",
    "addr:postcode":"9711 jw",
    "addr:street":"Folkingestraat",
    "iso:country":"NL",
    "sg:address":"Folkingestraat 22",
    "sg:city":"Groningen",
    "sg:orig_category":"Meubelzaken, Woning- And Keukeninrichting",
    "sg:phone":"+31 50 311 2659",
    "sg:postcode":"9711 JW",
    "sg:province":"Groningen",
    "wof:name":"Het Binnenste Buiten",
    "wof:placetype":"venue"
},
  "geometry": {"coordinates":[6.564708,53.216038],"type":"Point"}
}