{
  "type": "Feature",
  "properties": {
    "addr:full":"C De Wittln 45 S Gravenhage Zuid-Holland 2582 AC",
    "addr:housenumber":"45;gravenhage",
    "addr:postcode":"2582 ac",
    "addr:street":"C;S",
    "iso:country":"NL",
    "sg:address":"C De Wittln 45",
    "sg:city":"S Gravenhage",
    "sg:orig_category":"Artsen - Huisartsen",
    "sg:phone":"+31 70 352 1717",
    "sg:postcode":"2582 AC",
    "sg:province":"Zuid-Holland",
    "wof:name":"Schmidt, E F",
    "wof:placetype":"venue"
},
  "geometry": {"coordinates":[4.27852,52.092411],"type":"Point"}
}