{
  "type": "Feature",
  "properties": {
    "addr:full":"Westerwg 60 Purmerend Noord-Holland 1445 AD",
    "addr:housenumber":"60",
    "addr:postcode":"1445 ad",
    "addr:street":"Westerwg",
    "iso:country":"NL",
    "sg:address":"Westerwg 60",
    "sg:city":"Purmerend",
    "sg:classifiers":[
        {
            "category":"Travel",
            "subcategory":"Hotels & Motels",
            "type":"Entertainment"
        }
    ],
    "sg:phone":"+31 299 481 666",
    "sg:postcode":"1445 AD",
    "sg:province":"Noord-Holland",
    "sg:website":"http://www.hampshire-hotels.com",
    "wof:name":"Hampshire Hotel Waterland",
    "wof:placetype":"venue"
},
  "geometry": {"coordinates":[4.993369,52.501003],"type":"Point"}
}