{
  "type": "Feature",
  "properties": {
    "addr:full":"Waterstraat 69 Tiel Gelderland 4001 AN",
    "addr:housenumber":"69",
    "addr:postcode":"4001 an",
    "addr:street":"Waterstraat;Gelderland",
    "iso:country":"NL",
    "sg:address":"Waterstraat 69",
    "sg:city":"Tiel",
    "sg:classifiers":[
        {
            "category":"Shopping",
            "subcategory":"Clothing, Apparel, & Fashions",
            "type":"Retail Goods"
        }
    ],
    "sg:phone":"+31 344 620 660",
    "sg:postcode":"4001 AN",
    "sg:province":"Gelderland",
    "sg:tags":[
        "ondergoed",
        "lingerie"
    ],
    "wof:name":"Livera Lips",
    "wof:placetype":"venue"
},
  "geometry": {"coordinates":[5.430696,51.888096],"type":"Point"}
}