{
  "type": "Feature",
  "properties": {
    "addr:full":"Sixlaan 42 Hillegom Zuid-Holland 2182 AC",
    "addr:housenumber":"42",
    "addr:postcode":"2182 ac",
    "addr:street":"Sixlaan",
    "iso:country":"NL",
    "sg:address":"Sixlaan 42",
    "sg:city":"Hillegom",
    "sg:orig_category":"Vers Brood And Banket Fab",
    "sg:phone":"+31 252 522 165",
    "sg:postcode":"2182 AC",
    "sg:province":"Zuid-Holland",
    "wof:name":"Edel Natuurvoeding",
    "wof:placetype":"venue"
},
  "geometry": {"coordinates":[4.578123,52.298607],"type":"Point"}
}