{
  "type": "Feature",
  "properties": {
    "addr:full":"Bornsestr 1D Hengelo Ov Overijssel 7556 BA",
    "addr:housenumber":"1d",
    "addr:postcode":"7556 ba",
    "addr:street":"Ov",
    "iso:country":"NL",
    "sg:address":"Bornsestr 1D",
    "sg:city":"Hengelo Ov",
    "sg:orig_category":"Webdesign Bureaus",
    "sg:phone":"+31 74 250 8068",
    "sg:postcode":"7556 BA",
    "sg:province":"Overijssel",
    "wof:name":"Pagelink",
    "wof:placetype":"venue"
},
  "geometry": {"coordinates":[6.7915649414,52.2673912048],"type":"Point"}
}