{
  "type": "Feature",
  "properties": {
    "addr:full":"Vryheidsln 11 Valthermond Drenthe 7876 GJ",
    "addr:housenumber":"11",
    "addr:postcode":"7876 gj",
    "addr:street":"Vryheidsln",
    "iso:country":"NL",
    "sg:address":"Vryheidsln 11",
    "sg:city":"Valthermond",
    "sg:orig_category":"Verenigingsgebouwen",
    "sg:phone":"+31 599 662 677",
    "sg:postcode":"7876 GJ",
    "sg:province":"Drenthe",
    "wof:name":"Afdraai, Stich De",
    "wof:placetype":"venue"
},
  "geometry": {"coordinates":[6.948975,52.874722],"type":"Point"}
}