{
  "type": "Feature",
  "properties": {
    "addr:full":"Recollectenstraat 5A Weert Limburg 6001 AJ",
    "addr:housenumber":"5a",
    "addr:postcode":"6001 aj",
    "addr:street":"Recollectenstraat",
    "iso:country":"NL",
    "sg:address":"Recollectenstraat 5A",
    "sg:city":"Weert",
    "sg:orig_category":"Musea And Historische Gebouwen",
    "sg:phone":"+31 495 537 158",
    "sg:postcode":"6001 AJ",
    "sg:province":"Limburg",
    "wof:name":"Museum De Tiendschuur",
    "wof:placetype":"venue"
},
  "geometry": {"coordinates":[5.709404,51.258167],"type":"Point"}
}