{
  "type": "Feature",
  "properties": {
    "addr:full":"Kerkstr 1 Ilpendam Noord-Holland 1452 PR",
    "addr:housenumber":"1",
    "addr:postcode":"1452 pr",
    "addr:street":"Kerkstr",
    "iso:country":"NL",
    "sg:address":"Kerkstr 1",
    "sg:city":"Ilpendam",
    "sg:orig_category":"Verenigingsgebouwen",
    "sg:phone":"+31 20 436 1972",
    "sg:postcode":"1452 PR",
    "sg:province":"Noord-Holland",
    "wof:name":"Party Service Ilpendam",
    "wof:placetype":"venue"
},
  "geometry": {"coordinates":[4.950606,52.463173],"type":"Point"}
}