{
  "type": "Feature",
  "properties": {
    "iso:country":"NL",
    "sg:address":"Bruistensngl 150",
    "sg:city":"S Hertogenbosch",
    "sg:orig_category":"Hypotheken",
    "sg:phone":"+31 73 640 8438",
    "sg:postcode":"5232 AC",
    "sg:province":"North Brabant",
    "wof:name":"Kroon",
    "wof:placetype":"venue"
},
  "geometry": {"coordinates":[5.319015,51.701176],"type":"Point"}
}