{
  "type": "Feature",
  "properties": {
    "addr:full":"Bangkokdreef 157 Utrecht Utrecht 3564 SK",
    "addr:housenumber":"157",
    "addr:postcode":"3564 sk",
    "addr:street":"Bangkokdreef",
    "iso:country":"NL",
    "sg:address":"Bangkokdreef 157",
    "sg:city":"Utrecht",
    "sg:orig_category":"Reinigingsdiensten",
    "sg:phone":"+31 30 266 0744",
    "sg:postcode":"3564 SK",
    "sg:province":"Utrecht",
    "wof:name":"Bright & Shine",
    "wof:placetype":"venue"
},
  "geometry": {"coordinates":[5.104311,52.122826],"type":"Point"}
}