{
  "type": "Feature",
  "properties": {
    "addr:full":"O L Vrouwe Ter Duinenln 48 Ossendrecht Noord-Brabant 4641 HG",
    "addr:housenumber":"48",
    "addr:postcode":"4641 hg",
    "addr:street":"O;Vrouwe",
    "iso:country":"NL",
    "sg:address":"O L Vrouwe Ter Duinenln 48",
    "sg:city":"Ossendrecht",
    "sg:orig_category":"Glas",
    "sg:phone":"+31 164 613 873",
    "sg:postcode":"4641 HG",
    "sg:province":"Noord-Brabant",
    "wof:name":"Veldhoven, P Van",
    "wof:placetype":"venue"
},
  "geometry": {"coordinates":[4.328241,51.396687],"type":"Point"}
}