{
  "type": "Feature",
  "properties": {
    "addr:full":"Wagenmakersstr 13 Vaassen Gelderland 8171 CV",
    "addr:housenumber":"13",
    "addr:postcode":"8171 cv",
    "addr:street":"Wagenmakersstr;Gelderland",
    "iso:country":"NL",
    "sg:address":"Wagenmakersstr 13",
    "sg:city":"Vaassen",
    "sg:orig_category":"Fotojournalisten Freelance",
    "sg:phone":"+31 578 574 765",
    "sg:postcode":"8171 CV",
    "sg:province":"Gelderland",
    "wof:name":"Vlekkert, Hans Van De",
    "wof:placetype":"venue"
},
  "geometry": {"coordinates":[5.970861,52.287983],"type":"Point"}
}