{
  "type": "Feature",
  "properties": {
    "iso:country":"NL",
    "sg:address":"Postbus 151",
    "sg:city":"Aalsmeer",
    "sg:orig_category":"Fietsen En Bromfietsen Onderdelen - Fabr. En Grooth",
    "sg:phone":"+31 297 328 606",
    "sg:postcode":"1430 AD",
    "sg:province":"North Holland",
    "wof:name":"Luma Benelux Bv",
    "wof:placetype":"venue"
},
  "geometry": {"coordinates":[4.749068,52.266991],"type":"Point"}
}