{
  "type": "Feature",
  "properties": {
    "addr:full":"Planetenbaan 27 Maarssen Utrecht 3606 AK",
    "addr:housenumber":"27",
    "addr:postcode":"3606 ak",
    "addr:street":"Planetenbaan",
    "iso:country":"NL",
    "sg:address":"Planetenbaan 27",
    "sg:city":"Maarssen",
    "sg:orig_category":"Scheerapparaten En -Benodigdheden",
    "sg:phone":"+31 346 585 585",
    "sg:postcode":"3606 AK",
    "sg:province":"Utrecht",
    "wof:name":"Wilkinson Sword Bv",
    "wof:placetype":"venue"
},
  "geometry": {"coordinates":[5.037495,52.126568],"type":"Point"}
}