{
  "type": "Feature",
  "properties": {
    "addr:full":"Einsteinstr 21A Veenendaal Utrecht 3902 HN",
    "addr:housenumber":"21a",
    "addr:postcode":"3902 hn",
    "addr:street":"Einsteinstr",
    "iso:country":"NL",
    "sg:address":"Einsteinstr 21A",
    "sg:city":"Veenendaal",
    "sg:orig_category":"Verlichtingsartikelen - Groothandel",
    "sg:phone":"+31 318 655 177",
    "sg:postcode":"3902 HN",
    "sg:province":"Utrecht",
    "wof:name":"Rocalux",
    "wof:placetype":"venue"
},
  "geometry": {"coordinates":[5.568824,52.038113],"type":"Point"}
}