{
  "type": "Feature",
  "properties": {
    "addr:full":"Klarendalseweg 530 Arnhem Gelderland 6822 GZ",
    "addr:housenumber":"530",
    "addr:postcode":"6822 gz",
    "addr:street":"Klarendalseweg",
    "iso:country":"NL",
    "sg:address":"Klarendalseweg 530",
    "sg:city":"Arnhem",
    "sg:orig_category":"Technische Studies And Onderzoek",
    "sg:phone":"+31 26 443 9977",
    "sg:postcode":"6822 GZ",
    "sg:province":"Gelderland",
    "wof:name":"Moy Concept & Design",
    "wof:placetype":"venue"
},
  "geometry": {"coordinates":[5.916035,51.98605],"type":"Point"}
}