{
  "type": "Feature",
  "properties": {
    "addr:full":"Houtvester 27 Leusden Utrecht 3834 CV",
    "addr:housenumber":"27",
    "addr:postcode":"3834 cv",
    "addr:street":"Houtvester",
    "iso:country":"NL",
    "sg:address":"Houtvester 27",
    "sg:city":"Leusden",
    "sg:orig_category":"Adviesbureaus Bedrijfsveiligheid",
    "sg:phone":"+31 33 494 8989",
    "sg:postcode":"3834 CV",
    "sg:province":"Utrecht",
    "wof:name":"Elodea Bv",
    "wof:placetype":"venue"
},
  "geometry": {"coordinates":[5.443989,52.125488],"type":"Point"}
}