{
  "type": "Feature",
  "properties": {
    "addr:full":"Boutensstr 29 Ridderkerk South Holland 2985 CA",
    "addr:housenumber":"29",
    "addr:postcode":"2985 ca",
    "addr:street":"Boutensstr",
    "iso:country":"NL",
    "sg:address":"Boutensstr 29",
    "sg:city":"Ridderkerk",
    "sg:orig_category":"Vertalers",
    "sg:phone":"+31 180 426 059",
    "sg:postcode":"2985 CA",
    "sg:province":"South Holland",
    "wof:name":"Put, P",
    "wof:placetype":"venue"
},
  "geometry": {"coordinates":[4.603372,51.86108],"type":"Point"}
}