{
  "type": "Feature",
  "properties": {
    "iso:country":"NL",
    "sg:address":"Schavenweide 1",
    "sg:city":"Doetinchem",
    "sg:orig_category":"Bejaarden - Verzorgingstehuizen",
    "sg:phone":"+31 314 325 432",
    "sg:postcode":"7003 EA",
    "sg:province":"Gelderland",
    "wof:name":"Markenheem",
    "wof:placetype":"venue"
},
  "geometry": {"coordinates":[6.30189,51.961514],"type":"Point"}
}