{
  "type": "Feature",
  "properties": {
    "addr:full":"Postbus 89 Meerssen Limburg 6230 AB",
    "addr:housenumber":"89",
    "addr:postcode":"6230 ab",
    "addr:street":"Postbus",
    "iso:country":"NL",
    "sg:address":"Postbus 89",
    "sg:city":"Meerssen",
    "sg:orig_category":"Elektronica - Ontwikkeling En Groothandel",
    "sg:phone":"+31 43 364 9330",
    "sg:postcode":"6230 AB",
    "sg:province":"Limburg",
    "wof:name":"Fade Bv",
    "wof:placetype":"venue"
},
  "geometry": {"coordinates":[5.753205,50.885006],"type":"Point"}
}