{
  "type": "Feature",
  "properties": {
    "addr:full":"Delflandplein 24A Amsterdam Noord-Holland 1062 HR",
    "addr:housenumber":"24a",
    "addr:postcode":"1062 hr",
    "addr:street":"Delflandplein",
    "iso:country":"NL",
    "sg:address":"Delflandplein 24A",
    "sg:city":"Amsterdam",
    "sg:orig_category":"Advocaten And Juridische Adviseurs",
    "sg:phone":"+31 20 669 8909",
    "sg:postcode":"1062 HR",
    "sg:province":"Noord-Holland",
    "wof:name":"Van Deijk Jaasma Advocaten",
    "wof:placetype":"venue"
},
  "geometry": {"coordinates":[4.839793,52.349812],"type":"Point"}
}