{
  "type": "Feature",
  "properties": {
    "addr:full":"Grasmeent 77 Almere Flevoland 1357 JJ",
    "addr:housenumber":"77",
    "addr:postcode":"1357 jj",
    "addr:street":"Grasmeent;Flevoland",
    "iso:country":"NL",
    "sg:address":"Grasmeent 77",
    "sg:city":"Almere",
    "sg:orig_category":"Bedrijfsopleidingen",
    "sg:phone":"+31 36 540 0355",
    "sg:postcode":"1357 JJ",
    "sg:province":"Flevoland",
    "wof:name":"Fundamental Coaching",
    "wof:placetype":"venue"
},
  "geometry": {"coordinates":[5.241126,52.334995],"type":"Point"}
}