{
  "type": "Feature",
  "properties": {
    "addr:full":"De Elzen 66 Veenwouden Provincie Friesland 9269 SK",
    "addr:housenumber":"66;9269",
    "addr:street":"De Elzen;Provincie Friesland",
    "iso:country":"NL",
    "sg:address":"De Elzen 66",
    "sg:city":"Veenwouden",
    "sg:orig_category":"Kinderopvang",
    "sg:phone":"+31 511 477 136",
    "sg:postcode":"9269 SK",
    "sg:province":"Provincie Friesland",
    "wof:name":"Nof",
    "wof:placetype":"venue"
},
  "geometry": {"coordinates":[5.994463,53.243931],"type":"Point"}
}