{
  "type": "Feature",
  "properties": {
    "iso:country":"NL",
    "sg:address":"Ruysdaelkd 161",
    "sg:city":"Amsterdam",
    "sg:orig_category":"Horecabenodigdheden",
    "sg:phone":"+31 20 676 9146",
    "sg:postcode":"1072 AS",
    "sg:province":"Noord-Holland",
    "wof:name":"Vanilla Venture",
    "wof:placetype":"venue"
},
  "geometry": {"coordinates":[4.89067,52.354012],"type":"Point"}
}