{
  "type": "Feature",
  "properties": {
    "addr:full":"Kuilenrode 13 Hooge Mierde North Brabant 5095 BA",
    "addr:housenumber":"13",
    "addr:postcode":"5095 ba",
    "addr:street":"Kuilenrode",
    "iso:country":"NL",
    "sg:address":"Kuilenrode 13",
    "sg:city":"Hooge Mierde",
    "sg:orig_category":"Elektronische Bedrijfsinstallaties",
    "sg:phone":"+31 13 509 3013",
    "sg:postcode":"5095 BA",
    "sg:province":"North Brabant",
    "wof:name":"Cosec",
    "wof:placetype":"venue"
},
  "geometry": {"coordinates":[5.13108,51.396851],"type":"Point"}
}