{
  "type": "Feature",
  "properties": {
    "addr:full":"F Hendrikln 5A Alkmaar Noord-Holland 1814 JM",
    "addr:housenumber":"5a",
    "addr:postcode":"1814 jm",
    "iso:country":"NL",
    "sg:address":"F Hendrikln 5A",
    "sg:city":"Alkmaar",
    "sg:orig_category":"Bloemen En Planten - Decoratie",
    "sg:phone":"+31 72 511 0481",
    "sg:postcode":"1814 JM",
    "sg:province":"Noord-Holland",
    "wof:name":"Helianthus",
    "wof:placetype":"venue"
},
  "geometry": {"coordinates":[4.746258,52.634361],"type":"Point"}
}