{
  "type": "Feature",
  "properties": {
    "addr:full":"Hoogoorddreef 56 Amsterdam Zuidoost Noord-Holland 1101 BE",
    "addr:housenumber":"56",
    "addr:postcode":"zuidoost;1101",
    "addr:street":"Hoogoorddreef",
    "iso:country":"NL",
    "sg:address":"Hoogoorddreef 56",
    "sg:city":"Amsterdam Zuidoost",
    "sg:orig_category":"Verzekerings- Maatschappijen",
    "sg:phone":"+31 20 651 5253",
    "sg:postcode":"1101 BE",
    "sg:province":"Noord-Holland",
    "sg:website":"http://www.europeesche.nl",
    "wof:name":"Europeesche",
    "wof:placetype":"venue"
},
  "geometry": {"coordinates":[4.946158,52.311077],"type":"Point"}
}