{
  "type": "Feature",
  "properties": {
    "iso:country":"NL",
    "sg:address":"Oudenoord 123",
    "sg:city":"Utrecht",
    "sg:orig_category":"Hypotheken",
    "sg:phone":"+31 30 236 8480",
    "sg:postcode":"3513 EM",
    "sg:province":"Utrecht",
    "sg:website":"http://www.rendementadviesgroep.nl",
    "wof:name":"Rendement Adviesgroep",
    "wof:placetype":"venue"
},
  "geometry": {"coordinates":[5.112529,52.097672],"type":"Point"}
}