{
  "type": "Feature",
  "properties": {
    "addr:full":"Mr J Heemskerkstr 2 Heemstede North Holland 2104 XE",
    "addr:housenumber":"2",
    "addr:postcode":"2104 xe",
    "addr:street":"Mr J Heemskerkstr",
    "iso:country":"NL",
    "sg:address":"Mr J Heemskerkstr 2",
    "sg:city":"Heemstede",
    "sg:orig_category":"Kappers",
    "sg:phone":"+31 23 528 1931",
    "sg:postcode":"2104 XE",
    "sg:province":"North Holland",
    "wof:name":"Trendline",
    "wof:placetype":"venue"
},
  "geometry": {"coordinates":[4.613651,52.332279],"type":"Point"}
}