{
  "type": "Feature",
  "properties": {
    "addr:full":"Pr Ireneln 208 Ryswyk Zh Zuid-Holland 2285 GB",
    "addr:housenumber":"208",
    "addr:postcode":"2285 gb",
    "addr:street":"Ryswyk",
    "iso:country":"NL",
    "sg:address":"Pr Ireneln 208",
    "sg:city":"Ryswyk Zh",
    "sg:orig_category":"Postkantoren",
    "sg:phone":"+31 70 394 8891",
    "sg:postcode":"2285 GB",
    "sg:province":"Zuid-Holland",
    "sg:website":"http://www.postkantoor.nl",
    "wof:name":"Postkantoor",
    "wof:placetype":"venue"
},
  "geometry": {"coordinates":[4.32436,52.037251],"type":"Point"}
}