{
  "type": "Feature",
  "properties": {
    "addr:full":"Dorpsstr 677 Assendelft Noord-Holland 1566 EC",
    "addr:housenumber":"677",
    "addr:postcode":"1566 ec",
    "iso:country":"NL",
    "sg:address":"Dorpsstr 677",
    "sg:city":"Assendelft",
    "sg:orig_category":"Beeldende Kunstenaars",
    "sg:phone":"+31 75 687 4105",
    "sg:postcode":"1566 EC",
    "sg:province":"Noord-Holland",
    "wof:name":"Neelen, B",
    "wof:placetype":"venue"
},
  "geometry": {"coordinates":[4.750752,52.480076],"type":"Point"}
}