{
  "type": "Feature",
  "properties": {
    "addr:full":"Jericholn 73 Eindhoven Noord-Brabant 5625 TG",
    "addr:housenumber":"73",
    "addr:postcode":"5625 tg",
    "addr:street":"Jericholn",
    "iso:country":"NL",
    "sg:address":"Jericholn 73",
    "sg:city":"Eindhoven",
    "sg:orig_category":"Beeldende Kunstenaars",
    "sg:phone":"+31 40 242 3009",
    "sg:postcode":"5625 TG",
    "sg:province":"Noord-Brabant",
    "wof:name":"Mierlo, P P J Van",
    "wof:placetype":"venue"
},
  "geometry": {"coordinates":[5.47419,51.471748],"type":"Point"}
}