{
  "type": "Feature",
  "properties": {
    "addr:full":"Hoofdstraat Winsum 70 Winsum Gn Groningen 9951 AC",
    "addr:housenumber":"70",
    "addr:postcode":"gn;9951 ac",
    "addr:street":"Hoofdstraat Winsum",
    "iso:country":"NL",
    "sg:address":"Hoofdstraat Winsum 70",
    "sg:city":"Winsum Gn",
    "sg:orig_category":"Overheidsdiensten",
    "sg:phone":"+31 595 447 777",
    "sg:postcode":"9951 AC",
    "sg:province":"Groningen",
    "wof:name":"Gemeente Winsum",
    "wof:placetype":"venue"
},
  "geometry": {"coordinates":[6.5159859657,53.3286094666],"type":"Point"}
}