{
  "type": "Feature",
  "properties": {
    "addr:full":"Amsterdamsestraatweg 42 Baarn Utrecht 3741 GS",
    "addr:housenumber":"42",
    "addr:postcode":"3741 gs",
    "addr:street":"Amsterdamsestraatweg",
    "iso:country":"NL",
    "sg:address":"Amsterdamsestraatweg 42",
    "sg:city":"Baarn",
    "sg:orig_category":"Benzinestations And Brandstoffen",
    "sg:phone":"+31 35 541 4579",
    "sg:postcode":"3741 GS",
    "sg:province":"Utrecht",
    "wof:name":"Shell",
    "wof:placetype":"venue"
},
  "geometry": {"coordinates":[5.262687,52.218475],"type":"Point"}
}