{
  "type": "Feature",
  "properties": {
    "addr:full":"De S Lohmanln 12 Zeist Utrecht 3705 CM",
    "addr:housenumber":"12",
    "addr:postcode":"3705 cm",
    "addr:street":"De",
    "iso:country":"NL",
    "sg:address":"De S Lohmanln 12",
    "sg:city":"Zeist",
    "sg:orig_category":"Luchtreclame",
    "sg:phone":"+31 30 699 3350",
    "sg:postcode":"3705 CM",
    "sg:province":"Utrecht",
    "sg:website":"http://www.adlin.nl",
    "wof:name":"Adlin Zepvertising",
    "wof:placetype":"venue"
},
  "geometry": {"coordinates":[5.24387,52.08548],"type":"Point"}
}