{
  "type": "Feature",
  "properties": {
    "addr:full":"Produktiewg 9 Alphen Aan Den Ryn South Holland 2404 CC",
    "addr:housenumber":"9",
    "addr:postcode":"2404 cc",
    "addr:street":"Produktiewg;Aan Den Ryn",
    "iso:country":"NL",
    "sg:address":"Produktiewg 9",
    "sg:city":"Alphen Aan Den Ryn",
    "sg:orig_category":"Metaalbewerking",
    "sg:phone":"+31 172 432 256",
    "sg:postcode":"2404 CC",
    "sg:province":"South Holland",
    "sg:website":"http://www.afa-bv.nl",
    "wof:name":"Afa Bv",
    "wof:placetype":"venue"
},
  "geometry": {"coordinates":[4.643094,52.132183],"type":"Point"}
}