{
  "type": "Feature",
  "properties": {
    "addr:full":"Ln V Niftarlake 7 Tienhoven Ut Utrecht 3612 BK",
    "addr:housenumber":"7",
    "addr:postcode":"3612 bk",
    "addr:street":"Ln;Niftarlake",
    "iso:country":"NL",
    "sg:address":"Ln V Niftarlake 7",
    "sg:city":"Tienhoven Ut",
    "sg:orig_category":"Adviesbureaus Bedrijfsorganisatie",
    "sg:phone":"+31 346 282 116",
    "sg:postcode":"3612 BK",
    "sg:province":"Utrecht",
    "wof:name":"Fratomex",
    "wof:placetype":"venue"
},
  "geometry": {"coordinates":[5.08764,52.161224],"type":"Point"}
}