{
  "type": "Feature",
  "properties": {
    "addr:full":"Sluiskade 1 Broek Op Langedijk North Holland 1721 CB",
    "addr:housenumber":"1",
    "addr:postcode":"1721 cb",
    "addr:street":"Sluiskade",
    "iso:country":"NL",
    "sg:address":"Sluiskade 1",
    "sg:city":"Broek Op Langedijk",
    "sg:orig_category":"Fruit And Groenten Gh",
    "sg:phone":"+31 226 313 981",
    "sg:postcode":"1721 CB",
    "sg:province":"North Holland",
    "wof:name":"Glas Groenten",
    "wof:placetype":"venue"
},
  "geometry": {"coordinates":[4.807541,52.674812],"type":"Point"}
}