{
  "type": "Feature",
  "properties": {
    "iso:country":"NL",
    "sg:address":"It Fabryk 1",
    "sg:city":"Lollum",
    "sg:orig_category":"Foerage",
    "sg:phone":"+31 517 469 131",
    "sg:postcode":"8823 SZ",
    "sg:province":"Provincie Friesland",
    "wof:name":"Politiek, K",
    "wof:placetype":"venue"
},
  "geometry": {"coordinates":[5.533692,53.123528],"type":"Point"}
}