{
  "type": "Feature",
  "properties": {
    "addr:full":"Anthony Fokkerweg 15 Amsterdam Noord-Holland 1059 CM",
    "addr:housenumber":"15",
    "addr:postcode":"1059 cm",
    "addr:street":"Anthony Fokkerweg",
    "iso:country":"NL",
    "sg:address":"Anthony Fokkerweg 15",
    "sg:city":"Amsterdam",
    "sg:orig_category":"Beveiligingsdiensten And Bewakingsbedrijven",
    "sg:phone":"+31 20 617 1215",
    "sg:postcode":"1059 CM",
    "sg:province":"Noord-Holland",
    "wof:name":"Master Security Bv",
    "wof:placetype":"venue"
},
  "geometry": {"coordinates":[4.841985,52.343616],"type":"Point"}
}