{
  "type": "Feature",
  "properties": {
    "addr:full":"Kennemerln 184 Ymuiden North Holland 1972 ET",
    "addr:housenumber":"184",
    "addr:postcode":"1972 et",
    "addr:street":"Ymuiden North",
    "iso:country":"NL",
    "sg:address":"Kennemerln 184",
    "sg:city":"Ymuiden",
    "sg:orig_category":"Kappers",
    "sg:phone":"+31 255 514 825",
    "sg:postcode":"1972 ET",
    "sg:province":"North Holland",
    "wof:name":"Pier\u00f4t",
    "wof:placetype":"venue"
},
  "geometry": {"coordinates":[4.612144,52.459663],"type":"Point"}
}