{
  "type": "Feature",
  "properties": {
    "addr:full":"Leidsestr 89-93 Amsterdam Noord-Holland 1017 NZ",
    "addr:housenumber":"89-93",
    "addr:postcode":"1017 nz",
    "iso:country":"NL",
    "sg:address":"Leidsestr 89-93",
    "sg:city":"Amsterdam",
    "sg:orig_category":"Boeken En Tijdschriften",
    "sg:phone":"+31 20 622 0578",
    "sg:postcode":"1017 NZ",
    "sg:province":"Noord-Holland",
    "sg:website":"http://www.bruna.nl",
    "wof:name":"Bruna",
    "wof:placetype":"venue"
},
  "geometry": {"coordinates":[4.884145,52.364704],"type":"Point"}
}