{
  "type": "Feature",
  "properties": {
    "addr:full":"Bastionwg 30 Bergen Op Zoom North Brabant 4614 RM",
    "addr:housenumber":"30",
    "addr:postcode":"4614 rm",
    "addr:street":"Bastionwg",
    "iso:country":"NL",
    "sg:address":"Bastionwg 30",
    "sg:city":"Bergen Op Zoom",
    "sg:orig_category":"Fitnesscentra",
    "sg:phone":"+31 164 210 000",
    "sg:postcode":"4614 RM",
    "sg:province":"North Brabant",
    "sg:website":"http://www.fitnessfirst.com",
    "wof:name":"Fitness First",
    "wof:placetype":"venue"
},
  "geometry": {"coordinates":[4.306128,51.505047],"type":"Point"}
}