{
  "type": "Feature",
  "properties": {
    "iso:country":"NL",
    "sg:address":"Sandenburg 47",
    "sg:city":"Vlissingen",
    "sg:orig_category":"Loonbedrijven",
    "sg:phone":"+31 118 476 893",
    "sg:postcode":"4385 GC",
    "sg:province":"Zeeland",
    "wof:name":"Gelder Services, Van",
    "wof:placetype":"venue"
},
  "geometry": {"coordinates":[3.573878,51.462692],"type":"Point"}
}