{
  "type": "Feature",
  "properties": {
    "addr:full":"De Omloop 10 Oldehove Groningen 9883 PW",
    "addr:housenumber":"10",
    "addr:postcode":"9883 pw",
    "addr:street":"De Omloop",
    "iso:country":"NL",
    "sg:address":"De Omloop 10",
    "sg:city":"Oldehove",
    "sg:classifiers":[
        {
            "category":"Education",
            "subcategory":"Preschool",
            "type":"Public Place"
        }
    ],
    "sg:phone":"+31 594 591 750",
    "sg:postcode":"9883 PW",
    "sg:province":"Groningen",
    "sg:tags":[
        "kleuteronderwijs",
        "basis-"
    ],
    "wof:name":"Gereformeerde School Onder De Wieken",
    "wof:placetype":"venue"
},
  "geometry": {"coordinates":[6.397499,53.302742],"type":"Point"}
}