{
  "type": "Feature",
  "properties": {
    "addr:full":"Reiger 42 Raalte Overijssel 8103 AX",
    "addr:housenumber":"42",
    "addr:postcode":"8103 ax",
    "addr:street":"Reiger",
    "iso:country":"NL",
    "sg:address":"Reiger 42",
    "sg:city":"Raalte",
    "sg:orig_category":"Begrafenisverzorging",
    "sg:phone":"+31 572 356 671",
    "sg:postcode":"8103 AX",
    "sg:province":"Overijssel",
    "wof:name":"Brussel, Berna Van",
    "wof:placetype":"venue"
},
  "geometry": {"coordinates":[6.293409,52.391117],"type":"Point"}
}