{
  "type": "Feature",
  "properties": {
    "addr:full":"V Beethovenln 37 Losser Overijssel 7582 EL",
    "addr:housenumber":"37",
    "addr:postcode":"7582 el",
    "iso:country":"NL",
    "sg:address":"V Beethovenln 37",
    "sg:city":"Losser",
    "sg:orig_category":"Autorijscholen",
    "sg:phone":"+31 53 536 0006",
    "sg:postcode":"7582 EL",
    "sg:province":"Overijssel",
    "wof:name":"Olav Fijen",
    "wof:placetype":"venue"
},
  "geometry": {"coordinates":[7.005806,52.261173],"type":"Point"}
}