{
  "type": "Feature",
  "properties": {
    "addr:full":"Spittaalstr 34 Zutphen Gelderland 7201 EE",
    "addr:housenumber":"34",
    "addr:postcode":"7201 ee",
    "addr:street":"Spittaalstr;Gelderland",
    "iso:country":"NL",
    "sg:address":"Spittaalstr 34",
    "sg:city":"Zutphen",
    "sg:orig_category":"Fietsen En Bromfietsen",
    "sg:phone":"+31 575 519 526",
    "sg:postcode":"7201 EE",
    "sg:province":"Gelderland",
    "wof:name":"Bleumink",
    "wof:placetype":"venue"
},
  "geometry": {"coordinates":[6.199562,52.138039],"type":"Point"}
}