{
  "type": "Feature",
  "properties": {
    "addr:full":"Keizersweg 41 Holten Overijssel 7451 PH",
    "addr:housenumber":"41",
    "addr:postcode":"7451",
    "addr:street":"Keizersweg",
    "iso:country":"NL",
    "sg:address":"Keizersweg 41",
    "sg:city":"Holten",
    "sg:orig_category":"Goederenvervoer Over De Weg",
    "sg:phone":"+31 548 363 335",
    "sg:postcode":"7451 PH",
    "sg:province":"Overijssel",
    "wof:name":"A. Muller Logistic Services Bv",
    "wof:placetype":"venue"
},
  "geometry": {"coordinates":[6.409953,52.281067],"type":"Point"}
}