{
  "type": "Feature",
  "properties": {
    "addr:full":"Herbenusstr 73 Maastricht Limburg 6211 RB",
    "addr:housenumber":"73",
    "addr:postcode":"6211 rb",
    "addr:street":"Herbenusstr",
    "iso:country":"NL",
    "sg:address":"Herbenusstr 73",
    "sg:city":"Maastricht",
    "sg:orig_category":"Fotoarchieven",
    "sg:phone":"+31 43 325 7757",
    "sg:postcode":"6211 RB",
    "sg:province":"Limburg",
    "wof:name":"Tutkey",
    "wof:placetype":"venue"
},
  "geometry": {"coordinates":[5.682702,50.852089],"type":"Point"}
}