{
  "type": "Feature",
  "properties": {
    "iso:country":"NL",
    "sg:address":"Revelsant 80",
    "sg:city":"Emmeloord",
    "sg:orig_category":"Verenigingen En Stichtingen",
    "sg:phone":"+31 527 697 369",
    "sg:postcode":"8303 ZD",
    "sg:province":"Flevoland",
    "wof:name":"Welzijn Ouderen",
    "wof:placetype":"venue"
},
  "geometry": {"coordinates":[5.735336,52.706146],"type":"Point"}
}