{
  "type": "Feature",
  "properties": {
    "addr:full":"Nijverheidsweg 15 Heemstede Noord-Holland 2102 LJ",
    "addr:housenumber":"15",
    "addr:postcode":"2102 lj",
    "addr:street":"Nijverheidsweg",
    "iso:country":"NL",
    "sg:address":"Nijverheidsweg 15",
    "sg:city":"Heemstede",
    "sg:orig_category":"Fotografische And Optische Artikelen Gh",
    "sg:phone":"+31 23 523 2700",
    "sg:postcode":"2102 LJ",
    "sg:province":"Noord-Holland",
    "wof:name":"Friederichs Bv",
    "wof:placetype":"venue"
},
  "geometry": {"coordinates":[4.627504,52.34642],"type":"Point"}
}