{
  "type": "Feature",
  "properties": {
    "addr:full":"Rijndijk 2 Pannerden Gelderland 6911 KA",
    "addr:housenumber":"2",
    "addr:postcode":"6911 ka",
    "addr:street":"Rijndijk;Gelderland",
    "iso:country":"NL",
    "sg:address":"Rijndijk 2",
    "sg:city":"Pannerden",
    "sg:classifiers":[
        {
            "category":"Retail",
            "subcategory":"Storage",
            "type":"Services"
        }
    ],
    "sg:phone":"+31 316 371 296",
    "sg:postcode":"6911 KA",
    "sg:province":"Gelderland",
    "sg:tags":[
        "opslag",
        "bewaring"
    ],
    "wof:name":"A.M.J.J. Hulshoff Bv",
    "wof:placetype":"venue"
},
  "geometry": {"coordinates":[6.0536527634,51.8854637146],"type":"Point"}
}