{
  "type": "Feature",
  "properties": {
    "addr:full":"Jan Dorrekenskade-Oost 102 Waddinxveen South Holland 2741 HX",
    "addr:housenumber":"102",
    "addr:postcode":"2741 hx",
    "addr:street":"Jan Dorrekenskade-Oost",
    "iso:country":"NL",
    "sg:address":"Jan Dorrekenskade-Oost 102",
    "sg:city":"Waddinxveen",
    "sg:orig_category":"Goederenvervoer Over De Weg",
    "sg:phone":"+31 182 612 815",
    "sg:postcode":"2741 HX",
    "sg:province":"South Holland",
    "wof:name":"A Van Nielen & Zn Vof",
    "wof:placetype":"venue"
},
  "geometry": {"coordinates":[4.657761,52.042473],"type":"Point"}
}