{
  "type": "Feature",
  "properties": {
    "iso:country":"NL",
    "sg:address":"Onderste Sittarderweg 2",
    "sg:city":"Limbricht",
    "sg:orig_category":"Kinderopvang Behalve Thuis",
    "sg:phone":"+31 46 458 1748",
    "sg:postcode":"6141 AZ",
    "sg:province":"Limburg",
    "wof:name":"Medisch Kleuterdagverblijf Limbricht",
    "wof:placetype":"venue"
},
  "geometry": {"coordinates":[5.844205,51.012341],"type":"Point"}
}