{
  "type": "Feature",
  "properties": {
    "iso:country":"NL",
    "sg:address":"Stevenswg 10",
    "sg:city":"Vyfhuizen",
    "sg:orig_category":"Adviesbureaus Bedrijfsorganisatie",
    "sg:phone":"+31 23 558 1824",
    "sg:postcode":"2141 VL",
    "sg:province":"Noord-Holland",
    "wof:name":"Grijsen Bv",
    "wof:placetype":"venue"
},
  "geometry": {"coordinates":[4.686567,52.350079],"type":"Point"}
}