{
  "type": "Feature",
  "properties": {
    "addr:full":"Birkholm 214 Hoofddorp Noord-Holland 2133 CK",
    "addr:housenumber":"214",
    "addr:postcode":"2133 ck",
    "addr:street":"Birkholm",
    "iso:country":"NL",
    "sg:address":"Birkholm 214",
    "sg:city":"Hoofddorp",
    "sg:orig_category":"Luchtvrachtexpediteurs",
    "sg:phone":"+31 23 561 1874",
    "sg:postcode":"2133 CK",
    "sg:province":"Noord-Holland",
    "sg:website":"http://www.abaircargo.nl",
    "wof:name":"A & B Services",
    "wof:placetype":"venue"
},
  "geometry": {"coordinates":[4.670593,52.307438],"type":"Point"}
}