{
  "type": "Feature",
  "properties": {
    "addr:full":"Coendersborgstr 5 Almere Flevoland 1333 VN",
    "addr:housenumber":"5",
    "addr:postcode":"1333 vn",
    "addr:street":"Coendersborgstr;Flevoland",
    "iso:country":"NL",
    "sg:address":"Coendersborgstr 5",
    "sg:city":"Almere",
    "sg:orig_category":"Projectontwikkeling",
    "sg:phone":"+31 36 532 5704",
    "sg:postcode":"1333 VN",
    "sg:province":"Flevoland",
    "wof:name":"3Bmda",
    "wof:placetype":"venue"
},
  "geometry": {"coordinates":[5.26918,52.391933],"type":"Point"}
}