{
  "type": "Feature",
  "properties": {
    "addr:full":"Slotlaan 44 Zeist Utrecht 3701 GM",
    "addr:housenumber":"44",
    "addr:postcode":"3701 gm",
    "addr:street":"Slotlaan",
    "iso:country":"NL",
    "sg:address":"Slotlaan 44",
    "sg:city":"Zeist",
    "sg:orig_category":"Juweliers",
    "sg:phone":"+31 30 692 5454",
    "sg:postcode":"3701 GM",
    "sg:province":"Utrecht",
    "wof:name":"Nico Heijkoop Juwelier Zeist Bv",
    "wof:placetype":"venue"
},
  "geometry": {"coordinates":[5.241271,52.083061],"type":"Point"}
}