{
  "type": "Feature",
  "properties": {
    "addr:full":"Krokussenstraat 1 Volendam North Holland 1131 LJ",
    "addr:housenumber":"1",
    "addr:postcode":"1131 lj",
    "addr:street":"Krokussenstraat",
    "iso:country":"NL",
    "sg:address":"Krokussenstraat 1",
    "sg:city":"Volendam",
    "sg:orig_category":"Wasserettes And Stomerijen",
    "sg:phone":"+31 299 320 051",
    "sg:postcode":"1131 LJ",
    "sg:province":"North Holland",
    "wof:name":"Stomerij Wasserij 'T Wasbeertje",
    "wof:placetype":"venue"
},
  "geometry": {"coordinates":[5.0717630386,52.4997787476],"type":"Point"}
}