{
  "type": "Feature",
  "properties": {
    "addr:full":"Burchtstraat 1 Aardenburg Zeeland 4527 CH",
    "addr:housenumber":"1",
    "addr:postcode":"4527",
    "addr:street":"Burchtstraat",
    "iso:country":"NL",
    "sg:address":"Burchtstraat 1",
    "sg:city":"Aardenburg",
    "sg:orig_category":"Schilderwerk",
    "sg:phone":"+31 117 491 925",
    "sg:postcode":"4527 CH",
    "sg:province":"Zeeland",
    "wof:name":"Schildersbedrijf J.W. Pieters",
    "wof:placetype":"venue"
},
  "geometry": {"coordinates":[3.446974,51.272438],"type":"Point"}
}