{
  "type": "Feature",
  "properties": {
    "iso:country":"NL",
    "sg:address":"Engwg 24E",
    "sg:city":"Driebergen Rysenb",
    "sg:orig_category":"Verenigingsgebouwen",
    "sg:phone":"+31 343 520 573",
    "sg:postcode":"3972 JH",
    "sg:province":"Utrecht",
    "wof:name":"Nix Multifunctioneel Centrum",
    "wof:placetype":"venue"
},
  "geometry": {"coordinates":[5.281623,52.050346],"type":"Point"}
}