{
  "type": "Feature",
  "properties": {
    "addr:full":"S Gravelandseweg 131 Hilversum Noord-Holland 1217 ER",
    "addr:housenumber":"131",
    "addr:postcode":"hilversum;1217 er",
    "iso:country":"NL",
    "sg:address":"S Gravelandseweg 131",
    "sg:city":"Hilversum",
    "sg:classifiers":[
        {
            "category":"Professional",
            "subcategory":"Accounting & Tax Preparation",
            "type":"Services"
        }
    ],
    "sg:phone":"+31 35 624 4784",
    "sg:postcode":"1217 ER",
    "sg:province":"Noord-Holland",
    "sg:tags":[
        "accountant"
    ],
    "wof:name":"Accountantskantoor Heykants Bv",
    "wof:placetype":"venue"
},
  "geometry": {"coordinates":[5.148439,52.235699],"type":"Point"}
}