{
  "type": "Feature",
  "properties": {
    "addr:full":"Ryndk 2G Hazerswoude Ryndyk Zuid-Holland 2394 AH",
    "addr:housenumber":"2g hazerswoude ryndyk",
    "addr:postcode":"2394 ah",
    "addr:street":"Ryndk",
    "iso:country":"NL",
    "sg:address":"Ryndk 2G",
    "sg:city":"Hazerswoude Ryndyk",
    "sg:orig_category":"Parketvloeren",
    "sg:phone":"+31 71 341 4373",
    "sg:postcode":"2394 AH",
    "sg:province":"Zuid-Holland",
    "wof:name":"Euro Vloeren",
    "wof:placetype":"venue"
},
  "geometry": {"coordinates":[4.595154,52.131054],"type":"Point"}
}