{
  "type": "Feature",
  "properties": {
    "addr:full":"Huygensstraat 20 Ede Gld Gelderland 6717 CC",
    "addr:housenumber":"20",
    "addr:postcode":"6717 cc",
    "addr:street":"Huygensstraat;Gld Gelderland",
    "iso:country":"NL",
    "sg:address":"Huygensstraat 20",
    "sg:city":"Ede Gld",
    "sg:orig_category":"Bloemen And Planten",
    "sg:phone":"+31 318 636 364",
    "sg:postcode":"6717 CC",
    "sg:province":"Gelderland",
    "wof:name":"Bloemenshop Flamingo",
    "wof:placetype":"venue"
},
  "geometry": {"coordinates":[5.653964,52.028767],"type":"Point"}
}