{
  "type": "Feature",
  "properties": {
    "addr:full":"Fortwg 6 Deurne Noord-Brabant 5752 PP",
    "addr:housenumber":"6",
    "addr:postcode":"5752 pp",
    "addr:street":"Fortwg",
    "iso:country":"NL",
    "sg:address":"Fortwg 6",
    "sg:city":"Deurne",
    "sg:orig_category":"Lasbedrijven",
    "sg:phone":"+31 493 312 690",
    "sg:postcode":"5752 PP",
    "sg:province":"Noord-Brabant",
    "wof:name":"Michels",
    "wof:placetype":"venue"
},
  "geometry": {"coordinates":[5.794891,51.489708],"type":"Point"}
}