{
  "type": "Feature",
  "properties": {
    "addr:full":"Dorpsstraat 9 Sint Maarten North Holland 1744 KJ",
    "addr:housenumber":"9",
    "addr:postcode":"1744 kj",
    "addr:street":"Dorpsstraat;Holland",
    "iso:country":"NL",
    "sg:address":"Dorpsstraat 9",
    "sg:city":"Sint Maarten",
    "sg:classifiers":[
        {
            "category":"Education",
            "subcategory":"Preschool",
            "type":"Public Place"
        }
    ],
    "sg:phone":"+31 224 561 101",
    "sg:postcode":"1744 KJ",
    "sg:province":"North Holland",
    "sg:tags":[
        "kleuteronderwijs",
        "basis-"
    ],
    "wof:name":"Openbare Basisschool De Zwerm",
    "wof:placetype":"venue"
},
  "geometry": {"coordinates":[4.745493,52.772682],"type":"Point"}
}