{
  "type": "Feature",
  "properties": {
    "iso:country":"NL",
    "sg:address":"Postbus 353",
    "sg:city":"Weesp",
    "sg:orig_category":"Horloges - Groothandel",
    "sg:phone":"+31 294 419 691",
    "sg:postcode":"1380 AJ",
    "sg:province":"North Holland",
    "wof:name":"Davis La Montre Bv",
    "wof:placetype":"venue"
},
  "geometry": {"coordinates":[5.03828,52.308315],"type":"Point"}
}