{
  "type": "Feature",
  "properties": {
    "addr:full":"St Janstr 28 Keyenborg Gelderland 7256 BC",
    "addr:housenumber":"28",
    "addr:postcode":"7256 bc",
    "addr:street":"Keyenborg Gelderland",
    "iso:country":"NL",
    "sg:address":"St Janstr 28",
    "sg:city":"Keyenborg",
    "sg:classifiers":[
        {
            "category":"Retail",
            "subcategory":"Auto Repair",
            "type":"Services"
        }
    ],
    "sg:phone":"+31 575 461 977",
    "sg:postcode":"7256 BC",
    "sg:province":"Gelderland",
    "sg:tags":[
        "garage"
    ],
    "wof:name":"Kemp",
    "wof:placetype":"venue"
},
  "geometry": {"coordinates":[6.29712,52.030472],"type":"Point"}
}