{
  "type": "Feature",
  "properties": {
    "addr:full":"Postbus 14884 Amsterdam North Holland 1001 LJ",
    "addr:housenumber":"14884",
    "addr:postcode":"1001 lj",
    "addr:street":"Postbus",
    "iso:country":"NL",
    "sg:address":"Postbus 14884",
    "sg:city":"Amsterdam",
    "sg:orig_category":"Vertaalbureaus",
    "sg:phone":"+31 20 421 1811",
    "sg:postcode":"1001 LJ",
    "sg:province":"North Holland",
    "sg:website":"http://www.aotranslators.nl",
    "wof:name":"Atlas Orient Translators",
    "wof:placetype":"venue"
},
  "geometry": {"coordinates":[4.89319,52.373119],"type":"Point"}
}