{
  "type": "Feature",
  "properties": {
    "addr:full":"Loosdrechtseweg 150 Hilversum North Holland 1215 KC",
    "addr:housenumber":"150",
    "addr:postcode":"1215 kc",
    "addr:street":"Loosdrechtseweg",
    "iso:country":"NL",
    "sg:address":"Loosdrechtseweg 150",
    "sg:city":"Hilversum",
    "sg:orig_category":"Film-, Tv- And Videoproductie",
    "sg:phone":"+31 35 624 3384",
    "sg:postcode":"1215 KC",
    "sg:province":"North Holland",
    "wof:name":"Karel Das Eftep Bv",
    "wof:placetype":"venue"
},
  "geometry": {"coordinates":[5.15236,52.2155],"type":"Point"}
}