{
  "type": "Feature",
  "properties": {
    "addr:full":"Raadhuisstraat 20 Vorden Gelderland 7251  A",
    "addr:housenumber":"20;7251 a",
    "addr:street":"Raadhuisstraat;Gelderland",
    "iso:country":"NL",
    "sg:address":"Raadhuisstraat 20",
    "sg:city":"Vorden",
    "sg:orig_category":"Boekenuitgeverijen",
    "sg:phone":"+31 575 553 100",
    "sg:postcode":"7251  A",
    "sg:province":"Gelderland",
    "wof:name":"Bruna",
    "wof:placetype":"venue"
},
  "geometry": {"coordinates":[6.311782,52.10276],"type":"Point"}
}