{
  "type": "Feature",
  "properties": {
    "addr:full":"Stratumsedijk 75 Eindhoven North Brabant 5611 NC",
    "addr:housenumber":"75",
    "addr:postcode":"5611 nc",
    "addr:street":"Stratumsedijk",
    "iso:country":"NL",
    "sg:address":"Stratumsedijk 75",
    "sg:city":"Eindhoven",
    "sg:orig_category":"Krantenuitgeverijen",
    "sg:phone":"+31 40 212 0345",
    "sg:postcode":"5611 NC",
    "sg:province":"North Brabant",
    "wof:name":"Pressport Bv",
    "wof:placetype":"venue"
},
  "geometry": {"coordinates":[5.486351,51.430248],"type":"Point"}
}