{
  "type": "Feature",
  "properties": {
    "addr:full":"Treverilaan 28 Apeldoorn Gelderland 7312 HC",
    "addr:housenumber":"28",
    "addr:postcode":"7312 hc",
    "addr:street":"Treverilaan;Gelderland",
    "iso:country":"NL",
    "sg:address":"Treverilaan 28",
    "sg:city":"Apeldoorn",
    "sg:orig_category":"Public Relationbureaus",
    "sg:phone":"+31 55 355 5028",
    "sg:postcode":"7312 HC",
    "sg:province":"Gelderland",
    "wof:name":"Erica De Vries-Grentzius",
    "wof:placetype":"venue"
},
  "geometry": {"coordinates":[5.932933,52.206783],"type":"Point"}
}