{
  "type": "Feature",
  "properties": {
    "addr:full":"Schenkeldk 66 S Gravendeel Zuid-Holland 3295 EH",
    "addr:housenumber":"66",
    "addr:postcode":"3295 eh",
    "addr:street":"Schenkeldk;S Gravendeel",
    "iso:country":"NL",
    "sg:address":"Schenkeldk 66",
    "sg:city":"S Gravendeel",
    "sg:orig_category":"Honden- En Kattentrimsalons",
    "sg:phone":"+31 78 673 6026",
    "sg:postcode":"3295 EH",
    "sg:province":"Zuid-Holland",
    "wof:name":"Christa",
    "wof:placetype":"venue"
},
  "geometry": {"coordinates":[4.600408,51.743076],"type":"Point"}
}