{
  "type": "Feature",
  "properties": {
    "iso:country":"NL",
    "sg:address":"Westeinde 336",
    "sg:city":"Vriezenveen",
    "sg:orig_category":"Verzekeringen - Verzekeringskantoren",
    "sg:phone":"+31 546 561 465",
    "sg:postcode":"7671 CM",
    "sg:province":"NL.08",
    "sg:website":"http://www.benk.nl",
    "wof:name":"Buddenberg & Kobes",
    "wof:placetype":"venue"
},
  "geometry": {"coordinates":[6.6157641411,52.4090232849],"type":"Point"}
}