{
  "type": "Feature",
  "properties": {
    "iso:country":"NL",
    "sg:address":"Weegbreeplnts 21",
    "sg:city":"Berkel En Rodenrys",
    "sg:orig_category":"Adviesbureaus Bedrijfsorganisatie",
    "sg:phone":"+31 10 511 5321",
    "sg:postcode":"2651 MA",
    "sg:province":"Zuid-Holland",
    "wof:name":"Broek, Van Den",
    "wof:placetype":"venue"
},
  "geometry": {"coordinates":[4.47659,51.994122],"type":"Point"}
}