{
  "type": "Feature",
  "properties": {
    "addr:full":"Ln V Meerdervoort 1032 S Gravenhage South Holland 2564 AW",
    "addr:housenumber":"1032",
    "addr:postcode":"2564 aw",
    "addr:street":"Ln;Meerdervoort;S Gravenhage",
    "iso:country":"NL",
    "sg:address":"Ln V Meerdervoort 1032",
    "sg:city":"S Gravenhage",
    "sg:orig_category":"Administratie- En Boekhoudkantoren",
    "sg:phone":"+31 70 346 8564",
    "sg:postcode":"2564 AW",
    "sg:province":"South Holland",
    "wof:name":"Koster",
    "wof:placetype":"venue"
},
  "geometry": {"coordinates":[4.25946,52.06805],"type":"Point"}
}