{
  "type": "Feature",
  "properties": {
    "addr:full":"Postbus 375 Terneuzen Zeeland 4530 AJ",
    "addr:housenumber":"375",
    "addr:postcode":"4530 aj",
    "addr:street":"Postbus",
    "iso:country":"NL",
    "sg:address":"Postbus 375",
    "sg:city":"Terneuzen",
    "sg:orig_category":"Scholen Voor Algemeen Voortgezet Onderwijs",
    "sg:phone":"+31 115 612 155",
    "sg:postcode":"4530 AJ",
    "sg:province":"Zeeland",
    "sg:website":"http://www.derede.nl",
    "wof:name":"Rede Ssg, De",
    "wof:placetype":"venue"
},
  "geometry": {"coordinates":[3.827559,51.338146],"type":"Point"}
}