{
  "type": "Feature",
  "properties": {
    "addr:full":"Cassandraplein 9 Eindhoven Noord-Brabant 5631 BA",
    "addr:housenumber":"9",
    "addr:postcode":"5631 ba",
    "addr:street":"Cassandraplein",
    "iso:country":"NL",
    "sg:address":"Cassandraplein 9",
    "sg:city":"Eindhoven",
    "sg:orig_category":"Bibliotheken And Openbare Archieven",
    "sg:phone":"+31 40 243 8743",
    "sg:postcode":"5631 BA",
    "sg:province":"Noord-Brabant",
    "wof:name":"Gemeenschappelijke Openbare Bibliotheek",
    "wof:placetype":"venue"
},
  "geometry": {"coordinates":[5.489735,51.459774],"type":"Point"}
}