{
  "type": "Feature",
  "properties": {
    "iso:country":"NL",
    "sg:address":"V Heutszln 3",
    "sg:city":"Arnhem",
    "sg:orig_category":"Drukkerijen",
    "sg:phone":"+31 26 370 9378",
    "sg:postcode":"6821 KB",
    "sg:province":"Gelderland",
    "wof:name":"Altera Pars Media Bv",
    "wof:placetype":"venue"
},
  "geometry": {"coordinates":[5.91455,51.993698],"type":"Point"}
}