{
  "type": "Feature",
  "properties": {
    "addr:full":"Vliegerlaan 2-4 Voorburg Zuid-Holland 2273 BV",
    "addr:housenumber":"2-4",
    "addr:postcode":"2273 bv",
    "addr:street":"Vliegerlaan",
    "iso:country":"NL",
    "sg:address":"Vliegerlaan 2-4",
    "sg:city":"Voorburg",
    "sg:orig_category":"Fitnesscentra",
    "sg:phone":"+31 70 386 7700",
    "sg:postcode":"2273 BV",
    "sg:province":"Zuid-Holland",
    "wof:name":"Fitness Voorburg",
    "wof:placetype":"venue"
},
  "geometry": {"coordinates":[4.360976,52.074238],"type":"Point"}
}