{
  "type": "Feature",
  "properties": {
    "iso:country":"NL",
    "sg:address":"Baron Van Coehoornlaan 13",
    "sg:city":"Sint Oedenrode",
    "sg:orig_category":"Houten Verpakkingen Fab",
    "sg:phone":"+31 413 472 190",
    "sg:postcode":"5492 GR",
    "sg:province":"Noord-Brabant",
    "wof:name":"Stichting Hoepelmakerijen En Kuiperij",
    "wof:placetype":"venue"
},
  "geometry": {"coordinates":[5.462128,51.558453],"type":"Point"}
}