{
  "type": "Feature",
  "properties": {
    "iso:country":"NL",
    "sg:address":"Delistr 17 , (Mobiele Tel.)",
    "sg:city":"S Gravenhage",
    "sg:orig_category":"Verbouwingen",
    "sg:phone":"+31 6 51828569",
    "sg:postcode":"2585 VW",
    "sg:province":"Zuid-Holland",
    "wof:name":"Cullen, R",
    "wof:placetype":"venue"
},
  "geometry": {"coordinates":[4.29777,52.094799],"type":"Point"}
}