{
  "type": "Feature",
  "properties": {
    "iso:country":"NL",
    "sg:address":"Helvoirtsewg 181A",
    "sg:city":"Vught",
    "sg:orig_category":"Verzekeringen - Verzekeringskantoren",
    "sg:phone":"+31 73 613 0274",
    "sg:postcode":"5263 EC",
    "sg:province":"North Brabant",
    "wof:name":"Brabant Bv",
    "wof:placetype":"venue"
},
  "geometry": {"coordinates":[5.287808,51.656116],"type":"Point"}
}