{
  "type": "Feature",
  "properties": {
    "addr:full":"Dr Berlageln 30 Eindhoven Noord-Brabant 5622 HD",
    "addr:housenumber":"30",
    "addr:postcode":"5622 hd",
    "iso:country":"NL",
    "sg:address":"Dr Berlageln 30",
    "sg:city":"Eindhoven",
    "sg:orig_category":"Juridische Adviseurs",
    "sg:phone":"+31 40 269 2896",
    "sg:postcode":"5622 HD",
    "sg:province":"Noord-Brabant",
    "wof:name":"Kleefman",
    "wof:placetype":"venue"
},
  "geometry": {"coordinates":[5.46291,51.459381],"type":"Point"}
}