{
  "type": "Feature",
  "properties": {
    "addr:full":"Dorpsstraat 47 Lunteren Gelderland 6741 AB",
    "addr:housenumber":"47",
    "addr:postcode":"6741 ab",
    "addr:street":"Dorpsstraat;Gelderland",
    "iso:country":"NL",
    "sg:address":"Dorpsstraat 47",
    "sg:city":"Lunteren",
    "sg:orig_category":"Wasserettes And Stomerijen",
    "sg:phone":"+31 318 482 510",
    "sg:postcode":"6741 AB",
    "sg:province":"Gelderland",
    "wof:name":"Stomerij Multinette",
    "wof:placetype":"venue"
},
  "geometry": {"coordinates":[5.6213002205,52.0836143494],"type":"Point"}
}