{
  "type": "Feature",
  "properties": {
    "iso:country":"NL",
    "sg:address":"Tarwekamp 14",
    "sg:city":"Diemen",
    "sg:orig_category":"Loopbaanbegeleiding",
    "sg:phone":"+31 20 600 1270",
    "sg:postcode":"1112 HD",
    "sg:province":"North Holland",
    "sg:website":"http://www.loopbaanadvies.net",
    "wof:name":"Dreessen, M D",
    "wof:placetype":"venue"
},
  "geometry": {"coordinates":[4.952293,52.333847],"type":"Point"}
}