{
  "type": "Feature",
  "properties": {
    "iso:country":"NL",
    "sg:address":"Caproniln 25",
    "sg:city":"Schiphol Ryk",
    "sg:orig_category":"Onroerende Goederen",
    "sg:phone":"+31 20 655 6666",
    "sg:postcode":"1119 NP",
    "sg:province":"North Holland",
    "sg:website":"http://www.prologis.com",
    "wof:name":"Prologis Bv",
    "wof:placetype":"venue"
},
  "geometry": {"coordinates":[4.76793,52.286606],"type":"Point"}
}