{
  "type": "Feature",
  "properties": {
    "iso:country":"NL",
    "sg:address":"Amer 228",
    "sg:city":"Zwolle",
    "sg:orig_category":"Binnenhuisarchitectuur",
    "sg:phone":"+31 38 454 7371",
    "sg:postcode":"8032 GV",
    "sg:province":"NL.08",
    "wof:name":"Deutekom, A",
    "wof:placetype":"venue"
},
  "geometry": {"coordinates":[6.09914,52.532997],"type":"Point"}
}