{
  "type": "Feature",
  "properties": {
    "addr:full":"Lange Heul 782 Bussum North Holland 1403 PE",
    "addr:housenumber":"782",
    "addr:postcode":"1403 pe",
    "addr:street":"Lange Heul",
    "iso:country":"NL",
    "sg:address":"Lange Heul 782",
    "sg:city":"Bussum",
    "sg:orig_category":"Loodgieterswerk, Verwarming And Sanitaire Installaties",
    "sg:phone":"+31 35 693 3195",
    "sg:postcode":"1403 PE",
    "sg:province":"North Holland",
    "wof:name":"Onderhouds- En Klussenbedrijf J.P. Verwe",
    "wof:placetype":"venue"
},
  "geometry": {"coordinates":[5.172763,52.261921],"type":"Point"}
}