{
  "type": "Feature",
  "properties": {
    "iso:country":"NL",
    "sg:address":"V Heeswykstr 55",
    "sg:city":"Kaatsheuvel",
    "sg:orig_category":"Scholen Voor Basisonderwijs",
    "sg:phone":"+31 416 272 166",
    "sg:postcode":"5171 KJ",
    "sg:province":"Noord-Brabant",
    "wof:name":"Vaert Rk, De",
    "wof:placetype":"venue"
},
  "geometry": {"coordinates":[5.033175,51.659588],"type":"Point"}
}