{
  "type": "Feature",
  "properties": {
    "addr:full":"Moeraskersln 11 Enschede Overijssel 7534 JR",
    "addr:housenumber":"11",
    "addr:postcode":"7534 jr",
    "addr:street":"Moeraskersln",
    "iso:country":"NL",
    "sg:address":"Moeraskersln 11",
    "sg:city":"Enschede",
    "sg:orig_category":"Verzekeringen - Verzekeringskantoren",
    "sg:phone":"+31 53 432 1399",
    "sg:postcode":"7534 JR",
    "sg:province":"Overijssel",
    "wof:name":"Grevink",
    "wof:placetype":"venue"
},
  "geometry": {"coordinates":[6.970155,52.215504],"type":"Point"}
}