{
  "type": "Feature",
  "properties": {
    "iso:country":"NL",
    "sg:address":"Het Sticht 82",
    "sg:city":"Assen",
    "sg:orig_category":"Diverse Grafische Activiteiten",
    "sg:phone":"+31 592 352 560",
    "sg:postcode":"9405 NR",
    "sg:province":"Provincie Drenthe",
    "wof:name":"2D Collection",
    "wof:placetype":"venue"
},
  "geometry": {"coordinates":[6.533188,52.983116],"type":"Point"}
}