{
  "type": "Feature",
  "properties": {
    "addr:full":"Heksenwiellaan 114 Breda Noord-Brabant 4823 HB",
    "addr:housenumber":"114",
    "addr:postcode":"4823 hb",
    "addr:street":"Heksenwiellaan",
    "iso:country":"NL",
    "sg:address":"Heksenwiellaan 114",
    "sg:city":"Breda",
    "sg:orig_category":"Muziekinstrumenten Fab",
    "sg:phone":"+31 76 541 6339",
    "sg:postcode":"4823 HB",
    "sg:province":"Noord-Brabant",
    "wof:name":"Sonora",
    "wof:placetype":"venue"
},
  "geometry": {"coordinates":[4.740439,51.626266],"type":"Point"}
}