{
  "type": "Feature",
  "properties": {
    "iso:country":"NL",
    "sg:address":"Voorweide 4",
    "sg:city":"Castricum",
    "sg:orig_category":"Meubelmakerijen",
    "sg:phone":"+31 251 658 685",
    "sg:postcode":"1902 SV",
    "sg:province":"Noord-Holland",
    "wof:name":"Mourik, Van",
    "wof:placetype":"venue"
},
  "geometry": {"coordinates":[4.677052,52.542843],"type":"Point"}
}