{
  "type": "Feature",
  "properties": {
    "addr:full":"Voorweide 4 Castricum Noord-Holland 1902 SV",
    "addr:housenumber":"4",
    "addr:postcode":"1902 sv",
    "addr:street":"Voorweide",
    "iso:country":"NL",
    "sg:address":"Voorweide 4",
    "sg:city":"Castricum",
    "sg:orig_category":"Meubelmakerijen",
    "sg:phone":"+31 251 658 685",
    "sg:postcode":"1902 SV",
    "sg:province":"Noord-Holland",
    "wof:name":"Mourik, Van",
    "wof:placetype":"venue"
},
  "geometry": {"coordinates":[4.677052,52.542843],"type":"Point"}
}