{
  "type": "Feature",
  "properties": {
    "addr:full":"A Cuypstr 1A Zwolle NL.08 8021 DT",
    "addr:housenumber":"1a",
    "addr:postcode":"8021 dt",
    "iso:country":"NL",
    "sg:address":"A Cuypstr 1A",
    "sg:city":"Zwolle",
    "sg:orig_category":"Sportverenigingen En Ontspannings- Verenigingen",
    "sg:phone":"+31 38 453 2419",
    "sg:postcode":"8021 DT",
    "sg:province":"NL.08",
    "wof:name":"Flits, Tafeltennisver",
    "wof:placetype":"venue"
},
  "geometry": {"coordinates":[6.091582,52.517002],"type":"Point"}
}