{
  "type": "Feature",
  "properties": {
    "addr:full":"F Bolstr 43 Amsterdam Noord-Holland 1072 LB",
    "addr:housenumber":"43",
    "addr:postcode":"1072 lb",
    "iso:country":"NL",
    "sg:address":"F Bolstr 43",
    "sg:city":"Amsterdam",
    "sg:orig_category":"Sportschoenen - Winkels",
    "sg:phone":"+31 20 671 5118",
    "sg:postcode":"1072 LB",
    "sg:province":"Noord-Holland",
    "sg:website":"http://www.footlocker.com",
    "wof:name":"Footlocker",
    "wof:placetype":"venue"
},
  "geometry": {"coordinates":[4.89067,52.354012],"type":"Point"}
}