{
  "type": "Feature",
  "properties": {
    "addr:full":"Burg Crezeeln 74 De Lier Zuid-Holland 2678 KZ",
    "addr:housenumber":"74",
    "addr:postcode":"2678 kz",
    "addr:street":"Burg",
    "iso:country":"NL",
    "sg:address":"Burg Crezeeln 74",
    "sg:city":"De Lier",
    "sg:orig_category":"Hek- En Rasterwerken",
    "sg:phone":"+31 174 520 900",
    "sg:postcode":"2678 KZ",
    "sg:province":"Zuid-Holland",
    "wof:name":"Schram",
    "wof:placetype":"venue"
},
  "geometry": {"coordinates":[4.25138,51.975086],"type":"Point"}
}