{
  "type": "Feature",
  "properties": {
    "addr:full":"Karstraat 32 Mill Pennsylvania 5451 AV",
    "addr:housenumber":"32",
    "addr:postcode":"5451 av",
    "addr:street":"Karstraat",
    "iso:country":"NL",
    "sg:address":"Karstraat 32",
    "sg:city":"Mill",
    "sg:orig_category":"Hout Gh",
    "sg:phone":"+31 485 451 532",
    "sg:postcode":"5451 AV",
    "sg:province":"Pennsylvania",
    "wof:name":"Mill Oak Bv",
    "wof:placetype":"venue"
},
  "geometry": {"coordinates":[-77.762939,41.90403],"type":"Point"}
}