{
  "type": "Feature",
  "properties": {
    "iso:country":"NL",
    "sg:address":"Weezenhof 2024",
    "sg:city":"Nijmegen",
    "sg:orig_category":"Verenigingen En Stichtingen",
    "sg:phone":"+31 24 344 1861",
    "sg:postcode":"6536 JM",
    "sg:province":"Gelderland",
    "wof:name":"Werkgroep Kind En Ziekenhuis",
    "wof:placetype":"venue"
},
  "geometry": {"coordinates":[5.802886,51.800797],"type":"Point"}
}