{
  "type": "Feature",
  "properties": {
    "addr:full":"Stationswg 24 Vorden Gelderland 7251 EM",
    "addr:housenumber":"24",
    "addr:postcode":"7251 em",
    "addr:street":"Stationswg;Gelderland",
    "iso:country":"NL",
    "sg:address":"Stationswg 24",
    "sg:city":"Vorden",
    "sg:classifiers":[
        {
            "category":"Travel",
            "subcategory":"Hotels & Motels",
            "type":"Entertainment"
        }
    ],
    "sg:phone":"+31 575 551 227",
    "sg:postcode":"7251 EM",
    "sg:province":"Gelderland",
    "wof:name":"Bloemendaal",
    "wof:placetype":"venue"
},
  "geometry": {"coordinates":[6.317119,52.106213],"type":"Point"}
}