{
  "type": "Feature",
  "properties": {
    "addr:full":"Zuideinde 10 Barendrecht Zuid-Holland 2991 LK",
    "addr:housenumber":"10",
    "addr:postcode":"2991 lk",
    "addr:street":"Zuideinde",
    "iso:country":"NL",
    "sg:address":"Zuideinde 10",
    "sg:city":"Barendrecht",
    "sg:orig_category":"Elektrotechnische Apparatuur - Fabrieken En Groothandel",
    "sg:phone":"+31 180 611 444",
    "sg:postcode":"2991 LK",
    "sg:province":"Zuid-Holland",
    "wof:name":"Rexel Wolff",
    "wof:placetype":"venue"
},
  "geometry": {"coordinates":[4.54064,51.853176],"type":"Point"}
}