{
  "type": "Feature",
  "properties": {
    "addr:full":"W Dreesplnts 21 Amsterdam North Holland 1067 VD",
    "addr:housenumber":"21",
    "addr:postcode":"1067 vd",
    "addr:street":"W",
    "iso:country":"NL",
    "sg:address":"W Dreesplnts 21",
    "sg:city":"Amsterdam",
    "sg:classifiers":[
        {
            "category":"Personal",
            "subcategory":"Nail Salon",
            "type":"Services"
        }
    ],
    "sg:phone":"+31 20 611 1220",
    "sg:postcode":"1067 VD",
    "sg:province":"North Holland",
    "sg:tags":[
        "pedicure"
    ],
    "wof:name":"Westerhuis, I B",
    "wof:placetype":"venue"
},
  "geometry": {"coordinates":[4.78353,52.367722],"type":"Point"}
}