{
  "type": "Feature",
  "properties": {
    "addr:full":"Van Suchtelenstraat 48 Zutphen Gelderland 7203 DG",
    "addr:housenumber":"48",
    "addr:postcode":"7203 dg",
    "addr:street":"Van Suchtelenstraat;Gelderland",
    "iso:country":"NL",
    "sg:address":"Van Suchtelenstraat 48",
    "sg:city":"Zutphen",
    "sg:classifiers":[
        {
            "category":"Professional",
            "subcategory":"Accounting & Tax Preparation",
            "type":"Services"
        }
    ],
    "sg:phone":"+31 575 513 967",
    "sg:postcode":"7203 DG",
    "sg:province":"Gelderland",
    "sg:tags":[
        "accountant"
    ],
    "wof:name":"Schut & Van Helden Accountant En Belastingadviesbu",
    "wof:placetype":"venue"
},
  "geometry": {"coordinates":[6.218714,52.152077],"type":"Point"}
}