{
  "type": "Feature",
  "properties": {
    "addr:full":"Weeresteinstr 110 Hillegom North Holland 2181 GD",
    "addr:housenumber":"110",
    "addr:postcode":"2181 gd",
    "iso:country":"NL",
    "sg:address":"Weeresteinstr 110",
    "sg:city":"Hillegom",
    "sg:orig_category":"Verzekeringen - Verzekeringskantoren",
    "sg:phone":"+31 252 519 725",
    "sg:postcode":"2181 GD",
    "sg:province":"North Holland",
    "wof:name":"Hageman, Jack",
    "wof:placetype":"venue"
},
  "geometry": {"coordinates":[4.583032,52.301346],"type":"Point"}
}