{
  "type": "Feature",
  "properties": {
    "addr:full":"Stationsstraat 5 Almere NL. 1315 KE",
    "addr:housenumber":"5",
    "addr:postcode":"1315 ke",
    "addr:street":"Stationsstraat;Nl.",
    "iso:country":"NL",
    "sg:address":"Stationsstraat 5",
    "sg:city":"Almere",
    "sg:orig_category":"Kappers",
    "sg:phone":"+31 36 530 0463",
    "sg:postcode":"1315 KE",
    "sg:province":"NL.",
    "wof:name":"Team Kapsalon",
    "wof:placetype":"venue"
},
  "geometry": {"coordinates":[5.219823,52.374195],"type":"Point"}
}