{
  "type": "Feature",
  "properties": {
    "addr:full":"Gibraltarstr 80 Amsterdam Noord-Holland 1055 NT",
    "addr:housenumber":"80",
    "addr:postcode":"1055 nt",
    "addr:street":"Gibraltarstr",
    "iso:country":"NL",
    "sg:address":"Gibraltarstr 80",
    "sg:city":"Amsterdam",
    "sg:orig_category":"Autoschade- Herstelbedrijven",
    "sg:phone":"+31 20 682 6317",
    "sg:postcode":"1055 NT",
    "sg:province":"Noord-Holland",
    "wof:name":"Autosteenslag",
    "wof:placetype":"venue"
},
  "geometry": {"coordinates":[4.84937,52.384342],"type":"Point"}
}