{
  "type": "Feature",
  "properties": {
    "addr:full":"Havikstr 24 Badhoevedorp North Holland 1171 DX",
    "addr:housenumber":"24",
    "addr:postcode":"1171 dx",
    "addr:street":"Havikstr",
    "iso:country":"NL",
    "sg:address":"Havikstr 24",
    "sg:city":"Badhoevedorp",
    "sg:orig_category":"Psychosociale Therapeuten",
    "sg:phone":"+31 20 659 9070",
    "sg:postcode":"1171 DX",
    "sg:province":"North Holland",
    "wof:name":"Cic Company",
    "wof:placetype":"venue"
},
  "geometry": {"coordinates":[4.783607,52.338722],"type":"Point"}
}