{
  "type": "Feature",
  "properties": {
    "addr:full":"Leeksterwg 71 Haulerwyk Provincie Friesland 8433 KW",
    "addr:housenumber":"71",
    "addr:postcode":"8433 kw",
    "addr:street":"Leeksterwg;Provincie Friesland",
    "iso:country":"NL",
    "sg:address":"Leeksterwg 71",
    "sg:city":"Haulerwyk",
    "sg:orig_category":"Zuivel - Fabrieken",
    "sg:phone":"+31 516 422 676",
    "sg:postcode":"8433 KW",
    "sg:province":"Provincie Friesland",
    "wof:name":"Wagenaar Bv, Gebr",
    "wof:placetype":"venue"
},
  "geometry": {"coordinates":[6.332057,53.074696],"type":"Point"}
}