{
  "type": "Feature",
  "properties": {
    "iso:country":"NL",
    "sg:address":"In De Fuik 15",
    "sg:city":"Hoogvliet Rt",
    "sg:orig_category":"Zuivelproducten",
    "sg:phone":"+31 10 438 4757",
    "sg:postcode":"3192 HD",
    "sg:province":"Zuid-Holland",
    "wof:name":"Den Besten Kaas",
    "wof:placetype":"venue"
},
  "geometry": {"coordinates":[4.369752,51.850746],"type":"Point"}
}