{
  "type": "Feature",
  "properties": {
    "addr:full":"Wachtendonckstraat 15 Landgraaf Limburg 6371 VV",
    "addr:housenumber":"15",
    "addr:postcode":"6371 vv",
    "addr:street":"Wachtendonckstraat",
    "iso:country":"NL",
    "sg:address":"Wachtendonckstraat 15",
    "sg:city":"Landgraaf",
    "sg:orig_category":"Kinderopvang Behalve Thuis",
    "sg:phone":"+31 45 531 0845",
    "sg:postcode":"6371 VV",
    "sg:province":"Limburg",
    "wof:name":"Kinderdagverblijf De Petteflet",
    "wof:placetype":"venue"
},
  "geometry": {"coordinates":[6.018875,50.899101],"type":"Point"}
}