{
  "type": "Feature",
  "properties": {
    "addr:full":"Molukkenstraat 56 Haarlem Noord-Holland 2022 CD",
    "addr:housenumber":"56",
    "addr:postcode":"2022 cd",
    "addr:street":"Molukkenstraat",
    "iso:country":"NL",
    "sg:address":"Molukkenstraat 56",
    "sg:city":"Haarlem",
    "sg:orig_category":"Huishoudapparatuur, Televisies And Radio'S",
    "sg:phone":"+31 23 526 7171",
    "sg:postcode":"2022 CD",
    "sg:province":"Noord-Holland",
    "wof:name":"Giant Satellite Systems",
    "wof:placetype":"venue"
},
  "geometry": {"coordinates":[4.650168,52.400181],"type":"Point"}
}