{
  "type": "Feature",
  "properties": {
    "addr:full":"Rijnkade 17B Weesp Noord-Holland 1382 GS",
    "addr:housenumber":"17b",
    "addr:postcode":"1382 gs",
    "addr:street":"Rijnkade",
    "iso:country":"NL",
    "sg:address":"Rijnkade 17B",
    "sg:city":"Weesp",
    "sg:orig_category":"Fotostudio'S And Fotografen",
    "sg:phone":"+31 294 412 086",
    "sg:postcode":"1382 GS",
    "sg:province":"Noord-Holland",
    "wof:name":"Team Unlimited",
    "wof:placetype":"venue"
},
  "geometry": {"coordinates":[5.021828,52.306683],"type":"Point"}
}