{
  "type": "Feature",
  "properties": {
    "iso:country":"NL",
    "sg:address":"Binnenwg 57-59",
    "sg:city":"Heemstede",
    "sg:orig_category":"Fietsen En Bromfietsen",
    "sg:phone":"+31 23 528 5296",
    "sg:postcode":"2101 JB",
    "sg:province":"Noord-Holland",
    "wof:name":"Aad Verdonschot Tweewielers",
    "wof:placetype":"venue"
},
  "geometry": {"coordinates":[4.621463,52.352005],"type":"Point"}
}