{
  "type": "Feature",
  "properties": {
    "addr:full":"Leeuweriklaan 46 'S Gravenzande Zuid-Holland 2691 CM",
    "addr:housenumber":"46",
    "addr:postcode":"2691 cm",
    "addr:street":"Leeuweriklaan;' S",
    "iso:country":"NL",
    "sg:address":"Leeuweriklaan 46",
    "sg:city":"'S Gravenzande",
    "sg:classifiers":[
        {
            "category":"Professional",
            "subcategory":"Accounting & Tax Preparation",
            "type":"Services"
        }
    ],
    "sg:phone":"+31 174 413 717",
    "sg:postcode":"2691 CM",
    "sg:province":"Zuid-Holland",
    "sg:tags":[
        "accountant"
    ],
    "wof:name":"Drs. C.D. V.D. Merwe",
    "wof:placetype":"venue"
},
  "geometry": {"coordinates":[4.175936,52.002773],"type":"Point"}
}