{
  "type": "Feature",
  "properties": {
    "iso:country":"NL",
    "sg:address":"Helmichstraat 17",
    "sg:city":"Huissen",
    "sg:orig_category":"Huishoudapparatuur, Televisies And Radio'S",
    "sg:phone":"+31 26 325 1616",
    "sg:postcode":"6851 CB",
    "sg:province":"Gelderland",
    "wof:name":"Janssen Electro Service Vof",
    "wof:placetype":"venue"
},
  "geometry": {"coordinates":[5.940553,51.934872],"type":"Point"}
}