{
  "type": "Feature",
  "properties": {
    "addr:full":"Grotestraat 207 Waalwijk Noord-Brabant 5141 JS",
    "addr:housenumber":"207",
    "addr:postcode":"5141 js",
    "addr:street":"Grotestraat",
    "iso:country":"NL",
    "sg:address":"Grotestraat 207",
    "sg:city":"Waalwijk",
    "sg:orig_category":"Airconditioning And Ventilatie",
    "sg:phone":"+31 416 330 019",
    "sg:postcode":"5141 JS",
    "sg:province":"Noord-Brabant",
    "wof:name":"Zonnecentrum Sentjens",
    "wof:placetype":"venue"
},
  "geometry": {"coordinates":[5.063522,51.690369],"type":"Point"}
}