{
  "type": "Feature",
  "properties": {
    "addr:full":"Hietkampen 43 Westerbork Provincie Drenthe 9431 HC",
    "addr:housenumber":"43",
    "addr:postcode":"9431 hc",
    "addr:street":"Hietkampen;Provincie Drenthe",
    "iso:country":"NL",
    "sg:address":"Hietkampen 43",
    "sg:city":"Westerbork",
    "sg:orig_category":"Kappers",
    "sg:phone":"+31 593 331 389",
    "sg:postcode":"9431 HC",
    "sg:province":"Provincie Drenthe",
    "wof:name":"Kapsalon Ten Berge",
    "wof:placetype":"venue"
},
  "geometry": {"coordinates":[6.5999140739,52.8576316833],"type":"Point"}
}