{
  "type": "Feature",
  "properties": {
    "addr:full":"N Maesstr 107 Amsterdam Noord-Holland 1071 PV",
    "addr:housenumber":"107",
    "addr:postcode":"1071 pv",
    "addr:street":"N",
    "iso:country":"NL",
    "sg:address":"N Maesstr 107",
    "sg:city":"Amsterdam",
    "sg:classifiers":[
        {
            "category":"Travel",
            "subcategory":"Hotels & Motels",
            "type":"Entertainment"
        }
    ],
    "sg:phone":"+31 20 679 7972",
    "sg:postcode":"1071 PV",
    "sg:province":"Noord-Holland",
    "wof:name":"Marianne",
    "wof:placetype":"venue"
},
  "geometry": {"coordinates":[4.878882,52.354164],"type":"Point"}
}