{
  "type": "Feature",
  "properties": {
    "addr:full":"Leidsewg 308 Voorschoten Zuid-Holland 2253 JM",
    "addr:housenumber":"308",
    "addr:postcode":"2253 jm",
    "iso:country":"NL",
    "sg:address":"Leidsewg 308",
    "sg:city":"Voorschoten",
    "sg:orig_category":"Kunsthandel",
    "sg:phone":"+31 71 576 6735",
    "sg:postcode":"2253 JM",
    "sg:province":"Zuid-Holland",
    "wof:name":"Chevalet, Le",
    "wof:placetype":"venue"
},
  "geometry": {"coordinates":[4.465264,52.138245],"type":"Point"}
}