{
  "type": "Feature",
  "properties": {
    "addr:full":"Faassenpln 84 Schiedam Zuid-Holland 3123 NL",
    "addr:housenumber":"84",
    "addr:postcode":"3123 nl",
    "addr:street":"Faassenpln",
    "iso:country":"NL",
    "sg:address":"Faassenpln 84",
    "sg:city":"Schiedam",
    "sg:orig_category":"Autorijscholen",
    "sg:phone":"+31 10 470 0300",
    "sg:postcode":"3123 NL",
    "sg:province":"Zuid-Holland",
    "sg:website":"http://www.woudhoek.nl",
    "wof:name":"Woudhoek",
    "wof:placetype":"venue"
},
  "geometry": {"coordinates":[4.371508,51.940376],"type":"Point"}
}