{
  "type": "Feature",
  "properties": {
    "addr:full":"Kastanjeln 1A Roden Provincie Drenthe 9301 LD",
    "addr:housenumber":"1a",
    "addr:postcode":"9301 ld",
    "addr:street":"Kastanjeln;Provincie Drenthe",
    "iso:country":"NL",
    "sg:address":"Kastanjeln 1A",
    "sg:city":"Roden",
    "sg:orig_category":"Heftrucks",
    "sg:phone":"+31 50 501 6278",
    "sg:postcode":"9301 LD",
    "sg:province":"Provincie Drenthe",
    "wof:name":"Onderdelen Discount Roden",
    "wof:placetype":"venue"
},
  "geometry": {"coordinates":[6.433427,53.140865],"type":"Point"}
}