{
  "type": "Feature",
  "properties": {
    "addr:full":"Hoofdwg 28 De Cocksdorp North Holland 1795 JD",
    "addr:housenumber":"28",
    "addr:postcode":"1795 jd",
    "addr:street":"Hoofdwg",
    "iso:country":"NL",
    "sg:address":"Hoofdwg 28",
    "sg:city":"De Cocksdorp",
    "sg:orig_category":"Verhuur",
    "sg:phone":"+31 222 311 741",
    "sg:postcode":"1795 JD",
    "sg:province":"North Holland",
    "wof:name":"Tentorent",
    "wof:placetype":"venue"
},
  "geometry": {"coordinates":[4.842662,53.111229],"type":"Point"}
}