{
  "type": "Feature",
  "properties": {
    "addr:full":"Ysselsngl 158 S Hertogenbosch Noord-Brabant 5215 CN",
    "addr:housenumber":"158",
    "addr:postcode":"5215 cn",
    "addr:street":"S",
    "iso:country":"NL",
    "sg:address":"Ysselsngl 158",
    "sg:city":"S Hertogenbosch",
    "sg:orig_category":"Webdesign Bureaus",
    "sg:phone":"+31 73 613 6108",
    "sg:postcode":"5215 CN",
    "sg:province":"Noord-Brabant",
    "sg:website":"http://www.contemplated.net",
    "wof:name":"Contemplated",
    "wof:placetype":"venue"
},
  "geometry": {"coordinates":[5.2982401848,51.6907501221],"type":"Point"}
}