{
  "type": "Feature",
  "properties": {
    "addr:full":"Dr. Nassaulaan 10 Assen Drenthe 9401 HK",
    "addr:housenumber":"10",
    "addr:postcode":"9401 hk",
    "addr:street":"Nassaulaan",
    "iso:country":"NL",
    "sg:address":"Dr. Nassaulaan 10",
    "sg:city":"Assen",
    "sg:orig_category":"Fitnesscentra",
    "sg:phone":"+31 592 315 618",
    "sg:postcode":"9401 HK",
    "sg:province":"Drenthe",
    "wof:name":"Healthy Balance",
    "wof:placetype":"venue"
},
  "geometry": {"coordinates":[6.557231,52.991524],"type":"Point"}
}