{
  "type": "Feature",
  "properties": {
    "addr:full":"Westelijke Parallelweg 6 Lunteren Gelderland 6741 ZM",
    "addr:housenumber":"6",
    "addr:postcode":"6741 zm",
    "addr:street":"Westelijke Parallelweg;Gelderland",
    "iso:country":"NL",
    "sg:address":"Westelijke Parallelweg 6",
    "sg:city":"Lunteren",
    "sg:orig_category":"Metaalbekleding And -Behandeling",
    "sg:phone":"+31 318 482 726",
    "sg:postcode":"6741 ZM",
    "sg:province":"Gelderland",
    "wof:name":"C. Bassa",
    "wof:placetype":"venue"
},
  "geometry": {"coordinates":[5.622616,52.087566],"type":"Point"}
}