{
  "type": "Feature",
  "properties": {
    "addr:full":"Rijksweg 129 Groningen Groningen 9731 AH",
    "addr:housenumber":"129",
    "addr:postcode":"9731 ah",
    "addr:street":"Rijksweg",
    "iso:country":"NL",
    "sg:address":"Rijksweg 129",
    "sg:city":"Groningen",
    "sg:classifiers":[
        {
            "category":"Retail",
            "subcategory":"Photofinishing",
            "type":"Services"
        }
    ],
    "sg:phone":"+31 50 542 1433",
    "sg:postcode":"9731 AH",
    "sg:province":"Groningen",
    "sg:tags":[
        "foto",
        "film"
    ],
    "wof:name":"Objektief Nijveen",
    "wof:placetype":"venue"
},
  "geometry": {"coordinates":[6.595994,53.226189],"type":"Point"}
}