{
  "type": "Feature",
  "properties": {
    "addr:full":"Rijksstraatweg 13 Baambrugge Utrecht 1396 JC",
    "addr:housenumber":"13",
    "addr:postcode":"1396 jc",
    "addr:street":"Rijksstraatweg",
    "iso:country":"NL",
    "sg:address":"Rijksstraatweg 13",
    "sg:city":"Baambrugge",
    "sg:orig_category":"Diverse Consumentenartikelen Gh",
    "sg:phone":"+31 294 291 443",
    "sg:postcode":"1396 JC",
    "sg:province":"Utrecht",
    "wof:name":"J.M. Trading",
    "wof:placetype":"venue"
},
  "geometry": {"coordinates":[4.992348,52.257191],"type":"Point"}
}