{
  "type": "Feature",
  "properties": {
    "addr:full":"Marisstr 14-16 Geleen Limburg 6165 AS",
    "addr:housenumber":"14-16",
    "addr:postcode":"6165 as",
    "addr:street":"Geleen Limburg",
    "iso:country":"NL",
    "sg:address":"Marisstr 14-16",
    "sg:city":"Geleen",
    "sg:orig_category":"Fietsen En Bromfietsen",
    "sg:phone":"+31 46 474 9237",
    "sg:postcode":"6165 AS",
    "sg:province":"Limburg",
    "wof:name":"Olthof, Simon",
    "wof:placetype":"venue"
},
  "geometry": {"coordinates":[5.825305,50.959755],"type":"Point"}
}