{
  "type": "Feature",
  "properties": {
    "addr:full":"Arumerweg 16 Witmarsum Friesland 8748 AD",
    "addr:housenumber":"16",
    "addr:postcode":"8748 ad",
    "addr:street":"Arumerweg",
    "iso:country":"NL",
    "sg:address":"Arumerweg 16",
    "sg:city":"Witmarsum",
    "sg:orig_category":"Kappers",
    "sg:phone":"+31 517 531 290",
    "sg:postcode":"8748 AD",
    "sg:province":"Friesland",
    "wof:name":"L.Wierda",
    "wof:placetype":"venue"
},
  "geometry": {"coordinates":[5.46843,53.102898],"type":"Point"}
}