{
  "type": "Feature",
  "properties": {
    "addr:full":"Enkhuizerplein 2 Amsterdam Noord-Holland 1023 VT",
    "addr:housenumber":"2",
    "addr:postcode":"1023",
    "addr:street":"Enkhuizerplein",
    "iso:country":"NL",
    "sg:address":"Enkhuizerplein 2",
    "sg:city":"Amsterdam",
    "sg:orig_category":"Artsen And Specialisten",
    "sg:phone":"+31 20 636 0514",
    "sg:postcode":"1023 VT",
    "sg:province":"Noord-Holland",
    "wof:name":"J.A. V.D. Bosch",
    "wof:placetype":"venue"
},
  "geometry": {"coordinates":[4.94138,52.39212],"type":"Point"}
}