{
  "type": "Feature",
  "properties": {
    "addr:full":"Puntelstr 32A Simpelveld Limburg 6369 TC",
    "addr:housenumber":"32a",
    "addr:postcode":"6369 tc",
    "addr:street":"Puntelstr",
    "iso:country":"NL",
    "sg:address":"Puntelstr 32A",
    "sg:city":"Simpelveld",
    "sg:orig_category":"Autorijscholen",
    "sg:phone":"+31 45 544 2480",
    "sg:postcode":"6369 TC",
    "sg:province":"Limburg",
    "wof:name":"Winthagen",
    "wof:placetype":"venue"
},
  "geometry": {"coordinates":[5.987715,50.832748],"type":"Point"}
}