{
  "type": "Feature",
  "properties": {
    "addr:full":"J Muyskenwg 86 Amsterdam Noord-Holland 1099 CK",
    "addr:housenumber":"86",
    "addr:postcode":"1099 ck",
    "iso:country":"NL",
    "sg:address":"J Muyskenwg 86",
    "sg:city":"Amsterdam",
    "sg:orig_category":"Omroep",
    "sg:phone":"+31 20 562 0666",
    "sg:postcode":"1099 CK",
    "sg:province":"Noord-Holland",
    "sg:website":"http://www.kindernet.nl",
    "wof:name":"Kindernet Cv",
    "wof:placetype":"venue"
},
  "geometry": {"coordinates":[4.92788,52.320251],"type":"Point"}
}