{
  "type": "Feature",
  "properties": {
    "addr:full":"Gerestein 9 Tiel Gelderland 4003 GD",
    "addr:housenumber":"9",
    "addr:postcode":"4003 gd",
    "addr:street":"Gerestein;Gelderland",
    "iso:country":"NL",
    "sg:address":"Gerestein 9",
    "sg:city":"Tiel",
    "sg:orig_category":"Public Relationbureaus",
    "sg:phone":"+31 344 631 567",
    "sg:postcode":"4003 GD",
    "sg:province":"Gelderland",
    "wof:name":"S.E. Huising",
    "wof:placetype":"venue"
},
  "geometry": {"coordinates":[5.405983,51.897251],"type":"Point"}
}