{
  "type": "Feature",
  "properties": {
    "addr:full":"Muiderslotstr 62 Schiedam Zuid-Holland 3123 RM",
    "addr:housenumber":"62",
    "addr:postcode":"3123 rm",
    "addr:street":"Muiderslotstr",
    "iso:country":"NL",
    "sg:address":"Muiderslotstr 62",
    "sg:city":"Schiedam",
    "sg:orig_category":"Autorijscholen",
    "sg:phone":"+31 10 470 9252",
    "sg:postcode":"3123 RM",
    "sg:province":"Zuid-Holland",
    "wof:name":"Verboom",
    "wof:placetype":"venue"
},
  "geometry": {"coordinates":[4.366194,51.945045],"type":"Point"}
}