{
  "type": "Feature",
  "properties": {
    "addr:full":"Boutershemstraat 54-56 Bergen Op Zoom Noord-Brabant 4611 KD",
    "addr:housenumber":"54-56",
    "addr:postcode":"4611 kd",
    "addr:street":"Boutershemstraat",
    "iso:country":"NL",
    "sg:address":"Boutershemstraat 54-56",
    "sg:city":"Bergen Op Zoom",
    "sg:orig_category":"Discountwinkels",
    "sg:phone":"+31 164 244 892",
    "sg:postcode":"4611 KD",
    "sg:province":"Noord-Brabant",
    "wof:name":"De Bergse Dumphal",
    "wof:placetype":"venue"
},
  "geometry": {"coordinates":[4.282305,51.493164],"type":"Point"}
}