{
  "type": "Feature",
  "properties": {
    "addr:full":"D Steurhof 136 Volendam Noord-Holland 1132 DP",
    "addr:housenumber":"136",
    "addr:postcode":"1132 dp",
    "addr:street":"D Steurhof",
    "iso:country":"NL",
    "sg:address":"D Steurhof 136",
    "sg:city":"Volendam",
    "sg:orig_category":"Kinderkleding",
    "sg:phone":"+31 299 365 387",
    "sg:postcode":"1132 DP",
    "sg:province":"Noord-Holland",
    "wof:name":"Guppy",
    "wof:placetype":"venue"
},
  "geometry": {"coordinates":[5.052862,52.493225],"type":"Point"}
}