{
  "type": "Feature",
  "properties": {
    "iso:country":"NL",
    "sg:address":"Gortstraat 14",
    "sg:city":"'S Gravenhage",
    "sg:orig_category":"Bloemen And Planten",
    "sg:phone":"+31 70 364 6085",
    "sg:postcode":"2511 AP",
    "sg:province":"Zuid-Holland",
    "wof:name":"Fleur-Ever",
    "wof:placetype":"venue"
},
  "geometry": {"coordinates":[4.310759,52.077335],"type":"Point"}
}