{
  "type": "Feature",
  "properties": {
    "iso:country":"NL",
    "sg:address":"Sterrebos 28",
    "sg:city":"Almelo",
    "sg:orig_category":"Biljarts - Fabrieken",
    "sg:phone":"+31 6 53996129",
    "sg:postcode":"7609 ZP",
    "sg:province":"Overijssel",
    "wof:name":"Sl",
    "wof:placetype":"venue"
},
  "geometry": {"coordinates":[6.661724,52.331097],"type":"Point"}
}