{
  "type": "Feature",
  "properties": {
    "iso:country":"NL",
    "sg:address":"Langewal 41",
    "sg:city":"Gorredijk",
    "sg:orig_category":"Dierenspeciaalzaken",
    "sg:phone":"+31 513 466 048",
    "sg:postcode":"8401 DE",
    "sg:province":"Friesland",
    "wof:name":"Dierenspeciaalzaak Divola",
    "wof:placetype":"venue"
},
  "geometry": {"coordinates":[6.067995,53.001369],"type":"Point"}
}