{
  "type": "Feature",
  "properties": {
    "addr:full":"Ulftseweg 83 Silvolde Gelderland 7064 BC",
    "addr:housenumber":"83",
    "addr:postcode":"7064 bc",
    "addr:street":"Ulftseweg;Gelderland",
    "iso:country":"NL",
    "sg:address":"Ulftseweg 83",
    "sg:city":"Silvolde",
    "sg:orig_category":"Meubelzaken, Woning- And Keukeninrichting",
    "sg:phone":"+31 315 330 233",
    "sg:postcode":"7064 BC",
    "sg:province":"Gelderland",
    "wof:name":"Vof Gregoor Manoumeubelen",
    "wof:placetype":"venue"
},
  "geometry": {"coordinates":[6.3863940239,51.9048309326],"type":"Point"}
}