{
  "type": "Feature",
  "properties": {
    "addr:full":"Schuitvlotstr 13 Middelburg Zeeland 4331 SX",
    "addr:housenumber":"13",
    "addr:postcode":"4331 sx",
    "addr:street":"Schuitvlotstr",
    "iso:country":"NL",
    "sg:address":"Schuitvlotstr 13",
    "sg:city":"Middelburg",
    "sg:orig_category":"Fotoreportages",
    "sg:phone":"+31 118 616 120",
    "sg:postcode":"4331 SX",
    "sg:province":"Zeeland",
    "wof:name":"Anda Van Riet",
    "wof:placetype":"venue"
},
  "geometry": {"coordinates":[3.620498,51.502197],"type":"Point"}
}