{
  "type": "Feature",
  "properties": {
    "iso:country":"NL",
    "sg:address":"Splinterlaan 15",
    "sg:city":"Leiderdorp",
    "sg:classifiers":[
        {
            "category":"Bakery",
            "type":"Food & Drink"
        }
    ],
    "sg:phone":"+31 71 541 1516",
    "sg:postcode":"2352 SB",
    "sg:province":"Zuid-Holland",
    "sg:tags":[
        "brood",
        "banket"
    ],
    "wof:name":"Fa Preenen",
    "wof:placetype":"venue"
},
  "geometry": {"coordinates":[4.516769,52.161167],"type":"Point"}
}