{
  "type": "Feature",
  "properties": {
    "addr:full":"Burg Wynenstr 44 Asten Noord-Brabant 5721 AJ",
    "addr:housenumber":"44",
    "addr:postcode":"5721 aj",
    "addr:street":"Burg",
    "iso:country":"NL",
    "sg:address":"Burg Wynenstr 44",
    "sg:city":"Asten",
    "sg:orig_category":"Opticiens",
    "sg:phone":"+31 493 694 232",
    "sg:postcode":"5721 AJ",
    "sg:province":"Noord-Brabant",
    "wof:name":"Philip Optiek",
    "wof:placetype":"venue"
},
  "geometry": {"coordinates":[5.7467079163,51.4064445496],"type":"Point"}
}