{
  "type": "Feature",
  "properties": {
    "addr:full":"Nw Nieuwstr 78 Boxtel Noord-Brabant 5283 CG",
    "addr:housenumber":"78",
    "addr:postcode":"5283 cg",
    "iso:country":"NL",
    "sg:address":"Nw Nieuwstr 78",
    "sg:city":"Boxtel",
    "sg:orig_category":"Schilders",
    "sg:phone":"+31 6 53119464",
    "sg:postcode":"5283 CG",
    "sg:province":"Noord-Brabant",
    "wof:name":"Weert, Van",
    "wof:placetype":"venue"
},
  "geometry": {"coordinates":[5.339496,51.591366],"type":"Point"}
}