{
  "type": "Feature",
  "properties": {
    "iso:country":"NL",
    "sg:address":"Heuvelwg 8A",
    "sg:city":"Soest",
    "sg:orig_category":"Antiquiteiten - Restauratie",
    "sg:phone":"+31 35 609 0129",
    "sg:postcode":"3761 XN",
    "sg:province":"Utrecht",
    "wof:name":"Otte, Walter",
    "wof:placetype":"venue"
},
  "geometry": {"coordinates":[5.289466,52.187954],"type":"Point"}
}