{
  "type": "Feature",
  "properties": {
    "addr:full":"Warnsveldsewg 47 Zutphen Gelderland 7204 BB",
    "addr:housenumber":"47",
    "addr:postcode":"7204 bb",
    "addr:street":"Warnsveldsewg;Gelderland",
    "iso:country":"NL",
    "sg:address":"Warnsveldsewg 47",
    "sg:city":"Zutphen",
    "sg:orig_category":"Logopedisten",
    "sg:phone":"+31 575 512 664",
    "sg:postcode":"7204 BB",
    "sg:province":"Gelderland",
    "wof:name":"Stottercentr Zutphen",
    "wof:placetype":"venue"
},
  "geometry": {"coordinates":[6.207301,52.141773],"type":"Point"}
}