{
  "type": "Feature",
  "properties": {
    "addr:full":"Lavendelplnts 9 Almere Flevoland 1313 EW",
    "addr:housenumber":"9",
    "addr:postcode":"1313 ew",
    "addr:street":"Lavendelplnts;Flevoland",
    "iso:country":"NL",
    "sg:address":"Lavendelplnts 9",
    "sg:city":"Almere",
    "sg:orig_category":"Fotoreportages",
    "sg:phone":"+31 36 533 1775",
    "sg:postcode":"1313 EW",
    "sg:province":"Flevoland",
    "wof:name":"Fred Jansen",
    "wof:placetype":"venue"
},
  "geometry": {"coordinates":[5.22223,52.376598],"type":"Point"}
}