{
  "type": "Feature",
  "properties": {
    "addr:full":"Minderbroederspad 3A Tilburg North Brabant 5025 JZ",
    "addr:housenumber":"3a",
    "addr:postcode":"5025 jz",
    "addr:street":"Minderbroederspad",
    "iso:country":"NL",
    "sg:address":"Minderbroederspad 3A",
    "sg:city":"Tilburg",
    "sg:orig_category":"Meubelen",
    "sg:phone":"+31 13 542 0695",
    "sg:postcode":"5025 JZ",
    "sg:province":"North Brabant",
    "wof:name":"Linda",
    "wof:placetype":"venue"
},
  "geometry": {"coordinates":[5.07126,51.550797],"type":"Point"}
}