{
  "type": "Feature",
  "properties": {
    "addr:full":"Stadspoort 2A Ede Gld Gelderland 6716 RH",
    "addr:housenumber":"2a",
    "addr:postcode":"6716 rh",
    "addr:street":"Stadspoort;Gld Gelderland",
    "iso:country":"NL",
    "sg:address":"Stadspoort 2A",
    "sg:city":"Ede Gld",
    "sg:orig_category":"Banken And Kredietinstellingen",
    "sg:phone":"+31 318 631 628",
    "sg:postcode":"6716 RH",
    "sg:province":"Gelderland",
    "wof:name":"Postkantoor",
    "wof:placetype":"venue"
},
  "geometry": {"coordinates":[5.651164,52.017681],"type":"Point"}
}