{
  "type": "Feature",
  "properties": {
    "addr:full":"Julianaln 233 Bilthoven Utrecht 3722 GM",
    "addr:housenumber":"233",
    "addr:postcode":"3722 gm",
    "addr:street":"Bilthoven",
    "iso:country":"NL",
    "sg:address":"Julianaln 233",
    "sg:city":"Bilthoven",
    "sg:orig_category":"Adviesbureaus",
    "sg:phone":"+31 30 225 0513",
    "sg:postcode":"3722 GM",
    "sg:province":"Utrecht",
    "wof:name":"Tatilent",
    "wof:placetype":"venue"
},
  "geometry": {"coordinates":[5.224786,52.132889],"type":"Point"}
}