{
  "type": "Feature",
  "properties": {
    "addr:full":"Postbus 271 Nieuwerkerk Yssel 2910 AG",
    "addr:housenumber":"271",
    "addr:postcode":"2910",
    "addr:street":"Postbus",
    "iso:country":"NL",
    "sg:address":"Postbus 271",
    "sg:city":"Nieuwerkerk Yssel",
    "sg:orig_category":"Grondwerken",
    "sg:phone":"+31 180 322 747",
    "sg:postcode":"2910 AG",
    "sg:website":"http://www.gnrubbertracks.nl",
    "wof:name":"Gn Bv",
    "wof:placetype":"venue"
},
  "geometry": {"coordinates":[4.60531,51.969898],"type":"Point"}
}