{
  "type": "Feature",
  "properties": {
    "iso:country":"NL",
    "sg:address":"Oranjewg 53",
    "sg:city":"Hollum",
    "sg:orig_category":"Vakantieverblijven",
    "sg:phone":"+31 519 554 555",
    "sg:postcode":"9161 CB",
    "sg:province":"Friesland",
    "wof:name":"Vuurtoren, Bij De",
    "wof:placetype":"venue"
},
  "geometry": {"coordinates":[5.6262,53.449337],"type":"Point"}
}