{
  "type": "Feature",
  "properties": {
    "addr:full":"Oranjewg 53 Hollum Friesland 9161 CB",
    "addr:housenumber":"53",
    "addr:postcode":"9161 cb",
    "addr:street":"Oranjewg",
    "iso:country":"NL",
    "sg:address":"Oranjewg 53",
    "sg:city":"Hollum",
    "sg:orig_category":"Vakantieverblijven",
    "sg:phone":"+31 519 554 555",
    "sg:postcode":"9161 CB",
    "sg:province":"Friesland",
    "wof:name":"Vuurtoren, Bij De",
    "wof:placetype":"venue"
},
  "geometry": {"coordinates":[5.6262,53.449337],"type":"Point"}
}