{
  "type": "Feature",
  "properties": {
    "addr:full":"3E Pynackerstr 11 Rotterdam Zuid-Holland 3035 CK",
    "addr:housenumber":"11",
    "addr:postcode":"3035 ck",
    "addr:street":"3E Pynackerstr",
    "iso:country":"NL",
    "sg:address":"3E Pynackerstr 11",
    "sg:city":"Rotterdam",
    "sg:orig_category":"Honden- En Kattentrimsalons",
    "sg:phone":"+31 10 265 0806",
    "sg:postcode":"3035 CK",
    "sg:province":"Zuid-Holland",
    "wof:name":"Hoven, D Van Den",
    "wof:placetype":"venue"
},
  "geometry": {"coordinates":[4.478127,51.933586],"type":"Point"}
}