{
  "type": "Feature",
  "properties": {
    "iso:country":"NL",
    "sg:address":"Daltonstraat 17A",
    "sg:city":"Dordrecht",
    "sg:orig_category":"Wasserettes, Stomerijen And Reiniging",
    "sg:phone":"+31 78 631 6652",
    "sg:postcode":"3316 GD",
    "sg:province":"Zuid-Holland",
    "wof:name":"Chemdry",
    "wof:placetype":"venue"
},
  "geometry": {"coordinates":[4.637843132,51.7778701782],"type":"Point"}
}