{
  "type": "Feature",
  "properties": {
    "addr:full":"J V Lennephof 50 Hellevoetsluis Zuid-Holland 3221 VM",
    "addr:housenumber":"50",
    "addr:postcode":"3221 vm",
    "addr:street":"J;Lennephof",
    "iso:country":"NL",
    "sg:address":"J V Lennephof 50",
    "sg:city":"Hellevoetsluis",
    "sg:orig_category":"Onderhoudswerken",
    "sg:phone":"+31 181 315 589",
    "sg:postcode":"3221 VM",
    "sg:province":"Zuid-Holland",
    "wof:name":"Kaa, C Van Der",
    "wof:placetype":"venue"
},
  "geometry": {"coordinates":[4.14703,51.830406],"type":"Point"}
}