{
  "type": "Feature",
  "properties": {
    "addr:full":"Blauwkarper 4 Leiden Zuid-Holland 2318 NN",
    "addr:housenumber":"4",
    "addr:postcode":"2318 nn",
    "addr:street":"Blauwkarper",
    "iso:country":"NL",
    "sg:address":"Blauwkarper 4",
    "sg:city":"Leiden",
    "sg:orig_category":"Tekstschrijversters",
    "sg:phone":"+31 71 523 4920",
    "sg:postcode":"2318 NN",
    "sg:province":"Zuid-Holland",
    "wof:name":"Tekst & Speech",
    "wof:placetype":"venue"
},
  "geometry": {"coordinates":[4.49892,52.182198],"type":"Point"}
}