{
  "type": "Feature",
  "properties": {
    "addr:full":"Gustave Stresemannstraat 53 Diemen North Holland 1111 KL",
    "addr:housenumber":"53",
    "addr:postcode":"1111 kl",
    "addr:street":"Gustave Stresemannstraat",
    "iso:country":"NL",
    "sg:address":"Gustave Stresemannstraat 53",
    "sg:city":"Diemen",
    "sg:orig_category":"Verzekeringen",
    "sg:phone":"+31 20 600 5515",
    "sg:postcode":"1111 KL",
    "sg:province":"North Holland",
    "wof:name":"F.M.G. Banking Facility Support Bv",
    "wof:placetype":"venue"
},
  "geometry": {"coordinates":[4.963112,52.344803],"type":"Point"}
}