{
  "type": "Feature",
  "properties": {
    "addr:full":"A Kooistrahof 36 Amsterdam Zuidoost Noord-Holland 1106 WH",
    "addr:housenumber":"36",
    "addr:postcode":"zuidoost;1106 wh",
    "addr:street":"A Kooistrahof",
    "iso:country":"NL",
    "sg:address":"A Kooistrahof 36",
    "sg:city":"Amsterdam Zuidoost",
    "sg:orig_category":"Verzekeringen - Verzekeringskantoren",
    "sg:phone":"+31 20 345 6780",
    "sg:postcode":"1106 WH",
    "sg:province":"Noord-Holland",
    "sg:website":"http://www.allsurance.nl",
    "wof:name":"Allsurance",
    "wof:placetype":"venue"
},
  "geometry": {"coordinates":[4.991364,52.299145],"type":"Point"}
}