{
  "type": "Feature",
  "properties": {
    "addr:full":"Aalsmeerderdk 66 Oude Meer Noord-Holland 1438 AT",
    "addr:housenumber":"66",
    "addr:postcode":"meer;1438",
    "addr:street":"Aalsmeerderdk",
    "iso:country":"NL",
    "sg:address":"Aalsmeerderdk 66",
    "sg:city":"Oude Meer",
    "sg:orig_category":"Administratie- En Boekhoudkantoren",
    "sg:phone":"+31 20 502 2870",
    "sg:postcode":"1438 AT",
    "sg:province":"Noord-Holland",
    "wof:name":"Oemar",
    "wof:placetype":"venue"
},
  "geometry": {"coordinates":[-98.579796,34.781834],"type":"Point"}
}