{
  "type": "Feature",
  "properties": {
    "addr:full":"Wilhelminastraat 22 Mariahout Noord-Brabant 5738 AE",
    "addr:housenumber":"22",
    "addr:postcode":"5738 ae",
    "addr:street":"Wilhelminastraat",
    "iso:country":"NL",
    "sg:address":"Wilhelminastraat 22",
    "sg:city":"Mariahout",
    "sg:orig_category":"Landbouwmachines Gh",
    "sg:phone":"+31 499 421 627",
    "sg:postcode":"5738 AE",
    "sg:province":"Noord-Brabant",
    "wof:name":"Vereijken Bv",
    "wof:placetype":"venue"
},
  "geometry": {"coordinates":[5.576891,51.540428],"type":"Point"}
}