{
  "type": "Feature",
  "properties": {
    "addr:full":"Annerstreek 80 Annen Drenthe 9468 AR",
    "addr:housenumber":"80",
    "addr:postcode":"9468",
    "addr:street":"Annerstreek",
    "iso:country":"NL",
    "sg:address":"Annerstreek 80",
    "sg:city":"Annen",
    "sg:orig_category":"Metaalafval, Schrootrecycling And Sloperijen",
    "sg:phone":"+31 592 271 506",
    "sg:postcode":"9468 AR",
    "sg:province":"Drenthe",
    "wof:name":"B. Schuiling",
    "wof:placetype":"venue"
},
  "geometry": {"coordinates":[-79.253815,33.471233],"type":"Point"}
}