{
  "type": "Feature",
  "properties": {
    "addr:full":"Merwestr 3A Werkendam Noord-Brabant 4251 CR",
    "addr:housenumber":"3a",
    "addr:postcode":"4251 cr",
    "addr:street":"Merwestr",
    "iso:country":"NL",
    "sg:address":"Merwestr 3A",
    "sg:city":"Werkendam",
    "sg:orig_category":"Grafisch Ontwerpers",
    "sg:phone":"+31 183 503 508",
    "sg:postcode":"4251 CR",
    "sg:province":"Noord-Brabant",
    "wof:name":"Vos & Vos",
    "wof:placetype":"venue"
},
  "geometry": {"coordinates":[4.895124,51.814548],"type":"Point"}
}