{
  "type": "Feature",
  "properties": {
    "addr:full":"Rochussenstr 3 Delft Zuid-Holland 2613 BX",
    "addr:housenumber":"3",
    "addr:postcode":"2613 bx",
    "addr:street":"Rochussenstr",
    "iso:country":"NL",
    "sg:address":"Rochussenstr 3",
    "sg:city":"Delft",
    "sg:orig_category":"Fietsen En Bromfietsen",
    "sg:phone":"+31 15 212 2505",
    "sg:postcode":"2613 BX",
    "sg:province":"Zuid-Holland",
    "wof:name":"Plank, Van Der",
    "wof:placetype":"venue"
},
  "geometry": {"coordinates":[4.347151,52.012161],"type":"Point"}
}