{
  "type": "Feature",
  "properties": {
    "addr:full":"Ds S Tjadenstr C C114 Nieuwe Pekela Groningen 9663 RE",
    "addr:housenumber":"c114",
    "addr:postcode":"9663",
    "addr:street":"Ds S;C;Pekela",
    "iso:country":"NL",
    "sg:address":"Ds S Tjadenstr C C114",
    "sg:city":"Nieuwe Pekela",
    "sg:classifiers":[
        {
            "category":"Personal",
            "subcategory":"Nail Salon",
            "type":"Services"
        }
    ],
    "sg:phone":"+31 597 646 916",
    "sg:postcode":"9663 RE",
    "sg:province":"Groningen",
    "sg:tags":[
        "pedicure"
    ],
    "wof:name":"Marga",
    "wof:placetype":"venue"
},
  "geometry": {"coordinates":[6.956866,53.070999],"type":"Point"}
}