{
  "type": "Feature",
  "properties": {
    "addr:full":"Boelemaheerd 19 Groningen Groningen 9736 HA",
    "addr:housenumber":"19",
    "addr:postcode":"9736 ha",
    "addr:street":"Boelemaheerd",
    "iso:country":"NL",
    "sg:address":"Boelemaheerd 19",
    "sg:city":"Groningen",
    "sg:orig_category":"Verenigingen En Stichtingen",
    "sg:phone":"+31 50 579 9310",
    "sg:postcode":"9736 HA",
    "sg:province":"Groningen",
    "wof:name":"Posthuis, Sticht",
    "wof:placetype":"venue"
},
  "geometry": {"coordinates":[6.605224,53.24897],"type":"Point"}
}