{
  "type": "Feature",
  "properties": {
    "addr:full":"Peperstr 7 Beverwyk Noord-Holland 1941 GA",
    "addr:housenumber":"7",
    "addr:postcode":"1941 ga",
    "addr:street":"Peperstr",
    "iso:country":"NL",
    "sg:address":"Peperstr 7",
    "sg:city":"Beverwyk",
    "sg:classifiers":[
        {
            "category":"Retail",
            "subcategory":"Auto Repair",
            "type":"Services"
        }
    ],
    "sg:phone":"+31 251 224 629",
    "sg:postcode":"1941 GA",
    "sg:province":"Noord-Holland",
    "sg:tags":[
        "garage"
    ],
    "wof:name":"Erf, Van Der",
    "wof:placetype":"venue"
},
  "geometry": {"coordinates":[-83.222931,32.678131],"type":"Point"}
}