{
  "type": "Feature",
  "properties": {
    "iso:country":"NL",
    "sg:address":"Koraalstr 2",
    "sg:city":"Alkmaar",
    "sg:orig_category":"Autopoetsbedrijven",
    "sg:phone":"+31 72 547 0914",
    "sg:postcode":"1812 RK",
    "sg:province":"North Holland",
    "wof:name":"Polytop",
    "wof:placetype":"venue"
},
  "geometry": {"coordinates":[4.749507,52.610558],"type":"Point"}
}