{
  "type": "Feature",
  "properties": {
    "addr:full":"Noordeinde 17A Leiden South Holland 2311 CA",
    "addr:housenumber":"17a",
    "addr:postcode":"2311 ca",
    "addr:street":"Noordeinde",
    "iso:country":"NL",
    "sg:address":"Noordeinde 17A",
    "sg:city":"Leiden",
    "sg:orig_category":"Verzekeringen - Verzekeringskantoren",
    "sg:phone":"+31 71 514 6676",
    "sg:postcode":"2311 CA",
    "sg:province":"South Holland",
    "wof:name":"Rijnstreek Bv",
    "wof:placetype":"venue"
},
  "geometry": {"coordinates":[4.482753,52.160034],"type":"Point"}
}