{
  "type": "Feature",
  "properties": {
    "iso:country":"NL",
    "sg:address":"Keijzerstraat 3",
    "sg:city":"Stellendam",
    "sg:orig_category":"Goederenvervoer Over De Weg",
    "sg:phone":"+31 78 651 2688",
    "sg:postcode":"3251 AN",
    "sg:province":"South Holland",
    "wof:name":"S.J. Jansen Transport Vof",
    "wof:placetype":"venue"
},
  "geometry": {"coordinates":[4.024602,51.807369],"type":"Point"}
}