{
  "type": "Feature",
  "properties": {
    "addr:full":"Adm Helfrichstr 41 Herten Limburg 6049 AR",
    "addr:housenumber":"41",
    "addr:postcode":"6049",
    "iso:country":"NL",
    "sg:address":"Adm Helfrichstr 41",
    "sg:city":"Herten",
    "sg:orig_category":"Kermisexploitatie",
    "sg:phone":"+31 475 315 787",
    "sg:postcode":"6049 AR",
    "sg:province":"Limburg",
    "wof:name":"Stuy, P J",
    "wof:placetype":"venue"
},
  "geometry": {"coordinates":[5.967644,51.179344],"type":"Point"}
}