{
  "type": "Feature",
  "properties": {
    "addr:full":"Kastanjeln 60 Hilversum Noord-Holland 1214 LJ",
    "addr:housenumber":"60",
    "addr:postcode":"1214 lj",
    "addr:street":"Kastanjeln",
    "iso:country":"NL",
    "sg:address":"Kastanjeln 60",
    "sg:city":"Hilversum",
    "sg:orig_category":"Bedrijfsopleidingen",
    "sg:phone":"+31 35 621 9213",
    "sg:postcode":"1214 LJ",
    "sg:province":"Noord-Holland",
    "sg:website":"http://www.teppematrainingen.nl",
    "wof:name":"Teppema, Trainingen",
    "wof:placetype":"venue"
},
  "geometry": {"coordinates":[5.1695,52.228565],"type":"Point"}
}