{
  "type": "Feature",
  "properties": {
    "addr:full":"Heijermanslaan 15 Hilversum Noord-Holland 1215 JL",
    "addr:housenumber":"15",
    "addr:postcode":"1215 jl",
    "addr:street":"Heijermanslaan",
    "iso:country":"NL",
    "sg:address":"Heijermanslaan 15",
    "sg:city":"Hilversum",
    "sg:orig_category":"Artsen And Specialisten",
    "sg:phone":"+31 35 623 6880",
    "sg:postcode":"1215 JL",
    "sg:province":"Noord-Holland",
    "wof:name":"Drs. H.J. Stramrood",
    "wof:placetype":"venue"
},
  "geometry": {"coordinates":[5.1566,52.220997],"type":"Point"}
}