{
  "type": "Feature",
  "properties": {
    "addr:full":"Sumatrastraat 112 Leiden Zuid-Holland 2315 BD",
    "addr:housenumber":"112",
    "addr:postcode":"2315 bd",
    "addr:street":"Sumatrastraat",
    "iso:country":"NL",
    "sg:address":"Sumatrastraat 112",
    "sg:city":"Leiden",
    "sg:orig_category":"Bloemen And Planten",
    "sg:phone":"+31 71 522 5566",
    "sg:postcode":"2315 BD",
    "sg:province":"Zuid-Holland",
    "wof:name":"T Bloemenhoekje",
    "wof:placetype":"venue"
},
  "geometry": {"coordinates":[4.512068,52.166031],"type":"Point"}
}