{
  "type": "Feature",
  "properties": {
    "addr:full":"3E Industriewg 5 Asperen Gelderland 4147 CV",
    "addr:housenumber":"5",
    "addr:postcode":"4147 cv",
    "addr:street":"3E Industriewg;Gelderland",
    "iso:country":"NL",
    "sg:address":"3E Industriewg 5",
    "sg:city":"Asperen",
    "sg:orig_category":"Kantoor- En Bedrijfsmeubelen",
    "sg:phone":"+31 345 616 500",
    "sg:postcode":"4147 CV",
    "sg:province":"Gelderland",
    "wof:name":"Enpo Bv",
    "wof:placetype":"venue"
},
  "geometry": {"coordinates":[5.1125121117,51.8832817078],"type":"Point"}
}