{
  "type": "Feature",
  "properties": {
    "addr:full":"Van Vlotenstraat 23 'S Gravenhage Zuid-Holland 2523 JA",
    "addr:housenumber":"23",
    "addr:postcode":"2523 ja",
    "addr:street":"Van Vlotenstraat;' S",
    "iso:country":"NL",
    "sg:address":"Van Vlotenstraat 23",
    "sg:city":"'S Gravenhage",
    "sg:orig_category":"Vertaal- And Tolkenbureaus",
    "sg:phone":"+31 70 393 4901",
    "sg:postcode":"2523 JA",
    "sg:province":"Zuid-Holland",
    "wof:name":"M J Vd Lubbe-Van Gogh",
    "wof:placetype":"venue"
},
  "geometry": {"coordinates":[4.31724,52.055519],"type":"Point"}
}