{
  "type": "Feature",
  "properties": {
    "addr:full":"Hoogbrugstr 37 Maastricht Limburg 6221 CP",
    "addr:housenumber":"37",
    "addr:postcode":"6221 cp",
    "addr:street":"Hoogbrugstr",
    "iso:country":"NL",
    "sg:address":"Hoogbrugstr 37",
    "sg:city":"Maastricht",
    "sg:orig_category":"Psychotherapeuten",
    "sg:phone":"+31 43 321 5368",
    "sg:postcode":"6221 CP",
    "sg:province":"Limburg",
    "wof:name":"Bremer-Schulte, Dr M",
    "wof:placetype":"venue"
},
  "geometry": {"coordinates":[5.69999,50.847191],"type":"Point"}
}