{
  "type": "Feature",
  "properties": {
    "addr:full":"Postbus 65 Bunnik Utrecht 3980 CB",
    "addr:housenumber":"65",
    "addr:postcode":"3980 cb",
    "addr:street":"Postbus",
    "iso:country":"NL",
    "sg:address":"Postbus 65",
    "sg:city":"Bunnik",
    "sg:orig_category":"Verenigingen En Stichtingen",
    "sg:phone":"+31 30 657 0009",
    "sg:postcode":"3980 CB",
    "sg:province":"Utrecht",
    "sg:website":"http://www.humana.nl",
    "wof:name":"Humana, Sticht",
    "wof:placetype":"venue"
},
  "geometry": {"coordinates":[5.19958,52.067097],"type":"Point"}
}