{
  "type": "Feature",
  "properties": {
    "addr:full":"Dokter Brabersstraat 17 Roosendaal Noord-Brabant 4701 AT",
    "addr:housenumber":"17",
    "addr:postcode":"4701",
    "addr:street":"Dokter Brabersstraat",
    "iso:country":"NL",
    "sg:address":"Dokter Brabersstraat 17",
    "sg:city":"Roosendaal",
    "sg:orig_category":"Werving And Selectie Van Tijdelijk Personeel And Uitzendkantoren",
    "sg:phone":"+31 165 524 620",
    "sg:postcode":"4701 AT",
    "sg:province":"Noord-Brabant",
    "wof:name":"Unique Uitzendburo",
    "wof:placetype":"venue"
},
  "geometry": {"coordinates":[4.454059124,51.532207489],"type":"Point"}
}