{
  "type": "Feature",
  "properties": {
    "iso:country":"NL",
    "sg:address":"Knapenhoek 4",
    "sg:city":"Sint Oedenrode",
    "sg:orig_category":"Fotostudio'S And Fotografen",
    "sg:phone":"+31 413 478 647",
    "sg:postcode":"5492 AG",
    "sg:province":"North Brabant",
    "wof:name":"M.S. Lodewijk",
    "wof:placetype":"venue"
},
  "geometry": {"coordinates":[5.458834,51.56303],"type":"Point"}
}