{
  "type": "Feature",
  "properties": {
    "addr:full":"Z Meentstg 11 Rhenen Utrecht 3911 TD",
    "addr:housenumber":"11",
    "addr:postcode":"3911 td",
    "iso:country":"NL",
    "sg:address":"Z Meentstg 11",
    "sg:city":"Rhenen",
    "sg:orig_category":"Verpakkingen En Verpakkingsmaterialen",
    "sg:phone":"+31 317 681 186",
    "sg:postcode":"3911 TD",
    "sg:province":"Utrecht",
    "wof:name":"Keizer Int Vof",
    "wof:placetype":"venue"
},
  "geometry": {"coordinates":[5.567005,51.957603],"type":"Point"}
}