{
  "type": "Feature",
  "properties": {
    "addr:full":"Grote Noord 87 Hoorn Nh North Holland 1621 KG",
    "addr:housenumber":"87",
    "addr:postcode":"1621 kg",
    "addr:street":"Grote Noord;Nh North",
    "iso:country":"NL",
    "sg:address":"Grote Noord 87",
    "sg:city":"Hoorn Nh",
    "sg:orig_category":"Opticiens",
    "sg:phone":"+31 229 214 507",
    "sg:postcode":"1621 KG",
    "sg:province":"North Holland",
    "wof:name":"Osinga Optiek En Contactlenzen",
    "wof:placetype":"venue"
},
  "geometry": {"coordinates":[5.0555701256,52.6416969299],"type":"Point"}
}