{
  "type": "Feature",
  "properties": {
    "addr:full":"James Wattstraat 25 Leeuwarden Friesland 8912 AS",
    "addr:housenumber":"25",
    "addr:postcode":"8912 as",
    "addr:street":"James Wattstraat",
    "iso:country":"NL",
    "sg:address":"James Wattstraat 25",
    "sg:city":"Leeuwarden",
    "sg:orig_category":"Hout Gh",
    "sg:phone":"+31 58 213 4973",
    "sg:postcode":"8912 AS",
    "sg:province":"Friesland",
    "wof:name":"K. & G. Postma Bv",
    "wof:placetype":"venue"
},
  "geometry": {"coordinates":[5.760766,53.191299],"type":"Point"}
}