{
  "type": "Feature",
  "properties": {
    "addr:full":"Bergrand 228 Roosendaal Noord-Brabant 4707 AT",
    "addr:housenumber":"228",
    "addr:postcode":"4707",
    "addr:street":"Bergrand",
    "iso:country":"NL",
    "sg:address":"Bergrand 228",
    "sg:city":"Roosendaal",
    "sg:classifiers":[
        {
            "category":"Professional",
            "subcategory":"Accounting & Tax Preparation",
            "type":"Services"
        }
    ],
    "sg:phone":"+31 165 570 606",
    "sg:postcode":"4707 AT",
    "sg:province":"Noord-Brabant",
    "sg:tags":[
        "accountant"
    ],
    "wof:name":"Accountantskantoor Ooms",
    "wof:placetype":"venue"
},
  "geometry": {"coordinates":[4.448145,51.523529],"type":"Point"}
}