{
  "type": "Feature",
  "properties": {
    "addr:full":"Bultweg 30 De Bult NL.08 8346 KD",
    "addr:housenumber":"30",
    "addr:postcode":"nl.08 8346 kd",
    "addr:street":"Bultweg",
    "iso:country":"NL",
    "sg:address":"Bultweg 30",
    "sg:city":"De Bult",
    "sg:orig_category":"Kampeerterreinen",
    "sg:phone":"+31 521 512 674",
    "sg:postcode":"8346 KD",
    "sg:province":"NL.08",
    "wof:name":"Camping De Bult",
    "wof:placetype":"venue"
},
  "geometry": {"coordinates":[6.1195597649,52.8152236938],"type":"Point"}
}