{
  "type": "Feature",
  "properties": {
    "iso:country":"NL",
    "sg:address":"Kloosterstraat 10",
    "sg:city":"Tiel",
    "sg:orig_category":"Begrafenisondernemers",
    "sg:phone":"+31 344 613 007",
    "sg:postcode":"4001 NC",
    "sg:province":"Gelderland",
    "wof:name":"Uitvaartverzorging J. Tijssen",
    "wof:placetype":"venue"
},
  "geometry": {"coordinates":[5.436522,51.885342],"type":"Point"}
}