{
  "type": "Feature",
  "properties": {
    "addr:full":"Zoutkeetsgr 7 Amsterdam North Holland 1013 LC",
    "addr:housenumber":"7",
    "addr:postcode":"1013 lc",
    "addr:street":"Zoutkeetsgr",
    "iso:country":"NL",
    "sg:address":"Zoutkeetsgr 7",
    "sg:city":"Amsterdam",
    "sg:orig_category":"Beeldende Kunstenaars",
    "sg:phone":"+31 20 622 6442",
    "sg:postcode":"1013 LC",
    "sg:province":"North Holland",
    "wof:name":"Strijker, J A",
    "wof:placetype":"venue"
},
  "geometry": {"coordinates":[4.889937,52.388134],"type":"Point"}
}