{
  "type": "Feature",
  "properties": {
    "addr:full":"Talmabuurt 4 Balkbrug Overijssel 7707 RD",
    "addr:housenumber":"4",
    "addr:postcode":"7707 rd",
    "addr:street":"Talmabuurt",
    "iso:country":"NL",
    "sg:address":"Talmabuurt 4",
    "sg:city":"Balkbrug",
    "sg:orig_category":"Meubelmakerijen",
    "sg:phone":"+31 523 649 318",
    "sg:postcode":"7707 RD",
    "sg:province":"Overijssel",
    "wof:name":"Vrieling",
    "wof:placetype":"venue"
},
  "geometry": {"coordinates":[6.354491,52.625538],"type":"Point"}
}