{
  "type": "Feature",
  "properties": {
    "iso:country":"NL",
    "sg:address":"Prieswyk 46",
    "sg:city":"Elim",
    "sg:orig_category":"Bestratingen",
    "sg:phone":"+31 528 352 106",
    "sg:postcode":"7916 RD",
    "sg:province":"Provincie Drenthe",
    "wof:name":"Groote, Bert",
    "wof:placetype":"venue"
},
  "geometry": {"coordinates":[6.58208,52.682388],"type":"Point"}
}