{
  "type": "Feature",
  "properties": {
    "addr:full":"Neutronwg 8 Hoorn Nh North Holland 1627 LG",
    "addr:housenumber":"8",
    "addr:postcode":"1627 lg",
    "addr:street":"Neutronwg;Nh North",
    "iso:country":"NL",
    "sg:address":"Neutronwg 8",
    "sg:city":"Hoorn Nh",
    "sg:orig_category":"Verpakkingen En Verpakkingsmaterialen",
    "sg:phone":"+31 229 214 050",
    "sg:postcode":"1627 LG",
    "sg:province":"North Holland",
    "sg:website":"http://www.baasbusinessmarkt.nl",
    "wof:name":"Baas Business Market",
    "wof:placetype":"venue"
},
  "geometry": {"coordinates":[5.095352,52.640354],"type":"Point"}
}