{
  "type": "Feature",
  "properties": {
    "addr:full":"Hortensiastr 56 Zwolle NL.08 8013 AE",
    "addr:housenumber":"56",
    "addr:postcode":"8013 ae",
    "addr:street":"Hortensiastr",
    "iso:country":"NL",
    "sg:address":"Hortensiastr 56",
    "sg:city":"Zwolle",
    "sg:orig_category":"Koffie-Automaten",
    "sg:phone":"+31 38 421 6131",
    "sg:postcode":"8013 AE",
    "sg:province":"NL.08",
    "sg:website":"http://www.arron.nl",
    "wof:name":"Arron",
    "wof:placetype":"venue"
},
  "geometry": {"coordinates":[6.11047,52.50148],"type":"Point"}
}