{
  "type": "Feature",
  "properties": {
    "addr:full":"Hoogstraat 171 Rotterdam Zuid-Holland 3011 PM",
    "addr:housenumber":"171",
    "addr:postcode":"3011 pm",
    "addr:street":"Hoogstraat",
    "iso:country":"NL",
    "sg:address":"Hoogstraat 171",
    "sg:city":"Rotterdam",
    "sg:classifiers":[
        {
            "category":"Shopping",
            "subcategory":"Gifts & Souvenirs",
            "type":"Retail Goods"
        }
    ],
    "sg:phone":"+31 10 412 0447",
    "sg:postcode":"3011 PM",
    "sg:province":"Zuid-Holland",
    "sg:tags":[
        "geschenken"
    ],
    "wof:name":"Hallo",
    "wof:placetype":"venue"
},
  "geometry": {"coordinates":[4.485116,51.920883],"type":"Point"}
}