{
  "type": "Feature",
  "properties": {
    "addr:full":"Postbus 547 Hengelo Ov 7550 AM",
    "addr:housenumber":"547",
    "addr:postcode":"7550",
    "addr:street":"Postbus;Ov",
    "iso:country":"NL",
    "sg:address":"Postbus 547",
    "sg:city":"Hengelo Ov",
    "sg:orig_category":"Verenigingen En Stichtingen",
    "sg:phone":"+31 74 278 1035",
    "sg:postcode":"7550 AM",
    "wof:name":"Animato Accordeonver",
    "wof:placetype":"venue"
},
  "geometry": {"coordinates":[6.78971,52.266331],"type":"Point"}
}