{
  "type": "Feature",
  "properties": {
    "iso:country":"NL",
    "sg:address":"Oostergrachtswal 7",
    "sg:city":"Leeuwarden",
    "sg:orig_category":"Fietsen En Bromfietsen",
    "sg:phone":"+31 58 212 5017",
    "sg:postcode":"8921 AA",
    "sg:province":"Friesland",
    "wof:name":"Tigchelaar, Rijwielhandel J",
    "wof:placetype":"venue"
},
  "geometry": {"coordinates":[5.803787,53.202534],"type":"Point"}
}