{
  "type": "Feature",
  "properties": {
    "iso:country":"NL",
    "sg:address":"Pluuthaven 35",
    "sg:city":"Zeewolde",
    "sg:orig_category":"Binnenhuisarchitectuur",
    "sg:phone":"+31 36 522 5938",
    "sg:postcode":"3891 AW",
    "sg:province":"NL.",
    "wof:name":"Kunst, J",
    "wof:placetype":"venue"
},
  "geometry": {"coordinates":[5.547163,52.334915],"type":"Point"}
}