{
  "type": "Feature",
  "properties": {
    "iso:country":"NL",
    "sg:address":"J Stewartstr 258",
    "sg:city":"Almere",
    "sg:orig_category":"Organisatiebureaus",
    "sg:phone":"+31 36 537 6400",
    "sg:postcode":"1325 JN",
    "sg:province":"Flevoland",
    "wof:name":"Draoidh Bv",
    "wof:placetype":"venue"
},
  "geometry": {"coordinates":[5.2329478264,52.3692474365],"type":"Point"}
}