{
  "type": "Feature",
  "properties": {
    "addr:full":"Heringsaweg 10 Vragender Gelderland 7134 RC",
    "addr:housenumber":"10",
    "addr:postcode":"7134 rc",
    "addr:street":"Heringsaweg;Gelderland",
    "iso:country":"NL",
    "sg:address":"Heringsaweg 10",
    "sg:city":"Vragender",
    "sg:orig_category":"Goederenvervoer Over De Weg",
    "sg:phone":"+31 544 462 114",
    "sg:postcode":"7134 RC",
    "sg:province":"Gelderland",
    "wof:name":"Transportbedrijf J. Harbers Vof",
    "wof:placetype":"venue"
},
  "geometry": {"coordinates":[6.589399,51.994488],"type":"Point"}
}