{
  "type": "Feature",
  "properties": {
    "addr:full":"Haverpln 7 Groningen Groningen 9734 AK",
    "addr:housenumber":"7",
    "addr:postcode":"9734 ak",
    "addr:street":"Haverpln",
    "iso:country":"NL",
    "sg:address":"Haverpln 7",
    "sg:city":"Groningen",
    "sg:orig_category":"Autorijscholen",
    "sg:phone":"+31 50 541 6129",
    "sg:postcode":"9734 AK",
    "sg:province":"Groningen",
    "wof:name":"Schaank Autorijschool",
    "wof:placetype":"venue"
},
  "geometry": {"coordinates":[6.63058,53.232151],"type":"Point"}
}