{
  "type": "Feature",
  "properties": {
    "iso:country":"NL",
    "sg:address":"Hammerstr 16",
    "sg:city":"Herkenbosch",
    "sg:orig_category":"Verenigingen En Stichtingen",
    "sg:phone":"+31 475 531 861",
    "sg:postcode":"6075 AK",
    "sg:province":"Limburg",
    "wof:name":"Joc, Sticht",
    "wof:placetype":"venue"
},
  "geometry": {"coordinates":[6.058699,51.151703],"type":"Point"}
}