{
  "type": "Feature",
  "properties": {
    "addr:full":"Tynjedk 76 Leeuwarden Friesland 8936 AD",
    "addr:housenumber":"76",
    "addr:postcode":"8936 ad",
    "addr:street":"Tynjedk",
    "iso:country":"NL",
    "sg:address":"Tynjedk 76",
    "sg:city":"Leeuwarden",
    "sg:orig_category":"Boeken En Tijdschriften",
    "sg:phone":"+31 58 280 2658",
    "sg:postcode":"8936 AD",
    "sg:province":"Friesland",
    "wof:name":"Bruna",
    "wof:placetype":"venue"
},
  "geometry": {"coordinates":[5.817075,53.190887],"type":"Point"}
}