{
  "type": "Feature",
  "properties": {
    "iso:country":"NL",
    "sg:address":"Bartolesstr 17",
    "sg:city":"Visvliet",
    "sg:orig_category":"Verzekeringen - Verzekeringskantoren",
    "sg:phone":"+31 594 212 291",
    "sg:postcode":"9845 AK",
    "sg:province":"Groningen",
    "wof:name":"Visser, H",
    "wof:placetype":"venue"
},
  "geometry": {"coordinates":[6.248796,53.265259],"type":"Point"}
}