{
  "type": "Feature",
  "properties": {
    "addr:full":"Taborstraat 4 Rotterdam Zuid-Holland 3061 EW",
    "addr:housenumber":"4",
    "addr:postcode":"3061 ew",
    "addr:street":"Taborstraat",
    "iso:country":"NL",
    "sg:address":"Taborstraat 4",
    "sg:city":"Rotterdam",
    "sg:orig_category":"Damesmodezaken",
    "sg:phone":"+31 10 411 6415",
    "sg:postcode":"3061 EW",
    "sg:province":"Zuid-Holland",
    "wof:name":"Orange Outlet",
    "wof:placetype":"venue"
},
  "geometry": {"coordinates":[4.509243,51.927505],"type":"Point"}
}