{
  "type": "Feature",
  "properties": {
    "iso:country":"NL",
    "sg:address":"Westerwolde 18",
    "sg:city":"Lelystad",
    "sg:orig_category":"Grafisch Ontwerpers",
    "sg:phone":"+31 320 216 267",
    "sg:postcode":"8245 DD",
    "sg:province":"NL.",
    "wof:name":"Noort",
    "wof:placetype":"venue"
},
  "geometry": {"coordinates":[5.469575,52.495872],"type":"Point"}
}