{
  "type": "Feature",
  "properties": {
    "iso:country":"NL",
    "sg:address":"De Barch 2",
    "sg:city":"Maasland",
    "sg:orig_category":"Artsen And Specialisten",
    "sg:phone":"+31 10 591 2046",
    "sg:postcode":"3155 BB",
    "sg:province":"Zuid-Holland",
    "wof:name":"C.M.J. Van Hees",
    "wof:placetype":"venue"
},
  "geometry": {"coordinates":[4.270249,51.932041],"type":"Point"}
}