{
  "type": "Feature",
  "properties": {
    "addr:full":"Rode Zee 2 Zaandam Noord-Holland 1503 TN",
    "addr:housenumber":"2",
    "addr:postcode":"1503",
    "addr:street":"Rode Zee",
    "iso:country":"NL",
    "sg:address":"Rode Zee 2",
    "sg:city":"Zaandam",
    "sg:orig_category":"Administratie- En Boekhoudkantoren",
    "sg:phone":"+31 75 617 2531",
    "sg:postcode":"1503 TN",
    "sg:province":"Noord-Holland",
    "wof:name":"Integraal Hoogland",
    "wof:placetype":"venue"
},
  "geometry": {"coordinates":[4.842245,52.449421],"type":"Point"}
}