{
  "type": "Feature",
  "properties": {
    "addr:full":"Janninkswg 60 Enschede Overijssel 7513 DL",
    "addr:housenumber":"60",
    "addr:postcode":"7513 dl",
    "addr:street":"Janninkswg",
    "iso:country":"NL",
    "sg:address":"Janninkswg 60",
    "sg:city":"Enschede",
    "sg:orig_category":"Antiquiteiten",
    "sg:phone":"+31 53 432 4777",
    "sg:postcode":"7513 DL",
    "sg:province":"Overijssel",
    "wof:name":"Meinema, A",
    "wof:placetype":"venue"
},
  "geometry": {"coordinates":[6.879391,52.213402],"type":"Point"}
}