{
  "type": "Feature",
  "properties": {
    "addr:full":"Koestr 12 Tilburg Noord-Brabant 5014 ED",
    "addr:housenumber":"12",
    "addr:postcode":"5014 ed",
    "addr:street":"Koestr",
    "iso:country":"NL",
    "sg:address":"Koestr 12",
    "sg:city":"Tilburg",
    "sg:orig_category":"Koffie- En Theehuizen",
    "sg:phone":"+31 13 542 1616",
    "sg:postcode":"5014 ED",
    "sg:province":"Noord-Brabant",
    "wof:name":"Shiva",
    "wof:placetype":"venue"
},
  "geometry": {"coordinates":[5.106271,51.554928],"type":"Point"}
}