{
  "type": "Feature",
  "properties": {
    "iso:country":"NL",
    "sg:address":"De Steiger 200",
    "sg:city":"Almere",
    "sg:orig_category":"Geluidsinstallaties - Verhuur",
    "sg:phone":"+31 36 534 9496",
    "sg:postcode":"1351 AW",
    "sg:province":"Flevoland",
    "wof:name":"Smit",
    "wof:placetype":"venue"
},
  "geometry": {"coordinates":[5.223528,52.347954],"type":"Point"}
}