{
  "type": "Feature",
  "properties": {
    "addr:full":"Theresiastraat 145 'S Gravenhage South Holland 2593 AG",
    "addr:housenumber":"145 '",
    "addr:postcode":"2593",
    "addr:street":"Theresiastraat",
    "iso:country":"NL",
    "sg:address":"Theresiastraat 145",
    "sg:city":"'S Gravenhage",
    "sg:orig_category":"Fitnesscentra",
    "sg:phone":"+31 70 382 0203",
    "sg:postcode":"2593 AG",
    "sg:province":"South Holland",
    "wof:name":"Slagman Sportcentrum",
    "wof:placetype":"venue"
},
  "geometry": {"coordinates":[4.337873,52.086426],"type":"Point"}
}