{
  "type": "Feature",
  "properties": {
    "addr:full":"Hoefstraat 200 Tilburg North Brabant 5014 NP",
    "addr:housenumber":"200",
    "addr:postcode":"5014 np",
    "addr:street":"Hoefstraat",
    "iso:country":"NL",
    "sg:address":"Hoefstraat 200",
    "sg:city":"Tilburg",
    "sg:orig_category":"Bejaardeninstellingen And Serviceflats",
    "sg:phone":"+31 13 543 0295",
    "sg:postcode":"5014 NP",
    "sg:province":"North Brabant",
    "wof:name":"Pensiontehuis Van Opstal-Van Der Voort",
    "wof:placetype":"venue"
},
  "geometry": {"coordinates":[5.091076,51.570938],"type":"Point"}
}