{
  "type": "Feature",
  "properties": {
    "addr:full":"Genenberg 5 Sint Michielsgestel Noord-Brabant 5271 SE",
    "addr:housenumber":"5;michielsgestel",
    "addr:postcode":"5271 se",
    "addr:street":"Genenberg",
    "iso:country":"NL",
    "sg:address":"Genenberg 5",
    "sg:city":"Sint Michielsgestel",
    "sg:classifiers":[
        {
            "category":"Fast Food",
            "type":"Food & Drink"
        }
    ],
    "sg:phone":"+31 73 551 3472",
    "sg:postcode":"5271 SE",
    "sg:province":"Noord-Brabant",
    "sg:tags":[
        "afhaal",
        "restaurant"
    ],
    "wof:name":"C L De Raden",
    "wof:placetype":"venue"
},
  "geometry": {"coordinates":[5.35675,51.634567],"type":"Point"}
}