{
  "type": "Feature",
  "properties": {
    "addr:full":"Belle Van Zuylenstraat 64 Arnhem Gelderland 6836 PZ",
    "addr:housenumber":"64",
    "addr:postcode":"6836 pz",
    "addr:street":"Belle Van Zuylenstraat",
    "iso:country":"NL",
    "sg:address":"Belle Van Zuylenstraat 64",
    "sg:city":"Arnhem",
    "sg:orig_category":"Diverse Grafische Activiteiten",
    "sg:phone":"+31 26 327 2106",
    "sg:postcode":"6836 PZ",
    "sg:province":"Gelderland",
    "wof:name":"A4 Plus",
    "wof:placetype":"venue"
},
  "geometry": {"coordinates":[5.88806,51.94223],"type":"Point"}
}