{
  "type": "Feature",
  "properties": {
    "addr:full":"Paltrok 50 Amsterdam North Holland 1035 AH",
    "addr:housenumber":"50",
    "addr:postcode":"1035 ah",
    "addr:street":"Paltrok",
    "iso:country":"NL",
    "sg:address":"Paltrok 50",
    "sg:city":"Amsterdam",
    "sg:orig_category":"Yoga-Instituten",
    "sg:phone":"+31 20 631 0624",
    "sg:postcode":"1035 AH",
    "sg:province":"North Holland",
    "wof:name":"Kruif, Tom De",
    "wof:placetype":"venue"
},
  "geometry": {"coordinates":[4.888053,52.420273],"type":"Point"}
}