{
  "type": "Feature",
  "properties": {
    "addr:full":"Langewg 11 Nieuw Beyerland Zuid-Holland 3264 LA",
    "addr:housenumber":"11",
    "addr:postcode":"3264 la",
    "addr:street":"Langewg;Nieuw Beyerland",
    "iso:country":"NL",
    "sg:address":"Langewg 11",
    "sg:city":"Nieuw Beyerland",
    "sg:orig_category":"Verzekeringen - Verzekeringskantoren",
    "sg:phone":"+31 186 662 669",
    "sg:postcode":"3264 LA",
    "sg:province":"Zuid-Holland",
    "sg:website":"http://www.petersadviseurs.nl",
    "wof:name":"Peters, P",
    "wof:placetype":"venue"
},
  "geometry": {"coordinates":[4.362854,51.785721],"type":"Point"}
}