{
  "type": "Feature",
  "properties": {
    "addr:full":"Heer Hugostr 2 Rotterdam Zuid-Holland 3061 NL",
    "addr:housenumber":"2",
    "addr:postcode":"3061 nl",
    "addr:street":"Heer Hugostr",
    "iso:country":"NL",
    "sg:address":"Heer Hugostr 2",
    "sg:city":"Rotterdam",
    "sg:orig_category":"Medische Installaties En Instrumenten",
    "sg:phone":"+31 10 452 0233",
    "sg:postcode":"3061 NL",
    "sg:province":"Zuid-Holland",
    "wof:name":"Wimac",
    "wof:placetype":"venue"
},
  "geometry": {"coordinates":[4.503751,51.929447],"type":"Point"}
}