{
  "type": "Feature",
  "properties": {
    "addr:full":"Kloveniersburgwal 20 Amsterdam Noord-Holland 1012 CV",
    "addr:housenumber":"20",
    "addr:postcode":"1012 cv",
    "addr:street":"Kloveniersburgwal",
    "iso:country":"NL",
    "sg:address":"Kloveniersburgwal 20",
    "sg:city":"Amsterdam",
    "sg:classifiers":[
        {
            "category":"Travel",
            "subcategory":"Hotels & Motels",
            "type":"Entertainment"
        }
    ],
    "sg:phone":"+31 20 330 6241",
    "sg:postcode":"1012 CV",
    "sg:province":"Noord-Holland",
    "sg:website":"http://www.zosa-online.com",
    "wof:name":"Zosa",
    "wof:placetype":"venue"
},
  "geometry": {"coordinates":[4.899006,52.371727],"type":"Point"}
}