{
  "type": "Feature",
  "properties": {
    "addr:full":"Drieboomln 125 Hoorn Nh North Holland 1624 BD",
    "addr:housenumber":"125",
    "addr:postcode":"1624 bd",
    "addr:street":"Nh North",
    "iso:country":"NL",
    "sg:address":"Drieboomln 125",
    "sg:city":"Hoorn Nh",
    "sg:orig_category":"Fietsen En Bromfietsen",
    "sg:phone":"+31 229 215 467",
    "sg:postcode":"1624 BD",
    "sg:province":"North Holland",
    "wof:name":"Profile De Fietsenmaker",
    "wof:placetype":"venue"
},
  "geometry": {"coordinates":[5.063561,52.647072],"type":"Point"}
}