{
  "type": "Feature",
  "properties": {
    "addr:full":"Haspelwg 35A Deurne Noord-Brabant 5751 JH",
    "addr:housenumber":"35a",
    "addr:postcode":"5751 jh",
    "addr:street":"Haspelwg",
    "iso:country":"NL",
    "sg:address":"Haspelwg 35A",
    "sg:city":"Deurne",
    "sg:classifiers":[
        {
            "category":"Retail",
            "subcategory":"Auto Repair",
            "type":"Services"
        }
    ],
    "sg:phone":"+31 493 315 991",
    "sg:postcode":"5751 JH",
    "sg:province":"Noord-Brabant",
    "sg:tags":[
        "garage"
    ],
    "wof:name":"Roefs, Willie",
    "wof:placetype":"venue"
},
  "geometry": {"coordinates":[5.781848,51.458012],"type":"Point"}
}