{
  "type": "Feature",
  "properties": {
    "iso:country":"NL",
    "sg:address":"Reinaldstraat 40",
    "sg:city":"Valkenburg Lb",
    "sg:orig_category":"Boekenuitgeverijen",
    "sg:phone":"+31 43 601 5045",
    "sg:postcode":"6301 EC",
    "sg:province":"Limburg",
    "wof:name":"Uitgeversmaatschappij Limburgs Dagblad Bv",
    "wof:placetype":"venue"
},
  "geometry": {"coordinates":[5.834773,50.865871],"type":"Point"}
}