{
  "type": "Feature",
  "properties": {
    "addr:full":"Hof Der Toekomst 21 Amersfoort Utrecht 3823 HX",
    "addr:housenumber":"21",
    "addr:postcode":"3823 hx",
    "addr:street":"Hof Der Toekomst",
    "iso:country":"NL",
    "sg:address":"Hof Der Toekomst 21",
    "sg:city":"Amersfoort",
    "sg:orig_category":"Homeopathie",
    "sg:phone":"+31 33 456 1215",
    "sg:postcode":"3823 HX",
    "sg:province":"Utrecht",
    "wof:name":"Leeuwen, J M Van",
    "wof:placetype":"venue"
},
  "geometry": {"coordinates":[5.388088,52.192764],"type":"Point"}
}