{
  "type": "Feature",
  "properties": {
    "iso:country":"NL",
    "sg:address":"Gozewynstr 44",
    "sg:city":"Kudelstaart",
    "sg:orig_category":"Kantoor- En Interieurbeplanting",
    "sg:phone":"+31 297 322 961",
    "sg:postcode":"1433 JC",
    "sg:province":"North Holland",
    "wof:name":"Pajoplant",
    "wof:placetype":"venue"
},
  "geometry": {"coordinates":[4.7465882301,52.2313957214],"type":"Point"}
}