{
  "type": "Feature",
  "properties": {
    "addr:full":"Westergo 51 Zoetermeer Zuid-Holland 2716 CA",
    "addr:housenumber":"51",
    "addr:postcode":"2716 ca",
    "addr:street":"Westergo",
    "iso:country":"NL",
    "sg:address":"Westergo 51",
    "sg:city":"Zoetermeer",
    "sg:orig_category":"Adviesbureaus Bedrijfsorganisatie",
    "sg:phone":"+31 79 351 6983",
    "sg:postcode":"2716 CA",
    "sg:province":"Zuid-Holland",
    "wof:name":"Gerssen",
    "wof:placetype":"venue"
},
  "geometry": {"coordinates":[4.460509,52.052326],"type":"Point"}
}