{
  "type": "Feature",
  "properties": {
    "addr:full":"Willebrordstraat 46 Ijmuiden Noord-Holland 1971 DD",
    "addr:housenumber":"46",
    "addr:postcode":"1971 dd",
    "addr:street":"Willebrordstraat",
    "iso:country":"NL",
    "sg:address":"Willebrordstraat 46",
    "sg:city":"Ijmuiden",
    "sg:orig_category":"Boekhouders",
    "sg:phone":"+31 255 520 306",
    "sg:postcode":"1971 DD",
    "sg:province":"Noord-Holland",
    "wof:name":"K. Meijer",
    "wof:placetype":"venue"
},
  "geometry": {"coordinates":[4.629004,52.462376],"type":"Point"}
}