{
  "type": "Feature",
  "properties": {
    "iso:country":"NL",
    "sg:address":"Zinkstraat 1",
    "sg:city":"Ridderkerk",
    "sg:orig_category":"Meubels And Huishoudapparatuur Gh",
    "sg:phone":"+31 180 434 982",
    "sg:postcode":"2984 AL",
    "sg:province":"Zuid-Holland",
    "wof:name":"Ceha Products",
    "wof:placetype":"venue"
},
  "geometry": {"coordinates":[4.604395,51.873817],"type":"Point"}
}