{
  "type": "Feature",
  "properties": {
    "addr:full":"Molenweg 31 Giethoorn NL.08 8355 AS",
    "addr:housenumber":"31;nl.08",
    "addr:postcode":"8355",
    "addr:street":"Molenweg",
    "iso:country":"NL",
    "sg:address":"Molenweg 31",
    "sg:city":"Giethoorn",
    "sg:orig_category":"Juridische Dienstverlening",
    "sg:phone":"+31 521 362 898",
    "sg:postcode":"8355 AS",
    "sg:province":"NL.08",
    "wof:name":"Mr. L.C. V.D. Veer",
    "wof:placetype":"venue"
},
  "geometry": {"coordinates":[6.082355,52.742134],"type":"Point"}
}