{
  "type": "Feature",
  "properties": {
    "addr:full":"Verschuurweg 2 Etten-Leur Noord-Brabant 4878 AB",
    "addr:housenumber":"2",
    "addr:postcode":"4878 ab",
    "addr:street":"Verschuurweg",
    "iso:country":"NL",
    "sg:address":"Verschuurweg 2",
    "sg:city":"Etten-Leur",
    "sg:orig_category":"Diverse Bedrijfsinstallaties Gh",
    "sg:phone":"+31 76 502 2227",
    "sg:postcode":"4878 AB",
    "sg:province":"Noord-Brabant",
    "wof:name":"Visser Watervoorzieningen En Beregenings",
    "wof:placetype":"venue"
},
  "geometry": {"coordinates":[4.622541,51.571247],"type":"Point"}
}