{
  "type": "Feature",
  "properties": {
    "addr:full":"Galileiplantsoen 6 Amsterdam North Holland 1098 NA",
    "addr:housenumber":"6",
    "addr:postcode":"1098 na",
    "addr:street":"Galileiplantsoen",
    "iso:country":"NL",
    "sg:address":"Galileiplantsoen 6",
    "sg:city":"Amsterdam",
    "sg:orig_category":"Film-, Tv- And Videoproductie",
    "sg:phone":"+31 20 694 3025",
    "sg:postcode":"1098 NA",
    "sg:province":"North Holland",
    "wof:name":"Joop Van Essen Filmprodukties",
    "wof:placetype":"venue"
},
  "geometry": {"coordinates":[4.937681,52.352135],"type":"Point"}
}