{
  "type": "Feature",
  "properties": {
    "addr:full":"Borchsateln 61 Rotterdam South Holland 3055 ZG",
    "addr:housenumber":"61",
    "addr:postcode":"3055 zg",
    "addr:street":"Borchsateln",
    "iso:country":"NL",
    "sg:address":"Borchsateln 61",
    "sg:city":"Rotterdam",
    "sg:orig_category":"Pompen",
    "sg:phone":"+31 10 422 2896",
    "sg:postcode":"3055 ZG",
    "sg:province":"South Holland",
    "sg:website":"http://www.krolpompen.nl",
    "wof:name":"Krol Pompen",
    "wof:placetype":"venue"
},
  "geometry": {"coordinates":[4.50689,51.961319],"type":"Point"}
}