{
  "type": "Feature",
  "properties": {
    "addr:full":"Reigerhof 91 Nieuwerkerk Ad Ijssel Zuid-Holland 2914 KD",
    "addr:housenumber":"91",
    "addr:postcode":"ijssel;2914 kd",
    "addr:street":"Reigerhof",
    "iso:country":"NL",
    "sg:address":"Reigerhof 91",
    "sg:city":"Nieuwerkerk Ad Ijssel",
    "sg:orig_category":"Opticiens",
    "sg:phone":"+31 180 317 232",
    "sg:postcode":"2914 KD",
    "sg:province":"Zuid-Holland",
    "wof:name":"Groeneveld Brillen",
    "wof:placetype":"venue"
},
  "geometry": {"coordinates":[4.6166582108,51.9681243896],"type":"Point"}
}