{
  "type": "Feature",
  "properties": {
    "addr:full":"Bloemenstr 31 Bemmel Gelderland 6681 NM",
    "addr:housenumber":"31",
    "addr:postcode":"6681",
    "addr:street":"Bloemenstr;Gelderland",
    "iso:country":"NL",
    "sg:address":"Bloemenstr 31",
    "sg:city":"Bemmel",
    "sg:orig_category":"Boomverzorging",
    "sg:phone":"+31 6 51174120",
    "sg:postcode":"6681 NM",
    "sg:province":"Gelderland",
    "wof:name":"Jansen",
    "wof:placetype":"venue"
},
  "geometry": {"coordinates":[5.886406,51.892204],"type":"Point"}
}