{
  "type": "Feature",
  "properties": {
    "addr:full":"Ratelaar 5 Maarheeze Noord-Brabant 6026 AL",
    "addr:housenumber":"5",
    "addr:postcode":"6026 al",
    "addr:street":"Ratelaar",
    "iso:country":"NL",
    "sg:address":"Ratelaar 5",
    "sg:city":"Maarheeze",
    "sg:orig_category":"Muziekinstrumenten - Fabrieken En Groothandel",
    "sg:phone":"+31 495 592 730",
    "sg:postcode":"6026 AL",
    "sg:province":"Noord-Brabant",
    "wof:name":"Vos, H De",
    "wof:placetype":"venue"
},
  "geometry": {"coordinates":[5.61926,51.307461],"type":"Point"}
}