{
  "type": "Feature",
  "properties": {
    "iso:country":"NL",
    "sg:address":"Mgr Nolensstr 11",
    "sg:city":"Ryen",
    "sg:orig_category":"Meubelen",
    "sg:phone":"+31 161 225 978",
    "sg:postcode":"5121 AL",
    "sg:province":"North Brabant",
    "wof:name":"Pame Design",
    "wof:placetype":"venue"
},
  "geometry": {"coordinates":[4.9197,51.588017],"type":"Point"}
}