{
  "type": "Feature",
  "properties": {
    "iso:country":"NL",
    "sg:address":"Kerkstraat 51",
    "sg:city":"Randwijk",
    "sg:orig_category":"Verlichting And Huishoudartikelen",
    "sg:phone":"+31 488 491 429",
    "sg:postcode":"6668 AP",
    "sg:province":"Gelderland",
    "wof:name":"Vof G. Floor",
    "wof:placetype":"venue"
},
  "geometry": {"coordinates":[5.709882,51.95105],"type":"Point"}
}