{
  "type": "Feature",
  "properties": {
    "addr:full":"V Harenstr 4/C Wolvega Friesland 8471 JD",
    "addr:housenumber":"4 / c",
    "addr:postcode":"8471 jd",
    "addr:street":"Harenstr",
    "iso:country":"NL",
    "sg:address":"V Harenstr 4/C",
    "sg:city":"Wolvega",
    "sg:orig_category":"Drogisterijen",
    "sg:phone":"+31 561 617 531",
    "sg:postcode":"8471 JD",
    "sg:province":"Friesland",
    "wof:name":"Kruidvat",
    "wof:placetype":"venue"
},
  "geometry": {"coordinates":[5.99809,52.87521],"type":"Point"}
}