{
  "type": "Feature",
  "properties": {
    "addr:full":"Vaart Zz 35 Nieuw Amsterdam Drenthe 7833 AB",
    "addr:housenumber":"35",
    "addr:postcode":"7833 ab",
    "addr:street":"Vaart Zz",
    "iso:country":"NL",
    "sg:address":"Vaart Zz 35",
    "sg:city":"Nieuw Amsterdam",
    "sg:orig_category":"Schoenen - Reparaties",
    "sg:phone":"+31 591 351 457",
    "sg:postcode":"7833 AB",
    "sg:province":"Drenthe",
    "wof:name":"Bakker",
    "wof:placetype":"venue"
},
  "geometry": {"coordinates":[6.855021,52.7155],"type":"Point"}
}