{
  "type": "Feature",
  "properties": {
    "addr:full":"Toorenvliedtwg 1 Middelburg Zeeland 4335 HE",
    "addr:housenumber":"1",
    "addr:postcode":"4335 he",
    "addr:street":"Toorenvliedtwg",
    "iso:country":"NL",
    "sg:address":"Toorenvliedtwg 1",
    "sg:city":"Middelburg",
    "sg:orig_category":"Hulpverlening Sociaal",
    "sg:phone":"+31 118 613 226",
    "sg:postcode":"4335 HE",
    "sg:province":"Zeeland",
    "wof:name":"Azz, Sticht",
    "wof:placetype":"venue"
},
  "geometry": {"coordinates":[3.60027,51.491402],"type":"Point"}
}