{
  "type": "Feature",
  "properties": {
    "addr:full":"C Verolmewg 9 Sassenheim Zuid-Holland 2171 KV",
    "addr:housenumber":"9",
    "addr:postcode":"2171 kv",
    "iso:country":"NL",
    "sg:address":"C Verolmewg 9",
    "sg:city":"Sassenheim",
    "sg:orig_category":"Mode Artikelen Dames En Heren - Fabrieken En Groothandel",
    "sg:phone":"+31 252 218 503",
    "sg:postcode":"2171 KV",
    "sg:province":"Zuid-Holland",
    "wof:name":"Paletti Collections Bv",
    "wof:placetype":"venue"
},
  "geometry": {"coordinates":[4.507625,52.214363],"type":"Point"}
}