{
  "type": "Feature",
  "properties": {
    "addr:full":"Bleekerweg 24 Heusden Gem Asten North Brabant 5725 BE",
    "addr:housenumber":"24",
    "addr:postcode":"5725",
    "addr:street":"Bleekerweg",
    "iso:country":"NL",
    "sg:address":"Bleekerweg 24",
    "sg:city":"Heusden Gem Asten",
    "sg:orig_category":"Pluimveehouderijen",
    "sg:phone":"+31 493 565 228",
    "sg:postcode":"5725 BE",
    "sg:province":"North Brabant",
    "wof:name":"J.M. V.D. Velden-Van Tilburg",
    "wof:placetype":"venue"
},
  "geometry": {"coordinates":[5.782547,51.38213],"type":"Point"}
}