{
  "type": "Feature",
  "properties": {
    "addr:full":"Amsterdamsewg 30 Velsen Zuid North Holland 1981 LE",
    "addr:housenumber":"30;1981",
    "addr:postcode":"le",
    "addr:street":"Amsterdamsewg;Velsen Zuid North Holland",
    "iso:country":"NL",
    "sg:address":"Amsterdamsewg 30",
    "sg:city":"Velsen Zuid",
    "sg:classifiers":[
        {
            "category":"Sports & Exercise",
            "subcategory":"Stables",
            "type":"Entertainment"
        }
    ],
    "sg:phone":"+31 255 534 547",
    "sg:postcode":"1981 LE",
    "sg:province":"North Holland",
    "sg:tags":[
        "maneges"
    ],
    "wof:name":"Groene Heuvel, De",
    "wof:placetype":"venue"
},
  "geometry": {"coordinates":[4.685225,52.445938],"type":"Point"}
}