{
  "type": "Feature",
  "properties": {
    "addr:full":"Grevengoedln 99 Doetinchem Gelderland 7009 DZ",
    "addr:housenumber":"99",
    "addr:postcode":"7009 dz",
    "addr:street":"Grevengoedln;Gelderland",
    "iso:country":"NL",
    "sg:address":"Grevengoedln 99",
    "sg:city":"Doetinchem",
    "sg:orig_category":"Homeopathie",
    "sg:phone":"+31 314 326 167",
    "sg:postcode":"7009 DZ",
    "sg:province":"Gelderland",
    "wof:name":"Liesveld, H G",
    "wof:placetype":"venue"
},
  "geometry": {"coordinates":[6.294572,51.981987],"type":"Point"}
}