{
  "type": "Feature",
  "properties": {
    "iso:country":"NL",
    "sg:address":"Raadhuisstr 52",
    "sg:city":"Amsterdam",
    "sg:orig_category":"Modellenbureaus En Modellen Freelance",
    "sg:phone":"+31 20 627 0406",
    "sg:postcode":"1016 DG",
    "sg:province":"Noord-Holland",
    "wof:name":"Euromodel Bv",
    "wof:placetype":"venue"
},
  "geometry": {"coordinates":[4.885747,52.373993],"type":"Point"}
}