{
  "type": "Feature",
  "properties": {
    "addr:full":"Industriestr 12 Stadskanaal Groningen 9502 EJ",
    "addr:housenumber":"12",
    "addr:postcode":"9502 ej",
    "addr:street":"Industriestr",
    "iso:country":"NL",
    "sg:address":"Industriestr 12",
    "sg:city":"Stadskanaal",
    "sg:orig_category":"Betonindustrie",
    "sg:phone":"+31 599 620 103",
    "sg:postcode":"9502 EJ",
    "sg:province":"Groningen",
    "wof:name":"Drents Groningse Betonindustrie Bv",
    "wof:placetype":"venue"
},
  "geometry": {"coordinates":[6.980593,52.973129],"type":"Point"}
}