{
  "type": "Feature",
  "properties": {
    "addr:full":"Struytse Hoeck 63F Hellevoetsluis Zuid-Holland 3224 HA",
    "addr:housenumber":"63f",
    "addr:postcode":"3224 ha",
    "addr:street":"Struytse Hoeck",
    "iso:country":"NL",
    "sg:address":"Struytse Hoeck 63F",
    "sg:city":"Hellevoetsluis",
    "sg:orig_category":"Bloemen And Planten",
    "sg:phone":"+31 181 319 627",
    "sg:postcode":"3224 HA",
    "sg:province":"Zuid-Holland",
    "wof:name":"Bloemencentrum Hellevoetsluis Vof",
    "wof:placetype":"venue"
},
  "geometry": {"coordinates":[4.14682,51.832069],"type":"Point"}
}