{
  "type": "Feature",
  "properties": {
    "addr:full":"Herenhof 150 Alphen Aan Den Ryn Zuid-Holland 2402 DP",
    "addr:housenumber":"150",
    "addr:postcode":"2402 dp",
    "addr:street":"Herenhof;Aan Den Ryn",
    "iso:country":"NL",
    "sg:address":"Herenhof 150",
    "sg:city":"Alphen Aan Den Ryn",
    "sg:classifiers":[
        {
            "category":"Farming",
            "subcategory":"Fish & Marine Products",
            "type":"Manufacturing & Wholesale Goods"
        }
    ],
    "sg:phone":"+31 172 241 231",
    "sg:postcode":"2402 DP",
    "sg:province":"Zuid-Holland",
    "sg:tags":[
        "vi"
    ],
    "wof:name":"Visscher",
    "wof:placetype":"venue"
},
  "geometry": {"coordinates":[4.660572,52.151653],"type":"Point"}
}