{
  "type": "Feature",
  "properties": {
    "addr:full":"Oostsngl 51 Delft Zuid-Holland 2612 HD",
    "addr:housenumber":"51",
    "addr:postcode":"2612 hd",
    "addr:street":"Oostsngl",
    "iso:country":"NL",
    "sg:address":"Oostsngl 51",
    "sg:city":"Delft",
    "sg:orig_category":"Artsen - Huisartsen",
    "sg:phone":"+31 15 212 6741",
    "sg:postcode":"2612 HD",
    "sg:province":"Zuid-Holland",
    "wof:name":"Nijkamp, J B M",
    "wof:placetype":"venue"
},
  "geometry": {"coordinates":[4.35869,52.011505],"type":"Point"}
}