{
  "type": "Feature",
  "properties": {
    "addr:full":"Grt Overstr 25 Deventer NL.08 7411 JA",
    "addr:housenumber":"25;nl.08",
    "addr:postcode":"7411 ja",
    "iso:country":"NL",
    "sg:address":"Grt Overstr 25",
    "sg:city":"Deventer",
    "sg:orig_category":"Kappers",
    "sg:phone":"+31 570 613 225",
    "sg:postcode":"7411 JA",
    "sg:province":"NL.08",
    "wof:name":"La Coupe",
    "wof:placetype":"venue"
},
  "geometry": {"coordinates":[6.158285,52.252937],"type":"Point"}
}