{
  "type": "Feature",
  "properties": {
    "addr:full":"Stationsstraat 10 Wierden Overijssel 7641 BW",
    "addr:housenumber":"10",
    "addr:postcode":"7641 bw",
    "addr:street":"Stationsstraat",
    "iso:country":"NL",
    "sg:address":"Stationsstraat 10",
    "sg:city":"Wierden",
    "sg:orig_category":"Kappers",
    "sg:phone":"+31 546 571 678",
    "sg:postcode":"7641 BW",
    "sg:province":"Overijssel",
    "wof:name":"H.B. Meijer",
    "wof:placetype":"venue"
},
  "geometry": {"coordinates":[6.5751228333,52.2890205383],"type":"Point"}
}