{
  "type": "Feature",
  "properties": {
    "addr:full":"Hoofdstr 57 Emmen Provincie Drenthe 7811 ED",
    "addr:housenumber":"57",
    "addr:postcode":"7811 ed",
    "addr:street":"Hoofdstr;Provincie Drenthe",
    "iso:country":"NL",
    "sg:address":"Hoofdstr 57",
    "sg:city":"Emmen",
    "sg:orig_category":"Kinderkleding",
    "sg:phone":"+31 591 643 006",
    "sg:postcode":"7811 ED",
    "sg:province":"Provincie Drenthe",
    "wof:name":"Butterfly",
    "wof:placetype":"venue"
},
  "geometry": {"coordinates":[6.894176,52.786346],"type":"Point"}
}