{
  "type": "Feature",
  "properties": {
    "addr:full":"Wouwsewg 112 Roosendaal Noord-Brabant 4703 BW",
    "addr:housenumber":"112",
    "addr:postcode":"4703 bw",
    "iso:country":"NL",
    "sg:address":"Wouwsewg 112",
    "sg:city":"Roosendaal",
    "sg:orig_category":"Bloemen En Planten",
    "sg:phone":"+31 165 565 875",
    "sg:postcode":"4703 BW",
    "sg:province":"Noord-Brabant",
    "wof:name":"Flower Power",
    "wof:placetype":"venue"
},
  "geometry": {"coordinates":[4.438988,51.531349],"type":"Point"}
}