{
  "type": "Feature",
  "properties": {
    "addr:full":"Vd Sterrwg 6 Den Hoorn Texel North Holland 1797 SV",
    "addr:housenumber":"6",
    "addr:postcode":"1797 sv",
    "iso:country":"NL",
    "sg:address":"Vd Sterrwg 6",
    "sg:city":"Den Hoorn Texel",
    "sg:orig_category":"Loonbedrijven",
    "sg:phone":"+31 222 319 483",
    "sg:postcode":"1797 SV",
    "sg:province":"North Holland",
    "wof:name":"Steege, Ter",
    "wof:placetype":"venue"
},
  "geometry": {"coordinates":[4.785045,53.005547],"type":"Point"}
}