{
  "type": "Feature",
  "properties": {
    "iso:country":"NL",
    "sg:address":"Tomberstraat 11",
    "sg:city":"Papenhoven",
    "sg:orig_category":"Hout Gh",
    "sg:phone":"+31 46 481 0580",
    "sg:postcode":"6124 AK",
    "sg:province":"Limburg",
    "wof:name":"Kitzen Tuinhout",
    "wof:placetype":"venue"
},
  "geometry": {"coordinates":[5.78514,51.040474],"type":"Point"}
}