{
  "type": "Feature",
  "properties": {
    "addr:full":"Kanaaldk Nw 67 Helmond Noord-Brabant 5707 LC",
    "addr:housenumber":"67",
    "addr:postcode":"5707 lc",
    "addr:street":"Nw",
    "iso:country":"NL",
    "sg:address":"Kanaaldk Nw 67",
    "sg:city":"Helmond",
    "sg:orig_category":"Accountants - Administratie- Consulenten En -Kantoren",
    "sg:phone":"+31 492 522 756",
    "sg:postcode":"5707 LC",
    "sg:province":"Noord-Brabant",
    "sg:website":"http://www.putsenbaeten.nl",
    "wof:name":"Puts & Baeten",
    "wof:placetype":"venue"
},
  "geometry": {"coordinates":[5.651095,51.482075],"type":"Point"}
}