{
  "type": "Feature",
  "properties": {
    "addr:full":"Heiliglevenstr 11 Montfoort Utrecht 3417 HL",
    "addr:housenumber":"11",
    "addr:postcode":"3417 hl",
    "addr:street":"Heiliglevenstr",
    "iso:country":"NL",
    "sg:address":"Heiliglevenstr 11",
    "sg:city":"Montfoort",
    "sg:orig_category":"Kappers",
    "sg:phone":"+31 348 473 455",
    "sg:postcode":"3417 HL",
    "sg:province":"Utrecht",
    "wof:name":"Kapperij, De",
    "wof:placetype":"venue"
},
  "geometry": {"coordinates":[4.9469108582,52.0441474915],"type":"Point"}
}