{
  "type": "Feature",
  "properties": {
    "iso:country":"NL",
    "sg:address":"Gildenkwartier 153",
    "sg:city":"Utrecht",
    "sg:orig_category":"Meubelzaken, Woning- And Keukeninrichting",
    "sg:phone":"+31 30 232 8869",
    "sg:postcode":"3511 DE",
    "sg:province":"Utrecht",
    "wof:name":"Jencikova International",
    "wof:placetype":"venue"
},
  "geometry": {"coordinates":[5.111234,52.09177],"type":"Point"}
}