{
  "type": "Feature",
  "properties": {
    "addr:full":"Utrechtsestr 62 Arnhem Gelderland 6811 LZ",
    "addr:housenumber":"62",
    "addr:postcode":"6811 lz",
    "addr:street":"Utrechtsestr",
    "iso:country":"NL",
    "sg:address":"Utrechtsestr 62",
    "sg:city":"Arnhem",
    "sg:orig_category":"Fotoreportages",
    "sg:phone":"+31 26 351 8147",
    "sg:postcode":"6811 LZ",
    "sg:province":"Gelderland",
    "wof:name":"Franken, W B",
    "wof:placetype":"venue"
},
  "geometry": {"coordinates":[5.895237,51.98444],"type":"Point"}
}