{
  "type": "Feature",
  "properties": {
    "addr:full":"Fivelingo 161 Zoetermeer Zuid-Holland 2716 BC",
    "addr:housenumber":"161",
    "addr:postcode":"2716 bc",
    "addr:street":"Fivelingo",
    "iso:country":"NL",
    "sg:address":"Fivelingo 161",
    "sg:city":"Zoetermeer",
    "sg:classifiers":[
        {
            "category":"Personal",
            "subcategory":"Nail Salon",
            "type":"Services"
        }
    ],
    "sg:phone":"+31 79 351 2575",
    "sg:postcode":"2716 BC",
    "sg:province":"Zuid-Holland",
    "sg:tags":[
        "pedicure"
    ],
    "wof:name":"Weening, S M",
    "wof:placetype":"venue"
},
  "geometry": {"coordinates":[4.467378,52.05434],"type":"Point"}
}