{
  "type": "Feature",
  "properties": {
    "addr:full":"Postbus 848 Haarlem Noord-Holland 2003 RV",
    "addr:housenumber":"848",
    "addr:postcode":"2003 rv",
    "addr:street":"Postbus",
    "iso:country":"NL",
    "sg:address":"Postbus 848",
    "sg:city":"Haarlem",
    "sg:orig_category":"Fotoreportages",
    "sg:phone":"+31 23 565 7255",
    "sg:postcode":"2003 RV",
    "sg:province":"Noord-Holland",
    "wof:name":"Digifoto",
    "wof:placetype":"venue"
},
  "geometry": {"coordinates":[4.64225,52.380562],"type":"Point"}
}