{
  "type": "Feature",
  "properties": {
    "addr:full":"Burgemeester Weimalaan 5 Nijeveen Drenthe 7948 AL",
    "addr:housenumber":"5",
    "addr:postcode":"7948 al",
    "addr:street":"Burgemeester Weimalaan",
    "iso:country":"NL",
    "sg:address":"Burgemeester Weimalaan 5",
    "sg:city":"Nijeveen",
    "sg:orig_category":"Metaalbekleding And -Behandeling",
    "sg:phone":"+31 522 491 913",
    "sg:postcode":"7948 AL",
    "sg:province":"Drenthe",
    "wof:name":"K. Veenstra Slijpgereedschap",
    "wof:placetype":"venue"
},
  "geometry": {"coordinates":[6.168805,52.731876],"type":"Point"}
}