{
  "type": "Feature",
  "properties": {
    "addr:full":"Hazelaarstr 30 Ter Aar South Holland 2461 DP",
    "addr:housenumber":"30",
    "addr:postcode":"2461 dp",
    "addr:street":"Hazelaarstr",
    "iso:country":"NL",
    "sg:address":"Hazelaarstr 30",
    "sg:city":"Ter Aar",
    "sg:orig_category":"Modelbouw",
    "sg:phone":"+31 172 605 949",
    "sg:postcode":"2461 DP",
    "sg:province":"South Holland",
    "wof:name":"Verzaal",
    "wof:placetype":"venue"
},
  "geometry": {"coordinates":[4.708464,52.170212],"type":"Point"}
}