{
  "type": "Feature",
  "properties": {
    "addr:full":"Luchtenburgseweg 2 Ulvenhout Noord-Brabant 4858 RJ",
    "addr:housenumber":"2",
    "addr:postcode":"4858 rj",
    "addr:street":"Luchtenburgseweg",
    "iso:country":"NL",
    "sg:address":"Luchtenburgseweg 2",
    "sg:city":"Ulvenhout",
    "sg:orig_category":"Grafisch Ontwerpers",
    "sg:phone":"+31 76 564 2502",
    "sg:postcode":"4858 RJ",
    "sg:province":"Noord-Brabant",
    "wof:name":"Zwart, Kees",
    "wof:placetype":"venue"
},
  "geometry": {"coordinates":[4.822217,51.536259],"type":"Point"}
}