{
  "type": "Feature",
  "properties": {
    "addr:full":"Raadhuisstraat 2 Doetinchem Gelderland 7001 EW",
    "addr:housenumber":"2",
    "addr:postcode":"7001 ew",
    "addr:street":"Raadhuisstraat;Gelderland",
    "iso:country":"NL",
    "sg:address":"Raadhuisstraat 2",
    "sg:city":"Doetinchem",
    "sg:orig_category":"Overheidsdiensten",
    "sg:phone":"+31 314 377 377",
    "sg:postcode":"7001 EW",
    "sg:province":"Gelderland",
    "wof:name":"Gemeente Doetinchem",
    "wof:placetype":"venue"
},
  "geometry": {"coordinates":[6.2920107841,51.9638442993],"type":"Point"}
}