{
  "type": "Feature",
  "properties": {
    "addr:full":"Brouwhorst 15 Helmond Noord-Brabant 5704 EG",
    "addr:housenumber":"15",
    "addr:postcode":"5704 eg",
    "addr:street":"Brouwhorst",
    "iso:country":"NL",
    "sg:address":"Brouwhorst 15",
    "sg:city":"Helmond",
    "sg:orig_category":"Fietsen En Bromfietsen",
    "sg:phone":"+31 492 512 137",
    "sg:postcode":"5704 EG",
    "sg:province":"Noord-Brabant",
    "wof:name":"Halin",
    "wof:placetype":"venue"
},
  "geometry": {"coordinates":[5.703106,51.469601],"type":"Point"}
}