{
  "type": "Feature",
  "properties": {
    "addr:full":"Postbus 1166 Zaandam Noord-Holland 1500 AD",
    "addr:housenumber":"1166",
    "addr:postcode":"1500 ad",
    "addr:street":"Postbus",
    "iso:country":"NL",
    "sg:address":"Postbus 1166",
    "sg:city":"Zaandam",
    "sg:orig_category":"Geluidsinstallaties",
    "sg:phone":"+31 6 30024310",
    "sg:postcode":"1500 AD",
    "sg:province":"Noord-Holland",
    "wof:name":"Mantel, W",
    "wof:placetype":"venue"
},
  "geometry": {"coordinates":[4.81295,52.44162],"type":"Point"}
}