{
  "type": "Feature",
  "properties": {
    "addr:full":"Baverdestr 73 Lieshout Noord-Brabant 5737 AB",
    "addr:housenumber":"73",
    "addr:postcode":"5737 ab",
    "addr:street":"Baverdestr",
    "iso:country":"NL",
    "sg:address":"Baverdestr 73",
    "sg:city":"Lieshout",
    "sg:orig_category":"Woningstoffeerders",
    "sg:phone":"+31 6 51076113",
    "sg:postcode":"5737 AB",
    "sg:province":"Noord-Brabant",
    "wof:name":"Leest, M De",
    "wof:placetype":"venue"
},
  "geometry": {"coordinates":[5.5992841721,51.5220451355],"type":"Point"}
}