{
  "type": "Feature",
  "properties": {
    "addr:full":"Loowg 78 Bathmen Overijssel 7437 RT",
    "addr:housenumber":"78",
    "addr:postcode":"7437 rt",
    "addr:street":"Loowg",
    "iso:country":"NL",
    "sg:address":"Loowg 78",
    "sg:city":"Bathmen",
    "sg:orig_category":"Adviesbureaus",
    "sg:phone":"+31 570 542 946",
    "sg:postcode":"7437 RT",
    "sg:province":"Overijssel",
    "wof:name":"Agro Serv Bv",
    "wof:placetype":"venue"
},
  "geometry": {"coordinates":[6.327942,52.255226],"type":"Point"}
}