{
  "type": "Feature",
  "properties": {
    "addr:full":"Dreischorstraat 50 Tilburg Noord-Brabant 5043 JB",
    "addr:housenumber":"50",
    "addr:postcode":"5043 jb",
    "addr:street":"Dreischorstraat",
    "iso:country":"NL",
    "sg:address":"Dreischorstraat 50",
    "sg:city":"Tilburg",
    "sg:orig_category":"Kappers",
    "sg:phone":"+31 13 570 0023",
    "sg:postcode":"5043 JB",
    "sg:province":"Noord-Brabant",
    "wof:name":"Lydia",
    "wof:placetype":"venue"
},
  "geometry": {"coordinates":[5.016555,51.577785],"type":"Point"}
}