{
  "type": "Feature",
  "properties": {
    "addr:full":"Kanaaldk 14 Koedyk Noord-Holland 1832 AA",
    "addr:housenumber":"14",
    "addr:postcode":"1832 aa",
    "addr:street":"Kanaaldk",
    "iso:country":"NL",
    "sg:address":"Kanaaldk 14",
    "sg:city":"Koedyk",
    "sg:orig_category":"Pottenbakkerijen",
    "sg:phone":"+31 72 561 5830",
    "sg:postcode":"1832 AA",
    "sg:province":"Noord-Holland",
    "wof:name":"Mal, De",
    "wof:placetype":"venue"
},
  "geometry": {"coordinates":[4.736331,52.686459],"type":"Point"}
}