{
  "type": "Feature",
  "properties": {
    "addr:full":"Sassenheimstr 82-Iii Amsterdam Noord-Holland 1059 BM",
    "addr:housenumber":"82-iii",
    "addr:postcode":"1059 bm",
    "addr:street":"Sassenheimstr",
    "iso:country":"NL",
    "sg:address":"Sassenheimstr 82-Iii",
    "sg:city":"Amsterdam",
    "sg:orig_category":"Koeriersdiensten",
    "sg:phone":"+31 20 778 2463",
    "sg:postcode":"1059 BM",
    "sg:province":"Noord-Holland",
    "wof:name":"Ab Connected",
    "wof:placetype":"venue"
},
  "geometry": {"coordinates":[4.84673,52.344818],"type":"Point"}
}