{
  "type": "Feature",
  "properties": {
    "addr:full":"Portsmuiden 17 Amsterdam North Holland 1046 AH",
    "addr:housenumber":"17",
    "addr:postcode":"1046 ah",
    "addr:street":"Portsmuiden",
    "iso:country":"NL",
    "sg:address":"Portsmuiden 17",
    "sg:city":"Amsterdam",
    "sg:orig_category":"Orthopedische Artikelen - Fabrieken En Groothandel",
    "sg:phone":"+31 20 611 8455",
    "sg:postcode":"1046 AH",
    "sg:province":"North Holland",
    "wof:name":"Schulte Bv, J Th",
    "wof:placetype":"venue"
},
  "geometry": {"coordinates":[4.7855081558,52.3896942139],"type":"Point"}
}