{
  "type": "Feature",
  "properties": {
    "iso:country":"NL",
    "sg:address":"P Potterstr 22",
    "sg:city":"Kerkrade",
    "sg:orig_category":"Bedrijfsopleidingen",
    "sg:phone":"+31 45 567 1790",
    "sg:postcode":"6464 CB",
    "sg:province":"Limburg",
    "wof:name":"Int Management Consulting",
    "wof:placetype":"venue"
},
  "geometry": {"coordinates":[6.07523,50.879528],"type":"Point"}
}