{
  "type": "Feature",
  "properties": {
    "addr:full":"Dennekruid 70 Rotterdam Zuid-Holland 3068 SJ",
    "addr:housenumber":"70",
    "addr:postcode":"3068",
    "addr:street":"Dennekruid",
    "iso:country":"NL",
    "sg:address":"Dennekruid 70",
    "sg:city":"Rotterdam",
    "sg:orig_category":"Vertalers",
    "sg:phone":"+31 10 421 8697",
    "sg:postcode":"3068 SJ",
    "sg:province":"Zuid-Holland",
    "wof:name":"Baver",
    "wof:placetype":"venue"
},
  "geometry": {"coordinates":[4.555034,51.959881],"type":"Point"}
}