{
  "type": "Feature",
  "properties": {
    "addr:full":"Winterdk 14 Sprang Capelle Noord-Brabant 5161 PH",
    "addr:housenumber":"14",
    "addr:postcode":"5161",
    "addr:street":"Winterdk",
    "iso:country":"NL",
    "sg:address":"Winterdk 14",
    "sg:city":"Sprang Capelle",
    "sg:orig_category":"Binnenhuisarchitectuur",
    "sg:phone":"+31 416 561 480",
    "sg:postcode":"5161 PH",
    "sg:province":"Noord-Brabant",
    "wof:name":"Vries, Gerda De",
    "wof:placetype":"venue"
},
  "geometry": {"coordinates":[5.017783,51.689877],"type":"Point"}
}