{
  "type": "Feature",
  "properties": {
    "addr:full":"Vaart Z. Z. 37 Appelscha Friesland 8426 AD",
    "addr:housenumber":"37",
    "addr:postcode":"8426 ad",
    "addr:street":"Vaart Z. Z.",
    "iso:country":"NL",
    "sg:address":"Vaart Z. Z. 37",
    "sg:city":"Appelscha",
    "sg:orig_category":"Verzekeringen",
    "sg:phone":"+31 516 432 999",
    "sg:postcode":"8426 AD",
    "sg:province":"Friesland",
    "wof:name":"Koelma Assurantien En Makelaardij",
    "wof:placetype":"venue"
},
  "geometry": {"coordinates":[6.351159,52.956146],"type":"Point"}
}