{
  "type": "Feature",
  "properties": {
    "addr:full":"Koningspln 8 Tilburg Noord-Brabant 5038 WG",
    "addr:housenumber":"8",
    "addr:postcode":"5038 wg",
    "addr:street":"Koningspln",
    "iso:country":"NL",
    "sg:address":"Koningspln 8",
    "sg:city":"Tilburg",
    "sg:orig_category":"Adviesbureaus Bedrijfsorganisatie",
    "sg:phone":"+31 13 542 9303",
    "sg:postcode":"5038 WG",
    "sg:province":"Noord-Brabant",
    "wof:name":"Bkw",
    "wof:placetype":"venue"
},
  "geometry": {"coordinates":[5.086664,51.553879],"type":"Point"}
}