{
  "type": "Feature",
  "properties": {
    "iso:country":"NL",
    "sg:address":"Corlaerstr 5",
    "sg:city":"Nykerk Gld",
    "sg:orig_category":"Geluidsinstallaties",
    "sg:phone":"+31 33 246 1823",
    "sg:postcode":"3863 ZC",
    "sg:province":"Gelderland",
    "wof:name":"4 Holland, Studio",
    "wof:placetype":"venue"
},
  "geometry": {"coordinates":[5.470317,52.214035],"type":"Point"}
}