{
  "type": "Feature",
  "properties": {
    "iso:country":"NL",
    "sg:address":"Van Salmstraat 5",
    "sg:city":"Boxtel",
    "sg:orig_category":"Hout Gh",
    "sg:phone":"+31 411 672 488",
    "sg:postcode":"5281 RP",
    "sg:province":"North Brabant",
    "wof:name":"Houthandel Langenhuijsen Bv",
    "wof:placetype":"venue"
},
  "geometry": {"coordinates":[5.314845,51.586327],"type":"Point"}
}