{
  "type": "Feature",
  "properties": {
    "addr:full":"Electronicawg 23 Stadskanaal Groningen 9503 GA",
    "addr:housenumber":"23",
    "addr:postcode":"9503 ga",
    "addr:street":"Electronicawg",
    "iso:country":"NL",
    "sg:address":"Electronicawg 23",
    "sg:city":"Stadskanaal",
    "sg:classifiers":[
        {
            "category":"Professional",
            "subcategory":"Accounting & Tax Preparation",
            "type":"Services"
        }
    ],
    "sg:phone":"+31 599 653 811",
    "sg:postcode":"9503 GA",
    "sg:province":"Groningen",
    "sg:tags":[
        "accountant",
        "en",
        "-kantoren",
        "register-"
    ],
    "sg:website":"http://www.admifa.nl",
    "wof:name":"Admifa Accountants En Adviseurs",
    "wof:placetype":"venue"
},
  "geometry": {"coordinates":[6.969287,52.974228],"type":"Point"}
}