{
  "type": "Feature",
  "properties": {
    "addr:full":"Spuiwg 63 Lelystad Flevoland 8243 PW",
    "addr:housenumber":"63",
    "addr:postcode":"8243 pw",
    "addr:street":"Spuiwg;Flevoland",
    "iso:country":"NL",
    "sg:address":"Spuiwg 63",
    "sg:city":"Lelystad",
    "sg:orig_category":"Fotoapparatuur En -Artikelen - Groothandel",
    "sg:phone":"+31 320 261 030",
    "sg:postcode":"8243 PW",
    "sg:province":"Flevoland",
    "wof:name":"Flits Bv",
    "wof:placetype":"venue"
},
  "geometry": {"coordinates":[5.433769,52.502487],"type":"Point"}
}