{
  "type": "Feature",
  "properties": {
    "addr:full":"Postbus 69400 Amsterdam Noord-Holland 1060 CL",
    "addr:postcode":"69400;1060",
    "addr:street":"Postbus",
    "iso:country":"NL",
    "sg:address":"Postbus 69400",
    "sg:city":"Amsterdam",
    "sg:orig_category":"Herenkleding - Groothandel",
    "sg:phone":"+31 20 617 9159",
    "sg:postcode":"1060 CL",
    "sg:province":"Noord-Holland",
    "wof:name":"Doramafi",
    "wof:placetype":"venue"
},
  "geometry": {"coordinates":[4.77754,52.34988],"type":"Point"}
}