{
  "type": "Feature",
  "properties": {
    "addr:full":"Wildforster 4 Barneveld Gelderland 3772 WB",
    "addr:housenumber":"4",
    "addr:postcode":"3772 wb",
    "addr:street":"Wildforster;Gelderland",
    "iso:country":"NL",
    "sg:address":"Wildforster 4",
    "sg:city":"Barneveld",
    "sg:orig_category":"Loodgieterswerk, Verwarming And Sanitaire Installaties",
    "sg:phone":"+31 342 420 884",
    "sg:postcode":"3772 WB",
    "sg:province":"Gelderland",
    "wof:name":"H. Top",
    "wof:placetype":"venue"
},
  "geometry": {"coordinates":[5.594801,52.13155],"type":"Point"}
}