{
  "type": "Feature",
  "properties": {
    "addr:full":"Ternatestr 2 Utrecht Utrecht 3531 RZ",
    "addr:housenumber":"2",
    "addr:postcode":"3531 rz",
    "addr:street":"Ternatestr",
    "iso:country":"NL",
    "sg:address":"Ternatestr 2",
    "sg:city":"Utrecht",
    "sg:orig_category":"Verenigingen En Stichtingen",
    "sg:phone":"+31 30 290 0850",
    "sg:postcode":"3531 RZ",
    "sg:province":"Utrecht",
    "wof:name":"Taalhulp, Sticht",
    "wof:placetype":"venue"
},
  "geometry": {"coordinates":[5.099865,52.092091],"type":"Point"}
}