{
  "type": "Feature",
  "properties": {
    "addr:full":"Drossard De La Courtstr 2 Gemert Noord-Brabant 5421 JH",
    "addr:housenumber":"2",
    "addr:postcode":"5421 jh",
    "addr:street":"Drossard De La Courtstr",
    "iso:country":"NL",
    "sg:address":"Drossard De La Courtstr 2",
    "sg:city":"Gemert",
    "sg:orig_category":"Kinderopvang Behalve Thuis",
    "sg:phone":"+31 492 367 511",
    "sg:postcode":"5421 JH",
    "sg:province":"Noord-Brabant",
    "wof:name":"Stichting Kinderopvang",
    "wof:placetype":"venue"
},
  "geometry": {"coordinates":[5.69392,51.553066],"type":"Point"}
}