{
  "type": "Feature",
  "properties": {
    "addr:full":"T Zuden 67 Leek Groningen 9351 LC",
    "addr:housenumber":"67",
    "addr:postcode":"9351 lc",
    "addr:street":"T Zuden",
    "iso:country":"NL",
    "sg:address":"T Zuden 67",
    "sg:city":"Leek",
    "sg:orig_category":"Nagelstudio'S",
    "sg:phone":"+31 594 519 997",
    "sg:postcode":"9351 LC",
    "sg:province":"Groningen",
    "wof:name":"Marjo",
    "wof:placetype":"venue"
},
  "geometry": {"coordinates":[6.371552,53.165478],"type":"Point"}
}