{
  "type": "Feature",
  "properties": {
    "iso:country":"NL",
    "sg:address":"T Zuden 67",
    "sg:city":"Leek",
    "sg:orig_category":"Nagelstudio'S",
    "sg:phone":"+31 594 519 997",
    "sg:postcode":"9351 LC",
    "sg:province":"Groningen",
    "wof:name":"Marjo",
    "wof:placetype":"venue"
},
  "geometry": {"coordinates":[6.371552,53.165478],"type":"Point"}
}