{
  "type": "Feature",
  "properties": {
    "iso:country":"NL",
    "sg:address":"Waalsewg 62A",
    "sg:city":"Tull En T Waal",
    "sg:orig_category":"Kabelwerken",
    "sg:phone":"+31 30 606 3362",
    "sg:postcode":"3999 NT",
    "sg:province":"Utrecht",
    "wof:name":"Verbree Bv",
    "wof:placetype":"venue"
},
  "geometry": {"coordinates":[5.1331949234,52.002166748],"type":"Point"}
}