{
  "type": "Feature",
  "properties": {
    "iso:country":"NL",
    "sg:address":"Parkietstr 20",
    "sg:city":"Badhoevedorp",
    "sg:orig_category":"Horloges En Klokken Fournituren - Fabr. En Grooth",
    "sg:phone":"+31 20 659 5990",
    "sg:postcode":"1171 HV",
    "sg:province":"Noord-Holland",
    "wof:name":"Bogaerts Bv",
    "wof:placetype":"venue"
},
  "geometry": {"coordinates":[4.788059,52.336727],"type":"Point"}
}