{
  "type": "Feature",
  "properties": {
    "addr:full":"Amstel 177 Amsterdam Noord-Holland 1018 ES",
    "addr:housenumber":"177",
    "addr:postcode":"1018 es",
    "addr:street":"Amstel",
    "iso:country":"NL",
    "sg:address":"Amstel 177",
    "sg:city":"Amsterdam",
    "sg:orig_category":"Loopbaanbegeleiding",
    "sg:phone":"+31 20 344 6480",
    "sg:postcode":"1018 ES",
    "sg:province":"Noord-Holland",
    "sg:website":"http://www.fullmotion.nl",
    "wof:name":"Fullmotion Bv",
    "wof:placetype":"venue"
},
  "geometry": {"coordinates":[4.904772,52.360744],"type":"Point"}
}