{
  "type": "Feature",
  "properties": {
    "addr:full":"Grote Kerkstraat 14 Venlo Limburg 5911 CH",
    "addr:housenumber":"14",
    "addr:postcode":"5911",
    "addr:street":"Grote Kerkstraat",
    "iso:country":"NL",
    "sg:address":"Grote Kerkstraat 14",
    "sg:city":"Venlo",
    "sg:orig_category":"Boeken En Tijdschriften",
    "sg:phone":"+31 77 354 4069",
    "sg:postcode":"5911 CH",
    "sg:province":"Limburg",
    "wof:name":"Laerpoort, De",
    "wof:placetype":"venue"
},
  "geometry": {"coordinates":[6.170959,51.370281],"type":"Point"}
}