{
  "type": "Feature",
  "properties": {
    "iso:country":"NL",
    "sg:address":"Gazellelaan 20",
    "sg:city":"Helmond",
    "sg:orig_category":"Modellenbureaus",
    "sg:phone":"+31 492 511 492",
    "sg:postcode":"5704 DL",
    "sg:province":"Noord-Brabant",
    "wof:name":"Modellen & Opleidingsinstituut Inside Out",
    "wof:placetype":"venue"
},
  "geometry": {"coordinates":[5.696391,51.458191],"type":"Point"}
}