{
  "type": "Feature",
  "properties": {
    "addr:full":"St Catharinastr 27 Ulestraten Limburg 6235 BC",
    "addr:housenumber":"27",
    "addr:postcode":"6235 bc",
    "iso:country":"NL",
    "sg:address":"St Catharinastr 27",
    "sg:city":"Ulestraten",
    "sg:orig_category":"Kappers",
    "sg:phone":"+31 43 364 3107",
    "sg:postcode":"6235 BC",
    "sg:province":"Limburg",
    "wof:name":"Jacobs, Haarmode",
    "wof:placetype":"venue"
},
  "geometry": {"coordinates":[5.7833228111,50.9057121277],"type":"Point"}
}