{
  "type": "Feature",
  "properties": {
    "addr:full":"Wageningselaan 46C Veenendaal Utrecht 3903 LA",
    "addr:housenumber":"46c",
    "addr:postcode":"3903 la",
    "addr:street":"Wageningselaan",
    "iso:country":"NL",
    "sg:address":"Wageningselaan 46C",
    "sg:city":"Veenendaal",
    "sg:orig_category":"Wintersportkleding En -Artikelen",
    "sg:phone":"+31 318 505 255",
    "sg:postcode":"3903 LA",
    "sg:province":"Utrecht",
    "sg:website":"http://www.miezelmoe.nl",
    "wof:name":"Miezelmoe",
    "wof:placetype":"venue"
},
  "geometry": {"coordinates":[5.5751371384,52.0093765259],"type":"Point"}
}