{
  "type": "Feature",
  "properties": {
    "addr:full":"Postbus 35 Nuenen Noord-Brabant 5670 AA",
    "addr:housenumber":"35",
    "addr:postcode":"5670 aa",
    "addr:street":"Postbus",
    "iso:country":"NL",
    "sg:address":"Postbus 35",
    "sg:city":"Nuenen",
    "sg:orig_category":"Bodemonderzoek",
    "sg:phone":"+31 40 234 8800",
    "sg:postcode":"5670 AA",
    "sg:province":"Noord-Brabant",
    "wof:name":"Nederlands Instituut Voor Toegepaste Geowetenschap Tno",
    "wof:placetype":"venue"
},
  "geometry": {"coordinates":[5.54893,51.473518],"type":"Point"}
}