{
  "type": "Feature",
  "properties": {
    "iso:country":"NL",
    "sg:address":"Dordtseln 26",
    "sg:city":"Rotterdam",
    "sg:orig_category":"Koffie- En Theehuizen",
    "sg:phone":"+31 10 485 2250",
    "sg:postcode":"3073 GB",
    "sg:province":"South Holland",
    "wof:name":"Mbaskent",
    "wof:placetype":"venue"
},
  "geometry": {"coordinates":[4.505596,51.891674],"type":"Point"}
}