{
  "type": "Feature",
  "properties": {
    "addr:full":"Pieter De Hooghstraat 35 Heemstede North Holland 2102 BX",
    "addr:housenumber":"35",
    "addr:postcode":"2102 bx",
    "addr:street":"Pieter De Hooghstraat",
    "iso:country":"NL",
    "sg:address":"Pieter De Hooghstraat 35",
    "sg:city":"Heemstede",
    "sg:orig_category":"Autokeuringen",
    "sg:phone":"+31 23 528 4530",
    "sg:postcode":"2102 BX",
    "sg:province":"North Holland",
    "wof:name":"Wito Bv",
    "wof:placetype":"venue"
},
  "geometry": {"coordinates":[4.629889,52.359917],"type":"Point"}
}