{
  "type": "Feature",
  "properties": {
    "addr:full":"Wijde Geldelozepad 22 Haarlem Noord-Holland 2012 EK",
    "addr:housenumber":"22",
    "addr:postcode":"2012 ek",
    "addr:street":"Wijde Geldelozepad",
    "iso:country":"NL",
    "sg:address":"Wijde Geldelozepad 22",
    "sg:city":"Haarlem",
    "sg:orig_category":"Loodgieterswerk, Verwarming And Sanitaire Installaties",
    "sg:phone":"+31 23 532 3346",
    "sg:postcode":"2012 EK",
    "sg:province":"Noord-Holland",
    "wof:name":"T.V. De Leeuw",
    "wof:placetype":"venue"
},
  "geometry": {"coordinates":[4.629277,52.37495],"type":"Point"}
}