{
  "type": "Feature",
  "properties": {
    "iso:country":"NL",
    "sg:address":"Oude Garderenseweg 30",
    "sg:city":"Putten",
    "sg:orig_category":"Bedrijfsinventaris Gh",
    "sg:phone":"+31 341 352 410",
    "sg:postcode":"3881 PR",
    "sg:province":"Gelderland",
    "wof:name":"Van Beek Jukeboxen",
    "wof:placetype":"venue"
},
  "geometry": {"coordinates":[5.652137,52.236938],"type":"Point"}
}