{
  "type": "Feature",
  "properties": {
    "addr:full":"Nyenheim 33-26 Zeist Utrecht 3704 SE",
    "addr:housenumber":"33-26",
    "addr:postcode":"3704 se",
    "iso:country":"NL",
    "sg:address":"Nyenheim 33-26",
    "sg:city":"Zeist",
    "sg:orig_category":"Veiligheidsuitrusting En -Kleding",
    "sg:phone":"+31 30 696 3433",
    "sg:postcode":"3704 SE",
    "sg:province":"Utrecht",
    "sg:website":"http://www.eartech.nl",
    "wof:name":"Eartech Gehoorbescherming",
    "wof:placetype":"venue"
},
  "geometry": {"coordinates":[5.24387,52.08548],"type":"Point"}
}