{
  "type": "Feature",
  "properties": {
    "addr:full":"James Wattstraat 2 Oud Beijerland Zuid-Holland 3261 MB",
    "addr:housenumber":"2",
    "addr:postcode":"3261 mb",
    "addr:street":"James Wattstraat;Oud Beijerland",
    "iso:country":"NL",
    "sg:address":"James Wattstraat 2",
    "sg:city":"Oud Beijerland",
    "sg:orig_category":"Goederenvervoer Over De Weg",
    "sg:phone":"+31 186 613 466",
    "sg:postcode":"3261 MB",
    "sg:province":"Zuid-Holland",
    "wof:name":"Van Der Mark Internationaal Transportbedrijf Bv",
    "wof:placetype":"venue"
},
  "geometry": {"coordinates":[4.432094,51.829571],"type":"Point"}
}