{
  "type": "Feature",
  "properties": {
    "addr:full":"Maisberg 138 Roosendaal Noord-Brabant 4708 NR",
    "addr:housenumber":"138",
    "addr:postcode":"4708 nr",
    "addr:street":"Maisberg",
    "iso:country":"NL",
    "sg:address":"Maisberg 138",
    "sg:city":"Roosendaal",
    "sg:orig_category":"Voetbalverenigingen",
    "sg:phone":"+31 6 51822353",
    "sg:postcode":"4708 NR",
    "sg:province":"Noord-Brabant",
    "wof:name":"Rzvv",
    "wof:placetype":"venue"
},
  "geometry": {"coordinates":[4.435084,51.520187],"type":"Point"}
}