{
  "type": "Feature",
  "properties": {
    "addr:full":"Lorentzwg 34 Lekkerkerk Zuid-Holland 2941 VE",
    "addr:housenumber":"34",
    "addr:postcode":"2941",
    "addr:street":"Lorentzwg;Ve",
    "iso:country":"NL",
    "sg:address":"Lorentzwg 34",
    "sg:city":"Lekkerkerk",
    "sg:orig_category":"Houtgroothandel",
    "sg:phone":"+31 180 510 414",
    "sg:postcode":"2941 VE",
    "sg:province":"Zuid-Holland",
    "wof:name":"Terdu En Zn Bv",
    "wof:placetype":"venue"
},
  "geometry": {"coordinates":[4.681861,51.89867],"type":"Point"}
}