{
  "type": "Feature",
  "properties": {
    "addr:full":"Waterstraat 43 Tiel Gelderland 4001 AM",
    "addr:housenumber":"43",
    "addr:postcode":"4001",
    "addr:street":"Waterstraat;Gelderland",
    "iso:country":"NL",
    "sg:address":"Waterstraat 43",
    "sg:city":"Tiel",
    "sg:orig_category":"Bloemen And Planten",
    "sg:phone":"+31 344 626 655",
    "sg:postcode":"4001 AM",
    "sg:province":"Gelderland",
    "wof:name":"Florado-Centrum",
    "wof:placetype":"venue"
},
  "geometry": {"coordinates":[5.430696,51.888096],"type":"Point"}
}