{
  "type": "Feature",
  "properties": {
    "addr:full":"Nieuwstraat 85 Deventer NL.08 7411 LK",
    "addr:housenumber":"85;nl.08",
    "addr:postcode":"7411 lk",
    "addr:street":"Nieuwstraat",
    "iso:country":"NL",
    "sg:address":"Nieuwstraat 85",
    "sg:city":"Deventer",
    "sg:orig_category":"Meubelzaken, Woning- And Keukeninrichting",
    "sg:phone":"+31 570 623 720",
    "sg:postcode":"7411 LK",
    "sg:province":"NL.08",
    "wof:name":"Sleeptrent Waterbedden Slaapgigant",
    "wof:placetype":"venue"
},
  "geometry": {"coordinates":[6.159899,52.251034],"type":"Point"}
}