{
  "type": "Feature",
  "properties": {
    "addr:full":"Crocusstraat 25 Hattem Gelderland 8051 DN",
    "addr:housenumber":"25",
    "addr:postcode":"8051 dn",
    "addr:street":"Crocusstraat;Gelderland",
    "iso:country":"NL",
    "sg:address":"Crocusstraat 25",
    "sg:city":"Hattem",
    "sg:orig_category":"Goederenvervoer Over De Weg",
    "sg:phone":"+31 38 444 2634",
    "sg:postcode":"8051 DN",
    "sg:province":"Gelderland",
    "wof:name":"Het Stuurwiel",
    "wof:placetype":"venue"
},
  "geometry": {"coordinates":[6.073176,52.469433],"type":"Point"}
}