{
  "type": "Feature",
  "properties": {
    "addr:full":"Bardolinogaard 12 Spijkenisse Zuid-Holland 3206 PB",
    "addr:housenumber":"12",
    "addr:postcode":"3206 pb",
    "addr:street":"Bardolinogaard",
    "iso:country":"NL",
    "sg:address":"Bardolinogaard 12",
    "sg:city":"Spijkenisse",
    "sg:orig_category":"Technische Studies And Onderzoek",
    "sg:phone":"+31 181 631 063",
    "sg:postcode":"3206 PB",
    "sg:province":"Zuid-Holland",
    "wof:name":"Vof Keijnemans En Van Laviere",
    "wof:placetype":"venue"
},
  "geometry": {"coordinates":[4.32897,51.828171],"type":"Point"}
}