{
  "type": "Feature",
  "properties": {
    "addr:full":"Konynenberg 31A Breda Noord-Brabant 4825 BC",
    "addr:housenumber":"31a",
    "addr:postcode":"4825 bc",
    "addr:street":"Konynenberg",
    "iso:country":"NL",
    "sg:address":"Konynenberg 31A",
    "sg:city":"Breda",
    "sg:classifiers":[
        {
            "category":"Retail",
            "subcategory":"Auto Repair",
            "type":"Services"
        }
    ],
    "sg:phone":"+31 76 578 7911",
    "sg:postcode":"4825 BC",
    "sg:province":"Noord-Brabant",
    "sg:tags":[
        "garage"
    ],
    "wof:name":"Tilba Bv",
    "wof:placetype":"venue"
},
  "geometry": {"coordinates":[4.768158,51.611782],"type":"Point"}
}