{
  "type": "Feature",
  "properties": {
    "addr:full":"Henri Dunantplein 22 Hillegom North Holland 2181 EM",
    "addr:housenumber":"22",
    "addr:postcode":"2181 em",
    "addr:street":"Henri Dunantplein",
    "iso:country":"NL",
    "sg:address":"Henri Dunantplein 22",
    "sg:city":"Hillegom",
    "sg:orig_category":"Kappers",
    "sg:phone":"+31 252 518 232",
    "sg:postcode":"2181 EM",
    "sg:province":"North Holland",
    "wof:name":"Haarstudio Extra Vaganza",
    "wof:placetype":"venue"
},
  "geometry": {"coordinates":[4.5779857635,52.292591095],"type":"Point"}
}