{
  "type": "Feature",
  "properties": {
    "addr:full":"Berkenweg 15 Zuidlaren Provincie Drenthe 9471 VA",
    "addr:housenumber":"15",
    "addr:postcode":"9471",
    "addr:street":"Berkenweg;Provincie Drenthe",
    "iso:country":"NL",
    "sg:address":"Berkenweg 15",
    "sg:city":"Zuidlaren",
    "sg:classifiers":[
        {
            "category":"Education",
            "subcategory":"Preschool",
            "type":"Public Place"
        }
    ],
    "sg:phone":"+31 50 409 4059",
    "sg:postcode":"9471 VA",
    "sg:province":"Provincie Drenthe",
    "sg:tags":[
        "kleuteronderwijs",
        "basis-"
    ],
    "wof:name":"Openbare Basisschool De Waterburcht",
    "wof:placetype":"venue"
},
  "geometry": {"coordinates":[6.661587,53.083954],"type":"Point"}
}