{
  "type": "Feature",
  "properties": {
    "addr:full":"Noorderdiep 99 Nieuw Buinen Drenthe 9521 BC",
    "addr:housenumber":"99",
    "addr:postcode":"buinen;9521 bc",
    "addr:street":"Noorderdiep",
    "iso:country":"NL",
    "sg:address":"Noorderdiep 99",
    "sg:city":"Nieuw Buinen",
    "sg:orig_category":"Kinderopvang",
    "sg:phone":"+31 599 616 649",
    "sg:postcode":"9521 BC",
    "sg:province":"Drenthe",
    "wof:name":"Jippie",
    "wof:placetype":"venue"
},
  "geometry": {"coordinates":[6.941352,52.961189],"type":"Point"}
}