{
  "type": "Feature",
  "properties": {
    "iso:country":"NL",
    "sg:address":"Treilerdwwg 3",
    "sg:city":"S Gravenhage",
    "sg:orig_category":"Banken",
    "sg:phone":"+31 70 371 8888",
    "sg:postcode":"2583 DA",
    "sg:province":"Zuid-Holland",
    "sg:website":"http://www.rabobank.nl",
    "wof:name":"Rabobank",
    "wof:placetype":"venue"
},
  "geometry": {"coordinates":[4.25526,52.09124],"type":"Point"}
}