{
  "type": "Feature",
  "properties": {
    "addr:full":"R Spierln 7 Heemstede Noord-Holland 2104 TW",
    "addr:housenumber":"7",
    "addr:postcode":"2104 tw",
    "iso:country":"NL",
    "sg:address":"R Spierln 7",
    "sg:city":"Heemstede",
    "sg:orig_category":"Autorijscholen",
    "sg:phone":"+31 23 529 2707",
    "sg:postcode":"2104 TW",
    "sg:province":"Noord-Holland",
    "wof:name":"Capel, Bert",
    "wof:placetype":"venue"
},
  "geometry": {"coordinates":[4.611075,52.330429],"type":"Point"}
}