{
  "type": "Feature",
  "properties": {
    "iso:country":"NL",
    "sg:address":"Winkelcentrum Galacop 14",
    "sg:city":"Nieuwegein",
    "sg:orig_category":"Bloemen And Planten",
    "sg:phone":"+31 30 604 3572",
    "sg:postcode":"3437 JV",
    "sg:province":"Utrecht",
    "wof:name":"T Kevertje",
    "wof:placetype":"venue"
},
  "geometry": {"coordinates":[5.082165,52.053513],"type":"Point"}
}