{
  "type": "Feature",
  "properties": {
    "addr:full":"Dr Posthumusln 20 Eenrum Groningen 9967 PN",
    "addr:housenumber":"20",
    "addr:postcode":"9967 pn",
    "addr:street":"Eenrum",
    "iso:country":"NL",
    "sg:address":"Dr Posthumusln 20",
    "sg:city":"Eenrum",
    "sg:orig_category":"Voetbalverenigingen",
    "sg:phone":"+31 595 491 945",
    "sg:postcode":"9967 PN",
    "sg:province":"Groningen",
    "wof:name":"Eenrum Vv",
    "wof:placetype":"venue"
},
  "geometry": {"coordinates":[6.461958,53.361912],"type":"Point"}
}