{
  "type": "Feature",
  "properties": {
    "addr:full":"Gebbelswg 21 Ospel Limburg 6035 EA",
    "addr:housenumber":"21",
    "addr:postcode":"6035 ea",
    "addr:street":"Gebbelswg",
    "iso:country":"NL",
    "sg:address":"Gebbelswg 21",
    "sg:city":"Ospel",
    "sg:orig_category":"Loonbedrijven",
    "sg:phone":"+31 495 625 502",
    "sg:postcode":"6035 EA",
    "sg:province":"Limburg",
    "wof:name":"Heugten En Slaats Vof, Van",
    "wof:placetype":"venue"
},
  "geometry": {"coordinates":[-86.165451,34.620892],"type":"Point"}
}