{
  "type": "Feature",
  "properties": {
    "addr:full":"Ginnekenwg 236 Breda North Brabant 4835 NJ",
    "addr:housenumber":"236",
    "addr:postcode":"4835 nj",
    "iso:country":"NL",
    "sg:address":"Ginnekenwg 236",
    "sg:city":"Breda",
    "sg:orig_category":"Makelaars En Adviseurs Onroerende Goederen",
    "sg:phone":"+31 76 560 0404",
    "sg:postcode":"4835 NJ",
    "sg:province":"North Brabant",
    "sg:website":"http://www.sweegershomepage.nl",
    "wof:name":"Frank Sweegers Makelaardij",
    "wof:placetype":"venue"
},
  "geometry": {"coordinates":[4.783472,51.571381],"type":"Point"}
}