{
  "type": "Feature",
  "properties": {
    "addr:full":"Mgr Nolensstr 2 Ryen Noord-Brabant 5121 AM",
    "addr:housenumber":"2",
    "addr:postcode":"5121",
    "addr:street":"Nolensstr",
    "iso:country":"NL",
    "sg:address":"Mgr Nolensstr 2",
    "sg:city":"Ryen",
    "sg:orig_category":"Scholen Voor Basisonderwijs",
    "sg:phone":"+31 161 223 541",
    "sg:postcode":"5121 AM",
    "sg:province":"Noord-Brabant",
    "wof:name":"Vijf Eiken Prot Chr, De",
    "wof:placetype":"venue"
},
  "geometry": {"coordinates":[4.9197,51.588017],"type":"Point"}
}