{
  "type": "Feature",
  "properties": {
    "addr:full":"Bunzingln 27 Veenendaal Utrecht 3903 CS",
    "addr:housenumber":"27",
    "addr:postcode":"3903 cs",
    "addr:street":"Bunzingln",
    "iso:country":"NL",
    "sg:address":"Bunzingln 27",
    "sg:city":"Veenendaal",
    "sg:orig_category":"Adviesbureaus Bouwkunde",
    "sg:phone":"+31 318 652 165",
    "sg:postcode":"3903 CS",
    "sg:province":"Utrecht",
    "wof:name":"Hendriksen",
    "wof:placetype":"venue"
},
  "geometry": {"coordinates":[5.549003,52.008499],"type":"Point"}
}