{
  "type": "Feature",
  "properties": {
    "iso:country":"NL",
    "sg:address":"V Riebeeckwg 43B",
    "sg:city":"Hilversum",
    "sg:orig_category":"Hypotheken",
    "sg:phone":"+31 35 642 3505",
    "sg:postcode":"1212 EH",
    "sg:province":"Noord-Holland",
    "sg:website":"http://www.vanbruggen.nl",
    "wof:name":"Bruggen Adviesgroep, Van",
    "wof:placetype":"venue"
},
  "geometry": {"coordinates":[5.1695,52.228565],"type":"Point"}
}