{
  "type": "Feature",
  "properties": {
    "iso:country":"NL",
    "sg:address":"Fort 32",
    "sg:city":"Veeningen",
    "sg:orig_category":"Pluimveehouderijen",
    "sg:phone":"+31 528 391 069",
    "sg:postcode":"7924 RB",
    "sg:province":"Drenthe",
    "wof:name":"Van Gent International",
    "wof:placetype":"venue"
},
  "geometry": {"coordinates":[6.382376,52.653671],"type":"Point"}
}