{
  "type": "Feature",
  "properties": {
    "addr:full":"Karrestr 26 Oosterhout Nb Noord-Brabant 4904 VL",
    "addr:housenumber":"26",
    "addr:postcode":"4904 vl",
    "addr:street":"Karrestr",
    "iso:country":"NL",
    "sg:address":"Karrestr 26",
    "sg:city":"Oosterhout Nb",
    "sg:orig_category":"Fotoreportages",
    "sg:phone":"+31 6 51788771",
    "sg:postcode":"4904 VL",
    "sg:province":"Noord-Brabant",
    "wof:name":"Schouten",
    "wof:placetype":"venue"
},
  "geometry": {"coordinates":[4.836261,51.644432],"type":"Point"}
}