{
  "type": "Feature",
  "properties": {
    "iso:country":"NL",
    "sg:address":"Slypkruikwg 53",
    "sg:city":"Ede Gld",
    "sg:orig_category":"Onroerende Goederen",
    "sg:phone":"+31 318 613 027",
    "sg:postcode":"6712 DJ",
    "sg:province":"Gelderland",
    "wof:name":"Borgmij Ede Bv",
    "wof:placetype":"venue"
},
  "geometry": {"coordinates":[5.659373,52.046967],"type":"Point"}
}