{
  "type": "Feature",
  "properties": {
    "addr:full":"E Griegstraat 4 Zuid-Beijerland Zuid-Holland 3284 BB",
    "addr:housenumber":"4",
    "addr:postcode":"3284 bb",
    "addr:street":"E Griegstraat",
    "iso:country":"NL",
    "sg:address":"E Griegstraat 4",
    "sg:city":"Zuid-Beijerland",
    "sg:orig_category":"Technische Studies And Onderzoek",
    "sg:phone":"+31 186 660 016",
    "sg:postcode":"3284 BB",
    "sg:province":"Zuid-Holland",
    "wof:name":"Rifa",
    "wof:placetype":"venue"
},
  "geometry": {"coordinates":[4.321596,51.754227],"type":"Point"}
}