{
  "type": "Feature",
  "properties": {
    "addr:full":"Oude Schans 64 Bunschoten Spakenb Utrecht 3752 AH",
    "addr:housenumber":"64",
    "addr:postcode":"3752 ah",
    "addr:street":"Oude Schans",
    "iso:country":"NL",
    "sg:address":"Oude Schans 64",
    "sg:city":"Bunschoten Spakenb",
    "sg:orig_category":"Kinderkleding",
    "sg:phone":"+31 33 298 4142",
    "sg:postcode":"3752 AH",
    "sg:province":"Utrecht",
    "sg:website":"http://www.weetal.net/dwerg",
    "wof:name":"Dwerg, De",
    "wof:placetype":"venue"
},
  "geometry": {"coordinates":[5.378015,52.254791],"type":"Point"}
}