{
  "type": "Feature",
  "properties": {
    "addr:full":"Stationsstr 49 Veghel Noord-Brabant 5461 JT",
    "addr:housenumber":"49",
    "addr:postcode":"5461 jt",
    "addr:street":"Stationsstr",
    "iso:country":"NL",
    "sg:address":"Stationsstr 49",
    "sg:city":"Veghel",
    "sg:orig_category":"Parketvloeren",
    "sg:phone":"+31 413 363 186",
    "sg:postcode":"5461 JT",
    "sg:province":"Noord-Brabant",
    "wof:name":"Meijerij, De",
    "wof:placetype":"venue"
},
  "geometry": {"coordinates":[5.545398,51.621017],"type":"Point"}
}