{
  "type": "Feature",
  "properties": {
    "iso:country":"NL",
    "sg:address":"Lijnbaan 4",
    "sg:city":"Werkendam",
    "sg:classifiers":[
        {
            "category":"Bakery",
            "type":"Food & Drink"
        }
    ],
    "sg:phone":"+31 183 501 104",
    "sg:postcode":"4251 CS",
    "sg:province":"Noord-Brabant",
    "sg:tags":[
        "brood",
        "banket"
    ],
    "wof:name":"Le Geste",
    "wof:placetype":"venue"
},
  "geometry": {"coordinates":[4.896878,51.814316],"type":"Point"}
}