{
  "type": "Feature",
  "properties": {
    "addr:full":"Koningsplein 8 Asten Noord-Brabant 5721 GJ",
    "addr:housenumber":"8",
    "addr:postcode":"5721 gj",
    "addr:street":"Koningsplein",
    "iso:country":"NL",
    "sg:address":"Koningsplein 8",
    "sg:city":"Asten",
    "sg:orig_category":"Advocaten And Juridische Adviseurs",
    "sg:phone":"+31 493 691 237",
    "sg:postcode":"5721 GJ",
    "sg:province":"Noord-Brabant",
    "wof:name":"Advocatenkantoor Koningsplein Asten",
    "wof:placetype":"venue"
},
  "geometry": {"coordinates":[5.744701,51.403835],"type":"Point"}
}