{
  "type": "Feature",
  "properties": {
    "addr:full":"Delphinus 8 Loon Op Zand Noord-Brabant 5175 VC",
    "addr:housenumber":"8",
    "addr:postcode":"5175 vc",
    "addr:street":"Delphinus",
    "iso:country":"NL",
    "sg:address":"Delphinus 8",
    "sg:city":"Loon Op Zand",
    "sg:orig_category":"Webdesign Bureaus",
    "sg:phone":"+31 416 362 236",
    "sg:postcode":"5175 VC",
    "sg:province":"Noord-Brabant",
    "sg:website":"http://www.flover.nl/clickart.benelux",
    "wof:name":"Click-Art",
    "wof:placetype":"venue"
},
  "geometry": {"coordinates":[5.0820212364,51.6253738403],"type":"Point"}
}