{
  "type": "Feature",
  "properties": {
    "addr:full":"Burg Uilkensstr 6 Bergambacht Zuid-Holland 2861 AE",
    "addr:housenumber":"6",
    "addr:postcode":"2861 ae",
    "addr:street":"Burg Uilkensstr",
    "iso:country":"NL",
    "sg:address":"Burg Uilkensstr 6",
    "sg:city":"Bergambacht",
    "sg:orig_category":"Optiek - Fabrieken En Groothandel",
    "sg:phone":"+31 182 350 450",
    "sg:postcode":"2861 AE",
    "sg:province":"Zuid-Holland",
    "wof:name":"Nhm",
    "wof:placetype":"venue"
},
  "geometry": {"coordinates":[4.7831192017,51.9364624023],"type":"Point"}
}