{
  "type": "Feature",
  "properties": {
    "iso:country":"NL",
    "sg:address":"Emmastr 1",
    "sg:city":"Lochem",
    "sg:orig_category":"Kappers",
    "sg:phone":"+31 573 256 407",
    "sg:postcode":"7241 EH",
    "sg:province":"Gelderland",
    "sg:website":"http://www.hairstylingeffect.nl",
    "wof:name":"Effect, Hairstyling",
    "wof:placetype":"venue"
},
  "geometry": {"coordinates":[6.4164638519,52.1594467163],"type":"Point"}
}