{
  "type": "Feature",
  "properties": {
    "addr:full":"Oud Loosd Dk 79A Loosdrecht Noord-Holland 1231 LR",
    "addr:housenumber":"79a",
    "addr:postcode":"1231 lr",
    "addr:street":"Oud;Dk",
    "iso:country":"NL",
    "sg:address":"Oud Loosd Dk 79A",
    "sg:city":"Loosdrecht",
    "sg:orig_category":"Jachthavens - Jachtwerven",
    "sg:phone":"+31 35 582 1462",
    "sg:postcode":"1231 LR",
    "sg:province":"Noord-Holland",
    "sg:website":"http://www.jachthavenloosdrecht.nl",
    "wof:name":"Jachthaven Loosdrecht",
    "wof:placetype":"venue"
},
  "geometry": {"coordinates":[5.108362,52.20676],"type":"Point"}
}