{
  "type": "Feature",
  "properties": {
    "addr:full":"Nieuwemeerdijk 32 Badhoevedorp Noord-Holland 1171 NB",
    "addr:housenumber":"32",
    "addr:postcode":"1171 nb",
    "addr:street":"Nieuwemeerdijk",
    "iso:country":"NL",
    "sg:address":"Nieuwemeerdijk 32",
    "sg:city":"Badhoevedorp",
    "sg:orig_category":"Meubelzaken, Woning- And Keukeninrichting",
    "sg:phone":"+31 20 659 9171",
    "sg:postcode":"1171 NB",
    "sg:province":"Noord-Holland",
    "wof:name":"Enchanted",
    "wof:placetype":"venue"
},
  "geometry": {"coordinates":[4.789554,52.341785],"type":"Point"}
}