{
  "type": "Feature",
  "properties": {
    "addr:full":"Burg. Prinsensingel 20 Roosendaal North Brabant 4701 HM",
    "addr:housenumber":"20",
    "addr:postcode":"4701 hm",
    "addr:street":"Burg. Prinsensingel",
    "iso:country":"NL",
    "sg:address":"Burg. Prinsensingel 20",
    "sg:city":"Roosendaal",
    "sg:orig_category":"Meubelzaken, Woning- And Keukeninrichting",
    "sg:phone":"+31 165 558 097",
    "sg:postcode":"4701 HM",
    "sg:province":"North Brabant",
    "wof:name":"Brabantsch Korfke",
    "wof:placetype":"venue"
},
  "geometry": {"coordinates":[4.460649,51.535332],"type":"Point"}
}