{
  "type": "Feature",
  "properties": {
    "addr:full":"Wagendwstr 22 Utrecht Utrecht 3581 WL",
    "addr:housenumber":"22",
    "addr:postcode":"3581 wl",
    "addr:street":"Wagendwstr",
    "iso:country":"NL",
    "sg:address":"Wagendwstr 22",
    "sg:city":"Utrecht",
    "sg:orig_category":"Natuur- En Milieuorganisaties",
    "sg:phone":"+31 30 252 0738",
    "sg:postcode":"3581 WL",
    "sg:province":"Utrecht",
    "wof:name":"Meulenbroek",
    "wof:placetype":"venue"
},
  "geometry": {"coordinates":[5.134707,52.089703],"type":"Point"}
}