{
  "type": "Feature",
  "properties": {
    "addr:full":"Van Brienenlaan 7 Wassenaar South Holland 2244 BP",
    "addr:housenumber":"7",
    "addr:postcode":"2244 bp",
    "addr:street":"Van Brienenlaan",
    "iso:country":"NL",
    "sg:address":"Van Brienenlaan 7",
    "sg:city":"Wassenaar",
    "sg:orig_category":"Juridische Adviseurs",
    "sg:phone":"+31 70 324 0357",
    "sg:postcode":"2244 BP",
    "sg:province":"South Holland",
    "wof:name":"Kreek, M",
    "wof:placetype":"venue"
},
  "geometry": {"coordinates":[4.340776,52.103081],"type":"Point"}
}