{
  "type": "Feature",
  "properties": {
    "iso:country":"NL",
    "sg:address":"Grt Spie 207",
    "sg:city":"Breda",
    "sg:orig_category":"Accountants - Administratie- Consulenten En -Kantoren",
    "sg:phone":"+31 76 522 5005",
    "sg:postcode":"4819 CS",
    "sg:province":"Noord-Brabant",
    "wof:name":"Atd",
    "wof:placetype":"venue"
},
  "geometry": {"coordinates":[4.768312,51.574329],"type":"Point"}
}