{
  "type": "Feature",
  "properties": {
    "addr:full":"Vlasakker 6 Uithuizermeeden Groningen 9982 HG",
    "addr:housenumber":"6",
    "addr:postcode":"9982 hg",
    "addr:street":"Vlasakker",
    "iso:country":"NL",
    "sg:address":"Vlasakker 6",
    "sg:city":"Uithuizermeeden",
    "sg:orig_category":"Banken",
    "sg:phone":"+31 595 412 576",
    "sg:postcode":"9982 HG",
    "sg:province":"Groningen",
    "wof:name":"Sns",
    "wof:placetype":"venue"
},
  "geometry": {"coordinates":[6.724521,53.414806],"type":"Point"}
}