{
  "type": "Feature",
  "properties": {
    "iso:country":"NL",
    "sg:address":"Gemeenelandswg 72",
    "sg:city":"Den Oever",
    "sg:orig_category":"Kaas",
    "sg:phone":"+31 227 511 037",
    "sg:postcode":"1779 GC",
    "sg:province":"North Holland",
    "sg:website":"http://www.cometo/poortman",
    "wof:name":"Land Van Wieringen",
    "wof:placetype":"venue"
},
  "geometry": {"coordinates":[5.0072398186,52.9315452576],"type":"Point"}
}