{
  "type": "Feature",
  "properties": {
    "addr:full":"Maxwellstr 53 Dordrecht Zuid-Holland 3316 GP",
    "addr:housenumber":"53",
    "addr:postcode":"3316 gp",
    "addr:street":"Maxwellstr",
    "iso:country":"NL",
    "sg:address":"Maxwellstr 53",
    "sg:city":"Dordrecht",
    "sg:orig_category":"Kantoor- En Bedrijfsmeubelen",
    "sg:phone":"+31 78 617 6240",
    "sg:postcode":"3316 GP",
    "sg:province":"Zuid-Holland",
    "sg:website":"http://www.verstraten.com",
    "wof:name":"Brink Dordrecht Bv",
    "wof:placetype":"venue"
},
  "geometry": {"coordinates":[4.6336598396,51.7817764282],"type":"Point"}
}