{
  "type": "Feature",
  "properties": {
    "iso:country":"NL",
    "sg:address":"Groenedijk 5",
    "sg:city":"Laren Gld",
    "sg:orig_category":"Bloemen And Planten",
    "sg:phone":"+31 573 221 364",
    "sg:postcode":"7245 SV",
    "sg:province":"Gelderland",
    "wof:name":"M.J. Kroeze",
    "wof:placetype":"venue"
},
  "geometry": {"coordinates":[6.396407,52.234516],"type":"Point"}
}