{
  "type": "Feature",
  "properties": {
    "addr:full":"Groenedijk 5 Laren Gld Gelderland 7245 SV",
    "addr:housenumber":"5",
    "addr:postcode":"7245 sv",
    "addr:street":"Groenedijk;Gld Gelderland",
    "iso:country":"NL",
    "sg:address":"Groenedijk 5",
    "sg:city":"Laren Gld",
    "sg:orig_category":"Bloemen And Planten",
    "sg:phone":"+31 573 221 364",
    "sg:postcode":"7245 SV",
    "sg:province":"Gelderland",
    "wof:name":"M.J. Kroeze",
    "wof:placetype":"venue"
},
  "geometry": {"coordinates":[6.396407,52.234516],"type":"Point"}
}