{
  "type": "Feature",
  "properties": {
    "addr:full":"Europalaan 5 Sas Van Gent BE.08 4551 VA",
    "addr:housenumber":"5",
    "addr:postcode":"4551",
    "addr:street":"Europalaan",
    "iso:country":"NL",
    "sg:address":"Europalaan 5",
    "sg:city":"Sas Van Gent",
    "sg:orig_category":"Goederenvervoer Over De Weg",
    "sg:phone":"+31 115 453 413",
    "sg:postcode":"4551 VA",
    "sg:province":"BE.08",
    "wof:name":"F.A. Van Damme",
    "wof:placetype":"venue"
},
  "geometry": {"coordinates":[3.790147,51.232471],"type":"Point"}
}