{
  "type": "Feature",
  "properties": {
    "addr:full":"Vergierdewg 5Zw Haarlem Noord-Holland 2025 TG",
    "addr:housenumber":"5zw",
    "addr:postcode":"2025 tg",
    "addr:street":"Vergierdewg",
    "iso:country":"NL",
    "sg:address":"Vergierdewg 5Zw",
    "sg:city":"Haarlem",
    "sg:orig_category":"Maaltijdbezorging",
    "sg:phone":"+31 23 538 9080",
    "sg:postcode":"2025 TG",
    "sg:province":"Noord-Holland",
    "wof:name":"Canton Express",
    "wof:placetype":"venue"
},
  "geometry": {"coordinates":[4.650987,52.413235],"type":"Point"}
}