{
  "type": "Feature",
  "properties": {
    "iso:country":"NL",
    "sg:address":"Dorpsstr 21",
    "sg:city":"Oude Niedorp",
    "sg:orig_category":"Administratie- En Boekhoudkantoren",
    "sg:phone":"+31 226 421 494",
    "sg:postcode":"1734 JH",
    "sg:province":"Noord-Holland",
    "wof:name":"Langen, A J Van",
    "wof:placetype":"venue"
},
  "geometry": {"coordinates":[4.876656,52.71946],"type":"Point"}
}