{
  "type": "Feature",
  "properties": {
    "addr:full":"Hulsdonkstraat 4 Zundert Noord-Brabant 4882 JM",
    "addr:housenumber":"4",
    "addr:postcode":"4882 jm",
    "addr:street":"Hulsdonkstraat",
    "iso:country":"NL",
    "sg:address":"Hulsdonkstraat 4",
    "sg:city":"Zundert",
    "sg:orig_category":"Gebouwenafwerking, Renovaties And Reiniging",
    "sg:phone":"+31 76 597 2824",
    "sg:postcode":"4882 JM",
    "sg:province":"Noord-Brabant",
    "wof:name":"Reinigingsbedrijf Oostvogels",
    "wof:placetype":"venue"
},
  "geometry": {"coordinates":[4.619096,51.474739],"type":"Point"}
}