{
  "type": "Feature",
  "properties": {
    "addr:full":"Zevenlindenweg 5 Baarn Utrecht 3744 BC",
    "addr:housenumber":"5",
    "addr:postcode":"3744 bc",
    "addr:street":"Zevenlindenweg",
    "iso:country":"NL",
    "sg:address":"Zevenlindenweg 5",
    "sg:city":"Baarn",
    "sg:orig_category":"Technische Studies And Onderzoek",
    "sg:phone":"+31 35 666 8170",
    "sg:postcode":"3744 BC",
    "sg:province":"Utrecht",
    "wof:name":"Van Dammen Engineering",
    "wof:placetype":"venue"
},
  "geometry": {"coordinates":[5.24697,52.196251],"type":"Point"}
}