{
  "type": "Feature",
  "properties": {
    "addr:full":"Dorpspln 8 Kesteren Gelderland 4041 GH",
    "addr:housenumber":"8",
    "addr:postcode":"4041 gh",
    "addr:street":"Dorpspln;Gelderland",
    "iso:country":"NL",
    "sg:address":"Dorpspln 8",
    "sg:city":"Kesteren",
    "sg:orig_category":"Cafetaria'S",
    "sg:phone":"+31 488 481 892",
    "sg:postcode":"4041 GH",
    "sg:province":"Gelderland",
    "wof:name":"Karrewiel, 'T",
    "wof:placetype":"venue"
},
  "geometry": {"coordinates":[5.572982,51.936089],"type":"Point"}
}