{
  "type": "Feature",
  "properties": {
    "iso:country":"NL",
    "sg:address":"Pr Bernhardln 14",
    "sg:city":"Heeze",
    "sg:orig_category":"Keukens",
    "sg:phone":"+31 40 226 0199",
    "sg:postcode":"5591 GD",
    "sg:province":"Noord-Brabant",
    "wof:name":"Fd Montage",
    "wof:placetype":"venue"
},
  "geometry": {"coordinates":[5.577821,51.379597],"type":"Point"}
}