{
  "type": "Feature",
  "properties": {
    "addr:full":"W Buytewechstr 30-32 Rotterdam Zuid-Holland 3024 BN",
    "addr:housenumber":"30-32",
    "addr:postcode":"rotterdam;3024 bn",
    "addr:street":"W",
    "iso:country":"NL",
    "sg:address":"W Buytewechstr 30-32",
    "sg:city":"Rotterdam",
    "sg:classifiers":[
        {
            "category":"Retail",
            "subcategory":"Auto Repair",
            "type":"Services"
        }
    ],
    "sg:phone":"+31 10 425 9124",
    "sg:postcode":"3024 BN",
    "sg:province":"Zuid-Holland",
    "sg:tags":[
        "garage"
    ],
    "wof:name":"Onem",
    "wof:placetype":"venue"
},
  "geometry": {"coordinates":[4.461697,51.907516],"type":"Point"}
}