{
  "type": "Feature",
  "properties": {
    "iso:country":"NL",
    "sg:address":"Rietschoot 274",
    "sg:city":"Oostzaan",
    "sg:orig_category":"Adviesbureaus Bouwkunde",
    "sg:phone":"+31 75 684 3428",
    "sg:postcode":"1511 WT",
    "sg:province":"Noord-Holland",
    "wof:name":"Idea",
    "wof:placetype":"venue"
},
  "geometry": {"coordinates":[4.884313,52.436054],"type":"Point"}
}