{
  "type": "Feature",
  "properties": {
    "iso:country":"NL",
    "sg:address":"Postbus 1681",
    "sg:city":"Amsterdam",
    "sg:classifiers":[
        {
            "category":"Military Area",
            "subcategory":"Air Force Base",
            "type":"Public Place"
        }
    ],
    "sg:phone":"+31 20 428 9690",
    "sg:postcode":"1000 BR",
    "sg:province":"Noord-Holland",
    "sg:tags":[
        "cabaret"
    ],
    "wof:name":"Amsterdams Kleinkunst Festival",
    "wof:placetype":"venue"
},
  "geometry": {"coordinates":[4.89319,52.373119],"type":"Point"}
}