{
  "type": "Feature",
  "properties": {
    "addr:full":"Grt Heiligland 67 Haarlem Noord-Holland 2011 EP",
    "addr:housenumber":"67",
    "addr:postcode":"2011 ep",
    "addr:street":"Grt Heiligland",
    "iso:country":"NL",
    "sg:address":"Grt Heiligland 67",
    "sg:city":"Haarlem",
    "sg:orig_category":"Projectontwikkeling",
    "sg:phone":"+31 23 531 0133",
    "sg:postcode":"2011 EP",
    "sg:province":"Noord-Holland",
    "wof:name":"Ecostad Bv",
    "wof:placetype":"venue"
},
  "geometry": {"coordinates":[4.633861,52.376579],"type":"Point"}
}