{
  "type": "Feature",
  "properties": {
    "iso:country":"NL",
    "sg:address":"Plutolaan 43",
    "sg:city":"Roermond",
    "sg:orig_category":"Werving And Selectie Van Tijdelijk Personeel And Uitzendkantoren",
    "sg:phone":"+31 475 329 990",
    "sg:postcode":"6043 VN",
    "sg:province":"Limburg",
    "wof:name":"Mettin",
    "wof:placetype":"venue"
},
  "geometry": {"coordinates":[6.0142278671,51.185508728],"type":"Point"}
}