{
  "type": "Feature",
  "properties": {
    "addr:full":"Voorstraat 313 Lelystad NL. 8226 KB",
    "addr:housenumber":"313",
    "addr:postcode":"8226 kb",
    "addr:street":"Voorstraat;Nl.",
    "iso:country":"NL",
    "sg:address":"Voorstraat 313",
    "sg:city":"Lelystad",
    "sg:orig_category":"Bibliotheken And Openbare Archieven",
    "sg:phone":"+31 320 256 111",
    "sg:postcode":"8226 KB",
    "sg:province":"NL.",
    "wof:name":"De Bever",
    "wof:placetype":"venue"
},
  "geometry": {"coordinates":[5.492395,52.494202],"type":"Point"}
}