{
  "type": "Feature",
  "properties": {
    "addr:full":"De Steiger 63B Almere NL. 1351 AD",
    "addr:housenumber":"63b",
    "addr:postcode":"1351 ad",
    "addr:street":"De Steiger;Nl.",
    "iso:country":"NL",
    "sg:address":"De Steiger 63B",
    "sg:city":"Almere",
    "sg:orig_category":"Wasmachines En Wasdrogers - Onderhoud En Reparatie",
    "sg:phone":"+31 6 51227626",
    "sg:postcode":"1351 AD",
    "sg:province":"NL.",
    "sg:website":"http://www.selectra.nl",
    "wof:name":"Rim",
    "wof:placetype":"venue"
},
  "geometry": {"coordinates":[5.2247200012,52.3501243591],"type":"Point"}
}