{
  "type": "Feature",
  "properties": {
    "addr:full":"Mient 23 Alkmaar North Holland 1811 NB",
    "addr:housenumber":"23",
    "addr:postcode":"1811 nb",
    "addr:street":"Mient",
    "iso:country":"NL",
    "sg:address":"Mient 23",
    "sg:city":"Alkmaar",
    "sg:orig_category":"Woninginrichting",
    "sg:phone":"+31 72 512 0844",
    "sg:postcode":"1811 NB",
    "sg:province":"North Holland",
    "sg:website":"http://www.goodhousing.nl",
    "wof:name":"Good Housing Bv",
    "wof:placetype":"venue"
},
  "geometry": {"coordinates":[4.7503871918,52.6304969788],"type":"Point"}
}