{
  "type": "Feature",
  "properties": {
    "addr:full":"Schooneggendreef 220 Utrecht Utrecht 3562 GM",
    "addr:housenumber":"220",
    "addr:postcode":"3562 gm",
    "addr:street":"Schooneggendreef",
    "iso:country":"NL",
    "sg:address":"Schooneggendreef 220",
    "sg:city":"Utrecht",
    "sg:orig_category":"Webdesign Bureaus",
    "sg:phone":"+31 30 262 2044",
    "sg:postcode":"3562 GM",
    "sg:province":"Utrecht",
    "sg:website":"http://www.treedesign.nl",
    "wof:name":"Tree",
    "wof:placetype":"venue"
},
  "geometry": {"coordinates":[5.1168079376,52.1208114624],"type":"Point"}
}