{
  "type": "Feature",
  "properties": {
    "iso:country":"NL",
    "sg:address":"Helling 2",
    "sg:city":"Wanssum",
    "sg:orig_category":"Technische Studies And Onderzoek",
    "sg:phone":"+31 478 532 929",
    "sg:postcode":"5861 AA",
    "sg:province":"Limburg",
    "wof:name":"Volleberg Transporttechniek Vof",
    "wof:placetype":"venue"
},
  "geometry": {"coordinates":[6.082925,51.531605],"type":"Point"}
}