{
  "type": "Feature",
  "properties": {
    "addr:full":"Amstelveensewg 330 Amsterdam Noord-Holland 1076 CS",
    "addr:housenumber":"330",
    "addr:postcode":"1076 cs",
    "iso:country":"NL",
    "sg:address":"Amstelveensewg 330",
    "sg:city":"Amsterdam",
    "sg:orig_category":"Bedrijfsopleidingen",
    "sg:phone":"+31 20 639 0008",
    "sg:postcode":"1076 CS",
    "sg:province":"Noord-Holland",
    "sg:website":"http://www.alexvangroningen.nl",
    "wof:name":"Alex Van Groningen Corporate & Finance Training",
    "wof:placetype":"venue"
},
  "geometry": {"coordinates":[4.857264,52.345837],"type":"Point"}
}