{
  "type": "Feature",
  "properties": {
    "iso:country":"NL",
    "sg:address":"Loenermark 558A",
    "sg:city":"Amsterdam",
    "sg:orig_category":"Verzekeringen - Verzekeringskantoren",
    "sg:phone":"+31 20 614 3340",
    "sg:postcode":"1025 TX",
    "sg:province":"North Holland",
    "sg:website":"http://www.eerste.nl",
    "wof:name":"Eerste Nederlandsche Direkt",
    "wof:placetype":"venue"
},
  "geometry": {"coordinates":[4.931928,52.399662],"type":"Point"}
}