{
  "type": "Feature",
  "properties": {
    "iso:country":"NL",
    "sg:address":"Jan Pieterszoon Coenstr 62",
    "sg:city":"Utrecht",
    "sg:classifiers":[
        {
            "category":"Bars & Pubs",
            "type":"Food & Drink"
        }
    ],
    "sg:phone":"+31 30 294 4927",
    "sg:postcode":"3531 EX",
    "sg:province":"Utrecht",
    "wof:name":"Oz - Pamukkale",
    "wof:placetype":"venue"
},
  "geometry": {"coordinates":[5.097079,52.091888],"type":"Point"}
}