{
  "type": "Feature",
  "properties": {
    "iso:country":"NL",
    "sg:address":"Lichtenvoordsestraatweg 15",
    "sg:city":"Aalten",
    "sg:classifiers":[
        {
            "category":"Fast Food",
            "type":"Food & Drink"
        }
    ],
    "sg:phone":"+31 543 475 152",
    "sg:postcode":"7121 AA",
    "sg:province":"Gelderland",
    "sg:tags":[
        "afhaal",
        "restaurant"
    ],
    "wof:name":"Chinees-Indisch Restaurant Kota Radja",
    "wof:placetype":"venue"
},
  "geometry": {"coordinates":[6.580776,51.929901],"type":"Point"}
}