{
  "type": "Feature",
  "properties": {
    "addr:full":"Ged Schalkburg Gr 49 Haarlem Noord-Holland 2021 AJ",
    "addr:housenumber":"49",
    "addr:postcode":"2021 aj",
    "addr:street":"Gr",
    "iso:country":"NL",
    "sg:address":"Ged Schalkburg Gr 49",
    "sg:city":"Haarlem",
    "sg:orig_category":"Administratie- En Boekhoudkantoren",
    "sg:phone":"+31 23 527 6857",
    "sg:postcode":"2021 AJ",
    "sg:province":"Noord-Holland",
    "wof:name":"Avantage",
    "wof:placetype":"venue"
},
  "geometry": {"coordinates":[4.64225,52.380562],"type":"Point"}
}