{
  "type": "Feature",
  "properties": {
    "addr:full":"5E Industriestr 13 Vlaardingen Zuid-Holland 3133 EL",
    "addr:housenumber":"13",
    "addr:postcode":"3133 el",
    "addr:street":"5E Industriestr",
    "iso:country":"NL",
    "sg:address":"5E Industriestr 13",
    "sg:city":"Vlaardingen",
    "sg:orig_category":"Autoschade- Herstelbedrijven",
    "sg:phone":"+31 10 435 6609",
    "sg:postcode":"3133 EL",
    "sg:province":"Zuid-Holland",
    "wof:name":"Jaap'S Autoschade",
    "wof:placetype":"venue"
},
  "geometry": {"coordinates":[4.328406,51.902649],"type":"Point"}
}