{
  "type": "Feature",
  "properties": {
    "addr:full":"Lynbaan 77 Heemskerk Noord-Holland 1969 ND",
    "addr:housenumber":"77",
    "addr:postcode":"1969 nd",
    "addr:street":"Lynbaan",
    "iso:country":"NL",
    "sg:address":"Lynbaan 77",
    "sg:city":"Heemskerk",
    "sg:orig_category":"Wijnkoperijen En -Groothandel",
    "sg:phone":"+31 251 247 204",
    "sg:postcode":"1969 ND",
    "sg:province":"Noord-Holland",
    "sg:website":"http://www.smeraglia.nl",
    "wof:name":"Smeraglia",
    "wof:placetype":"venue"
},
  "geometry": {"coordinates":[-100.3017120361,47.4677314758],"type":"Point"}
}