{
  "type": "Feature",
  "properties": {
    "iso:country":"NL",
    "sg:address":"Franse Kerkstr 3A",
    "sg:city":"Voorburg",
    "sg:orig_category":"Nagelstudio'S",
    "sg:phone":"+31 70 369 2864",
    "sg:postcode":"2271 CM",
    "sg:province":"Zuid-Holland",
    "wof:name":"Sensationails",
    "wof:placetype":"venue"
},
  "geometry": {"coordinates":[4.363391,52.06744],"type":"Point"}
}