{
  "type": "Feature",
  "properties": {
    "iso:country":"NL",
    "sg:address":"Klapstraat 45",
    "sg:city":"Arnhem",
    "sg:orig_category":"Bloemen And Planten",
    "sg:phone":"+31 26 381 6021",
    "sg:postcode":"6842 AC",
    "sg:province":"Gelderland",
    "wof:name":"Vof Bloemenhuis Elden",
    "wof:placetype":"venue"
},
  "geometry": {"coordinates":[5.87795,51.960209],"type":"Point"}
}