{
  "type": "Feature",
  "properties": {
    "addr:full":"Molenrand 7A Gemert Noord-Brabant 5421 VZ",
    "addr:housenumber":"7a",
    "addr:postcode":"5421 vz",
    "addr:street":"Molenrand",
    "iso:country":"NL",
    "sg:address":"Molenrand 7A",
    "sg:city":"Gemert",
    "sg:orig_category":"Autopoetsbedrijven",
    "sg:phone":"+31 492 553 365",
    "sg:postcode":"5421 VZ",
    "sg:province":"Noord-Brabant",
    "wof:name":"Number One",
    "wof:placetype":"venue"
},
  "geometry": {"coordinates":[5.681675,51.556126],"type":"Point"}
}