{
  "type": "Feature",
  "properties": {
    "addr:full":"Vismarkt Groningen Groningen 9712 CB",
    "addr:postcode":"9712 cb",
    "addr:street":"Vismarkt",
    "iso:country":"NL",
    "sg:address":"Vismarkt",
    "sg:city":"Groningen",
    "sg:orig_category":"Bloemen En Planten",
    "sg:phone":"+31 50 314 8275",
    "sg:postcode":"9712 CB",
    "sg:province":"Groningen",
    "wof:name":"Westerhof, Luuk",
    "wof:placetype":"venue"
},
  "geometry": {"coordinates":[6.564894,53.217346],"type":"Point"}
}