{
  "type": "Feature",
  "properties": {
    "iso:country":"NL",
    "sg:address":"Sportlaan 18",
    "sg:city":"Hulst",
    "sg:classifiers":[
        {
            "category":"Education",
            "subcategory":"Preschool",
            "type":"Public Place"
        }
    ],
    "sg:phone":"+31 114 319 130",
    "sg:postcode":"4561 KZ",
    "sg:province":"Zeeland",
    "sg:tags":[
        "kleuteronderwijs",
        "basis-"
    ],
    "wof:name":"Openbare Basisschool De Reynaert",
    "wof:placetype":"venue"
},
  "geometry": {"coordinates":[4.052311,51.289925],"type":"Point"}
}