{
  "type": "Feature",
  "properties": {
    "iso:country":"NL",
    "sg:address":"Waterstraat 1",
    "sg:city":"Beneden Leeuwen",
    "sg:orig_category":"Kantoor- And Schoolbenodigdheden Gh",
    "sg:phone":"+31 487 593 179",
    "sg:postcode":"6658 AA",
    "sg:province":"Gelderland",
    "wof:name":"Maas En Waalse Dozenhandel",
    "wof:placetype":"venue"
},
  "geometry": {"coordinates":[5.5321102142,51.8814125061],"type":"Point"}
}