{
  "type": "Feature",
  "properties": {
    "addr:full":"Waterstraat 1 Beneden Leeuwen Gelderland 6658 AA",
    "addr:housenumber":"1",
    "addr:postcode":"6658 aa",
    "addr:street":"Waterstraat",
    "iso:country":"NL",
    "sg:address":"Waterstraat 1",
    "sg:city":"Beneden Leeuwen",
    "sg:orig_category":"Kantoor- And Schoolbenodigdheden Gh",
    "sg:phone":"+31 487 593 179",
    "sg:postcode":"6658 AA",
    "sg:province":"Gelderland",
    "wof:name":"Maas En Waalse Dozenhandel",
    "wof:placetype":"venue"
},
  "geometry": {"coordinates":[5.5321102142,51.8814125061],"type":"Point"}
}