{
  "type": "Feature",
  "properties": {
    "addr:full":"Snoertsebaan 21 Deurne Noord-Brabant 5753 RS",
    "addr:housenumber":"21",
    "addr:postcode":"5753 rs",
    "addr:street":"Snoertsebaan",
    "iso:country":"NL",
    "sg:address":"Snoertsebaan 21",
    "sg:city":"Deurne",
    "sg:orig_category":"Voegwerken",
    "sg:phone":"+31 493 321 584",
    "sg:postcode":"5753 RS",
    "sg:province":"Noord-Brabant",
    "wof:name":"Hans Joosten",
    "wof:placetype":"venue"
},
  "geometry": {"coordinates":[5.830742,51.447453],"type":"Point"}
}