{
  "type": "Feature",
  "properties": {
    "addr:full":"Brink 3 Makkinga Friesland 8423 TE",
    "addr:housenumber":"3",
    "addr:postcode":"8423 te",
    "addr:street":"Brink",
    "iso:country":"NL",
    "sg:address":"Brink 3",
    "sg:city":"Makkinga",
    "sg:orig_category":"Verzekeringen",
    "sg:phone":"+31 516 441 646",
    "sg:postcode":"8423 TE",
    "sg:province":"Friesland",
    "wof:name":"Piet Rauwerda Verzekeringen",
    "wof:placetype":"venue"
},
  "geometry": {"coordinates":[6.217267,52.980354],"type":"Point"}
}