{
  "type": "Feature",
  "properties": {
    "addr:full":"Pynackerpln 5B Rotterdam Zuid-Holland 3035 GB",
    "addr:housenumber":"5b",
    "addr:postcode":"3035 gb",
    "addr:street":"Pynackerpln",
    "iso:country":"NL",
    "sg:address":"Pynackerpln 5B",
    "sg:city":"Rotterdam",
    "sg:classifiers":[
        {
            "category":"Personal",
            "subcategory":"Nail Salon",
            "type":"Services"
        }
    ],
    "sg:phone":"+31 10 466 3919",
    "sg:postcode":"3035 GB",
    "sg:province":"Zuid-Holland",
    "sg:tags":[
        "pedicure"
    ],
    "wof:name":"Waard, De",
    "wof:placetype":"venue"
},
  "geometry": {"coordinates":[4.479467,51.934223],"type":"Point"}
}