{
  "type": "Feature",
  "properties": {
    "addr:full":"Oldenzaalsestr 217 Hengelo Ov Overijssel 7557 GL",
    "addr:housenumber":"217",
    "addr:postcode":"7557 gl",
    "addr:street":"Ov",
    "iso:country":"NL",
    "sg:address":"Oldenzaalsestr 217",
    "sg:city":"Hengelo Ov",
    "sg:orig_category":"Meubelen",
    "sg:phone":"+31 74 256 8600",
    "sg:postcode":"7557 GL",
    "sg:province":"Overijssel",
    "sg:website":"HTTP://www.woodstockwonen.nl",
    "wof:name":"Woodstock",
    "wof:placetype":"venue"
},
  "geometry": {"coordinates":[6.80622,52.270725],"type":"Point"}
}