{
  "type": "Feature",
  "properties": {
    "iso:country":"NL",
    "sg:address":"Koorkerkhof 16",
    "sg:city":"Middelburg",
    "sg:orig_category":"Fotoreportages",
    "sg:phone":"+31 118 640 470",
    "sg:postcode":"4331 BB",
    "sg:province":"Zeeland",
    "wof:name":"Haak & Visser, Studio",
    "wof:placetype":"venue"
},
  "geometry": {"coordinates":[3.615613,51.499832],"type":"Point"}
}