{
  "type": "Feature",
  "properties": {
    "addr:full":"Sternln 17 Kamperland Zeeland 4493 SH",
    "addr:housenumber":"17",
    "addr:postcode":"4493 sh",
    "addr:street":"Sternln",
    "iso:country":"NL",
    "sg:address":"Sternln 17",
    "sg:city":"Kamperland",
    "sg:orig_category":"Binnenhuisarchitectuur",
    "sg:phone":"+31 113 372 152",
    "sg:postcode":"4493 SH",
    "sg:province":"Zeeland",
    "wof:name":"Cam Management Group Cv",
    "wof:placetype":"venue"
},
  "geometry": {"coordinates":[3.675797,51.562824],"type":"Point"}
}