{
  "type": "Feature",
  "properties": {
    "addr:full":"Meerkoldreef 12 Tilburg Noord-Brabant 5042 PN",
    "addr:housenumber":"12",
    "addr:postcode":"5042 pn",
    "addr:street":"Meerkoldreef",
    "iso:country":"NL",
    "sg:address":"Meerkoldreef 12",
    "sg:city":"Tilburg",
    "sg:classifiers":[
        {
            "category":"Education",
            "subcategory":"Preschool",
            "type":"Public Place"
        }
    ],
    "sg:phone":"+31 13 467 0809",
    "sg:postcode":"5042 PN",
    "sg:province":"Noord-Brabant",
    "sg:tags":[
        "kleuteronderwijs",
        "basis-"
    ],
    "wof:name":"Jan Ligthartschool Rendierhof",
    "wof:placetype":"venue"
},
  "geometry": {"coordinates":[5.049828,51.566292],"type":"Point"}
}