{
  "type": "Feature",
  "properties": {
    "iso:country":"NL",
    "sg:address":"Het Rietveld 22",
    "sg:city":"Apeldoorn",
    "sg:orig_category":"Bedden En Matrassen",
    "sg:phone":"+31 55 360 1377",
    "sg:postcode":"7321 CT",
    "sg:province":"Gelderland",
    "wof:name":"Oase",
    "wof:placetype":"venue"
},
  "geometry": {"coordinates":[5.99748,52.212097],"type":"Point"}
}