{
  "type": "Feature",
  "properties": {
    "addr:full":"Zonnewg 39 Amsterdam Noord-Holland 1033 CG",
    "addr:housenumber":"39",
    "addr:postcode":"1033 cg",
    "addr:street":"Zonnewg",
    "iso:country":"NL",
    "sg:address":"Zonnewg 39",
    "sg:city":"Amsterdam",
    "sg:orig_category":"Schilders",
    "sg:phone":"+31 20 337 1137",
    "sg:postcode":"1033 CG",
    "sg:province":"Noord-Holland",
    "wof:name":"Van Munster, W J",
    "wof:placetype":"venue"
},
  "geometry": {"coordinates":[4.8899860382,52.4125480652],"type":"Point"}
}