{
  "type": "Feature",
  "properties": {
    "addr:full":"Viltstraat 11 Bakel Noord-Brabant 5761 BR",
    "addr:housenumber":"11",
    "addr:postcode":"5761 br",
    "addr:street":"Viltstraat",
    "iso:country":"NL",
    "sg:address":"Viltstraat 11",
    "sg:city":"Bakel",
    "sg:orig_category":"Hoger Onderwijs",
    "sg:phone":"+31 492 342 443",
    "sg:postcode":"5761 BR",
    "sg:province":"Noord-Brabant",
    "wof:name":"A. Spaan-Nelissen",
    "wof:placetype":"venue"
},
  "geometry": {"coordinates":[5.743071,51.503399],"type":"Point"}
}