{
  "type": "Feature",
  "properties": {
    "iso:country":"NL",
    "sg:address":"Berliozlaan 40",
    "sg:city":"Rotterdam",
    "sg:orig_category":"Diverse Consumentenartikelen Gh",
    "sg:phone":"+31 10 461 3138",
    "sg:postcode":"3055 KB",
    "sg:province":"Zuid-Holland",
    "wof:name":"Swedutch Services",
    "wof:placetype":"venue"
},
  "geometry": {"coordinates":[4.511271,51.95837],"type":"Point"}
}