{
  "type": "Feature",
  "properties": {
    "addr:full":"Wilhelminastraat 8 Wemeldinge Zeeland 4424 BC",
    "addr:housenumber":"8",
    "addr:postcode":"4424 bc",
    "addr:street":"Wilhelminastraat",
    "iso:country":"NL",
    "sg:address":"Wilhelminastraat 8",
    "sg:city":"Wemeldinge",
    "sg:orig_category":"Begrafenisondernemers",
    "sg:phone":"+31 113 621 463",
    "sg:postcode":"4424 BC",
    "sg:province":"Zeeland",
    "wof:name":"Begrafenisonderneming J. Haverhoek",
    "wof:placetype":"venue"
},
  "geometry": {"coordinates":[3.995656,51.517677],"type":"Point"}
}