{
  "type": "Feature",
  "properties": {
    "addr:full":"Kennemerstrwg 506 Heiloo Noord-Holland 1851 NH",
    "addr:housenumber":"506",
    "addr:postcode":"1851 nh",
    "iso:country":"NL",
    "sg:address":"Kennemerstrwg 506",
    "sg:city":"Heiloo",
    "sg:classifiers":[
        {
            "category":"Food & Beverages",
            "subcategory":"Bakery",
            "type":"Retail Goods"
        }
    ],
    "sg:phone":"+31 72 533 1157",
    "sg:postcode":"1851 NH",
    "sg:province":"Noord-Holland",
    "sg:tags":[
        "brood",
        "en",
        "banket"
    ],
    "wof:name":"Kaandorp Bv",
    "wof:placetype":"venue"
},
  "geometry": {"coordinates":[4.713702,52.604191],"type":"Point"}
}