{
  "type": "Feature",
  "properties": {
    "addr:full":"Slochterstr 75 Sappemeer Groningen 9611 CN",
    "addr:housenumber":"75",
    "addr:postcode":"9611 cn",
    "addr:street":"Slochterstr",
    "iso:country":"NL",
    "sg:address":"Slochterstr 75",
    "sg:city":"Sappemeer",
    "sg:orig_category":"Sportverenigingen En Ontspannings- Verenigingen",
    "sg:phone":"+31 598 392 161",
    "sg:postcode":"9611 CN",
    "sg:province":"Groningen",
    "wof:name":"Dfs Sportver",
    "wof:placetype":"venue"
},
  "geometry": {"coordinates":[6.789749,53.166412],"type":"Point"}
}