{
  "type": "Feature",
  "properties": {
    "addr:full":"Vondelln 86 Beverwyk North Holland 1942 LL",
    "addr:housenumber":"86",
    "addr:postcode":"1942 ll",
    "addr:street":"Vondelln;North",
    "iso:country":"NL",
    "sg:address":"Vondelln 86",
    "sg:city":"Beverwyk",
    "sg:orig_category":"Bedrijfsopleidingen",
    "sg:phone":"+31 251 222 252",
    "sg:postcode":"1942 LL",
    "sg:province":"North Holland",
    "wof:name":"Eggermont",
    "wof:placetype":"venue"
},
  "geometry": {"coordinates":[4.645246,52.482559],"type":"Point"}
}