{
  "type": "Feature",
  "properties": {
    "addr:full":"Deventerpad 2 Almere Flevoland 1324 EE",
    "addr:housenumber":"2",
    "addr:postcode":"1324 ee",
    "addr:street":"Deventerpad;Flevoland",
    "iso:country":"NL",
    "sg:address":"Deventerpad 2",
    "sg:city":"Almere",
    "sg:classifiers":[
        {
            "category":"Fast Food",
            "type":"Food & Drink"
        }
    ],
    "sg:phone":"+31 36 533 0165",
    "sg:postcode":"1324 EE",
    "sg:province":"Flevoland",
    "sg:tags":[
        "afhaal",
        "restaurant"
    ],
    "wof:name":"Nile Sphinx",
    "wof:placetype":"venue"
},
  "geometry": {"coordinates":[5.214539,52.367844],"type":"Point"}
}