{
  "type": "Feature",
  "properties": {
    "addr:full":"Dissel 80 Barger Compascuum Provincie Drenthe 7884 PD",
    "addr:housenumber":"80",
    "addr:postcode":"7884 pd",
    "addr:street":"Dissel;Drenthe",
    "iso:country":"NL",
    "sg:address":"Dissel 80",
    "sg:city":"Barger Compascuum",
    "sg:orig_category":"Gebouwenafwerking, Renovaties And Reiniging",
    "sg:phone":"+31 591 349 569",
    "sg:postcode":"7884 PD",
    "sg:province":"Provincie Drenthe",
    "wof:name":"Kuik",
    "wof:placetype":"venue"
},
  "geometry": {"coordinates":[7.044045,52.7565],"type":"Point"}
}