{
  "type": "Feature",
  "properties": {
    "addr:full":"Colynpln 20 S Gravenhage Zuid-Holland 2555 HA",
    "addr:housenumber":"20;gravenhage",
    "addr:postcode":"2555 ha",
    "addr:street":"Colynpln;S",
    "iso:country":"NL",
    "sg:address":"Colynpln 20",
    "sg:city":"S Gravenhage",
    "sg:classifiers":[
        {
            "category":"Professional",
            "subcategory":"Accounting & Tax Preparation",
            "type":"Services"
        }
    ],
    "sg:phone":"+31 70 363 5881",
    "sg:postcode":"2555 HA",
    "sg:province":"Zuid-Holland",
    "sg:tags":[
        "accountant",
        "en",
        "-kantoren",
        "register-"
    ],
    "wof:name":"Maas",
    "wof:placetype":"venue"
},
  "geometry": {"coordinates":[4.2417,52.06638],"type":"Point"}
}