{
  "type": "Feature",
  "properties": {
    "addr:full":"Peelstr 150 Erica Provincie Drenthe 7887 TM",
    "addr:housenumber":"150",
    "addr:postcode":"7887 tm",
    "addr:street":"Erica Provincie Drenthe",
    "iso:country":"NL",
    "sg:address":"Peelstr 150",
    "sg:city":"Erica",
    "sg:orig_category":"Loonbedrijven",
    "sg:phone":"+31 591 301 495",
    "sg:postcode":"7887 TM",
    "sg:province":"Provincie Drenthe",
    "wof:name":"Oost",
    "wof:placetype":"venue"
},
  "geometry": {"coordinates":[6.920782,52.687824],"type":"Point"}
}