{
  "type": "Feature",
  "properties": {
    "iso:country":"NL",
    "sg:address":"Struisvogelstraat 1",
    "sg:city":"Gorinchem",
    "sg:classifiers":[
        {
            "category":"Education",
            "subcategory":"Preschool",
            "type":"Public Place"
        }
    ],
    "sg:phone":"+31 183 630 508",
    "sg:postcode":"4201 GJ",
    "sg:province":"Zuid-Holland",
    "sg:tags":[
        "kleuteronderwijs",
        "basis-"
    ],
    "wof:name":"Basisschool De Tweemaster",
    "wof:placetype":"venue"
},
  "geometry": {"coordinates":[4.97182,51.8298],"type":"Point"}
}