{
  "type": "Feature",
  "properties": {
    "iso:country":"NL",
    "sg:address":"Noordhoekring 46",
    "sg:city":"Tilburg",
    "sg:orig_category":"Psychotherapeuten",
    "sg:phone":"+31 6 14419452",
    "sg:postcode":"5038 GE",
    "sg:province":"Noord-Brabant",
    "sg:website":"http://www.therapeutencollectief.8m.com",
    "wof:name":"Praktijk Voor Dramatherapie",
    "wof:placetype":"venue"
},
  "geometry": {"coordinates":[5.078348,51.559669],"type":"Point"}
}