{
  "type": "Feature",
  "properties": {
    "addr:full":"Ribbeltsweg 18 Enschede NL.08 7514 EJ",
    "addr:housenumber":"18",
    "addr:postcode":"7514 ej",
    "addr:street":"Ribbeltsweg",
    "iso:country":"NL",
    "sg:address":"Ribbeltsweg 18",
    "sg:city":"Enschede",
    "sg:orig_category":"Huishoudapparatuur, Televisies And Radio'S",
    "sg:phone":"+31 53 435 7602",
    "sg:postcode":"7514 EJ",
    "sg:province":"NL.08",
    "wof:name":"Supersat",
    "wof:placetype":"venue"
},
  "geometry": {"coordinates":[6.909111,52.225079],"type":"Point"}
}