{
  "type": "Feature",
  "properties": {
    "addr:full":"Sumatrakd 197 Amsterdam Noord-Holland 1019 PK",
    "addr:housenumber":"197",
    "addr:postcode":"1019 pk",
    "iso:country":"NL",
    "sg:address":"Sumatrakd 197",
    "sg:city":"Amsterdam",
    "sg:orig_category":"Adviesbureaus Bedrijfsorganisatie",
    "sg:phone":"+31 20 419 3648",
    "sg:postcode":"1019 PK",
    "sg:province":"Noord-Holland",
    "wof:name":"Grotenhuis Mcs",
    "wof:placetype":"venue"
},
  "geometry": {"coordinates":[4.934603,52.377964],"type":"Point"}
}