{
  "type": "Feature",
  "properties": {
    "addr:full":"Heilooerdk 89 Alkmaar Noord-Holland 1814 LM",
    "addr:housenumber":"89",
    "addr:postcode":"1814 lm",
    "addr:street":"Heilooerdk",
    "iso:country":"NL",
    "sg:address":"Heilooerdk 89",
    "sg:city":"Alkmaar",
    "sg:classifiers":[
        {
            "category":"Manufacturing",
            "subcategory":"Textiles",
            "type":"Manufacturing & Wholesale Goods"
        }
    ],
    "sg:phone":"+31 72 511 2968",
    "sg:postcode":"1814 LM",
    "sg:province":"Noord-Holland",
    "sg:tags":[
        "polyester"
    ],
    "wof:name":"Rooy Bv Polyestergrondstoffen, Martin De",
    "wof:placetype":"venue"
},
  "geometry": {"coordinates":[4.744362,52.618931],"type":"Point"}
}