{
  "type": "Feature",
  "properties": {
    "iso:country":"NL",
    "sg:address":"Middenraai 65",
    "sg:city":"Nieuweroord",
    "sg:orig_category":"Goederenvervoer Over De Weg",
    "sg:phone":"+31 528 341 267",
    "sg:postcode":"7912 TH",
    "sg:province":"Drenthe",
    "wof:name":"J. Van De Weide & Zoon Bv",
    "wof:placetype":"venue"
},
  "geometry": {"coordinates":[6.566326,52.72937],"type":"Point"}
}