{
  "type": "Feature",
  "properties": {
    "addr:full":"N Parallelwg 18 Ede Gld Gelderland 6713 KN",
    "addr:housenumber":"18",
    "addr:postcode":"6713 kn",
    "addr:street":"N;Gld Gelderland",
    "iso:country":"NL",
    "sg:address":"N Parallelwg 18",
    "sg:city":"Ede Gld",
    "sg:classifiers":[
        {
            "category":"Retail",
            "subcategory":"Auto Repair",
            "type":"Services"
        }
    ],
    "sg:phone":"+31 318 630 902",
    "sg:postcode":"6713 KN",
    "sg:province":"Gelderland",
    "sg:tags":[
        "garage"
    ],
    "sg:website":"http://www.autojawes.nl",
    "wof:name":"Jawes",
    "wof:placetype":"venue"
},
  "geometry": {"coordinates":[5.667675,52.044979],"type":"Point"}
}