{
  "type": "Feature",
  "properties": {
    "addr:full":"Jachtlaan 13 Winschoten Groningen 9675 JA",
    "addr:housenumber":"13",
    "addr:postcode":"9675 ja",
    "addr:street":"Jachtlaan",
    "iso:country":"NL",
    "sg:address":"Jachtlaan 13",
    "sg:city":"Winschoten",
    "sg:classifiers":[
        {
            "category":"Fast Food",
            "type":"Food & Drink"
        }
    ],
    "sg:phone":"+31 597 417 549",
    "sg:postcode":"9675 JA",
    "sg:province":"Groningen",
    "sg:tags":[
        "afhaal",
        "restaurant"
    ],
    "wof:name":"Snackbar Noord",
    "wof:placetype":"venue"
},
  "geometry": {"coordinates":[7.032565,53.155895],"type":"Point"}
}