{
  "type": "Feature",
  "properties": {
    "iso:country":"NL",
    "sg:address":"J F Vlekkewg 12",
    "sg:city":"Tilburg",
    "sg:orig_category":"Bedrijfskleding",
    "sg:phone":"+31 13 590 0523",
    "sg:postcode":"5026 RJ",
    "sg:province":"North Brabant",
    "wof:name":"Lucon Bv",
    "wof:placetype":"venue"
},
  "geometry": {"coordinates":[5.060401,51.540901],"type":"Point"}
}