{
  "type": "Feature",
  "properties": {
    "addr:full":"Venneperhof 8 Nieuw Vennep North Holland 2151 AZ",
    "addr:housenumber":"8",
    "addr:postcode":"2151 az",
    "addr:street":"Venneperhof;Nieuw Vennep North",
    "iso:country":"NL",
    "sg:address":"Venneperhof 8",
    "sg:city":"Nieuw Vennep",
    "sg:orig_category":"Verzekeringen",
    "sg:phone":"+31 252 674 474",
    "sg:postcode":"2151 AZ",
    "sg:province":"North Holland",
    "wof:name":"Bottinga Financieel Diensten Centrum Bv",
    "wof:placetype":"venue"
},
  "geometry": {"coordinates":[4.63119,52.264103],"type":"Point"}
}