{
  "type": "Feature",
  "properties": {
    "addr:full":"Dorpstraat 8 'S Hertogenbosch North Brabant 5221 AH",
    "addr:housenumber":"8 ' s",
    "addr:postcode":"5221 ah",
    "addr:street":"Dorpstraat;Hertogenbosch",
    "iso:country":"NL",
    "sg:address":"Dorpstraat 8",
    "sg:city":"'S Hertogenbosch",
    "sg:orig_category":"Medische Apparatuur And Prothesen Fab",
    "sg:phone":"+31 73 631 2044",
    "sg:postcode":"5221 AH",
    "sg:province":"North Brabant",
    "wof:name":"Dkdent Tandtechnisch Laboratorium",
    "wof:placetype":"venue"
},
  "geometry": {"coordinates":[5.271376,51.720436],"type":"Point"}
}