{
  "type": "Feature",
  "properties": {
    "addr:full":"Zirkoon 14 Heerhugowaard Noord-Holland 1703 CS",
    "addr:housenumber":"14",
    "addr:postcode":"1703 cs",
    "addr:street":"Zirkoon",
    "iso:country":"NL",
    "sg:address":"Zirkoon 14",
    "sg:city":"Heerhugowaard",
    "sg:orig_category":"Film-, Tv- And Videoproductie",
    "sg:phone":"+31 72 572 7156",
    "sg:postcode":"1703 CS",
    "sg:province":"Noord-Holland",
    "wof:name":"Jos Baltus Produkties",
    "wof:placetype":"venue"
},
  "geometry": {"coordinates":[4.820661,52.659294],"type":"Point"}
}