{
  "type": "Feature",
  "properties": {
    "addr:full":"Lorentzkade 86 Haarlem Noord-Holland 2014 CB",
    "addr:housenumber":"86",
    "addr:postcode":"2014 cb",
    "addr:street":"Lorentzkade",
    "iso:country":"NL",
    "sg:address":"Lorentzkade 86",
    "sg:city":"Haarlem",
    "sg:orig_category":"Verzekeringen",
    "sg:phone":"+31 23 524 1763",
    "sg:postcode":"2014 CB",
    "sg:province":"Noord-Holland",
    "wof:name":"Assurantiekantoor Lorentz",
    "wof:placetype":"venue"
},
  "geometry": {"coordinates":[4.60983,52.370762],"type":"Point"}
}