{
  "type": "Feature",
  "properties": {
    "iso:country":"NL",
    "sg:address":"Hanzeweg 70",
    "sg:city":"Deventer",
    "sg:orig_category":"Technische Studies And Onderzoek",
    "sg:phone":"+31 570 631 116",
    "sg:postcode":"7418 AT",
    "sg:province":"NL.08",
    "wof:name":"Pw+B Environment",
    "wof:placetype":"venue"
},
  "geometry": {"coordinates":[6.18057,52.252949],"type":"Point"}
}