{
  "type": "Feature",
  "properties": {
    "addr:full":"Dkn Quodbachln 41 Kerkrade Limburg 6461 XP",
    "addr:housenumber":"41",
    "addr:postcode":"6461 xp",
    "iso:country":"NL",
    "sg:address":"Dkn Quodbachln 41",
    "sg:city":"Kerkrade",
    "sg:orig_category":"Adviesbureaus Bouwkunde",
    "sg:phone":"+31 45 545 7529",
    "sg:postcode":"6461 XP",
    "sg:province":"Limburg",
    "wof:name":"Huijnen",
    "wof:placetype":"venue"
},
  "geometry": {"coordinates":[6.059685,50.863773],"type":"Point"}
}