{
  "type": "Feature",
  "properties": {
    "iso:country":"NL",
    "sg:address":"Nieuwstraat 7",
    "sg:city":"Den Helder",
    "sg:orig_category":"Technische Studies And Onderzoek",
    "sg:phone":"+31 223 621 226",
    "sg:postcode":"1781 TE",
    "sg:province":"Noord-Holland",
    "wof:name":"M.A. De Vries Kompassteller",
    "wof:placetype":"venue"
},
  "geometry": {"coordinates":[4.772002,52.955444],"type":"Point"}
}