{
  "type": "Feature",
  "properties": {
    "addr:full":"Anjeliersstraat 131C Amsterdam Noord-Holland 1015 NE",
    "addr:housenumber":"131c;1015",
    "addr:postcode":"ne",
    "addr:street":"Anjeliersstraat",
    "iso:country":"NL",
    "sg:address":"Anjeliersstraat 131C",
    "sg:city":"Amsterdam",
    "sg:orig_category":"Fotostudio'S And Fotografen",
    "sg:phone":"+31 20 624 2019",
    "sg:postcode":"1015 NE",
    "sg:province":"Noord-Holland",
    "wof:name":"D. Blok",
    "wof:placetype":"venue"
},
  "geometry": {"coordinates":[4.88234,52.377399],"type":"Point"}
}