{
  "type": "Feature",
  "properties": {
    "iso:country":"NL",
    "sg:address":"Oost Zeedijk 6",
    "sg:city":"Colijnsplaat",
    "sg:orig_category":"Fruit And Groenten Gh",
    "sg:phone":"+31 113 695 285",
    "sg:postcode":"4486 PN",
    "sg:province":"Zeeland",
    "wof:name":"J.J. Lamse Bv",
    "wof:placetype":"venue"
},
  "geometry": {"coordinates":[3.852144,51.601048],"type":"Point"}
}