{
  "type": "Feature",
  "properties": {
    "iso:country":"NL",
    "sg:address":"Pinksterbloem 33",
    "sg:city":"Hardenberg",
    "sg:orig_category":"Keukens",
    "sg:phone":"+31 523 260 547",
    "sg:postcode":"7772 NK",
    "sg:province":"Overijssel",
    "wof:name":"Hakkers, H",
    "wof:placetype":"venue"
},
  "geometry": {"coordinates":[6.649432,52.5802],"type":"Point"}
}