{
  "type": "Feature",
  "properties": {
    "addr:full":"Zeilmakerstr 2 Katwyk Zh Zuid-Holland 2222 AA",
    "addr:housenumber":"2",
    "addr:postcode":"2222 aa",
    "addr:street":"Zeilmakerstr",
    "iso:country":"NL",
    "sg:address":"Zeilmakerstr 2",
    "sg:city":"Katwyk Zh",
    "sg:orig_category":"Juweliers",
    "sg:phone":"+31 71 402 7592",
    "sg:postcode":"2222 AA",
    "sg:province":"Zuid-Holland",
    "wof:name":"Zwart Bv, Juweliersshop V/D",
    "wof:placetype":"venue"
},
  "geometry": {"coordinates":[4.4331269264,52.2031021118],"type":"Point"}
}