{
  "type": "Feature",
  "properties": {
    "addr:full":"Schoolstr 24 Varsseveld Gelderland 7051 DC",
    "addr:housenumber":"24",
    "addr:postcode":"7051",
    "addr:street":"Schoolstr;Gelderland",
    "iso:country":"NL",
    "sg:address":"Schoolstr 24",
    "sg:city":"Varsseveld",
    "sg:orig_category":"Administratie- En Boekhoudkantoren",
    "sg:phone":"+31 315 241 085",
    "sg:postcode":"7051 DC",
    "sg:province":"Gelderland",
    "wof:name":"Hengeveld, H W",
    "wof:placetype":"venue"
},
  "geometry": {"coordinates":[6.465428,51.9445],"type":"Point"}
}