{
  "type": "Feature",
  "properties": {
    "addr:full":"Singel 95 Amsterdam North Holland 1012 VG",
    "addr:housenumber":"95",
    "addr:postcode":"1012 vg",
    "addr:street":"Singel",
    "iso:country":"NL",
    "sg:address":"Singel 95",
    "sg:city":"Amsterdam",
    "sg:orig_category":"Psychotherapeuten",
    "sg:phone":"+31 20 623 6461",
    "sg:postcode":"1012 VG",
    "sg:province":"North Holland",
    "wof:name":"Werkplaats",
    "wof:placetype":"venue"
},
  "geometry": {"coordinates":[4.891471,52.375919],"type":"Point"}
}