{
  "type": "Feature",
  "properties": {
    "addr:full":"Koningstr 70 Arnhem Gelderland 6811 DJ",
    "addr:housenumber":"70",
    "addr:postcode":"6811 dj",
    "addr:street":"Koningstr",
    "iso:country":"NL",
    "sg:address":"Koningstr 70",
    "sg:city":"Arnhem",
    "sg:orig_category":"Gordijnen",
    "sg:phone":"+31 26 442 1755",
    "sg:postcode":"6811 DJ",
    "sg:province":"Gelderland",
    "wof:name":"Rido Gordijnen",
    "wof:placetype":"venue"
},
  "geometry": {"coordinates":[5.909792,51.981178],"type":"Point"}
}