{
  "type": "Feature",
  "properties": {
    "iso:country":"NL",
    "sg:address":"Kormelinkwg 116",
    "sg:city":"Amsterdam Zuidoost",
    "sg:orig_category":"Video - Faciliteiten En Producties",
    "sg:phone":"+31 20 690 3181",
    "sg:postcode":"1104 NT",
    "sg:province":"North Holland",
    "sg:website":"http://www.geocities.com/juandegraaf",
    "wof:name":"Graaf, Juan De",
    "wof:placetype":"venue"
},
  "geometry": {"coordinates":[4.970896,52.316128],"type":"Point"}
}