{
  "type": "Feature",
  "properties": {
    "iso:country":"NL",
    "sg:address":"Promenade 201",
    "sg:city":"Zoetermeer",
    "sg:orig_category":"Baby- And Kinderkleding",
    "sg:phone":"+31 79 341 4689",
    "sg:postcode":"2711 AP",
    "sg:province":"Zuid-Holland",
    "wof:name":"Cool Cat Junior",
    "wof:placetype":"venue"
},
  "geometry": {"coordinates":[4.490632,52.061424],"type":"Point"}
}