{
  "type": "Feature",
  "properties": {
    "iso:country":"NL",
    "sg:address":"Oostkant 2",
    "sg:city":"Terneuzen",
    "sg:orig_category":"Verplichte Sociale Verzekeringen",
    "sg:phone":"+31 115 677 700",
    "sg:postcode":"4531 HA",
    "sg:province":"Zeeland",
    "wof:name":"Oz Zorgverzekeringen",
    "wof:placetype":"venue"
},
  "geometry": {"coordinates":[3.831136,51.33614],"type":"Point"}
}