{
  "type": "Feature",
  "properties": {
    "addr:full":"Boezemsingel 23 Rotterdam Zuid-Holland 3034 EB",
    "addr:housenumber":"23",
    "addr:postcode":"3034 eb",
    "addr:street":"Boezemsingel",
    "iso:country":"NL",
    "sg:address":"Boezemsingel 23",
    "sg:city":"Rotterdam",
    "sg:orig_category":"Marktonderzoekbureaus",
    "sg:phone":"+31 10 467 6429",
    "sg:postcode":"3034 EB",
    "sg:province":"Zuid-Holland",
    "wof:name":"Newmarket Advertising Bv",
    "wof:placetype":"venue"
},
  "geometry": {"coordinates":[4.494026,51.93029],"type":"Point"}
}