{
  "type": "Feature",
  "properties": {
    "iso:country":"NL",
    "sg:address":"Lekdijk 35",
    "sg:city":"Nieuw Lekkerland",
    "sg:orig_category":"Metaalwerken",
    "sg:phone":"+31 184 683 646",
    "sg:postcode":"2957 CB",
    "sg:province":"Zuid-Holland",
    "wof:name":"De Reuver Afbouw Bv",
    "wof:placetype":"venue"
},
  "geometry": {"coordinates":[4.708149,51.894382],"type":"Point"}
}