{
  "type": "Feature",
  "properties": {
    "addr:full":"Boswachtersveld 313 Apeldoorn Gelderland 7327 JT",
    "addr:housenumber":"313",
    "addr:postcode":"7327 jt",
    "addr:street":"Boswachtersveld;Gelderland",
    "iso:country":"NL",
    "sg:address":"Boswachtersveld 313",
    "sg:city":"Apeldoorn",
    "sg:orig_category":"Adviesbureaus",
    "sg:phone":"+31 6 21512596",
    "sg:postcode":"7327 JT",
    "sg:province":"Gelderland",
    "wof:name":"Maten, De",
    "wof:placetype":"venue"
},
  "geometry": {"coordinates":[5.996901,52.184196],"type":"Point"}
}