{
  "type": "Feature",
  "properties": {
    "addr:full":"Kruittorenstr 15 Tholen Zeeland 4691 EN",
    "addr:housenumber":"15",
    "addr:postcode":"4691 en",
    "addr:street":"Kruittorenstr",
    "iso:country":"NL",
    "sg:address":"Kruittorenstr 15",
    "sg:city":"Tholen",
    "sg:orig_category":"Adviesbureaus Bedrijfsorganisatie",
    "sg:phone":"+31 6 22555385",
    "sg:postcode":"4691 EN",
    "sg:province":"Zeeland",
    "wof:name":"Liere, Van",
    "wof:placetype":"venue"
},
  "geometry": {"coordinates":[4.223643,51.533752],"type":"Point"}
}