{
  "type": "Feature",
  "properties": {
    "addr:full":"Hollandsch Diep 7173 Capelle Ad Yssel Zuid-Holland 2904 EP",
    "addr:housenumber":"7173;2904",
    "addr:postcode":"ep",
    "addr:street":"Hollandsch Diep",
    "iso:country":"NL",
    "sg:address":"Hollandsch Diep 7173",
    "sg:city":"Capelle Ad Yssel",
    "sg:orig_category":"Verzekeringen - Verzekeringskantoren",
    "sg:phone":"+31 10 450 7766",
    "sg:postcode":"2904 EP",
    "sg:province":"Zuid-Holland",
    "wof:name":"Otte Bv",
    "wof:placetype":"venue"
},
  "geometry": {"coordinates":[4.60287,51.936932],"type":"Point"}
}