{
  "type": "Feature",
  "properties": {
    "addr:full":"Terheijdenseweg 152 Breda Noord-Brabant 4816 AB",
    "addr:housenumber":"152",
    "addr:postcode":"4816 ab",
    "addr:street":"Terheijdenseweg",
    "iso:country":"NL",
    "sg:address":"Terheijdenseweg 152",
    "sg:city":"Breda",
    "sg:classifiers":[
        {
            "category":"Professional",
            "subcategory":"Accounting & Tax Preparation",
            "type":"Services"
        }
    ],
    "sg:phone":"+31 76 587 3989",
    "sg:postcode":"4816 AB",
    "sg:province":"Noord-Brabant",
    "sg:tags":[
        "accountant"
    ],
    "wof:name":"Administratiekant Mfj Hermans",
    "wof:placetype":"venue"
},
  "geometry": {"coordinates":[4.77845,51.601395],"type":"Point"}
}