{
  "type": "Feature",
  "properties": {
    "addr:full":"Postbus 28122 Hoogland Utrecht 3828 ZJ",
    "addr:postcode":"28122;3828 zj",
    "addr:street":"Postbus",
    "iso:country":"NL",
    "sg:address":"Postbus 28122",
    "sg:city":"Hoogland",
    "sg:orig_category":"Kantoor- En Secretariaatsservice",
    "sg:phone":"+31 6 50238351",
    "sg:postcode":"3828 ZJ",
    "sg:province":"Utrecht",
    "sg:website":"http://www.querico.nl",
    "wof:name":"Querico",
    "wof:placetype":"venue"
},
  "geometry": {"coordinates":[5.3759331703,52.186630249],"type":"Point"}
}