{
  "type": "Feature",
  "properties": {
    "iso:country":"NL",
    "sg:address":"Stranwei 7",
    "sg:city":"Makkum Fr",
    "sg:orig_category":"Pleziervaartuigen And Reparatie",
    "sg:phone":"+31 515 232 528",
    "sg:postcode":"8754 HA",
    "sg:province":"Friesland",
    "wof:name":"Bloemsma Aluminiumbouw Vof",
    "wof:placetype":"venue"
},
  "geometry": {"coordinates":[5.400318,53.051109],"type":"Point"}
}