{
  "type": "Feature",
  "properties": {
    "iso:country":"NL",
    "sg:address":"Oude Markt 25",
    "sg:city":"Stadskanaal",
    "sg:orig_category":"Adviesbureaus Beveiliging",
    "sg:phone":"+31 599 652 548",
    "sg:postcode":"9501 VK",
    "sg:province":"Groningen",
    "wof:name":"Schoonebeek, Fa",
    "wof:placetype":"venue"
},
  "geometry": {"coordinates":[6.954366,52.987778],"type":"Point"}
}