{
  "type": "Feature",
  "properties": {
    "addr:full":"Dronkelaarseweg 12 Terschuur Gelderland 3784 WB",
    "addr:housenumber":"12",
    "addr:postcode":"3784 wb",
    "addr:street":"Dronkelaarseweg;Gelderland",
    "iso:country":"NL",
    "sg:address":"Dronkelaarseweg 12",
    "sg:city":"Terschuur",
    "sg:orig_category":"Huizensloop And Bouwrijp Maken",
    "sg:phone":"+31 342 422 579",
    "sg:postcode":"3784 WB",
    "sg:province":"Gelderland",
    "wof:name":"H. Van Dijk Grondwerk Verhuur",
    "wof:placetype":"venue"
},
  "geometry": {"coordinates":[5.546355,52.156143],"type":"Point"}
}