{
  "type": "Feature",
  "properties": {
    "iso:country":"NL",
    "sg:address":"Insulindewg 476",
    "sg:city":"Amsterdam",
    "sg:orig_category":"Artsen - Huisartsen",
    "sg:phone":"+31 20 665 9828",
    "sg:postcode":"1094 MH",
    "sg:province":"North Holland",
    "wof:name":"Scheeve, E",
    "wof:placetype":"venue"
},
  "geometry": {"coordinates":[4.939106,52.361359],"type":"Point"}
}