{
  "type": "Feature",
  "properties": {
    "addr:full":"Ambachtsstraat 15 Terneuzen Zeeland 4538 AV",
    "addr:housenumber":"15",
    "addr:postcode":"4538 av",
    "addr:street":"Ambachtsstraat",
    "iso:country":"NL",
    "sg:address":"Ambachtsstraat 15",
    "sg:city":"Terneuzen",
    "sg:orig_category":"Koffers And Tassen Fab",
    "sg:phone":"+31 115 648 754",
    "sg:postcode":"4538 AV",
    "sg:province":"Zeeland",
    "wof:name":"Yasem",
    "wof:placetype":"venue"
},
  "geometry": {"coordinates":[3.849882,51.307934],"type":"Point"}
}