{
  "type": "Feature",
  "properties": {
    "addr:full":"Boxhofstede 4 Vaassen Gelderland 8171 KA",
    "addr:housenumber":"4",
    "addr:postcode":"8171 ka",
    "addr:street":"Boxhofstede;Gelderland",
    "iso:country":"NL",
    "sg:address":"Boxhofstede 4",
    "sg:city":"Vaassen",
    "sg:orig_category":"Betonboringen",
    "sg:phone":"+31 578 576 608",
    "sg:postcode":"8171 KA",
    "sg:province":"Gelderland",
    "sg:website":"http://www.sjar?.nl",
    "wof:name":"Sjar?",
    "wof:placetype":"venue"
},
  "geometry": {"coordinates":[5.975954,52.288811],"type":"Point"}
}