{
  "type": "Feature",
  "properties": {
    "iso:country":"NL",
    "sg:address":"Sloelaan 41",
    "sg:city":"Terneuzen",
    "sg:classifiers":[
        {
            "category":"Education",
            "subcategory":"Preschool",
            "type":"Public Place"
        }
    ],
    "sg:phone":"+31 115 696 768",
    "sg:postcode":"4535 ED",
    "sg:province":"Zeeland",
    "sg:tags":[
        "kleuteronderwijs",
        "basis-"
    ],
    "wof:name":"Obs De Meerpaal",
    "wof:placetype":"venue"
},
  "geometry": {"coordinates":[3.855466,51.31311],"type":"Point"}
}