{
  "type": "Feature",
  "properties": {
    "addr:full":"De Messenmaker 8 Veldhoven North Brabant 5506 CG",
    "addr:housenumber":"8",
    "addr:postcode":"5506 cg",
    "addr:street":"De Messenmaker",
    "iso:country":"NL",
    "sg:address":"De Messenmaker 8",
    "sg:city":"Veldhoven",
    "sg:orig_category":"Kinderopvang Behalve Thuis",
    "sg:phone":"+31 40 254 9770",
    "sg:postcode":"5506 CG",
    "sg:province":"North Brabant",
    "wof:name":"Gastoudercentrale Kinderopvang Humanitas",
    "wof:placetype":"venue"
},
  "geometry": {"coordinates":[5.387235,51.416969],"type":"Point"}
}