{
  "type": "Feature",
  "properties": {
    "addr:full":"Pr Ireneln 1 Ysselstein Ut Utrecht 3402 CE",
    "addr:housenumber":"1",
    "addr:postcode":"3402 ce",
    "addr:street":"Ysselstein",
    "iso:country":"NL",
    "sg:address":"Pr Ireneln 1",
    "sg:city":"Ysselstein Ut",
    "sg:orig_category":"Afzuiginstallaties",
    "sg:phone":"+31 30 687 4167",
    "sg:postcode":"3402 CE",
    "sg:province":"Utrecht",
    "wof:name":"Keller Lufttechniek",
    "wof:placetype":"venue"
},
  "geometry": {"coordinates":[5.0281,52.02663],"type":"Point"}
}