{
  "type": "Feature",
  "properties": {
    "addr:full":"Ringdk 10 Ridderkerk Zuid-Holland 2981 EW",
    "addr:housenumber":"10",
    "addr:postcode":"2981 ew",
    "addr:street":"Ringdk",
    "iso:country":"NL",
    "sg:address":"Ringdk 10",
    "sg:city":"Ridderkerk",
    "sg:orig_category":"Antiquiteiten",
    "sg:phone":"+31 180 429 142",
    "sg:postcode":"2981 EW",
    "sg:province":"Zuid-Holland",
    "wof:name":"Roode Deur, De",
    "wof:placetype":"venue"
},
  "geometry": {"coordinates":[4.603537,51.870846],"type":"Point"}
}