{
  "type": "Feature",
  "properties": {
    "addr:full":"Dorpsstr 658 Noord Scharwoude North Holland 1723 HL",
    "addr:housenumber":"658",
    "addr:postcode":"1723 hl",
    "iso:country":"NL",
    "sg:address":"Dorpsstr 658",
    "sg:city":"Noord Scharwoude",
    "sg:orig_category":"Elektronica - Ontwikkeling En Groothandel",
    "sg:phone":"+31 226 315 151",
    "sg:postcode":"1723 HL",
    "sg:province":"North Holland",
    "wof:name":"Thor",
    "wof:placetype":"venue"
},
  "geometry": {"coordinates":[4.811012,52.705399],"type":"Point"}
}