{
  "type": "Feature",
  "properties": {
    "addr:full":"Waterhoenhof 8 Purmerend Noord-Holland 1444 VL",
    "addr:housenumber":"8",
    "addr:postcode":"1444 vl",
    "addr:street":"Waterhoenhof",
    "iso:country":"NL",
    "sg:address":"Waterhoenhof 8",
    "sg:city":"Purmerend",
    "sg:orig_category":"Administratie- En Boekhoudkantoren",
    "sg:phone":"+31 299 425 125",
    "sg:postcode":"1444 VL",
    "sg:province":"Noord-Holland",
    "wof:name":"Hazelhoff, E L",
    "wof:placetype":"venue"
},
  "geometry": {"coordinates":[4.959556,52.52113],"type":"Point"}
}