{
  "type": "Feature",
  "properties": {
    "iso:country":"NL",
    "sg:address":"De Mors 22",
    "sg:city":"Bornerbroek",
    "sg:orig_category":"Daken And Skeletbouw",
    "sg:phone":"+31 74 384 1715",
    "sg:postcode":"7627 MA",
    "sg:province":"Overijssel",
    "wof:name":"B. Westen Installatiewerken",
    "wof:placetype":"venue"
},
  "geometry": {"coordinates":[6.656912,52.310673],"type":"Point"}
}