{
  "type": "Feature",
  "properties": {
    "addr:full":"Saffierstraat 14 Hengelo Ov NL.08 7554 TG",
    "addr:housenumber":"14;7554",
    "addr:postcode":"tg",
    "addr:street":"Saffierstraat;Ov",
    "iso:country":"NL",
    "sg:address":"Saffierstraat 14",
    "sg:city":"Hengelo Ov",
    "sg:orig_category":"Wegen And Sportterreinen",
    "sg:phone":"+31 74 243 4333",
    "sg:postcode":"7554 TG",
    "sg:province":"NL.08",
    "wof:name":"Hbg Civiel Bv",
    "wof:placetype":"venue"
},
  "geometry": {"coordinates":[6.7742562294,52.2431983948],"type":"Point"}
}