{
  "type": "Feature",
  "properties": {
    "iso:country":"NL",
    "sg:address":"De Kempen 4",
    "sg:city":"Budel",
    "sg:orig_category":"Kabels",
    "sg:phone":"+31 495 499 049",
    "sg:postcode":"6021 PZ",
    "sg:province":"Noord-Brabant",
    "wof:name":"Helukabel Bv",
    "wof:placetype":"venue"
},
  "geometry": {"coordinates":[5.5702600479,51.2705535889],"type":"Point"}
}