{
  "type": "Feature",
  "properties": {
    "addr:full":"De Kempen 4 Budel Noord-Brabant 6021 PZ",
    "addr:housenumber":"4",
    "addr:postcode":"6021 pz",
    "addr:street":"De Kempen",
    "iso:country":"NL",
    "sg:address":"De Kempen 4",
    "sg:city":"Budel",
    "sg:orig_category":"Kabels",
    "sg:phone":"+31 495 499 049",
    "sg:postcode":"6021 PZ",
    "sg:province":"Noord-Brabant",
    "wof:name":"Helukabel Bv",
    "wof:placetype":"venue"
},
  "geometry": {"coordinates":[5.5702600479,51.2705535889],"type":"Point"}
}