{
  "type": "Feature",
  "properties": {
    "addr:full":"Kortlandstraat 27 Nieuwerkerk Ad Ijssel Zuid-Holland 2911 BG",
    "addr:housenumber":"27",
    "addr:postcode":"ijssel;2911",
    "addr:street":"Kortlandstraat",
    "iso:country":"NL",
    "sg:address":"Kortlandstraat 27",
    "sg:city":"Nieuwerkerk Ad Ijssel",
    "sg:orig_category":"Bloemen And Planten",
    "sg:phone":"+31 180 320 816",
    "sg:postcode":"2911 BG",
    "sg:province":"Zuid-Holland",
    "wof:name":"J.A. De Hoog",
    "wof:placetype":"venue"
},
  "geometry": {"coordinates":[4.62624,51.962994],"type":"Point"}
}