{
  "type": "Feature",
  "properties": {
    "iso:country":"NL",
    "sg:address":"Albert Cuijpstr 92",
    "sg:city":"Amsterdam",
    "sg:orig_category":"Koffie- En Theehuizen",
    "sg:phone":"+31 20 671 1505",
    "sg:postcode":"1072 CX",
    "sg:province":"North Holland",
    "wof:name":"Cuyp, De",
    "wof:placetype":"venue"
},
  "geometry": {"coordinates":[4.89117,52.355053],"type":"Point"}
}