{
  "type": "Feature",
  "properties": {
    "addr:full":"De Zandkuil 7 Ymuiden Noord-Holland 1974 RG",
    "addr:housenumber":"7",
    "addr:postcode":"1974 rg",
    "addr:street":"De Zandkuil",
    "iso:country":"NL",
    "sg:address":"De Zandkuil 7",
    "sg:city":"Ymuiden",
    "sg:orig_category":"Lasbedrijven",
    "sg:phone":"+31 255 515 126",
    "sg:postcode":"1974 RG",
    "sg:province":"Noord-Holland",
    "wof:name":"Gorter",
    "wof:placetype":"venue"
},
  "geometry": {"coordinates":[4.593851,52.450321],"type":"Point"}
}