{
  "type": "Feature",
  "properties": {
    "addr:full":"Grt Wade 21K Nieuwegein Utrecht 3439 NX",
    "addr:housenumber":"21k",
    "addr:postcode":"3439 nx",
    "addr:street":"Wade",
    "iso:country":"NL",
    "sg:address":"Grt Wade 21K",
    "sg:city":"Nieuwegein",
    "sg:orig_category":"Muziekinstrumenten En Bladmuziek",
    "sg:phone":"+31 30 267 0711",
    "sg:postcode":"3439 NX",
    "sg:province":"Utrecht",
    "wof:name":"Protone",
    "wof:placetype":"venue"
},
  "geometry": {"coordinates":[5.112533,52.048363],"type":"Point"}
}