{
  "type": "Feature",
  "properties": {
    "iso:country":"NL",
    "sg:address":"Haarlemmerweg 337",
    "sg:city":"Amsterdam",
    "sg:orig_category":"Metaalwerken",
    "sg:phone":"+31 20 688 1000",
    "sg:postcode":"1051 LH",
    "sg:province":"Noord-Holland",
    "wof:name":"Carpet Land",
    "wof:placetype":"venue"
},
  "geometry": {"coordinates":[4.86298,52.385151],"type":"Point"}
}