{
  "type": "Feature",
  "properties": {
    "iso:country":"NL",
    "sg:address":"De Moesmate 7",
    "sg:city":"Zutphen",
    "sg:orig_category":"Adviesbureaus",
    "sg:phone":"+31 575 570 319",
    "sg:postcode":"7206 AC",
    "sg:province":"Gelderland",
    "wof:name":"Ask",
    "wof:placetype":"venue"
},
  "geometry": {"coordinates":[6.208895,52.124271],"type":"Point"}
}