{
  "type": "Feature",
  "properties": {
    "addr:full":"Adelheidstr 83 S Gravenhage South Holland 2595 EC",
    "addr:housenumber":"83",
    "addr:postcode":"2595 ec",
    "addr:street":"Adelheidstr;S Gravenhage",
    "iso:country":"NL",
    "sg:address":"Adelheidstr 83",
    "sg:city":"S Gravenhage",
    "sg:orig_category":"Webdesign Bureaus",
    "sg:phone":"+31 70 305 0304",
    "sg:postcode":"2595 EC",
    "sg:province":"South Holland",
    "sg:website":"http://www.web2publish.com",
    "wof:name":"Web2Publish",
    "wof:placetype":"venue"
},
  "geometry": {"coordinates":[4.3350701332,52.0814208984],"type":"Point"}
}