{
  "type": "Feature",
  "properties": {
    "iso:country":"NL",
    "sg:address":"Textielwg 24",
    "sg:city":"Amersfoort",
    "sg:classifiers":[
        {
            "category":"Manufacturing",
            "subcategory":"Electronics",
            "type":"Manufacturing & Wholesale Goods"
        }
    ],
    "sg:phone":"+31 33 495 1115",
    "sg:postcode":"3812 RV",
    "sg:province":"Utrecht",
    "sg:tags":[
        "en",
        "laser",
        "lasertechniek"
    ],
    "sg:website":"http://www.abclaser.com",
    "wof:name":"Abc Bv",
    "wof:placetype":"venue"
},
  "geometry": {"coordinates":[5.367284,52.165359],"type":"Point"}
}