{
  "type": "Feature",
  "properties": {
    "iso:country":"NL",
    "sg:address":"Veerpolder 32",
    "sg:city":"Warmond",
    "sg:orig_category":"Houtwaren - Fabrieken En Groothandel",
    "sg:phone":"+31 71 301 0200",
    "sg:postcode":"2361 KW",
    "sg:province":"South Holland",
    "wof:name":"Dekker Warmond Bv",
    "wof:placetype":"venue"
},
  "geometry": {"coordinates":[4.501988,52.189407],"type":"Point"}
}