{
  "type": "Feature",
  "properties": {
    "iso:country":"NL",
    "sg:address":"Schubertlaan 8",
    "sg:city":"Hoogezand",
    "sg:orig_category":"Technische Studies And Onderzoek",
    "sg:phone":"+31 598 325 558",
    "sg:postcode":"9603 AX",
    "sg:province":"Groningen",
    "wof:name":"Up To Date Bv",
    "wof:placetype":"venue"
},
  "geometry": {"coordinates":[6.76094,53.158657],"type":"Point"}
}