{
  "type": "Feature",
  "properties": {
    "iso:country":"NL",
    "sg:address":"Veilingkade 7",
    "sg:city":"Breda",
    "sg:orig_category":"Beveiligingsdiensten And Bewakingsbedrijven",
    "sg:phone":"+31 76 578 0420",
    "sg:postcode":"4815 HC",
    "sg:province":"Noord-Brabant",
    "wof:name":"Gom Schoonhouden Bv",
    "wof:placetype":"venue"
},
  "geometry": {"coordinates":[4.766605,51.598991],"type":"Point"}
}