{
  "type": "Feature",
  "properties": {
    "iso:country":"NL",
    "sg:address":"Burgemeester Wijnenstr 30",
    "sg:city":"Asten",
    "sg:classifiers":[
        {
            "category":"Retail",
            "subcategory":"Photofinishing",
            "type":"Services"
        }
    ],
    "sg:phone":"+31 493 692 541",
    "sg:postcode":"5721 AJ",
    "sg:province":"North Brabant",
    "sg:tags":[
        "foto",
        "film"
    ],
    "wof:name":"Expert Asten Bv",
    "wof:placetype":"venue"
},
  "geometry": {"coordinates":[5.743951,51.404957],"type":"Point"}
}