{
  "type": "Feature",
  "properties": {
    "addr:full":"Wijk 2 66 Urk Flevoland 8321 ES",
    "addr:housenumber":"66",
    "addr:postcode":"8321 es",
    "addr:street":"Wijk 2;Flevoland",
    "iso:country":"NL",
    "sg:address":"Wijk 2 66",
    "sg:city":"Urk",
    "sg:orig_category":"Cafetaria'S",
    "sg:phone":"+31 527 682 356",
    "sg:postcode":"8321 ES",
    "sg:province":"Flevoland",
    "wof:name":"Ommelebommelestien, De",
    "wof:placetype":"venue"
},
  "geometry": {"coordinates":[5.592915,52.660725],"type":"Point"}
}