{
  "type": "Feature",
  "properties": {
    "addr:full":"Ravelyn 1 Emmen Provincie Drenthe 7823 TA",
    "addr:housenumber":"1",
    "addr:postcode":"7823 ta",
    "addr:street":"Ravelyn;Provincie Drenthe",
    "iso:country":"NL",
    "sg:address":"Ravelyn 1",
    "sg:city":"Emmen",
    "sg:orig_category":"Lasbedrijven",
    "sg:phone":"+31 591 625 007",
    "sg:postcode":"7823 TA",
    "sg:province":"Provincie Drenthe",
    "wof:name":"Santing, A Z",
    "wof:placetype":"venue"
},
  "geometry": {"coordinates":[6.931918,52.796307],"type":"Point"}
}