{
  "type": "Feature",
  "properties": {
    "addr:full":"Elvis Presleystraat 36 Almere Flevoland 1311 HS",
    "addr:housenumber":"36",
    "addr:postcode":"1311 hs",
    "addr:street":"Elvis Presleystraat;Flevoland",
    "iso:country":"NL",
    "sg:address":"Elvis Presleystraat 36",
    "sg:city":"Almere",
    "sg:orig_category":"Elektronische Bedrijfsinstallaties",
    "sg:phone":"+31 36 536 7332",
    "sg:postcode":"1311 HS",
    "sg:province":"Flevoland",
    "wof:name":"Provision Security",
    "wof:placetype":"venue"
},
  "geometry": {"coordinates":[5.174943,52.367344],"type":"Point"}
}