{
  "type": "Feature",
  "properties": {
    "addr:full":"Voorstraat 246 Dordrecht Zuid-Holland 3311 ET",
    "addr:housenumber":"246",
    "addr:postcode":"3311 et",
    "addr:street":"Voorstraat",
    "iso:country":"NL",
    "sg:address":"Voorstraat 246",
    "sg:city":"Dordrecht",
    "sg:orig_category":"Meubelzaken, Woning- And Keukeninrichting",
    "sg:phone":"+31 78 648 9748",
    "sg:postcode":"3311 ET",
    "sg:province":"Zuid-Holland",
    "wof:name":"Interessant",
    "wof:placetype":"venue"
},
  "geometry": {"coordinates":[4.668148,51.815117],"type":"Point"}
}