{
  "type": "Feature",
  "properties": {
    "addr:full":"Kl Berg 21 Eindhoven North Brabant 5611 JS",
    "addr:housenumber":"21",
    "addr:postcode":"5611 js",
    "addr:street":"Kl Berg",
    "iso:country":"NL",
    "sg:address":"Kl Berg 21",
    "sg:city":"Eindhoven",
    "sg:orig_category":"Balletartikelen",
    "sg:phone":"+31 40 245 5673",
    "sg:postcode":"5611 JS",
    "sg:province":"North Brabant",
    "wof:name":"Le Papillon",
    "wof:placetype":"venue"
},
  "geometry": {"coordinates":[5.476411,51.436707],"type":"Point"}
}