{
  "type": "Feature",
  "properties": {
    "addr:full":"Neonwg 30 Amersfoort Utrecht 3812 RH",
    "addr:housenumber":"30",
    "addr:postcode":"3812 rh",
    "addr:street":"Neonwg",
    "iso:country":"NL",
    "sg:address":"Neonwg 30",
    "sg:city":"Amersfoort",
    "sg:orig_category":"Waterbehandeling En Waterzuiverings- Systemen",
    "sg:phone":"+31 33 422 0788",
    "sg:postcode":"3812 RH",
    "sg:province":"Utrecht",
    "wof:name":"Rioolwaterzuivering Amersfoort",
    "wof:placetype":"venue"
},
  "geometry": {"coordinates":[5.3524971008,52.1725959778],"type":"Point"}
}