{
  "type": "Feature",
  "properties": {
    "iso:country":"NL",
    "sg:address":"Deventerstraat 211",
    "sg:city":"Apeldoorn",
    "sg:orig_category":"Bloemen And Planten",
    "sg:phone":"+31 55 366 4386",
    "sg:postcode":"7322 RE",
    "sg:province":"Gelderland",
    "wof:name":"Bloemenkwekerij Buitenhuis",
    "wof:placetype":"venue"
},
  "geometry": {"coordinates":[5.991451,52.215958],"type":"Point"}
}