{
  "type": "Feature",
  "properties": {
    "addr:full":"Frambozenstraat 74 'S Gravenhage South Holland 2564 XN",
    "addr:housenumber":"74",
    "addr:postcode":"2564 xn",
    "addr:street":"Frambozenstraat;' S Gravenhage",
    "iso:country":"NL",
    "sg:address":"Frambozenstraat 74",
    "sg:city":"'S Gravenhage",
    "sg:orig_category":"Kappers",
    "sg:phone":"+31 70 325 5574",
    "sg:postcode":"2564 XN",
    "sg:province":"South Holland",
    "wof:name":"Twins Hair Styling",
    "wof:placetype":"venue"
},
  "geometry": {"coordinates":[4.255114,52.069756],"type":"Point"}
}