{
  "type": "Feature",
  "properties": {
    "addr:full":"Douwes Dekkerstraat 24Bg Amsterdam North Holland 1053 SX",
    "addr:housenumber":"24bg",
    "addr:postcode":"1053 sx",
    "addr:street":"Douwes Dekkerstraat",
    "iso:country":"NL",
    "sg:address":"Douwes Dekkerstraat 24Bg",
    "sg:city":"Amsterdam",
    "sg:orig_category":"Visspeciaalzaken",
    "sg:phone":"+31 20 412 0515",
    "sg:postcode":"1053 SX",
    "sg:province":"North Holland",
    "wof:name":"Viswinkel Mediterranee",
    "wof:placetype":"venue"
},
  "geometry": {"coordinates":[4.865816,52.368526],"type":"Point"}
}