{
  "type": "Feature",
  "properties": {
    "addr:full":"Weeresteinstr 26 Hillegom North Holland 2181 GA",
    "addr:housenumber":"26",
    "addr:postcode":"2181 ga",
    "addr:street":"Weeresteinstr",
    "iso:country":"NL",
    "sg:address":"Weeresteinstr 26",
    "sg:city":"Hillegom",
    "sg:orig_category":"Verzekeringen - Verzekeringskantoren",
    "sg:phone":"+31 252 521 819",
    "sg:postcode":"2181 GA",
    "sg:province":"North Holland",
    "wof:name":"Cosman En Van Norden",
    "wof:placetype":"venue"
},
  "geometry": {"coordinates":[4.582038,52.300083],"type":"Point"}
}