{
  "type": "Feature",
  "properties": {
    "addr:full":"Klm Laan 28 Hoogerheide Noord-Brabant 4631 JW",
    "addr:housenumber":"28",
    "addr:postcode":"4631 jw",
    "addr:street":"Klm Laan",
    "iso:country":"NL",
    "sg:address":"Klm Laan 28",
    "sg:city":"Hoogerheide",
    "sg:orig_category":"Dierenspeciaalzaken",
    "sg:phone":"+31 164 620 207",
    "sg:postcode":"4631 JW",
    "sg:province":"Noord-Brabant",
    "wof:name":"Dierenspeciaalzaak Gabber",
    "wof:placetype":"venue"
},
  "geometry": {"coordinates":[4.328845,51.426292],"type":"Point"}
}