{
  "type": "Feature",
  "properties": {
    "addr:full":"Gemeenteweg 62 Staphorst Overijssel 7951 CP",
    "addr:housenumber":"62",
    "addr:postcode":"7951 cp",
    "addr:street":"Gemeenteweg",
    "iso:country":"NL",
    "sg:address":"Gemeenteweg 62",
    "sg:city":"Staphorst",
    "sg:orig_category":"Banken And Kredietinstellingen",
    "sg:phone":"+31 522 462 423",
    "sg:postcode":"7951 CP",
    "sg:province":"Overijssel",
    "wof:name":"Abn Amro",
    "wof:placetype":"venue"
},
  "geometry": {"coordinates":[6.208368,52.646038],"type":"Point"}
}