{
  "type": "Feature",
  "properties": {
    "addr:full":"Noordzijde 23 Oud Alblas Zuid-Holland 2969 AR",
    "addr:housenumber":"23",
    "addr:postcode":"2969",
    "addr:street":"Noordzijde;Oud Alblas",
    "iso:country":"NL",
    "sg:address":"Noordzijde 23",
    "sg:city":"Oud Alblas",
    "sg:orig_category":"Zuivelproducten And Spijsoli?n Gh",
    "sg:phone":"+31 184 691 344",
    "sg:postcode":"2969 AR",
    "sg:province":"Zuid-Holland",
    "wof:name":"Gebroeders Heykoop Kaasmakerij",
    "wof:placetype":"venue"
},
  "geometry": {"coordinates":[4.719938,51.860565],"type":"Point"}
}