{
  "type": "Feature",
  "properties": {
    "iso:country":"NL",
    "sg:address":"Meester Werkmanstraat 24",
    "sg:city":"Hellendoorn",
    "sg:orig_category":"Kampeerterreinen",
    "sg:phone":"+31 548 681 376",
    "sg:postcode":"7447 RZ",
    "sg:province":"Overijssel",
    "wof:name":"Kampeerboerderij 'T Vosje",
    "wof:placetype":"venue"
},
  "geometry": {"coordinates":[6.4852871895,52.4096832275],"type":"Point"}
}