{
  "type": "Feature",
  "properties": {
    "iso:country":"NL",
    "sg:address":"Blaaksedk O 3",
    "sg:city":"Heinenoord",
    "sg:orig_category":"Fietsen En Bromfietsen",
    "sg:phone":"+31 186 601 320",
    "sg:postcode":"3274 LA",
    "sg:province":"South Holland",
    "wof:name":"Enden, Gebr Van Den",
    "wof:placetype":"venue"
},
  "geometry": {"coordinates":[4.519036,51.811291],"type":"Point"}
}