{
  "type": "Feature",
  "properties": {
    "addr:full":"Kerkbuurt 18 Tuitjenhorn Noord-Holland 1747 GP",
    "addr:housenumber":"18",
    "addr:postcode":"1747 gp",
    "addr:street":"Kerkbuurt",
    "iso:country":"NL",
    "sg:address":"Kerkbuurt 18",
    "sg:city":"Tuitjenhorn",
    "sg:orig_category":"Public Relationbureaus",
    "sg:phone":"+31 226 391 878",
    "sg:postcode":"1747 GP",
    "sg:province":"Noord-Holland",
    "wof:name":"Jan Van Musscher Reclame-Adviseur Bv",
    "wof:placetype":"venue"
},
  "geometry": {"coordinates":[4.758621,52.7397],"type":"Point"}
}