{
  "type": "Feature",
  "properties": {
    "addr:full":"Oude Asserstr 15 Vries Drenthe 9481 BK",
    "addr:housenumber":"15",
    "addr:postcode":"9481 bk",
    "addr:street":"Oude Asserstr",
    "iso:country":"NL",
    "sg:address":"Oude Asserstr 15",
    "sg:city":"Vries",
    "sg:orig_category":"Autorijscholen",
    "sg:phone":"+31 592 580 804",
    "sg:postcode":"9481 BK",
    "sg:province":"Drenthe",
    "wof:name":"Excellent",
    "wof:placetype":"venue"
},
  "geometry": {"coordinates":[-85.944946,42.811916],"type":"Point"}
}