{
  "type": "Feature",
  "properties": {
    "iso:country":"NL",
    "sg:address":"Loolaan 5A",
    "sg:city":"S Gravenhage",
    "sg:orig_category":"Verenigingen En Stichtingen",
    "sg:phone":"+31 70 383 5767",
    "sg:postcode":"2592 CM",
    "sg:province":"South Holland",
    "wof:name":"Laredo",
    "wof:placetype":"venue"
},
  "geometry": {"coordinates":[4.35298,52.089199],"type":"Point"}
}