{
  "type": "Feature",
  "properties": {
    "iso:country":"NL",
    "sg:address":"Professor Lindeboomlaan 52",
    "sg:city":"Ermelo",
    "sg:orig_category":"Elektronische Bedrijfsinstallaties",
    "sg:phone":"+31 341 557 034",
    "sg:postcode":"3853 GD",
    "sg:province":"Gelderland",
    "wof:name":"A J Vosselman",
    "wof:placetype":"venue"
},
  "geometry": {"coordinates":[5.600201,52.301659],"type":"Point"}
}