{
  "type": "Feature",
  "properties": {
    "addr:full":"Houttuinen 36 Dordrecht Zuid-Holland 3311 CE",
    "addr:housenumber":"36",
    "addr:postcode":"3311 ce",
    "addr:street":"Houttuinen",
    "iso:country":"NL",
    "sg:address":"Houttuinen 36",
    "sg:city":"Dordrecht",
    "sg:orig_category":"Advocaten And Juridische Adviseurs",
    "sg:phone":"+31 78 613 3966",
    "sg:postcode":"3311 CE",
    "sg:province":"Zuid-Holland",
    "wof:name":"Veldhuijzen Schep & Nuiten Advocaten",
    "wof:placetype":"venue"
},
  "geometry": {"coordinates":[4.660883,51.81477],"type":"Point"}
}