{
  "type": "Feature",
  "properties": {
    "iso:country":"NL",
    "sg:address":"Statenwg 152C",
    "sg:city":"Rotterdam",
    "sg:orig_category":"Keukens",
    "sg:phone":"+31 10 467 5307",
    "sg:postcode":"3039 JN",
    "sg:province":"Zuid-Holland",
    "wof:name":"Fabru",
    "wof:placetype":"venue"
},
  "geometry": {"coordinates":[4.460804,51.928486],"type":"Point"}
}