{
  "type": "Feature",
  "properties": {
    "addr:full":"Dyckmeesterwg 12A Zutphen Gelderland 7201 AL",
    "addr:housenumber":"12a",
    "addr:postcode":"7201",
    "addr:street":"Dyckmeesterwg;Gelderland",
    "iso:country":"NL",
    "sg:address":"Dyckmeesterwg 12A",
    "sg:city":"Zutphen",
    "sg:orig_category":"Verzekeringen - Verzekeringskantoren",
    "sg:phone":"+31 575 515 747",
    "sg:postcode":"7201 AL",
    "sg:province":"Gelderland",
    "sg:website":"http://www.consor.nl",
    "wof:name":"Peters Adviesgroep",
    "wof:placetype":"venue"
},
  "geometry": {"coordinates":[6.191525,52.140202],"type":"Point"}
}