{
  "type": "Feature",
  "properties": {
    "addr:full":"Dam 41 Alblasserdam Zuid-Holland 2952 AB",
    "addr:housenumber":"41",
    "addr:postcode":"2952 ab",
    "addr:street":"Dam",
    "iso:country":"NL",
    "sg:address":"Dam 41",
    "sg:city":"Alblasserdam",
    "sg:orig_category":"Zalenverhuur",
    "sg:phone":"+31 184 682 872",
    "sg:postcode":"2952 AB",
    "sg:province":"Zuid-Holland",
    "wof:name":"Concordia",
    "wof:placetype":"venue"
},
  "geometry": {"coordinates":[4.66,51.859371],"type":"Point"}
}