{
  "type": "Feature",
  "properties": {
    "iso:country":"NL",
    "sg:address":"Dr Schreuderstr 54",
    "sg:city":"Zwammerdam",
    "sg:orig_category":"Adviesbureaus Bedrijfsorganisatie",
    "sg:phone":"+31 172 612 079",
    "sg:postcode":"2471 PT",
    "sg:province":"South Holland",
    "wof:name":"Blaauwgeers",
    "wof:placetype":"venue"
},
  "geometry": {"coordinates":[4.724047,52.104259],"type":"Point"}
}