{
  "type": "Feature",
  "properties": {
    "addr:full":"Kerkstraat 14 Tegelen Limburg 5931 NN",
    "addr:housenumber":"14",
    "addr:postcode":"5931 nn",
    "addr:street":"Kerkstraat",
    "iso:country":"NL",
    "sg:address":"Kerkstraat 14",
    "sg:city":"Tegelen",
    "sg:orig_category":"Discountwinkels",
    "sg:phone":"+31 77 373 1758",
    "sg:postcode":"5931 NN",
    "sg:province":"Limburg",
    "wof:name":"Zeeman Textielsupers",
    "wof:placetype":"venue"
},
  "geometry": {"coordinates":[6.138262,51.3423],"type":"Point"}
}