{
  "type": "Feature",
  "properties": {
    "iso:country":"NL",
    "sg:address":"Kerkstraat 14",
    "sg:city":"Tegelen",
    "sg:orig_category":"Discountwinkels",
    "sg:phone":"+31 77 373 1758",
    "sg:postcode":"5931 NN",
    "sg:province":"Limburg",
    "wof:name":"Zeeman Textielsupers",
    "wof:placetype":"venue"
},
  "geometry": {"coordinates":[6.138262,51.3423],"type":"Point"}
}