{
  "type": "Feature",
  "properties": {
    "addr:full":"Straatweg 158 Rotterdam Zuid-Holland 3054 AJ",
    "addr:housenumber":"158",
    "addr:postcode":"3054 aj",
    "addr:street":"Straatweg",
    "iso:country":"NL",
    "sg:address":"Straatweg 158",
    "sg:city":"Rotterdam",
    "sg:orig_category":"Verenigingen En Stichtingen",
    "sg:phone":"+31 10 422 6970",
    "sg:postcode":"3054 AJ",
    "sg:province":"Zuid-Holland",
    "wof:name":"Filosofisch Centrum",
    "wof:placetype":"venue"
},
  "geometry": {"coordinates":[4.486617,51.948612],"type":"Point"}
}