{
  "type": "Feature",
  "properties": {
    "iso:country":"NL",
    "sg:address":"Watergoorwg 69",
    "sg:city":"Nykerk Gld",
    "sg:orig_category":"Plastic Verwerkende Industrie",
    "sg:phone":"+31 33 245 6410",
    "sg:postcode":"3861 MA",
    "sg:province":"Gelderland",
    "sg:website":"http://www.veriplast.com",
    "wof:name":"Veriplast Nijkerk",
    "wof:placetype":"venue"
},
  "geometry": {"coordinates":[5.471819,52.230682],"type":"Point"}
}