{
  "type": "Feature",
  "properties": {
    "addr:full":"T Blok 61 Breda North Brabant 4823 JC",
    "addr:housenumber":"61",
    "addr:postcode":"4823 jc",
    "addr:street":"T Blok",
    "iso:country":"NL",
    "sg:address":"T Blok 61",
    "sg:city":"Breda",
    "sg:orig_category":"Verzekeringen - Verzekeringskantoren",
    "sg:phone":"+31 76 542 3444",
    "sg:postcode":"4823 JC",
    "sg:province":"North Brabant",
    "sg:website":"http://www.setiakawan-assurantie.nl",
    "wof:name":"Setiakawan Assurantiebureau Bv",
    "wof:placetype":"venue"
},
  "geometry": {"coordinates":[4.73972,51.624836],"type":"Point"}
}