{
  "type": "Feature",
  "properties": {
    "addr:full":"Rotterdamseweg 56 2920 Ab Pernambuco KRIM PE",
    "addr:housenumber":"56",
    "addr:postcode":"2920 ab",
    "addr:street":"Rotterdamseweg",
    "iso:country":"NL",
    "sg:address":"Rotterdamseweg 56",
    "sg:city":"2920 Ab",
    "sg:classifiers":[
        {
            "category":"Banks & Credit Unions",
            "subcategory":"Bank",
            "type":"Services"
        }
    ],
    "sg:phone":"+31 180 514 411",
    "sg:postcode":"KRIM PE",
    "sg:province":"Pernambuco",
    "wof:name":"Ing Bank Nv",
    "wof:placetype":"venue"
},
  "geometry": {"coordinates":[-38.083542,-8.37738],"type":"Point"}
}