{
  "type": "Feature",
  "properties": {
    "addr:full":"Gentiaan 37 Nykerk Gld Gelderland 3863 DR",
    "addr:housenumber":"37;3863",
    "addr:street":"Gentiaan;Gld Gelderland;Dr",
    "iso:country":"NL",
    "sg:address":"Gentiaan 37",
    "sg:city":"Nykerk Gld",
    "sg:orig_category":"Kabels",
    "sg:phone":"+31 33 246 4493",
    "sg:postcode":"3863 DR",
    "sg:province":"Gelderland",
    "wof:name":"Voituron Handelsonderneming",
    "wof:placetype":"venue"
},
  "geometry": {"coordinates":[5.4584021568,52.2195053101],"type":"Point"}
}