{
  "type": "Feature",
  "properties": {
    "addr:full":"De Stuw 8 Dalfsen Overijssel 7722 VJ",
    "addr:housenumber":"8",
    "addr:postcode":"7722 vj",
    "addr:street":"De Stuw",
    "iso:country":"NL",
    "sg:address":"De Stuw 8",
    "sg:city":"Dalfsen",
    "sg:orig_category":"Kampeerterreinen",
    "sg:phone":"+31 529 471 745",
    "sg:postcode":"7722 VJ",
    "sg:province":"Overijssel",
    "wof:name":"Camping De Bosvreugd",
    "wof:placetype":"venue"
},
  "geometry": {"coordinates":[6.3358149529,52.523223877],"type":"Point"}
}