{
  "type": "Feature",
  "properties": {
    "addr:full":"Vilderdijk 82 Oss Noord-Brabant 5345 PP",
    "addr:housenumber":"82",
    "addr:postcode":"5345 pp",
    "addr:street":"Vilderdijk",
    "iso:country":"NL",
    "sg:address":"Vilderdijk 82",
    "sg:city":"Oss",
    "sg:orig_category":"Glaszetten",
    "sg:phone":"+31 412 635 540",
    "sg:postcode":"5345 PP",
    "sg:province":"Noord-Brabant",
    "wof:name":"A.H.M.J. V.D. Heijden",
    "wof:placetype":"venue"
},
  "geometry": {"coordinates":[-77.235214,38.312599],"type":"Point"}
}