{
  "type": "Feature",
  "properties": {
    "addr:full":"Molenweg 6 Surhuisterveen Friesland 9231 HS",
    "addr:housenumber":"6",
    "addr:postcode":"9231 hs",
    "addr:street":"Molenweg",
    "iso:country":"NL",
    "sg:address":"Molenweg 6",
    "sg:city":"Surhuisterveen",
    "sg:orig_category":"Kantoorartikelen",
    "sg:phone":"+31 512 361 441",
    "sg:postcode":"9231 HS",
    "sg:province":"Friesland",
    "wof:name":"Riemersma Projektmeubilair Bv",
    "wof:placetype":"venue"
},
  "geometry": {"coordinates":[6.1787090302,53.1814117432],"type":"Point"}
}