{
  "type": "Feature",
  "properties": {
    "iso:country":"NL",
    "sg:address":"Parkstraat 20",
    "sg:city":"Nuenen",
    "sg:orig_category":"Juweliers",
    "sg:phone":"+31 40 283 5442",
    "sg:postcode":"5671 GG",
    "sg:province":"North Brabant",
    "wof:name":"Ron Van Buuren Juwelier",
    "wof:placetype":"venue"
},
  "geometry": {"coordinates":[5.545893,51.472488],"type":"Point"}
}