{
  "type": "Feature",
  "properties": {
    "addr:full":"Enschedesestr 32 Haaksbergen Overijssel 7481 CR",
    "addr:housenumber":"32",
    "addr:postcode":"7481 cr",
    "addr:street":"Enschedesestr",
    "iso:country":"NL",
    "sg:address":"Enschedesestr 32",
    "sg:city":"Haaksbergen",
    "sg:classifiers":[
        {
            "category":"Shopping",
            "subcategory":"News",
            "type":"Retail Goods"
        }
    ],
    "sg:phone":"+31 53 572 6589",
    "sg:postcode":"7481 CR",
    "sg:province":"Overijssel",
    "sg:tags":[
        "maandbladen",
        "en",
        "week-"
    ],
    "wof:name":"Weekblad Rond Haaksbergen",
    "wof:placetype":"venue"
},
  "geometry": {"coordinates":[6.7468881607,52.1561088562],"type":"Point"}
}