{
  "type": "Feature",
  "properties": {
    "addr:full":"Plesmanstr 89 Hoogeveen Drenthe 7903 BG",
    "addr:housenumber":"89",
    "addr:postcode":"7903",
    "addr:street":"Plesmanstr",
    "iso:country":"NL",
    "sg:address":"Plesmanstr 89",
    "sg:city":"Hoogeveen",
    "sg:classifiers":[
        {
            "category":"Retail",
            "subcategory":"Auto Repair",
            "type":"Services"
        }
    ],
    "sg:phone":"+31 528 223 366",
    "sg:postcode":"7903 BG",
    "sg:province":"Drenthe",
    "sg:tags":[
        "garage"
    ],
    "sg:website":"http://www.garagejansen.nl",
    "wof:name":"Jansen, Garage",
    "wof:placetype":"venue"
},
  "geometry": {"coordinates":[6.519397,52.736492],"type":"Point"}
}