{
  "type": "Feature",
  "properties": {
    "addr:full":"De Noesten 10 Westerbork Drenthe 9431 TC",
    "addr:housenumber":"10",
    "addr:postcode":"9431 tc",
    "addr:street":"De Noesten",
    "iso:country":"NL",
    "sg:address":"De Noesten 10",
    "sg:city":"Westerbork",
    "sg:orig_category":"Verlichting And Huishoudartikelen",
    "sg:phone":"+31 593 332 222",
    "sg:postcode":"9431 TC",
    "sg:province":"Drenthe",
    "wof:name":"Intergold Trade Service Bv",
    "wof:placetype":"venue"
},
  "geometry": {"coordinates":[6.618404,52.845387],"type":"Point"}
}