{
  "type": "Feature",
  "properties": {
    "addr:full":"Braamstukken 60 Eelde Provincie Drenthe 9761 LL",
    "addr:housenumber":"60",
    "addr:postcode":"9761 ll",
    "addr:street":"Braamstukken;Provincie Drenthe",
    "iso:country":"NL",
    "sg:address":"Braamstukken 60",
    "sg:city":"Eelde",
    "sg:orig_category":"Parfum And Cosmetica Gh",
    "sg:phone":"+31 50 309 5953",
    "sg:postcode":"9761 LL",
    "sg:province":"Provincie Drenthe",
    "wof:name":"Oriflame",
    "wof:placetype":"venue"
},
  "geometry": {"coordinates":[6.55366,53.136738],"type":"Point"}
}