{
  "type": "Feature",
  "properties": {
    "addr:full":"Akerstraat 68 Kerkrade Limburg 6466 HK",
    "addr:housenumber":"68",
    "addr:postcode":"6466 hk",
    "addr:street":"Akerstraat",
    "iso:country":"NL",
    "sg:address":"Akerstraat 68",
    "sg:city":"Kerkrade",
    "sg:classifiers":[
        {
            "category":"Bakery",
            "type":"Food & Drink"
        }
    ],
    "sg:phone":"+31 45 541 3367",
    "sg:postcode":"6466 HK",
    "sg:province":"Limburg",
    "sg:tags":[
        "brood",
        "banket"
    ],
    "wof:name":"Echte Bakkers F. Werres",
    "wof:placetype":"venue"
},
  "geometry": {"coordinates":[6.026123,50.857761],"type":"Point"}
}