{
  "type": "Feature",
  "properties": {
    "addr:full":"Dahliastraat 16 Rhenen Utrecht 3911 WD",
    "addr:housenumber":"16",
    "addr:postcode":"3911 wd",
    "addr:street":"Dahliastraat",
    "iso:country":"NL",
    "sg:address":"Dahliastraat 16",
    "sg:city":"Rhenen",
    "sg:orig_category":"Werving And Selectie Van Vast Personeel",
    "sg:phone":"+31 317 613 580",
    "sg:postcode":"3911 WD",
    "sg:province":"Utrecht",
    "wof:name":"S.B.C. De Frel",
    "wof:placetype":"venue"
},
  "geometry": {"coordinates":[5.5693540573,51.9671554565],"type":"Point"}
}