{
  "type": "Feature",
  "properties": {
    "addr:full":"Hanzeweg 33 Barneveld Gelderland 3771 NG",
    "addr:housenumber":"33",
    "addr:postcode":"3771 ng",
    "addr:street":"Hanzeweg;Gelderland",
    "iso:country":"NL",
    "sg:address":"Hanzeweg 33",
    "sg:city":"Barneveld",
    "sg:orig_category":"Autokeuringen",
    "sg:phone":"+31 342 490 756",
    "sg:postcode":"3771 NG",
    "sg:province":"Gelderland",
    "wof:name":"Polyesterbedrijf De Valk Bv",
    "wof:placetype":"venue"
},
  "geometry": {"coordinates":[5.613918,52.167458],"type":"Point"}
}