{
  "type": "Feature",
  "properties": {
    "addr:full":"Molenweg 3 Gorssel Gelderland 7213 XA",
    "addr:housenumber":"3",
    "addr:postcode":"7213 xa",
    "addr:street":"Molenweg;Gelderland",
    "iso:country":"NL",
    "sg:address":"Molenweg 3",
    "sg:city":"Gorssel",
    "sg:orig_category":"Koeriersdiensten",
    "sg:phone":"+31 575 494 592",
    "sg:postcode":"7213 XA",
    "sg:province":"Gelderland",
    "wof:name":"A4",
    "wof:placetype":"venue"
},
  "geometry": {"coordinates":[6.197089,52.205105],"type":"Point"}
}