{
  "type": "Feature",
  "properties": {
    "addr:full":"Siebengewaldsewg 41 Bergen Lb Limburg 5854 PA",
    "addr:housenumber":"41",
    "addr:postcode":"lb;5854 pa",
    "addr:street":"Siebengewaldsewg",
    "iso:country":"NL",
    "sg:address":"Siebengewaldsewg 41",
    "sg:city":"Bergen Lb",
    "sg:orig_category":"Makelaars En Adviseurs Onroerende Goederen",
    "sg:phone":"+31 485 343 566",
    "sg:postcode":"5854 PA",
    "sg:province":"Limburg",
    "wof:name":"Agriteam Zuid Oost Ned",
    "wof:placetype":"venue"
},
  "geometry": {"coordinates":[-93.129936,36.705662],"type":"Point"}
}