{
  "type": "Feature",
  "properties": {
    "addr:full":"Hekendorperwg 2 Oudewater Utrecht 3421 VK",
    "addr:housenumber":"2",
    "addr:postcode":"3421 vk",
    "addr:street":"Hekendorperwg",
    "iso:country":"NL",
    "sg:address":"Hekendorperwg 2",
    "sg:city":"Oudewater",
    "sg:orig_category":"Bejaarden - Verzorgingstehuizen",
    "sg:phone":"+31 348 562 324",
    "sg:postcode":"3421 VK",
    "sg:province":"Utrecht",
    "wof:name":"Schuylenburcht",
    "wof:placetype":"venue"
},
  "geometry": {"coordinates":[4.865589,52.025082],"type":"Point"}
}