{
  "type": "Feature",
  "properties": {
    "addr:full":"Lopikerweg Oost 102 Lopik Utrecht 3411 LW",
    "addr:housenumber":"102",
    "addr:postcode":"3411 lw",
    "addr:street":"Lopikerweg Oost",
    "iso:country":"NL",
    "sg:address":"Lopikerweg Oost 102",
    "sg:city":"Lopik",
    "sg:orig_category":"Diverse Consumentenartikelen Gh",
    "sg:phone":"+31 348 552 627",
    "sg:postcode":"3411 LW",
    "sg:province":"Utrecht",
    "wof:name":"A. Bosch",
    "wof:placetype":"venue"
},
  "geometry": {"coordinates":[4.998466,51.986076],"type":"Point"}
}