{
  "type": "Feature",
  "properties": {
    "addr:full":"Kr Palmstr 5-7 Amsterdam Noord-Holland 1015 HH",
    "addr:housenumber":"5-7",
    "addr:postcode":"1015 hh",
    "addr:street":"Palmstr",
    "iso:country":"NL",
    "sg:address":"Kr Palmstr 5-7",
    "sg:city":"Amsterdam",
    "sg:orig_category":"Administratie- En Boekhoudkantoren",
    "sg:phone":"+31 20 627 8357",
    "sg:postcode":"1015 HH",
    "sg:province":"Noord-Holland",
    "wof:name":"Cono",
    "wof:placetype":"venue"
},
  "geometry": {"coordinates":[4.88264,52.382534],"type":"Point"}
}