{
  "type": "Feature",
  "properties": {
    "iso:country":"NL",
    "sg:address":"Mullerln 108",
    "sg:city":"Veldhoven",
    "sg:orig_category":"Tuinontwerp En -Advies",
    "sg:phone":"+31 40 253 3647",
    "sg:postcode":"5505 VG",
    "sg:province":"Noord-Brabant",
    "wof:name":"Seuntjens, Lea",
    "wof:placetype":"venue"
},
  "geometry": {"coordinates":[5.404554,51.421745],"type":"Point"}
}