{
  "type": "Feature",
  "properties": {
    "addr:full":"Burgemeester Heijmansstr 4 Hoogwoud Noord-Holland 1718 AN",
    "addr:housenumber":"4",
    "addr:postcode":"1718 an",
    "addr:street":"Burgemeester Heijmansstr",
    "iso:country":"NL",
    "sg:address":"Burgemeester Heijmansstr 4",
    "sg:city":"Hoogwoud",
    "sg:classifiers":[
        {
            "category":"Education",
            "subcategory":"Preschool",
            "type":"Public Place"
        }
    ],
    "sg:phone":"+31 226 355 843",
    "sg:postcode":"1718 AN",
    "sg:province":"Noord-Holland",
    "sg:tags":[
        "kleuteronderwijs",
        "basis-"
    ],
    "wof:name":"Basisschool Sint Wulfram",
    "wof:placetype":"venue"
},
  "geometry": {"coordinates":[4.937621,52.71497],"type":"Point"}
}