{
  "type": "Feature",
  "properties": {
    "addr:full":"Postbus 98 Boxmeer Noord-Brabant 5830 AB",
    "addr:housenumber":"98",
    "addr:postcode":"5830 ab",
    "addr:street":"Postbus",
    "iso:country":"NL",
    "sg:address":"Postbus 98",
    "sg:city":"Boxmeer",
    "sg:orig_category":"Omroep",
    "sg:phone":"+31 485 576 667",
    "sg:postcode":"5830 AB",
    "sg:province":"Noord-Brabant",
    "wof:name":"Blos",
    "wof:placetype":"venue"
},
  "geometry": {"coordinates":[5.950357,51.646206],"type":"Point"}
}