{
  "type": "Feature",
  "properties": {
    "iso:country":"NL",
    "sg:address":"Zaadmarkt 88",
    "sg:city":"Zutphen",
    "sg:orig_category":"Musea And Historische Gebouwen",
    "sg:phone":"+31 575 516 878",
    "sg:postcode":"7201 DE",
    "sg:province":"Gelderland",
    "wof:name":"Museum Henriette Polak",
    "wof:placetype":"venue"
},
  "geometry": {"coordinates":[6.196963,52.140331],"type":"Point"}
}