{
  "type": "Feature",
  "properties": {
    "addr:full":"Plein 1957 27A Kwintsheul Zuid-Holland 2295 PK",
    "addr:housenumber":"27a",
    "addr:postcode":"2295 pk",
    "addr:street":"Plein 1957",
    "iso:country":"NL",
    "sg:address":"Plein 1957 27A",
    "sg:city":"Kwintsheul",
    "sg:orig_category":"Begrafenisverzorging",
    "sg:phone":"+31 174 292 926",
    "sg:postcode":"2295 PK",
    "sg:province":"Zuid-Holland",
    "wof:name":"Dijk & Noordermeer, Van",
    "wof:placetype":"venue"
},
  "geometry": {"coordinates":[4.25564,52.013626],"type":"Point"}
}