{
  "type": "Feature",
  "properties": {
    "addr:full":"Willem De Zwijgerlaan 115 Amsterdam North Holland 1056 JJ",
    "addr:housenumber":"115",
    "addr:postcode":"1056 jj",
    "addr:street":"Willem De Zwijgerlaan",
    "iso:country":"NL",
    "sg:address":"Willem De Zwijgerlaan 115",
    "sg:city":"Amsterdam",
    "sg:orig_category":"Kappers",
    "sg:phone":"+31 20 618 6586",
    "sg:postcode":"1056 JJ",
    "sg:province":"North Holland",
    "wof:name":"M G Hairstudio",
    "wof:placetype":"venue"
},
  "geometry": {"coordinates":[4.862901,52.373737],"type":"Point"}
}