{
  "type": "Feature",
  "properties": {
    "addr:full":"Makadocenter 25 Nieuwegein Utrecht 3431 AW",
    "addr:housenumber":"25",
    "addr:postcode":"3431 aw",
    "addr:street":"Makadocenter",
    "iso:country":"NL",
    "sg:address":"Makadocenter 25",
    "sg:city":"Nieuwegein",
    "sg:classifiers":[
        {
            "category":"Food & Beverages",
            "subcategory":"Fruits & Vegetables",
            "type":"Retail Goods"
        }
    ],
    "sg:phone":"+31 30 604 6112",
    "sg:postcode":"3431 AW",
    "sg:province":"Utrecht",
    "sg:tags":[
        "groenten"
    ],
    "wof:name":"Verwey Groenten En Fruit Bv",
    "wof:placetype":"venue"
},
  "geometry": {"coordinates":[5.082356,52.033718],"type":"Point"}
}