{
  "type": "Feature",
  "properties": {
    "addr:full":"Paganinistr 24 Leiden Zuid-Holland 2324 BC",
    "addr:housenumber":"24",
    "addr:postcode":"2324 bc",
    "addr:street":"Paganinistr",
    "iso:country":"NL",
    "sg:address":"Paganinistr 24",
    "sg:city":"Leiden",
    "sg:classifiers":[
        {
            "category":"Food & Beverages",
            "subcategory":"Candy",
            "type":"Retail Goods"
        }
    ],
    "sg:phone":"+31 71 576 1262",
    "sg:postcode":"2324 BC",
    "sg:province":"Zuid-Holland",
    "sg:tags":[
        "sport-",
        "en",
        "spelartikelen"
    ],
    "sg:website":"http://www.windtrade.nl",
    "wof:name":"Windrade",
    "wof:placetype":"venue"
},
  "geometry": {"coordinates":[4.473541,52.139927],"type":"Point"}
}