{
  "type": "Feature",
  "properties": {
    "iso:country":"NL",
    "sg:address":"Kerkstraat 13",
    "sg:city":"Strijen",
    "sg:classifiers":[
        {
            "category":"Shopping",
            "subcategory":"Clothing, Apparel, & Fashions",
            "type":"Retail Goods"
        }
    ],
    "sg:phone":"+31 78 674 4483",
    "sg:postcode":"3291 AJ",
    "sg:province":"South Holland",
    "sg:tags":[
        "ondergoed",
        "lingerie"
    ],
    "wof:name":"B. Kruijthof",
    "wof:placetype":"venue"
},
  "geometry": {"coordinates":[4.553145,51.742794],"type":"Point"}
}