{
  "type": "Feature",
  "properties": {
    "addr:full":"Sint Nicasiusstraat 12 Heeze Noord-Brabant 5591 EX",
    "addr:housenumber":"12",
    "addr:postcode":"5591 ex",
    "addr:street":"Sint Nicasiusstraat",
    "iso:country":"NL",
    "sg:address":"Sint Nicasiusstraat 12",
    "sg:city":"Heeze",
    "sg:orig_category":"Diverse Opleidingen And Onderwijs",
    "sg:phone":"+31 40 226 5410",
    "sg:postcode":"5591 EX",
    "sg:province":"Noord-Brabant",
    "wof:name":"Alliance Francaise Eindhoven",
    "wof:placetype":"venue"
},
  "geometry": {"coordinates":[5.577603,51.382771],"type":"Point"}
}