{
  "type": "Feature",
  "properties": {
    "addr:full":"Stadswg 7 T Harde Gelderland 8084 PH",
    "addr:housenumber":"7 t",
    "addr:postcode":"8084",
    "addr:street":"Stadswg;Harde Gelderland",
    "iso:country":"NL",
    "sg:address":"Stadswg 7",
    "sg:city":"T Harde",
    "sg:orig_category":"Bloemen En Planten",
    "sg:phone":"+31 525 683 557",
    "sg:postcode":"8084 PH",
    "sg:province":"Gelderland",
    "wof:name":"Aperloo, Droogbloemenboerderij",
    "wof:placetype":"venue"
},
  "geometry": {"coordinates":[5.861128,52.4249],"type":"Point"}
}