{
  "type": "Feature",
  "properties": {
    "addr:full":"Lekstraat 16 Oss Noord-Brabant 5347 KV",
    "addr:housenumber":"16",
    "addr:postcode":"5347 kv",
    "addr:street":"Lekstraat",
    "iso:country":"NL",
    "sg:address":"Lekstraat 16",
    "sg:city":"Oss",
    "sg:orig_category":"Goederenvervoer Over De Weg",
    "sg:phone":"+31 412 643 835",
    "sg:postcode":"5347 KV",
    "sg:province":"Noord-Brabant",
    "wof:name":"Van Doorn Bv",
    "wof:placetype":"venue"
},
  "geometry": {"coordinates":[-77.235214,38.312599],"type":"Point"}
}