{
  "type": "Feature",
  "properties": {
    "addr:full":"Hofsedam 21 Wychen Gelderland 6601 GX",
    "addr:housenumber":"21",
    "addr:postcode":"6601 gx",
    "addr:street":"Hofsedam;Gelderland",
    "iso:country":"NL",
    "sg:address":"Hofsedam 21",
    "sg:city":"Wychen",
    "sg:orig_category":"Kassenbouw",
    "sg:phone":"+31 24 642 4821",
    "sg:postcode":"6601 GX",
    "sg:province":"Gelderland",
    "wof:name":"Lama Vof",
    "wof:placetype":"venue"
},
  "geometry": {"coordinates":[5.739404,51.816956],"type":"Point"}
}