{
  "type": "Feature",
  "properties": {
    "addr:full":"Korte Tuinstraat 24 Enkhuizen Noord-Holland 1601 CJ",
    "addr:housenumber":"24",
    "addr:postcode":"1601 cj",
    "addr:street":"Korte Tuinstraat",
    "iso:country":"NL",
    "sg:address":"Korte Tuinstraat 24",
    "sg:city":"Enkhuizen",
    "sg:orig_category":"Bloemen And Planten Gh",
    "sg:phone":"+31 228 314 184",
    "sg:postcode":"1601 CJ",
    "sg:province":"Noord-Holland",
    "wof:name":"G.A. Mosselman Bv",
    "wof:placetype":"venue"
},
  "geometry": {"coordinates":[5.279716,52.699905],"type":"Point"}
}