{
  "type": "Feature",
  "properties": {
    "addr:full":"Vierlinghwg 57 Bergschenhoek Zuid-Holland 2661 TM",
    "addr:housenumber":"57",
    "addr:postcode":"2661 tm",
    "addr:street":"Vierlinghwg",
    "iso:country":"NL",
    "sg:address":"Vierlinghwg 57",
    "sg:city":"Bergschenhoek",
    "sg:orig_category":"Administratie- En Boekhoudkantoren",
    "sg:phone":"+31 10 519 0283",
    "sg:postcode":"2661 TM",
    "sg:province":"Zuid-Holland",
    "wof:name":"Adwel",
    "wof:placetype":"venue"
},
  "geometry": {"coordinates":[4.500133,51.989536],"type":"Point"}
}