{
  "type": "Feature",
  "properties": {
    "iso:country":"NL",
    "sg:address":"Saxe Gothastr 3",
    "sg:city":"Boxmeer",
    "sg:orig_category":"Machinefabrieken",
    "sg:phone":"+31 485 574 766",
    "sg:postcode":"5831 AX",
    "sg:province":"Noord-Brabant",
    "wof:name":"Boxmeer Metaal Bv",
    "wof:placetype":"venue"
},
  "geometry": {"coordinates":[5.936191,51.638863],"type":"Point"}
}