{
  "type": "Feature",
  "properties": {
    "addr:full":"Kerkweg 30 Lemele Overijssel 8148 PZ",
    "addr:housenumber":"30",
    "addr:postcode":"8148 pz",
    "addr:street":"Kerkweg",
    "iso:country":"NL",
    "sg:address":"Kerkweg 30",
    "sg:city":"Lemele",
    "sg:orig_category":"Kampeerterreinen",
    "sg:phone":"+31 572 331 246",
    "sg:postcode":"8148 PZ",
    "sg:province":"Overijssel",
    "wof:name":"De Olde Lucas Hoeve Kamping",
    "wof:placetype":"venue"
},
  "geometry": {"coordinates":[6.4123148918,52.4549179077],"type":"Point"}
}