{
  "type": "Feature",
  "properties": {
    "addr:full":"Hoofdstraat 30 Veenendaal Utrecht 3901 AN",
    "addr:housenumber":"30",
    "addr:postcode":"3901 an",
    "addr:street":"Hoofdstraat",
    "iso:country":"NL",
    "sg:address":"Hoofdstraat 30",
    "sg:city":"Veenendaal",
    "sg:orig_category":"Warenhuizen",
    "sg:phone":"+31 318 511 216",
    "sg:postcode":"3901 AN",
    "sg:province":"Utrecht",
    "wof:name":"Varitail Bv",
    "wof:placetype":"venue"
},
  "geometry": {"coordinates":[5.5551891327,52.0259475708],"type":"Point"}
}