{
  "type": "Feature",
  "properties": {
    "iso:country":"NL",
    "sg:address":"Keizersgr 62-64",
    "sg:city":"Amsterdam",
    "sg:orig_category":"Kantoor- En Secretariaatsservice",
    "sg:phone":"+31 20 520 7500",
    "sg:postcode":"1015 CS",
    "sg:province":"Noord-Holland",
    "sg:website":"http://www.eurobusinesscenter.nl",
    "wof:name":"Euro Business Center",
    "wof:placetype":"venue"
},
  "geometry": {"coordinates":[4.8881788254,52.3783912659],"type":"Point"}
}