{
  "type": "Feature",
  "properties": {
    "iso:country":"NL",
    "sg:address":"Traay 92",
    "sg:city":"Driebergen Rysenb",
    "sg:orig_category":"Architecten En Architectenbureaus",
    "sg:phone":"+31 343 521 729",
    "sg:postcode":"3971 GR",
    "sg:province":"Utrecht",
    "wof:name":"Schildknegt, Ron",
    "wof:placetype":"venue"
},
  "geometry": {"coordinates":[5.289412,52.054504],"type":"Point"}
}