{
  "type": "Feature",
  "properties": {
    "addr:full":"Traay 92 Driebergen Rysenb Utrecht 3971 GR",
    "addr:housenumber":"92",
    "addr:postcode":"3971",
    "addr:street":"Traay;Rysenb",
    "iso:country":"NL",
    "sg:address":"Traay 92",
    "sg:city":"Driebergen Rysenb",
    "sg:orig_category":"Architecten En Architectenbureaus",
    "sg:phone":"+31 343 521 729",
    "sg:postcode":"3971 GR",
    "sg:province":"Utrecht",
    "wof:name":"Schildknegt, Ron",
    "wof:placetype":"venue"
},
  "geometry": {"coordinates":[5.289412,52.054504],"type":"Point"}
}