{
  "type": "Feature",
  "properties": {
    "addr:full":"Ten Busschekamp 28 Zwolle NL.08 8014 EE",
    "addr:housenumber":"28",
    "addr:postcode":"8014 ee",
    "addr:street":"Ten Busschekamp",
    "iso:country":"NL",
    "sg:address":"Ten Busschekamp 28",
    "sg:city":"Zwolle",
    "sg:classifiers":[
        {
            "category":"Fast Food",
            "type":"Food & Drink"
        }
    ],
    "sg:phone":"+31 38 465 2218",
    "sg:postcode":"8014 EE",
    "sg:province":"NL.08",
    "sg:tags":[
        "afhaal",
        "restaurant"
    ],
    "wof:name":"Fa A & K Tran",
    "wof:placetype":"venue"
},
  "geometry": {"coordinates":[6.113663,52.492535],"type":"Point"}
}