{
  "type": "Feature",
  "properties": {
    "addr:full":"Oostvlietwg 19A Leidschendam Zuid-Holland 2266 GM",
    "addr:housenumber":"19a",
    "addr:postcode":"2266 gm",
    "addr:street":"Oostvlietwg",
    "iso:country":"NL",
    "sg:address":"Oostvlietwg 19A",
    "sg:city":"Leidschendam",
    "sg:orig_category":"Beveiliging",
    "sg:phone":"+31 70 320 1416",
    "sg:postcode":"2266 GM",
    "sg:province":"Zuid-Holland",
    "wof:name":"Tht",
    "wof:placetype":"venue"
},
  "geometry": {"coordinates":[4.406389,52.086334],"type":"Point"}
}