{
  "type": "Feature",
  "properties": {
    "addr:full":"Molenweg 38 Zwolle NL.08 8012 WK",
    "addr:housenumber":"38",
    "addr:postcode":"8012",
    "addr:street":"Molenweg;Wk",
    "iso:country":"NL",
    "sg:address":"Molenweg 38",
    "sg:city":"Zwolle",
    "sg:orig_category":"Overheidsdiensten",
    "sg:phone":"+31 38 421 1660",
    "sg:postcode":"8012 WK",
    "sg:province":"NL.08",
    "wof:name":"St Vrye Evangelisatie Zwolle",
    "wof:placetype":"venue"
},
  "geometry": {"coordinates":[6.0982480049,52.5053062439],"type":"Point"}
}