{
  "type": "Feature",
  "properties": {
    "addr:full":"Markt 38 Prinsenbeek Noord-Brabant 4841 AC",
    "addr:housenumber":"38",
    "addr:postcode":"4841 ac",
    "addr:street":"Markt",
    "iso:country":"NL",
    "sg:address":"Markt 38",
    "sg:city":"Prinsenbeek",
    "sg:orig_category":"Verenigingen En Stichtingen",
    "sg:phone":"+31 76 549 3777",
    "sg:postcode":"4841 AC",
    "sg:province":"Noord-Brabant",
    "sg:website":"http://www.vnao.nl",
    "wof:name":"Afvalondernemingen, Ver Ned",
    "wof:placetype":"venue"
},
  "geometry": {"coordinates":[4.720007,51.600971],"type":"Point"}
}