{
  "type": "Feature",
  "properties": {
    "addr:full":"A Plesmanwg 200 Rotterdam South Holland 3088 GD",
    "addr:housenumber":"200",
    "addr:postcode":"3088 gd",
    "iso:country":"NL",
    "sg:address":"A Plesmanwg 200",
    "sg:city":"Rotterdam",
    "sg:classifiers":[
        {
            "category":"Retail",
            "subcategory":"Storage",
            "type":"Services"
        }
    ],
    "sg:phone":"+31 10 491 3600",
    "sg:postcode":"3088 GD",
    "sg:province":"South Holland",
    "sg:tags":[
        "op-",
        "en",
        "overslagbedrijven"
    ],
    "sg:website":"http://www.rsc.nl/home.htm",
    "wof:name":"Rail Service Center Rotterdam Bv",
    "wof:placetype":"venue"
},
  "geometry": {"coordinates":[4.430795,51.872353],"type":"Point"}
}