{
  "type": "Feature",
  "properties": {
    "addr:full":"Weerln 3 Hillegom North Holland 2181 HG",
    "addr:housenumber":"3",
    "addr:postcode":"2181 hg",
    "addr:street":"Weerln",
    "iso:country":"NL",
    "sg:address":"Weerln 3",
    "sg:city":"Hillegom",
    "sg:orig_category":"Verzekeringen - Verzekeringskantoren",
    "sg:phone":"+31 252 524 844",
    "sg:postcode":"2181 HG",
    "sg:province":"North Holland",
    "wof:name":"Aktiv",
    "wof:placetype":"venue"
},
  "geometry": {"coordinates":[4.578603,52.290993],"type":"Point"}
}