{
  "type": "Feature",
  "properties": {
    "addr:full":"Burg Patynln 54A Zeist Utrecht 3705 CG",
    "addr:housenumber":"54a",
    "addr:postcode":"3705 cg",
    "addr:street":"Burg Patynln",
    "iso:country":"NL",
    "sg:address":"Burg Patynln 54A",
    "sg:city":"Zeist",
    "sg:orig_category":"Podotherapeuten",
    "sg:phone":"+31 30 692 3677",
    "sg:postcode":"3705 CG",
    "sg:province":"Utrecht",
    "wof:name":"Podotherapie Praktijk Zeist",
    "wof:placetype":"venue"
},
  "geometry": {"coordinates":[5.24387,52.08548],"type":"Point"}
}