{
  "type": "Feature",
  "properties": {
    "addr:full":"Mascagniln 4 Berkel Enschot Noord-Brabant 5056 BA",
    "addr:housenumber":"4",
    "addr:postcode":"5056 ba",
    "addr:street":"Mascagniln",
    "iso:country":"NL",
    "sg:address":"Mascagniln 4",
    "sg:city":"Berkel Enschot",
    "sg:orig_category":"Adviesbureaus Bedrijfsorganisatie",
    "sg:phone":"+31 13 533 1886",
    "sg:postcode":"5056 BA",
    "sg:province":"Noord-Brabant",
    "wof:name":"Nee-Ica",
    "wof:placetype":"venue"
},
  "geometry": {"coordinates":[5.140549,51.579765],"type":"Point"}
}