{
  "type": "Feature",
  "properties": {
    "addr:full":"Ettensebaan 17A Breda North Brabant 4812 XA",
    "addr:housenumber":"17a",
    "addr:postcode":"4812 xa",
    "addr:street":"Ettensebaan",
    "iso:country":"NL",
    "sg:address":"Ettensebaan 17A",
    "sg:city":"Breda",
    "sg:orig_category":"Woninginrichting",
    "sg:phone":"+31 76 533 0717",
    "sg:postcode":"4812 XA",
    "sg:province":"North Brabant",
    "wof:name":"Suite 17 Bv",
    "wof:placetype":"venue"
},
  "geometry": {"coordinates":[4.7441020012,51.5820045471],"type":"Point"}
}