{
  "type": "Feature",
  "properties": {
    "iso:country":"NL",
    "sg:address":"Kon Beatrixln 9",
    "sg:city":"Vrouwenpolder",
    "sg:orig_category":"Webdesign Bureaus",
    "sg:phone":"+31 118 591 341",
    "sg:postcode":"4354 BK",
    "sg:province":"Zeeland",
    "sg:website":"http://www.vrouwenpolder.net",
    "wof:name":"Vrouwenpolder Net",
    "wof:placetype":"venue"
},
  "geometry": {"coordinates":[3.6116878986,51.5769882202],"type":"Point"}
}