{
  "type": "Feature",
  "properties": {
    "addr:full":"De Hanekampen 29 Beilen Drenthe 9411 XN",
    "addr:housenumber":"29",
    "addr:postcode":"9411 xn",
    "addr:street":"De Hanekampen",
    "iso:country":"NL",
    "sg:address":"De Hanekampen 29",
    "sg:city":"Beilen",
    "sg:orig_category":"Land- En Tuinbouw - Mechanisatie",
    "sg:phone":"+31 593 540 232",
    "sg:postcode":"9411 XN",
    "sg:province":"Drenthe",
    "wof:name":"Popken-Koenrades Vof",
    "wof:placetype":"venue"
},
  "geometry": {"coordinates":[6.514306,52.87579],"type":"Point"}
}