{
  "type": "Feature",
  "properties": {
    "iso:country":"NL",
    "sg:address":"De Hanekampen 29",
    "sg:city":"Beilen",
    "sg:orig_category":"Land- En Tuinbouw - Mechanisatie",
    "sg:phone":"+31 593 540 232",
    "sg:postcode":"9411 XN",
    "sg:province":"Drenthe",
    "wof:name":"Popken-Koenrades Vof",
    "wof:placetype":"venue"
},
  "geometry": {"coordinates":[6.514306,52.87579],"type":"Point"}
}