{
  "type": "Feature",
  "properties": {
    "iso:country":"NL",
    "sg:address":"Ridderstraat 4",
    "sg:city":"Wouw",
    "sg:orig_category":"Bloemen And Planten",
    "sg:phone":"+31 165 302 412",
    "sg:postcode":"4724 AB",
    "sg:province":"Noord-Brabant",
    "wof:name":"P.J. Schoonen",
    "wof:placetype":"venue"
},
  "geometry": {"coordinates":[4.38798,51.525356],"type":"Point"}
}