{
  "type": "Feature",
  "properties": {
    "addr:full":"Waverstr 22-2H Amsterdam Noord-Holland 1079 VL",
    "addr:housenumber":"22-2h",
    "addr:postcode":"1079 vl",
    "addr:street":"Waverstr",
    "iso:country":"NL",
    "sg:address":"Waverstr 22-2H",
    "sg:city":"Amsterdam",
    "sg:orig_category":"Webdesign Bureaus",
    "sg:phone":"+31 20 427 9254",
    "sg:postcode":"1079 VL",
    "sg:province":"Noord-Holland",
    "sg:website":"http://www.vgdevelopment.com",
    "wof:name":"V&G Development",
    "wof:placetype":"venue"
},
  "geometry": {"coordinates":[4.910255909,52.3463134766],"type":"Point"}
}