{
  "type": "Feature",
  "properties": {
    "iso:country":"NL",
    "sg:address":"Kanaal A Nz 208",
    "sg:city":"Emmer Compascuum",
    "sg:orig_category":"Geluidsopnamestudio'S",
    "sg:phone":"+31 591 351 971",
    "sg:postcode":"7881 KT",
    "sg:province":"Drenthe",
    "wof:name":"Borderline",
    "wof:placetype":"venue"
},
  "geometry": {"coordinates":[170.36663799999999,-43.587711],"type":"Point"}
}