{
  "type": "Feature",
  "properties": {
    "addr:full":"Honingstraat 14 Hilversum North Holland 1211 AW",
    "addr:housenumber":"14",
    "addr:postcode":"1211 aw",
    "addr:street":"Honingstraat",
    "iso:country":"NL",
    "sg:address":"Honingstraat 14",
    "sg:city":"Hilversum",
    "sg:orig_category":"Public Relationbureaus",
    "sg:phone":"+31 35 623 8185",
    "sg:postcode":"1211 AW",
    "sg:province":"North Holland",
    "wof:name":"Peter Kanters Public Relations Bv",
    "wof:placetype":"venue"
},
  "geometry": {"coordinates":[5.177289,52.228939],"type":"Point"}
}