{
  "type": "Feature",
  "properties": {
    "addr:full":"Kanaalstr 60 D Roden Drenthe 9301 LT",
    "addr:housenumber":"60 d",
    "addr:postcode":"9301 lt",
    "addr:street":"Kanaalstr",
    "iso:country":"NL",
    "sg:address":"Kanaalstr 60 D",
    "sg:city":"Roden",
    "sg:orig_category":"Verloskundigen",
    "sg:phone":"+31 50 501 7030",
    "sg:postcode":"9301 LT",
    "sg:province":"Drenthe",
    "wof:name":"Ma Lune",
    "wof:placetype":"venue"
},
  "geometry": {"coordinates":[6.432789,53.142551],"type":"Point"}
}