{
  "type": "Feature",
  "properties": {
    "addr:full":"Grt Hertoginneln 37-39 S Gravenhage Zuid-Holland 2517 EB",
    "addr:housenumber":"37-39;gravenhage",
    "addr:postcode":"2517 eb",
    "addr:street":"S",
    "iso:country":"NL",
    "sg:address":"Grt Hertoginneln 37-39",
    "sg:city":"S Gravenhage",
    "sg:orig_category":"Verenigingen En Stichtingen",
    "sg:phone":"+31 70 356 1862",
    "sg:postcode":"2517 EB",
    "sg:province":"Zuid-Holland",
    "sg:website":"http://www.svfn.nl",
    "wof:name":"Samenwerkende Vakfotografen Nederland",
    "wof:placetype":"venue"
},
  "geometry": {"coordinates":[4.28708,52.08667],"type":"Point"}
}