{
  "type": "Feature",
  "properties": {
    "addr:full":"Singel 526 Amsterdam North Holland 1017 AZ",
    "addr:housenumber":"526",
    "addr:postcode":"1017 az",
    "addr:street":"Singel",
    "iso:country":"NL",
    "sg:address":"Singel 526",
    "sg:city":"Amsterdam",
    "sg:orig_category":"Juweliers",
    "sg:phone":"+31 20 624 9715",
    "sg:postcode":"1017 AZ",
    "sg:province":"North Holland",
    "wof:name":"Singel Diamonds",
    "wof:placetype":"venue"
},
  "geometry": {"coordinates":[4.89156,52.366795],"type":"Point"}
}