{
  "type": "Feature",
  "properties": {
    "iso:country":"NL",
    "sg:address":"Singel 526",
    "sg:city":"Amsterdam",
    "sg:orig_category":"Juweliers",
    "sg:phone":"+31 20 624 9715",
    "sg:postcode":"1017 AZ",
    "sg:province":"North Holland",
    "wof:name":"Singel Diamonds",
    "wof:placetype":"venue"
},
  "geometry": {"coordinates":[4.89156,52.366795],"type":"Point"}
}