{
  "type": "Feature",
  "properties": {
    "iso:country":"NL",
    "sg:address":"Julianastr 18",
    "sg:city":"Lunteren",
    "sg:orig_category":"Onderhoudswerken",
    "sg:phone":"+31 318 485 712",
    "sg:postcode":"6741 AV",
    "sg:province":"Gelderland",
    "wof:name":"Schuurman",
    "wof:placetype":"venue"
},
  "geometry": {"coordinates":[5.618186,52.084694],"type":"Point"}
}