{
  "type": "Feature",
  "properties": {
    "iso:country":"NL",
    "sg:address":"Aronskelk 50",
    "sg:city":"Elsloo Lb",
    "sg:orig_category":"Verzekeringen - Verzekeringskantoren",
    "sg:phone":"+31 46 437 0645",
    "sg:postcode":"6181 MK",
    "sg:province":"BE.05",
    "wof:name":"Knipsael",
    "wof:placetype":"venue"
},
  "geometry": {"coordinates":[5.738695,50.960476],"type":"Point"}
}