{
  "type": "Feature",
  "properties": {
    "iso:country":"NL",
    "sg:address":"Doormanstr 3A",
    "sg:city":"Ommen",
    "sg:orig_category":"Etiketten",
    "sg:phone":"+31 529 469 950",
    "sg:postcode":"7731 BN",
    "sg:province":"Overijssel",
    "wof:name":"Golden Graphics",
    "wof:placetype":"venue"
},
  "geometry": {"coordinates":[6.430162,52.519413],"type":"Point"}
}