{
  "type": "Feature",
  "properties": {
    "addr:full":"Kapt Grantstr 21/23 Tilburg Noord-Brabant 5015 BA",
    "addr:housenumber":"21 / 23",
    "addr:postcode":"5015 ba",
    "iso:country":"NL",
    "sg:address":"Kapt Grantstr 21/23",
    "sg:city":"Tilburg",
    "sg:orig_category":"Machinefabrieken",
    "sg:phone":"+31 13 542 3712",
    "sg:postcode":"5015 BA",
    "sg:province":"Noord-Brabant",
    "wof:name":"Cmm Bv",
    "wof:placetype":"venue"
},
  "geometry": {"coordinates":[5.114494,51.566784],"type":"Point"}
}