{
  "type": "Feature",
  "properties": {
    "iso:country":"NL",
    "sg:address":"Lange Nieuwstraat 469",
    "sg:city":"Ijmuiden",
    "sg:orig_category":"Schoenen",
    "sg:phone":"+31 255 511 117",
    "sg:postcode":"1971 GE",
    "sg:province":"North Holland",
    "wof:name":"Leemans Schoenen",
    "wof:placetype":"venue"
},
  "geometry": {"coordinates":[4.619032,52.458664],"type":"Point"}
}