{
  "type": "Feature",
  "properties": {
    "addr:full":"Lovense Kanaaldijk 1 Tilburg Noord-Brabant 5046 AV",
    "addr:housenumber":"1",
    "addr:postcode":"5046 av",
    "addr:street":"Kanaaldijk",
    "iso:country":"NL",
    "sg:address":"Lovense Kanaaldijk 1",
    "sg:city":"Tilburg",
    "sg:orig_category":"Beeldende Kunstenaars",
    "sg:phone":"+31 13 542 1335",
    "sg:postcode":"5046 AV",
    "sg:province":"Noord-Brabant",
    "wof:name":"Claesen, I",
    "wof:placetype":"venue"
},
  "geometry": {"coordinates":[5.085152,51.578548],"type":"Point"}
}