{
  "type": "Feature",
  "properties": {
    "addr:full":"Buitenveldertseln 3840 Amsterdam Noord-Holland 1081 AA",
    "addr:housenumber":"3840",
    "addr:postcode":"1081 aa",
    "iso:country":"NL",
    "sg:address":"Buitenveldertseln 3840",
    "sg:city":"Amsterdam",
    "sg:orig_category":"Bloemen En Planten",
    "sg:phone":"+31 20 642 3217",
    "sg:postcode":"1081 AA",
    "sg:province":"Noord-Holland",
    "wof:name":"O?se",
    "wof:placetype":"venue"
},
  "geometry": {"coordinates":[4.86888,52.324619],"type":"Point"}
}