{
  "type": "Feature",
  "properties": {
    "addr:full":"Westfalenstr 30 Alkmaar Noord-Holland 1827 AZ",
    "addr:housenumber":"30",
    "addr:postcode":"1827 az",
    "addr:street":"Westfalenstr",
    "iso:country":"NL",
    "sg:address":"Westfalenstr 30",
    "sg:city":"Alkmaar",
    "sg:orig_category":"Administratie- En Boekhoudkantoren",
    "sg:phone":"+31 72 561 6903",
    "sg:postcode":"1827 AZ",
    "sg:province":"Noord-Holland",
    "wof:name":"Koper, T",
    "wof:placetype":"venue"
},
  "geometry": {"coordinates":[4.757321,52.667053],"type":"Point"}
}