{
  "type": "Feature",
  "properties": {
    "addr:full":"Prickwaert 93 Sliedrecht Zuid-Holland 3363 BB",
    "addr:housenumber":"93",
    "addr:postcode":"3363 bb",
    "addr:street":"Prickwaert",
    "iso:country":"NL",
    "sg:address":"Prickwaert 93",
    "sg:city":"Sliedrecht",
    "sg:orig_category":"Organisatiebureaus",
    "sg:phone":"+31 184 490 490",
    "sg:postcode":"3363 BB",
    "sg:province":"Zuid-Holland",
    "wof:name":"Ellen",
    "wof:placetype":"venue"
},
  "geometry": {"coordinates":[4.7591428757,51.8287315369],"type":"Point"}
}