{
  "type": "Feature",
  "properties": {
    "addr:full":"Reestr 18-20 Amsterdam Noord-Holland 1016 DN",
    "addr:housenumber":"18-20",
    "addr:postcode":"1016 dn",
    "iso:country":"NL",
    "sg:address":"Reestr 18-20",
    "sg:city":"Amsterdam",
    "sg:orig_category":"Kaarsen - Fabrieken En Groothandel",
    "sg:phone":"+31 20 626 5274",
    "sg:postcode":"1016 DN",
    "sg:province":"Noord-Holland",
    "wof:name":"Kramer E/ Pontifex",
    "wof:placetype":"venue"
},
  "geometry": {"coordinates":[4.8838410378,52.3725204468],"type":"Point"}
}