{
  "type": "Feature",
  "properties": {
    "addr:full":"Kortrykstr 10 Breda Noord-Brabant 4826 LX",
    "addr:housenumber":"10",
    "addr:postcode":"4826 lx",
    "addr:street":"Kortrykstr",
    "iso:country":"NL",
    "sg:address":"Kortrykstr 10",
    "sg:city":"Breda",
    "sg:orig_category":"Verpakkingen En Verpakkingsmaterialen",
    "sg:phone":"+31 76 587 3788",
    "sg:postcode":"4826 LX",
    "sg:province":"Noord-Brabant",
    "wof:name":"P & M Ned",
    "wof:placetype":"venue"
},
  "geometry": {"coordinates":[4.782989,51.607285],"type":"Point"}
}