{
  "type": "Feature",
  "properties": {
    "addr:full":"Tarthorst 481 Wageningen Gelderland 6708 HR",
    "addr:housenumber":"481",
    "addr:postcode":"6708 hr",
    "addr:street":"Tarthorst;Gelderland",
    "iso:country":"NL",
    "sg:address":"Tarthorst 481",
    "sg:city":"Wageningen",
    "sg:orig_category":"Diverse Opleidingen And Onderwijs",
    "sg:phone":"+31 317 417 049",
    "sg:postcode":"6708 HR",
    "sg:province":"Gelderland",
    "wof:name":"Anke Dillissen",
    "wof:placetype":"venue"
},
  "geometry": {"coordinates":[5.660578,51.979774],"type":"Point"}
}