{
  "type": "Feature",
  "properties": {
    "addr:full":"Janskerkhof 12 Utrecht Utrecht 3512 BL",
    "addr:housenumber":"12",
    "addr:postcode":"3512 bl",
    "addr:street":"Janskerkhof",
    "iso:country":"NL",
    "sg:address":"Janskerkhof 12",
    "sg:city":"Utrecht",
    "sg:orig_category":"Bedrijfs- And Managementsconsultants",
    "sg:phone":"+31 30 230 4254",
    "sg:postcode":"3512 BL",
    "sg:province":"Utrecht",
    "wof:name":"Hugli Pollock Read",
    "wof:placetype":"venue"
},
  "geometry": {"coordinates":[5.12276,52.093037],"type":"Point"}
}