{
  "type": "Feature",
  "properties": {
    "addr:full":"Noordsigt 16 Dordrecht Zuid-Holland 3319 WE",
    "addr:housenumber":"16",
    "addr:postcode":"3319 we",
    "addr:street":"Noordsigt",
    "iso:country":"NL",
    "sg:address":"Noordsigt 16",
    "sg:city":"Dordrecht",
    "sg:orig_category":"Glas",
    "sg:phone":"+31 78 621 1478",
    "sg:postcode":"3319 WE",
    "sg:province":"Zuid-Holland",
    "wof:name":"Vries, R De",
    "wof:placetype":"venue"
},
  "geometry": {"coordinates":[4.698483,51.800598],"type":"Point"}
}