{
  "type": "Feature",
  "properties": {
    "addr:full":"Atoomwg 1 Roosendaal North Brabant 4706 PN",
    "addr:housenumber":"1",
    "addr:postcode":"4706 pn",
    "addr:street":"Atoomwg",
    "iso:country":"NL",
    "sg:address":"Atoomwg 1",
    "sg:city":"Roosendaal",
    "sg:orig_category":"Kantoor- En Bedrijfsmeubelen",
    "sg:phone":"+31 165 560 542",
    "sg:postcode":"4706 PN",
    "sg:province":"North Brabant",
    "wof:name":"Inofec",
    "wof:placetype":"venue"
},
  "geometry": {"coordinates":[4.5010151863,51.5399208069],"type":"Point"}
}