{
  "type": "Feature",
  "properties": {
    "addr:full":"Kalkmarkt 8 Amsterdam North Holland 1011 BD",
    "addr:housenumber":"8",
    "addr:postcode":"1011 bd",
    "addr:street":"Kalkmarkt",
    "iso:country":"NL",
    "sg:address":"Kalkmarkt 8",
    "sg:city":"Amsterdam",
    "sg:orig_category":"Artsen - Huisartsen",
    "sg:phone":"+31 20 624 4600",
    "sg:postcode":"1011 BD",
    "sg:province":"North Holland",
    "wof:name":"Voorsluis-Spanhoff & L A A Viruly, F N",
    "wof:placetype":"venue"
},
  "geometry": {"coordinates":[4.906726,52.372746],"type":"Point"}
}