{
  "type": "Feature",
  "properties": {
    "addr:full":"De Velduil 12 Harlingen Friesland 8862 LP",
    "addr:housenumber":"12",
    "addr:postcode":"8862 lp",
    "addr:street":"De Velduil",
    "iso:country":"NL",
    "sg:address":"De Velduil 12",
    "sg:city":"Harlingen",
    "sg:orig_category":"Adviesbureaus Bedrijfsorganisatie",
    "sg:phone":"+31 517 431 415",
    "sg:postcode":"8862 LP",
    "sg:province":"Friesland",
    "wof:name":"Jonge, De",
    "wof:placetype":"venue"
},
  "geometry": {"coordinates":[5.43531,53.158783],"type":"Point"}
}