{
  "type": "Feature",
  "properties": {
    "addr:full":"De Wesenberg 2 Wijhe Overijssel 8131 TH",
    "addr:housenumber":"2",
    "addr:postcode":"8131 th",
    "addr:street":"De Wesenberg",
    "iso:country":"NL",
    "sg:address":"De Wesenberg 2",
    "sg:city":"Wijhe",
    "sg:orig_category":"Juridische Dienstverlening",
    "sg:phone":"+31 570 521 657",
    "sg:postcode":"8131 TH",
    "sg:province":"Overijssel",
    "wof:name":"Publiekrechtelijk Adviesburo Deunk",
    "wof:placetype":"venue"
},
  "geometry": {"coordinates":[6.188717,52.372932],"type":"Point"}
}