{
  "type": "Feature",
  "properties": {
    "addr:full":"Nieuwe Ginnekenstraat 12 Breda Noord-Brabant 4811 NR",
    "addr:housenumber":"12",
    "addr:postcode":"4811 nr",
    "addr:street":"Nieuwe Ginnekenstraat",
    "iso:country":"NL",
    "sg:address":"Nieuwe Ginnekenstraat 12",
    "sg:city":"Breda",
    "sg:orig_category":"Huishoudapparatuur, Televisies And Radio'S",
    "sg:phone":"+31 76 514 3752",
    "sg:postcode":"4811 NR",
    "sg:province":"Noord-Brabant",
    "wof:name":"Koelkasten Rooij Witgoedspeciaalzaak Van",
    "wof:placetype":"venue"
},
  "geometry": {"coordinates":[4.776753,51.582497],"type":"Point"}
}