{
  "type": "Feature",
  "properties": {
    "iso:country":"NL",
    "sg:address":"Weverstr 2",
    "sg:city":"Venray",
    "sg:orig_category":"Keukens",
    "sg:phone":"+31 478 583 249",
    "sg:postcode":"5801 SZ",
    "sg:province":"Limburg",
    "wof:name":"Liemar Bv",
    "wof:placetype":"venue"
},
  "geometry": {"coordinates":[5.961977,51.520733],"type":"Point"}
}