{
  "type": "Feature",
  "properties": {
    "addr:full":"Hoogstraat 4 Hasselt Overijssel 8061 HC",
    "addr:housenumber":"4",
    "addr:postcode":"8061 hc",
    "addr:street":"Hoogstraat",
    "iso:country":"NL",
    "sg:address":"Hoogstraat 4",
    "sg:city":"Hasselt",
    "sg:classifiers":[
        {
            "category":"Food & Beverages",
            "subcategory":"Fruits & Vegetables",
            "type":"Retail Goods"
        }
    ],
    "sg:phone":"+31 38 477 2233",
    "sg:postcode":"8061 HC",
    "sg:province":"Overijssel",
    "sg:tags":[
        "groenten"
    ],
    "wof:name":"Vof R. Robaard",
    "wof:placetype":"venue"
},
  "geometry": {"coordinates":[6.08891,52.590935],"type":"Point"}
}