{
  "type": "Feature",
  "properties": {
    "addr:full":"Arnhemsewg 144 Apeldoorn Gelderland 7335 DN",
    "addr:housenumber":"144",
    "addr:postcode":"7335 dn",
    "addr:street":"Gelderland",
    "iso:country":"NL",
    "sg:address":"Arnhemsewg 144",
    "sg:city":"Apeldoorn",
    "sg:orig_category":"Meubelen",
    "sg:phone":"+31 55 542 9772",
    "sg:postcode":"7335 DN",
    "sg:province":"Gelderland",
    "wof:name":"Kasten Studio Bv",
    "wof:placetype":"venue"
},
  "geometry": {"coordinates":[5.9592,52.200371],"type":"Point"}
}