{
  "type": "Feature",
  "properties": {
    "addr:full":"Javastr 49 Utrecht Utrecht 3531 PN",
    "addr:housenumber":"49",
    "addr:postcode":"3531 pn",
    "addr:street":"Javastr",
    "iso:country":"NL",
    "sg:address":"Javastr 49",
    "sg:city":"Utrecht",
    "sg:orig_category":"Vertaalbureaus",
    "sg:phone":"+31 30 293 7057",
    "sg:postcode":"3531 PN",
    "sg:province":"Utrecht",
    "wof:name":"Jong, De",
    "wof:placetype":"venue"
},
  "geometry": {"coordinates":[5.101846,52.091179],"type":"Point"}
}