{
  "type": "Feature",
  "properties": {
    "addr:full":"Byenmeent 7 Hilversum North Holland 1218 GB",
    "addr:housenumber":"7",
    "addr:postcode":"1218 gb",
    "addr:street":"Byenmeent",
    "iso:country":"NL",
    "sg:address":"Byenmeent 7",
    "sg:city":"Hilversum",
    "sg:orig_category":"Houtgroothandel",
    "sg:phone":"+31 35 693 7316",
    "sg:postcode":"1218 GB",
    "sg:province":"North Holland",
    "wof:name":"Ranisa Bv",
    "wof:placetype":"venue"
},
  "geometry": {"coordinates":[5.14097,52.270107],"type":"Point"}
}