{
  "type": "Feature",
  "properties": {
    "addr:full":"Steenwg 76 Sittard Limburg 6131 BH",
    "addr:housenumber":"76",
    "addr:postcode":"6131 bh",
    "addr:street":"Steenwg",
    "iso:country":"NL",
    "sg:address":"Steenwg 76",
    "sg:city":"Sittard",
    "sg:orig_category":"Modelbouw",
    "sg:phone":"+31 46 449 0149",
    "sg:postcode":"6131 BH",
    "sg:province":"Limburg",
    "wof:name":"Vleugels",
    "wof:placetype":"venue"
},
  "geometry": {"coordinates":[5.861892,51.000973],"type":"Point"}
}