{
  "type": "Feature",
  "properties": {
    "addr:full":"Balboastr 20C Amsterdam Noord-Holland 1057 VW",
    "addr:housenumber":"20c",
    "addr:postcode":"1057 vw",
    "addr:street":"Balboastr",
    "iso:country":"NL",
    "sg:address":"Balboastr 20C",
    "sg:city":"Amsterdam",
    "sg:orig_category":"Administratie- En Boekhoudkantoren",
    "sg:phone":"+31 20 412 5661",
    "sg:postcode":"1057 VW",
    "sg:province":"Noord-Holland",
    "wof:name":"Kok, Louis",
    "wof:placetype":"venue"
},
  "geometry": {"coordinates":[4.855018,52.369373],"type":"Point"}
}