{
  "type": "Feature",
  "properties": {
    "addr:full":"Slachthuisstr 4 Zaandam Noord-Holland 1508 ED",
    "addr:housenumber":"4",
    "addr:postcode":"1508 ed",
    "addr:street":"Slachthuisstr",
    "iso:country":"NL",
    "sg:address":"Slachthuisstr 4",
    "sg:city":"Zaandam",
    "sg:orig_category":"Wasmachines En Wasdrogers",
    "sg:phone":"+31 75 617 0859",
    "sg:postcode":"1508 ED",
    "sg:province":"Noord-Holland",
    "wof:name":"Vet",
    "wof:placetype":"venue"
},
  "geometry": {"coordinates":[4.8159489632,52.4603691101],"type":"Point"}
}