{
  "type": "Feature",
  "properties": {
    "addr:full":"Soestdijkseweg Zuid 280 Bilthoven Utrecht 3721 AK",
    "addr:housenumber":"280",
    "addr:postcode":"3721 ak",
    "addr:street":"Soestdijkseweg Zuid",
    "iso:country":"NL",
    "sg:address":"Soestdijkseweg Zuid 280",
    "sg:city":"Bilthoven",
    "sg:orig_category":"Makelaars In Onroerend Goed",
    "sg:phone":"+31 30 229 0079",
    "sg:postcode":"3721 AK",
    "sg:province":"Utrecht",
    "wof:name":"Hol & Molenbeek Bilthoven Bv",
    "wof:placetype":"venue"
},
  "geometry": {"coordinates":[5.204504,52.128773],"type":"Point"}
}