{
  "type": "Feature",
  "properties": {
    "addr:full":"Westluidensestraat 49 Tiel Gelderland 4001 NE",
    "addr:housenumber":"49;4001",
    "addr:street":"Westluidensestraat;Gelderland;Ne",
    "iso:country":"NL",
    "sg:address":"Westluidensestraat 49",
    "sg:city":"Tiel",
    "sg:classifiers":[
        {
            "category":"Fast Food",
            "type":"Food & Drink"
        }
    ],
    "sg:phone":"+31 344 615 702",
    "sg:postcode":"4001 NE",
    "sg:province":"Gelderland",
    "sg:tags":[
        "afhaal",
        "restaurant"
    ],
    "wof:name":"Chin. Ind. Jap. Restaurant Lotus",
    "wof:placetype":"venue"
},
  "geometry": {"coordinates":[5.437597,51.885338],"type":"Point"}
}