{
  "type": "Feature",
  "properties": {
    "iso:country":"NL",
    "sg:address":"Sweerts De Landasstraat 42",
    "sg:city":"Arnhem",
    "sg:orig_category":"Advocaten And Juridische Adviseurs",
    "sg:phone":"+31 26 442 0192",
    "sg:postcode":"6814 DG",
    "sg:province":"Gelderland",
    "wof:name":"Advocatenkantoor Mr R C Tubbergen",
    "wof:placetype":"venue"
},
  "geometry": {"coordinates":[5.902357,51.986137],"type":"Point"}
}