{
  "type": "Feature",
  "properties": {
    "addr:full":"Bree 13 Rotterdam Zuid-Holland 3074 BA",
    "addr:housenumber":"13",
    "addr:postcode":"3074 ba",
    "addr:street":"Bree",
    "iso:country":"NL",
    "sg:address":"Bree 13",
    "sg:city":"Rotterdam",
    "sg:orig_category":"Automaterialen En Gereedschappen",
    "sg:phone":"+31 10 419 1898",
    "sg:postcode":"3074 BA",
    "sg:province":"Zuid-Holland",
    "wof:name":"Delmee",
    "wof:placetype":"venue"
},
  "geometry": {"coordinates":[4.512702,51.890499],"type":"Point"}
}