{
  "type": "Feature",
  "properties": {
    "addr:full":"Leijsenhoek 37 Oosterhout Nb North Brabant 4901 ER",
    "addr:housenumber":"37;nb",
    "addr:postcode":"4901 er",
    "addr:street":"Leijsenhoek",
    "iso:country":"NL",
    "sg:address":"Leijsenhoek 37",
    "sg:city":"Oosterhout Nb",
    "sg:orig_category":"Kappers",
    "sg:phone":"+31 162 458 754",
    "sg:postcode":"4901 ER",
    "sg:province":"North Brabant",
    "wof:name":"Herenkapsalon Richard",
    "wof:placetype":"venue"
},
  "geometry": {"coordinates":[4.8639230728,51.6451148987],"type":"Point"}
}