{
  "type": "Feature",
  "properties": {
    "iso:country":"NL",
    "sg:address":"Woudwg 1",
    "sg:city":"Teuge",
    "sg:orig_category":"Wijnkoperijen En -Groothandel",
    "sg:phone":"+31 55 578 8789",
    "sg:postcode":"7395 SH",
    "sg:province":"Gelderland",
    "wof:name":"Kaapkelder Bv",
    "wof:placetype":"venue"
},
  "geometry": {"coordinates":[6.0413360596,52.2310905457],"type":"Point"}
}