{
  "type": "Feature",
  "properties": {
    "addr:full":"Schoterlandseweg 82 Oudeschoot Provincie Friesland 8451 KD",
    "addr:housenumber":"82",
    "addr:postcode":"8451 kd",
    "addr:street":"Schoterlandseweg;Provincie Friesland",
    "iso:country":"NL",
    "sg:address":"Schoterlandseweg 82",
    "sg:city":"Oudeschoot",
    "sg:orig_category":"Hoefdierhouderijen",
    "sg:phone":"+31 513 631 837",
    "sg:postcode":"8451 KD",
    "sg:province":"Provincie Friesland",
    "wof:name":"T. Smeding",
    "wof:placetype":"venue"
},
  "geometry": {"coordinates":[5.973813,52.932743],"type":"Point"}
}