{
  "type": "Feature",
  "properties": {
    "addr:full":"Hazeldonks Zandwg 28D Zevenbergen Noord-Brabant 4762 AL",
    "addr:housenumber":"28d",
    "addr:postcode":"4762 al",
    "iso:country":"NL",
    "sg:address":"Hazeldonks Zandwg 28D",
    "sg:city":"Zevenbergen",
    "sg:orig_category":"Geluidsinstallaties - Verhuur",
    "sg:phone":"+31 168 325 722",
    "sg:postcode":"4762 AL",
    "sg:province":"Noord-Brabant",
    "wof:name":"Dekkers",
    "wof:placetype":"venue"
},
  "geometry": {"coordinates":[4.613406,51.64072],"type":"Point"}
}