{
  "type": "Feature",
  "properties": {
    "iso:country":"NL",
    "sg:address":"Korvezeestr 142",
    "sg:city":"Delft",
    "sg:orig_category":"Verhuizingen",
    "sg:phone":"+31 15 261 2274",
    "sg:postcode":"2628 DG",
    "sg:province":"Zuid-Holland",
    "wof:name":"Sanatan Dharm",
    "wof:placetype":"venue"
},
  "geometry": {"coordinates":[4.372172,51.99791],"type":"Point"}
}