{
  "type": "Feature",
  "properties": {
    "addr:full":"Korvezeestr 142 Delft Zuid-Holland 2628 DG",
    "addr:housenumber":"142",
    "addr:postcode":"delft;2628 dg",
    "iso:country":"NL",
    "sg:address":"Korvezeestr 142",
    "sg:city":"Delft",
    "sg:orig_category":"Verhuizingen",
    "sg:phone":"+31 15 261 2274",
    "sg:postcode":"2628 DG",
    "sg:province":"Zuid-Holland",
    "wof:name":"Sanatan Dharm",
    "wof:placetype":"venue"
},
  "geometry": {"coordinates":[4.372172,51.99791],"type":"Point"}
}