{
  "type": "Feature",
  "properties": {
    "addr:full":"Kempenaar 1-1 Lelystad NL. 8242 BA",
    "addr:postcode":"8242 ba",
    "addr:street":"Kempenaar 1-1;Nl.",
    "iso:country":"NL",
    "sg:address":"Kempenaar 1-1",
    "sg:city":"Lelystad",
    "sg:orig_category":"Autoverhuur",
    "sg:phone":"+31 320 232 929",
    "sg:postcode":"8242 BA",
    "sg:province":"NL.",
    "sg:website":"http://www.budget.nl",
    "wof:name":"Budget Rent A Car",
    "wof:placetype":"venue"
},
  "geometry": {"coordinates":[5.457547,52.519459],"type":"Point"}
}