{
  "type": "Feature",
  "properties": {
    "iso:country":"NL",
    "sg:address":"Kzr Ottostr 8",
    "sg:city":"Bussum",
    "sg:orig_category":"Boeken En Tijdschriften",
    "sg:phone":"+31 35 691 5571",
    "sg:postcode":"1402 VS",
    "sg:province":"Noord-Holland",
    "wof:name":"Random House Int",
    "wof:placetype":"venue"
},
  "geometry": {"coordinates":[5.178504,52.276268],"type":"Point"}
}