{
  "type": "Feature",
  "properties": {
    "addr:full":"Langenhorst 30 Alphen A/D Rijn South Holland 2402 PX",
    "addr:housenumber":"30",
    "addr:postcode":"2402 px",
    "addr:street":"Langenhorst",
    "iso:country":"NL",
    "sg:address":"Langenhorst 30",
    "sg:city":"Alphen A/D Rijn",
    "sg:orig_category":"Juridische Dienstverlening",
    "sg:phone":"+31 172 435 143",
    "sg:postcode":"2402 PX",
    "sg:province":"South Holland",
    "wof:name":"Mr. J.R. Juriaans",
    "wof:placetype":"venue"
},
  "geometry": {"coordinates":[4.672206,52.152828],"type":"Point"}
}