{
  "type": "Feature",
  "properties": {
    "iso:country":"NL",
    "sg:address":"Hoogte Kadk 32",
    "sg:city":"Amsterdam",
    "sg:orig_category":"Filmstudio'S En -Productie",
    "sg:phone":"+31 20 620 0785",
    "sg:postcode":"1018 BM",
    "sg:province":"North Holland",
    "sg:website":"http://www.rebelfilm.com",
    "wof:name":"Rebel",
    "wof:placetype":"venue"
},
  "geometry": {"coordinates":[4.913396,52.369869],"type":"Point"}
}