{
  "type": "Feature",
  "properties": {
    "addr:full":"Voorstraat 28 Nieuweschans Groningen 9693 EG",
    "addr:housenumber":"28",
    "addr:postcode":"9693 eg",
    "addr:street":"Voorstraat",
    "iso:country":"NL",
    "sg:address":"Voorstraat 28",
    "sg:city":"Nieuweschans",
    "sg:orig_category":"Bloemen And Planten",
    "sg:phone":"+31 597 521 920",
    "sg:postcode":"9693 EG",
    "sg:province":"Groningen",
    "wof:name":"De Oude Gevel",
    "wof:placetype":"venue"
},
  "geometry": {"coordinates":[7.20761,53.180046],"type":"Point"}
}