{
  "type": "Feature",
  "properties": {
    "addr:full":"Scheiwg 8 Gemert North Brabant 5421 XL",
    "addr:housenumber":"8",
    "addr:postcode":"5421 xl",
    "addr:street":"Scheiwg",
    "iso:country":"NL",
    "sg:address":"Scheiwg 8",
    "sg:city":"Gemert",
    "sg:orig_category":"Verhuur",
    "sg:phone":"+31 492 363 657",
    "sg:postcode":"5421 XL",
    "sg:province":"North Brabant",
    "wof:name":"Opheij, Ad",
    "wof:placetype":"venue"
},
  "geometry": {"coordinates":[5.706314,51.566216],"type":"Point"}
}