{
  "type": "Feature",
  "properties": {
    "addr:full":"Keizersgr 606 Amsterdam Noord-Holland 1017 EP",
    "addr:housenumber":"606",
    "addr:postcode":"1017 ep",
    "iso:country":"NL",
    "sg:address":"Keizersgr 606",
    "sg:city":"Amsterdam",
    "sg:orig_category":"Adviesbureaus Bedrijfsorganisatie",
    "sg:phone":"+31 20 638 0308",
    "sg:postcode":"1017 EP",
    "sg:province":"Noord-Holland",
    "sg:website":"http://www.l-h.com/waarzit.htm",
    "wof:name":"Leupen & Hagedoorn",
    "wof:placetype":"venue"
},
  "geometry": {"coordinates":[4.890004,52.363838],"type":"Point"}
}