{
  "type": "Feature",
  "properties": {
    "addr:full":"Stationsweg 32 Wezep Gelderland 8091 AD",
    "addr:housenumber":"32",
    "addr:postcode":"8091 ad",
    "addr:street":"Stationsweg",
    "iso:country":"NL",
    "sg:address":"Stationsweg 32",
    "sg:city":"Wezep",
    "sg:classifiers":[
        {
            "category":"Fast Food",
            "type":"Food & Drink"
        }
    ],
    "sg:phone":"+31 38 376 2012",
    "sg:postcode":"8091 AD",
    "sg:province":"Gelderland",
    "sg:tags":[
        "afhaal",
        "restaurant"
    ],
    "wof:name":"Vof Ijssalon-Cafetaria De Oranjeboom",
    "wof:placetype":"venue"
},
  "geometry": {"coordinates":[5.995052,52.460938],"type":"Point"}
}