{
  "type": "Feature",
  "properties": {
    "addr:full":"Lindenheuvel 14 Hilversum North Holland 1217 JX",
    "addr:housenumber":"14",
    "addr:postcode":"1217 jx",
    "addr:street":"Lindenheuvel",
    "iso:country":"NL",
    "sg:address":"Lindenheuvel 14",
    "sg:city":"Hilversum",
    "sg:orig_category":"Kunststofverpakkingen Fab",
    "sg:phone":"+31 35 621 4775",
    "sg:postcode":"1217 JX",
    "sg:province":"North Holland",
    "wof:name":"Koopmans Verpakkingen Bv",
    "wof:placetype":"venue"
},
  "geometry": {"coordinates":[5.161511,52.229019],"type":"Point"}
}