{
  "type": "Feature",
  "properties": {
    "addr:full":"Adriaan Van Ostadestraat 13 Rijssen NL.08 7462 BS",
    "addr:housenumber":"13;nl.08",
    "addr:postcode":"7462 bs",
    "addr:street":"Adriaan Van Ostadestraat",
    "iso:country":"NL",
    "sg:address":"Adriaan Van Ostadestraat 13",
    "sg:city":"Rijssen",
    "sg:orig_category":"Koeriersdiensten",
    "sg:phone":"+31 548 518 518",
    "sg:postcode":"7462 BS",
    "sg:province":"NL.08",
    "wof:name":"Koeriersdienst Rijssen",
    "wof:placetype":"venue"
},
  "geometry": {"coordinates":[6.519485,52.298573],"type":"Point"}
}