{
  "type": "Feature",
  "properties": {
    "addr:full":"Nachtegaalstr 31 Haarlem North Holland 2025 VG",
    "addr:housenumber":"31",
    "addr:postcode":"2025 vg",
    "addr:street":"Nachtegaalstr",
    "iso:country":"NL",
    "sg:address":"Nachtegaalstr 31",
    "sg:city":"Haarlem",
    "sg:orig_category":"Voegwerken",
    "sg:phone":"+31 6 53316088",
    "sg:postcode":"2025 VG",
    "sg:province":"North Holland",
    "wof:name":"Rooijen & Van Dijk Vof, Van",
    "wof:placetype":"venue"
},
  "geometry": {"coordinates":[4.653167,52.413628],"type":"Point"}
}