{
  "type": "Feature",
  "properties": {
    "addr:full":"Hoofdwg 15 Schildwolde Groningen 9626 AA",
    "addr:housenumber":"15",
    "addr:postcode":"9626 aa",
    "addr:street":"Hoofdwg",
    "iso:country":"NL",
    "sg:address":"Hoofdwg 15",
    "sg:city":"Schildwolde",
    "sg:orig_category":"Schoenen",
    "sg:phone":"+31 598 421 276",
    "sg:postcode":"9626 AA",
    "sg:province":"Groningen",
    "wof:name":"Helm, Van Der",
    "wof:placetype":"venue"
},
  "geometry": {"coordinates":[6.806822,53.222153],"type":"Point"}
}