{
  "type": "Feature",
  "properties": {
    "addr:full":"Zuiddk 96A Zaandam Noord-Holland 1501 CP",
    "addr:housenumber":"96a",
    "addr:postcode":"1501 cp",
    "addr:street":"Zuiddk",
    "iso:country":"NL",
    "sg:address":"Zuiddk 96A",
    "sg:city":"Zaandam",
    "sg:orig_category":"Kappers",
    "sg:phone":"+31 75 614 1420",
    "sg:postcode":"1501 CP",
    "sg:province":"Noord-Holland",
    "wof:name":"Kapper, De",
    "wof:placetype":"venue"
},
  "geometry": {"coordinates":[4.8314580917,52.4364280701],"type":"Point"}
}