{
  "type": "Feature",
  "properties": {
    "addr:full":"Zeestr 135 Zevenbergen Noord-Brabant 4761 HJ",
    "addr:housenumber":"135",
    "addr:postcode":"4761 hj",
    "addr:street":"Zevenbergen",
    "iso:country":"NL",
    "sg:address":"Zeestr 135",
    "sg:city":"Zevenbergen",
    "sg:orig_category":"Schoonheidsinstituten",
    "sg:phone":"+31 168 328 625",
    "sg:postcode":"4761 HJ",
    "sg:province":"Noord-Brabant",
    "wof:name":"Face",
    "wof:placetype":"venue"
},
  "geometry": {"coordinates":[4.597653,51.650658],"type":"Point"}
}