{
  "type": "Feature",
  "properties": {
    "iso:country":"NL",
    "sg:address":"Van De Takstraat 83",
    "sg:city":"Rotterdam",
    "sg:orig_category":"Kappers",
    "sg:phone":"+31 10 412 4593",
    "sg:postcode":"3071 LK",
    "sg:province":"Zuid-Holland",
    "wof:name":"Kapsalon Lisan",
    "wof:placetype":"venue"
},
  "geometry": {"coordinates":[4.5032701492,51.9105911255],"type":"Point"}
}