{
  "type": "Feature",
  "properties": {
    "addr:full":"Nic Stellingwerffstraat 36 Medemblik North Holland 1671 EP",
    "addr:housenumber":"36",
    "addr:postcode":"1671 ep",
    "addr:street":"Stellingwerffstraat",
    "iso:country":"NL",
    "sg:address":"Nic Stellingwerffstraat 36",
    "sg:city":"Medemblik",
    "sg:orig_category":"Diverse Dierenfokkers",
    "sg:phone":"+31 227 544 165",
    "sg:postcode":"1671 EP",
    "sg:province":"North Holland",
    "wof:name":"C Zonneveld",
    "wof:placetype":"venue"
},
  "geometry": {"coordinates":[5.099989,52.768364],"type":"Point"}
}