{
  "type": "Feature",
  "properties": {
    "addr:full":"Nieuweweg 15 Hoogkarspel Noord-Holland 1616 BA",
    "addr:housenumber":"15",
    "addr:postcode":"1616 ba",
    "addr:street":"Nieuweweg",
    "iso:country":"NL",
    "sg:address":"Nieuweweg 15",
    "sg:city":"Hoogkarspel",
    "sg:classifiers":[
        {
            "category":"Bakery",
            "type":"Food & Drink"
        }
    ],
    "sg:phone":"+31 228 561 951",
    "sg:postcode":"1616 BA",
    "sg:province":"Noord-Holland",
    "sg:tags":[
        "brood",
        "banket"
    ],
    "wof:name":"Echte Bakker Ko En Trudy Koenis",
    "wof:placetype":"venue"
},
  "geometry": {"coordinates":[5.177239,52.693493],"type":"Point"}
}