{
  "type": "Feature",
  "properties": {
    "addr:full":"Groenewg 25 Ermelo Gelderland 3851 KA",
    "addr:housenumber":"25",
    "addr:postcode":"3851 ka",
    "addr:street":"Groenewg;Gelderland",
    "iso:country":"NL",
    "sg:address":"Groenewg 25",
    "sg:city":"Ermelo",
    "sg:classifiers":[
        {
            "category":"Retail",
            "subcategory":"Auto Repair",
            "type":"Services"
        }
    ],
    "sg:phone":"+31 341 562 370",
    "sg:postcode":"3851 KA",
    "sg:province":"Gelderland",
    "sg:tags":[
        "garage"
    ],
    "wof:name":"Berg, Gert Van Den",
    "wof:placetype":"venue"
},
  "geometry": {"coordinates":[5.619404,52.298378],"type":"Point"}
}