{
  "type": "Feature",
  "properties": {
    "addr:full":"Mercatorpln 43-45 Apeldoorn Gelderland 7316 HJ",
    "addr:housenumber":"43-45",
    "addr:postcode":"7316 hj",
    "addr:street":"Gelderland",
    "iso:country":"NL",
    "sg:address":"Mercatorpln 43-45",
    "sg:city":"Apeldoorn",
    "sg:orig_category":"Zonnebank- En Solariumcentra",
    "sg:phone":"+31 55 521 1934",
    "sg:postcode":"7316 HJ",
    "sg:province":"Gelderland",
    "wof:name":"Ergoline Body & Suncenter",
    "wof:placetype":"venue"
},
  "geometry": {"coordinates":[5.959923,52.229465],"type":"Point"}
}