{
  "type": "Feature",
  "properties": {
    "iso:country":"NL",
    "sg:address":"Debussystr 29",
    "sg:city":"Culemborg",
    "sg:orig_category":"Webdesign Bureaus",
    "sg:phone":"+31 345 534 234",
    "sg:postcode":"4102 AR",
    "sg:province":"Gelderland",
    "sg:website":"http://www.aemotion.com",
    "wof:name":"Aemotion",
    "wof:placetype":"venue"
},
  "geometry": {"coordinates":[5.236623764,51.9526519775],"type":"Point"}
}