{
  "type": "Feature",
  "properties": {
    "iso:country":"NL",
    "sg:address":"Knibbelwg 24",
    "sg:city":"Zevenhuizen Zh",
    "sg:orig_category":"Bloemen En Planten",
    "sg:phone":"+31 180 631 023",
    "sg:postcode":"2761 JE",
    "sg:province":"Zuid-Holland",
    "wof:name":"Orchicultura Bv",
    "wof:placetype":"venue"
},
  "geometry": {"coordinates":[4.597704,52.010693],"type":"Point"}
}