{
  "type": "Feature",
  "properties": {
    "addr:full":"Wilhelminastraat 1 Rosmalen Noord-Brabant 5246 XA",
    "addr:housenumber":"1",
    "addr:postcode":"5246 xa",
    "addr:street":"Wilhelminastraat",
    "iso:country":"NL",
    "sg:address":"Wilhelminastraat 1",
    "sg:city":"Rosmalen",
    "sg:orig_category":"Boekhouders",
    "sg:phone":"+31 73 644 1508",
    "sg:postcode":"5246 XA",
    "sg:province":"Noord-Brabant",
    "wof:name":"R. Coppens Administratie En Fiscaal Adviseur",
    "wof:placetype":"venue"
},
  "geometry": {"coordinates":[5.345334,51.703499],"type":"Point"}
}