{
  "type": "Feature",
  "properties": {
    "iso:country":"NL",
    "sg:address":"Admiraliteitskd 96",
    "sg:city":"Rotterdam",
    "sg:orig_category":"Zonweringen",
    "sg:phone":"+31 10 411 1444",
    "sg:postcode":"3063 EH",
    "sg:province":"Zuid-Holland",
    "wof:name":"Europoort Bv",
    "wof:placetype":"venue"
},
  "geometry": {"coordinates":[4.499876,51.922325],"type":"Point"}
}