{
  "type": "Feature",
  "properties": {
    "addr:full":"Rijksstraatweg 56 Duivendrecht North Holland 1115 AT",
    "addr:housenumber":"56",
    "addr:postcode":"1115",
    "addr:street":"Rijksstraatweg",
    "iso:country":"NL",
    "sg:address":"Rijksstraatweg 56",
    "sg:city":"Duivendrecht",
    "sg:orig_category":"Politie",
    "sg:phone":"+31 900 8844",
    "sg:postcode":"1115 AT",
    "sg:province":"North Holland",
    "wof:name":"Politie Amsterdam Amstelland Wijkbureau",
    "wof:placetype":"venue"
},
  "geometry": {"coordinates":[4.940834,52.332352],"type":"Point"}
}