{
  "type": "Feature",
  "properties": {
    "addr:full":"Nieuwendk 112 Apeldoorn Gelderland 7311 RM",
    "addr:housenumber":"112",
    "addr:postcode":"7311 rm",
    "addr:street":"Gelderland",
    "iso:country":"NL",
    "sg:address":"Nieuwendk 112",
    "sg:city":"Apeldoorn",
    "sg:orig_category":"Fotografie Reclame En Mode",
    "sg:phone":"+31 55 521 5522",
    "sg:postcode":"7311 RM",
    "sg:province":"Gelderland",
    "wof:name":"Gewe",
    "wof:placetype":"venue"
},
  "geometry": {"coordinates":[5.965563,52.210339],"type":"Point"}
}