{
  "type": "Feature",
  "properties": {
    "addr:full":"Wormerwg 1 Almere Flevoland 1311 XA",
    "addr:housenumber":"1",
    "addr:postcode":"1311 xa",
    "addr:street":"Wormerwg;Flevoland",
    "iso:country":"NL",
    "sg:address":"Wormerwg 1",
    "sg:city":"Almere",
    "sg:classifiers":[
        {
            "category":"Wholesale",
            "subcategory":"Meat",
            "type":"Manufacturing & Wholesale Goods"
        }
    ],
    "sg:phone":"+31 36 538 7333",
    "sg:postcode":"1311 XA",
    "sg:province":"Flevoland",
    "sg:tags":[
        "regeltechniek",
        "en",
        "meet-"
    ],
    "sg:website":"http://www.alfatechniek.nl",
    "wof:name":"Alfa Techniek",
    "wof:placetype":"venue"
},
  "geometry": {"coordinates":[5.17381,52.364685],"type":"Point"}
}