{
  "type": "Feature",
  "properties": {
    "addr:full":"Korianderveld 6 Schiedam Zuid-Holland 3124 CC",
    "addr:housenumber":"6",
    "addr:postcode":"3124 cc",
    "addr:street":"Korianderveld",
    "iso:country":"NL",
    "sg:address":"Korianderveld 6",
    "sg:city":"Schiedam",
    "sg:orig_category":"Binnenhuisarchitecten",
    "sg:phone":"+31 10 247 0411",
    "sg:postcode":"3124 CC",
    "sg:province":"Zuid-Holland",
    "wof:name":"Don Interieur Architectuur",
    "wof:placetype":"venue"
},
  "geometry": {"coordinates":[4.378613,51.945244],"type":"Point"}
}