{
  "type": "Feature",
  "properties": {
    "iso:country":"NL",
    "sg:address":"Ravenswade 98",
    "sg:city":"Nieuwegein",
    "sg:orig_category":"Partyservice",
    "sg:phone":"+31 30 284 9191",
    "sg:postcode":"3439 LD",
    "sg:province":"Utrecht",
    "sg:website":"http://www.grandcatering.nl",
    "wof:name":"Grand Catering",
    "wof:placetype":"venue"
},
  "geometry": {"coordinates":[5.115413,52.050537],"type":"Point"}
}