{
  "type": "Feature",
  "properties": {
    "addr:full":"Knikbloem 27 Rotterdam South Holland 3068 AD",
    "addr:housenumber":"27",
    "addr:postcode":"3068 ad",
    "addr:street":"Knikbloem",
    "iso:country":"NL",
    "sg:address":"Knikbloem 27",
    "sg:city":"Rotterdam",
    "sg:orig_category":"Onroerende Goederen",
    "sg:phone":"+31 6 51266614",
    "sg:postcode":"3068 AD",
    "sg:province":"South Holland",
    "wof:name":"Home Improvement Bv",
    "wof:placetype":"venue"
},
  "geometry": {"coordinates":[4.534711,51.95528],"type":"Point"}
}