{
  "type": "Feature",
  "properties": {
    "addr:full":"Het Spyk 4 Huizen Noord-Holland 1274 AX",
    "addr:housenumber":"4",
    "addr:postcode":"1274 ax",
    "addr:street":"Het Spyk",
    "iso:country":"NL",
    "sg:address":"Het Spyk 4",
    "sg:city":"Huizen",
    "sg:orig_category":"Onderhoudswerken",
    "sg:phone":"+31 35 525 2133",
    "sg:postcode":"1274 AX",
    "sg:province":"Noord-Holland",
    "wof:name":"Nagel, P V",
    "wof:placetype":"venue"
},
  "geometry": {"coordinates":[5.273543,52.303356],"type":"Point"}
}