{
  "type": "Feature",
  "properties": {
    "addr:full":"Zweringwg 210 Enschede Overijssel 7545 DA",
    "addr:housenumber":"210",
    "addr:postcode":"7545 da",
    "iso:country":"NL",
    "sg:address":"Zweringwg 210",
    "sg:city":"Enschede",
    "sg:classifiers":[
        {
            "category":"Food & Beverages",
            "subcategory":"Bakery",
            "type":"Retail Goods"
        }
    ],
    "sg:phone":"+31 53 431 0892",
    "sg:postcode":"7545 DA",
    "sg:province":"Overijssel",
    "sg:tags":[
        "pizza"
    ],
    "wof:name":"Samassi",
    "wof:placetype":"venue"
},
  "geometry": {"coordinates":[6.862569,52.210262],"type":"Point"}
}