{
  "type": "Feature",
  "properties": {
    "addr:full":"Klijne Meer 53 Vinkeveen Utrecht 3645 WR",
    "addr:housenumber":"53",
    "addr:postcode":"3645 wr",
    "addr:street":"Klijne Meer",
    "iso:country":"NL",
    "sg:address":"Klijne Meer 53",
    "sg:city":"Vinkeveen",
    "sg:orig_category":"Pleziervaartuigen And Reparatie",
    "sg:phone":"+31 297 262 416",
    "sg:postcode":"3645 WR",
    "sg:province":"Utrecht",
    "wof:name":"Jachtexpertise",
    "wof:placetype":"venue"
},
  "geometry": {"coordinates":[4.926425,52.207718],"type":"Point"}
}