{
  "type": "Feature",
  "properties": {
    "iso:country":"NL",
    "sg:address":"Kastanjelaan 72-74",
    "sg:city":"Bergen Op Zoom",
    "sg:classifiers":[
        {
            "category":"Fast Food",
            "type":"Food & Drink"
        }
    ],
    "sg:phone":"+31 164 255 774",
    "sg:postcode":"4621 HH",
    "sg:province":"North Brabant",
    "sg:tags":[
        "afhaal",
        "restaurant"
    ],
    "wof:name":"Restaria En Partyservice `T Vijfde",
    "wof:placetype":"venue"
},
  "geometry": {"coordinates":[4.298699,51.492119],"type":"Point"}
}