{
  "type": "Feature",
  "properties": {
    "addr:full":"Vlamingstr 19 S Gravenhage Zuid-Holland 2511 AZ",
    "addr:housenumber":"19;gravenhage",
    "addr:postcode":"2511 az",
    "addr:street":"Vlamingstr;S",
    "iso:country":"NL",
    "sg:address":"Vlamingstr 19",
    "sg:city":"S Gravenhage",
    "sg:orig_category":"Sportschoenen - Winkels",
    "sg:phone":"+31 70 392 7383",
    "sg:postcode":"2511 AZ",
    "sg:province":"Zuid-Holland",
    "wof:name":"Coach",
    "wof:placetype":"venue"
},
  "geometry": {"coordinates":[4.31627,52.07896],"type":"Point"}
}