{
  "type": "Feature",
  "properties": {
    "addr:full":"Wijngaardstraat 1 Goes Zeeland 4461 DA",
    "addr:housenumber":"1",
    "addr:postcode":"4461 da",
    "addr:street":"Wijngaardstraat",
    "iso:country":"NL",
    "sg:address":"Wijngaardstraat 1",
    "sg:city":"Goes",
    "sg:orig_category":"Binnenhuisarchitecten",
    "sg:phone":"+31 113 215 505",
    "sg:postcode":"4461 DA",
    "sg:province":"Zeeland",
    "wof:name":"Firma F.J. Boone",
    "wof:placetype":"venue"
},
  "geometry": {"coordinates":[-83.914169,39.768833],"type":"Point"}
}