{
  "type": "Feature",
  "properties": {
    "addr:full":"Boerhaaveln 13 Barendrecht South Holland 2992 KB",
    "addr:housenumber":"13",
    "addr:postcode":"2992 kb",
    "addr:street":"Boerhaaveln",
    "iso:country":"NL",
    "sg:address":"Boerhaaveln 13",
    "sg:city":"Barendrecht",
    "sg:orig_category":"Kappers",
    "sg:phone":"+31 180 618 429",
    "sg:postcode":"2992 KB",
    "sg:province":"South Holland",
    "wof:name":"F+T",
    "wof:placetype":"venue"
},
  "geometry": {"coordinates":[4.5406398773,51.8531761169],"type":"Point"}
}