{
  "type": "Feature",
  "properties": {
    "addr:full":"Albrechtlaan 14 Bussum Noord-Holland 1404 AK",
    "addr:housenumber":"14",
    "addr:postcode":"1404 ak",
    "addr:street":"Albrechtlaan",
    "iso:country":"NL",
    "sg:address":"Albrechtlaan 14",
    "sg:city":"Bussum",
    "sg:classifiers":[
        {
            "category":"Travel",
            "subcategory":"Hotels & Motels",
            "type":"Entertainment"
        }
    ],
    "sg:phone":"+31 35 694 8608",
    "sg:postcode":"1404 AK",
    "sg:province":"Noord-Holland",
    "wof:name":"Kamerverhuurbedrijf Elif En Dennenoord",
    "wof:placetype":"venue"
},
  "geometry": {"coordinates":[5.158568,52.280811],"type":"Point"}
}