{
  "type": "Feature",
  "properties": {
    "addr:full":"Abrikozengaard 13 Wijk Bij Duurstede Utrecht 3962 HS",
    "addr:housenumber":"13",
    "addr:postcode":"3962 hs",
    "addr:street":"Abrikozengaard",
    "iso:country":"NL",
    "sg:address":"Abrikozengaard 13",
    "sg:city":"Wijk Bij Duurstede",
    "sg:orig_category":"Wasserettes And Stomerijen",
    "sg:phone":"+31 343 572 960",
    "sg:postcode":"3962 HS",
    "sg:province":"Utrecht",
    "wof:name":"Van Lunssen",
    "wof:placetype":"venue"
},
  "geometry": {"coordinates":[5.3433179855,51.9807014465],"type":"Point"}
}