{
  "type": "Feature",
  "properties": {
    "addr:full":"Het Slot 35 Bunnik Utrecht 3981 KB",
    "addr:housenumber":"35",
    "addr:postcode":"3981 kb",
    "addr:street":"Het Slot",
    "iso:country":"NL",
    "sg:address":"Het Slot 35",
    "sg:city":"Bunnik",
    "sg:classifiers":[
        {
            "category":"Food & Beverages",
            "subcategory":"Bakery",
            "type":"Retail Goods"
        }
    ],
    "sg:phone":"+31 30 656 1371",
    "sg:postcode":"3981 KB",
    "sg:province":"Utrecht",
    "sg:tags":[
        "brood",
        "en",
        "banket"
    ],
    "sg:website":"http://www.echtebakkervonk.nl",
    "wof:name":"Vonk",
    "wof:placetype":"venue"
},
  "geometry": {"coordinates":[5.200724,52.067936],"type":"Point"}
}