{
  "type": "Feature",
  "properties": {
    "addr:full":"Van Humboldtstraat 16 Utrecht Utrecht 3514 GP",
    "addr:housenumber":"16",
    "addr:postcode":"3514 gp",
    "addr:street":"Van Humboldtstraat",
    "iso:country":"NL",
    "sg:address":"Van Humboldtstraat 16",
    "sg:city":"Utrecht",
    "sg:classifiers":[
        {
            "category":"Food & Beverages",
            "subcategory":"Fruits & Vegetables",
            "type":"Retail Goods"
        }
    ],
    "sg:phone":"+31 30 271 9204",
    "sg:postcode":"3514 GP",
    "sg:province":"Utrecht",
    "sg:tags":[
        "groenten"
    ],
    "wof:name":"Groentenhandel F.G. Van Oort Vof",
    "wof:placetype":"venue"
},
  "geometry": {"coordinates":[5.121906,52.099224],"type":"Point"}
}