{
  "type": "Feature",
  "properties": {
    "addr:full":"Roselaar 21 Roosendaal North Brabant 4701 BA",
    "addr:housenumber":"21",
    "addr:postcode":"4701 ba",
    "addr:street":"Roselaar",
    "iso:country":"NL",
    "sg:address":"Roselaar 21",
    "sg:city":"Roosendaal",
    "sg:orig_category":"Kantoorbenodigdheden",
    "sg:phone":"+31 165 561 120",
    "sg:postcode":"4701 BA",
    "sg:province":"North Brabant",
    "wof:name":"Wortman",
    "wof:placetype":"venue"
},
  "geometry": {"coordinates":[4.4533982277,51.5306434631],"type":"Point"}
}