{
  "type": "Feature",
  "properties": {
    "iso:country":"NL",
    "sg:address":"Hoenderwg 13",
    "sg:city":"Ermelo",
    "sg:orig_category":"Accountants - Administratie- Consulenten En -Kantoren",
    "sg:phone":"+31 341 560 573",
    "sg:postcode":"3851 RZ",
    "sg:province":"Gelderland",
    "wof:name":"Kok",
    "wof:placetype":"venue"
},
  "geometry": {"coordinates":[5.617015,52.314262],"type":"Point"}
}