{
  "type": "Feature",
  "properties": {
    "iso:country":"NL",
    "sg:address":"Wienkeskoel 38",
    "sg:city":"Melick",
    "sg:orig_category":"Luchtbehandelings- Apparaten",
    "sg:phone":"+31 475 537 204",
    "sg:postcode":"6074 HG",
    "sg:province":"Limburg",
    "wof:name":"Hendrickx",
    "wof:placetype":"venue"
},
  "geometry": {"coordinates":[-98.924362,20.49721],"type":"Point"}
}