{
  "type": "Feature",
  "properties": {
    "iso:country":"NL",
    "sg:address":"Albertdonk 6",
    "sg:city":"Roosendaal",
    "sg:orig_category":"Administratie- En Boekhoudkantoren",
    "sg:phone":"+31 165 567 680",
    "sg:postcode":"4707 XZ",
    "sg:province":"Noord-Brabant",
    "sg:website":"http://www.dammerbel.nl",
    "wof:name":"Dam & Van De Merbel",
    "wof:placetype":"venue"
},
  "geometry": {"coordinates":[4.474747,51.521717],"type":"Point"}
}