{
  "type": "Feature",
  "properties": {
    "addr:full":"1E Jerichostraat 25C Rotterdam Zuid-Holland 3061 GC",
    "addr:housenumber":"25c",
    "addr:postcode":"3061 gc",
    "addr:street":"1E Jerichostraat",
    "iso:country":"NL",
    "sg:address":"1E Jerichostraat 25C",
    "sg:city":"Rotterdam",
    "sg:orig_category":"Artsen And Specialisten",
    "sg:phone":"+31 10 212 2622",
    "sg:postcode":"3061 GC",
    "sg:province":"Zuid-Holland",
    "wof:name":"C.M.H. Starrenburg",
    "wof:placetype":"venue"
},
  "geometry": {"coordinates":[4.509989,51.928902],"type":"Point"}
}