{
  "type": "Feature",
  "properties": {
    "addr:full":"Stationsstr 27 Aalten Gelderland 7122 AS",
    "addr:housenumber":"27",
    "addr:postcode":"7122 as",
    "addr:street":"Stationsstr;Gelderland",
    "iso:country":"NL",
    "sg:address":"Stationsstr 27",
    "sg:city":"Aalten",
    "sg:orig_category":"Verzekeringen - Verzekeringskantoren",
    "sg:phone":"+31 543 473 230",
    "sg:postcode":"7122 AS",
    "sg:province":"Gelderland",
    "wof:name":"Zonnenberg",
    "wof:placetype":"venue"
},
  "geometry": {"coordinates":[6.579371,51.924068],"type":"Point"}
}