{
  "type": "Feature",
  "properties": {
    "addr:full":"Hamburgwg 7 Deventer Overijssel 7418 ES",
    "addr:housenumber":"7",
    "addr:postcode":"7418 es",
    "addr:street":"Hamburgwg",
    "iso:country":"NL",
    "sg:address":"Hamburgwg 7",
    "sg:city":"Deventer",
    "sg:orig_category":"Autoruiten",
    "sg:phone":"+31 570 626 146",
    "sg:postcode":"7418 ES",
    "sg:province":"Overijssel",
    "sg:website":"http://www.aramautoglas.nl",
    "wof:name":"Aram Autoglasservice Bv",
    "wof:placetype":"venue"
},
  "geometry": {"coordinates":[6.199863,52.240215],"type":"Point"}
}