{
  "type": "Feature",
  "properties": {
    "addr:full":"Nyverheidswg 8F Druten Gelderland 6651 KS",
    "addr:housenumber":"8f",
    "addr:postcode":"6651 ks",
    "iso:country":"NL",
    "sg:address":"Nyverheidswg 8F",
    "sg:city":"Druten",
    "sg:orig_category":"Sanitaire Artikelen",
    "sg:phone":"+31 487 518 503",
    "sg:postcode":"6651 KS",
    "sg:province":"Gelderland",
    "wof:name":"Installatieshop, De",
    "wof:placetype":"venue"
},
  "geometry": {"coordinates":[5.574393,51.885174],"type":"Point"}
}