{
  "type": "Feature",
  "properties": {
    "addr:full":"Duinwg 44 Zoutelande Zeeland 4374 EG",
    "addr:housenumber":"44",
    "addr:postcode":"4374 eg",
    "addr:street":"Duinwg",
    "iso:country":"NL",
    "sg:address":"Duinwg 44",
    "sg:city":"Zoutelande",
    "sg:classifiers":[
        {
            "category":"Travel",
            "subcategory":"Hotels & Motels",
            "type":"Entertainment"
        }
    ],
    "sg:phone":"+31 118 561 261",
    "sg:postcode":"4374 EG",
    "sg:province":"Zeeland",
    "sg:website":"http://www.duinhotelzomerlust.nl",
    "wof:name":"Zomerlust, Duinhotel",
    "wof:placetype":"venue"
},
  "geometry": {"coordinates":[3.492106,51.498493],"type":"Point"}
}