{
  "type": "Feature",
  "properties": {
    "addr:full":"Stationsweg 7 Ouddorp Zh Zuid-Holland 3253 AP",
    "addr:housenumber":"7",
    "addr:postcode":"3253 ap",
    "addr:street":"Stationsweg",
    "iso:country":"NL",
    "sg:address":"Stationsweg 7",
    "sg:city":"Ouddorp Zh",
    "sg:classifiers":[
        {
            "category":"Fast Food",
            "type":"Food & Drink"
        }
    ],
    "sg:phone":"+31 187 687 132",
    "sg:postcode":"3253 AP",
    "sg:province":"Zuid-Holland",
    "sg:tags":[
        "afhaal",
        "restaurant"
    ],
    "wof:name":"Chin.Ind. Afhaalcentrum Top Food",
    "wof:placetype":"venue"
},
  "geometry": {"coordinates":[3.93704,51.809059],"type":"Point"}
}