{
  "type": "Feature",
  "properties": {
    "addr:full":"Peperstraat 3 Vlaardingen South Holland 3131 CT",
    "addr:housenumber":"3",
    "addr:postcode":"3131 ct",
    "addr:street":"Peperstraat",
    "iso:country":"NL",
    "sg:address":"Peperstraat 3",
    "sg:city":"Vlaardingen",
    "sg:orig_category":"Kappers",
    "sg:phone":"+31 10 435 9096",
    "sg:postcode":"3131 CT",
    "sg:province":"South Holland",
    "wof:name":"Kapsalon 'T Salonnetje",
    "wof:placetype":"venue"
},
  "geometry": {"coordinates":[4.3425850868,51.9085998535],"type":"Point"}
}