{
  "type": "Feature",
  "properties": {
    "iso:country":"NL",
    "sg:address":"Koningsln 17",
    "sg:city":"Amsterdam",
    "sg:orig_category":"Projectinrichting",
    "sg:phone":"+31 20 675 1465",
    "sg:postcode":"1075 AA",
    "sg:province":"Noord-Holland",
    "wof:name":"C + M",
    "wof:placetype":"venue"
},
  "geometry": {"coordinates":[4.863592,52.35516],"type":"Point"}
}