{
  "type": "Feature",
  "properties": {
    "iso:country":"NL",
    "sg:address":"Burg Reigerstr 86",
    "sg:city":"Utrecht",
    "sg:orig_category":"Verenigingen En Stichtingen",
    "sg:phone":"+31 30 254 9600",
    "sg:postcode":"3581 KW",
    "sg:province":"Utrecht",
    "sg:website":"http://www.opbouw.nl",
    "wof:name":"Opbouw, Sticht De",
    "wof:placetype":"venue"
},
  "geometry": {"coordinates":[5.138291,52.088642],"type":"Point"}
}