{
  "type": "Feature",
  "properties": {
    "addr:full":"Blauwpypstr 2 Amsterdam Noord-Holland 1019 KW",
    "addr:housenumber":"2",
    "addr:postcode":"1019 kw",
    "addr:street":"Blauwpypstr",
    "iso:country":"NL",
    "sg:address":"Blauwpypstr 2",
    "sg:city":"Amsterdam",
    "sg:orig_category":"Bloemen En Planten - Decoratie",
    "sg:phone":"+31 20 418 6321",
    "sg:postcode":"1019 KW",
    "sg:province":"Noord-Holland",
    "wof:name":"Hulzebos",
    "wof:placetype":"venue"
},
  "geometry": {"coordinates":[4.939838,52.37093],"type":"Point"}
}