{
  "type": "Feature",
  "properties": {
    "addr:full":"Nyverheidswg 20 Stellendam Zuid-Holland 3251 LP",
    "addr:housenumber":"20",
    "addr:postcode":"3251 lp",
    "addr:street":"Nyverheidswg",
    "iso:country":"NL",
    "sg:address":"Nyverheidswg 20",
    "sg:city":"Stellendam",
    "sg:orig_category":"Baggerwerken",
    "sg:phone":"+31 187 497 090",
    "sg:postcode":"3251 LP",
    "sg:province":"Zuid-Holland",
    "wof:name":"Timro Bv",
    "wof:placetype":"venue"
},
  "geometry": {"coordinates":[4.041105,51.816246],"type":"Point"}
}