{
  "type": "Feature",
  "properties": {
    "iso:country":"NL",
    "sg:address":"Ripperdastraat 36",
    "sg:city":"Haarlem",
    "sg:orig_category":"Loodgieterswerk, Verwarming And Sanitaire Installaties",
    "sg:phone":"+31 23 531 7817",
    "sg:postcode":"2011 KH",
    "sg:province":"Noord-Holland",
    "wof:name":"Loodgietersbedrijf Joh. Winkel & Zoon",
    "wof:placetype":"venue"
},
  "geometry": {"coordinates":[4.640317,52.38586],"type":"Point"}
}