{
  "type": "Feature",
  "properties": {
    "addr:full":"Den Burghstr 20 Voorburg Zuid-Holland 2275 TN",
    "addr:housenumber":"20",
    "addr:postcode":"2275",
    "iso:country":"NL",
    "sg:address":"Den Burghstr 20",
    "sg:city":"Voorburg",
    "sg:orig_category":"Adviesbureaus Bedrijfsorganisatie",
    "sg:phone":"+31 70 390 1600",
    "sg:postcode":"2275 TN",
    "sg:province":"Zuid-Holland",
    "wof:name":"Korbee",
    "wof:placetype":"venue"
},
  "geometry": {"coordinates":[4.347319,52.059975],"type":"Point"}
}