{
  "type": "Feature",
  "properties": {
    "iso:country":"NL",
    "sg:address":"Sportln 74",
    "sg:city":"S Hertogenbosch",
    "sg:orig_category":"Kunststoffen- Verwerkende Industrie",
    "sg:phone":"+31 73 622 2400",
    "sg:postcode":"5223 AZ",
    "sg:province":"North Brabant",
    "sg:website":"http://www.aboned.nl",
    "wof:name":"Aboned Bv",
    "wof:placetype":"venue"
},
  "geometry": {"coordinates":[5.26181,51.689812],"type":"Point"}
}