{
  "type": "Feature",
  "properties": {
    "addr:full":"Hoofdstr 49 Kortgene Zeeland 4484 CB",
    "addr:housenumber":"49",
    "addr:postcode":"4484 cb",
    "addr:street":"Hoofdstr",
    "iso:country":"NL",
    "sg:address":"Hoofdstr 49",
    "sg:city":"Kortgene",
    "sg:orig_category":"Bloemen En Planten",
    "sg:phone":"+31 113 301 681",
    "sg:postcode":"4484 CB",
    "sg:province":"Zeeland",
    "wof:name":"Hengsdijk",
    "wof:placetype":"venue"
},
  "geometry": {"coordinates":[3.801672,51.557362],"type":"Point"}
}