{
  "type": "Feature",
  "properties": {
    "addr:full":"De Meren 9 Eestrum Provincie Friesland 9258 GM",
    "addr:housenumber":"9",
    "addr:postcode":"9258 gm",
    "addr:street":"De Meren;Provincie Friesland",
    "iso:country":"NL",
    "sg:address":"De Meren 9",
    "sg:city":"Eestrum",
    "sg:orig_category":"Adviesbureaus Bouwkunde",
    "sg:phone":"+31 512 471 565",
    "sg:postcode":"9258 GM",
    "sg:province":"Provincie Friesland",
    "wof:name":"Terpstra",
    "wof:placetype":"venue"
},
  "geometry": {"coordinates":[6.065328,53.212421],"type":"Point"}
}