{
  "type": "Feature",
  "properties": {
    "addr:full":"Tengnagelwaard 8 Spyk Gld Gelderland 6917 AE",
    "addr:housenumber":"8",
    "addr:postcode":"6917 ae",
    "addr:street":"Tengnagelwaard;Gld Gelderland",
    "iso:country":"NL",
    "sg:address":"Tengnagelwaard 8",
    "sg:city":"Spyk Gld",
    "sg:orig_category":"Scheepsbouw En -Reparatie",
    "sg:phone":"+31 316 541 857",
    "sg:postcode":"6917 AE",
    "sg:province":"Gelderland",
    "wof:name":"Wemmer Vof",
    "wof:placetype":"venue"
},
  "geometry": {"coordinates":[6.150501,51.847797],"type":"Point"}
}