{
  "type": "Feature",
  "properties": {
    "addr:full":"Ketelwg 73 Papendrecht South Holland 3356 LD",
    "addr:housenumber":"73",
    "addr:postcode":"3356 ld",
    "addr:street":"Ketelwg",
    "iso:country":"NL",
    "sg:address":"Ketelwg 73",
    "sg:city":"Papendrecht",
    "sg:orig_category":"Verhuur",
    "sg:phone":"+31 800 2447356",
    "sg:postcode":"3356 LD",
    "sg:province":"South Holland",
    "sg:website":"http://www.aggreko.nl",
    "wof:name":"Aggreko Nederland Bv",
    "wof:placetype":"venue"
},
  "geometry": {"coordinates":[4.729659,51.828388],"type":"Point"}
}