{
  "type": "Feature",
  "properties": {
    "addr:full":"Sandtln 36F Katwyk Zh Zuid-Holland 2223 GG",
    "addr:housenumber":"36f",
    "addr:postcode":"2223 gg",
    "addr:street":"Katwyk",
    "iso:country":"NL",
    "sg:address":"Sandtln 36F",
    "sg:city":"Katwyk Zh",
    "sg:orig_category":"Verzekeringen - Verzekeringskantoren",
    "sg:phone":"+31 71 407 7547",
    "sg:postcode":"2223 GG",
    "sg:province":"Zuid-Holland",
    "wof:name":"Heijing & Partners Bv",
    "wof:placetype":"venue"
},
  "geometry": {"coordinates":[4.424369812,52.196685791],"type":"Point"}
}