{
  "type": "Feature",
  "properties": {
    "addr:full":"Hastelwg 79 Eindhoven Noord-Brabant 5616 HK",
    "addr:housenumber":"79",
    "addr:postcode":"5616 hk",
    "addr:street":"Hastelwg",
    "iso:country":"NL",
    "sg:address":"Hastelwg 79",
    "sg:city":"Eindhoven",
    "sg:orig_category":"Bestratingen",
    "sg:phone":"+31 40 255 0100",
    "sg:postcode":"5616 HK",
    "sg:province":"Noord-Brabant",
    "wof:name":"Smulders, Henry",
    "wof:placetype":"venue"
},
  "geometry": {"coordinates":[5.454071,51.436695],"type":"Point"}
}