{
  "type": "Feature",
  "properties": {
    "addr:full":"Cruquiusstr 23 Vlissingen Zeeland 4382 KK",
    "addr:housenumber":"23",
    "addr:postcode":"4382 kk",
    "addr:street":"Cruquiusstr",
    "iso:country":"NL",
    "sg:address":"Cruquiusstr 23",
    "sg:city":"Vlissingen",
    "sg:orig_category":"Fitnesscentra",
    "sg:phone":"+31 118 412 011",
    "sg:postcode":"4382 KK",
    "sg:province":"Zeeland",
    "wof:name":"Fitnessclub Vlissingen",
    "wof:placetype":"venue"
},
  "geometry": {"coordinates":[3.5669,51.455341],"type":"Point"}
}