{
  "type": "Feature",
  "properties": {
    "addr:full":"Postbus 10 Best Noord-Brabant 5680 AA",
    "addr:housenumber":"10",
    "addr:postcode":"5680 aa",
    "addr:street":"Postbus",
    "iso:country":"NL",
    "sg:address":"Postbus 10",
    "sg:city":"Best",
    "sg:classifiers":[
        {
            "category":"Shopping",
            "subcategory":"News",
            "type":"Retail Goods"
        }
    ],
    "sg:phone":"+31 499 391 000",
    "sg:postcode":"5680 AA",
    "sg:province":"Noord-Brabant",
    "sg:tags":[
        "maandbladen",
        "en",
        "week-"
    ],
    "wof:name":"Gaykrant Bv, De",
    "wof:placetype":"venue"
},
  "geometry": {"coordinates":[-101.3792724609,31.1080169678],"type":"Point"}
}