{
  "type": "Feature",
  "properties": {
    "addr:full":"Hulswitwg 27A Haarlem Noord-Holland 2031 BG",
    "addr:housenumber":"27a",
    "addr:postcode":"2031",
    "addr:street":"Hulswitwg",
    "iso:country":"NL",
    "sg:address":"Hulswitwg 27A",
    "sg:city":"Haarlem",
    "sg:orig_category":"Administratie- En Boekhoudkantoren",
    "sg:phone":"+31 23 551 3513",
    "sg:postcode":"2031 BG",
    "sg:province":"Noord-Holland",
    "wof:name":"Jvl Bv",
    "wof:placetype":"venue"
},
  "geometry": {"coordinates":[4.667538,52.389473],"type":"Point"}
}