{
  "type": "Feature",
  "properties": {
    "addr:full":"Burgemeester Wallerstr 159 Oldenzaal Overijssel 7574 AN",
    "addr:housenumber":"159",
    "addr:postcode":"7574 an",
    "addr:street":"Burgemeester Wallerstr",
    "iso:country":"NL",
    "sg:address":"Burgemeester Wallerstr 159",
    "sg:city":"Oldenzaal",
    "sg:orig_category":"Bloemen And Planten",
    "sg:phone":"+31 541 515 633",
    "sg:postcode":"7574 AN",
    "sg:province":"Overijssel",
    "wof:name":"Bloemen Macks",
    "wof:placetype":"venue"
},
  "geometry": {"coordinates":[6.93524,52.300571],"type":"Point"}
}