{
  "type": "Feature",
  "properties": {
    "iso:country":"NL",
    "sg:address":"Hoofdstr 93",
    "sg:city":"Kaatsheuvel",
    "sg:orig_category":"Schoenen - Reparaties",
    "sg:phone":"+31 416 275 491",
    "sg:postcode":"5171 DK",
    "sg:province":"Noord-Brabant",
    "wof:name":"Jan Van Der Velden",
    "wof:placetype":"venue"
},
  "geometry": {"coordinates":[5.032021,51.661732],"type":"Point"}
}