{
  "type": "Feature",
  "properties": {
    "iso:country":"NL",
    "sg:address":"Veerwg 24",
    "sg:city":"Kamperland",
    "sg:orig_category":"Jachthavens - Jachtwerven",
    "sg:phone":"+31 113 371 345",
    "sg:postcode":"4493 AS",
    "sg:province":"Zeeland",
    "wof:name":"Leendertse, P M",
    "wof:placetype":"venue"
},
  "geometry": {"coordinates":[3.70379,51.571651],"type":"Point"}
}