{
  "type": "Feature",
  "properties": {
    "addr:full":"Weststraat 31 Kortgene Zeeland 4484 AA",
    "addr:housenumber":"31",
    "addr:postcode":"4484 aa",
    "addr:street":"Weststraat",
    "iso:country":"NL",
    "sg:address":"Weststraat 31",
    "sg:city":"Kortgene",
    "sg:orig_category":"Architecten",
    "sg:phone":"+31 113 301 945",
    "sg:postcode":"4484 AA",
    "sg:province":"Zeeland",
    "wof:name":"Ir. A. Blankenstijn/ Architectenbureau",
    "wof:placetype":"venue"
},
  "geometry": {"coordinates":[3.800693,51.557018],"type":"Point"}
}