{
  "type": "Feature",
  "properties": {
    "addr:full":"Van Reigersbergenstraat 716 Amsterdam Noord-Holland 1052 WK",
    "addr:housenumber":"716",
    "addr:postcode":"1052 wk",
    "addr:street":"Van Reigersbergenstraat",
    "iso:country":"NL",
    "sg:address":"Van Reigersbergenstraat 716",
    "sg:city":"Amsterdam",
    "sg:orig_category":"Diverse Grafische Activiteiten",
    "sg:phone":"+31 20 684 3372",
    "sg:postcode":"1052 WK",
    "sg:province":"Noord-Holland",
    "wof:name":"R E Van Asselt",
    "wof:placetype":"venue"
},
  "geometry": {"coordinates":[4.869292,52.372787],"type":"Point"}
}