{
  "type": "Feature",
  "properties": {
    "iso:country":"NL",
    "sg:address":"Collegewg 1",
    "sg:city":"Raamsdonksveer",
    "sg:orig_category":"Scholen Voor Algemeen Voortgezet Onderwijs",
    "sg:phone":"+31 162 513 469",
    "sg:postcode":"4942 VC",
    "sg:province":"Noord-Brabant",
    "sg:website":"http://www.dongemondcollege.nl",
    "wof:name":"Dongemond College",
    "wof:placetype":"venue"
},
  "geometry": {"coordinates":[4.87163,51.70467],"type":"Point"}
}