{
  "type": "Feature",
  "properties": {
    "addr:full":"Collegewg 1 Raamsdonksveer Noord-Brabant 4942 VC",
    "addr:housenumber":"1",
    "addr:postcode":"4942 vc",
    "addr:street":"Collegewg",
    "iso:country":"NL",
    "sg:address":"Collegewg 1",
    "sg:city":"Raamsdonksveer",
    "sg:orig_category":"Scholen Voor Algemeen Voortgezet Onderwijs",
    "sg:phone":"+31 162 513 469",
    "sg:postcode":"4942 VC",
    "sg:province":"Noord-Brabant",
    "sg:website":"http://www.dongemondcollege.nl",
    "wof:name":"Dongemond College",
    "wof:placetype":"venue"
},
  "geometry": {"coordinates":[4.87163,51.70467],"type":"Point"}
}