{
  "type": "Feature",
  "properties": {
    "addr:full":"Watertorenwg 404 Rotterdam South Holland 3063 HA",
    "addr:housenumber":"404",
    "addr:postcode":"3063 ha",
    "iso:country":"NL",
    "sg:address":"Watertorenwg 404",
    "sg:city":"Rotterdam",
    "sg:orig_category":"Webdesign Bureaus",
    "sg:phone":"+31 10 452 2657",
    "sg:postcode":"3063 HA",
    "sg:province":"South Holland",
    "sg:website":"http://www.bellybutton.nl",
    "wof:name":"Bellybutton",
    "wof:placetype":"venue"
},
  "geometry": {"coordinates":[4.519507885,51.9109649658],"type":"Point"}
}