{
  "type": "Feature",
  "properties": {
    "addr:full":"Julianastraat 66 Diessen Noord-Brabant 5087 BB",
    "addr:housenumber":"66",
    "addr:postcode":"5087 bb",
    "addr:street":"Julianastraat",
    "iso:country":"NL",
    "sg:address":"Julianastraat 66",
    "sg:city":"Diessen",
    "sg:orig_category":"Architecten",
    "sg:phone":"+31 13 504 1261",
    "sg:postcode":"5087 BB",
    "sg:province":"Noord-Brabant",
    "wof:name":"Architectenburo De Rooij Bv",
    "wof:placetype":"venue"
},
  "geometry": {"coordinates":[5.181399,51.478451],"type":"Point"}
}