{
  "type": "Feature",
  "properties": {
    "addr:full":"Mijnweg 1 Geleen Limburg 6167 AC",
    "addr:housenumber":"1",
    "addr:postcode":"6167 ac",
    "addr:street":"Mijnweg",
    "iso:country":"NL",
    "sg:address":"Mijnweg 1",
    "sg:city":"Geleen",
    "sg:orig_category":"Diverse Zakelijke Dienstverlening",
    "sg:phone":"+31 46 476 4303",
    "sg:postcode":"6167 AC",
    "sg:province":"Limburg",
    "wof:name":"Bv Facilitair Bedrijf Ipl",
    "wof:placetype":"venue"
},
  "geometry": {"coordinates":[5.822275,50.975254],"type":"Point"}
}