{
  "type": "Feature",
  "properties": {
    "addr:full":"Rykswg N 39 Swalmen Limburg 6071 KS",
    "addr:postcode":"6071 ks",
    "addr:street":"N 39",
    "iso:country":"NL",
    "sg:address":"Rykswg N 39",
    "sg:city":"Swalmen",
    "sg:orig_category":"Bodemonderzoek",
    "sg:phone":"+31 475 504 961",
    "sg:postcode":"6071 KS",
    "sg:province":"Limburg",
    "sg:website":"http://www.bodemonderzoek.nl",
    "wof:name":"Econsultancy Bv",
    "wof:placetype":"venue"
},
  "geometry": {"coordinates":[6.040698,51.234722],"type":"Point"}
}