{
  "type": "Feature",
  "properties": {
    "iso:country":"NL",
    "sg:address":"Weerdestein 206",
    "sg:city":"Amsterdam",
    "sg:orig_category":"Verzekerings- Maatschappijen",
    "sg:phone":"+31 20 546 1400",
    "sg:postcode":"1083 GN",
    "sg:province":"Noord-Holland",
    "wof:name":"Praevenio Bv",
    "wof:placetype":"venue"
},
  "geometry": {"coordinates":[4.888285,52.330151],"type":"Point"}
}