{
  "type": "Feature",
  "properties": {
    "addr:full":"Pergamijndonk 158 Maastricht Limburg 6218 GX",
    "addr:housenumber":"158",
    "addr:postcode":"6218 gx",
    "addr:street":"Pergamijndonk",
    "iso:country":"NL",
    "sg:address":"Pergamijndonk 158",
    "sg:city":"Maastricht",
    "sg:orig_category":"Boekhouders",
    "sg:phone":"+31 43 343 3835",
    "sg:postcode":"6218 GX",
    "sg:province":"Limburg",
    "wof:name":"Administratiekantoor Silvesters",
    "wof:placetype":"venue"
},
  "geometry": {"coordinates":[5.664278,50.865894],"type":"Point"}
}