{
  "type": "Feature",
  "properties": {
    "addr:full":"Naritaweg 12E Amsterdam Noord-Holland 1043 BZ",
    "addr:housenumber":"12e",
    "addr:postcode":"1043 bz",
    "addr:street":"Naritaweg",
    "iso:country":"NL",
    "sg:address":"Naritaweg 12E",
    "sg:city":"Amsterdam",
    "sg:orig_category":"Werving And Selectie Van Tijdelijk Personeel And Uitzendkantoren",
    "sg:phone":"+31 20 681 7100",
    "sg:postcode":"1043 BZ",
    "sg:province":"Noord-Holland",
    "wof:name":"Outstanding Uitzendburo",
    "wof:placetype":"venue"
},
  "geometry": {"coordinates":[4.8328399658,52.388168335],"type":"Point"}
}