{
  "type": "Feature",
  "properties": {
    "addr:full":"Noorddammerwg 108 Amstelveen North Holland 1187 ZV",
    "addr:housenumber":"108",
    "addr:postcode":"1187 zv",
    "iso:country":"NL",
    "sg:address":"Noorddammerwg 108",
    "sg:city":"Amstelveen",
    "sg:orig_category":"Meubelen - Fabrieken En Groothandel",
    "sg:phone":"+31 20 345 7221",
    "sg:postcode":"1187 ZV",
    "sg:province":"North Holland",
    "wof:name":"Furenka",
    "wof:placetype":"venue"
},
  "geometry": {"coordinates":[4.808568,52.258541],"type":"Point"}
}