{
  "type": "Feature",
  "properties": {
    "iso:country":"NL",
    "sg:address":"Biezendreef 4",
    "sg:city":"Putte",
    "sg:orig_category":"Honden- En Kattentrimsalons",
    "sg:phone":"+31 164 602 644",
    "sg:postcode":"4645 GA",
    "sg:province":"Noord-Brabant",
    "wof:name":"Annemarie",
    "wof:placetype":"venue"
},
  "geometry": {"coordinates":[4.398543,51.363567],"type":"Point"}
}