{
  "type": "Feature",
  "properties": {
    "iso:country":"NL",
    "sg:address":"Ploegstr 48",
    "sg:city":"Dordrecht",
    "sg:classifiers":[
        {
            "category":"Food & Beverages",
            "subcategory":"Bakery",
            "type":"Retail Goods"
        }
    ],
    "sg:phone":"+31 78 621 9200",
    "sg:postcode":"3319 LG",
    "sg:province":"Zuid-Holland",
    "sg:tags":[
        "pizza"
    ],
    "sg:website":"http://www.dominos.nl",
    "wof:name":"Domino",
    "wof:placetype":"venue"
},
  "geometry": {"coordinates":[4.717261,51.797325],"type":"Point"}
}