{
  "type": "Feature",
  "properties": {
    "addr:full":"Grt Belt 153 Hoofddorp Noord-Holland 2133 GW",
    "addr:housenumber":"153",
    "addr:postcode":"2133 gw",
    "addr:street":"Belt",
    "iso:country":"NL",
    "sg:address":"Grt Belt 153",
    "sg:city":"Hoofddorp",
    "sg:orig_category":"Administratie- En Boekhoudkantoren",
    "sg:phone":"+31 23 562 0872",
    "sg:postcode":"2133 GW",
    "sg:province":"Noord-Holland",
    "wof:name":"Heming",
    "wof:placetype":"venue"
},
  "geometry": {"coordinates":[4.667825,52.31337],"type":"Point"}
}