{
  "type": "Feature",
  "properties": {
    "addr:full":"Kleveringwg 35 Delft Zuid-Holland 2616 LZ",
    "addr:housenumber":"35",
    "addr:postcode":"2616 lz",
    "addr:street":"Kleveringwg",
    "iso:country":"NL",
    "sg:address":"Kleveringwg 35",
    "sg:city":"Delft",
    "sg:orig_category":"Kinderactiviteiten",
    "sg:phone":"+31 15 219 0673",
    "sg:postcode":"2616 LZ",
    "sg:province":"Zuid-Holland",
    "wof:name":"Kids Playground",
    "wof:placetype":"venue"
},
  "geometry": {"coordinates":[4.364014,52.025612],"type":"Point"}
}