{
  "type": "Feature",
  "properties": {
    "addr:full":"Krommenbeemd 3 Eindhoven North Brabant 5641 JW",
    "addr:housenumber":"3",
    "addr:postcode":"5641 jw",
    "addr:street":"Krommenbeemd",
    "iso:country":"NL",
    "sg:address":"Krommenbeemd 3",
    "sg:city":"Eindhoven",
    "sg:orig_category":"Plafonds",
    "sg:phone":"+31 40 281 0037",
    "sg:postcode":"5641 JW",
    "sg:province":"North Brabant",
    "wof:name":"Bakker",
    "wof:placetype":"venue"
},
  "geometry": {"coordinates":[5.523936,51.452045],"type":"Point"}
}