{
  "type": "Feature",
  "properties": {
    "addr:full":"Boterdk 38 Uithoorn North Holland 1423 NB",
    "addr:housenumber":"38",
    "addr:postcode":"1423 nb",
    "addr:street":"Boterdk",
    "iso:country":"NL",
    "sg:address":"Boterdk 38",
    "sg:city":"Uithoorn",
    "sg:orig_category":"Kantoor- En Secretariaatsservice",
    "sg:phone":"+31 297 534 088",
    "sg:postcode":"1423 NB",
    "sg:province":"North Holland",
    "wof:name":"Bas",
    "wof:placetype":"venue"
},
  "geometry": {"coordinates":[4.8101639748,52.2384185791],"type":"Point"}
}