{
  "type": "Feature",
  "properties": {
    "addr:full":"Nw Dreef 10 Ulvenhout Noord-Brabant 4851 BN",
    "addr:housenumber":"10",
    "addr:postcode":"4851 bn",
    "addr:street":"Nw Dreef",
    "iso:country":"NL",
    "sg:address":"Nw Dreef 10",
    "sg:city":"Ulvenhout",
    "sg:orig_category":"Verzekeringen - Verzekeringskantoren",
    "sg:phone":"+31 76 561 6091",
    "sg:postcode":"4851 BN",
    "sg:province":"Noord-Brabant",
    "wof:name":"Nouwen",
    "wof:placetype":"venue"
},
  "geometry": {"coordinates":[4.808964,51.547722],"type":"Point"}
}