{
  "type": "Feature",
  "properties": {
    "addr:full":"Rooysestr 44 Dreumel Gelderland 6621 AN",
    "addr:housenumber":"44",
    "addr:postcode":"6621 an",
    "addr:street":"Rooysestr;Gelderland",
    "iso:country":"NL",
    "sg:address":"Rooysestr 44",
    "sg:city":"Dreumel",
    "sg:orig_category":"Bejaarden - Verzorgingstehuizen",
    "sg:phone":"+31 487 571 439",
    "sg:postcode":"6621 AN",
    "sg:province":"Gelderland",
    "wof:name":"Barbara, St",
    "wof:placetype":"venue"
},
  "geometry": {"coordinates":[5.429593,51.847279],"type":"Point"}
}