{
  "type": "Feature",
  "properties": {
    "addr:full":"Postbus 13 Heelsum Gelderland 6866 ZG",
    "addr:housenumber":"13",
    "addr:postcode":"6866 zg",
    "addr:street":"Postbus;Gelderland",
    "iso:country":"NL",
    "sg:address":"Postbus 13",
    "sg:city":"Heelsum",
    "sg:orig_category":"Scholen Voor Basisonderwijs",
    "sg:phone":"+31 317 312 567",
    "sg:postcode":"6866 ZG",
    "sg:province":"Gelderland",
    "wof:name":"Airborne Chr",
    "wof:placetype":"venue"
},
  "geometry": {"coordinates":[5.7534599304,51.9838447571],"type":"Point"}
}