{
  "type": "Feature",
  "properties": {
    "addr:full":"Eendrachtsweg 3 Zevenhuizen Zh South Holland 2761 VT",
    "addr:housenumber":"3;zh",
    "addr:postcode":"2761",
    "addr:street":"Eendrachtsweg",
    "iso:country":"NL",
    "sg:address":"Eendrachtsweg 3",
    "sg:city":"Zevenhuizen Zh",
    "sg:orig_category":"Boekhouders",
    "sg:phone":"+31 180 631 472",
    "sg:postcode":"2761 VT",
    "sg:province":"South Holland",
    "wof:name":"Accountants- En Administratie- Kantoor H.G. Van De",
    "wof:placetype":"venue"
},
  "geometry": {"coordinates":[4.57673,52.012142],"type":"Point"}
}