{
  "type": "Feature",
  "properties": {
    "addr:full":"Voorzand 35 Ridderkerk Zuid-Holland 2984 BH",
    "addr:housenumber":"35",
    "addr:postcode":"2984 bh",
    "addr:street":"Voorzand",
    "iso:country":"NL",
    "sg:address":"Voorzand 35",
    "sg:city":"Ridderkerk",
    "sg:orig_category":"Autokeuringen",
    "sg:phone":"+31 180 426 769",
    "sg:postcode":"2984 BH",
    "sg:province":"Zuid-Holland",
    "wof:name":"Rene Van Oudenaarde Auto'S",
    "wof:placetype":"venue"
},
  "geometry": {"coordinates":[4.608141,51.870155],"type":"Point"}
}