{
  "type": "Feature",
  "properties": {
    "addr:full":"Schutsluis 2A Vroomshoop Overijssel 7681 KG",
    "addr:housenumber":"2a",
    "addr:postcode":"7681 kg",
    "addr:street":"Schutsluis",
    "iso:country":"NL",
    "sg:address":"Schutsluis 2A",
    "sg:city":"Vroomshoop",
    "sg:orig_category":"Houtindustrie",
    "sg:phone":"+31 546 642 298",
    "sg:postcode":"7681 KG",
    "sg:province":"Overijssel",
    "wof:name":"Groot-Zagers Vof, De",
    "wof:placetype":"venue"
},
  "geometry": {"coordinates":[6.566861,52.449051],"type":"Point"}
}