{
  "type": "Feature",
  "properties": {
    "addr:full":"Scheer 1 Emmeloord NL. 8303 KN",
    "addr:housenumber":"1",
    "addr:postcode":"8303 kn",
    "addr:street":"Scheer;Nl.",
    "iso:country":"NL",
    "sg:address":"Scheer 1",
    "sg:city":"Emmeloord",
    "sg:classifiers":[
        {
            "category":"Education",
            "subcategory":"Preschool",
            "type":"Public Place"
        }
    ],
    "sg:phone":"+31 527 698 644",
    "sg:postcode":"8303 KN",
    "sg:province":"NL.",
    "sg:tags":[
        "kleuteronderwijs",
        "basis-"
    ],
    "wof:name":"Chr Basisschool De Lichtboei",
    "wof:placetype":"venue"
},
  "geometry": {"coordinates":[5.72772,52.713181],"type":"Point"}
}