{
  "type": "Feature",
  "properties": {
    "addr:full":"Dommelstraat 41 Valkenswaard North Brabant 5551 TA",
    "addr:housenumber":"41",
    "addr:postcode":"5551 ta",
    "addr:street":"Dommelstraat",
    "iso:country":"NL",
    "sg:address":"Dommelstraat 41",
    "sg:city":"Valkenswaard",
    "sg:orig_category":"Diverse Artikelen Fab",
    "sg:phone":"+31 40 201 2483",
    "sg:postcode":"5551 TA",
    "sg:province":"North Brabant",
    "wof:name":"Kaarsenfabriek Rombauts Vof",
    "wof:placetype":"venue"
},
  "geometry": {"coordinates":[5.438014,51.355633],"type":"Point"}
}