{
  "type": "Feature",
  "properties": {
    "addr:full":"Butewacht 106 Drachten Friesland 9202 JV",
    "addr:housenumber":"106",
    "addr:postcode":"9202 jv",
    "iso:country":"NL",
    "sg:address":"Butewacht 106",
    "sg:city":"Drachten",
    "sg:orig_category":"Nagelstudio'S",
    "sg:phone":"+31 512 530 310",
    "sg:postcode":"9202 JV",
    "sg:province":"Friesland",
    "wof:name":"Rianne",
    "wof:placetype":"venue"
},
  "geometry": {"coordinates":[6.124509,53.108509],"type":"Point"}
}