{
  "type": "Feature",
  "properties": {
    "iso:country":"NL",
    "sg:address":"T Erf 18",
    "sg:city":"Bemmel",
    "sg:orig_category":"Autorijscholen",
    "sg:phone":"+31 481 450 593",
    "sg:postcode":"6681 GD",
    "sg:province":"Gelderland",
    "wof:name":"Brandenburg, C Van",
    "wof:placetype":"venue"
},
  "geometry": {"coordinates":[5.899248,51.897739],"type":"Point"}
}