{
  "type": "Feature",
  "properties": {
    "addr:full":"Leemstr 11 Roosendaal North Brabant 4705 RT",
    "addr:housenumber":"11",
    "addr:postcode":"4705 rt",
    "addr:street":"Leemstr",
    "iso:country":"NL",
    "sg:address":"Leemstr 11",
    "sg:city":"Roosendaal",
    "sg:orig_category":"Automaterialen En Gereedschappen",
    "sg:phone":"+31 165 552 262",
    "sg:postcode":"4705 RT",
    "sg:province":"North Brabant",
    "wof:name":"Hoofd, Willem Van Der",
    "wof:placetype":"venue"
},
  "geometry": {"coordinates":[4.491774,51.545448],"type":"Point"}
}