{
  "type": "Feature",
  "properties": {
    "addr:full":"Dieselstraat 1 Hoogeveen Drenthe 7903 AR",
    "addr:housenumber":"1",
    "addr:postcode":"7903",
    "addr:street":"Dieselstraat",
    "iso:country":"NL",
    "sg:address":"Dieselstraat 1",
    "sg:city":"Hoogeveen",
    "sg:orig_category":"Autokeuringen",
    "sg:phone":"+31 528 277 232",
    "sg:postcode":"7903 AR",
    "sg:province":"Drenthe",
    "wof:name":"Bv Spuiterij Sent Waninge",
    "wof:placetype":"venue"
},
  "geometry": {"coordinates":[6.49799,52.736519],"type":"Point"}
}