{
  "type": "Feature",
  "properties": {
    "addr:full":"P C Hooftstr 112 Amsterdam North Holland 1071 CD",
    "addr:housenumber":"112",
    "addr:postcode":"1071 cd",
    "addr:street":"P C Hooftstr",
    "iso:country":"NL",
    "sg:address":"P C Hooftstr 112",
    "sg:city":"Amsterdam",
    "sg:orig_category":"Herenkleding",
    "sg:phone":"+31 20 379 5050",
    "sg:postcode":"1071 CD",
    "sg:province":"North Holland",
    "wof:name":"Hugo Boss",
    "wof:placetype":"venue"
},
  "geometry": {"coordinates":[4.879091,52.359951],"type":"Point"}
}