{
  "type": "Feature",
  "properties": {
    "iso:country":"NL",
    "sg:address":"Huygensstraat 51",
    "sg:city":"Sint Annaland",
    "sg:orig_category":"Metaalwerken",
    "sg:phone":"+31 166 652 248",
    "sg:postcode":"4697 DA",
    "sg:province":"Zeeland",
    "wof:name":"Cb Spanplafonds",
    "wof:placetype":"venue"
},
  "geometry": {"coordinates":[4.098388,51.596954],"type":"Point"}
}