{
  "type": "Feature",
  "properties": {
    "addr:full":"Pelgrimstr 25 Gaanderen Gelderland 7011 BH",
    "addr:housenumber":"25",
    "addr:postcode":"7011 bh",
    "addr:street":"Pelgrimstr;Gelderland",
    "iso:country":"NL",
    "sg:address":"Pelgrimstr 25",
    "sg:city":"Gaanderen",
    "sg:orig_category":"Letselschadespecialisten",
    "sg:phone":"+31 24 388 6680",
    "sg:postcode":"7011 BH",
    "sg:province":"Gelderland",
    "sg:website":"http://www.hijink.com",
    "wof:name":"Hijink Rechtspraktijk",
    "wof:placetype":"venue"
},
  "geometry": {"coordinates":[6.345791,51.932865],"type":"Point"}
}