{
  "type": "Feature",
  "properties": {
    "addr:full":"Stationsstraat 90 Apeldoorn Gelderland 7311 MJ",
    "addr:housenumber":"90",
    "addr:postcode":"7311 mj",
    "addr:street":"Stationsstraat;Gelderland",
    "iso:country":"NL",
    "sg:address":"Stationsstraat 90",
    "sg:city":"Apeldoorn",
    "sg:orig_category":"Werving And Selectie Van Tijdelijk Personeel And Uitzendkantoren",
    "sg:phone":"+31 55 519 1733",
    "sg:postcode":"7311 MJ",
    "sg:province":"Gelderland",
    "wof:name":"Outstanding Uitzenduro",
    "wof:placetype":"venue"
},
  "geometry": {"coordinates":[5.9674019814,52.2128982544],"type":"Point"}
}