{
  "type": "Feature",
  "properties": {
    "addr:full":"Vervoornstraat 124 Putten Gelderland 3882 XR",
    "addr:housenumber":"124",
    "addr:postcode":"3882 xr",
    "addr:street":"Vervoornstraat;Gelderland",
    "iso:country":"NL",
    "sg:address":"Vervoornstraat 124",
    "sg:city":"Putten",
    "sg:orig_category":"Krantenuitgeverijen",
    "sg:phone":"+31 341 361 513",
    "sg:postcode":"3882 XR",
    "sg:province":"Gelderland",
    "wof:name":"Kabelkrant",
    "wof:placetype":"venue"
},
  "geometry": {"coordinates":[5.60327,52.251911],"type":"Point"}
}