{
  "type": "Feature",
  "properties": {
    "addr:full":"S Stevinwg 101 Hilversum Noord-Holland 1222 SP",
    "addr:housenumber":"101",
    "addr:postcode":"hilversum;1222 sp",
    "iso:country":"NL",
    "sg:address":"S Stevinwg 101",
    "sg:city":"Hilversum",
    "sg:classifiers":[
        {
            "category":"Personal",
            "subcategory":"Nail Salon",
            "type":"Services"
        }
    ],
    "sg:phone":"+31 35 685 7312",
    "sg:postcode":"1222 SP",
    "sg:province":"Noord-Holland",
    "sg:tags":[
        "pedicure"
    ],
    "wof:name":"Verweij-Oudshoorn, P C",
    "wof:placetype":"venue"
},
  "geometry": {"coordinates":[5.182647,52.23447],"type":"Point"}
}