{
  "type": "Feature",
  "properties": {
    "iso:country":"NL",
    "sg:address":"Graafschap Hornelaan 9",
    "sg:city":"Weert",
    "sg:orig_category":"Goederenvervoer Over De Weg",
    "sg:phone":"+31 495 535 751",
    "sg:postcode":"6001 AA",
    "sg:province":"Limburg",
    "wof:name":"Verhappen Expeditie",
    "wof:placetype":"venue"
},
  "geometry": {"coordinates":[5.71394,51.251442],"type":"Point"}
}