{
  "type": "Feature",
  "properties": {
    "addr:full":"Graafschap Hornelaan 9 Weert Limburg 6001 AA",
    "addr:housenumber":"9",
    "addr:postcode":"6001 aa",
    "addr:street":"Graafschap Hornelaan",
    "iso:country":"NL",
    "sg:address":"Graafschap Hornelaan 9",
    "sg:city":"Weert",
    "sg:orig_category":"Goederenvervoer Over De Weg",
    "sg:phone":"+31 495 535 751",
    "sg:postcode":"6001 AA",
    "sg:province":"Limburg",
    "wof:name":"Verhappen Expeditie",
    "wof:placetype":"venue"
},
  "geometry": {"coordinates":[5.71394,51.251442],"type":"Point"}
}