{
  "type": "Feature",
  "properties": {
    "addr:full":"Vlierstr 33 Vaassen Gelderland 8171 BA",
    "addr:housenumber":"33",
    "addr:postcode":"8171 ba",
    "addr:street":"Vlierstr;Gelderland",
    "iso:country":"NL",
    "sg:address":"Vlierstr 33",
    "sg:city":"Vaassen",
    "sg:orig_category":"Scholen Voor Basisonderwijs",
    "sg:phone":"+31 578 573 247",
    "sg:postcode":"8171 BA",
    "sg:province":"Gelderland",
    "wof:name":"Violier Chr, De",
    "wof:placetype":"venue"
},
  "geometry": {"coordinates":[5.971295,52.293095],"type":"Point"}
}