{
  "type": "Feature",
  "properties": {
    "addr:full":"Centrumpassage 83 Capelle Ad Yssel Zuid-Holland 2903 HB",
    "addr:housenumber":"83",
    "addr:postcode":"2903 hb",
    "addr:street":"Centrumpassage",
    "iso:country":"NL",
    "sg:address":"Centrumpassage 83",
    "sg:city":"Capelle Ad Yssel",
    "sg:orig_category":"Juweliers",
    "sg:phone":"+31 10 284 7270",
    "sg:postcode":"2903 HB",
    "sg:province":"Zuid-Holland",
    "wof:name":"Jewel Trend",
    "wof:placetype":"venue"
},
  "geometry": {"coordinates":[4.589148,51.931965],"type":"Point"}
}