{
  "type": "Feature",
  "properties": {
    "addr:full":"Rengerslaan 10 Leeuwarden Friesland 8917 DD",
    "addr:housenumber":"10",
    "addr:postcode":"8917 dd",
    "addr:street":"Rengerslaan",
    "iso:country":"NL",
    "sg:address":"Rengerslaan 10",
    "sg:city":"Leeuwarden",
    "sg:orig_category":"Drukkerijen And Copyshops",
    "sg:phone":"+31 58 293 4410",
    "sg:postcode":"8917 DD",
    "sg:province":"Friesland",
    "wof:name":"Reprografisch Centrum",
    "wof:placetype":"venue"
},
  "geometry": {"coordinates":[5.799106,53.212772],"type":"Point"}
}