{
  "type": "Feature",
  "properties": {
    "addr:full":"Valkstraat 12 Helmond Noord-Brabant 5702 PL",
    "addr:housenumber":"12",
    "addr:postcode":"5702 pl",
    "addr:street":"Valkstraat",
    "iso:country":"NL",
    "sg:address":"Valkstraat 12",
    "sg:city":"Helmond",
    "sg:orig_category":"Fitnesscentra",
    "sg:phone":"+31 492 534 814",
    "sg:postcode":"5702 PL",
    "sg:province":"Noord-Brabant",
    "wof:name":"Sportschool Van De Pol",
    "wof:placetype":"venue"
},
  "geometry": {"coordinates":[5.66319,51.489044],"type":"Point"}
}