{
  "type": "Feature",
  "properties": {
    "iso:country":"NL",
    "sg:address":"Sportln 255",
    "sg:city":"Sliedrecht",
    "sg:orig_category":"Elektronica - Ontwikkeling En Groothandel",
    "sg:phone":"+31 184 434 160",
    "sg:postcode":"3364 DK",
    "sg:province":"South Holland",
    "wof:name":"Daewoo Bv",
    "wof:placetype":"venue"
},
  "geometry": {"coordinates":[4.772605,51.823555],"type":"Point"}
}