{
  "type": "Feature",
  "properties": {
    "addr:full":"Gouvernestr 133 Rotterdam Zuid-Holland 3014 PM",
    "addr:housenumber":"133",
    "addr:postcode":"3014 pm",
    "iso:country":"NL",
    "sg:address":"Gouvernestr 133",
    "sg:city":"Rotterdam",
    "sg:orig_category":"Bioscopen",
    "sg:phone":"+31 10 277 2266",
    "sg:postcode":"3014 PM",
    "sg:province":"Zuid-Holland",
    "sg:website":"http://www.lantaren-venster.nl",
    "wof:name":"Lantaren/Venster",
    "wof:placetype":"venue"
},
  "geometry": {"coordinates":[4.469284,51.917614],"type":"Point"}
}