{
  "type": "Feature",
  "properties": {
    "addr:full":"Noorderwg 162 Hilversum Noord-Holland 1222 PH",
    "addr:housenumber":"162",
    "addr:postcode":"hilversum;1222",
    "iso:country":"NL",
    "sg:address":"Noorderwg 162",
    "sg:city":"Hilversum",
    "sg:orig_category":"Journalisten Freelance",
    "sg:phone":"+31 35 666 8521",
    "sg:postcode":"1222 PH",
    "sg:province":"Noord-Holland",
    "wof:name":"Embrechts, A L M B",
    "wof:placetype":"venue"
},
  "geometry": {"coordinates":[5.18488,52.2495],"type":"Point"}
}