{
  "type": "Feature",
  "properties": {
    "iso:country":"NL",
    "sg:address":"Staringln 17C",
    "sg:city":"Waddinxveen",
    "sg:orig_category":"Projectinrichting",
    "sg:phone":"+31 182 619 029",
    "sg:postcode":"2741 GC",
    "sg:province":"Zuid-Holland",
    "wof:name":"All-Round Waddinxveen Bv",
    "wof:placetype":"venue"
},
  "geometry": {"coordinates":[4.659366,52.056332],"type":"Point"}
}