{
  "type": "Feature",
  "properties": {
    "addr:full":"Rosmolenweg 9C Papendrecht Zuid-Holland 3356 LK",
    "addr:housenumber":"9c",
    "addr:postcode":"3356 lk",
    "addr:street":"Rosmolenweg",
    "iso:country":"NL",
    "sg:address":"Rosmolenweg 9C",
    "sg:city":"Papendrecht",
    "sg:orig_category":"Aggregaten",
    "sg:phone":"+31 78 682 2055",
    "sg:postcode":"3356 LK",
    "sg:province":"Zuid-Holland",
    "sg:website":"http://www.energiesystemenholland.nl",
    "wof:name":"Esh Bv",
    "wof:placetype":"venue"
},
  "geometry": {"coordinates":[4.731152,51.825867],"type":"Point"}
}