{
  "type": "Feature",
  "properties": {
    "iso:country":"NL",
    "sg:address":"Graanakker 25",
    "sg:city":"S Hertogenbosch",
    "sg:orig_category":"Mode Artikelen Dames En Heren - Fabrieken En Groothandel",
    "sg:phone":"+31 73 641 0567",
    "sg:postcode":"5236 VH",
    "sg:province":"Noord-Brabant",
    "wof:name":"Pinxten & De Keyser Vof, Van",
    "wof:placetype":"venue"
},
  "geometry": {"coordinates":[5.326933,51.73576],"type":"Point"}
}