{
  "type": "Feature",
  "properties": {
    "iso:country":"NL",
    "sg:address":"Burg Gommansstr 153",
    "sg:city":"Venlo",
    "sg:orig_category":"Banden",
    "sg:phone":"+31 77 324 0745",
    "sg:postcode":"5922 AH",
    "sg:province":"Limburg",
    "sg:website":"http://www.kwik-fit.nl",
    "wof:name":"Kwik-Fit",
    "wof:placetype":"venue"
},
  "geometry": {"coordinates":[6.14543,51.375278],"type":"Point"}
}