{
  "type": "Feature",
  "properties": {
    "addr:full":"It Koartlan 2 Berlikum Fr Friesland 9041 VB",
    "addr:housenumber":"2",
    "addr:postcode":"9041 vb",
    "iso:country":"NL",
    "sg:address":"It Koartlan 2",
    "sg:city":"Berlikum Fr",
    "sg:orig_category":"Automaterialen En Gereedschappen",
    "sg:phone":"+31 518 462 598",
    "sg:postcode":"9041 VB",
    "sg:province":"Friesland",
    "wof:name":"Erwin Taal",
    "wof:placetype":"venue"
},
  "geometry": {"coordinates":[5.641769,53.237328],"type":"Point"}
}