{
  "type": "Feature",
  "properties": {
    "addr:full":"Havenstraat 14 Zuidlaren Drenthe 9471 AM",
    "addr:housenumber":"14",
    "addr:postcode":"9471",
    "addr:street":"Havenstraat",
    "iso:country":"NL",
    "sg:address":"Havenstraat 14",
    "sg:city":"Zuidlaren",
    "sg:orig_category":"Verhuur Huishoudartikelen",
    "sg:phone":"+31 50 409 2800",
    "sg:postcode":"9471 AM",
    "sg:province":"Drenthe",
    "wof:name":"Tanja Verhuur Bv",
    "wof:placetype":"venue"
},
  "geometry": {"coordinates":[6.691965,53.09816],"type":"Point"}
}