{
  "type": "Feature",
  "properties": {
    "addr:full":"Amsterdamsestraatweg 296 Utrecht Utrecht 3551 CS",
    "addr:housenumber":"296",
    "addr:postcode":"3551 cs",
    "addr:street":"Amsterdamsestraatweg",
    "iso:country":"NL",
    "sg:address":"Amsterdamsestraatweg 296",
    "sg:city":"Utrecht",
    "sg:orig_category":"Diverse Opleidingen And Onderwijs",
    "sg:phone":"+31 30 243 1907",
    "sg:postcode":"3551 CS",
    "sg:province":"Utrecht",
    "wof:name":"Eurocom Opleidingen Bv",
    "wof:placetype":"venue"
},
  "geometry": {"coordinates":[5.098616,52.101326],"type":"Point"}
}