{
  "type": "Feature",
  "properties": {
    "iso:country":"NL",
    "sg:address":"Grote Janstraat 44",
    "sg:city":"Beverwijk",
    "sg:classifiers":[
        {
            "category":"Fast Food",
            "type":"Food & Drink"
        }
    ],
    "sg:phone":"+31 251 214 424",
    "sg:postcode":"1947 KH",
    "sg:province":"North Holland",
    "sg:tags":[
        "afhaal",
        "restaurant"
    ],
    "wof:name":"Shalom",
    "wof:placetype":"venue"
},
  "geometry": {"coordinates":[4.6624159813,52.482509613],"type":"Point"}
}