{
  "type": "Feature",
  "properties": {
    "iso:country":"NL",
    "sg:address":"Pasteurstr 175",
    "sg:city":"S Gravenhage",
    "sg:orig_category":"Loodgieters",
    "sg:phone":"+31 70 390 7262",
    "sg:postcode":"2522 RJ",
    "sg:province":"Zuid-Holland",
    "wof:name":"Dekker Bv, Den",
    "wof:placetype":"venue"
},
  "geometry": {"coordinates":[4.32729,52.060848],"type":"Point"}
}