{
  "type": "Feature",
  "properties": {
    "iso:country":"NL",
    "sg:address":"Korte Ruigeweg 2",
    "sg:city":"Schagerbrug",
    "sg:orig_category":"Geluidsopnamen",
    "sg:phone":"+31 224 571 315",
    "sg:postcode":"1751 DE",
    "sg:province":"Noord-Holland",
    "wof:name":"Musado",
    "wof:placetype":"venue"
},
  "geometry": {"coordinates":[4.753779,52.811169],"type":"Point"}
}