{
  "type": "Feature",
  "properties": {
    "addr:full":"Parallelweg 6A Veenendaal Utrecht 3903 BA",
    "addr:housenumber":"6a",
    "addr:postcode":"3903 ba",
    "addr:street":"Parallelweg",
    "iso:country":"NL",
    "sg:address":"Parallelweg 6A",
    "sg:city":"Veenendaal",
    "sg:orig_category":"Feestartikelen",
    "sg:phone":"+31 318 552 225",
    "sg:postcode":"3903 BA",
    "sg:province":"Utrecht",
    "wof:name":"Extion",
    "wof:placetype":"venue"
},
  "geometry": {"coordinates":[5.550667,52.018463],"type":"Point"}
}