{
  "type": "Feature",
  "properties": {
    "iso:country":"NL",
    "sg:address":"Lange Geere 7",
    "sg:city":"Middelburg",
    "sg:orig_category":"Baby- And Kinderkleding",
    "sg:phone":"+31 118 639 255",
    "sg:postcode":"4331 LX",
    "sg:province":"Zeeland",
    "wof:name":"Hummels",
    "wof:placetype":"venue"
},
  "geometry": {"coordinates":[3.608741,51.497002],"type":"Point"}
}