{
  "type": "Feature",
  "properties": {
    "iso:country":"NL",
    "sg:address":"S Meeszstr 12",
    "sg:city":"Noordwyk Zh",
    "sg:orig_category":"Zeilbotenverhuur",
    "sg:phone":"+31 71 361 8265",
    "sg:postcode":"2203 BM",
    "sg:province":"Zuid-Holland",
    "wof:name":"V & S",
    "wof:placetype":"venue"
},
  "geometry": {"coordinates":[4.4477,52.234261],"type":"Point"}
}