{
  "type": "Feature",
  "properties": {
    "addr:full":"Buitenveer 10 Weesp North Holland 1381 AD",
    "addr:housenumber":"10",
    "addr:postcode":"1381 ad",
    "addr:street":"Buitenveer",
    "iso:country":"NL",
    "sg:address":"Buitenveer 10",
    "sg:city":"Weesp",
    "sg:orig_category":"Kappers",
    "sg:phone":"+31 294 413 066",
    "sg:postcode":"1381 AD",
    "sg:province":"North Holland",
    "wof:name":"Grijpink, H A",
    "wof:placetype":"venue"
},
  "geometry": {"coordinates":[5.0385909081,52.3084373474],"type":"Point"}
}