{
  "type": "Feature",
  "properties": {
    "addr:full":"Dreef 101 Breda Noord-Brabant 4813 EE",
    "addr:housenumber":"101",
    "addr:postcode":"4813 ee",
    "addr:street":"Dreef",
    "iso:country":"NL",
    "sg:address":"Dreef 101",
    "sg:city":"Breda",
    "sg:orig_category":"Autokeuringen",
    "sg:phone":"+31 76 521 8311",
    "sg:postcode":"4813 EE",
    "sg:province":"Noord-Brabant",
    "wof:name":"Vos Autorecreatie",
    "wof:placetype":"venue"
},
  "geometry": {"coordinates":[4.74337,51.574509],"type":"Point"}
}