{
  "type": "Feature",
  "properties": {
    "addr:full":"Bonstr 1 Wervershoof Noord-Holland 1693 BT",
    "addr:housenumber":"1",
    "addr:postcode":"1693 bt",
    "addr:street":"Bonstr",
    "iso:country":"NL",
    "sg:address":"Bonstr 1",
    "sg:city":"Wervershoof",
    "sg:orig_category":"Beeldende Kunstenaars",
    "sg:phone":"+31 228 581 023",
    "sg:postcode":"1693 BT",
    "sg:province":"Noord-Holland",
    "wof:name":"Koomen, C",
    "wof:placetype":"venue"
},
  "geometry": {"coordinates":[5.14762,52.730137],"type":"Point"}
}