{
  "type": "Feature",
  "properties": {
    "addr:full":"Stationsstr 20 Assen Drenthe 9401 KX",
    "addr:housenumber":"20",
    "addr:postcode":"9401 kx",
    "addr:street":"Stationsstr",
    "iso:country":"NL",
    "sg:address":"Stationsstr 20",
    "sg:city":"Assen",
    "sg:orig_category":"Verenigingen En Stichtingen",
    "sg:phone":"+31 592 305 942",
    "sg:postcode":"9401 KX",
    "sg:province":"Drenthe",
    "wof:name":"Monumentenwacht, Sticht",
    "wof:placetype":"venue"
},
  "geometry": {"coordinates":[6.567197,52.993214],"type":"Point"}
}