{
  "type": "Feature",
  "properties": {
    "addr:full":"Gatsedijk 78 Maasdam Zuid-Holland 3299 LC",
    "addr:housenumber":"78",
    "addr:postcode":"3299 lc",
    "addr:street":"Gatsedijk",
    "iso:country":"NL",
    "sg:address":"Gatsedijk 78",
    "sg:city":"Maasdam",
    "sg:orig_category":"Goederenvervoer Over De Weg",
    "sg:phone":"+31 78 676 4178",
    "sg:postcode":"3299 LC",
    "sg:province":"Zuid-Holland",
    "wof:name":"A.J. Van Wingerden Transport",
    "wof:placetype":"venue"
},
  "geometry": {"coordinates":[4.546763,51.776047],"type":"Point"}
}