{
  "type": "Feature",
  "properties": {
    "addr:full":"Kerkln 21 Heemskerk Georgia 1961 GA",
    "addr:housenumber":"21",
    "addr:postcode":"1961 ga",
    "addr:street":"Kerkln;Georgia",
    "iso:country":"NL",
    "sg:address":"Kerkln 21",
    "sg:city":"Heemskerk",
    "sg:orig_category":"Juweliers",
    "sg:phone":"+31 251 232 133",
    "sg:postcode":"1961 GA",
    "sg:province":"Georgia",
    "wof:name":"Zeitzen",
    "wof:placetype":"venue"
},
  "geometry": {"coordinates":[-83.222931,32.678131],"type":"Point"}
}