{
  "type": "Feature",
  "properties": {
    "iso:country":"NL",
    "sg:address":"Alm 43",
    "sg:city":"Zwolle",
    "sg:orig_category":"Onderhoudswerken",
    "sg:phone":"+31 38 465 7002",
    "sg:postcode":"8032 BK",
    "sg:province":"Overijssel",
    "wof:name":"Oosten, J Van",
    "wof:placetype":"venue"
},
  "geometry": {"coordinates":[6.107471,52.525616],"type":"Point"}
}