{
  "type": "Feature",
  "properties": {
    "addr:full":"Paarlaarstg 7 Haarlem Noord-Holland 2011 TA",
    "addr:housenumber":"7",
    "addr:postcode":"2011 ta",
    "addr:street":"Paarlaarstg",
    "iso:country":"NL",
    "sg:address":"Paarlaarstg 7",
    "sg:city":"Haarlem",
    "sg:orig_category":"Koffie- En Theehuizen",
    "sg:phone":"+31 23 531 5051",
    "sg:postcode":"2011 TA",
    "sg:province":"Noord-Holland",
    "wof:name":"Steegje, Het",
    "wof:placetype":"venue"
},
  "geometry": {"coordinates":[4.635115,52.380833],"type":"Point"}
}