{
  "type": "Feature",
  "properties": {
    "addr:full":"Oostzeedijk 220 Rotterdam Zuid-Holland 3063 BN",
    "addr:housenumber":"220",
    "addr:postcode":"3063 bn",
    "addr:street":"Oostzeedijk",
    "iso:country":"NL",
    "sg:address":"Oostzeedijk 220",
    "sg:city":"Rotterdam",
    "sg:classifiers":[
        {
            "category":"Communications",
            "subcategory":"Television Station",
            "type":"Services"
        }
    ],
    "sg:phone":"+31 10 453 2210",
    "sg:postcode":"3063 BN",
    "sg:province":"Zuid-Holland",
    "sg:tags":[
        "video",
        "audio",
        "verhuur"
    ],
    "wof:name":"De Filmfreak Oostzeedijk",
    "wof:placetype":"venue"
},
  "geometry": {"coordinates":[4.50599,51.92157],"type":"Point"}
}