{
  "type": "Feature",
  "properties": {
    "iso:country":"NL",
    "sg:address":"Pr Hendrikln 21",
    "sg:city":"Helmond",
    "sg:orig_category":"Video - Faciliteiten En Producties",
    "sg:phone":"+31 492 539 523",
    "sg:postcode":"5707 CJ",
    "sg:province":"North Brabant",
    "wof:name":"Broek Productions Bv, Van Den",
    "wof:placetype":"venue"
},
  "geometry": {"coordinates":[5.644666,51.478508],"type":"Point"}
}