{
  "type": "Feature",
  "properties": {
    "iso:country":"NL",
    "sg:address":"Dorpsstraat 129",
    "sg:city":"Zevenhuizen Zh",
    "sg:orig_category":"Banken And Kredietinstellingen",
    "sg:phone":"+31 180 631 999",
    "sg:postcode":"2761 AL",
    "sg:province":"Zuid-Holland",
    "wof:name":"Postkantoor",
    "wof:placetype":"venue"
},
  "geometry": {"coordinates":[4.580302,52.012947],"type":"Point"}
}