{
  "type": "Feature",
  "properties": {
    "addr:full":"Ryndk 125A Hazerswoude Ryndyk Zuid-Holland 2394 AG",
    "addr:housenumber":"125a",
    "addr:postcode":"2394",
    "addr:street":"Hazerswoude Ryndyk",
    "iso:country":"NL",
    "sg:address":"Ryndk 125A",
    "sg:city":"Hazerswoude Ryndyk",
    "sg:orig_category":"Balletscholen",
    "sg:phone":"+31 71 341 9248",
    "sg:postcode":"2394 AG",
    "sg:province":"Zuid-Holland",
    "wof:name":"Mirjam Ouwerkerk",
    "wof:placetype":"venue"
},
  "geometry": {"coordinates":[4.595154,52.131054],"type":"Point"}
}