{
  "type": "Feature",
  "properties": {
    "addr:full":"Asingastr 37 Ulrum Groningen 9971 CA",
    "addr:housenumber":"37",
    "addr:postcode":"9971 ca",
    "addr:street":"Asingastr",
    "iso:country":"NL",
    "sg:address":"Asingastr 37",
    "sg:city":"Ulrum",
    "sg:orig_category":"Boeken En Tijdschriften",
    "sg:phone":"+31 595 401 245",
    "sg:postcode":"9971 CA",
    "sg:province":"Groningen",
    "wof:name":"Wichers-Janssens, G",
    "wof:placetype":"venue"
},
  "geometry": {"coordinates":[6.335267,53.358662],"type":"Point"}
}