{
  "type": "Feature",
  "properties": {
    "iso:country":"NL",
    "sg:address":"Haarlemmerdk 57",
    "sg:city":"Amsterdam",
    "sg:classifiers":[
        {
            "category":"Shopping",
            "subcategory":"Adult",
            "type":"Retail Goods"
        }
    ],
    "sg:phone":"+31 20 624 3876",
    "sg:postcode":"1013 KB",
    "sg:province":"Noord-Holland",
    "sg:tags":[
        "lingerie",
        "en",
        "tricotage"
    ],
    "wof:name":"Mary-Ann Lingerie",
    "wof:placetype":"venue"
},
  "geometry": {"coordinates":[4.887568,52.382309],"type":"Point"}
}