{
  "type": "Feature",
  "properties": {
    "addr:full":"Pannenwg 304/306 Nederweert Limburg 6031 RK",
    "addr:housenumber":"304 / 306",
    "addr:postcode":"6031 rk",
    "iso:country":"NL",
    "sg:address":"Pannenwg 304/306",
    "sg:city":"Nederweert",
    "sg:orig_category":"Verhuur",
    "sg:phone":"+31 495 634 397",
    "sg:postcode":"6031 RK",
    "sg:province":"Limburg",
    "sg:website":"http://www.events-unlimited.nl",
    "wof:name":"Events Unlimited Bv",
    "wof:placetype":"venue"
},
  "geometry": {"coordinates":[5.751013,51.276253],"type":"Point"}
}