{
  "type": "Feature",
  "properties": {
    "addr:full":"Middelwyk 39 Drachten Friesland 9202 GN",
    "addr:housenumber":"39",
    "addr:postcode":"9202 gn",
    "addr:street":"Middelwyk",
    "iso:country":"NL",
    "sg:address":"Middelwyk 39",
    "sg:city":"Drachten",
    "sg:orig_category":"Discountwinkels",
    "sg:phone":"+31 512 518 750",
    "sg:postcode":"9202 GN",
    "sg:province":"Friesland",
    "wof:name":"Pieter Spinder",
    "wof:placetype":"venue"
},
  "geometry": {"coordinates":[6.112366,53.109547],"type":"Point"}
}