{
  "type": "Feature",
  "properties": {
    "addr:full":"Pastoor Van Winkelstraat 110 Schaijk North Brabant 5374 BL",
    "addr:housenumber":"110",
    "addr:postcode":"5374 bl",
    "addr:street":"Pastoor Van Winkelstraat",
    "iso:country":"NL",
    "sg:address":"Pastoor Van Winkelstraat 110",
    "sg:city":"Schaijk",
    "sg:orig_category":"Fietshandelaren",
    "sg:phone":"+31 486 461 392",
    "sg:postcode":"5374 BL",
    "sg:province":"North Brabant",
    "wof:name":"J. Appelhof Tweewielerbedrijf",
    "wof:placetype":"venue"
},
  "geometry": {"coordinates":[5.65255,51.745071],"type":"Point"}
}