{
  "type": "Feature",
  "properties": {
    "addr:full":"Torenzichtln 2 Leersum Utrecht 3956 HA",
    "addr:housenumber":"2",
    "addr:postcode":"3956 ha",
    "addr:street":"Torenzichtln",
    "iso:country":"NL",
    "sg:address":"Torenzichtln 2",
    "sg:city":"Leersum",
    "sg:orig_category":"Bejaarden - Verzorgingstehuizen",
    "sg:phone":"+31 343 459 459",
    "sg:postcode":"3956 HA",
    "sg:province":"Utrecht",
    "wof:name":"Schermerij, De",
    "wof:placetype":"venue"
},
  "geometry": {"coordinates":[5.431821,52.009537],"type":"Point"}
}