{
  "type": "Feature",
  "properties": {
    "addr:full":"Burg Winklerpln 18 Sliedrecht Zuid-Holland 3362 AA",
    "addr:housenumber":"18",
    "addr:postcode":"3362 aa",
    "addr:street":"Burg",
    "iso:country":"NL",
    "sg:address":"Burg Winklerpln 18",
    "sg:city":"Sliedrecht",
    "sg:orig_category":"Schoenen",
    "sg:phone":"+31 184 412 977",
    "sg:postcode":"3362 AA",
    "sg:province":"Zuid-Holland",
    "wof:name":"Huijbregts",
    "wof:placetype":"venue"
},
  "geometry": {"coordinates":[4.777282,51.822643],"type":"Point"}
}