{
  "type": "Feature",
  "properties": {
    "addr:full":"Dr Ottenstr 52 Simpelveld Limburg 6369 VP",
    "addr:housenumber":"52",
    "addr:postcode":"6369 vp",
    "iso:country":"NL",
    "sg:address":"Dr Ottenstr 52",
    "sg:city":"Simpelveld",
    "sg:orig_category":"Verenigingen En Stichtingen",
    "sg:phone":"+31 45 544 1113",
    "sg:postcode":"6369 VP",
    "sg:province":"Limburg",
    "wof:name":"Swobs",
    "wof:placetype":"venue"
},
  "geometry": {"coordinates":[5.982154,50.83474],"type":"Point"}
}