{
  "type": "Feature",
  "properties": {
    "addr:full":"Zuiderzeestraatweg West 44 Doornspijk Gelderland 8085 AG",
    "addr:housenumber":"44",
    "addr:postcode":"8085",
    "addr:street":"Zuiderzeestraatweg West;Gelderland",
    "iso:country":"NL",
    "sg:address":"Zuiderzeestraatweg West 44",
    "sg:city":"Doornspijk",
    "sg:orig_category":"Warenhuizen",
    "sg:phone":"+31 525 661 291",
    "sg:postcode":"8085 AG",
    "sg:province":"Gelderland",
    "wof:name":"Fa. Vlieger En Van Boven",
    "wof:placetype":"venue"
},
  "geometry": {"coordinates":[5.8226261139,52.4211425781],"type":"Point"}
}