{
  "type": "Feature",
  "properties": {
    "addr:full":"Demmerik 94A Vinkeveen Utrecht 3645 EE",
    "addr:housenumber":"94a",
    "addr:postcode":"3645 ee",
    "addr:street":"Demmerik",
    "iso:country":"NL",
    "sg:address":"Demmerik 94A",
    "sg:city":"Vinkeveen",
    "sg:orig_category":"Grafische Materialen",
    "sg:phone":"+31 297 262 251",
    "sg:postcode":"3645 EE",
    "sg:province":"Utrecht",
    "wof:name":"Howarine Ned Bv",
    "wof:placetype":"venue"
},
  "geometry": {"coordinates":[4.931948,52.204784],"type":"Point"}
}