{
  "type": "Feature",
  "properties": {
    "iso:country":"NL",
    "sg:address":"Koninginneweg 17",
    "sg:city":"Hilversum",
    "sg:orig_category":"Artiestenbureaus",
    "sg:phone":"+31 35 628 5055",
    "sg:postcode":"1217 KR",
    "sg:province":"Noord-Holland",
    "sg:website":"http://www.dutch-artists.nl",
    "wof:name":"Dutch Artists Management B.V.",
    "wof:placetype":"venue"
},
  "geometry": {"coordinates":[5.168716,52.22971],"type":"Point"}
}