{
  "type": "Feature",
  "properties": {
    "iso:country":"NL",
    "sg:address":"Dommelstr 21-62",
    "sg:city":"Oss",
    "sg:orig_category":"Betonijzervlechten",
    "sg:phone":"+31 412 404 560",
    "sg:postcode":"5347 JK",
    "sg:province":"Noord-Brabant",
    "wof:name":"Esch & Zonen",
    "wof:placetype":"venue"
},
  "geometry": {"coordinates":[-77.235214,38.312599],"type":"Point"}
}