{
  "type": "Feature",
  "properties": {
    "iso:country":"NL",
    "sg:address":"P V Ypelaarstr 58",
    "sg:city":"Geertruidenberg",
    "sg:orig_category":"Koffie-Automaten",
    "sg:phone":"+31 162 521 266",
    "sg:postcode":"4931 RX",
    "sg:province":"North Brabant",
    "wof:name":"Jan Som",
    "wof:placetype":"venue"
},
  "geometry": {"coordinates":[4.858335,51.701351],"type":"Point"}
}