{
  "type": "Feature",
  "properties": {
    "addr:full":"Hoogvenne Kazernehof 76 Tilburg Noord-Brabant 5017 EV",
    "addr:housenumber":"76",
    "addr:postcode":"5017 ev",
    "addr:street":"Kazernehof",
    "iso:country":"NL",
    "sg:address":"Hoogvenne Kazernehof 76",
    "sg:city":"Tilburg",
    "sg:orig_category":"Overheidsdiensten",
    "sg:phone":"+31 13 542 2730",
    "sg:postcode":"5017 EV",
    "sg:province":"Noord-Brabant",
    "wof:name":"Hoog Venne",
    "wof:placetype":"venue"
},
  "geometry": {"coordinates":[5.0927801132,51.5564804077],"type":"Point"}
}