{
  "type": "Feature",
  "properties": {
    "addr:full":"Kerkstr 6 Loenen Ad Vecht Utrecht 3632 EL",
    "addr:housenumber":"6",
    "addr:postcode":"3632 el",
    "addr:street":"Kerkstr;Vecht",
    "iso:country":"NL",
    "sg:address":"Kerkstr 6",
    "sg:city":"Loenen Ad Vecht",
    "sg:orig_category":"Logopedisten",
    "sg:phone":"+31 294 234 510",
    "sg:postcode":"3632 EL",
    "sg:province":"Utrecht",
    "wof:name":"Essen-Lettinga, A T Van",
    "wof:placetype":"venue"
},
  "geometry": {"coordinates":[5.011726,52.222843],"type":"Point"}
}