{
  "type": "Feature",
  "properties": {
    "addr:full":"Binnenpad 53 Giethoorn NL.08 8355 BS",
    "addr:housenumber":"53;nl.08",
    "addr:postcode":"8355 bs",
    "addr:street":"Binnenpad",
    "iso:country":"NL",
    "sg:address":"Binnenpad 53",
    "sg:city":"Giethoorn",
    "sg:orig_category":"Architecten En Architectenbureaus",
    "sg:phone":"+31 521 362 629",
    "sg:postcode":"8355 BS",
    "sg:province":"NL.08",
    "wof:name":"Mulder, Ton",
    "wof:placetype":"venue"
},
  "geometry": {"coordinates":[6.089728,52.72295],"type":"Point"}
}