{
  "type": "Feature",
  "properties": {
    "addr:full":"Waaldk 13 Slyk Ewyk Gelderland 6677 MA",
    "addr:housenumber":"13",
    "addr:postcode":"6677 ma",
    "addr:street":"Waaldk;Gelderland",
    "iso:country":"NL",
    "sg:address":"Waaldk 13",
    "sg:city":"Slyk Ewyk",
    "sg:orig_category":"Bestratingen",
    "sg:phone":"+31 481 481 394",
    "sg:postcode":"6677 MA",
    "sg:province":"Gelderland",
    "wof:name":"Elings",
    "wof:placetype":"venue"
},
  "geometry": {"coordinates":[5.768295,51.88586],"type":"Point"}
}