{
  "type": "Feature",
  "properties": {
    "addr:full":"Kirunastr 21 Hengelo Ov Overijssel 7559 JH",
    "addr:housenumber":"21",
    "addr:postcode":"7559 jh",
    "addr:street":"Kirunastr;Ov",
    "iso:country":"NL",
    "sg:address":"Kirunastr 21",
    "sg:city":"Hengelo Ov",
    "sg:orig_category":"Schilders",
    "sg:phone":"+31 74 278 3436",
    "sg:postcode":"7559 JH",
    "sg:province":"Overijssel",
    "sg:website":"http://www.barinkschilderwerken.nl",
    "wof:name":"Barink Schilderwerken",
    "wof:placetype":"venue"
},
  "geometry": {"coordinates":[6.796242,52.294769],"type":"Point"}
}