{
  "type": "Feature",
  "properties": {
    "addr:full":"Gommerskerspel 25 Nieuw Vennep North Holland 2151 RB",
    "addr:housenumber":"25",
    "addr:postcode":"2151 rb",
    "addr:street":"Gommerskerspel;Nieuw Vennep North",
    "iso:country":"NL",
    "sg:address":"Gommerskerspel 25",
    "sg:city":"Nieuw Vennep",
    "sg:orig_category":"Loodgieterswerk, Verwarming And Sanitaire Installaties",
    "sg:phone":"+31 252 686 182",
    "sg:postcode":"2151 RB",
    "sg:province":"North Holland",
    "wof:name":"Petmar Montage Service",
    "wof:placetype":"venue"
},
  "geometry": {"coordinates":[4.619213,52.259178],"type":"Point"}
}