{
  "type": "Feature",
  "properties": {
    "iso:country":"NL",
    "sg:address":"Amersfoortsestr 84A",
    "sg:city":"Soesterberg",
    "sg:orig_category":"Opticiens",
    "sg:phone":"+31 33 469 7200",
    "sg:postcode":"3769 AM",
    "sg:province":"Utrecht",
    "wof:name":"Pearle Opticiens",
    "wof:placetype":"venue"
},
  "geometry": {"coordinates":[5.3178668022,52.1293640137],"type":"Point"}
}