{
  "type": "Feature",
  "properties": {
    "iso:country":"NL",
    "sg:address":"Hoofdstraat 54",
    "sg:city":"Noordwijk Zh",
    "sg:orig_category":"Verlichting And Huishoudartikelen",
    "sg:phone":"+31 71 361 2951",
    "sg:postcode":"2202 GB",
    "sg:province":"South Holland",
    "wof:name":"Blokker",
    "wof:placetype":"venue"
},
  "geometry": {"coordinates":[4.432121,52.243092],"type":"Point"}
}