{
  "type": "Feature",
  "properties": {
    "iso:country":"NL",
    "sg:address":"Schansburg 1",
    "sg:city":"Gorredijk",
    "sg:orig_category":"Bibliotheken En Leeszalen Openbare",
    "sg:phone":"+31 513 461 548",
    "sg:postcode":"8401 RX",
    "sg:province":"Provincie Friesland",
    "wof:name":"Openb Bibliotheek",
    "wof:placetype":"venue"
},
  "geometry": {"coordinates":[6.065486,53.003952],"type":"Point"}
}