{
  "type": "Feature",
  "properties": {
    "addr:full":"Ln V Sarsina 6 Lopik Utrecht 3411 GC",
    "addr:housenumber":"6",
    "addr:postcode":"3411 gc",
    "addr:street":"Ln V Sarsina",
    "iso:country":"NL",
    "sg:address":"Ln V Sarsina 6",
    "sg:city":"Lopik",
    "sg:orig_category":"Betonijzervlechten",
    "sg:phone":"+31 348 553 107",
    "sg:postcode":"3411 GC",
    "sg:province":"Utrecht",
    "wof:name":"Betonstaal Montage Lopik",
    "wof:placetype":"venue"
},
  "geometry": {"coordinates":[4.945286,51.97467],"type":"Point"}
}