{
  "type": "Feature",
  "properties": {
    "addr:full":"Molenstraat 64 Vught North Brabant 5262 EE",
    "addr:housenumber":"64",
    "addr:postcode":"5262 ee",
    "addr:street":"Molenstraat",
    "iso:country":"NL",
    "sg:address":"Molenstraat 64",
    "sg:city":"Vught",
    "sg:orig_category":"Elektronische Bedrijfsinstallaties",
    "sg:phone":"+31 73 656 3079",
    "sg:postcode":"5262 EE",
    "sg:province":"North Brabant",
    "wof:name":"De Bruijn Bliksembeveiliging",
    "wof:placetype":"venue"
},
  "geometry": {"coordinates":[5.279279,51.645859],"type":"Point"}
}