{
  "type": "Feature",
  "properties": {
    "addr:full":"Stationstraat 1 Boxtel Noord-Brabant 5281 GA",
    "addr:housenumber":"1",
    "addr:postcode":"5281 ga",
    "addr:street":"Stationstraat",
    "iso:country":"NL",
    "sg:address":"Stationstraat 1",
    "sg:city":"Boxtel",
    "sg:orig_category":"Opticiens",
    "sg:phone":"+31 411 672 176",
    "sg:postcode":"5281 GA",
    "sg:province":"Noord-Brabant",
    "wof:name":"Zwart Optiek",
    "wof:placetype":"venue"
},
  "geometry": {"coordinates":[5.3242578506,51.5882263184],"type":"Point"}
}