{
  "type": "Feature",
  "properties": {
    "addr:full":"Aristoteleslaan 28 Zeist Utrecht 3707 EL",
    "addr:housenumber":"28",
    "addr:postcode":"3707 el",
    "addr:street":"Aristoteleslaan",
    "iso:country":"NL",
    "sg:address":"Aristoteleslaan 28",
    "sg:city":"Zeist",
    "sg:orig_category":"Artsen And Specialisten",
    "sg:phone":"+31 30 692 2700",
    "sg:postcode":"3707 EL",
    "sg:province":"Utrecht",
    "wof:name":"Centrum Voor Psycho- En Seksuologische Hulpverl",
    "wof:placetype":"venue"
},
  "geometry": {"coordinates":[5.257352,52.090996],"type":"Point"}
}