{
  "type": "Feature",
  "properties": {
    "addr:full":"Borgmanwg 15 Hengelo Ov NL.08 7558 PN",
    "addr:housenumber":"15",
    "addr:postcode":"7558 pn",
    "addr:street":"Borgmanwg;Ov",
    "iso:country":"NL",
    "sg:address":"Borgmanwg 15",
    "sg:city":"Hengelo Ov",
    "sg:orig_category":"Mineralen",
    "sg:phone":"+31 74 277 0709",
    "sg:postcode":"7558 PN",
    "sg:province":"NL.08",
    "sg:website":"http://www.bodemschat.nl",
    "wof:name":"Bodemschat, De",
    "wof:placetype":"venue"
},
  "geometry": {"coordinates":[6.845258,52.285885],"type":"Point"}
}