{
  "type": "Feature",
  "properties": {
    "iso:country":"NL",
    "sg:address":"Gerberaln 48",
    "sg:city":"Naaldwyk",
    "sg:orig_category":"Bedrijfsopleidingen",
    "sg:phone":"+31 174 629 223",
    "sg:postcode":"2671 KE",
    "sg:province":"Zuid-Holland",
    "wof:name":"Ts-Lotus",
    "wof:placetype":"venue"
},
  "geometry": {"coordinates":[4.205249,51.991398],"type":"Point"}
}