{
  "type": "Feature",
  "properties": {
    "addr:full":"Poortershaven 3 Hoek Van Holland Zuid-Holland 3151 XT",
    "addr:housenumber":"3",
    "addr:postcode":"3151 xt",
    "addr:street":"Poortershaven",
    "iso:country":"NL",
    "sg:address":"Poortershaven 3",
    "sg:city":"Hoek Van Holland",
    "sg:classifiers":[
        {
            "category":"Food & Beverages",
            "subcategory":"Fruits & Vegetables",
            "type":"Retail Goods"
        }
    ],
    "sg:phone":"+31 6 53246678",
    "sg:postcode":"3151 XT",
    "sg:province":"Zuid-Holland",
    "sg:tags":[
        "groenten"
    ],
    "wof:name":"Koelhuis Poortershaven",
    "wof:placetype":"venue"
},
  "geometry": {"coordinates":[4.214599,51.936821],"type":"Point"}
}