{
  "type": "Feature",
  "properties": {
    "addr:full":"Geestdorp 35D Woerden Utrecht 3444 BE",
    "addr:housenumber":"35d",
    "addr:postcode":"3444",
    "addr:street":"Geestdorp",
    "iso:country":"NL",
    "sg:address":"Geestdorp 35D",
    "sg:city":"Woerden",
    "sg:orig_category":"Loodgieters",
    "sg:phone":"+31 348 411 072",
    "sg:postcode":"3444 BE",
    "sg:province":"Utrecht",
    "wof:name":"Snel, F H",
    "wof:placetype":"venue"
},
  "geometry": {"coordinates":[4.922199,52.10323],"type":"Point"}
}