{
  "type": "Feature",
  "properties": {
    "iso:country":"NL",
    "sg:address":"Lindeln 34",
    "sg:city":"Heemstede",
    "sg:orig_category":"Verzekeringen - Verzekeringskantoren",
    "sg:phone":"+31 23 528 2385",
    "sg:postcode":"2101 XJ",
    "sg:province":"North Holland",
    "wof:name":"Prins",
    "wof:placetype":"venue"
},
  "geometry": {"coordinates":[4.6212477684,52.345287323],"type":"Point"}
}