{
  "type": "Feature",
  "properties": {
    "addr:full":"Adm De Ruyterwg 220 2Hg Amsterdam Noord-Holland 1055 ML",
    "addr:housenumber":"220",
    "addr:postcode":"1055 ml",
    "addr:street":"2Hg",
    "iso:country":"NL",
    "sg:address":"Adm De Ruyterwg 220 2Hg",
    "sg:city":"Amsterdam",
    "sg:orig_category":"Webdesign Bureaus",
    "sg:phone":"+31 20 686 1117",
    "sg:postcode":"1055 ML",
    "sg:province":"Noord-Holland",
    "sg:website":"http://www.sitemate.nl",
    "wof:name":"Sitemate",
    "wof:placetype":"venue"
},
  "geometry": {"coordinates":[4.8533701897,52.3804092407],"type":"Point"}
}