{
  "type": "Feature",
  "properties": {
    "addr:full":"Piusstraat 124 Tilburg Noord-Brabant 5021 JC",
    "addr:housenumber":"124",
    "addr:postcode":"5021 jc",
    "addr:street":"Piusstraat",
    "iso:country":"NL",
    "sg:address":"Piusstraat 124",
    "sg:city":"Tilburg",
    "sg:classifiers":[
        {
            "category":"Bars & Pubs",
            "type":"Food & Drink"
        }
    ],
    "sg:phone":"+31 13 543 3400",
    "sg:postcode":"5021 JC",
    "sg:province":"Noord-Brabant",
    "wof:name":"Ochtendgloren",
    "wof:placetype":"venue"
},
  "geometry": {"coordinates":[5.088784,51.550484],"type":"Point"}
}