{
  "type": "Feature",
  "properties": {
    "addr:full":"Van Genkstraat 10 Etten-Leur North Brabant 4871 XA",
    "addr:housenumber":"10",
    "addr:postcode":"4871 xa",
    "addr:street":"Van Genkstraat",
    "iso:country":"NL",
    "sg:address":"Van Genkstraat 10",
    "sg:city":"Etten-Leur",
    "sg:classifiers":[
        {
            "category":"Education",
            "subcategory":"Preschool",
            "type":"Public Place"
        }
    ],
    "sg:phone":"+31 76 503 4518",
    "sg:postcode":"4871 XA",
    "sg:province":"North Brabant",
    "sg:tags":[
        "kleuteronderwijs",
        "basis-"
    ],
    "wof:name":"Het Kompas",
    "wof:placetype":"venue"
},
  "geometry": {"coordinates":[4.647788,51.584023],"type":"Point"}
}