{
  "type": "Feature",
  "properties": {
    "addr:full":"Beethovenstr 3 Amsterdam Noord-Holland 1077 HK",
    "addr:housenumber":"3",
    "addr:postcode":"1077 hk",
    "addr:street":"Beethovenstr",
    "iso:country":"NL",
    "sg:address":"Beethovenstr 3",
    "sg:city":"Amsterdam",
    "sg:orig_category":"Woninginrichting",
    "sg:phone":"+31 20 627 1341",
    "sg:postcode":"1077 HK",
    "sg:province":"Noord-Holland",
    "wof:name":"Hella Pais",
    "wof:placetype":"venue"
},
  "geometry": {"coordinates":[4.8785758018,52.3501548767],"type":"Point"}
}