{
  "type": "Feature",
  "properties": {
    "addr:full":"Wolfstr 7 Maastricht Limburg 6211 GM",
    "addr:housenumber":"7",
    "addr:postcode":"6211 gm",
    "addr:street":"Wolfstr",
    "iso:country":"NL",
    "sg:address":"Wolfstr 7",
    "sg:city":"Maastricht",
    "sg:orig_category":"Juweliers",
    "sg:phone":"+31 43 321 7392",
    "sg:postcode":"6211 GM",
    "sg:province":"Limburg",
    "wof:name":"Hochstenbach, Chrit",
    "wof:placetype":"venue"
},
  "geometry": {"coordinates":[5.692824,50.84877],"type":"Point"}
}