{
  "type": "Feature",
  "properties": {
    "addr:full":"Lakenkoperswg 36 Weesp North Holland 1383 CT",
    "addr:housenumber":"36",
    "addr:postcode":"1383 ct",
    "addr:street":"Lakenkoperswg",
    "iso:country":"NL",
    "sg:address":"Lakenkoperswg 36",
    "sg:city":"Weesp",
    "sg:orig_category":"Kantoor- En Interieurbeplanting",
    "sg:phone":"+31 294 432 205",
    "sg:postcode":"1383 CT",
    "sg:province":"North Holland",
    "sg:website":"http://www.plantservice.nl",
    "wof:name":"Plantservice",
    "wof:placetype":"venue"
},
  "geometry": {"coordinates":[5.0373649597,52.2991256714],"type":"Point"}
}