{
  "type": "Feature",
  "properties": {
    "iso:country":"NL",
    "sg:address":"Bloemendaalseweg 158",
    "sg:city":"Overveen",
    "sg:orig_category":"Overheidsdiensten",
    "sg:phone":"+31 23 522 5555",
    "sg:postcode":"2051 GJ",
    "sg:province":"North Holland",
    "wof:name":"Gemeente Bloemendaal",
    "wof:placetype":"venue"
},
  "geometry": {"coordinates":[4.6125721931,52.3967247009],"type":"Point"}
}