{
  "type": "Feature",
  "properties": {
    "addr:full":"Zaagmolenstraat 48 Rotterdam Zuid-Holland 3035 HC",
    "addr:housenumber":"48",
    "addr:postcode":"3035 hc",
    "addr:street":"Zaagmolenstraat",
    "iso:country":"NL",
    "sg:address":"Zaagmolenstraat 48",
    "sg:city":"Rotterdam",
    "sg:orig_category":"Goederenvervoer Over De Weg",
    "sg:phone":"+31 10 465 7415",
    "sg:postcode":"3035 HC",
    "sg:province":"Zuid-Holland",
    "wof:name":"Uljee & Zoon Hodn Zeilstra",
    "wof:placetype":"venue"
},
  "geometry": {"coordinates":[4.487163,51.933331],"type":"Point"}
}