{
  "type": "Feature",
  "properties": {
    "addr:full":"L Willemstg 6 Gouda South Holland 2801 WC",
    "addr:housenumber":"6",
    "addr:postcode":"2801 wc",
    "iso:country":"NL",
    "sg:address":"L Willemstg 6",
    "sg:city":"Gouda",
    "sg:orig_category":"Bliksembeveiliging",
    "sg:phone":"+31 182 527 717",
    "sg:postcode":"2801 WC",
    "sg:province":"South Holland",
    "wof:name":"Static-Care Bv",
    "wof:placetype":"venue"
},
  "geometry": {"coordinates":[4.708097,52.008896],"type":"Point"}
}