{
  "type": "Feature",
  "properties": {
    "iso:country":"NL",
    "sg:address":"Johanna Naberstraat 41",
    "sg:city":"Alkmaar",
    "sg:orig_category":"Kappers",
    "sg:phone":"+31 72 562 5871",
    "sg:postcode":"1827 LA",
    "sg:province":"North Holland",
    "wof:name":"Kapsalon Ro En Friends",
    "wof:placetype":"venue"
},
  "geometry": {"coordinates":[4.7668018341,52.6656608582],"type":"Point"}
}