{
  "type": "Feature",
  "properties": {
    "addr:full":"Wittebrinkweg 9 Zelhem Gelderland 7021 KK",
    "addr:housenumber":"9",
    "addr:postcode":"7021 kk",
    "addr:street":"Wittebrinkweg;Gelderland",
    "iso:country":"NL",
    "sg:address":"Wittebrinkweg 9",
    "sg:city":"Zelhem",
    "sg:orig_category":"Granen, Zaden And Diervoeders Gh",
    "sg:phone":"+31 314 335 745",
    "sg:postcode":"7021 KK",
    "sg:province":"Gelderland",
    "wof:name":"Veevoederhandel Frans Evers",
    "wof:placetype":"venue"
},
  "geometry": {"coordinates":[6.298583,51.995842],"type":"Point"}
}