{
  "type": "Feature",
  "properties": {
    "addr:full":"Bourgondieweg 98C Bovenkarspel Noord-Holland 1611 WL",
    "addr:housenumber":"98c",
    "addr:postcode":"1611 wl",
    "addr:street":"Bourgondieweg",
    "iso:country":"NL",
    "sg:address":"Bourgondieweg 98C",
    "sg:city":"Bovenkarspel",
    "sg:classifiers":[
        {
            "category":"Education",
            "subcategory":"Preschool",
            "type":"Public Place"
        }
    ],
    "sg:phone":"+31 228 518 166",
    "sg:postcode":"1611 WL",
    "sg:province":"Noord-Holland",
    "sg:tags":[
        "kleuteronderwijs",
        "basis-"
    ],
    "wof:name":"Peuterspeelzaal De Oostersluis Drie Turven",
    "wof:placetype":"venue"
},
  "geometry": {"coordinates":[5.238959,52.690853],"type":"Point"}
}