{
  "type": "Feature",
  "properties": {
    "iso:country":"NL",
    "sg:address":"Struik 11",
    "sg:city":"Schimmert",
    "sg:orig_category":"Adviesbureaus Gezondheidszorg",
    "sg:phone":"+31 45 404 1237",
    "sg:postcode":"6333 BP",
    "sg:province":"Limburg",
    "wof:name":"Peeters, Advies & Management",
    "wof:placetype":"venue"
},
  "geometry": {"coordinates":[5.828936,50.90781],"type":"Point"}
}