{
  "type": "Feature",
  "properties": {
    "addr:full":"Loodsweg 13 Westknollendam North Holland 1525 RH",
    "addr:housenumber":"13",
    "addr:postcode":"1525 rh",
    "addr:street":"Loodsweg",
    "iso:country":"NL",
    "sg:address":"Loodsweg 13",
    "sg:city":"Westknollendam",
    "sg:orig_category":"Etaleurs And Showroominrichters",
    "sg:phone":"+31 75 628 4391",
    "sg:postcode":"1525 RH",
    "sg:province":"North Holland",
    "wof:name":"G.J. Kijlstra",
    "wof:placetype":"venue"
},
  "geometry": {"coordinates":[4.776807,52.516312],"type":"Point"}
}