{
  "type": "Feature",
  "properties": {
    "iso:country":"NL",
    "sg:address":"Bunderweg 14",
    "sg:city":"Nieuweschans",
    "sg:orig_category":"Bibliotheken And Openbare Archieven",
    "sg:phone":"+31 597 521 528",
    "sg:postcode":"9693 BS",
    "sg:province":"Groningen",
    "wof:name":"Openbare Bibliotheek",
    "wof:placetype":"venue"
},
  "geometry": {"coordinates":[7.207798,53.182213],"type":"Point"}
}