{
  "type": "Feature",
  "properties": {
    "addr:full":"V Schendelstr 18 Groningen Groningen 9721 GW",
    "addr:housenumber":"18",
    "addr:postcode":"9721 gw",
    "iso:country":"NL",
    "sg:address":"V Schendelstr 18",
    "sg:city":"Groningen",
    "sg:orig_category":"Medische Installaties En Instrumenten",
    "sg:phone":"+31 50 527 2492",
    "sg:postcode":"9721 GW",
    "sg:province":"Groningen",
    "wof:name":"G\u00fclseren",
    "wof:placetype":"venue"
},
  "geometry": {"coordinates":[6.57473,53.194111],"type":"Point"}
}