{
  "type": "Feature",
  "properties": {
    "addr:full":"Turnerstr 12 Amsterdam Noord-Holland 1076 VD",
    "addr:housenumber":"12",
    "addr:postcode":"1076 vd",
    "addr:street":"Turnerstr",
    "iso:country":"NL",
    "sg:address":"Turnerstr 12",
    "sg:city":"Amsterdam",
    "sg:classifiers":[
        {
            "category":"Utilities",
            "subcategory":"Cable",
            "type":"Services"
        }
    ],
    "sg:phone":"+31 20 770 3247",
    "sg:postcode":"1076 VD",
    "sg:province":"Noord-Holland",
    "sg:tags":[
        "masseur",
        "en",
        "heilgymnasten"
    ],
    "wof:name":"Gase, G",
    "wof:placetype":"venue"
},
  "geometry": {"coordinates":[-74.11232800000001,42.977543],"type":"Point"}
}