{
  "type": "Feature",
  "properties": {
    "addr:full":"Vleutensewg 158 Utrecht Utrecht 3532 HN",
    "addr:housenumber":"158",
    "addr:postcode":"3532 hn",
    "iso:country":"NL",
    "sg:address":"Vleutensewg 158",
    "sg:city":"Utrecht",
    "sg:orig_category":"Woninginrichting",
    "sg:phone":"+31 30 299 2276",
    "sg:postcode":"3532 HN",
    "sg:province":"Utrecht",
    "wof:name":"Gina",
    "wof:placetype":"venue"
},
  "geometry": {"coordinates":[5.0993728638,52.0929527283],"type":"Point"}
}