{
  "type": "Feature",
  "properties": {
    "addr:full":"Bieslookgaarde 18 Gouda South Holland 2803 RC",
    "addr:housenumber":"18",
    "addr:postcode":"2803 rc",
    "addr:street":"Bieslookgaarde",
    "iso:country":"NL",
    "sg:address":"Bieslookgaarde 18",
    "sg:city":"Gouda",
    "sg:classifiers":[
        {
            "category":"Shopping",
            "subcategory":"Gifts & Souvenirs",
            "type":"Retail Goods"
        }
    ],
    "sg:phone":"+31 6 10696939",
    "sg:postcode":"2803 RC",
    "sg:province":"South Holland",
    "sg:tags":[
        "wens-",
        "en",
        "prentbriefkaarten"
    ],
    "sg:website":"http://www.p-oostcards.nl",
    "wof:name":"Oostcards, P",
    "wof:placetype":"venue"
},
  "geometry": {"coordinates":[4.6966309547,52.0287437439],"type":"Point"}
}