{
  "type": "Feature",
  "properties": {
    "iso:country":"NL",
    "sg:address":"De Dellen 16E",
    "sg:city":"Surhuisterveen",
    "sg:orig_category":"Juweliers",
    "sg:phone":"+31 512 361 733",
    "sg:postcode":"9231 EB",
    "sg:province":"Friesland",
    "wof:name":"Hoop, J De",
    "wof:placetype":"venue"
},
  "geometry": {"coordinates":[6.169268,53.183292],"type":"Point"}
}