{
  "type": "Feature",
  "properties": {
    "addr:full":"A Verherentstr 1 Heemskerk Noord-Holland 1961 GD",
    "addr:housenumber":"1",
    "addr:postcode":"1961 gd",
    "iso:country":"NL",
    "sg:address":"A Verherentstr 1",
    "sg:city":"Heemskerk",
    "sg:orig_category":"Verenigingsgebouwen",
    "sg:phone":"+31 251 230 995",
    "sg:postcode":"1961 GD",
    "sg:province":"Noord-Holland",
    "wof:name":"Donkey-Shot",
    "wof:placetype":"venue"
},
  "geometry": {"coordinates":[4.674467,52.511578],"type":"Point"}
}