{
  "type": "Feature",
  "properties": {
    "addr:full":"Dagelijkse Groenmarkt 28 'S Gravenhage Zuid-Holland 2513 AL",
    "addr:housenumber":"28",
    "addr:postcode":"2513 al",
    "addr:street":"Dagelijkse Groenmarkt;' S",
    "iso:country":"NL",
    "sg:address":"Dagelijkse Groenmarkt 28",
    "sg:city":"'S Gravenhage",
    "sg:orig_category":"Werving And Selectie Van Tijdelijk Personeel And Uitzendkantoren",
    "sg:phone":"+31 70 360 1815",
    "sg:postcode":"2513 AL",
    "sg:province":"Zuid-Holland",
    "wof:name":"Mailprofs Uitzendbureaux",
    "wof:placetype":"venue"
},
  "geometry": {"coordinates":[4.3088541031,52.0777015686],"type":"Point"}
}