{
  "type": "Feature",
  "properties": {
    "addr:full":"P. Potterstraat 26 Amsterdam Noord-Holland 1071 DA",
    "addr:housenumber":"26",
    "addr:postcode":"1071 da",
    "addr:street":"P. Potterstraat",
    "iso:country":"NL",
    "sg:address":"P. Potterstraat 26",
    "sg:city":"Amsterdam",
    "sg:orig_category":"Werving And Selectie Van Vast Personeel",
    "sg:phone":"+31 20 670 7717",
    "sg:postcode":"1071 DA",
    "sg:province":"Noord-Holland",
    "wof:name":"Job Score Werving & Selectie",
    "wof:placetype":"venue"
},
  "geometry": {"coordinates":[4.8806648254,52.3589286804],"type":"Point"}
}