{
  "type": "Feature",
  "properties": {
    "addr:full":"Lutterveldwg 6 Tiel Gelderland 4005 LD",
    "addr:housenumber":"6",
    "addr:postcode":"4005 ld",
    "addr:street":"Lutterveldwg;Gelderland",
    "iso:country":"NL",
    "sg:address":"Lutterveldwg 6",
    "sg:city":"Tiel",
    "sg:orig_category":"Woningbouw- Verenigingen En -Stichtingen",
    "sg:phone":"+31 344 615 214",
    "sg:postcode":"4005 LD",
    "sg:province":"Gelderland",
    "wof:name":"Volkshuisvesting Tiel, Sticht",
    "wof:placetype":"venue"
},
  "geometry": {"coordinates":[5.446595192,51.8975601196],"type":"Point"}
}