{
  "type": "Feature",
  "properties": {
    "addr:full":"Zwaansweg 12 Kedichem Zuid-Holland 4247 EX",
    "addr:housenumber":"12",
    "addr:postcode":"4247 ex",
    "addr:street":"Zwaansweg",
    "iso:country":"NL",
    "sg:address":"Zwaansweg 12",
    "sg:city":"Kedichem",
    "sg:orig_category":"Hypotheken And Hypotheekbanken",
    "sg:phone":"+31 183 561 127",
    "sg:postcode":"4247 EX",
    "sg:province":"Zuid-Holland",
    "wof:name":"M.A.F.S.",
    "wof:placetype":"venue"
},
  "geometry": {"coordinates":[5.047745,51.861279],"type":"Point"}
}