{
  "type": "Feature",
  "properties": {
    "iso:country":"NL",
    "sg:address":"Zwaansweg 12",
    "sg:city":"Kedichem",
    "sg:orig_category":"Hypotheken And Hypotheekbanken",
    "sg:phone":"+31 183 561 127",
    "sg:postcode":"4247 EX",
    "sg:province":"Zuid-Holland",
    "wof:name":"M.A.F.S.",
    "wof:placetype":"venue"
},
  "geometry": {"coordinates":[5.047745,51.861279],"type":"Point"}
}