{
  "type": "Feature",
  "properties": {
    "addr:full":"Putstraat 1 'T Loo Oldebroek Gelderland 8095 PV",
    "addr:housenumber":"1",
    "addr:postcode":"8095 pv",
    "addr:street":"Putstraat",
    "iso:country":"NL",
    "sg:address":"Putstraat 1",
    "sg:city":"'T Loo Oldebroek",
    "sg:orig_category":"Banken And Kredietinstellingen",
    "sg:phone":"+31 525 632 160",
    "sg:postcode":"8095 PV",
    "sg:province":"Gelderland",
    "wof:name":"Rabobank",
    "wof:placetype":"venue"
},
  "geometry": {"coordinates":[5.951053,52.444817],"type":"Point"}
}