{
  "type": "Feature",
  "properties": {
    "addr:full":"Wetterkant 5B Gorredyk Friesland 8401 GC",
    "addr:housenumber":"5b",
    "addr:postcode":"8401 gc",
    "addr:street":"Wetterkant",
    "iso:country":"NL",
    "sg:address":"Wetterkant 5B",
    "sg:city":"Gorredyk",
    "sg:classifiers":[
        {
            "category":"Wholesale",
            "subcategory":"Motor Vehicles",
            "type":"Manufacturing & Wholesale Goods"
        }
    ],
    "sg:phone":"+31 513 462 532",
    "sg:postcode":"8401 GC",
    "sg:province":"Friesland",
    "sg:tags":[
        "scooter",
        "en"
    ],
    "wof:name":"Harley Heaven",
    "wof:placetype":"venue"
},
  "geometry": {"coordinates":[6.053438,53.009342],"type":"Point"}
}