{
  "type": "Feature",
  "properties": {
    "iso:country":"NL",
    "sg:address":"Hendrikstr 4",
    "sg:city":"Beek Lb",
    "sg:orig_category":"Beeldende Kunstenaars",
    "sg:phone":"+31 46 437 4158",
    "sg:postcode":"6191 XN",
    "sg:province":"Limburg",
    "wof:name":"Ramakers, Jo",
    "wof:placetype":"venue"
},
  "geometry": {"coordinates":[-93.129936,36.705662],"type":"Point"}
}