{
  "type": "Feature",
  "properties": {
    "addr:full":"Voltastr 8 Leeuwarden Friesland 8912 AE",
    "addr:housenumber":"8",
    "addr:postcode":"8912 ae",
    "addr:street":"Voltastr",
    "iso:country":"NL",
    "sg:address":"Voltastr 8",
    "sg:city":"Leeuwarden",
    "sg:orig_category":"Geluidsinstallaties - Verhuur",
    "sg:phone":"+31 58 215 7003",
    "sg:postcode":"8912 AE",
    "sg:province":"Friesland",
    "sg:website":"http://www.infogvaudio.com",
    "wof:name":"Gv",
    "wof:placetype":"venue"
},
  "geometry": {"coordinates":[5.771632,53.19672],"type":"Point"}
}