{
  "type": "Feature",
  "properties": {
    "addr:full":"Nyverheidsbuurt 5 Zegveld Utrecht 3474 LA",
    "addr:housenumber":"5",
    "addr:postcode":"3474 la",
    "addr:street":"Nyverheidsbuurt",
    "iso:country":"NL",
    "sg:address":"Nyverheidsbuurt 5",
    "sg:city":"Zegveld",
    "sg:orig_category":"Machineonderhoud En -Reparatie",
    "sg:phone":"+31 348 692 388",
    "sg:postcode":"3474 LA",
    "sg:province":"Utrecht",
    "wof:name":"Donselaar",
    "wof:placetype":"venue"
},
  "geometry": {"coordinates":[4.849181,52.104839],"type":"Point"}
}