{
  "type": "Feature",
  "properties": {
    "addr:full":"Weverstr 33 Arnhem Gelderland 6811 EM",
    "addr:housenumber":"33",
    "addr:postcode":"6811 em",
    "addr:street":"Weverstr",
    "iso:country":"NL",
    "sg:address":"Weverstr 33",
    "sg:city":"Arnhem",
    "sg:orig_category":"Meubelen",
    "sg:phone":"+31 26 442 0840",
    "sg:postcode":"6811 EM",
    "sg:province":"Gelderland",
    "sg:website":"http://www.lundia.nl",
    "wof:name":"Lundia Bv",
    "wof:placetype":"venue"
},
  "geometry": {"coordinates":[5.906542,51.98032],"type":"Point"}
}