{
  "type": "Feature",
  "properties": {
    "addr:full":"Eekwal 16 Renkum Gelderland 6871 LS",
    "addr:housenumber":"16",
    "addr:postcode":"6871 ls",
    "addr:street":"Eekwal;Gelderland",
    "iso:country":"NL",
    "sg:address":"Eekwal 16",
    "sg:city":"Renkum",
    "sg:orig_category":"Kappers",
    "sg:phone":"+31 317 310 317",
    "sg:postcode":"6871 LS",
    "sg:province":"Gelderland",
    "wof:name":"A S",
    "wof:placetype":"venue"
},
  "geometry": {"coordinates":[5.7441139221,51.9839744568],"type":"Point"}
}