{
  "type": "Feature",
  "properties": {
    "iso:country":"NL",
    "sg:address":"Puccinistraat 32",
    "sg:city":"Zevenaar",
    "sg:orig_category":"Meubels And Huishoudapparatuur Gh",
    "sg:phone":"+31 316 343 023",
    "sg:postcode":"6904 EZ",
    "sg:province":"Gelderland",
    "wof:name":"Mamut",
    "wof:placetype":"venue"
},
  "geometry": {"coordinates":[6.05961,51.930485],"type":"Point"}
}