{
  "type": "Feature",
  "properties": {
    "addr:full":"Zeemanstraat 59 Barendrecht Zuid-Holland 2991 XR",
    "addr:housenumber":"59",
    "addr:postcode":"2991 xr",
    "addr:street":"Zeemanstraat",
    "iso:country":"NL",
    "sg:address":"Zeemanstraat 59",
    "sg:city":"Barendrecht",
    "sg:orig_category":"Elektronische Bedrijfsinstallaties",
    "sg:phone":"+31 10 292 7399",
    "sg:postcode":"2991 XR",
    "sg:province":"Zuid-Holland",
    "wof:name":"Jules Bliksembeveiliging Goossens Bv",
    "wof:placetype":"venue"
},
  "geometry": {"coordinates":[4.548061,51.867619],"type":"Point"}
}