{
  "type": "Feature",
  "properties": {
    "addr:full":"Borgercompagnie 90 Borgercompagnie Groningen 9631 TK",
    "addr:housenumber":"90",
    "addr:postcode":"9631 tk",
    "addr:street":"Borgercompagnie",
    "iso:country":"NL",
    "sg:address":"Borgercompagnie 90",
    "sg:city":"Borgercompagnie",
    "sg:orig_category":"Video - Faciliteiten En Producties",
    "sg:phone":"+31 598 620 868",
    "sg:postcode":"9631 TK",
    "sg:province":"Groningen",
    "sg:website":"http://www.cinetransferservice.nl",
    "wof:name":"Cin\u00e9 Transfer Service",
    "wof:placetype":"venue"
},
  "geometry": {"coordinates":[6.814098,53.123611],"type":"Point"}
}