{
  "type": "Feature",
  "properties": {
    "addr:full":"Rutbeekwg 130 Enschede Overijssel 7546 PR",
    "addr:housenumber":"130",
    "addr:postcode":"7546 pr",
    "iso:country":"NL",
    "sg:address":"Rutbeekwg 130",
    "sg:city":"Enschede",
    "sg:orig_category":"Grondwerken",
    "sg:phone":"+31 53 428 1455",
    "sg:postcode":"7546 PR",
    "sg:province":"Overijssel",
    "wof:name":"Eshuis, Frans",
    "wof:placetype":"venue"
},
  "geometry": {"coordinates":[6.804079,52.169319],"type":"Point"}
}