{
  "type": "Feature",
  "properties": {
    "addr:full":"Hoolhuis 6 Bunde Limburg 6241 GP",
    "addr:housenumber":"6",
    "addr:postcode":"6241 gp",
    "addr:street":"Hoolhuis",
    "iso:country":"NL",
    "sg:address":"Hoolhuis 6",
    "sg:city":"Bunde",
    "sg:orig_category":"Advocaten En Advocatenkantoren",
    "sg:phone":"+31 43 364 5321",
    "sg:postcode":"6241 GP",
    "sg:province":"Limburg",
    "wof:name":"Waelen, Mr H H M E",
    "wof:placetype":"venue"
},
  "geometry": {"coordinates":[5.74325,50.893562],"type":"Point"}
}