{
  "type": "Feature",
  "properties": {
    "iso:country":"NL",
    "sg:address":"Van Oldenbarneveldtweg 23",
    "sg:city":"Castricum",
    "sg:orig_category":"Verzekeringen",
    "sg:phone":"+31 251 651 034",
    "sg:postcode":"1901 KA",
    "sg:province":"Noord-Holland",
    "wof:name":"R.A.G.M. Kolenbrander, Verzekeringsconsulent",
    "wof:placetype":"venue"
},
  "geometry": {"coordinates":[4.663725,52.546844],"type":"Point"}
}