{
  "type": "Feature",
  "properties": {
    "addr:full":"Kruisweg 713 Hoofddorp North Holland 2132 ND",
    "addr:housenumber":"713",
    "addr:postcode":"2132 nd",
    "addr:street":"Kruisweg",
    "iso:country":"NL",
    "sg:address":"Kruisweg 713",
    "sg:city":"Hoofddorp",
    "sg:orig_category":"Verhuur Voertuigen Behalve Auto'S",
    "sg:phone":"+31 20 653 3442",
    "sg:postcode":"2132 ND",
    "sg:province":"North Holland",
    "wof:name":"Vervloed",
    "wof:placetype":"venue"
},
  "geometry": {"coordinates":[4.713675,52.294518],"type":"Point"}
}