{
  "type": "Feature",
  "properties": {
    "iso:country":"NL",
    "sg:address":"Edveensweg 3",
    "sg:city":"Oosterhesselen",
    "sg:orig_category":"Boekhouders",
    "sg:phone":"+31 524 582 289",
    "sg:postcode":"7861 AM",
    "sg:province":"Provincie Drenthe",
    "wof:name":"Boekhoud- En Administratiekantoor J. Hov",
    "wof:placetype":"venue"
},
  "geometry": {"coordinates":[6.717822,52.757698],"type":"Point"}
}