{
  "type": "Feature",
  "properties": {
    "iso:country":"NL",
    "sg:address":"Pastoor Van Nuenenstraat 46",
    "sg:city":"Utrecht",
    "sg:orig_category":"Diverse Consumentenartikelen Gh",
    "sg:phone":"+31 30 236 9254",
    "sg:postcode":"3511 RG",
    "sg:province":"Utrecht",
    "wof:name":"Indigo Nederland",
    "wof:placetype":"venue"
},
  "geometry": {"coordinates":[5.112936,52.095337],"type":"Point"}
}