{
  "type": "Feature",
  "properties": {
    "addr:full":"Wg Pln 44 Amsterdam Noord-Holland 1054 RB",
    "addr:housenumber":"44",
    "addr:postcode":"1054 rb",
    "addr:street":"Wg Pln",
    "iso:country":"NL",
    "sg:address":"Wg Pln 44",
    "sg:city":"Amsterdam",
    "sg:orig_category":"Psychotherapeuten",
    "sg:phone":"+31 20 685 1861",
    "sg:postcode":"1054 RB",
    "sg:province":"Noord-Holland",
    "wof:name":"Paardt, Drs L R H Van Der",
    "wof:placetype":"venue"
},
  "geometry": {"coordinates":[4.871467,52.363525],"type":"Point"}
}