{
  "type": "Feature",
  "properties": {
    "iso:country":"NL",
    "sg:address":"Foarwei 2",
    "sg:city":"Oudwoude",
    "sg:orig_category":"Kappers",
    "sg:phone":"+31 511 454 200",
    "sg:postcode":"9294 KD",
    "sg:province":"Provincie Friesland",
    "wof:name":"Nelly",
    "wof:placetype":"venue"
},
  "geometry": {"coordinates":[6.127742,53.27776],"type":"Point"}
}