{
  "type": "Feature",
  "properties": {
    "addr:full":"Erfstraat 3 Randwijk Gelderland 6668 AD",
    "addr:housenumber":"3",
    "addr:postcode":"6668 ad",
    "addr:street":"Erfstraat;Gelderland",
    "iso:country":"NL",
    "sg:address":"Erfstraat 3",
    "sg:city":"Randwijk",
    "sg:orig_category":"Bloemen And Planten",
    "sg:phone":"+31 488 491 629",
    "sg:postcode":"6668 AD",
    "sg:province":"Gelderland",
    "wof:name":"De Bloemisterij Hyacinth",
    "wof:placetype":"venue"
},
  "geometry": {"coordinates":[5.709238,51.954323],"type":"Point"}
}