{
  "type": "Feature",
  "properties": {
    "addr:full":"Noordzandstraat 15 Yerseke Zeeland 4401 CE",
    "addr:housenumber":"15",
    "addr:postcode":"4401 ce",
    "addr:street":"Noordzandstraat",
    "iso:country":"NL",
    "sg:address":"Noordzandstraat 15",
    "sg:city":"Yerseke",
    "sg:orig_category":"Kappers",
    "sg:phone":"+31 113 571 895",
    "sg:postcode":"4401 CE",
    "sg:province":"Zeeland",
    "wof:name":"Hairpoint De Kunder",
    "wof:placetype":"venue"
},
  "geometry": {"coordinates":[4.0503082275,51.4935646057],"type":"Point"}
}