{
  "type": "Feature",
  "properties": {
    "addr:full":"Schoutenstr 31A Barneveld Gelderland 3771 CE",
    "addr:housenumber":"31a",
    "addr:postcode":"3771 ce",
    "addr:street":"Schoutenstr;Gelderland",
    "iso:country":"NL",
    "sg:address":"Schoutenstr 31A",
    "sg:city":"Barneveld",
    "sg:orig_category":"Autoradio'S",
    "sg:phone":"+31 342 421 420",
    "sg:postcode":"3771 CE",
    "sg:province":"Gelderland",
    "wof:name":"Gloria",
    "wof:placetype":"venue"
},
  "geometry": {"coordinates":[5.580287,52.141106],"type":"Point"}
}