{
  "type": "Feature",
  "properties": {
    "iso:country":"NL",
    "sg:address":"Elferinksweg 1",
    "sg:city":"Enschede",
    "sg:classifiers":[
        {
            "category":"Communications",
            "subcategory":"Television Station",
            "type":"Services"
        }
    ],
    "sg:phone":"+31 53 432 2664",
    "sg:postcode":"7545 KA",
    "sg:province":"Overijssel",
    "sg:tags":[
        "video",
        "audio",
        "verhuur"
    ],
    "wof:name":"Elferink Videotheek",
    "wof:placetype":"venue"
},
  "geometry": {"coordinates":[6.871701,52.215942],"type":"Point"}
}