{
  "type": "Feature",
  "properties": {
    "addr:full":"Nachtegaalpln 19C Rotterdam South Holland 3082 NK",
    "addr:housenumber":"19c",
    "addr:postcode":"3082 nk",
    "addr:street":"Nachtegaalpln",
    "iso:country":"NL",
    "sg:address":"Nachtegaalpln 19C",
    "sg:city":"Rotterdam",
    "sg:orig_category":"Fotoreportages",
    "sg:phone":"+31 10 495 3223",
    "sg:postcode":"3082 NK",
    "sg:province":"South Holland",
    "wof:name":"Benschop, Guido",
    "wof:placetype":"venue"
},
  "geometry": {"coordinates":[4.470993,51.887299],"type":"Point"}
}