{
  "type": "Feature",
  "properties": {
    "addr:full":"De Vlouw 66 Delft Zuid-Holland 2611 EZ",
    "addr:housenumber":"66",
    "addr:postcode":"2611 ez",
    "addr:street":"De Vlouw",
    "iso:country":"NL",
    "sg:address":"De Vlouw 66",
    "sg:city":"Delft",
    "sg:orig_category":"Binnenhuisarchitecten",
    "sg:phone":"+31 15 214 4447",
    "sg:postcode":"2611 EZ",
    "sg:province":"Zuid-Holland",
    "wof:name":"Tonka",
    "wof:placetype":"venue"
},
  "geometry": {"coordinates":[4.359458,52.012959],"type":"Point"}
}