{
  "type": "Feature",
  "properties": {
    "addr:full":"Langstraat 20E Weert Limburg 6001 CV",
    "addr:housenumber":"20e",
    "addr:postcode":"6001 cv",
    "addr:street":"Langstraat",
    "iso:country":"NL",
    "sg:address":"Langstraat 20E",
    "sg:city":"Weert",
    "sg:orig_category":"Opticiens",
    "sg:phone":"+31 495 545 645",
    "sg:postcode":"6001 CV",
    "sg:province":"Limburg",
    "wof:name":"Pearle Opticiens",
    "wof:placetype":"venue"
},
  "geometry": {"coordinates":[5.7037811279,51.2550163269],"type":"Point"}
}