{
  "type": "Feature",
  "properties": {
    "addr:full":"Westzyde 99 Zaandam North Holland 1506 GA",
    "addr:housenumber":"99",
    "addr:postcode":"1506 ga",
    "addr:street":"Westzyde",
    "iso:country":"NL",
    "sg:address":"Westzyde 99",
    "sg:city":"Zaandam",
    "sg:orig_category":"Ontbijtservice",
    "sg:phone":"+31 75 616 3492",
    "sg:postcode":"1506 GA",
    "sg:province":"North Holland",
    "sg:website":"http://www.tenwolde.nl",
    "wof:name":"Piet En Wil Ten Wolde Traiteurs",
    "wof:placetype":"venue"
},
  "geometry": {"coordinates":[4.808925,52.44944],"type":"Point"}
}