{
  "type": "Feature",
  "properties": {
    "addr:full":"Strypsestr 41 Eindhoven Noord-Brabant 5616 GL",
    "addr:housenumber":"41",
    "addr:postcode":"5616 gl",
    "addr:street":"Strypsestr",
    "iso:country":"NL",
    "sg:address":"Strypsestr 41",
    "sg:city":"Eindhoven",
    "sg:orig_category":"Autorijscholen",
    "sg:phone":"+31 40 257 2929",
    "sg:postcode":"5616 GL",
    "sg:province":"Noord-Brabant",
    "sg:website":"http://www.rijschool-robert-wetzel.nl",
    "wof:name":"Dongen En Robert Wetzel",
    "wof:placetype":"venue"
},
  "geometry": {"coordinates":[5.459692,51.438557],"type":"Point"}
}