{
  "type": "Feature",
  "properties": {
    "iso:country":"NL",
    "sg:address":"Benedenkerkstr 70",
    "sg:city":"Waspik",
    "sg:orig_category":"Apotheken",
    "sg:phone":"+31 416 313 777",
    "sg:postcode":"5165 CD",
    "sg:province":"Noord-Brabant",
    "wof:name":"Waesbeeck",
    "wof:placetype":"venue"
},
  "geometry": {"coordinates":[4.932963,51.68618],"type":"Point"}
}