{
  "type": "Feature",
  "properties": {
    "addr:full":"Jan Evertsenstraat 8 Amsterdam North Holland 1056 EC",
    "addr:housenumber":"8",
    "addr:postcode":"1056 ec",
    "addr:street":"Jan Evertsenstraat",
    "iso:country":"NL",
    "sg:address":"Jan Evertsenstraat 8",
    "sg:city":"Amsterdam",
    "sg:orig_category":"Meubelzaken, Woning- And Keukeninrichting",
    "sg:phone":"+31 20 616 7757",
    "sg:postcode":"1056 EC",
    "sg:province":"North Holland",
    "wof:name":"Woninginrichting J.A. Van Doornewaard Bv",
    "wof:placetype":"venue"
},
  "geometry": {"coordinates":[4.858956,52.37149],"type":"Point"}
}