{
  "type": "Feature",
  "properties": {
    "addr:full":"Dorpsstr 67 Moordrecht Zuid-Holland 2841 BH",
    "addr:housenumber":"67",
    "addr:postcode":"2841 bh",
    "addr:street":"Dorpsstr",
    "iso:country":"NL",
    "sg:address":"Dorpsstr 67",
    "sg:city":"Moordrecht",
    "sg:orig_category":"Kinderkleding",
    "sg:phone":"+31 182 370 022",
    "sg:postcode":"2841 BH",
    "sg:province":"Zuid-Holland",
    "wof:name":"It'S For Kids",
    "wof:placetype":"venue"
},
  "geometry": {"coordinates":[4.669853,51.985332],"type":"Point"}
}