{
  "type": "Feature",
  "properties": {
    "addr:full":"Velperweg 83 Arnhem Gelderland 6824 HH",
    "addr:housenumber":"83",
    "addr:postcode":"6824 hh",
    "addr:street":"Velperweg",
    "iso:country":"NL",
    "sg:address":"Velperweg 83",
    "sg:city":"Arnhem",
    "sg:classifiers":[
        {
            "category":"Professional",
            "subcategory":"Accounting & Tax Preparation",
            "type":"Services"
        }
    ],
    "sg:phone":"+31 26 362 0851",
    "sg:postcode":"6824 HH",
    "sg:province":"Gelderland",
    "sg:tags":[
        "accountant"
    ],
    "wof:name":"Accountantskantoor F.J.M. Bolder Ra",
    "wof:placetype":"venue"
},
  "geometry": {"coordinates":[5.934649,51.989082],"type":"Point"}
}