{
  "type": "Feature",
  "properties": {
    "addr:full":"Konynenberg 90 Breda Noord-Brabant 4825 BE",
    "addr:housenumber":"90",
    "addr:postcode":"4825",
    "addr:street":"Konynenberg",
    "iso:country":"NL",
    "sg:address":"Konynenberg 90",
    "sg:city":"Breda",
    "sg:orig_category":"Magazijninrichtingen",
    "sg:phone":"+31 76 571 5110",
    "sg:postcode":"4825 BE",
    "sg:province":"Noord-Brabant",
    "sg:website":"http://www.overtoom.com",
    "wof:name":"Overtoom Bv",
    "wof:placetype":"venue"
},
  "geometry": {"coordinates":[4.76852,51.611752],"type":"Point"}
}