{
  "type": "Feature",
  "properties": {
    "iso:country":"NL",
    "sg:address":"Arnhemsewg 295",
    "sg:city":"Apeldoorn",
    "sg:orig_category":"Koffie En Thee - Apparaten En Artikelen",
    "sg:phone":"+31 55 533 8757",
    "sg:postcode":"7333 NC",
    "sg:province":"Gelderland",
    "wof:name":"Lako",
    "wof:placetype":"venue"
},
  "geometry": {"coordinates":[5.962425,52.190166],"type":"Point"}
}