{
  "type": "Feature",
  "properties": {
    "addr:full":"Europaln 11 S Hertogenbosch North Brabant 5232 BC",
    "addr:housenumber":"11",
    "addr:postcode":"5232 bc",
    "addr:street":"Europaln;S Hertogenbosch",
    "iso:country":"NL",
    "sg:address":"Europaln 11",
    "sg:city":"S Hertogenbosch",
    "sg:orig_category":"Schilders",
    "sg:phone":"+31 73 611 1378",
    "sg:postcode":"5232 BC",
    "sg:province":"North Brabant",
    "wof:name":"Interno Bv",
    "wof:placetype":"venue"
},
  "geometry": {"coordinates":[5.33234,51.708462],"type":"Point"}
}