{
  "type": "Feature",
  "properties": {
    "iso:country":"NL",
    "sg:address":"Europaln 11",
    "sg:city":"S Hertogenbosch",
    "sg:orig_category":"Schilders",
    "sg:phone":"+31 73 611 1378",
    "sg:postcode":"5232 BC",
    "sg:province":"North Brabant",
    "wof:name":"Interno Bv",
    "wof:placetype":"venue"
},
  "geometry": {"coordinates":[5.33234,51.708462],"type":"Point"}
}