{
  "type": "Feature",
  "properties": {
    "addr:full":"Vlieland 128 Utrecht Utrecht 3524 AC",
    "addr:housenumber":"128",
    "addr:postcode":"3524 ac",
    "addr:street":"Vlieland",
    "iso:country":"NL",
    "sg:address":"Vlieland 128",
    "sg:city":"Utrecht",
    "sg:orig_category":"Organisatiebureaus",
    "sg:phone":"+31 30 288 5044",
    "sg:postcode":"3524 AC",
    "sg:province":"Utrecht",
    "wof:name":"Madrigaal",
    "wof:placetype":"venue"
},
  "geometry": {"coordinates":[5.1360549927,52.0682945251],"type":"Point"}
}