{
  "type": "Feature",
  "properties": {
    "iso:country":"NL",
    "sg:address":"Robijnlaan 105",
    "sg:city":"Cuijk",
    "sg:orig_category":"Kinderopvang Behalve Thuis",
    "sg:phone":"+31 485 321 975",
    "sg:postcode":"5431 ZN",
    "sg:province":"Noord-Brabant",
    "wof:name":"De Kukel",
    "wof:placetype":"venue"
},
  "geometry": {"coordinates":[5.869619,51.74258],"type":"Point"}
}