{
  "type": "Feature",
  "properties": {
    "iso:country":"NL",
    "sg:address":"Erasmusln 1",
    "sg:city":"Heerhugowaard",
    "sg:orig_category":"Mode-Artikelen Dames En Heren",
    "sg:phone":"+31 72 571 6192",
    "sg:postcode":"1702 GH",
    "sg:province":"Noord-Holland",
    "wof:name":"Alkha",
    "wof:placetype":"venue"
},
  "geometry": {"coordinates":[4.839281,52.669182],"type":"Point"}
}