{
  "type": "Feature",
  "properties": {
    "iso:country":"NL",
    "sg:address":"Reewal 18",
    "sg:city":"Reeuwijk",
    "sg:orig_category":"Zuivelproducten And Spijsoli?n Gh",
    "sg:phone":"+31 182 398 600",
    "sg:postcode":"2811 PT",
    "sg:province":"South Holland",
    "wof:name":"Th. Vergeer & Zonen Bv",
    "wof:placetype":"venue"
},
  "geometry": {"coordinates":[4.741632,52.033031],"type":"Point"}
}