{
  "type": "Feature",
  "properties": {
    "addr:full":"Oude Turfstr 48 Venlo Limburg 5916 NW",
    "addr:housenumber":"48",
    "addr:postcode":"5916 nw",
    "addr:street":"Oude Turfstr",
    "iso:country":"NL",
    "sg:address":"Oude Turfstr 48",
    "sg:city":"Venlo",
    "sg:orig_category":"Verenigingen En Stichtingen",
    "sg:phone":"+31 77 351 8715",
    "sg:postcode":"5916 NW",
    "sg:province":"Limburg",
    "wof:name":"Ehbo Venlo",
    "wof:placetype":"venue"
},
  "geometry": {"coordinates":[6.193302,51.384495],"type":"Point"}
}