{
  "type": "Feature",
  "properties": {
    "addr:full":"Plein 3 Wateringen South Holland 2291 CA",
    "addr:housenumber":"3",
    "addr:postcode":"2291 ca",
    "addr:street":"Plein",
    "iso:country":"NL",
    "sg:address":"Plein 3",
    "sg:city":"Wateringen",
    "sg:orig_category":"Woninginrichting",
    "sg:phone":"+31 174 295 732",
    "sg:postcode":"2291 CA",
    "sg:province":"South Holland",
    "wof:name":"Dekor Vof",
    "wof:placetype":"venue"
},
  "geometry": {"coordinates":[4.2746357918,52.0237007141],"type":"Point"}
}