{
  "type": "Feature",
  "properties": {
    "iso:country":"NL",
    "sg:address":"Zijlweg 36",
    "sg:city":"Haarlem",
    "sg:orig_category":"Verhuur Medische Uitrustingen",
    "sg:phone":"+31 23 512 3023",
    "sg:postcode":"2013 DJ",
    "sg:province":"Noord-Holland",
    "wof:name":"Thuiszorgwinkel",
    "wof:placetype":"venue"
},
  "geometry": {"coordinates":[4.627174,52.384205],"type":"Point"}
}