{
  "type": "Feature",
  "properties": {
    "iso:country":"NL",
    "sg:address":"Loefzyde 11",
    "sg:city":"Amsterdam",
    "sg:orig_category":"Bedrijfsopleidingen",
    "sg:phone":"+31 20 633 3353",
    "sg:postcode":"1034 KW",
    "sg:province":"Noord-Holland",
    "wof:name":"Gedachtengoed",
    "wof:placetype":"venue"
},
  "geometry": {"coordinates":[4.91588,52.408401],"type":"Point"}
}