{
  "type": "Feature",
  "properties": {
    "iso:country":"NL",
    "sg:address":"Passage 18",
    "sg:city":"Valkenswaard",
    "sg:classifiers":[
        {
            "category":"Retail",
            "subcategory":"Photofinishing",
            "type":"Services"
        }
    ],
    "sg:phone":"+31 40 207 5785",
    "sg:postcode":"5554 AH",
    "sg:province":"North Brabant",
    "sg:tags":[
        "foto",
        "film"
    ],
    "wof:name":"Foto Ton Smeets Bv",
    "wof:placetype":"venue"
},
  "geometry": {"coordinates":[5.45897,51.35051],"type":"Point"}
}