{
  "type": "Feature",
  "properties": {
    "addr:full":"Mockstraat 61 Maastricht Limburg 6226 CB",
    "addr:housenumber":"61",
    "addr:postcode":"6226 cb",
    "addr:street":"Mockstraat",
    "iso:country":"NL",
    "sg:address":"Mockstraat 61",
    "sg:city":"Maastricht",
    "sg:orig_category":"Hoger Onderwijs",
    "sg:phone":"+31 43 363 4100",
    "sg:postcode":"6226 CB",
    "sg:province":"Limburg",
    "wof:name":"Modevakschool Unique",
    "wof:placetype":"venue"
},
  "geometry": {"coordinates":[5.719472,50.846996],"type":"Point"}
}