{
  "type": "Feature",
  "properties": {
    "addr:full":"Azalealn 39 Helmond Noord-Brabant 5701 CJ",
    "addr:housenumber":"39",
    "addr:postcode":"5701 cj",
    "addr:street":"Azalealn",
    "iso:country":"NL",
    "sg:address":"Azalealn 39",
    "sg:city":"Helmond",
    "sg:orig_category":"Bloemen En Planten",
    "sg:phone":"+31 492 541 027",
    "sg:postcode":"5701 CJ",
    "sg:province":"Noord-Brabant",
    "wof:name":"Giel'S Bloemenboetiek",
    "wof:placetype":"venue"
},
  "geometry": {"coordinates":[5.658284,51.482239],"type":"Point"}
}