{
  "type": "Feature",
  "properties": {
    "addr:full":"Goudestein 82 Rotterdam South Holland 3085 DC",
    "addr:housenumber":"82",
    "addr:postcode":"3085",
    "addr:street":"Goudestein",
    "iso:country":"NL",
    "sg:address":"Goudestein 82",
    "sg:city":"Rotterdam",
    "sg:orig_category":"Voetbalverenigingen",
    "sg:phone":"+31 10 480 6514",
    "sg:postcode":"3085 DC",
    "sg:province":"South Holland",
    "wof:name":"Coal",
    "wof:placetype":"venue"
},
  "geometry": {"coordinates":[4.487231,51.873634],"type":"Point"}
}