{
  "type": "Feature",
  "properties": {
    "addr:full":"Kikkerbeet 23 Oudkarspel Noord-Holland 1724 XS",
    "addr:housenumber":"23",
    "addr:postcode":"1724 xs",
    "addr:street":"Kikkerbeet",
    "iso:country":"NL",
    "sg:address":"Kikkerbeet 23",
    "sg:city":"Oudkarspel",
    "sg:orig_category":"Metselwerken",
    "sg:phone":"+31 226 320 692",
    "sg:postcode":"1724 XS",
    "sg:province":"Noord-Holland",
    "wof:name":"Smit",
    "wof:placetype":"venue"
},
  "geometry": {"coordinates":[4.803657,52.710972],"type":"Point"}
}