{
  "type": "Feature",
  "properties": {
    "addr:full":"Watermanwg 7 Rotterdam South Holland 3067 GA",
    "addr:housenumber":"7",
    "addr:postcode":"3067 ga",
    "addr:street":"Watermanwg",
    "iso:country":"NL",
    "sg:address":"Watermanwg 7",
    "sg:city":"Rotterdam",
    "sg:orig_category":"Meubelen",
    "sg:phone":"+31 10 421 9410",
    "sg:postcode":"3067 GA",
    "sg:province":"South Holland",
    "wof:name":"Mesh Bv",
    "wof:placetype":"venue"
},
  "geometry": {"coordinates":[4.560121,51.95145],"type":"Point"}
}