{
  "type": "Feature",
  "properties": {
    "addr:full":"Klooster 42 Coevorden Drenthe 7741 ND",
    "addr:housenumber":"42",
    "addr:postcode":"7741 nd",
    "addr:street":"Klooster",
    "iso:country":"NL",
    "sg:address":"Klooster 42",
    "sg:city":"Coevorden",
    "sg:orig_category":"Loodgieterswerk, Verwarming And Sanitaire Installaties",
    "sg:phone":"+31 524 524 873",
    "sg:postcode":"7741 ND",
    "sg:province":"Drenthe",
    "wof:name":"Klus En Montagebedrijf Habing",
    "wof:placetype":"venue"
},
  "geometry": {"coordinates":[6.714247,52.653645],"type":"Point"}
}