{
  "type": "Feature",
  "properties": {
    "addr:full":"Zigt 37 Warmenhuizen Noord-Holland 1749 KH",
    "addr:housenumber":"37",
    "addr:postcode":"1749 kh",
    "addr:street":"Zigt",
    "iso:country":"NL",
    "sg:address":"Zigt 37",
    "sg:city":"Warmenhuizen",
    "sg:orig_category":"Adviesbureaus Bedrijfsorganisatie",
    "sg:phone":"+31 226 390 123",
    "sg:postcode":"1749 KH",
    "sg:province":"Noord-Holland",
    "sg:website":"http://www.vanrossumorganisatieontwikkeling.nl",
    "wof:name":"Rossum, Van",
    "wof:placetype":"venue"
},
  "geometry": {"coordinates":[4.743539,52.716957],"type":"Point"}
}