{
  "type": "Feature",
  "properties": {
    "addr:full":"Boekdrukker 9A Nykerk Gld Gelderland 3861 SE",
    "addr:housenumber":"9a;3861",
    "addr:street":"Boekdrukker;Gld Gelderland;Se",
    "iso:country":"NL",
    "sg:address":"Boekdrukker 9A",
    "sg:city":"Nykerk Gld",
    "sg:orig_category":"Bloemen En Planten",
    "sg:phone":"+31 33 475 8550",
    "sg:postcode":"3861 SE",
    "sg:province":"Gelderland",
    "wof:name":"Vergeet Mij Niet",
    "wof:placetype":"venue"
},
  "geometry": {"coordinates":[5.4831,52.221569],"type":"Point"}
}