{
  "type": "Feature",
  "properties": {
    "iso:country":"NL",
    "sg:address":"Kerkstr 58",
    "sg:city":"S Hertogenbosch",
    "sg:orig_category":"Postzegels",
    "sg:phone":"+31 73 614 7236",
    "sg:postcode":"5211 KH",
    "sg:province":"Noord-Brabant",
    "wof:name":"Nieuwe Post, De",
    "wof:placetype":"venue"
},
  "geometry": {"coordinates":[5.29824,51.69075],"type":"Point"}
}