{
  "type": "Feature",
  "properties": {
    "addr:full":"Rijksstraatweg 317 Leersum Utrecht 3956 CP",
    "addr:housenumber":"317",
    "addr:postcode":"3956 cp",
    "addr:street":"Rijksstraatweg",
    "iso:country":"NL",
    "sg:address":"Rijksstraatweg 317",
    "sg:city":"Leersum",
    "sg:orig_category":"Verhuur Audiovisuele Apparatuur",
    "sg:phone":"+31 343 457 689",
    "sg:postcode":"3956 CP",
    "sg:province":"Utrecht",
    "wof:name":"H M Van Keken Bisarmik Merchandise",
    "wof:placetype":"venue"
},
  "geometry": {"coordinates":[5.416066,52.01577],"type":"Point"}
}