{
  "type": "Feature",
  "properties": {
    "iso:country":"NL",
    "sg:address":"Rijksstraatweg 317",
    "sg:city":"Leersum",
    "sg:orig_category":"Verhuur Audiovisuele Apparatuur",
    "sg:phone":"+31 343 457 689",
    "sg:postcode":"3956 CP",
    "sg:province":"Utrecht",
    "wof:name":"H M Van Keken Bisarmik Merchandise",
    "wof:placetype":"venue"
},
  "geometry": {"coordinates":[5.416066,52.01577],"type":"Point"}
}