{
  "type": "Feature",
  "properties": {
    "iso:country":"NL",
    "sg:address":"Saffierlaan 10",
    "sg:city":"Rhoon",
    "sg:classifiers":[
        {
            "category":"Professional",
            "subcategory":"Computer Services",
            "type":"Services"
        }
    ],
    "sg:postcode":"3162PL",
    "sg:tags":[
        "Recommendations",
        "technology",
        "computational-linguistics",
        "alfa-informatics",
        "webintelligence",
        "Search-engine"
    ],
    "sg:website":"http://www.moorelaboratories.com",
    "wof:name":"Moore Laboratories",
    "wof:placetype":"venue"
},
  "geometry": {"coordinates":[4.476691,51.858203],"type":"Point"}
}