{
  "type": "Feature",
  "properties": {
    "iso:country":"NL",
    "sg:address":"Velduil 16",
    "sg:city":"Emmen",
    "sg:orig_category":"Boekhouders",
    "sg:phone":"+31 591 634 992",
    "sg:postcode":"7827 GT",
    "sg:province":"Drenthe",
    "wof:name":"Administratiekantoor W. Braam",
    "wof:placetype":"venue"
},
  "geometry": {"coordinates":[6.889041,52.754864],"type":"Point"}
}