{
  "type": "Feature",
  "properties": {
    "addr:full":"Heerderwg 41 Epe Gelderland 8161 BL",
    "addr:housenumber":"41",
    "addr:postcode":"8161 bl",
    "addr:street":"Heerderwg;Gelderland",
    "iso:country":"NL",
    "sg:address":"Heerderwg 41",
    "sg:city":"Epe",
    "sg:orig_category":"Antiquariaten",
    "sg:phone":"+31 578 614 293",
    "sg:postcode":"8161 BL",
    "sg:province":"Gelderland",
    "wof:name":"Vyfpoot, De",
    "wof:placetype":"venue"
},
  "geometry": {"coordinates":[6.002493,52.361946],"type":"Point"}
}