{
  "type": "Feature",
  "properties": {
    "addr:full":"Vondelhof 6 Brunssum Limburg 6445 AL",
    "addr:housenumber":"6",
    "addr:postcode":"6445 al",
    "addr:street":"Vondelhof",
    "iso:country":"NL",
    "sg:address":"Vondelhof 6",
    "sg:city":"Brunssum",
    "sg:orig_category":"Verzekeringen",
    "sg:phone":"+31 45 525 4478",
    "sg:postcode":"6445 AL",
    "sg:province":"Limburg",
    "wof:name":"R.W. Super Adviesbureau",
    "wof:placetype":"venue"
},
  "geometry": {"coordinates":[5.968127,50.931953],"type":"Point"}
}