{
  "type": "Feature",
  "properties": {
    "iso:country":"NL",
    "sg:address":"Havenstr 20",
    "sg:city":"Ysselstein Ut",
    "sg:orig_category":"Verzekeringen - Verzekeringskantoren",
    "sg:phone":"+31 30 687 5198",
    "sg:postcode":"3401 DM",
    "sg:province":"Utrecht",
    "wof:name":"Uitvaart Advies Ned Bv",
    "wof:placetype":"venue"
},
  "geometry": {"coordinates":[5.045832,52.019424],"type":"Point"}
}