{
  "type": "Feature",
  "properties": {
    "addr:full":"Euvelwegen 6 Heeze Noord-Brabant 5591 TK",
    "addr:housenumber":"6",
    "addr:postcode":"5591 tk",
    "addr:street":"Euvelwegen",
    "iso:country":"NL",
    "sg:address":"Euvelwegen 6",
    "sg:city":"Heeze",
    "sg:orig_category":"Levende Dieren Gh",
    "sg:phone":"+31 40 226 1663",
    "sg:postcode":"5591 TK",
    "sg:province":"Noord-Brabant",
    "wof:name":"Varkens- En Veehandel L. Snoeijen",
    "wof:placetype":"venue"
},
  "geometry": {"coordinates":[5.590915,51.361237],"type":"Point"}
}