{
  "type": "Feature",
  "properties": {
    "addr:full":"Kzr Karelwg 391 Amstelveen North Holland 1181 RG",
    "addr:housenumber":"391",
    "addr:postcode":"1181 rg",
    "iso:country":"NL",
    "sg:address":"Kzr Karelwg 391",
    "sg:city":"Amstelveen",
    "sg:orig_category":"Verenigingen En Stichtingen",
    "sg:phone":"+31 20 641 3676",
    "sg:postcode":"1181 RG",
    "sg:province":"North Holland",
    "wof:name":"Samenwerkend Verzet 1940-1945, Sticht",
    "wof:placetype":"venue"
},
  "geometry": {"coordinates":[4.856249,52.310169],"type":"Point"}
}