{
  "type": "Feature",
  "properties": {
    "addr:full":"Ids Wiersmastraat 10 Brantgum Provincie Friesland 9153 BS",
    "addr:housenumber":"10",
    "addr:postcode":"9153 bs",
    "addr:street":"Ids Wiersmastraat;Provincie Friesland",
    "iso:country":"NL",
    "sg:address":"Ids Wiersmastraat 10",
    "sg:city":"Brantgum",
    "sg:orig_category":"Kappers",
    "sg:phone":"+31 519 562 606",
    "sg:postcode":"9153 BS",
    "sg:province":"Provincie Friesland",
    "wof:name":"M. V.D. Kooi",
    "wof:placetype":"venue"
},
  "geometry": {"coordinates":[5.929769,53.352245],"type":"Point"}
}