{
  "type": "Feature",
  "properties": {
    "addr:full":"Gelderstr 56 Hilvarenbeek Noord-Brabant 5081 AD",
    "addr:housenumber":"56",
    "addr:postcode":"5081 ad",
    "addr:street":"Gelderstr",
    "iso:country":"NL",
    "sg:address":"Gelderstr 56",
    "sg:city":"Hilvarenbeek",
    "sg:orig_category":"Verf En Lak",
    "sg:phone":"+31 13 505 1946",
    "sg:postcode":"5081 AD",
    "sg:province":"Noord-Brabant",
    "wof:name":"Wouw, Van De",
    "wof:placetype":"venue"
},
  "geometry": {"coordinates":[5.138517,51.48222],"type":"Point"}
}