{
  "type": "Feature",
  "properties": {
    "addr:full":"Ambachtswg 42 Huizen Noord-Holland 1271 AM",
    "addr:housenumber":"42",
    "addr:postcode":"1271",
    "addr:street":"Ambachtswg",
    "iso:country":"NL",
    "sg:address":"Ambachtswg 42",
    "sg:city":"Huizen",
    "sg:orig_category":"Muziekdrukkerijen En -Uitgeverijen",
    "sg:phone":"+31 35 524 2104",
    "sg:postcode":"1271 AM",
    "sg:province":"Noord-Holland",
    "wof:name":"European Music Centre",
    "wof:placetype":"venue"
},
  "geometry": {"coordinates":[5.243885,52.303658],"type":"Point"}
}