{
  "type": "Feature",
  "properties": {
    "addr:full":"G V Prinstererln 274 S Gravenhage Zuid-Holland 2555 HZ",
    "addr:housenumber":"274;gravenhage",
    "addr:postcode":"2555 hz",
    "addr:street":"V Prinstererln;S",
    "iso:country":"NL",
    "sg:address":"G V Prinstererln 274",
    "sg:city":"S Gravenhage",
    "sg:orig_category":"Scholen: Hoger Beroepsonderwijs",
    "sg:phone":"+31 70 325 0022",
    "sg:postcode":"2555 HZ",
    "sg:province":"Zuid-Holland",
    "sg:website":"http://www.mon3aan.nl",
    "wof:name":"Mondriaan Onderwijsgroep, De",
    "wof:placetype":"venue"
},
  "geometry": {"coordinates":[4.2417,52.06638],"type":"Point"}
}