{
  "type": "Feature",
  "properties": {
    "addr:full":"K Bree 2 Gieten Provincie Drenthe 9461 CG",
    "addr:housenumber":"2",
    "addr:postcode":"9461 cg",
    "addr:street":"K Bree;Provincie Drenthe",
    "iso:country":"NL",
    "sg:address":"K Bree 2",
    "sg:city":"Gieten",
    "sg:orig_category":"Fotoreportages",
    "sg:phone":"+31 592 265 844",
    "sg:postcode":"9461 CG",
    "sg:province":"Provincie Drenthe",
    "sg:website":"http://www.hdp.nl",
    "wof:name":"Driever, H",
    "wof:placetype":"venue"
},
  "geometry": {"coordinates":[6.757628,53.008698],"type":"Point"}
}