{
  "type": "Feature",
  "properties": {
    "addr:full":"Thorbeckeln 95 Barneveld Gelderland 3771 ED",
    "addr:housenumber":"95",
    "addr:postcode":"3771 ed",
    "addr:street":"Thorbeckeln;Gelderland",
    "iso:country":"NL",
    "sg:address":"Thorbeckeln 95",
    "sg:city":"Barneveld",
    "sg:orig_category":"Belastingconsulenten/ Belastingadviseurs",
    "sg:phone":"+31 342 415 414",
    "sg:postcode":"3771 ED",
    "sg:province":"Gelderland",
    "wof:name":"Tanghe De Ruiter & Morren",
    "wof:placetype":"venue"
},
  "geometry": {"coordinates":[5.588843,52.141216],"type":"Point"}
}