{
  "type": "Feature",
  "properties": {
    "addr:full":"Harmenjanswg 77 Haarlem North Holland 2031 WJ",
    "addr:housenumber":"77",
    "addr:postcode":"2031 wj",
    "addr:street":"Harmenjanswg",
    "iso:country":"NL",
    "sg:address":"Harmenjanswg 77",
    "sg:city":"Haarlem",
    "sg:orig_category":"Vertalers",
    "sg:phone":"+31 23 535 6444",
    "sg:postcode":"2031 WJ",
    "sg:province":"North Holland",
    "wof:name":"Schooneman",
    "wof:placetype":"venue"
},
  "geometry": {"coordinates":[4.645878,52.384449],"type":"Point"}
}