{
  "type": "Feature",
  "properties": {
    "addr:full":"Oudehoofdplein 4 Rotterdam Zuid-Holland 3011 TM",
    "addr:housenumber":"4",
    "addr:postcode":"3011 tm",
    "addr:street":"Oudehoofdplein",
    "iso:country":"NL",
    "sg:address":"Oudehoofdplein 4",
    "sg:city":"Rotterdam",
    "sg:orig_category":"Werving And Selectie Van Vast Personeel",
    "sg:phone":"+31 10 411 2355",
    "sg:postcode":"3011 TM",
    "sg:province":"Zuid-Holland",
    "wof:name":"Focus Nederland",
    "wof:placetype":"venue"
},
  "geometry": {"coordinates":[4.4940371513,51.9191169739],"type":"Point"}
}