{
  "type": "Feature",
  "properties": {
    "addr:full":"Ruinerwoldstraat 39 Tilburg North Brabant 5035 DA",
    "addr:housenumber":"39",
    "addr:postcode":"5035 da",
    "addr:street":"Ruinerwoldstraat",
    "iso:country":"NL",
    "sg:address":"Ruinerwoldstraat 39",
    "sg:city":"Tilburg",
    "sg:classifiers":[
        {
            "category":"Professional",
            "subcategory":"Accounting & Tax Preparation",
            "type":"Services"
        }
    ],
    "sg:phone":"+31 13 571 2856",
    "sg:postcode":"5035 DA",
    "sg:province":"North Brabant",
    "sg:tags":[
        "accountant"
    ],
    "wof:name":"Helfrich Adviesgroep",
    "wof:placetype":"venue"
},
  "geometry": {"coordinates":[4.980147,51.587662],"type":"Point"}
}