{
  "type": "Feature",
  "properties": {
    "addr:full":"Van Speykstraat 109 Rotterdam South Holland 3014 VG",
    "addr:housenumber":"109",
    "addr:postcode":"3014 vg",
    "addr:street":"Van Speykstraat",
    "iso:country":"NL",
    "sg:address":"Van Speykstraat 109",
    "sg:city":"Rotterdam",
    "sg:classifiers":[
        {
            "category":"Education",
            "subcategory":"Preschool",
            "type":"Public Place"
        }
    ],
    "sg:phone":"+31 10 436 5808",
    "sg:postcode":"3014 VG",
    "sg:province":"South Holland",
    "sg:tags":[
        "kleuteronderwijs",
        "basis-"
    ],
    "wof:name":"Openbare Basisschool Babylon",
    "wof:placetype":"venue"
},
  "geometry": {"coordinates":[4.466072,51.917034],"type":"Point"}
}