{
  "type": "Feature",
  "properties": {
    "addr:full":"Waldeck Pyrmontweg 14 Dordrecht Zuid-Holland 3314 NZ",
    "addr:housenumber":"14",
    "addr:postcode":"3314 nz",
    "addr:street":"Waldeck Pyrmontweg",
    "iso:country":"NL",
    "sg:address":"Waldeck Pyrmontweg 14",
    "sg:city":"Dordrecht",
    "sg:orig_category":"Verzekeringen",
    "sg:phone":"+31 78 613 0145",
    "sg:postcode":"3314 NZ",
    "sg:province":"Zuid-Holland",
    "wof:name":"Assurantiekantoor R L Nieman",
    "wof:placetype":"venue"
},
  "geometry": {"coordinates":[4.668807,51.798817],"type":"Point"}
}