{
  "type": "Feature",
  "properties": {
    "addr:full":"Hoofdstraat 25 Oirlo Limburg 5808 AS",
    "addr:housenumber":"25",
    "addr:postcode":"5808 as",
    "addr:street":"Hoofdstraat",
    "iso:country":"NL",
    "sg:address":"Hoofdstraat 25",
    "sg:city":"Oirlo",
    "sg:orig_category":"Banken And Kredietinstellingen",
    "sg:phone":"+31 478 530 300",
    "sg:postcode":"5808 AS",
    "sg:province":"Limburg",
    "wof:name":"Rabobank",
    "wof:placetype":"venue"
},
  "geometry": {"coordinates":[6.037346,51.51012],"type":"Point"}
}