{
  "type": "Feature",
  "properties": {
    "addr:full":"Oranjeln 6 Nykerk Gld Gelderland 3862 CX",
    "addr:housenumber":"6",
    "addr:postcode":"3862 cx",
    "addr:street":"Oranjeln;Gld Gelderland",
    "iso:country":"NL",
    "sg:address":"Oranjeln 6",
    "sg:city":"Nykerk Gld",
    "sg:orig_category":"Verzekerings- Maatschappijen",
    "sg:phone":"+31 33 246 0044",
    "sg:postcode":"3862 CX",
    "sg:province":"Gelderland",
    "sg:website":"http://www.accesnet.nl/univehgv",
    "wof:name":"Univ\u00e9 Midden-Nederland",
    "wof:placetype":"venue"
},
  "geometry": {"coordinates":[5.51415,52.21376],"type":"Point"}
}