{
  "type": "Feature",
  "properties": {
    "addr:full":"Dorpsstraat 79 Breskens Zeeland 4511 EC",
    "addr:housenumber":"79",
    "addr:postcode":"4511 ec",
    "addr:street":"Dorpsstraat",
    "iso:country":"NL",
    "sg:address":"Dorpsstraat 79",
    "sg:city":"Breskens",
    "sg:orig_category":"Zuivelproducten And Spijsoli?n Gh",
    "sg:phone":"+31 117 381 949",
    "sg:postcode":"4511 EC",
    "sg:province":"Zeeland",
    "wof:name":"J. Oskam",
    "wof:placetype":"venue"
},
  "geometry": {"coordinates":[3.553889,51.393986],"type":"Point"}
}