{
  "type": "Feature",
  "properties": {
    "addr:full":"P N Kruiswijkstraat 17 Loenersloot Utrecht 3634 AX",
    "addr:housenumber":"17",
    "addr:postcode":"3634 ax",
    "addr:street":"P N Kruiswijkstraat",
    "iso:country":"NL",
    "sg:address":"P N Kruiswijkstraat 17",
    "sg:city":"Loenersloot",
    "sg:orig_category":"Verhuur Catering-, Feest- En Evenementbenodigdheden",
    "sg:phone":"+31 294 291 739",
    "sg:postcode":"3634 AX",
    "sg:province":"Utrecht",
    "wof:name":"M. V.D. Linden",
    "wof:placetype":"venue"
},
  "geometry": {"coordinates":[5.002591,52.231037],"type":"Point"}
}