{
  "type": "Feature",
  "properties": {
    "iso:country":"NL",
    "sg:address":"Straelsewg 102",
    "sg:city":"Venlo",
    "sg:orig_category":"Partyservice",
    "sg:phone":"+31 77 354 8321",
    "sg:postcode":"5914 AR",
    "sg:province":"Limburg",
    "wof:name":"G/S",
    "wof:placetype":"venue"
},
  "geometry": {"coordinates":[6.178567,51.375481],"type":"Point"}
}