{
  "type": "Feature",
  "properties": {
    "addr:full":"Dahlialaan 2 Oegstgeest South Holland 2343 XE",
    "addr:housenumber":"2",
    "addr:postcode":"2343 xe",
    "addr:street":"Dahlialaan",
    "iso:country":"NL",
    "sg:address":"Dahlialaan 2",
    "sg:city":"Oegstgeest",
    "sg:orig_category":"Autokeuringen",
    "sg:phone":"+31 71 515 4913",
    "sg:postcode":"2343 XE",
    "sg:province":"South Holland",
    "wof:name":"Automobielbedrijf Van Der Hoorn",
    "wof:placetype":"venue"
},
  "geometry": {"coordinates":[4.46793,52.189445],"type":"Point"}
}