{
  "type": "Feature",
  "properties": {
    "addr:full":"Kanaalstr 37 Roden Drenthe 9301 LR",
    "addr:housenumber":"37",
    "addr:postcode":"9301 lr",
    "addr:street":"Kanaalstr",
    "iso:country":"NL",
    "sg:address":"Kanaalstr 37",
    "sg:city":"Roden",
    "sg:orig_category":"Keukens",
    "sg:phone":"+31 50 501 4588",
    "sg:postcode":"9301 LR",
    "sg:province":"Drenthe",
    "wof:name":"Keukenstudio",
    "wof:placetype":"venue"
},
  "geometry": {"coordinates":[6.43277,53.140167],"type":"Point"}
}