{
  "type": "Feature",
  "properties": {
    "iso:country":"NL",
    "sg:address":"Laagsestraat 16",
    "sg:city":"Oud Ootmarsum",
    "sg:orig_category":"Goederenvervoer Over De Weg",
    "sg:phone":"+31 541 291 282",
    "sg:postcode":"7637 PB",
    "sg:province":"Overijssel",
    "wof:name":"Internationaal Transport En Logistiek Kamphuis Bv",
    "wof:placetype":"venue"
},
  "geometry": {"coordinates":[6.901682,52.413261],"type":"Point"}
}