{
  "type": "Feature",
  "properties": {
    "addr:full":"Goltziusstr 27 Venlo Limburg 5911 AT",
    "addr:housenumber":"27",
    "addr:postcode":"5911",
    "addr:street":"Goltziusstr",
    "iso:country":"NL",
    "sg:address":"Goltziusstr 27",
    "sg:city":"Venlo",
    "sg:orig_category":"Begrafenisverzorging",
    "sg:phone":"+31 77 354 7753",
    "sg:postcode":"5911 AT",
    "sg:province":"Limburg",
    "wof:name":"Oosterveld, Lies",
    "wof:placetype":"venue"
},
  "geometry": {"coordinates":[6.175534,51.371368],"type":"Point"}
}