{
  "type": "Feature",
  "properties": {
    "addr:full":"Houtrustweg 120 'S-Gravenhage Zuid-Holland 2566 GJ",
    "addr:housenumber":"120",
    "addr:postcode":"s-gravenhage;2566 gj",
    "addr:street":"Houtrustweg",
    "iso:country":"NL",
    "sg:address":"Houtrustweg 120",
    "sg:city":"'S-Gravenhage",
    "sg:orig_category":"Waterbehandeling En Waterzuiverings- Systemen",
    "sg:phone":"+31 70 365 3808",
    "sg:postcode":"2566 GJ",
    "sg:province":"Zuid-Holland",
    "wof:name":"Houtrust, A W Z I",
    "wof:placetype":"venue"
},
  "geometry": {"coordinates":[4.2680969238,52.088432312],"type":"Point"}
}