{
  "type": "Feature",
  "properties": {
    "addr:full":"Hoofdstraat 38 Bergambacht Zuid-Holland 2861 AP",
    "addr:housenumber":"38",
    "addr:postcode":"2861 ap",
    "addr:street":"Hoofdstraat",
    "iso:country":"NL",
    "sg:address":"Hoofdstraat 38",
    "sg:city":"Bergambacht",
    "sg:classifiers":[
        {
            "category":"Food & Beverages",
            "subcategory":"Fruits & Vegetables",
            "type":"Retail Goods"
        }
    ],
    "sg:phone":"+31 182 351 735",
    "sg:postcode":"2861 AP",
    "sg:province":"Zuid-Holland",
    "sg:tags":[
        "groenten"
    ],
    "wof:name":"Zuijderwijn Groente En Fruit",
    "wof:placetype":"venue"
},
  "geometry": {"coordinates":[4.782754,51.933327],"type":"Point"}
}