{
  "type": "Feature",
  "properties": {
    "iso:country":"NL",
    "sg:address":"Flevostr 104",
    "sg:city":"Purmerend",
    "sg:orig_category":"Grafische Bedrijven",
    "sg:phone":"+31 299 432 216",
    "sg:postcode":"1442 PZ",
    "sg:province":"Noord-Holland",
    "wof:name":"Cachet-Stansvormen",
    "wof:placetype":"venue"
},
  "geometry": {"coordinates":[4.979581,52.518234],"type":"Point"}
}