{
  "type": "Feature",
  "properties": {
    "addr:full":"Flevostr 104 Purmerend Noord-Holland 1442 PZ",
    "addr:housenumber":"104",
    "addr:postcode":"1442 pz",
    "iso:country":"NL",
    "sg:address":"Flevostr 104",
    "sg:city":"Purmerend",
    "sg:orig_category":"Grafische Bedrijven",
    "sg:phone":"+31 299 432 216",
    "sg:postcode":"1442 PZ",
    "sg:province":"Noord-Holland",
    "wof:name":"Cachet-Stansvormen",
    "wof:placetype":"venue"
},
  "geometry": {"coordinates":[4.979581,52.518234],"type":"Point"}
}