{
  "type": "Feature",
  "properties": {
    "addr:full":"Smallewg 5 Giethoorn NL.08 8355 VB",
    "addr:housenumber":"5;nl.08",
    "addr:postcode":"8355 vb",
    "addr:street":"Smallewg",
    "iso:country":"NL",
    "sg:address":"Smallewg 5",
    "sg:city":"Giethoorn",
    "sg:orig_category":"Verenigingen En Stichtingen",
    "sg:phone":"+31 521 371 499",
    "sg:postcode":"8355 VB",
    "sg:province":"NL.08",
    "wof:name":"Zonnebloem, De",
    "wof:placetype":"venue"
},
  "geometry": {"coordinates":[6.043542,52.752659],"type":"Point"}
}