{
  "type": "Feature",
  "properties": {
    "addr:full":"Bocholterwg 132 Weert Limburg 6006 TP",
    "addr:housenumber":"132",
    "addr:postcode":"6006",
    "addr:street":"Weert Limburg",
    "iso:country":"NL",
    "sg:address":"Bocholterwg 132",
    "sg:city":"Weert",
    "sg:orig_category":"Kappers",
    "sg:phone":"+31 495 530 823",
    "sg:postcode":"6006 TP",
    "sg:province":"Limburg",
    "wof:name":"Heymans-Caris, M",
    "wof:placetype":"venue"
},
  "geometry": {"coordinates":[5.6688499451,51.2144508362],"type":"Point"}
}