{
  "type": "Feature",
  "properties": {
    "iso:country":"NL",
    "sg:address":"Rede 75",
    "sg:city":"Zeewolde",
    "sg:orig_category":"Zuivelproducten And Spijsoli?n Gh",
    "sg:phone":"+31 321 380 120",
    "sg:postcode":"3891 AP",
    "sg:province":"Flevoland",
    "wof:name":"Quadflieg Management Consultancy Bv (Qmc",
    "wof:placetype":"venue"
},
  "geometry": {"coordinates":[5.54712,52.331078],"type":"Point"}
}