{
  "type": "Feature",
  "properties": {
    "addr:full":"Rede 75 Zeewolde Flevoland 3891 AP",
    "addr:housenumber":"75",
    "addr:postcode":"3891 ap",
    "addr:street":"Rede;Flevoland",
    "iso:country":"NL",
    "sg:address":"Rede 75",
    "sg:city":"Zeewolde",
    "sg:orig_category":"Zuivelproducten And Spijsoli?n Gh",
    "sg:phone":"+31 321 380 120",
    "sg:postcode":"3891 AP",
    "sg:province":"Flevoland",
    "wof:name":"Quadflieg Management Consultancy Bv (Qmc",
    "wof:placetype":"venue"
},
  "geometry": {"coordinates":[5.54712,52.331078],"type":"Point"}
}