{
  "type": "Feature",
  "properties": {
    "iso:country":"NL",
    "sg:address":"Achterbergstraat 12",
    "sg:city":"Dordrecht",
    "sg:orig_category":"Wegen And Sportterreinen",
    "sg:phone":"+31 78 616 4500",
    "sg:postcode":"3319 BA",
    "sg:province":"Zuid-Holland",
    "wof:name":"De Klinker",
    "wof:placetype":"venue"
},
  "geometry": {"coordinates":[4.7021961212,51.7979125977],"type":"Point"}
}