{
  "type": "Feature",
  "properties": {
    "addr:full":"Wierdensestr 112 Almelo Overijssel 7604 BK",
    "addr:housenumber":"112",
    "addr:postcode":"7604 bk",
    "iso:country":"NL",
    "sg:address":"Wierdensestr 112",
    "sg:city":"Almelo",
    "sg:orig_category":"Hypotheken",
    "sg:phone":"+31 546 815 555",
    "sg:postcode":"7604 BK",
    "sg:province":"Overijssel",
    "sg:website":"http://www.schakel.nl",
    "wof:name":"Hypotheekkantoor, 'T",
    "wof:placetype":"venue"
},
  "geometry": {"coordinates":[6.651994,52.355198],"type":"Point"}
}