{
  "type": "Feature",
  "properties": {
    "addr:full":"Mariaplaats 48 Utrecht Utrecht 3511 LM",
    "addr:housenumber":"48",
    "addr:postcode":"3511 lm",
    "addr:street":"Mariaplaats",
    "iso:country":"NL",
    "sg:address":"Mariaplaats 48",
    "sg:city":"Utrecht",
    "sg:orig_category":"Verlichting",
    "sg:phone":"+31 30 232 8724",
    "sg:postcode":"3511 LM",
    "sg:province":"Utrecht",
    "sg:website":"http://www.queensgallery.nl",
    "wof:name":"Queens Gallery",
    "wof:placetype":"venue"
},
  "geometry": {"coordinates":[5.118164,52.089397],"type":"Point"}
}