{
  "type": "Feature",
  "properties": {
    "addr:full":"Gruttostr 1 Heerlen Limburg 6414 VX",
    "addr:housenumber":"1",
    "addr:postcode":"6414 vx",
    "addr:street":"Gruttostr",
    "iso:country":"NL",
    "sg:address":"Gruttostr 1",
    "sg:city":"Heerlen",
    "sg:orig_category":"Glazenwasserijen",
    "sg:phone":"+31 45 521 4188",
    "sg:postcode":"6414 VX",
    "sg:province":"Limburg",
    "wof:name":"Ster, De",
    "wof:placetype":"venue"
},
  "geometry": {"coordinates":[5.976748,50.911945],"type":"Point"}
}