{
  "type": "Feature",
  "properties": {
    "iso:country":"NL",
    "sg:address":"Lange Hezelstraat 103",
    "sg:city":"Nijmegen",
    "sg:orig_category":"Juweliers",
    "sg:phone":"+31 24 323 7754",
    "sg:postcode":"6511 CE",
    "sg:province":"Gelderland",
    "wof:name":"B. Verkroost Goud Zilver Sieraden",
    "wof:placetype":"venue"
},
  "geometry": {"coordinates":[5.857189,51.848236],"type":"Point"}
}