{
  "type": "Feature",
  "properties": {
    "addr:full":"Lopikerstr 25 Schoonhoven South Holland 2871 BT",
    "addr:housenumber":"25",
    "addr:postcode":"2871 bt",
    "addr:street":"Lopikerstr",
    "iso:country":"NL",
    "sg:address":"Lopikerstr 25",
    "sg:city":"Schoonhoven",
    "sg:orig_category":"Kinderkleding",
    "sg:phone":"+31 182 384 195",
    "sg:postcode":"2871 BT",
    "sg:province":"South Holland",
    "wof:name":"Chips For Kids",
    "wof:placetype":"venue"
},
  "geometry": {"coordinates":[4.853177,51.946323],"type":"Point"}
}