{
  "type": "Feature",
  "properties": {
    "addr:full":"Spanbroekerweg 140 Spanbroek North Holland 1715 GT",
    "addr:housenumber":"140",
    "addr:postcode":"1715 gt",
    "addr:street":"Spanbroekerweg",
    "iso:country":"NL",
    "sg:address":"Spanbroekerweg 140",
    "sg:city":"Spanbroek",
    "sg:orig_category":"Paramedische Behandelingen",
    "sg:phone":"+31 226 352 844",
    "sg:postcode":"1715 GT",
    "sg:province":"North Holland",
    "wof:name":"Stg Thuiszorg West-Friesland",
    "wof:placetype":"venue"
},
  "geometry": {"coordinates":[4.957791,52.698479],"type":"Point"}
}