{
  "type": "Feature",
  "properties": {
    "addr:full":"Tafelstr 28 Maastricht Limburg 6211 JD",
    "addr:housenumber":"28",
    "addr:postcode":"6211 jd",
    "addr:street":"Tafelstr",
    "iso:country":"NL",
    "sg:address":"Tafelstr 28",
    "sg:city":"Maastricht",
    "sg:classifiers":[
        {
            "category":"Travel",
            "subcategory":"Hotels & Motels",
            "type":"Entertainment"
        }
    ],
    "sg:phone":"+31 43 321 5479",
    "sg:postcode":"6211 JD",
    "sg:province":"Limburg",
    "sg:website":"http://www.hoteldis.nl",
    "wof:name":"Dis",
    "wof:placetype":"venue"
},
  "geometry": {"coordinates":[5.690616,50.845985],"type":"Point"}
}