{
  "type": "Feature",
  "properties": {
    "addr:full":"Wouwseweg 120 Roosendaal Noord-Brabant 4703 BW",
    "addr:housenumber":"120",
    "addr:postcode":"4703 bw",
    "addr:street":"Wouwseweg",
    "iso:country":"NL",
    "sg:address":"Wouwseweg 120",
    "sg:city":"Roosendaal",
    "sg:orig_category":"Schoonheidssalons",
    "sg:phone":"+31 165 555 506",
    "sg:postcode":"4703 BW",
    "sg:province":"Noord-Brabant",
    "wof:name":"Althaea, Salon Voor Huid- En Schoonh.Verz.",
    "wof:placetype":"venue"
},
  "geometry": {"coordinates":[4.438464,51.531281],"type":"Point"}
}