{
  "type": "Feature",
  "properties": {
    "addr:full":"Postbus 221 Hillegom Zuid-Holland 2180 AE",
    "addr:housenumber":"221",
    "addr:postcode":"2180 ae",
    "addr:street":"Postbus",
    "iso:country":"NL",
    "sg:address":"Postbus 221",
    "sg:city":"Hillegom",
    "sg:orig_category":"Bloembollen - Groothandel",
    "sg:phone":"+31 252 520 854",
    "sg:postcode":"2180 AE",
    "sg:province":"Zuid-Holland",
    "wof:name":"Warmenhoven, Fa W S",
    "wof:placetype":"venue"
},
  "geometry": {"coordinates":[4.578603,52.290993],"type":"Point"}
}