{
  "type": "Feature",
  "properties": {
    "iso:country":"NL",
    "sg:address":"Burg Poswg 19",
    "sg:city":"Brakel",
    "sg:orig_category":"Verf En Lak",
    "sg:phone":"+31 418 671 349",
    "sg:postcode":"5306 GA",
    "sg:province":"Gelderland",
    "wof:name":"Beek, Van",
    "wof:placetype":"venue"
},
  "geometry": {"coordinates":[5.094254,51.819618],"type":"Point"}
}