{
  "type": "Feature",
  "properties": {
    "addr:full":"Zonstr 85 Utrecht Utrecht 3581 MR",
    "addr:housenumber":"85",
    "addr:postcode":"3581 mr",
    "addr:street":"Zonstr",
    "iso:country":"NL",
    "sg:address":"Zonstr 85",
    "sg:city":"Utrecht",
    "sg:orig_category":"Loopbaanbegeleiding",
    "sg:phone":"+31 30 658 6530",
    "sg:postcode":"3581 MR",
    "sg:province":"Utrecht",
    "wof:name":"Via Trias",
    "wof:placetype":"venue"
},
  "geometry": {"coordinates":[5.136546,52.084839],"type":"Point"}
}