{
  "type": "Feature",
  "properties": {
    "addr:full":"Kamperzeedk 149A Genemuiden Overijssel 8281 PE",
    "addr:housenumber":"149a",
    "addr:postcode":"8281 pe",
    "iso:country":"NL",
    "sg:address":"Kamperzeedk 149A",
    "sg:city":"Genemuiden",
    "sg:orig_category":"Paardenhandelaren",
    "sg:phone":"+31 38 344 6235",
    "sg:postcode":"8281 PE",
    "sg:province":"Overijssel",
    "wof:name":"Toering, M P",
    "wof:placetype":"venue"
},
  "geometry": {"coordinates":[6.0216288567,52.6067237854],"type":"Point"}
}