{
  "type": "Feature",
  "properties": {
    "addr:full":"Herensngl 174 Weesp Noord-Holland 1382 VV",
    "addr:housenumber":"174",
    "addr:postcode":"1382 vv",
    "iso:country":"NL",
    "sg:address":"Herensngl 174",
    "sg:city":"Weesp",
    "sg:orig_category":"Accountants - Administratie- Consulenten En -Kantoren",
    "sg:phone":"+31 294 410 395",
    "sg:postcode":"1382 VV",
    "sg:province":"Noord-Holland",
    "wof:name":"Berrevoets",
    "wof:placetype":"venue"
},
  "geometry": {"coordinates":[5.03828,52.308315],"type":"Point"}
}