{
  "type": "Feature",
  "properties": {
    "addr:full":"Kattensngl 7 Gouda Zuid-Holland 2801 CA",
    "addr:housenumber":"7",
    "addr:postcode":"2801 ca",
    "addr:street":"Kattensngl",
    "iso:country":"NL",
    "sg:address":"Kattensngl 7",
    "sg:city":"Gouda",
    "sg:orig_category":"Psychologen",
    "sg:phone":"+31 182 548 772",
    "sg:postcode":"2801 CA",
    "sg:province":"Zuid-Holland",
    "wof:name":"Prakt Voor Eerstelijns Psychologie Gouda",
    "wof:placetype":"venue"
},
  "geometry": {"coordinates":[4.710715,52.010006],"type":"Point"}
}