{
  "type": "Feature",
  "properties": {
    "addr:full":"Stationswg 91 Breukelen Ut Utrecht 3621 LK",
    "addr:housenumber":"91",
    "addr:postcode":"3621 lk",
    "addr:street":"Stationswg",
    "iso:country":"NL",
    "sg:address":"Stationswg 91",
    "sg:city":"Breukelen Ut",
    "sg:classifiers":[
        {
            "category":"Travel",
            "subcategory":"Hotels & Motels",
            "type":"Entertainment"
        }
    ],
    "sg:phone":"+31 346 265 888",
    "sg:postcode":"3621 LK",
    "sg:province":"Utrecht",
    "sg:website":"http://www.valk.com",
    "wof:name":"Hotel Breukelen",
    "wof:placetype":"venue"
},
  "geometry": {"coordinates":[5.001585,52.172958],"type":"Point"}
}