{
  "type": "Feature",
  "properties": {
    "addr:full":"Zyde 204 Boskoop Zuid-Holland 2771 ET",
    "addr:housenumber":"204",
    "addr:postcode":"2771 et",
    "iso:country":"NL",
    "sg:address":"Zyde 204",
    "sg:city":"Boskoop",
    "sg:orig_category":"Fotopersbureaus",
    "sg:phone":"+31 6 22406128",
    "sg:postcode":"2771 ET",
    "sg:province":"Zuid-Holland",
    "wof:name":"Fioole, A",
    "wof:placetype":"venue"
},
  "geometry": {"coordinates":[4.64775,52.074986],"type":"Point"}
}