{
  "type": "Feature",
  "properties": {
    "addr:full":"Kerkstr 11 Assen Drenthe 9401 GV",
    "addr:housenumber":"11",
    "addr:postcode":"9401 gv",
    "addr:street":"Kerkstr",
    "iso:country":"NL",
    "sg:address":"Kerkstr 11",
    "sg:city":"Assen",
    "sg:classifiers":[
        {
            "category":"Food & Beverages",
            "subcategory":"Bakery",
            "type":"Retail Goods"
        }
    ],
    "sg:phone":"+31 592 314 801",
    "sg:postcode":"9401 GV",
    "sg:province":"Drenthe",
    "sg:tags":[
        "pizza"
    ],
    "wof:name":"Bella Italia",
    "wof:placetype":"venue"
},
  "geometry": {"coordinates":[6.560053,52.99287],"type":"Point"}
}