{
  "type": "Feature",
  "properties": {
    "addr:full":"Kostverlorenwg 15 Amstelveen North Holland 1183 TM",
    "addr:housenumber":"15",
    "addr:postcode":"1183 tm",
    "addr:street":"Kostverlorenwg",
    "iso:country":"NL",
    "sg:address":"Kostverlorenwg 15",
    "sg:city":"Amstelveen",
    "sg:orig_category":"Verenigingen En Stichtingen",
    "sg:phone":"+31 20 645 8867",
    "sg:postcode":"1183 TM",
    "sg:province":"North Holland",
    "wof:name":"Amnesty International Groep",
    "wof:placetype":"venue"
},
  "geometry": {"coordinates":[4.89402,52.318626],"type":"Point"}
}