{
  "type": "Feature",
  "properties": {
    "addr:full":"Oude Koemarkt 7 Sneek Provincie Friesland 8601 EH",
    "addr:housenumber":"7",
    "addr:postcode":"8601 eh",
    "addr:street":"Oude Koemarkt;Provincie Friesland",
    "iso:country":"NL",
    "sg:address":"Oude Koemarkt 7",
    "sg:city":"Sneek",
    "sg:orig_category":"Kappers",
    "sg:phone":"+31 515 414 141",
    "sg:postcode":"8601 EH",
    "sg:province":"Provincie Friesland",
    "wof:name":"Kapsalon Therese",
    "wof:placetype":"venue"
},
  "geometry": {"coordinates":[5.6586461067,53.0313110352],"type":"Point"}
}