{
  "type": "Feature",
  "properties": {
    "addr:full":"Cattenhagestr 43 Naarden Noord-Holland 1411 CS",
    "addr:housenumber":"43",
    "addr:postcode":"1411 cs",
    "addr:street":"Cattenhagestr",
    "iso:country":"NL",
    "sg:address":"Cattenhagestr 43",
    "sg:city":"Naarden",
    "sg:orig_category":"Cafetaria'S",
    "sg:phone":"+31 35 694 1413",
    "sg:postcode":"1411 CS",
    "sg:province":"Noord-Holland",
    "wof:name":"Vesting, De",
    "wof:placetype":"venue"
},
  "geometry": {"coordinates":[5.160388,52.295643],"type":"Point"}
}