{
  "type": "Feature",
  "properties": {
    "iso:country":"NL",
    "sg:address":"Ervesestraat 1",
    "sg:city":"Ottersum",
    "sg:orig_category":"Verhuur Audiovisuele Apparatuur",
    "sg:phone":"+31 485 512 361",
    "sg:postcode":"6595 PE",
    "sg:province":"Limburg",
    "wof:name":"Geluidstechniek Nol Tissen",
    "wof:placetype":"venue"
},
  "geometry": {"coordinates":[6.02687,51.686253],"type":"Point"}
}