{
  "type": "Feature",
  "properties": {
    "addr:full":"Hykerwg 11 Hooghalen Drenthe 9414 VA",
    "addr:housenumber":"11",
    "addr:postcode":"9414",
    "addr:street":"Hykerwg",
    "iso:country":"NL",
    "sg:address":"Hykerwg 11",
    "sg:city":"Hooghalen",
    "sg:orig_category":"Vakantieverblijven",
    "sg:phone":"+31 593 592 351",
    "sg:postcode":"9414 VA",
    "sg:province":"Drenthe",
    "wof:name":"Hiekerhoes, 'T",
    "wof:placetype":"venue"
},
  "geometry": {"coordinates":[-79.771446,38.003349],"type":"Point"}
}