{
  "type": "Feature",
  "properties": {
    "addr:full":"Tobe 16 Oud Gastel Noord-Brabant 4751 GB",
    "addr:housenumber":"16",
    "addr:postcode":"4751 gb",
    "addr:street":"Tobe",
    "iso:country":"NL",
    "sg:address":"Tobe 16",
    "sg:city":"Oud Gastel",
    "sg:orig_category":"Metaalwerken",
    "sg:phone":"+31 165 513 081",
    "sg:postcode":"4751 GB",
    "sg:province":"Noord-Brabant",
    "wof:name":"J.D.J. Van Trijp",
    "wof:placetype":"venue"
},
  "geometry": {"coordinates":[-2.23218,54.313919],"type":"Point"}
}