{
  "type": "Feature",
  "properties": {
    "addr:full":"Hoofdweg 136 Harkstede Groningen 9617 AK",
    "addr:housenumber":"136",
    "addr:postcode":"9617 ak",
    "addr:street":"Hoofdweg",
    "iso:country":"NL",
    "sg:address":"Hoofdweg 136",
    "sg:city":"Harkstede",
    "sg:orig_category":"Kappers",
    "sg:phone":"+31 50 404 2659",
    "sg:postcode":"9617 AK",
    "sg:province":"Groningen",
    "wof:name":"Derk'S Hairfashion",
    "wof:placetype":"venue"
},
  "geometry": {"coordinates":[6.6850919724,53.2104454041],"type":"Point"}
}