{
  "type": "Feature",
  "properties": {
    "iso:country":"NL",
    "sg:address":"Vlakdissel 3",
    "sg:city":"De Goorn",
    "sg:classifiers":[
        {
            "category":"Retail",
            "subcategory":"Storage",
            "type":"Services"
        }
    ],
    "sg:phone":"+31 229 542 627",
    "sg:postcode":"1648 HJ",
    "sg:province":"Noord-Holland",
    "sg:tags":[
        "opslag",
        "bewaring"
    ],
    "wof:name":"Space 2000 Bv",
    "wof:placetype":"venue"
},
  "geometry": {"coordinates":[4.9558691978,52.6267814636],"type":"Point"}
}