{
  "type": "Feature",
  "properties": {
    "iso:country":"NL",
    "sg:address":"Beetgumerstraat 62",
    "sg:city":"Leeuwarden",
    "sg:orig_category":"Zuivelproducten",
    "sg:phone":"+31 58 213 0995",
    "sg:postcode":"8913 AV",
    "sg:province":"Friesland",
    "wof:name":"Melk- En Zuivelhandel Boorsma",
    "wof:placetype":"venue"
},
  "geometry": {"coordinates":[5.780661,53.203449],"type":"Point"}
}