{
  "type": "Feature",
  "properties": {
    "addr:full":"Sumatrastraat 23 Enschede Overijssel 7512 CS",
    "addr:housenumber":"23",
    "addr:postcode":"7512 cs",
    "addr:street":"Sumatrastraat",
    "iso:country":"NL",
    "sg:address":"Sumatrastraat 23",
    "sg:city":"Enschede",
    "sg:orig_category":"Metaalwerken",
    "sg:phone":"+31 53 430 3006",
    "sg:postcode":"7512 CS",
    "sg:province":"Overijssel",
    "wof:name":"Alutex - Voogdgeert",
    "wof:placetype":"venue"
},
  "geometry": {"coordinates":[6.893982,52.211926],"type":"Point"}
}