{
  "type": "Feature",
  "properties": {
    "addr:full":"Deurningerstraat 1 Enschede Overijssel 7514 BC",
    "addr:housenumber":"1",
    "addr:postcode":"7514 bc",
    "addr:street":"Deurningerstraat",
    "iso:country":"NL",
    "sg:address":"Deurningerstraat 1",
    "sg:city":"Enschede",
    "sg:orig_category":"Herenmodezaken",
    "sg:phone":"+31 53 435 3529",
    "sg:postcode":"7514 BC",
    "sg:province":"Overijssel",
    "wof:name":"Nietsch Modehuis Bv",
    "wof:placetype":"venue"
},
  "geometry": {"coordinates":[6.89198,52.223549],"type":"Point"}
}