{
  "type": "Feature",
  "properties": {
    "addr:full":"Schutwg 47 Lelystad Flevoland 8243 PC",
    "addr:housenumber":"47",
    "addr:postcode":"8243 pc",
    "addr:street":"Schutwg;Flevoland",
    "iso:country":"NL",
    "sg:address":"Schutwg 47",
    "sg:city":"Lelystad",
    "sg:orig_category":"Wegenbouw - Materieel",
    "sg:phone":"+31 320 257 890",
    "sg:postcode":"8243 PC",
    "sg:province":"Flevoland",
    "wof:name":"Reproad Bv",
    "wof:placetype":"venue"
},
  "geometry": {"coordinates":[5.4467358589,52.5036087036],"type":"Point"}
}