{
  "type": "Feature",
  "properties": {
    "addr:full":"Isendoornstr 1 Zutphen Gelderland 7201 NJ",
    "addr:housenumber":"1",
    "addr:postcode":"7201",
    "addr:street":"Isendoornstr;Gelderland",
    "iso:country":"NL",
    "sg:address":"Isendoornstr 1",
    "sg:city":"Zutphen",
    "sg:orig_category":"Scholen Voor Algemeen Voortgezet Onderwijs",
    "sg:phone":"+31 575 515 041",
    "sg:postcode":"7201 NJ",
    "sg:province":"Gelderland",
    "wof:name":"Baudartius College",
    "wof:placetype":"venue"
},
  "geometry": {"coordinates":[6.19844,52.1451],"type":"Point"}
}