{
  "type": "Feature",
  "properties": {
    "addr:full":"Amstelplein 1 Amsterdam Noord-Holland 1096 HA",
    "addr:housenumber":"1",
    "addr:postcode":"1096 ha",
    "addr:street":"Amstelplein",
    "iso:country":"NL",
    "sg:address":"Amstelplein 1",
    "sg:city":"Amsterdam",
    "sg:orig_category":"Ambassades And Consulaten",
    "sg:phone":"+31 20 679 9916",
    "sg:postcode":"1096 HA",
    "sg:province":"Noord-Holland",
    "wof:name":"Consulaat Generaal Van Thailand",
    "wof:placetype":"venue"
},
  "geometry": {"coordinates":[4.917649,52.344311],"type":"Point"}
}