{
  "type": "Feature",
  "properties": {
    "addr:full":"Doctor Huber Noodtstraat 10 Doetinchem Gelderland 7001 DW",
    "addr:housenumber":"10",
    "addr:postcode":"7001 dw",
    "addr:street":"Doctor Huber Noodtstraat;Gelderland",
    "iso:country":"NL",
    "sg:address":"Doctor Huber Noodtstraat 10",
    "sg:city":"Doetinchem",
    "sg:orig_category":"Meubelzaken, Woning- And Keukeninrichting",
    "sg:phone":"+31 314 334 291",
    "sg:postcode":"7001 DW",
    "sg:province":"Gelderland",
    "wof:name":"Rulof Slaapcomfort Bv",
    "wof:placetype":"venue"
},
  "geometry": {"coordinates":[6.291328,51.966976],"type":"Point"}
}