{
  "type": "Feature",
  "properties": {
    "iso:country":"NL",
    "sg:address":"John F Kennedylaan 79",
    "sg:city":"Valkenswaard",
    "sg:orig_category":"Wasserettes And Stomerijen",
    "sg:phone":"+31 40 201 6832",
    "sg:postcode":"5555 XC",
    "sg:province":"Noord-Brabant",
    "wof:name":"Espres Strijkerij Perserij Reconditioneren Stomen",
    "wof:placetype":"venue"
},
  "geometry": {"coordinates":[5.4916157722,51.351474762],"type":"Point"}
}