{
  "type": "Feature",
  "properties": {
    "addr:full":"Rynsburgerwg 10 Leiden Zuid-Holland 2333 AA",
    "addr:housenumber":"10",
    "addr:postcode":"2333 aa",
    "addr:street":"Rynsburgerwg",
    "iso:country":"NL",
    "sg:address":"Rynsburgerwg 10",
    "sg:city":"Leiden",
    "sg:orig_category":"Belastingconsulenten/ Belastingadviseurs",
    "sg:phone":"+31 71 523 0240",
    "sg:postcode":"2333 AA",
    "sg:province":"Zuid-Holland",
    "wof:name":"Vvaa",
    "wof:placetype":"venue"
},
  "geometry": {"coordinates":[4.481427,52.168404],"type":"Point"}
}