{
  "type": "Feature",
  "properties": {
    "addr:full":"Einsteinstr 12 Almelo Overijssel 7601 PR",
    "addr:housenumber":"12",
    "addr:postcode":"7601 pr",
    "addr:street":"Einsteinstr",
    "iso:country":"NL",
    "sg:address":"Einsteinstr 12",
    "sg:city":"Almelo",
    "sg:orig_category":"Gordijnstoffen - Fabrieken En Groothandel",
    "sg:phone":"+31 546 873 305",
    "sg:postcode":"7601 PR",
    "sg:province":"Overijssel",
    "wof:name":"Rigarnet Stark Bv",
    "wof:placetype":"venue"
},
  "geometry": {"coordinates":[6.68162,52.341499],"type":"Point"}
}