{
  "type": "Feature",
  "properties": {
    "addr:full":"Postbus 111 Roden Drenthe 9300 AC",
    "addr:housenumber":"111",
    "addr:postcode":"9300 ac",
    "addr:street":"Postbus",
    "iso:country":"NL",
    "sg:address":"Postbus 111",
    "sg:city":"Roden",
    "sg:orig_category":"Geluidshinderbestrijding",
    "sg:phone":"+31 50 501 0066",
    "sg:postcode":"9300 AC",
    "sg:province":"Drenthe",
    "wof:name":"Teensma Bv",
    "wof:placetype":"venue"
},
  "geometry": {"coordinates":[6.43283,53.138321],"type":"Point"}
}