{
  "type": "Feature",
  "properties": {
    "addr:full":"Herenwg 22 Rynsaterwoude South Holland 2465 AC",
    "addr:housenumber":"22",
    "addr:postcode":"2465 ac",
    "addr:street":"Herenwg",
    "iso:country":"NL",
    "sg:address":"Herenwg 22",
    "sg:city":"Rynsaterwoude",
    "sg:orig_category":"Verenigingsgebouwen",
    "sg:phone":"+31 172 509 708",
    "sg:postcode":"2465 AC",
    "sg:province":"South Holland",
    "wof:name":"Schoolhuis, 'T",
    "wof:placetype":"venue"
},
  "geometry": {"coordinates":[4.670552,52.199837],"type":"Point"}
}