{
  "type": "Feature",
  "properties": {
    "addr:full":"Plantage 28 Oude Wetering Zuid-Holland 2377 AJ",
    "addr:housenumber":"28",
    "addr:postcode":"wetering;2377 aj",
    "addr:street":"Plantage",
    "iso:country":"NL",
    "sg:address":"Plantage 28",
    "sg:city":"Oude Wetering",
    "sg:orig_category":"Pleziervaartuigen And Reparatie",
    "sg:phone":"+31 71 331 2250",
    "sg:postcode":"2377 AJ",
    "sg:province":"Zuid-Holland",
    "wof:name":"Jachtwerf Van Der Meer",
    "wof:placetype":"venue"
},
  "geometry": {"coordinates":[4.64713,52.20697],"type":"Point"}
}