{
  "type": "Feature",
  "properties": {
    "addr:full":"Groeneweg 3 Leeuwarden Provincie Friesland 8911 EH",
    "addr:housenumber":"3",
    "addr:postcode":"8911 eh",
    "addr:street":"Groeneweg;Provincie Friesland",
    "iso:country":"NL",
    "sg:address":"Groeneweg 3",
    "sg:city":"Leeuwarden",
    "sg:orig_category":"Kinderopvang Behalve Thuis",
    "sg:phone":"+31 58 212 1902",
    "sg:postcode":"8911 EH",
    "sg:province":"Provincie Friesland",
    "wof:name":"Vila Kakelbont Kinderopvang",
    "wof:placetype":"venue"
},
  "geometry": {"coordinates":[5.794496,53.204502],"type":"Point"}
}