{
  "type": "Feature",
  "properties": {
    "addr:full":"Sperwer 1 Staphorst NL.08 7951 MG",
    "addr:housenumber":"1;nl.08",
    "addr:postcode":"7951 mg",
    "addr:street":"Sperwer",
    "iso:country":"NL",
    "sg:address":"Sperwer 1",
    "sg:city":"Staphorst",
    "sg:orig_category":"Wegen And Sportterreinen",
    "sg:phone":"+31 522 464 952",
    "sg:postcode":"7951 MG",
    "sg:province":"NL.08",
    "wof:name":"H. Dunnink",
    "wof:placetype":"venue"
},
  "geometry": {"coordinates":[6.2114090919,52.6389808655],"type":"Point"}
}