{
  "type": "Feature",
  "properties": {
    "addr:full":"Dillenburgsngl 9 Vlaardingen South Holland 3136 EA",
    "addr:housenumber":"9",
    "addr:postcode":"3136 ea",
    "addr:street":"Dillenburgsngl",
    "iso:country":"NL",
    "sg:address":"Dillenburgsngl 9",
    "sg:city":"Vlaardingen",
    "sg:orig_category":"Kappers",
    "sg:phone":"+31 10 475 9376",
    "sg:postcode":"3136 EA",
    "sg:province":"South Holland",
    "wof:name":"Vaartland",
    "wof:placetype":"venue"
},
  "geometry": {"coordinates":[4.347273,51.924168],"type":"Point"}
}