{
  "type": "Feature",
  "properties": {
    "addr:full":"De Brauwstr 35 Woerden Utrecht 3443 TE",
    "addr:housenumber":"35",
    "addr:postcode":"3443 te",
    "addr:street":"Woerden",
    "iso:country":"NL",
    "sg:address":"De Brauwstr 35",
    "sg:city":"Woerden",
    "sg:orig_category":"Onderhoudswerken",
    "sg:phone":"+31 348 415 345",
    "sg:postcode":"3443 TE",
    "sg:province":"Utrecht",
    "wof:name":"Wirilon",
    "wof:placetype":"venue"
},
  "geometry": {"coordinates":[4.875684,52.088562],"type":"Point"}
}