{
  "type": "Feature",
  "properties": {
    "addr:full":"De Trompet 30 Enkhuizen Noord-Holland 1601 MK",
    "addr:housenumber":"30",
    "addr:postcode":"1601",
    "addr:street":"De Trompet",
    "iso:country":"NL",
    "sg:address":"De Trompet 30",
    "sg:city":"Enkhuizen",
    "sg:orig_category":"Gespecialiseerde Bouw",
    "sg:phone":"+31 228 313 641",
    "sg:postcode":"1601 MK",
    "sg:province":"Noord-Holland",
    "wof:name":"Enkhuizer Constructiebedrijf J. De Bruin Bv",
    "wof:placetype":"venue"
},
  "geometry": {"coordinates":[5.2677,52.692894],"type":"Point"}
}