{
  "type": "Feature",
  "properties": {
    "addr:full":"Julianalaan 45 Montfoort Utrecht 3417 GJ",
    "addr:housenumber":"45",
    "addr:postcode":"3417 gj",
    "addr:street":"Julianalaan",
    "iso:country":"NL",
    "sg:address":"Julianalaan 45",
    "sg:city":"Montfoort",
    "sg:orig_category":"Koeriersdiensten",
    "sg:phone":"+31 348 472 380",
    "sg:postcode":"3417 GJ",
    "sg:province":"Utrecht",
    "wof:name":"K.B.S. Koeriers Bedrijf Sas",
    "wof:placetype":"venue"
},
  "geometry": {"coordinates":[4.941907,52.041557],"type":"Point"}
}