{
  "type": "Feature",
  "properties": {
    "iso:country":"NL",
    "sg:address":"Westewagenstr 54",
    "sg:city":"Rotterdam",
    "sg:orig_category":"Verzekeringen - Verzekeringskantoren",
    "sg:phone":"+31 10 511 5829",
    "sg:postcode":"3011 AT",
    "sg:province":"Zuid-Holland",
    "wof:name":"Montes Kompaan Groep Bv",
    "wof:placetype":"venue"
},
  "geometry": {"coordinates":[4.482799,51.921619],"type":"Point"}
}