{
  "type": "Feature",
  "properties": {
    "iso:country":"NL",
    "sg:address":"Swingoerd 15",
    "sg:city":"Wommels",
    "sg:orig_category":"Metaalbekleding And -Behandeling",
    "sg:phone":"+31 515 577 515",
    "sg:postcode":"8731 CV",
    "sg:province":"Provincie Friesland",
    "wof:name":"Folkertsma Montagebedrijf",
    "wof:placetype":"venue"
},
  "geometry": {"coordinates":[5.592361,53.111729],"type":"Point"}
}