{
  "type": "Feature",
  "properties": {
    "addr:full":"De Schoof 48 Hendrik Ido Ambacht Zuid-Holland 3341 EB",
    "addr:housenumber":"48",
    "addr:postcode":"ido ambacht;3341 eb",
    "addr:street":"De Schoof",
    "iso:country":"NL",
    "sg:address":"De Schoof 48",
    "sg:city":"Hendrik Ido Ambacht",
    "sg:orig_category":"Verlichting And Huishoudartikelen",
    "sg:phone":"+31 78 684 0957",
    "sg:postcode":"3341 EB",
    "sg:province":"Zuid-Holland",
    "wof:name":"Marskramer",
    "wof:placetype":"venue"
},
  "geometry": {"coordinates":[4.644821,51.849392],"type":"Point"}
}