{
  "type": "Feature",
  "properties": {
    "iso:country":"NL",
    "sg:address":"T Steenwerk 32",
    "sg:city":"Ravenstein",
    "sg:orig_category":"Kabelwerken",
    "sg:phone":"+31 486 432 534",
    "sg:postcode":"5371 LA",
    "sg:province":"North Brabant",
    "wof:name":"Swanenberg",
    "wof:placetype":"venue"
},
  "geometry": {"coordinates":[5.6293182373,51.8026847839],"type":"Point"}
}