{
  "type": "Feature",
  "properties": {
    "addr:full":"Schenkeldijk 75 Strijen South Holland 3291 EP",
    "addr:housenumber":"75",
    "addr:postcode":"3291 ep",
    "addr:street":"Schenkeldijk",
    "iso:country":"NL",
    "sg:address":"Schenkeldijk 75",
    "sg:city":"Strijen",
    "sg:orig_category":"Fruit And Groenten Gh",
    "sg:phone":"+31 78 674 4235",
    "sg:postcode":"3291 EP",
    "sg:province":"South Holland",
    "wof:name":"Adios",
    "wof:placetype":"venue"
},
  "geometry": {"coordinates":[4.569059,51.730389],"type":"Point"}
}