{
  "type": "Feature",
  "properties": {
    "addr:full":"Stationswg 6 Maasbracht Limburg 6051 KL",
    "addr:housenumber":"6",
    "addr:postcode":"6051 kl",
    "addr:street":"Stationswg",
    "iso:country":"NL",
    "sg:address":"Stationswg 6",
    "sg:city":"Maasbracht",
    "sg:orig_category":"Keukens",
    "sg:phone":"+31 475 464 339",
    "sg:postcode":"6051 KL",
    "sg:province":"Limburg",
    "wof:name":"Rc",
    "wof:placetype":"venue"
},
  "geometry": {"coordinates":[5.909238,51.147842],"type":"Point"}
}