{
  "type": "Feature",
  "properties": {
    "addr:full":"Vinkenweg 32 Soest Utrecht 3762 TH",
    "addr:housenumber":"32",
    "addr:postcode":"3762 th",
    "addr:street":"Vinkenweg",
    "iso:country":"NL",
    "sg:address":"Vinkenweg 32",
    "sg:city":"Soest",
    "sg:orig_category":"Meubelreparatie And -Restauratie",
    "sg:phone":"+31 35 602 5056",
    "sg:postcode":"3762 TH",
    "sg:province":"Utrecht",
    "wof:name":"Zeilmakerij H.J. Wever",
    "wof:placetype":"venue"
},
  "geometry": {"coordinates":[5.278778,52.181183],"type":"Point"}
}