{
  "type": "Feature",
  "properties": {
    "addr:full":"Frederikstr 571 S Gravenhage Zuid-Holland 2514 LR",
    "addr:housenumber":"571;gravenhage",
    "addr:postcode":"2514 lr",
    "addr:street":"S",
    "iso:country":"NL",
    "sg:address":"Frederikstr 571",
    "sg:city":"S Gravenhage",
    "sg:orig_category":"Mode-Artikelen Dames En Heren",
    "sg:phone":"+31 70 360 8910",
    "sg:postcode":"2514 LR",
    "sg:province":"Zuid-Holland",
    "wof:name":"Tips",
    "wof:placetype":"venue"
},
  "geometry": {"coordinates":[4.30935,52.084148],"type":"Point"}
}