{
  "type": "Feature",
  "properties": {
    "iso:country":"NL",
    "sg:address":"Lindenln 3",
    "sg:city":"Valkenburg Lb",
    "sg:orig_category":"Veiligheidsuitrusting En -Kleding",
    "sg:phone":"+31 43 601 2888",
    "sg:postcode":"6301 HA",
    "sg:province":"Limburg",
    "wof:name":"Alpine Gehoorbescherming",
    "wof:placetype":"venue"
},
  "geometry": {"coordinates":[5.832836,50.866318],"type":"Point"}
}