{
  "type": "Feature",
  "properties": {
    "addr:full":"Middeldiepstraat 2 Sliedrecht South Holland 3361 VT",
    "addr:housenumber":"2",
    "addr:postcode":"3361",
    "addr:street":"Middeldiepstraat",
    "iso:country":"NL",
    "sg:address":"Middeldiepstraat 2",
    "sg:city":"Sliedrecht",
    "sg:orig_category":"Paramedische Behandelingen",
    "sg:phone":"+31 184 415 688",
    "sg:postcode":"3361 VT",
    "sg:province":"South Holland",
    "wof:name":"Dutch Treatment Beautycenter",
    "wof:placetype":"venue"
},
  "geometry": {"coordinates":[4.770786,51.819897],"type":"Point"}
}