{
  "type": "Feature",
  "properties": {
    "addr:full":"Prinsenln 82 Emmen Provincie Drenthe 7822 GJ",
    "addr:housenumber":"82",
    "addr:postcode":"7822 gj",
    "addr:street":"Prinsenln;Provincie Drenthe",
    "iso:country":"NL",
    "sg:address":"Prinsenln 82",
    "sg:city":"Emmen",
    "sg:orig_category":"Logopedisten",
    "sg:phone":"+31 591 613 213",
    "sg:postcode":"7822 GJ",
    "sg:province":"Provincie Drenthe",
    "wof:name":"Bosch, W M Van Den",
    "wof:placetype":"venue"
},
  "geometry": {"coordinates":[6.90359,52.784389],"type":"Point"}
}