{
  "type": "Feature",
  "properties": {
    "addr:full":"Marktstr 38C Mierlo North Brabant 5731 HW",
    "addr:housenumber":"38c",
    "addr:postcode":"5731 hw",
    "addr:street":"Marktstr",
    "iso:country":"NL",
    "sg:address":"Marktstr 38C",
    "sg:city":"Mierlo",
    "sg:classifiers":[
        {
            "category":"Wholesale",
            "subcategory":"Motor Vehicles",
            "type":"Manufacturing & Wholesale Goods"
        }
    ],
    "sg:phone":"+31 492 665 544",
    "sg:postcode":"5731 HW",
    "sg:province":"North Brabant",
    "sg:tags":[
        "scooter",
        "en"
    ],
    "wof:name":"Laverdist, De",
    "wof:placetype":"venue"
},
  "geometry": {"coordinates":[5.622781,51.444942],"type":"Point"}
}