{
  "type": "Feature",
  "properties": {
    "addr:full":"Korteraarseweg 25 Ter Aar South Holland 2461 GG",
    "addr:housenumber":"25",
    "addr:postcode":"2461 gg",
    "addr:street":"Korteraarseweg",
    "iso:country":"NL",
    "sg:address":"Korteraarseweg 25",
    "sg:city":"Ter Aar",
    "sg:orig_category":"Diverse Consumentenartikelen Gh",
    "sg:phone":"+31 172 603 010",
    "sg:postcode":"2461 GG",
    "sg:province":"South Holland",
    "wof:name":"Muziekhandel Straathof",
    "wof:placetype":"venue"
},
  "geometry": {"coordinates":[4.72809,52.166771],"type":"Point"}
}