{
  "type": "Feature",
  "properties": {
    "addr:full":"Haverstraat 7 Nieuw Vennep North Holland 2153 GB",
    "addr:housenumber":"7",
    "addr:postcode":"2153 gb",
    "addr:street":"Haverstraat;Nieuw Vennep North",
    "iso:country":"NL",
    "sg:address":"Haverstraat 7",
    "sg:city":"Nieuw Vennep",
    "sg:orig_category":"Parfum And Cosmetica Gh",
    "sg:phone":"+31 252 687 371",
    "sg:postcode":"2153 GB",
    "sg:province":"North Holland",
    "wof:name":"Revlon Nederland Bv",
    "wof:placetype":"venue"
},
  "geometry": {"coordinates":[4.641675,52.267742],"type":"Point"}
}