{
  "type": "Feature",
  "properties": {
    "addr:full":"Zuiderhoofdstraat 8 Exloo Drenthe 7875 BX",
    "addr:housenumber":"8",
    "addr:postcode":"7875 bx",
    "addr:street":"Zuiderhoofdstraat",
    "iso:country":"NL",
    "sg:address":"Zuiderhoofdstraat 8",
    "sg:city":"Exloo",
    "sg:orig_category":"Musea And Historische Gebouwen",
    "sg:phone":"+31 591 549 242",
    "sg:postcode":"7875 BX",
    "sg:province":"Drenthe",
    "wof:name":"Museum Bebinghehoes",
    "wof:placetype":"venue"
},
  "geometry": {"coordinates":[6.86435,52.880833],"type":"Point"}
}