{
  "type": "Feature",
  "properties": {
    "iso:country":"NL",
    "sg:address":"Nieuwe Crooswijkseweg 62",
    "sg:city":"Rotterdam",
    "sg:orig_category":"Afvalinzameling And -Verwerking",
    "sg:phone":"+31 10 433 4689",
    "sg:postcode":"3034 PS",
    "sg:province":"Zuid-Holland",
    "wof:name":"Isolatieservice Isocom Bv",
    "wof:placetype":"venue"
},
  "geometry": {"coordinates":[4.496964,51.934525],"type":"Point"}
}