{
  "type": "Feature",
  "properties": {
    "iso:country":"NL",
    "sg:address":"Goudsestraatweg 8",
    "sg:city":"Oudewater",
    "sg:orig_category":"Banken And Kredietinstellingen",
    "sg:phone":"+31 348 563 744",
    "sg:postcode":"3421 GJ",
    "sg:province":"Utrecht",
    "wof:name":"Ing Bank",
    "wof:placetype":"venue"
},
  "geometry": {"coordinates":[4.867007,52.021786],"type":"Point"}
}