{
  "type": "Feature",
  "properties": {
    "addr:full":"Friesestrwg 426 Groningen Groningen 9746 TL",
    "addr:housenumber":"426",
    "addr:postcode":"9746 tl",
    "iso:country":"NL",
    "sg:address":"Friesestrwg 426",
    "sg:city":"Groningen",
    "sg:orig_category":"Land- En Tuinbouw - Loonbedrijven",
    "sg:phone":"+31 50 579 0678",
    "sg:postcode":"9746 TL",
    "sg:province":"Groningen",
    "wof:name":"Klooster, D M",
    "wof:placetype":"venue"
},
  "geometry": {"coordinates":[6.514095,53.250099],"type":"Point"}
}