{
  "type": "Feature",
  "properties": {
    "addr:full":"Wilhelminaln 45 Maasbracht Limburg 6051 BH",
    "addr:housenumber":"45",
    "addr:postcode":"6051 bh",
    "addr:street":"Wilhelminaln",
    "iso:country":"NL",
    "sg:address":"Wilhelminaln 45",
    "sg:city":"Maasbracht",
    "sg:orig_category":"Verhuizingen",
    "sg:phone":"+31 475 461 587",
    "sg:postcode":"6051 BH",
    "sg:province":"Limburg",
    "wof:name":"Wilms Bv",
    "wof:placetype":"venue"
},
  "geometry": {"coordinates":[5.891117,51.147446],"type":"Point"}
}