{
  "type": "Feature",
  "properties": {
    "iso:country":"NL",
    "sg:address":"Trip 6",
    "sg:city":"Arcen",
    "sg:classifiers":[
        {
            "category":"Retail",
            "subcategory":"Photofinishing",
            "type":"Services"
        }
    ],
    "sg:phone":"+31 77 473 1250",
    "sg:postcode":"5944 CT",
    "sg:province":"Limburg",
    "sg:tags":[
        "foto",
        "film"
    ],
    "wof:name":"M J M Lommen",
    "wof:placetype":"venue"
},
  "geometry": {"coordinates":[6.180865,51.476917],"type":"Point"}
}