{
  "type": "Feature",
  "properties": {
    "addr:full":"Pernambucodreef 40 Utrecht Utrecht 3563 CT",
    "addr:housenumber":"40",
    "addr:postcode":"3563 ct",
    "addr:street":"Pernambucodreef",
    "iso:country":"NL",
    "sg:address":"Pernambucodreef 40",
    "sg:city":"Utrecht",
    "sg:orig_category":"Glazenwasserijen",
    "sg:phone":"+31 30 261 4216",
    "sg:postcode":"3563 CT",
    "sg:province":"Utrecht",
    "sg:website":"http://www.deladder.com",
    "wof:name":"Ladder Glazenwasserij, De",
    "wof:placetype":"venue"
},
  "geometry": {"coordinates":[5.101515,52.119595],"type":"Point"}
}