{
  "type": "Feature",
  "properties": {
    "iso:country":"NL",
    "sg:address":"Quistenburg 1",
    "sg:city":"Borssele",
    "sg:classifiers":[
        {
            "category":"Retail",
            "subcategory":"Storage",
            "type":"Services"
        }
    ],
    "sg:phone":"+31 113 351 235",
    "sg:postcode":"4454 PZ",
    "sg:province":"Zeeland",
    "sg:tags":[
        "opslag",
        "bewaring"
    ],
    "wof:name":"Schikker Logistics Bv",
    "wof:placetype":"venue"
},
  "geometry": {"coordinates":[3.7433290482,51.4287986755],"type":"Point"}
}