{
  "type": "Feature",
  "properties": {
    "iso:country":"NL",
    "sg:address":"Emmastraat 3",
    "sg:city":"Winschoten",
    "sg:orig_category":"Paramedische Behandelingen",
    "sg:phone":"+31 597 415 262",
    "sg:postcode":"9671 AP",
    "sg:province":"Groningen",
    "wof:name":"Oosterlengte Lokatie Thuiszorg Oost Groningen",
    "wof:placetype":"venue"
},
  "geometry": {"coordinates":[7.037354,53.14061],"type":"Point"}
}