{
  "type": "Feature",
  "properties": {
    "addr:full":"Emmastraat 3 Winschoten Groningen 9671 AP",
    "addr:housenumber":"3",
    "addr:postcode":"9671 ap",
    "addr:street":"Emmastraat",
    "iso:country":"NL",
    "sg:address":"Emmastraat 3",
    "sg:city":"Winschoten",
    "sg:orig_category":"Paramedische Behandelingen",
    "sg:phone":"+31 597 415 262",
    "sg:postcode":"9671 AP",
    "sg:province":"Groningen",
    "wof:name":"Oosterlengte Lokatie Thuiszorg Oost Groningen",
    "wof:placetype":"venue"
},
  "geometry": {"coordinates":[7.037354,53.14061],"type":"Point"}
}