{
  "type": "Feature",
  "properties": {
    "addr:full":"Pynswg 72 Heerlen Limburg 6419 CM",
    "addr:housenumber":"72",
    "addr:postcode":"6419 cm",
    "addr:street":"Pynswg",
    "iso:country":"NL",
    "sg:address":"Pynswg 72",
    "sg:city":"Heerlen",
    "sg:orig_category":"Banken",
    "sg:phone":"+31 45 574 0200",
    "sg:postcode":"6419 CM",
    "sg:province":"Limburg",
    "wof:name":"Regio Bank",
    "wof:placetype":"venue"
},
  "geometry": {"coordinates":[5.9661,50.875561],"type":"Point"}
}