{
  "type": "Feature",
  "properties": {
    "addr:full":"Van Hilligaertstraat 10 Amsterdam Noord-Holland 1072 JZ",
    "addr:housenumber":"10",
    "addr:postcode":"1072 jz",
    "addr:street":"Van Hilligaertstraat",
    "iso:country":"NL",
    "sg:address":"Van Hilligaertstraat 10",
    "sg:city":"Amsterdam",
    "sg:orig_category":"Binnenhuisarchitecten",
    "sg:phone":"+31 20 671 6685",
    "sg:postcode":"1072 JZ",
    "sg:province":"Noord-Holland",
    "wof:name":"Dawkins De Boer",
    "wof:placetype":"venue"
},
  "geometry": {"coordinates":[4.887108,52.34959],"type":"Point"}
}