{
  "type": "Feature",
  "properties": {
    "addr:full":"Norholm 15 Hoofddorp North Holland 2133 HJ",
    "addr:housenumber":"15",
    "addr:postcode":"2133 hj",
    "addr:street":"Norholm",
    "iso:country":"NL",
    "sg:address":"Norholm 15",
    "sg:city":"Hoofddorp",
    "sg:orig_category":"Bedrijfs- And Managementsconsultants",
    "sg:phone":"+31 23 555 6670",
    "sg:postcode":"2133 HJ",
    "sg:province":"North Holland",
    "wof:name":"A.B. Bartels",
    "wof:placetype":"venue"
},
  "geometry": {"coordinates":[4.670609,52.313183],"type":"Point"}
}