{
  "type": "Feature",
  "properties": {
    "addr:full":"Opalinestr 61 Maastricht Limburg 6216 VW",
    "addr:housenumber":"61",
    "addr:postcode":"6216 vw",
    "addr:street":"Opalinestr",
    "iso:country":"NL",
    "sg:address":"Opalinestr 61",
    "sg:city":"Maastricht",
    "sg:orig_category":"Beeldende Kunstenaars",
    "sg:phone":"+31 43 347 7520",
    "sg:postcode":"6216 VW",
    "sg:province":"Limburg",
    "wof:name":"Heijden, J A Van Der",
    "wof:placetype":"venue"
},
  "geometry": {"coordinates":[5.655315,50.850342],"type":"Point"}
}