{
  "type": "Feature",
  "properties": {
    "addr:full":"Lavendellaar 19 Veghel Noord-Brabant 5467 BG",
    "addr:housenumber":"19",
    "addr:postcode":"5467",
    "addr:street":"Lavendellaar",
    "iso:country":"NL",
    "sg:address":"Lavendellaar 19",
    "sg:city":"Veghel",
    "sg:orig_category":"Ingenieursbureaus",
    "sg:phone":"+31 413 365 485",
    "sg:postcode":"5467 BG",
    "sg:province":"Noord-Brabant",
    "wof:name":"Matek",
    "wof:placetype":"venue"
},
  "geometry": {"coordinates":[5.552004,51.61969],"type":"Point"}
}