{
  "type": "Feature",
  "properties": {
    "addr:full":"Donau 86 Leidschendam South Holland 2267 DV",
    "addr:housenumber":"86",
    "addr:postcode":"2267 dv",
    "addr:street":"Donau",
    "iso:country":"NL",
    "sg:address":"Donau 86",
    "sg:city":"Leidschendam",
    "sg:orig_category":"Zuivelproducten And Spijsoli?n Gh",
    "sg:phone":"+31 70 301 2760",
    "sg:postcode":"2267 DV",
    "sg:province":"South Holland",
    "wof:name":"Ravoska Kaas Import Bv",
    "wof:placetype":"venue"
},
  "geometry": {"coordinates":[4.40032,52.07888],"type":"Point"}
}