{
  "type": "Feature",
  "properties": {
    "addr:full":"Weerdingerstraat 252 Emmen Drenthe 7811 CL",
    "addr:housenumber":"252",
    "addr:postcode":"7811",
    "addr:street":"Weerdingerstraat",
    "iso:country":"NL",
    "sg:address":"Weerdingerstraat 252",
    "sg:city":"Emmen",
    "sg:orig_category":"Hypotheken And Hypotheekbanken",
    "sg:phone":"+31 591 650 660",
    "sg:postcode":"7811 CL",
    "sg:province":"Drenthe",
    "wof:name":"Hypotheek Visie Emmen",
    "wof:placetype":"venue"
},
  "geometry": {"coordinates":[6.894331,52.789436],"type":"Point"}
}