{
  "type": "Feature",
  "properties": {
    "iso:country":"NL",
    "sg:address":"Krommestraat 41",
    "sg:city":"Amersfoort",
    "sg:classifiers":[
        {
            "category":"Bars & Pubs",
            "type":"Food & Drink"
        }
    ],
    "sg:phone":"+31 33 462 2690",
    "sg:postcode":"3811 CB",
    "sg:province":"Utrecht",
    "wof:name":"Trenchtown",
    "wof:placetype":"venue"
},
  "geometry": {"coordinates":[5.388439,52.156548],"type":"Point"}
}