{
  "type": "Feature",
  "properties": {
    "addr:full":"Industriestr 61 Tubbergen Overijssel 7651 AN",
    "addr:housenumber":"61",
    "addr:postcode":"7651 an",
    "addr:street":"Industriestr",
    "iso:country":"NL",
    "sg:address":"Industriestr 61",
    "sg:city":"Tubbergen",
    "sg:orig_category":"Sanitaire Artikelen",
    "sg:phone":"+31 546 621 765",
    "sg:postcode":"7651 AN",
    "sg:province":"Overijssel",
    "sg:website":"http://www.laarmansanitair.nl",
    "wof:name":"Laarman Sanitair En Tegels",
    "wof:placetype":"venue"
},
  "geometry": {"coordinates":[6.78649,52.403175],"type":"Point"}
}