{
  "type": "Feature",
  "properties": {
    "addr:full":"Da Costastraat 25 Zoetermeer Zuid-Holland 2712 EV",
    "addr:housenumber":"25",
    "addr:street":"Da Costastraat",
    "iso:country":"NL",
    "sg:address":"Da Costastraat 25",
    "sg:city":"Zoetermeer",
    "sg:orig_category":"Goederenvervoer Over De Weg",
    "sg:phone":"+31 79 316 7651",
    "sg:postcode":"2712 EV",
    "sg:province":"Zuid-Holland",
    "wof:name":"Vof C.J. Paul Transport",
    "wof:placetype":"venue"
},
  "geometry": {"coordinates":[4.49259,52.050171],"type":"Point"}
}