{
  "type": "Feature",
  "properties": {
    "addr:full":"Julianapln 1 Akersloot Noord-Holland 1921 AZ",
    "addr:housenumber":"1",
    "addr:postcode":"1921 az",
    "addr:street":"Julianapln",
    "iso:country":"NL",
    "sg:address":"Julianapln 1",
    "sg:city":"Akersloot",
    "sg:orig_category":"Bloemen En Planten",
    "sg:phone":"+31 251 312 246",
    "sg:postcode":"1921 AZ",
    "sg:province":"Noord-Holland",
    "wof:name":"Verduin Vof, J G",
    "wof:placetype":"venue"
},
  "geometry": {"coordinates":[4.733658,52.558701],"type":"Point"}
}