{
  "type": "Feature",
  "properties": {
    "addr:full":"Liessentstr 8 Uden Noord-Brabant 5405 AG",
    "addr:housenumber":"8",
    "addr:postcode":"5405",
    "addr:street":"Liessentstr",
    "iso:country":"NL",
    "sg:address":"Liessentstr 8",
    "sg:city":"Uden",
    "sg:orig_category":"Non-Classified Establishments",
    "sg:phone":"+31 413 333 225",
    "sg:postcode":"5405 AG",
    "sg:province":"Noord-Brabant",
    "wof:name":"Cv",
    "wof:placetype":"venue"
},
  "geometry": {"coordinates":[5.648382,51.652596],"type":"Point"}
}