{
  "type": "Feature",
  "properties": {
    "iso:country":"NL",
    "sg:address":"Everlaan 6",
    "sg:city":"Wageningen",
    "sg:orig_category":"Bedrijfs- And Managementsconsultants",
    "sg:phone":"+31 317 413 458",
    "sg:postcode":"6705 DJ",
    "sg:province":"Gelderland",
    "wof:name":"Selhorst Financieel Management",
    "wof:placetype":"venue"
},
  "geometry": {"coordinates":[5.689919,51.986176],"type":"Point"}
}