{
  "type": "Feature",
  "properties": {
    "addr:full":"Louis Saalbornstraat 10 Hengelo Ov Overijssel 7558 ST",
    "addr:housenumber":"10",
    "addr:postcode":"7558 st",
    "addr:street":"Louis Saalbornstraat;Ov",
    "iso:country":"NL",
    "sg:address":"Louis Saalbornstraat 10",
    "sg:city":"Hengelo Ov",
    "sg:orig_category":"Fitnesscentra",
    "sg:phone":"+31 74 277 5628",
    "sg:postcode":"7558 ST",
    "sg:province":"Overijssel",
    "wof:name":"Club Sportief",
    "wof:placetype":"venue"
},
  "geometry": {"coordinates":[6.842221,52.284195],"type":"Point"}
}