{
  "type": "Feature",
  "properties": {
    "addr:full":"Scheen 5 Joure Friesland 8501 HA",
    "addr:housenumber":"5",
    "addr:postcode":"8501 ha",
    "addr:street":"Scheen",
    "iso:country":"NL",
    "sg:address":"Scheen 5",
    "sg:city":"Joure",
    "sg:orig_category":"Bloemen And Planten",
    "sg:phone":"+31 513 417 959",
    "sg:postcode":"8501 HA",
    "sg:province":"Friesland",
    "wof:name":"Memsh",
    "wof:placetype":"venue"
},
  "geometry": {"coordinates":[5.79961,52.963608],"type":"Point"}
}