{
  "type": "Feature",
  "properties": {
    "addr:full":"Ln V Beek En R 30 Zeist Utrecht 3701 AJ",
    "addr:housenumber":"30",
    "addr:postcode":"3701 aj",
    "addr:street":"Ln V Beek En R",
    "iso:country":"NL",
    "sg:address":"Ln V Beek En R 30",
    "sg:city":"Zeist",
    "sg:classifiers":[
        {
            "category":"Professional",
            "subcategory":"Accounting & Tax Preparation",
            "type":"Services"
        }
    ],
    "sg:phone":"+31 30 692 0074",
    "sg:postcode":"3701 AJ",
    "sg:province":"Utrecht",
    "sg:tags":[
        "accountant",
        "en",
        "-kantoren",
        "register-"
    ],
    "sg:website":"http://www.borrie.nl",
    "wof:name":"Borrie & Co",
    "wof:placetype":"venue"
},
  "geometry": {"coordinates":[5.24387,52.08548],"type":"Point"}
}