{
  "type": "Feature",
  "properties": {
    "addr:full":"Eibergsestr 23 Haaksbergen NL.08 7481 HE",
    "addr:housenumber":"23;nl.08",
    "addr:postcode":"7481 he",
    "addr:street":"Eibergsestr",
    "iso:country":"NL",
    "sg:address":"Eibergsestr 23",
    "sg:city":"Haaksbergen",
    "sg:orig_category":"Cafetaria'S",
    "sg:phone":"+31 53 572 2266",
    "sg:postcode":"7481 HE",
    "sg:province":"NL.08",
    "wof:name":"Menzing",
    "wof:placetype":"venue"
},
  "geometry": {"coordinates":[6.739048,52.152637],"type":"Point"}
}