{
  "type": "Feature",
  "properties": {
    "addr:full":"Sillenhoek 9 Leveroy Limburg 6091 PC",
    "addr:housenumber":"9",
    "addr:postcode":"6091 pc",
    "addr:street":"Sillenhoek",
    "iso:country":"NL",
    "sg:address":"Sillenhoek 9",
    "sg:city":"Leveroy",
    "sg:orig_category":"Fietsen En Bromfietsen",
    "sg:phone":"+31 495 651 662",
    "sg:postcode":"6091 PC",
    "sg:province":"Limburg",
    "wof:name":"Verwielen, W J",
    "wof:placetype":"venue"
},
  "geometry": {"coordinates":[5.843309,51.251495],"type":"Point"}
}