{
  "type": "Feature",
  "properties": {
    "addr:full":"Promenade 261 Zoetermeer Zuid-Holland 2711 BS",
    "addr:housenumber":"261",
    "addr:postcode":"2711 bs",
    "addr:street":"Promenade",
    "iso:country":"NL",
    "sg:address":"Promenade 261",
    "sg:city":"Zoetermeer",
    "sg:orig_category":"Discountwinkels",
    "sg:phone":"+31 79 346 0517",
    "sg:postcode":"2711 BS",
    "sg:province":"Zuid-Holland",
    "wof:name":"Zeeman Textielsupers",
    "wof:placetype":"venue"
},
  "geometry": {"coordinates":[4.492215,52.061489],"type":"Point"}
}