{
  "type": "Feature",
  "properties": {
    "addr:full":"Grotestr 15B Bedum Groningen 9781 HA",
    "addr:housenumber":"15b",
    "addr:postcode":"9781 ha",
    "addr:street":"Grotestr",
    "iso:country":"NL",
    "sg:address":"Grotestr 15B",
    "sg:city":"Bedum",
    "sg:orig_category":"Boeken En Tijdschriften",
    "sg:phone":"+31 50 301 0635",
    "sg:postcode":"9781 HA",
    "sg:province":"Groningen",
    "wof:name":"Bruna",
    "wof:placetype":"venue"
},
  "geometry": {"coordinates":[6.60456,53.301525],"type":"Point"}
}