{
  "type": "Feature",
  "properties": {
    "addr:full":"Lulofsstraat 55 Den Haag Zuid-Holland 2521 AL",
    "addr:housenumber":"55",
    "addr:postcode":"2521 al",
    "addr:street":"Lulofsstraat",
    "iso:country":"NL",
    "sg:address":"Lulofsstraat 55",
    "sg:city":"Den Haag",
    "sg:orig_category":"Maatschappelijk Werk",
    "sg:phone":"+31 70 305 3400",
    "sg:postcode":"2521 AL",
    "sg:province":"Zuid-Holland",
    "wof:name":"Centrum Vakopleiding Haaglanden",
    "wof:placetype":"venue"
},
  "geometry": {"coordinates":[4.317212,52.063614],"type":"Point"}
}