{
  "type": "Feature",
  "properties": {
    "addr:full":"Haarlemmerstraat 180 Leiden Zuid-Holland 2312 GH",
    "addr:housenumber":"180",
    "addr:postcode":"2312 gh",
    "addr:street":"Haarlemmerstraat",
    "iso:country":"NL",
    "sg:address":"Haarlemmerstraat 180",
    "sg:city":"Leiden",
    "sg:classifiers":[
        {
            "category":"Shopping",
            "subcategory":"Gifts & Souvenirs",
            "type":"Retail Goods"
        }
    ],
    "sg:phone":"+31 71 513 2744",
    "sg:postcode":"2312 GH",
    "sg:province":"Zuid-Holland",
    "sg:tags":[
        "geschenken"
    ],
    "wof:name":"Silver Bazar",
    "wof:placetype":"venue"
},
  "geometry": {"coordinates":[4.494394,52.160465],"type":"Point"}
}