{
  "type": "Feature",
  "properties": {
    "addr:full":"Tuinstr 40 Brummen Gelderland 6971 BJ",
    "addr:housenumber":"40",
    "addr:postcode":"6971 bj",
    "addr:street":"Tuinstr;Gelderland",
    "iso:country":"NL",
    "sg:address":"Tuinstr 40",
    "sg:city":"Brummen",
    "sg:orig_category":"Adviesbureaus Bouwkunde",
    "sg:phone":"+31 575 560 103",
    "sg:postcode":"6971 BJ",
    "sg:province":"Gelderland",
    "sg:website":"http://www.3dbouw.nl",
    "wof:name":"Oudendijk",
    "wof:placetype":"venue"
},
  "geometry": {"coordinates":[6.154425,52.086758],"type":"Point"}
}