{
  "type": "Feature",
  "properties": {
    "addr:full":"Rykswg Z 79 Rucphen Noord-Brabant 4715 TA",
    "addr:housenumber":"79",
    "addr:postcode":"4715 ta",
    "iso:country":"NL",
    "sg:address":"Rykswg Z 79",
    "sg:city":"Rucphen",
    "sg:orig_category":"Hoogwerkers",
    "sg:phone":"+31 165 344 811",
    "sg:postcode":"4715 TA",
    "sg:province":"Noord-Brabant",
    "wof:name":"Ladderspecialist, De",
    "wof:placetype":"venue"
},
  "geometry": {"coordinates":[4.558125,51.533405],"type":"Point"}
}