{
  "type": "Feature",
  "properties": {
    "addr:full":"Purmerpln 18 Amsterdam North Holland 1023 BD",
    "addr:housenumber":"18",
    "addr:postcode":"1023 bd",
    "addr:street":"Purmerpln",
    "iso:country":"NL",
    "sg:address":"Purmerpln 18",
    "sg:city":"Amsterdam",
    "sg:orig_category":"Fietsen En Bromfietsen",
    "sg:phone":"+31 20 637 5460",
    "sg:postcode":"1023 BD",
    "sg:province":"North Holland",
    "wof:name":"Allrounder, De",
    "wof:placetype":"venue"
},
  "geometry": {"coordinates":[4.943745,52.390743],"type":"Point"}
}