{
  "type": "Feature",
  "properties": {
    "addr:full":"Vogelaarstraat 11 Berkel En Rodenrijs South Holland 2651 CS",
    "addr:housenumber":"11",
    "addr:postcode":"2651 cs",
    "addr:street":"Vogelaarstraat",
    "iso:country":"NL",
    "sg:address":"Vogelaarstraat 11",
    "sg:city":"Berkel En Rodenrijs",
    "sg:orig_category":"Verzekeringen",
    "sg:phone":"+31 10 511 5829",
    "sg:postcode":"2651 CS",
    "sg:province":"South Holland",
    "wof:name":"Montes Kompaan Groep Bv",
    "wof:placetype":"venue"
},
  "geometry": {"coordinates":[4.47821,51.99609],"type":"Point"}
}