{
  "type": "Feature",
  "properties": {
    "addr:full":"Wymerswg 13 Loppersum Groningen 9919 BH",
    "addr:housenumber":"13",
    "addr:postcode":"9919 bh",
    "addr:street":"Wymerswg",
    "iso:country":"NL",
    "sg:address":"Wymerswg 13",
    "sg:city":"Loppersum",
    "sg:orig_category":"Politie",
    "sg:phone":"+31 900 8844",
    "sg:postcode":"9919 BH",
    "sg:province":"Groningen",
    "wof:name":"Politie",
    "wof:placetype":"venue"
},
  "geometry": {"coordinates":[6.739763,53.330742],"type":"Point"}
}