{
  "type": "Feature",
  "properties": {
    "iso:country":"NL",
    "sg:address":"Voeghoutenstr 23",
    "sg:city":"Klazienaveen",
    "sg:orig_category":"Scholen Voor Basisonderwijs",
    "sg:phone":"+31 591 390 225",
    "sg:postcode":"7891 LA",
    "sg:province":"Drenthe",
    "wof:name":"Spil Obs, De",
    "wof:placetype":"venue"
},
  "geometry": {"coordinates":[6.992973,52.722061],"type":"Point"}
}