{
  "type": "Feature",
  "properties": {
    "iso:country":"NL",
    "sg:address":"Adm De Ruyterwg 418",
    "sg:city":"Amsterdam",
    "sg:classifiers":[
        {
            "category":"Retail",
            "subcategory":"Auto Repair",
            "type":"Services"
        }
    ],
    "sg:phone":"+31 20 686 9193",
    "sg:postcode":"1055 ND",
    "sg:province":"Noord-Holland",
    "sg:tags":[
        "garage"
    ],
    "wof:name":"Ohm",
    "wof:placetype":"venue"
},
  "geometry": {"coordinates":[4.85337,52.380409],"type":"Point"}
}