{
  "type": "Feature",
  "properties": {
    "addr:full":"Randweg-Zuid 5 Budel Noord-Brabant 6021 PW",
    "addr:housenumber":"5",
    "addr:postcode":"6021 pw",
    "addr:street":"Randweg-Zuid",
    "iso:country":"NL",
    "sg:address":"Randweg-Zuid 5",
    "sg:city":"Budel",
    "sg:orig_category":"Gespecialiseerde Bouw",
    "sg:phone":"+31 495 431 000",
    "sg:postcode":"6021 PW",
    "sg:province":"Noord-Brabant",
    "wof:name":"Constructiebedrijf Lammers Bv",
    "wof:placetype":"venue"
},
  "geometry": {"coordinates":[5.59694,51.260372],"type":"Point"}
}