{
  "type": "Feature",
  "properties": {
    "addr:full":"Wilhelminastraat 19 Waalwijk Noord-Brabant 5141 HJ",
    "addr:housenumber":"19",
    "addr:postcode":"5141 hj",
    "addr:street":"Wilhelminastraat",
    "iso:country":"NL",
    "sg:address":"Wilhelminastraat 19",
    "sg:city":"Waalwijk",
    "sg:orig_category":"Werving And Selectie Van Tijdelijk Personeel And Uitzendkantoren",
    "sg:phone":"+31 416 336 707",
    "sg:postcode":"5141 HJ",
    "sg:province":"Noord-Brabant",
    "wof:name":"Accuraat Uitzendbureau",
    "wof:placetype":"venue"
},
  "geometry": {"coordinates":[5.0696721077,51.6902313232],"type":"Point"}
}