{
  "type": "Feature",
  "properties": {
    "addr:full":"De Clercqstraat 84 Amsterdam Noord-Holland 1052 NL",
    "addr:housenumber":"84",
    "addr:postcode":"1052 nl",
    "addr:street":"De Clercqstraat",
    "iso:country":"NL",
    "sg:address":"De Clercqstraat 84",
    "sg:city":"Amsterdam",
    "sg:orig_category":"Opticiens",
    "sg:phone":"+31 20 618 5054",
    "sg:postcode":"1052 NL",
    "sg:province":"Noord-Holland",
    "wof:name":"Ooglijn Optiek",
    "wof:placetype":"venue"
},
  "geometry": {"coordinates":[4.8677649498,52.3704986572],"type":"Point"}
}