{
  "type": "Feature",
  "properties": {
    "addr:full":"Spechtendonk 36 St Willebrord Noord-Brabant 4711 LM",
    "addr:housenumber":"36",
    "addr:postcode":"4711 lm",
    "addr:street":"Spechtendonk",
    "iso:country":"NL",
    "sg:address":"Spechtendonk 36",
    "sg:city":"St Willebrord",
    "sg:orig_category":"Autorijscholen",
    "sg:phone":"+31 165 386 080",
    "sg:postcode":"4711 LM",
    "sg:province":"Noord-Brabant",
    "wof:name":"Metro",
    "wof:placetype":"venue"
},
  "geometry": {"coordinates":[4.584985,51.540642],"type":"Point"}
}