{
  "type": "Feature",
  "properties": {
    "addr:full":"De Steenkamp 118 Voorthuizen Gelderland 3781 VV",
    "addr:housenumber":"118",
    "addr:postcode":"3781 vv",
    "addr:street":"De Steenkamp;Gelderland",
    "iso:country":"NL",
    "sg:address":"De Steenkamp 118",
    "sg:city":"Voorthuizen",
    "sg:orig_category":"Voegwerken",
    "sg:phone":"+31 342 490 547",
    "sg:postcode":"3781 VV",
    "sg:province":"Gelderland",
    "wof:name":"Pater",
    "wof:placetype":"venue"
},
  "geometry": {"coordinates":[5.620524,52.187443],"type":"Point"}
}