{
  "type": "Feature",
  "properties": {
    "addr:full":"Vischmarkt 36 Harderwyk Gelderland 3841 BG",
    "addr:housenumber":"36",
    "addr:postcode":"3841",
    "addr:street":"Vischmarkt;Gelderland",
    "iso:country":"NL",
    "sg:address":"Vischmarkt 36",
    "sg:city":"Harderwyk",
    "sg:orig_category":"Adviesbureaus Bedrijfsorganisatie",
    "sg:phone":"+31 341 417 685",
    "sg:postcode":"3841 BG",
    "sg:province":"Gelderland",
    "wof:name":"Versluis, C",
    "wof:placetype":"venue"
},
  "geometry": {"coordinates":[22.5543,43.988049],"type":"Point"}
}