{
  "type": "Feature",
  "properties": {
    "iso:country":"NL",
    "sg:address":"Scharmbarg 105",
    "sg:city":"Assen",
    "sg:orig_category":"Postkantoren",
    "sg:phone":"+31 592 343 325",
    "sg:postcode":"9407 EC",
    "sg:province":"Provincie Drenthe",
    "sg:website":"http://www.postkantoor.nl",
    "wof:name":"Postkantoor",
    "wof:placetype":"venue"
},
  "geometry": {"coordinates":[6.56137,53.017014],"type":"Point"}
}