{
  "type": "Feature",
  "properties": {
    "addr:full":"Westerwg 17 Oosterwolde Gld Gelderland 8097 PB",
    "addr:housenumber":"17",
    "addr:postcode":"8097 pb",
    "addr:street":"Westerwg",
    "iso:country":"NL",
    "sg:address":"Westerwg 17",
    "sg:city":"Oosterwolde Gld",
    "sg:orig_category":"Sanitaire Artikelen",
    "sg:phone":"+31 525 621 872",
    "sg:postcode":"8097 PB",
    "sg:province":"Gelderland",
    "wof:name":"Spronk Vof, Hessel",
    "wof:placetype":"venue"
},
  "geometry": {"coordinates":[5.877413,52.455357],"type":"Point"}
}