{
  "type": "Feature",
  "properties": {
    "iso:country":"NL",
    "sg:address":"Schoolstr 12",
    "sg:city":"Velp Gld",
    "sg:orig_category":"Peuterspeelzalen",
    "sg:phone":"+31 26 364 6640",
    "sg:postcode":"6882 NS",
    "sg:province":"Gelderland",
    "wof:name":"Duifje, 'T",
    "wof:placetype":"venue"
},
  "geometry": {"coordinates":[5.974708,51.992214],"type":"Point"}
}