{
  "type": "Feature",
  "properties": {
    "addr:full":"Boterdiep Oz 10 Bedum Groningen 9781 JA",
    "addr:housenumber":"10",
    "addr:postcode":"9781 ja",
    "addr:street":"Boterdiep Oz",
    "iso:country":"NL",
    "sg:address":"Boterdiep Oz 10",
    "sg:city":"Bedum",
    "sg:orig_category":"Verhuur",
    "sg:phone":"+31 50 301 5996",
    "sg:postcode":"9781 JA",
    "sg:province":"Groningen",
    "sg:website":"http://www.reisiger.com",
    "wof:name":"Reisiger Total Support",
    "wof:placetype":"venue"
},
  "geometry": {"coordinates":[6.596962,53.299999],"type":"Point"}
}