{
  "type": "Feature",
  "properties": {
    "addr:full":"Bas De Blokrede 35 Capelle A/D Ijssel South Holland 2901 CA",
    "addr:housenumber":"35;a / d",
    "addr:postcode":"2901 ca",
    "addr:street":"Bas De Blokrede;Ijssel South",
    "iso:country":"NL",
    "sg:address":"Bas De Blokrede 35",
    "sg:city":"Capelle A/D Ijssel",
    "sg:orig_category":"Koeriersdiensten",
    "sg:phone":"+31 10 442 5621",
    "sg:postcode":"2901 CA",
    "sg:province":"South Holland",
    "wof:name":"E.J.J. Hoogduijn Postbus Bezorg Service",
    "wof:placetype":"venue"
},
  "geometry": {"coordinates":[4.559056,51.914154],"type":"Point"}
}