{
  "type": "Feature",
  "properties": {
    "addr:full":"Hagedisweide 10 Nieuwegein Utrecht 3437 VR",
    "addr:housenumber":"10",
    "addr:postcode":"3437 vr",
    "addr:street":"Hagedisweide",
    "iso:country":"NL",
    "sg:address":"Hagedisweide 10",
    "sg:city":"Nieuwegein",
    "sg:orig_category":"Binnenhuisarchitecten",
    "sg:phone":"+31 30 603 3954",
    "sg:postcode":"3437 VR",
    "sg:province":"Utrecht",
    "wof:name":"Erik De Groot Binnen- En Buitenhuisarchi",
    "wof:placetype":"venue"
},
  "geometry": {"coordinates":[5.067356,52.04443],"type":"Point"}
}