{
  "type": "Feature",
  "properties": {
    "addr:full":"Oosterblokker 77 Oosterblokker Noord-Holland 1696 BC",
    "addr:housenumber":"77",
    "addr:postcode":"1696 bc",
    "addr:street":"Oosterblokker",
    "iso:country":"NL",
    "sg:address":"Oosterblokker 77",
    "sg:city":"Oosterblokker",
    "sg:classifiers":[
        {
            "category":"Retail",
            "subcategory":"Storage",
            "type":"Services"
        }
    ],
    "sg:phone":"+31 229 261 895",
    "sg:postcode":"1696 BC",
    "sg:province":"Noord-Holland",
    "sg:tags":[
        "opslag",
        "bewaring"
    ],
    "wof:name":"Vlaar Markerings Technieken",
    "wof:placetype":"venue"
},
  "geometry": {"coordinates":[5.1213598251,52.6699790955],"type":"Point"}
}