{
  "type": "Feature",
  "properties": {
    "iso:country":"NL",
    "sg:address":"Beijerlandselaan 50",
    "sg:city":"Rotterdam",
    "sg:classifiers":[
        {
            "category":"Fast Food",
            "type":"Food & Drink"
        }
    ],
    "sg:phone":"+31 10 432 2573",
    "sg:postcode":"3074 EK",
    "sg:province":"South Holland",
    "sg:tags":[
        "afhaal",
        "restaurant"
    ],
    "wof:name":"Netanya Shoarma",
    "wof:placetype":"venue"
},
  "geometry": {"coordinates":[4.511151,51.897915],"type":"Point"}
}