{
  "type": "Feature",
  "properties": {
    "addr:full":"Sinoutskerke 6 'S Heer Abtskerke Zeeland 4444 RT",
    "addr:housenumber":"6 '",
    "addr:postcode":"4444 rt",
    "addr:street":"Sinoutskerke;S Heer Abtskerke",
    "iso:country":"NL",
    "sg:address":"Sinoutskerke 6",
    "sg:city":"'S Heer Abtskerke",
    "sg:orig_category":"Onderhoud And Reparatie Kantoorapparatuur",
    "sg:phone":"+31 113 316 020",
    "sg:postcode":"4444 RT",
    "sg:province":"Zeeland",
    "wof:name":"Onsite",
    "wof:placetype":"venue"
},
  "geometry": {"coordinates":[3.864274,51.47337],"type":"Point"}
}