{
  "type": "Feature",
  "properties": {
    "addr:full":"Meteorenweg 127 Amsterdam North Holland 1033 GX",
    "addr:housenumber":"127",
    "addr:postcode":"1033 gx",
    "addr:street":"Meteorenweg",
    "iso:country":"NL",
    "sg:address":"Meteorenweg 127",
    "sg:city":"Amsterdam",
    "sg:orig_category":"Bloemen And Planten",
    "sg:phone":"+31 20 631 7873",
    "sg:postcode":"1033 GX",
    "sg:province":"North Holland",
    "wof:name":"Bloemsierkunst J.J. Eichelberg",
    "wof:placetype":"venue"
},
  "geometry": {"coordinates":[4.88693,52.41188],"type":"Point"}
}