{
  "type": "Feature",
  "properties": {
    "iso:country":"NL",
    "sg:address":"St.-Bonifaciusstraat 8",
    "sg:city":"Utrecht",
    "sg:classifiers":[
        {
            "category":"Education",
            "subcategory":"Preschool",
            "type":"Public Place"
        }
    ],
    "sg:phone":"+31 30 244 1393",
    "sg:postcode":"3553 SR",
    "sg:province":"Utrecht",
    "sg:tags":[
        "kleuteronderwijs",
        "basis-"
    ],
    "wof:name":"Ludgerschool",
    "wof:placetype":"venue"
},
  "geometry": {"coordinates":[5.087173,52.109596],"type":"Point"}
}