{
  "type": "Feature",
  "properties": {
    "addr:full":"Kortrijk 175 Amsterdam Noord-Holland 1066 TB",
    "addr:housenumber":"175",
    "addr:postcode":"1066 tb",
    "addr:street":"Kortrijk",
    "iso:country":"NL",
    "sg:address":"Kortrijk 175",
    "sg:city":"Amsterdam",
    "sg:orig_category":"Schilderwerk",
    "sg:phone":"+31 20 669 3928",
    "sg:postcode":"1066 TB",
    "sg:province":"Noord-Holland",
    "wof:name":"Post Schildersbedrijf",
    "wof:placetype":"venue"
},
  "geometry": {"coordinates":[4.802257,52.342407],"type":"Point"}
}