{
  "type": "Feature",
  "properties": {
    "iso:country":"NL",
    "sg:address":"Binnendijk 30",
    "sg:city":"Rottum Fr",
    "sg:orig_category":"Meubelzaken, Woning- And Keukeninrichting",
    "sg:phone":"+31 513 552 130",
    "sg:postcode":"8461 LE",
    "sg:province":"Friesland",
    "wof:name":"Grenalda",
    "wof:placetype":"venue"
},
  "geometry": {"coordinates":[5.890581,52.935574],"type":"Point"}
}