{
  "type": "Feature",
  "properties": {
    "addr:full":"Meijelsedijk 193 Ospel Limburg 6035 RJ",
    "addr:housenumber":"193",
    "addr:postcode":"6035 rj",
    "addr:street":"Meijelsedijk",
    "iso:country":"NL",
    "sg:address":"Meijelsedijk 193",
    "sg:city":"Ospel",
    "sg:orig_category":"Gespecialiseerde Bouw",
    "sg:phone":"+31 495 641 380",
    "sg:postcode":"6035 RJ",
    "sg:province":"Limburg",
    "wof:name":"E.T.H. Driessen",
    "wof:placetype":"venue"
},
  "geometry": {"coordinates":[-42.9212,-22.06716],"type":"Point"}
}