{
  "type": "Feature",
  "properties": {
    "iso:country":"NL",
    "sg:address":"Haagwg 423",
    "sg:city":"Breda",
    "sg:orig_category":"Kunstnijverheid",
    "sg:phone":"+31 76 520 5127",
    "sg:postcode":"4813 XD",
    "sg:province":"Noord-Brabant",
    "wof:name":"Annes",
    "wof:placetype":"venue"
},
  "geometry": {"coordinates":[4.740868,51.577744],"type":"Point"}
}