{
  "type": "Feature",
  "properties": {
    "addr:full":"Eksterstr 53 Badhoevedorp Noord-Holland 1171 TA",
    "addr:housenumber":"53",
    "addr:postcode":"1171 ta",
    "addr:street":"Eksterstr",
    "iso:country":"NL",
    "sg:address":"Eksterstr 53",
    "sg:city":"Badhoevedorp",
    "sg:orig_category":"Loodgieters",
    "sg:phone":"+31 20 659 4052",
    "sg:postcode":"1171 TA",
    "sg:province":"Noord-Holland",
    "wof:name":"Poppe, P",
    "wof:placetype":"venue"
},
  "geometry": {"coordinates":[4.777426,52.333504],"type":"Point"}
}