{
  "type": "Feature",
  "properties": {
    "addr:full":"Pr Hendrikstr 207 Hoek Van Holland Zuid-Holland 3151 AH",
    "addr:housenumber":"207",
    "addr:postcode":"3151 ah",
    "iso:country":"NL",
    "sg:address":"Pr Hendrikstr 207",
    "sg:city":"Hoek Van Holland",
    "sg:orig_category":"Bloemen En Planten",
    "sg:phone":"+31 174 382 869",
    "sg:postcode":"3151 AH",
    "sg:province":"Zuid-Holland",
    "wof:name":"Mos Jr, Dick",
    "wof:placetype":"venue"
},
  "geometry": {"coordinates":[4.131906,51.976677],"type":"Point"}
}