{
  "type": "Feature",
  "properties": {
    "addr:full":"Lovense Kanaaldk 47 Tilburg North Brabant 5013 BJ",
    "addr:housenumber":"47",
    "addr:postcode":"5013 bj",
    "iso:country":"NL",
    "sg:address":"Lovense Kanaaldk 47",
    "sg:city":"Tilburg",
    "sg:orig_category":"Verhuizingen",
    "sg:phone":"+31 13 542 5935",
    "sg:postcode":"5013 BJ",
    "sg:province":"North Brabant",
    "wof:name":"Horsten & De Bresser Bv",
    "wof:placetype":"venue"
},
  "geometry": {"coordinates":[5.09157,51.577271],"type":"Point"}
}