{
  "type": "Feature",
  "properties": {
    "addr:full":"Telexstr 7 Tilburg Noord-Brabant 5038 DJ",
    "addr:housenumber":"7",
    "addr:postcode":"5038 dj",
    "addr:street":"Telexstr",
    "iso:country":"NL",
    "sg:address":"Telexstr 7",
    "sg:city":"Tilburg",
    "sg:orig_category":"Wijnkoperijen En -Groothandel",
    "sg:phone":"+31 13 542 0210",
    "sg:postcode":"5038 DJ",
    "sg:province":"Noord-Brabant",
    "wof:name":"Lauwaars",
    "wof:placetype":"venue"
},
  "geometry": {"coordinates":[5.0856871605,51.5585861206],"type":"Point"}
}