{
  "type": "Feature",
  "properties": {
    "iso:country":"NL",
    "sg:address":"Zonegge 1916",
    "sg:city":"Zevenaar",
    "sg:orig_category":"Postzegels",
    "sg:phone":"+31 316 529 241",
    "sg:postcode":"6903 GV",
    "sg:province":"Gelderland",
    "wof:name":"Zegelservice",
    "wof:placetype":"venue"
},
  "geometry": {"coordinates":[6.06435,51.937454],"type":"Point"}
}