{
  "type": "Feature",
  "properties": {
    "addr:full":"Breestr 95-97 Beverwyk Noord-Holland 1941 EG",
    "addr:housenumber":"95-97",
    "addr:postcode":"1941 eg",
    "addr:street":"Beverwyk Noord-Holland",
    "iso:country":"NL",
    "sg:address":"Breestr 95-97",
    "sg:city":"Beverwyk",
    "sg:orig_category":"Makelaars En Adviseurs Onroerende Goederen",
    "sg:phone":"+31 251 229 225",
    "sg:postcode":"1941 EG",
    "sg:province":"Noord-Holland",
    "sg:website":"http://www.teer.nl",
    "wof:name":"Teer",
    "wof:placetype":"venue"
},
  "geometry": {"coordinates":[4.658516,52.481987],"type":"Point"}
}