{
  "type": "Feature",
  "properties": {
    "addr:full":"Kerkwg 37 Maarssen Utrecht 3603 CL",
    "addr:housenumber":"37",
    "addr:postcode":"3603",
    "addr:street":"Kerkwg",
    "iso:country":"NL",
    "sg:address":"Kerkwg 37",
    "sg:city":"Maarssen",
    "sg:orig_category":"Psychotherapeuten",
    "sg:phone":"+31 346 565 146",
    "sg:postcode":"3603 CL",
    "sg:province":"Utrecht",
    "wof:name":"Leeuwen-Treffers, E J Van",
    "wof:placetype":"venue"
},
  "geometry": {"coordinates":[5.039523,52.138119],"type":"Point"}
}