{
  "type": "Feature",
  "properties": {
    "addr:full":"Voorstraat 49 Vianen Zh South Holland 4132 AN",
    "addr:housenumber":"49",
    "addr:postcode":"zh;4132 an",
    "addr:street":"Voorstraat",
    "iso:country":"NL",
    "sg:address":"Voorstraat 49",
    "sg:city":"Vianen Zh",
    "sg:orig_category":"Kantoorartikelen",
    "sg:phone":"+31 347 372 090",
    "sg:postcode":"4132 AN",
    "sg:province":"South Holland",
    "wof:name":"Kantoorvakhandel Atlas",
    "wof:placetype":"venue"
},
  "geometry": {"coordinates":[5.0921468735,51.9942092896],"type":"Point"}
}