{
  "type": "Feature",
  "properties": {
    "addr:full":"B Pasternak Erf 216 Dordrecht Zuid-Holland 3315 BT",
    "addr:housenumber":"216",
    "addr:postcode":"3315 bt",
    "addr:street":"Pasternak Erf",
    "iso:country":"NL",
    "sg:address":"B Pasternak Erf 216",
    "sg:city":"Dordrecht",
    "sg:orig_category":"Autorijscholen",
    "sg:phone":"+31 78 630 0114",
    "sg:postcode":"3315 BT",
    "sg:province":"Zuid-Holland",
    "wof:name":"Linden, H A Van De",
    "wof:placetype":"venue"
},
  "geometry": {"coordinates":[4.7275,51.798882],"type":"Point"}
}