{
  "type": "Feature",
  "properties": {
    "iso:country":"NL",
    "sg:address":"Rivieraplein 5",
    "sg:city":"Haarlem",
    "sg:orig_category":"Kappers",
    "sg:phone":"+31 23 540 6054",
    "sg:postcode":"2037 AS",
    "sg:province":"North Holland",
    "wof:name":"Cosmo",
    "wof:placetype":"venue"
},
  "geometry": {"coordinates":[4.653195858,52.3573455811],"type":"Point"}
}