{
  "type": "Feature",
  "properties": {
    "addr:full":"Singel 303 Dordrecht Zuid-Holland 3311 HD",
    "addr:housenumber":"303",
    "addr:postcode":"3311 hd",
    "addr:street":"Singel",
    "iso:country":"NL",
    "sg:address":"Singel 303",
    "sg:city":"Dordrecht",
    "sg:orig_category":"Autoradio'S",
    "sg:phone":"+31 78 614 5000",
    "sg:postcode":"3311 HD",
    "sg:province":"Zuid-Holland",
    "sg:website":"http://www.chrishifi.nl",
    "wof:name":"Chris",
    "wof:placetype":"venue"
},
  "geometry": {"coordinates":[4.665632,51.809387],"type":"Point"}
}