{
  "type": "Feature",
  "properties": {
    "addr:full":"Provincialewg 80 Oosteind Noord-Brabant 4909 AK",
    "addr:housenumber":"80",
    "addr:postcode":"4909 ak",
    "addr:street":"Provincialewg",
    "iso:country":"NL",
    "sg:address":"Provincialewg 80",
    "sg:city":"Oosteind",
    "sg:orig_category":"Antiquiteiten",
    "sg:phone":"+31 162 426 545",
    "sg:postcode":"4909 AK",
    "sg:province":"Noord-Brabant",
    "wof:name":"Polder, A",
    "wof:placetype":"venue"
},
  "geometry": {"coordinates":[4.900161,51.644665],"type":"Point"}
}