{
  "type": "Feature",
  "properties": {
    "addr:full":"Grevelingenstr 16 Middelburg Zeeland 4335 XG",
    "addr:housenumber":"16",
    "addr:postcode":"4335 xg",
    "addr:street":"Grevelingenstr",
    "iso:country":"NL",
    "sg:address":"Grevelingenstr 16",
    "sg:city":"Middelburg",
    "sg:orig_category":"Loopbaanbegeleiding",
    "sg:phone":"+31 118 630 241",
    "sg:postcode":"4335 XG",
    "sg:province":"Zeeland",
    "wof:name":"Flexpool Bv",
    "wof:placetype":"venue"
},
  "geometry": {"coordinates":[3.597891,51.483421],"type":"Point"}
}