{
  "type": "Feature",
  "properties": {
    "addr:full":"Haarwg 1 Gorinchem South Holland 4205 NC",
    "addr:housenumber":"1",
    "addr:postcode":"4205 nc",
    "addr:street":"Haarwg",
    "iso:country":"NL",
    "sg:address":"Haarwg 1",
    "sg:city":"Gorinchem",
    "sg:orig_category":"Begrafenisverzorging",
    "sg:phone":"+31 183 633 500",
    "sg:postcode":"4205 NC",
    "sg:province":"South Holland",
    "wof:name":"Grote Haar, De",
    "wof:placetype":"venue"
},
  "geometry": {"coordinates":[4.972122,51.850048],"type":"Point"}
}