{
  "type": "Feature",
  "properties": {
    "addr:full":"Plantage Parklaan 12 Amsterdam Noord-Holland 1018 ST",
    "addr:housenumber":"12",
    "addr:postcode":"1018 st",
    "addr:street":"Plantage Parklaan",
    "iso:country":"NL",
    "sg:address":"Plantage Parklaan 12",
    "sg:city":"Amsterdam",
    "sg:orig_category":"Werving And Selectie Van Vast Personeel",
    "sg:phone":"+31 20 422 3050",
    "sg:postcode":"1018 ST",
    "sg:province":"Noord-Holland",
    "wof:name":"Slooter & Partners",
    "wof:placetype":"venue"
},
  "geometry": {"coordinates":[4.9094629288,52.3673629761],"type":"Point"}
}