{
  "type": "Feature",
  "properties": {
    "addr:full":"Voorstr 276 Dordrecht Zuid-Holland 3311 ET",
    "addr:housenumber":"276",
    "addr:postcode":"3311 et",
    "iso:country":"NL",
    "sg:address":"Voorstr 276",
    "sg:city":"Dordrecht",
    "sg:orig_category":"Kinderkleding",
    "sg:phone":"+31 78 631 1227",
    "sg:postcode":"3311 ET",
    "sg:province":"Zuid-Holland",
    "wof:name":"Mochic",
    "wof:placetype":"venue"
},
  "geometry": {"coordinates":[4.66645,51.814438],"type":"Point"}
}