{
  "type": "Feature",
  "properties": {
    "addr:full":"Molenstraat 2 Raamsdonk North Brabant 4944 AC",
    "addr:housenumber":"2",
    "addr:postcode":"4944 ac",
    "addr:street":"Molenstraat",
    "iso:country":"NL",
    "sg:address":"Molenstraat 2",
    "sg:city":"Raamsdonk",
    "sg:orig_category":"Discountwinkels",
    "sg:phone":"+31 162 512 427",
    "sg:postcode":"4944 AC",
    "sg:province":"North Brabant",
    "wof:name":"N.J. V.D. Plas - De Groot",
    "wof:placetype":"venue"
},
  "geometry": {"coordinates":[4.911772,51.688221],"type":"Point"}
}