{
  "type": "Feature",
  "properties": {
    "iso:country":"NL",
    "sg:address":"Meentdk 4",
    "sg:city":"Ede Gld",
    "sg:orig_category":"Loonbedrijven",
    "sg:phone":"+31 318 514 154",
    "sg:postcode":"6718 PA",
    "sg:province":"Utrecht",
    "wof:name":"Roekel Vof, H Van",
    "wof:placetype":"venue"
},
  "geometry": {"coordinates":[5.588337,52.014038],"type":"Point"}
}