{
  "type": "Feature",
  "properties": {
    "addr:full":"Mariastr 4B Apeldoorn Gelderland 7311 HL",
    "addr:housenumber":"4b",
    "addr:postcode":"7311 hl",
    "addr:street":"Mariastr;Gelderland",
    "iso:country":"NL",
    "sg:address":"Mariastr 4B",
    "sg:city":"Apeldoorn",
    "sg:orig_category":"Kinderkleding",
    "sg:phone":"+31 55 522 5249",
    "sg:postcode":"7311 HL",
    "sg:province":"Gelderland",
    "wof:name":"Chris + Tina",
    "wof:placetype":"venue"
},
  "geometry": {"coordinates":[5.962218,52.214325],"type":"Point"}
}