{
  "type": "Feature",
  "properties": {
    "addr:full":"Rithsestr 8 Breda Noord-Brabant 4813 GX",
    "addr:housenumber":"8",
    "addr:postcode":"4813 gx",
    "addr:street":"Rithsestr",
    "iso:country":"NL",
    "sg:address":"Rithsestr 8",
    "sg:city":"Breda",
    "sg:orig_category":"Artiesten/Gezelschappen",
    "sg:phone":"+31 76 514 7843",
    "sg:postcode":"4813 GX",
    "sg:province":"Noord-Brabant",
    "wof:name":"Hoosemans Vof, Cees",
    "wof:placetype":"venue"
},
  "geometry": {"coordinates":[4.742205,51.569141],"type":"Point"}
}