{
  "type": "Feature",
  "properties": {
    "addr:full":"Vrijheidslaan 45 Amsterdam North Holland 1079 KD",
    "addr:housenumber":"45",
    "addr:postcode":"1079 kd",
    "addr:street":"Vrijheidslaan",
    "iso:country":"NL",
    "sg:address":"Vrijheidslaan 45",
    "sg:city":"Amsterdam",
    "sg:orig_category":"Wasserettes And Stomerijen",
    "sg:phone":"+31 20 644 8637",
    "sg:postcode":"1079 KD",
    "sg:province":"North Holland",
    "wof:name":"Brandt Textielreiniging",
    "wof:placetype":"venue"
},
  "geometry": {"coordinates":[4.9081611633,52.3463134766],"type":"Point"}
}