{
  "type": "Feature",
  "properties": {
    "iso:country":"NL",
    "sg:address":"Uilenburg 12",
    "sg:city":"S Hertogenbosch",
    "sg:orig_category":"Galeries",
    "sg:phone":"+31 73 690 1379",
    "sg:postcode":"5211 EV",
    "sg:province":"Noord-Brabant",
    "wof:name":"Diestkant, D'N",
    "wof:placetype":"venue"
},
  "geometry": {"coordinates":[5.300078,51.688538],"type":"Point"}
}