{
  "type": "Feature",
  "properties": {
    "addr:full":"De Scheren 15 Lelystad Flevoland 8212 EA",
    "addr:housenumber":"15",
    "addr:postcode":"8212 ea",
    "addr:street":"De Scheren;Flevoland",
    "iso:country":"NL",
    "sg:address":"De Scheren 15",
    "sg:city":"Lelystad",
    "sg:orig_category":"Adviesbureaus Bedrijfsorganisatie",
    "sg:phone":"+31 320 236 695",
    "sg:postcode":"8212 EA",
    "sg:province":"Flevoland",
    "wof:name":"Insight-Out",
    "wof:placetype":"venue"
},
  "geometry": {"coordinates":[5.4974,52.506897],"type":"Point"}
}