{
  "type": "Feature",
  "properties": {
    "addr:full":"Jachthaven 1 Sloten Fr Friesland 8556 AM",
    "addr:housenumber":"1",
    "addr:postcode":"8556",
    "addr:street":"Jachthaven",
    "iso:country":"NL",
    "sg:address":"Jachthaven 1",
    "sg:city":"Sloten Fr",
    "sg:orig_category":"Pleziervaartuigen And Reparatie",
    "sg:phone":"+31 514 531 386",
    "sg:postcode":"8556 AM",
    "sg:province":"Friesland",
    "wof:name":"Jachtwerf Sloten",
    "wof:placetype":"venue"
},
  "geometry": {"coordinates":[5.643349,52.893131],"type":"Point"}
}