{
  "type": "Feature",
  "properties": {
    "addr:full":"Van Brakelstraat 6 Eindhoven Noord-Brabant 5612 GP",
    "addr:housenumber":"6",
    "addr:postcode":"5612 gp",
    "addr:street":"Van Brakelstraat",
    "iso:country":"NL",
    "sg:address":"Van Brakelstraat 6",
    "sg:city":"Eindhoven",
    "sg:orig_category":"Visspeciaalzaken",
    "sg:phone":"+31 40 243 6847",
    "sg:postcode":"5612 GP",
    "sg:province":"Noord-Brabant",
    "wof:name":"Viveens Vishandel",
    "wof:placetype":"venue"
},
  "geometry": {"coordinates":[5.470306,51.451534],"type":"Point"}
}