{
  "type": "Feature",
  "properties": {
    "addr:full":"Steenpad 5 Willemstad Nb Noord-Brabant 4797 SG",
    "addr:housenumber":"5",
    "addr:postcode":"4797 sg",
    "addr:street":"Steenpad",
    "iso:country":"NL",
    "sg:address":"Steenpad 5",
    "sg:city":"Willemstad Nb",
    "sg:orig_category":"Kunststoffen - Fabrieken En Groothandel",
    "sg:phone":"+31 168 473 651",
    "sg:postcode":"4797 SG",
    "sg:province":"Noord-Brabant",
    "wof:name":"Friatec Bv",
    "wof:placetype":"venue"
},
  "geometry": {"coordinates":[4.435297,51.677353],"type":"Point"}
}