{
  "type": "Feature",
  "properties": {
    "addr:full":"Rozenln 100 Schagen Noord-Holland 1741 ZD",
    "addr:housenumber":"100",
    "addr:postcode":"1741 zd",
    "addr:street":"Schagen",
    "iso:country":"NL",
    "sg:address":"Rozenln 100",
    "sg:city":"Schagen",
    "sg:orig_category":"Verhuur",
    "sg:phone":"+31 224 297 159",
    "sg:postcode":"1741 ZD",
    "sg:province":"Noord-Holland",
    "wof:name":"Meo, Fa",
    "wof:placetype":"venue"
},
  "geometry": {"coordinates":[4.797976,52.794193],"type":"Point"}
}