{
  "type": "Feature",
  "properties": {
    "addr:full":"Molenweg 2 Halle Arkansas 7025 EB",
    "addr:housenumber":"2",
    "addr:postcode":"7025 eb",
    "addr:street":"Molenweg",
    "iso:country":"NL",
    "sg:address":"Molenweg 2",
    "sg:city":"Halle",
    "sg:orig_category":"Begrafenisondernemers",
    "sg:phone":"+31 314 631 348",
    "sg:postcode":"7025 EB",
    "sg:province":"Arkansas",
    "wof:name":"Firma Menkhorst En Zoon",
    "wof:placetype":"venue"
},
  "geometry": {"coordinates":[-91.33019299999999,33.535301],"type":"Point"}
}