{
  "type": "Feature",
  "properties": {
    "addr:full":"W F Hildebrandstr 13 Garmerwolde Groningen 9798 PH",
    "addr:housenumber":"13",
    "addr:postcode":"9798",
    "addr:street":"W F Hildebrandstr",
    "iso:country":"NL",
    "sg:address":"W F Hildebrandstr 13",
    "sg:city":"Garmerwolde",
    "sg:orig_category":"Begrafenisverzorging",
    "sg:phone":"+31 50 541 6495",
    "sg:postcode":"9798 PH",
    "sg:province":"Groningen",
    "wof:name":"Garmerwolde",
    "wof:placetype":"venue"
},
  "geometry": {"coordinates":[6.648996,53.249222],"type":"Point"}
}