{
  "type": "Feature",
  "properties": {
    "addr:full":"Kasteellaan 30 Tegelen Limburg 5932 AG",
    "addr:housenumber":"30",
    "addr:postcode":"5932",
    "addr:street":"Kasteellaan",
    "iso:country":"NL",
    "sg:address":"Kasteellaan 30",
    "sg:city":"Tegelen",
    "sg:orig_category":"Goederenvervoer Over De Weg",
    "sg:phone":"+31 77 373 8481",
    "sg:postcode":"5932 AG",
    "sg:province":"Limburg",
    "wof:name":"M Wijnhoven Int",
    "wof:placetype":"venue"
},
  "geometry": {"coordinates":[6.141829,51.332771],"type":"Point"}
}