{
  "type": "Feature",
  "properties": {
    "addr:full":"Klaverpln 1 Veldhoven North Brabant 5503 PH",
    "addr:housenumber":"1",
    "addr:postcode":"5503",
    "addr:street":"Klaverpln",
    "iso:country":"NL",
    "sg:address":"Klaverpln 1",
    "sg:city":"Veldhoven",
    "sg:orig_category":"Grafische Bedrijven",
    "sg:phone":"+31 40 255 6300",
    "sg:postcode":"5503 PH",
    "sg:province":"North Brabant",
    "wof:name":"Kemper, J P M",
    "wof:placetype":"venue"
},
  "geometry": {"coordinates":[5.403141,51.414452],"type":"Point"}
}