{
  "type": "Feature",
  "properties": {
    "addr:full":"Kanaalstr 10 Ymuiden Noord-Holland 1975 BE",
    "addr:housenumber":"10",
    "addr:postcode":"1975",
    "addr:street":"Kanaalstr",
    "iso:country":"NL",
    "sg:address":"Kanaalstr 10",
    "sg:city":"Ymuiden",
    "sg:orig_category":"Plafonds",
    "sg:phone":"+31 255 527 744",
    "sg:postcode":"1975 BE",
    "sg:province":"Noord-Holland",
    "sg:website":"http://www.intergips.nl",
    "wof:name":"Intergips Afbouw",
    "wof:placetype":"venue"
},
  "geometry": {"coordinates":[4.5895,52.463039],"type":"Point"}
}