{
  "type": "Feature",
  "properties": {
    "addr:full":"Elststraat 2 Rosmalen Noord-Brabant 5242 AE",
    "addr:housenumber":"2",
    "addr:postcode":"5242 ae",
    "addr:street":"Elststraat",
    "iso:country":"NL",
    "sg:address":"Elststraat 2",
    "sg:city":"Rosmalen",
    "sg:orig_category":"Public Relationbureaus",
    "sg:phone":"+31 73 522 0504",
    "sg:postcode":"5242 AE",
    "sg:province":"Noord-Brabant",
    "wof:name":"Van Voorst Communicatie",
    "wof:placetype":"venue"
},
  "geometry": {"coordinates":[5.356358,51.706509],"type":"Point"}
}