{
  "type": "Feature",
  "properties": {
    "iso:country":"NL",
    "sg:address":"Weurden 31",
    "sg:city":"Winterswijk",
    "sg:orig_category":"Meubelzaken, Woning- And Keukeninrichting",
    "sg:phone":"+31 543 522 564",
    "sg:postcode":"7101 NH",
    "sg:province":"Gelderland",
    "wof:name":"Het Rotanhuis",
    "wof:placetype":"venue"
},
  "geometry": {"coordinates":[6.722383,51.968708],"type":"Point"}
}