{
  "type": "Feature",
  "properties": {
    "addr:full":"Hompertsweg 30 Landgraaf Limburg 6371 CX",
    "addr:housenumber":"30",
    "addr:postcode":"6371 cx",
    "addr:street":"Hompertsweg",
    "iso:country":"NL",
    "sg:address":"Hompertsweg 30",
    "sg:city":"Landgraaf",
    "sg:orig_category":"Verzekeringen",
    "sg:phone":"+31 45 532 2124",
    "sg:postcode":"6371 CX",
    "sg:province":"Limburg",
    "wof:name":"Judith Vintges Assurantien",
    "wof:placetype":"venue"
},
  "geometry": {"coordinates":[5.994858,50.903744],"type":"Point"}
}