{
  "type": "Feature",
  "properties": {
    "addr:full":"Rie Cramerstraat 15 Amstelveen North Holland 1183 CP",
    "addr:housenumber":"15",
    "addr:postcode":"1183 cp",
    "addr:street":"Rie Cramerstraat",
    "iso:country":"NL",
    "sg:address":"Rie Cramerstraat 15",
    "sg:city":"Amstelveen",
    "sg:orig_category":"Fotostudio'S And Fotografen",
    "sg:phone":"+31 20 640 0075",
    "sg:postcode":"1183 CP",
    "sg:province":"North Holland",
    "wof:name":"P. Van Riel",
    "wof:placetype":"venue"
},
  "geometry": {"coordinates":[4.875824,52.316315],"type":"Point"}
}