{
  "type": "Feature",
  "properties": {
    "addr:full":"Pastoorsdijk 24 Schalkhaar NL.08 7433 DK",
    "addr:housenumber":"24;nl.08",
    "addr:postcode":"7433 dk",
    "addr:street":"Pastoorsdijk",
    "iso:country":"NL",
    "sg:address":"Pastoorsdijk 24",
    "sg:city":"Schalkhaar",
    "sg:orig_category":"Meubelzaken, Woning- And Keukeninrichting",
    "sg:phone":"+31 570 622 737",
    "sg:postcode":"7433 DK",
    "sg:province":"NL.08",
    "wof:name":"Berghuis Kompleet Wonen",
    "wof:placetype":"venue"
},
  "geometry": {"coordinates":[6.192662,52.267677],"type":"Point"}
}