{
  "type": "Feature",
  "properties": {
    "addr:full":"Provincialeweg 7 Veldhoven Noord-Brabant 5503 HA",
    "addr:housenumber":"7",
    "addr:postcode":"5503 ha",
    "addr:street":"Provincialeweg",
    "iso:country":"NL",
    "sg:address":"Provincialeweg 7",
    "sg:city":"Veldhoven",
    "sg:orig_category":"Goederenvervoer Over De Weg",
    "sg:phone":"+31 40 253 9052",
    "sg:postcode":"5503 HA",
    "sg:province":"Noord-Brabant",
    "wof:name":"E Willems",
    "wof:placetype":"venue"
},
  "geometry": {"coordinates":[5.413003,51.411873],"type":"Point"}
}