{
  "type": "Feature",
  "properties": {
    "addr:full":"Industriewg 105 Rotterdam Zuid-Holland 3044 AS",
    "addr:housenumber":"105",
    "addr:postcode":"3044 as",
    "iso:country":"NL",
    "sg:address":"Industriewg 105",
    "sg:city":"Rotterdam",
    "sg:orig_category":"Pluimveebedrijven En -Handelaren",
    "sg:phone":"+31 10 262 3695",
    "sg:postcode":"3044 AS",
    "sg:province":"Zuid-Holland",
    "sg:website":"http://www.hilaltacukculuk.nl",
    "wof:name":"Hilal Tacukculuk",
    "wof:placetype":"venue"
},
  "geometry": {"coordinates":[4.419539,51.928909],"type":"Point"}
}