{
  "type": "Feature",
  "properties": {
    "addr:full":"Postbus 119 Wyk By Duurstede 3960 BC",
    "addr:housenumber":"119",
    "addr:postcode":"3960 bc",
    "addr:street":"Postbus",
    "iso:country":"NL",
    "sg:address":"Postbus 119",
    "sg:city":"Wyk By Duurstede",
    "sg:orig_category":"Verenigingen En Stichtingen",
    "sg:phone":"+31 343 576 626",
    "sg:postcode":"3960 BC",
    "sg:website":"http://www.vbn.borstvoeding.nl",
    "wof:name":"Borstvoeding Natuurlijk, Ver",
    "wof:placetype":"venue"
},
  "geometry": {"coordinates":[5.34525,51.97282],"type":"Point"}
}