{
  "type": "Feature",
  "properties": {
    "addr:full":"Boschdk 1045 Eindhoven Noord-Brabant 5626 AD",
    "addr:housenumber":"1045",
    "addr:postcode":"5626 ad",
    "iso:country":"NL",
    "sg:address":"Boschdk 1045",
    "sg:city":"Eindhoven",
    "sg:orig_category":"Honden- En Kattentrimsalons",
    "sg:phone":"+31 40 262 4759",
    "sg:postcode":"5626 AD",
    "sg:province":"Noord-Brabant",
    "wof:name":"Bibi'S",
    "wof:placetype":"venue"
},
  "geometry": {"coordinates":[5.43863,51.477451],"type":"Point"}
}