{
  "type": "Feature",
  "properties": {
    "addr:full":"Afrikalaan 83 Drunen Noord-Brabant 5152 MB",
    "addr:housenumber":"83",
    "addr:postcode":"5152 mb",
    "addr:street":"Afrikalaan",
    "iso:country":"NL",
    "sg:address":"Afrikalaan 83",
    "sg:city":"Drunen",
    "sg:orig_category":"Kappers",
    "sg:phone":"+31 416 372 807",
    "sg:postcode":"5152 MB",
    "sg:province":"Noord-Brabant",
    "wof:name":"Monique",
    "wof:placetype":"venue"
},
  "geometry": {"coordinates":[5.125697,51.684559],"type":"Point"}
}