{
  "type": "Feature",
  "properties": {
    "addr:full":"Grotestraat 46 Tubbergen Overijssel 7651 CJ",
    "addr:housenumber":"46",
    "addr:postcode":"7651 cj",
    "addr:street":"Grotestraat",
    "iso:country":"NL",
    "sg:address":"Grotestraat 46",
    "sg:city":"Tubbergen",
    "sg:orig_category":"Huishoudapparatuur, Televisies And Radio'S",
    "sg:phone":"+31 546 621 777",
    "sg:postcode":"7651 CJ",
    "sg:province":"Overijssel",
    "wof:name":"Technisch Centrum Rene Eppink",
    "wof:placetype":"venue"
},
  "geometry": {"coordinates":[6.781945,52.406769],"type":"Point"}
}