{
  "type": "Feature",
  "properties": {
    "iso:country":"NL",
    "sg:address":"Oostergoo 9",
    "sg:city":"Assen",
    "sg:orig_category":"Scholen Voor Basisonderwijs",
    "sg:phone":"+31 592 398 160",
    "sg:postcode":"9405 GZ",
    "sg:province":"Provincie Drenthe",
    "wof:name":"Baggelhuizen Openb",
    "wof:placetype":"venue"
},
  "geometry": {"coordinates":[6.532188,52.986137],"type":"Point"}
}