{
  "type": "Feature",
  "properties": {
    "iso:country":"NL",
    "sg:address":"Stationsweg 4",
    "sg:city":"Lelystad",
    "sg:orig_category":"Banken And Kredietinstellingen",
    "sg:phone":"+31 320 274 211",
    "sg:postcode":"8232 DN",
    "sg:province":"Flevoland",
    "wof:name":"Ing Bank",
    "wof:placetype":"venue"
},
  "geometry": {"coordinates":[5.472901,52.513321],"type":"Point"}
}