{
  "type": "Feature",
  "properties": {
    "addr:full":"Graaf Gerardstraat 2 Roermond Limburg 6041 HH",
    "addr:housenumber":"2",
    "addr:postcode":"6041 hh",
    "addr:street":"Graaf Gerardstraat",
    "iso:country":"NL",
    "sg:address":"Graaf Gerardstraat 2",
    "sg:city":"Roermond",
    "sg:orig_category":"Drogisterijen",
    "sg:phone":"+31 475 332 976",
    "sg:postcode":"6041 HH",
    "sg:province":"Limburg",
    "wof:name":"Hema",
    "wof:placetype":"venue"
},
  "geometry": {"coordinates":[5.989245,51.192783],"type":"Point"}
}