{
  "type": "Feature",
  "properties": {
    "iso:country":"NL",
    "sg:address":"Doornburg 42",
    "sg:city":"Hoofddorp",
    "sg:orig_category":"Autorijscholen",
    "sg:phone":"+31 23 555 3449",
    "sg:postcode":"2135 CZ",
    "sg:province":"Noord-Holland",
    "sg:website":"http://www.e-r-opleidingen.nl",
    "wof:name":"E & R",
    "wof:placetype":"venue"
},
  "geometry": {"coordinates":[4.656865,52.306602],"type":"Point"}
}