{
  "type": "Feature",
  "properties": {
    "iso:country":"NL",
    "sg:address":"Kanaalwg 38B",
    "sg:city":"Hoogeveen",
    "sg:orig_category":"Fitnesscentra",
    "sg:phone":"+31 528 272 674",
    "sg:postcode":"7902 LM",
    "sg:province":"Drenthe",
    "wof:name":"Fitinn",
    "wof:placetype":"venue"
},
  "geometry": {"coordinates":[6.489831,52.724998],"type":"Point"}
}