{
  "type": "Feature",
  "properties": {
    "addr:full":"Meeuwenln 38 Rotterdam South Holland 3055 CM",
    "addr:housenumber":"38",
    "addr:postcode":"3055 cm",
    "addr:street":"Meeuwenln",
    "iso:country":"NL",
    "sg:address":"Meeuwenln 38",
    "sg:city":"Rotterdam",
    "sg:orig_category":"Psychotherapeuten",
    "sg:phone":"+31 10 418 8363",
    "sg:postcode":"3055 CM",
    "sg:province":"South Holland",
    "wof:name":"Venne, J A M Van De",
    "wof:placetype":"venue"
},
  "geometry": {"coordinates":[4.502702,51.961864],"type":"Point"}
}