{
  "type": "Feature",
  "properties": {
    "addr:full":"Cor Zwakmanweg 6 Bergen Nh Noord-Holland 1861 NS",
    "addr:housenumber":"6",
    "addr:postcode":"1861 ns",
    "addr:street":"Zwakmanweg",
    "iso:country":"NL",
    "sg:address":"Cor Zwakmanweg 6",
    "sg:city":"Bergen Nh",
    "sg:orig_category":"Verzekeringen",
    "sg:phone":"+31 72 581 7771",
    "sg:postcode":"1861 NS",
    "sg:province":"Noord-Holland",
    "wof:name":"Schoenhof",
    "wof:placetype":"venue"
},
  "geometry": {"coordinates":[4.708761,52.662712],"type":"Point"}
}