{
  "type": "Feature",
  "properties": {
    "addr:full":"Bernhardln 30 Roermond Limburg 6042 HS",
    "addr:housenumber":"30",
    "addr:postcode":"6042 hs",
    "addr:street":"Bernhardln",
    "iso:country":"NL",
    "sg:address":"Bernhardln 30",
    "sg:city":"Roermond",
    "sg:orig_category":"Koeriersdiensten",
    "sg:phone":"+31 475 690 208",
    "sg:postcode":"6042 HS",
    "sg:province":"Limburg",
    "wof:name":"Dijcrotrans",
    "wof:placetype":"venue"
},
  "geometry": {"coordinates":[6.048408,51.19352],"type":"Point"}
}