{
  "type": "Feature",
  "properties": {
    "addr:full":"Zoeksestr 5A Schyf Noord-Brabant 4721 AC",
    "addr:housenumber":"5a",
    "addr:postcode":"4721 ac",
    "addr:street":"Zoeksestr",
    "iso:country":"NL",
    "sg:address":"Zoeksestr 5A",
    "sg:city":"Schyf",
    "sg:orig_category":"Verenigingsgebouwen",
    "sg:phone":"+31 165 348 677",
    "sg:postcode":"4721 AC",
    "sg:province":"Noord-Brabant",
    "wof:name":"Hoge Dries, D'R",
    "wof:placetype":"venue"
},
  "geometry": {"coordinates":[4.559291,51.496342],"type":"Point"}
}