{
  "type": "Feature",
  "properties": {
    "iso:country":"NL",
    "sg:address":"De Nieuwe Vaart 17",
    "sg:city":"Bussum",
    "sg:orig_category":"Fitnesscentra",
    "sg:phone":"+31 35 697 0902",
    "sg:postcode":"1401 GN",
    "sg:province":"Noord-Holland",
    "wof:name":"Fitness Promo Bv",
    "wof:placetype":"venue"
},
  "geometry": {"coordinates":[5.16324,52.284],"type":"Point"}
}