{
  "type": "Feature",
  "properties": {
    "iso:country":"NL",
    "sg:address":"Wilhelminapk 41",
    "sg:city":"Utrecht",
    "sg:orig_category":"Onroerende Goederen",
    "sg:phone":"+31 30 230 5060",
    "sg:postcode":"3581 NK",
    "sg:province":"Utrecht",
    "wof:name":"Niroc Vastgoedontwikkeling Bv",
    "wof:placetype":"venue"
},
  "geometry": {"coordinates":[5.138295,52.086807],"type":"Point"}
}