{
  "type": "Feature",
  "properties": {
    "addr:full":"Havenmeesterwg 307 Luchth Schiphol Noord-Holland 1118 CE",
    "addr:housenumber":"307",
    "addr:postcode":"1118 ce",
    "addr:street":"Luchth",
    "iso:country":"NL",
    "sg:address":"Havenmeesterwg 307",
    "sg:city":"Luchth Schiphol",
    "sg:orig_category":"Begrafenisverzorging",
    "sg:phone":"+31 20 316 4260",
    "sg:postcode":"1118 CE",
    "sg:province":"Noord-Holland",
    "wof:name":"Mortuarium Schiphol",
    "wof:placetype":"venue"
},
  "geometry": {"coordinates":[4.76049,52.306221],"type":"Point"}
}