{
  "type": "Feature",
  "properties": {
    "addr:full":"Noordermarkt 32 Amsterdam Noord-Holland 1015 MZ",
    "addr:housenumber":"32",
    "addr:postcode":"1015 mz",
    "addr:street":"Noordermarkt",
    "iso:country":"NL",
    "sg:address":"Noordermarkt 32",
    "sg:city":"Amsterdam",
    "sg:orig_category":"Modellenbureaus En Modellen Freelance",
    "sg:phone":"+31 20 624 8613",
    "sg:postcode":"1015 MZ",
    "sg:province":"Noord-Holland",
    "wof:name":"Second-Unit",
    "wof:placetype":"venue"
},
  "geometry": {"coordinates":[4.885962,52.379559],"type":"Point"}
}