{
  "type": "Feature",
  "properties": {
    "addr:full":"De Rede 58-60 Dronten NL. 8251 EX",
    "addr:housenumber":"58-60",
    "addr:postcode":"8251 ex",
    "addr:street":"De Rede;Nl.",
    "iso:country":"NL",
    "sg:address":"De Rede 58-60",
    "sg:city":"Dronten",
    "sg:orig_category":"Banken",
    "sg:phone":"+31 320 292 500",
    "sg:postcode":"8251 EX",
    "sg:province":"NL.",
    "sg:website":"http://www.rabobank.nl",
    "wof:name":"Rabobank",
    "wof:placetype":"venue"
},
  "geometry": {"coordinates":[5.717173,52.523983],"type":"Point"}
}