{
  "type": "Feature",
  "properties": {
    "addr:full":"Stephensonstr 15 Hoogeveen Drenthe 7903 AS",
    "addr:housenumber":"15",
    "addr:postcode":"7903 as",
    "addr:street":"Stephensonstr",
    "iso:country":"NL",
    "sg:address":"Stephensonstr 15",
    "sg:city":"Hoogeveen",
    "sg:orig_category":"Sanitaire Artikelen - Fabrieken En Groothandel",
    "sg:phone":"+31 528 274 849",
    "sg:postcode":"7903 AS",
    "sg:province":"Drenthe",
    "wof:name":"Vihamij Bv",
    "wof:placetype":"venue"
},
  "geometry": {"coordinates":[6.508675,52.72979],"type":"Point"}
}