{
  "type": "Feature",
  "properties": {
    "addr:full":"Hessenwg 131 De Bilt Utrecht 3731 JG",
    "addr:housenumber":"131",
    "addr:postcode":"3731 jg",
    "iso:country":"NL",
    "sg:address":"Hessenwg 131",
    "sg:city":"De Bilt",
    "sg:orig_category":"Fietsen En Bromfietsen",
    "sg:phone":"+31 30 220 0782",
    "sg:postcode":"3731 JG",
    "sg:province":"Utrecht",
    "wof:name":"Profile Rene De Fietsspecialist",
    "wof:placetype":"venue"
},
  "geometry": {"coordinates":[5.181007,52.109947],"type":"Point"}
}