{
  "type": "Feature",
  "properties": {
    "iso:country":"NL",
    "sg:address":"Eindhovenseweg 42",
    "sg:city":"Best",
    "sg:classifiers":[
        {
            "category":"Professional",
            "subcategory":"Accounting & Tax Preparation",
            "type":"Services"
        }
    ],
    "sg:phone":"+31 499 398 529",
    "sg:postcode":"5683 KJ",
    "sg:province":"Noord-Brabant",
    "sg:tags":[
        "accountant"
    ],
    "wof:name":"Accountants Ketelaars Rijnbeek & Partners",
    "wof:placetype":"venue"
},
  "geometry": {"coordinates":[-101.618134,31.224251],"type":"Point"}
}