{
  "type": "Feature",
  "properties": {
    "iso:country":"NL",
    "sg:address":"Ted Visserweg 15",
    "sg:city":"Maarn",
    "sg:orig_category":"Juridische Dienstverlening",
    "sg:phone":"+31 343 441 859",
    "sg:postcode":"3951 CC",
    "sg:province":"Utrecht",
    "wof:name":"Bv Notarispraktijk A. De Gier",
    "wof:placetype":"venue"
},
  "geometry": {"coordinates":[5.36911,52.067078],"type":"Point"}
}