{
  "type": "Feature",
  "properties": {
    "addr:full":"Gr Willemstr 202 Bovenkarspel Noord-Holland 1611 HP",
    "addr:housenumber":"202",
    "addr:postcode":"1611 hp",
    "iso:country":"NL",
    "sg:address":"Gr Willemstr 202",
    "sg:city":"Bovenkarspel",
    "sg:orig_category":"Adviesbureaus Bedrijfsorganisatie",
    "sg:phone":"+31 228 522 747",
    "sg:postcode":"1611 HP",
    "sg:province":"Noord-Holland",
    "wof:name":"Pvr",
    "wof:placetype":"venue"
},
  "geometry": {"coordinates":[5.237079,52.69194],"type":"Point"}
}