{
  "type": "Feature",
  "properties": {
    "addr:full":"Admiraal De Ruijterweg 226 Amsterdam Noord-Holland 1055 ML",
    "addr:housenumber":"226",
    "addr:postcode":"1055 ml",
    "addr:street":"Admiraal De Ruijterweg",
    "iso:country":"NL",
    "sg:address":"Admiraal De Ruijterweg 226",
    "sg:city":"Amsterdam",
    "sg:orig_category":"Politie",
    "sg:phone":"+31 900 8844",
    "sg:postcode":"1055 ML",
    "sg:province":"Noord-Holland",
    "wof:name":"Politie Amsterdam Amstelland Wijkbureau Adm De Ruy",
    "wof:placetype":"venue"
},
  "geometry": {"coordinates":[4.857949,52.377598],"type":"Point"}
}