{
  "type": "Feature",
  "properties": {
    "addr:full":"Neerstraat 52 Roermond Limburg 6041 KD",
    "addr:housenumber":"52",
    "addr:postcode":"6041 kd",
    "addr:street":"Neerstraat",
    "iso:country":"NL",
    "sg:address":"Neerstraat 52",
    "sg:city":"Roermond",
    "sg:orig_category":"Boekhandels",
    "sg:phone":"+31 475 317 645",
    "sg:postcode":"6041 KD",
    "sg:province":"Limburg",
    "wof:name":"Standaard Boekhandel Willems",
    "wof:placetype":"venue"
},
  "geometry": {"coordinates":[5.985454,51.193111],"type":"Point"}
}