{
  "type": "Feature",
  "properties": {
    "iso:country":"NL",
    "sg:address":"Waarlandsweg 16",
    "sg:city":"Waarland",
    "sg:orig_category":"Hoefdierhouderijen",
    "sg:phone":"+31 226 422 723",
    "sg:postcode":"1738 DL",
    "sg:province":"Noord-Holland",
    "wof:name":"Beukers Trainingstal",
    "wof:placetype":"venue"
},
  "geometry": {"coordinates":[4.812486,52.7379],"type":"Point"}
}