{
  "type": "Feature",
  "properties": {
    "addr:full":"Boswg 23 Berg En Dal Gelderland 6571 CD",
    "addr:housenumber":"23",
    "addr:postcode":"6571 cd",
    "addr:street":"Boswg",
    "iso:country":"NL",
    "sg:address":"Boswg 23",
    "sg:city":"Berg En Dal",
    "sg:orig_category":"Loopbaanbegeleiding",
    "sg:phone":"+31 24 324 5527",
    "sg:postcode":"6571 CD",
    "sg:province":"Gelderland",
    "wof:name":"Cremers, Consultancy",
    "wof:placetype":"venue"
},
  "geometry": {"coordinates":[5.918861,51.817162],"type":"Point"}
}