{
  "type": "Feature",
  "properties": {
    "addr:full":"Peulenplein 3 Hardinxveld Giessend Zuid-Holland 3371 XV",
    "addr:housenumber":"3;giessend",
    "addr:postcode":"3371 xv",
    "addr:street":"Peulenplein",
    "iso:country":"NL",
    "sg:address":"Peulenplein 3",
    "sg:city":"Hardinxveld Giessend",
    "sg:classifiers":[
        {
            "category":"Fast Food",
            "type":"Food & Drink"
        }
    ],
    "sg:phone":"+31 184 614 122",
    "sg:postcode":"3371 XV",
    "sg:province":"Zuid-Holland",
    "sg:tags":[
        "afhaal",
        "restaurant"
    ],
    "wof:name":"Mediterreanee",
    "wof:placetype":"venue"
},
  "geometry": {"coordinates":[4.826571,51.82402],"type":"Point"}
}