{
  "type": "Feature",
  "properties": {
    "addr:full":"Oostermeent Z 11 Huizen Noord-Holland 1274 ST",
    "addr:housenumber":"11",
    "addr:postcode":"1274 st",
    "iso:country":"NL",
    "sg:address":"Oostermeent Z 11",
    "sg:city":"Huizen",
    "sg:orig_category":"Kaas",
    "sg:phone":"+31 35 525 0235",
    "sg:postcode":"1274 ST",
    "sg:province":"Noord-Holland",
    "wof:name":"Kaasspecialist, De",
    "wof:placetype":"venue"
},
  "geometry": {"coordinates":[5.2641758919,52.2949638367],"type":"Point"}
}