{
  "type": "Feature",
  "properties": {
    "addr:full":"Noordzandstr 32 Yerseke Zeeland 4401 CG",
    "addr:housenumber":"32",
    "addr:postcode":"4401 cg",
    "addr:street":"Noordzandstr",
    "iso:country":"NL",
    "sg:address":"Noordzandstr 32",
    "sg:city":"Yerseke",
    "sg:orig_category":"Kinderkleding",
    "sg:phone":"+31 113 571 193",
    "sg:postcode":"4401 CG",
    "sg:province":"Zeeland",
    "sg:website":"http://www.am-boetiek.nl",
    "wof:name":"A&M",
    "wof:placetype":"venue"
},
  "geometry": {"coordinates":[4.050272,51.494244],"type":"Point"}
}