{
  "type": "Feature",
  "properties": {
    "iso:country":"NL",
    "sg:address":"Hoolhof 26",
    "sg:city":"Eersel",
    "sg:orig_category":"Hulpverlening Sociaal",
    "sg:phone":"+31 497 512 166",
    "sg:postcode":"5521 JR",
    "sg:province":"North Brabant",
    "wof:name":"Alg Hulpdienst Graag Gedaan",
    "wof:placetype":"venue"
},
  "geometry": {"coordinates":[5.319151,51.356258],"type":"Point"}
}