{
  "type": "Feature",
  "properties": {
    "addr:full":"Zwarteweg 50 Milsbeek Limburg 6596 MJ",
    "addr:housenumber":"50",
    "addr:postcode":"6596 mj",
    "addr:street":"Zwarteweg",
    "iso:country":"NL",
    "sg:address":"Zwarteweg 50",
    "sg:city":"Milsbeek",
    "sg:orig_category":"Diverse Dierenfokkers",
    "sg:phone":"+31 485 515 543",
    "sg:postcode":"6596 MJ",
    "sg:province":"Limburg",
    "wof:name":"Holthuysen Coppers Vof",
    "wof:placetype":"venue"
},
  "geometry": {"coordinates":[5.955827,51.734074],"type":"Point"}
}