{
  "type": "Feature",
  "properties": {
    "addr:full":"Nw Boezemstr 35 Rotterdam Zuid-Holland 3034 PH",
    "addr:housenumber":"35",
    "addr:postcode":"3034",
    "iso:country":"NL",
    "sg:address":"Nw Boezemstr 35",
    "sg:city":"Rotterdam",
    "sg:orig_category":"Woningstoffeerders",
    "sg:phone":"+31 6 55732575",
    "sg:postcode":"3034 PH",
    "sg:province":"Zuid-Holland",
    "wof:name":"Koring",
    "wof:placetype":"venue"
},
  "geometry": {"coordinates":[4.4980039597,51.9347496033],"type":"Point"}
}