{
  "type": "Feature",
  "properties": {
    "iso:country":"NL",
    "sg:address":"De Brink 3",
    "sg:city":"Arnhem",
    "sg:orig_category":"Schilders",
    "sg:phone":"+31 26 381 6630",
    "sg:postcode":"6842 AT",
    "sg:province":"Gelderland",
    "wof:name":"Baars, Gebr",
    "wof:placetype":"venue"
},
  "geometry": {"coordinates":[5.883819,51.957615],"type":"Point"}
}