{
  "type": "Feature",
  "properties": {
    "addr:full":"Ijweg 1097 Hoofddorp Noord-Holland 2133 MH",
    "addr:housenumber":"1097",
    "addr:postcode":"2133 mh",
    "addr:street":"Ijweg",
    "iso:country":"NL",
    "sg:address":"Ijweg 1097",
    "sg:city":"Hoofddorp",
    "sg:orig_category":"Verzekeringen",
    "sg:phone":"+31 23 563 5373",
    "sg:postcode":"2133 MH",
    "sg:province":"Noord-Holland",
    "wof:name":"Assurantiekantoor T.C. Schaay",
    "wof:placetype":"venue"
},
  "geometry": {"coordinates":[4.65739,52.308781],"type":"Point"}
}