{
  "type": "Feature",
  "properties": {
    "addr:full":"Romerostr 15 Gouda Zuid-Holland 2807 RK",
    "addr:housenumber":"15",
    "addr:postcode":"2807 rk",
    "addr:street":"Romerostr",
    "iso:country":"NL",
    "sg:address":"Romerostr 15",
    "sg:city":"Gouda",
    "sg:orig_category":"Plafonds",
    "sg:phone":"+31 182 514 969",
    "sg:postcode":"2807 RK",
    "sg:province":"Zuid-Holland",
    "wof:name":"Vane, Bert",
    "wof:placetype":"venue"
},
  "geometry": {"coordinates":[4.753891,52.006668],"type":"Point"}
}