{
  "type": "Feature",
  "properties": {
    "addr:full":"Hoogstraat 11 Heesch Noord-Brabant 5384 BJ",
    "addr:housenumber":"11",
    "addr:postcode":"5384 bj",
    "addr:street":"Hoogstraat",
    "iso:country":"NL",
    "sg:address":"Hoogstraat 11",
    "sg:city":"Heesch",
    "sg:orig_category":"Alternatieve Geneeskunde",
    "sg:phone":"+31 412 453 608",
    "sg:postcode":"5384 BJ",
    "sg:province":"Noord-Brabant",
    "wof:name":"Praktijk Voor Fysiotherapie",
    "wof:placetype":"venue"
},
  "geometry": {"coordinates":[5.533608,51.735012],"type":"Point"}
}