{
  "type": "Feature",
  "properties": {
    "addr:full":"Gr V Solmswg 113 S Hertogenbosch Noord-Brabant 5222 BS",
    "addr:housenumber":"113",
    "addr:postcode":"5222 bs",
    "addr:street":"Gr V Solmswg;S Hertogenbosch",
    "iso:country":"NL",
    "sg:address":"Gr V Solmswg 113",
    "sg:city":"S Hertogenbosch",
    "sg:orig_category":"Machinehandel",
    "sg:phone":"+31 73 623 0602",
    "sg:postcode":"5222 BS",
    "sg:province":"Noord-Brabant",
    "wof:name":"Benier Far East Bv",
    "wof:placetype":"venue"
},
  "geometry": {"coordinates":[5.2772,51.702991],"type":"Point"}
}