{
  "type": "Feature",
  "properties": {
    "addr:full":"De Kronkels 20 Bunschoten Spakenb Utrecht 3752 LM",
    "addr:housenumber":"20",
    "addr:postcode":"lm",
    "addr:street":"De Kronkels",
    "iso:country":"NL",
    "sg:address":"De Kronkels 20",
    "sg:city":"Bunschoten Spakenb",
    "sg:orig_category":"Zonweringen",
    "sg:phone":"+31 33 299 0292",
    "sg:postcode":"3752 LM",
    "sg:province":"Utrecht",
    "sg:website":"http://www.jpczonwering.nl",
    "wof:name":"Jpc Zonwering",
    "wof:placetype":"venue"
},
  "geometry": {"coordinates":[5.363644,52.228695],"type":"Point"}
}