{
  "type": "Feature",
  "properties": {
    "iso:country":"NL",
    "sg:address":"Henegouwerlaan 106",
    "sg:city":"Rotterdam",
    "sg:orig_category":"Technische Studies And Onderzoek",
    "sg:phone":"+31 10 413 4146",
    "sg:postcode":"3014 CG",
    "sg:province":"South Holland",
    "wof:name":"Interventor",
    "wof:placetype":"venue"
},
  "geometry": {"coordinates":[4.463727,51.919994],"type":"Point"}
}