{
  "type": "Feature",
  "properties": {
    "iso:country":"NL",
    "sg:address":"V Walbeeckstr 85 1Hg",
    "sg:city":"Amsterdam",
    "sg:orig_category":"Homeopathie",
    "sg:phone":"+31 20 618 2958",
    "sg:postcode":"1058 CM",
    "sg:province":"Noord-Holland",
    "wof:name":"Dam, C L",
    "wof:placetype":"venue"
},
  "geometry": {"coordinates":[4.85094,52.357658],"type":"Point"}
}