{
  "type": "Feature",
  "properties": {
    "addr:full":"Westkanaalwg 54 Ter Aar South Holland 2461 EG",
    "addr:housenumber":"54",
    "addr:postcode":"2461 eg",
    "addr:street":"Westkanaalwg",
    "iso:country":"NL",
    "sg:address":"Westkanaalwg 54",
    "sg:city":"Ter Aar",
    "sg:orig_category":"Fietsen En Bromfietsen",
    "sg:phone":"+31 172 603 030",
    "sg:postcode":"2461 EG",
    "sg:province":"South Holland",
    "wof:name":"Kroon, J W",
    "wof:placetype":"venue"
},
  "geometry": {"coordinates":[4.720765,52.180141],"type":"Point"}
}