{
  "type": "Feature",
  "properties": {
    "addr:full":"De Haecken 28 Bladel Noord-Brabant 5531 DD",
    "addr:housenumber":"28",
    "addr:postcode":"5531 dd",
    "addr:street":"De Haecken",
    "iso:country":"NL",
    "sg:address":"De Haecken 28",
    "sg:city":"Bladel",
    "sg:orig_category":"Montagebedrijven",
    "sg:phone":"+31 497 384 783",
    "sg:postcode":"5531 DD",
    "sg:province":"Noord-Brabant",
    "wof:name":"Shs",
    "wof:placetype":"venue"
},
  "geometry": {"coordinates":[5.224634,51.375195],"type":"Point"}
}