{
  "type": "Feature",
  "properties": {
    "addr:full":"T Hofke 153 Eindhoven Noord-Brabant 5641 AK",
    "addr:housenumber":"153",
    "addr:postcode":"5641 ak",
    "addr:street":"T Hofke",
    "iso:country":"NL",
    "sg:address":"T Hofke 153",
    "sg:city":"Eindhoven",
    "sg:orig_category":"Airconditioning And Ventilatie",
    "sg:phone":"+31 40 281 4176",
    "sg:postcode":"5641 AK",
    "sg:province":"Noord-Brabant",
    "wof:name":"De Win Koeltechniek",
    "wof:placetype":"venue"
},
  "geometry": {"coordinates":[5.517993,51.44825],"type":"Point"}
}