{
  "type": "Feature",
  "properties": {
    "iso:country":"NL",
    "sg:address":"Wildeveenstr 16B",
    "sg:city":"Rotterdam",
    "sg:orig_category":"Maquettes",
    "sg:phone":"+31 10 212 1774",
    "sg:postcode":"3061 GZ",
    "sg:province":"Zuid-Holland",
    "wof:name":"Tilburg, R Van",
    "wof:placetype":"venue"
},
  "geometry": {"coordinates":[4.508473,51.931416],"type":"Point"}
}