{
  "type": "Feature",
  "properties": {
    "addr:full":"Akerkhof 43A Groningen Groningen 9712 BC",
    "addr:housenumber":"43a",
    "addr:postcode":"9712 bc",
    "addr:street":"Akerkhof",
    "iso:country":"NL",
    "sg:address":"Akerkhof 43A",
    "sg:city":"Groningen",
    "sg:orig_category":"Marktonderzoekbureaus",
    "sg:phone":"+31 50 313 7176",
    "sg:postcode":"9712 BC",
    "sg:province":"Groningen",
    "wof:name":"Aha",
    "wof:placetype":"venue"
},
  "geometry": {"coordinates":[6.561643,53.21666],"type":"Point"}
}