{
  "type": "Feature",
  "properties": {
    "addr:full":"Schalmstraat 41 Eindhoven Noord-Brabant 5614 AC",
    "addr:housenumber":"41",
    "addr:postcode":"5614 ac",
    "addr:street":"Schalmstraat",
    "iso:country":"NL",
    "sg:address":"Schalmstraat 41",
    "sg:city":"Eindhoven",
    "sg:orig_category":"Wegen And Sportterreinen",
    "sg:phone":"+31 40 211 2627",
    "sg:postcode":"5614 AC",
    "sg:province":"Noord-Brabant",
    "wof:name":"I.A. Bouchee",
    "wof:placetype":"venue"
},
  "geometry": {"coordinates":[5.4912610054,51.4283638],"type":"Point"}
}