{
  "type": "Feature",
  "properties": {
    "addr:full":"Hofwg 43 Rotterdam Zuid-Holland 3046 NJ",
    "addr:housenumber":"43",
    "addr:postcode":"3046 nj",
    "addr:street":"Hofwg",
    "iso:country":"NL",
    "sg:address":"Hofwg 43",
    "sg:city":"Rotterdam",
    "sg:orig_category":"Kantoor- En Bedrijfsmeubelen - Fabrieken En Groothandel",
    "sg:phone":"+31 10 471 2011",
    "sg:postcode":"3046 NJ",
    "sg:province":"Zuid-Holland",
    "wof:name":"Gio Bv",
    "wof:placetype":"venue"
},
  "geometry": {"coordinates":[4.4099860191,51.9623794556],"type":"Point"}
}