{
  "type": "Feature",
  "properties": {
    "iso:country":"NL",
    "sg:address":"Baarnsewg 65",
    "sg:city":"Den Dolder",
    "sg:orig_category":"Schilders",
    "sg:phone":"+31 30 229 1693",
    "sg:postcode":"3734 CA",
    "sg:province":"Utrecht",
    "wof:name":"Vermeulen, J",
    "wof:placetype":"venue"
},
  "geometry": {"coordinates":[5.241888,52.137394],"type":"Point"}
}