{
  "type": "Feature",
  "properties": {
    "addr:full":"Kraaiersln 4 Noordwyk Zh South Holland 2204 AP",
    "addr:housenumber":"4;zh",
    "addr:postcode":"2204 ap",
    "addr:street":"Kraaiersln",
    "iso:country":"NL",
    "sg:address":"Kraaiersln 4",
    "sg:city":"Noordwyk Zh",
    "sg:orig_category":"Webdesign Bureaus",
    "sg:phone":"+31 6 16032586",
    "sg:postcode":"2204 AP",
    "sg:province":"South Holland",
    "sg:website":"http://www.dhogervorst.com",
    "wof:name":"Dhogervorst .Com",
    "wof:placetype":"venue"
},
  "geometry": {"coordinates":[4.4477000237,52.2342605591],"type":"Point"}
}