{
  "type": "Feature",
  "properties": {
    "addr:full":"Stationsweg 37 Emst Gelderland 8166 KA",
    "addr:housenumber":"37",
    "addr:postcode":"8166 ka",
    "addr:street":"Stationsweg;Gelderland",
    "iso:country":"NL",
    "sg:address":"Stationsweg 37",
    "sg:city":"Emst",
    "sg:orig_category":"Loodgieterswerk, Verwarming And Sanitaire Installaties",
    "sg:phone":"+31 578 662 196",
    "sg:postcode":"8166 KA",
    "sg:province":"Gelderland",
    "wof:name":"K. Keizer",
    "wof:placetype":"venue"
},
  "geometry": {"coordinates":[5.977997,52.314419],"type":"Point"}
}