{
  "type": "Feature",
  "properties": {
    "iso:country":"NL",
    "sg:address":"Achterzeedijk 57",
    "sg:city":"Barendrecht",
    "sg:orig_category":"Goederenvervoer Over De Weg",
    "sg:phone":"+31 180 621 925",
    "sg:postcode":"2992 SB",
    "sg:province":"South Holland",
    "wof:name":"Portfreight Bv",
    "wof:placetype":"venue"
},
  "geometry": {"coordinates":[4.529279,51.835228],"type":"Point"}
}