{
  "type": "Feature",
  "properties": {
    "iso:country":"NL",
    "sg:address":"Splytloffkamp 9",
    "sg:city":"Zwolle",
    "sg:orig_category":"Hulpverlening Sociaal",
    "sg:phone":"+31 38 460 2003",
    "sg:postcode":"8014 GK",
    "sg:province":"Overijssel",
    "sg:website":"http://www.stoppenmetgokken.nl",
    "wof:name":"Agog Zwolle",
    "wof:placetype":"venue"
},
  "geometry": {"coordinates":[6.116489,52.487141],"type":"Point"}
}