{
  "type": "Feature",
  "properties": {
    "addr:full":"Westerkd 22 Rotterdam Zuid-Holland 3016 CM",
    "addr:housenumber":"22",
    "addr:postcode":"3016 cm",
    "addr:street":"Westerkd",
    "iso:country":"NL",
    "sg:address":"Westerkd 22",
    "sg:city":"Rotterdam",
    "sg:orig_category":"Werving En Selectie",
    "sg:phone":"+31 10 436 3731",
    "sg:postcode":"3016 CM",
    "sg:province":"Zuid-Holland",
    "wof:name":"Centerpoint Bv",
    "wof:placetype":"venue"
},
  "geometry": {"coordinates":[4.4773402214,51.9112586975],"type":"Point"}
}