{
  "type": "Feature",
  "properties": {
    "addr:full":"Badhuisstraat 206 'S Gravenhage South Holland 2584 HN",
    "addr:housenumber":"206 '",
    "addr:postcode":"2584 hn",
    "addr:street":"Badhuisstraat",
    "iso:country":"NL",
    "sg:address":"Badhuisstraat 206",
    "sg:city":"'S Gravenhage",
    "sg:classifiers":[
        {
            "category":"Food & Beverages",
            "subcategory":"Fruits & Vegetables",
            "type":"Retail Goods"
        }
    ],
    "sg:phone":"+31 70 350 7591",
    "sg:postcode":"2584 HN",
    "sg:province":"South Holland",
    "sg:tags":[
        "groenten"
    ],
    "wof:name":"Van Binsbergen Groente- En Fruitspeciali",
    "wof:placetype":"venue"
},
  "geometry": {"coordinates":[4.279294,52.103611],"type":"Point"}
}