{
  "type": "Feature",
  "properties": {
    "addr:full":"Herenweg 165 Rijnsaterwoude Zuid-Holland 2465 AH",
    "addr:housenumber":"165",
    "addr:postcode":"2465 ah",
    "addr:street":"Herenweg",
    "iso:country":"NL",
    "sg:address":"Herenweg 165",
    "sg:city":"Rijnsaterwoude",
    "sg:orig_category":"Overheidsdiensten",
    "sg:phone":"+31 172 503 100",
    "sg:postcode":"2465 AH",
    "sg:province":"Zuid-Holland",
    "wof:name":"Gemeente Jacobswoude",
    "wof:placetype":"venue"
},
  "geometry": {"coordinates":[4.6722259521,52.1930465698],"type":"Point"}
}