{
  "type": "Feature",
  "properties": {
    "addr:full":"Westerstr 43-45 Enkhuizen North Holland 1601 AB",
    "addr:housenumber":"43-45",
    "addr:postcode":"1601 ab",
    "iso:country":"NL",
    "sg:address":"Westerstr 43-45",
    "sg:city":"Enkhuizen",
    "sg:orig_category":"Woninginrichting",
    "sg:phone":"+31 228 317 340",
    "sg:postcode":"1601 AB",
    "sg:province":"North Holland",
    "wof:name":"Tierlantijn Wonen",
    "wof:placetype":"venue"
},
  "geometry": {"coordinates":[5.29185009,52.7041778564],"type":"Point"}
}