{
  "type": "Feature",
  "properties": {
    "addr:full":"Dr De Boerstraat 53 Oostzaan Noord-Holland 1511 VG",
    "addr:housenumber":"53",
    "addr:postcode":"1511 vg",
    "addr:street":"Dr De Boerstraat",
    "iso:country":"NL",
    "sg:address":"Dr De Boerstraat 53",
    "sg:city":"Oostzaan",
    "sg:classifiers":[
        {
            "category":"Education",
            "subcategory":"Preschool",
            "type":"Public Place"
        }
    ],
    "sg:phone":"+31 75 684 1468",
    "sg:postcode":"1511 VG",
    "sg:province":"Noord-Holland",
    "sg:tags":[
        "kleuteronderwijs",
        "basis-"
    ],
    "wof:name":"Christelijke Basisschool De Korenaar",
    "wof:placetype":"venue"
},
  "geometry": {"coordinates":[4.878216,52.442055],"type":"Point"}
}