{
  "type": "Feature",
  "properties": {
    "addr:full":"Coryluslaan 15 Heerhugowaard Noord-Holland 1702 VM",
    "addr:housenumber":"15",
    "addr:postcode":"1702 vm",
    "addr:street":"Coryluslaan",
    "iso:country":"NL",
    "sg:address":"Coryluslaan 15",
    "sg:city":"Heerhugowaard",
    "sg:orig_category":"Boekhouders",
    "sg:phone":"+31 72 571 5631",
    "sg:postcode":"1702 VM",
    "sg:province":"Noord-Holland",
    "wof:name":"Administratiekantoor En Adviesbureau Fin",
    "wof:placetype":"venue"
},
  "geometry": {"coordinates":[4.835383,52.662304],"type":"Point"}
}