{
  "type": "Feature",
  "properties": {
    "iso:country":"NL",
    "sg:address":"Merelstr 26",
    "sg:city":"Varsseveld",
    "sg:orig_category":"Administratie- En Boekhoudkantoren",
    "sg:phone":"+31 315 242 050",
    "sg:postcode":"7051 XM",
    "sg:province":"Gelderland",
    "sg:website":"http://www.lobeek.club.tip.nl",
    "wof:name":"Lobeek",
    "wof:placetype":"venue"
},
  "geometry": {"coordinates":[6.455955,51.948441],"type":"Point"}
}