{
  "type": "Feature",
  "properties": {
    "addr:full":"M Louisestr 2 Joure Friesland 8501 LB",
    "addr:housenumber":"2",
    "addr:postcode":"8501 lb",
    "iso:country":"NL",
    "sg:address":"M Louisestr 2",
    "sg:city":"Joure",
    "sg:orig_category":"Poppen En Poppenhuismaterialen",
    "sg:phone":"+31 513 410 118",
    "sg:postcode":"8501 LB",
    "sg:province":"Friesland",
    "sg:website":"http://clix.to/poppenhuizen",
    "wof:name":"Yvonne",
    "wof:placetype":"venue"
},
  "geometry": {"coordinates":[5.803908,52.959557],"type":"Point"}
}