{
  "type": "Feature",
  "properties": {
    "iso:country":"NL",
    "sg:address":"Abeliadonk 13",
    "sg:city":"Roosendaal",
    "sg:orig_category":"Woninginrichting",
    "sg:phone":"+31 165 558 862",
    "sg:postcode":"4707 EZ",
    "sg:province":"North Brabant",
    "wof:name":"Jazo",
    "wof:placetype":"venue"
},
  "geometry": {"coordinates":[4.4737448692,51.5199966431],"type":"Point"}
}