{
  "type": "Feature",
  "properties": {
    "addr:full":"Van Heemstralaan 28 Fijnaart Noord-Brabant 4793 BJ",
    "addr:housenumber":"28",
    "addr:postcode":"4793 bj",
    "addr:street":"Van Heemstralaan",
    "iso:country":"NL",
    "sg:address":"Van Heemstralaan 28",
    "sg:city":"Fijnaart",
    "sg:orig_category":"Partycatering And -Organisatie",
    "sg:phone":"+31 168 463 009",
    "sg:postcode":"4793 BJ",
    "sg:province":"Noord-Brabant",
    "wof:name":"G Van Beem",
    "wof:placetype":"venue"
},
  "geometry": {"coordinates":[4.471323,51.641098],"type":"Point"}
}