{
  "type": "Feature",
  "properties": {
    "addr:full":"Amsterdamsewg 40 Ede Gld Gelderland 6712 GJ",
    "addr:housenumber":"40",
    "addr:postcode":"6712 gj",
    "addr:street":"Amsterdamsewg;Gld Gelderland",
    "iso:country":"NL",
    "sg:address":"Amsterdamsewg 40",
    "sg:city":"Ede Gld",
    "sg:orig_category":"Sportverenigingen En Ontspannings- Verenigingen",
    "sg:phone":"+31 318 693 140",
    "sg:postcode":"6712 GJ",
    "sg:province":"Gelderland",
    "wof:name":"Ebc 50 Bridgever",
    "wof:placetype":"venue"
},
  "geometry": {"coordinates":[5.664847,52.04961],"type":"Point"}
}