{
  "type": "Feature",
  "properties": {
    "addr:full":"Geenhovensedreef 121 Valkenswaard Noord-Brabant 5552 BC",
    "addr:housenumber":"121",
    "addr:postcode":"5552 bc",
    "addr:street":"Geenhovensedreef",
    "iso:country":"NL",
    "sg:address":"Geenhovensedreef 121",
    "sg:city":"Valkenswaard",
    "sg:orig_category":"Artsen - Huisartsen",
    "sg:phone":"+31 40 201 2649",
    "sg:postcode":"5552 BC",
    "sg:province":"Noord-Brabant",
    "wof:name":"Leeuw En M M Van Der Leeuw-Van Naamen, M J Van Der",
    "wof:placetype":"venue"
},
  "geometry": {"coordinates":[5.449141,51.358738],"type":"Point"}
}