{
  "type": "Feature",
  "properties": {
    "addr:full":"W Claesdochterln 1 Monnickendam Noord-Holland 1141 JA",
    "addr:housenumber":"1",
    "addr:postcode":"1141 ja",
    "addr:street":"W",
    "iso:country":"NL",
    "sg:address":"W Claesdochterln 1",
    "sg:city":"Monnickendam",
    "sg:orig_category":"Peuterspeelzalen",
    "sg:phone":"+31 299 654 721",
    "sg:postcode":"1141 JA",
    "sg:province":"Noord-Holland",
    "wof:name":"Pinokkio",
    "wof:placetype":"venue"
},
  "geometry": {"coordinates":[5.040389,52.452106],"type":"Point"}
}