{
  "type": "Feature",
  "properties": {
    "addr:full":"Witte De Withstraat 76/B Rotterdam South Holland 3012 BS",
    "addr:housenumber":"76 / b",
    "addr:postcode":"3012 bs",
    "addr:street":"Witte De Withstraat",
    "iso:country":"NL",
    "sg:address":"Witte De Withstraat 76/B",
    "sg:city":"Rotterdam",
    "sg:classifiers":[
        {
            "category":"Fast Food",
            "type":"Food & Drink"
        }
    ],
    "sg:phone":"+31 10 414 9614",
    "sg:postcode":"3012 BS",
    "sg:province":"South Holland",
    "sg:tags":[
        "afhaal",
        "restaurant"
    ],
    "wof:name":"Grillroom Shoarma Eilat",
    "wof:placetype":"venue"
},
  "geometry": {"coordinates":[4.476349,51.915321],"type":"Point"}
}