{
  "type": "Feature",
  "properties": {
    "iso:country":"NL",
    "sg:address":"Zandstr 30",
    "sg:city":"Gennep",
    "sg:orig_category":"Drogisterijen",
    "sg:phone":"+31 485 518 181",
    "sg:postcode":"6591 DD",
    "sg:province":"Limburg",
    "wof:name":"Kruidvat",
    "wof:placetype":"venue"
},
  "geometry": {"coordinates":[5.97119,51.699299],"type":"Point"}
}