{
  "type": "Feature",
  "properties": {
    "addr:full":"Gamerschestraat 32 Zaltbommel Gelderland 5301 AS",
    "addr:housenumber":"32",
    "addr:postcode":"5301 as",
    "addr:street":"Gamerschestraat;Gelderland",
    "iso:country":"NL",
    "sg:address":"Gamerschestraat 32",
    "sg:city":"Zaltbommel",
    "sg:orig_category":"Banken And Kredietinstellingen",
    "sg:phone":"+31 418 518 040",
    "sg:postcode":"5301 AS",
    "sg:province":"Gelderland",
    "wof:name":"Postkantoor",
    "wof:placetype":"venue"
},
  "geometry": {"coordinates":[5.245553,51.813187],"type":"Point"}
}