{
  "type": "Feature",
  "properties": {
    "addr:full":"Beemdstr 21 Eindhoven North Brabant 5653 MA",
    "addr:housenumber":"21",
    "addr:postcode":"5653 ma",
    "addr:street":"Beemdstr",
    "iso:country":"NL",
    "sg:address":"Beemdstr 21",
    "sg:city":"Eindhoven",
    "sg:orig_category":"Adviesbureaus Bouwkunde",
    "sg:phone":"+31 40 251 3400",
    "sg:postcode":"5653 MA",
    "sg:province":"North Brabant",
    "wof:name":"Facade Bv",
    "wof:placetype":"venue"
},
  "geometry": {"coordinates":[5.448622,51.42907],"type":"Point"}
}