{
  "type": "Feature",
  "properties": {
    "addr:full":"Esschenwg 16 Heerlen Limburg 6412 PV",
    "addr:housenumber":"16",
    "addr:postcode":"6412 pv",
    "addr:street":"Esschenwg",
    "iso:country":"NL",
    "sg:address":"Esschenwg 16",
    "sg:city":"Heerlen",
    "sg:orig_category":"Glazenwasserijen",
    "sg:phone":"+31 45 575 0841",
    "sg:postcode":"6412 PV",
    "sg:province":"Limburg",
    "wof:name":"Graven, Schoonmaakbedrijf Van",
    "wof:placetype":"venue"
},
  "geometry": {"coordinates":[5.933027,50.901134],"type":"Point"}
}