{
  "type": "Feature",
  "properties": {
    "addr:full":"Bolksbeekstraat 24 Utrecht Utrecht 3521 CS",
    "addr:housenumber":"24",
    "addr:postcode":"3521 cs",
    "addr:street":"Bolksbeekstraat",
    "iso:country":"NL",
    "sg:address":"Bolksbeekstraat 24",
    "sg:city":"Utrecht",
    "sg:orig_category":"Mode-, Juwelen- And Meubelontwerpers",
    "sg:phone":"+31 30 294 4199",
    "sg:postcode":"3521 CS",
    "sg:province":"Utrecht",
    "wof:name":"Van Luyk",
    "wof:placetype":"venue"
},
  "geometry": {"coordinates":[5.113626,52.078053],"type":"Point"}
}