{
  "type": "Feature",
  "properties": {
    "addr:full":"Hoogkana 9 A Ingen Gelderland 4031 MK",
    "addr:housenumber":"9 a",
    "addr:postcode":"4031",
    "addr:street":"Hoogkana;Gelderland",
    "iso:country":"NL",
    "sg:address":"Hoogkana 9 A",
    "sg:city":"Ingen",
    "sg:orig_category":"Loodgieterswerk, Verwarming And Sanitaire Installaties",
    "sg:phone":"+31 344 601 967",
    "sg:postcode":"4031 MK",
    "sg:province":"Gelderland",
    "wof:name":"A.M.D. Van Den Berg",
    "wof:placetype":"venue"
},
  "geometry": {"coordinates":[21.751289,41.60281],"type":"Point"}
}