{
  "type": "Feature",
  "properties": {
    "iso:country":"NL",
    "sg:address":"Hoogkana 9 A",
    "sg:city":"Ingen",
    "sg:orig_category":"Loodgieterswerk, Verwarming And Sanitaire Installaties",
    "sg:phone":"+31 344 601 967",
    "sg:postcode":"4031 MK",
    "sg:province":"Gelderland",
    "wof:name":"A.M.D. Van Den Berg",
    "wof:placetype":"venue"
},
  "geometry": {"coordinates":[21.751289,41.60281],"type":"Point"}
}