{
  "type": "Feature",
  "properties": {
    "addr:full":"Churchillln 48 Helmond Noord-Brabant 5705 BK",
    "addr:housenumber":"48",
    "addr:postcode":"5705 bk",
    "addr:street":"Churchillln",
    "iso:country":"NL",
    "sg:address":"Churchillln 48",
    "sg:city":"Helmond",
    "sg:orig_category":"Autowasserettes",
    "sg:phone":"+31 492 555 613",
    "sg:postcode":"5705 BK",
    "sg:province":"Noord-Brabant",
    "wof:name":"Autowaspark Helmond Bv",
    "wof:placetype":"venue"
},
  "geometry": {"coordinates":[5.658284,51.482239],"type":"Point"}
}