{
  "type": "Feature",
  "properties": {
    "addr:full":"Anjerlaan 40 Almkerk Noord-Brabant 4286 CR",
    "addr:housenumber":"40",
    "addr:postcode":"4286 cr",
    "addr:street":"Anjerlaan",
    "iso:country":"NL",
    "sg:address":"Anjerlaan 40",
    "sg:city":"Almkerk",
    "sg:classifiers":[
        {
            "category":"Fast Food",
            "type":"Food & Drink"
        }
    ],
    "sg:phone":"+31 183 403 569",
    "sg:postcode":"4286 CR",
    "sg:province":"Noord-Brabant",
    "sg:tags":[
        "afhaal",
        "restaurant"
    ],
    "wof:name":"J.P. V.D. Linden",
    "wof:placetype":"venue"
},
  "geometry": {"coordinates":[4.962599,51.773373],"type":"Point"}
}