{
  "type": "Feature",
  "properties": {
    "iso:country":"NL",
    "sg:address":"Kraaienweg 71",
    "sg:city":"Apeldoorn",
    "sg:orig_category":"Glaszetten",
    "sg:phone":"+31 55 533 2101",
    "sg:postcode":"7331 HW",
    "sg:province":"Gelderland",
    "wof:name":"Kleiboer'S Glasservice Bv",
    "wof:placetype":"venue"
},
  "geometry": {"coordinates":[5.967224,52.197762],"type":"Point"}
}