{
  "type": "Feature",
  "properties": {
    "iso:country":"NL",
    "sg:address":"Postbus 115",
    "sg:city":"Coevorden",
    "sg:orig_category":"Bliksembeveiliging",
    "sg:phone":"+31 524 514 340",
    "sg:postcode":"7740 AC",
    "sg:province":"Drenthe",
    "wof:name":"Bopa",
    "wof:placetype":"venue"
},
  "geometry": {"coordinates":[6.73891,52.6642],"type":"Point"}
}