{
  "type": "Feature",
  "properties": {
    "iso:country":"NL",
    "sg:address":"Weezenhof 5520",
    "sg:city":"Nijmegen",
    "sg:orig_category":"Kappers",
    "sg:phone":"+31 24 344 4948",
    "sg:postcode":"6536 EE",
    "sg:province":"Gelderland",
    "wof:name":"Gemmy'S Hair-Styling",
    "wof:placetype":"venue"
},
  "geometry": {"coordinates":[5.80768013,51.8018035889],"type":"Point"}
}