{
  "type": "Feature",
  "properties": {
    "iso:country":"NL",
    "sg:address":"Kerkln 57-59",
    "sg:city":"Sassenheim",
    "sg:orig_category":"Bloemen En Planten",
    "sg:phone":"+31 252 232 085",
    "sg:postcode":"2171 GB",
    "sg:province":"Zuid-Holland",
    "sg:website":"http://www.carolbloemiste.nl",
    "wof:name":"Carol",
    "wof:placetype":"venue"
},
  "geometry": {"coordinates":[4.519567,52.223663],"type":"Point"}
}