{
  "type": "Feature",
  "properties": {
    "addr:full":"Gildenwg 11 Maastricht Limburg 6214 SG",
    "addr:housenumber":"11",
    "addr:postcode":"6214 sg",
    "addr:street":"Gildenwg",
    "iso:country":"NL",
    "sg:address":"Gildenwg 11",
    "sg:city":"Maastricht",
    "sg:orig_category":"Koeriersdiensten",
    "sg:phone":"+31 6 54900091",
    "sg:postcode":"6214 SG",
    "sg:province":"Limburg",
    "wof:name":"Cruts Vof",
    "wof:placetype":"venue"
},
  "geometry": {"coordinates":[5.677544,50.844788],"type":"Point"}
}