{
  "type": "Feature",
  "properties": {
    "addr:full":"Begoniastr 29 Enkhuizen North Holland 1602 XG",
    "addr:housenumber":"29",
    "addr:postcode":"1602 xg",
    "addr:street":"Begoniastr",
    "iso:country":"NL",
    "sg:address":"Begoniastr 29",
    "sg:city":"Enkhuizen",
    "sg:orig_category":"Koeriersdiensten",
    "sg:phone":"+31 228 318 672",
    "sg:postcode":"1602 XG",
    "sg:province":"North Holland",
    "sg:website":"http://www.vandijkkoeriers.nl",
    "wof:name":"Dijk, Van",
    "wof:placetype":"venue"
},
  "geometry": {"coordinates":[5.286354,52.711941],"type":"Point"}
}