{
  "type": "Feature",
  "properties": {
    "addr:full":"Nieuwstr 57 Oldenzaal Overijssel 7572 BX",
    "addr:housenumber":"57",
    "addr:postcode":"7572 bx",
    "addr:street":"Nieuwstr",
    "iso:country":"NL",
    "sg:address":"Nieuwstr 57",
    "sg:city":"Oldenzaal",
    "sg:orig_category":"Woninginrichting",
    "sg:phone":"+31 541 534 701",
    "sg:postcode":"7572 BX",
    "sg:province":"Overijssel",
    "sg:website":"http://www.decorette.nl",
    "wof:name":"Decorette",
    "wof:placetype":"venue"
},
  "geometry": {"coordinates":[6.9266037941,52.3099250793],"type":"Point"}
}