{
  "type": "Feature",
  "properties": {
    "addr:full":"Van Der Helstlaan 6 Loosdrecht Noord-Holland 1231 AM",
    "addr:housenumber":"6",
    "addr:postcode":"1231",
    "addr:street":"Van Der Helstlaan",
    "iso:country":"NL",
    "sg:address":"Van Der Helstlaan 6",
    "sg:city":"Loosdrecht",
    "sg:classifiers":[
        {
            "category":"Professional",
            "subcategory":"Accounting & Tax Preparation",
            "type":"Services"
        }
    ],
    "sg:phone":"+31 35 582 7910",
    "sg:postcode":"1231 AM",
    "sg:province":"Noord-Holland",
    "sg:tags":[
        "accountant"
    ],
    "wof:name":"Administratiekantoor Swierstra",
    "wof:placetype":"venue"
},
  "geometry": {"coordinates":[5.134907,52.205856],"type":"Point"}
}