{
  "type": "Feature",
  "properties": {
    "iso:country":"NL",
    "sg:address":"Saroleastraat 1",
    "sg:city":"Heerlen",
    "sg:orig_category":"Juweliers",
    "sg:phone":"+31 45 571 5321",
    "sg:postcode":"6411 LR",
    "sg:province":"Limburg",
    "wof:name":"Bour Juwelier",
    "wof:placetype":"venue"
},
  "geometry": {"coordinates":[5.978353,50.887409],"type":"Point"}
}