{
  "type": "Feature",
  "properties": {
    "addr:full":"Spinozawg 451 Rotterdam South Holland 3076 EW",
    "addr:housenumber":"451",
    "addr:postcode":"3076 ew",
    "iso:country":"NL",
    "sg:address":"Spinozawg 451",
    "sg:city":"Rotterdam",
    "sg:orig_category":"Bejaarden - Verzorgingstehuizen",
    "sg:phone":"+31 10 291 8171",
    "sg:postcode":"3076 EW",
    "sg:province":"South Holland",
    "wof:name":"Koningshof, De",
    "wof:placetype":"venue"
},
  "geometry": {"coordinates":[4.511748,51.877529],"type":"Point"}
}