{
  "type": "Feature",
  "properties": {
    "addr:full":"Ooievaardreef 39 Moordrecht Zuid-Holland 2841 PA",
    "addr:housenumber":"39",
    "addr:postcode":"2841 pa",
    "addr:street":"Ooievaardreef",
    "iso:country":"NL",
    "sg:address":"Ooievaardreef 39",
    "sg:city":"Moordrecht",
    "sg:orig_category":"Bloemen En Planten",
    "sg:phone":"+31 182 373 665",
    "sg:postcode":"2841 PA",
    "sg:province":"Zuid-Holland",
    "wof:name":"Arte Verde",
    "wof:placetype":"venue"
},
  "geometry": {"coordinates":[4.665403,51.993065],"type":"Point"}
}