{
  "type": "Feature",
  "properties": {
    "addr:full":"Heinsbergerwg 12 Melick Limburg 6074 AD",
    "addr:housenumber":"12",
    "addr:postcode":"6074 ad",
    "addr:street":"Heinsbergerwg",
    "iso:country":"NL",
    "sg:address":"Heinsbergerwg 12",
    "sg:city":"Melick",
    "sg:orig_category":"Vakantieverblijven",
    "sg:phone":"+31 475 532 095",
    "sg:postcode":"6074 AD",
    "sg:province":"Limburg",
    "wof:name":"Roerdalhoeve, Hofstee De",
    "wof:placetype":"venue"
},
  "geometry": {"coordinates":[6.006048,51.153957],"type":"Point"}
}