{
  "type": "Feature",
  "properties": {
    "iso:country":"NL",
    "sg:address":"Hollewg 9",
    "sg:city":"Blaricum",
    "sg:orig_category":"Onroerende Goederen",
    "sg:phone":"+31 35 538 7003",
    "sg:postcode":"1261 BW",
    "sg:province":"North Holland",
    "wof:name":"Athos International Bv",
    "wof:placetype":"venue"
},
  "geometry": {"coordinates":[5.230807,52.274441],"type":"Point"}
}