{
  "type": "Feature",
  "properties": {
    "iso:country":"NL",
    "sg:address":"Oostzeedijk 316",
    "sg:city":"Rotterdam",
    "sg:orig_category":"Kappers",
    "sg:phone":"+31 10 411 3209",
    "sg:postcode":"3063 CC",
    "sg:province":"South Holland",
    "wof:name":"T Pakhuis",
    "wof:placetype":"venue"
},
  "geometry": {"coordinates":[4.5001840591,51.9226913452],"type":"Point"}
}