{
  "type": "Feature",
  "properties": {
    "iso:country":"NL",
    "sg:address":"Gorredijksterweg 19",
    "sg:city":"Jubbega",
    "sg:orig_category":"Diverse Artikelen Fab",
    "sg:phone":"+31 516 461 223",
    "sg:postcode":"8411 KA",
    "sg:province":"Friesland",
    "wof:name":"A. Bergsma",
    "wof:placetype":"venue"
},
  "geometry": {"coordinates":[6.0981,52.983646],"type":"Point"}
}