{
  "type": "Feature",
  "properties": {
    "iso:country":"NL",
    "sg:address":"Parkln 6",
    "sg:city":"Sittard",
    "sg:orig_category":"Banken",
    "sg:phone":"+31 46 420 8300",
    "sg:postcode":"6131 KG",
    "sg:province":"Limburg",
    "wof:name":"Fortis",
    "wof:placetype":"venue"
},
  "geometry": {"coordinates":[5.8678,50.996353],"type":"Point"}
}