{
  "type": "Feature",
  "properties": {
    "addr:full":"Heugemerwg 95 Maastricht Limburg 6221 GH",
    "addr:housenumber":"95",
    "addr:postcode":"6221 gh",
    "addr:street":"Heugemerwg",
    "iso:country":"NL",
    "sg:address":"Heugemerwg 95",
    "sg:city":"Maastricht",
    "sg:orig_category":"Architecten En Architectenbureaus",
    "sg:phone":"+31 43 325 2971",
    "sg:postcode":"6221 GH",
    "sg:province":"Limburg",
    "wof:name":"Gerards",
    "wof:placetype":"venue"
},
  "geometry": {"coordinates":[5.704413,50.842857],"type":"Point"}
}