{
  "type": "Feature",
  "properties": {
    "addr:full":"Past Siebenstr 9 St Odilienberg Limburg 6077 AJ",
    "addr:housenumber":"9",
    "addr:postcode":"6077 aj",
    "addr:street":"St Odilienberg Limburg",
    "iso:country":"NL",
    "sg:address":"Past Siebenstr 9",
    "sg:city":"St Odilienberg",
    "sg:orig_category":"Onderhoudswerken",
    "sg:phone":"+31 475 531 419",
    "sg:postcode":"6077 AJ",
    "sg:province":"Limburg",
    "wof:name":"Hilkens",
    "wof:placetype":"venue"
},
  "geometry": {"coordinates":[6.001952,51.146965],"type":"Point"}
}