{
  "type": "Feature",
  "properties": {
    "iso:country":"NL",
    "sg:address":"Thedingecamp 2",
    "sg:city":"Emmen",
    "sg:orig_category":"Ingenieursbureaus",
    "sg:phone":"+31 591 671 313",
    "sg:postcode":"7824 GV",
    "sg:province":"Provincie Drenthe",
    "sg:website":"http://www.goudstikker.nl",
    "wof:name":"Goudstikker-De Vries Emmen Bv",
    "wof:placetype":"venue"
},
  "geometry": {"coordinates":[6.927144,52.780815],"type":"Point"}
}