{
  "type": "Feature",
  "properties": {
    "addr:full":"Oosteinde 243 Voorburg Zuid-Holland 2271 EG",
    "addr:housenumber":"243",
    "addr:postcode":"2271 eg",
    "addr:street":"Oosteinde",
    "iso:country":"NL",
    "sg:address":"Oosteinde 243",
    "sg:city":"Voorburg",
    "sg:classifiers":[
        {
            "category":"Retail",
            "subcategory":"Auto Repair",
            "type":"Services"
        }
    ],
    "sg:phone":"+31 70 386 2841",
    "sg:postcode":"2271 EG",
    "sg:province":"Zuid-Holland",
    "sg:tags":[
        "garage"
    ],
    "wof:name":"Vronesteyn",
    "wof:placetype":"venue"
},
  "geometry": {"coordinates":[4.381193,52.077663],"type":"Point"}
}