{
  "type": "Feature",
  "properties": {
    "addr:full":"Rigawg 9 Groningen Groningen 9723 TE",
    "addr:housenumber":"9",
    "addr:postcode":"9723 te",
    "addr:street":"Rigawg",
    "iso:country":"NL",
    "sg:address":"Rigawg 9",
    "sg:city":"Groningen",
    "sg:orig_category":"Verf En Lak - Fabrieken En Groothandel",
    "sg:phone":"+31 50 549 0049",
    "sg:postcode":"9723 TE",
    "sg:province":"Groningen",
    "wof:name":"Bijholt Bv",
    "wof:placetype":"venue"
},
  "geometry": {"coordinates":[6.608522,53.210606],"type":"Point"}
}