{
  "type": "Feature",
  "properties": {
    "iso:country":"NL",
    "sg:address":"Phoenixstraat 28",
    "sg:city":"2601 Cx",
    "sg:classifiers":[
        {
            "category":"Banks & Credit Unions",
            "subcategory":"Bank",
            "type":"Services"
        }
    ],
    "sg:phone":"+31 15 215 3500",
    "sg:postcode":"DELF T",
    "wof:name":"Ing Bank Nv",
    "wof:placetype":"venue"
},
  "geometry": {"coordinates":[105.629272,-10.49582],"type":"Point"}
}