{
  "type": "Feature",
  "properties": {
    "addr:full":"Luchthavenweg 16 Den Helder Noord-Holland 1786 PP",
    "addr:housenumber":"16",
    "addr:postcode":"1786 pp",
    "addr:street":"Luchthavenweg",
    "iso:country":"NL",
    "sg:address":"Luchthavenweg 16",
    "sg:city":"Den Helder",
    "sg:orig_category":"Olie- And Gaswinning",
    "sg:phone":"+31 223 670 111",
    "sg:postcode":"1786 PP",
    "sg:province":"Noord-Holland",
    "wof:name":"Totalfinaelf E&P Nederland Bv",
    "wof:placetype":"venue"
},
  "geometry": {"coordinates":[4.785365,52.920212],"type":"Point"}
}