{
  "type": "Feature",
  "properties": {
    "addr:full":"Verdihof 30 Alphen A/D Rijn South Holland 2402 VC",
    "addr:housenumber":"30",
    "addr:postcode":"2402 vc",
    "addr:street":"Verdihof",
    "iso:country":"NL",
    "sg:address":"Verdihof 30",
    "sg:city":"Alphen A/D Rijn",
    "sg:orig_category":"Chemische Producten Gh",
    "sg:phone":"+31 172 432 729",
    "sg:postcode":"2402 VC",
    "sg:province":"South Holland",
    "wof:name":"H.A. Brugman",
    "wof:placetype":"venue"
},
  "geometry": {"coordinates":[4.667725,52.145638],"type":"Point"}
}