{
  "type": "Feature",
  "properties": {
    "iso:country":"NL",
    "sg:address":"Elzenweg 29",
    "sg:city":"Waalwijk",
    "sg:orig_category":"Koffers And Tassen Fab",
    "sg:phone":"+31 416 332 798",
    "sg:postcode":"5144 MB",
    "sg:province":"North Brabant",
    "wof:name":"H.J. De Rooy Lederwaren Bv",
    "wof:placetype":"venue"
},
  "geometry": {"coordinates":[5.05397,51.682362],"type":"Point"}
}