{
  "type": "Feature",
  "properties": {
    "iso:country":"NL",
    "sg:address":"Gr V Berghstr 6",
    "sg:city":"Millingen Ad Ryn",
    "sg:orig_category":"Fotoreportages",
    "sg:phone":"+31 481 452 598",
    "sg:postcode":"6566 BE",
    "sg:province":"Gelderland",
    "wof:name":"Gijs Kroes",
    "wof:placetype":"venue"
},
  "geometry": {"coordinates":[6.046855,51.864063],"type":"Point"}
}