{
  "type": "Feature",
  "properties": {
    "iso:country":"NL",
    "sg:address":"Industriestr 11",
    "sg:city":"Noord Scharwoude",
    "sg:orig_category":"Koel- En Vrieshuizen",
    "sg:phone":"+31 226 312 519",
    "sg:postcode":"1723 LE",
    "sg:province":"Noord-Holland",
    "wof:name":"Skb Vof",
    "wof:placetype":"venue"
},
  "geometry": {"coordinates":[4.81024,52.698441],"type":"Point"}
}