{
  "type": "Feature",
  "properties": {
    "addr:full":"Koolzaadhof 148 Biddinghuizen Flevoland 8256 AH",
    "addr:housenumber":"148",
    "addr:postcode":"8256 ah",
    "addr:street":"Koolzaadhof;Flevoland",
    "iso:country":"NL",
    "sg:address":"Koolzaadhof 148",
    "sg:city":"Biddinghuizen",
    "sg:orig_category":"Verzekeringen - Verzekeringskantoren",
    "sg:phone":"+31 321 313 168",
    "sg:postcode":"8256 AH",
    "sg:province":"Flevoland",
    "wof:name":"Nijdam, J",
    "wof:placetype":"venue"
},
  "geometry": {"coordinates":[5.694632,52.452473],"type":"Point"}
}