{
  "type": "Feature",
  "properties": {
    "iso:country":"NL",
    "sg:address":"Borneostr 23",
    "sg:city":"Heemstede",
    "sg:orig_category":"Vaatwasmachines",
    "sg:phone":"+31 23 547 2067",
    "sg:postcode":"2103 TN",
    "sg:province":"Noord-Holland",
    "wof:name":"Gerard Dulk Technische Dienst",
    "wof:placetype":"venue"
},
  "geometry": {"coordinates":[4.627536,52.342693],"type":"Point"}
}