{
  "type": "Feature",
  "properties": {
    "addr:full":"Lijnbaanweg 62 Noordwijk Zh Zuid-Holland 2201 LG",
    "addr:housenumber":"62",
    "addr:postcode":"2201 lg",
    "addr:street":"Lijnbaanweg",
    "iso:country":"NL",
    "sg:address":"Lijnbaanweg 62",
    "sg:city":"Noordwijk Zh",
    "sg:orig_category":"Bloemen And Planten Gh",
    "sg:phone":"+31 71 361 9031",
    "sg:postcode":"2201 LG",
    "sg:province":"Zuid-Holland",
    "wof:name":"Hans Bierman Bloemenexport Bv",
    "wof:placetype":"venue"
},
  "geometry": {"coordinates":[4.440978,52.235336],"type":"Point"}
}