{
  "type": "Feature",
  "properties": {
    "addr:full":"Iepenln 204 Groningen Groningen 9741 GH",
    "addr:housenumber":"204",
    "addr:postcode":"9741 gh",
    "iso:country":"NL",
    "sg:address":"Iepenln 204",
    "sg:city":"Groningen",
    "sg:orig_category":"Begraafplaatsen",
    "sg:phone":"+31 50 577 8762",
    "sg:postcode":"9741 GH",
    "sg:province":"Groningen",
    "wof:name":"Selwerderhof",
    "wof:placetype":"venue"
},
  "geometry": {"coordinates":[6.55452,53.237789],"type":"Point"}
}