{
  "type": "Feature",
  "properties": {
    "addr:full":"Dorpsstr 187 Zuid Beyerland Zuid-Holland 3284 AG",
    "addr:housenumber":"187;beyerland",
    "addr:postcode":"3284",
    "iso:country":"NL",
    "sg:address":"Dorpsstr 187",
    "sg:city":"Zuid Beyerland",
    "sg:classifiers":[
        {
            "category":"Food & Beverages",
            "subcategory":"Bakery",
            "type":"Retail Goods"
        }
    ],
    "sg:phone":"+31 186 661 425",
    "sg:postcode":"3284 AG",
    "sg:province":"Zuid-Holland",
    "sg:tags":[
        "brood",
        "en",
        "banket"
    ],
    "wof:name":"Rien Van De Merwe",
    "wof:placetype":"venue"
},
  "geometry": {"coordinates":[4.366544,51.749893],"type":"Point"}
}