{
  "type": "Feature",
  "properties": {
    "addr:full":"Tussen De Bogen 50 Amsterdam North Holland 1013 JB",
    "addr:housenumber":"50",
    "addr:postcode":"1013 jb",
    "addr:street":"Tussen De Bogen",
    "iso:country":"NL",
    "sg:address":"Tussen De Bogen 50",
    "sg:city":"Amsterdam",
    "sg:orig_category":"Grafisch Ontwerpers",
    "sg:phone":"+31 20 682 7370",
    "sg:postcode":"1013 JB",
    "sg:province":"North Holland",
    "wof:name":"Silvestri, Gebr",
    "wof:placetype":"venue"
},
  "geometry": {"coordinates":[4.886515,52.384182],"type":"Point"}
}