{
  "type": "Feature",
  "properties": {
    "iso:country":"NL",
    "sg:address":"Jolinkweg 6",
    "sg:city":"Rheden",
    "sg:orig_category":"Kappers",
    "sg:phone":"+31 26 495 4523",
    "sg:postcode":"6991 HJ",
    "sg:province":"Gelderland",
    "wof:name":"Angelique Hairstyling",
    "wof:placetype":"venue"
},
  "geometry": {"coordinates":[6.0407838821,52.0061531067],"type":"Point"}
}