{
  "type": "Feature",
  "properties": {
    "addr:full":"Bijlmerplein 979 Amsterdam Zuidoost Noord-Holland 1102 MK",
    "addr:housenumber":"979",
    "addr:postcode":"zuidoost;1102",
    "addr:street":"Bijlmerplein",
    "iso:country":"NL",
    "sg:address":"Bijlmerplein 979",
    "sg:city":"Amsterdam Zuidoost",
    "sg:orig_category":"Verlichting And Huishoudartikelen",
    "sg:phone":"+31 20 609 6851",
    "sg:postcode":"1102 MK",
    "sg:province":"Noord-Holland",
    "wof:name":"Gordijnenhuis De Poort",
    "wof:placetype":"venue"
},
  "geometry": {"coordinates":[4.951973,52.313931],"type":"Point"}
}