{
  "type": "Feature",
  "properties": {
    "addr:full":"J J Van Deinselaan 40 Enschede Overijssel 7541 PE",
    "addr:housenumber":"40",
    "addr:postcode":"7541 pe",
    "addr:street":"Van Deinselaan",
    "iso:country":"NL",
    "sg:address":"J J Van Deinselaan 40",
    "sg:city":"Enschede",
    "sg:orig_category":"Overheidsdiensten",
    "sg:phone":"+31 53 431 0541",
    "sg:postcode":"7541 PE",
    "sg:province":"Overijssel",
    "wof:name":"Zuid Eschmarke",
    "wof:placetype":"venue"
},
  "geometry": {"coordinates":[6.8971719742,52.2073554993],"type":"Point"}
}