{
  "type": "Feature",
  "properties": {
    "addr:full":"G Brautigamsngl 80 Leiden South Holland 2331 SP",
    "addr:housenumber":"80",
    "addr:postcode":"2331 sp",
    "iso:country":"NL",
    "sg:address":"G Brautigamsngl 80",
    "sg:city":"Leiden",
    "sg:orig_category":"Verenigingen En Stichtingen",
    "sg:phone":"+31 71 576 9965",
    "sg:postcode":"2331 SP",
    "sg:province":"South Holland",
    "wof:name":"Docos Vv",
    "wof:placetype":"venue"
},
  "geometry": {"coordinates":[4.450714,52.144527],"type":"Point"}
}