{
  "type": "Feature",
  "properties": {
    "addr:full":"Valkenburgerstr 28 Amsterdam Noord-Holland 1011 LZ",
    "addr:housenumber":"28",
    "addr:postcode":"1011 lz",
    "addr:street":"Valkenburgerstr",
    "iso:country":"NL",
    "sg:address":"Valkenburgerstr 28",
    "sg:city":"Amsterdam",
    "sg:orig_category":"Fitnesscentra",
    "sg:phone":"+31 20 620 6631",
    "sg:postcode":"1011 LZ",
    "sg:province":"Noord-Holland",
    "sg:website":"http://www.clubsportive.nl",
    "wof:name":"Club Sportive Waterlooplein",
    "wof:placetype":"venue"
},
  "geometry": {"coordinates":[4.908341,52.370132],"type":"Point"}
}