{
  "type": "Feature",
  "properties": {
    "addr:full":"Cassandrapln 7 Eindhoven North Brabant 5631 BA",
    "addr:housenumber":"7",
    "addr:postcode":"5631 ba",
    "addr:street":"Cassandrapln",
    "iso:country":"NL",
    "sg:address":"Cassandrapln 7",
    "sg:city":"Eindhoven",
    "sg:classifiers":[
        {
            "category":"Food & Beverages",
            "subcategory":"Bakery",
            "type":"Retail Goods"
        }
    ],
    "sg:phone":"+31 40 245 0348",
    "sg:postcode":"5631 BA",
    "sg:province":"North Brabant",
    "sg:tags":[
        "pizza"
    ],
    "wof:name":"Pinokkio, Pizzeria Shoarma",
    "wof:placetype":"venue"
},
  "geometry": {"coordinates":[5.489672,51.45969],"type":"Point"}
}