{
  "type": "Feature",
  "properties": {
    "iso:country":"NL",
    "sg:address":"Grotestr 12",
    "sg:city":"Bedum",
    "sg:orig_category":"Verenigingen En Stichtingen",
    "sg:phone":"+31 50 301 7134",
    "sg:postcode":"9781 HC",
    "sg:province":"Groningen",
    "wof:name":"Opmaat, Sticht",
    "wof:placetype":"venue"
},
  "geometry": {"coordinates":[6.604123,53.301434],"type":"Point"}
}