{
  "type": "Feature",
  "properties": {
    "addr:full":"Kerklaan 22 Sirjansland Zeeland 4308 AL",
    "addr:housenumber":"22",
    "addr:postcode":"4308 al",
    "addr:street":"Kerklaan",
    "iso:country":"NL",
    "sg:address":"Kerklaan 22",
    "sg:city":"Sirjansland",
    "sg:orig_category":"Verhuur Bouwmachines",
    "sg:phone":"+31 111 641 194",
    "sg:postcode":"4308 AL",
    "sg:province":"Zeeland",
    "wof:name":"P.L. V.D. Oever",
    "wof:placetype":"venue"
},
  "geometry": {"coordinates":[4.031862,51.676689],"type":"Point"}
}