{
  "type": "Feature",
  "properties": {
    "iso:country":"NL",
    "sg:address":"Hopklaverstr 2",
    "sg:city":"Almere",
    "sg:orig_category":"Kaas",
    "sg:phone":"+31 36 533 5769",
    "sg:postcode":"1314 SX",
    "sg:province":"Flevoland",
    "wof:name":"Poppelen, F W M M Van",
    "wof:placetype":"venue"
},
  "geometry": {"coordinates":[5.2068791389,52.3839645386],"type":"Point"}
}