{
  "type": "Feature",
  "properties": {
    "iso:country":"NL",
    "sg:address":"Slotsteeg 18",
    "sg:city":"Hengelo Gld",
    "sg:orig_category":"Autokeuringen",
    "sg:phone":"+31 575 462 779",
    "sg:postcode":"7255 LH",
    "sg:province":"Gelderland",
    "wof:name":"Rietman Autobanden",
    "wof:placetype":"venue"
},
  "geometry": {"coordinates":[6.318131,52.076923],"type":"Point"}
}