{
  "type": "Feature",
  "properties": {
    "iso:country":"NL",
    "sg:address":"Burg Vd Venstr 3",
    "sg:city":"Haaren",
    "sg:orig_category":"Administratie- En Boekhoudkantoren",
    "sg:phone":"+31 411 622 545",
    "sg:postcode":"5076 CG",
    "sg:province":"Noord-Brabant",
    "wof:name":"Loon, Van",
    "wof:placetype":"venue"
},
  "geometry": {"coordinates":[5.223196,51.599529],"type":"Point"}
}