{
  "type": "Feature",
  "properties": {
    "addr:full":"Atalantaberm 30 Houten Utrecht 3994 WB",
    "addr:housenumber":"30",
    "addr:postcode":"3994 wb",
    "addr:street":"Atalantaberm",
    "iso:country":"NL",
    "sg:address":"Atalantaberm 30",
    "sg:city":"Houten",
    "sg:orig_category":"Adviesbureaus Bedrijfsorganisatie",
    "sg:phone":"+31 30 608 1797",
    "sg:postcode":"3994 WB",
    "sg:province":"Utrecht",
    "sg:website":"http://www.consiliumphilosophicum.nl",
    "wof:name":"Consilium Philosophicum",
    "wof:placetype":"venue"
},
  "geometry": {"coordinates":[5.183836,52.037117],"type":"Point"}
}