{
  "type": "Feature",
  "properties": {
    "addr:full":"Postbus 137 Leeuwarden Friesland 8900 AC",
    "addr:housenumber":"137",
    "addr:postcode":"8900 ac",
    "addr:street":"Postbus",
    "iso:country":"NL",
    "sg:address":"Postbus 137",
    "sg:city":"Leeuwarden",
    "sg:orig_category":"Verenigingen En Stichtingen",
    "sg:phone":"+31 58 215 7365",
    "sg:postcode":"8900 AC",
    "sg:province":"Friesland",
    "wof:name":"Monumentenwacht Frysl\u00e2n",
    "wof:placetype":"venue"
},
  "geometry": {"coordinates":[5.79143,53.203049],"type":"Point"}
}