{
  "type": "Feature",
  "properties": {
    "addr:full":"Stationsplein 10 Uithuizen Groningen 9981 BH",
    "addr:housenumber":"10",
    "addr:postcode":"9981 bh",
    "addr:street":"Stationsplein",
    "iso:country":"NL",
    "sg:address":"Stationsplein 10",
    "sg:city":"Uithuizen",
    "sg:orig_category":"Woningbouwverenigingen",
    "sg:phone":"+31 595 432 560",
    "sg:postcode":"9981 BH",
    "sg:province":"Groningen",
    "wof:name":"Stichting Uithuizer Woningbouw",
    "wof:placetype":"venue"
},
  "geometry": {"coordinates":[6.6743249893,53.4092102051],"type":"Point"}
}