{
  "type": "Feature",
  "properties": {
    "addr:full":"Groenstr 12 Berlicum Nb North Brabant 5258 TH",
    "addr:housenumber":"12;nb",
    "addr:postcode":"5258 th",
    "addr:street":"Groenstr",
    "iso:country":"NL",
    "sg:address":"Groenstr 12",
    "sg:city":"Berlicum Nb",
    "sg:orig_category":"Voetbalverenigingen",
    "sg:phone":"+31 73 503 1236",
    "sg:postcode":"5258 TH",
    "sg:province":"North Brabant",
    "wof:name":"Bmc",
    "wof:placetype":"venue"
},
  "geometry": {"coordinates":[5.414081,51.671017],"type":"Point"}
}