{
  "type": "Feature",
  "properties": {
    "addr:full":"V Roosendaalstr 33 Venhuizen Noord-Holland 1606 XC",
    "addr:housenumber":"33",
    "addr:postcode":"1606 xc",
    "iso:country":"NL",
    "sg:address":"V Roosendaalstr 33",
    "sg:city":"Venhuizen",
    "sg:orig_category":"Evenementenverzorging",
    "sg:phone":"+31 228 544 971",
    "sg:postcode":"1606 XC",
    "sg:province":"Noord-Holland",
    "sg:website":"http://www.argo-ent.nl",
    "wof:name":"Argo",
    "wof:placetype":"venue"
},
  "geometry": {"coordinates":[5.199493,52.662418],"type":"Point"}
}