{
  "type": "Feature",
  "properties": {
    "addr:full":"Kon Wilhelminaln 26 Swalmen Limburg 6071 EP",
    "addr:housenumber":"26",
    "addr:postcode":"6071 ep",
    "addr:street":"Kon",
    "iso:country":"NL",
    "sg:address":"Kon Wilhelminaln 26",
    "sg:city":"Swalmen",
    "sg:orig_category":"Verenigingen En Stichtingen",
    "sg:phone":"+31 475 600 035",
    "sg:postcode":"6071 EP",
    "sg:province":"Limburg",
    "wof:name":"Meldpunt Vrijwilligershulp Swalmen",
    "wof:placetype":"venue"
},
  "geometry": {"coordinates":[6.037616,51.228737],"type":"Point"}
}