{
  "type": "Feature",
  "properties": {
    "iso:country":"NL",
    "sg:address":"Talingweide 77",
    "sg:city":"Ysselstein Ut",
    "sg:classifiers":[
        {
            "category":"Personal",
            "subcategory":"Nail Salon",
            "type":"Services"
        }
    ],
    "sg:phone":"+31 30 688 9034",
    "sg:postcode":"3403 AC",
    "sg:province":"Utrecht",
    "sg:tags":[
        "pedicure"
    ],
    "wof:name":"Brugge, M Van Der",
    "wof:placetype":"venue"
},
  "geometry": {"coordinates":[5.026435,52.020599],"type":"Point"}
}