{
  "type": "Feature",
  "properties": {
    "addr:full":"Hoofdweg 7 Capelle A/D Ijssel South Holland 2908 LB",
    "addr:housenumber":"7;a / d",
    "addr:postcode":"2908 lb",
    "addr:street":"Hoofdweg;Ijssel South",
    "iso:country":"NL",
    "sg:address":"Hoofdweg 7",
    "sg:city":"Capelle A/D Ijssel",
    "sg:orig_category":"Bloemen And Planten",
    "sg:phone":"+31 10 451 9499",
    "sg:postcode":"2908 LB",
    "sg:province":"South Holland",
    "wof:name":"Schollevaart Bv",
    "wof:placetype":"venue"
},
  "geometry": {"coordinates":[4.57048,51.953869],"type":"Point"}
}