{
  "type": "Feature",
  "properties": {
    "iso:country":"NL",
    "sg:address":"Linnaeusdreef 23",
    "sg:city":"Breukelen Ut",
    "sg:orig_category":"Tuinontwerp En -Advies",
    "sg:phone":"+31 346 264 272",
    "sg:postcode":"3621 XT",
    "sg:province":"Utrecht",
    "wof:name":"Megen, Anneke Van",
    "wof:placetype":"venue"
},
  "geometry": {"coordinates":[5.00121,52.185085],"type":"Point"}
}