{
  "type": "Feature",
  "properties": {
    "iso:country":"NL",
    "sg:address":"Lemmerstr 31",
    "sg:city":"Tilburg",
    "sg:orig_category":"Bedrijfsmechanisatie En -Automatisering",
    "sg:phone":"+31 13 571 6234",
    "sg:postcode":"5045 WP",
    "sg:province":"North Brabant",
    "wof:name":"Jonat Automation",
    "wof:placetype":"venue"
},
  "geometry": {"coordinates":[5.001027,51.588509],"type":"Point"}
}