{
  "type": "Feature",
  "properties": {
    "addr:full":"Fluitekruid 5 Klazienaveen Drenthe 7891 DA",
    "addr:housenumber":"5",
    "addr:postcode":"7891 da",
    "addr:street":"Fluitekruid",
    "iso:country":"NL",
    "sg:address":"Fluitekruid 5",
    "sg:city":"Klazienaveen",
    "sg:orig_category":"Bejaarden - Verzorgingstehuizen",
    "sg:phone":"+31 591 317 520",
    "sg:postcode":"7891 DA",
    "sg:province":"Drenthe",
    "sg:website":"http://www.tangenborgh.nl",
    "wof:name":"Tangenborgh",
    "wof:placetype":"venue"
},
  "geometry": {"coordinates":[6.978208,52.728706],"type":"Point"}
}