{
  "type": "Feature",
  "properties": {
    "iso:country":"NL",
    "sg:address":"H Hermansln 108",
    "sg:city":"Geleen",
    "sg:orig_category":"Kappers",
    "sg:phone":"+31 46 449 0150",
    "sg:postcode":"6162 GJ",
    "sg:province":"Limburg",
    "wof:name":"Viv Vof",
    "wof:placetype":"venue"
},
  "geometry": {"coordinates":[5.831647,50.975815],"type":"Point"}
}