{
  "type": "Feature",
  "properties": {
    "addr:full":"Wierdensestr 35 Almelo Overijssel 7607 GE",
    "addr:housenumber":"35",
    "addr:postcode":"7607",
    "addr:street":"Wierdensestr",
    "iso:country":"NL",
    "sg:address":"Wierdensestr 35",
    "sg:city":"Almelo",
    "sg:orig_category":"Verenigingen En Stichtingen",
    "sg:phone":"+31 546 851 435",
    "sg:postcode":"7607 GE",
    "sg:province":"Overijssel",
    "wof:name":"Jarabee De Dolfijn",
    "wof:placetype":"venue"
},
  "geometry": {"coordinates":[6.660046,52.355255],"type":"Point"}
}