{
  "type": "Feature",
  "properties": {
    "addr:full":"Tipstraat 12 Maasbracht Limburg 6051 CX",
    "addr:housenumber":"12",
    "addr:postcode":"6051 cx",
    "addr:street":"Tipstraat",
    "iso:country":"NL",
    "sg:address":"Tipstraat 12",
    "sg:city":"Maasbracht",
    "sg:classifiers":[
        {
            "category":"Shopping",
            "subcategory":"Bicycles & Sporting Goods",
            "type":"Retail Goods"
        }
    ],
    "sg:phone":"+31 475 463 161",
    "sg:postcode":"6051 CX",
    "sg:province":"Limburg",
    "sg:tags":[
        "sport-",
        "kampeerartikelen"
    ],
    "wof:name":"Watersport De Tip",
    "wof:placetype":"venue"
},
  "geometry": {"coordinates":[5.891523,51.147671],"type":"Point"}
}