{
  "type": "Feature",
  "properties": {
    "addr:full":"Bedryvenstr 9 Giessen North Brabant 4283 JJ",
    "addr:housenumber":"9",
    "addr:postcode":"4283 jj",
    "addr:street":"Bedryvenstr",
    "iso:country":"NL",
    "sg:address":"Bedryvenstr 9",
    "sg:city":"Giessen",
    "sg:orig_category":"Machinefabrieken",
    "sg:phone":"+31 183 440 585",
    "sg:postcode":"4283 JJ",
    "sg:province":"North Brabant",
    "sg:website":"http://www.copierbv.nl",
    "wof:name":"Copier Machinebouw",
    "wof:placetype":"venue"
},
  "geometry": {"coordinates":[5.011815,51.778946],"type":"Point"}
}