{
  "type": "Feature",
  "properties": {
    "addr:full":"Frieselaan 12 Groesbeek Gelderland 6562 BE",
    "addr:housenumber":"12",
    "addr:postcode":"6562",
    "addr:street":"Frieselaan;Gelderland",
    "iso:country":"NL",
    "sg:address":"Frieselaan 12",
    "sg:city":"Groesbeek",
    "sg:orig_category":"Artiesten",
    "sg:phone":"+31 24 397 4724",
    "sg:postcode":"6562 BE",
    "sg:province":"Gelderland",
    "wof:name":"Tonnie Peters",
    "wof:placetype":"venue"
},
  "geometry": {"coordinates":[5.936198,51.774319],"type":"Point"}
}