{
  "type": "Feature",
  "properties": {
    "iso:country":"NL",
    "sg:address":"Burg Honykstr 3",
    "sg:city":"Venhuizen",
    "sg:orig_category":"Voetbalverenigingen",
    "sg:phone":"+31 228 541 408",
    "sg:postcode":"1606 XL",
    "sg:province":"Noord-Holland",
    "wof:name":"Asv 55",
    "wof:placetype":"venue"
},
  "geometry": {"coordinates":[5.199493,52.662418],"type":"Point"}
}