{
  "type": "Feature",
  "properties": {
    "addr:full":"Hyacintenlaan 2 Hillegom Zuid-Holland 2182 DE",
    "addr:housenumber":"2",
    "addr:postcode":"2182 de",
    "addr:street":"Hyacintenlaan",
    "iso:country":"NL",
    "sg:address":"Hyacintenlaan 2",
    "sg:city":"Hillegom",
    "sg:orig_category":"Bloemen- And Plantenteelt",
    "sg:phone":"+31 252 519 444",
    "sg:postcode":"2182 DE",
    "sg:province":"Zuid-Holland",
    "wof:name":"Bloembollenhandel Walter Blom En Zoon Bv",
    "wof:placetype":"venue"
},
  "geometry": {"coordinates":[4.570823,52.277748],"type":"Point"}
}