{
  "type": "Feature",
  "properties": {
    "iso:country":"NL",
    "sg:address":"Ruitersbosln 64",
    "sg:city":"Breda",
    "sg:orig_category":"Projectontwikkeling",
    "sg:phone":"+31 76 565 1002",
    "sg:postcode":"4837 CK",
    "sg:province":"Noord-Brabant",
    "wof:name":"Beek Bv, Van",
    "wof:placetype":"venue"
},
  "geometry": {"coordinates":[4.766699,51.568306],"type":"Point"}
}