{
  "type": "Feature",
  "properties": {
    "addr:full":"Zoetelaarpassage 19 Almere Flevoland 1315 AV",
    "addr:housenumber":"19;1315",
    "addr:postcode":"av",
    "addr:street":"Zoetelaarpassage;Flevoland",
    "iso:country":"NL",
    "sg:address":"Zoetelaarpassage 19",
    "sg:city":"Almere",
    "sg:orig_category":"Verenigingen En Stichtingen",
    "sg:phone":"+31 36 534 7760",
    "sg:postcode":"1315 AV",
    "sg:province":"Flevoland",
    "wof:name":"Vluchtelingen En Nieuwkomers, Sticht Voor",
    "wof:placetype":"venue"
},
  "geometry": {"coordinates":[5.216062,52.36948],"type":"Point"}
}