{
  "type": "Feature",
  "properties": {
    "iso:country":"NL",
    "sg:address":"Radioweg 28Hs",
    "sg:city":"Amsterdam",
    "sg:orig_category":"Fotostudio'S And Fotografen",
    "sg:phone":"+31 20 668 3867",
    "sg:postcode":"1098 NH",
    "sg:province":"North Holland",
    "wof:name":"Studio Fixed",
    "wof:placetype":"venue"
},
  "geometry": {"coordinates":[4.940322,52.352264],"type":"Point"}
}