{
  "type": "Feature",
  "properties": {
    "iso:country":"NL",
    "sg:address":"Eigen Haard 14",
    "sg:city":"Balk",
    "sg:orig_category":"Horeca-Inrichtingen En -Uitrustingen",
    "sg:phone":"+31 514 569 750",
    "sg:postcode":"8561 EX",
    "sg:province":"Friesland",
    "sg:website":"http://www.merito.nl",
    "wof:name":"Merito",
    "wof:placetype":"venue"
},
  "geometry": {"coordinates":[-100.82858299999999,36.608829],"type":"Point"}
}