{
  "type": "Feature",
  "properties": {
    "iso:country":"NL",
    "sg:address":"Violenstr 39",
    "sg:city":"Den Helder",
    "sg:orig_category":"Administratie- En Boekhoudkantoren",
    "sg:phone":"+31 223 614 446",
    "sg:postcode":"1782 KA",
    "sg:province":"Noord-Holland",
    "wof:name":"Fj\u00e4der",
    "wof:placetype":"venue"
},
  "geometry": {"coordinates":[4.757817,52.952934],"type":"Point"}
}