{
  "type": "Feature",
  "properties": {
    "addr:full":"Piet Heinstraat 21 Noordwijk Zh Zuid-Holland 2202 KS",
    "addr:housenumber":"21",
    "addr:postcode":"2202 ks",
    "addr:street":"Piet Heinstraat",
    "iso:country":"NL",
    "sg:address":"Piet Heinstraat 21",
    "sg:city":"Noordwijk Zh",
    "sg:orig_category":"Wasserettes And Stomerijen",
    "sg:phone":"+31 71 361 3485",
    "sg:postcode":"2202 KS",
    "sg:province":"Zuid-Holland",
    "wof:name":"Wassalon Piet Hein",
    "wof:placetype":"venue"
},
  "geometry": {"coordinates":[4.4370927811,52.2442626953],"type":"Point"}
}