{
  "type": "Feature",
  "properties": {
    "addr:full":"Antoon Derkinderenstraat 7 Eindhoven North Brabant 5613 JL",
    "addr:housenumber":"7",
    "addr:postcode":"5613 jl",
    "addr:street":"Antoon Derkinderenstraat",
    "iso:country":"NL",
    "sg:address":"Antoon Derkinderenstraat 7",
    "sg:city":"Eindhoven",
    "sg:orig_category":"Loodgieterswerk, Verwarming And Sanitaire Installaties",
    "sg:phone":"+31 40 246 2567",
    "sg:postcode":"5613 JL",
    "sg:province":"North Brabant",
    "wof:name":"Van Heerwaarden",
    "wof:placetype":"venue"
},
  "geometry": {"coordinates":[5.499383,51.438091],"type":"Point"}
}