{
  "type": "Feature",
  "properties": {
    "addr:full":"Korfmakersstr 127 Rotterdam South Holland 3026 XG",
    "addr:housenumber":"127",
    "addr:postcode":"3026 xg",
    "iso:country":"NL",
    "sg:address":"Korfmakersstr 127",
    "sg:city":"Rotterdam",
    "sg:orig_category":"Kinderopvang",
    "sg:phone":"+31 10 262 4548",
    "sg:postcode":"3026 XG",
    "sg:province":"South Holland",
    "wof:name":"Vangnet, Het",
    "wof:placetype":"venue"
},
  "geometry": {"coordinates":[4.437707,51.913586],"type":"Point"}
}