{
  "type": "Feature",
  "properties": {
    "iso:country":"NL",
    "sg:address":"Dorpsstr 5",
    "sg:city":"Oisterwyk",
    "sg:orig_category":"Boeken En Tijdschriften",
    "sg:phone":"+31 13 528 2300",
    "sg:postcode":"5061 HH",
    "sg:province":"Noord-Brabant",
    "wof:name":"Ako",
    "wof:placetype":"venue"
},
  "geometry": {"coordinates":[5.192281,51.580471],"type":"Point"}
}