{
  "type": "Feature",
  "properties": {
    "addr:full":"P Lastmanstr 7 S Gravenhage Zuid-Holland 2526 MZ",
    "addr:housenumber":"7 s",
    "addr:postcode":"2526 mz",
    "addr:street":"P Lastmanstr",
    "iso:country":"NL",
    "sg:address":"P Lastmanstr 7",
    "sg:city":"S Gravenhage",
    "sg:orig_category":"Voetbalverenigingen",
    "sg:phone":"+31 70 389 6169",
    "sg:postcode":"2526 MZ",
    "sg:province":"Zuid-Holland",
    "wof:name":"Odb",
    "wof:placetype":"venue"
},
  "geometry": {"coordinates":[4.30555,52.0681],"type":"Point"}
}