{
  "type": "Feature",
  "properties": {
    "iso:country":"NL",
    "sg:address":"Tussen Meer 63",
    "sg:city":"Amsterdam",
    "sg:orig_category":"Kappers",
    "sg:phone":"+31 20 619 5788",
    "sg:postcode":"1068 EZ",
    "sg:province":"Noord-Holland",
    "wof:name":"Loes De Kort, Haarmode",
    "wof:placetype":"venue"
},
  "geometry": {"coordinates":[4.800996,52.358162],"type":"Point"}
}