{
  "type": "Feature",
  "properties": {
    "addr:full":"Handelslaan 3 Uden Noord-Brabant 5405 AE",
    "addr:housenumber":"3",
    "addr:postcode":"5405 ae",
    "addr:street":"Handelslaan",
    "iso:country":"NL",
    "sg:address":"Handelslaan 3",
    "sg:city":"Uden",
    "sg:orig_category":"Goederenvervoer Over De Weg",
    "sg:phone":"+31 413 333 111",
    "sg:postcode":"5405 AE",
    "sg:province":"Noord-Brabant",
    "wof:name":"Verinex Bv",
    "wof:placetype":"venue"
},
  "geometry": {"coordinates":[5.644845,51.654793],"type":"Point"}
}