{
  "type": "Feature",
  "properties": {
    "addr:full":"Koopvaardywg 30 Oosterhout Nb North Brabant 4906 CV",
    "addr:housenumber":"30;nb",
    "addr:postcode":"4906 cv",
    "addr:street":"Koopvaardywg",
    "iso:country":"NL",
    "sg:address":"Koopvaardywg 30",
    "sg:city":"Oosterhout Nb",
    "sg:orig_category":"Houtgroothandel Hardhout",
    "sg:phone":"+31 162 425 039",
    "sg:postcode":"4906 CV",
    "sg:province":"North Brabant",
    "wof:name":"Snijders, A",
    "wof:placetype":"venue"
},
  "geometry": {"coordinates":[4.836593,51.665657],"type":"Point"}
}