{
  "type": "Feature",
  "properties": {
    "addr:full":"Schuifelenberg 3 Deurne Noord-Brabant 5751 HZ",
    "addr:housenumber":"3",
    "addr:postcode":"5751 hz",
    "addr:street":"Schuifelenberg",
    "iso:country":"NL",
    "sg:address":"Schuifelenberg 3",
    "sg:city":"Deurne",
    "sg:orig_category":"Fotostudio'S And Fotografen",
    "sg:phone":"+31 493 315 088",
    "sg:postcode":"5751 HZ",
    "sg:province":"Noord-Brabant",
    "wof:name":"Dom Melskens Bv",
    "wof:placetype":"venue"
},
  "geometry": {"coordinates":[5.794268,51.462521],"type":"Point"}
}