{
  "type": "Feature",
  "properties": {
    "addr:full":"Middenwg 287 1Hg Amsterdam North Holland 1098 AS",
    "addr:housenumber":"287",
    "addr:postcode":"1098 as",
    "addr:street":"1Hg",
    "iso:country":"NL",
    "sg:address":"Middenwg 287 1Hg",
    "sg:city":"Amsterdam",
    "sg:orig_category":"Fotoreportages",
    "sg:phone":"+31 20 463 0461",
    "sg:postcode":"1098 AS",
    "sg:province":"North Holland",
    "wof:name":"R\u00f6ckener",
    "wof:placetype":"venue"
},
  "geometry": {"coordinates":[4.939665,52.348179],"type":"Point"}
}