{
  "type": "Feature",
  "properties": {
    "iso:country":"NL",
    "sg:address":"Noordvliet 69",
    "sg:city":"Maassluis",
    "sg:orig_category":"Kappers",
    "sg:phone":"+31 10 591 8667",
    "sg:postcode":"3142 CJ",
    "sg:province":"Zuid-Holland",
    "wof:name":"Kapsalon Slotboom",
    "wof:placetype":"venue"
},
  "geometry": {"coordinates":[4.2570238113,51.9235305786],"type":"Point"}
}