{
  "type": "Feature",
  "properties": {
    "iso:country":"NL",
    "sg:address":"Buitendijk 4",
    "sg:city":"Strijensas",
    "sg:orig_category":"Architecten",
    "sg:phone":"+31 78 674 3717",
    "sg:postcode":"3292 LB",
    "sg:province":"Zuid-Holland",
    "wof:name":"Bro Buro Voor Ruimtelijke Ordening & Architektuur",
    "wof:placetype":"venue"
},
  "geometry": {"coordinates":[4.584998,51.713985],"type":"Point"}
}