{
  "type": "Feature",
  "properties": {
    "addr:full":"Looydijk 150 De Bilt Utrecht 3731 VB",
    "addr:housenumber":"150",
    "addr:postcode":"3731 vb",
    "addr:street":"Looydijk",
    "iso:country":"NL",
    "sg:address":"Looydijk 150",
    "sg:city":"De Bilt",
    "sg:orig_category":"Artsen - Huisartsen",
    "sg:phone":"+31 30 220 0907",
    "sg:postcode":"3731 VB",
    "sg:province":"Utrecht",
    "wof:name":"Smit, L H",
    "wof:placetype":"venue"
},
  "geometry": {"coordinates":[5.1799049377,52.1080207825],"type":"Point"}
}