{
  "type": "Feature",
  "properties": {
    "addr:full":"Grasbroekerweg 16 Heerlen Limburg 6412 BE",
    "addr:housenumber":"16",
    "addr:postcode":"6412",
    "addr:street":"Grasbroekerweg",
    "iso:country":"NL",
    "sg:address":"Grasbroekerweg 16",
    "sg:city":"Heerlen",
    "sg:orig_category":"Woningbouwverenigingen",
    "sg:phone":"+31 45 561 5215",
    "sg:postcode":"6412 BE",
    "sg:province":"Limburg",
    "wof:name":"Woningvereniging De Volkswoning",
    "wof:placetype":"venue"
},
  "geometry": {"coordinates":[5.9762711525,50.8934211731],"type":"Point"}
}