{
  "type": "Feature",
  "properties": {
    "addr:full":"Haspel 35/C65 Ermelo Gelderland 3852 LS",
    "addr:housenumber":"35 / c65",
    "addr:postcode":"3852 ls",
    "addr:street":"Haspel;Gelderland",
    "iso:country":"NL",
    "sg:address":"Haspel 35/C65",
    "sg:city":"Ermelo",
    "sg:orig_category":"Wegen And Sportterreinen",
    "sg:phone":"+31 341 419 837",
    "sg:postcode":"3852 LS",
    "sg:province":"Gelderland",
    "wof:name":"R. V.D. Stad",
    "wof:placetype":"venue"
},
  "geometry": {"coordinates":[5.7043061256,52.2693862915],"type":"Point"}
}