{
  "type": "Feature",
  "properties": {
    "addr:full":"Roermondseweg 150 Steijl Limburg 5935 AE",
    "addr:housenumber":"150",
    "addr:postcode":"5935 ae",
    "addr:street":"Roermondseweg",
    "iso:country":"NL",
    "sg:address":"Roermondseweg 150",
    "sg:city":"Steijl",
    "sg:orig_category":"Loodgieterswerk, Verwarming And Sanitaire Installaties",
    "sg:phone":"+31 77 373 0077",
    "sg:postcode":"5935 AE",
    "sg:province":"Limburg",
    "wof:name":"Ims",
    "wof:placetype":"venue"
},
  "geometry": {"coordinates":[6.123025,51.333511],"type":"Point"}
}