{
  "type": "Feature",
  "properties": {
    "addr:full":"Breezand 10 Huizen Noord-Holland 1274 TD",
    "addr:housenumber":"10",
    "addr:postcode":"1274 td",
    "addr:street":"Breezand",
    "iso:country":"NL",
    "sg:address":"Breezand 10",
    "sg:city":"Huizen",
    "sg:orig_category":"Adviesbureaus Personeel",
    "sg:phone":"+31 35 525 5391",
    "sg:postcode":"1274 TD",
    "sg:province":"Noord-Holland",
    "sg:website":"http://www.peereboomforyou.com",
    "wof:name":"Peereboom",
    "wof:placetype":"venue"
},
  "geometry": {"coordinates":[5.278189,52.299892],"type":"Point"}
}