{
  "type": "Feature",
  "properties": {
    "addr:full":"Heistraat 84 Helmond North Brabant 5701 HR",
    "addr:housenumber":"84",
    "addr:postcode":"5701 hr",
    "addr:street":"Heistraat",
    "iso:country":"NL",
    "sg:address":"Heistraat 84",
    "sg:city":"Helmond",
    "sg:orig_category":"Werving And Selectie Van Tijdelijk Personeel And Uitzendkantoren",
    "sg:phone":"+31 492 590 990",
    "sg:postcode":"5701 HR",
    "sg:province":"North Brabant",
    "wof:name":"Avanti",
    "wof:placetype":"venue"
},
  "geometry": {"coordinates":[5.6616258621,51.4836235046],"type":"Point"}
}