{
  "type": "Feature",
  "properties": {
    "iso:country":"NL",
    "sg:address":"Vogelkerslaan 10",
    "sg:city":"Leersum",
    "sg:orig_category":"Boekhouders",
    "sg:phone":"+31 343 456 585",
    "sg:postcode":"3956 DL",
    "sg:province":"Utrecht",
    "wof:name":"Administratief Adviesbureau M. Oudshoorn",
    "wof:placetype":"venue"
},
  "geometry": {"coordinates":[5.432052,52.015057],"type":"Point"}
}