{
  "type": "Feature",
  "properties": {
    "addr:full":"Smirnoffwg 3 Rotterdam Zuid-Holland 3088 HE",
    "addr:housenumber":"3",
    "addr:postcode":"3088 he",
    "addr:street":"Smirnoffwg",
    "iso:country":"NL",
    "sg:address":"Smirnoffwg 3",
    "sg:city":"Rotterdam",
    "sg:classifiers":[
        {
            "category":"Education",
            "subcategory":"Special Training",
            "type":"Public Place"
        }
    ],
    "sg:phone":"+31 10 495 5811",
    "sg:postcode":"3088 HE",
    "sg:province":"Zuid-Holland",
    "sg:tags":[
        "expertise"
    ],
    "wof:name":"Sas & Associates Bv, J C Van",
    "wof:placetype":"venue"
},
  "geometry": {"coordinates":[4.436355,51.878086],"type":"Point"}
}