{
  "type": "Feature",
  "properties": {
    "addr:full":"Voorsterwg 13 Marknesse Flevoland 8316 PP",
    "addr:housenumber":"13",
    "addr:postcode":"8316 pp",
    "addr:street":"Voorsterwg;Flevoland",
    "iso:country":"NL",
    "sg:address":"Voorsterwg 13",
    "sg:city":"Marknesse",
    "sg:orig_category":"Koel- En Vrieshuizen",
    "sg:phone":"+31 527 203 261",
    "sg:postcode":"8316 PP",
    "sg:province":"Flevoland",
    "wof:name":"Daniels Vof",
    "wof:placetype":"venue"
},
  "geometry": {"coordinates":[5.894622,52.691181],"type":"Point"}
}