{
  "type": "Feature",
  "properties": {
    "addr:full":"Wilgenln 41 Oud Alblas Zuid-Holland 2969 BT",
    "addr:housenumber":"41",
    "addr:postcode":"2969 bt",
    "addr:street":"Wilgenln;Oud Alblas",
    "iso:country":"NL",
    "sg:address":"Wilgenln 41",
    "sg:city":"Oud Alblas",
    "sg:orig_category":"Drukwerkverspreiding",
    "sg:phone":"+31 184 694 995",
    "sg:postcode":"2969 BT",
    "sg:province":"Zuid-Holland",
    "sg:website":"http://www.danique.com",
    "wof:name":"Danique",
    "wof:placetype":"venue"
},
  "geometry": {"coordinates":[4.706618,51.856964],"type":"Point"}
}