{
  "type": "Feature",
  "properties": {
    "addr:full":"Kempenlandstr 11 Boxtel Noord-Brabant 5283 CK",
    "addr:housenumber":"11",
    "addr:postcode":"5283 ck",
    "addr:street":"Kempenlandstr",
    "iso:country":"NL",
    "sg:address":"Kempenlandstr 11",
    "sg:city":"Boxtel",
    "sg:orig_category":"Kappers",
    "sg:phone":"+31 411 672 036",
    "sg:postcode":"5283 CK",
    "sg:province":"Noord-Brabant",
    "wof:name":"Marjan",
    "wof:placetype":"venue"
},
  "geometry": {"coordinates":[5.334911,51.590252],"type":"Point"}
}