{
  "type": "Feature",
  "properties": {
    "addr:full":"V Goghstr 27 Groningen Groningen 9718 MP",
    "addr:housenumber":"27",
    "addr:postcode":"9718 mp",
    "iso:country":"NL",
    "sg:address":"V Goghstr 27",
    "sg:city":"Groningen",
    "sg:orig_category":"Adviesbureaus Beroeps-, School- And Studiekeuze",
    "sg:phone":"+31 50 312 0261",
    "sg:postcode":"9718 MP",
    "sg:province":"Groningen",
    "sg:website":"http://www.loopbaanpsychologen.nl",
    "wof:name":"Heller Psychologisch Adviesbureau",
    "wof:placetype":"venue"
},
  "geometry": {"coordinates":[6.574715,53.217144],"type":"Point"}
}