{
  "type": "Feature",
  "properties": {
    "addr:full":"De Waal 2 Best Noord-Brabant 5684 PH",
    "addr:housenumber":"2",
    "addr:postcode":"5684",
    "addr:street":"De Waal",
    "iso:country":"NL",
    "sg:address":"De Waal 2",
    "sg:city":"Best",
    "sg:orig_category":"Projectontwikkeling",
    "sg:phone":"+31 499 375 050",
    "sg:postcode":"5684 PH",
    "sg:province":"Noord-Brabant",
    "wof:name":"Berlaere Bv",
    "wof:placetype":"venue"
},
  "geometry": {"coordinates":[-101.45208700000001,31.191275],"type":"Point"}
}