{
  "type": "Feature",
  "properties": {
    "iso:country":"NL",
    "sg:address":"Den Brielstr 22",
    "sg:city":"Amsterdam",
    "sg:orig_category":"Sanitaire Artikelen - Fabrieken En Groothandel",
    "sg:phone":"+31 20 684 8748",
    "sg:postcode":"1055 RV",
    "sg:province":"Noord-Holland",
    "wof:name":"Cvs Groothandel",
    "wof:placetype":"venue"
},
  "geometry": {"coordinates":[4.85951,52.382771],"type":"Point"}
}