{
  "type": "Feature",
  "properties": {
    "addr:full":"Nw Binnenwg 87A Rotterdam South Holland 3014 GE",
    "addr:housenumber":"87a",
    "addr:postcode":"3014",
    "iso:country":"NL",
    "sg:address":"Nw Binnenwg 87A",
    "sg:city":"Rotterdam",
    "sg:orig_category":"Mobiele- En Autotelefoons",
    "sg:phone":"+31 10 484 0110",
    "sg:postcode":"3014 GE",
    "sg:province":"South Holland",
    "sg:website":"http://www.smarttelecom.nl",
    "wof:name":"Smart Telecom",
    "wof:placetype":"venue"
},
  "geometry": {"coordinates":[4.468669,51.916225],"type":"Point"}
}