{
  "type": "Feature",
  "properties": {
    "addr:full":"Reguliersdwarsstraat 4 Amsterdam Noord-Holland 1017 BM",
    "addr:housenumber":"4",
    "addr:postcode":"1017 bm",
    "addr:street":"Reguliersdwarsstraat",
    "iso:country":"NL",
    "sg:address":"Reguliersdwarsstraat 4",
    "sg:city":"Amsterdam",
    "sg:orig_category":"Kappers",
    "sg:phone":"+31 20 626 8075",
    "sg:postcode":"1017 BM",
    "sg:province":"Noord-Holland",
    "wof:name":"Hot Heads",
    "wof:placetype":"venue"
},
  "geometry": {"coordinates":[4.8890151978,52.3667984009],"type":"Point"}
}