{
  "type": "Feature",
  "properties": {
    "addr:full":"Dr H V Nesln 76 Noordwyk Zh Zuid-Holland 2201 GE",
    "addr:housenumber":"76",
    "addr:postcode":"2201",
    "addr:street":"Dr H V Nesln",
    "iso:country":"NL",
    "sg:address":"Dr H V Nesln 76",
    "sg:city":"Noordwyk Zh",
    "sg:orig_category":"Verzekeringen - Verzekeringskantoren",
    "sg:phone":"+31 71 361 9124",
    "sg:postcode":"2201 GE",
    "sg:province":"Zuid-Holland",
    "wof:name":"Jelierse",
    "wof:placetype":"venue"
},
  "geometry": {"coordinates":[4.447704,52.234268],"type":"Point"}
}