{
  "type": "Feature",
  "properties": {
    "addr:full":"De Giek 19 Drachten Provincie Friesland 9206 AS",
    "addr:housenumber":"19",
    "addr:postcode":"9206 as",
    "addr:street":"De Giek;Provincie Friesland",
    "iso:country":"NL",
    "sg:address":"De Giek 19",
    "sg:city":"Drachten",
    "sg:orig_category":"Verf En Lak",
    "sg:phone":"+31 512 515 670",
    "sg:postcode":"9206 AS",
    "sg:province":"Provincie Friesland",
    "wof:name":"Hoogterp'S Verfhandel Bv",
    "wof:placetype":"venue"
},
  "geometry": {"coordinates":[6.074315,53.114861],"type":"Point"}
}