{
  "type": "Feature",
  "properties": {
    "addr:full":"Briandflat 67 Uithoorn Noord-Holland 1422 TW",
    "addr:housenumber":"67",
    "addr:postcode":"1422 tw",
    "addr:street":"Briandflat",
    "iso:country":"NL",
    "sg:address":"Briandflat 67",
    "sg:city":"Uithoorn",
    "sg:orig_category":"Schilderwerk",
    "sg:phone":"+31 297 562 425",
    "sg:postcode":"1422 TW",
    "sg:province":"Noord-Holland",
    "wof:name":"Schildersbedrijf Bloemraad",
    "wof:placetype":"venue"
},
  "geometry": {"coordinates":[4.830471,52.250507],"type":"Point"}
}