{
  "type": "Feature",
  "properties": {
    "addr:full":"Koningshoek 92054 Maassluis Friesland 3144 BA",
    "addr:housenumber":"92054",
    "addr:postcode":"3144 ba",
    "addr:street":"Koningshoek",
    "iso:country":"NL",
    "sg:address":"Koningshoek 92054",
    "sg:city":"Maassluis",
    "sg:orig_category":"Herenmodezaken",
    "sg:phone":"+31 10 591 9919",
    "sg:postcode":"3144 BA",
    "sg:province":"Friesland",
    "wof:name":"Adam Herenmodes Bv",
    "wof:placetype":"venue"
},
  "geometry": {"coordinates":[4.240003,51.927864],"type":"Point"}
}