{
  "type": "Feature",
  "properties": {
    "addr:full":"Nachtegaalstr 1 Spykenisse Zuid-Holland 3201 VL",
    "addr:housenumber":"1",
    "addr:postcode":"3201 vl",
    "addr:street":"Nachtegaalstr",
    "iso:country":"NL",
    "sg:address":"Nachtegaalstr 1",
    "sg:city":"Spykenisse",
    "sg:orig_category":"Fietsen En Bromfietsen",
    "sg:phone":"+31 181 612 377",
    "sg:postcode":"3201 VL",
    "sg:province":"Zuid-Holland",
    "wof:name":"Baecke Motoren",
    "wof:placetype":"venue"
},
  "geometry": {"coordinates":[4.325567,51.847263],"type":"Point"}
}