{
  "type": "Feature",
  "properties": {
    "addr:full":"Maaijkant 2 Ulicoten Noord-Brabant 5113 BC",
    "addr:housenumber":"2",
    "addr:postcode":"5113 bc",
    "addr:street":"Maaijkant",
    "iso:country":"NL",
    "sg:address":"Maaijkant 2",
    "sg:city":"Ulicoten",
    "sg:orig_category":"Pluimveebedrijven En -Handelaren",
    "sg:phone":"+31 13 519 9283",
    "sg:postcode":"5113 BC",
    "sg:province":"Noord-Brabant",
    "wof:name":"Jespers, C J B",
    "wof:placetype":"venue"
},
  "geometry": {"coordinates":[4.865038,51.46146],"type":"Point"}
}