{
  "type": "Feature",
  "properties": {
    "iso:country":"NL",
    "sg:address":"Poppelseweg 9A",
    "sg:city":"Goirle",
    "sg:orig_category":"Pluimveehouderijen",
    "sg:phone":"+31 13 534 1309",
    "sg:postcode":"5051 PL",
    "sg:province":"Noord-Brabant",
    "wof:name":"F.P.W.M. Van Abeelen-Vughts",
    "wof:placetype":"venue"
},
  "geometry": {"coordinates":[5.05409,51.50396],"type":"Point"}
}