{
  "type": "Feature",
  "properties": {
    "addr:full":"Poppelseweg 9A Goirle Noord-Brabant 5051 PL",
    "addr:housenumber":"9a",
    "addr:postcode":"5051 pl",
    "addr:street":"Poppelseweg",
    "iso:country":"NL",
    "sg:address":"Poppelseweg 9A",
    "sg:city":"Goirle",
    "sg:orig_category":"Pluimveehouderijen",
    "sg:phone":"+31 13 534 1309",
    "sg:postcode":"5051 PL",
    "sg:province":"Noord-Brabant",
    "wof:name":"F.P.W.M. Van Abeelen-Vughts",
    "wof:placetype":"venue"
},
  "geometry": {"coordinates":[5.05409,51.50396],"type":"Point"}
}