{
  "type": "Feature",
  "properties": {
    "addr:full":"Bergpolderpln 2+3 Rotterdam Zuid-Holland 3051 GA",
    "addr:housenumber":"2 + 3",
    "addr:postcode":"3051 ga",
    "addr:street":"Bergpolderpln",
    "iso:country":"NL",
    "sg:address":"Bergpolderpln 2+3",
    "sg:city":"Rotterdam",
    "sg:orig_category":"Honden- En Kattentrimsalons",
    "sg:phone":"+31 10 461 1295",
    "sg:postcode":"3051 GA",
    "sg:province":"Zuid-Holland",
    "wof:name":"Corry'S Dieren- & Duivenspec Zaak",
    "wof:placetype":"venue"
},
  "geometry": {"coordinates":[4.476148,51.945221],"type":"Point"}
}