{
  "type": "Feature",
  "properties": {
    "iso:country":"NL",
    "sg:address":"Pagestraat 4",
    "sg:city":"Limbricht",
    "sg:orig_category":"Marktonderzoekbureaus",
    "sg:phone":"+31 46 451 8719",
    "sg:postcode":"6141 AL",
    "sg:province":"Limburg",
    "wof:name":"Drs H.A.G. Rombouts Marktonderz & Marktadvies",
    "wof:placetype":"venue"
},
  "geometry": {"coordinates":[5.839063,51.011581],"type":"Point"}
}