{
  "type": "Feature",
  "properties": {
    "addr:full":"Opaal 15 'S Hertogenbosch Noord-Brabant 5231 KE",
    "addr:housenumber":"15",
    "addr:postcode":"5231 ke",
    "addr:street":"Opaal;' S",
    "iso:country":"NL",
    "sg:address":"Opaal 15",
    "sg:city":"'S Hertogenbosch",
    "sg:orig_category":"Verpakkingsbedrijven",
    "sg:phone":"+31 73 642 3571",
    "sg:postcode":"5231 KE",
    "sg:province":"Noord-Brabant",
    "wof:name":"T.W.C. Liberty",
    "wof:placetype":"venue"
},
  "geometry": {"coordinates":[5.30389,51.712627],"type":"Point"}
}