{
  "type": "Feature",
  "properties": {
    "addr:full":"Hilvarenbeekse Wg 606 Tilburg North Brabant 5022 GC",
    "addr:housenumber":"606",
    "addr:postcode":"5022 gc",
    "addr:street":"Wg",
    "iso:country":"NL",
    "sg:address":"Hilvarenbeekse Wg 606",
    "sg:city":"Tilburg",
    "sg:orig_category":"Bloemen En Planten",
    "sg:phone":"+31 13 539 2962",
    "sg:postcode":"5022 GC",
    "sg:province":"North Brabant",
    "wof:name":"Fleur Vof, La",
    "wof:placetype":"venue"
},
  "geometry": {"coordinates":[5.10576,51.53756],"type":"Point"}
}