{
  "type": "Feature",
  "properties": {
    "iso:country":"NL",
    "sg:address":"Laan Van Beek En Royen 30",
    "sg:city":"Zeist",
    "sg:classifiers":[
        {
            "category":"Professional",
            "subcategory":"Accounting & Tax Preparation",
            "type":"Services"
        }
    ],
    "sg:phone":"+31 30 692 0074",
    "sg:postcode":"3701 AJ",
    "sg:province":"Utrecht",
    "sg:tags":[
        "accountant"
    ],
    "wof:name":"Schneider Storm Accountants En Belasting",
    "wof:placetype":"venue"
},
  "geometry": {"coordinates":[5.245081,52.082352],"type":"Point"}
}