{
  "type": "Feature",
  "properties": {
    "addr:full":"Eurowg 15 Leek Groningen 9351 EM",
    "addr:housenumber":"15",
    "addr:postcode":"9351 em",
    "addr:street":"Eurowg",
    "iso:country":"NL",
    "sg:address":"Eurowg 15",
    "sg:city":"Leek",
    "sg:orig_category":"Elektronica - Ontwikkeling En Groothandel",
    "sg:phone":"+31 594 512 700",
    "sg:postcode":"9351 EM",
    "sg:province":"Groningen",
    "wof:name":"Power Bv",
    "wof:placetype":"venue"
},
  "geometry": {"coordinates":[6.380571,53.165115],"type":"Point"}
}