{
  "type": "Feature",
  "properties": {
    "iso:country":"NL",
    "sg:address":"Paramasiebaan 17",
    "sg:city":"Ameide",
    "sg:orig_category":"Overheidsdiensten",
    "sg:phone":"+31 183 601 557",
    "sg:postcode":"4233 EX",
    "sg:province":"Zuid-Holland",
    "wof:name":"Het Spant",
    "wof:placetype":"venue"
},
  "geometry": {"coordinates":[4.9618620872,51.9551277161],"type":"Point"}
}