{
  "type": "Feature",
  "properties": {
    "iso:country":"NL",
    "sg:address":"Brasemstr 22",
    "sg:city":"Almere",
    "sg:orig_category":"Evenementenverzorging",
    "sg:phone":"+31 36 534 3190",
    "sg:postcode":"1317 PX",
    "sg:province":"Flevoland",
    "sg:website":"http://www.COR-Events.nl",
    "wof:name":"Cor-Events",
    "wof:placetype":"venue"
},
  "geometry": {"coordinates":[5.231149,52.392467],"type":"Point"}
}