{
  "type": "Feature",
  "properties": {
    "addr:full":"Kamgarenpln 54 Tilburg Noord-Brabant 5046 RE",
    "addr:housenumber":"54",
    "addr:postcode":"5046 re",
    "addr:street":"Kamgarenpln",
    "iso:country":"NL",
    "sg:address":"Kamgarenpln 54",
    "sg:city":"Tilburg",
    "sg:orig_category":"Autorijscholen",
    "sg:phone":"+31 13 535 6582",
    "sg:postcode":"5046 RE",
    "sg:province":"Noord-Brabant",
    "wof:name":"Desmares, Twan",
    "wof:placetype":"venue"
},
  "geometry": {"coordinates":[5.07546,51.575687],"type":"Point"}
}