{
  "type": "Feature",
  "properties": {
    "addr:full":"Strienemonde 11 Oud Beyerland Zuid-Holland 3261 VC",
    "addr:housenumber":"11",
    "addr:postcode":"3261 vc",
    "addr:street":"Strienemonde;Oud Beyerland",
    "iso:country":"NL",
    "sg:address":"Strienemonde 11",
    "sg:city":"Oud Beyerland",
    "sg:orig_category":"Glazenwasserijen",
    "sg:phone":"+31 186 618 600",
    "sg:postcode":"3261 VC",
    "sg:province":"Zuid-Holland",
    "wof:name":"Koopman, M",
    "wof:placetype":"venue"
},
  "geometry": {"coordinates":[4.421982,51.82563],"type":"Point"}
}