{
  "type": "Feature",
  "properties": {
    "addr:full":"Regentesselaan 30 Haarlem North Holland 2015 BZ",
    "addr:housenumber":"30",
    "addr:postcode":"2015 bz",
    "addr:street":"Regentesselaan",
    "iso:country":"NL",
    "sg:address":"Regentesselaan 30",
    "sg:city":"Haarlem",
    "sg:orig_category":"Bedrijfs- And Managementsconsultants",
    "sg:phone":"+31 23 534 1489",
    "sg:postcode":"2015 BZ",
    "sg:province":"North Holland",
    "wof:name":"Adviesbureau Van Breemen En Partner Bv",
    "wof:placetype":"venue"
},
  "geometry": {"coordinates":[4.6195240021,52.3879013062],"type":"Point"}
}