{
  "type": "Feature",
  "properties": {
    "addr:full":"H Dullaertpln 34 Rotterdam Zuid-Holland 3024 CC",
    "addr:housenumber":"34",
    "addr:postcode":"3024 cc",
    "iso:country":"NL",
    "sg:address":"H Dullaertpln 34",
    "sg:city":"Rotterdam",
    "sg:orig_category":"Kappers",
    "sg:phone":"+31 10 476 2334",
    "sg:postcode":"3024 CC",
    "sg:province":"Zuid-Holland",
    "wof:name":"Jorika",
    "wof:placetype":"venue"
},
  "geometry": {"coordinates":[4.4553780556,51.9051971436],"type":"Point"}
}