{
  "type": "Feature",
  "properties": {
    "iso:country":"NL",
    "sg:address":"Naaldwyksewg 29",
    "sg:city":"Wateringen",
    "sg:orig_category":"Verhuur",
    "sg:phone":"+31 6 54692818",
    "sg:postcode":"2291 PA",
    "sg:province":"Zuid-Holland",
    "wof:name":"Tv Telescoopverhuur",
    "wof:placetype":"venue"
},
  "geometry": {"coordinates":[4.2735,52.023331],"type":"Point"}
}