{
  "type": "Feature",
  "properties": {
    "addr:full":"Julianastr 47 Rhoon Zuid-Holland 3161 AJ",
    "addr:housenumber":"47",
    "addr:postcode":"3161 aj",
    "addr:street":"Julianastr",
    "iso:country":"NL",
    "sg:address":"Julianastr 47",
    "sg:city":"Rhoon",
    "sg:orig_category":"Bloemen En Planten",
    "sg:phone":"+31 10 501 5969",
    "sg:postcode":"3161 AJ",
    "sg:province":"Zuid-Holland",
    "sg:website":"http://www.myosoticbloemen.nl",
    "wof:name":"Myosotis",
    "wof:placetype":"venue"
},
  "geometry": {"coordinates":[4.418554,51.856426],"type":"Point"}
}