{
  "type": "Feature",
  "properties": {
    "addr:full":"De Bleek 1 Woerden Utrecht 3447 GV",
    "addr:housenumber":"1",
    "addr:postcode":"3447 gv",
    "addr:street":"De Bleek",
    "iso:country":"NL",
    "sg:address":"De Bleek 1",
    "sg:city":"Woerden",
    "sg:orig_category":"Bedrijfsopleidingen",
    "sg:phone":"+31 348 429 933",
    "sg:postcode":"3447 GV",
    "sg:province":"Utrecht",
    "wof:name":"Sod",
    "wof:placetype":"venue"
},
  "geometry": {"coordinates":[4.888263,52.078171],"type":"Point"}
}