{
  "type": "Feature",
  "properties": {
    "iso:country":"NL",
    "sg:address":"Postbus 8203",
    "sg:city":"Utrecht",
    "sg:orig_category":"Verenigingen En Stichtingen",
    "sg:phone":"+31 30 298 5222",
    "sg:postcode":"3503 RE",
    "sg:province":"Utrecht",
    "sg:website":"http://www.fondsenzw.nl",
    "wof:name":"Sectorfondsen Zorg En Welzijn",
    "wof:placetype":"venue"
},
  "geometry": {"coordinates":[5.1154,52.088928],"type":"Point"}
}