{
  "type": "Feature",
  "properties": {
    "addr:full":"Nw Kerkstr 4 Rotterdam Zuid-Holland 3054 NJ",
    "addr:housenumber":"4",
    "addr:postcode":"3054 nj",
    "addr:street":"Kerkstr",
    "iso:country":"NL",
    "sg:address":"Nw Kerkstr 4",
    "sg:city":"Rotterdam",
    "sg:orig_category":"Herenkleding",
    "sg:phone":"+31 10 265 0014",
    "sg:postcode":"3054 NJ",
    "sg:province":"Zuid-Holland",
    "sg:website":"http://www.amatoclothing.nl",
    "wof:name":"Amato",
    "wof:placetype":"venue"
},
  "geometry": {"coordinates":[4.493362,51.957443],"type":"Point"}
}