{
  "type": "Feature",
  "properties": {
    "addr:full":"A Pauwstr 15 Wassenaar Zuid-Holland 2242 LS",
    "addr:housenumber":"15",
    "addr:postcode":"2242 ls",
    "iso:country":"NL",
    "sg:address":"A Pauwstr 15",
    "sg:city":"Wassenaar",
    "sg:classifiers":[
        {
            "category":"Retail",
            "subcategory":"Auto Repair",
            "type":"Services"
        }
    ],
    "sg:phone":"+31 70 511 2603",
    "sg:postcode":"2242 LS",
    "sg:province":"Zuid-Holland",
    "sg:tags":[
        "garage"
    ],
    "wof:name":"Korbee, M",
    "wof:placetype":"venue"
},
  "geometry": {"coordinates":[4.400499,52.144375],"type":"Point"}
}