{
  "type": "Feature",
  "properties": {
    "addr:full":"Grootzand 25 Sneek Friesland 8601 AR",
    "addr:housenumber":"25",
    "addr:postcode":"8601",
    "addr:street":"Grootzand",
    "iso:country":"NL",
    "sg:address":"Grootzand 25",
    "sg:city":"Sneek",
    "sg:orig_category":"Farmaceutische Producten Gh",
    "sg:phone":"+31 515 426 970",
    "sg:postcode":"8601 AR",
    "sg:province":"Friesland",
    "wof:name":"Geschenkenwinkel Happy Day",
    "wof:placetype":"venue"
},
  "geometry": {"coordinates":[5.660869,53.031532],"type":"Point"}
}