{
  "type": "Feature",
  "properties": {
    "addr:full":"Pontanusstr 255 Amsterdam Noord-Holland 1093 SH",
    "addr:housenumber":"255;1093",
    "addr:postcode":"sh",
    "iso:country":"NL",
    "sg:address":"Pontanusstr 255",
    "sg:city":"Amsterdam",
    "sg:orig_category":"Architecten En Architectenbureaus",
    "sg:phone":"+31 20 463 5638",
    "sg:postcode":"1093 SH",
    "sg:province":"Noord-Holland",
    "wof:name":"Abraham Berkenpas",
    "wof:placetype":"venue"
},
  "geometry": {"coordinates":[4.930413,52.361748],"type":"Point"}
}