{
  "type": "Feature",
  "properties": {
    "iso:country":"NL",
    "sg:address":"Greate Pierwei 50",
    "sg:city":"Kimswerd",
    "sg:orig_category":"Fruit And Groenten Gh",
    "sg:phone":"+31 517 642 209",
    "sg:postcode":"8821 LW",
    "sg:province":"Provincie Friesland",
    "wof:name":"B.P. De Vries En Zonen Bv",
    "wof:placetype":"venue"
},
  "geometry": {"coordinates":[5.45572,53.136841],"type":"Point"}
}