{
  "type": "Feature",
  "properties": {
    "addr:full":"Sliffertsestr 354 Eindhoven Noord-Brabant 5657 AS",
    "addr:housenumber":"354",
    "addr:postcode":"5657 as",
    "iso:country":"NL",
    "sg:address":"Sliffertsestr 354",
    "sg:city":"Eindhoven",
    "sg:orig_category":"Open Haarden",
    "sg:phone":"+31 40 253 1863",
    "sg:postcode":"5657 AS",
    "sg:province":"Noord-Brabant",
    "wof:name":"Henk Kanen",
    "wof:placetype":"venue"
},
  "geometry": {"coordinates":[5.425029,51.433159],"type":"Point"}
}