{
  "type": "Feature",
  "properties": {
    "addr:full":"Middenstraat 20 Sluiskil Zeeland 4541 AD",
    "addr:housenumber":"20",
    "addr:postcode":"4541 ad",
    "addr:street":"Middenstraat",
    "iso:country":"NL",
    "sg:address":"Middenstraat 20",
    "sg:city":"Sluiskil",
    "sg:orig_category":"Zalenexploitatie",
    "sg:phone":"+31 115 471 410",
    "sg:postcode":"4541 AD",
    "sg:province":"Zeeland",
    "wof:name":"Jeanne Munsterman",
    "wof:placetype":"venue"
},
  "geometry": {"coordinates":[3.838262,51.280224],"type":"Point"}
}