{
  "type": "Feature",
  "properties": {
    "addr:full":"Westhavenplaats 37 Vlaardingen Zuid-Holland 3131 BT",
    "addr:housenumber":"37",
    "addr:postcode":"3131 bt",
    "addr:street":"Westhavenplaats",
    "iso:country":"NL",
    "sg:address":"Westhavenplaats 37",
    "sg:city":"Vlaardingen",
    "sg:orig_category":"Bloemen And Planten",
    "sg:phone":"+31 10 435 9899",
    "sg:postcode":"3131 BT",
    "sg:province":"Zuid-Holland",
    "wof:name":"Bloemenpaviljoen De Visbank Bloemsierkun",
    "wof:placetype":"venue"
},
  "geometry": {"coordinates":[4.343871,51.909069],"type":"Point"}
}