{
  "type": "Feature",
  "properties": {
    "addr:full":"Zeeweg 60 Huizen Noord-Holland 1271 VZ",
    "addr:housenumber":"60",
    "addr:postcode":"1271 vz",
    "addr:street":"Zeeweg",
    "iso:country":"NL",
    "sg:address":"Zeeweg 60",
    "sg:city":"Huizen",
    "sg:orig_category":"Binnenhuisarchitecten",
    "sg:phone":"+31 35 525 7262",
    "sg:postcode":"1271 VZ",
    "sg:province":"Noord-Holland",
    "wof:name":"Jeroen Binnekade Interieur & Tuintechniek",
    "wof:placetype":"venue"
},
  "geometry": {"coordinates":[5.232101,52.302113],"type":"Point"}
}