{
  "type": "Feature",
  "properties": {
    "addr:full":"Grevenbroekstraat 11 Kessel Lb Limburg 5995 CK",
    "addr:housenumber":"11",
    "addr:postcode":"lb;5995 ck",
    "addr:street":"Grevenbroekstraat",
    "iso:country":"NL",
    "sg:address":"Grevenbroekstraat 11",
    "sg:city":"Kessel Lb",
    "sg:orig_category":"Schoonheidssalons",
    "sg:phone":"+31 77 462 2913",
    "sg:postcode":"5995 CK",
    "sg:province":"Limburg",
    "wof:name":"Marlies",
    "wof:placetype":"venue"
},
  "geometry": {"coordinates":[6.052297,51.294621],"type":"Point"}
}