{
  "type": "Feature",
  "properties": {
    "addr:full":"F Elsingastr 38 Rotterdam South Holland 3067 NW",
    "addr:housenumber":"38",
    "addr:postcode":"3067 nw",
    "iso:country":"NL",
    "sg:address":"F Elsingastr 38",
    "sg:city":"Rotterdam",
    "sg:orig_category":"Woningbouw- Verenigingen En -Stichtingen",
    "sg:phone":"+31 10 286 6350",
    "sg:postcode":"3067 NW",
    "sg:province":"South Holland",
    "wof:name":"Nieuwe Unie, De",
    "wof:placetype":"venue"
},
  "geometry": {"coordinates":[4.5442490578,51.939868927],"type":"Point"}
}