{
  "type": "Feature",
  "properties": {
    "addr:full":"Pannekeetwg 19 Heerhugowaard Noord-Holland 1704 PL",
    "addr:housenumber":"19",
    "addr:postcode":"1704 pl",
    "addr:street":"Pannekeetwg",
    "iso:country":"NL",
    "sg:address":"Pannekeetwg 19",
    "sg:city":"Heerhugowaard",
    "sg:orig_category":"On- Offshore",
    "sg:phone":"+31 72 564 6800",
    "sg:postcode":"1704 PL",
    "sg:province":"Noord-Holland",
    "wof:name":"Smith Bits",
    "wof:placetype":"venue"
},
  "geometry": {"coordinates":[4.828996,52.694794],"type":"Point"}
}