{
  "type": "Feature",
  "properties": {
    "iso:country":"NL",
    "sg:address":"Dorpsstr 589",
    "sg:city":"Noord Scharwoude",
    "sg:orig_category":"Wereldwinkels",
    "sg:phone":"+31 226 321 381",
    "sg:postcode":"1723 HB",
    "sg:province":"Noord-Holland",
    "wof:name":"Wereldwinkel Langedijk",
    "wof:placetype":"venue"
},
  "geometry": {"coordinates":[4.8108491898,52.7022857666],"type":"Point"}
}