{
  "type": "Feature",
  "properties": {
    "addr:full":"Karstraat 1 Zaltbommel Gelderland 5301 BP",
    "addr:housenumber":"1",
    "addr:postcode":"5301 bp",
    "addr:street":"Karstraat;Gelderland",
    "iso:country":"NL",
    "sg:address":"Karstraat 1",
    "sg:city":"Zaltbommel",
    "sg:orig_category":"Goederenvervoer Over De Weg",
    "sg:phone":"+31 418 540 704",
    "sg:postcode":"5301 BP",
    "sg:province":"Gelderland",
    "wof:name":"M.G. Van Zandwijk",
    "wof:placetype":"venue"
},
  "geometry": {"coordinates":[5.245311,51.81284],"type":"Point"}
}