{
  "type": "Feature",
  "properties": {
    "iso:country":"NL",
    "sg:address":"Spakenburgsestr 48",
    "sg:city":"S Gravenhage",
    "sg:orig_category":"Verzekeringen - Verzekeringskantoren",
    "sg:phone":"+31 70 323 0730",
    "sg:postcode":"2574 JW",
    "sg:province":"South Holland",
    "wof:name":"Scherf, P M W",
    "wof:placetype":"venue"
},
  "geometry": {"coordinates":[4.277523,52.064205],"type":"Point"}
}