{
  "type": "Feature",
  "properties": {
    "addr:full":"Parallelwg 9 Bussum Noord-Holland 1405 AE",
    "addr:housenumber":"9",
    "addr:postcode":"1405 ae",
    "addr:street":"Parallelwg",
    "iso:country":"NL",
    "sg:address":"Parallelwg 9",
    "sg:city":"Bussum",
    "sg:orig_category":"Adviesbureaus Bedrijfsorganisatie",
    "sg:phone":"+31 35 694 0306",
    "sg:postcode":"1405 AE",
    "sg:province":"Noord-Holland",
    "wof:name":"In-Match",
    "wof:placetype":"venue"
},
  "geometry": {"coordinates":[5.156263,52.28027],"type":"Point"}
}