{
  "type": "Feature",
  "properties": {
    "addr:full":"Ronde Hil 21 Breda Noord-Brabant 4822 AJ",
    "addr:housenumber":"21",
    "addr:postcode":"4822 aj",
    "addr:street":"Ronde Hil",
    "iso:country":"NL",
    "sg:address":"Ronde Hil 21",
    "sg:city":"Breda",
    "sg:orig_category":"Administratie- En Boekhoudkantoren",
    "sg:phone":"+31 76 541 9281",
    "sg:postcode":"4822 AJ",
    "sg:province":"Noord-Brabant",
    "wof:name":"Kunst",
    "wof:placetype":"venue"
},
  "geometry": {"coordinates":[4.742251,51.619904],"type":"Point"}
}