{
  "type": "Feature",
  "properties": {
    "iso:country":"NL",
    "sg:address":"Nyverheidswg 11",
    "sg:city":"Mydrecht",
    "sg:orig_category":"Dierenvoeder - Fabrieken",
    "sg:phone":"+31 297 280 700",
    "sg:postcode":"3641 RP",
    "sg:province":"Utrecht",
    "wof:name":"Tentego Bv",
    "wof:placetype":"venue"
},
  "geometry": {"coordinates":[4.86178,52.20578],"type":"Point"}
}