{
  "type": "Feature",
  "properties": {
    "iso:country":"NL",
    "sg:address":"Burgemeester Mooijstraat 27",
    "sg:city":"Castricum",
    "sg:classifiers":[
        {
            "category":"Retail",
            "subcategory":"Photofinishing",
            "type":"Services"
        }
    ],
    "sg:phone":"+31 251 650 960",
    "sg:postcode":"1901 ER",
    "sg:province":"North Holland",
    "sg:tags":[
        "foto",
        "film"
    ],
    "wof:name":"Vof Combi Loek Anderson",
    "wof:placetype":"venue"
},
  "geometry": {"coordinates":[4.660059,52.546562],"type":"Point"}
}