{
  "type": "Feature",
  "properties": {
    "iso:country":"NL",
    "sg:address":"H K Onneswg 22",
    "sg:city":"Alphen Aan Den Ryn",
    "sg:orig_category":"Houtbewerking",
    "sg:phone":"+31 172 477 038",
    "sg:postcode":"2408 AW",
    "sg:province":"South Holland",
    "wof:name":"Blom Bv, Jac",
    "wof:placetype":"venue"
},
  "geometry": {"coordinates":[4.647202,52.129128],"type":"Point"}
}