{
  "type": "Feature",
  "properties": {
    "iso:country":"NL",
    "sg:address":"Kerkwg 57",
    "sg:city":"Leek",
    "sg:orig_category":"Oldtimers",
    "sg:phone":"+31 594 519 468",
    "sg:postcode":"9351 AK",
    "sg:province":"Groningen",
    "sg:website":"http://www.brove.nl",
    "wof:name":"Brov?",
    "wof:placetype":"venue"
},
  "geometry": {"coordinates":[6.385711,53.156853],"type":"Point"}
}