{
  "type": "Feature",
  "properties": {
    "addr:full":"Hippolytusbuurt 22 Delft Zuid-Holland 2611 HN",
    "addr:housenumber":"22",
    "addr:postcode":"2611 hn",
    "addr:street":"Hippolytusbuurt",
    "iso:country":"NL",
    "sg:address":"Hippolytusbuurt 22",
    "sg:city":"Delft",
    "sg:orig_category":"Werving And Selectie Van Tijdelijk Personeel And Uitzendkantoren",
    "sg:phone":"+31 15 214 7341",
    "sg:postcode":"2611 HN",
    "sg:province":"Zuid-Holland",
    "wof:name":"Uitzendbureau Start",
    "wof:placetype":"venue"
},
  "geometry": {"coordinates":[4.3571891785,52.0124816895],"type":"Point"}
}