{
  "type": "Feature",
  "properties": {
    "iso:country":"NL",
    "sg:address":"Hulsenwg 22",
    "sg:city":"Nederweert",
    "sg:orig_category":"Hek- En Rasterwerken",
    "sg:phone":"+31 495 632 103",
    "sg:postcode":"6031 SP",
    "sg:province":"Limburg",
    "sg:website":"http://www.raco-hekwerken.nl",
    "wof:name":"Raco Hekwerken",
    "wof:placetype":"venue"
},
  "geometry": {"coordinates":[5.7571,51.2812],"type":"Point"}
}