{
  "type": "Feature",
  "properties": {
    "addr:full":"Noord 223 Noordscheschut Provincie Drenthe 7914 PX",
    "addr:housenumber":"223",
    "addr:postcode":"7914 px",
    "addr:street":"Noord;Provincie Drenthe",
    "iso:country":"NL",
    "sg:address":"Noord 223",
    "sg:city":"Noordscheschut",
    "sg:orig_category":"Kantoor- En Interieurbeplanting",
    "sg:phone":"+31 528 266 249",
    "sg:postcode":"7914 PX",
    "sg:province":"Provincie Drenthe",
    "wof:name":"Orion Vof",
    "wof:placetype":"venue"
},
  "geometry": {"coordinates":[6.5348501205,52.7244987488],"type":"Point"}
}