{
  "type": "Feature",
  "properties": {
    "addr:full":"Slaak 86 Rotterdam Zuid-Holland 3061 CZ",
    "addr:housenumber":"86",
    "addr:postcode":"3061",
    "addr:street":"Slaak",
    "iso:country":"NL",
    "sg:address":"Slaak 86",
    "sg:city":"Rotterdam",
    "sg:orig_category":"Autorijscholen",
    "sg:phone":"+31 10 412 4020",
    "sg:postcode":"3061 CZ",
    "sg:province":"Zuid-Holland",
    "sg:website":"http://www.verkeersschoolhaan.nl",
    "wof:name":"Haan Auto- Aanhangwagen- En Motorrijschool",
    "wof:placetype":"venue"
},
  "geometry": {"coordinates":[4.49888,51.924023],"type":"Point"}
}