{
  "type": "Feature",
  "properties": {
    "addr:full":"Nieuwstr 41 Deventer Overijssel 7411 LG",
    "addr:housenumber":"41",
    "addr:postcode":"7411 lg",
    "addr:street":"Nieuwstr",
    "iso:country":"NL",
    "sg:address":"Nieuwstr 41",
    "sg:city":"Deventer",
    "sg:classifiers":[
        {
            "category":"Travel",
            "subcategory":"Hotels & Motels",
            "type":"Entertainment"
        }
    ],
    "sg:phone":"+31 570 641 846",
    "sg:postcode":"7411 LG",
    "sg:province":"Overijssel",
    "sg:website":"http://www.gilde-hotel.nl",
    "wof:name":"Gilde Bv, 'T",
    "wof:placetype":"venue"
},
  "geometry": {"coordinates":[6.159899,52.251034],"type":"Point"}
}