{
  "type": "Feature",
  "properties": {
    "addr:full":"Wanraaij 21 Andelst Gelderland 6673 DM",
    "addr:housenumber":"21",
    "addr:postcode":"6673 dm",
    "addr:street":"Wanraaij;Gelderland",
    "iso:country":"NL",
    "sg:address":"Wanraaij 21",
    "sg:city":"Andelst",
    "sg:classifiers":[
        {
            "category":"Food & Beverages",
            "subcategory":"Fruits & Vegetables",
            "type":"Retail Goods"
        }
    ],
    "sg:phone":"+31 488 473 310",
    "sg:postcode":"6673 DM",
    "sg:province":"Gelderland",
    "sg:tags":[
        "groenten"
    ],
    "wof:name":"Van Dijk Wessels",
    "wof:placetype":"venue"
},
  "geometry": {"coordinates":[5.718954,51.913528],"type":"Point"}
}