{
  "type": "Feature",
  "properties": {
    "addr:full":"Oegstgeesterwg 241 Rynsburg Zuid-Holland 2231 AV",
    "addr:housenumber":"241",
    "addr:postcode":"2231 av",
    "addr:street":"Rynsburg",
    "iso:country":"NL",
    "sg:address":"Oegstgeesterwg 241",
    "sg:city":"Rynsburg",
    "sg:orig_category":"Administratie- En Boekhoudkantoren",
    "sg:phone":"+31 71 402 0219",
    "sg:postcode":"2231 AV",
    "sg:province":"Zuid-Holland",
    "wof:name":"Heemskerk, J C",
    "wof:placetype":"venue"
},
  "geometry": {"coordinates":[4.451644,52.192299],"type":"Point"}
}