{
  "type": "Feature",
  "properties": {
    "addr:full":"Kleingouw 122 Andijk Noord-Holland 1619 CJ",
    "addr:housenumber":"122",
    "addr:postcode":"1619 cj",
    "addr:street":"Kleingouw",
    "iso:country":"NL",
    "sg:address":"Kleingouw 122",
    "sg:city":"Andijk",
    "sg:orig_category":"Bedrijfs- And Managementsconsultants",
    "sg:phone":"+31 228 597 590",
    "sg:postcode":"1619 CJ",
    "sg:province":"Noord-Holland",
    "wof:name":"A. Roggeveen Management Bv",
    "wof:placetype":"venue"
},
  "geometry": {"coordinates":[5.195333,52.739655],"type":"Point"}
}