{
  "type": "Feature",
  "properties": {
    "addr:full":"Hoefstr 1 Tilburg Noord-Brabant 5046 BA",
    "addr:housenumber":"1",
    "addr:postcode":"5046 ba",
    "addr:street":"Hoefstr",
    "iso:country":"NL",
    "sg:address":"Hoefstr 1",
    "sg:city":"Tilburg",
    "sg:orig_category":"Gordijnen",
    "sg:phone":"+31 13 542 7926",
    "sg:postcode":"5046 BA",
    "sg:province":"Noord-Brabant",
    "wof:name":"Schmitz-Engelen",
    "wof:placetype":"venue"
},
  "geometry": {"coordinates":[5.08502,51.57579],"type":"Point"}
}