{
  "type": "Feature",
  "properties": {
    "addr:full":"Zyde 155 Boskoop Zuid-Holland 2771 EV",
    "addr:housenumber":"155",
    "iso:country":"NL",
    "sg:address":"Zyde 155",
    "sg:city":"Boskoop",
    "sg:orig_category":"Bloemen En Planten",
    "sg:phone":"+31 172 212 120",
    "sg:postcode":"2771 EV",
    "sg:province":"Zuid-Holland",
    "wof:name":"Spek Bv, Jan",
    "wof:placetype":"venue"
},
  "geometry": {"coordinates":[4.639183,52.075874],"type":"Point"}
}