{
  "type": "Feature",
  "properties": {
    "iso:country":"NL",
    "sg:address":"Holendrechtpln 30",
    "sg:city":"Amsterdam Zuidoost",
    "sg:orig_category":"Kappers",
    "sg:phone":"+31 20 697 5227",
    "sg:postcode":"1106 LP",
    "sg:province":"North Holland",
    "wof:name":"Horst, Marion Van Der",
    "wof:placetype":"venue"
},
  "geometry": {"coordinates":[4.9649238586,52.3000335693],"type":"Point"}
}