{
  "type": "Feature",
  "properties": {
    "addr:full":"Vuurdoorn 9 Naaldwyk South Holland 2671 NM",
    "addr:housenumber":"9",
    "addr:postcode":"2671",
    "addr:street":"Vuurdoorn",
    "iso:country":"NL",
    "sg:address":"Vuurdoorn 9",
    "sg:city":"Naaldwyk",
    "sg:orig_category":"Metselwerken",
    "sg:phone":"+31 174 623 507",
    "sg:postcode":"2671 NM",
    "sg:province":"South Holland",
    "wof:name":"Bram Meijer",
    "wof:placetype":"venue"
},
  "geometry": {"coordinates":[4.195609,51.991348],"type":"Point"}
}