{
  "type": "Feature",
  "properties": {
    "addr:full":"Carnegiedreef 20 Utrecht Utrecht 3563 AA",
    "addr:housenumber":"20",
    "addr:postcode":"3563 aa",
    "addr:street":"Carnegiedreef",
    "iso:country":"NL",
    "sg:address":"Carnegiedreef 20",
    "sg:city":"Utrecht",
    "sg:orig_category":"Apotheken",
    "sg:phone":"+31 30 261 7341",
    "sg:postcode":"3563 AA",
    "sg:province":"Utrecht",
    "wof:name":"Lusse Bv Apotheek",
    "wof:placetype":"venue"
},
  "geometry": {"coordinates":[5.108755,52.117268],"type":"Point"}
}