{
  "type": "Feature",
  "properties": {
    "addr:full":"Herenweg 93 Rijnsaterwoude Zuid-Holland 2465 AD",
    "addr:housenumber":"93",
    "addr:postcode":"2465 ad",
    "addr:street":"Herenweg",
    "iso:country":"NL",
    "sg:address":"Herenweg 93",
    "sg:city":"Rijnsaterwoude",
    "sg:orig_category":"Landbouwmachines Gh",
    "sg:phone":"+31 172 508 217",
    "sg:postcode":"2465 AD",
    "sg:province":"Zuid-Holland",
    "wof:name":"Firma J. Van Iperen En Zn.",
    "wof:placetype":"venue"
},
  "geometry": {"coordinates":[4.671365,52.196033],"type":"Point"}
}