{
  "type": "Feature",
  "properties": {
    "addr:full":"Gentiaan 13 Boskoop Zuid-Holland 2771 SL",
    "addr:housenumber":"13",
    "addr:postcode":"2771 sl",
    "addr:street":"Gentiaan",
    "iso:country":"NL",
    "sg:address":"Gentiaan 13",
    "sg:city":"Boskoop",
    "sg:classifiers":[
        {
            "category":"Professional",
            "subcategory":"Accounting & Tax Preparation",
            "type":"Services"
        }
    ],
    "sg:phone":"+31 172 230 875",
    "sg:postcode":"2771 SL",
    "sg:province":"Zuid-Holland",
    "sg:tags":[
        "accountant"
    ],
    "wof:name":"C M Kroes Praktijk Bv",
    "wof:placetype":"venue"
},
  "geometry": {"coordinates":[4.640897,52.071636],"type":"Point"}
}