{
  "type": "Feature",
  "properties": {
    "addr:full":"Hoofdstr 82 Veenendaal Utrecht 3901 AV",
    "addr:housenumber":"82",
    "addr:postcode":"3901 av",
    "addr:street":"Hoofdstr",
    "iso:country":"NL",
    "sg:address":"Hoofdstr 82",
    "sg:city":"Veenendaal",
    "sg:orig_category":"Herenkleding",
    "sg:phone":"+31 318 555 756",
    "sg:postcode":"3901 AV",
    "sg:province":"Utrecht",
    "wof:name":"Collexi Items",
    "wof:placetype":"venue"
},
  "geometry": {"coordinates":[5.55671,52.027958],"type":"Point"}
}