{
  "type": "Feature",
  "properties": {
    "iso:country":"NL",
    "sg:address":"Fjellingsreed 6",
    "sg:city":"Engwierum",
    "sg:orig_category":"Psychosociale Therapeuten",
    "sg:phone":"+31 519 518 581",
    "sg:postcode":"9132 EN",
    "sg:province":"Provincie Friesland",
    "wof:name":"Noach, Sticht",
    "wof:placetype":"venue"
},
  "geometry": {"coordinates":[6.125938,53.331238],"type":"Point"}
}