{
  "type": "Feature",
  "properties": {
    "addr:full":"De Poort 42 Houten Utrecht 3991 DV",
    "addr:housenumber":"42",
    "addr:postcode":"3991 dv",
    "addr:street":"De Poort",
    "iso:country":"NL",
    "sg:address":"De Poort 42",
    "sg:city":"Houten",
    "sg:orig_category":"Boekhandels",
    "sg:phone":"+31 30 639 4041",
    "sg:postcode":"3991 DV",
    "sg:province":"Utrecht",
    "sg:website":"http://www.boekenmeer.nl",
    "wof:name":"Bgn",
    "wof:placetype":"venue"
},
  "geometry": {"coordinates":[5.156901,52.028736],"type":"Point"}
}