{
  "type": "Feature",
  "properties": {
    "addr:full":"Europawg 33 Hardenberg Overijssel 7772 BN",
    "addr:housenumber":"33",
    "addr:postcode":"7772 bn",
    "addr:street":"Europawg",
    "iso:country":"NL",
    "sg:address":"Europawg 33",
    "sg:city":"Hardenberg",
    "sg:orig_category":"Behangselpapier En Wandbekleding",
    "sg:phone":"+31 523 261 035",
    "sg:postcode":"7772 BN",
    "sg:province":"Overijssel",
    "sg:website":"http://www.joopkistbehang.nl",
    "wof:name":"Kist, Joop",
    "wof:placetype":"venue"
},
  "geometry": {"coordinates":[6.616543,52.573181],"type":"Point"}
}