{
  "type": "Feature",
  "properties": {
    "addr:full":"Kevelaar 4 Oosterhout Nb Noord-Brabant 4907 KW",
    "addr:housenumber":"4",
    "addr:postcode":"4907 kw",
    "addr:street":"Kevelaar",
    "iso:country":"NL",
    "sg:address":"Kevelaar 4",
    "sg:city":"Oosterhout Nb",
    "sg:orig_category":"Scholen Voor Basisonderwijs",
    "sg:phone":"+31 162 431 375",
    "sg:postcode":"4907 KW",
    "sg:province":"Noord-Brabant",
    "wof:name":"Berkenhof Rk, De",
    "wof:placetype":"venue"
},
  "geometry": {"coordinates":[4.867462,51.659946],"type":"Point"}
}