{
  "type": "Feature",
  "properties": {
    "addr:full":"Vossenbergseln 36 Kaatsheuvel Noord-Brabant 5171 CD",
    "addr:housenumber":"36",
    "addr:postcode":"5171 cd",
    "addr:street":"Vossenbergseln",
    "iso:country":"NL",
    "sg:address":"Vossenbergseln 36",
    "sg:city":"Kaatsheuvel",
    "sg:orig_category":"Podotherapeuten",
    "sg:phone":"+31 416 530 259",
    "sg:postcode":"5171 CD",
    "sg:province":"Noord-Brabant",
    "wof:name":"Eerden, W V/D",
    "wof:placetype":"venue"
},
  "geometry": {"coordinates":[5.023302,51.660889],"type":"Point"}
}