{
  "type": "Feature",
  "properties": {
    "iso:country":"NL",
    "sg:address":"De Oude Veiling 102",
    "sg:city":"Zwaag",
    "sg:classifiers":[
        {
            "category":"Retail",
            "subcategory":"Auto Repair",
            "type":"Services"
        }
    ],
    "sg:phone":"+31 229 249 461",
    "sg:postcode":"1689 AD",
    "sg:province":"North Holland",
    "sg:tags":[
        "garage"
    ],
    "sg:website":"http://www.guus-hamers.nl",
    "wof:name":"Guus Hamers Autobedrijf",
    "wof:placetype":"venue"
},
  "geometry": {"coordinates":[5.063266,52.661407],"type":"Point"}
}