{
  "type": "Feature",
  "properties": {
    "addr:full":"B Kooymanstr 19 Oud Vossemeer Zeeland 4698 AL",
    "addr:housenumber":"19",
    "addr:postcode":"4698 al",
    "iso:country":"NL",
    "sg:address":"B Kooymanstr 19",
    "sg:city":"Oud Vossemeer",
    "sg:orig_category":"Verenigingsgebouwen",
    "sg:phone":"+31 166 672 737",
    "sg:postcode":"4698 AL",
    "sg:province":"Zeeland",
    "wof:name":"Bahnerth, J C E",
    "wof:placetype":"venue"
},
  "geometry": {"coordinates":[4.195637,51.570213],"type":"Point"}
}