{
  "type": "Feature",
  "properties": {
    "addr:full":"Hengelosestraat 545 Enschede Overijssel 7521 AG",
    "addr:housenumber":"545",
    "addr:postcode":"7521",
    "addr:street":"Hengelosestraat",
    "iso:country":"NL",
    "sg:address":"Hengelosestraat 545",
    "sg:city":"Enschede",
    "sg:orig_category":"Juridische Dienstverlening",
    "sg:phone":"+31 53 431 9722",
    "sg:postcode":"7521 AG",
    "sg:province":"Overijssel",
    "wof:name":"Arnold En Siedsma Octrooigemachtigden",
    "wof:placetype":"venue"
},
  "geometry": {"coordinates":[6.853831,52.236183],"type":"Point"}
}