{
  "type": "Feature",
  "properties": {
    "addr:full":"Elisabethhof 21 Leiderdorp Zuid-Holland 2353 EW",
    "addr:housenumber":"21",
    "addr:postcode":"2353 ew",
    "addr:street":"Elisabethhof",
    "iso:country":"NL",
    "sg:address":"Elisabethhof 21",
    "sg:city":"Leiderdorp",
    "sg:orig_category":"Diverse Bedrijfsinstallaties Gh",
    "sg:phone":"+31 71 589 6956",
    "sg:postcode":"2353 EW",
    "sg:province":"Zuid-Holland",
    "wof:name":"Bis Both Industrial Services Bv",
    "wof:placetype":"venue"
},
  "geometry": {"coordinates":[4.546675,52.159554],"type":"Point"}
}