{
  "type": "Feature",
  "properties": {
    "addr:full":"Molenstraat 20 Herwen Gelderland 6914 AC",
    "addr:housenumber":"20",
    "addr:postcode":"6914 ac",
    "addr:street":"Molenstraat;Gelderland",
    "iso:country":"NL",
    "sg:address":"Molenstraat 20",
    "sg:city":"Herwen",
    "sg:classifiers":[
        {
            "category":"Fast Food",
            "type":"Food & Drink"
        }
    ],
    "sg:phone":"+31 316 248 787",
    "sg:postcode":"6914 AC",
    "sg:province":"Gelderland",
    "sg:tags":[
        "afhaal",
        "restaurant"
    ],
    "wof:name":"Vof 'T Hoekje",
    "wof:placetype":"venue"
},
  "geometry": {"coordinates":[6.097632,51.883369],"type":"Point"}
}