{
  "type": "Feature",
  "properties": {
    "iso:country":"NL",
    "sg:address":"Emmapk 110",
    "sg:city":"Pynacker",
    "sg:orig_category":"Boekhandels",
    "sg:phone":"+31 15 369 2992",
    "sg:postcode":"2641 EN",
    "sg:province":"South Holland",
    "wof:name":"Atten Kantoorboekhandel, H Van",
    "wof:placetype":"venue"
},
  "geometry": {"coordinates":[4.430646,52.018066],"type":"Point"}
}