{
  "type": "Feature",
  "properties": {
    "addr:full":"Industriewg 24D Beesd Gelderland 4153 BW",
    "addr:housenumber":"24d",
    "addr:postcode":"4153 bw",
    "addr:street":"Industriewg;Gelderland",
    "iso:country":"NL",
    "sg:address":"Industriewg 24D",
    "sg:city":"Beesd",
    "sg:orig_category":"Geluidsinstallaties - Verhuur",
    "sg:phone":"+31 345 520 383",
    "sg:postcode":"4153 BW",
    "sg:province":"Gelderland",
    "wof:name":"Parasound",
    "wof:placetype":"venue"
},
  "geometry": {"coordinates":[5.19335,51.893402],"type":"Point"}
}