{
  "type": "Feature",
  "properties": {
    "addr:full":"Westzanerdk 200 Zaandam Noord-Holland 1507 AM",
    "addr:housenumber":"200",
    "addr:postcode":"1507",
    "iso:country":"NL",
    "sg:address":"Westzanerdk 200",
    "sg:city":"Zaandam",
    "sg:orig_category":"Beeldende Kunstenaars",
    "sg:phone":"+31 75 631 2086",
    "sg:postcode":"1507 AM",
    "sg:province":"Noord-Holland",
    "wof:name":"Ven, Will Van Der",
    "wof:placetype":"venue"
},
  "geometry": {"coordinates":[4.804331,52.433071],"type":"Point"}
}