{
  "type": "Feature",
  "properties": {
    "addr:full":"Wemeldingestr 62 Rotterdam Zuid-Holland 3086 JV",
    "addr:housenumber":"62",
    "addr:postcode":"3086 jv",
    "addr:street":"Wemeldingestr",
    "iso:country":"NL",
    "sg:address":"Wemeldingestr 62",
    "sg:city":"Rotterdam",
    "sg:orig_category":"Adviesbureaus Bedrijfsorganisatie",
    "sg:phone":"+31 10 480 3084",
    "sg:postcode":"3086 JV",
    "sg:province":"Zuid-Holland",
    "wof:name":"Oudshoorn, E",
    "wof:placetype":"venue"
},
  "geometry": {"coordinates":[4.46072,51.873455],"type":"Point"}
}