{
  "type": "Feature",
  "properties": {
    "addr:full":"Van De Kasteelestraat 6 'S Gravenzande Zuid-Holland 2691 ZN",
    "addr:housenumber":"6 ';2691",
    "addr:postcode":"zn",
    "addr:street":"Van De Kasteelestraat",
    "iso:country":"NL",
    "sg:address":"Van De Kasteelestraat 6",
    "sg:city":"'S Gravenzande",
    "sg:orig_category":"Werving And Selectie Van Tijdelijk Personeel And Uitzendkantoren",
    "sg:phone":"+31 174 440 200",
    "sg:postcode":"2691 ZN",
    "sg:province":"Zuid-Holland",
    "wof:name":"Rka Uitzendbureau",
    "wof:placetype":"venue"
},
  "geometry": {"coordinates":[4.1624569893,52.0014915466],"type":"Point"}
}