{
  "type": "Feature",
  "properties": {
    "addr:full":"Molenstr 61 S Gravenhage Zuid-Holland 2513 BJ",
    "addr:housenumber":"61;gravenhage",
    "addr:postcode":"2513 bj",
    "addr:street":"Molenstr;S",
    "iso:country":"NL",
    "sg:address":"Molenstr 61",
    "sg:city":"S Gravenhage",
    "sg:orig_category":"Wijnkoperijen En -Groothandel",
    "sg:phone":"+31 70 361 4157",
    "sg:postcode":"2513 BJ",
    "sg:province":"Zuid-Holland",
    "wof:name":"Firullo",
    "wof:placetype":"venue"
},
  "geometry": {"coordinates":[4.3033900261,52.0784416199],"type":"Point"}
}