{
  "type": "Feature",
  "properties": {
    "addr:full":"Waalsewg 28 Tull En T Waal Utrecht 3999 NS",
    "addr:housenumber":"28",
    "addr:postcode":"3999 ns",
    "addr:street":"Waalsewg;Tull En T Waal",
    "iso:country":"NL",
    "sg:address":"Waalsewg 28",
    "sg:city":"Tull En T Waal",
    "sg:orig_category":"Haarden En Kachels",
    "sg:phone":"+31 30 601 9670",
    "sg:postcode":"3999 NS",
    "sg:province":"Utrecht",
    "wof:name":"Bos",
    "wof:placetype":"venue"
},
  "geometry": {"coordinates":[5.145097,51.998474],"type":"Point"}
}