{
  "type": "Feature",
  "properties": {
    "addr:full":"Eksterweg 73 Apeldoorn Gelderland 7331 JM",
    "addr:housenumber":"73",
    "addr:postcode":"7331 jm",
    "addr:street":"Eksterweg;Gelderland",
    "iso:country":"NL",
    "sg:address":"Eksterweg 73",
    "sg:city":"Apeldoorn",
    "sg:orig_category":"Dansscholen",
    "sg:phone":"+31 55 541 1345",
    "sg:postcode":"7331 JM",
    "sg:province":"Gelderland",
    "wof:name":"Fantasy Dance",
    "wof:placetype":"venue"
},
  "geometry": {"coordinates":[5.968413,52.195866],"type":"Point"}
}