{
  "type": "Feature",
  "properties": {
    "addr:full":"Markt 48 Geertruidenberg Noord-Brabant 4931 BT",
    "addr:housenumber":"48",
    "addr:postcode":"4931 bt",
    "addr:street":"Markt",
    "iso:country":"NL",
    "sg:address":"Markt 48",
    "sg:city":"Geertruidenberg",
    "sg:orig_category":"Damesmodezaken",
    "sg:phone":"+31 162 517 738",
    "sg:postcode":"4931 BT",
    "sg:province":"Noord-Brabant",
    "wof:name":"Mountain Fashion",
    "wof:placetype":"venue"
},
  "geometry": {"coordinates":[4.860058,51.700661],"type":"Point"}
}