{
  "type": "Feature",
  "properties": {
    "addr:full":"Poststraat 28 Stadskanaal Groningen 9501 ER",
    "addr:housenumber":"28",
    "addr:postcode":"9501 er",
    "addr:street":"Poststraat",
    "iso:country":"NL",
    "sg:address":"Poststraat 28",
    "sg:city":"Stadskanaal",
    "sg:orig_category":"Discountwinkels",
    "sg:phone":"+31 599 612 307",
    "sg:postcode":"9501 ER",
    "sg:province":"Groningen",
    "wof:name":"Wieringa Textiel",
    "wof:placetype":"venue"
},
  "geometry": {"coordinates":[6.942513,52.993767],"type":"Point"}
}