{
  "type": "Feature",
  "properties": {
    "iso:country":"NL",
    "sg:address":"Grt Krocht 25",
    "sg:city":"Zandvoort",
    "sg:classifiers":[
        {
            "category":"Food & Beverages",
            "subcategory":"Fruits & Vegetables",
            "type":"Retail Goods"
        }
    ],
    "sg:phone":"+31 23 571 4404",
    "sg:postcode":"2042 LT",
    "sg:province":"North Holland",
    "sg:tags":[
        "en",
        "groenten"
    ],
    "wof:name":"Dani?l Groente En Fruit",
    "wof:placetype":"venue"
},
  "geometry": {"coordinates":[4.53157,52.371578],"type":"Point"}
}