{
  "type": "Feature",
  "properties": {
    "addr:full":"V Cruchtenstr 4 Swalmen Limburg 6071 VE",
    "addr:housenumber":"4",
    "addr:postcode":"6071",
    "addr:street":"Cruchtenstr;Ve",
    "iso:country":"NL",
    "sg:address":"V Cruchtenstr 4",
    "sg:city":"Swalmen",
    "sg:orig_category":"Administratie- En Boekhoudkantoren",
    "sg:phone":"+31 475 600 886",
    "sg:postcode":"6071 VE",
    "sg:province":"Limburg",
    "wof:name":"Likras",
    "wof:placetype":"venue"
},
  "geometry": {"coordinates":[6.040993,51.234772],"type":"Point"}
}