{
  "type": "Feature",
  "properties": {
    "iso:country":"NL",
    "sg:address":"Plutoweg 9",
    "sg:city":"Leeuwarden",
    "sg:orig_category":"Verhuisdiensten",
    "sg:phone":"+31 58 288 7485",
    "sg:postcode":"8938 AC",
    "sg:province":"Friesland",
    "wof:name":"Bandsma Bultje Verhuizingen",
    "wof:placetype":"venue"
},
  "geometry": {"coordinates":[5.836226,53.198006],"type":"Point"}
}