{
  "type": "Feature",
  "properties": {
    "addr:full":"Molenstr 22 Hillegom Zuid-Holland 2181 JB",
    "addr:housenumber":"22",
    "addr:postcode":"2181 jb",
    "addr:street":"Molenstr",
    "iso:country":"NL",
    "sg:address":"Molenstr 22",
    "sg:city":"Hillegom",
    "sg:orig_category":"Drukkerijen",
    "sg:phone":"+31 252 519 821",
    "sg:postcode":"2181 JB",
    "sg:province":"Zuid-Holland",
    "wof:name":"Pelhad",
    "wof:placetype":"venue"
},
  "geometry": {"coordinates":[4.576172,52.292305],"type":"Point"}
}