{
  "type": "Feature",
  "properties": {
    "iso:country":"NL",
    "sg:address":"Engelenburgstr 37",
    "sg:city":"Twello",
    "sg:orig_category":"Meubelmakerijen",
    "sg:phone":"+31 571 270 070",
    "sg:postcode":"7391 AM",
    "sg:province":"Gelderland",
    "wof:name":"Kloppenberg",
    "wof:placetype":"venue"
},
  "geometry": {"coordinates":[6.0834569931,52.2241439819],"type":"Point"}
}