{
  "type": "Feature",
  "properties": {
    "addr:full":"Doezastr 27A Leiden Zuid-Holland 2311 HA",
    "addr:housenumber":"27a",
    "addr:postcode":"2311 ha",
    "addr:street":"Doezastr",
    "iso:country":"NL",
    "sg:address":"Doezastr 27A",
    "sg:city":"Leiden",
    "sg:orig_category":"Psychotherapeuten",
    "sg:phone":"+31 71 513 0349",
    "sg:postcode":"2311 HA",
    "sg:province":"Zuid-Holland",
    "wof:name":"Jong, Drs H O De",
    "wof:placetype":"venue"
},
  "geometry": {"coordinates":[4.4892997742,52.1542930603],"type":"Point"}
}