{
  "type": "Feature",
  "properties": {
    "addr:full":"Zuidhaven 91 Zevenbergen North Brabant 4761 CT",
    "addr:housenumber":"91",
    "addr:postcode":"4761 ct",
    "addr:street":"Zuidhaven",
    "iso:country":"NL",
    "sg:address":"Zuidhaven 91",
    "sg:city":"Zevenbergen",
    "sg:orig_category":"Opticiens",
    "sg:phone":"+31 168 326 490",
    "sg:postcode":"4761 CT",
    "sg:province":"North Brabant",
    "wof:name":"Boon, Rob",
    "wof:placetype":"venue"
},
  "geometry": {"coordinates":[4.6046528816,51.6445503235],"type":"Point"}
}