{
  "type": "Feature",
  "properties": {
    "iso:country":"NL",
    "sg:address":"Krammer 8",
    "sg:city":"Brielle",
    "sg:orig_category":"Adviesbureaus Economie",
    "sg:phone":"+31 181 470 407",
    "sg:postcode":"3232 HE",
    "sg:province":"South Holland",
    "wof:name":"Geld & Leven",
    "wof:placetype":"venue"
},
  "geometry": {"coordinates":[4.168821,51.897579],"type":"Point"}
}