{
  "type": "Feature",
  "properties": {
    "addr:full":"Kleinzand 9 Sneek Provincie Friesland 8601 BE",
    "addr:housenumber":"9",
    "addr:postcode":"8601",
    "addr:street":"Kleinzand;Provincie Friesland",
    "iso:country":"NL",
    "sg:address":"Kleinzand 9",
    "sg:city":"Sneek",
    "sg:orig_category":"Verlichting And Huishoudartikelen",
    "sg:phone":"+31 515 412 583",
    "sg:postcode":"8601 BE",
    "sg:province":"Provincie Friesland",
    "wof:name":"Aukema Interieurs Bv",
    "wof:placetype":"venue"
},
  "geometry": {"coordinates":[5.66278,53.032581],"type":"Point"}
}