{
  "type": "Feature",
  "properties": {
    "addr:full":"De Overmaat 39 Arnhem Gelderland 6831 AE",
    "addr:housenumber":"39",
    "addr:postcode":"6831 ae",
    "addr:street":"De Overmaat",
    "iso:country":"NL",
    "sg:address":"De Overmaat 39",
    "sg:city":"Arnhem",
    "sg:orig_category":"Verhuisdiensten",
    "sg:phone":"+31 26 323 0320",
    "sg:postcode":"6831 AE",
    "sg:province":"Gelderland",
    "wof:name":"Derksen Verhuizingen",
    "wof:placetype":"venue"
},
  "geometry": {"coordinates":[5.886048,51.955811],"type":"Point"}
}