{
  "type": "Feature",
  "properties": {
    "addr:full":"Stationsstraat 11 Maarheeze Noord-Brabant 6026 CR",
    "addr:housenumber":"11",
    "addr:postcode":"6026 cr",
    "addr:street":"Stationsstraat",
    "iso:country":"NL",
    "sg:address":"Stationsstraat 11",
    "sg:city":"Maarheeze",
    "sg:orig_category":"Banken And Kredietinstellingen",
    "sg:phone":"+31 495 498 498",
    "sg:postcode":"6026 CR",
    "sg:province":"Noord-Brabant",
    "wof:name":"Rabobank",
    "wof:placetype":"venue"
},
  "geometry": {"coordinates":[5.611695,51.310448],"type":"Point"}
}