{
  "type": "Feature",
  "properties": {
    "addr:full":"Postbus 42 Wormerveer Noord-Holland 1520 AA",
    "addr:housenumber":"42",
    "addr:postcode":"1520 aa",
    "addr:street":"Postbus",
    "iso:country":"NL",
    "sg:address":"Postbus 42",
    "sg:city":"Wormerveer",
    "sg:orig_category":"Naamplaten - Fabrieken",
    "sg:phone":"+31 75 621 6262",
    "sg:postcode":"1520 AA",
    "sg:province":"Noord-Holland",
    "sg:website":"http://www.fotometaal.nl",
    "wof:name":"Fotometaal Bv",
    "wof:placetype":"venue"
},
  "geometry": {"coordinates":[4.79178,52.493271],"type":"Point"}
}