{
  "type": "Feature",
  "properties": {
    "addr:full":"Nw Leliestr 80 Amsterdam North Holland 1015 SV",
    "addr:housenumber":"80",
    "addr:postcode":"1015 sv",
    "iso:country":"NL",
    "sg:address":"Nw Leliestr 80",
    "sg:city":"Amsterdam",
    "sg:orig_category":"Kappers",
    "sg:phone":"+31 20 624 7969",
    "sg:postcode":"1015 SV",
    "sg:province":"North Holland",
    "wof:name":"Musscher, A J Van",
    "wof:placetype":"venue"
},
  "geometry": {"coordinates":[4.881116,52.3755],"type":"Point"}
}