{
  "type": "Feature",
  "properties": {
    "iso:country":"NL",
    "sg:address":"Van Deventerlaan 5",
    "sg:city":"Voorburg",
    "sg:classifiers":[
        {
            "category":"Shopping",
            "subcategory":"Gifts & Souvenirs",
            "type":"Retail Goods"
        }
    ],
    "sg:phone":"+31 70 386 3940",
    "sg:postcode":"2271 TT",
    "sg:province":"Zuid-Holland",
    "sg:tags":[
        "geschenken"
    ],
    "wof:name":"Ines Merhottein",
    "wof:placetype":"venue"
},
  "geometry": {"coordinates":[4.3673,52.073967],"type":"Point"}
}