{
  "type": "Feature",
  "properties": {
    "addr:full":"Winkelcentrum Drieslag Arnhem Gelderland 6832  A",
    "addr:housenumber":"6832 a",
    "addr:street":"Winkelcentrum Drieslag",
    "iso:country":"NL",
    "sg:address":"Winkelcentrum Drieslag",
    "sg:city":"Arnhem",
    "sg:classifiers":[
        {
            "category":"Bakery",
            "type":"Food & Drink"
        }
    ],
    "sg:phone":"+31 26 321 8530",
    "sg:postcode":"6832  A",
    "sg:province":"Gelderland",
    "sg:tags":[
        "brood",
        "banket"
    ],
    "wof:name":"Jos Broekman",
    "wof:placetype":"venue"
},
  "geometry": {"coordinates":[5.904585,51.985519],"type":"Point"}
}