{
  "type": "Feature",
  "properties": {
    "iso:country":"NL",
    "sg:address":"Bolder 35",
    "sg:city":"Groningen",
    "sg:orig_category":"Loodgieterswerk, Verwarming And Sanitaire Installaties",
    "sg:phone":"+31 50 541 8112",
    "sg:postcode":"9732 PB",
    "sg:province":"Groningen",
    "wof:name":"Meindert Klussenier Tuinstra",
    "wof:placetype":"venue"
},
  "geometry": {"coordinates":[6.619119,53.232441],"type":"Point"}
}