{
  "type": "Feature",
  "properties": {
    "addr:full":"Knibbelwg 9B Zevenhuizen Zh Zuid-Holland 2761 JB",
    "addr:housenumber":"9b",
    "addr:postcode":"2761 jb",
    "addr:street":"Knibbelwg",
    "iso:country":"NL",
    "sg:address":"Knibbelwg 9B",
    "sg:city":"Zevenhuizen Zh",
    "sg:orig_category":"Bloemen En Planten",
    "sg:phone":"+31 180 631 379",
    "sg:postcode":"2761 JB",
    "sg:province":"Zuid-Holland",
    "wof:name":"Kooij Cv, C N Van Der",
    "wof:placetype":"venue"
},
  "geometry": {"coordinates":[4.587137,52.017452],"type":"Point"}
}