{
  "type": "Feature",
  "properties": {
    "addr:full":"Geerwg 33 Ter Aar Zuid-Holland 2461 TS",
    "addr:housenumber":"33",
    "addr:postcode":"aar;2461 ts",
    "addr:street":"Geerwg;Ter",
    "iso:country":"NL",
    "sg:address":"Geerwg 33",
    "sg:city":"Ter Aar",
    "sg:orig_category":"Horloges En Klokken - Reparatie En Onderhoud",
    "sg:phone":"+31 172 602 376",
    "sg:postcode":"2461 TS",
    "sg:province":"Zuid-Holland",
    "wof:name":"Vale, G",
    "wof:placetype":"venue"
},
  "geometry": {"coordinates":[4.72589,52.198772],"type":"Point"}
}