{
  "type": "Feature",
  "properties": {
    "iso:country":"NL",
    "sg:address":"Krijgertje 47",
    "sg:city":"Best",
    "sg:orig_category":"Drukkerijen And Copyshops",
    "sg:phone":"+31 499 371 451",
    "sg:postcode":"5683 LC",
    "sg:province":"Noord-Brabant",
    "wof:name":"Piko Sportkleding",
    "wof:placetype":"venue"
},
  "geometry": {"coordinates":[-101.618134,31.224251],"type":"Point"}
}