{
  "type": "Feature",
  "properties": {
    "iso:country":"NL",
    "sg:address":"Raadhuispln 2",
    "sg:city":"Lekkerkerk",
    "sg:orig_category":"Verzekeringen - Verzekeringskantoren",
    "sg:phone":"+31 180 661 644",
    "sg:postcode":"2941 BR",
    "sg:province":"South Holland",
    "wof:name":"Onderlinge Lek En Ijssel Ua",
    "wof:placetype":"venue"
},
  "geometry": {"coordinates":[4.683992,51.896217],"type":"Point"}
}