{
  "type": "Feature",
  "properties": {
    "addr:full":"Handelstraat 11 Leerdam Zuid-Holland 4143 HT",
    "addr:housenumber":"11",
    "addr:postcode":"4143 ht",
    "addr:street":"Handelstraat",
    "iso:country":"NL",
    "sg:address":"Handelstraat 11",
    "sg:city":"Leerdam",
    "sg:orig_category":"Zuivelproducten And Spijsoli?n Gh",
    "sg:phone":"+31 345 639 900",
    "sg:postcode":"4143 HT",
    "sg:province":"Zuid-Holland",
    "wof:name":"Frico Cheese",
    "wof:placetype":"venue"
},
  "geometry": {"coordinates":[5.104772,51.898533],"type":"Point"}
}