{
  "type": "Feature",
  "properties": {
    "iso:country":"NL",
    "sg:address":"Capellaln 65",
    "sg:city":"Hoofddorp",
    "sg:orig_category":"Boeken En Tijdschriften",
    "sg:phone":"+31 23 556 4939",
    "sg:postcode":"2132 JL",
    "sg:province":"North Holland",
    "wof:name":"Top Sant?",
    "wof:placetype":"venue"
},
  "geometry": {"coordinates":[4.69296,52.305393],"type":"Point"}
}