{
  "type": "Feature",
  "properties": {
    "addr:full":"Admiraal De Ruyterstraat 10 Aalten Gelderland 7122 WJ",
    "addr:housenumber":"10",
    "addr:postcode":"7122 wj",
    "addr:street":"Admiraal De Ruyterstraat;Gelderland",
    "iso:country":"NL",
    "sg:address":"Admiraal De Ruyterstraat 10",
    "sg:city":"Aalten",
    "sg:orig_category":"Fitnesscentra",
    "sg:phone":"+31 543 476 761",
    "sg:postcode":"7122 WJ",
    "sg:province":"Gelderland",
    "wof:name":"Sportinstituut Rob'S Sport",
    "wof:placetype":"venue"
},
  "geometry": {"coordinates":[6.576171,51.923828],"type":"Point"}
}