{
  "type": "Feature",
  "properties": {
    "iso:country":"NL",
    "sg:address":"Havenpad 6",
    "sg:city":"Stavenisse",
    "sg:orig_category":"Metselwerken",
    "sg:phone":"+31 6 11250616",
    "sg:postcode":"4696 RN",
    "sg:province":"Zeeland",
    "wof:name":"Priem",
    "wof:placetype":"venue"
},
  "geometry": {"coordinates":[4.014684,51.588661],"type":"Point"}
}