{
  "type": "Feature",
  "properties": {
    "iso:country":"NL",
    "sg:address":"Van Woustraat 41",
    "sg:city":"Amsterdam",
    "sg:orig_category":"Juweliers",
    "sg:phone":"+31 20 662 6737",
    "sg:postcode":"1074 AB",
    "sg:province":"Noord-Holland",
    "wof:name":"Ibo",
    "wof:placetype":"venue"
},
  "geometry": {"coordinates":[4.900278,52.356308],"type":"Point"}
}