{
  "type": "Feature",
  "properties": {
    "iso:country":"NL",
    "sg:address":"Callunastr 24",
    "sg:city":"Arnhem",
    "sg:orig_category":"Loodgieters",
    "sg:phone":"+31 26 443 3384",
    "sg:postcode":"6813 EW",
    "sg:province":"Gelderland",
    "wof:name":"Hendriks, R J",
    "wof:placetype":"venue"
},
  "geometry": {"coordinates":[5.879602,51.988029],"type":"Point"}
}