{
  "type": "Feature",
  "properties": {
    "addr:full":"Edisonstr 2 Heerhugowaard Noord-Holland 1704 RL",
    "addr:housenumber":"2",
    "addr:postcode":"1704 rl",
    "addr:street":"Edisonstr",
    "iso:country":"NL",
    "sg:address":"Edisonstr 2",
    "sg:city":"Heerhugowaard",
    "sg:orig_category":"Verzinkerijen",
    "sg:phone":"+31 72 576 2150",
    "sg:postcode":"1704 RL",
    "sg:province":"Noord-Holland",
    "sg:website":"http://www.verzinkerij-heerhugowaard.nl",
    "wof:name":"Verzinkerij Heerhugowaard Bv",
    "wof:placetype":"venue"
},
  "geometry": {"coordinates":[4.832786,52.676212],"type":"Point"}
}