{
  "type": "Feature",
  "properties": {
    "iso:country":"NL",
    "sg:address":"Van Boetzelaerlaan 30",
    "sg:city":"'S Gravenhage",
    "sg:orig_category":"Boekhouders",
    "sg:phone":"+31 70 358 6018",
    "sg:postcode":"2581 AJ",
    "sg:province":"Zuid-Holland",
    "wof:name":"Electronische Administratie Service Pruim Bv",
    "wof:placetype":"venue"
},
  "geometry": {"coordinates":[4.271668,52.088139],"type":"Point"}
}