{
  "type": "Feature",
  "properties": {
    "addr:full":"Van Boetzelaerlaan 30 'S Gravenhage Zuid-Holland 2581 AJ",
    "addr:housenumber":"30",
    "addr:postcode":"2581 aj",
    "addr:street":"Van Boetzelaerlaan;' S",
    "iso:country":"NL",
    "sg:address":"Van Boetzelaerlaan 30",
    "sg:city":"'S Gravenhage",
    "sg:orig_category":"Boekhouders",
    "sg:phone":"+31 70 358 6018",
    "sg:postcode":"2581 AJ",
    "sg:province":"Zuid-Holland",
    "wof:name":"Electronische Administratie Service Pruim Bv",
    "wof:placetype":"venue"
},
  "geometry": {"coordinates":[4.271668,52.088139],"type":"Point"}
}