{
  "type": "Feature",
  "properties": {
    "addr:full":"Nijverheidstraat 48 Bemmel Gelderland 6681 LN",
    "addr:housenumber":"48",
    "addr:postcode":"6681 ln",
    "addr:street":"Nijverheidstraat;Gelderland",
    "iso:country":"NL",
    "sg:address":"Nijverheidstraat 48",
    "sg:city":"Bemmel",
    "sg:orig_category":"Verhuur Audiovisuele Apparatuur",
    "sg:phone":"+31 26 325 5392",
    "sg:postcode":"6681 LN",
    "sg:province":"Gelderland",
    "wof:name":"Martin Rental Nederland Bv",
    "wof:placetype":"venue"
},
  "geometry": {"coordinates":[5.923332,51.906948],"type":"Point"}
}