{
  "type": "Feature",
  "properties": {
    "addr:full":"Palmbosstr 16 Zundert North Brabant 4882 NR",
    "addr:housenumber":"16",
    "addr:postcode":"4882 nr",
    "addr:street":"Palmbosstr",
    "iso:country":"NL",
    "sg:address":"Palmbosstr 16",
    "sg:city":"Zundert",
    "sg:orig_category":"Kappers",
    "sg:phone":"+31 76 597 5846",
    "sg:postcode":"4882 NR",
    "sg:province":"North Brabant",
    "wof:name":"Nouws-Peeters, J C M",
    "wof:placetype":"venue"
},
  "geometry": {"coordinates":[4.675544,51.48962],"type":"Point"}
}