{
  "type": "Feature",
  "properties": {
    "addr:full":"Hoofdstraat 37 Noordbroek Groningen 9635 AS",
    "addr:housenumber":"37",
    "addr:postcode":"9635 as",
    "addr:street":"Hoofdstraat",
    "iso:country":"NL",
    "sg:address":"Hoofdstraat 37",
    "sg:city":"Noordbroek",
    "sg:orig_category":"Autokeuringen",
    "sg:phone":"+31 598 453 231",
    "sg:postcode":"9635 AS",
    "sg:province":"Groningen",
    "wof:name":"Vakgarage Van Leeuwen",
    "wof:placetype":"venue"
},
  "geometry": {"coordinates":[6.873658,53.195213],"type":"Point"}
}