{
  "type": "Feature",
  "properties": {
    "iso:country":"NL",
    "sg:address":"Mercuriushof 4",
    "sg:city":"Hoorn Nh",
    "sg:orig_category":"Bewakingsdiensten",
    "sg:phone":"+31 6 21561310",
    "sg:postcode":"1622 BJ",
    "sg:province":"Noord-Holland",
    "wof:name":"All Around",
    "wof:placetype":"venue"
},
  "geometry": {"coordinates":[5.042044,52.642395],"type":"Point"}
}