{
  "type": "Feature",
  "properties": {
    "addr:full":"Hamstraat 18 Roermond Limburg 6041 HB",
    "addr:housenumber":"18",
    "addr:postcode":"6041 hb",
    "addr:street":"Hamstraat",
    "iso:country":"NL",
    "sg:address":"Hamstraat 18",
    "sg:city":"Roermond",
    "sg:orig_category":"Damesmodezaken",
    "sg:phone":"+31 475 311 515",
    "sg:postcode":"6041 HB",
    "sg:province":"Limburg",
    "wof:name":"Modehuis Ter Horst Van Geel",
    "wof:placetype":"venue"
},
  "geometry": {"coordinates":[5.991087,51.192852],"type":"Point"}
}