{
  "type": "Feature",
  "properties": {
    "addr:full":"J P Engelmanstraat 1A Heerenveen Friesland 8442 GE",
    "addr:housenumber":"1a",
    "addr:postcode":"8442",
    "addr:street":"J P Engelmanstraat",
    "iso:country":"NL",
    "sg:address":"J P Engelmanstraat 1A",
    "sg:city":"Heerenveen",
    "sg:orig_category":"Organisaties And Verenigingen",
    "sg:phone":"+31 513 627 477",
    "sg:postcode":"8442 GE",
    "sg:province":"Friesland",
    "wof:name":"Kunstuitleen",
    "wof:placetype":"venue"
},
  "geometry": {"coordinates":[5.929104805,52.9556655884],"type":"Point"}
}