{
  "type": "Feature",
  "properties": {
    "addr:full":"Schouten Einde 65 Puttershoek Zuid-Holland 3297 AS",
    "addr:housenumber":"65",
    "addr:postcode":"3297 as",
    "addr:street":"Schouten Einde",
    "iso:country":"NL",
    "sg:address":"Schouten Einde 65",
    "sg:city":"Puttershoek",
    "sg:orig_category":"Begrafenisondernemers",
    "sg:phone":"+31 78 676 2273",
    "sg:postcode":"3297 AS",
    "sg:province":"Zuid-Holland",
    "wof:name":"Begrafenisonderneming J. Van Steenselen",
    "wof:placetype":"venue"
},
  "geometry": {"coordinates":[4.573447,51.803734],"type":"Point"}
}