{
  "type": "Feature",
  "properties": {
    "iso:country":"NL",
    "sg:address":"Twentsewg 218",
    "sg:city":"Lemelerveld",
    "sg:orig_category":"Keukens",
    "sg:phone":"+31 572 371 155",
    "sg:postcode":"8152 DM",
    "sg:province":"NL.08",
    "wof:name":"Huysmans Vof",
    "wof:placetype":"venue"
},
  "geometry": {"coordinates":[6.299274,52.442841],"type":"Point"}
}