{
  "type": "Feature",
  "properties": {
    "iso:country":"NL",
    "sg:address":"Pomeranusstr 11",
    "sg:city":"Etten Leur",
    "sg:orig_category":"Autorijscholen",
    "sg:phone":"+31 76 502 2569",
    "sg:postcode":"4871 XC",
    "sg:province":"Noord-Brabant",
    "wof:name":"Bartje",
    "wof:placetype":"venue"
},
  "geometry": {"coordinates":[4.64845,51.582607],"type":"Point"}
}