{
  "type": "Feature",
  "properties": {
    "iso:country":"NL",
    "sg:address":"Opera 43",
    "sg:city":"Zaandam",
    "sg:orig_category":"Begrafenisondernemers",
    "sg:phone":"+31 75 617 9542",
    "sg:postcode":"1507 VG",
    "sg:province":"Noord-Holland",
    "wof:name":"G. Winters",
    "wof:placetype":"venue"
},
  "geometry": {"coordinates":[4.807919,52.441067],"type":"Point"}
}