{
  "type": "Feature",
  "properties": {
    "iso:country":"NL",
    "sg:address":"Reitzstr 98",
    "sg:city":"Haarlem",
    "sg:orig_category":"Fietsen En Bromfietsen",
    "sg:phone":"+31 23 526 7113",
    "sg:postcode":"2021 TV",
    "sg:province":"Noord-Holland",
    "wof:name":"Visser, Rijwielhandel De",
    "wof:placetype":"venue"
},
  "geometry": {"coordinates":[4.649455,52.393654],"type":"Point"}
}