{
  "type": "Feature",
  "properties": {
    "iso:country":"NL",
    "sg:address":"Heuningstraat 23",
    "sg:city":"Ochten",
    "sg:orig_category":"Metaalbekleding And -Behandeling",
    "sg:phone":"+31 344 641 549",
    "sg:postcode":"4051 CA",
    "sg:province":"Gelderland",
    "wof:name":"F.M. Angelino Ochten Bv",
    "wof:placetype":"venue"
},
  "geometry": {"coordinates":[5.550974,51.911957],"type":"Point"}
}