{
  "type": "Feature",
  "properties": {
    "iso:country":"NL",
    "sg:address":"Bergerothwg 58/A",
    "sg:city":"Stramproy",
    "sg:orig_category":"Kantoor- En Bedrijfsmeubelen",
    "sg:phone":"+31 495 562 256",
    "sg:postcode":"6039 AN",
    "sg:province":"Limburg",
    "wof:name":"Linders Vof, L",
    "wof:placetype":"venue"
},
  "geometry": {"coordinates":[5.7136287689,51.1981697083],"type":"Point"}
}