{
  "type": "Feature",
  "properties": {
    "addr:full":"Winkelcentrum 5 Etten Leur Noord-Brabant 4873 AA",
    "addr:housenumber":"5",
    "addr:postcode":"4873 aa",
    "addr:street":"Winkelcentrum",
    "iso:country":"NL",
    "sg:address":"Winkelcentrum 5",
    "sg:city":"Etten Leur",
    "sg:orig_category":"Noten",
    "sg:phone":"+31 76 501 3292",
    "sg:postcode":"4873 AA",
    "sg:province":"Noord-Brabant",
    "sg:website":"http://www.cestbon.nl",
    "wof:name":"C'Est Bon",
    "wof:placetype":"venue"
},
  "geometry": {"coordinates":[4.635494,51.568321],"type":"Point"}
}