{
  "type": "Feature",
  "properties": {
    "iso:country":"NL",
    "sg:address":"Taborstr 15A",
    "sg:city":"Rotterdam",
    "sg:orig_category":"Koffie- En Theehuizen",
    "sg:phone":"+31 10 414 4667",
    "sg:postcode":"3061 EV",
    "sg:province":"South Holland",
    "wof:name":"The Chief",
    "wof:placetype":"venue"
},
  "geometry": {"coordinates":[4.508747,51.92728],"type":"Point"}
}