{
  "type": "Feature",
  "properties": {
    "iso:country":"NL",
    "sg:address":"Prins Bernhardstraat 8",
    "sg:city":"Den Bosch",
    "sg:orig_category":"Kansspelen",
    "sg:phone":"+31 73 613 5707",
    "sg:postcode":"5211 HE",
    "sg:province":"North Brabant",
    "wof:name":"Vereniging Societeit Casino",
    "wof:placetype":"venue"
},
  "geometry": {"coordinates":[5.2930197716,51.6830406189],"type":"Point"}
}