{
  "type": "Feature",
  "properties": {
    "addr:full":"Postbus 16 Bakel Noord-Brabant 5760 AA",
    "addr:housenumber":"16",
    "addr:postcode":"5760 aa",
    "addr:street":"Postbus",
    "iso:country":"NL",
    "sg:address":"Postbus 16",
    "sg:city":"Bakel",
    "sg:orig_category":"Ziekenhuizen, Sanatoria, Verpleeghuizen",
    "sg:phone":"+31 492 348 553",
    "sg:postcode":"5760 AA",
    "sg:province":"Noord-Brabant",
    "wof:name":"Zorgboog, De",
    "wof:placetype":"venue"
},
  "geometry": {"coordinates":[5.74122,51.50412],"type":"Point"}
}