{
  "type": "Feature",
  "properties": {
    "addr:full":"Iepenln 52 Bunde Limburg 6241 AG",
    "addr:housenumber":"52",
    "addr:postcode":"6241",
    "addr:street":"Iepenln",
    "iso:country":"NL",
    "sg:address":"Iepenln 52",
    "sg:city":"Bunde",
    "sg:orig_category":"Adviesbureaus Bedrijfsorganisatie",
    "sg:phone":"+31 43 365 5381",
    "sg:postcode":"6241 AG",
    "sg:province":"Limburg",
    "sg:website":"http://www.mcdialoog.nl",
    "wof:name":"M & C Dialoog Bv",
    "wof:placetype":"venue"
},
  "geometry": {"coordinates":[5.731195,50.891899],"type":"Point"}
}