{
  "type": "Feature",
  "properties": {
    "iso:country":"NL",
    "sg:address":"George Stephensonstraat 25",
    "sg:city":"Zwolle",
    "sg:orig_category":"Zuivelproducten And Spijsoli?n Gh",
    "sg:phone":"+31 38 465 0839",
    "sg:postcode":"8013 NL",
    "sg:province":"Overijssel",
    "wof:name":"Yakult Nederland Bv",
    "wof:placetype":"venue"
},
  "geometry": {"coordinates":[6.120051,52.49258],"type":"Point"}
}