{
  "type": "Feature",
  "properties": {
    "iso:country":"NL",
    "sg:address":"Boomgaard 204",
    "sg:city":"Ysselstein Ut",
    "sg:orig_category":"Keukens",
    "sg:phone":"+31 30 688 3366",
    "sg:postcode":"3404 TB",
    "sg:province":"Utrecht",
    "wof:name":"Leusden Vof, Van",
    "wof:placetype":"venue"
},
  "geometry": {"coordinates":[5.038415,52.006561],"type":"Point"}
}