{
  "type": "Feature",
  "properties": {
    "addr:full":"Amsterdamsewg 8 Amersfoort Utrecht 3812 RS",
    "addr:housenumber":"8",
    "addr:postcode":"3812 rs",
    "addr:street":"Amsterdamsewg",
    "iso:country":"NL",
    "sg:address":"Amsterdamsewg 8",
    "sg:city":"Amersfoort",
    "sg:orig_category":"Wasmachines En Wasdrogers",
    "sg:phone":"+31 33 462 5015",
    "sg:postcode":"3812 RS",
    "sg:province":"Utrecht",
    "wof:name":"Bcc",
    "wof:placetype":"venue"
},
  "geometry": {"coordinates":[5.3763661385,52.1605415344],"type":"Point"}
}