{
  "type": "Feature",
  "properties": {
    "addr:full":"Kruisstraat 113 Eindhoven Noord-Brabant 5612 CE",
    "addr:housenumber":"113",
    "addr:postcode":"5612 ce",
    "addr:street":"Kruisstraat",
    "iso:country":"NL",
    "sg:address":"Kruisstraat 113",
    "sg:city":"Eindhoven",
    "sg:orig_category":"Drukkerijen And Copyshops",
    "sg:phone":"+31 40 243 5705",
    "sg:postcode":"5612 CE",
    "sg:province":"Noord-Brabant",
    "wof:name":"Algrafisch Bedrijf Van Tuijl Bv",
    "wof:placetype":"venue"
},
  "geometry": {"coordinates":[5.475088,51.444729],"type":"Point"}
}