{
  "type": "Feature",
  "properties": {
    "addr:full":"Kruisstraat 4 Borger Provincie Drenthe 9531 JE",
    "addr:housenumber":"4",
    "addr:postcode":"9531 je",
    "addr:street":"Kruisstraat;Provincie",
    "iso:country":"NL",
    "sg:address":"Kruisstraat 4",
    "sg:city":"Borger",
    "sg:orig_category":"Biljart- And Snookerzalen",
    "sg:phone":"+31 599 234 931",
    "sg:postcode":"9531 JE",
    "sg:province":"Provincie Drenthe",
    "wof:name":"Restaurant D'Aole Bakkerij",
    "wof:placetype":"venue"
},
  "geometry": {"coordinates":[6.789802,52.925804],"type":"Point"}
}