{
  "type": "Feature",
  "properties": {
    "addr:full":"Tuinbouwwg 41 Haarsteeg Noord-Brabant 5254 VJ",
    "addr:housenumber":"41",
    "addr:postcode":"5254 vj",
    "addr:street":"Tuinbouwwg",
    "iso:country":"NL",
    "sg:address":"Tuinbouwwg 41",
    "sg:city":"Haarsteeg",
    "sg:orig_category":"Wegenbouw - Materieel",
    "sg:phone":"+31 73 518 5664",
    "sg:postcode":"5254 VJ",
    "sg:province":"Noord-Brabant",
    "wof:name":"John Klerks",
    "wof:placetype":"venue"
},
  "geometry": {"coordinates":[5.2016801834,51.709854126],"type":"Point"}
}