{
  "type": "Feature",
  "properties": {
    "addr:full":"Sluiskamp 3112 Wijchen Gelderland 6605 SM",
    "addr:housenumber":"3112",
    "addr:postcode":"6605 sm",
    "addr:street":"Sluiskamp;Gelderland",
    "iso:country":"NL",
    "sg:address":"Sluiskamp 3112",
    "sg:city":"Wijchen",
    "sg:orig_category":"Wegen And Sportterreinen",
    "sg:phone":"+31 24 641 1492",
    "sg:postcode":"6605 SM",
    "sg:province":"Gelderland",
    "wof:name":"W.E. Van Kol",
    "wof:placetype":"venue"
},
  "geometry": {"coordinates":[5.7087020874,51.7995452881],"type":"Point"}
}