{
  "type": "Feature",
  "properties": {
    "iso:country":"NL",
    "sg:address":"Bourgondischelaan 1",
    "sg:city":"Amstelveen",
    "sg:orig_category":"Kappers",
    "sg:phone":"+31 20 643 2428",
    "sg:postcode":"1181 DC",
    "sg:province":"Noord-Holland",
    "wof:name":"Maison Mady",
    "wof:placetype":"venue"
},
  "geometry": {"coordinates":[4.86532,52.317787],"type":"Point"}
}