{
  "type": "Feature",
  "properties": {
    "addr:full":"Pollux 66 Berkel En Rodenrys Zuid-Holland 2651 HC",
    "addr:housenumber":"66",
    "addr:postcode":"2651 hc",
    "addr:street":"Pollux;Berkel",
    "iso:country":"NL",
    "sg:address":"Pollux 66",
    "sg:city":"Berkel En Rodenrys",
    "sg:orig_category":"Fotoreportages",
    "sg:phone":"+31 10 511 8313",
    "sg:postcode":"2651 HC",
    "sg:province":"Zuid-Holland",
    "wof:name":"Lengkeek",
    "wof:placetype":"venue"
},
  "geometry": {"coordinates":[4.48478,52.004604],"type":"Point"}
}