{
  "type": "Feature",
  "properties": {
    "addr:full":"Lakenstr 44 Geldrop Noord-Brabant 5667 TR",
    "addr:housenumber":"44",
    "addr:postcode":"5667 tr",
    "addr:street":"Lakenstr",
    "iso:country":"NL",
    "sg:address":"Lakenstr 44",
    "sg:city":"Geldrop",
    "sg:orig_category":"Glazenwasserijen",
    "sg:phone":"+31 40 286 1488",
    "sg:postcode":"5667 TR",
    "sg:province":"Noord-Brabant",
    "wof:name":"Run, R Van",
    "wof:placetype":"venue"
},
  "geometry": {"coordinates":[5.57057,51.431164],"type":"Point"}
}