{
  "type": "Feature",
  "properties": {
    "iso:country":"NL",
    "sg:address":"Valkenlaan 27",
    "sg:city":"Maarheeze",
    "sg:orig_category":"Verzekeringen",
    "sg:phone":"+31 495 592 588",
    "sg:postcode":"6026 SG",
    "sg:province":"Noord-Brabant",
    "wof:name":"Assurantie- En Advieskantoor Vlijmincx",
    "wof:placetype":"venue"
},
  "geometry": {"coordinates":[5.643499,51.309017],"type":"Point"}
}