{
  "type": "Feature",
  "properties": {
    "addr:full":"Kruisstr 15 Baarlo Lb Limburg 5991 EM",
    "addr:housenumber":"15",
    "addr:postcode":"lb;5991 em",
    "addr:street":"Kruisstr",
    "iso:country":"NL",
    "sg:address":"Kruisstr 15",
    "sg:city":"Baarlo Lb",
    "sg:classifiers":[
        {
            "category":"Retail",
            "subcategory":"Auto Repair",
            "type":"Services"
        }
    ],
    "sg:phone":"+31 77 477 0977",
    "sg:postcode":"5991 EM",
    "sg:province":"Limburg",
    "sg:tags":[
        "garage"
    ],
    "wof:name":"Pro Usa Cars",
    "wof:placetype":"venue"
},
  "geometry": {"coordinates":[6.089369,51.332668],"type":"Point"}
}