{
  "type": "Feature",
  "properties": {
    "addr:full":"Arendshof 36 Oosterhout Nb North Brabant 4901 LH",
    "addr:housenumber":"36;nb",
    "addr:postcode":"4901 lh",
    "addr:street":"Arendshof",
    "iso:country":"NL",
    "sg:address":"Arendshof 36",
    "sg:city":"Oosterhout Nb",
    "sg:orig_category":"Kunst And Kunstenaarsbenodigdheden",
    "sg:phone":"+31 162 451 438",
    "sg:postcode":"4901 LH",
    "sg:province":"North Brabant",
    "wof:name":"Kunsthandel De Passage",
    "wof:placetype":"venue"
},
  "geometry": {"coordinates":[4.856235,51.643925],"type":"Point"}
}