{
  "type": "Feature",
  "properties": {
    "iso:country":"NL",
    "sg:address":"Meent 133",
    "sg:city":"Rotterdam",
    "sg:orig_category":"Verlichting And Huishoudartikelen",
    "sg:phone":"+31 10 404 6840",
    "sg:postcode":"3011 JH",
    "sg:province":"Zuid-Holland",
    "wof:name":"El Totem",
    "wof:placetype":"venue"
},
  "geometry": {"coordinates":[4.48134,51.921783],"type":"Point"}
}