{
  "type": "Feature",
  "properties": {
    "addr:full":"Karel Doormanstraat 35 Genemuiden Overijssel 8281 DJ",
    "addr:housenumber":"35",
    "addr:postcode":"8281 dj",
    "addr:street":"Karel Doormanstraat",
    "iso:country":"NL",
    "sg:address":"Karel Doormanstraat 35",
    "sg:city":"Genemuiden",
    "sg:orig_category":"Onderhoud And Reparatie Kantoorapparatuur",
    "sg:phone":"+31 38 385 6966",
    "sg:postcode":"8281 DJ",
    "sg:province":"Overijssel",
    "wof:name":"Pebo",
    "wof:placetype":"venue"
},
  "geometry": {"coordinates":[6.046188,52.619293],"type":"Point"}
}