{
  "type": "Feature",
  "properties": {
    "addr:full":"Kinderhuissngl 6J Haarlem Noord-Holland 2013 AS",
    "addr:housenumber":"6j",
    "addr:postcode":"2013 as",
    "addr:street":"Kinderhuissngl",
    "iso:country":"NL",
    "sg:address":"Kinderhuissngl 6J",
    "sg:city":"Haarlem",
    "sg:orig_category":"Beeldende Kunstenaars",
    "sg:phone":"+31 23 531 2114",
    "sg:postcode":"2013 AS",
    "sg:province":"Noord-Holland",
    "wof:name":"Krijnen, Cees",
    "wof:placetype":"venue"
},
  "geometry": {"coordinates":[4.642253,52.380562],"type":"Point"}
}