{
  "type": "Feature",
  "properties": {
    "addr:full":"A Goekoopln 3 S Gravenhage Zuid-Holland 2517 JX",
    "addr:housenumber":"3;gravenhage",
    "addr:postcode":"2517 jx",
    "addr:street":"S",
    "iso:country":"NL",
    "sg:address":"A Goekoopln 3",
    "sg:city":"S Gravenhage",
    "sg:orig_category":"Onroerende Goederen",
    "sg:phone":"+31 70 351 5000",
    "sg:postcode":"2517 JX",
    "sg:province":"Zuid-Holland",
    "wof:name":"Nat Grondbezit Nv, Kon",
    "wof:placetype":"venue"
},
  "geometry": {"coordinates":[4.28708,52.08667],"type":"Point"}
}