{
  "type": "Feature",
  "properties": {
    "addr:full":"Noordeinde 128 S Gravenhage Zuid-Holland 2514 GN",
    "addr:housenumber":"128;gravenhage",
    "addr:postcode":"2514 gn",
    "addr:street":"Noordeinde;S",
    "iso:country":"NL",
    "sg:address":"Noordeinde 128",
    "sg:city":"S Gravenhage",
    "sg:orig_category":"Antiquiteiten",
    "sg:phone":"+31 70 345 1369",
    "sg:postcode":"2514 GN",
    "sg:province":"Zuid-Holland",
    "sg:website":"http://www.vdven.com",
    "wof:name":"Alexander Van De Ven",
    "wof:placetype":"venue"
},
  "geometry": {"coordinates":[4.30935,52.084148],"type":"Point"}
}