{
  "type": "Feature",
  "properties": {
    "iso:country":"NL",
    "sg:address":"Broekergouw 1",
    "sg:city":"Amsterdam",
    "sg:classifiers":[
        {
            "category":"Sports & Exercise",
            "subcategory":"Stables",
            "type":"Entertainment"
        }
    ],
    "sg:phone":"+31 20 636 9456",
    "sg:postcode":"1027 AH",
    "sg:province":"Noord-Holland",
    "sg:tags":[
        "maneges"
    ],
    "wof:name":"Zunderdorp Bv",
    "wof:placetype":"venue"
},
  "geometry": {"coordinates":[4.969021,52.411736],"type":"Point"}
}