{
  "type": "Feature",
  "properties": {
    "addr:full":"Dauwbraam 31 Katwijk Zh South Holland 2224 DA",
    "addr:housenumber":"31",
    "addr:postcode":"zh;2224 da",
    "addr:street":"Dauwbraam",
    "iso:country":"NL",
    "sg:address":"Dauwbraam 31",
    "sg:city":"Katwijk Zh",
    "sg:orig_category":"Bloemen And Planten",
    "sg:phone":"+31 71 403 0660",
    "sg:postcode":"2224 DA",
    "sg:province":"South Holland",
    "wof:name":"R.J. Beking",
    "wof:placetype":"venue"
},
  "geometry": {"coordinates":[4.39656,52.205101],"type":"Point"}
}