{
  "type": "Feature",
  "properties": {
    "addr:full":"L Hei 10 Sprundel Noord-Brabant 4714 RE",
    "addr:housenumber":"10",
    "addr:postcode":"4714 re",
    "addr:street":"L Hei",
    "iso:country":"NL",
    "sg:address":"L Hei 10",
    "sg:city":"Sprundel",
    "sg:classifiers":[
        {
            "category":"Manufacturing",
            "subcategory":"Textiles",
            "type":"Manufacturing & Wholesale Goods"
        }
    ],
    "sg:phone":"+31 165 387 933",
    "sg:postcode":"4714 RE",
    "sg:province":"Noord-Brabant",
    "sg:tags":[
        "polyester"
    ],
    "wof:name":"Damo Polyesterverwerking",
    "wof:placetype":"venue"
},
  "geometry": {"coordinates":[4.601045,51.538265],"type":"Point"}
}