{
  "type": "Feature",
  "properties": {
    "addr:full":"Soerenseweg 67 Apeldoorn Gelderland 7314 JE",
    "addr:housenumber":"67",
    "addr:postcode":"7314 je",
    "addr:street":"Soerenseweg;Gelderland",
    "iso:country":"NL",
    "sg:address":"Soerenseweg 67",
    "sg:city":"Apeldoorn",
    "sg:orig_category":"Fietshandelaren",
    "sg:phone":"+31 55 355 2090",
    "sg:postcode":"7314 JE",
    "sg:province":"Gelderland",
    "wof:name":"Rijwiel En Motorenhdl J R Sinninghe Damste",
    "wof:placetype":"venue"
},
  "geometry": {"coordinates":[5.94175,52.219795],"type":"Point"}
}