{
  "type": "Feature",
  "properties": {
    "addr:full":"Struytse Hoeck 313 Hellevoetsluis Zuid-Holland 3223 DE",
    "addr:housenumber":"313",
    "addr:postcode":"3223 de",
    "addr:street":"Struytse Hoeck",
    "iso:country":"NL",
    "sg:address":"Struytse Hoeck 313",
    "sg:city":"Hellevoetsluis",
    "sg:orig_category":"Schoenen",
    "sg:phone":"+31 181 399 089",
    "sg:postcode":"3223 DE",
    "sg:province":"Zuid-Holland",
    "wof:name":"Haren Bv, Van",
    "wof:placetype":"venue"
},
  "geometry": {"coordinates":[4.145144,51.829445],"type":"Point"}
}