{
  "type": "Feature",
  "properties": {
    "addr:full":"Dorpsstraat 118 De Bilt Utrecht 3732 HL",
    "addr:housenumber":"118",
    "addr:postcode":"3732 hl",
    "addr:street":"Dorpsstraat",
    "iso:country":"NL",
    "sg:address":"Dorpsstraat 118",
    "sg:city":"De Bilt",
    "sg:orig_category":"Verzekeringen",
    "sg:phone":"+31 30 220 4114",
    "sg:postcode":"3732 HL",
    "sg:province":"Utrecht",
    "wof:name":"Raadgevers Medische Beroepen",
    "wof:placetype":"venue"
},
  "geometry": {"coordinates":[5.177578,52.103451],"type":"Point"}
}