{
  "type": "Feature",
  "properties": {
    "iso:country":"NL",
    "sg:address":"Osseweg 2",
    "sg:city":"Berghem",
    "sg:orig_category":"Kappers",
    "sg:phone":"+31 412 401 566",
    "sg:postcode":"5351 AD",
    "sg:province":"Noord-Brabant",
    "wof:name":"F.C.M. V.D. Sloot",
    "wof:placetype":"venue"
},
  "geometry": {"coordinates":[5.5636110306,51.7692260742],"type":"Point"}
}