{
  "type": "Feature",
  "properties": {
    "addr:full":"F Vd Paltshof 46 Rhenen Utrecht 3911 LB",
    "addr:housenumber":"46",
    "addr:postcode":"3911 lb",
    "iso:country":"NL",
    "sg:address":"F Vd Paltshof 46",
    "sg:city":"Rhenen",
    "sg:orig_category":"Bloemen En Planten",
    "sg:phone":"+31 317 612 784",
    "sg:postcode":"3911 LB",
    "sg:province":"Utrecht",
    "wof:name":"Marco",
    "wof:placetype":"venue"
},
  "geometry": {"coordinates":[5.566082,51.957542],"type":"Point"}
}