{
  "type": "Feature",
  "properties": {
    "addr:full":"Ekkersrijt 2025 Son Texas 5692  B",
    "addr:housenumber":"2025;5692 b",
    "addr:street":"Ekkersrijt;Texas",
    "iso:country":"NL",
    "sg:address":"Ekkersrijt 2025",
    "sg:city":"Son",
    "sg:orig_category":"Vers Brood And Banket Fab",
    "sg:phone":"+31 499 472 215",
    "sg:postcode":"5692  B",
    "sg:province":"Texas",
    "wof:name":"Luxe Bakkerij Schoonderwoerd",
    "wof:placetype":"venue"
},
  "geometry": {"coordinates":[-101.937622,35.189621],"type":"Point"}
}