{
  "type": "Feature",
  "properties": {
    "addr:full":"Schoolstr 6B Bathmen NL.08 7437 AE",
    "addr:housenumber":"6b;nl.08",
    "addr:postcode":"7437 ae",
    "addr:street":"Schoolstr",
    "iso:country":"NL",
    "sg:address":"Schoolstr 6B",
    "sg:city":"Bathmen",
    "sg:orig_category":"Verenigingsgebouwen",
    "sg:phone":"+31 570 541 655",
    "sg:postcode":"7437 AE",
    "sg:province":"NL.08",
    "wof:name":"Soc Kult Werk",
    "wof:placetype":"venue"
},
  "geometry": {"coordinates":[6.286367,52.249676],"type":"Point"}
}