{
  "type": "Feature",
  "properties": {
    "addr:full":"Uilenburgerwerf 24 Amsterdam Noord-Holland 1011 MZ",
    "addr:housenumber":"24",
    "addr:postcode":"1011 mz",
    "addr:street":"Uilenburgerwerf",
    "iso:country":"NL",
    "sg:address":"Uilenburgerwerf 24",
    "sg:city":"Amsterdam",
    "sg:orig_category":"Loopbaanbegeleiding",
    "sg:phone":"+31 20 423 6423",
    "sg:postcode":"1011 MZ",
    "sg:province":"Noord-Holland",
    "wof:name":"Os, Van",
    "wof:placetype":"venue"
},
  "geometry": {"coordinates":[4.904509,52.370075],"type":"Point"}
}