{
  "type": "Feature",
  "properties": {
    "addr:full":"Koekoekslaan 47 Schiedam South Holland 3121 XJ",
    "addr:housenumber":"47",
    "addr:postcode":"3121 xj",
    "addr:street":"Koekoekslaan",
    "iso:country":"NL",
    "sg:address":"Koekoekslaan 47",
    "sg:city":"Schiedam",
    "sg:orig_category":"Goederenvervoer Over De Weg",
    "sg:phone":"+31 10 470 2962",
    "sg:postcode":"3121 XJ",
    "sg:province":"South Holland",
    "wof:name":"Van Lingen Transporten Bv",
    "wof:placetype":"venue"
},
  "geometry": {"coordinates":[4.382453,51.935089],"type":"Point"}
}