{
  "type": "Feature",
  "properties": {
    "addr:full":"Vd Vennestraat 127 Den Haag South Holland 2525 CC",
    "addr:housenumber":"127",
    "addr:postcode":"2525 cc",
    "addr:street":"Vennestraat",
    "iso:country":"NL",
    "sg:address":"Vd Vennestraat 127",
    "sg:city":"Den Haag",
    "sg:orig_category":"Werving And Selectie Van Tijdelijk Personeel And Uitzendkantoren",
    "sg:phone":"+31 70 402 0208",
    "sg:postcode":"2525 CC",
    "sg:province":"South Holland",
    "wof:name":"Momba",
    "wof:placetype":"venue"
},
  "geometry": {"coordinates":[4.3020977974,52.0661048889],"type":"Point"}
}