{
  "type": "Feature",
  "properties": {
    "addr:full":"Veerwg 46 Papendrecht South Holland 3353 GT",
    "addr:housenumber":"46",
    "addr:postcode":"3353 gt",
    "addr:street":"Veerwg",
    "iso:country":"NL",
    "sg:address":"Veerwg 46",
    "sg:city":"Papendrecht",
    "sg:orig_category":"Kappers",
    "sg:phone":"+31 78 642 7980",
    "sg:postcode":"3353 GT",
    "sg:province":"South Holland",
    "wof:name":"Trendy Hair",
    "wof:placetype":"venue"
},
  "geometry": {"coordinates":[4.684102,51.826515],"type":"Point"}
}