{
  "type": "Feature",
  "properties": {
    "addr:full":"Rietdekkersdreef 729 Apeldoorn Gelderland 7328 AL",
    "addr:housenumber":"729",
    "addr:postcode":"7328",
    "addr:street":"Rietdekkersdreef;Gelderland",
    "iso:country":"NL",
    "sg:address":"Rietdekkersdreef 729",
    "sg:city":"Apeldoorn",
    "sg:orig_category":"Verhuur Bouwmachines",
    "sg:phone":"+31 55 542 1050",
    "sg:postcode":"7328 AL",
    "sg:province":"Gelderland",
    "wof:name":"Boeff Minigravers Apeldoorn",
    "wof:placetype":"venue"
},
  "geometry": {"coordinates":[5.984381,52.195225],"type":"Point"}
}