{
  "type": "Feature",
  "properties": {
    "addr:full":"Memlingstr 9 Amsterdam Noord-Holland 1077 LP",
    "addr:housenumber":"9",
    "addr:postcode":"1077 lp",
    "addr:street":"Memlingstr",
    "iso:country":"NL",
    "sg:address":"Memlingstr 9",
    "sg:city":"Amsterdam",
    "sg:orig_category":"Homeopathie",
    "sg:phone":"+31 20 673 4652",
    "sg:postcode":"1077 LP",
    "sg:province":"Noord-Holland",
    "wof:name":"Gelder, L Van",
    "wof:placetype":"venue"
},
  "geometry": {"coordinates":[4.874779,52.349995],"type":"Point"}
}