{
  "type": "Feature",
  "properties": {
    "iso:country":"NL",
    "sg:address":"Lammenschansweg 138",
    "sg:city":"Leiden",
    "sg:orig_category":"Meubelzaken, Woning- And Keukeninrichting",
    "sg:phone":"+31 71 576 6013",
    "sg:postcode":"2321 JX",
    "sg:province":"Zuid-Holland",
    "wof:name":"Old Inn Wonen",
    "wof:placetype":"venue"
},
  "geometry": {"coordinates":[4.488906,52.143425],"type":"Point"}
}