{
  "type": "Feature",
  "properties": {
    "addr:full":"Molenweg 49 Gorssel Gelderland 7213 XC",
    "addr:housenumber":"49",
    "addr:postcode":"7213 xc",
    "addr:street":"Molenweg;Gelderland",
    "iso:country":"NL",
    "sg:address":"Molenweg 49",
    "sg:city":"Gorssel",
    "sg:orig_category":"Huishoudapparatuur, Televisies And Radio'S",
    "sg:phone":"+31 575 491 350",
    "sg:postcode":"7213 XC",
    "sg:province":"Gelderland",
    "wof:name":"G.R. Kluin",
    "wof:placetype":"venue"
},
  "geometry": {"coordinates":[6.201893,52.202946],"type":"Point"}
}