{
  "type": "Feature",
  "properties": {
    "addr:full":"Boekelsedijk 6 Zeeland Noord-Brabant 5411 NW",
    "addr:housenumber":"6",
    "addr:postcode":"5411 nw",
    "addr:street":"Boekelsedijk",
    "iso:country":"NL",
    "sg:address":"Boekelsedijk 6",
    "sg:city":"Zeeland",
    "sg:orig_category":"Landbouwmachines Gh",
    "sg:phone":"+31 486 452 708",
    "sg:postcode":"5411 NW",
    "sg:province":"Noord-Brabant",
    "wof:name":"Handelsonderneming H. Trienekens Bv",
    "wof:placetype":"venue"
},
  "geometry": {"coordinates":[5.671996,51.683159],"type":"Point"}
}