{
  "type": "Feature",
  "properties": {
    "addr:full":"Handelsstraat 38 Hardenberg Overijssel 7772 TR",
    "addr:housenumber":"38",
    "addr:postcode":"7772 tr",
    "addr:street":"Handelsstraat",
    "iso:country":"NL",
    "sg:address":"Handelsstraat 38",
    "sg:city":"Hardenberg",
    "sg:orig_category":"Geluidsopnamen",
    "sg:phone":"+31 523 264 309",
    "sg:postcode":"7772 TR",
    "sg:province":"Overijssel",
    "wof:name":"Eagle Music Recordings Emr",
    "wof:placetype":"venue"
},
  "geometry": {"coordinates":[6.637757,52.559692],"type":"Point"}
}