{
  "type": "Feature",
  "properties": {
    "addr:full":"Dreef 115 Leersum Utrecht 3956 ES",
    "addr:housenumber":"115",
    "addr:postcode":"3956 es",
    "addr:street":"Dreef",
    "iso:country":"NL",
    "sg:address":"Dreef 115",
    "sg:city":"Leersum",
    "sg:orig_category":"Verenigingsgebouwen",
    "sg:phone":"+31 343 452 735",
    "sg:postcode":"3956 ES",
    "sg:province":"Utrecht",
    "wof:name":"Hervormd Centr De Kolk",
    "wof:placetype":"venue"
},
  "geometry": {"coordinates":[5.42201,52.010792],"type":"Point"}
}