{
  "type": "Feature",
  "properties": {
    "iso:country":"NL",
    "sg:address":"Berenkoog 51",
    "sg:city":"Alkmaar",
    "sg:orig_category":"Boekbinderijen",
    "sg:phone":"+31 72 561 4664",
    "sg:postcode":"1822 BN",
    "sg:province":"Noord-Holland",
    "wof:name":"Verkerke Bv",
    "wof:placetype":"venue"
},
  "geometry": {"coordinates":[4.789027,52.652847],"type":"Point"}
}