{
  "type": "Feature",
  "properties": {
    "addr:full":"Esserhaag 6 Groningen Groningen 9722 RW",
    "addr:housenumber":"6",
    "addr:postcode":"9722 rw",
    "addr:street":"Esserhaag",
    "iso:country":"NL",
    "sg:address":"Esserhaag 6",
    "sg:city":"Groningen",
    "sg:orig_category":"Verenigingen En Stichtingen",
    "sg:phone":"+31 50 525 3043",
    "sg:postcode":"9722 RW",
    "sg:province":"Groningen",
    "wof:name":"Bekker Toonkunstkoor",
    "wof:placetype":"venue"
},
  "geometry": {"coordinates":[6.592181,53.191692],"type":"Point"}
}