{
  "type": "Feature",
  "properties": {
    "iso:country":"NL",
    "sg:address":"Couwenhoven 1100",
    "sg:city":"Zeist",
    "sg:orig_category":"Omroep",
    "sg:phone":"+31 30 691 2040",
    "sg:postcode":"3703 VV",
    "sg:province":"Utrecht",
    "sg:website":"http://www.slotstad.nl",
    "wof:name":"Slotstad Rtv",
    "wof:placetype":"venue"
},
  "geometry": {"coordinates":[5.221219,52.080135],"type":"Point"}
}