{
  "type": "Feature",
  "properties": {
    "addr:full":"James Wattstraat 25 Alkmaar North Holland 1817 DC",
    "addr:housenumber":"25",
    "addr:postcode":"1817",
    "addr:street":"James Wattstraat",
    "iso:country":"NL",
    "sg:address":"James Wattstraat 25",
    "sg:city":"Alkmaar",
    "sg:orig_category":"Diverse Grafische Activiteiten",
    "sg:phone":"+31 72 571 8083",
    "sg:postcode":"1817 DC",
    "sg:province":"North Holland",
    "wof:name":"Tebulo Engineering Bv",
    "wof:placetype":"venue"
},
  "geometry": {"coordinates":[4.739245,52.64962],"type":"Point"}
}