{
  "type": "Feature",
  "properties": {
    "addr:full":"Prins Hendriklaan 21 Utrecht Utrecht 3583 EB",
    "addr:housenumber":"21",
    "addr:postcode":"3583 eb",
    "addr:street":"Prins Hendriklaan",
    "iso:country":"NL",
    "sg:address":"Prins Hendriklaan 21",
    "sg:city":"Utrecht",
    "sg:orig_category":"Advocaten And Juridische Adviseurs",
    "sg:phone":"+31 30 252 1802",
    "sg:postcode":"3583 EB",
    "sg:province":"Utrecht",
    "wof:name":"Tomlow Advokaten",
    "wof:placetype":"venue"
},
  "geometry": {"coordinates":[5.14354,52.086311],"type":"Point"}
}