{
  "type": "Feature",
  "properties": {
    "addr:full":"Beneluxpad 5 Bergen Op Zoom North Brabant 4614 KG",
    "addr:housenumber":"5",
    "addr:postcode":"4614 kg",
    "addr:street":"Beneluxpad",
    "iso:country":"NL",
    "sg:address":"Beneluxpad 5",
    "sg:city":"Bergen Op Zoom",
    "sg:orig_category":"Juridische Adviseurs",
    "sg:phone":"+31 164 643 158",
    "sg:postcode":"4614 KG",
    "sg:province":"North Brabant",
    "wof:name":"Adviespraktijk, De",
    "wof:placetype":"venue"
},
  "geometry": {"coordinates":[4.286128,51.509403],"type":"Point"}
}