{
  "type": "Feature",
  "properties": {
    "iso:country":"NL",
    "sg:address":"Rokkeveensewg Z 125",
    "sg:city":"Zoetermeer",
    "sg:orig_category":"Glazenwasserijen",
    "sg:phone":"+31 79 363 0559",
    "sg:postcode":"2718 EM",
    "sg:province":"South Holland",
    "wof:name":"Schneider",
    "wof:placetype":"venue"
},
  "geometry": {"coordinates":[4.499161,52.043903],"type":"Point"}
}