{
  "type": "Feature",
  "properties": {
    "addr:full":"Oosterveldsestraat 90 Emmen Drenthe 7826 HA",
    "addr:housenumber":"90",
    "addr:postcode":"7826 ha",
    "addr:street":"Oosterveldsestraat",
    "iso:country":"NL",
    "sg:address":"Oosterveldsestraat 90",
    "sg:city":"Emmen",
    "sg:classifiers":[
        {
            "category":"Education",
            "subcategory":"Preschool",
            "type":"Public Place"
        }
    ],
    "sg:phone":"+31 591 629 364",
    "sg:postcode":"7826 HA",
    "sg:province":"Drenthe",
    "sg:tags":[
        "kleuteronderwijs",
        "basis-"
    ],
    "wof:name":"Openbare Basisschool Op 'T Veld",
    "wof:placetype":"venue"
},
  "geometry": {"coordinates":[6.953466,52.768414],"type":"Point"}
}