{
  "type": "Feature",
  "properties": {
    "addr:full":"De Ruyterstr 7 Huizen North Holland 1271 SR",
    "addr:housenumber":"7",
    "addr:postcode":"1271 sr",
    "iso:country":"NL",
    "sg:address":"De Ruyterstr 7",
    "sg:city":"Huizen",
    "sg:orig_category":"Logopedisten",
    "sg:phone":"+31 35 523 2676",
    "sg:postcode":"1271 SR",
    "sg:province":"North Holland",
    "wof:name":"Visnet, 'T",
    "wof:placetype":"venue"
},
  "geometry": {"coordinates":[5.229558,52.29776],"type":"Point"}
}