{
  "type": "Feature",
  "properties": {
    "addr:full":"Kranenstg 4 Deventer Overijssel 7411 NN",
    "addr:housenumber":"4",
    "addr:postcode":"7411 nn",
    "addr:street":"Kranenstg",
    "iso:country":"NL",
    "sg:address":"Kranenstg 4",
    "sg:city":"Deventer",
    "sg:orig_category":"Handwerkartikelen",
    "sg:phone":"+31 570 641 320",
    "sg:postcode":"7411 NN",
    "sg:province":"Overijssel",
    "wof:name":"Min, J I Van",
    "wof:placetype":"venue"
},
  "geometry": {"coordinates":[6.214359,52.252972],"type":"Point"}
}