{
  "type": "Feature",
  "properties": {
    "addr:full":"Breedeln 36/A Heiloo Noord-Holland 1851 MD",
    "addr:housenumber":"36 / a",
    "addr:postcode":"1851",
    "addr:street":"Breedeln",
    "iso:country":"NL",
    "sg:address":"Breedeln 36/A",
    "sg:city":"Heiloo",
    "sg:orig_category":"Adviesbureaus Bouwkunde",
    "sg:phone":"+31 72 533 3572",
    "sg:postcode":"1851 MD",
    "sg:province":"Noord-Holland",
    "wof:name":"Nwe",
    "wof:placetype":"venue"
},
  "geometry": {"coordinates":[4.713702,52.604191],"type":"Point"}
}