{
  "type": "Feature",
  "properties": {
    "addr:full":"Polder 6 Wormer North Holland 1531 NL",
    "addr:housenumber":"6",
    "addr:postcode":"1531 nl",
    "addr:street":"Polder",
    "iso:country":"NL",
    "sg:address":"Polder 6",
    "sg:city":"Wormer",
    "sg:orig_category":"Beursorganisaties And Standbouw",
    "sg:phone":"+31 75 642 7986",
    "sg:postcode":"1531 NL",
    "sg:province":"North Holland",
    "wof:name":"B. Kef",
    "wof:placetype":"venue"
},
  "geometry": {"coordinates":[4.810272,52.493999],"type":"Point"}
}