{
  "type": "Feature",
  "properties": {
    "iso:country":"NL",
    "sg:address":"Victoriberg 63",
    "sg:city":"Noordwijkerhout",
    "sg:orig_category":"Bloemen And Planten Gh",
    "sg:phone":"+31 252 340 599",
    "sg:postcode":"2211 DM",
    "sg:province":"Zuid-Holland",
    "wof:name":"Betty",
    "wof:placetype":"venue"
},
  "geometry": {"coordinates":[4.490351,52.262276],"type":"Point"}
}