{
  "type": "Feature",
  "properties": {
    "addr:full":"Kempenaar 2637 Lelystad Flevoland 8231 CJ",
    "addr:postcode":"2637;8231 cj",
    "addr:street":"Kempenaar;Flevoland",
    "iso:country":"NL",
    "sg:address":"Kempenaar 2637",
    "sg:city":"Lelystad",
    "sg:orig_category":"Administratie- En Boekhoudkantoren",
    "sg:phone":"+31 320 222 937",
    "sg:postcode":"8231 CJ",
    "sg:province":"Flevoland",
    "wof:name":"Benri Na",
    "wof:placetype":"venue"
},
  "geometry": {"coordinates":[5.469924,52.519093],"type":"Point"}
}