{
  "type": "Feature",
  "properties": {
    "addr:full":"Valeriusstr 86 Amsterdam Noord-Holland 1071 MN",
    "addr:housenumber":"86",
    "addr:postcode":"1071 mn",
    "addr:street":"Valeriusstr",
    "iso:country":"NL",
    "sg:address":"Valeriusstr 86",
    "sg:city":"Amsterdam",
    "sg:orig_category":"Adviesbureaus Bedrijfsorganisatie",
    "sg:phone":"+31 20 662 1350",
    "sg:postcode":"1071 MN",
    "sg:province":"Noord-Holland",
    "wof:name":"Iparto Bv",
    "wof:placetype":"venue"
},
  "geometry": {"coordinates":[4.869274,52.354443],"type":"Point"}
}