{
  "type": "Feature",
  "properties": {
    "iso:country":"NL",
    "sg:address":"Grotestraat 6",
    "sg:city":"Gendringen",
    "sg:orig_category":"Verlichting And Huishoudartikelen",
    "sg:phone":"+31 315 681 391",
    "sg:postcode":"7081 CE",
    "sg:province":"Gelderland",
    "wof:name":"J.A. Rietman Novalux Vof",
    "wof:placetype":"venue"
},
  "geometry": {"coordinates":[6.379057,51.87117],"type":"Point"}
}