{
  "type": "Feature",
  "properties": {
    "addr:full":"Beneluxln 909 Utrecht Utrecht 3526 KK",
    "addr:housenumber":"909",
    "addr:postcode":"3526 kk",
    "iso:country":"NL",
    "sg:address":"Beneluxln 909",
    "sg:city":"Utrecht",
    "sg:orig_category":"Verenigingen En Stichtingen",
    "sg:phone":"+31 30 284 4532",
    "sg:postcode":"3526 KK",
    "sg:province":"Utrecht",
    "wof:name":"Rim",
    "wof:placetype":"venue"
},
  "geometry": {"coordinates":[5.102438,52.068104],"type":"Point"}
}