{
  "type": "Feature",
  "properties": {
    "addr:full":"Postbus 812 Sittard Limburg 6130 AV",
    "addr:housenumber":"812",
    "addr:postcode":"6130 av",
    "addr:street":"Postbus",
    "iso:country":"NL",
    "sg:address":"Postbus 812",
    "sg:city":"Sittard",
    "sg:orig_category":"Organisatiebureaus",
    "sg:phone":"+31 46 474 5484",
    "sg:postcode":"6130 AV",
    "sg:province":"Limburg",
    "wof:name":"Vanderlyde",
    "wof:placetype":"venue"
},
  "geometry": {"coordinates":[5.8629198074,50.998298645],"type":"Point"}
}