{
  "type": "Feature",
  "properties": {
    "addr:full":"Willemsweg 1 Schoondijke Zeeland 4507 AR",
    "addr:housenumber":"1",
    "addr:postcode":"4507",
    "addr:street":"Willemsweg",
    "iso:country":"NL",
    "sg:address":"Willemsweg 1",
    "sg:city":"Schoondijke",
    "sg:orig_category":"Makelaars In Onroerend Goed",
    "sg:phone":"+31 117 401 970",
    "sg:postcode":"4507 AR",
    "sg:province":"Zeeland",
    "wof:name":"Hateka Assurantie- En Makelaarskantoor",
    "wof:placetype":"venue"
},
  "geometry": {"coordinates":[3.556213,51.353271],"type":"Point"}
}