{
  "type": "Feature",
  "properties": {
    "iso:country":"NL",
    "sg:address":"Coldenhovenseweg 5",
    "sg:city":"Eerbeek",
    "sg:classifiers":[
        {
            "category":"Fast Food",
            "type":"Food & Drink"
        }
    ],
    "sg:phone":"+31 313 654 910",
    "sg:postcode":"6961 EA",
    "sg:province":"Gelderland",
    "sg:tags":[
        "afhaal",
        "restaurant"
    ],
    "wof:name":"Cafetaria Kokkie",
    "wof:placetype":"venue"
},
  "geometry": {"coordinates":[6.066057,52.1045],"type":"Point"}
}