{
  "type": "Feature",
  "properties": {
    "iso:country":"NL",
    "sg:address":"Varsenerpoort 9",
    "sg:city":"Ommen",
    "sg:orig_category":"Opticiens",
    "sg:phone":"+31 529 451 753",
    "sg:postcode":"7731 DG",
    "sg:province":"NL.08",
    "wof:name":"Pearle Opticiens",
    "wof:placetype":"venue"
},
  "geometry": {"coordinates":[6.4229111671,52.5192337036],"type":"Point"}
}