{
  "type": "Feature",
  "properties": {
    "addr:full":"Bunuellaan 26 Almere Flevoland 1325 PL",
    "addr:housenumber":"26",
    "addr:postcode":"1325 pl",
    "addr:street":"Bunuellaan;Flevoland",
    "iso:country":"NL",
    "sg:address":"Bunuellaan 26",
    "sg:city":"Almere",
    "sg:orig_category":"Fotolaboratoria",
    "sg:phone":"+31 36 537 9355",
    "sg:postcode":"1325 PL",
    "sg:province":"Flevoland",
    "wof:name":"Foto Doorman",
    "wof:placetype":"venue"
},
  "geometry": {"coordinates":[5.242142,52.363579],"type":"Point"}
}