{
  "type": "Feature",
  "properties": {
    "addr:full":"Donstr 6 Assen Drenthe 9406 RZ",
    "addr:housenumber":"6",
    "addr:postcode":"9406 rz",
    "addr:street":"Donstr",
    "iso:country":"NL",
    "sg:address":"Donstr 6",
    "sg:city":"Assen",
    "sg:orig_category":"Kantoorbenodigdheden",
    "sg:phone":"+31 592 460 520",
    "sg:postcode":"9406 RZ",
    "sg:province":"Drenthe",
    "sg:website":"http://www.afdruk.nl",
    "wof:name":"Afdruk.Nl",
    "wof:placetype":"venue"
},
  "geometry": {"coordinates":[6.5440602303,53.0064430237],"type":"Point"}
}