{
  "type": "Feature",
  "properties": {
    "iso:country":"NL",
    "sg:address":"Kerkstr 33",
    "sg:city":"Nieuwaal",
    "sg:orig_category":"Scholen Voor Basisonderwijs",
    "sg:phone":"+31 418 561 614",
    "sg:postcode":"5313 AP",
    "sg:province":"Gelderland",
    "wof:name":"Regenboog, De",
    "wof:placetype":"venue"
},
  "geometry": {"coordinates":[5.177097,51.809608],"type":"Point"}
}