{
  "type": "Feature",
  "properties": {
    "addr:full":"Raadhuislaan 91 Spijkenisse Zuid-Holland 3201 EM",
    "addr:housenumber":"91",
    "addr:postcode":"3201 em",
    "addr:street":"Raadhuislaan",
    "iso:country":"NL",
    "sg:address":"Raadhuislaan 91",
    "sg:city":"Spijkenisse",
    "sg:orig_category":"Banken And Kredietinstellingen",
    "sg:phone":"+31 181 654 500",
    "sg:postcode":"3201 EM",
    "sg:province":"Zuid-Holland",
    "wof:name":"Abn Amro",
    "wof:placetype":"venue"
},
  "geometry": {"coordinates":[4.329085,51.847618],"type":"Point"}
}