{
  "type": "Feature",
  "properties": {
    "iso:country":"NL",
    "sg:address":"Venewg 57",
    "sg:city":"Wanneperveen",
    "sg:orig_category":"Wolartikelen En Breiwol",
    "sg:phone":"+31 522 281 260",
    "sg:postcode":"7946 LD",
    "sg:province":"Overijssel",
    "wof:name":"Boer, J De",
    "wof:placetype":"venue"
},
  "geometry": {"coordinates":[6.1290659904,52.7049293518],"type":"Point"}
}