{
  "type": "Feature",
  "properties": {
    "addr:full":"Verhammestr 7 Heemskerk Noord-Holland 1964 TG",
    "addr:housenumber":"7",
    "addr:postcode":"1964 tg",
    "addr:street":"Verhammestr",
    "iso:country":"NL",
    "sg:address":"Verhammestr 7",
    "sg:city":"Heemskerk",
    "sg:orig_category":"Afzuiginstallaties",
    "sg:phone":"+31 251 254 535",
    "sg:postcode":"1964 TG",
    "sg:province":"Noord-Holland",
    "wof:name":"Valkhoff",
    "wof:placetype":"venue"
},
  "geometry": {"coordinates":[4.664607,52.509754],"type":"Point"}
}