{
  "type": "Feature",
  "properties": {
    "addr:full":"Zuiderveldwg 14A Putten Gelderland 3881 LJ",
    "addr:housenumber":"14a;lj",
    "addr:postcode":"3881",
    "addr:street":"Zuiderveldwg;Gelderland",
    "iso:country":"NL",
    "sg:address":"Zuiderveldwg 14A",
    "sg:city":"Putten",
    "sg:orig_category":"Grondwerken",
    "sg:phone":"+31 341 360 855",
    "sg:postcode":"3881 LJ",
    "sg:province":"Gelderland",
    "wof:name":"Broek Kraanverhuur, G Van Den",
    "wof:placetype":"venue"
},
  "geometry": {"coordinates":[5.605699,52.273235],"type":"Point"}
}