{
  "type": "Feature",
  "properties": {
    "iso:country":"NL",
    "sg:address":"Hadewijchstraat 31",
    "sg:city":"Alkmaar",
    "sg:classifiers":[
        {
            "category":"Fast Food",
            "type":"Food & Drink"
        }
    ],
    "sg:phone":"+31 72 540 0497",
    "sg:postcode":"1813 JG",
    "sg:province":"North Holland",
    "sg:tags":[
        "afhaal",
        "restaurant"
    ],
    "wof:name":"Hong Kong Chinees-Indisch Restaurant",
    "wof:placetype":"venue"
},
  "geometry": {"coordinates":[4.754017,52.617649],"type":"Point"}
}