{
  "type": "Feature",
  "properties": {
    "addr:full":"George Van Saksenlaan 1 Appingedam Groningen 9902 JA",
    "addr:housenumber":"1",
    "addr:postcode":"9902 ja",
    "addr:street":"George Van Saksenlaan",
    "iso:country":"NL",
    "sg:address":"George Van Saksenlaan 1",
    "sg:city":"Appingedam",
    "sg:orig_category":"Fitnesscentra",
    "sg:phone":"+31 596 623 209",
    "sg:postcode":"9902 JA",
    "sg:province":"Groningen",
    "wof:name":"Gym 2000 (Sportcenter)",
    "wof:placetype":"venue"
},
  "geometry": {"coordinates":[6.8656,53.315819],"type":"Point"}
}