{
  "type": "Feature",
  "properties": {
    "addr:full":"Mercuriusweg 37 Barneveld Gelderland 3771 NC",
    "addr:housenumber":"37;3771",
    "addr:street":"Mercuriusweg;Gelderland",
    "iso:country":"NL",
    "sg:address":"Mercuriusweg 37",
    "sg:city":"Barneveld",
    "sg:orig_category":"Technische Studies And Onderzoek",
    "sg:phone":"+31 342 400 606",
    "sg:postcode":"3771 NC",
    "sg:province":"Gelderland",
    "wof:name":"Pro Monitoring Bv",
    "wof:placetype":"venue"
},
  "geometry": {"coordinates":[5.60414,52.16856],"type":"Point"}
}