{
  "type": "Feature",
  "properties": {
    "addr:full":"Nieuwendk 126 Amsterdam North Holland 1012 MS",
    "addr:housenumber":"126",
    "addr:postcode":"1012 ms",
    "iso:country":"NL",
    "sg:address":"Nieuwendk 126",
    "sg:city":"Amsterdam",
    "sg:orig_category":"Kappers",
    "sg:phone":"+31 20 620 5101",
    "sg:postcode":"1012 MS",
    "sg:province":"North Holland",
    "wof:name":"Collors Hairstylers",
    "wof:placetype":"venue"
},
  "geometry": {"coordinates":[4.8955011368,52.3760566711],"type":"Point"}
}