{
  "type": "Feature",
  "properties": {
    "addr:full":"S Carmiggeltln 10 Hoogezand Groningen 9602 AZ",
    "addr:housenumber":"10",
    "addr:postcode":"9602 az",
    "iso:country":"NL",
    "sg:address":"S Carmiggeltln 10",
    "sg:city":"Hoogezand",
    "sg:orig_category":"Bloemen En Planten",
    "sg:phone":"+31 598 327 584",
    "sg:postcode":"9602 AZ",
    "sg:province":"Groningen",
    "wof:name":"Meijer, S",
    "wof:placetype":"venue"
},
  "geometry": {"coordinates":[6.740414,53.160107],"type":"Point"}
}