{
  "type": "Feature",
  "properties": {
    "iso:country":"NL",
    "sg:address":"Aletta Jacobsstraat 93",
    "sg:city":"Heemskerk",
    "sg:orig_category":"Bloemen And Planten",
    "sg:phone":"+31 251 235 751",
    "sg:postcode":"1963 CM",
    "sg:province":"Noord-Holland",
    "wof:name":"Bloemenservice Aad Van Duivenvoorde",
    "wof:placetype":"venue"
},
  "geometry": {"coordinates":[4.685143,52.519367],"type":"Point"}
}