{
  "type": "Feature",
  "properties": {
    "addr:full":"Voorstr 121 Brielle Zuid-Holland 3231 BH",
    "addr:housenumber":"121",
    "addr:postcode":"3231 bh",
    "iso:country":"NL",
    "sg:address":"Voorstr 121",
    "sg:city":"Brielle",
    "sg:orig_category":"Makelaars En Adviseurs Onroerende Goederen",
    "sg:phone":"+31 181 416 366",
    "sg:postcode":"3231 BH",
    "sg:province":"Zuid-Holland",
    "wof:name":"Barendregt",
    "wof:placetype":"venue"
},
  "geometry": {"coordinates":[4.167875,51.90406],"type":"Point"}
}