{
  "type": "Feature",
  "properties": {
    "addr:full":"Broeker Werf 8 Broek Op Langedyk Noord-Holland 1721 PC",
    "addr:housenumber":"8",
    "addr:postcode":"1721 pc",
    "addr:street":"Broeker Werf;Op Langedyk",
    "iso:country":"NL",
    "sg:address":"Broeker Werf 8",
    "sg:city":"Broek Op Langedyk",
    "sg:classifiers":[
        {
            "category":"Shopping",
            "subcategory":"News",
            "type":"Retail Goods"
        }
    ],
    "sg:phone":"+31 226 333 311",
    "sg:postcode":"1721 PC",
    "sg:province":"Noord-Holland",
    "sg:tags":[
        "maandbladen",
        "en",
        "week-"
    ],
    "wof:name":"Den Helder Op Zondag",
    "wof:placetype":"venue"
},
  "geometry": {"coordinates":[4.8008918762,52.676235199],"type":"Point"}
}