{
  "type": "Feature",
  "properties": {
    "addr:full":"Ploegstr 31 Purmerend Noord-Holland 1445 RT",
    "addr:housenumber":"31",
    "addr:postcode":"1445 rt",
    "addr:street":"Ploegstr",
    "iso:country":"NL",
    "sg:address":"Ploegstr 31",
    "sg:city":"Purmerend",
    "sg:orig_category":"Accountants - Administratie- Consulenten En -Kantoren",
    "sg:phone":"+31 299 640 303",
    "sg:postcode":"1445 RT",
    "sg:province":"Noord-Holland",
    "wof:name":"Ab & M",
    "wof:placetype":"venue"
},
  "geometry": {"coordinates":[4.977999,52.506001],"type":"Point"}
}