{
  "type": "Feature",
  "properties": {
    "addr:full":"Noordhaven 74 Zevenbergen North Brabant 4761 DC",
    "addr:housenumber":"74",
    "addr:postcode":"4761",
    "addr:street":"Noordhaven",
    "iso:country":"NL",
    "sg:address":"Noordhaven 74",
    "sg:city":"Zevenbergen",
    "sg:orig_category":"Granen, Zaden And Diervoeders Gh",
    "sg:phone":"+31 168 324 093",
    "sg:postcode":"4761 DC",
    "sg:province":"North Brabant",
    "wof:name":"Vof C. Verschuren",
    "wof:placetype":"venue"
},
  "geometry": {"coordinates":[4.605121,51.645252],"type":"Point"}
}