{
  "type": "Feature",
  "properties": {
    "addr:full":"Manderveen 39 Zaandam North Holland 1507 MD",
    "addr:housenumber":"39",
    "addr:postcode":"1507",
    "addr:street":"Manderveen",
    "iso:country":"NL",
    "sg:address":"Manderveen 39",
    "sg:city":"Zaandam",
    "sg:orig_category":"Verbouwingen",
    "sg:phone":"+31 75 631 2647",
    "sg:postcode":"1507 MD",
    "sg:province":"North Holland",
    "wof:name":"Max Hartog",
    "wof:placetype":"venue"
},
  "geometry": {"coordinates":[4.801209,52.453033],"type":"Point"}
}