{
  "type": "Feature",
  "properties": {
    "addr:full":"Groene Hilledk 246 Rotterdam Zuid-Holland 3074 AD",
    "addr:housenumber":"246",
    "addr:postcode":"3074 ad",
    "addr:street":"Groene Hilledk",
    "iso:country":"NL",
    "sg:address":"Groene Hilledk 246",
    "sg:city":"Rotterdam",
    "sg:orig_category":"Boeken En Tijdschriften",
    "sg:phone":"+31 10 419 0564",
    "sg:postcode":"3074 AD",
    "sg:province":"Zuid-Holland",
    "wof:name":"Read Shop, The",
    "wof:placetype":"venue"
},
  "geometry": {"coordinates":[4.508823,51.891426],"type":"Point"}
}