{
  "type": "Feature",
  "properties": {
    "iso:country":"NL",
    "sg:address":"Akerstr 70",
    "sg:city":"Kerkrade",
    "sg:orig_category":"Meubelstoffering",
    "sg:phone":"+31 45 541 2735",
    "sg:postcode":"6466 HL",
    "sg:province":"Limburg",
    "wof:name":"Kloprogge",
    "wof:placetype":"venue"
},
  "geometry": {"coordinates":[6.025851,50.858067],"type":"Point"}
}