{
  "type": "Feature",
  "properties": {
    "addr:full":"Walramstr 19 Sittard Limburg 6131 BK",
    "addr:housenumber":"19",
    "addr:postcode":"6131 bk",
    "addr:street":"Walramstr",
    "iso:country":"NL",
    "sg:address":"Walramstr 19",
    "sg:city":"Sittard",
    "sg:orig_category":"Loopbaanbegeleiding",
    "sg:phone":"+31 46 486 1204",
    "sg:postcode":"6131 BK",
    "sg:province":"Limburg",
    "sg:website":"http://www.lhh.nl",
    "wof:name":"Lee Hecht Harisson Nederland Bv",
    "wof:placetype":"venue"
},
  "geometry": {"coordinates":[5.864559,51.001026],"type":"Point"}
}