{
  "type": "Feature",
  "properties": {
    "addr:full":"Hartwg 62 Soest Utrecht 3762 SG",
    "addr:housenumber":"62",
    "addr:postcode":"3762 sg",
    "addr:street":"Hartwg",
    "iso:country":"NL",
    "sg:address":"Hartwg 62",
    "sg:city":"Soest",
    "sg:orig_category":"Onderwijsmateriaal",
    "sg:phone":"+31 35 602 3103",
    "sg:postcode":"3762 SG",
    "sg:province":"Utrecht",
    "wof:name":"Uiterwijk-Luijk, Drs E",
    "wof:placetype":"venue"
},
  "geometry": {"coordinates":[5.274386,52.184174],"type":"Point"}
}