{
  "type": "Feature",
  "properties": {
    "addr:full":"Markt 8 Veere Zeeland 4351 AH",
    "addr:housenumber":"8",
    "addr:postcode":"4351 ah",
    "addr:street":"Markt",
    "iso:country":"NL",
    "sg:address":"Markt 8",
    "sg:city":"Veere",
    "sg:orig_category":"Damesmodezaken",
    "sg:phone":"+31 118 501 413",
    "sg:postcode":"4351 AH",
    "sg:province":"Zeeland",
    "wof:name":"Boetiek My Way",
    "wof:placetype":"venue"
},
  "geometry": {"coordinates":[3.668018,51.549084],"type":"Point"}
}