{
  "type": "Feature",
  "properties": {
    "addr:full":"Merkebuorren 69 Wijnjewoude Friesland 9241 GC",
    "addr:housenumber":"69",
    "addr:postcode":"9241 gc",
    "addr:street":"Merkebuorren",
    "iso:country":"NL",
    "sg:address":"Merkebuorren 69",
    "sg:city":"Wijnjewoude",
    "sg:orig_category":"Bloemen And Planten",
    "sg:phone":"+31 516 481 237",
    "sg:postcode":"9241 GC",
    "sg:province":"Friesland",
    "wof:name":"Firma Kamminga",
    "wof:placetype":"venue"
},
  "geometry": {"coordinates":[6.203717,53.058014],"type":"Point"}
}