{
  "type": "Feature",
  "properties": {
    "addr:full":"A Tasmanwg 9 Lutjegast Groningen 9866 TA",
    "addr:housenumber":"9",
    "addr:postcode":"9866 ta",
    "addr:street":"Lutjegast",
    "iso:country":"NL",
    "sg:address":"A Tasmanwg 9",
    "sg:city":"Lutjegast",
    "sg:classifiers":[
        {
            "category":"Personal",
            "subcategory":"Nail Salon",
            "type":"Services"
        }
    ],
    "sg:phone":"+31 594 612 003",
    "sg:postcode":"9866 TA",
    "sg:province":"Groningen",
    "sg:tags":[
        "pedicure"
    ],
    "wof:name":"Vegter-Holtrop, G",
    "wof:placetype":"venue"
},
  "geometry": {"coordinates":[6.279108,53.236908],"type":"Point"}
}