{
  "type": "Feature",
  "properties": {
    "addr:full":"F Hendrikln 22B Haarlem Noord-Holland 2012 SH",
    "addr:housenumber":"22b",
    "addr:postcode":"2012 sh",
    "iso:country":"NL",
    "sg:address":"F Hendrikln 22B",
    "sg:city":"Haarlem",
    "sg:orig_category":"Psychologen",
    "sg:phone":"+31 23 547 5505",
    "sg:postcode":"2012 SH",
    "sg:province":"Noord-Holland",
    "wof:name":"Heyning-Van Maanen, Drs J C C",
    "wof:placetype":"venue"
},
  "geometry": {"coordinates":[4.632131,52.361687],"type":"Point"}
}