{
  "type": "Feature",
  "properties": {
    "iso:country":"NL",
    "sg:address":"Nobelstraat 47",
    "sg:city":"Brielle",
    "sg:orig_category":"Huishoudapparatuur, Televisies And Radio'S",
    "sg:phone":"+31 181 415 634",
    "sg:postcode":"3231 BB",
    "sg:province":"Zuid-Holland",
    "wof:name":"Radio Wageveld Film Bv",
    "wof:placetype":"venue"
},
  "geometry": {"coordinates":[4.163868,51.900909],"type":"Point"}
}