{
  "type": "Feature",
  "properties": {
    "iso:country":"NL",
    "sg:address":"Zuidlarenstr 247",
    "sg:city":"S Gravenhage",
    "sg:orig_category":"Administratie- En Boekhoudkantoren",
    "sg:phone":"+31 70 359 5105",
    "sg:postcode":"2545 VV",
    "sg:province":"Zuid-Holland",
    "wof:name":"Goudsteen & De Leeuw Bv",
    "wof:placetype":"venue"
},
  "geometry": {"coordinates":[4.27049,52.05093],"type":"Point"}
}