{
  "type": "Feature",
  "properties": {
    "iso:country":"NL",
    "sg:address":"Wolfhezerwg 63",
    "sg:city":"Wolfheze",
    "sg:orig_category":"Montagebedrijven",
    "sg:phone":"+31 26 482 2006",
    "sg:postcode":"6874 AB",
    "sg:province":"Gelderland",
    "wof:name":"Meerveld, W",
    "wof:placetype":"venue"
},
  "geometry": {"coordinates":[5.792011,52.005165],"type":"Point"}
}