{
  "type": "Feature",
  "properties": {
    "addr:full":"De Vest 20 Valkenswaard Noord-Brabant 5555 XL",
    "addr:housenumber":"20",
    "addr:postcode":"5555 xl",
    "addr:street":"De Vest",
    "iso:country":"NL",
    "sg:address":"De Vest 20",
    "sg:city":"Valkenswaard",
    "sg:orig_category":"Loodgieterswerk, Verwarming And Sanitaire Installaties",
    "sg:phone":"+31 40 201 2241",
    "sg:postcode":"5555 XL",
    "sg:province":"Noord-Brabant",
    "wof:name":"Roycon Installaties Bv",
    "wof:placetype":"venue"
},
  "geometry": {"coordinates":[5.486645,51.348553],"type":"Point"}
}