{
  "type": "Feature",
  "properties": {
    "addr:full":"Corridor 33B Valkenswaard Noord-Brabant 5554 HL",
    "addr:housenumber":"33b",
    "addr:postcode":"5554 hl",
    "addr:street":"Corridor",
    "iso:country":"NL",
    "sg:address":"Corridor 33B",
    "sg:city":"Valkenswaard",
    "sg:orig_category":"Kinderkleding",
    "sg:phone":"+31 40 201 8428",
    "sg:postcode":"5554 HL",
    "sg:province":"Noord-Brabant",
    "wof:name":"Domino",
    "wof:placetype":"venue"
},
  "geometry": {"coordinates":[5.458961,51.3526],"type":"Point"}
}