{
  "type": "Feature",
  "properties": {
    "addr:full":"Akersteenweg 124 Maastricht Limburg 6227 AC",
    "addr:housenumber":"124",
    "addr:postcode":"6227 ac",
    "addr:street":"Akersteenweg",
    "iso:country":"NL",
    "sg:address":"Akersteenweg 124",
    "sg:city":"Maastricht",
    "sg:orig_category":"Goederenvervoer Over De Weg",
    "sg:phone":"+31 43 325 4348",
    "sg:postcode":"6227 AC",
    "sg:province":"Limburg",
    "wof:name":"Selektvracht",
    "wof:placetype":"venue"
},
  "geometry": {"coordinates":[5.728726,50.843304],"type":"Point"}
}