{
  "type": "Feature",
  "properties": {
    "addr:full":"Bretelerstr 16 Hengevelde Overijssel 7496 PP",
    "addr:housenumber":"16",
    "addr:postcode":"7496 pp",
    "addr:street":"Bretelerstr",
    "iso:country":"NL",
    "sg:address":"Bretelerstr 16",
    "sg:city":"Hengevelde",
    "sg:orig_category":"Fitnesscentra",
    "sg:phone":"+31 547 333 710",
    "sg:postcode":"7496 PP",
    "sg:province":"Overijssel",
    "wof:name":"Fysio-Sport En Trainingscentrum",
    "wof:placetype":"venue"
},
  "geometry": {"coordinates":[6.638615,52.197407],"type":"Point"}
}