{
  "type": "Feature",
  "properties": {
    "addr:full":"Dykstr W 176B Veenendaal Utrecht 3906 WR",
    "addr:housenumber":"176b",
    "addr:postcode":"3906 wr",
    "addr:street":"W",
    "iso:country":"NL",
    "sg:address":"Dykstr W 176B",
    "sg:city":"Veenendaal",
    "sg:orig_category":"Administratie- En Boekhoudkantoren",
    "sg:phone":"+31 318 500 656",
    "sg:postcode":"3906 WR",
    "sg:province":"Utrecht",
    "wof:name":"Kievid, De",
    "wof:placetype":"venue"
},
  "geometry": {"coordinates":[5.55418,52.024902],"type":"Point"}
}