{
  "type": "Feature",
  "properties": {
    "addr:full":"S Gravenwg 720 Rotterdam Zuid-Holland 3065 SJ",
    "addr:housenumber":"720",
    "addr:postcode":"3065",
    "iso:country":"NL",
    "sg:address":"S Gravenwg 720",
    "sg:city":"Rotterdam",
    "sg:orig_category":"Adviesbureaus Bedrijfsorganisatie",
    "sg:phone":"+31 10 447 1517",
    "sg:postcode":"3065 SJ",
    "sg:province":"Zuid-Holland",
    "wof:name":"Geos Bv",
    "wof:placetype":"venue"
},
  "geometry": {"coordinates":[4.55832,51.923679],"type":"Point"}
}