{
  "type": "Feature",
  "properties": {
    "addr:full":"Zinniastraat 13 Hilversum North Holland 1214 KN",
    "addr:housenumber":"13",
    "addr:postcode":"1214 kn",
    "addr:street":"Zinniastraat",
    "iso:country":"NL",
    "sg:address":"Zinniastraat 13",
    "sg:city":"Hilversum",
    "sg:orig_category":"Boekhouders",
    "sg:phone":"+31 35 621 3695",
    "sg:postcode":"1214 KN",
    "sg:province":"North Holland",
    "wof:name":"Administratiekantoor Brussee",
    "wof:placetype":"venue"
},
  "geometry": {"coordinates":[5.165642,52.210484],"type":"Point"}
}