{
  "type": "Feature",
  "properties": {
    "addr:full":"De Meesterware 7 Zwolle Overijssel 8014 SB",
    "addr:housenumber":"7",
    "addr:postcode":"8014 sb",
    "addr:street":"De Meesterware",
    "iso:country":"NL",
    "sg:address":"De Meesterware 7",
    "sg:city":"Zwolle",
    "sg:orig_category":"Fotoreportages",
    "sg:phone":"+31 38 460 0858",
    "sg:postcode":"8014 SB",
    "sg:province":"Overijssel",
    "wof:name":"Slotman, Marja",
    "wof:placetype":"venue"
},
  "geometry": {"coordinates":[6.110646,52.478336],"type":"Point"}
}