{
  "type": "Feature",
  "properties": {
    "iso:country":"NL",
    "sg:address":"Amstelkd 186",
    "sg:city":"Amsterdam",
    "sg:orig_category":"Wijnkoperijen En -Groothandel",
    "sg:phone":"+31 20 778 0178",
    "sg:postcode":"1078 BB",
    "sg:province":"North Holland",
    "sg:website":"http://www.bubbels.com",
    "wof:name":"Jeroboam, Le",
    "wof:placetype":"venue"
},
  "geometry": {"coordinates":[4.8866581917,52.3476715088],"type":"Point"}
}