{
  "type": "Feature",
  "properties": {
    "iso:country":"NL",
    "sg:address":"Heideweg 66",
    "sg:city":"Hooglanderveen",
    "sg:orig_category":"Metaalwerken",
    "sg:phone":"+31 33 253 5674",
    "sg:postcode":"3829 BB",
    "sg:province":"Utrecht",
    "wof:name":"Maxsol",
    "wof:placetype":"venue"
},
  "geometry": {"coordinates":[5.425441,52.18932],"type":"Point"}
}