{
  "type": "Feature",
  "properties": {
    "addr:full":"Canadabaan 14 Nistelrode Noord-Brabant 5388 RT",
    "addr:housenumber":"14",
    "addr:postcode":"5388 rt",
    "addr:street":"Canadabaan",
    "iso:country":"NL",
    "sg:address":"Canadabaan 14",
    "sg:city":"Nistelrode",
    "sg:orig_category":"Wegenbouw - Materieel",
    "sg:phone":"+31 412 613 344",
    "sg:postcode":"5388 RT",
    "sg:province":"Noord-Brabant",
    "wof:name":"Hanenberg Bv",
    "wof:placetype":"venue"
},
  "geometry": {"coordinates":[5.5677161217,51.713558197],"type":"Point"}
}