{
  "type": "Feature",
  "properties": {
    "addr:full":"Vicarieln 2 Heerde Gelderland 8181 KA",
    "addr:housenumber":"2",
    "addr:postcode":"8181 ka",
    "addr:street":"Vicarieln;Gelderland",
    "iso:country":"NL",
    "sg:address":"Vicarieln 2",
    "sg:city":"Heerde",
    "sg:orig_category":"Meel - Fabrieken En Groothandel",
    "sg:phone":"+31 578 693 896",
    "sg:postcode":"8181 KA",
    "sg:province":"Gelderland",
    "wof:name":"Vlijt Bv, De",
    "wof:placetype":"venue"
},
  "geometry": {"coordinates":[6.037087,52.386574],"type":"Point"}
}