{
  "type": "Feature",
  "properties": {
    "iso:country":"NL",
    "sg:address":"Cauberg 10",
    "sg:city":"Valkenburg Lb",
    "sg:orig_category":"Fotopersbureaus",
    "sg:phone":"+31 43 601 2402",
    "sg:postcode":"6301 BT",
    "sg:province":"Limburg",
    "wof:name":"Habets, Thijs",
    "wof:placetype":"venue"
},
  "geometry": {"coordinates":[5.828773,50.862385],"type":"Point"}
}