{
  "type": "Feature",
  "properties": {
    "addr:full":"Amsterdamseweg 16 Amersfoort Utrecht 3812 RS",
    "addr:housenumber":"16",
    "addr:postcode":"3812 rs",
    "addr:street":"Amsterdamseweg",
    "iso:country":"NL",
    "sg:address":"Amsterdamseweg 16",
    "sg:city":"Amersfoort",
    "sg:orig_category":"Paramedische Behandelingen",
    "sg:phone":"+31 33 421 6100",
    "sg:postcode":"3812 RS",
    "sg:province":"Utrecht",
    "wof:name":"Nederlands Paramedisch Instituut",
    "wof:placetype":"venue"
},
  "geometry": {"coordinates":[5.375153,52.160625],"type":"Point"}
}