{
  "type": "Feature",
  "properties": {
    "addr:full":"Kalkhaven 36 Gorinchem Zuid-Holland 4201 BB",
    "addr:housenumber":"36",
    "addr:postcode":"4201 bb",
    "addr:street":"Kalkhaven",
    "iso:country":"NL",
    "sg:address":"Kalkhaven 36",
    "sg:city":"Gorinchem",
    "sg:orig_category":"Onroerende Goederen",
    "sg:phone":"+31 183 630 924",
    "sg:postcode":"4201 BB",
    "sg:province":"Zuid-Holland",
    "wof:name":"Appeldijk Bv",
    "wof:placetype":"venue"
},
  "geometry": {"coordinates":[4.977954,51.828548],"type":"Point"}
}