{
  "type": "Feature",
  "properties": {
    "iso:country":"NL",
    "sg:address":"O L Vrouwestr 95",
    "sg:city":"Zegge",
    "sg:classifiers":[
        {
            "category":"Personal",
            "subcategory":"Nail Salon",
            "type":"Services"
        }
    ],
    "sg:phone":"+31 165 545 509",
    "sg:postcode":"4735 AA",
    "sg:province":"Noord-Brabant",
    "sg:tags":[
        "pedicure"
    ],
    "wof:name":"Pied Nouveau, Le",
    "wof:placetype":"venue"
},
  "geometry": {"coordinates":[4.515908,51.554829],"type":"Point"}
}