{
  "type": "Feature",
  "properties": {
    "addr:full":"Voltastr 33 Doetinchem Gelderland 7006 RT",
    "addr:housenumber":"33;7006",
    "addr:postcode":"rt",
    "addr:street":"Voltastr;Gelderland",
    "iso:country":"NL",
    "sg:address":"Voltastr 33",
    "sg:city":"Doetinchem",
    "sg:orig_category":"Linnenverhuur",
    "sg:phone":"+31 314 340 825",
    "sg:postcode":"7006 RT",
    "sg:province":"Gelderland",
    "sg:website":"http://www.gls.nl",
    "wof:name":"Gelderse Linnen Service Bv",
    "wof:placetype":"venue"
},
  "geometry": {"coordinates":[6.255744,51.970684],"type":"Point"}
}