{
  "type": "Feature",
  "properties": {
    "iso:country":"NL",
    "sg:address":"Piusstraat 98",
    "sg:city":"Tilburg",
    "sg:orig_category":"Fitnesscentra",
    "sg:phone":"+31 13 582 1998",
    "sg:postcode":"5021 JC",
    "sg:province":"Noord-Brabant",
    "wof:name":"American Gym, The",
    "wof:placetype":"venue"
},
  "geometry": {"coordinates":[5.089053,51.551033],"type":"Point"}
}