{
  "type": "Feature",
  "properties": {
    "addr:full":"Havendk 24 Tilburg Noord-Brabant 5017 AM",
    "addr:housenumber":"24",
    "addr:postcode":"5017",
    "addr:street":"Havendk",
    "iso:country":"NL",
    "sg:address":"Havendk 24",
    "sg:city":"Tilburg",
    "sg:orig_category":"Loodgieters",
    "sg:phone":"+31 13 544 6436",
    "sg:postcode":"5017 AM",
    "sg:province":"Noord-Brabant",
    "wof:name":"Jasta Installaties",
    "wof:placetype":"venue"
},
  "geometry": {"coordinates":[5.102762,51.55328],"type":"Point"}
}