{
  "type": "Feature",
  "properties": {
    "addr:full":"Kromstraat 61 Valkenswaard North Brabant 5554 NG",
    "addr:housenumber":"61",
    "addr:postcode":"5554 ng",
    "addr:street":"Kromstraat",
    "iso:country":"NL",
    "sg:address":"Kromstraat 61",
    "sg:city":"Valkenswaard",
    "sg:orig_category":"Kappers",
    "sg:phone":"+31 40 201 7173",
    "sg:postcode":"5554 NG",
    "sg:province":"North Brabant",
    "wof:name":"Ine Adriaans Thuiskapster",
    "wof:placetype":"venue"
},
  "geometry": {"coordinates":[5.4500160217,51.3473548889],"type":"Point"}
}