{
  "type": "Feature",
  "properties": {
    "addr:full":"Ln V Nw Guinea 131 Utrecht Utrecht 3531 JH",
    "addr:housenumber":"131",
    "addr:postcode":"3531 jh",
    "addr:street":"Ln V Nw Guinea",
    "iso:country":"NL",
    "sg:address":"Ln V Nw Guinea 131",
    "sg:city":"Utrecht",
    "sg:orig_category":"Journalisten Freelance",
    "sg:phone":"+31 30 296 5384",
    "sg:postcode":"3531 JH",
    "sg:province":"Utrecht",
    "wof:name":"Aagje",
    "wof:placetype":"venue"
},
  "geometry": {"coordinates":[5.09574,52.090012],"type":"Point"}
}