{
  "type": "Feature",
  "properties": {
    "addr:full":"Zwenkgras 29 Leeuwarden Friesland 8935 HB",
    "addr:housenumber":"29",
    "addr:postcode":"8935 hb",
    "addr:street":"Zwenkgras",
    "iso:country":"NL",
    "sg:address":"Zwenkgras 29",
    "sg:city":"Leeuwarden",
    "sg:classifiers":[
        {
            "category":"Personal",
            "subcategory":"Nail Salon",
            "type":"Services"
        }
    ],
    "sg:phone":"+31 58 289 0258",
    "sg:postcode":"8935 HB",
    "sg:province":"Friesland",
    "sg:tags":[
        "pedicure"
    ],
    "wof:name":"Bos-Hempenius, E J",
    "wof:placetype":"venue"
},
  "geometry": {"coordinates":[5.814032,53.185093],"type":"Point"}
}