{
  "type": "Feature",
  "properties": {
    "addr:full":"De Vlotkampweg 14 Nijmegen Gelderland 6545 AG",
    "addr:housenumber":"14",
    "addr:postcode":"6545",
    "addr:street":"De Vlotkampweg;Gelderland",
    "iso:country":"NL",
    "sg:address":"De Vlotkampweg 14",
    "sg:city":"Nijmegen",
    "sg:orig_category":"Fruit And Groenten Gh",
    "sg:phone":"+31 24 377 6935",
    "sg:postcode":"6545 AG",
    "sg:province":"Gelderland",
    "wof:name":"Holland Food Service Vers Panklaar Bv",
    "wof:placetype":"venue"
},
  "geometry": {"coordinates":[5.812142,51.846359],"type":"Point"}
}