{
  "type": "Feature",
  "properties": {
    "addr:full":"Dorpsstr 24 Twello Gelderland 7391 DE",
    "addr:housenumber":"24",
    "addr:postcode":"7391 de",
    "addr:street":"Dorpsstr;Gelderland",
    "iso:country":"NL",
    "sg:address":"Dorpsstr 24",
    "sg:city":"Twello",
    "sg:orig_category":"Banken",
    "sg:phone":"+31 575 509 709",
    "sg:postcode":"7391 DE",
    "sg:province":"Gelderland",
    "sg:website":"http://www.rabobank.nl",
    "wof:name":"Rabobank",
    "wof:placetype":"venue"
},
  "geometry": {"coordinates":[6.104433,52.23732],"type":"Point"}
}