{
  "type": "Feature",
  "properties": {
    "addr:full":"Heming 21 Broekhuizenvorst Limburg 5871 AH",
    "addr:housenumber":"21",
    "addr:postcode":"5871 ah",
    "addr:street":"Heming",
    "iso:country":"NL",
    "sg:address":"Heming 21",
    "sg:city":"Broekhuizenvorst",
    "sg:orig_category":"Homeopathie",
    "sg:phone":"+31 77 463 8333",
    "sg:postcode":"5871 AH",
    "sg:province":"Limburg",
    "wof:name":"Hendrix, Monique L J",
    "wof:placetype":"venue"
},
  "geometry": {"coordinates":[6.156944,51.493382],"type":"Point"}
}