{
  "type": "Feature",
  "properties": {
    "iso:country":"NL",
    "sg:address":"Rivierdijk 122",
    "sg:city":"Hardinxveld Giessend",
    "sg:orig_category":"Kantoor- And Schoolbenodigdheden Gh",
    "sg:phone":"+31 184 630 240",
    "sg:postcode":"3372 BJ",
    "sg:province":"South Holland",
    "wof:name":"Bakker Drukwerk Service Bds",
    "wof:placetype":"venue"
},
  "geometry": {"coordinates":[4.8995108604,51.827381134],"type":"Point"}
}