{
  "type": "Feature",
  "properties": {
    "iso:country":"NL",
    "sg:address":"Sprundelseweg 22",
    "sg:city":"Rucphen",
    "sg:orig_category":"Huizensloop And Bouwrijp Maken",
    "sg:phone":"+31 165 343 501",
    "sg:postcode":"4715 RC",
    "sg:province":"Noord-Brabant",
    "wof:name":"Marijnissen",
    "wof:placetype":"venue"
},
  "geometry": {"coordinates":[4.571857,51.531181],"type":"Point"}
}