{
  "type": "Feature",
  "properties": {
    "addr:full":"Roselo 47 Rotterdam South Holland 3085 MN",
    "addr:housenumber":"47",
    "addr:postcode":"3085 mn",
    "addr:street":"Roselo",
    "iso:country":"NL",
    "sg:address":"Roselo 47",
    "sg:city":"Rotterdam",
    "sg:orig_category":"Poetsmaterialen - Fabrieken En Groothandel",
    "sg:phone":"+31 10 410 2482",
    "sg:postcode":"3085 MN",
    "sg:province":"South Holland",
    "wof:name":"Balgooy, H P Van",
    "wof:placetype":"venue"
},
  "geometry": {"coordinates":[4.479468,51.874046],"type":"Point"}
}