{
  "type": "Feature",
  "properties": {
    "addr:full":"Dr. Ramaerlaan 102 Den Dolder Utrecht 3734 EB",
    "addr:housenumber":"102",
    "addr:postcode":"3734 eb",
    "addr:street":"Dr. Ramaerlaan",
    "iso:country":"NL",
    "sg:address":"Dr. Ramaerlaan 102",
    "sg:city":"Den Dolder",
    "sg:orig_category":"Kinderopvang Behalve Thuis",
    "sg:phone":"+31 30 225 0776",
    "sg:postcode":"3734 EB",
    "sg:province":"Utrecht",
    "wof:name":"Stichting Kinderopvang Zeist",
    "wof:placetype":"venue"
},
  "geometry": {"coordinates":[5.239129,52.141342],"type":"Point"}
}