{
  "type": "Feature",
  "properties": {
    "iso:country":"NL",
    "sg:address":"Laan Van Brabant 64",
    "sg:city":"Roosendaal",
    "sg:orig_category":"Werving And Selectie Van Vast Personeel",
    "sg:phone":"+31 165 574 100",
    "sg:postcode":"4701 BL",
    "sg:province":"Noord-Brabant",
    "wof:name":"Arbeidsbureau Roosendaal",
    "wof:placetype":"venue"
},
  "geometry": {"coordinates":[4.4530901909,51.5288772583],"type":"Point"}
}