{
  "type": "Feature",
  "properties": {
    "addr:full":"Venneperwg 451 Nieuw Vennep Noord-Holland 2153 AC",
    "addr:housenumber":"451",
    "addr:postcode":"2153 ac",
    "addr:street":"Nieuw Vennep",
    "iso:country":"NL",
    "sg:address":"Venneperwg 451",
    "sg:city":"Nieuw Vennep",
    "sg:orig_category":"Kappers",
    "sg:phone":"+31 252 672 575",
    "sg:postcode":"2153 AC",
    "sg:province":"Noord-Holland",
    "wof:name":"Knappe Koppe",
    "wof:placetype":"venue"
},
  "geometry": {"coordinates":[4.636842,52.263401],"type":"Point"}
}