{
  "type": "Feature",
  "properties": {
    "addr:full":"Watermolen 23 Zierikzee Zeeland 4301 HP",
    "addr:housenumber":"23",
    "addr:postcode":"4301 hp",
    "addr:street":"Watermolen",
    "iso:country":"NL",
    "sg:address":"Watermolen 23",
    "sg:city":"Zierikzee",
    "sg:orig_category":"Schilderwerk",
    "sg:phone":"+31 111 414 496",
    "sg:postcode":"4301 HP",
    "sg:province":"Zeeland",
    "wof:name":"C. V.D. Wekken",
    "wof:placetype":"venue"
},
  "geometry": {"coordinates":[3.919124,51.652424],"type":"Point"}
}