{
  "type": "Feature",
  "properties": {
    "addr:full":"Bulderweg 1 Ermelo Gelderland 3853 PA",
    "addr:housenumber":"1",
    "addr:postcode":"3853",
    "addr:street":"Bulderweg;Gelderland",
    "iso:country":"NL",
    "sg:address":"Bulderweg 1",
    "sg:city":"Ermelo",
    "sg:orig_category":"Kinderopvang Behalve Thuis",
    "sg:phone":"+31 341 554 294",
    "sg:postcode":"3853 PA",
    "sg:province":"Gelderland",
    "wof:name":"Beertje Puk",
    "wof:placetype":"venue"
},
  "geometry": {"coordinates":[5.595819,52.2901],"type":"Point"}
}