{
  "type": "Feature",
  "properties": {
    "iso:country":"NL",
    "sg:address":"Oenenburgweg 174",
    "sg:city":"Nunspeet",
    "sg:orig_category":"Technische Studies And Onderzoek",
    "sg:phone":"+31 341 256 854",
    "sg:postcode":"8072 GN",
    "sg:province":"Gelderland",
    "wof:name":"Qualikwant",
    "wof:placetype":"venue"
},
  "geometry": {"coordinates":[5.798115,52.386776],"type":"Point"}
}