{
  "type": "Feature",
  "properties": {
    "addr:full":"Oenenburgweg 174 Nunspeet Gelderland 8072 GN",
    "addr:housenumber":"174",
    "addr:postcode":"8072 gn",
    "addr:street":"Oenenburgweg;Gelderland",
    "iso:country":"NL",
    "sg:address":"Oenenburgweg 174",
    "sg:city":"Nunspeet",
    "sg:orig_category":"Technische Studies And Onderzoek",
    "sg:phone":"+31 341 256 854",
    "sg:postcode":"8072 GN",
    "sg:province":"Gelderland",
    "wof:name":"Qualikwant",
    "wof:placetype":"venue"
},
  "geometry": {"coordinates":[5.798115,52.386776],"type":"Point"}
}