{
  "type": "Feature",
  "properties": {
    "iso:country":"NL",
    "sg:address":"Lengwg 150",
    "sg:city":"Hoogvliet Rt",
    "sg:orig_category":"Verenigingsgebouwen",
    "sg:phone":"+31 10 295 6060",
    "sg:postcode":"3192 BM",
    "sg:province":"South Holland",
    "wof:name":"Welzijn Hoogvliet, Stichting",
    "wof:placetype":"venue"
},
  "geometry": {"coordinates":[4.356618,51.854519],"type":"Point"}
}