{
  "type": "Feature",
  "properties": {
    "addr:full":"V Haestrechtsngl 106 S Hertogenbosch Noord-Brabant 5237 SK",
    "addr:housenumber":"106",
    "addr:street":"S;5237",
    "iso:country":"NL",
    "sg:address":"V Haestrechtsngl 106",
    "sg:city":"S Hertogenbosch",
    "sg:orig_category":"Luchtvaart- Maatschappijen",
    "sg:phone":"+31 73 642 9579",
    "sg:postcode":"5237 SK",
    "sg:province":"Noord-Brabant",
    "sg:website":"http://www.easycharter.com",
    "wof:name":"Easycharter",
    "wof:placetype":"venue"
},
  "geometry": {"coordinates":[5.2886,51.730911],"type":"Point"}
}