{
  "type": "Feature",
  "properties": {
    "iso:country":"NL",
    "sg:address":"Frankenstg 3",
    "sg:city":"Zutphen",
    "sg:classifiers":[
        {
            "category":"Shopping",
            "subcategory":"Adult",
            "type":"Retail Goods"
        }
    ],
    "sg:phone":"+31 575 512 668",
    "sg:postcode":"7201 KN",
    "sg:province":"Gelderland",
    "sg:tags":[
        "lingerie",
        "en",
        "tricotage"
    ],
    "wof:name":"Why Not",
    "wof:placetype":"venue"
},
  "geometry": {"coordinates":[6.195661,52.141567],"type":"Point"}
}