{
  "type": "Feature",
  "properties": {
    "addr:full":"Spaarneweg 61 Cruquius North Holland 2142 EP",
    "addr:housenumber":"61",
    "addr:postcode":"2142 ep",
    "addr:street":"Spaarneweg",
    "iso:country":"NL",
    "sg:address":"Spaarneweg 61",
    "sg:city":"Cruquius",
    "sg:orig_category":"Meubelzaken, Woning- And Keukeninrichting",
    "sg:phone":"+31 23 529 5253",
    "sg:postcode":"2142 EP",
    "sg:province":"North Holland",
    "wof:name":"Happy Home",
    "wof:placetype":"venue"
},
  "geometry": {"coordinates":[4.62883,52.333286],"type":"Point"}
}