{
  "type": "Feature",
  "properties": {
    "addr:full":"Industrieweg 67 Mijdrecht Utrecht 3641 RK",
    "addr:housenumber":"67",
    "addr:postcode":"3641 rk",
    "addr:street":"Industrieweg",
    "iso:country":"NL",
    "sg:address":"Industrieweg 67",
    "sg:city":"Mijdrecht",
    "sg:orig_category":"Autokeuringen",
    "sg:phone":"+31 297 273 224",
    "sg:postcode":"3641 RK",
    "sg:province":"Utrecht",
    "wof:name":"Mijdrecht Car Cleaning Service",
    "wof:placetype":"venue"
},
  "geometry": {"coordinates":[4.88261,52.206692],"type":"Point"}
}