{
  "type": "Feature",
  "properties": {
    "addr:full":"Evers Dykhuizenln 55 Spyk Gn Groningen 9909 EB",
    "addr:housenumber":"55;gn",
    "addr:postcode":"9909 eb",
    "addr:street":"Spyk",
    "iso:country":"NL",
    "sg:address":"Evers Dykhuizenln 55",
    "sg:city":"Spyk Gn",
    "sg:orig_category":"Scholen Voor Basisonderwijs",
    "sg:phone":"+31 596 591 468",
    "sg:postcode":"9909 EB",
    "sg:province":"Groningen",
    "wof:name":"Fiepko Coolman Openb",
    "wof:placetype":"venue"
},
  "geometry": {"coordinates":[6.83624,53.388969],"type":"Point"}
}