{
  "type": "Feature",
  "properties": {
    "iso:country":"NL",
    "sg:address":"Lange Nieuwstraat 403",
    "sg:city":"Ijmuiden",
    "sg:orig_category":"Apothekers",
    "sg:phone":"+31 255 514 204",
    "sg:postcode":"1971 GD",
    "sg:province":"Noord-Holland",
    "wof:name":"Apotheek Kuijlman Cv",
    "wof:placetype":"venue"
},
  "geometry": {"coordinates":[4.616965,52.458298],"type":"Point"}
}