{
  "type": "Feature",
  "properties": {
    "addr:full":"Kesterenln 158-160 Breda Noord-Brabant 4822 WK",
    "addr:housenumber":"158-160",
    "addr:postcode":"4822 wk",
    "iso:country":"NL",
    "sg:address":"Kesterenln 158-160",
    "sg:city":"Breda",
    "sg:orig_category":"Boeken En Tijdschriften",
    "sg:phone":"+31 76 541 5048",
    "sg:postcode":"4822 WK",
    "sg:province":"Noord-Brabant",
    "wof:name":"Joepla",
    "wof:placetype":"venue"
},
  "geometry": {"coordinates":[4.723075,51.613152],"type":"Point"}
}