{
  "type": "Feature",
  "properties": {
    "addr:full":"Burg M V Veenln 7 Enschede NL.08 7543 AH",
    "addr:housenumber":"7",
    "addr:postcode":"7543 ah",
    "addr:street":"Burg;Veenln",
    "iso:country":"NL",
    "sg:address":"Burg M V Veenln 7",
    "sg:city":"Enschede",
    "sg:classifiers":[
        {
            "category":"Home & Garden",
            "subcategory":"Hardware",
            "type":"Retail Goods"
        }
    ],
    "sg:phone":"+31 53 431 2471",
    "sg:postcode":"7543 AH",
    "sg:province":"NL.08",
    "sg:tags":[
        "machine",
        "houtbewerking",
        "-"
    ],
    "wof:name":"Beckers Bv, Gebr",
    "wof:placetype":"venue"
},
  "geometry": {"coordinates":[6.878757,52.205578],"type":"Point"}
}