{
  "type": "Feature",
  "properties": {
    "addr:full":"Rubensstr 7 Groningen Groningen 9718 MA",
    "addr:housenumber":"7",
    "addr:postcode":"9718 ma",
    "addr:street":"Rubensstr",
    "iso:country":"NL",
    "sg:address":"Rubensstr 7",
    "sg:city":"Groningen",
    "sg:orig_category":"Adviesbureaus Chemische Techniek",
    "sg:phone":"+31 50 313 0770",
    "sg:postcode":"9718 MA",
    "sg:province":"Groningen",
    "wof:name":"Eppy Con",
    "wof:placetype":"venue"
},
  "geometry": {"coordinates":[6.546117,53.217976],"type":"Point"}
}