{
  "type": "Feature",
  "properties": {
    "addr:full":"Mackaylaan 58 Naarden North Holland 1412 CR",
    "addr:housenumber":"58",
    "addr:postcode":"1412 cr",
    "addr:street":"Mackaylaan",
    "iso:country":"NL",
    "sg:address":"Mackaylaan 58",
    "sg:city":"Naarden",
    "sg:orig_category":"Bloemen And Planten",
    "sg:phone":"+31 35 694 5940",
    "sg:postcode":"1412 CR",
    "sg:province":"North Holland",
    "wof:name":"Dlotus",
    "wof:placetype":"venue"
},
  "geometry": {"coordinates":[5.148678,52.284599],"type":"Point"}
}