{
  "type": "Feature",
  "properties": {
    "iso:country":"NL",
    "sg:address":"Conradpark 18",
    "sg:city":"Nieuwveen",
    "sg:classifiers":[
        {
            "category":"Education",
            "subcategory":"Preschool",
            "type":"Public Place"
        }
    ],
    "sg:phone":"+31 172 539 502",
    "sg:postcode":"2441 AG",
    "sg:province":"South Holland",
    "sg:tags":[
        "kleuteronderwijs",
        "basis-"
    ],
    "wof:name":"Openbare Basisschool De Tamboerijn",
    "wof:placetype":"venue"
},
  "geometry": {"coordinates":[4.755265,52.195721],"type":"Point"}
}