{
  "type": "Feature",
  "properties": {
    "iso:country":"NL",
    "sg:address":"Willeskop 8",
    "sg:city":"Montfoort",
    "sg:orig_category":"Kaas",
    "sg:phone":"+31 348 474 325",
    "sg:postcode":"3417 MD",
    "sg:province":"Utrecht",
    "wof:name":"Hilhorst Vof",
    "wof:placetype":"venue"
},
  "geometry": {"coordinates":[4.9426369667,52.0415344238],"type":"Point"}
}