{
  "type": "Feature",
  "properties": {
    "addr:full":"Kolveniershof 6 B Goes Zeeland 4461 DB",
    "addr:housenumber":"6 b",
    "addr:postcode":"4461 db",
    "addr:street":"Kolveniershof",
    "iso:country":"NL",
    "sg:address":"Kolveniershof 6 B",
    "sg:city":"Goes",
    "sg:orig_category":"Verkeersbureaus",
    "sg:phone":"+31 113 220 329",
    "sg:postcode":"4461 DB",
    "sg:province":"Zeeland",
    "sg:website":"http://www.intox-nederland.nl",
    "wof:name":"Intox",
    "wof:placetype":"venue"
},
  "geometry": {"coordinates":[-83.914169,39.768833],"type":"Point"}
}