{
  "type": "Feature",
  "properties": {
    "addr:full":"De Iep 18 Haaksbergen Overijssel 7482 WE",
    "addr:housenumber":"18",
    "addr:postcode":"7482 we",
    "addr:street":"De Iep",
    "iso:country":"NL",
    "sg:address":"De Iep 18",
    "sg:city":"Haaksbergen",
    "sg:orig_category":"Acupunctuur",
    "sg:phone":"+31 53 572 4818",
    "sg:postcode":"7482 WE",
    "sg:province":"Overijssel",
    "wof:name":"Bouwhuis, R",
    "wof:placetype":"venue"
},
  "geometry": {"coordinates":[6.748998,52.167706],"type":"Point"}
}