{
  "type": "Feature",
  "properties": {
    "iso:country":"NL",
    "sg:address":"Leeuwerik 42",
    "sg:city":"Veenendaal",
    "sg:orig_category":"Zonweringen",
    "sg:phone":"+31 6 51406353",
    "sg:postcode":"3906 NJ",
    "sg:province":"Utrecht",
    "wof:name":"Koops, W H",
    "wof:placetype":"venue"
},
  "geometry": {"coordinates":[5.527373,52.029873],"type":"Point"}
}