{
  "type": "Feature",
  "properties": {
    "addr:full":"Asserw 274 Rotterdam South Holland 3052 AG",
    "addr:housenumber":"274",
    "addr:postcode":"3052",
    "iso:country":"NL",
    "sg:address":"Asserw 274",
    "sg:city":"Rotterdam",
    "sg:orig_category":"Behangselpapier En Wandbekleding",
    "sg:phone":"+31 10 422 1355",
    "sg:postcode":"3052 AG",
    "sg:province":"South Holland",
    "wof:name":"Hess, J A",
    "wof:placetype":"venue"
},
  "geometry": {"coordinates":[4.465629,51.952339],"type":"Point"}
}