{
  "type": "Feature",
  "properties": {
    "addr:full":"Bergstr 9 Liempde Noord-Brabant 5298 VJ",
    "addr:housenumber":"9",
    "addr:postcode":"5298 vj",
    "addr:street":"Bergstr",
    "iso:country":"NL",
    "sg:address":"Bergstr 9",
    "sg:city":"Liempde",
    "sg:orig_category":"Schilders",
    "sg:phone":"+31 411 633 571",
    "sg:postcode":"5298 VJ",
    "sg:province":"Noord-Brabant",
    "wof:name":"Loo Schildersbedrijf, M Van De",
    "wof:placetype":"venue"
},
  "geometry": {"coordinates":[5.365514,51.574566],"type":"Point"}
}