{
  "type": "Feature",
  "properties": {
    "addr:full":"Nachtegaalstr 82 Utrecht Utrecht 3581 AN",
    "addr:housenumber":"82",
    "addr:postcode":"3581 an",
    "addr:street":"Nachtegaalstr",
    "iso:country":"NL",
    "sg:address":"Nachtegaalstr 82",
    "sg:city":"Utrecht",
    "sg:orig_category":"Pensioenfondsen",
    "sg:phone":"+31 30 232 2522",
    "sg:postcode":"3581 AN",
    "sg:province":"Utrecht",
    "wof:name":"Financi\u00eble Coach Utrecht Bv, De",
    "wof:placetype":"venue"
},
  "geometry": {"coordinates":[5.132209,52.091534],"type":"Point"}
}