{
  "type": "Feature",
  "properties": {
    "addr:full":"Patrijzenln 49 Doorwerth Gelderland 6865 XW",
    "addr:housenumber":"49",
    "addr:postcode":"6865 xw",
    "addr:street":"Patrijzenln;Gelderland",
    "iso:country":"NL",
    "sg:address":"Patrijzenln 49",
    "sg:city":"Doorwerth",
    "sg:orig_category":"Makelaars En Adviseurs Onroerende Goederen",
    "sg:phone":"+31 26 334 1255",
    "sg:postcode":"6865 XW",
    "sg:province":"Gelderland",
    "wof:name":"Kalverla",
    "wof:placetype":"venue"
},
  "geometry": {"coordinates":[5.794218,51.978619],"type":"Point"}
}