{
  "type": "Feature",
  "properties": {
    "addr:full":"Grachtstr 1 Oirsbeek Limburg 6438 HL",
    "addr:housenumber":"1",
    "addr:postcode":"6438 hl",
    "addr:street":"Grachtstr",
    "iso:country":"NL",
    "sg:address":"Grachtstr 1",
    "sg:city":"Oirsbeek",
    "sg:orig_category":"Verenigingen En Stichtingen",
    "sg:phone":"+31 46 442 8199",
    "sg:postcode":"6438 HL",
    "sg:province":"Limburg",
    "wof:name":"Weldadige Sticht Jan De Limpen",
    "wof:placetype":"venue"
},
  "geometry": {"coordinates":[5.907755,50.949997],"type":"Point"}
}