{
  "type": "Feature",
  "properties": {
    "addr:full":"Breekwagen 6 Bergharen Gelderland 6617 KC",
    "addr:housenumber":"6",
    "addr:postcode":"6617 kc",
    "addr:street":"Breekwagen;Gelderland",
    "iso:country":"NL",
    "sg:address":"Breekwagen 6",
    "sg:city":"Bergharen",
    "sg:orig_category":"Gespecialiseerde Bouw",
    "sg:phone":"+31 487 531 487",
    "sg:postcode":"6617 KC",
    "sg:province":"Gelderland",
    "wof:name":"Moors Constructiebedrijf Bergharen Bv",
    "wof:placetype":"venue"
},
  "geometry": {"coordinates":[5.658241,51.85054],"type":"Point"}
}