{
  "type": "Feature",
  "properties": {
    "addr:full":"Schoolstr 74 Vlagtwedde Groningen 9541 CM",
    "addr:housenumber":"74",
    "addr:postcode":"9541 cm",
    "addr:street":"Schoolstr",
    "iso:country":"NL",
    "sg:address":"Schoolstr 74",
    "sg:city":"Vlagtwedde",
    "sg:orig_category":"Schilders",
    "sg:phone":"+31 599 313 206",
    "sg:postcode":"9541 CM",
    "sg:province":"Groningen",
    "wof:name":"Akkerman Schildersbedrijf",
    "wof:placetype":"venue"
},
  "geometry": {"coordinates":[7.103304,53.033142],"type":"Point"}
}