{
  "type": "Feature",
  "properties": {
    "iso:country":"NL",
    "sg:address":"Rhone 32",
    "sg:city":"Leidschendam",
    "sg:orig_category":"Elektronische Bedrijfsinstallaties",
    "sg:phone":"+31 70 320 9098",
    "sg:postcode":"2266 DA",
    "sg:province":"Zuid-Holland",
    "wof:name":"Vnv Risicom Techniek",
    "wof:placetype":"venue"
},
  "geometry": {"coordinates":[4.4389,52.096062],"type":"Point"}
}