{
  "type": "Feature",
  "properties": {
    "addr:full":"Hogelandsngl 113 Enschede Overijssel 7512 GD",
    "addr:housenumber":"113",
    "addr:postcode":"7512 gd",
    "iso:country":"NL",
    "sg:address":"Hogelandsngl 113",
    "sg:city":"Enschede",
    "sg:orig_category":"Banken",
    "sg:phone":"+31 53 430 0735",
    "sg:postcode":"7512 GD",
    "sg:province":"Overijssel",
    "sg:website":"http://www.sns.nl",
    "wof:name":"Sns",
    "wof:placetype":"venue"
},
  "geometry": {"coordinates":[6.906665,52.212494],"type":"Point"}
}