{
  "type": "Feature",
  "properties": {
    "addr:full":"Markt 63 Delft Zuid-Holland 2611 GS",
    "addr:housenumber":"63",
    "addr:postcode":"2611 gs",
    "addr:street":"Markt",
    "iso:country":"NL",
    "sg:address":"Markt 63",
    "sg:city":"Delft",
    "sg:orig_category":"Horloges En Klokken",
    "sg:phone":"+31 15 212 3735",
    "sg:postcode":"2611 GS",
    "sg:province":"Zuid-Holland",
    "sg:website":"http://www.antiekeklokken.nl",
    "wof:name":"Loenen, Stadsuurwerkmaker Van",
    "wof:placetype":"venue"
},
  "geometry": {"coordinates":[4.359665,52.011478],"type":"Point"}
}