{
  "type": "Feature",
  "properties": {
    "addr:full":"Julianastr 20 Avenhorn Noord-Holland 1633 JM",
    "addr:housenumber":"20",
    "addr:postcode":"1633 jm",
    "addr:street":"Julianastr",
    "iso:country":"NL",
    "sg:address":"Julianastr 20",
    "sg:city":"Avenhorn",
    "sg:orig_category":"Bloemen En Planten - Decoratie",
    "sg:phone":"+31 229 541 591",
    "sg:postcode":"1633 JM",
    "sg:province":"Noord-Holland",
    "wof:name":"Keizerskroon, De",
    "wof:placetype":"venue"
},
  "geometry": {"coordinates":[4.941432,52.622089],"type":"Point"}
}