{
  "type": "Feature",
  "properties": {
    "iso:country":"NL",
    "sg:address":"Buitenbassinweg 76",
    "sg:city":"Rotterdam",
    "sg:orig_category":"Vertaal- And Tolkenbureaus",
    "sg:phone":"+31 10 447 2605",
    "sg:postcode":"3063 TB",
    "sg:province":"South Holland",
    "wof:name":"Hollanders Vertalingen",
    "wof:placetype":"venue"
},
  "geometry": {"coordinates":[4.519388,51.909451],"type":"Point"}
}