{
  "type": "Feature",
  "properties": {
    "iso:country":"NL",
    "sg:address":"Leusderwg 196",
    "sg:city":"Amersfoort",
    "sg:orig_category":"Kunststof Ramen",
    "sg:phone":"+31 33 463 5943",
    "sg:postcode":"3817 KE",
    "sg:province":"Utrecht",
    "wof:name":"Hab",
    "wof:placetype":"venue"
},
  "geometry": {"coordinates":[5.37989,52.142502],"type":"Point"}
}