{
  "type": "Feature",
  "properties": {
    "addr:full":"Dokter Hoogkamerlaan 21 Middenmeer Noord-Holland 1775 EJ",
    "addr:housenumber":"21",
    "addr:postcode":"1775 ej",
    "addr:street":"Dokter Hoogkamerlaan",
    "iso:country":"NL",
    "sg:address":"Dokter Hoogkamerlaan 21",
    "sg:city":"Middenmeer",
    "sg:orig_category":"Kappers",
    "sg:phone":"+31 227 502 308",
    "sg:postcode":"1775 EJ",
    "sg:province":"Noord-Holland",
    "wof:name":"Monique Van Der Veldt",
    "wof:placetype":"venue"
},
  "geometry": {"coordinates":[5.004664,52.808052],"type":"Point"}
}