{
  "type": "Feature",
  "properties": {
    "addr:full":"Jan Van Gentstraat 92 Badhoevedorp Noord-Holland 1171 GM",
    "addr:housenumber":"92",
    "addr:postcode":"1171 gm",
    "addr:street":"Jan Van Gentstraat",
    "iso:country":"NL",
    "sg:address":"Jan Van Gentstraat 92",
    "sg:city":"Badhoevedorp",
    "sg:orig_category":"Verlichting And Huishoudartikelen",
    "sg:phone":"+31 20 659 4846",
    "sg:postcode":"1171 GM",
    "sg:province":"Noord-Holland",
    "wof:name":"Tapijt- En Gordijncentrum Badhoevedorp Bv",
    "wof:placetype":"venue"
},
  "geometry": {"coordinates":[4.794828,52.33667],"type":"Point"}
}