{
  "type": "Feature",
  "properties": {
    "addr:full":"De Run 4234 Veldhoven Noord-Brabant 5503 LL",
    "addr:housenumber":"4234",
    "addr:postcode":"5503 ll",
    "addr:street":"De Run",
    "iso:country":"NL",
    "sg:address":"De Run 4234",
    "sg:city":"Veldhoven",
    "sg:orig_category":"Metaalwaren - Fabrieken",
    "sg:phone":"+31 40 254 4565",
    "sg:postcode":"5503 LL",
    "sg:province":"Noord-Brabant",
    "wof:name":"Nsa Bv",
    "wof:placetype":"venue"
},
  "geometry": {"coordinates":[5.427463,51.412094],"type":"Point"}
}