{
  "type": "Feature",
  "properties": {
    "addr:full":"Corio Center 3 Heerlen Limburg 6411 LX",
    "addr:housenumber":"3",
    "addr:postcode":"6411 lx",
    "addr:street":"Corio Center",
    "iso:country":"NL",
    "sg:address":"Corio Center 3",
    "sg:city":"Heerlen",
    "sg:classifiers":[
        {
            "category":"Bars & Pubs",
            "type":"Food & Drink"
        }
    ],
    "sg:phone":"+31 45 400 9765",
    "sg:postcode":"6411 LX",
    "sg:province":"Limburg",
    "wof:name":"Sally O'Briens Bv",
    "wof:placetype":"venue"
},
  "geometry": {"coordinates":[5.975622,50.888828],"type":"Point"}
}