{
  "type": "Feature",
  "properties": {
    "addr:full":"Oudegr A/D Werf 179 Utrecht Utrecht 3511 NE",
    "addr:housenumber":"d;179",
    "addr:postcode":"3511 ne",
    "addr:street":"Werf",
    "iso:country":"NL",
    "sg:address":"Oudegr A/D Werf 179",
    "sg:city":"Utrecht",
    "sg:orig_category":"Webdesign Bureaus",
    "sg:phone":"+31 30 233 3771",
    "sg:postcode":"3511 NE",
    "sg:province":"Utrecht",
    "wof:name":"Spring Vision",
    "wof:placetype":"venue"
},
  "geometry": {"coordinates":[5.1154050827,52.0889320374],"type":"Point"}
}