{
  "type": "Feature",
  "properties": {
    "addr:full":"Merelstraat 1 Haastrecht Zuid-Holland 2851 VS",
    "addr:housenumber":"1",
    "addr:postcode":"2851 vs",
    "addr:street":"Merelstraat",
    "iso:country":"NL",
    "sg:address":"Merelstraat 1",
    "sg:city":"Haastrecht",
    "sg:orig_category":"Verhuur Bouwmachines",
    "sg:phone":"+31 182 501 267",
    "sg:postcode":"2851 VS",
    "sg:province":"Zuid-Holland",
    "wof:name":"A.B.H. Spruit",
    "wof:placetype":"venue"
},
  "geometry": {"coordinates":[4.774072,51.998528],"type":"Point"}
}