{
  "type": "Feature",
  "properties": {
    "addr:full":"Breestr 31 Koog Aan De Zaan Noord-Holland 1541 EA",
    "addr:housenumber":"31",
    "addr:postcode":"1541 ea",
    "addr:street":"Breestr",
    "iso:country":"NL",
    "sg:address":"Breestr 31",
    "sg:city":"Koog Aan De Zaan",
    "sg:orig_category":"Administratie- En Boekhoudkantoren",
    "sg:phone":"+31 75 617 2371",
    "sg:postcode":"1541 EA",
    "sg:province":"Noord-Holland",
    "wof:name":"Boekwerk",
    "wof:placetype":"venue"
},
  "geometry": {"coordinates":[4.809067,52.458717],"type":"Point"}
}