{
  "type": "Feature",
  "properties": {
    "addr:full":"Hoofdstr 28 Ryen North Brabant 5121 JE",
    "addr:housenumber":"28",
    "addr:postcode":"5121 je",
    "addr:street":"Hoofdstr",
    "iso:country":"NL",
    "sg:address":"Hoofdstr 28",
    "sg:city":"Ryen",
    "sg:orig_category":"Handwerkartikelen",
    "sg:phone":"+31 161 223 156",
    "sg:postcode":"5121 JE",
    "sg:province":"North Brabant",
    "sg:website":"http://www.elbekreatief.nl",
    "wof:name":"Elbe Kreatief",
    "wof:placetype":"venue"
},
  "geometry": {"coordinates":[4.9197,51.588017],"type":"Point"}
}