{
  "type": "Feature",
  "properties": {
    "addr:full":"Meanderlaan 202 Tholen Zeeland 4691 LJ",
    "addr:housenumber":"202",
    "addr:postcode":"4691 lj",
    "addr:street":"Meanderlaan",
    "iso:country":"NL",
    "sg:address":"Meanderlaan 202",
    "sg:city":"Tholen",
    "sg:orig_category":"Boekhouders",
    "sg:phone":"+31 166 603 799",
    "sg:postcode":"4691 LJ",
    "sg:province":"Zeeland",
    "wof:name":"Meander Bv",
    "wof:placetype":"venue"
},
  "geometry": {"coordinates":[4.211416,51.528301],"type":"Point"}
}