{
  "type": "Feature",
  "properties": {
    "addr:full":"Mulderswg 4 Staphorst Overijssel 7951 DG",
    "addr:housenumber":"4",
    "addr:postcode":"7951 dg",
    "addr:street":"Mulderswg",
    "iso:country":"NL",
    "sg:address":"Mulderswg 4",
    "sg:city":"Staphorst",
    "sg:orig_category":"Musea",
    "sg:phone":"+31 522 461 087",
    "sg:postcode":"7951 DG",
    "sg:province":"Overijssel",
    "wof:name":"Museumboerderij",
    "wof:placetype":"venue"
},
  "geometry": {"coordinates":[6.204278,52.642349],"type":"Point"}
}