{
  "type": "Feature",
  "properties": {
    "addr:full":"Van Baerlestraat 41Hs Amsterdam Noord-Holland 1071 AP",
    "addr:housenumber":"41hs",
    "addr:postcode":"1071 ap",
    "addr:street":"Van Baerlestraat",
    "iso:country":"NL",
    "sg:address":"Van Baerlestraat 41Hs",
    "sg:city":"Amsterdam",
    "sg:orig_category":"Werving And Selectie Van Tijdelijk Personeel And Uitzendkantoren",
    "sg:phone":"+31 20 679 4455",
    "sg:postcode":"1071 AP",
    "sg:province":"Noord-Holland",
    "wof:name":"Manpower",
    "wof:placetype":"venue"
},
  "geometry": {"coordinates":[4.8804969788,52.3558540344],"type":"Point"}
}