{
  "type": "Feature",
  "properties": {
    "iso:country":"NL",
    "sg:address":"Poolmanswg 66",
    "sg:city":"Enschede",
    "sg:orig_category":"Schoenen",
    "sg:phone":"+31 53 431 1845",
    "sg:postcode":"7545 LS",
    "sg:province":"NL.08",
    "wof:name":"Flip",
    "wof:placetype":"venue"
},
  "geometry": {"coordinates":[6.868908,52.216965],"type":"Point"}
}