{
  "type": "Feature",
  "properties": {
    "addr:full":"Kennemerlaan 120 Ijmuiden North Holland 1972 ES",
    "addr:housenumber":"120",
    "addr:postcode":"1972 es",
    "addr:street":"Kennemerlaan",
    "iso:country":"NL",
    "sg:address":"Kennemerlaan 120",
    "sg:city":"Ijmuiden",
    "sg:orig_category":"Meubelreparatie And -Restauratie",
    "sg:phone":"+31 255 510 612",
    "sg:postcode":"1972 ES",
    "sg:province":"North Holland",
    "wof:name":"H.R. Bremer",
    "wof:placetype":"venue"
},
  "geometry": {"coordinates":[4.609155,52.460026],"type":"Point"}
}