{
  "type": "Feature",
  "properties": {
    "addr:full":"Kernwg 13 Hoorn Nh Noord-Holland 1627 LC",
    "addr:housenumber":"13",
    "addr:postcode":"1627 lc",
    "addr:street":"Kernwg",
    "iso:country":"NL",
    "sg:address":"Kernwg 13",
    "sg:city":"Hoorn Nh",
    "sg:orig_category":"Autoschade- Herstelbedrijven",
    "sg:phone":"+31 229 235 876",
    "sg:postcode":"1627 LC",
    "sg:province":"Noord-Holland",
    "wof:name":"Autogarant",
    "wof:placetype":"venue"
},
  "geometry": {"coordinates":[5.098626,52.642361],"type":"Point"}
}