{
  "type": "Feature",
  "properties": {
    "addr:full":"Kritzingerstr 168 S Gravenhage Zuid-Holland 2572 XV",
    "addr:housenumber":"168;gravenhage",
    "addr:postcode":"2572 xv",
    "addr:street":"S",
    "iso:country":"NL",
    "sg:address":"Kritzingerstr 168",
    "sg:city":"S Gravenhage",
    "sg:orig_category":"Grafisch Ontwerpers",
    "sg:phone":"+31 70 345 1171",
    "sg:postcode":"2572 XV",
    "sg:province":"Zuid-Holland",
    "sg:website":"http://www.sinas.info",
    "wof:name":"Sinas",
    "wof:placetype":"venue"
},
  "geometry": {"coordinates":[4.29421,52.06422],"type":"Point"}
}