{
  "type": "Feature",
  "properties": {
    "addr:full":"Heralmastr 15 Saaksum Groningen 9886 PG",
    "addr:housenumber":"15",
    "addr:postcode":"9886 pg",
    "addr:street":"Heralmastr",
    "iso:country":"NL",
    "sg:address":"Heralmastr 15",
    "sg:city":"Saaksum",
    "sg:orig_category":"Verenigingsgebouwen",
    "sg:phone":"+31 594 622 000",
    "sg:postcode":"9886 PG",
    "sg:province":"Groningen",
    "wof:name":"Heralmahuus",
    "wof:placetype":"venue"
},
  "geometry": {"coordinates":[6.418273,53.314384],"type":"Point"}
}