{
  "type": "Feature",
  "properties": {
    "addr:full":"Adelaarsw 80 Amsterdam Noord-Holland 1021 BW",
    "addr:housenumber":"80",
    "addr:postcode":"1021 bw",
    "addr:street":"Adelaarsw",
    "iso:country":"NL",
    "sg:address":"Adelaarsw 80",
    "sg:city":"Amsterdam",
    "sg:orig_category":"Artsen - Huisartsen",
    "sg:phone":"+31 20 636 0139",
    "sg:postcode":"1021 BW",
    "sg:province":"Noord-Holland",
    "wof:name":"Versloot, C W H",
    "wof:placetype":"venue"
},
  "geometry": {"coordinates":[4.917195,52.38731],"type":"Point"}
}