{
  "type": "Feature",
  "properties": {
    "addr:full":"Vrouwenstraat 4 Alkmaar North Holland 1811 GA",
    "addr:housenumber":"4",
    "addr:postcode":"1811 ga",
    "addr:street":"Vrouwenstraat",
    "iso:country":"NL",
    "sg:address":"Vrouwenstraat 4",
    "sg:city":"Alkmaar",
    "sg:orig_category":"Meubelreparatie And -Restauratie",
    "sg:phone":"+31 72 511 9991",
    "sg:postcode":"1811 GA",
    "sg:province":"North Holland",
    "wof:name":"Woning- En Meubelstoffeerderij Kleine Huis",
    "wof:placetype":"venue"
},
  "geometry": {"coordinates":[4.742821,52.630447],"type":"Point"}
}