{
  "type": "Feature",
  "properties": {
    "addr:full":"Roer 20 Rotterdam Zuid-Holland 3068 LE",
    "addr:housenumber":"20",
    "addr:postcode":"3068 le",
    "addr:street":"Roer",
    "iso:country":"NL",
    "sg:address":"Roer 20",
    "sg:city":"Rotterdam",
    "sg:orig_category":"Metaalbewerking",
    "sg:phone":"+31 10 207 1999",
    "sg:postcode":"3068 LE",
    "sg:province":"Zuid-Holland",
    "wof:name":"Multibedrijven Rotterdam Ultimade",
    "wof:placetype":"venue"
},
  "geometry": {"coordinates":[4.571024,51.959694],"type":"Point"}
}