{
  "type": "Feature",
  "properties": {
    "addr:full":"W Sonneveldln 77 Utrecht Utrecht 3584 ZP",
    "addr:housenumber":"77",
    "addr:postcode":"3584 zp",
    "addr:street":"W",
    "iso:country":"NL",
    "sg:address":"W Sonneveldln 77",
    "sg:city":"Utrecht",
    "sg:orig_category":"Adviesbureaus Bedrijfsorganisatie",
    "sg:phone":"+31 30 251 1866",
    "sg:postcode":"3584 ZP",
    "sg:province":"Utrecht",
    "wof:name":"Beljaars",
    "wof:placetype":"venue"
},
  "geometry": {"coordinates":[5.157156,52.087158],"type":"Point"}
}