{
  "type": "Feature",
  "properties": {
    "addr:full":"Wielkamp 10 Zaltbommel Gelderland 5301 DB",
    "addr:housenumber":"10",
    "addr:postcode":"5301 db",
    "addr:street":"Wielkamp;Gelderland",
    "iso:country":"NL",
    "sg:address":"Wielkamp 10",
    "sg:city":"Zaltbommel",
    "sg:orig_category":"Administratie- En Boekhoudkantoren",
    "sg:phone":"+31 418 540 260",
    "sg:postcode":"5301 DB",
    "sg:province":"Gelderland",
    "wof:name":"Gibo Groep",
    "wof:placetype":"venue"
},
  "geometry": {"coordinates":[5.242001,51.800144],"type":"Point"}
}