{
  "type": "Feature",
  "properties": {
    "addr:full":"Boeiersngl 6 Groningen Groningen 9745 CA",
    "addr:housenumber":"6",
    "addr:postcode":"9745 ca",
    "addr:street":"Boeiersngl",
    "iso:country":"NL",
    "sg:address":"Boeiersngl 6",
    "sg:city":"Groningen",
    "sg:orig_category":"Adviesbureaus Bedrijfsorganisatie",
    "sg:phone":"+31 6 50516583",
    "sg:postcode":"9745 CA",
    "sg:province":"Groningen",
    "wof:name":"Kimmenaede",
    "wof:placetype":"venue"
},
  "geometry": {"coordinates":[6.50229,53.21357],"type":"Point"}
}