{
  "type": "Feature",
  "properties": {
    "iso:country":"NL",
    "sg:address":"New Yorkweg 97",
    "sg:city":"Almere",
    "sg:orig_category":"Meubelzaken, Woning- And Keukeninrichting",
    "sg:phone":"+31 36 532 8925",
    "sg:postcode":"1334 NA",
    "sg:province":"Flevoland",
    "wof:name":"Spaan Kastencentrum",
    "wof:placetype":"venue"
},
  "geometry": {"coordinates":[5.274869,52.394386],"type":"Point"}
}