{
  "type": "Feature",
  "properties": {
    "iso:country":"NL",
    "sg:address":"Balyewg 90",
    "sg:city":"Maastricht",
    "sg:orig_category":"Verenigingen En Stichtingen",
    "sg:phone":"+31 43 362 4545",
    "sg:postcode":"6222 BJ",
    "sg:province":"Limburg",
    "wof:name":"Hulp Aan Tsjernobyl Kinderen, Sticht",
    "wof:placetype":"venue"
},
  "geometry": {"coordinates":[5.71695,50.87904],"type":"Point"}
}