{
  "type": "Feature",
  "properties": {
    "iso:country":"NL",
    "sg:address":"Oeverbiesstr 15",
    "sg:city":"S Gravenhage",
    "sg:orig_category":"Autorijscholen",
    "sg:phone":"+31 6 22440504",
    "sg:postcode":"2548 WP",
    "sg:province":"Zuid-Holland",
    "wof:name":"Metropole",
    "wof:placetype":"venue"
},
  "geometry": {"coordinates":[4.2901,52.029888],"type":"Point"}
}