{
  "type": "Feature",
  "properties": {
    "addr:full":"Zwanenveld 8403 Nijmegen Friesland 6538 TL",
    "addr:housenumber":"8403",
    "addr:postcode":"6538 tl",
    "addr:street":"Zwanenveld",
    "iso:country":"NL",
    "sg:address":"Zwanenveld 8403",
    "sg:city":"Nijmegen",
    "sg:orig_category":"Bloemen And Planten",
    "sg:phone":"+31 24 345 0342",
    "sg:postcode":"6538 TL",
    "sg:province":"Friesland",
    "wof:name":"Bloemenwinkeltje Doornroosje",
    "wof:placetype":"venue"
},
  "geometry": {"coordinates":[5.793491,51.823383],"type":"Point"}
}