{
  "type": "Feature",
  "properties": {
    "addr:full":"Boveneindselaan 23 Krimpen A/D Ijssel South Holland 2924 BA",
    "addr:housenumber":"23;a / d",
    "addr:postcode":"2924 ba",
    "addr:street":"Boveneindselaan;Ijssel South",
    "iso:country":"NL",
    "sg:address":"Boveneindselaan 23",
    "sg:city":"Krimpen A/D Ijssel",
    "sg:orig_category":"Bloemen And Planten",
    "sg:phone":"+31 180 522 882",
    "sg:postcode":"2924 BA",
    "sg:province":"South Holland",
    "wof:name":"Tuincentrum De Wilgen",
    "wof:placetype":"venue"
},
  "geometry": {"coordinates":[4.617207,51.925865],"type":"Point"}
}