{
  "type": "Feature",
  "properties": {
    "iso:country":"NL",
    "sg:address":"Weg En Bos 3",
    "sg:city":"Bergschenhoek",
    "sg:orig_category":"Voeding, Dranken And Tabak Gh",
    "sg:phone":"+31 10 522 0411",
    "sg:postcode":"2661 DG",
    "sg:province":"Zuid-Holland",
    "wof:name":"De Jong Diepvries Bv",
    "wof:placetype":"venue"
},
  "geometry": {"coordinates":[4.503153,51.978043],"type":"Point"}
}