{
  "type": "Feature",
  "properties": {
    "addr:full":"Fidelio 293 Capelle Ad Yssel Zuid-Holland 2907 KE",
    "addr:housenumber":"293",
    "addr:postcode":"2907 ke",
    "addr:street":"Fidelio",
    "iso:country":"NL",
    "sg:address":"Fidelio 293",
    "sg:city":"Capelle Ad Yssel",
    "sg:orig_category":"Woningbouw- Verenigingen En -Stichtingen",
    "sg:phone":"+31 10 458 1876",
    "sg:postcode":"2907 KE",
    "sg:province":"Zuid-Holland",
    "wof:name":"Spinoza",
    "wof:placetype":"venue"
},
  "geometry": {"coordinates":[4.5865998268,51.9514884949],"type":"Point"}
}