{
  "type": "Feature",
  "properties": {
    "addr:full":"Parkweg 6 Boxtel Noord-Brabant 5282 SM",
    "addr:housenumber":"6",
    "addr:postcode":"5282 sm",
    "addr:street":"Parkweg",
    "iso:country":"NL",
    "sg:address":"Parkweg 6",
    "sg:city":"Boxtel",
    "sg:orig_category":"Diverse Consumentenartikelen Gh",
    "sg:phone":"+31 411 686 542",
    "sg:postcode":"5282 SM",
    "sg:province":"Noord-Brabant",
    "wof:name":"Vinis Vof",
    "wof:placetype":"venue"
},
  "geometry": {"coordinates":[5.31222,51.598419],"type":"Point"}
}