{
  "type": "Feature",
  "properties": {
    "addr:full":"Turnhoutsewg 14 Reusel Noord-Brabant 5541 NX",
    "addr:housenumber":"14",
    "addr:postcode":"5541 nx",
    "addr:street":"Turnhoutsewg",
    "iso:country":"NL",
    "sg:address":"Turnhoutsewg 14",
    "sg:city":"Reusel",
    "sg:orig_category":"Woninginrichting",
    "sg:phone":"+31 497 641 798",
    "sg:postcode":"5541 NX",
    "sg:province":"Noord-Brabant",
    "wof:name":"Cash & Carry",
    "wof:placetype":"venue"
},
  "geometry": {"coordinates":[5.1497612,51.3582115173],"type":"Point"}
}