{
  "type": "Feature",
  "properties": {
    "addr:full":"Stadionweg 200 Heerenveen Friesland 8448 ZZ",
    "addr:housenumber":"200",
    "addr:postcode":"8448 zz",
    "addr:street":"Stadionweg",
    "iso:country":"NL",
    "sg:address":"Stadionweg 200",
    "sg:city":"Heerenveen",
    "sg:classifiers":[
        {
            "category":"Education",
            "subcategory":"Preschool",
            "type":"Public Place"
        }
    ],
    "sg:phone":"+31 513 618 461",
    "sg:postcode":"8448 ZZ",
    "sg:province":"Friesland",
    "sg:tags":[
        "kleuteronderwijs",
        "basis-"
    ],
    "wof:name":"De Regenboog Openb",
    "wof:placetype":"venue"
},
  "geometry": {"coordinates":[5.931241,52.964893],"type":"Point"}
}