{
  "type": "Feature",
  "properties": {
    "addr:full":"Maaskade 42 Rotterdam Zuid-Holland 3071 NB",
    "addr:housenumber":"42",
    "addr:postcode":"3071 nb",
    "addr:street":"Maaskade",
    "iso:country":"NL",
    "sg:address":"Maaskade 42",
    "sg:city":"Rotterdam",
    "sg:orig_category":"Overheidsdiensten",
    "sg:phone":"+31 10 412 2966",
    "sg:postcode":"3071 NB",
    "sg:province":"Zuid-Holland",
    "wof:name":"Buurthuis 'T Eiland",
    "wof:placetype":"venue"
},
  "geometry": {"coordinates":[4.4972791672,51.9156799316],"type":"Point"}
}