{
  "type": "Feature",
  "properties": {
    "addr:full":"Onderweg 6 Kedichem South Holland 4247 EJ",
    "addr:housenumber":"6",
    "addr:postcode":"4247 ej",
    "addr:street":"Onderweg",
    "iso:country":"NL",
    "sg:address":"Onderweg 6",
    "sg:city":"Kedichem",
    "sg:orig_category":"Makelaars In Onroerend Goed",
    "sg:phone":"+31 183 562 010",
    "sg:postcode":"4247 EJ",
    "sg:province":"South Holland",
    "wof:name":"J Den Besten Bv",
    "wof:placetype":"venue"
},
  "geometry": {"coordinates":[5.043574,51.860359],"type":"Point"}
}