{
  "type": "Feature",
  "properties": {
    "addr:full":"Koorstr 2 Boxmeer Noord-Brabant 5831 GH",
    "addr:housenumber":"2",
    "addr:postcode":"5831 gh",
    "addr:street":"Koorstr",
    "iso:country":"NL",
    "sg:address":"Koorstr 2",
    "sg:city":"Boxmeer",
    "sg:orig_category":"Accountants - Administratie- Consulenten En -Kantoren",
    "sg:phone":"+31 485 572 120",
    "sg:postcode":"5831 GH",
    "sg:province":"Noord-Brabant",
    "wof:name":"Abab",
    "wof:placetype":"venue"
},
  "geometry": {"coordinates":[5.94737,51.647064],"type":"Point"}
}