{
  "type": "Feature",
  "properties": {
    "addr:full":"Fazantstr 35 Haaksbergen Overijssel 7481 BG",
    "addr:housenumber":"35",
    "addr:postcode":"7481",
    "addr:street":"Fazantstr",
    "iso:country":"NL",
    "sg:address":"Fazantstr 35",
    "sg:city":"Haaksbergen",
    "sg:orig_category":"Zalenverhuur",
    "sg:phone":"+31 53 572 1474",
    "sg:postcode":"7481 BG",
    "sg:province":"Overijssel",
    "wof:name":"Oude Molen, De",
    "wof:placetype":"venue"
},
  "geometry": {"coordinates":[6.747955,52.158813],"type":"Point"}
}