{
  "type": "Feature",
  "properties": {
    "addr:full":"Dishoek 1 Koudekerke Zeeland 4371 NT",
    "addr:housenumber":"1",
    "addr:postcode":"4371 nt",
    "addr:street":"Dishoek",
    "iso:country":"NL",
    "sg:address":"Dishoek 1",
    "sg:city":"Koudekerke",
    "sg:orig_category":"Kampeerterreinen",
    "sg:phone":"+31 118 551 348",
    "sg:postcode":"4371 NT",
    "sg:province":"Zeeland",
    "wof:name":"Camping Dishoek",
    "wof:placetype":"venue"
},
  "geometry": {"coordinates":[3.5242369175,51.4678344727],"type":"Point"}
}