{
  "type": "Feature",
  "properties": {
    "iso:country":"NL",
    "sg:address":"Wilgenpad 5",
    "sg:city":"Kloosterburen",
    "sg:classifiers":[
        {
            "category":"Sports & Exercise",
            "subcategory":"Stables",
            "type":"Entertainment"
        }
    ],
    "sg:phone":"+31 595 481 933",
    "sg:postcode":"9977 SJ",
    "sg:province":"Groningen",
    "sg:tags":[
        "maneges"
    ],
    "wof:name":"Marneruiters, De",
    "wof:placetype":"venue"
},
  "geometry": {"coordinates":[6.39597,53.38863],"type":"Point"}
}