{
  "type": "Feature",
  "properties": {
    "addr:full":"Houttuinen Z 82 Apeldoorn Gelderland 7325 RL",
    "addr:housenumber":"82",
    "addr:postcode":"7325 rl",
    "addr:street":"Houttuinen;Gelderland",
    "iso:country":"NL",
    "sg:address":"Houttuinen Z 82",
    "sg:city":"Apeldoorn",
    "sg:orig_category":"Sportverenigingen En Ontspannings- Verenigingen",
    "sg:phone":"+31 55 360 0789",
    "sg:postcode":"7325 RL",
    "sg:province":"Gelderland",
    "wof:name":"Go Cl Denksport",
    "wof:placetype":"venue"
},
  "geometry": {"coordinates":[6.015867,52.210316],"type":"Point"}
}