{
  "type": "Feature",
  "properties": {
    "addr:full":"Ds T Fliednerstr 2 Eindhoven Noord-Brabant 5631 BN",
    "addr:housenumber":"2",
    "addr:postcode":"5631 bn",
    "addr:street":"Ds",
    "iso:country":"NL",
    "sg:address":"Ds T Fliednerstr 2",
    "sg:city":"Eindhoven",
    "sg:orig_category":"Boeken En Tijdschriften",
    "sg:phone":"+31 40 260 5906",
    "sg:postcode":"5631 BN",
    "sg:province":"Noord-Brabant",
    "wof:name":"Piere, Van",
    "wof:placetype":"venue"
},
  "geometry": {"coordinates":[5.489731,51.454056],"type":"Point"}
}