{
  "type": "Feature",
  "properties": {
    "addr:full":"Pastorietuin 31 Harkstede Groningen 9617 ED",
    "addr:housenumber":"31",
    "addr:postcode":"9617 ed",
    "addr:street":"Pastorietuin",
    "iso:country":"NL",
    "sg:address":"Pastorietuin 31",
    "sg:city":"Harkstede",
    "sg:orig_category":"Beeldende Kunstenaars",
    "sg:phone":"+31 50 404 1783",
    "sg:postcode":"9617 ED",
    "sg:province":"Groningen",
    "sg:website":"http://www.lucasklein.nl",
    "wof:name":"Klein, Lucas",
    "wof:placetype":"venue"
},
  "geometry": {"coordinates":[6.704404,53.20546],"type":"Point"}
}