{
  "type": "Feature",
  "properties": {
    "iso:country":"NL",
    "sg:address":"Zandstraat 56",
    "sg:city":"Montfort",
    "sg:orig_category":"Landbouwmachines Gh",
    "sg:phone":"+31 475 541 403",
    "sg:postcode":"6065 AH",
    "sg:province":"Limburg",
    "wof:name":"H. Janssen",
    "wof:placetype":"venue"
},
  "geometry": {"coordinates":[5.950564,51.12093],"type":"Point"}
}