{
  "type": "Feature",
  "properties": {
    "addr:full":"Alex Willemsstraat 2 Winssen Gelderland 6645 BJ",
    "addr:housenumber":"2",
    "addr:postcode":"6645 bj",
    "addr:street":"Alex Willemsstraat;Gelderland",
    "iso:country":"NL",
    "sg:address":"Alex Willemsstraat 2",
    "sg:city":"Winssen",
    "sg:orig_category":"Verlichting And Huishoudartikelen",
    "sg:phone":"+31 487 521 601",
    "sg:postcode":"6645 BJ",
    "sg:province":"Gelderland",
    "wof:name":"Firma Marcusse",
    "wof:placetype":"venue"
},
  "geometry": {"coordinates":[5.704943,51.882698],"type":"Point"}
}