{
  "type": "Feature",
  "properties": {
    "addr:full":"Tollensstraat 56 Gouda South Holland 2802 LP",
    "addr:housenumber":"56",
    "addr:postcode":"2802 lp",
    "addr:street":"Tollensstraat",
    "iso:country":"NL",
    "sg:address":"Tollensstraat 56",
    "sg:city":"Gouda",
    "sg:classifiers":[
        {
            "category":"Retail",
            "subcategory":"Photofinishing",
            "type":"Services"
        }
    ],
    "sg:phone":"+31 182 514 192",
    "sg:postcode":"2802 LP",
    "sg:province":"South Holland",
    "sg:tags":[
        "foto",
        "film"
    ],
    "wof:name":"Rio",
    "wof:placetype":"venue"
},
  "geometry": {"coordinates":[4.702384,52.004406],"type":"Point"}
}