{
  "type": "Feature",
  "properties": {
    "iso:country":"NL",
    "sg:address":"G Stephensonstr 21",
    "sg:city":"Zwolle",
    "sg:orig_category":"Verpakkingsbedrijven",
    "sg:phone":"+31 38 460 0324",
    "sg:postcode":"8013 NL",
    "sg:province":"Overijssel",
    "wof:name":"Interpanel Bv",
    "wof:placetype":"venue"
},
  "geometry": {"coordinates":[6.119637,52.492832],"type":"Point"}
}