{
  "type": "Feature",
  "properties": {
    "addr:full":"Nieuwstr 33 Gemert Noord-Brabant 5421 KN",
    "addr:housenumber":"33",
    "addr:postcode":"5421 kn",
    "addr:street":"Nieuwstr",
    "iso:country":"NL",
    "sg:address":"Nieuwstr 33",
    "sg:city":"Gemert",
    "sg:orig_category":"Warenhuizen",
    "sg:phone":"+31 492 366 196",
    "sg:postcode":"5421 KN",
    "sg:province":"Noord-Brabant",
    "wof:name":"Hema",
    "wof:placetype":"venue"
},
  "geometry": {"coordinates":[5.6822972298,51.5574035645],"type":"Point"}
}