{
  "type": "Feature",
  "properties": {
    "iso:country":"NL",
    "sg:address":"F Maelsonstr 20",
    "sg:city":"S Gravenhage",
    "sg:orig_category":"Verbouwingen",
    "sg:phone":"+31 70 358 4908",
    "sg:postcode":"2582 KC",
    "sg:province":"Zuid-Holland",
    "wof:name":"Jomien'S",
    "wof:placetype":"venue"
},
  "geometry": {"coordinates":[4.27852,52.092411],"type":"Point"}
}