{
  "type": "Feature",
  "properties": {
    "addr:full":"Dokkumertrekwg 28 Leeuwarden Provincie Friesland 8917 AA",
    "addr:housenumber":"28",
    "addr:postcode":"8917 aa",
    "addr:street":"Dokkumertrekwg;Provincie Friesland",
    "iso:country":"NL",
    "sg:address":"Dokkumertrekwg 28",
    "sg:city":"Leeuwarden",
    "sg:orig_category":"Autoschade- Herstelbedrijven",
    "sg:phone":"+31 58 215 9138",
    "sg:postcode":"8917 AA",
    "sg:province":"Provincie Friesland",
    "wof:name":"Car Care",
    "wof:placetype":"venue"
},
  "geometry": {"coordinates":[5.800821,53.211514],"type":"Point"}
}