{
  "type": "Feature",
  "properties": {
    "addr:full":"Kanaalwg 108 Harlingen Friesland 8861 KJ",
    "addr:housenumber":"108",
    "addr:postcode":"8861 kj",
    "iso:country":"NL",
    "sg:address":"Kanaalwg 108",
    "sg:city":"Harlingen",
    "sg:orig_category":"Houtgroothandel Hardhout",
    "sg:phone":"+31 517 413 377",
    "sg:postcode":"8861 KJ",
    "sg:province":"Friesland",
    "wof:name":"Houtcompagnie Almenum Bv",
    "wof:placetype":"venue"
},
  "geometry": {"coordinates":[5.447755,53.173996],"type":"Point"}
}