{
  "type": "Feature",
  "properties": {
    "addr:full":"Volderstr 1 Oostburg Zeeland 4501 JM",
    "addr:housenumber":"1",
    "addr:postcode":"4501 jm",
    "addr:street":"Volderstr",
    "iso:country":"NL",
    "sg:address":"Volderstr 1",
    "sg:city":"Oostburg",
    "sg:orig_category":"Elektrotechnische Installatiebureaus",
    "sg:phone":"+31 117 452 896",
    "sg:postcode":"4501 JM",
    "sg:province":"Zeeland",
    "wof:name":"Quist Bv",
    "wof:placetype":"venue"
},
  "geometry": {"coordinates":[3.489047,51.327499],"type":"Point"}
}