{
  "type": "Feature",
  "properties": {
    "iso:country":"NL",
    "sg:address":"Pieter Heusstraat 1",
    "sg:city":"'S Gravenzande",
    "sg:orig_category":"Drukkerijen And Copyshops",
    "sg:phone":"+31 174 412 544",
    "sg:postcode":"2691 BW",
    "sg:province":"Zuid-Holland",
    "wof:name":"Repro Filmo",
    "wof:placetype":"venue"
},
  "geometry": {"coordinates":[4.162133,52.000965],"type":"Point"}
}