{
  "type": "Feature",
  "properties": {
    "addr:full":"Kaneelstraat 25 Cuijk North Brabant 5431 DV",
    "addr:housenumber":"25",
    "addr:postcode":"5431 dv",
    "addr:street":"Kaneelstraat",
    "iso:country":"NL",
    "sg:address":"Kaneelstraat 25",
    "sg:city":"Cuijk",
    "sg:orig_category":"Kappers",
    "sg:phone":"+31 485 321 047",
    "sg:postcode":"5431 DV",
    "sg:province":"North Brabant",
    "wof:name":"Vof Kapsalon Gerrits",
    "wof:placetype":"venue"
},
  "geometry": {"coordinates":[5.881118,51.727028],"type":"Point"}
}