{
  "type": "Feature",
  "properties": {
    "addr:full":"Molenstraat 169 Ede Gld Gelderland 6712 CV",
    "addr:housenumber":"169",
    "addr:postcode":"6712 cv",
    "addr:street":"Molenstraat;Gld Gelderland",
    "iso:country":"NL",
    "sg:address":"Molenstraat 169",
    "sg:city":"Ede Gld",
    "sg:orig_category":"Drukkerijen And Copyshops",
    "sg:phone":"+31 318 619 018",
    "sg:postcode":"6712 CV",
    "sg:province":"Gelderland",
    "wof:name":"Repro Mercurius Bv",
    "wof:placetype":"venue"
},
  "geometry": {"coordinates":[5.655808,52.046303],"type":"Point"}
}