{
  "type": "Feature",
  "properties": {
    "addr:full":"Meiendel 5 Haarlem North Holland 2036 HN",
    "addr:housenumber":"5",
    "addr:postcode":"2036 hn",
    "addr:street":"Meiendel",
    "iso:country":"NL",
    "sg:address":"Meiendel 5",
    "sg:city":"Haarlem",
    "sg:orig_category":"Boekhouders",
    "sg:phone":"+31 23 533 0846",
    "sg:postcode":"2036 HN",
    "sg:province":"North Holland",
    "wof:name":"J.Th.G. Spronk",
    "wof:placetype":"venue"
},
  "geometry": {"coordinates":[4.648383,52.348312],"type":"Point"}
}