{
  "type": "Feature",
  "properties": {
    "addr:full":"Vrederustln 127 S Gravenhage South Holland 2543 SM",
    "addr:housenumber":"127",
    "addr:postcode":"2543 sm",
    "addr:street":"S Gravenhage",
    "iso:country":"NL",
    "sg:address":"Vrederustln 127",
    "sg:city":"S Gravenhage",
    "sg:orig_category":"Kappers",
    "sg:phone":"+31 70 308 0004",
    "sg:postcode":"2543 SM",
    "sg:province":"South Holland",
    "sg:website":"http://www.zahaira.nl",
    "wof:name":"Zahaira",
    "wof:placetype":"venue"
},
  "geometry": {"coordinates":[4.26264,52.040501],"type":"Point"}
}