{
  "type": "Feature",
  "properties": {
    "iso:country":"NL",
    "sg:address":"Isebrandtsheerd 95",
    "sg:city":"Groningen",
    "sg:orig_category":"Vertaal- And Tolkenbureaus",
    "sg:phone":"+31 50 542 2536",
    "sg:postcode":"9737 LK",
    "sg:province":"Groningen",
    "wof:name":"M J Kruyt Vertalingen",
    "wof:placetype":"venue"
},
  "geometry": {"coordinates":[6.59239,53.244995],"type":"Point"}
}