{
  "type": "Feature",
  "properties": {
    "iso:country":"NL",
    "sg:address":"Energieweg 34",
    "sg:city":"Oosterhout Nb",
    "sg:orig_category":"Diverse Bedrijfsinstallaties Gh",
    "sg:phone":"+31 162 456 397",
    "sg:postcode":"4906 CG",
    "sg:province":"Noord-Brabant",
    "wof:name":"Reggiana Riduttori",
    "wof:placetype":"venue"
},
  "geometry": {"coordinates":[4.847243,51.657406],"type":"Point"}
}