{
  "type": "Feature",
  "properties": {
    "addr:full":"Erasmusweg 7 Culemborg Gelderland 4104 AK",
    "addr:housenumber":"7",
    "addr:postcode":"4104 ak",
    "addr:street":"Erasmusweg;Gelderland",
    "iso:country":"NL",
    "sg:address":"Erasmusweg 7",
    "sg:city":"Culemborg",
    "sg:orig_category":"Diverse Grafische Activiteiten",
    "sg:phone":"+31 345 545 555",
    "sg:postcode":"4104 AK",
    "sg:province":"Gelderland",
    "wof:name":"Binderij Saturnus Bv",
    "wof:placetype":"venue"
},
  "geometry": {"coordinates":[5.213892,51.94009],"type":"Point"}
}