{
  "type": "Feature",
  "properties": {
    "addr:full":"Fonteynenburghln 8 Voorburg South Holland 2275 CX",
    "addr:housenumber":"8",
    "addr:postcode":"2275 cx",
    "addr:street":"Fonteynenburghln",
    "iso:country":"NL",
    "sg:address":"Fonteynenburghln 8",
    "sg:city":"Voorburg",
    "sg:orig_category":"Bedrijfsopleidingen",
    "sg:phone":"+31 70 336 8861",
    "sg:postcode":"2275 CX",
    "sg:province":"South Holland",
    "wof:name":"Samenwerkingsverband Zh, Sticht",
    "wof:placetype":"venue"
},
  "geometry": {"coordinates":[4.352571,52.061844],"type":"Point"}
}