{
  "type": "Feature",
  "properties": {
    "addr:full":"M Stokeln 10 S Gravenhage Zuid-Holland 2533 EA",
    "addr:housenumber":"10;gravenhage",
    "addr:postcode":"2533 ea",
    "addr:street":"S",
    "iso:country":"NL",
    "sg:address":"M Stokeln 10",
    "sg:city":"S Gravenhage",
    "sg:orig_category":"Fietsen En Bromfietsen Onderdelen - Fabr. En Grooth",
    "sg:phone":"+31 70 388 5360",
    "sg:postcode":"2533 EA",
    "sg:province":"Zuid-Holland",
    "wof:name":"Emmerik",
    "wof:placetype":"venue"
},
  "geometry": {"coordinates":[4.28581,52.05286],"type":"Point"}
}