{
  "type": "Feature",
  "properties": {
    "iso:country":"NL",
    "sg:address":"Stationsplein 10",
    "sg:city":"Rijen",
    "sg:orig_category":"Koffers And Tassen Fab",
    "sg:phone":"+31 161 224 655",
    "sg:postcode":"5121 EA",
    "sg:province":"North Brabant",
    "wof:name":"Emac Bv",
    "wof:placetype":"venue"
},
  "geometry": {"coordinates":[4.923981,51.584118],"type":"Point"}
}