{
  "type": "Feature",
  "properties": {
    "addr:full":"Terbregsewg 120 Rotterdam Zuid-Holland 3056 JX",
    "addr:housenumber":"120",
    "addr:postcode":"3056 jx",
    "iso:country":"NL",
    "sg:address":"Terbregsewg 120",
    "sg:city":"Rotterdam",
    "sg:orig_category":"Petrochemische Industrie - Installaties En Onderhoud",
    "sg:phone":"+31 10 420 6011",
    "sg:postcode":"3056 JX",
    "sg:province":"Zuid-Holland",
    "sg:website":"http://www.dopak.com",
    "wof:name":"Dovianus Bv",
    "wof:placetype":"venue"
},
  "geometry": {"coordinates":[4.524913,51.951942],"type":"Point"}
}