{
  "type": "Feature",
  "properties": {
    "iso:country":"NL",
    "sg:address":"Hoofdweg 88",
    "sg:city":"Harkstede",
    "sg:orig_category":"Bloemen And Planten",
    "sg:phone":"+31 50 404 1707",
    "sg:postcode":"9617 AJ",
    "sg:province":"Groningen",
    "wof:name":"Bloemenhuis Kamps",
    "wof:placetype":"venue"
},
  "geometry": {"coordinates":[6.693691,53.212387],"type":"Point"}
}