{
  "type": "Feature",
  "properties": {
    "addr:full":"Baas Gansendonckstraat 2 Amsterdam North Holland 1061 DA",
    "addr:housenumber":"2",
    "addr:postcode":"1061 da",
    "addr:street":"Baas Gansendonckstraat",
    "iso:country":"NL",
    "sg:address":"Baas Gansendonckstraat 2",
    "sg:city":"Amsterdam",
    "sg:orig_category":"Fitnesscentra",
    "sg:phone":"+31 20 688 1556",
    "sg:postcode":"1061 DA",
    "sg:province":"North Holland",
    "wof:name":"R Van De Vathorst",
    "wof:placetype":"venue"
},
  "geometry": {"coordinates":[4.840741,52.377316],"type":"Point"}
}