{
  "type": "Feature",
  "properties": {
    "iso:country":"NL",
    "sg:address":"Baas Gansendonckstraat 2",
    "sg:city":"Amsterdam",
    "sg:orig_category":"Fitnesscentra",
    "sg:phone":"+31 20 688 1556",
    "sg:postcode":"1061 DA",
    "sg:province":"North Holland",
    "wof:name":"R Van De Vathorst",
    "wof:placetype":"venue"
},
  "geometry": {"coordinates":[4.840741,52.377316],"type":"Point"}
}