{
  "type": "Feature",
  "properties": {
    "addr:full":"Lundlaan 8 Utrecht Utrecht 3584 EA",
    "addr:housenumber":"8",
    "addr:postcode":"3584 ea",
    "addr:street":"Lundlaan",
    "iso:country":"NL",
    "sg:address":"Lundlaan 8",
    "sg:city":"Utrecht",
    "sg:orig_category":"Bloed- And Andere Donoren",
    "sg:phone":"+31 30 250 3700",
    "sg:postcode":"3584 EA",
    "sg:province":"Utrecht",
    "wof:name":"Bloedbank Midden Nederland",
    "wof:placetype":"venue"
},
  "geometry": {"coordinates":[5.179218,52.088444],"type":"Point"}
}