{
  "type": "Feature",
  "properties": {
    "iso:country":"NL",
    "sg:address":"Kleipad 3",
    "sg:city":"Chaam",
    "sg:orig_category":"Kappers",
    "sg:phone":"+31 161 492 666",
    "sg:postcode":"4861 CB",
    "sg:province":"Noord-Brabant",
    "wof:name":"Marisca",
    "wof:placetype":"venue"
},
  "geometry": {"coordinates":[4.856422,51.499123],"type":"Point"}
}