{
  "type": "Feature",
  "properties": {
    "addr:full":"Dorpstr 41 Lieshout North Brabant 5737 GA",
    "addr:housenumber":"41",
    "addr:postcode":"5737 ga",
    "addr:street":"Dorpstr",
    "iso:country":"NL",
    "sg:address":"Dorpstr 41",
    "sg:city":"Lieshout",
    "sg:orig_category":"Bloemen En Planten",
    "sg:phone":"+31 499 422 841",
    "sg:postcode":"5737 GA",
    "sg:province":"North Brabant",
    "wof:name":"Hanneke",
    "wof:placetype":"venue"
},
  "geometry": {"coordinates":[5.593426,51.522125],"type":"Point"}
}