{
  "type": "Feature",
  "properties": {
    "addr:full":"Oudewg 92 Siddeburen Groningen 9628 CG",
    "addr:housenumber":"92",
    "addr:postcode":"9628 cg",
    "addr:street":"Oudewg",
    "iso:country":"NL",
    "sg:address":"Oudewg 92",
    "sg:city":"Siddeburen",
    "sg:orig_category":"Kappers",
    "sg:phone":"+31 598 431 238",
    "sg:postcode":"9628 CG",
    "sg:province":"Groningen",
    "wof:name":"Paola",
    "wof:placetype":"venue"
},
  "geometry": {"coordinates":[6.869438,53.249641],"type":"Point"}
}