{
  "type": "Feature",
  "properties": {
    "iso:country":"NL",
    "sg:address":"V Zuilenln 17",
    "sg:city":"Hooglanderveen",
    "sg:orig_category":"Accountants - Administratie- Consulenten En -Kantoren",
    "sg:phone":"+31 33 258 0169",
    "sg:postcode":"3829 AP",
    "sg:province":"Utrecht",
    "wof:name":"Petersen, G",
    "wof:placetype":"venue"
},
  "geometry": {"coordinates":[5.431815,52.188042],"type":"Point"}
}