{
  "type": "Feature",
  "properties": {
    "iso:country":"NL",
    "sg:address":"Kuiperswg 23-25",
    "sg:city":"Middelburg",
    "sg:orig_category":"Verhuizingen",
    "sg:phone":"+31 118 626 649",
    "sg:postcode":"4338 PH",
    "sg:province":"Zeeland",
    "sg:website":"http://www.caljouw-rademaker.nl",
    "wof:name":"Caljouw Rademaker Verhuizingen",
    "wof:placetype":"venue"
},
  "geometry": {"coordinates":[3.634731,51.497047],"type":"Point"}
}