{
  "type": "Feature",
  "properties": {
    "iso:country":"NL",
    "sg:address":"St Catharinapln 16",
    "sg:city":"Bergen Op Zoom",
    "sg:orig_category":"Hengelsportartikelen",
    "sg:phone":"+31 164 233 056",
    "sg:postcode":"4611 TS",
    "sg:province":"North Brabant",
    "wof:name":"Jurgers, A",
    "wof:placetype":"venue"
},
  "geometry": {"coordinates":[4.286144,51.496784],"type":"Point"}
}