{
  "type": "Feature",
  "properties": {
    "addr:full":"Churchillsngl 484 Vlaardingen Zuid-Holland 3137 XB",
    "addr:housenumber":"484",
    "addr:postcode":"3137 xb",
    "iso:country":"NL",
    "sg:address":"Churchillsngl 484",
    "sg:city":"Vlaardingen",
    "sg:orig_category":"Huidtherapeuten",
    "sg:phone":"+31 10 475 2777",
    "sg:postcode":"3137 XB",
    "sg:province":"Zuid-Holland",
    "sg:website":"http://www.skintherapie.nl",
    "wof:name":"Skin Therapy",
    "wof:placetype":"venue"
},
  "geometry": {"coordinates":[4.340359,51.910442],"type":"Point"}
}