{
  "type": "Feature",
  "properties": {
    "addr:full":"Parkweg 37 Ede Gld Gelderland 6717 HL",
    "addr:housenumber":"37",
    "addr:postcode":"6717 hl",
    "addr:street":"Parkweg;Gld Gelderland",
    "iso:country":"NL",
    "sg:address":"Parkweg 37",
    "sg:city":"Ede Gld",
    "sg:classifiers":[
        {
            "category":"Fast Food",
            "type":"Food & Drink"
        }
    ],
    "sg:phone":"+31 318 641 494",
    "sg:postcode":"6717 HL",
    "sg:province":"Gelderland",
    "sg:tags":[
        "afhaal",
        "restaurant"
    ],
    "wof:name":"Vof Piramide",
    "wof:placetype":"venue"
},
  "geometry": {"coordinates":[5.669597,52.027657],"type":"Point"}
}