{
  "type": "Feature",
  "properties": {
    "addr:full":"P Jelles Troelstraln 28 Amersfoort Utrecht 3818 KT",
    "addr:housenumber":"28",
    "addr:postcode":"3818 kt",
    "addr:street":"P Jelles Troelstraln",
    "iso:country":"NL",
    "sg:address":"P Jelles Troelstraln 28",
    "sg:city":"Amersfoort",
    "sg:orig_category":"Artsen And Specialisten",
    "sg:phone":"+31 33 465 0207",
    "sg:postcode":"3818 KT",
    "sg:province":"Utrecht",
    "wof:name":"H.J. Stoel",
    "wof:placetype":"venue"
},
  "geometry": {"coordinates":[5.360787,52.150398],"type":"Point"}
}