{
  "type": "Feature",
  "properties": {
    "addr:full":"Burgemeester Bickerstr 46A Diemen Noord-Holland 1111 CC",
    "addr:housenumber":"46a",
    "addr:postcode":"1111 cc",
    "addr:street":"Burgemeester Bickerstr",
    "iso:country":"NL",
    "sg:address":"Burgemeester Bickerstr 46A",
    "sg:city":"Diemen",
    "sg:orig_category":"Verenigingen En Stichtingen",
    "sg:phone":"+31 20 699 6750",
    "sg:postcode":"1111 CC",
    "sg:province":"Noord-Holland",
    "wof:name":"Schakel, De",
    "wof:placetype":"venue"
},
  "geometry": {"coordinates":[4.962123,52.340752],"type":"Point"}
}