{
  "type": "Feature",
  "properties": {
    "addr:full":"Stokhorstlaan 90 Enschede Overijssel 7531 JG",
    "addr:housenumber":"90",
    "addr:postcode":"7531 jg",
    "addr:street":"Stokhorstlaan",
    "iso:country":"NL",
    "sg:address":"Stokhorstlaan 90",
    "sg:city":"Enschede",
    "sg:orig_category":"Autokeuringen",
    "sg:phone":"+31 53 435 4680",
    "sg:postcode":"7531 JG",
    "sg:province":"Overijssel",
    "wof:name":"Autoscala Enschede Bv",
    "wof:placetype":"venue"
},
  "geometry": {"coordinates":[6.91417,52.23748],"type":"Point"}
}