{
  "type": "Feature",
  "properties": {
    "addr:full":"Verduinsbos 57 Halsteren North Brabant 4661 NV",
    "addr:housenumber":"57",
    "addr:postcode":"4661 nv",
    "addr:street":"Verduinsbos",
    "iso:country":"NL",
    "sg:address":"Verduinsbos 57",
    "sg:city":"Halsteren",
    "sg:orig_category":"Psychotherapeuten",
    "sg:phone":"+31 164 683 391",
    "sg:postcode":"4661 NV",
    "sg:province":"North Brabant",
    "wof:name":"Bons-Vanlommel B M A",
    "wof:placetype":"venue"
},
  "geometry": {"coordinates":[4.284125,51.525661],"type":"Point"}
}