{
  "type": "Feature",
  "properties": {
    "addr:full":"Halseweg 34 Zelhem Gelderland 7021 HV",
    "addr:housenumber":"34",
    "addr:postcode":"7021 hv",
    "addr:street":"Halseweg;Gelderland",
    "iso:country":"NL",
    "sg:address":"Halseweg 34",
    "sg:city":"Zelhem",
    "sg:orig_category":"Medische Apparatuur And Prothesen Fab",
    "sg:phone":"+31 314 621 626",
    "sg:postcode":"7021 HV",
    "sg:province":"Gelderland",
    "wof:name":"R C Van Soest Zelhem",
    "wof:placetype":"venue"
},
  "geometry": {"coordinates":[6.367451,52.005116],"type":"Point"}
}