{
  "type": "Feature",
  "properties": {
    "addr:full":"Terrasweg 32 Santpoort Noord British Columbia 2071 BC",
    "addr:housenumber":"32",
    "addr:postcode":"2071 bc",
    "addr:street":"Terrasweg;Santpoort Noord",
    "iso:country":"NL",
    "sg:address":"Terrasweg 32",
    "sg:city":"Santpoort Noord",
    "sg:orig_category":"Wasserettes And Stomerijen",
    "sg:phone":"+31 23 537 7611",
    "sg:postcode":"2071 BC",
    "sg:province":"British Columbia",
    "wof:name":"G W Slenders",
    "wof:placetype":"venue"
},
  "geometry": {"coordinates":[-126.5555114746,54.4856681824],"type":"Point"}
}