{
  "type": "Feature",
  "properties": {
    "addr:full":"Van Rosenburgweg 6 Nijmegen Gelderland 6537 TM",
    "addr:housenumber":"6",
    "addr:postcode":"6537 tm",
    "addr:street":"Van Rosenburgweg;Gelderland",
    "iso:country":"NL",
    "sg:address":"Van Rosenburgweg 6",
    "sg:city":"Nijmegen",
    "sg:orig_category":"Dansscholen",
    "sg:phone":"+31 24 344 0534",
    "sg:postcode":"6537 TM",
    "sg:province":"Gelderland",
    "wof:name":"Ballet & Sportcentrum Lines Dancing Arts",
    "wof:placetype":"venue"
},
  "geometry": {"coordinates":[5.790792,51.822693],"type":"Point"}
}