{
  "type": "Feature",
  "properties": {
    "addr:full":"R Amundsenstr 60 Emmen Provincie Drenthe 7825 AV",
    "addr:housenumber":"60;7825",
    "addr:postcode":"av",
    "addr:street":"Provincie Drenthe",
    "iso:country":"NL",
    "sg:address":"R Amundsenstr 60",
    "sg:city":"Emmen",
    "sg:orig_category":"Autoschade- Herstelbedrijven",
    "sg:phone":"+31 591 394 086",
    "sg:postcode":"7825 AV",
    "sg:province":"Provincie Drenthe",
    "wof:name":"Autoschade Oranjedorp",
    "wof:placetype":"venue"
},
  "geometry": {"coordinates":[6.94363,52.7449],"type":"Point"}
}