{
  "type": "Feature",
  "properties": {
    "addr:full":"Zuiderbeemd 13 Oosterhout Nb North Brabant 4907 EL",
    "addr:housenumber":"13;nb",
    "addr:postcode":"4907 el",
    "addr:street":"Zuiderbeemd",
    "iso:country":"NL",
    "sg:address":"Zuiderbeemd 13",
    "sg:city":"Oosterhout Nb",
    "sg:orig_category":"Goederenvervoer Over De Weg",
    "sg:phone":"+31 162 431 480",
    "sg:postcode":"4907 EL",
    "sg:province":"North Brabant",
    "wof:name":"Auke Redelaar",
    "wof:placetype":"venue"
},
  "geometry": {"coordinates":[4.857027,51.659924],"type":"Point"}
}