{
  "type": "Feature",
  "properties": {
    "iso:country":"NL",
    "sg:address":"Tweebosstraat 153",
    "sg:city":"Rotterdam",
    "sg:orig_category":"Diverse Consumentenartikelen Gh",
    "sg:phone":"+31 10 485 9284",
    "sg:postcode":"3072 BP",
    "sg:province":"South Holland",
    "wof:name":"Handelsonderneming Tausif",
    "wof:placetype":"venue"
},
  "geometry": {"coordinates":[4.507549,51.899227],"type":"Point"}
}