{
  "type": "Feature",
  "properties": {
    "addr:full":"Limbrichterstr 12 Sittard Limburg 6131 EC",
    "addr:housenumber":"12",
    "addr:postcode":"6131 ec",
    "addr:street":"Limbrichterstr",
    "iso:country":"NL",
    "sg:address":"Limbrichterstr 12",
    "sg:city":"Sittard",
    "sg:classifiers":[
        {
            "category":"Farming",
            "subcategory":"Fish & Marine Products",
            "type":"Manufacturing & Wholesale Goods"
        }
    ],
    "sg:phone":"+31 46 452 8004",
    "sg:postcode":"6131 EC",
    "sg:province":"Limburg",
    "sg:tags":[
        "vi"
    ],
    "wof:name":"Visscher, De",
    "wof:placetype":"venue"
},
  "geometry": {"coordinates":[5.869552,50.99802],"type":"Point"}
}