{
  "type": "Feature",
  "properties": {
    "addr:full":"Elleboogstraat 5 Katwijk Zh Zuid-Holland 2225 GK",
    "addr:housenumber":"5",
    "addr:postcode":"2225 gk",
    "addr:street":"Elleboogstraat",
    "iso:country":"NL",
    "sg:address":"Elleboogstraat 5",
    "sg:city":"Katwijk Zh",
    "sg:classifiers":[
        {
            "category":"Professional",
            "subcategory":"Accounting & Tax Preparation",
            "type":"Services"
        }
    ],
    "sg:phone":"+31 71 407 4212",
    "sg:postcode":"2225 GK",
    "sg:province":"Zuid-Holland",
    "sg:tags":[
        "accountant"
    ],
    "wof:name":"Accountantskantoor Drs. L.K. Van Rijn",
    "wof:placetype":"venue"
},
  "geometry": {"coordinates":[4.396129,52.202839],"type":"Point"}
}