{
  "type": "Feature",
  "properties": {
    "addr:full":"Hoeksterpad 16 Leeuwarden Provincie Friesland 8911 JW",
    "addr:housenumber":"16",
    "addr:postcode":"8911 jw",
    "addr:street":"Hoeksterpad;Provincie Friesland",
    "iso:country":"NL",
    "sg:address":"Hoeksterpad 16",
    "sg:city":"Leeuwarden",
    "sg:orig_category":"Peuterspeelzalen",
    "sg:phone":"+31 58 213 9268",
    "sg:postcode":"8911 JW",
    "sg:province":"Provincie Friesland",
    "wof:name":"Kr\u00fbmelhoek, De",
    "wof:placetype":"venue"
},
  "geometry": {"coordinates":[5.802649,53.205082],"type":"Point"}
}