{
  "type": "Feature",
  "properties": {
    "addr:full":"Gerard Doustraat 170 'S Gravenhage Zuid-Holland 2526 NK",
    "addr:housenumber":"170 '",
    "addr:postcode":"2526 nk",
    "addr:street":"Gerard Doustraat",
    "iso:country":"NL",
    "sg:address":"Gerard Doustraat 170",
    "sg:city":"'S Gravenhage",
    "sg:orig_category":"Geluidsopnamen",
    "sg:phone":"+31 70 389 9509",
    "sg:postcode":"2526 NK",
    "sg:province":"Zuid-Holland",
    "wof:name":"Slick",
    "wof:placetype":"venue"
},
  "geometry": {"coordinates":[4.303761,52.068466],"type":"Point"}
}