{
  "type": "Feature",
  "properties": {
    "addr:full":"Hof V Venetie 6 Leiden South Holland 2312 TA",
    "addr:housenumber":"6",
    "addr:postcode":"2312 ta",
    "addr:street":"Venetie",
    "iso:country":"NL",
    "sg:address":"Hof V Venetie 6",
    "sg:city":"Leiden",
    "sg:orig_category":"Meditatietechnieken",
    "sg:phone":"+31 71 522 1432",
    "sg:postcode":"2312 TA",
    "sg:province":"South Holland",
    "wof:name":"Metman Van Reijn",
    "wof:placetype":"venue"
},
  "geometry": {"coordinates":[4.49463,52.154572],"type":"Point"}
}