{
  "type": "Feature",
  "properties": {
    "addr:full":"De Vriesstr 38 Eindhoven Noord-Brabant 5612 KK",
    "addr:housenumber":"38",
    "addr:postcode":"5612 kk",
    "iso:country":"NL",
    "sg:address":"De Vriesstr 38",
    "sg:city":"Eindhoven",
    "sg:classifiers":[
        {
            "category":"Personal",
            "subcategory":"Nail Salon",
            "type":"Services"
        }
    ],
    "sg:phone":"+31 40 246 0854",
    "sg:postcode":"5612 KK",
    "sg:province":"Noord-Brabant",
    "sg:tags":[
        "pedicure"
    ],
    "wof:name":"Your Emanation",
    "wof:placetype":"venue"
},
  "geometry": {"coordinates":[5.471836,51.447628],"type":"Point"}
}