{
  "type": "Feature",
  "properties": {
    "addr:full":"Oude Weerln 60 Hillegom Zuid-Holland 2181 HZ",
    "addr:housenumber":"60",
    "addr:postcode":"2181 hz",
    "addr:street":"Oude Weerln",
    "iso:country":"NL",
    "sg:address":"Oude Weerln 60",
    "sg:city":"Hillegom",
    "sg:classifiers":[
        {
            "category":"Sports & Exercise",
            "subcategory":"Stables",
            "type":"Entertainment"
        }
    ],
    "sg:phone":"+31 252 520 373",
    "sg:postcode":"2181 HZ",
    "sg:province":"Zuid-Holland",
    "sg:tags":[
        "maneges"
    ],
    "wof:name":"Hillegom, Manege",
    "wof:placetype":"venue"
},
  "geometry": {"coordinates":[4.594118,52.299309],"type":"Point"}
}