{
  "type": "Feature",
  "properties": {
    "addr:full":"Dampoortstraat 12 Middelburg Zeeland 4332 AV",
    "addr:housenumber":"12",
    "addr:postcode":"4332 av",
    "addr:street":"Dampoortstraat",
    "iso:country":"NL",
    "sg:address":"Dampoortstraat 12",
    "sg:city":"Middelburg",
    "sg:orig_category":"Kantoorartikelen",
    "sg:phone":"+31 118 612 325",
    "sg:postcode":"4332 AV",
    "sg:province":"Zeeland",
    "wof:name":"Paul Zijnen Techniek",
    "wof:placetype":"venue"
},
  "geometry": {"coordinates":[3.6241359711,51.5014266968],"type":"Point"}
}