{
  "type": "Feature",
  "properties": {
    "iso:country":"NL",
    "sg:address":"Plein 13",
    "sg:city":"Wateringen",
    "sg:orig_category":"Boekhouders",
    "sg:phone":"+31 174 270 388",
    "sg:postcode":"2291 CA",
    "sg:province":"South Holland",
    "wof:name":"Bf & A Consultancy",
    "wof:placetype":"venue"
},
  "geometry": {"coordinates":[4.274468,52.024117],"type":"Point"}
}