{
  "type": "Feature",
  "properties": {
    "addr:full":"Bovenwg 21 De Blesse Provincie Friesland 8397 GA",
    "addr:housenumber":"21",
    "addr:postcode":"8397 ga",
    "addr:street":"Bovenwg;Friesland",
    "iso:country":"NL",
    "sg:address":"Bovenwg 21",
    "sg:city":"De Blesse",
    "sg:orig_category":"Voetbalverenigingen",
    "sg:phone":"+31 561 441 741",
    "sg:postcode":"8397 GA",
    "sg:province":"Provincie Friesland",
    "wof:name":"Blesse, De",
    "wof:placetype":"venue"
},
  "geometry": {"coordinates":[6.04433,52.843262],"type":"Point"}
}