{
  "type": "Feature",
  "properties": {
    "addr:full":"Litauensestr 5 Zutphen Gelderland 7202 CN",
    "addr:housenumber":"5",
    "addr:postcode":"7202 cn",
    "addr:street":"Litauensestr;Gelderland",
    "iso:country":"NL",
    "sg:address":"Litauensestr 5",
    "sg:city":"Zutphen",
    "sg:orig_category":"Metaalbewerking",
    "sg:phone":"+31 575 516 790",
    "sg:postcode":"7202 CN",
    "sg:province":"Gelderland",
    "sg:website":"http://www.justivometaaltechniek.nl",
    "wof:name":"Justivo Metaaltechniek Bv",
    "wof:placetype":"venue"
},
  "geometry": {"coordinates":[6.197746,52.158192],"type":"Point"}
}