{
  "type": "Feature",
  "properties": {
    "addr:full":"Kampakkers 24 Borger Drenthe 9531 HT",
    "addr:housenumber":"24",
    "addr:postcode":"9531 ht",
    "addr:street":"Kampakkers",
    "iso:country":"NL",
    "sg:address":"Kampakkers 24",
    "sg:city":"Borger",
    "sg:orig_category":"Goederenvervoer Over De Weg",
    "sg:phone":"+31 599 236 326",
    "sg:postcode":"9531 HT",
    "sg:province":"Drenthe",
    "wof:name":"Albo Trans",
    "wof:placetype":"venue"
},
  "geometry": {"coordinates":[6.79403,52.930847],"type":"Point"}
}