{
  "type": "Feature",
  "properties": {
    "addr:full":"Koestraat 8 Tilburg Noord-Brabant 5014 ED",
    "addr:housenumber":"8",
    "addr:postcode":"5014 ed",
    "addr:street":"Koestraat",
    "iso:country":"NL",
    "sg:address":"Koestraat 8",
    "sg:city":"Tilburg",
    "sg:classifiers":[
        {
            "category":"Fast Food",
            "type":"Food & Drink"
        }
    ],
    "sg:phone":"+31 13 536 9115",
    "sg:postcode":"5014 ED",
    "sg:province":"Noord-Brabant",
    "sg:tags":[
        "afhaal",
        "restaurant"
    ],
    "wof:name":"Restaurant Tilburg",
    "wof:placetype":"venue"
},
  "geometry": {"coordinates":[5.106271,51.554928],"type":"Point"}
}