{
  "type": "Feature",
  "properties": {
    "iso:country":"NL",
    "sg:address":"Nieuwstg 45",
    "sg:city":"Hoorn Nh",
    "sg:orig_category":"Kinderkleding",
    "sg:phone":"+31 229 249 450",
    "sg:postcode":"1621 EC",
    "sg:province":"Noord-Holland",
    "wof:name":"Stout",
    "wof:placetype":"venue"
},
  "geometry": {"coordinates":[5.059096,52.641521],"type":"Point"}
}