{
  "type": "Feature",
  "properties": {
    "addr:full":"Dorpsstr 43 Wormer Noord-Holland 1531 HA",
    "addr:housenumber":"43",
    "addr:postcode":"1531 ha",
    "addr:street":"Dorpsstr",
    "iso:country":"NL",
    "sg:address":"Dorpsstr 43",
    "sg:city":"Wormer",
    "sg:orig_category":"Banken",
    "sg:phone":"+31 75 653 6536",
    "sg:postcode":"1531 HA",
    "sg:province":"Noord-Holland",
    "sg:website":"http://www.rabobank.nl",
    "wof:name":"Rabobank",
    "wof:placetype":"venue"
},
  "geometry": {"coordinates":[4.811834,52.498348],"type":"Point"}
}