{
  "type": "Feature",
  "properties": {
    "addr:full":"Aak 21 Kropswolde Groningen 9606 PX",
    "addr:housenumber":"21",
    "addr:postcode":"9606 px",
    "addr:street":"Aak",
    "iso:country":"NL",
    "sg:address":"Aak 21",
    "sg:city":"Kropswolde",
    "sg:orig_category":"Architecten En Architectenbureaus",
    "sg:phone":"+31 598 322 862",
    "sg:postcode":"9606 PX",
    "sg:province":"Groningen",
    "wof:name":"Huitema Vof",
    "wof:placetype":"venue"
},
  "geometry": {"coordinates":[6.714478,53.145412],"type":"Point"}
}