{
  "type": "Feature",
  "properties": {
    "addr:full":"Kanaalwg 94C Utrecht Utrecht 3533 HH",
    "addr:housenumber":"94c",
    "addr:postcode":"3533 hh",
    "addr:street":"Kanaalwg",
    "iso:country":"NL",
    "sg:address":"Kanaalwg 94C",
    "sg:city":"Utrecht",
    "sg:orig_category":"Kinderopvang",
    "sg:phone":"+31 30 294 9077",
    "sg:postcode":"3533 HH",
    "sg:province":"Utrecht",
    "wof:name":"Irene",
    "wof:placetype":"venue"
},
  "geometry": {"coordinates":[5.087833,52.08897],"type":"Point"}
}