{
  "type": "Feature",
  "properties": {
    "addr:full":"Vismarkt 2 Leiden South Holland 2311 EH",
    "addr:housenumber":"2",
    "addr:postcode":"2311 eh",
    "addr:street":"Vismarkt",
    "iso:country":"NL",
    "sg:address":"Vismarkt 2",
    "sg:city":"Leiden",
    "sg:orig_category":"Schoenen",
    "sg:phone":"+31 71 512 1065",
    "sg:postcode":"2311 EH",
    "sg:province":"South Holland",
    "wof:name":"Hollants",
    "wof:placetype":"venue"
},
  "geometry": {"coordinates":[4.491028,52.158829],"type":"Point"}
}