{
  "type": "Feature",
  "properties": {
    "addr:full":"Rietzanger 52 Hoorn Nh Noord-Holland 1628 CN",
    "addr:housenumber":"52",
    "addr:postcode":"1628 cn",
    "addr:street":"Rietzanger",
    "iso:country":"NL",
    "sg:address":"Rietzanger 52",
    "sg:city":"Hoorn Nh",
    "sg:orig_category":"Bedrijfsopleidingen",
    "sg:phone":"+31 229 275 068",
    "sg:postcode":"1628 CN",
    "sg:province":"Noord-Holland",
    "wof:name":"Opl",
    "wof:placetype":"venue"
},
  "geometry": {"coordinates":[5.078669,52.650208],"type":"Point"}
}