{
  "type": "Feature",
  "properties": {
    "iso:country":"NL",
    "sg:address":"Biltstraat 447",
    "sg:city":"Utrecht",
    "sg:orig_category":"Werving And Selectie Van Tijdelijk Personeel And Uitzendkantoren",
    "sg:phone":"+31 30 231 1044",
    "sg:postcode":"3572 AW",
    "sg:province":"Utrecht",
    "wof:name":"Susa Studenten Uitzendbureau",
    "wof:placetype":"venue"
},
  "geometry": {"coordinates":[5.1360430717,52.0954246521],"type":"Point"}
}