{
  "type": "Feature",
  "properties": {
    "addr:full":"Ryswyksewg 195 S Gravenhage Zuid-Holland 2516 HC",
    "addr:housenumber":"195;gravenhage",
    "addr:postcode":"2516 hc",
    "addr:street":"S",
    "iso:country":"NL",
    "sg:address":"Ryswyksewg 195",
    "sg:city":"S Gravenhage",
    "sg:orig_category":"Administratie- En Boekhoudkantoren",
    "sg:phone":"+31 70 365 9503",
    "sg:postcode":"2516 HC",
    "sg:province":"Zuid-Holland",
    "wof:name":"Lam, W Ch",
    "wof:placetype":"venue"
},
  "geometry": {"coordinates":[4.33931,52.06786],"type":"Point"}
}