{
  "type": "Feature",
  "properties": {
    "iso:country":"NL",
    "sg:address":"2E Balsemienstraat 14",
    "sg:city":"Rotterdam",
    "sg:classifiers":[
        {
            "category":"Education",
            "subcategory":"Preschool",
            "type":"Public Place"
        }
    ],
    "sg:phone":"+31 10 485 3325",
    "sg:postcode":"3073 VE",
    "sg:province":"Zuid-Holland",
    "sg:tags":[
        "kleuteronderwijs",
        "basis-"
    ],
    "wof:name":"Openbare Basisschool De Groeneweg",
    "wof:placetype":"venue"
},
  "geometry": {"coordinates":[4.500846,51.894234],"type":"Point"}
}