{
  "type": "Feature",
  "properties": {
    "iso:country":"NL",
    "sg:address":"Broekstraat 11/11A",
    "sg:city":"Bergeyk",
    "sg:orig_category":"Elektrotechnische Artikelen",
    "sg:phone":"+31 497 571 631",
    "sg:postcode":"5571 KJ",
    "sg:province":"Noord-Brabant",
    "wof:name":"Hendriks Vof, Gebr",
    "wof:placetype":"venue"
},
  "geometry": {"coordinates":[5.357207,51.313698],"type":"Point"}
}