{
  "type": "Feature",
  "properties": {
    "addr:full":"Plantsoen 1 Geertruidenberg North Brabant 4931 AT",
    "addr:housenumber":"1",
    "addr:postcode":"4931",
    "addr:street":"Plantsoen",
    "iso:country":"NL",
    "sg:address":"Plantsoen 1",
    "sg:city":"Geertruidenberg",
    "sg:orig_category":"Kappers",
    "sg:phone":"+31 162 517 265",
    "sg:postcode":"4931 AT",
    "sg:province":"North Brabant",
    "wof:name":"Knippen Enzo",
    "wof:placetype":"venue"
},
  "geometry": {"coordinates":[4.863695,51.699551],"type":"Point"}
}