{
  "type": "Feature",
  "properties": {
    "addr:full":"Muldershof 2 Geleen Limburg 6162 JP",
    "addr:housenumber":"2",
    "addr:postcode":"6162 jp",
    "addr:street":"Muldershof",
    "iso:country":"NL",
    "sg:address":"Muldershof 2",
    "sg:city":"Geleen",
    "sg:orig_category":"Webdesign Bureaus",
    "sg:phone":"+31 6 21580238",
    "sg:postcode":"6162 JP",
    "sg:province":"Limburg",
    "sg:website":"http://www.dbl-webdesign.com",
    "wof:name":"Dbl",
    "wof:placetype":"venue"
},
  "geometry": {"coordinates":[5.8326430321,50.9792137146],"type":"Point"}
}