{
  "type": "Feature",
  "properties": {
    "addr:full":"J Abersonstr 34 Purmerend Noord-Holland 1447 HJ",
    "addr:housenumber":"34",
    "addr:postcode":"1447 hj",
    "iso:country":"NL",
    "sg:address":"J Abersonstr 34",
    "sg:city":"Purmerend",
    "sg:orig_category":"Administratie- En Boekhoudkantoren",
    "sg:phone":"+31 299 465 506",
    "sg:postcode":"1447 HJ",
    "sg:province":"Noord-Holland",
    "wof:name":"Lead Service",
    "wof:placetype":"venue"
},
  "geometry": {"coordinates":[4.959337,52.49128],"type":"Point"}
}