{
  "type": "Feature",
  "properties": {
    "iso:country":"NL",
    "sg:address":"Dorpsstr 344",
    "sg:city":"Assendelft",
    "sg:orig_category":"Kaas",
    "sg:phone":"+31 75 687 4288",
    "sg:postcode":"1566 BR",
    "sg:province":"North Holland",
    "wof:name":"Komart Bv",
    "wof:placetype":"venue"
},
  "geometry": {"coordinates":[4.7392520905,52.46509552],"type":"Point"}
}