{
  "type": "Feature",
  "properties": {
    "iso:country":"NL",
    "sg:address":"Ringvaart 36",
    "sg:city":"Schiedam",
    "sg:orig_category":"Adviesbureaus Gezondheidszorg",
    "sg:phone":"+31 10 471 2350",
    "sg:postcode":"3124 PB",
    "sg:province":"Zuid-Holland",
    "wof:name":"Pati\u00ebnten Belangenver Schiedam",
    "wof:placetype":"venue"
},
  "geometry": {"coordinates":[4.38632,51.938271],"type":"Point"}
}