{
  "type": "Feature",
  "properties": {
    "addr:full":"Julianaplein 7 Zetten California 6671 CA",
    "addr:housenumber":"7",
    "addr:postcode":"6671 ca",
    "addr:street":"Julianaplein",
    "iso:country":"NL",
    "sg:address":"Julianaplein 7",
    "sg:city":"Zetten",
    "sg:orig_category":"Kappers",
    "sg:phone":"+31 488 451 597",
    "sg:postcode":"6671 CA",
    "sg:province":"California",
    "wof:name":"Erica'S Haarmode",
    "wof:placetype":"venue"
},
  "geometry": {"coordinates":[-119.27020263670001,37.2718315125],"type":"Point"}
}