{
  "type": "Feature",
  "properties": {
    "addr:full":"Westersngl 19 Groningen Groningen 9718 CA",
    "addr:housenumber":"19",
    "addr:postcode":"9718 ca",
    "addr:street":"Westersngl",
    "iso:country":"NL",
    "sg:address":"Westersngl 19",
    "sg:city":"Groningen",
    "sg:orig_category":"Makelaars En Adviseurs Onroerende Goederen",
    "sg:phone":"+31 50 312 8133",
    "sg:postcode":"9718 CA",
    "sg:province":"Groningen",
    "sg:website":"http://www.mdbgroningen.nl",
    "wof:name":"Brink, De",
    "wof:placetype":"venue"
},
  "geometry": {"coordinates":[6.574715,53.217144],"type":"Point"}
}