{
  "type": "Feature",
  "properties": {
    "addr:full":"Parelvissersstr 325 Apeldoorn Gelderland 7323 BR",
    "addr:housenumber":"325",
    "addr:postcode":"7323 br",
    "addr:street":"Gelderland",
    "iso:country":"NL",
    "sg:address":"Parelvissersstr 325",
    "sg:city":"Apeldoorn",
    "sg:orig_category":"Fotografie Reclame En Mode",
    "sg:phone":"+31 55 367 2070",
    "sg:postcode":"7323 BR",
    "sg:province":"Gelderland",
    "wof:name":"Marchand, Arno",
    "wof:placetype":"venue"
},
  "geometry": {"coordinates":[5.981031,52.232796],"type":"Point"}
}