{
  "type": "Feature",
  "properties": {
    "addr:full":"B Boeyingastr 6 Amsterdam Noord-Holland 1025 ML",
    "addr:housenumber":"6",
    "addr:postcode":"1025 ml",
    "iso:country":"NL",
    "sg:address":"B Boeyingastr 6",
    "sg:city":"Amsterdam",
    "sg:orig_category":"Bijouterie?n - Fabrieken En Groothandel",
    "sg:phone":"+31 20 636 0908",
    "sg:postcode":"1025 ML",
    "sg:province":"Noord-Holland",
    "wof:name":"Tov",
    "wof:placetype":"venue"
},
  "geometry": {"coordinates":[4.9373,52.400349],"type":"Point"}
}