{
  "type": "Feature",
  "properties": {
    "addr:full":"Hoofdstraat 17 Terborg Gelderland 7061 CG",
    "addr:housenumber":"17",
    "addr:postcode":"7061 cg",
    "addr:street":"Hoofdstraat;Gelderland",
    "iso:country":"NL",
    "sg:address":"Hoofdstraat 17",
    "sg:city":"Terborg",
    "sg:orig_category":"Metaalwerken",
    "sg:phone":"+31 315 323 305",
    "sg:postcode":"7061 CG",
    "sg:province":"Gelderland",
    "wof:name":"De Keizer Van Terborg",
    "wof:placetype":"venue"
},
  "geometry": {"coordinates":[6.36088,51.919758],"type":"Point"}
}