{
  "type": "Feature",
  "properties": {
    "addr:full":"Dr Nolensln 143 Sittard Limburg 6136 GM",
    "addr:housenumber":"143",
    "addr:postcode":"6136 gm",
    "addr:street":"Sittard Limburg",
    "iso:country":"NL",
    "sg:address":"Dr Nolensln 143",
    "sg:city":"Sittard",
    "sg:orig_category":"Koolzuur - Fabrieken En Groothandel",
    "sg:phone":"+31 46 452 3512",
    "sg:postcode":"6136 GM",
    "sg:province":"Limburg",
    "wof:name":"Znkc Gas Groep Bv",
    "wof:placetype":"venue"
},
  "geometry": {"coordinates":[5.866939,51.019032],"type":"Point"}
}