{
  "type": "Feature",
  "properties": {
    "iso:country":"NL",
    "sg:address":"B F Suermanstr 15Bis",
    "sg:city":"Utrecht",
    "sg:orig_category":"Voetbalverenigingen",
    "sg:phone":"+31 30 271 3873",
    "sg:postcode":"3515 XK",
    "sg:province":"Utrecht",
    "wof:name":"Domstad Majella",
    "wof:placetype":"venue"
},
  "geometry": {"coordinates":[5.121409,52.103245],"type":"Point"}
}