{
  "type": "Feature",
  "properties": {
    "iso:country":"NL",
    "sg:address":"Wg L De Begraafp 3",
    "sg:city":"Arnhem",
    "sg:orig_category":"Begrafenisverzorging",
    "sg:phone":"+31 26 442 3102",
    "sg:postcode":"6815 AZ",
    "sg:province":"Gelderland",
    "sg:website":"http://www.kramerbv.nl",
    "wof:name":"Kramer Bv",
    "wof:placetype":"venue"
},
  "geometry": {"coordinates":[5.904585,51.985519],"type":"Point"}
}