{
  "type": "Feature",
  "properties": {
    "addr:full":"Anton Constandsestraat 26 Amsterdam Noord-Holland 1097 HX",
    "addr:housenumber":"26",
    "addr:postcode":"1097 hx",
    "addr:street":"Anton Constandsestraat",
    "iso:country":"NL",
    "sg:address":"Anton Constandsestraat 26",
    "sg:city":"Amsterdam",
    "sg:orig_category":"Juridische Dienstverlening",
    "sg:phone":"+31 20 665 5243",
    "sg:postcode":"1097 HX",
    "sg:province":"Noord-Holland",
    "wof:name":"Adviesbureau Arbeidsrecht Van Dorsten",
    "wof:placetype":"venue"
},
  "geometry": {"coordinates":[4.922032,52.347008],"type":"Point"}
}