{
  "type": "Feature",
  "properties": {
    "addr:full":"Godelindelaan 13 Loosdrecht North Holland 1231 VX",
    "addr:housenumber":"13",
    "addr:postcode":"1231 vx",
    "addr:street":"Godelindelaan",
    "iso:country":"NL",
    "sg:address":"Godelindelaan 13",
    "sg:city":"Loosdrecht",
    "sg:orig_category":"Goederenvervoer Over De Weg",
    "sg:phone":"+31 35 582 7382",
    "sg:postcode":"1231 VX",
    "sg:province":"North Holland",
    "wof:name":"Rob Kok Transport",
    "wof:placetype":"venue"
},
  "geometry": {"coordinates":[5.138523,52.197639],"type":"Point"}
}