{
  "type": "Feature",
  "properties": {
    "addr:full":"Amsteldijk Noord 49 Amstelveen Noord-Holland 1184 TD",
    "addr:housenumber":"49",
    "addr:postcode":"1184 td",
    "addr:street":"Amsteldijk Noord",
    "iso:country":"NL",
    "sg:address":"Amsteldijk Noord 49",
    "sg:city":"Amstelveen",
    "sg:orig_category":"Loodgieterswerk, Verwarming And Sanitaire Installaties",
    "sg:phone":"+31 20 496 1332",
    "sg:postcode":"1184 TD",
    "sg:province":"Noord-Holland",
    "wof:name":"Isolatie- En Klussenbedrijf Maut De Viss",
    "wof:placetype":"venue"
},
  "geometry": {"coordinates":[4.905185,52.305355],"type":"Point"}
}