{
  "type": "Feature",
  "properties": {
    "addr:full":"Broekhuisdijk 11 Gelselaar NL.08 7275 CB",
    "addr:housenumber":"11;nl.08",
    "addr:postcode":"7275 cb",
    "addr:street":"Broekhuisdijk",
    "iso:country":"NL",
    "sg:address":"Broekhuisdijk 11",
    "sg:city":"Gelselaar",
    "sg:orig_category":"Hout Gh",
    "sg:phone":"+31 545 481 580",
    "sg:postcode":"7275 CB",
    "sg:province":"NL.08",
    "wof:name":"J.A. Roesink",
    "wof:placetype":"venue"
},
  "geometry": {"coordinates":[6.513317,52.179852],"type":"Point"}
}