{
  "type": "Feature",
  "properties": {
    "iso:country":"NL",
    "sg:address":"Schaapbulterwg 6",
    "sg:city":"Meedhuizen",
    "sg:classifiers":[
        {
            "category":"Wholesale",
            "subcategory":"Motor Vehicles",
            "type":"Manufacturing & Wholesale Goods"
        }
    ],
    "sg:phone":"+31 596 533 598",
    "sg:postcode":"9937 TL",
    "sg:province":"Groningen",
    "sg:tags":[
        "scooter",
        "en"
    ],
    "wof:name":"Sieuw De Boer",
    "wof:placetype":"venue"
},
  "geometry": {"coordinates":[6.914871,53.282715],"type":"Point"}
}