{
  "type": "Feature",
  "properties": {
    "addr:full":"Sterkenburg 3 Veenendaal Utrecht 3904 JS",
    "addr:housenumber":"3",
    "addr:postcode":"3904 js",
    "addr:street":"Sterkenburg",
    "iso:country":"NL",
    "sg:address":"Sterkenburg 3",
    "sg:city":"Veenendaal",
    "sg:classifiers":[
        {
            "category":"Professional",
            "subcategory":"Accounting & Tax Preparation",
            "type":"Services"
        }
    ],
    "sg:phone":"+31 318 510 444",
    "sg:postcode":"3904 JS",
    "sg:province":"Utrecht",
    "sg:tags":[
        "accountant"
    ],
    "wof:name":"Accountantskantoor J. De Jongste Bv",
    "wof:placetype":"venue"
},
  "geometry": {"coordinates":[5.541363,52.009956],"type":"Point"}
}