{
  "type": "Feature",
  "properties": {
    "iso:country":"NL",
    "sg:address":"It Hof 14",
    "sg:city":"Goingaryp",
    "sg:orig_category":"Scholen Voor Basisonderwijs",
    "sg:phone":"+31 566 689 450",
    "sg:postcode":"8511 AG",
    "sg:province":"Provincie Friesland",
    "wof:name":"Openbare Basisschool Goingaryp",
    "wof:placetype":"venue"
},
  "geometry": {"coordinates":[5.77157,53.009926],"type":"Point"}
}