{
  "type": "Feature",
  "properties": {
    "iso:country":"NL",
    "sg:address":"Jan Van Arkelstraat 7",
    "sg:city":"Raalte",
    "sg:classifiers":[
        {
            "category":"Education",
            "subcategory":"Preschool",
            "type":"Public Place"
        }
    ],
    "sg:phone":"+31 572 362 990",
    "sg:postcode":"8101 EN",
    "sg:province":"Overijssel",
    "sg:tags":[
        "kleuteronderwijs",
        "basis-"
    ],
    "wof:name":"Kath Basisschool De Korenbloem",
    "wof:placetype":"venue"
},
  "geometry": {"coordinates":[6.266667,52.382904],"type":"Point"}
}