{
  "type": "Feature",
  "properties": {
    "addr:full":"Wallestein 10 Loenen A/D Vecht Utrecht 3632 WL",
    "addr:housenumber":"10;a / d",
    "addr:postcode":"3632 wl",
    "addr:street":"Wallestein;Vecht",
    "iso:country":"NL",
    "sg:address":"Wallestein 10",
    "sg:city":"Loenen A/D Vecht",
    "sg:orig_category":"Technische Studies And Onderzoek",
    "sg:phone":"+31 294 237 039",
    "sg:postcode":"3632 WL",
    "sg:province":"Utrecht",
    "wof:name":"Meer Logistiek",
    "wof:placetype":"venue"
},
  "geometry": {"coordinates":[5.028213,52.214424],"type":"Point"}
}