{
  "type": "Feature",
  "properties": {
    "addr:full":"Molenaar 10 Oud Beyerland South Holland 3262 DE",
    "addr:housenumber":"10",
    "addr:postcode":"3262 de",
    "addr:street":"Molenaar",
    "iso:country":"NL",
    "sg:address":"Molenaar 10",
    "sg:city":"Oud Beyerland",
    "sg:orig_category":"Cafetaria'S",
    "sg:phone":"+31 186 619 285",
    "sg:postcode":"3262 DE",
    "sg:province":"South Holland",
    "wof:name":"Effe Om",
    "wof:placetype":"venue"
},
  "geometry": {"coordinates":[4.395463,51.822605],"type":"Point"}
}