{
  "type": "Feature",
  "properties": {
    "iso:country":"NL",
    "sg:address":"Raadhuisplein 2",
    "sg:city":"Pijnacker",
    "sg:orig_category":"Verlichting And Huishoudartikelen",
    "sg:phone":"+31 15 369 7250",
    "sg:postcode":"2641 DR",
    "sg:province":"Zuid-Holland",
    "wof:name":"Mirror",
    "wof:placetype":"venue"
},
  "geometry": {"coordinates":[4.431593,52.018875],"type":"Point"}
}