{
  "type": "Feature",
  "properties": {
    "addr:full":"Hofmeestery 9 Huissen Gelderland 6852 NA",
    "addr:housenumber":"9",
    "addr:postcode":"6852 na",
    "addr:street":"Hofmeestery;Gelderland",
    "iso:country":"NL",
    "sg:address":"Hofmeestery 9",
    "sg:city":"Huissen",
    "sg:orig_category":"Kappers",
    "sg:phone":"+31 26 325 7578",
    "sg:postcode":"6852 NA",
    "sg:province":"Gelderland",
    "wof:name":"Aalten, Marcel Van",
    "wof:placetype":"venue"
},
  "geometry": {"coordinates":[5.928235054,51.9356651306],"type":"Point"}
}