{
  "type": "Feature",
  "properties": {
    "addr:full":"Markt 8 Hapert North Brabant 5527 EN",
    "addr:housenumber":"8",
    "addr:postcode":"5527 en",
    "addr:street":"Markt",
    "iso:country":"NL",
    "sg:address":"Markt 8",
    "sg:city":"Hapert",
    "sg:orig_category":"Dierenspeciaalzaken",
    "sg:phone":"+31 497 382 040",
    "sg:postcode":"5527 EN",
    "sg:province":"North Brabant",
    "wof:name":"Dierenspeciaalzaak Dierelantijn",
    "wof:placetype":"venue"
},
  "geometry": {"coordinates":[5.252126,51.36898],"type":"Point"}
}