{
  "type": "Feature",
  "properties": {
    "addr:full":"Brandwijksedijk 14 Brandwijk Zuid-Holland 2974 LB",
    "addr:housenumber":"14",
    "addr:postcode":"2974 lb",
    "addr:street":"Brandwijksedijk",
    "iso:country":"NL",
    "sg:address":"Brandwijksedijk 14",
    "sg:city":"Brandwijk",
    "sg:orig_category":"Autokeuringen",
    "sg:phone":"+31 184 642 393",
    "sg:postcode":"2974 LB",
    "sg:province":"Zuid-Holland",
    "wof:name":"Gebr. Muilwijk",
    "wof:placetype":"venue"
},
  "geometry": {"coordinates":[4.811746,51.889027],"type":"Point"}
}