{
  "type": "Feature",
  "properties": {
    "addr:full":"Beneden Oosterd 65/A Veendam Groningen 9641 JB",
    "addr:housenumber":"65 / a",
    "addr:postcode":"9641 jb",
    "addr:street":"Beneden Oosterd",
    "iso:country":"NL",
    "sg:address":"Beneden Oosterd 65/A",
    "sg:city":"Veendam",
    "sg:orig_category":"Verzekeringen - Verzekeringskantoren",
    "sg:phone":"+31 598 616 350",
    "sg:postcode":"9641 JB",
    "sg:province":"Groningen",
    "sg:website":"http://www.steenhuis.nl",
    "wof:name":"Steenhuis",
    "wof:placetype":"venue"
},
  "geometry": {"coordinates":[6.8831,53.106831],"type":"Point"}
}