{
  "type": "Feature",
  "properties": {
    "iso:country":"NL",
    "sg:address":"Rynzathe 4",
    "sg:city":"De Meern",
    "sg:orig_category":"Kantoor- En Bedrijfsmeubelen",
    "sg:phone":"+31 30 666 7020",
    "sg:postcode":"3454 PV",
    "sg:province":"Utrecht",
    "sg:website":"http://www.giroflex.nl",
    "wof:name":"Giroflex Ned Bv",
    "wof:placetype":"venue"
},
  "geometry": {"coordinates":[5.053003788,52.0714187622],"type":"Point"}
}