{
  "type": "Feature",
  "properties": {
    "addr:full":"Overnes 39 Amersfoort Utrecht 3813 NS",
    "addr:housenumber":"39",
    "addr:postcode":"3813 ns",
    "addr:street":"Overnes",
    "iso:country":"NL",
    "sg:address":"Overnes 39",
    "sg:city":"Amersfoort",
    "sg:orig_category":"Fotografie Reclame En Mode",
    "sg:phone":"+31 6 20953183",
    "sg:postcode":"3813 NS",
    "sg:province":"Utrecht",
    "wof:name":"Trendfilm",
    "wof:placetype":"venue"
},
  "geometry": {"coordinates":[5.391604,52.174675],"type":"Point"}
}