{
  "type": "Feature",
  "properties": {
    "addr:full":"Korte Hezeweg 11 Apeldoorn Gelderland 7335 BJ",
    "addr:housenumber":"11",
    "addr:postcode":"7335 bj",
    "addr:street":"Korte Hezeweg;Gelderland",
    "iso:country":"NL",
    "sg:address":"Korte Hezeweg 11",
    "sg:city":"Apeldoorn",
    "sg:orig_category":"Loodgieterswerk, Verwarming And Sanitaire Installaties",
    "sg:phone":"+31 55 533 7450",
    "sg:postcode":"7335 BJ",
    "sg:province":"Gelderland",
    "wof:name":"Firma Van Zuidam",
    "wof:placetype":"venue"
},
  "geometry": {"coordinates":[5.952336,52.202164],"type":"Point"}
}