{
  "type": "Feature",
  "properties": {
    "addr:full":"Noordstr 74 Terneuzen Zeeland 4531 GJ",
    "addr:housenumber":"74",
    "addr:postcode":"4531 gj",
    "addr:street":"Noordstr",
    "iso:country":"NL",
    "sg:address":"Noordstr 74",
    "sg:city":"Terneuzen",
    "sg:orig_category":"Juweliers",
    "sg:phone":"+31 115 649 950",
    "sg:postcode":"4531 GJ",
    "sg:province":"Zeeland",
    "wof:name":"Deijk, Van",
    "wof:placetype":"venue"
},
  "geometry": {"coordinates":[3.8265910149,51.3374214172],"type":"Point"}
}