{
  "type": "Feature",
  "properties": {
    "addr:full":"Eendrachtlaan 315 Utrecht Utrecht 3526 LB",
    "addr:housenumber":"315",
    "addr:postcode":"3526 lb",
    "addr:street":"Eendrachtlaan",
    "iso:country":"NL",
    "sg:address":"Eendrachtlaan 315",
    "sg:city":"Utrecht",
    "sg:orig_category":"Boekhouders",
    "sg:phone":"+31 30 283 6441",
    "sg:postcode":"3526 LB",
    "sg:province":"Utrecht",
    "wof:name":"Interpay Stichting Bevordering Chequever",
    "wof:placetype":"venue"
},
  "geometry": {"coordinates":[5.109333,52.061993],"type":"Point"}
}