{
  "type": "Feature",
  "properties": {
    "addr:full":"Sniederslaan 12 Bladel North Brabant 5531 EL",
    "addr:housenumber":"12",
    "addr:postcode":"5531 el",
    "addr:street":"Sniederslaan",
    "iso:country":"NL",
    "sg:address":"Sniederslaan 12",
    "sg:city":"Bladel",
    "sg:orig_category":"Schoenen",
    "sg:phone":"+31 497 360 003",
    "sg:postcode":"5531 EL",
    "sg:province":"North Brabant",
    "wof:name":"Massa Schoen & Mode",
    "wof:placetype":"venue"
},
  "geometry": {"coordinates":[5.217068,51.367107],"type":"Point"}
}