{
  "type": "Feature",
  "properties": {
    "addr:full":"Ariadnestr 21 Rotterdam Zuid-Holland 3054 WE",
    "addr:housenumber":"21",
    "addr:postcode":"3054 we",
    "addr:street":"Ariadnestr",
    "iso:country":"NL",
    "sg:address":"Ariadnestr 21",
    "sg:city":"Rotterdam",
    "sg:orig_category":"Administratie- En Boekhoudkantoren",
    "sg:phone":"+31 10 418 2948",
    "sg:postcode":"3054 WE",
    "sg:province":"Zuid-Holland",
    "wof:name":"A & F",
    "wof:placetype":"venue"
},
  "geometry": {"coordinates":[4.489691,51.965401],"type":"Point"}
}