{
  "type": "Feature",
  "properties": {
    "iso:country":"NL",
    "sg:address":"Schikswg 34",
    "sg:city":"Oosterwolde Gld",
    "sg:orig_category":"Loonbedrijven",
    "sg:phone":"+31 525 621 292",
    "sg:postcode":"8097 SG",
    "sg:province":"Gelderland",
    "wof:name":"Doornewaard",
    "wof:placetype":"venue"
},
  "geometry": {"coordinates":[5.880974,52.46619],"type":"Point"}
}