{
  "type": "Feature",
  "properties": {
    "addr:full":"Pyramideweg 3 Urk NL. 8321 CG",
    "addr:housenumber":"3",
    "addr:postcode":"8321 cg",
    "addr:street":"Pyramideweg;Nl.",
    "iso:country":"NL",
    "sg:address":"Pyramideweg 3",
    "sg:city":"Urk",
    "sg:orig_category":"Schoenen",
    "sg:phone":"+31 527 686 868",
    "sg:postcode":"8321 CG",
    "sg:province":"NL.",
    "wof:name":"Schoenhandel En Lederwaren M Visser",
    "wof:placetype":"venue"
},
  "geometry": {"coordinates":[5.607,52.662292],"type":"Point"}
}