{
  "type": "Feature",
  "properties": {
    "iso:country":"NL",
    "sg:address":"Pyramideweg 3",
    "sg:city":"Urk",
    "sg:orig_category":"Schoenen",
    "sg:phone":"+31 527 686 868",
    "sg:postcode":"8321 CG",
    "sg:province":"NL.",
    "wof:name":"Schoenhandel En Lederwaren M Visser",
    "wof:placetype":"venue"
},
  "geometry": {"coordinates":[5.607,52.662292],"type":"Point"}
}