{
  "type": "Feature",
  "properties": {
    "addr:full":"Dr Reilinghpln 3 Leerdam Zuid-Holland 4141 DA",
    "addr:housenumber":"3",
    "addr:postcode":"4141 da",
    "iso:country":"NL",
    "sg:address":"Dr Reilinghpln 3",
    "sg:city":"Leerdam",
    "sg:orig_category":"Bibliotheken En Leeszalen Openbare",
    "sg:phone":"+31 345 612 419",
    "sg:postcode":"4141 DA",
    "sg:province":"Zuid-Holland",
    "wof:name":"Openb Bibliotheek",
    "wof:placetype":"venue"
},
  "geometry": {"coordinates":[5.092859,51.893093],"type":"Point"}
}