{
  "type": "Feature",
  "properties": {
    "addr:full":"Oosterstr 1 Deventer Overijssel 7413 XV",
    "addr:housenumber":"1",
    "addr:postcode":"7413 xv",
    "addr:street":"Oosterstr",
    "iso:country":"NL",
    "sg:address":"Oosterstr 1",
    "sg:city":"Deventer",
    "sg:orig_category":"Nachtclubs",
    "sg:phone":"+31 570 630 795",
    "sg:postcode":"7413 XV",
    "sg:province":"Overijssel",
    "wof:name":"Isabelle",
    "wof:placetype":"venue"
},
  "geometry": {"coordinates":[6.159899,52.251034],"type":"Point"}
}