{
  "type": "Feature",
  "properties": {
    "addr:full":"Lynbaan 297 Zoetermeer Zuid-Holland 2728 AH",
    "addr:housenumber":"297",
    "addr:postcode":"2728 ah",
    "iso:country":"NL",
    "sg:address":"Lynbaan 297",
    "sg:city":"Zoetermeer",
    "sg:orig_category":"Kappers",
    "sg:phone":"+31 79 342 2031",
    "sg:postcode":"2728 AH",
    "sg:province":"Zuid-Holland",
    "wof:name":"Sandor",
    "wof:placetype":"venue"
},
  "geometry": {"coordinates":[4.52224,52.077229],"type":"Point"}
}