{
  "type": "Feature",
  "properties": {
    "addr:full":"Achterwerf 113 Almere Flevoland 1357 BP",
    "addr:housenumber":"113",
    "addr:postcode":"1357 bp",
    "addr:street":"Achterwerf;Flevoland",
    "iso:country":"NL",
    "sg:address":"Achterwerf 113",
    "sg:city":"Almere",
    "sg:orig_category":"Beveiliging",
    "sg:phone":"+31 36 535 5033",
    "sg:postcode":"1357 BP",
    "sg:province":"Flevoland",
    "wof:name":"Safe Care",
    "wof:placetype":"venue"
},
  "geometry": {"coordinates":[5.228354,52.336899],"type":"Point"}
}