{
  "type": "Feature",
  "properties": {
    "addr:full":"Noortheystraat 6 Voorschoten South Holland 2251 SW",
    "addr:housenumber":"6;2251",
    "addr:street":"Noortheystraat;Sw",
    "iso:country":"NL",
    "sg:address":"Noortheystraat 6",
    "sg:city":"Voorschoten",
    "sg:orig_category":"Kappers",
    "sg:phone":"+31 71 561 3771",
    "sg:postcode":"2251 SW",
    "sg:province":"South Holland",
    "wof:name":"Maison Riche",
    "wof:placetype":"venue"
},
  "geometry": {"coordinates":[4.453225,52.127666],"type":"Point"}
}