{
  "type": "Feature",
  "properties": {
    "iso:country":"NL",
    "sg:address":"Van Schendelstraat 24",
    "sg:city":"Dordrecht",
    "sg:classifiers":[
        {
            "category":"Education",
            "subcategory":"Preschool",
            "type":"Public Place"
        }
    ],
    "sg:phone":"+31 78 616 1358",
    "sg:postcode":"3319 RN",
    "sg:province":"South Holland",
    "sg:tags":[
        "kleuteronderwijs",
        "basis-"
    ],
    "wof:name":"Chr Basisschool Beatrix",
    "wof:placetype":"venue"
},
  "geometry": {"coordinates":[4.69913,51.794926],"type":"Point"}
}