{
  "type": "Feature",
  "properties": {
    "addr:full":"Zuiderkruisstr 26 Ymuiden North Holland 1973 XL",
    "addr:housenumber":"26",
    "addr:postcode":"1973 xl",
    "addr:street":"Zuiderkruisstr;North",
    "iso:country":"NL",
    "sg:address":"Zuiderkruisstr 26",
    "sg:city":"Ymuiden",
    "sg:classifiers":[
        {
            "category":"Personal",
            "subcategory":"Nail Salon",
            "type":"Services"
        }
    ],
    "sg:phone":"+31 255 518 968",
    "sg:postcode":"1973 XL",
    "sg:province":"North Holland",
    "sg:tags":[
        "pedicure"
    ],
    "wof:name":"Wetering, J M Van",
    "wof:placetype":"venue"
},
  "geometry": {"coordinates":[4.600681,52.453819],"type":"Point"}
}