{
  "type": "Feature",
  "properties": {
    "addr:full":"Min Cort Vd Lindenstr 17 Halfweg Nh Noord-Holland 1165 GR",
    "addr:housenumber":"17",
    "addr:postcode":"1165",
    "addr:street":"Min Cort Vd Lindenstr",
    "iso:country":"NL",
    "sg:address":"Min Cort Vd Lindenstr 17",
    "sg:city":"Halfweg Nh",
    "sg:orig_category":"Zuivelproducten",
    "sg:phone":"+31 20 497 4707",
    "sg:postcode":"1165 GR",
    "sg:province":"Noord-Holland",
    "wof:name":"Melkhandel A Kreike",
    "wof:placetype":"venue"
},
  "geometry": {"coordinates":[4.75446,52.383404],"type":"Point"}
}