{
  "type": "Feature",
  "properties": {
    "iso:country":"NL",
    "sg:address":"Kon Julianastr 48",
    "sg:city":"Twello",
    "sg:orig_category":"Zonweringen",
    "sg:phone":"+31 571 273 429",
    "sg:postcode":"7391 EC",
    "sg:province":"Gelderland",
    "wof:name":"Bosscher, Martie",
    "wof:placetype":"venue"
},
  "geometry": {"coordinates":[6.097406,52.238853],"type":"Point"}
}