{
  "type": "Feature",
  "properties": {
    "addr:full":"Industriewg 5 Roden Drenthe 9301 LM",
    "addr:housenumber":"5",
    "addr:postcode":"9301 lm",
    "addr:street":"Industriewg",
    "iso:country":"NL",
    "sg:address":"Industriewg 5",
    "sg:city":"Roden",
    "sg:classifiers":[
        {
            "category":"Wholesale",
            "subcategory":"Meat",
            "type":"Manufacturing & Wholesale Goods"
        }
    ],
    "sg:phone":"+31 50 501 3813",
    "sg:postcode":"9301 LM",
    "sg:province":"Drenthe",
    "sg:tags":[
        "regeltechniek",
        "en",
        "meet-"
    ],
    "wof:name":"Stiko Bv",
    "wof:placetype":"venue"
},
  "geometry": {"coordinates":[6.43644,53.14447],"type":"Point"}
}