{
  "type": "Feature",
  "properties": {
    "addr:full":"Dalwagen 27 Dodewaard Gelderland 6669 CA",
    "addr:housenumber":"27",
    "addr:postcode":"6669 ca",
    "addr:street":"Dalwagen;Gelderland",
    "iso:country":"NL",
    "sg:address":"Dalwagen 27",
    "sg:city":"Dodewaard",
    "sg:orig_category":"Verzekeringen",
    "sg:phone":"+31 488 443 002",
    "sg:postcode":"6669 CA",
    "sg:province":"Gelderland",
    "wof:name":"Assurantiekantoor Van Eldik",
    "wof:placetype":"venue"
},
  "geometry": {"coordinates":[-119.270203,37.271832],"type":"Point"}
}