{
  "type": "Feature",
  "properties": {
    "addr:full":"Hoofdstraat 8 Hoensbroek Limburg 6431 LC",
    "addr:housenumber":"8",
    "addr:postcode":"6431 lc",
    "addr:street":"Hoofdstraat",
    "iso:country":"NL",
    "sg:address":"Hoofdstraat 8",
    "sg:city":"Hoensbroek",
    "sg:orig_category":"Kappers",
    "sg:phone":"+31 45 522 7055",
    "sg:postcode":"6431 LC",
    "sg:province":"Limburg",
    "wof:name":"City Coiffure",
    "wof:placetype":"venue"
},
  "geometry": {"coordinates":[5.9266290665,50.9248695374],"type":"Point"}
}