{
  "type": "Feature",
  "properties": {
    "addr:full":"Alexanderstraat 3 Tilburg Noord-Brabant 5038 XW",
    "addr:housenumber":"3",
    "addr:postcode":"5038 xw",
    "addr:street":"Alexanderstraat",
    "iso:country":"NL",
    "sg:address":"Alexanderstraat 3",
    "sg:city":"Tilburg",
    "sg:orig_category":"Werving And Selectie Van Tijdelijk Personeel And Uitzendkantoren",
    "sg:phone":"+31 13 544 3248",
    "sg:postcode":"5038 XW",
    "sg:province":"Noord-Brabant",
    "wof:name":"Creyf'S Interim",
    "wof:placetype":"venue"
},
  "geometry": {"coordinates":[5.086397171,51.5555343628],"type":"Point"}
}