{
  "type": "Feature",
  "properties": {
    "addr:full":"Weg Acker 23 Heemskerk Noord-Holland 1965 TE",
    "addr:housenumber":"23",
    "addr:postcode":"1965 te",
    "addr:street":"Weg Acker",
    "iso:country":"NL",
    "sg:address":"Weg Acker 23",
    "sg:city":"Heemskerk",
    "sg:orig_category":"Boekhandels",
    "sg:phone":"+31 251 244 832",
    "sg:postcode":"1965 TE",
    "sg:province":"Noord-Holland",
    "wof:name":"Media Expresse",
    "wof:placetype":"venue"
},
  "geometry": {"coordinates":[4.665476,52.504612],"type":"Point"}
}