{
  "type": "Feature",
  "properties": {
    "addr:full":"Grasbroekerweg 18 Heerlen Limburg 6412 BE",
    "addr:housenumber":"18",
    "addr:postcode":"6412",
    "addr:street":"Grasbroekerweg",
    "iso:country":"NL",
    "sg:address":"Grasbroekerweg 18",
    "sg:city":"Heerlen",
    "sg:orig_category":"Kinderopvang Behalve Thuis",
    "sg:phone":"+31 45 572 7856",
    "sg:postcode":"6412 BE",
    "sg:province":"Limburg",
    "wof:name":"Kinderdagverblijf Alles Ki(D)Ts",
    "wof:placetype":"venue"
},
  "geometry": {"coordinates":[5.97628,50.893665],"type":"Point"}
}