{
  "type": "Feature",
  "properties": {
    "addr:full":"Giessenwg 46 Rotterdam Zuid-Holland 3044 AL",
    "addr:housenumber":"46",
    "addr:postcode":"3044 al",
    "addr:street":"Giessenwg",
    "iso:country":"NL",
    "sg:address":"Giessenwg 46",
    "sg:city":"Rotterdam",
    "sg:orig_category":"Wegenbouw",
    "sg:phone":"+31 10 208 3379",
    "sg:postcode":"3044 AL",
    "sg:province":"Zuid-Holland",
    "wof:name":"Langeveld Bv",
    "wof:placetype":"venue"
},
  "geometry": {"coordinates":[4.4193129539,51.9234771729],"type":"Point"}
}