{
  "type": "Feature",
  "properties": {
    "addr:full":"Walburgbuitensngl 14 Tiel Gelderland 4001 ML",
    "addr:housenumber":"14",
    "addr:postcode":"4001 ml",
    "addr:street":"Walburgbuitensngl;Gelderland",
    "iso:country":"NL",
    "sg:address":"Walburgbuitensngl 14",
    "sg:city":"Tiel",
    "sg:orig_category":"Handelscentra",
    "sg:phone":"+31 344 623 987",
    "sg:postcode":"4001 ML",
    "sg:province":"Gelderland",
    "wof:name":"Erna Vof",
    "wof:placetype":"venue"
},
  "geometry": {"coordinates":[5.430306,51.885265],"type":"Point"}
}