{
  "type": "Feature",
  "properties": {
    "addr:full":"Ridderhof 33 Alphen Aan Den Ryn Zuid-Holland 2402 EN",
    "addr:housenumber":"33",
    "addr:postcode":"2402 en",
    "addr:street":"Ridderhof;Aan Den Ryn",
    "iso:country":"NL",
    "sg:address":"Ridderhof 33",
    "sg:city":"Alphen Aan Den Ryn",
    "sg:orig_category":"Bloemen En Planten",
    "sg:phone":"+31 172 421 693",
    "sg:postcode":"2402 EN",
    "sg:province":"Zuid-Holland",
    "wof:name":"Madelon, De",
    "wof:placetype":"venue"
},
  "geometry": {"coordinates":[4.674503,52.145233],"type":"Point"}
}