{
  "type": "Feature",
  "properties": {
    "addr:full":"Industriewg 56 Hoogeveen Drenthe 7903 AK",
    "addr:housenumber":"56",
    "addr:postcode":"7903 ak",
    "addr:street":"Industriewg",
    "iso:country":"NL",
    "sg:address":"Industriewg 56",
    "sg:city":"Hoogeveen",
    "sg:orig_category":"Arbo- En Bedrijfsgezondheids- Diensten",
    "sg:phone":"+31 528 296 307",
    "sg:postcode":"7903 AK",
    "sg:province":"Drenthe",
    "wof:name":"Arbo Management Groep",
    "wof:placetype":"venue"
},
  "geometry": {"coordinates":[6.485794,52.731613],"type":"Point"}
}