{
  "type": "Feature",
  "properties": {
    "addr:full":"Hoofdstr 2 Zuidhorn Groningen 9801 BW",
    "addr:housenumber":"2",
    "addr:postcode":"9801 bw",
    "addr:street":"Hoofdstr",
    "iso:country":"NL",
    "sg:address":"Hoofdstr 2",
    "sg:city":"Zuidhorn",
    "sg:classifiers":[
        {
            "category":"Travel",
            "subcategory":"Hotels & Motels",
            "type":"Entertainment"
        }
    ],
    "sg:phone":"+31 594 505 353",
    "sg:postcode":"9801 BW",
    "sg:province":"Groningen",
    "wof:name":"In 'T Holt",
    "wof:placetype":"venue"
},
  "geometry": {"coordinates":[6.410739,53.243145],"type":"Point"}
}