{
  "type": "Feature",
  "properties": {
    "addr:full":"T Zand 32 Utrecht Utrecht 3544 NC",
    "addr:housenumber":"32",
    "addr:postcode":"3544 nc",
    "addr:street":"T Zand",
    "iso:country":"NL",
    "sg:address":"T Zand 32",
    "sg:city":"Utrecht",
    "sg:orig_category":"Hypotheken And Hypotheekbanken",
    "sg:phone":"+31 30 666 4633",
    "sg:postcode":"3544 NC",
    "sg:province":"Utrecht",
    "wof:name":"Fa Ad Stols Makelaardij",
    "wof:placetype":"venue"
},
  "geometry": {"coordinates":[5.043297,52.08979],"type":"Point"}
}