{
  "type": "Feature",
  "properties": {
    "addr:full":"De Grutto 4 Almelo NL.08 7609 DA",
    "addr:housenumber":"4;nl.08",
    "addr:postcode":"7609 da",
    "addr:street":"De Grutto",
    "iso:country":"NL",
    "sg:address":"De Grutto 4",
    "sg:city":"Almelo",
    "sg:orig_category":"Kaas",
    "sg:phone":"+31 546 826 548",
    "sg:postcode":"7609 DA",
    "sg:province":"NL.08",
    "wof:name":"Kaaswaag, De",
    "wof:placetype":"venue"
},
  "geometry": {"coordinates":[6.6354370117,52.337600708],"type":"Point"}
}