{
  "type": "Feature",
  "properties": {
    "addr:full":"Peppelkade 60 Houten Utrecht 3992 AK",
    "addr:housenumber":"60",
    "addr:postcode":"3992 ak",
    "addr:street":"Peppelkade",
    "iso:country":"NL",
    "sg:address":"Peppelkade 60",
    "sg:city":"Houten",
    "sg:orig_category":"Bedrijfsinventaris Gh",
    "sg:phone":"+31 30 638 0696",
    "sg:postcode":"3992 AK",
    "sg:province":"Utrecht",
    "wof:name":"Gti Koudetechniek Bv Vestiging Houten",
    "wof:placetype":"venue"
},
  "geometry": {"coordinates":[5.144163,52.039631],"type":"Point"}
}