{
  "type": "Feature",
  "properties": {
    "addr:full":"Van Maerlantpark 36 Capelle A/D Ijssel South Holland 2902 BT",
    "addr:housenumber":"36;a / d",
    "addr:postcode":"2902 bt",
    "addr:street":"Van Maerlantpark;Ijssel South",
    "iso:country":"NL",
    "sg:address":"Van Maerlantpark 36",
    "sg:city":"Capelle A/D Ijssel",
    "sg:orig_category":"Huishoudapparatuur, Televisies And Radio'S",
    "sg:phone":"+31 10 450 7986",
    "sg:postcode":"2902 BT",
    "sg:province":"South Holland",
    "wof:name":"Radio Swaep Bv",
    "wof:placetype":"venue"
},
  "geometry": {"coordinates":[4.577351,51.924095],"type":"Point"}
}