{
  "type": "Feature",
  "properties": {
    "addr:full":"Groenstr 27A Prinsenbeek Noord-Brabant 4841 BA",
    "addr:housenumber":"27a",
    "addr:postcode":"4841 ba",
    "addr:street":"Groenstr",
    "iso:country":"NL",
    "sg:address":"Groenstr 27A",
    "sg:city":"Prinsenbeek",
    "sg:orig_category":"Adviesbureaus Bedrijfsorganisatie",
    "sg:phone":"+31 76 543 9680",
    "sg:postcode":"4841 BA",
    "sg:province":"Noord-Brabant",
    "wof:name":"Emc",
    "wof:placetype":"venue"
},
  "geometry": {"coordinates":[4.716152,51.598251],"type":"Point"}
}