{
  "type": "Feature",
  "properties": {
    "iso:country":"NL",
    "sg:address":"Kinderbalk 35",
    "sg:city":"Hoorn Nh",
    "sg:orig_category":"Fotoreportages",
    "sg:phone":"+31 229 234 830",
    "sg:postcode":"1628 MD",
    "sg:province":"North Holland",
    "sg:website":"http://www.rl-videoprodukties-tk",
    "wof:name":"Rl",
    "wof:placetype":"venue"
},
  "geometry": {"coordinates":[5.092461,52.653885],"type":"Point"}
}