{
  "type": "Feature",
  "properties": {
    "addr:full":"Weverstr 56 Den Burg Noord-Holland 1791 AE",
    "addr:housenumber":"56",
    "addr:postcode":"1791 ae",
    "addr:street":"Weverstr",
    "iso:country":"NL",
    "sg:address":"Weverstr 56",
    "sg:city":"Den Burg",
    "sg:orig_category":"Administratie- En Boekhoudkantoren",
    "sg:phone":"+31 222 312 888",
    "sg:postcode":"1791 AE",
    "sg:province":"Noord-Holland",
    "wof:name":"Koorn Bv",
    "wof:placetype":"venue"
},
  "geometry": {"coordinates":[-94.071686,34.232082],"type":"Point"}
}