{
  "type": "Feature",
  "properties": {
    "iso:country":"NL",
    "sg:address":"Glinthuisweg 15",
    "sg:city":"Hasselt",
    "sg:orig_category":"Verzekeringen",
    "sg:phone":"+31 38 477 1959",
    "sg:postcode":"8061 PN",
    "sg:province":"NL.08",
    "wof:name":"Auberge Genne",
    "wof:placetype":"venue"
},
  "geometry": {"coordinates":[6.117795,52.562325],"type":"Point"}
}