{
  "type": "Feature",
  "properties": {
    "iso:country":"NL",
    "sg:address":"Koninginnewg 1B",
    "sg:city":"Boskoop",
    "sg:orig_category":"Kappers",
    "sg:phone":"+31 172 213 187",
    "sg:postcode":"2771 DN",
    "sg:province":"Zuid-Holland",
    "wof:name":"Snel, M",
    "wof:placetype":"venue"
},
  "geometry": {"coordinates":[4.658291,52.074116],"type":"Point"}
}