{
  "type": "Feature",
  "properties": {
    "addr:full":"Wielakkerstr 10B Arnhem Gelderland 6811 DB",
    "addr:housenumber":"10b",
    "addr:postcode":"6811 db",
    "addr:street":"Wielakkerstr",
    "iso:country":"NL",
    "sg:address":"Wielakkerstr 10B",
    "sg:city":"Arnhem",
    "sg:orig_category":"Goudsmeden En Zilversmeden",
    "sg:phone":"+31 26 351 4980",
    "sg:postcode":"6811 DB",
    "sg:province":"Gelderland",
    "wof:name":"Atelier 12 Hoven",
    "wof:placetype":"venue"
},
  "geometry": {"coordinates":[5.908038,51.981461],"type":"Point"}
}