{
  "type": "Feature",
  "properties": {
    "iso:country":"NL",
    "sg:address":"Singel 54",
    "sg:city":"Amsterdam",
    "sg:orig_category":"Verenigingen En Stichtingen",
    "sg:phone":"+31 20 625 3111",
    "sg:postcode":"1015 AB",
    "sg:province":"Noord-Holland",
    "wof:name":"Scip",
    "wof:placetype":"venue"
},
  "geometry": {"coordinates":[4.892375,52.377857],"type":"Point"}
}