{
  "type": "Feature",
  "properties": {
    "addr:full":"Rietgors 47 Mynsheerenland Zuid-Holland 3271 XC",
    "addr:housenumber":"47",
    "addr:postcode":"3271 xc",
    "addr:street":"Rietgors",
    "iso:country":"NL",
    "sg:address":"Rietgors 47",
    "sg:city":"Mynsheerenland",
    "sg:orig_category":"Onroerende Goederen",
    "sg:phone":"+31 186 603 077",
    "sg:postcode":"3271 XC",
    "sg:province":"Zuid-Holland",
    "wof:name":"Intermaas Bv",
    "wof:placetype":"venue"
},
  "geometry": {"coordinates":[4.478061,51.795898],"type":"Point"}
}