{
  "type": "Feature",
  "properties": {
    "addr:full":"Krayenhoffstraat 10 Amsterdam Noord-Holland 1018 RK",
    "addr:housenumber":"10",
    "addr:postcode":"1018 rk",
    "addr:street":"Krayenhoffstraat",
    "iso:country":"NL",
    "sg:address":"Krayenhoffstraat 10",
    "sg:city":"Amsterdam",
    "sg:classifiers":[
        {
            "category":"Education",
            "subcategory":"Preschool",
            "type":"Public Place"
        }
    ],
    "sg:phone":"+31 20 639 1045",
    "sg:postcode":"1018 RK",
    "sg:province":"Noord-Holland",
    "sg:tags":[
        "kleuteronderwijs",
        "basis-"
    ],
    "wof:name":"Basisschool Oostelijke Eilanden",
    "wof:placetype":"venue"
},
  "geometry": {"coordinates":[4.928716,52.368481],"type":"Point"}
}