{
  "type": "Feature",
  "properties": {
    "addr:full":"Looierslaan 93 Voorburg South Holland 2272 BJ",
    "addr:housenumber":"93",
    "addr:postcode":"2272 bj",
    "addr:street":"Looierslaan",
    "iso:country":"NL",
    "sg:address":"Looierslaan 93",
    "sg:city":"Voorburg",
    "sg:orig_category":"Fitnesscentra",
    "sg:phone":"+31 70 386 3806",
    "sg:postcode":"2272 BJ",
    "sg:province":"South Holland",
    "wof:name":"Sportstudio The Art",
    "wof:placetype":"venue"
},
  "geometry": {"coordinates":[4.386431,52.082878],"type":"Point"}
}