{
  "type": "Feature",
  "properties": {
    "addr:full":"Noordeinde 86 Aarlanderveen Zuid-Holland 2445 XG",
    "addr:housenumber":"86",
    "addr:postcode":"2445 xg",
    "addr:street":"Noordeinde",
    "iso:country":"NL",
    "sg:address":"Noordeinde 86",
    "sg:city":"Aarlanderveen",
    "sg:orig_category":"Hoger Onderwijs",
    "sg:phone":"+31 172 574 390",
    "sg:postcode":"2445 XG",
    "sg:province":"Zuid-Holland",
    "wof:name":"E.R. Nederpeld",
    "wof:placetype":"venue"
},
  "geometry": {"coordinates":[4.726705,52.144169],"type":"Point"}
}