{
  "type": "Feature",
  "properties": {
    "iso:country":"NL",
    "sg:address":"Harderwykerwg 128C",
    "sg:city":"Ermelo",
    "sg:orig_category":"Parketvloeren",
    "sg:phone":"+31 341 410 202",
    "sg:postcode":"3852 AG",
    "sg:province":"Gelderland",
    "sg:website":"http://www.tenkaten.nl",
    "wof:name":"Katen, Gebr Ten",
    "wof:placetype":"venue"
},
  "geometry": {"coordinates":[5.626421,52.316273],"type":"Point"}
}