{
  "type": "Feature",
  "properties": {
    "addr:full":"Hamsestraat 62 Opheusden Gelderland 4043 LJ",
    "addr:housenumber":"62;lj",
    "addr:postcode":"4043",
    "addr:street":"Hamsestraat;Gelderland",
    "iso:country":"NL",
    "sg:address":"Hamsestraat 62",
    "sg:city":"Opheusden",
    "sg:orig_category":"Film-, Tv- And Videoproductie",
    "sg:phone":"+31 6 51333424",
    "sg:postcode":"4043 LJ",
    "sg:province":"Gelderland",
    "wof:name":"Refresh",
    "wof:placetype":"venue"
},
  "geometry": {"coordinates":[5.620516,51.932262],"type":"Point"}
}