{
  "type": "Feature",
  "properties": {
    "addr:full":"S-Gravenbroekseweg 34 Reeuwijk Zuid-Holland 2811 GE",
    "addr:housenumber":"34",
    "addr:postcode":"2811",
    "addr:street":"S-Gravenbroekseweg",
    "iso:country":"NL",
    "sg:address":"S-Gravenbroekseweg 34",
    "sg:city":"Reeuwijk",
    "sg:classifiers":[
        {
            "category":"Professional",
            "subcategory":"Accounting & Tax Preparation",
            "type":"Services"
        }
    ],
    "sg:phone":"+31 182 394 101",
    "sg:postcode":"2811 GE",
    "sg:province":"Zuid-Holland",
    "sg:tags":[
        "accountant"
    ],
    "wof:name":"Accountantskantoor Arenthals En Partners",
    "wof:placetype":"venue"
},
  "geometry": {"coordinates":[4.726234,52.042068],"type":"Point"}
}