{
  "type": "Feature",
  "properties": {
    "addr:full":"Kennemerln 53 Ymuiden Noord-Holland 1972 EH",
    "addr:housenumber":"53",
    "addr:postcode":"1972 eh",
    "addr:street":"Kennemerln",
    "iso:country":"NL",
    "sg:address":"Kennemerln 53",
    "sg:city":"Ymuiden",
    "sg:orig_category":"Honden- En Kattentrimsalons",
    "sg:phone":"+31 255 511 936",
    "sg:postcode":"1972 EH",
    "sg:province":"Noord-Holland",
    "sg:website":"HTTP://www.deplukschuur.nl",
    "wof:name":"Plukschuur",
    "wof:placetype":"venue"
},
  "geometry": {"coordinates":[4.60581,52.460751],"type":"Point"}
}