{
  "type": "Feature",
  "properties": {
    "addr:full":"Prins Mauritsstraat 2 Baambrugge Utrecht 1396 JZ",
    "addr:housenumber":"2",
    "addr:postcode":"1396 jz",
    "addr:street":"Prins Mauritsstraat",
    "iso:country":"NL",
    "sg:address":"Prins Mauritsstraat 2",
    "sg:city":"Baambrugge",
    "sg:orig_category":"Artsen And Specialisten",
    "sg:phone":"+31 294 293 518",
    "sg:postcode":"1396 JZ",
    "sg:province":"Utrecht",
    "wof:name":"Huisartspraktijk P.G.H. Janssen",
    "wof:placetype":"venue"
},
  "geometry": {"coordinates":[4.988797,52.245777],"type":"Point"}
}