{
  "type": "Feature",
  "properties": {
    "addr:full":"Bluijssens Broekdijk 20 Asten Noord-Brabant 5721 RN",
    "addr:housenumber":"20",
    "addr:postcode":"5721 rn",
    "addr:street":"Bluijssens Broekdijk",
    "iso:country":"NL",
    "sg:address":"Bluijssens Broekdijk 20",
    "sg:city":"Asten",
    "sg:orig_category":"Levende Dieren Gh",
    "sg:phone":"+31 493 560 331",
    "sg:postcode":"5721 RN",
    "sg:province":"Noord-Brabant",
    "wof:name":"Van Zeeland",
    "wof:placetype":"venue"
},
  "geometry": {"coordinates":[5.788536,51.384674],"type":"Point"}
}