{
  "type": "Feature",
  "properties": {
    "iso:country":"NL",
    "sg:address":"Wordragensestraat 8",
    "sg:city":"Ammerzoden",
    "sg:orig_category":"Film-, Tv- And Videoproductie",
    "sg:phone":"+31 73 599 4644",
    "sg:postcode":"5324 JM",
    "sg:province":"Gelderland",
    "wof:name":"A. Fliervoet Film- En T.V. Produkties",
    "wof:placetype":"venue"
},
  "geometry": {"coordinates":[5.228194,51.756821],"type":"Point"}
}