{
  "type": "Feature",
  "properties": {
    "addr:full":"Mollenberg 15 Breda Noord-Brabant 4816 HC",
    "addr:housenumber":"15",
    "addr:postcode":"4816 hc",
    "addr:street":"Mollenberg",
    "iso:country":"NL",
    "sg:address":"Mollenberg 15",
    "sg:city":"Breda",
    "sg:orig_category":"Koeriersdiensten",
    "sg:phone":"+31 6 52090145",
    "sg:postcode":"4816 HC",
    "sg:province":"Noord-Brabant",
    "wof:name":"Ridder, De",
    "wof:placetype":"venue"
},
  "geometry": {"coordinates":[4.79895,51.600365],"type":"Point"}
}