{
  "type": "Feature",
  "properties": {
    "iso:country":"NL",
    "sg:address":"Suderseleane 29",
    "sg:city":"Workum",
    "sg:orig_category":"Kampeerterreinen",
    "sg:phone":"+31 515 541 443",
    "sg:postcode":"8711 GX",
    "sg:province":"Provincie Friesland",
    "wof:name":"Paviljoen It Soal",
    "wof:placetype":"venue"
},
  "geometry": {"coordinates":[5.4153118134,52.9698486328],"type":"Point"}
}