{
  "type": "Feature",
  "properties": {
    "iso:country":"NL",
    "sg:address":"Wilhelminaln 34",
    "sg:city":"Giessenburg",
    "sg:classifiers":[
        {
            "category":"Retail",
            "subcategory":"Storage",
            "type":"Services"
        }
    ],
    "sg:phone":"+31 184 651 597",
    "sg:postcode":"3381 BP",
    "sg:province":"South Holland",
    "sg:tags":[
        "op-",
        "en",
        "overslagbedrijven"
    ],
    "wof:name":"Muilwijk",
    "wof:placetype":"venue"
},
  "geometry": {"coordinates":[4.888878,51.849262],"type":"Point"}
}