{
  "type": "Feature",
  "properties": {
    "addr:full":"Benedendorpsweg 163 Oosterbeek Gelderland 6862 WH",
    "addr:housenumber":"163",
    "addr:postcode":"6862 wh",
    "addr:street":"Benedendorpsweg;Gelderland",
    "iso:country":"NL",
    "sg:address":"Benedendorpsweg 163",
    "sg:city":"Oosterbeek",
    "sg:classifiers":[
        {
            "category":"Food & Beverages",
            "subcategory":"Fruits & Vegetables",
            "type":"Retail Goods"
        }
    ],
    "sg:phone":"+31 26 333 4293",
    "sg:postcode":"6862 WH",
    "sg:province":"Gelderland",
    "sg:tags":[
        "groenten"
    ],
    "wof:name":"Vof H.T. Peters En Zoon",
    "wof:placetype":"venue"
},
  "geometry": {"coordinates":[5.835793,51.978912],"type":"Point"}
}