{
  "type": "Feature",
  "properties": {
    "addr:full":"Sperwer 52 Ommen Overijssel 7731 KB",
    "addr:housenumber":"52",
    "addr:postcode":"7731 kb",
    "addr:street":"Sperwer",
    "iso:country":"NL",
    "sg:address":"Sperwer 52",
    "sg:city":"Ommen",
    "sg:orig_category":"Schilders",
    "sg:phone":"+31 529 451 526",
    "sg:postcode":"7731 KB",
    "sg:province":"Overijssel",
    "wof:name":"Deen Vof",
    "wof:placetype":"venue"
},
  "geometry": {"coordinates":[6.412422,52.52227],"type":"Point"}
}