{
  "type": "Feature",
  "properties": {
    "addr:full":"Ettenstraat 5 Beilen Provincie Drenthe 9411 KT",
    "addr:housenumber":"5",
    "addr:postcode":"9411 kt",
    "addr:street":"Ettenstraat;Provincie Drenthe",
    "iso:country":"NL",
    "sg:address":"Ettenstraat 5",
    "sg:city":"Beilen",
    "sg:orig_category":"Politie",
    "sg:phone":"+31 900 8844",
    "sg:postcode":"9411 KT",
    "sg:province":"Provincie Drenthe",
    "wof:name":"Politie Midden Drenthe",
    "wof:placetype":"venue"
},
  "geometry": {"coordinates":[6.514339,52.859955],"type":"Point"}
}