{
  "type": "Feature",
  "properties": {
    "addr:full":"Europawg 4 Zoetermeer Zuid-Holland 2711 AH",
    "addr:housenumber":"4",
    "addr:postcode":"2711 ah",
    "addr:street":"Europawg",
    "iso:country":"NL",
    "sg:address":"Europawg 4",
    "sg:city":"Zoetermeer",
    "sg:orig_category":"Ministeries En Overheidsinstellingen",
    "sg:phone":"+31 79 323 3413",
    "sg:postcode":"2711 AH",
    "sg:province":"Zuid-Holland",
    "sg:website":"http://www.minocw.nl",
    "wof:name":"Ministerie Van Onderwijs Cultuur En Wetenschappen",
    "wof:placetype":"venue"
},
  "geometry": {"coordinates":[4.489664,52.063419],"type":"Point"}
}