{
  "type": "Feature",
  "properties": {
    "addr:full":"T B Huurmanlaan 9 Bussum Noord-Holland 1403 SL",
    "addr:housenumber":"9",
    "addr:street":"Huurmanlaan",
    "iso:country":"NL",
    "sg:address":"T B Huurmanlaan 9",
    "sg:city":"Bussum",
    "sg:classifiers":[
        {
            "category":"Food & Beverages",
            "subcategory":"Fruits & Vegetables",
            "type":"Retail Goods"
        }
    ],
    "sg:phone":"+31 35 691 5159",
    "sg:postcode":"1403 SL",
    "sg:province":"Noord-Holland",
    "sg:tags":[
        "groenten"
    ],
    "wof:name":"Sjaak Banaan",
    "wof:placetype":"venue"
},
  "geometry": {"coordinates":[5.174214,52.267273],"type":"Point"}
}