{
  "type": "Feature",
  "properties": {
    "addr:full":"Oudkerkhof 12 Utrecht Utrecht 3512 GK",
    "addr:housenumber":"12",
    "addr:postcode":"3512 gk",
    "addr:street":"Oudkerkhof",
    "iso:country":"NL",
    "sg:address":"Oudkerkhof 12",
    "sg:city":"Utrecht",
    "sg:orig_category":"Damesmodezaken",
    "sg:phone":"+31 30 231 5539",
    "sg:postcode":"3512 GK",
    "sg:province":"Utrecht",
    "wof:name":"Bongers Fashion Bv",
    "wof:placetype":"venue"
},
  "geometry": {"coordinates":[5.120833,52.091854],"type":"Point"}
}