{
  "type": "Feature",
  "properties": {
    "iso:country":"NL",
    "sg:address":"Jos Van Aalderenlaan 9",
    "sg:city":"Hoogeveen",
    "sg:orig_category":"Fotostudio'S And Fotografen",
    "sg:phone":"+31 528 235 833",
    "sg:postcode":"7908 HC",
    "sg:province":"Provincie Drenthe",
    "wof:name":"Gerrit Boer Fotografie",
    "wof:placetype":"venue"
},
  "geometry": {"coordinates":[6.458733,52.7169],"type":"Point"}
}