{
  "type": "Feature",
  "properties": {
    "addr:full":"Bloemkwekersstraat 78 Rotterdam Zuid-Holland 3014 PE",
    "addr:housenumber":"78",
    "addr:postcode":"3014 pe",
    "addr:street":"Bloemkwekersstraat",
    "iso:country":"NL",
    "sg:address":"Bloemkwekersstraat 78",
    "sg:city":"Rotterdam",
    "sg:orig_category":"Werving And Selectie Van Tijdelijk Personeel And Uitzendkantoren",
    "sg:phone":"+31 10 436 4701",
    "sg:postcode":"3014 PE",
    "sg:province":"Zuid-Holland",
    "wof:name":"Cub Bv",
    "wof:placetype":"venue"
},
  "geometry": {"coordinates":[4.468682766,51.9163703918],"type":"Point"}
}