{
  "type": "Feature",
  "properties": {
    "addr:full":"Kollergang 9 Eerbeek Gelderland 6961 LZ",
    "addr:housenumber":"9",
    "addr:postcode":"6961 lz",
    "addr:street":"Kollergang;Gelderland",
    "iso:country":"NL",
    "sg:address":"Kollergang 9",
    "sg:city":"Eerbeek",
    "sg:orig_category":"Fotografische And Optische Artikelen Gh",
    "sg:phone":"+31 313 677 677",
    "sg:postcode":"6961 LZ",
    "sg:province":"Gelderland",
    "wof:name":"Procornea Nederland Bv",
    "wof:placetype":"venue"
},
  "geometry": {"coordinates":[6.083103,52.099689],"type":"Point"}
}