{
  "type": "Feature",
  "properties": {
    "addr:full":"Houtzaagmolen 108 Ridderkerk South Holland 2986 GE",
    "addr:housenumber":"108",
    "addr:postcode":"2986",
    "addr:street":"Houtzaagmolen",
    "iso:country":"NL",
    "sg:address":"Houtzaagmolen 108",
    "sg:city":"Ridderkerk",
    "sg:orig_category":"Werving En Selectie",
    "sg:phone":"+31 180 434 575",
    "sg:postcode":"2986 GE",
    "sg:province":"South Holland",
    "wof:name":"Ace Partner",
    "wof:placetype":"venue"
},
  "geometry": {"coordinates":[4.6182107925,51.8661384583],"type":"Point"}
}