{
  "type": "Feature",
  "properties": {
    "addr:full":"Dorpsdk 12 Wissenkerke Zeeland 4491 EC",
    "addr:housenumber":"12",
    "addr:postcode":"4491 ec",
    "addr:street":"Dorpsdk",
    "iso:country":"NL",
    "sg:address":"Dorpsdk 12",
    "sg:city":"Wissenkerke",
    "sg:orig_category":"Vakantieverblijven",
    "sg:phone":"+31 113 376 033",
    "sg:postcode":"4491 EC",
    "sg:province":"Zeeland",
    "sg:website":"http://www.recreatiezeeland.nl/vlasschure",
    "wof:name":"Countryhouse De Vlasschure",
    "wof:placetype":"venue"
},
  "geometry": {"coordinates":[3.749919,51.587261],"type":"Point"}
}