{
  "type": "Feature",
  "properties": {
    "addr:full":"Past Nicolaas Creftenstr 19 Meerssen Limburg 6231 HH",
    "addr:housenumber":"19",
    "addr:postcode":"6231 hh",
    "addr:street":"Creftenstr",
    "iso:country":"NL",
    "sg:address":"Past Nicolaas Creftenstr 19",
    "sg:city":"Meerssen",
    "sg:orig_category":"Politie",
    "sg:phone":"+31 900 8844",
    "sg:postcode":"6231 HH",
    "sg:province":"Limburg",
    "wof:name":"Politie Limburg Zuid Basiseenheid Meerssen",
    "wof:placetype":"venue"
},
  "geometry": {"coordinates":[5.751971,50.887493],"type":"Point"}
}