{
  "type": "Feature",
  "properties": {
    "addr:full":"Westerstraat 34 Enkhuizen Noord-Holland 1601 AK",
    "addr:housenumber":"34",
    "addr:postcode":"1601 ak",
    "addr:street":"Westerstraat",
    "iso:country":"NL",
    "sg:address":"Westerstraat 34",
    "sg:city":"Enkhuizen",
    "sg:classifiers":[
        {
            "category":"Shopping",
            "subcategory":"Gifts & Souvenirs",
            "type":"Retail Goods"
        }
    ],
    "sg:phone":"+31 228 322 484",
    "sg:postcode":"1601 AK",
    "sg:province":"Noord-Holland",
    "sg:tags":[
        "geschenken"
    ],
    "wof:name":"Souvenir-Giftshop Den Vergulden Sleutel",
    "wof:placetype":"venue"
},
  "geometry": {"coordinates":[5.293295,52.704536],"type":"Point"}
}