{
  "type": "Feature",
  "properties": {
    "iso:country":"NL",
    "sg:address":"Coopsstr 16",
    "sg:city":"Doetinchem",
    "sg:orig_category":"Kermisexploitatie",
    "sg:phone":"+31 6 54298816",
    "sg:postcode":"7009 KJ",
    "sg:province":"Gelderland",
    "wof:name":"Break Freee Fun Company",
    "wof:placetype":"venue"
},
  "geometry": {"coordinates":[6.299981,51.976376],"type":"Point"}
}