{
  "type": "Feature",
  "properties": {
    "addr:full":"Amperewg 19 Delft Zuid-Holland 2627 BG",
    "addr:housenumber":"19",
    "addr:postcode":"2627",
    "addr:street":"Amperewg",
    "iso:country":"NL",
    "sg:address":"Amperewg 19",
    "sg:city":"Delft",
    "sg:orig_category":"Meubelmakerijen",
    "sg:phone":"+31 15 262 2478",
    "sg:postcode":"2627 BG",
    "sg:province":"Zuid-Holland",
    "wof:name":"Spazio",
    "wof:placetype":"venue"
},
  "geometry": {"coordinates":[-95.0895,43.990925],"type":"Point"}
}