{
  "type": "Feature",
  "properties": {
    "addr:full":"Groen Van Prinstererstr 32 Nijverdal NL.08 7442 MV",
    "addr:housenumber":"32;nl.08",
    "addr:postcode":"7442 mv",
    "addr:street":"Groen Van Prinstererstr",
    "iso:country":"NL",
    "sg:address":"Groen Van Prinstererstr 32",
    "sg:city":"Nijverdal",
    "sg:orig_category":"Kappers",
    "sg:phone":"+31 548 615 827",
    "sg:postcode":"7442 MV",
    "sg:province":"NL.08",
    "wof:name":"Kapsalon Simone Audrey",
    "wof:placetype":"venue"
},
  "geometry": {"coordinates":[6.4585747719,52.3642311096],"type":"Point"}
}