{
  "type": "Feature",
  "properties": {
    "addr:full":"Volkspln 37 Maastricht Limburg 6214 AN",
    "addr:housenumber":"37",
    "addr:postcode":"6214 an",
    "addr:street":"Volkspln",
    "iso:country":"NL",
    "sg:address":"Volkspln 37",
    "sg:city":"Maastricht",
    "sg:orig_category":"Verf En Lak",
    "sg:phone":"+31 43 321 1555",
    "sg:postcode":"6214 AN",
    "sg:province":"Limburg",
    "sg:website":"http://www.verfland.nl",
    "wof:name":"Verfland Bv",
    "wof:placetype":"venue"
},
  "geometry": {"coordinates":[5.676797,50.848419],"type":"Point"}
}