{
  "type": "Feature",
  "properties": {
    "addr:full":"Sint Elisabethstraat 48 Vught Noord-Brabant 5261 VN",
    "addr:housenumber":"48",
    "addr:postcode":"5261 vn",
    "addr:street":"Sint Elisabethstraat",
    "iso:country":"NL",
    "sg:address":"Sint Elisabethstraat 48",
    "sg:city":"Vught",
    "sg:classifiers":[
        {
            "category":"Bakery",
            "type":"Food & Drink"
        }
    ],
    "sg:phone":"+31 73 656 2912",
    "sg:postcode":"5261 VN",
    "sg:province":"Noord-Brabant",
    "sg:tags":[
        "brood",
        "banket"
    ],
    "wof:name":"L. Goossens Boulangerie",
    "wof:placetype":"venue"
},
  "geometry": {"coordinates":[5.295751,51.655144],"type":"Point"}
}