{
  "type": "Feature",
  "properties": {
    "addr:full":"Groenmarkt 31 Zutphen Gelderland 7201 HW",
    "addr:housenumber":"31",
    "addr:postcode":"7201 hw",
    "addr:street":"Groenmarkt;Gelderland",
    "iso:country":"NL",
    "sg:address":"Groenmarkt 31",
    "sg:city":"Zutphen",
    "sg:orig_category":"Kappers",
    "sg:phone":"+31 575 542 640",
    "sg:postcode":"7201 HW",
    "sg:province":"Gelderland",
    "wof:name":"Unique Coiffures",
    "wof:placetype":"venue"
},
  "geometry": {"coordinates":[6.194682,52.141541],"type":"Point"}
}