{
  "type": "Feature",
  "properties": {
    "iso:country":"NL",
    "sg:address":"Vliegenierswg 116",
    "sg:city":"Sassenheim",
    "sg:orig_category":"Bloembollen - Groothandel",
    "sg:phone":"+31 252 213 182",
    "sg:postcode":"2171 PE",
    "sg:province":"South Holland",
    "wof:name":"Heyl, Fa W J",
    "wof:placetype":"venue"
},
  "geometry": {"coordinates":[4.508596,52.21962],"type":"Point"}
}