{
  "type": "Feature",
  "properties": {
    "addr:full":"Poortenaarln 60 Nieuwegein Utrecht 3431 RJ",
    "addr:housenumber":"60",
    "addr:postcode":"3431 rj",
    "addr:street":"Poortenaarln",
    "iso:country":"NL",
    "sg:address":"Poortenaarln 60",
    "sg:city":"Nieuwegein",
    "sg:orig_category":"Orthopedagogen",
    "sg:phone":"+31 30 630 2253",
    "sg:postcode":"3431 RJ",
    "sg:province":"Utrecht",
    "wof:name":"Prakt Vecht Rijn En Ijssel",
    "wof:placetype":"venue"
},
  "geometry": {"coordinates":[5.0779690742,52.0326499939],"type":"Point"}
}