{
  "type": "Feature",
  "properties": {
    "iso:country":"NL",
    "sg:address":"Lombardstraat 30",
    "sg:city":"Dordrecht",
    "sg:orig_category":"Keramische Producten Fab",
    "sg:phone":"+31 78 613 0446",
    "sg:postcode":"3311 VL",
    "sg:province":"South Holland",
    "wof:name":"A.M. Spaan",
    "wof:placetype":"venue"
},
  "geometry": {"coordinates":[4.665014,51.813072],"type":"Point"}
}