{
  "type": "Feature",
  "properties": {
    "addr:full":"Noorderhaven 61 Groningen Groningen 9712 VJ",
    "addr:housenumber":"61",
    "addr:postcode":"9712 vj",
    "addr:street":"Noorderhaven",
    "iso:country":"NL",
    "sg:address":"Noorderhaven 61",
    "sg:city":"Groningen",
    "sg:orig_category":"Kunst And Kunstenaarsbenodigdheden",
    "sg:phone":"+31 50 312 9990",
    "sg:postcode":"9712 VJ",
    "sg:province":"Groningen",
    "wof:name":"Richards'S Kunst-Atelier",
    "wof:placetype":"venue"
},
  "geometry": {"coordinates":[6.557043,53.219913],"type":"Point"}
}