{
  "type": "Feature",
  "properties": {
    "addr:full":"Planetenwg 4 Berkel En Rodenrys South Holland 2651 JC",
    "addr:housenumber":"4",
    "addr:postcode":"2651 jc",
    "addr:street":"Planetenwg;Berkel",
    "iso:country":"NL",
    "sg:address":"Planetenwg 4",
    "sg:city":"Berkel En Rodenrys",
    "sg:orig_category":"Puien",
    "sg:phone":"+31 10 512 0089",
    "sg:postcode":"2651 JC",
    "sg:province":"South Holland",
    "wof:name":"R\u00fbve",
    "wof:placetype":"venue"
},
  "geometry": {"coordinates":[4.484238,52.006252],"type":"Point"}
}