{
  "type": "Feature",
  "properties": {
    "addr:full":"Scheiwg 11 Gemert Noord-Brabant 5421 XL",
    "addr:housenumber":"11",
    "addr:postcode":"5421 xl",
    "addr:street":"Scheiwg",
    "iso:country":"NL",
    "sg:address":"Scheiwg 11",
    "sg:city":"Gemert",
    "sg:orig_category":"Bedrijfskleding",
    "sg:phone":"+31 492 390 516",
    "sg:postcode":"5421 XL",
    "sg:province":"Noord-Brabant",
    "sg:website":"http://www.asgpneumatics.nl",
    "wof:name":"Asg Pneumatics",
    "wof:placetype":"venue"
},
  "geometry": {"coordinates":[5.705921,51.566002],"type":"Point"}
}