{
  "type": "Feature",
  "properties": {
    "addr:full":"Potgieterln 17 Leiden Zuid-Holland 2321 XX",
    "addr:housenumber":"17",
    "addr:postcode":"2321 xx",
    "addr:street":"Potgieterln",
    "iso:country":"NL",
    "sg:address":"Potgieterln 17",
    "sg:city":"Leiden",
    "sg:orig_category":"Bestratingen",
    "sg:phone":"+31 71 576 1873",
    "sg:postcode":"2321 XX",
    "sg:province":"Zuid-Holland",
    "wof:name":"Mimo",
    "wof:placetype":"venue"
},
  "geometry": {"coordinates":[4.47769,52.157059],"type":"Point"}
}