{
  "type": "Feature",
  "properties": {
    "addr:full":"Nieuwewg 43 Honselersdyk Sofiya 2675 BG",
    "addr:housenumber":"43",
    "addr:postcode":"2675",
    "addr:street":"Nieuwewg",
    "iso:country":"NL",
    "sg:address":"Nieuwewg 43",
    "sg:city":"Honselersdyk",
    "sg:orig_category":"Bloembollen - Groothandel",
    "sg:phone":"+31 174 623 217",
    "sg:postcode":"2675 BG",
    "sg:province":"Sofiya",
    "wof:name":"Nieuwkerk, C J Van",
    "wof:placetype":"venue"
},
  "geometry": {"coordinates":[23.061251,42.181301],"type":"Point"}
}