{
  "type": "Feature",
  "properties": {
    "addr:full":"Kerkring 62 Oude Tonge Zuid-Holland 3255 AH",
    "addr:housenumber":"62",
    "addr:postcode":"3255 ah",
    "addr:street":"Kerkring",
    "iso:country":"NL",
    "sg:address":"Kerkring 62",
    "sg:city":"Oude Tonge",
    "sg:orig_category":"Drogisterijen",
    "sg:phone":"+31 187 641 252",
    "sg:postcode":"3255 AH",
    "sg:province":"Zuid-Holland",
    "wof:name":"Loon, Fa M Van",
    "wof:placetype":"venue"
},
  "geometry": {"coordinates":[4.212185,51.691158],"type":"Point"}
}