{
  "type": "Feature",
  "properties": {
    "addr:full":"Industriestraat 19 Naaldwijk Zuid-Holland 2671 CT",
    "addr:housenumber":"19",
    "addr:postcode":"2671 ct",
    "addr:street":"Industriestraat",
    "iso:country":"NL",
    "sg:address":"Industriestraat 19",
    "sg:city":"Naaldwijk",
    "sg:orig_category":"Zuivelproducten",
    "sg:phone":"+31 174 629 757",
    "sg:postcode":"2671 CT",
    "sg:province":"Zuid-Holland",
    "wof:name":"Gebroeders Van Den Ende Vof",
    "wof:placetype":"venue"
},
  "geometry": {"coordinates":[4.211478,52.000298],"type":"Point"}
}