{
  "type": "Feature",
  "properties": {
    "addr:full":"Moleneind Nz 124 Drachten Friesland 9203 ZS",
    "addr:housenumber":"124",
    "addr:postcode":"9203 zs",
    "addr:street":"Moleneind Nz",
    "iso:country":"NL",
    "sg:address":"Moleneind Nz 124",
    "sg:city":"Drachten",
    "sg:orig_category":"Bedrijfsmechanisatie En -Automatisering",
    "sg:phone":"+31 512 549 790",
    "sg:postcode":"9203 ZS",
    "sg:province":"Friesland",
    "wof:name":"Sw-Technische Modelbouw",
    "wof:placetype":"venue"
},
  "geometry": {"coordinates":[6.0902,53.106396],"type":"Point"}
}