{
  "type": "Feature",
  "properties": {
    "addr:full":"Postbus 14861 Amsterdam North Holland 1001 LJ",
    "addr:housenumber":"14861",
    "addr:postcode":"1001 lj",
    "addr:street":"Postbus",
    "iso:country":"NL",
    "sg:address":"Postbus 14861",
    "sg:city":"Amsterdam",
    "sg:orig_category":"Makelaars En Adviseurs Onroerende Goederen",
    "sg:phone":"+31 20 625 5818",
    "sg:postcode":"1001 LJ",
    "sg:province":"North Holland",
    "wof:name":"Floris Hampe Bv",
    "wof:placetype":"venue"
},
  "geometry": {"coordinates":[4.89319,52.373119],"type":"Point"}
}