{
  "type": "Feature",
  "properties": {
    "addr:full":"Hof Van Spaland 45 Schiedam Zuid-Holland 3121 CA",
    "addr:housenumber":"45",
    "addr:postcode":"3121 ca",
    "addr:street":"Hof Van Spaland",
    "iso:country":"NL",
    "sg:address":"Hof Van Spaland 45",
    "sg:city":"Schiedam",
    "sg:orig_category":"Medische Apparatuur And Prothesen Fab",
    "sg:phone":"+31 10 471 1320",
    "sg:postcode":"3121 CA",
    "sg:province":"Zuid-Holland",
    "wof:name":"Veringmeier Bv",
    "wof:placetype":"venue"
},
  "geometry": {"coordinates":[4.375473,51.93457],"type":"Point"}
}