{
  "type": "Feature",
  "properties": {
    "addr:full":"Watermanweg 121 Rotterdam South Holland 3067 GA",
    "addr:housenumber":"121",
    "addr:postcode":"3067 ga",
    "addr:street":"Watermanweg",
    "iso:country":"NL",
    "sg:address":"Watermanweg 121",
    "sg:city":"Rotterdam",
    "sg:orig_category":"Meubelzaken, Woning- And Keukeninrichting",
    "sg:phone":"+31 10 286 0980",
    "sg:postcode":"3067 GA",
    "sg:province":"South Holland",
    "wof:name":"Jencikova International Bv",
    "wof:placetype":"venue"
},
  "geometry": {"coordinates":[4.559378,51.951332],"type":"Point"}
}