{
  "type": "Feature",
  "properties": {
    "addr:full":"D Staalwg 5 Ermelo Gelderland 3851 LG",
    "addr:housenumber":"5",
    "addr:postcode":"3851 lg",
    "addr:street":"Gelderland",
    "iso:country":"NL",
    "sg:address":"D Staalwg 5",
    "sg:city":"Ermelo",
    "sg:orig_category":"Onroerende Goederen",
    "sg:phone":"+31 341 561 428",
    "sg:postcode":"3851 LG",
    "sg:province":"Gelderland",
    "wof:name":"Visbeek",
    "wof:placetype":"venue"
},
  "geometry": {"coordinates":[5.624483,52.299938],"type":"Point"}
}