{
  "type": "Feature",
  "properties": {
    "addr:full":"Kerkhof 2 Heeze North Brabant 5591 TD",
    "addr:housenumber":"2",
    "addr:postcode":"5591 td",
    "addr:street":"Kerkhof",
    "iso:country":"NL",
    "sg:address":"Kerkhof 2",
    "sg:city":"Heeze",
    "sg:orig_category":"Bloemen En Planten",
    "sg:phone":"+31 40 226 4306",
    "sg:postcode":"5591 TD",
    "sg:province":"North Brabant",
    "wof:name":"Bree Kuijpers, M A Van",
    "wof:placetype":"venue"
},
  "geometry": {"coordinates":[5.566743,51.370232],"type":"Point"}
}