{
  "type": "Feature",
  "properties": {
    "addr:full":"V Bassenstr 2 Rotterdam South Holland 3067 XD",
    "addr:housenumber":"2",
    "addr:postcode":"3067 xd",
    "addr:street":"Bassenstr",
    "iso:country":"NL",
    "sg:address":"V Bassenstr 2",
    "sg:city":"Rotterdam",
    "sg:orig_category":"Artsen - Huisartsen",
    "sg:phone":"+31 10 420 0439",
    "sg:postcode":"3067 XD",
    "sg:province":"South Holland",
    "wof:name":"Haarmans, H M M",
    "wof:placetype":"venue"
},
  "geometry": {"coordinates":[4.55193,51.944969],"type":"Point"}
}