{
  "type": "Feature",
  "properties": {
    "addr:full":"Lysterbesln 37 Oudorp Nh Noord-Holland 1829 HA",
    "addr:housenumber":"37",
    "addr:postcode":"1829 ha",
    "addr:street":"Lysterbesln",
    "iso:country":"NL",
    "sg:address":"Lysterbesln 37",
    "sg:city":"Oudorp Nh",
    "sg:orig_category":"Afslankinstituten",
    "sg:phone":"+31 72 512 5875",
    "sg:postcode":"1829 HA",
    "sg:province":"Noord-Holland",
    "wof:name":"Vital Power",
    "wof:placetype":"venue"
},
  "geometry": {"coordinates":[4.774885,52.636589],"type":"Point"}
}