{
  "type": "Feature",
  "properties": {
    "addr:full":"Palmentuin 63 Rotterdam South Holland 3078 KJ",
    "addr:housenumber":"63",
    "addr:postcode":"3078 kj",
    "addr:street":"Palmentuin",
    "iso:country":"NL",
    "sg:address":"Palmentuin 63",
    "sg:city":"Rotterdam",
    "sg:orig_category":"Orthopedisch Schoeisel",
    "sg:phone":"+31 10 479 7144",
    "sg:postcode":"3078 KJ",
    "sg:province":"South Holland",
    "sg:website":"http://www.wittekamp-broos.nl",
    "wof:name":"Wittekamp & Broos",
    "wof:placetype":"venue"
},
  "geometry": {"coordinates":[4.5503149033,51.8895568848],"type":"Point"}
}