{
  "type": "Feature",
  "properties": {
    "addr:full":"Utrechtsewg 141 Zeist Utrecht 3702 AC",
    "addr:housenumber":"141",
    "addr:postcode":"3702 ac",
    "iso:country":"NL",
    "sg:address":"Utrechtsewg 141",
    "sg:city":"Zeist",
    "sg:orig_category":"Hulpverlening Sociaal",
    "sg:phone":"+31 30 691 8289",
    "sg:postcode":"3702 AC",
    "sg:province":"Utrecht",
    "wof:name":"Slachtofferhulp Zuid- Oost Utrecht, Buro",
    "wof:placetype":"venue"
},
  "geometry": {"coordinates":[5.237268,52.084122],"type":"Point"}
}