{
  "type": "Feature",
  "properties": {
    "addr:full":"Wijngaardpln 48 Eindhoven North Brabant 5632 MC",
    "addr:housenumber":"48",
    "addr:postcode":"5632 mc",
    "addr:street":"Wijngaardpln",
    "iso:country":"NL",
    "sg:address":"Wijngaardpln 48",
    "sg:city":"Eindhoven",
    "sg:orig_category":"Cafetaria'S",
    "sg:phone":"+31 40 241 9255",
    "sg:postcode":"5632 MC",
    "sg:province":"North Brabant",
    "wof:name":"Wijngaard, De",
    "wof:placetype":"venue"
},
  "geometry": {"coordinates":[5.493408,51.477394],"type":"Point"}
}