{
  "type": "Feature",
  "properties": {
    "addr:full":"Sisalstr 22 Genemuiden NL.08 8281 JJ",
    "addr:housenumber":"22;nl.08",
    "addr:postcode":"8281 jj",
    "addr:street":"Sisalstr",
    "iso:country":"NL",
    "sg:address":"Sisalstr 22",
    "sg:city":"Genemuiden",
    "sg:orig_category":"Verf En Lak - Fabrieken En Groothandel",
    "sg:phone":"+31 38 385 5444",
    "sg:postcode":"8281 JJ",
    "sg:province":"NL.08",
    "wof:name":"Cronolin",
    "wof:placetype":"venue"
},
  "geometry": {"coordinates":[6.062518,52.623352],"type":"Point"}
}