{
  "type": "Feature",
  "properties": {
    "addr:full":"Dollardstraat 160 Amersfoort Utrecht 3812 EP",
    "addr:housenumber":"160",
    "addr:postcode":"3812 ep",
    "addr:street":"Dollardstraat",
    "iso:country":"NL",
    "sg:address":"Dollardstraat 160",
    "sg:city":"Amersfoort",
    "sg:orig_category":"Film-, Tv- And Videoproductie",
    "sg:phone":"+31 33 465 2486",
    "sg:postcode":"3812 EP",
    "sg:province":"Utrecht",
    "wof:name":"P. Meijer",
    "wof:placetype":"venue"
},
  "geometry": {"coordinates":[5.365468,52.162342],"type":"Point"}
}