{
  "type": "Feature",
  "properties": {
    "addr:full":"Sonmansstr 76B Rotterdam Zuid-Holland 3039 DM",
    "addr:housenumber":"76b",
    "addr:postcode":"3039 dm",
    "addr:street":"Sonmansstr",
    "iso:country":"NL",
    "sg:address":"Sonmansstr 76B",
    "sg:city":"Rotterdam",
    "sg:orig_category":"Kantoor- En Secretariaatsservice",
    "sg:phone":"+31 6 47224824",
    "sg:postcode":"3039 DM",
    "sg:province":"Zuid-Holland",
    "wof:name":"Vinden, Van Der",
    "wof:placetype":"venue"
},
  "geometry": {"coordinates":[4.4593849182,51.9333534241],"type":"Point"}
}