{
  "type": "Feature",
  "properties": {
    "addr:full":"Kalverdk 81 Tuitjenhorn Noord-Holland 1747 GK",
    "addr:housenumber":"81",
    "addr:postcode":"1747 gk",
    "addr:street":"Kalverdk",
    "iso:country":"NL",
    "sg:address":"Kalverdk 81",
    "sg:city":"Tuitjenhorn",
    "sg:orig_category":"Makelaars En Adviseurs Onroerende Goederen",
    "sg:phone":"+31 226 393 800",
    "sg:postcode":"1747 GK",
    "sg:province":"Noord-Holland",
    "wof:name":"Brederode, L Van",
    "wof:placetype":"venue"
},
  "geometry": {"coordinates":[4.767972,52.732468],"type":"Point"}
}