{
  "type": "Feature",
  "properties": {
    "addr:full":"Lindestraat 33 Valkenswaard Noord-Brabant 5553 EA",
    "addr:housenumber":"33",
    "addr:postcode":"5553 ea",
    "addr:street":"Lindestraat",
    "iso:country":"NL",
    "sg:address":"Lindestraat 33",
    "sg:city":"Valkenswaard",
    "sg:orig_category":"Metaalbekleding And -Behandeling",
    "sg:phone":"+31 40 201 5868",
    "sg:postcode":"5553 EA",
    "sg:province":"Noord-Brabant",
    "wof:name":"Vof Mollen",
    "wof:placetype":"venue"
},
  "geometry": {"coordinates":[5.46678,51.356548],"type":"Point"}
}