{
  "type": "Feature",
  "properties": {
    "addr:full":"Halve Maan 18 Lobith Gelderland 6915 SW",
    "addr:housenumber":"18;6915",
    "addr:street":"Halve Maan;Gelderland;Sw",
    "iso:country":"NL",
    "sg:address":"Halve Maan 18",
    "sg:city":"Lobith",
    "sg:orig_category":"Woningbouw- Verenigingen En -Stichtingen",
    "sg:phone":"+31 900 2027500",
    "sg:postcode":"6915 SW",
    "sg:province":"Gelderland",
    "sg:website":"http://www.degoedewoninglobith.nl",
    "wof:name":"Rijnwaarden Woonservice Bv",
    "wof:placetype":"venue"
},
  "geometry": {"coordinates":[6.1113801003,51.8653488159],"type":"Point"}
}