{
  "type": "Feature",
  "properties": {
    "iso:country":"NL",
    "sg:address":"Berline 32",
    "sg:city":"Sassenheim",
    "sg:orig_category":"Schilders",
    "sg:phone":"+31 252 222 129",
    "sg:postcode":"2171 MG",
    "sg:province":"Zuid-Holland",
    "wof:name":"Goddijn, Hein",
    "wof:placetype":"venue"
},
  "geometry": {"coordinates":[4.511679,52.223103],"type":"Point"}
}