{
  "type": "Feature",
  "properties": {
    "addr:full":"Kattestaart 10 Papendrecht Zuid-Holland 3355 PP",
    "addr:housenumber":"10",
    "addr:postcode":"3355 pp",
    "addr:street":"Kattestaart",
    "iso:country":"NL",
    "sg:address":"Kattestaart 10",
    "sg:city":"Papendrecht",
    "sg:orig_category":"Schilders",
    "sg:phone":"+31 78 642 0000",
    "sg:postcode":"3355 PP",
    "sg:province":"Zuid-Holland",
    "sg:website":"http://www.groenbv.nl",
    "wof:name":"Groen Schildersbedrijf Bv",
    "wof:placetype":"venue"
},
  "geometry": {"coordinates":[4.70454,51.831844],"type":"Point"}
}