{
  "type": "Feature",
  "properties": {
    "addr:full":"Harmoniehof 8-1 Amsterdam Noord-Holland 1071 TC",
    "addr:housenumber":"8-1",
    "addr:postcode":"1071 tc",
    "addr:street":"Harmoniehof",
    "iso:country":"NL",
    "sg:address":"Harmoniehof 8-1",
    "sg:city":"Amsterdam",
    "sg:orig_category":"Onroerende Goederen",
    "sg:phone":"+31 20 671 1700",
    "sg:postcode":"1071 TC",
    "sg:province":"Noord-Holland",
    "wof:name":"Multi Services",
    "wof:placetype":"venue"
},
  "geometry": {"coordinates":[4.884057,52.351402],"type":"Point"}
}