{
  "type": "Feature",
  "properties": {
    "iso:country":"NL",
    "sg:address":"C H Moensstr 12",
    "sg:city":"Beverwyk",
    "sg:orig_category":"Voegwerken",
    "sg:phone":"+31 251 211 616",
    "sg:postcode":"1942 EC",
    "sg:province":"Noord-Holland",
    "wof:name":"Gellekom",
    "wof:placetype":"venue"
},
  "geometry": {"coordinates":[4.652614,52.482826],"type":"Point"}
}