{
  "type": "Feature",
  "properties": {
    "addr:full":"Dwarsvaartwg 71 Boyl Friesland 8392 MT",
    "addr:housenumber":"71",
    "addr:postcode":"8392",
    "addr:street":"Dwarsvaartwg;Mt",
    "iso:country":"NL",
    "sg:address":"Dwarsvaartwg 71",
    "sg:city":"Boyl",
    "sg:orig_category":"Bloemen En Planten - Groothandel",
    "sg:phone":"+31 561 431 502",
    "sg:postcode":"8392 MT",
    "sg:province":"Friesland",
    "wof:name":"Exceptio",
    "wof:placetype":"venue"
},
  "geometry": {"coordinates":[-90.72695899999999,33.703896],"type":"Point"}
}