{
  "type": "Feature",
  "properties": {
    "addr:full":"De Eglantier 248 Apeldoorn Gelderland 7329 DH",
    "addr:housenumber":"248",
    "addr:postcode":"7329 dh",
    "addr:street":"De Eglantier;Gelderland",
    "iso:country":"NL",
    "sg:address":"De Eglantier 248",
    "sg:city":"Apeldoorn",
    "sg:orig_category":"Opticiens",
    "sg:phone":"+31 55 542 1337",
    "sg:postcode":"7329 DH",
    "sg:province":"Gelderland",
    "sg:website":"http://www.optiek.com",
    "wof:name":"Klein Optiek",
    "wof:placetype":"venue"
},
  "geometry": {"coordinates":[6.0052599907,52.193561554],"type":"Point"}
}