{
  "type": "Feature",
  "properties": {
    "addr:full":"J Boschln 30 Zwyndrecht South Holland 3331 HS",
    "addr:housenumber":"30",
    "addr:postcode":"3331 hs",
    "addr:street":"Zwyndrecht South",
    "iso:country":"NL",
    "sg:address":"J Boschln 30",
    "sg:city":"Zwyndrecht",
    "sg:classifiers":[
        {
            "category":"Personal",
            "subcategory":"Nail Salon",
            "type":"Services"
        }
    ],
    "sg:phone":"+31 78 612 4758",
    "sg:postcode":"3331 HS",
    "sg:province":"South Holland",
    "sg:tags":[
        "pedicure"
    ],
    "wof:name":"Stolk-Schreuder, A C",
    "wof:placetype":"venue"
},
  "geometry": {"coordinates":[4.64073,51.820702],"type":"Point"}
}