{
  "type": "Feature",
  "properties": {
    "addr:full":"Kerkbuurt 200 Sliedrecht South Holland 3361 BM",
    "addr:housenumber":"200",
    "addr:postcode":"3361 bm",
    "addr:street":"Kerkbuurt",
    "iso:country":"NL",
    "sg:address":"Kerkbuurt 200",
    "sg:city":"Sliedrecht",
    "sg:orig_category":"Ziekenhuizen, Sanatoria, Verpleeghuizen",
    "sg:phone":"+31 184 412 033",
    "sg:postcode":"3361 BM",
    "sg:province":"South Holland",
    "wof:name":"Waerthove",
    "wof:placetype":"venue"
},
  "geometry": {"coordinates":[4.768483,51.823444],"type":"Point"}
}