{
  "type": "Feature",
  "properties": {
    "iso:country":"NL",
    "sg:address":"Kl Westerwyksestr 13",
    "sg:city":"Biest Houtakker",
    "sg:orig_category":"Dierenvoeder - Fabrieken",
    "sg:phone":"+31 13 514 2853",
    "sg:postcode":"5084 HN",
    "sg:province":"North Brabant",
    "wof:name":"Schapendonk & Van Oort",
    "wof:placetype":"venue"
},
  "geometry": {"coordinates":[5.144592,51.513546],"type":"Point"}
}