{
  "type": "Feature",
  "properties": {
    "addr:full":"Kerkstr 4 Arnhem Gelderland 6811 DL",
    "addr:housenumber":"4",
    "addr:postcode":"6811 dl",
    "addr:street":"Kerkstr",
    "iso:country":"NL",
    "sg:address":"Kerkstr 4",
    "sg:city":"Arnhem",
    "sg:orig_category":"Babyartikelen",
    "sg:phone":"+31 26 442 2629",
    "sg:postcode":"6811 DL",
    "sg:province":"Gelderland",
    "wof:name":"Vibel",
    "wof:placetype":"venue"
},
  "geometry": {"coordinates":[5.909642,51.98061],"type":"Point"}
}