{
  "type": "Feature",
  "properties": {
    "addr:full":"Koloniedijk 46 Vinkenbuurt Overijssel 7739 PB",
    "addr:housenumber":"46",
    "addr:postcode":"7739 pb",
    "addr:street":"Koloniedijk",
    "iso:country":"NL",
    "sg:address":"Koloniedijk 46",
    "sg:city":"Vinkenbuurt",
    "sg:orig_category":"Loodgieterswerk, Verwarming And Sanitaire Installaties",
    "sg:phone":"+31 523 656 702",
    "sg:postcode":"7739 PB",
    "sg:province":"Overijssel",
    "wof:name":"H. Hulst",
    "wof:placetype":"venue"
},
  "geometry": {"coordinates":[6.343392,52.578888],"type":"Point"}
}