{
  "type": "Feature",
  "properties": {
    "addr:full":"Larikslaan 10 Leusden Utrecht 3833 AM",
    "addr:housenumber":"10",
    "addr:postcode":"3833",
    "addr:street":"Larikslaan",
    "iso:country":"NL",
    "sg:address":"Larikslaan 10",
    "sg:city":"Leusden",
    "sg:orig_category":"Fitnesscentra",
    "sg:phone":"+31 33 494 6409",
    "sg:postcode":"3833 AM",
    "sg:province":"Utrecht",
    "wof:name":"Theo Meijer Sport",
    "wof:placetype":"venue"
},
  "geometry": {"coordinates":[5.421887,52.140404],"type":"Point"}
}