{
  "type": "Feature",
  "properties": {
    "addr:full":"Knibbelakker 63 Epe Gelderland 8162 ZP",
    "addr:housenumber":"63",
    "addr:postcode":"8162 zp",
    "addr:street":"Knibbelakker;Gelderland",
    "iso:country":"NL",
    "sg:address":"Knibbelakker 63",
    "sg:city":"Epe",
    "sg:orig_category":"Onderhoudswerken",
    "sg:phone":"+31 578 616 573",
    "sg:postcode":"8162 ZP",
    "sg:province":"Gelderland",
    "wof:name":"Weerd, J H De",
    "wof:placetype":"venue"
},
  "geometry": {"coordinates":[5.969629,52.344917],"type":"Point"}
}