{
  "type": "Feature",
  "properties": {
    "addr:full":"Hogeweg 12 Zeeland Noord-Brabant 5411 LP",
    "addr:housenumber":"12",
    "addr:postcode":"5411 lp",
    "addr:street":"Hogeweg",
    "iso:country":"NL",
    "sg:address":"Hogeweg 12",
    "sg:city":"Zeeland",
    "sg:orig_category":"Zuivelproducten And Spijsoli?n Gh",
    "sg:phone":"+31 486 451 558",
    "sg:postcode":"5411 LP",
    "sg:province":"Noord-Brabant",
    "wof:name":"G.C.M. Verhoeven",
    "wof:placetype":"venue"
},
  "geometry": {"coordinates":[5.677165,51.70763],"type":"Point"}
}