{
  "type": "Feature",
  "properties": {
    "addr:full":"Kampweg 81 Doorn Utrecht 3941 HE",
    "addr:housenumber":"81",
    "addr:postcode":"3941 he",
    "addr:street":"Kampweg",
    "iso:country":"NL",
    "sg:address":"Kampweg 81",
    "sg:city":"Doorn",
    "sg:orig_category":"Fruit And Groenten Gh",
    "sg:phone":"+31 343 412 669",
    "sg:postcode":"3941 HE",
    "sg:province":"Utrecht",
    "wof:name":"P. Van Woudenberg",
    "wof:placetype":"venue"
},
  "geometry": {"coordinates":[5.340797,52.037685],"type":"Point"}
}