{
  "type": "Feature",
  "properties": {
    "addr:full":"Groenlandsstraatje 60 Tiel Gelderland 4001 HM",
    "addr:housenumber":"60",
    "addr:postcode":"4001 hm",
    "addr:street":"Groenlandsstraatje;Gelderland",
    "iso:country":"NL",
    "sg:address":"Groenlandsstraatje 60",
    "sg:city":"Tiel",
    "sg:orig_category":"Schilderwerk",
    "sg:phone":"+31 344 620 264",
    "sg:postcode":"4001 HM",
    "sg:province":"Gelderland",
    "wof:name":"Nico De Meesterschilder Schildersbedrijf",
    "wof:placetype":"venue"
},
  "geometry": {"coordinates":[5.432903,51.890385],"type":"Point"}
}