{
  "type": "Feature",
  "properties": {
    "addr:full":"Postbus 138 Putte Noord-Brabant 4645 ZJ",
    "addr:housenumber":"138",
    "addr:postcode":"4645 zj",
    "addr:street":"Postbus",
    "iso:country":"NL",
    "sg:address":"Postbus 138",
    "sg:city":"Putte",
    "sg:orig_category":"Graveermachines",
    "sg:phone":"+31 20 691 1032",
    "sg:postcode":"4645 ZJ",
    "sg:province":"Noord-Brabant",
    "wof:name":"Gravograph Benelux",
    "wof:placetype":"venue"
},
  "geometry": {"coordinates":[4.393308,51.359718],"type":"Point"}
}