{
  "type": "Feature",
  "properties": {
    "addr:full":"Suikerbrink 3 Vaassen Gelderland 8172 XZ",
    "addr:housenumber":"3",
    "addr:postcode":"8172 xz",
    "addr:street":"Suikerbrink;Gelderland",
    "iso:country":"NL",
    "sg:address":"Suikerbrink 3",
    "sg:city":"Vaassen",
    "sg:orig_category":"Verbouwingen",
    "sg:phone":"+31 578 570 259",
    "sg:postcode":"8172 XZ",
    "sg:province":"Gelderland",
    "wof:name":"Visser Bouwbedrijf",
    "wof:placetype":"venue"
},
  "geometry": {"coordinates":[5.965903,52.284176],"type":"Point"}
}