{
  "type": "Feature",
  "properties": {
    "addr:full":"T V Berkhoutstr 7 Baarn Utrecht 3743 BT",
    "addr:housenumber":"7",
    "addr:postcode":"3743 bt",
    "addr:street":"T;Berkhoutstr",
    "iso:country":"NL",
    "sg:address":"T V Berkhoutstr 7",
    "sg:city":"Baarn",
    "sg:orig_category":"Postkantoren",
    "sg:phone":"+31 35 541 2002",
    "sg:postcode":"3743 BT",
    "sg:province":"Utrecht",
    "sg:website":"http://www.postkantoor.nl",
    "wof:name":"Postkantoor",
    "wof:placetype":"venue"
},
  "geometry": {"coordinates":[5.292121,52.21101],"type":"Point"}
}