{
  "type": "Feature",
  "properties": {
    "addr:full":"Akkerstr 97 Groningen Groningen 9717 KZ",
    "addr:housenumber":"97",
    "addr:postcode":"9717 kz",
    "addr:street":"Akkerstr",
    "iso:country":"NL",
    "sg:address":"Akkerstr 97",
    "sg:city":"Groningen",
    "sg:orig_category":"Filmstudio'S En -Productie",
    "sg:phone":"+31 50 853 3300",
    "sg:postcode":"9717 KZ",
    "sg:province":"Groningen",
    "sg:website":"http://www.noordkaap.nl",
    "wof:name":"Noordkaap",
    "wof:placetype":"venue"
},
  "geometry": {"coordinates":[6.557746,53.22736],"type":"Point"}
}