{
  "type": "Feature",
  "properties": {
    "iso:country":"NL",
    "sg:address":"Weegschaal 31",
    "sg:city":"Amstelveen",
    "sg:orig_category":"Verenigingen En Stichtingen",
    "sg:phone":"+31 20 643 8410",
    "sg:postcode":"1188 CA",
    "sg:province":"Noord-Holland",
    "wof:name":"Paardensport A'Dam, Sticht",
    "wof:placetype":"venue"
},
  "geometry": {"coordinates":[4.855244,52.28368],"type":"Point"}
}