{
  "type": "Feature",
  "properties": {
    "addr:full":"Ijsseldk N 422 Ouderkerk A/D Ijssel South Holland 2935 CT",
    "addr:housenumber":"422;a / d",
    "addr:postcode":"2935 ct",
    "addr:street":"N;Ijssel South",
    "iso:country":"NL",
    "sg:address":"Ijsseldk N 422",
    "sg:city":"Ouderkerk A/D Ijssel",
    "sg:orig_category":"Houtgroothandel",
    "sg:phone":"+31 180 681 744",
    "sg:postcode":"2935 CT",
    "sg:province":"South Holland",
    "wof:name":"Zwaantje Bv, 'T",
    "wof:placetype":"venue"
},
  "geometry": {"coordinates":[4.648075,51.970963],"type":"Point"}
}