{
  "type": "Feature",
  "properties": {
    "iso:country":"NL",
    "sg:address":"Bilderdammerwg 72",
    "sg:city":"Kudelstaart",
    "sg:orig_category":"Fietsen En Bromfietsen",
    "sg:phone":"+31 297 320 641",
    "sg:postcode":"1433 HJ",
    "sg:province":"Noord-Holland",
    "sg:website":"http://www.klaasgroot.nl",
    "wof:name":"Klaas Groot Racefietsenspec",
    "wof:placetype":"venue"
},
  "geometry": {"coordinates":[4.742554,52.23214],"type":"Point"}
}