{
  "type": "Feature",
  "properties": {
    "addr:full":"Elsmaathorst 33 Enschede NL.08 7531 LC",
    "addr:housenumber":"33",
    "addr:postcode":"7531",
    "addr:street":"Elsmaathorst",
    "iso:country":"NL",
    "sg:address":"Elsmaathorst 33",
    "sg:city":"Enschede",
    "sg:orig_category":"Architecten",
    "sg:phone":"+31 53 433 7078",
    "sg:postcode":"7531 LC",
    "sg:province":"NL.08",
    "wof:name":"N.J. Klaver",
    "wof:placetype":"venue"
},
  "geometry": {"coordinates":[6.918518,52.235317],"type":"Point"}
}