{
  "type": "Feature",
  "properties": {
    "addr:full":"Walstr 60 Doetinchem Gelderland 7001 BV",
    "addr:housenumber":"60",
    "addr:postcode":"7001 bv",
    "addr:street":"Walstr;Gelderland",
    "iso:country":"NL",
    "sg:address":"Walstr 60",
    "sg:city":"Doetinchem",
    "sg:orig_category":"Fitnesscentra",
    "sg:phone":"+31 314 343 874",
    "sg:postcode":"7001 BV",
    "sg:province":"Gelderland",
    "wof:name":"Fitness & Aerobic",
    "wof:placetype":"venue"
},
  "geometry": {"coordinates":[6.28741,51.967014],"type":"Point"}
}