{
  "type": "Feature",
  "properties": {
    "addr:full":"Galvanistr 15 Rotterdam Zuid-Holland 3029 AD",
    "addr:housenumber":"15",
    "addr:postcode":"3029 ad",
    "addr:street":"Galvanistr",
    "iso:country":"NL",
    "sg:address":"Galvanistr 15",
    "sg:city":"Rotterdam",
    "sg:orig_category":"Projectontwikkeling",
    "sg:phone":"+31 10 489 6944",
    "sg:postcode":"3029 AD",
    "sg:province":"Zuid-Holland",
    "sg:website":"http://www.obr.rotterdam.nl",
    "wof:name":"Ontwikkelingsbedrijf Rotterdam",
    "wof:placetype":"venue"
},
  "geometry": {"coordinates":[4.430562,51.911674],"type":"Point"}
}