{
  "type": "Feature",
  "properties": {
    "addr:full":"Korendijk 12 Middelburg Zeeland 4331 HP",
    "addr:housenumber":"12",
    "addr:postcode":"4331 hp",
    "addr:street":"Korendijk",
    "iso:country":"NL",
    "sg:address":"Korendijk 12",
    "sg:city":"Middelburg",
    "sg:orig_category":"Meubelzaken, Woning- And Keukeninrichting",
    "sg:phone":"+31 118 650 858",
    "sg:postcode":"4331 HP",
    "sg:province":"Zeeland",
    "wof:name":"Vof De Bies",
    "wof:placetype":"venue"
},
  "geometry": {"coordinates":[3.617716,51.497452],"type":"Point"}
}