{
  "type": "Feature",
  "properties": {
    "addr:full":"Nieuwstraat 3 Maastricht Limburg 6211 CR",
    "addr:housenumber":"3",
    "addr:postcode":"6211 cr",
    "addr:street":"Nieuwstraat",
    "iso:country":"NL",
    "sg:address":"Nieuwstraat 3",
    "sg:city":"Maastricht",
    "sg:orig_category":"Herenmodezaken",
    "sg:phone":"+31 43 321 9328",
    "sg:postcode":"6211 CR",
    "sg:province":"Limburg",
    "wof:name":"Fred. Bronneberg Mannenmode Bv",
    "wof:placetype":"venue"
},
  "geometry": {"coordinates":[5.691476,50.850796],"type":"Point"}
}