{
  "type": "Feature",
  "properties": {
    "addr:full":"1E Atjehstr 50 Amsterdam Noord-Holland 1094 KP",
    "addr:housenumber":"50",
    "addr:postcode":"1094 kp",
    "addr:street":"1E Atjehstr",
    "iso:country":"NL",
    "sg:address":"1E Atjehstr 50",
    "sg:city":"Amsterdam",
    "sg:orig_category":"Fotoreportages",
    "sg:phone":"+31 20 663 9136",
    "sg:postcode":"1094 KP",
    "sg:province":"Noord-Holland",
    "wof:name":"Voort, M Van De",
    "wof:placetype":"venue"
},
  "geometry": {"coordinates":[4.934052,52.362434],"type":"Point"}
}