{
  "type": "Feature",
  "properties": {
    "addr:full":"Stoofwg 1 Hellevoetsluis South Holland 3223 CC",
    "addr:housenumber":"1",
    "addr:postcode":"3223 cc",
    "addr:street":"Stoofwg",
    "iso:country":"NL",
    "sg:address":"Stoofwg 1",
    "sg:city":"Hellevoetsluis",
    "sg:orig_category":"Adviesbureaus Bedrijfsveiligheid",
    "sg:phone":"+31 181 312 194",
    "sg:postcode":"3223 CC",
    "sg:province":"South Holland",
    "wof:name":"Mak-I",
    "wof:placetype":"venue"
},
  "geometry": {"coordinates":[4.144625,51.850834],"type":"Point"}
}