{
  "type": "Feature",
  "properties": {
    "addr:full":"Middenweg 56 Nederhorst Den Berg California 1394 AL",
    "addr:housenumber":"56",
    "addr:postcode":"1394 al",
    "addr:street":"Middenweg",
    "iso:country":"NL",
    "sg:address":"Middenweg 56",
    "sg:city":"Nederhorst Den Berg",
    "sg:orig_category":"Loodgieterswerk, Verwarming And Sanitaire Installaties",
    "sg:phone":"+31 294 257 660",
    "sg:postcode":"1394 AL",
    "sg:province":"California",
    "wof:name":"Technische Handelsonderneming Klinge",
    "wof:placetype":"venue"
},
  "geometry": {"coordinates":[-121.624138,39.182121],"type":"Point"}
}