{
  "type": "Feature",
  "properties": {
    "addr:full":"Steenwg 81 Neerynen Gelderland 4182 PA",
    "addr:housenumber":"81",
    "addr:postcode":"4182",
    "addr:street":"Steenwg;Gelderland",
    "iso:country":"NL",
    "sg:address":"Steenwg 81",
    "sg:city":"Neerynen",
    "sg:classifiers":[
        {
            "category":"Retail",
            "subcategory":"Auto Repair",
            "type":"Services"
        }
    ],
    "sg:phone":"+31 345 569 378",
    "sg:postcode":"4182 PA",
    "sg:province":"Gelderland",
    "sg:tags":[
        "garage"
    ],
    "wof:name":"Vliet & Zn, J J Van",
    "wof:placetype":"venue"
},
  "geometry": {"coordinates":[5.276841,51.854485],"type":"Point"}
}