{
  "type": "Feature",
  "properties": {
    "iso:country":"NL",
    "sg:address":"A Cuypstr 45",
    "sg:city":"Zutphen",
    "sg:orig_category":"Adviesbureaus Marketing",
    "sg:phone":"+31 575 546 087",
    "sg:postcode":"7204 BR",
    "sg:province":"Gelderland",
    "wof:name":"Mendelson",
    "wof:placetype":"venue"
},
  "geometry": {"coordinates":[6.209406,52.139687],"type":"Point"}
}