{
  "type": "Feature",
  "properties": {
    "addr:full":"Middendk 14 Nybroek Gelderland 7397 NA",
    "addr:housenumber":"14",
    "addr:postcode":"7397 na",
    "addr:street":"Middendk;Gelderland",
    "iso:country":"NL",
    "sg:address":"Middendk 14",
    "sg:city":"Nybroek",
    "sg:orig_category":"Keukens",
    "sg:phone":"+31 571 291 670",
    "sg:postcode":"7397 NA",
    "sg:province":"Gelderland",
    "sg:website":"http://www.deroodehoeve.nl",
    "wof:name":"Roode Hoeve De",
    "wof:placetype":"venue"
},
  "geometry": {"coordinates":[6.069934,52.27454],"type":"Point"}
}