{
  "type": "Feature",
  "properties": {
    "addr:full":"Veluwestr 11 Arnhem Gelderland 6813 EA",
    "addr:housenumber":"11",
    "addr:postcode":"6813 ea",
    "addr:street":"Veluwestr",
    "iso:country":"NL",
    "sg:address":"Veluwestr 11",
    "sg:city":"Arnhem",
    "sg:orig_category":"Adviesbureaus Bedrijfsorganisatie",
    "sg:phone":"+31 26 351 3880",
    "sg:postcode":"6813 EA",
    "sg:province":"Gelderland",
    "wof:name":"M & M Select",
    "wof:placetype":"venue"
},
  "geometry": {"coordinates":[5.890964,51.98793],"type":"Point"}
}