{
  "type": "Feature",
  "properties": {
    "addr:full":"Hof V Wenen 40 Doetinchem Gelderland 7007 JP",
    "addr:housenumber":"40",
    "addr:postcode":"7007 jp",
    "addr:street":"Wenen;Gelderland",
    "iso:country":"NL",
    "sg:address":"Hof V Wenen 40",
    "sg:city":"Doetinchem",
    "sg:orig_category":"Onderhoudswerken",
    "sg:phone":"+31 314 327 387",
    "sg:postcode":"7007 JP",
    "sg:province":"Gelderland",
    "wof:name":"Spiek & Hiet Vof",
    "wof:placetype":"venue"
},
  "geometry": {"coordinates":[6.291055,51.963596],"type":"Point"}
}