{
  "type": "Feature",
  "properties": {
    "addr:full":"Htg Aalbrechtwg 18 Alkmaar Noord-Holland 1823 DL",
    "addr:housenumber":"18",
    "addr:postcode":"1823 dl",
    "iso:country":"NL",
    "sg:address":"Htg Aalbrechtwg 18",
    "sg:city":"Alkmaar",
    "sg:classifiers":[
        {
            "category":"Professional",
            "subcategory":"Accounting & Tax Preparation",
            "type":"Services"
        }
    ],
    "sg:phone":"+31 72 567 1167",
    "sg:postcode":"1823 DL",
    "sg:province":"Noord-Holland",
    "sg:tags":[
        "accountant",
        "en",
        "-kantoren",
        "register-"
    ],
    "sg:website":"http://www.ey.nl",
    "wof:name":"Ernst & Young",
    "wof:placetype":"venue"
},
  "geometry": {"coordinates":[4.769976,52.645901],"type":"Point"}
}