{
  "type": "Feature",
  "properties": {
    "addr:full":"Frederikstr 21 Groningen Groningen 9724 KA",
    "addr:housenumber":"21",
    "addr:postcode":"9724 ka",
    "addr:street":"Frederikstr",
    "iso:country":"NL",
    "sg:address":"Frederikstr 21",
    "sg:city":"Groningen",
    "sg:orig_category":"Organisatiebureaus",
    "sg:phone":"+31 50 312 5027",
    "sg:postcode":"9724 KA",
    "sg:province":"Groningen",
    "wof:name":"Brandenburg Prod",
    "wof:placetype":"venue"
},
  "geometry": {"coordinates":[6.5778541565,53.209854126],"type":"Point"}
}