{
  "type": "Feature",
  "properties": {
    "addr:full":"Herenwg 32 Oosterzee Friesland 8536 TN",
    "addr:housenumber":"32",
    "addr:postcode":"8536",
    "addr:street":"Herenwg",
    "iso:country":"NL",
    "sg:address":"Herenwg 32",
    "sg:city":"Oosterzee",
    "sg:orig_category":"Bloemen En Planten",
    "sg:phone":"+31 514 541 878",
    "sg:postcode":"8536 TN",
    "sg:province":"Friesland",
    "wof:name":"Passie Flora",
    "wof:placetype":"venue"
},
  "geometry": {"coordinates":[-85.978554,35.83062],"type":"Point"}
}