{
  "type": "Feature",
  "properties": {
    "addr:full":"Paalbergweg 2 Amsterdam Zuidoost Noord-Holland 1105 AG",
    "addr:housenumber":"2",
    "addr:postcode":"zuidoost;1105",
    "addr:street":"Paalbergweg",
    "iso:country":"NL",
    "sg:address":"Paalbergweg 2",
    "sg:city":"Amsterdam Zuidoost",
    "sg:orig_category":"Bedrijfs- And Managementsconsultants",
    "sg:phone":"+31 20 430 5300",
    "sg:postcode":"1105 AG",
    "sg:province":"Noord-Holland",
    "wof:name":"Aon Consulting Nederland C.V.",
    "wof:placetype":"venue"
},
  "geometry": {"coordinates":[4.953849,52.300289],"type":"Point"}
}