{
  "type": "Feature",
  "properties": {
    "addr:full":"Van Deelenstraat 2A Heusden Gem Heusden Noord-Brabant 5256 JC",
    "addr:housenumber":"2a",
    "addr:postcode":"5256 jc",
    "addr:street":"Van Deelenstraat",
    "iso:country":"NL",
    "sg:address":"Van Deelenstraat 2A",
    "sg:city":"Heusden Gem Heusden",
    "sg:orig_category":"Kinderopvang Behalve Thuis",
    "sg:phone":"+31 416 663 106",
    "sg:postcode":"5256 JC",
    "sg:province":"Noord-Brabant",
    "wof:name":"Kinderdagverblijf Pidie Plokwok",
    "wof:placetype":"venue"
},
  "geometry": {"coordinates":[5.140809,51.724545],"type":"Point"}
}