{
  "type": "Feature",
  "properties": {
    "addr:full":"S De Beauvoirln 54 Huizen Noord-Holland 1277 BK",
    "addr:housenumber":"54",
    "addr:postcode":"1277 bk",
    "addr:street":"S",
    "iso:country":"NL",
    "sg:address":"S De Beauvoirln 54",
    "sg:city":"Huizen",
    "sg:orig_category":"Administratie- En Boekhoudkantoren",
    "sg:phone":"+31 35 526 7443",
    "sg:postcode":"1277 BK",
    "sg:province":"Noord-Holland",
    "wof:name":"M8",
    "wof:placetype":"venue"
},
  "geometry": {"coordinates":[5.279375,52.296528],"type":"Point"}
}