{
  "type": "Feature",
  "properties": {
    "addr:full":"Meidoornplnts 2 Groesbeek Gelderland 6562 GH",
    "addr:housenumber":"2",
    "addr:postcode":"6562 gh",
    "addr:street":"Meidoornplnts;Gelderland",
    "iso:country":"NL",
    "sg:address":"Meidoornplnts 2",
    "sg:city":"Groesbeek",
    "sg:orig_category":"Kermisexploitatie",
    "sg:phone":"+31 24 397 3343",
    "sg:postcode":"6562 GH",
    "sg:province":"Gelderland",
    "wof:name":"Raymond Saedt Vof",
    "wof:placetype":"venue"
},
  "geometry": {"coordinates":[5.93249,51.776745],"type":"Point"}
}