{
  "type": "Feature",
  "properties": {
    "iso:country":"NL",
    "sg:address":"Piet Heinstraat 9",
    "sg:city":"Waalre",
    "sg:orig_category":"Drukkerijen And Copyshops",
    "sg:phone":"+31 40 221 3598",
    "sg:postcode":"5582 JK",
    "sg:province":"Noord-Brabant",
    "wof:name":"Drukkerij Timmermans",
    "wof:placetype":"venue"
},
  "geometry": {"coordinates":[5.472526,51.395451],"type":"Point"}
}