{
  "type": "Feature",
  "properties": {
    "iso:country":"NL",
    "sg:address":"Verdonckstr 3",
    "sg:city":"Someren",
    "sg:orig_category":"Verzekeringen - Verzekeringskantoren",
    "sg:phone":"+31 493 495 889",
    "sg:postcode":"5711 ER",
    "sg:province":"Noord-Brabant",
    "wof:name":"Leenen Assurantie En Adviesbureau",
    "wof:placetype":"venue"
},
  "geometry": {"coordinates":[5.710538,51.384163],"type":"Point"}
}