{
  "type": "Feature",
  "properties": {
    "addr:full":"Herenstr 17 Nieuwegein Utrecht 3438 AJ",
    "addr:housenumber":"17",
    "addr:postcode":"3438 aj",
    "addr:street":"Herenstr",
    "iso:country":"NL",
    "sg:address":"Herenstr 17",
    "sg:city":"Nieuwegein",
    "sg:orig_category":"Verzekeringen - Verzekeringskantoren",
    "sg:phone":"+31 30 601 3513",
    "sg:postcode":"3438 AJ",
    "sg:province":"Utrecht",
    "wof:name":"Kraay",
    "wof:placetype":"venue"
},
  "geometry": {"coordinates":[5.09498,52.037842],"type":"Point"}
}