{
  "type": "Feature",
  "properties": {
    "iso:country":"NL",
    "sg:address":"Lieuwenburg 85",
    "sg:city":"Leeuwarden",
    "sg:orig_category":"Kappers",
    "sg:phone":"+31 58 266 3344",
    "sg:postcode":"8925 CJ",
    "sg:province":"Provincie Friesland",
    "wof:name":"Siep Offenga De Kapper",
    "wof:placetype":"venue"
},
  "geometry": {"coordinates":[5.83865,53.211365],"type":"Point"}
}