{
  "type": "Feature",
  "properties": {
    "iso:country":"NL",
    "sg:address":"Akkermansbeekwg 2A",
    "sg:city":"Terborg",
    "sg:orig_category":"Machinetransporten",
    "sg:phone":"+31 315 243 900",
    "sg:postcode":"7061 ZA",
    "sg:province":"Gelderland",
    "wof:name":"Horst Vof, Ter",
    "wof:placetype":"venue"
},
  "geometry": {"coordinates":[6.338151,51.924606],"type":"Point"}
}