{
  "type": "Feature",
  "properties": {
    "addr:full":"Hoefstr 215 Tilburg Noord-Brabant 5014 NL",
    "addr:housenumber":"215",
    "addr:postcode":"5014 nl",
    "addr:street":"Tilburg",
    "iso:country":"NL",
    "sg:address":"Hoefstr 215",
    "sg:city":"Tilburg",
    "sg:orig_category":"Beurzen",
    "sg:phone":"+31 13 535 1149",
    "sg:postcode":"5014 NL",
    "sg:province":"Noord-Brabant",
    "wof:name":"Beo",
    "wof:placetype":"venue"
},
  "geometry": {"coordinates":[5.092375,51.569019],"type":"Point"}
}