{
  "type": "Feature",
  "properties": {
    "iso:country":"NL",
    "sg:address":"Provincialeweg 71",
    "sg:city":"Veldhoven",
    "sg:orig_category":"Meubelzaken, Woning- And Keukeninrichting",
    "sg:phone":"+31 40 254 2170",
    "sg:postcode":"5503 HB",
    "sg:province":"North Brabant",
    "wof:name":"Tapijt- En Gordijnenservice Veldhoven Bv",
    "wof:placetype":"venue"
},
  "geometry": {"coordinates":[5.419151,51.414387],"type":"Point"}
}