{
  "type": "Feature",
  "properties": {
    "addr:full":"Hoofdstraat 161 Hoogeveen Provincie Drenthe 7902 EG",
    "addr:housenumber":"161",
    "addr:postcode":"7902 eg",
    "addr:street":"Hoofdstraat;Provincie",
    "iso:country":"NL",
    "sg:address":"Hoofdstraat 161",
    "sg:city":"Hoogeveen",
    "sg:orig_category":"Boekhouders",
    "sg:phone":"+31 528 279 539",
    "sg:postcode":"7902 EG",
    "sg:province":"Provincie Drenthe",
    "wof:name":"Administratiekantoor Van Es",
    "wof:placetype":"venue"
},
  "geometry": {"coordinates":[6.477955,52.723026],"type":"Point"}
}