{
  "type": "Feature",
  "properties": {
    "iso:country":"NL",
    "sg:address":"Ardennenln 5",
    "sg:city":"Venray",
    "sg:orig_category":"Vertaalbureaus",
    "sg:phone":"+31 478 550 151",
    "sg:postcode":"5801 PP",
    "sg:province":"Limburg",
    "wof:name":"Slavia",
    "wof:placetype":"venue"
},
  "geometry": {"coordinates":[5.956198,51.518387],"type":"Point"}
}