{
  "type": "Feature",
  "properties": {
    "addr:full":"Alinghoek 9 Drouwen Drenthe 9533 PD",
    "addr:housenumber":"9",
    "addr:postcode":"9533 pd",
    "addr:street":"Alinghoek",
    "iso:country":"NL",
    "sg:address":"Alinghoek 9",
    "sg:city":"Drouwen",
    "sg:orig_category":"Adviesbureaus Economie",
    "sg:phone":"+31 599 565 225",
    "sg:postcode":"9533 PD",
    "sg:province":"Drenthe",
    "wof:name":"Albatros Bv",
    "wof:placetype":"venue"
},
  "geometry": {"coordinates":[6.795952,52.954697],"type":"Point"}
}