{
  "type": "Feature",
  "properties": {
    "addr:full":"Kastanjeln 86 Enkhuizen North Holland 1602 SM",
    "addr:housenumber":"86",
    "addr:postcode":"1602 sm",
    "addr:street":"Kastanjeln",
    "iso:country":"NL",
    "sg:address":"Kastanjeln 86",
    "sg:city":"Enkhuizen",
    "sg:orig_category":"Schippers",
    "sg:phone":"+31 228 315 176",
    "sg:postcode":"1602 SM",
    "sg:province":"North Holland",
    "wof:name":"Zwart Sss, De",
    "wof:placetype":"venue"
},
  "geometry": {"coordinates":[5.27837,52.708103],"type":"Point"}
}