{
  "type": "Feature",
  "properties": {
    "addr:full":"Slachthuispln 25 S Gravenhage South Holland 2521 EC",
    "addr:housenumber":"25",
    "addr:postcode":"2521 ec",
    "addr:street":"Slachthuispln;S Gravenhage",
    "iso:country":"NL",
    "sg:address":"Slachthuispln 25",
    "sg:city":"S Gravenhage",
    "sg:orig_category":"Gemeentelijke Informatie",
    "sg:phone":"+31 70 353 7700",
    "sg:postcode":"2521 EC",
    "sg:province":"South Holland",
    "wof:name":"Stadsdeelkantoor Laak",
    "wof:placetype":"venue"
},
  "geometry": {"coordinates":[4.32071,52.062988],"type":"Point"}
}