{
  "type": "Feature",
  "properties": {
    "addr:full":"A M De Jongstraat 32 Spijkenisse Zuid-Holland 3202 AD",
    "addr:housenumber":"32",
    "addr:postcode":"3202 ad",
    "addr:street":"A M De Jongstraat",
    "iso:country":"NL",
    "sg:address":"A M De Jongstraat 32",
    "sg:city":"Spijkenisse",
    "sg:orig_category":"Loodgieterswerk, Verwarming And Sanitaire Installaties",
    "sg:phone":"+31 181 618 287",
    "sg:postcode":"3202 AD",
    "sg:province":"Zuid-Holland",
    "wof:name":"M. Vercouteren Installatiebedrijf",
    "wof:placetype":"venue"
},
  "geometry": {"coordinates":[4.310698,51.85313],"type":"Point"}
}