{
  "type": "Feature",
  "properties": {
    "addr:full":"Nassauln 62 Ryen North Brabant 5121 BC",
    "addr:housenumber":"62",
    "addr:postcode":"5121 bc",
    "addr:street":"Nassauln",
    "iso:country":"NL",
    "sg:address":"Nassauln 62",
    "sg:city":"Ryen",
    "sg:orig_category":"Verenigingen En Stichtingen",
    "sg:phone":"+31 161 227 197",
    "sg:postcode":"5121 BC",
    "sg:province":"North Brabant",
    "wof:name":"Oase",
    "wof:placetype":"venue"
},
  "geometry": {"coordinates":[4.9197,51.588017],"type":"Point"}
}