{
  "type": "Feature",
  "properties": {
    "iso:country":"NL",
    "sg:address":"Transportwei 2",
    "sg:city":"Joure",
    "sg:orig_category":"Hefwerktuigen",
    "sg:phone":"+31 513 481 122",
    "sg:postcode":"8501 ZP",
    "sg:province":"Friesland",
    "sg:website":"http://www.bijlsma.nl",
    "wof:name":"Bijlsma Bv",
    "wof:placetype":"venue"
},
  "geometry": {"coordinates":[5.81467,52.961315],"type":"Point"}
}