{
  "type": "Feature",
  "properties": {
    "iso:country":"NL",
    "sg:address":"Dorpsstr 15",
    "sg:city":"Slyk Ewyk",
    "sg:orig_category":"Verenigingsgebouwen",
    "sg:phone":"+31 481 481 519",
    "sg:postcode":"6677 PG",
    "sg:province":"Gelderland",
    "wof:name":"Beatrix",
    "wof:placetype":"venue"
},
  "geometry": {"coordinates":[5.789779,51.886604],"type":"Point"}
}