{
  "type": "Feature",
  "properties": {
    "iso:country":"NL",
    "sg:address":"Vordenseweg 4",
    "sg:city":"Hengelo Gld",
    "sg:orig_category":"Wegen And Sportterreinen",
    "sg:phone":"+31 575 462 150",
    "sg:postcode":"7255 BW",
    "sg:province":"Gelderland",
    "wof:name":"Wolsink Straatmakers",
    "wof:placetype":"venue"
},
  "geometry": {"coordinates":[6.3069839478,52.0549468994],"type":"Point"}
}