{
  "type": "Feature",
  "properties": {
    "addr:full":"Sassenstraat 50 Zwolle NL.08 8011 PC",
    "addr:housenumber":"50",
    "addr:postcode":"8011 pc",
    "addr:street":"Sassenstraat",
    "iso:country":"NL",
    "sg:address":"Sassenstraat 50",
    "sg:city":"Zwolle",
    "sg:orig_category":"Kappers",
    "sg:phone":"+31 38 421 0748",
    "sg:postcode":"8011 PC",
    "sg:province":"NL.08",
    "wof:name":"Kapsalon Van Der Worp",
    "wof:placetype":"venue"
},
  "geometry": {"coordinates":[6.0946121216,52.5106544495],"type":"Point"}
}