{
  "type": "Feature",
  "properties": {
    "addr:full":"Spui 5 Edam Noord-Holland 1135 BA",
    "addr:housenumber":"5",
    "addr:postcode":"1135 ba",
    "addr:street":"Spui",
    "iso:country":"NL",
    "sg:address":"Spui 5",
    "sg:city":"Edam",
    "sg:orig_category":"Opticiens",
    "sg:phone":"+31 299 315 057",
    "sg:postcode":"1135 BA",
    "sg:province":"Noord-Holland",
    "wof:name":"Ton De Graaf Optiek",
    "wof:placetype":"venue"
},
  "geometry": {"coordinates":[5.0483422279,52.5126495361],"type":"Point"}
}