{
  "type": "Feature",
  "properties": {
    "iso:country":"NL",
    "sg:address":"Markt 33",
    "sg:city":"Sittard",
    "sg:orig_category":"Wasmachines En Wasdrogers - Onderhoud En Reparatie",
    "sg:phone":"+31 46 411 1684",
    "sg:postcode":"6131 EL",
    "sg:province":"Limburg",
    "wof:name":"Onderdelenshop Sittard",
    "wof:placetype":"venue"
},
  "geometry": {"coordinates":[5.8708090782,50.9982261658],"type":"Point"}
}