{
  "type": "Feature",
  "properties": {
    "addr:full":"Hoofdwg 271 Hoofddorp North Holland 2131 LK",
    "addr:housenumber":"271",
    "addr:postcode":"2131 lk",
    "iso:country":"NL",
    "sg:address":"Hoofdwg 271",
    "sg:city":"Hoofddorp",
    "sg:orig_category":"Bloemen En Planten",
    "sg:phone":"+31 23 555 1604",
    "sg:postcode":"2131 LK",
    "sg:province":"North Holland",
    "wof:name":"Viooltje, Het",
    "wof:placetype":"venue"
},
  "geometry": {"coordinates":[4.735452,52.335861],"type":"Point"}
}