{
  "type": "Feature",
  "properties": {
    "iso:country":"NL",
    "sg:address":"Dorpsstr 109",
    "sg:city":"Putten",
    "sg:classifiers":[
        {
            "category":"Retail",
            "subcategory":"Auto Repair",
            "type":"Services"
        }
    ],
    "sg:phone":"+31 341 455 593",
    "sg:postcode":"3881 BC",
    "sg:province":"Gelderland",
    "sg:tags":[
        "garage"
    ],
    "wof:name":"Rakhorst Autoservice",
    "wof:placetype":"venue"
},
  "geometry": {"coordinates":[5.60046,52.259998],"type":"Point"}
}