{
  "type": "Feature",
  "properties": {
    "addr:full":"Den Hof 29 Nistelrode North Brabant 5388 GN",
    "addr:housenumber":"29",
    "addr:postcode":"5388 gn",
    "addr:street":"Den Hof",
    "iso:country":"NL",
    "sg:address":"Den Hof 29",
    "sg:city":"Nistelrode",
    "sg:orig_category":"Vertalers",
    "sg:phone":"+31 412 617 006",
    "sg:postcode":"5388 GN",
    "sg:province":"North Brabant",
    "wof:name":"Toptaal",
    "wof:placetype":"venue"
},
  "geometry": {"coordinates":[5.559584,51.703682],"type":"Point"}
}