{
  "type": "Feature",
  "properties": {
    "addr:full":"Admiraliteitskd 50 Rotterdam Zuid-Holland 3063 ED",
    "addr:housenumber":"50",
    "addr:postcode":"3063 ed",
    "addr:street":"Admiraliteitskd",
    "iso:country":"NL",
    "sg:address":"Admiraliteitskd 50",
    "sg:city":"Rotterdam",
    "sg:orig_category":"Pensioenen",
    "sg:phone":"+31 10 452 7071",
    "sg:postcode":"3063 ED",
    "sg:province":"Zuid-Holland",
    "wof:name":"Assudex Bv",
    "wof:placetype":"venue"
},
  "geometry": {"coordinates":[4.503853,51.921436],"type":"Point"}
}