{
  "type": "Feature",
  "properties": {
    "addr:full":"Turfsingel 38 Groningen Groningen 9712 KR",
    "addr:housenumber":"38",
    "addr:postcode":"9712 kr",
    "addr:street":"Turfsingel",
    "iso:country":"NL",
    "sg:address":"Turfsingel 38",
    "sg:city":"Groningen",
    "sg:orig_category":"Fietshandelaren",
    "sg:phone":"+31 50 311 8085",
    "sg:postcode":"9712 KR",
    "sg:province":"Groningen",
    "wof:name":"Wheels Service Shop",
    "wof:placetype":"venue"
},
  "geometry": {"coordinates":[6.567856,53.222355],"type":"Point"}
}