{
  "type": "Feature",
  "properties": {
    "iso:country":"NL",
    "sg:address":"Postbus 440",
    "sg:city":"Raamsdonksveer",
    "sg:orig_category":"Verzekeringen - Verzekeringskantoren",
    "sg:phone":"+31 162 521 855",
    "sg:postcode":"4940 AK",
    "sg:province":"North Brabant",
    "wof:name":"Eerste Dordrechtse Ass Societeit Bv",
    "wof:placetype":"venue"
},
  "geometry": {"coordinates":[4.8749,51.695019],"type":"Point"}
}