{
  "type": "Feature",
  "properties": {
    "addr:full":"Landaaswg 8 Woudenberg Utrecht 3931 GA",
    "addr:housenumber":"8",
    "addr:postcode":"3931 ga",
    "addr:street":"Landaaswg",
    "iso:country":"NL",
    "sg:address":"Landaaswg 8",
    "sg:city":"Woudenberg",
    "sg:orig_category":"Open Haarden",
    "sg:phone":"+31 33 286 4091",
    "sg:postcode":"3931 GA",
    "sg:province":"Utrecht",
    "wof:name":"Home Fire",
    "wof:placetype":"venue"
},
  "geometry": {"coordinates":[5.449066,52.079426],"type":"Point"}
}