{
  "type": "Feature",
  "properties": {
    "addr:full":"Foijingaweg 100 Kollumerpomp Friesland 9293 LP",
    "addr:housenumber":"100",
    "addr:postcode":"9293 lp",
    "addr:street":"Foijingaweg",
    "iso:country":"NL",
    "sg:address":"Foijingaweg 100",
    "sg:city":"Kollumerpomp",
    "sg:orig_category":"Autokeuringen",
    "sg:phone":"+31 511 408 633",
    "sg:postcode":"9293 LP",
    "sg:province":"Friesland",
    "wof:name":"Vakgarage Kooistra",
    "wof:placetype":"venue"
},
  "geometry": {"coordinates":[6.195873,53.302273],"type":"Point"}
}