{
  "type": "Feature",
  "properties": {
    "iso:country":"NL",
    "sg:address":"Willem Lodewijkstraat 14",
    "sg:city":"Bourtange",
    "sg:classifiers":[
        {
            "category":"Bakery",
            "type":"Food & Drink"
        }
    ],
    "sg:phone":"+31 599 354 617",
    "sg:postcode":"9545 PB",
    "sg:province":"Groningen",
    "sg:tags":[
        "brood",
        "banket"
    ],
    "wof:name":"J. Meendering",
    "wof:placetype":"venue"
},
  "geometry": {"coordinates":[7.187077,53.009186],"type":"Point"}
}