{
  "type": "Feature",
  "properties": {
    "addr:full":"Zevenend 29 Laren Nh Noord-Holland 1251 RL",
    "addr:housenumber":"29",
    "addr:postcode":"1251 rl",
    "addr:street":"Zevenend",
    "iso:country":"NL",
    "sg:address":"Zevenend 29",
    "sg:city":"Laren Nh",
    "sg:orig_category":"Woninginrichting",
    "sg:phone":"+31 35 538 1847",
    "sg:postcode":"1251 RL",
    "sg:province":"Noord-Holland",
    "sg:website":"http://www.bahnthai.nl",
    "wof:name":"Bahn Thai",
    "wof:placetype":"venue"
},
  "geometry": {"coordinates":[5.2278299332,52.2533950806],"type":"Point"}
}