{
  "type": "Feature",
  "properties": {
    "iso:country":"NL",
    "sg:address":"St. Annastraat 42",
    "sg:city":"Nijmegen",
    "sg:orig_category":"Fietshandelaren",
    "sg:phone":"+31 24 323 0158",
    "sg:postcode":"6524 GE",
    "sg:province":"Gelderland",
    "wof:name":"Wheels Fietskoopjeshal",
    "wof:placetype":"venue"
},
  "geometry": {"coordinates":[5.859872,51.839306],"type":"Point"}
}