{
  "type": "Feature",
  "properties": {
    "iso:country":"NL",
    "sg:address":"Noorderpoort 7",
    "sg:city":"Venlo",
    "sg:orig_category":"Juridische Adviseurs",
    "sg:phone":"+31 77 320 1920",
    "sg:postcode":"5916 PJ",
    "sg:province":"Limburg",
    "sg:website":"http://www.huysvlaminckx.nl",
    "wof:name":"Vlaminckx",
    "wof:placetype":"venue"
},
  "geometry": {"coordinates":[6.175049,51.392509],"type":"Point"}
}