{
  "type": "Feature",
  "properties": {
    "addr:full":"Achterdyk 31 Helmond Noord-Brabant 5705 CB",
    "addr:housenumber":"31",
    "addr:postcode":"5705 cb",
    "addr:street":"Achterdyk",
    "iso:country":"NL",
    "sg:address":"Achterdyk 31",
    "sg:city":"Helmond",
    "sg:orig_category":"Adviesbureaus Bedrijfsorganisatie",
    "sg:phone":"+31 492 553 353",
    "sg:postcode":"5705 CB",
    "sg:province":"Noord-Brabant",
    "wof:name":"Muskens Industries Bv",
    "wof:placetype":"venue"
},
  "geometry": {"coordinates":[5.658284,51.482239],"type":"Point"}
}