{
  "type": "Feature",
  "properties": {
    "addr:full":"Anjerdreef 21 Berkel En Rodenrijs Zuid-Holland 2651 XR",
    "addr:housenumber":"21",
    "addr:postcode":"2651 xr",
    "addr:street":"Anjerdreef",
    "iso:country":"NL",
    "sg:address":"Anjerdreef 21",
    "sg:city":"Berkel En Rodenrijs",
    "sg:orig_category":"Bloemen And Planten Gh",
    "sg:phone":"+31 10 511 4249",
    "sg:postcode":"2651 XR",
    "sg:province":"Zuid-Holland",
    "wof:name":"F.A. Blauw",
    "wof:placetype":"venue"
},
  "geometry": {"coordinates":[4.46385,51.984024],"type":"Point"}
}