{
  "type": "Feature",
  "properties": {
    "addr:full":"Dorpsstraat 62 Bemmel Gelderland 6681 BP",
    "addr:housenumber":"62",
    "addr:postcode":"6681 bp",
    "addr:street":"Dorpsstraat;Gelderland",
    "iso:country":"NL",
    "sg:address":"Dorpsstraat 62",
    "sg:city":"Bemmel",
    "sg:orig_category":"Advocaten And Juridische Adviseurs",
    "sg:phone":"+31 481 464 432",
    "sg:postcode":"6681 BP",
    "sg:province":"Gelderland",
    "wof:name":"Advocatenkantoor Hanssen Hermsen Heerink",
    "wof:placetype":"venue"
},
  "geometry": {"coordinates":[5.897417,51.888973],"type":"Point"}
}