{
  "type": "Feature",
  "properties": {
    "iso:country":"NL",
    "sg:address":"Heuvel 74",
    "sg:city":"Geldrop",
    "sg:orig_category":"Verzekeringen - Verzekeringskantoren",
    "sg:phone":"+31 40 848 1830",
    "sg:postcode":"5664 HM",
    "sg:province":"North Brabant",
    "wof:name":"Aa Hypozeker Bv",
    "wof:placetype":"venue"
},
  "geometry": {"coordinates":[5.560038,51.422562],"type":"Point"}
}