{
  "type": "Feature",
  "properties": {
    "iso:country":"NL",
    "sg:address":"Heinsbergerwg 18",
    "sg:city":"Melick",
    "sg:orig_category":"Verzekeringen - Verzekeringskantoren",
    "sg:phone":"+31 475 532 300",
    "sg:postcode":"6074 AD",
    "sg:province":"Limburg",
    "wof:name":"Heemels",
    "wof:placetype":"venue"
},
  "geometry": {"coordinates":[6.00642,51.15443],"type":"Point"}
}