{
  "type": "Feature",
  "properties": {
    "addr:full":"Veenwg 35 Apeldoorn Gelderland 7336 AE",
    "addr:housenumber":"35",
    "addr:postcode":"7336 ae",
    "addr:street":"Veenwg;Gelderland",
    "iso:country":"NL",
    "sg:address":"Veenwg 35",
    "sg:city":"Apeldoorn",
    "sg:orig_category":"Onderhoudswerken",
    "sg:phone":"+31 55 542 1066",
    "sg:postcode":"7336 AE",
    "sg:province":"Gelderland",
    "wof:name":"Bob Onderhoudsbedrijf",
    "wof:placetype":"venue"
},
  "geometry": {"coordinates":[5.946104,52.200211],"type":"Point"}
}