{
  "type": "Feature",
  "properties": {
    "addr:full":"Fred. V/D Paltshof 32 Rhenen Utrecht 3911  L",
    "addr:housenumber":"d;32",
    "addr:postcode":"3911 l",
    "addr:street":"Fred.;Paltshof",
    "iso:country":"NL",
    "sg:address":"Fred. V/D Paltshof 32",
    "sg:city":"Rhenen",
    "sg:orig_category":"Boekenuitgeverijen",
    "sg:phone":"+31 317 612 164",
    "sg:postcode":"3911  L",
    "sg:province":"Utrecht",
    "wof:name":"Bruna",
    "wof:placetype":"venue"
},
  "geometry": {"coordinates":[5.567005,51.957603],"type":"Point"}
}