{
  "type": "Feature",
  "properties": {
    "addr:full":"Oosteinde 16 Voorburg Zuid-Holland 2271 EH",
    "addr:housenumber":"16",
    "addr:postcode":"2271 eh",
    "addr:street":"Oosteinde",
    "iso:country":"NL",
    "sg:address":"Oosteinde 16",
    "sg:city":"Voorburg",
    "sg:orig_category":"Sportverenigingen En Ontspannings- Verenigingen",
    "sg:phone":"+31 70 386 1483",
    "sg:postcode":"2271 EH",
    "sg:province":"Zuid-Holland",
    "wof:name":"Forum Hadriani",
    "wof:placetype":"venue"
},
  "geometry": {"coordinates":[4.369959,52.070393],"type":"Point"}
}