{
  "type": "Feature",
  "properties": {
    "iso:country":"NL",
    "sg:address":"Amstel 256",
    "sg:city":"Amsterdam",
    "sg:orig_category":"Werving En Selectie",
    "sg:phone":"+31 20 489 2706",
    "sg:postcode":"1017 AL",
    "sg:province":"Noord-Holland",
    "sg:website":"http://www.vb-p.nl",
    "wof:name":"Beuningen En Partners, Van",
    "wof:placetype":"venue"
},
  "geometry": {"coordinates":[4.9013462067,52.3635902405],"type":"Point"}
}