{
  "type": "Feature",
  "properties": {
    "iso:country":"NL",
    "sg:address":"Kalmoesln 35",
    "sg:city":"Rynsaterwoude",
    "sg:orig_category":"Loonbedrijven",
    "sg:phone":"+31 172 507 804",
    "sg:postcode":"2465 BL",
    "sg:province":"Zuid-Holland",
    "wof:name":"Flikweert Vof, R",
    "wof:placetype":"venue"
},
  "geometry": {"coordinates":[4.671365,52.196033],"type":"Point"}
}