{
  "type": "Feature",
  "properties": {
    "addr:full":"Prinses Julianaplein 16 Goor NL.08 7471 AZ",
    "addr:housenumber":"16;nl.08",
    "addr:postcode":"7471",
    "addr:street":"Prinses Julianaplein",
    "iso:country":"NL",
    "sg:address":"Prinses Julianaplein 16",
    "sg:city":"Goor",
    "sg:classifiers":[
        {
            "category":"Fast Food",
            "type":"Food & Drink"
        }
    ],
    "sg:phone":"+31 547 272 492",
    "sg:postcode":"7471 AZ",
    "sg:province":"NL.08",
    "sg:tags":[
        "afhaal",
        "restaurant"
    ],
    "wof:name":"Chin. Ind. Restaurant Wing Wah",
    "wof:placetype":"venue"
},
  "geometry": {"coordinates":[6.589848,52.234386],"type":"Point"}
}