{
  "type": "Feature",
  "properties": {
    "addr:full":"Verviersstr 6A Breda North Brabant 4826 HT",
    "addr:housenumber":"6a",
    "addr:postcode":"4826 ht",
    "addr:street":"Verviersstr",
    "iso:country":"NL",
    "sg:address":"Verviersstr 6A",
    "sg:city":"Breda",
    "sg:orig_category":"Kinderopvang",
    "sg:phone":"+31 76 572 0919",
    "sg:postcode":"4826 HT",
    "sg:province":"North Brabant",
    "sg:website":"http://www.cokb.nl",
    "wof:name":"Betje Beer",
    "wof:placetype":"venue"
},
  "geometry": {"coordinates":[4.786941,51.602711],"type":"Point"}
}