{
  "type": "Feature",
  "properties": {
    "addr:full":"Alexanderstr 14 Haarlem North Holland 2011 VE",
    "addr:housenumber":"14",
    "addr:postcode":"2011",
    "addr:street":"Alexanderstr;Ve",
    "iso:country":"NL",
    "sg:address":"Alexanderstr 14",
    "sg:city":"Haarlem",
    "sg:orig_category":"Psychotherapeuten",
    "sg:phone":"+31 23 531 1482",
    "sg:postcode":"2011 VE",
    "sg:province":"North Holland",
    "wof:name":"Haaring, Drs L",
    "wof:placetype":"venue"
},
  "geometry": {"coordinates":[4.626269,52.378532],"type":"Point"}
}