{
  "type": "Feature",
  "properties": {
    "addr:full":"Piusstr 34 Tilburg Noord-Brabant 5038 WT",
    "addr:housenumber":"34",
    "addr:postcode":"5038 wt",
    "addr:street":"Piusstr",
    "iso:country":"NL",
    "sg:address":"Piusstr 34",
    "sg:city":"Tilburg",
    "sg:orig_category":"Handwerkartikelen",
    "sg:phone":"+31 13 543 4371",
    "sg:postcode":"5038 WT",
    "sg:province":"Noord-Brabant",
    "wof:name":"Rosa",
    "wof:placetype":"venue"
},
  "geometry": {"coordinates":[5.089587,51.552631],"type":"Point"}
}