{
  "type": "Feature",
  "properties": {
    "iso:country":"NL",
    "sg:address":"Heiveldstraat 58",
    "sg:city":"Kerkrade",
    "sg:orig_category":"Bloemen And Planten",
    "sg:phone":"+31 45 541 4532",
    "sg:postcode":"6466 AL",
    "sg:province":"Limburg",
    "wof:name":"Bloemsierkunst Tamara",
    "wof:placetype":"venue"
},
  "geometry": {"coordinates":[6.039996,50.863991],"type":"Point"}
}