{
  "type": "Feature",
  "properties": {
    "addr:full":"Smidsweg 24 Westmaas Zuid-Holland 3273 LK",
    "addr:housenumber":"24",
    "addr:postcode":"3273 lk",
    "addr:street":"Smidsweg",
    "iso:country":"NL",
    "sg:address":"Smidsweg 24",
    "sg:city":"Westmaas",
    "sg:orig_category":"Granen, Zaden And Diervoeders Gh",
    "sg:phone":"+31 186 573 000",
    "sg:postcode":"3273 LK",
    "sg:province":"Zuid-Holland",
    "wof:name":"Van Iperen Bv",
    "wof:placetype":"venue"
},
  "geometry": {"coordinates":[4.47034,51.789169],"type":"Point"}
}