{
  "type": "Feature",
  "properties": {
    "iso:country":"NL",
    "sg:address":"H V Soelenln 41",
    "sg:city":"S Gravenhage",
    "sg:orig_category":"Onroerende Goederen",
    "sg:phone":"+31 70 366 6562",
    "sg:postcode":"2545 EV",
    "sg:province":"Zuid-Holland",
    "wof:name":"Joshua Invest Bv",
    "wof:placetype":"venue"
},
  "geometry": {"coordinates":[4.27049,52.05093],"type":"Point"}
}