{
  "type": "Feature",
  "properties": {
    "addr:full":"Spaarnestr 111 Ymuiden Noord-Holland 1971 XC",
    "addr:housenumber":"111",
    "addr:postcode":"1971 xc",
    "iso:country":"NL",
    "sg:address":"Spaarnestr 111",
    "sg:city":"Ymuiden",
    "sg:orig_category":"Vertaalbureaus",
    "sg:phone":"+31 255 514 849",
    "sg:postcode":"1971 XC",
    "sg:province":"Noord-Holland",
    "wof:name":"A Very Tale",
    "wof:placetype":"venue"
},
  "geometry": {"coordinates":[4.617742,52.4561],"type":"Point"}
}