{
  "type": "Feature",
  "properties": {
    "iso:country":"NL",
    "sg:address":"Havendam 3",
    "sg:city":"Rhoon",
    "sg:orig_category":"Marktonderzoekbureaus",
    "sg:phone":"+31 10 416 9000",
    "sg:postcode":"3161 XB",
    "sg:province":"South Holland",
    "wof:name":"Vos Commerciele Diensten",
    "wof:placetype":"venue"
},
  "geometry": {"coordinates":[4.421424,51.849072],"type":"Point"}
}