{
  "type": "Feature",
  "properties": {
    "addr:full":"Zandenweg 3 Maren Kessel Gelderland 5398 KD",
    "addr:housenumber":"3",
    "addr:postcode":"5398 kd",
    "addr:street":"Zandenweg;Maren;Gelderland",
    "iso:country":"NL",
    "sg:address":"Zandenweg 3",
    "sg:city":"Maren Kessel",
    "sg:orig_category":"Hoger Onderwijs",
    "sg:phone":"+31 412 479 470",
    "sg:postcode":"5398 KD",
    "sg:province":"Gelderland",
    "wof:name":"Ensaid",
    "wof:placetype":"venue"
},
  "geometry": {"coordinates":[5.365668,51.76255],"type":"Point"}
}