{
  "type": "Feature",
  "properties": {
    "addr:full":"Tolbergcentrum 154 Roosendaal North Brabant 4708 HK",
    "addr:housenumber":"154",
    "addr:postcode":"4708 hk",
    "addr:street":"Tolbergcentrum",
    "iso:country":"NL",
    "sg:address":"Tolbergcentrum 154",
    "sg:city":"Roosendaal",
    "sg:orig_category":"Banken And Kredietinstellingen",
    "sg:phone":"+31 165 562 200",
    "sg:postcode":"4708 HK",
    "sg:province":"North Brabant",
    "wof:name":"Cards & Magazines",
    "wof:placetype":"venue"
},
  "geometry": {"coordinates":[4.439203,51.513412],"type":"Point"}
}