{
  "type": "Feature",
  "properties": {
    "iso:country":"NL",
    "sg:address":"Oudestr 32",
    "sg:city":"Neede",
    "sg:classifiers":[
        {
            "category":"Food & Beverages",
            "subcategory":"Bakery",
            "type":"Retail Goods"
        }
    ],
    "sg:phone":"+31 545 296 663",
    "sg:postcode":"7161 DW",
    "sg:province":"Gelderland",
    "sg:tags":[
        "pizza"
    ],
    "wof:name":"Leonardo",
    "wof:placetype":"venue"
},
  "geometry": {"coordinates":[-121.31706200000001,38.299633],"type":"Point"}
}