{
  "type": "Feature",
  "properties": {
    "addr:full":"Stoofstr 12 Yerseke Zeeland 4401 BC",
    "addr:housenumber":"12",
    "addr:postcode":"4401 bc",
    "addr:street":"Stoofstr",
    "iso:country":"NL",
    "sg:address":"Stoofstr 12",
    "sg:city":"Yerseke",
    "sg:orig_category":"Honden- En Kattentrimsalons",
    "sg:phone":"+31 113 572 949",
    "sg:postcode":"4401 BC",
    "sg:province":"Zeeland",
    "wof:name":"Zoeteweij, Hondentrimsalon I",
    "wof:placetype":"venue"
},
  "geometry": {"coordinates":[4.0425629616,51.5013046265],"type":"Point"}
}