{
  "type": "Feature",
  "properties": {
    "addr:full":"Oostln 25 Pynacker South Holland 2641 DL",
    "addr:housenumber":"25",
    "addr:postcode":"2641 dl",
    "addr:street":"Oostln;Pynacker South",
    "iso:country":"NL",
    "sg:address":"Oostln 25",
    "sg:city":"Pynacker",
    "sg:orig_category":"Makelaars En Adviseurs Onroerende Goederen",
    "sg:phone":"+31 15 369 9099",
    "sg:postcode":"2641 DL",
    "sg:province":"South Holland",
    "sg:website":"http://www.voorberg.nl",
    "wof:name":"Voorberg Bv",
    "wof:placetype":"venue"
},
  "geometry": {"coordinates":[4.425071,51.987968],"type":"Point"}
}