{
  "type": "Feature",
  "properties": {
    "addr:full":"Postbus 73 Enkhuizen Noord-Holland 1920 AB",
    "addr:housenumber":"73",
    "addr:postcode":"1920 ab",
    "addr:street":"Postbus",
    "iso:country":"NL",
    "sg:address":"Postbus 73",
    "sg:city":"Enkhuizen",
    "sg:orig_category":"Bloemen And Planten",
    "sg:phone":"+31 71 331 7492",
    "sg:postcode":"1920 AB",
    "sg:province":"Noord-Holland",
    "wof:name":"Hafafleur Bv",
    "wof:placetype":"venue"
},
  "geometry": {"coordinates":[5.29008,52.703671],"type":"Point"}
}