{
  "type": "Feature",
  "properties": {
    "addr:full":"Loolaan 18 Voorburg Zuid-Holland 2271 TN",
    "addr:housenumber":"18",
    "addr:postcode":"2271",
    "addr:street":"Loolaan",
    "iso:country":"NL",
    "sg:address":"Loolaan 18",
    "sg:city":"Voorburg",
    "sg:orig_category":"Meubelreparatie And -Restauratie",
    "sg:phone":"+31 70 386 2666",
    "sg:postcode":"2271 TN",
    "sg:province":"Zuid-Holland",
    "wof:name":"J Vd Drift",
    "wof:placetype":"venue"
},
  "geometry": {"coordinates":[4.374497,52.073383],"type":"Point"}
}