{
  "type": "Feature",
  "properties": {
    "addr:full":"Postbus 618 Maastricht Limburg 6200 AP",
    "addr:housenumber":"618",
    "addr:postcode":"6200 ap",
    "addr:street":"Postbus",
    "iso:country":"NL",
    "sg:address":"Postbus 618",
    "sg:city":"Maastricht",
    "sg:orig_category":"Kinderactiviteiten",
    "sg:phone":"+31 43 326 1018",
    "sg:postcode":"6200 AP",
    "sg:province":"Limburg",
    "wof:name":"Hobbyclub",
    "wof:placetype":"venue"
},
  "geometry": {"coordinates":[5.68726,50.84985],"type":"Point"}
}