{
  "type": "Feature",
  "properties": {
    "addr:full":"Veldzigtlaan 1 Haarlem Noord-Holland 2015 CD",
    "addr:housenumber":"1",
    "addr:postcode":"2015 cd",
    "addr:street":"Veldzigtlaan",
    "iso:country":"NL",
    "sg:address":"Veldzigtlaan 1",
    "sg:city":"Haarlem",
    "sg:orig_category":"Hoger Onderwijs",
    "sg:phone":"+31 23 541 2612",
    "sg:postcode":"2015 CD",
    "sg:province":"Noord-Holland",
    "wof:name":"Hogeschool Haarlem Sector Techniek En Gezondheidsz",
    "wof:placetype":"venue"
},
  "geometry": {"coordinates":[4.613675,52.38813],"type":"Point"}
}