{
  "type": "Feature",
  "properties": {
    "addr:full":"A De M Vispoort 30 Deventer Overijssel 7411 SL",
    "addr:housenumber":"30",
    "addr:postcode":"7411 sl",
    "addr:street":"A De M Vispoort",
    "iso:country":"NL",
    "sg:address":"A De M Vispoort 30",
    "sg:city":"Deventer",
    "sg:orig_category":"Meubelstoffering",
    "sg:phone":"+31 570 600 701",
    "sg:postcode":"7411 SL",
    "sg:province":"Overijssel",
    "wof:name":"Bekendam",
    "wof:placetype":"venue"
},
  "geometry": {"coordinates":[6.159899,52.251034],"type":"Point"}
}