{
  "type": "Feature",
  "properties": {
    "addr:full":"Hazelaarpad 28 Venlo Limburg 5925 AX",
    "addr:housenumber":"28",
    "addr:postcode":"5925 ax",
    "addr:street":"Hazelaarpad",
    "iso:country":"NL",
    "sg:address":"Hazelaarpad 28",
    "sg:city":"Venlo",
    "sg:orig_category":"Goederenvervoer Over De Weg",
    "sg:phone":"+31 77 387 2273",
    "sg:postcode":"5925 AX",
    "sg:province":"Limburg",
    "wof:name":"John Weijers Transport",
    "wof:placetype":"venue"
},
  "geometry": {"coordinates":[6.129931,51.376331],"type":"Point"}
}