{
  "type": "Feature",
  "properties": {
    "addr:full":"Iabc 5311 Breda Gelderland 4814 RC",
    "addr:housenumber":"5311",
    "addr:postcode":"4814 rc",
    "addr:street":"Iabc;Gelderland",
    "iso:country":"NL",
    "sg:address":"Iabc 5311",
    "sg:city":"Breda",
    "sg:orig_category":"Fruit And Groenten Gh",
    "sg:phone":"+31 76 530 1700",
    "sg:postcode":"4814 RC",
    "sg:province":"Gelderland",
    "wof:name":"Jac. Bezemer & Zn Bv",
    "wof:placetype":"venue"
},
  "geometry": {"coordinates":[4.731353,51.586956],"type":"Point"}
}