{
  "type": "Feature",
  "properties": {
    "addr:full":"Provinc Wg Zuna 5 Zuna NL.08 7466 PJ",
    "addr:housenumber":"5;nl.08",
    "addr:postcode":"7466 pj",
    "addr:street":"Wg Zuna",
    "iso:country":"NL",
    "sg:address":"Provinc Wg Zuna 5",
    "sg:city":"Zuna",
    "sg:classifiers":[
        {
            "category":"Sports & Exercise",
            "subcategory":"Stables",
            "type":"Entertainment"
        }
    ],
    "sg:phone":"+31 548 518 671",
    "sg:postcode":"7466 PJ",
    "sg:province":"NL.08",
    "sg:tags":[
        "maneges"
    ],
    "wof:name":"Zuna Ruiters",
    "wof:placetype":"venue"
},
  "geometry": {"coordinates":[6.492979,52.337502],"type":"Point"}
}