{
  "type": "Feature",
  "properties": {
    "addr:full":"Groene Kerkwg 5 Bergambacht Zuid-Holland 2861 EA",
    "addr:housenumber":"5",
    "addr:postcode":"2861 ea",
    "addr:street":"Groene Kerkwg",
    "iso:country":"NL",
    "sg:address":"Groene Kerkwg 5",
    "sg:city":"Bergambacht",
    "sg:orig_category":"Loonbedrijven",
    "sg:phone":"+31 182 351 027",
    "sg:postcode":"2861 EA",
    "sg:province":"Zuid-Holland",
    "wof:name":"Boer, P Den",
    "wof:placetype":"venue"
},
  "geometry": {"coordinates":[4.77826,51.93055],"type":"Point"}
}