{
  "type": "Feature",
  "properties": {
    "addr:full":"Waleweinln 199 Geldrop Noord-Brabant 5665 CJ",
    "addr:housenumber":"199",
    "addr:postcode":"5665 cj",
    "iso:country":"NL",
    "sg:address":"Waleweinln 199",
    "sg:city":"Geldrop",
    "sg:orig_category":"Verzekeringen - Verzekeringskantoren",
    "sg:phone":"+31 40 285 8559",
    "sg:postcode":"5665 CJ",
    "sg:province":"Noord-Brabant",
    "wof:name":"Kieft",
    "wof:placetype":"venue"
},
  "geometry": {"coordinates":[5.567832,51.41568],"type":"Point"}
}