{
  "type": "Feature",
  "properties": {
    "addr:full":"Snipperlingsdk 56 Deventer Overijssel 7417 BK",
    "addr:housenumber":"56",
    "addr:postcode":"7417 bk",
    "addr:street":"Snipperlingsdk",
    "iso:country":"NL",
    "sg:address":"Snipperlingsdk 56",
    "sg:city":"Deventer",
    "sg:orig_category":"Keukens",
    "sg:phone":"+31 570 634 629",
    "sg:postcode":"7417 BK",
    "sg:province":"Overijssel",
    "wof:name":"Kiffen Montagebedrijf",
    "wof:placetype":"venue"
},
  "geometry": {"coordinates":[6.186629,52.251919],"type":"Point"}
}