{
  "type": "Feature",
  "properties": {
    "addr:full":"Van Brederodestraat 30 Noordeloos Zuid-Holland 4225 RD",
    "addr:housenumber":"30",
    "addr:postcode":"4225 rd",
    "addr:street":"Van Brederodestraat",
    "iso:country":"NL",
    "sg:address":"Van Brederodestraat 30",
    "sg:city":"Noordeloos",
    "sg:orig_category":"Loodgieterswerk, Verwarming And Sanitaire Installaties",
    "sg:phone":"+31 183 582 287",
    "sg:postcode":"4225 RD",
    "sg:province":"Zuid-Holland",
    "wof:name":"F.A. Van Veen",
    "wof:placetype":"venue"
},
  "geometry": {"coordinates":[4.94088,51.905994],"type":"Point"}
}