{
  "type": "Feature",
  "properties": {
    "addr:full":"Aaksterveld 2 Ameide Zuid-Holland 4233 GC",
    "addr:housenumber":"2",
    "addr:postcode":"4233 gc",
    "addr:street":"Aaksterveld",
    "iso:country":"NL",
    "sg:address":"Aaksterveld 2",
    "sg:city":"Ameide",
    "sg:orig_category":"Wasmachines En Wasdrogers",
    "sg:phone":"+31 183 601 271",
    "sg:postcode":"4233 GC",
    "sg:province":"Zuid-Holland",
    "wof:name":"Pek & Zn, Fa N",
    "wof:placetype":"venue"
},
  "geometry": {"coordinates":[4.9624838829,51.9542770386],"type":"Point"}
}