{
  "type": "Feature",
  "properties": {
    "addr:full":"Broekstr 16 Zelhem Gelderland 7021 JX",
    "addr:housenumber":"16",
    "addr:postcode":"7021 jx",
    "addr:street":"Broekstr;Gelderland",
    "iso:country":"NL",
    "sg:address":"Broekstr 16",
    "sg:city":"Zelhem",
    "sg:orig_category":"Pluimveebedrijven En -Handelaren",
    "sg:phone":"+31 314 335 749",
    "sg:postcode":"7021 JX",
    "sg:province":"Gelderland",
    "wof:name":"Bouwens Bv, Gebr",
    "wof:placetype":"venue"
},
  "geometry": {"coordinates":[6.350575,52.006802],"type":"Point"}
}