{
  "type": "Feature",
  "properties": {
    "addr:full":"Heuvelstr 1A Tilburg North Brabant 5038 AA",
    "addr:housenumber":"1a",
    "addr:postcode":"5038 aa",
    "addr:street":"Heuvelstr",
    "iso:country":"NL",
    "sg:address":"Heuvelstr 1A",
    "sg:city":"Tilburg",
    "sg:orig_category":"Sportschoenen - Winkels",
    "sg:phone":"+31 13 581 0202",
    "sg:postcode":"5038 AA",
    "sg:province":"North Brabant",
    "wof:name":"Coach",
    "wof:placetype":"venue"
},
  "geometry": {"coordinates":[5.089293,51.557175],"type":"Point"}
}