{
  "type": "Feature",
  "properties": {
    "addr:full":"Delfwg 79 Noordwykerhout Zuid-Holland 2211 VK",
    "addr:housenumber":"79",
    "addr:postcode":"2211 vk",
    "addr:street":"Delfwg",
    "iso:country":"NL",
    "sg:address":"Delfwg 79",
    "sg:city":"Noordwykerhout",
    "sg:orig_category":"Bloembollen - Groothandel",
    "sg:phone":"+31 252 414 023",
    "sg:postcode":"2211 VK",
    "sg:province":"Zuid-Holland",
    "wof:name":"Vlugt & Zn, Fa C Van Der",
    "wof:placetype":"venue"
},
  "geometry": {"coordinates":[4.534803,52.280399],"type":"Point"}
}