{
  "type": "Feature",
  "properties": {
    "addr:full":"Dorppolderwg 12 Schipluiden Zuid-Holland 2636 HE",
    "addr:housenumber":"12",
    "addr:postcode":"2636 he",
    "addr:street":"Dorppolderwg",
    "iso:country":"NL",
    "sg:address":"Dorppolderwg 12",
    "sg:city":"Schipluiden",
    "sg:orig_category":"Bloemen En Planten",
    "sg:phone":"+31 15 380 9502",
    "sg:postcode":"2636 HE",
    "sg:province":"Zuid-Holland",
    "wof:name":"Wijk, A G M Van",
    "wof:placetype":"venue"
},
  "geometry": {"coordinates":[4.302543,51.979794],"type":"Point"}
}