{
  "type": "Feature",
  "properties": {
    "iso:country":"NL",
    "sg:address":"Geversstr 43",
    "sg:city":"Oegstgeest",
    "sg:orig_category":"Adviesbureaus Bouwkunde",
    "sg:phone":"+31 71 515 2459",
    "sg:postcode":"2341 GA",
    "sg:province":"Zuid-Holland",
    "sg:website":"http://www.vanvelsen-chiang.nl",
    "wof:name":"Velsen & Chiang, Van",
    "wof:placetype":"venue"
},
  "geometry": {"coordinates":[4.466833,52.177742],"type":"Point"}
}