{
  "type": "Feature",
  "properties": {
    "iso:country":"NL",
    "sg:address":"Hooghiemstrapln 96",
    "sg:city":"Utrecht",
    "sg:orig_category":"Vertaalbureaus",
    "sg:phone":"+31 30 271 4224",
    "sg:postcode":"3514 AX",
    "sg:province":"Utrecht",
    "wof:name":"T-Bizz",
    "wof:placetype":"venue"
},
  "geometry": {"coordinates":[5.125126,52.098324],"type":"Point"}
}