{
  "type": "Feature",
  "properties": {
    "addr:full":"Industrieweg 2 Nieuwegein Utrecht 3433 NL",
    "addr:housenumber":"2",
    "addr:postcode":"3433 nl",
    "addr:street":"Industrieweg",
    "iso:country":"NL",
    "sg:address":"Industrieweg 2",
    "sg:city":"Nieuwegein",
    "sg:orig_category":"Autokeuringen",
    "sg:phone":"+31 30 606 6383",
    "sg:postcode":"3433 NL",
    "sg:province":"Utrecht",
    "wof:name":"Van Kuik Services",
    "wof:placetype":"venue"
},
  "geometry": {"coordinates":[5.101868,52.011993],"type":"Point"}
}