{
  "type": "Feature",
  "properties": {
    "addr:full":"Ulvenhoutselaan 147 Breda Noord-Brabant 4834 ME",
    "addr:housenumber":"147",
    "addr:postcode":"4834 me",
    "addr:street":"Ulvenhoutselaan",
    "iso:country":"NL",
    "sg:address":"Ulvenhoutselaan 147",
    "sg:city":"Breda",
    "sg:orig_category":"Etaleurs And Showroominrichters",
    "sg:phone":"+31 76 560 0503",
    "sg:postcode":"4834 ME",
    "sg:province":"Noord-Brabant",
    "wof:name":"Etalagestudio Marianne Roos",
    "wof:placetype":"venue"
},
  "geometry": {"coordinates":[4.792632,51.557247],"type":"Point"}
}