{
  "type": "Feature",
  "properties": {
    "addr:full":"Oostmyzerdk 2 Schermerhorn Noord-Holland 1636 WC",
    "addr:housenumber":"2",
    "addr:postcode":"1636 wc",
    "addr:street":"Oostmyzerdk",
    "iso:country":"NL",
    "sg:address":"Oostmyzerdk 2",
    "sg:city":"Schermerhorn",
    "sg:orig_category":"Administratie- En Boekhoudkantoren",
    "sg:phone":"+31 6 53950871",
    "sg:postcode":"1636 WC",
    "sg:province":"Noord-Holland",
    "wof:name":"Boekwerk",
    "wof:placetype":"venue"
},
  "geometry": {"coordinates":[4.900145,52.602299],"type":"Point"}
}