{
  "type": "Feature",
  "properties": {
    "addr:full":"Sarphatipk 98 Amsterdam North Holland 1073 EC",
    "addr:housenumber":"98",
    "addr:postcode":"1073 ec",
    "addr:street":"Sarphatipk",
    "iso:country":"NL",
    "sg:address":"Sarphatipk 98",
    "sg:city":"Amsterdam",
    "sg:orig_category":"Kamerverhuur En -Bemiddeling",
    "sg:phone":"+31 20 470 4488",
    "sg:postcode":"1073 EC",
    "sg:province":"North Holland",
    "wof:name":"Alpha Rental Housing",
    "wof:placetype":"venue"
},
  "geometry": {"coordinates":[4.8972201347,52.3536491394],"type":"Point"}
}