{
  "type": "Feature",
  "properties": {
    "iso:country":"NL",
    "sg:address":"Quellynstr 62",
    "sg:city":"Amsterdam",
    "sg:orig_category":"Verenigingsgebouwen",
    "sg:phone":"+31 20 662 0667",
    "sg:postcode":"1072 XV",
    "sg:province":"Noord-Holland",
    "wof:name":"Quellijn, Het",
    "wof:placetype":"venue"
},
  "geometry": {"coordinates":[4.889154,52.356724],"type":"Point"}
}