{
  "type": "Feature",
  "properties": {
    "addr:full":"Kortlandplaats 4 Arnhem Gelderland 6843 HA",
    "addr:housenumber":"4",
    "addr:postcode":"6843 ha",
    "addr:street":"Kortlandplaats",
    "iso:country":"NL",
    "sg:address":"Kortlandplaats 4",
    "sg:city":"Arnhem",
    "sg:orig_category":"Paramedische Behandelingen",
    "sg:phone":"+31 26 383 0074",
    "sg:postcode":"6843 HA",
    "sg:province":"Gelderland",
    "wof:name":"W Horlings Podotherapeut",
    "wof:placetype":"venue"
},
  "geometry": {"coordinates":[5.8576,51.956928],"type":"Point"}
}