{
  "type": "Feature",
  "properties": {
    "addr:full":"Hamersveldsewg 6 Leusden Utrecht 3833 GP",
    "addr:housenumber":"6",
    "addr:postcode":"3833 gp",
    "addr:street":"Hamersveldsewg",
    "iso:country":"NL",
    "sg:address":"Hamersveldsewg 6",
    "sg:city":"Leusden",
    "sg:orig_category":"Automaterialen En Gereedschappen",
    "sg:phone":"+31 33 494 8852",
    "sg:postcode":"3833 GP",
    "sg:province":"Utrecht",
    "sg:website":"http://www.brezan.nl",
    "wof:name":"Brezan",
    "wof:placetype":"venue"
},
  "geometry": {"coordinates":[5.426829,52.136204],"type":"Point"}
}