{
  "type": "Feature",
  "properties": {
    "addr:full":"Boulev Heuvelink 170 Arnhem Gelderland 6828 KX",
    "addr:housenumber":"170",
    "addr:postcode":"6828 kx",
    "addr:street":"Boulev Heuvelink",
    "iso:country":"NL",
    "sg:address":"Boulev Heuvelink 170",
    "sg:city":"Arnhem",
    "sg:orig_category":"Juridische Adviseurs",
    "sg:phone":"+31 26 370 9191",
    "sg:postcode":"6828 KX",
    "sg:province":"Gelderland",
    "wof:name":"Verhelst",
    "wof:placetype":"venue"
},
  "geometry": {"coordinates":[5.923086,51.980835],"type":"Point"}
}