{
  "type": "Feature",
  "properties": {
    "iso:country":"NL",
    "sg:address":"Akerstraat Noord 136",
    "sg:city":"Hoensbroek",
    "sg:orig_category":"Kappers",
    "sg:phone":"+31 45 523 1518",
    "sg:postcode":"6431 HR",
    "sg:province":"Limburg",
    "wof:name":"Kapsalon Trendline",
    "wof:placetype":"venue"
},
  "geometry": {"coordinates":[5.9355559349,50.9302864075],"type":"Point"}
}