{
  "type": "Feature",
  "properties": {
    "iso:country":"NL",
    "sg:address":"Nassaulaan 25",
    "sg:city":"Zoeterwoude",
    "sg:orig_category":"Goederenvervoer Over De Weg",
    "sg:phone":"+31 71 541 1609",
    "sg:postcode":"2382 GC",
    "sg:province":"South Holland",
    "wof:name":"R.E.H.M. Van Veen",
    "wof:placetype":"venue"
},
  "geometry": {"coordinates":[4.52594,52.142059],"type":"Point"}
}