{
  "type": "Feature",
  "properties": {
    "iso:country":"NL",
    "sg:address":"Arnhemsestrwg 45",
    "sg:city":"Rheden",
    "sg:orig_category":"Psychotherapeuten",
    "sg:phone":"+31 26 495 4428",
    "sg:postcode":"6991 AE",
    "sg:province":"Gelderland",
    "wof:name":"Stolk, A P",
    "wof:placetype":"venue"
},
  "geometry": {"coordinates":[6.03264,52.002544],"type":"Point"}
}