{
  "type": "Feature",
  "properties": {
    "iso:country":"NL",
    "sg:address":"Wederik 16",
    "sg:city":"Veenendaal",
    "sg:orig_category":"Verzekeringen - Verzekeringskantoren",
    "sg:phone":"+31 318 500 320",
    "sg:postcode":"3903 EC",
    "sg:province":"Utrecht",
    "wof:name":"Overeem",
    "wof:placetype":"venue"
},
  "geometry": {"coordinates":[5.55295,52.003082],"type":"Point"}
}