{
  "type": "Feature",
  "properties": {
    "iso:country":"NL",
    "sg:address":"Stationswg 42",
    "sg:city":"Stedum",
    "sg:orig_category":"Fotojournalisten Freelance",
    "sg:phone":"+31 596 551 922",
    "sg:postcode":"9921 PW",
    "sg:province":"Groningen",
    "wof:name":"Pitt",
    "wof:placetype":"venue"
},
  "geometry": {"coordinates":[6.688604,53.32497],"type":"Point"}
}