{
  "type": "Feature",
  "properties": {
    "addr:full":"Weibuorren 100 Ureterp Provincie Friesland 9247 BD",
    "addr:housenumber":"100",
    "addr:postcode":"9247 bd",
    "addr:street":"Weibuorren;Provincie Friesland",
    "iso:country":"NL",
    "sg:address":"Weibuorren 100",
    "sg:city":"Ureterp",
    "sg:orig_category":"Verhuur Catering-, Feest- En Evenementbenodigdheden",
    "sg:phone":"+31 512 301 778",
    "sg:postcode":"9247 BD",
    "sg:province":"Provincie Friesland",
    "wof:name":"Eetcafe It Alde Ste Bv",
    "wof:placetype":"venue"
},
  "geometry": {"coordinates":[6.172814,53.095325],"type":"Point"}
}