{
  "type": "Feature",
  "properties": {
    "addr:full":"Beekstr 41-47 Epe Gelderland 8162 HA",
    "addr:housenumber":"41-47",
    "addr:postcode":"8162 ha",
    "addr:street":"Gelderland",
    "iso:country":"NL",
    "sg:address":"Beekstr 41-47",
    "sg:city":"Epe",
    "sg:orig_category":"Verzekeringen - Verzekeringskantoren",
    "sg:phone":"+31 578 612 349",
    "sg:postcode":"8162 HA",
    "sg:province":"Gelderland",
    "sg:website":"http://www.accesnet.nl/univehgv",
    "wof:name":"Univ\u00e9 Noord-Veluwe",
    "wof:placetype":"venue"
},
  "geometry": {"coordinates":[5.97796,52.346882],"type":"Point"}
}