{
  "type": "Feature",
  "properties": {
    "addr:full":"L Delft 61 Middelburg Zeeland 4331 AL",
    "addr:housenumber":"61",
    "addr:postcode":"4331 al",
    "addr:street":"L Delft",
    "iso:country":"NL",
    "sg:address":"L Delft 61",
    "sg:city":"Middelburg",
    "sg:orig_category":"Sportschoenen - Winkels",
    "sg:phone":"+31 118 651 144",
    "sg:postcode":"4331 AL",
    "sg:province":"Zeeland",
    "wof:name":"Aktiesport",
    "wof:placetype":"venue"
},
  "geometry": {"coordinates":[3.615138,51.498695],"type":"Point"}
}