{
  "type": "Feature",
  "properties": {
    "iso:country":"NL",
    "sg:address":"Achterstraat 3",
    "sg:city":"Eindhoven",
    "sg:orig_category":"Autoreparatie And Auto-Onderhoud",
    "sg:phone":"+31 40 252 0982",
    "sg:postcode":"5614  H",
    "sg:province":"North Brabant",
    "wof:name":"A.B. Cars",
    "wof:placetype":"venue"
},
  "geometry": {"coordinates":[5.49282,51.42807],"type":"Point"}
}