{
  "type": "Feature",
  "properties": {
    "addr:full":"Voorstreek 89 Leeuwarden Provincie Friesland 8911 JM",
    "addr:housenumber":"89",
    "addr:postcode":"8911 jm",
    "addr:street":"Voorstreek;Provincie Friesland",
    "iso:country":"NL",
    "sg:address":"Voorstreek 89",
    "sg:city":"Leeuwarden",
    "sg:orig_category":"Muziekinstrumenten",
    "sg:phone":"+31 58 212 0681",
    "sg:postcode":"8911 JM",
    "sg:province":"Provincie Friesland",
    "wof:name":"Saxofoon Atelier Leeuwarden",
    "wof:placetype":"venue"
},
  "geometry": {"coordinates":[5.800635,53.204933],"type":"Point"}
}