{
  "type": "Feature",
  "properties": {
    "addr:full":"Hazeldonk 6364 Breda North Brabant 4836 LJ",
    "addr:housenumber":"6364",
    "addr:postcode":"4836 lj",
    "addr:street":"Hazeldonk",
    "iso:country":"NL",
    "sg:address":"Hazeldonk 6364",
    "sg:city":"Breda",
    "sg:classifiers":[
        {
            "category":"Retail",
            "subcategory":"Storage",
            "type":"Services"
        }
    ],
    "sg:phone":"+31 76 596 4496",
    "sg:postcode":"4836 LJ",
    "sg:province":"North Brabant",
    "sg:tags":[
        "opslag",
        "bewaring"
    ],
    "wof:name":"Loodet Bv",
    "wof:placetype":"venue"
},
  "geometry": {"coordinates":[4.7477908134,51.4944725037],"type":"Point"}
}