{
  "type": "Feature",
  "properties": {
    "addr:full":"Montaubanstr 229 Zeist Utrecht 3701 HN",
    "addr:housenumber":"229",
    "addr:postcode":"3701 hn",
    "iso:country":"NL",
    "sg:address":"Montaubanstr 229",
    "sg:city":"Zeist",
    "sg:orig_category":"Accountants - Administratie- Consulenten En -Kantoren",
    "sg:phone":"+31 30 692 0833",
    "sg:postcode":"3701 HN",
    "sg:province":"Utrecht",
    "wof:name":"Huibers, J",
    "wof:placetype":"venue"
},
  "geometry": {"coordinates":[5.238424,52.085938],"type":"Point"}
}