{
  "type": "Feature",
  "properties": {
    "addr:full":"Keizerserf 9 Nijverdal Overijssel 7442 MG",
    "addr:housenumber":"9",
    "addr:postcode":"7442 mg",
    "addr:street":"Keizerserf",
    "iso:country":"NL",
    "sg:address":"Keizerserf 9",
    "sg:city":"Nijverdal",
    "sg:orig_category":"Meubelzaken, Woning- And Keukeninrichting",
    "sg:phone":"+31 548 612 288",
    "sg:postcode":"7442 MG",
    "sg:province":"Overijssel",
    "wof:name":"Wolters Wonen",
    "wof:placetype":"venue"
},
  "geometry": {"coordinates":[6.459858,52.364872],"type":"Point"}
}