{
  "type": "Feature",
  "properties": {
    "addr:full":"Emmaplein 20 Bilthoven Utrecht 3722 AD",
    "addr:housenumber":"20",
    "addr:postcode":"3722 ad",
    "addr:street":"Emmaplein",
    "iso:country":"NL",
    "sg:address":"Emmaplein 20",
    "sg:city":"Bilthoven",
    "sg:orig_category":"Boekenuitgeverijen",
    "sg:phone":"+31 30 228 1014",
    "sg:postcode":"3722 AD",
    "sg:province":"Utrecht",
    "wof:name":"Boekhandel Jongerius",
    "wof:placetype":"venue"
},
  "geometry": {"coordinates":[5.205405,52.129639],"type":"Point"}
}