{
  "type": "Feature",
  "properties": {
    "addr:full":"Helmersflat 26 Roosendaal Noord-Brabant 4707 CM",
    "addr:housenumber":"26",
    "addr:postcode":"4707 cm",
    "addr:street":"Helmersflat",
    "iso:country":"NL",
    "sg:address":"Helmersflat 26",
    "sg:city":"Roosendaal",
    "sg:orig_category":"Kunststoffen - Fabrieken En Groothandel",
    "sg:phone":"+31 165 391 985",
    "sg:postcode":"4707 CM",
    "sg:province":"Noord-Brabant",
    "wof:name":"Neimex",
    "wof:placetype":"venue"
},
  "geometry": {"coordinates":[4.462357,51.518925],"type":"Point"}
}