{
  "type": "Feature",
  "properties": {
    "iso:country":"NL",
    "sg:address":"Laantje 42",
    "sg:city":"Westwoud",
    "sg:orig_category":"Loodgieterswerk, Verwarming And Sanitaire Installaties",
    "sg:phone":"+31 228 564 401",
    "sg:postcode":"1617 KM",
    "sg:province":"North Holland",
    "wof:name":"Paul Vlaar",
    "wof:placetype":"venue"
},
  "geometry": {"coordinates":[5.128898,52.68758],"type":"Point"}
}