{
  "type": "Feature",
  "properties": {
    "addr:full":"Goudsbloemstraat 35 Amsterdam North Holland 1015 JJ",
    "addr:housenumber":"35",
    "addr:postcode":"1015 jj",
    "addr:street":"Goudsbloemstraat",
    "iso:country":"NL",
    "sg:address":"Goudsbloemstraat 35",
    "sg:city":"Amsterdam",
    "sg:orig_category":"Bedrijfs- And Managementsconsultants",
    "sg:phone":"+31 20 638 6065",
    "sg:postcode":"1015 JJ",
    "sg:province":"North Holland",
    "wof:name":"Watkins Coaching En Training",
    "wof:placetype":"venue"
},
  "geometry": {"coordinates":[4.886035,52.38084],"type":"Point"}
}