{
  "type": "Feature",
  "properties": {
    "addr:full":"Hulwg 90 Lunteren Gelderland 6741 CJ",
    "addr:housenumber":"90",
    "addr:postcode":"6741 cj",
    "addr:street":"Hulwg;Gelderland",
    "iso:country":"NL",
    "sg:address":"Hulwg 90",
    "sg:city":"Lunteren",
    "sg:orig_category":"Sportverenigingen En Ontspannings- Verenigingen",
    "sg:phone":"+31 318 485 715",
    "sg:postcode":"6741 CJ",
    "sg:province":"Gelderland",
    "wof:name":"Lunaruiters, De",
    "wof:placetype":"venue"
},
  "geometry": {"coordinates":[5.615725,52.078705],"type":"Point"}
}