{
  "type": "Feature",
  "properties": {
    "addr:full":"T Vlot 2 Ulvenhout Noord-Brabant 4851 EZ",
    "addr:housenumber":"2",
    "addr:postcode":"4851 ez",
    "addr:street":"T Vlot",
    "iso:country":"NL",
    "sg:address":"T Vlot 2",
    "sg:city":"Ulvenhout",
    "sg:orig_category":"Marktonderzoekbureaus",
    "sg:phone":"+31 76 565 1619",
    "sg:postcode":"4851 EZ",
    "sg:province":"Noord-Brabant",
    "wof:name":"J.P. Van Rijen, Marketing Adviseur",
    "wof:placetype":"venue"
},
  "geometry": {"coordinates":[4.794669,51.545338],"type":"Point"}
}