{
  "type": "Feature",
  "properties": {
    "addr:full":"Ubbenaseweg 3 Zeijen Provincie Drenthe 9491 AA",
    "addr:housenumber":"3",
    "addr:postcode":"9491 aa",
    "addr:street":"Ubbenaseweg;Provincie Drenthe",
    "iso:country":"NL",
    "sg:address":"Ubbenaseweg 3",
    "sg:city":"Zeijen",
    "sg:classifiers":[
        {
            "category":"Education",
            "subcategory":"Preschool",
            "type":"Public Place"
        }
    ],
    "sg:phone":"+31 592 291 476",
    "sg:postcode":"9491 AA",
    "sg:province":"Provincie Drenthe",
    "sg:tags":[
        "kleuteronderwijs",
        "basis-"
    ],
    "wof:name":"Obs Daltonschool",
    "wof:placetype":"venue"
},
  "geometry": {"coordinates":[6.547245,53.048004],"type":"Point"}
}