{
  "type": "Feature",
  "properties": {
    "addr:full":"Hogenkampswg 41 Zwolle Overijssel 8022 DA",
    "addr:housenumber":"41",
    "addr:postcode":"8022 da",
    "addr:street":"Hogenkampswg",
    "iso:country":"NL",
    "sg:address":"Hogenkampswg 41",
    "sg:city":"Zwolle",
    "sg:orig_category":"Postkantoren",
    "sg:phone":"+31 38 453 3618",
    "sg:postcode":"8022 DA",
    "sg:province":"Overijssel",
    "sg:website":"http://www.postkantoor.nl",
    "wof:name":"Postkantoor",
    "wof:placetype":"venue"
},
  "geometry": {"coordinates":[6.105314,52.521324],"type":"Point"}
}