{
  "type": "Feature",
  "properties": {
    "addr:full":"Lambert Rimastraat 25 Amsterdam Zuidoost North Holland 1106 ZS",
    "addr:housenumber":"25",
    "addr:postcode":"1106 zs",
    "addr:street":"Lambert Rimastraat",
    "iso:country":"NL",
    "sg:address":"Lambert Rimastraat 25",
    "sg:city":"Amsterdam Zuidoost",
    "sg:orig_category":"Boekhouders",
    "sg:phone":"+31 20 409 0483",
    "sg:postcode":"1106 ZS",
    "sg:province":"North Holland",
    "wof:name":"Administratie- En Advieskant Vd Watering",
    "wof:placetype":"venue"
},
  "geometry": {"coordinates":[4.998824,52.300304],"type":"Point"}
}