{
  "type": "Feature",
  "properties": {
    "addr:full":"Julianaplein 1 Amsterdam Noord-Holland 1097 DN",
    "addr:housenumber":"1",
    "addr:postcode":"1097 dn",
    "addr:street":"Julianaplein",
    "iso:country":"NL",
    "sg:address":"Julianaplein 1",
    "sg:city":"Amsterdam",
    "sg:classifiers":[
        {
            "category":"Fast Food",
            "type":"Food & Drink"
        }
    ],
    "sg:phone":"+31 20 463 1111",
    "sg:postcode":"1097 DN",
    "sg:province":"Noord-Holland",
    "sg:tags":[
        "afhaal",
        "restaurant"
    ],
    "wof:name":"Pizza Hut",
    "wof:placetype":"venue"
},
  "geometry": {"coordinates":[4.918135,52.347408],"type":"Point"}
}