{
  "type": "Feature",
  "properties": {
    "iso:country":"NL",
    "sg:address":"Past V Zantenln 11",
    "sg:city":"Amstelveen",
    "sg:orig_category":"Machineonderhoud En -Reparatie",
    "sg:phone":"+31 297 582 503",
    "sg:postcode":"1189 WD",
    "sg:province":"North Holland",
    "wof:name":"Douma, T D",
    "wof:placetype":"venue"
},
  "geometry": {"coordinates":[4.872697,52.260387],"type":"Point"}
}