{
  "type": "Feature",
  "properties": {
    "addr:full":"Past V Zantenln 11 Amstelveen North Holland 1189 WD",
    "addr:housenumber":"11",
    "addr:postcode":"1189 wd",
    "addr:street":"Past;Zantenln",
    "iso:country":"NL",
    "sg:address":"Past V Zantenln 11",
    "sg:city":"Amstelveen",
    "sg:orig_category":"Machineonderhoud En -Reparatie",
    "sg:phone":"+31 297 582 503",
    "sg:postcode":"1189 WD",
    "sg:province":"North Holland",
    "wof:name":"Douma, T D",
    "wof:placetype":"venue"
},
  "geometry": {"coordinates":[4.872697,52.260387],"type":"Point"}
}