{
  "type": "Feature",
  "properties": {
    "iso:country":"NL",
    "sg:address":"T Hofke 139",
    "sg:city":"Eindhoven",
    "sg:classifiers":[
        {
            "category":"Shopping",
            "subcategory":"Gifts & Souvenirs",
            "type":"Retail Goods"
        }
    ],
    "sg:phone":"+31 40 285 4030",
    "sg:postcode":"5641 AK",
    "sg:province":"North Brabant",
    "sg:tags":[
        "wens-",
        "en",
        "prentbriefkaarten"
    ],
    "wof:name":"Thijssen",
    "wof:placetype":"venue"
},
  "geometry": {"coordinates":[5.5179100037,51.448928833],"type":"Point"}
}