{
  "type": "Feature",
  "properties": {
    "addr:full":"Marktplein 33 Ijmuiden Georgia 1972 GA",
    "addr:housenumber":"33",
    "addr:postcode":"1972 ga",
    "addr:street":"Marktplein;Georgia",
    "iso:country":"NL",
    "sg:address":"Marktplein 33",
    "sg:city":"Ijmuiden",
    "sg:orig_category":"Boekenuitgeverijen",
    "sg:phone":"+31 255 513 144",
    "sg:postcode":"1972 GA",
    "sg:province":"Georgia",
    "wof:name":"Boekhandel Erasmus Bv",
    "wof:placetype":"venue"
},
  "geometry": {"coordinates":[-83.222931,32.678131],"type":"Point"}
}