{
  "type": "Feature",
  "properties": {
    "addr:full":"Hoofdstraat 125 Stadskanaal Groningen 9501 CS",
    "addr:housenumber":"125",
    "addr:postcode":"9501 cs",
    "addr:street":"Hoofdstraat",
    "iso:country":"NL",
    "sg:address":"Hoofdstraat 125",
    "sg:city":"Stadskanaal",
    "sg:orig_category":"Bloemen And Planten",
    "sg:phone":"+31 599 612 180",
    "sg:postcode":"9501 CS",
    "sg:province":"Groningen",
    "wof:name":"Dier & Tuin Wolter Smit",
    "wof:placetype":"venue"
},
  "geometry": {"coordinates":[6.963541,52.980354],"type":"Point"}
}