{
  "type": "Feature",
  "properties": {
    "addr:full":"Hoornbrugln 51 Ryswyk Zh Zuid-Holland 2281 AV",
    "addr:housenumber":"51",
    "addr:postcode":"2281 av",
    "addr:street":"Hoornbrugln",
    "iso:country":"NL",
    "sg:address":"Hoornbrugln 51",
    "sg:city":"Ryswyk Zh",
    "sg:orig_category":"Acupunctuur",
    "sg:phone":"+31 70 390 0380",
    "sg:postcode":"2281 AV",
    "sg:province":"Zuid-Holland",
    "wof:name":"Rijk, Guido De",
    "wof:placetype":"venue"
},
  "geometry": {"coordinates":[4.341704,52.056934],"type":"Point"}
}