{
  "type": "Feature",
  "properties": {
    "addr:full":"Kerkedk 7/S Bergen Nh North Holland 1862 BD",
    "addr:housenumber":"7 / s",
    "addr:postcode":"1862 bd",
    "addr:street":"Kerkedk;Nh North",
    "iso:country":"NL",
    "sg:address":"Kerkedk 7/S",
    "sg:city":"Bergen Nh",
    "sg:orig_category":"Beeldende Kunstenaars",
    "sg:phone":"+31 72 589 4733",
    "sg:postcode":"1862 BD",
    "sg:province":"North Holland",
    "wof:name":"Roobeek",
    "wof:placetype":"venue"
},
  "geometry": {"coordinates":[4.70139,52.669979],"type":"Point"}
}