{
  "type": "Feature",
  "properties": {
    "addr:full":"Amazone 59 Dordrecht Zuid-Holland 3315 WH",
    "addr:housenumber":"59",
    "addr:postcode":"3315 wh",
    "addr:street":"Amazone",
    "iso:country":"NL",
    "sg:address":"Amazone 59",
    "sg:city":"Dordrecht",
    "sg:orig_category":"Schilders",
    "sg:phone":"+31 78 621 4698",
    "sg:postcode":"3315 WH",
    "sg:province":"Zuid-Holland",
    "wof:name":"Cannister, Schildersbedrijf",
    "wof:placetype":"venue"
},
  "geometry": {"coordinates":[4.704262,51.80735],"type":"Point"}
}