{
  "type": "Feature",
  "properties": {
    "addr:full":"Rimsky-Korssakovweg 39 Almere Flevoland 1323 LP",
    "addr:housenumber":"39",
    "addr:postcode":"1323 lp",
    "addr:street":"Rimsky-Korssakovweg;Flevoland",
    "iso:country":"NL",
    "sg:address":"Rimsky-Korssakovweg 39",
    "sg:city":"Almere",
    "sg:orig_category":"Banken And Kredietinstellingen",
    "sg:phone":"+31 36 536 4095",
    "sg:postcode":"1323 LP",
    "sg:province":"Flevoland",
    "wof:name":"Abn Amro",
    "wof:placetype":"venue"
},
  "geometry": {"coordinates":[5.191128,52.366814],"type":"Point"}
}