{
  "type": "Feature",
  "properties": {
    "addr:full":"Burgwal 77 Haarlem Noord-Holland 2011 BC",
    "addr:housenumber":"77",
    "addr:postcode":"2011 bc",
    "addr:street":"Burgwal",
    "iso:country":"NL",
    "sg:address":"Burgwal 77",
    "sg:city":"Haarlem",
    "sg:orig_category":"Beeldende Kunstenaars",
    "sg:phone":"+31 23 533 5119",
    "sg:postcode":"2011 BC",
    "sg:province":"Noord-Holland",
    "wof:name":"Veenen, Ruth Van",
    "wof:placetype":"venue"
},
  "geometry": {"coordinates":[4.641762,52.377964],"type":"Point"}
}