{
  "type": "Feature",
  "properties": {
    "addr:full":"Glacisweg 74 Maastricht Limburg 6212 BR",
    "addr:housenumber":"74",
    "addr:postcode":"6212 br",
    "addr:street":"Glacisweg",
    "iso:country":"NL",
    "sg:address":"Glacisweg 74",
    "sg:city":"Maastricht",
    "sg:orig_category":"Kappers",
    "sg:phone":"+31 43 325 4043",
    "sg:postcode":"6212 BR",
    "sg:province":"Limburg",
    "wof:name":"New Wave Vof",
    "wof:placetype":"venue"
},
  "geometry": {"coordinates":[5.687504,50.839603],"type":"Point"}
}