{
  "type": "Feature",
  "properties": {
    "addr:full":"Weislag 3 S Hertogenbosch Noord-Brabant 5221 AZ",
    "addr:housenumber":"3",
    "addr:postcode":"5221 az",
    "addr:street":"Weislag",
    "iso:country":"NL",
    "sg:address":"Weislag 3",
    "sg:city":"S Hertogenbosch",
    "sg:orig_category":"Modelbouw",
    "sg:phone":"+31 73 631 1564",
    "sg:postcode":"5221 AZ",
    "sg:province":"Noord-Brabant",
    "wof:name":"Jan Hollebeek",
    "wof:placetype":"venue"
},
  "geometry": {"coordinates":[5.268478,51.723579],"type":"Point"}
}