{
  "type": "Feature",
  "properties": {
    "addr:full":"Wilhelminalaan 29 Ermelo Gelderland 3851 XT",
    "addr:housenumber":"29",
    "addr:postcode":"3851 xt",
    "addr:street":"Wilhelminalaan;Gelderland",
    "iso:country":"NL",
    "sg:address":"Wilhelminalaan 29",
    "sg:city":"Ermelo",
    "sg:orig_category":"Huishoudapparatuur, Televisies And Radio'S",
    "sg:phone":"+31 341 557 130",
    "sg:postcode":"3851 XT",
    "sg:province":"Gelderland",
    "wof:name":"Musitronics",
    "wof:placetype":"venue"
},
  "geometry": {"coordinates":[5.619842,52.304382],"type":"Point"}
}