{
  "type": "Feature",
  "properties": {
    "addr:full":"Prunellalaan 20 Waalre Noord-Brabant 5582 HB",
    "addr:housenumber":"20",
    "addr:postcode":"5582 hb",
    "addr:street":"Prunellalaan",
    "iso:country":"NL",
    "sg:address":"Prunellalaan 20",
    "sg:city":"Waalre",
    "sg:orig_category":"Autokeuringen",
    "sg:phone":"+31 40 221 4130",
    "sg:postcode":"5582 HB",
    "sg:province":"Noord-Brabant",
    "wof:name":"Autoschadebedrijf Waalre Bv",
    "wof:placetype":"venue"
},
  "geometry": {"coordinates":[5.472605,51.399178],"type":"Point"}
}