{
  "type": "Feature",
  "properties": {
    "addr:full":"Kerkstr 1 Wagenborgen Groningen 9945 SB",
    "addr:housenumber":"1",
    "addr:postcode":"9945 sb",
    "addr:street":"Kerkstr",
    "iso:country":"NL",
    "sg:address":"Kerkstr 1",
    "sg:city":"Wagenborgen",
    "sg:orig_category":"Schilders",
    "sg:phone":"+31 596 541 951",
    "sg:postcode":"9945 SB",
    "sg:province":"Groningen",
    "wof:name":"Boneschansker",
    "wof:placetype":"venue"
},
  "geometry": {"coordinates":[6.93252,53.255856],"type":"Point"}
}