{
  "type": "Feature",
  "properties": {
    "addr:full":"Parallelwg 1 Beverwyk Noord-Holland 1948 NK",
    "addr:housenumber":"1",
    "addr:postcode":"1948 nk",
    "addr:street":"Parallelwg",
    "iso:country":"NL",
    "sg:address":"Parallelwg 1",
    "sg:city":"Beverwyk",
    "sg:orig_category":"Keukens",
    "sg:phone":"+31 251 221 393",
    "sg:postcode":"1948 NK",
    "sg:province":"Noord-Holland",
    "wof:name":"Edmon",
    "wof:placetype":"venue"
},
  "geometry": {"coordinates":[4.657081,52.475601],"type":"Point"}
}