{
  "type": "Feature",
  "properties": {
    "iso:country":"NL",
    "sg:address":"Kyckerwg 22",
    "sg:city":"De Lier",
    "sg:orig_category":"Woninginrichting",
    "sg:phone":"+31 174 523 335",
    "sg:postcode":"2678 AD",
    "sg:province":"South Holland",
    "sg:website":"http://www.duchatenier.nl",
    "wof:name":"Chatenier, Du",
    "wof:placetype":"venue"
},
  "geometry": {"coordinates":[4.2456321716,51.9745941162],"type":"Point"}
}