{
  "type": "Feature",
  "properties": {
    "addr:full":"Louis Van Gasterenstraat 57 Hengelo Ov NL.08 7558 SJ",
    "addr:housenumber":"57",
    "addr:postcode":"7558",
    "addr:street":"Louis Van Gasterenstraat;Ov",
    "iso:country":"NL",
    "sg:address":"Louis Van Gasterenstraat 57",
    "sg:city":"Hengelo Ov",
    "sg:classifiers":[
        {
            "category":"Education",
            "subcategory":"Preschool",
            "type":"Public Place"
        }
    ],
    "sg:phone":"+31 74 277 6616",
    "sg:postcode":"7558 SJ",
    "sg:province":"NL.08",
    "sg:tags":[
        "kleuteronderwijs",
        "basis-"
    ],
    "wof:name":"De Meent",
    "wof:placetype":"venue"
},
  "geometry": {"coordinates":[6.78971,52.266331],"type":"Point"}
}