{
  "type": "Feature",
  "properties": {
    "addr:full":"Oostsingel 51 Delft Zuid-Holland 2612 HD",
    "addr:housenumber":"51",
    "addr:postcode":"2612 hd",
    "addr:street":"Oostsingel",
    "iso:country":"NL",
    "sg:address":"Oostsingel 51",
    "sg:city":"Delft",
    "sg:orig_category":"Artsen And Specialisten",
    "sg:phone":"+31 15 212 6741",
    "sg:postcode":"2612 HD",
    "sg:province":"Zuid-Holland",
    "wof:name":"J.B.M. Nijkamp",
    "wof:placetype":"venue"
},
  "geometry": {"coordinates":[4.366667,52.013107],"type":"Point"}
}