{
  "type": "Feature",
  "properties": {
    "addr:full":"Noordweg 43 Oostkapelle Zeeland 4356 EB",
    "addr:housenumber":"43",
    "addr:postcode":"4356 eb",
    "addr:street":"Noordweg",
    "iso:country":"NL",
    "sg:address":"Noordweg 43",
    "sg:city":"Oostkapelle",
    "sg:classifiers":[
        {
            "category":"Travel",
            "subcategory":"Hotels & Motels",
            "type":"Entertainment"
        }
    ],
    "sg:phone":"+31 118 591 223",
    "sg:postcode":"4356 EB",
    "sg:province":"Zeeland",
    "wof:name":"Green White Hotel",
    "wof:placetype":"venue"
},
  "geometry": {"coordinates":[3.56984,51.567135],"type":"Point"}
}