{
  "type": "Feature",
  "properties": {
    "iso:country":"NL",
    "sg:address":"Nieuwstr 132",
    "sg:city":"Tilburg",
    "sg:orig_category":"Onderhoudswerken",
    "sg:phone":"+31 13 544 3222",
    "sg:postcode":"5021 WX",
    "sg:province":"Noord-Brabant",
    "sg:website":"http://www.albecon.nl",
    "wof:name":"Albecon Bv",
    "wof:placetype":"venue"
},
  "geometry": {"coordinates":[5.09061,51.548569],"type":"Point"}
}