{
  "type": "Feature",
  "properties": {
    "addr:full":"Veursewg 96 Voorschoten Zuid-Holland 2252 AE",
    "addr:housenumber":"96",
    "addr:postcode":"2252 ae",
    "addr:street":"Veursewg",
    "iso:country":"NL",
    "sg:address":"Veursewg 96",
    "sg:city":"Voorschoten",
    "sg:orig_category":"Adviesbureaus Bouwkunde",
    "sg:phone":"+31 71 561 1660",
    "sg:postcode":"2252 AE",
    "sg:province":"Zuid-Holland",
    "sg:website":"http://www.bouwbesluit.nl",
    "wof:name":"Bouwbesluit Bv",
    "wof:placetype":"venue"
},
  "geometry": {"coordinates":[4.43847,52.119171],"type":"Point"}
}