{
  "type": "Feature",
  "properties": {
    "addr:full":"Spaklerwg 4 Amsterdam Noord-Holland 1096 BA",
    "addr:housenumber":"4",
    "addr:postcode":"1096 ba",
    "addr:street":"Spaklerwg",
    "iso:country":"NL",
    "sg:address":"Spaklerwg 4",
    "sg:city":"Amsterdam",
    "sg:orig_category":"Verzekerings- Maatschappijen",
    "sg:phone":"+31 20 594 9111",
    "sg:postcode":"1096 BA",
    "sg:province":"Noord-Holland",
    "wof:name":"Delta Lloyd",
    "wof:placetype":"venue"
},
  "geometry": {"coordinates":[4.918202,52.343288],"type":"Point"}
}