{
  "type": "Feature",
  "properties": {
    "addr:full":"Beneluxweg 10 Groningen Groningen 9723 TR",
    "addr:housenumber":"10",
    "addr:postcode":"9723 tr",
    "addr:street":"Beneluxweg",
    "iso:country":"NL",
    "sg:address":"Beneluxweg 10",
    "sg:city":"Groningen",
    "sg:orig_category":"Benzinestations And Brandstoffen",
    "sg:phone":"+31 50 541 4181",
    "sg:postcode":"9723 TR",
    "sg:province":"Groningen",
    "wof:name":"Shell",
    "wof:placetype":"venue"
},
  "geometry": {"coordinates":[6.611429,53.21793],"type":"Point"}
}