{
  "type": "Feature",
  "properties": {
    "addr:full":"Johannieterpad 1 Zuiderhaven Mechelen Limburg 6281 AT",
    "addr:housenumber":"1",
    "addr:postcode":"6281",
    "addr:street":"Johannieterpad;Zuiderhaven",
    "iso:country":"NL",
    "sg:address":"Johannieterpad 1 Zuiderhaven",
    "sg:city":"Mechelen",
    "sg:orig_category":"Vakantieverblijven",
    "sg:phone":"+31 45 522 6900",
    "sg:postcode":"6281 AT",
    "sg:province":"Limburg",
    "wof:name":"Gronden, Ds J W Van De",
    "wof:placetype":"venue"
},
  "geometry": {"coordinates":[5.925868,50.796379],"type":"Point"}
}