{
  "type": "Feature",
  "properties": {
    "addr:full":"Fakkelln 1A Eindhoven North Brabant 5624 EA",
    "addr:housenumber":"1a",
    "addr:postcode":"5624 ea",
    "addr:street":"Fakkelln",
    "iso:country":"NL",
    "sg:address":"Fakkelln 1A",
    "sg:city":"Eindhoven",
    "sg:orig_category":"Kinderopvang",
    "sg:phone":"+31 40 296 3653",
    "sg:postcode":"5624 EA",
    "sg:province":"North Brabant",
    "wof:name":"Bereboot, De",
    "wof:placetype":"venue"
},
  "geometry": {"coordinates":[5.45493,51.470402],"type":"Point"}
}