{
  "type": "Feature",
  "properties": {
    "addr:full":"Kempenaersplein 22 Heerenveen Friesland 8442 DV",
    "addr:housenumber":"22",
    "addr:postcode":"8442 dv",
    "addr:street":"Kempenaersplein",
    "iso:country":"NL",
    "sg:address":"Kempenaersplein 22",
    "sg:city":"Heerenveen",
    "sg:classifiers":[
        {
            "category":"Fast Food",
            "type":"Food & Drink"
        }
    ],
    "sg:phone":"+31 513 628 001",
    "sg:postcode":"8442 DV",
    "sg:province":"Friesland",
    "sg:tags":[
        "afhaal",
        "restaurant"
    ],
    "wof:name":"Snackbar 'T Pleintje",
    "wof:placetype":"venue"
},
  "geometry": {"coordinates":[5.92701,52.951977],"type":"Point"}
}