{
  "type": "Feature",
  "properties": {
    "addr:full":"Soestdyksekd 716 S Gravenhage Zuid-Holland 2574 EB",
    "addr:housenumber":"716;gravenhage",
    "addr:postcode":"2574 eb",
    "addr:street":"S",
    "iso:country":"NL",
    "sg:address":"Soestdyksekd 716",
    "sg:city":"S Gravenhage",
    "sg:orig_category":"Honden- En Kattentrimsalons",
    "sg:phone":"+31 70 388 2342",
    "sg:postcode":"2574 EB",
    "sg:province":"Zuid-Holland",
    "wof:name":"Carola",
    "wof:placetype":"venue"
},
  "geometry": {"coordinates":[4.277523,52.064205],"type":"Point"}
}