{
  "type": "Feature",
  "properties": {
    "addr:full":"Industriestraat 1 Heerhugowaard Noord-Holland 1704 AA",
    "addr:housenumber":"1",
    "addr:postcode":"1704 aa",
    "addr:street":"Industriestraat",
    "iso:country":"NL",
    "sg:address":"Industriestraat 1",
    "sg:city":"Heerhugowaard",
    "sg:orig_category":"Huishoudapparatuur, Televisies And Radio'S",
    "sg:phone":"+31 72 572 1171",
    "sg:postcode":"1704 AA",
    "sg:province":"Noord-Holland",
    "wof:name":"Chaparral Europe Bv",
    "wof:placetype":"venue"
},
  "geometry": {"coordinates":[4.823286,52.670921],"type":"Point"}
}