{
  "type": "Feature",
  "properties": {
    "addr:full":"Emmausstraat 5 Sint Oedenrode Noord-Brabant 5492 BK",
    "addr:housenumber":"5;oedenrode",
    "addr:postcode":"5492 bk",
    "addr:street":"Emmausstraat",
    "iso:country":"NL",
    "sg:address":"Emmausstraat 5",
    "sg:city":"Sint Oedenrode",
    "sg:orig_category":"Kunst And Kunstenaarsbenodigdheden",
    "sg:phone":"+31 413 476 500",
    "sg:postcode":"5492 BK",
    "sg:province":"Noord-Brabant",
    "wof:name":"De Inlijsterij, Kunst In Lijsten",
    "wof:placetype":"venue"
},
  "geometry": {"coordinates":[5.45839,51.561253],"type":"Point"}
}