{
  "type": "Feature",
  "properties": {
    "addr:full":"Danzigerkd 8 Amsterdam North Holland 1013 AP",
    "addr:housenumber":"8",
    "addr:postcode":"1013 ap",
    "addr:street":"Danzigerkd",
    "iso:country":"NL",
    "sg:address":"Danzigerkd 8",
    "sg:city":"Amsterdam",
    "sg:orig_category":"Grafisch Ontwerpers",
    "sg:phone":"+31 20 609 0875",
    "sg:postcode":"1013 AP",
    "sg:province":"North Holland",
    "wof:name":"Maat, Lex",
    "wof:placetype":"venue"
},
  "geometry": {"coordinates":[4.893195,52.373119],"type":"Point"}
}