{
  "type": "Feature",
  "properties": {
    "addr:full":"O Randwg 18 Moerdyk North Brabant 4782 PZ",
    "addr:housenumber":"18",
    "addr:postcode":"4782 pz",
    "addr:street":"Moerdyk North",
    "iso:country":"NL",
    "sg:address":"O Randwg 18",
    "sg:city":"Moerdyk",
    "sg:orig_category":"Dieselmotoren",
    "sg:phone":"+31 168 388 488",
    "sg:postcode":"4782 PZ",
    "sg:province":"North Brabant",
    "sg:website":"http://www.dieselpowerholland.com",
    "wof:name":"Diesel Power Holland Bv",
    "wof:placetype":"venue"
},
  "geometry": {"coordinates":[4.63733,51.68322],"type":"Point"}
}