{
  "type": "Feature",
  "properties": {
    "addr:full":"J Lelimanhof 14 Amsterdam Noord-Holland 1067 LE",
    "addr:housenumber":"14",
    "addr:postcode":"1067 le",
    "addr:street":"Lelimanhof",
    "iso:country":"NL",
    "sg:address":"J Lelimanhof 14",
    "sg:city":"Amsterdam",
    "sg:orig_category":"Kappers",
    "sg:phone":"+31 20 614 6662",
    "sg:postcode":"1067 LE",
    "sg:province":"Noord-Holland",
    "wof:name":"Eddy",
    "wof:placetype":"venue"
},
  "geometry": {"coordinates":[4.7962059975,52.378616333],"type":"Point"}
}