{
  "type": "Feature",
  "properties": {
    "addr:full":"De Horst 45 Zevenaar Gelderland 6902 BC",
    "addr:housenumber":"45",
    "addr:postcode":"6902 bc",
    "addr:street":"De Horst",
    "iso:country":"NL",
    "sg:address":"De Horst 45",
    "sg:city":"Zevenaar",
    "sg:orig_category":"Adviesbureaus Financieel",
    "sg:phone":"+31 316 343 032",
    "sg:postcode":"6902 BC",
    "sg:province":"Gelderland",
    "wof:name":"Roosenboom Consultancy Bv",
    "wof:placetype":"venue"
},
  "geometry": {"coordinates":[6.090065,51.929153],"type":"Point"}
}