{
  "type": "Feature",
  "properties": {
    "addr:full":"Gildenring 22 Bunnik Utrecht 3981 JE",
    "addr:housenumber":"22",
    "addr:postcode":"3981 je",
    "addr:street":"Gildenring",
    "iso:country":"NL",
    "sg:address":"Gildenring 22",
    "sg:city":"Bunnik",
    "sg:orig_category":"Kantoorartikelen",
    "sg:phone":"+31 30 656 4908",
    "sg:postcode":"3981 JE",
    "sg:province":"Utrecht",
    "wof:name":"Buroforce Kantoorinrichting",
    "wof:placetype":"venue"
},
  "geometry": {"coordinates":[5.1891298294,52.0713920593],"type":"Point"}
}