{
  "type": "Feature",
  "properties": {
    "addr:full":"De Steiger 190 Almere Flevoland 1351 AV",
    "addr:housenumber":"190;1351",
    "addr:postcode":"av",
    "addr:street":"De Steiger;Flevoland",
    "iso:country":"NL",
    "sg:address":"De Steiger 190",
    "sg:city":"Almere",
    "sg:orig_category":"Kantoorbenodigdheden - Fabrieken En Groothandel",
    "sg:phone":"+31 36 531 3554",
    "sg:postcode":"1351 AV",
    "sg:province":"Flevoland",
    "wof:name":"Vermes Bv, G",
    "wof:placetype":"venue"
},
  "geometry": {"coordinates":[5.2247409821,52.3489341736],"type":"Point"}
}