{
  "type": "Feature",
  "properties": {
    "addr:full":"Oldehoofsterkerkh 4 Leeuwarden Friesland 8911 DH",
    "addr:housenumber":"4",
    "addr:postcode":"8911 dh",
    "addr:street":"Oldehoofsterkerkh",
    "iso:country":"NL",
    "sg:address":"Oldehoofsterkerkh 4",
    "sg:city":"Leeuwarden",
    "sg:orig_category":"Postkantoren",
    "sg:phone":"+31 58 213 0998",
    "sg:postcode":"8911 DH",
    "sg:province":"Friesland",
    "sg:website":"http://www.postkantoor.nl",
    "wof:name":"Postkantoor",
    "wof:placetype":"venue"
},
  "geometry": {"coordinates":[5.789758,53.202564],"type":"Point"}
}