{
  "type": "Feature",
  "properties": {
    "addr:full":"Meranti 251 Dordrecht Zuid-Holland 3315 TW",
    "addr:housenumber":"251",
    "addr:postcode":"3315 tw",
    "addr:street":"Meranti",
    "iso:country":"NL",
    "sg:address":"Meranti 251",
    "sg:city":"Dordrecht",
    "sg:orig_category":"Vertalers",
    "sg:phone":"+31 78 616 1481",
    "sg:postcode":"3315 TW",
    "sg:province":"Zuid-Holland",
    "wof:name":"Menoea",
    "wof:placetype":"venue"
},
  "geometry": {"coordinates":[4.71557,51.805752],"type":"Point"}
}