{
  "type": "Feature",
  "properties": {
    "iso:country":"NL",
    "sg:address":"Kratonlaan 92",
    "sg:city":"Zevenhuizen Zh",
    "sg:orig_category":"Bedrijvencentra",
    "sg:phone":"+31 180 634 277",
    "sg:postcode":"2761 SH",
    "sg:province":"Zuid-Holland",
    "wof:name":"De Graaff",
    "wof:placetype":"venue"
},
  "geometry": {"coordinates":[4.583855,52.006786],"type":"Point"}
}