{
  "type": "Feature",
  "properties": {
    "addr:full":"Oosteinderweg 277 Aalsmeer Noord-Holland 1432 AV",
    "addr:housenumber":"277",
    "addr:postcode":"1432 av",
    "addr:street":"Oosteinderweg",
    "iso:country":"NL",
    "sg:address":"Oosteinderweg 277",
    "sg:city":"Aalsmeer",
    "sg:orig_category":"Bloemen And Planten Gh",
    "sg:phone":"+31 297 346 519",
    "sg:postcode":"1432 AV",
    "sg:province":"Noord-Holland",
    "wof:name":"Mummy Plants Bv",
    "wof:placetype":"venue"
},
  "geometry": {"coordinates":[4.789835,52.281628],"type":"Point"}
}