{
  "type": "Feature",
  "properties": {
    "iso:country":"NL",
    "sg:address":"Osdorpplein 370",
    "sg:city":"Amsterdam",
    "sg:orig_category":"Baby- And Kinderkleding",
    "sg:phone":"+31 20 410 0561",
    "sg:postcode":"1068 EV",
    "sg:province":"Noord-Holland",
    "wof:name":"We Men",
    "wof:placetype":"venue"
},
  "geometry": {"coordinates":[4.80371,52.359791],"type":"Point"}
}