{
  "type": "Feature",
  "properties": {
    "addr:full":"Eikenlaan 59 'S-Gravenzande Zuid-Holland 2691 DZ",
    "addr:housenumber":"59",
    "addr:postcode":"2691 dz",
    "addr:street":"Eikenlaan",
    "iso:country":"NL",
    "sg:address":"Eikenlaan 59",
    "sg:city":"'S-Gravenzande",
    "sg:orig_category":"Onderhoudswerken",
    "sg:phone":"+31 6 51208515",
    "sg:postcode":"2691 DZ",
    "sg:province":"Zuid-Holland",
    "wof:name":"Wijnbergen, Wilco",
    "wof:placetype":"venue"
},
  "geometry": {"coordinates":[4.166018,51.997055],"type":"Point"}
}