{
  "type": "Feature",
  "properties": {
    "addr:full":"Tuinstraat 3 Eindhoven Noord-Brabant 5611 PL",
    "addr:housenumber":"3",
    "addr:postcode":"5611 pl",
    "addr:street":"Tuinstraat",
    "iso:country":"NL",
    "sg:address":"Tuinstraat 3",
    "sg:city":"Eindhoven",
    "sg:orig_category":"Architecten",
    "sg:phone":"+31 40 212 3529",
    "sg:postcode":"5611 PL",
    "sg:province":"Noord-Brabant",
    "wof:name":"Ir Tom Veeger",
    "wof:placetype":"venue"
},
  "geometry": {"coordinates":[5.487476,51.431431],"type":"Point"}
}