{
  "type": "Feature",
  "properties": {
    "addr:full":"Schutsboomstraat 14 Schaijk North Brabant 5374 CC",
    "addr:housenumber":"14",
    "addr:postcode":"5374 cc",
    "addr:street":"Schutsboomstraat",
    "iso:country":"NL",
    "sg:address":"Schutsboomstraat 14",
    "sg:city":"Schaijk",
    "sg:orig_category":"Paramedische Behandelingen",
    "sg:phone":"+31 486 461 287",
    "sg:postcode":"5374 CC",
    "sg:province":"North Brabant",
    "wof:name":"Sticht Thuiszorg",
    "wof:placetype":"venue"
},
  "geometry": {"coordinates":[5.6325,51.744778],"type":"Point"}
}