{
  "type": "Feature",
  "properties": {
    "addr:full":"Zeeburgerdijk 23 Amsterdam Noord-Holland 1093 SK",
    "addr:housenumber":"23",
    "addr:street":"Zeeburgerdijk;1093",
    "iso:country":"NL",
    "sg:address":"Zeeburgerdijk 23",
    "sg:city":"Amsterdam",
    "sg:orig_category":"Kinderopvang Behalve Thuis",
    "sg:phone":"+31 20 663 2083",
    "sg:postcode":"1093 SK",
    "sg:province":"Noord-Holland",
    "wof:name":"Kinderdagverblijf Roomtuintjes St Uk",
    "wof:placetype":"venue"
},
  "geometry": {"coordinates":[4.928466,52.366123],"type":"Point"}
}