{
  "type": "Feature",
  "properties": {
    "addr:full":"Zwaanstraat 1 Enkhuizen North Holland 1601 KM",
    "addr:housenumber":"1",
    "addr:street":"Zwaanstraat;1601 Km",
    "iso:country":"NL",
    "sg:address":"Zwaanstraat 1",
    "sg:city":"Enkhuizen",
    "sg:orig_category":"Diverse Grafische Activiteiten",
    "sg:phone":"+31 228 321 212",
    "sg:postcode":"1601 KM",
    "sg:province":"North Holland",
    "sg:website":"http://www.minkowsky.com",
    "wof:name":"Minkowsky Visuele Communicatie",
    "wof:placetype":"venue"
},
  "geometry": {"coordinates":[5.29543,52.703751],"type":"Point"}
}