{
  "type": "Feature",
  "properties": {
    "addr:full":"Lg Mosten 11 Breda Noord-Brabant 4822 NJ",
    "addr:housenumber":"11",
    "addr:postcode":"4822 nj",
    "addr:street":"Lg Mosten",
    "iso:country":"NL",
    "sg:address":"Lg Mosten 11",
    "sg:city":"Breda",
    "sg:orig_category":"Zoetwaren - Fabrieken En Groothandel",
    "sg:phone":"+31 76 548 6600",
    "sg:postcode":"4822 NJ",
    "sg:province":"Noord-Brabant",
    "wof:name":"Verduijn Bv, Gebr",
    "wof:placetype":"venue"
},
  "geometry": {"coordinates":[4.724609,51.604202],"type":"Point"}
}