{
  "type": "Feature",
  "properties": {
    "addr:full":"Utrechtseweg 247 Arnhem Gelderland 6812 AE",
    "addr:housenumber":"247",
    "addr:postcode":"6812 ae",
    "addr:street":"Utrechtseweg",
    "iso:country":"NL",
    "sg:address":"Utrechtseweg 247",
    "sg:city":"Arnhem",
    "sg:orig_category":"Loodgieterswerk, Verwarming And Sanitaire Installaties",
    "sg:phone":"+31 26 442 5168",
    "sg:postcode":"6812 AE",
    "sg:province":"Gelderland",
    "wof:name":"Firma W.F. Slingerland",
    "wof:placetype":"venue"
},
  "geometry": {"coordinates":[5.872351,51.983238],"type":"Point"}
}