{
  "type": "Feature",
  "properties": {
    "addr:full":"1E Beukenln 9 Apeldoorn Gelderland 7313 AJ",
    "addr:housenumber":"9",
    "addr:postcode":"7313 aj",
    "addr:street":"1E Beukenln;Gelderland",
    "iso:country":"NL",
    "sg:address":"1E Beukenln 9",
    "sg:city":"Apeldoorn",
    "sg:classifiers":[
        {
            "category":"Personal",
            "subcategory":"Nail Salon",
            "type":"Services"
        }
    ],
    "sg:phone":"+31 55 355 8330",
    "sg:postcode":"7313 AJ",
    "sg:province":"Gelderland",
    "sg:tags":[
        "pedicure"
    ],
    "wof:name":"Herberg-Oskamp, H Van Der",
    "wof:placetype":"venue"
},
  "geometry": {"coordinates":[5.936309,52.224964],"type":"Point"}
}