{
  "type": "Feature",
  "properties": {
    "addr:full":"Monte Viso 19 Amsterdam Noord-Holland 1060 PE",
    "addr:housenumber":"19",
    "addr:postcode":"1060 pe",
    "addr:street":"Monte Viso",
    "iso:country":"NL",
    "sg:address":"Monte Viso 19",
    "sg:city":"Amsterdam",
    "sg:orig_category":"Diverse Grafische Activiteiten",
    "sg:phone":"+31 20 410 0133",
    "sg:postcode":"1060 PE",
    "sg:province":"Noord-Holland",
    "wof:name":"B. Drughorn",
    "wof:placetype":"venue"
},
  "geometry": {"coordinates":[4.775868,52.350613],"type":"Point"}
}