{
  "type": "Feature",
  "properties": {
    "addr:full":"Roomwg 82 Enschede Overijssel 7523 BS",
    "addr:housenumber":"82",
    "addr:postcode":"7523 bs",
    "addr:street":"Roomwg",
    "iso:country":"NL",
    "sg:address":"Roomwg 82",
    "sg:city":"Enschede",
    "sg:orig_category":"Maaltijdbezorging",
    "sg:phone":"+31 53 431 2421",
    "sg:postcode":"7523 BS",
    "sg:province":"Overijssel",
    "wof:name":"Fako",
    "wof:placetype":"venue"
},
  "geometry": {"coordinates":[6.893055,52.231144],"type":"Point"}
}