{
  "type": "Feature",
  "properties": {
    "addr:full":"Oosterwoldseweg 74 Oldeberkoop Friesland 8421 RN",
    "addr:housenumber":"74",
    "addr:postcode":"8421 rn",
    "addr:street":"Oosterwoldseweg",
    "iso:country":"NL",
    "sg:address":"Oosterwoldseweg 74",
    "sg:city":"Oldeberkoop",
    "sg:orig_category":"Houten Verpakkingen Fab",
    "sg:phone":"+31 516 451 968",
    "sg:postcode":"8421 RN",
    "sg:province":"Friesland",
    "wof:name":"De Jong Pallets Bv",
    "wof:placetype":"venue"
},
  "geometry": {"coordinates":[-36.775188,-5.90648],"type":"Point"}
}