{
  "type": "Feature",
  "properties": {
    "addr:full":"Hagedoorn 6 Maassluis South Holland 3142 KB",
    "addr:housenumber":"6",
    "addr:postcode":"3142 kb",
    "addr:street":"Hagedoorn",
    "iso:country":"NL",
    "sg:address":"Hagedoorn 6",
    "sg:city":"Maassluis",
    "sg:orig_category":"Afdichtingen",
    "sg:phone":"+31 10 591 7099",
    "sg:postcode":"3142 KB",
    "sg:province":"South Holland",
    "wof:name":"Mari-Trade Bv",
    "wof:placetype":"venue"
},
  "geometry": {"coordinates":[4.255491,51.928577],"type":"Point"}
}