{
  "type": "Feature",
  "properties": {
    "addr:full":"Rupelstraat 4 Helmond North Brabant 5704 AX",
    "addr:housenumber":"4",
    "addr:postcode":"5704 ax",
    "addr:street":"Rupelstraat",
    "iso:country":"NL",
    "sg:address":"Rupelstraat 4",
    "sg:city":"Helmond",
    "sg:classifiers":[
        {
            "category":"Communications",
            "subcategory":"Television Station",
            "type":"Services"
        }
    ],
    "sg:phone":"+31 492 518 446",
    "sg:postcode":"5704 AX",
    "sg:province":"North Brabant",
    "sg:tags":[
        "video",
        "audio",
        "verhuur"
    ],
    "wof:name":"Zazou Video Entertainment Inkoopgroep",
    "wof:placetype":"venue"
},
  "geometry": {"coordinates":[5.698104,51.462822],"type":"Point"}
}