{
  "type": "Feature",
  "properties": {
    "addr:full":"Belkmerwg 51 St Maartensvlotbr Noord-Holland 1753 GD",
    "addr:housenumber":"51",
    "addr:postcode":"1753 gd",
    "addr:street":"Belkmerwg;St Maartensvlotbr",
    "iso:country":"NL",
    "sg:address":"Belkmerwg 51",
    "sg:city":"St Maartensvlotbr",
    "sg:orig_category":"Bloembollen - Groothandel",
    "sg:phone":"+31 226 381 463",
    "sg:postcode":"1753 GD",
    "sg:province":"Noord-Holland",
    "wof:name":"Waal, Gebr D & W",
    "wof:placetype":"venue"
},
  "geometry": {"coordinates":[-61.69894,12.11267],"type":"Point"}
}