{
  "type": "Feature",
  "properties": {
    "iso:country":"NL",
    "sg:address":"Belkmerwg 51",
    "sg:city":"St Maartensvlotbr",
    "sg:orig_category":"Bloembollen - Groothandel",
    "sg:phone":"+31 226 381 463",
    "sg:postcode":"1753 GD",
    "sg:province":"Noord-Holland",
    "wof:name":"Waal, Gebr D & W",
    "wof:placetype":"venue"
},
  "geometry": {"coordinates":[-61.69894,12.11267],"type":"Point"}
}