{
  "type": "Feature",
  "properties": {
    "addr:full":"Corkstr 32 Rotterdam South Holland 3047 AC",
    "addr:housenumber":"32",
    "addr:postcode":"3047 ac",
    "addr:street":"Corkstr",
    "iso:country":"NL",
    "sg:address":"Corkstr 32",
    "sg:city":"Rotterdam",
    "sg:orig_category":"Koeriersdiensten",
    "sg:phone":"+31 10 208 0808",
    "sg:postcode":"3047 AC",
    "sg:province":"South Holland",
    "wof:name":"Tnt Ned Bv",
    "wof:placetype":"venue"
},
  "geometry": {"coordinates":[4.412324,51.944172],"type":"Point"}
}