{
  "type": "Feature",
  "properties": {
    "addr:full":"Spoorstraat 20 Didam Gelderland 6942 ED",
    "addr:housenumber":"20",
    "addr:postcode":"6942 ed",
    "addr:street":"Spoorstraat;Gelderland",
    "iso:country":"NL",
    "sg:address":"Spoorstraat 20",
    "sg:city":"Didam",
    "sg:orig_category":"Bloemen And Planten",
    "sg:phone":"+31 316 220 262",
    "sg:postcode":"6942 ED",
    "sg:province":"Gelderland",
    "wof:name":"Ideaal",
    "wof:placetype":"venue"
},
  "geometry": {"coordinates":[6.130107,51.934566],"type":"Point"}
}