{
  "type": "Feature",
  "properties": {
    "iso:country":"NL",
    "sg:address":"Spoorstraat 20",
    "sg:city":"Didam",
    "sg:orig_category":"Bloemen And Planten",
    "sg:phone":"+31 316 220 262",
    "sg:postcode":"6942 ED",
    "sg:province":"Gelderland",
    "wof:name":"Ideaal",
    "wof:placetype":"venue"
},
  "geometry": {"coordinates":[6.130107,51.934566],"type":"Point"}
}