{
  "type": "Feature",
  "properties": {
    "iso:country":"NL",
    "sg:address":"Topaas 2",
    "sg:city":"Zoetermeer",
    "sg:orig_category":"Verzekeringen - Verzekeringskantoren",
    "sg:phone":"+31 79 362 3609",
    "sg:postcode":"2719 VD",
    "sg:province":"South Holland",
    "wof:name":"Vdk",
    "wof:placetype":"venue"
},
  "geometry": {"coordinates":[4.476764,52.035515],"type":"Point"}
}