{
  "type": "Feature",
  "properties": {
    "addr:full":"Nieuw Loosdrechtsedijk 200 Loosdrecht Utrecht 1231 LE",
    "addr:housenumber":"200",
    "addr:postcode":"1231 le",
    "iso:country":"NL",
    "sg:address":"Nieuw Loosdrechtsedijk 200",
    "sg:city":"Loosdrecht",
    "sg:orig_category":"Kampeerterreinen",
    "sg:phone":"+31 35 582 1762",
    "sg:postcode":"1231 LE",
    "sg:province":"Utrecht",
    "wof:name":"Camping De Drechthoeve Bv",
    "wof:placetype":"venue"
},
  "geometry": {"coordinates":[5.106235981,52.1894111633],"type":"Point"}
}