{
  "type": "Feature",
  "properties": {
    "addr:full":"Zuidgrensweg 12 Haaksbergen NL.08 7481 SE",
    "addr:housenumber":"12;nl.08",
    "addr:postcode":"7481 se",
    "addr:street":"Zuidgrensweg",
    "iso:country":"NL",
    "sg:address":"Zuidgrensweg 12",
    "sg:city":"Haaksbergen",
    "sg:orig_category":"Vakantiehuizen",
    "sg:phone":"+31 53 569 6707",
    "sg:postcode":"7481 SE",
    "sg:province":"NL.08",
    "wof:name":"Hummelhof",
    "wof:placetype":"venue"
},
  "geometry": {"coordinates":[6.842201,52.129616],"type":"Point"}
}