{
  "type": "Feature",
  "properties": {
    "addr:full":"J Wattstr 14 Alkmaar Noord-Holland 1817 DC",
    "addr:housenumber":"14",
    "addr:postcode":"1817",
    "iso:country":"NL",
    "sg:address":"J Wattstr 14",
    "sg:city":"Alkmaar",
    "sg:orig_category":"Bedrijfshuisvesting",
    "sg:phone":"+31 72 567 0707",
    "sg:postcode":"1817 DC",
    "sg:province":"Noord-Holland",
    "sg:website":"http://www.midicenter.nl",
    "wof:name":"Midi Center",
    "wof:placetype":"venue"
},
  "geometry": {"coordinates":[4.738854,52.650215],"type":"Point"}
}