{
  "type": "Feature",
  "properties": {
    "iso:country":"NL",
    "sg:address":"Rijksweg Zuid 62",
    "sg:city":"Elst Gld",
    "sg:orig_category":"Loodgieterswerk, Verwarming And Sanitaire Installaties",
    "sg:phone":"+31 481 350 751",
    "sg:postcode":"6662 KG",
    "sg:province":"Gelderland",
    "wof:name":"Weidema Onderhoud",
    "wof:placetype":"venue"
},
  "geometry": {"coordinates":[5.842811,51.912621],"type":"Point"}
}