{
  "type": "Feature",
  "properties": {
    "addr:full":"Scheveningsewg 15 S Gravenhage South Holland 2517 KS",
    "addr:housenumber":"15",
    "addr:postcode":"2517 ks",
    "addr:street":"Scheveningsewg;S Gravenhage",
    "iso:country":"NL",
    "sg:address":"Scheveningsewg 15",
    "sg:city":"S Gravenhage",
    "sg:classifiers":[
        {
            "category":"Wholesale",
            "subcategory":"Meat",
            "type":"Manufacturing & Wholesale Goods"
        }
    ],
    "sg:phone":"+31 70 392 4421",
    "sg:postcode":"2517 KS",
    "sg:province":"South Holland",
    "sg:tags":[
        "regeltechniek",
        "en",
        "meet-"
    ],
    "sg:website":"http://www.feteris.nl",
    "wof:name":"Feteris Bv, P J",
    "wof:placetype":"venue"
},
  "geometry": {"coordinates":[4.28708,52.08667],"type":"Point"}
}