{
  "type": "Feature",
  "properties": {
    "addr:full":"Poortstr 44 Utrecht Utrecht 3572 HK",
    "addr:housenumber":"44",
    "addr:postcode":"3572 hk",
    "addr:street":"Poortstr",
    "iso:country":"NL",
    "sg:address":"Poortstr 44",
    "sg:city":"Utrecht",
    "sg:orig_category":"Hypotheken",
    "sg:phone":"+31 30 276 9010",
    "sg:postcode":"3572 HK",
    "sg:province":"Utrecht",
    "sg:website":"http://www.utrecht.hypotheekshop.nl/880",
    "wof:name":"Hypotheekshop, De",
    "wof:placetype":"venue"
},
  "geometry": {"coordinates":[5.133886,52.096859],"type":"Point"}
}