{
  "type": "Feature",
  "properties": {
    "iso:country":"NL",
    "sg:address":"Dorpstr 7",
    "sg:city":"Macharen",
    "sg:orig_category":"Schilders",
    "sg:phone":"+31 412 492 666",
    "sg:postcode":"5367 AK",
    "sg:province":"Noord-Brabant",
    "wof:name":"Breda, Herman Van",
    "wof:placetype":"venue"
},
  "geometry": {"coordinates":[5.544287,51.804344],"type":"Point"}
}