{
  "type": "Feature",
  "properties": {
    "iso:country":"NL",
    "sg:address":"Alsteedseweg 81",
    "sg:city":"Haaksbergen",
    "sg:orig_category":"Diverse Consumentenartikelen Gh",
    "sg:phone":"+31 53 569 6520",
    "sg:postcode":"7481 RT",
    "sg:province":"Overijssel",
    "wof:name":"Volierebouw Bakker",
    "wof:placetype":"venue"
},
  "geometry": {"coordinates":[6.866754,52.129646],"type":"Point"}
}