{
  "type": "Feature",
  "properties": {
    "addr:full":"Sotaweg 41 Roelofarendsveen South Holland 2371 GA",
    "addr:housenumber":"41",
    "addr:postcode":"2371 ga",
    "addr:street":"Sotaweg",
    "iso:country":"NL",
    "sg:address":"Sotaweg 41",
    "sg:city":"Roelofarendsveen",
    "sg:orig_category":"Bloemen And Planten",
    "sg:phone":"+31 71 331 4858",
    "sg:postcode":"2371 GA",
    "sg:province":"South Holland",
    "wof:name":"Akerboom Freesia Cv",
    "wof:placetype":"venue"
},
  "geometry": {"coordinates":[4.630272,52.211178],"type":"Point"}
}