{
  "type": "Feature",
  "properties": {
    "addr:full":"Grotestr 18B Sambeek North Brabant 5836 AE",
    "addr:housenumber":"18b",
    "addr:postcode":"5836 ae",
    "addr:street":"Grotestr",
    "iso:country":"NL",
    "sg:address":"Grotestr 18B",
    "sg:city":"Sambeek",
    "sg:orig_category":"Bedrijfskleding",
    "sg:phone":"+31 485 520 021",
    "sg:postcode":"5836 AE",
    "sg:province":"North Brabant",
    "wof:name":"Mipa Hdl",
    "wof:placetype":"venue"
},
  "geometry": {"coordinates":[5.963659,51.63908],"type":"Point"}
}