{
  "type": "Feature",
  "properties": {
    "addr:full":"Boekweitstr 106 Nieuw Vennep North Holland 2153 GL",
    "addr:housenumber":"106",
    "addr:postcode":"2153 gl",
    "addr:street":"Nieuw Vennep North",
    "iso:country":"NL",
    "sg:address":"Boekweitstr 106",
    "sg:city":"Nieuw Vennep",
    "sg:orig_category":"Fotografie Reclame En Mode",
    "sg:phone":"+31 252 689 292",
    "sg:postcode":"2153 GL",
    "sg:province":"North Holland",
    "wof:name":"Ruud Snoeren",
    "wof:placetype":"venue"
},
  "geometry": {"coordinates":[4.651208,52.266689],"type":"Point"}
}