{
  "type": "Feature",
  "properties": {
    "addr:full":"Vogelzand 2313 Den Helder Noord-Holland 1788 GE",
    "addr:housenumber":"2313",
    "addr:postcode":"1788",
    "addr:street":"Vogelzand",
    "iso:country":"NL",
    "sg:address":"Vogelzand 2313",
    "sg:city":"Den Helder",
    "sg:orig_category":"Vertaal- And Tolkenbureaus",
    "sg:phone":"+31 223 644 892",
    "sg:postcode":"1788 GE",
    "sg:province":"Noord-Holland",
    "wof:name":"Anglo-Pro Translations",
    "wof:placetype":"venue"
},
  "geometry": {"coordinates":[4.738133,52.897537],"type":"Point"}
}