{
  "type": "Feature",
  "properties": {
    "addr:full":"Handelskade 13 Zwartsluis NL.08 8064 DV",
    "addr:housenumber":"13;nl.08",
    "addr:postcode":"8064",
    "addr:street":"Handelskade",
    "iso:country":"NL",
    "sg:address":"Handelskade 13",
    "sg:city":"Zwartsluis",
    "sg:orig_category":"Woningbouwverenigingen",
    "sg:phone":"+31 38 386 1300",
    "sg:postcode":"8064 DV",
    "sg:province":"NL.08",
    "wof:name":"Wetland Wonen Groep",
    "wof:placetype":"venue"
},
  "geometry": {"coordinates":[6.0722641945,52.6399726868],"type":"Point"}
}