{
  "type": "Feature",
  "properties": {
    "addr:full":"Burg D Kooimanwg 1027 Purmerend North Holland 1444 CK",
    "addr:housenumber":"1027",
    "addr:postcode":"1444 ck",
    "addr:street":"Burg",
    "iso:country":"NL",
    "sg:address":"Burg D Kooimanwg 1027",
    "sg:city":"Purmerend",
    "sg:orig_category":"Bedrijfsopleidingen",
    "sg:phone":"+31 299 775 860",
    "sg:postcode":"1444 CK",
    "sg:province":"North Holland",
    "wof:name":"Tao Training Advies & Opleiding",
    "wof:placetype":"venue"
},
  "geometry": {"coordinates":[4.958106,52.526909],"type":"Point"}
}