{
  "type": "Feature",
  "properties": {
    "addr:full":"Helsinkiln 8 Woerden Utrecht 3446 AH",
    "addr:housenumber":"8",
    "addr:postcode":"3446 ah",
    "addr:street":"Helsinkiln",
    "iso:country":"NL",
    "sg:address":"Helsinkiln 8",
    "sg:city":"Woerden",
    "sg:orig_category":"Verzekeringen - Verzekeringskantoren",
    "sg:phone":"+31 348 495 111",
    "sg:postcode":"3446 AH",
    "sg:province":"Utrecht",
    "sg:website":"http://www.patoirvlugt.nl",
    "wof:name":"Patoir & Van Der Vlugt",
    "wof:placetype":"venue"
},
  "geometry": {"coordinates":[4.898471,52.083988],"type":"Point"}
}