{
  "type": "Feature",
  "properties": {
    "addr:full":"Lammerweide 65 Zoetermeer South Holland 2727 EV",
    "addr:housenumber":"65",
    "addr:street":"Lammerweide",
    "iso:country":"NL",
    "sg:address":"Lammerweide 65",
    "sg:city":"Zoetermeer",
    "sg:orig_category":"Verlichtingsartikelen - Groothandel",
    "sg:phone":"+31 79 331 2109",
    "sg:postcode":"2727 EV",
    "sg:province":"South Holland",
    "wof:name":"Regt, De",
    "wof:placetype":"venue"
},
  "geometry": {"coordinates":[4.515434,52.071548],"type":"Point"}
}