{
  "type": "Feature",
  "properties": {
    "addr:full":"Windmolen 38 Weert Limburg 6003 BK",
    "addr:housenumber":"38",
    "addr:postcode":"6003 bk",
    "addr:street":"Windmolen",
    "iso:country":"NL",
    "sg:address":"Windmolen 38",
    "sg:city":"Weert",
    "sg:orig_category":"Honden- En Kattentrimsalons",
    "sg:phone":"+31 495 548 077",
    "sg:postcode":"6003 BK",
    "sg:province":"Limburg",
    "wof:name":"Esmiralda",
    "wof:placetype":"venue"
},
  "geometry": {"coordinates":[5.70576,51.26096],"type":"Point"}
}