{
  "type": "Feature",
  "properties": {
    "addr:full":"G Gezellestr 37 Papendrecht Zuid-Holland 3351 CL",
    "addr:housenumber":"37",
    "addr:postcode":"3351",
    "addr:street":"Papendrecht",
    "iso:country":"NL",
    "sg:address":"G Gezellestr 37",
    "sg:city":"Papendrecht",
    "sg:orig_category":"Adviesbureaus Bouwkunde",
    "sg:phone":"+31 78 642 9336",
    "sg:postcode":"3351 CL",
    "sg:province":"Zuid-Holland",
    "wof:name":"Kalis",
    "wof:placetype":"venue"
},
  "geometry": {"coordinates":[4.678913,51.832672],"type":"Point"}
}