{
  "type": "Feature",
  "properties": {
    "addr:full":"Hofln 25 Vlaardingen Zuid-Holland 3134 AA",
    "addr:housenumber":"25",
    "addr:postcode":"3134 aa",
    "addr:street":"Hofln",
    "iso:country":"NL",
    "sg:address":"Hofln 25",
    "sg:city":"Vlaardingen",
    "sg:orig_category":"Verlichting",
    "sg:phone":"+31 10 890 8950",
    "sg:postcode":"3134 AA",
    "sg:province":"Zuid-Holland",
    "wof:name":"Citytec",
    "wof:placetype":"venue"
},
  "geometry": {"coordinates":[4.340359,51.910442],"type":"Point"}
}