{
  "type": "Feature",
  "properties": {
    "addr:full":"Dunantstraat 24 Vriezenveen Overijssel 7671 BL",
    "addr:housenumber":"24",
    "addr:postcode":"7671 bl",
    "addr:street":"Dunantstraat",
    "iso:country":"NL",
    "sg:address":"Dunantstraat 24",
    "sg:city":"Vriezenveen",
    "sg:orig_category":"Huisdierenfokkers",
    "sg:phone":"+31 546 564 519",
    "sg:postcode":"7671 BL",
    "sg:province":"Overijssel",
    "wof:name":"Van Donaran",
    "wof:placetype":"venue"
},
  "geometry": {"coordinates":[6.62986,52.411015],"type":"Point"}
}