{
  "type": "Feature",
  "properties": {
    "iso:country":"NL",
    "sg:address":"Rietdekkersdreef 423",
    "sg:city":"Apeldoorn",
    "sg:orig_category":"Geluidsinstallaties",
    "sg:phone":"+31 55 534 8547",
    "sg:postcode":"7328 AE",
    "sg:province":"Gelderland",
    "wof:name":"Rocha Prod",
    "wof:placetype":"venue"
},
  "geometry": {"coordinates":[5.985667,52.195778],"type":"Point"}
}