{
  "type": "Feature",
  "properties": {
    "addr:full":"Weemse Hof 3 Ravenstein Noord-Brabant 5371 MA",
    "addr:housenumber":"3",
    "addr:postcode":"5371 ma",
    "addr:street":"Weemse Hof",
    "iso:country":"NL",
    "sg:address":"Weemse Hof 3",
    "sg:city":"Ravenstein",
    "sg:orig_category":"Metaalafval, Schrootrecycling And Sloperijen",
    "sg:phone":"+31 486 411 193",
    "sg:postcode":"5371 MA",
    "sg:province":"Noord-Brabant",
    "wof:name":"J.J. Vos",
    "wof:placetype":"venue"
},
  "geometry": {"coordinates":[5.63743,51.79089],"type":"Point"}
}