{
  "type": "Feature",
  "properties": {
    "addr:full":"Galvanistraat 148 Rotterdam Zuid-Holland 3029 AD",
    "addr:housenumber":"148",
    "addr:postcode":"3029 ad",
    "addr:street":"Galvanistraat",
    "iso:country":"NL",
    "sg:address":"Galvanistraat 148",
    "sg:city":"Rotterdam",
    "sg:orig_category":"Pleziervaartuigen And Reparatie",
    "sg:phone":"+31 10 436 6188",
    "sg:postcode":"3029 AD",
    "sg:province":"Zuid-Holland",
    "wof:name":"Datema Delfzijl Bv",
    "wof:placetype":"venue"
},
  "geometry": {"coordinates":[4.42932,51.911171],"type":"Point"}
}