{
  "type": "Feature",
  "properties": {
    "addr:full":"Kapelstr 19 Pastoorshof Lomm Limburg 5943 AE",
    "addr:housenumber":"19",
    "addr:postcode":"5943 ae",
    "addr:street":"Kapelstr;Pastoorshof",
    "iso:country":"NL",
    "sg:address":"Kapelstr 19 Pastoorshof",
    "sg:city":"Lomm",
    "sg:orig_category":"Verenigingsgebouwen",
    "sg:phone":"+31 77 473 1915",
    "sg:postcode":"5943 AE",
    "sg:province":"Limburg",
    "wof:name":"Pastoorshof",
    "wof:placetype":"venue"
},
  "geometry": {"coordinates":[6.17411,51.448318],"type":"Point"}
}