{
  "type": "Feature",
  "properties": {
    "addr:full":"Oudegracht 90 Utrecht Utrecht 3511 AV",
    "addr:housenumber":"90",
    "addr:postcode":"3511 av",
    "addr:street":"Oudegracht",
    "iso:country":"NL",
    "sg:address":"Oudegracht 90",
    "sg:city":"Utrecht",
    "sg:orig_category":"Werving And Selectie Van Tijdelijk Personeel And Uitzendkantoren",
    "sg:phone":"+31 30 223 2236",
    "sg:postcode":"3511 AV",
    "sg:province":"Utrecht",
    "wof:name":"Kolibrie Bv",
    "wof:placetype":"venue"
},
  "geometry": {"coordinates":[5.1154050827,52.0889320374],"type":"Point"}
}