{
  "type": "Feature",
  "properties": {
    "iso:country":"NL",
    "sg:address":"Professor Zernikestraat 5",
    "sg:city":"Sneek",
    "sg:orig_category":"Motoren",
    "sg:phone":"+31 515 411 134",
    "sg:postcode":"8606 JS",
    "sg:province":"Provincie Friesland",
    "wof:name":"Fiets O Fit Bv",
    "wof:placetype":"venue"
},
  "geometry": {"coordinates":[5.684426,53.020042],"type":"Point"}
}