{
  "type": "Feature",
  "properties": {
    "addr:full":"Gr Ansfriedstr 27 Kerkdriel Gelderland 5331 BC",
    "addr:housenumber":"27",
    "addr:postcode":"5331 bc",
    "addr:street":"Gelderland",
    "iso:country":"NL",
    "sg:address":"Gr Ansfriedstr 27",
    "sg:city":"Kerkdriel",
    "sg:classifiers":[
        {
            "category":"Home & Garden",
            "subcategory":"Garden Supply",
            "type":"Retail Goods"
        }
    ],
    "sg:phone":"+31 418 637 475",
    "sg:postcode":"5331 BC",
    "sg:province":"Gelderland",
    "sg:tags":[
        "zand",
        "en",
        "grind"
    ],
    "wof:name":"Hooymans Rederij Vof",
    "wof:placetype":"venue"
},
  "geometry": {"coordinates":[5.336734,51.773506],"type":"Point"}
}