{
  "type": "Feature",
  "properties": {
    "addr:full":"Berg En Dalseweg 432 Nijmegen Gelderland 6523 LP",
    "addr:housenumber":"432",
    "addr:postcode":"6523 lp",
    "addr:street":"Berg En Dalseweg;Gelderland",
    "iso:country":"NL",
    "sg:address":"Berg En Dalseweg 432",
    "sg:city":"Nijmegen",
    "sg:orig_category":"Autokeuringen",
    "sg:phone":"+31 24 323 3484",
    "sg:postcode":"6523 LP",
    "sg:province":"Gelderland",
    "wof:name":"Shell",
    "wof:placetype":"venue"
},
  "geometry": {"coordinates":[5.897297,51.831627],"type":"Point"}
}