{
  "type": "Feature",
  "properties": {
    "addr:full":"Brinkstraat 6 Hengelo Ov NL.08 7551 CC",
    "addr:housenumber":"6",
    "addr:postcode":"7551 cc",
    "addr:street":"Brinkstraat;Ov",
    "iso:country":"NL",
    "sg:address":"Brinkstraat 6",
    "sg:city":"Hengelo Ov",
    "sg:orig_category":"Damesmodezaken",
    "sg:phone":"+31 74 291 3607",
    "sg:postcode":"7551 CC",
    "sg:province":"NL.08",
    "wof:name":"Modehuis Wagenaar Bv",
    "wof:placetype":"venue"
},
  "geometry": {"coordinates":[6.792592,52.265114],"type":"Point"}
}