{
  "type": "Feature",
  "properties": {
    "iso:country":"NL",
    "sg:address":"Koolzaadstr 19",
    "sg:city":"Hengelo Ov",
    "sg:orig_category":"Adviesbureaus Bouwkunde",
    "sg:phone":"+31 74 256 9686",
    "sg:postcode":"7552 ER",
    "sg:province":"Overijssel",
    "sg:website":"http://www.bureau-vrij.nl",
    "wof:name":"Bureau Vrij",
    "wof:placetype":"venue"
},
  "geometry": {"coordinates":[6.814413,52.260254],"type":"Point"}
}