{
  "type": "Feature",
  "properties": {
    "addr:full":"Kometenhof 7 Emmeloord NL. 8303 CM",
    "addr:housenumber":"7",
    "addr:postcode":"8303 cm",
    "addr:street":"Kometenhof;Nl.",
    "iso:country":"NL",
    "sg:address":"Kometenhof 7",
    "sg:city":"Emmeloord",
    "sg:orig_category":"Autoruiten",
    "sg:phone":"+31 527 612 512",
    "sg:postcode":"8303 CM",
    "sg:province":"NL.",
    "sg:website":"http://www.glasgarage.nl",
    "wof:name":"Bulthuis Emmeloord",
    "wof:placetype":"venue"
},
  "geometry": {"coordinates":[5.739972,52.706596],"type":"Point"}
}