{
  "type": "Feature",
  "properties": {
    "addr:full":"Winkelhof 20 Leiderdorp South Holland 2353 TS",
    "addr:housenumber":"20",
    "addr:postcode":"2353 ts",
    "addr:street":"Winkelhof",
    "iso:country":"NL",
    "sg:address":"Winkelhof 20",
    "sg:city":"Leiderdorp",
    "sg:orig_category":"Opticiens",
    "sg:phone":"+31 71 541 2521",
    "sg:postcode":"2353 TS",
    "sg:province":"South Holland",
    "wof:name":"Saton Optiek Bv",
    "wof:placetype":"venue"
},
  "geometry": {"coordinates":[4.5325431824,52.163066864],"type":"Point"}
}