{
  "type": "Feature",
  "properties": {
    "addr:full":"H Stykelpln 18-19 S Gravenhage Zuid-Holland 2597 NS",
    "addr:housenumber":"18-19;gravenhage",
    "addr:postcode":"2597 ns",
    "addr:street":"S",
    "iso:country":"NL",
    "sg:address":"H Stykelpln 18-19",
    "sg:city":"S Gravenhage",
    "sg:orig_category":"Kappers",
    "sg:phone":"+31 70 354 2629",
    "sg:postcode":"2597 NS",
    "sg:province":"Zuid-Holland",
    "wof:name":"Gregor Coiffures",
    "wof:placetype":"venue"
},
  "geometry": {"coordinates":[4.3181700706,52.1103096008],"type":"Point"}
}