{
  "type": "Feature",
  "properties": {
    "addr:full":"Marconiwg 35 Hellevoetsluis Zuid-Holland 3225 LV",
    "addr:housenumber":"35",
    "addr:postcode":"3225",
    "addr:street":"Marconiwg",
    "iso:country":"NL",
    "sg:address":"Marconiwg 35",
    "sg:city":"Hellevoetsluis",
    "sg:orig_category":"Zeilmakerijen",
    "sg:phone":"+31 181 325 694",
    "sg:postcode":"3225 LV",
    "sg:province":"Zuid-Holland",
    "wof:name":"Bezemer Bv, J & W",
    "wof:placetype":"venue"
},
  "geometry": {"coordinates":[4.168576,51.840511],"type":"Point"}
}