{
  "type": "Feature",
  "properties": {
    "addr:full":"Zylstr 88 Haarlem North Holland 2011 TR",
    "addr:housenumber":"88",
    "addr:postcode":"2011 tr",
    "addr:street":"Zylstr",
    "iso:country":"NL",
    "sg:address":"Zylstr 88",
    "sg:city":"Haarlem",
    "sg:orig_category":"Kappers",
    "sg:phone":"+31 23 531 0817",
    "sg:postcode":"2011 TR",
    "sg:province":"North Holland",
    "wof:name":"Pi\u00e8rl\u00f4t, L G",
    "wof:placetype":"venue"
},
  "geometry": {"coordinates":[4.642253,52.380562],"type":"Point"}
}