{
  "type": "Feature",
  "properties": {
    "addr:full":"De Ruyterwg 11 Leeuwarden Friesland 8921 KH",
    "addr:housenumber":"11",
    "addr:postcode":"8921 kh",
    "iso:country":"NL",
    "sg:address":"De Ruyterwg 11",
    "sg:city":"Leeuwarden",
    "sg:orig_category":"Videotheken",
    "sg:phone":"+31 58 213 3725",
    "sg:postcode":"8921 KH",
    "sg:province":"Friesland",
    "wof:name":"Immanuel",
    "wof:placetype":"venue"
},
  "geometry": {"coordinates":[5.80993,53.20425],"type":"Point"}
}