{
  "type": "Feature",
  "properties": {
    "iso:country":"NL",
    "sg:address":"Greffelingsestr 29",
    "sg:city":"Alphen Gld",
    "sg:orig_category":"Jachthavens - Jachtwerven",
    "sg:phone":"+31 487 561 304",
    "sg:postcode":"6626 AP",
    "sg:province":"Gelderland",
    "wof:name":"Ooijen, W P Van",
    "wof:placetype":"venue"
},
  "geometry": {"coordinates":[5.47509,51.824944],"type":"Point"}
}