{
  "type": "Feature",
  "properties": {
    "iso:country":"NL",
    "sg:address":"Bleijenhoek 43",
    "sg:city":"Bladel",
    "sg:orig_category":"Granen, Zaden And Diervoeders Gh",
    "sg:phone":"+31 497 385 925",
    "sg:postcode":"5531 BL",
    "sg:province":"North Brabant",
    "wof:name":"Firma F.R. Vosters En Zn",
    "wof:placetype":"venue"
},
  "geometry": {"coordinates":[5.209769,51.363998],"type":"Point"}
}