{
  "type": "Feature",
  "properties": {
    "iso:country":"NL",
    "sg:address":"Kerkstraat 45",
    "sg:city":"Panningen",
    "sg:orig_category":"Verlichting And Huishoudartikelen",
    "sg:phone":"+31 77 307 7005",
    "sg:postcode":"5981 CD",
    "sg:province":"Limburg",
    "wof:name":"Joosten Verlichtingsspeciaalzaak",
    "wof:placetype":"venue"
},
  "geometry": {"coordinates":[5.974971,51.326649],"type":"Point"}
}