{
  "type": "Feature",
  "properties": {
    "iso:country":"NL",
    "sg:address":"Planetenbaan 80",
    "sg:city":"Maarssen",
    "sg:orig_category":"Boekenuitgeverijen",
    "sg:phone":"+31 346 577 577",
    "sg:postcode":"3606 AK",
    "sg:province":"Utrecht",
    "wof:name":"Elsevier Bedrijfsinformatie Bv",
    "wof:placetype":"venue"
},
  "geometry": {"coordinates":[5.03808,52.126652],"type":"Point"}
}