{
  "type": "Feature",
  "properties": {
    "addr:full":"Vogelwikke 20 Maartensdijk Utrecht 3738 TT",
    "addr:housenumber":"20",
    "addr:postcode":"3738 tt",
    "addr:street":"Vogelwikke",
    "iso:country":"NL",
    "sg:address":"Vogelwikke 20",
    "sg:city":"Maartensdijk",
    "sg:classifiers":[
        {
            "category":"Professional",
            "subcategory":"Accounting & Tax Preparation",
            "type":"Services"
        }
    ],
    "sg:phone":"+31 346 213 595",
    "sg:postcode":"3738 TT",
    "sg:province":"Utrecht",
    "sg:tags":[
        "accountant"
    ],
    "wof:name":"O. Feenstra Ra",
    "wof:placetype":"venue"
},
  "geometry": {"coordinates":[5.1720747948,52.1522903442],"type":"Point"}
}