{
  "type": "Feature",
  "properties": {
    "iso:country":"NL",
    "sg:address":"Rooseveltstraat 46",
    "sg:city":"Leiden",
    "sg:orig_category":"Motoren",
    "sg:phone":"+31 71 579 1580",
    "sg:postcode":"2321 BM",
    "sg:province":"Zuid-Holland",
    "wof:name":"Augusta Benelux Bv",
    "wof:placetype":"venue"
},
  "geometry": {"coordinates":[4.481978,52.143284],"type":"Point"}
}