{
  "type": "Feature",
  "properties": {
    "addr:full":"Abel Tasmanstraat 61 Rotterdam South Holland 3165 AM",
    "addr:housenumber":"61",
    "addr:postcode":"3165",
    "addr:street":"Abel Tasmanstraat",
    "iso:country":"NL",
    "sg:address":"Abel Tasmanstraat 61",
    "sg:city":"Rotterdam",
    "sg:orig_category":"Goederenvervoer Over De Weg",
    "sg:phone":"+31 10 283 6363",
    "sg:postcode":"3165 AM",
    "sg:province":"South Holland",
    "wof:name":"Ritmeester Bezorgers Bv",
    "wof:placetype":"venue"
},
  "geometry": {"coordinates":[4.415835,51.868698],"type":"Point"}
}