{
  "type": "Feature",
  "properties": {
    "addr:full":"Nyverheidstr 1 Losser NL.08 7581 PV",
    "addr:housenumber":"1;nl.08",
    "addr:postcode":"7581 pv",
    "addr:street":"Nyverheidstr",
    "iso:country":"NL",
    "sg:address":"Nyverheidstr 1",
    "sg:city":"Losser",
    "sg:orig_category":"Glas",
    "sg:phone":"+31 53 538 4840",
    "sg:postcode":"7581 PV",
    "sg:province":"NL.08",
    "wof:name":"Woning Bv, Van Der",
    "wof:placetype":"venue"
},
  "geometry": {"coordinates":[7.009836,52.250996],"type":"Point"}
}