{
  "type": "Feature",
  "properties": {
    "addr:full":"Lindebaan 11 Bergen Op Zoom Noord-Brabant 4611 LW",
    "addr:housenumber":"11",
    "addr:postcode":"4611 lw",
    "addr:street":"Lindebaan",
    "iso:country":"NL",
    "sg:address":"Lindebaan 11",
    "sg:city":"Bergen Op Zoom",
    "sg:orig_category":"Werving And Selectie Van Tijdelijk Personeel And Uitzendkantoren",
    "sg:phone":"+31 164 260 268",
    "sg:postcode":"4611 LW",
    "sg:province":"Noord-Brabant",
    "wof:name":"Eurozend Bv",
    "wof:placetype":"venue"
},
  "geometry": {"coordinates":[4.2868690491,51.4923171997],"type":"Point"}
}