{
  "type": "Feature",
  "properties": {
    "addr:full":"G Waldastr 2 Zuidhorn Groningen 9801 AW",
    "addr:housenumber":"2",
    "addr:postcode":"9801 aw",
    "addr:street":"Zuidhorn",
    "iso:country":"NL",
    "sg:address":"G Waldastr 2",
    "sg:city":"Zuidhorn",
    "sg:orig_category":"Scholen Voor Basisonderwijs",
    "sg:phone":"+31 594 500 313",
    "sg:postcode":"9801 AW",
    "sg:province":"Groningen",
    "wof:name":"Anker Chr, Het",
    "wof:placetype":"venue"
},
  "geometry": {"coordinates":[6.400236,53.253029],"type":"Point"}
}