{
  "type": "Feature",
  "properties": {
    "iso:country":"NL",
    "sg:address":"Warmoesstr 111",
    "sg:city":"Amsterdam",
    "sg:orig_category":"Drukkerijen",
    "sg:phone":"+31 20 624 2576",
    "sg:postcode":"1012 JA",
    "sg:province":"Noord-Holland",
    "wof:name":"Atlantic",
    "wof:placetype":"venue"
},
  "geometry": {"coordinates":[4.896716,52.374195],"type":"Point"}
}