{
  "type": "Feature",
  "properties": {
    "addr:full":"Schoolstr 6 St Oedenrode North Brabant 5491 ZB",
    "addr:housenumber":"6",
    "addr:postcode":"5491 zb",
    "addr:street":"Schoolstr",
    "iso:country":"NL",
    "sg:address":"Schoolstr 6",
    "sg:city":"St Oedenrode",
    "sg:orig_category":"Accountants - Administratie- Consulenten En -Kantoren",
    "sg:phone":"+31 413 490 342",
    "sg:postcode":"5491 ZB",
    "sg:province":"North Brabant",
    "wof:name":"Double You Bv",
    "wof:placetype":"venue"
},
  "geometry": {"coordinates":[5.406412,51.581261],"type":"Point"}
}