{
  "type": "Feature",
  "properties": {
    "addr:full":"Hobbemastraat 19 Eindhoven Noord-Brabant 5613 HK",
    "addr:housenumber":"19",
    "addr:postcode":"5613 hk",
    "addr:street":"Hobbemastraat",
    "iso:country":"NL",
    "sg:address":"Hobbemastraat 19",
    "sg:city":"Eindhoven",
    "sg:orig_category":"Bibliotheken And Openbare Archieven",
    "sg:phone":"+31 40 243 2851",
    "sg:postcode":"5613 HK",
    "sg:province":"Noord-Brabant",
    "wof:name":"Gemeenschappelijke Openbare Bibliotheek",
    "wof:placetype":"venue"
},
  "geometry": {"coordinates":[5.504206,51.438644],"type":"Point"}
}