{
  "type": "Feature",
  "properties": {
    "addr:full":"Bilderdijkkade 25/Hs Amsterdam Noord-Holland 1053 VB",
    "addr:housenumber":"25 / hs",
    "addr:postcode":"1053 vb",
    "addr:street":"Bilderdijkkade",
    "iso:country":"NL",
    "sg:address":"Bilderdijkkade 25/Hs",
    "sg:city":"Amsterdam",
    "sg:orig_category":"Huishoudapparatuur, Televisies And Radio'S",
    "sg:phone":"+31 20 618 0115",
    "sg:postcode":"1053 VB",
    "sg:province":"Noord-Holland",
    "wof:name":"Hewea Electrotechnisch Installatie Burea",
    "wof:placetype":"venue"
},
  "geometry": {"coordinates":[4.86733,52.366638],"type":"Point"}
}