{
  "type": "Feature",
  "properties": {
    "iso:country":"NL",
    "sg:address":"Haefland 7",
    "sg:city":"Brunssum",
    "sg:orig_category":"Verhuur Catering-, Feest- En Evenementbenodigdheden",
    "sg:phone":"+31 45 525 6600",
    "sg:postcode":"6441 PA",
    "sg:province":"Limburg",
    "wof:name":"Eurosit",
    "wof:placetype":"venue"
},
  "geometry": {"coordinates":[5.971306,50.957909],"type":"Point"}
}