{
  "type": "Feature",
  "properties": {
    "addr:full":"Herenwg 9 Hoogwoud Noord-Holland 1718 AB",
    "addr:housenumber":"9",
    "addr:postcode":"1718 ab",
    "addr:street":"Herenwg",
    "iso:country":"NL",
    "sg:address":"Herenwg 9",
    "sg:city":"Hoogwoud",
    "sg:orig_category":"Warmtetechniek",
    "sg:phone":"+31 226 353 777",
    "sg:postcode":"1718 AB",
    "sg:province":"Noord-Holland",
    "wof:name":"S & G",
    "wof:placetype":"venue"
},
  "geometry": {"coordinates":[4.9424419403,52.7130699158],"type":"Point"}
}