{
  "type": "Feature",
  "properties": {
    "addr:full":"Voorstr 78 Zwaagwesteinde Friesland 9271 KJ",
    "addr:housenumber":"78",
    "addr:postcode":"9271 kj",
    "addr:street":"Voorstr",
    "iso:country":"NL",
    "sg:address":"Voorstr 78",
    "sg:city":"Zwaagwesteinde",
    "sg:orig_category":"Bloemen En Planten",
    "sg:phone":"+31 511 449 210",
    "sg:postcode":"9271 KJ",
    "sg:province":"Friesland",
    "wof:name":"Blomster, De",
    "wof:placetype":"venue"
},
  "geometry": {"coordinates":[6.040894,53.261505],"type":"Point"}
}