{
  "type": "Feature",
  "properties": {
    "iso:country":"NL",
    "sg:address":"Stemerdingweg 11",
    "sg:city":"Soesterberg",
    "sg:orig_category":"Pompen And Compressoren Fab",
    "sg:phone":"+31 346 351 150",
    "sg:postcode":"3769 CE",
    "sg:province":"Utrecht",
    "wof:name":"Chyparse",
    "wof:placetype":"venue"
},
  "geometry": {"coordinates":[5.275824,52.122398],"type":"Point"}
}