{
  "type": "Feature",
  "properties": {
    "addr:full":"Stemerdingweg 11 Soesterberg Utrecht 3769 CE",
    "addr:housenumber":"11",
    "addr:postcode":"3769 ce",
    "addr:street":"Stemerdingweg",
    "iso:country":"NL",
    "sg:address":"Stemerdingweg 11",
    "sg:city":"Soesterberg",
    "sg:orig_category":"Pompen And Compressoren Fab",
    "sg:phone":"+31 346 351 150",
    "sg:postcode":"3769 CE",
    "sg:province":"Utrecht",
    "wof:name":"Chyparse",
    "wof:placetype":"venue"
},
  "geometry": {"coordinates":[5.275824,52.122398],"type":"Point"}
}