{
  "type": "Feature",
  "properties": {
    "addr:full":"Provincialewg O 79 Haastrecht Zuid-Holland 2851 AC",
    "addr:housenumber":"79",
    "addr:postcode":"2851 ac",
    "iso:country":"NL",
    "sg:address":"Provincialewg O 79",
    "sg:city":"Haastrecht",
    "sg:orig_category":"Antiquiteiten",
    "sg:phone":"+31 182 502 712",
    "sg:postcode":"2851 AC",
    "sg:province":"Zuid-Holland",
    "wof:name":"Kloasterke, 'T",
    "wof:placetype":"venue"
},
  "geometry": {"coordinates":[4.8012208939,52.0114822388],"type":"Point"}
}