{
  "type": "Feature",
  "properties": {
    "addr:full":"Hoofdweg 66 Slochteren Groningen 9621 AM",
    "addr:housenumber":"66",
    "addr:postcode":"9621",
    "addr:street":"Hoofdweg",
    "iso:country":"NL",
    "sg:address":"Hoofdweg 66",
    "sg:city":"Slochteren",
    "sg:orig_category":"Notarissen",
    "sg:phone":"+31 598 422 722",
    "sg:postcode":"9621 AM",
    "sg:province":"Groningen",
    "wof:name":"Mr. S. Kalfsbeek Notaris",
    "wof:placetype":"venue"
},
  "geometry": {"coordinates":[6.802485,53.212296],"type":"Point"}
}