{
  "type": "Feature",
  "properties": {
    "iso:country":"NL",
    "sg:address":"Markt 12",
    "sg:city":"Roermond",
    "sg:orig_category":"Herenmodezaken",
    "sg:phone":"+31 475 317 167",
    "sg:postcode":"6041 EL",
    "sg:province":"Limburg",
    "wof:name":"Vof Claessen Minkenberg",
    "wof:placetype":"venue"
},
  "geometry": {"coordinates":[5.98528,51.19553],"type":"Point"}
}