{
  "type": "Feature",
  "properties": {
    "addr:full":"Industriestr 45 Ymuiden Noord-Holland 1976 CT",
    "addr:housenumber":"45",
    "addr:postcode":"1976 ct",
    "addr:street":"Industriestr",
    "iso:country":"NL",
    "sg:address":"Industriestr 45",
    "sg:city":"Ymuiden",
    "sg:orig_category":"Verpakkingsbedrijven",
    "sg:phone":"+31 255 523 673",
    "sg:postcode":"1976 CT",
    "sg:province":"Noord-Holland",
    "wof:name":"Ijmond",
    "wof:placetype":"venue"
},
  "geometry": {"coordinates":[4.588834,52.457691],"type":"Point"}
}