{
  "type": "Feature",
  "properties": {
    "addr:full":"Meer En Geerwg 5 Leidschendam Zuid-Holland 2266 HW",
    "addr:housenumber":"5",
    "addr:postcode":"2266 hw",
    "addr:street":"Meer En Geerwg",
    "iso:country":"NL",
    "sg:address":"Meer En Geerwg 5",
    "sg:city":"Leidschendam",
    "sg:classifiers":[
        {
            "category":"Sports & Exercise",
            "subcategory":"Stables",
            "type":"Entertainment"
        }
    ],
    "sg:phone":"+31 71 580 2109",
    "sg:postcode":"2266 HW",
    "sg:province":"Zuid-Holland",
    "sg:tags":[
        "maneges"
    ],
    "wof:name":"Groene Meer, De",
    "wof:placetype":"venue"
},
  "geometry": {"coordinates":[4.468691,52.090477],"type":"Point"}
}