{
  "type": "Feature",
  "properties": {
    "addr:full":"Burgemeester Korstenstr 3 Herten Limburg 6049 AL",
    "addr:housenumber":"3",
    "addr:postcode":"6049 al",
    "addr:street":"Burgemeester Korstenstr",
    "iso:country":"NL",
    "sg:address":"Burgemeester Korstenstr 3",
    "sg:city":"Herten",
    "sg:orig_category":"Paramedische Behandelingen",
    "sg:phone":"+31 475 317 004",
    "sg:postcode":"6049 AL",
    "sg:province":"Limburg",
    "wof:name":"E.M.J.H. Debruijn-Kuijer",
    "wof:placetype":"venue"
},
  "geometry": {"coordinates":[5.968843,51.180622],"type":"Point"}
}