{
  "type": "Feature",
  "properties": {
    "iso:country":"NL",
    "sg:address":"Dorpsstr 50",
    "sg:city":"Wormer",
    "sg:orig_category":"Parketvloeren",
    "sg:phone":"+31 75 642 8206",
    "sg:postcode":"1531 HN",
    "sg:province":"Noord-Holland",
    "wof:name":"Nieuwenhuijs Parketvloeren",
    "wof:placetype":"venue"
},
  "geometry": {"coordinates":[4.812974,52.498363],"type":"Point"}
}