{
  "type": "Feature",
  "properties": {
    "addr:full":"Grotestr 177 Almelo Overijssel 7607 CK",
    "addr:housenumber":"177",
    "addr:postcode":"7607 ck",
    "iso:country":"NL",
    "sg:address":"Grotestr 177",
    "sg:city":"Almelo",
    "sg:orig_category":"Kappers",
    "sg:phone":"+31 546 829 099",
    "sg:postcode":"7607 CK",
    "sg:province":"Overijssel",
    "wof:name":"Seth'S",
    "wof:placetype":"venue"
},
  "geometry": {"coordinates":[6.665169,52.352791],"type":"Point"}
}