{
  "type": "Feature",
  "properties": {
    "addr:full":"Dorpsstr 18 Geesteren Ov Overijssel 7678 AW",
    "addr:housenumber":"18",
    "addr:postcode":"7678 aw",
    "addr:street":"Dorpsstr;Ov",
    "iso:country":"NL",
    "sg:address":"Dorpsstr 18",
    "sg:city":"Geesteren Ov",
    "sg:classifiers":[
        {
            "category":"Food & Beverages",
            "subcategory":"Bakery",
            "type":"Retail Goods"
        }
    ],
    "sg:phone":"+31 546 632 502",
    "sg:postcode":"7678 AW",
    "sg:province":"Overijssel",
    "sg:tags":[
        "brood",
        "en",
        "banket"
    ],
    "wof:name":"Kraai, De",
    "wof:placetype":"venue"
},
  "geometry": {"coordinates":[6.739006,52.420792],"type":"Point"}
}