{
  "type": "Feature",
  "properties": {
    "addr:full":"Wilhelmina Van Pruisenln 437 Gouda Zuid-Holland 2807 MH",
    "addr:housenumber":"437",
    "addr:postcode":"2807 mh",
    "addr:street":"Wilhelmina Van Pruisenln",
    "iso:country":"NL",
    "sg:address":"Wilhelmina Van Pruisenln 437",
    "sg:city":"Gouda",
    "sg:orig_category":"Goederenvervoer Over De Weg",
    "sg:phone":"+31 182 585 717",
    "sg:postcode":"2807 MH",
    "sg:province":"Zuid-Holland",
    "wof:name":"A.W. Van Winkelen",
    "wof:placetype":"venue"
},
  "geometry": {"coordinates":[4.749425,52.010677],"type":"Point"}
}