{
  "type": "Feature",
  "properties": {
    "addr:full":"V Nesstr 25A Alphen Aan Den Ryn Zuid-Holland 2404 AV",
    "addr:housenumber":"25a",
    "addr:postcode":"2404 av",
    "addr:street":"Aan Den Ryn",
    "iso:country":"NL",
    "sg:address":"V Nesstr 25A",
    "sg:city":"Alphen Aan Den Ryn",
    "sg:orig_category":"Podotherapeuten",
    "sg:phone":"+31 172 426 700",
    "sg:postcode":"2404 AV",
    "sg:province":"Zuid-Holland",
    "wof:name":"Padmos, M",
    "wof:placetype":"venue"
},
  "geometry": {"coordinates":[4.658921,52.12719],"type":"Point"}
}