{
  "type": "Feature",
  "properties": {
    "addr:full":"Gasthuisstraat 68 Kaatsheuvel Noord-Brabant 5171 GH",
    "addr:housenumber":"68",
    "addr:postcode":"5171 gh",
    "addr:street":"Gasthuisstraat",
    "iso:country":"NL",
    "sg:address":"Gasthuisstraat 68",
    "sg:city":"Kaatsheuvel",
    "sg:orig_category":"Diverse Grafische Activiteiten",
    "sg:phone":"+31 416 281 196",
    "sg:postcode":"5171 GH",
    "sg:province":"Noord-Brabant",
    "wof:name":"2D Studio Voor Grafische Vormgeving",
    "wof:placetype":"venue"
},
  "geometry": {"coordinates":[5.037623,51.658024],"type":"Point"}
}