{
  "type": "Feature",
  "properties": {
    "addr:full":"Mahlersingel 20 Nieuwegein Utrecht 3438 XA",
    "addr:housenumber":"20",
    "addr:postcode":"3438 xa",
    "addr:street":"Mahlersingel",
    "iso:country":"NL",
    "sg:address":"Mahlersingel 20",
    "sg:city":"Nieuwegein",
    "sg:orig_category":"Kappers",
    "sg:phone":"+31 6 54328881",
    "sg:postcode":"3438 XA",
    "sg:province":"Utrecht",
    "wof:name":"Wendy",
    "wof:placetype":"venue"
},
  "geometry": {"coordinates":[5.089856,52.041294],"type":"Point"}
}