{
  "type": "Feature",
  "properties": {
    "addr:full":"Diepenstraat 59 Tilburg Noord-Brabant 5025 MR",
    "addr:housenumber":"59",
    "addr:postcode":"5025 mr",
    "addr:street":"Diepenstraat",
    "iso:country":"NL",
    "sg:address":"Diepenstraat 59",
    "sg:city":"Tilburg",
    "sg:orig_category":"Loodgieterswerk, Verwarming And Sanitaire Installaties",
    "sg:phone":"+31 13 463 3110",
    "sg:postcode":"5025 MR",
    "sg:province":"Noord-Brabant",
    "wof:name":"Loodgieters- En Tegelzetters- Bedrijf A. Bierings",
    "wof:placetype":"venue"
},
  "geometry": {"coordinates":[5.069049,51.551071],"type":"Point"}
}