{
  "type": "Feature",
  "properties": {
    "addr:full":"Nijverheidsweg-Noord 58 Amersfoort Utrecht 3812 PM",
    "addr:housenumber":"58",
    "addr:postcode":"3812 pm",
    "addr:street":"Nijverheidsweg-Noord",
    "iso:country":"NL",
    "sg:address":"Nijverheidsweg-Noord 58",
    "sg:city":"Amersfoort",
    "sg:orig_category":"Boekhouders",
    "sg:phone":"+31 33 469 9964",
    "sg:postcode":"3812 PM",
    "sg:province":"Utrecht",
    "wof:name":"Beunke De Bes Accountantskantoor",
    "wof:placetype":"venue"
},
  "geometry": {"coordinates":[5.371482,52.165077],"type":"Point"}
}