{
  "type": "Feature",
  "properties": {
    "iso:country":"NL",
    "sg:address":"Vryburgstr 3A",
    "sg:city":"Voorburg",
    "sg:orig_category":"Adviesbureaus Bedrijfsorganisatie",
    "sg:phone":"+31 70 369 4945",
    "sg:postcode":"2275 BX",
    "sg:province":"Zuid-Holland",
    "wof:name":"Melsen",
    "wof:placetype":"venue"
},
  "geometry": {"coordinates":[4.355853,52.063866],"type":"Point"}
}