{
  "type": "Feature",
  "properties": {
    "addr:full":"De Schepershilt 8 Leusden Utrecht 3831 NS",
    "addr:housenumber":"8",
    "addr:postcode":"3831 ns",
    "addr:street":"De Schepershilt",
    "iso:country":"NL",
    "sg:address":"De Schepershilt 8",
    "sg:city":"Leusden",
    "sg:orig_category":"Parketvloeren",
    "sg:phone":"+31 33 494 7078",
    "sg:postcode":"3831 NS",
    "sg:province":"Utrecht",
    "wof:name":"Daas, Den",
    "wof:placetype":"venue"
},
  "geometry": {"coordinates":[5.42959,52.131248],"type":"Point"}
}