{
  "type": "Feature",
  "properties": {
    "addr:full":"Van 'T Hoffplein 11 Schiedam Zuid-Holland 3112 JS",
    "addr:housenumber":"11",
    "addr:postcode":"3112 js",
    "addr:street":"Van ' T Hoffplein",
    "iso:country":"NL",
    "sg:address":"Van 'T Hoffplein 11",
    "sg:city":"Schiedam",
    "sg:classifiers":[
        {
            "category":"Fast Food",
            "type":"Food & Drink"
        }
    ],
    "sg:phone":"+31 10 437 6968",
    "sg:postcode":"3112 JS",
    "sg:province":"Zuid-Holland",
    "sg:tags":[
        "afhaal",
        "restaurant"
    ],
    "wof:name":"Snackbar De Nieuwe Beertjes",
    "wof:placetype":"venue"
},
  "geometry": {"coordinates":[4.412951,51.915958],"type":"Point"}
}