{
  "type": "Feature",
  "properties": {
    "addr:full":"Diepenbrockstraat 18 Heerlen Limburg 6411 TJ",
    "addr:housenumber":"18",
    "addr:postcode":"6411 tj",
    "addr:street":"Diepenbrockstraat",
    "iso:country":"NL",
    "sg:address":"Diepenbrockstraat 18",
    "sg:city":"Heerlen",
    "sg:orig_category":"Kappers",
    "sg:phone":"+31 45 571 2353",
    "sg:postcode":"6411 TJ",
    "sg:province":"Limburg",
    "wof:name":"Dames-En Herenkapsalon Tonja",
    "wof:placetype":"venue"
},
  "geometry": {"coordinates":[5.9645571709,50.8892822266],"type":"Point"}
}