{
  "type": "Feature",
  "properties": {
    "addr:full":"Archimedesweg 1 Leiden South Holland 2333 CM",
    "addr:housenumber":"1",
    "addr:postcode":"2333 cm",
    "addr:street":"Archimedesweg",
    "iso:country":"NL",
    "sg:address":"Archimedesweg 1",
    "sg:city":"Leiden",
    "sg:orig_category":"Overheidsdiensten",
    "sg:phone":"+31 71 525 9125",
    "sg:postcode":"2333 CM",
    "sg:province":"South Holland",
    "wof:name":"Hoogheemraadschapvan Rijnland",
    "wof:placetype":"venue"
},
  "geometry": {"coordinates":[4.465528965,52.1647644043],"type":"Point"}
}