{
  "type": "Feature",
  "properties": {
    "addr:full":"Brink 23 Assen Drenthe 9401 HT",
    "addr:housenumber":"23",
    "addr:postcode":"9401 ht",
    "addr:street":"Brink",
    "iso:country":"NL",
    "sg:address":"Brink 23",
    "sg:city":"Assen",
    "sg:classifiers":[
        {
            "category":"Fast Food",
            "type":"Food & Drink"
        }
    ],
    "sg:phone":"+31 592 312 112",
    "sg:postcode":"9401 HT",
    "sg:province":"Drenthe",
    "sg:tags":[
        "afhaal",
        "restaurant"
    ],
    "wof:name":"Restaurant You-Yi Express",
    "wof:placetype":"venue"
},
  "geometry": {"coordinates":[6.562137,52.993877],"type":"Point"}
}