{
  "type": "Feature",
  "properties": {
    "addr:full":"Walenburgerpln 174 Rotterdam Zuid-Holland 3039 AP",
    "addr:housenumber":"174",
    "addr:postcode":"3039 ap",
    "iso:country":"NL",
    "sg:address":"Walenburgerpln 174",
    "sg:city":"Rotterdam",
    "sg:orig_category":"Verzekeringen - Verzekeringskantoren",
    "sg:phone":"+31 10 243 0766",
    "sg:postcode":"3039 AP",
    "sg:province":"Zuid-Holland",
    "wof:name":"E & N Assuranti\u00ebn",
    "wof:placetype":"venue"
},
  "geometry": {"coordinates":[4.465691,51.92907],"type":"Point"}
}