{
  "type": "Feature",
  "properties": {
    "iso:country":"NL",
    "sg:address":"C Huygensstr 112",
    "sg:city":"Gouda",
    "sg:orig_category":"Boeken En Tijdschriften",
    "sg:phone":"+31 182 510 447",
    "sg:postcode":"2802 LZ",
    "sg:province":"Zuid-Holland",
    "wof:name":"Boekelier, De",
    "wof:placetype":"venue"
},
  "geometry": {"coordinates":[4.701288,52.005547],"type":"Point"}
}