{
  "type": "Feature",
  "properties": {
    "addr:full":"Handelskade 55 Stadskanaal Groningen 9503 AC",
    "addr:housenumber":"55",
    "addr:postcode":"9503 ac",
    "addr:street":"Handelskade",
    "iso:country":"NL",
    "sg:address":"Handelskade 55",
    "sg:city":"Stadskanaal",
    "sg:orig_category":"Diverse Grafische Activiteiten",
    "sg:phone":"+31 6 28641396",
    "sg:postcode":"9503 AC",
    "sg:province":"Groningen",
    "wof:name":"Bizcom",
    "wof:placetype":"venue"
},
  "geometry": {"coordinates":[6.93825,52.996506],"type":"Point"}
}