{
  "type": "Feature",
  "properties": {
    "iso:country":"NL",
    "sg:address":"Boerendanserdijk 2A",
    "sg:city":"Zwolle",
    "sg:orig_category":"Werving And Selectie Van Tijdelijk Personeel And Uitzendkantoren",
    "sg:phone":"+31 38 453 0807",
    "sg:postcode":"8024 AH",
    "sg:province":"NL.08",
    "wof:name":"De Graaf Contracting Bv",
    "wof:placetype":"venue"
},
  "geometry": {"coordinates":[6.1287970543,52.520778656],"type":"Point"}
}