{
  "type": "Feature",
  "properties": {
    "addr:full":"Oude Doetinch Wg 36 Zeddam Gelderland 7038 BJ",
    "addr:housenumber":"36",
    "addr:postcode":"7038 bj",
    "addr:street":"Oude;Wg;Gelderland",
    "iso:country":"NL",
    "sg:address":"Oude Doetinch Wg 36",
    "sg:city":"Zeddam",
    "sg:orig_category":"Waterbehandeling En Waterzuiverings- Systemen",
    "sg:phone":"+31 314 651 013",
    "sg:postcode":"7038 BJ",
    "sg:province":"Gelderland",
    "wof:name":"Vriesen",
    "wof:placetype":"venue"
},
  "geometry": {"coordinates":[6.2628960609,51.9053153992],"type":"Point"}
}