{
  "type": "Feature",
  "properties": {
    "iso:country":"NL",
    "sg:address":"Sluisplein 16",
    "sg:city":"Anna Paulowna",
    "sg:orig_category":"Banken And Kredietinstellingen",
    "sg:phone":"+31 223 531 210",
    "sg:postcode":"1761 BT",
    "sg:province":"Noord-Holland",
    "wof:name":"Postkantoor",
    "wof:placetype":"venue"
},
  "geometry": {"coordinates":[4.831671,52.861778],"type":"Point"}
}