{
  "type": "Feature",
  "properties": {
    "iso:country":"NL",
    "sg:address":"Nieuwstraat 3",
    "sg:city":"Loppersum",
    "sg:orig_category":"Verlichting And Huishoudartikelen",
    "sg:phone":"+31 596 571 403",
    "sg:postcode":"9919 AZ",
    "sg:province":"Groningen",
    "wof:name":"Warenhuis Van Der Molen",
    "wof:placetype":"venue"
},
  "geometry": {"coordinates":[6.743985,53.33276],"type":"Point"}
}