{
  "type": "Feature",
  "properties": {
    "addr:full":"Grotestr 7 Ootmarsum Overijssel 7631 BT",
    "addr:housenumber":"7",
    "addr:postcode":"7631 bt",
    "addr:street":"Grotestr",
    "iso:country":"NL",
    "sg:address":"Grotestr 7",
    "sg:city":"Ootmarsum",
    "sg:classifiers":[
        {
            "category":"Travel",
            "subcategory":"Hotels & Motels",
            "type":"Entertainment"
        }
    ],
    "sg:phone":"+31 541 291 281",
    "sg:postcode":"7631 BT",
    "sg:province":"Overijssel",
    "sg:website":"http://www.vandermaas.nl",
    "wof:name":"Maas Hotel, Van Der",
    "wof:placetype":"venue"
},
  "geometry": {"coordinates":[6.895911,52.407684],"type":"Point"}
}