{
  "type": "Feature",
  "properties": {
    "iso:country":"NL",
    "sg:address":"Dorpskade 1",
    "sg:city":"Wateringen",
    "sg:orig_category":"Overheidsdiensten",
    "sg:phone":"+31 174 291 300",
    "sg:postcode":"2291 HN",
    "sg:province":"Zuid-Holland",
    "wof:name":"Gemeente Wateringen",
    "wof:placetype":"venue"
},
  "geometry": {"coordinates":[4.2734389305,52.0227088928],"type":"Point"}
}