{
  "type": "Feature",
  "properties": {
    "addr:full":"Tussen De Bogen 23 Amsterdam Noord-Holland 1013 JB",
    "addr:housenumber":"23",
    "addr:postcode":"1013 jb",
    "addr:street":"Tussen De Bogen",
    "iso:country":"NL",
    "sg:address":"Tussen De Bogen 23",
    "sg:city":"Amsterdam",
    "sg:orig_category":"Balletscholen",
    "sg:phone":"+31 20 627 7788",
    "sg:postcode":"1013 JB",
    "sg:province":"Noord-Holland",
    "wof:name":"Arte Flamenco",
    "wof:placetype":"venue"
},
  "geometry": {"coordinates":[4.887733,52.383499],"type":"Point"}
}