{
  "type": "Feature",
  "properties": {
    "addr:full":"L Doniastr 7 Franeker Friesland 8801 HD",
    "addr:housenumber":"7",
    "addr:postcode":"8801 hd",
    "iso:country":"NL",
    "sg:address":"L Doniastr 7",
    "sg:city":"Franeker",
    "sg:orig_category":"Autorijscholen",
    "sg:phone":"+31 517 393 229",
    "sg:postcode":"8801 HD",
    "sg:province":"Friesland",
    "wof:name":"Mosselaar",
    "wof:placetype":"venue"
},
  "geometry": {"coordinates":[5.536546,53.188156],"type":"Point"}
}