{
  "type": "Feature",
  "properties": {
    "addr:full":"Hendrikstraat 14 Urmond Limburg 6129 AK",
    "addr:housenumber":"14",
    "addr:postcode":"6129 ak",
    "addr:street":"Hendrikstraat",
    "iso:country":"NL",
    "sg:address":"Hendrikstraat 14",
    "sg:city":"Urmond",
    "sg:orig_category":"Beautyfarms And Sauna'S",
    "sg:phone":"+31 46 433 5409",
    "sg:postcode":"6129 AK",
    "sg:province":"Limburg",
    "wof:name":"Marina",
    "wof:placetype":"venue"
},
  "geometry": {"coordinates":[5.773978,51.006592],"type":"Point"}
}