{
  "type": "Feature",
  "properties": {
    "iso:country":"NL",
    "sg:address":"Golstr 13",
    "sg:city":"Deventer",
    "sg:orig_category":"Kappers",
    "sg:phone":"+31 570 613 345",
    "sg:postcode":"7411 BN",
    "sg:province":"NL.08",
    "wof:name":"Halavurt",
    "wof:placetype":"venue"
},
  "geometry": {"coordinates":[6.1616501808,52.2531394958],"type":"Point"}
}