{
  "type": "Feature",
  "properties": {
    "addr:full":"Krommewg 4 St Michielsgestel North Brabant 5271 CV",
    "addr:housenumber":"4",
    "addr:postcode":"5271 cv",
    "addr:street":"Krommewg",
    "iso:country":"NL",
    "sg:address":"Krommewg 4",
    "sg:city":"St Michielsgestel",
    "sg:orig_category":"Loodgieters",
    "sg:phone":"+31 73 551 3064",
    "sg:postcode":"5271 CV",
    "sg:province":"North Brabant",
    "wof:name":"Donk, W Van Der",
    "wof:placetype":"venue"
},
  "geometry": {"coordinates":[5.358335,51.641861],"type":"Point"}
}