{
  "type": "Feature",
  "properties": {
    "addr:full":"W V Amersfoortstr 27 Achterveld Gelderland 3791 AN",
    "addr:housenumber":"27",
    "addr:postcode":"3791 an",
    "addr:street":"W V Amersfoortstr;Gelderland",
    "iso:country":"NL",
    "sg:address":"W V Amersfoortstr 27",
    "sg:city":"Achterveld",
    "sg:orig_category":"Woningstoffeerders",
    "sg:phone":"+31 6 20091257",
    "sg:postcode":"3791 AN",
    "sg:province":"Gelderland",
    "wof:name":"Berg Woningstoffeerder, J H Van Den",
    "wof:placetype":"venue"
},
  "geometry": {"coordinates":[5.4969029427,52.1367454529],"type":"Point"}
}