{
  "type": "Feature",
  "properties": {
    "iso:country":"NL",
    "sg:address":"M Wesselingstr 8",
    "sg:city":"Rotterdam",
    "sg:orig_category":"Verenigingsgebouwen",
    "sg:phone":"+31 10 266 8777",
    "sg:postcode":"3065 GA",
    "sg:province":"Zuid-Holland",
    "wof:name":"Zjaak",
    "wof:placetype":"venue"
},
  "geometry": {"coordinates":[4.547411,51.92794],"type":"Point"}
}