{
  "type": "Feature",
  "properties": {
    "addr:full":"Kloosterpln 11 Breda Noord-Brabant 4811 GP",
    "addr:housenumber":"11",
    "addr:postcode":"4811 gp",
    "addr:street":"Kloosterpln",
    "iso:country":"NL",
    "sg:address":"Kloosterpln 11",
    "sg:city":"Breda",
    "sg:orig_category":"Banken",
    "sg:phone":"+31 76 515 2694",
    "sg:postcode":"4811 GP",
    "sg:province":"Noord-Brabant",
    "wof:name":"Fortis",
    "wof:placetype":"venue"
},
  "geometry": {"coordinates":[4.781971,51.588062],"type":"Point"}
}