{
  "type": "Feature",
  "properties": {
    "addr:full":"Ten Ankerwg 8 Tholen Zeeland 4691 GW",
    "addr:housenumber":"8",
    "addr:postcode":"4691 gw",
    "addr:street":"Ten Ankerwg",
    "iso:country":"NL",
    "sg:address":"Ten Ankerwg 8",
    "sg:city":"Tholen",
    "sg:orig_category":"Leesportefeuilles",
    "sg:phone":"+31 166 603 774",
    "sg:postcode":"4691 GW",
    "sg:province":"Zeeland",
    "wof:name":"Leesnet",
    "wof:placetype":"venue"
},
  "geometry": {"coordinates":[4.222351,51.535107],"type":"Point"}
}