{
  "type": "Feature",
  "properties": {
    "addr:full":"Costerwg 5-44 Wageningen Gelderland 6702 AA",
    "addr:housenumber":"5-44",
    "addr:postcode":"6702 aa",
    "addr:street":"Gelderland",
    "iso:country":"NL",
    "sg:address":"Costerwg 5-44",
    "sg:city":"Wageningen",
    "sg:orig_category":"Houtgroothandel Hardhout",
    "sg:phone":"+31 317 425 828",
    "sg:postcode":"6702 AA",
    "sg:province":"Gelderland",
    "sg:website":"http://www.ecohout.nl",
    "wof:name":"Ecohout, Stichting",
    "wof:placetype":"venue"
},
  "geometry": {"coordinates":[5.658259,51.964684],"type":"Point"}
}