{
  "type": "Feature",
  "properties": {
    "addr:full":"Lusakastr 26 Delft Zuid-Holland 2622 LM",
    "addr:housenumber":"26",
    "addr:postcode":"2622 lm",
    "addr:street":"Lusakastr",
    "iso:country":"NL",
    "sg:address":"Lusakastr 26",
    "sg:city":"Delft",
    "sg:orig_category":"Metselwerken",
    "sg:phone":"+31 15 256 2797",
    "sg:postcode":"2622 LM",
    "sg:province":"Zuid-Holland",
    "wof:name":"Breedveld",
    "wof:placetype":"venue"
},
  "geometry": {"coordinates":[4.340063,51.980911],"type":"Point"}
}