{
  "type": "Feature",
  "properties": {
    "addr:full":"Bouwery 4 Amstelveen Noord-Holland 1185 XX",
    "addr:housenumber":"4",
    "addr:postcode":"1185 xx",
    "addr:street":"Bouwery",
    "iso:country":"NL",
    "sg:address":"Bouwery 4",
    "sg:city":"Amstelveen",
    "sg:orig_category":"Adviesbureaus Bedrijfsorganisatie",
    "sg:phone":"+31 20 453 6522",
    "sg:postcode":"1185 XX",
    "sg:province":"Noord-Holland",
    "sg:website":"http://www.itasc.nl",
    "wof:name":"Itasc Amsterdam Bv",
    "wof:placetype":"venue"
},
  "geometry": {"coordinates":[4.839631,52.283443],"type":"Point"}
}