{
  "type": "Feature",
  "properties": {
    "iso:country":"NL",
    "sg:address":"Aldringastraat 36",
    "sg:city":"Niekerk Grootegast",
    "sg:orig_category":"Diverse Consumentenartikelen Gh",
    "sg:phone":"+31 594 504 070",
    "sg:postcode":"9822 AN",
    "sg:province":"Groningen",
    "wof:name":"Fries-Groningse Handelsonderneming",
    "wof:placetype":"venue"
},
  "geometry": {"coordinates":[6.354383,53.223331],"type":"Point"}
}