{
  "type": "Feature",
  "properties": {
    "addr:full":"Kleiweg 27 Gouda Zuid-Holland 2801 GB",
    "addr:housenumber":"27",
    "addr:postcode":"2801 gb",
    "addr:street":"Kleiweg",
    "iso:country":"NL",
    "sg:address":"Kleiweg 27",
    "sg:city":"Gouda",
    "sg:orig_category":"Discountwinkels",
    "sg:phone":"+31 182 599 381",
    "sg:postcode":"2801 GB",
    "sg:province":"Zuid-Holland",
    "wof:name":"Zeeman Textielsupers",
    "wof:placetype":"venue"
},
  "geometry": {"coordinates":[4.709919,52.013577],"type":"Point"}
}