{
  "type": "Feature",
  "properties": {
    "addr:full":"Vryheidstr 19 Heerlen Limburg 6418 AG",
    "addr:housenumber":"19",
    "addr:postcode":"6418",
    "addr:street":"Vryheidstr",
    "iso:country":"NL",
    "sg:address":"Vryheidstr 19",
    "sg:city":"Heerlen",
    "sg:orig_category":"Administratie- En Boekhoudkantoren",
    "sg:phone":"+31 45 541 1476",
    "sg:postcode":"6418 AG",
    "sg:province":"Limburg",
    "wof:name":"Hundscheid",
    "wof:placetype":"venue"
},
  "geometry": {"coordinates":[5.996815,50.873501],"type":"Point"}
}