{
  "type": "Feature",
  "properties": {
    "addr:full":"Engelse Kamp 6 Groningen Groningen 9722 AX",
    "addr:housenumber":"6",
    "addr:postcode":"9722 ax",
    "addr:street":"Engelse Kamp",
    "iso:country":"NL",
    "sg:address":"Engelse Kamp 6",
    "sg:city":"Groningen",
    "sg:orig_category":"Vakorganisaties",
    "sg:phone":"+31 50 363 1000",
    "sg:postcode":"9722 AX",
    "sg:province":"Groningen",
    "sg:website":"http://www.fnv.nl",
    "wof:name":"Fnv Bondgenoten",
    "wof:placetype":"venue"
},
  "geometry": {"coordinates":[6.581283,53.202644],"type":"Point"}
}