{
  "type": "Feature",
  "properties": {
    "addr:full":"Van Konijnenburgstraat 151 Haarlem North Holland 2035 XH",
    "addr:housenumber":"151",
    "addr:postcode":"2035 xh",
    "addr:street":"Van Konijnenburgstraat",
    "iso:country":"NL",
    "sg:address":"Van Konijnenburgstraat 151",
    "sg:city":"Haarlem",
    "sg:orig_category":"Verhuisdiensten",
    "sg:phone":"+31 23 533 2722",
    "sg:postcode":"2035 XH",
    "sg:province":"North Holland",
    "wof:name":"C. Schreuder",
    "wof:placetype":"venue"
},
  "geometry": {"coordinates":[4.6661,52.365482],"type":"Point"}
}