{
  "type": "Feature",
  "properties": {
    "addr:full":"Groenewg 1 Colynsplaat Zeeland 4486 RA",
    "addr:housenumber":"1",
    "addr:postcode":"4486 ra",
    "addr:street":"Groenewg;Zeeland",
    "iso:country":"NL",
    "sg:address":"Groenewg 1",
    "sg:city":"Colynsplaat",
    "sg:orig_category":"Adviesbureaus",
    "sg:phone":"+31 113 695 788",
    "sg:postcode":"4486 RA",
    "sg:province":"Zeeland",
    "wof:name":"Wisse, Aly",
    "wof:placetype":"venue"
},
  "geometry": {"coordinates":[3.799868,51.585026],"type":"Point"}
}