{
  "type": "Feature",
  "properties": {
    "addr:full":"Passage 13 Oeffelt Noord-Brabant 5441 BS",
    "addr:housenumber":"13",
    "addr:postcode":"5441 bs",
    "addr:street":"Passage",
    "iso:country":"NL",
    "sg:address":"Passage 13",
    "sg:city":"Oeffelt",
    "sg:orig_category":"Verenigingen En Stichtingen",
    "sg:phone":"+31 485 362 229",
    "sg:postcode":"5441 BS",
    "sg:province":"Noord-Brabant",
    "wof:name":"Steunpunt Passage Oeffelt",
    "wof:placetype":"venue"
},
  "geometry": {"coordinates":[5.936224,51.695011],"type":"Point"}
}