{
  "type": "Feature",
  "properties": {
    "addr:full":"Molenwal 2 Steenwijk Overijssel 8331 HT",
    "addr:housenumber":"2",
    "addr:postcode":"8331 ht",
    "addr:street":"Molenwal",
    "iso:country":"NL",
    "sg:address":"Molenwal 2",
    "sg:city":"Steenwijk",
    "sg:orig_category":"Verzekeringen",
    "sg:phone":"+31 521 512 182",
    "sg:postcode":"8331 HT",
    "sg:province":"Overijssel",
    "wof:name":"Assurantiekant M H Kuiper",
    "wof:placetype":"venue"
},
  "geometry": {"coordinates":[6.12013,52.786987],"type":"Point"}
}