{
  "type": "Feature",
  "properties": {
    "iso:country":"NL",
    "sg:address":"De Zuidmaten 12",
    "sg:city":"Beilen",
    "sg:orig_category":"Fitnesscentra",
    "sg:phone":"+31 593 526 621",
    "sg:postcode":"9411 PT",
    "sg:province":"Drenthe",
    "wof:name":"Fitnesscentrum Body Art",
    "wof:placetype":"venue"
},
  "geometry": {"coordinates":[6.518199,52.851509],"type":"Point"}
}