{
  "type": "Feature",
  "properties": {
    "addr:full":"De Zuidmaten 12 Beilen Drenthe 9411 PT",
    "addr:housenumber":"12",
    "addr:postcode":"9411 pt",
    "addr:street":"De Zuidmaten",
    "iso:country":"NL",
    "sg:address":"De Zuidmaten 12",
    "sg:city":"Beilen",
    "sg:orig_category":"Fitnesscentra",
    "sg:phone":"+31 593 526 621",
    "sg:postcode":"9411 PT",
    "sg:province":"Drenthe",
    "wof:name":"Fitnesscentrum Body Art",
    "wof:placetype":"venue"
},
  "geometry": {"coordinates":[6.518199,52.851509],"type":"Point"}
}