{
  "type": "Feature",
  "properties": {
    "addr:full":"Aalsmeerderweg 882 Rijsenhout Noord-Holland 1435 EX",
    "addr:housenumber":"882",
    "addr:postcode":"1435 ex",
    "addr:street":"Aalsmeerderweg",
    "iso:country":"NL",
    "sg:address":"Aalsmeerderweg 882",
    "sg:city":"Rijsenhout",
    "sg:orig_category":"Bloemen And Planten",
    "sg:phone":"+31 297 322 799",
    "sg:postcode":"1435 EX",
    "sg:province":"Noord-Holland",
    "wof:name":"Handelskwekerij Humako Bv",
    "wof:placetype":"venue"
},
  "geometry": {"coordinates":[4.698385,52.254097],"type":"Point"}
}