{
  "type": "Feature",
  "properties": {
    "addr:full":"Corridor 4 Valkenswaard Noord-Brabant 5554 HM",
    "addr:housenumber":"4",
    "addr:postcode":"5554 hm",
    "addr:street":"Corridor",
    "iso:country":"NL",
    "sg:address":"Corridor 4",
    "sg:city":"Valkenswaard",
    "sg:orig_category":"Opticiens",
    "sg:phone":"+31 40 204 4540",
    "sg:postcode":"5554 HM",
    "sg:province":"Noord-Brabant",
    "wof:name":"Hans Anders Opticiens",
    "wof:placetype":"venue"
},
  "geometry": {"coordinates":[5.4609718323,51.3523406982],"type":"Point"}
}