{
  "type": "Feature",
  "properties": {
    "addr:full":"Europalaan 40 Stadskanaal Groningen 9501 CW",
    "addr:housenumber":"40",
    "addr:postcode":"9501 cw",
    "addr:street":"Europalaan",
    "iso:country":"NL",
    "sg:address":"Europalaan 40",
    "sg:city":"Stadskanaal",
    "sg:classifiers":[
        {
            "category":"Shopping",
            "subcategory":"Bicycles & Sporting Goods",
            "type":"Retail Goods"
        }
    ],
    "sg:phone":"+31 599 618 024",
    "sg:postcode":"9501 CW",
    "sg:province":"Groningen",
    "sg:tags":[
        "sport-",
        "kampeerartikelen"
    ],
    "wof:name":"Vof Sporthuis De Jonge",
    "wof:placetype":"venue"
},
  "geometry": {"coordinates":[6.953876,52.988155],"type":"Point"}
}