{
  "type": "Feature",
  "properties": {
    "addr:full":"Vaesrade 56 Nuth Limburg 6361 HH",
    "addr:housenumber":"56",
    "addr:postcode":"6361 hh",
    "addr:street":"Vaesrade",
    "iso:country":"NL",
    "sg:address":"Vaesrade 56",
    "sg:city":"Nuth",
    "sg:orig_category":"Meubelzaken, Woning- And Keukeninrichting",
    "sg:phone":"+31 45 524 5901",
    "sg:postcode":"6361 HH",
    "sg:province":"Limburg",
    "wof:name":"Romantisch Wonen",
    "wof:placetype":"venue"
},
  "geometry": {"coordinates":[5.90282,50.929977],"type":"Point"}
}