{
  "type": "Feature",
  "properties": {
    "addr:full":"Tussen Meer 339 Amsterdam North Holland 1069 DR",
    "addr:housenumber":"339",
    "addr:postcode":"1069 dr",
    "addr:street":"Tussen Meer",
    "iso:country":"NL",
    "sg:address":"Tussen Meer 339",
    "sg:city":"Amsterdam",
    "sg:orig_category":"Kappers",
    "sg:phone":"+31 20 619 9526",
    "sg:postcode":"1069 DR",
    "sg:province":"North Holland",
    "wof:name":"Sterk, Pim",
    "wof:placetype":"venue"
},
  "geometry": {"coordinates":[4.793007,52.356594],"type":"Point"}
}