{
  "type": "Feature",
  "properties": {
    "addr:full":"Amersfoortsewg 40 Maarn Utrecht 3951 LC",
    "addr:housenumber":"40",
    "addr:postcode":"3951 lc",
    "addr:street":"Amersfoortsewg",
    "iso:country":"NL",
    "sg:address":"Amersfoortsewg 40",
    "sg:city":"Maarn",
    "sg:orig_category":"Meubelen - Fabrieken En Groothandel",
    "sg:phone":"+31 343 442 644",
    "sg:postcode":"3951 LC",
    "sg:province":"Utrecht",
    "wof:name":"Meubin Bv",
    "wof:placetype":"venue"
},
  "geometry": {"coordinates":[5.357675,52.064915],"type":"Point"}
}