{
  "type": "Feature",
  "properties": {
    "addr:full":"S Robertsonln 16 Amstelveen North Holland 1187 PK",
    "addr:housenumber":"16",
    "addr:postcode":"1187 pk",
    "iso:country":"NL",
    "sg:address":"S Robertsonln 16",
    "sg:city":"Amstelveen",
    "sg:orig_category":"Adviesbureaus Bedrijfsorganisatie",
    "sg:phone":"+31 20 643 2993",
    "sg:postcode":"1187 PK",
    "sg:province":"North Holland",
    "wof:name":"Totus Cons Bv",
    "wof:placetype":"venue"
},
  "geometry": {"coordinates":[4.82836,52.284748],"type":"Point"}
}