{
  "type": "Feature",
  "properties": {
    "addr:full":"Spaceshuttle 8C Amersfoort Utrecht 3824 ML",
    "addr:housenumber":"8c",
    "addr:postcode":"3824 ml",
    "addr:street":"Spaceshuttle",
    "iso:country":"NL",
    "sg:address":"Spaceshuttle 8C",
    "sg:city":"Amersfoort",
    "sg:orig_category":"Verf En Lak - Fabrieken En Groothandel",
    "sg:phone":"+31 33 456 7100",
    "sg:postcode":"3824 ML",
    "sg:province":"Utrecht",
    "sg:website":"http://www.bevela.nl",
    "wof:name":"Bevela Bv",
    "wof:placetype":"venue"
},
  "geometry": {"coordinates":[5.392178,52.195972],"type":"Point"}
}