{
  "type": "Feature",
  "properties": {
    "addr:full":"Cobrastraat 8 Almere Flevoland 1338 HL",
    "addr:housenumber":"8",
    "addr:postcode":"1338 hl",
    "addr:street":"Cobrastraat;Flevoland",
    "iso:country":"NL",
    "sg:address":"Cobrastraat 8",
    "sg:city":"Almere",
    "sg:orig_category":"Binnenhuisarchitecten",
    "sg:phone":"+31 36 532 5340",
    "sg:postcode":"1338 HL",
    "sg:province":"Flevoland",
    "wof:name":"Bureau Le Grand Interieur-Architectuur",
    "wof:placetype":"venue"
},
  "geometry": {"coordinates":[5.271457,52.382084],"type":"Point"}
}