{
  "type": "Feature",
  "properties": {
    "addr:full":"Ieplaan 141 Rijswijk Zh Zuid-Holland 2282 CZ",
    "addr:housenumber":"141",
    "addr:postcode":"zh;2282",
    "addr:street":"Ieplaan",
    "iso:country":"NL",
    "sg:address":"Ieplaan 141",
    "sg:city":"Rijswijk Zh",
    "sg:orig_category":"Algemene Werktuigbouw",
    "sg:phone":"+31 70 414 0901",
    "sg:postcode":"2282 CZ",
    "sg:province":"Zuid-Holland",
    "wof:name":"Hofman Installatie Techniek",
    "wof:placetype":"venue"
},
  "geometry": {"coordinates":[4.338425,52.051933],"type":"Point"}
}