{
  "type": "Feature",
  "properties": {
    "iso:country":"NL",
    "sg:address":"Luttekestr 62",
    "sg:city":"Zwolle",
    "sg:orig_category":"Bloemen En Planten",
    "sg:phone":"+31 38 422 7597",
    "sg:postcode":"8011 LS",
    "sg:province":"NL.08",
    "wof:name":"Plasant",
    "wof:placetype":"venue"
},
  "geometry": {"coordinates":[6.090228,52.510902],"type":"Point"}
}