{
  "type": "Feature",
  "properties": {
    "addr:full":"V Keppelmarke 31 Zwolle NL.08 8016 GH",
    "addr:housenumber":"31",
    "addr:postcode":"8016 gh",
    "addr:street":"V Keppelmarke",
    "iso:country":"NL",
    "sg:address":"V Keppelmarke 31",
    "sg:city":"Zwolle",
    "sg:orig_category":"Adviesbureaus Bedrijfsorganisatie",
    "sg:phone":"+31 38 460 1671",
    "sg:postcode":"8016 GH",
    "sg:province":"NL.08",
    "wof:name":"Langcom",
    "wof:placetype":"venue"
},
  "geometry": {"coordinates":[6.098511,52.488434],"type":"Point"}
}