{
  "type": "Feature",
  "properties": {
    "addr:full":"Veenestr 60B Bunschoten Spakenb Utrecht 3751 GJ",
    "addr:housenumber":"60b",
    "addr:postcode":"3751 gj",
    "addr:street":"Veenestr",
    "iso:country":"NL",
    "sg:address":"Veenestr 60B",
    "sg:city":"Bunschoten Spakenb",
    "sg:orig_category":"Parketvloeren",
    "sg:phone":"+31 33 298 3270",
    "sg:postcode":"3751 GJ",
    "sg:province":"Utrecht",
    "wof:name":"Aa Eerlijk Hout",
    "wof:placetype":"venue"
},
  "geometry": {"coordinates":[5.371586,52.23262],"type":"Point"}
}