{
  "type": "Feature",
  "properties": {
    "addr:full":"Rozengr 60 Amsterdam North Holland 1016 ND",
    "addr:housenumber":"60",
    "addr:postcode":"1016 nd",
    "addr:street":"Rozengr",
    "iso:country":"NL",
    "sg:address":"Rozengr 60",
    "sg:city":"Amsterdam",
    "sg:orig_category":"Geschenkartikelen",
    "sg:phone":"+31 20 320 9490",
    "sg:postcode":"1016 ND",
    "sg:province":"North Holland",
    "wof:name":"Cibali",
    "wof:placetype":"venue"
},
  "geometry": {"coordinates":[4.880804,52.373566],"type":"Point"}
}