{
  "type": "Feature",
  "properties": {
    "addr:full":"Sperwerhoek 26 Spykenisse South Holland 3201 SK",
    "addr:housenumber":"26",
    "addr:street":"Sperwerhoek;3201",
    "iso:country":"NL",
    "sg:address":"Sperwerhoek 26",
    "sg:city":"Spykenisse",
    "sg:orig_category":"Bedrijfsopleidingen",
    "sg:phone":"+31 6 51157217",
    "sg:postcode":"3201 SK",
    "sg:province":"South Holland",
    "wof:name":"Hartmann'S Teamland",
    "wof:placetype":"venue"
},
  "geometry": {"coordinates":[4.325045,51.849525],"type":"Point"}
}