{
  "type": "Feature",
  "properties": {
    "addr:full":"Palmweg 43 Doorn Utrecht 3941 BN",
    "addr:housenumber":"43",
    "addr:postcode":"3941 bn",
    "addr:street":"Palmweg",
    "iso:country":"NL",
    "sg:address":"Palmweg 43",
    "sg:city":"Doorn",
    "sg:orig_category":"Boekhouders",
    "sg:phone":"+31 343 420 668",
    "sg:postcode":"3941 BN",
    "sg:province":"Utrecht",
    "wof:name":"S.B.B. Salarissen",
    "wof:placetype":"venue"
},
  "geometry": {"coordinates":[5.317895,52.034645],"type":"Point"}
}