{
  "type": "Feature",
  "properties": {
    "addr:full":"Gyroscoopwg 23 Amsterdam Noord-Holland 1042 AC",
    "addr:housenumber":"23",
    "addr:postcode":"1042 ac",
    "addr:street":"Gyroscoopwg",
    "iso:country":"NL",
    "sg:address":"Gyroscoopwg 23",
    "sg:city":"Amsterdam",
    "sg:orig_category":"Bedrijfsmechanisatie En -Automatisering",
    "sg:phone":"+31 20 447 2777",
    "sg:postcode":"1042 AC",
    "sg:province":"Noord-Holland",
    "sg:website":"http://www.iapbv.nl",
    "wof:name":"Iap Bis",
    "wof:placetype":"venue"
},
  "geometry": {"coordinates":[4.841977,52.4016],"type":"Point"}
}