{
  "type": "Feature",
  "properties": {
    "addr:full":"Torenstr 16 Beerta Groningen 9686 SN",
    "addr:housenumber":"16",
    "addr:postcode":"9686 sn",
    "addr:street":"Torenstr",
    "iso:country":"NL",
    "sg:address":"Torenstr 16",
    "sg:city":"Beerta",
    "sg:orig_category":"Verenigingsgebouwen",
    "sg:phone":"+31 597 333 088",
    "sg:postcode":"9686 SN",
    "sg:province":"Groningen",
    "wof:name":"Iemek\u00f6rf, De",
    "wof:placetype":"venue"
},
  "geometry": {"coordinates":[7.097175,53.174583],"type":"Point"}
}