{
  "type": "Feature",
  "properties": {
    "addr:full":"Warmoesstraat 90 Amsterdam Noord-Holland 1012 JH",
    "addr:housenumber":"90",
    "addr:postcode":"1012 jh",
    "addr:street":"Warmoesstraat",
    "iso:country":"NL",
    "sg:address":"Warmoesstraat 90",
    "sg:city":"Amsterdam",
    "sg:classifiers":[
        {
            "category":"Bars & Pubs",
            "type":"Food & Drink"
        }
    ],
    "sg:phone":"+31 20 627 8634",
    "sg:postcode":"1012 JH",
    "sg:province":"Noord-Holland",
    "wof:name":"Bar The Eagle",
    "wof:placetype":"venue"
},
  "geometry": {"coordinates":[4.896907,52.374695],"type":"Point"}
}