{
  "type": "Feature",
  "properties": {
    "addr:full":"Verlengde Vaart Zz 75 Erica Drenthe 7887 EN",
    "addr:housenumber":"75",
    "addr:postcode":"7887 en",
    "addr:street":"Verlengde Vaart Zz",
    "iso:country":"NL",
    "sg:address":"Verlengde Vaart Zz 75",
    "sg:city":"Erica",
    "sg:classifiers":[
        {
            "category":"Travel",
            "subcategory":"Hotels & Motels",
            "type":"Entertainment"
        }
    ],
    "sg:phone":"+31 591 301 391",
    "sg:postcode":"7887 EN",
    "sg:province":"Drenthe",
    "wof:name":"Hotel Restaurant Het Centrum",
    "wof:placetype":"venue"
},
  "geometry": {"coordinates":[6.924588,52.70956],"type":"Point"}
}