{
  "type": "Feature",
  "properties": {
    "addr:full":"Archipel 2244 Lelystad Flevoland 8224 GN",
    "addr:postcode":"2244;8224 gn",
    "addr:street":"Archipel;Flevoland",
    "iso:country":"NL",
    "sg:address":"Archipel 2244",
    "sg:city":"Lelystad",
    "sg:orig_category":"Bedrijfs- And Managementsconsultants",
    "sg:phone":"+31 320 232 709",
    "sg:postcode":"8224 GN",
    "sg:province":"Flevoland",
    "wof:name":"B. Berendsen",
    "wof:placetype":"venue"
},
  "geometry": {"coordinates":[5.486394,52.509422],"type":"Point"}
}