{
  "type": "Feature",
  "properties": {
    "addr:full":"V Gilseln 86 Roosendaal Noord-Brabant 4702 GM",
    "addr:housenumber":"86",
    "addr:postcode":"4702 gm",
    "iso:country":"NL",
    "sg:address":"V Gilseln 86",
    "sg:city":"Roosendaal",
    "sg:orig_category":"Adviesbureaus Economie",
    "sg:phone":"+31 165 521 555",
    "sg:postcode":"4702 GM",
    "sg:province":"Noord-Brabant",
    "wof:name":"Vooghden, Drs A C",
    "wof:placetype":"venue"
},
  "geometry": {"coordinates":[4.45767,51.531403],"type":"Point"}
}