{
  "type": "Feature",
  "properties": {
    "addr:full":"Stationswg 3 Leeuwarden Friesland 8911 AG",
    "addr:housenumber":"3",
    "addr:postcode":"8911",
    "addr:street":"Stationswg",
    "iso:country":"NL",
    "sg:address":"Stationswg 3",
    "sg:city":"Leeuwarden",
    "sg:orig_category":"Fietsen En Bromfietsen Stalling",
    "sg:phone":"+31 58 213 9800",
    "sg:postcode":"8911 AG",
    "sg:province":"Friesland",
    "wof:name":"Vries, J De",
    "wof:placetype":"venue"
},
  "geometry": {"coordinates":[5.794088,53.196735],"type":"Point"}
}