{
  "type": "Feature",
  "properties": {
    "addr:full":"Sophiawg 6 Nymegen Gelderland 6523 NJ",
    "addr:housenumber":"6",
    "addr:postcode":"6523",
    "addr:street":"Sophiawg;Gelderland",
    "iso:country":"NL",
    "sg:address":"Sophiawg 6",
    "sg:city":"Nymegen",
    "sg:orig_category":"Verenigingen En Stichtingen",
    "sg:phone":"+31 24 322 9269",
    "sg:postcode":"6523 NJ",
    "sg:province":"Gelderland",
    "sg:website":"http://www.st-moria.nl",
    "wof:name":"Moria, Sticht",
    "wof:placetype":"venue"
},
  "geometry": {"coordinates":[-74.72672300000001,40.14278],"type":"Point"}
}