{
  "type": "Feature",
  "properties": {
    "addr:full":"Roermondseweg 119 Weert Limburg 6004 AR",
    "addr:housenumber":"119",
    "addr:postcode":"6004",
    "addr:street":"Roermondseweg",
    "iso:country":"NL",
    "sg:address":"Roermondseweg 119",
    "sg:city":"Weert",
    "sg:orig_category":"Verhuur Bouwmachines",
    "sg:phone":"+31 495 531 207",
    "sg:postcode":"6004 AR",
    "sg:province":"Limburg",
    "wof:name":"Themarent Bv",
    "wof:placetype":"venue"
},
  "geometry": {"coordinates":[5.734085,51.248329],"type":"Point"}
}