{
  "type": "Feature",
  "properties": {
    "addr:full":"Nw Steen 2 Hoorn Nh North Holland 1625 HV",
    "addr:housenumber":"2",
    "addr:postcode":"1625 hv",
    "addr:street":"Nw Steen;Nh North",
    "iso:country":"NL",
    "sg:address":"Nw Steen 2",
    "sg:city":"Hoorn Nh",
    "sg:orig_category":"Administratie- En Boekhoudkantoren",
    "sg:phone":"+31 229 299 723",
    "sg:postcode":"1625 HV",
    "sg:province":"North Holland",
    "sg:website":"http://www.admi-lux.nl",
    "wof:name":"Admi-Lux",
    "wof:placetype":"venue"
},
  "geometry": {"coordinates":[5.05321,52.655369],"type":"Point"}
}