{
  "type": "Feature",
  "properties": {
    "iso:country":"NL",
    "sg:address":"Eewal 51",
    "sg:city":"Leeuwarden",
    "sg:orig_category":"Accountants - Administratie- Consulenten En -Kantoren",
    "sg:phone":"+31 58 212 4969",
    "sg:postcode":"8911 GR",
    "sg:province":"Friesland",
    "wof:name":"Vries, S De",
    "wof:placetype":"venue"
},
  "geometry": {"coordinates":[5.79257,53.197319],"type":"Point"}
}