{
  "type": "Feature",
  "properties": {
    "addr:full":"De Kampen 39 Engwierum Friesland 9132 LV",
    "addr:housenumber":"39",
    "addr:postcode":"9132",
    "addr:street":"De Kampen",
    "iso:country":"NL",
    "sg:address":"De Kampen 39",
    "sg:city":"Engwierum",
    "sg:classifiers":[
        {
            "category":"Education",
            "subcategory":"Preschool",
            "type":"Public Place"
        }
    ],
    "sg:phone":"+31 511 408 500",
    "sg:postcode":"9132 LV",
    "sg:province":"Friesland",
    "sg:tags":[
        "kleuteronderwijs",
        "basis-"
    ],
    "wof:name":"De Springplanke Chr Basisschool",
    "wof:placetype":"venue"
},
  "geometry": {"coordinates":[6.139109,53.318565],"type":"Point"}
}