{
  "type": "Feature",
  "properties": {
    "addr:full":"Postbus 51211 Amsterdam Noord-Brabant 1007 EE",
    "addr:housenumber":"51211",
    "addr:postcode":"1007 ee",
    "addr:street":"Postbus",
    "iso:country":"NL",
    "sg:address":"Postbus 51211",
    "sg:city":"Amsterdam",
    "sg:orig_category":"Webdesign Bureaus",
    "sg:phone":"+31 20 671 7666",
    "sg:postcode":"1007 EE",
    "sg:province":"Noord-Brabant",
    "sg:website":"http://www.abeleto.nl",
    "wof:name":"Abeleto",
    "wof:placetype":"venue"
},
  "geometry": {"coordinates":[4.8920497894,52.373550415],"type":"Point"}
}