{
  "type": "Feature",
  "properties": {
    "addr:full":"Zandvoortseln 8/B Heemstede Noord-Holland 2106 CN",
    "addr:housenumber":"8 / b",
    "addr:postcode":"2106 cn",
    "addr:street":"Zandvoortseln",
    "iso:country":"NL",
    "sg:address":"Zandvoortseln 8/B",
    "sg:city":"Heemstede",
    "sg:orig_category":"Bloemen En Planten",
    "sg:phone":"+31 23 528 5024",
    "sg:postcode":"2106 CN",
    "sg:province":"Noord-Holland",
    "wof:name":"Gerard'S, Flowershop",
    "wof:placetype":"venue"
},
  "geometry": {"coordinates":[4.611614,52.359344],"type":"Point"}
}