{
  "type": "Feature",
  "properties": {
    "iso:country":"NL",
    "sg:address":"Runstr 4",
    "sg:city":"Eindhoven",
    "sg:orig_category":"Homeopathie",
    "sg:phone":"+31 40 245 0171",
    "sg:postcode":"5622 AZ",
    "sg:province":"Noord-Brabant",
    "wof:name":"Beek & Heesakkers, A & H",
    "wof:placetype":"venue"
},
  "geometry": {"coordinates":[5.470201,51.456032],"type":"Point"}
}