{
  "type": "Feature",
  "properties": {
    "addr:full":"Vierwiekenplein 25 Oud Beijerland Zuid-Holland 3262 AN",
    "addr:housenumber":"25",
    "addr:postcode":"3262 an",
    "addr:street":"Vierwiekenplein;Oud Beijerland",
    "iso:country":"NL",
    "sg:address":"Vierwiekenplein 25",
    "sg:city":"Oud Beijerland",
    "sg:classifiers":[
        {
            "category":"Fast Food",
            "type":"Food & Drink"
        }
    ],
    "sg:phone":"+31 186 613 001",
    "sg:postcode":"3262 AN",
    "sg:province":"Zuid-Holland",
    "sg:tags":[
        "afhaal",
        "restaurant"
    ],
    "wof:name":"De Wiekslag",
    "wof:placetype":"venue"
},
  "geometry": {"coordinates":[4.410033,51.827789],"type":"Point"}
}