{
  "type": "Feature",
  "properties": {
    "addr:full":"Hof V Azuur 49 Delft Zuid-Holland 2614 TB",
    "addr:housenumber":"49",
    "addr:postcode":"2614 tb",
    "addr:street":"Azuur",
    "iso:country":"NL",
    "sg:address":"Hof V Azuur 49",
    "sg:city":"Delft",
    "sg:orig_category":"Journalisten Freelance",
    "sg:phone":"+31 15 213 3531",
    "sg:postcode":"2614 TB",
    "sg:province":"Zuid-Holland",
    "sg:website":"http://www.studio-9.nl",
    "wof:name":"Braun, Luuk",
    "wof:placetype":"venue"
},
  "geometry": {"coordinates":[4.35869,52.011505],"type":"Point"}
}