{
  "type": "Feature",
  "properties": {
    "iso:country":"NL",
    "sg:address":"Hoekstraat 23",
    "sg:city":"Nuenen",
    "sg:orig_category":"Organisaties And Verenigingen",
    "sg:phone":"+31 40 284 1197",
    "sg:postcode":"5674 NN",
    "sg:province":"Noord-Brabant",
    "wof:name":"T Roedelke",
    "wof:placetype":"venue"
},
  "geometry": {"coordinates":[5.5242900848,51.4918708801],"type":"Point"}
}