{
  "type": "Feature",
  "properties": {
    "addr:full":"Hornwg 91A Aalsmeer North Holland 1432 GE",
    "addr:housenumber":"91a",
    "addr:postcode":"1432",
    "addr:street":"Hornwg",
    "iso:country":"NL",
    "sg:address":"Hornwg 91A",
    "sg:city":"Aalsmeer",
    "sg:orig_category":"Verhuur",
    "sg:phone":"+31 297 321 997",
    "sg:postcode":"1432 GE",
    "sg:province":"North Holland",
    "wof:name":"Tropicana",
    "wof:placetype":"venue"
},
  "geometry": {"coordinates":[4.785733,52.268093],"type":"Point"}
}