{
  "type": "Feature",
  "properties": {
    "addr:full":"Canadastraat 48 Heino Minnesota 8141 AD",
    "addr:housenumber":"48",
    "addr:postcode":"8141 ad",
    "addr:street":"Canadastraat;Minnesota",
    "iso:country":"NL",
    "sg:address":"Canadastraat 48",
    "sg:city":"Heino",
    "sg:orig_category":"Kappers",
    "sg:phone":"+31 572 391 413",
    "sg:postcode":"8141 AD",
    "sg:province":"Minnesota",
    "wof:name":"Haarmode 'T Spiegelbeeld",
    "wof:placetype":"venue"
},
  "geometry": {"coordinates":[-95.39873504640001,46.4989051819],"type":"Point"}
}