{
  "type": "Feature",
  "properties": {
    "addr:full":"Van Weedestraat 84 Soest Utrecht 3761 CH",
    "addr:housenumber":"84",
    "addr:postcode":"3761",
    "addr:street":"Van Weedestraat",
    "iso:country":"NL",
    "sg:address":"Van Weedestraat 84",
    "sg:city":"Soest",
    "sg:orig_category":"Discountwinkels",
    "sg:phone":"+31 35 602 9813",
    "sg:postcode":"3761 CH",
    "sg:province":"Utrecht",
    "wof:name":"Zeeman Textielsupers",
    "wof:placetype":"venue"
},
  "geometry": {"coordinates":[5.294486,52.186764],"type":"Point"}
}