{
  "type": "Feature",
  "properties": {
    "addr:full":"Beurspln 37 Wtc Rotterdam South Holland 3011 AA",
    "addr:housenumber":"37",
    "addr:postcode":"3011 aa",
    "addr:street":"Beurspln",
    "iso:country":"NL",
    "sg:address":"Beurspln 37 Wtc",
    "sg:city":"Rotterdam",
    "sg:classifiers":[
        {
            "category":"Wholesale",
            "subcategory":"Motor Vehicles",
            "type":"Manufacturing & Wholesale Goods"
        }
    ],
    "sg:phone":"+31 10 281 6790",
    "sg:postcode":"3011 AA",
    "sg:province":"South Holland",
    "sg:tags":[
        "scooter",
        "en"
    ],
    "wof:name":"Shelter Bv",
    "wof:placetype":"venue"
},
  "geometry": {"coordinates":[4.478455,51.922836],"type":"Point"}
}