{
  "type": "Feature",
  "properties": {
    "addr:full":"Velswykwg 46 Zelhem Gelderland 7021 KT",
    "addr:housenumber":"46",
    "addr:postcode":"7021 kt",
    "addr:street":"Velswykwg;Gelderland",
    "iso:country":"NL",
    "sg:address":"Velswykwg 46",
    "sg:city":"Zelhem",
    "sg:orig_category":"Scholen Voor Basisonderwijs",
    "sg:phone":"+31 314 641 655",
    "sg:postcode":"7021 KT",
    "sg:province":"Gelderland",
    "wof:name":"Velswijk Openb",
    "wof:placetype":"venue"
},
  "geometry": {"coordinates":[6.30298,52.010452],"type":"Point"}
}