{
  "type": "Feature",
  "properties": {
    "addr:full":"Van Nesstraat 21 Haarlem North Holland 2024 DK",
    "addr:housenumber":"21",
    "addr:postcode":"2024 dk",
    "addr:street":"Van Nesstraat",
    "iso:country":"NL",
    "sg:address":"Van Nesstraat 21",
    "sg:city":"Haarlem",
    "sg:orig_category":"Farmaceutische Producten Gh",
    "sg:phone":"+31 23 526 6771",
    "sg:postcode":"2024 DK",
    "sg:province":"North Holland",
    "wof:name":"Fa De Jager",
    "wof:placetype":"venue"
},
  "geometry": {"coordinates":[4.646918,52.405083],"type":"Point"}
}