{
  "type": "Feature",
  "properties": {
    "addr:full":"Achterom 16 Papendrecht Zuid-Holland 3351 PC",
    "addr:housenumber":"16",
    "addr:postcode":"3351 pc",
    "addr:street":"Achterom",
    "iso:country":"NL",
    "sg:address":"Achterom 16",
    "sg:city":"Papendrecht",
    "sg:classifiers":[
        {
            "category":"Communications",
            "subcategory":"Television Station",
            "type":"Services"
        }
    ],
    "sg:postcode":"3351 PC",
    "sg:province":"Zuid-Holland",
    "sg:tags":[
        "video",
        "audio",
        "verhuur"
    ],
    "wof:name":"Videoland Papendrecht Verhuurautomaat",
    "wof:placetype":"venue"
},
  "geometry": {"coordinates":[4.68263,51.825909],"type":"Point"}
}