{
  "type": "Feature",
  "properties": {
    "addr:full":"Raadhuisplein 132 Krimpen Aan Den Ijssel South Holland 2922 AL",
    "addr:housenumber":"132",
    "addr:postcode":"2922 al",
    "addr:street":"Raadhuisplein",
    "iso:country":"NL",
    "sg:address":"Raadhuisplein 132",
    "sg:city":"Krimpen Aan Den Ijssel",
    "sg:orig_category":"Verzekeringen",
    "sg:phone":"+31 180 515 522",
    "sg:postcode":"2922 AL",
    "sg:province":"South Holland",
    "wof:name":"Breijer Assurantien",
    "wof:placetype":"venue"
},
  "geometry": {"coordinates":[4.587833,51.914433],"type":"Point"}
}