{
  "type": "Feature",
  "properties": {
    "addr:full":"De Look 9 Den Hoorn Zh South Holland 2635 GE",
    "addr:housenumber":"9",
    "addr:postcode":"2635",
    "addr:street":"De Look",
    "iso:country":"NL",
    "sg:address":"De Look 9",
    "sg:city":"Den Hoorn Zh",
    "sg:orig_category":"Public Relationbureaus",
    "sg:phone":"+31 15 257 6424",
    "sg:postcode":"2635 GE",
    "sg:province":"South Holland",
    "wof:name":"Remmerswaal Pr Services",
    "wof:placetype":"venue"
},
  "geometry": {"coordinates":[4.328862,52.001972],"type":"Point"}
}