{
  "type": "Feature",
  "properties": {
    "addr:full":"Baarnhoeve 2 Vlaardingen Zuid-Holland 3137 RL",
    "addr:housenumber":"2",
    "addr:postcode":"3137 rl",
    "addr:street":"Baarnhoeve",
    "iso:country":"NL",
    "sg:address":"Baarnhoeve 2",
    "sg:city":"Vlaardingen",
    "sg:orig_category":"Kinderopvang",
    "sg:phone":"+31 10 474 2864",
    "sg:postcode":"3137 RL",
    "sg:province":"Zuid-Holland",
    "sg:website":"http://www.skv.nl",
    "wof:name":"Villa Kakelbont",
    "wof:placetype":"venue"
},
  "geometry": {"coordinates":[4.353923,51.938686],"type":"Point"}
}