{
  "type": "Feature",
  "properties": {
    "addr:full":"Broekstraat 82 Molenschot Noord-Brabant 5124 NK",
    "addr:housenumber":"82",
    "addr:postcode":"5124 nk",
    "addr:street":"Broekstraat",
    "iso:country":"NL",
    "sg:address":"Broekstraat 82",
    "sg:city":"Molenschot",
    "sg:orig_category":"Verhuur Bouwmachines",
    "sg:phone":"+31 161 412 552",
    "sg:postcode":"5124 NK",
    "sg:province":"Noord-Brabant",
    "wof:name":"Van Oosterwijk Molenschot Bv",
    "wof:placetype":"venue"
},
  "geometry": {"coordinates":[4.892526,51.573715],"type":"Point"}
}