{
  "type": "Feature",
  "properties": {
    "addr:full":"Kerkbuurt 243 Sliedrecht Zuid-Holland 3361 BH",
    "addr:housenumber":"243",
    "addr:postcode":"3361 bh",
    "addr:street":"Kerkbuurt",
    "iso:country":"NL",
    "sg:address":"Kerkbuurt 243",
    "sg:city":"Sliedrecht",
    "sg:orig_category":"Boekhouders",
    "sg:phone":"+31 184 416 633",
    "sg:postcode":"3361 BH",
    "sg:province":"Zuid-Holland",
    "wof:name":"Administratiekantoor Klop",
    "wof:placetype":"venue"
},
  "geometry": {"coordinates":[4.767049,51.824512],"type":"Point"}
}