{
  "type": "Feature",
  "properties": {
    "addr:full":"Bergerweg 200 Alkmaar Noord-Holland 1817 MN",
    "addr:housenumber":"200",
    "addr:postcode":"1817 mn",
    "addr:street":"Bergerweg",
    "iso:country":"NL",
    "sg:address":"Bergerweg 200",
    "sg:city":"Alkmaar",
    "sg:orig_category":"Hoger Onderwijs",
    "sg:phone":"+31 72 518 3555",
    "sg:postcode":"1817 MN",
    "sg:province":"Noord-Holland",
    "wof:name":"Conservatorium Hogeschool Alkmaar",
    "wof:placetype":"venue"
},
  "geometry": {"coordinates":[4.724547,52.642151],"type":"Point"}
}