{
  "type": "Feature",
  "properties": {
    "addr:full":"Willem Alexanderstraat 27 Mierlo Noord-Brabant 5731 BD",
    "addr:housenumber":"27",
    "addr:postcode":"5731 bd",
    "addr:street":"Willem Alexanderstraat",
    "iso:country":"NL",
    "sg:address":"Willem Alexanderstraat 27",
    "sg:city":"Mierlo",
    "sg:orig_category":"Boekhouders",
    "sg:phone":"+31 492 662 345",
    "sg:postcode":"5731 BD",
    "sg:province":"Noord-Brabant",
    "wof:name":"Makona Buro Voor Administratie Dienstver",
    "wof:placetype":"venue"
},
  "geometry": {"coordinates":[5.617632,51.442574],"type":"Point"}
}