{
  "type": "Feature",
  "properties": {
    "addr:full":"Goorwg 4 Deurne Noord-Brabant 5752 PR",
    "addr:housenumber":"4",
    "addr:postcode":"5752 pr",
    "addr:street":"Goorwg",
    "iso:country":"NL",
    "sg:address":"Goorwg 4",
    "sg:city":"Deurne",
    "sg:classifiers":[
        {
            "category":"Autos & Motor Vehicles",
            "subcategory":"Automobile Sales",
            "type":"Retail Goods"
        }
    ],
    "sg:phone":"+31 493 312 935",
    "sg:postcode":"5752 PR",
    "sg:province":"Noord-Brabant",
    "sg:tags":[
        "caravan",
        "stalling",
        "-"
    ],
    "wof:name":"Verbaarschot, M J",
    "wof:placetype":"venue"
},
  "geometry": {"coordinates":[5.808501,51.481014],"type":"Point"}
}