{
  "type": "Feature",
  "properties": {
    "iso:country":"NL",
    "sg:address":"Steenweg 24",
    "sg:city":"Moerdijk",
    "sg:orig_category":"Loodgieterswerk, Verwarming And Sanitaire Installaties",
    "sg:phone":"+31 168 412 727",
    "sg:postcode":"4781 AP",
    "sg:province":"Noord-Brabant",
    "wof:name":"De Pienes",
    "wof:placetype":"venue"
},
  "geometry": {"coordinates":[4.630654,51.699764],"type":"Point"}
}