{
  "type": "Feature",
  "properties": {
    "addr:full":"Deldenerstraat 208 Hengelo Ov Overijssel 7555 AJ",
    "addr:housenumber":"208",
    "addr:postcode":"7555 aj",
    "addr:street":"Deldenerstraat;Ov",
    "iso:country":"NL",
    "sg:address":"Deldenerstraat 208",
    "sg:city":"Hengelo Ov",
    "sg:orig_category":"Autokeuringen",
    "sg:phone":"+31 74 291 2686",
    "sg:postcode":"7555 AJ",
    "sg:province":"Overijssel",
    "wof:name":"Jansema'S Tankstation Bv",
    "wof:placetype":"venue"
},
  "geometry": {"coordinates":[6.77567,52.266663],"type":"Point"}
}