{
  "type": "Feature",
  "properties": {
    "addr:full":"De Hanekampen 39 Beilen Provincie Drenthe 9411 XN",
    "addr:housenumber":"39",
    "addr:postcode":"9411 xn",
    "addr:street":"De Hanekampen;Provincie Drenthe",
    "iso:country":"NL",
    "sg:address":"De Hanekampen 39",
    "sg:city":"Beilen",
    "sg:orig_category":"Zoetwaren - Fabrieken En Groothandel",
    "sg:phone":"+31 593 523 671",
    "sg:postcode":"9411 XN",
    "sg:province":"Provincie Drenthe",
    "wof:name":"Visser Vof",
    "wof:placetype":"venue"
},
  "geometry": {"coordinates":[6.515171,52.874729],"type":"Point"}
}