{
  "type": "Feature",
  "properties": {
    "addr:full":"V Ruysdaelln 103 Bergschenhoek South Holland 2661 SH",
    "addr:housenumber":"103",
    "addr:postcode":"2661 sh",
    "iso:country":"NL",
    "sg:address":"V Ruysdaelln 103",
    "sg:city":"Bergschenhoek",
    "sg:classifiers":[
        {
            "category":"Wholesale",
            "subcategory":"Meat",
            "type":"Manufacturing & Wholesale Goods"
        }
    ],
    "sg:phone":"+31 10 522 2646",
    "sg:postcode":"2661 SH",
    "sg:province":"South Holland",
    "sg:tags":[
        "regeltechniek",
        "en",
        "meet-"
    ],
    "sg:website":"http://www.flexim-instruments.nl",
    "wof:name":"Flexim Benelux Bv",
    "wof:placetype":"venue"
},
  "geometry": {"coordinates":[4.500133,51.989536],"type":"Point"}
}