{
  "type": "Feature",
  "properties": {
    "addr:full":"Middendorpsstr 1 Meppen Drenthe 7855 PR",
    "addr:housenumber":"1",
    "addr:postcode":"7855 pr",
    "addr:street":"Middendorpsstr",
    "iso:country":"NL",
    "sg:address":"Middendorpsstr 1",
    "sg:city":"Meppen",
    "sg:orig_category":"Begrafenisverzorging",
    "sg:phone":"+31 6 53944823",
    "sg:postcode":"7855 PR",
    "sg:province":"Drenthe",
    "wof:name":"Laatste Eer, De",
    "wof:placetype":"venue"
},
  "geometry": {"coordinates":[6.696046,52.78162],"type":"Point"}
}