{
  "type": "Feature",
  "properties": {
    "iso:country":"NL",
    "sg:address":"Ommelse Bos 5",
    "sg:city":"Ommel",
    "sg:orig_category":"Pluimveeslachterijen",
    "sg:phone":"+31 493 681 222",
    "sg:postcode":"5724 AZ",
    "sg:province":"Noord-Brabant",
    "sg:website":"http://www.astenhof.nl",
    "wof:name":"Astenhof Bv",
    "wof:placetype":"venue"
},
  "geometry": {"coordinates":[-111.93034400000001,34.168091],"type":"Point"}
}