{
  "type": "Feature",
  "properties": {
    "iso:country":"NL",
    "sg:address":"Essenln 42",
    "sg:city":"Ouderkerk Ad Yssel",
    "sg:orig_category":"Schippers",
    "sg:phone":"+31 180 682 355",
    "sg:postcode":"2935 SN",
    "sg:province":"Zuid-Holland",
    "wof:name":"Dam, J Van",
    "wof:placetype":"venue"
},
  "geometry": {"coordinates":[4.637585,51.932926],"type":"Point"}
}