{
  "type": "Feature",
  "properties": {
    "iso:country":"NL",
    "sg:address":"Gebroken Meeldijk 1",
    "sg:city":"Barendrecht",
    "sg:orig_category":"Goederenvervoer Over De Weg",
    "sg:phone":"+31 180 612 057",
    "sg:postcode":"2991 VB",
    "sg:province":"Zuid-Holland",
    "wof:name":"Wtb Willemstein Transportbedrijf Bv",
    "wof:placetype":"venue"
},
  "geometry": {"coordinates":[4.562275,51.854546],"type":"Point"}
}