{
  "type": "Feature",
  "properties": {
    "addr:full":"Dorpsweg 34 Westerwijtwerd Groningen 9993 TK",
    "addr:housenumber":"34",
    "addr:postcode":"9993 tk",
    "addr:street":"Dorpsweg",
    "iso:country":"NL",
    "sg:address":"Dorpsweg 34",
    "sg:city":"Westerwijtwerd",
    "sg:orig_category":"Goederenvervoer Over De Weg",
    "sg:phone":"+31 595 551 467",
    "sg:postcode":"9993 TK",
    "sg:province":"Groningen",
    "wof:name":"V E Bosman",
    "wof:placetype":"venue"
},
  "geometry": {"coordinates":[6.638666,53.333061],"type":"Point"}
}