{
  "type": "Feature",
  "properties": {
    "addr:full":"Stationspln 5 Bergen Op Zoom Noord-Brabant 4611 BX",
    "addr:housenumber":"5",
    "addr:postcode":"4611 bx",
    "addr:street":"Stationspln",
    "iso:country":"NL",
    "sg:address":"Stationspln 5",
    "sg:city":"Bergen Op Zoom",
    "sg:classifiers":[
        {
            "category":"Travel",
            "subcategory":"Hotels & Motels",
            "type":"Entertainment"
        }
    ],
    "sg:phone":"+31 164 255 557",
    "sg:postcode":"4611 BX",
    "sg:province":"Noord-Brabant",
    "wof:name":"Blauwe Vogel, De",
    "wof:placetype":"venue"
},
  "geometry": {"coordinates":[4.293674,51.495373],"type":"Point"}
}