{
  "type": "Feature",
  "properties": {
    "addr:full":"Kerkstraat 11 Oss Virginia 5341 BK",
    "addr:housenumber":"11",
    "addr:postcode":"5341 bk",
    "addr:street":"Kerkstraat",
    "iso:country":"NL",
    "sg:address":"Kerkstraat 11",
    "sg:city":"Oss",
    "sg:orig_category":"Verlichting And Huishoudartikelen",
    "sg:phone":"+31 412 647 701",
    "sg:postcode":"5341 BK",
    "sg:province":"Virginia",
    "wof:name":"De Louw-Van Der Zanden Verlichting",
    "wof:placetype":"venue"
},
  "geometry": {"coordinates":[-77.235214,38.312599],"type":"Point"}
}