{
  "type": "Feature",
  "properties": {
    "addr:full":"Antilopespoor 605 Maarssen Utrecht 3605 XG",
    "addr:housenumber":"605",
    "addr:postcode":"3605 xg",
    "addr:street":"Antilopespoor",
    "iso:country":"NL",
    "sg:address":"Antilopespoor 605",
    "sg:city":"Maarssen",
    "sg:orig_category":"Milieu",
    "sg:phone":"+31 346 283 218",
    "sg:postcode":"3605 XG",
    "sg:province":"Utrecht",
    "wof:name":"Schriel",
    "wof:placetype":"venue"
},
  "geometry": {"coordinates":[5.035075,52.132423],"type":"Point"}
}