{
  "type": "Feature",
  "properties": {
    "iso:country":"NL",
    "sg:address":"Raadhuisstr 9",
    "sg:city":"Enschede",
    "sg:orig_category":"Schoenen",
    "sg:phone":"+31 53 432 3351",
    "sg:postcode":"7511 HJ",
    "sg:province":"Overijssel",
    "sg:website":"http://www.andreas.shoes.nl",
    "wof:name":"Andreas",
    "wof:placetype":"venue"
},
  "geometry": {"coordinates":[6.896499,52.218609],"type":"Point"}
}