{
  "type": "Feature",
  "properties": {
    "iso:country":"NL",
    "sg:address":"Dorpsstr 25",
    "sg:city":"Kommerzyl",
    "sg:orig_category":"Zalenverhuur",
    "sg:phone":"+31 594 212 354",
    "sg:postcode":"9881 PA",
    "sg:province":"Groningen",
    "wof:name":"Soltketen Dorpshuis",
    "wof:placetype":"venue"
},
  "geometry": {"coordinates":[6.323587,53.285889],"type":"Point"}
}