{
  "type": "Feature",
  "properties": {
    "addr:full":"Nieuwstr 8 Beverwyk Noord-Holland 1941 JG",
    "addr:housenumber":"8",
    "addr:postcode":"1941 jg",
    "addr:street":"Nieuwstr",
    "iso:country":"NL",
    "sg:address":"Nieuwstr 8",
    "sg:city":"Beverwyk",
    "sg:orig_category":"Feestartikelen",
    "sg:phone":"+31 251 218 745",
    "sg:postcode":"1941 JG",
    "sg:province":"Noord-Holland",
    "wof:name":"Feestwinkeltje, 'T",
    "wof:placetype":"venue"
},
  "geometry": {"coordinates":[4.658248,52.480595],"type":"Point"}
}