{
  "type": "Feature",
  "properties": {
    "addr:full":"Brouwerstr 21 Ede Gld Gelderland 6711 AS",
    "addr:housenumber":"21",
    "addr:postcode":"6711 as",
    "addr:street":"Brouwerstr;Gld Gelderland",
    "iso:country":"NL",
    "sg:address":"Brouwerstr 21",
    "sg:city":"Ede Gld",
    "sg:orig_category":"Warenhuizen",
    "sg:phone":"+31 318 693 866",
    "sg:postcode":"6711 AS",
    "sg:province":"Gelderland",
    "sg:website":"http://www.vroomendreesmann.nl",
    "wof:name":"V & D",
    "wof:placetype":"venue"
},
  "geometry": {"coordinates":[5.6697711945,52.0460853577],"type":"Point"}
}