{
  "type": "Feature",
  "properties": {
    "addr:full":"Heutinkstraat 10 Enschede NL.08 7512 GM",
    "addr:housenumber":"10",
    "addr:postcode":"7512 gm",
    "addr:street":"Heutinkstraat",
    "iso:country":"NL",
    "sg:address":"Heutinkstraat 10",
    "sg:city":"Enschede",
    "sg:orig_category":"Muziekinstrumenten",
    "sg:phone":"+31 53 430 7249",
    "sg:postcode":"7512 GM",
    "sg:province":"NL.08",
    "wof:name":"W. Beijes",
    "wof:placetype":"venue"
},
  "geometry": {"coordinates":[6.90534,52.216061],"type":"Point"}
}