{
  "type": "Feature",
  "properties": {
    "addr:full":"Haaksbergerstr 323 Enschede Overijssel 7545 GK",
    "addr:housenumber":"323",
    "addr:postcode":"7545 gk",
    "iso:country":"NL",
    "sg:address":"Haaksbergerstr 323",
    "sg:city":"Enschede",
    "sg:classifiers":[
        {
            "category":"Food & Beverages",
            "subcategory":"Bakery",
            "type":"Retail Goods"
        }
    ],
    "sg:phone":"+31 53 432 3613",
    "sg:postcode":"7545 GK",
    "sg:province":"Overijssel",
    "sg:tags":[
        "brood",
        "en",
        "banket"
    ],
    "wof:name":"Busch",
    "wof:placetype":"venue"
},
  "geometry": {"coordinates":[6.874685,52.208923],"type":"Point"}
}