{
  "type": "Feature",
  "properties": {
    "addr:full":"Klappolder 19 Bleiswijk South Holland 2665 LP",
    "addr:housenumber":"19",
    "addr:postcode":"2665 lp",
    "addr:street":"Klappolder",
    "iso:country":"NL",
    "sg:address":"Klappolder 19",
    "sg:city":"Bleiswijk",
    "sg:orig_category":"Bloemen And Planten Gh",
    "sg:phone":"+31 10 524 2500",
    "sg:postcode":"2665 LP",
    "sg:province":"South Holland",
    "wof:name":"Bloemen En Plantengroothandel W.L. De Mooy",
    "wof:placetype":"venue"
},
  "geometry": {"coordinates":[4.541719,52.028095],"type":"Point"}
}