{
  "type": "Feature",
  "properties": {
    "iso:country":"NL",
    "sg:address":"Boekhorsterwg 21",
    "sg:city":"Oosterwolde Fr",
    "sg:orig_category":"Kinderopvang",
    "sg:phone":"+31 516 515 200",
    "sg:postcode":"8431 CW",
    "sg:province":"Friesland",
    "wof:name":"Clowntje, Kinderopvang 'T",
    "wof:placetype":"venue"
},
  "geometry": {"coordinates":[6.291017,52.983532],"type":"Point"}
}