{
  "type": "Feature",
  "properties": {
    "addr:full":"Vetteoordskd 6 Vlaardingen Zuid-Holland 3131 PZ",
    "addr:housenumber":"6",
    "addr:postcode":"3131 pz",
    "addr:street":"Vetteoordskd",
    "iso:country":"NL",
    "sg:address":"Vetteoordskd 6",
    "sg:city":"Vlaardingen",
    "sg:orig_category":"Kantoor- En Bedrijfsmeubelen",
    "sg:phone":"+31 10 460 0100",
    "sg:postcode":"3131 PZ",
    "sg:province":"Zuid-Holland",
    "sg:website":"http://www.vanlopik-alkate.nl",
    "wof:name":"Lopik Alkat?, Van",
    "wof:placetype":"venue"
},
  "geometry": {"coordinates":[4.3444972038,51.9058189392],"type":"Point"}
}