{
  "type": "Feature",
  "properties": {
    "addr:full":"Prof Lindeboomln 52 Ermelo Gelderland 3853 GD",
    "addr:housenumber":"52",
    "addr:postcode":"3853 gd",
    "addr:street":"Gelderland",
    "iso:country":"NL",
    "sg:address":"Prof Lindeboomln 52",
    "sg:city":"Ermelo",
    "sg:orig_category":"Adviesbureaus Beveiliging",
    "sg:phone":"+31 341 557 034",
    "sg:postcode":"3853 GD",
    "sg:province":"Gelderland",
    "wof:name":"Vosselman, A J",
    "wof:placetype":"venue"
},
  "geometry": {"coordinates":[5.600201,52.301659],"type":"Point"}
}