{
  "type": "Feature",
  "properties": {
    "iso:country":"NL",
    "sg:address":"Hoofdpoort 107",
    "sg:city":"Kaatsheuvel",
    "sg:orig_category":"Fitnesscentra",
    "sg:phone":"+31 416 530 243",
    "sg:postcode":"5171 DN",
    "sg:province":"Noord-Brabant",
    "sg:website":"http://www.moresports.nl",
    "wof:name":"More Sports",
    "wof:placetype":"venue"
},
  "geometry": {"coordinates":[5.035764,51.661217],"type":"Point"}
}