{
  "type": "Feature",
  "properties": {
    "iso:country":"NL",
    "sg:address":"Hagemuntwg 9",
    "sg:city":"Etten Leur",
    "sg:orig_category":"Projectontwikkeling",
    "sg:phone":"+31 76 503 3108",
    "sg:postcode":"4879 NM",
    "sg:province":"North Brabant",
    "wof:name":"Propluss Bv",
    "wof:placetype":"venue"
},
  "geometry": {"coordinates":[4.623169,51.555988],"type":"Point"}
}