{
  "type": "Feature",
  "properties": {
    "addr:full":"Bolwerk 2 Zuidlaren Drenthe 9471 AT",
    "addr:housenumber":"2",
    "addr:postcode":"9471",
    "addr:street":"Bolwerk",
    "iso:country":"NL",
    "sg:address":"Bolwerk 2",
    "sg:city":"Zuidlaren",
    "sg:orig_category":"Behangselpapier En Wandbekleding - Fabr. En Grooth",
    "sg:phone":"+31 50 409 1131",
    "sg:postcode":"9471 AT",
    "sg:province":"Drenthe",
    "wof:name":"Noordwand Bv",
    "wof:placetype":"venue"
},
  "geometry": {"coordinates":[6.691333,53.098911],"type":"Point"}
}