{
  "type": "Feature",
  "properties": {
    "addr:full":"Sniedersln 23 Bladel Noord-Brabant 5531 EG",
    "addr:housenumber":"23",
    "addr:postcode":"5531 eg",
    "addr:street":"Sniedersln",
    "iso:country":"NL",
    "sg:address":"Sniedersln 23",
    "sg:city":"Bladel",
    "sg:orig_category":"Fotozaken",
    "sg:phone":"+31 497 382 531",
    "sg:postcode":"5531 EG",
    "sg:province":"Noord-Brabant",
    "wof:name":"Driesen, Hans",
    "wof:placetype":"venue"
},
  "geometry": {"coordinates":[5.218089,51.367107],"type":"Point"}
}