{
  "type": "Feature",
  "properties": {
    "addr:full":"Dorpsstraat 1 Velden Limburg 5941 EW",
    "addr:housenumber":"1",
    "addr:postcode":"5941 ew",
    "addr:street":"Dorpsstraat",
    "iso:country":"NL",
    "sg:address":"Dorpsstraat 1",
    "sg:city":"Velden",
    "sg:orig_category":"Apothekers",
    "sg:phone":"+31 77 472 3145",
    "sg:postcode":"5941 EW",
    "sg:province":"Limburg",
    "wof:name":"Apotheek St. Andreas",
    "wof:placetype":"venue"
},
  "geometry": {"coordinates":[6.163466,51.414555],"type":"Point"}
}