{
  "type": "Feature",
  "properties": {
    "iso:country":"NL",
    "sg:address":"Oostwal 10",
    "sg:city":"Oss",
    "sg:orig_category":"Adviesbureaus Bouwkunde",
    "sg:phone":"+31 412 625 734",
    "sg:postcode":"5341 KX",
    "sg:province":"Noord-Brabant",
    "wof:name":"Elemans Bv, Adviesburo",
    "wof:placetype":"venue"
},
  "geometry": {"coordinates":[-91.14875000000001,44.587059],"type":"Point"}
}