{
  "type": "Feature",
  "properties": {
    "iso:country":"NL",
    "sg:address":"Postbus 44",
    "sg:city":"Spykenisse",
    "sg:orig_category":"Verenigingen En Stichtingen",
    "sg:phone":"+31 181 656 854",
    "sg:postcode":"3200 AA",
    "sg:province":"South Holland",
    "wof:name":"Aangepaste Sporten Voorne Putte",
    "wof:placetype":"venue"
},
  "geometry": {"coordinates":[4.35844,51.837879],"type":"Point"}
}