{
  "type": "Feature",
  "properties": {
    "addr:full":"Marktstraat 2 Uden Noord-Brabant 5401 GH",
    "addr:housenumber":"2",
    "addr:postcode":"5401 gh",
    "addr:street":"Marktstraat",
    "iso:country":"NL",
    "sg:address":"Marktstraat 2",
    "sg:city":"Uden",
    "sg:orig_category":"Herenmodezaken",
    "sg:phone":"+31 413 261 578",
    "sg:postcode":"5401 GH",
    "sg:province":"Noord-Brabant",
    "wof:name":"Wehberg Mode Bv",
    "wof:placetype":"venue"
},
  "geometry": {"coordinates":[5.612535,51.657818],"type":"Point"}
}