{
  "type": "Feature",
  "properties": {
    "addr:full":"Prinsenhof 15 Kesteren Gelderland 4041 BM",
    "addr:housenumber":"15",
    "addr:postcode":"4041 bm",
    "addr:street":"Prinsenhof;Gelderland",
    "iso:country":"NL",
    "sg:address":"Prinsenhof 15",
    "sg:city":"Kesteren",
    "sg:orig_category":"Webdesign Bureaus",
    "sg:phone":"+31 6 24842538",
    "sg:postcode":"4041 BM",
    "sg:province":"Gelderland",
    "sg:website":"http://www.idiensten.nl",
    "wof:name":"Webm@Ster Idiensten Net",
    "wof:placetype":"venue"
},
  "geometry": {"coordinates":[5.5683188438,51.9334945679],"type":"Point"}
}