{
  "type": "Feature",
  "properties": {
    "iso:country":"NL",
    "sg:address":"Bloemendaalsewg 228",
    "sg:city":"Overveen",
    "sg:orig_category":"Natuurvoeding En Reformartikelen",
    "sg:phone":"+31 23 525 0764",
    "sg:postcode":"2051 GM",
    "sg:province":"Noord-Holland",
    "wof:name":"Natuurwinkel Overveen",
    "wof:placetype":"venue"
},
  "geometry": {"coordinates":[4.609267,52.391586],"type":"Point"}
}