{
  "type": "Feature",
  "properties": {
    "addr:full":"Meye 82 Bodegraven Zuid-Holland 2411 PL",
    "addr:housenumber":"82",
    "addr:postcode":"2411 pl",
    "addr:street":"Meye",
    "iso:country":"NL",
    "sg:address":"Meye 82",
    "sg:city":"Bodegraven",
    "sg:orig_category":"Pianostemmen En -Reparatie",
    "sg:phone":"+31 172 685 690",
    "sg:postcode":"2411 PL",
    "sg:province":"Zuid-Holland",
    "wof:name":"Mostert",
    "wof:placetype":"venue"
},
  "geometry": {"coordinates":[4.747547,52.085552],"type":"Point"}
}