{
  "type": "Feature",
  "properties": {
    "addr:full":"Pieter Sipmawei 290 Leeuwarden Provincie Friesland 8915 EH",
    "addr:housenumber":"290",
    "addr:postcode":"8915 eh",
    "addr:street":"Pieter Sipmawei;Provincie Friesland",
    "iso:country":"NL",
    "sg:address":"Pieter Sipmawei 290",
    "sg:city":"Leeuwarden",
    "sg:orig_category":"Bejaardeninstellingen And Serviceflats",
    "sg:phone":"+31 58 215 4255",
    "sg:postcode":"8915 EH",
    "sg:province":"Provincie Friesland",
    "wof:name":"Stichting Palet Locatie Swettehiem",
    "wof:placetype":"venue"
},
  "geometry": {"coordinates":[5.767589,53.209042],"type":"Point"}
}