{
  "type": "Feature",
  "properties": {
    "addr:full":"Schoonderbeekln 39 Putten Gelderland 3881 LN",
    "addr:housenumber":"39",
    "addr:postcode":"3881 ln",
    "addr:street":"Schoonderbeekln;Gelderland",
    "iso:country":"NL",
    "sg:address":"Schoonderbeekln 39",
    "sg:city":"Putten",
    "sg:orig_category":"Adviesbureaus Bedrijfsorganisatie",
    "sg:phone":"+31 341 352 225",
    "sg:postcode":"3881 LN",
    "sg:province":"Gelderland",
    "wof:name":"Vis Bv, J",
    "wof:placetype":"venue"
},
  "geometry": {"coordinates":[5.608844,52.268673],"type":"Point"}
}