{
  "type": "Feature",
  "properties": {
    "iso:country":"NL",
    "sg:address":"Weerenwg 28B",
    "sg:city":"Zwanenburg",
    "sg:orig_category":"Bedrijfsmechanisatie En -Automatisering",
    "sg:phone":"+31 20 497 0032",
    "sg:postcode":"1161 AJ",
    "sg:province":"Noord-Holland",
    "sg:website":"http://www.abar.nl",
    "wof:name":"Abar Bv",
    "wof:placetype":"venue"
},
  "geometry": {"coordinates":[4.737202,52.383327],"type":"Point"}
}