{
  "type": "Feature",
  "properties": {
    "iso:country":"NL",
    "sg:address":"Herenweg 232",
    "sg:city":"Wilnis",
    "sg:orig_category":"Diverse Bedrijfsinstallaties Gh",
    "sg:phone":"+31 297 282 287",
    "sg:postcode":"3648 CR",
    "sg:province":"Utrecht",
    "wof:name":"Brederode Van J.P.M. Hr.",
    "wof:placetype":"venue"
},
  "geometry": {"coordinates":[4.880611,52.198093],"type":"Point"}
}