{
  "type": "Feature",
  "properties": {
    "addr:full":"Koekoeksbloemstr 12 Berkel En Rodenrys Zuid-Holland 2651 ME",
    "addr:housenumber":"12",
    "addr:postcode":"2651 me",
    "addr:street":"Koekoeksbloemstr;Berkel",
    "iso:country":"NL",
    "sg:address":"Koekoeksbloemstr 12",
    "sg:city":"Berkel En Rodenrys",
    "sg:orig_category":"Loonbedrijven",
    "sg:phone":"+31 10 511 5258",
    "sg:postcode":"2651 ME",
    "sg:province":"Zuid-Holland",
    "wof:name":"Keijzer, R De",
    "wof:placetype":"venue"
},
  "geometry": {"coordinates":[4.467769,51.991077],"type":"Point"}
}