{
  "type": "Feature",
  "properties": {
    "addr:full":"Simon Stevinstraat 14 Amsterdam Noord-Holland 1097 BZ",
    "addr:housenumber":"14",
    "addr:postcode":"1097 bz",
    "addr:street":"Simon Stevinstraat",
    "iso:country":"NL",
    "sg:address":"Simon Stevinstraat 14",
    "sg:city":"Amsterdam",
    "sg:orig_category":"Loodgieterswerk, Verwarming And Sanitaire Installaties",
    "sg:phone":"+31 20 665 2304",
    "sg:postcode":"1097 BZ",
    "sg:province":"Noord-Holland",
    "wof:name":"Diekema Onderhoudswerken Bv",
    "wof:placetype":"venue"
},
  "geometry": {"coordinates":[4.927436,52.354202],"type":"Point"}
}