{
  "type": "Feature",
  "properties": {
    "iso:country":"NL",
    "sg:address":"D Costerstr 44",
    "sg:city":"Rotterdam",
    "sg:orig_category":"Administratie- En Boekhoudkantoren",
    "sg:phone":"+31 10 455 3617",
    "sg:postcode":"3069 WE",
    "sg:province":"Zuid-Holland",
    "wof:name":"Jaconed",
    "wof:placetype":"venue"
},
  "geometry": {"coordinates":[4.565034,51.967194],"type":"Point"}
}