{
  "type": "Feature",
  "properties": {
    "addr:full":"Meursstraat 11 Heesch North Brabant 5384 ND",
    "addr:housenumber":"11",
    "addr:postcode":"5384 nd",
    "addr:street":"Meursstraat",
    "iso:country":"NL",
    "sg:address":"Meursstraat 11",
    "sg:city":"Heesch",
    "sg:orig_category":"Levende Dieren Gh",
    "sg:phone":"+31 412 451 094",
    "sg:postcode":"5384 ND",
    "sg:province":"North Brabant",
    "wof:name":"Vof Enrico Van Orsouw",
    "wof:placetype":"venue"
},
  "geometry": {"coordinates":[5.530526,51.738827],"type":"Point"}
}