{
  "type": "Feature",
  "properties": {
    "addr:full":"Molendijk 187 Sliedrecht South Holland 3361 EM",
    "addr:housenumber":"187",
    "addr:postcode":"3361 em",
    "addr:street":"Molendijk",
    "iso:country":"NL",
    "sg:address":"Molendijk 187",
    "sg:city":"Sliedrecht",
    "sg:orig_category":"Kappers",
    "sg:phone":"+31 184 412 994",
    "sg:postcode":"3361 EM",
    "sg:province":"South Holland",
    "wof:name":"Salon Nicoise",
    "wof:placetype":"venue"
},
  "geometry": {"coordinates":[4.756308,51.824726],"type":"Point"}
}