{
  "type": "Feature",
  "properties": {
    "addr:full":"Hobbemastr 1 Middelharnis Zuid-Holland 3241 AC",
    "addr:housenumber":"1",
    "addr:postcode":"3241 ac",
    "addr:street":"Hobbemastr",
    "iso:country":"NL",
    "sg:address":"Hobbemastr 1",
    "sg:city":"Middelharnis",
    "sg:orig_category":"Autoradio'S",
    "sg:phone":"+31 187 486 144",
    "sg:postcode":"3241 AC",
    "sg:province":"Zuid-Holland",
    "sg:website":"http://www.qualitycenters.nl",
    "wof:name":"Re-Cars",
    "wof:placetype":"venue"
},
  "geometry": {"coordinates":[4.162285,51.758247],"type":"Point"}
}