{
  "type": "Feature",
  "properties": {
    "addr:full":"Stationsstr 26 Oosterwolde Fr Friesland 8431 EV",
    "addr:housenumber":"26",
    "addr:street":"Stationsstr",
    "iso:country":"NL",
    "sg:address":"Stationsstr 26",
    "sg:city":"Oosterwolde Fr",
    "sg:orig_category":"Warenhuizen",
    "sg:phone":"+31 516 514 636",
    "sg:postcode":"8431 EV",
    "sg:province":"Friesland",
    "wof:name":"Hema",
    "wof:placetype":"venue"
},
  "geometry": {"coordinates":[6.2907500267,52.9897155762],"type":"Point"}
}