{
  "type": "Feature",
  "properties": {
    "addr:full":"Merkelbachstr 2 Amersfoort Utrecht 3822 EP",
    "addr:housenumber":"2",
    "addr:postcode":"3822 ep",
    "addr:street":"Merkelbachstr",
    "iso:country":"NL",
    "sg:address":"Merkelbachstr 2",
    "sg:city":"Amersfoort",
    "sg:orig_category":"Autorijscholen",
    "sg:phone":"+31 6 54213124",
    "sg:postcode":"3822 EP",
    "sg:province":"Utrecht",
    "wof:name":"Burgsteden, Van",
    "wof:placetype":"venue"
},
  "geometry": {"coordinates":[5.399148,52.183289],"type":"Point"}
}