{
  "type": "Feature",
  "properties": {
    "addr:full":"Groesbeeksedwwg 299 Nymegen Gelderland 6521 DK",
    "addr:housenumber":"299",
    "addr:postcode":"6521 dk",
    "addr:street":"Nymegen Gelderland",
    "iso:country":"NL",
    "sg:address":"Groesbeeksedwwg 299",
    "sg:city":"Nymegen",
    "sg:orig_category":"Biljartzalen",
    "sg:phone":"+31 24 322 1423",
    "sg:postcode":"6521 DK",
    "sg:province":"Gelderland",
    "wof:name":"La Zambomba, Caf?-Biljart",
    "wof:placetype":"venue"
},
  "geometry": {"coordinates":[9.51668,56.2757],"type":"Point"}
}