{
  "type": "Feature",
  "properties": {
    "iso:country":"NL",
    "sg:address":"Dorpsstraat 47",
    "sg:city":"Emmen",
    "sg:orig_category":"Autokeuringen",
    "sg:phone":"+31 591 615 490",
    "sg:postcode":"7814 PT",
    "sg:province":"Drenthe",
    "wof:name":"J Hidding",
    "wof:placetype":"venue"
},
  "geometry": {"coordinates":[6.917507,52.818783],"type":"Point"}
}