{
  "type": "Feature",
  "properties": {
    "addr:full":"Hoofdstr 189 Sassenheim Zuid-Holland 2171 BC",
    "addr:housenumber":"189",
    "addr:postcode":"sassenheim;2171 bc",
    "iso:country":"NL",
    "sg:address":"Hoofdstr 189",
    "sg:city":"Sassenheim",
    "sg:orig_category":"Wasmachines En Wasdrogers",
    "sg:phone":"+31 252 210 398",
    "sg:postcode":"2171 BC",
    "sg:province":"Zuid-Holland",
    "wof:name":"Duynstee Bv",
    "wof:placetype":"venue"
},
  "geometry": {"coordinates":[4.5214657784,52.2260055542],"type":"Point"}
}