{
  "type": "Feature",
  "properties": {
    "addr:full":"Burg Uilkensstr 19 Bergambacht Zuid-Holland 2861 AD",
    "addr:housenumber":"19",
    "addr:postcode":"2861 ad",
    "addr:street":"Burg",
    "iso:country":"NL",
    "sg:address":"Burg Uilkensstr 19",
    "sg:city":"Bergambacht",
    "sg:orig_category":"Sportaccommodaties - Aanleg En Onderhoud",
    "sg:phone":"+31 182 354 194",
    "sg:postcode":"2861 AD",
    "sg:province":"Zuid-Holland",
    "wof:name":"Siebenga",
    "wof:placetype":"venue"
},
  "geometry": {"coordinates":[4.784343,51.931713],"type":"Point"}
}