{
  "type": "Feature",
  "properties": {
    "addr:full":"Noord 47B Krimpen Aan De Lek Zuid-Holland 2931 SJ",
    "addr:housenumber":"47b",
    "addr:postcode":"2931",
    "addr:street":"Noord",
    "iso:country":"NL",
    "sg:address":"Noord 47B",
    "sg:city":"Krimpen Aan De Lek",
    "sg:orig_category":"Houtbewerking",
    "sg:phone":"+31 180 512 170",
    "sg:postcode":"2931 SJ",
    "sg:province":"Zuid-Holland",
    "sg:website":"http://www.bergenzn.nl",
    "wof:name":"Berg En Zn Vof, T Van Den",
    "wof:placetype":"venue"
},
  "geometry": {"coordinates":[4.593714,51.902905],"type":"Point"}
}