{
  "type": "Feature",
  "properties": {
    "addr:full":"Groenoordln 10 Apeldoorn Gelderland 7322 HW",
    "addr:housenumber":"10",
    "addr:postcode":"7322 hw",
    "addr:street":"Groenoordln;Gelderland",
    "iso:country":"NL",
    "sg:address":"Groenoordln 10",
    "sg:city":"Apeldoorn",
    "sg:orig_category":"Adviesbureaus Bedrijfsorganisatie",
    "sg:phone":"+31 55 312 2162",
    "sg:postcode":"7322 HW",
    "sg:province":"Gelderland",
    "wof:name":"Limburg Consultancy",
    "wof:placetype":"venue"
},
  "geometry": {"coordinates":[5.977657,52.216442],"type":"Point"}
}