{
  "type": "Feature",
  "properties": {
    "addr:full":"Atalanta 41 Zeewolde Flevoland 3892 EB",
    "addr:housenumber":"41",
    "addr:postcode":"3892 eb",
    "addr:street":"Atalanta;Flevoland",
    "iso:country":"NL",
    "sg:address":"Atalanta 41",
    "sg:city":"Zeewolde",
    "sg:orig_category":"Verzekeringen - Verzekeringskantoren",
    "sg:phone":"+31 36 522 3914",
    "sg:postcode":"3892 EB",
    "sg:province":"Flevoland",
    "wof:name":"Verdon Bv",
    "wof:placetype":"venue"
},
  "geometry": {"coordinates":[5.544846,52.320831],"type":"Point"}
}