{
  "type": "Feature",
  "properties": {
    "iso:country":"NL",
    "sg:address":"Havenwg 1",
    "sg:city":"Helmond",
    "sg:orig_category":"Energiebedrijven",
    "sg:phone":"+31 492 594 888",
    "sg:postcode":"5701 RS",
    "sg:province":"North Brabant",
    "sg:website":"http://www.obragas.nl",
    "wof:name":"Obragas Holding Nv",
    "wof:placetype":"venue"
},
  "geometry": {"coordinates":[5.652298,51.480038],"type":"Point"}
}