{
  "type": "Feature",
  "properties": {
    "iso:country":"NL",
    "sg:address":"Oudez Achterburgw 125",
    "sg:city":"Amsterdam",
    "sg:orig_category":"Filmstudio'S En -Productie",
    "sg:phone":"+31 20 620 9468",
    "sg:postcode":"1012 DE",
    "sg:province":"Noord-Holland",
    "wof:name":"Picture Search",
    "wof:placetype":"venue"
},
  "geometry": {"coordinates":[4.897796,52.372066],"type":"Point"}
}