{
  "type": "Feature",
  "properties": {
    "addr:full":"Persoonsstr 1 Rotterdam Zuid-Holland 3071 EG",
    "addr:housenumber":"1",
    "addr:postcode":"3071 eg",
    "addr:street":"Persoonsstr",
    "iso:country":"NL",
    "sg:address":"Persoonsstr 1",
    "sg:city":"Rotterdam",
    "sg:orig_category":"Scholen Voor Basisonderwijs",
    "sg:phone":"+31 10 485 5250",
    "sg:postcode":"3071 EG",
    "sg:province":"Zuid-Holland",
    "wof:name":"Dukdalf Montessori, De",
    "wof:placetype":"venue"
},
  "geometry": {"coordinates":[4.505116,51.91053],"type":"Point"}
}