{
  "type": "Feature",
  "properties": {
    "addr:full":"Vletstraat 2 Nieuw Lekkerland Zuid-Holland 2957 GH",
    "addr:housenumber":"2",
    "addr:postcode":"2957 gh",
    "addr:street":"Vletstraat",
    "iso:country":"NL",
    "sg:address":"Vletstraat 2",
    "sg:city":"Nieuw Lekkerland",
    "sg:orig_category":"Sportterreinen And Installaties Behalve Sportcentra",
    "sg:phone":"+31 184 681 929",
    "sg:postcode":"2957 GH",
    "sg:province":"Zuid-Holland",
    "wof:name":"Zwembad Schoonenburg",
    "wof:placetype":"venue"
},
  "geometry": {"coordinates":[4.661776,51.883846],"type":"Point"}
}