{
  "type": "Feature",
  "properties": {
    "addr:full":"V Hardenbroekstr 18 St Nicolaasga Friesland 8521 KA",
    "addr:housenumber":"18",
    "addr:postcode":"8521 ka",
    "addr:street":"St",
    "iso:country":"NL",
    "sg:address":"V Hardenbroekstr 18",
    "sg:city":"St Nicolaasga",
    "sg:orig_category":"Onderhoudswerken",
    "sg:phone":"+31 513 432 080",
    "sg:postcode":"8521 KA",
    "sg:province":"Friesland",
    "wof:name":"Wagt De, Allard",
    "wof:placetype":"venue"
},
  "geometry": {"coordinates":[5.743665,52.923367],"type":"Point"}
}