{
  "type": "Feature",
  "properties": {
    "addr:full":"Sebastiaanstr 30 Ell Limburg 6011 RE",
    "addr:housenumber":"30",
    "addr:postcode":"6011 re",
    "addr:street":"Sebastiaanstr",
    "iso:country":"NL",
    "sg:address":"Sebastiaanstr 30",
    "sg:city":"Ell",
    "sg:classifiers":[
        {
            "category":"Retail",
            "subcategory":"Auto Repair",
            "type":"Services"
        }
    ],
    "sg:phone":"+31 495 552 042",
    "sg:postcode":"6011 RE",
    "sg:province":"Limburg",
    "sg:tags":[
        "garage"
    ],
    "wof:name":"Heemels",
    "wof:placetype":"venue"
},
  "geometry": {"coordinates":[-98.101067,27.527],"type":"Point"}
}