{
  "type": "Feature",
  "properties": {
    "addr:full":"Ambachtsweg 18 Hasselt NL.08 8061 RN",
    "addr:housenumber":"18",
    "addr:postcode":"8061 rn",
    "addr:street":"Ambachtsweg",
    "iso:country":"NL",
    "sg:address":"Ambachtsweg 18",
    "sg:city":"Hasselt",
    "sg:orig_category":"Loodgieterswerk, Verwarming And Sanitaire Installaties",
    "sg:phone":"+31 38 477 1470",
    "sg:postcode":"8061 RN",
    "sg:province":"NL.08",
    "wof:name":"De Vreught Scheepsreparatie & Electronica",
    "wof:placetype":"venue"
},
  "geometry": {"coordinates":[6.088755,52.592861],"type":"Point"}
}