{
  "type": "Feature",
  "properties": {
    "addr:full":"Marktveldpassage 20 Vught Noord-Brabant 5261 ED",
    "addr:housenumber":"20",
    "addr:postcode":"5261 ed",
    "addr:street":"Marktveldpassage",
    "iso:country":"NL",
    "sg:address":"Marktveldpassage 20",
    "sg:city":"Vught",
    "sg:orig_category":"Discountwinkels",
    "sg:phone":"+31 73 684 0168",
    "sg:postcode":"5261 ED",
    "sg:province":"Noord-Brabant",
    "wof:name":"Zeeman Textielsupers",
    "wof:placetype":"venue"
},
  "geometry": {"coordinates":[5.300832,51.658348],"type":"Point"}
}