{
  "type": "Feature",
  "properties": {
    "addr:full":"Bieslookstr 31E9 Groningen Groningen 9731 HH",
    "addr:housenumber":"31e9",
    "addr:postcode":"9731 hh",
    "addr:street":"Bieslookstr",
    "iso:country":"NL",
    "sg:address":"Bieslookstr 31E9",
    "sg:city":"Groningen",
    "sg:orig_category":"Beeldende Kunstenaars",
    "sg:phone":"+31 50 549 0426",
    "sg:postcode":"9731 HH",
    "sg:province":"Groningen",
    "sg:website":"http://home.hetnet.nl/~artgalery-thali",
    "wof:name":"Thali, Atelier",
    "wof:placetype":"venue"
},
  "geometry": {"coordinates":[6.602241,53.233734],"type":"Point"}
}