{
  "type": "Feature",
  "properties": {
    "addr:full":"Sardiniewg 6 Amsterdam Noord-Holland 1044 AE",
    "addr:housenumber":"6",
    "addr:postcode":"1044 ae",
    "addr:street":"Sardiniewg",
    "iso:country":"NL",
    "sg:address":"Sardiniewg 6",
    "sg:city":"Amsterdam",
    "sg:classifiers":[
        {
            "category":"Retail",
            "subcategory":"Storage",
            "type":"Services"
        }
    ],
    "sg:phone":"+31 20 614 8585",
    "sg:postcode":"1044 AE",
    "sg:province":"Noord-Holland",
    "sg:tags":[
        "op-",
        "en",
        "overslagbedrijven"
    ],
    "wof:name":"Avcb",
    "wof:placetype":"venue"
},
  "geometry": {"coordinates":[4.813614,52.399479],"type":"Point"}
}