{
  "type": "Feature",
  "properties": {
    "iso:country":"NL",
    "sg:address":"Haaksbergerstraat 324",
    "sg:city":"Enschede",
    "sg:orig_category":"Kappers",
    "sg:phone":"+31 53 432 3008",
    "sg:postcode":"7513 EH",
    "sg:province":"Overijssel",
    "wof:name":"Salon Midi",
    "wof:placetype":"venue"
},
  "geometry": {"coordinates":[6.880868,52.212193],"type":"Point"}
}