{
  "type": "Feature",
  "properties": {
    "iso:country":"NL",
    "sg:address":"Frederikstr 56G",
    "sg:city":"S Gravenhage",
    "sg:orig_category":"Bloemen En Planten",
    "sg:phone":"+31 70 363 2121",
    "sg:postcode":"2514 LL",
    "sg:province":"Zuid-Holland",
    "wof:name":"Hofman, Ton",
    "wof:placetype":"venue"
},
  "geometry": {"coordinates":[4.30935,52.084148],"type":"Point"}
}