{
  "type": "Feature",
  "properties": {
    "addr:full":"Voorstraat 11 Zwaagwesteinde Friesland 9271 KE",
    "addr:housenumber":"11",
    "addr:postcode":"9271 ke",
    "addr:street":"Voorstraat",
    "iso:country":"NL",
    "sg:address":"Voorstraat 11",
    "sg:city":"Zwaagwesteinde",
    "sg:orig_category":"Verlichting And Huishoudartikelen",
    "sg:phone":"+31 511 441 497",
    "sg:postcode":"9271 KE",
    "sg:province":"Friesland",
    "wof:name":"A Van Der Veen",
    "wof:placetype":"venue"
},
  "geometry": {"coordinates":[6.0315,53.261353],"type":"Point"}
}