{
  "type": "Feature",
  "properties": {
    "addr:full":"Postbus 10 Slagharen Overijssel 7776 ZG",
    "addr:housenumber":"10",
    "addr:postcode":"7776 zg",
    "addr:street":"Postbus",
    "iso:country":"NL",
    "sg:address":"Postbus 10",
    "sg:city":"Slagharen",
    "sg:orig_category":"Vakantieverblijven",
    "sg:phone":"+31 523 262 800",
    "sg:postcode":"7776 ZG",
    "sg:province":"Overijssel",
    "wof:name":"Collendoorn Bv",
    "wof:placetype":"venue"
},
  "geometry": {"coordinates":[6.55249,52.629036],"type":"Point"}
}