{
  "type": "Feature",
  "properties": {
    "addr:full":"Broeklanderwg 12 Beemte Broekland Gelderland 7341 PJ",
    "addr:housenumber":"12",
    "addr:postcode":"7341 pj",
    "addr:street":"Broeklanderwg",
    "iso:country":"NL",
    "sg:address":"Broeklanderwg 12",
    "sg:city":"Beemte Broekland",
    "sg:orig_category":"Open Haard Houtblokken",
    "sg:phone":"+31 55 312 1544",
    "sg:postcode":"7341 PJ",
    "sg:province":"Gelderland",
    "wof:name":"Disbergen, B H",
    "wof:placetype":"venue"
},
  "geometry": {"coordinates":[5.992558,52.265686],"type":"Point"}
}