{
  "type": "Feature",
  "properties": {
    "addr:full":"Meerweg 24 Berkel En Rodenrijs Zuid-Holland 2651 KS",
    "addr:housenumber":"24",
    "addr:postcode":"2651 ks",
    "addr:street":"Meerweg",
    "iso:country":"NL",
    "sg:address":"Meerweg 24",
    "sg:city":"Berkel En Rodenrijs",
    "sg:orig_category":"Huizensloop And Bouwrijp Maken",
    "sg:phone":"+31 10 511 8966",
    "sg:postcode":"2651 KS",
    "sg:province":"Zuid-Holland",
    "wof:name":"Handelsonderneming/Loonbedrijf Mdb",
    "wof:placetype":"venue"
},
  "geometry": {"coordinates":[4.458423,51.999134],"type":"Point"}
}