{
  "type": "Feature",
  "properties": {
    "addr:full":"Chopinpln 189 Culemborg Gelderland 4102 CT",
    "addr:housenumber":"189",
    "addr:postcode":"4102 ct",
    "addr:street":"Gelderland",
    "iso:country":"NL",
    "sg:address":"Chopinpln 189",
    "sg:city":"Culemborg",
    "sg:orig_category":"Autorijscholen",
    "sg:phone":"+31 345 515 196",
    "sg:postcode":"4102 CT",
    "sg:province":"Gelderland",
    "wof:name":"Kool",
    "wof:placetype":"venue"
},
  "geometry": {"coordinates":[5.238526,51.952717],"type":"Point"}
}