{
  "type": "Feature",
  "properties": {
    "iso:country":"NL",
    "sg:address":"Bosstraat 19",
    "sg:city":"Driebergen-Rijsenburg",
    "sg:orig_category":"Kappers",
    "sg:phone":"+31 343 520 801",
    "sg:postcode":"3971 XA",
    "sg:province":"Utrecht",
    "wof:name":"Grb, For Hair",
    "wof:placetype":"venue"
},
  "geometry": {"coordinates":[5.2821030617,52.0538787842],"type":"Point"}
}