{
  "type": "Feature",
  "properties": {
    "addr:full":"Planker 5 Asten Noord-Brabant 5721 VG",
    "addr:housenumber":"5",
    "addr:postcode":"5721 vg",
    "addr:street":"Planker",
    "iso:country":"NL",
    "sg:address":"Planker 5",
    "sg:city":"Asten",
    "sg:orig_category":"Kunststoffen- Verwerkende Industrie",
    "sg:phone":"+31 493 689 130",
    "sg:postcode":"5721 VG",
    "sg:province":"Noord-Brabant",
    "wof:name":"Haasje, 'T",
    "wof:placetype":"venue"
},
  "geometry": {"coordinates":[5.756536,51.41396],"type":"Point"}
}