{
  "type": "Feature",
  "properties": {
    "addr:full":"Raadhuisstr 37A Roermond Limburg 6042 JK",
    "addr:housenumber":"37a",
    "addr:postcode":"6042 jk",
    "addr:street":"Raadhuisstr",
    "iso:country":"NL",
    "sg:address":"Raadhuisstr 37A",
    "sg:city":"Roermond",
    "sg:orig_category":"Loodgieters",
    "sg:phone":"+31 475 329 898",
    "sg:postcode":"6042 JK",
    "sg:province":"Limburg",
    "wof:name":"Karel Hermans",
    "wof:placetype":"venue"
},
  "geometry": {"coordinates":[6.012623,51.198017],"type":"Point"}
}