{
  "type": "Feature",
  "properties": {
    "addr:full":"Kerkstr 105A Noordwykerhout Zuid-Holland 2211 RG",
    "addr:housenumber":"105a",
    "addr:postcode":"noordwykerhout;2211 rg",
    "iso:country":"NL",
    "sg:address":"Kerkstr 105A",
    "sg:city":"Noordwykerhout",
    "sg:classifiers":[
        {
            "category":"Food & Beverages",
            "subcategory":"Bakery",
            "type":"Retail Goods"
        }
    ],
    "sg:phone":"+31 252 372 778",
    "sg:postcode":"2211 RG",
    "sg:province":"Zuid-Holland",
    "sg:tags":[
        "brood",
        "en",
        "banket"
    ],
    "wof:name":"Eeden, Van",
    "wof:placetype":"venue"
},
  "geometry": {"coordinates":[4.486942,52.251316],"type":"Point"}
}