{
  "type": "Feature",
  "properties": {
    "addr:full":"Richard Holstraat 5 Nijmegen Gelderland 6523 AE",
    "addr:housenumber":"5",
    "addr:postcode":"6523 ae",
    "addr:street":"Richard Holstraat;Gelderland",
    "iso:country":"NL",
    "sg:address":"Richard Holstraat 5",
    "sg:city":"Nijmegen",
    "sg:orig_category":"Vertaal- And Tolkenbureaus",
    "sg:phone":"+31 24 360 4364",
    "sg:postcode":"6523 AE",
    "sg:province":"Gelderland",
    "wof:name":"Birgitte Devilee",
    "wof:placetype":"venue"
},
  "geometry": {"coordinates":[5.876079,51.834156],"type":"Point"}
}