{
  "type": "Feature",
  "properties": {
    "addr:full":"Berlageln 97 Almelo NL.08 7606 SP",
    "addr:housenumber":"97;nl.08",
    "addr:postcode":"7606 sp",
    "addr:street":"Berlageln",
    "iso:country":"NL",
    "sg:address":"Berlageln 97",
    "sg:city":"Almelo",
    "sg:orig_category":"Banken",
    "sg:phone":"+31 546 547 111",
    "sg:postcode":"7606 SP",
    "sg:province":"NL.08",
    "sg:website":"http://www.rabobank.nl",
    "wof:name":"Rabobank",
    "wof:placetype":"venue"
},
  "geometry": {"coordinates":[6.664543,52.354954],"type":"Point"}
}