{
  "type": "Feature",
  "properties": {
    "addr:full":"Randweg 11 Medemblik North Holland 1671 GG",
    "addr:housenumber":"11",
    "addr:postcode":"1671 gg",
    "addr:street":"Randweg",
    "iso:country":"NL",
    "sg:address":"Randweg 11",
    "sg:city":"Medemblik",
    "sg:orig_category":"Boekenuitgeverijen",
    "sg:phone":"+31 227 541 990",
    "sg:postcode":"1671 GG",
    "sg:province":"North Holland",
    "wof:name":"Drukkerij En Uitgeverij A.A. Idema Bv",
    "wof:placetype":"venue"
},
  "geometry": {"coordinates":[5.099363,52.765369],"type":"Point"}
}