{
  "type": "Feature",
  "properties": {
    "addr:full":"Reigerlaan 15 Beilen Drenthe 9411 GS",
    "addr:housenumber":"15",
    "addr:postcode":"9411 gs",
    "addr:street":"Reigerlaan",
    "iso:country":"NL",
    "sg:address":"Reigerlaan 15",
    "sg:city":"Beilen",
    "sg:orig_category":"Supermarkten",
    "sg:phone":"+31 593 523 170",
    "sg:postcode":"9411 GS",
    "sg:province":"Drenthe",
    "wof:name":"Edah",
    "wof:placetype":"venue"
},
  "geometry": {"coordinates":[6.505701,52.863148],"type":"Point"}
}