{
  "type": "Feature",
  "properties": {
    "iso:country":"NL",
    "sg:address":"Huizumerlaan 13",
    "sg:city":"Leeuwarden",
    "sg:orig_category":"Elektrische Apparatuur Gh",
    "sg:phone":"+31 58 280 0061",
    "sg:postcode":"8934 BC",
    "sg:province":"Friesland",
    "wof:name":"Hoc",
    "wof:placetype":"venue"
},
  "geometry": {"coordinates":[5.80196,53.193283],"type":"Point"}
}