{
  "type": "Feature",
  "properties": {
    "addr:full":"Maalstroom 33 Oostzaan Noord-Holland 1511 JL",
    "addr:housenumber":"33",
    "addr:postcode":"1511 jl",
    "addr:street":"Maalstroom",
    "iso:country":"NL",
    "sg:address":"Maalstroom 33",
    "sg:city":"Oostzaan",
    "sg:orig_category":"Gespecialiseerde Bouw",
    "sg:phone":"+31 75 684 1586",
    "sg:postcode":"1511 JL",
    "sg:province":"Noord-Holland",
    "wof:name":"Firma A.J.C. Botterman",
    "wof:placetype":"venue"
},
  "geometry": {"coordinates":[4.877878,52.433746],"type":"Point"}
}