{
  "type": "Feature",
  "properties": {
    "addr:full":"Suezln 62 Deurne Noord-Brabant 5752 RC",
    "addr:housenumber":"62",
    "addr:postcode":"5752 rc",
    "addr:street":"Suezln",
    "iso:country":"NL",
    "sg:address":"Suezln 62",
    "sg:city":"Deurne",
    "sg:orig_category":"Autorijscholen",
    "sg:phone":"+31 493 310 601",
    "sg:postcode":"5752 RC",
    "sg:province":"Noord-Brabant",
    "wof:name":"Wit, C De",
    "wof:placetype":"venue"
},
  "geometry": {"coordinates":[5.802605,51.473717],"type":"Point"}
}