{
  "type": "Feature",
  "properties": {
    "addr:full":"Schrans 99 Leeuwarden Friesland 8932 NC",
    "addr:housenumber":"99",
    "addr:postcode":"8932 nc",
    "addr:street":"Schrans",
    "iso:country":"NL",
    "sg:address":"Schrans 99",
    "sg:city":"Leeuwarden",
    "sg:orig_category":"Bloemen En Planten",
    "sg:phone":"+31 58 288 5482",
    "sg:postcode":"8932 NC",
    "sg:province":"Friesland",
    "wof:name":"Acanthus Bloembinderij",
    "wof:placetype":"venue"
},
  "geometry": {"coordinates":[5.798849,53.194782],"type":"Point"}
}