{
  "type": "Feature",
  "properties": {
    "iso:country":"NL",
    "sg:address":"De Palmen Grift 387",
    "sg:city":"Veenendaal",
    "sg:orig_category":"Geluidsopnamestudio'S",
    "sg:phone":"+31 318 520 576",
    "sg:postcode":"3901 NK",
    "sg:province":"Utrecht",
    "wof:name":"Beentjes, Jos",
    "wof:placetype":"venue"
},
  "geometry": {"coordinates":[5.560705,52.021641],"type":"Point"}
}