{
  "type": "Feature",
  "properties": {
    "addr:full":"Walstraat 23 Oss Noord-Brabant 5341 CJ",
    "addr:housenumber":"23",
    "addr:postcode":"5341 cj",
    "addr:street":"Walstraat",
    "iso:country":"NL",
    "sg:address":"Walstraat 23",
    "sg:city":"Oss",
    "sg:orig_category":"Metaalbekleding And -Behandeling",
    "sg:phone":"+31 412 622 078",
    "sg:postcode":"5341 CJ",
    "sg:province":"Noord-Brabant",
    "wof:name":"Techisch Handelsbedrijf Kocken Bv",
    "wof:placetype":"venue"
},
  "geometry": {"coordinates":[-77.235214,38.312599],"type":"Point"}
}