{
  "type": "Feature",
  "properties": {
    "addr:full":"Nobelstraat 12 Oud Beijerland Zuid-Holland 3262 PM",
    "addr:housenumber":"12",
    "addr:postcode":"3262 pm",
    "addr:street":"Nobelstraat;Oud Beijerland",
    "iso:country":"NL",
    "sg:address":"Nobelstraat 12",
    "sg:city":"Oud Beijerland",
    "sg:classifiers":[
        {
            "category":"Fast Food",
            "type":"Food & Drink"
        }
    ],
    "sg:phone":"+31 186 612 673",
    "sg:postcode":"3262 PM",
    "sg:province":"Zuid-Holland",
    "sg:tags":[
        "afhaal",
        "restaurant"
    ],
    "wof:name":"Shoarma Bol Bol",
    "wof:placetype":"venue"
},
  "geometry": {"coordinates":[4.409182,51.826542],"type":"Point"}
}