{
  "type": "Feature",
  "properties": {
    "addr:full":"K Doormanln 70 Huizen Noord-Holland 1271 CD",
    "addr:housenumber":"70",
    "addr:postcode":"1271 cd",
    "addr:street":"Doormanln",
    "iso:country":"NL",
    "sg:address":"K Doormanln 70",
    "sg:city":"Huizen",
    "sg:orig_category":"Onderhoudswerken",
    "sg:phone":"+31 35 693 6701",
    "sg:postcode":"1271 CD",
    "sg:province":"Noord-Holland",
    "wof:name":"Liefhebber",
    "wof:placetype":"venue"
},
  "geometry": {"coordinates":[5.227464,52.300072],"type":"Point"}
}