{
  "type": "Feature",
  "properties": {
    "iso:country":"NL",
    "sg:address":"Beemsterhoek 104",
    "sg:city":"Capelle A/D Ijssel",
    "sg:orig_category":"Schilderwerk",
    "sg:phone":"+31 10 450 8579",
    "sg:postcode":"2905 XG",
    "sg:province":"Zuid-Holland",
    "wof:name":"Vazo Schilder- En Afwerkingsbedrijf Vof",
    "wof:placetype":"venue"
},
  "geometry": {"coordinates":[4.592709,51.938206],"type":"Point"}
}