{
  "type": "Feature",
  "properties": {
    "addr:full":"Middenstr 4 Oud Gastel Noord-Brabant 4751 PW",
    "addr:housenumber":"4",
    "addr:postcode":"4751 pw",
    "addr:street":"Middenstr",
    "iso:country":"NL",
    "sg:address":"Middenstr 4",
    "sg:city":"Oud Gastel",
    "sg:orig_category":"Meubelen Gebruikte",
    "sg:phone":"+31 165 512 990",
    "sg:postcode":"4751 PW",
    "sg:province":"Noord-Brabant",
    "sg:website":"http://www.ple4.nl",
    "wof:name":"Ple4 Bv Bazaar",
    "wof:placetype":"venue"
},
  "geometry": {"coordinates":[4.469995,51.57935],"type":"Point"}
}