{
  "type": "Feature",
  "properties": {
    "addr:full":"2E Ijzerstraat 2 Rotterdam Zuid-Holland 3024 CX",
    "addr:housenumber":"2",
    "addr:postcode":"3024 cx",
    "addr:street":"2E Ijzerstraat",
    "iso:country":"NL",
    "sg:address":"2E Ijzerstraat 2",
    "sg:city":"Rotterdam",
    "sg:orig_category":"Diverse Grafische Activiteiten",
    "sg:phone":"+31 10 477 8200",
    "sg:postcode":"3024 CX",
    "sg:province":"Zuid-Holland",
    "wof:name":"Lijn 5 Ontwerpers",
    "wof:placetype":"venue"
},
  "geometry": {"coordinates":[4.456489,51.905121],"type":"Point"}
}