{
  "type": "Feature",
  "properties": {
    "addr:full":"Havendk 28 Bunschoten Spakenb Utrecht 3751 AJ",
    "addr:housenumber":"28",
    "addr:postcode":"3751 aj",
    "addr:street":"Havendk",
    "iso:country":"NL",
    "sg:address":"Havendk 28",
    "sg:city":"Bunschoten Spakenb",
    "sg:orig_category":"Verenigingen En Stichtingen",
    "sg:phone":"+31 33 299 6044",
    "sg:postcode":"3751 AJ",
    "sg:province":"Utrecht",
    "wof:name":"Bruine Vloot, De",
    "wof:placetype":"venue"
},
  "geometry": {"coordinates":[5.381317,52.255878],"type":"Point"}
}