{
  "type": "Feature",
  "properties": {
    "addr:full":"Benschopperstraat 7 Ijsselstein Ut Utrecht 3401 DG",
    "addr:housenumber":"7",
    "addr:postcode":"3401 dg",
    "addr:street":"Benschopperstraat",
    "iso:country":"NL",
    "sg:address":"Benschopperstraat 7",
    "sg:city":"Ijsselstein Ut",
    "sg:orig_category":"Slagerijen",
    "sg:phone":"+31 30 688 1331",
    "sg:postcode":"3401 DG",
    "sg:province":"Utrecht",
    "wof:name":"Slagerij Jan Van Zijl Ijsselstein Bv",
    "wof:placetype":"venue"
},
  "geometry": {"coordinates":[5.041562,52.01865],"type":"Point"}
}