{
  "type": "Feature",
  "properties": {
    "addr:full":"Straussln 36 Voorthuizen Gelderland 3781 HN",
    "addr:housenumber":"36",
    "addr:postcode":"3781 hn",
    "addr:street":"Straussln;Gelderland",
    "iso:country":"NL",
    "sg:address":"Straussln 36",
    "sg:city":"Voorthuizen",
    "sg:orig_category":"Bloemen En Planten - Groothandel",
    "sg:phone":"+31 342 473 751",
    "sg:postcode":"3781 HN",
    "sg:province":"Gelderland",
    "wof:name":"Fleurosa",
    "wof:placetype":"venue"
},
  "geometry": {"coordinates":[5.606088,52.181652],"type":"Point"}
}