{
  "type": "Feature",
  "properties": {
    "iso:country":"NL",
    "sg:address":"Wilhelminastr 33",
    "sg:city":"Dalfsen",
    "sg:orig_category":"Bloemen En Planten - Decoratie",
    "sg:phone":"+31 529 435 877",
    "sg:postcode":"7721 CD",
    "sg:province":"Overijssel",
    "wof:name":"Lean",
    "wof:placetype":"venue"
},
  "geometry": {"coordinates":[6.260646,52.507313],"type":"Point"}
}