{
  "type": "Feature",
  "properties": {
    "addr:full":"Grotestr 200 Waalwyk Noord-Brabant 5141 HD",
    "addr:housenumber":"200",
    "addr:postcode":"5141 hd",
    "addr:street":"Waalwyk",
    "iso:country":"NL",
    "sg:address":"Grotestr 200",
    "sg:city":"Waalwyk",
    "sg:orig_category":"Kousen En Sokken",
    "sg:phone":"+31 416 332 649",
    "sg:postcode":"5141 HD",
    "sg:province":"Noord-Brabant",
    "wof:name":"Jambelle",
    "wof:placetype":"venue"
},
  "geometry": {"coordinates":[5.065623,51.690281],"type":"Point"}
}