{
  "type": "Feature",
  "properties": {
    "addr:full":"Schermerhoek 469 Capelle Ad Yssel Zuid-Holland 2905 TW",
    "addr:housenumber":"469",
    "addr:postcode":"2905 tw",
    "addr:street":"Schermerhoek",
    "iso:country":"NL",
    "sg:address":"Schermerhoek 469",
    "sg:city":"Capelle Ad Yssel",
    "sg:orig_category":"Voetbalverenigingen",
    "sg:phone":"+31 6 53292316",
    "sg:postcode":"2905 TW",
    "sg:province":"Zuid-Holland",
    "wof:name":"Noc",
    "wof:placetype":"venue"
},
  "geometry": {"coordinates":[4.600819,51.941341],"type":"Point"}
}