{
  "type": "Feature",
  "properties": {
    "addr:full":"Houtln 1 Rotterdam South Holland 3016 DA",
    "addr:housenumber":"1",
    "addr:postcode":"3016 da",
    "addr:street":"Houtln",
    "iso:country":"NL",
    "sg:address":"Houtln 1",
    "sg:city":"Rotterdam",
    "sg:orig_category":"Bibliotheken En Leeszalen Openbare",
    "sg:phone":"+31 10 411 2389",
    "sg:postcode":"3016 DA",
    "sg:province":"South Holland",
    "wof:name":"Openb Bibliotheek",
    "wof:placetype":"venue"
},
  "geometry": {"coordinates":[4.478455,51.922836],"type":"Point"}
}