{
  "type": "Feature",
  "properties": {
    "addr:full":"Vd Heimstr 62 S Gravenhage South Holland 2582 SB",
    "addr:housenumber":"62",
    "addr:postcode":"2582 sb",
    "addr:street":"S Gravenhage",
    "iso:country":"NL",
    "sg:address":"Vd Heimstr 62",
    "sg:city":"S Gravenhage",
    "sg:orig_category":"Vertaalbureaus",
    "sg:phone":"+31 70 354 2046",
    "sg:postcode":"2582 SB",
    "sg:province":"South Holland",
    "wof:name":"Yland",
    "wof:placetype":"venue"
},
  "geometry": {"coordinates":[4.27852,52.092411],"type":"Point"}
}