{
  "type": "Feature",
  "properties": {
    "iso:country":"NL",
    "sg:address":"Schout Backstraat 43",
    "sg:city":"Tilburg",
    "sg:orig_category":"Kinderopvang Behalve Thuis",
    "sg:phone":"+31 13 590 0168",
    "sg:postcode":"5037 MJ",
    "sg:province":"Noord-Brabant",
    "wof:name":"Kindercentrum 'T Keetje",
    "wof:placetype":"venue"
},
  "geometry": {"coordinates":[5.054665,51.552963],"type":"Point"}
}