{
  "type": "Feature",
  "properties": {
    "addr:full":"Indumaweg 11 Someren Noord-Brabant 5711 EA",
    "addr:housenumber":"11",
    "addr:postcode":"5711 ea",
    "addr:street":"Indumaweg",
    "iso:country":"NL",
    "sg:address":"Indumaweg 11",
    "sg:city":"Someren",
    "sg:orig_category":"Diverse Bedrijfsinstallaties Gh",
    "sg:phone":"+31 493 490 290",
    "sg:postcode":"5711 EA",
    "sg:province":"Noord-Brabant",
    "wof:name":"High Tech Mechatronics Bv",
    "wof:placetype":"venue"
},
  "geometry": {"coordinates":[5.72572,51.391537],"type":"Point"}
}