{
  "type": "Feature",
  "properties": {
    "addr:full":"Willemsparkweg 99 Amsterdam North Holland 1071 GV",
    "addr:housenumber":"99",
    "addr:postcode":"1071 gv",
    "addr:street":"Willemsparkweg",
    "iso:country":"NL",
    "sg:address":"Willemsparkweg 99",
    "sg:city":"Amsterdam",
    "sg:orig_category":"Paramedische Behandelingen",
    "sg:phone":"+31 20 664 0206",
    "sg:postcode":"1071 GV",
    "sg:province":"North Holland",
    "wof:name":"Medisch Centrum Amsterdam",
    "wof:placetype":"venue"
},
  "geometry": {"coordinates":[4.873632,52.356659],"type":"Point"}
}