{
  "type": "Feature",
  "properties": {
    "addr:full":"Dr. A.C. Van Raaltestraat 11 Ommen Overijssel 7731  G",
    "addr:housenumber":"11;7731 g",
    "addr:street":"Raaltestraat",
    "iso:country":"NL",
    "sg:address":"Dr. A.C. Van Raaltestraat 11",
    "sg:city":"Ommen",
    "sg:orig_category":"Schoonheidssalons",
    "sg:phone":"+31 529 450 048",
    "sg:postcode":"7731  G",
    "sg:province":"Overijssel",
    "wof:name":"Ariane Inden",
    "wof:placetype":"venue"
},
  "geometry": {"coordinates":[6.42297,52.517754],"type":"Point"}
}