{
  "type": "Feature",
  "properties": {
    "addr:full":"Bergse L Rottekd 283 Rotterdam South Holland 3056 LJ",
    "addr:housenumber":"283",
    "addr:postcode":"3056 lj",
    "addr:street":"Bergse",
    "iso:country":"NL",
    "sg:address":"Bergse L Rottekd 283",
    "sg:city":"Rotterdam",
    "sg:orig_category":"Wintersportkleding En -Artikelen",
    "sg:phone":"+31 10 421 3231",
    "sg:postcode":"3056 LJ",
    "sg:province":"South Holland",
    "wof:name":"Ski-Reparatie",
    "wof:placetype":"venue"
},
  "geometry": {"coordinates":[4.5170221329,51.9531288147],"type":"Point"}
}