{
  "type": "Feature",
  "properties": {
    "addr:full":"Almelopln 54 S Gravenhage Zuid-Holland 2533 AC",
    "addr:housenumber":"54;gravenhage",
    "addr:postcode":"2533 ac",
    "addr:street":"Almelopln;S",
    "iso:country":"NL",
    "sg:address":"Almelopln 54",
    "sg:city":"S Gravenhage",
    "sg:orig_category":"Fietsen En Bromfietsen",
    "sg:phone":"+31 70 367 1671",
    "sg:postcode":"2533 AC",
    "sg:province":"Zuid-Holland",
    "wof:name":"Badoux",
    "wof:placetype":"venue"
},
  "geometry": {"coordinates":[4.28581,52.05286],"type":"Point"}
}