{
  "type": "Feature",
  "properties": {
    "iso:country":"NL",
    "sg:address":"Plesmanstr 72",
    "sg:city":"Soesterberg",
    "sg:orig_category":"Bijouterie?n",
    "sg:phone":"+31 346 354 379",
    "sg:postcode":"3769 HN",
    "sg:province":"Utrecht",
    "wof:name":"Chrystel",
    "wof:placetype":"venue"
},
  "geometry": {"coordinates":[5.283573,52.11647],"type":"Point"}
}