{
  "type": "Feature",
  "properties": {
    "addr:full":"Capellewg 7 Kruiningen Zeeland 4416 PN",
    "addr:housenumber":"7",
    "addr:postcode":"4416 pn",
    "addr:street":"Capellewg",
    "iso:country":"NL",
    "sg:address":"Capellewg 7",
    "sg:city":"Kruiningen",
    "sg:orig_category":"Bloemen En Planten - Decoratie",
    "sg:phone":"+31 113 383 063",
    "sg:postcode":"4416 PN",
    "sg:province":"Zeeland",
    "wof:name":"Lokerse, A",
    "wof:placetype":"venue"
},
  "geometry": {"coordinates":[4.040904,51.464619],"type":"Point"}
}