{
  "type": "Feature",
  "properties": {
    "addr:full":"Hasseltstraat 265 Tilburg Noord-Brabant 5046 LL",
    "addr:housenumber":"265",
    "addr:postcode":"5046 ll",
    "addr:street":"Hasseltstraat",
    "iso:country":"NL",
    "sg:address":"Hasseltstraat 265",
    "sg:city":"Tilburg",
    "sg:orig_category":"Kappers",
    "sg:phone":"+31 13 542 1946",
    "sg:postcode":"5046 LL",
    "sg:province":"Noord-Brabant",
    "wof:name":"A J A Van Gorp",
    "wof:placetype":"venue"
},
  "geometry": {"coordinates":[5.0740199089,51.5691490173],"type":"Point"}
}