{
  "type": "Feature",
  "properties": {
    "iso:country":"NL",
    "sg:address":"Kievitln 15",
    "sg:city":"Koudekerk Ad Ryn",
    "sg:orig_category":"Adviesbureaus Bedrijfsorganisatie",
    "sg:phone":"+31 71 341 6111",
    "sg:postcode":"2396 JC",
    "sg:province":"Zuid-Holland",
    "wof:name":"Meerbeek",
    "wof:placetype":"venue"
},
  "geometry": {"coordinates":[4.603195,52.133533],"type":"Point"}
}