{
  "type": "Feature",
  "properties": {
    "iso:country":"NL",
    "sg:address":"Nw Gouwe Oz 11B",
    "sg:city":"Gouda",
    "sg:classifiers":[
        {
            "category":"Wholesale",
            "subcategory":"Meat",
            "type":"Manufacturing & Wholesale Goods"
        }
    ],
    "sg:phone":"+31 182 538 943",
    "sg:postcode":"2801 SB",
    "sg:province":"Zuid-Holland",
    "sg:tags":[
        "regeltechniek",
        "en",
        "meet-"
    ],
    "sg:website":"http://www.meetcentrumpp.nl",
    "wof:name":"Meetcentrum Pp",
    "wof:placetype":"venue"
},
  "geometry": {"coordinates":[4.684009,52.018795],"type":"Point"}
}