{
  "type": "Feature",
  "properties": {
    "addr:full":"Pascalwg 4 Zwolle NL.08 8013 RC",
    "addr:housenumber":"4",
    "addr:postcode":"8013 rc",
    "addr:street":"Pascalwg",
    "iso:country":"NL",
    "sg:address":"Pascalwg 4",
    "sg:city":"Zwolle",
    "sg:orig_category":"Loodgieters- Benodigdheden",
    "sg:phone":"+31 38 468 4747",
    "sg:postcode":"8013 RC",
    "sg:province":"NL.08",
    "wof:name":"Kz Bv",
    "wof:placetype":"venue"
},
  "geometry": {"coordinates":[6.132564,52.498775],"type":"Point"}
}