{
  "type": "Feature",
  "properties": {
    "addr:full":"Finsestr 7 Kraggenburg Flevoland 8317 AK",
    "addr:housenumber":"7",
    "addr:postcode":"8317 ak",
    "addr:street":"Finsestr;Flevoland",
    "iso:country":"NL",
    "sg:address":"Finsestr 7",
    "sg:city":"Kraggenburg",
    "sg:orig_category":"Automaterialen En Gereedschappen",
    "sg:phone":"+31 527 252 653",
    "sg:postcode":"8317 AK",
    "sg:province":"Flevoland",
    "wof:name":"Wre",
    "wof:placetype":"venue"
},
  "geometry": {"coordinates":[5.89838,52.661552],"type":"Point"}
}