{
  "type": "Feature",
  "properties": {
    "iso:country":"NL",
    "sg:address":"Langs De Hey 3",
    "sg:city":"Sittard",
    "sg:orig_category":"Plafonds",
    "sg:phone":"+31 46 452 0599",
    "sg:postcode":"6136 KR",
    "sg:province":"Limburg",
    "wof:name":"Hanssen",
    "wof:placetype":"venue"
},
  "geometry": {"coordinates":[5.870028,51.016033],"type":"Point"}
}