{
  "type": "Feature",
  "properties": {
    "addr:full":"Oeverzegge 1 Breda Noord-Brabant 4823 MS",
    "addr:housenumber":"1",
    "addr:postcode":"4823 ms",
    "addr:street":"Oeverzegge",
    "iso:country":"NL",
    "sg:address":"Oeverzegge 1",
    "sg:city":"Breda",
    "sg:orig_category":"Scholen Voor Basisonderwijs",
    "sg:phone":"+31 76 541 1769",
    "sg:postcode":"4823 MS",
    "sg:province":"Noord-Brabant",
    "sg:website":"http://www.driezwing.nl",
    "wof:name":"Driezwing, De",
    "wof:placetype":"venue"
},
  "geometry": {"coordinates":[4.731933,51.620285],"type":"Point"}
}