{
  "type": "Feature",
  "properties": {
    "addr:full":"Sweelinckstraat 5 Oss Virginia 5344 AE",
    "addr:housenumber":"5",
    "addr:postcode":"5344 ae",
    "addr:street":"Sweelinckstraat",
    "iso:country":"NL",
    "sg:address":"Sweelinckstraat 5",
    "sg:city":"Oss",
    "sg:orig_category":"Bouwnijverheidsmachines Gh",
    "sg:phone":"+31 412 634 831",
    "sg:postcode":"5344 AE",
    "sg:province":"Virginia",
    "wof:name":"Probin Van Dijk Oss",
    "wof:placetype":"venue"
},
  "geometry": {"coordinates":[-77.235214,38.312599],"type":"Point"}
}