{
  "type": "Feature",
  "properties": {
    "iso:country":"NL",
    "sg:address":"Dapperstr 26-26A",
    "sg:city":"Deventer",
    "sg:orig_category":"Cafetaria'S",
    "sg:phone":"+31 570 628 478",
    "sg:postcode":"7415 SJ",
    "sg:province":"Overijssel",
    "wof:name":"Tuindorp",
    "wof:placetype":"venue"
},
  "geometry": {"coordinates":[6.165244,52.265728],"type":"Point"}
}