{
  "type": "Feature",
  "properties": {
    "addr:full":"Anjelierenstraat 2 Rijnsburg South Holland 2231 GT",
    "addr:housenumber":"2",
    "addr:postcode":"2231 gt",
    "addr:street":"Anjelierenstraat",
    "iso:country":"NL",
    "sg:address":"Anjelierenstraat 2",
    "sg:city":"Rijnsburg",
    "sg:orig_category":"Banken And Kredietinstellingen",
    "sg:phone":"+31 71 402 2849",
    "sg:postcode":"2231 GT",
    "sg:province":"South Holland",
    "wof:name":"Postkantoor",
    "wof:placetype":"venue"
},
  "geometry": {"coordinates":[4.442815,52.191322],"type":"Point"}
}