{
  "type": "Feature",
  "properties": {
    "addr:full":"Stenenplaats 8 Den Burg Noord-Holland 1791 EA",
    "addr:housenumber":"8",
    "addr:postcode":"1791 ea",
    "addr:street":"Stenenplaats",
    "iso:country":"NL",
    "sg:address":"Stenenplaats 8",
    "sg:city":"Den Burg",
    "sg:orig_category":"Visspeciaalzaken",
    "sg:phone":"+31 222 315 398",
    "sg:postcode":"1791 EA",
    "sg:province":"Noord-Holland",
    "wof:name":"Viscenter Waddenzee",
    "wof:placetype":"venue"
},
  "geometry": {"coordinates":[-94.071686,34.232082],"type":"Point"}
}