{
  "type": "Feature",
  "properties": {
    "addr:full":"Hooghiemstrapln 96 Utrecht Utrecht 3514 AX",
    "addr:housenumber":"96",
    "addr:postcode":"3514 ax",
    "addr:street":"Hooghiemstrapln",
    "iso:country":"NL",
    "sg:address":"Hooghiemstrapln 96",
    "sg:city":"Utrecht",
    "sg:orig_category":"Grafisch Ontwerpers",
    "sg:phone":"+31 30 272 1788",
    "sg:postcode":"3514 AX",
    "sg:province":"Utrecht",
    "sg:website":"http://www.euronet.nl/~eijkpunt",
    "wof:name":"Eijkpunt Grafische Vormgeving",
    "wof:placetype":"venue"
},
  "geometry": {"coordinates":[5.125126,52.098324],"type":"Point"}
}