{
  "type": "Feature",
  "properties": {
    "addr:full":"Wilhelminaplein 3/B Kaatsheuvel North Brabant 5171 KX",
    "addr:housenumber":"3 / b",
    "addr:postcode":"5171 kx",
    "addr:street":"Wilhelminaplein",
    "iso:country":"NL",
    "sg:address":"Wilhelminaplein 3/B",
    "sg:city":"Kaatsheuvel",
    "sg:orig_category":"Architecten",
    "sg:phone":"+31 416 279 868",
    "sg:postcode":"5171 KX",
    "sg:province":"North Brabant",
    "wof:name":"V.B.P. Holland",
    "wof:placetype":"venue"
},
  "geometry": {"coordinates":[5.045931,51.656635],"type":"Point"}
}