{
  "type": "Feature",
  "properties": {
    "addr:full":"Rijssensestraat 197 Nijverdal NL.08 7441 AD",
    "addr:housenumber":"197;nl.08",
    "addr:postcode":"7441 ad",
    "addr:street":"Rijssensestraat",
    "iso:country":"NL",
    "sg:address":"Rijssensestraat 197",
    "sg:city":"Nijverdal",
    "sg:orig_category":"Bedrijfs- And Managementsconsultants",
    "sg:phone":"+31 548 615 456",
    "sg:postcode":"7441 AD",
    "sg:province":"NL.08",
    "wof:name":"Arc Advies",
    "wof:placetype":"venue"
},
  "geometry": {"coordinates":[6.46303,52.359219],"type":"Point"}
}