{
  "type": "Feature",
  "properties": {
    "addr:full":"Hortusplnts 12 Amsterdam North Holland 1018 TZ",
    "addr:housenumber":"12",
    "addr:postcode":"1018 tz",
    "addr:street":"Hortusplnts",
    "iso:country":"NL",
    "sg:address":"Hortusplnts 12",
    "sg:city":"Amsterdam",
    "sg:orig_category":"Beeldende Kunstenaars",
    "sg:phone":"+31 20 627 2410",
    "sg:postcode":"1018 TZ",
    "sg:province":"North Holland",
    "wof:name":"Bernard Ruygrok",
    "wof:placetype":"venue"
},
  "geometry": {"coordinates":[4.893195,52.373119],"type":"Point"}
}