{
  "type": "Feature",
  "properties": {
    "addr:full":"Postbus 1025 Den Helder North Holland 1780 EA",
    "addr:housenumber":"1025",
    "addr:postcode":"1780 ea",
    "addr:street":"Postbus",
    "iso:country":"NL",
    "sg:address":"Postbus 1025",
    "sg:city":"Den Helder",
    "sg:orig_category":"Postorderbedrijven",
    "sg:phone":"+31 6 51104917",
    "sg:postcode":"1780 EA",
    "sg:province":"North Holland",
    "sg:website":"http://www.thexxxshop.com",
    "wof:name":"Dutch Adult Entertainment Comp",
    "wof:placetype":"venue"
},
  "geometry": {"coordinates":[4.7588248253,52.958190918],"type":"Point"}
}