{
  "type": "Feature",
  "properties": {
    "addr:full":"Tarwelaan 15 Eindhoven Noord-Brabant 5632 KB",
    "addr:housenumber":"15",
    "addr:postcode":"5632 kb",
    "addr:street":"Tarwelaan",
    "iso:country":"NL",
    "sg:address":"Tarwelaan 15",
    "sg:city":"Eindhoven",
    "sg:orig_category":"Paramedische Behandelingen",
    "sg:phone":"+31 40 241 2054",
    "sg:postcode":"5632 KB",
    "sg:province":"Noord-Brabant",
    "wof:name":"Dr. M.C.H.J. V.D. Ven",
    "wof:placetype":"venue"
},
  "geometry": {"coordinates":[5.498913,51.47707],"type":"Point"}
}