{
  "type": "Feature",
  "properties": {
    "addr:full":"Reigerpad 10 Ysselstein Ut Utrecht 3403 AP",
    "addr:housenumber":"10",
    "addr:postcode":"3403 ap",
    "addr:street":"Reigerpad",
    "iso:country":"NL",
    "sg:address":"Reigerpad 10",
    "sg:city":"Ysselstein Ut",
    "sg:orig_category":"Voetverzorging",
    "sg:phone":"+31 30 688 6885",
    "sg:postcode":"3403 AP",
    "sg:province":"Utrecht",
    "wof:name":"Bus-V.D. Horst, M J",
    "wof:placetype":"venue"
},
  "geometry": {"coordinates":[5.025497,52.022293],"type":"Point"}
}