{
  "type": "Feature",
  "properties": {
    "addr:full":"Hg Ryndk 166 Leiden Zuid-Holland 2314 AH",
    "addr:housenumber":"166",
    "addr:postcode":"2314 ah",
    "iso:country":"NL",
    "sg:address":"Hg Ryndk 166",
    "sg:city":"Leiden",
    "sg:orig_category":"Koeriersdiensten",
    "sg:phone":"+31 6 22234893",
    "sg:postcode":"2314 AH",
    "sg:province":"Zuid-Holland",
    "wof:name":"A-B Transport Koeriers",
    "wof:placetype":"venue"
},
  "geometry": {"coordinates":[4.514857769,52.1550140381],"type":"Point"}
}