{
  "type": "Feature",
  "properties": {
    "addr:full":"Mr. P.J. Troelstraweg 15 Leeuwarden Friesland 8916 AA",
    "addr:housenumber":"15",
    "addr:postcode":"8916 aa",
    "addr:street":"Mr. P.J. Troelstraweg",
    "iso:country":"NL",
    "sg:address":"Mr. P.J. Troelstraweg 15",
    "sg:city":"Leeuwarden",
    "sg:orig_category":"Boekhandels",
    "sg:phone":"+31 58 212 3553",
    "sg:postcode":"8916 AA",
    "sg:province":"Friesland",
    "wof:name":"Het Jokertje",
    "wof:placetype":"venue"
},
  "geometry": {"coordinates":[5.78498,53.208649],"type":"Point"}
}