{
  "type": "Feature",
  "properties": {
    "iso:country":"NL",
    "sg:address":"Begoniastr 10",
    "sg:city":"St Michielsgestel",
    "sg:orig_category":"Goudsmeden En Zilversmeden",
    "sg:phone":"+31 73 549 4792",
    "sg:postcode":"5271 GR",
    "sg:province":"Noord-Brabant",
    "wof:name":"Metal Maid",
    "wof:placetype":"venue"
},
  "geometry": {"coordinates":[5.342946,51.639915],"type":"Point"}
}