{
  "type": "Feature",
  "properties": {
    "iso:country":"NL",
    "sg:address":"Marchandweg 17A",
    "sg:city":"Barneveld",
    "sg:orig_category":"Bedrijfsinventaris Gh",
    "sg:phone":"+31 342 450 632",
    "sg:postcode":"3771 ML",
    "sg:province":"Gelderland",
    "wof:name":"Tukker Products",
    "wof:placetype":"venue"
},
  "geometry": {"coordinates":[5.581547,52.162971],"type":"Point"}
}