{
  "type": "Feature",
  "properties": {
    "iso:country":"NL",
    "sg:address":"Waalhaven Z.Z. 2",
    "sg:city":"Rotterdam",
    "sg:classifiers":[
        {
            "category":"Retail",
            "subcategory":"Storage",
            "type":"Services"
        }
    ],
    "sg:phone":"+31 10 283 1000",
    "sg:postcode":"3088 HH",
    "sg:province":"Zuid-Holland",
    "sg:tags":[
        "opslag",
        "bewaring"
    ],
    "wof:name":"Henry Bath Bv",
    "wof:placetype":"venue"
},
  "geometry": {"coordinates":[4.452226162,51.8776931763],"type":"Point"}
}