{
  "type": "Feature",
  "properties": {
    "addr:full":"Edesewg 67 Bennekom Gelderland 6721 JP",
    "addr:housenumber":"67",
    "addr:postcode":"6721 jp",
    "addr:street":"Edesewg;Gelderland",
    "iso:country":"NL",
    "sg:address":"Edesewg 67",
    "sg:city":"Bennekom",
    "sg:orig_category":"Beeldende Kunstenaars",
    "sg:phone":"+31 318 414 163",
    "sg:postcode":"6721 JP",
    "sg:province":"Gelderland",
    "wof:name":"Stouten, L",
    "wof:placetype":"venue"
},
  "geometry": {"coordinates":[5.675081,52.002903],"type":"Point"}
}