{
  "type": "Feature",
  "properties": {
    "addr:full":"Deutzstraat 12 Heemskerk North Holland 1961 NT",
    "addr:housenumber":"12",
    "addr:postcode":"1961 nt",
    "addr:street":"Deutzstraat",
    "iso:country":"NL",
    "sg:address":"Deutzstraat 12",
    "sg:city":"Heemskerk",
    "sg:classifiers":[
        {
            "category":"Retail",
            "subcategory":"Photofinishing",
            "type":"Services"
        }
    ],
    "sg:phone":"+31 251 233 284",
    "sg:postcode":"1961 NT",
    "sg:province":"North Holland",
    "sg:tags":[
        "foto",
        "film"
    ],
    "wof:name":"Combi Blom",
    "wof:placetype":"venue"
},
  "geometry": {"coordinates":[4.670558,52.511417],"type":"Point"}
}