{
  "type": "Feature",
  "properties": {
    "addr:full":"Voltastr 4 Terneuzen Zeeland 4532 LH",
    "addr:housenumber":"4",
    "addr:postcode":"4532 lh",
    "addr:street":"Voltastr",
    "iso:country":"NL",
    "sg:address":"Voltastr 4",
    "sg:city":"Terneuzen",
    "sg:orig_category":"Verhuur",
    "sg:phone":"+31 115 630 106",
    "sg:postcode":"4532 LH",
    "sg:province":"Zeeland",
    "wof:name":"Stockman, Gebroeders",
    "wof:placetype":"venue"
},
  "geometry": {"coordinates":[3.849024,51.32766],"type":"Point"}
}