{
  "type": "Feature",
  "properties": {
    "addr:full":"Kleiweg 9 Gouda Zuid-Holland 2801 GB",
    "addr:housenumber":"9",
    "addr:postcode":"2801 gb",
    "addr:street":"Kleiweg",
    "iso:country":"NL",
    "sg:address":"Kleiweg 9",
    "sg:city":"Gouda",
    "sg:orig_category":"Opticiens",
    "sg:phone":"+31 182 599 995",
    "sg:postcode":"2801 GB",
    "sg:province":"Zuid-Holland",
    "wof:name":"Specsavers Opticiens Gouda Bv",
    "wof:placetype":"venue"
},
  "geometry": {"coordinates":[4.7099051476,52.0131225586],"type":"Point"}
}