{
  "type": "Feature",
  "properties": {
    "iso:country":"NL",
    "sg:address":"Noorderweg 5",
    "sg:city":"De Kiel",
    "sg:orig_category":"Goederenvervoer Over De Weg",
    "sg:phone":"+31 591 381 594",
    "sg:postcode":"7849 TB",
    "sg:province":"Provincie Drenthe",
    "wof:name":"E Bos",
    "wof:placetype":"venue"
},
  "geometry": {"coordinates":[6.738211,52.87149],"type":"Point"}
}