{
  "type": "Feature",
  "properties": {
    "iso:country":"NL",
    "sg:address":"Traay 2C",
    "sg:city":"Driebergen Rysenb",
    "sg:orig_category":"Makelaars En Adviseurs Onroerende Goederen",
    "sg:phone":"+31 343 533 489",
    "sg:postcode":"3971 GN",
    "sg:province":"Utrecht",
    "sg:website":"http://www.postmamakelaars.nl",
    "wof:name":"Postma Partners",
    "wof:placetype":"venue"
},
  "geometry": {"coordinates":[5.283028,52.051903],"type":"Point"}
}