{
  "type": "Feature",
  "properties": {
    "addr:full":"Hoek En Vaarthof 4 Santpoort-Zuid Noord-Holland 2082 EW",
    "addr:housenumber":"4",
    "addr:postcode":"2082 ew",
    "addr:street":"Hoek En Vaarthof",
    "iso:country":"NL",
    "sg:address":"Hoek En Vaarthof 4",
    "sg:city":"Santpoort-Zuid",
    "sg:orig_category":"Adviesbureaus",
    "sg:phone":"+31 23 531 8009",
    "sg:postcode":"2082 EW",
    "sg:province":"Noord-Holland",
    "wof:name":"Schellinger & Van Rossum Vof",
    "wof:placetype":"venue"
},
  "geometry": {"coordinates":[4.628408,52.413479],"type":"Point"}
}