{
  "type": "Feature",
  "properties": {
    "iso:country":"NL",
    "sg:address":"Molenstraat 16",
    "sg:city":"'S Heerenberg",
    "sg:orig_category":"Kappers",
    "sg:phone":"+31 314 662 461",
    "sg:postcode":"7041 AE",
    "sg:province":"North Rhine-Westphalia",
    "wof:name":"Haarsalon Jose",
    "wof:placetype":"venue"
},
  "geometry": {"coordinates":[6.24327,51.875198],"type":"Point"}
}