{
  "type": "Feature",
  "properties": {
    "addr:full":"Marconiwg 6 Coevorden Drenthe 7741 KM",
    "addr:housenumber":"6",
    "addr:postcode":"7741 km",
    "addr:street":"Marconiwg",
    "iso:country":"NL",
    "sg:address":"Marconiwg 6",
    "sg:city":"Coevorden",
    "sg:orig_category":"Veenderijen",
    "sg:phone":"+31 524 593 600",
    "sg:postcode":"7741 KM",
    "sg:province":"Drenthe",
    "sg:website":"http://www.trefgroup.nl",
    "wof:name":"Tref Substrates Bv",
    "wof:placetype":"venue"
},
  "geometry": {"coordinates":[6.735435,52.656448],"type":"Point"}
}