{
  "type": "Feature",
  "properties": {
    "addr:full":"St Jozefpk 1 Tuitjenhorn Noord-Holland 1747 HK",
    "addr:housenumber":"1",
    "addr:postcode":"1747 hk",
    "iso:country":"NL",
    "sg:address":"St Jozefpk 1",
    "sg:city":"Tuitjenhorn",
    "sg:orig_category":"Verenigingen En Stichtingen",
    "sg:phone":"+31 226 393 335",
    "sg:postcode":"1747 HK",
    "sg:province":"Noord-Holland",
    "wof:name":"Graag Gedaan",
    "wof:placetype":"venue"
},
  "geometry": {"coordinates":[4.748639,52.739227],"type":"Point"}
}