{
  "type": "Feature",
  "properties": {
    "addr:full":"V W V Dykveldstr 50 S Gravenhage Zuid-Holland 2582 KW",
    "addr:housenumber":"50;gravenhage",
    "addr:postcode":"2582 kw",
    "addr:street":"W V Dykveldstr;S",
    "iso:country":"NL",
    "sg:address":"V W V Dykveldstr 50",
    "sg:city":"S Gravenhage",
    "sg:orig_category":"Bedrijfsopleidingen",
    "sg:phone":"+31 70 362 2717",
    "sg:postcode":"2582 KW",
    "sg:province":"Zuid-Holland",
    "wof:name":"Mariposa",
    "wof:placetype":"venue"
},
  "geometry": {"coordinates":[4.27852,52.092411],"type":"Point"}
}