{
  "type": "Feature",
  "properties": {
    "addr:full":"Hinthamerstraat 104 Den Bosch North Brabant 5212 MS",
    "addr:housenumber":"104",
    "addr:postcode":"5212 ms",
    "addr:street":"Hinthamerstraat",
    "iso:country":"NL",
    "sg:address":"Hinthamerstraat 104",
    "sg:city":"Den Bosch",
    "sg:classifiers":[
        {
            "category":"Bars & Pubs",
            "type":"Food & Drink"
        }
    ],
    "sg:phone":"+31 73 612 4584",
    "sg:postcode":"5212 MS",
    "sg:province":"North Brabant",
    "wof:name":"Meetpoint Bv",
    "wof:placetype":"venue"
},
  "geometry": {"coordinates":[5.30916,51.696529],"type":"Point"}
}