{
  "type": "Feature",
  "properties": {
    "addr:full":"Merelln 286 Capelle Ad Yssel South Holland 2902 JM",
    "addr:housenumber":"286",
    "addr:postcode":"2902 jm",
    "addr:street":"Yssel",
    "iso:country":"NL",
    "sg:address":"Merelln 286",
    "sg:city":"Capelle Ad Yssel",
    "sg:orig_category":"Pianostemmen En -Reparatie",
    "sg:phone":"+31 10 450 0383",
    "sg:postcode":"2902 JM",
    "sg:province":"South Holland",
    "wof:name":"Birnie, Frans",
    "wof:placetype":"venue"
},
  "geometry": {"coordinates":[4.57697,51.926311],"type":"Point"}
}