{
  "type": "Feature",
  "properties": {
    "addr:full":"Molenvlietbrink 13A Woerden Utrecht 3448 HT",
    "addr:housenumber":"13a",
    "addr:postcode":"3448 ht",
    "addr:street":"Molenvlietbrink",
    "iso:country":"NL",
    "sg:address":"Molenvlietbrink 13A",
    "sg:city":"Woerden",
    "sg:orig_category":"Homeopathie",
    "sg:phone":"+31 348 421 286",
    "sg:postcode":"3448 HT",
    "sg:province":"Utrecht",
    "wof:name":"Holtkamp Gf, Arts",
    "wof:placetype":"venue"
},
  "geometry": {"coordinates":[4.863576,52.07655],"type":"Point"}
}