{
  "type": "Feature",
  "properties": {
    "iso:country":"NL",
    "sg:address":"Stadsweg 87",
    "sg:city":"Ten Boer",
    "sg:orig_category":"Levende Dieren Gh",
    "sg:phone":"+31 50 302 3177",
    "sg:postcode":"9791 KC",
    "sg:province":"Groningen",
    "wof:name":"Handelsonderneming Sake Van Der Goot",
    "wof:placetype":"venue"
},
  "geometry": {"coordinates":[6.694356,53.278675],"type":"Point"}
}