{
  "type": "Feature",
  "properties": {
    "iso:country":"NL",
    "sg:address":"Romelaan 25",
    "sg:city":"Oudenbosch",
    "sg:orig_category":"Loodgieterswerk, Verwarming And Sanitaire Installaties",
    "sg:phone":"+31 165 316 611",
    "sg:postcode":"4731 EE",
    "sg:province":"Noord-Brabant",
    "wof:name":"Dive Klussenbedrijf",
    "wof:placetype":"venue"
},
  "geometry": {"coordinates":[4.548445,51.592663],"type":"Point"}
}