{
  "type": "Feature",
  "properties": {
    "addr:full":"Oerdk 81B Schalkhaar Overijssel 7433 PA",
    "addr:housenumber":"81b",
    "addr:postcode":"7433 pa",
    "addr:street":"Oerdk",
    "iso:country":"NL",
    "sg:address":"Oerdk 81B",
    "sg:city":"Schalkhaar",
    "sg:classifiers":[
        {
            "category":"Sports & Exercise",
            "subcategory":"Stables",
            "type":"Entertainment"
        }
    ],
    "sg:phone":"+31 570 623 640",
    "sg:postcode":"7433 PA",
    "sg:province":"Overijssel",
    "sg:tags":[
        "maneges"
    ],
    "wof:name":"Schalkhaar",
    "wof:placetype":"venue"
},
  "geometry": {"coordinates":[6.206218,52.266388],"type":"Point"}
}