{
  "type": "Feature",
  "properties": {
    "addr:full":"Kanaalstr 212 Lisse Zuid-Holland 2161 JW",
    "addr:housenumber":"212",
    "addr:postcode":"lisse;2161 jw",
    "iso:country":"NL",
    "sg:address":"Kanaalstr 212",
    "sg:city":"Lisse",
    "sg:orig_category":"Huidtherapeuten",
    "sg:phone":"+31 252 422 420",
    "sg:postcode":"2161 JW",
    "sg:province":"Zuid-Holland",
    "wof:name":"Astrid Akbar",
    "wof:placetype":"venue"
},
  "geometry": {"coordinates":[4.565016,52.257229],"type":"Point"}
}