{
  "type": "Feature",
  "properties": {
    "addr:full":"A Cuypstr 8 Zutphen Gelderland 7204 BS",
    "addr:housenumber":"8",
    "addr:postcode":"7204 bs",
    "addr:street":"Gelderland",
    "iso:country":"NL",
    "sg:address":"A Cuypstr 8",
    "sg:city":"Zutphen",
    "sg:classifiers":[
        {
            "category":"Personal",
            "subcategory":"Nail Salon",
            "type":"Services"
        }
    ],
    "sg:phone":"+31 575 511 816",
    "sg:postcode":"7204 BS",
    "sg:province":"Gelderland",
    "sg:tags":[
        "pedicure"
    ],
    "wof:name":"Veen, F Van Der",
    "wof:placetype":"venue"
},
  "geometry": {"coordinates":[6.206936,52.139389],"type":"Point"}
}