{
  "type": "Feature",
  "properties": {
    "iso:country":"NL",
    "sg:address":"Str V A Cramer 1",
    "sg:city":"Haarlem",
    "sg:orig_category":"Voegwerken",
    "sg:phone":"+31 23 535 7585",
    "sg:postcode":"2033 RZ",
    "sg:province":"Noord-Holland",
    "wof:name":"Olphen, P J Van",
    "wof:placetype":"venue"
},
  "geometry": {"coordinates":[4.66298,52.37672],"type":"Point"}
}