{
  "type": "Feature",
  "properties": {
    "addr:full":"Waalstraat 89 3 Hoog Amsterdam Noord-Holland 1079 DS",
    "addr:housenumber":"89 3",
    "addr:postcode":"1079 ds",
    "addr:street":"Waalstraat;Hoog",
    "iso:country":"NL",
    "sg:address":"Waalstraat 89 3 Hoog",
    "sg:city":"Amsterdam",
    "sg:orig_category":"Partycatering And -Organisatie",
    "sg:phone":"+31 20 642 5851",
    "sg:postcode":"1079 DS",
    "sg:province":"Noord-Holland",
    "wof:name":"Geerts Catering",
    "wof:placetype":"venue"
},
  "geometry": {"coordinates":[4.89319,52.373119],"type":"Point"}
}