{
  "type": "Feature",
  "properties": {
    "addr:full":"Achter De Keizer 1 Nijverdal Overijssel 7442 NR",
    "addr:housenumber":"1",
    "addr:postcode":"7442 nr",
    "addr:street":"Achter De Keizer",
    "iso:country":"NL",
    "sg:address":"Achter De Keizer 1",
    "sg:city":"Nijverdal",
    "sg:orig_category":"Werving And Selectie Van Vast Personeel",
    "sg:phone":"+31 74 255 7600",
    "sg:postcode":"7442 NR",
    "sg:province":"Overijssel",
    "wof:name":"Arbeidsbureau Nijverdal",
    "wof:placetype":"venue"
},
  "geometry": {"coordinates":[6.4613208771,52.3634872437],"type":"Point"}
}