{
  "type": "Feature",
  "properties": {
    "addr:full":"Schapendrift 2 Laren Nh Noord-Holland 1251 XG",
    "addr:housenumber":"2",
    "addr:postcode":"1251 xg",
    "addr:street":"Schapendrift",
    "iso:country":"NL",
    "sg:address":"Schapendrift 2",
    "sg:city":"Laren Nh",
    "sg:orig_category":"Fietsen En Bromfietsen",
    "sg:phone":"+31 35 538 9645",
    "sg:postcode":"1251 XG",
    "sg:province":"Noord-Holland",
    "wof:name":"Bel Fietsen",
    "wof:placetype":"venue"
},
  "geometry": {"coordinates":[5.236667,52.24968],"type":"Point"}
}