{
  "type": "Feature",
  "properties": {
    "addr:full":"Dionisiusstr 36 Roermond Limburg 6041 GE",
    "addr:housenumber":"36",
    "addr:postcode":"6041",
    "addr:street":"Dionisiusstr",
    "iso:country":"NL",
    "sg:address":"Dionisiusstr 36",
    "sg:city":"Roermond",
    "sg:orig_category":"Onroerende Goederen",
    "sg:phone":"+31 475 331 447",
    "sg:postcode":"6041 GE",
    "sg:province":"Limburg",
    "wof:name":"Mertens",
    "wof:placetype":"venue"
},
  "geometry": {"coordinates":[5.990435,51.194881],"type":"Point"}
}