{
  "type": "Feature",
  "properties": {
    "addr:full":"Heidewg 34 Elst Ut Utrecht 3921 CL",
    "addr:housenumber":"34",
    "addr:postcode":"ut;3921",
    "addr:street":"Heidewg",
    "iso:country":"NL",
    "sg:address":"Heidewg 34",
    "sg:city":"Elst Ut",
    "sg:orig_category":"Organisatiebureaus",
    "sg:phone":"+31 318 471 601",
    "sg:postcode":"3921 CL",
    "sg:province":"Utrecht",
    "wof:name":"Boba",
    "wof:placetype":"venue"
},
  "geometry": {"coordinates":[5.5029492378,51.9842376709],"type":"Point"}
}