{
  "type": "Feature",
  "properties": {
    "addr:full":"Luzernestr 25A Nieuw Vennep Noord-Holland 2153 GM",
    "addr:housenumber":"25a nieuw vennep",
    "addr:postcode":"2153 gm",
    "addr:street":"Luzernestr",
    "iso:country":"NL",
    "sg:address":"Luzernestr 25A",
    "sg:city":"Nieuw Vennep",
    "sg:orig_category":"Bloemen En Planten - Decoratie",
    "sg:phone":"+31 252 680 297",
    "sg:postcode":"2153 GM",
    "sg:province":"Noord-Holland",
    "wof:name":"Pragma Bv",
    "wof:placetype":"venue"
},
  "geometry": {"coordinates":[4.647643,52.263302],"type":"Point"}
}