{
  "type": "Feature",
  "properties": {
    "addr:full":"De Hoef 3D Gameren Gelderland 5311 GH",
    "addr:housenumber":"3d",
    "addr:postcode":"5311 gh",
    "addr:street":"De Hoef;Gelderland",
    "iso:country":"NL",
    "sg:address":"De Hoef 3D",
    "sg:city":"Gameren",
    "sg:orig_category":"Kaas",
    "sg:phone":"+31 418 561 699",
    "sg:postcode":"5311 GH",
    "sg:province":"Gelderland",
    "wof:name":"Brandwijk",
    "wof:placetype":"venue"
},
  "geometry": {"coordinates":[5.202917099,51.7982788086],"type":"Point"}
}