{
  "type": "Feature",
  "properties": {
    "addr:full":"Oranjeboomstraat 81 Breda North Brabant 4812 EB",
    "addr:housenumber":"81",
    "addr:postcode":"4812 eb",
    "addr:street":"Oranjeboomstraat",
    "iso:country":"NL",
    "sg:address":"Oranjeboomstraat 81",
    "sg:city":"Breda",
    "sg:orig_category":"Kappers",
    "sg:phone":"+31 76 521 2324",
    "sg:postcode":"4812 EB",
    "sg:province":"North Brabant",
    "wof:name":"Knippen Enzo",
    "wof:placetype":"venue"
},
  "geometry": {"coordinates":[4.761932,51.580982],"type":"Point"}
}