{
  "type": "Feature",
  "properties": {
    "addr:full":"Overheek 62 Klimmen Limburg 6343 PC",
    "addr:housenumber":"62",
    "addr:postcode":"6343 pc",
    "addr:street":"Overheek",
    "iso:country":"NL",
    "sg:address":"Overheek 62",
    "sg:city":"Klimmen",
    "sg:orig_category":"Vakantiehuizen",
    "sg:phone":"+31 45 405 1584",
    "sg:postcode":"6343 PC",
    "sg:province":"Limburg",
    "wof:name":"Clumma",
    "wof:placetype":"venue"
},
  "geometry": {"coordinates":[5.873982,50.880756],"type":"Point"}
}