{
  "type": "Feature",
  "properties": {
    "iso:country":"NL",
    "sg:address":"Reigerstr 6",
    "sg:city":"Katwyk Zh",
    "sg:orig_category":"Bestratingen",
    "sg:phone":"+31 71 401 7038",
    "sg:postcode":"2225 PM",
    "sg:province":"South Holland",
    "sg:website":"http://www.vanleeuwen-katwijk.nl",
    "wof:name":"Leeuwen Sierbestrating Bv, Van",
    "wof:placetype":"venue"
},
  "geometry": {"coordinates":[4.403815,52.199043],"type":"Point"}
}