{
  "type": "Feature",
  "properties": {
    "addr:full":"Kerkweg 5 Swalmen Limburg 6071 AL",
    "addr:housenumber":"5",
    "addr:postcode":"6071 al",
    "addr:street":"Kerkweg",
    "iso:country":"NL",
    "sg:address":"Kerkweg 5",
    "sg:city":"Swalmen",
    "sg:orig_category":"Overheidsdiensten",
    "sg:phone":"+31 475 501 782",
    "sg:postcode":"6071 AL",
    "sg:province":"Limburg",
    "wof:name":"De Kamp",
    "wof:placetype":"venue"
},
  "geometry": {"coordinates":[6.046998024,51.2149047852],"type":"Point"}
}