{
  "type": "Feature",
  "properties": {
    "addr:full":"Heiveld 35 Rysbergen Noord-Brabant 4891 VD",
    "addr:housenumber":"35",
    "addr:postcode":"4891 vd",
    "addr:street":"Heiveld",
    "iso:country":"NL",
    "sg:address":"Heiveld 35",
    "sg:city":"Rysbergen",
    "sg:orig_category":"Natuurgeneeskundigen",
    "sg:phone":"+31 76 596 3380",
    "sg:postcode":"4891 VD",
    "sg:province":"Noord-Brabant",
    "sg:website":"http://www.levensboom.com",
    "wof:name":"Levensboom, De",
    "wof:placetype":"venue"
},
  "geometry": {"coordinates":[4.693161,51.519672],"type":"Point"}
}