{
  "type": "Feature",
  "properties": {
    "addr:full":"Klompenmakerstr 20 Hoogvliet Rt Zuid-Holland 3194 DE",
    "addr:housenumber":"20",
    "addr:postcode":"rt;3194 de",
    "addr:street":"Klompenmakerstr",
    "iso:country":"NL",
    "sg:address":"Klompenmakerstr 20",
    "sg:city":"Hoogvliet Rt",
    "sg:orig_category":"Schilders",
    "sg:phone":"+31 10 289 1110",
    "sg:postcode":"3194 DE",
    "sg:province":"Zuid-Holland",
    "wof:name":"Essen Bv, Van",
    "wof:placetype":"venue"
},
  "geometry": {"coordinates":[4.3785481453,51.8679885864],"type":"Point"}
}