{
  "type": "Feature",
  "properties": {
    "addr:full":"Pr Beatrixln 118 Waddinxveen Zuid-Holland 2741 DJ",
    "addr:housenumber":"118",
    "addr:postcode":"waddinxveen;2741 dj",
    "iso:country":"NL",
    "sg:address":"Pr Beatrixln 118",
    "sg:city":"Waddinxveen",
    "sg:orig_category":"Zoetwaren - Fabrieken En Groothandel",
    "sg:phone":"+31 182 614 324",
    "sg:postcode":"2741 DJ",
    "sg:province":"Zuid-Holland",
    "wof:name":"Kok, R",
    "wof:placetype":"venue"
},
  "geometry": {"coordinates":[4.650636,52.048824],"type":"Point"}
}