{
  "type": "Feature",
  "properties": {
    "iso:country":"NL",
    "sg:address":"Herenstr 64",
    "sg:city":"Leiden",
    "sg:orig_category":"Peuterspeelzalen",
    "sg:phone":"+31 71 514 6637",
    "sg:postcode":"2313 AM",
    "sg:province":"Zuid-Holland",
    "wof:name":"Kleine Urt, De",
    "wof:placetype":"venue"
},
  "geometry": {"coordinates":[4.488873,52.151314],"type":"Point"}
}