{
  "type": "Feature",
  "properties": {
    "addr:full":"Drakenstein 2 Landsmeer Noord-Holland 1121 HA",
    "addr:housenumber":"2",
    "addr:postcode":"1121 ha",
    "addr:street":"Drakenstein",
    "iso:country":"NL",
    "sg:address":"Drakenstein 2",
    "sg:city":"Landsmeer",
    "sg:orig_category":"Reclame",
    "sg:phone":"+31 20 482 2294",
    "sg:postcode":"1121 HA",
    "sg:province":"Noord-Holland",
    "wof:name":"Maramoja",
    "wof:placetype":"venue"
},
  "geometry": {"coordinates":[4.915682,52.427692],"type":"Point"}
}