{
  "type": "Feature",
  "properties": {
    "iso:country":"NL",
    "sg:address":"Dykwg 29",
    "sg:city":"Zevenaar",
    "sg:orig_category":"Vervoercentra",
    "sg:phone":"+31 316 527 057",
    "sg:postcode":"6905 BA",
    "sg:province":"Gelderland",
    "wof:name":"Vervoerplan Nederland Bv",
    "wof:placetype":"venue"
},
  "geometry": {"coordinates":[6.08225,51.915859],"type":"Point"}
}