{
  "type": "Feature",
  "properties": {
    "addr:full":"Herestr 94 Groningen Groningen 9711 LM",
    "addr:housenumber":"94",
    "addr:postcode":"9711 lm",
    "addr:street":"Herestr",
    "iso:country":"NL",
    "sg:address":"Herestr 94",
    "sg:city":"Groningen",
    "sg:orig_category":"Juweliers",
    "sg:phone":"+31 50 318 7359",
    "sg:postcode":"9711 LM",
    "sg:province":"Groningen",
    "wof:name":"Franc Nyboer",
    "wof:placetype":"venue"
},
  "geometry": {"coordinates":[6.569126,53.214622],"type":"Point"}
}