{
  "type": "Feature",
  "properties": {
    "addr:full":"Emslandweg 17 Ommen NL.08 7731 RP",
    "addr:housenumber":"17;nl.08",
    "addr:postcode":"7731",
    "addr:street":"Emslandweg",
    "iso:country":"NL",
    "sg:address":"Emslandweg 17",
    "sg:city":"Ommen",
    "sg:orig_category":"Fitnesscentra",
    "sg:phone":"+31 529 453 084",
    "sg:postcode":"7731 RP",
    "sg:province":"NL.08",
    "wof:name":"Sportcentrum Emsland",
    "wof:placetype":"venue"
},
  "geometry": {"coordinates":[6.387128,52.533394],"type":"Point"}
}