{
  "type": "Feature",
  "properties": {
    "addr:full":"Ln V Cattenbroeck 32 Zeist Utrecht 3703 BN",
    "addr:housenumber":"32",
    "addr:postcode":"3703 bn",
    "addr:street":"Ln;Cattenbroeck",
    "iso:country":"NL",
    "sg:address":"Ln V Cattenbroeck 32",
    "sg:city":"Zeist",
    "sg:orig_category":"Journalisten Freelance",
    "sg:phone":"+31 30 691 6084",
    "sg:postcode":"3703 BN",
    "sg:province":"Utrecht",
    "wof:name":"Elzinga, Herman",
    "wof:placetype":"venue"
},
  "geometry": {"coordinates":[5.225812,52.08028],"type":"Point"}
}