{
  "type": "Feature",
  "properties": {
    "addr:full":"E Wolffstr 66 Amsterdam Noord-Holland 1053 TW",
    "addr:housenumber":"66",
    "addr:postcode":"1053 tw",
    "iso:country":"NL",
    "sg:address":"E Wolffstr 66",
    "sg:city":"Amsterdam",
    "sg:orig_category":"Acupunctuur",
    "sg:phone":"+31 20 618 2246",
    "sg:postcode":"1053 TW",
    "sg:province":"Noord-Holland",
    "wof:name":"Veld, T In 'T",
    "wof:placetype":"venue"
},
  "geometry": {"coordinates":[4.867454,52.369232],"type":"Point"}
}