{
  "type": "Feature",
  "properties": {
    "addr:full":"Koningin Wilhelminastr 1 Sneek Provincie Friesland 8606 BV",
    "addr:housenumber":"1",
    "addr:postcode":"8606 bv",
    "addr:street":"Koningin Wilhelminastr;Provincie Friesland",
    "iso:country":"NL",
    "sg:address":"Koningin Wilhelminastr 1",
    "sg:city":"Sneek",
    "sg:orig_category":"Metaalafval, Schrootrecycling And Sloperijen",
    "sg:phone":"+31 515 420 034",
    "sg:postcode":"8606 BV",
    "sg:province":"Provincie Friesland",
    "wof:name":"J. Vermaning",
    "wof:placetype":"venue"
},
  "geometry": {"coordinates":[5.668755,53.026173],"type":"Point"}
}