{
  "type": "Feature",
  "properties": {
    "iso:country":"NL",
    "sg:address":"Zuidbargerstraat 72",
    "sg:city":"Emmen",
    "sg:orig_category":"Verhuur Bouwmachines",
    "sg:phone":"+31 591 630 622",
    "sg:postcode":"7812 AJ",
    "sg:province":"Drenthe",
    "wof:name":"Verhuurbedrijf Zuidbarge",
    "wof:placetype":"venue"
},
  "geometry": {"coordinates":[6.903977,52.752911],"type":"Point"}
}