{
  "type": "Feature",
  "properties": {
    "addr:full":"Zuidbargerstraat 72 Emmen Drenthe 7812 AJ",
    "addr:housenumber":"72",
    "addr:postcode":"7812 aj",
    "addr:street":"Zuidbargerstraat",
    "iso:country":"NL",
    "sg:address":"Zuidbargerstraat 72",
    "sg:city":"Emmen",
    "sg:orig_category":"Verhuur Bouwmachines",
    "sg:phone":"+31 591 630 622",
    "sg:postcode":"7812 AJ",
    "sg:province":"Drenthe",
    "wof:name":"Verhuurbedrijf Zuidbarge",
    "wof:placetype":"venue"
},
  "geometry": {"coordinates":[6.903977,52.752911],"type":"Point"}
}