{
  "type": "Feature",
  "properties": {
    "addr:full":"De Brink 100 Zutphen Gelderland 7206 KC",
    "addr:housenumber":"100",
    "addr:postcode":"7206 kc",
    "addr:street":"De Brink;Gelderland",
    "iso:country":"NL",
    "sg:address":"De Brink 100",
    "sg:city":"Zutphen",
    "sg:orig_category":"Kappers",
    "sg:phone":"+31 575 525 981",
    "sg:postcode":"7206 KC",
    "sg:province":"Gelderland",
    "wof:name":"Maison Madelene",
    "wof:placetype":"venue"
},
  "geometry": {"coordinates":[6.191525,52.140202],"type":"Point"}
}