{
  "type": "Feature",
  "properties": {
    "addr:full":"Hondsrugln 89C Eindhoven Noord-Brabant 5628 DB",
    "addr:housenumber":"89c",
    "addr:postcode":"5628 db",
    "addr:street":"Hondsrugln",
    "iso:country":"NL",
    "sg:address":"Hondsrugln 89C",
    "sg:city":"Eindhoven",
    "sg:orig_category":"Adviesbureaus",
    "sg:phone":"+31 40 241 1662",
    "sg:postcode":"5628 DB",
    "sg:province":"Noord-Brabant",
    "sg:website":"http://www.veilignb.nl",
    "wof:name":"Veiligheidsdienst Noord-Brabant Bv",
    "wof:placetype":"venue"
},
  "geometry": {"coordinates":[5.47191,51.48011],"type":"Point"}
}