{
  "type": "Feature",
  "properties": {
    "addr:full":"Willemsparkwg 189 Amsterdam Noord-Holland 1071 HA",
    "addr:housenumber":"189",
    "addr:postcode":"1071 ha",
    "iso:country":"NL",
    "sg:address":"Willemsparkwg 189",
    "sg:city":"Amsterdam",
    "sg:orig_category":"Adviesbureaus Bedrijfsorganisatie",
    "sg:phone":"+31 20 662 1655",
    "sg:postcode":"1071 HA",
    "sg:province":"Noord-Holland",
    "wof:name":"Kuipers Bv, J E",
    "wof:placetype":"venue"
},
  "geometry": {"coordinates":[4.869777,52.35564],"type":"Point"}
}