{
  "type": "Feature",
  "properties": {
    "addr:full":"Koperslagery 62 Zevenbergen Noord-Brabant 4762 AP",
    "addr:housenumber":"62",
    "addr:postcode":"4762 ap",
    "addr:street":"Koperslagery",
    "iso:country":"NL",
    "sg:address":"Koperslagery 62",
    "sg:city":"Zevenbergen",
    "sg:orig_category":"Verf En Lak",
    "sg:phone":"+31 168 323 251",
    "sg:postcode":"4762 AP",
    "sg:province":"Noord-Brabant",
    "wof:name":"Inter-Verf",
    "wof:placetype":"venue"
},
  "geometry": {"coordinates":[4.617285,51.644512],"type":"Point"}
}