{
  "type": "Feature",
  "properties": {
    "addr:full":"Griftdk 9A Oosterhout Nymegen Gelderland 6679 AE",
    "addr:housenumber":"9a",
    "addr:postcode":"6679 ae",
    "addr:street":"Griftdk",
    "iso:country":"NL",
    "sg:address":"Griftdk 9A",
    "sg:city":"Oosterhout Nymegen",
    "sg:classifiers":[
        {
            "category":"Travel",
            "subcategory":"Hotels & Motels",
            "type":"Entertainment"
        }
    ],
    "sg:phone":"+31 24 348 1150",
    "sg:postcode":"6679 AE",
    "sg:province":"Gelderland",
    "wof:name":"Halve Weg, De",
    "wof:placetype":"venue"
},
  "geometry": {"coordinates":[5.839649,51.888618],"type":"Point"}
}