{
  "type": "Feature",
  "properties": {
    "addr:full":"Balboastr 18 Amsterdam Noord-Holland 1057 VW",
    "addr:housenumber":"18",
    "addr:postcode":"1057 vw",
    "addr:street":"Balboastr",
    "iso:country":"NL",
    "sg:address":"Balboastr 18",
    "sg:city":"Amsterdam",
    "sg:orig_category":"Hulpverlening Sociaal",
    "sg:phone":"+31 20 683 2767",
    "sg:postcode":"1057 VW",
    "sg:province":"Noord-Holland",
    "wof:name":"Amw Amsterdam Oud West",
    "wof:placetype":"venue"
},
  "geometry": {"coordinates":[4.855196,52.369404],"type":"Point"}
}