{
  "type": "Feature",
  "properties": {
    "addr:full":"Hendrik Hamerstraat 77 'S Gravendeel Zuid-Holland 3295 CG",
    "addr:housenumber":"77",
    "addr:postcode":"3295 cg",
    "addr:street":"Hendrik Hamerstraat;' S",
    "iso:country":"NL",
    "sg:address":"Hendrik Hamerstraat 77",
    "sg:city":"'S Gravendeel",
    "sg:orig_category":"Kappers",
    "sg:phone":"+31 78 673 3855",
    "sg:postcode":"3295 CG",
    "sg:province":"Zuid-Holland",
    "wof:name":"Haarmode Elly Buitendijk",
    "wof:placetype":"venue"
},
  "geometry": {"coordinates":[4.6145682335,51.7772903442],"type":"Point"}
}