{
  "type": "Feature",
  "properties": {
    "addr:full":"Muntpln 14 Nieuwegein Utrecht 3437 AN",
    "addr:housenumber":"14",
    "addr:postcode":"3437 an",
    "addr:street":"Muntpln",
    "iso:country":"NL",
    "sg:address":"Muntpln 14",
    "sg:city":"Nieuwegein",
    "sg:orig_category":"Postkantoren",
    "sg:phone":"+31 30 603 9433",
    "sg:postcode":"3437 AN",
    "sg:province":"Utrecht",
    "sg:website":"http://www.postkantoor.nl",
    "wof:name":"Postkantoor",
    "wof:placetype":"venue"
},
  "geometry": {"coordinates":[5.078093,52.041054],"type":"Point"}
}