{
  "type": "Feature",
  "properties": {
    "addr:full":"Botenmakersstr 43 Zaandam Noord-Holland 1506 TA",
    "addr:housenumber":"43",
    "addr:postcode":"1506 ta",
    "addr:street":"Botenmakersstr",
    "iso:country":"NL",
    "sg:address":"Botenmakersstr 43",
    "sg:city":"Zaandam",
    "sg:orig_category":"Verzekeringen - Verzekeringskantoren",
    "sg:phone":"+31 75 670 0500",
    "sg:postcode":"1506 TA",
    "sg:province":"Noord-Holland",
    "wof:name":"Jan Der Nederlanden",
    "wof:placetype":"venue"
},
  "geometry": {"coordinates":[4.8197,52.442001],"type":"Point"}
}