{
  "type": "Feature",
  "properties": {
    "addr:full":"Gemertsewg 24 Beek En Donk Noord-Brabant 5741 PE",
    "addr:housenumber":"24",
    "addr:postcode":"5741 pe",
    "addr:street":"Gemertsewg",
    "iso:country":"NL",
    "sg:address":"Gemertsewg 24",
    "sg:city":"Beek En Donk",
    "sg:orig_category":"Ongediertebestrijding En Ontsmetting",
    "sg:phone":"+31 492 462 859",
    "sg:postcode":"5741 PE",
    "sg:province":"Noord-Brabant",
    "wof:name":"Aaa Control",
    "wof:placetype":"venue"
},
  "geometry": {"coordinates":[5.655597,51.53616],"type":"Point"}
}