{
  "type": "Feature",
  "properties": {
    "addr:full":"Havenstr 40 Noordwykerhout South Holland 2211 EJ",
    "addr:housenumber":"40",
    "addr:postcode":"2211 ej",
    "addr:street":"Havenstr",
    "iso:country":"NL",
    "sg:address":"Havenstr 40",
    "sg:city":"Noordwykerhout",
    "sg:orig_category":"Webdesign Bureaus",
    "sg:phone":"+31 252 344 720",
    "sg:postcode":"2211 EJ",
    "sg:province":"South Holland",
    "sg:website":"http://www.tm-webdesign.nl",
    "wof:name":"Witteman & Weerdenburg",
    "wof:placetype":"venue"
},
  "geometry": {"coordinates":[4.4948577881,52.2617340088],"type":"Point"}
}