{
  "type": "Feature",
  "properties": {
    "addr:full":"Stationsplein 4 Amersfoort Utrecht 3818 LE",
    "addr:housenumber":"4",
    "addr:postcode":"3818 le",
    "addr:street":"Stationsplein",
    "iso:country":"NL",
    "sg:address":"Stationsplein 4",
    "sg:city":"Amersfoort",
    "sg:orig_category":"Chemische Producten Gh",
    "sg:phone":"+31 33 467 6885",
    "sg:postcode":"3818 LE",
    "sg:province":"Utrecht",
    "wof:name":"Methanor Vof",
    "wof:placetype":"venue"
},
  "geometry": {"coordinates":[5.386085,52.152325],"type":"Point"}
}