{
  "type": "Feature",
  "properties": {
    "addr:full":"Thorbeckelaan 112 Sliedrecht South Holland 3362 BV",
    "addr:housenumber":"112",
    "addr:postcode":"3362 bv",
    "addr:street":"Thorbeckelaan",
    "iso:country":"NL",
    "sg:address":"Thorbeckelaan 112",
    "sg:city":"Sliedrecht",
    "sg:classifiers":[
        {
            "category":"Education",
            "subcategory":"Preschool",
            "type":"Public Place"
        }
    ],
    "sg:phone":"+31 184 415 760",
    "sg:postcode":"3362 BV",
    "sg:province":"South Holland",
    "sg:tags":[
        "kleuteronderwijs",
        "basis-"
    ],
    "wof:name":"Peuterspeelzaal De Lapjeskat",
    "wof:placetype":"venue"
},
  "geometry": {"coordinates":[4.784439,51.82349],"type":"Point"}
}