{
  "type": "Feature",
  "properties": {
    "addr:full":"Malakkastraat 196 'S Gravenhage Zuid-Holland 2585 SW",
    "addr:housenumber":"196 ';2585",
    "addr:street":"Malakkastraat;Sw",
    "iso:country":"NL",
    "sg:address":"Malakkastraat 196",
    "sg:city":"'S Gravenhage",
    "sg:orig_category":"Glaszetten",
    "sg:phone":"+31 70 354 9965",
    "sg:postcode":"2585 SW",
    "sg:province":"Zuid-Holland",
    "wof:name":"Glashandel Brommersma",
    "wof:placetype":"venue"
},
  "geometry": {"coordinates":[4.297755,52.090015],"type":"Point"}
}