{
  "type": "Feature",
  "properties": {
    "iso:country":"NL",
    "sg:address":"Rochussenstraat 397",
    "sg:city":"Rotterdam",
    "sg:orig_category":"Werving And Selectie Van Tijdelijk Personeel And Uitzendkantoren",
    "sg:phone":"+31 10 425 9922",
    "sg:postcode":"3023 DK",
    "sg:province":"Zuid-Holland",
    "wof:name":"De Telecedent",
    "wof:placetype":"venue"
},
  "geometry": {"coordinates":[4.4513101578,51.9094734192],"type":"Point"}
}