{
  "type": "Feature",
  "properties": {
    "addr:full":"Mimosastr 1 Zwolle Overijssel 8013 SB",
    "addr:housenumber":"1",
    "addr:postcode":"8013 sb",
    "addr:street":"Mimosastr",
    "iso:country":"NL",
    "sg:address":"Mimosastr 1",
    "sg:city":"Zwolle",
    "sg:orig_category":"Verenigingen En Stichtingen",
    "sg:phone":"+31 38 422 8519",
    "sg:postcode":"8013 SB",
    "sg:province":"Overijssel",
    "sg:website":"http://www.doas.nl",
    "wof:name":"Oude Ambachtsschool",
    "wof:placetype":"venue"
},
  "geometry": {"coordinates":[6.108595,52.499489],"type":"Point"}
}