{
  "type": "Feature",
  "properties": {
    "addr:full":"Van Vredenburchweg 75 Rijswijk Zh South Holland 2282 SE",
    "addr:housenumber":"75",
    "addr:postcode":"2282 se",
    "addr:street":"Van Vredenburchweg",
    "iso:country":"NL",
    "sg:address":"Van Vredenburchweg 75",
    "sg:city":"Rijswijk Zh",
    "sg:classifiers":[
        {
            "category":"Education",
            "subcategory":"Preschool",
            "type":"Public Place"
        }
    ],
    "sg:phone":"+31 70 395 4050",
    "sg:postcode":"2282 SE",
    "sg:province":"South Holland",
    "sg:tags":[
        "kleuteronderwijs",
        "basis-"
    ],
    "wof:name":"Mariaschool",
    "wof:placetype":"venue"
},
  "geometry": {"coordinates":[4.328685,52.05262],"type":"Point"}
}