{
  "type": "Feature",
  "properties": {
    "iso:country":"NL",
    "sg:address":"Reitdiepskd 16-18",
    "sg:city":"Zoutkamp",
    "sg:orig_category":"Bloemisterijartikelen - Fabrieken En Groothandel",
    "sg:phone":"+31 595 401 301",
    "sg:postcode":"9974 PJ",
    "sg:province":"Groningen",
    "wof:name":"Brands Zoutkamp Bv, E J",
    "wof:placetype":"venue"
},
  "geometry": {"coordinates":[6.30772,53.336971],"type":"Point"}
}