{
  "type": "Feature",
  "properties": {
    "addr:full":"Kastelenstr 80 Amsterdam North Holland 1083 DE",
    "addr:housenumber":"80",
    "addr:postcode":"1083 de",
    "addr:street":"Kastelenstr",
    "iso:country":"NL",
    "sg:address":"Kastelenstr 80",
    "sg:city":"Amsterdam",
    "sg:orig_category":"Bejaarden - Verzorgingstehuizen",
    "sg:phone":"+31 20 661 1516",
    "sg:postcode":"1083 DE",
    "sg:province":"North Holland",
    "wof:name":"Beth Shalom",
    "wof:placetype":"venue"
},
  "geometry": {"coordinates":[4.881467,52.326271],"type":"Point"}
}