{
  "type": "Feature",
  "properties": {
    "iso:country":"NL",
    "sg:address":"Haddingestraat 31",
    "sg:city":"Groningen",
    "sg:orig_category":"Boekhouders",
    "sg:phone":"+31 50 314 2251",
    "sg:postcode":"9711 KC",
    "sg:province":"Groningen",
    "wof:name":"Profijt & Co Advies- En Administratiekantoor",
    "wof:placetype":"venue"
},
  "geometry": {"coordinates":[6.565637,53.215721],"type":"Point"}
}