{
  "type": "Feature",
  "properties": {
    "iso:country":"NL",
    "sg:address":"Papiermakerstraat 9",
    "sg:city":"Putten",
    "sg:orig_category":"Glaszetten",
    "sg:phone":"+31 341 351 535",
    "sg:postcode":"3881 BK",
    "sg:province":"Gelderland",
    "wof:name":"Vof Decorette Elanto",
    "wof:placetype":"venue"
},
  "geometry": {"coordinates":[5.60591,52.261204],"type":"Point"}
}