{
  "type": "Feature",
  "properties": {
    "addr:full":"Friesestraat 84 Coevorden Provincie Drenthe 7741 GX",
    "addr:housenumber":"84",
    "addr:postcode":"7741 gx",
    "addr:street":"Friesestraat;Provincie Drenthe",
    "iso:country":"NL",
    "sg:address":"Friesestraat 84",
    "sg:city":"Coevorden",
    "sg:orig_category":"Kledingzaken",
    "sg:phone":"+31 524 525 380",
    "sg:postcode":"7741 GX",
    "sg:province":"Provincie Drenthe",
    "wof:name":"Combi Sport",
    "wof:placetype":"venue"
},
  "geometry": {"coordinates":[6.737864,52.662807],"type":"Point"}
}