{
  "type": "Feature",
  "properties": {
    "addr:full":"Dorpsstraat 99 Bunschoten Spakenburg Utrecht 3751 EN",
    "addr:housenumber":"99",
    "addr:postcode":"3751 en",
    "addr:street":"Dorpsstraat",
    "iso:country":"NL",
    "sg:address":"Dorpsstraat 99",
    "sg:city":"Bunschoten Spakenburg",
    "sg:classifiers":[
        {
            "category":"Food & Beverages",
            "subcategory":"Fruits & Vegetables",
            "type":"Retail Goods"
        }
    ],
    "sg:phone":"+31 33 298 1110",
    "sg:postcode":"3751 EN",
    "sg:province":"Utrecht",
    "sg:tags":[
        "groenten"
    ],
    "wof:name":"Van Dasselaar Groenten-En Fruithandel",
    "wof:placetype":"venue"
},
  "geometry": {"coordinates":[5.3736,52.239166],"type":"Point"}
}