{
  "type": "Feature",
  "properties": {
    "addr:full":"Ommerwg 18 Hellendoorn Overijssel 7447 RE",
    "addr:housenumber":"18",
    "addr:postcode":"7447 re",
    "addr:street":"Ommerwg",
    "iso:country":"NL",
    "sg:address":"Ommerwg 18",
    "sg:city":"Hellendoorn",
    "sg:orig_category":"Adviesbureaus Bouwkunde",
    "sg:phone":"+31 548 654 123",
    "sg:postcode":"7447 RE",
    "sg:province":"Overijssel",
    "wof:name":"Ksk",
    "wof:placetype":"venue"
},
  "geometry": {"coordinates":[6.448687,52.393627],"type":"Point"}
}