{
  "type": "Feature",
  "properties": {
    "iso:country":"NL",
    "sg:address":"Koraalzwam 65",
    "sg:city":"Alphen Aan Den Ryn",
    "sg:orig_category":"Koeriersdiensten",
    "sg:phone":"+31 6 51254954",
    "sg:postcode":"2403 SR",
    "sg:province":"Zuid-Holland",
    "wof:name":"Kwikki Transport",
    "wof:placetype":"venue"
},
  "geometry": {"coordinates":[4.68254,52.151398],"type":"Point"}
}