{
  "type": "Feature",
  "properties": {
    "addr:full":"Vondelstr 106 Wormerveer North Holland 1521 ZT",
    "addr:housenumber":"106",
    "addr:postcode":"1521 zt",
    "iso:country":"NL",
    "sg:address":"Vondelstr 106",
    "sg:city":"Wormerveer",
    "sg:orig_category":"Behangers",
    "sg:phone":"+31 6 53976865",
    "sg:postcode":"1521 ZT",
    "sg:province":"North Holland",
    "wof:name":"Holsvoogd, J H",
    "wof:placetype":"venue"
},
  "geometry": {"coordinates":[4.785419,52.501431],"type":"Point"}
}