{
  "type": "Feature",
  "properties": {
    "addr:full":"Sijzenhof 1 Elsloo Lb Limburg 6181 KP",
    "addr:housenumber":"1",
    "addr:postcode":"lb;6181 kp",
    "addr:street":"Sijzenhof",
    "iso:country":"NL",
    "sg:address":"Sijzenhof 1",
    "sg:city":"Elsloo Lb",
    "sg:orig_category":"Schilderwerk",
    "sg:phone":"+31 46 437 5434",
    "sg:postcode":"6181 KP",
    "sg:province":"Limburg",
    "wof:name":"Schildersbedrijf Jacobs",
    "wof:placetype":"venue"
},
  "geometry": {"coordinates":[5.767516,50.952175],"type":"Point"}
}