{
  "type": "Feature",
  "properties": {
    "addr:full":"Wierdijk 44 Enkhuizen Noord-Holland 1600 AG",
    "addr:housenumber":"44",
    "addr:postcode":"1600",
    "addr:street":"Wierdijk",
    "iso:country":"NL",
    "sg:address":"Wierdijk 44",
    "sg:city":"Enkhuizen",
    "sg:orig_category":"Paramedische Behandelingen",
    "sg:phone":"+31 228 318 961",
    "sg:postcode":"1600 AG",
    "sg:province":"Noord-Holland",
    "wof:name":"S.R. De Korte Verloskundige",
    "wof:placetype":"venue"
},
  "geometry": {"coordinates":[5.29614,52.701118],"type":"Point"}
}