{
  "type": "Feature",
  "properties": {
    "iso:country":"NL",
    "sg:address":"Varsseldersewg 9",
    "sg:city":"Etten Gld",
    "sg:classifiers":[
        {
            "category":"Bus Charters",
            "type":"Transportation"
        }
    ],
    "sg:phone":"+31 315 323 585",
    "sg:postcode":"7075 DR",
    "sg:province":"Gelderland",
    "sg:tags":[
        "caravan"
    ],
    "wof:name":"Slootermeer",
    "wof:placetype":"venue"
},
  "geometry": {"coordinates":[6.35485,51.898441],"type":"Point"}
}