{
  "type": "Feature",
  "properties": {
    "addr:full":"De Milt 21 Geesteren Ov Overijssel 7678 CB",
    "addr:housenumber":"21",
    "addr:postcode":"7678 cb",
    "addr:street":"De Milt;Ov",
    "iso:country":"NL",
    "sg:address":"De Milt 21",
    "sg:city":"Geesteren Ov",
    "sg:orig_category":"Metaalwerken",
    "sg:phone":"+31 546 632 334",
    "sg:postcode":"7678 CB",
    "sg:province":"Overijssel",
    "wof:name":"H & O Zonwering",
    "wof:placetype":"venue"
},
  "geometry": {"coordinates":[6.727115,52.417515],"type":"Point"}
}