{
  "type": "Feature",
  "properties": {
    "iso:country":"NL",
    "sg:address":"Moezelhavenweg 9",
    "sg:city":"Amsterdam",
    "sg:orig_category":"Gespecialiseerde Bouw",
    "sg:phone":"+31 20 448 6633",
    "sg:postcode":"1043 AM",
    "sg:province":"Noord-Holland",
    "wof:name":"Amstelland Materieel Service Bv",
    "wof:placetype":"venue"
},
  "geometry": {"coordinates":[4.819839,52.393372],"type":"Point"}
}