{
  "type": "Feature",
  "properties": {
    "addr:full":"Eurowerft 15 Denekamp Overijssel 7591 DE",
    "addr:housenumber":"15",
    "addr:postcode":"7591 de",
    "addr:street":"Eurowerft",
    "iso:country":"NL",
    "sg:address":"Eurowerft 15",
    "sg:city":"Denekamp",
    "sg:orig_category":"Herenkleding",
    "sg:phone":"+31 541 680 096",
    "sg:postcode":"7591 DE",
    "sg:province":"Overijssel",
    "wof:name":"Broekenhuis, Het",
    "wof:placetype":"venue"
},
  "geometry": {"coordinates":[7.006313,52.375889],"type":"Point"}
}