{
  "type": "Feature",
  "properties": {
    "iso:country":"NL",
    "sg:address":"Wolvenweg 2",
    "sg:city":"Ruinen",
    "sg:orig_category":"Bloemen And Planten",
    "sg:phone":"+31 522 471 267",
    "sg:postcode":"7963 BG",
    "sg:province":"Drenthe",
    "wof:name":"Tuincentrum Wolverlei",
    "wof:placetype":"venue"
},
  "geometry": {"coordinates":[26.16386,43.018551],"type":"Point"}
}