{
  "type": "Feature",
  "properties": {
    "addr:full":"Zutphensestraat 6 Brummen Gelderland 6971 EM",
    "addr:housenumber":"6",
    "addr:postcode":"6971 em",
    "addr:street":"Zutphensestraat;Gelderland",
    "iso:country":"NL",
    "sg:address":"Zutphensestraat 6",
    "sg:city":"Brummen",
    "sg:orig_category":"Postkantoren",
    "sg:phone":"+31 575 561 414",
    "sg:postcode":"6971 EM",
    "sg:province":"Gelderland",
    "wof:name":"Postkantoor",
    "wof:placetype":"venue"
},
  "geometry": {"coordinates":[6.156782,52.088402],"type":"Point"}
}