{
  "type": "Feature",
  "properties": {
    "iso:country":"NL",
    "sg:address":"Zutphensestraat 6",
    "sg:city":"Brummen",
    "sg:orig_category":"Postkantoren",
    "sg:phone":"+31 575 561 414",
    "sg:postcode":"6971 EM",
    "sg:province":"Gelderland",
    "wof:name":"Postkantoor",
    "wof:placetype":"venue"
},
  "geometry": {"coordinates":[6.156782,52.088402],"type":"Point"}
}