{
  "type": "Feature",
  "properties": {
    "addr:full":"Emmerhoutstr 147 Emmen Drenthe 7814 XX",
    "addr:housenumber":"147",
    "addr:postcode":"7814 xx",
    "iso:country":"NL",
    "sg:address":"Emmerhoutstr 147",
    "sg:city":"Emmen",
    "sg:orig_category":"Kunststoffen- Verwerkende Industrie",
    "sg:phone":"+31 591 621 401",
    "sg:postcode":"7814 XX",
    "sg:province":"Drenthe",
    "wof:name":"Sirex",
    "wof:placetype":"venue"
},
  "geometry": {"coordinates":[6.934965,52.808758],"type":"Point"}
}