{
  "type": "Feature",
  "properties": {
    "addr:full":"Papenpad 38 Wageningen Gelderland 6705 CP",
    "addr:housenumber":"38",
    "addr:postcode":"6705 cp",
    "addr:street":"Papenpad;Gelderland",
    "iso:country":"NL",
    "sg:address":"Papenpad 38",
    "sg:city":"Wageningen",
    "sg:orig_category":"Schoonheidsinstituten",
    "sg:phone":"+31 317 418 303",
    "sg:postcode":"6705 CP",
    "sg:province":"Gelderland",
    "wof:name":"Janssen-Nijmeijer, R",
    "wof:placetype":"venue"
},
  "geometry": {"coordinates":[5.686922,51.992714],"type":"Point"}
}