{
  "type": "Feature",
  "properties": {
    "addr:full":"Schouwstraat 6 Rijsenhout Noord-Holland 1435 KN",
    "addr:housenumber":"6",
    "addr:postcode":"1435 kn",
    "addr:street":"Schouwstraat",
    "iso:country":"NL",
    "sg:address":"Schouwstraat 6",
    "sg:city":"Rijsenhout",
    "sg:orig_category":"Banken And Kredietinstellingen",
    "sg:phone":"+31 297 327 187",
    "sg:postcode":"1435 KN",
    "sg:province":"Noord-Holland",
    "wof:name":"Rabobank",
    "wof:placetype":"venue"
},
  "geometry": {"coordinates":[4.716474,52.258114],"type":"Point"}
}