{
  "type": "Feature",
  "properties": {
    "addr:full":"V Bemmelenstr 16 Leiden Zuid-Holland 2313 RB",
    "addr:housenumber":"16",
    "addr:postcode":"2313 rb",
    "iso:country":"NL",
    "sg:address":"V Bemmelenstr 16",
    "sg:city":"Leiden",
    "sg:orig_category":"Webdesign Bureaus",
    "sg:phone":"+31 71 514 5852",
    "sg:postcode":"2313 RB",
    "sg:province":"Zuid-Holland",
    "wof:name":"Toxopeus",
    "wof:placetype":"venue"
},
  "geometry": {"coordinates":[4.4946298599,52.1545715332],"type":"Point"}
}