{
  "type": "Feature",
  "properties": {
    "iso:country":"NL",
    "sg:address":"Gramserweg 78",
    "sg:city":"Austerlitz",
    "sg:orig_category":"Medische Installaties En Instrumenten",
    "sg:phone":"+31 343 554 935",
    "sg:postcode":"3711 AZ",
    "sg:province":"Utrecht",
    "wof:name":"Mediall International Bv",
    "wof:placetype":"venue"
},
  "geometry": {"coordinates":[5.31595,52.081673],"type":"Point"}
}