{
  "type": "Feature",
  "properties": {
    "iso:country":"NL",
    "sg:address":"Julianalaan 13",
    "sg:city":"Vlissingen",
    "sg:orig_category":"Kinderopvang Behalve Thuis",
    "sg:phone":"+31 118 416 506",
    "sg:postcode":"4382 AT",
    "sg:province":"Zeeland",
    "wof:name":"Peuterspeelzaal De Ukkies",
    "wof:placetype":"venue"
},
  "geometry": {"coordinates":[3.563014,51.450642],"type":"Point"}
}