{
  "type": "Feature",
  "properties": {
    "iso:country":"NL",
    "sg:address":"Broedertrouw 32",
    "sg:city":"St Jacobiparochie",
    "sg:orig_category":"Schilders",
    "sg:phone":"+31 518 491 202",
    "sg:postcode":"9079 KX",
    "sg:province":"Friesland",
    "wof:name":"Jager & Triemstra, De",
    "wof:placetype":"venue"
},
  "geometry": {"coordinates":[5.610083,53.271423],"type":"Point"}
}