{
  "type": "Feature",
  "properties": {
    "addr:full":"Broedertrouw 32 St Jacobiparochie Friesland 9079 KX",
    "addr:housenumber":"32",
    "addr:postcode":"9079 kx",
    "addr:street":"Broedertrouw;St Jacobiparochie Friesland",
    "iso:country":"NL",
    "sg:address":"Broedertrouw 32",
    "sg:city":"St Jacobiparochie",
    "sg:orig_category":"Schilders",
    "sg:phone":"+31 518 491 202",
    "sg:postcode":"9079 KX",
    "sg:province":"Friesland",
    "wof:name":"Jager & Triemstra, De",
    "wof:placetype":"venue"
},
  "geometry": {"coordinates":[5.610083,53.271423],"type":"Point"}
}