{
  "type": "Feature",
  "properties": {
    "addr:full":"Schubertdreef 59 Barendrecht South Holland 2992 EV",
    "addr:housenumber":"59",
    "addr:postcode":"2992 ev",
    "addr:street":"Schubertdreef",
    "iso:country":"NL",
    "sg:address":"Schubertdreef 59",
    "sg:city":"Barendrecht",
    "sg:orig_category":"Logopedisten",
    "sg:phone":"+31 180 619 006",
    "sg:postcode":"2992 EV",
    "sg:province":"South Holland",
    "wof:name":"Griend, A I E Van De",
    "wof:placetype":"venue"
},
  "geometry": {"coordinates":[4.521795,51.853016],"type":"Point"}
}