{
  "type": "Feature",
  "properties": {
    "addr:full":"Otterswyk 13 Dedemsvaart Overijssel 7701 PC",
    "addr:housenumber":"13",
    "addr:postcode":"7701 pc",
    "addr:street":"Otterswyk",
    "iso:country":"NL",
    "sg:address":"Otterswyk 13",
    "sg:city":"Dedemsvaart",
    "sg:orig_category":"Artiesten/Gezelschappen",
    "sg:phone":"+31 523 638 435",
    "sg:postcode":"7701 PC",
    "sg:province":"Overijssel",
    "wof:name":"Jeugd Orkest Ned",
    "wof:placetype":"venue"
},
  "geometry": {"coordinates":[6.457315,52.606258],"type":"Point"}
}