{
  "type": "Feature",
  "properties": {
    "addr:full":"Rechtstraat 52 Maastricht Limburg 6221 EK",
    "addr:housenumber":"52",
    "addr:postcode":"6221 ek",
    "addr:street":"Rechtstraat",
    "iso:country":"NL",
    "sg:address":"Rechtstraat 52",
    "sg:city":"Maastricht",
    "sg:orig_category":"Damesmodezaken",
    "sg:phone":"+31 43 321 8925",
    "sg:postcode":"6221 EK",
    "sg:province":"Limburg",
    "wof:name":"Modehuis Bremen",
    "wof:placetype":"venue"
},
  "geometry": {"coordinates":[5.69816,50.84885],"type":"Point"}
}