{
  "type": "Feature",
  "properties": {
    "iso:country":"NL",
    "sg:address":"Markerkant 10 Nr 120",
    "sg:city":"Almere",
    "sg:orig_category":"Hek- En Rasterwerken",
    "sg:phone":"+31 36 533 3641",
    "sg:postcode":"1316 AL",
    "sg:province":"Flevoland",
    "wof:name":"Grootendorst",
    "wof:placetype":"venue"
},
  "geometry": {"coordinates":[5.22223,52.376598],"type":"Point"}
}