{
  "type": "Feature",
  "properties": {
    "addr:full":"Westzyde 26 Zaandam North Holland 1506 EE",
    "addr:housenumber":"26",
    "addr:postcode":"1506 ee",
    "addr:street":"Westzyde",
    "iso:country":"NL",
    "sg:address":"Westzyde 26",
    "sg:city":"Zaandam",
    "sg:orig_category":"Verf En Lak",
    "sg:phone":"+31 75 616 3189",
    "sg:postcode":"1506 EE",
    "sg:province":"North Holland",
    "wof:name":"Groen Bv, D",
    "wof:placetype":"venue"
},
  "geometry": {"coordinates":[4.808925,52.44944],"type":"Point"}
}