{
  "type": "Feature",
  "properties": {
    "iso:country":"NL",
    "sg:address":"Lijtweg 12",
    "sg:city":"Leidschendam",
    "sg:orig_category":"Loodgieterswerk, Verwarming And Sanitaire Installaties",
    "sg:phone":"+31 70 327 2509",
    "sg:postcode":"2263 KC",
    "sg:province":"Zuid-Holland",
    "wof:name":"A.F. Van Houten Beheer Leidschendam Bv",
    "wof:placetype":"venue"
},
  "geometry": {"coordinates":[4.416262,52.101025],"type":"Point"}
}