{
  "type": "Feature",
  "properties": {
    "addr:full":"Garst 7 Winschoten Groningen 9673 AA",
    "addr:housenumber":"7",
    "addr:postcode":"9673 aa",
    "addr:street":"Garst",
    "iso:country":"NL",
    "sg:address":"Garst 7",
    "sg:city":"Winschoten",
    "sg:orig_category":"Arbeidsbemiddeling",
    "sg:phone":"+31 597 456 444",
    "sg:postcode":"9673 AA",
    "sg:province":"Groningen",
    "sg:website":"http://www.serin.nl",
    "wof:name":"Serin Bv",
    "wof:placetype":"venue"
},
  "geometry": {"coordinates":[7.029106,53.139225],"type":"Point"}
}