{
  "type": "Feature",
  "properties": {
    "addr:full":"Posthoornwg 6A Lemelerveld Overijssel 8152 AZ",
    "addr:housenumber":"6a",
    "addr:postcode":"8152 az",
    "addr:street":"Posthoornwg",
    "iso:country":"NL",
    "sg:address":"Posthoornwg 6A",
    "sg:city":"Lemelerveld",
    "sg:orig_category":"Fietsen En Bromfietsen",
    "sg:phone":"+31 572 372 640",
    "sg:postcode":"8152 AZ",
    "sg:province":"Overijssel",
    "sg:website":"http://www.josdijkman.nl",
    "wof:name":"Dijkman, Jos",
    "wof:placetype":"venue"
},
  "geometry": {"coordinates":[6.334516,52.443707],"type":"Point"}
}