{
  "type": "Feature",
  "properties": {
    "addr:full":"Peeleik 7 Helmond Noord-Brabant 5704 AP",
    "addr:housenumber":"7",
    "addr:postcode":"5704 ap",
    "addr:street":"Peeleik",
    "iso:country":"NL",
    "sg:address":"Peeleik 7",
    "sg:city":"Helmond",
    "sg:orig_category":"Verenigingsgebouwen",
    "sg:phone":"+31 492 511 735",
    "sg:postcode":"5704 AP",
    "sg:province":"Noord-Brabant",
    "wof:name":"Loop, De",
    "wof:placetype":"venue"
},
  "geometry": {"coordinates":[5.701896,51.459747],"type":"Point"}
}