{
  "type": "Feature",
  "properties": {
    "addr:full":"Kromstr 1B Veldhoven North Brabant 5504 BA",
    "addr:housenumber":"1b",
    "addr:postcode":"5504 ba",
    "addr:street":"Kromstr",
    "iso:country":"NL",
    "sg:address":"Kromstr 1B",
    "sg:city":"Veldhoven",
    "sg:orig_category":"Kappers",
    "sg:phone":"+31 40 254 5329",
    "sg:postcode":"5504 BA",
    "sg:province":"North Brabant",
    "wof:name":"Ren\u00e9",
    "wof:placetype":"venue"
},
  "geometry": {"coordinates":[5.396516,51.403782],"type":"Point"}
}