{
  "type": "Feature",
  "properties": {
    "addr:full":"Madewg 1 Monster Zuid-Holland 2681 PJ",
    "addr:housenumber":"1",
    "addr:postcode":"2681 pj",
    "addr:street":"Madewg",
    "iso:country":"NL",
    "sg:address":"Madewg 1",
    "sg:city":"Monster",
    "sg:orig_category":"Bloemen En Planten",
    "sg:phone":"+31 174 247 713",
    "sg:postcode":"2681 PJ",
    "sg:province":"Zuid-Holland",
    "wof:name":"Flower-Art",
    "wof:placetype":"venue"
},
  "geometry": {"coordinates":[-84.369049,40.363762],"type":"Point"}
}