{
  "type": "Feature",
  "properties": {
    "iso:country":"NL",
    "sg:address":"Banjopad 8",
    "sg:city":"Duiven",
    "sg:orig_category":"Afslankinstituten",
    "sg:phone":"+31 316 268 294",
    "sg:postcode":"6922 KE",
    "sg:province":"Gelderland",
    "sg:website":"http://www.yourpersonaltrainer.nl",
    "wof:name":"Your Personal Trainer",
    "wof:placetype":"venue"
},
  "geometry": {"coordinates":[5.996977,51.944248],"type":"Point"}
}