{
  "type": "Feature",
  "properties": {
    "iso:country":"NL",
    "sg:address":"Dakdekkerstraat 24",
    "sg:city":"Venray",
    "sg:orig_category":"Bouwnijverheidsmachines Gh",
    "sg:phone":"+31 478 582 646",
    "sg:postcode":"5801 TK",
    "sg:province":"Limburg",
    "wof:name":"M.W. Peeters",
    "wof:placetype":"venue"
},
  "geometry": {"coordinates":[5.963995,51.520412],"type":"Point"}
}