{
  "type": "Feature",
  "properties": {
    "iso:country":"NL",
    "sg:address":"V Ostadestr 40",
    "sg:city":"Deventer",
    "sg:orig_category":"Verenigingen En Stichtingen",
    "sg:phone":"+31 570 611 604",
    "sg:postcode":"7412 RT",
    "sg:province":"Overijssel",
    "wof:name":"Vriendschap Hondensportver, De",
    "wof:placetype":"venue"
},
  "geometry": {"coordinates":[6.159899,52.251034],"type":"Point"}
}