{
  "type": "Feature",
  "properties": {
    "iso:country":"NL",
    "sg:address":"Twickelerlaan 13",
    "sg:city":"Ambt Delden",
    "sg:orig_category":"Bloemen And Planten",
    "sg:phone":"+31 74 376 4123",
    "sg:postcode":"7495 VG",
    "sg:province":"Overijssel",
    "wof:name":"Vof De Border",
    "wof:placetype":"venue"
},
  "geometry": {"coordinates":[6.708566,52.275452],"type":"Point"}
}