{
  "type": "Feature",
  "properties": {
    "addr:full":"Westfrankelandsestraat 106-110 Schiedam Zuid-Holland 3117 AW",
    "addr:housenumber":"106-110",
    "addr:postcode":"3117 aw",
    "addr:street":"Westfrankelandsestraat",
    "iso:country":"NL",
    "sg:address":"Westfrankelandsestraat 106-110",
    "sg:city":"Schiedam",
    "sg:orig_category":"Bloemen And Planten",
    "sg:phone":"+31 10 426 2767",
    "sg:postcode":"3117 AW",
    "sg:province":"Zuid-Holland",
    "wof:name":"Boko Flower Discount Bv",
    "wof:placetype":"venue"
},
  "geometry": {"coordinates":[4.388927,51.913788],"type":"Point"}
}