{
  "type": "Feature",
  "properties": {
    "addr:full":"Molenstr 94 Nijmegen Gelderland 6511 HJ",
    "addr:housenumber":"94",
    "addr:postcode":"6511 hj",
    "addr:street":"Molenstr;Gelderland",
    "iso:country":"NL",
    "sg:address":"Molenstr 94",
    "sg:city":"Nijmegen",
    "sg:orig_category":"Dameskleding",
    "sg:phone":"+31 24 323 6361",
    "sg:postcode":"6511 HJ",
    "sg:province":"Gelderland",
    "wof:name":"Eve",
    "wof:placetype":"venue"
},
  "geometry": {"coordinates":[5.862054,51.844322],"type":"Point"}
}