{
  "type": "Feature",
  "properties": {
    "addr:full":"Galileistr 62 S Gravenhage Zuid-Holland 2561 TH",
    "addr:housenumber":"62;gravenhage;2561",
    "addr:postcode":"th",
    "addr:street":"Galileistr;S",
    "iso:country":"NL",
    "sg:address":"Galileistr 62",
    "sg:city":"S Gravenhage",
    "sg:orig_category":"Meubelstoffering",
    "sg:phone":"+31 70 360 6236",
    "sg:postcode":"2561 TH",
    "sg:province":"Zuid-Holland",
    "wof:name":"Etoffe",
    "wof:placetype":"venue"
},
  "geometry": {"coordinates":[4.27581,52.074532],"type":"Point"}
}