{
  "type": "Feature",
  "properties": {
    "addr:full":"Roggeveenstraat 139 Amsterdam Noord-Holland 1013 PS",
    "addr:housenumber":"139",
    "addr:postcode":"1013 ps",
    "addr:street":"Roggeveenstraat",
    "iso:country":"NL",
    "sg:address":"Roggeveenstraat 139",
    "sg:city":"Amsterdam",
    "sg:orig_category":"Zuivelproducten And Spijsoli?n Gh",
    "sg:phone":"+31 20 770 1953",
    "sg:postcode":"1013 PS",
    "sg:province":"Noord-Holland",
    "wof:name":"Zuivelservice Gort",
    "wof:placetype":"venue"
},
  "geometry": {"coordinates":[4.886456,52.389736],"type":"Point"}
}