{
  "type": "Feature",
  "properties": {
    "addr:full":"Kleinstr 3 Berg En Terblyt Limburg 6325 CV",
    "addr:housenumber":"3",
    "addr:postcode":"6325 cv",
    "addr:street":"Kleinstr;Limburg",
    "iso:country":"NL",
    "sg:address":"Kleinstr 3",
    "sg:city":"Berg En Terblyt",
    "sg:orig_category":"Fotoreportages",
    "sg:phone":"+31 43 362 5088",
    "sg:postcode":"6325 CV",
    "sg:province":"Limburg",
    "wof:name":"Franssen, Richard",
    "wof:placetype":"venue"
},
  "geometry": {"coordinates":[5.776337,50.860867],"type":"Point"}
}