{
  "type": "Feature",
  "properties": {
    "addr:full":"Churchilllaan 112 Amsterdam Noord-Holland 1078 EM",
    "addr:housenumber":"112",
    "addr:postcode":"1078 em",
    "addr:street":"Churchilllaan",
    "iso:country":"NL",
    "sg:address":"Churchilllaan 112",
    "sg:city":"Amsterdam",
    "sg:orig_category":"Paramedische Behandelingen",
    "sg:phone":"+31 20 679 1704",
    "sg:postcode":"1078 EM",
    "sg:province":"Noord-Holland",
    "wof:name":"Conny De By - Tiny Pinkse - Corrie De Beer",
    "wof:placetype":"venue"
},
  "geometry": {"coordinates":[4.896611,52.347172],"type":"Point"}
}