{
  "type": "Feature",
  "properties": {
    "addr:full":"Dragonder 3 Valkenswaard North Brabant 5554 GM",
    "addr:housenumber":"3",
    "addr:postcode":"5554 gm",
    "addr:street":"Dragonder",
    "iso:country":"NL",
    "sg:address":"Dragonder 3",
    "sg:city":"Valkenswaard",
    "sg:orig_category":"Verzekeringen - Verzekeringskantoren",
    "sg:phone":"+31 40 207 3100",
    "sg:postcode":"5554 GM",
    "sg:province":"North Brabant",
    "sg:website":"http://www.dfd.nl",
    "wof:name":"Dfd",
    "wof:placetype":"venue"
},
  "geometry": {"coordinates":[5.464269,51.34008],"type":"Point"}
}