{
  "type": "Feature",
  "properties": {
    "addr:full":"Spuistr 51 Amsterdam North Holland 1012 ST",
    "addr:housenumber":"51",
    "addr:postcode":"1012 st",
    "addr:street":"Spuistr",
    "iso:country":"NL",
    "sg:address":"Spuistr 51",
    "sg:city":"Amsterdam",
    "sg:orig_category":"Koffie- En Theehuizen",
    "sg:phone":"+31 20 622 6241",
    "sg:postcode":"1012 ST",
    "sg:province":"North Holland",
    "wof:name":"Chocolata",
    "wof:placetype":"venue"
},
  "geometry": {"coordinates":[4.892526,52.376034],"type":"Point"}
}