{
  "type": "Feature",
  "properties": {
    "iso:country":"NL",
    "sg:address":"Mahatma Gandhistr 46",
    "sg:city":"Rotterdam",
    "sg:orig_category":"Projectontwikkeling",
    "sg:phone":"+31 10 202 3031",
    "sg:postcode":"3066 VA",
    "sg:province":"Zuid-Holland",
    "wof:name":"Overmans",
    "wof:placetype":"venue"
},
  "geometry": {"coordinates":[4.557389,51.931683],"type":"Point"}
}