{
  "type": "Feature",
  "properties": {
    "addr:full":"Nwe Dukenburgsew 15 Nijmegen Gelderland 6534 AD",
    "addr:housenumber":"15",
    "addr:postcode":"6534 ad",
    "addr:street":"Gelderland",
    "iso:country":"NL",
    "sg:address":"Nwe Dukenburgsew 15",
    "sg:city":"Nijmegen",
    "sg:orig_category":"Verenigingen En Stichtingen",
    "sg:phone":"+31 24 359 0654",
    "sg:postcode":"6534 AD",
    "sg:province":"Gelderland",
    "sg:website":"http://www.arcuris.nl",
    "wof:name":"Arcuris, Sticht",
    "wof:placetype":"venue"
},
  "geometry": {"coordinates":[5.820518,51.821194],"type":"Point"}
}