{
  "type": "Feature",
  "properties": {
    "iso:country":"NL",
    "sg:address":"Zwolse Binnenwg 5",
    "sg:city":"Apeldoorn",
    "sg:orig_category":"Zonweringen",
    "sg:phone":"+31 55 521 1646",
    "sg:postcode":"7315 CA",
    "sg:province":"Gelderland",
    "sg:website":"http://www.dekazon.nl",
    "wof:name":"Dekazon",
    "wof:placetype":"venue"
},
  "geometry": {"coordinates":[5.955881,52.225227],"type":"Point"}
}