{
  "type": "Feature",
  "properties": {
    "addr:full":"Hoofdwg 106 Lynden North Holland 1175 LC",
    "addr:housenumber":"106",
    "addr:postcode":"1175 lc",
    "addr:street":"Lynden North",
    "iso:country":"NL",
    "sg:address":"Hoofdwg 106",
    "sg:city":"Lynden",
    "sg:orig_category":"Loodgieters",
    "sg:phone":"+31 6 52052803",
    "sg:postcode":"1175 LC",
    "sg:province":"North Holland",
    "wof:name":"Modelfino",
    "wof:placetype":"venue"
},
  "geometry": {"coordinates":[4.754176,52.347912],"type":"Point"}
}