{
  "type": "Feature",
  "properties": {
    "addr:full":"Fransenstr 17-19 Vlaardingen South Holland 3131 CC",
    "addr:housenumber":"17-19",
    "addr:postcode":"3131 cc",
    "iso:country":"NL",
    "sg:address":"Fransenstr 17-19",
    "sg:city":"Vlaardingen",
    "sg:orig_category":"Schoenen",
    "sg:phone":"+31 10 434 3938",
    "sg:postcode":"3131 CC",
    "sg:province":"South Holland",
    "wof:name":"Kempers Wo&Man Shoes",
    "wof:placetype":"venue"
},
  "geometry": {"coordinates":[4.341035,51.909073],"type":"Point"}
}