{
  "type": "Feature",
  "properties": {
    "addr:full":"Mr W M O V Veenwg 38B Burgum Georgia 9251 GA",
    "addr:housenumber":"38b",
    "addr:postcode":"9251 ga",
    "addr:street":"W;Veenwg;Georgia",
    "iso:country":"NL",
    "sg:address":"Mr W M O V Veenwg 38B",
    "sg:city":"Burgum",
    "sg:orig_category":"Onderhoudswerken",
    "sg:phone":"+31 511 480 000",
    "sg:postcode":"9251 GA",
    "sg:province":"Georgia",
    "sg:website":"http://www.aanneembedrijf.nl",
    "wof:name":"Aanneembedrijf Corporateholding Friesland",
    "wof:placetype":"venue"
},
  "geometry": {"coordinates":[-83.222931,32.678131],"type":"Point"}
}