{
  "type": "Feature",
  "properties": {
    "iso:country":"NL",
    "sg:address":"Raadhuisstraat 19",
    "sg:city":"Dirkshorn",
    "sg:classifiers":[
        {
            "category":"Retail",
            "subcategory":"Photofinishing",
            "type":"Services"
        }
    ],
    "sg:phone":"+31 224 551 273",
    "sg:postcode":"1746 BE",
    "sg:province":"Noord-Holland",
    "sg:tags":[
        "foto",
        "film"
    ],
    "wof:name":"Kant-Koster Bv",
    "wof:placetype":"venue"
},
  "geometry": {"coordinates":[4.776802,52.749901],"type":"Point"}
}