{
  "type": "Feature",
  "properties": {
    "iso:country":"NL",
    "sg:address":"Veldwg 20",
    "sg:city":"Almkerk",
    "sg:orig_category":"Adviesbureaus Bedrijfsorganisatie",
    "sg:phone":"+31 183 409 040",
    "sg:postcode":"4286 EK",
    "sg:province":"Noord-Brabant",
    "wof:name":"Orgaflow Bv",
    "wof:placetype":"venue"
},
  "geometry": {"coordinates":[4.944665,51.790535],"type":"Point"}
}