{
  "type": "Feature",
  "properties": {
    "addr:full":"Past Moormanstr 80 Maastricht Limburg 6219 AX",
    "addr:housenumber":"80",
    "addr:postcode":"6219 ax",
    "iso:country":"NL",
    "sg:address":"Past Moormanstr 80",
    "sg:city":"Maastricht",
    "sg:orig_category":"Verenigingen En Stichtingen",
    "sg:phone":"+31 43 321 4896",
    "sg:postcode":"6219 AX",
    "sg:province":"Limburg",
    "wof:name":"Alphonsus, Sticht",
    "wof:placetype":"venue"
},
  "geometry": {"coordinates":[5.689654,50.863121],"type":"Point"}
}