{
  "type": "Feature",
  "properties": {
    "addr:full":"Hoofdweg 117 Zegveld Utrecht 3474 JC",
    "addr:housenumber":"117",
    "addr:postcode":"3474 jc",
    "addr:street":"Hoofdweg",
    "iso:country":"NL",
    "sg:address":"Hoofdweg 117",
    "sg:city":"Zegveld",
    "sg:classifiers":[
        {
            "category":"Shopping",
            "subcategory":"Gifts & Souvenirs",
            "type":"Retail Goods"
        }
    ],
    "sg:phone":"+31 348 691 790",
    "sg:postcode":"3474 JC",
    "sg:province":"Utrecht",
    "sg:tags":[
        "geschenken"
    ],
    "wof:name":"Lovely Presents",
    "wof:placetype":"venue"
},
  "geometry": {"coordinates":[4.84328,52.110622],"type":"Point"}
}