{
  "type": "Feature",
  "properties": {
    "addr:full":"Willem Fenengastraat 6 Amsterdam Noord-Holland 1096 BN",
    "addr:housenumber":"6",
    "addr:postcode":"1096 bn",
    "addr:street":"Willem Fenengastraat",
    "iso:country":"NL",
    "sg:address":"Willem Fenengastraat 6",
    "sg:city":"Amsterdam",
    "sg:orig_category":"Verhuur Bouwmachines",
    "sg:phone":"+31 20 693 0841",
    "sg:postcode":"1096 BN",
    "sg:province":"Noord-Holland",
    "wof:name":"Boudam Bouwmachines Bv",
    "wof:placetype":"venue"
},
  "geometry": {"coordinates":[4.918497,52.334625],"type":"Point"}
}