{
  "type": "Feature",
  "properties": {
    "iso:country":"NL",
    "sg:address":"Hadewychlaan 19",
    "sg:city":"Leiden",
    "sg:orig_category":"Onderhoud And Reparatie Kantoorapparatuur",
    "sg:phone":"+31 71 513 4041",
    "sg:postcode":"2331 BC",
    "sg:province":"Zuid-Holland",
    "wof:name":"V-Zes Software",
    "wof:placetype":"venue"
},
  "geometry": {"coordinates":[4.446841,52.155437],"type":"Point"}
}