{
  "type": "Feature",
  "properties": {
    "iso:country":"NL",
    "sg:address":"Rooseveltlaan 23",
    "sg:city":"Harderwijk",
    "sg:orig_category":"Verzekeringen",
    "sg:phone":"+31 341 413 586",
    "sg:postcode":"3844 AH",
    "sg:province":"Gelderland",
    "wof:name":"Advies- En Bemiddelingsbureau Zegers Bv",
    "wof:placetype":"venue"
},
  "geometry": {"coordinates":[5.618264,52.331856],"type":"Point"}
}