{
  "type": "Feature",
  "properties": {
    "addr:full":"Rooseveltlaan 23 Harderwijk Gelderland 3844 AH",
    "addr:housenumber":"23",
    "addr:postcode":"3844 ah",
    "addr:street":"Rooseveltlaan;Gelderland",
    "iso:country":"NL",
    "sg:address":"Rooseveltlaan 23",
    "sg:city":"Harderwijk",
    "sg:orig_category":"Verzekeringen",
    "sg:phone":"+31 341 413 586",
    "sg:postcode":"3844 AH",
    "sg:province":"Gelderland",
    "wof:name":"Advies- En Bemiddelingsbureau Zegers Bv",
    "wof:placetype":"venue"
},
  "geometry": {"coordinates":[5.618264,52.331856],"type":"Point"}
}