{
  "type": "Feature",
  "properties": {
    "iso:country":"NL",
    "sg:address":"Burg Hogguerstr 1183B",
    "sg:city":"Amsterdam",
    "sg:orig_category":"Verenigingen En Stichtingen",
    "sg:phone":"+31 20 614 4105",
    "sg:postcode":"1064 EK",
    "sg:province":"North Holland",
    "sg:website":"http://www.vriendendiensten.nl",
    "wof:name":"Amsterdamse Vriendendiensten, Sticht",
    "wof:placetype":"venue"
},
  "geometry": {"coordinates":[4.828161,52.373779],"type":"Point"}
}