{
  "type": "Feature",
  "properties": {
    "addr:full":"Kalkoven 4 Leek Groningen 9351 NP",
    "addr:housenumber":"4",
    "addr:postcode":"9351 np",
    "addr:street":"Kalkoven",
    "iso:country":"NL",
    "sg:address":"Kalkoven 4",
    "sg:city":"Leek",
    "sg:orig_category":"Plafonds",
    "sg:phone":"+31 594 517 707",
    "sg:postcode":"9351 NP",
    "sg:province":"Groningen",
    "wof:name":"Nivam Bv",
    "wof:placetype":"venue"
},
  "geometry": {"coordinates":[6.36802,53.153759],"type":"Point"}
}