{
  "type": "Feature",
  "properties": {
    "addr:full":"Ludensweg 59 Winschoten Groningen 9675 AN",
    "addr:housenumber":"59",
    "addr:postcode":"9675 an",
    "addr:street":"Ludensweg",
    "iso:country":"NL",
    "sg:address":"Ludensweg 59",
    "sg:city":"Winschoten",
    "sg:orig_category":"Goederenvervoer Over De Weg",
    "sg:phone":"+31 597 421 261",
    "sg:postcode":"9675 AN",
    "sg:province":"Groningen",
    "wof:name":"R. Jager",
    "wof:placetype":"venue"
},
  "geometry": {"coordinates":[7.037524,53.149815],"type":"Point"}
}