{
  "type": "Feature",
  "properties": {
    "iso:country":"NL",
    "sg:address":"Haarlemmerstr 124B",
    "sg:city":"Amsterdam",
    "sg:orig_category":"Webdesign Bureaus",
    "sg:phone":"+31 20 620 7647",
    "sg:postcode":"1013 EX",
    "sg:province":"North Holland",
    "sg:website":"http://www.davdigital.com",
    "wof:name":"Dav Studio",
    "wof:placetype":"venue"
},
  "geometry": {"coordinates":[4.8903961182,52.381061554],"type":"Point"}
}