{
  "type": "Feature",
  "properties": {
    "addr:full":"Linschotenstr 57A Haarlem Carabobo 2012 VE",
    "addr:housenumber":"57a",
    "addr:postcode":"2012",
    "addr:street":"Linschotenstr;Carabobo;Ve",
    "iso:country":"NL",
    "sg:address":"Linschotenstr 57A",
    "sg:city":"Haarlem",
    "sg:orig_category":"Kinderopvang",
    "sg:phone":"+31 23 542 4249",
    "sg:postcode":"2012 VE",
    "sg:province":"Carabobo",
    "wof:name":"Bengels",
    "wof:placetype":"venue"
},
  "geometry": {"coordinates":[-67.642662,9.95175],"type":"Point"}
}