{
  "type": "Feature",
  "properties": {
    "addr:full":"Hornweg 242 Aalsmeer Noord-Holland 1432 GT",
    "addr:housenumber":"242",
    "addr:postcode":"1432 gt",
    "addr:street":"Hornweg",
    "iso:country":"NL",
    "sg:address":"Hornweg 242",
    "sg:city":"Aalsmeer",
    "sg:orig_category":"Bloemen And Planten Gh",
    "sg:phone":"+31 297 388 888",
    "sg:postcode":"1432 GT",
    "sg:province":"Noord-Holland",
    "wof:name":"Las Palmas International Trade Bv",
    "wof:placetype":"venue"
},
  "geometry": {"coordinates":[4.801108,52.273045],"type":"Point"}
}