{
  "type": "Feature",
  "properties": {
    "addr:full":"Stoutenburgstraat 41 Breda Noord-Brabant 4834 LN",
    "addr:housenumber":"41",
    "addr:postcode":"4834 ln",
    "addr:street":"Stoutenburgstraat",
    "iso:country":"NL",
    "sg:address":"Stoutenburgstraat 41",
    "sg:city":"Breda",
    "sg:orig_category":"Juridische Dienstverlening",
    "sg:phone":"+31 76 565 4442",
    "sg:postcode":"4834 LN",
    "sg:province":"Noord-Brabant",
    "wof:name":"B.J.M. Fievez Adviezen Dienstverlening",
    "wof:placetype":"venue"
},
  "geometry": {"coordinates":[4.808797,51.571434],"type":"Point"}
}