{
  "type": "Feature",
  "properties": {
    "addr:full":"Torenstr 35A Helvoirt Noord-Brabant 5268 AS",
    "addr:housenumber":"35a",
    "addr:postcode":"5268 as",
    "addr:street":"Torenstr",
    "iso:country":"NL",
    "sg:address":"Torenstr 35A",
    "sg:city":"Helvoirt",
    "sg:orig_category":"Adviesbureaus Financieringen",
    "sg:phone":"+31 411 625 288",
    "sg:postcode":"5268 AS",
    "sg:province":"Noord-Brabant",
    "wof:name":"Kroot",
    "wof:placetype":"venue"
},
  "geometry": {"coordinates":[5.234936,51.633469],"type":"Point"}
}