{
  "type": "Feature",
  "properties": {
    "addr:full":"Klarendalsewg 401 Arnhem Gelderland 6822 GT",
    "addr:housenumber":"401",
    "addr:postcode":"6822 gt",
    "iso:country":"NL",
    "sg:address":"Klarendalsewg 401",
    "sg:city":"Arnhem",
    "sg:orig_category":"Goudsmeden En Zilversmeden",
    "sg:phone":"+31 26 442 5689",
    "sg:postcode":"6822 GT",
    "sg:province":"Gelderland",
    "wof:name":"Stoll?, Hendrik",
    "wof:placetype":"venue"
},
  "geometry": {"coordinates":[5.922847,51.988991],"type":"Point"}
}