{
  "type": "Feature",
  "properties": {
    "addr:full":"Vlasstr 10 Ridderkerk South Holland 2988 XR",
    "addr:housenumber":"10",
    "addr:postcode":"2988 xr",
    "addr:street":"Vlasstr",
    "iso:country":"NL",
    "sg:address":"Vlasstr 10",
    "sg:city":"Ridderkerk",
    "sg:orig_category":"Sportverenigingen En Ontspannings- Verenigingen",
    "sg:phone":"+31 180 427 660",
    "sg:postcode":"2988 XR",
    "sg:province":"South Holland",
    "wof:name":"De Waal, Erhv",
    "wof:placetype":"venue"
},
  "geometry": {"coordinates":[4.598176,51.851444],"type":"Point"}
}