{
  "type": "Feature",
  "properties": {
    "iso:country":"NL",
    "sg:address":"Hoofdstr 33",
    "sg:city":"Velp Gld",
    "sg:orig_category":"Fotoreportages",
    "sg:phone":"+31 26 361 9271",
    "sg:postcode":"6881 TB",
    "sg:province":"Gelderland",
    "wof:name":"Beurden, Ad Van",
    "wof:placetype":"venue"
},
  "geometry": {"coordinates":[5.974473,51.99585],"type":"Point"}
}