{
  "type": "Feature",
  "properties": {
    "addr:full":"Hoofdstr 33 Velp Gld Gelderland 6881 TB",
    "addr:housenumber":"33",
    "addr:postcode":"6881 tb",
    "addr:street":"Hoofdstr;Gld Gelderland",
    "iso:country":"NL",
    "sg:address":"Hoofdstr 33",
    "sg:city":"Velp Gld",
    "sg:orig_category":"Fotoreportages",
    "sg:phone":"+31 26 361 9271",
    "sg:postcode":"6881 TB",
    "sg:province":"Gelderland",
    "wof:name":"Beurden, Ad Van",
    "wof:placetype":"venue"
},
  "geometry": {"coordinates":[5.974473,51.99585],"type":"Point"}
}