{
  "type": "Feature",
  "properties": {
    "addr:full":"Fjildwei 14 Akmaryp Friesland 8541 AC",
    "addr:housenumber":"14",
    "addr:postcode":"8541 ac",
    "addr:street":"Fjildwei",
    "iso:country":"NL",
    "sg:address":"Fjildwei 14",
    "sg:city":"Akmaryp",
    "sg:classifiers":[
        {
            "category":"Personal",
            "subcategory":"Nail Salon",
            "type":"Services"
        }
    ],
    "sg:phone":"+31 566 689 482",
    "sg:postcode":"8541 AC",
    "sg:province":"Friesland",
    "sg:tags":[
        "pedicure"
    ],
    "wof:name":"Tetje Haven",
    "wof:placetype":"venue"
},
  "geometry": {"coordinates":[5.78924,53.004025],"type":"Point"}
}