{
  "type": "Feature",
  "properties": {
    "addr:full":"M H Trompln 25 Enschede Overijssel 7513 AB",
    "addr:housenumber":"25",
    "addr:postcode":"7513 ab",
    "addr:street":"M",
    "iso:country":"NL",
    "sg:address":"M H Trompln 25",
    "sg:city":"Enschede",
    "sg:orig_category":"Hypotheken",
    "sg:phone":"+31 53 432 3980",
    "sg:postcode":"7513 AB",
    "sg:province":"Overijssel",
    "sg:website":"http://www.cfai.nl",
    "wof:name":"Cfai Intermediar",
    "wof:placetype":"venue"
},
  "geometry": {"coordinates":[6.895374,52.223576],"type":"Point"}
}