{
  "type": "Feature",
  "properties": {
    "iso:country":"NL",
    "sg:address":"M H Trompln 25",
    "sg:city":"Enschede",
    "sg:orig_category":"Hypotheken",
    "sg:phone":"+31 53 432 3980",
    "sg:postcode":"7513 AB",
    "sg:province":"Overijssel",
    "sg:website":"http://www.cfai.nl",
    "wof:name":"Cfai Intermediar",
    "wof:placetype":"venue"
},
  "geometry": {"coordinates":[6.895374,52.223576],"type":"Point"}
}