{
  "type": "Feature",
  "properties": {
    "addr:full":"Jan Aarjensz Prinsstraat 8 Den Helder Noord-Holland 1785 BC",
    "addr:housenumber":"8",
    "addr:postcode":"1785 bc",
    "addr:street":"Jan Aarjensz Prinsstraat",
    "iso:country":"NL",
    "sg:address":"Jan Aarjensz Prinsstraat 8",
    "sg:city":"Den Helder",
    "sg:orig_category":"Verzekeringen",
    "sg:phone":"+31 223 634 612",
    "sg:postcode":"1785 BC",
    "sg:province":"Noord-Holland",
    "wof:name":"Assurantiekantoor Adrivon",
    "wof:placetype":"venue"
},
  "geometry": {"coordinates":[-126.555511,54.485668],"type":"Point"}
}