{
  "type": "Feature",
  "properties": {
    "addr:full":"Havenstraat 39 Bakhuizen Friesland 8574 SG",
    "addr:housenumber":"39",
    "addr:postcode":"8574 sg",
    "addr:street":"Havenstraat",
    "iso:country":"NL",
    "sg:address":"Havenstraat 39",
    "sg:city":"Bakhuizen",
    "sg:orig_category":"Bloemen And Planten",
    "sg:phone":"+31 514 581 539",
    "sg:postcode":"8574 SG",
    "sg:province":"Friesland",
    "wof:name":"Pompstation - Serviceshop Th. De Boer",
    "wof:placetype":"venue"
},
  "geometry": {"coordinates":[5.457904,52.871674],"type":"Point"}
}