{
  "type": "Feature",
  "properties": {
    "addr:full":"Broekerstraat 18 Leende Noord-Brabant 5595 CW",
    "addr:housenumber":"18",
    "addr:postcode":"5595 cw",
    "addr:street":"Broekerstraat",
    "iso:country":"NL",
    "sg:address":"Broekerstraat 18",
    "sg:city":"Leende",
    "sg:orig_category":"Verzekeringen",
    "sg:phone":"+31 40 206 1563",
    "sg:postcode":"5595 CW",
    "sg:province":"Noord-Brabant",
    "wof:name":"Assurantiekantoor Rutten Vof",
    "wof:placetype":"venue"
},
  "geometry": {"coordinates":[5.557012,51.348137],"type":"Point"}
}