{
  "type": "Feature",
  "properties": {
    "addr:full":"Potterstraat 12 Utrecht Utrecht 3512 TA",
    "addr:housenumber":"12",
    "addr:postcode":"3512 ta",
    "addr:street":"Potterstraat",
    "iso:country":"NL",
    "sg:address":"Potterstraat 12",
    "sg:city":"Utrecht",
    "sg:orig_category":"Werving And Selectie Van Tijdelijk Personeel And Uitzendkantoren",
    "sg:phone":"+31 30 234 0846",
    "sg:postcode":"3512 TA",
    "sg:province":"Utrecht",
    "wof:name":"Start",
    "wof:placetype":"venue"
},
  "geometry": {"coordinates":[5.117500782,52.0936164856],"type":"Point"}
}