{
  "type": "Feature",
  "properties": {
    "iso:country":"NL",
    "sg:address":"Vughterstr 88B",
    "sg:city":"S Hertogenbosch",
    "sg:orig_category":"Babyartikelen",
    "sg:phone":"+31 73 691 1899",
    "sg:postcode":"5211 GL",
    "sg:province":"North Brabant",
    "wof:name":"Geboortewinkel",
    "wof:placetype":"venue"
},
  "geometry": {"coordinates":[5.299971,51.686577],"type":"Point"}
}