{
  "type": "Feature",
  "properties": {
    "iso:country":"NL",
    "sg:address":"Oranjesingel 24",
    "sg:city":"Nijmegen",
    "sg:orig_category":"Krantenuitgeverijen",
    "sg:phone":"+31 24 388 8906",
    "sg:postcode":"6511 NV",
    "sg:province":"Gelderland",
    "wof:name":"Uitgeverij Logikos",
    "wof:placetype":"venue"
},
  "geometry": {"coordinates":[5.864075,51.842461],"type":"Point"}
}