{
  "type": "Feature",
  "properties": {
    "addr:full":"I Dammanstr 40 , (Mobiele Telefoon) Zaandam Noord-Holland 1507 PH",
    "addr:housenumber":"40",
    "addr:postcode":"1507",
    "addr:street":"Mobiele Telefoon",
    "iso:country":"NL",
    "sg:address":"I Dammanstr 40 , (Mobiele Telefoon)",
    "sg:city":"Zaandam",
    "sg:orig_category":"Jachthavens - Jachtwerven",
    "sg:phone":"+31 6 26102475",
    "sg:postcode":"1507 PH",
    "sg:province":"Noord-Holland",
    "wof:name":"Voorzaan Bv",
    "wof:placetype":"venue"
},
  "geometry": {"coordinates":[4.80102,52.438808],"type":"Point"}
}