{
  "type": "Feature",
  "properties": {
    "addr:full":"Haarsterwg 6 Marum Groningen 9363 VD",
    "addr:housenumber":"6",
    "addr:postcode":"9363 vd",
    "addr:street":"Haarsterwg",
    "iso:country":"NL",
    "sg:address":"Haarsterwg 6",
    "sg:city":"Marum",
    "sg:orig_category":"Melktransporten",
    "sg:phone":"+31 594 642 606",
    "sg:postcode":"9363 VD",
    "sg:province":"Groningen",
    "wof:name":"Venema Vof, J",
    "wof:placetype":"venue"
},
  "geometry": {"coordinates":[6.244389,53.13776],"type":"Point"}
}