{
  "type": "Feature",
  "properties": {
    "iso:country":"NL",
    "sg:address":"Zanderskamp 117",
    "sg:city":"Doesburg",
    "sg:orig_category":"Belastingconsulenten/ Belastingadviseurs",
    "sg:phone":"+31 313 484 110",
    "sg:postcode":"6983 CH",
    "sg:province":"Ticino",
    "wof:name":"Domage",
    "wof:placetype":"venue"
},
  "geometry": {"coordinates":[8.887845,45.983334],"type":"Point"}
}