{
  "type": "Feature",
  "properties": {
    "iso:country":"NL",
    "sg:address":"Kinkerstr 335",
    "sg:city":"Amsterdam",
    "sg:orig_category":"Wassalons",
    "sg:phone":"+31 20 618 0457",
    "sg:postcode":"1053 EW",
    "sg:province":"North Holland",
    "wof:name":"Kinker",
    "wof:placetype":"venue"
},
  "geometry": {"coordinates":[4.8618350029,52.3644523621],"type":"Point"}
}