{
  "type": "Feature",
  "properties": {
    "iso:country":"NL",
    "sg:address":"Aquamarijn 14",
    "sg:city":"Krimpen A/D Ijssel",
    "sg:orig_category":"Bedrijfs- And Managementsconsultants",
    "sg:phone":"+31 180 590 048",
    "sg:postcode":"2924 VR",
    "sg:province":"Zuid-Holland",
    "wof:name":"Van Kooij Management Consulting Bv",
    "wof:placetype":"venue"
},
  "geometry": {"coordinates":[4.607462,51.924904],"type":"Point"}
}