{
  "type": "Feature",
  "properties": {
    "addr:full":"Zandwg 13 Heerlen Limburg 6417 AS",
    "addr:housenumber":"13",
    "addr:postcode":"6417 as",
    "addr:street":"Zandwg",
    "iso:country":"NL",
    "sg:address":"Zandwg 13",
    "sg:city":"Heerlen",
    "sg:orig_category":"Publiciteitsbureaus",
    "sg:phone":"+31 6 23818172",
    "sg:postcode":"6417 AS",
    "sg:province":"Limburg",
    "wof:name":"Torena",
    "wof:placetype":"venue"
},
  "geometry": {"coordinates":[5.924681,50.924797],"type":"Point"}
}