{
  "type": "Feature",
  "properties": {
    "iso:country":"NL",
    "sg:address":"Pieter Langendijkstraat 47 Hs",
    "sg:city":"Amsterdam",
    "sg:orig_category":"Wasserettes And Stomerijen",
    "sg:phone":"+31 20 612 3946",
    "sg:postcode":"1054 XZ",
    "sg:province":"Noord-Holland",
    "wof:name":"Clean-Express Van Der Ahe",
    "wof:placetype":"venue"
},
  "geometry": {"coordinates":[4.8685698509,52.3614082336],"type":"Point"}
}