{
  "type": "Feature",
  "properties": {
    "addr:full":"Kl Broekstr 20A Bergeyk North Brabant 5571 KG",
    "addr:housenumber":"20a",
    "addr:postcode":"5571 kg",
    "addr:street":"Bergeyk North",
    "iso:country":"NL",
    "sg:address":"Kl Broekstr 20A",
    "sg:city":"Bergeyk",
    "sg:orig_category":"Kinderkleding",
    "sg:phone":"+31 497 577 075",
    "sg:postcode":"5571 KG",
    "sg:province":"North Brabant",
    "wof:name":"Jippie",
    "wof:placetype":"venue"
},
  "geometry": {"coordinates":[5.360135,51.323326],"type":"Point"}
}