{
  "type": "Feature",
  "properties": {
    "addr:full":"Wagenaarstraat 370 Amsterdam Noord-Holland 1093 CX",
    "addr:housenumber":"370",
    "addr:postcode":"1093 cx",
    "addr:street":"Wagenaarstraat",
    "iso:country":"NL",
    "sg:address":"Wagenaarstraat 370",
    "sg:city":"Amsterdam",
    "sg:orig_category":"Mode-, Juwelen- And Meubelontwerpers",
    "sg:phone":"+31 20 694 3541",
    "sg:postcode":"1093 CX",
    "sg:province":"Noord-Holland",
    "wof:name":"Van Der Molen",
    "wof:placetype":"venue"
},
  "geometry": {"coordinates":[4.928357,52.363358],"type":"Point"}
}