{
  "type": "Feature",
  "properties": {
    "addr:full":"Calandstraat 26 Werkendam North Brabant 4251 NZ",
    "addr:housenumber":"26",
    "addr:postcode":"4251 nz",
    "addr:street":"Calandstraat",
    "iso:country":"NL",
    "sg:address":"Calandstraat 26",
    "sg:city":"Werkendam",
    "sg:orig_category":"Watersport-, Sport- And Kampeerbenodigdheden Verhuur",
    "sg:phone":"+31 183 504 333",
    "sg:postcode":"4251 NZ",
    "sg:province":"North Brabant",
    "wof:name":"De Biesbosch Kanocentrum",
    "wof:placetype":"venue"
},
  "geometry": {"coordinates":[4.8675251007,51.8021011353],"type":"Point"}
}