{
  "type": "Feature",
  "properties": {
    "iso:country":"NL",
    "sg:address":"Groene Kruisweg 5",
    "sg:city":"Herkingen",
    "sg:orig_category":"Boekhouders",
    "sg:phone":"+31 187 669 371",
    "sg:postcode":"3249 AG",
    "sg:province":"Zuid-Holland",
    "wof:name":"Administratie & Assurantiekantoor Spitte",
    "wof:placetype":"venue"
},
  "geometry": {"coordinates":[4.093909,51.707973],"type":"Point"}
}