{
  "type": "Feature",
  "properties": {
    "addr:full":"Zeelandiahoeve 5-7 Amstelveen North Holland 1187 KR",
    "addr:housenumber":"5-7",
    "addr:postcode":"1187 kr",
    "addr:street":"Zeelandiahoeve",
    "iso:country":"NL",
    "sg:address":"Zeelandiahoeve 5-7",
    "sg:city":"Amstelveen",
    "sg:classifiers":[
        {
            "category":"Education",
            "subcategory":"Preschool",
            "type":"Public Place"
        }
    ],
    "sg:phone":"+31 20 645 3825",
    "sg:postcode":"1187 KR",
    "sg:province":"North Holland",
    "sg:tags":[
        "kleuteronderwijs",
        "basis-"
    ],
    "wof:name":"De Triangel",
    "wof:placetype":"venue"
},
  "geometry": {"coordinates":[4.825616,52.280643],"type":"Point"}
}