{
  "type": "Feature",
  "properties": {
    "iso:country":"NL",
    "sg:address":"J V Zutphenstr 128-140",
    "sg:city":"Haarlem",
    "sg:orig_category":"Artsen - Huisartsen",
    "sg:phone":"+31 23 533 3536",
    "sg:postcode":"2037 VC",
    "sg:province":"North Holland",
    "wof:name":"Faber, S G P",
    "wof:placetype":"venue"
},
  "geometry": {"coordinates":[4.66426,52.353531],"type":"Point"}
}