{
  "type": "Feature",
  "properties": {
    "addr:full":"Noordzeepassage 24 Katwijk Zh Zuid-Holland 2225 BS",
    "addr:housenumber":"24",
    "addr:postcode":"2225 bs",
    "addr:street":"Noordzeepassage",
    "iso:country":"NL",
    "sg:address":"Noordzeepassage 24",
    "sg:city":"Katwijk Zh",
    "sg:orig_category":"Verlichting And Huishoudartikelen",
    "sg:phone":"+31 71 407 5526",
    "sg:postcode":"2225 BS",
    "sg:province":"Zuid-Holland",
    "wof:name":"Misja'S Lampenwinkel",
    "wof:placetype":"venue"
},
  "geometry": {"coordinates":[4.395199,52.205143],"type":"Point"}
}