{
  "type": "Feature",
  "properties": {
    "addr:full":"Heerlenersteenweg 81 Kerkrade Limburg 6466 KS",
    "addr:housenumber":"81",
    "addr:postcode":"6466 ks",
    "addr:street":"Heerlenersteenweg",
    "iso:country":"NL",
    "sg:address":"Heerlenersteenweg 81",
    "sg:city":"Kerkrade",
    "sg:classifiers":[
        {
            "category":"Travel",
            "subcategory":"Hotels & Motels",
            "type":"Entertainment"
        }
    ],
    "sg:phone":"+31 45 542 0909",
    "sg:postcode":"6466 KS",
    "sg:province":"Limburg",
    "wof:name":"Hotel Formule 1",
    "wof:placetype":"venue"
},
  "geometry": {"coordinates":[6.016089,50.861504],"type":"Point"}
}