{
  "type": "Feature",
  "properties": {
    "addr:full":"Stolperweg 17 Schagerbrug Noord-Holland 1751 DG",
    "addr:housenumber":"17",
    "addr:postcode":"1751 dg",
    "addr:street":"Stolperweg",
    "iso:country":"NL",
    "sg:address":"Stolperweg 17",
    "sg:city":"Schagerbrug",
    "sg:orig_category":"Autokeuringen",
    "sg:phone":"+31 224 573 086",
    "sg:postcode":"1751 DG",
    "sg:province":"Noord-Holland",
    "wof:name":"J Manneveld",
    "wof:placetype":"venue"
},
  "geometry": {"coordinates":[4.728345,52.81287],"type":"Point"}
}