{
  "type": "Feature",
  "properties": {
    "addr:full":"Molenwg 46 Sommelsdyk Zuid-Holland 3245 LS",
    "addr:housenumber":"46",
    "addr:postcode":"3245 ls",
    "addr:street":"Molenwg",
    "iso:country":"NL",
    "sg:address":"Molenwg 46",
    "sg:city":"Sommelsdyk",
    "sg:orig_category":"Bloemen En Planten",
    "sg:phone":"+31 187 483 803",
    "sg:postcode":"3245 LS",
    "sg:province":"Zuid-Holland",
    "wof:name":"Baan & Zoon Vof, J Van Der",
    "wof:placetype":"venue"
},
  "geometry": {"coordinates":[4.144203,51.757801],"type":"Point"}
}