{
  "type": "Feature",
  "properties": {
    "addr:full":"Sluiswg 9A Lemmer Friesland 8531 DJ",
    "addr:housenumber":"9a",
    "addr:postcode":"8531 dj",
    "addr:street":"Sluiswg",
    "iso:country":"NL",
    "sg:address":"Sluiswg 9A",
    "sg:city":"Lemmer",
    "sg:orig_category":"Jachthavens - Jachtwerven",
    "sg:phone":"+31 514 561 873",
    "sg:postcode":"8531 DJ",
    "sg:province":"Friesland",
    "sg:website":"http://www.mekon.nl",
    "wof:name":"Mekon Bv",
    "wof:placetype":"venue"
},
  "geometry": {"coordinates":[5.715637,52.841843],"type":"Point"}
}