{
  "type": "Feature",
  "properties": {
    "addr:full":"Klipper 8 Volendam Noord-Holland 1132 GV",
    "addr:housenumber":"8",
    "addr:postcode":"1132 gv",
    "addr:street":"Klipper",
    "iso:country":"NL",
    "sg:address":"Klipper 8",
    "sg:city":"Volendam",
    "sg:orig_category":"Manueel Therapeuten",
    "sg:phone":"+31 299 361 822",
    "sg:postcode":"1132 GV",
    "sg:province":"Noord-Holland",
    "wof:name":"Pot, A",
    "wof:placetype":"venue"
},
  "geometry": {"coordinates":[5.044034,52.498741],"type":"Point"}
}