{
  "type": "Feature",
  "properties": {
    "addr:full":"Westblaak 37 Rotterdam Zuid-Holland 3012 KD",
    "addr:housenumber":"37",
    "addr:postcode":"3012 kd",
    "addr:street":"Westblaak",
    "iso:country":"NL",
    "sg:address":"Westblaak 37",
    "sg:city":"Rotterdam",
    "sg:classifiers":[
        {
            "category":"Professional",
            "subcategory":"Accounting & Tax Preparation",
            "type":"Services"
        }
    ],
    "sg:phone":"+31 10 412 3052",
    "sg:postcode":"3012 KD",
    "sg:province":"Zuid-Holland",
    "sg:tags":[
        "accountant"
    ],
    "wof:name":"Pasman & Bakker Accountants",
    "wof:placetype":"venue"
},
  "geometry": {"coordinates":[4.477807,51.917404],"type":"Point"}
}