{
  "type": "Feature",
  "properties": {
    "addr:full":"Engelsesteeg 4 Amsterdam Noord-Holland 1012 NA",
    "addr:housenumber":"4",
    "addr:postcode":"1012 na",
    "addr:street":"Engelsesteeg",
    "iso:country":"NL",
    "sg:address":"Engelsesteeg 4",
    "sg:city":"Amsterdam",
    "sg:orig_category":"Autoverhuur",
    "sg:phone":"+31 20 623 6123",
    "sg:postcode":"1012 NA",
    "sg:province":"Noord-Holland",
    "wof:name":"Hertz Amsterdam",
    "wof:placetype":"venue"
},
  "geometry": {"coordinates":[4.895144,52.378235],"type":"Point"}
}