{
  "type": "Feature",
  "properties": {
    "addr:full":"C Clusiusln 3 Voorhout Zuid-Holland 2215 RV",
    "addr:housenumber":"3",
    "addr:postcode":"2215 rv",
    "iso:country":"NL",
    "sg:address":"C Clusiusln 3",
    "sg:city":"Voorhout",
    "sg:orig_category":"Kaas",
    "sg:phone":"+31 252 214 452",
    "sg:postcode":"2215 RV",
    "sg:province":"Zuid-Holland",
    "wof:name":"Verswinkel Bv",
    "wof:placetype":"venue"
},
  "geometry": {"coordinates":[4.4825201035,52.2218742371],"type":"Point"}
}