{
  "type": "Feature",
  "properties": {
    "addr:full":"Industriewg Z 11 Westdorpe Zeeland 4554 LL",
    "addr:housenumber":"11",
    "addr:postcode":"4554 ll",
    "iso:country":"NL",
    "sg:address":"Industriewg Z 11",
    "sg:city":"Westdorpe",
    "sg:orig_category":"Verenigingen En Stichtingen",
    "sg:phone":"+31 115 478 200",
    "sg:postcode":"4554 LL",
    "sg:province":"Zeeland",
    "wof:name":"Co\u00f6p Zuidel Aan-En Verk Ver",
    "wof:placetype":"venue"
},
  "geometry": {"coordinates":[3.872096,51.267567],"type":"Point"}
}