{
  "type": "Feature",
  "properties": {
    "iso:country":"NL",
    "sg:address":"Vliet 63",
    "sg:city":"Zwolle",
    "sg:orig_category":"Marktonderzoekbureaus",
    "sg:phone":"+31 38 452 5558",
    "sg:postcode":"8032 AS",
    "sg:province":"Overijssel",
    "wof:name":"Honselaar Selectie Bureau",
    "wof:placetype":"venue"
},
  "geometry": {"coordinates":[6.098898,52.525417],"type":"Point"}
}