{
  "type": "Feature",
  "properties": {
    "iso:country":"NL",
    "sg:address":"Heemraadhof 22",
    "sg:city":"Krimpen A/D Ijssel",
    "sg:orig_category":"Elektriciens",
    "sg:phone":"+31 180 553 525",
    "sg:postcode":"2922 CK",
    "sg:province":"South Holland",
    "wof:name":"Hoogendijk",
    "wof:placetype":"venue"
},
  "geometry": {"coordinates":[4.593167,51.920452],"type":"Point"}
}