{
  "type": "Feature",
  "properties": {
    "iso:country":"NL",
    "sg:address":"Hinkelenoord 23",
    "sg:city":"Bergen Op Zoom",
    "sg:orig_category":"Fotoreportages",
    "sg:phone":"+31 164 248 448",
    "sg:postcode":"4617 NC",
    "sg:province":"Noord-Brabant",
    "wof:name":"Chantal Foto Art",
    "wof:placetype":"venue"
},
  "geometry": {"coordinates":[4.279475,51.475613],"type":"Point"}
}