{
  "type": "Feature",
  "properties": {
    "iso:country":"NL",
    "sg:address":"Ter Heydestraat 1C",
    "sg:city":"Den Haag",
    "sg:orig_category":"Werving And Selectie Van Tijdelijk Personeel And Uitzendkantoren",
    "sg:phone":"+31 6 51676493",
    "sg:postcode":"2512 SE",
    "sg:province":"South Holland",
    "wof:name":"Connect",
    "wof:placetype":"venue"
},
  "geometry": {"coordinates":[4.2960438728,52.0699462891],"type":"Point"}
}