{
  "type": "Feature",
  "properties": {
    "addr:full":"Tintln 99 Zoetermeer Zuid-Holland 2719 AM",
    "addr:housenumber":"99",
    "addr:postcode":"2719",
    "addr:street":"Tintln",
    "iso:country":"NL",
    "sg:address":"Tintln 99",
    "sg:city":"Zoetermeer",
    "sg:orig_category":"Werving En Selectie",
    "sg:phone":"+31 79 362 0150",
    "sg:postcode":"2719 AM",
    "sg:province":"Zuid-Holland",
    "wof:name":"Ymago",
    "wof:placetype":"venue"
},
  "geometry": {"coordinates":[4.4889249802,52.063079834],"type":"Point"}
}