{
  "type": "Feature",
  "properties": {
    "addr:full":"Verzetstr 1 Kaatsheuvel Noord-Brabant 5171 PT",
    "addr:housenumber":"1",
    "addr:postcode":"5171 pt",
    "addr:street":"Verzetstr",
    "iso:country":"NL",
    "sg:address":"Verzetstr 1",
    "sg:city":"Kaatsheuvel",
    "sg:orig_category":"Keukens",
    "sg:phone":"+31 416 277 717",
    "sg:postcode":"5171 PT",
    "sg:province":"Noord-Brabant",
    "sg:website":"http://www.elbe.nl",
    "wof:name":"Elb\u00e9",
    "wof:placetype":"venue"
},
  "geometry": {"coordinates":[5.036786,51.664597],"type":"Point"}
}