{
  "type": "Feature",
  "properties": {
    "addr:full":"Wegaln 42 Hoofddorp North Holland 2132 JC",
    "addr:housenumber":"42",
    "addr:postcode":"2132 jc",
    "addr:street":"Wegaln",
    "iso:country":"NL",
    "sg:address":"Wegaln 42",
    "sg:city":"Hoofddorp",
    "sg:orig_category":"Medische Keuringen",
    "sg:phone":"+31 23 554 1540",
    "sg:postcode":"2132 JC",
    "sg:province":"North Holland",
    "wof:name":"Meditel Bv",
    "wof:placetype":"venue"
},
  "geometry": {"coordinates":[4.69296,52.305393],"type":"Point"}
}