{
  "type": "Feature",
  "properties": {
    "addr:full":"Jousterweg 18 Heerenveen Provincie Friesland 8447 RH",
    "addr:housenumber":"18",
    "addr:postcode":"8447 rh",
    "addr:street":"Jousterweg;Provincie Friesland",
    "iso:country":"NL",
    "sg:address":"Jousterweg 18",
    "sg:city":"Heerenveen",
    "sg:orig_category":"Verhuur Gereedschapsmachines And Gereedschappen",
    "sg:phone":"+31 513 610 910",
    "sg:postcode":"8447 RH",
    "sg:province":"Provincie Friesland",
    "wof:name":"Boels Verhuur",
    "wof:placetype":"venue"
},
  "geometry": {"coordinates":[5.90554,52.964897],"type":"Point"}
}