{
  "type": "Feature",
  "properties": {
    "addr:full":"Orchisln 6 Oostvoorne Zuid-Holland 3233 VE",
    "addr:housenumber":"6",
    "addr:postcode":"3233",
    "addr:street":"Orchisln;Ve",
    "iso:country":"NL",
    "sg:address":"Orchisln 6",
    "sg:city":"Oostvoorne",
    "sg:orig_category":"Beeldende Kunstenaars",
    "sg:phone":"+31 181 484 182",
    "sg:postcode":"3233 VE",
    "sg:province":"Zuid-Holland",
    "wof:name":"Kooi, Kobi Van Der",
    "wof:placetype":"venue"
},
  "geometry": {"coordinates":[4.103859,51.913956],"type":"Point"}
}