{
  "type": "Feature",
  "properties": {
    "addr:full":"Struikheiweg 16 Bussum North Holland 1406 TK",
    "addr:housenumber":"16",
    "addr:postcode":"1406 tk",
    "addr:street":"Struikheiweg",
    "iso:country":"NL",
    "sg:address":"Struikheiweg 16",
    "sg:city":"Bussum",
    "sg:orig_category":"Fitnesscentra",
    "sg:phone":"+31 35 692 0117",
    "sg:postcode":"1406 TK",
    "sg:province":"North Holland",
    "wof:name":"Jacqueline'S Body Line",
    "wof:placetype":"venue"
},
  "geometry": {"coordinates":[5.15625,52.265659],"type":"Point"}
}