{
  "type": "Feature",
  "properties": {
    "iso:country":"NL",
    "sg:address":"Dorpsstr 138",
    "sg:city":"Castricum",
    "sg:orig_category":"Hypotheken",
    "sg:phone":"+31 251 672 008",
    "sg:postcode":"1901 EN",
    "sg:province":"Noord-Holland",
    "wof:name":"Hypotheeknet",
    "wof:placetype":"venue"
},
  "geometry": {"coordinates":[4.668717,52.549229],"type":"Point"}
}