{
  "type": "Feature",
  "properties": {
    "iso:country":"NL",
    "sg:address":"Zuidpromenade 2",
    "sg:city":"Soest",
    "sg:orig_category":"Bijouterie?n",
    "sg:phone":"+31 35 588 1054",
    "sg:postcode":"3768 EM",
    "sg:province":"Utrecht",
    "wof:name":"Charvida",
    "wof:placetype":"venue"
},
  "geometry": {"coordinates":[5.30052,52.145535],"type":"Point"}
}