{
  "type": "Feature",
  "properties": {
    "addr:full":"Overtoom 443 Amsterdam North Holland 1054 KG",
    "addr:housenumber":"443",
    "addr:postcode":"1054 kg",
    "addr:street":"Overtoom",
    "iso:country":"NL",
    "sg:address":"Overtoom 443",
    "sg:city":"Amsterdam",
    "sg:orig_category":"Erotische Etablissementen",
    "sg:phone":"+31 20 618 9110",
    "sg:postcode":"1054 KG",
    "sg:province":"North Holland",
    "wof:name":"Adam Prive",
    "wof:placetype":"venue"
},
  "geometry": {"coordinates":[4.859831,52.358711],"type":"Point"}
}