{
  "type": "Feature",
  "properties": {
    "addr:full":"Goereesestr 12 Rotterdam Zuid-Holland 3083 DJ",
    "addr:housenumber":"12",
    "addr:postcode":"3083 dj",
    "addr:street":"Goereesestr",
    "iso:country":"NL",
    "sg:address":"Goereesestr 12",
    "sg:city":"Rotterdam",
    "sg:orig_category":"Advocaten En Advocatenkantoren",
    "sg:phone":"+31 10 481 6622",
    "sg:postcode":"3083 DJ",
    "sg:province":"Zuid-Holland",
    "sg:website":"http://www.dehaanslageradvocaten.nl",
    "wof:name":"Haan & Slager, De",
    "wof:placetype":"venue"
},
  "geometry": {"coordinates":[4.487142,51.88887],"type":"Point"}
}