{
  "type": "Feature",
  "properties": {
    "addr:full":"Kruiswg 1173 Hoofddorp Noord-Holland 2131 MD",
    "addr:housenumber":"1173",
    "addr:postcode":"hoofddorp;2131",
    "iso:country":"NL",
    "sg:address":"Kruiswg 1173",
    "sg:city":"Hoofddorp",
    "sg:orig_category":"Autorijscholen",
    "sg:phone":"+31 23 562 0646",
    "sg:postcode":"2131 MD",
    "sg:province":"Noord-Holland",
    "wof:name":"Elderhorst",
    "wof:placetype":"venue"
},
  "geometry": {"coordinates":[4.682129,52.311558],"type":"Point"}
}