{
  "type": "Feature",
  "properties": {
    "iso:country":"NL",
    "sg:address":"Van Iddekingeweg 192",
    "sg:city":"Groningen",
    "sg:orig_category":"Kinderopvang Behalve Thuis",
    "sg:phone":"+31 50 525 2717",
    "sg:postcode":"9721 CM",
    "sg:province":"Groningen",
    "wof:name":"Kinderopvang Wolkewietje",
    "wof:placetype":"venue"
},
  "geometry": {"coordinates":[6.565908,53.197105],"type":"Point"}
}