{
  "type": "Feature",
  "properties": {
    "addr:full":"Koornmarkt 16 Delft Zuid-Holland 2611 EE",
    "addr:housenumber":"16",
    "addr:postcode":"2611 ee",
    "addr:street":"Koornmarkt",
    "iso:country":"NL",
    "sg:address":"Koornmarkt 16",
    "sg:city":"Delft",
    "sg:classifiers":[
        {
            "category":"Travel",
            "subcategory":"Hotels & Motels",
            "type":"Entertainment"
        }
    ],
    "sg:phone":"+31 15 214 7741",
    "sg:postcode":"2611 EE",
    "sg:province":"Zuid-Holland",
    "wof:name":"Hotel Leeuwenbrug",
    "wof:placetype":"venue"
},
  "geometry": {"coordinates":[4.359729,52.008869],"type":"Point"}
}