{
  "type": "Feature",
  "properties": {
    "addr:full":"Tussenbeeksweg 62 Ijmuiden Noord-Holland 1971 ND",
    "addr:housenumber":"62",
    "addr:postcode":"1971 nd",
    "addr:street":"Tussenbeeksweg",
    "iso:country":"NL",
    "sg:address":"Tussenbeeksweg 62",
    "sg:city":"Ijmuiden",
    "sg:classifiers":[
        {
            "category":"Fast Food",
            "type":"Food & Drink"
        }
    ],
    "sg:phone":"+31 255 511 238",
    "sg:postcode":"1971 ND",
    "sg:province":"Noord-Holland",
    "sg:tags":[
        "afhaal",
        "restaurant"
    ],
    "wof:name":"Rose Garden",
    "wof:placetype":"venue"
},
  "geometry": {"coordinates":[-100.30171199999999,47.467731],"type":"Point"}
}