{
  "type": "Feature",
  "properties": {
    "iso:country":"NL",
    "sg:address":"Bronnegerstraat 3",
    "sg:city":"Buinen",
    "sg:orig_category":"Architecten",
    "sg:phone":"+31 599 212 645",
    "sg:postcode":"9528 TB",
    "sg:province":"Provincie Drenthe",
    "wof:name":"R. Strietman",
    "wof:placetype":"venue"
},
  "geometry": {"coordinates":[6.834157,52.938766],"type":"Point"}
}