{
  "type": "Feature",
  "properties": {
    "addr:full":"Bronnegerstraat 3 Buinen Provincie Drenthe 9528 TB",
    "addr:housenumber":"3",
    "addr:postcode":"9528 tb",
    "addr:street":"Bronnegerstraat;Provincie Drenthe",
    "iso:country":"NL",
    "sg:address":"Bronnegerstraat 3",
    "sg:city":"Buinen",
    "sg:orig_category":"Architecten",
    "sg:phone":"+31 599 212 645",
    "sg:postcode":"9528 TB",
    "sg:province":"Provincie Drenthe",
    "wof:name":"R. Strietman",
    "wof:placetype":"venue"
},
  "geometry": {"coordinates":[6.834157,52.938766],"type":"Point"}
}