{
  "type": "Feature",
  "properties": {
    "iso:country":"NL",
    "sg:address":"Opwettenseweg 54",
    "sg:city":"Nuenen",
    "sg:orig_category":"Goederenvervoer Over De Weg",
    "sg:phone":"+31 40 283 6456",
    "sg:postcode":"5672 AJ",
    "sg:province":"Noord-Brabant",
    "wof:name":"Vof Transportbedrijf V. Kemenade",
    "wof:placetype":"venue"
},
  "geometry": {"coordinates":[5.540276,51.468128],"type":"Point"}
}