{
  "type": "Feature",
  "properties": {
    "addr:full":"Binn Wieringerstr 9 Amsterdam Noord-Holland 1013 EA",
    "addr:housenumber":"9",
    "addr:postcode":"1013 ea",
    "addr:street":"Binn Wieringerstr",
    "iso:country":"NL",
    "sg:address":"Binn Wieringerstr 9",
    "sg:city":"Amsterdam",
    "sg:classifiers":[
        {
            "category":"Travel",
            "subcategory":"Hotels & Motels",
            "type":"Entertainment"
        }
    ],
    "sg:phone":"+31 20 627 4390",
    "sg:postcode":"1013 EA",
    "sg:province":"Noord-Holland",
    "wof:name":"Regal, The",
    "wof:placetype":"venue"
},
  "geometry": {"coordinates":[4.892793,52.379742],"type":"Point"}
}