{
  "type": "Feature",
  "properties": {
    "iso:country":"NL",
    "sg:address":"Tuinhaversveld 2",
    "sg:city":"Grubbenvorst",
    "sg:orig_category":"Psychosociale Therapeuten",
    "sg:phone":"+31 77 327 0046",
    "sg:postcode":"5971 DJ",
    "sg:province":"Limburg",
    "sg:website":"http://www.reiki.nl",
    "wof:name":"Steegh",
    "wof:placetype":"venue"
},
  "geometry": {"coordinates":[6.138251,51.416901],"type":"Point"}
}