{
  "type": "Feature",
  "properties": {
    "addr:full":"Postbus 397 Nymegen Gelderland 6500 AJ",
    "addr:housenumber":"397",
    "addr:postcode":"6500 aj",
    "addr:street":"Postbus;Gelderland",
    "iso:country":"NL",
    "sg:address":"Postbus 397",
    "sg:city":"Nymegen",
    "sg:orig_category":"Journalisten Freelance",
    "sg:phone":"+31 24 324 0500",
    "sg:postcode":"6500 AJ",
    "sg:province":"Gelderland",
    "sg:website":"http://www.preustingpers.nl",
    "wof:name":"Preusting",
    "wof:placetype":"venue"
},
  "geometry": {"coordinates":[5.83296,51.842651],"type":"Point"}
}