{
  "type": "Feature",
  "properties": {
    "addr:full":"Isebrandtsheerd 97 Groningen Groningen 9737 LK",
    "addr:housenumber":"97",
    "addr:postcode":"9737 lk",
    "addr:street":"Isebrandtsheerd",
    "iso:country":"NL",
    "sg:address":"Isebrandtsheerd 97",
    "sg:city":"Groningen",
    "sg:orig_category":"Verenigingsgebouwen",
    "sg:phone":"+31 50 541 0070",
    "sg:postcode":"9737 LK",
    "sg:province":"Groningen",
    "wof:name":"Heerdenhoes, 'T",
    "wof:placetype":"venue"
},
  "geometry": {"coordinates":[6.59213,53.244907],"type":"Point"}
}