{
  "type": "Feature",
  "properties": {
    "addr:full":"St Hubertusln 106A Driebergen Rysenb Utrecht 3972 WP",
    "addr:housenumber":"106a",
    "addr:postcode":"3972 wp",
    "addr:street":"Driebergen Rysenb",
    "iso:country":"NL",
    "sg:address":"St Hubertusln 106A",
    "sg:city":"Driebergen Rysenb",
    "sg:orig_category":"Bedrijfsopleidingen",
    "sg:phone":"+31 343 430 493",
    "sg:postcode":"3972 WP",
    "sg:province":"Utrecht",
    "wof:name":"Hwb",
    "wof:placetype":"venue"
},
  "geometry": {"coordinates":[5.268162,52.049889],"type":"Point"}
}