{
  "type": "Feature",
  "properties": {
    "iso:country":"NL",
    "sg:address":"Kroonse Wal 14",
    "sg:city":"Arnhem",
    "sg:orig_category":"Bloemen And Planten",
    "sg:phone":"+31 26 389 0708",
    "sg:postcode":"6844 GS",
    "sg:province":"Gelderland",
    "wof:name":"Bloembinderij 'T Kroontje",
    "wof:placetype":"venue"
},
  "geometry": {"coordinates":[5.859909,51.95137],"type":"Point"}
}