{
  "type": "Feature",
  "properties": {
    "iso:country":"NL",
    "sg:address":"Schakelplein 16",
    "sg:city":"Eindhoven",
    "sg:orig_category":"Werving And Selectie Van Tijdelijk Personeel And Uitzendkantoren",
    "sg:phone":"+31 40 261 8381",
    "sg:postcode":"5651 GR",
    "sg:province":"Noord-Brabant",
    "wof:name":"Tempo Team",
    "wof:placetype":"venue"
},
  "geometry": {"coordinates":[5.4209599495,51.4652824402],"type":"Point"}
}