{
  "type": "Feature",
  "properties": {
    "addr:full":"Belvedereweg 3 Soest Utrecht 3762 EE",
    "addr:housenumber":"3",
    "addr:postcode":"3762 ee",
    "addr:street":"Belvedereweg",
    "iso:country":"NL",
    "sg:address":"Belvedereweg 3",
    "sg:city":"Soest",
    "sg:orig_category":"Papier And Karton Fab",
    "sg:phone":"+31 35 601 6551",
    "sg:postcode":"3762 EE",
    "sg:province":"Utrecht",
    "wof:name":"Lamineerbedrijf Briljant Bv",
    "wof:placetype":"venue"
},
  "geometry": {"coordinates":[5.270521,52.181358],"type":"Point"}
}