{
  "type": "Feature",
  "properties": {
    "addr:full":"Postbus 4154 Apeldoorn Gelderland 7320 AD",
    "addr:housenumber":"4154",
    "addr:postcode":"7320 ad",
    "addr:street":"Postbus;Gelderland",
    "iso:country":"NL",
    "sg:address":"Postbus 4154",
    "sg:city":"Apeldoorn",
    "sg:orig_category":"Bedrijfsopleidingen",
    "sg:phone":"+31 55 368 9870",
    "sg:postcode":"7320 AD",
    "sg:province":"Gelderland",
    "sg:website":"http://www.tminederland.nl",
    "wof:name":"Tmi Nederland Bv",
    "wof:placetype":"venue"
},
  "geometry": {"coordinates":[5.96246,52.214329],"type":"Point"}
}