{
  "type": "Feature",
  "properties": {
    "iso:country":"NL",
    "sg:address":"Dorpsstr 32",
    "sg:city":"Moerkapelle",
    "sg:orig_category":"Boeken En Tijdschriften",
    "sg:phone":"+31 79 593 3622",
    "sg:postcode":"2751 BA",
    "sg:province":"Zuid-Holland",
    "sg:website":"http://www.bruna.nl",
    "wof:name":"Boekelier, De",
    "wof:placetype":"venue"
},
  "geometry": {"coordinates":[4.575687,52.043465],"type":"Point"}
}