{
  "type": "Feature",
  "properties": {
    "addr:full":"Hoogeveensewg 7 Boskoop Zuid-Holland 2771 TA",
    "addr:housenumber":"7",
    "addr:postcode":"2771 ta",
    "addr:street":"Hoogeveensewg",
    "iso:country":"NL",
    "sg:address":"Hoogeveensewg 7",
    "sg:city":"Boskoop",
    "sg:classifiers":[
        {
            "category":"Retail",
            "subcategory":"Auto Repair",
            "type":"Services"
        }
    ],
    "sg:phone":"+31 172 215 254",
    "sg:postcode":"2771 TA",
    "sg:province":"Zuid-Holland",
    "sg:tags":[
        "garage"
    ],
    "wof:name":"Techno Service Zuid-West",
    "wof:placetype":"venue"
},
  "geometry": {"coordinates":[4.631525,52.076004],"type":"Point"}
}