{
  "type": "Feature",
  "properties": {
    "addr:full":"Mierlosewg 10 Helmond Noord-Brabant 5707 AL",
    "addr:housenumber":"10",
    "addr:postcode":"5707 al",
    "addr:street":"Mierlosewg",
    "iso:country":"NL",
    "sg:address":"Mierlosewg 10",
    "sg:city":"Helmond",
    "sg:orig_category":"Boeken En Tijdschriften",
    "sg:phone":"+31 492 599 471",
    "sg:postcode":"5707 AL",
    "sg:province":"Noord-Brabant",
    "wof:name":"Boekelier, De",
    "wof:placetype":"venue"
},
  "geometry": {"coordinates":[5.645207,51.476585],"type":"Point"}
}