{
  "type": "Feature",
  "properties": {
    "addr:full":"De Steenenborch 6 Nieuwkuyk Noord-Brabant 5253 XC",
    "addr:housenumber":"6",
    "addr:postcode":"5253 xc",
    "addr:street":"De Steenenborch",
    "iso:country":"NL",
    "sg:address":"De Steenenborch 6",
    "sg:city":"Nieuwkuyk",
    "sg:orig_category":"Artsen - Huisartsen",
    "sg:phone":"+31 73 511 2545",
    "sg:postcode":"5253 XC",
    "sg:province":"Noord-Brabant",
    "wof:name":"Versteeg, J",
    "wof:placetype":"venue"
},
  "geometry": {"coordinates":[5.18056,51.692101],"type":"Point"}
}