{
  "type": "Feature",
  "properties": {
    "addr:full":"Hazenkoog 17C Alkmaar Noord-Holland 1822 BS",
    "addr:housenumber":"17c",
    "addr:postcode":"1822 bs",
    "addr:street":"Hazenkoog",
    "iso:country":"NL",
    "sg:address":"Hazenkoog 17C",
    "sg:city":"Alkmaar",
    "sg:orig_category":"Voegwerken",
    "sg:phone":"+31 72 562 9979",
    "sg:postcode":"1822 BS",
    "sg:province":"Noord-Holland",
    "wof:name":"Vemola Bv",
    "wof:placetype":"venue"
},
  "geometry": {"coordinates":[4.792927,52.652172],"type":"Point"}
}