{
  "type": "Feature",
  "properties": {
    "addr:full":"Prinses Julianastraat 22 Naaldwijk South Holland 2671 EK",
    "addr:housenumber":"22",
    "addr:postcode":"2671 ek",
    "addr:street":"Prinses Julianastraat",
    "iso:country":"NL",
    "sg:address":"Prinses Julianastraat 22",
    "sg:city":"Naaldwijk",
    "sg:classifiers":[
        {
            "category":"Fast Food",
            "type":"Food & Drink"
        }
    ],
    "sg:phone":"+31 174 641 304",
    "sg:postcode":"2671 EK",
    "sg:province":"South Holland",
    "sg:tags":[
        "afhaal",
        "restaurant"
    ],
    "wof:name":"Piramide",
    "wof:placetype":"venue"
},
  "geometry": {"coordinates":[4.205005,51.994106],"type":"Point"}
}