{
  "type": "Feature",
  "properties": {
    "addr:full":"Beekstr 12 Fil Elburg Gelderland 8081 EC",
    "addr:housenumber":"12",
    "addr:postcode":"8081 ec",
    "addr:street":"Beekstr",
    "iso:country":"NL",
    "sg:address":"Beekstr 12 Fil",
    "sg:city":"Elburg",
    "sg:orig_category":"Warenhuizen",
    "sg:phone":"+31 525 681 320",
    "sg:postcode":"8081 EC",
    "sg:province":"Gelderland",
    "wof:name":"Hema",
    "wof:placetype":"venue"
},
  "geometry": {"coordinates":[5.8355498314,52.4477996826],"type":"Point"}
}