{
  "type": "Feature",
  "properties": {
    "addr:full":"Ln V Verhof 3 Rynsburg South Holland 2231 BZ",
    "addr:housenumber":"3",
    "addr:postcode":"2231 bz",
    "addr:street":"Ln;Verhof",
    "iso:country":"NL",
    "sg:address":"Ln V Verhof 3",
    "sg:city":"Rynsburg",
    "sg:orig_category":"Bloemen En Planten - Groothandel",
    "sg:phone":"+31 71 409 0760",
    "sg:postcode":"2231 BZ",
    "sg:province":"South Holland",
    "wof:name":"Ouwehand, Gebroeders",
    "wof:placetype":"venue"
},
  "geometry": {"coordinates":[4.443285,52.1884],"type":"Point"}
}