{
  "type": "Feature",
  "properties": {
    "iso:country":"NL",
    "sg:address":"Stadhouderslaan 76",
    "sg:city":"Soest",
    "sg:orig_category":"Diverse Bedrijfsinstallaties Gh",
    "sg:phone":"+31 35 609 0970",
    "sg:postcode":"3761 EN",
    "sg:province":"Utrecht",
    "wof:name":"Wals Systems Soest Bv",
    "wof:placetype":"venue"
},
  "geometry": {"coordinates":[5.29636,52.186283],"type":"Point"}
}