{
  "type": "Feature",
  "properties": {
    "addr:full":"G Vinckestr 2 Steenbergen Nb North Brabant 4651 DJ",
    "addr:housenumber":"2;nb",
    "addr:postcode":"4651 dj",
    "iso:country":"NL",
    "sg:address":"G Vinckestr 2",
    "sg:city":"Steenbergen Nb",
    "sg:orig_category":"Postkantoren",
    "sg:phone":"+31 167 563 533",
    "sg:postcode":"4651 DJ",
    "sg:province":"North Brabant",
    "sg:website":"http://www.postkantoor.nl",
    "wof:name":"Postkantoor",
    "wof:placetype":"venue"
},
  "geometry": {"coordinates":[4.314555,51.585594],"type":"Point"}
}