{
  "type": "Feature",
  "properties": {
    "addr:full":"Scheggertdk 54A Almen Kansas 7218 NB",
    "addr:housenumber":"54a",
    "addr:postcode":"7218 nb",
    "addr:street":"Scheggertdk",
    "iso:country":"NL",
    "sg:address":"Scheggertdk 54A",
    "sg:city":"Almen",
    "sg:orig_category":"Jachthavens - Jachtwerven",
    "sg:phone":"+31 575 432 305",
    "sg:postcode":"7218 NB",
    "sg:province":"Kansas",
    "sg:website":"http://www.arendnautic.nl",
    "wof:name":"Arend Nautic",
    "wof:placetype":"venue"
},
  "geometry": {"coordinates":[-99.706757,39.892494],"type":"Point"}
}