{
  "type": "Feature",
  "properties": {
    "iso:country":"NL",
    "sg:address":"Schillingwg 41",
    "sg:city":"Nieuw Vennep",
    "sg:orig_category":"Organisatiebureaus",
    "sg:phone":"+31 252 343 634",
    "sg:postcode":"2153 PL",
    "sg:province":"Noord-Holland",
    "sg:website":"http://www.granaada.nl",
    "wof:name":"Granaada & Partner Bv",
    "wof:placetype":"venue"
},
  "geometry": {"coordinates":[4.6293330193,52.255645752],"type":"Point"}
}