{
  "type": "Feature",
  "properties": {
    "addr:full":"Sweelinckhof 68 Terneuzen Zeeland 4536 HC",
    "addr:housenumber":"68",
    "addr:postcode":"4536 hc",
    "addr:street":"Sweelinckhof",
    "iso:country":"NL",
    "sg:address":"Sweelinckhof 68",
    "sg:city":"Terneuzen",
    "sg:orig_category":"Leesportefeuilles",
    "sg:phone":"+31 115 620 256",
    "sg:postcode":"4536 HC",
    "sg:province":"Zeeland",
    "wof:name":"L M Distry Vof",
    "wof:placetype":"venue"
},
  "geometry": {"coordinates":[3.847355,51.31723],"type":"Point"}
}