{
  "type": "Feature",
  "properties": {
    "addr:full":"Langemeetstraat 6 Hellevoetsluis South Holland 3223 BL",
    "addr:housenumber":"6",
    "addr:postcode":"3223 bl",
    "addr:street":"Langemeetstraat",
    "iso:country":"NL",
    "sg:address":"Langemeetstraat 6",
    "sg:city":"Hellevoetsluis",
    "sg:orig_category":"Bejaarden - Verzorgingstehuizen",
    "sg:phone":"+31 181 332 233",
    "sg:postcode":"3223 BL",
    "sg:province":"South Holland",
    "sg:website":"http://www.zwg.nl",
    "wof:name":"Rozenhoek, De",
    "wof:placetype":"venue"
},
  "geometry": {"coordinates":[4.146182,51.853485],"type":"Point"}
}