{
  "type": "Feature",
  "properties": {
    "addr:full":"Heuvel 24 Sint Oedenrode Noord-Brabant 5492 AD",
    "addr:housenumber":"24;oedenrode",
    "addr:postcode":"5492 ad",
    "addr:street":"Heuvel",
    "iso:country":"NL",
    "sg:address":"Heuvel 24",
    "sg:city":"Sint Oedenrode",
    "sg:orig_category":"Schoenen",
    "sg:phone":"+31 413 472 329",
    "sg:postcode":"5492 AD",
    "sg:province":"Noord-Brabant",
    "wof:name":"Termeer Schoenen",
    "wof:placetype":"venue"
},
  "geometry": {"coordinates":[5.45939,51.563072],"type":"Point"}
}