{
  "type": "Feature",
  "properties": {
    "addr:full":"Schoolstr 65 Nederweert Limburg 6031 CV",
    "addr:housenumber":"65",
    "addr:postcode":"6031 cv",
    "addr:street":"Schoolstr",
    "iso:country":"NL",
    "sg:address":"Schoolstr 65",
    "sg:city":"Nederweert",
    "sg:orig_category":"Kappers",
    "sg:phone":"+31 495 625 874",
    "sg:postcode":"6031 CV",
    "sg:province":"Limburg",
    "wof:name":"Carla, Salon",
    "wof:placetype":"venue"
},
  "geometry": {"coordinates":[5.752175808,51.286819458],"type":"Point"}
}