{
  "type": "Feature",
  "properties": {
    "addr:full":"Puntenburgerlaan 68 Amersfoort Utrecht 3812 CG",
    "addr:housenumber":"68",
    "addr:postcode":"3812 cg",
    "addr:street":"Puntenburgerlaan",
    "iso:country":"NL",
    "sg:address":"Puntenburgerlaan 68",
    "sg:city":"Amersfoort",
    "sg:orig_category":"Loodgieterswerk, Verwarming And Sanitaire Installaties",
    "sg:phone":"+31 33 463 0755",
    "sg:postcode":"3812 CG",
    "sg:province":"Utrecht",
    "wof:name":"Eshome",
    "wof:placetype":"venue"
},
  "geometry": {"coordinates":[5.375723,52.157631],"type":"Point"}
}