{
  "type": "Feature",
  "properties": {
    "addr:full":"Sebastiaanswg 1 Moerdyk Noord-Brabant 4781 PE",
    "addr:housenumber":"1",
    "addr:postcode":"4781 pe",
    "addr:street":"Sebastiaanswg",
    "iso:country":"NL",
    "sg:address":"Sebastiaanswg 1",
    "sg:city":"Moerdyk",
    "sg:classifiers":[
        {
            "category":"Travel",
            "subcategory":"Hotels & Motels",
            "type":"Entertainment"
        }
    ],
    "sg:phone":"+31 168 416 641",
    "sg:postcode":"4781 PE",
    "sg:province":"Noord-Brabant",
    "wof:name":"Holiday Inn Express",
    "wof:placetype":"venue"
},
  "geometry": {"coordinates":[4.6467,51.693569],"type":"Point"}
}