{
  "type": "Feature",
  "properties": {
    "iso:country":"NL",
    "sg:address":"Weversstraat 7",
    "sg:city":"Lelystad",
    "sg:orig_category":"Verlichting And Huishoudartikelen",
    "sg:phone":"+31 320 230 381",
    "sg:postcode":"8223 AB",
    "sg:province":"Flevoland",
    "wof:name":"Marskramer",
    "wof:placetype":"venue"
},
  "geometry": {"coordinates":[5.483493,52.519951],"type":"Point"}
}