{
  "type": "Feature",
  "properties": {
    "addr:full":"Postbus 4010 Sneek Friesland 8600 GA",
    "addr:housenumber":"4010",
    "addr:postcode":"8600 ga",
    "addr:street":"Postbus",
    "iso:country":"NL",
    "sg:address":"Postbus 4010",
    "sg:city":"Sneek",
    "sg:orig_category":"Adviesbureaus Bedrijfsorganisatie",
    "sg:phone":"+31 515 432 440",
    "sg:postcode":"8600 GA",
    "sg:province":"Friesland",
    "sg:website":"http://www.bulthuis-berndsen.nl",
    "wof:name":"Bulthuis & Berndsen",
    "wof:placetype":"venue"
},
  "geometry": {"coordinates":[5.66197,53.033459],"type":"Point"}
}