{
  "type": "Feature",
  "properties": {
    "addr:full":"Coloradodreef 24 Utrecht Utrecht 3565 BT",
    "addr:housenumber":"24",
    "addr:postcode":"3565 bt",
    "addr:street":"Coloradodreef",
    "iso:country":"NL",
    "sg:address":"Coloradodreef 24",
    "sg:city":"Utrecht",
    "sg:orig_category":"Verf En Lak - Fabrieken En Groothandel",
    "sg:phone":"+31 30 262 2441",
    "sg:postcode":"3565 BT",
    "sg:province":"Utrecht",
    "wof:name":"Gramkow",
    "wof:placetype":"venue"
},
  "geometry": {"coordinates":[5.088504,52.125092],"type":"Point"}
}