{
  "type": "Feature",
  "properties": {
    "iso:country":"NL",
    "sg:address":"Breestraat 165",
    "sg:city":"Beverwijk",
    "sg:classifiers":[
        {
            "category":"Retail",
            "subcategory":"Photofinishing",
            "type":"Services"
        }
    ],
    "sg:phone":"+31 251 213 630",
    "sg:postcode":"1941 EH",
    "sg:province":"Noord-Holland",
    "sg:tags":[
        "foto",
        "film"
    ],
    "wof:name":"Foto Andre",
    "wof:placetype":"venue"
},
  "geometry": {"coordinates":[4.660777,52.483433],"type":"Point"}
}