{
  "type": "Feature",
  "properties": {
    "addr:full":"Hoofdstraat 103-105 Stadskanaal Groningen 9501 CR",
    "addr:housenumber":"103-105",
    "addr:postcode":"9501 cr",
    "addr:street":"Hoofdstraat",
    "iso:country":"NL",
    "sg:address":"Hoofdstraat 103-105",
    "sg:city":"Stadskanaal",
    "sg:orig_category":"Bloemen And Planten",
    "sg:phone":"+31 599 616 114",
    "sg:postcode":"9501 CR",
    "sg:province":"Groningen",
    "wof:name":"Bloemenhuis Margreet",
    "wof:placetype":"venue"
},
  "geometry": {"coordinates":[6.960637,52.982231],"type":"Point"}
}