{
  "type": "Feature",
  "properties": {
    "iso:country":"NL",
    "sg:address":"Blokmaalder 10",
    "sg:city":"Wormer",
    "sg:orig_category":"Begrafenisondernemers",
    "sg:phone":"+31 75 642 3597",
    "sg:postcode":"1531 PG",
    "sg:province":"Noord-Holland",
    "wof:name":"Begrafenisvereniging St. Barbara",
    "wof:placetype":"venue"
},
  "geometry": {"coordinates":[4.812272,52.491844],"type":"Point"}
}