{
  "type": "Feature",
  "properties": {
    "addr:full":"De Waterdief 83 Uitgeest Noord-Holland 1911 JP",
    "addr:housenumber":"83",
    "addr:postcode":"1911 jp",
    "addr:street":"De Waterdief",
    "iso:country":"NL",
    "sg:address":"De Waterdief 83",
    "sg:city":"Uitgeest",
    "sg:classifiers":[
        {
            "category":"Personal",
            "subcategory":"Nail Salon",
            "type":"Services"
        }
    ],
    "sg:phone":"+31 251 320 551",
    "sg:postcode":"1911 JP",
    "sg:province":"Noord-Holland",
    "sg:tags":[
        "pedicure"
    ],
    "wof:name":"Bruijne, E M",
    "wof:placetype":"venue"
},
  "geometry": {"coordinates":[4.698574,52.518497],"type":"Point"}
}