{
  "type": "Feature",
  "properties": {
    "iso:country":"NL",
    "sg:address":"Lijtweg 8",
    "sg:city":"Oegstgeest",
    "sg:orig_category":"Banken And Kredietinstellingen",
    "sg:phone":"+31 71 517 0462",
    "sg:postcode":"2341 HA",
    "sg:province":"South Holland",
    "wof:name":"Fortis Bank",
    "wof:placetype":"venue"
},
  "geometry": {"coordinates":[4.470446,52.184757],"type":"Point"}
}