{
  "type": "Feature",
  "properties": {
    "addr:full":"Contactweg 36 Amsterdam Noord-Holland 1014 AN",
    "addr:housenumber":"36",
    "addr:postcode":"1014 an",
    "addr:street":"Contactweg",
    "iso:country":"NL",
    "sg:address":"Contactweg 36",
    "sg:city":"Amsterdam",
    "sg:orig_category":"Volwassenenonderwijs",
    "sg:phone":"+31 20 606 2001",
    "sg:postcode":"1014 AN",
    "sg:province":"Noord-Holland",
    "wof:name":"Grafisch Lyceum Amsterdam",
    "wof:placetype":"venue"
},
  "geometry": {"coordinates":[4.855586,52.390591],"type":"Point"}
}