{
  "type": "Feature",
  "properties": {
    "addr:full":"Churchill-Laan 21 Harderwijk Gelderland 3844 BK",
    "addr:housenumber":"21",
    "addr:postcode":"3844 bk",
    "addr:street":"Churchill-Laan;Gelderland",
    "iso:country":"NL",
    "sg:address":"Churchill-Laan 21",
    "sg:city":"Harderwijk",
    "sg:orig_category":"Drukkerijen And Copyshops",
    "sg:phone":"+31 341 416 280",
    "sg:postcode":"3844 BK",
    "sg:province":"Gelderland",
    "wof:name":"Stencil- En Offsetburo Alco",
    "wof:placetype":"venue"
},
  "geometry": {"coordinates":[5.61855,52.336205],"type":"Point"}
}