{
  "type": "Feature",
  "properties": {
    "addr:full":"Voltastraat 2 Schoonhoven Zuid-Holland 2871 ZN",
    "addr:housenumber":"2",
    "addr:postcode":"2871 zn",
    "addr:street":"Voltastraat",
    "iso:country":"NL",
    "sg:address":"Voltastraat 2",
    "sg:city":"Schoonhoven",
    "sg:classifiers":[
        {
            "category":"Education",
            "subcategory":"Preschool",
            "type":"Public Place"
        }
    ],
    "sg:phone":"+31 182 380 978",
    "sg:postcode":"2871 ZN",
    "sg:province":"Zuid-Holland",
    "sg:tags":[
        "kleuteronderwijs",
        "basis-"
    ],
    "wof:name":"Obs De Vlieger",
    "wof:placetype":"venue"
},
  "geometry": {"coordinates":[4.839735,51.951809],"type":"Point"}
}