{
  "type": "Feature",
  "properties": {
    "iso:country":"NL",
    "sg:address":"Grotestraat 26",
    "sg:city":"Beers Nb",
    "sg:orig_category":"Verzekeringen",
    "sg:phone":"+31 485 315 145",
    "sg:postcode":"5437 AS",
    "sg:province":"Noord-Brabant",
    "wof:name":"J.Th. Pas Verzekeringen",
    "wof:placetype":"venue"
},
  "geometry": {"coordinates":[5.828668,51.724815],"type":"Point"}
}