{
  "type": "Feature",
  "properties": {
    "addr:full":"Zonneweide 13 'S Heerenberg Gelderland 7041 DC",
    "addr:housenumber":"13",
    "addr:postcode":"7041",
    "addr:street":"Zonneweide;' S Heerenberg Gelderland",
    "iso:country":"NL",
    "sg:address":"Zonneweide 13",
    "sg:city":"'S Heerenberg",
    "sg:orig_category":"Boekhouders",
    "sg:phone":"+31 314 665 970",
    "sg:postcode":"7041 DC",
    "sg:province":"Gelderland",
    "wof:name":"Administratiekantoor Giezenaar",
    "wof:placetype":"venue"
},
  "geometry": {"coordinates":[6.257398,51.881321],"type":"Point"}
}