{
  "type": "Feature",
  "properties": {
    "iso:country":"NL",
    "sg:address":"Valutaboulevard 21",
    "sg:city":"Amsterdam",
    "sg:orig_category":"Schilders",
    "sg:phone":"+31 20 619 9627",
    "sg:postcode":"1060 RX",
    "sg:province":"Noord-Holland",
    "wof:name":"Buitenboard",
    "wof:placetype":"venue"
},
  "geometry": {"coordinates":[4.788633,52.348377],"type":"Point"}
}