{
  "type": "Feature",
  "properties": {
    "addr:full":"Wierdensestraat 159 Almelo Overijssel 7604 BH",
    "addr:housenumber":"159",
    "addr:postcode":"7604 bh",
    "addr:street":"Wierdensestraat",
    "iso:country":"NL",
    "sg:address":"Wierdensestraat 159",
    "sg:city":"Almelo",
    "sg:orig_category":"Elektronische Bedrijfsinstallaties",
    "sg:phone":"+31 546 455 582",
    "sg:postcode":"7604 BH",
    "sg:province":"Overijssel",
    "wof:name":"Cipo Beveiliging",
    "wof:placetype":"venue"
},
  "geometry": {"coordinates":[6.627135,52.356209],"type":"Point"}
}