{
  "type": "Feature",
  "properties": {
    "addr:full":"Postbus 4558 Eindhoven Noord-Brabant 5601 EN",
    "addr:housenumber":"4558",
    "addr:postcode":"5601 en",
    "addr:street":"Postbus",
    "iso:country":"NL",
    "sg:address":"Postbus 4558",
    "sg:city":"Eindhoven",
    "sg:orig_category":"Adviesbureaus",
    "sg:phone":"+31 6 21866392",
    "sg:postcode":"5601 EN",
    "sg:province":"Noord-Brabant",
    "wof:name":"Pcs",
    "wof:placetype":"venue"
},
  "geometry": {"coordinates":[5.48016,51.437061],"type":"Point"}
}