{
  "type": "Feature",
  "properties": {
    "addr:full":"Aabeekstraat 28 Goirle North Brabant 5051 VP",
    "addr:housenumber":"28",
    "addr:postcode":"5051 vp",
    "addr:street":"Aabeekstraat",
    "iso:country":"NL",
    "sg:address":"Aabeekstraat 28",
    "sg:city":"Goirle",
    "sg:orig_category":"Verhuur Bouwmachines",
    "sg:phone":"+31 13 534 4062",
    "sg:postcode":"5051 VP",
    "sg:province":"North Brabant",
    "wof:name":"H.B. Ligtvoet",
    "wof:placetype":"venue"
},
  "geometry": {"coordinates":[5.0736,51.522488],"type":"Point"}
}