{
  "type": "Feature",
  "properties": {
    "addr:full":"Marktstr 10 Helmond Noord-Brabant 5701 RN",
    "addr:housenumber":"10",
    "addr:postcode":"5701 rn",
    "addr:street":"Marktstr",
    "iso:country":"NL",
    "sg:address":"Marktstr 10",
    "sg:city":"Helmond",
    "sg:orig_category":"Meubelen",
    "sg:phone":"+31 492 524 929",
    "sg:postcode":"5701 RN",
    "sg:province":"Noord-Brabant",
    "wof:name":"Lantaarn Woonwinkel, De",
    "wof:placetype":"venue"
},
  "geometry": {"coordinates":[5.657637,51.481197],"type":"Point"}
}