{
  "type": "Feature",
  "properties": {
    "addr:full":"Prinses Margrietlaan 4-6 Alphen Aan Den Rijn South Holland 2404 HA",
    "addr:housenumber":"4-6",
    "addr:postcode":"2404 ha",
    "addr:street":"Prinses Margrietlaan",
    "iso:country":"NL",
    "sg:address":"Prinses Margrietlaan 4-6",
    "sg:city":"Alphen Aan Den Rijn",
    "sg:orig_category":"Personenvervoer Zonder Dienstregeling",
    "sg:phone":"+31 172 460 000",
    "sg:postcode":"2404 HA",
    "sg:province":"South Holland",
    "wof:name":"Autoverhuur Overbeek",
    "wof:placetype":"venue"
},
  "geometry": {"coordinates":[4.64927,52.135406],"type":"Point"}
}