{
  "type": "Feature",
  "properties": {
    "addr:full":"Mulderskolk 10 Leusden Utrecht 3833 KR",
    "addr:housenumber":"10",
    "addr:postcode":"3833 kr",
    "addr:street":"Mulderskolk",
    "iso:country":"NL",
    "sg:address":"Mulderskolk 10",
    "sg:city":"Leusden",
    "sg:orig_category":"Nagelstudio'S",
    "sg:phone":"+31 33 432 2030",
    "sg:postcode":"3833 KR",
    "sg:province":"Utrecht",
    "sg:website":"http://www.anastashia.nl",
    "wof:name":"Anastashia",
    "wof:placetype":"venue"
},
  "geometry": {"coordinates":[5.421565,52.123749],"type":"Point"}
}