{
  "type": "Feature",
  "properties": {
    "addr:full":"Linge 24 Veenendaal Utrecht 3904 NB",
    "addr:housenumber":"24",
    "addr:postcode":"3904 nb",
    "addr:street":"Linge",
    "iso:country":"NL",
    "sg:address":"Linge 24",
    "sg:city":"Veenendaal",
    "sg:orig_category":"Kunsthandel",
    "sg:phone":"+31 318 589 642",
    "sg:postcode":"3904 NB",
    "sg:province":"Utrecht",
    "wof:name":"Pampus-Art",
    "wof:placetype":"venue"
},
  "geometry": {"coordinates":[5.531495,52.022736],"type":"Point"}
}