{
  "type": "Feature",
  "properties": {
    "addr:full":"Grotestr 106 Almelo NL.08 7607 CV",
    "addr:housenumber":"106;nl.08",
    "addr:postcode":"7607 cv",
    "iso:country":"NL",
    "sg:address":"Grotestr 106",
    "sg:city":"Almelo",
    "sg:orig_category":"Bloemen En Planten",
    "sg:phone":"+31 546 455 221",
    "sg:postcode":"7607 CV",
    "sg:province":"NL.08",
    "wof:name":"Bloemenrijk, Het",
    "wof:placetype":"venue"
},
  "geometry": {"coordinates":[6.666218,52.355042],"type":"Point"}
}