{
  "type": "Feature",
  "properties": {
    "addr:full":"Kerkstr 96 Hilversum North Holland 1211 CS",
    "addr:housenumber":"96",
    "addr:postcode":"1211 cs",
    "addr:street":"Kerkstr",
    "iso:country":"NL",
    "sg:address":"Kerkstr 96",
    "sg:city":"Hilversum",
    "sg:orig_category":"Juweliers",
    "sg:phone":"+31 35 624 5867",
    "sg:postcode":"1211 CS",
    "sg:province":"North Holland",
    "wof:name":"Rutgers Juwelier Horloger",
    "wof:placetype":"venue"
},
  "geometry": {"coordinates":[5.1695,52.228565],"type":"Point"}
}