{
  "type": "Feature",
  "properties": {
    "iso:country":"NL",
    "sg:address":"Moerasakker 1",
    "sg:city":"Noord-Scharwoude",
    "sg:orig_category":"Boekhouders",
    "sg:phone":"+31 226 340 270",
    "sg:postcode":"1723 BJ",
    "sg:province":"Noord-Holland",
    "wof:name":"Administratiekantoor Boersma",
    "wof:placetype":"venue"
},
  "geometry": {"coordinates":[4.803319,52.697578],"type":"Point"}
}