{
  "type": "Feature",
  "properties": {
    "addr:full":"Ketel 23 Urk Flevoland 8321 RE",
    "addr:housenumber":"23",
    "addr:postcode":"8321",
    "addr:street":"Ketel;Flevoland",
    "iso:country":"NL",
    "sg:address":"Ketel 23",
    "sg:city":"Urk",
    "sg:orig_category":"Loodgieterswerk, Verwarming And Sanitaire Installaties",
    "sg:phone":"+31 527 684 180",
    "sg:postcode":"8321 RE",
    "sg:province":"Flevoland",
    "wof:name":"Ide Bakker",
    "wof:placetype":"venue"
},
  "geometry": {"coordinates":[5.618136,52.663128],"type":"Point"}
}