{
  "type": "Feature",
  "properties": {
    "addr:full":"De Dinkel 13 Hattem Gelderland 8051 KA",
    "addr:housenumber":"13",
    "addr:postcode":"8051 ka",
    "addr:street":"De Dinkel;Gelderland",
    "iso:country":"NL",
    "sg:address":"De Dinkel 13",
    "sg:city":"Hattem",
    "sg:orig_category":"Modellenbureaus",
    "sg:phone":"+31 38 444 5377",
    "sg:postcode":"8051 KA",
    "sg:province":"Gelderland",
    "wof:name":"Maps - Mode! Advies Promotie Shows",
    "wof:placetype":"venue"
},
  "geometry": {"coordinates":[6.053127,52.477867],"type":"Point"}
}