{
  "type": "Feature",
  "properties": {
    "addr:full":"Haagwg 270 Breda Noord-Brabant 4812 XG",
    "addr:housenumber":"270",
    "addr:postcode":"4812 xg",
    "iso:country":"NL",
    "sg:address":"Haagwg 270",
    "sg:city":"Breda",
    "sg:orig_category":"Meubelstoffering",
    "sg:phone":"+31 76 561 2216",
    "sg:postcode":"4812 XG",
    "sg:province":"Noord-Brabant",
    "wof:name":"Glabbeek Vof, P E Van",
    "wof:placetype":"venue"
},
  "geometry": {"coordinates":[4.754327,51.580196],"type":"Point"}
}