{
  "type": "Feature",
  "properties": {
    "addr:full":"Kaldenkerkerwg 129 Tegelen Limburg 5932 DA",
    "addr:housenumber":"129",
    "addr:postcode":"5932 da",
    "iso:country":"NL",
    "sg:address":"Kaldenkerkerwg 129",
    "sg:city":"Tegelen",
    "sg:orig_category":"Bestratingen",
    "sg:phone":"+31 77 373 1859",
    "sg:postcode":"5932 DA",
    "sg:province":"Limburg",
    "wof:name":"Smolenaers",
    "wof:placetype":"venue"
},
  "geometry": {"coordinates":[6.161009,51.333511],"type":"Point"}
}