{
  "type": "Feature",
  "properties": {
    "addr:full":"Wg-Plein 380 Amsterdam Noord-Holland 1054 SG",
    "addr:housenumber":"380",
    "addr:postcode":"1054 sg",
    "addr:street":"Wg-Plein",
    "iso:country":"NL",
    "sg:address":"Wg-Plein 380",
    "sg:city":"Amsterdam",
    "sg:orig_category":"Boekenuitgeverijen",
    "sg:phone":"+31 20 689 8468",
    "sg:postcode":"1054 SG",
    "sg:province":"Noord-Holland",
    "wof:name":"Vita Leven",
    "wof:placetype":"venue"
},
  "geometry": {"coordinates":[4.871368,52.364368],"type":"Point"}
}