{
  "type": "Feature",
  "properties": {
    "iso:country":"NL",
    "sg:address":"Kievitstraat 3",
    "sg:city":"Alphen A/D Rijn",
    "sg:orig_category":"Schilderwerk",
    "sg:phone":"+31 172 479 381",
    "sg:postcode":"2406 ER",
    "sg:province":"Zuid-Holland",
    "wof:name":"Finish",
    "wof:placetype":"venue"
},
  "geometry": {"coordinates":[4.668637,52.132435],"type":"Point"}
}