{
  "type": "Feature",
  "properties": {
    "addr:full":"Postwg 33 De Lutte Overijssel 7587 PB",
    "addr:housenumber":"33",
    "addr:postcode":"7587 pb",
    "addr:street":"Postwg",
    "iso:country":"NL",
    "sg:address":"Postwg 33",
    "sg:city":"De Lutte",
    "sg:orig_category":"Huifkarren - Verhuur En Verkoop",
    "sg:phone":"+31 541 552 110",
    "sg:postcode":"7587 PB",
    "sg:province":"Overijssel",
    "wof:name":"Luts, Huifkarrenverhuur De",
    "wof:placetype":"venue"
},
  "geometry": {"coordinates":[6.985185,52.302242],"type":"Point"}
}