{
  "type": "Feature",
  "properties": {
    "addr:full":"Reinaldstr 7 Arnhem Gelderland 6824 GN",
    "addr:housenumber":"7",
    "addr:postcode":"6824 gn",
    "addr:street":"Reinaldstr",
    "iso:country":"NL",
    "sg:address":"Reinaldstr 7",
    "sg:city":"Arnhem",
    "sg:orig_category":"Onroerende Goederen",
    "sg:phone":"+31 26 364 9439",
    "sg:postcode":"6824 GN",
    "sg:province":"Gelderland",
    "wof:name":"Peters",
    "wof:placetype":"venue"
},
  "geometry": {"coordinates":[5.941579,51.98888],"type":"Point"}
}