{
  "type": "Feature",
  "properties": {
    "addr:full":"Friese Varkenmarkt 22 Haarlem Noord-Holland 2011 JA",
    "addr:housenumber":"22",
    "addr:postcode":"2011 ja",
    "addr:street":"Friese Varkenmarkt",
    "iso:country":"NL",
    "sg:address":"Friese Varkenmarkt 22",
    "sg:city":"Haarlem",
    "sg:classifiers":[
        {
            "category":"Fast Food",
            "type":"Food & Drink"
        }
    ],
    "sg:phone":"+31 23 532 7765",
    "sg:postcode":"2011 JA",
    "sg:province":"Noord-Holland",
    "sg:tags":[
        "afhaal",
        "restaurant"
    ],
    "wof:name":"Vof Viskiosk Balk",
    "wof:placetype":"venue"
},
  "geometry": {"coordinates":[4.644608,52.385651],"type":"Point"}
}