{
  "type": "Feature",
  "properties": {
    "addr:full":"Bos En Lommerwg 163 Amsterdam North Holland 1055 DS",
    "addr:housenumber":"163",
    "addr:postcode":"1055 ds",
    "addr:street":"Bos En Lommerwg",
    "iso:country":"NL",
    "sg:address":"Bos En Lommerwg 163",
    "sg:city":"Amsterdam",
    "sg:orig_category":"Koffie- En Theehuizen",
    "sg:phone":"+31 20 688 0715",
    "sg:postcode":"1055 DS",
    "sg:province":"North Holland",
    "wof:name":"Risky",
    "wof:placetype":"venue"
},
  "geometry": {"coordinates":[4.85594,52.381435],"type":"Point"}
}