{
  "type": "Feature",
  "properties": {
    "addr:full":"Korhoenln 1 Ede Gld Gelderland 6713 BL",
    "addr:housenumber":"1;6713 bl",
    "addr:street":"Korhoenln;Gld Gelderland",
    "iso:country":"NL",
    "sg:address":"Korhoenln 1",
    "sg:city":"Ede Gld",
    "sg:classifiers":[
        {
            "category":"Wholesale",
            "subcategory":"Motor Vehicles",
            "type":"Manufacturing & Wholesale Goods"
        }
    ],
    "sg:phone":"+31 318 619 608",
    "sg:postcode":"6713 BL",
    "sg:province":"Gelderland",
    "sg:tags":[
        "scooter",
        "en"
    ],
    "wof:name":"Beukhof",
    "wof:placetype":"venue"
},
  "geometry": {"coordinates":[5.6591,52.040928],"type":"Point"}
}