{
  "type": "Feature",
  "properties": {
    "addr:full":"Hoofdweg 111 De Kwakel North Holland 1424 PE",
    "addr:housenumber":"111",
    "addr:postcode":"1424 pe",
    "addr:street":"Hoofdweg",
    "iso:country":"NL",
    "sg:address":"Hoofdweg 111",
    "sg:city":"De Kwakel",
    "sg:orig_category":"Bloemen En Planten - Groothandel",
    "sg:phone":"+31 297 363 163",
    "sg:postcode":"1424 PE",
    "sg:province":"North Holland",
    "sg:website":"http://www.nieuwkoop-dekwakel.nl",
    "wof:name":"Nieuwkoop De Kwakel Bv",
    "wof:placetype":"venue"
},
  "geometry": {"coordinates":[4.774069,52.241333],"type":"Point"}
}