{
  "type": "Feature",
  "properties": {
    "addr:full":"Scheldestr 2 Velp Gld Gelderland 6882 NE",
    "addr:housenumber":"2;6882",
    "addr:street":"Scheldestr;Gld Gelderland;Ne",
    "iso:country":"NL",
    "sg:address":"Scheldestr 2",
    "sg:city":"Velp Gld",
    "sg:orig_category":"Acupunctuur",
    "sg:phone":"+31 26 362 0636",
    "sg:postcode":"6882 NE",
    "sg:province":"Gelderland",
    "wof:name":"Gr?newald",
    "wof:placetype":"venue"
},
  "geometry": {"coordinates":[5.97811,51.990761],"type":"Point"}
}