{
  "type": "Feature",
  "properties": {
    "addr:full":"Schuddebeursstraat 2 Middelburg Zeeland 4331 GT",
    "addr:housenumber":"2",
    "addr:postcode":"4331 gt",
    "addr:street":"Schuddebeursstraat",
    "iso:country":"NL",
    "sg:address":"Schuddebeursstraat 2",
    "sg:city":"Middelburg",
    "sg:orig_category":"Binnenhuisarchitecten",
    "sg:phone":"+31 118 614 569",
    "sg:postcode":"4331 GT",
    "sg:province":"Zeeland",
    "wof:name":"Adviesstudio Pieter Zijnen En Partner",
    "wof:placetype":"venue"
},
  "geometry": {"coordinates":[3.619252,51.500057],"type":"Point"}
}