{
  "type": "Feature",
  "properties": {
    "addr:full":"S Gravendamsewg 19 Noordwykerhout Zuid-Holland 2211 WG",
    "addr:housenumber":"19",
    "addr:postcode":"2211 wg",
    "iso:country":"NL",
    "sg:address":"S Gravendamsewg 19",
    "sg:city":"Noordwykerhout",
    "sg:orig_category":"Metselwerken",
    "sg:phone":"+31 252 377 392",
    "sg:postcode":"2211 WG",
    "sg:province":"Zuid-Holland",
    "wof:name":"Poel, J A M Van Der",
    "wof:placetype":"venue"
},
  "geometry": {"coordinates":[4.494252,52.245449],"type":"Point"}
}