{
  "type": "Feature",
  "properties": {
    "addr:full":"Dintel 27 Tilburg Noord-Brabant 5032 CM",
    "addr:housenumber":"27",
    "addr:postcode":"5032 cm",
    "addr:street":"Dintel",
    "iso:country":"NL",
    "sg:address":"Dintel 27",
    "sg:city":"Tilburg",
    "sg:orig_category":"Adviesbureaus",
    "sg:phone":"+31 13 468 1965",
    "sg:postcode":"5032 CM",
    "sg:province":"Noord-Brabant",
    "wof:name":"Manders",
    "wof:placetype":"venue"
},
  "geometry": {"coordinates":[5.032314,51.542744],"type":"Point"}
}