{
  "type": "Feature",
  "properties": {
    "iso:country":"NL",
    "sg:address":"Handelstr 63",
    "sg:city":"Utrecht",
    "sg:orig_category":"Herenkleding",
    "sg:phone":"+31 30 293 2775",
    "sg:postcode":"3533 GH",
    "sg:province":"Utrecht",
    "wof:name":"Bastiaanse, Peter",
    "wof:placetype":"venue"
},
  "geometry": {"coordinates":[5.085605,52.086674],"type":"Point"}
}