{
  "type": "Feature",
  "properties": {
    "addr:full":"Spaarne 61 B Haarlem Noord-Holland 2011 CG",
    "addr:housenumber":"61 b",
    "addr:postcode":"2011 cg",
    "addr:street":"Spaarne",
    "iso:country":"NL",
    "sg:address":"Spaarne 61 B",
    "sg:city":"Haarlem",
    "sg:orig_category":"Fotostudio'S And Fotografen",
    "sg:phone":"+31 23 536 8776",
    "sg:postcode":"2011 CG",
    "sg:province":"Noord-Holland",
    "wof:name":"J & J Fotografie",
    "wof:placetype":"venue"
},
  "geometry": {"coordinates":[4.638747,52.378441],"type":"Point"}
}