{
  "type": "Feature",
  "properties": {
    "addr:full":"Stationsstraat 19 Bergen Op Zoom Noord-Brabant 4611 CB",
    "addr:housenumber":"19",
    "addr:postcode":"4611 cb",
    "addr:street":"Stationsstraat",
    "iso:country":"NL",
    "sg:address":"Stationsstraat 19",
    "sg:city":"Bergen Op Zoom",
    "sg:orig_category":"Advocaten And Juridische Adviseurs",
    "sg:phone":"+31 164 211 311",
    "sg:postcode":"4611 CB",
    "sg:province":"Noord-Brabant",
    "wof:name":"Van Ginneken Schute & Haans Cs Advocaten",
    "wof:placetype":"venue"
},
  "geometry": {"coordinates":[4.294499,51.495213],"type":"Point"}
}