{
  "type": "Feature",
  "properties": {
    "addr:full":"Koorman 5 Groenlo Gelderland 7141 NP",
    "addr:housenumber":"5",
    "addr:postcode":"7141 np",
    "addr:street":"Koorman;Gelderland",
    "iso:country":"NL",
    "sg:address":"Koorman 5",
    "sg:city":"Groenlo",
    "sg:classifiers":[
        {
            "category":"Personal",
            "subcategory":"Nail Salon",
            "type":"Services"
        }
    ],
    "sg:phone":"+31 544 466 044",
    "sg:postcode":"7141 NP",
    "sg:province":"Gelderland",
    "sg:tags":[
        "pedicure"
    ],
    "wof:name":"Dykman Reijrink, Jacqueline",
    "wof:placetype":"venue"
},
  "geometry": {"coordinates":[6.608893,52.034794],"type":"Point"}
}