{
  "type": "Feature",
  "properties": {
    "addr:full":"Stationsstr 15 Tilburg North Brabant 5038 EB",
    "addr:housenumber":"15",
    "addr:postcode":"5038 eb",
    "addr:street":"Stationsstr",
    "iso:country":"NL",
    "sg:address":"Stationsstr 15",
    "sg:city":"Tilburg",
    "sg:orig_category":"Verenigingen En Stichtingen",
    "sg:phone":"+31 13 535 1535",
    "sg:postcode":"5038 EB",
    "sg:province":"North Brabant",
    "wof:name":"Pon",
    "wof:placetype":"venue"
},
  "geometry": {"coordinates":[5.082519,51.559406],"type":"Point"}
}