{
  "type": "Feature",
  "properties": {
    "addr:full":"Klaaskampen 6A Laren Nh Noord-Holland 1251 KP",
    "addr:housenumber":"6a",
    "addr:postcode":"1251 kp",
    "addr:street":"Klaaskampen",
    "iso:country":"NL",
    "sg:address":"Klaaskampen 6A",
    "sg:city":"Laren Nh",
    "sg:orig_category":"Herenkleding - Groothandel",
    "sg:phone":"+31 35 539 5500",
    "sg:postcode":"1251 KP",
    "sg:province":"Noord-Holland",
    "wof:name":"Elshof Bv",
    "wof:placetype":"venue"
},
  "geometry": {"coordinates":[5.223532,52.255978],"type":"Point"}
}