{
  "type": "Feature",
  "properties": {
    "addr:full":"Blauwwater 14 Belfeld Limburg 5951 DB",
    "addr:housenumber":"14",
    "addr:postcode":"5951 db",
    "addr:street":"Blauwwater",
    "iso:country":"NL",
    "sg:address":"Blauwwater 14",
    "sg:city":"Belfeld",
    "sg:orig_category":"Machinehandel",
    "sg:phone":"+31 77 475 1515",
    "sg:postcode":"5951 DB",
    "sg:province":"Limburg",
    "wof:name":"Tact Venlo Bv",
    "wof:placetype":"venue"
},
  "geometry": {"coordinates":[6.122928,51.318386],"type":"Point"}
}