{
  "type": "Feature",
  "properties": {
    "iso:country":"NL",
    "sg:address":"Woldpromenade 9",
    "sg:city":"Steenwijk",
    "sg:orig_category":"Gespecialiseerde Voeding",
    "sg:phone":"+31 521 510 883",
    "sg:postcode":"8331 JD",
    "sg:province":"NL.08",
    "wof:name":"Poeliersbedrijf En Toko Vos",
    "wof:placetype":"venue"
},
  "geometry": {"coordinates":[6.113771,52.786594],"type":"Point"}
}