{
  "type": "Feature",
  "properties": {
    "addr:full":"Lijndonk 7 Molenschot North Brabant 5124 RK",
    "addr:housenumber":"7",
    "addr:postcode":"5124 rk",
    "addr:street":"Lijndonk",
    "iso:country":"NL",
    "sg:address":"Lijndonk 7",
    "sg:city":"Molenschot",
    "sg:orig_category":"Goederenvervoer Over De Weg",
    "sg:phone":"+31 161 412 679",
    "sg:postcode":"5124 RK",
    "sg:province":"North Brabant",
    "wof:name":"J.D.C. Van Mook-Touw",
    "wof:placetype":"venue"
},
  "geometry": {"coordinates":[4.883949,51.565639],"type":"Point"}
}