{
  "type": "Feature",
  "properties": {
    "addr:full":"Passage 24 S Gravenhage South Holland 2511 AD",
    "addr:housenumber":"24",
    "addr:postcode":"2511 ad",
    "addr:street":"Passage;S Gravenhage",
    "iso:country":"NL",
    "sg:address":"Passage 24",
    "sg:city":"S Gravenhage",
    "sg:orig_category":"Koffie En Thee - Apparaten En Artikelen",
    "sg:phone":"+31 70 346 5534",
    "sg:postcode":"2511 AD",
    "sg:province":"South Holland",
    "sg:website":"http://www.simonlevelt.nl",
    "wof:name":"Simon L\u00e9velt",
    "wof:placetype":"venue"
},
  "geometry": {"coordinates":[4.31627,52.07896],"type":"Point"}
}