{
  "type": "Feature",
  "properties": {
    "addr:full":"Hartelstein 2 Weert Limburg 6002 VL",
    "addr:housenumber":"2",
    "addr:postcode":"6002 vl",
    "addr:street":"Hartelstein",
    "iso:country":"NL",
    "sg:address":"Hartelstein 2",
    "sg:city":"Weert",
    "sg:orig_category":"Vertaalbureaus",
    "sg:phone":"+31 495 534 014",
    "sg:postcode":"6002 VL",
    "sg:province":"Limburg",
    "wof:name":"Hajo, Translations",
    "wof:placetype":"venue"
},
  "geometry": {"coordinates":[5.689764,51.259506],"type":"Point"}
}