{
  "type": "Feature",
  "properties": {
    "addr:full":"Obbichterstraat 2 Urmond Limburg 6129 AS",
    "addr:housenumber":"2",
    "addr:postcode":"6129 as",
    "addr:street":"Obbichterstraat",
    "iso:country":"NL",
    "sg:address":"Obbichterstraat 2",
    "sg:city":"Urmond",
    "sg:classifiers":[
        {
            "category":"Bakery",
            "type":"Food & Drink"
        }
    ],
    "sg:phone":"+31 46 433 3621",
    "sg:postcode":"6129 AS",
    "sg:province":"Limburg",
    "sg:tags":[
        "brood",
        "banket"
    ],
    "wof:name":"Kwaliteitsbakkerij Steevens / W H J Krau",
    "wof:placetype":"venue"
},
  "geometry": {"coordinates":[5.772131,51.00499],"type":"Point"}
}