{
  "type": "Feature",
  "properties": {
    "addr:full":"Valkenburgerstr 120A Amsterdam Noord-Holland 1011 NA",
    "addr:housenumber":"120a",
    "addr:postcode":"1011 na",
    "iso:country":"NL",
    "sg:address":"Valkenburgerstr 120A",
    "sg:city":"Amsterdam",
    "sg:orig_category":"Beeldende Kunstenaars",
    "sg:phone":"+31 20 624 9930",
    "sg:postcode":"1011 NA",
    "sg:province":"Noord-Holland",
    "wof:name":"Perlmuter, P",
    "wof:placetype":"venue"
},
  "geometry": {"coordinates":[4.906618,52.369717],"type":"Point"}
}