{
  "type": "Feature",
  "properties": {
    "addr:full":"Ds Janzoniusstr 13 Moordrecht Zuid-Holland 2841 SM",
    "addr:housenumber":"13",
    "addr:postcode":"2841 sm",
    "addr:street":"Ds Janzoniusstr",
    "iso:country":"NL",
    "sg:address":"Ds Janzoniusstr 13",
    "sg:city":"Moordrecht",
    "sg:orig_category":"Beeldende Kunstenaars",
    "sg:phone":"+31 182 379 398",
    "sg:postcode":"2841 SM",
    "sg:province":"Zuid-Holland",
    "wof:name":"Yovach",
    "wof:placetype":"venue"
},
  "geometry": {"coordinates":[4.663023,51.987507],"type":"Point"}
}