{
  "type": "Feature",
  "properties": {
    "addr:full":"Vyfhuizenbaan 6A Riel North Brabant 5133 NH",
    "addr:housenumber":"6a",
    "addr:postcode":"5133 nh",
    "addr:street":"Vyfhuizenbaan",
    "iso:country":"NL",
    "sg:address":"Vyfhuizenbaan 6A",
    "sg:city":"Riel",
    "sg:orig_category":"Hoefsmederijen",
    "sg:phone":"+31 6 20431709",
    "sg:postcode":"5133 NH",
    "sg:province":"North Brabant",
    "wof:name":"Huijgenvoort, Paul Van",
    "wof:placetype":"venue"
},
  "geometry": {"coordinates":[5.003588,51.521656],"type":"Point"}
}