{
  "type": "Feature",
  "properties": {
    "iso:country":"NL",
    "sg:address":"Amsterdamseweg 196",
    "sg:city":"Amstelveen",
    "sg:orig_category":"Kappers",
    "sg:phone":"+31 20 641 1911",
    "sg:postcode":"1182 HL",
    "sg:province":"North Holland",
    "wof:name":"T.J. Kelly Hairdesign Vof",
    "wof:placetype":"venue"
},
  "geometry": {"coordinates":[4.847082,52.312492],"type":"Point"}
}