{
  "type": "Feature",
  "properties": {
    "iso:country":"NL",
    "sg:address":"Lage Rijndijk 19A",
    "sg:city":"Leiden",
    "sg:orig_category":"Bloemen And Planten",
    "sg:phone":"+31 71 522 4678",
    "sg:postcode":"2315 JK",
    "sg:province":"Zuid-Holland",
    "wof:name":"Karin'S Bloemencentrum",
    "wof:placetype":"venue"
},
  "geometry": {"coordinates":[4.506844,52.161911],"type":"Point"}
}