{
  "type": "Feature",
  "properties": {
    "addr:full":"Nicolaaswg 17 Utrecht Utrecht 3581 VE",
    "addr:housenumber":"17",
    "addr:postcode":"3581",
    "addr:street":"Nicolaaswg",
    "iso:country":"NL",
    "sg:address":"Nicolaaswg 17",
    "sg:city":"Utrecht",
    "sg:orig_category":"Vertaalbureaus",
    "sg:phone":"+31 30 254 0334",
    "sg:postcode":"3581 VE",
    "sg:province":"Utrecht",
    "wof:name":"English Translations & Editing",
    "wof:placetype":"venue"
},
  "geometry": {"coordinates":[5.137628,52.087891],"type":"Point"}
}