{
  "type": "Feature",
  "properties": {
    "addr:full":"Reijer Keijserstraat 6 Texel Noord-Holland 1791 AX",
    "addr:housenumber":"6",
    "addr:postcode":"1791 ax",
    "addr:street":"Reijer Keijserstraat",
    "iso:country":"NL",
    "sg:address":"Reijer Keijserstraat 6",
    "sg:city":"Texel",
    "sg:orig_category":"Timmerwerk Van Hout And Kunststof",
    "sg:phone":"+31 222 310 933",
    "sg:postcode":"1791 AX",
    "sg:province":"Noord-Holland",
    "wof:name":"Bousma Timmerbedrijf",
    "wof:placetype":"venue"
},
  "geometry": {"coordinates":[4.804824,53.050949],"type":"Point"}
}