{
  "type": "Feature",
  "properties": {
    "iso:country":"NL",
    "sg:address":"Nevadadreef 32",
    "sg:city":"Utrecht",
    "sg:orig_category":"Juridische Dienstverlening",
    "sg:phone":"+31 30 261 9944",
    "sg:postcode":"3565 CC",
    "sg:province":"Utrecht",
    "wof:name":"Cobrar Nederland Bv",
    "wof:placetype":"venue"
},
  "geometry": {"coordinates":[5.089315,52.124584],"type":"Point"}
}