{
  "type": "Feature",
  "properties": {
    "addr:full":"Steijnpad 1 Gouda South Holland 2805 JE",
    "addr:housenumber":"1",
    "addr:postcode":"2805 je",
    "addr:street":"Steijnpad",
    "iso:country":"NL",
    "sg:address":"Steijnpad 1",
    "sg:city":"Gouda",
    "sg:classifiers":[
        {
            "category":"Education",
            "subcategory":"Preschool",
            "type":"Public Place"
        }
    ],
    "sg:phone":"+31 182 512 691",
    "sg:postcode":"2805 JE",
    "sg:province":"South Holland",
    "sg:tags":[
        "kleuteronderwijs",
        "basis-"
    ],
    "wof:name":"Basisschool Graaf Jan Van Nassau",
    "wof:placetype":"venue"
},
  "geometry": {"coordinates":[4.722479,52.017311],"type":"Point"}
}