{
  "type": "Feature",
  "properties": {
    "addr:full":"Buurtweg 45 Rheden Gelderland 6991 VV",
    "addr:housenumber":"45",
    "addr:postcode":"6991 vv",
    "addr:street":"Buurtweg;Gelderland",
    "iso:country":"NL",
    "sg:address":"Buurtweg 45",
    "sg:city":"Rheden",
    "sg:orig_category":"Muziekinstrumenten",
    "sg:phone":"+31 26 495 4141",
    "sg:postcode":"6991 VV",
    "sg:province":"Gelderland",
    "wof:name":"E.J. Futselaar",
    "wof:placetype":"venue"
},
  "geometry": {"coordinates":[6.025586,52.003185],"type":"Point"}
}