{
  "type": "Feature",
  "properties": {
    "addr:full":"Zernikeplaats 350 Rotterdam Zuid-Holland 3068 JB",
    "addr:housenumber":"350",
    "addr:postcode":"3068 jb",
    "addr:street":"Zernikeplaats",
    "iso:country":"NL",
    "sg:address":"Zernikeplaats 350",
    "sg:city":"Rotterdam",
    "sg:orig_category":"Woningbouw- Verenigingen En -Stichtingen",
    "sg:phone":"+31 10 443 2403",
    "sg:postcode":"3068 JB",
    "sg:province":"Zuid-Holland",
    "wof:name":"Woningbedrijf Rotterdam",
    "wof:placetype":"venue"
},
  "geometry": {"coordinates":[4.5336780548,51.9578742981],"type":"Point"}
}