{
  "type": "Feature",
  "properties": {
    "iso:country":"NL",
    "sg:address":"Van Rosenburgweg 10",
    "sg:city":"Nijmegen",
    "sg:classifiers":[
        {
            "category":"Communications",
            "subcategory":"Television Station",
            "type":"Services"
        }
    ],
    "sg:phone":"+31 24 344 2424",
    "sg:postcode":"6537 TM",
    "sg:province":"Gelderland",
    "sg:tags":[
        "video",
        "audio",
        "verhuur"
    ],
    "wof:name":"Hollywood Video Entertainment Bv",
    "wof:placetype":"venue"
},
  "geometry": {"coordinates":[5.790155,51.822433],"type":"Point"}
}