{
  "type": "Feature",
  "properties": {
    "addr:full":"Ravensewg 13F Hellevoetsluis Zuid-Holland 3223 LM",
    "addr:housenumber":"13f",
    "addr:postcode":"3223 lm",
    "iso:country":"NL",
    "sg:address":"Ravensewg 13F",
    "sg:city":"Hellevoetsluis",
    "sg:classifiers":[
        {
            "category":"Retail",
            "subcategory":"Auto Repair",
            "type":"Services"
        }
    ],
    "sg:phone":"+31 181 326 523",
    "sg:postcode":"3223 LM",
    "sg:province":"Zuid-Holland",
    "sg:tags":[
        "garage"
    ],
    "wof:name":"Sbm",
    "wof:placetype":"venue"
},
  "geometry": {"coordinates":[4.167373,51.846104],"type":"Point"}
}