{
  "type": "Feature",
  "properties": {
    "addr:full":"Planckstr 57 Dordrecht Zuid-Holland 3316 GS",
    "addr:housenumber":"57",
    "addr:postcode":"3316 gs",
    "addr:street":"Planckstr",
    "iso:country":"NL",
    "sg:address":"Planckstr 57",
    "sg:city":"Dordrecht",
    "sg:orig_category":"Pompen",
    "sg:phone":"+31 78 652 0101",
    "sg:postcode":"3316 GS",
    "sg:province":"Zuid-Holland",
    "wof:name":"Bos Benelux Bv",
    "wof:placetype":"venue"
},
  "geometry": {"coordinates":[4.634761,51.775539],"type":"Point"}
}