{
  "type": "Feature",
  "properties": {
    "addr:full":"Beresteinlaan 283 'S Gravenhage South Holland 2542 JH",
    "addr:housenumber":"283 '",
    "addr:postcode":"2542 jh",
    "addr:street":"Beresteinlaan",
    "iso:country":"NL",
    "sg:address":"Beresteinlaan 283",
    "sg:city":"'S Gravenhage",
    "sg:orig_category":"Kappers",
    "sg:phone":"+31 70 359 5704",
    "sg:postcode":"2542 JH",
    "sg:province":"South Holland",
    "wof:name":"Kapsalon Rob'S Haarstudio",
    "wof:placetype":"venue"
},
  "geometry": {"coordinates":[4.2560091019,52.0403709412],"type":"Point"}
}