{
  "type": "Feature",
  "properties": {
    "addr:full":"Maasdijk 90 Aalst Gld Gelderland 5308 JE",
    "addr:housenumber":"90",
    "addr:postcode":"5308 je",
    "addr:street":"Maasdijk;Gld Gelderland",
    "iso:country":"NL",
    "sg:address":"Maasdijk 90",
    "sg:city":"Aalst Gld",
    "sg:orig_category":"Kappers",
    "sg:phone":"+31 418 677 061",
    "sg:postcode":"5308 JE",
    "sg:province":"Gelderland",
    "wof:name":"Kapsalon Anja",
    "wof:placetype":"venue"
},
  "geometry": {"coordinates":[5.1241641045,51.7800712585],"type":"Point"}
}