{
  "type": "Feature",
  "properties": {
    "addr:full":"Vierwindenln 36 Tilburg Noord-Brabant 5037 MP",
    "addr:housenumber":"36",
    "addr:postcode":"5037 mp",
    "addr:street":"Vierwindenln",
    "iso:country":"NL",
    "sg:address":"Vierwindenln 36",
    "sg:city":"Tilburg",
    "sg:orig_category":"Onroerende Goederen",
    "sg:phone":"+31 13 467 4396",
    "sg:postcode":"5037 MP",
    "sg:province":"Noord-Brabant",
    "wof:name":"Reynen Bv",
    "wof:placetype":"venue"
},
  "geometry": {"coordinates":[5.05094,51.556992],"type":"Point"}
}