{
  "type": "Feature",
  "properties": {
    "addr:full":"Flamingohof 10 Bovenkarspel North Holland 1611 DN",
    "addr:housenumber":"10",
    "addr:postcode":"1611 dn",
    "addr:street":"Flamingohof",
    "iso:country":"NL",
    "sg:address":"Flamingohof 10",
    "sg:city":"Bovenkarspel",
    "sg:orig_category":"Loodgieterswerk, Verwarming And Sanitaire Installaties",
    "sg:phone":"+31 228 518 093",
    "sg:postcode":"1611 DN",
    "sg:province":"North Holland",
    "wof:name":"H.S.T. Home Service Totaal",
    "wof:placetype":"venue"
},
  "geometry": {"coordinates":[5.250599,52.693783],"type":"Point"}
}