{
  "type": "Feature",
  "properties": {
    "addr:full":"Sleewykstr 104 Amsterdam Zuidoost Noord-Holland 1107 TX",
    "addr:housenumber":"104",
    "addr:postcode":"zuidoost;1107 tx",
    "iso:country":"NL",
    "sg:address":"Sleewykstr 104",
    "sg:city":"Amsterdam Zuidoost",
    "sg:orig_category":"Vertaalbureaus",
    "sg:phone":"+31 20 696 0473",
    "sg:postcode":"1107 TX",
    "sg:province":"Noord-Holland",
    "wof:name":"Rex",
    "wof:placetype":"venue"
},
  "geometry": {"coordinates":[-100.07679,31.168989],"type":"Point"}
}