{
  "type": "Feature",
  "properties": {
    "addr:full":"Dever 39 Haarlem North Holland 2036 HK",
    "addr:housenumber":"39",
    "addr:postcode":"2036 hk",
    "addr:street":"Dever",
    "iso:country":"NL",
    "sg:address":"Dever 39",
    "sg:city":"Haarlem",
    "sg:orig_category":"Loodgieterswerk, Verwarming And Sanitaire Installaties",
    "sg:phone":"+31 23 535 4153",
    "sg:postcode":"2036 HK",
    "sg:province":"North Holland",
    "wof:name":"Vd Meer En Hoogewerf Loodgieters",
    "wof:placetype":"venue"
},
  "geometry": {"coordinates":[4.648919,52.349316],"type":"Point"}
}