{
  "type": "Feature",
  "properties": {
    "iso:country":"NL",
    "sg:address":"Neherkd 71D",
    "sg:city":"S Gravenhage",
    "sg:orig_category":"Drukkerijen",
    "sg:phone":"+31 70 399 7899",
    "sg:postcode":"2521 WP",
    "sg:province":"Zuid-Holland",
    "wof:name":"Pols & Zn, A",
    "wof:placetype":"venue"
},
  "geometry": {"coordinates":[4.32071,52.062988],"type":"Point"}
}