{
  "type": "Feature",
  "properties": {
    "addr:full":"Wassenaarsewg 94 Den Haag South Holland 2596 CZ",
    "addr:housenumber":"94",
    "addr:postcode":"2596",
    "addr:street":"Wassenaarsewg",
    "iso:country":"NL",
    "sg:address":"Wassenaarsewg 94",
    "sg:city":"Den Haag",
    "sg:orig_category":"Beeldende Kunstenaars",
    "sg:phone":"+31 70 324 9255",
    "sg:postcode":"2596 CZ",
    "sg:province":"South Holland",
    "wof:name":"Schreuder, C E",
    "wof:placetype":"venue"
},
  "geometry": {"coordinates":[4.322023,52.093773],"type":"Point"}
}