{
  "type": "Feature",
  "properties": {
    "addr:full":"Dorpsstr 104 Bergen Nh North Holland 1861 KZ",
    "addr:housenumber":"104",
    "addr:postcode":"1861 kz",
    "addr:street":"Nh North",
    "iso:country":"NL",
    "sg:address":"Dorpsstr 104",
    "sg:city":"Bergen Nh",
    "sg:orig_category":"Bloemen En Planten",
    "sg:phone":"+31 72 589 8495",
    "sg:postcode":"1861 KZ",
    "sg:province":"North Holland",
    "wof:name":"Jansmijn, De",
    "wof:placetype":"venue"
},
  "geometry": {"coordinates":[4.709647,52.666313],"type":"Point"}
}