{
  "type": "Feature",
  "properties": {
    "addr:full":"Wylerbaan 4 Groesbeek Gelderland 6561 KR",
    "addr:housenumber":"4",
    "addr:postcode":"6561 kr",
    "addr:street":"Wylerbaan;Gelderland",
    "iso:country":"NL",
    "sg:address":"Wylerbaan 4",
    "sg:city":"Groesbeek",
    "sg:orig_category":"Musea",
    "sg:phone":"+31 24 397 4404",
    "sg:postcode":"6561 KR",
    "sg:province":"Gelderland",
    "wof:name":"Nat Bevrijdingsmuseum 1944-1945",
    "wof:placetype":"venue"
},
  "geometry": {"coordinates":[5.936474,51.786087],"type":"Point"}
}