{
  "type": "Feature",
  "properties": {
    "iso:country":"NL",
    "sg:address":"Oude Dijk 7",
    "sg:city":"Abcoude",
    "sg:orig_category":"Levende Dieren Gh",
    "sg:phone":"+31 294 285 810",
    "sg:postcode":"1391 KP",
    "sg:province":"Utrecht",
    "wof:name":"Veehandel Nico Zagt",
    "wof:placetype":"venue"
},
  "geometry": {"coordinates":[4.978163,52.261898],"type":"Point"}
}