{
  "type": "Feature",
  "properties": {
    "addr:full":"Rysdk 13 Rhoon Zuid-Holland 3161 HK",
    "addr:housenumber":"13",
    "addr:postcode":"3161 hk",
    "addr:street":"Rysdk",
    "iso:country":"NL",
    "sg:address":"Rysdk 13",
    "sg:city":"Rhoon",
    "sg:orig_category":"Scheepvaart- Agentschappen",
    "sg:phone":"+31 10 501 9977",
    "sg:postcode":"3161 HK",
    "sg:province":"Zuid-Holland",
    "wof:name":"Beejay Bv",
    "wof:placetype":"venue"
},
  "geometry": {"coordinates":[4.419975,51.855656],"type":"Point"}
}