{
  "type": "Feature",
  "properties": {
    "iso:country":"NL",
    "sg:address":"Naaldhof 8 , (Mobiele Telefoon)",
    "sg:city":"Nunspeet",
    "sg:orig_category":"Woningstoffeerders",
    "sg:phone":"+31 6 51714563",
    "sg:postcode":"8071 AW",
    "sg:province":"Gelderland",
    "wof:name":"B & M",
    "wof:placetype":"venue"
},
  "geometry": {"coordinates":[5.7928481102,52.3781776428],"type":"Point"}
}