{
  "type": "Feature",
  "properties": {
    "addr:full":"Veenslagenwg 109 Hoevelaken Gelderland 3871 NB",
    "addr:housenumber":"109",
    "addr:postcode":"3871 nb",
    "addr:street":"Gelderland",
    "iso:country":"NL",
    "sg:address":"Veenslagenwg 109",
    "sg:city":"Hoevelaken",
    "sg:orig_category":"Adviesbureaus Bedrijfsorganisatie",
    "sg:phone":"+31 6 53967295",
    "sg:postcode":"3871 NB",
    "sg:province":"Gelderland",
    "wof:name":"Creative Gears",
    "wof:placetype":"venue"
},
  "geometry": {"coordinates":[5.454526,52.178837],"type":"Point"}
}