{
  "type": "Feature",
  "properties": {
    "addr:full":"Boergoensestr 114A Rotterdam Zuid-Holland 3082 KD",
    "addr:housenumber":"114a",
    "addr:postcode":"3082 kd",
    "iso:country":"NL",
    "sg:address":"Boergoensestr 114A",
    "sg:city":"Rotterdam",
    "sg:orig_category":"Meubelen Gebruikte",
    "sg:phone":"+31 6 23349049",
    "sg:postcode":"3082 KD",
    "sg:province":"Zuid-Holland",
    "wof:name":"Cirkel",
    "wof:placetype":"venue"
},
  "geometry": {"coordinates":[4.470508,51.891537],"type":"Point"}
}