{
  "type": "Feature",
  "properties": {
    "addr:full":"Vrouwenhuisstraat 3 Montfoort Utrecht 3417 EH",
    "addr:housenumber":"3",
    "addr:postcode":"3417 eh",
    "addr:street":"Vrouwenhuisstraat",
    "iso:country":"NL",
    "sg:address":"Vrouwenhuisstraat 3",
    "sg:city":"Montfoort",
    "sg:orig_category":"Bloemen And Planten",
    "sg:phone":"+31 348 471 933",
    "sg:postcode":"3417 EH",
    "sg:province":"Utrecht",
    "wof:name":"Bloemenmagazijn Zorina",
    "wof:placetype":"venue"
},
  "geometry": {"coordinates":[4.951155,52.04533],"type":"Point"}
}