{
  "type": "Feature",
  "properties": {
    "addr:full":"Het Kasteel 195 Apeldoorn Gelderland 7325 PC",
    "addr:housenumber":"195",
    "addr:postcode":"7325 pc",
    "addr:street":"Het Kasteel;Gelderland",
    "iso:country":"NL",
    "sg:address":"Het Kasteel 195",
    "sg:city":"Apeldoorn",
    "sg:orig_category":"Bedrijfsinventaris Gh",
    "sg:phone":"+31 55 360 0735",
    "sg:postcode":"7325 PC",
    "sg:province":"Gelderland",
    "wof:name":"Studio A",
    "wof:placetype":"venue"
},
  "geometry": {"coordinates":[6.013373,52.211746],"type":"Point"}
}