{
  "type": "Feature",
  "properties": {
    "addr:full":"Boulevard Barnaart 68 Zandvoort Noord-Holland 2041 JA",
    "addr:housenumber":"68",
    "addr:postcode":"2041 ja",
    "addr:street":"Boulevard Barnaart",
    "iso:country":"NL",
    "sg:address":"Boulevard Barnaart 68",
    "sg:city":"Zandvoort",
    "sg:orig_category":"Kampeerterreinen",
    "sg:phone":"+31 23 571 2312",
    "sg:postcode":"2041 JA",
    "sg:province":"Noord-Holland",
    "wof:name":"Caravanpark De Duinrand Bv",
    "wof:placetype":"venue"
},
  "geometry": {"coordinates":[4.5304198265,52.3808708191],"type":"Point"}
}