{
  "type": "Feature",
  "properties": {
    "addr:full":"Amstelveensewg 85 Amsterdam Noord-Holland 1075 VW",
    "addr:housenumber":"85",
    "addr:postcode":"1075 vw",
    "addr:street":"Amstelveensewg",
    "iso:country":"NL",
    "sg:address":"Amstelveensewg 85",
    "sg:city":"Amsterdam",
    "sg:orig_category":"Broodjeszaken",
    "sg:phone":"+31 20 364 1431",
    "sg:postcode":"1075 VW",
    "sg:province":"Noord-Holland",
    "wof:name":"Panineria",
    "wof:placetype":"venue"
},
  "geometry": {"coordinates":[4.856169,52.353054],"type":"Point"}
}