{
  "type": "Feature",
  "properties": {
    "addr:full":"Burg Schumanln 23 Lopik Utrecht 3411 XM",
    "addr:housenumber":"23",
    "addr:postcode":"3411 xm",
    "addr:street":"Burg",
    "iso:country":"NL",
    "sg:address":"Burg Schumanln 23",
    "sg:city":"Lopik",
    "sg:orig_category":"Gordijnenateliers",
    "sg:phone":"+31 348 552 932",
    "sg:postcode":"3411 XM",
    "sg:province":"Utrecht",
    "wof:name":"Annie",
    "wof:placetype":"venue"
},
  "geometry": {"coordinates":[4.945286,51.97467],"type":"Point"}
}