{
  "type": "Feature",
  "properties": {
    "iso:country":"NL",
    "sg:address":"Trosjespeergaarde 37",
    "sg:city":"Amersfoort",
    "sg:orig_category":"Verzekeringen",
    "sg:phone":"+31 33 456 0977",
    "sg:postcode":"3824 BA",
    "sg:province":"Utrecht",
    "wof:name":"Redejo Adviesgroep",
    "wof:placetype":"venue"
},
  "geometry": {"coordinates":[5.370582,52.197975],"type":"Point"}
}