{
  "type": "Feature",
  "properties": {
    "addr:full":"Loonse Molenstraat 49 Loon Op Zand Noord-Brabant 5175 PS",
    "addr:housenumber":"49",
    "addr:postcode":"5175 ps",
    "addr:street":"Loonse Molenstraat",
    "iso:country":"NL",
    "sg:address":"Loonse Molenstraat 49",
    "sg:city":"Loon Op Zand",
    "sg:orig_category":"Kampeerterreinen",
    "sg:phone":"+31 416 361 779",
    "sg:postcode":"5175 PS",
    "sg:province":"Noord-Brabant",
    "wof:name":"Kampeerboerderij Binnenheide",
    "wof:placetype":"venue"
},
  "geometry": {"coordinates":[5.0978498459,51.6264533997],"type":"Point"}
}