{
  "type": "Feature",
  "properties": {
    "addr:full":"Baanstraat 70 Beverwijk Noord-Holland 1942 CK",
    "addr:housenumber":"70",
    "addr:postcode":"1942 ck",
    "addr:street":"Baanstraat",
    "iso:country":"NL",
    "sg:address":"Baanstraat 70",
    "sg:city":"Beverwijk",
    "sg:classifiers":[
        {
            "category":"Bakery",
            "type":"Food & Drink"
        }
    ],
    "sg:phone":"+31 251 223 378",
    "sg:postcode":"1942 CK",
    "sg:province":"Noord-Holland",
    "sg:tags":[
        "brood",
        "banket"
    ],
    "wof:name":"P.G. Klees Bv",
    "wof:placetype":"venue"
},
  "geometry": {"coordinates":[4.654789,52.483356],"type":"Point"}
}