{
  "type": "Feature",
  "properties": {
    "addr:full":"Papendrechtstraat 9 Amsterdam Zuidoost Noord-Holland 1106 BM",
    "addr:housenumber":"9",
    "addr:postcode":"zuidoost;1106 bm",
    "addr:street":"Papendrechtstraat",
    "iso:country":"NL",
    "sg:address":"Papendrechtstraat 9",
    "sg:city":"Amsterdam Zuidoost",
    "sg:orig_category":"Begrafenisondernemers",
    "sg:phone":"+31 20 453 0845",
    "sg:postcode":"1106 BM",
    "sg:province":"Noord-Holland",
    "wof:name":"Uitvaartorganisatie Een Laatste Groet",
    "wof:placetype":"venue"
},
  "geometry": {"coordinates":[4.976185,52.298615],"type":"Point"}
}