{
  "type": "Feature",
  "properties": {
    "addr:full":"Grotestraat 196 Almelo NL.08 7607 CZ",
    "addr:housenumber":"196;nl.08",
    "addr:postcode":"7607",
    "addr:street":"Grotestraat",
    "iso:country":"NL",
    "sg:address":"Grotestraat 196",
    "sg:city":"Almelo",
    "sg:orig_category":"Verlichting And Huishoudartikelen",
    "sg:phone":"+31 546 813 952",
    "sg:postcode":"7607 CZ",
    "sg:province":"NL.08",
    "wof:name":"Firma Haghuis - Woninginrichting",
    "wof:placetype":"venue"
},
  "geometry": {"coordinates":[6.665294,52.351624],"type":"Point"}
}