{
  "type": "Feature",
  "properties": {
    "iso:country":"NL",
    "sg:address":"Grotestraat 196",
    "sg:city":"Almelo",
    "sg:orig_category":"Verlichting And Huishoudartikelen",
    "sg:phone":"+31 546 813 952",
    "sg:postcode":"7607 CZ",
    "sg:province":"NL.08",
    "wof:name":"Firma Haghuis - Woninginrichting",
    "wof:placetype":"venue"
},
  "geometry": {"coordinates":[6.665294,52.351624],"type":"Point"}
}