{
  "type": "Feature",
  "properties": {
    "addr:full":"Latherusstr 110A Amsterdam Noord-Holland 1032 EG",
    "addr:housenumber":"110a",
    "addr:postcode":"1032 eg",
    "iso:country":"NL",
    "sg:address":"Latherusstr 110A",
    "sg:city":"Amsterdam",
    "sg:orig_category":"Mensendieck - Oefentherapeuten",
    "sg:phone":"+31 20 634 1212",
    "sg:postcode":"1032 EG",
    "sg:province":"Noord-Holland",
    "wof:name":"Gevers, M H",
    "wof:placetype":"venue"
},
  "geometry": {"coordinates":[4.915398,52.395279],"type":"Point"}
}