{
  "type": "Feature",
  "properties": {
    "addr:full":"Boekenderstraat 250 Venlo Limburg 5925 NB",
    "addr:housenumber":"250",
    "addr:postcode":"5925 nb",
    "addr:street":"Boekenderstraat",
    "iso:country":"NL",
    "sg:address":"Boekenderstraat 250",
    "sg:city":"Venlo",
    "sg:orig_category":"Bloemen And Planten",
    "sg:phone":"+31 77 382 0494",
    "sg:postcode":"5925 NB",
    "sg:province":"Limburg",
    "wof:name":"Saris Bloemen Vof",
    "wof:placetype":"venue"
},
  "geometry": {"coordinates":[6.132123,51.377342],"type":"Point"}
}