{
  "type": "Feature",
  "properties": {
    "addr:full":"Akersteenweg 118 Maastricht Limburg 6227 AC",
    "addr:housenumber":"118",
    "addr:postcode":"6227 ac",
    "addr:street":"Akersteenweg",
    "iso:country":"NL",
    "sg:address":"Akersteenweg 118",
    "sg:city":"Maastricht",
    "sg:orig_category":"Juweliers",
    "sg:phone":"+31 43 361 5093",
    "sg:postcode":"6227 AC",
    "sg:province":"Limburg",
    "wof:name":"Juwelier Van Velthuijsen",
    "wof:placetype":"venue"
},
  "geometry": {"coordinates":[5.726601,50.843052],"type":"Point"}
}