{
  "type": "Feature",
  "properties": {
    "addr:full":"Valkstr 6 Putten Gelderland 3882 HV",
    "addr:housenumber":"6",
    "addr:postcode":"3882 hv",
    "addr:street":"Valkstr;Gelderland",
    "iso:country":"NL",
    "sg:address":"Valkstr 6",
    "sg:city":"Putten",
    "sg:orig_category":"Metselwerken",
    "sg:phone":"+31 341 354 658",
    "sg:postcode":"3882 HV",
    "sg:province":"Gelderland",
    "wof:name":"Reijersen Vof",
    "wof:placetype":"venue"
},
  "geometry": {"coordinates":[5.588982,52.259888],"type":"Point"}
}