{
  "type": "Feature",
  "properties": {
    "addr:full":"Lambertusstr 65 Neeritter Limburg 6015 AR",
    "addr:housenumber":"65",
    "addr:postcode":"6015",
    "addr:street":"Lambertusstr",
    "iso:country":"NL",
    "sg:address":"Lambertusstr 65",
    "sg:city":"Neeritter",
    "sg:orig_category":"Adviesbureaus Bedrijfsorganisatie",
    "sg:phone":"+31 475 564 859",
    "sg:postcode":"6015 AR",
    "sg:province":"Limburg",
    "wof:name":"Fit",
    "wof:placetype":"venue"
},
  "geometry": {"coordinates":[-61.04258,-35.022549],"type":"Point"}
}