{
  "type": "Feature",
  "properties": {
    "addr:full":"V Nesstr 80 Haarlem North Holland 2024 DR",
    "addr:housenumber":"80",
    "addr:postcode":"2024 dr",
    "iso:country":"NL",
    "sg:address":"V Nesstr 80",
    "sg:city":"Haarlem",
    "sg:orig_category":"Administratie- En Boekhoudkantoren",
    "sg:phone":"+31 23 525 0749",
    "sg:postcode":"2024 DR",
    "sg:province":"North Holland",
    "wof:name":"Mudde Van 1938 Bv",
    "wof:placetype":"venue"
},
  "geometry": {"coordinates":[4.63761,52.40593],"type":"Point"}
}