{
  "type": "Feature",
  "properties": {
    "iso:country":"NL",
    "sg:address":"Top Naeffstraat 9",
    "sg:city":"Leiden",
    "sg:orig_category":"Diverse Grafische Activiteiten",
    "sg:phone":"+31 71 531 5169",
    "sg:postcode":"2331 HD",
    "sg:province":"Zuid-Holland",
    "wof:name":"Readable",
    "wof:placetype":"venue"
},
  "geometry": {"coordinates":[4.451732,52.152275],"type":"Point"}
}