{
  "type": "Feature",
  "properties": {
    "iso:country":"NL",
    "sg:address":"Kootwykerbroek Wg 72",
    "sg:city":"Kootwykerbroek",
    "sg:classifiers":[
        {
            "category":"Retail",
            "subcategory":"Auto Repair",
            "type":"Services"
        }
    ],
    "sg:phone":"+31 342 441 972",
    "sg:postcode":"3774 BV",
    "sg:province":"Gelderland",
    "sg:tags":[
        "garage"
    ],
    "wof:name":"Brink, H Van Den",
    "wof:placetype":"venue"
},
  "geometry": {"coordinates":[5.680027,52.162556],"type":"Point"}
}