{
  "type": "Feature",
  "properties": {
    "addr:full":"Spanjestraat 23 Montfort Limburg 6065 BT",
    "addr:housenumber":"23",
    "addr:postcode":"6065 bt",
    "addr:street":"Spanjestraat",
    "iso:country":"NL",
    "sg:address":"Spanjestraat 23",
    "sg:city":"Montfort",
    "sg:orig_category":"Binnenhuisarchitecten",
    "sg:phone":"+31 475 541 528",
    "sg:postcode":"6065 BT",
    "sg:province":"Limburg",
    "wof:name":"Axis M.J.L. Knoben",
    "wof:placetype":"venue"
},
  "geometry": {"coordinates":[5.949678,51.126884],"type":"Point"}
}