{
  "type": "Feature",
  "properties": {
    "addr:full":"De Corantyn 25A Zwaag Noord-Holland 1689 AN",
    "addr:housenumber":"25a",
    "addr:postcode":"1689 an",
    "iso:country":"NL",
    "sg:address":"De Corantyn 25A",
    "sg:city":"Zwaag",
    "sg:orig_category":"Administratie- En Boekhoudkantoren",
    "sg:phone":"+31 229 295 326",
    "sg:postcode":"1689 AN",
    "sg:province":"Noord-Holland",
    "wof:name":"Klaver",
    "wof:placetype":"venue"
},
  "geometry": {"coordinates":[5.070396,52.669456],"type":"Point"}
}