{
  "type": "Feature",
  "properties": {
    "addr:full":"Donkslagen 6 Breda Noord-Brabant 4823 KE",
    "addr:housenumber":"6",
    "addr:postcode":"4823 ke",
    "addr:street":"Donkslagen",
    "iso:country":"NL",
    "sg:address":"Donkslagen 6",
    "sg:city":"Breda",
    "sg:orig_category":"Boekhouders",
    "sg:phone":"+31 76 542 9020",
    "sg:postcode":"4823 KE",
    "sg:province":"Noord-Brabant",
    "wof:name":"Administratiekantoor Visker",
    "wof:placetype":"venue"
},
  "geometry": {"coordinates":[4.734675,51.622513],"type":"Point"}
}