{
  "type": "Feature",
  "properties": {
    "addr:full":"Hopstr 21 Delft South Holland 2611 TA",
    "addr:housenumber":"21",
    "addr:postcode":"2611 ta",
    "addr:street":"Hopstr",
    "iso:country":"NL",
    "sg:address":"Hopstr 21",
    "sg:city":"Delft",
    "sg:orig_category":"Psychotherapeuten",
    "sg:phone":"+31 15 213 0655",
    "sg:postcode":"2611 TA",
    "sg:province":"South Holland",
    "wof:name":"Coco",
    "wof:placetype":"venue"
},
  "geometry": {"coordinates":[4.365525,52.011974],"type":"Point"}
}