{
  "type": "Feature",
  "properties": {
    "addr:full":"Staverdensewg 92A Elspeet Gelderland 8075 AS",
    "addr:housenumber":"92a",
    "addr:postcode":"8075 as",
    "addr:street":"Staverdensewg;Gelderland",
    "iso:country":"NL",
    "sg:address":"Staverdensewg 92A",
    "sg:city":"Elspeet",
    "sg:orig_category":"Meubelen",
    "sg:phone":"+31 577 491 191",
    "sg:postcode":"8075 AS",
    "sg:province":"Gelderland",
    "wof:name":"Decoratiehuis, Het",
    "wof:placetype":"venue"
},
  "geometry": {"coordinates":[5.77571,52.291874],"type":"Point"}
}