{
  "type": "Feature",
  "properties": {
    "iso:country":"NL",
    "sg:address":"Van Heemstraweg 109",
    "sg:city":"Wamel",
    "sg:classifiers":[
        {
            "category":"Food & Beverages",
            "subcategory":"Fruits & Vegetables",
            "type":"Retail Goods"
        }
    ],
    "sg:phone":"+31 487 501 326",
    "sg:postcode":"6659 KE",
    "sg:province":"Gelderland",
    "sg:tags":[
        "groenten"
    ],
    "wof:name":"D.H.G.A. Janssen",
    "wof:placetype":"venue"
},
  "geometry": {"coordinates":[5.456107,51.87487],"type":"Point"}
}