{
  "type": "Feature",
  "properties": {
    "iso:country":"NL",
    "sg:address":"Zeestr 77",
    "sg:city":"Noordwykerhout",
    "sg:orig_category":"Loodgieters",
    "sg:phone":"+31 252 373 340",
    "sg:postcode":"2211 XC",
    "sg:province":"South Holland",
    "wof:name":"Seijsener, W",
    "wof:placetype":"venue"
},
  "geometry": {"coordinates":[4.487942,52.26292],"type":"Point"}
}