{
  "type": "Feature",
  "properties": {
    "addr:full":"J P Heyestraat 14 Hengelo Ov NL.08 7552 MS",
    "addr:housenumber":"14",
    "addr:postcode":"7552 ms",
    "addr:street":"J P Heyestraat;Ov",
    "iso:country":"NL",
    "sg:address":"J P Heyestraat 14",
    "sg:city":"Hengelo Ov",
    "sg:orig_category":"Kinderopvang Behalve Thuis",
    "sg:phone":"+31 74 249 0200",
    "sg:postcode":"7552 MS",
    "sg:province":"NL.08",
    "wof:name":"Stichting Jeugdzorg Twente Afdeling Dagbehandeling",
    "wof:placetype":"venue"
},
  "geometry": {"coordinates":[6.82431,52.268749],"type":"Point"}
}