{
  "type": "Feature",
  "properties": {
    "addr:full":"Koudekerkseweg 137 Middelburg Zeeland 4335 SL",
    "addr:housenumber":"137",
    "addr:postcode":"4335 sl",
    "addr:street":"Koudekerkseweg",
    "iso:country":"NL",
    "sg:address":"Koudekerkseweg 137",
    "sg:city":"Middelburg",
    "sg:orig_category":"Geluidsopnamen",
    "sg:phone":"+31 118 633 262",
    "sg:postcode":"4335 SL",
    "sg:province":"Zeeland",
    "wof:name":"Studio 66",
    "wof:placetype":"venue"
},
  "geometry": {"coordinates":[3.595966,51.490627],"type":"Point"}
}