{
  "type": "Feature",
  "properties": {
    "iso:country":"NL",
    "sg:address":"Fazantenkamp 890",
    "sg:city":"Maarssen",
    "sg:orig_category":"Journalisten Freelance",
    "sg:phone":"+31 346 563 470",
    "sg:postcode":"3607 EE",
    "sg:province":"Utrecht",
    "wof:name":"Helden, Ton Van",
    "wof:placetype":"venue"
},
  "geometry": {"coordinates":[5.022615,52.130749],"type":"Point"}
}