{
  "type": "Feature",
  "properties": {
    "addr:full":"De Voortwg 6 Brummen Gelderland 6971 JX",
    "addr:housenumber":"6",
    "addr:postcode":"6971 jx",
    "addr:street":"Gelderland",
    "iso:country":"NL",
    "sg:address":"De Voortwg 6",
    "sg:city":"Brummen",
    "sg:orig_category":"Projectontwikkeling",
    "sg:phone":"+31 575 476 250",
    "sg:postcode":"6971 JX",
    "sg:province":"Gelderland",
    "wof:name":"Berkenrode Bv",
    "wof:placetype":"venue"
},
  "geometry": {"coordinates":[6.157554,52.129295],"type":"Point"}
}