{
  "type": "Feature",
  "properties": {
    "iso:country":"NL",
    "sg:address":"Voltaplein 10",
    "sg:city":"Amsterdam",
    "sg:orig_category":"Boekenuitgeverijen",
    "sg:phone":"+31 20 693 5834",
    "sg:postcode":"1098 NR",
    "sg:province":"Noord-Holland",
    "wof:name":"Instituut De Haan",
    "wof:placetype":"venue"
},
  "geometry": {"coordinates":[4.940956,52.353142],"type":"Point"}
}