{
  "type": "Feature",
  "properties": {
    "addr:full":"Evertsenln 88 Terneuzen Zeeland 4535 AD",
    "addr:housenumber":"88",
    "addr:postcode":"4535 ad",
    "addr:street":"Evertsenln",
    "iso:country":"NL",
    "sg:address":"Evertsenln 88",
    "sg:city":"Terneuzen",
    "sg:orig_category":"Kinderactiviteiten",
    "sg:phone":"+31 115 617 462",
    "sg:postcode":"4535 AD",
    "sg:province":"Zeeland",
    "wof:name":"Kinderboerderij Terneuzen",
    "wof:placetype":"venue"
},
  "geometry": {"coordinates":[3.853084,51.323437],"type":"Point"}
}