{
  "type": "Feature",
  "properties": {
    "addr:full":"T Woud 1 Brielle Zuid-Holland 3232 LN",
    "addr:housenumber":"1",
    "addr:postcode":"3232 ln",
    "addr:street":"T Woud",
    "iso:country":"NL",
    "sg:address":"T Woud 1",
    "sg:city":"Brielle",
    "sg:classifiers":[
        {
            "category":"Parking",
            "subcategory":"Lot",
            "type":"Transportation"
        }
    ],
    "sg:phone":"+31 181 417 500",
    "sg:postcode":"3232 LN",
    "sg:province":"Zuid-Holland",
    "sg:tags":[
        "fab",
        "metalen",
        "tank"
    ],
    "wof:name":"D. De Bruin Piping Construction Bpc Bv",
    "wof:placetype":"venue"
},
  "geometry": {"coordinates":[4.162128,51.889687],"type":"Point"}
}