{
  "type": "Feature",
  "properties": {
    "iso:country":"NL",
    "sg:address":"Paulus Potterstraat 1",
    "sg:city":"Raamsdonksveer",
    "sg:orig_category":"Goederenvervoer Over De Weg",
    "sg:phone":"+31 162 512 629",
    "sg:postcode":"4941 ZP",
    "sg:province":"Noord-Brabant",
    "wof:name":"Firma H.M. Kommers En Zonen",
    "wof:placetype":"venue"
},
  "geometry": {"coordinates":[4.867232,51.695538],"type":"Point"}
}