{
  "type": "Feature",
  "properties": {
    "addr:full":"Twenteweg 30 Enschede Overijssel 7532 ST",
    "addr:housenumber":"30",
    "addr:postcode":"7532 st",
    "addr:street":"Twenteweg",
    "iso:country":"NL",
    "sg:address":"Twenteweg 30",
    "sg:city":"Enschede",
    "sg:orig_category":"Wegen And Sportterreinen",
    "sg:phone":"+31 53 461 4411",
    "sg:postcode":"7532 ST",
    "sg:province":"Overijssel",
    "wof:name":"Te Pas Infra Bv",
    "wof:placetype":"venue"
},
  "geometry": {"coordinates":[6.9463939667,52.2224693298],"type":"Point"}
}