{
  "type": "Feature",
  "properties": {
    "addr:full":"Noordeindsewg 262 Berkel En Rodenrys South Holland 2651 LL",
    "addr:housenumber":"262",
    "addr:postcode":"2651 ll",
    "addr:street":"Berkel",
    "iso:country":"NL",
    "sg:address":"Noordeindsewg 262",
    "sg:city":"Berkel En Rodenrys",
    "sg:orig_category":"Meubelen Gebruikte",
    "sg:phone":"+31 10 511 1888",
    "sg:postcode":"2651 LL",
    "sg:province":"South Holland",
    "sg:website":"http://www.ideo-design.nl",
    "wof:name":"Ideo",
    "wof:placetype":"venue"
},
  "geometry": {"coordinates":[4.484661,52.01255],"type":"Point"}
}