{
  "type": "Feature",
  "properties": {
    "addr:full":"Havik 47 Amersfoort Utrecht 3811 EX",
    "addr:housenumber":"47",
    "addr:postcode":"3811 ex",
    "addr:street":"Havik",
    "iso:country":"NL",
    "sg:address":"Havik 47",
    "sg:city":"Amersfoort",
    "sg:orig_category":"Antiekzaken",
    "sg:phone":"+31 33 461 3494",
    "sg:postcode":"3811 EX",
    "sg:province":"Utrecht",
    "wof:name":"Firma G. Van Ramselaar & Zonen.",
    "wof:placetype":"venue"
},
  "geometry": {"coordinates":[5.389743,52.157314],"type":"Point"}
}