{
  "type": "Feature",
  "properties": {
    "addr:full":"Gerberasngl 111 Berkel En Rodenrys Zuid-Holland 2651 XZ",
    "addr:housenumber":"111",
    "addr:postcode":"2651 xz",
    "addr:street":"Berkel",
    "iso:country":"NL",
    "sg:address":"Gerberasngl 111",
    "sg:city":"Berkel En Rodenrys",
    "sg:orig_category":"Peuterspeelzalen",
    "sg:phone":"+31 10 511 5406",
    "sg:postcode":"2651 XZ",
    "sg:province":"Zuid-Holland",
    "wof:name":"Olleke Bolleke",
    "wof:placetype":"venue"
},
  "geometry": {"coordinates":[4.47659,51.994122],"type":"Point"}
}