{
  "type": "Feature",
  "properties": {
    "addr:full":"Julianastr 49 Poeldyk South Holland 2685 BB",
    "addr:housenumber":"49",
    "addr:postcode":"2685 bb",
    "addr:street":"Julianastr;Poeldyk South",
    "iso:country":"NL",
    "sg:address":"Julianastr 49",
    "sg:city":"Poeldyk",
    "sg:orig_category":"Peuterspeelzalen",
    "sg:phone":"+31 174 243 859",
    "sg:postcode":"2685 BB",
    "sg:province":"South Holland",
    "wof:name":"Hummeloord",
    "wof:placetype":"venue"
},
  "geometry": {"coordinates":[4.215826,52.024906],"type":"Point"}
}