{
  "type": "Feature",
  "properties": {
    "iso:country":"NL",
    "sg:address":"Julianastr 49",
    "sg:city":"Poeldyk",
    "sg:orig_category":"Peuterspeelzalen",
    "sg:phone":"+31 174 243 859",
    "sg:postcode":"2685 BB",
    "sg:province":"South Holland",
    "wof:name":"Hummeloord",
    "wof:placetype":"venue"
},
  "geometry": {"coordinates":[4.215826,52.024906],"type":"Point"}
}