{
  "type": "Feature",
  "properties": {
    "addr:full":"Wingerd 1 Vroomshoop NL.08 7681 JB",
    "addr:housenumber":"1;nl.08",
    "addr:postcode":"7681 jb",
    "addr:street":"Wingerd",
    "iso:country":"NL",
    "sg:address":"Wingerd 1",
    "sg:city":"Vroomshoop",
    "sg:orig_category":"Banken",
    "sg:phone":"+31 548 631 111",
    "sg:postcode":"7681 JB",
    "sg:province":"NL.08",
    "sg:website":"http://www.rabobank.nl",
    "wof:name":"Rabobank",
    "wof:placetype":"venue"
},
  "geometry": {"coordinates":[6.566406,52.462666],"type":"Point"}
}