{
  "type": "Feature",
  "properties": {
    "iso:country":"NL",
    "sg:address":"Westdijk 87",
    "sg:city":"Mijnsheerenland",
    "sg:orig_category":"Verhuur Huishoudartikelen",
    "sg:phone":"+31 186 603 903",
    "sg:postcode":"3271 LL",
    "sg:province":"South Holland",
    "wof:name":"Frako Verhuur",
    "wof:placetype":"venue"
},
  "geometry": {"coordinates":[4.462097168,51.8129806519],"type":"Point"}
}