{
  "type": "Feature",
  "properties": {
    "addr:full":"Drontermeerln 35 Leiden Zuid-Holland 2317 GH",
    "addr:housenumber":"35",
    "addr:postcode":"2317 gh",
    "addr:street":"Drontermeerln",
    "iso:country":"NL",
    "sg:address":"Drontermeerln 35",
    "sg:city":"Leiden",
    "sg:orig_category":"Adviesbureaus Bedrijfsorganisatie",
    "sg:phone":"+31 71 523 5618",
    "sg:postcode":"2317 GH",
    "sg:province":"Zuid-Holland",
    "wof:name":"Bron",
    "wof:placetype":"venue"
},
  "geometry": {"coordinates":[4.515875,52.17392],"type":"Point"}
}