{
  "type": "Feature",
  "properties": {
    "addr:full":"Maatkampweg 20 Baarn Utrecht 3742 XM",
    "addr:housenumber":"20",
    "addr:postcode":"3742 xm",
    "addr:street":"Maatkampweg",
    "iso:country":"NL",
    "sg:address":"Maatkampweg 20",
    "sg:city":"Baarn",
    "sg:orig_category":"Kinderopvang Behalve Thuis",
    "sg:phone":"+31 35 548 8488",
    "sg:postcode":"3742 XM",
    "sg:province":"Utrecht",
    "wof:name":"Kinderdagverblijf Stg Kinderopvang Baarn",
    "wof:placetype":"venue"
},
  "geometry": {"coordinates":[5.301524,52.206017],"type":"Point"}
}