{
  "type": "Feature",
  "properties": {
    "addr:full":"Grachtstr 44 Voerendaal Limburg 6367 CC",
    "addr:housenumber":"44",
    "addr:postcode":"6367 cc",
    "addr:street":"Grachtstr",
    "iso:country":"NL",
    "sg:address":"Grachtstr 44",
    "sg:city":"Voerendaal",
    "sg:orig_category":"Belastingconsulenten/ Belastingadviseurs",
    "sg:phone":"+31 45 575 2703",
    "sg:postcode":"6367 CC",
    "sg:province":"Limburg",
    "wof:name":"Thevissen",
    "wof:placetype":"venue"
},
  "geometry": {"coordinates":[5.942433,50.878574],"type":"Point"}
}