{
  "type": "Feature",
  "properties": {
    "iso:country":"NL",
    "sg:address":"Het Rond 39",
    "sg:city":"Houten",
    "sg:orig_category":"Kappers",
    "sg:phone":"+31 30 637 5374",
    "sg:postcode":"3995 DK",
    "sg:province":"Utrecht",
    "wof:name":"Haarmode 2000",
    "wof:placetype":"venue"
},
  "geometry": {"coordinates":[5.1689629555,52.035068512],"type":"Point"}
}