{
  "type": "Feature",
  "properties": {
    "iso:country":"NL",
    "sg:address":"Dr. De Vriesstraat 37",
    "sg:city":"Benningbroek",
    "sg:orig_category":"Benzinestations And Brandstoffen",
    "sg:phone":"+31 229 591 292",
    "sg:postcode":"1654 JT",
    "sg:province":"Noord-Holland",
    "wof:name":"Fina",
    "wof:placetype":"venue"
},
  "geometry": {"coordinates":[5.022177,52.702557],"type":"Point"}
}