{
  "type": "Feature",
  "properties": {
    "addr:full":"Biest 98 Weert Limburg 6001 AS",
    "addr:housenumber":"98",
    "addr:postcode":"6001 as",
    "addr:street":"Biest",
    "iso:country":"NL",
    "sg:address":"Biest 98",
    "sg:city":"Weert",
    "sg:orig_category":"Video - Faciliteiten En Producties",
    "sg:phone":"+31 495 452 222",
    "sg:postcode":"6001 AS",
    "sg:province":"Limburg",
    "wof:name":"Linden, Van Der",
    "wof:placetype":"venue"
},
  "geometry": {"coordinates":[5.71335,51.259281],"type":"Point"}
}