{
  "type": "Feature",
  "properties": {
    "addr:full":"Damstraat 6 Amsterdam Noord-Holland 1012 JM",
    "addr:housenumber":"6",
    "addr:postcode":"1012 jm",
    "addr:street":"Damstraat",
    "iso:country":"NL",
    "sg:address":"Damstraat 6",
    "sg:city":"Amsterdam",
    "sg:classifiers":[
        {
            "category":"Shopping",
            "subcategory":"Gifts & Souvenirs",
            "type":"Retail Goods"
        }
    ],
    "sg:phone":"+31 20 626 2701",
    "sg:postcode":"1012 JM",
    "sg:province":"Noord-Holland",
    "sg:tags":[
        "geschenken"
    ],
    "wof:name":"Rally Wachtel",
    "wof:placetype":"venue"
},
  "geometry": {"coordinates":[4.894161,52.37225],"type":"Point"}
}