{
  "type": "Feature",
  "properties": {
    "iso:country":"NL",
    "sg:address":"Ln V Vollenhove 812",
    "sg:city":"Zeist",
    "sg:orig_category":"Acupunctuur",
    "sg:phone":"+31 30 693 0630",
    "sg:postcode":"3706 AA",
    "sg:province":"Utrecht",
    "wof:name":"Bos, A Van Den",
    "wof:placetype":"venue"
},
  "geometry": {"coordinates":[5.22124,52.100739],"type":"Point"}
}