{
  "type": "Feature",
  "properties": {
    "addr:full":"Holstr 23 Horst C\u00f3rdoba 5963 AR",
    "addr:housenumber":"23;5963",
    "addr:street":"Holstr;Co\u0301Rdoba",
    "iso:country":"NL",
    "sg:address":"Holstr 23",
    "sg:city":"Horst",
    "sg:orig_category":"Hek- En Rasterwerken",
    "sg:phone":"+31 77 398 5306",
    "sg:postcode":"5963 AR",
    "sg:province":"C\u00f3rdoba",
    "wof:name":"Roscha",
    "wof:placetype":"venue"
},
  "geometry": {"coordinates":[-63.418892,-31.569691],"type":"Point"}
}