{
  "type": "Feature",
  "properties": {
    "addr:full":"Wouwsewg 11 Roosendaal North Brabant 4703 BK",
    "addr:housenumber":"11",
    "addr:postcode":"4703 bk",
    "addr:street":"Wouwsewg",
    "iso:country":"NL",
    "sg:address":"Wouwsewg 11",
    "sg:city":"Roosendaal",
    "sg:orig_category":"Loodgieters",
    "sg:phone":"+31 165 534 439",
    "sg:postcode":"4703 BK",
    "sg:province":"North Brabant",
    "wof:name":"Adan, Firma",
    "wof:placetype":"venue"
},
  "geometry": {"coordinates":[4.445467,51.531925],"type":"Point"}
}