{
  "type": "Feature",
  "properties": {
    "addr:full":"Matsloot 16 Matsloot Provincie Drenthe 9749 TJ",
    "addr:housenumber":"16",
    "addr:postcode":"9749 tj",
    "addr:street":"Matsloot;Provincie",
    "iso:country":"NL",
    "sg:address":"Matsloot 16",
    "sg:city":"Matsloot",
    "sg:orig_category":"Loonbedrijven",
    "sg:phone":"+31 50 551 5467",
    "sg:postcode":"9749 TJ",
    "sg:province":"Provincie Drenthe",
    "wof:name":"Wobbes, Jan",
    "wof:placetype":"venue"
},
  "geometry": {"coordinates":[6.499402,53.194576],"type":"Point"}
}