{
  "type": "Feature",
  "properties": {
    "addr:full":"Leeuwenburgh 32 Abcoude Utrecht 1391 RE",
    "addr:housenumber":"32",
    "addr:postcode":"1391",
    "addr:street":"Leeuwenburgh",
    "iso:country":"NL",
    "sg:address":"Leeuwenburgh 32",
    "sg:city":"Abcoude",
    "sg:orig_category":"Organisatiebureaus",
    "sg:phone":"+31 294 285 082",
    "sg:postcode":"1391 RE",
    "sg:province":"Utrecht",
    "wof:name":"Feestgewoel, Het",
    "wof:placetype":"venue"
},
  "geometry": {"coordinates":[4.9662327766,52.2746658325],"type":"Point"}
}