{
  "type": "Feature",
  "properties": {
    "addr:full":"Noorderhoofdstr 169 Krommenie North Holland 1561 AT",
    "addr:housenumber":"169",
    "addr:postcode":"1561",
    "iso:country":"NL",
    "sg:address":"Noorderhoofdstr 169",
    "sg:city":"Krommenie",
    "sg:orig_category":"Machinehandel",
    "sg:phone":"+31 75 622 4519",
    "sg:postcode":"1561 AT",
    "sg:province":"North Holland",
    "wof:name":"Bakker, Simon",
    "wof:placetype":"venue"
},
  "geometry": {"coordinates":[4.772304,52.503139],"type":"Point"}
}