{
  "type": "Feature",
  "properties": {
    "addr:full":"Dauwdruppelhof 3 Fijnaart North Brabant 4793 CJ",
    "addr:housenumber":"3",
    "addr:postcode":"4793 cj",
    "addr:street":"Dauwdruppelhof",
    "iso:country":"NL",
    "sg:address":"Dauwdruppelhof 3",
    "sg:city":"Fijnaart",
    "sg:orig_category":"Kappers",
    "sg:phone":"+31 168 464 782",
    "sg:postcode":"4793 CJ",
    "sg:province":"North Brabant",
    "wof:name":"De Thuisknipperie",
    "wof:placetype":"venue"
},
  "geometry": {"coordinates":[4.4687619209,51.6394691467],"type":"Point"}
}