{
  "type": "Feature",
  "properties": {
    "iso:country":"NL",
    "sg:address":"Oostermeent W 19",
    "sg:city":"Huizen",
    "sg:orig_category":"Banken",
    "sg:phone":"+31 35 526 4118",
    "sg:postcode":"1274 SP",
    "sg:province":"Noord-Holland",
    "sg:website":"http://www.sns.nl",
    "wof:name":"Sns",
    "wof:placetype":"venue"
},
  "geometry": {"coordinates":[5.263126,52.295132],"type":"Point"}
}