{
  "type": "Feature",
  "properties": {
    "addr:full":"Paradysvogelstr 11E Groningen Groningen 9713 BV",
    "addr:housenumber":"11e",
    "addr:postcode":"9713 bv",
    "addr:street":"Paradysvogelstr",
    "iso:country":"NL",
    "sg:address":"Paradysvogelstr 11E",
    "sg:city":"Groningen",
    "sg:orig_category":"Onderzoekbureaus",
    "sg:phone":"+31 50 313 1273",
    "sg:postcode":"9713 BV",
    "sg:province":"Groningen",
    "wof:name":"Histodata",
    "wof:placetype":"venue"
},
  "geometry": {"coordinates":[6.583062,53.231667],"type":"Point"}
}