{
  "type": "Feature",
  "properties": {
    "addr:full":"Postbus 329 Dordrecht Zuid-Holland 3300 AH",
    "addr:housenumber":"329",
    "addr:postcode":"3300 ah",
    "addr:street":"Postbus",
    "iso:country":"NL",
    "sg:address":"Postbus 329",
    "sg:city":"Dordrecht",
    "sg:orig_category":"Scholen Voor Algemeen Voortgezet Onderwijs",
    "sg:phone":"+31 78 614 2322",
    "sg:postcode":"3300 AH",
    "sg:province":"Zuid-Holland",
    "wof:name":"Wartburgcoll",
    "wof:placetype":"venue"
},
  "geometry": {"coordinates":[4.66837,51.811199],"type":"Point"}
}