{
  "type": "Feature",
  "properties": {
    "iso:country":"NL",
    "sg:address":"J Vd Vondelln 13",
    "sg:city":"Apeldoorn",
    "sg:orig_category":"Verloskundigen",
    "sg:phone":"+31 55 355 4004",
    "sg:postcode":"7314 PE",
    "sg:province":"Gelderland",
    "wof:name":"Kamp-Vd Ven, P G Vd",
    "wof:placetype":"venue"
},
  "geometry": {"coordinates":[5.96566,52.216518],"type":"Point"}
}