{
  "type": "Feature",
  "properties": {
    "addr:full":"Dorpsstr 31 Oosterhout Gld Gelderland 6678 BE",
    "addr:housenumber":"31",
    "addr:postcode":"6678",
    "addr:street":"Dorpsstr;Gld Gelderland",
    "iso:country":"NL",
    "sg:address":"Dorpsstr 31",
    "sg:city":"Oosterhout Gld",
    "sg:classifiers":[
        {
            "category":"Retail",
            "subcategory":"Auto Repair",
            "type":"Services"
        }
    ],
    "sg:phone":"+31 481 481 080",
    "sg:postcode":"6678 BE",
    "sg:province":"Gelderland",
    "sg:tags":[
        "garage"
    ],
    "wof:name":"Hoogsteder, Vakgarage",
    "wof:placetype":"venue"
},
  "geometry": {"coordinates":[5.825567,51.878593],"type":"Point"}
}