{
  "type": "Feature",
  "properties": {
    "iso:country":"NL",
    "sg:address":"Gr Wichman 5",
    "sg:city":"Huizen",
    "sg:orig_category":"Bejaarden - Verzorgingstehuizen",
    "sg:phone":"+31 35 524 8070",
    "sg:postcode":"1276 KA",
    "sg:province":"Noord-Holland",
    "wof:name":"Marke De Meenthoek, De",
    "wof:placetype":"venue"
},
  "geometry": {"coordinates":[5.242299,52.299263],"type":"Point"}
}