{
  "type": "Feature",
  "properties": {
    "iso:country":"NL",
    "sg:address":"Buizerdstraat 68",
    "sg:city":"Maassluis",
    "sg:orig_category":"Fotografische And Optische Artikelen Gh",
    "sg:phone":"+31 10 591 3258",
    "sg:postcode":"3145 AD",
    "sg:province":"South Holland",
    "wof:name":"Jan Klip Optiek",
    "wof:placetype":"venue"
},
  "geometry": {"coordinates":[4.234137,51.934185],"type":"Point"}
}