{
  "type": "Feature",
  "properties": {
    "addr:full":"Vlaardingenstr 10 Almere Flevoland 1324 LC",
    "addr:housenumber":"10",
    "addr:postcode":"1324 lc",
    "addr:street":"Vlaardingenstr;Flevoland",
    "iso:country":"NL",
    "sg:address":"Vlaardingenstr 10",
    "sg:city":"Almere",
    "sg:orig_category":"Verhuur",
    "sg:phone":"+31 36 530 3443",
    "sg:postcode":"1324 LC",
    "sg:province":"Flevoland",
    "sg:website":"http://www.boels.nl",
    "wof:name":"Boels Almere",
    "wof:placetype":"venue"
},
  "geometry": {"coordinates":[5.201278,52.362335],"type":"Point"}
}