{
  "type": "Feature",
  "properties": {
    "iso:country":"NL",
    "sg:address":"Kerkeland 37",
    "sg:city":"Enkhuizen",
    "sg:orig_category":"Verzekeringen",
    "sg:phone":"+31 228 315 511",
    "sg:postcode":"1602 LE",
    "sg:province":"North Holland",
    "wof:name":"Peter De Wilde Vof",
    "wof:placetype":"venue"
},
  "geometry": {"coordinates":[5.273979,52.713879],"type":"Point"}
}