{
  "type": "Feature",
  "properties": {
    "addr:full":"Dollard 89 Drachten Friesland 9204 CM",
    "addr:housenumber":"89",
    "addr:postcode":"9204 cm",
    "addr:street":"Dollard",
    "iso:country":"NL",
    "sg:address":"Dollard 89",
    "sg:city":"Drachten",
    "sg:orig_category":"Scholen Voor Basisonderwijs",
    "sg:phone":"+31 512 510 150",
    "sg:postcode":"9204 CM",
    "sg:province":"Friesland",
    "wof:name":"Tweesprong Openb, De",
    "wof:placetype":"venue"
},
  "geometry": {"coordinates":[6.069341,53.098675],"type":"Point"}
}