{
  "type": "Feature",
  "properties": {
    "addr:full":"Sloetsweg 100 Hengelo Ov Overijssel 7557 HP",
    "addr:housenumber":"100",
    "addr:postcode":"7557 hp",
    "addr:street":"Sloetsweg;Ov",
    "iso:country":"NL",
    "sg:address":"Sloetsweg 100",
    "sg:city":"Hengelo Ov",
    "sg:orig_category":"Schoenen",
    "sg:phone":"+31 74 291 4085",
    "sg:postcode":"7557 HP",
    "sg:province":"Overijssel",
    "wof:name":"Nijhof Schoenen En Tassen Bv",
    "wof:placetype":"venue"
},
  "geometry": {"coordinates":[6.804398,52.273174],"type":"Point"}
}