{
  "type": "Feature",
  "properties": {
    "addr:full":"Brouwerstr 5 Sliedrecht South Holland 3364 BE",
    "addr:housenumber":"5",
    "addr:postcode":"3364",
    "addr:street":"Brouwerstr",
    "iso:country":"NL",
    "sg:address":"Brouwerstr 5",
    "sg:city":"Sliedrecht",
    "sg:orig_category":"Woninginrichting",
    "sg:phone":"+31 184 425 711",
    "sg:postcode":"3364 BE",
    "sg:province":"South Holland",
    "wof:name":"Kwantum",
    "wof:placetype":"venue"
},
  "geometry": {"coordinates":[4.7499699593,51.8325462341],"type":"Point"}
}