{
  "type": "Feature",
  "properties": {
    "addr:full":"Aak 3 Assen Provincie Drenthe 9408 CD",
    "addr:housenumber":"3",
    "addr:postcode":"9408 cd",
    "addr:street":"Aak;Provincie Drenthe",
    "iso:country":"NL",
    "sg:address":"Aak 3",
    "sg:city":"Assen",
    "sg:orig_category":"Webdesign Bureaus",
    "sg:phone":"+31 592 399 334",
    "sg:postcode":"9408 CD",
    "sg:province":"Provincie Drenthe",
    "sg:website":"http://www.webd-sign.nl",
    "wof:name":"Cygnus",
    "wof:placetype":"venue"
},
  "geometry": {"coordinates":[6.5131230354,52.9972839355],"type":"Point"}
}