{
  "type": "Feature",
  "properties": {
    "addr:full":"Scheldestr 58 Alkmaar North Holland 1823 WB",
    "addr:housenumber":"58",
    "addr:postcode":"1823 wb",
    "addr:street":"Scheldestr",
    "iso:country":"NL",
    "sg:address":"Scheldestr 58",
    "sg:city":"Alkmaar",
    "sg:orig_category":"Hypotheken",
    "sg:phone":"+31 800 1600",
    "sg:postcode":"1823 WB",
    "sg:province":"North Holland",
    "sg:website":"http://www.vanbruggen.nl",
    "wof:name":"Bruggen Adviesgroep, Van",
    "wof:placetype":"venue"
},
  "geometry": {"coordinates":[4.766358,52.629993],"type":"Point"}
}