{
  "type": "Feature",
  "properties": {
    "iso:country":"NL",
    "sg:address":"Bornholmstraat 20",
    "sg:city":"Groningen",
    "sg:orig_category":"Pleziervaartuigen And Reparatie",
    "sg:phone":"+31 50 313 7665",
    "sg:postcode":"9723 AX",
    "sg:province":"Groningen",
    "wof:name":"Droogdok Groningen",
    "wof:placetype":"venue"
},
  "geometry": {"coordinates":[6.593303,53.217213],"type":"Point"}
}