{
  "type": "Feature",
  "properties": {
    "addr:full":"Beelaarts V Bloklandstr 10 Tilburg North Brabant 5042 PM",
    "addr:housenumber":"10",
    "addr:postcode":"5042 pm",
    "addr:street":"Bloklandstr",
    "iso:country":"NL",
    "sg:address":"Beelaarts V Bloklandstr 10",
    "sg:city":"Tilburg",
    "sg:orig_category":"Goederenvervoer Over De Weg",
    "sg:phone":"+31 13 463 8038",
    "sg:postcode":"5042 PM",
    "sg:province":"North Brabant",
    "wof:name":"Transportbedrijf Jos Zebregs & Zonen Bv",
    "wof:placetype":"venue"
},
  "geometry": {"coordinates":[5.059773,51.564026],"type":"Point"}
}