{
  "type": "Feature",
  "properties": {
    "iso:country":"NL",
    "sg:address":"Wormerhoek 14",
    "sg:city":"Capelle Ad Yssel",
    "sg:classifiers":[
        {
            "category":"Professional",
            "subcategory":"Accounting & Tax Preparation",
            "type":"Services"
        }
    ],
    "sg:phone":"+31 10 450 7677",
    "sg:postcode":"2905 TX",
    "sg:province":"Zuid-Holland",
    "sg:tags":[
        "accountant",
        "en",
        "-kantoren",
        "register-"
    ],
    "wof:name":"Ruigendijk, J",
    "wof:placetype":"venue"
},
  "geometry": {"coordinates":[-100.07679,31.168989],"type":"Point"}
}