{
  "type": "Feature",
  "properties": {
    "addr:full":"Postbus 82 Volendam North Holland 1130 AB",
    "addr:housenumber":"82",
    "addr:postcode":"1130 ab",
    "addr:street":"Postbus",
    "iso:country":"NL",
    "sg:address":"Postbus 82",
    "sg:city":"Volendam",
    "sg:orig_category":"Voetbalverenigingen",
    "sg:phone":"+31 299 369 400",
    "sg:postcode":"1130 AB",
    "sg:province":"North Holland",
    "wof:name":"Fc Volendam",
    "wof:placetype":"venue"
},
  "geometry": {"coordinates":[5.07119,52.49493],"type":"Point"}
}