{
  "type": "Feature",
  "properties": {
    "iso:country":"NL",
    "sg:address":"Ln V D H Meesters 429",
    "sg:city":"Amstelveen",
    "sg:orig_category":"Bedrijfsopleidingen",
    "sg:phone":"+31 20 643 9344",
    "sg:postcode":"1186 AL",
    "sg:province":"Noord-Holland",
    "wof:name":"Im & B Bv",
    "wof:placetype":"venue"
},
  "geometry": {"coordinates":[4.856945,52.303444],"type":"Point"}
}