{
  "type": "Feature",
  "properties": {
    "iso:country":"NL",
    "sg:address":"Kofschipstraat 10",
    "sg:city":"Alkmaar",
    "sg:classifiers":[
        {
            "category":"Education",
            "subcategory":"Preschool",
            "type":"Public Place"
        }
    ],
    "sg:phone":"+31 72 561 5008",
    "sg:postcode":"1826 CG",
    "sg:province":"Noord-Holland",
    "sg:tags":[
        "kleuteronderwijs",
        "basis-"
    ],
    "wof:name":"Openbare Basisschool De Vlieger",
    "wof:placetype":"venue"
},
  "geometry": {"coordinates":[4.763602,52.652962],"type":"Point"}
}