{
  "type": "Feature",
  "properties": {
    "iso:country":"NL",
    "sg:address":"Hazelaarweg 48",
    "sg:city":"Hengelo Ov",
    "sg:orig_category":"Wasserettes And Stomerijen",
    "sg:phone":"+31 74 291 3281",
    "sg:postcode":"7556 DP",
    "sg:province":"Overijssel",
    "wof:name":"Wasserij F. Rosink",
    "wof:placetype":"venue"
},
  "geometry": {"coordinates":[6.7931919098,52.2724380493],"type":"Point"}
}