{
  "type": "Feature",
  "properties": {
    "addr:full":"Wilhelminalaan 20 Soest Utrecht 3761 DP",
    "addr:housenumber":"20",
    "addr:postcode":"3761 dp",
    "addr:street":"Wilhelminalaan",
    "iso:country":"NL",
    "sg:address":"Wilhelminalaan 20",
    "sg:city":"Soest",
    "sg:orig_category":"Loodgieterswerk, Verwarming And Sanitaire Installaties",
    "sg:phone":"+31 35 601 7332",
    "sg:postcode":"3761 DP",
    "sg:province":"Utrecht",
    "wof:name":"Loodgietersbedrijf Soest Bv",
    "wof:placetype":"venue"
},
  "geometry": {"coordinates":[5.300385,52.184044],"type":"Point"}
}