{
  "type": "Feature",
  "properties": {
    "addr:full":"Daalseweg 111 Nijmegen Gelderland 6521 GG",
    "addr:housenumber":"111",
    "addr:postcode":"6521 gg",
    "addr:street":"Daalseweg;Gelderland",
    "iso:country":"NL",
    "sg:address":"Daalseweg 111",
    "sg:city":"Nijmegen",
    "sg:orig_category":"Kappers",
    "sg:phone":"+31 24 322 9460",
    "sg:postcode":"6521 GG",
    "sg:province":"Gelderland",
    "wof:name":"Kapsalon Ter Huurne",
    "wof:placetype":"venue"
},
  "geometry": {"coordinates":[5.8719167709,51.8407554626],"type":"Point"}
}