{
  "type": "Feature",
  "properties": {
    "addr:full":"Osdorper Ban 64 Amsterdam Noord-Holland 1068 MJ",
    "addr:housenumber":"64",
    "addr:postcode":"1068 mj",
    "addr:street":"Osdorper Ban",
    "iso:country":"NL",
    "sg:address":"Osdorper Ban 64",
    "sg:city":"Amsterdam",
    "sg:orig_category":"Kappers",
    "sg:phone":"+31 20 610 0126",
    "sg:postcode":"1068 MJ",
    "sg:province":"Noord-Holland",
    "wof:name":"Haarverzorging Liselot",
    "wof:placetype":"venue"
},
  "geometry": {"coordinates":[4.8002490997,52.3623008728],"type":"Point"}
}