{
  "type": "Feature",
  "properties": {
    "addr:full":"Bergse Maas 9 Pynacker South Holland 2641 VV",
    "addr:housenumber":"9",
    "addr:postcode":"2641 vv",
    "addr:street":"Bergse Maas;Pynacker South",
    "iso:country":"NL",
    "sg:address":"Bergse Maas 9",
    "sg:city":"Pynacker",
    "sg:orig_category":"Waterbehandeling En Waterzuiverings- Systemen",
    "sg:phone":"+31 15 364 0527",
    "sg:postcode":"2641 VV",
    "sg:province":"South Holland",
    "sg:website":"http://www.ovitae.nl",
    "wof:name":"Ovitae",
    "wof:placetype":"venue"
},
  "geometry": {"coordinates":[4.4336562157,52.0104942322],"type":"Point"}
}