{
  "type": "Feature",
  "properties": {
    "addr:full":"Jan Binneslaan 88 Surhuisterveen Provincie Friesland 9231 CC",
    "addr:housenumber":"88",
    "addr:postcode":"9231 cc",
    "addr:street":"Jan Binneslaan;Provincie Friesland",
    "iso:country":"NL",
    "sg:address":"Jan Binneslaan 88",
    "sg:city":"Surhuisterveen",
    "sg:orig_category":"Schilderwerk",
    "sg:phone":"+31 512 361 454",
    "sg:postcode":"9231 CC",
    "sg:province":"Provincie Friesland",
    "wof:name":"Firma H. Walda En Zoon",
    "wof:placetype":"venue"
},
  "geometry": {"coordinates":[6.169531,53.180016],"type":"Point"}
}