{
  "type": "Feature",
  "properties": {
    "addr:full":"Kortewelle 26 Rotterdam Zuid-Holland 3075 WS",
    "addr:housenumber":"26",
    "addr:postcode":"3075 ws",
    "addr:street":"Kortewelle",
    "iso:country":"NL",
    "sg:address":"Kortewelle 26",
    "sg:city":"Rotterdam",
    "sg:orig_category":"Loodgieters",
    "sg:phone":"+31 10 419 3644",
    "sg:postcode":"3075 WS",
    "sg:province":"Zuid-Holland",
    "wof:name":"Meggelen, J Van",
    "wof:placetype":"venue"
},
  "geometry": {"coordinates":[4.514411,51.889202],"type":"Point"}
}