{
  "type": "Feature",
  "properties": {
    "addr:full":"Stoofstraat 21 Oudenbosch Noord-Brabant 4731 HW",
    "addr:housenumber":"21",
    "addr:postcode":"4731 hw",
    "addr:street":"Stoofstraat",
    "iso:country":"NL",
    "sg:address":"Stoofstraat 21",
    "sg:city":"Oudenbosch",
    "sg:orig_category":"Elektronische Bedrijfsinstallaties",
    "sg:phone":"+31 165 315 772",
    "sg:postcode":"4731 HW",
    "sg:province":"Noord-Brabant",
    "wof:name":"Bbbbb",
    "wof:placetype":"venue"
},
  "geometry": {"coordinates":[4.527113,51.5896],"type":"Point"}
}