{
  "type": "Feature",
  "properties": {
    "addr:full":"Concordialaan 8 Ede Gld Gelderland 6712 GM",
    "addr:housenumber":"8",
    "addr:postcode":"6712 gm",
    "addr:street":"Concordialaan;Gld Gelderland",
    "iso:country":"NL",
    "sg:address":"Concordialaan 8",
    "sg:city":"Ede Gld",
    "sg:orig_category":"Veilingen",
    "sg:phone":"+31 318 610 057",
    "sg:postcode":"6712 GM",
    "sg:province":"Gelderland",
    "wof:name":"J. Spies",
    "wof:placetype":"venue"
},
  "geometry": {"coordinates":[5.665527,52.050392],"type":"Point"}
}