{
  "type": "Feature",
  "properties": {
    "addr:full":"Uno Str 43 Hulsberg Limburg 6336 BS",
    "addr:housenumber":"43",
    "addr:postcode":"6336 bs",
    "addr:street":"Str",
    "iso:country":"NL",
    "sg:address":"Uno Str 43",
    "sg:city":"Hulsberg",
    "sg:orig_category":"Voegwerken",
    "sg:phone":"+31 45 405 1641",
    "sg:postcode":"6336 BS",
    "sg:province":"Limburg",
    "wof:name":"Garant",
    "wof:placetype":"venue"
},
  "geometry": {"coordinates":[5.855893,50.886414],"type":"Point"}
}