{
  "type": "Feature",
  "properties": {
    "addr:full":"Peperstraat 1 Grevenbicht Limburg 6127 AS",
    "addr:housenumber":"1",
    "addr:postcode":"6127 as",
    "addr:street":"Peperstraat",
    "iso:country":"NL",
    "sg:address":"Peperstraat 1",
    "sg:city":"Grevenbicht",
    "sg:classifiers":[
        {
            "category":"Food & Beverages",
            "subcategory":"Fruits & Vegetables",
            "type":"Retail Goods"
        }
    ],
    "sg:phone":"+31 46 485 7520",
    "sg:postcode":"6127 AS",
    "sg:province":"Limburg",
    "sg:tags":[
        "groenten"
    ],
    "wof:name":"A.M.C. V Didden-Storms",
    "wof:placetype":"venue"
},
  "geometry": {"coordinates":[5.770016,51.041306],"type":"Point"}
}