{
  "type": "Feature",
  "properties": {
    "addr:full":"Espelerlaan 33 Emmeloord Flevoland 8302 CE",
    "addr:housenumber":"33",
    "addr:postcode":"8302 ce",
    "addr:street":"Espelerlaan;Flevoland",
    "iso:country":"NL",
    "sg:address":"Espelerlaan 33",
    "sg:city":"Emmeloord",
    "sg:orig_category":"Artsen And Specialisten",
    "sg:phone":"+31 527 612 100",
    "sg:postcode":"8302 CE",
    "sg:province":"Flevoland",
    "wof:name":"J Van Faassen",
    "wof:placetype":"venue"
},
  "geometry": {"coordinates":[5.749289,52.712566],"type":"Point"}
}