{
  "type": "Feature",
  "properties": {
    "addr:full":"De Haal 4 Oostzaan Noord-Holland 1511 AR",
    "addr:housenumber":"4",
    "addr:postcode":"1511",
    "addr:street":"De Haal",
    "iso:country":"NL",
    "sg:address":"De Haal 4",
    "sg:city":"Oostzaan",
    "sg:orig_category":"Beeldende Kunstenaars",
    "sg:phone":"+31 75 684 1805",
    "sg:postcode":"1511 AR",
    "sg:province":"Noord-Holland",
    "wof:name":"Klop, J",
    "wof:placetype":"venue"
},
  "geometry": {"coordinates":[4.868997,52.45546],"type":"Point"}
}