{
  "type": "Feature",
  "properties": {
    "addr:full":"Tarasconwg 10 Eindhoven North Brabant 5627 GB",
    "addr:housenumber":"10",
    "addr:postcode":"5627 gb",
    "addr:street":"Tarasconwg",
    "iso:country":"NL",
    "sg:address":"Tarasconwg 10",
    "sg:city":"Eindhoven",
    "sg:classifiers":[
        {
            "category":"Wholesale",
            "subcategory":"Meat",
            "type":"Manufacturing & Wholesale Goods"
        }
    ],
    "sg:phone":"+31 40 248 2255",
    "sg:postcode":"5627 GB",
    "sg:province":"North Brabant",
    "sg:tags":[
        "regeltechniek",
        "en",
        "meet-"
    ],
    "wof:name":"Fischer Bv, H",
    "wof:placetype":"venue"
},
  "geometry": {"coordinates":[5.442849,51.478199],"type":"Point"}
}