{
  "type": "Feature",
  "properties": {
    "addr:full":"Papesteeg 98 Tiel Gelderland 4006 WG",
    "addr:housenumber":"98",
    "addr:postcode":"4006 wg",
    "addr:street":"Papesteeg;Gelderland",
    "iso:country":"NL",
    "sg:address":"Papesteeg 98",
    "sg:city":"Tiel",
    "sg:orig_category":"Goederenvervoer Over De Weg",
    "sg:phone":"+31 344 654 975",
    "sg:postcode":"4006 WG",
    "sg:province":"Gelderland",
    "wof:name":"Wetro Tiel Bv",
    "wof:placetype":"venue"
},
  "geometry": {"coordinates":[5.415692,51.884815],"type":"Point"}
}