{
  "type": "Feature",
  "properties": {
    "iso:country":"NL",
    "sg:address":"Dorpstraat 4",
    "sg:city":"Elsloo Lb",
    "sg:orig_category":"Kappers",
    "sg:phone":"+31 46 437 9569",
    "sg:postcode":"6181 GX",
    "sg:province":"Limburg",
    "wof:name":"Fonzies",
    "wof:placetype":"venue"
},
  "geometry": {"coordinates":[5.7594819069,50.9474143982],"type":"Point"}
}