{
  "type": "Feature",
  "properties": {
    "iso:country":"NL",
    "sg:address":"Burgemeester Tonckensstr 53",
    "sg:city":"Zuidwolde Dr",
    "sg:orig_category":"Bloemen And Planten",
    "sg:phone":"+31 528 374 312",
    "sg:postcode":"7921 KB",
    "sg:province":"Drenthe",
    "wof:name":"Groencentrum Zuidwolde",
    "wof:placetype":"venue"
},
  "geometry": {"coordinates":[6.42853,52.67675],"type":"Point"}
}