{
  "type": "Feature",
  "properties": {
    "addr:full":"Edisonwg 9 Bunschoten Spakenb Utrecht 3752 LV",
    "addr:housenumber":"9",
    "addr:postcode":"3752",
    "addr:street":"Edisonwg",
    "iso:country":"NL",
    "sg:address":"Edisonwg 9",
    "sg:city":"Bunschoten Spakenb",
    "sg:orig_category":"Ovenbouw",
    "sg:phone":"+31 33 298 1944",
    "sg:postcode":"3752 LV",
    "sg:province":"Utrecht",
    "wof:name":"Pol Bv, Van Der",
    "wof:placetype":"venue"
},
  "geometry": {"coordinates":[5.3665552139,52.2301254272],"type":"Point"}
}