{
  "type": "Feature",
  "properties": {
    "addr:full":"Sluisdijk 25 Joure Friesland 8501 BZ",
    "addr:housenumber":"25",
    "addr:postcode":"8501 bz",
    "addr:street":"Sluisdijk",
    "iso:country":"NL",
    "sg:address":"Sluisdijk 25",
    "sg:city":"Joure",
    "sg:classifiers":[
        {
            "category":"Education",
            "subcategory":"Preschool",
            "type":"Public Place"
        }
    ],
    "sg:phone":"+31 513 414 244",
    "sg:postcode":"8501 BZ",
    "sg:province":"Friesland",
    "sg:tags":[
        "kleuteronderwijs",
        "basis-"
    ],
    "wof:name":"Dr. G.A. Wumkesskoalle",
    "wof:placetype":"venue"
},
  "geometry": {"coordinates":[5.798252,52.969879],"type":"Point"}
}