{
  "type": "Feature",
  "properties": {
    "iso:country":"NL",
    "sg:address":"Berglustln 28",
    "sg:city":"Rotterdam",
    "sg:orig_category":"Adviesbureaus Bedrijfsorganisatie",
    "sg:phone":"+31 10 418 8405",
    "sg:postcode":"3054 BH",
    "sg:province":"Zuid-Holland",
    "wof:name":"Deutz Ebeling, A H",
    "wof:placetype":"venue"
},
  "geometry": {"coordinates":[4.49156,51.955482],"type":"Point"}
}