{
  "type": "Feature",
  "properties": {
    "iso:country":"NL",
    "sg:address":"Lindeijerlaan 8",
    "sg:city":"Vlissingen",
    "sg:orig_category":"Overheidsdiensten",
    "sg:phone":"+31 118 460 337",
    "sg:postcode":"4386 EA",
    "sg:province":"Zeeland",
    "wof:name":"Het Bolwerk",
    "wof:placetype":"venue"
},
  "geometry": {"coordinates":[3.5819840431,51.4659919739],"type":"Point"}
}