{
  "type": "Feature",
  "properties": {
    "addr:full":"Bornestraat 252 Almelo Overijssel 7601 PC",
    "addr:housenumber":"252",
    "addr:postcode":"7601 pc",
    "addr:street":"Bornestraat",
    "iso:country":"NL",
    "sg:address":"Bornestraat 252",
    "sg:city":"Almelo",
    "sg:classifiers":[
        {
            "category":"Fast Food",
            "type":"Food & Drink"
        }
    ],
    "sg:phone":"+31 546 814 849",
    "sg:postcode":"7601 PC",
    "sg:province":"Overijssel",
    "sg:tags":[
        "afhaal",
        "restaurant"
    ],
    "wof:name":"International Chin. Indisch Japans Rest.",
    "wof:placetype":"venue"
},
  "geometry": {"coordinates":[6.661127,52.347752],"type":"Point"}
}