{
  "type": "Feature",
  "properties": {
    "iso:country":"NL",
    "sg:address":"Jan Van Gentstraat 96",
    "sg:city":"Badhoevedorp",
    "sg:orig_category":"Meubelzaken, Woning- And Keukeninrichting",
    "sg:phone":"+31 20 659 8892",
    "sg:postcode":"1171 GM",
    "sg:province":"North Holland",
    "wof:name":"J. V.D. Pol Interieur & Projekt",
    "wof:placetype":"venue"
},
  "geometry": {"coordinates":[4.794904,52.336597],"type":"Point"}
}