{
  "type": "Feature",
  "properties": {
    "iso:country":"NL",
    "sg:address":"A Pieckln 15",
    "sg:city":"Hollandsche Rading",
    "sg:orig_category":"Adviesbureaus Personeel",
    "sg:phone":"+31 35 577 1671",
    "sg:postcode":"3739 LG",
    "sg:province":"Utrecht",
    "wof:name":"P & O Support",
    "wof:placetype":"venue"
},
  "geometry": {"coordinates":[5.175085,52.174858],"type":"Point"}
}