{
  "type": "Feature",
  "properties": {
    "iso:country":"NL",
    "sg:address":"De West 1",
    "sg:city":"Dronten",
    "sg:orig_category":"Schilders",
    "sg:phone":"+31 6 20056394",
    "sg:postcode":"8251 ST",
    "sg:province":"Flevoland",
    "wof:name":"Engelen, Van",
    "wof:placetype":"venue"
},
  "geometry": {"coordinates":[5.701415,52.522099],"type":"Point"}
}