{
  "type": "Feature",
  "properties": {
    "addr:full":"Geerdinkswg 141 Hengelo Ov Overijssel 7555 DL",
    "addr:housenumber":"141",
    "addr:postcode":"7555 dl",
    "addr:street":"Ov",
    "iso:country":"NL",
    "sg:address":"Geerdinkswg 141",
    "sg:city":"Hengelo Ov",
    "sg:orig_category":"Ziekenhuizen, Sanatoria, Verpleeghuizen",
    "sg:phone":"+31 74 247 5387",
    "sg:postcode":"7555 DL",
    "sg:province":"Overijssel",
    "wof:name":"Zorgservices Twente",
    "wof:placetype":"venue"
},
  "geometry": {"coordinates":[6.77394,52.263618],"type":"Point"}
}