{
  "type": "Feature",
  "properties": {
    "addr:full":"Ginderdoor 15 Mariahout North Brabant 5738 AA",
    "addr:housenumber":"15",
    "addr:postcode":"5738 aa",
    "addr:street":"Ginderdoor",
    "iso:country":"NL",
    "sg:address":"Ginderdoor 15",
    "sg:city":"Mariahout",
    "sg:classifiers":[
        {
            "category":"Retail",
            "subcategory":"Auto Repair",
            "type":"Services"
        }
    ],
    "sg:phone":"+31 499 422 222",
    "sg:postcode":"5738 AA",
    "sg:province":"North Brabant",
    "sg:tags":[
        "garage"
    ],
    "wof:name":"Sanders, J",
    "wof:placetype":"venue"
},
  "geometry": {"coordinates":[5.580399,51.534401],"type":"Point"}
}