{
  "type": "Feature",
  "properties": {
    "addr:full":"Zandstr 22 Liessel North Brabant 5757 BM",
    "addr:housenumber":"22",
    "addr:postcode":"5757 bm",
    "addr:street":"Zandstr",
    "iso:country":"NL",
    "sg:address":"Zandstr 22",
    "sg:city":"Liessel",
    "sg:orig_category":"Metselwerken",
    "sg:phone":"+31 493 342 687",
    "sg:postcode":"5757 BM",
    "sg:province":"North Brabant",
    "wof:name":"Meulendijks, F",
    "wof:placetype":"venue"
},
  "geometry": {"coordinates":[5.821032,51.411179],"type":"Point"}
}