{
  "type": "Feature",
  "properties": {
    "addr:full":"Kloosterkd 155 Delft Zuid-Holland 2628 HZ",
    "addr:housenumber":"155",
    "addr:postcode":"delft;2628 hz",
    "iso:country":"NL",
    "sg:address":"Kloosterkd 155",
    "sg:city":"Delft",
    "sg:orig_category":"Fotostudio'S",
    "sg:phone":"+31 6 51107536",
    "sg:postcode":"2628 HZ",
    "sg:province":"Zuid-Holland",
    "sg:website":"http://www.zonderland.nl",
    "wof:name":"Zonderland, Herman",
    "wof:placetype":"venue"
},
  "geometry": {"coordinates":[4.379029,52.005882],"type":"Point"}
}