{
  "type": "Feature",
  "properties": {
    "addr:full":"Kostverlorenweg 6 Soest Utrecht 3762 EM",
    "addr:housenumber":"6",
    "addr:postcode":"3762 em",
    "addr:street":"Kostverlorenweg",
    "iso:country":"NL",
    "sg:address":"Kostverlorenweg 6",
    "sg:city":"Soest",
    "sg:orig_category":"Autokeuringen",
    "sg:phone":"+31 35 601 8175",
    "sg:postcode":"3762 EM",
    "sg:province":"Utrecht",
    "wof:name":"Temur Doe Het Zelf Garage",
    "wof:placetype":"venue"
},
  "geometry": {"coordinates":[5.272987,52.181274],"type":"Point"}
}