{
  "type": "Feature",
  "properties": {
    "iso:country":"NL",
    "sg:address":"Jean Sibeliusstraat 105",
    "sg:city":"Rotterdam",
    "sg:orig_category":"Verhuur Diversen",
    "sg:phone":"+31 10 456 2821",
    "sg:postcode":"3069 MJ",
    "sg:province":"South Holland",
    "wof:name":"Lion Facilitair Vof",
    "wof:placetype":"venue"
},
  "geometry": {"coordinates":[4.55846,51.965317],"type":"Point"}
}