{
  "type": "Feature",
  "properties": {
    "addr:full":"V Zeggelenln 220 S Gravenhage Zuid-Holland 2524 AX",
    "addr:housenumber":"220;gravenhage",
    "addr:postcode":"2524 ax",
    "addr:street":"S",
    "iso:country":"NL",
    "sg:address":"V Zeggelenln 220",
    "sg:city":"S Gravenhage",
    "sg:orig_category":"Wasserijen",
    "sg:phone":"+31 70 390 1115",
    "sg:postcode":"2524 AX",
    "sg:province":"Zuid-Holland",
    "wof:name":"Bright, Wasserij",
    "wof:placetype":"venue"
},
  "geometry": {"coordinates":[4.3153800964,52.0524215698],"type":"Point"}
}