{
  "type": "Feature",
  "properties": {
    "addr:full":"Weidehek 58-C Breda Noord-Brabant 4824 AS",
    "addr:housenumber":"58-c",
    "addr:postcode":"4824 as",
    "addr:street":"Weidehek",
    "iso:country":"NL",
    "sg:address":"Weidehek 58-C",
    "sg:city":"Breda",
    "sg:orig_category":"Geluidsinstallaties",
    "sg:phone":"+31 76 549 8808",
    "sg:postcode":"4824 AS",
    "sg:province":"Noord-Brabant",
    "sg:website":"http://www.mjsound.nl",
    "wof:name":"Mj Sound",
    "wof:placetype":"venue"
},
  "geometry": {"coordinates":[4.75365,51.615002],"type":"Point"}
}