{
  "type": "Feature",
  "properties": {
    "addr:full":"Grote Houtstraat 28 Haarlem Noord-Holland 2011 SN",
    "addr:housenumber":"28",
    "addr:postcode":"2011 sn",
    "addr:street":"Grote Houtstraat",
    "iso:country":"NL",
    "sg:address":"Grote Houtstraat 28",
    "sg:city":"Haarlem",
    "sg:orig_category":"Baby- And Kinderkleding",
    "sg:phone":"+31 23 531 5769",
    "sg:postcode":"2011 SN",
    "sg:province":"Noord-Holland",
    "wof:name":"We Men",
    "wof:placetype":"venue"
},
  "geometry": {"coordinates":[4.634794,52.380306],"type":"Point"}
}