{
  "type": "Feature",
  "properties": {
    "addr:full":"Hilversumseweg 51 Laren Nh North Holland 1251 EW",
    "addr:housenumber":"51",
    "addr:postcode":"1251 ew",
    "addr:street":"Hilversumseweg;Nh North",
    "iso:country":"NL",
    "sg:address":"Hilversumseweg 51",
    "sg:city":"Laren Nh",
    "sg:orig_category":"Musea And Historische Gebouwen",
    "sg:phone":"+31 35 538 2520",
    "sg:postcode":"1251 EW",
    "sg:province":"North Holland",
    "wof:name":"Geologisch Museum Hofland",
    "wof:placetype":"venue"
},
  "geometry": {"coordinates":[5.207433,52.246052],"type":"Point"}
}