{
  "type": "Feature",
  "properties": {
    "iso:country":"NL",
    "sg:address":"Hilversumseweg 51",
    "sg:city":"Laren Nh",
    "sg:orig_category":"Musea And Historische Gebouwen",
    "sg:phone":"+31 35 538 2520",
    "sg:postcode":"1251 EW",
    "sg:province":"North Holland",
    "wof:name":"Geologisch Museum Hofland",
    "wof:placetype":"venue"
},
  "geometry": {"coordinates":[5.207433,52.246052],"type":"Point"}
}