{
  "type": "Feature",
  "properties": {
    "addr:full":"Westdk 5B Alkmaar Noord-Holland 1812 MC",
    "addr:housenumber":"5b",
    "addr:postcode":"1812 mc",
    "addr:street":"Westdk",
    "iso:country":"NL",
    "sg:address":"Westdk 5B",
    "sg:city":"Alkmaar",
    "sg:orig_category":"Verenigingen En Stichtingen",
    "sg:phone":"+31 72 511 3559",
    "sg:postcode":"1812 MC",
    "sg:province":"Noord-Holland",
    "wof:name":"Atv De Westdijk Tuinver",
    "wof:placetype":"venue"
},
  "geometry": {"coordinates":[4.76596,52.609928],"type":"Point"}
}