{
  "type": "Feature",
  "properties": {
    "iso:country":"NL",
    "sg:address":"Tielsestraat 11",
    "sg:city":"Opheusden",
    "sg:orig_category":"Bloemen- And Plantenteelt",
    "sg:phone":"+31 488 442 345",
    "sg:postcode":"4043 JP",
    "sg:province":"Gelderland",
    "wof:name":"Den Haan Boom- En Bloemenkwekerij",
    "wof:placetype":"venue"
},
  "geometry": {"coordinates":[5.614932,51.935814],"type":"Point"}
}