{
  "type": "Feature",
  "properties": {
    "addr:full":"Kameraarsweide 8 Nieuwegein Utrecht 3437 CB",
    "addr:housenumber":"8",
    "addr:postcode":"3437 cb",
    "addr:street":"Kameraarsweide",
    "iso:country":"NL",
    "sg:address":"Kameraarsweide 8",
    "sg:city":"Nieuwegein",
    "sg:orig_category":"Verzekeringen",
    "sg:phone":"+31 30 603 5723",
    "sg:postcode":"3437 CB",
    "sg:province":"Utrecht",
    "wof:name":"Robecass",
    "wof:placetype":"venue"
},
  "geometry": {"coordinates":[5.071314,52.041248],"type":"Point"}
}