{
  "type": "Feature",
  "properties": {
    "addr:full":"De Wetering 129 Oosterhout Nb North Brabant 4906 CT",
    "addr:housenumber":"129;nb",
    "addr:postcode":"4906 ct",
    "addr:street":"De Wetering",
    "iso:country":"NL",
    "sg:address":"De Wetering 129",
    "sg:city":"Oosterhout Nb",
    "sg:orig_category":"Kunststof Ramen",
    "sg:phone":"+31 162 455 894",
    "sg:postcode":"4906 CT",
    "sg:province":"North Brabant",
    "sg:website":"http://www.gloudemansgevelprodukten.nl",
    "wof:name":"Gloudemans Gevelprodukten Bv",
    "wof:placetype":"venue"
},
  "geometry": {"coordinates":[4.84302,51.65432],"type":"Point"}
}