{
  "type": "Feature",
  "properties": {
    "iso:country":"NL",
    "sg:address":"Hefnerstraat 13",
    "sg:city":"Ijmuiden",
    "sg:orig_category":"Autokeuringen",
    "sg:phone":"+31 255 531 936",
    "sg:postcode":"1976 BK",
    "sg:province":"Noord-Holland",
    "wof:name":"Garage Beers",
    "wof:placetype":"venue"
},
  "geometry": {"coordinates":[4.581541,52.453518],"type":"Point"}
}