{
  "type": "Feature",
  "properties": {
    "iso:country":"NL",
    "sg:address":"Smitsweg 10",
    "sg:city":"Uithuizermeeden",
    "sg:classifiers":[
        {
            "category":"Professional",
            "subcategory":"Accounting & Tax Preparation",
            "type":"Services"
        }
    ],
    "sg:phone":"+31 595 412 436",
    "sg:postcode":"9982 HT",
    "sg:province":"Groningen",
    "sg:tags":[
        "accountant"
    ],
    "wof:name":"Administratie- & Adviesburo Dieterman",
    "wof:placetype":"venue"
},
  "geometry": {"coordinates":[6.723243,53.417133],"type":"Point"}
}