{
  "type": "Feature",
  "properties": {
    "addr:full":"Bedrijvenpark Twente 15 Almelo Overijssel 7602 KA",
    "addr:housenumber":"15",
    "addr:postcode":"7602 ka",
    "addr:street":"Bedrijvenpark Twente",
    "iso:country":"NL",
    "sg:address":"Bedrijvenpark Twente 15",
    "sg:city":"Almelo",
    "sg:orig_category":"Metaalafval, Schrootrecycling And Sloperijen",
    "sg:phone":"+31 546 578 300",
    "sg:postcode":"7602 KA",
    "sg:province":"Overijssel",
    "wof:name":"Gema International Bv",
    "wof:placetype":"venue"
},
  "geometry": {"coordinates":[6.612253,52.382702],"type":"Point"}
}