{
  "type": "Feature",
  "properties": {
    "addr:full":"Reilinkswg 12 Holten Overijssel 7451 CP",
    "addr:housenumber":"12",
    "addr:postcode":"7451 cp",
    "addr:street":"Reilinkswg",
    "iso:country":"NL",
    "sg:address":"Reilinkswg 12",
    "sg:city":"Holten",
    "sg:orig_category":"Accountants - Administratie- Consulenten En -Kantoren",
    "sg:phone":"+31 548 378 353",
    "sg:postcode":"7451 CP",
    "sg:province":"Overijssel",
    "wof:name":"Braak",
    "wof:placetype":"venue"
},
  "geometry": {"coordinates":[6.414189,52.282143],"type":"Point"}
}