{
  "type": "Feature",
  "properties": {
    "addr:full":"De Werf 27 'S Gravenhage South Holland 2544 EH",
    "addr:housenumber":"27",
    "addr:postcode":"2544 eh",
    "addr:street":"De Werf;' S Gravenhage",
    "iso:country":"NL",
    "sg:address":"De Werf 27",
    "sg:city":"'S Gravenhage",
    "sg:orig_category":"Binnenhuisarchitecten",
    "sg:phone":"+31 70 329 0842",
    "sg:postcode":"2544 EH",
    "sg:province":"South Holland",
    "wof:name":"Van 'T Wout Woonkunst Bv",
    "wof:placetype":"venue"
},
  "geometry": {"coordinates":[4.242695,52.043533],"type":"Point"}
}