{
  "type": "Feature",
  "properties": {
    "addr:full":"Hoogstr 47-49 Hasselt Overijssel 8061 HB",
    "addr:housenumber":"47-49",
    "addr:postcode":"8061 hb",
    "iso:country":"NL",
    "sg:address":"Hoogstr 47-49",
    "sg:city":"Hasselt",
    "sg:orig_category":"Artsen - Huisartsen",
    "sg:phone":"+31 38 477 1224",
    "sg:postcode":"8061 HB",
    "sg:province":"Overijssel",
    "wof:name":"Tuinstra, N H P",
    "wof:placetype":"venue"
},
  "geometry": {"coordinates":[6.088923,52.592331],"type":"Point"}
}