{
  "type": "Feature",
  "properties": {
    "addr:full":"Neuwg 447 Hilversum Noord-Holland 1215 JC",
    "addr:housenumber":"447",
    "addr:postcode":"hilversum;1215 jc",
    "iso:country":"NL",
    "sg:address":"Neuwg 447",
    "sg:city":"Hilversum",
    "sg:orig_category":"Adviesbureaus Bedrijfsorganisatie",
    "sg:phone":"+31 35 621 3583",
    "sg:postcode":"1215 JC",
    "sg:province":"Noord-Holland",
    "wof:name":"Rozemond",
    "wof:placetype":"venue"
},
  "geometry": {"coordinates":[5.156841,52.213406],"type":"Point"}
}