{
  "type": "Feature",
  "properties": {
    "addr:full":"Hg Vaartkant 24 Etten Leur Noord-Brabant 4873 LL",
    "addr:housenumber":"24",
    "addr:postcode":"4873 ll",
    "addr:street":"Hg Vaartkant",
    "iso:country":"NL",
    "sg:address":"Hg Vaartkant 24",
    "sg:city":"Etten Leur",
    "sg:orig_category":"Kaas",
    "sg:phone":"+31 76 501 2702",
    "sg:postcode":"4873 LL",
    "sg:province":"Noord-Brabant",
    "wof:name":"Vaartje, 'T",
    "wof:placetype":"venue"
},
  "geometry": {"coordinates":[4.6695680618,51.5618896484],"type":"Point"}
}