{
  "type": "Feature",
  "properties": {
    "addr:full":"W De Zwygerstr 66 Utrecht Utrecht 3583 HD",
    "addr:housenumber":"66",
    "addr:postcode":"3583 hd",
    "addr:street":"W De Zwygerstr",
    "iso:country":"NL",
    "sg:address":"W De Zwygerstr 66",
    "sg:city":"Utrecht",
    "sg:orig_category":"Vertalers",
    "sg:phone":"+31 30 251 6537",
    "sg:postcode":"3583 HD",
    "sg:province":"Utrecht",
    "wof:name":"Eggen, N",
    "wof:placetype":"venue"
},
  "geometry": {"coordinates":[5.14371,52.086601],"type":"Point"}
}