{
  "type": "Feature",
  "properties": {
    "addr:full":"Vd Schellingstr 62 Rotterdam Zuid-Holland 3033 VR",
    "addr:housenumber":"62",
    "addr:postcode":"3033 vr",
    "iso:country":"NL",
    "sg:address":"Vd Schellingstr 62",
    "sg:city":"Rotterdam",
    "sg:orig_category":"Autorijscholen",
    "sg:phone":"+31 10 466 2231",
    "sg:postcode":"3033 VR",
    "sg:province":"Zuid-Holland",
    "wof:name":"Arena",
    "wof:placetype":"venue"
},
  "geometry": {"coordinates":[4.468864,51.928352],"type":"Point"}
}