{
  "type": "Feature",
  "properties": {
    "addr:full":"Nieuwe-Marktpassage 1 Gouda South Holland 2801 HW",
    "addr:housenumber":"1",
    "addr:postcode":"2801 hw",
    "addr:street":"Nieuwe-Marktpassage",
    "iso:country":"NL",
    "sg:address":"Nieuwe-Marktpassage 1",
    "sg:city":"Gouda",
    "sg:orig_category":"Bloemen And Planten",
    "sg:phone":"+31 182 511 120",
    "sg:postcode":"2801 HW",
    "sg:province":"South Holland",
    "wof:name":"Slingerland Bloemen Bv",
    "wof:placetype":"venue"
},
  "geometry": {"coordinates":[4.711149,52.013481],"type":"Point"}
}