{
  "type": "Feature",
  "properties": {
    "addr:full":"Judith Van Marlelaan 16 Dedemsvaart Overijssel 7701 HW",
    "addr:housenumber":"16",
    "addr:postcode":"7701 hw",
    "addr:street":"Judith Van Marlelaan",
    "iso:country":"NL",
    "sg:address":"Judith Van Marlelaan 16",
    "sg:city":"Dedemsvaart",
    "sg:orig_category":"Schilderwerk",
    "sg:phone":"+31 523 613 951",
    "sg:postcode":"7701 HW",
    "sg:province":"Overijssel",
    "wof:name":"Schildersbedrijf Blauw Dopmeyer Bv",
    "wof:placetype":"venue"
},
  "geometry": {"coordinates":[6.453692,52.601387],"type":"Point"}
}