{
  "type": "Feature",
  "properties": {
    "iso:country":"NL",
    "sg:address":"Kerkstr 4",
    "sg:city":"Batenburg",
    "sg:orig_category":"Adviesbureaus Planologie",
    "sg:phone":"+31 487 542 906",
    "sg:postcode":"6634 AJ",
    "sg:province":"Gelderland",
    "wof:name":"Hsro Bv",
    "wof:placetype":"venue"
},
  "geometry": {"coordinates":[5.629307,51.8232],"type":"Point"}
}