{
  "type": "Feature",
  "properties": {
    "addr:full":"Jousterwg 24 Heerenveen Friesland 8447 RH",
    "addr:housenumber":"24",
    "addr:postcode":"8447 rh",
    "addr:street":"Jousterwg",
    "iso:country":"NL",
    "sg:address":"Jousterwg 24",
    "sg:city":"Heerenveen",
    "sg:orig_category":"Verf En Lak - Fabrieken En Groothandel",
    "sg:phone":"+31 513 620 092",
    "sg:postcode":"8447 RH",
    "sg:province":"Friesland",
    "wof:name":"Sikkens Friesland",
    "wof:placetype":"venue"
},
  "geometry": {"coordinates":[5.903947,52.964386],"type":"Point"}
}