{
  "type": "Feature",
  "properties": {
    "addr:full":"Blankespoorsel Wg 15 Lunteren Gelderland 6741 ZZ",
    "addr:housenumber":"15",
    "addr:postcode":"6741 zz",
    "addr:street":"Wg;Gelderland",
    "iso:country":"NL",
    "sg:address":"Blankespoorsel Wg 15",
    "sg:city":"Lunteren",
    "sg:orig_category":"Fotoreportages",
    "sg:phone":"+31 318 486 696",
    "sg:postcode":"6741 ZZ",
    "sg:province":"Gelderland",
    "wof:name":"Vleesch Du Bois, Susanne",
    "wof:placetype":"venue"
},
  "geometry": {"coordinates":[5.621629,52.091679],"type":"Point"}
}