{
  "type": "Feature",
  "properties": {
    "addr:full":"N Beetsstr 30 Putten Gelderland 3881 XD",
    "addr:housenumber":"30",
    "addr:postcode":"3881 xd",
    "addr:street":"N;Gelderland",
    "iso:country":"NL",
    "sg:address":"N Beetsstr 30",
    "sg:city":"Putten",
    "sg:orig_category":"Plafonds",
    "sg:phone":"+31 341 361 779",
    "sg:postcode":"3881 XD",
    "sg:province":"Gelderland",
    "wof:name":"Haklander",
    "wof:placetype":"venue"
},
  "geometry": {"coordinates":[5.613089,52.253448],"type":"Point"}
}