{
  "type": "Feature",
  "properties": {
    "addr:full":"Deelensewg 30 Arnhem Gelderland 6816 TS",
    "addr:housenumber":"30",
    "addr:postcode":"6816 ts",
    "addr:street":"Deelensewg",
    "iso:country":"NL",
    "sg:address":"Deelensewg 30",
    "sg:city":"Arnhem",
    "sg:classifiers":[
        {
            "category":"Retail",
            "subcategory":"Auto Repair",
            "type":"Services"
        }
    ],
    "sg:phone":"+31 26 442 3431",
    "sg:postcode":"6816 TS",
    "sg:province":"Gelderland",
    "sg:tags":[
        "garage"
    ],
    "wof:name":"Pluim, Autobedrijf B",
    "wof:placetype":"venue"
},
  "geometry": {"coordinates":[5.888335,52.034088],"type":"Point"}
}