{
  "type": "Feature",
  "properties": {
    "iso:country":"NL",
    "sg:address":"Steenhoffstraat 46",
    "sg:city":"Soest",
    "sg:orig_category":"Overheidsdiensten",
    "sg:phone":"+31 35 602 8672",
    "sg:postcode":"3764 BM",
    "sg:province":"Utrecht",
    "wof:name":"T Gildehuis",
    "wof:placetype":"venue"
},
  "geometry": {"coordinates":[5.3047261238,52.1804237366],"type":"Point"}
}