{
  "type": "Feature",
  "properties": {
    "addr:full":"Maasstr 14 Haarlem Noord-Holland 2025 RL",
    "addr:housenumber":"14",
    "addr:postcode":"2025 rl",
    "addr:street":"Maasstr",
    "iso:country":"NL",
    "sg:address":"Maasstr 14",
    "sg:city":"Haarlem",
    "sg:orig_category":"Glazenwasserijen",
    "sg:phone":"+31 23 537 0725",
    "sg:postcode":"2025 RL",
    "sg:province":"Noord-Holland",
    "wof:name":"Westhof",
    "wof:placetype":"venue"
},
  "geometry": {"coordinates":[4.649114,52.414089],"type":"Point"}
}