{
  "type": "Feature",
  "properties": {
    "iso:country":"NL",
    "sg:address":"Kayersdk 95",
    "sg:city":"Apeldoorn",
    "sg:orig_category":"Zeilmakerijen",
    "sg:phone":"+31 55 533 3151",
    "sg:postcode":"7332 AM",
    "sg:province":"Gelderland",
    "wof:name":"Atz",
    "wof:placetype":"venue"
},
  "geometry": {"coordinates":[5.979763,52.198322],"type":"Point"}
}