{
  "type": "Feature",
  "properties": {
    "iso:country":"NL",
    "sg:address":"Putsewg 1A",
    "sg:city":"Hoogerheide",
    "sg:orig_category":"Houtgroothandel",
    "sg:phone":"+31 164 620 032",
    "sg:postcode":"4631 CH",
    "sg:province":"Noord-Brabant",
    "wof:name":"Lubox Holl Bv",
    "wof:placetype":"venue"
},
  "geometry": {"coordinates":[4.324727,51.422459],"type":"Point"}
}