{
  "type": "Feature",
  "properties": {
    "addr:full":"Wilgensngl 192 Rotterdam Zuid-Holland 3053 CZ",
    "addr:housenumber":"192",
    "addr:postcode":"3053",
    "iso:country":"NL",
    "sg:address":"Wilgensngl 192",
    "sg:city":"Rotterdam",
    "sg:orig_category":"Vertaalbureaus",
    "sg:phone":"+31 10 218 1607",
    "sg:postcode":"3053 CZ",
    "sg:province":"Zuid-Holland",
    "wof:name":"Dool-De Hoest, Drs W H Van Den",
    "wof:placetype":"venue"
},
  "geometry": {"coordinates":[4.47609,51.966759],"type":"Point"}
}