{
  "type": "Feature",
  "properties": {
    "addr:full":"Ryksstrwg 219 Beek Ubbergen Gelderland 6573 CS",
    "addr:housenumber":"219",
    "addr:postcode":"6573 cs",
    "iso:country":"NL",
    "sg:address":"Ryksstrwg 219",
    "sg:city":"Beek Ubbergen",
    "sg:orig_category":"Bloemen En Planten",
    "sg:phone":"+31 24 684 1226",
    "sg:postcode":"6573 CS",
    "sg:province":"Gelderland",
    "wof:name":"Semper Florence",
    "wof:placetype":"venue"
},
  "geometry": {"coordinates":[5.92779,51.831219],"type":"Point"}
}