{
  "type": "Feature",
  "properties": {
    "addr:full":"Pastoor Van Weerdtstraat 19 Teeffelen Noord-Brabant 5395 TG",
    "addr:housenumber":"19",
    "addr:postcode":"5395 tg",
    "addr:street":"Pastoor Van Weerdtstraat",
    "iso:country":"NL",
    "sg:address":"Pastoor Van Weerdtstraat 19",
    "sg:city":"Teeffelen",
    "sg:orig_category":"Levende Dieren Gh",
    "sg:phone":"+31 412 481 413",
    "sg:postcode":"5395 TG",
    "sg:province":"Noord-Brabant",
    "wof:name":"Vof Van Den Brand Teeffelen",
    "wof:placetype":"venue"
},
  "geometry": {"coordinates":[5.488668,51.799561],"type":"Point"}
}