{
  "type": "Feature",
  "properties": {
    "iso:country":"NL",
    "sg:address":"Deurningerstraat 302",
    "sg:city":"Enschede",
    "sg:orig_category":"Kappers",
    "sg:phone":"+31 53 435 5343",
    "sg:postcode":"7522 CN",
    "sg:province":"Overijssel",
    "wof:name":"Haarmode Solo",
    "wof:placetype":"venue"
},
  "geometry": {"coordinates":[6.8858847618,52.2348327637],"type":"Point"}
}