{
  "type": "Feature",
  "properties": {
    "addr:full":"V Oldenbarnev Ln 46 Uithoorn Noord-Holland 1421 TT",
    "addr:housenumber":"46",
    "addr:postcode":"1421 tt",
    "addr:street":"Oldenbarnev Ln",
    "iso:country":"NL",
    "sg:address":"V Oldenbarnev Ln 46",
    "sg:city":"Uithoorn",
    "sg:orig_category":"Glazenwasserijen",
    "sg:phone":"+31 6 22246195",
    "sg:postcode":"1421 TT",
    "sg:province":"Noord-Holland",
    "wof:name":"Driehuis, K",
    "wof:placetype":"venue"
},
  "geometry": {"coordinates":[4.828947,52.233421],"type":"Point"}
}