{
  "type": "Feature",
  "properties": {
    "addr:full":"Lonnekerbrugstr 80 Enschede Overijssel 7547 AJ",
    "addr:housenumber":"80",
    "addr:postcode":"7547 aj",
    "addr:street":"Lonnekerbrugstr",
    "iso:country":"NL",
    "sg:address":"Lonnekerbrugstr 80",
    "sg:city":"Enschede",
    "sg:orig_category":"Projectinrichting",
    "sg:phone":"+31 53 431 1511",
    "sg:postcode":"7547 AJ",
    "sg:province":"Overijssel",
    "sg:website":"http://www.duototaalproject.nl",
    "wof:name":"Duo Totaal Project Bv",
    "wof:placetype":"venue"
},
  "geometry": {"coordinates":[6.856399,52.225788],"type":"Point"}
}