{
  "type": "Feature",
  "properties": {
    "addr:full":"Molenpad 6 Oude Niedorp Noord-Holland 1734 JM",
    "addr:housenumber":"6",
    "addr:postcode":"1734 jm",
    "addr:street":"Molenpad",
    "iso:country":"NL",
    "sg:address":"Molenpad 6",
    "sg:city":"Oude Niedorp",
    "sg:orig_category":"Honden- En Kattentrimsalons",
    "sg:phone":"+31 226 423 288",
    "sg:postcode":"1734 JM",
    "sg:province":"Noord-Holland",
    "wof:name":"Ossa",
    "wof:placetype":"venue"
},
  "geometry": {"coordinates":[4.867687,52.719784],"type":"Point"}
}