{
  "type": "Feature",
  "properties": {
    "addr:full":"Havenweg 7 Weert Limburg 6006 SM",
    "addr:housenumber":"7",
    "addr:postcode":"6006 sm",
    "addr:street":"Havenweg",
    "iso:country":"NL",
    "sg:address":"Havenweg 7",
    "sg:city":"Weert",
    "sg:orig_category":"Zuivelproducten And Spijsoli?n Gh",
    "sg:phone":"+31 495 531 355",
    "sg:postcode":"6006 SM",
    "sg:province":"Limburg",
    "wof:name":"Comma Benelux",
    "wof:placetype":"venue"
},
  "geometry": {"coordinates":[5.676392,51.245239],"type":"Point"}
}