{
  "type": "Feature",
  "properties": {
    "iso:country":"NL",
    "sg:address":"Heerewaardensestraat 32",
    "sg:city":"Heerewaarden",
    "sg:orig_category":"Autokeuringen",
    "sg:phone":"+31 487 572 397",
    "sg:postcode":"6624 KK",
    "sg:province":"Gelderland",
    "wof:name":"Garagebedrijf N. Hooijkaas",
    "wof:placetype":"venue"
},
  "geometry": {"coordinates":[5.402494,51.825554],"type":"Point"}
}