{
  "type": "Feature",
  "properties": {
    "iso:country":"NL",
    "sg:address":"Veurkapel .",
    "sg:city":"Leidschendam",
    "sg:orig_category":"Bloemen En Planten",
    "sg:phone":"+31 70 327 6051",
    "sg:postcode":"2264 MN",
    "sg:province":"South Holland",
    "wof:name":"Janson, A",
    "wof:placetype":"venue"
},
  "geometry": {"coordinates":[4.401075,52.093246],"type":"Point"}
}