{
  "type": "Feature",
  "properties": {
    "addr:full":"Ronkert 44 Lage Mierde Noord-Brabant 5094 EW",
    "addr:housenumber":"44",
    "addr:postcode":"5094 ew",
    "addr:street":"Ronkert",
    "iso:country":"NL",
    "sg:address":"Ronkert 44",
    "sg:city":"Lage Mierde",
    "sg:orig_category":"Elektronica - Ontwikkeling En Groothandel",
    "sg:phone":"+31 13 509 6024",
    "sg:postcode":"5094 EW",
    "sg:province":"Noord-Brabant",
    "wof:name":"Hoeben Electronics",
    "wof:placetype":"venue"
},
  "geometry": {"coordinates":[5.146673,51.407829],"type":"Point"}
}