{
  "type": "Feature",
  "properties": {
    "iso:country":"NL",
    "sg:address":"Zwenkgrasstraat 15",
    "sg:city":"Almere",
    "sg:orig_category":"Technische Studies And Onderzoek",
    "sg:phone":"+31 36 535 9292",
    "sg:postcode":"1313 LC",
    "sg:province":"Flevoland",
    "wof:name":"Polysep Bv",
    "wof:placetype":"venue"
},
  "geometry": {"coordinates":[5.205495,52.386272],"type":"Point"}
}