{
  "type": "Feature",
  "properties": {
    "addr:full":"Amnestyln 1 Middelburg Zeeland 4336 LA",
    "addr:housenumber":"1",
    "addr:postcode":"4336 la",
    "addr:street":"Amnestyln",
    "iso:country":"NL",
    "sg:address":"Amnestyln 1",
    "sg:city":"Middelburg",
    "sg:orig_category":"Balletscholen",
    "sg:phone":"+31 118 624 154",
    "sg:postcode":"4336 LA",
    "sg:province":"Zeeland",
    "wof:name":"Dazzle",
    "wof:placetype":"venue"
},
  "geometry": {"coordinates":[3.611343,51.483299],"type":"Point"}
}