{
  "type": "Feature",
  "properties": {
    "addr:full":"Zirkoon 17 S Gravenzande Zuid-Holland 2691 HP",
    "addr:housenumber":"17;gravenzande",
    "addr:postcode":"2691 hp",
    "addr:street":"Zirkoon;S",
    "iso:country":"NL",
    "sg:address":"Zirkoon 17",
    "sg:city":"S Gravenzande",
    "sg:orig_category":"Nagelstudio'S",
    "sg:phone":"+31 174 418 118",
    "sg:postcode":"2691 HP",
    "sg:province":"Zuid-Holland",
    "wof:name":"Butterfly",
    "wof:placetype":"venue"
},
  "geometry": {"coordinates":[4.16846,51.992756],"type":"Point"}
}