{
  "type": "Feature",
  "properties": {
    "addr:full":"Femina Mullerstraat 74 Hoofddorp North Holland 2135 MS",
    "addr:housenumber":"74",
    "addr:postcode":"2135 ms",
    "addr:street":"Femina Mullerstraat",
    "iso:country":"NL",
    "sg:address":"Femina Mullerstraat 74",
    "sg:city":"Hoofddorp",
    "sg:classifiers":[
        {
            "category":"Education",
            "subcategory":"Preschool",
            "type":"Public Place"
        }
    ],
    "sg:phone":"+31 23 562 2855",
    "sg:postcode":"2135 MS",
    "sg:province":"North Holland",
    "sg:tags":[
        "kleuteronderwijs",
        "basis-"
    ],
    "wof:name":"Christelijke Basisschool Tabitha",
    "wof:placetype":"venue"
},
  "geometry": {"coordinates":[4.670828,52.296085],"type":"Point"}
}