{
  "type": "Feature",
  "properties": {
    "addr:full":"Gasthuisln 64 Delft Zuid-Holland 2611 RB",
    "addr:housenumber":"64",
    "addr:postcode":"2611 rb",
    "addr:street":"Gasthuisln",
    "iso:country":"NL",
    "sg:address":"Gasthuisln 64",
    "sg:city":"Delft",
    "sg:orig_category":"Kappers",
    "sg:phone":"+31 15 212 0504",
    "sg:postcode":"2611 RB",
    "sg:province":"Zuid-Holland",
    "wof:name":"Headquarter",
    "wof:placetype":"venue"
},
  "geometry": {"coordinates":[4.358689785,52.011505127],"type":"Point"}
}