{
  "type": "Feature",
  "properties": {
    "addr:full":"Stadhouderslaan 50 'S Gravenhage Zuid-Holland 2517 HZ",
    "addr:housenumber":"50",
    "addr:postcode":"2517 hz",
    "addr:street":"Stadhouderslaan;' S",
    "iso:country":"NL",
    "sg:address":"Stadhouderslaan 50",
    "sg:city":"'S Gravenhage",
    "sg:orig_category":"Boekenuitgeverijen",
    "sg:phone":"+31 70 363 8171",
    "sg:postcode":"2517 HZ",
    "sg:province":"Zuid-Holland",
    "wof:name":"P G M De Kleyn",
    "wof:placetype":"venue"
},
  "geometry": {"coordinates":[4.28091,52.086372],"type":"Point"}
}