{
  "type": "Feature",
  "properties": {
    "addr:full":"K De Grotestr 25 Wyk By Duurstede Utrecht 3962 CJ",
    "addr:housenumber":"25",
    "addr:postcode":"duurstede;3962 cj",
    "addr:street":"K De Grotestr",
    "iso:country":"NL",
    "sg:address":"K De Grotestr 25",
    "sg:city":"Wyk By Duurstede",
    "sg:orig_category":"Honden- En Kattentrimsalons",
    "sg:phone":"+31 343 460 093",
    "sg:postcode":"3962 CJ",
    "sg:province":"Utrecht",
    "wof:name":"Tyco",
    "wof:placetype":"venue"
},
  "geometry": {"coordinates":[5.3754,51.985378],"type":"Point"}
}