{
  "type": "Feature",
  "properties": {
    "addr:full":"Nw Pyramide 24 Wyk By Duurstede Utrecht 3962 HV",
    "addr:housenumber":"24",
    "addr:postcode":"duurstede;3962 hv",
    "addr:street":"Pyramide",
    "iso:country":"NL",
    "sg:address":"Nw Pyramide 24",
    "sg:city":"Wyk By Duurstede",
    "sg:orig_category":"Makelaars En Adviseurs Onroerende Goederen",
    "sg:phone":"+31 343 591 399",
    "sg:postcode":"3962 HV",
    "sg:province":"Utrecht",
    "wof:name":"Hameter",
    "wof:placetype":"venue"
},
  "geometry": {"coordinates":[5.347164,51.980564],"type":"Point"}
}