{
  "type": "Feature",
  "properties": {
    "addr:full":"Koepoortstraat 40 Doesburg Gelderland 6981 AT",
    "addr:housenumber":"40",
    "addr:postcode":"6981",
    "addr:street":"Koepoortstraat;Gelderland",
    "iso:country":"NL",
    "sg:address":"Koepoortstraat 40",
    "sg:city":"Doesburg",
    "sg:orig_category":"Kunst And Kunstenaarsbenodigdheden",
    "sg:phone":"+31 313 475 200",
    "sg:postcode":"6981 AT",
    "sg:province":"Gelderland",
    "wof:name":"Kunsthandel J. Nieuwenhuis",
    "wof:placetype":"venue"
},
  "geometry": {"coordinates":[6.133148,52.016388],"type":"Point"}
}