{
  "type": "Feature",
  "properties": {
    "addr:full":"Liguster 67 Leidschendam South Holland 2262 AC",
    "addr:housenumber":"67",
    "addr:postcode":"2262 ac",
    "addr:street":"Liguster",
    "iso:country":"NL",
    "sg:address":"Liguster 67",
    "sg:city":"Leidschendam",
    "sg:orig_category":"Kinderkleding",
    "sg:phone":"+31 70 317 5156",
    "sg:postcode":"2262 AC",
    "sg:province":"South Holland",
    "sg:website":"http://www.mexx.com",
    "wof:name":"Mexx",
    "wof:placetype":"venue"
},
  "geometry": {"coordinates":[4.38399,52.087357],"type":"Point"}
}