{
  "type": "Feature",
  "properties": {
    "iso:country":"NL",
    "sg:address":"Staat 2",
    "sg:city":"Nederweert",
    "sg:orig_category":"Autoradio'S",
    "sg:phone":"+31 495 624 827",
    "sg:postcode":"6031 EM",
    "sg:province":"Limburg",
    "wof:name":"Pitstop, Fa",
    "wof:placetype":"venue"
},
  "geometry": {"coordinates":[5.750554,51.282772],"type":"Point"}
}