{
  "type": "Feature",
  "properties": {
    "addr:full":"Van Der Helllaan 20 Arnhem Gelderland 6824 HT",
    "addr:housenumber":"20",
    "addr:postcode":"6824 ht",
    "addr:street":"Van Der Helllaan",
    "iso:country":"NL",
    "sg:address":"Van Der Helllaan 20",
    "sg:city":"Arnhem",
    "sg:classifiers":[
        {
            "category":"Food & Beverages",
            "subcategory":"Fruits & Vegetables",
            "type":"Retail Goods"
        }
    ],
    "sg:phone":"+31 26 443 9790",
    "sg:postcode":"6824 HT",
    "sg:province":"Gelderland",
    "sg:tags":[
        "groenten"
    ],
    "wof:name":"Derk Jan De Groenteman",
    "wof:placetype":"venue"
},
  "geometry": {"coordinates":[5.933454,51.990879],"type":"Point"}
}