{
  "type": "Feature",
  "properties": {
    "addr:full":"Bergweidedijk 2 Deventer NL.08 7418 AD",
    "addr:housenumber":"2;nl.08",
    "addr:postcode":"7418 ad",
    "addr:street":"Bergweidedijk",
    "iso:country":"NL",
    "sg:address":"Bergweidedijk 2",
    "sg:city":"Deventer",
    "sg:orig_category":"Kantoorartikelen",
    "sg:phone":"+31 570 850 850",
    "sg:postcode":"7418 AD",
    "sg:province":"NL.08",
    "wof:name":"Klein Beernink Bv",
    "wof:placetype":"venue"
},
  "geometry": {"coordinates":[6.1782212257,52.2395057678],"type":"Point"}
}