{
  "type": "Feature",
  "properties": {
    "iso:country":"NL",
    "sg:address":"H Siccamasngl 243",
    "sg:city":"Groningen",
    "sg:orig_category":"Webdesign Bureaus",
    "sg:phone":"+31 50 527 4522",
    "sg:postcode":"9721 HG",
    "sg:province":"Groningen",
    "sg:website":"http://www.mapabo.nl",
    "wof:name":"Mapabo Webdesign",
    "wof:placetype":"venue"
},
  "geometry": {"coordinates":[6.5747299194,53.1941108704],"type":"Point"}
}