{
  "type": "Feature",
  "properties": {
    "addr:full":"Rulselaan 10 Heeze Noord-Brabant 5591 CA",
    "addr:housenumber":"10",
    "addr:postcode":"5591 ca",
    "addr:street":"Rulselaan",
    "iso:country":"NL",
    "sg:address":"Rulselaan 10",
    "sg:city":"Heeze",
    "sg:orig_category":"Goederenvervoer Over De Weg",
    "sg:phone":"+31 40 226 1698",
    "sg:postcode":"5591 CA",
    "sg:province":"Noord-Brabant",
    "wof:name":"Peter Keijsers Transport Bv",
    "wof:placetype":"venue"
},
  "geometry": {"coordinates":[5.570882,51.390648],"type":"Point"}
}