{
  "type": "Feature",
  "properties": {
    "iso:country":"NL",
    "sg:address":"Bredasewg 229",
    "sg:city":"Tilburg",
    "sg:orig_category":"Yoga-Instituten",
    "sg:phone":"+31 13 467 6520",
    "sg:postcode":"5038 NE",
    "sg:province":"Noord-Brabant",
    "wof:name":"Brocken Yoga, Doortje",
    "wof:placetype":"venue"
},
  "geometry": {"coordinates":[5.0662,51.55621],"type":"Point"}
}