{
  "type": "Feature",
  "properties": {
    "addr:full":"Emmastraat 17 'S Gravenhage Zuid-Holland 2595 EG",
    "addr:housenumber":"17",
    "addr:postcode":"2595 eg",
    "addr:street":"Emmastraat;' S",
    "iso:country":"NL",
    "sg:address":"Emmastraat 17",
    "sg:city":"'S Gravenhage",
    "sg:orig_category":"Kappers",
    "sg:phone":"+31 70 385 9988",
    "sg:postcode":"2595 EG",
    "sg:province":"Zuid-Holland",
    "wof:name":"Dameskappersbedrijf Rob Van De Nol",
    "wof:placetype":"venue"
},
  "geometry": {"coordinates":[4.3313779831,52.0842666626],"type":"Point"}
}