{
  "type": "Feature",
  "properties": {
    "addr:full":"Oude Broekdk 1 Kesteren Gelderland 4041 AR",
    "addr:housenumber":"1",
    "addr:postcode":"4041",
    "addr:street":"Oude Broekdk;Gelderland",
    "iso:country":"NL",
    "sg:address":"Oude Broekdk 1",
    "sg:city":"Kesteren",
    "sg:orig_category":"Adviesbureaus Bedrijfsorganisatie",
    "sg:phone":"+31 6 20612073",
    "sg:postcode":"4041 AR",
    "sg:province":"Gelderland",
    "wof:name":"Ravestein Financial Services Bv",
    "wof:placetype":"venue"
},
  "geometry": {"coordinates":[5.56956,51.923088],"type":"Point"}
}