{
  "type": "Feature",
  "properties": {
    "addr:full":"Grt Sloot 137 Burgerbrug Noord-Holland 1754 JD",
    "addr:housenumber":"137",
    "addr:postcode":"1754 jd",
    "addr:street":"Grt Sloot",
    "iso:country":"NL",
    "sg:address":"Grt Sloot 137",
    "sg:city":"Burgerbrug",
    "sg:orig_category":"Meubelen",
    "sg:phone":"+31 224 561 259",
    "sg:postcode":"1754 JD",
    "sg:province":"Noord-Holland",
    "sg:website":"http://www.ooyenbargh.nl",
    "wof:name":"Ooyenbargh, Interieurhoeve",
    "wof:placetype":"venue"
},
  "geometry": {"coordinates":[4.712268,52.765514],"type":"Point"}
}