{
  "type": "Feature",
  "properties": {
    "addr:full":"Boulev Heuvelink 131 Arnhem Gelderland 6828 KL",
    "addr:housenumber":"131",
    "addr:postcode":"6828 kl",
    "addr:street":"Boulev Heuvelink",
    "iso:country":"NL",
    "sg:address":"Boulev Heuvelink 131",
    "sg:city":"Arnhem",
    "sg:orig_category":"Adviesbureaus Bedrijfsorganisatie",
    "sg:phone":"+31 26 443 0371",
    "sg:postcode":"6828 KL",
    "sg:province":"Gelderland",
    "wof:name":"Boulevard Bv",
    "wof:placetype":"venue"
},
  "geometry": {"coordinates":[5.920709,51.980328],"type":"Point"}
}