{
  "type": "Feature",
  "properties": {
    "addr:full":"Industrieweg 17 Soest Utrecht 3762 EG",
    "addr:housenumber":"17",
    "addr:postcode":"3762 eg",
    "addr:street":"Industrieweg",
    "iso:country":"NL",
    "sg:address":"Industrieweg 17",
    "sg:city":"Soest",
    "sg:orig_category":"Hout Gh",
    "sg:phone":"+31 35 601 0304",
    "sg:postcode":"3762 EG",
    "sg:province":"Utrecht",
    "wof:name":"Schipper Soest Bv",
    "wof:placetype":"venue"
},
  "geometry": {"coordinates":[5.273912,52.180191],"type":"Point"}
}