{
  "type": "Feature",
  "properties": {
    "addr:full":"Streek 180 Rotsterhaule Provincie Friesland 8463 NH",
    "addr:housenumber":"180",
    "addr:postcode":"8463 nh",
    "addr:street":"Streek;Provincie Friesland",
    "iso:country":"NL",
    "sg:address":"Streek 180",
    "sg:city":"Rotsterhaule",
    "sg:orig_category":"Woninginrichting",
    "sg:phone":"+31 513 551 310",
    "sg:postcode":"8463 NH",
    "sg:province":"Provincie Friesland",
    "sg:website":"http://www.gebo-wonen.nl",
    "wof:name":"Gebo",
    "wof:placetype":"venue"
},
  "geometry": {"coordinates":[5.8495850563,52.9274864197],"type":"Point"}
}