{
  "type": "Feature",
  "properties": {
    "addr:full":"P Donderspln 14 St Michielsgestel Noord-Brabant 5271 AA",
    "addr:housenumber":"14",
    "addr:postcode":"5271 aa",
    "addr:street":"P;St Michielsgestel",
    "iso:country":"NL",
    "sg:address":"P Donderspln 14",
    "sg:city":"St Michielsgestel",
    "sg:orig_category":"Kantoorbenodigdheden",
    "sg:phone":"+31 73 551 5113",
    "sg:postcode":"5271 AA",
    "sg:province":"Noord-Brabant",
    "sg:website":"http://www.readshop.nl",
    "wof:name":"Read Shop, The",
    "wof:placetype":"venue"
},
  "geometry": {"coordinates":[5.3503518105,51.6380653381],"type":"Point"}
}