{
  "type": "Feature",
  "properties": {
    "iso:country":"NL",
    "sg:address":"Loowg 51",
    "sg:city":"Coevorden",
    "sg:orig_category":"Parketvloeren",
    "sg:phone":"+31 524 524 142",
    "sg:postcode":"7741 EG",
    "sg:province":"Provincie Drenthe",
    "wof:name":"Country",
    "wof:placetype":"venue"
},
  "geometry": {"coordinates":[6.741319,52.675774],"type":"Point"}
}