{
  "type": "Feature",
  "properties": {
    "addr:full":"Neringwg 300 Lelystad NL. 8224 KL",
    "addr:housenumber":"300",
    "addr:postcode":"8224 kl",
    "addr:street":"Nl.",
    "iso:country":"NL",
    "sg:address":"Neringwg 300",
    "sg:city":"Lelystad",
    "sg:orig_category":"Videotheken",
    "sg:phone":"+31 320 249 287",
    "sg:postcode":"8224 KL",
    "sg:province":"NL.",
    "sg:website":"http://www.videoland.nl",
    "wof:name":"Videoland",
    "wof:placetype":"venue"
},
  "geometry": {"coordinates":[5.477561,52.50771],"type":"Point"}
}