{
  "type": "Feature",
  "properties": {
    "addr:full":"Nyverheidswg 21 Soest Utrecht 3762 EP",
    "addr:housenumber":"21",
    "addr:postcode":"3762 ep",
    "addr:street":"Nyverheidswg",
    "iso:country":"NL",
    "sg:address":"Nyverheidswg 21",
    "sg:city":"Soest",
    "sg:orig_category":"Webdesign Bureaus",
    "sg:phone":"+31 35 602 5445",
    "sg:postcode":"3762 EP",
    "sg:province":"Utrecht",
    "sg:website":"http://www.omni-trade.nl",
    "wof:name":"Omni Trade Bv",
    "wof:placetype":"venue"
},
  "geometry": {"coordinates":[5.2787470818,52.1770172119],"type":"Point"}
}