{
  "type": "Feature",
  "properties": {
    "iso:country":"NL",
    "sg:address":"Traay 98",
    "sg:city":"Driebergen Rysenb",
    "sg:orig_category":"Juweliers",
    "sg:phone":"+31 343 518 796",
    "sg:postcode":"3971 GR",
    "sg:province":"Utrecht",
    "wof:name":"Wechgelaar, Diek",
    "wof:placetype":"venue"
},
  "geometry": {"coordinates":[5.290012,52.054752],"type":"Point"}
}