{
  "type": "Feature",
  "properties": {
    "addr:full":"Hermusstraat 12 Bergen Op Zoom Noord-Brabant 4611 BM",
    "addr:housenumber":"12",
    "addr:postcode":"4611 bm",
    "addr:street":"Hermusstraat",
    "iso:country":"NL",
    "sg:address":"Hermusstraat 12",
    "sg:city":"Bergen Op Zoom",
    "sg:orig_category":"Kantoorartikelen",
    "sg:phone":"+31 164 235 880",
    "sg:postcode":"4611 BM",
    "sg:province":"Noord-Brabant",
    "wof:name":"Mato Kantoor- En Bedrijfsmeubelen",
    "wof:placetype":"venue"
},
  "geometry": {"coordinates":[4.2930798531,51.4937438965],"type":"Point"}
}