{
  "type": "Feature",
  "properties": {
    "addr:full":"Rochusstr 28 Venray Limburg 5801 RR",
    "addr:housenumber":"28",
    "addr:postcode":"5801 rr",
    "addr:street":"Rochusstr",
    "iso:country":"NL",
    "sg:address":"Rochusstr 28",
    "sg:city":"Venray",
    "sg:orig_category":"Adviesbureaus Bouwkunde",
    "sg:phone":"+31 478 516 780",
    "sg:postcode":"5801 RR",
    "sg:province":"Limburg",
    "sg:website":"http://www.zandbergen-mzhetnet.nl",
    "wof:name":"T S P",
    "wof:placetype":"venue"
},
  "geometry": {"coordinates":[5.966589,51.518738],"type":"Point"}
}