{
  "type": "Feature",
  "properties": {
    "iso:country":"NL",
    "sg:address":"Javastr 25",
    "sg:city":"Arnhem",
    "sg:orig_category":"Montagebedrijven",
    "sg:phone":"+31 6 53259416",
    "sg:postcode":"6822 DJ",
    "sg:province":"Gelderland",
    "wof:name":"Vertrouwd",
    "wof:placetype":"venue"
},
  "geometry": {"coordinates":[5.924526,51.988819],"type":"Point"}
}