{
  "type": "Feature",
  "properties": {
    "iso:country":"NL",
    "sg:address":"Kerkstraat 27 A",
    "sg:city":"Leerdam",
    "sg:orig_category":"Wasserettes And Stomerijen",
    "sg:phone":"+31 345 614 961",
    "sg:postcode":"4141 AT",
    "sg:province":"South Holland",
    "wof:name":"Stomerij Clean Inn.",
    "wof:placetype":"venue"
},
  "geometry": {"coordinates":[5.0938949585,51.8909034729],"type":"Point"}
}