{
  "type": "Feature",
  "properties": {
    "addr:full":"Delagoastraat 9 'S Gravenhage Zuid-Holland 2572 XD",
    "addr:housenumber":"9 '",
    "addr:postcode":"2572 xd",
    "addr:street":"Delagoastraat",
    "iso:country":"NL",
    "sg:address":"Delagoastraat 9",
    "sg:city":"'S Gravenhage",
    "sg:orig_category":"Werving And Selectie Van Tijdelijk Personeel And Uitzendkantoren",
    "sg:phone":"+31 70 380 2555",
    "sg:postcode":"2572 XD",
    "sg:province":"Zuid-Holland",
    "wof:name":"Jyoti",
    "wof:placetype":"venue"
},
  "geometry": {"coordinates":[4.293047905,52.0636253357],"type":"Point"}
}