{
  "type": "Feature",
  "properties": {
    "addr:full":"Schipholpoort 100 Haarlem Noord-Holland 2034 MC",
    "addr:housenumber":"100",
    "addr:postcode":"2034 mc",
    "addr:street":"Schipholpoort",
    "iso:country":"NL",
    "sg:address":"Schipholpoort 100",
    "sg:city":"Haarlem",
    "sg:classifiers":[
        {
            "category":"Professional",
            "subcategory":"Accounting & Tax Preparation",
            "type":"Services"
        }
    ],
    "sg:phone":"+31 23 530 0400",
    "sg:postcode":"2034 MC",
    "sg:province":"Noord-Holland",
    "sg:tags":[
        "accountant"
    ],
    "wof:name":"Niehe En Lancee",
    "wof:placetype":"venue"
},
  "geometry": {"coordinates":[4.642556,52.369808],"type":"Point"}
}