{
  "type": "Feature",
  "properties": {
    "addr:full":"Walburgpassage 24 Weert Limburg 6001 LA",
    "addr:housenumber":"24",
    "addr:postcode":"6001 la",
    "addr:street":"Walburgpassage",
    "iso:country":"NL",
    "sg:address":"Walburgpassage 24",
    "sg:city":"Weert",
    "sg:orig_category":"Fitnesscentra",
    "sg:phone":"+31 495 520 313",
    "sg:postcode":"6001 LA",
    "sg:province":"Limburg",
    "wof:name":"Fysioaktief",
    "wof:placetype":"venue"
},
  "geometry": {"coordinates":[5.708244,51.251884],"type":"Point"}
}