{
  "type": "Feature",
  "properties": {
    "iso:country":"NL",
    "sg:address":"Elzendreef 10",
    "sg:city":"Voorburg",
    "sg:orig_category":"Verenigingsgebouwen",
    "sg:phone":"+31 70 386 4295",
    "sg:postcode":"2272 EB",
    "sg:province":"Zuid-Holland",
    "wof:name":"Essensteijn",
    "wof:placetype":"venue"
},
  "geometry": {"coordinates":[4.36927,52.084244],"type":"Point"}
}