{
  "type": "Feature",
  "properties": {
    "addr:full":"Fonteinkruid 125 Deventer Overijssel 7422 MT",
    "addr:housenumber":"125",
    "addr:postcode":"7422",
    "addr:street":"Fonteinkruid;Mt",
    "iso:country":"NL",
    "sg:address":"Fonteinkruid 125",
    "sg:city":"Deventer",
    "sg:orig_category":"Artsen - Huisartsen",
    "sg:phone":"+31 570 654 727",
    "sg:postcode":"7422 MT",
    "sg:province":"Overijssel",
    "wof:name":"Zeeman-Morgenstern, G J H",
    "wof:placetype":"venue"
},
  "geometry": {"coordinates":[6.213954,52.24577],"type":"Point"}
}