{
  "type": "Feature",
  "properties": {
    "iso:country":"NL",
    "sg:address":"Kerkstraat 18",
    "sg:city":"Deventer",
    "sg:orig_category":"Woningbouwverenigingen",
    "sg:phone":"+31 570 691 900",
    "sg:postcode":"7412 XM",
    "sg:province":"NL.08",
    "wof:name":"Hanzewonen",
    "wof:placetype":"venue"
},
  "geometry": {"coordinates":[6.2845811844,52.2485656738],"type":"Point"}
}