{
  "type": "Feature",
  "properties": {
    "addr:full":"Kerkstraat 18 Deventer NL.08 7412 XM",
    "addr:housenumber":"18;nl.08",
    "addr:postcode":"7412 xm",
    "addr:street":"Kerkstraat",
    "iso:country":"NL",
    "sg:address":"Kerkstraat 18",
    "sg:city":"Deventer",
    "sg:orig_category":"Woningbouwverenigingen",
    "sg:phone":"+31 570 691 900",
    "sg:postcode":"7412 XM",
    "sg:province":"NL.08",
    "wof:name":"Hanzewonen",
    "wof:placetype":"venue"
},
  "geometry": {"coordinates":[6.2845811844,52.2485656738],"type":"Point"}
}