{
  "type": "Feature",
  "properties": {
    "iso:country":"NL",
    "sg:address":"Plein 7",
    "sg:city":"Vlijmen",
    "sg:orig_category":"Banken And Kredietinstellingen",
    "sg:phone":"+31 73 511 3305",
    "sg:postcode":"5251 AS",
    "sg:province":"Noord-Brabant",
    "wof:name":"Abn Amro",
    "wof:placetype":"venue"
},
  "geometry": {"coordinates":[5.218692,51.695324],"type":"Point"}
}