{
  "type": "Feature",
  "properties": {
    "addr:full":"Westhavenplaats 6 Vlaardingen Zuid-Holland 3131 BT",
    "addr:housenumber":"6",
    "addr:postcode":"3131 bt",
    "addr:street":"Westhavenplaats",
    "iso:country":"NL",
    "sg:address":"Westhavenplaats 6",
    "sg:city":"Vlaardingen",
    "sg:orig_category":"Bedrijfs- And Managementsconsultants",
    "sg:phone":"+31 10 435 5533",
    "sg:postcode":"3131 BT",
    "sg:province":"Zuid-Holland",
    "wof:name":"V/H Gebroeders H. & W. Hoffman",
    "wof:placetype":"venue"
},
  "geometry": {"coordinates":[4.343716,51.91021],"type":"Point"}
}