{
  "type": "Feature",
  "properties": {
    "addr:full":"Reewijkplein 1 Amsterdam Zuidoost North Holland 1106 AT",
    "addr:housenumber":"1",
    "addr:postcode":"1106",
    "addr:street":"Reewijkplein",
    "iso:country":"NL",
    "sg:address":"Reewijkplein 1",
    "sg:city":"Amsterdam Zuidoost",
    "sg:orig_category":"Autokeuringen",
    "sg:phone":"+31 20 697 6332",
    "sg:postcode":"1106 AT",
    "sg:province":"North Holland",
    "wof:name":"Bp",
    "wof:placetype":"venue"
},
  "geometry": {"coordinates":[4.974365,52.296261],"type":"Point"}
}