{
  "type": "Feature",
  "properties": {
    "addr:full":"Bloemendalsestr 22 Amersfoort Utrecht 3811 ES",
    "addr:housenumber":"22",
    "addr:postcode":"3811 es",
    "addr:street":"Bloemendalsestr",
    "iso:country":"NL",
    "sg:address":"Bloemendalsestr 22",
    "sg:city":"Amersfoort",
    "sg:orig_category":"Horecabenodigdheden",
    "sg:phone":"+31 33 470 1063",
    "sg:postcode":"3811 ES",
    "sg:province":"Utrecht",
    "wof:name":"Gerth, A H",
    "wof:placetype":"venue"
},
  "geometry": {"coordinates":[5.389697,52.158688],"type":"Point"}
}