{
  "type": "Feature",
  "properties": {
    "addr:full":"Korte Schijfstraat 21 Tilburg Noord-Brabant 5038 SV",
    "addr:housenumber":"21",
    "addr:postcode":"5038 sv",
    "addr:street":"Korte Schijfstraat",
    "iso:country":"NL",
    "sg:address":"Korte Schijfstraat 21",
    "sg:city":"Tilburg",
    "sg:classifiers":[
        {
            "category":"Education",
            "subcategory":"Preschool",
            "type":"Public Place"
        }
    ],
    "sg:phone":"+31 13 542 6712",
    "sg:postcode":"5038 SV",
    "sg:province":"Noord-Brabant",
    "sg:tags":[
        "kleuteronderwijs",
        "basis-"
    ],
    "wof:name":"Openbare Basisschool De Vuurvogel",
    "wof:placetype":"venue"
},
  "geometry": {"coordinates":[5.078215,51.557678],"type":"Point"}
}