{
  "type": "Feature",
  "properties": {
    "addr:full":"Hoogstr 30 Nieuwpoort South Holland 2965 AL",
    "addr:housenumber":"30",
    "addr:postcode":"2965 al",
    "addr:street":"Hoogstr",
    "iso:country":"NL",
    "sg:address":"Hoogstr 30",
    "sg:city":"Nieuwpoort",
    "sg:orig_category":"Wolartikelen En Breiwol",
    "sg:phone":"+31 184 602 678",
    "sg:postcode":"2965 AL",
    "sg:province":"South Holland",
    "wof:name":"Schapekop, De",
    "wof:placetype":"venue"
},
  "geometry": {"coordinates":[4.8696942329,51.9354629517],"type":"Point"}
}