{
  "type": "Feature",
  "properties": {
    "addr:full":"Meester Oude Groenstraat 10 Enschede Overijssel 7548 SB",
    "addr:housenumber":"10",
    "addr:postcode":"7548 sb",
    "addr:street":"Meester Oude Groenstraat",
    "iso:country":"NL",
    "sg:address":"Meester Oude Groenstraat 10",
    "sg:city":"Enschede",
    "sg:orig_category":"Artiestenbureaus",
    "sg:phone":"+31 53 428 1300",
    "sg:postcode":"7548 SB",
    "sg:province":"Overijssel",
    "wof:name":"K Stolwijk",
    "wof:placetype":"venue"
},
  "geometry": {"coordinates":[6.787096,52.204723],"type":"Point"}
}