{
  "type": "Feature",
  "properties": {
    "addr:full":"Energieweg 54 Vlaardingen Zuid-Holland 3133 EC",
    "addr:housenumber":"54",
    "addr:postcode":"3133 ec",
    "addr:street":"Energieweg",
    "iso:country":"NL",
    "sg:address":"Energieweg 54",
    "sg:city":"Vlaardingen",
    "sg:orig_category":"Diverse Bedrijfsinstallaties Gh",
    "sg:phone":"+31 10 434 1411",
    "sg:postcode":"3133 EC",
    "sg:province":"Zuid-Holland",
    "wof:name":"Bekker Reinigingstechniek Bv",
    "wof:placetype":"venue"
},
  "geometry": {"coordinates":[4.326205,51.902485],"type":"Point"}
}