{
  "type": "Feature",
  "properties": {
    "addr:full":"Ten Baanstr 43 Nieuwegein Utrecht 3431 CK",
    "addr:housenumber":"43",
    "addr:postcode":"3431 ck",
    "addr:street":"Ten",
    "iso:country":"NL",
    "sg:address":"Ten Baanstr 43",
    "sg:city":"Nieuwegein",
    "sg:orig_category":"Bloemen En Planten",
    "sg:phone":"+31 30 603 1718",
    "sg:postcode":"3431 CK",
    "sg:province":"Utrecht",
    "wof:name":"Genderen, G Van",
    "wof:placetype":"venue"
},
  "geometry": {"coordinates":[5.091229,52.035923],"type":"Point"}
}