{
  "type": "Feature",
  "properties": {
    "addr:full":"Prinsenhof 9 Lekkerkerk South Holland 2941 XZ",
    "addr:housenumber":"9",
    "addr:postcode":"2941 xz",
    "addr:street":"Prinsenhof",
    "iso:country":"NL",
    "sg:address":"Prinsenhof 9",
    "sg:city":"Lekkerkerk",
    "sg:orig_category":"Loodgieterswerk, Verwarming And Sanitaire Installaties",
    "sg:phone":"+31 180 661 354",
    "sg:postcode":"2941 XZ",
    "sg:province":"South Holland",
    "wof:name":"Installatieburo Bal-Koenders",
    "wof:placetype":"venue"
},
  "geometry": {"coordinates":[4.685625,51.901993],"type":"Point"}
}