{
  "type": "Feature",
  "properties": {
    "addr:full":"Burgemeester V Geusauwg 24 Geldermalsen Gelderland 4191 KW",
    "addr:housenumber":"24",
    "addr:postcode":"4191 kw",
    "addr:street":"Burgemeester V Geusauwg;Gelderland",
    "iso:country":"NL",
    "sg:address":"Burgemeester V Geusauwg 24",
    "sg:city":"Geldermalsen",
    "sg:orig_category":"Binnenhuisarchitecten",
    "sg:phone":"+31 345 580 803",
    "sg:postcode":"4191 KW",
    "sg:province":"Gelderland",
    "wof:name":"Biz Bv",
    "wof:placetype":"venue"
},
  "geometry": {"coordinates":[5.274805,51.883076],"type":"Point"}
}