{
  "type": "Feature",
  "properties": {
    "addr:full":"Wagemakerstr 10 Den Burg Noord-Holland 1791 EK",
    "addr:housenumber":"10",
    "addr:postcode":"1791 ek",
    "addr:street":"Wagemakerstr",
    "iso:country":"NL",
    "sg:address":"Wagemakerstr 10",
    "sg:city":"Den Burg",
    "sg:classifiers":[
        {
            "category":"Building & Trades",
            "subcategory":"Electrical",
            "type":"Services"
        }
    ],
    "sg:phone":"+31 222 312 684",
    "sg:postcode":"1791 EK",
    "sg:province":"Noord-Holland",
    "sg:tags":[
        "distributor"
    ],
    "wof:name":"Rijk, W M J",
    "wof:placetype":"venue"
},
  "geometry": {"coordinates":[4.796855,53.057919],"type":"Point"}
}