{
  "type": "Feature",
  "properties": {
    "addr:full":"Dorpsstraat 2 Assendelft Noord-Holland 1566 AK",
    "addr:housenumber":"2",
    "addr:postcode":"1566 ak",
    "addr:street":"Dorpsstraat",
    "iso:country":"NL",
    "sg:address":"Dorpsstraat 2",
    "sg:city":"Assendelft",
    "sg:orig_category":"Kansspelen",
    "sg:phone":"+31 75 687 1798",
    "sg:postcode":"1566 AK",
    "sg:province":"Noord-Holland",
    "wof:name":"R. De Haan Amusementautomaten",
    "wof:placetype":"venue"
},
  "geometry": {"coordinates":[4.7157177925,52.4381561279],"type":"Point"}
}