{
  "type": "Feature",
  "properties": {
    "addr:full":"Heeswyk 33 Montfoort Utrecht 3417 GP",
    "addr:housenumber":"33",
    "addr:postcode":"3417 gp",
    "addr:street":"Heeswyk",
    "iso:country":"NL",
    "sg:address":"Heeswyk 33",
    "sg:city":"Montfoort",
    "sg:orig_category":"Wasmachines En Wasdrogers - Onderhoud En Reparatie",
    "sg:phone":"+31 348 471 865",
    "sg:postcode":"3417 GP",
    "sg:province":"Utrecht",
    "wof:name":"Power Mobile",
    "wof:placetype":"venue"
},
  "geometry": {"coordinates":[4.9467291832,52.0440673828],"type":"Point"}
}