{
  "type": "Feature",
  "properties": {
    "addr:full":"Van Echtenskanaal N.Z. 162-163 Klazienaveen Drenthe 7891 AJ",
    "addr:housenumber":"162-163",
    "addr:postcode":"7891 aj",
    "addr:street":"Van Echtenskanaal N.Z.",
    "iso:country":"NL",
    "sg:address":"Van Echtenskanaal N.Z. 162-163",
    "sg:city":"Klazienaveen",
    "sg:orig_category":"Verzekeringen",
    "sg:phone":"+31 591 313 114",
    "sg:postcode":"7891 AJ",
    "sg:province":"Drenthe",
    "wof:name":"Assurantiekantoor Koster",
    "wof:placetype":"venue"
},
  "geometry": {"coordinates":[6.992317,52.725029],"type":"Point"}
}