{
  "type": "Feature",
  "properties": {
    "addr:full":"Zandvaart 177 Breezand Noord-Holland 1764 NP",
    "addr:housenumber":"177",
    "addr:postcode":"1764 np",
    "addr:street":"Zandvaart",
    "iso:country":"NL",
    "sg:address":"Zandvaart 177",
    "sg:city":"Breezand",
    "sg:orig_category":"Kappers",
    "sg:phone":"+31 223 521 212",
    "sg:postcode":"1764 NP",
    "sg:province":"Noord-Holland",
    "wof:name":"Ada",
    "wof:placetype":"venue"
},
  "geometry": {"coordinates":[4.8308820724,52.899356842],"type":"Point"}
}