{
  "type": "Feature",
  "properties": {
    "addr:full":"Mykenbroek 14 Breda North Brabant 4824 AB",
    "addr:housenumber":"14",
    "addr:postcode":"4824 ab",
    "addr:street":"Mykenbroek",
    "iso:country":"NL",
    "sg:address":"Mykenbroek 14",
    "sg:city":"Breda",
    "sg:orig_category":"Onderhoudswerken",
    "sg:phone":"+31 76 530 6800",
    "sg:postcode":"4824 AB",
    "sg:province":"North Brabant",
    "wof:name":"Ambacht",
    "wof:placetype":"venue"
},
  "geometry": {"coordinates":[4.75397,51.601913],"type":"Point"}
}