{
  "type": "Feature",
  "properties": {
    "addr:full":"Rembrandtln 1 Veghel Noord-Brabant 5462 CJ",
    "addr:housenumber":"1",
    "addr:postcode":"5462 cj",
    "addr:street":"Rembrandtln",
    "iso:country":"NL",
    "sg:address":"Rembrandtln 1",
    "sg:city":"Veghel",
    "sg:orig_category":"Parketvloeren",
    "sg:phone":"+31 413 363 497",
    "sg:postcode":"5462 CJ",
    "sg:province":"Noord-Brabant",
    "sg:website":"http://www.biggelaar-parket.nl",
    "wof:name":"Biggelaar Parket",
    "wof:placetype":"venue"
},
  "geometry": {"coordinates":[5.53123,51.609119],"type":"Point"}
}