{
  "type": "Feature",
  "properties": {
    "addr:full":"Hoofdstraat 92 Ter Apel Groningen 9561 JE",
    "addr:housenumber":"92",
    "addr:postcode":"9561 je",
    "addr:street":"Hoofdstraat",
    "iso:country":"NL",
    "sg:address":"Hoofdstraat 92",
    "sg:city":"Ter Apel",
    "sg:orig_category":"Bloemen And Planten",
    "sg:phone":"+31 599 587 775",
    "sg:postcode":"9561 JE",
    "sg:province":"Groningen",
    "wof:name":"Velema Bloemen En Planten",
    "wof:placetype":"venue"
},
  "geometry": {"coordinates":[7.052522,52.874054],"type":"Point"}
}