{
  "type": "Feature",
  "properties": {
    "addr:full":"Prinsestr 26 S Gravenhage South Holland 2513 CD",
    "addr:housenumber":"26",
    "addr:postcode":"2513 cd",
    "addr:street":"Prinsestr;S Gravenhage",
    "iso:country":"NL",
    "sg:address":"Prinsestr 26",
    "sg:city":"S Gravenhage",
    "sg:orig_category":"Kappers",
    "sg:phone":"+31 70 365 0611",
    "sg:postcode":"2513 CD",
    "sg:province":"South Holland",
    "wof:name":"Et Cetera",
    "wof:placetype":"venue"
},
  "geometry": {"coordinates":[4.3033900261,52.0784416199],"type":"Point"}
}