{
  "type": "Feature",
  "properties": {
    "addr:full":"Hamerstraat 2 Hengelo Ov Overijssel 7556 MZ",
    "addr:housenumber":"2",
    "addr:postcode":"7556 mz",
    "addr:street":"Hamerstraat;Ov",
    "iso:country":"NL",
    "sg:address":"Hamerstraat 2",
    "sg:city":"Hengelo Ov",
    "sg:orig_category":"Kantoorartikelen",
    "sg:phone":"+31 74 291 4956",
    "sg:postcode":"7556 MZ",
    "sg:province":"Overijssel",
    "wof:name":"Van Der Deen Bv",
    "wof:placetype":"venue"
},
  "geometry": {"coordinates":[6.8090248108,52.2796478271],"type":"Point"}
}