{
  "type": "Feature",
  "properties": {
    "iso:country":"NL",
    "sg:address":"Koopliedenwg 17",
    "sg:city":"Barendrecht",
    "sg:orig_category":"Bakkerijbenodigdheden En -Grondstoffen",
    "sg:phone":"+31 180 613 426",
    "sg:postcode":"2991 LN",
    "sg:province":"South Holland",
    "sg:website":"http://www.dhw.nl",
    "wof:name":"Hoekse Waard Bv Fruitgroothandel",
    "wof:placetype":"venue"
},
  "geometry": {"coordinates":[4.559429,51.856297],"type":"Point"}
}