{
  "type": "Feature",
  "properties": {
    "addr:full":"Glanswit 67 Zoetermeer Zuid-Holland 2718 AD",
    "addr:housenumber":"67",
    "addr:postcode":"2718 ad",
    "addr:street":"Glanswit",
    "iso:country":"NL",
    "sg:address":"Glanswit 67",
    "sg:city":"Zoetermeer",
    "sg:orig_category":"Verzekeringen - Verzekeringskantoren",
    "sg:phone":"+31 35 698 4281",
    "sg:postcode":"2718 AD",
    "sg:province":"Zuid-Holland",
    "wof:name":"Rokkeveen Bv",
    "wof:placetype":"venue"
},
  "geometry": {"coordinates":[4.489677,52.044464],"type":"Point"}
}