{
  "type": "Feature",
  "properties": {
    "addr:full":"Ds J J Ketstr 1 Giethoorn Overijssel 8355 DC",
    "addr:housenumber":"1",
    "addr:postcode":"8355",
    "addr:street":"Ds J;Ketstr",
    "iso:country":"NL",
    "sg:address":"Ds J J Ketstr 1",
    "sg:city":"Giethoorn",
    "sg:orig_category":"Verzekeringen - Verzekeringskantoren",
    "sg:phone":"+31 521 361 065",
    "sg:postcode":"8355 DC",
    "sg:province":"Overijssel",
    "wof:name":"Onderlinge",
    "wof:placetype":"venue"
},
  "geometry": {"coordinates":[6.081824,52.722],"type":"Point"}
}