{
  "type": "Feature",
  "properties": {
    "addr:full":"J Obrechtstr 12 Amsterdam North Holland 1071 KL",
    "addr:housenumber":"12",
    "addr:postcode":"1071 kl",
    "iso:country":"NL",
    "sg:address":"J Obrechtstr 12",
    "sg:city":"Amsterdam",
    "sg:orig_category":"Binnenhuisarchitectuur",
    "sg:phone":"+31 20 675 6527",
    "sg:postcode":"1071 KL",
    "sg:province":"North Holland",
    "wof:name":"Paul Lelieveld",
    "wof:placetype":"venue"
},
  "geometry": {"coordinates":[4.8747,52.356712],"type":"Point"}
}