{
  "type": "Feature",
  "properties": {
    "addr:full":"Denekamperweg 77 Tubbergen NL.08 7651 LC",
    "addr:housenumber":"77;nl.08",
    "addr:postcode":"7651 lc",
    "addr:street":"Denekamperweg",
    "iso:country":"NL",
    "sg:address":"Denekamperweg 77",
    "sg:city":"Tubbergen",
    "sg:orig_category":"Levende Dieren Gh",
    "sg:phone":"+31 546 621 396",
    "sg:postcode":"7651 LC",
    "sg:province":"NL.08",
    "wof:name":"Vof Veehandel Gebr. Boswerger",
    "wof:placetype":"venue"
},
  "geometry": {"coordinates":[6.77854,52.422859],"type":"Point"}
}