{
  "type": "Feature",
  "properties": {
    "addr:full":"H De Keyserstr 68 Rotterdam Zuid-Holland 3034 CN",
    "addr:housenumber":"68",
    "addr:postcode":"3034 cn",
    "iso:country":"NL",
    "sg:address":"H De Keyserstr 68",
    "sg:city":"Rotterdam",
    "sg:orig_category":"Verhuizingen",
    "sg:phone":"+31 10 413 4363",
    "sg:postcode":"3034 CN",
    "sg:province":"Zuid-Holland",
    "wof:name":"Lely Verhuizingen, M De",
    "wof:placetype":"venue"
},
  "geometry": {"coordinates":[4.48865,51.932018],"type":"Point"}
}