{
  "type": "Feature",
  "properties": {
    "addr:full":"L Polakwg 15 Haren Gn Groningen 9752 NT",
    "addr:housenumber":"15",
    "addr:postcode":"9752 nt",
    "iso:country":"NL",
    "sg:address":"L Polakwg 15",
    "sg:city":"Haren Gn",
    "sg:orig_category":"Adviesbureaus Bedrijfsorganisatie",
    "sg:phone":"+31 50 534 2969",
    "sg:postcode":"9752 NT",
    "sg:province":"Groningen",
    "sg:website":"http://www.protarget.nl",
    "wof:name":"Protarget",
    "wof:placetype":"venue"
},
  "geometry": {"coordinates":[6.600736,53.167267],"type":"Point"}
}