{
  "type": "Feature",
  "properties": {
    "addr:full":"Postbus 281 Eindhoven North Brabant 5600 AG",
    "addr:housenumber":"281",
    "addr:postcode":"5600",
    "addr:street":"Postbus",
    "iso:country":"NL",
    "sg:address":"Postbus 281",
    "sg:city":"Eindhoven",
    "sg:orig_category":"Onderzoekbureaus",
    "sg:phone":"+31 40 281 1497",
    "sg:postcode":"5600 AG",
    "sg:province":"North Brabant",
    "wof:name":"Pharus",
    "wof:placetype":"venue"
},
  "geometry": {"coordinates":[5.48411,51.434471],"type":"Point"}
}