{
  "type": "Feature",
  "properties": {
    "addr:full":"Heinsiusln 10 Rotterdam Zuid-Holland 3051 HD",
    "addr:housenumber":"10",
    "addr:postcode":"3051 hd",
    "addr:street":"Heinsiusln",
    "iso:country":"NL",
    "sg:address":"Heinsiusln 10",
    "sg:city":"Rotterdam",
    "sg:orig_category":"Vertaalbureaus",
    "sg:phone":"+31 10 461 4163",
    "sg:postcode":"3051 HD",
    "sg:province":"Zuid-Holland",
    "wof:name":"Ethd",
    "wof:placetype":"venue"
},
  "geometry": {"coordinates":[4.4782,51.945049],"type":"Point"}
}