{
  "type": "Feature",
  "properties": {
    "addr:full":"Dr Cuypersln 47 Eindhoven Noord-Brabant 5622 MA",
    "addr:housenumber":"47",
    "addr:postcode":"5622 ma",
    "iso:country":"NL",
    "sg:address":"Dr Cuypersln 47",
    "sg:city":"Eindhoven",
    "sg:orig_category":"Vakorganisaties",
    "sg:phone":"+31 40 246 4500",
    "sg:postcode":"5622 MA",
    "sg:province":"Noord-Brabant",
    "sg:website":"http://www.aob.nl",
    "wof:name":"Algemene Onderwijsbond",
    "wof:placetype":"venue"
},
  "geometry": {"coordinates":[5.46291,51.459381],"type":"Point"}
}