{
  "type": "Feature",
  "properties": {
    "addr:full":"Europapln 3 Gennep Limburg 6591 AV",
    "addr:housenumber":"3",
    "addr:postcode":"6591 av",
    "addr:street":"Europapln",
    "iso:country":"NL",
    "sg:address":"Europapln 3",
    "sg:city":"Gennep",
    "sg:orig_category":"Artsen - Huisartsen",
    "sg:phone":"+31 485 512 317",
    "sg:postcode":"6591 AV",
    "sg:province":"Limburg",
    "wof:name":"Gennep, Praktijk",
    "wof:placetype":"venue"
},
  "geometry": {"coordinates":[5.970435,51.69809],"type":"Point"}
}