{
  "type": "Feature",
  "properties": {
    "addr:full":"Spaarpot O 4 Geldrop Noord-Brabant 5667 KT",
    "addr:housenumber":"4",
    "addr:postcode":"5667 kt",
    "addr:street":"Spaarpot O",
    "iso:country":"NL",
    "sg:address":"Spaarpot O 4",
    "sg:city":"Geldrop",
    "sg:classifiers":[
        {
            "category":"Retail",
            "subcategory":"Storage",
            "type":"Services"
        }
    ],
    "sg:phone":"+31 40 280 9620",
    "sg:postcode":"5667 KT",
    "sg:province":"Noord-Brabant",
    "sg:tags":[
        "op-",
        "en",
        "overslagbedrijven"
    ],
    "wof:name":"Manders, Tinie",
    "wof:placetype":"venue"
},
  "geometry": {"coordinates":[5.563134,51.437775],"type":"Point"}
}