{
  "type": "Feature",
  "properties": {
    "iso:country":"NL",
    "sg:address":"Vogelzang 94",
    "sg:city":"Drachten",
    "sg:orig_category":"Verenigingen En Stichtingen",
    "sg:phone":"+31 512 523 616",
    "sg:postcode":"9201 SE",
    "sg:province":"Provincie Friesland",
    "wof:name":"Amnesty International",
    "wof:placetype":"venue"
},
  "geometry": {"coordinates":[6.103702,53.110016],"type":"Point"}
}