{
  "type": "Feature",
  "properties": {
    "addr:full":"Langestr 36 Noordhorn Groningen 9804 PL",
    "addr:housenumber":"36",
    "addr:postcode":"9804 pl",
    "addr:street":"Langestr",
    "iso:country":"NL",
    "sg:address":"Langestr 36",
    "sg:city":"Noordhorn",
    "sg:orig_category":"Acupunctuur",
    "sg:phone":"+31 594 529 100",
    "sg:postcode":"9804 PL",
    "sg:province":"Groningen",
    "sg:website":"http://www.natuurgeneeswijze.com",
    "wof:name":"Acupunctuur & Natuurgeneeskunde",
    "wof:placetype":"venue"
},
  "geometry": {"coordinates":[6.394882,53.260563],"type":"Point"}
}