{
  "type": "Feature",
  "properties": {
    "iso:country":"NL",
    "sg:address":"Aalsvoort 74",
    "sg:city":"Lochem",
    "sg:orig_category":"Koeltechniek",
    "sg:phone":"+31 573 288 381",
    "sg:postcode":"7241 MB",
    "sg:province":"Gelderland",
    "sg:website":"http://www.vortec-nl.com",
    "wof:name":"Vortec Europe",
    "wof:placetype":"venue"
},
  "geometry": {"coordinates":[6.382314,52.167645],"type":"Point"}
}