{
  "type": "Feature",
  "properties": {
    "addr:full":"Coenhavenweg 22 Amsterdam Noord-Holland 1013 BL",
    "addr:housenumber":"22",
    "addr:postcode":"1013 bl",
    "addr:street":"Coenhavenweg",
    "iso:country":"NL",
    "sg:address":"Coenhavenweg 22",
    "sg:city":"Amsterdam",
    "sg:classifiers":[
        {
            "category":"Retail",
            "subcategory":"Storage",
            "type":"Services"
        }
    ],
    "sg:phone":"+31 20 581 2200",
    "sg:postcode":"1013 BL",
    "sg:province":"Noord-Holland",
    "sg:tags":[
        "opslag",
        "bewaring"
    ],
    "wof:name":"Expeditie- En Veembedrijf Eggerding En Co Bv",
    "wof:placetype":"venue"
},
  "geometry": {"coordinates":[4.8594632149,52.4046554565],"type":"Point"}
}