{
  "type": "Feature",
  "properties": {
    "iso:country":"NL",
    "sg:address":"Polderpeil 29",
    "sg:city":"Alphen Aan Den Ryn",
    "sg:orig_category":"Voetbalverenigingen",
    "sg:phone":"+31 172 496 575",
    "sg:postcode":"2408 RD",
    "sg:province":"Zuid-Holland",
    "wof:name":"Avc Sant\u00e9",
    "wof:placetype":"venue"
},
  "geometry": {"coordinates":[4.65747,52.11425],"type":"Point"}
}