{
  "type": "Feature",
  "properties": {
    "iso:country":"NL",
    "sg:address":"Verdamstraat 56",
    "sg:city":"Leiden",
    "sg:orig_category":"Advocaten And Juridische Adviseurs",
    "sg:phone":"+31 71 513 2466",
    "sg:postcode":"2313 PN",
    "sg:province":"Zuid-Holland",
    "wof:name":"Advocatenkantoor Mr. C.M.T. Stolwijk-Vlek",
    "wof:placetype":"venue"
},
  "geometry": {"coordinates":[4.50858,52.15329],"type":"Point"}
}