{
  "type": "Feature",
  "properties": {
    "addr:full":"Van Meelstraat 16 Zwijndrecht Zuid-Holland 3331 KR",
    "addr:housenumber":"16",
    "addr:postcode":"3331 kr",
    "addr:street":"Van Meelstraat",
    "iso:country":"NL",
    "sg:address":"Van Meelstraat 16",
    "sg:city":"Zwijndrecht",
    "sg:orig_category":"Kappers",
    "sg:phone":"+31 78 612 7351",
    "sg:postcode":"3331 KR",
    "sg:province":"Zuid-Holland",
    "wof:name":"Dameskapsalon Hilko",
    "wof:placetype":"venue"
},
  "geometry": {"coordinates":[4.6341738701,51.824180603],"type":"Point"}
}