{
  "type": "Feature",
  "properties": {
    "addr:full":"St Servatiusstr 50 Heeswyk Dinther Noord-Brabant 5473 GB",
    "addr:housenumber":"50",
    "addr:postcode":"5473 gb",
    "addr:street":"Heeswyk Dinther",
    "iso:country":"NL",
    "sg:address":"St Servatiusstr 50",
    "sg:city":"Heeswyk Dinther",
    "sg:classifiers":[
        {
            "category":"Shopping",
            "subcategory":"Adult",
            "type":"Retail Goods"
        }
    ],
    "sg:phone":"+31 413 294 017",
    "sg:postcode":"5473 GB",
    "sg:province":"Noord-Brabant",
    "sg:tags":[
        "lingerie",
        "en",
        "tricotage"
    ],
    "sg:website":"http://www.sterrin.nl",
    "wof:name":"Sterrin",
    "wof:placetype":"venue"
},
  "geometry": {"coordinates":[5.474683,51.649246],"type":"Point"}
}