{
  "type": "Feature",
  "properties": {
    "addr:full":"De Gorzen 19 Oudenbosch North Brabant 4731 TV",
    "addr:housenumber":"19",
    "addr:postcode":"4731 tv",
    "addr:street":"De Gorzen",
    "iso:country":"NL",
    "sg:address":"De Gorzen 19",
    "sg:city":"Oudenbosch",
    "sg:orig_category":"Verpakkingsmachines Fab",
    "sg:phone":"+31 165 330 144",
    "sg:postcode":"4731 TV",
    "sg:province":"North Brabant",
    "wof:name":"Boxfill International Bv",
    "wof:placetype":"venue"
},
  "geometry": {"coordinates":[4.535162,51.614899],"type":"Point"}
}