{
  "type": "Feature",
  "properties": {
    "addr:full":"Schevelstraat 3 Uitgeest Noord-Holland 1911 CK",
    "addr:housenumber":"3",
    "addr:postcode":"1911 ck",
    "addr:street":"Schevelstraat",
    "iso:country":"NL",
    "sg:address":"Schevelstraat 3",
    "sg:city":"Uitgeest",
    "sg:orig_category":"Paramedische Behandelingen",
    "sg:phone":"+31 251 319 400",
    "sg:postcode":"1911 CK",
    "sg:province":"Noord-Holland",
    "wof:name":"Uitgeest & Akersloot",
    "wof:placetype":"venue"
},
  "geometry": {"coordinates":[4.713189,52.529758],"type":"Point"}
}