{
  "type": "Feature",
  "properties": {
    "addr:full":"Zwart Janstr 32A Rotterdam Zuid-Holland 3035 AT",
    "addr:housenumber":"32a",
    "addr:postcode":"3035",
    "iso:country":"NL",
    "sg:address":"Zwart Janstr 32A",
    "sg:city":"Rotterdam",
    "sg:orig_category":"Verhuur",
    "sg:phone":"+31 10 465 1277",
    "sg:postcode":"3035 AT",
    "sg:province":"Zuid-Holland",
    "sg:website":"http://www.skala.nl",
    "wof:name":"Skala",
    "wof:placetype":"venue"
},
  "geometry": {"coordinates":[4.479349,51.932755],"type":"Point"}
}