{
  "type": "Feature",
  "properties": {
    "iso:country":"NL",
    "sg:address":"Molenvlietbrink 246",
    "sg:city":"Woerden",
    "sg:orig_category":"Fietsen En Bromfietsen",
    "sg:phone":"+31 348 434 178",
    "sg:postcode":"3448 HS",
    "sg:province":"Utrecht",
    "wof:name":"Wit, Fa R De",
    "wof:placetype":"venue"
},
  "geometry": {"coordinates":[4.863584,52.0769],"type":"Point"}
}