{
  "type": "Feature",
  "properties": {
    "addr:full":"Ln V Meerdervoort 297 S Gravenhage South Holland 2563 AE",
    "addr:housenumber":"297",
    "addr:postcode":"2563 ae",
    "addr:street":"Ln;Meerdervoort;S Gravenhage",
    "iso:country":"NL",
    "sg:address":"Ln V Meerdervoort 297",
    "sg:city":"S Gravenhage",
    "sg:orig_category":"Verzekeringen - Verzekeringskantoren",
    "sg:phone":"+31 70 360 1004",
    "sg:postcode":"2563 AE",
    "sg:province":"South Holland",
    "sg:website":"http://www.mfisher.nl",
    "wof:name":"Fisher",
    "wof:placetype":"venue"
},
  "geometry": {"coordinates":[4.270956,52.072578],"type":"Point"}
}