{
  "type": "Feature",
  "properties": {
    "addr:full":"De Posten 155 Enschede NL.08 7544 LR",
    "addr:housenumber":"155",
    "addr:postcode":"7544 lr",
    "addr:street":"De Posten",
    "iso:country":"NL",
    "sg:address":"De Posten 155",
    "sg:city":"Enschede",
    "sg:orig_category":"Bejaarden - Verzorgingstehuizen",
    "sg:phone":"+31 53 477 8681",
    "sg:postcode":"7544 LR",
    "sg:province":"NL.08",
    "wof:name":"Groote Bueren",
    "wof:placetype":"venue"
},
  "geometry": {"coordinates":[6.880081,52.187256],"type":"Point"}
}