{
  "type": "Feature",
  "properties": {
    "addr:full":"Karel Doormanstraat 125 Amsterdam Noord-Holland 1055 VE",
    "addr:housenumber":"125",
    "addr:postcode":"1055",
    "addr:street":"Karel Doormanstraat;Ve",
    "iso:country":"NL",
    "sg:address":"Karel Doormanstraat 125",
    "sg:city":"Amsterdam",
    "sg:orig_category":"Overheidsdiensten",
    "sg:phone":"+31 20 686 1400",
    "sg:postcode":"1055 VE",
    "sg:province":"Noord-Holland",
    "wof:name":"Swwt Impuls B & P",
    "wof:placetype":"venue"
},
  "geometry": {"coordinates":[4.8585357666,52.3793296814],"type":"Point"}
}