{
  "type": "Feature",
  "properties": {
    "addr:full":"Stuifzandseweg 51 Hoogeveen Provincie Drenthe 7903 TA",
    "addr:housenumber":"51",
    "addr:postcode":"7903 ta",
    "addr:street":"Stuifzandseweg;Provincie",
    "iso:country":"NL",
    "sg:address":"Stuifzandseweg 51",
    "sg:city":"Hoogeveen",
    "sg:orig_category":"Bloemen And Planten",
    "sg:phone":"+31 528 269 767",
    "sg:postcode":"7903 TA",
    "sg:province":"Provincie Drenthe",
    "wof:name":"Millefleurs Hoveniersbedrijf",
    "wof:placetype":"venue"
},
  "geometry": {"coordinates":[6.488495,52.739269],"type":"Point"}
}