{
  "type": "Feature",
  "properties": {
    "addr:full":"Gestelsestraat 44 Eindhoven North Brabant 5615 LG",
    "addr:housenumber":"44",
    "addr:postcode":"5615 lg",
    "addr:street":"Gestelsestraat",
    "iso:country":"NL",
    "sg:address":"Gestelsestraat 44",
    "sg:city":"Eindhoven",
    "sg:orig_category":"Kunst And Kunstenaarsbenodigdheden",
    "sg:phone":"+31 40 244 7392",
    "sg:postcode":"5615 LG",
    "sg:province":"North Brabant",
    "wof:name":"Kunsthandel Ad Nijssen",
    "wof:placetype":"venue"
},
  "geometry": {"coordinates":[5.471808,51.431801],"type":"Point"}
}