{
  "type": "Feature",
  "properties": {
    "addr:full":"Mercatorplein 26 Amsterdam North Holland 1057 CC",
    "addr:housenumber":"26",
    "addr:postcode":"1057 cc",
    "addr:street":"Mercatorplein",
    "iso:country":"NL",
    "sg:address":"Mercatorplein 26",
    "sg:city":"Amsterdam",
    "sg:orig_category":"Wasserettes And Stomerijen",
    "sg:phone":"+31 20 616 1393",
    "sg:postcode":"1057 CC",
    "sg:province":"North Holland",
    "wof:name":"Miele Wassalon",
    "wof:placetype":"venue"
},
  "geometry": {"coordinates":[4.8515100479,52.3698616028],"type":"Point"}
}