{
  "type": "Feature",
  "properties": {
    "addr:full":"Vaartstr 90 Kaatsheuvel Noord-Brabant 5171 JG",
    "addr:housenumber":"90",
    "addr:postcode":"5171 jg",
    "addr:street":"Vaartstr",
    "iso:country":"NL",
    "sg:address":"Vaartstr 90",
    "sg:city":"Kaatsheuvel",
    "sg:orig_category":"Verzekeringen - Verzekeringskantoren",
    "sg:phone":"+31 416 283 836",
    "sg:postcode":"5171 JG",
    "sg:province":"Noord-Brabant",
    "wof:name":"Kruijf-Van Bladel, De",
    "wof:placetype":"venue"
},
  "geometry": {"coordinates":[5.050825,51.661102],"type":"Point"}
}