{
  "type": "Feature",
  "properties": {
    "addr:full":"Spaakstede 3649 Goes Zeeland 4463 EN",
    "addr:housenumber":"3649",
    "addr:postcode":"4463 en",
    "iso:country":"NL",
    "sg:address":"Spaakstede 3649",
    "sg:city":"Goes",
    "sg:orig_category":"Glazenwasserijen",
    "sg:phone":"+31 113 212 155",
    "sg:postcode":"4463 EN",
    "sg:province":"Zeeland",
    "wof:name":"Fk",
    "wof:placetype":"venue"
},
  "geometry": {"coordinates":[-83.914169,39.768833],"type":"Point"}
}