{
  "type": "Feature",
  "properties": {
    "addr:full":"Burg Martensln 52 Leersum Utrecht 3956 EN",
    "addr:housenumber":"52",
    "addr:postcode":"3956 en",
    "addr:street":"Burg;Leersum",
    "iso:country":"NL",
    "sg:address":"Burg Martensln 52",
    "sg:city":"Leersum",
    "sg:orig_category":"Kantoor- En Secretariaatsservice",
    "sg:phone":"+31 343 456 520",
    "sg:postcode":"3956 EN",
    "sg:province":"Utrecht",
    "wof:name":"Lucky Text",
    "wof:placetype":"venue"
},
  "geometry": {"coordinates":[5.4214401245,52.0097351074],"type":"Point"}
}