{
  "type": "Feature",
  "properties": {
    "iso:country":"NL",
    "sg:address":"Wageningseberg 180",
    "sg:city":"Utrecht",
    "sg:orig_category":"Juridische Dienstverlening",
    "sg:phone":"+31 30 280 1577",
    "sg:postcode":"3524 LT",
    "sg:province":"Utrecht",
    "wof:name":"Van Waveren & Partners",
    "wof:placetype":"venue"
},
  "geometry": {"coordinates":[5.128987,52.066696],"type":"Point"}
}