{
  "type": "Feature",
  "properties": {
    "addr:full":"Hulstweg 1 Hierden Gelderland 3849 NS",
    "addr:housenumber":"1",
    "addr:postcode":"3849 ns",
    "addr:street":"Hulstweg;Gelderland",
    "iso:country":"NL",
    "sg:address":"Hulstweg 1",
    "sg:city":"Hierden",
    "sg:orig_category":"Autokeuringen",
    "sg:phone":"+31 341 451 928",
    "sg:postcode":"3849 NS",
    "sg:province":"Gelderland",
    "wof:name":"Lhk Polyester",
    "wof:placetype":"venue"
},
  "geometry": {"coordinates":[5.681057,52.349007],"type":"Point"}
}