{
  "type": "Feature",
  "properties": {
    "addr:full":"P.O.Box 101 Sneek Friesland 8600 AC",
    "addr:housenumber":"101",
    "addr:postcode":"8600 ac",
    "addr:street":"P.O.Box",
    "iso:country":"NL",
    "sg:address":"P.O.Box 101",
    "sg:city":"Sneek",
    "sg:orig_category":"Artiestenbureaus",
    "sg:phone":"+31 515 438 239",
    "sg:postcode":"8600 AC",
    "sg:province":"Friesland",
    "wof:name":"Happy Noe Productions",
    "wof:placetype":"venue"
},
  "geometry": {"coordinates":[5.66197,53.033459],"type":"Point"}
}