{
  "type": "Feature",
  "properties": {
    "addr:full":"Industriekade 26A Sassenheim Zuid-Holland 2172 HV",
    "addr:housenumber":"26a",
    "addr:postcode":"2172 hv",
    "addr:street":"Industriekade",
    "iso:country":"NL",
    "sg:address":"Industriekade 26A",
    "sg:city":"Sassenheim",
    "sg:orig_category":"Drukkerijen",
    "sg:phone":"+31 252 213 302",
    "sg:postcode":"2172 HV",
    "sg:province":"Zuid-Holland",
    "wof:name":"Duineveld",
    "wof:placetype":"venue"
},
  "geometry": {"coordinates":[4.534359,52.224525],"type":"Point"}
}