{
  "type": "Feature",
  "properties": {
    "addr:full":"Beelmanstraat 19 Valkenswaard Noord-Brabant 5554 CJ",
    "addr:housenumber":"19",
    "addr:postcode":"5554 cj",
    "addr:street":"Beelmanstraat",
    "iso:country":"NL",
    "sg:address":"Beelmanstraat 19",
    "sg:city":"Valkenswaard",
    "sg:orig_category":"Kappers",
    "sg:phone":"+31 40 201 5571",
    "sg:postcode":"5554 CJ",
    "sg:province":"Noord-Brabant",
    "wof:name":"Dames En Herenkapsalon Hairline",
    "wof:placetype":"venue"
},
  "geometry": {"coordinates":[5.461523056,51.3534965515],"type":"Point"}
}