{
  "type": "Feature",
  "properties": {
    "addr:full":"Orttswarande 33 Breukelen Ut Utrecht 3621 XN",
    "addr:housenumber":"33",
    "addr:postcode":"3621 xn",
    "addr:street":"Orttswarande",
    "iso:country":"NL",
    "sg:address":"Orttswarande 33",
    "sg:city":"Breukelen Ut",
    "sg:orig_category":"Technische Studies And Onderzoek",
    "sg:phone":"+31 346 250 342",
    "sg:postcode":"3621 XN",
    "sg:province":"Utrecht",
    "wof:name":"J. Breeman",
    "wof:placetype":"venue"
},
  "geometry": {"coordinates":[4.99968,52.181965],"type":"Point"}
}