{
  "type": "Feature",
  "properties": {
    "addr:full":"Karrestr 25 Breda Noord-Brabant 4811 WT",
    "addr:housenumber":"25",
    "addr:postcode":"4811 wt",
    "addr:street":"Karrestr",
    "iso:country":"NL",
    "sg:address":"Karrestr 25",
    "sg:city":"Breda",
    "sg:orig_category":"Juweliers",
    "sg:phone":"+31 76 520 0302",
    "sg:postcode":"4811 WT",
    "sg:province":"Noord-Brabant",
    "wof:name":"Schaap & Citroen",
    "wof:placetype":"venue"
},
  "geometry": {"coordinates":[4.775797,51.587448],"type":"Point"}
}