{
  "type": "Feature",
  "properties": {
    "addr:full":"Dr Berlageln 34 Eindhoven North Brabant 5622 HD",
    "addr:housenumber":"34",
    "addr:postcode":"5622 hd",
    "iso:country":"NL",
    "sg:address":"Dr Berlageln 34",
    "sg:city":"Eindhoven",
    "sg:orig_category":"Verenigingen En Stichtingen",
    "sg:phone":"+31 40 244 6854",
    "sg:postcode":"5622 HD",
    "sg:province":"North Brabant",
    "wof:name":"Salvatoriaanse Gezinsadoptie",
    "wof:placetype":"venue"
},
  "geometry": {"coordinates":[5.46291,51.459381],"type":"Point"}
}