{
  "type": "Feature",
  "properties": {
    "addr:full":"Koekoekwg 18 Hengelo Ov Overijssel 7557 PH",
    "addr:housenumber":"18",
    "addr:postcode":"7557",
    "addr:street":"Koekoekwg;Ov",
    "iso:country":"NL",
    "sg:address":"Koekoekwg 18",
    "sg:city":"Hengelo Ov",
    "sg:orig_category":"Verenigingsgebouwen",
    "sg:phone":"+31 74 242 0177",
    "sg:postcode":"7557 PH",
    "sg:province":"Overijssel",
    "wof:name":"Jeugdzorg Twente",
    "wof:placetype":"venue"
},
  "geometry": {"coordinates":[6.805614,52.267323],"type":"Point"}
}