{
  "type": "Feature",
  "properties": {
    "addr:full":"Kerkstr 9 Nieuw Vennep Noord-Holland 2153 BD",
    "addr:housenumber":"9",
    "addr:postcode":"2153 bd",
    "addr:street":"Kerkstr;Nieuw Vennep",
    "iso:country":"NL",
    "sg:address":"Kerkstr 9",
    "sg:city":"Nieuw Vennep",
    "sg:orig_category":"Hek- En Rasterwerken",
    "sg:phone":"+31 252 689 018",
    "sg:postcode":"2153 BD",
    "sg:province":"Noord-Holland",
    "wof:name":"Jto Sierhekwerken",
    "wof:placetype":"venue"
},
  "geometry": {"coordinates":[4.633269,52.262962],"type":"Point"}
}