{
  "type": "Feature",
  "properties": {
    "addr:full":"Donkeregaarde 39 Nieuwegein Utrecht 3436 ZD",
    "addr:housenumber":"39",
    "addr:postcode":"3436 zd",
    "addr:street":"Donkeregaarde",
    "iso:country":"NL",
    "sg:address":"Donkeregaarde 39",
    "sg:city":"Nieuwegein",
    "sg:orig_category":"Administratie- En Boekhoudkantoren",
    "sg:phone":"+31 30 609 0788",
    "sg:postcode":"3436 ZD",
    "sg:province":"Utrecht",
    "wof:name":"Finadcom",
    "wof:placetype":"venue"
},
  "geometry": {"coordinates":[5.067683,52.030926],"type":"Point"}
}