{
  "type": "Feature",
  "properties": {
    "iso:country":"NL",
    "sg:address":"Europaln 22",
    "sg:city":"Utrecht",
    "sg:orig_category":"Postkantoren",
    "sg:phone":"+31 30 287 5310",
    "sg:postcode":"3526 KS",
    "sg:province":"Utrecht",
    "wof:name":"Postkantoor",
    "wof:placetype":"venue"
},
  "geometry": {"coordinates":[5.09982,52.063389],"type":"Point"}
}