{
  "type": "Feature",
  "properties": {
    "addr:full":"Haverstr Passage 58 Enschede Overijssel 7511 EX",
    "addr:housenumber":"58",
    "addr:postcode":"7511 ex",
    "addr:street":"Passage",
    "iso:country":"NL",
    "sg:address":"Haverstr Passage 58",
    "sg:city":"Enschede",
    "sg:orig_category":"Gelegenheidskleding",
    "sg:phone":"+31 53 430 3218",
    "sg:postcode":"7511 EX",
    "sg:province":"Overijssel",
    "wof:name":"Rubi Style",
    "wof:placetype":"venue"
},
  "geometry": {"coordinates":[6.897733,52.220802],"type":"Point"}
}