{
  "type": "Feature",
  "properties": {
    "iso:country":"NL",
    "sg:address":"Heiliglandsestr 13C",
    "sg:city":"Groessen",
    "sg:orig_category":"Accountants - Administratie- Consulenten En -Kantoren",
    "sg:phone":"+31 316 340 790",
    "sg:postcode":"6923 PH",
    "sg:province":"Gelderland",
    "wof:name":"Mulder, J B G H",
    "wof:placetype":"venue"
},
  "geometry": {"coordinates":[6.032345,51.933922],"type":"Point"}
}