{
  "type": "Feature",
  "properties": {
    "addr:full":"Walmolen 19 Amsterdam Noord-Holland 1035 BK",
    "addr:housenumber":"19",
    "addr:postcode":"1035 bk",
    "addr:street":"Walmolen",
    "iso:country":"NL",
    "sg:address":"Walmolen 19",
    "sg:city":"Amsterdam",
    "sg:classifiers":[
        {
            "category":"Personal",
            "subcategory":"Nail Salon",
            "type":"Services"
        }
    ],
    "sg:phone":"+31 20 633 7221",
    "sg:postcode":"1035 BK",
    "sg:province":"Noord-Holland",
    "sg:tags":[
        "pedicure"
    ],
    "wof:name":"Manja",
    "wof:placetype":"venue"
},
  "geometry": {"coordinates":[4.889739,52.418762],"type":"Point"}
}