{
  "type": "Feature",
  "properties": {
    "addr:full":"Haverdreef 109 Doetinchem Gelderland 7006 LH",
    "addr:housenumber":"109",
    "addr:postcode":"7006 lh",
    "addr:street":"Haverdreef;Gelderland",
    "iso:country":"NL",
    "sg:address":"Haverdreef 109",
    "sg:city":"Doetinchem",
    "sg:orig_category":"Diverse Bedrijfsinstallaties Gh",
    "sg:phone":"+31 314 364 468",
    "sg:postcode":"7006 LH",
    "sg:province":"Gelderland",
    "wof:name":"Transpotech",
    "wof:placetype":"venue"
},
  "geometry": {"coordinates":[6.24695,51.969322],"type":"Point"}
}