{
  "type": "Feature",
  "properties": {
    "addr:full":"Sluiskade 24 Hoogezand Groningen 9601 LC",
    "addr:housenumber":"24",
    "addr:postcode":"9601 lc",
    "addr:street":"Sluiskade",
    "iso:country":"NL",
    "sg:address":"Sluiskade 24",
    "sg:city":"Hoogezand",
    "sg:orig_category":"Kappers",
    "sg:phone":"+31 598 395 402",
    "sg:postcode":"9601 LC",
    "sg:province":"Groningen",
    "wof:name":"Hairfashion Monique",
    "wof:placetype":"venue"
},
  "geometry": {"coordinates":[6.7418618202,53.1639404297],"type":"Point"}
}