{
  "type": "Feature",
  "properties": {
    "addr:full":"Putstr 56 Sittard Limburg 6131 HN",
    "addr:housenumber":"56",
    "addr:postcode":"6131 hn",
    "addr:street":"Putstr",
    "iso:country":"NL",
    "sg:address":"Putstr 56",
    "sg:city":"Sittard",
    "sg:orig_category":"Webdesign Bureaus",
    "sg:phone":"+31 46 400 0393",
    "sg:postcode":"6131 HN",
    "sg:province":"Limburg",
    "sg:website":"http://www.nexis.nl",
    "wof:name":"Nexis",
    "wof:placetype":"venue"
},
  "geometry": {"coordinates":[5.8733110428,50.9968109131],"type":"Point"}
}