{
  "type": "Feature",
  "properties": {
    "addr:full":"Hoorn 23 Ede Gld Gelderland 6713 KR",
    "addr:housenumber":"23",
    "addr:postcode":"6713 kr",
    "addr:street":"Hoorn;Gld Gelderland",
    "iso:country":"NL",
    "sg:address":"Hoorn 23",
    "sg:city":"Ede Gld",
    "sg:orig_category":"Autokeuringen",
    "sg:phone":"+31 318 633 132",
    "sg:postcode":"6713 KR",
    "sg:province":"Gelderland",
    "wof:name":"K. Kriek",
    "wof:placetype":"venue"
},
  "geometry": {"coordinates":[5.652372,52.033676],"type":"Point"}
}