{
  "type": "Feature",
  "properties": {
    "addr:full":"Novaln 4 Arnhem Gelderland 6824 EM",
    "addr:housenumber":"4",
    "addr:postcode":"6824 em",
    "addr:street":"Novaln",
    "iso:country":"NL",
    "sg:address":"Novaln 4",
    "sg:city":"Arnhem",
    "sg:orig_category":"Verzekeringen - Verzekeringskantoren",
    "sg:phone":"+31 26 361 7788",
    "sg:postcode":"6824 EM",
    "sg:province":"Gelderland",
    "wof:name":"Smolders, J C",
    "wof:placetype":"venue"
},
  "geometry": {"coordinates":[5.93741,51.993671],"type":"Point"}
}