{
  "type": "Feature",
  "properties": {
    "iso:country":"NL",
    "sg:address":"Prinsenstr 14",
    "sg:city":"Groningen",
    "sg:orig_category":"Hypotheken",
    "sg:phone":"+31 50 526 9434",
    "sg:postcode":"9711 CM",
    "sg:province":"Groningen",
    "sg:website":"http://www.lahnsteinfc.nl",
    "wof:name":"Lahnstein Financial Consulting",
    "wof:placetype":"venue"
},
  "geometry": {"coordinates":[6.570333,53.21505],"type":"Point"}
}