{
  "type": "Feature",
  "properties": {
    "addr:full":"Nieuwe Kerkstraat 64 Amsterdam Noord-Holland 1018 EC",
    "addr:housenumber":"64",
    "addr:postcode":"1018 ec",
    "addr:street":"Nieuwe Kerkstraat",
    "iso:country":"NL",
    "sg:address":"Nieuwe Kerkstraat 64",
    "sg:city":"Amsterdam",
    "sg:orig_category":"Boekhouders",
    "sg:phone":"+31 20 624 4506",
    "sg:postcode":"1018 EC",
    "sg:province":"Noord-Holland",
    "wof:name":"Finance Umbrella Vof",
    "wof:placetype":"venue"
},
  "geometry": {"coordinates":[4.905245,52.363972],"type":"Point"}
}