{
  "type": "Feature",
  "properties": {
    "addr:full":"R Holstr 36 Dordrecht South Holland 3314 CK",
    "addr:housenumber":"36",
    "addr:postcode":"3314 ck",
    "iso:country":"NL",
    "sg:address":"R Holstr 36",
    "sg:city":"Dordrecht",
    "sg:orig_category":"Keukens",
    "sg:phone":"+31 6 53958667",
    "sg:postcode":"3314 CK",
    "sg:province":"South Holland",
    "wof:name":"Rehorst",
    "wof:placetype":"venue"
},
  "geometry": {"coordinates":[4.65162,51.801491],"type":"Point"}
}