{
  "type": "Feature",
  "properties": {
    "addr:full":"Ln V Fasna 87 Vaassen Gelderland 8171 NR",
    "addr:housenumber":"87",
    "addr:postcode":"8171",
    "addr:street":"Ln;Fasna;Gelderland;Nr",
    "iso:country":"NL",
    "sg:address":"Ln V Fasna 87",
    "sg:city":"Vaassen",
    "sg:orig_category":"Administratie- En Boekhoudkantoren",
    "sg:phone":"+31 578 574 808",
    "sg:postcode":"8171 NR",
    "sg:province":"Gelderland",
    "sg:website":"http://www.consultantnedgroep.nl",
    "wof:name":"Consultance Groep Nederland",
    "wof:placetype":"venue"
},
  "geometry": {"coordinates":[5.969314,52.290188],"type":"Point"}
}