{
  "type": "Feature",
  "properties": {
    "addr:full":"St.- Christoffelstraat 6 Elsendorp Noord-Brabant 5424 TE",
    "addr:housenumber":"6",
    "addr:postcode":"5424 te",
    "addr:street":"St. Christoffelstraat",
    "iso:country":"NL",
    "sg:address":"St.- Christoffelstraat 6",
    "sg:city":"Elsendorp",
    "sg:orig_category":"Metaalbekleding And -Behandeling",
    "sg:phone":"+31 492 351 518",
    "sg:postcode":"5424 TE",
    "sg:province":"Noord-Brabant",
    "wof:name":"W J Oostendorp",
    "wof:placetype":"venue"
},
  "geometry": {"coordinates":[5.769615,51.579811],"type":"Point"}
}