{
  "type": "Feature",
  "properties": {
    "addr:full":"Korte Voorhouterweg 33 Rijnsburg Zuid-Holland 2231 JH",
    "addr:housenumber":"33",
    "addr:postcode":"2231 jh",
    "addr:street":"Korte Voorhouterweg",
    "iso:country":"NL",
    "sg:address":"Korte Voorhouterweg 33",
    "sg:city":"Rijnsburg",
    "sg:orig_category":"Bloemen And Planten Gh",
    "sg:phone":"+31 71 402 8232",
    "sg:postcode":"2231 JH",
    "sg:province":"Zuid-Holland",
    "wof:name":"Bloemenexport Ben De Vries",
    "wof:placetype":"venue"
},
  "geometry": {"coordinates":[4.446695,52.195206],"type":"Point"}
}