{
  "type": "Feature",
  "properties": {
    "addr:full":"Steeg 31 Sevenum Limburg 5975 CD",
    "addr:housenumber":"31",
    "addr:postcode":"5975 cd",
    "addr:street":"Steeg",
    "iso:country":"NL",
    "sg:address":"Steeg 31",
    "sg:city":"Sevenum",
    "sg:orig_category":"Kinderopvang Behalve Thuis",
    "sg:phone":"+31 77 467 4341",
    "sg:postcode":"5975 CD",
    "sg:province":"Limburg",
    "wof:name":"Okki",
    "wof:placetype":"venue"
},
  "geometry": {"coordinates":[6.021398,51.404259],"type":"Point"}
}