{
  "type": "Feature",
  "properties": {
    "iso:country":"NL",
    "sg:address":"Lageweg 65",
    "sg:city":"Noordlaren",
    "sg:orig_category":"Watersport-, Sport- And Kampeerbenodigdheden Verhuur",
    "sg:phone":"+31 50 402 9008",
    "sg:postcode":"9479 PB",
    "sg:province":"Provincie Drenthe",
    "wof:name":"R Renting Bv",
    "wof:placetype":"venue"
},
  "geometry": {"coordinates":[6.6700129509,53.1186485291],"type":"Point"}
}