{
  "type": "Feature",
  "properties": {
    "iso:country":"NL",
    "sg:address":"Dorpsstraat 112",
    "sg:city":"Broek Op Langedijk",
    "sg:orig_category":"Pleziervaartuigen And Reparatie",
    "sg:phone":"+31 226 313 863",
    "sg:postcode":"1721 BN",
    "sg:province":"Noord-Holland",
    "wof:name":"Scheepswerf En Machineherstelplaats P De",
    "wof:placetype":"venue"
},
  "geometry": {"coordinates":[4.807984,52.67918],"type":"Point"}
}