{
  "type": "Feature",
  "properties": {
    "addr:full":"Mon Plaisir 102C Etten Leur North Brabant 4879 AT",
    "addr:housenumber":"102c",
    "addr:postcode":"4879",
    "addr:street":"Mon Plaisir",
    "iso:country":"NL",
    "sg:address":"Mon Plaisir 102C",
    "sg:city":"Etten Leur",
    "sg:orig_category":"Verhuizingen",
    "sg:phone":"+31 76 502 0276",
    "sg:postcode":"4879 AT",
    "sg:province":"North Brabant",
    "wof:name":"Martens",
    "wof:placetype":"venue"
},
  "geometry": {"coordinates":[4.613077,51.56176],"type":"Point"}
}