{
  "type": "Feature",
  "properties": {
    "addr:full":"P J Troelstralaan 87 Schiedam Zuid-Holland 3118 VC",
    "addr:housenumber":"87",
    "addr:postcode":"3118 vc",
    "addr:street":"P J Troelstralaan",
    "iso:country":"NL",
    "sg:address":"P J Troelstralaan 87",
    "sg:city":"Schiedam",
    "sg:classifiers":[
        {
            "category":"Fast Food",
            "type":"Food & Drink"
        }
    ],
    "sg:phone":"+31 10 471 9898",
    "sg:postcode":"3118 VC",
    "sg:province":"Zuid-Holland",
    "sg:tags":[
        "afhaal",
        "restaurant"
    ],
    "wof:name":"Star Food",
    "wof:placetype":"venue"
},
  "geometry": {"coordinates":[4.381474,51.917336],"type":"Point"}
}