{
  "type": "Feature",
  "properties": {
    "addr:full":"Noorderstraat 6 Emmen Drenthe 7811 AL",
    "addr:housenumber":"6",
    "addr:postcode":"7811 al",
    "addr:street":"Noorderstraat",
    "iso:country":"NL",
    "sg:address":"Noorderstraat 6",
    "sg:city":"Emmen",
    "sg:orig_category":"Juweliers",
    "sg:phone":"+31 591 612 478",
    "sg:postcode":"7811 AL",
    "sg:province":"Drenthe",
    "wof:name":"Juwelier P.J. De Nijs",
    "wof:placetype":"venue"
},
  "geometry": {"coordinates":[6.894369,52.786873],"type":"Point"}
}