{
  "type": "Feature",
  "properties": {
    "iso:country":"NL",
    "sg:address":"Edisonwg 9",
    "sg:city":"Elst Gld",
    "sg:orig_category":"Koeriersdiensten",
    "sg:phone":"+31 481 377 930",
    "sg:postcode":"6662 NW",
    "sg:province":"Gelderland",
    "wof:name":"Micodo",
    "wof:placetype":"venue"
},
  "geometry": {"coordinates":[5.864197,51.912949],"type":"Point"}
}