{
  "type": "Feature",
  "properties": {
    "addr:full":"Gastelsewg 60 Budel Noord-Brabant 6021 GM",
    "addr:housenumber":"60",
    "addr:postcode":"6021 gm",
    "addr:street":"Gastelsewg",
    "iso:country":"NL",
    "sg:address":"Gastelsewg 60",
    "sg:city":"Budel",
    "sg:orig_category":"Administratie- En Boekhoudkantoren",
    "sg:phone":"+31 495 430 705",
    "sg:postcode":"6021 GM",
    "sg:province":"Noord-Brabant",
    "sg:website":"http://www.bfa.nl",
    "wof:name":"Bf & A Kempenland Adm Kantoor",
    "wof:placetype":"venue"
},
  "geometry": {"coordinates":[5.568117,51.278263],"type":"Point"}
}