{
  "type": "Feature",
  "properties": {
    "addr:full":"Rietgors 5 Leusden Utrecht 3831 HK",
    "addr:housenumber":"5",
    "addr:postcode":"3831 hk",
    "addr:street":"Rietgors",
    "iso:country":"NL",
    "sg:address":"Rietgors 5",
    "sg:city":"Leusden",
    "sg:orig_category":"Diverse Bedrijfsinstallaties Gh",
    "sg:phone":"+31 33 494 8510",
    "sg:postcode":"3831 HK",
    "sg:province":"Utrecht",
    "wof:name":"Groothandel M. Furst",
    "wof:placetype":"venue"
},
  "geometry": {"coordinates":[5.443205,52.134247],"type":"Point"}
}