{
  "type": "Feature",
  "properties": {
    "iso:country":"NL",
    "sg:address":"S Bossestr 77",
    "sg:city":"Noordwyk Zh",
    "sg:orig_category":"Scholen Voor Basisonderwijs",
    "sg:phone":"+31 71 361 2031",
    "sg:postcode":"2203 GH",
    "sg:province":"Zuid-Holland",
    "wof:name":"Vierboet Prot Chr, De",
    "wof:placetype":"venue"
},
  "geometry": {"coordinates":[4.4477,52.234261],"type":"Point"}
}