{
  "type": "Feature",
  "properties": {
    "addr:full":"De Wittenkd 140 Amsterdam Noord-Holland 1051 AM",
    "addr:housenumber":"140",
    "addr:postcode":"1051",
    "iso:country":"NL",
    "sg:address":"De Wittenkd 140",
    "sg:city":"Amsterdam",
    "sg:orig_category":"Vertaalbureaus",
    "sg:phone":"+31 20 400 3766",
    "sg:postcode":"1051 AM",
    "sg:province":"Noord-Holland",
    "wof:name":"Forward Motion",
    "wof:placetype":"venue"
},
  "geometry": {"coordinates":[4.87107,52.37925],"type":"Point"}
}