{
  "type": "Feature",
  "properties": {
    "addr:full":"Tramstraat 44 Lochem Gelderland 7241 CK",
    "addr:housenumber":"44",
    "addr:postcode":"7241 ck",
    "addr:street":"Tramstraat;Gelderland",
    "iso:country":"NL",
    "sg:address":"Tramstraat 44",
    "sg:city":"Lochem",
    "sg:classifiers":[
        {
            "category":"Fast Food",
            "type":"Food & Drink"
        }
    ],
    "sg:phone":"+31 573 257 634",
    "sg:postcode":"7241 CK",
    "sg:province":"Gelderland",
    "sg:tags":[
        "afhaal",
        "restaurant"
    ],
    "wof:name":"T Kruuspunt",
    "wof:placetype":"venue"
},
  "geometry": {"coordinates":[6.408676,52.163338],"type":"Point"}
}