{
  "type": "Feature",
  "properties": {
    "addr:full":"Papiermolen 77 Capelle A/D Ijssel Zuid-Holland 2906 RC",
    "addr:housenumber":"77;a / d",
    "addr:postcode":"2906 rc",
    "addr:street":"Papiermolen",
    "iso:country":"NL",
    "sg:address":"Papiermolen 77",
    "sg:city":"Capelle A/D Ijssel",
    "sg:orig_category":"Gespecialiseerde Bouw",
    "sg:phone":"+31 10 450 7062",
    "sg:postcode":"2906 RC",
    "sg:province":"Zuid-Holland",
    "wof:name":"Firma A. Hagoort",
    "wof:placetype":"venue"
},
  "geometry": {"coordinates":[4.5664,51.939163],"type":"Point"}
}