{
  "type": "Feature",
  "properties": {
    "addr:full":"Kap Huybersln 12 Oisterwyk Noord-Brabant 5061 BC",
    "addr:housenumber":"12",
    "addr:postcode":"5061 bc",
    "addr:street":"Oisterwyk",
    "iso:country":"NL",
    "sg:address":"Kap Huybersln 12",
    "sg:city":"Oisterwyk",
    "sg:orig_category":"Architecten En Architectenbureaus",
    "sg:phone":"+31 13 528 3933",
    "sg:postcode":"5061 BC",
    "sg:province":"Noord-Brabant",
    "sg:website":"http://www.vandenhoutvandenoetelaar.nl",
    "wof:name":"Hout & V/D Oetelaar, Architektenburo V/D",
    "wof:placetype":"venue"
},
  "geometry": {"coordinates":[5.1821,51.57653],"type":"Point"}
}