{
  "type": "Feature",
  "properties": {
    "iso:country":"NL",
    "sg:address":"Ballumerweg 3",
    "sg:city":"Nes Ameland",
    "sg:classifiers":[
        {
            "category":"Fast Food",
            "type":"Food & Drink"
        }
    ],
    "sg:phone":"+31 519 542 720",
    "sg:postcode":"9163 GA",
    "sg:province":"Friesland",
    "sg:tags":[
        "afhaal",
        "restaurant"
    ],
    "wof:name":"Pizzeria San Remo",
    "wof:placetype":"venue"
},
  "geometry": {"coordinates":[5.765018,53.44611],"type":"Point"}
}