{
  "type": "Feature",
  "properties": {
    "addr:full":"Heuvelakkersestr 21 Aerdt Gelderland 6913 AA",
    "addr:housenumber":"21",
    "addr:postcode":"6913 aa",
    "addr:street":"Heuvelakkersestr;Gelderland",
    "iso:country":"NL",
    "sg:address":"Heuvelakkersestr 21",
    "sg:city":"Aerdt",
    "sg:orig_category":"Poppen En Poppenhuismaterialen",
    "sg:phone":"+31 316 248 640",
    "sg:postcode":"6913 AA",
    "sg:province":"Gelderland",
    "sg:website":"http://www.minilaars.nl",
    "wof:name":"Minilaars, De",
    "wof:placetype":"venue"
},
  "geometry": {"coordinates":[6.089419,51.888653],"type":"Point"}
}