{
  "type": "Feature",
  "properties": {
    "iso:country":"NL",
    "sg:address":"Bronovolaan 2",
    "sg:city":"'S Gravenhage",
    "sg:orig_category":"Makelaars In Onroerend Goed",
    "sg:phone":"+31 70 324 5434",
    "sg:postcode":"2597 AZ",
    "sg:province":"Zuid-Holland",
    "wof:name":"Alberts Makelaardij In Onroerend Goed",
    "wof:placetype":"venue"
},
  "geometry": {"coordinates":[4.314623,52.101505],"type":"Point"}
}