{
  "type": "Feature",
  "properties": {
    "iso:country":"NL",
    "sg:address":"Nijverheidsstraat 41A",
    "sg:city":"Nijkerk Gld",
    "sg:orig_category":"Warmtetechniek",
    "sg:phone":"+31 33 245 9634",
    "sg:postcode":"3861 RJ",
    "sg:province":"Gelderland",
    "wof:name":"Hoaf Apparatenfabriek Bv",
    "wof:placetype":"venue"
},
  "geometry": {"coordinates":[5.4775090218,52.23387146],"type":"Point"}
}