{
  "type": "Feature",
  "properties": {
    "addr:full":"Molenwyk 17 Amsterdam Noord-Holland 1035 EG",
    "addr:housenumber":"17",
    "addr:postcode":"1035 eg",
    "addr:street":"Molenwyk",
    "iso:country":"NL",
    "sg:address":"Molenwyk 17",
    "sg:city":"Amsterdam",
    "sg:orig_category":"Mensendieck - Oefentherapeuten",
    "sg:phone":"+31 20 633 1691",
    "sg:postcode":"1035 EG",
    "sg:province":"Noord-Holland",
    "wof:name":"Croesse & H N Visser A",
    "wof:placetype":"venue"
},
  "geometry": {"coordinates":[4.888625,52.421196],"type":"Point"}
}