{
  "type": "Feature",
  "properties": {
    "addr:full":"Grotestr 55 Almelo NL.08 7607 CC",
    "addr:housenumber":"55;nl.08",
    "addr:postcode":"7607 cc",
    "addr:street":"Grotestr",
    "iso:country":"NL",
    "sg:address":"Grotestr 55",
    "sg:city":"Almelo",
    "sg:orig_category":"Huishoudelijke Apparaten En Artikelen",
    "sg:phone":"+31 546 456 331",
    "sg:postcode":"7607 CC",
    "sg:province":"NL.08",
    "wof:name":"Euro Shop",
    "wof:placetype":"venue"
},
  "geometry": {"coordinates":[6.664531,52.357281],"type":"Point"}
}