{
  "type": "Feature",
  "properties": {
    "addr:full":"Zwijnsbergen 53 Elst Ut Utrecht 3921 DW",
    "addr:housenumber":"53",
    "addr:postcode":"ut;3921 dw",
    "addr:street":"Zwijnsbergen",
    "iso:country":"NL",
    "sg:address":"Zwijnsbergen 53",
    "sg:city":"Elst Ut",
    "sg:orig_category":"Verhuur Bouwmachines",
    "sg:phone":"+31 318 471 992",
    "sg:postcode":"3921 DW",
    "sg:province":"Utrecht",
    "wof:name":"J. Keuken",
    "wof:placetype":"venue"
},
  "geometry": {"coordinates":[5.511843,51.984146],"type":"Point"}
}