{
  "type": "Feature",
  "properties": {
    "addr:full":"Watermanwg 53 Rotterdam Zuid-Holland 3067 GA",
    "addr:housenumber":"53",
    "addr:postcode":"3067 ga",
    "addr:street":"Watermanwg",
    "iso:country":"NL",
    "sg:address":"Watermanwg 53",
    "sg:city":"Rotterdam",
    "sg:orig_category":"Behangselpapier En Wandbekleding",
    "sg:phone":"+31 10 421 8882",
    "sg:postcode":"3067 GA",
    "sg:province":"Zuid-Holland",
    "wof:name":"Rothmeijer",
    "wof:placetype":"venue"
},
  "geometry": {"coordinates":[4.559821,51.951405],"type":"Point"}
}