{
  "type": "Feature",
  "properties": {
    "addr:full":"Damstg 14 Nieuw Beyerland Zuid-Holland 3264 AZ",
    "addr:housenumber":"14",
    "addr:postcode":"3264 az",
    "addr:street":"Damstg;Nieuw Beyerland",
    "iso:country":"NL",
    "sg:address":"Damstg 14",
    "sg:city":"Nieuw Beyerland",
    "sg:orig_category":"Adviesbureaus Bouwkunde",
    "sg:phone":"+31 186 694 210",
    "sg:postcode":"3264 AZ",
    "sg:province":"Zuid-Holland",
    "wof:name":"Beijerland Bv, Bur",
    "wof:placetype":"venue"
},
  "geometry": {"coordinates":[4.334294,51.809929],"type":"Point"}
}