{
  "type": "Feature",
  "properties": {
    "addr:full":"Rooversbroekdijk 125 Lisse North Holland 2161 LP",
    "addr:housenumber":"125",
    "addr:postcode":"2161 lp",
    "addr:street":"Rooversbroekdijk",
    "iso:country":"NL",
    "sg:address":"Rooversbroekdijk 125",
    "sg:city":"Lisse",
    "sg:orig_category":"Bloemen And Planten Gh",
    "sg:phone":"+31 252 213 473",
    "sg:postcode":"2161 LP",
    "sg:province":"North Holland",
    "wof:name":"Will'S Flower Export",
    "wof:placetype":"venue"
},
  "geometry": {"coordinates":[4.553813,52.241104],"type":"Point"}
}