{
  "type": "Feature",
  "properties": {
    "addr:full":"Patrijsweg 2 Epe Gelderland 8161 VJ",
    "addr:housenumber":"2",
    "addr:postcode":"8161 vj",
    "addr:street":"Patrijsweg;Gelderland",
    "iso:country":"NL",
    "sg:address":"Patrijsweg 2",
    "sg:city":"Epe",
    "sg:orig_category":"Alternatieve Geneeskunde",
    "sg:phone":"+31 578 612 862",
    "sg:postcode":"8161 VJ",
    "sg:province":"Gelderland",
    "wof:name":"Fysiotherapiepraktijk Epe Oene",
    "wof:placetype":"venue"
},
  "geometry": {"coordinates":[5.985778,52.342827],"type":"Point"}
}