{
  "type": "Feature",
  "properties": {
    "addr:full":"T De Boerstr 8 Balk Friesland 8561 EL",
    "addr:housenumber":"8",
    "addr:postcode":"8561 el",
    "addr:street":"T;Boerstr",
    "iso:country":"NL",
    "sg:address":"T De Boerstr 8",
    "sg:city":"Balk",
    "sg:classifiers":[
        {
            "category":"Retail",
            "subcategory":"Auto Repair",
            "type":"Services"
        }
    ],
    "sg:phone":"+31 514 604 152",
    "sg:postcode":"8561 EL",
    "sg:province":"Friesland",
    "sg:tags":[
        "garage"
    ],
    "wof:name":"Zuiderbaan",
    "wof:placetype":"venue"
},
  "geometry": {"coordinates":[-100.82858299999999,36.608829],"type":"Point"}
}