{
  "type": "Feature",
  "properties": {
    "addr:full":"Veerdk 103 Wormer North Holland 1531 MB",
    "addr:housenumber":"103",
    "addr:postcode":"1531 mb",
    "addr:street":"Wormer North",
    "iso:country":"NL",
    "sg:address":"Veerdk 103",
    "sg:city":"Wormer",
    "sg:orig_category":"Jachthavens - Jachtwerven",
    "sg:phone":"+31 75 628 1565",
    "sg:postcode":"1531 MB",
    "sg:province":"North Holland",
    "wof:name":"Bijdam",
    "wof:placetype":"venue"
},
  "geometry": {"coordinates":[4.795577,52.500622],"type":"Point"}
}