{
  "type": "Feature",
  "properties": {
    "addr:full":"Nachtegaalln 66 Helmond Noord-Brabant 5702 KP",
    "addr:housenumber":"66",
    "addr:postcode":"5702 kp",
    "addr:street":"Nachtegaalln",
    "iso:country":"NL",
    "sg:address":"Nachtegaalln 66",
    "sg:city":"Helmond",
    "sg:orig_category":"Bejaarden - Verzorgingstehuizen",
    "sg:phone":"+31 492 537 844",
    "sg:postcode":"5702 KP",
    "sg:province":"Noord-Brabant",
    "wof:name":"Eeuwsels, De",
    "wof:placetype":"venue"
},
  "geometry": {"coordinates":[5.666468,51.49387],"type":"Point"}
}