{
  "type": "Feature",
  "properties": {
    "addr:full":"Loevesteinlaan 649 'S Gravenhage Zuid-Holland 2533 BH",
    "addr:housenumber":"649 '",
    "addr:postcode":"2533 bh",
    "addr:street":"Loevesteinlaan",
    "iso:country":"NL",
    "sg:address":"Loevesteinlaan 649",
    "sg:city":"'S Gravenhage",
    "sg:orig_category":"Kinderopvang Behalve Thuis",
    "sg:phone":"+31 70 329 8411",
    "sg:postcode":"2533 BH",
    "sg:province":"Zuid-Holland",
    "wof:name":"De Joppe",
    "wof:placetype":"venue"
},
  "geometry": {"coordinates":[4.287819,52.045837],"type":"Point"}
}