{
  "type": "Feature",
  "properties": {
    "addr:full":"Ceramstraat 36 Dordrecht South Holland 3312 SH",
    "addr:housenumber":"36",
    "addr:postcode":"3312 sh",
    "addr:street":"Ceramstraat",
    "iso:country":"NL",
    "sg:address":"Ceramstraat 36",
    "sg:city":"Dordrecht",
    "sg:orig_category":"Onderhoud And Reparatie Kantoorapparatuur",
    "sg:phone":"+31 78 639 0249",
    "sg:postcode":"3312 SH",
    "sg:province":"South Holland",
    "wof:name":"Improtech",
    "wof:placetype":"venue"
},
  "geometry": {"coordinates":[4.688087,51.808784],"type":"Point"}
}