{
  "type": "Feature",
  "properties": {
    "addr:full":"Kreelsewg 94 Ede Gld Gelderland 6718 SK",
    "addr:housenumber":"94",
    "addr:street":"Kreelsewg;Gld Gelderland 6718",
    "iso:country":"NL",
    "sg:address":"Kreelsewg 94",
    "sg:city":"Ede Gld",
    "sg:orig_category":"Land- En Tuinbouw - Loonbedrijven",
    "sg:phone":"+31 318 613 465",
    "sg:postcode":"6718 SK",
    "sg:province":"Gelderland",
    "wof:name":"Prangsma, H P",
    "wof:placetype":"venue"
},
  "geometry": {"coordinates":[5.681747,52.048584],"type":"Point"}
}