{
  "type": "Feature",
  "properties": {
    "addr:full":"Meint Veningastraat 16 Hoogezand Groningen 9601 KG",
    "addr:housenumber":"16",
    "addr:postcode":"9601 kg",
    "addr:street":"Meint Veningastraat",
    "iso:country":"NL",
    "sg:address":"Meint Veningastraat 16",
    "sg:city":"Hoogezand",
    "sg:orig_category":"Meubelzaken, Woning- And Keukeninrichting",
    "sg:phone":"+31 598 396 739",
    "sg:postcode":"9601 KG",
    "sg:province":"Groningen",
    "wof:name":"Hollander Scholtens Trading Bv",
    "wof:placetype":"venue"
},
  "geometry": {"coordinates":[6.742414,53.162983],"type":"Point"}
}