{
  "type": "Feature",
  "properties": {
    "addr:full":"Breedstraat 53 Enkhuizen Noord-Holland 1601 KA",
    "addr:housenumber":"53",
    "addr:postcode":"1601 ka",
    "addr:street":"Breedstraat",
    "iso:country":"NL",
    "sg:address":"Breedstraat 53",
    "sg:city":"Enkhuizen",
    "sg:orig_category":"Overheidsdiensten",
    "sg:phone":"+31 228 360 100",
    "sg:postcode":"1601 KA",
    "sg:province":"Noord-Holland",
    "wof:name":"Gemeente Enkhuizen",
    "wof:placetype":"venue"
},
  "geometry": {"coordinates":[5.294798851,52.7040634155],"type":"Point"}
}