{
  "type": "Feature",
  "properties": {
    "addr:full":"Bergwegplnts 390 Noord Rotterdam South Holland 3037 SK",
    "addr:housenumber":"390",
    "addr:postcode":"3037 sk",
    "iso:country":"NL",
    "sg:address":"Bergwegplnts 390 Noord",
    "sg:city":"Rotterdam",
    "sg:orig_category":"Logopedisten",
    "sg:phone":"+31 10 443 6126",
    "sg:postcode":"3037 SK",
    "sg:province":"South Holland",
    "wof:name":"Logopedisch Centr Rotterdam",
    "wof:placetype":"venue"
},
  "geometry": {"coordinates":[4.47416,51.937038],"type":"Point"}
}