{
  "type": "Feature",
  "properties": {
    "addr:full":"Veilingweg 8 Zaltbommel Gelderland 5301 KM",
    "addr:housenumber":"8",
    "addr:postcode":"5301",
    "addr:street":"Veilingweg;Gelderland;Km",
    "iso:country":"NL",
    "sg:address":"Veilingweg 8",
    "sg:city":"Zaltbommel",
    "sg:orig_category":"Zuivelproducten And Spijsoli?n Gh",
    "sg:phone":"+31 418 516 515",
    "sg:postcode":"5301 KM",
    "sg:province":"Gelderland",
    "wof:name":"Dots Distribution Holland Bv",
    "wof:placetype":"venue"
},
  "geometry": {"coordinates":[5.265701,51.80204],"type":"Point"}
}