{
  "type": "Feature",
  "properties": {
    "addr:full":"K Waarder 19 Nieuwerbrug Zuid-Holland 2415 AS",
    "addr:housenumber":"19",
    "addr:postcode":"2415 as",
    "addr:street":"K Waarder",
    "iso:country":"NL",
    "sg:address":"K Waarder 19",
    "sg:city":"Nieuwerbrug",
    "sg:orig_category":"Webdesign Bureaus",
    "sg:phone":"+31 6 28128808",
    "sg:postcode":"2415 AS",
    "sg:province":"Zuid-Holland",
    "wof:name":"Spider Creations",
    "wof:placetype":"venue"
},
  "geometry": {"coordinates":[4.8175611496,52.0764846802],"type":"Point"}
}