{
  "type": "Feature",
  "properties": {
    "addr:full":"Zellingstr 3 Krimpen Ad Yssel South Holland 2921 LS",
    "addr:housenumber":"3;2921",
    "addr:postcode":"ls",
    "addr:street":"Zellingstr;Yssel",
    "iso:country":"NL",
    "sg:address":"Zellingstr 3",
    "sg:city":"Krimpen Ad Yssel",
    "sg:orig_category":"Jachten - Schilderwerken En Onderhoud",
    "sg:phone":"+31 180 514 602",
    "sg:postcode":"2921 LS",
    "sg:province":"South Holland",
    "wof:name":"Cupedo Bv",
    "wof:placetype":"venue"
},
  "geometry": {"coordinates":[4.587139,51.90765],"type":"Point"}
}