{
  "type": "Feature",
  "properties": {
    "addr:full":"Bleekstr 3 Oldenzaal Overijssel 7571 CK",
    "addr:housenumber":"3",
    "addr:postcode":"7571 ck",
    "addr:street":"Bleekstr",
    "iso:country":"NL",
    "sg:address":"Bleekstr 3",
    "sg:city":"Oldenzaal",
    "sg:orig_category":"Gehandicapteninformatie",
    "sg:phone":"+31 541 515 578",
    "sg:postcode":"7571 CK",
    "sg:province":"Overijssel",
    "wof:name":"Woonzorg Twente 3130, Sticht",
    "wof:placetype":"venue"
},
  "geometry": {"coordinates":[6.933453,52.312668],"type":"Point"}
}