{
  "type": "Feature",
  "properties": {
    "addr:full":"E P Seidelstr 2 Ens NL. 8307 BL",
    "addr:housenumber":"2",
    "addr:postcode":"8307 bl",
    "addr:street":"Seidelstr;Nl.",
    "iso:country":"NL",
    "sg:address":"E P Seidelstr 2",
    "sg:city":"Ens",
    "sg:orig_category":"Verenigingsgebouwen",
    "sg:phone":"+31 527 253 100",
    "sg:postcode":"8307 BL",
    "sg:province":"NL.",
    "wof:name":"Clubhuis Ens Sv",
    "wof:placetype":"venue"
},
  "geometry": {"coordinates":[5.827819,52.63887],"type":"Point"}
}