{
  "type": "Feature",
  "properties": {
    "iso:country":"NL",
    "sg:address":"Wostokpln 12",
    "sg:city":"Krommenie",
    "sg:orig_category":"Adviesbureaus Bouwkosten",
    "sg:phone":"+31 75 640 4149",
    "sg:postcode":"1562 TT",
    "sg:province":"Noord-Holland",
    "wof:name":"Alko Lok",
    "wof:placetype":"venue"
},
  "geometry": {"coordinates":[4.754,52.507442],"type":"Point"}
}