{
  "type": "Feature",
  "properties": {
    "iso:country":"NL",
    "sg:address":"Zomervaart 156",
    "sg:city":"Haarlem",
    "sg:orig_category":"Fietsen En Bromfietsen",
    "sg:phone":"+31 23 533 3044",
    "sg:postcode":"2033 DC",
    "sg:province":"North Holland",
    "sg:website":"http://www.schousfietsen.nl",
    "wof:name":"Schous Fietsen & Bromfietsen Bv",
    "wof:placetype":"venue"
},
  "geometry": {"coordinates":[4.650432,52.376427],"type":"Point"}
}