{
  "type": "Feature",
  "properties": {
    "addr:full":"Dorpswg 2 Schellinkhout Noord-Holland 1697 KA",
    "addr:housenumber":"2",
    "addr:postcode":"1697 ka",
    "addr:street":"Dorpswg",
    "iso:country":"NL",
    "sg:address":"Dorpswg 2",
    "sg:city":"Schellinkhout",
    "sg:classifiers":[
        {
            "category":"Autos & Motor Vehicles",
            "subcategory":"Automobile Sales",
            "type":"Retail Goods"
        }
    ],
    "sg:phone":"+31 229 501 220",
    "sg:postcode":"1697 KA",
    "sg:province":"Noord-Holland",
    "sg:tags":[
        "caravan",
        "stalling",
        "-"
    ],
    "wof:name":"Snoeck Caravans Stalling",
    "wof:placetype":"venue"
},
  "geometry": {"coordinates":[5.119706,52.649799],"type":"Point"}
}