{
  "type": "Feature",
  "properties": {
    "iso:country":"NL",
    "sg:address":"Troelstraln 45",
    "sg:city":"Zutphen",
    "sg:orig_category":"Sportverenigingen En Ontspannings- Verenigingen",
    "sg:phone":"+31 575 526 352",
    "sg:postcode":"7204 LC",
    "sg:province":"Gelderland",
    "wof:name":"Dobro Dosli Volksdansver",
    "wof:placetype":"venue"
},
  "geometry": {"coordinates":[6.210916,52.131458],"type":"Point"}
}