{
  "type": "Feature",
  "properties": {
    "addr:full":"Weteringstr 38 Valkenswaard Noord-Brabant 5555 KN",
    "addr:housenumber":"38",
    "addr:postcode":"5555 kn",
    "addr:street":"Weteringstr",
    "iso:country":"NL",
    "sg:address":"Weteringstr 38",
    "sg:city":"Valkenswaard",
    "sg:classifiers":[
        {
            "category":"Retail",
            "subcategory":"Auto Repair",
            "type":"Services"
        }
    ],
    "sg:phone":"+31 40 201 2737",
    "sg:postcode":"5555 KN",
    "sg:province":"Noord-Brabant",
    "sg:tags":[
        "garage"
    ],
    "wof:name":"Verweijen, Broer",
    "wof:placetype":"venue"
},
  "geometry": {"coordinates":[5.472889,51.351292],"type":"Point"}
}