{
  "type": "Feature",
  "properties": {
    "addr:full":"Edisonstr 20 Amersfoort Utrecht 3817 VN",
    "addr:housenumber":"20",
    "addr:postcode":"3817 vn",
    "addr:street":"Edisonstr",
    "iso:country":"NL",
    "sg:address":"Edisonstr 20",
    "sg:city":"Amersfoort",
    "sg:orig_category":"Bedrijfsopleidingen",
    "sg:phone":"+31 33 463 8590",
    "sg:postcode":"3817 VN",
    "sg:province":"Utrecht",
    "wof:name":"Hooijman, Klaar",
    "wof:placetype":"venue"
},
  "geometry": {"coordinates":[5.381624,52.142578],"type":"Point"}
}