{
  "type": "Feature",
  "properties": {
    "addr:full":"Oosthoutpln 11 Voorhout South Holland 2215 VM",
    "addr:housenumber":"11",
    "addr:postcode":"2215 vm",
    "addr:street":"Oosthoutpln",
    "iso:country":"NL",
    "sg:address":"Oosthoutpln 11",
    "sg:city":"Voorhout",
    "sg:orig_category":"Kappers",
    "sg:phone":"+31 252 219 079",
    "sg:postcode":"2215 VM",
    "sg:province":"South Holland",
    "wof:name":"Francine",
    "wof:placetype":"venue"
},
  "geometry": {"coordinates":[4.4916357994,52.221862793],"type":"Point"}
}