{
  "type": "Feature",
  "properties": {
    "addr:full":"Viltroos 3 Leusden Utrecht 3831 CH",
    "addr:housenumber":"3",
    "addr:postcode":"3831",
    "addr:street":"Viltroos",
    "iso:country":"NL",
    "sg:address":"Viltroos 3",
    "sg:city":"Leusden",
    "sg:orig_category":"Adviesbureaus Bedrijfsorganisatie",
    "sg:phone":"+31 33 432 4364",
    "sg:postcode":"3831 CH",
    "sg:province":"Utrecht",
    "sg:website":"http://www.q-as.nl",
    "wof:name":"Q-As",
    "wof:placetype":"venue"
},
  "geometry": {"coordinates":[5.430571,52.133274],"type":"Point"}
}