{
  "type": "Feature",
  "properties": {
    "addr:full":"Dr Verbeeksngl 16 Veghel Noord-Brabant 5461 AJ",
    "addr:housenumber":"16",
    "addr:postcode":"veghel;5461 aj",
    "iso:country":"NL",
    "sg:address":"Dr Verbeeksngl 16",
    "sg:city":"Veghel",
    "sg:orig_category":"Onderhoudswerken",
    "sg:phone":"+31 413 364 472",
    "sg:postcode":"5461 AJ",
    "sg:province":"Noord-Brabant",
    "wof:name":"Marklus",
    "wof:placetype":"venue"
},
  "geometry": {"coordinates":[5.536509,51.619545],"type":"Point"}
}