{
  "type": "Feature",
  "properties": {
    "iso:country":"NL",
    "sg:address":"Dr Verbeeksngl 16",
    "sg:city":"Veghel",
    "sg:orig_category":"Onderhoudswerken",
    "sg:phone":"+31 413 364 472",
    "sg:postcode":"5461 AJ",
    "sg:province":"Noord-Brabant",
    "wof:name":"Marklus",
    "wof:placetype":"venue"
},
  "geometry": {"coordinates":[5.536509,51.619545],"type":"Point"}
}