{
  "type": "Feature",
  "properties": {
    "addr:full":"Groeneweg 12 Gorssel Gelderland 7213 DP",
    "addr:housenumber":"12",
    "addr:postcode":"7213 dp",
    "addr:street":"Groeneweg;Gelderland",
    "iso:country":"NL",
    "sg:address":"Groeneweg 12",
    "sg:city":"Gorssel",
    "sg:orig_category":"Goederenvervoer Over De Weg",
    "sg:phone":"+31 575 493 442",
    "sg:postcode":"7213 DP",
    "sg:province":"Gelderland",
    "wof:name":"A.M. Van Opijnen",
    "wof:placetype":"venue"
},
  "geometry": {"coordinates":[6.195883,52.198326],"type":"Point"}
}