{
  "type": "Feature",
  "properties": {
    "addr:full":"Grindweg 58 Wolvega Friesland 8471 EL",
    "addr:housenumber":"58",
    "addr:postcode":"8471 el",
    "addr:street":"Grindweg",
    "iso:country":"NL",
    "sg:address":"Grindweg 58",
    "sg:city":"Wolvega",
    "sg:orig_category":"Kappers",
    "sg:phone":"+31 561 616 564",
    "sg:postcode":"8471 EL",
    "sg:province":"Friesland",
    "wof:name":"Kapsalon Haarstudio Diana L",
    "wof:placetype":"venue"
},
  "geometry": {"coordinates":[5.991133213,52.8750991821],"type":"Point"}
}