{
  "type": "Feature",
  "properties": {
    "addr:full":"Gotenburgwg 36 Groningen Groningen 9723 TM",
    "addr:housenumber":"36",
    "addr:postcode":"9723 tm",
    "addr:street":"Gotenburgwg",
    "iso:country":"NL",
    "sg:address":"Gotenburgwg 36",
    "sg:city":"Groningen",
    "sg:orig_category":"Verf En Lak - Fabrieken En Groothandel",
    "sg:phone":"+31 50 542 2822",
    "sg:postcode":"9723 TM",
    "sg:province":"Groningen",
    "wof:name":"Olyslager Bv",
    "wof:placetype":"venue"
},
  "geometry": {"coordinates":[6.606711,53.208359],"type":"Point"}
}