{
  "type": "Feature",
  "properties": {
    "addr:full":"Grootzand 54 Sneek Provincie Friesland 8601 AX",
    "addr:housenumber":"54",
    "addr:postcode":"8601 ax",
    "addr:street":"Grootzand;Provincie Friesland",
    "iso:country":"NL",
    "sg:address":"Grootzand 54",
    "sg:city":"Sneek",
    "sg:orig_category":"Meubelzaken, Woning- And Keukeninrichting",
    "sg:phone":"+31 515 425 815",
    "sg:postcode":"8601 AX",
    "sg:province":"Provincie Friesland",
    "wof:name":"Leenbakker",
    "wof:placetype":"venue"
},
  "geometry": {"coordinates":[5.660864,53.030434],"type":"Point"}
}