{
  "type": "Feature",
  "properties": {
    "addr:full":"Amsteldk 13 Amsterdam Noord-Holland 1074 HR",
    "addr:housenumber":"13",
    "addr:postcode":"1074 hr",
    "addr:street":"Amsteldk",
    "iso:country":"NL",
    "sg:address":"Amsteldk 13",
    "sg:city":"Amsterdam",
    "sg:orig_category":"Kinderopvang",
    "sg:phone":"+31 20 675 0069",
    "sg:postcode":"1074 HR",
    "sg:province":"Noord-Holland",
    "wof:name":"Blauwe Bever, De",
    "wof:placetype":"venue"
},
  "geometry": {"coordinates":[4.904026,52.357517],"type":"Point"}
}