{
  "type": "Feature",
  "properties": {
    "addr:full":"Op De Peperkamp 14 Wellerlooi Limburg 5856 AP",
    "addr:housenumber":"14",
    "addr:postcode":"5856 ap",
    "addr:street":"Op De Peperkamp",
    "iso:country":"NL",
    "sg:address":"Op De Peperkamp 14",
    "sg:city":"Wellerlooi",
    "sg:orig_category":"Lijsten - Fabrieken En Groothandel",
    "sg:phone":"+31 478 502 088",
    "sg:postcode":"5856 AP",
    "sg:province":"Limburg",
    "wof:name":"Kersbergen Agenturen",
    "wof:placetype":"venue"
},
  "geometry": {"coordinates":[6.138848,51.53619],"type":"Point"}
}