{
  "type": "Feature",
  "properties": {
    "addr:full":"Voorstr 21 Woerden Utrecht 3441 CC",
    "addr:housenumber":"21",
    "addr:postcode":"3441 cc",
    "addr:street":"Voorstr",
    "iso:country":"NL",
    "sg:address":"Voorstr 21",
    "sg:city":"Woerden",
    "sg:orig_category":"Herenkleding",
    "sg:phone":"+31 348 413 563",
    "sg:postcode":"3441 CC",
    "sg:province":"Utrecht",
    "wof:name":"Ton & Betsy",
    "wof:placetype":"venue"
},
  "geometry": {"coordinates":[4.887371,52.085117],"type":"Point"}
}