{
  "type": "Feature",
  "properties": {
    "iso:country":"NL",
    "sg:address":"Ampereln 3",
    "sg:city":"Ryswyk Zh",
    "sg:orig_category":"Boekbinderijen",
    "sg:phone":"+31 70 319 2226",
    "sg:postcode":"2289 CD",
    "sg:province":"Zuid-Holland",
    "wof:name":"Koningh Bv, De",
    "wof:placetype":"venue"
},
  "geometry": {"coordinates":[4.32436,52.037251],"type":"Point"}
}