{
  "type": "Feature",
  "properties": {
    "addr:full":"Zandberg 83 Ter Apelkanaal Groningen 9563 PL",
    "addr:housenumber":"83",
    "addr:postcode":"9563 pl",
    "addr:street":"Zandberg",
    "iso:country":"NL",
    "sg:address":"Zandberg 83",
    "sg:city":"Ter Apelkanaal",
    "sg:classifiers":[
        {
            "category":"Fast Food",
            "type":"Food & Drink"
        }
    ],
    "sg:phone":"+31 599 412 748",
    "sg:postcode":"9563 PL",
    "sg:province":"Groningen",
    "sg:tags":[
        "afhaal",
        "restaurant"
    ],
    "wof:name":"T Ol Stee",
    "wof:placetype":"venue"
},
  "geometry": {"coordinates":[7.031651,52.919605],"type":"Point"}
}