{
  "type": "Feature",
  "properties": {
    "addr:full":"Bisonspoor 1056 Maarssen Noord-Holland 3605 KG",
    "addr:housenumber":"1056",
    "addr:postcode":"3605 kg",
    "addr:street":"Bisonspoor",
    "iso:country":"NL",
    "sg:address":"Bisonspoor 1056",
    "sg:city":"Maarssen",
    "sg:classifiers":[
        {
            "category":"Shopping",
            "subcategory":"Clothing, Apparel, & Fashions",
            "type":"Retail Goods"
        }
    ],
    "sg:phone":"+31 346 551 444",
    "sg:postcode":"3605 KG",
    "sg:province":"Noord-Holland",
    "sg:tags":[
        "ondergoed",
        "lingerie"
    ],
    "wof:name":"Petit Bon",
    "wof:placetype":"venue"
},
  "geometry": {"coordinates":[5.030435,52.135517],"type":"Point"}
}