{
  "type": "Feature",
  "properties": {
    "addr:full":"Kerkstr 106 Oisterwyk Noord-Brabant 5061 EL",
    "addr:housenumber":"106",
    "addr:postcode":"5061 el",
    "addr:street":"Oisterwyk",
    "iso:country":"NL",
    "sg:address":"Kerkstr 106",
    "sg:city":"Oisterwyk",
    "sg:orig_category":"Verf En Lak",
    "sg:phone":"+31 13 528 2162",
    "sg:postcode":"5061 EL",
    "sg:province":"Noord-Brabant",
    "wof:name":"Wijst Bv, M Van Der",
    "wof:placetype":"venue"
},
  "geometry": {"coordinates":[5.185188,51.579033],"type":"Point"}
}