{
  "type": "Feature",
  "properties": {
    "iso:country":"NL",
    "sg:address":"Schenkeldijk 10",
    "sg:city":"'S Gravendeel",
    "sg:orig_category":"Algemene Werktuigbouw",
    "sg:phone":"+31 78 673 3637",
    "sg:postcode":"3295 EG",
    "sg:province":"Zuid-Holland",
    "wof:name":"Slijperij Snijders",
    "wof:placetype":"venue"
},
  "geometry": {"coordinates":[4.594035,51.747662],"type":"Point"}
}