{
  "type": "Feature",
  "properties": {
    "addr:full":"Grote Voort 96 Zwolle Overijssel 8041 BH",
    "addr:housenumber":"96",
    "addr:postcode":"8041 bh",
    "addr:street":"Grote Voort",
    "iso:country":"NL",
    "sg:address":"Grote Voort 96",
    "sg:city":"Zwolle",
    "sg:orig_category":"Meubelzaken, Woning- And Keukeninrichting",
    "sg:phone":"+31 38 422 0508",
    "sg:postcode":"8041 BH",
    "sg:province":"Overijssel",
    "wof:name":"Rofra Meubelen Zwolle Bv",
    "wof:placetype":"venue"
},
  "geometry": {"coordinates":[6.0657,52.510658],"type":"Point"}
}