{
  "type": "Feature",
  "properties": {
    "addr:full":"Dr M V Drielpln 1 Ochten Gelderland 4051 AX",
    "addr:housenumber":"1",
    "addr:postcode":"4051 ax",
    "addr:street":"Drielpln;Gelderland",
    "iso:country":"NL",
    "sg:address":"Dr M V Drielpln 1",
    "sg:city":"Ochten",
    "sg:orig_category":"Postkantoren",
    "sg:phone":"+31 344 641 230",
    "sg:postcode":"4051 AX",
    "sg:province":"Gelderland",
    "sg:website":"http://ww.postkantoor.nl",
    "wof:name":"Postkantoor",
    "wof:placetype":"venue"
},
  "geometry": {"coordinates":[5.56602,51.90736],"type":"Point"}
}