{
  "type": "Feature",
  "properties": {
    "iso:country":"NL",
    "sg:address":"Spijkerboorsteeg 27",
    "sg:city":"Deventer",
    "sg:orig_category":"Kappers",
    "sg:phone":"+31 570 670 909",
    "sg:postcode":"7411 JE",
    "sg:province":"NL.08",
    "wof:name":"Kim Hairlyne",
    "wof:placetype":"venue"
},
  "geometry": {"coordinates":[6.1596469879,52.2526626587],"type":"Point"}
}