{
  "type": "Feature",
  "properties": {
    "addr:full":"Langeraarseweg 86 Ter Aar South Holland 2461 CL",
    "addr:housenumber":"86",
    "addr:postcode":"2461",
    "addr:street":"Langeraarseweg",
    "iso:country":"NL",
    "sg:address":"Langeraarseweg 86",
    "sg:city":"Ter Aar",
    "sg:classifiers":[
        {
            "category":"Education",
            "subcategory":"Preschool",
            "type":"Public Place"
        }
    ],
    "sg:phone":"+31 172 602 548",
    "sg:postcode":"2461 CL",
    "sg:province":"South Holland",
    "sg:tags":[
        "kleuteronderwijs",
        "basis-"
    ],
    "wof:name":"Katholieke Basisschool Aeresteijn",
    "wof:placetype":"venue"
},
  "geometry": {"coordinates":[4.71726,52.194359],"type":"Point"}
}