{
  "type": "Feature",
  "properties": {
    "addr:full":"Stobberakplnts 6 Utrecht Utrecht 3544 TD",
    "addr:housenumber":"6",
    "addr:postcode":"3544 td",
    "addr:street":"Stobberakplnts",
    "iso:country":"NL",
    "sg:address":"Stobberakplnts 6",
    "sg:city":"Utrecht",
    "sg:orig_category":"Beeldende Kunstenaars",
    "sg:phone":"+31 30 289 7512",
    "sg:postcode":"3544 TD",
    "sg:province":"Utrecht",
    "wof:name":"Keijser, Y H",
    "wof:placetype":"venue"
},
  "geometry": {"coordinates":[5.060051,52.084126],"type":"Point"}
}