{
  "type": "Feature",
  "properties": {
    "iso:country":"NL",
    "sg:address":"Slenkweg 2",
    "sg:city":"Ressen",
    "sg:orig_category":"Marktonderzoekbureaus",
    "sg:phone":"+31 481 463 695",
    "sg:postcode":"6684 DK",
    "sg:province":"Gelderland",
    "wof:name":"Systemhandel Food En Nonfood Nederland B",
    "wof:placetype":"venue"
},
  "geometry": {"coordinates":[5.868641,51.888954],"type":"Point"}
}