{
  "type": "Feature",
  "properties": {
    "addr:full":"In De Betouwstr 15 Nymegen Gelderland 6511 GA",
    "addr:housenumber":"15",
    "addr:postcode":"6511 ga",
    "addr:street":"In;Nymegen Gelderland",
    "iso:country":"NL",
    "sg:address":"In De Betouwstr 15",
    "sg:city":"Nymegen",
    "sg:orig_category":"Woningbureaus",
    "sg:phone":"+31 24 348 1900",
    "sg:postcode":"6511 GA",
    "sg:province":"Gelderland",
    "sg:website":"http://www.rotsvast.nl",
    "wof:name":"Rots-Vast Groep",
    "wof:placetype":"venue"
},
  "geometry": {"coordinates":[-83.2229309082,32.6781311035],"type":"Point"}
}