{
  "type": "Feature",
  "properties": {
    "iso:country":"NL",
    "sg:address":"Dorpstraat 7",
    "sg:city":"Ulvenhout",
    "sg:classifiers":[
        {
            "category":"Fast Food",
            "type":"Food & Drink"
        }
    ],
    "sg:phone":"+31 76 561 2294",
    "sg:postcode":"4851 CJ",
    "sg:province":"Noord-Brabant",
    "sg:tags":[
        "afhaal",
        "restaurant"
    ],
    "wof:name":"Cafetaria Bert Paulussen",
    "wof:placetype":"venue"
},
  "geometry": {"coordinates":[4.795491,51.553883],"type":"Point"}
}