{
  "type": "Feature",
  "properties": {
    "addr:full":"Kempermanstr 1 Ulft Gelderland 7071 XL",
    "addr:housenumber":"1",
    "addr:postcode":"7071 xl",
    "addr:street":"Kempermanstr;Gelderland",
    "iso:country":"NL",
    "sg:address":"Kempermanstr 1",
    "sg:city":"Ulft",
    "sg:orig_category":"Bejaarden - Verzorgingstehuizen",
    "sg:phone":"+31 315 681 849",
    "sg:postcode":"7071 XL",
    "sg:province":"Gelderland",
    "wof:name":"Debbeshoek",
    "wof:placetype":"venue"
},
  "geometry": {"coordinates":[6.377379,51.891949],"type":"Point"}
}