{
  "type": "Feature",
  "properties": {
    "addr:full":"Drebbelstr 197 S Gravenhage Zuid-Holland 2522 DA",
    "addr:housenumber":"197;gravenhage",
    "addr:postcode":"2522 da",
    "addr:street":"S",
    "iso:country":"NL",
    "sg:address":"Drebbelstr 197",
    "sg:city":"S Gravenhage",
    "sg:orig_category":"Evenementenverzorging",
    "sg:phone":"+31 6 41272663",
    "sg:postcode":"2522 DA",
    "sg:province":"Zuid-Holland",
    "wof:name":"Dhlb",
    "wof:placetype":"venue"
},
  "geometry": {"coordinates":[4.32729,52.060848],"type":"Point"}
}