{
  "type": "Feature",
  "properties": {
    "iso:country":"NL",
    "sg:address":"Hoofdstr 143",
    "sg:city":"Sassenheim",
    "sg:orig_category":"Accountants - Administratie- Consulenten En -Kantoren",
    "sg:phone":"+31 252 220 540",
    "sg:postcode":"2171 BA",
    "sg:province":"South Holland",
    "wof:name":"Lange Bv, De",
    "wof:placetype":"venue"
},
  "geometry": {"coordinates":[4.516783,52.222923],"type":"Point"}
}