{
  "type": "Feature",
  "properties": {
    "addr:full":"Catharinaplaats 10 Arnhem Gelderland 6811 BS",
    "addr:housenumber":"10",
    "addr:postcode":"6811 bs",
    "addr:street":"Catharinaplaats",
    "iso:country":"NL",
    "sg:address":"Catharinaplaats 10",
    "sg:city":"Arnhem",
    "sg:orig_category":"Verenigingen En Stichtingen",
    "sg:phone":"+31 26 351 2221",
    "sg:postcode":"6811 BS",
    "sg:province":"Gelderland",
    "wof:name":"Basta, Sticht",
    "wof:placetype":"venue"
},
  "geometry": {"coordinates":[5.912266,51.980751],"type":"Point"}
}