{
  "type": "Feature",
  "properties": {
    "addr:full":"Paramariboweg 21 Apeldoorn Gelderland 7333 PA",
    "addr:housenumber":"21",
    "addr:postcode":"7333",
    "addr:street":"Paramariboweg;Gelderland",
    "iso:country":"NL",
    "sg:address":"Paramariboweg 21",
    "sg:city":"Apeldoorn",
    "sg:orig_category":"Pleziervaartuigen And Reparatie",
    "sg:phone":"+31 55 542 1102",
    "sg:postcode":"7333 PA",
    "sg:province":"Gelderland",
    "wof:name":"Platbodem - Jachtbouw Averink/Koot",
    "wof:placetype":"venue"
},
  "geometry": {"coordinates":[5.972175,52.174629],"type":"Point"}
}