{
  "type": "Feature",
  "properties": {
    "addr:full":"Forel 2E Hellevoetsluis Zuid-Holland 3225 PA",
    "addr:housenumber":"2e",
    "addr:postcode":"3225 pa",
    "addr:street":"Forel",
    "iso:country":"NL",
    "sg:address":"Forel 2E",
    "sg:city":"Hellevoetsluis",
    "sg:orig_category":"Postkantoren",
    "sg:phone":"+31 181 316 855",
    "sg:postcode":"3225 PA",
    "sg:province":"Zuid-Holland",
    "sg:website":"http://www.postkantoor.nl",
    "wof:name":"Postkantoor",
    "wof:placetype":"venue"
},
  "geometry": {"coordinates":[4.165527,51.832581],"type":"Point"}
}