{
  "type": "Feature",
  "properties": {
    "addr:full":"Landstr 48 Aardenburg Zeeland 4527 CX",
    "addr:housenumber":"48",
    "addr:postcode":"4527 cx",
    "addr:street":"Landstr",
    "iso:country":"NL",
    "sg:address":"Landstr 48",
    "sg:city":"Aardenburg",
    "sg:orig_category":"Etalageverzorging",
    "sg:phone":"+31 117 492 012",
    "sg:postcode":"4527 CX",
    "sg:province":"Zeeland",
    "wof:name":"Pieters",
    "wof:placetype":"venue"
},
  "geometry": {"coordinates":[3.451255,51.271523],"type":"Point"}
}