{
  "type": "Feature",
  "properties": {
    "iso:country":"NL",
    "sg:address":"F H G Van Itersonlaan 29",
    "sg:city":"Oostvoorne",
    "sg:orig_category":"Public Relationbureaus",
    "sg:phone":"+31 181 484 510",
    "sg:postcode":"3233 EH",
    "sg:province":"Zuid-Holland",
    "wof:name":"Gerda Baeten, Communicatie",
    "wof:placetype":"venue"
},
  "geometry": {"coordinates":[4.091285,51.911713],"type":"Point"}
}