{
  "type": "Feature",
  "properties": {
    "addr:full":"Singel 150 Dordrecht Zuid-Holland 3311 PG",
    "addr:housenumber":"150",
    "addr:postcode":"3311 pg",
    "addr:street":"Singel",
    "iso:country":"NL",
    "sg:address":"Singel 150",
    "sg:city":"Dordrecht",
    "sg:orig_category":"Orthopedagogen",
    "sg:phone":"+31 78 631 2873",
    "sg:postcode":"3311 PG",
    "sg:province":"Zuid-Holland",
    "wof:name":"Baks, Mevr Drs S M A",
    "wof:placetype":"venue"
},
  "geometry": {"coordinates":[4.6721401215,51.8090171814],"type":"Point"}
}