{
  "type": "Feature",
  "properties": {
    "addr:full":"Lossersestr 50 Enschede Overijssel 7525 PG",
    "addr:housenumber":"50",
    "addr:postcode":"7525 pg",
    "addr:street":"Lossersestr",
    "iso:country":"NL",
    "sg:address":"Lossersestr 50",
    "sg:city":"Enschede",
    "sg:orig_category":"Vertalers",
    "sg:phone":"+31 53 433 3648",
    "sg:postcode":"7525 PG",
    "sg:province":"Overijssel",
    "wof:name":"Voortman, Drs H H M",
    "wof:placetype":"venue"
},
  "geometry": {"coordinates":[6.920474,52.24247],"type":"Point"}
}