{
  "type": "Feature",
  "properties": {
    "addr:full":"Willibrordusln 58 Waalre Noord-Brabant 5581 GG",
    "addr:housenumber":"58",
    "addr:postcode":"5581 gg",
    "addr:street":"Willibrordusln",
    "iso:country":"NL",
    "sg:address":"Willibrordusln 58",
    "sg:city":"Waalre",
    "sg:orig_category":"Video - Faciliteiten En Producties",
    "sg:phone":"+31 40 222 3989",
    "sg:postcode":"5581 GG",
    "sg:province":"Noord-Brabant",
    "wof:name":"Moustache",
    "wof:placetype":"venue"
},
  "geometry": {"coordinates":[5.450854,51.388313],"type":"Point"}
}