{
  "type": "Feature",
  "properties": {
    "addr:full":"Rouaanstr 27 Groningen Groningen 9723 CC",
    "addr:housenumber":"27",
    "addr:postcode":"9723 cc",
    "addr:street":"Rouaanstr",
    "iso:country":"NL",
    "sg:address":"Rouaanstr 27",
    "sg:city":"Groningen",
    "sg:orig_category":"Onderzoekbureaus",
    "sg:phone":"+31 50 369 4694",
    "sg:postcode":"9723 CC",
    "sg:province":"Groningen",
    "sg:website":"http://www.tno.nl",
    "wof:name":"Tno",
    "wof:placetype":"venue"
},
  "geometry": {"coordinates":[6.606198,53.197704],"type":"Point"}
}