{
  "type": "Feature",
  "properties": {
    "addr:full":"Katerstraat 40 Zundert Noord-Brabant 4881 AS",
    "addr:housenumber":"40",
    "addr:postcode":"4881 as",
    "addr:street":"Katerstraat",
    "iso:country":"NL",
    "sg:address":"Katerstraat 40",
    "sg:city":"Zundert",
    "sg:orig_category":"Apothekers",
    "sg:phone":"+31 76 597 2790",
    "sg:postcode":"4881 AS",
    "sg:province":"Noord-Brabant",
    "wof:name":"Apotheek Van Gogh",
    "wof:placetype":"venue"
},
  "geometry": {"coordinates":[4.661124,51.474396],"type":"Point"}
}