{
  "type": "Feature",
  "properties": {
    "addr:full":"Heemskerckstr 8 Zwolle Overijssel 8023 VK",
    "addr:housenumber":"8",
    "addr:postcode":"8023 vk",
    "addr:street":"Heemskerckstr",
    "iso:country":"NL",
    "sg:address":"Heemskerckstr 8",
    "sg:city":"Zwolle",
    "sg:orig_category":"Parketvloeren",
    "sg:phone":"+31 38 454 1882",
    "sg:postcode":"8023 VK",
    "sg:province":"Overijssel",
    "wof:name":"Amri",
    "wof:placetype":"venue"
},
  "geometry": {"coordinates":[6.111039,52.512093],"type":"Point"}
}