{
  "type": "Feature",
  "properties": {
    "iso:country":"NL",
    "sg:address":"De Ikkers 2",
    "sg:city":"Idskenhuizen",
    "sg:orig_category":"Verenigingsgebouwen",
    "sg:phone":"+31 513 431 288",
    "sg:postcode":"8523 NW",
    "sg:province":"Friesland",
    "wof:name":"Stj\u00ealp, De",
    "wof:placetype":"venue"
},
  "geometry": {"coordinates":[5.712802,52.928791],"type":"Point"}
}