{
  "type": "Feature",
  "properties": {
    "iso:country":"NL",
    "sg:address":"Dijk 48",
    "sg:city":"Enkhuizen",
    "sg:orig_category":"Visspeciaalzaken",
    "sg:phone":"+31 228 317 809",
    "sg:postcode":"1601 GJ",
    "sg:province":"Noord-Holland",
    "wof:name":"Theo Schilder Vishandel Enkhuizen",
    "wof:placetype":"venue"
},
  "geometry": {"coordinates":[5.292242,52.702019],"type":"Point"}
}