{
  "type": "Feature",
  "properties": {
    "addr:full":"Dokweg 6 Ijmuiden California 1976 CA",
    "addr:housenumber":"6",
    "addr:postcode":"1976 ca",
    "addr:street":"Dokweg",
    "iso:country":"NL",
    "sg:address":"Dokweg 6",
    "sg:city":"Ijmuiden",
    "sg:orig_category":"Meubelzaken, Woning- And Keukeninrichting",
    "sg:phone":"+31 255 515 378",
    "sg:postcode":"1976 CA",
    "sg:province":"California",
    "wof:name":"Matrassenfabriek",
    "wof:placetype":"venue"
},
  "geometry": {"coordinates":[-119.270203,37.271832],"type":"Point"}
}