{
  "type": "Feature",
  "properties": {
    "addr:full":"Gitaarerf 15 Amersfoort Utrecht 3822 DX",
    "addr:housenumber":"15",
    "addr:postcode":"3822 dx",
    "addr:street":"Gitaarerf",
    "iso:country":"NL",
    "sg:address":"Gitaarerf 15",
    "sg:city":"Amersfoort",
    "sg:orig_category":"Adviesbureaus Marketing",
    "sg:phone":"+31 33 453 1777",
    "sg:postcode":"3822 DX",
    "sg:province":"Utrecht",
    "wof:name":"Wilmarco",
    "wof:placetype":"venue"
},
  "geometry": {"coordinates":[5.404237,52.182842],"type":"Point"}
}