{
  "type": "Feature",
  "properties": {
    "iso:country":"NL",
    "sg:address":"C.J.A. Koelemanstraat 25",
    "sg:city":"Ter Aar",
    "sg:orig_category":"Verzekeringen",
    "sg:phone":"+31 172 604 143",
    "sg:postcode":"2461 WD",
    "sg:province":"Zuid-Holland",
    "wof:name":"Adviesburo E.P. Van Egmond",
    "wof:placetype":"venue"
},
  "geometry": {"coordinates":[4.70642,52.167164],"type":"Point"}
}