{
  "type": "Feature",
  "properties": {
    "addr:full":"Selderust 14 Amstelveen North Holland 1181 MJ",
    "addr:housenumber":"14",
    "addr:postcode":"1181 mj",
    "addr:street":"Selderust",
    "iso:country":"NL",
    "sg:address":"Selderust 14",
    "sg:city":"Amstelveen",
    "sg:orig_category":"Artsen - Huisartsen",
    "sg:phone":"+31 20 645 3535",
    "sg:postcode":"1181 MJ",
    "sg:province":"North Holland",
    "wof:name":"Weijel, J",
    "wof:placetype":"venue"
},
  "geometry": {"coordinates":[4.866698,52.312412],"type":"Point"}
}