{
  "type": "Feature",
  "properties": {
    "iso:country":"NL",
    "sg:address":"Spoorstraat 2",
    "sg:city":"Baarn",
    "sg:orig_category":"Juridische Dienstverlening",
    "sg:phone":"+31 35 543 1776",
    "sg:postcode":"3743 EG",
    "sg:province":"Utrecht",
    "wof:name":"Ipd Consulting Bv",
    "wof:placetype":"venue"
},
  "geometry": {"coordinates":[5.286938,52.211773],"type":"Point"}
}