{
  "type": "Feature",
  "properties": {
    "iso:country":"NL",
    "sg:address":"Herenstr 66-68",
    "sg:city":"Voorhout",
    "sg:orig_category":"Bloemen En Planten",
    "sg:phone":"+31 252 230 291",
    "sg:postcode":"2215 KJ",
    "sg:province":"South Holland",
    "wof:name":"Gevi",
    "wof:placetype":"venue"
},
  "geometry": {"coordinates":[4.479961,52.220398],"type":"Point"}
}