{
  "type": "Feature",
  "properties": {
    "addr:full":"Walramstr 18A Sittard Limburg 6131 BM",
    "addr:housenumber":"18a",
    "addr:postcode":"6131 bm",
    "addr:street":"Walramstr",
    "iso:country":"NL",
    "sg:address":"Walramstr 18A",
    "sg:city":"Sittard",
    "sg:orig_category":"Meubelen",
    "sg:phone":"+31 46 458 3322",
    "sg:postcode":"6131 BM",
    "sg:province":"Limburg",
    "wof:name":"Mondena",
    "wof:placetype":"venue"
},
  "geometry": {"coordinates":[5.864575,51.000706],"type":"Point"}
}