{
  "type": "Feature",
  "properties": {
    "addr:full":"Damsterdiep 291 Groningen Groningen 9713 EG",
    "addr:housenumber":"291",
    "addr:postcode":"9713 eg",
    "addr:street":"Damsterdiep",
    "iso:country":"NL",
    "sg:address":"Damsterdiep 291",
    "sg:city":"Groningen",
    "sg:orig_category":"Sportverenigingen En Ontspannings- Verenigingen",
    "sg:phone":"+31 50 313 6026",
    "sg:postcode":"9713 EG",
    "sg:province":"Groningen",
    "wof:name":"Drumfanfare Avanti",
    "wof:placetype":"venue"
},
  "geometry": {"coordinates":[6.589543,53.222324],"type":"Point"}
}