{
  "type": "Feature",
  "properties": {
    "addr:full":"Moerseweg 8 Hooge Zwaluwe North Brabant 4927 RK",
    "addr:housenumber":"8",
    "addr:postcode":"4927 rk",
    "addr:street":"Moerseweg",
    "iso:country":"NL",
    "sg:address":"Moerseweg 8",
    "sg:city":"Hooge Zwaluwe",
    "sg:orig_category":"Autokeuringen",
    "sg:phone":"+31 168 482 331",
    "sg:postcode":"4927 RK",
    "sg:province":"North Brabant",
    "wof:name":"J.D. Den Dunnen Bv",
    "wof:placetype":"venue"
},
  "geometry": {"coordinates":[4.75303,51.688705],"type":"Point"}
}