{
  "type": "Feature",
  "properties": {
    "addr:full":"Bernhardstr 25 Delden Overijssel 7491 EA",
    "addr:housenumber":"25",
    "addr:postcode":"7491 ea",
    "addr:street":"Bernhardstr",
    "iso:country":"NL",
    "sg:address":"Bernhardstr 25",
    "sg:city":"Delden",
    "sg:orig_category":"Peuterspeelzalen",
    "sg:phone":"+31 74 376 5317",
    "sg:postcode":"7491 EA",
    "sg:province":"Overijssel",
    "wof:name":"Kletskevertjes, De",
    "wof:placetype":"venue"
},
  "geometry": {"coordinates":[6.707624,52.256599],"type":"Point"}
}