{
  "type": "Feature",
  "properties": {
    "addr:full":"Hoflanderweg 45 Beverwijk North Holland 1947 ZB",
    "addr:housenumber":"45",
    "addr:postcode":"1947 zb",
    "addr:street":"Hoflanderweg",
    "iso:country":"NL",
    "sg:address":"Hoflanderweg 45",
    "sg:city":"Beverwijk",
    "sg:classifiers":[
        {
            "category":"Education",
            "subcategory":"Preschool",
            "type":"Public Place"
        }
    ],
    "sg:phone":"+31 251 223 840",
    "sg:postcode":"1947 ZB",
    "sg:province":"North Holland",
    "sg:tags":[
        "kleuteronderwijs",
        "basis-"
    ],
    "wof:name":"Katholieke Basisschool De Sleutelbloem",
    "wof:placetype":"venue"
},
  "geometry": {"coordinates":[4.664021,52.489174],"type":"Point"}
}