{
  "type": "Feature",
  "properties": {
    "iso:country":"NL",
    "sg:address":"Helftheuvelpassage 45",
    "sg:city":"'S Hertogenbosch",
    "sg:orig_category":"Banken And Kredietinstellingen",
    "sg:phone":"+31 73 623 1530",
    "sg:postcode":"5224 AA",
    "sg:province":"Noord-Brabant",
    "wof:name":"Postkantoor",
    "wof:placetype":"venue"
},
  "geometry": {"coordinates":[5.267775,51.696236],"type":"Point"}
}