{
  "type": "Feature",
  "properties": {
    "addr:full":"Lange Smeestraat 26 Utrecht Utrecht 3511 PX",
    "addr:housenumber":"26",
    "addr:postcode":"3511 px",
    "addr:street":"Lange Smeestraat",
    "iso:country":"NL",
    "sg:address":"Lange Smeestraat 26",
    "sg:city":"Utrecht",
    "sg:classifiers":[
        {
            "category":"Fast Food",
            "type":"Food & Drink"
        }
    ],
    "sg:phone":"+31 30 231 3085",
    "sg:postcode":"3511 PX",
    "sg:province":"Utrecht",
    "sg:tags":[
        "afhaal",
        "restaurant"
    ],
    "wof:name":"Cafetaria Utrecht",
    "wof:placetype":"venue"
},
  "geometry": {"coordinates":[5.120982,52.085857],"type":"Point"}
}