{
  "type": "Feature",
  "properties": {
    "addr:full":"Wikelerdijk 13 Balk Provincie Friesland 8561 BD",
    "addr:housenumber":"13",
    "addr:postcode":"8561 bd",
    "addr:street":"Wikelerdijk;Provincie Friesland",
    "iso:country":"NL",
    "sg:address":"Wikelerdijk 13",
    "sg:city":"Balk",
    "sg:orig_category":"Pleziervaartuigen And Reparatie",
    "sg:phone":"+31 514 603 016",
    "sg:postcode":"8561 BD",
    "sg:province":"Provincie Friesland",
    "wof:name":"Scheepstimmerbedrijf J. Wilmink",
    "wof:placetype":"venue"
},
  "geometry": {"coordinates":[5.590722,52.896225],"type":"Point"}
}