{
  "type": "Feature",
  "properties": {
    "addr:full":"Tingietersdonk 10 Apeldoorn Gelderland 7326 NA",
    "addr:housenumber":"10",
    "addr:postcode":"7326 na",
    "addr:street":"Tingietersdonk;Gelderland",
    "iso:country":"NL",
    "sg:address":"Tingietersdonk 10",
    "sg:city":"Apeldoorn",
    "sg:orig_category":"Technische Studies And Onderzoek",
    "sg:phone":"+31 55 542 2074",
    "sg:postcode":"7326 NA",
    "sg:province":"Gelderland",
    "wof:name":"S.F. Tammeling",
    "wof:placetype":"venue"
},
  "geometry": {"coordinates":[6.010776,52.197487],"type":"Point"}
}