{
  "type": "Feature",
  "properties": {
    "addr:full":"Tongelresestr 375 Eindhoven North Brabant 5642 NC",
    "addr:housenumber":"375",
    "addr:postcode":"5642 nc",
    "iso:country":"NL",
    "sg:address":"Tongelresestr 375",
    "sg:city":"Eindhoven",
    "sg:orig_category":"Wijnkoperijen En -Groothandel",
    "sg:phone":"+31 40 290 8389",
    "sg:postcode":"5642 NC",
    "sg:province":"North Brabant",
    "sg:website":"http://www.wilri-degit.nl",
    "wof:name":"Git Bv W De Drankengroot- En Kleinhandel",
    "wof:placetype":"venue"
},
  "geometry": {"coordinates":[5.5103979111,51.4427833557],"type":"Point"}
}