{
  "type": "Feature",
  "properties": {
    "iso:country":"NL",
    "sg:address":"Staringln 17E",
    "sg:city":"Waddinxveen",
    "sg:orig_category":"Pruiken",
    "sg:phone":"+31 182 614 543",
    "sg:postcode":"2741 GC",
    "sg:province":"Zuid-Holland",
    "wof:name":"Haarplus Boetiek",
    "wof:placetype":"venue"
},
  "geometry": {"coordinates":[4.659366,52.056332],"type":"Point"}
}