{
  "type": "Feature",
  "properties": {
    "addr:full":"Industriestr 12 Kerkdriel Gelderland 5331 HW",
    "addr:housenumber":"12",
    "addr:postcode":"5331 hw",
    "addr:street":"Industriestr;Gelderland",
    "iso:country":"NL",
    "sg:address":"Industriestr 12",
    "sg:city":"Kerkdriel",
    "sg:orig_category":"Kaasgroothandel",
    "sg:phone":"+31 418 633 101",
    "sg:postcode":"5331 HW",
    "sg:province":"Gelderland",
    "wof:name":"Remijn Vof",
    "wof:placetype":"venue"
},
  "geometry": {"coordinates":[5.3280668259,51.771648407],"type":"Point"}
}