{
  "type": "Feature",
  "properties": {
    "addr:full":"Bordeauxln 109 Eindhoven Noord-Brabant 5627 GT",
    "addr:housenumber":"109",
    "addr:postcode":"5627 gt",
    "iso:country":"NL",
    "sg:address":"Bordeauxln 109",
    "sg:city":"Eindhoven",
    "sg:orig_category":"Fotografie Reclame En Mode",
    "sg:phone":"+31 40 242 6162",
    "sg:postcode":"5627 GT",
    "sg:province":"Noord-Brabant",
    "wof:name":"Cornelissen, Ger",
    "wof:placetype":"venue"
},
  "geometry": {"coordinates":[5.44142,51.484638],"type":"Point"}
}