{
  "type": "Feature",
  "properties": {
    "addr:full":"Utrechtsewg 287 Doorwerth Gelderland 6865 CJ",
    "addr:housenumber":"287",
    "addr:postcode":"6865 cj",
    "addr:street":"Gelderland",
    "iso:country":"NL",
    "sg:address":"Utrechtsewg 287",
    "sg:city":"Doorwerth",
    "sg:orig_category":"Adviesbureaus Marketing",
    "sg:phone":"+31 6 53357580",
    "sg:postcode":"6865 CJ",
    "sg:province":"Gelderland",
    "sg:website":"http://www.exquo.com",
    "wof:name":"Exquo Consultancy Bv",
    "wof:placetype":"venue"
},
  "geometry": {"coordinates":[5.809544,51.987968],"type":"Point"}
}