{
  "type": "Feature",
  "properties": {
    "addr:full":"Papiermolen 14 Capelle A/D Ijssel Zuid-Holland 2906 RB",
    "addr:housenumber":"14;a / d",
    "addr:postcode":"2906 rb",
    "addr:street":"Papiermolen",
    "iso:country":"NL",
    "sg:address":"Papiermolen 14",
    "sg:city":"Capelle A/D Ijssel",
    "sg:orig_category":"Architecten",
    "sg:phone":"+31 10 451 4473",
    "sg:postcode":"2906 RB",
    "sg:province":"Zuid-Holland",
    "wof:name":"G.R. Consultancy",
    "wof:placetype":"venue"
},
  "geometry": {"coordinates":[4.566841,51.939182],"type":"Point"}
}