{
  "type": "Feature",
  "properties": {
    "addr:full":"Laarderwg 30 Bussum Noord-Holland 1402 BJ",
    "addr:housenumber":"30",
    "addr:postcode":"1402 bj",
    "addr:street":"Laarderwg",
    "iso:country":"NL",
    "sg:address":"Laarderwg 30",
    "sg:city":"Bussum",
    "sg:classifiers":[
        {
            "category":"Food & Beverages",
            "subcategory":"Bakery",
            "type":"Retail Goods"
        }
    ],
    "sg:phone":"+31 35 691 4501",
    "sg:postcode":"1402 BJ",
    "sg:province":"Noord-Holland",
    "sg:tags":[
        "brood",
        "en",
        "banket"
    ],
    "wof:name":"Breemen, Van",
    "wof:placetype":"venue"
},
  "geometry": {"coordinates":[5.165619,52.271133],"type":"Point"}
}