{
  "type": "Feature",
  "properties": {
    "addr:full":"Merelerf 12 Numansdorp South Holland 3281 JM",
    "addr:housenumber":"12",
    "addr:postcode":"3281 jm",
    "addr:street":"Merelerf",
    "iso:country":"NL",
    "sg:address":"Merelerf 12",
    "sg:city":"Numansdorp",
    "sg:orig_category":"Begrafenisverzorging",
    "sg:phone":"+31 186 651 581",
    "sg:postcode":"3281 JM",
    "sg:province":"South Holland",
    "wof:name":"Knape, L C",
    "wof:placetype":"venue"
},
  "geometry": {"coordinates":[4.440633,51.728195],"type":"Point"}
}