{
  "type": "Feature",
  "properties": {
    "iso:country":"NL",
    "sg:address":"Boekelerweg 3",
    "sg:city":"Zuidschermer",
    "sg:classifiers":[
        {
            "category":"Travel",
            "subcategory":"Hotels & Motels",
            "type":"Entertainment"
        }
    ],
    "sg:phone":"+31 72 504 4268",
    "sg:postcode":"1847 LJ",
    "sg:province":"North Holland",
    "wof:name":"Pension Prins Hendrik Th Vd Heijden",
    "wof:placetype":"venue"
},
  "geometry": {"coordinates":[4.785402,52.598362],"type":"Point"}
}