{
  "type": "Feature",
  "properties": {
    "addr:full":"Hoefbladln 28 Arnhem Gelderland 6841 CD",
    "addr:housenumber":"28",
    "addr:postcode":"6841 cd",
    "addr:street":"Hoefbladln",
    "iso:country":"NL",
    "sg:address":"Hoefbladln 28",
    "sg:city":"Arnhem",
    "sg:orig_category":"Gehandicapten - Hulpmiddelen",
    "sg:phone":"+31 26 388 3598",
    "sg:postcode":"6841 CD",
    "sg:province":"Gelderland",
    "wof:name":"Innocare Bv",
    "wof:placetype":"venue"
},
  "geometry": {"coordinates":[5.902406,51.968914],"type":"Point"}
}