{
  "type": "Feature",
  "properties": {
    "iso:country":"NL",
    "sg:address":"Laagstraat 67",
    "sg:city":"Rijen",
    "sg:orig_category":"Wasserettes And Stomerijen",
    "sg:phone":"+31 161 224 101",
    "sg:postcode":"5121 ZE",
    "sg:province":"North Brabant",
    "wof:name":"A. Van Loon",
    "wof:placetype":"venue"
},
  "geometry": {"coordinates":[4.9250650406,51.5891838074],"type":"Point"}
}