{
  "type": "Feature",
  "properties": {
    "iso:country":"NL",
    "sg:address":"Oostzeedk Beneden 33B",
    "sg:city":"Rotterdam",
    "sg:orig_category":"Galeries",
    "sg:phone":"+31 10 213 0309",
    "sg:postcode":"3062 VK",
    "sg:province":"Zuid-Holland",
    "sg:website":"http://www.honingen.com",
    "wof:name":"Honingen",
    "wof:placetype":"venue"
},
  "geometry": {"coordinates":[4.5121,51.920555],"type":"Point"}
}