{
  "type": "Feature",
  "properties": {
    "iso:country":"NL",
    "sg:address":"Hollands Diepstr 79",
    "sg:city":"Lelystad",
    "sg:orig_category":"Evenementenverzorging",
    "sg:phone":"+31 320 218 149",
    "sg:postcode":"8226 EG",
    "sg:province":"NL.",
    "wof:name":"Skatesch Ned",
    "wof:placetype":"venue"
},
  "geometry": {"coordinates":[5.484195,52.497074],"type":"Point"}
}