{
  "type": "Feature",
  "properties": {
    "addr:full":"V T Vd Koogwg 8 Oosterbeek Gelderland 6862 EC",
    "addr:housenumber":"8",
    "addr:postcode":"6862 ec",
    "addr:street":"Gelderland",
    "iso:country":"NL",
    "sg:address":"V T Vd Koogwg 8",
    "sg:city":"Oosterbeek",
    "sg:orig_category":"Bloemen En Planten",
    "sg:phone":"+31 26 339 0520",
    "sg:postcode":"6862 EC",
    "sg:province":"Gelderland",
    "sg:website":"http://www.florafaunabloemen.nl",
    "wof:name":"Flora & Fauna",
    "wof:placetype":"venue"
},
  "geometry": {"coordinates":[5.84094,51.987579],"type":"Point"}
}