{
  "type": "Feature",
  "properties": {
    "iso:country":"NL",
    "sg:address":"Doelstr 69",
    "sg:city":"Krabbendyke",
    "sg:orig_category":"Mensendieck - Oefentherapeuten",
    "sg:phone":"+31 113 504 775",
    "sg:postcode":"4413 BG",
    "sg:province":"Zeeland",
    "wof:name":"Reijns, Inge",
    "wof:placetype":"venue"
},
  "geometry": {"coordinates":[4.117964,51.432323],"type":"Point"}
}