{
  "type": "Feature",
  "properties": {
    "addr:full":"Groenhof 124 Almere NL. 1352 AL",
    "addr:housenumber":"124",
    "addr:postcode":"1352",
    "addr:street":"Groenhof;Nl.",
    "iso:country":"NL",
    "sg:address":"Groenhof 124",
    "sg:city":"Almere",
    "sg:orig_category":"Marktonderzoekbureaus",
    "sg:phone":"+31 36 534 9877",
    "sg:postcode":"1352 AL",
    "sg:province":"NL.",
    "wof:name":"Ics",
    "wof:placetype":"venue"
},
  "geometry": {"coordinates":[5.221253,52.342255],"type":"Point"}
}