{
  "type": "Feature",
  "properties": {
    "iso:country":"NL",
    "sg:address":"2E Dorpsstr 36",
    "sg:city":"Zeist",
    "sg:orig_category":"Wasmachines En Wasdrogers - Onderhoud En Reparatie",
    "sg:phone":"+31 30 691 7405",
    "sg:postcode":"3701 AB",
    "sg:province":"Utrecht",
    "wof:name":"Co Wasmachine-Onderdelenservice",
    "wof:placetype":"venue"
},
  "geometry": {"coordinates":[5.23914814,52.08152771],"type":"Point"}
}