{
  "type": "Feature",
  "properties": {
    "addr:full":"Zigzagoven 68 Wyk By Duurstede Utrecht 3961 EE",
    "addr:housenumber":"68",
    "addr:postcode":"3961 ee",
    "addr:street":"Zigzagoven;Duurstede",
    "iso:country":"NL",
    "sg:address":"Zigzagoven 68",
    "sg:city":"Wyk By Duurstede",
    "sg:orig_category":"Nagelstudio'S",
    "sg:phone":"+31 343 577 076",
    "sg:postcode":"3961 EE",
    "sg:province":"Utrecht",
    "wof:name":"Studio 68",
    "wof:placetype":"venue"
},
  "geometry": {"coordinates":[5.32979,51.977047],"type":"Point"}
}