{
  "type": "Feature",
  "properties": {
    "iso:country":"NL",
    "sg:address":"Marktstr 63",
    "sg:city":"Kerkrade",
    "sg:orig_category":"Vertaalbureaus",
    "sg:phone":"+31 45 545 6838",
    "sg:postcode":"6461 CV",
    "sg:province":"Limburg",
    "wof:name":"Ploum, K W",
    "wof:placetype":"venue"
},
  "geometry": {"coordinates":[6.065551,50.862976],"type":"Point"}
}