{
  "type": "Feature",
  "properties": {
    "addr:full":"Desire Geeraertsstraat 18 Baarle Nassau Noord-Brabant 5111 CH",
    "addr:housenumber":"18",
    "addr:postcode":"5111",
    "addr:street":"Geeraertsstraat",
    "iso:country":"NL",
    "sg:address":"Desire Geeraertsstraat 18",
    "sg:city":"Baarle Nassau",
    "sg:orig_category":"Bloemen And Planten",
    "sg:phone":"+31 13 507 9992",
    "sg:postcode":"5111 CH",
    "sg:province":"Noord-Brabant",
    "wof:name":"Esteria Bloemenstyling",
    "wof:placetype":"venue"
},
  "geometry": {"coordinates":[4.92629,51.449741],"type":"Point"}
}