{
  "type": "Feature",
  "properties": {
    "addr:full":"Wibautstr 105 Amsterdam Noord-Holland 1091 GL",
    "addr:housenumber":"105",
    "addr:postcode":"1091 gl",
    "iso:country":"NL",
    "sg:address":"Wibautstr 105",
    "sg:city":"Amsterdam",
    "sg:orig_category":"Fietsen En Bromfietsen",
    "sg:phone":"+31 20 663 6060",
    "sg:postcode":"1091 GL",
    "sg:province":"Noord-Holland",
    "sg:website":"http://www.moto-x.nl",
    "wof:name":"Moto-X Scooters",
    "wof:placetype":"venue"
},
  "geometry": {"coordinates":[4.911596,52.355991],"type":"Point"}
}