{
  "type": "Feature",
  "properties": {
    "addr:full":"Wilhelminapk 23 Venlo Limburg 5911 EC",
    "addr:housenumber":"23",
    "addr:postcode":"5911 ec",
    "addr:street":"Wilhelminapk",
    "iso:country":"NL",
    "sg:address":"Wilhelminapk 23",
    "sg:city":"Venlo",
    "sg:orig_category":"Verzekeringen - Verzekeringskantoren",
    "sg:phone":"+31 77 321 9110",
    "sg:postcode":"5911 EC",
    "sg:province":"Limburg",
    "wof:name":"Hauzer & Partners Bv",
    "wof:placetype":"venue"
},
  "geometry": {"coordinates":[6.169744,51.374542],"type":"Point"}
}