{
  "type": "Feature",
  "properties": {
    "addr:full":"Lekstraat 37 Enschede Overijssel 7523 HV",
    "addr:housenumber":"37",
    "addr:postcode":"7523 hv",
    "addr:street":"Lekstraat",
    "iso:country":"NL",
    "sg:address":"Lekstraat 37",
    "sg:city":"Enschede",
    "sg:orig_category":"Autokeuringen",
    "sg:phone":"+31 53 433 3805",
    "sg:postcode":"7523 HV",
    "sg:province":"Overijssel",
    "wof:name":"Wasstraat Gowi Bv",
    "wof:placetype":"venue"
},
  "geometry": {"coordinates":[6.897978,52.242199],"type":"Point"}
}