{
  "type": "Feature",
  "properties": {
    "iso:country":"NL",
    "sg:address":"De Corantijn 97",
    "sg:city":"Zwaag",
    "sg:orig_category":"Kunst And Kunstenaarsbenodigdheden",
    "sg:phone":"+31 229 245 123",
    "sg:postcode":"1689 AN",
    "sg:province":"Noord-Holland",
    "wof:name":"Modern Art Galerie",
    "wof:placetype":"venue"
},
  "geometry": {"coordinates":[5.067769,52.670113],"type":"Point"}
}