{
  "type": "Feature",
  "properties": {
    "addr:full":"Veliusstr 1 Tilburg Noord-Brabant 5014 KR",
    "addr:housenumber":"1",
    "addr:postcode":"5014 kr",
    "addr:street":"Veliusstr",
    "iso:country":"NL",
    "sg:address":"Veliusstr 1",
    "sg:city":"Tilburg",
    "sg:classifiers":[
        {
            "category":"Personal",
            "subcategory":"Nail Salon",
            "type":"Services"
        }
    ],
    "sg:phone":"+31 13 577 0797",
    "sg:postcode":"5014 KR",
    "sg:province":"Noord-Brabant",
    "sg:tags":[
        "pedicure"
    ],
    "wof:name":"Letitia",
    "wof:placetype":"venue"
},
  "geometry": {"coordinates":[5.094199,51.56871],"type":"Point"}
}