{
  "type": "Feature",
  "properties": {
    "addr:full":"Hemelrykstr 45 St Michielsgestel Noord-Brabant 5271 TX",
    "addr:housenumber":"45",
    "addr:postcode":"5271 tx",
    "addr:street":"Hemelrykstr;St Michielsgestel",
    "iso:country":"NL",
    "sg:address":"Hemelrykstr 45",
    "sg:city":"St Michielsgestel",
    "sg:orig_category":"Melktransporten",
    "sg:phone":"+31 73 551 3172",
    "sg:postcode":"5271 TX",
    "sg:province":"Noord-Brabant",
    "wof:name":"Steen Vof, Van Der",
    "wof:placetype":"venue"
},
  "geometry": {"coordinates":[5.341218,51.659168],"type":"Point"}
}