{
  "type": "Feature",
  "properties": {
    "addr:full":"Moleneind 1 Rynsburg South Holland 2231 HA",
    "addr:housenumber":"1",
    "addr:postcode":"2231 ha",
    "addr:street":"Moleneind",
    "iso:country":"NL",
    "sg:address":"Moleneind 1",
    "sg:city":"Rynsburg",
    "sg:orig_category":"Bloemen En Planten - Groothandel",
    "sg:phone":"+31 71 402 0214",
    "sg:postcode":"2231 HA",
    "sg:province":"South Holland",
    "wof:name":"Albloemex",
    "wof:placetype":"venue"
},
  "geometry": {"coordinates":[4.447964,52.190815],"type":"Point"}
}