{
  "type": "Feature",
  "properties": {
    "iso:country":"NL",
    "sg:address":"De Fok 19",
    "sg:city":"Schagen",
    "sg:orig_category":"Verlichtingsartikelen - Groothandel",
    "sg:phone":"+31 224 296 444",
    "sg:postcode":"1742 PC",
    "sg:province":"Noord-Holland",
    "wof:name":"Rjp, Technische Handelsondern",
    "wof:placetype":"venue"
},
  "geometry": {"coordinates":[4.780849,52.792217],"type":"Point"}
}