{
  "type": "Feature",
  "properties": {
    "addr:full":"Hamburgwg 9 Deventer Overijssel 7418 ES",
    "addr:housenumber":"9",
    "addr:postcode":"7418 es",
    "addr:street":"Hamburgwg",
    "iso:country":"NL",
    "sg:address":"Hamburgwg 9",
    "sg:city":"Deventer",
    "sg:orig_category":"Fotolitho- En Reprografie - Inrichtingen",
    "sg:phone":"+31 570 633 544",
    "sg:postcode":"7418 ES",
    "sg:province":"Overijssel",
    "wof:name":"Repro Deventer Bv",
    "wof:placetype":"venue"
},
  "geometry": {"coordinates":[6.200232,52.240288],"type":"Point"}
}