{
  "type": "Feature",
  "properties": {
    "addr:full":"Kasteelweg 11 Rotterdam Zuid-Holland 3077 BN",
    "addr:housenumber":"11",
    "addr:postcode":"3077 bn",
    "addr:street":"Kasteelweg",
    "iso:country":"NL",
    "sg:address":"Kasteelweg 11",
    "sg:city":"Rotterdam",
    "sg:orig_category":"Boekhouders",
    "sg:phone":"+31 10 482 7604",
    "sg:postcode":"3077 BN",
    "sg:province":"Zuid-Holland",
    "wof:name":"Centraal Boekhoudbureau Voor Nederland",
    "wof:placetype":"venue"
},
  "geometry": {"coordinates":[4.549228,51.900883],"type":"Point"}
}