{
  "type": "Feature",
  "properties": {
    "addr:full":"De Veken 13 Opmeer Noord-Holland 1716 KE",
    "addr:housenumber":"13",
    "addr:postcode":"1716 ke",
    "addr:street":"De Veken",
    "iso:country":"NL",
    "sg:address":"De Veken 13",
    "sg:city":"Opmeer",
    "sg:orig_category":"Parketvloeren",
    "sg:phone":"+31 226 354 268",
    "sg:postcode":"1716 KE",
    "sg:province":"Noord-Holland",
    "sg:website":"http://www.fredsmeubel.nl",
    "wof:name":"Fred'S Meubel Flooring",
    "wof:placetype":"venue"
},
  "geometry": {"coordinates":[4.957818,52.707893],"type":"Point"}
}