{
  "type": "Feature",
  "properties": {
    "addr:full":"B 38 Ottoland South Holland 2975 BH",
    "addr:housenumber":"38",
    "addr:postcode":"2975 bh",
    "addr:street":"B",
    "iso:country":"NL",
    "sg:address":"B 38",
    "sg:city":"Ottoland",
    "sg:orig_category":"Heiwerken En Funderingstechniek",
    "sg:phone":"+31 184 641 374",
    "sg:postcode":"2975 BH",
    "sg:province":"South Holland",
    "wof:name":"Dam Bv, Van",
    "wof:placetype":"venue"
},
  "geometry": {"coordinates":[4.858287,51.889191],"type":"Point"}
}