{
  "type": "Feature",
  "properties": {
    "addr:full":"Gijsbrecht Van Amstelstr 159 Hilversum Noord-Holland 1214 AX",
    "addr:housenumber":"159",
    "addr:postcode":"1214 ax",
    "addr:street":"Gijsbrecht Van Amstelstr",
    "iso:country":"NL",
    "sg:address":"Gijsbrecht Van Amstelstr 159",
    "sg:city":"Hilversum",
    "sg:orig_category":"Verlichting And Huishoudartikelen",
    "sg:phone":"+31 35 621 2018",
    "sg:postcode":"1214 AX",
    "sg:province":"Noord-Holland",
    "wof:name":"Lammertink",
    "wof:placetype":"venue"
},
  "geometry": {"coordinates":[5.168619,52.215618],"type":"Point"}
}