{
  "type": "Feature",
  "properties": {
    "addr:full":"J Vd Waalswg 108 Eindhoven North Brabant 5612 JD",
    "addr:housenumber":"108",
    "addr:postcode":"5612 jd",
    "iso:country":"NL",
    "sg:address":"J Vd Waalswg 108",
    "sg:city":"Eindhoven",
    "sg:orig_category":"Nagelstudio'S",
    "sg:phone":"+31 40 246 1762",
    "sg:postcode":"5612 JD",
    "sg:province":"North Brabant",
    "wof:name":"Professionails",
    "wof:placetype":"venue"
},
  "geometry": {"coordinates":[5.464162,51.449276],"type":"Point"}
}