{
  "type": "Feature",
  "properties": {
    "addr:full":"Prinsendam 79 Oosterhout Nb Noord-Brabant 4908 AD",
    "addr:housenumber":"79",
    "addr:postcode":"4908 ad",
    "addr:street":"Prinsendam",
    "iso:country":"NL",
    "sg:address":"Prinsendam 79",
    "sg:city":"Oosterhout Nb",
    "sg:orig_category":"Algemene Werktuigbouw",
    "sg:phone":"+31 162 433 574",
    "sg:postcode":"4908 AD",
    "sg:province":"Noord-Brabant",
    "wof:name":"Van Der Avoird Lastechniek",
    "wof:placetype":"venue"
},
  "geometry": {"coordinates":[4.860517,51.663548],"type":"Point"}
}