{
  "type": "Feature",
  "properties": {
    "addr:full":"J Bakerstr 34 Almere Flevoland 1311 GA",
    "addr:housenumber":"34",
    "addr:postcode":"1311 ga",
    "addr:street":"Flevoland",
    "iso:country":"NL",
    "sg:address":"J Bakerstr 34",
    "sg:city":"Almere",
    "sg:orig_category":"Modelmakerijen",
    "sg:phone":"+31 36 546 1460",
    "sg:postcode":"1311 GA",
    "sg:province":"Flevoland",
    "wof:name":"Jonk",
    "wof:placetype":"venue"
},
  "geometry": {"coordinates":[5.173251,52.366016],"type":"Point"}
}