{
  "type": "Feature",
  "properties": {
    "addr:full":"Saint Remystraat 14 Bunde Limburg 6241 JN",
    "addr:housenumber":"14",
    "addr:postcode":"6241 jn",
    "addr:street":"Remystraat",
    "iso:country":"NL",
    "sg:address":"Saint Remystraat 14",
    "sg:city":"Bunde",
    "sg:orig_category":"Kappers",
    "sg:phone":"+31 43 364 8732",
    "sg:postcode":"6241 JN",
    "sg:province":"Limburg",
    "wof:name":"Hairstyling Anja",
    "wof:placetype":"venue"
},
  "geometry": {"coordinates":[5.7274260521,50.8959388733],"type":"Point"}
}