{
  "type": "Feature",
  "properties": {
    "iso:country":"NL",
    "sg:address":"Amsterdamsewg 198",
    "sg:city":"Amstelveen",
    "sg:orig_category":"Woninginrichting",
    "sg:phone":"+31 20 645 3346",
    "sg:postcode":"1182 HL",
    "sg:province":"Noord-Holland",
    "wof:name":"Ende Vader En Zn Bv",
    "wof:placetype":"venue"
},
  "geometry": {"coordinates":[4.8470869064,52.3125991821],"type":"Point"}
}