{
  "type": "Feature",
  "properties": {
    "addr:full":"Adenauerln 38 Vlijmen Noord-Brabant 5252 BL",
    "addr:housenumber":"38",
    "addr:postcode":"5252 bl",
    "addr:street":"Adenauerln",
    "iso:country":"NL",
    "sg:address":"Adenauerln 38",
    "sg:city":"Vlijmen",
    "sg:orig_category":"Verloskundigen",
    "sg:phone":"+31 73 511 2968",
    "sg:postcode":"5252 BL",
    "sg:province":"Noord-Brabant",
    "wof:name":"Cornelis, M L I M",
    "wof:placetype":"venue"
},
  "geometry": {"coordinates":[5.211497,51.700394],"type":"Point"}
}