{
  "type": "Feature",
  "properties": {
    "iso:country":"NL",
    "sg:address":"Sint Domusstraat 17",
    "sg:city":"Zierikzee",
    "sg:orig_category":"Kunst And Kunstenaarsbenodigdheden",
    "sg:phone":"+31 111 416 467",
    "sg:postcode":"4301 CM",
    "sg:province":"Zeeland",
    "wof:name":"Lijstenmakerij Passe Partout",
    "wof:placetype":"venue"
},
  "geometry": {"coordinates":[3.921024,51.648685],"type":"Point"}
}