{
  "type": "Feature",
  "properties": {
    "addr:full":"E Goldmanwg 10 Tilburg Noord-Brabant 5032 MN",
    "addr:housenumber":"10",
    "addr:postcode":"5032 mn",
    "iso:country":"NL",
    "sg:address":"E Goldmanwg 10",
    "sg:city":"Tilburg",
    "sg:orig_category":"Huishoudelijke Apparaten En Artikelen",
    "sg:phone":"+31 13 594 0300",
    "sg:postcode":"5032 MN",
    "sg:province":"Noord-Brabant",
    "sg:website":"http://www.tristar-europe.nl",
    "wof:name":"Tristar Europe Bv",
    "wof:placetype":"venue"
},
  "geometry": {"coordinates":[5.037903,51.536301],"type":"Point"}
}