{
  "type": "Feature",
  "properties": {
    "addr:full":"Henric Van Veldekestraat 42 Sittard Limburg 6136 JC",
    "addr:housenumber":"42",
    "addr:postcode":"6136 jc",
    "addr:street":"Henric Van Veldekestraat",
    "iso:country":"NL",
    "sg:address":"Henric Van Veldekestraat 42",
    "sg:city":"Sittard",
    "sg:classifiers":[
        {
            "category":"Communications",
            "subcategory":"Television Station",
            "type":"Services"
        }
    ],
    "sg:phone":"+31 46 458 0790",
    "sg:postcode":"6136 JC",
    "sg:province":"Limburg",
    "sg:tags":[
        "video",
        "audio",
        "verhuur"
    ],
    "wof:name":"Videotheek Broadway",
    "wof:placetype":"venue"
},
  "geometry": {"coordinates":[5.874923,51.003311],"type":"Point"}
}