{
  "type": "Feature",
  "properties": {
    "addr:full":"H Memlingln 111 Bilthoven Utrecht 3723 WJ",
    "addr:housenumber":"111",
    "addr:postcode":"3723 wj",
    "addr:street":"Bilthoven",
    "iso:country":"NL",
    "sg:address":"H Memlingln 111",
    "sg:city":"Bilthoven",
    "sg:orig_category":"Onderhoudswerken",
    "sg:phone":"+31 30 225 1405",
    "sg:postcode":"3723 WJ",
    "sg:province":"Utrecht",
    "wof:name":"Avb",
    "wof:placetype":"venue"
},
  "geometry": {"coordinates":[5.191807,52.130127],"type":"Point"}
}