{
  "type": "Feature",
  "properties": {
    "addr:full":"Aalborg Haackslaan 51 Hendrik Ido Ambacht South Holland 3342 GK",
    "addr:housenumber":"51",
    "addr:postcode":"3342 gk",
    "addr:street":"Aalborg Haackslaan",
    "iso:country":"NL",
    "sg:address":"Aalborg Haackslaan 51",
    "sg:city":"Hendrik Ido Ambacht",
    "sg:orig_category":"Kappers",
    "sg:phone":"+31 78 681 4881",
    "sg:postcode":"3342 GK",
    "sg:province":"South Holland",
    "wof:name":"Esther Verhagen",
    "wof:placetype":"venue"
},
  "geometry": {"coordinates":[4.6230759621,51.8414039612],"type":"Point"}
}