{
  "type": "Feature",
  "properties": {
    "addr:full":"Mauritswg 1 Ridderkerk Zuid-Holland 2988 AE",
    "addr:housenumber":"1",
    "addr:postcode":"2988 ae",
    "addr:street":"Mauritswg",
    "iso:country":"NL",
    "sg:address":"Mauritswg 1",
    "sg:city":"Ridderkerk",
    "sg:orig_category":"Kinderopvang",
    "sg:phone":"+31 180 421 780",
    "sg:postcode":"2988 AE",
    "sg:province":"Zuid-Holland",
    "wof:name":"Bron, De",
    "wof:placetype":"venue"
},
  "geometry": {"coordinates":[4.59453,51.854439],"type":"Point"}
}