{
  "type": "Feature",
  "properties": {
    "iso:country":"NL",
    "sg:address":"C Vriendtstr 22",
    "sg:city":"Amsterdam",
    "sg:orig_category":"Webdesign Bureaus",
    "sg:phone":"+31 20 772 1377",
    "sg:postcode":"1067 AV",
    "sg:province":"Noord-Holland",
    "sg:website":"http://www.interlize.net",
    "wof:name":"Interlize",
    "wof:placetype":"venue"
},
  "geometry": {"coordinates":[4.799934864,52.3827285767],"type":"Point"}
}