{
  "type": "Feature",
  "properties": {
    "addr:full":"Karel Doormanlaan 21 Hilversum Noord-Holland 1215 NJ",
    "addr:housenumber":"21",
    "addr:postcode":"1215 nj",
    "addr:street":"Karel Doormanlaan",
    "iso:country":"NL",
    "sg:address":"Karel Doormanlaan 21",
    "sg:city":"Hilversum",
    "sg:orig_category":"Geluidsopnamen",
    "sg:phone":"+31 35 624 9039",
    "sg:postcode":"1215 NJ",
    "sg:province":"Noord-Holland",
    "wof:name":"Bochem Music",
    "wof:placetype":"venue"
},
  "geometry": {"coordinates":[-74.72672300000001,40.14278],"type":"Point"}
}