{
  "type": "Feature",
  "properties": {
    "addr:full":"Kon Julianastr 12H Nootdorp Zuid-Holland 2631 GB",
    "addr:housenumber":"12h",
    "addr:postcode":"2631 gb",
    "addr:street":"Kon",
    "iso:country":"NL",
    "sg:address":"Kon Julianastr 12H",
    "sg:city":"Nootdorp",
    "sg:orig_category":"Huishoudelijke Apparaten En Artikelen",
    "sg:phone":"+31 15 369 8011",
    "sg:postcode":"2631 GB",
    "sg:province":"Zuid-Holland",
    "wof:name":"Blokker",
    "wof:placetype":"venue"
},
  "geometry": {"coordinates":[4.395045,52.045879],"type":"Point"}
}