{
  "type": "Feature",
  "properties": {
    "addr:full":"St Elisabethstr 15A Grave Noord-Brabant 5361 HJ",
    "addr:housenumber":"15a",
    "addr:postcode":"5361 hj",
    "iso:country":"NL",
    "sg:address":"St Elisabethstr 15A",
    "sg:city":"Grave",
    "sg:orig_category":"Begrafenisverzorging",
    "sg:phone":"+31 486 472 074",
    "sg:postcode":"5361 HJ",
    "sg:province":"Noord-Brabant",
    "wof:name":"Adriaans",
    "wof:placetype":"venue"
},
  "geometry": {"coordinates":[-92.151741,32.929253],"type":"Point"}
}