{
  "type": "Feature",
  "properties": {
    "addr:full":"Emopad 29A Geldrop North Brabant 5663 PA",
    "addr:housenumber":"29a",
    "addr:postcode":"5663 pa",
    "addr:street":"Emopad",
    "iso:country":"NL",
    "sg:address":"Emopad 29A",
    "sg:city":"Geldrop",
    "sg:orig_category":"Autopoetsbedrijven",
    "sg:phone":"+31 40 368 5643",
    "sg:postcode":"5663 PA",
    "sg:province":"North Brabant",
    "wof:name":"Mr Polisch",
    "wof:placetype":"venue"
},
  "geometry": {"coordinates":[5.55426,51.412251],"type":"Point"}
}