{
  "type": "Feature",
  "properties": {
    "iso:country":"NL",
    "sg:address":"Prof Bronkhorstln 10",
    "sg:city":"Bilthoven",
    "sg:orig_category":"Adviesbureaus",
    "sg:phone":"+31 30 229 2727",
    "sg:postcode":"3723 MB",
    "sg:province":"Utrecht",
    "wof:name":"Factory Cro",
    "wof:placetype":"venue"
},
  "geometry": {"coordinates":[5.203953,52.154903],"type":"Point"}
}