{
  "type": "Feature",
  "properties": {
    "iso:country":"NL",
    "sg:address":"Schapendrift 53",
    "sg:city":"Beilen",
    "sg:orig_category":"Vertalers",
    "sg:phone":"+31 593 540 112",
    "sg:postcode":"9411 BL",
    "sg:province":"Drenthe",
    "wof:name":"Linguaplus",
    "wof:placetype":"venue"
},
  "geometry": {"coordinates":[6.510414,52.867233],"type":"Point"}
}