{
  "type": "Feature",
  "properties": {
    "addr:full":"Julianastraat 109 Rijen North Brabant 5121 LP",
    "addr:housenumber":"109",
    "addr:postcode":"5121 lp",
    "addr:street":"Julianastraat",
    "iso:country":"NL",
    "sg:address":"Julianastraat 109",
    "sg:city":"Rijen",
    "sg:orig_category":"Glaszetten",
    "sg:phone":"+31 161 240 104",
    "sg:postcode":"5121 LP",
    "sg:province":"North Brabant",
    "wof:name":"Van Uden Glaszettersbedrijf",
    "wof:placetype":"venue"
},
  "geometry": {"coordinates":[4.9234,51.583618],"type":"Point"}
}