{
  "type": "Feature",
  "properties": {
    "addr:full":"Lindtstr 6 Rotterdam Zuid-Holland 3073 SH",
    "addr:housenumber":"6",
    "addr:postcode":"3073 sh",
    "addr:street":"Lindtstr",
    "iso:country":"NL",
    "sg:address":"Lindtstr 6",
    "sg:city":"Rotterdam",
    "sg:orig_category":"Non-Classified Establishments",
    "sg:phone":"+31 10 486 2521",
    "sg:postcode":"3073 SH",
    "sg:province":"Zuid-Holland",
    "wof:name":"Dk Flex",
    "wof:placetype":"venue"
},
  "geometry": {"coordinates":[4.50579,51.894047],"type":"Point"}
}