{
  "type": "Feature",
  "properties": {
    "addr:full":"De Donk 22-24 Zevenbergen North Brabant 4761 JK",
    "addr:postcode":"22-24;4761 jk",
    "addr:street":"De Donk",
    "iso:country":"NL",
    "sg:address":"De Donk 22-24",
    "sg:city":"Zevenbergen",
    "sg:orig_category":"Kappers",
    "sg:phone":"+31 168 324 603",
    "sg:postcode":"4761 JK",
    "sg:province":"North Brabant",
    "wof:name":"Metamorfose 2000",
    "wof:placetype":"venue"
},
  "geometry": {"coordinates":[4.601587,51.649387],"type":"Point"}
}