{
  "type": "Feature",
  "properties": {
    "iso:country":"NL",
    "sg:address":"J V Nassaustr 6",
    "sg:city":"Castricum",
    "sg:orig_category":"Muziekscholen",
    "sg:phone":"+31 251 659 015",
    "sg:postcode":"1901 TJ",
    "sg:province":"Noord-Holland",
    "sg:website":"http://www.toonbeeld.tv",
    "wof:name":"Toonbeeld",
    "wof:placetype":"venue"
},
  "geometry": {"coordinates":[4.663725,52.546844],"type":"Point"}
}