{
  "type": "Feature",
  "properties": {
    "addr:full":"Waalstr 2 Rozenburg Zh Zuid-Holland 3181 ET",
    "addr:housenumber":"2",
    "addr:postcode":"zh;3181 et",
    "addr:street":"Waalstr",
    "iso:country":"NL",
    "sg:address":"Waalstr 2",
    "sg:city":"Rozenburg Zh",
    "sg:orig_category":"Verenigingen En Stichtingen",
    "sg:phone":"+31 181 212 227",
    "sg:postcode":"3181 ET",
    "sg:province":"Zuid-Holland",
    "wof:name":"Turkse Arbeiders Ver",
    "wof:placetype":"venue"
},
  "geometry": {"coordinates":[4.249615,51.904446],"type":"Point"}
}