{
  "type": "Feature",
  "properties": {
    "iso:country":"NL",
    "sg:address":"Overysselhaven 7",
    "sg:city":"Nieuwegein",
    "sg:orig_category":"Waterbehandeling En Waterzuiverings- Systemen",
    "sg:phone":"+31 30 606 2449",
    "sg:postcode":"3433 PH",
    "sg:province":"Utrecht",
    "wof:name":"Aqua Bv",
    "wof:placetype":"venue"
},
  "geometry": {"coordinates":[5.1054120064,52.0233306885],"type":"Point"}
}