{
  "type": "Feature",
  "properties": {
    "addr:full":"J De Waalstr 39 Lamswaarde Zeeland 4586 AD",
    "addr:housenumber":"39",
    "addr:postcode":"4586 ad",
    "addr:street":"J De Waalstr",
    "iso:country":"NL",
    "sg:address":"J De Waalstr 39",
    "sg:city":"Lamswaarde",
    "sg:orig_category":"Organisatiebureaus",
    "sg:phone":"+31 114 690 559",
    "sg:postcode":"4586 AD",
    "sg:province":"Zeeland",
    "sg:website":"http://www.camba.nl",
    "wof:name":"Camba",
    "wof:placetype":"venue"
},
  "geometry": {"coordinates":[4.0545349121,51.3457145691],"type":"Point"}
}