{
  "type": "Feature",
  "properties": {
    "addr:full":"Verwersstraat 75 'S Hertogenbosch Noord-Brabant 5211 HV",
    "addr:housenumber":"75",
    "addr:postcode":"5211 hv",
    "addr:street":"Verwersstraat;' S",
    "iso:country":"NL",
    "sg:address":"Verwersstraat 75",
    "sg:city":"'S Hertogenbosch",
    "sg:orig_category":"Architecten",
    "sg:phone":"+31 73 613 2689",
    "sg:postcode":"5211 HV",
    "sg:province":"Noord-Brabant",
    "wof:name":"Architectenbureau Jan Van Der Eerden Bv",
    "wof:placetype":"venue"
},
  "geometry": {"coordinates":[5.305936,51.686043],"type":"Point"}
}