{
  "type": "Feature",
  "properties": {
    "addr:full":"Grenadadreef 1 Utrecht Utrecht 3563 HE",
    "addr:housenumber":"1",
    "addr:postcode":"3563 he",
    "addr:street":"Grenadadreef",
    "iso:country":"NL",
    "sg:address":"Grenadadreef 1",
    "sg:city":"Utrecht",
    "sg:orig_category":"Film-, Tv- And Videoproductie",
    "sg:phone":"+31 30 261 8699",
    "sg:postcode":"3563 HE",
    "sg:province":"Utrecht",
    "wof:name":"Raymond Hartman Audio Visuele Produkties",
    "wof:placetype":"venue"
},
  "geometry": {"coordinates":[5.094529,52.123615],"type":"Point"}
}