{
  "type": "Feature",
  "properties": {
    "addr:full":"Stephensonstr 121 Hoogeveen Drenthe 7903 AS",
    "addr:housenumber":"121",
    "addr:postcode":"7903 as",
    "iso:country":"NL",
    "sg:address":"Stephensonstr 121",
    "sg:city":"Hoogeveen",
    "sg:orig_category":"Plafonds",
    "sg:phone":"+31 528 279 911",
    "sg:postcode":"7903 AS",
    "sg:province":"Drenthe",
    "wof:name":"Annhil Bv",
    "wof:placetype":"venue"
},
  "geometry": {"coordinates":[6.530626,52.728451],"type":"Point"}
}