{
  "type": "Feature",
  "properties": {
    "addr:full":"Taxandriawg 13 Waalwyk Noord-Brabant 5142 PA",
    "addr:housenumber":"13",
    "addr:postcode":"5142 pa",
    "addr:street":"Taxandriawg",
    "iso:country":"NL",
    "sg:address":"Taxandriawg 13",
    "sg:city":"Waalwyk",
    "sg:orig_category":"Verenigingsgebouwen",
    "sg:phone":"+31 416 340 322",
    "sg:postcode":"5142 PA",
    "sg:province":"Noord-Brabant",
    "wof:name":"Tavenu, De",
    "wof:placetype":"venue"
},
  "geometry": {"coordinates":[5.076697,51.693489],"type":"Point"}
}