{
  "type": "Feature",
  "properties": {
    "addr:full":"Oude Veendk 9 Vlagtwedde Groningen 9541 XE",
    "addr:housenumber":"9",
    "addr:postcode":"9541 xe",
    "addr:street":"Oude Veendk",
    "iso:country":"NL",
    "sg:address":"Oude Veendk 9",
    "sg:city":"Vlagtwedde",
    "sg:orig_category":"Loonbedrijven",
    "sg:phone":"+31 599 354 516",
    "sg:postcode":"9541 XE",
    "sg:province":"Groningen",
    "wof:name":"Wesseling, H",
    "wof:placetype":"venue"
},
  "geometry": {"coordinates":[7.150822,53.032497],"type":"Point"}
}