{
  "type": "Feature",
  "properties": {
    "iso:country":"NL",
    "sg:address":"Bylmerpln 719",
    "sg:city":"Amsterdam Zuidoost",
    "sg:orig_category":"Koffie- En Theehuizen",
    "sg:phone":"+31 20 697 8974",
    "sg:postcode":"1102 MA",
    "sg:province":"North Holland",
    "wof:name":"Abc",
    "wof:placetype":"venue"
},
  "geometry": {"coordinates":[4.955512,52.314281],"type":"Point"}
}