{
  "type": "Feature",
  "properties": {
    "addr:full":"K Doormanstr 459 Rotterdam Zuid-Holland 3012 GH",
    "addr:housenumber":"459",
    "addr:postcode":"3012 gh",
    "iso:country":"NL",
    "sg:address":"K Doormanstr 459",
    "sg:city":"Rotterdam",
    "sg:orig_category":"Juweliers",
    "sg:phone":"+31 10 433 4442",
    "sg:postcode":"3012 GH",
    "sg:province":"Zuid-Holland",
    "sg:website":"http://www.zaansejuweliers.nl",
    "wof:name":"Zaanse Juweliers",
    "wof:placetype":"venue"
},
  "geometry": {"coordinates":[4.476173,51.91832],"type":"Point"}
}