{
  "type": "Feature",
  "properties": {
    "addr:full":"M V Meelwg 15 Eindhoven North Brabant 5657 EN",
    "addr:housenumber":"15",
    "addr:postcode":"5657 en",
    "addr:street":"Meelwg",
    "iso:country":"NL",
    "sg:address":"M V Meelwg 15",
    "sg:city":"Eindhoven",
    "sg:orig_category":"Mode Artikelen Dames En Heren - Fabrieken En Groothandel",
    "sg:phone":"+31 40 291 4040",
    "sg:postcode":"5657 EN",
    "sg:province":"North Brabant",
    "wof:name":"Belt Fasion Eindhoven Bv",
    "wof:placetype":"venue"
},
  "geometry": {"coordinates":[5.39235,51.456921],"type":"Point"}
}