{
  "type": "Feature",
  "properties": {
    "iso:country":"NL",
    "sg:address":"Wilhelmina Druckerstraat 10",
    "sg:city":"Alphen A/D Rijn",
    "sg:orig_category":"Koffers And Tassen Fab",
    "sg:phone":"+31 172 443 313",
    "sg:postcode":"2401 KG",
    "sg:province":"South Holland",
    "wof:name":"B.J. De Levie",
    "wof:placetype":"venue"
},
  "geometry": {"coordinates":[4.658697,52.156521],"type":"Point"}
}