{
  "type": "Feature",
  "properties": {
    "addr:full":"James Cookstraat 2Hs Amsterdam North Holland 1056 RZ",
    "addr:housenumber":"2hs",
    "addr:postcode":"1056 rz",
    "addr:street":"James Cookstraat",
    "iso:country":"NL",
    "sg:address":"James Cookstraat 2Hs",
    "sg:city":"Amsterdam",
    "sg:orig_category":"Kappers",
    "sg:phone":"+31 20 612 9394",
    "sg:postcode":"1056 RZ",
    "sg:province":"North Holland",
    "wof:name":"Sahin Kapsalon",
    "wof:placetype":"venue"
},
  "geometry": {"coordinates":[4.85263,52.371357],"type":"Point"}
}