{
  "type": "Feature",
  "properties": {
    "addr:full":"H Moerkerkln 43 Rosmalen Noord-Brabant 5246 GE",
    "addr:housenumber":"43",
    "addr:postcode":"5246",
    "iso:country":"NL",
    "sg:address":"H Moerkerkln 43",
    "sg:city":"Rosmalen",
    "sg:orig_category":"Adviesbureaus Bedrijfsorganisatie",
    "sg:phone":"+31 73 643 1355",
    "sg:postcode":"5246 GE",
    "sg:province":"Noord-Brabant",
    "sg:website":"http://www.delfini.nl",
    "wof:name":"Delf\u00edni",
    "wof:placetype":"venue"
},
  "geometry": {"coordinates":[5.34293,51.700851],"type":"Point"}
}