{
  "type": "Feature",
  "properties": {
    "iso:country":"NL",
    "sg:address":"Stadhoudersln 96",
    "sg:city":"Utrecht",
    "sg:orig_category":"Psychologen",
    "sg:phone":"+31 30 251 3009",
    "sg:postcode":"3583 JN",
    "sg:province":"Utrecht",
    "wof:name":"Vianen, J T M",
    "wof:placetype":"venue"
},
  "geometry": {"coordinates":[5.14371,52.086601],"type":"Point"}
}