{
  "type": "Feature",
  "properties": {
    "addr:full":"Finnmark 1 Leusden Utrecht 3831 JE",
    "addr:housenumber":"1",
    "addr:postcode":"3831 je",
    "addr:street":"Finnmark",
    "iso:country":"NL",
    "sg:address":"Finnmark 1",
    "sg:city":"Leusden",
    "sg:orig_category":"Parketvloeren",
    "sg:phone":"+31 33 495 3153",
    "sg:postcode":"3831 JE",
    "sg:province":"Utrecht",
    "wof:name":"Pluim",
    "wof:placetype":"venue"
},
  "geometry": {"coordinates":[5.433311,52.136581],"type":"Point"}
}