{
  "type": "Feature",
  "properties": {
    "addr:full":"Loggerstr 65 Zaandam Noord-Holland 1503 KB",
    "addr:housenumber":"65",
    "addr:postcode":"1503 kb",
    "addr:street":"Loggerstr",
    "iso:country":"NL",
    "sg:address":"Loggerstr 65",
    "sg:city":"Zaandam",
    "sg:orig_category":"Adviesbureaus Bedrijfsorganisatie",
    "sg:phone":"+31 75 617 8908",
    "sg:postcode":"1503 KB",
    "sg:province":"Noord-Holland",
    "sg:website":"http://www.bedrijfsadviesmoesker.nl",
    "wof:name":"Moesker",
    "wof:placetype":"venue"
},
  "geometry": {"coordinates":[4.837407,52.449577],"type":"Point"}
}