{
  "type": "Feature",
  "properties": {
    "addr:full":"Den Ool 25 Hilversum Noord-Holland 1223 KV",
    "addr:housenumber":"25",
    "addr:postcode":"1223 kv",
    "addr:street":"Den Ool",
    "iso:country":"NL",
    "sg:address":"Den Ool 25",
    "sg:city":"Hilversum",
    "sg:orig_category":"Vertalers",
    "sg:phone":"+31 35 683 7095",
    "sg:postcode":"1223 KV",
    "sg:province":"Noord-Holland",
    "wof:name":"Sandra Van Hemert",
    "wof:placetype":"venue"
},
  "geometry": {"coordinates":[5.201154,52.228931],"type":"Point"}
}