{
  "type": "Feature",
  "properties": {
    "addr:full":"Kl Huisterwg 5 Pingjum Provincie Friesland 8749 TV",
    "addr:housenumber":"5",
    "addr:postcode":"8749 tv",
    "addr:street":"Provincie Friesland",
    "iso:country":"NL",
    "sg:address":"Kl Huisterwg 5",
    "sg:city":"Pingjum",
    "sg:orig_category":"Plastic Producten - Fabrieken En Groothandel",
    "sg:phone":"+31 517 579 592",
    "sg:postcode":"8749 TV",
    "sg:province":"Provincie Friesland",
    "wof:name":"Miklafles Holland",
    "wof:placetype":"venue"
},
  "geometry": {"coordinates":[5.440041,53.1152],"type":"Point"}
}