{
  "type": "Feature",
  "properties": {
    "iso:country":"NL",
    "sg:address":"Sterkenburg 30",
    "sg:city":"Alphen A/D Rijn",
    "sg:orig_category":"Fotostudio'S And Fotografen",
    "sg:phone":"+31 172 442 448",
    "sg:postcode":"2402 RB",
    "sg:province":"South Holland",
    "wof:name":"Bureau De Fotograaf",
    "wof:placetype":"venue"
},
  "geometry": {"coordinates":[4.67851,52.153549],"type":"Point"}
}