{
  "type": "Feature",
  "properties": {
    "addr:full":"Sterkenburg 30 Alphen A/D Rijn South Holland 2402 RB",
    "addr:housenumber":"30",
    "addr:postcode":"2402 rb",
    "addr:street":"Sterkenburg",
    "iso:country":"NL",
    "sg:address":"Sterkenburg 30",
    "sg:city":"Alphen A/D Rijn",
    "sg:orig_category":"Fotostudio'S And Fotografen",
    "sg:phone":"+31 172 442 448",
    "sg:postcode":"2402 RB",
    "sg:province":"South Holland",
    "wof:name":"Bureau De Fotograaf",
    "wof:placetype":"venue"
},
  "geometry": {"coordinates":[4.67851,52.153549],"type":"Point"}
}