{
  "type": "Feature",
  "properties": {
    "addr:full":"Laauwikstr 16 Lent Gelderland 6663 CJ",
    "addr:housenumber":"16",
    "addr:postcode":"6663 cj",
    "addr:street":"Laauwikstr;Gelderland",
    "iso:country":"NL",
    "sg:address":"Laauwikstr 16",
    "sg:city":"Lent",
    "sg:orig_category":"Kappers",
    "sg:phone":"+31 24 322 5746",
    "sg:postcode":"6663 CJ",
    "sg:province":"Gelderland",
    "wof:name":"Reuser, L J H",
    "wof:placetype":"venue"
},
  "geometry": {"coordinates":[-77.241432,38.151344],"type":"Point"}
}