{
  "type": "Feature",
  "properties": {
    "addr:full":"Parallelwg 35 Geleen Limburg 6161 SK",
    "addr:housenumber":"35",
    "addr:street":"Parallelwg;6161",
    "iso:country":"NL",
    "sg:address":"Parallelwg 35",
    "sg:city":"Geleen",
    "sg:orig_category":"Verpakkingen En Verpakkingsmaterialen",
    "sg:phone":"+31 46 475 2606",
    "sg:postcode":"6161 SK",
    "sg:province":"Limburg",
    "wof:name":"Stralen, Van",
    "wof:placetype":"venue"
},
  "geometry": {"coordinates":[5.821204,50.971291],"type":"Point"}
}