{
  "type": "Feature",
  "properties": {
    "addr:full":"W Vd Brinkstr 39 Purmerend Noord-Holland 1444 HB",
    "addr:housenumber":"39",
    "addr:postcode":"1444 hb",
    "addr:street":"W",
    "iso:country":"NL",
    "sg:address":"W Vd Brinkstr 39",
    "sg:city":"Purmerend",
    "sg:orig_category":"Onderhoudswerken",
    "sg:phone":"+31 299 431 519",
    "sg:postcode":"1444 HB",
    "sg:province":"Noord-Holland",
    "wof:name":"Eijk, De",
    "wof:placetype":"venue"
},
  "geometry": {"coordinates":[4.969039,52.521011],"type":"Point"}
}