{
  "type": "Feature",
  "properties": {
    "addr:full":"Prinsengr 993 Amsterdam Noord-Holland 1017 KM",
    "addr:housenumber":"993",
    "addr:street":"1017 Km",
    "iso:country":"NL",
    "sg:address":"Prinsengr 993",
    "sg:city":"Amsterdam",
    "sg:orig_category":"Filmstudio'S En -Productie",
    "sg:phone":"+31 20 622 8698",
    "sg:postcode":"1017 KM",
    "sg:province":"Noord-Holland",
    "wof:name":"Post, Nils",
    "wof:placetype":"venue"
},
  "geometry": {"coordinates":[4.893591,52.362213],"type":"Point"}
}