{
  "type": "Feature",
  "properties": {
    "addr:full":"Tolakkerweg 15 Hollandsche Rading Utrecht 3739 JG",
    "addr:housenumber":"15",
    "addr:postcode":"rading;3739 jg",
    "addr:street":"Tolakkerweg",
    "iso:country":"NL",
    "sg:address":"Tolakkerweg 15",
    "sg:city":"Hollandsche Rading",
    "sg:orig_category":"Werving En Selectie",
    "sg:phone":"+31 35 577 2150",
    "sg:postcode":"3739 JG",
    "sg:province":"Utrecht",
    "wof:name":"Pop",
    "wof:placetype":"venue"
},
  "geometry": {"coordinates":[5.1761770248,52.1762962341],"type":"Point"}
}