{
  "type": "Feature",
  "properties": {
    "addr:full":"J Roeckplnts 14-Iii Veenendaal Utrecht 3902 ZL",
    "addr:housenumber":"14-iii",
    "addr:postcode":"3902 zl",
    "iso:country":"NL",
    "sg:address":"J Roeckplnts 14-Iii",
    "sg:city":"Veenendaal",
    "sg:orig_category":"Autorijscholen",
    "sg:phone":"+31 6 25323626",
    "sg:postcode":"3902 ZL",
    "sg:province":"Utrecht",
    "wof:name":"Amro Vic",
    "wof:placetype":"venue"
},
  "geometry": {"coordinates":[5.55418,52.024902],"type":"Point"}
}