{
  "type": "Feature",
  "properties": {
    "addr:full":"Valkenkamp 554 Maarssen Utrecht 3607 MJ",
    "addr:housenumber":"554",
    "addr:postcode":"3607 mj",
    "addr:street":"Valkenkamp",
    "iso:country":"NL",
    "sg:address":"Valkenkamp 554",
    "sg:city":"Maarssen",
    "sg:orig_category":"Verenigingen En Stichtingen",
    "sg:phone":"+31 346 559 259",
    "sg:postcode":"3607 MJ",
    "sg:province":"Utrecht",
    "sg:website":"http://www.abrona.nl",
    "wof:name":"Abrona",
    "wof:placetype":"venue"
},
  "geometry": {"coordinates":[5.01173,52.135792],"type":"Point"}
}