{
  "type": "Feature",
  "properties": {
    "addr:full":"Losplaatswg 9 Noordwijk South Holland 2201 CS",
    "addr:housenumber":"9",
    "addr:postcode":"2201 cs",
    "addr:street":"Losplaatswg",
    "iso:country":"NL",
    "sg:address":"Losplaatswg 9",
    "sg:city":"Noordwijk",
    "sg:orig_category":"Natuur- En Milieuorganisaties",
    "sg:phone":"+31 71 361 8082",
    "sg:postcode":"2201 CS",
    "sg:province":"South Holland",
    "wof:name":"Kringloopproject, Sticht",
    "wof:placetype":"venue"
},
  "geometry": {"coordinates":[4.441699,52.233028],"type":"Point"}
}