{
  "type": "Feature",
  "properties": {
    "addr:full":"Nw Spiegelstr 11A Amsterdam Noord-Holland 1017 DB",
    "addr:housenumber":"11a",
    "addr:postcode":"1017 db",
    "iso:country":"NL",
    "sg:address":"Nw Spiegelstr 11A",
    "sg:city":"Amsterdam",
    "sg:orig_category":"Kappers",
    "sg:phone":"+31 20 624 2959",
    "sg:postcode":"1017 DB",
    "sg:province":"Noord-Holland",
    "wof:name":"Carlo Di Luca",
    "wof:placetype":"venue"
},
  "geometry": {"coordinates":[4.8901138306,52.3647232056],"type":"Point"}
}