{
  "type": "Feature",
  "properties": {
    "iso:country":"NL",
    "sg:address":"Fabriekwg 10",
    "sg:city":"Westknollendam",
    "sg:orig_category":"Directmail",
    "sg:phone":"+31 75 647 1111",
    "sg:postcode":"1525 RB",
    "sg:province":"North Holland",
    "sg:website":"http://www.maximail.nl",
    "wof:name":"Euro Mail",
    "wof:placetype":"venue"
},
  "geometry": {"coordinates":[4.779928,52.516964],"type":"Point"}
}