{
  "type": "Feature",
  "properties": {
    "addr:full":"Overysselln 77 Heemstede North Holland 2101 TB",
    "addr:housenumber":"77",
    "addr:postcode":"2101 tb",
    "addr:street":"Overysselln",
    "iso:country":"NL",
    "sg:address":"Overysselln 77",
    "sg:city":"Heemstede",
    "sg:orig_category":"Bloemen En Planten",
    "sg:phone":"+31 23 529 0834",
    "sg:postcode":"2101 TB",
    "sg:province":"North Holland",
    "wof:name":"Flower Power",
    "wof:placetype":"venue"
},
  "geometry": {"coordinates":[4.619641,52.347885],"type":"Point"}
}