{
  "type": "Feature",
  "properties": {
    "addr:full":"N Beetspln 107 Hoogeveen Provincie Drenthe 7901 KK",
    "addr:housenumber":"107",
    "addr:postcode":"7901 kk",
    "addr:street":"N;Provincie",
    "iso:country":"NL",
    "sg:address":"N Beetspln 107",
    "sg:city":"Hoogeveen",
    "sg:orig_category":"Schoenen",
    "sg:phone":"+31 528 233 563",
    "sg:postcode":"7901 KK",
    "sg:province":"Provincie Drenthe",
    "wof:name":"Feijer Schoenen",
    "wof:placetype":"venue"
},
  "geometry": {"coordinates":[6.476556,52.722549],"type":"Point"}
}