{
  "type": "Feature",
  "properties": {
    "addr:full":"Grt Belt 90 Hoofddorp North Holland 2133 GC",
    "addr:housenumber":"90",
    "addr:postcode":"2133 gc",
    "addr:street":"Belt",
    "iso:country":"NL",
    "sg:address":"Grt Belt 90",
    "sg:city":"Hoofddorp",
    "sg:orig_category":"Koeriersdiensten",
    "sg:phone":"+31 23 561 5846",
    "sg:postcode":"2133 GC",
    "sg:province":"North Holland",
    "wof:name":"Bloem, De",
    "wof:placetype":"venue"
},
  "geometry": {"coordinates":[4.668958,52.314285],"type":"Point"}
}