{
  "type": "Feature",
  "properties": {
    "addr:full":"Zandeveltwg 98 S Gravenzande Zuid-Holland 2692 AW",
    "addr:housenumber":"98;gravenzande",
    "addr:postcode":"2692 aw",
    "addr:street":"Zandeveltwg;S",
    "iso:country":"NL",
    "sg:address":"Zandeveltwg 98",
    "sg:city":"S Gravenzande",
    "sg:orig_category":"Montagebedrijven",
    "sg:phone":"+31 174 441 600",
    "sg:postcode":"2692 AW",
    "sg:province":"Zuid-Holland",
    "wof:name":"Knegt",
    "wof:placetype":"venue"
},
  "geometry": {"coordinates":[4.158216,52.000923],"type":"Point"}
}