{
  "type": "Feature",
  "properties": {
    "iso:country":"NL",
    "sg:address":"Bergstr 29",
    "sg:city":"Doesburg",
    "sg:classifiers":[
        {
            "category":"Farming",
            "subcategory":"Fish & Marine Products",
            "type":"Manufacturing & Wholesale Goods"
        }
    ],
    "sg:phone":"+31 313 472 592",
    "sg:postcode":"6981 DA",
    "sg:province":"Gelderland",
    "sg:tags":[
        "vi"
    ],
    "wof:name":"Kelderman Vof, H",
    "wof:placetype":"venue"
},
  "geometry": {"coordinates":[6.137508,52.015045],"type":"Point"}
}