{
  "type": "Feature",
  "properties": {
    "addr:full":"Dorpsstr 18 Aalsmeer North Holland 1431 CD",
    "addr:housenumber":"18",
    "addr:postcode":"1431 cd",
    "addr:street":"Dorpsstr",
    "iso:country":"NL",
    "sg:address":"Dorpsstr 18",
    "sg:city":"Aalsmeer",
    "sg:orig_category":"Belastingconsulenten/ Belastingadviseurs",
    "sg:phone":"+31 297 342 329",
    "sg:postcode":"1431 CD",
    "sg:province":"North Holland",
    "wof:name":"Coloniae",
    "wof:placetype":"venue"
},
  "geometry": {"coordinates":[4.747014,52.270077],"type":"Point"}
}