{
  "type": "Feature",
  "properties": {
    "addr:full":"Rondehoep W 33 Ouderkerk Amstel Noord-Holland 1191 KL",
    "addr:housenumber":"33",
    "addr:postcode":"1191 kl",
    "addr:street":"Rondehoep W;Amstel",
    "iso:country":"NL",
    "sg:address":"Rondehoep W 33",
    "sg:city":"Ouderkerk Amstel",
    "sg:orig_category":"Bloemen En Planten",
    "sg:phone":"+31 20 496 1582",
    "sg:postcode":"1191 KL",
    "sg:province":"Noord-Holland",
    "wof:name":"Paddenburg Bv, Van",
    "wof:placetype":"venue"
},
  "geometry": {"coordinates":[4.887824,52.2896],"type":"Point"}
}