{
  "type": "Feature",
  "properties": {
    "iso:country":"NL",
    "sg:address":"Paul Krugerlaan 82",
    "sg:city":"'S Gravenhage",
    "sg:orig_category":"Werving And Selectie Van Tijdelijk Personeel And Uitzendkantoren",
    "sg:phone":"+31 70 364 4925",
    "sg:postcode":"2571 HL",
    "sg:province":"South Holland",
    "wof:name":"Inzet Uitzend Buro",
    "wof:placetype":"venue"
},
  "geometry": {"coordinates":[4.2874488831,52.0698013306],"type":"Point"}
}