{
  "type": "Feature",
  "properties": {
    "addr:full":"Grisenstr 6 Kerkrade Limburg 6465 CE",
    "addr:housenumber":"6",
    "addr:postcode":"6465 ce",
    "addr:street":"Grisenstr",
    "iso:country":"NL",
    "sg:address":"Grisenstr 6",
    "sg:city":"Kerkrade",
    "sg:orig_category":"Verhuizingen",
    "sg:phone":"+31 45 542 8536",
    "sg:postcode":"6465 CE",
    "sg:province":"Limburg",
    "wof:name":"Schoenmaekers, C A J",
    "wof:placetype":"venue"
},
  "geometry": {"coordinates":[6.038475,50.854301],"type":"Point"}
}