{
  "type": "Feature",
  "properties": {
    "addr:full":"Linnaeusstraat 14 Amsterdam Noord-Holland 1092 CK",
    "addr:housenumber":"14",
    "addr:postcode":"1092 ck",
    "addr:street":"Linnaeusstraat",
    "iso:country":"NL",
    "sg:address":"Linnaeusstraat 14",
    "sg:city":"Amsterdam",
    "sg:orig_category":"Meubelzaken, Woning- And Keukeninrichting",
    "sg:phone":"+31 20 694 0298",
    "sg:postcode":"1092 CK",
    "sg:province":"Noord-Holland",
    "wof:name":"Vof Spaan Kastencentrum",
    "wof:placetype":"venue"
},
  "geometry": {"coordinates":[4.92521,52.359558],"type":"Point"}
}