{
  "type": "Feature",
  "properties": {
    "addr:full":"Vijverlaan 12 Zeist Utrecht 3701 CS",
    "addr:housenumber":"12",
    "addr:postcode":"3701 cs",
    "addr:street":"Vijverlaan",
    "iso:country":"NL",
    "sg:address":"Vijverlaan 12",
    "sg:city":"Zeist",
    "sg:orig_category":"Grafologen, Handlezers And Helderzienden",
    "sg:phone":"+31 30 693 0233",
    "sg:postcode":"3701 CS",
    "sg:province":"Utrecht",
    "wof:name":"Grafologisch Bureau H. Van De Weg",
    "wof:placetype":"venue"
},
  "geometry": {"coordinates":[5.248162,52.087238],"type":"Point"}
}