{
  "type": "Feature",
  "properties": {
    "addr:full":"Lange Bisschopstraat 7 Deventer Overijssel 7411 KG",
    "addr:housenumber":"7",
    "addr:postcode":"7411 kg",
    "addr:street":"Lange Bisschopstraat",
    "iso:country":"NL",
    "sg:address":"Lange Bisschopstraat 7",
    "sg:city":"Deventer",
    "sg:orig_category":"Verlichting And Huishoudartikelen",
    "sg:phone":"+31 570 642 714",
    "sg:postcode":"7411 KG",
    "sg:province":"Overijssel",
    "wof:name":"Xenos Bv",
    "wof:placetype":"venue"
},
  "geometry": {"coordinates":[6.156239,52.25256],"type":"Point"}
}