{
  "type": "Feature",
  "properties": {
    "addr:full":"Heintje Davidspad 17 Zaandam Noord-Holland 1507 SW",
    "addr:housenumber":"17;1507",
    "addr:street":"Heintje Davidspad;Sw",
    "iso:country":"NL",
    "sg:address":"Heintje Davidspad 17",
    "sg:city":"Zaandam",
    "sg:orig_category":"Wegen And Sportterreinen",
    "sg:phone":"+31 75 670 6253",
    "sg:postcode":"1507 SW",
    "sg:province":"Noord-Holland",
    "wof:name":"Zwietering",
    "wof:placetype":"venue"
},
  "geometry": {"coordinates":[4.8023071289,52.4457740784],"type":"Point"}
}