{
  "type": "Feature",
  "properties": {
    "addr:full":"Voorstr 6 St Philipsland Zeeland 4675 CB",
    "addr:housenumber":"6",
    "addr:postcode":"4675 cb",
    "addr:street":"Voorstr",
    "iso:country":"NL",
    "sg:address":"Voorstr 6",
    "sg:city":"St Philipsland",
    "sg:orig_category":"Kappers",
    "sg:phone":"+31 167 572 418",
    "sg:postcode":"4675 CB",
    "sg:province":"Zeeland",
    "wof:name":"Haarstudio, De",
    "wof:placetype":"venue"
},
  "geometry": {"coordinates":[4.1663680077,51.6165542603],"type":"Point"}
}