{
  "type": "Feature",
  "properties": {
    "iso:country":"NL",
    "sg:address":"Korund 8",
    "sg:city":"Heerhugowaard",
    "sg:orig_category":"Verzekeringen",
    "sg:phone":"+31 23 553 0530",
    "sg:postcode":"1703 CV",
    "sg:province":"Noord-Holland",
    "wof:name":"Arthur Abbink Financiele Dienstverlening",
    "wof:placetype":"venue"
},
  "geometry": {"coordinates":[4.822243,52.657948],"type":"Point"}
}