{
  "type": "Feature",
  "properties": {
    "addr:full":"De Drie Linden 1 Limmen Noord-Holland 1906 EM",
    "addr:housenumber":"1",
    "addr:postcode":"1906 em",
    "addr:street":"De Drie Linden",
    "iso:country":"NL",
    "sg:address":"De Drie Linden 1",
    "sg:city":"Limmen",
    "sg:orig_category":"Verzekeringen - Verzekeringskantoren",
    "sg:phone":"+31 72 505 4616",
    "sg:postcode":"1906 EM",
    "sg:province":"Noord-Holland",
    "sg:website":"http://www.budgetcare.nl",
    "wof:name":"Budget Care",
    "wof:placetype":"venue"
},
  "geometry": {"coordinates":[4.6923499107,52.5717735291],"type":"Point"}
}