{
  "type": "Feature",
  "properties": {
    "addr:full":"Vd Endeln 14 Hillegom Zuid-Holland 2181 EK",
    "addr:housenumber":"14",
    "addr:postcode":"2181 ek",
    "iso:country":"NL",
    "sg:address":"Vd Endeln 14",
    "sg:city":"Hillegom",
    "sg:orig_category":"Feestartikelen",
    "sg:phone":"+31 6 12612773",
    "sg:postcode":"2181 EK",
    "sg:province":"Zuid-Holland",
    "wof:name":"Happy Banners",
    "wof:placetype":"venue"
},
  "geometry": {"coordinates":[4.578656,52.294537],"type":"Point"}
}