{
  "type": "Feature",
  "properties": {
    "iso:country":"NL",
    "sg:address":"De Parken 12",
    "sg:city":"Druten",
    "sg:orig_category":"Organisatiebureaus",
    "sg:phone":"+31 487 511 437",
    "sg:postcode":"6652 GC",
    "sg:province":"Gelderland",
    "wof:name":"Raaijen, Bur Van",
    "wof:placetype":"venue"
},
  "geometry": {"coordinates":[5.605246067,51.8824119568],"type":"Point"}
}