{
  "type": "Feature",
  "properties": {
    "addr:full":"Wattstr 2 Barneveld Gelderland 3771 AG",
    "addr:housenumber":"2",
    "addr:postcode":"3771",
    "addr:street":"Wattstr;Gelderland",
    "iso:country":"NL",
    "sg:address":"Wattstr 2",
    "sg:city":"Barneveld",
    "sg:orig_category":"Verenigingen En Stichtingen",
    "sg:phone":"+31 342 420 554",
    "sg:postcode":"3771 AG",
    "sg:province":"Gelderland",
    "sg:website":"http://www.hulpoosteuropa.nl",
    "wof:name":"Hulp Oost-Europa, Sticht",
    "wof:placetype":"venue"
},
  "geometry": {"coordinates":[5.596743,52.136196],"type":"Point"}
}