{
  "type": "Feature",
  "properties": {
    "iso:country":"NL",
    "sg:address":"Borgerstraat 2",
    "sg:city":"Leiden",
    "sg:orig_category":"Fruit And Groenten Gh",
    "sg:phone":"+31 71 531 0027",
    "sg:postcode":"2321 XK",
    "sg:province":"Zuid-Holland",
    "wof:name":"Groente- En Fruithandel C. Wesselius",
    "wof:placetype":"venue"
},
  "geometry": {"coordinates":[4.476128,52.158306],"type":"Point"}
}