{
  "type": "Feature",
  "properties": {
    "iso:country":"NL",
    "sg:address":"Kraneweg 105",
    "sg:city":"Groningen",
    "sg:orig_category":"Kinderopvang Behalve Thuis",
    "sg:phone":"+31 50 589 2468",
    "sg:postcode":"9718 JM",
    "sg:province":"Groningen",
    "wof:name":"Toddler'S",
    "wof:placetype":"venue"
},
  "geometry": {"coordinates":[6.548223,53.21674],"type":"Point"}
}