{
  "type": "Feature",
  "properties": {
    "addr:full":"Dommelstraat 3 Dordrecht South Holland 3313 CK",
    "addr:housenumber":"3",
    "addr:postcode":"3313 ck",
    "addr:street":"Dommelstraat",
    "iso:country":"NL",
    "sg:address":"Dommelstraat 3",
    "sg:city":"Dordrecht",
    "sg:orig_category":"Autokeuringen",
    "sg:phone":"+31 78 631 0278",
    "sg:postcode":"3313 CK",
    "sg:province":"South Holland",
    "wof:name":"A. Schaarman Vof",
    "wof:placetype":"venue"
},
  "geometry": {"coordinates":[4.700188,51.817184],"type":"Point"}
}