{
  "type": "Feature",
  "properties": {
    "iso:country":"NL",
    "sg:address":"Dorpsstraat 65",
    "sg:city":"Hellendoorn",
    "sg:classifiers":[
        {
            "category":"Fast Food",
            "type":"Food & Drink"
        }
    ],
    "sg:phone":"+31 548 655 346",
    "sg:postcode":"7447 CP",
    "sg:province":"NL.08",
    "sg:tags":[
        "afhaal",
        "restaurant"
    ],
    "wof:name":"Restaurant Ying Ping",
    "wof:placetype":"venue"
},
  "geometry": {"coordinates":[6.449287,52.391174],"type":"Point"}
}