{
  "type": "Feature",
  "properties": {
    "addr:full":"Europalaan-Zuid 130 Budel North Brabant 6021 KJ",
    "addr:housenumber":"130",
    "addr:postcode":"6021 kj",
    "addr:street":"Europalaan-Zuid",
    "iso:country":"NL",
    "sg:address":"Europalaan-Zuid 130",
    "sg:city":"Budel",
    "sg:orig_category":"Sportprijzen, Postzegels And Munten",
    "sg:phone":"+31 495 491 032",
    "sg:postcode":"6021 KJ",
    "sg:province":"North Brabant",
    "wof:name":"Sportprijzen Vonken",
    "wof:placetype":"venue"
},
  "geometry": {"coordinates":[5.567187,51.272614],"type":"Point"}
}