{
  "type": "Feature",
  "properties": {
    "addr:full":"Lijsterbesstr 18 Waddinxveen South Holland 2742 XS",
    "addr:housenumber":"18",
    "addr:postcode":"2742 xs",
    "addr:street":"Lijsterbesstr",
    "iso:country":"NL",
    "sg:address":"Lijsterbesstr 18",
    "sg:city":"Waddinxveen",
    "sg:orig_category":"Verenigingsgebouwen",
    "sg:phone":"+31 182 612 276",
    "sg:postcode":"2742 XS",
    "sg:province":"South Holland",
    "sg:website":"http://www.paddestoel.nl.nu",
    "wof:name":"Paddestoel, De",
    "wof:placetype":"venue"
},
  "geometry": {"coordinates":[4.646217,52.042885],"type":"Point"}
}