{
  "type": "Feature",
  "properties": {
    "addr:full":"Zonnedauw 4 Limmen Noord-Holland 1906 HA",
    "addr:housenumber":"4",
    "addr:postcode":"1906 ha",
    "addr:street":"Zonnedauw",
    "iso:country":"NL",
    "sg:address":"Zonnedauw 4",
    "sg:city":"Limmen",
    "sg:orig_category":"Overheidsdiensten",
    "sg:phone":"+31 72 505 1456",
    "sg:postcode":"1906 HA",
    "sg:province":"Noord-Holland",
    "wof:name":"Gemeente Limmen",
    "wof:placetype":"venue"
},
  "geometry": {"coordinates":[4.6987352371,52.5728797913],"type":"Point"}
}