{
  "type": "Feature",
  "properties": {
    "addr:full":"Puteanusstraat 6 Venlo Limburg 5911 EV",
    "addr:housenumber":"6",
    "addr:postcode":"5911 ev",
    "addr:street":"Puteanusstraat",
    "iso:country":"NL",
    "sg:address":"Puteanusstraat 6",
    "sg:city":"Venlo",
    "sg:classifiers":[
        {
            "category":"Travel",
            "subcategory":"Hotels & Motels",
            "type":"Entertainment"
        }
    ],
    "sg:phone":"+31 77 351 5763",
    "sg:postcode":"5911 EV",
    "sg:province":"Limburg",
    "wof:name":"Pension Knapen",
    "wof:placetype":"venue"
},
  "geometry": {"coordinates":[6.170906,51.373295],"type":"Point"}
}