{
  "type": "Feature",
  "properties": {
    "addr:full":"Brusselseln 15 S Gravenhage South Holland 2587 AJ",
    "addr:housenumber":"15",
    "addr:postcode":"2587 aj",
    "addr:street":"Brusselseln;S Gravenhage",
    "iso:country":"NL",
    "sg:address":"Brusselseln 15",
    "sg:city":"S Gravenhage",
    "sg:orig_category":"Verenigingsgebouwen",
    "sg:phone":"+31 70 354 4289",
    "sg:postcode":"2587 AJ",
    "sg:province":"South Holland",
    "wof:name":"Pallandth, Van",
    "wof:placetype":"venue"
},
  "geometry": {"coordinates":[4.29118,52.112942],"type":"Point"}
}