{
  "type": "Feature",
  "properties": {
    "addr:full":"Courbetstr 38 Amsterdam North Holland 1077 ZV",
    "addr:housenumber":"38",
    "addr:postcode":"1077 zv",
    "addr:street":"Courbetstr",
    "iso:country":"NL",
    "sg:address":"Courbetstr 38",
    "sg:city":"Amsterdam",
    "sg:orig_category":"Modellenbureaus En Modellen Freelance",
    "sg:phone":"+31 20 676 2502",
    "sg:postcode":"1077 ZV",
    "sg:province":"North Holland",
    "wof:name":"Agency Yvonne",
    "wof:placetype":"venue"
},
  "geometry": {"coordinates":[4.869548,52.345303],"type":"Point"}
}