{
  "type": "Feature",
  "properties": {
    "addr:full":"Lijnbaanstraat 4 Beneden Leeuwen Gelderland 6658 BW",
    "addr:housenumber":"4",
    "addr:postcode":"6658 bw",
    "addr:street":"Lijnbaanstraat",
    "iso:country":"NL",
    "sg:address":"Lijnbaanstraat 4",
    "sg:city":"Beneden Leeuwen",
    "sg:orig_category":"Loodgieterswerk, Verwarming And Sanitaire Installaties",
    "sg:phone":"+31 487 595 027",
    "sg:postcode":"6658 BW",
    "sg:province":"Gelderland",
    "wof:name":"Janssen",
    "wof:placetype":"venue"
},
  "geometry": {"coordinates":[5.508399,51.88372],"type":"Point"}
}