{
  "type": "Feature",
  "properties": {
    "addr:full":"Granaathof 29 Leiden Zuid-Holland 2332 GZ",
    "addr:housenumber":"29",
    "addr:postcode":"2332 gz",
    "addr:street":"Granaathof",
    "iso:country":"NL",
    "sg:address":"Granaathof 29",
    "sg:city":"Leiden",
    "sg:orig_category":"Kappers",
    "sg:phone":"+31 71 576 3502",
    "sg:postcode":"2332 GZ",
    "sg:province":"Zuid-Holland",
    "wof:name":"Quick Hair Art",
    "wof:placetype":"venue"
},
  "geometry": {"coordinates":[4.466294,52.155884],"type":"Point"}
}