{
  "type": "Feature",
  "properties": {
    "addr:full":"Brugplein 11 Almere Flevoland 1332 BS",
    "addr:housenumber":"11",
    "addr:postcode":"1332 bs",
    "addr:street":"Brugplein;Flevoland",
    "iso:country":"NL",
    "sg:address":"Brugplein 11",
    "sg:city":"Almere",
    "sg:orig_category":"Diverse Bedrijfsinstallaties Gh",
    "sg:phone":"+31 36 549 3200",
    "sg:postcode":"1332 BS",
    "sg:province":"Flevoland",
    "wof:name":"Yanmar Europe Bv",
    "wof:placetype":"venue"
},
  "geometry": {"coordinates":[5.25235,52.407448],"type":"Point"}
}