{
  "type": "Feature",
  "properties": {
    "addr:full":"Laanstr 5 Soest Utrecht 3762 KA",
    "addr:housenumber":"5",
    "addr:postcode":"3762 ka",
    "addr:street":"Laanstr",
    "iso:country":"NL",
    "sg:address":"Laanstr 5",
    "sg:city":"Soest",
    "sg:orig_category":"Plafonds",
    "sg:phone":"+31 35 602 4865",
    "sg:postcode":"3762 KA",
    "sg:province":"Utrecht",
    "wof:name":"Kampen, J Van",
    "wof:placetype":"venue"
},
  "geometry": {"coordinates":[5.276288,52.181503],"type":"Point"}
}