{
  "type": "Feature",
  "properties": {
    "addr:full":"Giessenland 20 Hoornaar Zuid-Holland 4223 MV",
    "addr:housenumber":"20",
    "addr:postcode":"4223 mv",
    "addr:street":"Giessenland",
    "iso:country":"NL",
    "sg:address":"Giessenland 20",
    "sg:city":"Hoornaar",
    "sg:orig_category":"Geluidsinstallaties",
    "sg:phone":"+31 183 581 773",
    "sg:postcode":"4223 MV",
    "sg:province":"Zuid-Holland",
    "sg:website":"http://www.showlight-audio",
    "wof:name":"Showlight & Audio",
    "wof:placetype":"venue"
},
  "geometry": {"coordinates":[4.945262,51.875256],"type":"Point"}
}