{
  "type": "Feature",
  "properties": {
    "iso:country":"NL",
    "sg:address":"Burg Vd Veenwg 18",
    "sg:city":"Ossenzyl",
    "sg:orig_category":"Onderhoudswerken",
    "sg:phone":"+31 561 477 408",
    "sg:postcode":"8376 HL",
    "sg:province":"Overijssel",
    "wof:name":"Wal, Van Der",
    "wof:placetype":"venue"
},
  "geometry": {"coordinates":[5.917435,52.808163],"type":"Point"}
}