{
  "type": "Feature",
  "properties": {
    "addr:full":"Dorpsweg 51 Zijderveld South Holland 4122 GE",
    "addr:housenumber":"51",
    "addr:postcode":"4122",
    "addr:street":"Dorpsweg",
    "iso:country":"NL",
    "sg:address":"Dorpsweg 51",
    "sg:city":"Zijderveld",
    "sg:orig_category":"Goederenvervoer Over De Weg",
    "sg:phone":"+31 345 641 478",
    "sg:postcode":"4122 GE",
    "sg:province":"South Holland",
    "wof:name":"G. Van Gemert",
    "wof:placetype":"venue"
},
  "geometry": {"coordinates":[5.134167,51.938103],"type":"Point"}
}