{
  "type": "Feature",
  "properties": {
    "addr:full":"Sandtlaan 40 Katwijk Zh Zuid-Holland 2223 GG",
    "addr:housenumber":"40",
    "addr:postcode":"2223 gg",
    "addr:street":"Sandtlaan",
    "iso:country":"NL",
    "sg:address":"Sandtlaan 40",
    "sg:city":"Katwijk Zh",
    "sg:orig_category":"Kantoorartikelen",
    "sg:phone":"+31 71 407 7785",
    "sg:postcode":"2223 GG",
    "sg:province":"Zuid-Holland",
    "wof:name":"Multi Meubel",
    "wof:placetype":"venue"
},
  "geometry": {"coordinates":[4.4276518822,52.1904754639],"type":"Point"}
}