{
  "type": "Feature",
  "properties": {
    "addr:full":"H A Lorentzstraat 10 Zwijndrecht Zuid-Holland 3331 EE",
    "addr:housenumber":"10",
    "addr:postcode":"3331 ee",
    "addr:street":"Lorentzstraat",
    "iso:country":"NL",
    "sg:address":"H A Lorentzstraat 10",
    "sg:city":"Zwijndrecht",
    "sg:orig_category":"Kantoor- And Schoolbenodigdheden Gh",
    "sg:phone":"+31 78 620 1010",
    "sg:postcode":"3331 EE",
    "sg:province":"Zuid-Holland",
    "wof:name":"Rotterdamse Papierindustrie Family Cards",
    "wof:placetype":"venue"
},
  "geometry": {"coordinates":[4.6302599907,51.8188209534],"type":"Point"}
}