{
  "type": "Feature",
  "properties": {
    "addr:full":"Peerdsbroek 21 Breda North Brabant 4824 BL",
    "addr:housenumber":"21",
    "addr:postcode":"4824 bl",
    "addr:street":"Peerdsbroek",
    "iso:country":"NL",
    "sg:address":"Peerdsbroek 21",
    "sg:city":"Breda",
    "sg:orig_category":"Loodgieterswerk, Verwarming And Sanitaire Installaties",
    "sg:phone":"+31 76 542 6256",
    "sg:postcode":"4824 BL",
    "sg:province":"North Brabant",
    "wof:name":"M De Nijs",
    "wof:placetype":"venue"
},
  "geometry": {"coordinates":[4.744103,51.600471],"type":"Point"}
}