{
  "type": "Feature",
  "properties": {
    "addr:full":"B Ballotstr 4 Schoondyke Zeeland 4507 DA",
    "addr:housenumber":"4;4507",
    "addr:postcode":"da",
    "addr:street":"Schoondyke Zeeland",
    "iso:country":"NL",
    "sg:address":"B Ballotstr 4",
    "sg:city":"Schoondyke",
    "sg:orig_category":"Bedrijfsopleidingen",
    "sg:phone":"+31 117 406 045",
    "sg:postcode":"4507 DA",
    "sg:province":"Zeeland",
    "wof:name":"Swilion Bv",
    "wof:placetype":"venue"
},
  "geometry": {"coordinates":[3.60312,51.373348],"type":"Point"}
}