{
  "type": "Feature",
  "properties": {
    "addr:full":"Bospln 3 Katwijk Zuid-Holland 2224 GB",
    "addr:housenumber":"3",
    "addr:postcode":"2224 gb",
    "addr:street":"Bospln",
    "iso:country":"NL",
    "sg:address":"Bospln 3",
    "sg:city":"Katwijk",
    "sg:orig_category":"Hoortoestellen",
    "sg:phone":"+31 71 407 4770",
    "sg:postcode":"2224 GB",
    "sg:province":"Zuid-Holland",
    "wof:name":"Strating Katwijk",
    "wof:placetype":"venue"
},
  "geometry": {"coordinates":[4.411159,52.197163],"type":"Point"}
}