{
  "type": "Feature",
  "properties": {
    "addr:full":"Merelhof 4 Bussum Noord-Holland 1403 CX",
    "addr:housenumber":"4",
    "addr:postcode":"1403 cx",
    "addr:street":"Merelhof",
    "iso:country":"NL",
    "sg:address":"Merelhof 4",
    "sg:city":"Bussum",
    "sg:orig_category":"Adviesbureaus",
    "sg:phone":"+31 35 691 2665",
    "sg:postcode":"1403 CX",
    "sg:province":"Noord-Holland",
    "wof:name":"Turk Bv, Robert S",
    "wof:placetype":"venue"
},
  "geometry": {"coordinates":[5.193092,52.271034],"type":"Point"}
}