{
  "type": "Feature",
  "properties": {
    "addr:full":"Stationsstraat 178 Apeldoorn Gelderland 7311 MJ",
    "addr:housenumber":"178",
    "addr:postcode":"7311 mj",
    "addr:street":"Stationsstraat;Gelderland",
    "iso:country":"NL",
    "sg:address":"Stationsstraat 178",
    "sg:city":"Apeldoorn",
    "sg:orig_category":"Banken And Kredietinstellingen",
    "sg:phone":"+31 55 578 5100",
    "sg:postcode":"7311 MJ",
    "sg:province":"Gelderland",
    "wof:name":"Postkantoor",
    "wof:placetype":"venue"
},
  "geometry": {"coordinates":[5.965289,52.215668],"type":"Point"}
}