{
  "type": "Feature",
  "properties": {
    "addr:full":"Nieuwe Blaricummerweg 36 Huizen Noord-Holland 1272 RL",
    "addr:housenumber":"36",
    "addr:postcode":"1272 rl",
    "addr:street":"Nieuwe Blaricummerweg",
    "iso:country":"NL",
    "sg:address":"Nieuwe Blaricummerweg 36",
    "sg:city":"Huizen",
    "sg:orig_category":"Hoger Onderwijs",
    "sg:phone":"+31 35 693 3510",
    "sg:postcode":"1272 RL",
    "sg:province":"Noord-Holland",
    "wof:name":"L H Smits-Bom",
    "wof:placetype":"venue"
},
  "geometry": {"coordinates":[5.196618,52.272987],"type":"Point"}
}