{
  "type": "Feature",
  "properties": {
    "iso:country":"NL",
    "sg:address":"J V Nassaustr 21",
    "sg:city":"S Gravenhage",
    "sg:orig_category":"Bedrijfsopleidingen",
    "sg:phone":"+31 70 324 8613",
    "sg:postcode":"2596 BL",
    "sg:province":"South Holland",
    "sg:website":"http://www.imtnederland.nl",
    "wof:name":"Imt Ned Bv",
    "wof:placetype":"venue"
},
  "geometry": {"coordinates":[4.31846,52.093311],"type":"Point"}
}