{
  "type": "Feature",
  "properties": {
    "addr:full":"Oostpolderwg 1S Krabbendyke Zeeland 4413 NN",
    "addr:housenumber":"1s",
    "addr:postcode":"4413 nn",
    "addr:street":"Oostpolderwg;Zeeland",
    "iso:country":"NL",
    "sg:address":"Oostpolderwg 1S",
    "sg:city":"Krabbendyke",
    "sg:orig_category":"Orgels",
    "sg:phone":"+31 113 503 523",
    "sg:postcode":"4413 NN",
    "sg:province":"Zeeland",
    "wof:name":"Stolk Bv",
    "wof:placetype":"venue"
},
  "geometry": {"coordinates":[4.1277489662,51.4277610779],"type":"Point"}
}