{
  "type": "Feature",
  "properties": {
    "iso:country":"NL",
    "sg:address":"Amundsenweg 1",
    "sg:city":"Amsterdam",
    "sg:classifiers":[
        {
            "category":"Education",
            "subcategory":"Preschool",
            "type":"Public Place"
        }
    ],
    "sg:phone":"+31 20 683 1354",
    "sg:postcode":"1056 AS",
    "sg:province":"North Holland",
    "sg:tags":[
        "kleuteronderwijs",
        "basis-"
    ],
    "wof:name":"Basisschool El Amien",
    "wof:placetype":"venue"
},
  "geometry": {"coordinates":[4.845258,52.374043],"type":"Point"}
}