{
  "type": "Feature",
  "properties": {
    "addr:full":"Kleibultweg 31 Oldenzaal Overijssel 7575 BM",
    "addr:housenumber":"31",
    "addr:postcode":"7575 bm",
    "addr:street":"Kleibultweg",
    "iso:country":"NL",
    "sg:address":"Kleibultweg 31",
    "sg:city":"Oldenzaal",
    "sg:orig_category":"Meubelzaken, Woning- And Keukeninrichting",
    "sg:phone":"+31 541 516 820",
    "sg:postcode":"7575 BM",
    "sg:province":"Overijssel",
    "wof:name":"Smellink Wonen En Design Bv",
    "wof:placetype":"venue"
},
  "geometry": {"coordinates":[6.925529,52.29372],"type":"Point"}
}