{
  "type": "Feature",
  "properties": {
    "iso:country":"NL",
    "sg:address":"Burg V Oppenstr 107",
    "sg:city":"Maastricht",
    "sg:orig_category":"Kappers",
    "sg:phone":"+31 43 363 9175",
    "sg:postcode":"6224 ER",
    "sg:province":"Limburg",
    "wof:name":"Soigneur, De",
    "wof:placetype":"venue"
},
  "geometry": {"coordinates":[5.71167,50.850868],"type":"Point"}
}