{
  "type": "Feature",
  "properties": {
    "iso:country":"NL",
    "sg:address":"Pipeluurseweg 10",
    "sg:city":"Olburgen",
    "sg:orig_category":"Verhuur Huishoudartikelen",
    "sg:phone":"+31 575 452 656",
    "sg:postcode":"7225 ND",
    "sg:province":"Gelderland",
    "wof:name":"De Beach",
    "wof:placetype":"venue"
},
  "geometry": {"coordinates":[6.13698,52.042339],"type":"Point"}
}