{
  "type": "Feature",
  "properties": {
    "iso:country":"NL",
    "sg:address":"Hoofdstraat 60",
    "sg:city":"Terborg",
    "sg:orig_category":"Kappers",
    "sg:phone":"+31 315 327 893",
    "sg:postcode":"7061 CL",
    "sg:province":"Gelderland",
    "wof:name":"Dames- En Herenkapsalon Maluc",
    "wof:placetype":"venue"
},
  "geometry": {"coordinates":[6.3582348824,51.9194145203],"type":"Point"}
}