{
  "type": "Feature",
  "properties": {
    "addr:full":"Den Hoekstraat 4 Stein Lb Missouri 6171 VZ",
    "addr:housenumber":"4",
    "addr:postcode":"6171 vz",
    "addr:street":"Den Hoekstraat",
    "iso:country":"NL",
    "sg:address":"Den Hoekstraat 4",
    "sg:city":"Stein Lb",
    "sg:orig_category":"Glaszetten",
    "sg:phone":"+31 46 433 8143",
    "sg:postcode":"6171 VZ",
    "sg:province":"Missouri",
    "wof:name":"Glas Service Stein",
    "wof:placetype":"venue"
},
  "geometry": {"coordinates":[-93.129936,36.705662],"type":"Point"}
}