{
  "type": "Feature",
  "properties": {
    "addr:full":"Kl Frankryk 23 Goes Zeeland 4461 ZN",
    "addr:housenumber":"23",
    "addr:postcode":"4461 zn",
    "iso:country":"NL",
    "sg:address":"Kl Frankryk 23",
    "sg:city":"Goes",
    "sg:classifiers":[
        {
            "category":"Retail",
            "subcategory":"Auto Repair",
            "type":"Services"
        }
    ],
    "sg:phone":"+31 113 228 751",
    "sg:postcode":"4461 ZN",
    "sg:province":"Zeeland",
    "sg:tags":[
        "garage"
    ],
    "wof:name":"Vliet Bv, Van Der",
    "wof:placetype":"venue"
},
  "geometry": {"coordinates":[-83.914169,39.768833],"type":"Point"}
}