{
  "type": "Feature",
  "properties": {
    "addr:full":"Kallenkoterallee 80 Steenwijk NL.08 8331 AJ",
    "addr:housenumber":"80;nl.08",
    "addr:postcode":"8331 aj",
    "addr:street":"Kallenkoterallee",
    "iso:country":"NL",
    "sg:address":"Kallenkoterallee 80",
    "sg:city":"Steenwijk",
    "sg:orig_category":"Loodgieterswerk, Verwarming And Sanitaire Installaties",
    "sg:phone":"+31 521 514 890",
    "sg:postcode":"8331 AJ",
    "sg:province":"NL.08",
    "wof:name":"Geyserverhuur J. Van Dijk",
    "wof:placetype":"venue"
},
  "geometry": {"coordinates":[6.142228,52.785316],"type":"Point"}
}