{
  "type": "Feature",
  "properties": {
    "iso:country":"NL",
    "sg:address":"Warmeerweg 2",
    "sg:city":"Emmen",
    "sg:classifiers":[
        {
            "category":"Communications",
            "subcategory":"Television Station",
            "type":"Services"
        }
    ],
    "sg:phone":"+31 591 649 890",
    "sg:postcode":"7815 HG",
    "sg:province":"Provincie Drenthe",
    "sg:tags":[
        "video",
        "audio",
        "verhuur"
    ],
    "wof:name":"Videotheek 'T Emmermeertje",
    "wof:placetype":"venue"
},
  "geometry": {"coordinates":[6.899549,52.796257],"type":"Point"}
}