{
  "type": "Feature",
  "properties": {
    "addr:full":"Wethouder Nijhuisstraat 31 Enschede Overijssel 7545 NA",
    "addr:housenumber":"31",
    "addr:postcode":"7545 na",
    "addr:street":"Wethouder Nijhuisstraat",
    "iso:country":"NL",
    "sg:address":"Wethouder Nijhuisstraat 31",
    "sg:city":"Enschede",
    "sg:orig_category":"Autokeuringen",
    "sg:phone":"+31 53 431 6630",
    "sg:postcode":"7545 NA",
    "sg:province":"Overijssel",
    "wof:name":"Vof Autobedrijf Termijtelen",
    "wof:placetype":"venue"
},
  "geometry": {"coordinates":[6.863153,52.217201],"type":"Point"}
}