{
  "type": "Feature",
  "properties": {
    "addr:full":"Dorpsstr 27 Lage Zwaluwe North Brabant 4926 CP",
    "addr:housenumber":"27",
    "addr:postcode":"4926 cp",
    "addr:street":"Dorpsstr",
    "iso:country":"NL",
    "sg:address":"Dorpsstr 27",
    "sg:city":"Lage Zwaluwe",
    "sg:orig_category":"Grafisch Ontwerpers",
    "sg:phone":"+31 168 484 818",
    "sg:postcode":"4926 CP",
    "sg:province":"North Brabant",
    "wof:name":"Jena Producties",
    "wof:placetype":"venue"
},
  "geometry": {"coordinates":[4.708871,51.707172],"type":"Point"}
}