{
  "type": "Feature",
  "properties": {
    "addr:full":"Jericholaan 52B Rotterdam Zuid-Holland 3061 HH",
    "addr:housenumber":"52b",
    "addr:postcode":"3061 hh",
    "addr:street":"Jericholaan",
    "iso:country":"NL",
    "sg:address":"Jericholaan 52B",
    "sg:city":"Rotterdam",
    "sg:orig_category":"Binnenhuisarchitecten",
    "sg:phone":"+31 10 452 5958",
    "sg:postcode":"3061 HH",
    "sg:province":"Zuid-Holland",
    "wof:name":"Kuyken Interieurstudio",
    "wof:placetype":"venue"
},
  "geometry": {"coordinates":[4.506975,51.93045],"type":"Point"}
}