{
  "type": "Feature",
  "properties": {
    "addr:full":"Smedenstr 32 Deventer NL.08 7411 RD",
    "addr:housenumber":"32;nl.08",
    "addr:postcode":"7411 rd",
    "addr:street":"Smedenstr",
    "iso:country":"NL",
    "sg:address":"Smedenstr 32",
    "sg:city":"Deventer",
    "sg:orig_category":"Bloemen En Planten",
    "sg:phone":"+31 570 612 035",
    "sg:postcode":"7411 RD",
    "sg:province":"NL.08",
    "wof:name":"Bloomstyle",
    "wof:placetype":"venue"
},
  "geometry": {"coordinates":[6.157381,52.255074],"type":"Point"}
}