{
  "type": "Feature",
  "properties": {
    "iso:country":"NL",
    "sg:address":"Hoofdstraat 9",
    "sg:city":"Borger",
    "sg:orig_category":"Overheidsdiensten",
    "sg:phone":"+31 599 235 194",
    "sg:postcode":"9531 AA",
    "sg:province":"Drenthe",
    "wof:name":"Het Anker",
    "wof:placetype":"venue"
},
  "geometry": {"coordinates":[6.7898278236,52.9265441895],"type":"Point"}
}