{
  "type": "Feature",
  "properties": {
    "addr:full":"Beukenwg 33 Amsterdam Noord-Holland 1092 AZ",
    "addr:housenumber":"33",
    "addr:postcode":"1092 az",
    "addr:street":"Beukenwg",
    "iso:country":"NL",
    "sg:address":"Beukenwg 33",
    "sg:city":"Amsterdam",
    "sg:orig_category":"Fietsen En Bromfietsen",
    "sg:phone":"+31 20 665 5930",
    "sg:postcode":"1092 AZ",
    "sg:province":"Noord-Holland",
    "wof:name":"Harry",
    "wof:placetype":"venue"
},
  "geometry": {"coordinates":[4.919027,52.356033],"type":"Point"}
}