{
  "type": "Feature",
  "properties": {
    "iso:country":"NL",
    "sg:address":"Koninginneln 20A",
    "sg:city":"Groningen",
    "sg:orig_category":"Verenigingen En Stichtingen",
    "sg:phone":"+31 50 313 4628",
    "sg:postcode":"9717 BV",
    "sg:province":"Groningen",
    "wof:name":"Aepke",
    "wof:placetype":"venue"
},
  "geometry": {"coordinates":[6.550433,53.221848],"type":"Point"}
}