{
  "type": "Feature",
  "properties": {
    "addr:full":"L De Colignystr 37 Schiedam South Holland 3116 EH",
    "addr:housenumber":"37",
    "addr:postcode":"3116 eh",
    "addr:street":"L",
    "iso:country":"NL",
    "sg:address":"L De Colignystr 37",
    "sg:city":"Schiedam",
    "sg:orig_category":"Vertaalbureaus",
    "sg:phone":"+31 10 273 2639",
    "sg:postcode":"3116 EH",
    "sg:province":"South Holland",
    "wof:name":"Eggheads Inc",
    "wof:placetype":"venue"
},
  "geometry": {"coordinates":[4.395985,51.909424],"type":"Point"}
}