{
  "type": "Feature",
  "properties": {
    "iso:country":"NL",
    "sg:address":"Tasveld 28",
    "sg:city":"Montfoort",
    "sg:orig_category":"Diverse Bedrijfsinstallaties Gh",
    "sg:phone":"+31 348 471 813",
    "sg:postcode":"3417 XS",
    "sg:province":"Utrecht",
    "wof:name":"Handelsonderneming C. De Bruin Bv",
    "wof:placetype":"venue"
},
  "geometry": {"coordinates":[4.931334,52.044636],"type":"Point"}
}