{
  "type": "Feature",
  "properties": {
    "iso:country":"NL",
    "sg:address":"Vlietlaan 32",
    "sg:city":"Rotterdam",
    "sg:classifiers":[
        {
            "category":"Retail",
            "subcategory":"Photofinishing",
            "type":"Services"
        }
    ],
    "sg:phone":"+31 10 452 1184",
    "sg:postcode":"3061 DX",
    "sg:province":"Zuid-Holland",
    "sg:tags":[
        "foto",
        "film"
    ],
    "wof:name":"Foto Wolf",
    "wof:placetype":"venue"
},
  "geometry": {"coordinates":[4.502849,51.929565],"type":"Point"}
}