{
  "type": "Feature",
  "properties": {
    "iso:country":"NL",
    "sg:address":"Weidestraat 2",
    "sg:city":"Rosmalen",
    "sg:orig_category":"Woningbouwverenigingen",
    "sg:phone":"+31 73 521 9025",
    "sg:postcode":"5241 CB",
    "sg:province":"Noord-Brabant",
    "wof:name":"Woningstichting De Kleine Meierij",
    "wof:placetype":"venue"
},
  "geometry": {"coordinates":[5.3585968018,51.7134284973],"type":"Point"}
}