{
  "type": "Feature",
  "properties": {
    "addr:full":"Zuiderhoofdstr 22 Krommenie North Holland 1561 AL",
    "addr:housenumber":"22",
    "addr:postcode":"1561 al",
    "addr:street":"Zuiderhoofdstr",
    "iso:country":"NL",
    "sg:address":"Zuiderhoofdstr 22",
    "sg:city":"Krommenie",
    "sg:orig_category":"Fotozaken",
    "sg:phone":"+31 75 628 1853",
    "sg:postcode":"1561 AL",
    "sg:province":"North Holland",
    "wof:name":"Veer, W Van De",
    "wof:placetype":"venue"
},
  "geometry": {"coordinates":[4.767428,52.497276],"type":"Point"}
}