{
  "type": "Feature",
  "properties": {
    "addr:full":"Spykse Kweldk 94 Spyk Gem Lingewaal Gelderland 4211 CX",
    "addr:housenumber":"94",
    "addr:postcode":"4211 cx",
    "addr:street":"Spyk Gem",
    "iso:country":"NL",
    "sg:address":"Spykse Kweldk 94",
    "sg:city":"Spyk Gem Lingewaal",
    "sg:orig_category":"Scholen Voor Basisonderwijs",
    "sg:phone":"+31 183 563 784",
    "sg:postcode":"4211 CX",
    "sg:province":"Gelderland",
    "wof:name":"Hoeksteen Chr, De",
    "wof:placetype":"venue"
},
  "geometry": {"coordinates":[5.01184,51.856461],"type":"Point"}
}