{
  "type": "Feature",
  "properties": {
    "iso:country":"NL",
    "sg:address":"Eewal 13",
    "sg:city":"Burdaard",
    "sg:orig_category":"Schilderwerk",
    "sg:phone":"+31 519 332 327",
    "sg:postcode":"9112 HA",
    "sg:province":"Friesland",
    "wof:name":"Firma G. Visser Schildersbedrijf",
    "wof:placetype":"venue"
},
  "geometry": {"coordinates":[5.879193,53.294254],"type":"Point"}
}