{
  "type": "Feature",
  "properties": {
    "iso:country":"NL",
    "sg:address":"Leliegracht 12",
    "sg:city":"Amsterdam",
    "sg:orig_category":"Schoenen",
    "sg:phone":"+31 20 622 6645",
    "sg:postcode":"1015 DE",
    "sg:province":"Noord-Holland",
    "wof:name":"Big Shoe (Marjan Kouw)",
    "wof:placetype":"venue"
},
  "geometry": {"coordinates":[4.887318,52.375183],"type":"Point"}
}