{
  "type": "Feature",
  "properties": {
    "addr:full":"Residentie Azuree 18 Teteringen Noord-Brabant 4847 JA",
    "addr:housenumber":"18",
    "addr:postcode":"4847 ja",
    "iso:country":"NL",
    "sg:address":"Residentie Azuree 18",
    "sg:city":"Teteringen",
    "sg:orig_category":"Metaalbewerking",
    "sg:phone":"+31 76 581 1548",
    "sg:postcode":"4847 JA",
    "sg:province":"Noord-Brabant",
    "wof:name":"Llamas Frias",
    "wof:placetype":"venue"
},
  "geometry": {"coordinates":[4.816916,51.610752],"type":"Point"}
}