{
  "type": "Feature",
  "properties": {
    "addr:full":"Bospolderstraat 73 Nieuwerkerk Ad Ijssel Zuid-Holland 2912 PC",
    "addr:housenumber":"73",
    "addr:postcode":"ijssel;2912 pc",
    "addr:street":"Bospolderstraat",
    "iso:country":"NL",
    "sg:address":"Bospolderstraat 73",
    "sg:city":"Nieuwerkerk Ad Ijssel",
    "sg:orig_category":"Goederenvervoer Over De Weg",
    "sg:phone":"+31 180 312 347",
    "sg:postcode":"2912 PC",
    "sg:province":"Zuid-Holland",
    "wof:name":"Thema Transport",
    "wof:placetype":"venue"
},
  "geometry": {"coordinates":[4.611897,51.965008],"type":"Point"}
}