{
  "type": "Feature",
  "properties": {
    "addr:full":"B Ballotstr 40 Den Helder Noord-Holland 1782 HK",
    "addr:housenumber":"40",
    "addr:postcode":"1782 hk",
    "iso:country":"NL",
    "sg:address":"B Ballotstr 40",
    "sg:city":"Den Helder",
    "sg:orig_category":"Ontbijtservice",
    "sg:phone":"+31 223 625 721",
    "sg:postcode":"1782 HK",
    "sg:province":"Noord-Holland",
    "wof:name":"Lunchtime",
    "wof:placetype":"venue"
},
  "geometry": {"coordinates":[4.757596,52.955284],"type":"Point"}
}