{
  "type": "Feature",
  "properties": {
    "addr:full":"Schelmaatstraat 19A Oldenzaal Overijssel 7575 BC",
    "addr:housenumber":"19a",
    "addr:postcode":"7575 bc",
    "addr:street":"Schelmaatstraat",
    "iso:country":"NL",
    "sg:address":"Schelmaatstraat 19A",
    "sg:city":"Oldenzaal",
    "sg:orig_category":"Geluidsinstallaties - Verhuur",
    "sg:phone":"+31 541 532 944",
    "sg:postcode":"7575 BC",
    "sg:province":"Overijssel",
    "wof:name":"Zombie Sound",
    "wof:placetype":"venue"
},
  "geometry": {"coordinates":[6.927172,52.297821],"type":"Point"}
}