{
  "type": "Feature",
  "properties": {
    "addr:full":"Geerdinkhof 623 Amsterdam Zuidoost North Holland 1103 RM",
    "addr:housenumber":"623",
    "addr:postcode":"1103 rm",
    "addr:street":"Geerdinkhof",
    "iso:country":"NL",
    "sg:address":"Geerdinkhof 623",
    "sg:city":"Amsterdam Zuidoost",
    "sg:orig_category":"Koeriersdiensten",
    "sg:phone":"+31 20 698 0733",
    "sg:postcode":"1103 RM",
    "sg:province":"North Holland",
    "wof:name":"J.F.M. De Boer",
    "wof:placetype":"venue"
},
  "geometry": {"coordinates":[4.979265,52.326469],"type":"Point"}
}