{
  "type": "Feature",
  "properties": {
    "iso:country":"NL",
    "sg:address":"Ten Culen 6",
    "sg:city":"Helmond",
    "sg:orig_category":"Fitnesscentra",
    "sg:phone":"+31 492 537 934",
    "sg:postcode":"5706 MC",
    "sg:province":"Noord-Brabant",
    "wof:name":"Ki-Aikidosch Torii",
    "wof:placetype":"venue"
},
  "geometry": {"coordinates":[5.639169,51.457497],"type":"Point"}
}