{
  "type": "Feature",
  "properties": {
    "iso:country":"NL",
    "sg:address":"Egeldonk 40",
    "sg:city":"Amsterdam Zuidoost",
    "sg:orig_category":"Hulpverlening Sociaal",
    "sg:phone":"+31 20 690 7958",
    "sg:postcode":"1103 AK",
    "sg:province":"Noord-Holland",
    "wof:name":"Service Platform Amsterdam, Sticht",
    "wof:placetype":"venue"
},
  "geometry": {"coordinates":[4.966019,52.326591],"type":"Point"}
}