{
  "type": "Feature",
  "properties": {
    "addr:full":"Vissersdk 19 Winschoten Groningen 9671 EG",
    "addr:housenumber":"19",
    "addr:postcode":"9671 eg",
    "addr:street":"Vissersdk",
    "iso:country":"NL",
    "sg:address":"Vissersdk 19",
    "sg:city":"Winschoten",
    "sg:classifiers":[
        {
            "category":"Professional",
            "subcategory":"Accounting & Tax Preparation",
            "type":"Services"
        }
    ],
    "sg:phone":"+31 597 413 998",
    "sg:postcode":"9671 EG",
    "sg:province":"Groningen",
    "sg:tags":[
        "accountant",
        "en",
        "-kantoren",
        "register-"
    ],
    "sg:website":"http://www.ey.nl",
    "wof:name":"Ernst & Young",
    "wof:placetype":"venue"
},
  "geometry": {"coordinates":[7.037352,53.142612],"type":"Point"}
}