{
  "type": "Feature",
  "properties": {
    "addr:full":"Nieuwelandstraat 12 Ommen Overijssel 7731 TH",
    "addr:housenumber":"12",
    "addr:postcode":"7731 th",
    "addr:street":"Nieuwelandstraat",
    "iso:country":"NL",
    "sg:address":"Nieuwelandstraat 12",
    "sg:city":"Ommen",
    "sg:orig_category":"Fitnesscentra",
    "sg:phone":"+31 529 454 508",
    "sg:postcode":"7731 TH",
    "sg:province":"Overijssel",
    "wof:name":"Sport Plaza",
    "wof:placetype":"venue"
},
  "geometry": {"coordinates":[6.431627,52.526768],"type":"Point"}
}