{
  "type": "Feature",
  "properties": {
    "iso:country":"NL",
    "sg:address":"De Geitenhoef 2",
    "sg:city":"Goirle",
    "sg:orig_category":"Kantinebeheer",
    "sg:phone":"+31 6 54315818",
    "sg:postcode":"5051 JZ",
    "sg:province":"North Brabant",
    "sg:website":"http://www.ltcgoirle.nl",
    "wof:name":"Rdr",
    "wof:placetype":"venue"
},
  "geometry": {"coordinates":[5.0678877831,51.5186233521],"type":"Point"}
}