{
  "type": "Feature",
  "properties": {
    "addr:full":"Utrechtsewg 323 De Bilt Utrecht 3731 GA",
    "addr:housenumber":"323",
    "addr:postcode":"3731 ga",
    "iso:country":"NL",
    "sg:address":"Utrechtsewg 323",
    "sg:city":"De Bilt",
    "sg:orig_category":"Vertaalbureaus",
    "sg:phone":"+31 30 220 2624",
    "sg:postcode":"3731 GA",
    "sg:province":"Utrecht",
    "wof:name":"Techtra Ned Bv",
    "wof:placetype":"venue"
},
  "geometry": {"coordinates":[5.171799,52.101803],"type":"Point"}
}