{
  "type": "Feature",
  "properties": {
    "iso:country":"NL",
    "sg:address":"Eind 12B",
    "sg:city":"Nederweert Eind",
    "sg:orig_category":"Lpg-Installaties",
    "sg:phone":"+31 495 631 462",
    "sg:postcode":"6034 SN",
    "sg:province":"Limburg",
    "wof:name":"Nieuwenhoven, Van",
    "wof:placetype":"venue"
},
  "geometry": {"coordinates":[5.773951,51.275253],"type":"Point"}
}