{
  "type": "Feature",
  "properties": {
    "addr:full":"Grote Noord 16 Hoorn Nh Noord-Holland 1621 KJ",
    "addr:housenumber":"16",
    "addr:postcode":"1621 kj",
    "addr:street":"Grote Noord",
    "iso:country":"NL",
    "sg:address":"Grote Noord 16",
    "sg:city":"Hoorn Nh",
    "sg:orig_category":"Meubelzaken, Woning- And Keukeninrichting",
    "sg:phone":"+31 229 214 072",
    "sg:postcode":"1621 KJ",
    "sg:province":"Noord-Holland",
    "wof:name":"Haring Meubelen Bv",
    "wof:placetype":"venue"
},
  "geometry": {"coordinates":[5.05848,52.639908],"type":"Point"}
}