{
  "type": "Feature",
  "properties": {
    "iso:country":"NL",
    "sg:address":"Marktveld 10A",
    "sg:city":"Vught",
    "sg:classifiers":[
        {
            "category":"Communications",
            "subcategory":"Television Station",
            "type":"Services"
        }
    ],
    "sg:phone":"+31 73 656 9111",
    "sg:postcode":"5261 EB",
    "sg:province":"North Brabant",
    "sg:tags":[
        "video",
        "audio",
        "verhuur"
    ],
    "wof:name":"Filmclub Vught",
    "wof:placetype":"venue"
},
  "geometry": {"coordinates":[5.300628,51.659145],"type":"Point"}
}