{
  "type": "Feature",
  "properties": {
    "iso:country":"NL",
    "sg:address":"Livingstoneln 752",
    "sg:city":"Utrecht",
    "sg:orig_category":"Administratie- En Boekhoudkantoren",
    "sg:phone":"+31 30 288 1001",
    "sg:postcode":"3526 JJ",
    "sg:province":"Utrecht",
    "sg:website":"http://www.flantua.nl",
    "wof:name":"Flantua",
    "wof:placetype":"venue"
},
  "geometry": {"coordinates":[5.100735,52.069023],"type":"Point"}
}