{
  "type": "Feature",
  "properties": {
    "addr:full":"Grt Beer 3 Hoorn Nh Noord-Holland 1622 ES",
    "addr:housenumber":"3",
    "addr:postcode":"1622 es",
    "addr:street":"Beer",
    "iso:country":"NL",
    "sg:address":"Grt Beer 3",
    "sg:city":"Hoorn Nh",
    "sg:orig_category":"Bibliotheken En Leeszalen Openbare",
    "sg:phone":"+31 229 219 953",
    "sg:postcode":"1622 ES",
    "sg:province":"Noord-Holland",
    "sg:website":"http://www.bibliotheekhoorn.nl",
    "wof:name":"Bibliotheek Hoorn",
    "wof:placetype":"venue"
},
  "geometry": {"coordinates":[5.037234,52.639194],"type":"Point"}
}