{
  "type": "Feature",
  "properties": {
    "addr:full":"Meyerygaarde 11 Veghel Noord-Brabant 5461 KA",
    "addr:housenumber":"11",
    "addr:postcode":"5461 ka",
    "addr:street":"Meyerygaarde",
    "iso:country":"NL",
    "sg:address":"Meyerygaarde 11",
    "sg:city":"Veghel",
    "sg:orig_category":"Kappers",
    "sg:phone":"+31 413 377 523",
    "sg:postcode":"5461 KA",
    "sg:province":"Noord-Brabant",
    "wof:name":"Dymphie",
    "wof:placetype":"venue"
},
  "geometry": {"coordinates":[5.5417499542,51.6172218323],"type":"Point"}
}