{
  "type": "Feature",
  "properties": {
    "addr:full":"T Plein 2 Leusden Utrecht 3831 CR",
    "addr:housenumber":"2",
    "addr:postcode":"3831 cr",
    "addr:street":"T Plein",
    "iso:country":"NL",
    "sg:address":"T Plein 2",
    "sg:city":"Leusden",
    "sg:orig_category":"Bloemen And Planten",
    "sg:phone":"+31 33 494 5094",
    "sg:postcode":"3831 CR",
    "sg:province":"Utrecht",
    "wof:name":"C1000",
    "wof:placetype":"venue"
},
  "geometry": {"coordinates":[5.427746,52.128963],"type":"Point"}
}