{
  "type": "Feature",
  "properties": {
    "addr:full":"Geesterduin 69 Castricum Noord-Holland 1902 EJ",
    "addr:housenumber":"69",
    "addr:postcode":"1902 ej",
    "addr:street":"Geesterduin",
    "iso:country":"NL",
    "sg:address":"Geesterduin 69",
    "sg:city":"Castricum",
    "sg:classifiers":[
        {
            "category":"Fast Food",
            "type":"Food & Drink"
        }
    ],
    "sg:phone":"+31 251 655 309",
    "sg:postcode":"1902 EJ",
    "sg:province":"Noord-Holland",
    "sg:tags":[
        "afhaal",
        "restaurant"
    ],
    "wof:name":"Vof Snackbar Geesterduin",
    "wof:placetype":"venue"
},
  "geometry": {"coordinates":[4.673885,52.549564],"type":"Point"}
}