{
  "type": "Feature",
  "properties": {
    "addr:full":"Louis Couperusstraat 53 Gemert North Brabant 5421 RM",
    "addr:housenumber":"53",
    "addr:postcode":"5421 rm",
    "addr:street":"Louis Couperusstraat",
    "iso:country":"NL",
    "sg:address":"Louis Couperusstraat 53",
    "sg:city":"Gemert",
    "sg:orig_category":"Begrafenisondernemers",
    "sg:phone":"+31 492 363 089",
    "sg:postcode":"5421 RM",
    "sg:province":"North Brabant",
    "wof:name":"Gravendienst A.C. Van Der Burgt",
    "wof:placetype":"venue"
},
  "geometry": {"coordinates":[5.684926,51.563168],"type":"Point"}
}