{
  "type": "Feature",
  "properties": {
    "addr:full":"Schiedamsewg 55 Vlaardingen South Holland 3134 BB",
    "addr:housenumber":"55",
    "addr:postcode":"3134 bb",
    "addr:street":"Schiedamsewg",
    "iso:country":"NL",
    "sg:address":"Schiedamsewg 55",
    "sg:city":"Vlaardingen",
    "sg:orig_category":"Parketvloeren",
    "sg:phone":"+31 10 435 4146",
    "sg:postcode":"3134 BB",
    "sg:province":"South Holland",
    "wof:name":"Rubo",
    "wof:placetype":"venue"
},
  "geometry": {"coordinates":[4.347977,51.909435],"type":"Point"}
}