{
  "type": "Feature",
  "properties": {
    "iso:country":"NL",
    "sg:address":"Havensingel 67",
    "sg:city":"Den Bosch",
    "sg:orig_category":"Meubeltextiel Fab",
    "sg:phone":"+31 73 613 0836",
    "sg:postcode":"5211 TZ",
    "sg:province":"North Brabant",
    "wof:name":"Zeilmakerij M. Van Der Werff",
    "wof:placetype":"venue"
},
  "geometry": {"coordinates":[5.29824,51.69075],"type":"Point"}
}