{
  "type": "Feature",
  "properties": {
    "iso:country":"NL",
    "sg:address":"Dr J Mulderstraat 9 A",
    "sg:city":"Zaandijk",
    "sg:orig_category":"Fietshandelaren",
    "sg:phone":"+31 75 622 4520",
    "sg:postcode":"1544 VA",
    "sg:province":"Noord-Holland",
    "wof:name":"P. Molenaar",
    "wof:placetype":"venue"
},
  "geometry": {"coordinates":[4.802182,52.470387],"type":"Point"}
}