{
  "type": "Feature",
  "properties": {
    "addr:full":"Hofstad 2 S Hertogenbosch Noord-Brabant 5211 RD",
    "addr:housenumber":"2",
    "addr:postcode":"5211 rd",
    "addr:street":"Hofstad",
    "iso:country":"NL",
    "sg:address":"Hofstad 2",
    "sg:city":"S Hertogenbosch",
    "sg:orig_category":"Verenigingsgebouwen",
    "sg:phone":"+31 73 612 3444",
    "sg:postcode":"5211 RD",
    "sg:province":"Noord-Brabant",
    "wof:name":"Don Bosco",
    "wof:placetype":"venue"
},
  "geometry": {"coordinates":[5.315301,51.689484],"type":"Point"}
}