{
  "type": "Feature",
  "properties": {
    "iso:country":"NL",
    "sg:address":"Willem 2 Sngl 39",
    "sg:city":"Roermond",
    "sg:orig_category":"Hulpverlening Sociaal",
    "sg:phone":"+31 475 319 747",
    "sg:postcode":"6041 HR",
    "sg:province":"Limburg",
    "wof:name":"Cad Midden Limburg",
    "wof:placetype":"venue"
},
  "geometry": {"coordinates":[5.991407,51.190006],"type":"Point"}
}