{
  "type": "Feature",
  "properties": {
    "addr:full":"Hoendiepskade 6 Groningen Groningen 9718 BD",
    "addr:housenumber":"6",
    "addr:postcode":"9718 bd",
    "addr:street":"Hoendiepskade",
    "iso:country":"NL",
    "sg:address":"Hoendiepskade 6",
    "sg:city":"Groningen",
    "sg:orig_category":"Kinderopvang Behalve Thuis",
    "sg:phone":"+31 50 313 1837",
    "sg:postcode":"9718 BD",
    "sg:province":"Groningen",
    "wof:name":"Boddaertcentrum De Bolder Dagbehandeling Voor Kind",
    "wof:placetype":"venue"
},
  "geometry": {"coordinates":[6.556103,53.215801],"type":"Point"}
}