{
  "type": "Feature",
  "properties": {
    "addr:full":"Huserstr 6 Nykerk Gld Gelderland 3861 CK",
    "addr:housenumber":"6",
    "addr:postcode":"3861 ck",
    "addr:street":"Huserstr;Gld Gelderland",
    "iso:country":"NL",
    "sg:address":"Huserstr 6",
    "sg:city":"Nykerk Gld",
    "sg:orig_category":"Bejaarden - Verzorgingstehuizen",
    "sg:phone":"+31 33 245 3147",
    "sg:postcode":"3861 CK",
    "sg:province":"Gelderland",
    "wof:name":"Jozef, St",
    "wof:placetype":"venue"
},
  "geometry": {"coordinates":[5.4831,52.221569],"type":"Point"}
}