{
  "type": "Feature",
  "properties": {
    "addr:full":"De Helster 62 Elst Gld Gelderland 6661 AK",
    "addr:housenumber":"62",
    "addr:postcode":"6661 ak",
    "addr:street":"De Helster;Gld Gelderland",
    "iso:country":"NL",
    "sg:address":"De Helster 62",
    "sg:city":"Elst Gld",
    "sg:orig_category":"Elektronische Informatie- Systemen Off-Line",
    "sg:phone":"+31 481 375 229",
    "sg:postcode":"6661 AK",
    "sg:province":"Gelderland",
    "wof:name":"Complan",
    "wof:placetype":"venue"
},
  "geometry": {"coordinates":[5.850136,51.927597],"type":"Point"}
}