{
  "type": "Feature",
  "properties": {
    "addr:full":"D Leesensstr 87 Maastricht Limburg 6227 TW",
    "addr:housenumber":"87",
    "addr:postcode":"6227 tw",
    "iso:country":"NL",
    "sg:address":"D Leesensstr 87",
    "sg:city":"Maastricht",
    "sg:orig_category":"Autorijscholen",
    "sg:phone":"+31 43 361 3084",
    "sg:postcode":"6227 TW",
    "sg:province":"Limburg",
    "wof:name":"Janssen, Autorijschool L",
    "wof:placetype":"venue"
},
  "geometry": {"coordinates":[5.731575,50.8367],"type":"Point"}
}