{
  "type": "Feature",
  "properties": {
    "addr:full":"Zonnebloemstr 1 Veenendaal Utrecht 3905 ZC",
    "addr:housenumber":"1",
    "addr:postcode":"3905 zc",
    "addr:street":"Zonnebloemstr",
    "iso:country":"NL",
    "sg:address":"Zonnebloemstr 1",
    "sg:city":"Veenendaal",
    "sg:orig_category":"Verenigingsgebouwen",
    "sg:phone":"+31 318 520 523",
    "sg:postcode":"3905 ZC",
    "sg:province":"Utrecht",
    "wof:name":"Het Turfke",
    "wof:placetype":"venue"
},
  "geometry": {"coordinates":[5.545801,52.032635],"type":"Point"}
}