{
  "type": "Feature",
  "properties": {
    "iso:country":"NL",
    "sg:address":"Zonnebloemstr 1",
    "sg:city":"Veenendaal",
    "sg:orig_category":"Verenigingsgebouwen",
    "sg:phone":"+31 318 520 523",
    "sg:postcode":"3905 ZC",
    "sg:province":"Utrecht",
    "wof:name":"Het Turfke",
    "wof:placetype":"venue"
},
  "geometry": {"coordinates":[5.545801,52.032635],"type":"Point"}
}