{
  "type": "Feature",
  "properties": {
    "iso:country":"NL",
    "sg:address":"Industriewg 41",
    "sg:city":"Bedum",
    "sg:orig_category":"Landmeetkundige Bureaus",
    "sg:phone":"+31 50 301 5616",
    "sg:postcode":"9781 AC",
    "sg:province":"Groningen",
    "wof:name":"Mug",
    "wof:placetype":"venue"
},
  "geometry": {"coordinates":[6.593655,53.294792],"type":"Point"}
}