{
  "type": "Feature",
  "properties": {
    "addr:full":"Holtjesstr 23 Almelo Overijssel 7607 JE",
    "addr:housenumber":"23",
    "addr:postcode":"7607 je",
    "addr:street":"Holtjesstr",
    "iso:country":"NL",
    "sg:address":"Holtjesstr 23",
    "sg:city":"Almelo",
    "sg:orig_category":"Discotheken",
    "sg:phone":"+31 546 454 331",
    "sg:postcode":"7607 JE",
    "sg:province":"Overijssel",
    "wof:name":"Replay",
    "wof:placetype":"venue"
},
  "geometry": {"coordinates":[6.664492,52.352867],"type":"Point"}
}