{
  "type": "Feature",
  "properties": {
    "iso:country":"NL",
    "sg:address":"Praubstr 21",
    "sg:city":"Zwolle",
    "sg:orig_category":"Beeldende Kunstenaars",
    "sg:phone":"+31 38 454 0541",
    "sg:postcode":"8011 PN",
    "sg:province":"Overijssel",
    "wof:name":"Kunst Op Zolder",
    "wof:placetype":"venue"
},
  "geometry": {"coordinates":[6.092763,52.510506],"type":"Point"}
}