{
  "type": "Feature",
  "properties": {
    "iso:country":"NL",
    "sg:address":"Kasteelstraat 33",
    "sg:city":"Wamel",
    "sg:orig_category":"Loodgieterswerk, Verwarming And Sanitaire Installaties",
    "sg:phone":"+31 487 501 427",
    "sg:postcode":"6659 AV",
    "sg:province":"Gelderland",
    "wof:name":"Vecap",
    "wof:placetype":"venue"
},
  "geometry": {"coordinates":[5.473307,51.878613],"type":"Point"}
}