{
  "type": "Feature",
  "properties": {
    "addr:full":"Van Oldenbarneveltplein 73 Dordrecht South Holland 3317 ES",
    "addr:housenumber":"73",
    "addr:postcode":"3317 es",
    "addr:street":"Van Oldenbarneveltplein",
    "iso:country":"NL",
    "sg:address":"Van Oldenbarneveltplein 73",
    "sg:city":"Dordrecht",
    "sg:classifiers":[
        {
            "category":"Fast Food",
            "type":"Food & Drink"
        }
    ],
    "sg:phone":"+31 78 651 5230",
    "sg:postcode":"3317 ES",
    "sg:province":"South Holland",
    "sg:tags":[
        "afhaal",
        "restaurant"
    ],
    "wof:name":"Domino'S Pizza",
    "wof:placetype":"venue"
},
  "geometry": {"coordinates":[4.664596,51.790932],"type":"Point"}
}