{
  "type": "Feature",
  "properties": {
    "addr:full":"H Schaftstr 102 Leidschendam South Holland 2264 DL",
    "addr:housenumber":"102",
    "addr:postcode":"2264 dl",
    "iso:country":"NL",
    "sg:address":"H Schaftstr 102",
    "sg:city":"Leidschendam",
    "sg:orig_category":"Plafonds",
    "sg:phone":"+31 70 320 4432",
    "sg:postcode":"2264 DL",
    "sg:province":"South Holland",
    "wof:name":"Voorburg",
    "wof:placetype":"venue"
},
  "geometry": {"coordinates":[4.389023,52.08297],"type":"Point"}
}