{
  "type": "Feature",
  "properties": {
    "addr:full":"J Nicolasstr 13 Roermond Limburg 6041 JZ",
    "addr:housenumber":"13",
    "addr:postcode":"6041 jz",
    "iso:country":"NL",
    "sg:address":"J Nicolasstr 13",
    "sg:city":"Roermond",
    "sg:orig_category":"Herenkleding",
    "sg:phone":"+31 475 330 455",
    "sg:postcode":"6041 JZ",
    "sg:province":"Limburg",
    "wof:name":"Lazy Lord",
    "wof:placetype":"venue"
},
  "geometry": {"coordinates":[5.990556,51.191887],"type":"Point"}
}