{
  "type": "Feature",
  "properties": {
    "iso:country":"NL",
    "sg:address":"Nw Hilversumsewg 10",
    "sg:city":"Bussum",
    "sg:orig_category":"Artsen - Manuele Geneeskunde",
    "sg:phone":"+31 35 693 5544",
    "sg:postcode":"1406 TE",
    "sg:province":"Noord-Holland",
    "wof:name":"Sibbing-Van Gelderen J A Vollebregt, C",
    "wof:placetype":"venue"
},
  "geometry": {"coordinates":[5.15499,52.270893],"type":"Point"}
}