{
  "type": "Feature",
  "properties": {
    "addr:full":"Dorpsstr 114 Castricum Noord-Holland 1901 EN",
    "addr:housenumber":"114",
    "addr:postcode":"1901 en",
    "iso:country":"NL",
    "sg:address":"Dorpsstr 114",
    "sg:city":"Castricum",
    "sg:orig_category":"Makelaars En Adviseurs Onroerende Goederen",
    "sg:phone":"+31 251 676 788",
    "sg:postcode":"1901 EN",
    "sg:province":"Noord-Holland",
    "wof:name":"Slijkerman, Tammo",
    "wof:placetype":"venue"
},
  "geometry": {"coordinates":[4.66801,52.548553],"type":"Point"}
}