{
  "type": "Feature",
  "properties": {
    "addr:full":"Zandwg 147 De Meern Utrecht 3454 HA",
    "addr:housenumber":"147",
    "addr:postcode":"3454 ha",
    "iso:country":"NL",
    "sg:address":"Zandwg 147",
    "sg:city":"De Meern",
    "sg:orig_category":"Onderhoudswerken",
    "sg:phone":"+31 30 662 2319",
    "sg:postcode":"3454 HA",
    "sg:province":"Utrecht",
    "wof:name":"Bram",
    "wof:placetype":"venue"
},
  "geometry": {"coordinates":[5.03466,52.083496],"type":"Point"}
}