{
  "type": "Feature",
  "properties": {
    "addr:full":"Mgr Geurtsstr 74 Maashees North Brabant 5823 AG",
    "addr:housenumber":"74",
    "addr:postcode":"5823",
    "addr:street":"Geurtsstr",
    "iso:country":"NL",
    "sg:address":"Mgr Geurtsstr 74",
    "sg:city":"Maashees",
    "sg:orig_category":"Kappers",
    "sg:phone":"+31 478 636 753",
    "sg:postcode":"5823 AG",
    "sg:province":"North Brabant",
    "wof:name":"Scheepje, 'T",
    "wof:placetype":"venue"
},
  "geometry": {"coordinates":[6.035967,51.568806],"type":"Point"}
}