{
  "type": "Feature",
  "properties": {
    "addr:full":"Tadingastraat 3 Leeuwarden Friesland 8993 2 ",
    "addr:housenumber":"3;2",
    "addr:postcode":"8993",
    "addr:street":"Tadingastraat",
    "iso:country":"NL",
    "sg:address":"Tadingastraat 3",
    "sg:city":"Leeuwarden",
    "sg:orig_category":"Overheidsdiensten",
    "sg:phone":"+31 58 284 4844",
    "sg:postcode":"8993 2 ",
    "sg:province":"Friesland",
    "wof:name":"Guo Uitvoeringsinstelling",
    "wof:placetype":"venue"
},
  "geometry": {"coordinates":[5.7925701141,53.1973190308],"type":"Point"}
}