{
  "type": "Feature",
  "properties": {
    "addr:full":"Vlielandseweg 81 Pijnacker Zuid-Holland 2641 KA",
    "addr:housenumber":"81",
    "addr:postcode":"2641 ka",
    "addr:street":"Vlielandseweg",
    "iso:country":"NL",
    "sg:address":"Vlielandseweg 81",
    "sg:city":"Pijnacker",
    "sg:orig_category":"Boekhouders",
    "sg:phone":"+31 15 361 2418",
    "sg:postcode":"2641 KA",
    "sg:province":"Zuid-Holland",
    "wof:name":"H. Schwering",
    "wof:placetype":"venue"
},
  "geometry": {"coordinates":[4.435478,52.024323],"type":"Point"}
}