{
  "type": "Feature",
  "properties": {
    "addr:full":"Kroonpark 2A Arnhem Gelderland 6831 GV",
    "addr:housenumber":"2a",
    "addr:postcode":"6831 gv",
    "addr:street":"Kroonpark",
    "iso:country":"NL",
    "sg:address":"Kroonpark 2A",
    "sg:city":"Arnhem",
    "sg:orig_category":"Autokeuringen",
    "sg:phone":"+31 26 361 1116",
    "sg:postcode":"6831 GV",
    "sg:province":"Gelderland",
    "wof:name":"Fleetcontrol",
    "wof:placetype":"venue"
},
  "geometry": {"coordinates":[5.891861,51.958775],"type":"Point"}
}