{
  "type": "Feature",
  "properties": {
    "iso:country":"NL",
    "sg:address":"Brinkstr 24A",
    "sg:city":"Hoogeveen",
    "sg:orig_category":"Mensendieck - Oefentherapeuten",
    "sg:phone":"+31 528 275 758",
    "sg:postcode":"7901 LA",
    "sg:province":"Drenthe",
    "wof:name":"Dekker & B M Heling, J",
    "wof:placetype":"venue"
},
  "geometry": {"coordinates":[6.476995,52.730511],"type":"Point"}
}