{
  "type": "Feature",
  "properties": {
    "addr:full":"Kloosterstr 22 Venlo Limburg 5921 HC",
    "addr:housenumber":"22",
    "addr:postcode":"5921 hc",
    "addr:street":"Kloosterstr",
    "iso:country":"NL",
    "sg:address":"Kloosterstr 22",
    "sg:city":"Venlo",
    "sg:orig_category":"Schoenen",
    "sg:phone":"+31 77 387 2952",
    "sg:postcode":"5921 HC",
    "sg:province":"Limburg",
    "wof:name":"Schoenenreus",
    "wof:placetype":"venue"
},
  "geometry": {"coordinates":[6.153215,51.366405],"type":"Point"}
}