{
  "type": "Feature",
  "properties": {
    "addr:full":"B Limburgstr 88 Voorschoten Zuid-Holland 2251 RR",
    "addr:housenumber":"88",
    "addr:postcode":"2251 rr",
    "iso:country":"NL",
    "sg:address":"B Limburgstr 88",
    "sg:city":"Voorschoten",
    "sg:orig_category":"Adviesbureaus Waterbouwkunde",
    "sg:phone":"+31 71 561 0039",
    "sg:postcode":"2251 RR",
    "sg:province":"Zuid-Holland",
    "wof:name":"Wagter",
    "wof:placetype":"venue"
},
  "geometry": {"coordinates":[4.446902,52.116627],"type":"Point"}
}