{
  "type": "Feature",
  "properties": {
    "addr:full":"Koninginnelaan 25 Rijswijk Zh Zuid-Holland 2281 HA",
    "addr:housenumber":"25",
    "addr:postcode":"zh;2281 ha",
    "addr:street":"Koninginnelaan",
    "iso:country":"NL",
    "sg:address":"Koninginnelaan 25",
    "sg:city":"Rijswijk Zh",
    "sg:orig_category":"Schilderwerk",
    "sg:phone":"+31 70 399 3217",
    "sg:postcode":"2281 HA",
    "sg:province":"Zuid-Holland",
    "wof:name":"Hans Walther",
    "wof:placetype":"venue"
},
  "geometry": {"coordinates":[4.34315,52.05756],"type":"Point"}
}