{
  "type": "Feature",
  "properties": {
    "iso:country":"NL",
    "sg:address":"Turfschipper 11-13",
    "sg:city":"Wateringen",
    "sg:orig_category":"Kunststoffen- Verwerkende Industrie",
    "sg:phone":"+31 174 225 240",
    "sg:postcode":"2292 JC",
    "sg:province":"South Holland",
    "sg:website":"http://www.shannon.nl",
    "wof:name":"Shannon Bv",
    "wof:placetype":"venue"
},
  "geometry": {"coordinates":[4.291467,52.016327],"type":"Point"}
}