{
  "type": "Feature",
  "properties": {
    "addr:full":"Turfschipper 11-13 Wateringen South Holland 2292 JC",
    "addr:housenumber":"11-13",
    "addr:postcode":"2292 jc",
    "addr:street":"Turfschipper",
    "iso:country":"NL",
    "sg:address":"Turfschipper 11-13",
    "sg:city":"Wateringen",
    "sg:orig_category":"Kunststoffen- Verwerkende Industrie",
    "sg:phone":"+31 174 225 240",
    "sg:postcode":"2292 JC",
    "sg:province":"South Holland",
    "sg:website":"http://www.shannon.nl",
    "wof:name":"Shannon Bv",
    "wof:placetype":"venue"
},
  "geometry": {"coordinates":[4.291467,52.016327],"type":"Point"}
}