{
  "type": "Feature",
  "properties": {
    "addr:full":"Kornalynhorst 183 S Gravenhage South Holland 2592 HW",
    "addr:housenumber":"183",
    "addr:postcode":"2592 hw",
    "addr:street":"S Gravenhage",
    "iso:country":"NL",
    "sg:address":"Kornalynhorst 183",
    "sg:city":"S Gravenhage",
    "sg:classifiers":[
        {
            "category":"Wholesale",
            "subcategory":"Meat",
            "type":"Manufacturing & Wholesale Goods"
        }
    ],
    "sg:phone":"+31 70 320 2682",
    "sg:postcode":"2592 HW",
    "sg:province":"South Holland",
    "sg:tags":[
        "regeltechniek",
        "en",
        "meet-"
    ],
    "sg:website":"http://www.coteltelecom.com",
    "wof:name":"Cotel Vof",
    "wof:placetype":"venue"
},
  "geometry": {"coordinates":[4.35298,52.089199],"type":"Point"}
}