{
  "type": "Feature",
  "properties": {
    "iso:country":"NL",
    "sg:address":"Oploseweg 10",
    "sg:city":"Overloon",
    "sg:orig_category":"Verhuur Voertuigen Behalve Auto'S",
    "sg:phone":"+31 478 640 304",
    "sg:postcode":"5825 HN",
    "sg:province":"Noord-Brabant",
    "wof:name":"Henckens Aanhangwagens",
    "wof:placetype":"venue"
},
  "geometry": {"coordinates":[5.937642,51.570759],"type":"Point"}
}