{
  "type": "Feature",
  "properties": {
    "addr:full":"Noordsingel 51 Rotterdam Zuid-Holland 3035 EJ",
    "addr:housenumber":"51",
    "addr:postcode":"3035 ej",
    "addr:street":"Noordsingel",
    "iso:country":"NL",
    "sg:address":"Noordsingel 51",
    "sg:city":"Rotterdam",
    "sg:orig_category":"Meubelzaken, Woning- And Keukeninrichting",
    "sg:phone":"+31 10 466 0949",
    "sg:postcode":"3035 EJ",
    "sg:province":"Zuid-Holland",
    "wof:name":"Jan Van Staveren",
    "wof:placetype":"venue"
},
  "geometry": {"coordinates":[4.480076,51.930302],"type":"Point"}
}