{
  "type": "Feature",
  "properties": {
    "addr:full":"L Bouwmeesterstr 107 Hengelo Ov Overijssel 7558 TV",
    "addr:housenumber":"107",
    "addr:postcode":"7558 tv",
    "addr:street":"Ov",
    "iso:country":"NL",
    "sg:address":"L Bouwmeesterstr 107",
    "sg:city":"Hengelo Ov",
    "sg:orig_category":"Adviesbureaus Bedrijfsorganisatie",
    "sg:phone":"+31 74 278 3716",
    "sg:postcode":"7558 TV",
    "sg:province":"Overijssel",
    "sg:website":"http://www.enterlead.nl",
    "wof:name":"Enterlead Bv",
    "wof:placetype":"venue"
},
  "geometry": {"coordinates":[6.824075,52.290558],"type":"Point"}
}