{
  "type": "Feature",
  "properties": {
    "addr:full":"Gildebongerd 86 Zeddam Gelderland 7038 DG",
    "addr:housenumber":"86",
    "addr:postcode":"7038 dg",
    "addr:street":"Gildebongerd;Gelderland",
    "iso:country":"NL",
    "sg:address":"Gildebongerd 86",
    "sg:city":"Zeddam",
    "sg:orig_category":"Webdesign Bureaus",
    "sg:phone":"+31 314 653 038",
    "sg:postcode":"7038 DG",
    "sg:province":"Gelderland",
    "wof:name":"Hegman",
    "wof:placetype":"venue"
},
  "geometry": {"coordinates":[6.2603859901,51.9057235718],"type":"Point"}
}