{
  "type": "Feature",
  "properties": {
    "addr:full":"Westeind 42 Zuidbroek Groningen 9636 CD",
    "addr:housenumber":"42",
    "addr:postcode":"9636 cd",
    "addr:street":"Westeind;Zuidbroek",
    "iso:country":"NL",
    "sg:address":"Westeind 42",
    "sg:city":"Zuidbroek",
    "sg:orig_category":"Schilderwerk",
    "sg:phone":"+31 598 391 730",
    "sg:postcode":"9636 CD",
    "sg:province":"Groningen",
    "wof:name":"Schildersbedrijf J Strootman",
    "wof:placetype":"venue"
},
  "geometry": {"coordinates":[6.833888,53.162651],"type":"Point"}
}