{
  "type": "Feature",
  "properties": {
    "addr:full":"Lanen 79 Harlingen Friesland 8861 CC",
    "addr:housenumber":"79",
    "addr:postcode":"8861 cc",
    "addr:street":"Lanen",
    "iso:country":"NL",
    "sg:address":"Lanen 79",
    "sg:city":"Harlingen",
    "sg:orig_category":"Meubeltextiel Fab",
    "sg:phone":"+31 517 412 104",
    "sg:postcode":"8861 CC",
    "sg:province":"Friesland",
    "wof:name":"Van Der Plaats Zeilmakerij",
    "wof:placetype":"venue"
},
  "geometry": {"coordinates":[5.419027,53.173851],"type":"Point"}
}