{
  "type": "Feature",
  "properties": {
    "iso:country":"NL",
    "sg:address":"Hoofdstraat 4",
    "sg:city":"Terheijden",
    "sg:orig_category":"Verlichting And Huishoudartikelen",
    "sg:phone":"+31 76 593 3067",
    "sg:postcode":"4844 CE",
    "sg:province":"North Brabant",
    "wof:name":"Tinckerbell",
    "wof:placetype":"venue"
},
  "geometry": {"coordinates":[4.753705,51.642006],"type":"Point"}
}