{
  "type": "Feature",
  "properties": {
    "addr:full":"Ingenieur J.Nysinghweg 8 Noorden California 2432 CB",
    "addr:housenumber":"8",
    "addr:postcode":"2432 cb",
    "addr:street":"Ingenieur J.Nysinghweg",
    "iso:country":"NL",
    "sg:address":"Ingenieur J.Nysinghweg 8",
    "sg:city":"Noorden",
    "sg:orig_category":"Kampeerterreinen",
    "sg:phone":"+31 172 408 327",
    "sg:postcode":"2432 CB",
    "sg:province":"California",
    "wof:name":"Caravanpark Madeira",
    "wof:placetype":"venue"
},
  "geometry": {"coordinates":[-120.3638534546,39.3203735352],"type":"Point"}
}