{
  "type": "Feature",
  "properties": {
    "addr:full":"Schrans 21 Leeuwarden Friesland 8932 NA",
    "addr:housenumber":"21",
    "addr:postcode":"8932 na",
    "addr:street":"Schrans",
    "iso:country":"NL",
    "sg:address":"Schrans 21",
    "sg:city":"Leeuwarden",
    "sg:classifiers":[
        {
            "category":"Fast Food",
            "type":"Food & Drink"
        }
    ],
    "sg:phone":"+31 58 289 0800",
    "sg:postcode":"8932 NA",
    "sg:province":"Friesland",
    "sg:tags":[
        "afhaal",
        "restaurant"
    ],
    "wof:name":"Huizumer Snackhal",
    "wof:placetype":"venue"
},
  "geometry": {"coordinates":[5.797785,53.196117],"type":"Point"}
}