{
  "type": "Feature",
  "properties": {
    "iso:country":"NL",
    "sg:address":"Oekelsebaan 10",
    "sg:city":"Zundert",
    "sg:orig_category":"Chemische Producten Gh",
    "sg:phone":"+31 76 597 6003",
    "sg:postcode":"4881 NG",
    "sg:province":"Noord-Brabant",
    "wof:name":"Plastic Export Zundert Bv",
    "wof:placetype":"venue"
},
  "geometry": {"coordinates":[4.690068,51.477646],"type":"Point"}
}