{
  "type": "Feature",
  "properties": {
    "iso:country":"NL",
    "sg:address":"P C Hooftstr 3",
    "sg:city":"Breda",
    "sg:orig_category":"Artsen - Huisartsen",
    "sg:phone":"+31 76 521 4864",
    "sg:postcode":"4819 HK",
    "sg:province":"Noord-Brabant",
    "wof:name":"Leijten, J G N M",
    "wof:placetype":"venue"
},
  "geometry": {"coordinates":[4.76768,51.577656],"type":"Point"}
}