{
  "type": "Feature",
  "properties": {
    "addr:full":"Buitengasthuisstraat 8 Zwolle Overijssel 8041 AB",
    "addr:housenumber":"8",
    "addr:postcode":"8041 ab",
    "addr:street":"Buitengasthuisstraat",
    "iso:country":"NL",
    "sg:address":"Buitengasthuisstraat 8",
    "sg:city":"Zwolle",
    "sg:orig_category":"Sportcentra",
    "sg:phone":"+31 38 422 6129",
    "sg:postcode":"8041 AB",
    "sg:province":"Overijssel",
    "wof:name":"Sporthal Stichting Wrzv",
    "wof:placetype":"venue"
},
  "geometry": {"coordinates":[6.076243,52.516144],"type":"Point"}
}