{
  "type": "Feature",
  "properties": {
    "addr:full":"Gravenstraat 14 Dordrecht South Holland 3311 BC",
    "addr:housenumber":"14",
    "addr:postcode":"3311 bc",
    "addr:street":"Gravenstraat",
    "iso:country":"NL",
    "sg:address":"Gravenstraat 14",
    "sg:city":"Dordrecht",
    "sg:orig_category":"Loodgieterswerk, Verwarming And Sanitaire Installaties",
    "sg:phone":"+31 78 614 0047",
    "sg:postcode":"3311 BC",
    "sg:province":"South Holland",
    "wof:name":"Renolas",
    "wof:placetype":"venue"
},
  "geometry": {"coordinates":[4.666865,51.816799],"type":"Point"}
}