{
  "type": "Feature",
  "properties": {
    "addr:full":"Noordenwg 37 Ridderkerk Zuid-Holland 2984 AG",
    "addr:housenumber":"37",
    "addr:postcode":"2984",
    "addr:street":"Noordenwg",
    "iso:country":"NL",
    "sg:address":"Noordenwg 37",
    "sg:city":"Ridderkerk",
    "sg:classifiers":[
        {
            "category":"Retail",
            "subcategory":"Auto Repair",
            "type":"Services"
        }
    ],
    "sg:phone":"+31 180 412 432",
    "sg:postcode":"2984 AG",
    "sg:province":"Zuid-Holland",
    "sg:tags":[
        "garage"
    ],
    "sg:website":"http://www.ford.nl",
    "wof:name":"Hardenbol",
    "wof:placetype":"venue"
},
  "geometry": {"coordinates":[4.604066,51.871567],"type":"Point"}
}