{
  "type": "Feature",
  "properties": {
    "iso:country":"NL",
    "sg:address":"Ceintuurbaan 19",
    "sg:city":"Amsterdam",
    "sg:orig_category":"Vertalers",
    "sg:phone":"+31 20 664 2390",
    "sg:postcode":"1072 ES",
    "sg:province":"North Holland",
    "wof:name":"Spataro, E B",
    "wof:placetype":"venue"
},
  "geometry": {"coordinates":[4.887671,52.352478],"type":"Point"}
}