{
  "type": "Feature",
  "properties": {
    "addr:full":"Heyerstr 7 Westerhoven Noord-Brabant 5563 BM",
    "addr:housenumber":"7",
    "addr:postcode":"5563 bm",
    "addr:street":"Heyerstr",
    "iso:country":"NL",
    "sg:address":"Heyerstr 7",
    "sg:city":"Westerhoven",
    "sg:orig_category":"Autoschade- Herstelbedrijven",
    "sg:phone":"+31 40 201 2636",
    "sg:postcode":"5563 BM",
    "sg:province":"Noord-Brabant",
    "sg:website":"http://www.beukersautoschade.nl",
    "wof:name":"Beukers",
    "wof:placetype":"venue"
},
  "geometry": {"coordinates":[5.400685,51.331493],"type":"Point"}
}