{
  "type": "Feature",
  "properties": {
    "iso:country":"NL",
    "sg:address":"Doctor Colijnstraat 4",
    "sg:city":"Ridderkerk",
    "sg:orig_category":"Omroep",
    "sg:phone":"+31 180 426 700",
    "sg:postcode":"2982 AC",
    "sg:province":"South Holland",
    "wof:name":"M & M",
    "wof:placetype":"venue"
},
  "geometry": {"coordinates":[4.597238,51.873093],"type":"Point"}
}