{
  "type": "Feature",
  "properties": {
    "addr:full":"H Prinsenwg 1 Vlagtwedde Groningen 9541 XH",
    "addr:housenumber":"1",
    "addr:postcode":"9541 xh",
    "iso:country":"NL",
    "sg:address":"H Prinsenwg 1",
    "sg:city":"Vlagtwedde",
    "sg:orig_category":"Beeldende Kunstenaars",
    "sg:phone":"+31 599 354 729",
    "sg:postcode":"9541 XH",
    "sg:province":"Groningen",
    "wof:name":"Spierenburg",
    "wof:placetype":"venue"
},
  "geometry": {"coordinates":[7.157496,53.036251],"type":"Point"}
}