{
  "type": "Feature",
  "properties": {
    "addr:full":"Hoogstr 27 Hasselt NL.08 8061 HA",
    "addr:housenumber":"27",
    "addr:postcode":"8061 ha",
    "addr:street":"Hoogstr",
    "iso:country":"NL",
    "sg:address":"Hoogstr 27",
    "sg:city":"Hasselt",
    "sg:orig_category":"Woninginrichting",
    "sg:phone":"+31 38 477 3952",
    "sg:postcode":"8061 HA",
    "sg:province":"NL.08",
    "wof:name":"Kawi",
    "wof:placetype":"venue"
},
  "geometry": {"coordinates":[6.0890412331,52.5916786194],"type":"Point"}
}