{
  "type": "Feature",
  "properties": {
    "addr:full":"Hoefkade 820 'S Gravenhage South Holland 2526 CV",
    "addr:housenumber":"820 '",
    "addr:postcode":"2526 cv",
    "addr:street":"Hoefkade",
    "iso:country":"NL",
    "sg:address":"Hoefkade 820",
    "sg:city":"'S Gravenhage",
    "sg:orig_category":"Juweliers",
    "sg:phone":"+31 70 380 9880",
    "sg:postcode":"2526 CV",
    "sg:province":"South Holland",
    "wof:name":"Parbo Goud Bv",
    "wof:placetype":"venue"
},
  "geometry": {"coordinates":[4.310246,52.066692],"type":"Point"}
}