{
  "type": "Feature",
  "properties": {
    "addr:full":"Beukenhorst 4 Vught Noord-Brabant 5262 LG",
    "addr:housenumber":"4",
    "addr:postcode":"5262 lg",
    "addr:street":"Beukenhorst",
    "iso:country":"NL",
    "sg:address":"Beukenhorst 4",
    "sg:city":"Vught",
    "sg:orig_category":"Elektronische Bedrijfsinstallaties",
    "sg:phone":"+31 411 604 000",
    "sg:postcode":"5262 LG",
    "sg:province":"Noord-Brabant",
    "wof:name":"Serre Consultancy Bv",
    "wof:placetype":"venue"
},
  "geometry": {"coordinates":[5.289991,51.623917],"type":"Point"}
}