{
  "type": "Feature",
  "properties": {
    "addr:full":"Institutenweg 10 Enschede Overijssel 7521 PK",
    "addr:housenumber":"10",
    "addr:postcode":"7521 pk",
    "addr:street":"Institutenweg",
    "iso:country":"NL",
    "sg:address":"Institutenweg 10",
    "sg:city":"Enschede",
    "sg:classifiers":[
        {
            "category":"Professional",
            "subcategory":"Accounting & Tax Preparation",
            "type":"Services"
        }
    ],
    "sg:phone":"+31 53 434 0140",
    "sg:postcode":"7521 PK",
    "sg:province":"Overijssel",
    "sg:tags":[
        "accountant"
    ],
    "wof:name":"Accadi",
    "wof:placetype":"venue"
},
  "geometry": {"coordinates":[6.845836,52.237499],"type":"Point"}
}