{
  "type": "Feature",
  "properties": {
    "addr:full":"Bemelmansstr 24 Doenrade Limburg 6439 AW",
    "addr:housenumber":"24",
    "addr:postcode":"6439 aw",
    "addr:street":"Bemelmansstr",
    "iso:country":"NL",
    "sg:address":"Bemelmansstr 24",
    "sg:city":"Doenrade",
    "sg:orig_category":"Autorijscholen",
    "sg:phone":"+31 46 442 0462",
    "sg:postcode":"6439 AW",
    "sg:province":"Limburg",
    "wof:name":"Doenrade, Auto & Motorrijschool",
    "wof:placetype":"venue"
},
  "geometry": {"coordinates":[5.907964,50.966938],"type":"Point"}
}