{
  "type": "Feature",
  "properties": {
    "addr:full":"De Barones 18 Breda Noord-Brabant 4811 XZ",
    "addr:housenumber":"18",
    "addr:postcode":"4811 xz",
    "addr:street":"De Barones",
    "iso:country":"NL",
    "sg:address":"De Barones 18",
    "sg:city":"Breda",
    "sg:orig_category":"Damesmodezaken",
    "sg:phone":"+31 76 513 9090",
    "sg:postcode":"4811 XZ",
    "sg:province":"Noord-Brabant",
    "wof:name":"Paddy Bv",
    "wof:placetype":"venue"
},
  "geometry": {"coordinates":[4.775233,51.58717],"type":"Point"}
}