{
  "type": "Feature",
  "properties": {
    "addr:full":"M Putstraat 10 Brummen Gelderland 6971 AD",
    "addr:housenumber":"10",
    "addr:postcode":"6971 ad",
    "addr:street":"M Putstraat;Gelderland",
    "iso:country":"NL",
    "sg:address":"M Putstraat 10",
    "sg:city":"Brummen",
    "sg:orig_category":"Verzekeringen",
    "sg:phone":"+31 575 561 727",
    "sg:postcode":"6971 AD",
    "sg:province":"Gelderland",
    "wof:name":"Schouten En Hendriks Assurantien",
    "wof:placetype":"venue"
},
  "geometry": {"coordinates":[6.157874,52.086975],"type":"Point"}
}