{
  "type": "Feature",
  "properties": {
    "iso:country":"NL",
    "sg:address":"Slinge 584",
    "sg:city":"Rotterdam",
    "sg:orig_category":"Schoenen",
    "sg:phone":"+31 10 480 4790",
    "sg:postcode":"3086 EX",
    "sg:province":"South Holland",
    "wof:name":"De Zeeuw Schoenen",
    "wof:placetype":"venue"
},
  "geometry": {"coordinates":[4.468898,51.87468],"type":"Point"}
}