{
  "type": "Feature",
  "properties": {
    "iso:country":"NL",
    "sg:address":"Cor Gordijnsingel 61",
    "sg:city":"Leiderdorp",
    "sg:orig_category":"Apothekers",
    "sg:phone":"+31 71 541 9418",
    "sg:postcode":"2353 GH",
    "sg:province":"Zuid-Holland",
    "wof:name":"Apotheek Van Der Laan",
    "wof:placetype":"venue"
},
  "geometry": {"coordinates":[4.5283,52.164944],"type":"Point"}
}