{
  "type": "Feature",
  "properties": {
    "addr:full":"Prins Hendrikplein 2 Veendam Groningen 9641 GK",
    "addr:housenumber":"2",
    "addr:postcode":"9641 gk",
    "addr:street":"Prins Hendrikplein",
    "iso:country":"NL",
    "sg:address":"Prins Hendrikplein 2",
    "sg:city":"Veendam",
    "sg:orig_category":"Apothekers",
    "sg:phone":"+31 598 612 088",
    "sg:postcode":"9641 GK",
    "sg:province":"Groningen",
    "wof:name":"Apotheek Van Aken",
    "wof:placetype":"venue"
},
  "geometry": {"coordinates":[6.872906,53.106297],"type":"Point"}
}