{
  "type": "Feature",
  "properties": {
    "addr:full":"Achterdoelen 100 Ede Gld Gelderland 6711 AV",
    "addr:housenumber":"100;6711",
    "addr:postcode":"av",
    "addr:street":"Achterdoelen;Gld Gelderland",
    "iso:country":"NL",
    "sg:address":"Achterdoelen 100",
    "sg:city":"Ede Gld",
    "sg:orig_category":"Mode-Artikelen Dames En Heren",
    "sg:phone":"+31 318 694 909",
    "sg:postcode":"6711 AV",
    "sg:province":"Gelderland",
    "sg:website":"http://www.mexx.com",
    "wof:name":"Mexx Lifestyle",
    "wof:placetype":"venue"
},
  "geometry": {"coordinates":[5.671402,52.044659],"type":"Point"}
}