{
  "type": "Feature",
  "properties": {
    "iso:country":"NL",
    "sg:address":"Bolstoen 32A",
    "sg:city":"Amsterdam",
    "sg:orig_category":"Meubelmakerijen",
    "sg:phone":"+31 20 613 5638",
    "sg:postcode":"1046 AV",
    "sg:province":"Noord-Holland",
    "wof:name":"J & J Visuals",
    "wof:placetype":"venue"
},
  "geometry": {"coordinates":[4.789855,52.390862],"type":"Point"}
}