{
  "type": "Feature",
  "properties": {
    "addr:full":"Hoofdstr 47 Albergen NL.08 7665 AN",
    "addr:housenumber":"47;nl.08",
    "addr:postcode":"7665 an",
    "addr:street":"Hoofdstr",
    "iso:country":"NL",
    "sg:address":"Hoofdstr 47",
    "sg:city":"Albergen",
    "sg:orig_category":"Loodgieters",
    "sg:phone":"+31 546 441 719",
    "sg:postcode":"7665 AN",
    "sg:province":"NL.08",
    "wof:name":"Klumpers",
    "wof:placetype":"venue"
},
  "geometry": {"coordinates":[6.758661,52.371784],"type":"Point"}
}