{
  "type": "Feature",
  "properties": {
    "addr:full":"Trompln 1 Doorn Utrecht 3941 VR",
    "addr:housenumber":"1",
    "addr:postcode":"3941 vr",
    "addr:street":"Trompln",
    "iso:country":"NL",
    "sg:address":"Trompln 1",
    "sg:city":"Doorn",
    "sg:orig_category":"Peuterspeelzalen",
    "sg:phone":"+31 343 413 183",
    "sg:postcode":"3941 VR",
    "sg:province":"Utrecht",
    "wof:name":"Blokkendoos, De",
    "wof:placetype":"venue"
},
  "geometry": {"coordinates":[5.340395,52.043472],"type":"Point"}
}