{
  "type": "Feature",
  "properties": {
    "addr:full":"Hoofdwg 47B Zuurdyk Groningen 9966 VB",
    "addr:housenumber":"47b zuurdyk",
    "addr:postcode":"9966 vb",
    "addr:street":"Hoofdwg",
    "iso:country":"NL",
    "sg:address":"Hoofdwg 47B",
    "sg:city":"Zuurdyk",
    "sg:orig_category":"Geluidsinstallaties - Verhuur",
    "sg:phone":"+31 6 25484969",
    "sg:postcode":"9966 VB",
    "sg:province":"Groningen",
    "wof:name":"High Tech Audio",
    "wof:placetype":"venue"
},
  "geometry": {"coordinates":[6.376981,53.337723],"type":"Point"}
}