{
  "type": "Feature",
  "properties": {
    "addr:full":"Populierendreef 974 Voorburg South Holland 2272 HW",
    "addr:housenumber":"974",
    "addr:postcode":"2272 hw",
    "addr:street":"Populierendreef",
    "iso:country":"NL",
    "sg:address":"Populierendreef 974",
    "sg:city":"Voorburg",
    "sg:orig_category":"Boekenuitgeverijen",
    "sg:phone":"+31 70 369 4004",
    "sg:postcode":"2272 HW",
    "sg:province":"South Holland",
    "wof:name":"Drukkerij Voortvaren Bv",
    "wof:placetype":"venue"
},
  "geometry": {"coordinates":[4.362164,52.08498],"type":"Point"}
}