{
  "type": "Feature",
  "properties": {
    "iso:country":"NL",
    "sg:address":"1E Hogewg 22P",
    "sg:city":"Zeist",
    "sg:orig_category":"Wijnkoperijen En -Groothandel",
    "sg:phone":"+31 30 692 2465",
    "sg:postcode":"3701 HL",
    "sg:province":"Utrecht",
    "wof:name":"Witte Os, De",
    "wof:placetype":"venue"
},
  "geometry": {"coordinates":[5.2410287857,52.0853881836],"type":"Point"}
}