{
  "type": "Feature",
  "properties": {
    "addr:full":"Zuiderln 28C Zevenaar Gelderland 6905 AE",
    "addr:housenumber":"28c",
    "addr:postcode":"6905 ae",
    "addr:street":"Zuiderln",
    "iso:country":"NL",
    "sg:address":"Zuiderln 28C",
    "sg:city":"Zevenaar",
    "sg:orig_category":"Lasapparaten En Benodigdheden",
    "sg:phone":"+31 316 581 800",
    "sg:postcode":"6905 AE",
    "sg:province":"Gelderland",
    "wof:name":"Technolit Gmbh",
    "wof:placetype":"venue"
},
  "geometry": {"coordinates":[6.08225,51.915859],"type":"Point"}
}