{
  "type": "Feature",
  "properties": {
    "addr:full":"Coolsingel 40 Rotterdam Zuid-Holland 3011 AD",
    "addr:housenumber":"40",
    "addr:postcode":"3011 ad",
    "addr:street":"Coolsingel",
    "iso:country":"NL",
    "sg:address":"Coolsingel 40",
    "sg:city":"Rotterdam",
    "sg:orig_category":"Overheidsdiensten",
    "sg:phone":"+31 10 417 9111",
    "sg:postcode":"3011 AD",
    "sg:province":"Zuid-Holland",
    "wof:name":"Gemeente Rotterdam",
    "wof:placetype":"venue"
},
  "geometry": {"coordinates":[4.478910923,51.9226837158],"type":"Point"}
}