{
  "type": "Feature",
  "properties": {
    "addr:full":"Dorpsstraat 34 Putten Gelderland 3881 BD",
    "addr:housenumber":"34",
    "addr:postcode":"3881 bd",
    "addr:street":"Dorpsstraat;Gelderland",
    "iso:country":"NL",
    "sg:address":"Dorpsstraat 34",
    "sg:city":"Putten",
    "sg:orig_category":"Opticiens",
    "sg:phone":"+31 341 352 554",
    "sg:postcode":"3881 BD",
    "sg:province":"Gelderland",
    "wof:name":"Hans Anders Opticiens",
    "wof:placetype":"venue"
},
  "geometry": {"coordinates":[5.6050038338,52.2605895996],"type":"Point"}
}