{
  "type": "Feature",
  "properties": {
    "iso:country":"NL",
    "sg:address":"Spoorgr 5A",
    "sg:city":"Den Helder",
    "sg:orig_category":"Verenigingsgebouwen",
    "sg:phone":"+31 223 619 602",
    "sg:postcode":"1781 CC",
    "sg:province":"Noord-Holland",
    "wof:name":"Jutter, De",
    "wof:placetype":"venue"
},
  "geometry": {"coordinates":[4.766791,52.956886],"type":"Point"}
}