{
  "type": "Feature",
  "properties": {
    "addr:full":"Horsterwg 213 Ermelo Gelderland 3853 JC",
    "addr:housenumber":"213",
    "addr:postcode":"3853 jc",
    "addr:street":"Gelderland",
    "iso:country":"NL",
    "sg:address":"Horsterwg 213",
    "sg:city":"Ermelo",
    "sg:orig_category":"Poeliers",
    "sg:phone":"+31 341 558 052",
    "sg:postcode":"3853 JC",
    "sg:province":"Gelderland",
    "wof:name":"Tomassen, Poeliersbedrijf",
    "wof:placetype":"venue"
},
  "geometry": {"coordinates":[5.591765,52.31181],"type":"Point"}
}