{
  "type": "Feature",
  "properties": {
    "iso:country":"NL",
    "sg:address":"Lewestr 19",
    "sg:city":"Kloetinge",
    "sg:orig_category":"Satellietontvangst- En Antenne-Installaties",
    "sg:phone":"+31 113 223 221",
    "sg:postcode":"4481 BB",
    "sg:province":"Zeeland",
    "wof:name":"Velden, Van Der",
    "wof:placetype":"venue"
},
  "geometry": {"coordinates":[3.912759,51.498669],"type":"Point"}
}