{
  "type": "Feature",
  "properties": {
    "addr:full":"Kleiweg 73 Gouda Zuid-Holland 2801 GD",
    "addr:housenumber":"73",
    "addr:postcode":"2801 gd",
    "addr:street":"Kleiweg",
    "iso:country":"NL",
    "sg:address":"Kleiweg 73",
    "sg:city":"Gouda",
    "sg:orig_category":"Damesmodezaken",
    "sg:phone":"+31 182 583 101",
    "sg:postcode":"2801 GD",
    "sg:province":"Zuid-Holland",
    "wof:name":"Ouiset Mode",
    "wof:placetype":"venue"
},
  "geometry": {"coordinates":[4.709782,52.014217],"type":"Point"}
}