{
  "type": "Feature",
  "properties": {
    "addr:full":"Westerval 25 Enschede Overijssel 7545 MZ",
    "addr:housenumber":"25",
    "addr:postcode":"7545 mz",
    "addr:street":"Westerval",
    "iso:country":"NL",
    "sg:address":"Westerval 25",
    "sg:city":"Enschede",
    "sg:classifiers":[
        {
            "category":"Recreation",
            "subcategory":"Amusement Park",
            "type":"Entertainment"
        }
    ],
    "sg:phone":"+31 53 432 1911",
    "sg:postcode":"7545 MZ",
    "sg:province":"Overijssel",
    "wof:name":"Euregio",
    "wof:placetype":"venue"
},
  "geometry": {"coordinates":[6.869858,52.21806],"type":"Point"}
}