{
  "type": "Feature",
  "properties": {
    "addr:full":"Broersvest 74-76 Schiedam South Holland 3112 DG",
    "addr:housenumber":"74-76",
    "addr:postcode":"3112 dg",
    "addr:street":"Broersvest",
    "iso:country":"NL",
    "sg:address":"Broersvest 74-76",
    "sg:city":"Schiedam",
    "sg:orig_category":"Meubelzaken, Woning- And Keukeninrichting",
    "sg:phone":"+31 10 473 4982",
    "sg:postcode":"3112 DG",
    "sg:province":"South Holland",
    "wof:name":"Broersvest Meubelen",
    "wof:placetype":"venue"
},
  "geometry": {"coordinates":[4.402914,51.916824],"type":"Point"}
}