{
  "type": "Feature",
  "properties": {
    "addr:full":"Oude Schoolstr 33 Voerendaal Limburg 6367 HC",
    "addr:housenumber":"33",
    "addr:postcode":"6367 hc",
    "addr:street":"Oude Schoolstr",
    "iso:country":"NL",
    "sg:address":"Oude Schoolstr 33",
    "sg:city":"Voerendaal",
    "sg:orig_category":"Verenigingen En Stichtingen",
    "sg:phone":"+31 45 575 3568",
    "sg:postcode":"6367 HC",
    "sg:province":"Limburg",
    "wof:name":"Fanfare St Cecilia",
    "wof:placetype":"venue"
},
  "geometry": {"coordinates":[5.944661,50.85424],"type":"Point"}
}