{
  "type": "Feature",
  "properties": {
    "addr:full":"Hendriklaan 121 Roermond Limburg 6043 BR",
    "addr:housenumber":"121",
    "addr:postcode":"6043 br",
    "addr:street":"Hendriklaan",
    "iso:country":"NL",
    "sg:address":"Hendriklaan 121",
    "sg:city":"Roermond",
    "sg:classifiers":[
        {
            "category":"Education",
            "subcategory":"Preschool",
            "type":"Public Place"
        }
    ],
    "sg:phone":"+31 475 332 989",
    "sg:postcode":"6043 BR",
    "sg:province":"Limburg",
    "sg:tags":[
        "kleuteronderwijs",
        "basis-"
    ],
    "wof:name":"De Lolliepot",
    "wof:placetype":"venue"
},
  "geometry": {"coordinates":[5.99849,51.187008],"type":"Point"}
}