{
  "type": "Feature",
  "properties": {
    "addr:full":"Gedempte Zuiderdiep 150 Groningen Groningen 9711 HN",
    "addr:housenumber":"150",
    "addr:postcode":"9711 hn",
    "addr:street":"Gedempte Zuiderdiep",
    "iso:country":"NL",
    "sg:address":"Gedempte Zuiderdiep 150",
    "sg:city":"Groningen",
    "sg:orig_category":"Veilingen",
    "sg:phone":"+31 50 312 9274",
    "sg:postcode":"9711 HN",
    "sg:province":"Groningen",
    "wof:name":"Joop Van Den Enden'S Veilingen",
    "wof:placetype":"venue"
},
  "geometry": {"coordinates":[6.562161,53.214752],"type":"Point"}
}