{
  "type": "Feature",
  "properties": {
    "iso:country":"NL",
    "sg:address":"Gedempte Zuiderdiep 150",
    "sg:city":"Groningen",
    "sg:orig_category":"Veilingen",
    "sg:phone":"+31 50 312 9274",
    "sg:postcode":"9711 HN",
    "sg:province":"Groningen",
    "wof:name":"Joop Van Den Enden'S Veilingen",
    "wof:placetype":"venue"
},
  "geometry": {"coordinates":[6.562161,53.214752],"type":"Point"}
}