{
  "type": "Feature",
  "properties": {
    "addr:full":"Marco Polostraat 197 Amsterdam Noord-Holland 1057 WK",
    "addr:housenumber":"197",
    "addr:postcode":"1057 wk",
    "addr:street":"Marco Polostraat",
    "iso:country":"NL",
    "sg:address":"Marco Polostraat 197",
    "sg:city":"Amsterdam",
    "sg:classifiers":[
        {
            "category":"Communications",
            "subcategory":"Television Station",
            "type":"Services"
        }
    ],
    "sg:phone":"+31 20 616 9549",
    "sg:postcode":"1057 WK",
    "sg:province":"Noord-Holland",
    "sg:tags":[
        "video",
        "audio",
        "verhuur"
    ],
    "wof:name":"Naseeb Video & Music Centre",
    "wof:placetype":"venue"
},
  "geometry": {"coordinates":[4.855375,52.369961],"type":"Point"}
}