{
  "type": "Feature",
  "properties": {
    "iso:country":"NL",
    "sg:address":"Vinselaarsewg 14",
    "sg:city":"Stoutenburg Noord",
    "sg:orig_category":"Administratie- En Boekhoudkantoren",
    "sg:phone":"+31 342 451 103",
    "sg:postcode":"3836 PG",
    "sg:province":"Utrecht",
    "wof:name":"Brand, J",
    "wof:placetype":"venue"
},
  "geometry": {"coordinates":[5.479566,52.153183],"type":"Point"}
}