{
  "type": "Feature",
  "properties": {
    "addr:full":"Reigerskamp 556 Maarssen Utrecht 3607 JG",
    "addr:housenumber":"556",
    "addr:postcode":"3607 jg",
    "addr:street":"Reigerskamp",
    "iso:country":"NL",
    "sg:address":"Reigerskamp 556",
    "sg:city":"Maarssen",
    "sg:orig_category":"Kantoor- En Secretariaatsservice",
    "sg:phone":"+31 346 551 255",
    "sg:postcode":"3607 JG",
    "sg:province":"Utrecht",
    "wof:name":"Maarssenbroek",
    "wof:placetype":"venue"
},
  "geometry": {"coordinates":[5.0173530579,52.1336135864],"type":"Point"}
}