{
  "type": "Feature",
  "properties": {
    "iso:country":"NL",
    "sg:address":"Reigerskamp 556",
    "sg:city":"Maarssen",
    "sg:orig_category":"Kantoor- En Secretariaatsservice",
    "sg:phone":"+31 346 551 255",
    "sg:postcode":"3607 JG",
    "sg:province":"Utrecht",
    "wof:name":"Maarssenbroek",
    "wof:placetype":"venue"
},
  "geometry": {"coordinates":[5.0173530579,52.1336135864],"type":"Point"}
}