{
  "type": "Feature",
  "properties": {
    "addr:full":"Bosscheweg 52 Boxtel Noord-Brabant 5281 AK",
    "addr:housenumber":"52",
    "addr:postcode":"5281 ak",
    "addr:street":"Bosscheweg",
    "iso:country":"NL",
    "sg:address":"Bosscheweg 52",
    "sg:city":"Boxtel",
    "sg:classifiers":[
        {
            "category":"Travel",
            "subcategory":"Hotels & Motels",
            "type":"Entertainment"
        }
    ],
    "sg:phone":"+31 411 672 833",
    "sg:postcode":"5281 AK",
    "sg:province":"Noord-Brabant",
    "wof:name":"Hotel Cafe Restaurant De Postiljon",
    "wof:placetype":"venue"
},
  "geometry": {"coordinates":[5.324307,51.596203],"type":"Point"}
}