{
  "type": "Feature",
  "properties": {
    "addr:full":"Postbus 283 Tiel Gelderland 4000 AG",
    "addr:housenumber":"283",
    "addr:postcode":"4000",
    "addr:street":"Postbus;Gelderland",
    "iso:country":"NL",
    "sg:address":"Postbus 283",
    "sg:city":"Tiel",
    "sg:orig_category":"Omroep",
    "sg:phone":"+31 344 624 033",
    "sg:postcode":"4000 AG",
    "sg:province":"Gelderland",
    "wof:name":"Gelderland",
    "wof:placetype":"venue"
},
  "geometry": {"coordinates":[5.430696,51.888096],"type":"Point"}
}