{
  "type": "Feature",
  "properties": {
    "addr:full":"Heemraadstraat 251 'S Gravenhage Zuid-Holland 2586 SW",
    "addr:housenumber":"251 ';2586",
    "addr:street":"Heemraadstraat;Sw",
    "iso:country":"NL",
    "sg:address":"Heemraadstraat 251",
    "sg:city":"'S Gravenhage",
    "sg:orig_category":"Juweliers",
    "sg:phone":"+31 70 306 1192",
    "sg:postcode":"2586 SW",
    "sg:province":"Zuid-Holland",
    "wof:name":"Juwelier A. Van Wijnen",
    "wof:placetype":"venue"
},
  "geometry": {"coordinates":[4.278803,52.103893],"type":"Point"}
}