{
  "type": "Feature",
  "properties": {
    "iso:country":"NL",
    "sg:address":"Kwinkelerweg 27",
    "sg:city":"Enschede",
    "sg:orig_category":"Verzekeringen",
    "sg:phone":"+31 53 428 2304",
    "sg:postcode":"7548 BR",
    "sg:province":"NL.08",
    "wof:name":"Assurantiekantoor Hondeveld",
    "wof:placetype":"venue"
},
  "geometry": {"coordinates":[6.796777,52.206066],"type":"Point"}
}