{
  "type": "Feature",
  "properties": {
    "addr:full":"Kwinkelerweg 27 Enschede NL.08 7548 BR",
    "addr:housenumber":"27",
    "addr:postcode":"7548 br",
    "addr:street":"Kwinkelerweg",
    "iso:country":"NL",
    "sg:address":"Kwinkelerweg 27",
    "sg:city":"Enschede",
    "sg:orig_category":"Verzekeringen",
    "sg:phone":"+31 53 428 2304",
    "sg:postcode":"7548 BR",
    "sg:province":"NL.08",
    "wof:name":"Assurantiekantoor Hondeveld",
    "wof:placetype":"venue"
},
  "geometry": {"coordinates":[6.796777,52.206066],"type":"Point"}
}