{
  "type": "Feature",
  "properties": {
    "addr:full":"Lambertusstraat 181 Rotterdam South Holland 3061 XZ",
    "addr:housenumber":"181",
    "addr:postcode":"3061 xz",
    "addr:street":"Lambertusstraat",
    "iso:country":"NL",
    "sg:address":"Lambertusstraat 181",
    "sg:city":"Rotterdam",
    "sg:orig_category":"Etaleurs And Showroominrichters",
    "sg:phone":"+31 10 213 1312",
    "sg:postcode":"3061 XZ",
    "sg:province":"South Holland",
    "wof:name":"Etalage Styling",
    "wof:placetype":"venue"
},
  "geometry": {"coordinates":[4.509428,51.921352],"type":"Point"}
}