{
  "type": "Feature",
  "properties": {
    "iso:country":"NL",
    "sg:address":"Geestbrugw 71",
    "sg:city":"Rijswijk",
    "sg:orig_category":"Artsen - Huisartsen",
    "sg:phone":"+31 70 395 0808",
    "sg:postcode":"2281 CG",
    "sg:province":"Zuid-Holland",
    "wof:name":"Galestien, J L",
    "wof:placetype":"venue"
},
  "geometry": {"coordinates":[4.341444,52.058304],"type":"Point"}
}