{
  "type": "Feature",
  "properties": {
    "addr:full":"De Compagnie 17 Zwaag North Holland 1689 AG",
    "addr:housenumber":"17",
    "addr:postcode":"1689",
    "addr:street":"De Compagnie;Holland",
    "iso:country":"NL",
    "sg:address":"De Compagnie 17",
    "sg:city":"Zwaag",
    "sg:orig_category":"Grafische Bedrijven",
    "sg:phone":"+31 229 218 234",
    "sg:postcode":"1689 AG",
    "sg:province":"North Holland",
    "wof:name":"Duo Pak",
    "wof:placetype":"venue"
},
  "geometry": {"coordinates":[5.058868,52.669491],"type":"Point"}
}