{
  "type": "Feature",
  "properties": {
    "addr:full":"Montenaken 8 Steenbergen Nb North Brabant 4651 JL",
    "addr:housenumber":"8;nb",
    "addr:postcode":"4651 jl",
    "addr:street":"Montenaken",
    "iso:country":"NL",
    "sg:address":"Montenaken 8",
    "sg:city":"Steenbergen Nb",
    "sg:orig_category":"Makelaars In Onroerend Goed",
    "sg:phone":"+31 167 565 228",
    "sg:postcode":"4651 JL",
    "sg:province":"North Brabant",
    "wof:name":"Assurantien Een Vastgoed Van Loenhout Bv",
    "wof:placetype":"venue"
},
  "geometry": {"coordinates":[4.312267,51.577229],"type":"Point"}
}