{
  "type": "Feature",
  "properties": {
    "addr:full":"Langenoordstr 56 Zevenbergen Noord-Brabant 4761 DN",
    "addr:housenumber":"56",
    "addr:postcode":"4761 dn",
    "addr:street":"Langenoordstr",
    "iso:country":"NL",
    "sg:address":"Langenoordstr 56",
    "sg:city":"Zevenbergen",
    "sg:orig_category":"Zonweringen",
    "sg:phone":"+31 168 324 314",
    "sg:postcode":"4761 DN",
    "sg:province":"Noord-Brabant",
    "wof:name":"Florama Zevenbergen Bv",
    "wof:placetype":"venue"
},
  "geometry": {"coordinates":[4.605426,51.646156],"type":"Point"}
}