{
  "type": "Feature",
  "properties": {
    "iso:country":"NL",
    "sg:address":"Dorpswg 4",
    "sg:city":"Ysselmuiden",
    "sg:orig_category":"Woningbouw- Verenigingen En -Stichtingen",
    "sg:phone":"+31 38 332 3399",
    "sg:postcode":"8271 BM",
    "sg:province":"NL.08",
    "wof:name":"Beter Wonen, Sticht",
    "wof:placetype":"venue"
},
  "geometry": {"coordinates":[5.9310269356,52.5635490417],"type":"Point"}
}