{
  "type": "Feature",
  "properties": {
    "addr:full":"Cannerweg 342 Maastricht Limburg 6213 NC",
    "addr:housenumber":"342",
    "addr:postcode":"6213 nc",
    "addr:street":"Cannerweg",
    "iso:country":"NL",
    "sg:address":"Cannerweg 342",
    "sg:city":"Maastricht",
    "sg:orig_category":"Binnenhuisarchitecten",
    "sg:phone":"+31 43 325 0420",
    "sg:postcode":"6213 NC",
    "sg:province":"Limburg",
    "wof:name":"A. Bovens-Swinnen",
    "wof:placetype":"venue"
},
  "geometry": {"coordinates":[5.670018,50.830051],"type":"Point"}
}