{
  "type": "Feature",
  "properties": {
    "addr:full":"Dorpsstraat 6 Gapinge Zeeland 4352 AC",
    "addr:housenumber":"6",
    "addr:postcode":"4352 ac",
    "addr:street":"Dorpsstraat",
    "iso:country":"NL",
    "sg:address":"Dorpsstraat 6",
    "sg:city":"Gapinge",
    "sg:orig_category":"Boekhouders",
    "sg:phone":"+31 118 596 070",
    "sg:postcode":"4352 AC",
    "sg:province":"Zeeland",
    "wof:name":"P.M. Stam Administratie & Adviesburo",
    "wof:placetype":"venue"
},
  "geometry": {"coordinates":[3.628736,51.54718],"type":"Point"}
}