{
  "type": "Feature",
  "properties": {
    "addr:full":"Meezenbroekerwg 13 Heerlen Limburg 6415 SC",
    "addr:housenumber":"13",
    "addr:postcode":"6415 sc",
    "addr:street":"Meezenbroekerwg",
    "iso:country":"NL",
    "sg:address":"Meezenbroekerwg 13",
    "sg:city":"Heerlen",
    "sg:orig_category":"Bejaarden - Verzorgingstehuizen",
    "sg:phone":"+31 45 572 0020",
    "sg:postcode":"6415 SC",
    "sg:province":"Limburg",
    "wof:name":"Regenboog, De",
    "wof:placetype":"venue"
},
  "geometry": {"coordinates":[5.982699,50.900085],"type":"Point"}
}