{
  "type": "Feature",
  "properties": {
    "addr:full":"De Weert 5 Abcoude Utrecht 1391 JK",
    "addr:housenumber":"5",
    "addr:postcode":"1391 jk",
    "addr:street":"De Weert",
    "iso:country":"NL",
    "sg:address":"De Weert 5",
    "sg:city":"Abcoude",
    "sg:orig_category":"Kappers",
    "sg:phone":"+31 294 285 354",
    "sg:postcode":"1391 JK",
    "sg:province":"Utrecht",
    "wof:name":"Kapsalon Marian Van Den Haak",
    "wof:placetype":"venue"
},
  "geometry": {"coordinates":[4.965200901,52.2704963684],"type":"Point"}
}