{
  "type": "Feature",
  "properties": {
    "addr:full":"Dorpsplein 8 Kesteren Gelderland 4041 GH",
    "addr:housenumber":"8",
    "addr:postcode":"4041 gh",
    "addr:street":"Dorpsplein;Gelderland",
    "iso:country":"NL",
    "sg:address":"Dorpsplein 8",
    "sg:city":"Kesteren",
    "sg:classifiers":[
        {
            "category":"Fast Food",
            "type":"Food & Drink"
        }
    ],
    "sg:phone":"+31 488 481 892",
    "sg:postcode":"4041 GH",
    "sg:province":"Gelderland",
    "sg:tags":[
        "afhaal",
        "restaurant"
    ],
    "wof:name":"T Karrewiel",
    "wof:placetype":"venue"
},
  "geometry": {"coordinates":[5.572982,51.936089],"type":"Point"}
}