{
  "type": "Feature",
  "properties": {
    "addr:full":"Hoekstraat 21 Bunschoten Spakenburg Utrecht 3751 AL",
    "addr:housenumber":"21",
    "addr:postcode":"3751 al",
    "addr:street":"Hoekstraat",
    "iso:country":"NL",
    "sg:address":"Hoekstraat 21",
    "sg:city":"Bunschoten Spakenburg",
    "sg:orig_category":"Visspeciaalzaken",
    "sg:phone":"+31 33 298 7035",
    "sg:postcode":"3751 AL",
    "sg:province":"Utrecht",
    "wof:name":"Het Viscentrum Peter De Graaf En Zoon",
    "wof:placetype":"venue"
},
  "geometry": {"coordinates":[5.379358,52.254383],"type":"Point"}
}