{
  "type": "Feature",
  "properties": {
    "addr:full":"Vlasakkers 13 Vroomshoop Overijssel 7681 LR",
    "addr:housenumber":"13",
    "addr:postcode":"7681 lr",
    "addr:street":"Vlasakkers",
    "iso:country":"NL",
    "sg:address":"Vlasakkers 13",
    "sg:city":"Vroomshoop",
    "sg:orig_category":"Autorijscholen",
    "sg:phone":"+31 546 643 379",
    "sg:postcode":"7681 LR",
    "sg:province":"Overijssel",
    "wof:name":"Wolbers, Henk",
    "wof:placetype":"venue"
},
  "geometry": {"coordinates":[6.566984,52.468529],"type":"Point"}
}