{
  "type": "Feature",
  "properties": {
    "iso:country":"NL",
    "sg:address":"Toutenburg 14 Secr",
    "sg:city":"Heemskerk",
    "sg:orig_category":"Verenigingen En Stichtingen",
    "sg:phone":"+31 251 230 682",
    "sg:postcode":"1965 BX",
    "sg:province":"North Holland",
    "wof:name":"Hulp Kindertehuizen Roemenie, Sticht",
    "wof:placetype":"venue"
},
  "geometry": {"coordinates":[4.668349,52.502331],"type":"Point"}
}