{
  "type": "Feature",
  "properties": {
    "addr:full":"Laurent Rampartstraat 34 Halsteren Noord-Brabant 4661 KH",
    "addr:housenumber":"34",
    "addr:postcode":"4661 kh",
    "addr:street":"Laurent Rampartstraat",
    "iso:country":"NL",
    "sg:address":"Laurent Rampartstraat 34",
    "sg:city":"Halsteren",
    "sg:orig_category":"Loodgieterswerk, Verwarming And Sanitaire Installaties",
    "sg:phone":"+31 164 687 134",
    "sg:postcode":"4661 KH",
    "sg:province":"Noord-Brabant",
    "wof:name":"G. Lambregts Onderhoud En Service",
    "wof:placetype":"venue"
},
  "geometry": {"coordinates":[4.273885,51.523544],"type":"Point"}
}