{
  "type": "Feature",
  "properties": {
    "addr:full":"Masterode 1 Helmond Noord-Brabant 5709 HX",
    "addr:housenumber":"1",
    "addr:postcode":"5709 hx",
    "addr:street":"Masterode",
    "iso:country":"NL",
    "sg:address":"Masterode 1",
    "sg:city":"Helmond",
    "sg:orig_category":"Artsen And Specialisten",
    "sg:phone":"+31 492 510 515",
    "sg:postcode":"5709 HX",
    "sg:province":"Noord-Brabant",
    "wof:name":"C.P.W.J. V.D. Nieuwenhof",
    "wof:placetype":"venue"
},
  "geometry": {"coordinates":[5.70085,51.481094],"type":"Point"}
}