{
  "type": "Feature",
  "properties": {
    "addr:full":"Schakelweg 215 Hoogvliet Rt South Holland 3192 JL",
    "addr:housenumber":"215",
    "addr:postcode":"3192 jl",
    "addr:street":"Schakelweg;Rt South",
    "iso:country":"NL",
    "sg:address":"Schakelweg 215",
    "sg:city":"Hoogvliet Rt",
    "sg:orig_category":"Verzekeringen",
    "sg:phone":"+31 10 416 2702",
    "sg:postcode":"3192 JL",
    "sg:province":"South Holland",
    "wof:name":"Assurantiekantoor J Dijksman",
    "wof:placetype":"venue"
},
  "geometry": {"coordinates":[4.363529,51.850395],"type":"Point"}
}