{
  "type": "Feature",
  "properties": {
    "addr:full":"Deken Van Den Heuvelstr 64 Gemert North Brabant 5421 SH",
    "addr:housenumber":"64",
    "addr:postcode":"5421 sh",
    "addr:street":"Deken Van Den Heuvelstr",
    "iso:country":"NL",
    "sg:address":"Deken Van Den Heuvelstr 64",
    "sg:city":"Gemert",
    "sg:orig_category":"Geluidsopnamen",
    "sg:phone":"+31 492 366 167",
    "sg:postcode":"5421 SH",
    "sg:province":"North Brabant",
    "wof:name":"Smalltown Works",
    "wof:placetype":"venue"
},
  "geometry": {"coordinates":[5.691694,51.564198],"type":"Point"}
}