{
  "type": "Feature",
  "properties": {
    "addr:full":"Grenssteen 27 Breda Noord-Brabant 4815 PP",
    "addr:housenumber":"27",
    "addr:postcode":"4815 pp",
    "addr:street":"Grenssteen",
    "iso:country":"NL",
    "sg:address":"Grenssteen 27",
    "sg:city":"Breda",
    "sg:orig_category":"Projectontwikkeling",
    "sg:phone":"+31 76 541 8709",
    "sg:postcode":"4815 PP",
    "sg:province":"Noord-Brabant",
    "sg:website":"http://www.heja.com",
    "wof:name":"Veldzicht Vof",
    "wof:placetype":"venue"
},
  "geometry": {"coordinates":[4.742201,51.597107],"type":"Point"}
}