{
  "type": "Feature",
  "properties": {
    "iso:country":"NL",
    "sg:address":"Zichthof 10",
    "sg:city":"Purmerend",
    "sg:orig_category":"Bibliotheken And Openbare Archieven",
    "sg:phone":"+31 299 643 890",
    "sg:postcode":"1445 HC",
    "sg:province":"Noord-Holland",
    "wof:name":"Openbare Leeszaal En Bibliotheek",
    "wof:placetype":"venue"
},
  "geometry": {"coordinates":[4.985225,52.506939],"type":"Point"}
}