{
  "type": "Feature",
  "properties": {
    "addr:full":"Heerlerbaan 218 Heerlen Limburg 6418 CM",
    "addr:housenumber":"218",
    "addr:postcode":"6418 cm",
    "addr:street":"Heerlerbaan",
    "iso:country":"NL",
    "sg:address":"Heerlerbaan 218",
    "sg:city":"Heerlen",
    "sg:orig_category":"Verhuur Bouwmachines",
    "sg:phone":"+31 45 541 1515",
    "sg:postcode":"6418 CM",
    "sg:province":"Limburg",
    "wof:name":"P.B.M. Boels Heerlen Bv",
    "wof:placetype":"venue"
},
  "geometry": {"coordinates":[6.003651,50.86396],"type":"Point"}
}