{
  "type": "Feature",
  "properties": {
    "addr:full":"Baarsjesweg 145 Amsterdam North Holland 1057 HM",
    "addr:housenumber":"145",
    "addr:postcode":"1057 hm",
    "addr:street":"Baarsjesweg",
    "iso:country":"NL",
    "sg:address":"Baarsjesweg 145",
    "sg:city":"Amsterdam",
    "sg:orig_category":"Kinderopvang Behalve Thuis",
    "sg:phone":"+31 20 616 6861",
    "sg:postcode":"1057 HM",
    "sg:province":"North Holland",
    "wof:name":"Kinderdagverblijf Tuimelaar",
    "wof:placetype":"venue"
},
  "geometry": {"coordinates":[4.863005,52.368591],"type":"Point"}
}