{
  "type": "Feature",
  "properties": {
    "addr:full":"Agaatvlinder 66 Amersfoort Utrecht 3822 AZ",
    "addr:housenumber":"66",
    "addr:postcode":"3822",
    "addr:street":"Agaatvlinder",
    "iso:country":"NL",
    "sg:address":"Agaatvlinder 66",
    "sg:city":"Amersfoort",
    "sg:orig_category":"Adviesbureaus Verzekeringen",
    "sg:phone":"+31 33 457 2433",
    "sg:postcode":"3822 AZ",
    "sg:province":"Utrecht",
    "wof:name":"Input Bv",
    "wof:placetype":"venue"
},
  "geometry": {"coordinates":[5.405163,52.187103],"type":"Point"}
}