{
  "type": "Feature",
  "properties": {
    "addr:full":"Kerkstr 19 Noordwijk South Holland 2201 KK",
    "addr:housenumber":"19",
    "addr:postcode":"2201 kk",
    "addr:street":"Kerkstr",
    "iso:country":"NL",
    "sg:address":"Kerkstr 19",
    "sg:city":"Noordwijk",
    "sg:orig_category":"Bloemen En Planten",
    "sg:phone":"+31 71 361 7863",
    "sg:postcode":"2201 KK",
    "sg:province":"South Holland",
    "wof:name":"Vivace",
    "wof:placetype":"venue"
},
  "geometry": {"coordinates":[4.446261,52.234386],"type":"Point"}
}