{
  "type": "Feature",
  "properties": {
    "iso:country":"NL",
    "sg:address":"Suikerbakkerstr 12",
    "sg:city":"Hoogvliet Rt",
    "sg:orig_category":"Banden - Fabrieken En Groothandel",
    "sg:phone":"+31 10 416 6867",
    "sg:postcode":"3194 AK",
    "sg:province":"South Holland",
    "wof:name":"Free Tyre Bv",
    "wof:placetype":"venue"
},
  "geometry": {"coordinates":[4.379339,51.870571],"type":"Point"}
}