{
  "type": "Feature",
  "properties": {
    "addr:full":"Emmastr 12 Heinenoord South Holland 3274 AC",
    "addr:housenumber":"12",
    "addr:postcode":"3274 ac",
    "addr:street":"Emmastr",
    "iso:country":"NL",
    "sg:address":"Emmastr 12",
    "sg:city":"Heinenoord",
    "sg:orig_category":"Bloemen En Planten",
    "sg:phone":"+31 186 609 907",
    "sg:postcode":"3274 AC",
    "sg:province":"South Holland",
    "wof:name":"Crea-Fleur",
    "wof:placetype":"venue"
},
  "geometry": {"coordinates":[4.476987,51.826237],"type":"Point"}
}