{
  "type": "Feature",
  "properties": {
    "addr:full":"Boswijklaan 20 Doorn Utrecht 3941 ZN",
    "addr:housenumber":"20",
    "addr:postcode":"3941 zn",
    "addr:street":"Boswijklaan",
    "iso:country":"NL",
    "sg:address":"Boswijklaan 20",
    "sg:city":"Doorn",
    "sg:orig_category":"Loodgieterswerk, Verwarming And Sanitaire Installaties",
    "sg:phone":"+31 343 521 251",
    "sg:postcode":"3941 ZN",
    "sg:province":"Utrecht",
    "wof:name":"Gastechnisch Installatiebedrijf Houthuiz",
    "wof:placetype":"venue"
},
  "geometry": {"coordinates":[5.297527,52.038761],"type":"Point"}
}