{
  "type": "Feature",
  "properties": {
    "addr:full":"Ottho Heldringstraat 43 Amsterdam Noord-Holland 1066 XT",
    "addr:housenumber":"43",
    "addr:postcode":"1066 xt",
    "addr:street":"Ottho Heldringstraat",
    "iso:country":"NL",
    "sg:address":"Ottho Heldringstraat 43",
    "sg:city":"Amsterdam",
    "sg:orig_category":"Beveiligingsdiensten And Bewakingsbedrijven",
    "sg:phone":"+31 20 669 0801",
    "sg:postcode":"1066 XT",
    "sg:province":"Noord-Holland",
    "wof:name":"Seceurop Nederland Bv",
    "wof:placetype":"venue"
},
  "geometry": {"coordinates":[4.83273983,52.3476448059],"type":"Point"}
}