{
  "type": "Feature",
  "properties": {
    "addr:full":"Visbrug 6 Oudewater Utrecht 3421 AH",
    "addr:housenumber":"6",
    "addr:postcode":"3421 ah",
    "addr:street":"Visbrug",
    "iso:country":"NL",
    "sg:address":"Visbrug 6",
    "sg:city":"Oudewater",
    "sg:orig_category":"Adviesbureaus Bedrijfsorganisatie",
    "sg:phone":"+31 348 430 650",
    "sg:postcode":"3421 AH",
    "sg:province":"Utrecht",
    "wof:name":"Treecomm Bv",
    "wof:placetype":"venue"
},
  "geometry": {"coordinates":[4.87197,52.022362],"type":"Point"}
}