{
  "type": "Feature",
  "properties": {
    "iso:country":"NL",
    "sg:address":"Oranje Nassaulaan 47",
    "sg:city":"Amsterdam",
    "sg:classifiers":[
        {
            "category":"Professional",
            "subcategory":"Accounting & Tax Preparation",
            "type":"Services"
        }
    ],
    "sg:phone":"+31 20 676 3013",
    "sg:postcode":"1075 AK",
    "sg:province":"Noord-Holland",
    "sg:tags":[
        "accountant"
    ],
    "wof:name":"Omnyacc. Rijsselbloem Van Zuilen Accountants",
    "wof:placetype":"venue"
},
  "geometry": {"coordinates":[4.860279,52.353951],"type":"Point"}
}