{
  "type": "Feature",
  "properties": {
    "addr:full":"Hoofdstr 73 Diever Drenthe 7981 AD",
    "addr:housenumber":"73",
    "addr:postcode":"7981 ad",
    "addr:street":"Hoofdstr",
    "iso:country":"NL",
    "sg:address":"Hoofdstr 73",
    "sg:city":"Diever",
    "sg:orig_category":"Bloemen En Planten",
    "sg:phone":"+31 521 591 437",
    "sg:postcode":"7981 AD",
    "sg:province":"Drenthe",
    "sg:website":"http://www.bloemenhuishofman.nl",
    "wof:name":"Hofman, H",
    "wof:placetype":"venue"
},
  "geometry": {"coordinates":[6.321771,52.85371],"type":"Point"}
}