{
  "type": "Feature",
  "properties": {
    "iso:country":"NL",
    "sg:address":"Stadhoudersln 64",
    "sg:city":"Utrecht",
    "sg:classifiers":[
        {
            "category":"Professional",
            "subcategory":"Accounting & Tax Preparation",
            "type":"Services"
        }
    ],
    "sg:phone":"+31 30 251 4982",
    "sg:postcode":"3583 JL",
    "sg:province":"Utrecht",
    "sg:tags":[
        "accountant",
        "en",
        "-kantoren",
        "register-"
    ],
    "wof:name":"Overboom",
    "wof:placetype":"venue"
},
  "geometry": {"coordinates":[5.14371,52.086601],"type":"Point"}
}