{
  "type": "Feature",
  "properties": {
    "addr:full":"Kerkweg 30 Venhuizen Noord-Holland 1606 AR",
    "addr:housenumber":"30",
    "addr:postcode":"1606",
    "addr:street":"Kerkweg",
    "iso:country":"NL",
    "sg:address":"Kerkweg 30",
    "sg:city":"Venhuizen",
    "sg:orig_category":"Banken And Kredietinstellingen",
    "sg:phone":"+31 228 541 493",
    "sg:postcode":"1606 AR",
    "sg:province":"Noord-Holland",
    "wof:name":"Fortis Bank",
    "wof:placetype":"venue"
},
  "geometry": {"coordinates":[-58.535439,-34.526402],"type":"Point"}
}