{
  "type": "Feature",
  "properties": {
    "addr:full":"Glinswei 1 Leeuwarden Provincie Friesland 8939 CB",
    "addr:housenumber":"1;8939",
    "addr:postcode":"cb",
    "addr:street":"Glinswei;Provincie Friesland",
    "iso:country":"NL",
    "sg:address":"Glinswei 1",
    "sg:city":"Leeuwarden",
    "sg:orig_category":"Verenigingen En Stichtingen",
    "sg:phone":"+31 58 280 4715",
    "sg:postcode":"8939 CB",
    "sg:province":"Provincie Friesland",
    "wof:name":"Pleats, Sticht De",
    "wof:placetype":"venue"
},
  "geometry": {"coordinates":[5.83885,53.18074],"type":"Point"}
}