{
  "type": "Feature",
  "properties": {
    "addr:full":"Groenstr 262 Tilburg North Brabant 5021 LP",
    "addr:housenumber":"262",
    "addr:postcode":"5021 lp",
    "iso:country":"NL",
    "sg:address":"Groenstr 262",
    "sg:city":"Tilburg",
    "sg:orig_category":"Cafetaria'S",
    "sg:phone":"+31 13 542 0803",
    "sg:postcode":"5021 LP",
    "sg:province":"North Brabant",
    "wof:name":"Smoske, Bestaria 'T",
    "wof:placetype":"venue"
},
  "geometry": {"coordinates":[5.162858,51.623158],"type":"Point"}
}