{
  "type": "Feature",
  "properties": {
    "addr:full":"Achterdk 13C Helmond North Brabant 5705 CB",
    "addr:housenumber":"13c",
    "addr:postcode":"5705 cb",
    "addr:street":"Achterdk",
    "iso:country":"NL",
    "sg:address":"Achterdk 13C",
    "sg:city":"Helmond",
    "sg:classifiers":[
        {
            "category":"Manufacturing",
            "subcategory":"Textiles",
            "type":"Manufacturing & Wholesale Goods"
        }
    ],
    "sg:phone":"+31 6 50407090",
    "sg:postcode":"5705 CB",
    "sg:province":"North Brabant",
    "sg:tags":[
        "polyester"
    ],
    "sg:website":"http://www.vepo-polyester.nl",
    "wof:name":"Vepo-Polyester",
    "wof:placetype":"venue"
},
  "geometry": {"coordinates":[5.658284,51.482239],"type":"Point"}
}