{
  "type": "Feature",
  "properties": {
    "addr:full":"Weyerbeemd 6 Weert Limburg 6004 MC",
    "addr:housenumber":"6",
    "addr:postcode":"6004 mc",
    "addr:street":"Weyerbeemd",
    "iso:country":"NL",
    "sg:address":"Weyerbeemd 6",
    "sg:city":"Weert",
    "sg:orig_category":"Oud Metaal",
    "sg:phone":"+31 495 520 828",
    "sg:postcode":"6004 MC",
    "sg:province":"Limburg",
    "wof:name":"Pruymboom, J F",
    "wof:placetype":"venue"
},
  "geometry": {"coordinates":[5.7183580399,51.2555732727],"type":"Point"}
}