{
  "type": "Feature",
  "properties": {
    "addr:full":"Schorpioen 96 Bilthoven Utrecht 3721 WK",
    "addr:housenumber":"96",
    "addr:postcode":"3721 wk",
    "addr:street":"Schorpioen",
    "iso:country":"NL",
    "sg:address":"Schorpioen 96",
    "sg:city":"Bilthoven",
    "sg:orig_category":"Kunstnijverheid",
    "sg:phone":"+31 30 225 2287",
    "sg:postcode":"3721 WK",
    "sg:province":"Utrecht",
    "wof:name":"Matangi",
    "wof:placetype":"venue"
},
  "geometry": {"coordinates":[5.183847,52.123363],"type":"Point"}
}