{
  "type": "Feature",
  "properties": {
    "addr:full":"Balistr 51 S Gravenhage Zuid-Holland 2585 XM",
    "addr:housenumber":"51;gravenhage",
    "addr:postcode":"2585 xm",
    "addr:street":"Balistr;S",
    "iso:country":"NL",
    "sg:address":"Balistr 51",
    "sg:city":"S Gravenhage",
    "sg:orig_category":"Fotografie Reclame En Mode",
    "sg:phone":"+31 70 392 3999",
    "sg:postcode":"2585 XM",
    "sg:province":"Zuid-Holland",
    "wof:name":"Adriaans, Bas",
    "wof:placetype":"venue"
},
  "geometry": {"coordinates":[4.29777,52.094799],"type":"Point"}
}