{
  "type": "Feature",
  "properties": {
    "iso:country":"NL",
    "sg:address":"Oosterdiep 23",
    "sg:city":"Dordrecht",
    "sg:orig_category":"Beveiliging",
    "sg:phone":"+31 78 621 1449",
    "sg:postcode":"3313 TE",
    "sg:province":"Zuid-Holland",
    "sg:website":"http://www.powerlock.nl",
    "wof:name":"Powerlock",
    "wof:placetype":"venue"
},
  "geometry": {"coordinates":[4.721366,51.812332],"type":"Point"}
}