{
  "type": "Feature",
  "properties": {
    "addr:full":"Preludeweg 24 Almere Flevoland 1312 SX",
    "addr:housenumber":"24",
    "addr:postcode":"1312 sx",
    "addr:street":"Preludeweg;Flevoland",
    "iso:country":"NL",
    "sg:address":"Preludeweg 24",
    "sg:city":"Almere",
    "sg:orig_category":"Kantoorartikelen",
    "sg:phone":"+31 36 536 8879",
    "sg:postcode":"1312 SX",
    "sg:province":"Flevoland",
    "wof:name":"R. Ten Hagen",
    "wof:placetype":"venue"
},
  "geometry": {"coordinates":[5.1859369278,52.3778381348],"type":"Point"}
}