{
  "type": "Feature",
  "properties": {
    "addr:full":"Kerkstraat 245 Wormerveer North Holland 1521 JK",
    "addr:housenumber":"245",
    "addr:postcode":"1521 jk",
    "addr:street":"Kerkstraat",
    "iso:country":"NL",
    "sg:address":"Kerkstraat 245",
    "sg:city":"Wormerveer",
    "sg:orig_category":"Autokeuringen",
    "sg:phone":"+31 75 628 6619",
    "sg:postcode":"1521 JK",
    "sg:province":"North Holland",
    "wof:name":"Esso",
    "wof:placetype":"venue"
},
  "geometry": {"coordinates":[4.781372,52.496353],"type":"Point"}
}