{
  "type": "Feature",
  "properties": {
    "addr:full":"Gasselterweg 4 Gasselternijveen Drenthe 9514 BL",
    "addr:housenumber":"4",
    "addr:postcode":"9514 bl",
    "addr:street":"Gasselterweg",
    "iso:country":"NL",
    "sg:address":"Gasselterweg 4",
    "sg:city":"Gasselternijveen",
    "sg:orig_category":"Wasserettes And Stomerijen",
    "sg:phone":"+31 599 512 976",
    "sg:postcode":"9514 BL",
    "sg:province":"Drenthe",
    "wof:name":"Gerner-Stomen",
    "wof:placetype":"venue"
},
  "geometry": {"coordinates":[6.8446950912,52.987071991],"type":"Point"}
}