{
  "type": "Feature",
  "properties": {
    "addr:full":"Newtonpln 17 S Gravenhage Zuid-Holland 2562 JT",
    "addr:housenumber":"17;gravenhage",
    "addr:postcode":"2562 jt",
    "addr:street":"Newtonpln;S",
    "iso:country":"NL",
    "sg:address":"Newtonpln 17",
    "sg:city":"S Gravenhage",
    "sg:orig_category":"Vertalers",
    "sg:phone":"+31 70 364 2037",
    "sg:postcode":"2562 JT",
    "sg:province":"Zuid-Holland",
    "wof:name":"Freeman",
    "wof:placetype":"venue"
},
  "geometry": {"coordinates":[4.28326,52.075001],"type":"Point"}
}