{
  "type": "Feature",
  "properties": {
    "addr:full":"Corsica 9 Veghel Noord-Brabant 5465 PS",
    "addr:housenumber":"9",
    "addr:postcode":"5465 ps",
    "addr:street":"Corsica",
    "iso:country":"NL",
    "sg:address":"Corsica 9",
    "sg:city":"Veghel",
    "sg:orig_category":"Machinehandel",
    "sg:phone":"+31 413 341 145",
    "sg:postcode":"5465 PS",
    "sg:province":"Noord-Brabant",
    "wof:name":"Demaco",
    "wof:placetype":"venue"
},
  "geometry": {"coordinates":[5.531871,51.593319],"type":"Point"}
}