{
  "type": "Feature",
  "properties": {
    "iso:country":"NL",
    "sg:address":"Annadaal 22",
    "sg:city":"Ede Gld",
    "sg:orig_category":"Organisatiebureaus",
    "sg:phone":"+31 318 575 643",
    "sg:postcode":"6715 JA",
    "sg:province":"Gelderland",
    "wof:name":"Ouwendijk, Tineke",
    "wof:placetype":"venue"
},
  "geometry": {"coordinates":[5.6382279396,52.0419006348],"type":"Point"}
}