{
  "type": "Feature",
  "properties": {
    "addr:full":"Vughterstr 87C S Hertogenbosch Noord-Brabant 5211 EZ",
    "addr:housenumber":"87c",
    "addr:postcode":"5211 ez",
    "addr:street":"Vughterstr;S Hertogenbosch",
    "iso:country":"NL",
    "sg:address":"Vughterstr 87C",
    "sg:city":"S Hertogenbosch",
    "sg:orig_category":"Kappersbenodigdheden",
    "sg:phone":"+31 73 614 4109",
    "sg:postcode":"5211 EZ",
    "sg:province":"Noord-Brabant",
    "wof:name":"Hair Self Shop Kappersbenodigdheden",
    "wof:placetype":"venue"
},
  "geometry": {"coordinates":[5.299756,51.686817],"type":"Point"}
}