{
  "type": "Feature",
  "properties": {
    "iso:country":"NL",
    "sg:address":"Industriewg 4",
    "sg:city":"Helvoirt",
    "sg:orig_category":"Koeltechniek",
    "sg:phone":"+31 411 641 978",
    "sg:postcode":"5268 BC",
    "sg:province":"Noord-Brabant",
    "wof:name":"Techna-Koude Bv",
    "wof:placetype":"venue"
},
  "geometry": {"coordinates":[5.233261,51.638714],"type":"Point"}
}