{
  "type": "Feature",
  "properties": {
    "addr:full":"Werenfriedplein 15 Arnhem Gelderland 6832 AJ",
    "addr:housenumber":"15",
    "addr:postcode":"6832 aj",
    "addr:street":"Werenfriedplein",
    "iso:country":"NL",
    "sg:address":"Werenfriedplein 15",
    "sg:city":"Arnhem",
    "sg:orig_category":"Artsen - Huisartsen",
    "sg:phone":"+31 26 321 3643",
    "sg:postcode":"6832 AJ",
    "sg:province":"Gelderland",
    "wof:name":"Pol & J Wiepkema, M C Van Der",
    "wof:placetype":"venue"
},
  "geometry": {"coordinates":[5.908443,51.96619],"type":"Point"}
}