{
  "type": "Feature",
  "properties": {
    "addr:full":"Molenstr 35 Lith Noord-Brabant 5397 EK",
    "addr:housenumber":"35",
    "addr:postcode":"5397 ek",
    "addr:street":"Molenstr",
    "iso:country":"NL",
    "sg:address":"Molenstr 35",
    "sg:city":"Lith",
    "sg:orig_category":"Grafische Bedrijven",
    "sg:phone":"+31 412 485 044",
    "sg:postcode":"5397 EK",
    "sg:province":"Noord-Brabant",
    "wof:name":"Adept",
    "wof:placetype":"venue"
},
  "geometry": {"coordinates":[-82.170288,27.862659],"type":"Point"}
}