{
  "type": "Feature",
  "properties": {
    "iso:country":"NL",
    "sg:address":"Telefoon",
    "sg:orig_category":"Adviesbureaus Bouwkunde",
    "sg:phone":"+31 30 638 1400",
    "sg:postcode":" ",
    "sg:province":"Texas",
    "sg:website":"http://www.keurhuis.nl",
    "wof:name":"Keurhuis Nederland Bv",
    "wof:placetype":"venue"
},
  "geometry": {"coordinates":[-96.018784,33.781052],"type":"Point"}
}