{
  "type": "Feature",
  "properties": {
    "addr:full":"L Delft 13-15 Middelburg Zeeland 4331 AJ",
    "addr:housenumber":"13-15",
    "addr:postcode":"4331 aj",
    "addr:street":"L Delft",
    "iso:country":"NL",
    "sg:address":"L Delft 13-15",
    "sg:city":"Middelburg",
    "sg:orig_category":"Opticiens",
    "sg:phone":"+31 118 628 886",
    "sg:postcode":"4331 AJ",
    "sg:province":"Zeeland",
    "wof:name":"Pearle",
    "wof:placetype":"venue"
},
  "geometry": {"coordinates":[3.6133420467,51.4981918335],"type":"Point"}
}