{
  "type": "Feature",
  "properties": {
    "addr:full":"Admiraal Helfrichweg 11 Leiden Zuid-Holland 2315 VC",
    "addr:housenumber":"11",
    "addr:postcode":"2315 vc",
    "addr:street":"Admiraal Helfrichweg",
    "iso:country":"NL",
    "sg:address":"Admiraal Helfrichweg 11",
    "sg:city":"Leiden",
    "sg:orig_category":"Wegen And Sportterreinen",
    "sg:phone":"+31 71 522 3529",
    "sg:postcode":"2315 VC",
    "sg:province":"Zuid-Holland",
    "wof:name":"Van Eijk Grond- En Wegenwerken Bv",
    "wof:placetype":"venue"
},
  "geometry": {"coordinates":[4.5132060051,52.1604652405],"type":"Point"}
}