{
  "type": "Feature",
  "properties": {
    "addr:full":"Havikstraat 19 Apeldoorn Gelderland 7331 CK",
    "addr:housenumber":"19",
    "addr:postcode":"7331 ck",
    "addr:street":"Havikstraat;Gelderland",
    "iso:country":"NL",
    "sg:address":"Havikstraat 19",
    "sg:city":"Apeldoorn",
    "sg:orig_category":"Zuivelproducten",
    "sg:phone":"+31 55 533 8285",
    "sg:postcode":"7331 CK",
    "sg:province":"Gelderland",
    "wof:name":"Waayer De Kaasboer Bv",
    "wof:placetype":"venue"
},
  "geometry": {"coordinates":[5.967233,52.205856],"type":"Point"}
}