{
  "type": "Feature",
  "properties": {
    "iso:country":"NL",
    "sg:address":"Spoorhaag 146",
    "sg:city":"Houten",
    "sg:orig_category":"Opticiens",
    "sg:phone":"+31 30 635 3853",
    "sg:postcode":"3995 EA",
    "sg:province":"Utrecht",
    "wof:name":"Pearle Opticiens",
    "wof:placetype":"venue"
},
  "geometry": {"coordinates":[5.168211937,52.0362586975],"type":"Point"}
}