{
  "type": "Feature",
  "properties": {
    "addr:full":"Zonnedauw 5 Schaijk North Brabant 5374 MA",
    "addr:housenumber":"5",
    "addr:postcode":"5374 ma",
    "addr:street":"Zonnedauw",
    "iso:country":"NL",
    "sg:address":"Zonnedauw 5",
    "sg:city":"Schaijk",
    "sg:orig_category":"Loodgieterswerk, Verwarming And Sanitaire Installaties",
    "sg:phone":"+31 486 463 423",
    "sg:postcode":"5374 MA",
    "sg:province":"North Brabant",
    "wof:name":"Th.N. Peters",
    "wof:placetype":"venue"
},
  "geometry": {"coordinates":[5.632512,51.752285],"type":"Point"}
}