{
  "type": "Feature",
  "properties": {
    "addr:full":"Beldsweg 10 Ambt Delden NL.08 7495 PJ",
    "addr:housenumber":"10",
    "addr:postcode":"nl.08 7495 pj",
    "addr:street":"Beldsweg",
    "iso:country":"NL",
    "sg:address":"Beldsweg 10",
    "sg:city":"Ambt Delden",
    "sg:orig_category":"Kampeerterreinen",
    "sg:phone":"+31 547 292 513",
    "sg:postcode":"7495 PJ",
    "sg:province":"NL.08",
    "wof:name":"De Oosterhof",
    "wof:placetype":"venue"
},
  "geometry": {"coordinates":[6.6684689522,52.2399482727],"type":"Point"}
}