{
  "type": "Feature",
  "properties": {
    "addr:full":"Weversbaan 25 Leiderdorp Zuid-Holland 2352 BZ",
    "addr:housenumber":"25",
    "addr:postcode":"2352 bz",
    "addr:street":"Weversbaan",
    "iso:country":"NL",
    "sg:address":"Weversbaan 25",
    "sg:city":"Leiderdorp",
    "sg:orig_category":"Horecabenodigdheden",
    "sg:phone":"+31 71 541 2011",
    "sg:postcode":"2352 BZ",
    "sg:province":"Zuid-Holland",
    "wof:name":"Horesca Horecavo",
    "wof:placetype":"venue"
},
  "geometry": {"coordinates":[4.520044,52.162594],"type":"Point"}
}