{
  "type": "Feature",
  "properties": {
    "addr:full":"F V Mierisstr 69A Amsterdam Noord-Holland 1071 RL",
    "addr:housenumber":"69a",
    "addr:postcode":"1071 rl",
    "addr:street":"Mierisstr",
    "iso:country":"NL",
    "sg:address":"F V Mierisstr 69A",
    "sg:city":"Amsterdam",
    "sg:classifiers":[
        {
            "category":"Travel",
            "subcategory":"Hotels & Motels",
            "type":"Entertainment"
        }
    ],
    "sg:phone":"+31 20 679 7203",
    "sg:postcode":"1071 RL",
    "sg:province":"Noord-Holland",
    "wof:name":"Janson",
    "wof:placetype":"venue"
},
  "geometry": {"coordinates":[4.87701,52.355549],"type":"Point"}
}