{
  "type": "Feature",
  "properties": {
    "addr:full":"Vivaldiweg 1 Bunschoten Spakenburg Utrecht 3752 GW",
    "addr:housenumber":"1",
    "addr:postcode":"3752 gw",
    "addr:street":"Vivaldiweg",
    "iso:country":"NL",
    "sg:address":"Vivaldiweg 1",
    "sg:city":"Bunschoten Spakenburg",
    "sg:classifiers":[
        {
            "category":"Education",
            "subcategory":"Preschool",
            "type":"Public Place"
        }
    ],
    "sg:phone":"+31 33 298 0714",
    "sg:postcode":"3752 GW",
    "sg:province":"Utrecht",
    "sg:tags":[
        "kleuteronderwijs",
        "basis-"
    ],
    "wof:name":"Groen Van Prinstererschool",
    "wof:placetype":"venue"
},
  "geometry": {"coordinates":[5.37005,52.247051],"type":"Point"}
}