{
  "type": "Feature",
  "properties": {
    "iso:country":"NL",
    "sg:address":"Molenbossen 622 , (Blerick)",
    "sg:city":"Venlo",
    "sg:orig_category":"Kaasgroothandel",
    "sg:phone":"+31 77 324 3000",
    "sg:postcode":"5923 AJ",
    "sg:province":"Limburg",
    "wof:name":"Tebben Bv, Kaashandel",
    "wof:placetype":"venue"
},
  "geometry": {"coordinates":[6.1421260834,51.3588600159],"type":"Point"}
}