{
  "type": "Feature",
  "properties": {
    "addr:full":"Emmastraat 53 Velp Gld Gelderland 6881 SR",
    "addr:housenumber":"53;6881",
    "addr:postcode":"sr",
    "addr:street":"Emmastraat;Gld Gelderland",
    "iso:country":"NL",
    "sg:address":"Emmastraat 53",
    "sg:city":"Velp Gld",
    "sg:orig_category":"Zuivelproducten",
    "sg:phone":"+31 26 364 7624",
    "sg:postcode":"6881 SR",
    "sg:province":"Gelderland",
    "wof:name":"J A J Vlaswinkel",
    "wof:placetype":"venue"
},
  "geometry": {"coordinates":[5.9742,51.993877],"type":"Point"}
}