{
  "type": "Feature",
  "properties": {
    "iso:country":"NL",
    "sg:address":"Spoorstraat 149",
    "sg:city":"Gennep",
    "sg:classifiers":[
        {
            "category":"Retail",
            "subcategory":"Photofinishing",
            "type":"Services"
        }
    ],
    "sg:phone":"+31 485 511 478",
    "sg:postcode":"6591 GT",
    "sg:province":"Limburg",
    "sg:tags":[
        "foto",
        "film"
    ],
    "wof:name":"Foto Video V.D. Hurk",
    "wof:placetype":"venue"
},
  "geometry": {"coordinates":[5.972352,51.695076],"type":"Point"}
}