{
  "type": "Feature",
  "properties": {
    "addr:full":"Emmasingel 31 Eindhoven North Brabant 5611 AZ",
    "addr:housenumber":"31",
    "addr:postcode":"5611 az",
    "addr:street":"Emmasingel",
    "iso:country":"NL",
    "sg:address":"Emmasingel 31",
    "sg:city":"Eindhoven",
    "sg:orig_category":"Medische Apparatuur And Prothesen Fab",
    "sg:phone":"+31 40 244 2952",
    "sg:postcode":"5611 AZ",
    "sg:province":"North Brabant",
    "wof:name":"Audicien Van Boxtel Bv",
    "wof:placetype":"venue"
},
  "geometry": {"coordinates":[5.474912,51.438843],"type":"Point"}
}