{
  "type": "Feature",
  "properties": {
    "addr:full":"Annerstreek 44 Annen South Carolina 9468 AP",
    "addr:housenumber":"44;9468",
    "addr:street":"Annerstreek;Ap",
    "iso:country":"NL",
    "sg:address":"Annerstreek 44",
    "sg:city":"Annen",
    "sg:orig_category":"Machineonderhoud En -Reparatie",
    "sg:phone":"+31 592 271 604",
    "sg:postcode":"9468 AP",
    "sg:province":"South Carolina",
    "wof:name":"Hidding, Klussenbedrijf",
    "wof:placetype":"venue"
},
  "geometry": {"coordinates":[-79.253815,33.471233],"type":"Point"}
}