{
  "type": "Feature",
  "properties": {
    "addr:full":"J Marisstr 34 Amsterdam Noord-Holland 1058 JA",
    "addr:housenumber":"34",
    "addr:postcode":"1058 ja",
    "iso:country":"NL",
    "sg:address":"J Marisstr 34",
    "sg:city":"Amsterdam",
    "sg:orig_category":"Psychologen",
    "sg:phone":"+31 20 614 0903",
    "sg:postcode":"1058 JA",
    "sg:province":"Noord-Holland",
    "wof:name":"Kruis, Drs J H",
    "wof:placetype":"venue"
},
  "geometry": {"coordinates":[4.851998,52.35442],"type":"Point"}
}