{
  "type": "Feature",
  "properties": {
    "iso:country":"NL",
    "sg:address":"Heuvel Galerie 13",
    "sg:city":"Eindhoven",
    "sg:classifiers":[
        {
            "category":"Farming",
            "subcategory":"Fish & Marine Products",
            "type":"Manufacturing & Wholesale Goods"
        }
    ],
    "sg:phone":"+31 40 246 6005",
    "sg:postcode":"5611 DK",
    "sg:province":"Noord-Brabant",
    "sg:tags":[
        "vi"
    ],
    "sg:website":"http://www.fishenfood.nl",
    "wof:name":"Fish 'N Food",
    "wof:placetype":"venue"
},
  "geometry": {"coordinates":[5.484105,51.434471],"type":"Point"}
}