{
  "type": "Feature",
  "properties": {
    "addr:full":"Gooyumerwg 23 Zurich Provincie Friesland 8751 TN",
    "addr:housenumber":"23",
    "addr:postcode":"8751",
    "addr:street":"Gooyumerwg;Provincie Friesland",
    "iso:country":"NL",
    "sg:address":"Gooyumerwg 23",
    "sg:city":"Zurich",
    "sg:orig_category":"Verpakkingsbedrijven",
    "sg:phone":"+31 517 579 272",
    "sg:postcode":"8751 TN",
    "sg:province":"Provincie Friesland",
    "wof:name":"Bisschop, J",
    "wof:placetype":"venue"
},
  "geometry": {"coordinates":[5.396547,53.106468],"type":"Point"}
}