{
  "type": "Feature",
  "properties": {
    "iso:country":"NL",
    "sg:address":"Gooyumerwg 23",
    "sg:city":"Zurich",
    "sg:orig_category":"Verpakkingsbedrijven",
    "sg:phone":"+31 517 579 272",
    "sg:postcode":"8751 TN",
    "sg:province":"Provincie Friesland",
    "wof:name":"Bisschop, J",
    "wof:placetype":"venue"
},
  "geometry": {"coordinates":[5.396547,53.106468],"type":"Point"}
}