{
  "type": "Feature",
  "properties": {
    "addr:full":"Mennonietenbuurt 116 A Amstelhoek Utrecht 1427 BC",
    "addr:housenumber":"116 a",
    "addr:postcode":"1427 bc",
    "addr:street":"Mennonietenbuurt",
    "iso:country":"NL",
    "sg:address":"Mennonietenbuurt 116 A",
    "sg:city":"Amstelhoek",
    "sg:orig_category":"Bloemen And Planten",
    "sg:phone":"+31 297 561 024",
    "sg:postcode":"1427 BC",
    "sg:province":"Utrecht",
    "wof:name":"Tuincentrum Rosina",
    "wof:placetype":"venue"
},
  "geometry": {"coordinates":[4.823826,52.229301],"type":"Point"}
}