{
  "type": "Feature",
  "properties": {
    "addr:full":"Hoessenbosln 50 Berghem Noord-Brabant 5351 PD",
    "addr:housenumber":"50",
    "addr:postcode":"5351 pd",
    "addr:street":"Hoessenbosln",
    "iso:country":"NL",
    "sg:address":"Hoessenbosln 50",
    "sg:city":"Berghem",
    "sg:orig_category":"Makelaars En Adviseurs Onroerende Goederen",
    "sg:phone":"+31 412 402 078",
    "sg:postcode":"5351 PD",
    "sg:province":"Noord-Brabant",
    "sg:website":"http://www.koningwitzier.nl",
    "wof:name":"Koning Witzier, De",
    "wof:placetype":"venue"
},
  "geometry": {"coordinates":[5.583911,51.76413],"type":"Point"}
}