{
  "type": "Feature",
  "properties": {
    "addr:full":"Op De Graaf 11 Maastricht Limburg 6223 GG",
    "addr:housenumber":"11",
    "addr:postcode":"6223 gg",
    "addr:street":"Op De Graaf",
    "iso:country":"NL",
    "sg:address":"Op De Graaf 11",
    "sg:city":"Maastricht",
    "sg:orig_category":"Fotostudio'S And Fotografen",
    "sg:phone":"+31 43 362 0721",
    "sg:postcode":"6223 GG",
    "sg:province":"Limburg",
    "wof:name":"Vakfotografie Eijkenboom",
    "wof:placetype":"venue"
},
  "geometry": {"coordinates":[5.708675,50.895729],"type":"Point"}
}