{
  "type": "Feature",
  "properties": {
    "addr:full":"Plaza 24D Moerdyk Noord-Brabant 4782 SK",
    "addr:housenumber":"24d",
    "addr:street":"Plaza;4782",
    "iso:country":"NL",
    "sg:address":"Plaza 24D",
    "sg:city":"Moerdyk",
    "sg:orig_category":"Facilitaire Dienstverlening",
    "sg:phone":"+31 168 353 300",
    "sg:postcode":"4782 SK",
    "sg:province":"Noord-Brabant",
    "sg:website":"http://www.atworksolutions.nl",
    "wof:name":"Facilities At Work Bv",
    "wof:placetype":"venue"
},
  "geometry": {"coordinates":[4.613376,51.676739],"type":"Point"}
}