{
  "type": "Feature",
  "properties": {
    "addr:full":"Asterstraat 12 Heerenveen Friesland 8441 EG",
    "addr:housenumber":"12",
    "addr:postcode":"8441 eg",
    "addr:street":"Asterstraat",
    "iso:country":"NL",
    "sg:address":"Asterstraat 12",
    "sg:city":"Heerenveen",
    "sg:orig_category":"Loodgieterswerk, Verwarming And Sanitaire Installaties",
    "sg:phone":"+31 513 624 157",
    "sg:postcode":"8441 EG",
    "sg:province":"Friesland",
    "wof:name":"Onderhoudsbedrijf Boek",
    "wof:placetype":"venue"
},
  "geometry": {"coordinates":[5.923062,52.963047],"type":"Point"}
}