{
  "type": "Feature",
  "properties": {
    "addr:full":"Zuideinde 89-93 Westzaan North Holland 1551 EC",
    "addr:housenumber":"89-93",
    "addr:postcode":"1551 ec",
    "addr:street":"Zuideinde",
    "iso:country":"NL",
    "sg:address":"Zuideinde 89-93",
    "sg:city":"Westzaan",
    "sg:orig_category":"Verpakkingsbedrijven",
    "sg:phone":"+31 75 631 0307",
    "sg:postcode":"1551 EC",
    "sg:province":"North Holland",
    "wof:name":"Marvos Bv",
    "wof:placetype":"venue"
},
  "geometry": {"coordinates":[4.779971,52.434559],"type":"Point"}
}