{
  "type": "Feature",
  "properties": {
    "addr:full":"Oirschotsedijk 14 Eindhoven Noord-Brabant 5651 GC",
    "addr:housenumber":"14",
    "addr:postcode":"5651 gc",
    "addr:street":"Oirschotsedijk",
    "iso:country":"NL",
    "sg:address":"Oirschotsedijk 14",
    "sg:city":"Eindhoven",
    "sg:orig_category":"Opvangtehuizen",
    "sg:phone":"+31 40 266 8484",
    "sg:postcode":"5651 GC",
    "sg:province":"Noord-Brabant",
    "wof:name":"Oc Eindhoven Locatie Beatrixoord",
    "wof:placetype":"venue"
},
  "geometry": {"coordinates":[5.4409461021,51.460018158],"type":"Point"}
}