{
  "type": "Feature",
  "properties": {
    "addr:full":"Pr Hendrikstr 386 Hoek Van Holland Zuid-Holland 3151 AW",
    "addr:housenumber":"386",
    "addr:postcode":"3151 aw",
    "iso:country":"NL",
    "sg:address":"Pr Hendrikstr 386",
    "sg:city":"Hoek Van Holland",
    "sg:orig_category":"Boeken En Tijdschriften",
    "sg:phone":"+31 174 382 916",
    "sg:postcode":"3151 AW",
    "sg:province":"Zuid-Holland",
    "wof:name":"Boekelier, De",
    "wof:placetype":"venue"
},
  "geometry": {"coordinates":[4.128707,51.97794],"type":"Point"}
}