{
  "type": "Feature",
  "properties": {
    "addr:full":"Kapittelwg 16 Breda North Brabant 4827 HG",
    "addr:housenumber":"16",
    "addr:postcode":"4827 hg",
    "addr:street":"Kapittelwg",
    "iso:country":"NL",
    "sg:address":"Kapittelwg 16",
    "sg:city":"Breda",
    "sg:orig_category":"Metaalbewerking",
    "sg:phone":"+31 76 571 7170",
    "sg:postcode":"4827 HG",
    "sg:province":"North Brabant",
    "sg:website":"http://www.adeto.nl",
    "wof:name":"Adema & Touw Bv",
    "wof:placetype":"venue"
},
  "geometry": {"coordinates":[4.802012,51.605854],"type":"Point"}
}