{
  "type": "Feature",
  "properties": {
    "addr:full":"Lenshoek 21 Nederhemert Gelderland 5317 KM",
    "addr:housenumber":"21",
    "addr:street":"Lenshoek;Gelderland 5317 Km",
    "iso:country":"NL",
    "sg:address":"Lenshoek 21",
    "sg:city":"Nederhemert",
    "sg:orig_category":"Geschenkartikelen",
    "sg:phone":"+31 418 552 432",
    "sg:postcode":"5317 KM",
    "sg:province":"Gelderland",
    "sg:website":"http://www.houtsnijwerk.nl",
    "wof:name":"Ceel Heijkop",
    "wof:placetype":"venue"
},
  "geometry": {"coordinates":[5.175844,51.766117],"type":"Point"}
}