{
  "type": "Feature",
  "properties": {
    "addr:full":"Wilhelminaln 19 Alphen Aan Den Ryn South Holland 2405 EB",
    "addr:housenumber":"19",
    "addr:postcode":"2405 eb",
    "addr:street":"Wilhelminaln;Aan Den Ryn",
    "iso:country":"NL",
    "sg:address":"Wilhelminaln 19",
    "sg:city":"Alphen Aan Den Ryn",
    "sg:orig_category":"Meubelen",
    "sg:phone":"+31 172 474 741",
    "sg:postcode":"2405 EB",
    "sg:province":"South Holland",
    "wof:name":"Martens",
    "wof:placetype":"venue"
},
  "geometry": {"coordinates":[4.661893,52.132309],"type":"Point"}
}