{
  "type": "Feature",
  "properties": {
    "addr:full":"Reguliersdwstr 64 Amsterdam Noord-Holland 1017 BM",
    "addr:housenumber":"64",
    "addr:postcode":"1017 bm",
    "addr:street":"Reguliersdwstr",
    "iso:country":"NL",
    "sg:address":"Reguliersdwstr 64",
    "sg:city":"Amsterdam",
    "sg:orig_category":"Herenkleding",
    "sg:phone":"+31 20 423 2088",
    "sg:postcode":"1017 BM",
    "sg:province":"Noord-Holland",
    "wof:name":"Shirtshop",
    "wof:placetype":"venue"
},
  "geometry": {"coordinates":[4.892742,52.36599],"type":"Point"}
}