{
  "type": "Feature",
  "properties": {
    "addr:full":"Burgemeester Bosmastraat 41 Winterswijk Gelderland 7101 DE",
    "addr:housenumber":"41;7101",
    "addr:street":"Burgemeester Bosmastraat;Gelderland;De",
    "iso:country":"NL",
    "sg:address":"Burgemeester Bosmastraat 41",
    "sg:city":"Winterswijk",
    "sg:orig_category":"Banken And Kredietinstellingen",
    "sg:phone":"+31 543 541 414",
    "sg:postcode":"7101 DE",
    "sg:province":"Gelderland",
    "wof:name":"Rabobank",
    "wof:placetype":"venue"
},
  "geometry": {"coordinates":[6.718856,51.972504],"type":"Point"}
}