{
  "type": "Feature",
  "properties": {
    "addr:full":"Damrak 10 Amsterdam North Holland 1012 LG",
    "addr:housenumber":"10",
    "addr:postcode":"1012 lg",
    "addr:street":"Damrak",
    "iso:country":"NL",
    "sg:address":"Damrak 10",
    "sg:city":"Amsterdam",
    "sg:classifiers":[
        {
            "category":"Shopping",
            "subcategory":"Gifts & Souvenirs",
            "type":"Retail Goods"
        }
    ],
    "sg:phone":"+31 20 624 2740",
    "sg:postcode":"1012 LG",
    "sg:province":"North Holland",
    "sg:tags":[
        "geschenken"
    ],
    "wof:name":"J. Van Beek Bv",
    "wof:placetype":"venue"
},
  "geometry": {"coordinates":[4.897581,52.376884],"type":"Point"}
}