{
  "type": "Feature",
  "properties": {
    "addr:full":"Brugstr 5 Almkerk North Brabant 4286 AW",
    "addr:housenumber":"5",
    "addr:postcode":"4286 aw",
    "addr:street":"Brugstr",
    "iso:country":"NL",
    "sg:address":"Brugstr 5",
    "sg:city":"Almkerk",
    "sg:orig_category":"Schilders",
    "sg:phone":"+31 183 402 053",
    "sg:postcode":"4286 AW",
    "sg:province":"North Brabant",
    "wof:name":"Verhoeven",
    "wof:placetype":"venue"
},
  "geometry": {"coordinates":[4.965395,51.770844],"type":"Point"}
}