{
  "type": "Feature",
  "properties": {
    "addr:full":"D Curtiusstr 7Unit307B Amsterdam North Holland 1051 JL",
    "addr:housenumber":"7unit307b",
    "addr:postcode":"1051 jl",
    "iso:country":"NL",
    "sg:address":"D Curtiusstr 7Unit307B",
    "sg:city":"Amsterdam",
    "sg:orig_category":"Fotostudio'S",
    "sg:phone":"+31 20 612 7581",
    "sg:postcode":"1051 JL",
    "sg:province":"North Holland",
    "sg:website":"http://www.rent-an-eye.nl",
    "wof:name":"Rent An Eye",
    "wof:placetype":"venue"
},
  "geometry": {"coordinates":[4.871745,52.379089],"type":"Point"}
}