{
  "type": "Feature",
  "properties": {
    "addr:full":"Leusderweg 249 Amersfoort Utrecht 3818 AE",
    "addr:housenumber":"249",
    "addr:postcode":"3818 ae",
    "addr:street":"Leusderweg",
    "iso:country":"NL",
    "sg:address":"Leusderweg 249",
    "sg:city":"Amersfoort",
    "sg:classifiers":[
        {
            "category":"Education",
            "subcategory":"Preschool",
            "type":"Public Place"
        }
    ],
    "sg:phone":"+31 33 463 4443",
    "sg:postcode":"3818 AE",
    "sg:province":"Utrecht",
    "sg:tags":[
        "kleuteronderwijs",
        "basis-"
    ],
    "wof:name":"Islamitische Basisschool Bilal",
    "wof:placetype":"venue"
},
  "geometry": {"coordinates":[5.376088,52.137264],"type":"Point"}
}