{
  "type": "Feature",
  "properties": {
    "addr:full":"Bontemorgen 16 Lienden Gelderland 4033 CV",
    "addr:housenumber":"16",
    "addr:postcode":"4033 cv",
    "addr:street":"Bontemorgen;Gelderland",
    "iso:country":"NL",
    "sg:address":"Bontemorgen 16",
    "sg:city":"Lienden",
    "sg:orig_category":"Glaszetten",
    "sg:phone":"+31 344 603 095",
    "sg:postcode":"4033 CV",
    "sg:province":"Gelderland",
    "wof:name":"Rose Design Vof",
    "wof:placetype":"venue"
},
  "geometry": {"coordinates":[5.518405,51.962509],"type":"Point"}
}