{
  "type": "Feature",
  "properties": {
    "addr:full":"Geestbrugkade 19 Rijswijk Zh South Holland 2281 CV",
    "addr:housenumber":"19",
    "addr:postcode":"2281 cv",
    "addr:street":"Geestbrugkade",
    "iso:country":"NL",
    "sg:address":"Geestbrugkade 19",
    "sg:city":"Rijswijk Zh",
    "sg:orig_category":"Autokeuringen",
    "sg:phone":"+31 70 390 9903",
    "sg:postcode":"2281 CV",
    "sg:province":"South Holland",
    "wof:name":"Veban Rijswijk",
    "wof:placetype":"venue"
},
  "geometry": {"coordinates":[4.344667,52.058678],"type":"Point"}
}