{
  "type": "Feature",
  "properties": {
    "addr:full":"Aubachstraat 46 Beverwijk North Holland 1946 XK",
    "addr:housenumber":"46",
    "addr:postcode":"1946 xk",
    "addr:street":"Aubachstraat",
    "iso:country":"NL",
    "sg:address":"Aubachstraat 46",
    "sg:city":"Beverwijk",
    "sg:orig_category":"Verzekeringen",
    "sg:phone":"+31 251 230 159",
    "sg:postcode":"1946 XK",
    "sg:province":"North Holland",
    "wof:name":"A. Klarenbeek-Mester",
    "wof:placetype":"venue"
},
  "geometry": {"coordinates":[4.673695,52.494568],"type":"Point"}
}