{
  "type": "Feature",
  "properties": {
    "addr:full":"Heuvelstraat 43 Tilburg Noord-Brabant 5038 AB",
    "addr:housenumber":"43",
    "addr:postcode":"5038 ab",
    "addr:street":"Heuvelstraat",
    "iso:country":"NL",
    "sg:address":"Heuvelstraat 43",
    "sg:city":"Tilburg",
    "sg:orig_category":"Bloemen And Planten",
    "sg:phone":"+31 13 542 5889",
    "sg:postcode":"5038 AB",
    "sg:province":"Noord-Brabant",
    "wof:name":"Rozemarijn Bloemisten",
    "wof:placetype":"venue"
},
  "geometry": {"coordinates":[5.087769,51.556747],"type":"Point"}
}