{
  "type": "Feature",
  "properties": {
    "iso:country":"NL",
    "sg:address":"Energieweg 8",
    "sg:city":"Soest",
    "sg:orig_category":"Autokeuringen",
    "sg:phone":"+31 35 601 3792",
    "sg:postcode":"3762 ET",
    "sg:province":"Utrecht",
    "wof:name":"Stam Autoschade Bv",
    "wof:placetype":"venue"
},
  "geometry": {"coordinates":[5.276997,52.179863],"type":"Point"}
}