{
  "type": "Feature",
  "properties": {
    "addr:full":"Energieweg 8 Soest Utrecht 3762 ET",
    "addr:housenumber":"8",
    "addr:postcode":"3762 et",
    "addr:street":"Energieweg",
    "iso:country":"NL",
    "sg:address":"Energieweg 8",
    "sg:city":"Soest",
    "sg:orig_category":"Autokeuringen",
    "sg:phone":"+31 35 601 3792",
    "sg:postcode":"3762 ET",
    "sg:province":"Utrecht",
    "wof:name":"Stam Autoschade Bv",
    "wof:placetype":"venue"
},
  "geometry": {"coordinates":[5.276997,52.179863],"type":"Point"}
}