{
  "type": "Feature",
  "properties": {
    "addr:full":"Rheezerveensewg 60 Rheezerveen Overijssel 7797 HD",
    "addr:housenumber":"60",
    "addr:postcode":"7797 hd",
    "addr:street":"Rheezerveensewg",
    "iso:country":"NL",
    "sg:address":"Rheezerveensewg 60",
    "sg:city":"Rheezerveen",
    "sg:orig_category":"Haarden En Kachels",
    "sg:phone":"+31 523 638 220",
    "sg:postcode":"7797 HD",
    "sg:province":"Overijssel",
    "wof:name":"Drayer, Klaas",
    "wof:placetype":"venue"
},
  "geometry": {"coordinates":[6.519506,52.564308],"type":"Point"}
}