{
  "type": "Feature",
  "properties": {
    "addr:full":"Rijksstraatweg 169 Elst Ut Utrecht 3921 AE",
    "addr:housenumber":"169",
    "addr:postcode":"ut;3921 ae",
    "addr:street":"Rijksstraatweg",
    "iso:country":"NL",
    "sg:address":"Rijksstraatweg 169",
    "sg:city":"Elst Ut",
    "sg:orig_category":"Verhuur Bouwmachines",
    "sg:phone":"+31 318 471 785",
    "sg:postcode":"3921 AE",
    "sg:province":"Utrecht",
    "wof:name":"H.A. Timmer",
    "wof:placetype":"venue"
},
  "geometry": {"coordinates":[5.508412,51.982327],"type":"Point"}
}