{
  "type": "Feature",
  "properties": {
    "addr:full":"Woertheweg 1 Hellendoorn Overijssel 7447 CX",
    "addr:housenumber":"1",
    "addr:postcode":"7447 cx",
    "addr:street":"Woertheweg",
    "iso:country":"NL",
    "sg:address":"Woertheweg 1",
    "sg:city":"Hellendoorn",
    "sg:orig_category":"Hypotheken And Hypotheekbanken",
    "sg:phone":"+31 548 654 371",
    "sg:postcode":"7447 CX",
    "sg:province":"Overijssel",
    "wof:name":"Wispels Verzekeringen Bv",
    "wof:placetype":"venue"
},
  "geometry": {"coordinates":[6.446702,52.39233],"type":"Point"}
}