{
  "type": "Feature",
  "properties": {
    "addr:full":"V Mandersloostr 19 Alphen Aan Den Ryn South Holland 2406 CB",
    "addr:housenumber":"19",
    "addr:postcode":"2406 cb",
    "addr:street":"Aan Den Ryn",
    "iso:country":"NL",
    "sg:address":"V Mandersloostr 19",
    "sg:city":"Alphen Aan Den Ryn",
    "sg:orig_category":"Boeken En Tijdschriften",
    "sg:phone":"+31 172 473 047",
    "sg:postcode":"2406 CB",
    "sg:province":"South Holland",
    "sg:website":"http://www.haasbeek-libris.nl",
    "wof:name":"Haasbeek",
    "wof:placetype":"venue"
},
  "geometry": {"coordinates":[4.663239,52.129295],"type":"Point"}
}