{
  "type": "Feature",
  "properties": {
    "addr:full":"Hondsdrafveld 2 Doetinchem Gelderland 7006 VE",
    "addr:housenumber":"2",
    "addr:postcode":"7006",
    "addr:street":"Hondsdrafveld;Gelderland;Ve",
    "iso:country":"NL",
    "sg:address":"Hondsdrafveld 2",
    "sg:city":"Doetinchem",
    "sg:orig_category":"Boekhouders",
    "sg:phone":"+31 314 345 761",
    "sg:postcode":"7006 VE",
    "sg:province":"Gelderland",
    "wof:name":"G. Van Den Berg Administratie & Advies",
    "wof:placetype":"venue"
},
  "geometry": {"coordinates":[6.247748,51.962688],"type":"Point"}
}