{
  "type": "Feature",
  "properties": {
    "iso:country":"NL",
    "sg:address":"Lotstukken 2",
    "sg:city":"Eelde",
    "sg:orig_category":"Adviesbureaus",
    "sg:phone":"+31 6 29416362",
    "sg:postcode":"9761 KA",
    "sg:province":"Drenthe",
    "wof:name":"Griff",
    "wof:placetype":"venue"
},
  "geometry": {"coordinates":[6.55578,53.13884],"type":"Point"}
}