{
  "type": "Feature",
  "properties": {
    "addr:full":"Sloep 96 Groningen Groningen 9732 CE",
    "addr:housenumber":"96",
    "addr:postcode":"9732 ce",
    "addr:street":"Sloep",
    "iso:country":"NL",
    "sg:address":"Sloep 96",
    "sg:city":"Groningen",
    "sg:orig_category":"Kantoormachines",
    "sg:phone":"+31 6 11477604",
    "sg:postcode":"9732 CE",
    "sg:province":"Groningen",
    "wof:name":"Ipsofacto",
    "wof:placetype":"venue"
},
  "geometry": {"coordinates":[6.6292119026,53.2372283936],"type":"Point"}
}