{
  "type": "Feature",
  "properties": {
    "addr:full":"Duivenhoek 1 Rilland Zeeland 4411 SH",
    "addr:housenumber":"1",
    "addr:postcode":"4411 sh",
    "addr:street":"Duivenhoek",
    "iso:country":"NL",
    "sg:address":"Duivenhoek 1",
    "sg:city":"Rilland",
    "sg:orig_category":"Goederenvervoer Over De Weg",
    "sg:phone":"+31 113 551 368",
    "sg:postcode":"4411 SH",
    "sg:province":"Zeeland",
    "wof:name":"Firma J.A. Krijger En Zoon",
    "wof:placetype":"venue"
},
  "geometry": {"coordinates":[4.143855,51.42136],"type":"Point"}
}