{
  "type": "Feature",
  "properties": {
    "addr:full":"Borgercompagnie 3 Sappemeer Groningen 9611 TA",
    "addr:housenumber":"3",
    "addr:postcode":"9611 ta",
    "addr:street":"Borgercompagnie",
    "iso:country":"NL",
    "sg:address":"Borgercompagnie 3",
    "sg:city":"Sappemeer",
    "sg:orig_category":"Paardensport",
    "sg:phone":"+31 598 392 398",
    "sg:postcode":"9611 TA",
    "sg:province":"Groningen",
    "wof:name":"Hoorn, Van",
    "wof:placetype":"venue"
},
  "geometry": {"coordinates":[6.797093,53.153618],"type":"Point"}
}