{
  "type": "Feature",
  "properties": {
    "addr:full":"Duinoordsewg 20 Helvoirt Noord-Brabant 5268 LM",
    "addr:housenumber":"20",
    "addr:postcode":"5268 lm",
    "addr:street":"Duinoordsewg",
    "iso:country":"NL",
    "sg:address":"Duinoordsewg 20",
    "sg:city":"Helvoirt",
    "sg:orig_category":"Adviesbureaus Bedrijfsorganisatie",
    "sg:phone":"+31 411 643 973",
    "sg:postcode":"5268 LM",
    "sg:province":"Noord-Brabant",
    "wof:name":"Wieringa, Sander",
    "wof:placetype":"venue"
},
  "geometry": {"coordinates":[5.211711,51.658291],"type":"Point"}
}