{
  "type": "Feature",
  "properties": {
    "iso:country":"NL",
    "sg:address":"Donckseln 14",
    "sg:city":"Ridderkerk",
    "sg:orig_category":"Onderhoudswerken",
    "sg:phone":"+31 180 418 685",
    "sg:postcode":"2983 LC",
    "sg:province":"Zuid-Holland",
    "wof:name":"Lotte, R",
    "wof:placetype":"venue"
},
  "geometry": {"coordinates":[4.598051,51.871727],"type":"Point"}
}