{
  "type": "Feature",
  "properties": {
    "addr:full":"Julianalaan 67 Zuidlaren Provincie Drenthe 9471 EB",
    "addr:housenumber":"67",
    "addr:postcode":"9471 eb",
    "addr:street":"Julianalaan;Provincie Drenthe",
    "iso:country":"NL",
    "sg:address":"Julianalaan 67",
    "sg:city":"Zuidlaren",
    "sg:classifiers":[
        {
            "category":"Education",
            "subcategory":"Preschool",
            "type":"Public Place"
        }
    ],
    "sg:phone":"+31 50 409 2009",
    "sg:postcode":"9471 EB",
    "sg:province":"Provincie Drenthe",
    "sg:tags":[
        "kleuteronderwijs",
        "basis-"
    ],
    "wof:name":"Openbare Basisschool De Schuthoek",
    "wof:placetype":"venue"
},
  "geometry": {"coordinates":[6.687236,53.094616],"type":"Point"}
}