{
  "type": "Feature",
  "properties": {
    "addr:full":"De Vliet 33 Velserbroek North Holland 1991 CE",
    "addr:housenumber":"33",
    "addr:postcode":"1991 ce",
    "addr:street":"De Vliet",
    "iso:country":"NL",
    "sg:address":"De Vliet 33",
    "sg:city":"Velserbroek",
    "sg:orig_category":"Public Relationbureaus",
    "sg:phone":"+31 23 538 6063",
    "sg:postcode":"1991 CE",
    "sg:province":"North Holland",
    "wof:name":"Lindhout Kommunikatie",
    "wof:placetype":"venue"
},
  "geometry": {"coordinates":[4.657763,52.437332],"type":"Point"}
}