{
  "type": "Feature",
  "properties": {
    "addr:full":"Nieuwstraat 25 Almelo NL.08 7605 AA",
    "addr:housenumber":"25;nl.08",
    "addr:postcode":"7605 aa",
    "addr:street":"Nieuwstraat",
    "iso:country":"NL",
    "sg:address":"Nieuwstraat 25",
    "sg:city":"Almelo",
    "sg:orig_category":"Kappers",
    "sg:phone":"+31 546 825 932",
    "sg:postcode":"7605 AA",
    "sg:province":"NL.08",
    "wof:name":"Salon Gulperihan Abla",
    "wof:placetype":"venue"
},
  "geometry": {"coordinates":[6.664543,52.354954],"type":"Point"}
}