{
  "type": "Feature",
  "properties": {
    "addr:full":"Postbus 6369 Eindhoven North Brabant 5600 HJ",
    "addr:housenumber":"6369",
    "addr:postcode":"5600 hj",
    "addr:street":"Postbus",
    "iso:country":"NL",
    "sg:address":"Postbus 6369",
    "sg:city":"Eindhoven",
    "sg:orig_category":"Bedrijfsmechanisatie En -Automatisering",
    "sg:phone":"+31 40 281 6806",
    "sg:postcode":"5600 HJ",
    "sg:province":"North Brabant",
    "wof:name":"Topcontrol Bv",
    "wof:placetype":"venue"
},
  "geometry": {"coordinates":[5.48411,51.434471],"type":"Point"}
}