{
  "type": "Feature",
  "properties": {
    "addr:full":"Oranje Nassaulaan 1 Amsterdam Noord-Holland 1075 AH",
    "addr:housenumber":"1",
    "addr:postcode":"1075 ah",
    "addr:street":"Oranje Nassaulaan",
    "iso:country":"NL",
    "sg:address":"Oranje Nassaulaan 1",
    "sg:city":"Amsterdam",
    "sg:classifiers":[
        {
            "category":"Professional",
            "subcategory":"Accounting & Tax Preparation",
            "type":"Services"
        }
    ],
    "sg:phone":"+31 20 571 2345",
    "sg:postcode":"1075 AH",
    "sg:province":"Noord-Holland",
    "sg:tags":[
        "accountant"
    ],
    "wof:name":"Dubois & Co Registeraccountants",
    "wof:placetype":"venue"
},
  "geometry": {"coordinates":[4.863903,52.354942],"type":"Point"}
}