{
  "type": "Feature",
  "properties": {
    "addr:full":"Tiengemeten 195 Amstelveen North Holland 1181 CT",
    "addr:housenumber":"195",
    "addr:postcode":"1181 ct",
    "addr:street":"Tiengemeten",
    "iso:country":"NL",
    "sg:address":"Tiengemeten 195",
    "sg:city":"Amstelveen",
    "sg:orig_category":"Onderhoudswerken",
    "sg:phone":"+31 20 645 1057",
    "sg:postcode":"1181 CT",
    "sg:province":"North Holland",
    "wof:name":"Rusch",
    "wof:placetype":"venue"
},
  "geometry": {"coordinates":[4.869009,52.316669],"type":"Point"}
}