{
  "type": "Feature",
  "properties": {
    "addr:full":"Heerbaan 81 Millingen A/D Rijn Gelderland 6566 EE",
    "addr:housenumber":"81;a / d",
    "addr:postcode":"6566 ee",
    "addr:street":"Heerbaan;Rijn Gelderland",
    "iso:country":"NL",
    "sg:address":"Heerbaan 81",
    "sg:city":"Millingen A/D Rijn",
    "sg:orig_category":"Schoenen",
    "sg:phone":"+31 481 433 230",
    "sg:postcode":"6566 EE",
    "sg:province":"Gelderland",
    "wof:name":"Jansen Schoenmode En Sport",
    "wof:placetype":"venue"
},
  "geometry": {"coordinates":[6.04854,51.861496],"type":"Point"}
}