{
  "type": "Feature",
  "properties": {
    "addr:full":"Gibraltar 17 Zaandam Noord-Holland 1503 BM",
    "addr:housenumber":"17",
    "addr:postcode":"1503 bm",
    "addr:street":"Gibraltar",
    "iso:country":"NL",
    "sg:address":"Gibraltar 17",
    "sg:city":"Zaandam",
    "sg:orig_category":"Bloemen And Planten",
    "sg:phone":"+31 75 614 9435",
    "sg:postcode":"1503 BM",
    "sg:province":"Noord-Holland",
    "wof:name":"Buteijn'S Bloemen- En Plantenservice",
    "wof:placetype":"venue"
},
  "geometry": {"coordinates":[4.84575,52.445702],"type":"Point"}
}