{
  "type": "Feature",
  "properties": {
    "addr:full":"Amsterdamsestraatweg 535 Utrecht Utrecht 3553 EE",
    "addr:housenumber":"535",
    "addr:postcode":"3553 ee",
    "addr:street":"Amsterdamsestraatweg",
    "iso:country":"NL",
    "sg:address":"Amsterdamsestraatweg 535",
    "sg:city":"Utrecht",
    "sg:orig_category":"Elektronische Bedrijfsinstallaties",
    "sg:phone":"+31 30 244 7792",
    "sg:postcode":"3553 EE",
    "sg:province":"Utrecht",
    "wof:name":"Ece Beveiligingen",
    "wof:placetype":"venue"
},
  "geometry": {"coordinates":[5.087203,52.108269],"type":"Point"}
}