{
  "type": "Feature",
  "properties": {
    "iso:country":"NL",
    "sg:address":"Kozakkenwg 1",
    "sg:city":"Putten",
    "sg:orig_category":"Verlichtingsartikelen - Groothandel",
    "sg:phone":"+31 341 360 183",
    "sg:postcode":"3881 MG",
    "sg:province":"Gelderland",
    "wof:name":"Lichtster Vof, De",
    "wof:placetype":"venue"
},
  "geometry": {"coordinates":[5.618973,52.27039],"type":"Point"}
}