{
  "type": "Feature",
  "properties": {
    "addr:full":"A Mauvestr 7 Amersfoort Utrecht 3817 DL",
    "addr:housenumber":"7",
    "addr:postcode":"3817 dl",
    "iso:country":"NL",
    "sg:address":"A Mauvestr 7",
    "sg:city":"Amersfoort",
    "sg:orig_category":"Autorijscholen",
    "sg:phone":"+31 33 463 4629",
    "sg:postcode":"3817 DL",
    "sg:province":"Utrecht",
    "wof:name":"Rij-Stijl",
    "wof:placetype":"venue"
},
  "geometry": {"coordinates":[5.392434,52.148384],"type":"Point"}
}