{
  "type": "Feature",
  "properties": {
    "addr:full":"Suttnerstr 23 Stein Lb Limburg 6171 NM",
    "addr:housenumber":"23",
    "addr:postcode":"lb;6171",
    "addr:street":"Suttnerstr",
    "iso:country":"NL",
    "sg:address":"Suttnerstr 23",
    "sg:city":"Stein Lb",
    "sg:orig_category":"Kantoor- En Secretariaatsservice",
    "sg:phone":"+31 46 426 0256",
    "sg:postcode":"6171 NM",
    "sg:province":"Limburg",
    "wof:name":"Mm",
    "wof:placetype":"venue"
},
  "geometry": {"coordinates":[-93.1299362183,36.7056617737],"type":"Point"}
}