{
  "type": "Feature",
  "properties": {
    "addr:full":"Noorderdiep 45 Nieuw Buinen Drenthe 9521 BA",
    "addr:housenumber":"45",
    "addr:postcode":"buinen;9521 ba",
    "addr:street":"Noorderdiep",
    "iso:country":"NL",
    "sg:address":"Noorderdiep 45",
    "sg:city":"Nieuw Buinen",
    "sg:orig_category":"Fotojournalisten Freelance",
    "sg:phone":"+31 6 54687855",
    "sg:postcode":"9521 BA",
    "sg:province":"Drenthe",
    "wof:name":"Koremans, Rob",
    "wof:placetype":"venue"
},
  "geometry": {"coordinates":[6.909942,52.948669],"type":"Point"}
}