{
  "type": "Feature",
  "properties": {
    "addr:full":"Marnixstr 102-104 Amsterdam North Holland 1015 VZ",
    "addr:housenumber":"102-104",
    "addr:postcode":"1015 vz",
    "iso:country":"NL",
    "sg:address":"Marnixstr 102-104",
    "sg:city":"Amsterdam",
    "sg:orig_category":"Glas",
    "sg:phone":"+31 20 625 0517",
    "sg:postcode":"1015 VZ",
    "sg:province":"North Holland",
    "wof:name":"Actief, Glashandel",
    "wof:placetype":"venue"
},
  "geometry": {"coordinates":[4.879055,52.378704],"type":"Point"}
}