{
  "type": "Feature",
  "properties": {
    "addr:full":"Hoofdweg 271 Hoofddorp Noord-Holland 2131 LK",
    "addr:housenumber":"271",
    "addr:postcode":"2131 lk",
    "addr:street":"Hoofdweg",
    "iso:country":"NL",
    "sg:address":"Hoofdweg 271",
    "sg:city":"Hoofddorp",
    "sg:orig_category":"Bloemen And Planten",
    "sg:phone":"+31 23 555 1604",
    "sg:postcode":"2131 LK",
    "sg:province":"Noord-Holland",
    "wof:name":"Het Viooltje",
    "wof:placetype":"venue"
},
  "geometry": {"coordinates":[4.735452,52.335861],"type":"Point"}
}