{
  "type": "Feature",
  "properties": {
    "addr:full":"Wilhelminastr 19 Roden Drenthe 9301 AJ",
    "addr:housenumber":"19",
    "addr:postcode":"9301 aj",
    "addr:street":"Wilhelminastr",
    "iso:country":"NL",
    "sg:address":"Wilhelminastr 19",
    "sg:city":"Roden",
    "sg:orig_category":"Wasmachines En Wasdrogers - Onderhoud En Reparatie",
    "sg:phone":"+31 50 501 9400",
    "sg:postcode":"9301 AJ",
    "sg:province":"Drenthe",
    "wof:name":"Mulder, Bert",
    "wof:placetype":"venue"
},
  "geometry": {"coordinates":[6.4309821129,53.1385726929],"type":"Point"}
}