{
  "type": "Feature",
  "properties": {
    "addr:full":"Ambergeel 30 Zoetermeer Zuid-Holland 2718 BN",
    "addr:housenumber":"30",
    "addr:postcode":"2718 bn",
    "addr:street":"Ambergeel",
    "iso:country":"NL",
    "sg:address":"Ambergeel 30",
    "sg:city":"Zoetermeer",
    "sg:orig_category":"Bestratingen",
    "sg:phone":"+31 79 361 0049",
    "sg:postcode":"2718 BN",
    "sg:province":"Zuid-Holland",
    "wof:name":"Spaan",
    "wof:placetype":"venue"
},
  "geometry": {"coordinates":[4.492386,52.043144],"type":"Point"}
}