{
  "type": "Feature",
  "properties": {
    "iso:country":"NL",
    "sg:address":"Makassarstr 151",
    "sg:city":"Amsterdam",
    "sg:orig_category":"Artsen - Huisartsen",
    "sg:phone":"+31 20 665 2681",
    "sg:postcode":"1095 SV",
    "sg:province":"Noord-Holland",
    "wof:name":"Indische Buurt Gezondheidscentr",
    "wof:placetype":"venue"
},
  "geometry": {"coordinates":[4.943567,52.363949],"type":"Point"}
}