{
  "type": "Feature",
  "properties": {
    "addr:full":"Doetinchemseweg 25 Terborg Gelderland 7061 CP",
    "addr:housenumber":"25",
    "addr:postcode":"7061 cp",
    "addr:street":"Doetinchemseweg;Gelderland",
    "iso:country":"NL",
    "sg:address":"Doetinchemseweg 25",
    "sg:city":"Terborg",
    "sg:orig_category":"Werving And Selectie Van Tijdelijk Personeel And Uitzendkantoren",
    "sg:phone":"+31 315 341 450",
    "sg:postcode":"7061 CP",
    "sg:province":"Gelderland",
    "wof:name":"Randstad Uitzendbureau Bv",
    "wof:placetype":"venue"
},
  "geometry": {"coordinates":[6.361093998,51.9215698242],"type":"Point"}
}