{
  "type": "Feature",
  "properties": {
    "addr:full":"Eendenbrink 30 S Gravenhage 2492 PE",
    "addr:housenumber":"30",
    "addr:postcode":"2492 pe",
    "addr:street":"Eendenbrink;S Gravenhage",
    "iso:country":"NL",
    "sg:address":"Eendenbrink 30",
    "sg:city":"S Gravenhage",
    "sg:orig_category":"Binnenhuisarchitectuur",
    "sg:phone":"+31 70 360 2598",
    "sg:postcode":"2492 PE",
    "wof:name":"Straatsburg, Studio",
    "wof:placetype":"venue"
},
  "geometry": {"coordinates":[4.40783,52.067459],"type":"Point"}
}