{
  "type": "Feature",
  "properties": {
    "addr:full":"Onder De Mast 7 Zundert North Brabant 4881 AN",
    "addr:housenumber":"7",
    "addr:postcode":"4881 an",
    "addr:street":"Onder De Mast",
    "iso:country":"NL",
    "sg:address":"Onder De Mast 7",
    "sg:city":"Zundert",
    "sg:orig_category":"Verpleegartikelen",
    "sg:phone":"+31 76 597 1210",
    "sg:postcode":"4881 AN",
    "sg:province":"North Brabant",
    "wof:name":"Opticare Bv",
    "wof:placetype":"venue"
},
  "geometry": {"coordinates":[4.660205,51.473412],"type":"Point"}
}