{
  "type": "Feature",
  "properties": {
    "addr:full":"Vierhoeksingel 150 Oss Virginia 5341 PV",
    "addr:housenumber":"150",
    "addr:postcode":"5341 pv",
    "addr:street":"Vierhoeksingel",
    "iso:country":"NL",
    "sg:address":"Vierhoeksingel 150",
    "sg:city":"Oss",
    "sg:orig_category":"Bloemen And Planten Gh",
    "sg:phone":"+31 412 692 333",
    "sg:postcode":"5341 PV",
    "sg:province":"Virginia",
    "wof:name":"Kolff Plants Bv",
    "wof:placetype":"venue"
},
  "geometry": {"coordinates":[-77.235214,38.312599],"type":"Point"}
}