{
  "type": "Feature",
  "properties": {
    "addr:full":"Stationsstr 30B Ermelo Gelderland 3851 NH",
    "addr:housenumber":"30b",
    "addr:postcode":"3851 nh",
    "addr:street":"Stationsstr;Gelderland",
    "iso:country":"NL",
    "sg:address":"Stationsstr 30B",
    "sg:city":"Ermelo",
    "sg:orig_category":"Kappers",
    "sg:phone":"+31 341 558 386",
    "sg:postcode":"3851 NH",
    "sg:province":"Gelderland",
    "wof:name":"Kinder Knipshop, De",
    "wof:placetype":"venue"
},
  "geometry": {"coordinates":[5.6274318695,52.3007736206],"type":"Point"}
}