{
  "type": "Feature",
  "properties": {
    "addr:full":"Beukelsdk 16 Rotterdam Zuid-Holland 3021 AG",
    "addr:housenumber":"16",
    "addr:postcode":"3021",
    "addr:street":"Beukelsdk",
    "iso:country":"NL",
    "sg:address":"Beukelsdk 16",
    "sg:city":"Rotterdam",
    "sg:classifiers":[
        {
            "category":"Travel",
            "subcategory":"Hotels & Motels",
            "type":"Entertainment"
        }
    ],
    "sg:phone":"+31 10 477 0877",
    "sg:postcode":"3021 AG",
    "sg:province":"Zuid-Holland",
    "wof:name":"West",
    "wof:placetype":"venue"
},
  "geometry": {"coordinates":[4.459026,51.921604],"type":"Point"}
}