{
  "type": "Feature",
  "properties": {
    "iso:country":"NL",
    "sg:address":"De Kwinkelier 52",
    "sg:city":"Bilthoven",
    "sg:orig_category":"Meubelzaken, Woning- And Keukeninrichting",
    "sg:phone":"+31 30 229 1033",
    "sg:postcode":"3722 AS",
    "sg:province":"Utrecht",
    "wof:name":"Vof Schutte Interieur",
    "wof:placetype":"venue"
},
  "geometry": {"coordinates":[5.20972,52.12883],"type":"Point"}
}