{
  "type": "Feature",
  "properties": {
    "addr:full":"De Kwinkelier 52 Bilthoven Utrecht 3722 AS",
    "addr:housenumber":"52",
    "addr:postcode":"3722 as",
    "addr:street":"De Kwinkelier",
    "iso:country":"NL",
    "sg:address":"De Kwinkelier 52",
    "sg:city":"Bilthoven",
    "sg:orig_category":"Meubelzaken, Woning- And Keukeninrichting",
    "sg:phone":"+31 30 229 1033",
    "sg:postcode":"3722 AS",
    "sg:province":"Utrecht",
    "wof:name":"Vof Schutte Interieur",
    "wof:placetype":"venue"
},
  "geometry": {"coordinates":[5.20972,52.12883],"type":"Point"}
}