{
  "type": "Feature",
  "properties": {
    "iso:country":"NL",
    "sg:address":"Edixhovenstr 10",
    "sg:city":"Eygelshoven",
    "sg:orig_category":"Kaas",
    "sg:phone":"+31 45 535 1750",
    "sg:postcode":"6471 KJ",
    "sg:province":"Limburg",
    "wof:name":"Kaasspecialist, De",
    "wof:placetype":"venue"
},
  "geometry": {"coordinates":[6.0514087677,50.893901825],"type":"Point"}
}