{
  "type": "Feature",
  "properties": {
    "addr:full":"Bosschewg 239 Tilburg Noord-Brabant 5015 AD",
    "addr:housenumber":"239",
    "addr:postcode":"5015 ad",
    "addr:street":"Tilburg",
    "iso:country":"NL",
    "sg:address":"Bosschewg 239",
    "sg:city":"Tilburg",
    "sg:orig_category":"Woningtextiel",
    "sg:phone":"+31 13 467 8051",
    "sg:postcode":"5015 AD",
    "sg:province":"Noord-Brabant",
    "sg:website":"http://www.pouwdesign.com",
    "wof:name":"Pouw Design",
    "wof:placetype":"venue"
},
  "geometry": {"coordinates":[5.1091170311,51.5637512207],"type":"Point"}
}