{
  "type": "Feature",
  "properties": {
    "addr:full":"Kerkwg 19-23 Zeist Utrecht 3701 HD",
    "addr:housenumber":"19-23",
    "addr:postcode":"3701 hd",
    "iso:country":"NL",
    "sg:address":"Kerkwg 19-23",
    "sg:city":"Zeist",
    "sg:orig_category":"Verenigingen En Stichtingen",
    "sg:phone":"+31 30 692 4482",
    "sg:postcode":"3701 HD",
    "sg:province":"Utrecht",
    "wof:name":"Npb Zeist Eo, Vrijzinnige Geloofsgemsch",
    "wof:placetype":"venue"
},
  "geometry": {"coordinates":[5.24387,52.08548],"type":"Point"}
}