{
  "type": "Feature",
  "properties": {
    "addr:full":"Spaarnwouderstraat 27 Haarlem Noord-Holland 2011 AA",
    "addr:housenumber":"27",
    "addr:postcode":"2011 aa",
    "addr:street":"Spaarnwouderstraat",
    "iso:country":"NL",
    "sg:address":"Spaarnwouderstraat 27",
    "sg:city":"Haarlem",
    "sg:orig_category":"Paramedische Behandelingen",
    "sg:phone":"+31 23 535 5007",
    "sg:postcode":"2011 AA",
    "sg:province":"Noord-Holland",
    "wof:name":"Verloskundigenpraktijk Spaarnwoude",
    "wof:placetype":"venue"
},
  "geometry": {"coordinates":[4.642744,52.379856],"type":"Point"}
}