{
  "type": "Feature",
  "properties": {
    "addr:full":"Gemini 1 Amersfoort Utrecht 3824 MH",
    "addr:housenumber":"1",
    "addr:postcode":"3824 mh",
    "addr:street":"Gemini",
    "iso:country":"NL",
    "sg:address":"Gemini 1",
    "sg:city":"Amersfoort",
    "sg:classifiers":[
        {
            "category":"Professional",
            "type":"Services"
        }
    ],
    "sg:phone":"+31 33 453 6666",
    "sg:postcode":"3824 MH",
    "sg:province":"Utrecht",
    "sg:tags":[
        "leasing"
    ],
    "wof:name":"C A N",
    "wof:placetype":"venue"
},
  "geometry": {"coordinates":[5.395985,52.197159],"type":"Point"}
}