{
  "type": "Feature",
  "properties": {
    "addr:full":"Zuiderzeestraatweg 137 Oldebroek Gelderland 8096 BE",
    "addr:housenumber":"137",
    "addr:postcode":"8096",
    "addr:street":"Zuiderzeestraatweg;Gelderland",
    "iso:country":"NL",
    "sg:address":"Zuiderzeestraatweg 137",
    "sg:city":"Oldebroek",
    "sg:orig_category":"Banken And Kredietinstellingen",
    "sg:phone":"+31 525 638 600",
    "sg:postcode":"8096 BE",
    "sg:province":"Gelderland",
    "wof:name":"Rabobank",
    "wof:placetype":"venue"
},
  "geometry": {"coordinates":[5.901141,52.448765],"type":"Point"}
}