{
  "type": "Feature",
  "properties": {
    "addr:full":"B V Beekln 16 Kortenhoef Noord-Holland 1241 AH",
    "addr:housenumber":"16",
    "addr:postcode":"1241 ah",
    "addr:street":"V Beekln",
    "iso:country":"NL",
    "sg:address":"B V Beekln 16",
    "sg:city":"Kortenhoef",
    "sg:orig_category":"Verbouwingen",
    "sg:phone":"+31 35 656 3582",
    "sg:postcode":"1241 AH",
    "sg:province":"Noord-Holland",
    "wof:name":"Heelwerk",
    "wof:placetype":"venue"
},
  "geometry": {"coordinates":[5.115375,52.239986],"type":"Point"}
}