{
  "type": "Feature",
  "properties": {
    "addr:full":"Houtmarkt 65 Zutphen Gelderland 7201 KL",
    "addr:housenumber":"65",
    "addr:postcode":"7201 kl",
    "addr:street":"Houtmarkt;Gelderland",
    "iso:country":"NL",
    "sg:address":"Houtmarkt 65",
    "sg:city":"Zutphen",
    "sg:orig_category":"Opticiens",
    "sg:phone":"+31 575 519 040",
    "sg:postcode":"7201 KL",
    "sg:province":"Gelderland",
    "wof:name":"Loman & Van De Weerd Opticiens Vof",
    "wof:placetype":"venue"
},
  "geometry": {"coordinates":[6.1915249825,52.1402015686],"type":"Point"}
}