{
  "type": "Feature",
  "properties": {
    "addr:full":"Provincialeweg 16 Schalkwijk Utrecht 3998 JE",
    "addr:housenumber":"16",
    "addr:postcode":"3998 je",
    "addr:street":"Provincialeweg",
    "iso:country":"NL",
    "sg:address":"Provincialeweg 16",
    "sg:city":"Schalkwijk",
    "sg:orig_category":"Kappers",
    "sg:phone":"+31 30 601 1998",
    "sg:postcode":"3998 JE",
    "sg:province":"Utrecht",
    "wof:name":"Claudia'S Haarboetiek",
    "wof:placetype":"venue"
},
  "geometry": {"coordinates":[5.1951179504,51.9909210205],"type":"Point"}
}