{
  "type": "Feature",
  "properties": {
    "addr:full":"Havenstraat 5 Emmeloord NL. 8304 AG",
    "addr:housenumber":"5",
    "addr:postcode":"8304",
    "addr:street":"Havenstraat;Nl.",
    "iso:country":"NL",
    "sg:address":"Havenstraat 5",
    "sg:city":"Emmeloord",
    "sg:orig_category":"Meubelzaken, Woning- And Keukeninrichting",
    "sg:phone":"+31 527 612 144",
    "sg:postcode":"8304 AG",
    "sg:province":"NL.",
    "wof:name":"Fa J. Hardeman",
    "wof:placetype":"venue"
},
  "geometry": {"coordinates":[5.747845,52.701981],"type":"Point"}
}