{
  "type": "Feature",
  "properties": {
    "addr:full":"Binnenhof 4 Franeker Friesland 8802 ME",
    "addr:housenumber":"4",
    "addr:postcode":"8802 me",
    "addr:street":"Binnenhof",
    "iso:country":"NL",
    "sg:address":"Binnenhof 4",
    "sg:city":"Franeker",
    "sg:orig_category":"Beeldende Kunstenaars",
    "sg:phone":"+31 517 397 859",
    "sg:postcode":"8802 ME",
    "sg:province":"Friesland",
    "wof:name":"Launspach, Cees",
    "wof:placetype":"venue"
},
  "geometry": {"coordinates":[5.533632,53.196304],"type":"Point"}
}