{
  "type": "Feature",
  "properties": {
    "addr:full":"Kampstraat 10 Beilen Drenthe 9411 KS",
    "addr:housenumber":"10",
    "addr:postcode":"9411 ks",
    "addr:street":"Kampstraat",
    "iso:country":"NL",
    "sg:address":"Kampstraat 10",
    "sg:city":"Beilen",
    "sg:orig_category":"Kappers",
    "sg:phone":"+31 593 541 070",
    "sg:postcode":"9411 KS",
    "sg:province":"Drenthe",
    "wof:name":"Dameskapsalon Draaijer Sattler",
    "wof:placetype":"venue"
},
  "geometry": {"coordinates":[6.5125989914,52.8598175049],"type":"Point"}
}