{
  "type": "Feature",
  "properties": {
    "addr:full":"Bachstr 52 Oirsbeek Limburg 6438 KM",
    "addr:housenumber":"52",
    "addr:postcode":"6438 km",
    "addr:street":"Bachstr",
    "iso:country":"NL",
    "sg:address":"Bachstr 52",
    "sg:city":"Oirsbeek",
    "sg:orig_category":"Administratie- En Boekhoudkantoren",
    "sg:phone":"+31 46 442 2730",
    "sg:postcode":"6438 KM",
    "sg:province":"Limburg",
    "wof:name":"Dackus, B",
    "wof:placetype":"venue"
},
  "geometry": {"coordinates":[5.91453,50.947109],"type":"Point"}
}