{
  "type": "Feature",
  "properties": {
    "addr:full":"Achterdoelen 68 Ede Gld Gelderland 6711 AV",
    "addr:housenumber":"68;6711",
    "addr:postcode":"av",
    "addr:street":"Achterdoelen;Gld Gelderland",
    "iso:country":"NL",
    "sg:address":"Achterdoelen 68",
    "sg:city":"Ede Gld",
    "sg:orig_category":"Herenkleding",
    "sg:phone":"+31 318 694 921",
    "sg:postcode":"6711 AV",
    "sg:province":"Gelderland",
    "wof:name":"Setpoint",
    "wof:placetype":"venue"
},
  "geometry": {"coordinates":[5.671643,52.04512],"type":"Point"}
}