{
  "type": "Feature",
  "properties": {
    "addr:full":"Poolsestr 55 Sprang Capelle Noord-Brabant 5161 AL",
    "addr:housenumber":"55",
    "addr:postcode":"5161 al",
    "addr:street":"Poolsestr",
    "iso:country":"NL",
    "sg:address":"Poolsestr 55",
    "sg:city":"Sprang Capelle",
    "sg:orig_category":"Verenigingen En Stichtingen",
    "sg:phone":"+31 416 315 150",
    "sg:postcode":"5161 AL",
    "sg:province":"Noord-Brabant",
    "wof:name":"Graves Pati\u00ebnten, Ned Ver Voor",
    "wof:placetype":"venue"
},
  "geometry": {"coordinates":[4.978208,51.675854],"type":"Point"}
}