{
  "type": "Feature",
  "properties": {
    "addr:full":"Watermanweg 9 Rotterdam Zuid-Holland 3067 GA",
    "addr:housenumber":"9",
    "addr:postcode":"3067 ga",
    "addr:street":"Watermanweg",
    "iso:country":"NL",
    "sg:address":"Watermanweg 9",
    "sg:city":"Rotterdam",
    "sg:orig_category":"Meubelzaken, Woning- And Keukeninrichting",
    "sg:phone":"+31 10 220 4709",
    "sg:postcode":"3067 GA",
    "sg:province":"Zuid-Holland",
    "wof:name":"Van De Heuvel Verlichting Kleinmeubel Bv",
    "wof:placetype":"venue"
},
  "geometry": {"coordinates":[4.560108,51.95145],"type":"Point"}
}