{
  "type": "Feature",
  "properties": {
    "iso:country":"NL",
    "sg:address":"De Schelp 32",
    "sg:city":"Leek",
    "sg:orig_category":"Accountants - Administratie- Consulenten En -Kantoren",
    "sg:phone":"+31 594 519 888",
    "sg:postcode":"9351 NV",
    "sg:province":"Groningen",
    "wof:name":"Vries En Everts, De",
    "wof:placetype":"venue"
},
  "geometry": {"coordinates":[6.368231,53.155346],"type":"Point"}
}