{
  "type": "Feature",
  "properties": {
    "addr:full":"Rozenstraat 16 Bergen Op Zoom Noord-Brabant 4613 AJ",
    "addr:housenumber":"16",
    "addr:postcode":"4613 aj",
    "addr:street":"Rozenstraat",
    "iso:country":"NL",
    "sg:address":"Rozenstraat 16",
    "sg:city":"Bergen Op Zoom",
    "sg:orig_category":"Autokeuringen",
    "sg:phone":"+31 164 256 314",
    "sg:postcode":"4613 AJ",
    "sg:province":"Noord-Brabant",
    "wof:name":"Th.M. Wijsman",
    "wof:placetype":"venue"
},
  "geometry": {"coordinates":[4.282972,51.502258],"type":"Point"}
}