{
  "type": "Feature",
  "properties": {
    "addr:full":"Gabriel Metsustraat 49 Utrecht Utrecht 3583 ES",
    "addr:housenumber":"49",
    "addr:postcode":"3583 es",
    "addr:street":"Gabriel Metsustraat",
    "iso:country":"NL",
    "sg:address":"Gabriel Metsustraat 49",
    "sg:city":"Utrecht",
    "sg:orig_category":"Muziekinstrumenten",
    "sg:phone":"+31 30 251 8618",
    "sg:postcode":"3583 ES",
    "sg:province":"Utrecht",
    "wof:name":"Timo Schijf Piano'S, Vleugels",
    "wof:placetype":"venue"
},
  "geometry": {"coordinates":[5.147203,52.086155],"type":"Point"}
}