{
  "type": "Feature",
  "properties": {
    "iso:country":"NL",
    "sg:address":"Joubertstr 67",
    "sg:city":"Rotterdam",
    "sg:orig_category":"Vertaalbureaus",
    "sg:phone":"+31 10 485 0233",
    "sg:postcode":"3072 XV",
    "sg:province":"South Holland",
    "wof:name":"Kader",
    "wof:placetype":"venue"
},
  "geometry": {"coordinates":[4.499808,51.901253],"type":"Point"}
}