{
  "type": "Feature",
  "properties": {
    "addr:full":"De Heyderweg 19 Leiden South Holland 2314 XZ",
    "addr:housenumber":"19",
    "addr:postcode":"2314 xz",
    "addr:street":"De Heyderweg",
    "iso:country":"NL",
    "sg:address":"De Heyderweg 19",
    "sg:city":"Leiden",
    "sg:orig_category":"Verlichting And Huishoudartikelen",
    "sg:phone":"+31 71 589 8321",
    "sg:postcode":"2314 XZ",
    "sg:province":"South Holland",
    "wof:name":"Project Stoffering Leiden Bv",
    "wof:placetype":"venue"
},
  "geometry": {"coordinates":[4.509578,52.143185],"type":"Point"}
}