{
  "type": "Feature",
  "properties": {
    "addr:full":"Groot Hertoginnelaan 169 'S Gravenhage Zuid-Holland 2517 ER",
    "addr:housenumber":"169 '",
    "addr:postcode":"2517 er",
    "addr:street":"Groot Hertoginnelaan",
    "iso:country":"NL",
    "sg:address":"Groot Hertoginnelaan 169",
    "sg:city":"'S Gravenhage",
    "sg:orig_category":"Fitnesscentra",
    "sg:phone":"+31 70 345 8090",
    "sg:postcode":"2517 ER",
    "sg:province":"Zuid-Holland",
    "wof:name":"De Sportacademie E Van Nieuwenhuizen",
    "wof:placetype":"venue"
},
  "geometry": {"coordinates":[4.275976,52.081539],"type":"Point"}
}