{
  "type": "Feature",
  "properties": {
    "addr:full":"Veldweg 6 Herkenbosch Limburg 6075 NL",
    "addr:housenumber":"6",
    "addr:postcode":"6075 nl",
    "addr:street":"Veldweg",
    "iso:country":"NL",
    "sg:address":"Veldweg 6",
    "sg:city":"Herkenbosch",
    "sg:classifiers":[
        {
            "category":"Shopping",
            "subcategory":"Bicycles & Sporting Goods",
            "type":"Retail Goods"
        }
    ],
    "sg:phone":"+31 475 535 757",
    "sg:postcode":"6075 NL",
    "sg:province":"Limburg",
    "sg:tags":[
        "sport-",
        "kampeerartikelen"
    ],
    "wof:name":"Whitlock Marine Steering",
    "wof:placetype":"venue"
},
  "geometry": {"coordinates":[6.066955,51.166332],"type":"Point"}
}