{
  "type": "Feature",
  "properties": {
    "iso:country":"NL",
    "sg:address":"Haskeruitgang 1",
    "sg:city":"Heerenveen",
    "sg:classifiers":[
        {
            "category":"Professional",
            "subcategory":"Accounting & Tax Preparation",
            "type":"Services"
        }
    ],
    "sg:phone":"+31 513 621 740",
    "sg:postcode":"8447 CK",
    "sg:province":"Friesland",
    "sg:tags":[
        "accountant",
        "en",
        "-kantoren",
        "register-"
    ],
    "sg:website":"http://www.ey.nl",
    "wof:name":"Ernst & Young",
    "wof:placetype":"venue"
},
  "geometry": {"coordinates":[5.90797,52.964352],"type":"Point"}
}