{
  "type": "Feature",
  "properties": {
    "addr:full":"Lg Brink 23 Apeldoorn Gelderland 7317 BD",
    "addr:housenumber":"23",
    "addr:postcode":"7317 bd",
    "addr:street":"Lg Brink;Gelderland",
    "iso:country":"NL",
    "sg:address":"Lg Brink 23",
    "sg:city":"Apeldoorn",
    "sg:orig_category":"Verf En Lak - Fabrieken En Groothandel",
    "sg:phone":"+31 55 526 8222",
    "sg:postcode":"7317 BD",
    "sg:province":"Gelderland",
    "wof:name":"Winters Bv",
    "wof:placetype":"venue"
},
  "geometry": {"coordinates":[5.973488,52.243668],"type":"Point"}
}