{
  "type": "Feature",
  "properties": {
    "iso:country":"NL",
    "sg:address":"Vondelstraat 27/3",
    "sg:city":"Amsterdam",
    "sg:orig_category":"Film-, Tv- And Videoproductie",
    "sg:phone":"+31 20 689 5672",
    "sg:postcode":"1054 GJ",
    "sg:province":"North Holland",
    "wof:name":"Eqj Music & Media",
    "wof:placetype":"venue"
},
  "geometry": {"coordinates":[4.877116,52.36208],"type":"Point"}
}