{
  "type": "Feature",
  "properties": {
    "addr:full":"Gageldijk 65 Maarssen Utrecht 3602 AH",
    "addr:housenumber":"65",
    "addr:postcode":"3602 ah",
    "addr:street":"Gageldijk",
    "iso:country":"NL",
    "sg:address":"Gageldijk 65",
    "sg:city":"Maarssen",
    "sg:orig_category":"Partycatering And -Organisatie",
    "sg:phone":"+31 30 266 2551",
    "sg:postcode":"3602 AH",
    "sg:province":"Utrecht",
    "wof:name":"Kock Catering",
    "wof:placetype":"venue"
},
  "geometry": {"coordinates":[5.084442,52.137005],"type":"Point"}
}