{
  "type": "Feature",
  "properties": {
    "addr:full":"Meijboomlaan 1 Wassenaar South Holland 2242 PR",
    "addr:housenumber":"1",
    "addr:postcode":"2242 pr",
    "addr:street":"Meijboomlaan",
    "iso:country":"NL",
    "sg:address":"Meijboomlaan 1",
    "sg:city":"Wassenaar",
    "sg:orig_category":"Boekhandels",
    "sg:phone":"+31 70 512 2700",
    "sg:postcode":"2242 PR",
    "sg:province":"South Holland",
    "wof:name":"Reisboekhandel Zandvliet",
    "wof:placetype":"venue"
},
  "geometry": {"coordinates":[4.383506,52.159668],"type":"Point"}
}