{
  "type": "Feature",
  "properties": {
    "iso:country":"NL",
    "sg:address":"Radysstr 65A",
    "sg:city":"Groningen",
    "sg:orig_category":"Schilders",
    "sg:phone":"+31 50 579 1292",
    "sg:postcode":"9741 BL",
    "sg:province":"Groningen",
    "wof:name":"Valenteijn",
    "wof:placetype":"venue"
},
  "geometry": {"coordinates":[6.550398,53.229023],"type":"Point"}
}