{
  "type": "Feature",
  "properties": {
    "addr:full":"Geelgorsstr 69 Drachten Provincie Friesland 9201 TT",
    "addr:housenumber":"69",
    "addr:postcode":"9201 tt",
    "addr:street":"Geelgorsstr;Provincie Friesland",
    "iso:country":"NL",
    "sg:address":"Geelgorsstr 69",
    "sg:city":"Drachten",
    "sg:orig_category":"Montagebedrijven",
    "sg:phone":"+31 6 20134125",
    "sg:postcode":"9201 TT",
    "sg:province":"Provincie Friesland",
    "wof:name":"Gcb",
    "wof:placetype":"venue"
},
  "geometry": {"coordinates":[6.101734,53.113941],"type":"Point"}
}