{
  "type": "Feature",
  "properties": {
    "addr:full":"Luimesweg 20 Breedenbroek Gelderland 7084 AS",
    "addr:housenumber":"20",
    "addr:postcode":"7084 as",
    "addr:street":"Luimesweg;Gelderland",
    "iso:country":"NL",
    "sg:address":"Luimesweg 20",
    "sg:city":"Breedenbroek",
    "sg:orig_category":"Vertaal- And Tolkenbureaus",
    "sg:phone":"+31 315 617 566",
    "sg:postcode":"7084 AS",
    "sg:province":"Gelderland",
    "wof:name":"H. Tolkamp",
    "wof:placetype":"venue"
},
  "geometry": {"coordinates":[6.445521,51.888878],"type":"Point"}
}