{
  "type": "Feature",
  "properties": {
    "iso:country":"NL",
    "sg:address":"Spechtenkamp 231",
    "sg:city":"Maarssen",
    "sg:orig_category":"Fitnesscentra",
    "sg:phone":"+31 346 570 642",
    "sg:postcode":"3607 KN",
    "sg:province":"Utrecht",
    "wof:name":"Physical Spirits",
    "wof:placetype":"venue"
},
  "geometry": {"coordinates":[5.017437,52.137787],"type":"Point"}
}