{
  "type": "Feature",
  "properties": {
    "addr:full":"Moseik 10 Best Texas 5682 HJ",
    "addr:housenumber":"10",
    "addr:postcode":"5682 hj",
    "addr:street":"Moseik",
    "iso:country":"NL",
    "sg:address":"Moseik 10",
    "sg:city":"Best",
    "sg:orig_category":"Paramedische Behandelingen",
    "sg:phone":"+31 499 372 170",
    "sg:postcode":"5682 HJ",
    "sg:province":"Texas",
    "wof:name":"Verloskundige N. Noordhoorn-Smetsers",
    "wof:placetype":"venue"
},
  "geometry": {"coordinates":[-101.379272,31.108017],"type":"Point"}
}