{
  "type": "Feature",
  "properties": {
    "addr:full":"Geversstraat 63 Oegstgeest Zuid-Holland 2341 GC",
    "addr:housenumber":"63",
    "addr:postcode":"2341 gc",
    "addr:street":"Geversstraat",
    "iso:country":"NL",
    "sg:address":"Geversstraat 63",
    "sg:city":"Oegstgeest",
    "sg:orig_category":"Hypotheken And Hypotheekbanken",
    "sg:phone":"+31 71 519 1919",
    "sg:postcode":"2341 GC",
    "sg:province":"Zuid-Holland",
    "sg:website":"http://.",
    "wof:name":"Eigen Haard Makelaardij",
    "wof:placetype":"venue"
},
  "geometry": {"coordinates":[4.468275,52.176807],"type":"Point"}
}