{
  "type": "Feature",
  "properties": {
    "iso:country":"NL",
    "sg:address":"Veerwg 35",
    "sg:city":"Wolphaartsdyk",
    "sg:orig_category":"Bloemen En Planten",
    "sg:phone":"+31 113 582 052",
    "sg:postcode":"4471 BJ",
    "sg:province":"Zeeland",
    "wof:name":"Nationale Collectie Passifloras",
    "wof:placetype":"venue"
},
  "geometry": {"coordinates":[3.814716,51.53553],"type":"Point"}
}