{
  "type": "Feature",
  "properties": {
    "addr:full":"Gedempte Oude Gracht 93 Haarlem North Holland 2011 GN",
    "addr:housenumber":"93",
    "addr:postcode":"2011 gn",
    "addr:street":"Gedempte Oude Gracht",
    "iso:country":"NL",
    "sg:address":"Gedempte Oude Gracht 93",
    "sg:city":"Haarlem",
    "sg:orig_category":"Meubelzaken, Woning- And Keukeninrichting",
    "sg:phone":"+31 23 532 4614",
    "sg:postcode":"2011 GN",
    "sg:province":"North Holland",
    "wof:name":"Van Honschoten",
    "wof:placetype":"venue"
},
  "geometry": {"coordinates":[4.634417,52.378922],"type":"Point"}
}