{
  "type": "Feature",
  "properties": {
    "addr:full":"De Merodestr 30 Dordrecht Zuid-Holland 3319 BG",
    "addr:housenumber":"30",
    "addr:postcode":"3319",
    "iso:country":"NL",
    "sg:address":"De Merodestr 30",
    "sg:city":"Dordrecht",
    "sg:orig_category":"Wijnkoperijen En -Groothandel",
    "sg:phone":"+31 78 616 6319",
    "sg:postcode":"3319 BG",
    "sg:province":"Zuid-Holland",
    "wof:name":"Cave Michel",
    "wof:placetype":"venue"
},
  "geometry": {"coordinates":[4.7024569511,51.7969360352],"type":"Point"}
}