{
  "type": "Feature",
  "properties": {
    "addr:full":"Westerblokker 122 Blokker Noord-Holland 1695 AL",
    "addr:housenumber":"122;1695",
    "addr:postcode":"al",
    "addr:street":"Westerblokker",
    "iso:country":"NL",
    "sg:address":"Westerblokker 122",
    "sg:city":"Blokker",
    "sg:classifiers":[
        {
            "category":"Retail",
            "subcategory":"Auto Repair",
            "type":"Services"
        }
    ],
    "sg:phone":"+31 229 240 230",
    "sg:postcode":"1695 AL",
    "sg:province":"Noord-Holland",
    "sg:tags":[
        "garage"
    ],
    "wof:name":"Waag, De",
    "wof:placetype":"venue"
},
  "geometry": {"coordinates":[5.079331,52.657688],"type":"Point"}
}