{
  "type": "Feature",
  "properties": {
    "addr:full":"Vlinderveen 221 Spykenisse South Holland 3205 EB",
    "addr:housenumber":"221",
    "addr:postcode":"3205 eb",
    "addr:street":"Vlinderveen",
    "iso:country":"NL",
    "sg:address":"Vlinderveen 221",
    "sg:city":"Spykenisse",
    "sg:orig_category":"Scholen Voor Basisonderwijs",
    "sg:phone":"+31 181 640 087",
    "sg:postcode":"3205 EB",
    "sg:province":"South Holland",
    "wof:name":"Veenvlinder Openb, De",
    "wof:placetype":"venue"
},
  "geometry": {"coordinates":[4.342477,51.833569],"type":"Point"}
}