{
  "type": "Feature",
  "properties": {
    "addr:full":"Pr Margrietln 14 Bathmen NL.08 7437 VD",
    "addr:housenumber":"14;nl.08",
    "addr:postcode":"7437 vd",
    "iso:country":"NL",
    "sg:address":"Pr Margrietln 14",
    "sg:city":"Bathmen",
    "sg:orig_category":"Kantinebeheer",
    "sg:phone":"+31 570 544 429",
    "sg:postcode":"7437 VD",
    "sg:province":"NL.08",
    "wof:name":"Uutvlog, De",
    "wof:placetype":"venue"
},
  "geometry": {"coordinates":[6.2996368408,52.2504692078],"type":"Point"}
}