{
  "type": "Feature",
  "properties": {
    "addr:full":"Alteveerstr 3 Hoogeveen Provincie Drenthe 7906 CA",
    "addr:housenumber":"3",
    "addr:postcode":"7906 ca",
    "addr:street":"Alteveerstr;Provincie",
    "iso:country":"NL",
    "sg:address":"Alteveerstr 3",
    "sg:city":"Hoogeveen",
    "sg:orig_category":"Apotheken",
    "sg:phone":"+31 528 262 102",
    "sg:postcode":"7906 CA",
    "sg:province":"Provincie Drenthe",
    "wof:name":"Duivenstede",
    "wof:placetype":"venue"
},
  "geometry": {"coordinates":[6.477891,52.720219],"type":"Point"}
}