{
  "type": "Feature",
  "properties": {
    "addr:full":"Rijksstraatweg 170 Leersum Utrecht 3956 CV",
    "addr:housenumber":"170",
    "addr:postcode":"3956 cv",
    "addr:street":"Rijksstraatweg",
    "iso:country":"NL",
    "sg:address":"Rijksstraatweg 170",
    "sg:city":"Leersum",
    "sg:orig_category":"Autokeuringen",
    "sg:phone":"+31 343 451 315",
    "sg:postcode":"3956 CV",
    "sg:province":"Utrecht",
    "wof:name":"Garagebedrijf H. Bos En Zoon",
    "wof:placetype":"venue"
},
  "geometry": {"coordinates":[5.42393,52.013519],"type":"Point"}
}