{
  "type": "Feature",
  "properties": {
    "iso:country":"NL",
    "sg:address":"Karolusgulden 33",
    "sg:city":"Leiderdorp",
    "sg:orig_category":"Verhuur",
    "sg:phone":"+31 71 589 1792",
    "sg:postcode":"2353 TB",
    "sg:province":"Zuid-Holland",
    "wof:name":"Aclin 3 Bv",
    "wof:placetype":"venue"
},
  "geometry": {"coordinates":[4.533198,52.161304],"type":"Point"}
}