{
  "type": "Feature",
  "properties": {
    "iso:country":"NL",
    "sg:address":"Weurden 11",
    "sg:city":"Winterswijk",
    "sg:orig_category":"Zuivelproducten",
    "sg:phone":"+31 543 512 802",
    "sg:postcode":"7101 NG",
    "sg:province":"Gelderland",
    "wof:name":"Kaashandel J. Boes",
    "wof:placetype":"venue"
},
  "geometry": {"coordinates":[6.721913,51.9692],"type":"Point"}
}