{
  "type": "Feature",
  "properties": {
    "addr:full":"Sperwerstr 15 Brummen Gelderland 6971 VV",
    "addr:housenumber":"15",
    "addr:postcode":"6971 vv",
    "addr:street":"Sperwerstr;Gelderland",
    "iso:country":"NL",
    "sg:address":"Sperwerstr 15",
    "sg:city":"Brummen",
    "sg:orig_category":"Kappers",
    "sg:phone":"+31 575 566 108",
    "sg:postcode":"6971 VV",
    "sg:province":"Gelderland",
    "wof:name":"Charlotte",
    "wof:placetype":"venue"
},
  "geometry": {"coordinates":[6.158454895,52.0963439941],"type":"Point"}
}