{
  "type": "Feature",
  "properties": {
    "addr:full":"Oostwal 12 Oss Noord-Brabant 5341 KX",
    "addr:housenumber":"12",
    "addr:postcode":"5341 kx",
    "addr:street":"Oostwal",
    "iso:country":"NL",
    "sg:address":"Oostwal 12",
    "sg:city":"Oss",
    "sg:orig_category":"Gespecialiseerde Bouw",
    "sg:phone":"+31 412 625 734",
    "sg:postcode":"5341 KX",
    "sg:province":"Noord-Brabant",
    "wof:name":"Adviesburo Beton- En Staal- Constructies A.Th. Ele",
    "wof:placetype":"venue"
},
  "geometry": {"coordinates":[-91.223618,44.580818],"type":"Point"}
}