{
  "type": "Feature",
  "properties": {
    "iso:country":"NL",
    "sg:address":"J C Van Andelweg 7",
    "sg:city":"Staphorst",
    "sg:orig_category":"Verlichting And Huishoudartikelen",
    "sg:phone":"+31 522 461 773",
    "sg:postcode":"7951 DT",
    "sg:province":"Overijssel",
    "wof:name":"Lampenland",
    "wof:placetype":"venue"
},
  "geometry": {"coordinates":[6.223171,52.640064],"type":"Point"}
}