{
  "type": "Feature",
  "properties": {
    "addr:full":"Prins Hendriklaan 10 Bussum Noord-Holland 1404 AT",
    "addr:housenumber":"10",
    "addr:postcode":"1404",
    "addr:street":"Prins Hendriklaan",
    "iso:country":"NL",
    "sg:address":"Prins Hendriklaan 10",
    "sg:city":"Bussum",
    "sg:orig_category":"Makelaars In Onroerend Goed",
    "sg:phone":"+31 35 694 5142",
    "sg:postcode":"1404 AT",
    "sg:province":"Noord-Holland",
    "wof:name":"Albers Assurantie Makelaars & Adviseurs",
    "wof:placetype":"venue"
},
  "geometry": {"coordinates":[5.159544,52.28093],"type":"Point"}
}