{
  "type": "Feature",
  "properties": {
    "addr:full":"Wynstr 161 Dordrecht South Holland 3311 BV",
    "addr:housenumber":"161",
    "addr:postcode":"3311 bv",
    "iso:country":"NL",
    "sg:address":"Wynstr 161",
    "sg:city":"Dordrecht",
    "sg:orig_category":"Onroerende Goederen",
    "sg:phone":"+31 78 631 1054",
    "sg:postcode":"3311 BV",
    "sg:province":"South Holland",
    "wof:name":"Bastille Bv",
    "wof:placetype":"venue"
},
  "geometry": {"coordinates":[4.656506,51.811916],"type":"Point"}
}