{
  "type": "Feature",
  "properties": {
    "addr:full":"Diependaalsedk 19/B Maarssen Utrecht 3601 GH",
    "addr:housenumber":"19 / b",
    "addr:postcode":"3601 gh",
    "addr:street":"Diependaalsedk",
    "iso:country":"NL",
    "sg:address":"Diependaalsedk 19/B",
    "sg:city":"Maarssen",
    "sg:orig_category":"Musea",
    "sg:phone":"+31 346 554 440",
    "sg:postcode":"3601 GH",
    "sg:province":"Utrecht",
    "wof:name":"Museum Maarssen",
    "wof:placetype":"venue"
},
  "geometry": {"coordinates":[5.035247,52.144684],"type":"Point"}
}