{
  "type": "Feature",
  "properties": {
    "addr:full":"Toevlucht 8B Spanbroek Noord-Holland 1715 KH",
    "addr:housenumber":"8b",
    "addr:postcode":"1715 kh",
    "addr:street":"Toevlucht",
    "iso:country":"NL",
    "sg:address":"Toevlucht 8B",
    "sg:city":"Spanbroek",
    "sg:orig_category":"Autorijscholen",
    "sg:phone":"+31 65137116",
    "sg:postcode":"1715 KH",
    "sg:province":"Noord-Holland",
    "wof:name":"Schipper, P",
    "wof:placetype":"venue"
},
  "geometry": {"coordinates":[4.95866,52.697525],"type":"Point"}
}