{
  "type": "Feature",
  "properties": {
    "iso:country":"NL",
    "sg:address":"Henneland 30",
    "sg:city":"Ursem",
    "sg:orig_category":"Administratie- En Boekhoudkantoren",
    "sg:phone":"+31 72 502 2530",
    "sg:postcode":"1645 RW",
    "sg:province":"North Holland",
    "wof:name":"Beuken",
    "wof:placetype":"venue"
},
  "geometry": {"coordinates":[4.87692,52.634331],"type":"Point"}
}