{
  "type": "Feature",
  "properties": {
    "addr:full":"Kruisherengang 16 Maastricht Limburg 6211 NW",
    "addr:housenumber":"16",
    "addr:postcode":"6211 nw",
    "addr:street":"Kruisherengang",
    "iso:country":"NL",
    "sg:address":"Kruisherengang 16",
    "sg:city":"Maastricht",
    "sg:orig_category":"Boekbinderijen",
    "sg:phone":"+31 43 362 5889",
    "sg:postcode":"6211 NW",
    "sg:province":"Limburg",
    "wof:name":"Lipsch",
    "wof:placetype":"venue"
},
  "geometry": {"coordinates":[5.683419,50.848312],"type":"Point"}
}