{
  "type": "Feature",
  "properties": {
    "addr:full":"Hoekenes 13 Amsterdam Noord-Holland 1068 ML",
    "addr:housenumber":"13",
    "addr:postcode":"1068 ml",
    "addr:street":"Hoekenes",
    "iso:country":"NL",
    "sg:address":"Hoekenes 13",
    "sg:city":"Amsterdam",
    "sg:orig_category":"Fietsen En Bromfietsen",
    "sg:phone":"+31 20 610 3922",
    "sg:postcode":"1068 ML",
    "sg:province":"Noord-Holland",
    "wof:name":"Cornelis",
    "wof:placetype":"venue"
},
  "geometry": {"coordinates":[4.798504,52.361103],"type":"Point"}
}