{
  "type": "Feature",
  "properties": {
    "addr:full":"Steenplaats 5 Gorinchem South Holland 4207 GR",
    "addr:housenumber":"5",
    "addr:postcode":"4207",
    "addr:street":"Steenplaats",
    "iso:country":"NL",
    "sg:address":"Steenplaats 5",
    "sg:city":"Gorinchem",
    "sg:orig_category":"Projectontwikkeling",
    "sg:phone":"+31 183 690 903",
    "sg:postcode":"4207 GR",
    "sg:province":"South Holland",
    "wof:name":"Haeser Bv",
    "wof:placetype":"venue"
},
  "geometry": {"coordinates":[4.986269,51.830002],"type":"Point"}
}