{
  "type": "Feature",
  "properties": {
    "addr:full":"Leidsegr 51 Amsterdam Noord-Holland 1017 NB",
    "addr:housenumber":"51",
    "addr:postcode":"1017 nb",
    "addr:street":"Leidsegr",
    "iso:country":"NL",
    "sg:address":"Leidsegr 51",
    "sg:city":"Amsterdam",
    "sg:orig_category":"Filmstudio'S En -Productie",
    "sg:phone":"+31 20 626 6285",
    "sg:postcode":"1017 NB",
    "sg:province":"Noord-Holland",
    "wof:name":"Plukker",
    "wof:placetype":"venue"
},
  "geometry": {"coordinates":[4.88372,52.366219],"type":"Point"}
}