{
  "type": "Feature",
  "properties": {
    "iso:country":"NL",
    "sg:address":"Kerkln 10",
    "sg:city":"De Lier",
    "sg:orig_category":"Accountants - Administratie- Consulenten En -Kantoren",
    "sg:phone":"+31 174 513 782",
    "sg:postcode":"2678 SV",
    "sg:province":"South Holland",
    "wof:name":"Haze",
    "wof:placetype":"venue"
},
  "geometry": {"coordinates":[4.25138,51.975086],"type":"Point"}
}