{
  "type": "Feature",
  "properties": {
    "addr:full":"V Dykhuizenstr 76 Nykerkerveen Gelderland 3864 DW",
    "addr:housenumber":"76",
    "addr:postcode":"3864 dw",
    "addr:street":"V Dykhuizenstr;Gelderland",
    "iso:country":"NL",
    "sg:address":"V Dykhuizenstr 76",
    "sg:city":"Nykerkerveen",
    "sg:orig_category":"Autorijscholen",
    "sg:phone":"+31 33 257 2488",
    "sg:postcode":"3864 DW",
    "sg:province":"Gelderland",
    "wof:name":"Ruitenbeek, A",
    "wof:placetype":"venue"
},
  "geometry": {"coordinates":[5.455747,52.199169],"type":"Point"}
}