{
  "type": "Feature",
  "properties": {
    "iso:country":"NL",
    "sg:address":"Zonnehof 42",
    "sg:city":"Amersfoort",
    "sg:orig_category":"Hypotheken And Hypotheekbanken",
    "sg:phone":"+31 33 247 5040",
    "sg:postcode":"3811 ND",
    "sg:province":"Utrecht",
    "wof:name":"Profin Financiele En Assurantie Adviseurs",
    "wof:placetype":"venue"
},
  "geometry": {"coordinates":[5.383518,52.152645],"type":"Point"}
}