{
  "type": "Feature",
  "properties": {
    "addr:full":"Eindstraat 22 Breda North Brabant 4811 KL",
    "addr:housenumber":"22",
    "addr:postcode":"4811 kl",
    "addr:street":"Eindstraat",
    "iso:country":"NL",
    "sg:address":"Eindstraat 22",
    "sg:city":"Breda",
    "sg:orig_category":"Schoenen",
    "sg:phone":"+31 76 514 1599",
    "sg:postcode":"4811 KL",
    "sg:province":"North Brabant",
    "wof:name":"Manfield",
    "wof:placetype":"venue"
},
  "geometry": {"coordinates":[4.775984,51.58633],"type":"Point"}
}