{
  "type": "Feature",
  "properties": {
    "iso:country":"NL",
    "sg:address":"Zonnebloemveld 4",
    "sg:city":"Beuningen Gld",
    "sg:orig_category":"Autokeuringen",
    "sg:phone":"+31 24 677 9176",
    "sg:postcode":"6641 TA",
    "sg:province":"Gelderland",
    "wof:name":"Europa Car",
    "wof:placetype":"venue"
},
  "geometry": {"coordinates":[5.753187,51.864029],"type":"Point"}
}