{
  "type": "Feature",
  "properties": {
    "iso:country":"NL",
    "sg:address":"Adriaan Van Ostadestraat 38",
    "sg:city":"Groningen",
    "sg:orig_category":"Kinderopvang Behalve Thuis",
    "sg:phone":"+31 50 313 0388",
    "sg:postcode":"9718 RZ",
    "sg:province":"Groningen",
    "wof:name":"Stichting Buitenschoolseopvang Schildersbuurt",
    "wof:placetype":"venue"
},
  "geometry": {"coordinates":[6.541755,53.216572],"type":"Point"}
}