{
  "type": "Feature",
  "properties": {
    "iso:country":"NL",
    "sg:address":"Hof Vd Houte 49",
    "sg:city":"Etten Leur",
    "sg:orig_category":"Herenkleding",
    "sg:phone":"+31 76 503 7490",
    "sg:postcode":"4873 AZ",
    "sg:province":"North Brabant",
    "wof:name":"Dal Bv, Van",
    "wof:placetype":"venue"
},
  "geometry": {"coordinates":[4.638043,51.568291],"type":"Point"}
}