{
  "type": "Feature",
  "properties": {
    "addr:full":"Spuiweg 62 Lelystad Flevoland 8243 PW",
    "addr:housenumber":"62",
    "addr:postcode":"8243 pw",
    "addr:street":"Spuiweg;Flevoland",
    "iso:country":"NL",
    "sg:address":"Spuiweg 62",
    "sg:city":"Lelystad",
    "sg:orig_category":"Feestartikelen",
    "sg:phone":"+31 320 260 909",
    "sg:postcode":"8243 PW",
    "sg:province":"Flevoland",
    "wof:name":"Allflags",
    "wof:placetype":"venue"
},
  "geometry": {"coordinates":[5.433619,52.502766],"type":"Point"}
}