{
  "type": "Feature",
  "properties": {
    "addr:full":"Schouw 4809 Lelystad Flevoland 8232 BD",
    "addr:postcode":"4809;8232 bd",
    "addr:street":"Schouw;Flevoland",
    "iso:country":"NL",
    "sg:address":"Schouw 4809",
    "sg:city":"Lelystad",
    "sg:orig_category":"Autorijscholen",
    "sg:phone":"+31 320 236 198",
    "sg:postcode":"8232 BD",
    "sg:province":"Flevoland",
    "wof:name":"Amal",
    "wof:placetype":"venue"
},
  "geometry": {"coordinates":[5.463336,52.509857],"type":"Point"}
}