{
  "type": "Feature",
  "properties": {
    "addr:full":"R Holstln 652 Delft South Holland 2624 JA",
    "addr:housenumber":"652",
    "addr:postcode":"2624 ja",
    "iso:country":"NL",
    "sg:address":"R Holstln 652",
    "sg:city":"Delft",
    "sg:orig_category":"Kinderopvang",
    "sg:phone":"+31 15 262 5228",
    "sg:postcode":"2624 JA",
    "sg:province":"South Holland",
    "wof:name":"Ienie Mienie Hof",
    "wof:placetype":"venue"
},
  "geometry": {"coordinates":[4.35634,51.995491],"type":"Point"}
}