{
  "type": "Feature",
  "properties": {
    "addr:full":"Splitting 59 Emmen Drenthe 7826 CP",
    "addr:housenumber":"59",
    "addr:postcode":"7826 cp",
    "addr:street":"Splitting",
    "iso:country":"NL",
    "sg:address":"Splitting 59",
    "sg:city":"Emmen",
    "sg:orig_category":"Zalenverhuur",
    "sg:phone":"+31 591 622 464",
    "sg:postcode":"7826 CP",
    "sg:province":"Drenthe",
    "wof:name":"Flinthoek, De",
    "wof:placetype":"venue"
},
  "geometry": {"coordinates":[6.962825,52.773003],"type":"Point"}
}