{
  "type": "Feature",
  "properties": {
    "addr:full":"Kloosterstr 6 Ootmarsum Overijssel 7631 GA",
    "addr:housenumber":"6",
    "addr:postcode":"7631 ga",
    "addr:street":"Kloosterstr",
    "iso:country":"NL",
    "sg:address":"Kloosterstr 6",
    "sg:city":"Ootmarsum",
    "sg:orig_category":"Galeries",
    "sg:phone":"+31 541 295 084",
    "sg:postcode":"7631 GA",
    "sg:province":"Overijssel",
    "wof:name":"Kloosterhof",
    "wof:placetype":"venue"
},
  "geometry": {"coordinates":[6.900059,52.407455],"type":"Point"}
}