{
  "type": "Feature",
  "properties": {
    "addr:full":"Mylwg 5 Vianen Zh Utrecht 4131 PJ",
    "addr:housenumber":"5",
    "addr:postcode":"zh;4131 pj",
    "addr:street":"Mylwg",
    "iso:country":"NL",
    "sg:address":"Mylwg 5",
    "sg:city":"Vianen Zh",
    "sg:classifiers":[
        {
            "category":"Home & Garden",
            "subcategory":"Hardware",
            "type":"Retail Goods"
        }
    ],
    "sg:phone":"+31 347 377 000",
    "sg:postcode":"4131 PJ",
    "sg:province":"Utrecht",
    "sg:tags":[
        "machine",
        "houtbewerking",
        "-"
    ],
    "sg:website":"http://www.bosmachines.nl",
    "wof:name":"Bos Machines Bv",
    "wof:placetype":"venue"
},
  "geometry": {"coordinates":[5.100703,51.991146],"type":"Point"}
}