{
  "type": "Feature",
  "properties": {
    "addr:full":"Tollebekerwg 4 Espel Minnesota 8311 PM",
    "addr:housenumber":"4",
    "addr:postcode":"8311 pm",
    "addr:street":"Tollebekerwg;Minnesota",
    "iso:country":"NL",
    "sg:address":"Tollebekerwg 4",
    "sg:city":"Espel",
    "sg:orig_category":"Makelaars En Adviseurs Onroerende Goederen",
    "sg:phone":"+31 527 271 938",
    "sg:postcode":"8311 PM",
    "sg:province":"Minnesota",
    "wof:name":"Waalkens",
    "wof:placetype":"venue"
},
  "geometry": {"coordinates":[-95.71624799999999,48.223763],"type":"Point"}
}