{
  "type": "Feature",
  "properties": {
    "iso:country":"NL",
    "sg:address":"Westgaag 44",
    "sg:city":"Maasland",
    "sg:orig_category":"Bloemen- And Plantenteelt",
    "sg:phone":"+31 10 591 7946",
    "sg:postcode":"3155 DG",
    "sg:province":"Zuid-Holland",
    "wof:name":"Firma Hoogendijk",
    "wof:placetype":"venue"
},
  "geometry": {"coordinates":[4.265996,51.948727],"type":"Point"}
}