{
  "type": "Feature",
  "properties": {
    "addr:full":"Marswg 65A Zwolle Overijssel 8013 PE",
    "addr:housenumber":"65a",
    "addr:postcode":"8013 pe",
    "addr:street":"Marswg",
    "iso:country":"NL",
    "sg:address":"Marswg 65A",
    "sg:city":"Zwolle",
    "sg:orig_category":"Pompen - Verhuur",
    "sg:phone":"+31 38 465 6868",
    "sg:postcode":"8013 PE",
    "sg:province":"Overijssel",
    "wof:name":"Eekels Bv",
    "wof:placetype":"venue"
},
  "geometry": {"coordinates":[6.129458,52.487022],"type":"Point"}
}