{
  "type": "Feature",
  "properties": {
    "addr:full":"Tolweg 2 Ermelo Gelderland 3851 SK",
    "addr:housenumber":"2",
    "addr:street":"Tolweg;Gelderland 3851",
    "iso:country":"NL",
    "sg:address":"Tolweg 2",
    "sg:city":"Ermelo",
    "sg:orig_category":"Loodgieterswerk, Verwarming And Sanitaire Installaties",
    "sg:phone":"+31 341 563 227",
    "sg:postcode":"3851 SK",
    "sg:province":"Gelderland",
    "wof:name":"Van Panhuis Vastgoed Bv",
    "wof:placetype":"venue"
},
  "geometry": {"coordinates":[5.62121,52.318668],"type":"Point"}
}