{
  "type": "Feature",
  "properties": {
    "addr:full":"Verre Weiden 25 Ryen Noord-Brabant 5122 HA",
    "addr:housenumber":"25",
    "addr:postcode":"5122 ha",
    "addr:street":"Verre Weiden",
    "iso:country":"NL",
    "sg:address":"Verre Weiden 25",
    "sg:city":"Ryen",
    "sg:orig_category":"Kinderkleding",
    "sg:phone":"+31 161 226 083",
    "sg:postcode":"5122 HA",
    "sg:province":"Noord-Brabant",
    "wof:name":"Snuffy,S",
    "wof:placetype":"venue"
},
  "geometry": {"coordinates":[4.92752,51.59277],"type":"Point"}
}