{
  "type": "Feature",
  "properties": {
    "addr:full":"Nieuwestad 49 Leeuwarden Provincie Friesland 8911 CJ",
    "addr:housenumber":"49",
    "addr:postcode":"8911 cj",
    "addr:street":"Nieuwestad;Provincie Friesland",
    "iso:country":"NL",
    "sg:address":"Nieuwestad 49",
    "sg:city":"Leeuwarden",
    "sg:orig_category":"Discotheken",
    "sg:phone":"+31 58 212 0871",
    "sg:postcode":"8911 CJ",
    "sg:province":"Provincie Friesland",
    "sg:website":"http://www.firepalace.com",
    "wof:name":"Fire Palace",
    "wof:placetype":"venue"
},
  "geometry": {"coordinates":[5.791883,53.20166],"type":"Point"}
}