{
  "type": "Feature",
  "properties": {
    "addr:full":"Plaats 31 'S Gravenhage South Holland 2513 AD",
    "addr:housenumber":"31",
    "addr:postcode":"2513 ad",
    "addr:street":"Plaats;' S Gravenhage",
    "iso:country":"NL",
    "sg:address":"Plaats 31",
    "sg:city":"'S Gravenhage",
    "sg:orig_category":"Werving And Selectie Van Tijdelijk Personeel And Uitzendkantoren",
    "sg:phone":"+31 70 311 5500",
    "sg:postcode":"2513 AD",
    "sg:province":"South Holland",
    "wof:name":"Unique Uitzendburo",
    "wof:placetype":"venue"
},
  "geometry": {"coordinates":[4.3102431297,52.0798912048],"type":"Point"}
}