{
  "type": "Feature",
  "properties": {
    "addr:full":"Hunze 118 Drachten Provincie Friesland 9204 BT",
    "addr:housenumber":"118",
    "addr:postcode":"9204 bt",
    "addr:street":"Hunze;Provincie Friesland",
    "iso:country":"NL",
    "sg:address":"Hunze 118",
    "sg:city":"Drachten",
    "sg:orig_category":"Onderhoudswerken",
    "sg:phone":"+31 512 511 444",
    "sg:postcode":"9204 BT",
    "sg:province":"Provincie Friesland",
    "wof:name":"Helder",
    "wof:placetype":"venue"
},
  "geometry": {"coordinates":[6.077863,53.101467],"type":"Point"}
}