{
  "type": "Feature",
  "properties": {
    "addr:full":"Zanddk 44 Rozenburg Zh Zuid-Holland 3181 HV",
    "addr:housenumber":"44",
    "addr:postcode":"zh;3181 hv",
    "addr:street":"Zanddk",
    "iso:country":"NL",
    "sg:address":"Zanddk 44",
    "sg:city":"Rozenburg Zh",
    "sg:orig_category":"Schilders",
    "sg:phone":"+31 181 213 946",
    "sg:postcode":"3181 HV",
    "sg:province":"Zuid-Holland",
    "wof:name":"Edo",
    "wof:placetype":"venue"
},
  "geometry": {"coordinates":[4.236402,51.911522],"type":"Point"}
}