{
  "type": "Feature",
  "properties": {
    "addr:full":"Bisschopstr 39 Weerselo Overijssel 7595 AR",
    "addr:housenumber":"39",
    "addr:postcode":"7595",
    "addr:street":"Bisschopstr",
    "iso:country":"NL",
    "sg:address":"Bisschopstr 39",
    "sg:city":"Weerselo",
    "sg:orig_category":"Bloemen En Planten",
    "sg:phone":"+31 541 661 269",
    "sg:postcode":"7595 AR",
    "sg:province":"Overijssel",
    "wof:name":"Thea",
    "wof:placetype":"venue"
},
  "geometry": {"coordinates":[6.854326,52.350395],"type":"Point"}
}