{
  "type": "Feature",
  "properties": {
    "iso:country":"NL",
    "sg:address":"Limbrichterstraat 11",
    "sg:city":"Sittard",
    "sg:orig_category":"Verlichting And Huishoudartikelen",
    "sg:phone":"+31 46 452 8447",
    "sg:postcode":"6131 EA",
    "sg:province":"Limburg",
    "wof:name":"Hoyng Sittard",
    "wof:placetype":"venue"
},
  "geometry": {"coordinates":[5.869503,50.998287],"type":"Point"}
}