{
  "type": "Feature",
  "properties": {
    "addr:full":"Nieuwe Binnenweg 4 Rotterdam Zuid-Holland 3015 BA",
    "addr:housenumber":"4",
    "addr:postcode":"3015 ba",
    "addr:street":"Nieuwe Binnenweg",
    "iso:country":"NL",
    "sg:address":"Nieuwe Binnenweg 4",
    "sg:city":"Rotterdam",
    "sg:orig_category":"Kappers",
    "sg:phone":"+31 10 436 4350",
    "sg:postcode":"3015 BA",
    "sg:province":"Zuid-Holland",
    "wof:name":"Barbershop Nikolaas",
    "wof:placetype":"venue"
},
  "geometry": {"coordinates":[4.4724822044,51.9167823792],"type":"Point"}
}