{
  "type": "Feature",
  "properties": {
    "addr:full":"Slinger 37 Genemuiden NL.08 8281 MD",
    "addr:housenumber":"37;nl.08",
    "addr:postcode":"8281",
    "addr:street":"Slinger",
    "iso:country":"NL",
    "sg:address":"Slinger 37",
    "sg:city":"Genemuiden",
    "sg:orig_category":"Zuivelproducten",
    "sg:phone":"+31 38 385 4324",
    "sg:postcode":"8281 MD",
    "sg:province":"NL.08",
    "wof:name":"Melk En Zuivelhandel W. Visscher",
    "wof:placetype":"venue"
},
  "geometry": {"coordinates":[6.033691,52.623459],"type":"Point"}
}