{
  "type": "Feature",
  "properties": {
    "addr:full":"Johanniterlaan 8 Harderwijk Gelderland 3841 DT",
    "addr:housenumber":"8",
    "addr:postcode":"3841 dt",
    "addr:street":"Johanniterlaan;Gelderland",
    "iso:country":"NL",
    "sg:address":"Johanniterlaan 8",
    "sg:city":"Harderwijk",
    "sg:orig_category":"Verzekeringen",
    "sg:phone":"+31 341 426 900",
    "sg:postcode":"3841 DT",
    "sg:province":"Gelderland",
    "wof:name":"Assurantiebedrijf Hoekstra",
    "wof:placetype":"venue"
},
  "geometry": {"coordinates":[5.624048,52.345207],"type":"Point"}
}