{
  "type": "Feature",
  "properties": {
    "iso:country":"NL",
    "sg:address":"Raadhuisplein 1",
    "sg:city":"Stein Lb",
    "sg:orig_category":"Overheidsdiensten",
    "sg:phone":"+31 46 435 9393",
    "sg:postcode":"6171 JB",
    "sg:province":"Limburg",
    "wof:name":"Gemeente Stein",
    "wof:placetype":"venue"
},
  "geometry": {"coordinates":[-118.1173248291,33.7685890198],"type":"Point"}
}