{
  "type": "Feature",
  "properties": {
    "iso:country":"NL",
    "sg:address":"De Buurt 1",
    "sg:city":"Venhuizen",
    "sg:orig_category":"Film-, Tv- And Videoproductie",
    "sg:phone":"+31 228 543 300",
    "sg:postcode":"1606 AC",
    "sg:province":"Noord-Holland",
    "wof:name":"Aart Brouwer Productions",
    "wof:placetype":"venue"
},
  "geometry": {"coordinates":[5.229429,52.677143],"type":"Point"}
}