{
  "type": "Feature",
  "properties": {
    "addr:full":"2E Kostverlorenkd 127 Amsterdam North Holland 1053 SE",
    "addr:housenumber":"127",
    "addr:postcode":"1053 se",
    "addr:street":"2E Kostverlorenkd",
    "iso:country":"NL",
    "sg:address":"2E Kostverlorenkd 127",
    "sg:city":"Amsterdam",
    "sg:orig_category":"Fotojournalisten Freelance",
    "sg:phone":"+31 20 616 4704",
    "sg:postcode":"1053 SE",
    "sg:province":"North Holland",
    "wof:name":"Tolenaar, Paul",
    "wof:placetype":"venue"
},
  "geometry": {"coordinates":[4.860335,52.364285],"type":"Point"}
}