{
  "type": "Feature",
  "properties": {
    "iso:country":"NL",
    "sg:address":"Kelloggstr 126",
    "sg:city":"Hoofddorp",
    "sg:orig_category":"Logopedisten",
    "sg:phone":"+31 23 561 7492",
    "sg:postcode":"2131 SL",
    "sg:province":"North Holland",
    "wof:name":"Riekje Knol",
    "wof:placetype":"venue"
},
  "geometry": {"coordinates":[4.674678,52.306435],"type":"Point"}
}