{
  "type": "Feature",
  "properties": {
    "addr:full":"Meysstr 18 Wynandsrade Limburg 6363 BS",
    "addr:housenumber":"18",
    "addr:postcode":"6363 bs",
    "addr:street":"Meysstr;Limburg",
    "iso:country":"NL",
    "sg:address":"Meysstr 18",
    "sg:city":"Wynandsrade",
    "sg:orig_category":"Verhuur",
    "sg:phone":"+31 6 20991103",
    "sg:postcode":"6363 BS",
    "sg:province":"Limburg",
    "wof:name":"Marell",
    "wof:placetype":"venue"
},
  "geometry": {"coordinates":[5.9012,50.905365],"type":"Point"}
}