{
  "type": "Feature",
  "properties": {
    "addr:full":"Pikeursbaan 2 Deventer Overijssel 7411 GV",
    "addr:housenumber":"2",
    "addr:postcode":"7411 gv",
    "addr:street":"Pikeursbaan",
    "iso:country":"NL",
    "sg:address":"Pikeursbaan 2",
    "sg:city":"Deventer",
    "sg:orig_category":"Beroepsorganisaties",
    "sg:phone":"+31 570 613 848",
    "sg:postcode":"7411 GV",
    "sg:province":"Overijssel",
    "wof:name":"Fnv Dienstenbond",
    "wof:placetype":"venue"
},
  "geometry": {"coordinates":[6.160657,52.254677],"type":"Point"}
}