{
  "type": "Feature",
  "properties": {
    "addr:full":"Burg Coxln 2 Heeze Noord-Brabant 5591 EN",
    "addr:housenumber":"2",
    "addr:postcode":"5591 en",
    "addr:street":"Burg Coxln",
    "iso:country":"NL",
    "sg:address":"Burg Coxln 2",
    "sg:city":"Heeze",
    "sg:orig_category":"Waterbeheer",
    "sg:phone":"+31 40 224 1221",
    "sg:postcode":"5591 EN",
    "sg:province":"Noord-Brabant",
    "wof:name":"Nv Waterleidingmaatschappij Oost-Brabant",
    "wof:placetype":"venue"
},
  "geometry": {"coordinates":[5.5778207779,51.3795967102],"type":"Point"}
}