{
  "type": "Feature",
  "properties": {
    "addr:full":"Marktplein 134 Hoofddorp Noord-Holland 2132 DE",
    "addr:housenumber":"134",
    "addr:postcode":"2132 de",
    "addr:street":"Marktplein",
    "iso:country":"NL",
    "sg:address":"Marktplein 134",
    "sg:city":"Hoofddorp",
    "sg:orig_category":"Huishoudapparatuur, Televisies And Radio'S",
    "sg:phone":"+31 23 561 4290",
    "sg:postcode":"2132 DE",
    "sg:province":"Noord-Holland",
    "wof:name":"S & F Scheer & Foppen",
    "wof:placetype":"venue"
},
  "geometry": {"coordinates":[4.693987,52.303398],"type":"Point"}
}