{
  "type": "Feature",
  "properties": {
    "addr:full":"Palmstr 46 Amsterdam North Holland 1015 HS",
    "addr:housenumber":"46",
    "addr:postcode":"1015 hs",
    "addr:street":"Palmstr",
    "iso:country":"NL",
    "sg:address":"Palmstr 46",
    "sg:city":"Amsterdam",
    "sg:orig_category":"Fotografie Reclame En Mode",
    "sg:phone":"+31 20 620 9934",
    "sg:postcode":"1015 HS",
    "sg:province":"North Holland",
    "wof:name":"Sigurd Kranendonk Bv",
    "wof:placetype":"venue"
},
  "geometry": {"coordinates":[4.883906,52.381817],"type":"Point"}
}