{
  "type": "Feature",
  "properties": {
    "addr:full":"Kloosterwg 2 Elsloo Fr Friesland 8424 SH",
    "addr:housenumber":"2",
    "addr:postcode":"8424 sh",
    "addr:street":"Kloosterwg",
    "iso:country":"NL",
    "sg:address":"Kloosterwg 2",
    "sg:city":"Elsloo Fr",
    "sg:orig_category":"Beeldende Kunstenaars",
    "sg:phone":"+31 561 421 637",
    "sg:postcode":"8424 SH",
    "sg:province":"Friesland",
    "wof:name":"Jackie",
    "wof:placetype":"venue"
},
  "geometry": {"coordinates":[6.253785,52.942707],"type":"Point"}
}