{
  "type": "Feature",
  "properties": {
    "addr:full":"Mgr V Leeuwenln 11A Hillegom Zuid-Holland 2182 EM",
    "addr:housenumber":"11a",
    "addr:postcode":"2182 em",
    "addr:street":"Mgr;Leeuwenln",
    "iso:country":"NL",
    "sg:address":"Mgr V Leeuwenln 11A",
    "sg:city":"Hillegom",
    "sg:orig_category":"Kinderopvang",
    "sg:phone":"+31 252 520 165",
    "sg:postcode":"2182 EM",
    "sg:province":"Zuid-Holland",
    "wof:name":"Lawaai Papagaai",
    "wof:placetype":"venue"
},
  "geometry": {"coordinates":[4.578603,52.290993],"type":"Point"}
}