{
  "type": "Feature",
  "properties": {
    "addr:full":"Uilestr 26 Heerlen Limburg 6411 BX",
    "addr:housenumber":"26",
    "addr:postcode":"6411 bx",
    "addr:street":"Uilestr",
    "iso:country":"NL",
    "sg:address":"Uilestr 26",
    "sg:city":"Heerlen",
    "sg:orig_category":"Kabels",
    "sg:phone":"+31 45 571 8090",
    "sg:postcode":"6411 BX",
    "sg:province":"Limburg",
    "wof:name":"Voltec Bv",
    "wof:placetype":"venue"
},
  "geometry": {"coordinates":[5.9759440422,50.8860816956],"type":"Point"}
}