{
  "type": "Feature",
  "properties": {
    "addr:full":"Postbus 18 Rheden Gelderland 6990 AA",
    "addr:housenumber":"18",
    "addr:postcode":"6990 aa",
    "addr:street":"Postbus;Gelderland",
    "iso:country":"NL",
    "sg:address":"Postbus 18",
    "sg:city":"Rheden",
    "sg:orig_category":"Elektrotechnische Installatiebureaus",
    "sg:phone":"+31 26 495 2338",
    "sg:postcode":"6990 AA",
    "sg:province":"Gelderland",
    "wof:name":"Hagen, J A",
    "wof:placetype":"venue"
},
  "geometry": {"coordinates":[6.03264,52.002544],"type":"Point"}
}