{
  "type": "Feature",
  "properties": {
    "iso:country":"NL",
    "sg:address":"Begine 65",
    "sg:city":"Workum",
    "sg:orig_category":"Verenigingen En Stichtingen",
    "sg:phone":"+31 515 543 656",
    "sg:postcode":"8711 BH",
    "sg:province":"Provincie Friesland",
    "wof:name":"Zeilvracht, Ver",
    "wof:placetype":"venue"
},
  "geometry": {"coordinates":[5.446317,52.977989],"type":"Point"}
}