{
  "type": "Feature",
  "properties": {
    "addr:full":"Mastwykstr 28 Tilburg Noord-Brabant 5045 LB",
    "addr:housenumber":"28",
    "addr:postcode":"5045 lb",
    "addr:street":"Mastwykstr",
    "iso:country":"NL",
    "sg:address":"Mastwykstr 28",
    "sg:city":"Tilburg",
    "sg:orig_category":"Woningtextiel - Fabrieken En Groothandel",
    "sg:phone":"+31 13 572 1929",
    "sg:postcode":"5045 LB",
    "sg:province":"Noord-Brabant",
    "wof:name":"Vries, W E De",
    "wof:placetype":"venue"
},
  "geometry": {"coordinates":[4.9930691719,51.5949211121],"type":"Point"}
}