{
  "type": "Feature",
  "properties": {
    "addr:full":"Rozengracht 15D Amsterdam North Holland 1016 LP",
    "addr:housenumber":"15d",
    "addr:postcode":"1016 lp",
    "addr:street":"Rozengracht",
    "iso:country":"NL",
    "sg:address":"Rozengracht 15D",
    "sg:city":"Amsterdam",
    "sg:orig_category":"Meubelzaken, Woning- And Keukeninrichting",
    "sg:phone":"+31 20 624 1614",
    "sg:postcode":"1016 LP",
    "sg:province":"North Holland",
    "wof:name":"Futon Comfort",
    "wof:placetype":"venue"
},
  "geometry": {"coordinates":[4.882347,52.373661],"type":"Point"}
}