{
  "type": "Feature",
  "properties": {
    "addr:full":"Gijsbr. Van Amstelstraat 123 Hilversum Noord-Holland 1214  A",
    "addr:housenumber":"123;1214 a",
    "addr:street":"Van Amstelstraat",
    "iso:country":"NL",
    "sg:address":"Gijsbr. Van Amstelstraat 123",
    "sg:city":"Hilversum",
    "sg:orig_category":"Boekenuitgeverijen",
    "sg:phone":"+31 35 624 7571",
    "sg:postcode":"1214  A",
    "sg:province":"Noord-Holland",
    "wof:name":"Bruna",
    "wof:placetype":"venue"
},
  "geometry": {"coordinates":[5.1695,52.228565],"type":"Point"}
}