{
  "type": "Feature",
  "properties": {
    "iso:country":"NL",
    "sg:address":"Mesdaglaan 3",
    "sg:city":"Doorn",
    "sg:orig_category":"Autokeuringen",
    "sg:phone":"+31 343 421 069",
    "sg:postcode":"3941 CJ",
    "sg:province":"Utrecht",
    "wof:name":"Stip Bv",
    "wof:placetype":"venue"
},
  "geometry": {"coordinates":[5.333907,52.038654],"type":"Point"}
}