{
  "type": "Feature",
  "properties": {
    "addr:full":"Burg. Schonfeldplein 1 Winschoten Groningen 9671 CA",
    "addr:housenumber":"1",
    "addr:postcode":"9671 ca",
    "addr:street":"Burg. Schonfeldplein",
    "iso:country":"NL",
    "sg:address":"Burg. Schonfeldplein 1",
    "sg:city":"Winschoten",
    "sg:classifiers":[
        {
            "category":"Food & Beverages",
            "subcategory":"Fruits & Vegetables",
            "type":"Retail Goods"
        }
    ],
    "sg:phone":"+31 597 421 676",
    "sg:postcode":"9671 CA",
    "sg:province":"Groningen",
    "sg:tags":[
        "groenten"
    ],
    "wof:name":"Lubbers Groente En Fruit",
    "wof:placetype":"venue"
},
  "geometry": {"coordinates":[7.040486,53.142876],"type":"Point"}
}