{
  "type": "Feature",
  "properties": {
    "iso:country":"NL",
    "sg:address":"Davisstr 11",
    "sg:city":"Amsterdam",
    "sg:orig_category":"Homeopathie",
    "sg:phone":"+31 20 772 4388",
    "sg:postcode":"1057 TE",
    "sg:province":"Noord-Holland",
    "sg:website":"http://www.ellenvrins.nl",
    "wof:name":"Ellen Vrins",
    "wof:placetype":"venue"
},
  "geometry": {"coordinates":[4.856854,52.36581],"type":"Point"}
}