{
  "type": "Feature",
  "properties": {
    "iso:country":"NL",
    "sg:address":"Kennemerwg 78",
    "sg:city":"Zandvoort",
    "sg:orig_category":"Golfbanen",
    "sg:phone":"+31 23 571 4974",
    "sg:postcode":"2042 XT",
    "sg:province":"Noord-Holland",
    "wof:name":"Mark & Julia Hatcher Vof",
    "wof:placetype":"venue"
},
  "geometry": {"coordinates":[4.52729,52.370747],"type":"Point"}
}