{
  "type": "Feature",
  "properties": {
    "addr:full":"Heemskerkerwg 256 Beverwyk Noord-Holland 1945 TK",
    "addr:housenumber":"256;1945",
    "addr:postcode":"tk",
    "addr:street":"Beverwyk Noord-Holland",
    "iso:country":"NL",
    "sg:address":"Heemskerkerwg 256",
    "sg:city":"Beverwyk",
    "sg:orig_category":"Adviesbureaus",
    "sg:phone":"+31 251 240 864",
    "sg:postcode":"1945 TK",
    "sg:province":"Noord-Holland",
    "wof:name":"Sunrise Ltd",
    "wof:placetype":"venue"
},
  "geometry": {"coordinates":[4.665528,52.494247],"type":"Point"}
}