{
  "type": "Feature",
  "properties": {
    "addr:full":"Nieuwewg 221 Veenendaal Utrecht 3905 LM",
    "addr:housenumber":"221",
    "addr:postcode":"3905 lm",
    "iso:country":"NL",
    "sg:address":"Nieuwewg 221",
    "sg:city":"Veenendaal",
    "sg:orig_category":"Lpg-Installaties",
    "sg:phone":"+31 318 521 486",
    "sg:postcode":"3905 LM",
    "sg:province":"Utrecht",
    "wof:name":"Braber, R Den",
    "wof:placetype":"venue"
},
  "geometry": {"coordinates":[5.553429,52.037865],"type":"Point"}
}