{
  "type": "Feature",
  "properties": {
    "iso:country":"NL",
    "sg:address":"Weissenbruchstraat 16",
    "sg:city":"Amsterdam",
    "sg:orig_category":"Kappers",
    "sg:phone":"+31 20 615 8570",
    "sg:postcode":"1058 KM",
    "sg:province":"Noord-Holland",
    "wof:name":"Sandra Van Der Valk Coiffures",
    "wof:placetype":"venue"
},
  "geometry": {"coordinates":[4.850766,52.353649],"type":"Point"}
}