{
  "type": "Feature",
  "properties": {
    "addr:full":"Oudenboschstr 36B Wynandsrade Limburg 6363 BV",
    "addr:housenumber":"36b wynandsrade",
    "addr:postcode":"6363 bv",
    "addr:street":"Oudenboschstr",
    "iso:country":"NL",
    "sg:address":"Oudenboschstr 36B",
    "sg:city":"Wynandsrade",
    "sg:orig_category":"Artsen - Huisartsen",
    "sg:phone":"+31 45 524 2397",
    "sg:postcode":"6363 BV",
    "sg:province":"Limburg",
    "wof:name":"Hobus, P P M",
    "wof:placetype":"venue"
},
  "geometry": {"coordinates":[5.881669,50.904236],"type":"Point"}
}