{
  "type": "Feature",
  "properties": {
    "addr:full":"Edisonstr 6 Heerhugowaard Noord-Holland 1704 RL",
    "addr:housenumber":"6",
    "addr:postcode":"1704 rl",
    "addr:street":"Edisonstr",
    "iso:country":"NL",
    "sg:address":"Edisonstr 6",
    "sg:city":"Heerhugowaard",
    "sg:orig_category":"Banden",
    "sg:phone":"+31 72 571 8066",
    "sg:postcode":"1704 RL",
    "sg:province":"Noord-Holland",
    "sg:website":"http://www.euromaster.com",
    "wof:name":"Euromaster",
    "wof:placetype":"venue"
},
  "geometry": {"coordinates":[4.830635,52.676731],"type":"Point"}
}