{
  "type": "Feature",
  "properties": {
    "addr:full":"Jan Campertweg 43 Veenendaal Utrecht 3906 XJ",
    "addr:housenumber":"43",
    "addr:postcode":"3906 xj",
    "addr:street":"Jan Campertweg",
    "iso:country":"NL",
    "sg:address":"Jan Campertweg 43",
    "sg:city":"Veenendaal",
    "sg:orig_category":"Schoonheidssalons",
    "sg:phone":"+31 318 513 983",
    "sg:postcode":"3906 XJ",
    "sg:province":"Utrecht",
    "wof:name":"Akeroyd-Verhagen",
    "wof:placetype":"venue"
},
  "geometry": {"coordinates":[5.522813,52.028503],"type":"Point"}
}