{
  "type": "Feature",
  "properties": {
    "addr:full":"Loosdrechtseweg 5 Hilversum Noord-Holland 1217 TE",
    "addr:housenumber":"5",
    "addr:postcode":"1217 te",
    "addr:street":"Loosdrechtseweg",
    "iso:country":"NL",
    "sg:address":"Loosdrechtseweg 5",
    "sg:city":"Hilversum",
    "sg:classifiers":[
        {
            "category":"Fast Food",
            "type":"Food & Drink"
        }
    ],
    "sg:phone":"+31 35 624 8694",
    "sg:postcode":"1217 TE",
    "sg:province":"Noord-Holland",
    "sg:tags":[
        "afhaal",
        "restaurant"
    ],
    "wof:name":"Hans Snackshop",
    "wof:placetype":"venue"
},
  "geometry": {"coordinates":[5.158245,52.222904],"type":"Point"}
}