{
  "type": "Feature",
  "properties": {
    "addr:full":"J V Beaumontstr 39 Gouda Zuid-Holland 2805 RN",
    "addr:housenumber":"39",
    "addr:postcode":"2805 rn",
    "addr:street":"J;Beaumontstr",
    "iso:country":"NL",
    "sg:address":"J V Beaumontstr 39",
    "sg:city":"Gouda",
    "sg:orig_category":"Accountants - Administratie- Consulenten En -Kantoren",
    "sg:phone":"+31 182 512 316",
    "sg:postcode":"2805 RN",
    "sg:province":"Zuid-Holland",
    "wof:name":"Jongeneel, P",
    "wof:placetype":"venue"
},
  "geometry": {"coordinates":[4.710715,52.010006],"type":"Point"}
}