{
  "type": "Feature",
  "properties": {
    "addr:full":"Gommersstraat 71 Rijsbergen North Brabant 4891 AP",
    "addr:housenumber":"71",
    "addr:postcode":"4891 ap",
    "addr:street":"Gommersstraat",
    "iso:country":"NL",
    "sg:address":"Gommersstraat 71",
    "sg:city":"Rijsbergen",
    "sg:orig_category":"Wegen And Sportterreinen",
    "sg:phone":"+31 76 596 1977",
    "sg:postcode":"4891 AP",
    "sg:province":"North Brabant",
    "wof:name":"J.G. Koevoets",
    "wof:placetype":"venue"
},
  "geometry": {"coordinates":[4.6959481239,51.516330719],"type":"Point"}
}