{
  "type": "Feature",
  "properties": {
    "addr:full":"Prins Hendrikstraat 24 Raamsdonksveer Noord-Brabant 4941 JV",
    "addr:housenumber":"24",
    "addr:postcode":"4941 jv",
    "addr:street":"Prins Hendrikstraat",
    "iso:country":"NL",
    "sg:address":"Prins Hendrikstraat 24",
    "sg:city":"Raamsdonksveer",
    "sg:orig_category":"Kinderopvang Behalve Thuis",
    "sg:phone":"+31 162 520 262",
    "sg:postcode":"4941 JV",
    "sg:province":"Noord-Brabant",
    "wof:name":"Rikkie",
    "wof:placetype":"venue"
},
  "geometry": {"coordinates":[4.875779,51.696701],"type":"Point"}
}