{
  "type": "Feature",
  "properties": {
    "addr:full":"Oranjestr 138 Ridderkerk Zuid-Holland 2983 HW",
    "addr:housenumber":"138",
    "addr:postcode":"2983 hw",
    "iso:country":"NL",
    "sg:address":"Oranjestr 138",
    "sg:city":"Ridderkerk",
    "sg:orig_category":"Fotojournalisten Freelance",
    "sg:phone":"+31 180 415 849",
    "sg:postcode":"2983 HW",
    "sg:province":"Zuid-Holland",
    "wof:name":"Luider, E",
    "wof:placetype":"venue"
},
  "geometry": {"coordinates":[4.604156,51.879711],"type":"Point"}
}