{
  "type": "Feature",
  "properties": {
    "iso:country":"NL",
    "sg:address":"De Sitterlaan 15",
    "sg:city":"Veldhoven",
    "sg:orig_category":"Bedrijfs- And Managementsconsultants",
    "sg:phone":"+31 40 253 5392",
    "sg:postcode":"5505 AA",
    "sg:province":"North Brabant",
    "wof:name":"Semiconductors Bv",
    "wof:placetype":"venue"
},
  "geometry": {"coordinates":[5.3906,51.41341],"type":"Point"}
}