{
  "type": "Feature",
  "properties": {
    "addr:full":"Herenwg 21B Heemstede North Holland 2105 MB",
    "addr:housenumber":"21b",
    "addr:postcode":"2105 mb",
    "addr:street":"Herenwg",
    "iso:country":"NL",
    "sg:address":"Herenwg 21B",
    "sg:city":"Heemstede",
    "sg:orig_category":"Marketingbureaus",
    "sg:phone":"+31 23 584 2062",
    "sg:postcode":"2105 MB",
    "sg:province":"North Holland",
    "wof:name":"Drive Sports",
    "wof:placetype":"venue"
},
  "geometry": {"coordinates":[4.60527,52.339458],"type":"Point"}
}