{
  "type": "Feature",
  "properties": {
    "addr:full":"Noordzijde 96 Noordeloos Zuid-Holland 4225 PL",
    "addr:housenumber":"96",
    "addr:postcode":"4225 pl",
    "addr:street":"Noordzijde",
    "iso:country":"NL",
    "sg:address":"Noordzijde 96",
    "sg:city":"Noordeloos",
    "sg:orig_category":"Wegen And Sportterreinen",
    "sg:phone":"+31 183 581 222",
    "sg:postcode":"4225 PL",
    "sg:province":"Zuid-Holland",
    "wof:name":"Jacob Bikker",
    "wof:placetype":"venue"
},
  "geometry": {"coordinates":[4.9509677887,51.9063796997],"type":"Point"}
}