{
  "type": "Feature",
  "properties": {
    "addr:full":"Hobbemakd 68 Amsterdam Noord-Holland 1071 XM",
    "addr:housenumber":"68",
    "addr:postcode":"1071 xm",
    "addr:street":"Hobbemakd",
    "iso:country":"NL",
    "sg:address":"Hobbemakd 68",
    "sg:city":"Amsterdam",
    "sg:orig_category":"Artiesten/Gezelschappen",
    "sg:phone":"+31 20 662 1588",
    "sg:postcode":"1071 XM",
    "sg:province":"Noord-Holland",
    "wof:name":"Diridas",
    "wof:placetype":"venue"
},
  "geometry": {"coordinates":[4.87701,52.355549],"type":"Point"}
}