{
  "type": "Feature",
  "properties": {
    "iso:country":"NL",
    "sg:address":"Hoefberg 17",
    "sg:city":"Rosmalen",
    "sg:orig_category":"Adviesbureaus Bedrijfsorganisatie",
    "sg:phone":"+31 73 522 3635",
    "sg:postcode":"5242 JA",
    "sg:province":"Noord-Brabant",
    "sg:website":"http://www.fathom.nl",
    "wof:name":"Fathom",
    "wof:placetype":"venue"
},
  "geometry": {"coordinates":[5.371344,51.708649],"type":"Point"}
}