{
  "type": "Feature",
  "properties": {
    "addr:full":"Slichtenhorsterweg 18 Nijkerk Gld Gelderland 3862 NR",
    "addr:housenumber":"18",
    "addr:postcode":"3862",
    "addr:street":"Slichtenhorsterweg;Gld Gelderland;Nr",
    "iso:country":"NL",
    "sg:address":"Slichtenhorsterweg 18",
    "sg:city":"Nijkerk Gld",
    "sg:orig_category":"Granen, Zaden And Diervoeders Gh",
    "sg:phone":"+31 33 245 7675",
    "sg:postcode":"3862 NR",
    "sg:province":"Gelderland",
    "wof:name":"Fa. Van Dijk",
    "wof:placetype":"venue"
},
  "geometry": {"coordinates":[5.491032,52.204987],"type":"Point"}
}