{
  "type": "Feature",
  "properties": {
    "addr:full":"Kerkplein 10 Oisterwijk North Brabant 5061 EB",
    "addr:housenumber":"10",
    "addr:postcode":"5061 eb",
    "addr:street":"Kerkplein",
    "iso:country":"NL",
    "sg:address":"Kerkplein 10",
    "sg:city":"Oisterwijk",
    "sg:orig_category":"Bedrijfs- And Managementsconsultants",
    "sg:phone":"+31 13 521 3578",
    "sg:postcode":"5061 EB",
    "sg:province":"North Brabant",
    "wof:name":"Debossche Bedrijfskunde",
    "wof:placetype":"venue"
},
  "geometry": {"coordinates":[5.1836352348,51.5780677795],"type":"Point"}
}