{
  "type": "Feature",
  "properties": {
    "addr:full":"Oostindischewyk 4 Zevenhuizen Gn Provincie Drenthe 9354 TS",
    "addr:housenumber":"4",
    "addr:postcode":"gn;9354 ts",
    "addr:street":"Oostindischewyk",
    "iso:country":"NL",
    "sg:address":"Oostindischewyk 4",
    "sg:city":"Zevenhuizen Gn",
    "sg:orig_category":"Horecabenodigdheden",
    "sg:phone":"+31 594 631 592",
    "sg:postcode":"9354 TS",
    "sg:province":"Provincie Drenthe",
    "wof:name":"Osu",
    "wof:placetype":"venue"
},
  "geometry": {"coordinates":[6.374018,53.138515],"type":"Point"}
}