{
  "type": "Feature",
  "properties": {
    "addr:full":"Camplaan 22 Heemstede Noord-Holland 2103 GW",
    "addr:housenumber":"22",
    "addr:postcode":"2103 gw",
    "addr:street":"Camplaan",
    "iso:country":"NL",
    "sg:address":"Camplaan 22",
    "sg:city":"Heemstede",
    "sg:orig_category":"Verpakkingsmachines Fab",
    "sg:phone":"+31 23 529 0240",
    "sg:postcode":"2103 GW",
    "sg:province":"Noord-Holland",
    "wof:name":"Technisch Bureau Verduyn Bv",
    "wof:placetype":"venue"
},
  "geometry": {"coordinates":[4.622998,52.34483],"type":"Point"}
}