{
  "type": "Feature",
  "properties": {
    "addr:full":"Touwslagersdreef 63 Tholen Zeeland 4691 LW",
    "addr:housenumber":"63",
    "addr:postcode":"4691 lw",
    "addr:street":"Touwslagersdreef",
    "iso:country":"NL",
    "sg:address":"Touwslagersdreef 63",
    "sg:city":"Tholen",
    "sg:orig_category":"Autorijscholen",
    "sg:phone":"+31 166 602 008",
    "sg:postcode":"4691 LW",
    "sg:province":"Zeeland",
    "wof:name":"Eureka",
    "wof:placetype":"venue"
},
  "geometry": {"coordinates":[4.214532,51.526867],"type":"Point"}
}