{
  "type": "Feature",
  "properties": {
    "addr:full":"1E Nieuwstr 48 Hilversum North Holland 1211 JS",
    "addr:housenumber":"48",
    "addr:postcode":"1211 js",
    "addr:street":"1E Nieuwstr",
    "iso:country":"NL",
    "sg:address":"1E Nieuwstr 48",
    "sg:city":"Hilversum",
    "sg:orig_category":"Kantoor- En Secretariaatsservice",
    "sg:phone":"+31 35 624 3278",
    "sg:postcode":"1211 JS",
    "sg:province":"North Holland",
    "wof:name":"Voogd",
    "wof:placetype":"venue"
},
  "geometry": {"coordinates":[5.1659460068,52.2217330933],"type":"Point"}
}