{
  "type": "Feature",
  "properties": {
    "addr:full":"Patrijzenweg 6 Oud Vossemeer Zeeland 4698 AB",
    "addr:housenumber":"6",
    "addr:postcode":"4698 ab",
    "addr:street":"Patrijzenweg",
    "iso:country":"NL",
    "sg:address":"Patrijzenweg 6",
    "sg:city":"Oud Vossemeer",
    "sg:orig_category":"Boekhouders",
    "sg:phone":"+31 166 677 010",
    "sg:postcode":"4698 AB",
    "sg:province":"Zeeland",
    "wof:name":"Boekhoudkantoor Bahnerth",
    "wof:placetype":"venue"
},
  "geometry": {"coordinates":[4.195764,51.571583],"type":"Point"}
}