{
  "type": "Feature",
  "properties": {
    "addr:full":"Hooggoorns 14 Emmen Provincie Drenthe 7812 AM",
    "addr:housenumber":"14;7812",
    "addr:street":"Hooggoorns;Provincie Drenthe",
    "iso:country":"NL",
    "sg:address":"Hooggoorns 14",
    "sg:city":"Emmen",
    "sg:orig_category":"Notarissen",
    "sg:phone":"+31 591 640 000",
    "sg:postcode":"7812 AM",
    "sg:province":"Provincie Drenthe",
    "wof:name":"Notariaat 'T Suydevelt",
    "wof:placetype":"venue"
},
  "geometry": {"coordinates":[6.891485,52.77607],"type":"Point"}
}