{
  "type": "Feature",
  "properties": {
    "addr:full":"Utrechtsedwarsstraat 61 Amsterdam North Holland 1017 WC",
    "addr:housenumber":"61",
    "addr:postcode":"1017 wc",
    "addr:street":"Utrechtsedwarsstraat",
    "iso:country":"NL",
    "sg:address":"Utrechtsedwarsstraat 61",
    "sg:city":"Amsterdam",
    "sg:orig_category":"Boekhouders",
    "sg:phone":"+31 20 626 4320",
    "sg:postcode":"1017 WC",
    "sg:province":"North Holland",
    "wof:name":"Van Der Heijden & Partners",
    "wof:placetype":"venue"
},
  "geometry": {"coordinates":[4.898559,52.361519],"type":"Point"}
}