{
  "type": "Feature",
  "properties": {
    "addr:full":"Bijlmermeerstraat 10 Hoofddorp North Holland 2131 HG",
    "addr:housenumber":"10",
    "addr:postcode":"2131 hg",
    "addr:street":"Bijlmermeerstraat",
    "iso:country":"NL",
    "sg:address":"Bijlmermeerstraat 10",
    "sg:city":"Hoofddorp",
    "sg:orig_category":"Public Relationbureaus",
    "sg:phone":"+31 23 561 6265",
    "sg:postcode":"2131 HG",
    "sg:province":"North Holland",
    "wof:name":"O & K Communications",
    "wof:placetype":"venue"
},
  "geometry": {"coordinates":[4.688809,52.31665],"type":"Point"}
}