{
  "type": "Feature",
  "properties": {
    "addr:full":"Pijnackerplein 21 Rotterdam Zuid-Holland 3035 GC",
    "addr:housenumber":"21",
    "addr:postcode":"3035 gc",
    "addr:street":"Pijnackerplein",
    "iso:country":"NL",
    "sg:address":"Pijnackerplein 21",
    "sg:city":"Rotterdam",
    "sg:orig_category":"Autokeuringen",
    "sg:phone":"+31 10 465 6927",
    "sg:postcode":"3035 GC",
    "sg:province":"Zuid-Holland",
    "wof:name":"Quickservice Noord Rotterdam Q.N.R. Vof",
    "wof:placetype":"venue"
},
  "geometry": {"coordinates":[4.480952,51.934166],"type":"Point"}
}