{
  "type": "Feature",
  "properties": {
    "addr:full":"Dolmansstr 4 Maastricht Limburg 6222 EC",
    "addr:housenumber":"4",
    "addr:postcode":"6222 ec",
    "addr:street":"Dolmansstr",
    "iso:country":"NL",
    "sg:address":"Dolmansstr 4",
    "sg:city":"Maastricht",
    "sg:orig_category":"Peuterspeelzalen",
    "sg:phone":"+31 43 363 1969",
    "sg:postcode":"6222 EC",
    "sg:province":"Limburg",
    "wof:name":"Grummelkes, De",
    "wof:placetype":"venue"
},
  "geometry": {"coordinates":[5.705612,50.865746],"type":"Point"}
}