{
  "type": "Feature",
  "properties": {
    "addr:full":"Loosduinsewg 745 S Gravenhage Zuid-Holland 2571 AN",
    "addr:housenumber":"745;gravenhage",
    "addr:postcode":"2571 an",
    "addr:street":"S",
    "iso:country":"NL",
    "sg:address":"Loosduinsewg 745",
    "sg:city":"S Gravenhage",
    "sg:orig_category":"Glas",
    "sg:phone":"+31 70 364 7465",
    "sg:postcode":"2571 AN",
    "sg:province":"Zuid-Holland",
    "wof:name":"Zuiderpark Glashandel",
    "wof:placetype":"venue"
},
  "geometry": {"coordinates":[4.29037,52.06884],"type":"Point"}
}