{
  "type": "Feature",
  "properties": {
    "iso:country":"NL",
    "sg:address":"Purmerpln 30",
    "sg:city":"Amsterdam",
    "sg:orig_category":"Kunstgebitten",
    "sg:phone":"+31 20 636 0193",
    "sg:postcode":"1023 BD",
    "sg:province":"Noord-Holland",
    "wof:name":"Verkerk, Tandprothetische Praktijk",
    "wof:placetype":"venue"
},
  "geometry": {"coordinates":[4.944405,52.390518],"type":"Point"}
}