{
  "type": "Feature",
  "properties": {
    "iso:country":"NL",
    "sg:address":"Burgemeester Cortenstr 162",
    "sg:city":"Maastricht",
    "sg:orig_category":"Medische And Orthopedische Artikelen",
    "sg:phone":"+31 43 363 6711",
    "sg:postcode":"6226 GX",
    "sg:province":"Limburg",
    "wof:name":"Q-Medical",
    "wof:placetype":"venue"
},
  "geometry": {"coordinates":[5.728204,50.85043],"type":"Point"}
}