{
  "type": "Feature",
  "properties": {
    "addr:full":"Burgemeester Cortenstr 162 Maastricht Limburg 6226 GX",
    "addr:housenumber":"162",
    "addr:postcode":"6226 gx",
    "addr:street":"Burgemeester Cortenstr",
    "iso:country":"NL",
    "sg:address":"Burgemeester Cortenstr 162",
    "sg:city":"Maastricht",
    "sg:orig_category":"Medische And Orthopedische Artikelen",
    "sg:phone":"+31 43 363 6711",
    "sg:postcode":"6226 GX",
    "sg:province":"Limburg",
    "wof:name":"Q-Medical",
    "wof:placetype":"venue"
},
  "geometry": {"coordinates":[5.728204,50.85043],"type":"Point"}
}