{
  "type": "Feature",
  "properties": {
    "addr:full":"Molenstr 12 Oudenbosch North Brabant 4731 HE",
    "addr:housenumber":"12",
    "addr:postcode":"4731 he",
    "addr:street":"Molenstr",
    "iso:country":"NL",
    "sg:address":"Molenstr 12",
    "sg:city":"Oudenbosch",
    "sg:orig_category":"Kinderkleding",
    "sg:phone":"+31 165 314 174",
    "sg:postcode":"4731 HE",
    "sg:province":"North Brabant",
    "wof:name":"Veertje, 'T",
    "wof:placetype":"venue"
},
  "geometry": {"coordinates":[4.523808,51.588421],"type":"Point"}
}