{
  "type": "Feature",
  "properties": {
    "iso:country":"NL",
    "sg:address":"Molenstr 12",
    "sg:city":"Oudenbosch",
    "sg:orig_category":"Kinderkleding",
    "sg:phone":"+31 165 314 174",
    "sg:postcode":"4731 HE",
    "sg:province":"North Brabant",
    "wof:name":"Veertje, 'T",
    "wof:placetype":"venue"
},
  "geometry": {"coordinates":[4.523808,51.588421],"type":"Point"}
}