{
  "type": "Feature",
  "properties": {
    "addr:full":"V Echtenstr 14 Hoogeveen Drenthe 7902 EN",
    "addr:housenumber":"14",
    "addr:postcode":"7902 en",
    "iso:country":"NL",
    "sg:address":"V Echtenstr 14",
    "sg:city":"Hoogeveen",
    "sg:orig_category":"Kappers",
    "sg:phone":"+31 528 230 694",
    "sg:postcode":"7902 EN",
    "sg:province":"Drenthe",
    "wof:name":"New Image",
    "wof:placetype":"venue"
},
  "geometry": {"coordinates":[6.47552,52.725975],"type":"Point"}
}