{
  "type": "Feature",
  "properties": {
    "addr:full":"Factory 10D Zwaag (Hoorn) Noord-Holland 1689 AL",
    "addr:housenumber":"10d",
    "addr:postcode":"1689 al",
    "addr:street":"Factory",
    "iso:country":"NL",
    "sg:address":"Factory 10D",
    "sg:city":"Zwaag (Hoorn)",
    "sg:orig_category":"Matrassen Fab",
    "sg:phone":"+31 229 241 307",
    "sg:postcode":"1689 AL",
    "sg:province":"Noord-Holland",
    "sg:website":"http://www.vitalbedden.nl",
    "wof:name":"Vital-Matrassen-Bedden",
    "wof:placetype":"venue"
},
  "geometry": {"coordinates":[5.065337,52.667259],"type":"Point"}
}