{
  "type": "Feature",
  "properties": {
    "addr:full":"R Dieselwg 40 Venlo Limburg 5928 RA",
    "addr:housenumber":"40",
    "addr:postcode":"5928 ra",
    "iso:country":"NL",
    "sg:address":"R Dieselwg 40",
    "sg:city":"Venlo",
    "sg:orig_category":"Automaterialen En Gereedschappen",
    "sg:phone":"+31 77 382 3792",
    "sg:postcode":"5928 RA",
    "sg:province":"Limburg",
    "wof:name":"Technische Centrale Bv",
    "wof:placetype":"venue"
},
  "geometry": {"coordinates":[6.161696,51.378582],"type":"Point"}
}