{
  "type": "Feature",
  "properties": {
    "addr:full":"Beekpad 1 Rysbergen North Brabant 4891 SB",
    "addr:housenumber":"1",
    "addr:postcode":"4891 sb",
    "addr:street":"Beekpad",
    "iso:country":"NL",
    "sg:address":"Beekpad 1",
    "sg:city":"Rysbergen",
    "sg:orig_category":"Onroerende Goederen",
    "sg:phone":"+31 76 596 3091",
    "sg:postcode":"4891 SB",
    "sg:province":"North Brabant",
    "wof:name":"Roovers, A J M",
    "wof:placetype":"venue"
},
  "geometry": {"coordinates":[4.7105,51.518887],"type":"Point"}
}