{
  "type": "Feature",
  "properties": {
    "addr:full":"Groenestraat 170 Nijmegen Gelderland 6531 HW",
    "addr:housenumber":"170",
    "addr:postcode":"6531 hw",
    "addr:street":"Groenestraat;Gelderland",
    "iso:country":"NL",
    "sg:address":"Groenestraat 170",
    "sg:city":"Nijmegen",
    "sg:orig_category":"Overheidsdiensten",
    "sg:phone":"+31 24 354 0919",
    "sg:postcode":"6531 HW",
    "sg:province":"Gelderland",
    "wof:name":"De Haard",
    "wof:placetype":"venue"
},
  "geometry": {"coordinates":[5.8521261215,51.8310089111],"type":"Point"}
}