{
  "type": "Feature",
  "properties": {
    "iso:country":"NL",
    "sg:address":"Kleingouw 180",
    "sg:city":"Andijk",
    "sg:orig_category":"Artistiek Onderwijs",
    "sg:phone":"+31 228 593 904",
    "sg:postcode":"1619 CJ",
    "sg:province":"Noord-Holland",
    "wof:name":"W. Broer",
    "wof:placetype":"venue"
},
  "geometry": {"coordinates":[5.183354,52.738239],"type":"Point"}
}