{
  "type": "Feature",
  "properties": {
    "iso:country":"NL",
    "sg:address":"Ulriksholm 21",
    "sg:city":"Hoofddorp",
    "sg:orig_category":"Grafisch Ontwerpers",
    "sg:phone":"+31 23 561 5621",
    "sg:postcode":"2133 HX",
    "sg:province":"Noord-Holland",
    "sg:website":"http://www.jeroensikkema.nl",
    "wof:name":"Jeroen Sikkema, Ontwerpbureau",
    "wof:placetype":"venue"
},
  "geometry": {"coordinates":[4.67168,52.31432],"type":"Point"}
}