{
  "type": "Feature",
  "properties": {
    "iso:country":"NL",
    "sg:address":"Reitscheweg 36",
    "sg:city":"'S Hertogenbosch",
    "sg:orig_category":"Meubelzaken, Woning- And Keukeninrichting",
    "sg:phone":"+31 73 642 5210",
    "sg:postcode":"5232 BZ",
    "sg:province":"North Brabant",
    "wof:name":"Het Meubelhuis Heijmans Soetelieve Bv",
    "wof:placetype":"venue"
},
  "geometry": {"coordinates":[5.338081,51.709778],"type":"Point"}
}