{
  "type": "Feature",
  "properties": {
    "iso:country":"NL",
    "sg:address":"Koekoekstr 49",
    "sg:city":"Utrecht",
    "sg:orig_category":"Zonweringen",
    "sg:phone":"+31 30 271 7762",
    "sg:postcode":"3514 CT",
    "sg:province":"Utrecht",
    "wof:name":"Brinkers Tapijten",
    "wof:placetype":"venue"
},
  "geometry": {"coordinates":[5.11945,52.098934],"type":"Point"}
}