{
  "type": "Feature",
  "properties": {
    "iso:country":"NL",
    "sg:address":"Heieinde 12",
    "sg:city":"Tilburg",
    "sg:orig_category":"Huishoudelijk Textiel Fab",
    "sg:phone":"+31 13 571 0330",
    "sg:postcode":"5047 SX",
    "sg:province":"Noord-Brabant",
    "wof:name":"Am Design Raamdekoratie Bv",
    "wof:placetype":"venue"
},
  "geometry": {"coordinates":[5.010352,51.595093],"type":"Point"}
}