{
  "type": "Feature",
  "properties": {
    "addr:full":"Arnestr 16 Arnemuiden Zeeland 4341 CL",
    "addr:housenumber":"16",
    "addr:postcode":"4341",
    "addr:street":"Arnestr",
    "iso:country":"NL",
    "sg:address":"Arnestr 16",
    "sg:city":"Arnemuiden",
    "sg:orig_category":"Loodgieters",
    "sg:phone":"+31 118 603 781",
    "sg:postcode":"4341 CL",
    "sg:province":"Zeeland",
    "wof:name":"Walhout, Installatiebedrijf",
    "wof:placetype":"venue"
},
  "geometry": {"coordinates":[3.67447,51.499187],"type":"Point"}
}