{
  "type": "Feature",
  "properties": {
    "iso:country":"NL",
    "sg:address":"De Oude Wereld 76",
    "sg:city":"Alphen A/D Rijn",
    "sg:classifiers":[
        {
            "category":"Fast Food",
            "type":"Food & Drink"
        }
    ],
    "sg:phone":"+31 172 493 469",
    "sg:postcode":"2408 JV",
    "sg:province":"Zuid-Holland",
    "sg:tags":[
        "afhaal",
        "restaurant"
    ],
    "wof:name":"K.B. Ngo",
    "wof:placetype":"venue"
},
  "geometry": {"coordinates":[4.649256,52.119228],"type":"Point"}
}