{
  "type": "Feature",
  "properties": {
    "addr:full":"L Jansenpln 6 Amsterdam Noord-Holland 1063 GX",
    "addr:housenumber":"6",
    "addr:postcode":"1063 gx",
    "iso:country":"NL",
    "sg:address":"L Jansenpln 6",
    "sg:city":"Amsterdam",
    "sg:orig_category":"Webdesign Bureaus",
    "sg:phone":"+31 6 18676845",
    "sg:postcode":"1063 GX",
    "sg:province":"Noord-Holland",
    "wof:name":"Limmo",
    "wof:placetype":"venue"
},
  "geometry": {"coordinates":[4.8205680847,52.3840866089],"type":"Point"}
}