{
  "type": "Feature",
  "properties": {
    "addr:full":"K Schaft 3 Houten Utrecht 3991 AT",
    "addr:housenumber":"3",
    "addr:postcode":"3991",
    "addr:street":"K Schaft",
    "iso:country":"NL",
    "sg:address":"K Schaft 3",
    "sg:city":"Houten",
    "sg:orig_category":"Drukkerijen",
    "sg:phone":"+31 30 637 8179",
    "sg:postcode":"3991 AT",
    "sg:province":"Utrecht",
    "wof:name":"Dur & De Jonge, Drukkerij",
    "wof:placetype":"venue"
},
  "geometry": {"coordinates":[5.172226,52.021912],"type":"Point"}
}