{
  "type": "Feature",
  "properties": {
    "addr:full":"Korvelseweg 219 Tilburg Noord-Brabant 5025 JG",
    "addr:housenumber":"219",
    "addr:postcode":"5025 jg",
    "addr:street":"Korvelseweg",
    "iso:country":"NL",
    "sg:address":"Korvelseweg 219",
    "sg:city":"Tilburg",
    "sg:classifiers":[
        {
            "category":"Communications",
            "subcategory":"Television Station",
            "type":"Services"
        }
    ],
    "sg:phone":"+31 13 535 7181",
    "sg:postcode":"5025 JG",
    "sg:province":"Noord-Brabant",
    "sg:tags":[
        "video",
        "audio",
        "verhuur"
    ],
    "wof:name":"Jumbo Videotheek",
    "wof:placetype":"venue"
},
  "geometry": {"coordinates":[5.071041,51.550552],"type":"Point"}
}