{
  "type": "Feature",
  "properties": {
    "addr:full":"Renswoudsestrwg 59 Lunteren Gelderland 6741 ME",
    "addr:housenumber":"59",
    "addr:postcode":"6741 me",
    "addr:street":"Renswoudsestrwg;Gelderland",
    "iso:country":"NL",
    "sg:address":"Renswoudsestrwg 59",
    "sg:city":"Lunteren",
    "sg:orig_category":"Land- En Tuinbouw - Loonbedrijven",
    "sg:phone":"+31 342 421 701",
    "sg:postcode":"6741 ME",
    "sg:province":"Gelderland",
    "wof:name":"Geresteijn, H Van",
    "wof:placetype":"venue"
},
  "geometry": {"coordinates":[5.550465,52.108631],"type":"Point"}
}