{
  "type": "Feature",
  "properties": {
    "addr:full":"Olympisch Stadion 40 Amsterdam Noord-Holland 1076 DE",
    "addr:housenumber":"40;1076",
    "addr:postcode":"de",
    "addr:street":"Olympisch Stadion",
    "iso:country":"NL",
    "sg:address":"Olympisch Stadion 40",
    "sg:city":"Amsterdam",
    "sg:orig_category":"Sportaccommodaties - Aanleg En Onderhoud",
    "sg:phone":"+31 20 672 0203",
    "sg:postcode":"1076 DE",
    "sg:province":"Noord-Holland",
    "wof:name":"Burggolf Bv",
    "wof:placetype":"venue"
},
  "geometry": {"coordinates":[4.855258,52.344318],"type":"Point"}
}