{
  "type": "Feature",
  "properties": {
    "addr:full":"Boswg 20 Scheemda Groningen 9679 TR",
    "addr:housenumber":"20",
    "addr:postcode":"9679 tr",
    "addr:street":"Boswg",
    "iso:country":"NL",
    "sg:address":"Boswg 20",
    "sg:city":"Scheemda",
    "sg:orig_category":"Wasmachines En Wasdrogers - Onderhoud En Reparatie",
    "sg:phone":"+31 597 592 472",
    "sg:postcode":"9679 TR",
    "sg:province":"Groningen",
    "wof:name":"Twikler, J",
    "wof:placetype":"venue"
},
  "geometry": {"coordinates":[6.9911370277,53.1736907959],"type":"Point"}
}