{
  "type": "Feature",
  "properties": {
    "addr:full":"De Vlinderhoven 136 Schiedam South Holland 3124 BV",
    "addr:housenumber":"136",
    "addr:postcode":"3124 bv",
    "addr:street":"De Vlinderhoven",
    "iso:country":"NL",
    "sg:address":"De Vlinderhoven 136",
    "sg:city":"Schiedam",
    "sg:classifiers":[
        {
            "category":"Personal",
            "subcategory":"Nail Salon",
            "type":"Services"
        }
    ],
    "sg:phone":"+31 10 471 3988",
    "sg:postcode":"3124 BV",
    "sg:province":"South Holland",
    "sg:tags":[
        "pedicure"
    ],
    "wof:name":"Verspeek-Post, M W J",
    "wof:placetype":"venue"
},
  "geometry": {"coordinates":[4.382504,51.940735],"type":"Point"}
}