{
  "type": "Feature",
  "properties": {
    "iso:country":"NL",
    "sg:address":"Marslaan 145",
    "sg:city":"Nieuw Lekkerland",
    "sg:orig_category":"Kappers",
    "sg:phone":"+31 184 683 470",
    "sg:postcode":"2957 SG",
    "sg:province":"Zuid-Holland",
    "wof:name":"Haarstudio 145",
    "wof:placetype":"venue"
},
  "geometry": {"coordinates":[4.6715331078,51.8865242004],"type":"Point"}
}