{
  "type": "Feature",
  "properties": {
    "iso:country":"NL",
    "sg:address":"Kaapwg 4",
    "sg:city":"Meppel",
    "sg:orig_category":"Scheepswerven",
    "sg:phone":"+31 522 270 013",
    "sg:postcode":"7944 HV",
    "sg:province":"Drenthe",
    "wof:name":"Kaap Bv, De",
    "wof:placetype":"venue"
},
  "geometry": {"coordinates":[6.179079,52.694729],"type":"Point"}
}