{
  "type": "Feature",
  "properties": {
    "addr:full":"Obrechtsingel 1 Vught North Brabant 5262 HZ",
    "addr:housenumber":"1",
    "addr:postcode":"5262 hz",
    "addr:street":"Obrechtsingel",
    "iso:country":"NL",
    "sg:address":"Obrechtsingel 1",
    "sg:city":"Vught",
    "sg:orig_category":"Kantoorapparatuur Gh",
    "sg:phone":"+31 73 656 3844",
    "sg:postcode":"5262 HZ",
    "sg:province":"North Brabant",
    "wof:name":"Ton Hoven Kantoortechniek",
    "wof:placetype":"venue"
},
  "geometry": {"coordinates":[5.2860188484,51.6423568726],"type":"Point"}
}