{
  "type": "Feature",
  "properties": {
    "iso:country":"NL",
    "sg:address":"Wiepke Hofstraat 5",
    "sg:city":"Lemmer",
    "sg:orig_category":"Werving And Selectie Van Vast Personeel",
    "sg:phone":"+31 514 561 478",
    "sg:postcode":"8531 GJ",
    "sg:province":"Provincie Friesland",
    "wof:name":"Arbeidsbureau Lemmer",
    "wof:placetype":"venue"
},
  "geometry": {"coordinates":[5.7142062187,52.8454551697],"type":"Point"}
}