{
  "type": "Feature",
  "properties": {
    "addr:full":"Twentewg 16 Enschede Overijssel 7532 ST",
    "addr:housenumber":"16",
    "addr:postcode":"7532 st",
    "addr:street":"Twentewg",
    "iso:country":"NL",
    "sg:address":"Twentewg 16",
    "sg:city":"Enschede",
    "sg:orig_category":"Metaaldraaierijen",
    "sg:phone":"+31 53 461 1148",
    "sg:postcode":"7532 ST",
    "sg:province":"Overijssel",
    "wof:name":"Wieco Metaaldraaierij & Slijperij Bv",
    "wof:placetype":"venue"
},
  "geometry": {"coordinates":[6.946661,52.223618],"type":"Point"}
}