{
  "type": "Feature",
  "properties": {
    "addr:full":"Sperwerln 229 Vlaardingen South Holland 3136 GE",
    "addr:housenumber":"229",
    "addr:postcode":"3136",
    "iso:country":"NL",
    "sg:address":"Sperwerln 229",
    "sg:city":"Vlaardingen",
    "sg:orig_category":"Voetbalverenigingen",
    "sg:phone":"+31 10 474 9927",
    "sg:postcode":"3136 GE",
    "sg:province":"South Holland",
    "wof:name":"Hvo",
    "wof:placetype":"venue"
},
  "geometry": {"coordinates":[4.340359,51.910442],"type":"Point"}
}