{
  "type": "Feature",
  "properties": {
    "addr:full":"Kedoestraat 102 Rotterdam South Holland 3029 CK",
    "addr:housenumber":"102",
    "addr:postcode":"3029 ck",
    "addr:street":"Kedoestraat",
    "iso:country":"NL",
    "sg:address":"Kedoestraat 102",
    "sg:city":"Rotterdam",
    "sg:classifiers":[
        {
            "category":"Education",
            "subcategory":"Preschool",
            "type":"Public Place"
        }
    ],
    "sg:phone":"+31 10 478 0808",
    "sg:postcode":"3029 CK",
    "sg:province":"South Holland",
    "sg:tags":[
        "kleuteronderwijs",
        "basis-"
    ],
    "wof:name":"Openbare Basisschool De Boog",
    "wof:placetype":"venue"
},
  "geometry": {"coordinates":[4.441423,51.903873],"type":"Point"}
}