{
  "type": "Feature",
  "properties": {
    "iso:country":"NL",
    "sg:address":"Hertogensngl 87",
    "sg:city":"Oss",
    "sg:classifiers":[
        {
            "category":"Retail",
            "subcategory":"Auto Repair",
            "type":"Services"
        }
    ],
    "sg:phone":"+31 412 623 555",
    "sg:postcode":"5341 AC",
    "sg:province":"Noord-Brabant",
    "sg:tags":[
        "garage"
    ],
    "sg:website":"http://www.vosautobedrijven.nl",
    "wof:name":"Vos, Gebr",
    "wof:placetype":"venue"
},
  "geometry": {"coordinates":[-77.235214,38.312599],"type":"Point"}
}