{
  "type": "Feature",
  "properties": {
    "addr:full":"Saskiadonk 11 Roosendaal Noord-Brabant 4707 WZ",
    "addr:housenumber":"11",
    "addr:postcode":"4707 wz",
    "addr:street":"Saskiadonk",
    "iso:country":"NL",
    "sg:address":"Saskiadonk 11",
    "sg:city":"Roosendaal",
    "sg:orig_category":"Voegwerken",
    "sg:phone":"+31 165 532 720",
    "sg:postcode":"4707 WZ",
    "sg:province":"Noord-Brabant",
    "wof:name":"Hopstaken Voegbedrijf, J",
    "wof:placetype":"venue"
},
  "geometry": {"coordinates":[4.469953,51.518696],"type":"Point"}
}