{
  "type": "Feature",
  "properties": {
    "addr:full":"Karel Doormanstraat 1 Rozenburg Zh Zuid-Holland 3181 VB",
    "addr:housenumber":"1",
    "addr:postcode":"zh;3181 vb",
    "addr:street":"Karel Doormanstraat",
    "iso:country":"NL",
    "sg:address":"Karel Doormanstraat 1",
    "sg:city":"Rozenburg Zh",
    "sg:orig_category":"Autokeuringen",
    "sg:phone":"+31 181 216 400",
    "sg:postcode":"3181 VB",
    "sg:province":"Zuid-Holland",
    "wof:name":"Servicestation D.C. Berkel Rozenburg Bv",
    "wof:placetype":"venue"
},
  "geometry": {"coordinates":[4.242881,51.905815],"type":"Point"}
}