{
  "type": "Feature",
  "properties": {
    "iso:country":"NL",
    "sg:address":"Luikerweg 19",
    "sg:city":"Maastricht",
    "sg:orig_category":"Kappers",
    "sg:phone":"+31 43 321 9065",
    "sg:postcode":"6212 ET",
    "sg:province":"Limburg",
    "wof:name":"Kapsalon L. Schwiebert",
    "wof:placetype":"venue"
},
  "geometry": {"coordinates":[5.687526226,50.8396263123],"type":"Point"}
}