{
  "type": "Feature",
  "properties": {
    "addr:full":"Pinxtenstraat 7 Haler Limburg 6012 RJ",
    "addr:housenumber":"7",
    "addr:postcode":"6012 rj",
    "addr:street":"Pinxtenstraat",
    "iso:country":"NL",
    "sg:address":"Pinxtenstraat 7",
    "sg:city":"Haler",
    "sg:orig_category":"Verzekeringen",
    "sg:phone":"+31 495 551 257",
    "sg:postcode":"6012 RJ",
    "sg:province":"Limburg",
    "wof:name":"H.H. Verheijden-Wolters",
    "wof:placetype":"venue"
},
  "geometry": {"coordinates":[5.778625,51.18858],"type":"Point"}
}