{
  "type": "Feature",
  "properties": {
    "iso:country":"NL",
    "sg:address":"Wagenwg 64",
    "sg:city":"Haarlem",
    "sg:orig_category":"Adviesbureaus Bedrijfsorganisatie",
    "sg:phone":"+31 23 532 9443",
    "sg:postcode":"2012 NG",
    "sg:province":"Noord-Holland",
    "wof:name":"Ruijter Bv, De",
    "wof:placetype":"venue"
},
  "geometry": {"coordinates":[4.625795,52.372707],"type":"Point"}
}