{
  "type": "Feature",
  "properties": {
    "iso:country":"NL",
    "sg:address":"Bastion 107",
    "sg:city":"Lelystad",
    "sg:orig_category":"Administratie- En Boekhoudkantoren",
    "sg:phone":"+31 320 246 531",
    "sg:postcode":"8223 GL",
    "sg:province":"Flevoland",
    "wof:name":"Frie Mind",
    "wof:placetype":"venue"
},
  "geometry": {"coordinates":[5.479938,52.519203],"type":"Point"}
}