{
  "type": "Feature",
  "properties": {
    "addr:full":"J Israelskd 412 Amsterdam Noord-Holland 1074 SR",
    "addr:housenumber":"412;1074",
    "addr:postcode":"sr",
    "iso:country":"NL",
    "sg:address":"J Israelskd 412",
    "sg:city":"Amsterdam",
    "sg:orig_category":"Loodgieters",
    "sg:phone":"+31 20 662 9132",
    "sg:postcode":"1074 SR",
    "sg:province":"Noord-Holland",
    "wof:name":"Borghols Bv",
    "wof:placetype":"venue"
},
  "geometry": {"coordinates":[4.90664,52.349697],"type":"Point"}
}