{
  "type": "Feature",
  "properties": {
    "addr:full":"Industrieweg 175 Rotterdam Zuid-Holland 3044 AS",
    "addr:housenumber":"175",
    "addr:postcode":"3044 as",
    "addr:street":"Industrieweg",
    "iso:country":"NL",
    "sg:address":"Industrieweg 175",
    "sg:city":"Rotterdam",
    "sg:orig_category":"Diverse Bedrijfsinstallaties Gh",
    "sg:phone":"+31 10 446 3700",
    "sg:postcode":"3044 AS",
    "sg:province":"Zuid-Holland",
    "wof:name":"Vector Aandrijftechniek Bv",
    "wof:placetype":"venue"
},
  "geometry": {"coordinates":[4.42634,51.923122],"type":"Point"}
}