{
  "type": "Feature",
  "properties": {
    "addr:full":"Diamantstr 1 Breda Noord-Brabant 4817 HT",
    "addr:housenumber":"1",
    "addr:postcode":"4817 ht",
    "addr:street":"Diamantstr",
    "iso:country":"NL",
    "sg:address":"Diamantstr 1",
    "sg:city":"Breda",
    "sg:orig_category":"Horeca-Inrichtingen En -Uitrustingen",
    "sg:phone":"+31 76 521 5132",
    "sg:postcode":"4817 HT",
    "sg:province":"Noord-Brabant",
    "wof:name":"Migchielsen, A M J",
    "wof:placetype":"venue"
},
  "geometry": {"coordinates":[4.79831,51.588234],"type":"Point"}
}