{
  "type": "Feature",
  "properties": {
    "addr:full":"Lekdijk West 78 Lopik Utrecht 3411 MZ",
    "addr:housenumber":"78",
    "addr:postcode":"3411 mz",
    "addr:street":"Lekdijk West",
    "iso:country":"NL",
    "sg:address":"Lekdijk West 78",
    "sg:city":"Lopik",
    "sg:orig_category":"Geluidsinstallaties - Accessoires En Onderdelen",
    "sg:phone":"+31 182 383 332",
    "sg:postcode":"3411 MZ",
    "sg:province":"Utrecht",
    "wof:name":"Itc",
    "wof:placetype":"venue"
},
  "geometry": {"coordinates":[4.878217,51.941185],"type":"Point"}
}