{
  "type": "Feature",
  "properties": {
    "addr:full":"Wegalaan 74 Groningen Groningen 9742 ND",
    "addr:housenumber":"74",
    "addr:postcode":"9742 nd",
    "addr:street":"Wegalaan",
    "iso:country":"NL",
    "sg:address":"Wegalaan 74",
    "sg:city":"Groningen",
    "sg:orig_category":"Goederenvervoer Over De Weg",
    "sg:phone":"+31 50 579 1554",
    "sg:postcode":"9742 ND",
    "sg:province":"Groningen",
    "wof:name":"Internat. En Nat. Transportbedrijf H Pom",
    "wof:placetype":"venue"
},
  "geometry": {"coordinates":[6.536347,53.227879],"type":"Point"}
}