{
  "type": "Feature",
  "properties": {
    "addr:full":"Helmwg 9 Callantsoog Noord-Holland 1759 NE",
    "addr:housenumber":"9",
    "addr:postcode":"1759 ne",
    "addr:street":"Helmwg",
    "iso:country":"NL",
    "sg:address":"Helmwg 9",
    "sg:city":"Callantsoog",
    "sg:classifiers":[
        {
            "category":"Restaurant",
            "type":"Food & Drink"
        }
    ],
    "sg:phone":"+31 224 581 421",
    "sg:postcode":"1759 NE",
    "sg:province":"Noord-Holland",
    "sg:website":"http://www.devijverhut.nl",
    "wof:name":"Vijverhut, De",
    "wof:placetype":"venue"
},
  "geometry": {"coordinates":[4.719634,52.860458],"type":"Point"}
}