{
  "type": "Feature",
  "properties": {
    "addr:full":"Boekelosewg 272 Hengelo Ov Overijssel 7554 RV",
    "addr:housenumber":"272",
    "addr:postcode":"7554 rv",
    "addr:street":"Ov",
    "iso:country":"NL",
    "sg:address":"Boekelosewg 272",
    "sg:city":"Hengelo Ov",
    "sg:orig_category":"Hoogwerkers",
    "sg:phone":"+31 74 291 7510",
    "sg:postcode":"7554 RV",
    "sg:province":"Overijssel",
    "wof:name":"Gunco Bv",
    "wof:placetype":"venue"
},
  "geometry": {"coordinates":[6.788533,52.239437],"type":"Point"}
}