{
  "type": "Feature",
  "properties": {
    "addr:full":"Vliegeniersstraat 27 Uden Ar Rifa\u2019 and Southern Region 5405 BH",
    "addr:housenumber":"27",
    "addr:postcode":"5405 bh",
    "addr:street":"Vliegeniersstraat",
    "iso:country":"NL",
    "sg:address":"Vliegeniersstraat 27",
    "sg:city":"Uden",
    "sg:orig_category":"Bouwmaterialen Gh",
    "sg:phone":"+31 413 272 683",
    "sg:postcode":"5405 BH",
    "sg:province":"Ar Rifa\u2019 and Southern Region",
    "wof:name":"Pvr Transport Bv",
    "wof:placetype":"venue"
},
  "geometry": {"coordinates":[50.5485,26.02475],"type":"Point"}
}