{
  "type": "Feature",
  "properties": {
    "addr:full":"Zuiderveldstr 40 Joure Provincie Friesland 8501 KD",
    "addr:housenumber":"40",
    "addr:postcode":"8501 kd",
    "addr:street":"Zuiderveldstr;Provincie Friesland",
    "iso:country":"NL",
    "sg:address":"Zuiderveldstr 40",
    "sg:city":"Joure",
    "sg:orig_category":"Land- En Tuinbouw - Loonbedrijven",
    "sg:phone":"+31 6 55341945",
    "sg:postcode":"8501 KD",
    "sg:province":"Provincie Friesland",
    "wof:name":"Schokker",
    "wof:placetype":"venue"
},
  "geometry": {"coordinates":[5.80101,52.956226],"type":"Point"}
}