{
  "type": "Feature",
  "properties": {
    "addr:full":"Kromhout 160 Dordrecht South Holland 3311 RJ",
    "addr:housenumber":"160",
    "addr:postcode":"3311 rj",
    "addr:street":"Kromhout",
    "iso:country":"NL",
    "sg:address":"Kromhout 160",
    "sg:city":"Dordrecht",
    "sg:orig_category":"Boekhouders",
    "sg:phone":"+31 78 631 1180",
    "sg:postcode":"3311 RJ",
    "sg:province":"South Holland",
    "wof:name":"R Lataster",
    "wof:placetype":"venue"
},
  "geometry": {"coordinates":[4.672399,51.812611],"type":"Point"}
}