{
  "type": "Feature",
  "properties": {
    "addr:full":"Wilhelminaln 7 Bennekom Gelderland 6721 ER",
    "addr:housenumber":"7",
    "addr:postcode":"6721 er",
    "addr:street":"Wilhelminaln;Gelderland",
    "iso:country":"NL",
    "sg:address":"Wilhelminaln 7",
    "sg:city":"Bennekom",
    "sg:orig_category":"Autorijscholen",
    "sg:phone":"+31 318 415 803",
    "sg:postcode":"6721 ER",
    "sg:province":"Gelderland",
    "wof:name":"Schrijver",
    "wof:placetype":"venue"
},
  "geometry": {"coordinates":[5.683505,52.001976],"type":"Point"}
}