{
  "type": "Feature",
  "properties": {
    "iso:country":"NL",
    "sg:address":"Goudenstein 12",
    "sg:city":"Ede Gld",
    "sg:orig_category":"Verzekeringen - Verzekeringskantoren",
    "sg:phone":"+31 318 639 415",
    "sg:postcode":"6714 DB",
    "sg:province":"Gelderland",
    "wof:name":"Hilberink",
    "wof:placetype":"venue"
},
  "geometry": {"coordinates":[5.649542,52.042435],"type":"Point"}
}