{
  "type": "Feature",
  "properties": {
    "addr:full":"Van Oldenbarneveltplein 91 Dordrecht Zuid-Holland 3317 ES",
    "addr:housenumber":"91",
    "addr:postcode":"3317 es",
    "addr:street":"Van Oldenbarneveltplein",
    "iso:country":"NL",
    "sg:address":"Van Oldenbarneveltplein 91",
    "sg:city":"Dordrecht",
    "sg:classifiers":[
        {
            "category":"Bakery",
            "type":"Food & Drink"
        }
    ],
    "sg:phone":"+31 78 617 3859",
    "sg:postcode":"3317 ES",
    "sg:province":"Zuid-Holland",
    "sg:tags":[
        "brood",
        "banket"
    ],
    "wof:name":"Echte Bakker Korteweg",
    "wof:placetype":"venue"
},
  "geometry": {"coordinates":[4.664225,51.79076],"type":"Point"}
}