{
  "type": "Feature",
  "properties": {
    "addr:full":"A V Dyckstr 7 Amsterdam Noord-Holland 1077 ME",
    "addr:housenumber":"7",
    "addr:postcode":"1077 me",
    "addr:street":"A V Dyckstr",
    "iso:country":"NL",
    "sg:address":"A V Dyckstr 7",
    "sg:city":"Amsterdam",
    "sg:orig_category":"Mode Artikelen Dames En Heren - Fabrieken En Groothandel",
    "sg:phone":"+31 20 470 0010",
    "sg:postcode":"1077 ME",
    "sg:province":"Noord-Holland",
    "sg:website":"http://www.himp-amsterdam.com",
    "wof:name":"Euro-American Marketing",
    "wof:placetype":"venue"
},
  "geometry": {"coordinates":[4.87585,52.345482],"type":"Point"}
}