{
  "type": "Feature",
  "properties": {
    "addr:full":"Linnaeusstraat 58 Amsterdam North Holland 1092 CM",
    "addr:housenumber":"58",
    "addr:postcode":"1092 cm",
    "addr:street":"Linnaeusstraat",
    "iso:country":"NL",
    "sg:address":"Linnaeusstraat 58",
    "sg:city":"Amsterdam",
    "sg:orig_category":"Boekhandels",
    "sg:phone":"+31 20 665 0759",
    "sg:postcode":"1092 CM",
    "sg:province":"North Holland",
    "wof:name":"Bv Kantoorboekhandel V/H Gebroeders Winter",
    "wof:placetype":"venue"
},
  "geometry": {"coordinates":[4.926695,52.357277],"type":"Point"}
}