{
  "type": "Feature",
  "properties": {
    "addr:full":"Vijverstraat 3 Prinsenbeek North Brabant 4841 AT",
    "addr:housenumber":"3",
    "addr:postcode":"4841",
    "addr:street":"Vijverstraat",
    "iso:country":"NL",
    "sg:address":"Vijverstraat 3",
    "sg:city":"Prinsenbeek",
    "sg:orig_category":"Bibliotheken And Openbare Archieven",
    "sg:phone":"+31 76 541 7092",
    "sg:postcode":"4841 AT",
    "sg:province":"North Brabant",
    "wof:name":"Bibliotheek",
    "wof:placetype":"venue"
},
  "geometry": {"coordinates":[4.721106,51.598389],"type":"Point"}
}