{
  "type": "Feature",
  "properties": {
    "addr:full":"Fokkerln 32 Amstelveen Noord-Holland 1185 JC",
    "addr:housenumber":"32",
    "addr:postcode":"1185 jc",
    "addr:street":"Fokkerln",
    "iso:country":"NL",
    "sg:address":"Fokkerln 32",
    "sg:city":"Amstelveen",
    "sg:orig_category":"Psychologen",
    "sg:phone":"+31 20 641 7716",
    "sg:postcode":"1185 JC",
    "sg:province":"Noord-Holland",
    "wof:name":"Geluk, H L C",
    "wof:placetype":"venue"
},
  "geometry": {"coordinates":[4.856945,52.303444],"type":"Point"}
}