{
  "type": "Feature",
  "properties": {
    "addr:full":"Keizer Karel V Singel 8 Eindhoven Noord-Brabant 5615 PE",
    "addr:housenumber":"8",
    "addr:postcode":"5615 pe",
    "addr:street":"Keizer Karel V Singel",
    "iso:country":"NL",
    "sg:address":"Keizer Karel V Singel 8",
    "sg:city":"Eindhoven",
    "sg:orig_category":"Werving And Selectie Van Tijdelijk Personeel And Uitzendkantoren",
    "sg:phone":"+31 40 259 1572",
    "sg:postcode":"5615 PE",
    "sg:province":"Noord-Brabant",
    "wof:name":"Animo Bv",
    "wof:placetype":"venue"
},
  "geometry": {"coordinates":[5.4633150101,51.4280319214],"type":"Point"}
}