{
  "type": "Feature",
  "properties": {
    "addr:full":"Noorderhemwg 42 Roelofarendsveen Zuid-Holland 2371 EC",
    "addr:housenumber":"42",
    "addr:postcode":"2371 ec",
    "addr:street":"Noorderhemwg",
    "iso:country":"NL",
    "sg:address":"Noorderhemwg 42",
    "sg:city":"Roelofarendsveen",
    "sg:orig_category":"Adviesbureaus Bedrijfsorganisatie",
    "sg:phone":"+31 71 331 3640",
    "sg:postcode":"2371 EC",
    "sg:province":"Zuid-Holland",
    "sg:website":"http://www.docadvies.nl",
    "wof:name":"Doc",
    "wof:placetype":"venue"
},
  "geometry": {"coordinates":[4.637853,52.196331],"type":"Point"}
}