{
  "type": "Feature",
  "properties": {
    "addr:full":"Land Van Maat 5 Heiloo Noord-Holland 1852 HP",
    "addr:housenumber":"5",
    "addr:postcode":"1852 hp",
    "addr:street":"Land Van Maat",
    "iso:country":"NL",
    "sg:address":"Land Van Maat 5",
    "sg:city":"Heiloo",
    "sg:orig_category":"Autokeuringen",
    "sg:phone":"+31 72 533 5337",
    "sg:postcode":"1852 HP",
    "sg:province":"Noord-Holland",
    "wof:name":"G.R. Hemmekam",
    "wof:placetype":"venue"
},
  "geometry": {"coordinates":[4.701689,52.60228],"type":"Point"}
}