{
  "type": "Feature",
  "properties": {
    "addr:full":"W V Mechelenstr 3 Amersfoort Utrecht 3817 BB",
    "addr:housenumber":"3",
    "addr:postcode":"3817 bb",
    "addr:street":"W V Mechelenstr",
    "iso:country":"NL",
    "sg:address":"W V Mechelenstr 3",
    "sg:city":"Amersfoort",
    "sg:classifiers":[
        {
            "category":"Wholesale",
            "subcategory":"Meat",
            "type":"Manufacturing & Wholesale Goods"
        }
    ],
    "sg:phone":"+31 33 461 4641",
    "sg:postcode":"3817 BB",
    "sg:province":"Utrecht",
    "sg:tags":[
        "regeltechniek",
        "en",
        "meet-"
    ],
    "wof:name":"Multitronics Bv",
    "wof:placetype":"venue"
},
  "geometry": {"coordinates":[5.386085,52.152325],"type":"Point"}
}