{
  "type": "Feature",
  "properties": {
    "iso:country":"NL",
    "sg:address":"Mr Bierenswg 39",
    "sg:city":"Prinsenbeek",
    "sg:orig_category":"Machineonderhoud En -Reparatie",
    "sg:phone":"+31 76 541 4411",
    "sg:postcode":"4841 AJ",
    "sg:province":"North Brabant",
    "wof:name":"Theeuwes",
    "wof:placetype":"venue"
},
  "geometry": {"coordinates":[4.732162,51.595932],"type":"Point"}
}