{
  "type": "Feature",
  "properties": {
    "iso:country":"NL",
    "sg:address":"Kraayenberg 9131",
    "sg:city":"Wychen",
    "sg:orig_category":"Psychologen",
    "sg:phone":"+31 24 397 8221",
    "sg:postcode":"6601 PL",
    "sg:province":"Gelderland",
    "wof:name":"Hulzen, Z J M Van",
    "wof:placetype":"venue"
},
  "geometry": {"coordinates":[5.69934,51.820381],"type":"Point"}
}