{
  "type": "Feature",
  "properties": {
    "addr:full":"Silodam 188 Amsterdam West North Holland 1013 AS",
    "addr:housenumber":"188",
    "addr:postcode":"1013 as",
    "addr:street":"Silodam;West",
    "iso:country":"NL",
    "sg:address":"Silodam 188",
    "sg:city":"Amsterdam West",
    "sg:orig_category":"Werving And Selectie Van Vast Personeel",
    "sg:phone":"+31 20 422 6200",
    "sg:postcode":"1013 AS",
    "sg:province":"North Holland",
    "wof:name":"People Dot Com",
    "wof:placetype":"venue"
},
  "geometry": {"coordinates":[4.8910698891,52.3911361694],"type":"Point"}
}