{
  "type": "Feature",
  "properties": {
    "addr:full":"Picassopassage 31 Capelle A/D Ijssel Zuid-Holland 2907 ME",
    "addr:housenumber":"31;a / d",
    "addr:postcode":"2907 me",
    "addr:street":"Picassopassage",
    "iso:country":"NL",
    "sg:address":"Picassopassage 31",
    "sg:city":"Capelle A/D Ijssel",
    "sg:orig_category":"Banken And Kredietinstellingen",
    "sg:phone":"+31 10 458 0588",
    "sg:postcode":"2907 ME",
    "sg:province":"Zuid-Holland",
    "wof:name":"Abn Amro",
    "wof:placetype":"venue"
},
  "geometry": {"coordinates":[4.584334,51.953362],"type":"Point"}
}