{
  "type": "Feature",
  "properties": {
    "addr:full":"Hingmanstr 3 Rotterdam Zuid-Holland 3078 WK",
    "addr:housenumber":"3",
    "addr:postcode":"3078 wk",
    "addr:street":"Hingmanstr",
    "iso:country":"NL",
    "sg:address":"Hingmanstr 3",
    "sg:city":"Rotterdam",
    "sg:orig_category":"Sanitaire Artikelen",
    "sg:phone":"+31 10 482 2632",
    "sg:postcode":"3078 WK",
    "sg:province":"Zuid-Holland",
    "wof:name":"Vedebo",
    "wof:placetype":"venue"
},
  "geometry": {"coordinates":[4.536864,51.892445],"type":"Point"}
}