{
  "type": "Feature",
  "properties": {
    "addr:full":"Speenkruid 25 Bedum Groningen 9781 WD",
    "addr:housenumber":"25",
    "addr:postcode":"9781 wd",
    "addr:street":"Speenkruid",
    "iso:country":"NL",
    "sg:address":"Speenkruid 25",
    "sg:city":"Bedum",
    "sg:orig_category":"Administratie- En Boekhoudkantoren",
    "sg:phone":"+31 50 301 2453",
    "sg:postcode":"9781 WD",
    "sg:province":"Groningen",
    "wof:name":"Detaccount Vof",
    "wof:placetype":"venue"
},
  "geometry": {"coordinates":[6.614741,53.296734],"type":"Point"}
}