{
  "type": "Feature",
  "properties": {
    "addr:full":"Zandweg 149 De Meern Utrecht 3454 HA",
    "addr:housenumber":"149",
    "addr:postcode":"3454 ha",
    "addr:street":"Zandweg",
    "iso:country":"NL",
    "sg:address":"Zandweg 149",
    "sg:city":"De Meern",
    "sg:orig_category":"Bedrijfs- And Managementsconsultants",
    "sg:phone":"+31 30 666 4906",
    "sg:postcode":"3454 HA",
    "sg:province":"Utrecht",
    "wof:name":"Themaat Bv",
    "wof:placetype":"venue"
},
  "geometry": {"coordinates":[5.033753,52.083656],"type":"Point"}
}