{
  "type": "Feature",
  "properties": {
    "addr:full":"V Tuyll V Serooskerkenwg 42 - 2 Amsterdam North Holland 1076 JM",
    "addr:housenumber":"42 2",
    "addr:postcode":"1076 jm",
    "addr:street":"V Tuyll V Serooskerkenwg",
    "iso:country":"NL",
    "sg:address":"V Tuyll V Serooskerkenwg 42 - 2",
    "sg:city":"Amsterdam",
    "sg:orig_category":"Vertaal- And Tolkenbureaus",
    "sg:phone":"+31 20 664 9634",
    "sg:postcode":"1076 JM",
    "sg:province":"North Holland",
    "wof:name":"Vertaalbureau Mars",
    "wof:placetype":"venue"
},
  "geometry": {"coordinates":[4.85812,52.344231],"type":"Point"}
}