{
  "type": "Feature",
  "properties": {
    "iso:country":"NL",
    "sg:address":"Nieuwe Markt 33C",
    "sg:city":"Roosendaal",
    "sg:orig_category":"Verzekeringen",
    "sg:phone":"+31 165 560 191",
    "sg:postcode":"4701 AB",
    "sg:province":"North Brabant",
    "wof:name":"J.B. Bruijnincx Assurantiekantoor",
    "wof:placetype":"venue"
},
  "geometry": {"coordinates":[4.457556,51.531719],"type":"Point"}
}