{
  "type": "Feature",
  "properties": {
    "iso:country":"NL",
    "sg:address":"De Sluis 3",
    "sg:city":"Dussen",
    "sg:orig_category":"Autokeuringen",
    "sg:phone":"+31 416 391 218",
    "sg:postcode":"4271 CZ",
    "sg:province":"Noord-Brabant",
    "wof:name":"Garage Kiewiet Bv",
    "wof:placetype":"venue"
},
  "geometry": {"coordinates":[15.47527,49.803791],"type":"Point"}
}