{
  "type": "Feature",
  "properties": {
    "addr:full":"Wouwsestr 23A Bergen Op Zoom Noord-Brabant 4611 PK",
    "addr:housenumber":"23a",
    "addr:postcode":"4611 pk",
    "addr:street":"Wouwsestr",
    "iso:country":"NL",
    "sg:address":"Wouwsestr 23A",
    "sg:city":"Bergen Op Zoom",
    "sg:orig_category":"Opticiens",
    "sg:phone":"+31 164 263 337",
    "sg:postcode":"4611 PK",
    "sg:province":"Noord-Brabant",
    "sg:website":"http://www.specsavers.nl",
    "wof:name":"Specsavers",
    "wof:placetype":"venue"
},
  "geometry": {"coordinates":[4.2919201851,51.4953689575],"type":"Point"}
}