{
  "type": "Feature",
  "properties": {
    "addr:full":"Markgravenln 3 Bergen Op Zoom North Brabant 4624 KK",
    "addr:housenumber":"3",
    "addr:postcode":"4624 kk",
    "addr:street":"Markgravenln",
    "iso:country":"NL",
    "sg:address":"Markgravenln 3",
    "sg:city":"Bergen Op Zoom",
    "sg:orig_category":"Adviesbureaus Bouwkunde",
    "sg:phone":"+31 164 251 818",
    "sg:postcode":"4624 KK",
    "sg:province":"North Brabant",
    "wof:name":"Gjm Bv",
    "wof:placetype":"venue"
},
  "geometry": {"coordinates":[4.297248,51.479515],"type":"Point"}
}