{
  "type": "Feature",
  "properties": {
    "iso:country":"NL",
    "sg:address":"Glasakker 7",
    "sg:city":"Dinteloord",
    "sg:classifiers":[
        {
            "category":"Professional",
            "subcategory":"Accounting & Tax Preparation",
            "type":"Services"
        }
    ],
    "sg:phone":"+31 167 523 630",
    "sg:postcode":"4671 KV",
    "sg:province":"Noord-Brabant",
    "sg:tags":[
        "accountant",
        "en",
        "-kantoren",
        "register-"
    ],
    "wof:name":"Meij, A E De",
    "wof:placetype":"venue"
},
  "geometry": {"coordinates":[4.370385,51.635994],"type":"Point"}
}