{
  "type": "Feature",
  "properties": {
    "addr:full":"Andreasplein 6 Katwijk Zuid-Holland 2225 GR",
    "addr:housenumber":"6",
    "addr:postcode":"2225",
    "addr:street":"Andreasplein",
    "iso:country":"NL",
    "sg:address":"Andreasplein 6",
    "sg:city":"Katwijk",
    "sg:orig_category":"Visspeciaalzaken",
    "sg:phone":"+31 71 401 6561",
    "sg:postcode":"2225 GR",
    "sg:province":"Zuid-Holland",
    "wof:name":"Viskiosk Hoek'S",
    "wof:placetype":"venue"
},
  "geometry": {"coordinates":[4.393176,52.202686],"type":"Point"}
}