{
  "type": "Feature",
  "properties": {
    "addr:full":"Pieter Calandlaan 91 Amsterdam Noord-Holland 1065 KK",
    "addr:housenumber":"91",
    "addr:postcode":"1065 kk",
    "addr:street":"Pieter Calandlaan",
    "iso:country":"NL",
    "sg:address":"Pieter Calandlaan 91",
    "sg:city":"Amsterdam",
    "sg:orig_category":"Kinderopvang Behalve Thuis",
    "sg:phone":"+31 20 614 2933",
    "sg:postcode":"1065 KK",
    "sg:province":"Noord-Holland",
    "wof:name":"Kinderdagverblijf Slotervaart St Uk",
    "wof:placetype":"venue"
},
  "geometry": {"coordinates":[4.823619,52.35603],"type":"Point"}
}