{
  "type": "Feature",
  "properties": {
    "addr:full":"Vennestr 17 Lisse Zuid-Holland 2161 LE",
    "addr:housenumber":"17",
    "addr:postcode":"2161 le",
    "addr:street":"Vennestr",
    "iso:country":"NL",
    "sg:address":"Vennestr 17",
    "sg:city":"Lisse",
    "sg:orig_category":"Meubelen",
    "sg:phone":"+31 252 438 100",
    "sg:postcode":"2161 LE",
    "sg:province":"Zuid-Holland",
    "wof:name":"Mijnders Bv",
    "wof:placetype":"venue"
},
  "geometry": {"coordinates":[4.55166,52.250999],"type":"Point"}
}