{
  "type": "Feature",
  "properties": {
    "addr:full":"Edward Jennerstraat 328 Haarlem Noord-Holland 2035 EW",
    "addr:housenumber":"328",
    "addr:postcode":"2035 ew",
    "addr:street":"Edward Jennerstraat",
    "iso:country":"NL",
    "sg:address":"Edward Jennerstraat 328",
    "sg:city":"Haarlem",
    "sg:orig_category":"Film-, Tv- And Videoproductie",
    "sg:phone":"+31 23 540 0008",
    "sg:postcode":"2035 EW",
    "sg:province":"Noord-Holland",
    "wof:name":"Promotime Publications",
    "wof:placetype":"venue"
},
  "geometry": {"coordinates":[4.656748,52.361042],"type":"Point"}
}