{
  "type": "Feature",
  "properties": {
    "addr:full":"Bozenhoven 152 Mydrecht Utrecht 3641 AJ",
    "addr:housenumber":"152",
    "addr:postcode":"3641 aj",
    "addr:street":"Bozenhoven",
    "iso:country":"NL",
    "sg:address":"Bozenhoven 152",
    "sg:city":"Mydrecht",
    "sg:orig_category":"Zalenverhuur",
    "sg:phone":"+31 297 287 695",
    "sg:postcode":"3641 AJ",
    "sg:province":"Utrecht",
    "wof:name":"Oude Parochiehuis, 'T",
    "wof:placetype":"venue"
},
  "geometry": {"coordinates":[4.872486,52.199661],"type":"Point"}
}