{
  "type": "Feature",
  "properties": {
    "addr:full":"Abeelstr 1 S Gravenzande Zuid-Holland 2691 DG",
    "addr:housenumber":"1;gravenzande",
    "addr:postcode":"2691 dg",
    "addr:street":"Abeelstr;S",
    "iso:country":"NL",
    "sg:address":"Abeelstr 1",
    "sg:city":"S Gravenzande",
    "sg:classifiers":[
        {
            "category":"Personal",
            "subcategory":"Nail Salon",
            "type":"Services"
        }
    ],
    "sg:phone":"+31 174 414 599",
    "sg:postcode":"2691 DG",
    "sg:province":"Zuid-Holland",
    "sg:tags":[
        "pedicure"
    ],
    "wof:name":"Kaaij-Hoogendoorn, A Van Der",
    "wof:placetype":"venue"
},
  "geometry": {"coordinates":[4.163893,51.998158],"type":"Point"}
}