{
  "type": "Feature",
  "properties": {
    "addr:full":"Nachtegaalln 30 Anna Paulowna Noord-Holland 1761 WH",
    "addr:housenumber":"30",
    "addr:postcode":"1761 wh",
    "addr:street":"Nachtegaalln",
    "iso:country":"NL",
    "sg:address":"Nachtegaalln 30",
    "sg:city":"Anna Paulowna",
    "sg:orig_category":"Verenigingen En Stichtingen",
    "sg:phone":"+31 223 532 655",
    "sg:postcode":"1761 WH",
    "sg:province":"Noord-Holland",
    "sg:website":"http://muziek.clubs.nl/annapaulowna",
    "wof:name":"Tamboer- & Lyrakorps Anna Paulowna",
    "wof:placetype":"venue"
},
  "geometry": {"coordinates":[4.820169,52.857452],"type":"Point"}
}