{
  "type": "Feature",
  "properties": {
    "addr:full":"Selenakker 28 Tilburg Noord-Brabant 5047 TP",
    "addr:housenumber":"28",
    "addr:postcode":"5047 tp",
    "addr:street":"Selenakker",
    "iso:country":"NL",
    "sg:address":"Selenakker 28",
    "sg:city":"Tilburg",
    "sg:orig_category":"Afzuiginstallaties",
    "sg:phone":"+31 13 570 1809",
    "sg:postcode":"5047 TP",
    "sg:province":"Noord-Brabant",
    "sg:website":"http://www.demzo.nl",
    "wof:name":"Demzo Bv",
    "wof:placetype":"venue"
},
  "geometry": {"coordinates":[5.028898,51.589409],"type":"Point"}
}