{
  "type": "Feature",
  "properties": {
    "iso:country":"NL",
    "sg:address":"Telefoonwg 82",
    "sg:city":"Ede Gld",
    "sg:orig_category":"Keukens",
    "sg:phone":"+31 318 610 277",
    "sg:postcode":"6713 AL",
    "sg:province":"Gelderland",
    "wof:name":"Ruyter, De",
    "wof:placetype":"venue"
},
  "geometry": {"coordinates":[5.66812,52.044392],"type":"Point"}
}