{
  "type": "Feature",
  "properties": {
    "addr:full":"Witte Veerstr 28 Zaandyk Noord-Holland 1544 CH",
    "addr:housenumber":"28",
    "addr:postcode":"1544",
    "addr:street":"Zaandyk Noord-Holland",
    "iso:country":"NL",
    "sg:address":"Witte Veerstr 28",
    "sg:city":"Zaandyk",
    "sg:orig_category":"Montagebedrijven",
    "sg:phone":"+31 6 41812287",
    "sg:postcode":"1544 CH",
    "sg:province":"Noord-Holland",
    "wof:name":"Kees",
    "wof:placetype":"venue"
},
  "geometry": {"coordinates":[4.807054,52.478622],"type":"Point"}
}