{
  "type": "Feature",
  "properties": {
    "iso:country":"NL",
    "sg:address":"Wilhelm Rontgenstraat 7",
    "sg:city":"Zwolle",
    "sg:orig_category":"Chemische Producten Gh",
    "sg:phone":"+31 38 465 7477",
    "sg:postcode":"8013 NE",
    "sg:province":"Overijssel",
    "wof:name":"Ispa Plastics",
    "wof:placetype":"venue"
},
  "geometry": {"coordinates":[6.124819,52.490772],"type":"Point"}
}