{
  "type": "Feature",
  "properties": {
    "addr:full":"Weverstr 28 Arnhem Gelderland 6811 EM",
    "addr:housenumber":"28",
    "addr:postcode":"6811 em",
    "addr:street":"Weverstr",
    "iso:country":"NL",
    "sg:address":"Weverstr 28",
    "sg:city":"Arnhem",
    "sg:orig_category":"Juweliers",
    "sg:phone":"+31 26 442 5538",
    "sg:postcode":"6811 EM",
    "sg:province":"Gelderland",
    "wof:name":"Goldline",
    "wof:placetype":"venue"
},
  "geometry": {"coordinates":[5.906635,51.980034],"type":"Point"}
}