{
  "type": "Feature",
  "properties": {
    "addr:full":"Koningin Julianalaan 1 Valkenburg Lb Limburg 6301 GT",
    "addr:housenumber":"1",
    "addr:postcode":"lb;6301 gt",
    "addr:street":"Koningin Julianalaan",
    "iso:country":"NL",
    "sg:address":"Koningin Julianalaan 1",
    "sg:city":"Valkenburg Lb",
    "sg:orig_category":"Adviesbureaus Bedrijfsorganisatie",
    "sg:phone":"+31 43 601 1656",
    "sg:postcode":"6301 GT",
    "sg:province":"Limburg",
    "wof:name":"Ineke Van De Braak",
    "wof:placetype":"venue"
},
  "geometry": {"coordinates":[5.830971,50.86692],"type":"Point"}
}