{
  "type": "Feature",
  "properties": {
    "addr:full":"Kostverlorenhof 61 Amstelveen Noord-Holland 1183 HG",
    "addr:housenumber":"61",
    "addr:postcode":"1183 hg",
    "addr:street":"Kostverlorenhof",
    "iso:country":"NL",
    "sg:address":"Kostverlorenhof 61",
    "sg:city":"Amstelveen",
    "sg:orig_category":"Bloemen And Planten",
    "sg:phone":"+31 20 647 0612",
    "sg:postcode":"1183 HG",
    "sg:province":"Noord-Holland",
    "wof:name":"Bloemenshop Debby",
    "wof:placetype":"venue"
},
  "geometry": {"coordinates":[4.875243,52.313065],"type":"Point"}
}