{
  "type": "Feature",
  "properties": {
    "addr:full":"Veerallee 64 Zwolle NL.08 8019 AE",
    "addr:housenumber":"64",
    "addr:postcode":"8019 ae",
    "addr:street":"Veerallee",
    "iso:country":"NL",
    "sg:address":"Veerallee 64",
    "sg:city":"Zwolle",
    "sg:orig_category":"Verenigingen En Stichtingen",
    "sg:phone":"+31 38 421 8691",
    "sg:postcode":"8019 AE",
    "sg:province":"NL.08",
    "sg:website":"http://www.ambulancezorg-wg.nl",
    "wof:name":"Ambulancezorg Nederland",
    "wof:placetype":"venue"
},
  "geometry": {"coordinates":[6.072843,52.504597],"type":"Point"}
}