{
  "type": "Feature",
  "properties": {
    "addr:full":"Ulvenhoutstr 43 Arnhem Gelderland 6843 RG",
    "addr:housenumber":"43",
    "addr:postcode":"6843 rg",
    "addr:street":"Ulvenhoutstr",
    "iso:country":"NL",
    "sg:address":"Ulvenhoutstr 43",
    "sg:city":"Arnhem",
    "sg:orig_category":"Accountants - Administratie- Consulenten En -Kantoren",
    "sg:phone":"+31 6 51532527",
    "sg:postcode":"6843 RG",
    "sg:province":"Gelderland",
    "wof:name":"Fierkens, E W H",
    "wof:placetype":"venue"
},
  "geometry": {"coordinates":[5.861993,51.953205],"type":"Point"}
}