{
  "type": "Feature",
  "properties": {
    "addr:full":"Paterswoldsewg 582 Groningen Groningen 9728 BE",
    "addr:housenumber":"582",
    "addr:postcode":"9728",
    "iso:country":"NL",
    "sg:address":"Paterswoldsewg 582",
    "sg:city":"Groningen",
    "sg:orig_category":"Bloemen En Planten",
    "sg:phone":"+31 50 526 1012",
    "sg:postcode":"9728 BE",
    "sg:province":"Groningen",
    "wof:name":"Schuiten, Jan",
    "wof:placetype":"venue"
},
  "geometry": {"coordinates":[6.558192,53.198311],"type":"Point"}
}