{
  "type": "Feature",
  "properties": {
    "iso:country":"NL",
    "sg:address":"Jachtln 24A",
    "sg:city":"Apeldoorn",
    "sg:orig_category":"Psychotherapeuten",
    "sg:phone":"+31 55 355 8436",
    "sg:postcode":"7313 CR",
    "sg:province":"Gelderland",
    "wof:name":"Dijkman-Sandmann",
    "wof:placetype":"venue"
},
  "geometry": {"coordinates":[5.96566,52.216518],"type":"Point"}
}