{
  "type": "Feature",
  "properties": {
    "iso:country":"NL",
    "sg:address":"Kees Van Lentsingel 6",
    "sg:city":"Heemstede",
    "sg:orig_category":"Zuivelproducten And Spijsoli?n Gh",
    "sg:phone":"+31 23 528 5123",
    "sg:postcode":"2101 EK",
    "sg:province":"North Holland",
    "wof:name":"Sijsenaar'S Groothandel Bv",
    "wof:placetype":"venue"
},
  "geometry": {"coordinates":[4.611756,52.349808],"type":"Point"}
}