{
  "type": "Feature",
  "properties": {
    "addr:full":"Sterrenlaan 25 Oosterhout Nb North Brabant 4907 GH",
    "addr:housenumber":"25;nb",
    "addr:postcode":"4907 gh",
    "addr:street":"Sterrenlaan",
    "iso:country":"NL",
    "sg:address":"Sterrenlaan 25",
    "sg:city":"Oosterhout Nb",
    "sg:classifiers":[
        {
            "category":"Education",
            "subcategory":"Preschool",
            "type":"Public Place"
        }
    ],
    "sg:phone":"+31 162 450 332",
    "sg:postcode":"4907 GH",
    "sg:province":"North Brabant",
    "sg:tags":[
        "kleuteronderwijs",
        "basis-"
    ],
    "wof:name":"Openbare Basisschool Sterrendonk",
    "wof:placetype":"venue"
},
  "geometry": {"coordinates":[4.85625,51.643051],"type":"Point"}
}