{
  "type": "Feature",
  "properties": {
    "addr:full":"Kerkstr 104 Gilze North Brabant 5126 GD",
    "addr:housenumber":"104",
    "addr:postcode":"5126 gd",
    "iso:country":"NL",
    "sg:address":"Kerkstr 104",
    "sg:city":"Gilze",
    "sg:orig_category":"Verenigingen En Stichtingen",
    "sg:phone":"+31 161 452 009",
    "sg:postcode":"5126 GD",
    "sg:province":"North Brabant",
    "wof:name":"Schakel, De",
    "wof:placetype":"venue"
},
  "geometry": {"coordinates":[4.941196,51.540226],"type":"Point"}
}