{
  "type": "Feature",
  "properties": {
    "addr:full":"Wilhelminastr 24 Beesd Gelderland 4153 BC",
    "addr:housenumber":"24",
    "addr:postcode":"4153 bc",
    "addr:street":"Wilhelminastr;Gelderland",
    "iso:country":"NL",
    "sg:address":"Wilhelminastr 24",
    "sg:city":"Beesd",
    "sg:orig_category":"Evenementenverzorging",
    "sg:phone":"+31 345 686 021",
    "sg:postcode":"4153 BC",
    "sg:province":"Gelderland",
    "sg:website":"http://www.pippelengineering.nl",
    "wof:name":"Snow Company Pec",
    "wof:placetype":"venue"
},
  "geometry": {"coordinates":[5.194292,51.888382],"type":"Point"}
}