{
  "type": "Feature",
  "properties": {
    "iso:country":"NL",
    "sg:address":"Leerlooiersstraat 4",
    "sg:city":"Sneek",
    "sg:orig_category":"Juweliers",
    "sg:phone":"+31 515 423 087",
    "sg:postcode":"8601 WK",
    "sg:province":"Provincie Friesland",
    "wof:name":"Scholte Klokken Bv",
    "wof:placetype":"venue"
},
  "geometry": {"coordinates":[5.631389,53.035984],"type":"Point"}
}