{
  "type": "Feature",
  "properties": {
    "addr:full":"Osdorppln 135 Amsterdam North Holland 1068 SR",
    "addr:housenumber":"135",
    "addr:postcode":"1068 sr",
    "iso:country":"NL",
    "sg:address":"Osdorppln 135",
    "sg:city":"Amsterdam",
    "sg:orig_category":"Schoenen",
    "sg:phone":"+31 20 619 8616",
    "sg:postcode":"1068 SR",
    "sg:province":"North Holland",
    "wof:name":"Bristol",
    "wof:placetype":"venue"
},
  "geometry": {"coordinates":[4.805832,52.360237],"type":"Point"}
}