{
  "type": "Feature",
  "properties": {
    "addr:full":"Bijlstraat 2 Rotterdam South Holland 3087 AA",
    "addr:housenumber":"2",
    "addr:postcode":"3087 aa",
    "addr:street":"Bijlstraat",
    "iso:country":"NL",
    "sg:address":"Bijlstraat 2",
    "sg:city":"Rotterdam",
    "sg:orig_category":"Verhuisdiensten",
    "sg:phone":"+31 10 429 7688",
    "sg:postcode":"3087 AA",
    "sg:province":"South Holland",
    "wof:name":"Castelijns Transportbedrijf Bv",
    "wof:placetype":"venue"
},
  "geometry": {"coordinates":[4.459888,51.897141],"type":"Point"}
}