{
  "type": "Feature",
  "properties": {
    "addr:full":"Voorwg 55 Heemskerk North Holland 1969 ME",
    "addr:housenumber":"55",
    "addr:postcode":"1969 me",
    "addr:street":"Voorwg",
    "iso:country":"NL",
    "sg:address":"Voorwg 55",
    "sg:city":"Heemskerk",
    "sg:orig_category":"Oldtimers",
    "sg:phone":"+31 251 243 900",
    "sg:postcode":"1969 ME",
    "sg:province":"North Holland",
    "sg:website":"http://www.dreamcars.nl",
    "wof:name":"Dreamcars",
    "wof:placetype":"venue"
},
  "geometry": {"coordinates":[4.629635,52.507259],"type":"Point"}
}