{
  "type": "Feature",
  "properties": {
    "addr:full":"Langven 21 Heesch Noord-Brabant 5384 PT",
    "addr:housenumber":"21",
    "addr:postcode":"5384 pt",
    "addr:street":"Langven",
    "iso:country":"NL",
    "sg:address":"Langven 21",
    "sg:city":"Heesch",
    "sg:orig_category":"Adviesbureaus Bedrijfsorganisatie",
    "sg:phone":"+31 412 457 248",
    "sg:postcode":"5384 PT",
    "sg:province":"Noord-Brabant",
    "wof:name":"Meijboom",
    "wof:placetype":"venue"
},
  "geometry": {"coordinates":[5.540495,51.734024],"type":"Point"}
}