{
  "type": "Feature",
  "properties": {
    "addr:full":"Nieuwe Laantjes 110 Scheveningen South Holland 2584 RX",
    "addr:housenumber":"110",
    "addr:postcode":"2584 rx",
    "addr:street":"Nieuwe Laantjes",
    "iso:country":"NL",
    "sg:address":"Nieuwe Laantjes 110",
    "sg:city":"Scheveningen",
    "sg:orig_category":"Drukkerijen And Copyshops",
    "sg:phone":"+31 70 355 5445",
    "sg:postcode":"2584 RX",
    "sg:province":"South Holland",
    "sg:website":"http://www.forma-zeefdruk.nl",
    "wof:name":"Forma Textiel Design",
    "wof:placetype":"venue"
},
  "geometry": {"coordinates":[4.274599,52.104679],"type":"Point"}
}