{
  "type": "Feature",
  "properties": {
    "addr:full":"Zwaluwstraat 3 Badhoevedorp Noord-Holland 1171 SM",
    "addr:housenumber":"3",
    "addr:postcode":"1171 sm",
    "addr:street":"Zwaluwstraat",
    "iso:country":"NL",
    "sg:address":"Zwaluwstraat 3",
    "sg:city":"Badhoevedorp",
    "sg:orig_category":"Zuivelproducten And Spijsoli?n Gh",
    "sg:phone":"+31 20 659 7000",
    "sg:postcode":"1171 SM",
    "sg:province":"Noord-Holland",
    "wof:name":"Multipower Holl Bv",
    "wof:placetype":"venue"
},
  "geometry": {"coordinates":[4.790024,52.338364],"type":"Point"}
}