{
  "type": "Feature",
  "properties": {
    "iso:country":"NL",
    "sg:address":"V Sevenhovenstr 72",
    "sg:city":"Stadskanaal",
    "sg:orig_category":"Boeken En Tijdschriften - Groothandel",
    "sg:phone":"+31 599 653 993",
    "sg:postcode":"9503 CG",
    "sg:province":"Groningen",
    "sg:website":"http://www.newleaf-dist.com",
    "wof:name":"New Leaf Europe Bv",
    "wof:placetype":"venue"
},
  "geometry": {"coordinates":[6.959475,52.984375],"type":"Point"}
}