{
  "type": "Feature",
  "properties": {
    "addr:full":"Rykswg 180 Hoogersmilde Drenthe 9423 PD",
    "addr:housenumber":"180",
    "addr:postcode":"9423 pd",
    "iso:country":"NL",
    "sg:address":"Rykswg 180",
    "sg:city":"Hoogersmilde",
    "sg:orig_category":"Bestratingen",
    "sg:phone":"+31 592 459 218",
    "sg:postcode":"9423 PD",
    "sg:province":"Drenthe",
    "wof:name":"Olde Smilde, D'",
    "wof:placetype":"venue"
},
  "geometry": {"coordinates":[6.39879,52.906898],"type":"Point"}
}