{
  "type": "Feature",
  "properties": {
    "addr:full":"Burg Stulemeyerln 1 Bergen Op Zoom Noord-Brabant 4611 EH",
    "addr:housenumber":"1",
    "addr:postcode":"4611 eh",
    "addr:street":"Burg Stulemeyerln",
    "iso:country":"NL",
    "sg:address":"Burg Stulemeyerln 1",
    "sg:city":"Bergen Op Zoom",
    "sg:orig_category":"Woningbouw- Verenigingen En -Stichtingen",
    "sg:phone":"+31 164 283 300",
    "sg:postcode":"4611 EH",
    "sg:province":"Noord-Brabant",
    "sg:website":"http://www.spectrumnet.nl",
    "wof:name":"Spectrum, Woningstichting",
    "wof:placetype":"venue"
},
  "geometry": {"coordinates":[4.2819871902,51.4959526062],"type":"Point"}
}