{
  "type": "Feature",
  "properties": {
    "iso:country":"NL",
    "sg:address":"Burgemeester Tellegenstr 196",
    "sg:city":"Amsterdam",
    "sg:orig_category":"Binnenhuisarchitecten",
    "sg:phone":"+31 20 664 6684",
    "sg:postcode":"1073 KG",
    "sg:province":"Noord-Holland",
    "wof:name":"J.P. Kuiper",
    "wof:placetype":"venue"
},
  "geometry": {"coordinates":[4.900143,52.350517],"type":"Point"}
}