{
  "type": "Feature",
  "properties": {
    "addr:full":"Krekelstr 11 Rotterdam South Holland 3061 VC",
    "addr:housenumber":"11",
    "addr:postcode":"3061 vc",
    "addr:street":"Krekelstr",
    "iso:country":"NL",
    "sg:address":"Krekelstr 11",
    "sg:city":"Rotterdam",
    "sg:orig_category":"Wijnkoperijen En -Groothandel",
    "sg:phone":"+31 10 414 8766",
    "sg:postcode":"3061 VC",
    "sg:province":"South Holland",
    "wof:name":"Kurk, De",
    "wof:placetype":"venue"
},
  "geometry": {"coordinates":[4.5038971901,51.9238891602],"type":"Point"}
}