{
  "type": "Feature",
  "properties": {
    "iso:country":"NL",
    "sg:address":"Antennestr 26",
    "sg:city":"Almere",
    "sg:orig_category":"Adviesbureaus Bedrijfsorganisatie",
    "sg:phone":"+31 36 546 0550",
    "sg:postcode":"1322 AB",
    "sg:province":"Flevoland",
    "sg:website":"http://www.rmcalmere.nl",
    "wof:name":"R\u00f6selaers Management Consultans",
    "wof:placetype":"venue"
},
  "geometry": {"coordinates":[5.190387,52.35194],"type":"Point"}
}