{
  "type": "Feature",
  "properties": {
    "addr:full":"K Poolsterstr 7 Rotterdam Zuid-Holland 3067 LZ",
    "addr:housenumber":"7",
    "addr:postcode":"3067 lz",
    "addr:street":"Poolsterstr",
    "iso:country":"NL",
    "sg:address":"K Poolsterstr 7",
    "sg:city":"Rotterdam",
    "sg:orig_category":"Herenkleding",
    "sg:phone":"+31 10 286 7322",
    "sg:postcode":"3067 LZ",
    "sg:province":"Zuid-Holland",
    "sg:website":"http://www.wefashion.com",
    "wof:name":"We",
    "wof:placetype":"venue"
},
  "geometry": {"coordinates":[4.554277,51.949688],"type":"Point"}
}