{
  "type": "Feature",
  "properties": {
    "iso:country":"NL",
    "sg:address":"Sloterwg 87",
    "sg:city":"Badhoevedorp",
    "sg:orig_category":"Beveiliging",
    "sg:phone":"+31 20 449 9444",
    "sg:postcode":"1171 CH",
    "sg:province":"Noord-Holland",
    "wof:name":"Devision Meldkamer Bv",
    "wof:placetype":"venue"
},
  "geometry": {"coordinates":[4.78145,52.33979],"type":"Point"}
}