{
  "type": "Feature",
  "properties": {
    "iso:country":"NL",
    "sg:address":"Loosdrechtsewg 101",
    "sg:city":"Hilversum",
    "sg:orig_category":"Orthopedische Artikelen - Fabrieken En Groothandel",
    "sg:phone":"+31 35 623 4345",
    "sg:postcode":"1215 JP",
    "sg:province":"Noord-Holland",
    "wof:name":"Vios",
    "wof:placetype":"venue"
},
  "geometry": {"coordinates":[5.1540899277,52.2169303894],"type":"Point"}
}