{
  "type": "Feature",
  "properties": {
    "iso:country":"NL",
    "sg:address":"Breitnerln 18",
    "sg:city":"Utrecht",
    "sg:orig_category":"Adviesbureaus Bedrijfsorganisatie",
    "sg:phone":"+31 30 254 2041",
    "sg:postcode":"3582 HB",
    "sg:province":"Utrecht",
    "wof:name":"Mertens, Drs A H",
    "wof:placetype":"venue"
},
  "geometry": {"coordinates":[5.140003,52.078583],"type":"Point"}
}