{
  "type": "Feature",
  "properties": {
    "addr:full":"Ceylonpoort 5-25 Haarlem Noord-Holland 2037 AA",
    "addr:housenumber":"5-25",
    "addr:postcode":"2037 aa",
    "iso:country":"NL",
    "sg:address":"Ceylonpoort 5-25",
    "sg:city":"Haarlem",
    "sg:classifiers":[
        {
            "category":"Shopping",
            "subcategory":"News",
            "type":"Retail Goods"
        }
    ],
    "sg:phone":"+31 23 546 3463",
    "sg:postcode":"2037 AA",
    "sg:province":"Noord-Holland",
    "sg:tags":[
        "maandbladen",
        "en",
        "week-"
    ],
    "wof:name":"Textilia/Vnu Business Publications",
    "wof:placetype":"venue"
},
  "geometry": {"coordinates":[4.6550159454,52.3601989746],"type":"Point"}
}