{
  "type": "Feature",
  "properties": {
    "addr:full":"Ratelaar 13 Alblasserdam Zuid-Holland 2954 ND",
    "addr:housenumber":"13",
    "addr:postcode":"2954 nd",
    "addr:street":"Ratelaar",
    "iso:country":"NL",
    "sg:address":"Ratelaar 13",
    "sg:city":"Alblasserdam",
    "sg:classifiers":[
        {
            "category":"Wholesale",
            "subcategory":"Meat",
            "type":"Manufacturing & Wholesale Goods"
        }
    ],
    "sg:phone":"+31 78 693 0878",
    "sg:postcode":"2954 ND",
    "sg:province":"Zuid-Holland",
    "sg:tags":[
        "hang-",
        "sluitwerk",
        "en"
    ],
    "wof:name":"Just In Case",
    "wof:placetype":"venue"
},
  "geometry": {"coordinates":[4.665768,51.871548],"type":"Point"}
}