{
  "type": "Feature",
  "properties": {
    "addr:full":"Herenwg 280 Vinkeveen Utrecht 3645 DX",
    "addr:housenumber":"280",
    "addr:postcode":"3645 dx",
    "addr:street":"Vinkeveen",
    "iso:country":"NL",
    "sg:address":"Herenwg 280",
    "sg:city":"Vinkeveen",
    "sg:orig_category":"Metselwerken",
    "sg:phone":"+31 297 264 399",
    "sg:postcode":"3645 DX",
    "sg:province":"Utrecht",
    "wof:name":"Vinkeveen Bv",
    "wof:placetype":"venue"
},
  "geometry": {"coordinates":[4.929998,52.222591],"type":"Point"}
}