{
  "type": "Feature",
  "properties": {
    "addr:full":"Haven Noordzijde 29 Brouwershaven Zeeland 4318 AC",
    "addr:housenumber":"29",
    "addr:postcode":"4318 ac",
    "addr:street":"Haven Noordzijde",
    "iso:country":"NL",
    "sg:address":"Haven Noordzijde 29",
    "sg:city":"Brouwershaven",
    "sg:orig_category":"Watersport-, Sport- And Kampeerbenodigdheden Verhuur",
    "sg:phone":"+31 111 691 191",
    "sg:postcode":"4318 AC",
    "sg:province":"Zeeland",
    "wof:name":"Ed Willemse Services Bv",
    "wof:placetype":"venue"
},
  "geometry": {"coordinates":[3.9150869846,51.7268371582],"type":"Point"}
}