{
  "type": "Feature",
  "properties": {
    "addr:full":"Sixlaan 4 Voorschoten Zuid-Holland 2252 CG",
    "addr:housenumber":"4",
    "addr:postcode":"2252 cg",
    "addr:street":"Sixlaan",
    "iso:country":"NL",
    "sg:address":"Sixlaan 4",
    "sg:city":"Voorschoten",
    "sg:orig_category":"Kinderopvang Behalve Thuis",
    "sg:phone":"+31 71 561 7731",
    "sg:postcode":"2252 CG",
    "sg:province":"Zuid-Holland",
    "wof:name":"Peuterspeelzaal De Boschfluiters",
    "wof:placetype":"venue"
},
  "geometry": {"coordinates":[4.437674,52.122456],"type":"Point"}
}