{
  "type": "Feature",
  "properties": {
    "addr:full":"Zandvoortselaan 61 Heemstede North Holland 2106 CK",
    "addr:housenumber":"61",
    "addr:postcode":"2106 ck",
    "addr:street":"Zandvoortselaan",
    "iso:country":"NL",
    "sg:address":"Zandvoortselaan 61",
    "sg:city":"Heemstede",
    "sg:orig_category":"Verzekeringen",
    "sg:phone":"+31 23 547 2299",
    "sg:postcode":"2106 CK",
    "sg:province":"North Holland",
    "wof:name":"Boerma Wessel Assurantien Vof",
    "wof:placetype":"venue"
},
  "geometry": {"coordinates":[4.61141,52.359406],"type":"Point"}
}