{
  "type": "Feature",
  "properties": {
    "iso:country":"NL",
    "sg:address":"V Blarcumlaan 13",
    "sg:city":"Ankeveen",
    "sg:orig_category":"Diverse Grafische Activiteiten",
    "sg:phone":"+31 35 656 1995",
    "sg:postcode":"1244 NX",
    "sg:province":"Noord-Holland",
    "wof:name":"A T/M",
    "wof:placetype":"venue"
},
  "geometry": {"coordinates":[5.098394,52.265591],"type":"Point"}
}