{
  "type": "Feature",
  "properties": {
    "addr:full":"Kroosdk 10 Zieuwent Gelderland 7136 KC",
    "addr:housenumber":"10",
    "addr:postcode":"7136 kc",
    "addr:street":"Kroosdk;Gelderland",
    "iso:country":"NL",
    "sg:address":"Kroosdk 10",
    "sg:city":"Zieuwent",
    "sg:orig_category":"Autopoetsbedrijven",
    "sg:phone":"+31 6 50460991",
    "sg:postcode":"7136 KC",
    "sg:province":"Gelderland",
    "wof:name":"Pierik",
    "wof:placetype":"venue"
},
  "geometry": {"coordinates":[6.519575,52.003925],"type":"Point"}
}