{
  "type": "Feature",
  "properties": {
    "addr:full":"Amsterdamwg 52 Almere Flevoland 1324 RR",
    "addr:housenumber":"52",
    "addr:postcode":"1324 rr",
    "addr:street":"Amsterdamwg;Flevoland",
    "iso:country":"NL",
    "sg:address":"Amsterdamwg 52",
    "sg:city":"Almere",
    "sg:orig_category":"Glazenwasserijen",
    "sg:phone":"+31 36 844 3159",
    "sg:postcode":"1324 RR",
    "sg:province":"Flevoland",
    "wof:name":"Terhorst, Glazenwasserij",
    "wof:placetype":"venue"
},
  "geometry": {"coordinates":[5.208646,52.367928],"type":"Point"}
}