{
  "type": "Feature",
  "properties": {
    "addr:full":"Provincialewg 73 Veldhoven North Brabant 5503 HB",
    "addr:housenumber":"73",
    "addr:postcode":"5503 hb",
    "addr:street":"Provincialewg",
    "iso:country":"NL",
    "sg:address":"Provincialewg 73",
    "sg:city":"Veldhoven",
    "sg:orig_category":"Autosloperijen En Autodemontagebedrijven",
    "sg:phone":"+31 40 254 1261",
    "sg:postcode":"5503 HB",
    "sg:province":"North Brabant",
    "wof:name":"Hegru",
    "wof:placetype":"venue"
},
  "geometry": {"coordinates":[5.419338,51.414417],"type":"Point"}
}