{
  "type": "Feature",
  "properties": {
    "addr:full":"Ledeboerstraat 26 Tilburg Noord-Brabant 5048 AD",
    "addr:housenumber":"26",
    "addr:postcode":"5048 ad",
    "addr:street":"Ledeboerstraat",
    "iso:country":"NL",
    "sg:address":"Ledeboerstraat 26",
    "sg:city":"Tilburg",
    "sg:orig_category":"Granen, Zaden And Diervoeders Gh",
    "sg:phone":"+31 13 532 1401",
    "sg:postcode":"5048 AD",
    "sg:province":"Noord-Brabant",
    "wof:name":"Schouten Bv",
    "wof:placetype":"venue"
},
  "geometry": {"coordinates":[5.056038,51.58234],"type":"Point"}
}