{
  "type": "Feature",
  "properties": {
    "addr:full":"Molenwg 67 Rozenburg Zh Zuid-Holland 3181 AT",
    "addr:housenumber":"67",
    "addr:postcode":"zh;3181",
    "addr:street":"Molenwg",
    "iso:country":"NL",
    "sg:address":"Molenwg 67",
    "sg:city":"Rozenburg Zh",
    "sg:classifiers":[
        {
            "category":"Food & Beverages",
            "subcategory":"Bakery",
            "type":"Retail Goods"
        }
    ],
    "sg:phone":"+31 181 276 590",
    "sg:postcode":"3181 AT",
    "sg:province":"Zuid-Holland",
    "sg:tags":[
        "brood",
        "en",
        "banket"
    ],
    "wof:name":"Voskamp",
    "wof:placetype":"venue"
},
  "geometry": {"coordinates":[4.249517,51.904617],"type":"Point"}
}