{
  "type": "Feature",
  "properties": {
    "addr:full":"H Swarthln 3 Uithoorn Noord-Holland 1422 KE",
    "addr:housenumber":"3",
    "addr:postcode":"1422 ke",
    "iso:country":"NL",
    "sg:address":"H Swarthln 3",
    "sg:city":"Uithoorn",
    "sg:orig_category":"Artsen - Huisartsen",
    "sg:phone":"+31 297 561 813",
    "sg:postcode":"1422 KE",
    "sg:province":"Noord-Holland",
    "wof:name":"Padding, J",
    "wof:placetype":"venue"
},
  "geometry": {"coordinates":[4.828947,52.233421],"type":"Point"}
}