{
  "type": "Feature",
  "properties": {
    "addr:full":"Voltawg 12 Delft Zuid-Holland 2627 BB",
    "addr:housenumber":"12",
    "addr:postcode":"2627 bb",
    "addr:street":"Voltawg",
    "iso:country":"NL",
    "sg:address":"Voltawg 12",
    "sg:city":"Delft",
    "sg:orig_category":"Koffers En Tassen - Fabrieken En Groothandel",
    "sg:phone":"+31 15 257 4751",
    "sg:postcode":"2627 BB",
    "sg:province":"Zuid-Holland",
    "wof:name":"Protect Cases",
    "wof:placetype":"venue"
},
  "geometry": {"coordinates":[4.374037,51.983662],"type":"Point"}
}