{
  "type": "Feature",
  "properties": {
    "iso:country":"NL",
    "sg:address":"Benedenlangs 165",
    "sg:city":"Amsterdam",
    "sg:orig_category":"Vertaalbureaus",
    "sg:phone":"+31 20 634 0960",
    "sg:postcode":"1025 KE",
    "sg:province":"Noord-Holland",
    "wof:name":"Sisters-A Vof",
    "wof:placetype":"venue"
},
  "geometry": {"coordinates":[4.933671,52.397655],"type":"Point"}
}