{
  "type": "Feature",
  "properties": {
    "iso:country":"NL",
    "sg:address":"Gr Ansfriedstr 9",
    "sg:city":"Kerkdriel",
    "sg:orig_category":"Kappers",
    "sg:phone":"+31 418 631 279",
    "sg:postcode":"5331 BC",
    "sg:province":"Gelderland",
    "wof:name":"Nendels, L",
    "wof:placetype":"venue"
},
  "geometry": {"coordinates":[5.338841,51.773582],"type":"Point"}
}