{
  "type": "Feature",
  "properties": {
    "addr:full":"Topaasstraat 12 Hengelo Ov NL.08 7554 TH",
    "addr:housenumber":"12",
    "addr:postcode":"7554 th",
    "addr:street":"Topaasstraat;Ov",
    "iso:country":"NL",
    "sg:address":"Topaasstraat 12",
    "sg:city":"Hengelo Ov",
    "sg:orig_category":"Metaalbekleding And -Behandeling",
    "sg:phone":"+31 74 242 7033",
    "sg:postcode":"7554 TH",
    "sg:province":"NL.08",
    "wof:name":"Erdelt Hengelo",
    "wof:placetype":"venue"
},
  "geometry": {"coordinates":[6.777483,52.239178],"type":"Point"}
}