{
  "type": "Feature",
  "properties": {
    "addr:full":"Rivieradreef 52 Haarlem Noord-Holland 2037 AH",
    "addr:housenumber":"52",
    "addr:postcode":"2037 ah",
    "addr:street":"Rivieradreef",
    "iso:country":"NL",
    "sg:address":"Rivieradreef 52",
    "sg:city":"Haarlem",
    "sg:orig_category":"Schoenen",
    "sg:phone":"+31 23 533 4290",
    "sg:postcode":"2037 AH",
    "sg:province":"Noord-Holland",
    "wof:name":"Haren Bv, Van",
    "wof:placetype":"venue"
},
  "geometry": {"coordinates":[4.653694,52.357811],"type":"Point"}
}