{
  "type": "Feature",
  "properties": {
    "addr:full":"Kaap Hoornstroom 6 Huizen North Holland 1271 EL",
    "addr:housenumber":"6",
    "addr:postcode":"1271 el",
    "addr:street":"Kaap Hoornstroom",
    "iso:country":"NL",
    "sg:address":"Kaap Hoornstroom 6",
    "sg:city":"Huizen",
    "sg:orig_category":"Pleziervaartuigen And Reparatie",
    "sg:phone":"+31 35 524 4799",
    "sg:postcode":"1271 EL",
    "sg:province":"North Holland",
    "wof:name":"Jachtbouw De Graaf",
    "wof:placetype":"venue"
},
  "geometry": {"coordinates":[5.248339,52.308067],"type":"Point"}
}