{
  "type": "Feature",
  "properties": {
    "iso:country":"NL",
    "sg:address":"Luxemburgln 148",
    "sg:city":"Zoetermeer",
    "sg:orig_category":"Zoetwaren - Winkels",
    "sg:phone":"+31 79 342 7287",
    "sg:postcode":"2711 EH",
    "sg:province":"Zuid-Holland",
    "wof:name":"Jamin",
    "wof:placetype":"venue"
},
  "geometry": {"coordinates":[4.492053,52.06229],"type":"Point"}
}