{
  "type": "Feature",
  "properties": {
    "addr:full":"Valdk 9 Prinsenbeek Noord-Brabant 4841 AE",
    "addr:housenumber":"9",
    "addr:postcode":"4841 ae",
    "addr:street":"Valdk",
    "iso:country":"NL",
    "sg:address":"Valdk 9",
    "sg:city":"Prinsenbeek",
    "sg:orig_category":"Lichtbakken",
    "sg:phone":"+31 76 544 0660",
    "sg:postcode":"4841 AE",
    "sg:province":"Noord-Brabant",
    "wof:name":"M-Net",
    "wof:placetype":"venue"
},
  "geometry": {"coordinates":[4.719385,51.599464],"type":"Point"}
}