{
  "type": "Feature",
  "properties": {
    "addr:full":"Hoogstr 122B Eindhoven Noord-Brabant 5615 PV",
    "addr:housenumber":"122b",
    "addr:postcode":"5615 pv",
    "iso:country":"NL",
    "sg:address":"Hoogstr 122B",
    "sg:city":"Eindhoven",
    "sg:orig_category":"Adviesbureaus Bouwkunde",
    "sg:phone":"+31 40 255 5510",
    "sg:postcode":"5615 PV",
    "sg:province":"Noord-Brabant",
    "wof:name":"Weide, Van Der",
    "wof:placetype":"venue"
},
  "geometry": {"coordinates":[5.484105,51.434471],"type":"Point"}
}