{
  "type": "Feature",
  "properties": {
    "iso:country":"NL",
    "sg:address":"Amsweersterweg 6",
    "sg:city":"Meedhuizen",
    "sg:orig_category":"Beursorganisaties And Standbouw",
    "sg:phone":"+31 596 634 345",
    "sg:postcode":"9937 TD",
    "sg:province":"Groningen",
    "wof:name":"J.W.A. Dey",
    "wof:placetype":"venue"
},
  "geometry": {"coordinates":[6.903643,53.307346],"type":"Point"}
}