{
  "type": "Feature",
  "properties": {
    "addr:full":"Gansfoortstr 2 Vlaardingen Zuid-Holland 3132 EM",
    "addr:housenumber":"2",
    "addr:postcode":"3132 em",
    "addr:street":"Gansfoortstr",
    "iso:country":"NL",
    "sg:address":"Gansfoortstr 2",
    "sg:city":"Vlaardingen",
    "sg:orig_category":"Fotopersbureaus",
    "sg:phone":"+31 10 460 0808",
    "sg:postcode":"3132 EM",
    "sg:province":"Zuid-Holland",
    "wof:name":"Dijkstra, R",
    "wof:placetype":"venue"
},
  "geometry": {"coordinates":[4.313261,51.908825],"type":"Point"}
}