{
  "type": "Feature",
  "properties": {
    "addr:full":"Asselsestr 88 Apeldoorn Gelderland 7311 ER",
    "addr:housenumber":"88",
    "addr:postcode":"7311 er",
    "addr:street":"Asselsestr;Gelderland",
    "iso:country":"NL",
    "sg:address":"Asselsestr 88",
    "sg:city":"Apeldoorn",
    "sg:orig_category":"Warenhuizen",
    "sg:phone":"+31 55 522 3355",
    "sg:postcode":"7311 ER",
    "sg:province":"Gelderland",
    "wof:name":"Middelink",
    "wof:placetype":"venue"
},
  "geometry": {"coordinates":[5.9553728104,52.2130508423],"type":"Point"}
}