{
  "type": "Feature",
  "properties": {
    "iso:country":"NL",
    "sg:address":"Neringwg 386",
    "sg:city":"Lelystad",
    "sg:orig_category":"Schoenen - Reparaties",
    "sg:phone":"+31 320 230 751",
    "sg:postcode":"8224 KK",
    "sg:province":"Flevoland",
    "wof:name":"Boonstra",
    "wof:placetype":"venue"
},
  "geometry": {"coordinates":[5.477764,52.50602],"type":"Point"}
}