{
  "type": "Feature",
  "properties": {
    "addr:full":"Maasboulevard 148 Rotterdam Zuid-Holland 3011 TX",
    "addr:housenumber":"148",
    "addr:postcode":"3011 tx",
    "addr:street":"Maasboulevard",
    "iso:country":"NL",
    "sg:address":"Maasboulevard 148",
    "sg:city":"Rotterdam",
    "sg:orig_category":"Boekhouders",
    "sg:phone":"+31 10 413 7050",
    "sg:postcode":"3011 TX",
    "sg:province":"Zuid-Holland",
    "wof:name":"Proper-Stok Groep Bv",
    "wof:placetype":"venue"
},
  "geometry": {"coordinates":[4.498684,51.919918],"type":"Point"}
}