{
  "type": "Feature",
  "properties": {
    "iso:country":"NL",
    "sg:address":"Grt Kerkstr 35",
    "sg:city":"Edam",
    "sg:orig_category":"Scholen Voor Basisonderwijs",
    "sg:phone":"+31 299 374 242",
    "sg:postcode":"1135 BC",
    "sg:province":"North Holland",
    "wof:name":"Onderwijs Zieke Kinderen Amsterdam, Sticht",
    "wof:placetype":"venue"
},
  "geometry": {"coordinates":[5.048176,52.514389],"type":"Point"}
}