{
  "type": "Feature",
  "properties": {
    "addr:full":"Nieuwlandstr 36 Tilburg North Brabant 5038 SP",
    "addr:housenumber":"36",
    "addr:postcode":"5038 sp",
    "addr:street":"Nieuwlandstr",
    "iso:country":"NL",
    "sg:address":"Nieuwlandstr 36",
    "sg:city":"Tilburg",
    "sg:orig_category":"Kampeerartikelen",
    "sg:phone":"+31 13 543 3844",
    "sg:postcode":"5038 SP",
    "sg:province":"North Brabant",
    "wof:name":"American Store Outdoor Shop",
    "wof:placetype":"venue"
},
  "geometry": {"coordinates":[5.0823941231,51.5561981201],"type":"Point"}
}