{
  "type": "Feature",
  "properties": {
    "iso:country":"NL",
    "sg:address":"Citadelln 2A",
    "sg:city":"S Hertogenbosch",
    "sg:orig_category":"Kappers",
    "sg:phone":"+31 73 613 1639",
    "sg:postcode":"5211 XB",
    "sg:province":"North Brabant",
    "wof:name":"Up To Date, Herenkapsalon",
    "wof:placetype":"venue"
},
  "geometry": {"coordinates":[5.29824,51.69075],"type":"Point"}
}