{
  "type": "Feature",
  "properties": {
    "addr:full":"Westvest 229 Schiedam South Holland 3111 BT",
    "addr:housenumber":"229",
    "addr:postcode":"3111 bt",
    "addr:street":"Westvest",
    "iso:country":"NL",
    "sg:address":"Westvest 229",
    "sg:city":"Schiedam",
    "sg:orig_category":"Adviesbureaus Automatisering",
    "sg:phone":"+31 10 476 3843",
    "sg:postcode":"3111 BT",
    "sg:province":"South Holland",
    "wof:name":"Pro-Md",
    "wof:placetype":"venue"
},
  "geometry": {"coordinates":[4.395767,51.915112],"type":"Point"}
}