{
  "type": "Feature",
  "properties": {
    "addr:full":"Boveneind Zuidzijde 31 Benschop Utrecht 3405 AM",
    "addr:housenumber":"31",
    "addr:postcode":"3405",
    "addr:street":"Boveneind Zuidzijde",
    "iso:country":"NL",
    "sg:address":"Boveneind Zuidzijde 31",
    "sg:city":"Benschop",
    "sg:orig_category":"Landbouwmachines Gh",
    "sg:phone":"+31 348 451 844",
    "sg:postcode":"3405 AM",
    "sg:province":"Utrecht",
    "wof:name":"Landbouwmechanisatiebedrijf C. Van Beusekom Bv",
    "wof:placetype":"venue"
},
  "geometry": {"coordinates":[5.000506,52.010124],"type":"Point"}
}