{
  "type": "Feature",
  "properties": {
    "addr:full":"Hoofdweg 178 Rotterdam South Holland 3067 GJ",
    "addr:housenumber":"178",
    "addr:postcode":"3067 gj",
    "addr:street":"Hoofdweg",
    "iso:country":"NL",
    "sg:address":"Hoofdweg 178",
    "sg:city":"Rotterdam",
    "sg:classifiers":[
        {
            "category":"Professional",
            "subcategory":"Accounting & Tax Preparation",
            "type":"Services"
        }
    ],
    "sg:phone":"+31 10 421 2020",
    "sg:postcode":"3067 GJ",
    "sg:province":"South Holland",
    "sg:tags":[
        "accountant"
    ],
    "wof:name":"De Roo En Van Der Veen",
    "wof:placetype":"venue"
},
  "geometry": {"coordinates":[4.543058,51.94725],"type":"Point"}
}