{
  "type": "Feature",
  "properties": {
    "addr:full":"Industriew 1 Vorden Gelderland 7251 JT",
    "addr:housenumber":"1",
    "addr:postcode":"7251 jt",
    "addr:street":"Industriew;Gelderland",
    "iso:country":"NL",
    "sg:address":"Industriew 1",
    "sg:city":"Vorden",
    "sg:orig_category":"Elektrotechnische Artikelen",
    "sg:phone":"+31 575 551 564",
    "sg:postcode":"7251 JT",
    "sg:province":"Gelderland",
    "sg:website":"HTTP://www.jmv.nl",
    "wof:name":"Jmv",
    "wof:placetype":"venue"
},
  "geometry": {"coordinates":[6.324854,52.105896],"type":"Point"}
}