{
  "type": "Feature",
  "properties": {
    "addr:full":"Stevensbloem 163 Leiden Zuid-Holland 2331 JC",
    "addr:housenumber":"163",
    "addr:postcode":"2331 jc",
    "addr:street":"Stevensbloem",
    "iso:country":"NL",
    "sg:address":"Stevensbloem 163",
    "sg:city":"Leiden",
    "sg:orig_category":"Damesmodezaken",
    "sg:phone":"+31 71 576 0402",
    "sg:postcode":"2331 JC",
    "sg:province":"Zuid-Holland",
    "wof:name":"Panic Fashion",
    "wof:placetype":"venue"
},
  "geometry": {"coordinates":[4.453555,52.151554],"type":"Point"}
}