{
  "type": "Feature",
  "properties": {
    "addr:full":"Kiosk 116 Venray Limburg 5802 NT",
    "addr:housenumber":"116",
    "addr:postcode":"5802 nt",
    "iso:country":"NL",
    "sg:address":"Kiosk 116",
    "sg:city":"Venray",
    "sg:orig_category":"Scholen Voor Basisonderwijs",
    "sg:phone":"+31 478 550 270",
    "sg:postcode":"5802 NT",
    "sg:province":"Limburg",
    "wof:name":"Flierefluit, De",
    "wof:placetype":"venue"
},
  "geometry": {"coordinates":[5.993218,51.520084],"type":"Point"}
}