{
  "type": "Feature",
  "properties": {
    "addr:full":"Pampuslaan 161 Weesp Noord-Holland 1382 JP",
    "addr:housenumber":"161",
    "addr:postcode":"1382 jp",
    "addr:street":"Pampuslaan",
    "iso:country":"NL",
    "sg:address":"Pampuslaan 161",
    "sg:city":"Weesp",
    "sg:orig_category":"Farmaceutische Producten Gh",
    "sg:phone":"+31 294 450 033",
    "sg:postcode":"1382 JP",
    "sg:province":"Noord-Holland",
    "wof:name":"Van Vliet Medical Supply Bv",
    "wof:placetype":"venue"
},
  "geometry": {"coordinates":[5.024629,52.316528],"type":"Point"}
}