{
  "type": "Feature",
  "properties": {
    "addr:full":"Ringersweg 16 Bergen Op Zoom Noord-Brabant 4612 PT",
    "addr:housenumber":"16",
    "addr:postcode":"4612 pt",
    "addr:street":"Ringersweg",
    "iso:country":"NL",
    "sg:address":"Ringersweg 16",
    "sg:city":"Bergen Op Zoom",
    "sg:orig_category":"Fitnesscentra",
    "sg:phone":"+31 164 239 323",
    "sg:postcode":"4612 PT",
    "sg:province":"Noord-Brabant",
    "wof:name":"Tije Fitnesscentra Nederland Ten",
    "wof:placetype":"venue"
},
  "geometry": {"coordinates":[4.271902,51.507328],"type":"Point"}
}