{
  "type": "Feature",
  "properties": {
    "iso:country":"NL",
    "sg:address":"2E Morgen 9",
    "sg:city":"S Hertogenbosch",
    "sg:orig_category":"Adviesbureaus",
    "sg:phone":"+31 73 644 0030",
    "sg:postcode":"5233 NE",
    "sg:province":"Noord-Brabant",
    "sg:website":"http://www.technowise.nl",
    "wof:name":"Technowise",
    "wof:placetype":"venue"
},
  "geometry": {"coordinates":[5.310092,51.718166],"type":"Point"}
}