{
  "type": "Feature",
  "properties": {
    "iso:country":"NL",
    "sg:address":"Horndk 11A",
    "sg:city":"Loosdrecht",
    "sg:orig_category":"Jachthavens - Jachtwerven",
    "sg:phone":"+31 35 582 1503",
    "sg:postcode":"1231 NW",
    "sg:province":"Noord-Holland",
    "wof:name":"Horndijk",
    "wof:placetype":"venue"
},
  "geometry": {"coordinates":[5.068117,52.210724],"type":"Point"}
}