{
  "type": "Feature",
  "properties": {
    "iso:country":"NL",
    "sg:address":"Duindoorn 9",
    "sg:city":"Leidschendam",
    "sg:orig_category":"Kappers",
    "sg:phone":"+31 70 327 6500",
    "sg:postcode":"2262 AR",
    "sg:province":"South Holland",
    "sg:website":"http://www.mario-s.nl",
    "wof:name":"Mario",
    "wof:placetype":"venue"
},
  "geometry": {"coordinates":[4.383781,52.090237],"type":"Point"}
}