{
  "type": "Feature",
  "properties": {
    "addr:full":"Kapelstr 15 Prinsenbeek Noord-Brabant 4841 GE",
    "addr:housenumber":"15",
    "addr:postcode":"4841",
    "addr:street":"Kapelstr",
    "iso:country":"NL",
    "sg:address":"Kapelstr 15",
    "sg:city":"Prinsenbeek",
    "sg:orig_category":"Gelegenheidskleding",
    "sg:phone":"+31 76 541 0550",
    "sg:postcode":"4841 GE",
    "sg:province":"Noord-Brabant",
    "wof:name":"Brands, Ronald",
    "wof:placetype":"venue"
},
  "geometry": {"coordinates":[4.717339,51.601074],"type":"Point"}
}