{
  "type": "Feature",
  "properties": {
    "iso:country":"NL",
    "sg:address":"4E Binnenvestgracht 27",
    "sg:city":"Leiden",
    "sg:orig_category":"Algemene Werktuigbouw",
    "sg:phone":"+31 71 513 0243",
    "sg:postcode":"2311 NV",
    "sg:province":"Zuid-Holland",
    "wof:name":"M.H. Van Tongeren",
    "wof:placetype":"venue"
},
  "geometry": {"coordinates":[4.499398,52.154236],"type":"Point"}
}