{
  "type": "Feature",
  "properties": {
    "iso:country":"NL",
    "sg:address":"Stationswg 72",
    "sg:city":"Drachten",
    "sg:orig_category":"Administratie- En Boekhoudkantoren",
    "sg:phone":"+31 512 546 499",
    "sg:postcode":"9201 GR",
    "sg:province":"Friesland",
    "wof:name":"Meijer",
    "wof:placetype":"venue"
},
  "geometry": {"coordinates":[6.097208,53.112152],"type":"Point"}
}