{
  "type": "Feature",
  "properties": {
    "addr:full":"Sint Maartensweg 40 Sint Maartensvlotbrug Noord-Holland 1753 BK",
    "addr:housenumber":"40",
    "addr:postcode":"1753 bk",
    "addr:street":"Sint Maartensweg",
    "iso:country":"NL",
    "sg:address":"Sint Maartensweg 40",
    "sg:city":"Sint Maartensvlotbrug",
    "sg:orig_category":"Kampeerterreinen",
    "sg:phone":"+31 224 561 318",
    "sg:postcode":"1753 BK",
    "sg:province":"Noord-Holland",
    "wof:name":"De Rusthoeve",
    "wof:placetype":"venue"
},
  "geometry": {"coordinates":[4.7121911049,52.7848205566],"type":"Point"}
}