{
  "type": "Feature",
  "properties": {
    "addr:full":"Abelenln 114A Rozenburg Zh South Holland 3181 WH",
    "addr:housenumber":"114a",
    "addr:postcode":"zh;3181 wh",
    "iso:country":"NL",
    "sg:address":"Abelenln 114A",
    "sg:city":"Rozenburg Zh",
    "sg:orig_category":"Organisatiebureaus",
    "sg:phone":"+31 181 290 677",
    "sg:postcode":"3181 WH",
    "sg:province":"South Holland",
    "wof:name":"Eph",
    "wof:placetype":"venue"
},
  "geometry": {"coordinates":[4.2552552223,51.9039344788],"type":"Point"}
}