{
  "type": "Feature",
  "properties": {
    "addr:full":"Golfresidentie 59 Dronten Flevoland 8251 NK",
    "addr:housenumber":"59",
    "addr:postcode":"8251 nk",
    "addr:street":"Golfresidentie;Flevoland",
    "iso:country":"NL",
    "sg:address":"Golfresidentie 59",
    "sg:city":"Dronten",
    "sg:orig_category":"Luchtvrachtexpediteurs",
    "sg:phone":"+31 321 338 403",
    "sg:postcode":"8251 NK",
    "sg:province":"Flevoland",
    "sg:website":"http://www.aircargo.nl",
    "wof:name":"Aircargo Bv",
    "wof:placetype":"venue"
},
  "geometry": {"coordinates":[5.720501,52.505215],"type":"Point"}
}