{
  "type": "Feature",
  "properties": {
    "addr:full":"W Prins Passage 54 Veendam Groningen 9641 DA",
    "addr:housenumber":"54",
    "addr:postcode":"9641 da",
    "addr:street":"W Prins Passage",
    "iso:country":"NL",
    "sg:address":"W Prins Passage 54",
    "sg:city":"Veendam",
    "sg:orig_category":"Orthopedisch Schoeisel",
    "sg:phone":"+31 598 635 021",
    "sg:postcode":"9641 DA",
    "sg:province":"Groningen",
    "wof:name":"Doc",
    "wof:placetype":"venue"
},
  "geometry": {"coordinates":[6.8804421425,53.106426239],"type":"Point"}
}