{
  "type": "Feature",
  "properties": {
    "addr:full":"Stationsstr 19 Best Noord-Brabant 5683 BA",
    "addr:housenumber":"19",
    "addr:postcode":"5683 ba",
    "addr:street":"Stationsstr",
    "iso:country":"NL",
    "sg:address":"Stationsstr 19",
    "sg:city":"Best",
    "sg:classifiers":[
        {
            "category":"Travel",
            "subcategory":"Hotels & Motels",
            "type":"Entertainment"
        }
    ],
    "sg:phone":"+31 499 338 228",
    "sg:postcode":"5683 BA",
    "sg:province":"Noord-Brabant",
    "wof:name":"Witlox Best",
    "wof:placetype":"venue"
},
  "geometry": {"coordinates":[-101.618134,31.224251],"type":"Point"}
}