{
  "type": "Feature",
  "properties": {
    "addr:full":"Copernicusweg 4 Bunschoten Spakenburg Utrecht 3752 LZ",
    "addr:housenumber":"4",
    "addr:postcode":"3752 lz",
    "addr:street":"Copernicusweg",
    "iso:country":"NL",
    "sg:address":"Copernicusweg 4",
    "sg:city":"Bunschoten Spakenburg",
    "sg:orig_category":"Vers Brood And Banket Fab",
    "sg:phone":"+31 33 298 1361",
    "sg:postcode":"3752 LZ",
    "sg:province":"Utrecht",
    "wof:name":"Muijs Banket",
    "wof:placetype":"venue"
},
  "geometry": {"coordinates":[5.368977,52.230255],"type":"Point"}
}