{
  "type": "Feature",
  "properties": {
    "iso:country":"NL",
    "sg:address":"W Doorsnee Nz 122",
    "sg:city":"Emmer Compascuum",
    "sg:orig_category":"Grondwerken",
    "sg:phone":"+31 591 354 388",
    "sg:postcode":"7881 PE",
    "sg:province":"Drenthe",
    "wof:name":"Klok, A",
    "wof:placetype":"venue"
},
  "geometry": {"coordinates":[170.36663799999999,-43.587711],"type":"Point"}
}