{
  "type": "Feature",
  "properties": {
    "addr:full":"Stationsweg 8 Harlingen Friesland 8861 GA",
    "addr:housenumber":"8",
    "addr:postcode":"8861 ga",
    "addr:street":"Stationsweg",
    "iso:country":"NL",
    "sg:address":"Stationsweg 8",
    "sg:city":"Harlingen",
    "sg:orig_category":"Autokeuringen",
    "sg:phone":"+31 517 420 004",
    "sg:postcode":"8861 GA",
    "sg:province":"Friesland",
    "wof:name":"Tankstation Harlingen",
    "wof:placetype":"venue"
},
  "geometry": {"coordinates":[5.426871,53.170742],"type":"Point"}
}