{
  "type": "Feature",
  "properties": {
    "addr:full":"Birkstr 99 Soest Utrecht 3768 HD",
    "addr:housenumber":"99",
    "addr:postcode":"3768 hd",
    "addr:street":"Birkstr",
    "iso:country":"NL",
    "sg:address":"Birkstr 99",
    "sg:city":"Soest",
    "sg:orig_category":"Meubelen",
    "sg:phone":"+31 35 601 1004",
    "sg:postcode":"3768 HD",
    "sg:province":"Utrecht",
    "sg:website":"http://www.middelman-wonen.nl",
    "wof:name":"Middelman Wonen",
    "wof:placetype":"venue"
},
  "geometry": {"coordinates":[5.313858,52.162312],"type":"Point"}
}