{
  "type": "Feature",
  "properties": {
    "addr:full":"Noordeinde 5 Dalfsen NL.08 7722 XG",
    "addr:housenumber":"5;nl.08",
    "addr:postcode":"7722 xg",
    "addr:street":"Noordeinde",
    "iso:country":"NL",
    "sg:address":"Noordeinde 5",
    "sg:city":"Dalfsen",
    "sg:orig_category":"Wasmachines En Wasdrogers - Onderhoud En Reparatie",
    "sg:phone":"+31 529 427 366",
    "sg:postcode":"7722 XG",
    "sg:province":"NL.08",
    "wof:name":"Leda Sound",
    "wof:placetype":"venue"
},
  "geometry": {"coordinates":[6.2020449638,52.5468330383],"type":"Point"}
}