{
  "type": "Feature",
  "properties": {
    "addr:full":"Beukstraat 129 'S Gravenhage Zuid-Holland 2565 XZ",
    "addr:housenumber":"129 '",
    "addr:postcode":"2565 xz",
    "addr:street":"Beukstraat",
    "iso:country":"NL",
    "sg:address":"Beukstraat 129",
    "sg:city":"'S Gravenhage",
    "sg:orig_category":"Schilderwerk",
    "sg:phone":"+31 70 363 2169",
    "sg:postcode":"2565 XZ",
    "sg:province":"Zuid-Holland",
    "wof:name":"Schildersbedrijf J.H. De Gier",
    "wof:placetype":"venue"
},
  "geometry": {"coordinates":[4.270525,52.078548],"type":"Point"}
}