{
  "type": "Feature",
  "properties": {
    "iso:country":"NL",
    "sg:address":"Liesbosstr 16",
    "sg:city":"Breda",
    "sg:orig_category":"Handwerkartikelen",
    "sg:phone":"+31 76 514 3012",
    "sg:postcode":"4813 BD",
    "sg:province":"Noord-Brabant",
    "wof:name":"Scandinavia Handwerken",
    "wof:placetype":"venue"
},
  "geometry": {"coordinates":[4.73776,51.577457],"type":"Point"}
}