{
  "type": "Feature",
  "properties": {
    "addr:full":"Willem 2 Sngl 4 Roermond Limburg 6041 HS",
    "addr:housenumber":"2;4",
    "addr:postcode":"6041 hs",
    "addr:street":"Willem;Sngl",
    "iso:country":"NL",
    "sg:address":"Willem 2 Sngl 4",
    "sg:city":"Roermond",
    "sg:orig_category":"Notarissen En Notariskantoren",
    "sg:phone":"+31 475 351 919",
    "sg:postcode":"6041 HS",
    "sg:province":"Limburg",
    "wof:name":"Hecke Houben & Urlings Notarissen, Van",
    "wof:placetype":"venue"
},
  "geometry": {"coordinates":[5.992098,51.191978],"type":"Point"}
}