{
  "type": "Feature",
  "properties": {
    "iso:country":"NL",
    "sg:address":"Anton Mauvestraat 3",
    "sg:city":"Amersfoort",
    "sg:orig_category":"Diverse Opleidingen And Onderwijs",
    "sg:phone":"+31 33 465 4133",
    "sg:postcode":"3817 DL",
    "sg:province":"Utrecht",
    "wof:name":"Alliance Francaise Amersfoort",
    "wof:placetype":"venue"
},
  "geometry": {"coordinates":[5.392187,52.148403],"type":"Point"}
}