{
  "type": "Feature",
  "properties": {
    "addr:full":"Korte Leidsedwarsstraat 77 Amsterdam Noord-Holland 1017 PW",
    "addr:housenumber":"77",
    "addr:postcode":"1017 pw",
    "addr:street":"Korte Leidsedwarsstraat",
    "iso:country":"NL",
    "sg:address":"Korte Leidsedwarsstraat 77",
    "sg:city":"Amsterdam",
    "sg:orig_category":"Biljart- And Snookerzalen",
    "sg:phone":"+31 20 420 1512",
    "sg:postcode":"1017 PW",
    "sg:province":"Noord-Holland",
    "wof:name":"Poolcafe Coffeeshop Get Down To It",
    "wof:placetype":"venue"
},
  "geometry": {"coordinates":[4.883928,52.36401],"type":"Point"}
}