{
  "type": "Feature",
  "properties": {
    "addr:full":"Bargermeerwg 10 Emmen Drenthe 7811 LC",
    "addr:housenumber":"10",
    "addr:postcode":"7811 lc",
    "addr:street":"Bargermeerwg",
    "iso:country":"NL",
    "sg:address":"Bargermeerwg 10",
    "sg:city":"Emmen",
    "sg:orig_category":"Woningstoffeerders",
    "sg:phone":"+31 591 642 496",
    "sg:postcode":"7811 LC",
    "sg:province":"Drenthe",
    "wof:name":"Trend-Vloer",
    "wof:placetype":"venue"
},
  "geometry": {"coordinates":[6.8992938995,52.7756347656],"type":"Point"}
}