{
  "type": "Feature",
  "properties": {
    "addr:full":"Elleboog 10 Ede Gld Gelderland 6713 KP",
    "addr:housenumber":"10",
    "addr:postcode":"6713 kp",
    "addr:street":"Elleboog;Gld Gelderland",
    "iso:country":"NL",
    "sg:address":"Elleboog 10",
    "sg:city":"Ede Gld",
    "sg:orig_category":"Werving And Selectie Van Tijdelijk Personeel And Uitzendkantoren",
    "sg:phone":"+31 318 630 206",
    "sg:postcode":"6713 KP",
    "sg:province":"Gelderland",
    "wof:name":"Ltb",
    "wof:placetype":"venue"
},
  "geometry": {"coordinates":[5.652012825,52.0329322815],"type":"Point"}
}