{
  "type": "Feature",
  "properties": {
    "addr:full":"Gashavenstr 53009 Deventer NL.08 7418 AL",
    "addr:postcode":"53009;nl.08 7418 al",
    "addr:street":"Gashavenstr",
    "iso:country":"NL",
    "sg:address":"Gashavenstr 53009",
    "sg:city":"Deventer",
    "sg:orig_category":"Sportverenigingen En Ontspannings- Verenigingen",
    "sg:phone":"+31 570 632 292",
    "sg:postcode":"7418 AL",
    "sg:province":"NL.08",
    "wof:name":"Dkv Kanover",
    "wof:placetype":"venue"
},
  "geometry": {"coordinates":[6.16691,52.243481],"type":"Point"}
}