{
  "type": "Feature",
  "properties": {
    "addr:full":"V Rietln 19 Linschoten Utrecht 3461 HW",
    "addr:housenumber":"19",
    "addr:postcode":"3461 hw",
    "iso:country":"NL",
    "sg:address":"V Rietln 19",
    "sg:city":"Linschoten",
    "sg:orig_category":"Adviesbureaus Bedrijfsorganisatie",
    "sg:phone":"+31 348 490 008",
    "sg:postcode":"3461 HW",
    "sg:province":"Utrecht",
    "sg:website":"http://www.castleandgreen.com",
    "wof:name":"Castle & Green Bv",
    "wof:placetype":"venue"
},
  "geometry": {"coordinates":[4.915227,52.061867],"type":"Point"}
}