{
  "type": "Feature",
  "properties": {
    "iso:country":"NL",
    "sg:address":"Driehoekstr 10",
    "sg:city":"Amsterdam",
    "sg:orig_category":"Gedistilleerd En Likeuren - Fabrieken",
    "sg:phone":"+31 20 626 6860",
    "sg:postcode":"1015 GL",
    "sg:province":"Noord-Holland",
    "wof:name":"Ooievaar, De",
    "wof:placetype":"venue"
},
  "geometry": {"coordinates":[4.883176,52.382675],"type":"Point"}
}