{
  "type": "Feature",
  "properties": {
    "addr:full":"Putstr 34 Sittard Limburg 6131 HL",
    "addr:housenumber":"34",
    "addr:postcode":"6131 hl",
    "addr:street":"Putstr",
    "iso:country":"NL",
    "sg:address":"Putstr 34",
    "sg:city":"Sittard",
    "sg:orig_category":"Kunstenaars- Benodigdheden",
    "sg:phone":"+31 46 458 6327",
    "sg:postcode":"6131 HL",
    "sg:province":"Limburg",
    "wof:name":"Artex Bv",
    "wof:placetype":"venue"
},
  "geometry": {"coordinates":[5.872654,50.99733],"type":"Point"}
}