{
  "type": "Feature",
  "properties": {
    "iso:country":"NL",
    "sg:address":"Voorstr 10",
    "sg:city":"Klaaswaal",
    "sg:orig_category":"Fietsen En Bromfietsen",
    "sg:phone":"+31 186 571 309",
    "sg:postcode":"3286 AX",
    "sg:province":"Zuid-Holland",
    "wof:name":"Lijster Vof, De",
    "wof:placetype":"venue"
},
  "geometry": {"coordinates":[4.445482,51.768269],"type":"Point"}
}