{
  "type": "Feature",
  "properties": {
    "addr:full":"Frieswijkerweg 10 Schalkhaar Overijssel 7433 RB",
    "addr:housenumber":"10",
    "addr:postcode":"7433 rb",
    "addr:street":"Frieswijkerweg",
    "iso:country":"NL",
    "sg:address":"Frieswijkerweg 10",
    "sg:city":"Schalkhaar",
    "sg:orig_category":"Goederenvervoer Over De Weg",
    "sg:phone":"+31 570 532 055",
    "sg:postcode":"7433 RB",
    "sg:province":"Overijssel",
    "wof:name":"Gebroeders Poll Bv",
    "wof:placetype":"venue"
},
  "geometry": {"coordinates":[6.203008,52.283409],"type":"Point"}
}