{
  "type": "Feature",
  "properties": {
    "addr:full":"V Veldekeln 36 Roosendaal Noord-Brabant 4707 AJ",
    "addr:housenumber":"36",
    "addr:postcode":"4707 aj",
    "iso:country":"NL",
    "sg:address":"V Veldekeln 36",
    "sg:city":"Roosendaal",
    "sg:orig_category":"Meubelen Gebruikte",
    "sg:phone":"+31 165 391 362",
    "sg:postcode":"4707 AJ",
    "sg:province":"Noord-Brabant",
    "wof:name":"Bronk Meubelen",
    "wof:placetype":"venue"
},
  "geometry": {"coordinates":[4.45767,51.531403],"type":"Point"}
}