{
  "type": "Feature",
  "properties": {
    "addr:full":"Zuidpln Hg 843 Rotterdam South Holland 3083 BK",
    "addr:housenumber":"843",
    "addr:postcode":"3083 bk",
    "addr:street":"Hg",
    "iso:country":"NL",
    "sg:address":"Zuidpln Hg 843",
    "sg:city":"Rotterdam",
    "sg:orig_category":"Huishoudelijke Apparaten En Artikelen",
    "sg:phone":"+31 10 480 7921",
    "sg:postcode":"3083 BK",
    "sg:province":"South Holland",
    "wof:name":"Blokker Bv",
    "wof:placetype":"venue"
},
  "geometry": {"coordinates":[4.490526,51.886951],"type":"Point"}
}