{
  "type": "Feature",
  "properties": {
    "addr:full":"Hoge Brake 18 Nuenen Noord-Brabant 5672 GL",
    "addr:housenumber":"18",
    "addr:postcode":"5672 gl",
    "addr:street":"Hoge Brake",
    "iso:country":"NL",
    "sg:address":"Hoge Brake 18",
    "sg:city":"Nuenen",
    "sg:orig_category":"Banken And Kredietinstellingen",
    "sg:phone":"+31 40 283 2420",
    "sg:postcode":"5672 GL",
    "sg:province":"Noord-Brabant",
    "wof:name":"Rabobank",
    "wof:placetype":"venue"
},
  "geometry": {"coordinates":[5.549164,51.464722],"type":"Point"}
}