{
  "type": "Feature",
  "properties": {
    "iso:country":"NL",
    "sg:address":"Hoge Brake 18",
    "sg:city":"Nuenen",
    "sg:orig_category":"Banken And Kredietinstellingen",
    "sg:phone":"+31 40 283 2420",
    "sg:postcode":"5672 GL",
    "sg:province":"Noord-Brabant",
    "wof:name":"Rabobank",
    "wof:placetype":"venue"
},
  "geometry": {"coordinates":[5.549164,51.464722],"type":"Point"}
}