{
  "type": "Feature",
  "properties": {
    "addr:full":"Grotestraat 9 Raalte Overijssel 8102 CD",
    "addr:housenumber":"9",
    "addr:postcode":"8102 cd",
    "addr:street":"Grotestraat",
    "iso:country":"NL",
    "sg:address":"Grotestraat 9",
    "sg:city":"Raalte",
    "sg:orig_category":"Schoenen",
    "sg:phone":"+31 572 354 312",
    "sg:postcode":"8102 CD",
    "sg:province":"Overijssel",
    "wof:name":"Schoenenreus Bv",
    "wof:placetype":"venue"
},
  "geometry": {"coordinates":[6.275475,52.385124],"type":"Point"}
}