{
  "type": "Feature",
  "properties": {
    "iso:country":"NL",
    "sg:address":"Meint Veningastraat 11",
    "sg:city":"Hoogezand",
    "sg:classifiers":[
        {
            "category":"Food & Beverages",
            "subcategory":"Fruits & Vegetables",
            "type":"Retail Goods"
        }
    ],
    "sg:phone":"+31 598 396 979",
    "sg:postcode":"9601 KC",
    "sg:province":"Groningen",
    "sg:tags":[
        "groenten"
    ],
    "wof:name":"Groente- En Fruithal Martenshoek",
    "wof:placetype":"venue"
},
  "geometry": {"coordinates":[6.74202,53.162926],"type":"Point"}
}