{
  "type": "Feature",
  "properties": {
    "iso:country":"NL",
    "sg:address":"Heemraadssingel 168",
    "sg:city":"Rotterdam",
    "sg:orig_category":"Verzekeringen",
    "sg:phone":"+31 10 477 9077",
    "sg:postcode":"3021 DL",
    "sg:province":"Zuid-Holland",
    "wof:name":"Bureau Verhulst En Van Der Pol Bv",
    "wof:placetype":"venue"
},
  "geometry": {"coordinates":[4.455983,51.91618],"type":"Point"}
}