{
  "type": "Feature",
  "properties": {
    "iso:country":"NL",
    "sg:address":"A Cuypstr 158",
    "sg:city":"Amsterdam",
    "sg:orig_category":"Koffie- En Theehuizen",
    "sg:phone":"+31 20 679 0849",
    "sg:postcode":"1073 BK",
    "sg:province":"Noord-Holland",
    "wof:name":"Wijnands",
    "wof:placetype":"venue"
},
  "geometry": {"coordinates":[4.894604,52.355656],"type":"Point"}
}