{
  "type": "Feature",
  "properties": {
    "iso:country":"NL",
    "sg:address":"Zwartewaterallee 20",
    "sg:city":"Zwolle",
    "sg:orig_category":"Ziekenhuizen, Sanatoria, Verpleeghuizen",
    "sg:phone":"+31 38 454 0333",
    "sg:postcode":"8031 DX",
    "sg:province":"NL.08",
    "wof:name":"Zorgcombinatie Zwolle",
    "wof:placetype":"venue"
},
  "geometry": {"coordinates":[6.09409,52.523006],"type":"Point"}
}