{
  "type": "Feature",
  "properties": {
    "addr:full":"Jacoba Van Beierenlaan 143 Delft Zuid-Holland 2613 JD",
    "addr:housenumber":"143",
    "addr:postcode":"2613 jd",
    "addr:street":"Jacoba Van Beierenlaan",
    "iso:country":"NL",
    "sg:address":"Jacoba Van Beierenlaan 143",
    "sg:city":"Delft",
    "sg:orig_category":"Architecten",
    "sg:phone":"+31 15 215 7868",
    "sg:postcode":"2613 JD",
    "sg:province":"Zuid-Holland",
    "wof:name":"Veltman Bouwkundig Ontwerp- En Tekenburo",
    "wof:placetype":"venue"
},
  "geometry": {"coordinates":[4.349847,52.001762],"type":"Point"}
}