{
  "type": "Feature",
  "properties": {
    "addr:full":"Oosthavenkade 14 Vlaardingen Zuid-Holland 3134 NV",
    "addr:housenumber":"14",
    "addr:postcode":"3134 nv",
    "addr:street":"Oosthavenkade",
    "iso:country":"NL",
    "sg:address":"Oosthavenkade 14",
    "sg:city":"Vlaardingen",
    "sg:orig_category":"Loodgieterswerk, Verwarming And Sanitaire Installaties",
    "sg:phone":"+31 10 434 3213",
    "sg:postcode":"3134 NV",
    "sg:province":"Zuid-Holland",
    "wof:name":"H. Van Kooy'S Loodgietersbedrijf Bv",
    "wof:placetype":"venue"
},
  "geometry": {"coordinates":[4.345076,51.908676],"type":"Point"}
}