{
  "type": "Feature",
  "properties": {
    "addr:full":"Groene Tuin 1 Rotterdam Zuid-Holland 3078 KA",
    "addr:housenumber":"1",
    "addr:postcode":"3078 ka",
    "addr:street":"Groene Tuin",
    "iso:country":"NL",
    "sg:address":"Groene Tuin 1",
    "sg:city":"Rotterdam",
    "sg:orig_category":"Bejaarden - Verzorgingstehuizen",
    "sg:phone":"+31 10 479 8798",
    "sg:postcode":"3078 KA",
    "sg:province":"Zuid-Holland",
    "wof:name":"Kvv Rotterdam, Sticht",
    "wof:placetype":"venue"
},
  "geometry": {"coordinates":[4.552997,51.888035],"type":"Point"}
}