{
  "type": "Feature",
  "properties": {
    "iso:country":"NL",
    "sg:address":"1E Gr V Loonstr 11",
    "sg:city":"Venlo",
    "sg:orig_category":"Kaas",
    "sg:phone":"+31 77 387 2039",
    "sg:postcode":"5921 JA",
    "sg:province":"Limburg",
    "wof:name":"Holland Kaascentr",
    "wof:placetype":"venue"
},
  "geometry": {"coordinates":[6.152613163,51.3677062988],"type":"Point"}
}