{
  "type": "Feature",
  "properties": {
    "addr:full":"1E Gr V Loonstr 11 Venlo Limburg 5921 JA",
    "addr:housenumber":"11",
    "addr:postcode":"5921 ja",
    "addr:street":"1E Gr V Loonstr",
    "iso:country":"NL",
    "sg:address":"1E Gr V Loonstr 11",
    "sg:city":"Venlo",
    "sg:orig_category":"Kaas",
    "sg:phone":"+31 77 387 2039",
    "sg:postcode":"5921 JA",
    "sg:province":"Limburg",
    "wof:name":"Holland Kaascentr",
    "wof:placetype":"venue"
},
  "geometry": {"coordinates":[6.152613163,51.3677062988],"type":"Point"}
}