{
  "type": "Feature",
  "properties": {
    "addr:full":"Graspieper 55 Ijsselmuiden Overijssel 8271 GZ",
    "addr:housenumber":"55",
    "addr:postcode":"8271 gz",
    "addr:street":"Graspieper",
    "iso:country":"NL",
    "sg:address":"Graspieper 55",
    "sg:city":"Ijsselmuiden",
    "sg:orig_category":"Metaalwerken",
    "sg:phone":"+31 38 332 3750",
    "sg:postcode":"8271 GZ",
    "sg:province":"Overijssel",
    "wof:name":"Hk Vof",
    "wof:placetype":"venue"
},
  "geometry": {"coordinates":[5.945488,52.568325],"type":"Point"}
}