{
  "type": "Feature",
  "properties": {
    "addr:full":"Zwaluwln 44 Bergschenhoek Zuid-Holland 2661 BS",
    "addr:housenumber":"44",
    "addr:postcode":"2661 bs",
    "addr:street":"Zwaluwln",
    "iso:country":"NL",
    "sg:address":"Zwaluwln 44",
    "sg:city":"Bergschenhoek",
    "sg:orig_category":"Kantoor- En Secretariaatsservice",
    "sg:phone":"+31 10 522 3518",
    "sg:postcode":"2661 BS",
    "sg:province":"Zuid-Holland",
    "wof:name":"Mlt Ned",
    "wof:placetype":"venue"
},
  "geometry": {"coordinates":[4.5001330376,51.9895362854],"type":"Point"}
}