{
  "type": "Feature",
  "properties": {
    "addr:full":"J Friso Promenade 63 Ryswyk Zh Zuid-Holland 2284 DE",
    "addr:housenumber":"63",
    "addr:postcode":"2284 de",
    "addr:street":"Friso Promenade",
    "iso:country":"NL",
    "sg:address":"J Friso Promenade 63",
    "sg:city":"Ryswyk Zh",
    "sg:orig_category":"Warenhuizen",
    "sg:phone":"+31 70 394 0112",
    "sg:postcode":"2284 DE",
    "sg:province":"Zuid-Holland",
    "wof:name":"Xenos Bv",
    "wof:placetype":"venue"
},
  "geometry": {"coordinates":[4.3243598938,52.0372505188],"type":"Point"}
}