{
  "type": "Feature",
  "properties": {
    "addr:full":"Schreiershoek 3 Leek Groningen 9351 AE",
    "addr:housenumber":"3",
    "addr:postcode":"9351 ae",
    "addr:street":"Schreiershoek",
    "iso:country":"NL",
    "sg:address":"Schreiershoek 3",
    "sg:city":"Leek",
    "sg:orig_category":"Warenhuizen",
    "sg:phone":"+31 594 580 662",
    "sg:postcode":"9351 AE",
    "sg:province":"Groningen",
    "sg:website":"http://www.action-shop.nl",
    "wof:name":"Action",
    "wof:placetype":"venue"
},
  "geometry": {"coordinates":[6.3936319351,53.1629943848],"type":"Point"}
}