{
  "type": "Feature",
  "properties": {
    "addr:full":"Mr P S Gerbrandysingel 35 Arnhem Gelderland 6836 KS",
    "addr:housenumber":"35",
    "addr:postcode":"6836 ks",
    "addr:street":"Mr P S Gerbrandysingel",
    "iso:country":"NL",
    "sg:address":"Mr P S Gerbrandysingel 35",
    "sg:city":"Arnhem",
    "sg:orig_category":"Huishoudapparatuur, Televisies And Radio'S",
    "sg:phone":"+31 26 323 2661",
    "sg:postcode":"6836 KS",
    "sg:province":"Gelderland",
    "wof:name":"J.R. Willems",
    "wof:placetype":"venue"
},
  "geometry": {"coordinates":[5.898197,51.942619],"type":"Point"}
}