{
  "type": "Feature",
  "properties": {
    "addr:full":"Strawinskyln 3035 Amsterdam North Holland 1077 ZX",
    "addr:housenumber":"3035",
    "addr:postcode":"1077 zx",
    "iso:country":"NL",
    "sg:address":"Strawinskyln 3035",
    "sg:city":"Amsterdam",
    "sg:orig_category":"Beleggingen",
    "sg:phone":"+31 20 504 0330",
    "sg:postcode":"1077 ZX",
    "sg:province":"North Holland",
    "wof:name":"Flemings Ned Bv",
    "wof:placetype":"venue"
},
  "geometry": {"coordinates":[4.869435,52.340435],"type":"Point"}
}