{
  "type": "Feature",
  "properties": {
    "iso:country":"NL",
    "sg:address":"Houtwg 12",
    "sg:city":"Oene",
    "sg:orig_category":"Banken",
    "sg:phone":"+31 578 641 751",
    "sg:postcode":"8167 PL",
    "sg:province":"Gelderland",
    "sg:website":"http://www.rabobank.nl",
    "wof:name":"Rabobank",
    "wof:placetype":"venue"
},
  "geometry": {"coordinates":[6.04966,52.344196],"type":"Point"}
}