{
  "type": "Feature",
  "properties": {
    "addr:full":"Groenseykerstr 19 Geleen Limburg 6161 SC",
    "addr:housenumber":"19",
    "addr:postcode":"6161 sc",
    "addr:street":"Groenseykerstr",
    "iso:country":"NL",
    "sg:address":"Groenseykerstr 19",
    "sg:city":"Geleen",
    "sg:orig_category":"Huishoudelijke Apparaten En Artikelen",
    "sg:phone":"+31 46 474 3063",
    "sg:postcode":"6161 SC",
    "sg:province":"Limburg",
    "sg:website":"http://www.twice-merchandise.nl",
    "wof:name":"Twice-Merchandise",
    "wof:placetype":"venue"
},
  "geometry": {"coordinates":[5.821259,50.970024],"type":"Point"}
}