{
  "type": "Feature",
  "properties": {
    "addr:full":"Soendaplein 37 Haarlem North Holland 2023 TT",
    "addr:housenumber":"37",
    "addr:postcode":"2023 tt",
    "addr:street":"Soendaplein",
    "iso:country":"NL",
    "sg:address":"Soendaplein 37",
    "sg:city":"Haarlem",
    "sg:orig_category":"Wasserettes And Stomerijen",
    "sg:phone":"+31 23 525 5661",
    "sg:postcode":"2023 TT",
    "sg:province":"North Holland",
    "wof:name":"Bv Rappinette Soendaplein",
    "wof:placetype":"venue"
},
  "geometry": {"coordinates":[4.6441459656,52.3994827271],"type":"Point"}
}