{
  "type": "Feature",
  "properties": {
    "iso:country":"NL",
    "sg:address":"Hoefkd 698",
    "sg:city":"S Gravenhage",
    "sg:orig_category":"Grafisch Ontwerpers",
    "sg:phone":"+31 70 392 5359",
    "sg:postcode":"2526 CP",
    "sg:province":"South Holland",
    "wof:name":"Ontwerp Burolamp",
    "wof:placetype":"venue"
},
  "geometry": {"coordinates":[4.30555,52.0681],"type":"Point"}
}