{
  "type": "Feature",
  "properties": {
    "addr:full":"Merendreef 22 Valkenswaard Noord-Brabant 5553 CD",
    "addr:housenumber":"22",
    "addr:postcode":"5553 cd",
    "addr:street":"Merendreef",
    "iso:country":"NL",
    "sg:address":"Merendreef 22",
    "sg:city":"Valkenswaard",
    "sg:orig_category":"Octrooigemachtigden- Bureaus",
    "sg:phone":"+31 40 201 2821",
    "sg:postcode":"5553 CD",
    "sg:province":"Noord-Brabant",
    "wof:name":"Flik, Drs R J",
    "wof:placetype":"venue"
},
  "geometry": {"coordinates":[5.4683041573,51.3607177734],"type":"Point"}
}