{
  "type": "Feature",
  "properties": {
    "iso:country":"NL",
    "sg:address":"Vijverlaan 96",
    "sg:city":"Arnhem",
    "sg:orig_category":"Fitnesscentra",
    "sg:phone":"+31 26 446 1952",
    "sg:postcode":"6822 HG",
    "sg:province":"Gelderland",
    "wof:name":"Sportcentrum Keumgang",
    "wof:placetype":"venue"
},
  "geometry": {"coordinates":[5.925999,51.992363],"type":"Point"}
}