{
  "type": "Feature",
  "properties": {
    "iso:country":"NL",
    "sg:address":"Schotwg 34",
    "sg:city":"Apeldoorn",
    "sg:orig_category":"Acupunctuur",
    "sg:phone":"+31 55 355 5374",
    "sg:postcode":"7311 DW",
    "sg:province":"Gelderland",
    "wof:name":"Metafysiek",
    "wof:placetype":"venue"
},
  "geometry": {"coordinates":[5.94963,52.212967],"type":"Point"}
}