{
  "type": "Feature",
  "properties": {
    "addr:full":"Preekhillaan 3 Ouddorp Zh Zuid-Holland 3253 VJ",
    "addr:housenumber":"3",
    "addr:postcode":"3253 vj",
    "addr:street":"Preekhillaan",
    "iso:country":"NL",
    "sg:address":"Preekhillaan 3",
    "sg:city":"Ouddorp Zh",
    "sg:orig_category":"Overheidsdiensten",
    "sg:phone":"+31 187 683 040",
    "sg:postcode":"3253 VJ",
    "sg:province":"Zuid-Holland",
    "wof:name":"Eben-Haezer",
    "wof:placetype":"venue"
},
  "geometry": {"coordinates":[3.9380838871,51.8104934692],"type":"Point"}
}