{
  "type": "Feature",
  "properties": {
    "iso:country":"NL",
    "sg:address":"Griend 11",
    "sg:city":"Elst Gld",
    "sg:orig_category":"Psychotherapeuten",
    "sg:phone":"+31 481 373 792",
    "sg:postcode":"6662 XS",
    "sg:province":"Gelderland",
    "wof:name":"Gent, Drs J A J M Van",
    "wof:placetype":"venue"
},
  "geometry": {"coordinates":[5.837167,51.913155],"type":"Point"}
}