{
  "type": "Feature",
  "properties": {
    "addr:full":"Schuttershof 30 Goes Zeeland 4461 DZ",
    "addr:housenumber":"30",
    "addr:postcode":"4461 dz",
    "addr:street":"Schuttershof",
    "iso:country":"NL",
    "sg:address":"Schuttershof 30",
    "sg:city":"Goes",
    "sg:orig_category":"Medische Apparatuur And Prothesen Fab",
    "sg:phone":"+31 113 251 751",
    "sg:postcode":"4461 DZ",
    "sg:province":"Zeeland",
    "wof:name":"All Ears Hoortoestellen Bv",
    "wof:placetype":"venue"
},
  "geometry": {"coordinates":[-83.914169,39.768833],"type":"Point"}
}