{
  "type": "Feature",
  "properties": {
    "addr:full":"Rijksstraatweg 309 Leersum Utrecht 3956 CP",
    "addr:housenumber":"309",
    "addr:postcode":"3956 cp",
    "addr:street":"Rijksstraatweg",
    "iso:country":"NL",
    "sg:address":"Rijksstraatweg 309",
    "sg:city":"Leersum",
    "sg:orig_category":"Bloemen And Planten",
    "sg:phone":"+31 343 457 828",
    "sg:postcode":"3956 CP",
    "sg:province":"Utrecht",
    "wof:name":"De Glazen Stad Van Leersum",
    "wof:placetype":"venue"
},
  "geometry": {"coordinates":[5.417423,52.015343],"type":"Point"}
}