{
  "type": "Feature",
  "properties": {
    "addr:full":"Dr. Lelykade 188 'S Gravenhage South Holland 2583 CN",
    "addr:housenumber":"188 '",
    "addr:postcode":"2583 cn",
    "addr:street":"Dr. Lelykade",
    "iso:country":"NL",
    "sg:address":"Dr. Lelykade 188",
    "sg:city":"'S Gravenhage",
    "sg:orig_category":"Diverse Consumentenartikelen Gh",
    "sg:phone":"+31 70 354 9394",
    "sg:postcode":"2583 CN",
    "sg:province":"South Holland",
    "wof:name":"Firma L. De Graaf En Zoon",
    "wof:placetype":"venue"
},
  "geometry": {"coordinates":[4.267499,52.095905],"type":"Point"}
}