{
  "type": "Feature",
  "properties": {
    "iso:country":"NL",
    "sg:address":"Willemstr 5",
    "sg:city":"Nuenen",
    "sg:orig_category":"Verzekeringen - Verzekeringskantoren",
    "sg:phone":"+31 40 283 6918",
    "sg:postcode":"5671 JC",
    "sg:province":"North Brabant",
    "wof:name":"Assurantie Advies Nuenen",
    "wof:placetype":"venue"
},
  "geometry": {"coordinates":[5.541165,51.473892],"type":"Point"}
}