{
  "type": "Feature",
  "properties": {
    "iso:country":"NL",
    "sg:address":"Parkwg 3A",
    "sg:city":"Deventer",
    "sg:orig_category":"Hulpverlening Sociaal",
    "sg:phone":"+31 570 614 419",
    "sg:postcode":"7411 SG",
    "sg:province":"NL.08",
    "wof:name":"Ithaka",
    "wof:placetype":"venue"
},
  "geometry": {"coordinates":[6.149667,52.256306],"type":"Point"}
}