{
  "type": "Feature",
  "properties": {
    "addr:full":"Zellebergen 1 Oudenbosch North Brabant 4731 NZ",
    "addr:housenumber":"1",
    "addr:postcode":"4731 nz",
    "addr:street":"Zellebergen",
    "iso:country":"NL",
    "sg:address":"Zellebergen 1",
    "sg:city":"Oudenbosch",
    "sg:orig_category":"Bejaarden - Verzorgingstehuizen",
    "sg:phone":"+31 165 390 600",
    "sg:postcode":"4731 NZ",
    "sg:province":"North Brabant",
    "wof:name":"Zellebergen, De",
    "wof:placetype":"venue"
},
  "geometry": {"coordinates":[4.51946,51.590633],"type":"Point"}
}