{
  "type": "Feature",
  "properties": {
    "addr:full":"Orteliusln 1041 Utrecht Noord-Holland 3528 BE",
    "addr:housenumber":"1041",
    "addr:postcode":"3528",
    "iso:country":"NL",
    "sg:address":"Orteliusln 1041",
    "sg:city":"Utrecht",
    "sg:orig_category":"Accountants - Administratie- Consulenten En -Kantoren",
    "sg:phone":"+31 30 299 5500",
    "sg:postcode":"3528 BE",
    "sg:province":"Noord-Holland",
    "wof:name":"Deloitte & Touche",
    "wof:placetype":"venue"
},
  "geometry": {"coordinates":[-73.996292,40.613091],"type":"Point"}
}