{
  "type": "Feature",
  "properties": {
    "addr:full":"Eperwg 8A Nunspeet Gelderland 8071 AX",
    "addr:housenumber":"8a",
    "addr:postcode":"8071 ax",
    "addr:street":"Eperwg;Gelderland",
    "iso:country":"NL",
    "sg:address":"Eperwg 8A",
    "sg:city":"Nunspeet",
    "sg:orig_category":"Fietsen En Bromfietsen",
    "sg:phone":"+31 341 252 558",
    "sg:postcode":"8071 AX",
    "sg:province":"Gelderland",
    "wof:name":"Tweewielercentr",
    "wof:placetype":"venue"
},
  "geometry": {"coordinates":[5.789574,52.376503],"type":"Point"}
}