{
  "type": "Feature",
  "properties": {
    "addr:full":"Dukaton 60 Volendam North Holland 1132 RD",
    "addr:housenumber":"60",
    "addr:postcode":"1132 rd",
    "addr:street":"Dukaton",
    "iso:country":"NL",
    "sg:address":"Dukaton 60",
    "sg:city":"Volendam",
    "sg:orig_category":"Montagebedrijven",
    "sg:phone":"+31 299 321 490",
    "sg:postcode":"1132 RD",
    "sg:province":"North Holland",
    "wof:name":"Koobra Vof",
    "wof:placetype":"venue"
},
  "geometry": {"coordinates":[5.060693,52.50629],"type":"Point"}
}