{
  "type": "Feature",
  "properties": {
    "iso:country":"NL",
    "sg:address":"Burgemeester Smitweg 107",
    "sg:city":"Hazerswoude Dorp",
    "sg:orig_category":"Bloemen And Planten",
    "sg:phone":"+31 172 588 954",
    "sg:postcode":"2391 NG",
    "sg:province":"South Holland",
    "wof:name":"Jac. Brand",
    "wof:placetype":"venue"
},
  "geometry": {"coordinates":[4.639461,52.098785],"type":"Point"}
}