{
  "type": "Feature",
  "properties": {
    "addr:full":"Het Rondeel 13 Maastricht Limburg 6219 PG",
    "addr:housenumber":"13",
    "addr:postcode":"6219 pg",
    "addr:street":"Het Rondeel",
    "iso:country":"NL",
    "sg:address":"Het Rondeel 13",
    "sg:city":"Maastricht",
    "sg:orig_category":"Meubelen",
    "sg:phone":"+31 43 326 0260",
    "sg:postcode":"6219 PG",
    "sg:province":"Limburg",
    "wof:name":"Meubelcentrum Maastricht",
    "wof:placetype":"venue"
},
  "geometry": {"coordinates":[5.679378,50.860161],"type":"Point"}
}