{
  "type": "Feature",
  "properties": {
    "addr:full":"Nieuwlandsedijk 20 'S Gravenzande Zuid-Holland 2691 KW",
    "addr:housenumber":"20",
    "addr:postcode":"2691 kw",
    "addr:street":"Nieuwlandsedijk;' S",
    "iso:country":"NL",
    "sg:address":"Nieuwlandsedijk 20",
    "sg:city":"'S Gravenzande",
    "sg:classifiers":[
        {
            "category":"Fast Food",
            "type":"Food & Drink"
        }
    ],
    "sg:phone":"+31 174 414 347",
    "sg:postcode":"2691 KW",
    "sg:province":"Zuid-Holland",
    "sg:tags":[
        "afhaal",
        "restaurant"
    ],
    "wof:name":"Paviljoen De Oase",
    "wof:placetype":"venue"
},
  "geometry": {"coordinates":[4.133742,51.998543],"type":"Point"}
}