{
  "type": "Feature",
  "properties": {
    "addr:full":"Violierstr 20 Almelo NL.08 7601 GS",
    "addr:housenumber":"20;nl.08",
    "addr:postcode":"7601 gs",
    "addr:street":"Violierstr",
    "iso:country":"NL",
    "sg:address":"Violierstr 20",
    "sg:city":"Almelo",
    "sg:orig_category":"Cafetaria'S",
    "sg:phone":"+31 546 815 465",
    "sg:postcode":"7601 GS",
    "sg:province":"NL.08",
    "wof:name":"Violier De",
    "wof:placetype":"venue"
},
  "geometry": {"coordinates":[6.672104,52.346771],"type":"Point"}
}