{
  "type": "Feature",
  "properties": {
    "addr:full":"Franciscahof 21 Vlaardingen Zuid-Holland 3135 PG",
    "addr:housenumber":"21",
    "addr:postcode":"3135 pg",
    "addr:street":"Franciscahof",
    "iso:country":"NL",
    "sg:address":"Franciscahof 21",
    "sg:city":"Vlaardingen",
    "sg:orig_category":"Juridische Adviseurs",
    "sg:phone":"+31 10 234 2448",
    "sg:postcode":"3135 PG",
    "sg:province":"Zuid-Holland",
    "wof:name":"Veeren Juridisch Vastgoed Adv",
    "wof:placetype":"venue"
},
  "geometry": {"coordinates":[4.357146,51.915039],"type":"Point"}
}