{
  "type": "Feature",
  "properties": {
    "addr:full":"Oldenzaalstraat 38 Almere Flevoland 1324 EZ",
    "addr:housenumber":"38",
    "addr:postcode":"1324 ez",
    "addr:street":"Oldenzaalstraat;Flevoland",
    "iso:country":"NL",
    "sg:address":"Oldenzaalstraat 38",
    "sg:city":"Almere",
    "sg:orig_category":"Schilderwerk",
    "sg:phone":"+31 36 533 5670",
    "sg:postcode":"1324 EZ",
    "sg:province":"Flevoland",
    "wof:name":"Grootveld",
    "wof:placetype":"venue"
},
  "geometry": {"coordinates":[5.209468,52.365227],"type":"Point"}
}