{
  "type": "Feature",
  "properties": {
    "addr:full":"Dorpsstraat 8 Heerjansdam Zuid-Holland 2995 XH",
    "addr:housenumber":"8",
    "addr:postcode":"2995 xh",
    "addr:street":"Dorpsstraat",
    "iso:country":"NL",
    "sg:address":"Dorpsstraat 8",
    "sg:city":"Heerjansdam",
    "sg:orig_category":"Wegen And Sportterreinen",
    "sg:phone":"+31 78 677 8888",
    "sg:postcode":"2995 XH",
    "sg:province":"Zuid-Holland",
    "wof:name":"D. Monshouwer Bv",
    "wof:placetype":"venue"
},
  "geometry": {"coordinates":[4.5597271919,51.835975647],"type":"Point"}
}