{
  "type": "Feature",
  "properties": {
    "addr:full":"Amperestr 10 Landgraaf Limburg 6372 BB",
    "addr:housenumber":"10",
    "addr:postcode":"6372 bb",
    "addr:street":"Amperestr",
    "iso:country":"NL",
    "sg:address":"Amperestr 10",
    "sg:city":"Landgraaf",
    "sg:orig_category":"Bestratingen",
    "sg:phone":"+31 45 532 0274",
    "sg:postcode":"6372 BB",
    "sg:province":"Limburg",
    "wof:name":"Gielkens, J A",
    "wof:placetype":"venue"
},
  "geometry": {"coordinates":[6.022192,50.889168],"type":"Point"}
}