{
  "type": "Feature",
  "properties": {
    "addr:full":"Van Oldenbarneveltplaats 24 Rotterdam Zuid-Holland 3012 AH",
    "addr:housenumber":"24",
    "addr:postcode":"3012 ah",
    "addr:street":"Van Oldenbarneveltplaats",
    "iso:country":"NL",
    "sg:address":"Van Oldenbarneveltplaats 24",
    "sg:city":"Rotterdam",
    "sg:orig_category":"Schoenen",
    "sg:phone":"+31 10 411 5011",
    "sg:postcode":"3012 AH",
    "sg:province":"Zuid-Holland",
    "wof:name":"Mata-Hari Shoes Rotterdam-Centrum Bv",
    "wof:placetype":"venue"
},
  "geometry": {"coordinates":[4.478225,51.919655],"type":"Point"}
}