{
  "type": "Feature",
  "properties": {
    "addr:full":"Bessemerln 7 Utrecht Utrecht 3553 GA",
    "addr:housenumber":"7",
    "addr:postcode":"3553 ga",
    "addr:street":"Bessemerln",
    "iso:country":"NL",
    "sg:address":"Bessemerln 7",
    "sg:city":"Utrecht",
    "sg:orig_category":"Bedrijfsopleidingen",
    "sg:phone":"+31 30 243 8078",
    "sg:postcode":"3553 GA",
    "sg:province":"Utrecht",
    "wof:name":"Torn, Van Der",
    "wof:placetype":"venue"
},
  "geometry": {"coordinates":[5.08441,52.109322],"type":"Point"}
}