{
  "type": "Feature",
  "properties": {
    "addr:full":"Gortstraat 6 'S Gravenhage Zuid-Holland 2511 AP",
    "addr:housenumber":"6 '",
    "addr:postcode":"2511 ap",
    "addr:street":"Gortstraat",
    "iso:country":"NL",
    "sg:address":"Gortstraat 6",
    "sg:city":"'S Gravenhage",
    "sg:classifiers":[
        {
            "category":"Bars & Pubs",
            "type":"Food & Drink"
        }
    ],
    "sg:phone":"+31 70 392 3585",
    "sg:postcode":"2511 AP",
    "sg:province":"Zuid-Holland",
    "wof:name":"Sky 2",
    "wof:placetype":"venue"
},
  "geometry": {"coordinates":[4.310509,52.077595],"type":"Point"}
}