{
  "type": "Feature",
  "properties": {
    "addr:full":"Industriewg 25 Hasselt Overijssel 8061 RB",
    "addr:housenumber":"25",
    "addr:postcode":"8061 rb",
    "addr:street":"Industriewg",
    "iso:country":"NL",
    "sg:address":"Industriewg 25",
    "sg:city":"Hasselt",
    "sg:orig_category":"Autoschade- Herstelbedrijven",
    "sg:phone":"+31 38 477 1100",
    "sg:postcode":"8061 RB",
    "sg:province":"Overijssel",
    "wof:name":"Hooikammer",
    "wof:placetype":"venue"
},
  "geometry": {"coordinates":[6.089288,52.584209],"type":"Point"}
}