{
  "type": "Feature",
  "properties": {
    "addr:full":"Jan Deckersstraat 57 Heeze North Brabant 5591 HP",
    "addr:housenumber":"57",
    "addr:postcode":"5591 hp",
    "addr:street":"Jan Deckersstraat",
    "iso:country":"NL",
    "sg:address":"Jan Deckersstraat 57",
    "sg:city":"Heeze",
    "sg:orig_category":"Kappers",
    "sg:phone":"+31 40 226 3207",
    "sg:postcode":"5591 HP",
    "sg:province":"North Brabant",
    "wof:name":"Ciseaux Coiffures",
    "wof:placetype":"venue"
},
  "geometry": {"coordinates":[5.57791996,51.376991272],"type":"Point"}
}