{
  "type": "Feature",
  "properties": {
    "addr:full":"Vinkenberg 21 Moergestel Noord-Brabant 5066 PD",
    "addr:housenumber":"21",
    "addr:postcode":"5066 pd",
    "addr:street":"Vinkenberg",
    "iso:country":"NL",
    "sg:address":"Vinkenberg 21",
    "sg:city":"Moergestel",
    "sg:orig_category":"Machineonderhoud En -Reparatie",
    "sg:phone":"+31 6 55152209",
    "sg:postcode":"5066 PD",
    "sg:province":"Noord-Brabant",
    "wof:name":"Dijck, John Van",
    "wof:placetype":"venue"
},
  "geometry": {"coordinates":[5.17838,51.533054],"type":"Point"}
}