{
  "type": "Feature",
  "properties": {
    "addr:full":"Rijksstraatweg 67 Twello Gelderland 7391 MJ",
    "addr:housenumber":"67",
    "addr:postcode":"7391 mj",
    "addr:street":"Rijksstraatweg;Gelderland",
    "iso:country":"NL",
    "sg:address":"Rijksstraatweg 67",
    "sg:city":"Twello",
    "sg:orig_category":"Reclamebureaus",
    "sg:phone":"+31 571 276 068",
    "sg:postcode":"7391 MJ",
    "sg:province":"Gelderland",
    "wof:name":"Via Design Bv",
    "wof:placetype":"venue"
},
  "geometry": {"coordinates":[6.111387,52.243477],"type":"Point"}
}