{
  "type": "Feature",
  "properties": {
    "addr:full":"Transeedk 6-8 Lobith Gelderland 6915 XX",
    "addr:housenumber":"6-8",
    "addr:postcode":"6915 xx",
    "addr:street":"Transeedk;Gelderland",
    "iso:country":"NL",
    "sg:address":"Transeedk 6-8",
    "sg:city":"Lobith",
    "sg:classifiers":[
        {
            "category":"Retail",
            "subcategory":"Auto Repair",
            "type":"Services"
        }
    ],
    "sg:phone":"+31 316 541 441",
    "sg:postcode":"6915 XX",
    "sg:province":"Gelderland",
    "sg:tags":[
        "garage"
    ],
    "wof:name":"Chevy 8 Shop",
    "wof:placetype":"venue"
},
  "geometry": {"coordinates":[6.116686,51.860336],"type":"Point"}
}