{
  "type": "Feature",
  "properties": {
    "addr:full":"Dorperheidewg 39 Arcen Limburg 5944 NK",
    "addr:housenumber":"39",
    "addr:postcode":"5944 nk",
    "addr:street":"Dorperheidewg",
    "iso:country":"NL",
    "sg:address":"Dorperheidewg 39",
    "sg:city":"Arcen",
    "sg:classifiers":[
        {
            "category":"Home & Garden",
            "subcategory":"Garden Supply",
            "type":"Retail Goods"
        }
    ],
    "sg:phone":"+31 77 473 2352",
    "sg:postcode":"5944 NK",
    "sg:province":"Limburg",
    "sg:tags":[
        "zand",
        "en",
        "grind"
    ],
    "wof:name":"Teunesen Bv",
    "wof:placetype":"venue"
},
  "geometry": {"coordinates":[6.203114,51.498657],"type":"Point"}
}