{
  "type": "Feature",
  "properties": {
    "iso:country":"NL",
    "sg:address":"Amsterdamsestrwg 72",
    "sg:city":"Utrecht",
    "sg:orig_category":"Banken",
    "sg:phone":"+31 30 239 2020",
    "sg:postcode":"3513 AJ",
    "sg:province":"Utrecht",
    "sg:website":"http://www.dhbbank.com",
    "wof:name":"Dhb",
    "wof:placetype":"venue"
},
  "geometry": {"coordinates":[5.107073,52.096424],"type":"Point"}
}