{
  "type": "Feature",
  "properties": {
    "addr:full":"Hogewal 10 De Valom Provincie Friesland 9109 NW",
    "addr:housenumber":"10;9109",
    "addr:postcode":"nw",
    "addr:street":"Hogewal;Valom Provincie Friesland",
    "iso:country":"NL",
    "sg:address":"Hogewal 10",
    "sg:city":"De Valom",
    "sg:orig_category":"Autokeuringen",
    "sg:phone":"+31 511 422 086",
    "sg:postcode":"9109 NW",
    "sg:province":"Provincie Friesland",
    "wof:name":"R Kloosterman Autobedrijf",
    "wof:placetype":"venue"
},
  "geometry": {"coordinates":[6.003272,53.267883],"type":"Point"}
}