{
  "type": "Feature",
  "properties": {
    "addr:full":"Johannes Verhulststraat 53 Amsterdam Noord-Holland 1071 MS",
    "addr:housenumber":"53",
    "addr:postcode":"1071 ms",
    "addr:street":"Johannes Verhulststraat",
    "iso:country":"NL",
    "sg:address":"Johannes Verhulststraat 53",
    "sg:city":"Amsterdam",
    "sg:orig_category":"Zalenexploitatie",
    "sg:phone":"+31 20 671 4087",
    "sg:postcode":"1071 MS",
    "sg:province":"Noord-Holland",
    "wof:name":"Galerie Studio A",
    "wof:placetype":"venue"
},
  "geometry": {"coordinates":[4.87468,52.355007],"type":"Point"}
}