{
  "type": "Feature",
  "properties": {
    "addr:full":"Hadewychln 21 Pynacker South Holland 2642 BA",
    "addr:housenumber":"21",
    "addr:postcode":"2642 ba",
    "addr:street":"Hadewychln;Pynacker South",
    "iso:country":"NL",
    "sg:address":"Hadewychln 21",
    "sg:city":"Pynacker",
    "sg:orig_category":"Onderhoudswerken",
    "sg:phone":"+31 15 369 7124",
    "sg:postcode":"2642 BA",
    "sg:province":"South Holland",
    "wof:name":"Sluis, Van Der",
    "wof:placetype":"venue"
},
  "geometry": {"coordinates":[4.45025,52.008888],"type":"Point"}
}