{
  "type": "Feature",
  "properties": {
    "addr:full":"M Dotingaln 164 Weesp Noord-Holland 1381 GG",
    "addr:housenumber":"164",
    "addr:postcode":"1381 gg",
    "iso:country":"NL",
    "sg:address":"M Dotingaln 164",
    "sg:city":"Weesp",
    "sg:orig_category":"Hydraulische Apparaten En Installaties",
    "sg:phone":"+31 294 410 595",
    "sg:postcode":"1381 GG",
    "sg:province":"Noord-Holland",
    "wof:name":"Thc",
    "wof:placetype":"venue"
},
  "geometry": {"coordinates":[5.052052,52.30183],"type":"Point"}
}