{
  "type": "Feature",
  "properties": {
    "addr:full":"Badwg 32 Schiermonnikoog Friesland 9166 NK",
    "addr:housenumber":"32",
    "addr:postcode":"9166 nk",
    "addr:street":"Badwg",
    "iso:country":"NL",
    "sg:address":"Badwg 32",
    "sg:city":"Schiermonnikoog",
    "sg:classifiers":[
        {
            "category":"Travel",
            "subcategory":"Hotels & Motels",
            "type":"Entertainment"
        }
    ],
    "sg:phone":"+31 519 531 111",
    "sg:postcode":"9166 NK",
    "sg:province":"Friesland",
    "wof:name":"Noderstraun",
    "wof:placetype":"venue"
},
  "geometry": {"coordinates":[6.150276,53.489933],"type":"Point"}
}