{
  "type": "Feature",
  "properties": {
    "addr:full":"V Schaffelaarstr 38 Barneveld Gelderland 3771 BV",
    "addr:housenumber":"38",
    "addr:postcode":"3771 bv",
    "addr:street":"Gelderland",
    "iso:country":"NL",
    "sg:address":"V Schaffelaarstr 38",
    "sg:city":"Barneveld",
    "sg:orig_category":"Drogisterijen",
    "sg:phone":"+31 342 413 193",
    "sg:postcode":"3771 BV",
    "sg:province":"Gelderland",
    "wof:name":"Da",
    "wof:placetype":"venue"
},
  "geometry": {"coordinates":[5.588843,52.141216],"type":"Point"}
}