{
  "type": "Feature",
  "properties": {
    "addr:full":"Kalshoven 16A Breda North Brabant 4825 AM",
    "addr:housenumber":"16a",
    "addr:postcode":"4825",
    "addr:street":"Kalshoven",
    "iso:country":"NL",
    "sg:address":"Kalshoven 16A",
    "sg:city":"Breda",
    "sg:orig_category":"Banden",
    "sg:phone":"+31 76 571 7272",
    "sg:postcode":"4825 AM",
    "sg:province":"North Brabant",
    "wof:name":"Ligtvoet Autobanden",
    "wof:placetype":"venue"
},
  "geometry": {"coordinates":[4.76844,51.604858],"type":"Point"}
}