{
  "type": "Feature",
  "properties": {
    "addr:full":"Westerveerstraat 47 Heerhugowaard Noord-Holland 1705 AT",
    "addr:housenumber":"47",
    "addr:postcode":"1705",
    "addr:street":"Westerveerstraat",
    "iso:country":"NL",
    "sg:address":"Westerveerstraat 47",
    "sg:city":"Heerhugowaard",
    "sg:orig_category":"Metaalwerken",
    "sg:phone":"+31 72 572 5436",
    "sg:postcode":"1705 AT",
    "sg:province":"Noord-Holland",
    "wof:name":"Divario",
    "wof:placetype":"venue"
},
  "geometry": {"coordinates":[4.838988,52.649933],"type":"Point"}
}