{
  "type": "Feature",
  "properties": {
    "iso:country":"NL",
    "sg:address":"Watertorenln 60",
    "sg:city":"Voorburg",
    "sg:orig_category":"Onroerende Goederen",
    "sg:phone":"+31 70 320 2222",
    "sg:postcode":"2275 AX",
    "sg:province":"Zuid-Holland",
    "wof:name":"Duijvestein",
    "wof:placetype":"venue"
},
  "geometry": {"coordinates":[4.356231,52.062244],"type":"Point"}
}