{
  "type": "Feature",
  "properties": {
    "addr:full":"Goeverneurlaan 276 'S-Gravenhage Zuid-Holland 2523 BS",
    "addr:housenumber":"276",
    "addr:postcode":"s-gravenhage;2523 bs",
    "addr:street":"Goeverneurlaan",
    "iso:country":"NL",
    "sg:address":"Goeverneurlaan 276",
    "sg:city":"'S-Gravenhage",
    "sg:orig_category":"Autorijscholen",
    "sg:phone":"+31 6 14477332",
    "sg:postcode":"2523 BS",
    "sg:province":"Zuid-Holland",
    "wof:name":"Nermin",
    "wof:placetype":"venue"
},
  "geometry": {"coordinates":[4.31927,52.056469],"type":"Point"}
}