{
  "type": "Feature",
  "properties": {
    "addr:full":"Pioenveld 32 Bergen Op Zoom North Brabant 4613 CP",
    "addr:housenumber":"32",
    "addr:postcode":"4613 cp",
    "addr:street":"Pioenveld",
    "iso:country":"NL",
    "sg:address":"Pioenveld 32",
    "sg:city":"Bergen Op Zoom",
    "sg:orig_category":"Bijouterie?n",
    "sg:phone":"+31 164 244 103",
    "sg:postcode":"4613 CP",
    "sg:province":"North Brabant",
    "wof:name":"Rem",
    "wof:placetype":"venue"
},
  "geometry": {"coordinates":[4.281488,51.502365],"type":"Point"}
}