{
  "type": "Feature",
  "properties": {
    "addr:full":"Harnjesweg 90 Wageningen Gelderland 6706 AV",
    "addr:housenumber":"90",
    "addr:postcode":"6706 av",
    "addr:street":"Harnjesweg;Gelderland",
    "iso:country":"NL",
    "sg:address":"Harnjesweg 90",
    "sg:city":"Wageningen",
    "sg:orig_category":"Discountwinkels",
    "sg:phone":"+31 317 427 115",
    "sg:postcode":"6706 AV",
    "sg:province":"Gelderland",
    "wof:name":"Dumpwinkel 'T Camohoekje",
    "wof:placetype":"venue"
},
  "geometry": {"coordinates":[5.674134,51.970577],"type":"Point"}
}