{
  "type": "Feature",
  "properties": {
    "addr:full":"Hogeweg 20 Oosterbeek Gelderland 6862 WX",
    "addr:housenumber":"20",
    "addr:postcode":"6862 wx",
    "addr:street":"Hogeweg;Gelderland",
    "iso:country":"NL",
    "sg:address":"Hogeweg 20",
    "sg:city":"Oosterbeek",
    "sg:orig_category":"Vertaal- And Tolkenbureaus",
    "sg:phone":"+31 26 370 6676",
    "sg:postcode":"6862 WX",
    "sg:province":"Gelderland",
    "wof:name":"Vertaalbureau Go English",
    "wof:placetype":"venue"
},
  "geometry": {"coordinates":[5.851583,51.980221],"type":"Point"}
}