{
  "type": "Feature",
  "properties": {
    "iso:country":"NL",
    "sg:address":"Rumpenerstraat 42",
    "sg:city":"Brunssum",
    "sg:orig_category":"Werving And Selectie Van Tijdelijk Personeel And Uitzendkantoren",
    "sg:phone":"+31 45 525 7373",
    "sg:postcode":"6443 CE",
    "sg:province":"Limburg",
    "wof:name":"Dactylo",
    "wof:placetype":"venue"
},
  "geometry": {"coordinates":[5.9689540863,50.9402160645],"type":"Point"}
}