{
  "type": "Feature",
  "properties": {
    "addr:full":"Zuiderkruis 27 Ulft Gelderland 7071 TA",
    "addr:housenumber":"27",
    "addr:postcode":"7071 ta",
    "addr:street":"Zuiderkruis;Gelderland",
    "iso:country":"NL",
    "sg:address":"Zuiderkruis 27",
    "sg:city":"Ulft",
    "sg:orig_category":"Ballonvaarten En -Reclame",
    "sg:phone":"+31 315 685 737",
    "sg:postcode":"7071 TA",
    "sg:province":"Gelderland",
    "sg:website":"http://www.airiaballooning.nl",
    "wof:name":"Airia",
    "wof:placetype":"venue"
},
  "geometry": {"coordinates":[6.378765,51.882896],"type":"Point"}
}