{
  "type": "Feature",
  "properties": {
    "addr:full":"Kommerweg 5 Erica Drenthe 7887 TE",
    "addr:housenumber":"5",
    "addr:postcode":"7887 te",
    "addr:street":"Kommerweg",
    "iso:country":"NL",
    "sg:address":"Kommerweg 5",
    "sg:city":"Erica",
    "sg:orig_category":"Bloemen And Planten",
    "sg:phone":"+31 591 301 757",
    "sg:postcode":"7887 TE",
    "sg:province":"Drenthe",
    "wof:name":"De Kommerhoek",
    "wof:placetype":"venue"
},
  "geometry": {"coordinates":[6.941548,52.696888],"type":"Point"}
}