{
  "type": "Feature",
  "properties": {
    "addr:full":"De Clercqstr 103 Amsterdam Noord-Holland 1053 AH",
    "addr:housenumber":"103",
    "addr:postcode":"1053 ah",
    "iso:country":"NL",
    "sg:address":"De Clercqstr 103",
    "sg:city":"Amsterdam",
    "sg:orig_category":"Grafisch Ontwerpers",
    "sg:phone":"+31 20 685 4978",
    "sg:postcode":"1053 AH",
    "sg:province":"Noord-Holland",
    "wof:name":"Beekman, A A H",
    "wof:placetype":"venue"
},
  "geometry": {"coordinates":[4.866751,52.369938],"type":"Point"}
}