{
  "type": "Feature",
  "properties": {
    "addr:full":"V Duivenvoordeln 17 Wassenaar South Holland 2241 SM",
    "addr:housenumber":"17",
    "addr:postcode":"2241 sm",
    "addr:street":"V Duivenvoordeln",
    "iso:country":"NL",
    "sg:address":"V Duivenvoordeln 17",
    "sg:city":"Wassenaar",
    "sg:orig_category":"Acupunctuur",
    "sg:phone":"+31 70 511 5002",
    "sg:postcode":"2241 SM",
    "sg:province":"South Holland",
    "wof:name":"Bottema, J F",
    "wof:placetype":"venue"
},
  "geometry": {"coordinates":[4.404357,52.145733],"type":"Point"}
}