{
  "type": "Feature",
  "properties": {
    "addr:full":"Mercuriuswg 17 Grubbenvorst Limburg 5971 LX",
    "addr:housenumber":"17",
    "addr:postcode":"5971 lx",
    "addr:street":"Mercuriuswg",
    "iso:country":"NL",
    "sg:address":"Mercuriuswg 17",
    "sg:city":"Grubbenvorst",
    "sg:orig_category":"Machinefabrieken",
    "sg:phone":"+31 77 366 2096",
    "sg:postcode":"5971 LX",
    "sg:province":"Limburg",
    "sg:website":"http://www.dekruyfmetaaltechniek.nl",
    "wof:name":"Kruyf, De",
    "wof:placetype":"venue"
},
  "geometry": {"coordinates":[6.144175,51.425583],"type":"Point"}
}