{
  "type": "Feature",
  "properties": {
    "addr:full":"Hommelstr 81 Arnhem Gelderland 6828 AJ",
    "addr:housenumber":"81",
    "addr:postcode":"6828 aj",
    "addr:street":"Hommelstr",
    "iso:country":"NL",
    "sg:address":"Hommelstr 81",
    "sg:city":"Arnhem",
    "sg:orig_category":"Fietsen En Bromfietsen",
    "sg:phone":"+31 26 445 0118",
    "sg:postcode":"6828 AJ",
    "sg:province":"Gelderland",
    "wof:name":"Kosters, M",
    "wof:placetype":"venue"
},
  "geometry": {"coordinates":[5.91416,51.985516],"type":"Point"}
}