{
  "type": "Feature",
  "properties": {
    "addr:full":"Prof Oranjestr 12 Amsterdam Noord-Holland 1063 ST",
    "addr:housenumber":"12",
    "addr:postcode":"1063 st",
    "iso:country":"NL",
    "sg:address":"Prof Oranjestr 12",
    "sg:city":"Amsterdam",
    "sg:orig_category":"Adviesbureaus Personeel",
    "sg:phone":"+31 20 447 1115",
    "sg:postcode":"1063 ST",
    "sg:province":"Noord-Holland",
    "wof:name":"Groen Bv, H G M",
    "wof:placetype":"venue"
},
  "geometry": {"coordinates":[4.835991,52.381729],"type":"Point"}
}