{
  "type": "Feature",
  "properties": {
    "iso:country":"NL",
    "sg:address":"Muntpassage 39",
    "sg:city":"Weert",
    "sg:orig_category":"Schoenen",
    "sg:phone":"+31 495 548 940",
    "sg:postcode":"6001 GL",
    "sg:province":"Limburg",
    "wof:name":"Contessa Bv",
    "wof:placetype":"venue"
},
  "geometry": {"coordinates":[5.704722,51.25436],"type":"Point"}
}