{
  "type": "Feature",
  "properties": {
    "iso:country":"NL",
    "sg:address":"Klifrakplnts 32",
    "sg:city":"Utrecht",
    "sg:orig_category":"Kappers",
    "sg:phone":"+31 30 670 1250",
    "sg:postcode":"3544 RA",
    "sg:province":"Utrecht",
    "wof:name":"Rose",
    "wof:placetype":"venue"
},
  "geometry": {"coordinates":[5.057384,52.082954],"type":"Point"}
}