{
  "type": "Feature",
  "properties": {
    "iso:country":"NL",
    "sg:address":"Theo Van Loonstraat 3",
    "sg:city":"Hengelo Ov",
    "sg:classifiers":[
        {
            "category":"Professional",
            "subcategory":"Accounting & Tax Preparation",
            "type":"Services"
        }
    ],
    "sg:phone":"+31 74 243 0434",
    "sg:postcode":"7552 GN",
    "sg:province":"NL.08",
    "sg:tags":[
        "accountant"
    ],
    "wof:name":"Nizwie",
    "wof:placetype":"venue"
},
  "geometry": {"coordinates":[6.78971,52.266331],"type":"Point"}
}