{
  "type": "Feature",
  "properties": {
    "iso:country":"NL",
    "sg:address":"Paardenmarkt 18",
    "sg:city":"Yerseke",
    "sg:orig_category":"Fruit And Groenten Gh",
    "sg:phone":"+31 113 571 984",
    "sg:postcode":"4401 EE",
    "sg:province":"Zeeland",
    "wof:name":"Groentehandel J. Van Den Berge",
    "wof:placetype":"venue"
},
  "geometry": {"coordinates":[4.04898,51.493],"type":"Point"}
}