{
  "type": "Feature",
  "properties": {
    "addr:full":"C Krusemanstr 58 Amsterdam Noord-Holland 1075 NS",
    "addr:housenumber":"58",
    "addr:postcode":"1075 ns",
    "iso:country":"NL",
    "sg:address":"C Krusemanstr 58",
    "sg:city":"Amsterdam",
    "sg:classifiers":[
        {
            "category":"Retail",
            "subcategory":"Auto Repair",
            "type":"Services"
        }
    ],
    "sg:phone":"+31 20 662 5478",
    "sg:postcode":"1075 NS",
    "sg:province":"Noord-Holland",
    "sg:tags":[
        "garage"
    ],
    "wof:name":"Rijk",
    "wof:placetype":"venue"
},
  "geometry": {"coordinates":[4.860198,52.350716],"type":"Point"}
}