{
  "type": "Feature",
  "properties": {
    "addr:full":"Tiekenveenweg 45 Overdinkel South Carolina 7586 SC",
    "addr:housenumber":"45;7586",
    "addr:street":"Tiekenveenweg",
    "iso:country":"NL",
    "sg:address":"Tiekenveenweg 45",
    "sg:city":"Overdinkel",
    "sg:orig_category":"Bloemen And Planten",
    "sg:phone":"+31 53 538 4031",
    "sg:postcode":"7586 SC",
    "sg:province":"South Carolina",
    "wof:name":"J. En J.W. Vos",
    "wof:placetype":"venue"
},
  "geometry": {"coordinates":[-80.947441,33.624981],"type":"Point"}
}