{
  "type": "Feature",
  "properties": {
    "addr:full":"Sluiswg 196 S Hertogenbosch Noord-Brabant 5237 MZ",
    "addr:housenumber":"196",
    "addr:postcode":"5237 mz",
    "addr:street":"S",
    "iso:country":"NL",
    "sg:address":"Sluiswg 196",
    "sg:city":"S Hertogenbosch",
    "sg:orig_category":"Verlichtingsartikelen - Groothandel",
    "sg:phone":"+31 73 644 5072",
    "sg:postcode":"5237 MZ",
    "sg:province":"Noord-Brabant",
    "wof:name":"Hooge",
    "wof:placetype":"venue"
},
  "geometry": {"coordinates":[5.282151,51.733177],"type":"Point"}
}