{
  "type": "Feature",
  "properties": {
    "addr:full":"Praagsngl 141 S Gravenhage South Holland 2548 TV",
    "addr:housenumber":"141",
    "addr:postcode":"2548 tv",
    "addr:street":"S Gravenhage",
    "iso:country":"NL",
    "sg:address":"Praagsngl 141",
    "sg:city":"S Gravenhage",
    "sg:orig_category":"Onderhoudswerken",
    "sg:phone":"+31 70 329 0023",
    "sg:postcode":"2548 TV",
    "sg:province":"South Holland",
    "wof:name":"Hoogenraat",
    "wof:placetype":"venue"
},
  "geometry": {"coordinates":[4.2901,52.029888],"type":"Point"}
}