{
  "type": "Feature",
  "properties": {
    "iso:country":"NL",
    "sg:address":"Raiffeisenstr 9",
    "sg:city":"St Annaland",
    "sg:orig_category":"Scholen Voor Basisonderwijs",
    "sg:phone":"+31 166 657 044",
    "sg:postcode":"4697 CE",
    "sg:province":"Zeeland",
    "wof:name":"Casembrootsch Openb, De",
    "wof:placetype":"venue"
},
  "geometry": {"coordinates":[4.101849,51.597839],"type":"Point"}
}