{
  "type": "Feature",
  "properties": {
    "iso:country":"NL",
    "sg:address":"Vliegertsdijk 8",
    "sg:city":"Grashoek",
    "sg:orig_category":"Bloemen And Planten",
    "sg:phone":"+31 77 307 1011",
    "sg:postcode":"5985 PD",
    "sg:province":"Limburg",
    "wof:name":"P. Neessen",
    "wof:placetype":"venue"
},
  "geometry": {"coordinates":[5.963789,51.358543],"type":"Point"}
}