{
  "type": "Feature",
  "properties": {
    "addr:full":"Mercuriusstraat 39 Spijkenisse South Holland 3204 BM",
    "addr:housenumber":"39",
    "addr:postcode":"3204 bm",
    "addr:street":"Mercuriusstraat",
    "iso:country":"NL",
    "sg:address":"Mercuriusstraat 39",
    "sg:city":"Spijkenisse",
    "sg:orig_category":"Verzekeringen",
    "sg:phone":"+31 181 610 122",
    "sg:postcode":"3204 BM",
    "sg:province":"South Holland",
    "wof:name":"Quatro Assurantie & Adviesgroep",
    "wof:placetype":"venue"
},
  "geometry": {"coordinates":[4.325451,51.839481],"type":"Point"}
}