{
  "type": "Feature",
  "properties": {
    "iso:country":"NL",
    "sg:address":"Heyenlande 7",
    "sg:city":"Zwijndrecht",
    "sg:orig_category":"Wasserettes And Stomerijen",
    "sg:phone":"+31 78 612 4239",
    "sg:postcode":"3332 KK",
    "sg:province":"Zuid-Holland",
    "wof:name":"M. Dekkers",
    "wof:placetype":"venue"
},
  "geometry": {"coordinates":[4.6461157799,51.8259620667],"type":"Point"}
}