{
  "type": "Feature",
  "properties": {
    "addr:full":"Prof Mekelstraat 24 Bedum Groningen 9781 JH",
    "addr:housenumber":"24",
    "addr:postcode":"9781 jh",
    "addr:street":"Prof Mekelstraat",
    "iso:country":"NL",
    "sg:address":"Prof Mekelstraat 24",
    "sg:city":"Bedum",
    "sg:orig_category":"Loodgieterswerk, Verwarming And Sanitaire Installaties",
    "sg:phone":"+31 50 301 5942",
    "sg:postcode":"9781 JH",
    "sg:province":"Groningen",
    "wof:name":"J. Mulder",
    "wof:placetype":"venue"
},
  "geometry": {"coordinates":[6.599414,53.298454],"type":"Point"}
}