{
  "type": "Feature",
  "properties": {
    "addr:full":"Hildo Kropplein 47 Amsterdam Noord-Holland 1019 EE",
    "addr:housenumber":"47",
    "addr:postcode":"1019 ee",
    "addr:street":"Hildo Kropplein",
    "iso:country":"NL",
    "sg:address":"Hildo Kropplein 47",
    "sg:city":"Amsterdam",
    "sg:orig_category":"Loodgieters",
    "sg:phone":"+31 20 463 3244",
    "sg:postcode":"1019 EE",
    "sg:province":"Noord-Holland",
    "wof:name":"Haavekost, Joop",
    "wof:placetype":"venue"
},
  "geometry": {"coordinates":[4.942375,52.367916],"type":"Point"}
}