{
  "type": "Feature",
  "properties": {
    "addr:full":"V Slingelandtpln 17/20 Zwolle NL.08 8022 BH",
    "addr:housenumber":"17 / 20",
    "addr:postcode":"8022 bh",
    "iso:country":"NL",
    "sg:address":"V Slingelandtpln 17/20",
    "sg:city":"Zwolle",
    "sg:orig_category":"Muziekinstrumenten En Bladmuziek",
    "sg:phone":"+31 38 454 0102",
    "sg:postcode":"8022 BH",
    "sg:province":"NL.08",
    "sg:website":"http://www.rmmusic.nl",
    "wof:name":"Rhythm & Music",
    "wof:placetype":"venue"
},
  "geometry": {"coordinates":[6.10748,52.520309],"type":"Point"}
}