{
  "type": "Feature",
  "properties": {
    "addr:full":"Marktstraat 19 Naarden Noord-Holland 1411 CX",
    "addr:housenumber":"19",
    "addr:postcode":"1411 cx",
    "addr:street":"Marktstraat",
    "iso:country":"NL",
    "sg:address":"Marktstraat 19",
    "sg:city":"Naarden",
    "sg:orig_category":"Boekenuitgeverijen",
    "sg:phone":"+31 35 694 8484",
    "sg:postcode":"1411 CX",
    "sg:province":"Noord-Holland",
    "wof:name":"Boekhandel Comenius",
    "wof:placetype":"venue"
},
  "geometry": {"coordinates":[5.162875,52.295956],"type":"Point"}
}