{
  "type": "Feature",
  "properties": {
    "iso:country":"NL",
    "sg:address":"Weerdingerstr 224",
    "sg:city":"Emmen",
    "sg:orig_category":"Zonnebanken En Solaria - Fabrieken En Groothandel",
    "sg:phone":"+31 591 615 888",
    "sg:postcode":"7811 CC",
    "sg:province":"Provincie Drenthe",
    "sg:website":"http://www.eurosolar.nl",
    "wof:name":"Eurosolar Bv",
    "wof:placetype":"venue"
},
  "geometry": {"coordinates":[6.898278,52.792591],"type":"Point"}
}