{
  "type": "Feature",
  "properties": {
    "addr:full":"Ln V Biel 22 Almelo Overijssel 7607 PP",
    "addr:housenumber":"22",
    "addr:postcode":"7607 pp",
    "addr:street":"Ln V Biel",
    "iso:country":"NL",
    "sg:address":"Ln V Biel 22",
    "sg:city":"Almelo",
    "sg:orig_category":"Beeldende Kunstenaars",
    "sg:phone":"+31 546 823 111",
    "sg:postcode":"7607 PP",
    "sg:province":"Overijssel",
    "wof:name":"Ijskes, E",
    "wof:placetype":"venue"
},
  "geometry": {"coordinates":[6.664543,52.354954],"type":"Point"}
}