{
  "type": "Feature",
  "properties": {
    "addr:full":"Prof E M Meyersln 5 Amstelveen Noord-Holland 1183 AV",
    "addr:housenumber":"5",
    "addr:postcode":"1183 av",
    "addr:street":"Prof",
    "iso:country":"NL",
    "sg:address":"Prof E M Meyersln 5",
    "sg:city":"Amstelveen",
    "sg:orig_category":"Actuarissen",
    "sg:phone":"+31 20 543 3000",
    "sg:postcode":"1183 AV",
    "sg:province":"Noord-Holland",
    "wof:name":"Watson Wyatt Brans & Co",
    "wof:placetype":"venue"
},
  "geometry": {"coordinates":[4.875262,52.317711],"type":"Point"}
}