{
  "type": "Feature",
  "properties": {
    "addr:full":"Ln V Brabant 1 Roosendaal North Brabant 4701 BM",
    "addr:housenumber":"1",
    "addr:postcode":"4701 bm",
    "addr:street":"Ln;Brabant",
    "iso:country":"NL",
    "sg:address":"Ln V Brabant 1",
    "sg:city":"Roosendaal",
    "sg:orig_category":"Fietsen En Bromfietsen Stalling",
    "sg:phone":"+31 165 538 494",
    "sg:postcode":"4701 BM",
    "sg:province":"North Brabant",
    "wof:name":"Roselaer, De",
    "wof:placetype":"venue"
},
  "geometry": {"coordinates":[4.45767,51.531403],"type":"Point"}
}