{
  "type": "Feature",
  "properties": {
    "addr:full":"Grebbelinie 6 Bunschoten Spakenburg Utrecht 3751 XR",
    "addr:housenumber":"6",
    "addr:postcode":"3751 xr",
    "addr:street":"Grebbelinie",
    "iso:country":"NL",
    "sg:address":"Grebbelinie 6",
    "sg:city":"Bunschoten Spakenburg",
    "sg:orig_category":"Boekhouders",
    "sg:phone":"+31 33 298 6244",
    "sg:postcode":"3751 XR",
    "sg:province":"Utrecht",
    "wof:name":"L. Hopman",
    "wof:placetype":"venue"
},
  "geometry": {"coordinates":[5.371926,52.231781],"type":"Point"}
}