{
  "type": "Feature",
  "properties": {
    "addr:full":"Schalkwijkerstraat 17 Haarlem Noord-Holland 2033 JB",
    "addr:housenumber":"17",
    "addr:postcode":"2033 jb",
    "addr:street":"Schalkwijkerstraat",
    "iso:country":"NL",
    "sg:address":"Schalkwijkerstraat 17",
    "sg:city":"Haarlem",
    "sg:orig_category":"Glaszetten",
    "sg:phone":"+31 23 536 1666",
    "sg:postcode":"2033 JB",
    "sg:province":"Noord-Holland",
    "wof:name":"Tjade Petri Bv",
    "wof:placetype":"venue"
},
  "geometry": {"coordinates":[4.64338,52.373631],"type":"Point"}
}