{
  "type": "Feature",
  "properties": {
    "addr:full":"Kamperstr 36 Zwolle NL.08 8011 LM",
    "addr:housenumber":"36",
    "addr:postcode":"8011 lm",
    "addr:street":"Kamperstr",
    "iso:country":"NL",
    "sg:address":"Kamperstr 36",
    "sg:city":"Zwolle",
    "sg:orig_category":"Kappers",
    "sg:phone":"+31 38 421 7554",
    "sg:postcode":"8011 LM",
    "sg:province":"NL.08",
    "wof:name":"Ronde",
    "wof:placetype":"venue"
},
  "geometry": {"coordinates":[6.088618,52.511917],"type":"Point"}
}