{
  "type": "Feature",
  "properties": {
    "addr:full":"Van Baerlestraat 154 Amsterdam Noord-Holland 1071 BG",
    "addr:housenumber":"154",
    "addr:postcode":"1071",
    "addr:street":"Van Baerlestraat",
    "iso:country":"NL",
    "sg:address":"Van Baerlestraat 154",
    "sg:city":"Amsterdam",
    "sg:orig_category":"Werving And Selectie Van Tijdelijk Personeel And Uitzendkantoren",
    "sg:phone":"+31 20 672 1900",
    "sg:postcode":"1071 BG",
    "sg:province":"Noord-Holland",
    "wof:name":"Start",
    "wof:placetype":"venue"
},
  "geometry": {"coordinates":[4.8812527657,52.353969574],"type":"Point"}
}