{
  "type": "Feature",
  "properties": {
    "iso:country":"NL",
    "sg:address":"Havikstr 5A",
    "sg:city":"Sittard",
    "sg:classifiers":[
        {
            "category":"Personal",
            "subcategory":"Nail Salon",
            "type":"Services"
        }
    ],
    "sg:phone":"+31 6 51761230",
    "sg:postcode":"6135 ED",
    "sg:province":"Limburg",
    "sg:tags":[
        "pedicure"
    ],
    "wof:name":"Manja",
    "wof:placetype":"venue"
},
  "geometry": {"coordinates":[5.845962,51.005093],"type":"Point"}
}