{
  "type": "Feature",
  "properties": {
    "iso:country":"NL",
    "sg:address":"Bosscherwg 173A",
    "sg:city":"Maastricht",
    "sg:orig_category":"Autoruiten",
    "sg:phone":"+31 43 326 3539",
    "sg:postcode":"6219 AA",
    "sg:province":"Limburg",
    "sg:website":"http://www.autoruitdirect.nl",
    "wof:name":"Autoruitdirect",
    "wof:placetype":"venue"
},
  "geometry": {"coordinates":[5.688443,50.862183],"type":"Point"}
}