{
  "type": "Feature",
  "properties": {
    "iso:country":"NL",
    "sg:address":"Nagelbeek 21",
    "sg:city":"Schinnen",
    "sg:orig_category":"Fruit And Groenten Gh",
    "sg:phone":"+31 46 443 1447",
    "sg:postcode":"6365 EH",
    "sg:province":"Limburg",
    "wof:name":"M.K.J.G. Damoiseaux",
    "wof:placetype":"venue"
},
  "geometry": {"coordinates":[5.872534,50.936531],"type":"Point"}
}