{
  "type": "Feature",
  "properties": {
    "addr:full":"Thurledewg 59 Rotterdam Zuid-Holland 3044 ER",
    "addr:housenumber":"59",
    "addr:postcode":"3044 er",
    "addr:street":"Thurledewg",
    "iso:country":"NL",
    "sg:address":"Thurledewg 59",
    "sg:city":"Rotterdam",
    "sg:classifiers":[
        {
            "category":"Retail",
            "subcategory":"Auto Repair",
            "type":"Services"
        }
    ],
    "sg:phone":"+31 10 462 2011",
    "sg:postcode":"3044 ER",
    "sg:province":"Zuid-Holland",
    "sg:tags":[
        "garage"
    ],
    "sg:website":"http://www.vuurman.nl",
    "wof:name":"Vuurman Bv",
    "wof:placetype":"venue"
},
  "geometry": {"coordinates":[4.413906,51.926952],"type":"Point"}
}