{
  "type": "Feature",
  "properties": {
    "addr:full":"Piet Heinstraat 3 Zutphen Gelderland 7204 JN",
    "addr:housenumber":"3",
    "addr:postcode":"7204 jn",
    "addr:street":"Piet Heinstraat;Gelderland",
    "iso:country":"NL",
    "sg:address":"Piet Heinstraat 3",
    "sg:city":"Zutphen",
    "sg:orig_category":"Boekhouders",
    "sg:phone":"+31 575 514 275",
    "sg:postcode":"7204 JN",
    "sg:province":"Gelderland",
    "wof:name":"Administratiekantoor Zutphen Bv",
    "wof:placetype":"venue"
},
  "geometry": {"coordinates":[6.218886,52.134735],"type":"Point"}
}