{
  "type": "Feature",
  "properties": {
    "addr:full":"Van Utrechtweg 93 Krimpen A/D Ijssel Zuid-Holland 2921 LN",
    "addr:housenumber":"93;a / d",
    "addr:postcode":"2921 ln",
    "addr:street":"Van Utrechtweg",
    "iso:country":"NL",
    "sg:address":"Van Utrechtweg 93",
    "sg:city":"Krimpen A/D Ijssel",
    "sg:orig_category":"Goederenvervoer Over De Weg",
    "sg:phone":"+31 180 518 061",
    "sg:postcode":"2921 LN",
    "sg:province":"Zuid-Holland",
    "wof:name":"J. De Pee Trans",
    "wof:placetype":"venue"
},
  "geometry": {"coordinates":[4.576288,51.908997],"type":"Point"}
}