{
  "type": "Feature",
  "properties": {
    "addr:full":"Eindhovenseweg 59 Best Para\u00edba 5683 PB",
    "addr:housenumber":"59",
    "addr:postcode":"5683 pb",
    "addr:street":"Eindhovenseweg",
    "iso:country":"NL",
    "sg:address":"Eindhovenseweg 59",
    "sg:city":"Best",
    "sg:classifiers":[
        {
            "category":"Fast Food",
            "type":"Food & Drink"
        }
    ],
    "sg:phone":"+31 499 375 333",
    "sg:postcode":"5683 PB",
    "sg:province":"Para\u00edba",
    "sg:tags":[
        "afhaal",
        "restaurant"
    ],
    "wof:name":"Mcdonald'S Restaurant Best",
    "wof:placetype":"venue"
},
  "geometry": {"coordinates":[-36.777691,-7.16501],"type":"Point"}
}