{
  "type": "Feature",
  "properties": {
    "addr:full":"R Kipling Erf 175 Dordrecht Zuid-Holland 3315 AG",
    "addr:housenumber":"175",
    "addr:postcode":"3315",
    "addr:street":"Kipling Erf",
    "iso:country":"NL",
    "sg:address":"R Kipling Erf 175",
    "sg:city":"Dordrecht",
    "sg:orig_category":"Milieu",
    "sg:phone":"+31 78 616 4198",
    "sg:postcode":"3315 AG",
    "sg:province":"Zuid-Holland",
    "wof:name":"Ecotechniek +",
    "wof:placetype":"venue"
},
  "geometry": {"coordinates":[4.721176,51.800907],"type":"Point"}
}