{
  "type": "Feature",
  "properties": {
    "addr:full":"Adriana Noorlandersingel 105 Rotterdam Zuid-Holland 3065 HE",
    "addr:housenumber":"105",
    "addr:postcode":"3065 he",
    "addr:street":"Adriana Noorlandersingel",
    "iso:country":"NL",
    "sg:address":"Adriana Noorlandersingel 105",
    "sg:city":"Rotterdam",
    "sg:orig_category":"Boekhouders",
    "sg:phone":"+31 10 202 4831",
    "sg:postcode":"3065 HE",
    "sg:province":"Zuid-Holland",
    "wof:name":"De Groot & Van Dam Bv",
    "wof:placetype":"venue"
},
  "geometry": {"coordinates":[4.55445,51.928291],"type":"Point"}
}