{
  "type": "Feature",
  "properties": {
    "iso:country":"NL",
    "sg:address":"Nw Holsterwg 15",
    "sg:city":"Posterholt",
    "sg:orig_category":"Adviesbureaus Bedrijfsorganisatie",
    "sg:phone":"+31 475 403 530",
    "sg:postcode":"6061 EG",
    "sg:province":"Limburg",
    "wof:name":"Coin Bv",
    "wof:placetype":"venue"
},
  "geometry": {"coordinates":[6.033745,51.123707],"type":"Point"}
}