{
  "type": "Feature",
  "properties": {
    "addr:full":"Mauritsstr 8 Breda North Brabant 4811 EP",
    "addr:housenumber":"8",
    "addr:postcode":"4811 ep",
    "addr:street":"Mauritsstr",
    "iso:country":"NL",
    "sg:address":"Mauritsstr 8",
    "sg:city":"Breda",
    "sg:orig_category":"Verenigingen En Stichtingen",
    "sg:phone":"+31 76 521 2062",
    "sg:postcode":"4811 EP",
    "sg:province":"North Brabant",
    "wof:name":"A Propos Circus, Sticht",
    "wof:placetype":"venue"
},
  "geometry": {"coordinates":[4.784613,51.592194],"type":"Point"}
}