{
  "type": "Feature",
  "properties": {
    "addr:full":"Oostvlietwg 18K Leidschendam Zuid-Holland 2266 BL",
    "addr:housenumber":"18k",
    "addr:postcode":"2266 bl",
    "addr:street":"Oostvlietwg",
    "iso:country":"NL",
    "sg:address":"Oostvlietwg 18K",
    "sg:city":"Leidschendam",
    "sg:orig_category":"Naamplaten - Fabrieken",
    "sg:phone":"+31 70 317 6920",
    "sg:postcode":"2266 BL",
    "sg:province":"Zuid-Holland",
    "wof:name":"Georgina Bv",
    "wof:placetype":"venue"
},
  "geometry": {"coordinates":[4.404171,52.0844],"type":"Point"}
}