{
  "type": "Feature",
  "properties": {
    "addr:full":"Vitusholt 4E Ln 1 Winschoten Groningen 9674 AS",
    "addr:housenumber":"1",
    "addr:postcode":"9674 as",
    "addr:street":"Vitusholt 4E Ln",
    "iso:country":"NL",
    "sg:address":"Vitusholt 4E Ln 1",
    "sg:city":"Winschoten",
    "sg:orig_category":"Motorrevisie En -Inbouw",
    "sg:phone":"+31 597 422 020",
    "sg:postcode":"9674 AS",
    "sg:province":"Groningen",
    "wof:name":"Pro Tuning",
    "wof:placetype":"venue"
},
  "geometry": {"coordinates":[7.017926,53.139198],"type":"Point"}
}