{
  "type": "Feature",
  "properties": {
    "addr:full":"Goudsbloemstr 207 Amsterdam Noord-Holland 1015 JN",
    "addr:housenumber":"207",
    "addr:postcode":"1015 jn",
    "iso:country":"NL",
    "sg:address":"Goudsbloemstr 207",
    "sg:city":"Amsterdam",
    "sg:orig_category":"Zalenverhuur",
    "sg:phone":"+31 20 625 2470",
    "sg:postcode":"1015 JN",
    "sg:province":"Noord-Holland",
    "sg:website":"http://www.thalia.nl",
    "wof:name":"Thalia Party Home",
    "wof:placetype":"venue"
},
  "geometry": {"coordinates":[4.881217,52.380135],"type":"Point"}
}