{
  "type": "Feature",
  "properties": {
    "addr:full":"Ohmwg 38 Alblasserdam Zuid-Holland 2952 BE",
    "addr:housenumber":"38",
    "addr:postcode":"2952",
    "addr:street":"Ohmwg",
    "iso:country":"NL",
    "sg:address":"Ohmwg 38",
    "sg:city":"Alblasserdam",
    "sg:orig_category":"Administratie- En Boekhoudkantoren",
    "sg:phone":"+31 78 693 3906",
    "sg:postcode":"2952 BE",
    "sg:province":"Zuid-Holland",
    "wof:name":"Dijk, De",
    "wof:placetype":"venue"
},
  "geometry": {"coordinates":[4.673199,51.85881],"type":"Point"}
}