{
  "type": "Feature",
  "properties": {
    "addr:full":"Seringenstr 11 Breskens Zeeland 4511 GJ",
    "addr:housenumber":"11",
    "addr:postcode":"4511 gj",
    "addr:street":"Seringenstr",
    "iso:country":"NL",
    "sg:address":"Seringenstr 11",
    "sg:city":"Breskens",
    "sg:orig_category":"Honden- En Kattentrimsalons",
    "sg:phone":"+31 117 382 868",
    "sg:postcode":"4511 GJ",
    "sg:province":"Zeeland",
    "wof:name":"Schuurtje Hondentrimsalon, 'T",
    "wof:placetype":"venue"
},
  "geometry": {"coordinates":[3.550831,51.396122],"type":"Point"}
}