{
  "type": "Feature",
  "properties": {
    "addr:full":"Brederodelaan 15 Deventer NL.08 7412 NG",
    "addr:housenumber":"15;nl.08",
    "addr:postcode":"7412 ng",
    "addr:street":"Brederodelaan",
    "iso:country":"NL",
    "sg:address":"Brederodelaan 15",
    "sg:city":"Deventer",
    "sg:orig_category":"Boekhouders",
    "sg:phone":"+31 570 640 858",
    "sg:postcode":"7412 NG",
    "sg:province":"NL.08",
    "wof:name":"Administratiekantoor Kolkman Vof",
    "wof:placetype":"venue"
},
  "geometry": {"coordinates":[6.135966,52.269073],"type":"Point"}
}