{
  "type": "Feature",
  "properties": {
    "addr:full":"Laan Van Vollenhove 3011 Zeist Utrecht 3706 AL",
    "addr:housenumber":"3011",
    "addr:postcode":"3706 al",
    "addr:street":"Laan Van Vollenhove",
    "iso:country":"NL",
    "sg:address":"Laan Van Vollenhove 3011",
    "sg:city":"Zeist",
    "sg:orig_category":"Banken And Kredietinstellingen",
    "sg:phone":"+31 30 695 5881",
    "sg:postcode":"3706 AL",
    "sg:province":"Utrecht",
    "wof:name":"Sigaren Boek Tijdschriften Gerrit Geutjes Bv",
    "wof:placetype":"venue"
},
  "geometry": {"coordinates":[5.221041,52.100868],"type":"Point"}
}