{
  "type": "Feature",
  "properties": {
    "addr:full":"Havik 10 Etten-Leur Noord-Brabant 4872 WG",
    "addr:housenumber":"10",
    "addr:postcode":"4872 wg",
    "addr:street":"Havik",
    "iso:country":"NL",
    "sg:address":"Havik 10",
    "sg:city":"Etten-Leur",
    "sg:classifiers":[
        {
            "category":"Bakery",
            "type":"Food & Drink"
        }
    ],
    "sg:phone":"+31 76 501 4547",
    "sg:postcode":"4872 WG",
    "sg:province":"Noord-Brabant",
    "sg:tags":[
        "brood",
        "banket"
    ],
    "wof:name":"J.P. Van Oers",
    "wof:placetype":"venue"
},
  "geometry": {"coordinates":[4.652592,51.572323],"type":"Point"}
}