{
  "type": "Feature",
  "properties": {
    "addr:full":"Ambachtstraat 1 Bergambacht South Holland 2861 EW",
    "addr:housenumber":"1",
    "addr:postcode":"2861 ew",
    "addr:street":"Ambachtstraat",
    "iso:country":"NL",
    "sg:address":"Ambachtstraat 1",
    "sg:city":"Bergambacht",
    "sg:orig_category":"Zuivelproducten And Spijsoli?n Gh",
    "sg:phone":"+31 182 352 233",
    "sg:postcode":"2861 EW",
    "sg:province":"South Holland",
    "wof:name":"Konings Zuivel Bv",
    "wof:placetype":"venue"
},
  "geometry": {"coordinates":[4.786181,51.929981],"type":"Point"}
}