{
  "type": "Feature",
  "properties": {
    "addr:full":"Edisonstr 35 Doetinchem Gelderland 7006 RA",
    "addr:housenumber":"35",
    "addr:postcode":"7006 ra",
    "addr:street":"Edisonstr;Gelderland",
    "iso:country":"NL",
    "sg:address":"Edisonstr 35",
    "sg:city":"Doetinchem",
    "sg:orig_category":"Autoschade- Herstelbedrijven",
    "sg:phone":"+31 314 341 030",
    "sg:postcode":"7006 RA",
    "sg:province":"Gelderland",
    "wof:name":"Asg",
    "wof:placetype":"venue"
},
  "geometry": {"coordinates":[6.262811,51.970425],"type":"Point"}
}