{
  "type": "Feature",
  "properties": {
    "addr:full":"Tolbaas 1 Gorredyk Friesland 8401 GD",
    "addr:housenumber":"1",
    "addr:postcode":"8401 gd",
    "addr:street":"Tolbaas",
    "iso:country":"NL",
    "sg:address":"Tolbaas 1",
    "sg:city":"Gorredyk",
    "sg:orig_category":"Metaalbewerking",
    "sg:phone":"+31 513 466 661",
    "sg:postcode":"8401 GD",
    "sg:province":"Friesland",
    "wof:name":"Haan, De",
    "wof:placetype":"venue"
},
  "geometry": {"coordinates":[6.062881,53.014408],"type":"Point"}
}