{
  "type": "Feature",
  "properties": {
    "iso:country":"NL",
    "sg:address":"Nijmegenstraat 26",
    "sg:city":"Rotterdam",
    "sg:classifiers":[
        {
            "category":"Retail",
            "subcategory":"Storage",
            "type":"Services"
        }
    ],
    "sg:phone":"+31 10 428 2544",
    "sg:postcode":"3087 CD",
    "sg:province":"Zuid-Holland",
    "sg:tags":[
        "opslag",
        "bewaring"
    ],
    "wof:name":"Dijfo Warehousing Bv",
    "wof:placetype":"venue"
},
  "geometry": {"coordinates":[4.4543180466,51.8891944885],"type":"Point"}
}