{
  "type": "Feature",
  "properties": {
    "iso:country":"NL",
    "sg:address":"Weth Lommenstr 72",
    "sg:city":"Venlo",
    "sg:orig_category":"Koeriersdiensten",
    "sg:phone":"+31 6 19190115",
    "sg:postcode":"5913 RR",
    "sg:province":"Limburg",
    "wof:name":"Rapid",
    "wof:placetype":"venue"
},
  "geometry": {"coordinates":[6.186979,51.363949],"type":"Point"}
}