{
  "type": "Feature",
  "properties": {
    "addr:full":"Kyckerwg 84 De Lier South Holland 2678 AE",
    "addr:housenumber":"84",
    "addr:postcode":"2678 ae",
    "addr:street":"Kyckerwg",
    "iso:country":"NL",
    "sg:address":"Kyckerwg 84",
    "sg:city":"De Lier",
    "sg:orig_category":"Kassenonderhoud",
    "sg:phone":"+31 174 516 755",
    "sg:postcode":"2678 AE",
    "sg:province":"South Holland",
    "wof:name":"Kester, T M M",
    "wof:placetype":"venue"
},
  "geometry": {"coordinates":[4.240755,51.97504],"type":"Point"}
}