{
  "type": "Feature",
  "properties": {
    "addr:full":"Brandlichterwg 2 Denekamp Overijssel 7591 AR",
    "addr:housenumber":"2",
    "addr:postcode":"7591",
    "addr:street":"Brandlichterwg",
    "iso:country":"NL",
    "sg:address":"Brandlichterwg 2",
    "sg:city":"Denekamp",
    "sg:classifiers":[
        {
            "category":"Food & Beverages",
            "subcategory":"Bakery",
            "type":"Retail Goods"
        }
    ],
    "sg:phone":"+31 541 351 694",
    "sg:postcode":"7591 AR",
    "sg:province":"Overijssel",
    "sg:tags":[
        "brood",
        "en",
        "banket"
    ],
    "wof:name":"Kienhuis",
    "wof:placetype":"venue"
},
  "geometry": {"coordinates":[7.008262,52.376831],"type":"Point"}
}