{
  "type": "Feature",
  "properties": {
    "addr:full":"Churchilllaan 181 Amsterdam Noord-Holland 1078 DZ",
    "addr:housenumber":"181",
    "addr:postcode":"1078 dz",
    "addr:street":"Churchilllaan",
    "iso:country":"NL",
    "sg:address":"Churchilllaan 181",
    "sg:city":"Amsterdam",
    "sg:orig_category":"Fotostudio'S And Fotografen",
    "sg:phone":"+31 20 671 5700",
    "sg:postcode":"1078 DZ",
    "sg:province":"Noord-Holland",
    "wof:name":"Ed Van Wersch Fotograaf",
    "wof:placetype":"venue"
},
  "geometry": {"coordinates":[4.889727,52.346848],"type":"Point"}
}