{
  "type": "Feature",
  "properties": {
    "addr:full":"Pr Bernhardln 228-232 Voorburg Zuid-Holland 2273 BP",
    "addr:postcode":"228-232;2273 bp",
    "iso:country":"NL",
    "sg:address":"Pr Bernhardln 228-232",
    "sg:city":"Voorburg",
    "sg:orig_category":"Woninginrichting",
    "sg:phone":"+31 70 386 4404",
    "sg:postcode":"2273 BP",
    "sg:province":"Zuid-Holland",
    "wof:name":"Veltman, Project & Woninginrichting",
    "wof:placetype":"venue"
},
  "geometry": {"coordinates":[4.3597698212,52.0784797668],"type":"Point"}
}