{
  "type": "Feature",
  "properties": {
    "addr:full":"Burg Maeyerstr 6 Moergestel North Brabant 5066 VL",
    "addr:housenumber":"6",
    "addr:postcode":"5066 vl",
    "addr:street":"Burg Maeyerstr",
    "iso:country":"NL",
    "sg:address":"Burg Maeyerstr 6",
    "sg:city":"Moergestel",
    "sg:orig_category":"Waterbouwkundige Werken",
    "sg:phone":"+31 6 51203745",
    "sg:postcode":"5066 VL",
    "sg:province":"North Brabant",
    "wof:name":"Berkel, J H E Van",
    "wof:placetype":"venue"
},
  "geometry": {"coordinates":[5.1836409569,51.5454978943],"type":"Point"}
}