{
  "type": "Feature",
  "properties": {
    "addr:full":"Oerdonk 11 Beuningen Gld Gelderland 6641 LH",
    "addr:housenumber":"11",
    "addr:postcode":"6641 lh",
    "addr:street":"Oerdonk",
    "iso:country":"NL",
    "sg:address":"Oerdonk 11",
    "sg:city":"Beuningen Gld",
    "sg:orig_category":"Administratie- En Boekhoudkantoren",
    "sg:phone":"+31 24 677 5795",
    "sg:postcode":"6641 LH",
    "sg:province":"Gelderland",
    "wof:name":"Lunei",
    "wof:placetype":"venue"
},
  "geometry": {"coordinates":[5.7577,51.867378],"type":"Point"}
}