{
  "type": "Feature",
  "properties": {
    "addr:full":"Cederlaan 75 Eindhoven Noord-Brabant 5616 SC",
    "addr:housenumber":"75",
    "addr:postcode":"5616 sc",
    "addr:street":"Cederlaan",
    "iso:country":"NL",
    "sg:address":"Cederlaan 75",
    "sg:city":"Eindhoven",
    "sg:orig_category":"Verzekeringen",
    "sg:phone":"+31 40 251 5064",
    "sg:postcode":"5616 SC",
    "sg:province":"Noord-Brabant",
    "wof:name":"Assurantiekantoor F. Saris",
    "wof:placetype":"venue"
},
  "geometry": {"coordinates":[5.451383,51.445141],"type":"Point"}
}