{
  "type": "Feature",
  "properties": {
    "iso:country":"NL",
    "sg:address":"Westerstr 15",
    "sg:city":"Amsterdam",
    "sg:orig_category":"Boeken En Tijdschriften",
    "sg:phone":"+31 20 638 9252",
    "sg:postcode":"1015 LT",
    "sg:province":"Noord-Holland",
    "sg:website":"http://www.libris.nl",
    "wof:name":"Island Bookstore",
    "wof:placetype":"venue"
},
  "geometry": {"coordinates":[4.88606,52.37878],"type":"Point"}
}