{
  "type": "Feature",
  "properties": {
    "addr:full":"Vier Ambachtenstraat 39 Sas Van Gent BE.08 4551 HA",
    "addr:housenumber":"39",
    "addr:postcode":"4551 ha",
    "addr:street":"Vier Ambachtenstraat",
    "iso:country":"NL",
    "sg:address":"Vier Ambachtenstraat 39",
    "sg:city":"Sas Van Gent",
    "sg:orig_category":"Kansspelen",
    "sg:phone":"+31 115 453 490",
    "sg:postcode":"4551 HA",
    "sg:province":"BE.08",
    "wof:name":"Hurricane Horeca Exploitatie Bv",
    "wof:placetype":"venue"
},
  "geometry": {"coordinates":[3.791960001,51.2291679382],"type":"Point"}
}