{
  "type": "Feature",
  "properties": {
    "addr:full":"Hummelosewg 8 Zelhem Gelderland 7021 AE",
    "addr:housenumber":"8",
    "addr:postcode":"7021 ae",
    "addr:street":"Hummelosewg;Gelderland",
    "iso:country":"NL",
    "sg:address":"Hummelosewg 8",
    "sg:city":"Zelhem",
    "sg:orig_category":"Banken",
    "sg:phone":"+31 314 628 611",
    "sg:postcode":"7021 AE",
    "sg:province":"Gelderland",
    "sg:website":"http://www.rabobank.nl",
    "wof:name":"Rabobank",
    "wof:placetype":"venue"
},
  "geometry": {"coordinates":[6.294474,52.003677],"type":"Point"}
}