{
  "type": "Feature",
  "properties": {
    "iso:country":"NL",
    "sg:address":"Gieteling 6",
    "sg:city":"Raalte",
    "sg:orig_category":"Goederenvervoer Over De Weg",
    "sg:phone":"+31 572 352 529",
    "sg:postcode":"8103 EZ",
    "sg:province":"NL.08",
    "wof:name":"Huiskamp Internationaal Transport",
    "wof:placetype":"venue"
},
  "geometry": {"coordinates":[6.287048,52.395039],"type":"Point"}
}