{
  "type": "Feature",
  "properties": {
    "addr:full":"Gieteling 6 Raalte NL.08 8103 EZ",
    "addr:housenumber":"6;nl.08",
    "addr:postcode":"8103 ez",
    "addr:street":"Gieteling",
    "iso:country":"NL",
    "sg:address":"Gieteling 6",
    "sg:city":"Raalte",
    "sg:orig_category":"Goederenvervoer Over De Weg",
    "sg:phone":"+31 572 352 529",
    "sg:postcode":"8103 EZ",
    "sg:province":"NL.08",
    "wof:name":"Huiskamp Internationaal Transport",
    "wof:placetype":"venue"
},
  "geometry": {"coordinates":[6.287048,52.395039],"type":"Point"}
}