{
  "type": "Feature",
  "properties": {
    "addr:full":"Molenstr 36 Schagen North Holland 1741 GK",
    "addr:housenumber":"36",
    "addr:postcode":"1741 gk",
    "addr:street":"Molenstr",
    "iso:country":"NL",
    "sg:address":"Molenstr 36",
    "sg:city":"Schagen",
    "sg:orig_category":"Babyartikelen",
    "sg:phone":"+31 224 297 346",
    "sg:postcode":"1741 GK",
    "sg:province":"North Holland",
    "wof:name":"Zeuvenuursgoed",
    "wof:placetype":"venue"
},
  "geometry": {"coordinates":[4.803001,52.787758],"type":"Point"}
}