{
  "type": "Feature",
  "properties": {
    "addr:full":"Oegstgeesterweg 2 Rijnsburg Zuid-Holland 2231 AX",
    "addr:housenumber":"2",
    "addr:postcode":"2231 ax",
    "addr:street":"Oegstgeesterweg",
    "iso:country":"NL",
    "sg:address":"Oegstgeesterweg 2",
    "sg:city":"Rijnsburg",
    "sg:orig_category":"Bloemen And Planten Gh",
    "sg:phone":"+31 71 402 0793",
    "sg:postcode":"2231 AX",
    "sg:province":"Zuid-Holland",
    "wof:name":"F. Noort",
    "wof:placetype":"venue"
},
  "geometry": {"coordinates":[4.440649,52.18911],"type":"Point"}
}