{
  "type": "Feature",
  "properties": {
    "addr:full":"Halmaheirastr 28 Amsterdam Noord-Holland 1094 RL",
    "addr:housenumber":"28",
    "addr:postcode":"1094 rl",
    "addr:street":"Halmaheirastr",
    "iso:country":"NL",
    "sg:address":"Halmaheirastr 28",
    "sg:city":"Amsterdam",
    "sg:orig_category":"Sauna'S",
    "sg:phone":"+31 20 665 6405",
    "sg:postcode":"1094 RL",
    "sg:province":"Noord-Holland",
    "sg:website":"http://www.sauna-viking.nl",
    "wof:name":"Viking",
    "wof:placetype":"venue"
},
  "geometry": {"coordinates":[4.939306,52.359783],"type":"Point"}
}