{
  "type": "Feature",
  "properties": {
    "addr:full":"Croonstadtln 4B Mydrecht Utrecht 3641 AL",
    "addr:housenumber":"4b",
    "addr:postcode":"3641 al",
    "addr:street":"Croonstadtln",
    "iso:country":"NL",
    "sg:address":"Croonstadtln 4B",
    "sg:city":"Mydrecht",
    "sg:orig_category":"Organisatiebureaus",
    "sg:phone":"+31 297 287 256",
    "sg:postcode":"3641 AL",
    "sg:province":"Utrecht",
    "sg:website":"http://www.invisible.nl",
    "wof:name":"Invisible Organizing",
    "wof:placetype":"venue"
},
  "geometry": {"coordinates":[4.8617801666,52.2057800293],"type":"Point"}
}