{
  "type": "Feature",
  "properties": {
    "addr:full":"Kerkweg 13 A Valkenswaard Noord-Brabant 5554 NJ",
    "addr:housenumber":"13 a",
    "addr:postcode":"5554 nj",
    "addr:street":"Kerkweg",
    "iso:country":"NL",
    "sg:address":"Kerkweg 13 A",
    "sg:city":"Valkenswaard",
    "sg:orig_category":"Hypotheken And Hypotheekbanken",
    "sg:phone":"+31 40 203 0300",
    "sg:postcode":"5554 NJ",
    "sg:province":"Noord-Brabant",
    "wof:name":"Verhappen Assurantien",
    "wof:placetype":"venue"
},
  "geometry": {"coordinates":[5.455777,51.349758],"type":"Point"}
}