{
  "type": "Feature",
  "properties": {
    "iso:country":"NL",
    "sg:address":"Bermdk 5",
    "sg:city":"Rotterdam",
    "sg:orig_category":"Adviesbureaus Bouwkunde",
    "sg:phone":"+31 10 479 6841",
    "sg:postcode":"3079 TM",
    "sg:province":"Zuid-Holland",
    "wof:name":"Gr Engeneering",
    "wof:placetype":"venue"
},
  "geometry": {"coordinates":[4.543522,51.875481],"type":"Point"}
}