{
  "type": "Feature",
  "properties": {
    "addr:full":"Troelstraln 9 Utrecht Utrecht 3515 CA",
    "addr:housenumber":"9",
    "addr:postcode":"3515 ca",
    "addr:street":"Troelstraln",
    "iso:country":"NL",
    "sg:address":"Troelstraln 9",
    "sg:city":"Utrecht",
    "sg:orig_category":"Beeldende Kunstenaars",
    "sg:phone":"+31 30 271 0843",
    "sg:postcode":"3515 CA",
    "sg:province":"Utrecht",
    "wof:name":"Huneman, J",
    "wof:placetype":"venue"
},
  "geometry": {"coordinates":[5.115589,52.101421],"type":"Point"}
}