{
  "type": "Feature",
  "properties": {
    "addr:full":"Ydoornln 599 Amsterdam Noord-Holland 1024 KT",
    "addr:housenumber":"599",
    "addr:postcode":"1024 kt",
    "iso:country":"NL",
    "sg:address":"Ydoornln 599",
    "sg:city":"Amsterdam",
    "sg:orig_category":"Artsen - Huisartsen",
    "sg:phone":"+31 20 494 0229",
    "sg:postcode":"1024 KT",
    "sg:province":"Noord-Holland",
    "wof:name":"Lie, A K",
    "wof:placetype":"venue"
},
  "geometry": {"coordinates":[4.952025,52.39674],"type":"Point"}
}