{
  "type": "Feature",
  "properties": {
    "addr:full":"Hoogstr 22A Rotterdam Zuid-Holland 3011 PP",
    "addr:housenumber":"22a",
    "addr:postcode":"3011 pp",
    "addr:street":"Hoogstr",
    "iso:country":"NL",
    "sg:address":"Hoogstr 22A",
    "sg:city":"Rotterdam",
    "sg:orig_category":"Scheepstextiel - Groothandel",
    "sg:phone":"+31 10 433 0500",
    "sg:postcode":"3011 PP",
    "sg:province":"Zuid-Holland",
    "wof:name":"Temaro Bv",
    "wof:placetype":"venue"
},
  "geometry": {"coordinates":[4.494168,51.922886],"type":"Point"}
}