{
  "type": "Feature",
  "properties": {
    "iso:country":"NL",
    "sg:address":"Zijlweg 58",
    "sg:city":"Haarlem",
    "sg:orig_category":"Bloemen And Planten",
    "sg:phone":"+31 23 532 6448",
    "sg:postcode":"2013 DJ",
    "sg:province":"Noord-Holland",
    "wof:name":"Aalsmeers Bloemenhuis",
    "wof:placetype":"venue"
},
  "geometry": {"coordinates":[4.625934,52.384533],"type":"Point"}
}