{
  "type": "Feature",
  "properties": {
    "addr:full":"Boommarkt 23 Leiden South Holland 2311 EA",
    "addr:housenumber":"23",
    "addr:postcode":"2311 ea",
    "addr:street":"Boommarkt",
    "iso:country":"NL",
    "sg:address":"Boommarkt 23",
    "sg:city":"Leiden",
    "sg:classifiers":[
        {
            "category":"Travel",
            "subcategory":"Hotels & Motels",
            "type":"Entertainment"
        }
    ],
    "sg:phone":"+31 71 512 6358",
    "sg:postcode":"2311 EA",
    "sg:province":"South Holland",
    "wof:name":"Nieuw Minerva Hotel-Restaurant Bv",
    "wof:placetype":"venue"
},
  "geometry": {"coordinates":[4.488246,52.160107],"type":"Point"}
}