{
  "type": "Feature",
  "properties": {
    "addr:full":"Kon Wilhelminaln 21 Wezep Gelderland 8091 AP",
    "addr:housenumber":"21",
    "addr:postcode":"8091 ap",
    "addr:street":"Kon",
    "iso:country":"NL",
    "sg:address":"Kon Wilhelminaln 21",
    "sg:city":"Wezep",
    "sg:orig_category":"Psychotherapeuten",
    "sg:phone":"+31 38 376 4245",
    "sg:postcode":"8091 AP",
    "sg:province":"Gelderland",
    "wof:name":"Weterings, A P",
    "wof:placetype":"venue"
},
  "geometry": {"coordinates":[6.002605,52.447659],"type":"Point"}
}