{
  "type": "Feature",
  "properties": {
    "addr:full":"Landleeuw 19 Hoofddorp Noord-Holland 2131 HV",
    "addr:housenumber":"19",
    "addr:postcode":"2131 hv",
    "addr:street":"Landleeuw",
    "iso:country":"NL",
    "sg:address":"Landleeuw 19",
    "sg:city":"Hoofddorp",
    "sg:orig_category":"Koel- En Vriestransporten",
    "sg:phone":"+31 23 561 5686",
    "sg:postcode":"2131 HV",
    "sg:province":"Noord-Holland",
    "wof:name":"Top, G Van De",
    "wof:placetype":"venue"
},
  "geometry": {"coordinates":[4.683626,52.314396],"type":"Point"}
}