{
  "type": "Feature",
  "properties": {
    "addr:full":"Loevenhoutsedijk 2 Utrecht Utrecht 3552 XE",
    "addr:housenumber":"2",
    "addr:postcode":"3552 xe",
    "addr:street":"Loevenhoutsedijk",
    "iso:country":"NL",
    "sg:address":"Loevenhoutsedijk 2",
    "sg:city":"Utrecht",
    "sg:orig_category":"Sportclubs",
    "sg:phone":"+31 30 261 4489",
    "sg:postcode":"3552 XE",
    "sg:province":"Utrecht",
    "wof:name":"Synergo Korfbalvereniging",
    "wof:placetype":"venue"
},
  "geometry": {"coordinates":[5.111946,52.108315],"type":"Point"}
}