{
  "type": "Feature",
  "properties": {
    "addr:full":"Kerkstraat 4 Alphen Gld Gelderland 6626 AK",
    "addr:housenumber":"4",
    "addr:postcode":"6626 ak",
    "addr:street":"Kerkstraat;Gld Gelderland",
    "iso:country":"NL",
    "sg:address":"Kerkstraat 4",
    "sg:city":"Alphen Gld",
    "sg:orig_category":"Kappers",
    "sg:phone":"+31 487 561 600",
    "sg:postcode":"6626 AK",
    "sg:province":"Gelderland",
    "wof:name":"Salon Nicolet",
    "wof:placetype":"venue"
},
  "geometry": {"coordinates":[5.474375,51.821445],"type":"Point"}
}