{
  "type": "Feature",
  "properties": {
    "iso:country":"NL",
    "sg:address":"Bronsteeweg 8",
    "sg:city":"Heemstede",
    "sg:orig_category":"Verlichting And Huishoudartikelen",
    "sg:phone":"+31 23 528 4422",
    "sg:postcode":"2101 AC",
    "sg:province":"North Holland",
    "wof:name":"Cameleon",
    "wof:placetype":"venue"
},
  "geometry": {"coordinates":[4.622755,52.357685],"type":"Point"}
}