{
  "type": "Feature",
  "properties": {
    "addr:full":"Ds De Jongln 1 Venlo Limburg 5913 RL",
    "addr:housenumber":"1",
    "addr:postcode":"5913 rl",
    "addr:street":"Ds;Jongln",
    "iso:country":"NL",
    "sg:address":"Ds De Jongln 1",
    "sg:city":"Venlo",
    "sg:orig_category":"Adviesbureaus Bouwkunde",
    "sg:phone":"+31 77 352 6486",
    "sg:postcode":"5913 RL",
    "sg:province":"Limburg",
    "wof:name":"Driessen'S Calculatie Buro",
    "wof:placetype":"venue"
},
  "geometry": {"coordinates":[6.17286,51.372421],"type":"Point"}
}