{
  "type": "Feature",
  "properties": {
    "addr:full":"Mon Plaisir 59 Etten-Leur Noord-Brabant 4879 AL",
    "addr:housenumber":"59",
    "addr:postcode":"4879 al",
    "addr:street":"Mon Plaisir",
    "iso:country":"NL",
    "sg:address":"Mon Plaisir 59",
    "sg:city":"Etten-Leur",
    "sg:orig_category":"Gespecialiseerde Bouw",
    "sg:phone":"+31 76 501 6404",
    "sg:postcode":"4879 AL",
    "sg:province":"Noord-Brabant",
    "wof:name":"Betonboringen Zuid Nederland Bv",
    "wof:placetype":"venue"
},
  "geometry": {"coordinates":[4.620907,51.562122],"type":"Point"}
}