{
  "type": "Feature",
  "properties": {
    "iso:country":"NL",
    "sg:address":"Hoofdweg 47",
    "sg:city":"De Kwakel",
    "sg:orig_category":"Bloemen And Planten",
    "sg:phone":"+31 297 343 359",
    "sg:postcode":"1424 PC",
    "sg:province":"Noord-Holland",
    "wof:name":"Kwekerij W. Van Diemen Bv",
    "wof:placetype":"venue"
},
  "geometry": {"coordinates":[4.774611,52.2416],"type":"Point"}
}