{
  "type": "Feature",
  "properties": {
    "addr:full":"Hoofdweg 47 De Kwakel Noord-Holland 1424 PC",
    "addr:housenumber":"47",
    "addr:postcode":"1424 pc",
    "addr:street":"Hoofdweg",
    "iso:country":"NL",
    "sg:address":"Hoofdweg 47",
    "sg:city":"De Kwakel",
    "sg:orig_category":"Bloemen And Planten",
    "sg:phone":"+31 297 343 359",
    "sg:postcode":"1424 PC",
    "sg:province":"Noord-Holland",
    "wof:name":"Kwekerij W. Van Diemen Bv",
    "wof:placetype":"venue"
},
  "geometry": {"coordinates":[4.774611,52.2416],"type":"Point"}
}