{
  "type": "Feature",
  "properties": {
    "addr:full":"Javastraat 53A 'S-Gravenhage South Holland 2585 AE",
    "addr:housenumber":"53a",
    "addr:postcode":"2585 ae",
    "addr:street":"Javastraat",
    "iso:country":"NL",
    "sg:address":"Javastraat 53A",
    "sg:city":"'S-Gravenhage",
    "sg:orig_category":"Beleggingen",
    "sg:phone":"+31 70 364 2433",
    "sg:postcode":"2585 AE",
    "sg:province":"South Holland",
    "wof:name":"Bmr",
    "wof:placetype":"venue"
},
  "geometry": {"coordinates":[4.309844,52.088989],"type":"Point"}
}