{
  "type": "Feature",
  "properties": {
    "addr:full":"2E Haagstr 40 Helmond Noord-Brabant 5707 VK",
    "addr:housenumber":"40",
    "addr:postcode":"5707 vk",
    "addr:street":"2E Haagstr",
    "iso:country":"NL",
    "sg:address":"2E Haagstr 40",
    "sg:city":"Helmond",
    "sg:orig_category":"Peuterspeelzalen",
    "sg:phone":"+31 492 550 681",
    "sg:postcode":"5707 VK",
    "sg:province":"Noord-Brabant",
    "wof:name":"Rakkertjes, De",
    "wof:placetype":"venue"
},
  "geometry": {"coordinates":[5.644832,51.475533],"type":"Point"}
}