{
  "type": "Feature",
  "properties": {
    "addr:full":"Doctor Gravemeyerstraat 28 Giessenburg South Holland 3381 LD",
    "addr:housenumber":"28",
    "addr:postcode":"3381 ld",
    "addr:street":"Doctor Gravemeyerstraat",
    "iso:country":"NL",
    "sg:address":"Doctor Gravemeyerstraat 28",
    "sg:city":"Giessenburg",
    "sg:orig_category":"Metaalwerken",
    "sg:phone":"+31 184 651 357",
    "sg:postcode":"3381 LD",
    "sg:province":"South Holland",
    "wof:name":"H. Wijnja Montagebedrijf Vof",
    "wof:placetype":"venue"
},
  "geometry": {"coordinates":[4.865087,51.842182],"type":"Point"}
}