{
  "type": "Feature",
  "properties": {
    "addr:full":"Ir Vd Sluysplnts 47 S Gravenhage Zuid-Holland 2591 CW",
    "addr:housenumber":"47;gravenhage",
    "addr:postcode":"2591 cw",
    "addr:street":"Ir;S",
    "iso:country":"NL",
    "sg:address":"Ir Vd Sluysplnts 47",
    "sg:city":"S Gravenhage",
    "sg:orig_category":"Adviesbureaus",
    "sg:phone":"+31 70 383 1455",
    "sg:postcode":"2591 CW",
    "sg:province":"Zuid-Holland",
    "wof:name":"Reinders Partn",
    "wof:placetype":"venue"
},
  "geometry": {"coordinates":[4.3639,52.09351],"type":"Point"}
}