{
  "type": "Feature",
  "properties": {
    "addr:full":"H Dunantln 133 Ryswyk Zh South Holland 2286 GD",
    "addr:housenumber":"133",
    "addr:postcode":"2286 gd",
    "addr:street":"Ryswyk Zh",
    "iso:country":"NL",
    "sg:address":"H Dunantln 133",
    "sg:city":"Ryswyk Zh",
    "sg:classifiers":[
        {
            "category":"Personal",
            "subcategory":"Nail Salon",
            "type":"Services"
        }
    ],
    "sg:phone":"+31 70 393 6238",
    "sg:postcode":"2286 GD",
    "sg:province":"South Holland",
    "sg:tags":[
        "pedicure"
    ],
    "wof:name":"Buss-Carbo, J",
    "wof:placetype":"venue"
},
  "geometry": {"coordinates":[4.32436,52.037251],"type":"Point"}
}