{
  "type": "Feature",
  "properties": {
    "addr:full":"Maldenhof 212 Amsterdam Zuidoost North Holland 1106 EX",
    "addr:housenumber":"212",
    "addr:postcode":"1106 ex",
    "addr:street":"Maldenhof",
    "iso:country":"NL",
    "sg:address":"Maldenhof 212",
    "sg:city":"Amsterdam Zuidoost",
    "sg:orig_category":"Kantoorartikelen",
    "sg:phone":"+31 20 697 3294",
    "sg:postcode":"1106 EX",
    "sg:province":"North Holland",
    "wof:name":"Tol Electronica",
    "wof:placetype":"venue"
},
  "geometry": {"coordinates":[4.9673218727,52.3031005859],"type":"Point"}
}