{
  "type": "Feature",
  "properties": {
    "addr:full":"Hogelandseweg 8 Nijmegen Gelderland 6545 AC",
    "addr:housenumber":"8",
    "addr:postcode":"6545 ac",
    "addr:street":"Hogelandseweg;Gelderland",
    "iso:country":"NL",
    "sg:address":"Hogelandseweg 8",
    "sg:city":"Nijmegen",
    "sg:orig_category":"Metaalafval, Schrootrecycling And Sloperijen",
    "sg:phone":"+31 24 377 6178",
    "sg:postcode":"6545 AC",
    "sg:province":"Gelderland",
    "wof:name":"Hoogland Autodemontagebedrijf",
    "wof:placetype":"venue"
},
  "geometry": {"coordinates":[5.814814,51.848106],"type":"Point"}
}