{
  "type": "Feature",
  "properties": {
    "addr:full":"Nieuwe Zeeweg 82 Noordwijk Zh Zuid-Holland 2202 HB",
    "addr:housenumber":"82",
    "addr:postcode":"2202 hb",
    "addr:street":"Nieuwe Zeeweg",
    "iso:country":"NL",
    "sg:address":"Nieuwe Zeeweg 82",
    "sg:city":"Noordwijk Zh",
    "sg:orig_category":"Paramedische Behandelingen",
    "sg:phone":"+31 800 0598",
    "sg:postcode":"2202 HB",
    "sg:province":"Zuid-Holland",
    "wof:name":"Kraamzorg Duin En Veen",
    "wof:placetype":"venue"
},
  "geometry": {"coordinates":[4.437854,52.242943],"type":"Point"}
}