{
  "type": "Feature",
  "properties": {
    "iso:country":"NL",
    "sg:address":"Pr Hendrikstr 5",
    "sg:city":"Nymegen",
    "sg:orig_category":"Verenigingen En Stichtingen",
    "sg:phone":"+31 24 323 3018",
    "sg:postcode":"6521 AV",
    "sg:province":"Paran\u00e1",
    "sg:website":"http://www.cossen.nl",
    "wof:name":"Cos Gelderland",
    "wof:placetype":"venue"
},
  "geometry": {"coordinates":[-51.314629,-24.61602],"type":"Point"}
}