{
  "type": "Feature",
  "properties": {
    "iso:country":"NL",
    "sg:address":"A Romein Vers Str 1",
    "sg:city":"Heerlen",
    "sg:orig_category":"Schilders",
    "sg:phone":"+31 45 541 0238",
    "sg:postcode":"6416 HP",
    "sg:province":"Limburg",
    "wof:name":"Laar Heerlen Bv, Van De",
    "wof:placetype":"venue"
},
  "geometry": {"coordinates":[5.991843,50.876255],"type":"Point"}
}