{
  "type": "Feature",
  "properties": {
    "addr:full":"De Moucheronstraat 120 'S Gravenhage Zuid-Holland 2593 RC",
    "addr:housenumber":"120 '",
    "addr:postcode":"2593 rc",
    "addr:street":"De Moucheronstraat",
    "iso:country":"NL",
    "sg:address":"De Moucheronstraat 120",
    "sg:city":"'S Gravenhage",
    "sg:orig_category":"Artistiek Onderwijs",
    "sg:phone":"+31 70 383 6605",
    "sg:postcode":"2593 RC",
    "sg:province":"Zuid-Holland",
    "wof:name":"Workshop Polder",
    "wof:placetype":"venue"
},
  "geometry": {"coordinates":[4.342945,52.0891],"type":"Point"}
}