{
  "type": "Feature",
  "properties": {
    "addr:full":"Molendwstr 54 Twello Gelderland 7391 ZS",
    "addr:housenumber":"54",
    "addr:postcode":"7391 zs",
    "addr:street":"Molendwstr;Gelderland",
    "iso:country":"NL",
    "sg:address":"Molendwstr 54",
    "sg:city":"Twello",
    "sg:orig_category":"Antiquiteiten - Restauratie",
    "sg:phone":"+31 6 51366894",
    "sg:postcode":"7391 ZS",
    "sg:province":"Gelderland",
    "wof:name":"Brouwer",
    "wof:placetype":"venue"
},
  "geometry": {"coordinates":[6.085845,52.233925],"type":"Point"}
}