{
  "type": "Feature",
  "properties": {
    "addr:full":"Lauriergr 148 Amsterdam Noord-Holland 1016 RT",
    "addr:housenumber":"148",
    "addr:postcode":"1016 rt",
    "iso:country":"NL",
    "sg:address":"Lauriergr 148",
    "sg:city":"Amsterdam",
    "sg:orig_category":"Grafisch Ontwerpers",
    "sg:phone":"+31 20 620 5319",
    "sg:postcode":"1016 RT",
    "sg:province":"Noord-Holland",
    "wof:name":"Schriever, Geert",
    "wof:placetype":"venue"
},
  "geometry": {"coordinates":[4.878108,52.370937],"type":"Point"}
}