{
  "type": "Feature",
  "properties": {
    "addr:full":"Het Nieuwe Diep 52 Den Helder Noord-Holland 1781 AE",
    "addr:housenumber":"52",
    "addr:postcode":"1781 ae",
    "addr:street":"Het Nieuwe Diep",
    "iso:country":"NL",
    "sg:address":"Het Nieuwe Diep 52",
    "sg:city":"Den Helder",
    "sg:orig_category":"Metaalbekleding And -Behandeling",
    "sg:phone":"+31 223 630 212",
    "sg:postcode":"1781 AE",
    "sg:province":"Noord-Holland",
    "wof:name":"Teerenstra Bv",
    "wof:placetype":"venue"
},
  "geometry": {"coordinates":[4.783442,52.951408],"type":"Point"}
}