{
  "type": "Feature",
  "properties": {
    "addr:full":"Brederodelaan 32 Beverwijk Noord-Holland 1943 BB",
    "addr:housenumber":"32",
    "addr:postcode":"1943 bb",
    "addr:street":"Brederodelaan",
    "iso:country":"NL",
    "sg:address":"Brederodelaan 32",
    "sg:city":"Beverwijk",
    "sg:orig_category":"Advocaten And Juridische Adviseurs",
    "sg:phone":"+31 251 211 146",
    "sg:postcode":"1943 BB",
    "sg:province":"Noord-Holland",
    "wof:name":"Advocatenkantoor Mr. A.J.P. Schram Bv",
    "wof:placetype":"venue"
},
  "geometry": {"coordinates":[4.642234,52.488823],"type":"Point"}
}