{
  "type": "Feature",
  "properties": {
    "addr:full":"J J Allanstr 427 Westzaan Noord-Holland 1551 RK",
    "addr:housenumber":"427",
    "addr:postcode":"1551 rk",
    "iso:country":"NL",
    "sg:address":"J J Allanstr 427",
    "sg:city":"Westzaan",
    "sg:classifiers":[
        {
            "category":"Home & Garden",
            "subcategory":"Hardware",
            "type":"Retail Goods"
        }
    ],
    "sg:phone":"+31 75 640 2564",
    "sg:postcode":"1551 RK",
    "sg:province":"Noord-Holland",
    "sg:tags":[
        "machine",
        "-",
        "metaalbewerking"
    ],
    "wof:name":"Molen, Van Der",
    "wof:placetype":"venue"
},
  "geometry": {"coordinates":[4.772985,52.460072],"type":"Point"}
}