{
  "type": "Feature",
  "properties": {
    "iso:country":"NL",
    "sg:address":"Haagwg 326",
    "sg:city":"Breda",
    "sg:orig_category":"Behangers",
    "sg:phone":"+31 76 514 4697",
    "sg:postcode":"4813 XE",
    "sg:province":"Noord-Brabant",
    "wof:name":"Stiphout Schilderwerken, M Van",
    "wof:placetype":"venue"
},
  "geometry": {"coordinates":[4.751125,51.579506],"type":"Point"}
}