{
  "type": "Feature",
  "properties": {
    "addr:full":"Berkenstouwe 1A Staphorst NL.08 7951 NC",
    "addr:housenumber":"1a;nl.08 7951",
    "addr:street":"Berkenstouwe",
    "iso:country":"NL",
    "sg:address":"Berkenstouwe 1A",
    "sg:city":"Staphorst",
    "sg:orig_category":"Bestratingen",
    "sg:phone":"+31 522 461 863",
    "sg:postcode":"7951 NC",
    "sg:province":"NL.08",
    "wof:name":"Kooiker, B",
    "wof:placetype":"venue"
},
  "geometry": {"coordinates":[6.232381,52.653118],"type":"Point"}
}