{
  "type": "Feature",
  "properties": {
    "addr:full":"Spanjaardstraat 105 Rotterdam Zuid-Holland 3025 TL",
    "addr:housenumber":"105",
    "addr:postcode":"3025 tl",
    "addr:street":"Spanjaardstraat",
    "iso:country":"NL",
    "sg:address":"Spanjaardstraat 105",
    "sg:city":"Rotterdam",
    "sg:orig_category":"Glaszetten",
    "sg:phone":"+31 10 476 1587",
    "sg:postcode":"3025 TL",
    "sg:province":"Zuid-Holland",
    "wof:name":"Alpino Glas- En Kozijntechniek",
    "wof:placetype":"venue"
},
  "geometry": {"coordinates":[4.44537,51.907188],"type":"Point"}
}