{
  "type": "Feature",
  "properties": {
    "addr:full":"It Stalt 31 Wommels Friesland 8731 EA",
    "addr:housenumber":"31",
    "addr:postcode":"8731 ea",
    "addr:street":"It Stalt",
    "iso:country":"NL",
    "sg:address":"It Stalt 31",
    "sg:city":"Wommels",
    "sg:orig_category":"Makelaars In Onroerend Goed",
    "sg:phone":"+31 515 332 661",
    "sg:postcode":"8731 EA",
    "sg:province":"Friesland",
    "wof:name":"Heem",
    "wof:placetype":"venue"
},
  "geometry": {"coordinates":[5.580899,53.10413],"type":"Point"}
}