{
  "type": "Feature",
  "properties": {
    "addr:full":"Kasteelln 16 Baarlo Lb Limburg 5991 BL",
    "addr:housenumber":"16",
    "addr:postcode":"lb;5991 bl",
    "addr:street":"Kasteelln",
    "iso:country":"NL",
    "sg:address":"Kasteelln 16",
    "sg:city":"Baarlo Lb",
    "sg:orig_category":"Adviesbureaus Bedrijfsorganisatie",
    "sg:phone":"+31 77 477 3363",
    "sg:postcode":"5991 BL",
    "sg:province":"Limburg",
    "wof:name":"Prosol Bv",
    "wof:placetype":"venue"
},
  "geometry": {"coordinates":[6.088565,51.32877],"type":"Point"}
}