{
  "type": "Feature",
  "properties": {
    "iso:country":"NL",
    "sg:address":"Atjehstr 48",
    "sg:city":"Haarlem",
    "sg:orig_category":"Loodgieters",
    "sg:phone":"+31 23 526 9184",
    "sg:postcode":"2022 BR",
    "sg:province":"North Holland",
    "wof:name":"Vink Installatiebedrijf",
    "wof:placetype":"venue"
},
  "geometry": {"coordinates":[4.647609,52.397743],"type":"Point"}
}