{
  "type": "Feature",
  "properties": {
    "addr:full":"M A Reinaldawg 55 Linschoten Utrecht 3461 CD",
    "addr:housenumber":"55",
    "addr:postcode":"3461 cd",
    "iso:country":"NL",
    "sg:address":"M A Reinaldawg 55",
    "sg:city":"Linschoten",
    "sg:orig_category":"Honden- En Kattentrimsalons",
    "sg:phone":"+31 348 415 024",
    "sg:postcode":"3461 CD",
    "sg:province":"Utrecht",
    "wof:name":"Honda Brava Trimsalon & Dagopv",
    "wof:placetype":"venue"
},
  "geometry": {"coordinates":[4.908918,52.064835],"type":"Point"}
}