{
  "type": "Feature",
  "properties": {
    "addr:full":"Dr W Dreeswg 17A Amstelveen Noord-Holland 1188 KA",
    "addr:housenumber":"17a",
    "addr:postcode":"1188 ka",
    "addr:street":"Dr W Dreeswg",
    "iso:country":"NL",
    "sg:address":"Dr W Dreeswg 17A",
    "sg:city":"Amstelveen",
    "sg:orig_category":"Administratie- En Boekhoudkantoren",
    "sg:phone":"+31 20 640 3814",
    "sg:postcode":"1188 KA",
    "sg:province":"Noord-Holland",
    "sg:website":"http://www.brego.nl",
    "wof:name":"Brego, Administratiekantoor",
    "wof:placetype":"venue"
},
  "geometry": {"coordinates":[4.844092,52.280846],"type":"Point"}
}