{
  "type": "Feature",
  "properties": {
    "addr:full":"Markt 7 Silvolde Gelderland 7064 AZ",
    "addr:housenumber":"7",
    "addr:postcode":"7064",
    "addr:street":"Markt;Gelderland",
    "iso:country":"NL",
    "sg:address":"Markt 7",
    "sg:city":"Silvolde",
    "sg:orig_category":"Plafonds",
    "sg:phone":"+31 315 328 728",
    "sg:postcode":"7064 AZ",
    "sg:province":"Gelderland",
    "wof:name":"Holweg",
    "wof:placetype":"venue"
},
  "geometry": {"coordinates":[6.380063,51.910995],"type":"Point"}
}