{
  "type": "Feature",
  "properties": {
    "addr:full":"1E Melmseweg 4 Veenendaal Utrecht 3905 MA",
    "addr:housenumber":"4",
    "addr:postcode":"3905 ma",
    "addr:street":"1E Melmseweg",
    "iso:country":"NL",
    "sg:address":"1E Melmseweg 4",
    "sg:city":"Veenendaal",
    "sg:orig_category":"Goederenvervoer Over De Weg",
    "sg:phone":"+31 318 510 815",
    "sg:postcode":"3905 MA",
    "sg:province":"Utrecht",
    "wof:name":"D. Van Asselt",
    "wof:placetype":"venue"
},
  "geometry": {"coordinates":[5.552923,52.038567],"type":"Point"}
}