{
  "type": "Feature",
  "properties": {
    "iso:country":"NL",
    "sg:address":"Bondstr 13",
    "sg:city":"Lisse",
    "sg:orig_category":"Dansscholen",
    "sg:phone":"+31 252 412 501",
    "sg:postcode":"2161 HA",
    "sg:province":"Zuid-Holland",
    "sg:website":"http://www.danscentrum-welkom.com",
    "wof:name":"Welkom",
    "wof:placetype":"venue"
},
  "geometry": {"coordinates":[4.554444,52.257805],"type":"Point"}
}