{
  "type": "Feature",
  "properties": {
    "iso:country":"NL",
    "sg:address":"Edisonwg 53C",
    "sg:city":"Vlissingen",
    "sg:orig_category":"Webdesign Bureaus",
    "sg:phone":"+31 118 468 585",
    "sg:postcode":"4382 NV",
    "sg:province":"Zeeland",
    "sg:website":"http://www.frisbee.nl",
    "wof:name":"Frisbee",
    "wof:placetype":"venue"
},
  "geometry": {"coordinates":[3.5919859409,51.4543991089],"type":"Point"}
}