{
  "type": "Feature",
  "properties": {
    "addr:full":"Lynbaanstr 14 Haarlem North Holland 2032 PV",
    "addr:housenumber":"14",
    "addr:postcode":"2032 pv",
    "addr:street":"Lynbaanstr",
    "iso:country":"NL",
    "sg:address":"Lynbaanstr 14",
    "sg:city":"Haarlem",
    "sg:orig_category":"Juridische Adviseurs",
    "sg:phone":"+31 23 535 7171",
    "sg:postcode":"2032 PV",
    "sg:province":"North Holland",
    "wof:name":"Kinderen, Mr Saskia Der",
    "wof:placetype":"venue"
},
  "geometry": {"coordinates":[4.64506,52.37841],"type":"Point"}
}