{
  "type": "Feature",
  "properties": {
    "iso:country":"NL",
    "sg:address":"I Sweersstr 23",
    "sg:city":"Nykerk Gld",
    "sg:classifiers":[
        {
            "category":"Professional",
            "subcategory":"Management & Consulting",
            "type":"Services"
        }
    ],
    "sg:phone":"+31 33 246 1975",
    "sg:postcode":"3861 EA",
    "sg:province":"Gelderland",
    "sg:tags":[
        "relation",
        "adviesbureaus",
        "public"
    ],
    "wof:name":"Wvr Pr",
    "wof:placetype":"venue"
},
  "geometry": {"coordinates":[5.4831,52.221569],"type":"Point"}
}