{
  "type": "Feature",
  "properties": {
    "iso:country":"NL",
    "sg:address":"Viswg 21B",
    "sg:city":"Egmond Binnen",
    "sg:orig_category":"Pensioenen",
    "sg:phone":"+31 72 507 1016",
    "sg:postcode":"1935 EB",
    "sg:province":"Noord-Holland",
    "sg:website":"http://www.fiscount.nl",
    "wof:name":"Assucount Kenniscentrum Bv",
    "wof:placetype":"venue"
},
  "geometry": {"coordinates":[4.653385,52.597794],"type":"Point"}
}