{
  "type": "Feature",
  "properties": {
    "iso:country":"NL",
    "sg:address":"Tonnekreek 68",
    "sg:city":"Amersfoort",
    "sg:orig_category":"Kantoorbenodigdheden - Fabrieken En Groothandel",
    "sg:phone":"+31 33 456 0236",
    "sg:postcode":"3823 JJ",
    "sg:province":"Utrecht",
    "wof:name":"Hijtec-Supplies",
    "wof:placetype":"venue"
},
  "geometry": {"coordinates":[5.3988251686,52.1911773682],"type":"Point"}
}