{
  "type": "Feature",
  "properties": {
    "addr:full":"Galileistr 35 Lichtenvoorde Gelderland 7131 PE",
    "addr:housenumber":"35",
    "addr:postcode":"7131 pe",
    "addr:street":"Galileistr;Gelderland",
    "iso:country":"NL",
    "sg:address":"Galileistr 35",
    "sg:city":"Lichtenvoorde",
    "sg:orig_category":"Meubelen - Fabrieken En Groothandel",
    "sg:phone":"+31 544 376 945",
    "sg:postcode":"7131 PE",
    "sg:province":"Gelderland",
    "wof:name":"Nienhuis",
    "wof:placetype":"venue"
},
  "geometry": {"coordinates":[-38.083542,-8.37738],"type":"Point"}
}