{
  "type": "Feature",
  "properties": {
    "addr:full":"Postbus 42 Eygelshoven Limburg 6470 EA",
    "addr:housenumber":"42",
    "addr:postcode":"6470 ea",
    "addr:street":"Postbus",
    "iso:country":"NL",
    "sg:address":"Postbus 42",
    "sg:city":"Eygelshoven",
    "sg:orig_category":"Metaalbewerking",
    "sg:phone":"+31 45 546 8888",
    "sg:postcode":"6470 EA",
    "sg:province":"Limburg",
    "wof:name":"Laura Eygelshoven Bv",
    "wof:placetype":"venue"
},
  "geometry": {"coordinates":[6.06059,50.893688],"type":"Point"}
}