{
  "type": "Feature",
  "properties": {
    "addr:full":"Spinfondswg 7 Vaassen Gelderland 8171 NT",
    "addr:housenumber":"7",
    "addr:postcode":"8171 nt",
    "addr:street":"Spinfondswg;Gelderland",
    "iso:country":"NL",
    "sg:address":"Spinfondswg 7",
    "sg:city":"Vaassen",
    "sg:orig_category":"Verpakkingen En Verpakkingsmaterialen",
    "sg:phone":"+31 578 571 540",
    "sg:postcode":"8171 NT",
    "sg:province":"Gelderland",
    "sg:website":"http://www.aarts.nl",
    "wof:name":"Aarts Bv, T",
    "wof:placetype":"venue"
},
  "geometry": {"coordinates":[5.986206,52.299026],"type":"Point"}
}