{
  "type": "Feature",
  "properties": {
    "addr:full":"Rooseveltlaan 11 Harderwijk Gelderland 3844 AH",
    "addr:housenumber":"11",
    "addr:postcode":"3844 ah",
    "addr:street":"Rooseveltlaan;Gelderland",
    "iso:country":"NL",
    "sg:address":"Rooseveltlaan 11",
    "sg:city":"Harderwijk",
    "sg:orig_category":"Hypotheken And Hypotheekbanken",
    "sg:phone":"+31 341 418 247",
    "sg:postcode":"3844 AH",
    "sg:province":"Gelderland",
    "wof:name":"Hoeksema Verzekeringen",
    "wof:placetype":"venue"
},
  "geometry": {"coordinates":[5.618703,52.333145],"type":"Point"}
}