{
  "type": "Feature",
  "properties": {
    "addr:full":"Wijnstr 160 Dordrecht South Holland 3311 BZ",
    "addr:housenumber":"160",
    "addr:postcode":"3311 bz",
    "iso:country":"NL",
    "sg:address":"Wijnstr 160",
    "sg:city":"Dordrecht",
    "sg:orig_category":"Verenigingen En Stichtingen",
    "sg:phone":"+31 78 613 6798",
    "sg:postcode":"3311 BZ",
    "sg:province":"South Holland",
    "wof:name":"Belangenbehart Marokkanen",
    "wof:placetype":"venue"
},
  "geometry": {"coordinates":[4.668098,51.816181],"type":"Point"}
}