{
  "type": "Feature",
  "properties": {
    "addr:full":"Henrick De Keijserplein 24 Amsterdam Noord-Holland 1073 SZ",
    "addr:housenumber":"24",
    "addr:postcode":"1073 sz",
    "addr:street":"Henrick De Keijserplein",
    "iso:country":"NL",
    "sg:address":"Henrick De Keijserplein 24",
    "sg:city":"Amsterdam",
    "sg:classifiers":[
        {
            "category":"Bakery",
            "type":"Food & Drink"
        }
    ],
    "sg:phone":"+31 20 671 2821",
    "sg:postcode":"1073 SZ",
    "sg:province":"Noord-Holland",
    "sg:tags":[
        "brood",
        "banket"
    ],
    "wof:name":"T.T.B. Catering",
    "wof:placetype":"venue"
},
  "geometry": {"coordinates":[4.89806,52.350777],"type":"Point"}
}