{
  "type": "Feature",
  "properties": {
    "addr:full":"De Ketting 16A Vught North Brabant 5261 LJ",
    "addr:housenumber":"16a",
    "addr:postcode":"5261 lj",
    "addr:street":"De Ketting",
    "iso:country":"NL",
    "sg:address":"De Ketting 16A",
    "sg:city":"Vught",
    "sg:orig_category":"Landmeetkundige Bureaus",
    "sg:phone":"+31 73 656 3487",
    "sg:postcode":"5261 LJ",
    "sg:province":"North Brabant",
    "sg:website":"http://www.geoassist.nl",
    "wof:name":"Geoassist",
    "wof:placetype":"venue"
},
  "geometry": {"coordinates":[5.29596,51.642109],"type":"Point"}
}