{
  "type": "Feature",
  "properties": {
    "addr:full":"Spoorstr 5 Zuidbroek Groningen 9636 AS",
    "addr:housenumber":"5",
    "addr:postcode":"9636 as",
    "addr:street":"Spoorstr",
    "iso:country":"NL",
    "sg:address":"Spoorstr 5",
    "sg:city":"Zuidbroek",
    "sg:orig_category":"Drogisterijen",
    "sg:phone":"+31 598 451 393",
    "sg:postcode":"9636 AS",
    "sg:province":"Groningen",
    "wof:name":"La Bruggen, Drogist",
    "wof:placetype":"venue"
},
  "geometry": {"coordinates":[6.863076,53.162098],"type":"Point"}
}