{
  "type": "Feature",
  "properties": {
    "iso:country":"NL",
    "sg:address":"Spoorstr 5",
    "sg:city":"Zuidbroek",
    "sg:orig_category":"Drogisterijen",
    "sg:phone":"+31 598 451 393",
    "sg:postcode":"9636 AS",
    "sg:province":"Groningen",
    "wof:name":"La Bruggen, Drogist",
    "wof:placetype":"venue"
},
  "geometry": {"coordinates":[6.863076,53.162098],"type":"Point"}
}