{
  "type": "Feature",
  "properties": {
    "addr:full":"Roompotstraat 34 Lewedorp Zeeland 4456 BE",
    "addr:housenumber":"34",
    "addr:postcode":"4456",
    "addr:street":"Roompotstraat",
    "iso:country":"NL",
    "sg:address":"Roompotstraat 34",
    "sg:city":"Lewedorp",
    "sg:orig_category":"Bloemen And Planten",
    "sg:phone":"+31 113 613 566",
    "sg:postcode":"4456 BE",
    "sg:province":"Zeeland",
    "wof:name":"Inge'S Bloemenkar",
    "wof:placetype":"venue"
},
  "geometry": {"coordinates":[3.74822,51.49696],"type":"Point"}
}