{
  "type": "Feature",
  "properties": {
    "addr:full":"Lijsterstraat 3 Gaanderen Gelderland 7011 DJ",
    "addr:housenumber":"3",
    "addr:postcode":"7011 dj",
    "addr:street":"Lijsterstraat;Gelderland",
    "iso:country":"NL",
    "sg:address":"Lijsterstraat 3",
    "sg:city":"Gaanderen",
    "sg:orig_category":"Meubels And Huishoudapparatuur Gh",
    "sg:phone":"+31 315 341 854",
    "sg:postcode":"7011 DJ",
    "sg:province":"Gelderland",
    "wof:name":"Bastian",
    "wof:placetype":"venue"
},
  "geometry": {"coordinates":[6.35245,51.928387],"type":"Point"}
}