{
  "type": "Feature",
  "properties": {
    "iso:country":"NL",
    "sg:address":"Wildhage 6",
    "sg:city":"Teteringen",
    "sg:orig_category":"Adviesbureaus Verzekeringen",
    "sg:phone":"+31 6 20439632",
    "sg:postcode":"4847 CR",
    "sg:province":"Noord-Brabant",
    "wof:name":"Damen Bv",
    "wof:placetype":"venue"
},
  "geometry": {"coordinates":[4.823705,51.604725],"type":"Point"}
}