{
  "type": "Feature",
  "properties": {
    "addr:full":"Tongelresestraat 207 Eindhoven North Brabant 5613 DG",
    "addr:housenumber":"207",
    "addr:postcode":"5613 dg",
    "addr:street":"Tongelresestraat",
    "iso:country":"NL",
    "sg:address":"Tongelresestraat 207",
    "sg:city":"Eindhoven",
    "sg:orig_category":"Paramedische Behandelingen",
    "sg:phone":"+31 40 243 2554",
    "sg:postcode":"5613 DG",
    "sg:province":"North Brabant",
    "wof:name":"Kraamzorg Ntn Thuiszorg",
    "wof:placetype":"venue"
},
  "geometry": {"coordinates":[5.500945,51.442451],"type":"Point"}
}