{
  "type": "Feature",
  "properties": {
    "addr:full":"Hoogstr 15 Werkendam Noord-Brabant 4251 CG",
    "addr:housenumber":"15",
    "addr:postcode":"4251 cg",
    "addr:street":"Hoogstr",
    "iso:country":"NL",
    "sg:address":"Hoogstr 15",
    "sg:city":"Werkendam",
    "sg:orig_category":"Graveerbedrijven",
    "sg:phone":"+31 183 501 329",
    "sg:postcode":"4251 CG",
    "sg:province":"Noord-Brabant",
    "wof:name":"Fixet",
    "wof:placetype":"venue"
},
  "geometry": {"coordinates":[4.895317,51.808372],"type":"Point"}
}