{
  "type": "Feature",
  "properties": {
    "addr:full":"Eindhovenseweg 6 Geldrop Noord-Brabant 5662 AA",
    "addr:housenumber":"6",
    "addr:postcode":"5662 aa",
    "addr:street":"Eindhovenseweg",
    "iso:country":"NL",
    "sg:address":"Eindhovenseweg 6",
    "sg:city":"Geldrop",
    "sg:orig_category":"Autokeuringen",
    "sg:phone":"+31 40 286 1378",
    "sg:postcode":"5662 AA",
    "sg:province":"Noord-Brabant",
    "wof:name":"Mabem",
    "wof:placetype":"venue"
},
  "geometry": {"coordinates":[5.551082,51.424038],"type":"Point"}
}