{
  "type": "Feature",
  "properties": {
    "addr:full":"Hoge Larenseweg 93 Hilversum Noord-Holland 1221 AL",
    "addr:housenumber":"93",
    "addr:postcode":"1221 al",
    "addr:street":"Hoge Larenseweg",
    "iso:country":"NL",
    "sg:address":"Hoge Larenseweg 93",
    "sg:city":"Hilversum",
    "sg:classifiers":[
        {
            "category":"Fast Food",
            "type":"Food & Drink"
        }
    ],
    "sg:phone":"+31 35 683 6841",
    "sg:postcode":"1221 AL",
    "sg:province":"Noord-Holland",
    "sg:tags":[
        "afhaal",
        "restaurant"
    ],
    "wof:name":"Snackbar De Kans",
    "wof:placetype":"venue"
},
  "geometry": {"coordinates":[5.182913,52.231422],"type":"Point"}
}