{
  "type": "Feature",
  "properties": {
    "iso:country":"NL",
    "sg:address":"Van Welderenstraat 27",
    "sg:city":"Nijmegen",
    "sg:orig_category":"Boekhandels",
    "sg:phone":"+31 24 323 6784",
    "sg:postcode":"6511 MB",
    "sg:province":"Gelderland",
    "wof:name":"Hilarion",
    "wof:placetype":"venue"
},
  "geometry": {"coordinates":[5.86479,51.843235],"type":"Point"}
}