{
  "type": "Feature",
  "properties": {
    "addr:full":"Wiltonstr 1 Veenendaal Utrecht 3905 KW",
    "addr:housenumber":"1",
    "addr:postcode":"3905 kw",
    "addr:street":"Wiltonstr",
    "iso:country":"NL",
    "sg:address":"Wiltonstr 1",
    "sg:city":"Veenendaal",
    "sg:classifiers":[
        {
            "category":"Education",
            "subcategory":"Special Training",
            "type":"Public Place"
        }
    ],
    "sg:phone":"+31 318 528 759",
    "sg:postcode":"3905 KW",
    "sg:province":"Utrecht",
    "sg:tags":[
        "expertise"
    ],
    "wof:name":"Midland",
    "wof:placetype":"venue"
},
  "geometry": {"coordinates":[5.563857,52.037472],"type":"Point"}
}