{
  "type": "Feature",
  "properties": {
    "addr:full":"Touwslagersstraat 1 Krimpen A/D Lek Zuid-Holland 2931 HB",
    "addr:housenumber":"1;a / d",
    "addr:postcode":"2931 hb",
    "addr:street":"Touwslagersstraat",
    "iso:country":"NL",
    "sg:address":"Touwslagersstraat 1",
    "sg:city":"Krimpen A/D Lek",
    "sg:orig_category":"Fitnesscentra",
    "sg:phone":"+31 180 551 090",
    "sg:postcode":"2931 HB",
    "sg:province":"Zuid-Holland",
    "wof:name":"Sportcenter Koguryo",
    "wof:placetype":"venue"
},
  "geometry": {"coordinates":[4.6277,51.892559],"type":"Point"}
}