{
  "type": "Feature",
  "properties": {
    "addr:full":"Schoenerstr 7 Emmeloord NL. 8301 AV",
    "addr:housenumber":"7",
    "addr:postcode":"8301 av",
    "addr:street":"Schoenerstr;Nl.",
    "iso:country":"NL",
    "sg:address":"Schoenerstr 7",
    "sg:city":"Emmeloord",
    "sg:orig_category":"Woninginrichting",
    "sg:phone":"+31 527 252 279",
    "sg:postcode":"8301 AV",
    "sg:province":"NL.",
    "sg:website":"http://www.flevostyle.nl",
    "wof:name":"Flevostyle",
    "wof:placetype":"venue"
},
  "geometry": {"coordinates":[5.7647042274,52.7084693909],"type":"Point"}
}