{
  "type": "Feature",
  "properties": {
    "addr:full":"Kogge 8 Barendrecht South Holland 2991 DE",
    "addr:housenumber":"8",
    "addr:postcode":"2991 de",
    "addr:street":"Kogge",
    "iso:country":"NL",
    "sg:address":"Kogge 8",
    "sg:city":"Barendrecht",
    "sg:orig_category":"Kappers",
    "sg:phone":"+31 180 619 766",
    "sg:postcode":"2991 DE",
    "sg:province":"South Holland",
    "wof:name":"Tjallie",
    "wof:placetype":"venue"
},
  "geometry": {"coordinates":[4.548376,51.84605],"type":"Point"}
}