{
  "type": "Feature",
  "properties": {
    "addr:full":"Molukkenstr 39 Amsterdam Noord-Holland 1095 AT",
    "addr:housenumber":"39",
    "addr:postcode":"1095",
    "addr:street":"Molukkenstr",
    "iso:country":"NL",
    "sg:address":"Molukkenstr 39",
    "sg:city":"Amsterdam",
    "sg:classifiers":[
        {
            "category":"Food & Beverages",
            "subcategory":"Bakery",
            "type":"Retail Goods"
        }
    ],
    "sg:phone":"+31 20 694 9730",
    "sg:postcode":"1095 AT",
    "sg:province":"Noord-Holland",
    "sg:tags":[
        "brood",
        "en",
        "banket"
    ],
    "wof:name":"Bartels",
    "wof:placetype":"venue"
},
  "geometry": {"coordinates":[4.939689,52.364777],"type":"Point"}
}