{
  "type": "Feature",
  "properties": {
    "addr:full":"Lettenburg 31 Hoofddorp Noord-Holland 2135 DD",
    "addr:housenumber":"31",
    "addr:postcode":"2135 dd",
    "addr:street":"Lettenburg",
    "iso:country":"NL",
    "sg:address":"Lettenburg 31",
    "sg:city":"Hoofddorp",
    "sg:orig_category":"Video - Faciliteiten En Producties",
    "sg:phone":"+31 23 565 0356",
    "sg:postcode":"2135 DD",
    "sg:province":"Noord-Holland",
    "wof:name":"Avalanche",
    "wof:placetype":"venue"
},
  "geometry": {"coordinates":[4.665823,52.302887],"type":"Point"}
}