{
  "type": "Feature",
  "properties": {
    "iso:country":"NL",
    "sg:address":"T Sander 38",
    "sg:city":"Enschede",
    "sg:orig_category":"Vertaal- And Tolkenbureaus",
    "sg:phone":"+31 53 435 2506",
    "sg:postcode":"7522 AM",
    "sg:province":"NL.08",
    "wof:name":"Vertaalbureau Bison Fute, Y. Lapaire",
    "wof:placetype":"venue"
},
  "geometry": {"coordinates":[6.874671,52.229961],"type":"Point"}
}