{
  "type": "Feature",
  "properties": {
    "addr:full":"T W S Mansholtstr 33 Groningen Groningen 9728 MC",
    "addr:housenumber":"33;9728",
    "addr:postcode":"mc",
    "addr:street":"W",
    "iso:country":"NL",
    "sg:address":"T W S Mansholtstr 33",
    "sg:city":"Groningen",
    "sg:orig_category":"Bedrijfsopleidingen",
    "sg:phone":"+31 6 20796733",
    "sg:postcode":"9728 MC",
    "sg:province":"Groningen",
    "wof:name":"Opleidingen En Preventie",
    "wof:placetype":"venue"
},
  "geometry": {"coordinates":[6.547791,53.184971],"type":"Point"}
}