{
  "type": "Feature",
  "properties": {
    "addr:full":"Baai 138 Lelystad NL. 8224 DT",
    "addr:housenumber":"138",
    "addr:postcode":"8224 dt",
    "addr:street":"Baai;Nl.",
    "iso:country":"NL",
    "sg:address":"Baai 138",
    "sg:city":"Lelystad",
    "sg:orig_category":"Verenigingen En Stichtingen",
    "sg:phone":"+31 320 230 643",
    "sg:postcode":"8224 DT",
    "sg:province":"NL.",
    "wof:name":"Dutch Weekly, Sticht",
    "wof:placetype":"venue"
},
  "geometry": {"coordinates":[5.489451,52.516777],"type":"Point"}
}