{
  "type": "Feature",
  "properties": {
    "addr:full":"Schildwolderdijk 36 Schildwolde Groningen 9626 AS",
    "addr:housenumber":"36",
    "addr:postcode":"9626 as",
    "addr:street":"Schildwolderdijk",
    "iso:country":"NL",
    "sg:address":"Schildwolderdijk 36",
    "sg:city":"Schildwolde",
    "sg:orig_category":"Bloemen And Planten",
    "sg:phone":"+31 598 422 848",
    "sg:postcode":"9626 AS",
    "sg:province":"Groningen",
    "wof:name":"Boomkwekerij Groenwold",
    "wof:placetype":"venue"
},
  "geometry": {"coordinates":[6.798926,53.225609],"type":"Point"}
}