{
  "type": "Feature",
  "properties": {
    "iso:country":"NL",
    "sg:address":"Maliebaan 16",
    "sg:city":"Utrecht",
    "sg:orig_category":"Bedrijfs- And Managementsconsultants",
    "sg:phone":"+31 30 236 3030",
    "sg:postcode":"3581 CN",
    "sg:province":"Utrecht",
    "wof:name":"Andersson Elffers Felix Bv",
    "wof:placetype":"venue"
},
  "geometry": {"coordinates":[5.131508,52.090508],"type":"Point"}
}