{
  "type": "Feature",
  "properties": {
    "addr:full":"Slichtenhorsterwg 16 Nykerk Gld Gelderland 3862 NR",
    "addr:housenumber":"16",
    "addr:postcode":"3862",
    "addr:street":"Slichtenhorsterwg;Gld Gelderland;Nr",
    "iso:country":"NL",
    "sg:address":"Slichtenhorsterwg 16",
    "sg:city":"Nykerk Gld",
    "sg:orig_category":"Adviesbureaus Bedrijfsorganisatie",
    "sg:phone":"+31 33 246 0440",
    "sg:postcode":"3862 NR",
    "sg:province":"Gelderland",
    "wof:name":"D & O",
    "wof:placetype":"venue"
},
  "geometry": {"coordinates":[5.488966,52.208076],"type":"Point"}
}