{
  "type": "Feature",
  "properties": {
    "addr:full":"Radboudstr 8 Hoogwoud Noord-Holland 1718 CD",
    "addr:housenumber":"8",
    "addr:postcode":"1718 cd",
    "addr:street":"Radboudstr",
    "iso:country":"NL",
    "sg:address":"Radboudstr 8",
    "sg:city":"Hoogwoud",
    "sg:orig_category":"Kappers",
    "sg:phone":"+31 226 357 475",
    "sg:postcode":"1718 CD",
    "sg:province":"Noord-Holland",
    "wof:name":"Marg\u00f4t",
    "wof:placetype":"venue"
},
  "geometry": {"coordinates":[4.934784,52.715996],"type":"Point"}
}