{
  "type": "Feature",
  "properties": {
    "addr:full":"Emmasngl 58 Weert Limburg 6001 BD",
    "addr:housenumber":"58",
    "addr:postcode":"6001 bd",
    "addr:street":"Emmasngl",
    "iso:country":"NL",
    "sg:address":"Emmasngl 58",
    "sg:city":"Weert",
    "sg:orig_category":"Werving En Selectie",
    "sg:phone":"+31 495 455 222",
    "sg:postcode":"6001 BD",
    "sg:province":"Limburg",
    "sg:website":"http://www.hermans-wens.nl",
    "wof:name":"Hermans",
    "wof:placetype":"venue"
},
  "geometry": {"coordinates":[5.7037811279,51.2550163269],"type":"Point"}
}