{
  "type": "Feature",
  "properties": {
    "addr:full":"Hengeveldstr 29 Utrecht Utrecht 3572 KH",
    "addr:housenumber":"29",
    "addr:postcode":"3572 kh",
    "addr:street":"Hengeveldstr",
    "iso:country":"NL",
    "sg:address":"Hengeveldstr 29",
    "sg:city":"Utrecht",
    "sg:orig_category":"Video - Faciliteiten En Producties",
    "sg:phone":"+31 30 299 3537",
    "sg:postcode":"3572 KH",
    "sg:province":"Utrecht",
    "wof:name":"Crawfurb.Com",
    "wof:placetype":"venue"
},
  "geometry": {"coordinates":[5.131715,52.10239],"type":"Point"}
}