{
  "type": "Feature",
  "properties": {
    "addr:full":"Eilenbergstraat 34 Tilburg Noord-Brabant 5011 EB",
    "addr:housenumber":"34",
    "addr:postcode":"5011 eb",
    "addr:street":"Eilenbergstraat",
    "iso:country":"NL",
    "sg:address":"Eilenbergstraat 34",
    "sg:city":"Tilburg",
    "sg:orig_category":"Boekhouders",
    "sg:phone":"+31 13 455 3078",
    "sg:postcode":"5011 EB",
    "sg:province":"Noord-Brabant",
    "wof:name":"Administratiekantoor P.C",
    "wof:placetype":"venue"
},
  "geometry": {"coordinates":[5.094314,51.587833],"type":"Point"}
}