{
  "type": "Feature",
  "properties": {
    "addr:full":"Asselsestr 52 Apeldoorn Gelderland 7311 EN",
    "addr:housenumber":"52",
    "addr:postcode":"7311 en",
    "addr:street":"Asselsestr;Gelderland",
    "iso:country":"NL",
    "sg:address":"Asselsestr 52",
    "sg:city":"Apeldoorn",
    "sg:orig_category":"Wijnkoperijen En -Groothandel",
    "sg:phone":"+31 55 522 1470",
    "sg:postcode":"7311 EN",
    "sg:province":"Gelderland",
    "wof:name":"Bloem",
    "wof:placetype":"venue"
},
  "geometry": {"coordinates":[5.9573478699,52.2136535645],"type":"Point"}
}