{
  "type": "Feature",
  "properties": {
    "addr:full":"Californiedreef 36 Utrecht Utrecht 3565 BM",
    "addr:housenumber":"36",
    "addr:postcode":"3565 bm",
    "addr:street":"Californiedreef",
    "iso:country":"NL",
    "sg:address":"Californiedreef 36",
    "sg:city":"Utrecht",
    "sg:orig_category":"Schilderwerk",
    "sg:phone":"+31 30 271 1473",
    "sg:postcode":"3565 BM",
    "sg:province":"Utrecht",
    "wof:name":"Pulle Schilders Bv",
    "wof:placetype":"venue"
},
  "geometry": {"coordinates":[5.088705,52.126472],"type":"Point"}
}