{
  "type": "Feature",
  "properties": {
    "addr:full":"Grettingalaan 43 Harlingen Friesland 8862 ZA",
    "addr:housenumber":"43",
    "addr:postcode":"8862",
    "addr:street":"Grettingalaan",
    "iso:country":"NL",
    "sg:address":"Grettingalaan 43",
    "sg:city":"Harlingen",
    "sg:classifiers":[
        {
            "category":"Education",
            "subcategory":"Preschool",
            "type":"Public Place"
        }
    ],
    "sg:phone":"+31 517 415 180",
    "sg:postcode":"8862 ZA",
    "sg:province":"Friesland",
    "sg:tags":[
        "kleuteronderwijs",
        "basis-"
    ],
    "wof:name":"Prins Johan Frisoschool",
    "wof:placetype":"venue"
},
  "geometry": {"coordinates":[-97.695549,26.189859],"type":"Point"}
}