{
  "type": "Feature",
  "properties": {
    "addr:full":"Sleestraat 16 Ittervoort Limburg 6014 CA",
    "addr:housenumber":"16",
    "addr:postcode":"6014 ca",
    "addr:street":"Sleestraat",
    "iso:country":"NL",
    "sg:address":"Sleestraat 16",
    "sg:city":"Ittervoort",
    "sg:orig_category":"Krantenuitgeverijen",
    "sg:phone":"+31 475 562 783",
    "sg:postcode":"6014 CA",
    "sg:province":"Limburg",
    "wof:name":"Pemar Publiciteit Bv",
    "wof:placetype":"venue"
},
  "geometry": {"coordinates":[5.828626,51.176723],"type":"Point"}
}