{
  "type": "Feature",
  "properties": {
    "addr:full":"Rijnstraat 115 Amsterdam North Holland 1079 HA",
    "addr:housenumber":"115",
    "addr:postcode":"1079 ha",
    "addr:street":"Rijnstraat",
    "iso:country":"NL",
    "sg:address":"Rijnstraat 115",
    "sg:city":"Amsterdam",
    "sg:orig_category":"Fotostudio'S And Fotografen",
    "sg:phone":"+31 20 644 3061",
    "sg:postcode":"1079 HA",
    "sg:province":"North Holland",
    "wof:name":"Hans B. The' - Photography",
    "wof:placetype":"venue"
},
  "geometry": {"coordinates":[4.906245,52.34407],"type":"Point"}
}