{
  "type": "Feature",
  "properties": {
    "iso:country":"NL",
    "sg:address":"Patynwg 84",
    "sg:city":"Goes",
    "sg:orig_category":"Fietsen En Bromfietsen",
    "sg:phone":"+31 113 228 308",
    "sg:postcode":"4461 LS",
    "sg:province":"Ohio",
    "wof:name":"Huissoon Vof",
    "wof:placetype":"venue"
},
  "geometry": {"coordinates":[-83.914169,39.768833],"type":"Point"}
}