{
  "type": "Feature",
  "properties": {
    "addr:full":"Meerpaal 22 Huizen Noord-Holland 1273 KN",
    "addr:housenumber":"22",
    "addr:postcode":"1273 kn",
    "addr:street":"Meerpaal",
    "iso:country":"NL",
    "sg:address":"Meerpaal 22",
    "sg:city":"Huizen",
    "sg:orig_category":"Psychotherapeuten",
    "sg:phone":"+31 35 525 1787",
    "sg:postcode":"1273 KN",
    "sg:province":"Noord-Holland",
    "sg:website":"http://www.speyerpraktijk.myweb.nl",
    "wof:name":"Werkhoven, G J M Van",
    "wof:placetype":"venue"
},
  "geometry": {"coordinates":[5.265528,52.297424],"type":"Point"}
}