{
  "type": "Feature",
  "properties": {
    "addr:full":"Dorpsstr 50A Aarle Rixtel Noord-Brabant 5735 EE",
    "addr:housenumber":"50a",
    "addr:postcode":"5735 ee",
    "addr:street":"Dorpsstr",
    "iso:country":"NL",
    "sg:address":"Dorpsstr 50A",
    "sg:city":"Aarle Rixtel",
    "sg:orig_category":"Verzekeringen - Verzekeringskantoren",
    "sg:phone":"+31 492 382 520",
    "sg:postcode":"5735 EE",
    "sg:province":"Noord-Brabant",
    "wof:name":"Jong, Theo De",
    "wof:placetype":"venue"
},
  "geometry": {"coordinates":[5.641321,51.510368],"type":"Point"}
}