{
  "type": "Feature",
  "properties": {
    "addr:full":"Koperslager 29 Nykerk Gld Gelderland 3861 SJ",
    "addr:housenumber":"29;3861",
    "addr:street":"Koperslager;Gld Gelderland",
    "iso:country":"NL",
    "sg:address":"Koperslager 29",
    "sg:city":"Nykerk Gld",
    "sg:orig_category":"Verpakkingen En Verpakkingsmaterialen",
    "sg:phone":"+31 33 246 5399",
    "sg:postcode":"3861 SJ",
    "sg:province":"Gelderland",
    "sg:website":"http://www.hodi.nl",
    "wof:name":"Hodi Bv",
    "wof:placetype":"venue"
},
  "geometry": {"coordinates":[5.467091,52.228252],"type":"Point"}
}