{
  "type": "Feature",
  "properties": {
    "iso:country":"NL",
    "sg:address":"Hoeksteen 149",
    "sg:city":"Hoofddorp",
    "sg:orig_category":"Luchtvrachtexpediteurs",
    "sg:phone":"+31 20 655 4755",
    "sg:postcode":"2132 MX",
    "sg:province":"North Holland",
    "wof:name":"Triple Bv",
    "wof:placetype":"venue"
},
  "geometry": {"coordinates":[4.72385,52.291576],"type":"Point"}
}