{
  "type": "Feature",
  "properties": {
    "addr:full":"Oostperkwg 45 Middelburg Zeeland 4332 SB",
    "addr:housenumber":"45",
    "addr:postcode":"4332 sb",
    "addr:street":"Oostperkwg",
    "iso:country":"NL",
    "sg:address":"Oostperkwg 45",
    "sg:city":"Middelburg",
    "sg:orig_category":"Papierwaren - Fabrieken En Groothandel",
    "sg:phone":"+31 118 643 464",
    "sg:postcode":"4332 SB",
    "sg:province":"Zeeland",
    "sg:website":"http://www.hti.nl",
    "wof:name":"Holografhics Tech Int Bv",
    "wof:placetype":"venue"
},
  "geometry": {"coordinates":[3.631683,51.504925],"type":"Point"}
}