{
  "type": "Feature",
  "properties": {
    "addr:full":"Vossenakker 27 Ede Gld Gelderland 6711 CX",
    "addr:housenumber":"27",
    "addr:postcode":"6711 cx",
    "addr:street":"Vossenakker;Gld Gelderland",
    "iso:country":"NL",
    "sg:address":"Vossenakker 27",
    "sg:city":"Ede Gld",
    "sg:orig_category":"Adviesbureaus Bedrijfsorganisatie",
    "sg:phone":"+31 318 615 633",
    "sg:postcode":"6711 CX",
    "sg:province":"Gelderland",
    "sg:website":"http://www.impulsus.com",
    "wof:name":"Impulsus Ede",
    "wof:placetype":"venue"
},
  "geometry": {"coordinates":[5.678116,52.047134],"type":"Point"}
}