{
  "type": "Feature",
  "properties": {
    "addr:full":"Naanhofswg 3 Nuth Limburg 6361 DP",
    "addr:housenumber":"3",
    "addr:postcode":"6361 dp",
    "addr:street":"Naanhofswg",
    "iso:country":"NL",
    "sg:address":"Naanhofswg 3",
    "sg:city":"Nuth",
    "sg:orig_category":"Pluimveebedrijven En -Handelaren",
    "sg:phone":"+31 45 524 1390",
    "sg:postcode":"6361 DP",
    "sg:province":"Limburg",
    "wof:name":"Schoonbroodt Bv, Gebr",
    "wof:placetype":"venue"
},
  "geometry": {"coordinates":[5.900437,50.923714],"type":"Point"}
}