{
  "type": "Feature",
  "properties": {
    "addr:full":"Lg Duin En D Wg 17 Bloemendaal North Holland 2061 BB",
    "addr:housenumber":"17",
    "addr:postcode":"2061 bb",
    "addr:street":"Duin En D Wg",
    "iso:country":"NL",
    "sg:address":"Lg Duin En D Wg 17",
    "sg:city":"Bloemendaal",
    "sg:orig_category":"Scholen Voor Basisonderwijs",
    "sg:phone":"+31 23 525 6205",
    "sg:postcode":"2061 BB",
    "sg:province":"North Holland",
    "wof:name":"Bloemendaalse Schoolver",
    "wof:placetype":"venue"
},
  "geometry": {"coordinates":[4.629037,52.409935],"type":"Point"}
}