{
  "type": "Feature",
  "properties": {
    "addr:full":"Pieterstr 16 Goedereede Zuid-Holland 3252 BL",
    "addr:housenumber":"16",
    "addr:postcode":"3252 bl",
    "addr:street":"Pieterstr",
    "iso:country":"NL",
    "sg:address":"Pieterstr 16",
    "sg:city":"Goedereede",
    "sg:classifiers":[
        {
            "category":"Food & Beverages",
            "subcategory":"Bakery",
            "type":"Retail Goods"
        }
    ],
    "sg:phone":"+31 187 491 150",
    "sg:postcode":"3252 BL",
    "sg:province":"Zuid-Holland",
    "sg:tags":[
        "brood",
        "en",
        "banket"
    ],
    "wof:name":"Vries, De",
    "wof:placetype":"venue"
},
  "geometry": {"coordinates":[3.982881,51.817432],"type":"Point"}
}