{
  "type": "Feature",
  "properties": {
    "addr:full":"De Werf 5 S Gravenhage South Holland 2544 EH",
    "addr:housenumber":"5",
    "addr:postcode":"2544 eh",
    "addr:street":"De Werf;S Gravenhage",
    "iso:country":"NL",
    "sg:address":"De Werf 5",
    "sg:city":"S Gravenhage",
    "sg:orig_category":"Plastic Producten - Fabrieken En Groothandel",
    "sg:phone":"+31 70 329 5293",
    "sg:postcode":"2544 EH",
    "sg:province":"South Holland",
    "sg:website":"http://www.globalfactories.nl",
    "wof:name":"Global Bv",
    "wof:placetype":"venue"
},
  "geometry": {"coordinates":[4.25157,52.039551],"type":"Point"}
}