{
  "type": "Feature",
  "properties": {
    "addr:full":"Regulusstraat 3 A Delfzijl Groningen 9933 EP",
    "addr:housenumber":"3 a",
    "addr:postcode":"9933 ep",
    "addr:street":"Regulusstraat",
    "iso:country":"NL",
    "sg:address":"Regulusstraat 3 A",
    "sg:city":"Delfzijl",
    "sg:orig_category":"Koeriersdiensten",
    "sg:phone":"+31 596 616 747",
    "sg:postcode":"9933 EP",
    "sg:province":"Groningen",
    "wof:name":"* Delftransport",
    "wof:placetype":"venue"
},
  "geometry": {"coordinates":[6.903212,53.331192],"type":"Point"}
}