{
  "type": "Feature",
  "properties": {
    "addr:full":"Piet Heinlaan 15 Winschoten Groningen 9675 AZ",
    "addr:housenumber":"15",
    "addr:postcode":"9675 az",
    "addr:street":"Piet Heinlaan",
    "iso:country":"NL",
    "sg:address":"Piet Heinlaan 15",
    "sg:city":"Winschoten",
    "sg:orig_category":"Kappers",
    "sg:phone":"+31 597 422 097",
    "sg:postcode":"9675 AZ",
    "sg:province":"Groningen",
    "wof:name":"Salon Cresta",
    "wof:placetype":"venue"
},
  "geometry": {"coordinates":[7.034765,53.151222],"type":"Point"}
}