{
  "type": "Feature",
  "properties": {
    "iso:country":"NL",
    "sg:address":"W Denijslaan 14",
    "sg:city":"Heemstede",
    "sg:orig_category":"Vertaal- And Tolkenbureaus",
    "sg:phone":"+31 23 528 7843",
    "sg:postcode":"2101 ER",
    "sg:province":"North Holland",
    "wof:name":"J.J. Barkhof",
    "wof:placetype":"venue"
},
  "geometry": {"coordinates":[4.613991,52.348305],"type":"Point"}
}