{
  "type": "Feature",
  "properties": {
    "addr:full":"Hilleniussngl 25 Rotterdam South Holland 3054 EX",
    "addr:housenumber":"25",
    "addr:postcode":"3054 ex",
    "addr:street":"Hilleniussngl",
    "iso:country":"NL",
    "sg:address":"Hilleniussngl 25",
    "sg:city":"Rotterdam",
    "sg:orig_category":"Adviesbureaus Bouwkunde",
    "sg:phone":"+31 10 461 3472",
    "sg:postcode":"3054 EX",
    "sg:province":"South Holland",
    "wof:name":"Adriaanse",
    "wof:placetype":"venue"
},
  "geometry": {"coordinates":[4.49284,51.957539],"type":"Point"}
}