{
  "type": "Feature",
  "properties": {
    "addr:full":"E Jennerstraat 330 Haarlem North Holland 2035 EW",
    "addr:housenumber":"330",
    "addr:postcode":"2035 ew",
    "addr:street":"E Jennerstraat",
    "iso:country":"NL",
    "sg:address":"E Jennerstraat 330",
    "sg:city":"Haarlem",
    "sg:orig_category":"Werving And Selectie Van Tijdelijk Personeel And Uitzendkantoren",
    "sg:phone":"+31 2353509001",
    "sg:postcode":"2035 EW",
    "sg:province":"North Holland",
    "wof:name":"Times Personnel",
    "wof:placetype":"venue"
},
  "geometry": {"coordinates":[4.6567549706,52.3610343933],"type":"Point"}
}