{
  "type": "Feature",
  "properties": {
    "addr:full":"Achterzeewg 29 Noordwyk Zh Zuid-Holland 2201 EN",
    "addr:housenumber":"29",
    "addr:postcode":"2201 en",
    "addr:street":"Achterzeewg",
    "iso:country":"NL",
    "sg:address":"Achterzeewg 29",
    "sg:city":"Noordwyk Zh",
    "sg:orig_category":"Administratie- En Boekhoudkantoren",
    "sg:phone":"+31 71 362 5072",
    "sg:postcode":"2201 EN",
    "sg:province":"Zuid-Holland",
    "wof:name":"Bakker, M",
    "wof:placetype":"venue"
},
  "geometry": {"coordinates":[4.439091,52.234924],"type":"Point"}
}