{
  "type": "Feature",
  "properties": {
    "iso:country":"NL",
    "sg:address":"Obrechtln 169",
    "sg:city":"S Gravenzande",
    "sg:orig_category":"Artsen - Huisartsen",
    "sg:phone":"+31 174 412 309",
    "sg:postcode":"2692 BT",
    "sg:province":"Zuid-Holland",
    "wof:name":"Visser En Y J Bezuyen En J W Attema, P D",
    "wof:placetype":"venue"
},
  "geometry": {"coordinates":[4.157428,51.999504],"type":"Point"}
}