{
  "type": "Feature",
  "properties": {
    "addr:full":"Dalemsedijk 9 Eersel North Brabant 5521 RM",
    "addr:housenumber":"9",
    "addr:postcode":"5521 rm",
    "addr:street":"Dalemsedijk",
    "iso:country":"NL",
    "sg:address":"Dalemsedijk 9",
    "sg:city":"Eersel",
    "sg:orig_category":"Huishoudapparatuur, Televisies And Radio'S",
    "sg:phone":"+31 497 516 430",
    "sg:postcode":"5521 RM",
    "sg:province":"North Brabant",
    "wof:name":"Antennebouw B. Van Der Sanden",
    "wof:placetype":"venue"
},
  "geometry": {"coordinates":[5.299601,51.360291],"type":"Point"}
}