{
  "type": "Feature",
  "properties": {
    "addr:full":"Wetering W 85 Wetering Overijssel 8363 TN",
    "addr:housenumber":"85",
    "addr:postcode":"8363",
    "addr:street":"Wetering W",
    "iso:country":"NL",
    "sg:address":"Wetering W 85",
    "sg:city":"Wetering",
    "sg:orig_category":"Non-Classified Establishments",
    "sg:phone":"+31 521 371 459",
    "sg:postcode":"8363 TN",
    "sg:province":"Overijssel",
    "wof:name":"Succes",
    "wof:placetype":"venue"
},
  "geometry": {"coordinates":[5.98682,52.769211],"type":"Point"}
}