{
  "type": "Feature",
  "properties": {
    "iso:country":"NL",
    "sg:address":"Haverstraat 57",
    "sg:city":"Nieuw Vennep",
    "sg:orig_category":"Farmaceutische Producten Gh",
    "sg:phone":"+31 252 689 550",
    "sg:postcode":"2153 GD",
    "sg:province":"Noord-Holland",
    "wof:name":"Beijst Medische Produkten Bv",
    "wof:placetype":"venue"
},
  "geometry": {"coordinates":[4.645391,52.270412],"type":"Point"}
}