{
  "type": "Feature",
  "properties": {
    "addr:full":"Hamburgerwg 195 Ermelo Gelderland 3851 EL",
    "addr:housenumber":"195",
    "addr:postcode":"3851 el",
    "addr:street":"Gelderland",
    "iso:country":"NL",
    "sg:address":"Hamburgerwg 195",
    "sg:city":"Ermelo",
    "sg:orig_category":"Verhuizingen",
    "sg:phone":"+31 341 552 514",
    "sg:postcode":"3851 EL",
    "sg:province":"Gelderland",
    "wof:name":"Beek Bv, Van",
    "wof:placetype":"venue"
},
  "geometry": {"coordinates":[5.612696,52.296619],"type":"Point"}
}