{
  "type": "Feature",
  "properties": {
    "addr:full":"Spanbeddestraat 14 Haaksbergen Overijssel 7481 ES",
    "addr:housenumber":"14",
    "addr:postcode":"7481 es",
    "addr:street":"Spanbeddestraat",
    "iso:country":"NL",
    "sg:address":"Spanbeddestraat 14",
    "sg:city":"Haaksbergen",
    "sg:orig_category":"Loodgieterswerk, Verwarming And Sanitaire Installaties",
    "sg:phone":"+31 53 572 4711",
    "sg:postcode":"7481 ES",
    "sg:province":"Overijssel",
    "wof:name":"G.J. Harmsen Klussendienst",
    "wof:placetype":"venue"
},
  "geometry": {"coordinates":[6.744617,52.152523],"type":"Point"}
}