{
  "type": "Feature",
  "properties": {
    "addr:full":"Raadhuisplein 31 Hoogkarspel Noord-Holland 1616 AV",
    "addr:housenumber":"31",
    "addr:postcode":"1616 av",
    "addr:street":"Raadhuisplein",
    "iso:country":"NL",
    "sg:address":"Raadhuisplein 31",
    "sg:city":"Hoogkarspel",
    "sg:orig_category":"Discountwinkels",
    "sg:phone":"+31 228 562 449",
    "sg:postcode":"1616 AV",
    "sg:province":"Noord-Holland",
    "wof:name":"Landgraaf Bv",
    "wof:placetype":"venue"
},
  "geometry": {"coordinates":[5.178566,52.695339],"type":"Point"}
}