{
  "type": "Feature",
  "properties": {
    "addr:full":"Dunantstr 1E Tilburg North Brabant 5017 KC",
    "addr:housenumber":"1e",
    "addr:postcode":"5017 kc",
    "addr:street":"Dunantstr",
    "iso:country":"NL",
    "sg:address":"Dunantstr 1E",
    "sg:city":"Tilburg",
    "sg:orig_category":"Architecten En Architectenbureaus",
    "sg:phone":"+31 13 535 0989",
    "sg:postcode":"5017 KC",
    "sg:province":"North Brabant",
    "wof:name":"Forum Architecten & Planners",
    "wof:placetype":"venue"
},
  "geometry": {"coordinates":[5.09578,51.557388],"type":"Point"}
}