{
  "type": "Feature",
  "properties": {
    "iso:country":"NL",
    "sg:address":"Schumannstr 21",
    "sg:city":"S Hertogenbosch",
    "sg:orig_category":"Bijouterie?n - Fabrieken En Groothandel",
    "sg:phone":"+31 73 689 0823",
    "sg:postcode":"5216 EZ",
    "sg:province":"Noord-Brabant",
    "sg:website":"http://www.beads.nl",
    "wof:name":"Beads By Remke",
    "wof:placetype":"venue"
},
  "geometry": {"coordinates":[5.324491,51.680542],"type":"Point"}
}