{
  "type": "Feature",
  "properties": {
    "iso:country":"NL",
    "sg:address":"Schouwburgring 14",
    "sg:city":"Tilburg",
    "sg:orig_category":"Binnenhuisarchitecten",
    "sg:phone":"+31 13 542 6740",
    "sg:postcode":"5038 TL",
    "sg:province":"Noord-Brabant",
    "wof:name":"W. Lebesque Tilburg Bv",
    "wof:placetype":"venue"
},
  "geometry": {"coordinates":[5.081243,51.554695],"type":"Point"}
}