{
  "type": "Feature",
  "properties": {
    "addr:full":"Not Fischerstraat 36 Ede Gld Gelderland 6711 BD",
    "addr:housenumber":"36",
    "addr:postcode":"6711 bd",
    "addr:street":"Fischerstraat;Gld Gelderland",
    "iso:country":"NL",
    "sg:address":"Not Fischerstraat 36",
    "sg:city":"Ede Gld",
    "sg:orig_category":"Verenigingen En Stichtingen",
    "sg:phone":"+31 318 672 277",
    "sg:postcode":"6711 BD",
    "sg:province":"Gelderland",
    "wof:name":"Humanitas Wooncentr Dmh, Sticht",
    "wof:placetype":"venue"
},
  "geometry": {"coordinates":[5.66767,52.044979],"type":"Point"}
}