{
  "type": "Feature",
  "properties": {
    "addr:full":"Beekstr 33 Meerssen Limburg 6231 LE",
    "addr:housenumber":"33",
    "addr:postcode":"6231 le",
    "addr:street":"Beekstr",
    "iso:country":"NL",
    "sg:address":"Beekstr 33",
    "sg:city":"Meerssen",
    "sg:orig_category":"Woninginrichting",
    "sg:phone":"+31 43 364 4141",
    "sg:postcode":"6231 LE",
    "sg:province":"Limburg",
    "wof:name":"Jussen Vof",
    "wof:placetype":"venue"
},
  "geometry": {"coordinates":[5.7550339699,50.8847618103],"type":"Point"}
}