{
  "type": "Feature",
  "properties": {
    "addr:full":"Henriettedreef 12 Utrecht Utrecht 3561 JV",
    "addr:housenumber":"12",
    "addr:postcode":"3561 jv",
    "addr:street":"Henriettedreef",
    "iso:country":"NL",
    "sg:address":"Henriettedreef 12",
    "sg:city":"Utrecht",
    "sg:orig_category":"Psychotherapeuten",
    "sg:phone":"+31 30 266 0665",
    "sg:postcode":"3561 JV",
    "sg:province":"Utrecht",
    "sg:website":"http://www.hypno-drama.nl",
    "wof:name":"Kramer-Medema, Karen",
    "wof:placetype":"venue"
},
  "geometry": {"coordinates":[5.116665,52.111401],"type":"Point"}
}