{
  "type": "Feature",
  "properties": {
    "addr:full":"Gasthuisstraat 56 Horst Limburg 5961 GB",
    "addr:housenumber":"56",
    "addr:postcode":"5961 gb",
    "addr:street":"Gasthuisstraat",
    "iso:country":"NL",
    "sg:address":"Gasthuisstraat 56",
    "sg:city":"Horst",
    "sg:orig_category":"Kinderopvang Behalve Thuis",
    "sg:phone":"+31 77 398 7603",
    "sg:postcode":"5961 GB",
    "sg:province":"Limburg",
    "wof:name":"De Kleinhorst Kindercentrum",
    "wof:placetype":"venue"
},
  "geometry": {"coordinates":[1.350616,52.728626],"type":"Point"}
}