{
  "type": "Feature",
  "properties": {
    "addr:full":"Nassaukd 36B Rotterdam Zuid-Holland 3071 JL",
    "addr:housenumber":"36b",
    "addr:postcode":"3071 jl",
    "addr:street":"Nassaukd",
    "iso:country":"NL",
    "sg:address":"Nassaukd 36B",
    "sg:city":"Rotterdam",
    "sg:classifiers":[
        {
            "category":"Food & Beverages",
            "subcategory":"Bakery",
            "type":"Retail Goods"
        }
    ],
    "sg:phone":"+31 10 484 9431",
    "sg:postcode":"3071 JL",
    "sg:province":"Zuid-Holland",
    "sg:tags":[
        "pizza"
    ],
    "wof:name":"Mare Akino, Il",
    "wof:placetype":"venue"
},
  "geometry": {"coordinates":[4.50327,51.910591],"type":"Point"}
}