{
  "type": "Feature",
  "properties": {
    "addr:full":"Hemonystr 1 Amsterdam Noord-Holland 1074 BK",
    "addr:housenumber":"1",
    "addr:postcode":"1074 bk",
    "addr:street":"Hemonystr",
    "iso:country":"NL",
    "sg:address":"Hemonystr 1",
    "sg:city":"Amsterdam",
    "sg:orig_category":"Hypotheken",
    "sg:phone":"+31 20 470 0554",
    "sg:postcode":"1074 BK",
    "sg:province":"Noord-Holland",
    "sg:website":"http://www.geldadvies.com",
    "wof:name":"Geldadvies",
    "wof:placetype":"venue"
},
  "geometry": {"coordinates":[4.901928,52.358257],"type":"Point"}
}