{
  "type": "Feature",
  "properties": {
    "addr:full":"Langestraat 3 'S Gravendeel Zuid-Holland 3295 BJ",
    "addr:housenumber":"3 ' s",
    "addr:postcode":"3295 bj",
    "addr:street":"Langestraat",
    "iso:country":"NL",
    "sg:address":"Langestraat 3",
    "sg:city":"'S Gravendeel",
    "sg:orig_category":"Kappers",
    "sg:phone":"+31 78 673 1867",
    "sg:postcode":"3295 BJ",
    "sg:province":"Zuid-Holland",
    "wof:name":"Ad Pegels Coiffures Vof",
    "wof:placetype":"venue"
},
  "geometry": {"coordinates":[4.6168980598,51.7790336609],"type":"Point"}
}