{
  "type": "Feature",
  "properties": {
    "addr:full":"Rietwijkerstraat 77 Amsterdam Noord-Holland 1059 VX",
    "addr:housenumber":"77",
    "addr:postcode":"1059 vx",
    "addr:street":"Rietwijkerstraat",
    "iso:country":"NL",
    "sg:address":"Rietwijkerstraat 77",
    "sg:city":"Amsterdam",
    "sg:orig_category":"Kinderopvang Behalve Thuis",
    "sg:phone":"+31 20 614 0848",
    "sg:postcode":"1059 VX",
    "sg:province":"Noord-Holland",
    "wof:name":"Kinderdagverblijf Plons",
    "wof:placetype":"venue"
},
  "geometry": {"coordinates":[4.847025,52.349434],"type":"Point"}
}