{
  "type": "Feature",
  "properties": {
    "addr:full":"Borgharensngl 14 Tilburg Noord-Brabant 5043 ZM",
    "addr:housenumber":"14",
    "addr:postcode":"5043 zm",
    "addr:street":"Borgharensngl",
    "iso:country":"NL",
    "sg:address":"Borgharensngl 14",
    "sg:city":"Tilburg",
    "sg:orig_category":"Verenigingen En Stichtingen",
    "sg:phone":"+31 13 570 1438",
    "sg:postcode":"5043 ZM",
    "sg:province":"Noord-Brabant",
    "wof:name":"Blinden & Slechtzienden, Ned Ver Van",
    "wof:placetype":"venue"
},
  "geometry": {"coordinates":[5.0156,51.578869],"type":"Point"}
}