{
  "type": "Feature",
  "properties": {
    "iso:country":"NL",
    "sg:address":"Populierstr 16",
    "sg:city":"Utrecht",
    "sg:classifiers":[
        {
            "category":"Personal",
            "subcategory":"Nail Salon",
            "type":"Services"
        }
    ],
    "sg:phone":"+31 30 244 2173",
    "sg:postcode":"3552 RG",
    "sg:province":"Utrecht",
    "sg:tags":[
        "pedicure"
    ],
    "wof:name":"Jeanette",
    "wof:placetype":"venue"
},
  "geometry": {"coordinates":[5.09829,52.104584],"type":"Point"}
}