{
  "type": "Feature",
  "properties": {
    "iso:country":"NL",
    "sg:address":"Florynwg 1",
    "sg:city":"Velp Gld",
    "sg:orig_category":"Zuivel - Groothandel",
    "sg:phone":"+31 26 363 4117",
    "sg:postcode":"6883 JN",
    "sg:province":"Gelderland",
    "wof:name":"Altensonne Ned Bv",
    "wof:placetype":"venue"
},
  "geometry": {"coordinates":[5.988668,51.983536],"type":"Point"}
}