{
  "type": "Feature",
  "properties": {
    "iso:country":"NL",
    "sg:address":"Naarderwg 51",
    "sg:city":"Blaricum",
    "sg:orig_category":"Medische Installaties En Instrumenten",
    "sg:phone":"+31 35 538 3382",
    "sg:postcode":"1261 BS",
    "sg:province":"Noord-Holland",
    "wof:name":"Jem Session Int",
    "wof:placetype":"venue"
},
  "geometry": {"coordinates":[5.232335,52.274822],"type":"Point"}
}