{
  "type": "Feature",
  "properties": {
    "addr:full":"Keelstraat 10 Valkenburg Lb Limburg 6301 XT",
    "addr:housenumber":"10",
    "addr:postcode":"lb;6301 xt",
    "addr:street":"Keelstraat",
    "iso:country":"NL",
    "sg:address":"Keelstraat 10",
    "sg:city":"Valkenburg Lb",
    "sg:orig_category":"Boekhouders",
    "sg:phone":"+31 43 601 4569",
    "sg:postcode":"6301 XT",
    "sg:province":"Limburg",
    "wof:name":"Tebad Administratieve Dienstverlening",
    "wof:placetype":"venue"
},
  "geometry": {"coordinates":[5.827565,50.873905],"type":"Point"}
}