{
  "type": "Feature",
  "properties": {
    "addr:full":"Provincialewg 302 Zaandam Noord-Holland 1506 MJ",
    "addr:housenumber":"302",
    "addr:postcode":"1506 mj",
    "iso:country":"NL",
    "sg:address":"Provincialewg 302",
    "sg:city":"Zaandam",
    "sg:orig_category":"Scholen Voor Algemeen Voortgezet Onderwijs",
    "sg:phone":"+31 75 616 5071",
    "sg:postcode":"1506 MJ",
    "sg:province":"Noord-Holland",
    "wof:name":"Christelijk Voortgezet Onderwijs",
    "wof:placetype":"venue"
},
  "geometry": {"coordinates":[4.806823,52.452465],"type":"Point"}
}