{
  "type": "Feature",
  "properties": {
    "iso:country":"NL",
    "sg:address":"Baanweg 26",
    "sg:city":"Harderwijk",
    "sg:orig_category":"Pompen And Compressoren Fab",
    "sg:phone":"+31 341 417 524",
    "sg:postcode":"3844 KS",
    "sg:province":"Gelderland",
    "wof:name":"Bagema Bv",
    "wof:placetype":"venue"
},
  "geometry": {"coordinates":[5.613322,52.336433],"type":"Point"}
}