{
  "type": "Feature",
  "properties": {
    "iso:country":"NL",
    "sg:address":"Archimedeswg 25",
    "sg:city":"Leiden",
    "sg:orig_category":"Farmaceutische Industrie En Groothandel",
    "sg:phone":"+31 71 524 4080",
    "sg:postcode":"2333 CM",
    "sg:province":"South Holland",
    "sg:website":"http://www.proxylab.nl",
    "wof:name":"Proxy Bv",
    "wof:placetype":"venue"
},
  "geometry": {"coordinates":[4.46876,52.166302],"type":"Point"}
}