{
  "type": "Feature",
  "properties": {
    "iso:country":"NL",
    "sg:address":"Postbus 608",
    "sg:city":"Voorburg",
    "sg:orig_category":"Voetbalverenigingen",
    "sg:phone":"+31 70 386 4302",
    "sg:postcode":"2270 AP",
    "sg:province":"Zuid-Holland",
    "sg:website":"http://www.forumsport.nl",
    "wof:name":"Forum Sport",
    "wof:placetype":"venue"
},
  "geometry": {"coordinates":[4.35847,52.075748],"type":"Point"}
}