{
  "type": "Feature",
  "properties": {
    "addr:full":"Kleiwegstr 16 Gouda Zuid-Holland 2801 GM",
    "addr:housenumber":"16",
    "addr:postcode":"2801 gm",
    "addr:street":"Kleiwegstr",
    "iso:country":"NL",
    "sg:address":"Kleiwegstr 16",
    "sg:city":"Gouda",
    "sg:classifiers":[
        {
            "category":"Shopping",
            "subcategory":"Adult",
            "type":"Retail Goods"
        }
    ],
    "sg:phone":"+31 182 520 240",
    "sg:postcode":"2801 GM",
    "sg:province":"Zuid-Holland",
    "sg:tags":[
        "lingerie",
        "en",
        "tricotage"
    ],
    "wof:name":"Sweet Body",
    "wof:placetype":"venue"
},
  "geometry": {"coordinates":[4.709056,52.014221],"type":"Point"}
}