{
  "type": "Feature",
  "properties": {
    "addr:full":"Oosterstr 20 Winsum Gn Groningen 9951 EB",
    "addr:housenumber":"20",
    "addr:postcode":"gn;9951 eb",
    "addr:street":"Oosterstr",
    "iso:country":"NL",
    "sg:address":"Oosterstr 20",
    "sg:city":"Winsum Gn",
    "sg:orig_category":"Vertalers",
    "sg:phone":"+31 595 441 448",
    "sg:postcode":"9951 EB",
    "sg:province":"Groningen",
    "wof:name":"Dicke, Drs Maaike",
    "wof:placetype":"venue"
},
  "geometry": {"coordinates":[6.517395,53.334412],"type":"Point"}
}