{
  "type": "Feature",
  "properties": {
    "addr:full":"Dyckmeesterwg 12 Zutphen Gelderland 7201 AL",
    "addr:housenumber":"12",
    "addr:postcode":"7201",
    "addr:street":"Dyckmeesterwg;Gelderland",
    "iso:country":"NL",
    "sg:address":"Dyckmeesterwg 12",
    "sg:city":"Zutphen",
    "sg:classifiers":[
        {
            "category":"Shopping",
            "subcategory":"News",
            "type":"Retail Goods"
        }
    ],
    "sg:phone":"+31 575 585 485",
    "sg:postcode":"7201 AL",
    "sg:province":"Gelderland",
    "sg:tags":[
        "maandbladen",
        "en",
        "week-"
    ],
    "wof:name":"Zutphense Koerier",
    "wof:placetype":"venue"
},
  "geometry": {"coordinates":[6.1915249825,52.1402015686],"type":"Point"}
}