{
  "type": "Feature",
  "properties": {
    "addr:full":"J. Evertsenstraat 16 Amsterdam Noord-Holland 1056 EC",
    "addr:housenumber":"16",
    "addr:postcode":"1056 ec",
    "addr:street":"J. Evertsenstraat",
    "iso:country":"NL",
    "sg:address":"J. Evertsenstraat 16",
    "sg:city":"Amsterdam",
    "sg:orig_category":"Werving And Selectie Van Tijdelijk Personeel And Uitzendkantoren",
    "sg:phone":"+31 20 589 1950",
    "sg:postcode":"1056 EC",
    "sg:province":"Noord-Holland",
    "wof:name":"Short Track Bv",
    "wof:placetype":"venue"
},
  "geometry": {"coordinates":[4.8584179878,52.3715019226],"type":"Point"}
}