{
  "type": "Feature",
  "properties": {
    "addr:full":"V Reenenpk 6 Nykerk Gld Gelderland 3862 CC",
    "addr:housenumber":"6;3862",
    "addr:postcode":"cc",
    "addr:street":"Reenenpk;Gld Gelderland",
    "iso:country":"NL",
    "sg:address":"V Reenenpk 6",
    "sg:city":"Nykerk Gld",
    "sg:orig_category":"Verenigingen En Stichtingen",
    "sg:phone":"+31 33 245 9528",
    "sg:postcode":"3862 CC",
    "sg:province":"Gelderland",
    "wof:name":"Bijbelstudie En Onderzoek, Sticht Centr Voor",
    "wof:placetype":"venue"
},
  "geometry": {"coordinates":[5.51415,52.21376],"type":"Point"}
}