{
  "type": "Feature",
  "properties": {
    "iso:country":"NL",
    "sg:address":"Boekelosewg 54",
    "sg:city":"Hengelo Ov",
    "sg:orig_category":"Kappers",
    "sg:phone":"+31 74 291 8437",
    "sg:postcode":"7553 DN",
    "sg:province":"NL.08",
    "wof:name":"Hartman",
    "wof:placetype":"venue"
},
  "geometry": {"coordinates":[6.7875189781,52.2540931702],"type":"Point"}
}