{
  "type": "Feature",
  "properties": {
    "iso:country":"NL",
    "sg:address":"Oudendk 28A",
    "sg:city":"Dordrecht",
    "sg:orig_category":"Gordijnenateliers",
    "sg:phone":"+31 78 617 7927",
    "sg:postcode":"3318 AH",
    "sg:province":"South Holland",
    "wof:name":"Spolitex",
    "wof:placetype":"venue"
},
  "geometry": {"coordinates":[4.680703,51.790886],"type":"Point"}
}