{
  "type": "Feature",
  "properties": {
    "iso:country":"NL",
    "sg:address":"Luijnhorststraat 7",
    "sg:city":"Didam",
    "sg:orig_category":"Architecten",
    "sg:phone":"+31 316 228 428",
    "sg:postcode":"6941 RD",
    "sg:province":"Gelderland",
    "wof:name":"Adviesbureau Planpartners",
    "wof:placetype":"venue"
},
  "geometry": {"coordinates":[6.114591,51.94627],"type":"Point"}
}