{
  "type": "Feature",
  "properties": {
    "addr:full":"4E Broekdk 31D Aalten Gelderland 7122 JD",
    "addr:housenumber":"31d",
    "addr:postcode":"7122 jd",
    "addr:street":"4E Broekdk;Gelderland",
    "iso:country":"NL",
    "sg:address":"4E Broekdk 31D",
    "sg:city":"Aalten",
    "sg:orig_category":"Schilders",
    "sg:phone":"+31 543 472 504",
    "sg:postcode":"7122 JD",
    "sg:province":"Gelderland",
    "wof:name":"Albers Vof",
    "wof:placetype":"venue"
},
  "geometry": {"coordinates":[6.569233,51.908401],"type":"Point"}
}