{
  "type": "Feature",
  "properties": {
    "addr:full":"Schonbergwg 62 Almere Flevoland 1323 HB",
    "addr:housenumber":"62",
    "addr:postcode":"1323 hb",
    "addr:street":"Schonbergwg;Flevoland",
    "iso:country":"NL",
    "sg:address":"Schonbergwg 62",
    "sg:city":"Almere",
    "sg:orig_category":"Grondwerken",
    "sg:phone":"+31 36 536 0858",
    "sg:postcode":"1323 HB",
    "sg:province":"Flevoland",
    "wof:name":"Kooijman & Zn Bv, Fa L",
    "wof:placetype":"venue"
},
  "geometry": {"coordinates":[5.193532,52.362434],"type":"Point"}
}