{
  "type": "Feature",
  "properties": {
    "iso:country":"NL",
    "sg:address":"Heemradenlaan 42",
    "sg:city":"Ijsselstein Ut",
    "sg:classifiers":[
        {
            "category":"Education",
            "subcategory":"Preschool",
            "type":"Public Place"
        }
    ],
    "sg:phone":"+31 30 688 8211",
    "sg:postcode":"3401 GX",
    "sg:province":"Utrecht",
    "sg:tags":[
        "kleuteronderwijs",
        "basis-"
    ],
    "wof:name":"Christelijke Basisschool De Brug",
    "wof:placetype":"venue"
},
  "geometry": {"coordinates":[5.027514,52.022339],"type":"Point"}
}