{
  "type": "Feature",
  "properties": {
    "addr:full":"Vlinderveen 218 Spykenisse Zuid-Holland 3205 EJ",
    "addr:housenumber":"218",
    "addr:postcode":"3205 ej",
    "addr:street":"Vlinderveen",
    "iso:country":"NL",
    "sg:address":"Vlinderveen 218",
    "sg:city":"Spykenisse",
    "sg:orig_category":"Bloemen En Planten",
    "sg:phone":"+31 181 644 250",
    "sg:postcode":"3205 EJ",
    "sg:province":"Zuid-Holland",
    "wof:name":"Spelt Bloemen- & Plantenhandel, V/D",
    "wof:placetype":"venue"
},
  "geometry": {"coordinates":[4.344272,51.834335],"type":"Point"}
}