{
  "type": "Feature",
  "properties": {
    "addr:full":"Pierinkdk 24 Gelselaar Gelderland 7275 AJ",
    "addr:housenumber":"24",
    "addr:postcode":"7275 aj",
    "addr:street":"Pierinkdk;Gelderland",
    "iso:country":"NL",
    "sg:address":"Pierinkdk 24",
    "sg:city":"Gelselaar",
    "sg:orig_category":"Schilders",
    "sg:phone":"+31 545 481 189",
    "sg:postcode":"7275 AJ",
    "sg:province":"Gelderland",
    "wof:name":"Bosman, J",
    "wof:placetype":"venue"
},
  "geometry": {"coordinates":[6.541441,52.17318],"type":"Point"}
}