{
  "type": "Feature",
  "properties": {
    "addr:full":"V Brederodestr 61 Callantsoog North Holland 1759 VG",
    "addr:housenumber":"61",
    "addr:postcode":"1759 vg",
    "iso:country":"NL",
    "sg:address":"V Brederodestr 61",
    "sg:city":"Callantsoog",
    "sg:orig_category":"Acupunctuur",
    "sg:phone":"+31 224 581 925",
    "sg:postcode":"1759 VG",
    "sg:province":"North Holland",
    "wof:name":"Joop Schaafsma",
    "wof:placetype":"venue"
},
  "geometry": {"coordinates":[4.695592,52.836597],"type":"Point"}
}