{
  "type": "Feature",
  "properties": {
    "iso:country":"NL",
    "sg:address":"V Brederodestr 61",
    "sg:city":"Callantsoog",
    "sg:orig_category":"Acupunctuur",
    "sg:phone":"+31 224 581 925",
    "sg:postcode":"1759 VG",
    "sg:province":"North Holland",
    "wof:name":"Joop Schaafsma",
    "wof:placetype":"venue"
},
  "geometry": {"coordinates":[4.695592,52.836597],"type":"Point"}
}