{
  "type": "Feature",
  "properties": {
    "addr:full":"Potdijk 8 Markelo Overijssel 7475 SL",
    "addr:housenumber":"8",
    "addr:postcode":"7475 sl",
    "addr:street":"Potdijk",
    "iso:country":"NL",
    "sg:address":"Potdijk 8",
    "sg:city":"Markelo",
    "sg:orig_category":"Bouwmaterialen Gh",
    "sg:phone":"+31 547 361 809",
    "sg:postcode":"7475 SL",
    "sg:province":"Overijssel",
    "wof:name":"Silexco Bv",
    "wof:placetype":"venue"
},
  "geometry": {"coordinates":[6.511953,52.240349],"type":"Point"}
}