{
  "type": "Feature",
  "properties": {
    "iso:country":"NL",
    "sg:address":"Brouwerijstraat 12",
    "sg:city":"Wagenberg",
    "sg:orig_category":"Boekhouders",
    "sg:phone":"+31 76 593 4464",
    "sg:postcode":"4845 CN",
    "sg:province":"North Brabant",
    "wof:name":"Administratiekantoor Van Steenhoven",
    "wof:placetype":"venue"
},
  "geometry": {"coordinates":[4.748511,51.666447],"type":"Point"}
}