{
  "type": "Feature",
  "properties": {
    "iso:country":"NL",
    "sg:address":"Hinthamerstraat 131",
    "sg:city":"'S Hertogenbosch",
    "sg:orig_category":"Kantoorartikelen",
    "sg:phone":"+31 73 614 3800",
    "sg:postcode":"5211 MJ",
    "sg:province":"North Brabant",
    "wof:name":"Repro Systems Nederland Bv",
    "wof:placetype":"venue"
},
  "geometry": {"coordinates":[5.3101010323,51.6884918213],"type":"Point"}
}