{
  "type": "Feature",
  "properties": {
    "addr:full":"Bosstr 7 Baarn Utrecht 3742 CK",
    "addr:housenumber":"7",
    "addr:postcode":"3742 ck",
    "addr:street":"Bosstr",
    "iso:country":"NL",
    "sg:address":"Bosstr 7",
    "sg:city":"Baarn",
    "sg:orig_category":"Verzekeringen - Verzekeringskantoren",
    "sg:phone":"+31 35 548 0770",
    "sg:postcode":"3742 CK",
    "sg:province":"Utrecht",
    "wof:name":"Bos",
    "wof:placetype":"venue"
},
  "geometry": {"coordinates":[5.292121,52.21101],"type":"Point"}
}