{
  "type": "Feature",
  "properties": {
    "addr:full":"P Bruegelstr 14A Vlymen Noord-Brabant 5251 LB",
    "addr:housenumber":"14a",
    "addr:postcode":"5251 lb",
    "addr:street":"P;Vlymen",
    "iso:country":"NL",
    "sg:address":"P Bruegelstr 14A",
    "sg:city":"Vlymen",
    "sg:orig_category":"Fitnesscentra",
    "sg:phone":"+31 73 511 4993",
    "sg:postcode":"5251 LB",
    "sg:province":"Noord-Brabant",
    "sg:website":"http://www.totalfitvlijmen.nl",
    "wof:name":"Total-Fit",
    "wof:placetype":"venue"
},
  "geometry": {"coordinates":[-118.192368,33.766418],"type":"Point"}
}