{
  "type": "Feature",
  "properties": {
    "addr:full":"Dorpsstraat 76 Uffelte Drenthe 7975 AR",
    "addr:housenumber":"76",
    "addr:postcode":"7975",
    "addr:street":"Dorpsstraat",
    "iso:country":"NL",
    "sg:address":"Dorpsstraat 76",
    "sg:city":"Uffelte",
    "sg:orig_category":"Kampeerterreinen",
    "sg:phone":"+31 521 351 661",
    "sg:postcode":"7975 AR",
    "sg:province":"Drenthe",
    "wof:name":"Bos En Ven",
    "wof:placetype":"venue"
},
  "geometry": {"coordinates":[6.2688298225,52.7900619507],"type":"Point"}
}