{
  "type": "Feature",
  "properties": {
    "addr:full":"Badweg 1 Lelystad Flevoland 8223 PA",
    "addr:housenumber":"1",
    "addr:postcode":"8223",
    "addr:street":"Badweg;Flevoland",
    "iso:country":"NL",
    "sg:address":"Badweg 1",
    "sg:city":"Lelystad",
    "sg:orig_category":"Kampeerterreinen",
    "sg:phone":"+31 320 231 735",
    "sg:postcode":"8223 PA",
    "sg:province":"Flevoland",
    "wof:name":"Camping De Houtrib",
    "wof:placetype":"venue"
},
  "geometry": {"coordinates":[5.4987478256,52.5206375122],"type":"Point"}
}