{
  "type": "Feature",
  "properties": {
    "addr:full":"Nieuwehaven 7 Gouda South Holland 2801 CS",
    "addr:housenumber":"7",
    "addr:postcode":"2801 cs",
    "addr:street":"Nieuwehaven",
    "iso:country":"NL",
    "sg:address":"Nieuwehaven 7",
    "sg:city":"Gouda",
    "sg:classifiers":[
        {
            "category":"Food & Beverages",
            "subcategory":"Fruits & Vegetables",
            "type":"Retail Goods"
        }
    ],
    "sg:phone":"+31 182 513 461",
    "sg:postcode":"2801 CS",
    "sg:province":"South Holland",
    "sg:tags":[
        "groenten"
    ],
    "wof:name":"T Westland",
    "wof:placetype":"venue"
},
  "geometry": {"coordinates":[4.708475,52.013706],"type":"Point"}
}