{
  "type": "Feature",
  "properties": {
    "addr:full":"Rode Schouw 17 Halsteren North Brabant 4661 VD",
    "addr:housenumber":"17",
    "addr:postcode":"4661 vd",
    "addr:street":"Rode Schouw",
    "iso:country":"NL",
    "sg:address":"Rode Schouw 17",
    "sg:city":"Halsteren",
    "sg:classifiers":[
        {
            "category":"Shopping",
            "subcategory":"Clothing, Apparel, & Fashions",
            "type":"Retail Goods"
        }
    ],
    "sg:phone":"+31 164 687 799",
    "sg:postcode":"4661 VD",
    "sg:province":"North Brabant",
    "sg:tags":[
        "ondergoed",
        "lingerie"
    ],
    "wof:name":"Nicole Foundation Service",
    "wof:placetype":"venue"
},
  "geometry": {"coordinates":[4.28365,51.523766],"type":"Point"}
}