{
  "type": "Feature",
  "properties": {
    "addr:full":"Schoolstr 10A Vleuten Utrecht 3451 AD",
    "addr:housenumber":"10a",
    "addr:postcode":"3451 ad",
    "addr:street":"Schoolstr",
    "iso:country":"NL",
    "sg:address":"Schoolstr 10A",
    "sg:city":"Vleuten",
    "sg:orig_category":"Verenigingen En Stichtingen",
    "sg:phone":"+31 30 230 3090",
    "sg:postcode":"3451 AD",
    "sg:province":"Utrecht",
    "wof:name":"Sportsticht Vleuten-De Meern",
    "wof:placetype":"venue"
},
  "geometry": {"coordinates":[5.012496,52.107975],"type":"Point"}
}