{
  "type": "Feature",
  "properties": {
    "addr:full":"Lochemseweg 127 Harfsen Gelderland 7217 RC",
    "addr:housenumber":"127",
    "addr:postcode":"7217 rc",
    "addr:street":"Lochemseweg;Gelderland",
    "iso:country":"NL",
    "sg:address":"Lochemseweg 127",
    "sg:city":"Harfsen",
    "sg:orig_category":"Meubelzaken, Woning- And Keukeninrichting",
    "sg:phone":"+31 573 431 274",
    "sg:postcode":"7217 RC",
    "sg:province":"Gelderland",
    "wof:name":"Firma Nengerman-Wuestman",
    "wof:placetype":"venue"
},
  "geometry": {"coordinates":[6.293039,52.207542],"type":"Point"}
}