{
  "type": "Feature",
  "properties": {
    "addr:full":"De Eclips 7 Dronten Flevoland 8254 AR",
    "addr:housenumber":"7",
    "addr:postcode":"8254",
    "addr:street":"De Eclips;Flevoland",
    "iso:country":"NL",
    "sg:address":"De Eclips 7",
    "sg:city":"Dronten",
    "sg:orig_category":"Keramiek - Fabrieken En Groothandel",
    "sg:phone":"+31 321 321 596",
    "sg:postcode":"8254 AR",
    "sg:province":"Flevoland",
    "wof:name":"D & S",
    "wof:placetype":"venue"
},
  "geometry": {"coordinates":[5.728269,52.525677],"type":"Point"}
}