{
  "type": "Feature",
  "properties": {
    "addr:full":"Wannerstraat 1 Heerlen Limburg 6413 EV",
    "addr:housenumber":"1",
    "addr:postcode":"6413 ev",
    "addr:street":"Wannerstraat",
    "iso:country":"NL",
    "sg:address":"Wannerstraat 1",
    "sg:city":"Heerlen",
    "sg:classifiers":[
        {
            "category":"Food & Beverages",
            "subcategory":"Fruits & Vegetables",
            "type":"Retail Goods"
        }
    ],
    "sg:phone":"+31 45 521 6940",
    "sg:postcode":"6413 EV",
    "sg:province":"Limburg",
    "sg:tags":[
        "groenten"
    ],
    "wof:name":"Versappeltje",
    "wof:placetype":"venue"
},
  "geometry": {"coordinates":[5.955773,50.915855],"type":"Point"}
}