{
  "type": "Feature",
  "properties": {
    "addr:full":"De Woudhorne 31 Dokkum Friesland 9101 DE",
    "addr:housenumber":"31",
    "addr:postcode":"9101 de",
    "addr:street":"De Woudhorne",
    "iso:country":"NL",
    "sg:address":"De Woudhorne 31",
    "sg:city":"Dokkum",
    "sg:orig_category":"Technische Studies And Onderzoek",
    "sg:phone":"+31 519 295 321",
    "sg:postcode":"9101 DE",
    "sg:province":"Friesland",
    "wof:name":"P. Prins Engineering Bv",
    "wof:placetype":"venue"
},
  "geometry": {"coordinates":[5.984717,53.319115],"type":"Point"}
}