{
  "type": "Feature",
  "properties": {
    "addr:full":"B V Egmondstr 41 Vianen Zh South Holland 4133 HP",
    "addr:housenumber":"41",
    "addr:postcode":"zh;4133 hp",
    "addr:street":"V Egmondstr",
    "iso:country":"NL",
    "sg:address":"B V Egmondstr 41",
    "sg:city":"Vianen Zh",
    "sg:orig_category":"Administratie- En Boekhoudkantoren",
    "sg:phone":"+31 347 326 266",
    "sg:postcode":"4133 HP",
    "sg:province":"South Holland",
    "wof:name":"Adking",
    "wof:placetype":"venue"
},
  "geometry": {"coordinates":[5.06668,51.980968],"type":"Point"}
}