{
  "type": "Feature",
  "properties": {
    "addr:full":"Bitgumerdyk 79 Marssum Provincie Friesland 9034 GH",
    "addr:housenumber":"79",
    "addr:postcode":"9034 gh",
    "addr:street":"Bitgumerdyk;Provincie Friesland",
    "iso:country":"NL",
    "sg:address":"Bitgumerdyk 79",
    "sg:city":"Marssum",
    "sg:orig_category":"Bloemen And Planten",
    "sg:phone":"+31 58 254 1313",
    "sg:postcode":"9034 GH",
    "sg:province":"Provincie Friesland",
    "wof:name":"Vof De Leeuw",
    "wof:placetype":"venue"
},
  "geometry": {"coordinates":[5.722893,53.207912],"type":"Point"}
}