{
  "type": "Feature",
  "properties": {
    "iso:country":"NL",
    "sg:address":"Plantsoen 55",
    "sg:city":"Wageningen",
    "sg:orig_category":"Banken And Kredietinstellingen",
    "sg:phone":"+31 317 478 111",
    "sg:postcode":"6701 AS",
    "sg:province":"Gelderland",
    "wof:name":"Rabobank",
    "wof:placetype":"venue"
},
  "geometry": {"coordinates":[5.664773,51.968143],"type":"Point"}
}