{
  "type": "Feature",
  "properties": {
    "addr:full":"Elzepas 40 Elst Gld Gelderland 6662 XC",
    "addr:housenumber":"40",
    "addr:postcode":"6662 xc",
    "addr:street":"Elzepas;Gld Gelderland",
    "iso:country":"NL",
    "sg:address":"Elzepas 40",
    "sg:city":"Elst Gld",
    "sg:orig_category":"Kantoor- En Secretariaatsservice",
    "sg:phone":"+31 481 350 517",
    "sg:postcode":"6662 XC",
    "sg:province":"Gelderland",
    "wof:name":"Vh Business Serv",
    "wof:placetype":"venue"
},
  "geometry": {"coordinates":[5.8377861977,51.9135818481],"type":"Point"}
}