{
  "type": "Feature",
  "properties": {
    "addr:full":"Raadhuisstraat 7 Panningen Limburg 5981 BA",
    "addr:housenumber":"7",
    "addr:postcode":"5981 ba",
    "addr:street":"Raadhuisstraat",
    "iso:country":"NL",
    "sg:address":"Raadhuisstraat 7",
    "sg:city":"Panningen",
    "sg:orig_category":"Meubelzaken, Woning- And Keukeninrichting",
    "sg:phone":"+31 77 307 1394",
    "sg:postcode":"5981 BA",
    "sg:province":"Limburg",
    "wof:name":"Omsels Woonsfeer Bv",
    "wof:placetype":"venue"
},
  "geometry": {"coordinates":[5.981672,51.328075],"type":"Point"}
}