{
  "type": "Feature",
  "properties": {
    "addr:full":"Fahrenheitstraat 512 'S Gravenhage Zuid-Holland 2561 DH",
    "addr:housenumber":"512 '",
    "addr:postcode":"2561 dh",
    "addr:street":"Fahrenheitstraat",
    "iso:country":"NL",
    "sg:address":"Fahrenheitstraat 512",
    "sg:city":"'S Gravenhage",
    "sg:orig_category":"Herenmodezaken",
    "sg:phone":"+31 70 392 4013",
    "sg:postcode":"2561 DH",
    "sg:province":"Zuid-Holland",
    "wof:name":"Roxy Herenmode",
    "wof:placetype":"venue"
},
  "geometry": {"coordinates":[4.27581,52.074532],"type":"Point"}
}