{
  "type": "Feature",
  "properties": {
    "addr:full":"Molenstr 46 Ophemert Gelderland 4061 AD",
    "addr:housenumber":"46",
    "addr:postcode":"4061 ad",
    "addr:street":"Molenstr;Gelderland",
    "iso:country":"NL",
    "sg:address":"Molenstr 46",
    "sg:city":"Ophemert",
    "sg:orig_category":"Kappers",
    "sg:phone":"+31 344 652 553",
    "sg:postcode":"4061 AD",
    "sg:province":"Gelderland",
    "wof:name":"Hair Drive",
    "wof:placetype":"venue"
},
  "geometry": {"coordinates":[5.3959918022,51.8476295471],"type":"Point"}
}