{
  "type": "Feature",
  "properties": {
    "iso:country":"NL",
    "sg:address":"Piskhoarnedk 3",
    "sg:city":"Wirdum Fr",
    "sg:orig_category":"Grafisch Ontwerpers",
    "sg:phone":"+31 58 288 6307",
    "sg:postcode":"9088 BX",
    "sg:province":"Provincie Friesland",
    "wof:name":"Andringa, P",
    "wof:placetype":"venue"
},
  "geometry": {"coordinates":[5.804648,53.149754],"type":"Point"}
}