{
  "type": "Feature",
  "properties": {
    "addr:full":"Molendijk 61 Rhoon Zuid-Holland 3161 KL",
    "addr:housenumber":"61",
    "addr:postcode":"3161 kl",
    "addr:street":"Molendijk",
    "iso:country":"NL",
    "sg:address":"Molendijk 61",
    "sg:city":"Rhoon",
    "sg:orig_category":"Kappers",
    "sg:phone":"+31 10 501 4182",
    "sg:postcode":"3161 KL",
    "sg:province":"Zuid-Holland",
    "wof:name":"N N Leentfaar-Van Gent",
    "wof:placetype":"venue"
},
  "geometry": {"coordinates":[4.423709,51.863777],"type":"Point"}
}