{
  "type": "Feature",
  "properties": {
    "addr:full":"Hogeweg 61 Burgh Haamstede Zeeland 4328 PB",
    "addr:housenumber":"61",
    "addr:postcode":"4328 pb",
    "addr:street":"Hogeweg;Haamstede",
    "iso:country":"NL",
    "sg:address":"Hogeweg 61",
    "sg:city":"Burgh Haamstede",
    "sg:orig_category":"Kampeerterreinen",
    "sg:phone":"+31 111 654 230",
    "sg:postcode":"4328 PB",
    "sg:province":"Zeeland",
    "wof:name":"In De Appelwei",
    "wof:placetype":"venue"
},
  "geometry": {"coordinates":[3.7198309898,51.6820678711],"type":"Point"}
}