{
  "type": "Feature",
  "properties": {
    "addr:full":"Didamsestr 17 Zevenaar Gelderland 6901 HB",
    "addr:housenumber":"17",
    "addr:postcode":"6901 hb",
    "addr:street":"Didamsestr",
    "iso:country":"NL",
    "sg:address":"Didamsestr 17",
    "sg:city":"Zevenaar",
    "sg:orig_category":"Warenhuizen",
    "sg:phone":"+31 316 524 302",
    "sg:postcode":"6901 HB",
    "sg:province":"Gelderland",
    "wof:name":"Hema",
    "wof:placetype":"venue"
},
  "geometry": {"coordinates":[6.0776629448,51.9281806946],"type":"Point"}
}