{
  "type": "Feature",
  "properties": {
    "addr:full":"Sniederslaan 21 Bladel Noord-Brabant 5531 EG",
    "addr:housenumber":"21",
    "addr:postcode":"5531 eg",
    "addr:street":"Sniederslaan",
    "iso:country":"NL",
    "sg:address":"Sniederslaan 21",
    "sg:city":"Bladel",
    "sg:orig_category":"Kappers",
    "sg:phone":"+31 497 383 036",
    "sg:postcode":"5531 EG",
    "sg:province":"Noord-Brabant",
    "wof:name":"Herenkapsalon Hamers",
    "wof:placetype":"venue"
},
  "geometry": {"coordinates":[5.217610836,51.3669662476],"type":"Point"}
}