{
  "type": "Feature",
  "properties": {
    "addr:full":"Lepelstraat 1 Haarlem Noord-Holland 2011 RD",
    "addr:housenumber":"1",
    "addr:postcode":"2011 rd",
    "addr:street":"Lepelstraat",
    "iso:country":"NL",
    "sg:address":"Lepelstraat 1",
    "sg:city":"Haarlem",
    "sg:classifiers":[
        {
            "category":"Shopping",
            "subcategory":"Gifts & Souvenirs",
            "type":"Retail Goods"
        }
    ],
    "sg:phone":"+31 23 532 4859",
    "sg:postcode":"2011 RD",
    "sg:province":"Noord-Holland",
    "sg:tags":[
        "geschenken"
    ],
    "wof:name":"Onder De Damiaatjes",
    "wof:placetype":"venue"
},
  "geometry": {"coordinates":[4.636383,52.381187],"type":"Point"}
}