{
  "type": "Feature",
  "properties": {
    "addr:full":"Oude Rijksweg 456 Rouveen NL.08 7954 GD",
    "addr:housenumber":"456;nl.08",
    "addr:postcode":"7954 gd",
    "addr:street":"Oude Rijksweg",
    "iso:country":"NL",
    "sg:address":"Oude Rijksweg 456",
    "sg:city":"Rouveen",
    "sg:orig_category":"Verhuur Bouwmachines",
    "sg:phone":"+31 522 291 220",
    "sg:postcode":"7954 GD",
    "sg:province":"NL.08",
    "wof:name":"Aannemersbedr + Puinbrekerverhuur Kruidh",
    "wof:placetype":"venue"
},
  "geometry": {"coordinates":[6.187864,52.613632],"type":"Point"}
}