{
  "type": "Feature",
  "properties": {
    "addr:full":"J Deckersstr 35A Heeze North Brabant 5591 HN",
    "addr:housenumber":"35a",
    "addr:postcode":"5591 hn",
    "iso:country":"NL",
    "sg:address":"J Deckersstr 35A",
    "sg:city":"Heeze",
    "sg:orig_category":"Kinderkleding",
    "sg:phone":"+31 40 226 6889",
    "sg:postcode":"5591 HN",
    "sg:province":"North Brabant",
    "sg:website":"http://www.ilpaperino.nl",
    "wof:name":"Il Paperino",
    "wof:placetype":"venue"
},
  "geometry": {"coordinates":[5.578555,51.378059],"type":"Point"}
}