{
  "type": "Feature",
  "properties": {
    "addr:full":"Molenln 66 Honselersdyk Zuid-Holland 2675 CE",
    "addr:housenumber":"66",
    "addr:postcode":"2675 ce",
    "addr:street":"Molenln",
    "iso:country":"NL",
    "sg:address":"Molenln 66",
    "sg:city":"Honselersdyk",
    "sg:orig_category":"Schilders",
    "sg:phone":"+31 174 627 911",
    "sg:postcode":"2675 CE",
    "sg:province":"Zuid-Holland",
    "wof:name":"Ben Sosef Bv",
    "wof:placetype":"venue"
},
  "geometry": {"coordinates":[4.22951,52.008755],"type":"Point"}
}