{
  "type": "Feature",
  "properties": {
    "addr:full":"Hoofdwg Boven 23 Haulerwyk Friesland 8433 LB",
    "addr:housenumber":"23",
    "addr:postcode":"8433 lb",
    "addr:street":"Boven",
    "iso:country":"NL",
    "sg:address":"Hoofdwg Boven 23",
    "sg:city":"Haulerwyk",
    "sg:orig_category":"Fietsen En Bromfietsen",
    "sg:phone":"+31 516 421 294",
    "sg:postcode":"8433 LB",
    "sg:province":"Friesland",
    "wof:name":"Terpstra Tweewielers",
    "wof:placetype":"venue"
},
  "geometry": {"coordinates":[6.330323,53.065681],"type":"Point"}
}