{
  "type": "Feature",
  "properties": {
    "addr:full":"Gedempte Gracht 122 Zaandam Noord-Holland 1506 CX",
    "addr:housenumber":"122",
    "addr:postcode":"1506 cx",
    "addr:street":"Gedempte Gracht",
    "iso:country":"NL",
    "sg:address":"Gedempte Gracht 122",
    "sg:city":"Zaandam",
    "sg:orig_category":"Juweliers",
    "sg:phone":"+31 75 612 5057",
    "sg:postcode":"1506 CX",
    "sg:province":"Noord-Holland",
    "wof:name":"Goldtime",
    "wof:placetype":"venue"
},
  "geometry": {"coordinates":[4.817689,52.438736],"type":"Point"}
}