{
  "type": "Feature",
  "properties": {
    "addr:full":"Tramstraat 1 Koudekerke Zeeland 4371 BV",
    "addr:housenumber":"1",
    "addr:postcode":"4371 bv",
    "addr:street":"Tramstraat",
    "iso:country":"NL",
    "sg:address":"Tramstraat 1",
    "sg:city":"Koudekerke",
    "sg:orig_category":"Loodgieterswerk, Verwarming And Sanitaire Installaties",
    "sg:phone":"+31 118 551 681",
    "sg:postcode":"4371 BV",
    "sg:province":"Zeeland",
    "wof:name":"G. Van Boven",
    "wof:placetype":"venue"
},
  "geometry": {"coordinates":[3.554229,51.481651],"type":"Point"}
}