{
  "type": "Feature",
  "properties": {
    "iso:country":"NL",
    "sg:address":"Van Tetsstraat 21",
    "sg:city":"Hillegom",
    "sg:orig_category":"Kappers",
    "sg:phone":"+31 252 530 115",
    "sg:postcode":"2181 DA",
    "sg:province":"North Holland",
    "wof:name":"Kapsalon Joke",
    "wof:placetype":"venue"
},
  "geometry": {"coordinates":[4.5836482048,52.2997169495],"type":"Point"}
}