{
  "type": "Feature",
  "properties": {
    "addr:full":"Churchilllaan 11 Utrecht Utrecht 3527 GV",
    "addr:housenumber":"11",
    "addr:postcode":"3527 gv",
    "addr:street":"Churchilllaan",
    "iso:country":"NL",
    "sg:address":"Churchilllaan 11",
    "sg:city":"Utrecht",
    "sg:orig_category":"Organisaties And Verenigingen",
    "sg:phone":"+31 30 291 6600",
    "sg:postcode":"3527 GV",
    "sg:province":"Utrecht",
    "wof:name":"Cg-Raad",
    "wof:placetype":"venue"
},
  "geometry": {"coordinates":[5.0957641602,52.0739135742],"type":"Point"}
}