{
  "type": "Feature",
  "properties": {
    "addr:full":"Kuipersweg 5 Ambt Delden Overijssel 7495 TV",
    "addr:housenumber":"5",
    "addr:postcode":"7495 tv",
    "addr:street":"Kuipersweg",
    "iso:country":"NL",
    "sg:address":"Kuipersweg 5",
    "sg:city":"Ambt Delden",
    "sg:orig_category":"Hoefdierhouderijen",
    "sg:phone":"+31 74 266 1864",
    "sg:postcode":"7495 TV",
    "sg:province":"Overijssel",
    "wof:name":"Voshaar En Olthof Paardenhandel",
    "wof:placetype":"venue"
},
  "geometry": {"coordinates":[6.712634,52.301819],"type":"Point"}
}