{
  "type": "Feature",
  "properties": {
    "addr:full":"Utrechtsewg 329 De Bilt Utrecht 3731 GA",
    "addr:housenumber":"329",
    "addr:postcode":"3731 ga",
    "iso:country":"NL",
    "sg:address":"Utrechtsewg 329",
    "sg:city":"De Bilt",
    "sg:orig_category":"Bedrijfsopleidingen",
    "sg:phone":"+31 30 220 1741",
    "sg:postcode":"3731 GA",
    "sg:province":"Utrecht",
    "sg:website":"http://www.wage.nl",
    "wof:name":"Wage Bv",
    "wof:placetype":"venue"
},
  "geometry": {"coordinates":[5.170755,52.101521],"type":"Point"}
}