{
  "type": "Feature",
  "properties": {
    "addr:full":"S Spierswg 21 Zaandam Noord-Holland 1506 RZ",
    "addr:housenumber":"21",
    "addr:postcode":"1506 rz",
    "iso:country":"NL",
    "sg:address":"S Spierswg 21",
    "sg:city":"Zaandam",
    "sg:orig_category":"Houtgroothandel",
    "sg:phone":"+31 75 681 9999",
    "sg:postcode":"1506 RZ",
    "sg:province":"Noord-Holland",
    "wof:name":"Pontcentrop",
    "wof:placetype":"venue"
},
  "geometry": {"coordinates":[4.817047,52.425438],"type":"Point"}
}