{
  "type": "Feature",
  "properties": {
    "addr:full":"Port Natalweg 22 Assen Drenthe 9401 PX",
    "addr:housenumber":"22",
    "addr:postcode":"9401 px",
    "addr:street":"Port Natalweg",
    "iso:country":"NL",
    "sg:address":"Port Natalweg 22",
    "sg:city":"Assen",
    "sg:orig_category":"Verzekeringen",
    "sg:phone":"+31 592 313 735",
    "sg:postcode":"9401 PX",
    "sg:province":"Drenthe",
    "wof:name":"Assurantiekantoor Meesters En Bauerhuit",
    "wof:placetype":"venue"
},
  "geometry": {"coordinates":[6.564123,52.986431],"type":"Point"}
}