{
  "type": "Feature",
  "properties": {
    "addr:full":"Arnhemsewg 14 Otterlo Gelderland 6731 BS",
    "addr:housenumber":"14",
    "addr:postcode":"6731 bs",
    "addr:street":"Arnhemsewg;Gelderland",
    "iso:country":"NL",
    "sg:address":"Arnhemsewg 14",
    "sg:city":"Otterlo",
    "sg:orig_category":"Banken",
    "sg:phone":"+31 318 591 261",
    "sg:postcode":"6731 BS",
    "sg:province":"Gelderland",
    "sg:website":"http://www.rabobank.nl",
    "wof:name":"Rabobank",
    "wof:placetype":"venue"
},
  "geometry": {"coordinates":[5.771277,52.099792],"type":"Point"}
}