{
  "type": "Feature",
  "properties": {
    "addr:full":"De Tienden 34 Nuenen Noord-Brabant 5674 TB",
    "addr:housenumber":"34",
    "addr:postcode":"5674 tb",
    "addr:street":"De Tienden",
    "iso:country":"NL",
    "sg:address":"De Tienden 34",
    "sg:city":"Nuenen",
    "sg:classifiers":[
        {
            "category":"Retail",
            "subcategory":"Auto Repair",
            "type":"Services"
        }
    ],
    "sg:phone":"+31 40 283 2521",
    "sg:postcode":"5674 TB",
    "sg:province":"Noord-Brabant",
    "sg:tags":[
        "garage"
    ],
    "wof:name":"Greef, B J V De",
    "wof:placetype":"venue"
},
  "geometry": {"coordinates":[5.552427,51.45042],"type":"Point"}
}