{
  "type": "Feature",
  "properties": {
    "iso:country":"NL",
    "sg:address":"Angelsloerdijk 31",
    "sg:city":"Emmen",
    "sg:orig_category":"Kampeerterreinen",
    "sg:phone":"+31 591 612 080",
    "sg:postcode":"7822 HK",
    "sg:province":"Drenthe",
    "wof:name":"Camping Emmen Vof",
    "wof:placetype":"venue"
},
  "geometry": {"coordinates":[6.9099140167,52.7809486389],"type":"Point"}
}