{
  "type": "Feature",
  "properties": {
    "addr:full":"Promenade 51 Heerlen Limburg 6411 JB",
    "addr:housenumber":"51",
    "addr:postcode":"6411 jb",
    "addr:street":"Promenade",
    "iso:country":"NL",
    "sg:address":"Promenade 51",
    "sg:city":"Heerlen",
    "sg:orig_category":"Damesmodezaken",
    "sg:phone":"+31 45 571 4357",
    "sg:postcode":"6411 JB",
    "sg:province":"Limburg",
    "wof:name":"New Generation Bv",
    "wof:placetype":"venue"
},
  "geometry": {"coordinates":[5.976584,50.887333],"type":"Point"}
}