{
  "type": "Feature",
  "properties": {
    "addr:full":"Past H C Maatstr 2 Oudorp Nh Noord-Holland 1829 BK",
    "addr:housenumber":"2",
    "addr:postcode":"1829 bk",
    "addr:street":"Past H C Maatstr",
    "iso:country":"NL",
    "sg:address":"Past H C Maatstr 2",
    "sg:city":"Oudorp Nh",
    "sg:orig_category":"Psychotherapeuten",
    "sg:phone":"+31 72 520 1488",
    "sg:postcode":"1829 BK",
    "sg:province":"Noord-Holland",
    "wof:name":"Praktijk Voor Psychotherapie",
    "wof:placetype":"venue"
},
  "geometry": {"coordinates":[4.773324,52.633186],"type":"Point"}
}