{
  "type": "Feature",
  "properties": {
    "addr:full":"De Wup 20 Broek Op Langedijk Noord-Holland 1721 EB",
    "addr:housenumber":"20",
    "addr:postcode":"1721 eb",
    "addr:street":"De Wup",
    "iso:country":"NL",
    "sg:address":"De Wup 20",
    "sg:city":"Broek Op Langedijk",
    "sg:orig_category":"Alternatieve Geneeskunde",
    "sg:phone":"+31 226 320 488",
    "sg:postcode":"1721 EB",
    "sg:province":"Noord-Holland",
    "wof:name":"Schoonheidssalon Unique",
    "wof:placetype":"venue"
},
  "geometry": {"coordinates":[4.804595,52.677204],"type":"Point"}
}