{
  "type": "Feature",
  "properties": {
    "addr:full":"A Duyckstr 16 S Gravenhage South Holland 2582 TK",
    "addr:housenumber":"16",
    "addr:postcode":"2582 tk",
    "addr:street":"S Gravenhage",
    "iso:country":"NL",
    "sg:address":"A Duyckstr 16",
    "sg:city":"S Gravenhage",
    "sg:orig_category":"Adviesbureaus Marketing",
    "sg:phone":"+31 70 354 7628",
    "sg:postcode":"2582 TK",
    "sg:province":"South Holland",
    "wof:name":"Wp Cons Ned",
    "wof:placetype":"venue"
},
  "geometry": {"coordinates":[4.27852,52.092411],"type":"Point"}
}