{
  "type": "Feature",
  "properties": {
    "addr:full":"Nobelstraat 4 Brielle Zuid-Holland 3231 BC",
    "addr:housenumber":"4",
    "addr:postcode":"3231 bc",
    "addr:street":"Nobelstraat",
    "iso:country":"NL",
    "sg:address":"Nobelstraat 4",
    "sg:city":"Brielle",
    "sg:orig_category":"Verlichting And Huishoudartikelen",
    "sg:phone":"+31 181 417 906",
    "sg:postcode":"3231 BC",
    "sg:province":"Zuid-Holland",
    "wof:name":"Artilight",
    "wof:placetype":"venue"
},
  "geometry": {"coordinates":[4.164551,51.902157],"type":"Point"}
}