{
  "type": "Feature",
  "properties": {
    "iso:country":"NL",
    "sg:address":"Brejeland 6",
    "sg:city":"Enkhuizen",
    "sg:orig_category":"Montagebedrijven",
    "sg:phone":"+31 228 325 440",
    "sg:postcode":"1602 KZ",
    "sg:province":"North Holland",
    "sg:website":"http://www.tecmoteam.nl",
    "wof:name":"Tecma Team Vof",
    "wof:placetype":"venue"
},
  "geometry": {"coordinates":[5.273302,52.715591],"type":"Point"}
}