{
  "type": "Feature",
  "properties": {
    "addr:full":"V A V Wyckskd 35 Utrecht Utrecht 3512 VR",
    "addr:housenumber":"35",
    "addr:postcode":"3512 vr",
    "addr:street":"V A V Wyckskd",
    "iso:country":"NL",
    "sg:address":"V A V Wyckskd 35",
    "sg:city":"Utrecht",
    "sg:orig_category":"Loodgieters",
    "sg:phone":"+31 30 231 4807",
    "sg:postcode":"3512 VR",
    "sg:province":"Utrecht",
    "wof:name":"Batijs Bv",
    "wof:placetype":"venue"
},
  "geometry": {"coordinates":[5.115405,52.088932],"type":"Point"}
}