{
  "type": "Feature",
  "properties": {
    "addr:full":"Klokstr 10 Leeuwarden Provincie Friesland 8911 HC",
    "addr:housenumber":"10",
    "addr:postcode":"8911 hc",
    "addr:street":"Klokstr;Provincie Friesland",
    "iso:country":"NL",
    "sg:address":"Klokstr 10",
    "sg:city":"Leeuwarden",
    "sg:orig_category":"Boeken Antiquarische En Gebruikte",
    "sg:phone":"+31 58 215 2288",
    "sg:postcode":"8911 HC",
    "sg:province":"Provincie Friesland",
    "wof:name":"Friesche Handboekbinder, De",
    "wof:placetype":"venue"
},
  "geometry": {"coordinates":[5.79712,53.201614],"type":"Point"}
}