{
  "type": "Feature",
  "properties": {
    "addr:full":"Bekemaln 40 Warffum Groningen 9989 CN",
    "addr:housenumber":"40",
    "addr:postcode":"9989 cn",
    "addr:street":"Bekemaln",
    "iso:country":"NL",
    "sg:address":"Bekemaln 40",
    "sg:city":"Warffum",
    "sg:orig_category":"Kappers",
    "sg:phone":"+31 595 426 445",
    "sg:postcode":"9989 CN",
    "sg:province":"Groningen",
    "wof:name":"Nicole",
    "wof:placetype":"venue"
},
  "geometry": {"coordinates":[6.552573,53.390388],"type":"Point"}
}