{
  "type": "Feature",
  "properties": {
    "addr:full":"Weverstraat 12 Uden Noord-Brabant 5405 BN",
    "addr:housenumber":"12",
    "addr:postcode":"5405 bn",
    "addr:street":"Weverstraat",
    "iso:country":"NL",
    "sg:address":"Weverstraat 12",
    "sg:city":"Uden",
    "sg:orig_category":"Meubelzaken, Woning- And Keukeninrichting",
    "sg:phone":"+31 413 337 474",
    "sg:postcode":"5405 BN",
    "sg:province":"Noord-Brabant",
    "wof:name":"Grosfillex Bv",
    "wof:placetype":"venue"
},
  "geometry": {"coordinates":[114.598969,4.52513],"type":"Point"}
}