{
  "type": "Feature",
  "properties": {
    "addr:full":"Grote Poelslak 26 Amersfoort Utrecht 3824 HW",
    "addr:housenumber":"26",
    "addr:postcode":"3824 hw",
    "addr:street":"Grote Poelslak",
    "iso:country":"NL",
    "sg:address":"Grote Poelslak 26",
    "sg:city":"Amersfoort",
    "sg:orig_category":"Weegwerktuigen - Fabrieken En Groothandel",
    "sg:phone":"+31 33 453 0000",
    "sg:postcode":"3824 HW",
    "sg:province":"Utrecht",
    "wof:name":"Heus",
    "wof:placetype":"venue"
},
  "geometry": {"coordinates":[5.3724389076,52.2016334534],"type":"Point"}
}