{
  "type": "Feature",
  "properties": {
    "iso:country":"NL",
    "sg:address":"Hoge Noordweg 21",
    "sg:city":"Naaldwijk",
    "sg:orig_category":"Metaalwerken",
    "sg:phone":"+31 174 640 726",
    "sg:postcode":"2671 DZ",
    "sg:province":"Zuid-Holland",
    "wof:name":"M.A. Van Der Sar",
    "wof:placetype":"venue"
},
  "geometry": {"coordinates":[4.230034,51.98077],"type":"Point"}
}