{
  "type": "Feature",
  "properties": {
    "iso:country":"NL",
    "sg:address":"Singel 36",
    "sg:city":"Sneek",
    "sg:orig_category":"Artsen And Specialisten",
    "sg:phone":"+31 515 412 624",
    "sg:postcode":"8601 AK",
    "sg:province":"Friesland",
    "wof:name":"W L Bogtstra En J P A M Van Wayenburg",
    "wof:placetype":"venue"
},
  "geometry": {"coordinates":[5.662578,53.031384],"type":"Point"}
}