{
  "type": "Feature",
  "properties": {
    "iso:country":"NL",
    "sg:address":"Kanaalweg 5",
    "sg:city":"Assendelft",
    "sg:orig_category":"Goederenvervoer Over De Weg",
    "sg:phone":"+31 75 687 1266",
    "sg:postcode":"1566 NA",
    "sg:province":"Noord-Holland",
    "wof:name":"Transportbedrijf W. Van Der Kolk En Zonen Vof",
    "wof:placetype":"venue"
},
  "geometry": {"coordinates":[4.6939,52.447475],"type":"Point"}
}