{
  "type": "Feature",
  "properties": {
    "addr:full":"Marktstraat 57 Musselkanaal Groningen 9581 AC",
    "addr:housenumber":"57",
    "addr:postcode":"9581 ac",
    "addr:street":"Marktstraat",
    "iso:country":"NL",
    "sg:address":"Marktstraat 57",
    "sg:city":"Musselkanaal",
    "sg:orig_category":"Schoenen",
    "sg:phone":"+31 599 412 554",
    "sg:postcode":"9581 AC",
    "sg:province":"Groningen",
    "wof:name":"Schoenhandel Boomsma",
    "wof:placetype":"venue"
},
  "geometry": {"coordinates":[7.012692,52.931183],"type":"Point"}
}