{
  "type": "Feature",
  "properties": {
    "addr:full":"Neuweg 384 Hilversum North Holland 1215 JJ",
    "addr:housenumber":"384",
    "addr:postcode":"1215 jj",
    "addr:street":"Neuweg",
    "iso:country":"NL",
    "sg:address":"Neuweg 384",
    "sg:city":"Hilversum",
    "sg:orig_category":"Beautyfarms And Sauna'S",
    "sg:phone":"+31 35 623 1125",
    "sg:postcode":"1215 JJ",
    "sg:province":"North Holland",
    "wof:name":"Sonja'S Beauty Center Bv",
    "wof:placetype":"venue"
},
  "geometry": {"coordinates":[5.155249,52.214066],"type":"Point"}
}