{
  "type": "Feature",
  "properties": {
    "addr:full":"Dirk Kleimanstraat 12 Zaandam Noord-Holland 1502 XE",
    "addr:housenumber":"12",
    "addr:postcode":"1502 xe",
    "addr:street":"Dirk Kleimanstraat",
    "iso:country":"NL",
    "sg:address":"Dirk Kleimanstraat 12",
    "sg:city":"Zaandam",
    "sg:orig_category":"Loodgieterswerk, Verwarming And Sanitaire Installaties",
    "sg:phone":"+31 6 54737443",
    "sg:postcode":"1502 XE",
    "sg:province":"Noord-Holland",
    "wof:name":"Imc",
    "wof:placetype":"venue"
},
  "geometry": {"coordinates":[4.833166,52.442715],"type":"Point"}
}