{
  "type": "Feature",
  "properties": {
    "addr:full":"Aquamarijnstraat 29 Leiden Zuid-Holland 2332 HE",
    "addr:housenumber":"29",
    "addr:postcode":"2332 he",
    "addr:street":"Aquamarijnstraat",
    "iso:country":"NL",
    "sg:address":"Aquamarijnstraat 29",
    "sg:city":"Leiden",
    "sg:orig_category":"Goederenvervoer Over De Weg",
    "sg:phone":"+31 71 572 0437",
    "sg:postcode":"2332 HE",
    "sg:province":"Zuid-Holland",
    "wof:name":"Pot Transport",
    "wof:placetype":"venue"
},
  "geometry": {"coordinates":[4.462697,52.152828],"type":"Point"}
}