{
  "type": "Feature",
  "properties": {
    "addr:full":"Orlandopassage 21 Kerkrade Limburg 6461 AM",
    "addr:housenumber":"21",
    "addr:postcode":"6461",
    "addr:street":"Orlandopassage",
    "iso:country":"NL",
    "sg:address":"Orlandopassage 21",
    "sg:city":"Kerkrade",
    "sg:orig_category":"Warenhuizen",
    "sg:phone":"+31 900 9800",
    "sg:postcode":"6461 AM",
    "sg:province":"Limburg",
    "wof:name":"Kijkshop",
    "wof:placetype":"venue"
},
  "geometry": {"coordinates":[6.0638852119,50.8656234741],"type":"Point"}
}