{
  "type": "Feature",
  "properties": {
    "addr:full":"De Vecht 44 Dronten Flevoland 8253 PH",
    "addr:housenumber":"44",
    "addr:postcode":"8253",
    "addr:street":"De Vecht;Flevoland",
    "iso:country":"NL",
    "sg:address":"De Vecht 44",
    "sg:city":"Dronten",
    "sg:orig_category":"Kunststoffen- Verwerkende Industrie",
    "sg:phone":"+31 321 316 425",
    "sg:postcode":"8253 PH",
    "sg:province":"Flevoland",
    "sg:website":"http://www.carbonprince.com",
    "wof:name":"Prince",
    "wof:placetype":"venue"
},
  "geometry": {"coordinates":[5.706436,52.541523],"type":"Point"}
}