{
  "type": "Feature",
  "properties": {
    "addr:full":"Binnenwg 14 Staphorst NL.08 7951 DE",
    "addr:housenumber":"14;nl.08 7951",
    "addr:postcode":"de",
    "addr:street":"Binnenwg",
    "iso:country":"NL",
    "sg:address":"Binnenwg 14",
    "sg:city":"Staphorst",
    "sg:orig_category":"Artsen - Huisartsen",
    "sg:phone":"+31 522 461 223",
    "sg:postcode":"7951 DE",
    "sg:province":"NL.08",
    "wof:name":"Steendijk, C B",
    "wof:placetype":"venue"
},
  "geometry": {"coordinates":[6.2076,52.642406],"type":"Point"}
}