{
  "type": "Feature",
  "properties": {
    "addr:full":"Stationsstraat 17 Waalwijk Noord-Brabant 5141 GB",
    "addr:housenumber":"17",
    "addr:postcode":"5141 gb",
    "addr:street":"Stationsstraat",
    "iso:country":"NL",
    "sg:address":"Stationsstraat 17",
    "sg:city":"Waalwijk",
    "sg:classifiers":[
        {
            "category":"Shopping",
            "subcategory":"Clothing, Apparel, & Fashions",
            "type":"Retail Goods"
        }
    ],
    "sg:phone":"+31 416 344 152",
    "sg:postcode":"5141 GB",
    "sg:province":"Noord-Brabant",
    "sg:tags":[
        "ondergoed",
        "lingerie"
    ],
    "wof:name":"Livera-Knip",
    "wof:placetype":"venue"
},
  "geometry": {"coordinates":[5.067036,51.6894],"type":"Point"}
}