{
  "type": "Feature",
  "properties": {
    "addr:full":"Overakkerstr 90 Breda North Brabant 4834 XN",
    "addr:housenumber":"90",
    "addr:postcode":"4834 xn",
    "addr:street":"Overakkerstr",
    "iso:country":"NL",
    "sg:address":"Overakkerstr 90",
    "sg:city":"Breda",
    "sg:orig_category":"Herenkleding - Groothandel",
    "sg:phone":"+31 76 560 7800",
    "sg:postcode":"4834 XN",
    "sg:province":"North Brabant",
    "wof:name":"Centaur Clothes Netherlands, Bv",
    "wof:placetype":"venue"
},
  "geometry": {"coordinates":[4.797797,51.570007],"type":"Point"}
}