{
  "type": "Feature",
  "properties": {
    "addr:full":"Achterbroek 21 Berkenwoude South Holland 2825 NC",
    "addr:housenumber":"21",
    "addr:postcode":"2825 nc",
    "addr:street":"Achterbroek",
    "iso:country":"NL",
    "sg:address":"Achterbroek 21",
    "sg:city":"Berkenwoude",
    "sg:orig_category":"Diverse Consumentenartikelen Gh",
    "sg:phone":"+31 182 367 031",
    "sg:postcode":"2825 NC",
    "sg:province":"South Holland",
    "wof:name":"A Oosterom",
    "wof:placetype":"venue"
},
  "geometry": {"coordinates":[4.693291,51.961555],"type":"Point"}
}