{
  "type": "Feature",
  "properties": {
    "iso:country":"NL",
    "sg:address":"De Holle Poarte 10",
    "sg:city":"Makkum Fr",
    "sg:classifiers":[
        {
            "category":"Restaurant",
            "type":"Food & Drink"
        }
    ],
    "sg:phone":"+31 515 238 222",
    "sg:postcode":"8754 HC",
    "sg:province":"Friesland",
    "wof:name":"Vigilante, De",
    "wof:placetype":"venue"
},
  "geometry": {"coordinates":[5.380204,53.051346],"type":"Point"}
}