{
  "type": "Feature",
  "properties": {
    "iso:country":"NL",
    "sg:address":"Roelsplnts 6",
    "sg:city":"Wateringen",
    "sg:orig_category":"Adviesbureaus Bouwkunde",
    "sg:phone":"+31 174 290 101",
    "sg:postcode":"2291 RK",
    "sg:province":"Zuid-Holland",
    "wof:name":"Zuiderwijk Bv",
    "wof:placetype":"venue"
},
  "geometry": {"coordinates":[4.2735,52.023331],"type":"Point"}
}