{
  "type": "Feature",
  "properties": {
    "addr:full":"Westereiland 86 Medemblik North Holland 1671 HT",
    "addr:housenumber":"86",
    "addr:postcode":"1671 ht",
    "addr:street":"Westereiland",
    "iso:country":"NL",
    "sg:address":"Westereiland 86",
    "sg:city":"Medemblik",
    "sg:orig_category":"Adviesbureaus Bouwkunde",
    "sg:phone":"+31 227 543 843",
    "sg:postcode":"1671 HT",
    "sg:province":"North Holland",
    "wof:name":"Stabilo Bv",
    "wof:placetype":"venue"
},
  "geometry": {"coordinates":[5.104642,52.768955],"type":"Point"}
}