{
  "type": "Feature",
  "properties": {
    "addr:full":"Huis Te Veldeln 16 Maasland Zuid-Holland 3155 SE",
    "addr:housenumber":"16",
    "addr:postcode":"3155 se",
    "addr:street":"Huis Te Veldeln",
    "iso:country":"NL",
    "sg:address":"Huis Te Veldeln 16",
    "sg:city":"Maasland",
    "sg:orig_category":"Verenigingsgebouwen",
    "sg:phone":"+31 10 591 3060",
    "sg:postcode":"3155 SE",
    "sg:province":"Zuid-Holland",
    "wof:name":"Magneet, De",
    "wof:placetype":"venue"
},
  "geometry": {"coordinates":[4.269032,51.935089],"type":"Point"}
}