{
  "type": "Feature",
  "properties": {
    "addr:full":"D Stalpertstr 80 Amsterdam Noord-Holland 1072 XK",
    "addr:housenumber":"80",
    "addr:postcode":"1072 xk",
    "iso:country":"NL",
    "sg:address":"D Stalpertstr 80",
    "sg:city":"Amsterdam",
    "sg:orig_category":"Kappers",
    "sg:phone":"+31 20 664 7344",
    "sg:postcode":"1072 XK",
    "sg:province":"Noord-Holland",
    "wof:name":"Robbedoes",
    "wof:placetype":"venue"
},
  "geometry": {"coordinates":[4.891019,52.35603],"type":"Point"}
}