{
  "type": "Feature",
  "properties": {
    "addr:full":"Molenkap 6 St Nicolaasga Friesland 8521 MH",
    "addr:housenumber":"6",
    "addr:postcode":"8521 mh",
    "addr:street":"Molenkap",
    "iso:country":"NL",
    "sg:address":"Molenkap 6",
    "sg:city":"St Nicolaasga",
    "sg:orig_category":"Bloemisterijartikelen - Fabrieken En Groothandel",
    "sg:phone":"+31 513 431 829",
    "sg:postcode":"8521 MH",
    "sg:province":"Friesland",
    "wof:name":"Amennis Trading",
    "wof:placetype":"venue"
},
  "geometry": {"coordinates":[5.745342,52.917168],"type":"Point"}
}