{
  "type": "Feature",
  "properties": {
    "iso:country":"NL",
    "sg:address":"Provincialeweg Noord 41",
    "sg:city":"Almkerk",
    "sg:orig_category":"Glaszetten",
    "sg:phone":"+31 183 403 436",
    "sg:postcode":"4286 EB",
    "sg:province":"Noord-Brabant",
    "wof:name":"Van Der Wiel Glaszettersbedrijf",
    "wof:placetype":"venue"
},
  "geometry": {"coordinates":[4.946407,51.778633],"type":"Point"}
}