{
  "type": "Feature",
  "properties": {
    "addr:full":"V Bemmelln 19 Monster Zuid-Holland 2681 CZ",
    "addr:housenumber":"19",
    "addr:postcode":"2681",
    "iso:country":"NL",
    "sg:address":"V Bemmelln 19",
    "sg:city":"Monster",
    "sg:orig_category":"Kassenonderhoud",
    "sg:phone":"+31 174 212 135",
    "sg:postcode":"2681 CZ",
    "sg:province":"Zuid-Holland",
    "wof:name":"Hoogenboom En Zn Vof, J P",
    "wof:placetype":"venue"
},
  "geometry": {"coordinates":[15.47527,49.803791],"type":"Point"}
}