{
  "type": "Feature",
  "properties": {
    "iso:country":"NL",
    "sg:address":"De Bleek 3",
    "sg:city":"Denekamp",
    "sg:orig_category":"Accountants - Administratie- Consulenten En -Kantoren",
    "sg:phone":"+31 541 352 943",
    "sg:postcode":"7591 BX",
    "sg:province":"Overijssel",
    "wof:name":"Koehorst Vof",
    "wof:placetype":"venue"
},
  "geometry": {"coordinates":[7.011256,52.379063],"type":"Point"}
}