{
  "type": "Feature",
  "properties": {
    "iso:country":"NL",
    "sg:address":"Leidsewallen 6",
    "sg:city":"Zoetermeer",
    "sg:orig_category":"Waterbouwkundige Werken",
    "sg:phone":"+31 79 316 5314",
    "sg:postcode":"2712 BW",
    "sg:province":"Zuid-Holland",
    "sg:website":"http://www.qmetrix.nl",
    "wof:name":"Qmetrix Bv",
    "wof:placetype":"venue"
},
  "geometry": {"coordinates":[4.4964928627,52.0568008423],"type":"Point"}
}