{
  "type": "Feature",
  "properties": {
    "iso:country":"NL",
    "sg:address":"Hinde 11",
    "sg:city":"Huizen",
    "sg:orig_category":"Film-, Tv- And Videoproductie",
    "sg:phone":"+31 35 526 4046",
    "sg:postcode":"1273 GN",
    "sg:province":"North Holland",
    "wof:name":"Brussaard Productions Vof",
    "wof:placetype":"venue"
},
  "geometry": {"coordinates":[5.257137,52.299355],"type":"Point"}
}