{
  "type": "Feature",
  "properties": {
    "addr:full":"Oranjerie 127 Apeldoorn Gelderland 7311 WE",
    "addr:housenumber":"127",
    "addr:postcode":"7311",
    "addr:street":"Oranjerie;Gelderland;We",
    "iso:country":"NL",
    "sg:address":"Oranjerie 127",
    "sg:city":"Apeldoorn",
    "sg:orig_category":"Zoetwaren - Winkels",
    "sg:phone":"+31 55 521 9537",
    "sg:postcode":"7311 WE",
    "sg:province":"Gelderland",
    "wof:name":"Snoepexpress Vof",
    "wof:placetype":"venue"
},
  "geometry": {"coordinates":[5.9619,52.212875],"type":"Point"}
}