{
  "type": "Feature",
  "properties": {
    "addr:full":"N Mulderstr 2 Noordbroek Groningen 9635 CL",
    "addr:housenumber":"2",
    "addr:postcode":"9635",
    "addr:street":"N Mulderstr",
    "iso:country":"NL",
    "sg:address":"N Mulderstr 2",
    "sg:city":"Noordbroek",
    "sg:orig_category":"Bejaarden - Verzorgingstehuizen",
    "sg:phone":"+31 598 452 655",
    "sg:postcode":"9635 CL",
    "sg:province":"Groningen",
    "wof:name":"Gockingaheem",
    "wof:placetype":"venue"
},
  "geometry": {"coordinates":[6.87233,53.194469],"type":"Point"}
}