{
  "type": "Feature",
  "properties": {
    "iso:country":"NL",
    "sg:address":"Noordendk 707",
    "sg:city":"Dordrecht",
    "sg:orig_category":"Elektrotechnische Installatiebureaus",
    "sg:phone":"+31 78 614 3945",
    "sg:postcode":"3319 GK",
    "sg:province":"Zuid-Holland",
    "wof:name":"Ag Elektrotechniek",
    "wof:placetype":"venue"
},
  "geometry": {"coordinates":[4.706994,51.802559],"type":"Point"}
}