{
  "type": "Feature",
  "properties": {
    "addr:full":"Oostwal 175 Oss Noord-Brabant 5341 KM",
    "addr:housenumber":"175",
    "addr:postcode":"5341 km",
    "addr:street":"Oostwal",
    "iso:country":"NL",
    "sg:address":"Oostwal 175",
    "sg:city":"Oss",
    "sg:classifiers":[
        {
            "category":"Travel",
            "subcategory":"Hotels & Motels",
            "type":"Entertainment"
        }
    ],
    "sg:phone":"+31 412 694 646",
    "sg:postcode":"5341 KM",
    "sg:province":"Noord-Brabant",
    "wof:name":"Weverij, De",
    "wof:placetype":"venue"
},
  "geometry": {"coordinates":[-77.235214,38.312599],"type":"Point"}
}