{
  "type": "Feature",
  "properties": {
    "iso:country":"NL",
    "sg:address":"Avenue Concordia 136",
    "sg:city":"Rotterdam",
    "sg:orig_category":"Antiquiteiten",
    "sg:phone":"+31 10 413 8075",
    "sg:postcode":"3062 LP",
    "sg:province":"Zuid-Holland",
    "wof:name":"Nieuwe Giessen, Vd",
    "wof:placetype":"venue"
},
  "geometry": {"coordinates":[4.511896,51.920555],"type":"Point"}
}