{
  "type": "Feature",
  "properties": {
    "addr:full":"Leeuwendaallaan 67 Rijswijk Zh Zuid-Holland 2281 GL",
    "addr:housenumber":"67",
    "addr:postcode":"zh;2281 gl",
    "addr:street":"Leeuwendaallaan",
    "iso:country":"NL",
    "sg:address":"Leeuwendaallaan 67",
    "sg:city":"Rijswijk Zh",
    "sg:orig_category":"Fotostudio'S And Fotografen",
    "sg:phone":"+31 70 395 0668",
    "sg:postcode":"2281 GL",
    "sg:province":"Zuid-Holland",
    "wof:name":"Andre Van Den Bos Fotografie",
    "wof:placetype":"venue"
},
  "geometry": {"coordinates":[4.343951,52.055424],"type":"Point"}
}