{
  "type": "Feature",
  "properties": {
    "addr:full":"Industriestraat 3 Rijen Noord-Brabant 5121 LE",
    "addr:housenumber":"3",
    "addr:postcode":"5121 le",
    "addr:street":"Industriestraat",
    "iso:country":"NL",
    "sg:address":"Industriestraat 3",
    "sg:city":"Rijen",
    "sg:orig_category":"Diverse Bedrijfsinstallaties Gh",
    "sg:phone":"+31 161 224 722",
    "sg:postcode":"5121 LE",
    "sg:province":"Noord-Brabant",
    "wof:name":"D & L Packaging Bv",
    "wof:placetype":"venue"
},
  "geometry": {"coordinates":[4.927782,51.581501],"type":"Point"}
}