{
  "type": "Feature",
  "properties": {
    "addr:full":"Klooienbergln 273 Zwolle Overijssel 8031 GA",
    "addr:housenumber":"273",
    "addr:postcode":"8031 ga",
    "iso:country":"NL",
    "sg:address":"Klooienbergln 273",
    "sg:city":"Zwolle",
    "sg:orig_category":"Administratie- En Boekhoudkantoren",
    "sg:phone":"+31 38 423 7035",
    "sg:postcode":"8031 GA",
    "sg:province":"Overijssel",
    "wof:name":"Abv",
    "wof:placetype":"venue"
},
  "geometry": {"coordinates":[6.075927,52.526924],"type":"Point"}
}