{
  "type": "Feature",
  "properties": {
    "addr:full":"Oud Loosd Dk 285B , (Mobiele Tel) Loosdrecht Noord-Holland 1231 LZ",
    "addr:housenumber":"285b",
    "addr:postcode":"1231 lz",
    "addr:street":"Oud;Dk;Mobiele Tel",
    "iso:country":"NL",
    "sg:address":"Oud Loosd Dk 285B , (Mobiele Tel)",
    "sg:city":"Loosdrecht",
    "sg:orig_category":"Bloemen En Planten - Decoratie",
    "sg:phone":"+31 6 22235814",
    "sg:postcode":"1231 LZ",
    "sg:province":"Noord-Holland",
    "wof:name":"Fleuriche",
    "wof:placetype":"venue"
},
  "geometry": {"coordinates":[5.069778,52.206848],"type":"Point"}
}