{
  "type": "Feature",
  "properties": {
    "addr:full":"Paarlstr 51 Utrecht Utrecht 3581 VN",
    "addr:housenumber":"51",
    "addr:postcode":"3581 vn",
    "addr:street":"Paarlstr",
    "iso:country":"NL",
    "sg:address":"Paarlstr 51",
    "sg:city":"Utrecht",
    "sg:orig_category":"Journalisten Freelance",
    "sg:phone":"+31 30 251 5378",
    "sg:postcode":"3581 VN",
    "sg:province":"Utrecht",
    "wof:name":"Oosterman, M G",
    "wof:placetype":"venue"
},
  "geometry": {"coordinates":[5.136069,52.087673],"type":"Point"}
}