{
  "type": "Feature",
  "properties": {
    "addr:full":"Hoogstraat 9 Dokkum Provincie Friesland 9101 LH",
    "addr:housenumber":"9",
    "addr:postcode":"9101 lh",
    "addr:street":"Hoogstraat;Provincie Friesland",
    "iso:country":"NL",
    "sg:address":"Hoogstraat 9",
    "sg:city":"Dokkum",
    "sg:orig_category":"Juweliers",
    "sg:phone":"+31 519 293 266",
    "sg:postcode":"9101 LH",
    "sg:province":"Provincie Friesland",
    "wof:name":"Dick En Elly Piersma Juweliers",
    "wof:placetype":"venue"
},
  "geometry": {"coordinates":[5.997923,53.325424],"type":"Point"}
}