{
  "type": "Feature",
  "properties": {
    "iso:country":"NL",
    "sg:address":"Hoogstraat 9",
    "sg:city":"Dokkum",
    "sg:orig_category":"Juweliers",
    "sg:phone":"+31 519 293 266",
    "sg:postcode":"9101 LH",
    "sg:province":"Provincie Friesland",
    "wof:name":"Dick En Elly Piersma Juweliers",
    "wof:placetype":"venue"
},
  "geometry": {"coordinates":[5.997923,53.325424],"type":"Point"}
}