{
  "type": "Feature",
  "properties": {
    "addr:full":"M Nyhoffstr 13 Gorinchem South Holland 4207 RP",
    "addr:housenumber":"13",
    "addr:postcode":"4207 rp",
    "iso:country":"NL",
    "sg:address":"M Nyhoffstr 13",
    "sg:city":"Gorinchem",
    "sg:orig_category":"Geluidsinstallaties - Verhuur",
    "sg:phone":"+31 183 629 437",
    "sg:postcode":"4207 RP",
    "sg:province":"South Holland",
    "sg:website":"http://www.soundco.nl",
    "wof:name":"Soundco",
    "wof:placetype":"venue"
},
  "geometry": {"coordinates":[4.969185,51.830631],"type":"Point"}
}