{
  "type": "Feature",
  "properties": {
    "iso:country":"NL",
    "sg:address":"Smaragdpln 226",
    "sg:city":"Utrecht",
    "sg:orig_category":"Kaas",
    "sg:phone":"+31 30 289 1002",
    "sg:postcode":"3523 EH",
    "sg:province":"Utrecht",
    "wof:name":"Besten, Den",
    "wof:placetype":"venue"
},
  "geometry": {"coordinates":[5.1258502007,52.0727081299],"type":"Point"}
}