{
  "type": "Feature",
  "properties": {
    "iso:country":"NL",
    "sg:address":"Laan 15",
    "sg:city":"Nunspeet",
    "sg:classifiers":[
        {
            "category":"Retail",
            "subcategory":"Photofinishing",
            "type":"Services"
        }
    ],
    "sg:phone":"+31 341 252 427",
    "sg:postcode":"8071 JG",
    "sg:province":"Gelderland",
    "sg:tags":[
        "foto",
        "film"
    ],
    "wof:name":"Firma Foto-Video Groeneveld",
    "wof:placetype":"venue"
},
  "geometry": {"coordinates":[5.78645,52.377518],"type":"Point"}
}