{
  "type": "Feature",
  "properties": {
    "addr:full":"P Ryckenstr 1 Arnhem Gelderland 6814 DK",
    "addr:housenumber":"1",
    "addr:postcode":"6814 dk",
    "addr:street":"P Ryckenstr",
    "iso:country":"NL",
    "sg:address":"P Ryckenstr 1",
    "sg:city":"Arnhem",
    "sg:orig_category":"Ministeries En Overheidsinstellingen",
    "sg:phone":"+31 26 352 8200",
    "sg:postcode":"6814 DK",
    "sg:province":"Gelderland",
    "wof:name":"Rijkskantorengebouw",
    "wof:placetype":"venue"
},
  "geometry": {"coordinates":[5.8987002373,51.9867362976],"type":"Point"}
}