{
  "type": "Feature",
  "properties": {
    "addr:full":"Tellerswg 6 Kerkwerve Zeeland 4321 TW",
    "addr:housenumber":"6",
    "addr:postcode":"4321 tw",
    "addr:street":"Tellerswg",
    "iso:country":"NL",
    "sg:address":"Tellerswg 6",
    "sg:city":"Kerkwerve",
    "sg:orig_category":"Administratie- En Boekhoudkantoren",
    "sg:phone":"+31 111 671 382",
    "sg:postcode":"4321 TW",
    "sg:province":"Zeeland",
    "wof:name":"Elvadi",
    "wof:placetype":"venue"
},
  "geometry": {"coordinates":[3.867451,51.685062],"type":"Point"}
}