{
  "type": "Feature",
  "properties": {
    "iso:country":"NL",
    "sg:address":"Diependaalselaan 337",
    "sg:city":"Hilversum",
    "sg:orig_category":"Bejaardeninstellingen And Serviceflats",
    "sg:phone":"+31 35 624 0458",
    "sg:postcode":"1215 KG",
    "sg:province":"Noord-Holland",
    "wof:name":"Stichting Prot Christelijk Zorgcentrum Zuiderheide",
    "wof:placetype":"venue"
},
  "geometry": {"coordinates":[5.159067,52.211765],"type":"Point"}
}