{
  "type": "Feature",
  "properties": {
    "iso:country":"NL",
    "sg:address":"Boekhorststraat 86",
    "sg:city":"'S Gravenhage",
    "sg:orig_category":"Kappers",
    "sg:phone":"+31 70 345 4902",
    "sg:postcode":"2512 CT",
    "sg:province":"Zuid-Holland",
    "wof:name":"Kapsalon Shampoo",
    "wof:placetype":"venue"
},
  "geometry": {"coordinates":[4.310901165,52.0728683472],"type":"Point"}
}