{
  "type": "Feature",
  "properties": {
    "addr:full":"Potskamp 5 Weerselo NL.08 7595 BG",
    "addr:housenumber":"5;nl.08",
    "addr:postcode":"7595",
    "addr:street":"Potskamp",
    "iso:country":"NL",
    "sg:address":"Potskamp 5",
    "sg:city":"Weerselo",
    "sg:orig_category":"Schilderwerk",
    "sg:phone":"+31 541 662 597",
    "sg:postcode":"7595 BG",
    "sg:province":"NL.08",
    "wof:name":"Asbe Bv",
    "wof:placetype":"venue"
},
  "geometry": {"coordinates":[6.861627,52.351002],"type":"Point"}
}