{
  "type": "Feature",
  "properties": {
    "addr:full":"K R Poststraat 91-3 Heerenveen Friesland 8441 EN",
    "addr:housenumber":"91-3",
    "addr:postcode":"8441 en",
    "addr:street":"K R Poststraat",
    "iso:country":"NL",
    "sg:address":"K R Poststraat 91-3",
    "sg:city":"Heerenveen",
    "sg:orig_category":"Adviesbureaus Bedrijfsorganisatie",
    "sg:phone":"+31 513 656 177",
    "sg:postcode":"8441 EN",
    "sg:province":"Friesland",
    "sg:website":"http://www.bwinterim.nl",
    "wof:name":"Beljon + Westerterp Interim Bv",
    "wof:placetype":"venue"
},
  "geometry": {"coordinates":[5.92727,52.963699],"type":"Point"}
}