{
  "type": "Feature",
  "properties": {
    "addr:full":"Graanwg 8 Moerdyk North Brabant 4782 PP",
    "addr:housenumber":"8",
    "addr:postcode":"4782 pp",
    "addr:street":"Graanwg",
    "iso:country":"NL",
    "sg:address":"Graanwg 8",
    "sg:city":"Moerdyk",
    "sg:orig_category":"Banden - Fabrieken En Groothandel",
    "sg:phone":"+31 168 380 777",
    "sg:postcode":"4782 PP",
    "sg:province":"North Brabant",
    "wof:name":"Itb",
    "wof:placetype":"venue"
},
  "geometry": {"coordinates":[4.605778,51.684048],"type":"Point"}
}