{
  "type": "Feature",
  "properties": {
    "addr:full":"De Clercqstraat 104 Amsterdam Noord-Holland 1052 NM",
    "addr:housenumber":"104",
    "addr:postcode":"1052",
    "addr:street":"De Clercqstraat",
    "iso:country":"NL",
    "sg:address":"De Clercqstraat 104",
    "sg:city":"Amsterdam",
    "sg:orig_category":"Kappers",
    "sg:phone":"+31 20 618 0216",
    "sg:postcode":"1052 NM",
    "sg:province":"Noord-Holland",
    "wof:name":"Marnick Kappers",
    "wof:placetype":"venue"
},
  "geometry": {"coordinates":[4.866654,52.370304],"type":"Point"}
}