{
  "type": "Feature",
  "properties": {
    "iso:country":"NL",
    "sg:address":"De Clercqstraat 104",
    "sg:city":"Amsterdam",
    "sg:orig_category":"Kappers",
    "sg:phone":"+31 20 618 0216",
    "sg:postcode":"1052 NM",
    "sg:province":"Noord-Holland",
    "wof:name":"Marnick Kappers",
    "wof:placetype":"venue"
},
  "geometry": {"coordinates":[4.866654,52.370304],"type":"Point"}
}