{
  "type": "Feature",
  "properties": {
    "addr:full":"Grevelingenstraat 4 Zierikzee Zeeland 4301 XX",
    "addr:housenumber":"4",
    "addr:postcode":"4301 xx",
    "addr:street":"Grevelingenstraat",
    "iso:country":"NL",
    "sg:address":"Grevelingenstraat 4",
    "sg:city":"Zierikzee",
    "sg:classifiers":[
        {
            "category":"Fast Food",
            "type":"Food & Drink"
        }
    ],
    "sg:phone":"+31 111 416 704",
    "sg:postcode":"4301 XX",
    "sg:province":"Zeeland",
    "sg:tags":[
        "afhaal",
        "restaurant"
    ],
    "wof:name":"Frituur Plan West",
    "wof:placetype":"venue"
},
  "geometry": {"coordinates":[3.906525,51.648521],"type":"Point"}
}