{
  "type": "Feature",
  "properties": {
    "addr:full":"Wijngaardstraat 3 Herkenbosch Limburg 6075 NC",
    "addr:housenumber":"3",
    "addr:postcode":"6075 nc",
    "addr:street":"Wijngaardstraat",
    "iso:country":"NL",
    "sg:address":"Wijngaardstraat 3",
    "sg:city":"Herkenbosch",
    "sg:orig_category":"Overheidsdiensten",
    "sg:phone":"+31 475 533 813",
    "sg:postcode":"6075 NC",
    "sg:province":"Limburg",
    "wof:name":"Beatrix",
    "wof:placetype":"venue"
},
  "geometry": {"coordinates":[6.0597009659,51.1625022888],"type":"Point"}
}