{
  "type": "Feature",
  "properties": {
    "addr:full":"Utrechtsestraat 81 Amsterdam North Holland 1017 VJ",
    "addr:housenumber":"81",
    "addr:postcode":"1017 vj",
    "addr:street":"Utrechtsestraat",
    "iso:country":"NL",
    "sg:address":"Utrechtsestraat 81",
    "sg:city":"Amsterdam",
    "sg:orig_category":"Meubelzaken, Woning- And Keukeninrichting",
    "sg:phone":"+31 20 624 2940",
    "sg:postcode":"1017 VJ",
    "sg:province":"North Holland",
    "sg:website":"http://www.formainterieurs.nl",
    "wof:name":"Forma Interieurs",
    "wof:placetype":"venue"
},
  "geometry": {"coordinates":[4.89875,52.363209],"type":"Point"}
}