{
  "type": "Feature",
  "properties": {
    "addr:full":"Mauvezand 1A Laren Nh Noord-Holland 1251 JC",
    "addr:housenumber":"1a",
    "addr:postcode":"1251 jc",
    "addr:street":"Mauvezand",
    "iso:country":"NL",
    "sg:address":"Mauvezand 1A",
    "sg:city":"Laren Nh",
    "sg:orig_category":"Kinderkleding",
    "sg:phone":"+31 35 538 0889",
    "sg:postcode":"1251 JC",
    "sg:province":"Noord-Holland",
    "wof:name":"Snuffel",
    "wof:placetype":"venue"
},
  "geometry": {"coordinates":[5.228251,52.259659],"type":"Point"}
}