{
  "type": "Feature",
  "properties": {
    "addr:full":"Waldorpstr 228 S Gravenhage South Holland 2521 CE",
    "addr:housenumber":"228",
    "addr:postcode":"2521 ce",
    "addr:street":"S Gravenhage",
    "iso:country":"NL",
    "sg:address":"Waldorpstr 228",
    "sg:city":"S Gravenhage",
    "sg:orig_category":"Meubelen Gebruikte",
    "sg:phone":"+31 70 388 9158",
    "sg:postcode":"2521 CE",
    "sg:province":"South Holland",
    "wof:name":"Zitten Etc",
    "wof:placetype":"venue"
},
  "geometry": {"coordinates":[4.32071,52.062988],"type":"Point"}
}