{
  "type": "Feature",
  "properties": {
    "addr:full":"Bonistr 31 S Gravenhage South Holland 2585 SZ",
    "addr:housenumber":"31",
    "addr:postcode":"2585 sz",
    "addr:street":"Bonistr;S Gravenhage",
    "iso:country":"NL",
    "sg:address":"Bonistr 31",
    "sg:city":"S Gravenhage",
    "sg:orig_category":"Fietsen En Bromfietsen",
    "sg:phone":"+31 70 355 0428",
    "sg:postcode":"2585 SZ",
    "sg:province":"South Holland",
    "wof:name":"Borgmeijer, P",
    "wof:placetype":"venue"
},
  "geometry": {"coordinates":[4.29777,52.094799],"type":"Point"}
}