{
  "type": "Feature",
  "properties": {
    "iso:country":"NL",
    "sg:address":"Hengelosestr 172",
    "sg:city":"Enschede",
    "sg:classifiers":[
        {
            "category":"Food & Beverages",
            "subcategory":"Bakery",
            "type":"Retail Goods"
        }
    ],
    "sg:phone":"+31 53 433 8855",
    "sg:postcode":"7521 AK",
    "sg:province":"Overijssel",
    "sg:tags":[
        "pizza"
    ],
    "wof:name":"Antonio, Pizzeria",
    "wof:placetype":"venue"
},
  "geometry": {"coordinates":[6.8788490295,52.2271766663],"type":"Point"}
}