{
  "type": "Feature",
  "properties": {
    "addr:full":"Schuttevaerwg 130 Rotterdam South Holland 3044 BB",
    "addr:housenumber":"130",
    "addr:postcode":"3044 bb",
    "iso:country":"NL",
    "sg:address":"Schuttevaerwg 130",
    "sg:city":"Rotterdam",
    "sg:classifiers":[
        {
            "category":"Professional",
            "subcategory":"Accounting & Tax Preparation",
            "type":"Services"
        }
    ],
    "sg:phone":"+31 10 437 3008",
    "sg:postcode":"3044 BB",
    "sg:province":"South Holland",
    "sg:tags":[
        "accountant",
        "en",
        "-kantoren",
        "register-"
    ],
    "wof:name":"Marseille Bax",
    "wof:placetype":"venue"
},
  "geometry": {"coordinates":[4.423307,51.921989],"type":"Point"}
}