{
  "type": "Feature",
  "properties": {
    "iso:country":"NL",
    "sg:address":"Vatternkade 91",
    "sg:city":"Amsterdam",
    "sg:orig_category":"Juridische Dienstverlening",
    "sg:phone":"+31 20 615 9294",
    "sg:postcode":"1060 PK",
    "sg:province":"Noord-Holland",
    "wof:name":"Interjuris",
    "wof:placetype":"venue"
},
  "geometry": {"coordinates":[4.782854,52.348946],"type":"Point"}
}