{
  "type": "Feature",
  "properties": {
    "addr:full":"Leenkamp 10 Leidschendam Zuid-Holland 2264 KX",
    "addr:housenumber":"10",
    "addr:postcode":"2264 kx",
    "addr:street":"Leenkamp",
    "iso:country":"NL",
    "sg:address":"Leenkamp 10",
    "sg:city":"Leidschendam",
    "sg:orig_category":"Vertalers",
    "sg:phone":"+31 70 320 2131",
    "sg:postcode":"2264 KX",
    "sg:province":"Zuid-Holland",
    "wof:name":"Dolfing-Overgaauw, O",
    "wof:placetype":"venue"
},
  "geometry": {"coordinates":[4.403007,52.091717],"type":"Point"}
}