{
  "type": "Feature",
  "properties": {
    "iso:country":"NL",
    "sg:address":"Kerkwyk 44A",
    "sg:city":"Berlicum Nb",
    "sg:orig_category":"Filmstudio'S En -Productie",
    "sg:phone":"+31 73 503 1500",
    "sg:postcode":"5258 KC",
    "sg:province":"Noord-Brabant",
    "sg:website":"http://www.mbgroup.nl",
    "wof:name":"Mb Group",
    "wof:placetype":"venue"
},
  "geometry": {"coordinates":[5.418169,51.663883],"type":"Point"}
}