{
  "type": "Feature",
  "properties": {
    "iso:country":"NL",
    "sg:address":"Stadhouderslaan 48",
    "sg:city":"Vlaardingen",
    "sg:orig_category":"Partycatering And -Organisatie",
    "sg:phone":"+31 10 249 9117",
    "sg:postcode":"3136 BN",
    "sg:province":"South Holland",
    "wof:name":"La Cafetiere",
    "wof:placetype":"venue"
},
  "geometry": {"coordinates":[4.347207,51.925648],"type":"Point"}
}