{
  "type": "Feature",
  "properties": {
    "addr:full":"Castersedijk 25A Hapert Noord-Brabant 5527 JR",
    "addr:housenumber":"25a",
    "addr:postcode":"5527 jr",
    "addr:street":"Castersedijk",
    "iso:country":"NL",
    "sg:address":"Castersedijk 25A",
    "sg:city":"Hapert",
    "sg:orig_category":"Overheidsdiensten",
    "sg:phone":"+31 497 381 217",
    "sg:postcode":"5527 JR",
    "sg:province":"Noord-Brabant",
    "wof:name":"Waterschap De Dommel",
    "wof:placetype":"venue"
},
  "geometry": {"coordinates":[5.2399449348,51.3812561035],"type":"Point"}
}