{
  "type": "Feature",
  "properties": {
    "addr:full":"Valentynstr 18 Tilburg Noord-Brabant 5014 KG",
    "addr:housenumber":"18",
    "addr:postcode":"5014 kg",
    "addr:street":"Valentynstr",
    "iso:country":"NL",
    "sg:address":"Valentynstr 18",
    "sg:city":"Tilburg",
    "sg:orig_category":"Cafetaria'S",
    "sg:phone":"+31 13 543 4443",
    "sg:postcode":"5014 KG",
    "sg:province":"Noord-Brabant",
    "wof:name":"Graafmans Bv",
    "wof:placetype":"venue"
},
  "geometry": {"coordinates":[5.096572,51.569084],"type":"Point"}
}