{
  "type": "Feature",
  "properties": {
    "addr:full":"Heksenkring 10 Breda North Brabant 4823 JS",
    "addr:housenumber":"10",
    "addr:postcode":"4823 js",
    "addr:street":"Heksenkring",
    "iso:country":"NL",
    "sg:address":"Heksenkring 10",
    "sg:city":"Breda",
    "sg:orig_category":"Fitnesscentra",
    "sg:phone":"+31 76 541 1552",
    "sg:postcode":"4823 JS",
    "sg:province":"North Brabant",
    "wof:name":"Tacoyo",
    "wof:placetype":"venue"
},
  "geometry": {"coordinates":[4.742454,51.62405],"type":"Point"}
}