{
  "type": "Feature",
  "properties": {
    "addr:full":"Bergweg 3 Velp Gld Gelderland 6881 LL",
    "addr:housenumber":"3",
    "addr:postcode":"6881 ll",
    "addr:street":"Bergweg;Gld Gelderland",
    "iso:country":"NL",
    "sg:address":"Bergweg 3",
    "sg:city":"Velp Gld",
    "sg:orig_category":"Loodgieterswerk, Verwarming And Sanitaire Installaties",
    "sg:phone":"+31 26 361 9430",
    "sg:postcode":"6881 LL",
    "sg:province":"Gelderland",
    "wof:name":"Van Geldere Klussenbedrijf",
    "wof:placetype":"venue"
},
  "geometry": {"coordinates":[5.968722,51.997025],"type":"Point"}
}