{
  "type": "Feature",
  "properties": {
    "addr:full":"Kortenaerlaan 36 Baarn Utrecht 3742 MC",
    "addr:housenumber":"36",
    "addr:postcode":"3742 mc",
    "addr:street":"Kortenaerlaan",
    "iso:country":"NL",
    "sg:address":"Kortenaerlaan 36",
    "sg:city":"Baarn",
    "sg:orig_category":"Boekhouders",
    "sg:phone":"+31 35 542 6490",
    "sg:postcode":"3742 MC",
    "sg:province":"Utrecht",
    "wof:name":"Administratiekantoor E.M. Nijholt",
    "wof:placetype":"venue"
},
  "geometry": {"coordinates":[5.304305,52.214165],"type":"Point"}
}