{
  "type": "Feature",
  "properties": {
    "addr:full":"Stevensbloem 37 Leiden Zuid-Holland 2331 JA",
    "addr:housenumber":"37",
    "addr:postcode":"2331 ja",
    "addr:street":"Stevensbloem",
    "iso:country":"NL",
    "sg:address":"Stevensbloem 37",
    "sg:city":"Leiden",
    "sg:orig_category":"Fietsen En Bromfietsen",
    "sg:phone":"+31 71 531 6654",
    "sg:postcode":"2331 JA",
    "sg:province":"Zuid-Holland",
    "wof:name":"Hulst, Fietsen Van",
    "wof:placetype":"venue"
},
  "geometry": {"coordinates":[4.454292,52.151249],"type":"Point"}
}