{
  "type": "Feature",
  "properties": {
    "iso:country":"NL",
    "sg:address":"Lelystraat 94",
    "sg:city":"Sliedrecht",
    "sg:orig_category":"Schilderwerk",
    "sg:phone":"+31 184 421 950",
    "sg:postcode":"3364 AJ",
    "sg:province":"Zuid-Holland",
    "wof:name":"Ploegaert Objectspuitbedrijf Bv",
    "wof:placetype":"venue"
},
  "geometry": {"coordinates":[4.766339,51.830475],"type":"Point"}
}