{
  "type": "Feature",
  "properties": {
    "addr:full":"Kronerweg 11 Maarn Utrecht 3951 BP",
    "addr:housenumber":"11",
    "addr:postcode":"3951 bp",
    "addr:street":"Kronerweg",
    "iso:country":"NL",
    "sg:address":"Kronerweg 11",
    "sg:city":"Maarn",
    "sg:orig_category":"Juridische Dienstverlening",
    "sg:phone":"+31 343 442 338",
    "sg:postcode":"3951 BP",
    "sg:province":"Utrecht",
    "wof:name":"Juridisch Adviesbureau Mr. C.Z. Tiesinga-Aardoom",
    "wof:placetype":"venue"
},
  "geometry": {"coordinates":[5.365865,52.066559],"type":"Point"}
}