{
  "type": "Feature",
  "properties": {
    "addr:full":"Nyverheidswg 23 Grootebroek Noord-Holland 1613 DZ",
    "addr:housenumber":"23",
    "addr:postcode":"1613 dz",
    "addr:street":"Nyverheidswg",
    "iso:country":"NL",
    "sg:address":"Nyverheidswg 23",
    "sg:city":"Grootebroek",
    "sg:orig_category":"Babyartikelen",
    "sg:phone":"+31 228 514 048",
    "sg:postcode":"1613 DZ",
    "sg:province":"Noord-Holland",
    "sg:website":"http://www.snowis.nl",
    "wof:name":"Snowis",
    "wof:placetype":"venue"
},
  "geometry": {"coordinates":[5.224552,52.693157],"type":"Point"}
}