{
  "type": "Feature",
  "properties": {
    "addr:full":"G Bildersstr 8 Deurne Noord-Brabant 5753 DE",
    "addr:housenumber":"8",
    "addr:postcode":"5753 de",
    "iso:country":"NL",
    "sg:address":"G Bildersstr 8",
    "sg:city":"Deurne",
    "sg:orig_category":"Accountants - Administratie- Consulenten En -Kantoren",
    "sg:phone":"+31 493 691 814",
    "sg:postcode":"5753 DE",
    "sg:province":"Noord-Brabant",
    "wof:name":"Brood En Van Ewijk",
    "wof:placetype":"venue"
},
  "geometry": {"coordinates":[5.79352,51.453522],"type":"Point"}
}