{
  "type": "Feature",
  "properties": {
    "addr:full":"Gravenstr 19 Amsterdam Noord-Holland 1012 NL",
    "addr:housenumber":"19",
    "addr:postcode":"1012 nl",
    "addr:street":"Gravenstr",
    "iso:country":"NL",
    "sg:address":"Gravenstr 19",
    "sg:city":"Amsterdam",
    "sg:orig_category":"Handwerkartikelen",
    "sg:phone":"+31 20 330 1077",
    "sg:postcode":"1012 NL",
    "sg:province":"Noord-Holland",
    "wof:name":"Pink",
    "wof:placetype":"venue"
},
  "geometry": {"coordinates":[4.891467,52.374062],"type":"Point"}
}