{
  "type": "Feature",
  "properties": {
    "addr:full":"Postbus 24203 Rotterdam Zuid-Holland 3007 DE",
    "addr:housenumber":"24203",
    "addr:postcode":"3007 de",
    "addr:street":"Postbus",
    "iso:country":"NL",
    "sg:address":"Postbus 24203",
    "sg:city":"Rotterdam",
    "sg:orig_category":"Adviesbureaus Scheepsbouwkunde",
    "sg:phone":"+31 6 53109089",
    "sg:postcode":"3007 DE",
    "sg:province":"Zuid-Holland",
    "wof:name":"Dijke, M W Van",
    "wof:placetype":"venue"
},
  "geometry": {"coordinates":[4.47075,51.922619],"type":"Point"}
}