{
  "type": "Feature",
  "properties": {
    "addr:full":"Puutbeek 35 Zwolle NL.08 8033 AA",
    "addr:housenumber":"35",
    "addr:postcode":"8033 aa",
    "addr:street":"Puutbeek",
    "iso:country":"NL",
    "sg:address":"Puutbeek 35",
    "sg:city":"Zwolle",
    "sg:orig_category":"Autorijscholen",
    "sg:phone":"+31 38 453 4250",
    "sg:postcode":"8033 AA",
    "sg:province":"NL.08",
    "wof:name":"Postuma",
    "wof:placetype":"venue"
},
  "geometry": {"coordinates":[6.109182,52.531841],"type":"Point"}
}