{
  "type": "Feature",
  "properties": {
    "addr:full":"Zuideinde 5 Aarlanderveen Zuid-Holland 2445 AS",
    "addr:housenumber":"5",
    "addr:postcode":"2445 as",
    "addr:street":"Zuideinde",
    "iso:country":"NL",
    "sg:address":"Zuideinde 5",
    "sg:city":"Aarlanderveen",
    "sg:orig_category":"Verzekeringen",
    "sg:phone":"+31 172 575 032",
    "sg:postcode":"2445 AS",
    "sg:province":"Zuid-Holland",
    "wof:name":"A.B. De Bruin-Jaspers",
    "wof:placetype":"venue"
},
  "geometry": {"coordinates":[4.73146,52.137703],"type":"Point"}
}