{
  "type": "Feature",
  "properties": {
    "addr:full":"Molenas 13 Etten-Leur Noord-Brabant 4873 HL",
    "addr:housenumber":"13",
    "addr:postcode":"4873 hl",
    "addr:street":"Molenas",
    "iso:country":"NL",
    "sg:address":"Molenas 13",
    "sg:city":"Etten-Leur",
    "sg:orig_category":"Verhuur Diversen",
    "sg:phone":"+31 76 502 1143",
    "sg:postcode":"4873 HL",
    "sg:province":"Noord-Brabant",
    "wof:name":"Gijsi",
    "wof:placetype":"venue"
},
  "geometry": {"coordinates":[4.649542,51.559307],"type":"Point"}
}