{
  "type": "Feature",
  "properties": {
    "addr:full":"Rozengaard 1220 Lelystad NL. 8212 DD",
    "addr:postcode":"1220;8212 dd",
    "addr:street":"Rozengaard;Nl.",
    "iso:country":"NL",
    "sg:address":"Rozengaard 1220",
    "sg:city":"Lelystad",
    "sg:orig_category":"Webdesign Bureaus",
    "sg:phone":"+31 320 268 219",
    "sg:postcode":"8212 DD",
    "sg:province":"NL.",
    "sg:website":"http://www.anshi-design.nl",
    "wof:name":"Anshi Design",
    "wof:placetype":"venue"
},
  "geometry": {"coordinates":[5.5044298172,52.5093803406],"type":"Point"}
}