{
  "type": "Feature",
  "properties": {
    "iso:country":"NL",
    "sg:address":"Kooikersplaats 35",
    "sg:city":"Apeldoorn",
    "sg:orig_category":"Verenigingen En Stichtingen",
    "sg:phone":"+31 55 541 6865",
    "sg:postcode":"7328 AX",
    "sg:province":"Gelderland",
    "sg:website":"http://www.bovdematen.nl",
    "wof:name":"Bov De Maten",
    "wof:placetype":"venue"
},
  "geometry": {"coordinates":[5.985319,52.197327],"type":"Point"}
}