{
  "type": "Feature",
  "properties": {
    "addr:full":"Schotdeuren 27 Gorinchem Zuid-Holland 4205 PC",
    "addr:housenumber":"27",
    "addr:postcode":"4205 pc",
    "addr:street":"Schotdeuren",
    "iso:country":"NL",
    "sg:address":"Schotdeuren 27",
    "sg:city":"Gorinchem",
    "sg:orig_category":"Autorijscholen",
    "sg:phone":"+31 183 625 773",
    "sg:postcode":"4205 PC",
    "sg:province":"Zuid-Holland",
    "wof:name":"Asmus Autorijschool, R D E",
    "wof:placetype":"venue"
},
  "geometry": {"coordinates":[4.962678,51.842487],"type":"Point"}
}