{
  "type": "Feature",
  "properties": {
    "addr:full":"Nyverheidswg 1 Barneveld Gelderland 3771 ME",
    "addr:housenumber":"1",
    "addr:postcode":"3771 me",
    "addr:street":"Nyverheidswg;Gelderland",
    "iso:country":"NL",
    "sg:address":"Nyverheidswg 1",
    "sg:city":"Barneveld",
    "sg:orig_category":"Keukens",
    "sg:phone":"+31 342 413 318",
    "sg:postcode":"3771 ME",
    "sg:province":"Gelderland",
    "sg:website":"http://www.demulderij.nl",
    "wof:name":"Mulderij, De",
    "wof:placetype":"venue"
},
  "geometry": {"coordinates":[5.588843,52.141216],"type":"Point"}
}