{
  "type": "Feature",
  "properties": {
    "iso:country":"NL",
    "sg:address":"Veldlaan 20",
    "sg:city":"Boskoop",
    "sg:orig_category":"Schilderwerk",
    "sg:phone":"+31 172 214 836",
    "sg:postcode":"2771 LX",
    "sg:province":"Zuid-Holland",
    "wof:name":"Schildersbedrijf J M Straver",
    "wof:placetype":"venue"
},
  "geometry": {"coordinates":[4.641978,52.073757],"type":"Point"}
}