{
  "type": "Feature",
  "properties": {
    "iso:country":"NL",
    "sg:address":"Kuiperbergweg 14B",
    "sg:city":"Amsterdam Zuidoost",
    "sg:orig_category":"Drukkerijen And Copyshops",
    "sg:phone":"+31 20 691 1331",
    "sg:postcode":"1101 AG",
    "sg:province":"Noord-Holland",
    "wof:name":"Refero Textiel & Bedrukking",
    "wof:placetype":"venue"
},
  "geometry": {"coordinates":[4.937768,52.302601],"type":"Point"}
}