{
  "type": "Feature",
  "properties": {
    "addr:full":"Laan Van Meerdervoort 341 'S Gravenhage South Holland 2563 AN",
    "addr:housenumber":"341 '",
    "addr:postcode":"2563 an",
    "addr:street":"Laan Van Meerdervoort",
    "iso:country":"NL",
    "sg:address":"Laan Van Meerdervoort 341",
    "sg:city":"'S Gravenhage",
    "sg:orig_category":"Fitnesscentra",
    "sg:phone":"+31 70 360 2288",
    "sg:postcode":"2563 AN",
    "sg:province":"South Holland",
    "wof:name":"Ontspanningscentr W F Fraufelder",
    "wof:placetype":"venue"
},
  "geometry": {"coordinates":[4.274624,52.078018],"type":"Point"}
}