{
  "type": "Feature",
  "properties": {
    "addr:full":"Mgr Vranckenstr 20 Sittard Limburg 6131 AD",
    "addr:housenumber":"20",
    "addr:postcode":"6131 ad",
    "addr:street":"Vranckenstr",
    "iso:country":"NL",
    "sg:address":"Mgr Vranckenstr 20",
    "sg:city":"Sittard",
    "sg:orig_category":"Keukens",
    "sg:phone":"+31 46 411 1650",
    "sg:postcode":"6131 AD",
    "sg:province":"Limburg",
    "wof:name":"Kellerhuis",
    "wof:placetype":"venue"
},
  "geometry": {"coordinates":[5.8678,50.996353],"type":"Point"}
}