{
  "type": "Feature",
  "properties": {
    "addr:full":"Gerard Burgerlaan 16 Vlaardingen South Holland 3131 KZ",
    "addr:housenumber":"16",
    "addr:postcode":"3131 kz",
    "addr:street":"Gerard Burgerlaan",
    "iso:country":"NL",
    "sg:address":"Gerard Burgerlaan 16",
    "sg:city":"Vlaardingen",
    "sg:orig_category":"Meubelzaken, Woning- And Keukeninrichting",
    "sg:phone":"+31 10 234 0508",
    "sg:postcode":"3131 KZ",
    "sg:province":"South Holland",
    "wof:name":"Beddenspeciaalzaak Rose Slaapcomfort",
    "wof:placetype":"venue"
},
  "geometry": {"coordinates":[4.336709,51.916927],"type":"Point"}
}