{
  "type": "Feature",
  "properties": {
    "addr:full":"Oranjegracht 24 Leiden South Holland 2312 SJ",
    "addr:housenumber":"24",
    "addr:postcode":"2312",
    "addr:street":"Oranjegracht",
    "iso:country":"NL",
    "sg:address":"Oranjegracht 24",
    "sg:city":"Leiden",
    "sg:orig_category":"Wegen And Sportterreinen",
    "sg:phone":"+31 71 513 3582",
    "sg:postcode":"2312 SJ",
    "sg:province":"South Holland",
    "wof:name":"W.F. Van Putten Bestratingen Bv",
    "wof:placetype":"venue"
},
  "geometry": {"coordinates":[4.5005970001,52.1570968628],"type":"Point"}
}