{
  "type": "Feature",
  "properties": {
    "iso:country":"NL",
    "sg:address":"Zandstr 159",
    "sg:city":"Beneden Leeuwen",
    "sg:orig_category":"Makelaars En Adviseurs Onroerende Goederen",
    "sg:phone":"+31 487 592 681",
    "sg:postcode":"6658 CS",
    "sg:province":"Gelderland",
    "wof:name":"Bouman Bv",
    "wof:placetype":"venue"
},
  "geometry": {"coordinates":[5.50019,51.879974],"type":"Point"}
}