{
  "type": "Feature",
  "properties": {
    "addr:full":"Midstr 87 Joure Friesland 8501 AG",
    "addr:housenumber":"87",
    "addr:postcode":"8501",
    "addr:street":"Midstr",
    "iso:country":"NL",
    "sg:address":"Midstr 87",
    "sg:city":"Joure",
    "sg:orig_category":"Woninginrichting",
    "sg:phone":"+31 513 413 794",
    "sg:postcode":"8501 AG",
    "sg:province":"Friesland",
    "sg:website":"http://www.bruinsmatapijt.nl",
    "wof:name":"Bruinsma Tapijt",
    "wof:placetype":"venue"
},
  "geometry": {"coordinates":[5.795563221,52.9676742554],"type":"Point"}
}