{
  "type": "Feature",
  "properties": {
    "addr:full":"Kemphaanstr 24B Den Helder North Holland 1781 WS",
    "addr:housenumber":"24b",
    "addr:postcode":"1781 ws",
    "addr:street":"Kemphaanstr",
    "iso:country":"NL",
    "sg:address":"Kemphaanstr 24B",
    "sg:city":"Den Helder",
    "sg:orig_category":"Verenigingsgebouwen",
    "sg:phone":"+31 223 615 587",
    "sg:postcode":"1781 WS",
    "sg:province":"North Holland",
    "wof:name":"Overzet, De",
    "wof:placetype":"venue"
},
  "geometry": {"coordinates":[4.76605,52.95145],"type":"Point"}
}