{
  "type": "Feature",
  "properties": {
    "addr:full":"Willemskade 1 Zwolle Overijssel 8011 AC",
    "addr:housenumber":"1",
    "addr:postcode":"8011 ac",
    "addr:street":"Willemskade",
    "iso:country":"NL",
    "sg:address":"Willemskade 1",
    "sg:city":"Zwolle",
    "sg:orig_category":"Banken And Kredietinstellingen",
    "sg:phone":"+31 38 428 7777",
    "sg:postcode":"8011 AC",
    "sg:province":"Overijssel",
    "wof:name":"Rabobank",
    "wof:placetype":"venue"
},
  "geometry": {"coordinates":[6.085435,52.509872],"type":"Point"}
}