{
  "type": "Feature",
  "properties": {
    "addr:full":"Handelsstraat 61 Hardenberg Overijssel 7772 TS",
    "addr:housenumber":"61",
    "addr:postcode":"7772 ts",
    "addr:street":"Handelsstraat",
    "iso:country":"NL",
    "sg:address":"Handelsstraat 61",
    "sg:city":"Hardenberg",
    "sg:classifiers":[
        {
            "category":"Retail",
            "subcategory":"Storage",
            "type":"Services"
        }
    ],
    "sg:phone":"+31 523 262 556",
    "sg:postcode":"7772 TS",
    "sg:province":"Overijssel",
    "sg:tags":[
        "opslag",
        "bewaring"
    ],
    "wof:name":"Inter Baarslag Bv",
    "wof:placetype":"venue"
},
  "geometry": {"coordinates":[6.6309289932,52.5632743835],"type":"Point"}
}