{
  "type": "Feature",
  "properties": {
    "addr:full":"Hoofdstraat 48 Kerkrade Limburg 6461 CR",
    "addr:housenumber":"48",
    "addr:postcode":"6461 cr",
    "addr:street":"Hoofdstraat",
    "iso:country":"NL",
    "sg:address":"Hoofdstraat 48",
    "sg:city":"Kerkrade",
    "sg:classifiers":[
        {
            "category":"Shopping",
            "subcategory":"Gifts & Souvenirs",
            "type":"Retail Goods"
        }
    ],
    "sg:phone":"+31 45 545 2800",
    "sg:postcode":"6461 CR",
    "sg:province":"Limburg",
    "sg:tags":[
        "geschenken"
    ],
    "wof:name":"Wiertz Geschenkenhuis",
    "wof:placetype":"venue"
},
  "geometry": {"coordinates":[6.067957,50.863529],"type":"Point"}
}