{
  "type": "Feature",
  "properties": {
    "addr:full":"Dorpsstr 3 Ledeacker North Brabant 5846 AB",
    "addr:housenumber":"3",
    "addr:postcode":"5846 ab",
    "addr:street":"Dorpsstr",
    "iso:country":"NL",
    "sg:address":"Dorpsstr 3",
    "sg:city":"Ledeacker",
    "sg:orig_category":"Fietsen En Bromfietsen",
    "sg:phone":"+31 485 381 409",
    "sg:postcode":"5846 AB",
    "sg:province":"North Brabant",
    "wof:name":"Aben, Theo",
    "wof:placetype":"venue"
},
  "geometry": {"coordinates":[5.876314,51.632828],"type":"Point"}
}