{
  "type": "Feature",
  "properties": {
    "addr:full":"Langestraat 65 Delden NL.08 7491 AB",
    "addr:housenumber":"65;nl.08",
    "addr:postcode":"7491 ab",
    "addr:street":"Langestraat",
    "iso:country":"NL",
    "sg:address":"Langestraat 65",
    "sg:city":"Delden",
    "sg:orig_category":"Fietshandelaren",
    "sg:phone":"+31 74 376 5161",
    "sg:postcode":"7491 AB",
    "sg:province":"NL.08",
    "wof:name":"Rijwielcentrum Delden",
    "wof:placetype":"venue"
},
  "geometry": {"coordinates":[6.70897,52.261898],"type":"Point"}
}