{
  "type": "Feature",
  "properties": {
    "addr:full":"Van Der Valk Boumanweg 188 Leiderdorp Zuid-Holland 2352 JE",
    "addr:housenumber":"188",
    "addr:postcode":"2352 je",
    "addr:street":"Van Der Valk Boumanweg",
    "iso:country":"NL",
    "sg:address":"Van Der Valk Boumanweg 188",
    "sg:city":"Leiderdorp",
    "sg:classifiers":[
        {
            "category":"Food & Beverages",
            "subcategory":"Fruits & Vegetables",
            "type":"Retail Goods"
        }
    ],
    "sg:phone":"+31 71 589 1279",
    "sg:postcode":"2352 JE",
    "sg:province":"Zuid-Holland",
    "sg:tags":[
        "groenten"
    ],
    "wof:name":"J A Stadt",
    "wof:placetype":"venue"
},
  "geometry": {"coordinates":[4.518283,52.159031],"type":"Point"}
}