{
  "type": "Feature",
  "properties": {
    "addr:full":"Winnerstr 17 Nederweert Limburg 6031 NK",
    "addr:housenumber":"17",
    "addr:postcode":"6031 nk",
    "addr:street":"Winnerstr",
    "iso:country":"NL",
    "sg:address":"Winnerstr 17",
    "sg:city":"Nederweert",
    "sg:orig_category":"Verzinkerijen",
    "sg:phone":"+31 495 461 700",
    "sg:postcode":"6031 NK",
    "sg:province":"Limburg",
    "sg:website":"http://www.vanaert.nl",
    "wof:name":"Aert, Van",
    "wof:placetype":"venue"
},
  "geometry": {"coordinates":[5.754383,51.301056],"type":"Point"}
}