{
  "type": "Feature",
  "properties": {
    "addr:full":"Grotestr 34 Drunen Noord-Brabant 5151 JE",
    "addr:housenumber":"34",
    "addr:postcode":"5151 je",
    "addr:street":"Grotestr",
    "iso:country":"NL",
    "sg:address":"Grotestr 34",
    "sg:city":"Drunen",
    "sg:orig_category":"Administratie- En Boekhoudkantoren",
    "sg:phone":"+31 416 375 703",
    "sg:postcode":"5151 JE",
    "sg:province":"Noord-Brabant",
    "wof:name":"Balkom, P Van",
    "wof:placetype":"venue"
},
  "geometry": {"coordinates":[5.124248,51.687645],"type":"Point"}
}