{
  "type": "Feature",
  "properties": {
    "addr:full":"F Rooseveltln 74 Breda Noord-Brabant 4835 AC",
    "addr:housenumber":"74",
    "addr:postcode":"4835 ac",
    "iso:country":"NL",
    "sg:address":"F Rooseveltln 74",
    "sg:city":"Breda",
    "sg:orig_category":"Psychotherapeuten",
    "sg:phone":"+31 76 564 0560",
    "sg:postcode":"4835 AC",
    "sg:province":"Noord-Brabant",
    "wof:name":"Engelen, Drs J F Van",
    "wof:placetype":"venue"
},
  "geometry": {"coordinates":[4.788534,51.575466],"type":"Point"}
}