{
  "type": "Feature",
  "properties": {
    "addr:full":"Purmerwg 29A Purmerend North Holland 1441 RA",
    "addr:housenumber":"29a",
    "addr:postcode":"1441 ra",
    "addr:street":"Purmerwg",
    "iso:country":"NL",
    "sg:address":"Purmerwg 29A",
    "sg:city":"Purmerend",
    "sg:orig_category":"Gordijnenateliers",
    "sg:phone":"+31 299 428 023",
    "sg:postcode":"1441 RA",
    "sg:province":"North Holland",
    "wof:name":"Roeland",
    "wof:placetype":"venue"
},
  "geometry": {"coordinates":[4.966082,52.503563],"type":"Point"}
}