{
  "type": "Feature",
  "properties": {
    "addr:full":"Caspar De Roblesdijk 46 Zurich Friesland 8751 TK",
    "addr:housenumber":"46",
    "addr:postcode":"8751 tk",
    "addr:street":"Caspar De Roblesdijk",
    "iso:country":"NL",
    "sg:address":"Caspar De Roblesdijk 46",
    "sg:city":"Zurich",
    "sg:orig_category":"Schilderwerk",
    "sg:phone":"+31 517 579 325",
    "sg:postcode":"8751 TK",
    "sg:province":"Friesland",
    "wof:name":"E Van Der Veen",
    "wof:placetype":"venue"
},
  "geometry": {"coordinates":[5.39146,53.110836],"type":"Point"}
}