{
  "type": "Feature",
  "properties": {
    "addr:full":"Hoevestein 19 Oosterhout Nb Noord-Brabant 4903 SE",
    "addr:housenumber":"19",
    "addr:postcode":"4903 se",
    "addr:street":"Hoevestein",
    "iso:country":"NL",
    "sg:address":"Hoevestein 19",
    "sg:city":"Oosterhout Nb",
    "sg:orig_category":"Meubels And Huishoudapparatuur Gh",
    "sg:phone":"+31 162 488 188",
    "sg:postcode":"4903 SE",
    "sg:province":"Noord-Brabant",
    "wof:name":"Designor Bv",
    "wof:placetype":"venue"
},
  "geometry": {"coordinates":[4.870904,51.628288],"type":"Point"}
}