{
  "type": "Feature",
  "properties": {
    "addr:full":"Eendenkd 6 Aalst Gld Gelderland 5308 NR",
    "addr:housenumber":"6",
    "addr:postcode":"5308",
    "addr:street":"Eendenkd;Gld Gelderland;Nr",
    "iso:country":"NL",
    "sg:address":"Eendenkd 6",
    "sg:city":"Aalst Gld",
    "sg:orig_category":"Adviesbureaus Bouwkunde",
    "sg:phone":"+31 418 554 150",
    "sg:postcode":"5308 NR",
    "sg:province":"Gelderland",
    "sg:website":"http://www.maas-support.nl",
    "wof:name":"Maas Support",
    "wof:placetype":"venue"
},
  "geometry": {"coordinates":[5.126693,51.783066],"type":"Point"}
}