{
  "type": "Feature",
  "properties": {
    "addr:full":"G Schipperstr 15 Naarden Noord-Holland 1411 TG",
    "addr:housenumber":"15",
    "addr:postcode":"1411 tg",
    "iso:country":"NL",
    "sg:address":"G Schipperstr 15",
    "sg:city":"Naarden",
    "sg:orig_category":"Schilders",
    "sg:phone":"+31 35 694 9892",
    "sg:postcode":"1411 TG",
    "sg:province":"Noord-Holland",
    "wof:name":"Bastion",
    "wof:placetype":"venue"
},
  "geometry": {"coordinates":[5.149136,52.298752],"type":"Point"}
}