{
  "type": "Feature",
  "properties": {
    "addr:full":"Gen Dibbetsln 86F Eindhoven Noord-Brabant 5623 JR",
    "addr:housenumber":"86f",
    "addr:postcode":"5623 jr",
    "iso:country":"NL",
    "sg:address":"Gen Dibbetsln 86F",
    "sg:city":"Eindhoven",
    "sg:classifiers":[
        {
            "category":"Retail",
            "subcategory":"Auto Repair",
            "type":"Services"
        }
    ],
    "sg:phone":"+31 40 243 8131",
    "sg:postcode":"5623 JR",
    "sg:province":"Noord-Brabant",
    "sg:tags":[
        "garage"
    ],
    "wof:name":"Wittenboer, Van Den",
    "wof:placetype":"venue"
},
  "geometry": {"coordinates":[5.47708,51.460041],"type":"Point"}
}