{
  "type": "Feature",
  "properties": {
    "iso:country":"NL",
    "sg:address":"Tuindorpwg 27",
    "sg:city":"Maarn",
    "sg:orig_category":"Evenementenverzorging",
    "sg:phone":"+31 343 441 109",
    "sg:postcode":"3951 BD",
    "sg:province":"Utrecht",
    "sg:website":"http://www.all-out.nl",
    "wof:name":"All-Out",
    "wof:placetype":"venue"
},
  "geometry": {"coordinates":[5.373313,52.064266],"type":"Point"}
}