{
  "type": "Feature",
  "properties": {
    "iso:country":"NL",
    "sg:address":"Molenstraat 83",
    "sg:city":"Zundert",
    "sg:orig_category":"Drukkerijen And Copyshops",
    "sg:phone":"+31 76 597 4319",
    "sg:postcode":"4881 CR",
    "sg:province":"Noord-Brabant",
    "wof:name":"Firma Drukkerij Jorissen En Zn",
    "wof:placetype":"venue"
},
  "geometry": {"coordinates":[4.659317,51.469681],"type":"Point"}
}