{
  "type": "Feature",
  "properties": {
    "addr:full":"Noordeinde 89A S Gravenhage Zuid-Holland 2514 GD",
    "addr:housenumber":"89a;gravenhage",
    "addr:postcode":"2514 gd",
    "addr:street":"Noordeinde;S",
    "iso:country":"NL",
    "sg:address":"Noordeinde 89A",
    "sg:city":"S Gravenhage",
    "sg:orig_category":"Fitnesscentra",
    "sg:phone":"+31 70 365 2918",
    "sg:postcode":"2514 GD",
    "sg:province":"Zuid-Holland",
    "sg:website":"http://www.silhouette.nu",
    "wof:name":"Silhouette Internationaal",
    "wof:placetype":"venue"
},
  "geometry": {"coordinates":[4.30935,52.084148],"type":"Point"}
}