{
  "type": "Feature",
  "properties": {
    "addr:full":"Hessenwg 181A De Bilt Utrecht 3731 JH",
    "addr:housenumber":"181a",
    "addr:postcode":"3731 jh",
    "iso:country":"NL",
    "sg:address":"Hessenwg 181A",
    "sg:city":"De Bilt",
    "sg:orig_category":"Poppen En Poppenhuismaterialen",
    "sg:phone":"+31 30 220 4297",
    "sg:postcode":"3731 JH",
    "sg:province":"Utrecht",
    "sg:website":"http://www.proxiredia/poppenatelier-wiesje.nl",
    "wof:name":"Wiesje Poppenatelier",
    "wof:placetype":"venue"
},
  "geometry": {"coordinates":[5.182345,52.111855],"type":"Point"}
}