{
  "type": "Feature",
  "properties": {
    "addr:full":"Zuiderdiep 42A Nieuw Buinen Drenthe 9521 AT",
    "addr:housenumber":"42a",
    "addr:postcode":"buinen;9521",
    "addr:street":"Zuiderdiep",
    "iso:country":"NL",
    "sg:address":"Zuiderdiep 42A",
    "sg:city":"Nieuw Buinen",
    "sg:orig_category":"Antiquiteiten",
    "sg:phone":"+31 599 212 607",
    "sg:postcode":"9521 AT",
    "sg:province":"Drenthe",
    "wof:name":"Paul Siepel",
    "wof:placetype":"venue"
},
  "geometry": {"coordinates":[6.910441,52.946499],"type":"Point"}
}