{
  "type": "Feature",
  "properties": {
    "iso:country":"NL",
    "sg:address":"Duinvlietstraat 2",
    "sg:city":"Velsen-Noord",
    "sg:orig_category":"Artsen And Specialisten",
    "sg:phone":"+31 251 223 745",
    "sg:postcode":"1951 XC",
    "sg:province":"Noord-Holland",
    "wof:name":"J.A.M. De Gouw",
    "wof:placetype":"venue"
},
  "geometry": {"coordinates":[4.641766,52.473328],"type":"Point"}
}