{
  "type": "Feature",
  "properties": {
    "addr:full":"Rusthoven 14 Eindhoven Noord-Brabant 5655 CM",
    "addr:housenumber":"14",
    "addr:postcode":"5655 cm",
    "addr:street":"Rusthoven",
    "iso:country":"NL",
    "sg:address":"Rusthoven 14",
    "sg:city":"Eindhoven",
    "sg:orig_category":"Beeldende Kunstenaars",
    "sg:phone":"+31 40 251 1779",
    "sg:postcode":"5655 CM",
    "sg:province":"Noord-Brabant",
    "wof:name":"Kwikkers-Broekhuizen, K J",
    "wof:placetype":"venue"
},
  "geometry": {"coordinates":[5.447049,51.414139],"type":"Point"}
}