{
  "type": "Feature",
  "properties": {
    "addr:full":"Aalsterwg 59 Eindhoven Noord-Brabant 5615 CB",
    "addr:housenumber":"59",
    "addr:postcode":"5615 cb",
    "addr:street":"Aalsterwg",
    "iso:country":"NL",
    "sg:address":"Aalsterwg 59",
    "sg:city":"Eindhoven",
    "sg:orig_category":"Bedden En Matrassen",
    "sg:phone":"+31 40 211 8364",
    "sg:postcode":"5615 CB",
    "sg:province":"Noord-Brabant",
    "sg:website":"http://www.droomland.nl",
    "wof:name":"Droomland",
    "wof:placetype":"venue"
},
  "geometry": {"coordinates":[5.486476,51.426193],"type":"Point"}
}