{
  "type": "Feature",
  "properties": {
    "addr:full":"Lusthofstr 70 Rotterdam South Holland 3061 WH",
    "addr:housenumber":"70",
    "addr:postcode":"3061 wh",
    "addr:street":"Lusthofstr",
    "iso:country":"NL",
    "sg:address":"Lusthofstr 70",
    "sg:city":"Rotterdam",
    "sg:classifiers":[
        {
            "category":"Farming",
            "subcategory":"Fish & Marine Products",
            "type":"Manufacturing & Wholesale Goods"
        }
    ],
    "sg:phone":"+31 10 413 6765",
    "sg:postcode":"3061 WH",
    "sg:province":"South Holland",
    "sg:tags":[
        "vi"
    ],
    "wof:name":"Dick Brijs",
    "wof:placetype":"venue"
},
  "geometry": {"coordinates":[4.510416,51.923969],"type":"Point"}
}