{
  "type": "Feature",
  "properties": {
    "addr:full":"J J Cremerpln 19-3 Amsterdam Noord-Holland 1054 TG",
    "addr:housenumber":"19-3",
    "addr:postcode":"1054 tg",
    "iso:country":"NL",
    "sg:address":"J J Cremerpln 19-3",
    "sg:city":"Amsterdam",
    "sg:orig_category":"Webdesign Bureaus",
    "sg:phone":"+31 20 412 6215",
    "sg:postcode":"1054 TG",
    "sg:province":"Noord-Holland",
    "sg:website":"http://www.mastermedia.nl",
    "wof:name":"Mastermedia",
    "wof:placetype":"venue"
},
  "geometry": {"coordinates":[4.8586788177,52.3591575623],"type":"Point"}
}