{
  "type": "Feature",
  "properties": {
    "addr:full":"Hasseltstraat 263 Tilburg North Brabant 5046 LL",
    "addr:housenumber":"263",
    "addr:postcode":"5046 ll",
    "addr:street":"Hasseltstraat",
    "iso:country":"NL",
    "sg:address":"Hasseltstraat 263",
    "sg:city":"Tilburg",
    "sg:orig_category":"Onderhoud And Reparatie Kantoorapparatuur",
    "sg:phone":"+31 13 536 3030",
    "sg:postcode":"5046 LL",
    "sg:province":"North Brabant",
    "wof:name":"Csb Bv",
    "wof:placetype":"venue"
},
  "geometry": {"coordinates":[5.07402,51.569149],"type":"Point"}
}