{
  "type": "Feature",
  "properties": {
    "addr:full":"Haarsteegsestraat 14 Haarsteeg Noord-Brabant 5254 JR",
    "addr:housenumber":"14",
    "addr:postcode":"5254 jr",
    "addr:street":"Haarsteegsestraat",
    "iso:country":"NL",
    "sg:address":"Haarsteegsestraat 14",
    "sg:city":"Haarsteeg",
    "sg:orig_category":"Kinderopvang Behalve Thuis",
    "sg:phone":"+31 73 511 2179",
    "sg:postcode":"5254 JR",
    "sg:province":"Noord-Brabant",
    "wof:name":"Dikkertje Dap",
    "wof:placetype":"venue"
},
  "geometry": {"coordinates":[5.198282,51.710281],"type":"Point"}
}