{
  "type": "Feature",
  "properties": {
    "addr:full":"Wasaweg 7 Groningen Groningen 9723 JD",
    "addr:housenumber":"7",
    "addr:postcode":"9723 jd",
    "addr:street":"Wasaweg",
    "iso:country":"NL",
    "sg:address":"Wasaweg 7",
    "sg:city":"Groningen",
    "sg:orig_category":"Verf En Lak - Fabrieken En Groothandel",
    "sg:phone":"+31 50 571 9180",
    "sg:postcode":"9723 JD",
    "sg:province":"Groningen",
    "wof:name":"Duister Vof",
    "wof:placetype":"venue"
},
  "geometry": {"coordinates":[6.60984,53.213505],"type":"Point"}
}