{
  "type": "Feature",
  "properties": {
    "iso:country":"NL",
    "sg:address":"Reeverweg 6",
    "sg:city":"Harfsen",
    "sg:orig_category":"Kantoorartikelen",
    "sg:phone":"+31 573 432 170",
    "sg:postcode":"7217 TB",
    "sg:province":"Gelderland",
    "wof:name":"Nordi Concept Bv",
    "wof:placetype":"venue"
},
  "geometry": {"coordinates":[6.2966661453,52.2064628601],"type":"Point"}
}