{
  "type": "Feature",
  "properties": {
    "iso:country":"NL",
    "sg:address":"1E Stoofweg 7",
    "sg:city":"Dirksland",
    "sg:orig_category":"Metaalafval, Schrootrecycling And Sloperijen",
    "sg:phone":"+31 187 603 091",
    "sg:postcode":"3247 LR",
    "sg:province":"Zuid-Holland",
    "wof:name":"F T Wesdijk",
    "wof:placetype":"venue"
},
  "geometry": {"coordinates":[4.081915,51.753666],"type":"Point"}
}