{
  "type": "Feature",
  "properties": {
    "addr:full":"Wg Ter Horst 26 Wychen Gelderland 6603 KK",
    "addr:housenumber":"26",
    "addr:postcode":"6603 kk",
    "addr:street":"Wg Ter Horst;Gelderland",
    "iso:country":"NL",
    "sg:address":"Wg Ter Horst 26",
    "sg:city":"Wychen",
    "sg:orig_category":"Loonbedrijven",
    "sg:phone":"+31 24 641 3372",
    "sg:postcode":"6603 KK",
    "sg:province":"Gelderland",
    "wof:name":"Derks, J T M",
    "wof:placetype":"venue"
},
  "geometry": {"coordinates":[4.41502,52.11562],"type":"Point"}
}