{
  "type": "Feature",
  "properties": {
    "iso:country":"NL",
    "sg:address":"Heistraat 62",
    "sg:city":"Kerkrade",
    "sg:orig_category":"Hoger Onderwijs",
    "sg:phone":"+31 45 542 2543",
    "sg:postcode":"6467 LR",
    "sg:province":"Limburg",
    "wof:name":"Ensaid",
    "wof:placetype":"venue"
},
  "geometry": {"coordinates":[6.020695,50.870792],"type":"Point"}
}