{
  "type": "Feature",
  "properties": {
    "addr:full":"Uiterwaardenstraat 90 Amsterdam North Holland 1079 CE",
    "addr:housenumber":"90",
    "addr:postcode":"1079 ce",
    "addr:street":"Uiterwaardenstraat",
    "iso:country":"NL",
    "sg:address":"Uiterwaardenstraat 90",
    "sg:city":"Amsterdam",
    "sg:classifiers":[
        {
            "category":"Food & Beverages",
            "subcategory":"Fruits & Vegetables",
            "type":"Retail Goods"
        }
    ],
    "sg:phone":"+31 20 644 9607",
    "sg:postcode":"1079 CE",
    "sg:province":"North Holland",
    "sg:tags":[
        "groenten"
    ],
    "wof:name":"Peterella'S Groente- En Fruithoekje",
    "wof:placetype":"venue"
},
  "geometry": {"coordinates":[4.908584,52.343132],"type":"Point"}
}