{
  "type": "Feature",
  "properties": {
    "addr:full":"Gulikstr 202 Venlo Limburg 5913 CZ",
    "addr:housenumber":"202",
    "addr:postcode":"5913",
    "iso:country":"NL",
    "sg:address":"Gulikstr 202",
    "sg:city":"Venlo",
    "sg:orig_category":"Verenigingsgebouwen",
    "sg:phone":"+31 77 351 1109",
    "sg:postcode":"5913 CZ",
    "sg:province":"Limburg",
    "wof:name":"D\u00f6rpel, D'N",
    "wof:placetype":"venue"
},
  "geometry": {"coordinates":[6.18858,51.369446],"type":"Point"}
}