{
  "type": "Feature",
  "properties": {
    "addr:full":"Hommerterweg 292 Amstenrade Limburg 6436 AM",
    "addr:housenumber":"292",
    "addr:postcode":"6436",
    "addr:street":"Hommerterweg",
    "iso:country":"NL",
    "sg:address":"Hommerterweg 292",
    "sg:city":"Amstenrade",
    "sg:orig_category":"Autokeuringen",
    "sg:phone":"+31 46 442 4256",
    "sg:postcode":"6436 AM",
    "sg:province":"Limburg",
    "wof:name":"Autoservice Fermans Bv",
    "wof:placetype":"venue"
},
  "geometry": {"coordinates":[5.916535,50.934418],"type":"Point"}
}