{
  "type": "Feature",
  "properties": {
    "iso:country":"NL",
    "sg:address":"Folkingestr 12B",
    "sg:city":"Groningen",
    "sg:orig_category":"Balletartikelen",
    "sg:phone":"+31 50 314 4238",
    "sg:postcode":"9711 JW",
    "sg:province":"Groningen",
    "wof:name":"The Fit",
    "wof:placetype":"venue"
},
  "geometry": {"coordinates":[6.56443,53.216255],"type":"Point"}
}