{
  "type": "Feature",
  "properties": {
    "addr:full":"Mierlosewg 19 Helmond North Brabant 5707 AB",
    "addr:housenumber":"19",
    "addr:postcode":"5707 ab",
    "addr:street":"Mierlosewg",
    "iso:country":"NL",
    "sg:address":"Mierlosewg 19",
    "sg:city":"Helmond",
    "sg:orig_category":"Kappersbenodigdheden",
    "sg:phone":"+31 492 550 982",
    "sg:postcode":"5707 AB",
    "sg:province":"North Brabant",
    "sg:website":"http://www.haircombi.nl",
    "wof:name":"Hair-Combi",
    "wof:placetype":"venue"
},
  "geometry": {"coordinates":[5.644386,51.476192],"type":"Point"}
}