{
  "type": "Feature",
  "properties": {
    "iso:country":"NL",
    "sg:address":"Spechtlaan 51",
    "sg:city":"Leidschendam",
    "sg:orig_category":"Verzekeringen",
    "sg:phone":"+31 70 327 3422",
    "sg:postcode":"2261 BB",
    "sg:province":"South Holland",
    "wof:name":"Bur Rietberg",
    "wof:placetype":"venue"
},
  "geometry": {"coordinates":[4.388917,52.098183],"type":"Point"}
}