{
  "type": "Feature",
  "properties": {
    "iso:country":"NL",
    "sg:address":"Ysselveld 18",
    "sg:city":"Montfoort",
    "sg:orig_category":"Metaalbewerking",
    "sg:phone":"+31 348 554 403",
    "sg:postcode":"3417 XH",
    "sg:province":"Utrecht",
    "wof:name":"Elmar Metaalbewerkingsbedrijf Bv",
    "wof:placetype":"venue"
},
  "geometry": {"coordinates":[4.946499,52.045784],"type":"Point"}
}