{
  "type": "Feature",
  "properties": {
    "addr:full":"Van De Spiegelstraat 38 Vlaardingen Zuid-Holland 3135 SH",
    "addr:housenumber":"38",
    "addr:postcode":"3135 sh",
    "addr:street":"Van De Spiegelstraat",
    "iso:country":"NL",
    "sg:address":"Van De Spiegelstraat 38",
    "sg:city":"Vlaardingen",
    "sg:classifiers":[
        {
            "category":"Fast Food",
            "type":"Food & Drink"
        }
    ],
    "sg:phone":"+31 10 470 0612",
    "sg:postcode":"3135 SH",
    "sg:province":"Zuid-Holland",
    "sg:tags":[
        "afhaal",
        "restaurant"
    ],
    "wof:name":"Snackbar De Spiegel",
    "wof:placetype":"venue"
},
  "geometry": {"coordinates":[4.362215,51.915432],"type":"Point"}
}