{
  "type": "Feature",
  "properties": {
    "iso:country":"NL",
    "sg:address":"Beverhof 37C",
    "sg:city":"Beverwyk",
    "sg:orig_category":"Warenhuizen",
    "sg:phone":"+31 251 215 488",
    "sg:postcode":"1941 EC",
    "sg:province":"Noord-Holland",
    "wof:name":"Xenos Bv",
    "wof:placetype":"venue"
},
  "geometry": {"coordinates":[4.6603450775,52.4819335938],"type":"Point"}
}