{
  "type": "Feature",
  "properties": {
    "addr:full":"Manegewg 9 Venlo Limburg 5916 NB",
    "addr:housenumber":"9",
    "addr:postcode":"5916 nb",
    "addr:street":"Manegewg",
    "iso:country":"NL",
    "sg:address":"Manegewg 9",
    "sg:city":"Venlo",
    "sg:orig_category":"Pijpleidingen",
    "sg:phone":"+31 77 320 1555",
    "sg:postcode":"5916 NB",
    "sg:province":"Limburg",
    "wof:name":"Rotterdam-Rijn-Pijpleidingen-Maatschappij Nv",
    "wof:placetype":"venue"
},
  "geometry": {"coordinates":[6.216222,51.376068],"type":"Point"}
}