{
  "type": "Feature",
  "properties": {
    "addr:full":"Lorentzpln 10 Haarlem Noord-Holland 2012 HG",
    "addr:housenumber":"10",
    "addr:postcode":"2012 hg",
    "addr:street":"Lorentzpln",
    "iso:country":"NL",
    "sg:address":"Lorentzpln 10",
    "sg:city":"Haarlem",
    "sg:orig_category":"Verzekeringen - Verzekeringskantoren",
    "sg:phone":"+31 23 531 5916",
    "sg:postcode":"2012 HG",
    "sg:province":"Noord-Holland",
    "wof:name":"Breeuwer & Gevers Vof",
    "wof:placetype":"venue"
},
  "geometry": {"coordinates":[4.628488,52.374981],"type":"Point"}
}