{
  "type": "Feature",
  "properties": {
    "addr:full":"Groenestraat 58 Hurwenen Gelderland 5327 AE",
    "addr:housenumber":"58",
    "addr:postcode":"5327 ae",
    "addr:street":"Groenestraat;Gelderland",
    "iso:country":"NL",
    "sg:address":"Groenestraat 58",
    "sg:city":"Hurwenen",
    "sg:orig_category":"Loodgieterswerk, Verwarming And Sanitaire Installaties",
    "sg:phone":"+31 418 512 900",
    "sg:postcode":"5327 AE",
    "sg:province":"Gelderland",
    "wof:name":"Z.K.B. Zaltbommels Klussenbedrijf",
    "wof:placetype":"venue"
},
  "geometry": {"coordinates":[5.314558,51.811584],"type":"Point"}
}