{
  "type": "Feature",
  "properties": {
    "addr:full":"Livornostraat 22 Amsterdam Noord-Holland 1055 ZZ",
    "addr:housenumber":"22",
    "addr:postcode":"1055 zz",
    "addr:street":"Livornostraat",
    "iso:country":"NL",
    "sg:address":"Livornostraat 22",
    "sg:city":"Amsterdam",
    "sg:orig_category":"Drukkerijen And Copyshops",
    "sg:phone":"+31 20 682 3551",
    "sg:postcode":"1055 ZZ",
    "sg:province":"Noord-Holland",
    "wof:name":"Studio All-Print",
    "wof:placetype":"venue"
},
  "geometry": {"coordinates":[4.853635,52.384239],"type":"Point"}
}