{
  "type": "Feature",
  "properties": {
    "addr:full":"Dorpsstr 80 Poortugaal Zuid-Holland 3171 EH",
    "addr:housenumber":"80",
    "addr:postcode":"3171 eh",
    "addr:street":"Dorpsstr",
    "iso:country":"NL",
    "sg:address":"Dorpsstr 80",
    "sg:city":"Poortugaal",
    "sg:orig_category":"Woningbouw- Verenigingen En -Stichtingen",
    "sg:phone":"+31 10 501 0455",
    "sg:postcode":"3171 EH",
    "sg:province":"Zuid-Holland",
    "wof:name":"Woonservice Albrandswaard Vof",
    "wof:placetype":"venue"
},
  "geometry": {"coordinates":[4.389081955,51.8556747437],"type":"Point"}
}