{
  "type": "Feature",
  "properties": {
    "addr:full":"Graafschedijk 46 Escharen Noord-Brabant 5364 PS",
    "addr:housenumber":"46",
    "addr:postcode":"5364 ps",
    "addr:street":"Graafschedijk",
    "iso:country":"NL",
    "sg:address":"Graafschedijk 46",
    "sg:city":"Escharen",
    "sg:orig_category":"Boekhouders",
    "sg:phone":"+31 486 420 915",
    "sg:postcode":"5364 PS",
    "sg:province":"Noord-Brabant",
    "wof:name":"H.A.M. Cruysen",
    "wof:placetype":"venue"
},
  "geometry": {"coordinates":[5.747564,51.74226],"type":"Point"}
}