{
  "type": "Feature",
  "properties": {
    "iso:country":"NL",
    "sg:address":"Heerestr 1",
    "sg:city":"Roden",
    "sg:classifiers":[
        {
            "category":"Travel",
            "subcategory":"Hotels & Motels",
            "type":"Entertainment"
        }
    ],
    "sg:phone":"+31 50 501 9192",
    "sg:postcode":"9301 AC",
    "sg:province":"Provincie Drenthe",
    "sg:website":"http://www.hetwapenvandrenthe.nl",
    "wof:name":"Wapen Van Drenthe, Het",
    "wof:placetype":"venue"
},
  "geometry": {"coordinates":[6.432542,53.136242],"type":"Point"}
}