{
  "type": "Feature",
  "properties": {
    "addr:full":"Merwedestraat 3 Velp Gld Gelderland 6882 LK",
    "addr:housenumber":"3",
    "addr:postcode":"6882 lk",
    "addr:street":"Merwedestraat;Gld Gelderland",
    "iso:country":"NL",
    "sg:address":"Merwedestraat 3",
    "sg:city":"Velp Gld",
    "sg:orig_category":"Boekhouders",
    "sg:phone":"+31 26 361 8881",
    "sg:postcode":"6882 LK",
    "sg:province":"Gelderland",
    "wof:name":"Deja Financieringen-Administraties",
    "wof:placetype":"venue"
},
  "geometry": {"coordinates":[5.97516,51.990379],"type":"Point"}
}