{
  "type": "Feature",
  "properties": {
    "addr:full":"Binkhorst 68 Alphen Aan Den Ryn South Holland 2402 MB",
    "addr:housenumber":"68",
    "addr:postcode":"2402 mb",
    "addr:street":"Binkhorst;Aan Den Ryn",
    "iso:country":"NL",
    "sg:address":"Binkhorst 68",
    "sg:city":"Alphen Aan Den Ryn",
    "sg:orig_category":"Horeca-Inrichtingen En -Uitrustingen",
    "sg:phone":"+31 172 432 726",
    "sg:postcode":"2402 MB",
    "sg:province":"South Holland",
    "wof:name":"Korte, De",
    "wof:placetype":"venue"
},
  "geometry": {"coordinates":[4.666771,52.150211],"type":"Point"}
}