{
  "type": "Feature",
  "properties": {
    "addr:full":"Clausstr 5 Rysbergen North Brabant 4891 XM",
    "addr:housenumber":"5",
    "addr:postcode":"4891 xm",
    "addr:street":"Clausstr",
    "iso:country":"NL",
    "sg:address":"Clausstr 5",
    "sg:city":"Rysbergen",
    "sg:classifiers":[
        {
            "category":"Personal",
            "subcategory":"Nail Salon",
            "type":"Services"
        }
    ],
    "sg:phone":"+31 76 596 2741",
    "sg:postcode":"4891 XM",
    "sg:province":"North Brabant",
    "sg:tags":[
        "pedicure"
    ],
    "wof:name":"Lips-De Bruin, R",
    "wof:placetype":"venue"
},
  "geometry": {"coordinates":[4.693745,51.517723],"type":"Point"}
}