{
  "type": "Feature",
  "properties": {
    "addr:full":"Veerstraat 31 Boxmeer Noord-Brabant 5831 JL",
    "addr:housenumber":"31",
    "addr:postcode":"5831 jl",
    "addr:street":"Veerstraat",
    "iso:country":"NL",
    "sg:address":"Veerstraat 31",
    "sg:city":"Boxmeer",
    "sg:orig_category":"Kappers",
    "sg:phone":"+31 485 571 373",
    "sg:postcode":"5831 JL",
    "sg:province":"Noord-Brabant",
    "wof:name":"J.H.A. Hermans",
    "wof:placetype":"venue"
},
  "geometry": {"coordinates":[5.9534392357,51.6488571167],"type":"Point"}
}