{
  "type": "Feature",
  "properties": {
    "addr:full":"Engelandln 330 Zoetermeer South Holland 2711 DZ",
    "addr:housenumber":"330",
    "addr:postcode":"2711 dz",
    "iso:country":"NL",
    "sg:address":"Engelandln 330",
    "sg:city":"Zoetermeer",
    "sg:orig_category":"Verenigingen En Stichtingen",
    "sg:phone":"+31 79 341 1981",
    "sg:postcode":"2711 DZ",
    "sg:province":"South Holland",
    "sg:website":"http://www.gasandoil.com/~iro",
    "wof:name":"Iro Branchver",
    "wof:placetype":"venue"
},
  "geometry": {"coordinates":[4.491106,52.060036],"type":"Point"}
}