{
  "type": "Feature",
  "properties": {
    "addr:full":"Victoriestr 8 Waalwyk Noord-Brabant 5142 RH",
    "addr:housenumber":"8",
    "addr:postcode":"5142 rh",
    "addr:street":"Victoriestr",
    "iso:country":"NL",
    "sg:address":"Victoriestr 8",
    "sg:city":"Waalwyk",
    "sg:orig_category":"Schilders",
    "sg:phone":"+31 416 340 986",
    "sg:postcode":"5142 RH",
    "sg:province":"Noord-Brabant",
    "wof:name":"Raaijmakers",
    "wof:placetype":"venue"
},
  "geometry": {"coordinates":[5.074888,51.687698],"type":"Point"}
}