{
  "type": "Feature",
  "properties": {
    "addr:full":"Htg Aalbrechtwg 4 Alkmaar North Holland 1823 DL",
    "addr:housenumber":"4",
    "addr:postcode":"1823 dl",
    "addr:street":"Aalbrechtwg",
    "iso:country":"NL",
    "sg:address":"Htg Aalbrechtwg 4",
    "sg:city":"Alkmaar",
    "sg:orig_category":"Zalenverhuur",
    "sg:phone":"+31 72 561 6391",
    "sg:postcode":"1823 DL",
    "sg:province":"North Holland",
    "wof:name":"Hoornse Vaart, De",
    "wof:placetype":"venue"
},
  "geometry": {"coordinates":[4.766186,52.643826],"type":"Point"}
}