{
  "type": "Feature",
  "properties": {
    "iso:country":"NL",
    "sg:address":"Ambachtstraat 1",
    "sg:city":"Beverwijk",
    "sg:orig_category":"Schilderwerk",
    "sg:phone":"+31 251 225 069",
    "sg:postcode":"1948 PB",
    "sg:province":"Noord-Holland",
    "wof:name":"Schildersbedrijf J. Conijn Bv",
    "wof:placetype":"venue"
},
  "geometry": {"coordinates":[-36.777691,-7.16501],"type":"Point"}
}