{
  "type": "Feature",
  "properties": {
    "addr:full":"Jan Evertsenstraat 38 Amsterdam Noord-Holland 1056 ED",
    "addr:housenumber":"38",
    "addr:postcode":"1056 ed",
    "addr:street":"Jan Evertsenstraat",
    "iso:country":"NL",
    "sg:address":"Jan Evertsenstraat 38",
    "sg:city":"Amsterdam",
    "sg:orig_category":"Medische Apparatuur And Prothesen Fab",
    "sg:phone":"+31 20 618 6587",
    "sg:postcode":"1056 ED",
    "sg:province":"Noord-Holland",
    "wof:name":"Beter Horen Audire",
    "wof:placetype":"venue"
},
  "geometry": {"coordinates":[4.857223,52.371414],"type":"Point"}
}