{
  "type": "Feature",
  "properties": {
    "addr:full":"Postbus 1491 Aalsmeer North Holland 1430 BL",
    "addr:housenumber":"1491",
    "addr:postcode":"1430 bl",
    "addr:street":"Postbus",
    "iso:country":"NL",
    "sg:address":"Postbus 1491",
    "sg:city":"Aalsmeer",
    "sg:orig_category":"Bloemen En Planten - Groothandel",
    "sg:phone":"+31 297 346 726",
    "sg:postcode":"1430 BL",
    "sg:province":"North Holland",
    "wof:name":"Roubos Almkerk Bv",
    "wof:placetype":"venue"
},
  "geometry": {"coordinates":[4.749068,52.266991],"type":"Point"}
}