{
  "type": "Feature",
  "properties": {
    "addr:full":"Vinkekampwg 20 Kootwykerbroek Gelderland 3774 PL",
    "addr:housenumber":"20",
    "addr:postcode":"3774 pl",
    "addr:street":"Vinkekampwg;Gelderland",
    "iso:country":"NL",
    "sg:address":"Vinkekampwg 20",
    "sg:city":"Kootwykerbroek",
    "sg:orig_category":"Meubelmakerijen",
    "sg:phone":"+31 342 401 161",
    "sg:postcode":"3774 PL",
    "sg:province":"Gelderland",
    "wof:name":"Wagtho",
    "wof:placetype":"venue"
},
  "geometry": {"coordinates":[5.642157,52.138027],"type":"Point"}
}