{
  "type": "Feature",
  "properties": {
    "addr:full":"Eenheidsstr 1 Puth Limburg 6155 LN",
    "addr:housenumber":"1",
    "addr:postcode":"6155 ln",
    "addr:street":"Eenheidsstr",
    "iso:country":"NL",
    "sg:address":"Eenheidsstr 1",
    "sg:city":"Puth",
    "sg:orig_category":"Margarine, Olie En Vet - Groothandel",
    "sg:phone":"+31 46 443 2057",
    "sg:postcode":"6155 LN",
    "sg:province":"Limburg",
    "wof:name":"Ad Janssen Vethandel Vof",
    "wof:placetype":"venue"
},
  "geometry": {"coordinates":[5.873912,50.95406],"type":"Point"}
}