{
  "type": "Feature",
  "properties": {
    "addr:full":"Hibbertsstraat 2 Haaksbergen NL.08 7481 JD",
    "addr:housenumber":"2;nl.08",
    "addr:postcode":"7481 jd",
    "addr:street":"Hibbertsstraat",
    "iso:country":"NL",
    "sg:address":"Hibbertsstraat 2",
    "sg:city":"Haaksbergen",
    "sg:orig_category":"Opticiens",
    "sg:phone":"+31 53 572 2446",
    "sg:postcode":"7481 JD",
    "sg:province":"NL.08",
    "wof:name":"L.G. Kuipers, Optiek",
    "wof:placetype":"venue"
},
  "geometry": {"coordinates":[6.7409000397,52.1553077698],"type":"Point"}
}