{
  "type": "Feature",
  "properties": {
    "addr:full":"Aalsvoort 5 Lochem Gelderland 7241 MA",
    "addr:housenumber":"5",
    "addr:postcode":"7241 ma",
    "addr:street":"Aalsvoort;Gelderland",
    "iso:country":"NL",
    "sg:address":"Aalsvoort 5",
    "sg:city":"Lochem",
    "sg:orig_category":"Kunststoffen- Verwerkende Industrie",
    "sg:phone":"+31 573 288 288",
    "sg:postcode":"7241 MA",
    "sg:province":"Gelderland",
    "sg:website":"http://www.kors.nl",
    "wof:name":"Kors Kunststoffen Bv",
    "wof:placetype":"venue"
},
  "geometry": {"coordinates":[6.391488,52.168022],"type":"Point"}
}