{
  "type": "Feature",
  "properties": {
    "addr:full":"Stationsplein 220 Leiden South Holland 2312 AR",
    "addr:housenumber":"220",
    "addr:postcode":"2312",
    "addr:street":"Stationsplein",
    "iso:country":"NL",
    "sg:address":"Stationsplein 220",
    "sg:city":"Leiden",
    "sg:orig_category":"Meubelzaken, Woning- And Keukeninrichting",
    "sg:phone":"+31 71 512 6745",
    "sg:postcode":"2312 AR",
    "sg:province":"South Holland",
    "wof:name":"Leenbakker",
    "wof:placetype":"venue"
},
  "geometry": {"coordinates":[4.482754,52.16608],"type":"Point"}
}