{
  "type": "Feature",
  "properties": {
    "addr:full":"Burg Van Engelenweg 34 Ijsselmuiden NL.08 8271 AS",
    "addr:housenumber":"34;nl.08",
    "addr:postcode":"8271",
    "addr:street":"Burg Van Engelenweg",
    "iso:country":"NL",
    "sg:address":"Burg Van Engelenweg 34",
    "sg:city":"Ijsselmuiden",
    "sg:orig_category":"Visspeciaalzaken",
    "sg:phone":"+31 38 332 4690",
    "sg:postcode":"8271 AS",
    "sg:province":"NL.08",
    "wof:name":"Vishandel Bottenberg",
    "wof:placetype":"venue"
},
  "geometry": {"coordinates":[5.925369,52.561081],"type":"Point"}
}