{
  "type": "Feature",
  "properties": {
    "iso:country":"NL",
    "sg:address":"Burg Van Engelenweg 34",
    "sg:city":"Ijsselmuiden",
    "sg:orig_category":"Visspeciaalzaken",
    "sg:phone":"+31 38 332 4690",
    "sg:postcode":"8271 AS",
    "sg:province":"NL.08",
    "wof:name":"Vishandel Bottenberg",
    "wof:placetype":"venue"
},
  "geometry": {"coordinates":[5.925369,52.561081],"type":"Point"}
}