{
  "type": "Feature",
  "properties": {
    "addr:full":"Elmpterweg 42 Roermond Limburg 6042 KL",
    "addr:housenumber":"42",
    "addr:postcode":"6042 kl",
    "addr:street":"Elmpterweg",
    "iso:country":"NL",
    "sg:address":"Elmpterweg 42",
    "sg:city":"Roermond",
    "sg:classifiers":[
        {
            "category":"Food & Beverages",
            "subcategory":"Fruits & Vegetables",
            "type":"Retail Goods"
        }
    ],
    "sg:phone":"+31 475 329 439",
    "sg:postcode":"6042 KL",
    "sg:province":"Limburg",
    "sg:tags":[
        "groenten"
    ],
    "wof:name":"A.G. Broedermans",
    "wof:placetype":"venue"
},
  "geometry": {"coordinates":[6.02029,51.201305],"type":"Point"}
}