{
  "type": "Feature",
  "properties": {
    "addr:full":"Waalstraat 31 Krimpen A/D Ijssel South Holland 2921 XN",
    "addr:housenumber":"31;a / d",
    "addr:postcode":"2921 xn",
    "addr:street":"Waalstraat;Ijssel South",
    "iso:country":"NL",
    "sg:address":"Waalstraat 31",
    "sg:city":"Krimpen A/D Ijssel",
    "sg:orig_category":"Keramische Producten Fab",
    "sg:phone":"+31 180 518 322",
    "sg:postcode":"2921 XN",
    "sg:province":"South Holland",
    "wof:name":"Pot-Dorie",
    "wof:placetype":"venue"
},
  "geometry": {"coordinates":[4.585017,51.912254],"type":"Point"}
}