{
  "type": "Feature",
  "properties": {
    "addr:full":"Garvelinkpln 20 Ruurlo Gelderland 7261 CK",
    "addr:housenumber":"20",
    "addr:postcode":"7261 ck",
    "addr:street":"Garvelinkpln;Gelderland",
    "iso:country":"NL",
    "sg:address":"Garvelinkpln 20",
    "sg:city":"Ruurlo",
    "sg:orig_category":"Parketvloeren",
    "sg:phone":"+31 573 451 661",
    "sg:postcode":"7261 CK",
    "sg:province":"Gelderland",
    "wof:name":"Hegro Bv",
    "wof:placetype":"venue"
},
  "geometry": {"coordinates":[6.454575,52.092869],"type":"Point"}
}