{
  "type": "Feature",
  "properties": {
    "iso:country":"NL",
    "sg:address":"Bremweg 6",
    "sg:city":"Venlo",
    "sg:orig_category":"Verzekeringen",
    "sg:phone":"+31 77 351 7227",
    "sg:postcode":"5915 GL",
    "sg:province":"Limburg",
    "wof:name":"Verzekeringskantoor A.J. Gommans",
    "wof:placetype":"venue"
},
  "geometry": {"coordinates":[6.190296,51.355152],"type":"Point"}
}