{
  "type": "Feature",
  "properties": {
    "iso:country":"NL",
    "sg:address":"Koningln 8",
    "sg:city":"Helmond",
    "sg:orig_category":"Hoeden",
    "sg:phone":"+31 492 547 003",
    "sg:postcode":"5708 ED",
    "sg:province":"Noord-Brabant",
    "wof:name":"Annet Verheij-Meulders",
    "wof:placetype":"venue"
},
  "geometry": {"coordinates":[5.603202,51.485821],"type":"Point"}
}