{
  "type": "Feature",
  "properties": {
    "addr:full":"Haffmansstraat 2 Aarle Rixtel Noord-Brabant 5735 CR",
    "addr:housenumber":"2",
    "addr:postcode":"5735 cr",
    "addr:street":"Haffmansstraat",
    "iso:country":"NL",
    "sg:address":"Haffmansstraat 2",
    "sg:city":"Aarle Rixtel",
    "sg:orig_category":"Schilderwerk",
    "sg:phone":"+31 492 381 657",
    "sg:postcode":"5735 CR",
    "sg:province":"Noord-Brabant",
    "wof:name":"Schildersbedrijf G Derks",
    "wof:placetype":"venue"
},
  "geometry": {"coordinates":[5.643841,51.511936],"type":"Point"}
}