{
  "type": "Feature",
  "properties": {
    "addr:full":"Boterbloemstr 32 St Willebrord North Brabant 4711 GX",
    "addr:housenumber":"32",
    "addr:postcode":"4711 gx",
    "addr:street":"Boterbloemstr;St",
    "iso:country":"NL",
    "sg:address":"Boterbloemstr 32",
    "sg:city":"St Willebrord",
    "sg:orig_category":"Woninginrichting",
    "sg:phone":"+31 165 387 789",
    "sg:postcode":"4711 GX",
    "sg:province":"North Brabant",
    "sg:website":"http://www.walterheerenstofferingen.nl",
    "wof:name":"Heeren, Stofferingen Walter",
    "wof:placetype":"venue"
},
  "geometry": {"coordinates":[4.5854411125,51.5473556519],"type":"Point"}
}