{
  "type": "Feature",
  "properties": {
    "iso:country":"NL",
    "sg:address":"Harmanshoeve 6",
    "sg:city":"Ouderkerk Ad Yssel",
    "sg:classifiers":[
        {
            "category":"Home & Garden",
            "subcategory":"Hardware",
            "type":"Retail Goods"
        }
    ],
    "sg:phone":"+31 180 681 488",
    "sg:postcode":"2935 AT",
    "sg:province":"Zuid-Holland",
    "sg:tags":[
        "machine",
        "-",
        "metaalbewerking"
    ],
    "sg:website":"http://www.metamach.nl",
    "wof:name":"Metamach Bv",
    "wof:placetype":"venue"
},
  "geometry": {"coordinates":[4.622381,51.934437],"type":"Point"}
}