{
  "type": "Feature",
  "properties": {
    "iso:country":"NL",
    "sg:address":"Jan Alsweg 20",
    "sg:city":"Beverwijk",
    "sg:classifiers":[
        {
            "category":"Fast Food",
            "type":"Food & Drink"
        }
    ],
    "sg:phone":"+31 251 212 201",
    "sg:postcode":"1941 CD",
    "sg:province":"Noord-Holland",
    "sg:tags":[
        "afhaal",
        "restaurant"
    ],
    "wof:name":"Pizzeria Lorenza",
    "wof:placetype":"venue"
},
  "geometry": {"coordinates":[4.656922,52.485207],"type":"Point"}
}