{
  "type": "Feature",
  "properties": {
    "addr:full":"J Steenln 49 Veenendaal Utrecht 3904 XM",
    "addr:housenumber":"49",
    "addr:postcode":"3904 xm",
    "iso:country":"NL",
    "sg:address":"J Steenln 49",
    "sg:city":"Veenendaal",
    "sg:orig_category":"Onderhoudswerken",
    "sg:phone":"+31 318 516 986",
    "sg:postcode":"3904 XM",
    "sg:province":"Utrecht",
    "wof:name":"Pietjouw",
    "wof:placetype":"venue"
},
  "geometry": {"coordinates":[5.543143,52.020657],"type":"Point"}
}