{
  "type": "Feature",
  "properties": {
    "iso:country":"NL",
    "sg:address":"Stationswg 8",
    "sg:city":"Maasbracht",
    "sg:orig_category":"Wasmachines En Wasdrogers - Onderhoud En Reparatie",
    "sg:phone":"+31 475 466 061",
    "sg:postcode":"6051 KL",
    "sg:province":"Limburg",
    "wof:name":"Linden Elektro, Van Der",
    "wof:placetype":"venue"
},
  "geometry": {"coordinates":[5.9095840454,51.147808075],"type":"Point"}
}