{
  "type": "Feature",
  "properties": {
    "addr:full":"Hamburgerstraat 46 Doetinchem Gelderland 7001 AL",
    "addr:housenumber":"46;7001",
    "addr:postcode":"al",
    "addr:street":"Hamburgerstraat;Gelderland",
    "iso:country":"NL",
    "sg:address":"Hamburgerstraat 46",
    "sg:city":"Doetinchem",
    "sg:classifiers":[
        {
            "category":"Bakery",
            "type":"Food & Drink"
        }
    ],
    "sg:phone":"+31 314 366 590",
    "sg:postcode":"7001 AL",
    "sg:province":"Gelderland",
    "sg:tags":[
        "brood",
        "banket"
    ],
    "wof:name":"Banketbakkerij Lunchroom Rest. Vinkenborg",
    "wof:placetype":"venue"
},
  "geometry": {"coordinates":[6.290203,51.964153],"type":"Point"}
}