{
  "type": "Feature",
  "properties": {
    "addr:full":"Damsterkd 8/1 Groningen Groningen 9711 SE",
    "addr:housenumber":"8 / 1",
    "addr:postcode":"9711 se",
    "addr:street":"Damsterkd",
    "iso:country":"NL",
    "sg:address":"Damsterkd 8/1",
    "sg:city":"Groningen",
    "sg:orig_category":"Videotheken",
    "sg:phone":"+31 50 312 9852",
    "sg:postcode":"9711 SE",
    "sg:province":"Groningen",
    "wof:name":"Ster Videotheek Groningen",
    "wof:placetype":"venue"
},
  "geometry": {"coordinates":[6.574629,53.217274],"type":"Point"}
}