{
  "type": "Feature",
  "properties": {
    "addr:full":"Boschdk 389 Eindhoven Noord-Brabant 5621 JB",
    "addr:housenumber":"389",
    "addr:postcode":"5621 jb",
    "iso:country":"NL",
    "sg:address":"Boschdk 389",
    "sg:city":"Eindhoven",
    "sg:orig_category":"Gordijnen",
    "sg:phone":"+31 40 244 3262",
    "sg:postcode":"5621 JB",
    "sg:province":"Noord-Brabant",
    "sg:website":"HTTP://www.szalai-fabrics.com",
    "wof:name":"Szalai, Monique",
    "wof:placetype":"venue"
},
  "geometry": {"coordinates":[5.461645,51.454418],"type":"Point"}
}