{
  "type": "Feature",
  "properties": {
    "addr:full":"Vennestraat 17 Drunen Noord-Brabant 5151 CA",
    "addr:housenumber":"17",
    "addr:postcode":"5151 ca",
    "addr:street":"Vennestraat",
    "iso:country":"NL",
    "sg:address":"Vennestraat 17",
    "sg:city":"Drunen",
    "sg:orig_category":"Boekhouders",
    "sg:phone":"+31 416 373 185",
    "sg:postcode":"5151 CA",
    "sg:province":"Noord-Brabant",
    "wof:name":"C.J. Van Loon",
    "wof:placetype":"venue"
},
  "geometry": {"coordinates":[5.136151,51.684551],"type":"Point"}
}