{
  "type": "Feature",
  "properties": {
    "iso:country":"NL",
    "sg:address":"Westeinde 23",
    "sg:city":"Zwartsluis",
    "sg:orig_category":"Verenigingsgebouwen",
    "sg:phone":"+31 38 386 6606",
    "sg:postcode":"8064 AJ",
    "sg:province":"Overijssel",
    "wof:name":"Sosz",
    "wof:placetype":"venue"
},
  "geometry": {"coordinates":[6.0617,52.638264],"type":"Point"}
}