{
  "type": "Feature",
  "properties": {
    "addr:full":"Dirkslandstr 7 Tilburg Noord-Brabant 5043 JE",
    "addr:housenumber":"7",
    "addr:postcode":"5043 je",
    "addr:street":"Dirkslandstr",
    "iso:country":"NL",
    "sg:address":"Dirkslandstr 7",
    "sg:city":"Tilburg",
    "sg:orig_category":"Autorijscholen",
    "sg:phone":"+31 13 570 2707",
    "sg:postcode":"5043 JE",
    "sg:province":"Noord-Brabant",
    "wof:name":"Leijten",
    "wof:placetype":"venue"
},
  "geometry": {"coordinates":[5.01581,51.577164],"type":"Point"}
}