{
  "type": "Feature",
  "properties": {
    "iso:country":"NL",
    "sg:address":"Uitweg 17",
    "sg:city":"Vinkeveen",
    "sg:orig_category":"Bloemen And Planten",
    "sg:phone":"+31 297 261 784",
    "sg:postcode":"3645 TA",
    "sg:province":"Utrecht",
    "wof:name":"Tuincentrum Rijdes",
    "wof:placetype":"venue"
},
  "geometry": {"coordinates":[4.922528,52.198318],"type":"Point"}
}