{
  "type": "Feature",
  "properties": {
    "addr:full":"Dorsvlegel 14 De Goorn Noord-Holland 1648 HX",
    "addr:housenumber":"14",
    "addr:postcode":"1648 hx",
    "addr:street":"Dorsvlegel",
    "iso:country":"NL",
    "sg:address":"Dorsvlegel 14",
    "sg:city":"De Goorn",
    "sg:classifiers":[
        {
            "category":"Professional",
            "subcategory":"Accounting & Tax Preparation",
            "type":"Services"
        }
    ],
    "sg:phone":"+31 229 541 952",
    "sg:postcode":"1648 HX",
    "sg:province":"Noord-Holland",
    "sg:tags":[
        "accountant"
    ],
    "wof:name":"Accountantskantoor Blom & Partners",
    "wof:placetype":"venue"
},
  "geometry": {"coordinates":[4.952553,52.624603],"type":"Point"}
}