{
  "type": "Feature",
  "properties": {
    "addr:full":"S Stevinstr 3 Dordrecht Zuid-Holland 3316 AT",
    "addr:housenumber":"3",
    "addr:postcode":"3316",
    "iso:country":"NL",
    "sg:address":"S Stevinstr 3",
    "sg:city":"Dordrecht",
    "sg:orig_category":"Horecabenodigdheden",
    "sg:phone":"+31 78 613 5003",
    "sg:postcode":"3316 AT",
    "sg:province":"Zuid-Holland",
    "wof:name":"Rocar",
    "wof:placetype":"venue"
},
  "geometry": {"coordinates":[4.642538,51.800022],"type":"Point"}
}