{
  "type": "Feature",
  "properties": {
    "iso:country":"NL",
    "sg:address":"Prins Hendrikstraat 224",
    "sg:city":"Alphen A/D Rijn",
    "sg:orig_category":"Boekhouders",
    "sg:phone":"+31 172 476 805",
    "sg:postcode":"2405 AP",
    "sg:province":"South Holland",
    "wof:name":"Adm.- En Belastingadviesburo Rijnstede B",
    "wof:placetype":"venue"
},
  "geometry": {"coordinates":[4.662103,52.125408],"type":"Point"}
}