{
  "type": "Feature",
  "properties": {
    "addr:full":"Ganzestaartsedk 10 Duizel Noord-Brabant 5525 KC",
    "addr:housenumber":"10",
    "addr:postcode":"5525 kc",
    "addr:street":"Ganzestaartsedk",
    "iso:country":"NL",
    "sg:address":"Ganzestaartsedk 10",
    "sg:city":"Duizel",
    "sg:orig_category":"Voegwerken",
    "sg:phone":"+31 497 514 195",
    "sg:postcode":"5525 KC",
    "sg:province":"Noord-Brabant",
    "sg:website":"http://www.members.tripdnet.nl/verhbouwonder",
    "wof:name":"Verhoeven Voegwerken Bv",
    "wof:placetype":"venue"
},
  "geometry": {"coordinates":[5.292876,51.36264],"type":"Point"}
}