{
  "type": "Feature",
  "properties": {
    "addr:full":"Zoom 1022 Lelystad NL. 8225 KB",
    "addr:postcode":"1022;8225 kb",
    "addr:street":"Zoom;Nl.",
    "iso:country":"NL",
    "sg:address":"Zoom 1022",
    "sg:city":"Lelystad",
    "sg:orig_category":"Maatschappelijk Werk",
    "sg:phone":"+31 320 241 224",
    "sg:postcode":"8225 KB",
    "sg:province":"NL.",
    "wof:name":"Remedial Teaching Flevoland",
    "wof:placetype":"venue"
},
  "geometry": {"coordinates":[5.506344,52.501537],"type":"Point"}
}