{
  "type": "Feature",
  "properties": {
    "addr:full":"Flessenbergerweg 39 Wapenveld Gelderland 8191 LH",
    "addr:housenumber":"39",
    "addr:postcode":"8191 lh",
    "addr:street":"Flessenbergerweg;Gelderland",
    "iso:country":"NL",
    "sg:address":"Flessenbergerweg 39",
    "sg:city":"Wapenveld",
    "sg:classifiers":[
        {
            "category":"Education",
            "subcategory":"Preschool",
            "type":"Public Place"
        }
    ],
    "sg:phone":"+31 38 447 8649",
    "sg:postcode":"8191 LH",
    "sg:province":"Gelderland",
    "sg:tags":[
        "kleuteronderwijs",
        "basis-"
    ],
    "wof:name":"Ds. Van Maasschool",
    "wof:placetype":"venue"
},
  "geometry": {"coordinates":[6.07377,52.424999],"type":"Point"}
}