{
  "type": "Feature",
  "properties": {
    "addr:full":"Kuyperstr 75 Nunspeet Gelderland 8072 BG",
    "addr:housenumber":"75",
    "addr:postcode":"8072",
    "addr:street":"Kuyperstr;Gelderland",
    "iso:country":"NL",
    "sg:address":"Kuyperstr 75",
    "sg:city":"Nunspeet",
    "sg:orig_category":"Beveiliging",
    "sg:phone":"+31 341 252 092",
    "sg:postcode":"8072 BG",
    "sg:province":"Gelderland",
    "wof:name":"Bbz",
    "wof:placetype":"venue"
},
  "geometry": {"coordinates":[5.807055,52.384186],"type":"Point"}
}