{
  "type": "Feature",
  "properties": {
    "iso:country":"NL",
    "sg:address":"Zweringweg 214",
    "sg:city":"Enschede",
    "sg:classifiers":[
        {
            "category":"Bakery",
            "type":"Food & Drink"
        }
    ],
    "sg:phone":"+31 53 431 1889",
    "sg:postcode":"7545 DA",
    "sg:province":"Overijssel",
    "sg:tags":[
        "brood",
        "banket"
    ],
    "wof:name":"Versbakkerij Savonije",
    "wof:placetype":"venue"
},
  "geometry": {"coordinates":[6.862658,52.210327],"type":"Point"}
}