{
  "type": "Feature",
  "properties": {
    "addr:full":"Polderweg 168 Den Helder Noord-Holland 1782 EC",
    "addr:housenumber":"168",
    "addr:postcode":"1782 ec",
    "addr:street":"Polderweg",
    "iso:country":"NL",
    "sg:address":"Polderweg 168",
    "sg:city":"Den Helder",
    "sg:orig_category":"Overheidsdiensten",
    "sg:phone":"+31 223 671 100",
    "sg:postcode":"1782 EC",
    "sg:province":"Noord-Holland",
    "wof:name":"Gemeente Den Helder Dienst Welzijn",
    "wof:placetype":"venue"
},
  "geometry": {"coordinates":[4.7580890656,52.9581604004],"type":"Point"}
}