{
  "type": "Feature",
  "properties": {
    "addr:full":"Antwerpsestrwg 394 Bergen Op Zoom North Brabant 4625 AE",
    "addr:housenumber":"394",
    "addr:postcode":"4625 ae",
    "iso:country":"NL",
    "sg:address":"Antwerpsestrwg 394",
    "sg:city":"Bergen Op Zoom",
    "sg:orig_category":"Fietsen En Bromfietsen",
    "sg:phone":"+31 164 233 413",
    "sg:postcode":"4625 AE",
    "sg:province":"North Brabant",
    "wof:name":"Besters En Zn",
    "wof:placetype":"venue"
},
  "geometry": {"coordinates":[4.301627,51.477928],"type":"Point"}
}