{
  "type": "Feature",
  "properties": {
    "addr:full":"Twentepoort O 22 Almelo NL.08 7609 RG",
    "addr:housenumber":"22;nl.08",
    "addr:postcode":"7609 rg",
    "addr:street":"Twentepoort O",
    "iso:country":"NL",
    "sg:address":"Twentepoort O 22",
    "sg:city":"Almelo",
    "sg:orig_category":"Adviesbureaus Personeel",
    "sg:phone":"+31 546 570 057",
    "sg:postcode":"7609 RG",
    "sg:province":"NL.08",
    "sg:website":"http://www.vandernoordt.nl",
    "wof:name":"Noordt Personeelsdiensten, Van Der",
    "wof:placetype":"venue"
},
  "geometry": {"coordinates":[6.648944,52.325607],"type":"Point"}
}