{
  "type": "Feature",
  "properties": {
    "addr:full":"Noorddijkerweg 52 Ursem Noord-Holland 1645 VG",
    "addr:housenumber":"52",
    "addr:postcode":"1645 vg",
    "addr:street":"Noorddijkerweg",
    "iso:country":"NL",
    "sg:address":"Noorddijkerweg 52",
    "sg:city":"Ursem",
    "sg:classifiers":[
        {
            "category":"Education",
            "subcategory":"Preschool",
            "type":"Public Place"
        }
    ],
    "sg:phone":"+31 72 502 1817",
    "sg:postcode":"1645 VG",
    "sg:province":"Noord-Holland",
    "sg:tags":[
        "kleuteronderwijs",
        "basis-"
    ],
    "wof:name":"Langereisschool",
    "wof:placetype":"venue"
},
  "geometry": {"coordinates":[4.891498,52.630127],"type":"Point"}
}