{
  "type": "Feature",
  "properties": {
    "addr:full":"Lange Hofstraat 29 Zutphen Gelderland 7201 HT",
    "addr:housenumber":"29",
    "addr:postcode":"7201 ht",
    "addr:street":"Lange Hofstraat;Gelderland",
    "iso:country":"NL",
    "sg:address":"Lange Hofstraat 29",
    "sg:city":"Zutphen",
    "sg:orig_category":"Werving And Selectie Van Tijdelijk Personeel And Uitzendkantoren",
    "sg:phone":"+31 575 542 077",
    "sg:postcode":"7201 HT",
    "sg:province":"Gelderland",
    "wof:name":"Flair Bv",
    "wof:placetype":"venue"
},
  "geometry": {"coordinates":[6.1950788498,52.1412010193],"type":"Point"}
}