{
  "type": "Feature",
  "properties": {
    "addr:full":"Baanstr 11Bis Utrecht Utrecht 3581 VS",
    "addr:housenumber":"11bis",
    "addr:postcode":"3581 vs",
    "iso:country":"NL",
    "sg:address":"Baanstr 11Bis",
    "sg:city":"Utrecht",
    "sg:orig_category":"Webdesign Bureaus",
    "sg:phone":"+31 30 258 1434",
    "sg:postcode":"3581 VS",
    "sg:province":"Utrecht",
    "sg:website":"http://www.plasticturtle.com",
    "wof:name":"Plasticturtle.Com",
    "wof:placetype":"venue"
},
  "geometry": {"coordinates":[5.1369299889,52.088470459],"type":"Point"}
}