{
  "type": "Feature",
  "properties": {
    "iso:country":"NL",
    "sg:address":"Slenterwg 8",
    "sg:city":"Zevenaar",
    "sg:orig_category":"Sportverenigingen En Ontspannings- Verenigingen",
    "sg:phone":"+31 316 525 651",
    "sg:postcode":"6905 DM",
    "sg:province":"Gelderland",
    "wof:name":"Crescendo Muziekver",
    "wof:placetype":"venue"
},
  "geometry": {"coordinates":[6.058424,51.91972],"type":"Point"}
}