{
  "type": "Feature",
  "properties": {
    "addr:full":"Amsterdamsewg 535 Amstelveen Noord-Holland 1181 BS",
    "addr:housenumber":"535",
    "addr:postcode":"1181 bs",
    "iso:country":"NL",
    "sg:address":"Amsterdamsewg 535",
    "sg:city":"Amstelveen",
    "sg:orig_category":"Makelaars En Adviseurs Onroerende Goederen",
    "sg:phone":"+31 20 647 8229",
    "sg:postcode":"1181 BS",
    "sg:province":"Noord-Holland",
    "wof:name":"Slot Makelaardij Og",
    "wof:placetype":"venue"
},
  "geometry": {"coordinates":[4.857165,52.321236],"type":"Point"}
}