{
  "type": "Feature",
  "properties": {
    "addr:full":"Jan Van Eyckstraat 44 Alkmaar Noord-Holland 1816 DB",
    "addr:housenumber":"44",
    "addr:postcode":"1816 db",
    "addr:street":"Jan Van Eyckstraat",
    "iso:country":"NL",
    "sg:address":"Jan Van Eyckstraat 44",
    "sg:city":"Alkmaar",
    "sg:orig_category":"Geluidsopnamen",
    "sg:phone":"+31 72 515 4528",
    "sg:postcode":"1816 DB",
    "sg:province":"Noord-Holland",
    "wof:name":"Randy Soundstudio",
    "wof:placetype":"venue"
},
  "geometry": {"coordinates":[4.72576,52.639553],"type":"Point"}
}