{
  "type": "Feature",
  "properties": {
    "addr:full":"Graanweg 7 Moerdijk North Brabant 4782 PP",
    "addr:housenumber":"7",
    "addr:postcode":"4782 pp",
    "addr:street":"Graanweg",
    "iso:country":"NL",
    "sg:address":"Graanweg 7",
    "sg:city":"Moerdijk",
    "sg:orig_category":"Metalen And Ertsen Gh",
    "sg:phone":"+31 183 505 177",
    "sg:postcode":"4782 PP",
    "sg:province":"North Brabant",
    "wof:name":"Solines Bv",
    "wof:placetype":"venue"
},
  "geometry": {"coordinates":[4.60909,51.68388],"type":"Point"}
}