{
  "type": "Feature",
  "properties": {
    "addr:full":"Bos En Lommerwg 244 Amsterdam Noord-Holland 1055 EJ",
    "addr:housenumber":"244",
    "addr:postcode":"1055 ej",
    "addr:street":"Bos En Lommerwg",
    "iso:country":"NL",
    "sg:address":"Bos En Lommerwg 244",
    "sg:city":"Amsterdam",
    "sg:orig_category":"Broodjeszaken",
    "sg:phone":"+31 20 686 7499",
    "sg:postcode":"1055 EJ",
    "sg:province":"Noord-Holland",
    "wof:name":"Broodje Bos & Lommer",
    "wof:placetype":"venue"
},
  "geometry": {"coordinates":[4.847754,52.378532],"type":"Point"}
}