{
  "type": "Feature",
  "properties": {
    "addr:full":"V Diemenstr 28 Amsterdam Noord-Holland 1013 NH",
    "addr:housenumber":"28",
    "addr:postcode":"1013 nh",
    "addr:street":"V Diemenstr",
    "iso:country":"NL",
    "sg:address":"V Diemenstr 28",
    "sg:city":"Amsterdam",
    "sg:classifiers":[
        {
            "category":"Shopping",
            "subcategory":"News",
            "type":"Retail Goods"
        }
    ],
    "sg:phone":"+31 20 531 3880",
    "sg:postcode":"1013 NH",
    "sg:province":"Noord-Holland",
    "sg:tags":[
        "maandbladen",
        "en",
        "week-"
    ],
    "sg:website":"http://www.emerce.nl",
    "wof:name":"Emerce Bv",
    "wof:placetype":"venue"
},
  "geometry": {"coordinates":[4.8931951523,52.3731193542],"type":"Point"}
}