{
  "type": "Feature",
  "properties": {
    "addr:full":"Burg De Vlugtln 71 Amsterdam Noord-Holland 1063 BH",
    "addr:housenumber":"71",
    "addr:postcode":"1063 bh",
    "iso:country":"NL",
    "sg:address":"Burg De Vlugtln 71",
    "sg:city":"Amsterdam",
    "sg:orig_category":"Postkantoren",
    "sg:phone":"+31 20 614 6421",
    "sg:postcode":"1063 BH",
    "sg:province":"Noord-Holland",
    "sg:website":"http://www.postkantoor.nl",
    "wof:name":"Postkantoor",
    "wof:placetype":"venue"
},
  "geometry": {"coordinates":[4.82559,52.3806],"type":"Point"}
}