{
  "type": "Feature",
  "properties": {
    "addr:full":"Dorpstr 68 Waddinxveen South Holland 2742 AK",
    "addr:housenumber":"68",
    "addr:postcode":"2742 ak",
    "addr:street":"Dorpstr",
    "iso:country":"NL",
    "sg:address":"Dorpstr 68",
    "sg:city":"Waddinxveen",
    "sg:orig_category":"Verhuur",
    "sg:phone":"+31 182 612 655",
    "sg:postcode":"2742 AK",
    "sg:province":"South Holland",
    "wof:name":"Zijl, B J",
    "wof:placetype":"venue"
},
  "geometry": {"coordinates":[4.641295,52.046879],"type":"Point"}
}