{
  "type": "Feature",
  "properties": {
    "addr:full":"Vosjacht 1 Giethoorn Overijssel 8355 CM",
    "addr:housenumber":"1",
    "addr:postcode":"8355 cm",
    "addr:street":"Vosjacht",
    "iso:country":"NL",
    "sg:address":"Vosjacht 1",
    "sg:city":"Giethoorn",
    "sg:orig_category":"Jachthavens - Jachtwerven",
    "sg:phone":"+31 521 361 688",
    "sg:postcode":"8355 CM",
    "sg:province":"Overijssel",
    "wof:name":"Brederwiede",
    "wof:placetype":"venue"
},
  "geometry": {"coordinates":[6.075132,52.721409],"type":"Point"}
}