{
  "type": "Feature",
  "properties": {
    "addr:full":"Spechtstraat 38 Goor NL.08 7471 HL",
    "addr:housenumber":"38;nl.08",
    "addr:postcode":"7471 hl",
    "addr:street":"Spechtstraat",
    "iso:country":"NL",
    "sg:address":"Spechtstraat 38",
    "sg:city":"Goor",
    "sg:orig_category":"Fotostudio'S And Fotografen",
    "sg:phone":"+31 547 275 417",
    "sg:postcode":"7471 HL",
    "sg:province":"NL.08",
    "wof:name":"Ruben Keestra Fotografie",
    "wof:placetype":"venue"
},
  "geometry": {"coordinates":[6.572287,52.243595],"type":"Point"}
}