{
  "type": "Feature",
  "properties": {
    "addr:full":"Asselsestr 66A Apeldoorn Gelderland 7311 EP",
    "addr:housenumber":"66a",
    "addr:postcode":"7311 ep",
    "addr:street":"Asselsestr;Gelderland",
    "iso:country":"NL",
    "sg:address":"Asselsestr 66A",
    "sg:city":"Apeldoorn",
    "sg:orig_category":"Zonweringen",
    "sg:phone":"+31 55 521 6165",
    "sg:postcode":"7311 EP",
    "sg:province":"Gelderland",
    "wof:name":"Dobbenberg",
    "wof:placetype":"venue"
},
  "geometry": {"coordinates":[5.95655,52.213394],"type":"Point"}
}