{
  "type": "Feature",
  "properties": {
    "iso:country":"NL",
    "sg:address":"Asselsestr 66A",
    "sg:city":"Apeldoorn",
    "sg:orig_category":"Zonweringen",
    "sg:phone":"+31 55 521 6165",
    "sg:postcode":"7311 EP",
    "sg:province":"Gelderland",
    "wof:name":"Dobbenberg",
    "wof:placetype":"venue"
},
  "geometry": {"coordinates":[5.95655,52.213394],"type":"Point"}
}