{
  "type": "Feature",
  "properties": {
    "addr:full":"Kleuvenstee 32 Assen Drenthe 9403 LR",
    "addr:housenumber":"32",
    "addr:postcode":"9403 lr",
    "addr:street":"Kleuvenstee",
    "iso:country":"NL",
    "sg:address":"Kleuvenstee 32",
    "sg:city":"Assen",
    "sg:orig_category":"Bloemen En Planten",
    "sg:phone":"+31 592 373 344",
    "sg:postcode":"9403 LR",
    "sg:province":"Drenthe",
    "wof:name":"Schuiten, Jan",
    "wof:placetype":"venue"
},
  "geometry": {"coordinates":[6.58498,53.017899],"type":"Point"}
}