{
  "type": "Feature",
  "properties": {
    "addr:full":"Beethovenring 6 Boxtel Noord-Brabant 5283 LH",
    "addr:housenumber":"6",
    "addr:postcode":"5283 lh",
    "addr:street":"Beethovenring",
    "iso:country":"NL",
    "sg:address":"Beethovenring 6",
    "sg:city":"Boxtel",
    "sg:orig_category":"Diverse Opleidingen And Onderwijs",
    "sg:phone":"+31 411 677 969",
    "sg:postcode":"5283 LH",
    "sg:province":"Noord-Brabant",
    "wof:name":"Bedrijfshulpverlening Traumacare",
    "wof:placetype":"venue"
},
  "geometry": {"coordinates":[5.335989,51.584827],"type":"Point"}
}