{
  "type": "Feature",
  "properties": {
    "addr:full":"Rozenstraat 23 Ittervoort Limburg 6014 AX",
    "addr:housenumber":"23",
    "addr:postcode":"6014 ax",
    "addr:street":"Rozenstraat",
    "iso:country":"NL",
    "sg:address":"Rozenstraat 23",
    "sg:city":"Ittervoort",
    "sg:orig_category":"Paramedische Behandelingen",
    "sg:phone":"+31 495 626 877",
    "sg:postcode":"6014 AX",
    "sg:province":"Limburg",
    "wof:name":"Logopediepraktijk G. Bijlmakers-Maassen",
    "wof:placetype":"venue"
},
  "geometry": {"coordinates":[5.820593,51.172668],"type":"Point"}
}