{
  "type": "Feature",
  "properties": {
    "addr:full":"Virulylaan 23 Leidschendam Zuid-Holland 2267 BR",
    "addr:housenumber":"23",
    "addr:postcode":"2267 br",
    "addr:street":"Virulylaan",
    "iso:country":"NL",
    "sg:address":"Virulylaan 23",
    "sg:city":"Leidschendam",
    "sg:orig_category":"Bedrijfs- And Managementsconsultants",
    "sg:phone":"+31 70 319 2966",
    "sg:postcode":"2267 BR",
    "sg:province":"Zuid-Holland",
    "wof:name":"Van Haersma Buma & Westerhout Bv",
    "wof:placetype":"venue"
},
  "geometry": {"coordinates":[4.357682,52.057457],"type":"Point"}
}