{
  "type": "Feature",
  "properties": {
    "addr:full":"Tesinkweg 40 Enschede Overijssel 7548 PH",
    "addr:housenumber":"40",
    "addr:postcode":"7548",
    "addr:street":"Tesinkweg",
    "iso:country":"NL",
    "sg:address":"Tesinkweg 40",
    "sg:city":"Enschede",
    "sg:orig_category":"Diverse Consumentenartikelen Gh",
    "sg:phone":"+31 53 428 1307",
    "sg:postcode":"7548 PH",
    "sg:province":"Overijssel",
    "wof:name":"Inter Globe/'T Spieker Bv",
    "wof:placetype":"venue"
},
  "geometry": {"coordinates":[6.806038,52.198952],"type":"Point"}
}