{
  "type": "Feature",
  "properties": {
    "iso:country":"NL",
    "sg:address":"Herman Heyermanslaan 8",
    "sg:city":"Eindhoven",
    "sg:orig_category":"Architecten",
    "sg:phone":"+31 40 211 5830",
    "sg:postcode":"5644 TH",
    "sg:province":"Noord-Brabant",
    "wof:name":"Tuinontwerp- En Adviesbureau Duizendblad",
    "wof:placetype":"venue"
},
  "geometry": {"coordinates":[5.483199,51.422531],"type":"Point"}
}