{
  "type": "Feature",
  "properties": {
    "addr:full":"Spinveld 21 Breda Noord-Brabant 4815 HR",
    "addr:housenumber":"21",
    "addr:postcode":"4815 hr",
    "addr:street":"Spinveld",
    "iso:country":"NL",
    "sg:address":"Spinveld 21",
    "sg:city":"Breda",
    "sg:orig_category":"Machineonderhoud En -Reparatie",
    "sg:phone":"+31 76 515 1433",
    "sg:postcode":"4815 HR",
    "sg:province":"Noord-Brabant",
    "wof:name":"Numac Bv",
    "wof:placetype":"venue"
},
  "geometry": {"coordinates":[4.757056,51.599937],"type":"Point"}
}