{
  "type": "Feature",
  "properties": {
    "addr:full":"Oranjeln 30 Rozenburg Zh Zuid-Holland 3181 HA",
    "addr:housenumber":"30",
    "addr:postcode":"zh;3181 ha",
    "addr:street":"Oranjeln",
    "iso:country":"NL",
    "sg:address":"Oranjeln 30",
    "sg:city":"Rozenburg Zh",
    "sg:orig_category":"Acupunctuur",
    "sg:phone":"+31 181 212 050",
    "sg:postcode":"3181 HA",
    "sg:province":"Zuid-Holland",
    "wof:name":"Uitert, J M Van",
    "wof:placetype":"venue"
},
  "geometry": {"coordinates":[4.241102,51.904442],"type":"Point"}
}