{
  "type": "Feature",
  "properties": {
    "addr:full":"Galvanistr 1 Leeuwarden Friesland 8912 AX",
    "addr:housenumber":"1",
    "addr:postcode":"8912 ax",
    "addr:street":"Galvanistr",
    "iso:country":"NL",
    "sg:address":"Galvanistr 1",
    "sg:city":"Leeuwarden",
    "sg:orig_category":"Bakkerijbenodigdheden En -Grondstoffen",
    "sg:phone":"+31 58 233 0660",
    "sg:postcode":"8912 AX",
    "sg:province":"Friesland",
    "wof:name":"Steensma Food Production Bv",
    "wof:placetype":"venue"
},
  "geometry": {"coordinates":[5.76935,53.188446],"type":"Point"}
}