{
  "type": "Feature",
  "properties": {
    "iso:country":"NL",
    "sg:address":"Hogelandseweg 19",
    "sg:city":"Nijmegen",
    "sg:orig_category":"Diverse Bedrijfsinstallaties Gh",
    "sg:phone":"+31 24 372 3620",
    "sg:postcode":"6545 AC",
    "sg:province":"Gelderland",
    "wof:name":"Briggs & Stratton Netherlands Bv",
    "wof:placetype":"venue"
},
  "geometry": {"coordinates":[5.810139,51.849682],"type":"Point"}
}