{
  "type": "Feature",
  "properties": {
    "addr:full":"Boorn 50 Rotterdam Zuid-Holland 3068 LA",
    "addr:housenumber":"50",
    "addr:postcode":"3068 la",
    "addr:street":"Boorn",
    "iso:country":"NL",
    "sg:address":"Boorn 50",
    "sg:city":"Rotterdam",
    "sg:orig_category":"Nagelstudio'S",
    "sg:phone":"+31 10 455 2867",
    "sg:postcode":"3068 LA",
    "sg:province":"Zuid-Holland",
    "wof:name":"Bi?n",
    "wof:placetype":"venue"
},
  "geometry": {"coordinates":[4.563873,51.961163],"type":"Point"}
}