{
  "type": "Feature",
  "properties": {
    "iso:country":"NL",
    "sg:address":"Driftwg 49",
    "sg:city":"Elst Ut",
    "sg:orig_category":"Verbouwingen",
    "sg:phone":"+31 318 472 509",
    "sg:postcode":"3921 DR",
    "sg:province":"Utrecht",
    "wof:name":"Hul, E G Van Den",
    "wof:placetype":"venue"
},
  "geometry": {"coordinates":[5.50711,51.990639],"type":"Point"}
}