{
  "type": "Feature",
  "properties": {
    "iso:country":"NL",
    "sg:address":"V Alphenstr 63S",
    "sg:city":"Voorburg",
    "sg:classifiers":[
        {
            "category":"Wholesale",
            "subcategory":"Meat",
            "type":"Manufacturing & Wholesale Goods"
        }
    ],
    "sg:phone":"+31 70 347 6431",
    "sg:postcode":"2274 NC",
    "sg:province":"Zuid-Holland",
    "sg:tags":[
        "regeltechniek",
        "en",
        "meet-"
    ],
    "sg:website":"http://www.tempcontrol.nl",
    "wof:name":"Tempcontrol Bv",
    "wof:placetype":"venue"
},
  "geometry": {"coordinates":[4.34952,52.073792],"type":"Point"}
}