{
  "type": "Feature",
  "properties": {
    "addr:full":"Kalmoes 47 Drachten Friesland 9207 EA",
    "addr:housenumber":"47",
    "addr:postcode":"9207 ea",
    "addr:street":"Kalmoes",
    "iso:country":"NL",
    "sg:address":"Kalmoes 47",
    "sg:city":"Drachten",
    "sg:orig_category":"Acupunctuur",
    "sg:phone":"+31 512 522 904",
    "sg:postcode":"9207 EA",
    "sg:province":"Friesland",
    "wof:name":"Lagendijk-Lakenberg Acupuncturist, A W",
    "wof:placetype":"venue"
},
  "geometry": {"coordinates":[6.102357,53.122505],"type":"Point"}
}