{
  "type": "Feature",
  "properties": {
    "addr:full":"Twikkelerwg 19 Markelo Overijssel 7475 ND",
    "addr:housenumber":"19",
    "addr:postcode":"7475 nd",
    "addr:street":"Twikkelerwg",
    "iso:country":"NL",
    "sg:address":"Twikkelerwg 19",
    "sg:city":"Markelo",
    "sg:classifiers":[
        {
            "category":"Travel",
            "subcategory":"Hotels & Motels",
            "type":"Entertainment"
        }
    ],
    "sg:phone":"+31 547 272 204",
    "sg:postcode":"7475 ND",
    "sg:province":"Overijssel",
    "wof:name":"Twikkel",
    "wof:placetype":"venue"
},
  "geometry": {"coordinates":[6.548935,52.229782],"type":"Point"}
}