{
  "type": "Feature",
  "properties": {
    "addr:full":"Postbus 200 Sliedrecht South Holland 3360 AE",
    "addr:housenumber":"200",
    "addr:postcode":"3360 ae",
    "addr:street":"Postbus",
    "iso:country":"NL",
    "sg:address":"Postbus 200",
    "sg:city":"Sliedrecht",
    "sg:orig_category":"Koeriersdiensten",
    "sg:phone":"+31 6 54695685",
    "sg:postcode":"3360 AE",
    "sg:province":"South Holland",
    "sg:website":"http://www.cargocab.nl",
    "wof:name":"Cargo-Cab-Courier",
    "wof:placetype":"venue"
},
  "geometry": {"coordinates":[4.772605,51.823555],"type":"Point"}
}