{
  "type": "Feature",
  "properties": {
    "addr:full":"Kerkweg 130 Kockengen Utrecht 3628 AS",
    "addr:housenumber":"130",
    "addr:postcode":"3628 as",
    "addr:street":"Kerkweg",
    "iso:country":"NL",
    "sg:address":"Kerkweg 130",
    "sg:city":"Kockengen",
    "sg:orig_category":"Loodgieterswerk, Verwarming And Sanitaire Installaties",
    "sg:phone":"+31 346 241 808",
    "sg:postcode":"3628 AS",
    "sg:province":"Utrecht",
    "wof:name":"Th. W. Nederend",
    "wof:placetype":"venue"
},
  "geometry": {"coordinates":[4.965454,52.150696],"type":"Point"}
}