{
  "type": "Feature",
  "properties": {
    "addr:full":"Drakenburgerwg 145 Baarn Utrecht 3741 GM",
    "addr:housenumber":"145",
    "addr:postcode":"3741 gm",
    "iso:country":"NL",
    "sg:address":"Drakenburgerwg 145",
    "sg:city":"Baarn",
    "sg:classifiers":[
        {
            "category":"Food & Beverages",
            "subcategory":"Fruits & Vegetables",
            "type":"Retail Goods"
        }
    ],
    "sg:phone":"+31 35 541 6040",
    "sg:postcode":"3741 GM",
    "sg:province":"Utrecht",
    "sg:tags":[
        "en",
        "groenten"
    ],
    "wof:name":"Wurff, Gebr Van Der",
    "wof:placetype":"venue"
},
  "geometry": {"coordinates":[5.260954,52.220562],"type":"Point"}
}