{
  "type": "Feature",
  "properties": {
    "iso:country":"NL",
    "sg:address":"Walstr 1A",
    "sg:city":"Oss",
    "sg:orig_category":"Bloemen En Planten",
    "sg:phone":"+31 412 642 217",
    "sg:postcode":"5341 CJ",
    "sg:province":"Virginia",
    "wof:name":"Klavertje, 'T",
    "wof:placetype":"venue"
},
  "geometry": {"coordinates":[-77.235214,38.312599],"type":"Point"}
}