{
  "type": "Feature",
  "properties": {
    "iso:country":"NL",
    "sg:address":"Wildenburgln 2",
    "sg:city":"Baarn",
    "sg:orig_category":"Bedrijfsopleidingen",
    "sg:phone":"+31 35 646 0207",
    "sg:postcode":"3744 MK",
    "sg:province":"Utrecht",
    "wof:name":"Ncg",
    "wof:placetype":"venue"
},
  "geometry": {"coordinates":[5.241609,52.219467],"type":"Point"}
}