{
  "type": "Feature",
  "properties": {
    "iso:country":"NL",
    "sg:address":"Ranonkelstraat 6",
    "sg:city":"Breda",
    "sg:orig_category":"Grafologen, Handlezers And Helderzienden",
    "sg:phone":"+31 76 522 5487",
    "sg:postcode":"4818 HP",
    "sg:province":"North Brabant",
    "wof:name":"T Verbond",
    "wof:placetype":"venue"
},
  "geometry": {"coordinates":[4.782008,51.578575],"type":"Point"}
}