{
  "type": "Feature",
  "properties": {
    "addr:full":"J V Burenln 198 Oldenzaal NL.08 7576 AW",
    "addr:housenumber":"198;nl.08",
    "addr:postcode":"7576 aw",
    "addr:street":"J;Burenln",
    "iso:country":"NL",
    "sg:address":"J V Burenln 198",
    "sg:city":"Oldenzaal",
    "sg:orig_category":"Postkantoren",
    "sg:phone":"+31 541 516 535",
    "sg:postcode":"7576 AW",
    "sg:province":"NL.08",
    "sg:website":"http://www.postkantoor.nl",
    "wof:name":"Postkantoor",
    "wof:placetype":"venue"
},
  "geometry": {"coordinates":[6.927277,52.309284],"type":"Point"}
}