{
  "type": "Feature",
  "properties": {
    "addr:full":"Poolsterstr 129 Rotterdam South Holland 3067 LX",
    "addr:housenumber":"129",
    "addr:postcode":"3067 lx",
    "iso:country":"NL",
    "sg:address":"Poolsterstr 129",
    "sg:city":"Rotterdam",
    "sg:orig_category":"Verlichting",
    "sg:phone":"+31 10 455 9370",
    "sg:postcode":"3067 LX",
    "sg:province":"South Holland",
    "wof:name":"Metro",
    "wof:placetype":"venue"
},
  "geometry": {"coordinates":[4.552797,51.950241],"type":"Point"}
}