{
  "type": "Feature",
  "properties": {
    "addr:full":"Lange Brinkweg 81 Soest Utrecht 3764 AB",
    "addr:housenumber":"81",
    "addr:postcode":"3764 ab",
    "addr:street":"Lange Brinkweg",
    "iso:country":"NL",
    "sg:address":"Lange Brinkweg 81",
    "sg:city":"Soest",
    "sg:orig_category":"Loodgieters- And Verwarmingsmateriaal Gh",
    "sg:phone":"+31 35 609 4411",
    "sg:postcode":"3764 AB",
    "sg:province":"Utrecht",
    "wof:name":"Gasrent-Stegas Bv",
    "wof:placetype":"venue"
},
  "geometry": {"coordinates":[5.307148,52.18145],"type":"Point"}
}