{
  "type": "Feature",
  "properties": {
    "addr:full":"Nykerkstr 7 Tilburg North Brabant 5045 MC",
    "addr:housenumber":"7",
    "addr:postcode":"5045 mc",
    "addr:street":"Nykerkstr",
    "iso:country":"NL",
    "sg:address":"Nykerkstr 7",
    "sg:city":"Tilburg",
    "sg:orig_category":"Adviesbureaus Bedrijfsorganisatie",
    "sg:phone":"+31 13 544 3101",
    "sg:postcode":"5045 MC",
    "sg:province":"North Brabant",
    "wof:name":"Zwaans",
    "wof:placetype":"venue"
},
  "geometry": {"coordinates":[4.98149,51.59214],"type":"Point"}
}