{
  "type": "Feature",
  "properties": {
    "addr:full":"Postbus 173 Eersel Noord-Brabant 5520 AD",
    "addr:housenumber":"173",
    "addr:postcode":"5520 ad",
    "addr:street":"Postbus",
    "iso:country":"NL",
    "sg:address":"Postbus 173",
    "sg:city":"Eersel",
    "sg:orig_category":"Adviesbureaus Automatisering",
    "sg:phone":"+31 497 531 900",
    "sg:postcode":"5520 AD",
    "sg:province":"Noord-Brabant",
    "sg:website":"http://www.client.nl",
    "wof:name":"Cli\u00ebnt Bv",
    "wof:placetype":"venue"
},
  "geometry": {"coordinates":[5.30905,51.358311],"type":"Point"}
}