{
  "type": "Feature",
  "properties": {
    "addr:full":"Htg Reinoudsngl 151 Venlo Limburg 5913 XD",
    "addr:housenumber":"151",
    "addr:postcode":"5913 xd",
    "iso:country":"NL",
    "sg:address":"Htg Reinoudsngl 151",
    "sg:city":"Venlo",
    "sg:orig_category":"Loopbaanbegeleiding",
    "sg:phone":"+31 77 351 8290",
    "sg:postcode":"5913 XD",
    "sg:province":"Limburg",
    "wof:name":"Canters, Hans",
    "wof:placetype":"venue"
},
  "geometry": {"coordinates":[6.17286,51.372421],"type":"Point"}
}