{
  "type": "Feature",
  "properties": {
    "addr:full":"Bylmerpln 719 Amsterdam Zuidoost Noord-Holland 1102 MA",
    "addr:housenumber":"719",
    "addr:postcode":"zuidoost;1102 ma",
    "iso:country":"NL",
    "sg:address":"Bylmerpln 719",
    "sg:city":"Amsterdam Zuidoost",
    "sg:orig_category":"Huishoudelijke Apparaten En Artikelen",
    "sg:phone":"+31 20 453 0458",
    "sg:postcode":"1102 MA",
    "sg:province":"Noord-Holland",
    "wof:name":"Blokker Bv",
    "wof:placetype":"venue"
},
  "geometry": {"coordinates":[4.955512,52.314281],"type":"Point"}
}