{
  "type": "Feature",
  "properties": {
    "addr:full":"Berkelstr 13/A Groningen Groningen 9725 GT",
    "addr:housenumber":"13 / a",
    "addr:postcode":"9725 gt",
    "addr:street":"Berkelstr",
    "iso:country":"NL",
    "sg:address":"Berkelstr 13/A",
    "sg:city":"Groningen",
    "sg:orig_category":"Adviesbureaus Bouwkunde",
    "sg:phone":"+31 50 527 6527",
    "sg:postcode":"9725 GT",
    "sg:province":"Groningen",
    "wof:name":"Bbv",
    "wof:placetype":"venue"
},
  "geometry": {"coordinates":[6.565476,53.207195],"type":"Point"}
}