{
  "type": "Feature",
  "properties": {
    "iso:country":"NL",
    "sg:address":"De Genestetstr 35",
    "sg:city":"Ridderkerk",
    "sg:orig_category":"Glazenwasserijen",
    "sg:phone":"+31 180 424 451",
    "sg:postcode":"2985 CE",
    "sg:province":"Zuid-Holland",
    "wof:name":"Oossanen Ridderkerk, Van",
    "wof:placetype":"venue"
},
  "geometry": {"coordinates":[4.601816,51.862537],"type":"Point"}
}