{
  "type": "Feature",
  "properties": {
    "addr:full":"Het Breed 699 Amsterdam Noord-Holland 1025 JA",
    "addr:housenumber":"699",
    "addr:postcode":"1025 ja",
    "addr:street":"Het Breed",
    "iso:country":"NL",
    "sg:address":"Het Breed 699",
    "sg:city":"Amsterdam",
    "sg:orig_category":"Verenigingen En Stichtingen",
    "sg:phone":"+31 20 632 4808",
    "sg:postcode":"1025 JA",
    "sg:province":"Noord-Holland",
    "wof:name":"Ver Van Eigenaren Flatgeb Werengouw",
    "wof:placetype":"venue"
},
  "geometry": {"coordinates":[4.938846,52.396599],"type":"Point"}
}