{
  "type": "Feature",
  "properties": {
    "iso:country":"NL",
    "sg:address":"Van Polanenpark 243",
    "sg:city":"Wassenaar",
    "sg:orig_category":"Kinderopvang Behalve Thuis",
    "sg:phone":"+31 70 511 3147",
    "sg:postcode":"2241 SL",
    "sg:province":"Zuid-Holland",
    "wof:name":"Stichting Kinderdagverblijven Wassenaar",
    "wof:placetype":"venue"
},
  "geometry": {"coordinates":[4.405351,52.151085],"type":"Point"}
}