{
  "type": "Feature",
  "properties": {
    "iso:country":"NL",
    "sg:address":"Groene Zoom 76",
    "sg:city":"Ten Boer",
    "sg:orig_category":"Boekhouders",
    "sg:phone":"+31 50 302 4474",
    "sg:postcode":"9791 BD",
    "sg:province":"Groningen",
    "wof:name":"Administratiekantoor Emka",
    "wof:placetype":"venue"
},
  "geometry": {"coordinates":[6.688239,53.273308],"type":"Point"}
}