{
  "type": "Feature",
  "properties": {
    "addr:full":"Kingsfordweg 1 Amsterdam North Holland 1043 GN",
    "addr:housenumber":"1",
    "addr:postcode":"1043 gn",
    "addr:street":"Kingsfordweg",
    "iso:country":"NL",
    "sg:address":"Kingsfordweg 1",
    "sg:city":"Amsterdam",
    "sg:orig_category":"Overheidsdiensten",
    "sg:phone":"+31 20 687 7999",
    "sg:postcode":"1043 GN",
    "sg:province":"North Holland",
    "wof:name":"Belastingdienst Particulieren Amsterdam",
    "wof:placetype":"venue"
},
  "geometry": {"coordinates":[4.8425478935,52.3883895874],"type":"Point"}
}