{
  "type": "Feature",
  "properties": {
    "iso:country":"NL",
    "sg:address":"N.Z. Voorburgwal 59",
    "sg:city":"Amsterdam",
    "sg:classifiers":[
        {
            "category":"Bars & Pubs",
            "type":"Food & Drink"
        }
    ],
    "sg:phone":"+31 20 624 6753",
    "sg:postcode":"1012 RD",
    "sg:province":"Noord-Holland",
    "wof:name":"The Grasshopper",
    "wof:placetype":"venue"
},
  "geometry": {"coordinates":[4.893195,52.373119],"type":"Point"}
}