{
  "type": "Feature",
  "properties": {
    "addr:full":"Bloemkamp 45 Drachten Friesland 9202 CB",
    "addr:housenumber":"45",
    "addr:postcode":"9202 cb",
    "addr:street":"Bloemkamp",
    "iso:country":"NL",
    "sg:address":"Bloemkamp 45",
    "sg:city":"Drachten",
    "sg:orig_category":"Graveerbedrijven",
    "sg:phone":"+31 512 515 400",
    "sg:postcode":"9202 CB",
    "sg:province":"Friesland",
    "wof:name":"Dick Dingshoff",
    "wof:placetype":"venue"
},
  "geometry": {"coordinates":[6.110446,53.112469],"type":"Point"}
}