{
  "type": "Feature",
  "properties": {
    "iso:country":"NL",
    "sg:address":"Moerven 102",
    "sg:city":"Veghel",
    "sg:orig_category":"Kappers",
    "sg:phone":"+31 413 352 110",
    "sg:postcode":"5464 PD",
    "sg:province":"Noord-Brabant",
    "wof:name":"Syl'S",
    "wof:placetype":"venue"
},
  "geometry": {"coordinates":[5.560924,51.631027],"type":"Point"}
}