{
  "type": "Feature",
  "properties": {
    "iso:country":"NL",
    "sg:address":"Grotestr 22",
    "sg:city":"Rossum Ov",
    "sg:orig_category":"Fietsen En Bromfietsen",
    "sg:phone":"+31 541 625 777",
    "sg:postcode":"7596 KE",
    "sg:province":"Overijssel",
    "sg:website":"http://www.kaptein-rijwielen.nl",
    "wof:name":"Kaptein",
    "wof:placetype":"venue"
},
  "geometry": {"coordinates":[6.924411,52.354511],"type":"Point"}
}