{
  "type": "Feature",
  "properties": {
    "addr:full":"Runstr 26 Amsterdam Noord-Holland 1016 GK",
    "addr:housenumber":"26",
    "addr:postcode":"1016 gk",
    "addr:street":"Runstr",
    "iso:country":"NL",
    "sg:address":"Runstr 26",
    "sg:city":"Amsterdam",
    "sg:orig_category":"Boeken En Tijdschriften",
    "sg:phone":"+31 20 622 4768",
    "sg:postcode":"1016 GK",
    "sg:province":"Noord-Holland",
    "wof:name":"Kookboekhandel, De",
    "wof:placetype":"venue"
},
  "geometry": {"coordinates":[4.883273,52.369041],"type":"Point"}
}