{
  "type": "Feature",
  "properties": {
    "addr:full":"Tormentil 6 Rotterdam South Holland 3191 KD",
    "addr:housenumber":"6",
    "addr:postcode":"3191 kd",
    "addr:street":"Tormentil",
    "iso:country":"NL",
    "sg:address":"Tormentil 6",
    "sg:city":"Rotterdam",
    "sg:orig_category":"Boekhouders",
    "sg:phone":"+31 10 472 2714",
    "sg:postcode":"3191 KD",
    "sg:province":"South Holland",
    "wof:name":"Administratiekantoor Ravin",
    "wof:placetype":"venue"
},
  "geometry": {"coordinates":[4.368113,51.861584],"type":"Point"}
}