{
  "type": "Feature",
  "properties": {
    "addr:full":"Duerswald 33 Wynjewoude Provincie Friesland 9241 GW",
    "addr:housenumber":"33",
    "addr:postcode":"9241 gw",
    "addr:street":"Duerswald;Provincie Friesland",
    "iso:country":"NL",
    "sg:address":"Duerswald 33",
    "sg:city":"Wynjewoude",
    "sg:orig_category":"Kampeerauto'S",
    "sg:phone":"+31 516 541 368",
    "sg:postcode":"9241 GW",
    "sg:province":"Provincie Friesland",
    "sg:website":"http://www.donkermotorhomes.nl",
    "wof:name":"Donker Motorhomes",
    "wof:placetype":"venue"
},
  "geometry": {"coordinates":[6.2221097946,53.0673561096],"type":"Point"}
}