{
  "type": "Feature",
  "properties": {
    "addr:full":"Van Woustraat 161 Amsterdam North Holland 1074 AK",
    "addr:housenumber":"161",
    "addr:postcode":"1074 ak",
    "addr:street":"Van Woustraat",
    "iso:country":"NL",
    "sg:address":"Van Woustraat 161",
    "sg:city":"Amsterdam",
    "sg:orig_category":"Opticiens",
    "sg:phone":"+31 20 676 8995",
    "sg:postcode":"1074 AK",
    "sg:province":"North Holland",
    "wof:name":"Hans Anders Opticiens",
    "wof:placetype":"venue"
},
  "geometry": {"coordinates":[4.9031338692,52.3523750305],"type":"Point"}
}