{
  "type": "Feature",
  "properties": {
    "iso:country":"NL",
    "sg:address":"Ambachtswei 11",
    "sg:city":"Joure",
    "sg:classifiers":[
        {
            "category":"Retail",
            "subcategory":"Auto Repair",
            "type":"Services"
        }
    ],
    "sg:phone":"+31 513 417 575",
    "sg:postcode":"8501 XA",
    "sg:province":"Provincie Friesland",
    "sg:tags":[
        "garage"
    ],
    "wof:name":"Hoekstra",
    "wof:placetype":"venue"
},
  "geometry": {"coordinates":[5.819586,52.963852],"type":"Point"}
}