{
  "type": "Feature",
  "properties": {
    "addr:full":"Diepenbrockln 15 Ede Gld Gelderland 6711 GL",
    "addr:housenumber":"15",
    "addr:postcode":"6711 gl",
    "addr:street":"Diepenbrockln;Gld Gelderland",
    "iso:country":"NL",
    "sg:address":"Diepenbrockln 15",
    "sg:city":"Ede Gld",
    "sg:orig_category":"Parketvloeren",
    "sg:phone":"+31 318 651 579",
    "sg:postcode":"6711 GL",
    "sg:province":"Gelderland",
    "wof:name":"Flart, De",
    "wof:placetype":"venue"
},
  "geometry": {"coordinates":[5.685464,52.042858],"type":"Point"}
}