{
  "type": "Feature",
  "properties": {
    "addr:full":"Hoogstraat 26 Nieuwpoort Zuid-Holland 2965 AL",
    "addr:housenumber":"26",
    "addr:postcode":"2965 al",
    "addr:street":"Hoogstraat",
    "iso:country":"NL",
    "sg:address":"Hoogstraat 26",
    "sg:city":"Nieuwpoort",
    "sg:orig_category":"Schoenen",
    "sg:phone":"+31 184 602 410",
    "sg:postcode":"2965 AL",
    "sg:province":"Zuid-Holland",
    "wof:name":"J.En M.Van Drenth Schoenen En Accessoire",
    "wof:placetype":"venue"
},
  "geometry": {"coordinates":[4.869911,51.935452],"type":"Point"}
}