{
  "type": "Feature",
  "properties": {
    "addr:full":"Koningstraat 2 A Beuningen Gld Gelderland 6641 KS",
    "addr:housenumber":"2 a",
    "addr:postcode":"6641 ks",
    "addr:street":"Koningstraat",
    "iso:country":"NL",
    "sg:address":"Koningstraat 2 A",
    "sg:city":"Beuningen Gld",
    "sg:orig_category":"Elektronische Bedrijfsinstallaties",
    "sg:phone":"+31 24 677 9697",
    "sg:postcode":"6641 KS",
    "sg:province":"Gelderland",
    "wof:name":"Fai Home Security",
    "wof:placetype":"venue"
},
  "geometry": {"coordinates":[5.743751,51.861359],"type":"Point"}
}