{
  "type": "Feature",
  "properties": {
    "addr:full":"Wg Pln 166 Amsterdam North Holland 1054 SC",
    "addr:housenumber":"166",
    "addr:postcode":"1054 sc",
    "addr:street":"Wg Pln",
    "iso:country":"NL",
    "sg:address":"Wg Pln 166",
    "sg:city":"Amsterdam",
    "sg:orig_category":"Adviesbureaus Bedrijfsorganisatie",
    "sg:phone":"+31 20 685 2988",
    "sg:postcode":"1054 SC",
    "sg:province":"North Holland",
    "sg:website":"http://www.trias-o.nl",
    "wof:name":"Trias-O Consulting",
    "wof:placetype":"venue"
},
  "geometry": {"coordinates":[4.871039,52.36425],"type":"Point"}
}