{
  "type": "Feature",
  "properties": {
    "iso:country":"NL",
    "sg:address":"Roerdompstr 26",
    "sg:city":"Stryen",
    "sg:orig_category":"Webdesign Bureaus",
    "sg:phone":"+31 78 674 7813",
    "sg:postcode":"3291 VL",
    "sg:province":"Zuid-Holland",
    "sg:website":"http://www.mve-webdesign.net",
    "wof:name":"Vermeulen",
    "wof:placetype":"venue"
},
  "geometry": {"coordinates":[4.5472698212,51.750831604],"type":"Point"}
}