{
  "type": "Feature",
  "properties": {
    "addr:full":"Leemstr 6C Roosendaal North Brabant 4705 RH",
    "addr:housenumber":"6c",
    "addr:postcode":"4705 rh",
    "addr:street":"Leemstr",
    "iso:country":"NL",
    "sg:address":"Leemstr 6C",
    "sg:city":"Roosendaal",
    "sg:orig_category":"Hang- En Sluitwerk - Fabrieken En Groothandel",
    "sg:phone":"+31 165 565 903",
    "sg:postcode":"4705 RH",
    "sg:province":"North Brabant",
    "sg:website":"http://www.eurobrass.nl",
    "wof:name":"Eurobrass Benelux Bv",
    "wof:placetype":"venue"
},
  "geometry": {"coordinates":[4.484729,51.545918],"type":"Point"}
}