{
  "type": "Feature",
  "properties": {
    "addr:full":"Sibadawei 26 Oosterend Gem Litt Friesland 8734 HE",
    "addr:housenumber":"26",
    "addr:postcode":"litt;8734 he",
    "addr:street":"Sibadawei",
    "iso:country":"NL",
    "sg:address":"Sibadawei 26",
    "sg:city":"Oosterend Gem Litt",
    "sg:orig_category":"Makelaars En Adviseurs Onroerende Goederen",
    "sg:phone":"+31 515 332 272",
    "sg:postcode":"8734 HE",
    "sg:province":"Friesland",
    "wof:name":"Vellinga, J",
    "wof:placetype":"venue"
},
  "geometry": {"coordinates":[5.617797,53.097633],"type":"Point"}
}