{
  "type": "Feature",
  "properties": {
    "addr:full":"Lange Noordstraat 37 Middelburg Zeeland 4331 CB",
    "addr:housenumber":"37",
    "addr:postcode":"4331 cb",
    "addr:street":"Lange Noordstraat",
    "iso:country":"NL",
    "sg:address":"Lange Noordstraat 37",
    "sg:city":"Middelburg",
    "sg:orig_category":"Boekhouders",
    "sg:phone":"+31 118 634 752",
    "sg:postcode":"4331 CB",
    "sg:province":"Zeeland",
    "wof:name":"Administratiekantoor Compurad Bv",
    "wof:placetype":"venue"
},
  "geometry": {"coordinates":[3.610538,51.500332],"type":"Point"}
}