{
  "type": "Feature",
  "properties": {
    "iso:country":"NL",
    "sg:address":"Rengerswg 64",
    "sg:city":"Oenkerk",
    "sg:orig_category":"Peuterspeelzalen",
    "sg:phone":"+31 58 256 1738",
    "sg:postcode":"9062 EG",
    "sg:province":"Friesland",
    "wof:name":"W\u00e2ldpykjes",
    "wof:placetype":"venue"
},
  "geometry": {"coordinates":[5.896616,53.251183],"type":"Point"}
}