{
  "type": "Feature",
  "properties": {
    "iso:country":"NL",
    "sg:address":"Schiestraat 14",
    "sg:city":"Rotterdam",
    "sg:orig_category":"Kantoorartikelen",
    "sg:phone":"+31 10 412 0708",
    "sg:postcode":"3013 AH",
    "sg:province":"Zuid-Holland",
    "wof:name":"D.M.S. Facilitaire Bedrijven C.V.",
    "wof:placetype":"venue"
},
  "geometry": {"coordinates":[4.4759831429,51.9255981445],"type":"Point"}
}