{
  "type": "Feature",
  "properties": {
    "addr:full":"Peperstr 32 Purmerend North Holland 1441 BJ",
    "addr:housenumber":"32",
    "addr:postcode":"1441 bj",
    "addr:street":"Peperstr",
    "iso:country":"NL",
    "sg:address":"Peperstr 32",
    "sg:city":"Purmerend",
    "sg:orig_category":"Zonweringen",
    "sg:phone":"+31 299 423 761",
    "sg:postcode":"1441 BJ",
    "sg:province":"North Holland",
    "wof:name":"Wolf & Zn, G De",
    "wof:placetype":"venue"
},
  "geometry": {"coordinates":[4.94614,52.510292],"type":"Point"}
}