{
  "type": "Feature",
  "properties": {
    "addr:full":"Bellinistraat 75 Alkmaar Noord-Holland 1817 JM",
    "addr:housenumber":"75",
    "addr:postcode":"1817 jm",
    "addr:street":"Bellinistraat",
    "iso:country":"NL",
    "sg:address":"Bellinistraat 75",
    "sg:city":"Alkmaar",
    "sg:classifiers":[
        {
            "category":"Fast Food",
            "type":"Food & Drink"
        }
    ],
    "sg:phone":"+31 72 515 1538",
    "sg:postcode":"1817 JM",
    "sg:province":"Noord-Holland",
    "sg:tags":[
        "afhaal",
        "restaurant"
    ],
    "wof:name":"Chinees-Indisch Restaurant Indrapoera",
    "wof:placetype":"venue"
},
  "geometry": {"coordinates":[4.73343,52.64447],"type":"Point"}
}