{
  "type": "Feature",
  "properties": {
    "addr:full":"Harpoenierstr 26 Den Helder Noord-Holland 1785 NB",
    "addr:housenumber":"26",
    "addr:postcode":"1785 nb",
    "addr:street":"Harpoenierstr",
    "iso:country":"NL",
    "sg:address":"Harpoenierstr 26",
    "sg:city":"Den Helder",
    "sg:orig_category":"Schoonheidsinstituten",
    "sg:phone":"+31 223 633 001",
    "sg:postcode":"1785 NB",
    "sg:province":"Noord-Holland",
    "wof:name":"Maud Barri?l Schoonheidssalon",
    "wof:placetype":"venue"
},
  "geometry": {"coordinates":[4.771375,52.939045],"type":"Point"}
}