{
  "type": "Feature",
  "properties": {
    "addr:full":"Rivierensngl 351 Helmond Noord-Brabant 5704 KP",
    "addr:housenumber":"351",
    "addr:postcode":"5704 kp",
    "iso:country":"NL",
    "sg:address":"Rivierensngl 351",
    "sg:city":"Helmond",
    "sg:orig_category":"Wegenbouw",
    "sg:phone":"+31 492 558 775",
    "sg:postcode":"5704 KP",
    "sg:province":"Noord-Brabant",
    "wof:name":"Braak, F M Van",
    "wof:placetype":"venue"
},
  "geometry": {"coordinates":[5.7008018494,51.4570655823],"type":"Point"}
}