{
  "type": "Feature",
  "properties": {
    "iso:country":"NL",
    "sg:address":"Ceintuurbaan 186-188",
    "sg:city":"Rotterdam",
    "sg:orig_category":"Onderhoudswerken",
    "sg:phone":"+31 10 418 9863",
    "sg:postcode":"3051 KD",
    "sg:province":"Zuid-Holland",
    "wof:name":"Moree En Znn Vof, A C",
    "wof:placetype":"venue"
},
  "geometry": {"coordinates":[4.472,51.941204],"type":"Point"}
}