{
  "type": "Feature",
  "properties": {
    "addr:full":"Ceintuurbaan 186-188 Rotterdam Zuid-Holland 3051 KD",
    "addr:housenumber":"186-188",
    "addr:postcode":"3051 kd",
    "addr:street":"Ceintuurbaan",
    "iso:country":"NL",
    "sg:address":"Ceintuurbaan 186-188",
    "sg:city":"Rotterdam",
    "sg:orig_category":"Onderhoudswerken",
    "sg:phone":"+31 10 418 9863",
    "sg:postcode":"3051 KD",
    "sg:province":"Zuid-Holland",
    "wof:name":"Moree En Znn Vof, A C",
    "wof:placetype":"venue"
},
  "geometry": {"coordinates":[4.472,51.941204],"type":"Point"}
}