{
  "type": "Feature",
  "properties": {
    "addr:full":"De Vennen 94 Delfzijl Groningen 9934 AH",
    "addr:housenumber":"94",
    "addr:postcode":"9934 ah",
    "addr:street":"De Vennen",
    "iso:country":"NL",
    "sg:address":"De Vennen 94",
    "sg:city":"Delfzijl",
    "sg:orig_category":"Logopedisten",
    "sg:phone":"+31 596 611 111",
    "sg:postcode":"9934 AH",
    "sg:province":"Groningen",
    "wof:name":"Logopedische Praktijk",
    "wof:placetype":"venue"
},
  "geometry": {"coordinates":[6.928577,53.333397],"type":"Point"}
}