{
  "type": "Feature",
  "properties": {
    "addr:full":"Genneperweg 9A Eindhoven North Brabant 5654 AG",
    "addr:housenumber":"9a",
    "addr:postcode":"5654",
    "addr:street":"Genneperweg",
    "iso:country":"NL",
    "sg:address":"Genneperweg 9A",
    "sg:city":"Eindhoven",
    "sg:orig_category":"Organisaties And Verenigingen",
    "sg:phone":"+31 40 255 0392",
    "sg:postcode":"5654 AG",
    "sg:province":"North Brabant",
    "wof:name":"Studentenhuis Theresia School",
    "wof:placetype":"venue"
},
  "geometry": {"coordinates":[5.4628710747,51.4237747192],"type":"Point"}
}