{
  "type": "Feature",
  "properties": {
    "iso:country":"NL",
    "sg:address":"Amersfoortsestr 15A",
    "sg:city":"Soesterberg",
    "sg:orig_category":"Verpakkingen En Verpakkingsmaterialen",
    "sg:phone":"+31 346 354 025",
    "sg:postcode":"3769 AD",
    "sg:province":"Utrecht",
    "wof:name":"Aluglas Bv",
    "wof:placetype":"venue"
},
  "geometry": {"coordinates":[5.291541,52.123489],"type":"Point"}
}