{
  "type": "Feature",
  "properties": {
    "addr:full":"Leidsewg 29Bis Utrecht Utrecht 3531 BA",
    "addr:housenumber":"29bis",
    "addr:postcode":"3531 ba",
    "iso:country":"NL",
    "sg:address":"Leidsewg 29Bis",
    "sg:city":"Utrecht",
    "sg:orig_category":"Adviesbureaus Bedrijfsorganisatie",
    "sg:phone":"+31 30 294 0535",
    "sg:postcode":"3531 BA",
    "sg:province":"Utrecht",
    "wof:name":"Blom, Ditter",
    "wof:placetype":"venue"
},
  "geometry": {"coordinates":[5.101529,52.089314],"type":"Point"}
}