{
  "type": "Feature",
  "properties": {
    "addr:full":"Krombraak 4 Oosterhout Nb Noord-Brabant 4906 CR",
    "addr:housenumber":"4",
    "addr:postcode":"4906 cr",
    "addr:street":"Krombraak",
    "iso:country":"NL",
    "sg:address":"Krombraak 4",
    "sg:city":"Oosterhout Nb",
    "sg:classifiers":[
        {
            "category":"Building & Trades",
            "subcategory":"Electrical",
            "type":"Services"
        }
    ],
    "sg:phone":"+31 162 436 360",
    "sg:postcode":"4906 CR",
    "sg:province":"Noord-Brabant",
    "sg:tags":[
        "distributor"
    ],
    "wof:name":"Remijsen Bv",
    "wof:placetype":"venue"
},
  "geometry": {"coordinates":[4.83941,51.651489],"type":"Point"}
}