{
  "type": "Feature",
  "properties": {
    "iso:country":"NL",
    "sg:address":"Bosschewg 2",
    "sg:city":"Vught",
    "sg:classifiers":[
        {
            "category":"Travel",
            "subcategory":"Hotels & Motels",
            "type":"Entertainment"
        }
    ],
    "sg:phone":"+31 73 658 7777",
    "sg:postcode":"5261 AA",
    "sg:province":"Noord-Brabant",
    "sg:website":"http://www.valk.com",
    "wof:name":"Hotel Vught",
    "wof:placetype":"venue"
},
  "geometry": {"coordinates":[5.29277,51.67038],"type":"Point"}
}