{
  "type": "Feature",
  "properties": {
    "addr:full":"Ingenieur Lelystraat 150 Heerlen Limburg 6419 XV",
    "addr:housenumber":"150",
    "addr:postcode":"6419 xv",
    "addr:street":"Ingenieur Lelystraat",
    "iso:country":"NL",
    "sg:address":"Ingenieur Lelystraat 150",
    "sg:city":"Heerlen",
    "sg:orig_category":"Paramedische Behandelingen",
    "sg:phone":"+31 45 571 7966",
    "sg:postcode":"6419 XV",
    "sg:province":"Limburg",
    "wof:name":"M.J. Schopping",
    "wof:placetype":"venue"
},
  "geometry": {"coordinates":[5.962344,50.873768],"type":"Point"}
}