{
  "type": "Feature",
  "properties": {
    "addr:full":"Arcadialn 26 Alkmaar Noord-Holland 1813 KN",
    "addr:housenumber":"26",
    "addr:postcode":"1813 kn",
    "addr:street":"Arcadialn",
    "iso:country":"NL",
    "sg:address":"Arcadialn 26",
    "sg:city":"Alkmaar",
    "sg:orig_category":"Adviesbureaus Bedrijfsorganisatie",
    "sg:phone":"+31 72 582 1020",
    "sg:postcode":"1813 KN",
    "sg:province":"Noord-Holland",
    "wof:name":"Rbg Change Company Bv",
    "wof:placetype":"venue"
},
  "geometry": {"coordinates":[4.746258,52.634361],"type":"Point"}
}