{
  "type": "Feature",
  "properties": {
    "iso:country":"NL",
    "sg:address":"Mauritsstraat 2-4",
    "sg:city":"Oosterhout Nb",
    "sg:orig_category":"Glaszetten",
    "sg:phone":"+31 162 427 670",
    "sg:postcode":"4905 AL",
    "sg:province":"North Brabant",
    "wof:name":"Jock'S Glasatelier",
    "wof:placetype":"venue"
},
  "geometry": {"coordinates":[4.850482,51.645035],"type":"Point"}
}