{
  "type": "Feature",
  "properties": {
    "addr:full":"De Meerleweg 1 Raalte Overijssel 8102 CZ",
    "addr:housenumber":"1",
    "addr:postcode":"8102",
    "iso:country":"NL",
    "sg:address":"De Meerleweg 1",
    "sg:city":"Raalte",
    "sg:orig_category":"Kinderopvang Behalve Thuis",
    "sg:phone":"+31 572 354 044",
    "sg:postcode":"8102 CZ",
    "sg:province":"Overijssel",
    "wof:name":"Peuterspeelzaal De Stoppeltjes",
    "wof:placetype":"venue"
},
  "geometry": {"coordinates":[6.27329,52.38607],"type":"Point"}
}