{
  "type": "Feature",
  "properties": {
    "iso:country":"NL",
    "sg:address":"Dammestr 1",
    "sg:city":"Lekkerkerk",
    "sg:orig_category":"Omroep",
    "sg:phone":"+31 180 664 080",
    "sg:postcode":"2941 BA",
    "sg:province":"Zuid-Holland",
    "wof:name":"Vrolek/Redelek",
    "wof:placetype":"venue"
},
  "geometry": {"coordinates":[4.689859,51.899975],"type":"Point"}
}