{
  "type": "Feature",
  "properties": {
    "iso:country":"NL",
    "sg:address":"Peperstraat 11",
    "sg:city":"Leeuwarden",
    "sg:orig_category":"Verlichting And Huishoudartikelen",
    "sg:phone":"+31 58 212 6860",
    "sg:postcode":"8911 HZ",
    "sg:province":"Friesland",
    "wof:name":"De Lampenier Handelsondern R. Borgerding",
    "wof:placetype":"venue"
},
  "geometry": {"coordinates":[5.797729,53.200958],"type":"Point"}
}