{
  "type": "Feature",
  "properties": {
    "addr:full":"Oudegr 33 Alkmaar North Holland 1811 CA",
    "addr:housenumber":"33",
    "addr:postcode":"1811 ca",
    "addr:street":"Oudegr",
    "iso:country":"NL",
    "sg:address":"Oudegr 33",
    "sg:city":"Alkmaar",
    "sg:orig_category":"Verhuizingen",
    "sg:phone":"+31 72 511 2614",
    "sg:postcode":"1811 CA",
    "sg:province":"North Holland",
    "wof:name":"Schipper & Znn, Fa D",
    "wof:placetype":"venue"
},
  "geometry": {"coordinates":[4.746258,52.634361],"type":"Point"}
}