{
  "type": "Feature",
  "properties": {
    "addr:full":"Ryksstrwg 75 Hardegaryp Friesland 9254 DB",
    "addr:housenumber":"75",
    "addr:postcode":"9254 db",
    "addr:street":"Ryksstrwg",
    "iso:country":"NL",
    "sg:address":"Ryksstrwg 75",
    "sg:city":"Hardegaryp",
    "sg:orig_category":"Kappers",
    "sg:phone":"+31 511 473 552",
    "sg:postcode":"9254 DB",
    "sg:province":"Friesland",
    "wof:name":"Tineke",
    "wof:placetype":"venue"
},
  "geometry": {"coordinates":[5.94131,53.215366],"type":"Point"}
}