{
  "type": "Feature",
  "properties": {
    "addr:full":"Burg De Withstr 41 De Bilt Utrecht 3732 EJ",
    "addr:housenumber":"41",
    "addr:postcode":"3732 ej",
    "iso:country":"NL",
    "sg:address":"Burg De Withstr 41",
    "sg:city":"De Bilt",
    "sg:classifiers":[
        {
            "category":"Personal",
            "subcategory":"Nail Salon",
            "type":"Services"
        }
    ],
    "sg:phone":"+31 30 221 0962",
    "sg:postcode":"3732 EJ",
    "sg:province":"Utrecht",
    "sg:tags":[
        "pedicure"
    ],
    "wof:name":"Janneke",
    "wof:placetype":"venue"
},
  "geometry": {"coordinates":[5.180099,52.105186],"type":"Point"}
}