{
  "type": "Feature",
  "properties": {
    "addr:full":"Boommarkt 5 Leiden South Holland 2311 EA",
    "addr:housenumber":"5",
    "addr:postcode":"2311 ea",
    "addr:street":"Boommarkt",
    "iso:country":"NL",
    "sg:address":"Boommarkt 5",
    "sg:city":"Leiden",
    "sg:orig_category":"Organisaties And Verenigingen",
    "sg:phone":"+31 71 514 4405",
    "sg:postcode":"2311 EA",
    "sg:province":"South Holland",
    "wof:name":"Quintus",
    "wof:placetype":"venue"
},
  "geometry": {"coordinates":[4.4861960411,52.1603813171],"type":"Point"}
}