{
  "type": "Feature",
  "properties": {
    "addr:full":"Koningstr 80 Arnhem Gelderland 6811 DK",
    "addr:housenumber":"80",
    "addr:postcode":"6811 dk",
    "addr:street":"Koningstr",
    "iso:country":"NL",
    "sg:address":"Koningstr 80",
    "sg:city":"Arnhem",
    "sg:orig_category":"Werving En Selectie",
    "sg:phone":"+31 26 370 1265",
    "sg:postcode":"6811 DK",
    "sg:province":"Gelderland",
    "sg:website":"http://www.stopinbraak.nl",
    "wof:name":"Stopinbraak.Nl",
    "wof:placetype":"venue"
},
  "geometry": {"coordinates":[5.9098391533,51.9816665649],"type":"Point"}
}