{
  "type": "Feature",
  "properties": {
    "addr:full":"Zuiderstationsstraat 7 Zwaagwesteinde Friesland 9271 HA",
    "addr:housenumber":"7",
    "addr:postcode":"9271 ha",
    "addr:street":"Zuiderstationsstraat",
    "iso:country":"NL",
    "sg:address":"Zuiderstationsstraat 7",
    "sg:city":"Zwaagwesteinde",
    "sg:orig_category":"Discountwinkels",
    "sg:phone":"+31 511 443 149",
    "sg:postcode":"9271 HA",
    "sg:province":"Friesland",
    "wof:name":"Hoogsteen'S Dumpstore",
    "wof:placetype":"venue"
},
  "geometry": {"coordinates":[6.035916,53.246841],"type":"Point"}
}