{
  "type": "Feature",
  "properties": {
    "addr:full":"Houtjeslaan 19 Schoorl Noord-Holland 1871 VC",
    "addr:housenumber":"19",
    "addr:postcode":"1871 vc",
    "addr:street":"Houtjeslaan",
    "iso:country":"NL",
    "sg:address":"Houtjeslaan 19",
    "sg:city":"Schoorl",
    "sg:orig_category":"Bedrijfs- And Managementsconsultants",
    "sg:phone":"+31 72 509 5541",
    "sg:postcode":"1871 VC",
    "sg:province":"Noord-Holland",
    "wof:name":"Van Rijswijk",
    "wof:placetype":"venue"
},
  "geometry": {"coordinates":[4.694844,52.710888],"type":"Point"}
}