{
  "type": "Feature",
  "properties": {
    "iso:country":"NL",
    "sg:address":"Schaesbergerweg 49",
    "sg:city":"Heerlen",
    "sg:orig_category":"Wasserettes And Stomerijen",
    "sg:phone":"+31 45 572 4706",
    "sg:postcode":"6415 AC",
    "sg:province":"Limburg",
    "wof:name":"Mengelers Stomerij Bv",
    "wof:placetype":"venue"
},
  "geometry": {"coordinates":[5.9884290695,50.8909759521],"type":"Point"}
}