{
  "type": "Feature",
  "properties": {
    "iso:country":"NL",
    "sg:address":"J Kriegestr 4",
    "sg:city":"Woerden",
    "sg:orig_category":"Adviesbureaus Bouwkosten",
    "sg:phone":"+31 348 411 805",
    "sg:postcode":"3443 TJ",
    "sg:province":"Utrecht",
    "wof:name":"Betacalc",
    "wof:placetype":"venue"
},
  "geometry": {"coordinates":[4.874433,52.08733],"type":"Point"}
}