{
  "type": "Feature",
  "properties": {
    "addr:full":"Plantsoenstr 5 Sappemeer Groningen 9611 EM",
    "addr:housenumber":"5",
    "addr:postcode":"9611 em",
    "addr:street":"Plantsoenstr",
    "iso:country":"NL",
    "sg:address":"Plantsoenstr 5",
    "sg:city":"Sappemeer",
    "sg:orig_category":"Begrafenisverzorging",
    "sg:phone":"+31 598 396 143",
    "sg:postcode":"9611 EM",
    "sg:province":"Groningen",
    "wof:name":"Sappemeer Onderlinge Ver",
    "wof:placetype":"venue"
},
  "geometry": {"coordinates":[6.781155,53.16404],"type":"Point"}
}