{
  "type": "Feature",
  "properties": {
    "addr:full":"Kleuvenstee 14 Assen Drenthe 9403 LR",
    "addr:housenumber":"14",
    "addr:postcode":"9403 lr",
    "addr:street":"Kleuvenstee",
    "iso:country":"NL",
    "sg:address":"Kleuvenstee 14",
    "sg:city":"Assen",
    "sg:orig_category":"Opticiens",
    "sg:phone":"+31 592 370 050",
    "sg:postcode":"9403 LR",
    "sg:province":"Drenthe",
    "wof:name":"See & Watch",
    "wof:placetype":"venue"
},
  "geometry": {"coordinates":[6.5847630501,53.0179634094],"type":"Point"}
}