{
  "type": "Feature",
  "properties": {
    "addr:full":"Borstelweg 29 Enschede Overijssel 7545 MR",
    "addr:housenumber":"29",
    "addr:postcode":"7545 mr",
    "addr:street":"Borstelweg",
    "iso:country":"NL",
    "sg:address":"Borstelweg 29",
    "sg:city":"Enschede",
    "sg:orig_category":"Artiesten",
    "sg:phone":"+31 53 432 2028",
    "sg:postcode":"7545 MR",
    "sg:province":"Overijssel",
    "wof:name":"Stichting De Werkhaven",
    "wof:placetype":"venue"
},
  "geometry": {"coordinates":[6.873169,52.218826],"type":"Point"}
}