{
  "type": "Feature",
  "properties": {
    "iso:country":"NL",
    "sg:address":"De Hooge Hoek 2A",
    "sg:city":"Renswoude",
    "sg:orig_category":"Pluimveebedrijven En -Handelaren",
    "sg:phone":"+31 318 578 250",
    "sg:postcode":"3927 GG",
    "sg:province":"Utrecht",
    "sg:website":"http://www.verbeek.nl",
    "wof:name":"Verbeek Bv",
    "wof:placetype":"venue"
},
  "geometry": {"coordinates":[5.537692,52.078354],"type":"Point"}
}