{
  "type": "Feature",
  "properties": {
    "addr:full":"Burg Eyckelhofstr 40 Millingen Ad Ryn Gelderland 6566 AV",
    "addr:housenumber":"40",
    "addr:postcode":"6566 av",
    "addr:street":"Burg;Gelderland",
    "iso:country":"NL",
    "sg:address":"Burg Eyckelhofstr 40",
    "sg:city":"Millingen Ad Ryn",
    "sg:orig_category":"Schilders",
    "sg:phone":"+31 481 431 619",
    "sg:postcode":"6566 AV",
    "sg:province":"Gelderland",
    "wof:name":"Dollevoet, Wynand",
    "wof:placetype":"venue"
},
  "geometry": {"coordinates":[6.046855,51.864063],"type":"Point"}
}