{
  "type": "Feature",
  "properties": {
    "iso:country":"NL",
    "sg:address":"Polderpln 114",
    "sg:city":"Hoofddorp",
    "sg:orig_category":"Wintersportkleding En -Artikelen",
    "sg:phone":"+31 23 565 1774",
    "sg:postcode":"2132 BE",
    "sg:province":"North Holland",
    "sg:website":"http://www.doublef.nl",
    "wof:name":"Double F",
    "wof:placetype":"venue"
},
  "geometry": {"coordinates":[4.6959972382,52.3027191162],"type":"Point"}
}