{
  "type": "Feature",
  "properties": {
    "addr:full":"S Gravendykwal 104 Rotterdam Zuid-Holland 3014 EJ",
    "addr:housenumber":"104",
    "addr:postcode":"3014 ej",
    "iso:country":"NL",
    "sg:address":"S Gravendykwal 104",
    "sg:city":"Rotterdam",
    "sg:orig_category":"Grafisch Ontwerpers",
    "sg:phone":"+31 10 241 7893",
    "sg:postcode":"3014 EJ",
    "sg:province":"Zuid-Holland",
    "wof:name":"Seesing, Theo",
    "wof:placetype":"venue"
},
  "geometry": {"coordinates":[4.463601,51.915039],"type":"Point"}
}