{
  "type": "Feature",
  "properties": {
    "addr:full":"Elzendwg 5 Bergharen Gelderland 6617 AV",
    "addr:housenumber":"5",
    "addr:postcode":"6617 av",
    "addr:street":"Elzendwg;Gelderland",
    "iso:country":"NL",
    "sg:address":"Elzendwg 5",
    "sg:city":"Bergharen",
    "sg:classifiers":[
        {
            "category":"Utilities",
            "subcategory":"Cable",
            "type":"Services"
        }
    ],
    "sg:phone":"+31 487 561 144",
    "sg:postcode":"6617 AV",
    "sg:province":"Gelderland",
    "sg:tags":[
        "masseur",
        "en",
        "heilgymnasten"
    ],
    "wof:name":"Smitse, De",
    "wof:placetype":"venue"
},
  "geometry": {"coordinates":[5.673253,51.854782],"type":"Point"}
}