{
  "type": "Feature",
  "properties": {
    "addr:full":"Grote Overstraat 4 Deventer Overijssel 7411 JC",
    "addr:housenumber":"4",
    "addr:postcode":"7411 jc",
    "addr:street":"Grote Overstraat",
    "iso:country":"NL",
    "sg:address":"Grote Overstraat 4",
    "sg:city":"Deventer",
    "sg:orig_category":"Verlichting And Huishoudartikelen",
    "sg:phone":"+31 570 613 325",
    "sg:postcode":"7411 JC",
    "sg:province":"Overijssel",
    "wof:name":"Woninginrichting Regenspurg",
    "wof:placetype":"venue"
},
  "geometry": {"coordinates":[6.156251,52.252003],"type":"Point"}
}