{
  "type": "Feature",
  "properties": {
    "iso:country":"NL",
    "sg:address":"Gerberaln 83",
    "sg:city":"Naaldwyk",
    "sg:orig_category":"Kassenbouw",
    "sg:phone":"+31 174 624 152",
    "sg:postcode":"2671 KC",
    "sg:province":"South Holland",
    "wof:name":"Moma",
    "wof:placetype":"venue"
},
  "geometry": {"coordinates":[4.205249,51.991398],"type":"Point"}
}