{
  "type": "Feature",
  "properties": {
    "addr:full":"Dorpsstr 72 A/B De Wyk Provincie Drenthe 7957 AW",
    "addr:housenumber":"72 a / b",
    "addr:postcode":"7957 aw",
    "addr:street":"Dorpsstr;De Wyk Provincie Drenthe",
    "iso:country":"NL",
    "sg:address":"Dorpsstr 72 A/B",
    "sg:city":"De Wyk",
    "sg:orig_category":"Bloemen En Planten",
    "sg:phone":"+31 522 442 640",
    "sg:postcode":"7957 AW",
    "sg:province":"Provincie Drenthe",
    "wof:name":"Bloem & Winkel, De",
    "wof:placetype":"venue"
},
  "geometry": {"coordinates":[6.28726,52.672199],"type":"Point"}
}