{
  "type": "Feature",
  "properties": {
    "addr:full":"Koningstr 24 Raamsdonksveer Noord-Brabant 4941 GW",
    "addr:housenumber":"24",
    "addr:postcode":"4941 gw",
    "addr:street":"Koningstr",
    "iso:country":"NL",
    "sg:address":"Koningstr 24",
    "sg:city":"Raamsdonksveer",
    "sg:orig_category":"Duikers",
    "sg:phone":"+31 162 522 247",
    "sg:postcode":"4941 GW",
    "sg:province":"Noord-Brabant",
    "wof:name":"Snoo, De",
    "wof:placetype":"venue"
},
  "geometry": {"coordinates":[4.870978,51.692883],"type":"Point"}
}