{
  "type": "Feature",
  "properties": {
    "addr:full":"Iependk 38 Goor NL.08 7471 BJ",
    "addr:housenumber":"38;nl.08",
    "addr:postcode":"7471 bj",
    "addr:street":"Iependk",
    "iso:country":"NL",
    "sg:address":"Iependk 38",
    "sg:city":"Goor",
    "sg:orig_category":"Wolartikelen En Breiwol",
    "sg:phone":"+31 547 275 885",
    "sg:postcode":"7471 BJ",
    "sg:province":"NL.08",
    "wof:name":"Marian",
    "wof:placetype":"venue"
},
  "geometry": {"coordinates":[6.5942168236,52.2327346802],"type":"Point"}
}