{
  "type": "Feature",
  "properties": {
    "addr:full":"Hoogstr 29 Montfoort Utrecht 3417 HA",
    "addr:housenumber":"29",
    "addr:postcode":"3417 ha",
    "addr:street":"Hoogstr",
    "iso:country":"NL",
    "sg:address":"Hoogstr 29",
    "sg:city":"Montfoort",
    "sg:orig_category":"Adviesbureaus Bedrijfsorganisatie",
    "sg:phone":"+31 348 474 410",
    "sg:postcode":"3417 HA",
    "sg:province":"Utrecht",
    "wof:name":"Leenders, Dr Frans H R",
    "wof:placetype":"venue"
},
  "geometry": {"coordinates":[4.946729,52.044067],"type":"Point"}
}