{
  "type": "Feature",
  "properties": {
    "addr:full":"Singel 27 Sneek Friesland 8601 AG",
    "addr:housenumber":"27",
    "addr:postcode":"8601",
    "addr:street":"Singel",
    "iso:country":"NL",
    "sg:address":"Singel 27",
    "sg:city":"Sneek",
    "sg:orig_category":"Behang Gh",
    "sg:phone":"+31 515 427 077",
    "sg:postcode":"8601 AG",
    "sg:province":"Friesland",
    "wof:name":"Wandmode Jan De Leeuw",
    "wof:placetype":"venue"
},
  "geometry": {"coordinates":[5.66252,53.031471],"type":"Point"}
}