{
  "type": "Feature",
  "properties": {
    "iso:country":"NL",
    "sg:address":"Ericawg 40",
    "sg:city":"Laren Nh",
    "sg:orig_category":"Bedrijfsmechanisatie En -Automatisering",
    "sg:phone":"+31 35 531 1220",
    "sg:postcode":"1251 WL",
    "sg:province":"North Holland",
    "wof:name":"World Wide Serv",
    "wof:placetype":"venue"
},
  "geometry": {"coordinates":[5.23464,52.249771],"type":"Point"}
}