{
  "type": "Feature",
  "properties": {
    "addr:full":"Ericawg 40 Laren Nh North Holland 1251 WL",
    "addr:housenumber":"40",
    "addr:postcode":"1251 wl",
    "addr:street":"Ericawg;Nh North",
    "iso:country":"NL",
    "sg:address":"Ericawg 40",
    "sg:city":"Laren Nh",
    "sg:orig_category":"Bedrijfsmechanisatie En -Automatisering",
    "sg:phone":"+31 35 531 1220",
    "sg:postcode":"1251 WL",
    "sg:province":"North Holland",
    "wof:name":"World Wide Serv",
    "wof:placetype":"venue"
},
  "geometry": {"coordinates":[5.23464,52.249771],"type":"Point"}
}