{
  "type": "Feature",
  "properties": {
    "addr:full":"Rubensstraat 35 Groningen Groningen 9718 MC",
    "addr:housenumber":"35",
    "addr:postcode":"9718 mc",
    "addr:street":"Rubensstraat",
    "iso:country":"NL",
    "sg:address":"Rubensstraat 35",
    "sg:city":"Groningen",
    "sg:orig_category":"Vertaal- And Tolkenbureaus",
    "sg:phone":"+31 50 314 3215",
    "sg:postcode":"9718 MC",
    "sg:province":"Groningen",
    "wof:name":"Arenaria Interpres",
    "wof:placetype":"venue"
},
  "geometry": {"coordinates":[6.547344,53.218006],"type":"Point"}
}