{
  "type": "Feature",
  "properties": {
    "addr:full":"V Oldenbarnev Str 27 Amsterdam Noord-Holland 1052 JR",
    "addr:housenumber":"27",
    "addr:postcode":"1052 jr",
    "addr:street":"Str",
    "iso:country":"NL",
    "sg:address":"V Oldenbarnev Str 27",
    "sg:city":"Amsterdam",
    "sg:orig_category":"Journalisten Freelance",
    "sg:phone":"+31 20 770 9630",
    "sg:postcode":"1052 JR",
    "sg:province":"Noord-Holland",
    "wof:name":"Italie Nieuws",
    "wof:placetype":"venue"
},
  "geometry": {"coordinates":[4.87379,52.377899],"type":"Point"}
}