{
  "type": "Feature",
  "properties": {
    "iso:country":"NL",
    "sg:address":"Scheibaan 5",
    "sg:city":"Oisterwijk",
    "sg:classifiers":[
        {
            "category":"Travel",
            "subcategory":"Hotels & Motels",
            "type":"Entertainment"
        }
    ],
    "sg:phone":"+31 13 528 2555",
    "sg:postcode":"5062 TM",
    "sg:province":"Noord-Brabant",
    "wof:name":"Hotel De Paddestoel",
    "wof:placetype":"venue"
},
  "geometry": {"coordinates":[5.227741,51.573463],"type":"Point"}
}