{
  "type": "Feature",
  "properties": {
    "addr:full":"Beukerstr 8 Zutphen Gelderland 7201 LD",
    "addr:housenumber":"8",
    "addr:postcode":"7201 ld",
    "addr:street":"Beukerstr;Gelderland",
    "iso:country":"NL",
    "sg:address":"Beukerstr 8",
    "sg:city":"Zutphen",
    "sg:orig_category":"Juweliers",
    "sg:phone":"+31 575 546 487",
    "sg:postcode":"7201 LD",
    "sg:province":"Gelderland",
    "wof:name":"Lucardi",
    "wof:placetype":"venue"
},
  "geometry": {"coordinates":[6.196221,52.142193],"type":"Point"}
}