{
  "type": "Feature",
  "properties": {
    "iso:country":"NL",
    "sg:address":"Stemerdingwg 12",
    "sg:city":"Soesterberg",
    "sg:orig_category":"Wijnkoperijen En -Groothandel",
    "sg:phone":"+31 35 603 7804",
    "sg:postcode":"3769 CE",
    "sg:province":"Utrecht",
    "wof:name":"Wijndoos, De",
    "wof:placetype":"venue"
},
  "geometry": {"coordinates":[5.2759151459,52.1229515076],"type":"Point"}
}