{
  "type": "Feature",
  "properties": {
    "addr:full":"Paradysstr 89 Voorburg Zuid-Holland 2275 EM",
    "addr:housenumber":"89",
    "addr:postcode":"2275 em",
    "addr:street":"Paradysstr",
    "iso:country":"NL",
    "sg:address":"Paradysstr 89",
    "sg:city":"Voorburg",
    "sg:orig_category":"Fotoreportages",
    "sg:phone":"+31 70 399 8222",
    "sg:postcode":"2275 EM",
    "sg:province":"Zuid-Holland",
    "wof:name":"Hercules",
    "wof:placetype":"venue"
},
  "geometry": {"coordinates":[4.349174,52.063297],"type":"Point"}
}