{
  "type": "Feature",
  "properties": {
    "addr:full":"M T Steynstr 55 Almelo Overijssel 7606 EB",
    "addr:housenumber":"55",
    "addr:postcode":"7606 eb",
    "iso:country":"NL",
    "sg:address":"M T Steynstr 55",
    "sg:city":"Almelo",
    "sg:orig_category":"Webdesign Bureaus",
    "sg:phone":"+31 546 455 234",
    "sg:postcode":"7606 EB",
    "sg:province":"Overijssel",
    "sg:website":"http://www.u-net-productions.nl",
    "wof:name":"U-Net Productions",
    "wof:placetype":"venue"
},
  "geometry": {"coordinates":[6.6590518951,52.3441200256],"type":"Point"}
}