{
  "type": "Feature",
  "properties": {
    "addr:full":"T Woud 28 Brielle Zuid-Holland 3232 LN",
    "addr:housenumber":"28",
    "addr:postcode":"3232 ln",
    "addr:street":"T Woud",
    "iso:country":"NL",
    "sg:address":"T Woud 28",
    "sg:city":"Brielle",
    "sg:orig_category":"Afdichtingen",
    "sg:phone":"+31 181 479 811",
    "sg:postcode":"3232 LN",
    "sg:province":"Zuid-Holland",
    "wof:name":"Rotary",
    "wof:placetype":"venue"
},
  "geometry": {"coordinates":[4.161907,51.889233],"type":"Point"}
}