{
  "type": "Feature",
  "properties": {
    "iso:country":"NL",
    "sg:address":"Velperbuitensngl 18",
    "sg:city":"Arnhem",
    "sg:orig_category":"Werving En Selectie",
    "sg:phone":"+31 26 353 1790",
    "sg:postcode":"6828 CV",
    "sg:province":"Gelderland",
    "sg:website":"http://www.flairoffice.nl",
    "wof:name":"Flair Tech Industry & Office",
    "wof:placetype":"venue"
},
  "geometry": {"coordinates":[5.9151668549,51.9823036194],"type":"Point"}
}