{
  "type": "Feature",
  "properties": {
    "iso:country":"NL",
    "sg:address":"Grypskerkstr 9",
    "sg:city":"Arnhem",
    "sg:orig_category":"Houtgroothandel Hardhout",
    "sg:phone":"+31 26 327 0102",
    "sg:postcode":"6835 DG",
    "sg:province":"Gelderland",
    "wof:name":"Robincap",
    "wof:placetype":"venue"
},
  "geometry": {"coordinates":[5.90143,51.950363],"type":"Point"}
}