{
  "type": "Feature",
  "properties": {
    "addr:full":"Scherpenzeelsewg 84 Goor Overijssel 7471 GS",
    "addr:housenumber":"84",
    "addr:postcode":"7471 gs",
    "addr:street":"Scherpenzeelsewg",
    "iso:country":"NL",
    "sg:address":"Scherpenzeelsewg 84",
    "sg:city":"Goor",
    "sg:orig_category":"Helderzienden",
    "sg:phone":"+31 547 271 887",
    "sg:postcode":"7471 GS",
    "sg:province":"Overijssel",
    "wof:name":"Zonnetje, Praktijk 'T",
    "wof:placetype":"venue"
},
  "geometry": {"coordinates":[6.570769,52.241127],"type":"Point"}
}