{
  "type": "Feature",
  "properties": {
    "addr:full":"Grotestraat 85 Tubbergen Overijssel 7651 CH",
    "addr:housenumber":"85",
    "addr:postcode":"7651",
    "addr:street":"Grotestraat",
    "iso:country":"NL",
    "sg:address":"Grotestraat 85",
    "sg:city":"Tubbergen",
    "sg:orig_category":"Glaszetten",
    "sg:phone":"+31 546 623 884",
    "sg:postcode":"7651 CH",
    "sg:province":"Overijssel",
    "wof:name":"D. Semprun Nicolas",
    "wof:placetype":"venue"
},
  "geometry": {"coordinates":[6.78175,52.408749],"type":"Point"}
}