{
  "type": "Feature",
  "properties": {
    "iso:country":"NL",
    "sg:address":"Dorpsstraat 151",
    "sg:city":"Helmond",
    "sg:orig_category":"Boekhouders",
    "sg:phone":"+31 492 539 452",
    "sg:postcode":"5708 GG",
    "sg:province":"Noord-Brabant",
    "wof:name":"Esdege",
    "wof:placetype":"venue"
},
  "geometry": {"coordinates":[5.625883,51.482609],"type":"Point"}
}