{
  "type": "Feature",
  "properties": {
    "addr:full":"Wildeman 6 Amsterdam North Holland 1068 BJ",
    "addr:housenumber":"6",
    "addr:postcode":"1068 bj",
    "addr:street":"Wildeman",
    "iso:country":"NL",
    "sg:address":"Wildeman 6",
    "sg:city":"Amsterdam",
    "sg:orig_category":"Loodgieterswerk, Verwarming And Sanitaire Installaties",
    "sg:phone":"+31 20 610 3537",
    "sg:postcode":"1068 BJ",
    "sg:province":"North Holland",
    "wof:name":"J.A.L. Zweerman",
    "wof:placetype":"venue"
},
  "geometry": {"coordinates":[4.796909,52.364376],"type":"Point"}
}