{
  "type": "Feature",
  "properties": {
    "addr:full":"Keizersdijk 44 Raamsdonksveer Noord-Brabant 4941 GG",
    "addr:housenumber":"44",
    "addr:postcode":"4941 gg",
    "addr:street":"Keizersdijk",
    "iso:country":"NL",
    "sg:address":"Keizersdijk 44",
    "sg:city":"Raamsdonksveer",
    "sg:orig_category":"Herenmodezaken",
    "sg:phone":"+31 162 516 090",
    "sg:postcode":"4941 GG",
    "sg:province":"Noord-Brabant",
    "wof:name":"Adam Herenkleding",
    "wof:placetype":"venue"
},
  "geometry": {"coordinates":[4.873203,51.698021],"type":"Point"}
}