{
  "type": "Feature",
  "properties": {
    "addr:full":"Grote Berg 18 Eindhoven Noord-Brabant 5611 KK",
    "addr:housenumber":"18",
    "addr:postcode":"5611 kk",
    "addr:street":"Grote Berg",
    "iso:country":"NL",
    "sg:address":"Grote Berg 18",
    "sg:city":"Eindhoven",
    "sg:orig_category":"Werving And Selectie Van Vast Personeel",
    "sg:phone":"+31 40 264 9749",
    "sg:postcode":"5611 KK",
    "sg:province":"Noord-Brabant",
    "wof:name":"Vitae",
    "wof:placetype":"venue"
},
  "geometry": {"coordinates":[5.4841051102,51.4344711304],"type":"Point"}
}