{
  "type": "Feature",
  "properties": {
    "addr:full":"Produktiewg 15 Alphen Aan Den Ryn Zuid-Holland 2404 CC",
    "addr:housenumber":"15",
    "addr:postcode":"2404 cc",
    "addr:street":"Produktiewg;Aan Den Ryn",
    "iso:country":"NL",
    "sg:address":"Produktiewg 15",
    "sg:city":"Alphen Aan Den Ryn",
    "sg:orig_category":"Puien",
    "sg:phone":"+31 172 432 621",
    "sg:postcode":"2404 CC",
    "sg:province":"Zuid-Holland",
    "wof:name":"Lieftink Bv",
    "wof:placetype":"venue"
},
  "geometry": {"coordinates":[4.642264,52.131996],"type":"Point"}
}