{
  "type": "Feature",
  "properties": {
    "addr:full":"Cellemuiden 44 Hasselt Overijssel 8061 RR",
    "addr:housenumber":"44",
    "addr:postcode":"8061 rr",
    "addr:street":"Cellemuiden",
    "iso:country":"NL",
    "sg:address":"Cellemuiden 44",
    "sg:city":"Hasselt",
    "sg:orig_category":"Scheepsmotoren - Reparatie",
    "sg:phone":"+31 38 477 1303",
    "sg:postcode":"8061 RR",
    "sg:province":"Overijssel",
    "wof:name":"Machinefabriek Hasselt",
    "wof:placetype":"venue"
},
  "geometry": {"coordinates":[6.083562,52.591763],"type":"Point"}
}