{
  "type": "Feature",
  "properties": {
    "addr:full":"Magdalenastr 23 Utrecht Utrecht 3512 NH",
    "addr:housenumber":"23",
    "addr:postcode":"3512 nh",
    "addr:street":"Magdalenastr",
    "iso:country":"NL",
    "sg:address":"Magdalenastr 23",
    "sg:city":"Utrecht",
    "sg:orig_category":"Meubelen - Fabrieken En Groothandel",
    "sg:phone":"+31 30 240 0350",
    "sg:postcode":"3512 NH",
    "sg:province":"Utrecht",
    "wof:name":"Vaart, Van Der",
    "wof:placetype":"venue"
},
  "geometry": {"coordinates":[5.127963,52.086994],"type":"Point"}
}