{
  "type": "Feature",
  "properties": {
    "addr:full":"Albrandswaardsedk 198 Poortugaal Zuid-Holland 3172 XB",
    "addr:housenumber":"198",
    "addr:postcode":"3172 xb",
    "iso:country":"NL",
    "sg:address":"Albrandswaardsedk 198",
    "sg:city":"Poortugaal",
    "sg:orig_category":"Sportverenigingen En Ontspannings- Verenigingen",
    "sg:phone":"+31 10 501 1794",
    "sg:postcode":"3172 XB",
    "sg:province":"Zuid-Holland",
    "wof:name":"Lr & Pc",
    "wof:placetype":"venue"
},
  "geometry": {"coordinates":[4.42242,51.844479],"type":"Point"}
}