{
  "type": "Feature",
  "properties": {
    "addr:full":"Brusselsestr 8 Maastricht Limburg 6211 PE",
    "addr:housenumber":"8",
    "addr:postcode":"6211 pe",
    "addr:street":"Brusselsestr",
    "iso:country":"NL",
    "sg:address":"Brusselsestr 8",
    "sg:city":"Maastricht",
    "sg:orig_category":"Displays, Showcards En Toonmaterialen",
    "sg:phone":"+31 43 321 2669",
    "sg:postcode":"6211 PE",
    "sg:province":"Limburg",
    "wof:name":"Vision",
    "wof:placetype":"venue"
},
  "geometry": {"coordinates":[5.684931,50.849705],"type":"Point"}
}