{
  "type": "Feature",
  "properties": {
    "addr:full":"Stevinstraat 278 'S Gravenhage Zuid-Holland 2587 EX",
    "addr:housenumber":"278 '",
    "addr:postcode":"2587 ex",
    "addr:street":"Stevinstraat",
    "iso:country":"NL",
    "sg:address":"Stevinstraat 278",
    "sg:city":"'S Gravenhage",
    "sg:orig_category":"Verhuisdiensten",
    "sg:phone":"+31 70 354 2539",
    "sg:postcode":"2587 EX",
    "sg:province":"Zuid-Holland",
    "wof:name":"Vogelaar Scheveningen",
    "wof:placetype":"venue"
},
  "geometry": {"coordinates":[4.295396,52.111538],"type":"Point"}
}