{
  "type": "Feature",
  "properties": {
    "addr:full":"Stampstr 28A Simpelveld Limburg 6369 BD",
    "addr:housenumber":"28a",
    "addr:postcode":"6369 bd",
    "addr:street":"Stampstr",
    "iso:country":"NL",
    "sg:address":"Stampstr 28A",
    "sg:city":"Simpelveld",
    "sg:orig_category":"Administratie- En Boekhoudkantoren",
    "sg:phone":"+31 45 544 5057",
    "sg:postcode":"6369 BD",
    "sg:province":"Limburg",
    "wof:name":"Actum",
    "wof:placetype":"venue"
},
  "geometry": {"coordinates":[5.977983,50.835022],"type":"Point"}
}