{
  "type": "Feature",
  "properties": {
    "addr:full":"Bloemgracht 181 Amsterdam Noord-Holland 1016 KN",
    "addr:housenumber":"181",
    "addr:postcode":"1016 kn",
    "addr:street":"Bloemgracht",
    "iso:country":"NL",
    "sg:address":"Bloemgracht 181",
    "sg:city":"Amsterdam",
    "sg:orig_category":"Geluidsopnamen",
    "sg:phone":"+31 20 638 9192",
    "sg:postcode":"1016 KN",
    "sg:province":"Noord-Holland",
    "wof:name":"Peter Warnier Studio Bv",
    "wof:placetype":"venue"
},
  "geometry": {"coordinates":[4.877586,52.373726],"type":"Point"}
}