{
  "type": "Feature",
  "properties": {
    "addr:full":"Honthem 51 Margraten Limburg 6269 NP",
    "addr:housenumber":"51",
    "addr:postcode":"6269 np",
    "addr:street":"Honthem",
    "iso:country":"NL",
    "sg:address":"Honthem 51",
    "sg:city":"Margraten",
    "sg:classifiers":[
        {
            "category":"Professional",
            "subcategory":"Accounting & Tax Preparation",
            "type":"Services"
        }
    ],
    "sg:phone":"+31 43 458 3181",
    "sg:postcode":"6269 NP",
    "sg:province":"Limburg",
    "sg:tags":[
        "accountant"
    ],
    "wof:name":"Ahwahnee Bv",
    "wof:placetype":"venue"
},
  "geometry": {"coordinates":[5.79372,50.817711],"type":"Point"}
}