{
  "type": "Feature",
  "properties": {
    "addr:full":"Postbus 193 Ysselstein Ut 3400 AD",
    "addr:housenumber":"193",
    "addr:postcode":"3400 ad",
    "addr:street":"Postbus",
    "iso:country":"NL",
    "sg:address":"Postbus 193",
    "sg:city":"Ysselstein Ut",
    "sg:orig_category":"Arbo- En Bedrijfsgezondheids- Diensten",
    "sg:phone":"+31 30 686 9260",
    "sg:postcode":"3400 AD",
    "wof:name":"Arbo Co\u00f6rdinatie Centrum Bv",
    "wof:placetype":"venue"
},
  "geometry": {"coordinates":[5.0281,52.02663],"type":"Point"}
}