{
  "type": "Feature",
  "properties": {
    "addr:full":"Oosterstr 59 Benningbroek North Holland 1654 JM",
    "addr:housenumber":"59",
    "addr:postcode":"1654 jm",
    "addr:street":"Oosterstr",
    "iso:country":"NL",
    "sg:address":"Oosterstr 59",
    "sg:city":"Benningbroek",
    "sg:orig_category":"Loonbedrijven",
    "sg:phone":"+31 229 591 769",
    "sg:postcode":"1654 JM",
    "sg:province":"North Holland",
    "wof:name":"Vlaar",
    "wof:placetype":"venue"
},
  "geometry": {"coordinates":[5.046794,52.704025],"type":"Point"}
}