{
  "type": "Feature",
  "properties": {
    "iso:country":"NL",
    "sg:address":"Mulderstraat 37",
    "sg:city":"Oosterend Nh",
    "sg:orig_category":"Overheidsdiensten",
    "sg:phone":"+31 222 318 691",
    "sg:postcode":"1794 AA",
    "sg:province":"Noord-Holland",
    "wof:name":"Bijenkorf",
    "wof:placetype":"venue"
},
  "geometry": {"coordinates":[4.8745541573,53.0858535767],"type":"Point"}
}