{
  "type": "Feature",
  "properties": {
    "iso:country":"NL",
    "sg:address":"Schoolstr 5A",
    "sg:city":"De Bilt",
    "sg:orig_category":"Loodgieters",
    "sg:phone":"+31 30 220 0159",
    "sg:postcode":"3732 DV",
    "sg:province":"Utrecht",
    "wof:name":"Waveren, Van",
    "wof:placetype":"venue"
},
  "geometry": {"coordinates":[5.181588,52.1064],"type":"Point"}
}