{
  "type": "Feature",
  "properties": {
    "addr:full":"Emmaplein 1 Groningen Groningen 9711 AP",
    "addr:housenumber":"1",
    "addr:postcode":"9711 ap",
    "addr:street":"Emmaplein",
    "iso:country":"NL",
    "sg:address":"Emmaplein 1",
    "sg:city":"Groningen",
    "sg:orig_category":"Werving And Selectie Van Tijdelijk Personeel And Uitzendkantoren",
    "sg:phone":"+31 50 318 7900",
    "sg:postcode":"9711 AP",
    "sg:province":"Groningen",
    "wof:name":"Mf Financieel",
    "wof:placetype":"venue"
},
  "geometry": {"coordinates":[6.5620279312,53.2136764526],"type":"Point"}
}