{
  "type": "Feature",
  "properties": {
    "addr:full":"Grevelingenstraat 10 Utrecht Utrecht 3522 PR",
    "addr:housenumber":"10",
    "addr:postcode":"3522 pr",
    "addr:street":"Grevelingenstraat",
    "iso:country":"NL",
    "sg:address":"Grevelingenstraat 10",
    "sg:city":"Utrecht",
    "sg:orig_category":"Paramedische Behandelingen",
    "sg:phone":"+31 30 289 0891",
    "sg:postcode":"3522 PR",
    "sg:province":"Utrecht",
    "wof:name":"Drs C.Y Abelsma",
    "wof:placetype":"venue"
},
  "geometry": {"coordinates":[5.116017,52.075836],"type":"Point"}
}