{
  "type": "Feature",
  "properties": {
    "addr:full":"Copernicusln 73 S Hertogenbosch Noord-Brabant 5223 EB",
    "addr:housenumber":"73",
    "addr:postcode":"5223 eb",
    "addr:street":"Copernicusln;S Hertogenbosch",
    "iso:country":"NL",
    "sg:address":"Copernicusln 73",
    "sg:city":"S Hertogenbosch",
    "sg:orig_category":"Verenigingen En Stichtingen",
    "sg:phone":"+31 73 622 1308",
    "sg:postcode":"5223 EB",
    "sg:province":"Noord-Brabant",
    "wof:name":"Nederlandse Helsinki Unie, Sticht",
    "wof:placetype":"venue"
},
  "geometry": {"coordinates":[5.28903,51.695515],"type":"Point"}
}