{
  "type": "Feature",
  "properties": {
    "addr:full":"R Visserstr 21 Achterveld Utrecht 3791 VV",
    "addr:housenumber":"21",
    "addr:postcode":"3791 vv",
    "addr:street":"Achterveld",
    "iso:country":"NL",
    "sg:address":"R Visserstr 21",
    "sg:city":"Achterveld",
    "sg:orig_category":"Adviesbureaus Personeel",
    "sg:phone":"+31 6 20300481",
    "sg:postcode":"3791 VV",
    "sg:province":"Utrecht",
    "wof:name":"Oest, Hanneke Van Der",
    "wof:placetype":"venue"
},
  "geometry": {"coordinates":[5.499809,52.136375],"type":"Point"}
}