{
  "type": "Feature",
  "properties": {
    "iso:country":"NL",
    "sg:address":"Linschotenstr 1",
    "sg:city":"Rotterdam",
    "sg:orig_category":"Verbouwingen",
    "sg:phone":"+31 6 54356034",
    "sg:postcode":"3044 AV",
    "sg:province":"South Holland",
    "wof:name":"Baarle, C A Van",
    "wof:placetype":"venue"
},
  "geometry": {"coordinates":[4.424535,51.930618],"type":"Point"}
}