{
  "type": "Feature",
  "properties": {
    "iso:country":"NL",
    "sg:address":"Zaanweg 115",
    "sg:city":"Wormerveer",
    "sg:orig_category":"Huishoudapparatuur, Televisies And Radio'S",
    "sg:phone":"+31 75 621 8576",
    "sg:postcode":"1521 DR",
    "sg:province":"North Holland",
    "wof:name":"Electronica J.C. De Graaf Bv",
    "wof:placetype":"venue"
},
  "geometry": {"coordinates":[4.790583,52.491951],"type":"Point"}
}