{
  "type": "Feature",
  "properties": {
    "addr:full":"De Beuk 15 Rhoon Zuid-Holland 3161 JG",
    "addr:housenumber":"15",
    "addr:postcode":"3161 jg",
    "addr:street":"De Beuk",
    "iso:country":"NL",
    "sg:address":"De Beuk 15",
    "sg:city":"Rhoon",
    "sg:orig_category":"Verhuur",
    "sg:phone":"+31 10 472 2144",
    "sg:postcode":"3161 JG",
    "sg:province":"Zuid-Holland",
    "sg:website":"http://www.mandemakerattractieverhuur.nl",
    "wof:name":"Mandemaker, Attractieverhuur",
    "wof:placetype":"venue"
},
  "geometry": {"coordinates":[4.427428,51.851681],"type":"Point"}
}