{
  "type": "Feature",
  "properties": {
    "addr:full":"Kastanjeln 6 Ridderkerk South Holland 2982 CM",
    "addr:housenumber":"6",
    "addr:postcode":"2982 cm",
    "addr:street":"Kastanjeln",
    "iso:country":"NL",
    "sg:address":"Kastanjeln 6",
    "sg:city":"Ridderkerk",
    "sg:orig_category":"Waterbouwkundige Werken",
    "sg:phone":"+31 180 441 720",
    "sg:postcode":"2982 CM",
    "sg:province":"South Holland",
    "wof:name":"Koegorspolder",
    "wof:placetype":"venue"
},
  "geometry": {"coordinates":[4.5890579224,51.8768577576],"type":"Point"}
}