{
  "type": "Feature",
  "properties": {
    "addr:full":"L V Leydenhage 12 Nieuwegein Utrecht 3437 NS",
    "addr:housenumber":"12",
    "addr:postcode":"3437 ns",
    "addr:street":"L;Leydenhage",
    "iso:country":"NL",
    "sg:address":"L V Leydenhage 12",
    "sg:city":"Nieuwegein",
    "sg:orig_category":"Onroerende Goederen",
    "sg:phone":"+31 30 603 5515",
    "sg:postcode":"3437 NS",
    "sg:province":"Utrecht",
    "wof:name":"Brandon & Lee Bv",
    "wof:placetype":"venue"
},
  "geometry": {"coordinates":[5.082197,52.027325],"type":"Point"}
}