{
  "type": "Feature",
  "properties": {
    "iso:country":"NL",
    "sg:address":"Ericasestraat 109",
    "sg:city":"Erica",
    "sg:orig_category":"Sportterreinen And Installaties Behalve Sportcentra",
    "sg:phone":"+31 591 301 352",
    "sg:postcode":"7887 GD",
    "sg:province":"Drenthe",
    "wof:name":"Manege Rietzicht",
    "wof:placetype":"venue"
},
  "geometry": {"coordinates":[6.917301,52.735916],"type":"Point"}
}