{
  "type": "Feature",
  "properties": {
    "addr:full":"Meeuwensngl 39 Rozenburg Zh Zuid-Holland 3181 SK",
    "addr:housenumber":"39",
    "addr:postcode":"zh",
    "addr:street":"Meeuwensngl;3181",
    "iso:country":"NL",
    "sg:address":"Meeuwensngl 39",
    "sg:city":"Rozenburg Zh",
    "sg:orig_category":"Adviesbureaus Bouwkunde",
    "sg:phone":"+31 181 215 723",
    "sg:postcode":"3181 SK",
    "sg:province":"Zuid-Holland",
    "wof:name":"Abt",
    "wof:placetype":"venue"
},
  "geometry": {"coordinates":[4.249615,51.904446],"type":"Point"}
}