{
  "type": "Feature",
  "properties": {
    "addr:full":"Europaboulev 337 Alkmaar Noord-Holland 1825 RK",
    "addr:housenumber":"337",
    "addr:postcode":"1825 rk",
    "iso:country":"NL",
    "sg:address":"Europaboulev 337",
    "sg:city":"Alkmaar",
    "sg:orig_category":"Fotozaken",
    "sg:phone":"+31 72 562 3103",
    "sg:postcode":"1825 RK",
    "sg:province":"Noord-Holland",
    "wof:name":"Flandria",
    "wof:placetype":"venue"
},
  "geometry": {"coordinates":[4.756,52.655354],"type":"Point"}
}