{
  "type": "Feature",
  "properties": {
    "addr:full":"Bisonspoor 1072 Maarssen Noord-Holland 3605 KJ",
    "addr:housenumber":"1072",
    "addr:postcode":"3605 kj",
    "addr:street":"Bisonspoor",
    "iso:country":"NL",
    "sg:address":"Bisonspoor 1072",
    "sg:city":"Maarssen",
    "sg:classifiers":[
        {
            "category":"Farming",
            "subcategory":"Fish & Marine Products",
            "type":"Manufacturing & Wholesale Goods"
        }
    ],
    "sg:phone":"+31 346 566 552",
    "sg:postcode":"3605 KJ",
    "sg:province":"Noord-Holland",
    "sg:tags":[
        "vi"
    ],
    "wof:name":"Volendammer Vishandel",
    "wof:placetype":"venue"
},
  "geometry": {"coordinates":[5.031087,52.134968],"type":"Point"}
}