{
  "type": "Feature",
  "properties": {
    "addr:full":"Cattepoelsewg 139 Arnhem Gelderland 6815 CA",
    "addr:housenumber":"139",
    "addr:postcode":"6815 ca",
    "iso:country":"NL",
    "sg:address":"Cattepoelsewg 139",
    "sg:city":"Arnhem",
    "sg:orig_category":"Onteigening",
    "sg:phone":"+31 26 370 1744",
    "sg:postcode":"6815 CA",
    "sg:province":"Gelderland",
    "sg:website":"http://www.vdh-m.nl",
    "wof:name":"Hoeven & Machielsen, Van Der",
    "wof:placetype":"venue"
},
  "geometry": {"coordinates":[5.912375,52.001446],"type":"Point"}
}