{
  "type": "Feature",
  "properties": {
    "addr:full":"Past Harkxpln 4 Eindhoven Noord-Brabant 5614 HX",
    "addr:housenumber":"4",
    "addr:postcode":"5614 hx",
    "iso:country":"NL",
    "sg:address":"Past Harkxpln 4",
    "sg:city":"Eindhoven",
    "sg:orig_category":"Makelaars En Adviseurs Onroerende Goederen",
    "sg:phone":"+31 40 212 9088",
    "sg:postcode":"5614 HX",
    "sg:province":"Noord-Brabant",
    "sg:website":"http://www.slippensvermeer.nl",
    "wof:name":"Slippens Vermeer",
    "wof:placetype":"venue"
},
  "geometry": {"coordinates":[5.488163,51.429264],"type":"Point"}
}