{
  "type": "Feature",
  "properties": {
    "addr:full":"Napoleonswg 62 Haelen Limburg 6081 AD",
    "addr:housenumber":"62",
    "addr:postcode":"6081 ad",
    "addr:street":"Napoleonswg",
    "iso:country":"NL",
    "sg:address":"Napoleonswg 62",
    "sg:city":"Haelen",
    "sg:orig_category":"Houtgroothandel",
    "sg:phone":"+31 475 595 959",
    "sg:postcode":"6081 AD",
    "sg:province":"Limburg",
    "wof:name":"Brentjens Bv",
    "wof:placetype":"venue"
},
  "geometry": {"coordinates":[5.950922,51.227764],"type":"Point"}
}