{
  "type": "Feature",
  "properties": {
    "addr:full":"Herkingenstr 6 Rotterdam Zuid-Holland 3086 BE",
    "addr:housenumber":"6",
    "addr:postcode":"3086",
    "addr:street":"Herkingenstr",
    "iso:country":"NL",
    "sg:address":"Herkingenstr 6",
    "sg:city":"Rotterdam",
    "sg:orig_category":"Verenigingen En Stichtingen",
    "sg:phone":"+31 10 410 2755",
    "sg:postcode":"3086 BE",
    "sg:province":"Zuid-Holland",
    "wof:name":"Pendrecht 2 En 3, Bewonersver",
    "wof:placetype":"venue"
},
  "geometry": {"coordinates":[-73.928871,42.775188],"type":"Point"}
}