{
  "type": "Feature",
  "properties": {
    "iso:country":"NL",
    "sg:address":"Leeuweriklaan 19",
    "sg:city":"Hoogeveen",
    "sg:orig_category":"Kinderopvang Behalve Thuis",
    "sg:phone":"+31 528 265 543",
    "sg:postcode":"7905 CA",
    "sg:province":"Drenthe",
    "wof:name":"De Krulekoare",
    "wof:placetype":"venue"
},
  "geometry": {"coordinates":[6.503039,52.71645],"type":"Point"}
}