{
  "type": "Feature",
  "properties": {
    "addr:full":"De Leemkuil 6 Laren Nh Noord-Holland 1251 AR",
    "addr:housenumber":"6",
    "addr:postcode":"1251",
    "addr:street":"De Leemkuil",
    "iso:country":"NL",
    "sg:address":"De Leemkuil 6",
    "sg:city":"Laren Nh",
    "sg:orig_category":"Advocaten And Juridische Adviseurs",
    "sg:phone":"+31 35 538 9310",
    "sg:postcode":"1251 AR",
    "sg:province":"Noord-Holland",
    "wof:name":"Advocatenkantoor Mr. De Meijer En Overbeek",
    "wof:placetype":"venue"
},
  "geometry": {"coordinates":[5.223093,52.262653],"type":"Point"}
}