{
  "type": "Feature",
  "properties": {
    "addr:full":"Stationswg 44 Oostvoorne Zuid-Holland 3233 CT",
    "addr:housenumber":"44",
    "addr:postcode":"3233 ct",
    "addr:street":"Stationswg",
    "iso:country":"NL",
    "sg:address":"Stationswg 44",
    "sg:city":"Oostvoorne",
    "sg:orig_category":"Artsen - Huisartsen",
    "sg:phone":"+31 181 483 200",
    "sg:postcode":"3233 CT",
    "sg:province":"Zuid-Holland",
    "wof:name":"Kok, P J F De",
    "wof:placetype":"venue"
},
  "geometry": {"coordinates":[4.097385,51.914482],"type":"Point"}
}