{
  "type": "Feature",
  "properties": {
    "addr:full":"A J Luthulistr 54 Purmerend North Holland 1447 XG",
    "addr:housenumber":"54",
    "addr:postcode":"1447 xg",
    "addr:street":"A",
    "iso:country":"NL",
    "sg:address":"A J Luthulistr 54",
    "sg:city":"Purmerend",
    "sg:orig_category":"Adviesbureaus Bedrijfsorganisatie",
    "sg:phone":"+31 299 426 661",
    "sg:postcode":"1447 XG",
    "sg:province":"North Holland",
    "wof:name":"Westheider Consultancy Bv",
    "wof:placetype":"venue"
},
  "geometry": {"coordinates":[4.956178,52.486645],"type":"Point"}
}