{
  "type": "Feature",
  "properties": {
    "addr:full":"Mr P J Oudln 44 Zwolle Overijssel 8014 ZT",
    "addr:housenumber":"44",
    "addr:postcode":"8014 zt",
    "addr:street":"Mr",
    "iso:country":"NL",
    "sg:address":"Mr P J Oudln 44",
    "sg:city":"Zwolle",
    "sg:classifiers":[
        {
            "category":"Personal",
            "subcategory":"Nail Salon",
            "type":"Services"
        }
    ],
    "sg:phone":"+31 38 465 3335",
    "sg:postcode":"8014 ZT",
    "sg:province":"Overijssel",
    "sg:tags":[
        "pedicure"
    ],
    "wof:name":"Wolters-Wessels, Ida",
    "wof:placetype":"venue"
},
  "geometry": {"coordinates":[6.088738,52.512566],"type":"Point"}
}