{
  "type": "Feature",
  "properties": {
    "addr:full":"Spoorven 14 Veghel Noord-Brabant 5464 PA",
    "addr:housenumber":"14",
    "addr:postcode":"5464 pa",
    "addr:street":"Spoorven",
    "iso:country":"NL",
    "sg:address":"Spoorven 14",
    "sg:city":"Veghel",
    "sg:orig_category":"Opticiens",
    "sg:phone":"+31 413 353 230",
    "sg:postcode":"5464 PA",
    "sg:province":"Noord-Brabant",
    "wof:name":"Peter Beks, Brillen En Lenzen",
    "wof:placetype":"venue"
},
  "geometry": {"coordinates":[5.5482130051,51.6281738281],"type":"Point"}
}