{
  "type": "Feature",
  "properties": {
    "iso:country":"NL",
    "sg:address":"Brasserskade 1",
    "sg:city":"Delft",
    "sg:orig_category":"Organisaties And Verenigingen",
    "sg:phone":"+31 15 214 7283",
    "sg:postcode":"2612 CA",
    "sg:province":"Zuid-Holland",
    "wof:name":"Terra Fertilis Studentenvereniging",
    "wof:placetype":"venue"
},
  "geometry": {"coordinates":[4.3528571129,52.0234069824],"type":"Point"}
}