{
  "type": "Feature",
  "properties": {
    "addr:full":"Haydnln 28 Groningen Groningen 9722 CJ",
    "addr:housenumber":"28",
    "addr:postcode":"9722 cj",
    "addr:street":"Haydnln",
    "iso:country":"NL",
    "sg:address":"Haydnln 28",
    "sg:city":"Groningen",
    "sg:orig_category":"Adviesbureaus Gezondheidszorg",
    "sg:phone":"+31 50 526 8529",
    "sg:postcode":"9722 CJ",
    "sg:province":"Groningen",
    "sg:website":"http://www.oprit.rug.nl/kropmans",
    "wof:name":"Kropmans Van Der Schans",
    "wof:placetype":"venue"
},
  "geometry": {"coordinates":[6.584616,53.20118],"type":"Point"}
}