{
  "type": "Feature",
  "properties": {
    "addr:full":"Ridderspoor 3 Borne Overijssel 7621 AS",
    "addr:housenumber":"3",
    "addr:postcode":"7621 as",
    "addr:street":"Ridderspoor",
    "iso:country":"NL",
    "sg:address":"Ridderspoor 3",
    "sg:city":"Borne",
    "sg:orig_category":"Glaszetten",
    "sg:phone":"+31 74 266 3666",
    "sg:postcode":"7621 AS",
    "sg:province":"Overijssel",
    "wof:name":"Glas In Lood- En Schilderwerken Snijders",
    "wof:placetype":"venue"
},
  "geometry": {"coordinates":[-70.54347199999999,41.78083],"type":"Point"}
}