{
  "type": "Feature",
  "properties": {
    "addr:full":"Huizermaatweg 23 Huizen Noord-Holland 1273 NA",
    "addr:housenumber":"23",
    "addr:postcode":"1273 na",
    "addr:street":"Huizermaatweg",
    "iso:country":"NL",
    "sg:address":"Huizermaatweg 23",
    "sg:city":"Huizen",
    "sg:orig_category":"Werving And Selectie Van Tijdelijk Personeel And Uitzendkantoren",
    "sg:phone":"+31 35 524 3900",
    "sg:postcode":"1273 NA",
    "sg:province":"Noord-Holland",
    "wof:name":"Accord",
    "wof:placetype":"venue"
},
  "geometry": {"coordinates":[5.2515349388,52.2971153259],"type":"Point"}
}