{
  "type": "Feature",
  "properties": {
    "iso:country":"NL",
    "sg:address":"Klaphekstr 50",
    "sg:city":"Ewyk",
    "sg:orig_category":"Prefabconstructies",
    "sg:phone":"+31 487 595 953",
    "sg:postcode":"6644 CN",
    "sg:province":"Gelderland",
    "sg:website":"http://www.destallenman.nl",
    "wof:name":"Stallenman, De",
    "wof:placetype":"venue"
},
  "geometry": {"coordinates":[5.741661,51.866779],"type":"Point"}
}