{
  "type": "Feature",
  "properties": {
    "iso:country":"NL",
    "sg:address":"Kievitswg 13",
    "sg:city":"Grypskerk",
    "sg:orig_category":"Wegenbouw",
    "sg:phone":"+31 594 280 123",
    "sg:postcode":"9843 HA",
    "sg:province":"Groningen",
    "wof:name":"Oosterhof Holman Bv",
    "wof:placetype":"venue"
},
  "geometry": {"coordinates":[6.312980175,53.2501106262],"type":"Point"}
}