{
  "type": "Feature",
  "properties": {
    "addr:full":"Klaverakker 65 Arnemuiden Zeeland 4341 MA",
    "addr:housenumber":"65",
    "addr:postcode":"4341 ma",
    "addr:street":"Klaverakker",
    "iso:country":"NL",
    "sg:address":"Klaverakker 65",
    "sg:city":"Arnemuiden",
    "sg:orig_category":"Scheepssleep- En Duwvaart",
    "sg:phone":"+31 118 606 161",
    "sg:postcode":"4341 MA",
    "sg:province":"Zeeland",
    "wof:name":"Bouter Bv",
    "wof:placetype":"venue"
},
  "geometry": {"coordinates":[3.667145,51.503731],"type":"Point"}
}