{
  "type": "Feature",
  "properties": {
    "iso:country":"NL",
    "sg:address":"Marcelisstr 121",
    "sg:city":"S Gravenhage",
    "sg:orig_category":"Onderhoudswerken",
    "sg:phone":"+31 70 338 8104",
    "sg:postcode":"2586 RT",
    "sg:province":"South Holland",
    "wof:name":"Abos",
    "wof:placetype":"venue"
},
  "geometry": {"coordinates":[4.277215,52.10672],"type":"Point"}
}