{
  "type": "Feature",
  "properties": {
    "addr:full":"Abbenbroekwg 6 S Gravenhage Zuid-Holland 2597 NT",
    "addr:housenumber":"6;gravenhage",
    "addr:postcode":"2597 nt",
    "addr:street":"Abbenbroekwg;S",
    "iso:country":"NL",
    "sg:address":"Abbenbroekwg 6",
    "sg:city":"S Gravenhage",
    "sg:orig_category":"Bedrijfsopleidingen",
    "sg:phone":"+31 70 350 6732",
    "sg:postcode":"2597 NT",
    "sg:province":"Zuid-Holland",
    "wof:name":"Spiegel",
    "wof:placetype":"venue"
},
  "geometry": {"coordinates":[4.31817,52.11031],"type":"Point"}
}