{
  "type": "Feature",
  "properties": {
    "addr:full":"Nieuwlandseweg 1 Amersfoort Utrecht 3824 XP",
    "addr:housenumber":"1",
    "addr:postcode":"3824 xp",
    "addr:street":"Nieuwlandseweg",
    "iso:country":"NL",
    "sg:address":"Nieuwlandseweg 1",
    "sg:city":"Amersfoort",
    "sg:orig_category":"Binnenhuisarchitecten",
    "sg:phone":"+31 33 455 4468",
    "sg:postcode":"3824 XP",
    "sg:province":"Utrecht",
    "wof:name":"Sphere",
    "wof:placetype":"venue"
},
  "geometry": {"coordinates":[5.388261,52.199791],"type":"Point"}
}