{
  "type": "Feature",
  "properties": {
    "addr:full":"Achterstraat 1 Lochem Gelderland 7241 AV",
    "addr:housenumber":"1",
    "addr:postcode":"7241 av",
    "addr:street":"Achterstraat;Gelderland",
    "iso:country":"NL",
    "sg:address":"Achterstraat 1",
    "sg:city":"Lochem",
    "sg:orig_category":"Wasserettes And Stomerijen",
    "sg:phone":"+31 573 252 610",
    "sg:postcode":"7241 AV",
    "sg:province":"Gelderland",
    "wof:name":"Chemisch Reinigingsbedrijf Good Clean",
    "wof:placetype":"venue"
},
  "geometry": {"coordinates":[6.4157891273,52.1608314514],"type":"Point"}
}