{
  "type": "Feature",
  "properties": {
    "iso:country":"NL",
    "sg:address":"Straatsburgln 6",
    "sg:city":"Sittard",
    "sg:orig_category":"Adviesbureaus Gezondheidszorg",
    "sg:phone":"+31 46 411 1804",
    "sg:postcode":"6137 JC",
    "sg:province":"Limburg",
    "wof:name":"Labrouche",
    "wof:placetype":"venue"
},
  "geometry": {"coordinates":[5.8973,51.00008],"type":"Point"}
}