{
  "type": "Feature",
  "properties": {
    "addr:full":"V Ittersumstr 97 Zwolle Overijssel 8012 TJ",
    "addr:housenumber":"97",
    "addr:postcode":"8012 tj",
    "iso:country":"NL",
    "sg:address":"V Ittersumstr 97",
    "sg:city":"Zwolle",
    "sg:orig_category":"Kinderkleding",
    "sg:phone":"+31 38 423 0023",
    "sg:postcode":"8012 TJ",
    "sg:province":"Overijssel",
    "wof:name":"Oki Doki",
    "wof:placetype":"venue"
},
  "geometry": {"coordinates":[6.088738,52.512566],"type":"Point"}
}