{
  "type": "Feature",
  "properties": {
    "iso:country":"NL",
    "sg:address":"Steltsestraat 71",
    "sg:city":"Lent",
    "sg:orig_category":"Loodgieterswerk, Verwarming And Sanitaire Installaties",
    "sg:phone":"+31 24 360 3137",
    "sg:postcode":"6663 BP",
    "sg:province":"Gelderland",
    "wof:name":"Vof Installatiebedrijf Harry Houterman",
    "wof:placetype":"venue"
},
  "geometry": {"coordinates":[-77.241432,38.151344],"type":"Point"}
}