{
  "type": "Feature",
  "properties": {
    "addr:full":"Azuurhof 17 Voorburg Zuid-Holland 2272 JJ",
    "addr:housenumber":"17",
    "addr:postcode":"2272 jj",
    "addr:street":"Azuurhof",
    "iso:country":"NL",
    "sg:address":"Azuurhof 17",
    "sg:city":"Voorburg",
    "sg:orig_category":"Binnenhuisarchitecten",
    "sg:phone":"+31 70 386 1170",
    "sg:postcode":"2272 JJ",
    "sg:province":"Zuid-Holland",
    "wof:name":"Els Design",
    "wof:placetype":"venue"
},
  "geometry": {"coordinates":[4.380152,52.078869],"type":"Point"}
}