{
  "type": "Feature",
  "properties": {
    "iso:country":"NL",
    "sg:address":"Graafstroomstraat 23",
    "sg:city":"Rotterdam",
    "sg:orig_category":"Papieren Kantoorbenodigdheden Fab",
    "sg:phone":"+31 10 462 0222",
    "sg:postcode":"3044 AN",
    "sg:province":"South Holland",
    "wof:name":"Henrar Van Lelyveld Bv",
    "wof:placetype":"venue"
},
  "geometry": {"coordinates":[4.428399,51.924805],"type":"Point"}
}