{
  "type": "Feature",
  "properties": {
    "addr:full":"De Tinneweide 139 Veenendaal Utrecht 3901 KJ",
    "addr:housenumber":"139",
    "addr:postcode":"3901 kj",
    "addr:street":"De Tinneweide",
    "iso:country":"NL",
    "sg:address":"De Tinneweide 139",
    "sg:city":"Veenendaal",
    "sg:orig_category":"Medische Installaties En Instrumenten",
    "sg:phone":"+31 318 503 381",
    "sg:postcode":"3901 KJ",
    "sg:province":"Utrecht",
    "wof:name":"Pegasus Zorg",
    "wof:placetype":"venue"
},
  "geometry": {"coordinates":[5.563525,52.02066],"type":"Point"}
}