{
  "type": "Feature",
  "properties": {
    "iso:country":"NL",
    "sg:address":"Calvercamp 19",
    "sg:city":"Monnickendam",
    "sg:orig_category":"Mensendieck - Oefentherapeuten",
    "sg:phone":"+31 299 652 927",
    "sg:postcode":"1141 RT",
    "sg:province":"Noord-Holland",
    "wof:name":"Pott, D C",
    "wof:placetype":"venue"
},
  "geometry": {"coordinates":[5.038518,52.447742],"type":"Point"}
}