{
  "type": "Feature",
  "properties": {
    "addr:full":"Farmsumerwg 101 Appingedam Groningen 9902 BN",
    "addr:housenumber":"101",
    "addr:postcode":"9902 bn",
    "addr:street":"Appingedam",
    "iso:country":"NL",
    "sg:address":"Farmsumerwg 101",
    "sg:city":"Appingedam",
    "sg:orig_category":"Administratie- En Boekhoudkantoren",
    "sg:phone":"+31 596 627 977",
    "sg:postcode":"9902 BN",
    "sg:province":"Groningen",
    "wof:name":"Maroli",
    "wof:placetype":"venue"
},
  "geometry": {"coordinates":[6.876802,53.319939],"type":"Point"}
}