{
  "type": "Feature",
  "properties": {
    "iso:country":"NL",
    "sg:address":"Veenslag 72",
    "sg:city":"Veenendaal",
    "sg:classifiers":[
        {
            "category":"Fast Food",
            "type":"Food & Drink"
        }
    ],
    "sg:phone":"+31 318 526 526",
    "sg:postcode":"3905 SL",
    "sg:province":"Utrecht",
    "sg:tags":[
        "afhaal",
        "restaurant"
    ],
    "wof:name":"Snackbar La Promenade",
    "wof:placetype":"venue"
},
  "geometry": {"coordinates":[5.532848,52.028149],"type":"Point"}
}