{
  "type": "Feature",
  "properties": {
    "addr:full":"Entingheweg 15 Dwingeloo Provincie Drenthe 7991 CC",
    "addr:housenumber":"15;7991",
    "addr:postcode":"cc",
    "addr:street":"Entingheweg;Provincie Drenthe",
    "iso:country":"NL",
    "sg:address":"Entingheweg 15",
    "sg:city":"Dwingeloo",
    "sg:orig_category":"Meubelzaken, Woning- And Keukeninrichting",
    "sg:phone":"+31 521 591 318",
    "sg:postcode":"7991 CC",
    "sg:province":"Provincie Drenthe",
    "wof:name":"Wiechers Woonoase Bv",
    "wof:placetype":"venue"
},
  "geometry": {"coordinates":[6.363357,52.837769],"type":"Point"}
}