{
  "type": "Feature",
  "properties": {
    "iso:country":"NL",
    "sg:address":"Minrebroederstr 13",
    "sg:city":"Utrecht",
    "sg:orig_category":"Boeken En Tijdschriften",
    "sg:phone":"+31 30 233 6500",
    "sg:postcode":"3512 GS",
    "sg:province":"Utrecht",
    "sg:website":"http://www.broese.net",
    "wof:name":"Broese",
    "wof:placetype":"venue"
},
  "geometry": {"coordinates":[5.120896,52.092396],"type":"Point"}
}