{
  "type": "Feature",
  "properties": {
    "addr:full":"Hopperzuigerstraat 13 Almere-Buiten Flevoland 1333 HL",
    "addr:housenumber":"13",
    "addr:postcode":"1333 hl",
    "addr:street":"Hopperzuigerstraat;Flevoland",
    "iso:country":"NL",
    "sg:address":"Hopperzuigerstraat 13",
    "sg:city":"Almere-Buiten",
    "sg:orig_category":"Kinderopvang Behalve Thuis",
    "sg:phone":"+31 36 532 8314",
    "sg:postcode":"1333 HL",
    "sg:province":"Flevoland",
    "sg:website":"http://www.kinderdagverblijfjami.nl",
    "wof:name":"Kinderdagverblijf Jami",
    "wof:placetype":"venue"
},
  "geometry": {"coordinates":[5.264047,52.40036],"type":"Point"}
}