{
  "type": "Feature",
  "properties": {
    "iso:country":"NL",
    "sg:address":"Spaarnwouderstraat 124",
    "sg:city":"Haarlem",
    "sg:classifiers":[
        {
            "category":"Shopping",
            "subcategory":"Gifts & Souvenirs",
            "type":"Retail Goods"
        }
    ],
    "sg:phone":"+31 23 535 7552",
    "sg:postcode":"2011 AH",
    "sg:province":"North Holland",
    "sg:tags":[
        "geschenken"
    ],
    "wof:name":"A. De Wit",
    "wof:placetype":"venue"
},
  "geometry": {"coordinates":[4.645164,52.380219],"type":"Point"}
}