{
  "type": "Feature",
  "properties": {
    "addr:full":"Korte Steynlaan 44 Zeist Utrecht 3701 EX",
    "addr:housenumber":"44",
    "addr:postcode":"3701 ex",
    "addr:street":"Korte Steynlaan",
    "iso:country":"NL",
    "sg:address":"Korte Steynlaan 44",
    "sg:city":"Zeist",
    "sg:orig_category":"Huishoudapparatuur, Televisies And Radio'S",
    "sg:phone":"+31 30 697 1664",
    "sg:postcode":"3701 EX",
    "sg:province":"Utrecht",
    "wof:name":"Morelisse",
    "wof:placetype":"venue"
},
  "geometry": {"coordinates":[5.24732,52.089062],"type":"Point"}
}