{
  "type": "Feature",
  "properties": {
    "addr:full":"Dyksestr 52 Didam Gelderland 6942 GD",
    "addr:housenumber":"52",
    "addr:postcode":"6942 gd",
    "addr:street":"Dyksestr;Gelderland",
    "iso:country":"NL",
    "sg:address":"Dyksestr 52",
    "sg:city":"Didam",
    "sg:orig_category":"Zalenverhuur",
    "sg:phone":"+31 316 226 058",
    "sg:postcode":"6942 GD",
    "sg:province":"Gelderland",
    "sg:website":"http://www.plok.nl",
    "wof:name":"Plok Partycentrum",
    "wof:placetype":"venue"
},
  "geometry": {"coordinates":[6.132886,51.926254],"type":"Point"}
}