{
  "type": "Feature",
  "properties": {
    "addr:full":"Weerdingerstraat 24 Emmen Provincie Drenthe 7815 SC",
    "addr:housenumber":"24;7815",
    "addr:street":"Weerdingerstraat;Provincie Drenthe",
    "iso:country":"NL",
    "sg:address":"Weerdingerstraat 24",
    "sg:city":"Emmen",
    "sg:orig_category":"Naai- And Breimachines",
    "sg:phone":"+31 591 611 661",
    "sg:postcode":"7815 SC",
    "sg:province":"Provincie Drenthe",
    "wof:name":"H. Drenth",
    "wof:placetype":"venue"
},
  "geometry": {"coordinates":[6.894795,52.789837],"type":"Point"}
}