{
  "type": "Feature",
  "properties": {
    "addr:full":"Poppelsewg 7D Goirle Noord-Brabant 5051 PL",
    "addr:housenumber":"7d",
    "addr:postcode":"goirle;5051 pl",
    "iso:country":"NL",
    "sg:address":"Poppelsewg 7D",
    "sg:city":"Goirle",
    "sg:orig_category":"Accountants - Administratie- Consulenten En -Kantoren",
    "sg:phone":"+31 13 534 0001",
    "sg:postcode":"5051 PL",
    "sg:province":"Noord-Brabant",
    "sg:website":"http://www.ldeacc.nl",
    "wof:name":"Luytgaarden Donders & Emmen",
    "wof:placetype":"venue"
},
  "geometry": {"coordinates":[5.054723,51.507141],"type":"Point"}
}