{
  "type": "Feature",
  "properties": {
    "addr:full":"Raadhuisplein 1 Meijel Limburg 5768 AR",
    "addr:housenumber":"1",
    "addr:postcode":"5768",
    "addr:street":"Raadhuisplein",
    "iso:country":"NL",
    "sg:address":"Raadhuisplein 1",
    "sg:city":"Meijel",
    "sg:orig_category":"Overheidsdiensten",
    "sg:phone":"+31 77 466 8181",
    "sg:postcode":"5768 AR",
    "sg:province":"Limburg",
    "wof:name":"Gemeente Meijel",
    "wof:placetype":"venue"
},
  "geometry": {"coordinates":[5.8854999542,51.3443374634],"type":"Point"}
}