{
  "type": "Feature",
  "properties": {
    "addr:full":"Boomkensdiep 31 Zwolle NL.08 8032 XZ",
    "addr:housenumber":"31",
    "addr:postcode":"8032 xz",
    "addr:street":"Boomkensdiep",
    "iso:country":"NL",
    "sg:address":"Boomkensdiep 31",
    "sg:city":"Zwolle",
    "sg:orig_category":"Adviesbureaus Personeel",
    "sg:phone":"+31 38 453 4103",
    "sg:postcode":"8032 XZ",
    "sg:province":"NL.08",
    "wof:name":"Gimbr\u00e8re, Meys",
    "wof:placetype":"venue"
},
  "geometry": {"coordinates":[6.103204,52.536285],"type":"Point"}
}