{
  "type": "Feature",
  "properties": {
    "addr:full":"Gijsbrecht Van Amstelstr 73 Hilversum Noord-Holland 1214 AT",
    "addr:housenumber":"73",
    "addr:postcode":"1214",
    "addr:street":"Gijsbrecht Van Amstelstr",
    "iso:country":"NL",
    "sg:address":"Gijsbrecht Van Amstelstr 73",
    "sg:city":"Hilversum",
    "sg:orig_category":"Metaalbekleding And -Behandeling",
    "sg:phone":"+31 35 624 2103",
    "sg:postcode":"1214 AT",
    "sg:province":"Noord-Holland",
    "wof:name":"Firma H.J. Torsing & Zn",
    "wof:placetype":"venue"
},
  "geometry": {"coordinates":[5.173493,52.215446],"type":"Point"}
}