{
  "type": "Feature",
  "properties": {
    "iso:country":"NL",
    "sg:address":"Zwanenoord 35",
    "sg:city":"Numansdorp",
    "sg:orig_category":"Autokeuringen",
    "sg:phone":"+31 186 651 867",
    "sg:postcode":"3281 JJ",
    "sg:province":"South Holland",
    "wof:name":"Zwanenoord Handelsonderneming",
    "wof:placetype":"venue"
},
  "geometry": {"coordinates":[4.440781,51.73093],"type":"Point"}
}