{
  "type": "Feature",
  "properties": {
    "addr:full":"Ysvogelstr 14 De Lutte NL.08 7587 BJ",
    "addr:housenumber":"14",
    "addr:postcode":"nl.08 7587 bj",
    "addr:street":"Ysvogelstr",
    "iso:country":"NL",
    "sg:address":"Ysvogelstr 14",
    "sg:city":"De Lutte",
    "sg:orig_category":"Verenigingen En Stichtingen",
    "sg:phone":"+31 541 551 827",
    "sg:postcode":"7587 BJ",
    "sg:province":"NL.08",
    "wof:name":"Kbo De Lutte",
    "wof:placetype":"venue"
},
  "geometry": {"coordinates":[6.992429,52.310905],"type":"Point"}
}