{
  "type": "Feature",
  "properties": {
    "iso:country":"NL",
    "sg:address":"Pastoryln 32",
    "sg:city":"Tzum",
    "sg:orig_category":"Autorijscholen",
    "sg:phone":"+31 517 452 211",
    "sg:postcode":"8804 SC",
    "sg:province":"Friesland",
    "wof:name":"Wagenaar",
    "wof:placetype":"venue"
},
  "geometry": {"coordinates":[5.565409,53.160343],"type":"Point"}
}