{
  "type": "Feature",
  "properties": {
    "addr:full":"Mondriaanln 92 Heerhugowaard Noord-Holland 1701 TG",
    "addr:housenumber":"92;1701",
    "addr:postcode":"tg",
    "addr:street":"Mondriaanln",
    "iso:country":"NL",
    "sg:address":"Mondriaanln 92",
    "sg:city":"Heerhugowaard",
    "sg:orig_category":"Administratie- En Boekhoudkantoren",
    "sg:phone":"+31 72 574 0236",
    "sg:postcode":"1701 TG",
    "sg:province":"Noord-Holland",
    "wof:name":"Bolink, H",
    "wof:placetype":"venue"
},
  "geometry": {"coordinates":[4.859599,52.670753],"type":"Point"}
}