{
  "type": "Feature",
  "properties": {
    "addr:full":"Mauritsln 49 Urmond Limburg 6129 EL",
    "addr:housenumber":"49",
    "addr:postcode":"6129 el",
    "addr:street":"Mauritsln",
    "iso:country":"NL",
    "sg:address":"Mauritsln 49",
    "sg:city":"Urmond",
    "sg:orig_category":"Petrochemische Industrie",
    "sg:phone":"+31 46 476 0392",
    "sg:postcode":"6129 EL",
    "sg:province":"Limburg",
    "wof:name":"Sabtec Bv",
    "wof:placetype":"venue"
},
  "geometry": {"coordinates":[5.76554,50.992336],"type":"Point"}
}