{
  "type": "Feature",
  "properties": {
    "addr:full":"Ypelobrink 206 Enschede Overijssel 7544 CJ",
    "addr:housenumber":"206",
    "addr:postcode":"7544 cj",
    "addr:street":"Ypelobrink",
    "iso:country":"NL",
    "sg:address":"Ypelobrink 206",
    "sg:city":"Enschede",
    "sg:orig_category":"Onderhoudswerken",
    "sg:phone":"+31 53 476 1264",
    "sg:postcode":"7544 CJ",
    "sg:province":"Overijssel",
    "wof:name":"Koehorst Timmerklussenbedrijf, A M",
    "wof:placetype":"venue"
},
  "geometry": {"coordinates":[6.870355,52.192799],"type":"Point"}
}