{
  "type": "Feature",
  "properties": {
    "addr:full":"Grotestr 308 Waalwyk Noord-Brabant 5142 CC",
    "addr:housenumber":"308",
    "addr:postcode":"5142 cc",
    "addr:street":"Waalwyk",
    "iso:country":"NL",
    "sg:address":"Grotestr 308",
    "sg:city":"Waalwyk",
    "sg:orig_category":"Adviesbureaus Telefoon",
    "sg:phone":"+31 416 338 800",
    "sg:postcode":"5142 CC",
    "sg:province":"Noord-Brabant",
    "sg:website":"http://www.telan.nl",
    "wof:name":"Telan",
    "wof:placetype":"venue"
},
  "geometry": {"coordinates":[5.073171,51.691006],"type":"Point"}
}