{
  "type": "Feature",
  "properties": {
    "addr:full":"Gasselstr 4 S Hertogenbosch Noord-Brabant 5211 KJ",
    "addr:housenumber":"4",
    "addr:postcode":"5211 kj",
    "addr:street":"Gasselstr",
    "iso:country":"NL",
    "sg:address":"Gasselstr 4",
    "sg:city":"S Hertogenbosch",
    "sg:orig_category":"Babyartikelen",
    "sg:phone":"+31 73 690 0936",
    "sg:postcode":"5211 KJ",
    "sg:province":"Noord-Brabant",
    "sg:website":"http://www.tata-sjop.nl",
    "wof:name":"Ta Ta",
    "wof:placetype":"venue"
},
  "geometry": {"coordinates":[5.305942,51.688839],"type":"Point"}
}