{
  "type": "Feature",
  "properties": {
    "addr:full":"W Brandtpln 14A Doetinchem Gelderland 7007 LB",
    "addr:housenumber":"14a",
    "addr:postcode":"7007 lb",
    "addr:street":"W;Gelderland",
    "iso:country":"NL",
    "sg:address":"W Brandtpln 14A",
    "sg:city":"Doetinchem",
    "sg:orig_category":"Kappers",
    "sg:phone":"+31 314 359 747",
    "sg:postcode":"7007 LB",
    "sg:province":"Gelderland",
    "wof:name":"Twins",
    "wof:placetype":"venue"
},
  "geometry": {"coordinates":[6.266061,51.953083],"type":"Point"}
}