{
  "type": "Feature",
  "properties": {
    "iso:country":"NL",
    "sg:address":"Marktwg 51",
    "sg:city":"Heerenveen",
    "sg:orig_category":"Schilders",
    "sg:phone":"+31 6 28672038",
    "sg:postcode":"8444 AB",
    "sg:province":"Friesland",
    "wof:name":"Dalen, W Van",
    "wof:placetype":"venue"
},
  "geometry": {"coordinates":[5.9522,52.9366],"type":"Point"}
}