{
  "type": "Feature",
  "properties": {
    "addr:full":"Bovenkerkwg 35 Montfoort Utrecht 3417 TA",
    "addr:housenumber":"35",
    "addr:postcode":"3417 ta",
    "addr:street":"Bovenkerkwg",
    "iso:country":"NL",
    "sg:address":"Bovenkerkwg 35",
    "sg:city":"Montfoort",
    "sg:orig_category":"Webdesign Bureaus",
    "sg:phone":"+31 348 475 056",
    "sg:postcode":"3417 TA",
    "sg:province":"Utrecht",
    "wof:name":"Brightsoft",
    "wof:placetype":"venue"
},
  "geometry": {"coordinates":[4.9551320076,52.042842865],"type":"Point"}
}