{
  "type": "Feature",
  "properties": {
    "addr:full":"Bellamypark 8 Vlissingen Zeeland 4381 CJ",
    "addr:housenumber":"8",
    "addr:postcode":"4381 cj",
    "addr:street":"Bellamypark",
    "iso:country":"NL",
    "sg:address":"Bellamypark 8",
    "sg:city":"Vlissingen",
    "sg:classifiers":[
        {
            "category":"Fast Food",
            "type":"Food & Drink"
        }
    ],
    "sg:phone":"+31 118 412 261",
    "sg:postcode":"4381 CJ",
    "sg:province":"Zeeland",
    "sg:tags":[
        "afhaal",
        "restaurant"
    ],
    "wof:name":"Foppe Vof",
    "wof:placetype":"venue"
},
  "geometry": {"coordinates":[3.574661,51.441132],"type":"Point"}
}