{
  "type": "Feature",
  "properties": {
    "addr:full":"Zwaluwstr 8 Utrecht Utrecht 3515 BM",
    "addr:housenumber":"8",
    "addr:postcode":"3515 bm",
    "addr:street":"Zwaluwstr",
    "iso:country":"NL",
    "sg:address":"Zwaluwstr 8",
    "sg:city":"Utrecht",
    "sg:orig_category":"Voegwerken",
    "sg:phone":"+31 30 271 5548",
    "sg:postcode":"3515 BM",
    "sg:province":"Utrecht",
    "wof:name":"Kreugel",
    "wof:placetype":"venue"
},
  "geometry": {"coordinates":[5.118573,52.101524],"type":"Point"}
}