{
  "type": "Feature",
  "properties": {
    "addr:full":"Havenstr 28 Huizen North Holland 1271 AE",
    "addr:housenumber":"28",
    "addr:postcode":"1271 ae",
    "addr:street":"Havenstr",
    "iso:country":"NL",
    "sg:address":"Havenstr 28",
    "sg:city":"Huizen",
    "sg:orig_category":"Wasmachines En Wasdrogers",
    "sg:phone":"+31 35 525 3682",
    "sg:postcode":"1271 AE",
    "sg:province":"North Holland",
    "sg:website":"http://www.deschouwwitgoed.nl",
    "wof:name":"Schouw, De",
    "wof:placetype":"venue"
},
  "geometry": {"coordinates":[5.2366199493,52.2994270325],"type":"Point"}
}