{
  "type": "Feature",
  "properties": {
    "addr:full":"Gieterij 39 Noordwijkerhout Zuid-Holland 2211 WC",
    "addr:housenumber":"39",
    "addr:postcode":"2211 wc",
    "addr:street":"Gieterij",
    "iso:country":"NL",
    "sg:address":"Gieterij 39",
    "sg:city":"Noordwijkerhout",
    "sg:orig_category":"Pleziervaartuigen And Reparatie",
    "sg:phone":"+31 252 377 955",
    "sg:postcode":"2211 WC",
    "sg:province":"Zuid-Holland",
    "wof:name":"W & S Jetsport",
    "wof:placetype":"venue"
},
  "geometry": {"coordinates":[4.492163,52.249279],"type":"Point"}
}