{
  "type": "Feature",
  "properties": {
    "iso:country":"NL",
    "sg:address":"Louise Wentstraat 141",
    "sg:city":"Amsterdam",
    "sg:orig_category":"Diverse Grafische Activiteiten",
    "sg:phone":"+31 20 625 1400",
    "sg:postcode":"1018 MS",
    "sg:province":"Noord-Holland",
    "wof:name":"Daniel De Heus",
    "wof:placetype":"venue"
},
  "geometry": {"coordinates":[4.92297,52.36565],"type":"Point"}
}