{
  "type": "Feature",
  "properties": {
    "addr:full":"Willebrordstraat 82 Ijmuiden North Holland 1971 DE",
    "addr:housenumber":"82",
    "addr:postcode":"1971 de",
    "addr:street":"Willebrordstraat",
    "iso:country":"NL",
    "sg:address":"Willebrordstraat 82",
    "sg:city":"Ijmuiden",
    "sg:orig_category":"Public Relationbureaus",
    "sg:phone":"+31 255 511 745",
    "sg:postcode":"1971 DE",
    "sg:province":"North Holland",
    "wof:name":"Inducom International Bv",
    "wof:placetype":"venue"
},
  "geometry": {"coordinates":[4.629232,52.461971],"type":"Point"}
}