{
  "type": "Feature",
  "properties": {
    "addr:full":"Kooikerspad 1 Zoeterwoude Zuid-Holland 2382 EA",
    "addr:housenumber":"1",
    "addr:postcode":"2382 ea",
    "addr:street":"Kooikerspad",
    "iso:country":"NL",
    "sg:address":"Kooikerspad 1",
    "sg:city":"Zoeterwoude",
    "sg:orig_category":"Peuterspeelzalen",
    "sg:phone":"+31 71 541 7300",
    "sg:postcode":"2382 EA",
    "sg:province":"Zuid-Holland",
    "wof:name":"Drie Turven Hoog",
    "wof:placetype":"venue"
},
  "geometry": {"coordinates":[4.522761,52.142841],"type":"Point"}
}