{
  "type": "Feature",
  "properties": {
    "addr:full":"Essenlaan 8 Ter Aar Zuid-Holland 2461 DH",
    "addr:housenumber":"8",
    "addr:postcode":"aar;2461 dh",
    "addr:street":"Essenlaan",
    "iso:country":"NL",
    "sg:address":"Essenlaan 8",
    "sg:city":"Ter Aar",
    "sg:orig_category":"Apothekers",
    "sg:phone":"+31 172 605 000",
    "sg:postcode":"2461 DH",
    "sg:province":"Zuid-Holland",
    "wof:name":"Apotheek Ter Aar",
    "wof:placetype":"venue"
},
  "geometry": {"coordinates":[4.708628,52.167126],"type":"Point"}
}