{
  "type": "Feature",
  "properties": {
    "addr:full":"Elsweg 37 Apeldoorn Gelderland 7311 GT",
    "addr:housenumber":"37",
    "addr:postcode":"7311 gt",
    "addr:street":"Elsweg;Gelderland",
    "iso:country":"NL",
    "sg:address":"Elsweg 37",
    "sg:city":"Apeldoorn",
    "sg:orig_category":"Metaalwerken",
    "sg:phone":"+31 55 542 0421",
    "sg:postcode":"7311 GT",
    "sg:province":"Gelderland",
    "wof:name":"Van Ark Zonweringen",
    "wof:placetype":"venue"
},
  "geometry": {"coordinates":[5.954528,52.210674],"type":"Point"}
}