{
  "type": "Feature",
  "properties": {
    "addr:full":"Moerstraatseweg 141 Steenbergen Nb Noord-Brabant 4651 VC",
    "addr:housenumber":"141",
    "addr:postcode":"4651 vc",
    "addr:street":"Moerstraatseweg",
    "iso:country":"NL",
    "sg:address":"Moerstraatseweg 141",
    "sg:city":"Steenbergen Nb",
    "sg:orig_category":"Huizensloop And Bouwrijp Maken",
    "sg:phone":"+31 167 566 959",
    "sg:postcode":"4651 VC",
    "sg:province":"Noord-Brabant",
    "wof:name":"Aannemersbedrijf Augustijn Steenbergen",
    "wof:placetype":"venue"
},
  "geometry": {"coordinates":[4.329653,51.554802],"type":"Point"}
}