{
  "type": "Feature",
  "properties": {
    "addr:full":"Singelstr 18 Utrecht Utrecht 3513 BN",
    "addr:housenumber":"18",
    "addr:postcode":"3513 bn",
    "addr:street":"Singelstr",
    "iso:country":"NL",
    "sg:address":"Singelstr 18",
    "sg:city":"Utrecht",
    "sg:orig_category":"Adviesbureaus Bouwkunde",
    "sg:phone":"+31 30 238 0103",
    "sg:postcode":"3513 BN",
    "sg:province":"Utrecht",
    "wof:name":"P W Resultancy Bv",
    "wof:placetype":"venue"
},
  "geometry": {"coordinates":[5.110984,52.096798],"type":"Point"}
}