{
  "type": "Feature",
  "properties": {
    "addr:full":"Nw Vaart 2 Vleuten Utrecht 3451 AJ",
    "addr:housenumber":"2",
    "addr:postcode":"3451 aj",
    "addr:street":"Nw Vaart",
    "iso:country":"NL",
    "sg:address":"Nw Vaart 2",
    "sg:city":"Vleuten",
    "sg:orig_category":"Accountants - Administratie- Consulenten En -Kantoren",
    "sg:phone":"+31 30 677 1616",
    "sg:postcode":"3451 AJ",
    "sg:province":"Utrecht",
    "sg:website":"http://www.glissenaar.nl",
    "wof:name":"Glissenaar Accountantskantoor",
    "wof:placetype":"venue"
},
  "geometry": {"coordinates":[5.010132,52.107708],"type":"Point"}
}