{
  "type": "Feature",
  "properties": {
    "addr:full":"Escampln 63 S Gravenhage Zuid-Holland 2547 GA",
    "addr:housenumber":"63;gravenhage",
    "addr:postcode":"2547 ga",
    "addr:street":"Escampln;S",
    "iso:country":"NL",
    "sg:address":"Escampln 63",
    "sg:city":"S Gravenhage",
    "sg:orig_category":"Omroep",
    "sg:phone":"+31 70 325 1122",
    "sg:postcode":"2547 GA",
    "sg:province":"Zuid-Holland",
    "sg:website":"http://www.zoba.nl",
    "wof:name":"Zoba",
    "wof:placetype":"venue"
},
  "geometry": {"coordinates":[4.26694,52.061771],"type":"Point"}
}