{
  "type": "Feature",
  "properties": {
    "addr:full":"Durgerdammerdk 93 Amsterdam North Holland 1026 CD",
    "addr:housenumber":"93",
    "addr:postcode":"1026 cd",
    "addr:street":"Durgerdammerdk",
    "iso:country":"NL",
    "sg:address":"Durgerdammerdk 93",
    "sg:city":"Amsterdam",
    "sg:orig_category":"Voetbalverenigingen",
    "sg:phone":"+31 20 490 4823",
    "sg:postcode":"1026 CD",
    "sg:province":"North Holland",
    "wof:name":"Drc",
    "wof:placetype":"venue"
},
  "geometry": {"coordinates":[4.99062,52.377708],"type":"Point"}
}