{
  "type": "Feature",
  "properties": {
    "addr:full":"Waaldk 5A Ridderkerk Zuid-Holland 2988 AT",
    "addr:housenumber":"5a",
    "addr:postcode":"2988",
    "addr:street":"Waaldk",
    "iso:country":"NL",
    "sg:address":"Waaldk 5A",
    "sg:city":"Ridderkerk",
    "sg:orig_category":"Video - Faciliteiten En Producties",
    "sg:phone":"+31 6 41226434",
    "sg:postcode":"2988 AT",
    "sg:province":"Zuid-Holland",
    "sg:website":"http://www.schut-av.nl",
    "wof:name":"Schut",
    "wof:placetype":"venue"
},
  "geometry": {"coordinates":[4.594921,51.849098],"type":"Point"}
}