{
  "type": "Feature",
  "properties": {
    "addr:full":"Middachtenstraat 46 Breda North Brabant 4834 PC",
    "addr:housenumber":"46",
    "addr:postcode":"4834 pc",
    "addr:street":"Middachtenstraat",
    "iso:country":"NL",
    "sg:address":"Middachtenstraat 46",
    "sg:city":"Breda",
    "sg:orig_category":"Krantenuitgeverijen",
    "sg:phone":"+31 76 560 0512",
    "sg:postcode":"4834 PC",
    "sg:province":"North Brabant",
    "wof:name":"Uitgeverij Adore",
    "wof:placetype":"venue"
},
  "geometry": {"coordinates":[4.81486,51.571892],"type":"Point"}
}