{
  "type": "Feature",
  "properties": {
    "iso:country":"NL",
    "sg:address":"Dorpswg 49",
    "sg:city":"Hoogblokland",
    "sg:orig_category":"Vertalers",
    "sg:phone":"+31 183 563 892",
    "sg:postcode":"4221 LG",
    "sg:province":"Zuid-Holland",
    "wof:name":"Penhoat-Boone, J F",
    "wof:placetype":"venue"
},
  "geometry": {"coordinates":[4.972226,51.874733],"type":"Point"}
}