{
  "type": "Feature",
  "properties": {
    "addr:full":"Tielsestr 73 Opheusden Gelderland 4043 JR",
    "addr:housenumber":"73",
    "addr:postcode":"4043 jr",
    "addr:street":"Tielsestr;Gelderland",
    "iso:country":"NL",
    "sg:address":"Tielsestr 73",
    "sg:city":"Opheusden",
    "sg:orig_category":"Keukens",
    "sg:phone":"+31 488 481 560",
    "sg:postcode":"4043 JR",
    "sg:province":"Gelderland",
    "sg:website":"http://www.dentorenburg.nl",
    "wof:name":"Torenburg, Den",
    "wof:placetype":"venue"
},
  "geometry": {"coordinates":[5.611383,51.935974],"type":"Point"}
}