{
  "type": "Feature",
  "properties": {
    "iso:country":"NL",
    "sg:address":"Wg Pln 59B",
    "sg:city":"Amsterdam",
    "sg:orig_category":"Verenigingen En Stichtingen",
    "sg:phone":"+31 20 618 7848",
    "sg:postcode":"1054 RB",
    "sg:province":"North Holland",
    "wof:name":"Wg",
    "wof:placetype":"venue"
},
  "geometry": {"coordinates":[4.871001,52.364071],"type":"Point"}
}