{
  "type": "Feature",
  "properties": {
    "addr:full":"Fluitekruidln 25 Scherpenzeel Gld Utrecht 3925 SB",
    "addr:housenumber":"25",
    "addr:postcode":"3925 sb",
    "addr:street":"Fluitekruidln;Gld",
    "iso:country":"NL",
    "sg:address":"Fluitekruidln 25",
    "sg:city":"Scherpenzeel Gld",
    "sg:orig_category":"Webdesign Bureaus",
    "sg:phone":"+31 33 532 3050",
    "sg:postcode":"3925 SB",
    "sg:province":"Utrecht",
    "sg:website":"http://www.nixward.net",
    "wof:name":"Nixward New Media Creations",
    "wof:placetype":"venue"
},
  "geometry": {"coordinates":[5.494125843,52.0754127502],"type":"Point"}
}