{
  "type": "Feature",
  "properties": {
    "iso:country":"NL",
    "sg:address":"St. Jacobslaan 118",
    "sg:city":"Nijmegen",
    "sg:orig_category":"Verzekeringen",
    "sg:phone":"+31 24 354 1750",
    "sg:postcode":"6533 BW",
    "sg:province":"Gelderland",
    "wof:name":"Assurantiekantoor Nieman",
    "wof:placetype":"venue"
},
  "geometry": {"coordinates":[5.850096,51.820141],"type":"Point"}
}