{
  "type": "Feature",
  "properties": {
    "addr:full":"Schoolstraat 12 Herkenbosch Limburg 6075 BT",
    "addr:housenumber":"12",
    "addr:postcode":"6075 bt",
    "addr:street":"Schoolstraat",
    "iso:country":"NL",
    "sg:address":"Schoolstraat 12",
    "sg:city":"Herkenbosch",
    "sg:orig_category":"Overheidsdiensten",
    "sg:phone":"+31 475 531 395",
    "sg:postcode":"6075 BT",
    "sg:province":"Limburg",
    "wof:name":"Amicale",
    "wof:placetype":"venue"
},
  "geometry": {"coordinates":[6.0662541389,51.154296875],"type":"Point"}
}