{
  "type": "Feature",
  "properties": {
    "iso:country":"NL",
    "sg:address":"Kennemerstraatweg 28",
    "sg:city":"Alkmaar",
    "sg:orig_category":"Marktonderzoekbureaus",
    "sg:phone":"+31 72 512 2929",
    "sg:postcode":"1815 LB",
    "sg:province":"Noord-Holland",
    "wof:name":"Douma Consultants",
    "wof:placetype":"venue"
},
  "geometry": {"coordinates":[4.735844,52.622726],"type":"Point"}
}