{
  "type": "Feature",
  "properties": {
    "addr:full":"Commandeur 1 Gemert Noord-Brabant 5421 LK",
    "addr:housenumber":"1",
    "addr:postcode":"5421 lk",
    "addr:street":"Commandeur",
    "iso:country":"NL",
    "sg:address":"Commandeur 1",
    "sg:city":"Gemert",
    "sg:classifiers":[
        {
            "category":"Fast Food",
            "type":"Food & Drink"
        }
    ],
    "sg:phone":"+31 492 368 202",
    "sg:postcode":"5421 LK",
    "sg:province":"Noord-Brabant",
    "sg:tags":[
        "afhaal",
        "restaurant"
    ],
    "wof:name":"Lunchroom Mickers",
    "wof:placetype":"venue"
},
  "geometry": {"coordinates":[5.682645,51.556843],"type":"Point"}
}