{
  "type": "Feature",
  "properties": {
    "addr:full":"Kosterijpad 6 Herwen Gelderland 6914 AV",
    "addr:housenumber":"6",
    "addr:postcode":"6914 av",
    "addr:street":"Kosterijpad;Gelderland",
    "iso:country":"NL",
    "sg:address":"Kosterijpad 6",
    "sg:city":"Herwen",
    "sg:orig_category":"Goederenvervoer Over De Weg",
    "sg:phone":"+31 316 247 637",
    "sg:postcode":"6914 AV",
    "sg:province":"Gelderland",
    "wof:name":"Transportbedrijf Saluut Bv",
    "wof:placetype":"venue"
},
  "geometry": {"coordinates":[6.103504,51.885136],"type":"Point"}
}