{
  "type": "Feature",
  "properties": {
    "addr:full":"Nieuwstraat 22 Weesp Noord-Holland 1381 BC",
    "addr:housenumber":"22",
    "addr:postcode":"1381 bc",
    "addr:street":"Nieuwstraat",
    "iso:country":"NL",
    "sg:address":"Nieuwstraat 22",
    "sg:city":"Weesp",
    "sg:orig_category":"Herenmodezaken",
    "sg:phone":"+31 294 412 454",
    "sg:postcode":"1381 BC",
    "sg:province":"Noord-Holland",
    "wof:name":"Ongers Herenmode",
    "wof:placetype":"venue"
},
  "geometry": {"coordinates":[5.041622,52.307728],"type":"Point"}
}