{
  "type": "Feature",
  "properties": {
    "iso:country":"NL",
    "sg:address":"Zilverpark 110",
    "sg:city":"'S Hertogenbosch",
    "sg:orig_category":"Verzekeringen",
    "sg:phone":"+31 73 642 8408",
    "sg:postcode":"5237 HT",
    "sg:province":"North Brabant",
    "wof:name":"V Heugten Verzekeringen",
    "wof:placetype":"venue"
},
  "geometry": {"coordinates":[5.293882,51.730453],"type":"Point"}
}