{
  "type": "Feature",
  "properties": {
    "addr:full":"Schuttevaerkd 12 Zwolle NL.08 8021 DB",
    "addr:housenumber":"12",
    "addr:postcode":"8021 db",
    "addr:street":"Schuttevaerkd",
    "iso:country":"NL",
    "sg:address":"Schuttevaerkd 12",
    "sg:city":"Zwolle",
    "sg:orig_category":"Binnenhuisarchitectuur",
    "sg:phone":"+31 38 465 8526",
    "sg:postcode":"8021 DB",
    "sg:province":"NL.08",
    "wof:name":"Stylet",
    "wof:placetype":"venue"
},
  "geometry": {"coordinates":[6.092656,52.516365],"type":"Point"}
}