{
  "type": "Feature",
  "properties": {
    "iso:country":"NL",
    "sg:address":"Westerkd 2",
    "sg:city":"Groningen",
    "sg:orig_category":"Vakorganisaties",
    "sg:phone":"+31 50 318 3318",
    "sg:postcode":"9718 AN",
    "sg:province":"Groningen",
    "sg:website":"http://www.cnv.nl/",
    "wof:name":"Cnv",
    "wof:placetype":"venue"
},
  "geometry": {"coordinates":[6.577923,53.260891],"type":"Point"}
}