{
  "type": "Feature",
  "properties": {
    "addr:full":"Den Texstr 40B Amsterdam Noord-Holland 1017 ZB",
    "addr:housenumber":"40b",
    "addr:postcode":"1017 zb",
    "iso:country":"NL",
    "sg:address":"Den Texstr 40B",
    "sg:city":"Amsterdam",
    "sg:orig_category":"Adviesbureaus Bedrijfsorganisatie",
    "sg:phone":"+31 20 625 3484",
    "sg:postcode":"1017 ZB",
    "sg:province":"Noord-Holland",
    "wof:name":"Horn, Jo",
    "wof:placetype":"venue"
},
  "geometry": {"coordinates":[4.89495,52.358707],"type":"Point"}
}