{
  "type": "Feature",
  "properties": {
    "addr:full":"Dommelsew 12A Valkenswaard North Brabant 5554 NR",
    "addr:housenumber":"12a",
    "addr:postcode":"5554 nr",
    "addr:street":"Dommelsew",
    "iso:country":"NL",
    "sg:address":"Dommelsew 12A",
    "sg:city":"Valkenswaard",
    "sg:orig_category":"Kappers",
    "sg:phone":"+31 40 201 4231",
    "sg:postcode":"5554 NR",
    "sg:province":"North Brabant",
    "wof:name":"Erp, M Van",
    "wof:placetype":"venue"
},
  "geometry": {"coordinates":[5.4555897713,51.3494338989],"type":"Point"}
}