{
  "type": "Feature",
  "properties": {
    "addr:full":"J V Renessepln 22 Gouda Zuid-Holland 2805 GT",
    "addr:housenumber":"22",
    "addr:postcode":"2805 gt",
    "addr:street":"J;Renessepln",
    "iso:country":"NL",
    "sg:address":"J V Renessepln 22",
    "sg:city":"Gouda",
    "sg:orig_category":"Medische Installaties En Instrumenten",
    "sg:phone":"+31 182 548 266",
    "sg:postcode":"2805 GT",
    "sg:province":"Zuid-Holland",
    "wof:name":"Medeq",
    "wof:placetype":"venue"
},
  "geometry": {"coordinates":[4.710715,52.010006],"type":"Point"}
}