{
  "type": "Feature",
  "properties": {
    "addr:full":"Vd Wateringeln 199 Voorburg South Holland 2274 CG",
    "addr:housenumber":"199",
    "addr:postcode":"2274 cg",
    "iso:country":"NL",
    "sg:address":"Vd Wateringeln 199",
    "sg:city":"Voorburg",
    "sg:orig_category":"Plafonds",
    "sg:phone":"+31 6 54746448",
    "sg:postcode":"2274 CG",
    "sg:province":"South Holland",
    "wof:name":"Boera",
    "wof:placetype":"venue"
},
  "geometry": {"coordinates":[4.345753,52.078518],"type":"Point"}
}