{
  "type": "Feature",
  "properties": {
    "addr:full":"Wolweversstr 5 Genemuiden Overijssel 8281 JL",
    "addr:housenumber":"5",
    "addr:postcode":"8281 jl",
    "addr:street":"Wolweversstr",
    "iso:country":"NL",
    "sg:address":"Wolweversstr 5",
    "sg:city":"Genemuiden",
    "sg:orig_category":"Banden",
    "sg:phone":"+31 38 385 7060",
    "sg:postcode":"8281 JL",
    "sg:province":"Overijssel",
    "wof:name":"Dijk, Van",
    "wof:placetype":"venue"
},
  "geometry": {"coordinates":[6.057858,52.627079],"type":"Point"}
}