{
  "type": "Feature",
  "properties": {
    "addr:full":"Ruurlosewg 70 Vorden Gelderland 7251 LV",
    "addr:housenumber":"70",
    "addr:postcode":"7251",
    "addr:street":"Ruurlosewg;Gelderland",
    "iso:country":"NL",
    "sg:address":"Ruurlosewg 70",
    "sg:city":"Vorden",
    "sg:orig_category":"Beeldende Kunstenaars",
    "sg:phone":"+31 575 556 554",
    "sg:postcode":"7251 LV",
    "sg:province":"Gelderland",
    "sg:website":"HTTP://www.animalart.nl",
    "wof:name":"Bosch, Gerda Van Den",
    "wof:placetype":"venue"
},
  "geometry": {"coordinates":[6.359467,52.101128],"type":"Point"}
}