{
  "type": "Feature",
  "properties": {
    "iso:country":"NL",
    "sg:address":"Grotestr 2",
    "sg:city":"Bedum",
    "sg:classifiers":[
        {
            "category":"Travel",
            "subcategory":"Hotels & Motels",
            "type":"Entertainment"
        }
    ],
    "sg:phone":"+31 50 301 2213",
    "sg:postcode":"9781 HC",
    "sg:province":"Groningen",
    "wof:name":"Gemeentehuis, 'T",
    "wof:placetype":"venue"
},
  "geometry": {"coordinates":[6.601542,53.301186],"type":"Point"}
}