{
  "type": "Feature",
  "properties": {
    "addr:full":"Meeuwenveld 1 Zoetermeer South Holland 2727 AK",
    "addr:housenumber":"1",
    "addr:postcode":"2727 ak",
    "addr:street":"Meeuwenveld",
    "iso:country":"NL",
    "sg:address":"Meeuwenveld 1",
    "sg:city":"Zoetermeer",
    "sg:orig_category":"Fitnesscentra",
    "sg:phone":"+31 79 331 3065",
    "sg:postcode":"2727 AK",
    "sg:province":"South Holland",
    "wof:name":"Impact",
    "wof:placetype":"venue"
},
  "geometry": {"coordinates":[4.509834,52.069462],"type":"Point"}
}