{
  "type": "Feature",
  "properties": {
    "addr:full":"Wijk 7 40 Urk Flevoland 8321 VM",
    "addr:housenumber":"40",
    "addr:postcode":"8321 vm",
    "addr:street":"Wijk 7;Flevoland",
    "iso:country":"NL",
    "sg:address":"Wijk 7 40",
    "sg:city":"Urk",
    "sg:orig_category":"Kappers",
    "sg:phone":"+31 527 681 400",
    "sg:postcode":"8321 VM",
    "sg:province":"Flevoland",
    "wof:name":"L. Visser",
    "wof:placetype":"venue"
},
  "geometry": {"coordinates":[5.59301,52.660984],"type":"Point"}
}