{
  "type": "Feature",
  "properties": {
    "addr:full":"Regoutstraat 4 Schiedam South Holland 3125 BH",
    "addr:housenumber":"4",
    "addr:postcode":"3125 bh",
    "addr:street":"Regoutstraat",
    "iso:country":"NL",
    "sg:address":"Regoutstraat 4",
    "sg:city":"Schiedam",
    "sg:orig_category":"Huishoudapparatuur, Televisies And Radio'S",
    "sg:phone":"+31 10 298 1777",
    "sg:postcode":"3125 BH",
    "sg:province":"South Holland",
    "wof:name":"Karwei Bouwmarkt Schiedam",
    "wof:placetype":"venue"
},
  "geometry": {"coordinates":[4.405182,51.930267],"type":"Point"}
}