{
  "type": "Feature",
  "properties": {
    "addr:full":"F Strouxstr 44 Stramproy Limburg 6039 GK",
    "addr:housenumber":"44",
    "addr:postcode":"6039 gk",
    "iso:country":"NL",
    "sg:address":"F Strouxstr 44",
    "sg:city":"Stramproy",
    "sg:classifiers":[
        {
            "category":"Sports & Exercise",
            "subcategory":"Stables",
            "type":"Entertainment"
        }
    ],
    "sg:phone":"+31 495 561 950",
    "sg:postcode":"6039 GK",
    "sg:province":"Limburg",
    "sg:tags":[
        "maneges"
    ],
    "wof:name":"Tw",
    "wof:placetype":"venue"
},
  "geometry": {"coordinates":[5.725062,51.185272],"type":"Point"}
}