{
  "type": "Feature",
  "properties": {
    "addr:full":"Voltastr 5D Zwolle Overijssel 8013 PM",
    "addr:housenumber":"5d",
    "addr:postcode":"8013 pm",
    "iso:country":"NL",
    "sg:address":"Voltastr 5D",
    "sg:city":"Zwolle",
    "sg:orig_category":"Verhuur",
    "sg:phone":"+31 38 465 6100",
    "sg:postcode":"8013 PM",
    "sg:province":"Overijssel",
    "sg:website":"http://www.boels.nl",
    "wof:name":"Boels Zwolle",
    "wof:placetype":"venue"
},
  "geometry": {"coordinates":[6.12868,52.490723],"type":"Point"}
}