{
  "type": "Feature",
  "properties": {
    "addr:full":"Oude Grintweg 69 Oirschot Noord-Brabant 5688 MB",
    "addr:housenumber":"69",
    "addr:postcode":"5688 mb",
    "addr:street":"Oude Grintweg",
    "iso:country":"NL",
    "sg:address":"Oude Grintweg 69",
    "sg:city":"Oirschot",
    "sg:orig_category":"Kampeerterreinen",
    "sg:phone":"+31 499 574 305",
    "sg:postcode":"5688 MB",
    "sg:province":"Noord-Brabant",
    "wof:name":"Camping De Bocht",
    "wof:placetype":"venue"
},
  "geometry": {"coordinates":[5.3085508347,51.5164718628],"type":"Point"}
}