{
  "type": "Feature",
  "properties": {
    "addr:full":"Postbus 193 Gorinchem Zuid-Holland 4200 AD",
    "addr:housenumber":"193",
    "addr:postcode":"4200 ad",
    "addr:street":"Postbus",
    "iso:country":"NL",
    "sg:address":"Postbus 193",
    "sg:city":"Gorinchem",
    "sg:orig_category":"Kantoorbenodigdheden",
    "sg:phone":"+31 183 565 344",
    "sg:postcode":"4200 AD",
    "sg:province":"Zuid-Holland",
    "sg:website":"http://www.offex.nl",
    "wof:name":"Offex",
    "wof:placetype":"venue"
},
  "geometry": {"coordinates":[4.9691848755,51.8306312561],"type":"Point"}
}