{
  "type": "Feature",
  "properties": {
    "addr:full":"Alb Agnesstr 2 Dordrecht South Holland 3314 LC",
    "addr:housenumber":"2",
    "addr:postcode":"3314 lc",
    "addr:street":"Agnesstr",
    "iso:country":"NL",
    "sg:address":"Alb Agnesstr 2",
    "sg:city":"Dordrecht",
    "sg:orig_category":"Zalenverhuur",
    "sg:phone":"+31 78 613 6382",
    "sg:postcode":"3314 LC",
    "sg:province":"South Holland",
    "wof:name":"Pauluskerk",
    "wof:placetype":"venue"
},
  "geometry": {"coordinates":[4.668206,51.803074],"type":"Point"}
}