{
  "type": "Feature",
  "properties": {
    "addr:full":"Waterstr 74 Halsteren Noord-Brabant 4661 RC",
    "addr:housenumber":"74",
    "addr:postcode":"4661 rc",
    "addr:street":"Waterstr",
    "iso:country":"NL",
    "sg:address":"Waterstr 74",
    "sg:city":"Halsteren",
    "sg:orig_category":"Administratie- En Boekhoudkantoren",
    "sg:phone":"+31 164 682 491",
    "sg:postcode":"4661 RC",
    "sg:province":"Noord-Brabant",
    "wof:name":"Krom, Jan De",
    "wof:placetype":"venue"
},
  "geometry": {"coordinates":[4.269271,51.535202],"type":"Point"}
}