{
  "type": "Feature",
  "properties": {
    "addr:full":"Pallieterburg 23 Capelle Ad Yssel South Holland 2907 CG",
    "addr:housenumber":"23",
    "addr:postcode":"2907 cg",
    "addr:street":"Pallieterburg;Yssel",
    "iso:country":"NL",
    "sg:address":"Pallieterburg 23",
    "sg:city":"Capelle Ad Yssel",
    "sg:classifiers":[
        {
            "category":"Personal",
            "subcategory":"Nail Salon",
            "type":"Services"
        }
    ],
    "sg:phone":"+31 10 451 5990",
    "sg:postcode":"2907 CG",
    "sg:province":"South Holland",
    "sg:tags":[
        "pedicure"
    ],
    "wof:name":"Vliet, P J Van",
    "wof:placetype":"venue"
},
  "geometry": {"coordinates":[4.577258,51.952072],"type":"Point"}
}