{
  "type": "Feature",
  "properties": {
    "addr:full":"Assendorperdk 132 Zwolle Overijssel 8012 EJ",
    "addr:housenumber":"132",
    "addr:postcode":"8012 ej",
    "iso:country":"NL",
    "sg:address":"Assendorperdk 132",
    "sg:city":"Zwolle",
    "sg:orig_category":"Acupunctuur",
    "sg:phone":"+31 38 422 1472",
    "sg:postcode":"8012 EJ",
    "sg:province":"Overijssel",
    "wof:name":"Tichelaar, H",
    "wof:placetype":"venue"
},
  "geometry": {"coordinates":[6.106847,52.505135],"type":"Point"}
}