{
  "type": "Feature",
  "properties": {
    "addr:full":"President Kennedylaan 30 Middelburg Zeeland 4334 EJ",
    "addr:housenumber":"30",
    "addr:postcode":"4334 ej",
    "addr:street":"President Kennedylaan",
    "iso:country":"NL",
    "sg:address":"President Kennedylaan 30",
    "sg:city":"Middelburg",
    "sg:orig_category":"Verzekeringen",
    "sg:phone":"+31 118 611 529",
    "sg:postcode":"4334 EJ",
    "sg:province":"Zeeland",
    "wof:name":"Van Velsen Assurantien",
    "wof:placetype":"venue"
},
  "geometry": {"coordinates":[3.590578,51.503082],"type":"Point"}
}