{
  "type": "Feature",
  "properties": {
    "addr:full":"Kerkwg 38 Cothen Utrecht 3945 BN",
    "addr:housenumber":"38",
    "addr:postcode":"3945 bn",
    "addr:street":"Kerkwg",
    "iso:country":"NL",
    "sg:address":"Kerkwg 38",
    "sg:city":"Cothen",
    "sg:orig_category":"Metselwerken",
    "sg:phone":"+31 343 561 365",
    "sg:postcode":"3945 BN",
    "sg:province":"Utrecht",
    "wof:name":"Balk Bv, J",
    "wof:placetype":"venue"
},
  "geometry": {"coordinates":[5.307057,51.999344],"type":"Point"}
}