{
  "type": "Feature",
  "properties": {
    "addr:full":"Haagdk 50 Breda North Brabant 4811 TV",
    "addr:housenumber":"50",
    "addr:postcode":"4811 tv",
    "addr:street":"Haagdk",
    "iso:country":"NL",
    "sg:address":"Haagdk 50",
    "sg:city":"Breda",
    "sg:orig_category":"Kasten - Fabrieken En Groothandel",
    "sg:phone":"+31 76 522 8533",
    "sg:postcode":"4811 TV",
    "sg:province":"North Brabant",
    "sg:website":"http://www.kasten.nl",
    "wof:name":"Jongwonen/Kastsystemen",
    "wof:placetype":"venue"
},
  "geometry": {"coordinates":[4.769744,51.588268],"type":"Point"}
}