{
  "type": "Feature",
  "properties": {
    "iso:country":"NL",
    "sg:address":"Noorderstr 195",
    "sg:city":"Sappemeer",
    "sg:orig_category":"Discotheken",
    "sg:phone":"+31 598 396 266",
    "sg:postcode":"9611 AE",
    "sg:province":"Groningen",
    "wof:name":"Avenue",
    "wof:placetype":"venue"
},
  "geometry": {"coordinates":[6.794903,53.164379],"type":"Point"}
}