{
  "type": "Feature",
  "properties": {
    "addr:full":"Krakeend 41 Uithoorn North Holland 1423 ST",
    "addr:housenumber":"41",
    "addr:postcode":"1423 st",
    "addr:street":"Krakeend",
    "iso:country":"NL",
    "sg:address":"Krakeend 41",
    "sg:city":"Uithoorn",
    "sg:orig_category":"Werving And Selectie Van Tijdelijk Personeel And Uitzendkantoren",
    "sg:phone":"+31 297 521 655",
    "sg:postcode":"1423 ST",
    "sg:province":"North Holland",
    "wof:name":"Huisman Management Bv",
    "wof:placetype":"venue"
},
  "geometry": {"coordinates":[4.814455986,52.2357749939],"type":"Point"}
}