{
  "type": "Feature",
  "properties": {
    "addr:full":"Becanusstr 13Bo3 Maastricht Limburg 6216 BX",
    "addr:housenumber":"13bo3",
    "addr:postcode":"6216 bx",
    "iso:country":"NL",
    "sg:address":"Becanusstr 13Bo3",
    "sg:city":"Maastricht",
    "sg:orig_category":"Adviesbureaus Chemische Techniek",
    "sg:phone":"+31 43 354 1280",
    "sg:postcode":"6216 BX",
    "sg:province":"Limburg",
    "wof:name":"Csma Ltd",
    "wof:placetype":"venue"
},
  "geometry": {"coordinates":[5.669866,50.849545],"type":"Point"}
}