{
  "type": "Feature",
  "properties": {
    "addr:full":"Einsteinstr 85 Kudelstaart Noord-Holland 1433 KJ",
    "addr:housenumber":"85",
    "addr:postcode":"1433 kj",
    "addr:street":"Einsteinstr",
    "iso:country":"NL",
    "sg:address":"Einsteinstr 85",
    "sg:city":"Kudelstaart",
    "sg:orig_category":"Huishoudelijke Apparaten En Artikelen",
    "sg:phone":"+31 297 362 990",
    "sg:postcode":"1433 KJ",
    "sg:province":"Noord-Holland",
    "wof:name":"Berg",
    "wof:placetype":"venue"
},
  "geometry": {"coordinates":[4.750021,52.234669],"type":"Point"}
}