{
  "type": "Feature",
  "properties": {
    "addr:full":"Zuidhof 14 Geleen Limburg 6164 BA",
    "addr:housenumber":"14",
    "addr:postcode":"6164 ba",
    "addr:street":"Zuidhof",
    "iso:country":"NL",
    "sg:address":"Zuidhof 14",
    "sg:city":"Geleen",
    "sg:classifiers":[
        {
            "category":"Food & Beverages",
            "subcategory":"Bakery",
            "type":"Retail Goods"
        }
    ],
    "sg:phone":"+31 46 474 8111",
    "sg:postcode":"6164 BA",
    "sg:province":"Limburg",
    "sg:tags":[
        "brood",
        "en",
        "banket"
    ],
    "wof:name":"Steevens Bv",
    "wof:placetype":"venue"
},
  "geometry": {"coordinates":[5.826336,50.957588],"type":"Point"}
}