{
  "type": "Feature",
  "properties": {
    "addr:full":"Willemstraat 30 Utrecht Utrecht 3511 RK",
    "addr:housenumber":"30",
    "addr:postcode":"3511 rk",
    "addr:street":"Willemstraat",
    "iso:country":"NL",
    "sg:address":"Willemstraat 30",
    "sg:city":"Utrecht",
    "sg:orig_category":"Verlichting And Huishoudartikelen",
    "sg:phone":"+31 30 231 8461",
    "sg:postcode":"3511 RK",
    "sg:province":"Utrecht",
    "wof:name":"Firma G. Van Lunteren En Zoon",
    "wof:placetype":"venue"
},
  "geometry": {"coordinates":[5.113124,52.094124],"type":"Point"}
}