{
  "type": "Feature",
  "properties": {
    "addr:full":"Mussentiend 21 Veen Noord-Brabant 4264 RR",
    "addr:housenumber":"21",
    "addr:postcode":"4264 rr",
    "addr:street":"Mussentiend",
    "iso:country":"NL",
    "sg:address":"Mussentiend 21",
    "sg:city":"Veen",
    "sg:orig_category":"Bloemen And Planten Gh",
    "sg:phone":"+31 416 692 818",
    "sg:postcode":"4264 RR",
    "sg:province":"Noord-Brabant",
    "wof:name":"G.C. Kwetters",
    "wof:placetype":"venue"
},
  "geometry": {"coordinates":[-61.766769,1.84229],"type":"Point"}
}