{
  "type": "Feature",
  "properties": {
    "iso:country":"NL",
    "sg:address":"Brinklaan 72",
    "sg:city":"Bussum",
    "sg:orig_category":"Juweliers",
    "sg:phone":"+31 35 691 8787",
    "sg:postcode":"1404 GL",
    "sg:province":"Noord-Holland",
    "wof:name":"Firma D Wielinga En Zoon",
    "wof:placetype":"venue"
},
  "geometry": {"coordinates":[5.162432,52.274387],"type":"Point"}
}