{
  "type": "Feature",
  "properties": {
    "addr:full":"Van Heemstraweg 37 Winssen Gelderland 6645 KE",
    "addr:housenumber":"37",
    "addr:postcode":"6645 ke",
    "addr:street":"Van Heemstraweg;Gelderland",
    "iso:country":"NL",
    "sg:address":"Van Heemstraweg 37",
    "sg:city":"Winssen",
    "sg:orig_category":"Levende Dieren Gh",
    "sg:phone":"+31 487 521 747",
    "sg:postcode":"6645 KE",
    "sg:province":"Gelderland",
    "wof:name":"Vof Degen Auto'S",
    "wof:placetype":"venue"
},
  "geometry": {"coordinates":[5.724656,51.874214],"type":"Point"}
}