{
  "type": "Feature",
  "properties": {
    "iso:country":"NL",
    "sg:address":"Nieuwstr 22A",
    "sg:city":"Alphen Nb",
    "sg:orig_category":"Kaas",
    "sg:phone":"+31 13 508 1606",
    "sg:postcode":"5131 BH",
    "sg:province":"North Brabant",
    "wof:name":"Joppe Vof, R C",
    "wof:placetype":"venue"
},
  "geometry": {"coordinates":[4.9570307732,51.4782943726],"type":"Point"}
}