{
  "type": "Feature",
  "properties": {
    "iso:country":"NL",
    "sg:address":"Croessrak 17",
    "sg:city":"Leusden",
    "sg:orig_category":"Metaalwerken",
    "sg:phone":"+31 33 494 0716",
    "sg:postcode":"3833 KN",
    "sg:province":"Utrecht",
    "wof:name":"Rostol",
    "wof:placetype":"venue"
},
  "geometry": {"coordinates":[5.421478,52.124084],"type":"Point"}
}