{
  "type": "Feature",
  "properties": {
    "addr:full":"Nyverheidstr 55 Bemmel Gelderland 6681 LN",
    "addr:housenumber":"55",
    "addr:postcode":"6681 ln",
    "addr:street":"Nyverheidstr;Gelderland",
    "iso:country":"NL",
    "sg:address":"Nyverheidstr 55",
    "sg:city":"Bemmel",
    "sg:orig_category":"Onderhoudswerken",
    "sg:phone":"+31 26 326 0010",
    "sg:postcode":"6681 LN",
    "sg:province":"Gelderland",
    "wof:name":"Hagemans Service",
    "wof:placetype":"venue"
},
  "geometry": {"coordinates":[5.92665,51.907234],"type":"Point"}
}