{
  "type": "Feature",
  "properties": {
    "addr:full":"Rosariumlaan 21 Driebergen-Rijsenburg Utrecht 3972 GE",
    "addr:housenumber":"21",
    "addr:postcode":"3972",
    "addr:street":"Rosariumlaan",
    "iso:country":"NL",
    "sg:address":"Rosariumlaan 21",
    "sg:city":"Driebergen-Rijsenburg",
    "sg:orig_category":"Bedrijfs- And Managementsconsultants",
    "sg:phone":"+31 343 517 744",
    "sg:postcode":"3972 GE",
    "sg:province":"Utrecht",
    "wof:name":"Boog Advies",
    "wof:placetype":"venue"
},
  "geometry": {"coordinates":[5.289455,52.048031],"type":"Point"}
}