{
  "type": "Feature",
  "properties": {
    "addr:full":"Vollevenstraat 2 Geertruidenberg North Brabant 4931 VC",
    "addr:housenumber":"2",
    "addr:postcode":"4931 vc",
    "addr:street":"Vollevenstraat",
    "iso:country":"NL",
    "sg:address":"Vollevenstraat 2",
    "sg:city":"Geertruidenberg",
    "sg:orig_category":"Meubelreparatie And -Restauratie",
    "sg:phone":"+31 162 520 031",
    "sg:postcode":"4931 VC",
    "sg:province":"North Brabant",
    "wof:name":"H. Brandenberg",
    "wof:placetype":"venue"
},
  "geometry": {"coordinates":[4.846045,51.704105],"type":"Point"}
}