{
  "type": "Feature",
  "properties": {
    "addr:full":"Haarlemerhouttuinen 37-43 Amsterdam North Holland 1013 GM",
    "addr:housenumber":"37-43",
    "addr:postcode":"1013 gm",
    "iso:country":"NL",
    "sg:address":"Haarlemerhouttuinen 37-43",
    "sg:city":"Amsterdam",
    "sg:orig_category":"Meubelzaken, Woning- And Keukeninrichting",
    "sg:phone":"+31 20 625 2109",
    "sg:postcode":"1013 GM",
    "sg:province":"North Holland",
    "wof:name":"Corelli Slaapkamers",
    "wof:placetype":"venue"
},
  "geometry": {"coordinates":[4.891592,52.380917],"type":"Point"}
}