{
  "type": "Feature",
  "properties": {
    "addr:full":"Wilhelminastr 20 Boxtel Noord-Brabant 5281 GR",
    "addr:housenumber":"20",
    "addr:postcode":"5281",
    "addr:street":"Wilhelminastr",
    "iso:country":"NL",
    "sg:address":"Wilhelminastr 20",
    "sg:city":"Boxtel",
    "sg:orig_category":"Makelaars En Adviseurs Onroerende Goederen",
    "sg:phone":"+31 411 611 404",
    "sg:postcode":"5281 GR",
    "sg:province":"Noord-Brabant",
    "wof:name":"Huijskenners, De",
    "wof:placetype":"venue"
},
  "geometry": {"coordinates":[5.319466,51.586159],"type":"Point"}
}