{
  "type": "Feature",
  "properties": {
    "addr:full":"Oldenzaalsestraat 761 Enschede Overijssel 7524 AD",
    "addr:housenumber":"761",
    "addr:postcode":"7524 ad",
    "addr:street":"Oldenzaalsestraat",
    "iso:country":"NL",
    "sg:address":"Oldenzaalsestraat 761",
    "sg:city":"Enschede",
    "sg:orig_category":"Elektronische Bedrijfsinstallaties",
    "sg:phone":"+31 53 433 4602",
    "sg:postcode":"7524 AD",
    "sg:province":"Overijssel",
    "wof:name":"Camview Electronic",
    "wof:placetype":"venue"
},
  "geometry": {"coordinates":[6.91764,52.256451],"type":"Point"}
}