{
  "type": "Feature",
  "properties": {
    "addr:full":"J H W Robersstr 150 Enschede Overijssel 7545 HG",
    "addr:housenumber":"150",
    "addr:postcode":"7545 hg",
    "iso:country":"NL",
    "sg:address":"J H W Robersstr 150",
    "sg:city":"Enschede",
    "sg:orig_category":"Orthopedische Artikelen",
    "sg:phone":"+31 53 430 2493",
    "sg:postcode":"7545 HG",
    "sg:province":"Overijssel",
    "wof:name":"Springer",
    "wof:placetype":"venue"
},
  "geometry": {"coordinates":[6.8640871048,52.2123641968],"type":"Point"}
}