{
  "type": "Feature",
  "properties": {
    "iso:country":"NL",
    "sg:address":"Bakkerstr 10",
    "sg:city":"Reusel",
    "sg:classifiers":[
        {
            "category":"Personal",
            "subcategory":"Nail Salon",
            "type":"Services"
        }
    ],
    "sg:phone":"+31 497 620 055",
    "sg:postcode":"5541 VC",
    "sg:province":"Noord-Brabant",
    "sg:tags":[
        "pedicure"
    ],
    "wof:name":"Basemans",
    "wof:placetype":"venue"
},
  "geometry": {"coordinates":[5.165398,51.362949],"type":"Point"}
}