{
  "type": "Feature",
  "properties": {
    "addr:full":"Rotterdamsewg 111 Delft South Holland 2628 AK",
    "addr:housenumber":"111",
    "addr:postcode":"2628 ak",
    "iso:country":"NL",
    "sg:address":"Rotterdamsewg 111",
    "sg:city":"Delft",
    "sg:orig_category":"Psychologen",
    "sg:phone":"+31 15 257 0254",
    "sg:postcode":"2628 AK",
    "sg:province":"South Holland",
    "wof:name":"Doeksen, T C",
    "wof:placetype":"venue"
},
  "geometry": {"coordinates":[4.365384,52.003578],"type":"Point"}
}