{
  "type": "Feature",
  "properties": {
    "iso:country":"NL",
    "sg:address":"Poeldijksepad 36",
    "sg:city":"Honselersdijk",
    "sg:orig_category":"Bloemen And Planten",
    "sg:phone":"+31 174 247 962",
    "sg:postcode":"2675 CM",
    "sg:province":"South Holland",
    "wof:name":"Fa J.W. Van Kester & Zn",
    "wof:placetype":"venue"
},
  "geometry": {"coordinates":[4.222935,52.020077],"type":"Point"}
}