{
  "type": "Feature",
  "properties": {
    "iso:country":"NL",
    "sg:address":"Bloemenschans 18",
    "sg:city":"Voorhout",
    "sg:orig_category":"Evenementenverzorging",
    "sg:phone":"+31 252 213 749",
    "sg:postcode":"2215 DE",
    "sg:province":"Zuid-Holland",
    "wof:name":"Abc",
    "wof:placetype":"venue"
},
  "geometry": {"coordinates":[4.489138,52.222057],"type":"Point"}
}