{
  "type": "Feature",
  "properties": {
    "addr:full":"Valeriusstraat 73 Zevenaar Gelderland 6904 DL",
    "addr:housenumber":"73",
    "addr:postcode":"6904 dl",
    "addr:street":"Valeriusstraat",
    "iso:country":"NL",
    "sg:address":"Valeriusstraat 73",
    "sg:city":"Zevenaar",
    "sg:orig_category":"Vertaal- And Tolkenbureaus",
    "sg:phone":"+31 316 529 770",
    "sg:postcode":"6904 DL",
    "sg:province":"Gelderland",
    "wof:name":"Vertaalbureau Elaine Bohlken",
    "wof:placetype":"venue"
},
  "geometry": {"coordinates":[6.060186,51.928101],"type":"Point"}
}