{
  "type": "Feature",
  "properties": {
    "iso:country":"NL",
    "sg:address":"Muurhuizen 159",
    "sg:city":"Amersfoort",
    "sg:orig_category":"Architecten En Architectenbureaus",
    "sg:phone":"+31 33 465 9988",
    "sg:postcode":"3811 EG",
    "sg:province":"Utrecht",
    "wof:name":"Schweigmann, J G",
    "wof:placetype":"venue"
},
  "geometry": {"coordinates":[5.391715,52.157612],"type":"Point"}
}