{
  "type": "Feature",
  "properties": {
    "addr:full":"Ds O Veeningln 6 Oldebroek Gelderland 8096 XE",
    "addr:housenumber":"6",
    "addr:postcode":"8096 xe",
    "addr:street":"Ds O Veeningln;Gelderland",
    "iso:country":"NL",
    "sg:address":"Ds O Veeningln 6",
    "sg:city":"Oldebroek",
    "sg:orig_category":"Ongediertebestrijding En Ontsmetting",
    "sg:phone":"+31 525 632 722",
    "sg:postcode":"8096 XE",
    "sg:province":"Gelderland",
    "wof:name":"B & W Vof",
    "wof:placetype":"venue"
},
  "geometry": {"coordinates":[5.8934,52.445419],"type":"Point"}
}