{
  "type": "Feature",
  "properties": {
    "addr:full":"Schoenmaeckersstr 10 Geleen Limburg 6163 BW",
    "addr:housenumber":"10",
    "addr:postcode":"6163 bw",
    "addr:street":"Schoenmaeckersstr",
    "iso:country":"NL",
    "sg:address":"Schoenmaeckersstr 10",
    "sg:city":"Geleen",
    "sg:orig_category":"Bibliotheken En Leeszalen Openbare",
    "sg:phone":"+31 46 474 4157",
    "sg:postcode":"6163 BW",
    "sg:province":"Limburg",
    "wof:name":"Openb Bibliotheek",
    "wof:placetype":"venue"
},
  "geometry": {"coordinates":[5.817771,50.983662],"type":"Point"}
}