{
  "type": "Feature",
  "properties": {
    "addr:full":"Markt 67 Bergum Friesland 9251 JR",
    "addr:housenumber":"67",
    "addr:postcode":"9251 jr",
    "addr:street":"Markt",
    "iso:country":"NL",
    "sg:address":"Markt 67",
    "sg:city":"Bergum",
    "sg:orig_category":"Kappers",
    "sg:phone":"+31 511 481 219",
    "sg:postcode":"9251 JR",
    "sg:province":"Friesland",
    "wof:name":"Haarzaak",
    "wof:placetype":"venue"
},
  "geometry": {"coordinates":[5.9922690392,53.191696167],"type":"Point"}
}