{
  "type": "Feature",
  "properties": {
    "addr:full":"Postbus 342 Putten Gelderland 3880 AH",
    "addr:housenumber":"342",
    "addr:postcode":"3880 ah",
    "addr:street":"Postbus;Gelderland",
    "iso:country":"NL",
    "sg:address":"Postbus 342",
    "sg:city":"Putten",
    "sg:orig_category":"Bodemonderzoek",
    "sg:phone":"+31 341 361 268",
    "sg:postcode":"3880 AH",
    "sg:province":"Gelderland",
    "sg:website":"http://www.elementair.net",
    "wof:name":"Elementair",
    "wof:placetype":"venue"
},
  "geometry": {"coordinates":[5.605482,52.257221],"type":"Point"}
}