{
  "type": "Feature",
  "properties": {
    "addr:full":"Staringstraat 27 Nieuw Vennep North Holland 2152 CW",
    "addr:housenumber":"27",
    "addr:postcode":"2152 cw",
    "addr:street":"Staringstraat;Nieuw Vennep North",
    "iso:country":"NL",
    "sg:address":"Staringstraat 27",
    "sg:city":"Nieuw Vennep",
    "sg:orig_category":"Diverse Grafische Activiteiten",
    "sg:phone":"+31 252 672 284",
    "sg:postcode":"2152 CW",
    "sg:province":"North Holland",
    "wof:name":"Bv Boekbinderij Erven Kramer",
    "wof:placetype":"venue"
},
  "geometry": {"coordinates":[4.627703,52.27206],"type":"Point"}
}