{
  "type": "Feature",
  "properties": {
    "addr:full":"Achterhoeksestr 55 Rucphen North Brabant 4715 BD",
    "addr:housenumber":"55",
    "addr:postcode":"4715 bd",
    "addr:street":"Achterhoeksestr",
    "iso:country":"NL",
    "sg:address":"Achterhoeksestr 55",
    "sg:city":"Rucphen",
    "sg:orig_category":"Onderhoudswerken",
    "sg:phone":"+31 165 342 207",
    "sg:postcode":"4715 BD",
    "sg:province":"North Brabant",
    "wof:name":"Brouwers",
    "wof:placetype":"venue"
},
  "geometry": {"coordinates":[4.559645,51.536186],"type":"Point"}
}