{
  "type": "Feature",
  "properties": {
    "addr:full":"Nykerkstr 41 Tilburg Noord-Brabant 5045 MC",
    "addr:housenumber":"41",
    "addr:postcode":"5045 mc",
    "addr:street":"Nykerkstr",
    "iso:country":"NL",
    "sg:address":"Nykerkstr 41",
    "sg:city":"Tilburg",
    "sg:orig_category":"Adviesbureaus Bedrijfsorganisatie",
    "sg:phone":"+31 13 571 8144",
    "sg:postcode":"5045 MC",
    "sg:province":"Noord-Brabant",
    "sg:website":"http://www.eventis.nl",
    "wof:name":"Eventis Bv",
    "wof:placetype":"venue"
},
  "geometry": {"coordinates":[4.98149,51.59214],"type":"Point"}
}