{
  "type": "Feature",
  "properties": {
    "addr:full":"Leywg 156B S Gravenhage Zuid-Holland 2545 CX",
    "addr:housenumber":"156b;gravenhage",
    "addr:postcode":"2545 cx",
    "addr:street":"S",
    "iso:country":"NL",
    "sg:address":"Leywg 156B",
    "sg:city":"S Gravenhage",
    "sg:orig_category":"Autorijscholen",
    "sg:phone":"+31 70 368 1068",
    "sg:postcode":"2545 CX",
    "sg:province":"Zuid-Holland",
    "wof:name":"Haas",
    "wof:placetype":"venue"
},
  "geometry": {"coordinates":[4.27049,52.05093],"type":"Point"}
}