{
  "type": "Feature",
  "properties": {
    "addr:full":"De Pinckart 25 Nuenen Noord-Brabant 5674 CB",
    "addr:housenumber":"25",
    "addr:postcode":"5674 cb",
    "addr:street":"De Pinckart",
    "iso:country":"NL",
    "sg:address":"De Pinckart 25",
    "sg:city":"Nuenen",
    "sg:orig_category":"Administratie- En Boekhoudkantoren",
    "sg:phone":"+31 40 283 5500",
    "sg:postcode":"5674 CB",
    "sg:province":"Noord-Brabant",
    "wof:name":"Jan Heijers Bv",
    "wof:placetype":"venue"
},
  "geometry": {"coordinates":[5.53304,51.466839],"type":"Point"}
}