{
  "type": "Feature",
  "properties": {
    "iso:country":"NL",
    "sg:address":"Gemeenlandsedk N 5",
    "sg:city":"Abbenbroek",
    "sg:orig_category":"Verhuur",
    "sg:phone":"+31 181 669 275",
    "sg:postcode":"3216 AG",
    "sg:province":"South Holland",
    "sg:website":"http://www.pvm.nl/pleasurerent/",
    "wof:name":"Pleasure",
    "wof:placetype":"venue"
},
  "geometry": {"coordinates":[4.243377,51.849483],"type":"Point"}
}