{
  "type": "Feature",
  "properties": {
    "addr:full":"Rippingstr 16A Alkmaar Noord-Holland 1814 HP",
    "addr:housenumber":"16a",
    "addr:postcode":"1814 hp",
    "addr:street":"Rippingstr",
    "iso:country":"NL",
    "sg:address":"Rippingstr 16A",
    "sg:city":"Alkmaar",
    "sg:orig_category":"Schoenen",
    "sg:phone":"+31 72 520 3368",
    "sg:postcode":"1814 HP",
    "sg:province":"Noord-Holland",
    "wof:name":"Kleine Voetjes",
    "wof:placetype":"venue"
},
  "geometry": {"coordinates":[4.737925,52.622452],"type":"Point"}
}