{
  "type": "Feature",
  "properties": {
    "addr:full":"Kapelstr 53 Veghel Noord-Brabant 5466 PB",
    "addr:housenumber":"53",
    "addr:postcode":"5466 pb",
    "addr:street":"Kapelstr",
    "iso:country":"NL",
    "sg:address":"Kapelstr 53",
    "sg:city":"Veghel",
    "sg:orig_category":"Kousen - Fabrieken En Groothandel",
    "sg:phone":"+31 413 363 774",
    "sg:postcode":"5466 PB",
    "sg:province":"Noord-Brabant",
    "wof:name":"Bouwmans Eerde Bv, W H",
    "wof:placetype":"venue"
},
  "geometry": {"coordinates":[5.495695,51.60524],"type":"Point"}
}