{
  "type": "Feature",
  "properties": {
    "addr:full":"Espenhof 4 Papendrecht South Holland 3355 BM",
    "addr:housenumber":"4",
    "addr:postcode":"3355 bm",
    "addr:street":"Espenhof",
    "iso:country":"NL",
    "sg:address":"Espenhof 4",
    "sg:city":"Papendrecht",
    "sg:classifiers":[
        {
            "category":"Fast Food",
            "type":"Food & Drink"
        }
    ],
    "sg:phone":"+31 78 641 3136",
    "sg:postcode":"3355 BM",
    "sg:province":"South Holland",
    "sg:tags":[
        "afhaal",
        "restaurant"
    ],
    "wof:name":"Hap Snap Papendrecht",
    "wof:placetype":"venue"
},
  "geometry": {"coordinates":[4.701595,51.836674],"type":"Point"}
}