{
  "type": "Feature",
  "properties": {
    "iso:country":"NL",
    "sg:address":"H Schaftln 3",
    "sg:city":"Olst",
    "sg:orig_category":"Administratie- En Boekhoudkantoren",
    "sg:phone":"+31 570 562 260",
    "sg:postcode":"8121 KE",
    "sg:province":"Overijssel",
    "wof:name":"Pierik & Jansen",
    "wof:placetype":"venue"
},
  "geometry": {"coordinates":[6.111195,52.333652],"type":"Point"}
}