{
  "type": "Feature",
  "properties": {
    "addr:full":"Nieuwewg 9 Honselersdyk Zuid-Holland 2675 BC",
    "addr:housenumber":"9",
    "addr:postcode":"2675 bc",
    "addr:street":"Nieuwewg",
    "iso:country":"NL",
    "sg:address":"Nieuwewg 9",
    "sg:city":"Honselersdyk",
    "sg:orig_category":"Bloemen En Planten",
    "sg:phone":"+31 174 623 798",
    "sg:postcode":"2675 BC",
    "sg:province":"Zuid-Holland",
    "wof:name":"Boschwoning, Firma",
    "wof:placetype":"venue"
},
  "geometry": {"coordinates":[-126.555511,54.485668],"type":"Point"}
}