{
  "type": "Feature",
  "properties": {
    "addr:full":"Patrimoniumlaan 67 Veenendaal Utrecht 3904 AB",
    "addr:housenumber":"67",
    "addr:postcode":"3904 ab",
    "addr:street":"Patrimoniumlaan",
    "iso:country":"NL",
    "sg:address":"Patrimoniumlaan 67",
    "sg:city":"Veenendaal",
    "sg:orig_category":"Bedrijfs- And Managementsconsultants",
    "sg:phone":"+31 318 552 200",
    "sg:postcode":"3904 AB",
    "sg:province":"Utrecht",
    "wof:name":"Van Den Helder Fin. Adviseur",
    "wof:placetype":"venue"
},
  "geometry": {"coordinates":[5.544257,52.019428],"type":"Point"}
}