{
  "type": "Feature",
  "properties": {
    "addr:full":"Chassestraat 87 Amsterdam Noord-Holland 1057 JB",
    "addr:housenumber":"87",
    "addr:postcode":"1057 jb",
    "addr:street":"Chassestraat",
    "iso:country":"NL",
    "sg:address":"Chassestraat 87",
    "sg:city":"Amsterdam",
    "sg:orig_category":"Overheidsdiensten",
    "sg:phone":"+31 20 616 1119",
    "sg:postcode":"1057 JB",
    "sg:province":"Noord-Holland",
    "wof:name":"Atalanta",
    "wof:placetype":"venue"
},
  "geometry": {"coordinates":[4.8610181808,52.3701019287],"type":"Point"}
}