{
  "type": "Feature",
  "properties": {
    "iso:country":"NL",
    "sg:address":"Heerenwg 109",
    "sg:city":"Heiloo",
    "sg:orig_category":"Hondenscholen",
    "sg:phone":"+31 72 533 4290",
    "sg:postcode":"1851 KM",
    "sg:province":"Noord-Holland",
    "wof:name":"Kynologenclub W-Friesland",
    "wof:placetype":"venue"
},
  "geometry": {"coordinates":[4.708204,52.603382],"type":"Point"}
}