{
  "type": "Feature",
  "properties": {
    "addr:full":"Ryksstrwg 19B Heemskerk North Holland 1969 LB",
    "addr:housenumber":"19b",
    "addr:postcode":"1969 lb",
    "addr:street":"Ryksstrwg",
    "iso:country":"NL",
    "sg:address":"Ryksstrwg 19B",
    "sg:city":"Heemskerk",
    "sg:orig_category":"Kantoor- En Bedrijfsmeubelen",
    "sg:phone":"+31 251 252 288",
    "sg:postcode":"1969 LB",
    "sg:province":"North Holland",
    "sg:website":"http://www.lnpartners.nl",
    "wof:name":"L&N Partners Voor Partners Bv",
    "wof:placetype":"venue"
},
  "geometry": {"coordinates":[4.626871109,52.5072135925],"type":"Point"}
}