{
  "type": "Feature",
  "properties": {
    "addr:full":"Zutphensestraat 26 Apeldoorn Gelderland 7321 CL",
    "addr:housenumber":"26",
    "addr:postcode":"7321",
    "addr:street":"Zutphensestraat;Gelderland",
    "iso:country":"NL",
    "sg:address":"Zutphensestraat 26",
    "sg:city":"Apeldoorn",
    "sg:orig_category":"Loodgieterswerk, Verwarming And Sanitaire Installaties",
    "sg:phone":"+31 55 360 2868",
    "sg:postcode":"7321 CL",
    "sg:province":"Gelderland",
    "wof:name":"Hylkema",
    "wof:placetype":"venue"
},
  "geometry": {"coordinates":[5.990197,52.212975],"type":"Point"}
}