{
  "type": "Feature",
  "properties": {
    "addr:full":"Zytak Oz 1 Nieuw Amsterdam Drenthe 7833 AL",
    "addr:housenumber":"1",
    "addr:postcode":"7833 al",
    "addr:street":"Zytak Oz;Nieuw",
    "iso:country":"NL",
    "sg:address":"Zytak Oz 1",
    "sg:city":"Nieuw Amsterdam",
    "sg:classifiers":[
        {
            "category":"Restaurant",
            "type":"Food & Drink"
        }
    ],
    "sg:phone":"+31 591 553 320",
    "sg:postcode":"7833 AL",
    "sg:province":"Drenthe",
    "wof:name":"Viersprong, De",
    "wof:placetype":"venue"
},
  "geometry": {"coordinates":[-94.605186,38.381996],"type":"Point"}
}