{
  "type": "Feature",
  "properties": {
    "iso:country":"NL",
    "sg:address":"Plein 1945 20",
    "sg:city":"Petten",
    "sg:classifiers":[
        {
            "category":"Food & Beverages",
            "subcategory":"Bakery",
            "type":"Retail Goods"
        }
    ],
    "sg:phone":"+31 226 383 126",
    "sg:postcode":"1755 NJ",
    "sg:province":"New Jersey",
    "sg:tags":[
        "brood",
        "en",
        "banket"
    ],
    "wof:name":"Barten, P",
    "wof:placetype":"venue"
},
  "geometry": {"coordinates":[-74.72672300000001,40.14278],"type":"Point"}
}