{
  "type": "Feature",
  "properties": {
    "addr:full":"Beethovenlaan 114 Aalsmeer Noord-Holland 1431 WZ",
    "addr:housenumber":"114",
    "addr:postcode":"1431 wz",
    "addr:street":"Beethovenlaan",
    "iso:country":"NL",
    "sg:address":"Beethovenlaan 114",
    "sg:city":"Aalsmeer",
    "sg:orig_category":"Sportcentra",
    "sg:phone":"+31 297 329 970",
    "sg:postcode":"1431 WZ",
    "sg:province":"Noord-Holland",
    "wof:name":"Racket Sport Aalsmeer",
    "wof:placetype":"venue"
},
  "geometry": {"coordinates":[4.769319,52.255116],"type":"Point"}
}