{
  "type": "Feature",
  "properties": {
    "addr:full":"Spuistr 250 Amsterdam North Holland 1012 VW",
    "addr:housenumber":"250",
    "addr:postcode":"1012 vw",
    "iso:country":"NL",
    "sg:address":"Spuistr 250",
    "sg:city":"Amsterdam",
    "sg:orig_category":"Meubelen",
    "sg:phone":"+31 20 627 6285",
    "sg:postcode":"1012 VW",
    "sg:province":"North Holland",
    "wof:name":"Loods, De",
    "wof:placetype":"venue"
},
  "geometry": {"coordinates":[4.888937,52.370781],"type":"Point"}
}