{
  "type": "Feature",
  "properties": {
    "iso:country":"NL",
    "sg:address":"De Mareesstr 27",
    "sg:city":"Hoek Van Holland",
    "sg:orig_category":"Loonbedrijven",
    "sg:phone":"+31 174 383 999",
    "sg:postcode":"3151 NA",
    "sg:province":"Zuid-Holland",
    "wof:name":"Alabas, L",
    "wof:placetype":"venue"
},
  "geometry": {"coordinates":[4.136909,51.974674],"type":"Point"}
}