{
  "type": "Feature",
  "properties": {
    "addr:full":"F V Riemsdykwg 4 Eindhoven Noord-Brabant 5657 EE",
    "addr:housenumber":"4",
    "addr:postcode":"5657 ee",
    "addr:street":"Riemsdykwg",
    "iso:country":"NL",
    "sg:address":"F V Riemsdykwg 4",
    "sg:city":"Eindhoven",
    "sg:orig_category":"Beveiliging",
    "sg:phone":"+31 40 255 0915",
    "sg:postcode":"5657 EE",
    "sg:province":"Noord-Brabant",
    "sg:website":"http://www.securicor.nl",
    "wof:name":"Securicor",
    "wof:placetype":"venue"
},
  "geometry": {"coordinates":[5.39235,51.456921],"type":"Point"}
}