{
  "type": "Feature",
  "properties": {
    "addr:full":"Farskewei 3 Tynje Friesland 8406 AE",
    "addr:housenumber":"3",
    "addr:postcode":"8406 ae",
    "addr:street":"Farskewei",
    "iso:country":"NL",
    "sg:address":"Farskewei 3",
    "sg:city":"Tynje",
    "sg:orig_category":"Loonbedrijven",
    "sg:phone":"+31 513 571 207",
    "sg:postcode":"8406 AE",
    "sg:province":"Friesland",
    "sg:website":"HTTP://www.loonbedrijflolkema.nl",
    "wof:name":"Lolkema Tynje",
    "wof:placetype":"venue"
},
  "geometry": {"coordinates":[5.966186,53.033077],"type":"Point"}
}