{
  "type": "Feature",
  "properties": {
    "addr:full":"Poortugaalsewg 22 Poortugaal Zuid-Holland 3176 PV",
    "addr:housenumber":"22",
    "addr:postcode":"3176 pv",
    "addr:street":"Poortugaalsewg",
    "iso:country":"NL",
    "sg:address":"Poortugaalsewg 22",
    "sg:city":"Poortugaal",
    "sg:orig_category":"Verzekeringen - Verzekeringskantoren",
    "sg:phone":"+31 10 506 7131",
    "sg:postcode":"3176 PV",
    "sg:province":"Zuid-Holland",
    "wof:name":"Spaa, Van Der",
    "wof:placetype":"venue"
},
  "geometry": {"coordinates":[4.40478,51.87072],"type":"Point"}
}