{
  "type": "Feature",
  "properties": {
    "iso:country":"NL",
    "sg:address":"Van Wassenaerstraat 2",
    "sg:city":"Voorburg",
    "sg:orig_category":"Kappers",
    "sg:phone":"+31 70 335 2820",
    "sg:postcode":"2274 RC",
    "sg:province":"South Holland",
    "wof:name":"Kapsalon Hair Art 2",
    "wof:placetype":"venue"
},
  "geometry": {"coordinates":[4.3449940681,52.0755577087],"type":"Point"}
}