{
  "type": "Feature",
  "properties": {
    "addr:full":"Monickskamp 18 Huizen North Holland 1273 JS",
    "addr:housenumber":"18",
    "addr:postcode":"1273 js",
    "addr:street":"Monickskamp",
    "iso:country":"NL",
    "sg:address":"Monickskamp 18",
    "sg:city":"Huizen",
    "sg:orig_category":"Werving And Selectie Van Tijdelijk Personeel And Uitzendkantoren",
    "sg:phone":"+31 35 526 0234",
    "sg:postcode":"1273 JS",
    "sg:province":"North Holland",
    "wof:name":"Kgu Bv",
    "wof:placetype":"venue"
},
  "geometry": {"coordinates":[5.2634410858,52.2956123352],"type":"Point"}
}