{
  "type": "Feature",
  "properties": {
    "iso:country":"NL",
    "sg:address":"Ligusterpad 21",
    "sg:city":"Venlo",
    "sg:orig_category":"Geluidsopnamestudio'S",
    "sg:phone":"+31 77 387 3805",
    "sg:postcode":"5925 BT",
    "sg:province":"Limburg",
    "wof:name":"Brother & Brother",
    "wof:placetype":"venue"
},
  "geometry": {"coordinates":[6.128939,51.376343],"type":"Point"}
}