{
  "type": "Feature",
  "properties": {
    "iso:country":"NL",
    "sg:address":"De Zuidmaten 3",
    "sg:city":"Beilen",
    "sg:orig_category":"Verf En Lak",
    "sg:phone":"+31 593 523 254",
    "sg:postcode":"9411 PT",
    "sg:province":"Drenthe",
    "wof:name":"Dolfing",
    "wof:placetype":"venue"
},
  "geometry": {"coordinates":[6.51635,52.85181],"type":"Point"}
}