{
  "type": "Feature",
  "properties": {
    "iso:country":"NL",
    "sg:address":"J Israelsstr 13",
    "sg:city":"Oisterwyk",
    "sg:orig_category":"Adviesbureaus",
    "sg:phone":"+31 13 521 1821",
    "sg:postcode":"5062 LR",
    "sg:province":"Noord-Brabant",
    "wof:name":"Group Oisterwijk, The",
    "wof:placetype":"venue"
},
  "geometry": {"coordinates":[5.184033,51.572453],"type":"Point"}
}