{
  "type": "Feature",
  "properties": {
    "addr:full":"Hessenwg 166 Achterveld Utrecht 3791 PM",
    "addr:housenumber":"166",
    "addr:postcode":"3791 pm",
    "addr:street":"Achterveld",
    "iso:country":"NL",
    "sg:address":"Hessenwg 166",
    "sg:city":"Achterveld",
    "sg:classifiers":[
        {
            "category":"Retail",
            "subcategory":"Auto Repair",
            "type":"Services"
        }
    ],
    "sg:phone":"+31 342 450 045",
    "sg:postcode":"3791 PM",
    "sg:province":"Utrecht",
    "sg:tags":[
        "garage"
    ],
    "wof:name":"Kleinveld Autoservice",
    "wof:placetype":"venue"
},
  "geometry": {"coordinates":[5.491694,52.13736],"type":"Point"}
}