{
  "type": "Feature",
  "properties": {
    "iso:country":"NL",
    "sg:address":"W Arntszkd 1",
    "sg:city":"Utrecht",
    "sg:orig_category":"Verzekeringen - Verzekeringskantoren",
    "sg:phone":"+31 30 271 0227",
    "sg:postcode":"3515 AG",
    "sg:province":"Utrecht",
    "wof:name":"Links, W",
    "wof:placetype":"venue"
},
  "geometry": {"coordinates":[5.118452,52.100712],"type":"Point"}
}