{
  "type": "Feature",
  "properties": {
    "addr:full":"De Smelen 3 Valkenswaard Noord-Brabant 5553 CT",
    "addr:housenumber":"3",
    "addr:postcode":"5553 ct",
    "addr:street":"De Smelen",
    "iso:country":"NL",
    "sg:address":"De Smelen 3",
    "sg:city":"Valkenswaard",
    "sg:orig_category":"Vertaal- And Tolkenbureaus",
    "sg:phone":"+31 40 204 6685",
    "sg:postcode":"5553 CT",
    "sg:province":"Noord-Brabant",
    "wof:name":"Drs M A M Van Schadewijk",
    "wof:placetype":"venue"
},
  "geometry": {"coordinates":[5.47143,51.355759],"type":"Point"}
}