{
  "type": "Feature",
  "properties": {
    "addr:full":"Spoorln 350 Tilburg Noord-Brabant 5038 CC",
    "addr:housenumber":"350",
    "addr:postcode":"5038 cc",
    "addr:street":"Tilburg",
    "iso:country":"NL",
    "sg:address":"Spoorln 350",
    "sg:city":"Tilburg",
    "sg:orig_category":"Accountants - Administratie- Consulenten En -Kantoren",
    "sg:phone":"+31 13 583 5555",
    "sg:postcode":"5038 CC",
    "sg:province":"Noord-Brabant",
    "wof:name":"Abab",
    "wof:placetype":"venue"
},
  "geometry": {"coordinates":[5.07758,51.556911],"type":"Point"}
}