{
  "type": "Feature",
  "properties": {
    "iso:country":"NL",
    "sg:address":"Arendshof 49",
    "sg:city":"Oosterhout Nb",
    "sg:orig_category":"Juweliers",
    "sg:phone":"+31 162 455 877",
    "sg:postcode":"4901 LG",
    "sg:province":"North Brabant",
    "wof:name":"T Goudhuysje",
    "wof:placetype":"venue"
},
  "geometry": {"coordinates":[4.855292,51.643803],"type":"Point"}
}