{
  "type": "Feature",
  "properties": {
    "addr:full":"Arendshof 49 Oosterhout Nb North Brabant 4901 LG",
    "addr:housenumber":"49;nb",
    "addr:postcode":"4901 lg",
    "addr:street":"Arendshof",
    "iso:country":"NL",
    "sg:address":"Arendshof 49",
    "sg:city":"Oosterhout Nb",
    "sg:orig_category":"Juweliers",
    "sg:phone":"+31 162 455 877",
    "sg:postcode":"4901 LG",
    "sg:province":"North Brabant",
    "wof:name":"T Goudhuysje",
    "wof:placetype":"venue"
},
  "geometry": {"coordinates":[4.855292,51.643803],"type":"Point"}
}