{
  "type": "Feature",
  "properties": {
    "addr:full":"Houtpln 2729 Haarlem Noord-Holland 2012 DE",
    "addr:housenumber":"2729",
    "addr:postcode":"2012 de",
    "iso:country":"NL",
    "sg:address":"Houtpln 2729",
    "sg:city":"Haarlem",
    "sg:orig_category":"Verhuur",
    "sg:phone":"+31 23 534 6291",
    "sg:postcode":"2012 DE",
    "sg:province":"Noord-Holland",
    "sg:website":"http://www.skala.nl",
    "wof:name":"Skala",
    "wof:placetype":"venue"
},
  "geometry": {"coordinates":[4.630574,52.374641],"type":"Point"}
}