{
  "type": "Feature",
  "properties": {
    "addr:full":"Duivendrechtsekd 80 Amsterdam Noord-Holland 1096 AH",
    "addr:housenumber":"80",
    "addr:postcode":"1096 ah",
    "addr:street":"Duivendrechtsekd",
    "iso:country":"NL",
    "sg:address":"Duivendrechtsekd 80",
    "sg:city":"Amsterdam",
    "sg:orig_category":"Filmstudio'S En -Productie",
    "sg:phone":"+31 20 694 0004",
    "sg:postcode":"1096 AH",
    "sg:province":"Noord-Holland",
    "wof:name":"Jointcam",
    "wof:placetype":"venue"
},
  "geometry": {"coordinates":[4.933595,52.337784],"type":"Point"}
}