{
  "type": "Feature",
  "properties": {
    "iso:country":"NL",
    "sg:address":"Rootstraat 22",
    "sg:city":"Oss",
    "sg:orig_category":"Algemene Werktuigbouw",
    "sg:phone":"+31 412 636 988",
    "sg:postcode":"5345 VE",
    "sg:province":"Noord-Brabant",
    "wof:name":"Walters - Lastechniek",
    "wof:placetype":"venue"
},
  "geometry": {"coordinates":[-77.235214,38.312599],"type":"Point"}
}