{
  "type": "Feature",
  "properties": {
    "addr:full":"Putstr 1 T Loo Oldebroek Gelderland 8095 PV",
    "addr:housenumber":"1 t",
    "addr:postcode":"8095 pv",
    "addr:street":"Putstr;Loo;Gelderland",
    "iso:country":"NL",
    "sg:address":"Putstr 1",
    "sg:city":"T Loo Oldebroek",
    "sg:orig_category":"Banken",
    "sg:phone":"+31 525 632 160",
    "sg:postcode":"8095 PV",
    "sg:province":"Gelderland",
    "sg:website":"http://www.rabobank.nl",
    "wof:name":"Rabobank",
    "wof:placetype":"venue"
},
  "geometry": {"coordinates":[5.951063,52.444813],"type":"Point"}
}