{
  "type": "Feature",
  "properties": {
    "addr:full":"Valleiln 2 Leusden Utrecht 3831 WE",
    "addr:housenumber":"2",
    "addr:postcode":"3831 we",
    "addr:street":"Valleiln",
    "iso:country":"NL",
    "sg:address":"Valleiln 2",
    "sg:city":"Leusden",
    "sg:orig_category":"Begrafenisverzorging",
    "sg:phone":"+31 33 494 4844",
    "sg:postcode":"3831 WE",
    "sg:province":"Utrecht",
    "wof:name":"Zwarteveen, F E",
    "wof:placetype":"venue"
},
  "geometry": {"coordinates":[5.42959,52.131248],"type":"Point"}
}