{
  "type": "Feature",
  "properties": {
    "addr:full":"Varkensmarkt 1A Goedereede Zuid-Holland 3252 BT",
    "addr:housenumber":"1a",
    "addr:postcode":"3252 bt",
    "addr:street":"Varkensmarkt",
    "iso:country":"NL",
    "sg:address":"Varkensmarkt 1A",
    "sg:city":"Goedereede",
    "sg:orig_category":"Advocaten En Advocatenkantoren",
    "sg:phone":"+31 187 491 670",
    "sg:postcode":"3252 BT",
    "sg:province":"Zuid-Holland",
    "wof:name":"Kaai, Mr G",
    "wof:placetype":"venue"
},
  "geometry": {"coordinates":[3.976749,51.818874],"type":"Point"}
}