{
  "type": "Feature",
  "properties": {
    "iso:country":"NL",
    "sg:address":"Beukenln 25",
    "sg:city":"Soest",
    "sg:orig_category":"Schilders",
    "sg:phone":"+31 35 541 1963",
    "sg:postcode":"3762 AE",
    "sg:province":"Utrecht",
    "wof:name":"Classiqe",
    "wof:placetype":"venue"
},
  "geometry": {"coordinates":[5.289068,52.176731],"type":"Point"}
}