{
  "type": "Feature",
  "properties": {
    "addr:full":"Minderbroedersngl 44 Roermond Limburg 6041 KK",
    "addr:housenumber":"44",
    "addr:postcode":"6041 kk",
    "addr:street":"Minderbroedersngl",
    "iso:country":"NL",
    "sg:address":"Minderbroedersngl 44",
    "sg:city":"Roermond",
    "sg:orig_category":"Artsen - Huisartsen",
    "sg:phone":"+31 475 316 080",
    "sg:postcode":"6041 KK",
    "sg:province":"Limburg",
    "wof:name":"Bakker, C G M M",
    "wof:placetype":"venue"
},
  "geometry": {"coordinates":[5.985093,51.191799],"type":"Point"}
}