{
  "type": "Feature",
  "properties": {
    "addr:full":"Visioenenstraat 36 Sint Anthonis Noord-Brabant 5845 CC",
    "addr:housenumber":"36",
    "addr:postcode":"anthonis;5845 cc",
    "addr:street":"Visioenenstraat",
    "iso:country":"NL",
    "sg:address":"Visioenenstraat 36",
    "sg:city":"Sint Anthonis",
    "sg:orig_category":"Metaalvrije Afvalrecycling",
    "sg:phone":"+31 485 384 604",
    "sg:postcode":"5845 CC",
    "sg:province":"Noord-Brabant",
    "wof:name":"Docucare Bv",
    "wof:placetype":"venue"
},
  "geometry": {"coordinates":[5.886577,51.623505],"type":"Point"}
}