{
  "type": "Feature",
  "properties": {
    "addr:full":"Bedryvenwg 11A Leiderdorp Zuid-Holland 2351 BC",
    "addr:housenumber":"11a",
    "addr:postcode":"2351 bc",
    "addr:street":"Bedryvenwg",
    "iso:country":"NL",
    "sg:address":"Bedryvenwg 11A",
    "sg:city":"Leiderdorp",
    "sg:orig_category":"Fotoreportages",
    "sg:phone":"+31 71 541 3038",
    "sg:postcode":"2351 BC",
    "sg:province":"Zuid-Holland",
    "wof:name":"Studio Graafland Cv",
    "wof:placetype":"venue"
},
  "geometry": {"coordinates":[4.546105,52.14167],"type":"Point"}
}