{
  "type": "Feature",
  "properties": {
    "iso:country":"NL",
    "sg:address":"Dorpsstr 28",
    "sg:city":"Vught",
    "sg:orig_category":"Bibliotheken En Leeszalen Openbare",
    "sg:phone":"+31 73 656 3320",
    "sg:postcode":"5261 CK",
    "sg:province":"Noord-Brabant",
    "wof:name":"Openb Bibliotheek",
    "wof:placetype":"venue"
},
  "geometry": {"coordinates":[5.297663,51.660519],"type":"Point"}
}