{
  "type": "Feature",
  "properties": {
    "addr:full":"Torenallee 17 Doetinchem Gelderland 7001 CJ",
    "addr:housenumber":"17",
    "addr:postcode":"7001 cj",
    "addr:street":"Torenallee;Gelderland",
    "iso:country":"NL",
    "sg:address":"Torenallee 17",
    "sg:city":"Doetinchem",
    "sg:orig_category":"Binnenhuisarchitectuur",
    "sg:phone":"+31 314 383 048",
    "sg:postcode":"7001 CJ",
    "sg:province":"Gelderland",
    "sg:website":"http://www.alco-interieurburo.nl",
    "wof:name":"Alco",
    "wof:placetype":"venue"
},
  "geometry": {"coordinates":[6.281902,51.967777],"type":"Point"}
}