{
  "type": "Feature",
  "properties": {
    "addr:full":"Oude Zwolsewg 152 Wenum Wiesel Gelderland 7345 DG",
    "addr:housenumber":"152",
    "addr:postcode":"7345 dg",
    "addr:street":"Oude Zwolsewg",
    "iso:country":"NL",
    "sg:address":"Oude Zwolsewg 152",
    "sg:city":"Wenum Wiesel",
    "sg:orig_category":"Verlichtingsartikelen - Groothandel",
    "sg:phone":"+31 55 534 5905",
    "sg:postcode":"7345 DG",
    "sg:province":"Gelderland",
    "sg:website":"http://www.luckylight.nl",
    "wof:name":"Lucky Light Projectverlichting Bv",
    "wof:placetype":"venue"
},
  "geometry": {"coordinates":[5.963562,52.254066],"type":"Point"}
}