{
  "type": "Feature",
  "properties": {
    "addr:full":"Verzetspln 46 Zandvoort Noord-Holland 2041 EB",
    "addr:housenumber":"46",
    "addr:postcode":"2041 eb",
    "addr:street":"Verzetspln",
    "iso:country":"NL",
    "sg:address":"Verzetspln 46",
    "sg:city":"Zandvoort",
    "sg:orig_category":"Administratie- En Boekhoudkantoren",
    "sg:phone":"+31 23 573 3841",
    "sg:postcode":"2041 EB",
    "sg:province":"Noord-Holland",
    "wof:name":"Noodzakelijk Kwaad",
    "wof:placetype":"venue"
},
  "geometry": {"coordinates":[4.532918,52.377605],"type":"Point"}
}