{
  "type": "Feature",
  "properties": {
    "addr:full":"Pascalstr 15 Reeuwyk Zuid-Holland 2811 EL",
    "addr:housenumber":"15",
    "addr:postcode":"2811 el",
    "addr:street":"Pascalstr",
    "iso:country":"NL",
    "sg:address":"Pascalstr 15",
    "sg:city":"Reeuwyk",
    "sg:orig_category":"Loonbedrijven",
    "sg:phone":"+31 182 396 284",
    "sg:postcode":"2811 EL",
    "sg:province":"Zuid-Holland",
    "wof:name":"Nieuwkoop Bv, Van",
    "wof:placetype":"venue"
},
  "geometry": {"coordinates":[4.716707,52.039528],"type":"Point"}
}