{
  "type": "Feature",
  "properties": {
    "addr:full":"Ruysdaelpln 4 Naarden North Holland 1411 RD",
    "addr:housenumber":"4",
    "addr:postcode":"1411 rd",
    "addr:street":"Ruysdaelpln",
    "iso:country":"NL",
    "sg:address":"Ruysdaelpln 4",
    "sg:city":"Naarden",
    "sg:orig_category":"Video - Faciliteiten En Producties",
    "sg:phone":"+31 35 694 3900",
    "sg:postcode":"1411 RD",
    "sg:province":"North Holland",
    "wof:name":"Rodin",
    "wof:placetype":"venue"
},
  "geometry": {"coordinates":[5.165696,52.29562],"type":"Point"}
}