{
  "type": "Feature",
  "properties": {
    "iso:country":"NL",
    "sg:address":"Neutronweg 2",
    "sg:city":"Hoorn Nh",
    "sg:orig_category":"Vers Brood And Banket Fab",
    "sg:phone":"+31 229 210 597",
    "sg:postcode":"1627 LG",
    "sg:province":"Noord-Holland",
    "wof:name":"Corda Banket Bv",
    "wof:placetype":"venue"
},
  "geometry": {"coordinates":[5.10168,52.641552],"type":"Point"}
}