{
  "type": "Feature",
  "properties": {
    "addr:full":"Groen Van Prinstererweg 43 De Bilt Utrecht 3731 HA",
    "addr:housenumber":"43",
    "addr:postcode":"3731 ha",
    "addr:street":"Groen Van Prinstererweg",
    "iso:country":"NL",
    "sg:address":"Groen Van Prinstererweg 43",
    "sg:city":"De Bilt",
    "sg:orig_category":"Autokeuringen",
    "sg:phone":"+31 30 220 0137",
    "sg:postcode":"3731 HA",
    "sg:province":"Utrecht",
    "wof:name":"Van Markus Autoschade De Bilt",
    "wof:placetype":"venue"
},
  "geometry": {"coordinates":[5.176004,52.107265],"type":"Point"}
}