{
  "type": "Feature",
  "properties": {
    "addr:full":"Mon Plaisir 89 Etten Leur Noord-Brabant 4879 AM",
    "addr:housenumber":"89",
    "addr:postcode":"4879",
    "addr:street":"Mon Plaisir",
    "iso:country":"NL",
    "sg:address":"Mon Plaisir 89",
    "sg:city":"Etten Leur",
    "sg:orig_category":"Adviesbureaus Bedrijfsorganisatie",
    "sg:phone":"+31 76 508 1100",
    "sg:postcode":"4879 AM",
    "sg:province":"Noord-Brabant",
    "wof:name":"Max",
    "wof:placetype":"venue"
},
  "geometry": {"coordinates":[4.615529,51.561691],"type":"Point"}
}