{
  "type": "Feature",
  "properties": {
    "addr:full":"Fahrenheitstraat 115 Amsterdam North Holland 1097 PP",
    "addr:housenumber":"115",
    "addr:postcode":"1097 pp",
    "addr:street":"Fahrenheitstraat",
    "iso:country":"NL",
    "sg:address":"Fahrenheitstraat 115",
    "sg:city":"Amsterdam",
    "sg:orig_category":"Bejaardeninstellingen And Serviceflats",
    "sg:phone":"+31 20 692 0622",
    "sg:postcode":"1097 PP",
    "sg:province":"North Holland",
    "wof:name":"Zorgcentrum De Open Hof",
    "wof:placetype":"venue"
},
  "geometry": {"coordinates":[4.927115,52.345222],"type":"Point"}
}