{
  "type": "Feature",
  "properties": {
    "addr:full":"Julianastr 6 Weesp Noord-Holland 1382 XX",
    "addr:housenumber":"6",
    "addr:postcode":"1382 xx",
    "addr:street":"Julianastr",
    "iso:country":"NL",
    "sg:address":"Julianastr 6",
    "sg:city":"Weesp",
    "sg:orig_category":"Beeldende Kunstenaars",
    "sg:phone":"+31 294 457 099",
    "sg:postcode":"1382 XX",
    "sg:province":"Noord-Holland",
    "wof:name":"Dieuwke Tamsma",
    "wof:placetype":"venue"
},
  "geometry": {"coordinates":[5.039416,52.308918],"type":"Point"}
}