{
  "type": "Feature",
  "properties": {
    "addr:full":"Lecksdk 18 Reeuwyk Zuid-Holland 2811 NK",
    "addr:housenumber":"18",
    "addr:postcode":"2811 nk",
    "addr:street":"Lecksdk",
    "iso:country":"NL",
    "sg:address":"Lecksdk 18",
    "sg:city":"Reeuwyk",
    "sg:orig_category":"Kantoor- En Secretariaatsservice",
    "sg:phone":"+31 182 392 116",
    "sg:postcode":"2811 NK",
    "sg:province":"Zuid-Holland",
    "wof:name":"Bijdehand",
    "wof:placetype":"venue"
},
  "geometry": {"coordinates":[4.7223367691,52.0449028015],"type":"Point"}
}