{
  "type": "Feature",
  "properties": {
    "iso:country":"NL",
    "sg:address":"Kerkstr 21B",
    "sg:city":"Berkel En Rodenrys",
    "sg:classifiers":[
        {
            "category":"Shopping",
            "subcategory":"Adult",
            "type":"Retail Goods"
        }
    ],
    "sg:phone":"+31 10 511 2680",
    "sg:postcode":"2651 CD",
    "sg:province":"Zuid-Holland",
    "sg:tags":[
        "lingerie",
        "en",
        "tricotage"
    ],
    "wof:name":"Se7Ven",
    "wof:placetype":"venue"
},
  "geometry": {"coordinates":[4.477383,51.993717],"type":"Point"}
}