{
  "type": "Feature",
  "properties": {
    "iso:country":"NL",
    "sg:address":"De Hoop 38",
    "sg:city":"Uitgeest",
    "sg:orig_category":"Glaszetten",
    "sg:phone":"+31 251 320 367",
    "sg:postcode":"1911 KZ",
    "sg:province":"Noord-Holland",
    "wof:name":"J.C.S. Schram",
    "wof:placetype":"venue"
},
  "geometry": {"coordinates":[4.701826,52.518684],"type":"Point"}
}