{
  "type": "Feature",
  "properties": {
    "addr:full":"Boshoverbeek 62 Weert Limburg 6006 LP",
    "addr:housenumber":"62",
    "addr:postcode":"6006 lp",
    "addr:street":"Boshoverbeek",
    "iso:country":"NL",
    "sg:address":"Boshoverbeek 62",
    "sg:city":"Weert",
    "sg:orig_category":"Werving And Selectie Van Tijdelijk Personeel And Uitzendkantoren",
    "sg:phone":"+31 495 543 918",
    "sg:postcode":"6006 LP",
    "sg:province":"Limburg",
    "wof:name":"Adviesburo Luijs",
    "wof:placetype":"venue"
},
  "geometry": {"coordinates":[5.683467865,51.2470703125],"type":"Point"}
}