{
  "type": "Feature",
  "properties": {
    "addr:full":"Hoekstraat 14 Bunschoten Spakenburg Utrecht 3751 AM",
    "addr:housenumber":"14",
    "addr:postcode":"3751",
    "addr:street":"Hoekstraat",
    "iso:country":"NL",
    "sg:address":"Hoekstraat 14",
    "sg:city":"Bunschoten Spakenburg",
    "sg:classifiers":[
        {
            "category":"Fast Food",
            "type":"Food & Drink"
        }
    ],
    "sg:phone":"+31 33 298 1563",
    "sg:postcode":"3751 AM",
    "sg:province":"Utrecht",
    "sg:tags":[
        "afhaal",
        "restaurant"
    ],
    "wof:name":"Firma De Goede Hoek",
    "wof:placetype":"venue"
},
  "geometry": {"coordinates":[5.379098,52.254196],"type":"Point"}
}