{
  "type": "Feature",
  "properties": {
    "addr:full":"Varikstr 57 Amsterdam Zuidoost Noord-Holland 1106 CT",
    "addr:housenumber":"57",
    "addr:postcode":"zuidoost;1106 ct",
    "addr:street":"Varikstr",
    "iso:country":"NL",
    "sg:address":"Varikstr 57",
    "sg:city":"Amsterdam Zuidoost",
    "sg:orig_category":"Beeldende Kunstenaars",
    "sg:phone":"+31 20 697 9462",
    "sg:postcode":"1106 CT",
    "sg:province":"Noord-Holland",
    "sg:website":"http://www.heleneterlien.exto.nl",
    "wof:name":"Terlien, H?l?ne",
    "wof:placetype":"venue"
},
  "geometry": {"coordinates":[4.982785,52.300144],"type":"Point"}
}