{
  "type": "Feature",
  "properties": {
    "addr:full":"Bloemendalerwg 51 Weesp Noord-Holland 1382 KB",
    "addr:housenumber":"51",
    "addr:postcode":"1382 kb",
    "addr:street":"Bloemendalerwg",
    "iso:country":"NL",
    "sg:address":"Bloemendalerwg 51",
    "sg:city":"Weesp",
    "sg:orig_category":"Evenementenverzorging",
    "sg:phone":"+31 294 483 428",
    "sg:postcode":"1382 KB",
    "sg:province":"Noord-Holland",
    "sg:website":"http://www.airworks.nl",
    "wof:name":"Airworks",
    "wof:placetype":"venue"
},
  "geometry": {"coordinates":[5.021499,52.321564],"type":"Point"}
}