{
  "type": "Feature",
  "properties": {
    "addr:full":"Kraayenberg 8018 Wijchen Gelderland 6601 RM",
    "addr:housenumber":"8018",
    "addr:postcode":"6601 rm",
    "addr:street":"Kraayenberg;Gelderland",
    "iso:country":"NL",
    "sg:address":"Kraayenberg 8018",
    "sg:city":"Wijchen",
    "sg:classifiers":[
        {
            "category":"Education",
            "subcategory":"Preschool",
            "type":"Public Place"
        }
    ],
    "sg:phone":"+31 24 645 2725",
    "sg:postcode":"6601 RM",
    "sg:province":"Gelderland",
    "sg:tags":[
        "kleuteronderwijs",
        "basis-"
    ],
    "wof:name":"Openbare Dalton Basisschool De Bolderberg",
    "wof:placetype":"venue"
},
  "geometry": {"coordinates":[5.73085,51.808395],"type":"Point"}
}