{
  "type": "Feature",
  "properties": {
    "iso:country":"NL",
    "sg:address":"Prinsenplein 38",
    "sg:city":"Meppel",
    "sg:orig_category":"Huishoudapparatuur, Televisies And Radio'S",
    "sg:phone":"+31 522 252 582",
    "sg:postcode":"7941 KW",
    "sg:province":"Provincie Drenthe",
    "wof:name":"Expert Meppel",
    "wof:placetype":"venue"
},
  "geometry": {"coordinates":[6.193115,52.696609],"type":"Point"}
}