{
  "type": "Feature",
  "properties": {
    "iso:country":"NL",
    "sg:address":"Nieuweweg 3",
    "sg:city":"Anna Paulowna",
    "sg:orig_category":"Fitnesscentra",
    "sg:phone":"+31 223 533 754",
    "sg:postcode":"1761 EC",
    "sg:province":"Noord-Holland",
    "wof:name":"Panatta Gym",
    "wof:placetype":"venue"
},
  "geometry": {"coordinates":[4.83282,52.86256],"type":"Point"}
}