{
  "type": "Feature",
  "properties": {
    "addr:full":"Van Bourlostraat 1 Zutphen Gelderland 7203 CL",
    "addr:housenumber":"1",
    "addr:postcode":"7203",
    "addr:street":"Van Bourlostraat;Gelderland",
    "iso:country":"NL",
    "sg:address":"Van Bourlostraat 1",
    "sg:city":"Zutphen",
    "sg:orig_category":"Loodgieterswerk, Verwarming And Sanitaire Installaties",
    "sg:phone":"+31 575 544 548",
    "sg:postcode":"7203 CL",
    "sg:province":"Gelderland",
    "wof:name":"Akb",
    "wof:placetype":"venue"
},
  "geometry": {"coordinates":[6.21384,52.15424],"type":"Point"}
}