{
  "type": "Feature",
  "properties": {
    "iso:country":"NL",
    "sg:address":"Zeeburgerdijk 289",
    "sg:city":"Amsterdam",
    "sg:orig_category":"Overheidsdiensten",
    "sg:phone":"+31 20 694 5647",
    "sg:postcode":"1095 AD",
    "sg:province":"North Holland",
    "wof:name":"Flevo",
    "wof:placetype":"venue"
},
  "geometry": {"coordinates":[4.9692149162,52.3616905212],"type":"Point"}
}