{
  "type": "Feature",
  "properties": {
    "addr:full":"Arnhemseweg 36 Amersfoort Utrecht 3817 CH",
    "addr:housenumber":"36",
    "addr:postcode":"3817",
    "addr:street":"Arnhemseweg",
    "iso:country":"NL",
    "sg:address":"Arnhemseweg 36",
    "sg:city":"Amersfoort",
    "sg:orig_category":"Juweliers",
    "sg:phone":"+31 33 461 3764",
    "sg:postcode":"3817 CH",
    "sg:province":"Utrecht",
    "wof:name":"Horloger-Juwelier Kok",
    "wof:placetype":"venue"
},
  "geometry": {"coordinates":[5.385181,52.150627],"type":"Point"}
}