{
  "type": "Feature",
  "properties": {
    "addr:full":"Haagdk 65 Breda Noord-Brabant 4811 TP",
    "addr:housenumber":"65",
    "addr:postcode":"4811 tp",
    "addr:street":"Haagdk",
    "iso:country":"NL",
    "sg:address":"Haagdk 65",
    "sg:city":"Breda",
    "sg:orig_category":"Herenkleding",
    "sg:phone":"+31 76 521 1339",
    "sg:postcode":"4811 TP",
    "sg:province":"Noord-Brabant",
    "wof:name":"Dirven",
    "wof:placetype":"venue"
},
  "geometry": {"coordinates":[4.769666,51.587719],"type":"Point"}
}