{
  "type": "Feature",
  "properties": {
    "addr:full":"Kastanjeln 1 Hengelo Gelderland 7255 AM",
    "addr:housenumber":"1",
    "addr:postcode":"7255",
    "addr:street":"Kastanjeln;Gelderland",
    "iso:country":"NL",
    "sg:address":"Kastanjeln 1",
    "sg:city":"Hengelo",
    "sg:orig_category":"Artsen - Huisartsen",
    "sg:phone":"+31 575 461 266",
    "sg:postcode":"7255 AM",
    "sg:province":"Gelderland",
    "wof:name":"Koning, J",
    "wof:placetype":"venue"
},
  "geometry": {"coordinates":[6.308347,52.048069],"type":"Point"}
}