{
  "type": "Feature",
  "properties": {
    "addr:full":"Smallevaert 26 Kaatsheuvel Noord-Brabant 5171 ML",
    "addr:housenumber":"26",
    "addr:postcode":"5171 ml",
    "addr:street":"Smallevaert",
    "iso:country":"NL",
    "sg:address":"Smallevaert 26",
    "sg:city":"Kaatsheuvel",
    "sg:orig_category":"Administratie- En Boekhoudkantoren",
    "sg:phone":"+31 416 280 504",
    "sg:postcode":"5171 ML",
    "sg:province":"Noord-Brabant",
    "wof:name":"J & A",
    "wof:placetype":"venue"
},
  "geometry": {"coordinates":[5.045255,51.660488],"type":"Point"}
}