{
  "type": "Feature",
  "properties": {
    "addr:full":"Diependorst 130 Ouddorp Zh South Holland 3253 VC",
    "addr:housenumber":"130",
    "addr:postcode":"zh;3253 vc",
    "addr:street":"Diependorst",
    "iso:country":"NL",
    "sg:address":"Diependorst 130",
    "sg:city":"Ouddorp Zh",
    "sg:classifiers":[
        {
            "category":"Personal",
            "subcategory":"Nail Salon",
            "type":"Services"
        }
    ],
    "sg:phone":"+31 187 683 711",
    "sg:postcode":"3253 VC",
    "sg:province":"South Holland",
    "sg:tags":[
        "pedicure"
    ],
    "wof:name":"Tanis, M",
    "wof:placetype":"venue"
},
  "geometry": {"coordinates":[3.94092,51.808903],"type":"Point"}
}