{
  "type": "Feature",
  "properties": {
    "addr:full":"Tesselschadestr 41 Deventer Overijssel 7412 NA",
    "addr:housenumber":"41",
    "addr:postcode":"7412 na",
    "addr:street":"Tesselschadestr",
    "iso:country":"NL",
    "sg:address":"Tesselschadestr 41",
    "sg:city":"Deventer",
    "sg:orig_category":"Fietsen En Bromfietsen",
    "sg:phone":"+31 570 671 268",
    "sg:postcode":"7412 NA",
    "sg:province":"Overijssel",
    "wof:name":"Laak, J Van Der",
    "wof:placetype":"venue"
},
  "geometry": {"coordinates":[6.139499,52.267754],"type":"Point"}
}