{
  "type": "Feature",
  "properties": {
    "addr:full":"Hoogstr 3 Haarlem Noord-Holland 2011 CS",
    "addr:housenumber":"3",
    "addr:postcode":"2011 cs",
    "addr:street":"Hoogstr",
    "iso:country":"NL",
    "sg:address":"Hoogstr 3",
    "sg:city":"Haarlem",
    "sg:orig_category":"Fietsen En Bromfietsen",
    "sg:phone":"+31 23 540 7076",
    "sg:postcode":"2011 CS",
    "sg:province":"Noord-Holland",
    "sg:website":"http://www.tmannetje.nl",
    "wof:name":"Mannetje Haarlem, 'T",
    "wof:placetype":"venue"
},
  "geometry": {"coordinates":[4.639062,52.379185],"type":"Point"}
}