{
  "type": "Feature",
  "properties": {
    "addr:full":"Zwartewg 8A T Veld Noord-Holland 1735 GL",
    "addr:housenumber":"8a",
    "addr:postcode":"1735 gl",
    "addr:street":"Zwartewg",
    "iso:country":"NL",
    "sg:address":"Zwartewg 8A",
    "sg:city":"T Veld",
    "sg:orig_category":"Verenigingsgebouwen",
    "sg:phone":"+31 226 421 753",
    "sg:postcode":"1735 GL",
    "sg:province":"Noord-Holland",
    "wof:name":"Dorpshuis Harmonie",
    "wof:placetype":"venue"
},
  "geometry": {"coordinates":[4.855078,52.738995],"type":"Point"}
}