{
  "type": "Feature",
  "properties": {
    "iso:country":"NL",
    "sg:address":"Groenestr 273",
    "sg:city":"Nymegen",
    "sg:orig_category":"Cafetaria'S",
    "sg:phone":"+31 24 355 8326",
    "sg:postcode":"6531 HK",
    "sg:province":"Gelderland",
    "wof:name":"Cicek Cafetaria",
    "wof:placetype":"venue"
},
  "geometry": {"coordinates":[114.153542,22.411249],"type":"Point"}
}