{
  "type": "Feature",
  "properties": {
    "addr:full":"Noordervaart 58 Stompetoren Noord-Holland 1841 HB",
    "addr:housenumber":"58",
    "addr:postcode":"1841 hb",
    "addr:street":"Noordervaart",
    "iso:country":"NL",
    "sg:address":"Noordervaart 58",
    "sg:city":"Stompetoren",
    "sg:orig_category":"Beautyfarms And Sauna'S",
    "sg:phone":"+31 72 503 9213",
    "sg:postcode":"1841 HB",
    "sg:province":"Noord-Holland",
    "wof:name":"M.R. Van Splunter",
    "wof:placetype":"venue"
},
  "geometry": {"coordinates":[4.829181,52.609505],"type":"Point"}
}