{
  "type": "Feature",
  "properties": {
    "addr:full":"Pres Rooseveltln 43 Helmond Noord-Brabant 5707 GB",
    "addr:housenumber":"43",
    "addr:postcode":"5707 gb",
    "iso:country":"NL",
    "sg:address":"Pres Rooseveltln 43",
    "sg:city":"Helmond",
    "sg:orig_category":"Evenementenverzorging",
    "sg:phone":"+31 492 525 483",
    "sg:postcode":"5707 GB",
    "sg:province":"Noord-Brabant",
    "sg:website":"http://www.vlooienmarkt.nl",
    "wof:name":"Aerle Organisatiebureau, Van",
    "wof:placetype":"venue"
},
  "geometry": {"coordinates":[5.658284,51.482239],"type":"Point"}
}