{
  "type": "Feature",
  "properties": {
    "addr:full":"Rustenburgerstraat 246 Amsterdam Noord-Holland 1073 GK",
    "addr:housenumber":"246",
    "addr:postcode":"1073 gk",
    "addr:street":"Rustenburgerstraat",
    "iso:country":"NL",
    "sg:address":"Rustenburgerstraat 246",
    "sg:city":"Amsterdam",
    "sg:classifiers":[
        {
            "category":"Education",
            "subcategory":"Preschool",
            "type":"Public Place"
        }
    ],
    "sg:phone":"+31 20 679 5475",
    "sg:postcode":"1073 GK",
    "sg:province":"Noord-Holland",
    "sg:tags":[
        "kleuteronderwijs",
        "basis-"
    ],
    "wof:name":"Het Mozaiek",
    "wof:placetype":"venue"
},
  "geometry": {"coordinates":[4.897519,52.352383],"type":"Point"}
}