{
  "type": "Feature",
  "properties": {
    "addr:full":"Andersonweg 4 Roermond Limburg 6041 JE",
    "addr:housenumber":"4",
    "addr:postcode":"6041 je",
    "addr:street":"Andersonweg",
    "iso:country":"NL",
    "sg:address":"Andersonweg 4",
    "sg:city":"Roermond",
    "sg:orig_category":"Zalenexploitatie",
    "sg:phone":"+31 475 330 555",
    "sg:postcode":"6041 JE",
    "sg:province":"Limburg",
    "wof:name":"Kunstuitleen Bonnefantenmuseum",
    "wof:placetype":"venue"
},
  "geometry": {"coordinates":[5.98851,51.187962],"type":"Point"}
}