{
  "type": "Feature",
  "properties": {
    "addr:full":"Nieuwe Kijk In 'T Jatstr 23 Groningen Groningen 9712 SB",
    "addr:housenumber":"23",
    "addr:postcode":"9712 sb",
    "addr:street":"Nieuwe Kijk In ' T Jatstr",
    "iso:country":"NL",
    "sg:address":"Nieuwe Kijk In 'T Jatstr 23",
    "sg:city":"Groningen",
    "sg:orig_category":"Vertaal- And Tolkenbureaus",
    "sg:phone":"+31 50 318 1987",
    "sg:postcode":"9712 SB",
    "sg:province":"Groningen",
    "wof:name":"Drs A M T Van Willigen-Ijland",
    "wof:placetype":"venue"
},
  "geometry": {"coordinates":[6.56368,53.221481],"type":"Point"}
}