{
  "type": "Feature",
  "properties": {
    "addr:full":"Bloemenlaan 7 Valkenburg Zh Zuid-Holland 2235 EM",
    "addr:housenumber":"7",
    "addr:postcode":"2235 em",
    "addr:street":"Bloemenlaan",
    "iso:country":"NL",
    "sg:address":"Bloemenlaan 7",
    "sg:city":"Valkenburg Zh",
    "sg:orig_category":"Autokeuringen",
    "sg:phone":"+31 71 407 2968",
    "sg:postcode":"2235 EM",
    "sg:province":"Zuid-Holland",
    "wof:name":"W.A. Vierbergen",
    "wof:placetype":"venue"
},
  "geometry": {"coordinates":[4.438382,52.177853],"type":"Point"}
}