{
  "type": "Feature",
  "properties": {
    "addr:full":"Van Beverningkstraat 22 'S Gravenhage Zuid-Holland 2582 VH",
    "addr:housenumber":"22",
    "addr:postcode":"2582 vh",
    "addr:street":"Van Beverningkstraat;' S",
    "iso:country":"NL",
    "sg:address":"Van Beverningkstraat 22",
    "sg:city":"'S Gravenhage",
    "sg:orig_category":"Boekenuitgeverijen",
    "sg:phone":"+31 70 352 2837",
    "sg:postcode":"2582 VH",
    "sg:province":"Zuid-Holland",
    "wof:name":"Uitg Primo Verf Bv",
    "wof:placetype":"venue"
},
  "geometry": {"coordinates":[4.273434,52.09206],"type":"Point"}
}