{
  "type": "Feature",
  "properties": {
    "addr:full":"Kloesstraat 15 Stein Lb Limburg 6171 BP",
    "addr:housenumber":"15",
    "addr:postcode":"lb;6171 bp",
    "addr:street":"Kloesstraat",
    "iso:country":"NL",
    "sg:address":"Kloesstraat 15",
    "sg:city":"Stein Lb",
    "sg:orig_category":"Daken And Skeletbouw",
    "sg:phone":"+31 46 433 5813",
    "sg:postcode":"6171 BP",
    "sg:province":"Limburg",
    "wof:name":"Dakbedekkingen H & W",
    "wof:placetype":"venue"
},
  "geometry": {"coordinates":[-93.129936,36.705662],"type":"Point"}
}