{
  "type": "Feature",
  "properties": {
    "addr:full":"Rynln 54 Utrecht Utrecht 3522 BP",
    "addr:housenumber":"54",
    "addr:postcode":"3522 bp",
    "addr:street":"Rynln",
    "iso:country":"NL",
    "sg:address":"Rynln 54",
    "sg:city":"Utrecht",
    "sg:orig_category":"Schoenen",
    "sg:phone":"+31 30 288 5762",
    "sg:postcode":"3522 BP",
    "sg:province":"Utrecht",
    "wof:name":"Broek, H G Van Den",
    "wof:placetype":"venue"
},
  "geometry": {"coordinates":[5.11568,52.070339],"type":"Point"}
}