{
  "type": "Feature",
  "properties": {
    "addr:full":"Herenstr 79 Hilversum North Holland 1211 CA",
    "addr:housenumber":"79",
    "addr:postcode":"1211 ca",
    "addr:street":"Herenstr",
    "iso:country":"NL",
    "sg:address":"Herenstr 79",
    "sg:city":"Hilversum",
    "sg:orig_category":"Kappers",
    "sg:phone":"+31 35 621 1409",
    "sg:postcode":"1211 CA",
    "sg:province":"North Holland",
    "wof:name":"Serge Nodelijk Kapsalon",
    "wof:placetype":"venue"
},
  "geometry": {"coordinates":[5.172576,52.223785],"type":"Point"}
}