{
  "type": "Feature",
  "properties": {
    "addr:full":"Gedempte Nieuwesloot 24 Alkmaar North Holland 1811 KT",
    "addr:housenumber":"24",
    "addr:postcode":"1811 kt",
    "addr:street":"Gedempte Nieuwesloot",
    "iso:country":"NL",
    "sg:address":"Gedempte Nieuwesloot 24",
    "sg:city":"Alkmaar",
    "sg:orig_category":"Herenmodezaken",
    "sg:phone":"+31 72 511 6375",
    "sg:postcode":"1811 KT",
    "sg:province":"North Holland",
    "wof:name":"Atello Herenmode",
    "wof:placetype":"venue"
},
  "geometry": {"coordinates":[4.749157,52.632446],"type":"Point"}
}