{
  "type": "Feature",
  "properties": {
    "addr:full":"Achterwerf 95 Almere Flevoland 1357 BM",
    "addr:housenumber":"95",
    "addr:postcode":"1357 bm",
    "addr:street":"Achterwerf;Flevoland",
    "iso:country":"NL",
    "sg:address":"Achterwerf 95",
    "sg:city":"Almere",
    "sg:orig_category":"Fotopersbureaus",
    "sg:phone":"+31 36 531 3888",
    "sg:postcode":"1357 BM",
    "sg:province":"Flevoland",
    "wof:name":"Almere Press",
    "wof:placetype":"venue"
},
  "geometry": {"coordinates":[5.229194,52.33672],"type":"Point"}
}