{
  "type": "Feature",
  "properties": {
    "addr:full":"De Zwingel 9 Lage Zwaluwe Noord-Brabant 4926 DC",
    "addr:housenumber":"9",
    "addr:postcode":"zwaluwe;4926",
    "addr:street":"De Zwingel",
    "iso:country":"NL",
    "sg:address":"De Zwingel 9",
    "sg:city":"Lage Zwaluwe",
    "sg:orig_category":"Diverse Consumentenartikelen Gh",
    "sg:phone":"+31 168 484 515",
    "sg:postcode":"4926 DC",
    "sg:province":"Noord-Brabant",
    "wof:name":"Comboland",
    "wof:placetype":"venue"
},
  "geometry": {"coordinates":[4.687683,51.712132],"type":"Point"}
}