{
  "type": "Feature",
  "properties": {
    "addr:full":"Midstr 153 Joure Friesland 8501 AL",
    "addr:housenumber":"153",
    "addr:postcode":"8501 al",
    "iso:country":"NL",
    "sg:address":"Midstr 153",
    "sg:city":"Joure",
    "sg:orig_category":"Schoenen - Reparaties",
    "sg:phone":"+31 513 416 601",
    "sg:postcode":"8501 AL",
    "sg:province":"Friesland",
    "wof:name":"Jong, De",
    "wof:placetype":"venue"
},
  "geometry": {"coordinates":[5.798056,52.966362],"type":"Point"}
}