{
  "type": "Feature",
  "properties": {
    "addr:full":"Modemstr 2A Amsterdam Noord-Holland 1033 RW",
    "addr:housenumber":"2a",
    "addr:postcode":"1033 rw",
    "addr:street":"Modemstr",
    "iso:country":"NL",
    "sg:address":"Modemstr 2A",
    "sg:city":"Amsterdam",
    "sg:orig_category":"Adviesbureaus Bedrijfsorganisatie",
    "sg:phone":"+31 20 633 4436",
    "sg:postcode":"1033 RW",
    "sg:province":"Noord-Holland",
    "sg:website":"http://www.renaval.nl",
    "wof:name":"Renaval",
    "wof:placetype":"venue"
},
  "geometry": {"coordinates":[4.889505,52.407539],"type":"Point"}
}