{
  "type": "Feature",
  "properties": {
    "addr:full":"Molenstraat 8 Geldrop Noord-Brabant 5664 HV",
    "addr:housenumber":"8",
    "addr:postcode":"5664 hv",
    "addr:street":"Molenstraat",
    "iso:country":"NL",
    "sg:address":"Molenstraat 8",
    "sg:city":"Geldrop",
    "sg:orig_category":"Schoenen",
    "sg:phone":"+31 40 286 2200",
    "sg:postcode":"5664 HV",
    "sg:province":"Noord-Brabant",
    "wof:name":"J.J. Paymans",
    "wof:placetype":"venue"
},
  "geometry": {"coordinates":[5.555536,51.416279],"type":"Point"}
}