{
  "type": "Feature",
  "properties": {
    "addr:full":"Drossard Meyerstr 30 Gemert Noord-Brabant 5421 JC",
    "addr:housenumber":"30",
    "addr:postcode":"5421 jc",
    "addr:street":"Meyerstr",
    "iso:country":"NL",
    "sg:address":"Drossard Meyerstr 30",
    "sg:city":"Gemert",
    "sg:orig_category":"Schilders",
    "sg:phone":"+31 492 364 931",
    "sg:postcode":"5421 JC",
    "sg:province":"Noord-Brabant",
    "wof:name":"Bungelaar, Mari Van Den",
    "wof:placetype":"venue"
},
  "geometry": {"coordinates":[5.695496,51.55455],"type":"Point"}
}