{
  "type": "Feature",
  "properties": {
    "addr:full":"Buitenpln 88 Amstelveen North Holland 1181 ZE",
    "addr:housenumber":"88",
    "addr:postcode":"1181 ze",
    "addr:street":"Buitenpln",
    "iso:country":"NL",
    "sg:address":"Buitenpln 88",
    "sg:city":"Amstelveen",
    "sg:orig_category":"Warenhuizen",
    "sg:phone":"+31 900 9800",
    "sg:postcode":"1181 ZE",
    "sg:province":"North Holland",
    "sg:website":"http://www.kijkshop.nl",
    "wof:name":"Kijkshop",
    "wof:placetype":"venue"
},
  "geometry": {"coordinates":[4.8636231422,52.3016815186],"type":"Point"}
}