{
  "type": "Feature",
  "properties": {
    "addr:full":"Wolfstr 55 Helmond Noord-Brabant 5701 JB",
    "addr:housenumber":"55",
    "addr:postcode":"5701 jb",
    "addr:street":"Wolfstr",
    "iso:country":"NL",
    "sg:address":"Wolfstr 55",
    "sg:city":"Helmond",
    "sg:classifiers":[
        {
            "category":"Food & Beverages",
            "subcategory":"Bakery",
            "type":"Retail Goods"
        }
    ],
    "sg:phone":"+31 492 523 255",
    "sg:postcode":"5701 JB",
    "sg:province":"Noord-Brabant",
    "sg:tags":[
        "brood",
        "en",
        "banket"
    ],
    "wof:name":"Steen, H Van Der",
    "wof:placetype":"venue"
},
  "geometry": {"coordinates":[5.664708,51.480434],"type":"Point"}
}