{
  "type": "Feature",
  "properties": {
    "addr:full":"Weezenhof 5522 Nijmegen Gelderland 6536 EE",
    "addr:housenumber":"5522",
    "addr:postcode":"6536 ee",
    "addr:street":"Weezenhof;Gelderland",
    "iso:country":"NL",
    "sg:address":"Weezenhof 5522",
    "sg:city":"Nijmegen",
    "sg:classifiers":[
        {
            "category":"Fast Food",
            "type":"Food & Drink"
        }
    ],
    "sg:phone":"+31 24 345 0883",
    "sg:postcode":"6536 EE",
    "sg:province":"Gelderland",
    "sg:tags":[
        "afhaal",
        "restaurant"
    ],
    "wof:name":"Bardolino Pizzeria",
    "wof:placetype":"venue"
},
  "geometry": {"coordinates":[5.807722,51.801792],"type":"Point"}
}