{
  "type": "Feature",
  "properties": {
    "addr:full":"Oosterpk 61 Amsterdam Noord-Holland 1092 AR",
    "addr:housenumber":"61",
    "addr:postcode":"1092",
    "addr:street":"Oosterpk",
    "iso:country":"NL",
    "sg:address":"Oosterpk 61",
    "sg:city":"Amsterdam",
    "sg:orig_category":"Artsen - Manuele Geneeskunde",
    "sg:phone":"+31 20 690 7572",
    "sg:postcode":"1092 AR",
    "sg:province":"Noord-Holland",
    "wof:name":"Mentink, E J",
    "wof:placetype":"venue"
},
  "geometry": {"coordinates":[-80.889038,40.459206],"type":"Point"}
}