{
  "type": "Feature",
  "properties": {
    "addr:full":"Havenstraat 55 Zaandam North Holland 1506 PJ",
    "addr:housenumber":"55",
    "addr:postcode":"1506 pj",
    "addr:street":"Havenstraat",
    "iso:country":"NL",
    "sg:address":"Havenstraat 55",
    "sg:city":"Zaandam",
    "sg:orig_category":"Loodgieterswerk, Verwarming And Sanitaire Installaties",
    "sg:phone":"+31 6 22946828",
    "sg:postcode":"1506 PJ",
    "sg:province":"North Holland",
    "wof:name":"V. Puttenaar",
    "wof:placetype":"venue"
},
  "geometry": {"coordinates":[4.831031,52.429466],"type":"Point"}
}