{
  "type": "Feature",
  "properties": {
    "addr:full":"Herenstraat 86 Voorhout Zuid-Holland 2215 KJ",
    "addr:housenumber":"86",
    "addr:postcode":"2215 kj",
    "addr:street":"Herenstraat",
    "iso:country":"NL",
    "sg:address":"Herenstraat 86",
    "sg:city":"Voorhout",
    "sg:classifiers":[
        {
            "category":"Food & Beverages",
            "subcategory":"Fruits & Vegetables",
            "type":"Retail Goods"
        }
    ],
    "sg:phone":"+31 252 214 075",
    "sg:postcode":"2215 KJ",
    "sg:province":"Zuid-Holland",
    "sg:tags":[
        "groenten"
    ],
    "wof:name":"Van Kesteren Groente En Fruit Vof",
    "wof:placetype":"venue"
},
  "geometry": {"coordinates":[4.480833,52.220943],"type":"Point"}
}