{
  "type": "Feature",
  "properties": {
    "iso:country":"NL",
    "sg:address":"Bonzywg 19A",
    "sg:city":"Wemeldinge",
    "sg:orig_category":"Geluidsinstallaties - Verhuur",
    "sg:phone":"+31 113 622 615",
    "sg:postcode":"4424 AN",
    "sg:province":"Zeeland",
    "wof:name":"Audio Consult",
    "wof:placetype":"venue"
},
  "geometry": {"coordinates":[3.997705,51.513371],"type":"Point"}
}