{
  "type": "Feature",
  "properties": {
    "addr:full":"Bieslook 24 Didam Gelderland 6942 SG",
    "addr:housenumber":"24",
    "addr:postcode":"6942",
    "addr:street":"Bieslook;Gelderland",
    "iso:country":"NL",
    "sg:address":"Bieslook 24",
    "sg:city":"Didam",
    "sg:orig_category":"Verenigingen En Stichtingen",
    "sg:phone":"+31 316 529 660",
    "sg:postcode":"6942 SG",
    "sg:province":"Gelderland",
    "wof:name":"Sti-Je-Bo",
    "wof:placetype":"venue"
},
  "geometry": {"coordinates":[6.115255,51.931461],"type":"Point"}
}