{
  "type": "Feature",
  "properties": {
    "addr:full":"Caumerweg 1 Heerlen Limburg 6418 BA",
    "addr:housenumber":"1",
    "addr:postcode":"6418 ba",
    "addr:street":"Caumerweg",
    "iso:country":"NL",
    "sg:address":"Caumerweg 1",
    "sg:city":"Heerlen",
    "sg:classifiers":[
        {
            "category":"Fast Food",
            "type":"Food & Drink"
        }
    ],
    "sg:phone":"+31 45 542 4513",
    "sg:postcode":"6418 BA",
    "sg:province":"Limburg",
    "sg:tags":[
        "afhaal",
        "restaurant"
    ],
    "wof:name":"Friterie Op Gen Baan",
    "wof:placetype":"venue"
},
  "geometry": {"coordinates":[5.998797,50.868477],"type":"Point"}
}