{
  "type": "Feature",
  "properties": {
    "iso:country":"NL",
    "sg:address":"Sportln 451",
    "sg:city":"Sliedrecht",
    "sg:orig_category":"Verpakkingen En Verpakkingsmaterialen",
    "sg:phone":"+31 184 416 566",
    "sg:postcode":"3364 DK",
    "sg:province":"Zuid-Holland",
    "sg:website":"http://www.pellikaan.nl",
    "wof:name":"Pellikaan'S Verpakkingen",
    "wof:placetype":"venue"
},
  "geometry": {"coordinates":[4.772605,51.823555],"type":"Point"}
}