{
  "type": "Feature",
  "properties": {
    "iso:country":"NL",
    "sg:address":"Hoofdstraat 66",
    "sg:city":"Terheijden",
    "sg:orig_category":"Bloemen And Planten",
    "sg:phone":"+31 76 593 2155",
    "sg:postcode":"4844 CG",
    "sg:province":"North Brabant",
    "wof:name":"Jongejans Boutiques",
    "wof:placetype":"venue"
},
  "geometry": {"coordinates":[4.756871,51.639145],"type":"Point"}
}