{
  "type": "Feature",
  "properties": {
    "addr:full":"Eemdijk 93 Eemdijk Utrecht 3754 ND",
    "addr:housenumber":"93",
    "addr:postcode":"3754 nd",
    "addr:street":"Eemdijk",
    "iso:country":"NL",
    "sg:address":"Eemdijk 93",
    "sg:city":"Eemdijk",
    "sg:classifiers":[
        {
            "category":"Bakery",
            "type":"Food & Drink"
        }
    ],
    "sg:phone":"+31 33 298 3727",
    "sg:postcode":"3754 ND",
    "sg:province":"Utrecht",
    "sg:tags":[
        "brood",
        "banket"
    ],
    "wof:name":"Vof J. En E. Veldhuizen",
    "wof:placetype":"venue"
},
  "geometry": {"coordinates":[5.325709,52.252438],"type":"Point"}
}