{
  "type": "Feature",
  "properties": {
    "iso:country":"NL",
    "sg:address":"Achthoven 76",
    "sg:city":"Lexmond",
    "sg:orig_category":"Grondwerken",
    "sg:phone":"+31 183 601 801",
    "sg:postcode":"4128 LX",
    "sg:province":"Zuid-Holland",
    "wof:name":"Kool, Daan",
    "wof:placetype":"venue"
},
  "geometry": {"coordinates":[4.98582,51.963692],"type":"Point"}
}