{
  "type": "Feature",
  "properties": {
    "addr:full":"Brouwery 67 Gorredyk Provincie Friesland 8401 PN",
    "addr:housenumber":"67",
    "addr:postcode":"8401 pn",
    "addr:street":"Brouwery;Provincie Friesland",
    "iso:country":"NL",
    "sg:address":"Brouwery 67",
    "sg:city":"Gorredyk",
    "sg:orig_category":"Autorijscholen",
    "sg:phone":"+31 513 463 345",
    "sg:postcode":"8401 PN",
    "sg:province":"Provincie Friesland",
    "wof:name":"Jongsma, Autorijschool",
    "wof:placetype":"venue"
},
  "geometry": {"coordinates":[6.073163,52.998661],"type":"Point"}
}