{
  "type": "Feature",
  "properties": {
    "addr:full":"Hermelynkoog 36 Alkmaar Noord-Holland 1822 CB",
    "addr:housenumber":"36",
    "addr:postcode":"1822 cb",
    "addr:street":"Hermelynkoog",
    "iso:country":"NL",
    "sg:address":"Hermelynkoog 36",
    "sg:city":"Alkmaar",
    "sg:orig_category":"Horecabenodigdheden",
    "sg:phone":"+31 72 562 8917",
    "sg:postcode":"1822 CB",
    "sg:province":"Noord-Holland",
    "sg:website":"http://www.tonhagedoorn.nl",
    "wof:name":"Hagedoorn",
    "wof:placetype":"venue"
},
  "geometry": {"coordinates":[4.791626,52.649693],"type":"Point"}
}