{
  "type": "Feature",
  "properties": {
    "iso:country":"NL",
    "sg:address":"Hermelynkoog 36",
    "sg:city":"Alkmaar",
    "sg:orig_category":"Horecabenodigdheden",
    "sg:phone":"+31 72 562 8917",
    "sg:postcode":"1822 CB",
    "sg:province":"Noord-Holland",
    "sg:website":"http://www.tonhagedoorn.nl",
    "wof:name":"Hagedoorn",
    "wof:placetype":"venue"
},
  "geometry": {"coordinates":[4.791626,52.649693],"type":"Point"}
}