{
  "type": "Feature",
  "properties": {
    "addr:full":"Zwartbroekstr 5 Roermond Limburg 6041 JL",
    "addr:housenumber":"5",
    "addr:postcode":"6041 jl",
    "addr:street":"Zwartbroekstr",
    "iso:country":"NL",
    "sg:address":"Zwartbroekstr 5",
    "sg:city":"Roermond",
    "sg:orig_category":"Plafonds",
    "sg:phone":"+31 475 315 353",
    "sg:postcode":"6041 JL",
    "sg:province":"Limburg",
    "wof:name":"Gepla Bv",
    "wof:placetype":"venue"
},
  "geometry": {"coordinates":[5.987166,51.190987],"type":"Point"}
}