{
  "type": "Feature",
  "properties": {
    "addr:full":"Molenparkwg 10 Lunteren Gelderland 6741 ZR",
    "addr:housenumber":"10",
    "addr:postcode":"6741",
    "addr:street":"Molenparkwg;Gelderland",
    "iso:country":"NL",
    "sg:address":"Molenparkwg 10",
    "sg:city":"Lunteren",
    "sg:orig_category":"Makelaars En Adviseurs Onroerende Goederen",
    "sg:phone":"+31 318 482 366",
    "sg:postcode":"6741 ZR",
    "sg:province":"Gelderland",
    "sg:website":"http://www.makelaardij.com",
    "wof:name":"Keus Bv",
    "wof:placetype":"venue"
},
  "geometry": {"coordinates":[5.620351,52.086452],"type":"Point"}
}