{
  "type": "Feature",
  "properties": {
    "addr:full":"Fluitersdreef 8 Renkum Gelderland 6871 LP",
    "addr:housenumber":"8",
    "addr:postcode":"6871 lp",
    "addr:street":"Fluitersdreef;Gelderland",
    "iso:country":"NL",
    "sg:address":"Fluitersdreef 8",
    "sg:city":"Renkum",
    "sg:orig_category":"Gehandicapten - Hulpmiddelen",
    "sg:phone":"+31 317 316 836",
    "sg:postcode":"6871 LP",
    "sg:province":"Gelderland",
    "sg:website":"http://www.rollingdutchman.nl",
    "wof:name":"Archimedec Vof",
    "wof:placetype":"venue"
},
  "geometry": {"coordinates":[5.744964,51.983639],"type":"Point"}
}