{
  "type": "Feature",
  "properties": {
    "addr:full":"Bilderdijklaan 1 Ridderkerk South Holland 2985 XA",
    "addr:housenumber":"1",
    "addr:postcode":"2985 xa",
    "addr:street":"Bilderdijklaan",
    "iso:country":"NL",
    "sg:address":"Bilderdijklaan 1",
    "sg:city":"Ridderkerk",
    "sg:orig_category":"Metaalbekleding And -Behandeling",
    "sg:phone":"+31 180 421 140",
    "sg:postcode":"2985 XA",
    "sg:province":"South Holland",
    "wof:name":"Hassink Bedrijfsdiensten Bv",
    "wof:placetype":"venue"
},
  "geometry": {"coordinates":[4.607189,51.86517],"type":"Point"}
}