{
  "type": "Feature",
  "properties": {
    "addr:full":"Munsterpln 19 Roermond Limburg 6041 HE",
    "addr:housenumber":"19",
    "addr:postcode":"6041 he",
    "addr:street":"Munsterpln",
    "iso:country":"NL",
    "sg:address":"Munsterpln 19",
    "sg:city":"Roermond",
    "sg:orig_category":"Dameskleding",
    "sg:phone":"+31 475 334 402",
    "sg:postcode":"6041 HE",
    "sg:province":"Limburg",
    "wof:name":"Fashion Team",
    "wof:placetype":"venue"
},
  "geometry": {"coordinates":[5.988102,51.193867],"type":"Point"}
}