{
  "type": "Feature",
  "properties": {
    "addr:full":"Schippersdonk 9 Breda Noord-Brabant 4824 DT",
    "addr:housenumber":"9",
    "addr:postcode":"4824 dt",
    "addr:street":"Schippersdonk",
    "iso:country":"NL",
    "sg:address":"Schippersdonk 9",
    "sg:city":"Breda",
    "sg:orig_category":"Loonbedrijven",
    "sg:phone":"+31 76 541 0616",
    "sg:postcode":"4824 DT",
    "sg:province":"Noord-Brabant",
    "wof:name":"Karaca, E",
    "wof:placetype":"venue"
},
  "geometry": {"coordinates":[4.747016,51.609608],"type":"Point"}
}