{
  "type": "Feature",
  "properties": {
    "iso:country":"NL",
    "sg:address":"Zandstr 11",
    "sg:city":"Nuland",
    "sg:orig_category":"Bedrijfsmechanisatie En -Automatisering",
    "sg:phone":"+31 73 534 1082",
    "sg:postcode":"5391 AL",
    "sg:province":"Noord-Brabant",
    "sg:website":"http://www.vandenakker.net",
    "wof:name":"Akker Electric Engineering, Van Den",
    "wof:placetype":"venue"
},
  "geometry": {"coordinates":[5.43647,51.727791],"type":"Point"}
}