{
  "type": "Feature",
  "properties": {
    "iso:country":"NL",
    "sg:address":"Prins Hendrikstraat 27",
    "sg:city":"Groot Ammers",
    "sg:orig_category":"Fotostudio'S And Fotografen",
    "sg:phone":"+31 184 662 595",
    "sg:postcode":"2964 CL",
    "sg:province":"South Holland",
    "wof:name":"Independent",
    "wof:placetype":"venue"
},
  "geometry": {"coordinates":[4.823415,51.924168],"type":"Point"}
}