{
  "type": "Feature",
  "properties": {
    "addr:full":"Herenwg 83 Wilnis Utrecht 3648 CB",
    "addr:housenumber":"83",
    "addr:postcode":"3648 cb",
    "addr:street":"Herenwg",
    "iso:country":"NL",
    "sg:address":"Herenwg 83",
    "sg:city":"Wilnis",
    "sg:orig_category":"Oud Metaal",
    "sg:phone":"+31 297 273 002",
    "sg:postcode":"3648 CB",
    "sg:province":"Utrecht",
    "wof:name":"Metaal Mijdrecht Bv",
    "wof:placetype":"venue"
},
  "geometry": {"coordinates":[4.8922710419,52.1945533752],"type":"Point"}
}