{
  "type": "Feature",
  "properties": {
    "addr:full":"Stationsweg 13 Woerden Utrecht 3445 AC",
    "addr:housenumber":"13",
    "addr:postcode":"3445 ac",
    "addr:street":"Stationsweg",
    "iso:country":"NL",
    "sg:address":"Stationsweg 13",
    "sg:city":"Woerden",
    "sg:classifiers":[
        {
            "category":"Professional",
            "subcategory":"Accounting & Tax Preparation",
            "type":"Services"
        }
    ],
    "sg:phone":"+31 348 430 770",
    "sg:postcode":"3445 AC",
    "sg:province":"Utrecht",
    "sg:tags":[
        "accountant"
    ],
    "wof:name":"Accountantskantoor C. Schalkwijk Bv",
    "wof:placetype":"venue"
},
  "geometry": {"coordinates":[4.891668,52.086605],"type":"Point"}
}