{
  "type": "Feature",
  "properties": {
    "addr:full":"Hoogstr 68 Wageningen Gelderland 6701 BX",
    "addr:housenumber":"68",
    "addr:postcode":"6701 bx",
    "addr:street":"Hoogstr;Gelderland",
    "iso:country":"NL",
    "sg:address":"Hoogstr 68",
    "sg:city":"Wageningen",
    "sg:orig_category":"Schoenen",
    "sg:phone":"+31 317 424 618",
    "sg:postcode":"6701 BX",
    "sg:province":"Gelderland",
    "wof:name":"Scapino",
    "wof:placetype":"venue"
},
  "geometry": {"coordinates":[5.660976,51.964355],"type":"Point"}
}