{
  "type": "Feature",
  "properties": {
    "addr:full":"Gravenwg 68 Landgraaf Limburg 6374 BB",
    "addr:housenumber":"68",
    "addr:postcode":"6374 bb",
    "addr:street":"Gravenwg",
    "iso:country":"NL",
    "sg:address":"Gravenwg 68",
    "sg:city":"Landgraaf",
    "sg:orig_category":"Houtgroothandel",
    "sg:phone":"+31 45 533 3116",
    "sg:postcode":"6374 BB",
    "sg:province":"Limburg",
    "sg:website":"http://www.bukkfa.nl",
    "wof:name":"B?kkfa Bv",
    "wof:placetype":"venue"
},
  "geometry": {"coordinates":[6.035749,50.918819],"type":"Point"}
}