{
  "type": "Feature",
  "properties": {
    "addr:full":"De Heurne 27 Enschede Overijssel 7511 GZ",
    "addr:housenumber":"27",
    "addr:postcode":"7511 gz",
    "addr:street":"De Heurne",
    "iso:country":"NL",
    "sg:address":"De Heurne 27",
    "sg:city":"Enschede",
    "sg:orig_category":"Boeken En Tijdschriften",
    "sg:phone":"+31 53 431 7799",
    "sg:postcode":"7511 GZ",
    "sg:province":"Overijssel",
    "wof:name":"Siwa, Lektuurshop",
    "wof:placetype":"venue"
},
  "geometry": {"coordinates":[6.89861,52.220909],"type":"Point"}
}