{
  "type": "Feature",
  "properties": {
    "addr:full":"Nieuwstraat 27 Purmerend Noord-Holland 1441 CK",
    "addr:housenumber":"27",
    "addr:postcode":"1441 ck",
    "addr:street":"Nieuwstraat",
    "iso:country":"NL",
    "sg:address":"Nieuwstraat 27",
    "sg:city":"Purmerend",
    "sg:orig_category":"Kappers",
    "sg:phone":"+31 299 438 008",
    "sg:postcode":"1441 CK",
    "sg:province":"Noord-Holland",
    "wof:name":"T Barbertje Excentrique",
    "wof:placetype":"venue"
},
  "geometry": {"coordinates":[4.944656,52.508678],"type":"Point"}
}