{
  "type": "Feature",
  "properties": {
    "addr:full":"Granaatstr 28-6 Hengelo Ov Overijssel 7554 TR",
    "addr:housenumber":"28-6",
    "addr:postcode":"7554 tr",
    "addr:street":"Ov",
    "iso:country":"NL",
    "sg:address":"Granaatstr 28-6",
    "sg:city":"Hengelo Ov",
    "sg:orig_category":"Open Haarden",
    "sg:phone":"+31 74 250 5634",
    "sg:postcode":"7554 TR",
    "sg:province":"Overijssel",
    "wof:name":"Kuipers Open Haarden",
    "wof:placetype":"venue"
},
  "geometry": {"coordinates":[6.78971,52.266331],"type":"Point"}
}