{
  "type": "Feature",
  "properties": {
    "addr:full":"Hoogstr 94-96 Werkendam Noord-Brabant 4251 CP",
    "addr:housenumber":"94-96",
    "addr:postcode":"werkendam;4251 cp",
    "iso:country":"NL",
    "sg:address":"Hoogstr 94-96",
    "sg:city":"Werkendam",
    "sg:orig_category":"Cafetaria'S",
    "sg:phone":"+31 183 501 591",
    "sg:postcode":"4251 CP",
    "sg:province":"Noord-Brabant",
    "wof:name":"Eetsalon",
    "wof:placetype":"venue"
},
  "geometry": {"coordinates":[4.895317,51.808372],"type":"Point"}
}