{
  "type": "Feature",
  "properties": {
    "addr:full":"Pr Irenestr 7 Ter Aar Zuid-Holland 2461 VA",
    "addr:housenumber":"7",
    "addr:postcode":"aar;2461",
    "iso:country":"NL",
    "sg:address":"Pr Irenestr 7",
    "sg:city":"Ter Aar",
    "sg:orig_category":"Verenigingen En Stichtingen",
    "sg:phone":"+31 172 600 117",
    "sg:postcode":"2461 VA",
    "sg:province":"Zuid-Holland",
    "wof:name":"Arti Et Religioni",
    "wof:placetype":"venue"
},
  "geometry": {"coordinates":[4.710777,52.164295],"type":"Point"}
}