{
  "type": "Feature",
  "properties": {
    "addr:full":"Hemonyln 24 Amsterdam Noord-Holland 1074 BJ",
    "addr:housenumber":"24",
    "addr:postcode":"1074 bj",
    "addr:street":"Hemonyln",
    "iso:country":"NL",
    "sg:address":"Hemonyln 24",
    "sg:city":"Amsterdam",
    "sg:orig_category":"Beeldende Kunstenaars",
    "sg:phone":"+31 20 679 7682",
    "sg:postcode":"1074 BJ",
    "sg:province":"Noord-Holland",
    "wof:name":"Moock, P Van",
    "wof:placetype":"venue"
},
  "geometry": {"coordinates":[4.901614,52.357574],"type":"Point"}
}