{
  "type": "Feature",
  "properties": {
    "addr:full":"Grift 11 Uithoorn Noord-Holland 1423 DH",
    "addr:housenumber":"11",
    "addr:postcode":"1423 dh",
    "addr:street":"Grift",
    "iso:country":"NL",
    "sg:address":"Grift 11",
    "sg:city":"Uithoorn",
    "sg:orig_category":"Boekhouders",
    "sg:phone":"+31 297 531 929",
    "sg:postcode":"1423 DH",
    "sg:province":"Noord-Holland",
    "wof:name":"Administratiekantoor Tersteeg Van Oudenallen",
    "wof:placetype":"venue"
},
  "geometry": {"coordinates":[4.819539,52.230587],"type":"Point"}
}