{
  "type": "Feature",
  "properties": {
    "iso:country":"NL",
    "sg:address":"Rooseveltstr 14L",
    "sg:city":"Leiden",
    "sg:orig_category":"Modelmakerijen",
    "sg:phone":"+31 71 572 5601",
    "sg:postcode":"2321 BM",
    "sg:province":"Zuid-Holland",
    "sg:website":"http://www.dimarco.nl",
    "wof:name":"Dimarco Technical Systems",
    "wof:placetype":"venue"
},
  "geometry": {"coordinates":[4.481573,52.144997],"type":"Point"}
}