{
  "type": "Feature",
  "properties": {
    "iso:country":"NL",
    "sg:address":"Beekpk 28",
    "sg:city":"Apeldoorn",
    "sg:orig_category":"Kamerverhuur En -Bemiddeling",
    "sg:phone":"+31 55 578 9444",
    "sg:postcode":"7311 BZ",
    "sg:province":"Gelderland",
    "wof:name":"Kamerbank",
    "wof:placetype":"venue"
},
  "geometry": {"coordinates":[5.9574317932,52.2166900635],"type":"Point"}
}