{
  "type": "Feature",
  "properties": {
    "addr:full":"Markt 20 Veere Zeeland 4351 AH",
    "addr:housenumber":"20",
    "addr:postcode":"4351 ah",
    "addr:street":"Markt",
    "iso:country":"NL",
    "sg:address":"Markt 20",
    "sg:city":"Veere",
    "sg:classifiers":[
        {
            "category":"Fast Food",
            "type":"Food & Drink"
        }
    ],
    "sg:phone":"+31 118 501 301",
    "sg:postcode":"4351 AH",
    "sg:province":"Zeeland",
    "sg:tags":[
        "afhaal",
        "restaurant"
    ],
    "wof:name":"Attent Veere Vof",
    "wof:placetype":"venue"
},
  "geometry": {"coordinates":[3.668688,51.548771],"type":"Point"}
}