{
  "type": "Feature",
  "properties": {
    "addr:full":"Julianawg 7 Heteren Connecticut 6666 CT",
    "addr:housenumber":"7",
    "addr:postcode":"6666 ct",
    "addr:street":"Julianawg",
    "iso:country":"NL",
    "sg:address":"Julianawg 7",
    "sg:city":"Heteren",
    "sg:orig_category":"Horloges En Klokken - Reparatie En Onderhoud",
    "sg:phone":"+31 26 472 2320",
    "sg:postcode":"6666 CT",
    "sg:province":"Connecticut",
    "wof:name":"Dijkgraaf, A J",
    "wof:placetype":"venue"
},
  "geometry": {"coordinates":[-72.75747699999999,41.515572],"type":"Point"}
}