{
  "type": "Feature",
  "properties": {
    "addr:full":"Kennemerpark 7 Alkmaar Noord-Holland 1811 DD",
    "addr:housenumber":"7",
    "addr:postcode":"1811 dd",
    "addr:street":"Kennemerpark",
    "iso:country":"NL",
    "sg:address":"Kennemerpark 7",
    "sg:city":"Alkmaar",
    "sg:orig_category":"Advocaten And Juridische Adviseurs",
    "sg:phone":"+31 72 511 4032",
    "sg:postcode":"1811 DD",
    "sg:province":"Noord-Holland",
    "wof:name":"Smal & Castelijns Advocaten",
    "wof:placetype":"venue"
},
  "geometry": {"coordinates":[4.746634,52.628281],"type":"Point"}
}