{
  "type": "Feature",
  "properties": {
    "addr:full":"Middenweg 67 Den Helder Noord-Holland 1782 BB",
    "addr:housenumber":"67",
    "addr:postcode":"1782 bb",
    "addr:street":"Middenweg",
    "iso:country":"NL",
    "sg:address":"Middenweg 67",
    "sg:city":"Den Helder",
    "sg:orig_category":"Film-, Tv- And Videoproductie",
    "sg:phone":"+31 223 621 088",
    "sg:postcode":"1782 BB",
    "sg:province":"Noord-Holland",
    "wof:name":"Av Video",
    "wof:placetype":"venue"
},
  "geometry": {"coordinates":[4.753583,52.954964],"type":"Point"}
}