{
  "type": "Feature",
  "properties": {
    "iso:country":"NL",
    "sg:address":"Frobenstr 15",
    "sg:city":"Rotterdam",
    "sg:orig_category":"Loodgieters",
    "sg:phone":"+31 10 418 0706",
    "sg:postcode":"3045 RD",
    "sg:province":"South Holland",
    "wof:name":"Tournier & Zn Bv, M F",
    "wof:placetype":"venue"
},
  "geometry": {"coordinates":[4.462781,51.947609],"type":"Point"}
}