{
  "type": "Feature",
  "properties": {
    "addr:full":"Heyhoefpromenade 144 Tilburg North Brabant 5043 RP",
    "addr:housenumber":"144",
    "addr:postcode":"5043 rp",
    "addr:street":"Heyhoefpromenade",
    "iso:country":"NL",
    "sg:address":"Heyhoefpromenade 144",
    "sg:city":"Tilburg",
    "sg:orig_category":"Onroerende Goederen",
    "sg:phone":"+31 13 578 4400",
    "sg:postcode":"5043 RP",
    "sg:province":"North Brabant",
    "wof:name":"Mog Bv",
    "wof:placetype":"venue"
},
  "geometry": {"coordinates":[5.004999,51.577438],"type":"Point"}
}