{
  "type": "Feature",
  "properties": {
    "iso:country":"NL",
    "sg:address":"Hekellaan 23",
    "sg:city":"Schaijk",
    "sg:orig_category":"Verhuur Diversen",
    "sg:phone":"+31 486 462 443",
    "sg:postcode":"5374 GM",
    "sg:province":"Noord-Brabant",
    "wof:name":"Vof F.M. Strik",
    "wof:placetype":"venue"
},
  "geometry": {"coordinates":[5.633062,51.743034],"type":"Point"}
}