{
  "type": "Feature",
  "properties": {
    "addr:full":"Pletterijstraat 93 'S Gravenhage Zuid-Holland 2515 AW",
    "addr:housenumber":"93",
    "addr:postcode":"2515 aw",
    "addr:street":"Pletterijstraat;' S",
    "iso:country":"NL",
    "sg:address":"Pletterijstraat 93",
    "sg:city":"'S Gravenhage",
    "sg:orig_category":"Autokeuringen",
    "sg:phone":"+31 70 383 5599",
    "sg:postcode":"2515 AW",
    "sg:province":"Zuid-Holland",
    "wof:name":"Pitbox Wheels & Tires",
    "wof:placetype":"venue"
},
  "geometry": {"coordinates":[4.324595,52.074535],"type":"Point"}
}