{
  "type": "Feature",
  "properties": {
    "addr:full":"Dahliastr 32 Olst Overijssel 8121 DJ",
    "addr:housenumber":"32",
    "addr:postcode":"8121 dj",
    "addr:street":"Dahliastr",
    "iso:country":"NL",
    "sg:address":"Dahliastr 32",
    "sg:city":"Olst",
    "sg:orig_category":"Verenigingen En Stichtingen",
    "sg:phone":"+31 570 563 207",
    "sg:postcode":"8121 DJ",
    "sg:province":"Overijssel",
    "wof:name":"Nat Fibromyalgie Ver",
    "wof:placetype":"venue"
},
  "geometry": {"coordinates":[6.126791,52.332005],"type":"Point"}
}