{
  "type": "Feature",
  "properties": {
    "addr:full":"Nieuwemarkt 100 Roosendaal Noord-Brabant 4701 AM",
    "addr:housenumber":"100",
    "addr:postcode":"4701",
    "addr:street":"Nieuwemarkt",
    "iso:country":"NL",
    "sg:address":"Nieuwemarkt 100",
    "sg:city":"Roosendaal",
    "sg:orig_category":"Hout Gh",
    "sg:phone":"+31 165 542 848",
    "sg:postcode":"4701 AM",
    "sg:province":"Noord-Brabant",
    "wof:name":"Matheuse-De Wit- Perez",
    "wof:placetype":"venue"
},
  "geometry": {"coordinates":[4.459184,51.531017],"type":"Point"}
}