{
  "type": "Feature",
  "properties": {
    "addr:full":"P Aertszstr 85 Amsterdam Noord-Holland 1073 SL",
    "addr:housenumber":"85",
    "addr:postcode":"1073 sl",
    "addr:street":"P",
    "iso:country":"NL",
    "sg:address":"P Aertszstr 85",
    "sg:city":"Amsterdam",
    "sg:orig_category":"Adviesbureaus Bedrijfsorganisatie",
    "sg:phone":"+31 20 675 0789",
    "sg:postcode":"1073 SL",
    "sg:province":"Noord-Holland",
    "wof:name":"Mcn",
    "wof:placetype":"venue"
},
  "geometry": {"coordinates":[4.901967,52.352661],"type":"Point"}
}