{
  "type": "Feature",
  "properties": {
    "addr:full":"Ds Martin Luther Kingwg 136 Purmerend North Holland 1444 EG",
    "addr:housenumber":"136",
    "addr:postcode":"1444 eg",
    "addr:street":"Ds Martin Luther Kingwg",
    "iso:country":"NL",
    "sg:address":"Ds Martin Luther Kingwg 136",
    "sg:city":"Purmerend",
    "sg:orig_category":"Hypotheken And Hypotheekbanken",
    "sg:phone":"+31 299 427 859",
    "sg:postcode":"1444 EG",
    "sg:province":"North Holland",
    "wof:name":"R. Versteeg",
    "wof:placetype":"venue"
},
  "geometry": {"coordinates":[4.970235,52.522274],"type":"Point"}
}