{
  "type": "Feature",
  "properties": {
    "addr:full":"Ophelialaan 139 Aalsmeer Noord-Holland 1431 HD",
    "addr:housenumber":"139",
    "addr:postcode":"1431 hd",
    "addr:street":"Ophelialaan",
    "iso:country":"NL",
    "sg:address":"Ophelialaan 139",
    "sg:city":"Aalsmeer",
    "sg:classifiers":[
        {
            "category":"Fast Food",
            "type":"Food & Drink"
        }
    ],
    "sg:phone":"+31 297 362 221",
    "sg:postcode":"1431 HD",
    "sg:province":"Noord-Holland",
    "sg:tags":[
        "afhaal",
        "restaurant"
    ],
    "wof:name":"Smulwereld Cozijn",
    "wof:placetype":"venue"
},
  "geometry": {"coordinates":[4.761836,52.264603],"type":"Point"}
}