{
  "type": "Feature",
  "properties": {
    "iso:country":"NL",
    "sg:address":"Hoofdweg 1243",
    "sg:city":"Nieuw Vennep",
    "sg:orig_category":"Granen, Zaden And Diervoeders Gh",
    "sg:phone":"+31 252 672 376",
    "sg:postcode":"2151 MH",
    "sg:province":"Noord-Holland",
    "wof:name":"Gerrit Nijssen Bv",
    "wof:placetype":"venue"
},
  "geometry": {"coordinates":[4.626197,52.259605],"type":"Point"}
}