{
  "type": "Feature",
  "properties": {
    "iso:country":"NL",
    "sg:address":"Steenweg 20",
    "sg:city":"Utrecht",
    "sg:orig_category":"Opticiens",
    "sg:phone":"+31 30 231 3115",
    "sg:postcode":"3511 JP",
    "sg:province":"Utrecht",
    "wof:name":"Abelmann Brilmode",
    "wof:placetype":"venue"
},
  "geometry": {"coordinates":[5.1187949181,52.0907897949],"type":"Point"}
}