{
  "type": "Feature",
  "properties": {
    "iso:country":"NL",
    "sg:address":"Biesterwg 31",
    "sg:city":"Almelo",
    "sg:orig_category":"Vertalers",
    "sg:phone":"+31 546 862 906",
    "sg:postcode":"7608 RN",
    "sg:province":"NL.08",
    "wof:name":"Beekman-Sonntag, Drs M",
    "wof:placetype":"venue"
},
  "geometry": {"coordinates":[6.679895,52.375233],"type":"Point"}
}