{
  "type": "Feature",
  "properties": {
    "addr:full":"Meerkoet 3 Harmelen Utrecht 3481 TA",
    "addr:housenumber":"3",
    "addr:postcode":"3481 ta",
    "addr:street":"Meerkoet",
    "iso:country":"NL",
    "sg:address":"Meerkoet 3",
    "sg:city":"Harmelen",
    "sg:orig_category":"Metaalwerken",
    "sg:phone":"+31 6 54977205",
    "sg:postcode":"3481 TA",
    "sg:province":"Utrecht",
    "wof:name":"A.G. V.D. Boomen",
    "wof:placetype":"venue"
},
  "geometry": {"coordinates":[4.957959,52.093517],"type":"Point"}
}