{
  "type": "Feature",
  "properties": {
    "addr:full":"Spoorstraat 8 Boxmeer Noord-Brabant 5831 CL",
    "addr:housenumber":"8",
    "addr:postcode":"5831",
    "addr:street":"Spoorstraat",
    "iso:country":"NL",
    "sg:address":"Spoorstraat 8",
    "sg:city":"Boxmeer",
    "sg:classifiers":[
        {
            "category":"Communications",
            "subcategory":"Television Station",
            "type":"Services"
        }
    ],
    "sg:phone":"+31 485 521 961",
    "sg:postcode":"5831 CL",
    "sg:province":"Noord-Brabant",
    "sg:tags":[
        "video",
        "audio",
        "verhuur"
    ],
    "wof:name":"Videoland",
    "wof:placetype":"venue"
},
  "geometry": {"coordinates":[5.943274,51.648129],"type":"Point"}
}