{
  "type": "Feature",
  "properties": {
    "addr:full":"Pastoriestraat 19 Vlierden North Brabant 5756 AL",
    "addr:housenumber":"19",
    "addr:postcode":"5756 al",
    "addr:street":"Pastoriestraat",
    "iso:country":"NL",
    "sg:address":"Pastoriestraat 19",
    "sg:city":"Vlierden",
    "sg:orig_category":"Banken And Kredietinstellingen",
    "sg:phone":"+31 493 392 222",
    "sg:postcode":"5756 AL",
    "sg:province":"North Brabant",
    "wof:name":"Rabobank",
    "wof:placetype":"venue"
},
  "geometry": {"coordinates":[5.758473,51.44442],"type":"Point"}
}