{
  "type": "Feature",
  "properties": {
    "addr:full":"Laan 1940 1945 26 Meteren Gelderland 4194 RH",
    "addr:housenumber":"26",
    "addr:postcode":"4194 rh",
    "addr:street":"Laan 1940 1945;Gelderland",
    "iso:country":"NL",
    "sg:address":"Laan 1940 1945 26",
    "sg:city":"Meteren",
    "sg:orig_category":"Hondenscholen",
    "sg:phone":"+31 345 575 239",
    "sg:postcode":"4194 RH",
    "sg:province":"Gelderland",
    "wof:name":"Telma",
    "wof:placetype":"venue"
},
  "geometry": {"coordinates":[5.28502,51.870243],"type":"Point"}
}