{
  "type": "Feature",
  "properties": {
    "iso:country":"NL",
    "sg:address":"Kloosterln 14",
    "sg:city":"Druten",
    "sg:orig_category":"Adviesbureaus Bedrijfsveiligheid",
    "sg:phone":"+31 6 20011521",
    "sg:postcode":"6651 TL",
    "sg:province":"Gelderland",
    "wof:name":"Dbaz",
    "wof:placetype":"venue"
},
  "geometry": {"coordinates":[5.60491,51.893715],"type":"Point"}
}