{
  "type": "Feature",
  "properties": {
    "addr:full":"De Mildestraat 2 'S Gravenhage Zuid-Holland 2596 SX",
    "addr:housenumber":"2 '",
    "addr:postcode":"2596 sx",
    "addr:street":"De Mildestraat",
    "iso:country":"NL",
    "sg:address":"De Mildestraat 2",
    "sg:city":"'S Gravenhage",
    "sg:orig_category":"Verzekeringen",
    "sg:phone":"+31 70 324 8976",
    "sg:postcode":"2596 SX",
    "sg:province":"Zuid-Holland",
    "wof:name":"N B A Van Ryckevorsel-Girardot",
    "wof:placetype":"venue"
},
  "geometry": {"coordinates":[4.320636,52.09724],"type":"Point"}
}