{
  "type": "Feature",
  "properties": {
    "addr:full":"De Mate 20 Hattem Gelderland 8051 VW",
    "addr:housenumber":"20",
    "addr:postcode":"8051",
    "addr:street":"De Mate;Gelderland;Vw",
    "iso:country":"NL",
    "sg:address":"De Mate 20",
    "sg:city":"Hattem",
    "sg:orig_category":"Onroerende Goederen",
    "sg:phone":"+31 38 444 8435",
    "sg:postcode":"8051 VW",
    "sg:province":"Gelderland",
    "wof:name":"Eik Bv, De",
    "wof:placetype":"venue"
},
  "geometry": {"coordinates":[6.061803,52.477207],"type":"Point"}
}