{
  "type": "Feature",
  "properties": {
    "addr:full":"Energiewg 8 Soest Utrecht 3762 ET",
    "addr:housenumber":"8",
    "addr:postcode":"3762 et",
    "addr:street":"Energiewg",
    "iso:country":"NL",
    "sg:address":"Energiewg 8",
    "sg:city":"Soest",
    "sg:orig_category":"Autoschade- Herstelbedrijven",
    "sg:phone":"+31 35 601 3792",
    "sg:postcode":"3762 ET",
    "sg:province":"Utrecht",
    "sg:website":"http://www.stam.nl",
    "wof:name":"Groene, De",
    "wof:placetype":"venue"
},
  "geometry": {"coordinates":[5.276997,52.179863],"type":"Point"}
}