{
  "type": "Feature",
  "properties": {
    "addr:full":"Herenstraat 92 Voorhout Zuid-Holland 2215 KK",
    "addr:housenumber":"92",
    "addr:postcode":"2215 kk",
    "addr:street":"Herenstraat",
    "iso:country":"NL",
    "sg:address":"Herenstraat 92",
    "sg:city":"Voorhout",
    "sg:orig_category":"Huishoudapparatuur, Televisies And Radio'S",
    "sg:phone":"+31 252 211 567",
    "sg:postcode":"2215 KK",
    "sg:province":"Zuid-Holland",
    "wof:name":"Expert Huyts & Post",
    "wof:placetype":"venue"
},
  "geometry": {"coordinates":[4.481321,52.221195],"type":"Point"}
}