{
  "type": "Feature",
  "properties": {
    "addr:full":"Wannestraat 4 Dalfsen NL.08 7722 RT",
    "addr:housenumber":"4;nl.08",
    "addr:postcode":"7722 rt",
    "addr:street":"Wannestraat",
    "iso:country":"NL",
    "sg:address":"Wannestraat 4",
    "sg:city":"Dalfsen",
    "sg:orig_category":"Woningbouwverenigingen",
    "sg:phone":"+31 529 438 866",
    "sg:postcode":"7722 RT",
    "sg:province":"NL.08",
    "wof:name":"Woonstichting Vechthorst",
    "wof:placetype":"venue"
},
  "geometry": {"coordinates":[6.2651281357,52.5101966858],"type":"Point"}
}