{
  "type": "Feature",
  "properties": {
    "iso:country":"NL",
    "sg:address":"Wannestraat 4",
    "sg:city":"Dalfsen",
    "sg:orig_category":"Woningbouwverenigingen",
    "sg:phone":"+31 529 438 866",
    "sg:postcode":"7722 RT",
    "sg:province":"NL.08",
    "wof:name":"Woonstichting Vechthorst",
    "wof:placetype":"venue"
},
  "geometry": {"coordinates":[6.2651281357,52.5101966858],"type":"Point"}
}