{
  "type": "Feature",
  "properties": {
    "addr:full":"Nauwe Noorderhorne 1 Sneek Provincie Friesland 8601 CW",
    "addr:housenumber":"1",
    "addr:postcode":"8601 cw",
    "addr:street":"Nauwe Noorderhorne;Provincie Friesland",
    "iso:country":"NL",
    "sg:address":"Nauwe Noorderhorne 1",
    "sg:city":"Sneek",
    "sg:orig_category":"Feestartikelen",
    "sg:phone":"+31 515 431 094",
    "sg:postcode":"8601 CW",
    "sg:province":"Provincie Friesland",
    "sg:website":"http://www.toverbal.com",
    "wof:name":"De Toverbal",
    "wof:placetype":"venue"
},
  "geometry": {"coordinates":[5.658091,53.032425],"type":"Point"}
}