{
  "type": "Feature",
  "properties": {
    "addr:full":"Deltastr 21 Bruinisse Zeeland 4311 GL",
    "addr:housenumber":"21",
    "addr:postcode":"4311 gl",
    "addr:street":"Deltastr",
    "iso:country":"NL",
    "sg:address":"Deltastr 21",
    "sg:city":"Bruinisse",
    "sg:orig_category":"Mosselen En Oesters",
    "sg:phone":"+31 111 484 161",
    "sg:postcode":"4311 GL",
    "sg:province":"Zeeland",
    "wof:name":"Okkerse, W",
    "wof:placetype":"venue"
},
  "geometry": {"coordinates":[4.088684,51.662521],"type":"Point"}
}