{
  "type": "Feature",
  "properties": {
    "addr:full":"Havezatestr 53 Tubbergen Overijssel 7651 JL",
    "addr:housenumber":"53",
    "addr:postcode":"7651 jl",
    "addr:street":"Havezatestr",
    "iso:country":"NL",
    "sg:address":"Havezatestr 53",
    "sg:city":"Tubbergen",
    "sg:orig_category":"Verloskundigen",
    "sg:phone":"+31 546 621 340",
    "sg:postcode":"7651 JL",
    "sg:province":"Overijssel",
    "wof:name":"Verloskundigenpraktijk Tubbergen, I",
    "wof:placetype":"venue"
},
  "geometry": {"coordinates":[6.795109,52.408321],"type":"Point"}
}