{
  "type": "Feature",
  "properties": {
    "addr:full":"Sleedoorn 29 Zeewolde NL. 3892 CN",
    "addr:housenumber":"29",
    "addr:postcode":"3892 cn",
    "addr:street":"Sleedoorn;Nl.",
    "iso:country":"NL",
    "sg:address":"Sleedoorn 29",
    "sg:city":"Zeewolde",
    "sg:orig_category":"Boekhouders",
    "sg:phone":"+31 36 522 6226",
    "sg:postcode":"3892 CN",
    "sg:province":"NL.",
    "wof:name":"Martin De Wit Warmtetechniek Bv",
    "wof:placetype":"venue"
},
  "geometry": {"coordinates":[5.534086,52.326073],"type":"Point"}
}