{
  "type": "Feature",
  "properties": {
    "addr:full":"Piepenbrockln 7 Waalre Noord-Brabant 5583 GE",
    "addr:housenumber":"7",
    "addr:postcode":"5583",
    "addr:street":"Piepenbrockln",
    "iso:country":"NL",
    "sg:address":"Piepenbrockln 7",
    "sg:city":"Waalre",
    "sg:orig_category":"Adviesbureaus Bedrijfsorganisatie",
    "sg:phone":"+31 40 222 1700",
    "sg:postcode":"5583 GE",
    "sg:province":"Noord-Brabant",
    "sg:website":"http://www.cmmc.nl",
    "wof:name":"Cmmc Management Consulting Bv",
    "wof:placetype":"venue"
},
  "geometry": {"coordinates":[5.488922,51.401268],"type":"Point"}
}