{
  "type": "Feature",
  "properties": {
    "addr:full":"Mijnzetellaan 4 Heerlen Limburg 6412 EN",
    "addr:housenumber":"4",
    "addr:postcode":"6412 en",
    "addr:street":"Mijnzetellaan",
    "iso:country":"NL",
    "sg:address":"Mijnzetellaan 4",
    "sg:city":"Heerlen",
    "sg:classifiers":[
        {
            "category":"Education",
            "subcategory":"Preschool",
            "type":"Public Place"
        }
    ],
    "sg:phone":"+31 45 572 3828",
    "sg:postcode":"6412 EN",
    "sg:province":"Limburg",
    "sg:tags":[
        "kleuteronderwijs",
        "basis-"
    ],
    "wof:name":"Openbare Basisschool De Piramide Locatie Freinet",
    "wof:placetype":"venue"
},
  "geometry": {"coordinates":[5.95914,50.898735],"type":"Point"}
}