{
  "type": "Feature",
  "properties": {
    "addr:full":"Purperreiger 58 Ouderkerk Amstel North Holland 1191 SM",
    "addr:housenumber":"58",
    "addr:postcode":"1191 sm",
    "addr:street":"Purperreiger;Amstel",
    "iso:country":"NL",
    "sg:address":"Purperreiger 58",
    "sg:city":"Ouderkerk Amstel",
    "sg:orig_category":"Vertalers",
    "sg:phone":"+31 20 496 7770",
    "sg:postcode":"1191 SM",
    "sg:province":"North Holland",
    "wof:name":"Men\u00e9ndez De Lagranda",
    "wof:placetype":"venue"
},
  "geometry": {"coordinates":[4.912653,52.292332],"type":"Point"}
}