{
  "type": "Feature",
  "properties": {
    "addr:full":"Burgemeester Rothestraat 96 Wijk Aan Zee Noord-Holland 1949 CG",
    "addr:housenumber":"96",
    "addr:postcode":"1949 cg",
    "addr:street":"Burgemeester Rothestraat",
    "iso:country":"NL",
    "sg:address":"Burgemeester Rothestraat 96",
    "sg:city":"Wijk Aan Zee",
    "sg:orig_category":"Schoonheidssalons",
    "sg:phone":"+31 251 375 882",
    "sg:postcode":"1949 CG",
    "sg:province":"Noord-Holland",
    "wof:name":"Salon Voor Huidverz. Lucie Van Den Heuve",
    "wof:placetype":"venue"
},
  "geometry": {"coordinates":[4.599593,52.493973],"type":"Point"}
}