{
  "type": "Feature",
  "properties": {
    "iso:country":"NL",
    "sg:address":"Schoolstr 14",
    "sg:city":"Rotterdam",
    "sg:orig_category":"Grafisch Ontwerpers",
    "sg:phone":"+31 10 461 2665",
    "sg:postcode":"3053 ZM",
    "sg:province":"Zuid-Holland",
    "wof:name":"Jamin, M G",
    "wof:placetype":"venue"
},
  "geometry": {"coordinates":[4.471753,51.963833],"type":"Point"}
}