{
  "type": "Feature",
  "properties": {
    "addr:full":"Oranjeboomstraat 230 Rotterdam South Holland 3071 BL",
    "addr:housenumber":"230",
    "addr:postcode":"3071 bl",
    "addr:street":"Oranjeboomstraat",
    "iso:country":"NL",
    "sg:address":"Oranjeboomstraat 230",
    "sg:city":"Rotterdam",
    "sg:orig_category":"Boekhouders",
    "sg:phone":"+31 10 485 9552",
    "sg:postcode":"3071 BL",
    "sg:province":"South Holland",
    "wof:name":"Administratiekantoor Postco",
    "wof:placetype":"venue"
},
  "geometry": {"coordinates":[4.509727,51.906403],"type":"Point"}
}