{
  "type": "Feature",
  "properties": {
    "addr:full":"M Euwepln 48 Amsterdam North Holland 1017 MB",
    "addr:housenumber":"48",
    "addr:postcode":"1017 mb",
    "iso:country":"NL",
    "sg:address":"M Euwepln 48",
    "sg:city":"Amsterdam",
    "sg:orig_category":"Herenkleding",
    "sg:phone":"+31 20 627 4793",
    "sg:postcode":"1017 MB",
    "sg:province":"North Holland",
    "wof:name":"Marc Smith",
    "wof:placetype":"venue"
},
  "geometry": {"coordinates":[4.882932,52.362354],"type":"Point"}
}