{
  "type": "Feature",
  "properties": {
    "addr:full":"H Tollensstr 1 Delft Zuid-Holland 2624 BH",
    "addr:housenumber":"1",
    "addr:postcode":"2624 bh",
    "addr:street":"Delft",
    "iso:country":"NL",
    "sg:address":"H Tollensstr 1",
    "sg:city":"Delft",
    "sg:orig_category":"Biljartzalen",
    "sg:phone":"+31 15 262 5680",
    "sg:postcode":"2624 BH",
    "sg:province":"Zuid-Holland",
    "wof:name":"Snooker Palace",
    "wof:placetype":"venue"
},
  "geometry": {"coordinates":[4.355088,51.996449],"type":"Point"}
}