{
  "type": "Feature",
  "properties": {
    "addr:full":"Ursulastr 2 Harreveld Gelderland 7135 JD",
    "addr:housenumber":"2",
    "addr:postcode":"7135 jd",
    "addr:street":"Ursulastr;Gelderland",
    "iso:country":"NL",
    "sg:address":"Ursulastr 2",
    "sg:city":"Harreveld",
    "sg:orig_category":"Verenigingsgebouwen",
    "sg:phone":"+31 544 372 959",
    "sg:postcode":"7135 JD",
    "sg:province":"Gelderland",
    "wof:name":"Kempken, 'T",
    "wof:placetype":"venue"
},
  "geometry": {"coordinates":[6.518938,51.978512],"type":"Point"}
}