{
  "type": "Feature",
  "properties": {
    "iso:country":"NL",
    "sg:address":"H Hoekstrahof 166",
    "sg:city":"Hoorn Nh",
    "sg:orig_category":"Kappers",
    "sg:phone":"+31 229 263 646",
    "sg:postcode":"1628 WV",
    "sg:province":"Noord-Holland",
    "wof:name":"Hair Express",
    "wof:placetype":"venue"
},
  "geometry": {"coordinates":[5.1050891876,52.6566314697],"type":"Point"}
}