{
  "type": "Feature",
  "properties": {
    "addr:full":"Woldweg 13 Appingedam Groningen 9902 AA",
    "addr:housenumber":"13",
    "addr:postcode":"9902 aa",
    "addr:street":"Woldweg",
    "iso:country":"NL",
    "sg:address":"Woldweg 13",
    "sg:city":"Appingedam",
    "sg:orig_category":"Autokeuringen",
    "sg:phone":"+31 596 627 837",
    "sg:postcode":"9902 AA",
    "sg:province":"Groningen",
    "wof:name":"Garage G J De Bruijn",
    "wof:placetype":"venue"
},
  "geometry": {"coordinates":[6.86116,53.31905],"type":"Point"}
}