{
  "type": "Feature",
  "properties": {
    "addr:full":"Zuideinde 26 Westzaan Noord-Holland 1551 EJ",
    "addr:housenumber":"26",
    "addr:postcode":"1551 ej",
    "addr:street":"Zuideinde",
    "iso:country":"NL",
    "sg:address":"Zuideinde 26",
    "sg:city":"Westzaan",
    "sg:orig_category":"Kantoorartikelen",
    "sg:phone":"+31 75 616 3540",
    "sg:postcode":"1551 EJ",
    "sg:province":"Noord-Holland",
    "wof:name":"Schildersbedrijf Sol",
    "wof:placetype":"venue"
},
  "geometry": {"coordinates":[4.7814269066,52.4319839478],"type":"Point"}
}