{
  "type": "Feature",
  "properties": {
    "iso:country":"NL",
    "sg:address":"Nieuwe Veenendaalseweg 61",
    "sg:city":"Rhenen",
    "sg:orig_category":"Loodgieterswerk, Verwarming And Sanitaire Installaties",
    "sg:phone":"+31 317 615 084",
    "sg:postcode":"3911  M",
    "sg:province":"Utrecht",
    "wof:name":"Installatiebedrijf Van Walsem",
    "wof:placetype":"venue"
},
  "geometry": {"coordinates":[5.568423,51.960678],"type":"Point"}
}