{
  "type": "Feature",
  "properties": {
    "addr:full":"Amstel 224H Amsterdam Noord-Holland 1017 AJ",
    "addr:housenumber":"224h",
    "addr:postcode":"1017 aj",
    "addr:street":"Amstel",
    "iso:country":"NL",
    "sg:address":"Amstel 224H",
    "sg:city":"Amsterdam",
    "sg:orig_category":"Vertalers",
    "sg:phone":"+31 20 422 3881",
    "sg:postcode":"1017 AJ",
    "sg:province":"Noord-Holland",
    "wof:name":"English Word, The",
    "wof:placetype":"venue"
},
  "geometry": {"coordinates":[4.900674,52.364876],"type":"Point"}
}