{
  "type": "Feature",
  "properties": {
    "addr:full":"Lange Mees 68 Veldhoven Noord-Brabant 5563 PT",
    "addr:housenumber":"68",
    "addr:postcode":"5563 pt",
    "addr:street":"Lange Mees",
    "iso:country":"NL",
    "sg:address":"Lange Mees 68",
    "sg:city":"Veldhoven",
    "sg:orig_category":"Onderhoud And Reparatie Kantoorapparatuur",
    "sg:phone":"+31 900 7006901",
    "sg:postcode":"5563 PT",
    "sg:province":"Noord-Brabant",
    "wof:name":"Repracom Computers",
    "wof:placetype":"venue"
},
  "geometry": {"coordinates":[5.405457,51.41589],"type":"Point"}
}