{
  "type": "Feature",
  "properties": {
    "addr:full":"Bakkenzuigerstraat 84 Almere-Buiten Flevoland 1333 HA",
    "addr:housenumber":"84",
    "addr:postcode":"1333 ha",
    "addr:street":"Bakkenzuigerstraat;Flevoland",
    "iso:country":"NL",
    "sg:address":"Bakkenzuigerstraat 84",
    "sg:city":"Almere-Buiten",
    "sg:orig_category":"Verlichting And Huishoudartikelen",
    "sg:phone":"+31 36 529 0611",
    "sg:postcode":"1333 HA",
    "sg:province":"Flevoland",
    "wof:name":"Bortly Neon",
    "wof:placetype":"venue"
},
  "geometry": {"coordinates":[5.271113,52.40424],"type":"Point"}
}