{
  "type": "Feature",
  "properties": {
    "addr:full":"Metaalstr 8 Wolvega Friesland 8471 AA",
    "addr:housenumber":"8",
    "addr:postcode":"8471 aa",
    "addr:street":"Metaalstr",
    "iso:country":"NL",
    "sg:address":"Metaalstr 8",
    "sg:city":"Wolvega",
    "sg:classifiers":[
        {
            "category":"Manufacturing",
            "subcategory":"Textiles",
            "type":"Manufacturing & Wholesale Goods"
        }
    ],
    "sg:phone":"+31 561 613 344",
    "sg:postcode":"8471 AA",
    "sg:province":"Friesland",
    "sg:tags":[
        "polyester"
    ],
    "wof:name":"Duursma, Fa",
    "wof:placetype":"venue"
},
  "geometry": {"coordinates":[5.988358,52.88076],"type":"Point"}
}