{
  "type": "Feature",
  "properties": {
    "addr:full":"Marktstraat 29 Mierlo Noord-Brabant 5731 HS",
    "addr:housenumber":"29",
    "addr:postcode":"5731 hs",
    "addr:street":"Marktstraat",
    "iso:country":"NL",
    "sg:address":"Marktstraat 29",
    "sg:city":"Mierlo",
    "sg:classifiers":[
        {
            "category":"Shopping",
            "subcategory":"Gifts & Souvenirs",
            "type":"Retail Goods"
        }
    ],
    "sg:phone":"+31 492 663 898",
    "sg:postcode":"5731 HS",
    "sg:province":"Noord-Brabant",
    "sg:tags":[
        "geschenken"
    ],
    "wof:name":"J.M.M.J. V.D. Vleuten",
    "wof:placetype":"venue"
},
  "geometry": {"coordinates":[5.621885,51.445004],"type":"Point"}
}