{
  "type": "Feature",
  "properties": {
    "addr:full":"Prins Hendrikstraat 36 Bodegraven Zuid-Holland 2411 CT",
    "addr:housenumber":"36",
    "addr:postcode":"2411 ct",
    "addr:street":"Prins Hendrikstraat",
    "iso:country":"NL",
    "sg:address":"Prins Hendrikstraat 36",
    "sg:city":"Bodegraven",
    "sg:orig_category":"Hout Gh",
    "sg:phone":"+31 172 616 520",
    "sg:postcode":"2411 CT",
    "sg:province":"Zuid-Holland",
    "wof:name":"Van Tol Houtvezelbedrijf Bv",
    "wof:placetype":"venue"
},
  "geometry": {"coordinates":[4.74608,52.082199],"type":"Point"}
}