{
  "type": "Feature",
  "properties": {
    "addr:full":"Preangerstraat 46 Enschede Overijssel 7541 AJ",
    "addr:housenumber":"46",
    "addr:postcode":"7541 aj",
    "addr:street":"Preangerstraat",
    "iso:country":"NL",
    "sg:address":"Preangerstraat 46",
    "sg:city":"Enschede",
    "sg:orig_category":"Werving And Selectie Van Vast Personeel",
    "sg:phone":"+31 53 480 0540",
    "sg:postcode":"7541 AJ",
    "sg:province":"Overijssel",
    "wof:name":"Quirasse Bv",
    "wof:placetype":"venue"
},
  "geometry": {"coordinates":[6.9073200226,52.2121505737],"type":"Point"}
}