{
  "type": "Feature",
  "properties": {
    "addr:full":"Ambyerstr Z 145 Maastricht Limburg 6225 AE",
    "addr:housenumber":"145",
    "addr:postcode":"6225 ae",
    "iso:country":"NL",
    "sg:address":"Ambyerstr Z 145",
    "sg:city":"Maastricht",
    "sg:orig_category":"Loopbaanbegeleiding",
    "sg:phone":"+31 43 362 8734",
    "sg:postcode":"6225 AE",
    "sg:province":"Limburg",
    "wof:name":"Witteveen, Ieke",
    "wof:placetype":"venue"
},
  "geometry": {"coordinates":[5.730963,50.859753],"type":"Point"}
}