{
  "type": "Feature",
  "properties": {
    "addr:full":"Spoorsingel 55 Delft Zuid-Holland 2613 BH",
    "addr:housenumber":"55",
    "addr:postcode":"2613 bh",
    "addr:street":"Spoorsingel",
    "iso:country":"NL",
    "sg:address":"Spoorsingel 55",
    "sg:city":"Delft",
    "sg:orig_category":"Boekhouders",
    "sg:phone":"+31 15 213 4349",
    "sg:postcode":"2613 BH",
    "sg:province":"Zuid-Holland",
    "wof:name":"Punch Service Buro",
    "wof:placetype":"venue"
},
  "geometry": {"coordinates":[4.352814,52.011669],"type":"Point"}
}