{
  "type": "Feature",
  "properties": {
    "addr:full":"Voorstreek 48 Leeuwarden Friesland 8911 JR",
    "addr:housenumber":"48",
    "addr:postcode":"8911 jr",
    "addr:street":"Voorstreek",
    "iso:country":"NL",
    "sg:address":"Voorstreek 48",
    "sg:city":"Leeuwarden",
    "sg:orig_category":"Boeken En Tijdschriften",
    "sg:phone":"+31 58 212 6744",
    "sg:postcode":"8911 JR",
    "sg:province":"Friesland",
    "wof:name":"Ichtus, Evangelische Boekwinkel",
    "wof:placetype":"venue"
},
  "geometry": {"coordinates":[5.800738,53.20319],"type":"Point"}
}