{
  "type": "Feature",
  "properties": {
    "addr:full":"Eemln 25 Eehoeve Zwolle NL.08 8032 EB",
    "addr:housenumber":"25",
    "addr:postcode":"8032 eb",
    "addr:street":"Eemln",
    "iso:country":"NL",
    "sg:address":"Eemln 25 Eehoeve",
    "sg:city":"Zwolle",
    "sg:orig_category":"Verenigingsgebouwen",
    "sg:phone":"+31 38 454 1658",
    "sg:postcode":"8032 EB",
    "sg:province":"NL.08",
    "wof:name":"Stad En Welzijn, Sticht",
    "wof:placetype":"venue"
},
  "geometry": {"coordinates":[6.101,52.534698],"type":"Point"}
}