{
  "type": "Feature",
  "properties": {
    "addr:full":"Nobelstraat 25 Heerlen Limburg 6411 EK",
    "addr:housenumber":"25",
    "addr:postcode":"6411 ek",
    "addr:street":"Nobelstraat",
    "iso:country":"NL",
    "sg:address":"Nobelstraat 25",
    "sg:city":"Heerlen",
    "sg:orig_category":"Verzekeringen",
    "sg:phone":"+31 45 560 9800",
    "sg:postcode":"6411 EK",
    "sg:province":"Limburg",
    "wof:name":"Sterpolis Schadeverzekeringen Heerlen",
    "wof:placetype":"venue"
},
  "geometry": {"coordinates":[5.979946,50.884956],"type":"Point"}
}