{
  "type": "Feature",
  "properties": {
    "addr:full":"Poppelaar 11 Lage Mierde North Brabant 5094 EX",
    "addr:housenumber":"11",
    "addr:postcode":"5094 ex",
    "addr:street":"Poppelaar",
    "iso:country":"NL",
    "sg:address":"Poppelaar 11",
    "sg:city":"Lage Mierde",
    "sg:orig_category":"Film-, Tv- And Videoproductie",
    "sg:phone":"+31 13 509 2687",
    "sg:postcode":"5094 EX",
    "sg:province":"North Brabant",
    "wof:name":"Melchers Audio-Visuele Techniek",
    "wof:placetype":"venue"
},
  "geometry": {"coordinates":[5.147155,51.407623],"type":"Point"}
}