{
  "type": "Feature",
  "properties": {
    "iso:country":"NL",
    "sg:address":"Ganzenmarkt 16B",
    "sg:city":"Utrecht",
    "sg:orig_category":"Biljartzalen",
    "sg:phone":"+31 30 233 2315",
    "sg:postcode":"3512 GD",
    "sg:province":"Utrecht",
    "wof:name":"Hart Van Utrecht",
    "wof:placetype":"venue"
},
  "geometry": {"coordinates":[5.1192,52.092319],"type":"Point"}
}