{
  "type": "Feature",
  "properties": {
    "addr:full":"Uitgeesterwg 15 Uitgeest North Holland 1911 NK",
    "addr:housenumber":"15",
    "addr:postcode":"1911 nk",
    "addr:street":"Uitgeesterwg",
    "iso:country":"NL",
    "sg:address":"Uitgeesterwg 15",
    "sg:city":"Uitgeest",
    "sg:classifiers":[
        {
            "category":"Sports & Exercise",
            "subcategory":"Stables",
            "type":"Entertainment"
        }
    ],
    "sg:phone":"+31 6 20560603",
    "sg:postcode":"1911 NK",
    "sg:province":"North Holland",
    "sg:tags":[
        "maneges"
    ],
    "wof:name":"Meijerij De",
    "wof:placetype":"venue"
},
  "geometry": {"coordinates":[4.709602,52.540817],"type":"Point"}
}