{
  "type": "Feature",
  "properties": {
    "iso:country":"NL",
    "sg:address":"Veilingwg 48A",
    "sg:city":"Berkel En Rodenrys",
    "sg:orig_category":"Displays, Showcards En Toonmaterialen",
    "sg:phone":"+31 10 511 6237",
    "sg:postcode":"2651 BE",
    "sg:province":"Zuid-Holland",
    "wof:name":"Meuldijk & Van Loon Bv",
    "wof:placetype":"venue"
},
  "geometry": {"coordinates":[4.456662,51.981499],"type":"Point"}
}