{
  "type": "Feature",
  "properties": {
    "addr:full":"Alpacastr 60 Almere Flevoland 1338 HR",
    "addr:housenumber":"60",
    "addr:postcode":"1338 hr",
    "addr:street":"Alpacastr;Flevoland",
    "iso:country":"NL",
    "sg:address":"Alpacastr 60",
    "sg:city":"Almere",
    "sg:orig_category":"Administratie- En Boekhoudkantoren",
    "sg:phone":"+31 36 549 0630",
    "sg:postcode":"1338 HR",
    "sg:province":"Flevoland",
    "wof:name":"Atriam Vof",
    "wof:placetype":"venue"
},
  "geometry": {"coordinates":[5.26843,52.385284],"type":"Point"}
}