{
  "type": "Feature",
  "properties": {
    "addr:full":"Alblasstr 48 Amsterdam North Holland 1079 ZN",
    "addr:housenumber":"48",
    "addr:postcode":"1079 zn",
    "addr:street":"Alblasstr",
    "iso:country":"NL",
    "sg:address":"Alblasstr 48",
    "sg:city":"Amsterdam",
    "sg:orig_category":"Voetbalverenigingen",
    "sg:phone":"+31 20 644 0634",
    "sg:postcode":"1079 ZN",
    "sg:province":"North Holland",
    "wof:name":"Amstelglorie",
    "wof:placetype":"venue"
},
  "geometry": {"coordinates":[4.899032,52.341469],"type":"Point"}
}