{
  "type": "Feature",
  "properties": {
    "addr:full":"Geleenstraat 57 Amsterdam North Holland 1078 LD",
    "addr:housenumber":"57",
    "addr:postcode":"1078 ld",
    "addr:street":"Geleenstraat",
    "iso:country":"NL",
    "sg:address":"Geleenstraat 57",
    "sg:city":"Amsterdam",
    "sg:orig_category":"Vertaal- And Tolkenbureaus",
    "sg:phone":"+31 20 470 5659",
    "sg:postcode":"1078 LD",
    "sg:province":"North Holland",
    "wof:name":"Impulso Spaans-Italiaanse Taalservice",
    "wof:placetype":"venue"
},
  "geometry": {"coordinates":[4.891304,52.343987],"type":"Point"}
}