{
  "type": "Feature",
  "properties": {
    "addr:full":"Herenstr 106A Nieuwegein Utrecht 3431 CB",
    "addr:housenumber":"106a",
    "addr:postcode":"3431 cb",
    "iso:country":"NL",
    "sg:address":"Herenstr 106A",
    "sg:city":"Nieuwegein",
    "sg:orig_category":"Automaterialen En Gereedschappen",
    "sg:phone":"+31 30 604 5042",
    "sg:postcode":"3431 CB",
    "sg:province":"Utrecht",
    "wof:name":"Techno Shop",
    "wof:placetype":"venue"
},
  "geometry": {"coordinates":[5.088618,52.03014],"type":"Point"}
}