{
  "type": "Feature",
  "properties": {
    "addr:full":"Jan Gooskaai 95 Enkhuizen Noord-Holland 1602 GC",
    "addr:housenumber":"95",
    "addr:postcode":"1602 gc",
    "addr:street":"Jan Gooskaai",
    "iso:country":"NL",
    "sg:address":"Jan Gooskaai 95",
    "sg:city":"Enkhuizen",
    "sg:orig_category":"Loodgieterswerk, Verwarming And Sanitaire Installaties",
    "sg:phone":"+31 228 322 308",
    "sg:postcode":"1602 GC",
    "sg:province":"Noord-Holland",
    "wof:name":"Timmerbedrijf Bert Hovenkamp",
    "wof:placetype":"venue"
},
  "geometry": {"coordinates":[5.263932,52.713722],"type":"Point"}
}