{
  "type": "Feature",
  "properties": {
    "addr:full":"Steenvoorde 21 Rotterdam Zuid-Holland 3085 TL",
    "addr:housenumber":"21",
    "addr:postcode":"3085 tl",
    "addr:street":"Steenvoorde",
    "iso:country":"NL",
    "sg:address":"Steenvoorde 21",
    "sg:city":"Rotterdam",
    "sg:orig_category":"Metaalwaren",
    "sg:phone":"+31 6 13881497",
    "sg:postcode":"3085 TL",
    "sg:province":"Zuid-Holland",
    "wof:name":"Dana",
    "wof:placetype":"venue"
},
  "geometry": {"coordinates":[4.493224,51.87233],"type":"Point"}
}