{
  "type": "Feature",
  "properties": {
    "addr:full":"Postbus 4021 Eindhoven Gelderland 5604 EA",
    "addr:housenumber":"4021",
    "addr:postcode":"5604 ea",
    "addr:street":"Postbus;Gelderland",
    "iso:country":"NL",
    "sg:address":"Postbus 4021",
    "sg:city":"Eindhoven",
    "sg:orig_category":"Organisatiebureaus",
    "sg:phone":"+31 40 213 8379",
    "sg:postcode":"5604 EA",
    "sg:province":"Gelderland",
    "sg:website":"http://www.peenonline.nl",
    "wof:name":"Peen! Projecten & Evenementen",
    "wof:placetype":"venue"
},
  "geometry": {"coordinates":[5.4801602364,51.4370613098],"type":"Point"}
}