{
  "type": "Feature",
  "properties": {
    "addr:full":"Kleikoeleweg 106 Landgraaf Limburg 6373 CD",
    "addr:housenumber":"106",
    "addr:postcode":"6373 cd",
    "addr:street":"Kleikoeleweg",
    "iso:country":"NL",
    "sg:address":"Kleikoeleweg 106",
    "sg:city":"Landgraaf",
    "sg:orig_category":"Hoger Onderwijs",
    "sg:phone":"+31 45 531 1993",
    "sg:postcode":"6373 CD",
    "sg:province":"Limburg",
    "wof:name":"Ensaid",
    "wof:placetype":"venue"
},
  "geometry": {"coordinates":[6.022986,50.912739],"type":"Point"}
}