{
  "type": "Feature",
  "properties": {
    "iso:country":"NL",
    "sg:address":"Molbergstg 1",
    "sg:city":"Deventer",
    "sg:orig_category":"Ventilatoren",
    "sg:phone":"+31 575 491 309",
    "sg:postcode":"7418 HD",
    "sg:province":"Overijssel",
    "wof:name":"Martin Ned Bv",
    "wof:placetype":"venue"
},
  "geometry": {"coordinates":[6.199713,52.231773],"type":"Point"}
}