{
  "type": "Feature",
  "properties": {
    "addr:full":"Gravestein 909 Amsterdam Zuidoost Noord-Holland 1103 BH",
    "addr:housenumber":"909",
    "addr:postcode":"zuidoost;1103 bh",
    "addr:street":"Gravestein",
    "iso:country":"NL",
    "sg:address":"Gravestein 909",
    "sg:city":"Amsterdam Zuidoost",
    "sg:orig_category":"Vertaal- And Tolkenbureaus",
    "sg:phone":"+31 20 690 0145",
    "sg:postcode":"1103 BH",
    "sg:province":"Noord-Holland",
    "wof:name":"V.E. Mittelberg",
    "wof:placetype":"venue"
},
  "geometry": {"coordinates":[4.96864,52.324841],"type":"Point"}
}