{
  "type": "Feature",
  "properties": {
    "addr:full":"Gentsestraat 3 Scheveningen South Holland 2587 HK",
    "addr:housenumber":"3",
    "addr:postcode":"2587 hk",
    "addr:street":"Gentsestraat",
    "iso:country":"NL",
    "sg:address":"Gentsestraat 3",
    "sg:city":"Scheveningen",
    "sg:classifiers":[
        {
            "category":"Retail",
            "subcategory":"Photofinishing",
            "type":"Services"
        }
    ],
    "sg:phone":"+31 70 355 6285",
    "sg:postcode":"2587 HK",
    "sg:province":"South Holland",
    "sg:tags":[
        "foto",
        "film"
    ],
    "wof:name":"Fotomaatje Bv",
    "wof:placetype":"venue"
},
  "geometry": {"coordinates":[4.288531,52.111507],"type":"Point"}
}