{
  "type": "Feature",
  "properties": {
    "addr:full":"Glipperwg 96 Heemstede North Holland 2104 AM",
    "addr:housenumber":"96",
    "addr:postcode":"2104",
    "addr:street":"Glipperwg",
    "iso:country":"NL",
    "sg:address":"Glipperwg 96",
    "sg:city":"Heemstede",
    "sg:orig_category":"Beeldende Kunstenaars",
    "sg:phone":"+31 23 547 0951",
    "sg:postcode":"2104 AM",
    "sg:province":"North Holland",
    "wof:name":"Lucia Bezemer",
    "wof:placetype":"venue"
},
  "geometry": {"coordinates":[4.604962,52.32613],"type":"Point"}
}