{
  "type": "Feature",
  "properties": {
    "iso:country":"NL",
    "sg:address":"Dunantstr 1D",
    "sg:city":"Tilburg",
    "sg:orig_category":"Kantoor- En Bedrijfsmeubelen - Fabrieken En Groothandel",
    "sg:phone":"+31 13 543 2462",
    "sg:postcode":"5017 KC",
    "sg:province":"Noord-Brabant",
    "wof:name":"Dd By Kd",
    "wof:placetype":"venue"
},
  "geometry": {"coordinates":[5.0957798958,51.5573883057],"type":"Point"}
}