{
  "type": "Feature",
  "properties": {
    "addr:full":"Noorderlicht 60 Katwijk Zh Zuid-Holland 2221 LW",
    "addr:housenumber":"60",
    "addr:postcode":"2221 lw",
    "addr:street":"Noorderlicht",
    "iso:country":"NL",
    "sg:address":"Noorderlicht 60",
    "sg:city":"Katwijk Zh",
    "sg:orig_category":"Diverse Grafische Activiteiten",
    "sg:phone":"+31 71 403 3496",
    "sg:postcode":"2221 LW",
    "sg:province":"Zuid-Holland",
    "wof:name":"J.L. Van Der Kooi",
    "wof:placetype":"venue"
},
  "geometry": {"coordinates":[4.418661,52.21426],"type":"Point"}
}