{
  "type": "Feature",
  "properties": {
    "addr:full":"Willemstraat 23 Delft Zuid-Holland 2613 DR",
    "addr:housenumber":"23",
    "addr:postcode":"2613 dr",
    "addr:street":"Willemstraat",
    "iso:country":"NL",
    "sg:address":"Willemstraat 23",
    "sg:city":"Delft",
    "sg:orig_category":"Schilderwerk",
    "sg:phone":"+31 15 215 8684",
    "sg:postcode":"2613 DR",
    "sg:province":"Zuid-Holland",
    "wof:name":"Schroder",
    "wof:placetype":"venue"
},
  "geometry": {"coordinates":[4.349782,52.010468],"type":"Point"}
}