{
  "type": "Feature",
  "properties": {
    "addr:full":"Postbus 170 Bodegraven Zuid-Holland 2410 AD",
    "addr:housenumber":"170",
    "addr:postcode":"2410 ad",
    "addr:street":"Postbus",
    "iso:country":"NL",
    "sg:address":"Postbus 170",
    "sg:city":"Bodegraven",
    "sg:orig_category":"Administratie- En Boekhoudkantoren",
    "sg:phone":"+31 172 630 010",
    "sg:postcode":"2410 AD",
    "sg:province":"Zuid-Holland",
    "sg:website":"http://www.hakkenberg.nl",
    "wof:name":"Hakkenberg Accountancy",
    "wof:placetype":"venue"
},
  "geometry": {"coordinates":[4.747547,52.085552],"type":"Point"}
}