{
  "type": "Feature",
  "properties": {
    "addr:full":"Ensahlaan 52 Bilthoven Utrecht 3723 HW",
    "addr:housenumber":"52",
    "addr:postcode":"3723 hw",
    "addr:street":"Ensahlaan",
    "iso:country":"NL",
    "sg:address":"Ensahlaan 52",
    "sg:city":"Bilthoven",
    "sg:orig_category":"Boekenuitgeverijen",
    "sg:phone":"+31 30 225 3047",
    "sg:postcode":"3723 HW",
    "sg:province":"Utrecht",
    "wof:name":"Uitgeverij Bosch En Hoven",
    "wof:placetype":"venue"
},
  "geometry": {"coordinates":[5.208012,52.132],"type":"Point"}
}