{
  "type": "Feature",
  "properties": {
    "addr:full":"Wikke 35 Nykerk Gld Gelderland 3863 DC",
    "addr:housenumber":"35",
    "addr:postcode":"3863",
    "addr:street":"Wikke;Gld Gelderland",
    "iso:country":"NL",
    "sg:address":"Wikke 35",
    "sg:city":"Nykerk Gld",
    "sg:orig_category":"Homeopathie",
    "sg:phone":"+31 33 245 3830",
    "sg:postcode":"3863 DC",
    "sg:province":"Gelderland",
    "wof:name":"Ria Wassink",
    "wof:placetype":"venue"
},
  "geometry": {"coordinates":[5.464432,52.21619],"type":"Point"}
}