{
  "type": "Feature",
  "properties": {
    "addr:full":"W De Nobelaerln 80 Voorburg Zuid-Holland 2273 HN",
    "addr:housenumber":"80",
    "addr:postcode":"2273 hn",
    "addr:street":"W De Nobelaerln",
    "iso:country":"NL",
    "sg:address":"W De Nobelaerln 80",
    "sg:city":"Voorburg",
    "sg:orig_category":"Onderhoudswerken",
    "sg:phone":"+31 70 387 5465",
    "sg:postcode":"2273 HN",
    "sg:province":"Zuid-Holland",
    "wof:name":"Snelders, C J",
    "wof:placetype":"venue"
},
  "geometry": {"coordinates":[4.35977,52.07848],"type":"Point"}
}