{
  "type": "Feature",
  "properties": {
    "addr:full":"Heiweg 6 Geleen Limburg 6161 DA",
    "addr:housenumber":"6",
    "addr:postcode":"6161 da",
    "addr:street":"Heiweg",
    "iso:country":"NL",
    "sg:address":"Heiweg 6",
    "sg:city":"Geleen",
    "sg:orig_category":"Boekhouders",
    "sg:phone":"+31 46 475 7210",
    "sg:postcode":"6161 DA",
    "sg:province":"Limburg",
    "wof:name":"De Coninck Belastingadviezen",
    "wof:placetype":"venue"
},
  "geometry": {"coordinates":[5.815437,50.963234],"type":"Point"}
}