{
  "type": "Feature",
  "properties": {
    "addr:full":"Schuitendiep 86 Groningen Groningen 9711 RG",
    "addr:housenumber":"86",
    "addr:postcode":"9711 rg",
    "addr:street":"Schuitendiep",
    "iso:country":"NL",
    "sg:address":"Schuitendiep 86",
    "sg:city":"Groningen",
    "sg:orig_category":"Organisaties And Verenigingen",
    "sg:phone":"+31 50 312 6035",
    "sg:postcode":"9711 RG",
    "sg:province":"Groningen",
    "wof:name":"A.S.V. Dizkartes",
    "wof:placetype":"venue"
},
  "geometry": {"coordinates":[6.5739150047,53.2174987793],"type":"Point"}
}