{
  "type": "Feature",
  "properties": {
    "addr:full":"Osdorppln 470 Amsterdam Noord-Holland 1068 SZ",
    "addr:housenumber":"470",
    "addr:postcode":"1068 sz",
    "iso:country":"NL",
    "sg:address":"Osdorppln 470",
    "sg:city":"Amsterdam",
    "sg:orig_category":"Warenhuizen",
    "sg:phone":"+31 900 9800",
    "sg:postcode":"1068 SZ",
    "sg:province":"Noord-Holland",
    "sg:website":"http://www.kijkshop.nl",
    "wof:name":"Kijkshop",
    "wof:placetype":"venue"
},
  "geometry": {"coordinates":[4.8029761314,52.3589553833],"type":"Point"}
}