{
  "type": "Feature",
  "properties": {
    "iso:country":"NL",
    "sg:address":"Geest 1",
    "sg:city":"S Gravenhage",
    "sg:orig_category":"Parkeergarages",
    "sg:phone":"+31 70 363 1250",
    "sg:postcode":"2513 VA",
    "sg:province":"Zuid-Holland",
    "wof:name":"Q-Park Bv",
    "wof:placetype":"venue"
},
  "geometry": {"coordinates":[4.30339,52.078442],"type":"Point"}
}