{
  "type": "Feature",
  "properties": {
    "iso:country":"NL",
    "sg:address":"Jan Thomeelaan 1",
    "sg:city":"Delft",
    "sg:orig_category":"Paramedische Behandelingen",
    "sg:phone":"+31 15 256 2428",
    "sg:postcode":"2625 DW",
    "sg:province":"Zuid-Holland",
    "wof:name":"Logopediepraktijk Delft-Zuid",
    "wof:placetype":"venue"
},
  "geometry": {"coordinates":[4.334094,51.995659],"type":"Point"}
}