{
  "type": "Feature",
  "properties": {
    "addr:full":"Dorpsstraat 17 Kloosterhaar Overijssel 7694 AA",
    "addr:housenumber":"17",
    "addr:postcode":"7694 aa",
    "addr:street":"Dorpsstraat",
    "iso:country":"NL",
    "sg:address":"Dorpsstraat 17",
    "sg:city":"Kloosterhaar",
    "sg:orig_category":"Overheidsdiensten",
    "sg:phone":"+31 523 241 273",
    "sg:postcode":"7694 AA",
    "sg:province":"Overijssel",
    "wof:name":"Kloosterhaar",
    "wof:placetype":"venue"
},
  "geometry": {"coordinates":[6.6705121994,52.4954986572],"type":"Point"}
}