{
  "type": "Feature",
  "properties": {
    "iso:country":"NL",
    "sg:address":"W Gertenbachstr 106",
    "sg:city":"Amsterdam Zuidoost",
    "sg:orig_category":"Beveiliging",
    "sg:phone":"+31 20 697 0430",
    "sg:postcode":"1106 WC",
    "sg:province":"Noord-Holland",
    "wof:name":"Praetorian",
    "wof:placetype":"venue"
},
  "geometry": {"coordinates":[4.989886,52.29908],"type":"Point"}
}