{
  "type": "Feature",
  "properties": {
    "addr:full":"Ulgersmawg 137C Groningen Groningen 9731 BR",
    "addr:housenumber":"137c",
    "addr:postcode":"9731 br",
    "addr:street":"Ulgersmawg",
    "iso:country":"NL",
    "sg:address":"Ulgersmawg 137C",
    "sg:city":"Groningen",
    "sg:orig_category":"Offsetdrukkerijen",
    "sg:phone":"+31 50 549 6597",
    "sg:postcode":"9731 BR",
    "sg:province":"Groningen",
    "wof:name":"Tienkamp En Verheij",
    "wof:placetype":"venue"
},
  "geometry": {"coordinates":[6.581998,53.236641],"type":"Point"}
}