{
  "type": "Feature",
  "properties": {
    "iso:country":"NL",
    "sg:address":"Olympiaweg 34B",
    "sg:city":"Rotterdam",
    "sg:orig_category":"Verhuur Bouwmachines",
    "sg:phone":"+31 10 479 4422",
    "sg:postcode":"3077 AL",
    "sg:province":"Zuid-Holland",
    "wof:name":"Altrex Hi Reach Bv",
    "wof:placetype":"venue"
},
  "geometry": {"coordinates":[4.519799,51.895233],"type":"Point"}
}