{
  "type": "Feature",
  "properties": {
    "addr:full":"Nederstr 35 Middelburg Zeeland 4332 AX",
    "addr:housenumber":"35",
    "addr:postcode":"4332 ax",
    "addr:street":"Nederstr",
    "iso:country":"NL",
    "sg:address":"Nederstr 35",
    "sg:city":"Middelburg",
    "sg:classifiers":[
        {
            "category":"Banks & Credit Unions",
            "subcategory":"Investment Brokerage",
            "type":"Services"
        }
    ],
    "sg:phone":"+31 118 639 850",
    "sg:postcode":"4332 AX",
    "sg:province":"Zeeland",
    "sg:tags":[
        "pension"
    ],
    "wof:name":"Bij De Punt",
    "wof:placetype":"venue"
},
  "geometry": {"coordinates":[3.623339,51.501846],"type":"Point"}
}