{
  "type": "Feature",
  "properties": {
    "iso:country":"NL",
    "sg:address":"Dorpsstraat 62",
    "sg:city":"Rosmalen",
    "sg:orig_category":"Banken And Kredietinstellingen",
    "sg:phone":"+31 73 523 0330",
    "sg:postcode":"5241 ED",
    "sg:province":"North Brabant",
    "wof:name":"Ing Bank",
    "wof:placetype":"venue"
},
  "geometry": {"coordinates":[5.362712,51.714859],"type":"Point"}
}