{
  "type": "Feature",
  "properties": {
    "addr:full":"Hooiweg 196 Paterswolde Drenthe 9765 EM",
    "addr:housenumber":"196",
    "addr:postcode":"9765 em",
    "addr:street":"Hooiweg",
    "iso:country":"NL",
    "sg:address":"Hooiweg 196",
    "sg:city":"Paterswolde",
    "sg:orig_category":"Fitnesscentra",
    "sg:phone":"+31 50 309 2204",
    "sg:postcode":"9765 EM",
    "sg:province":"Drenthe",
    "wof:name":"Sporthal De Marsch",
    "wof:placetype":"venue"
},
  "geometry": {"coordinates":[6.55451,53.148743],"type":"Point"}
}