{
  "type": "Feature",
  "properties": {
    "addr:full":"Cazenderstraat 14 Meerssen Limburg 6231 HZ",
    "addr:housenumber":"14",
    "addr:postcode":"6231 hz",
    "addr:street":"Cazenderstraat",
    "iso:country":"NL",
    "sg:address":"Cazenderstraat 14",
    "sg:city":"Meerssen",
    "sg:orig_category":"Fruit And Groenten Gh",
    "sg:phone":"+31 43 365 0281",
    "sg:postcode":"6231 HZ",
    "sg:province":"Limburg",
    "wof:name":"Groente En Fruit Schurkens",
    "wof:placetype":"venue"
},
  "geometry": {"coordinates":[5.752075,50.891029],"type":"Point"}
}