{
  "type": "Feature",
  "properties": {
    "addr:full":"Kruispln 25Q Rotterdam Zuid-Holland 3014 DB",
    "addr:housenumber":"25q",
    "addr:postcode":"3014 db",
    "addr:street":"Kruispln",
    "iso:country":"NL",
    "sg:address":"Kruispln 25Q",
    "sg:city":"Rotterdam",
    "sg:orig_category":"Verenigingen En Stichtingen",
    "sg:phone":"+31 10 206 5959",
    "sg:postcode":"3014 DB",
    "sg:province":"Zuid-Holland",
    "sg:website":"http://www.sbr.nl/",
    "wof:name":"Bouwresearch, Sticht",
    "wof:placetype":"venue"
},
  "geometry": {"coordinates":[4.470628,51.921852],"type":"Point"}
}