{
  "type": "Feature",
  "properties": {
    "iso:country":"NL",
    "sg:address":"Molenwg 27",
    "sg:city":"Oud Vossemeer",
    "sg:classifiers":[
        {
            "category":"Retail",
            "subcategory":"Auto Repair",
            "type":"Services"
        }
    ],
    "sg:phone":"+31 166 672 429",
    "sg:postcode":"4698 AW",
    "sg:province":"Zeeland",
    "sg:tags":[
        "garage"
    ],
    "wof:name":"Vds",
    "wof:placetype":"venue"
},
  "geometry": {"coordinates":[4.197494,51.564709],"type":"Point"}
}