{
  "type": "Feature",
  "properties": {
    "addr:full":"Zuidstraat 134 Westkapelle Zeeland 4361 AK",
    "addr:housenumber":"134",
    "addr:postcode":"4361 ak",
    "addr:street":"Zuidstraat",
    "iso:country":"NL",
    "sg:address":"Zuidstraat 134",
    "sg:city":"Westkapelle",
    "sg:orig_category":"Banken And Kredietinstellingen",
    "sg:phone":"+31 118 587 100",
    "sg:postcode":"4361 AK",
    "sg:province":"Zeeland",
    "wof:name":"Rabobank",
    "wof:placetype":"venue"
},
  "geometry": {"coordinates":[3.43954,51.527924],"type":"Point"}
}