{
  "type": "Feature",
  "properties": {
    "addr:full":"Gondaln 56 Goor Overijssel 7471 LE",
    "addr:housenumber":"56",
    "addr:postcode":"7471 le",
    "addr:street":"Gondaln",
    "iso:country":"NL",
    "sg:address":"Gondaln 56",
    "sg:city":"Goor",
    "sg:orig_category":"Sportverenigingen En Ontspannings- Verenigingen",
    "sg:phone":"+31 547 272 100",
    "sg:postcode":"7471 LE",
    "sg:province":"Overijssel",
    "wof:name":"Goorse Hengelaarsver Ghv",
    "wof:placetype":"venue"
},
  "geometry": {"coordinates":[6.587045,52.234573],"type":"Point"}
}