{
  "type": "Feature",
  "properties": {
    "iso:country":"NL",
    "sg:address":"Pollenstein 9",
    "sg:city":"Ede Gld",
    "sg:orig_category":"Schilders",
    "sg:phone":"+31 6 18150219",
    "sg:postcode":"6714 DC",
    "sg:province":"Gelderland",
    "wof:name":"Steeg, J Van De",
    "wof:placetype":"venue"
},
  "geometry": {"coordinates":[5.64717,52.043705],"type":"Point"}
}