{
  "type": "Feature",
  "properties": {
    "addr:full":"Klipper 156 Oud Beyerland Zuid-Holland 3263 NB",
    "addr:housenumber":"156",
    "addr:postcode":"3263 nb",
    "addr:street":"Klipper",
    "iso:country":"NL",
    "sg:address":"Klipper 156",
    "sg:city":"Oud Beyerland",
    "sg:orig_category":"Loopbaanbegeleiding",
    "sg:phone":"+31 186 627 455",
    "sg:postcode":"3263 NB",
    "sg:province":"Zuid-Holland",
    "wof:name":"Moerkerken-Baljeu, E J",
    "wof:placetype":"venue"
},
  "geometry": {"coordinates":[4.397574,51.825661],"type":"Point"}
}