{
  "type": "Feature",
  "properties": {
    "addr:full":"Geestbrugweg 71 Rijswijk Zh Zuid-Holland 2281 CG",
    "addr:housenumber":"71",
    "addr:postcode":"zh;2281 cg",
    "addr:street":"Geestbrugweg",
    "iso:country":"NL",
    "sg:address":"Geestbrugweg 71",
    "sg:city":"Rijswijk Zh",
    "sg:orig_category":"Artsen And Specialisten",
    "sg:phone":"+31 70 395 0808",
    "sg:postcode":"2281 CG",
    "sg:province":"Zuid-Holland",
    "wof:name":"J.L. Galestien",
    "wof:placetype":"venue"
},
  "geometry": {"coordinates":[4.341444,52.058304],"type":"Point"}
}