{
  "type": "Feature",
  "properties": {
    "addr:full":"Wilhelminastraat 19 Vlagtwedde Groningen 9541 AM",
    "addr:housenumber":"19",
    "addr:postcode":"9541",
    "addr:street":"Wilhelminastraat",
    "iso:country":"NL",
    "sg:address":"Wilhelminastraat 19",
    "sg:city":"Vlagtwedde",
    "sg:orig_category":"Juweliers",
    "sg:phone":"+31 599 313 519",
    "sg:postcode":"9541 AM",
    "sg:province":"Groningen",
    "wof:name":"Juwelier/Horloger J. Kluiter",
    "wof:placetype":"venue"
},
  "geometry": {"coordinates":[7.112775,53.02599],"type":"Point"}
}