{
  "type": "Feature",
  "properties": {
    "iso:country":"NL",
    "sg:address":"De La Reyln 37",
    "sg:city":"Zeist",
    "sg:orig_category":"Keukens",
    "sg:phone":"+31 30 691 2528",
    "sg:postcode":"3707 TK",
    "sg:province":"Utrecht",
    "sg:website":"http://www.natuurkeukens.nl",
    "wof:name":"Bernhagen Natuurkeukens",
    "wof:placetype":"venue"
},
  "geometry": {"coordinates":[5.24387,52.08548],"type":"Point"}
}