{
  "type": "Feature",
  "properties": {
    "addr:full":"Kraaivenstraat 36-03 Tilburg North Brabant 5038 CH",
    "addr:housenumber":"36-03",
    "addr:postcode":"5038",
    "addr:street":"Kraaivenstraat",
    "iso:country":"NL",
    "sg:address":"Kraaivenstraat 36-03",
    "sg:city":"Tilburg",
    "sg:orig_category":"Verhuur Catering-, Feest- En Evenementbenodigdheden",
    "sg:phone":"+31 13 536 1366",
    "sg:postcode":"5038 CH",
    "sg:province":"North Brabant",
    "wof:name":"Magic Play",
    "wof:placetype":"venue"
},
  "geometry": {"coordinates":[5.064558,51.57975],"type":"Point"}
}