{
  "type": "Feature",
  "properties": {
    "addr:full":"Dishoek 22 Koudekerke Zeeland 4371 NR",
    "addr:housenumber":"22",
    "addr:postcode":"4371 nr",
    "addr:street":"Dishoek",
    "iso:country":"NL",
    "sg:address":"Dishoek 22",
    "sg:city":"Koudekerke",
    "sg:classifiers":[
        {
            "category":"Travel",
            "subcategory":"Hotels & Motels",
            "type":"Entertainment"
        }
    ],
    "sg:phone":"+31 118 551 266",
    "sg:postcode":"4371 NR",
    "sg:province":"Zeeland",
    "wof:name":"Badhotel Zeeduin",
    "wof:placetype":"venue"
},
  "geometry": {"coordinates":[3.522595,51.474133],"type":"Point"}
}