{
  "type": "Feature",
  "properties": {
    "addr:full":"Notterwg 3 Wierden Overijssel 7642 LT",
    "addr:housenumber":"3",
    "addr:postcode":"7642 lt",
    "addr:street":"Notterwg",
    "iso:country":"NL",
    "sg:address":"Notterwg 3",
    "sg:city":"Wierden",
    "sg:orig_category":"Adviesbureaus Werktuigbouwkunde",
    "sg:phone":"+31 546 571 896",
    "sg:postcode":"7642 LT",
    "sg:province":"Overijssel",
    "wof:name":"Vos, M J",
    "wof:placetype":"venue"
},
  "geometry": {"coordinates":[6.550619,52.351807],"type":"Point"}
}