{
  "type": "Feature",
  "properties": {
    "addr:full":"Hoofdstr 62 Nieuwolda Groningen 9944 AH",
    "addr:housenumber":"62",
    "addr:postcode":"9944 ah",
    "addr:street":"Hoofdstr",
    "iso:country":"NL",
    "sg:address":"Hoofdstr 62",
    "sg:city":"Nieuwolda",
    "sg:orig_category":"Bejaarden - Verzorgingstehuizen",
    "sg:phone":"+31 596 541 633",
    "sg:postcode":"9944 AH",
    "sg:province":"Groningen",
    "wof:name":"Hamrik, 'T",
    "wof:placetype":"venue"
},
  "geometry": {"coordinates":[6.978559,53.245056],"type":"Point"}
}