{
  "type": "Feature",
  "properties": {
    "iso:country":"NL",
    "sg:address":"Van Nassauweg 11",
    "sg:city":"Krimpen A/D Ijssel",
    "sg:classifiers":[
        {
            "category":"Retail",
            "subcategory":"Storage",
            "type":"Services"
        }
    ],
    "sg:phone":"+31 180 551 644",
    "sg:postcode":"2921 LX",
    "sg:province":"Zuid-Holland",
    "sg:tags":[
        "opslag",
        "bewaring"
    ],
    "wof:name":"Rijnmond Meubeltransport Bv",
    "wof:placetype":"venue"
},
  "geometry": {"coordinates":[4.5786948204,51.9093894958],"type":"Point"}
}