{
  "type": "Feature",
  "properties": {
    "addr:full":"Veluweln 27 Wezep Gelderland 8091 ER",
    "addr:housenumber":"27",
    "addr:postcode":"8091 er",
    "addr:street":"Veluweln",
    "iso:country":"NL",
    "sg:address":"Veluweln 27",
    "sg:city":"Wezep",
    "sg:orig_category":"Projectinrichting",
    "sg:phone":"+31 38 376 3093",
    "sg:postcode":"8091 ER",
    "sg:province":"Gelderland",
    "wof:name":"Blok",
    "wof:placetype":"venue"
},
  "geometry": {"coordinates":[5.99888,52.458267],"type":"Point"}
}