{
  "type": "Feature",
  "properties": {
    "addr:full":"Olympiastaete 1 Geleen Limburg 6162 ED",
    "addr:housenumber":"1",
    "addr:postcode":"6162 ed",
    "addr:street":"Olympiastaete",
    "iso:country":"NL",
    "sg:address":"Olympiastaete 1",
    "sg:city":"Geleen",
    "sg:orig_category":"Bejaardeninstellingen And Serviceflats",
    "sg:phone":"+31 46 478 4848",
    "sg:postcode":"6162 ED",
    "sg:province":"Limburg",
    "wof:name":"Olympiastaete",
    "wof:placetype":"venue"
},
  "geometry": {"coordinates":[5.830274,50.973637],"type":"Point"}
}