{
  "type": "Feature",
  "properties": {
    "addr:full":"Van Geunslaan 2 Harderwijk Gelderland 3843 CZ",
    "addr:housenumber":"2",
    "addr:postcode":"3843",
    "addr:street":"Van Geunslaan;Gelderland",
    "iso:country":"NL",
    "sg:address":"Van Geunslaan 2",
    "sg:city":"Harderwijk",
    "sg:orig_category":"Sportclubs",
    "sg:phone":"+31 341 419 388",
    "sg:postcode":"3843 CZ",
    "sg:province":"Gelderland",
    "wof:name":"Stich Motortoerisme Nederland",
    "wof:placetype":"venue"
},
  "geometry": {"coordinates":[5.636145,52.334957],"type":"Point"}
}