{
  "type": "Feature",
  "properties": {
    "iso:country":"NL",
    "sg:address":"Graafschapsstraat 1",
    "sg:city":"Buren Gld",
    "sg:orig_category":"Boekenuitgeverijen",
    "sg:phone":"+31 344 571 215",
    "sg:postcode":"4116 GE",
    "sg:province":"Gelderland",
    "wof:name":"Spijker Media",
    "wof:placetype":"venue"
},
  "geometry": {"coordinates":[5.331684,51.908451],"type":"Point"}
}