{
  "type": "Feature",
  "properties": {
    "addr:full":"Kalter 65 Haaksbergen Overijssel 7481 LR",
    "addr:housenumber":"65",
    "addr:postcode":"7481 lr",
    "addr:street":"Kalter",
    "iso:country":"NL",
    "sg:address":"Kalter 65",
    "sg:city":"Haaksbergen",
    "sg:classifiers":[
        {
            "category":"Personal",
            "subcategory":"Nail Salon",
            "type":"Services"
        }
    ],
    "sg:phone":"+31 53 572 2907",
    "sg:postcode":"7481 LR",
    "sg:province":"Overijssel",
    "sg:tags":[
        "pedicure"
    ],
    "wof:name":"Ebben, T H M",
    "wof:placetype":"venue"
},
  "geometry": {"coordinates":[6.738825,52.157047],"type":"Point"}
}