{
  "type": "Feature",
  "properties": {
    "addr:full":"Kapteynstr 27 Barneveld Gelderland 3771 CA",
    "addr:housenumber":"27",
    "addr:postcode":"3771 ca",
    "addr:street":"Kapteynstr;Gelderland",
    "iso:country":"NL",
    "sg:address":"Kapteynstr 27",
    "sg:city":"Barneveld",
    "sg:orig_category":"Fotoreportages",
    "sg:phone":"+31 342 415 918",
    "sg:postcode":"3771 CA",
    "sg:province":"Gelderland",
    "wof:name":"Doodeweerd Fotostudio, Van",
    "wof:placetype":"venue"
},
  "geometry": {"coordinates":[5.58649,52.142235],"type":"Point"}
}