{
  "type": "Feature",
  "properties": {
    "iso:country":"NL",
    "sg:address":"Oostvlietweg 26",
    "sg:city":"Leidschendam",
    "sg:orig_category":"Autokeuringen",
    "sg:phone":"+31 70 320 2316",
    "sg:postcode":"2266 GM",
    "sg:province":"Zuid-Holland",
    "wof:name":"Rd Autoservice",
    "wof:placetype":"venue"
},
  "geometry": {"coordinates":[4.41734,52.095989],"type":"Point"}
}