{
  "type": "Feature",
  "properties": {
    "addr:full":"Nijenburg 27 Hoofddorp North Holland 2135 AK",
    "addr:housenumber":"27",
    "addr:postcode":"2135 ak",
    "addr:street":"Nijenburg",
    "iso:country":"NL",
    "sg:address":"Nijenburg 27",
    "sg:city":"Hoofddorp",
    "sg:orig_category":"Organisatiebureaus",
    "sg:phone":"+31 23 562 4341",
    "sg:postcode":"2135 AK",
    "sg:province":"North Holland",
    "wof:name":"Poldergile, Het",
    "wof:placetype":"venue"
},
  "geometry": {"coordinates":[4.6588888168,52.3012084961],"type":"Point"}
}