{
  "type": "Feature",
  "properties": {
    "addr:full":"Haydnstr 24 Eindhoven Noord-Brabant 5654 TB",
    "addr:housenumber":"24",
    "addr:postcode":"5654 tb",
    "addr:street":"Haydnstr",
    "iso:country":"NL",
    "sg:address":"Haydnstr 24",
    "sg:city":"Eindhoven",
    "sg:orig_category":"Autorijscholen",
    "sg:phone":"+31 40 252 7674",
    "sg:postcode":"5654 TB",
    "sg:province":"Noord-Brabant",
    "wof:name":"Grootel, Ties Van",
    "wof:placetype":"venue"
},
  "geometry": {"coordinates":[5.460841,51.425659],"type":"Point"}
}