{
  "type": "Feature",
  "properties": {
    "addr:full":"Hoofdstraat 27 Ovezande Zeeland 4441 AA",
    "addr:housenumber":"27",
    "addr:postcode":"4441 aa",
    "addr:street":"Hoofdstraat",
    "iso:country":"NL",
    "sg:address":"Hoofdstraat 27",
    "sg:city":"Ovezande",
    "sg:orig_category":"Kappers",
    "sg:phone":"+31 113 655 732",
    "sg:postcode":"4441 AA",
    "sg:province":"Zeeland",
    "wof:name":"Haircare",
    "wof:placetype":"venue"
},
  "geometry": {"coordinates":[3.8224649429,51.428478241],"type":"Point"}
}