{
  "type": "Feature",
  "properties": {
    "addr:full":"Kantelenweg 15 Oostvoorne South Holland 3233 RA",
    "addr:housenumber":"15",
    "addr:postcode":"3233 ra",
    "addr:street":"Kantelenweg",
    "iso:country":"NL",
    "sg:address":"Kantelenweg 15",
    "sg:city":"Oostvoorne",
    "sg:orig_category":"Paramedische Behandelingen",
    "sg:phone":"+31 181 484 096",
    "sg:postcode":"3233 RA",
    "sg:province":"South Holland",
    "wof:name":"Logopediepraktijk Westvoorne",
    "wof:placetype":"venue"
},
  "geometry": {"coordinates":[4.106735,51.914787],"type":"Point"}
}