{
  "type": "Feature",
  "properties": {
    "iso:country":"NL",
    "sg:address":"Poortweg 22",
    "sg:city":"Bergen Op Zoom",
    "sg:orig_category":"Houtverwerking",
    "sg:phone":"+31 164 265 839",
    "sg:postcode":"4613 BW",
    "sg:province":"Noord-Brabant",
    "wof:name":"Timmerbedrijf Musters",
    "wof:placetype":"venue"
},
  "geometry": {"coordinates":[4.278114,51.502361],"type":"Point"}
}