{
  "type": "Feature",
  "properties": {
    "iso:country":"NL",
    "sg:address":"Vd Lubbehof 17",
    "sg:city":"Leiden",
    "sg:orig_category":"Vertaalbureaus",
    "sg:phone":"+31 71 514 2464",
    "sg:postcode":"2312 CJ",
    "sg:province":"Zuid-Holland",
    "wof:name":"Smeets-Sirakova, Drs N A",
    "wof:placetype":"venue"
},
  "geometry": {"coordinates":[4.497214,52.157791],"type":"Point"}
}