{
  "type": "Feature",
  "properties": {
    "addr:full":"Siriusstraat 25 Tilburg Noord-Brabant 5015 BT",
    "addr:housenumber":"25",
    "addr:postcode":"5015 bt",
    "addr:street":"Siriusstraat",
    "iso:country":"NL",
    "sg:address":"Siriusstraat 25",
    "sg:city":"Tilburg",
    "sg:orig_category":"Kantoorapparatuur Gh",
    "sg:phone":"+31 13 460 9460",
    "sg:postcode":"5015 BT",
    "sg:province":"Noord-Brabant",
    "wof:name":"Hutten Bv",
    "wof:placetype":"venue"
},
  "geometry": {"coordinates":[5.1127958298,51.5773010254],"type":"Point"}
}