{
  "type": "Feature",
  "properties": {
    "iso:country":"NL",
    "sg:address":"Oostplein 425",
    "sg:city":"Rotterdam",
    "sg:orig_category":"Boekhouders",
    "sg:phone":"+31 10 212 0404",
    "sg:postcode":"3061 CH",
    "sg:province":"Zuid-Holland",
    "wof:name":"Kantoor Van Houwelingen Bv",
    "wof:placetype":"venue"
},
  "geometry": {"coordinates":[4.497847,51.923279],"type":"Point"}
}