{
  "type": "Feature",
  "properties": {
    "addr:full":"Omkromte 10 Joure Friesland 8501 CR",
    "addr:housenumber":"10",
    "addr:postcode":"8501 cr",
    "addr:street":"Omkromte",
    "iso:country":"NL",
    "sg:address":"Omkromte 10",
    "sg:city":"Joure",
    "sg:orig_category":"Adviesbureaus Economie",
    "sg:phone":"+31 513 413 078",
    "sg:postcode":"8501 CR",
    "sg:province":"Friesland",
    "wof:name":"Diever",
    "wof:placetype":"venue"
},
  "geometry": {"coordinates":[5.7854380608,52.9671974182],"type":"Point"}
}