{
  "type": "Feature",
  "properties": {
    "addr:full":"S V Capelwg 31A Noorden California 2431 AC",
    "addr:housenumber":"31a",
    "addr:postcode":"2431 ac",
    "addr:street":"Capelwg",
    "iso:country":"NL",
    "sg:address":"S V Capelwg 31A",
    "sg:city":"Noorden",
    "sg:orig_category":"Metselwerken",
    "sg:phone":"+31 172 409 736",
    "sg:postcode":"2431 AC",
    "sg:province":"California",
    "wof:name":"Koert Pietersen, Van",
    "wof:placetype":"venue"
},
  "geometry": {"coordinates":[-120.36385300000001,39.320374],"type":"Point"}
}