{
  "type": "Feature",
  "properties": {
    "addr:full":"Keienbergwg 62 Amsterdam Zuidoost Noord-Holland 1101 GC",
    "addr:housenumber":"62",
    "addr:postcode":"zuidoost;1101 gc",
    "addr:street":"Keienbergwg",
    "iso:country":"NL",
    "sg:address":"Keienbergwg 62",
    "sg:city":"Amsterdam Zuidoost",
    "sg:orig_category":"Sanitaire Artikelen",
    "sg:phone":"+31 20 691 4348",
    "sg:postcode":"1101 GC",
    "sg:province":"Noord-Holland",
    "wof:name":"Volkers",
    "wof:placetype":"venue"
},
  "geometry": {"coordinates":[4.934176,52.306587],"type":"Point"}
}