{
  "type": "Feature",
  "properties": {
    "addr:full":"Wikkeveld 7 Bavel Noord-Brabant 4854 MH",
    "addr:housenumber":"7",
    "addr:postcode":"4854 mh",
    "addr:street":"Wikkeveld",
    "iso:country":"NL",
    "sg:address":"Wikkeveld 7",
    "sg:city":"Bavel",
    "sg:orig_category":"Glaszetten",
    "sg:phone":"+31 161 434 581",
    "sg:postcode":"4854 MH",
    "sg:province":"Noord-Brabant",
    "wof:name":"Bas Timmers Montagebedrijf",
    "wof:placetype":"venue"
},
  "geometry": {"coordinates":[4.830617,51.572929],"type":"Point"}
}