{
  "type": "Feature",
  "properties": {
    "addr:full":"Bankastr 12 S Gravenhage Zuid-Holland 2585 EN",
    "addr:housenumber":"12;gravenhage",
    "addr:postcode":"2585 en",
    "addr:street":"Bankastr;S",
    "iso:country":"NL",
    "sg:address":"Bankastr 12",
    "sg:city":"S Gravenhage",
    "sg:orig_category":"Wijnkoperijen En -Groothandel",
    "sg:phone":"+31 70 350 3980",
    "sg:postcode":"2585 EN",
    "sg:province":"Zuid-Holland",
    "sg:website":"http://www.gransjean.nl",
    "wof:name":"Gransjean Wijnen & Delicatessen",
    "wof:placetype":"venue"
},
  "geometry": {"coordinates":[4.2977700233,52.0947990417],"type":"Point"}
}