{
  "type": "Feature",
  "properties": {
    "addr:full":"Achterdorp 21 Dirksland Zuid-Holland 3247 BA",
    "addr:housenumber":"21",
    "addr:postcode":"3247 ba",
    "addr:street":"Achterdorp",
    "iso:country":"NL",
    "sg:address":"Achterdorp 21",
    "sg:city":"Dirksland",
    "sg:orig_category":"Meubelzaken, Woning- And Keukeninrichting",
    "sg:phone":"+31 187 609 080",
    "sg:postcode":"3247 BA",
    "sg:province":"Zuid-Holland",
    "wof:name":"Kraai",
    "wof:placetype":"venue"
},
  "geometry": {"coordinates":[4.105012,51.748753],"type":"Point"}
}