{
  "type": "Feature",
  "properties": {
    "addr:full":"Lichtenvoordsestraatweg 3 Aalten Gelderland 7121 AA",
    "addr:housenumber":"3",
    "addr:postcode":"7121 aa",
    "addr:street":"Lichtenvoordsestraatweg;Gelderland",
    "iso:country":"NL",
    "sg:address":"Lichtenvoordsestraatweg 3",
    "sg:city":"Aalten",
    "sg:orig_category":"Werving And Selectie Van Tijdelijk Personeel And Uitzendkantoren",
    "sg:phone":"+31 543 477 440",
    "sg:postcode":"7121 AA",
    "sg:province":"Gelderland",
    "wof:name":"Start",
    "wof:placetype":"venue"
},
  "geometry": {"coordinates":[6.5808281898,51.9295845032],"type":"Point"}
}