{
  "type": "Feature",
  "properties": {
    "addr:full":"Kinkerstraat 331 Amsterdam Noord-Holland 1053 EW",
    "addr:housenumber":"331",
    "addr:postcode":"1053 ew",
    "addr:street":"Kinkerstraat",
    "iso:country":"NL",
    "sg:address":"Kinkerstraat 331",
    "sg:city":"Amsterdam",
    "sg:orig_category":"Apothekers",
    "sg:phone":"+31 20 618 0585",
    "sg:postcode":"1053 EW",
    "sg:province":"Noord-Holland",
    "wof:name":"Kinker Apotheek",
    "wof:placetype":"venue"
},
  "geometry": {"coordinates":[4.861959,52.364483],"type":"Point"}
}