{
  "type": "Feature",
  "properties": {
    "addr:full":"Brouwerijstraat 65 Kapellebrug Zeeland 4565 EL",
    "addr:housenumber":"65",
    "addr:postcode":"4565 el",
    "addr:street":"Brouwerijstraat",
    "iso:country":"NL",
    "sg:address":"Brouwerijstraat 65",
    "sg:city":"Kapellebrug",
    "sg:orig_category":"Fruit And Groenten Gh",
    "sg:phone":"+31 114 312 469",
    "sg:postcode":"4565 EL",
    "sg:province":"Zeeland",
    "wof:name":"Gebroeders Dobbelaer Bv",
    "wof:placetype":"venue"
},
  "geometry": {"coordinates":[4.058538,51.258186],"type":"Point"}
}