{
  "type": "Feature",
  "properties": {
    "addr:full":"Hoogeveenenwg 19F Nieuwerkerk Yssel South Holland 2913 LV",
    "addr:housenumber":"19f",
    "addr:postcode":"2913",
    "iso:country":"NL",
    "sg:address":"Hoogeveenenwg 19F",
    "sg:city":"Nieuwerkerk Yssel",
    "sg:orig_category":"Kantoor- En Bedrijfsmeubelen",
    "sg:phone":"+31 180 330 877",
    "sg:postcode":"2913 LV",
    "sg:province":"South Holland",
    "sg:website":"http://www.dehonbv.nl",
    "wof:name":"Dehon Bv",
    "wof:placetype":"venue"
},
  "geometry": {"coordinates":[4.611550808,51.9783439636],"type":"Point"}
}