{
  "type": "Feature",
  "properties": {
    "addr:full":"Postbus 108 Wyk By Duurstede Utrecht 3960 BC",
    "addr:housenumber":"108",
    "addr:postcode":"3960 bc",
    "addr:street":"Postbus;Duurstede",
    "iso:country":"NL",
    "sg:address":"Postbus 108",
    "sg:city":"Wyk By Duurstede",
    "sg:orig_category":"Webdesign Bureaus",
    "sg:phone":"+31 343 522 724",
    "sg:postcode":"3960 BC",
    "sg:province":"Utrecht",
    "wof:name":"A & P",
    "wof:placetype":"venue"
},
  "geometry": {"coordinates":[5.3452501297,51.972820282],"type":"Point"}
}