{
  "type": "Feature",
  "properties": {
    "addr:full":"Westerblokker 21 Blokker North Holland 1695 AA",
    "addr:housenumber":"21",
    "addr:postcode":"1695 aa",
    "addr:street":"Westerblokker;Holland",
    "iso:country":"NL",
    "sg:address":"Westerblokker 21",
    "sg:city":"Blokker",
    "sg:orig_category":"Autoschade- Herstelbedrijven",
    "sg:phone":"+31 229 262 797",
    "sg:postcode":"1695 AA",
    "sg:province":"North Holland",
    "wof:name":"Custom Body + Paint",
    "wof:placetype":"venue"
},
  "geometry": {"coordinates":[5.101551,52.664356],"type":"Point"}
}