{
  "type": "Feature",
  "properties": {
    "addr:full":"Veilingstraat 14 Elshout North Brabant 5154 AA",
    "addr:housenumber":"14",
    "addr:postcode":"5154 aa",
    "addr:street":"Veilingstraat",
    "iso:country":"NL",
    "sg:address":"Veilingstraat 14",
    "sg:city":"Elshout",
    "sg:orig_category":"Koffers And Tassen Fab",
    "sg:phone":"+31 416 379 560",
    "sg:postcode":"5154 AA",
    "sg:province":"North Brabant",
    "wof:name":"J.V.D. Lederwaren Vof",
    "wof:placetype":"venue"
},
  "geometry": {"coordinates":[5.1416,51.695641],"type":"Point"}
}