{
  "type": "Feature",
  "properties": {
    "iso:country":"NL",
    "sg:address":"Lindestraat 27",
    "sg:city":"Sint Willebrord",
    "sg:orig_category":"Bloemen And Planten Gh",
    "sg:phone":"+31 165 387 596",
    "sg:postcode":"4711 RM",
    "sg:province":"Noord-Brabant",
    "wof:name":"Vof Kianco",
    "wof:placetype":"venue"
},
  "geometry": {"coordinates":[4.577634,51.550945],"type":"Point"}
}