{
  "type": "Feature",
  "properties": {
    "addr:full":"H Ronnerpln 13Hs Amsterdam Noord-Holland 1073 KT",
    "addr:postcode":"1073 kt",
    "iso:country":"NL",
    "sg:address":"H Ronnerpln 13Hs",
    "sg:city":"Amsterdam",
    "sg:orig_category":"Geluidsinstallaties - Verhuur",
    "sg:phone":"+31 6 53222179",
    "sg:postcode":"1073 KT",
    "sg:province":"Noord-Holland",
    "sg:website":"http://www.d-s-a.nl",
    "wof:name":"Disco-Service-Amsterdam",
    "wof:placetype":"venue"
},
  "geometry": {"coordinates":[4.901428,52.349529],"type":"Point"}
}