{
  "type": "Feature",
  "properties": {
    "addr:full":"Ubbo Emmiussingel 27 Groningen Groningen 9711 BE",
    "addr:housenumber":"27",
    "addr:postcode":"9711",
    "addr:street":"Ubbo Emmiussingel",
    "iso:country":"NL",
    "sg:address":"Ubbo Emmiussingel 27",
    "sg:city":"Groningen",
    "sg:orig_category":"Werving And Selectie Van Vast Personeel",
    "sg:phone":"+31 50 311 5882",
    "sg:postcode":"9711 BE",
    "sg:province":"Groningen",
    "wof:name":"Hunter Select Bv",
    "wof:placetype":"venue"
},
  "geometry": {"coordinates":[6.5670619011,53.2130393982],"type":"Point"}
}