{
  "type": "Feature",
  "properties": {
    "addr:full":"De Boeleln 1105 Amsterdam Noord-Holland 1081 HV",
    "addr:housenumber":"1105",
    "addr:postcode":"1081 hv",
    "iso:country":"NL",
    "sg:address":"De Boeleln 1105",
    "sg:city":"Amsterdam",
    "sg:orig_category":"Juridische Adviseurs",
    "sg:phone":"+31 20 444 6331",
    "sg:postcode":"1081 HV",
    "sg:province":"Noord-Holland",
    "wof:name":"Rechtshulp Vu",
    "wof:placetype":"venue"
},
  "geometry": {"coordinates":[4.84344,52.330189],"type":"Point"}
}