{
  "type": "Feature",
  "properties": {
    "iso:country":"NL",
    "sg:address":"Zoutmanstr 23M",
    "sg:city":"S Gravenhage",
    "sg:orig_category":"Onroerende Goederen",
    "sg:phone":"+31 70 427 8770",
    "sg:postcode":"2518 GL",
    "sg:province":"South Holland",
    "wof:name":"Dido Vof",
    "wof:placetype":"venue"
},
  "geometry": {"coordinates":[4.29348,52.080318],"type":"Point"}
}