{
  "type": "Feature",
  "properties": {
    "addr:full":"Heezerweg 99 Eindhoven Noord-Brabant 5614 HC",
    "addr:housenumber":"99",
    "addr:postcode":"5614 hc",
    "addr:street":"Heezerweg",
    "iso:country":"NL",
    "sg:address":"Heezerweg 99",
    "sg:city":"Eindhoven",
    "sg:classifiers":[
        {
            "category":"Fast Food",
            "type":"Food & Drink"
        }
    ],
    "sg:phone":"+31 40 211 4826",
    "sg:postcode":"5614 HC",
    "sg:province":"Noord-Brabant",
    "sg:tags":[
        "afhaal",
        "restaurant"
    ],
    "wof:name":"Van Der Special",
    "wof:placetype":"venue"
},
  "geometry": {"coordinates":[5.492235,51.427311],"type":"Point"}
}