{
  "type": "Feature",
  "properties": {
    "addr:full":"Dr Rauppstr 18 Bergeyk Noord-Brabant 5571 CG",
    "addr:housenumber":"18",
    "addr:postcode":"5571 cg",
    "addr:street":"Bergeyk",
    "iso:country":"NL",
    "sg:address":"Dr Rauppstr 18",
    "sg:city":"Bergeyk",
    "sg:orig_category":"Administratie- En Boekhoudkantoren",
    "sg:phone":"+31 497 550 320",
    "sg:postcode":"5571 CG",
    "sg:province":"Noord-Brabant",
    "wof:name":"Kuijper",
    "wof:placetype":"venue"
},
  "geometry": {"coordinates":[5.359559,51.319996],"type":"Point"}
}