{
  "type": "Feature",
  "properties": {
    "addr:full":"Van 'T Hoffstraat 10 Leiden South Holland 2313 SP",
    "addr:housenumber":"10",
    "addr:postcode":"2313 sp",
    "addr:street":"Van ' T Hoffstraat",
    "iso:country":"NL",
    "sg:address":"Van 'T Hoffstraat 10",
    "sg:city":"Leiden",
    "sg:orig_category":"Artiestenbureaus",
    "sg:phone":"+31 71 514 5090",
    "sg:postcode":"2313 SP",
    "sg:province":"South Holland",
    "wof:name":"Happy Hour",
    "wof:placetype":"venue"
},
  "geometry": {"coordinates":[4.496493,52.149471],"type":"Point"}
}