{
  "type": "Feature",
  "properties": {
    "addr:full":"Floris Burgwal 208 Capelle A/D Ijssel Zuid-Holland 2907 PL",
    "addr:housenumber":"208;a / d",
    "addr:postcode":"2907 pl",
    "addr:street":"Floris Burgwal",
    "iso:country":"NL",
    "sg:address":"Floris Burgwal 208",
    "sg:city":"Capelle A/D Ijssel",
    "sg:orig_category":"Artsen And Specialisten",
    "sg:phone":"+31 10 458 3611",
    "sg:postcode":"2907 PL",
    "sg:province":"Zuid-Holland",
    "wof:name":"J. Hordijk",
    "wof:placetype":"venue"
},
  "geometry": {"coordinates":[4.580085,51.949974],"type":"Point"}
}