{
  "type": "Feature",
  "properties": {
    "addr:full":"Engelandwg 6 Bodegraven Zuid-Holland 2411 NS",
    "addr:housenumber":"6",
    "addr:postcode":"2411 ns",
    "addr:street":"Engelandwg",
    "iso:country":"NL",
    "sg:address":"Engelandwg 6",
    "sg:city":"Bodegraven",
    "sg:orig_category":"Kaasgroothandel",
    "sg:phone":"+31 172 619 335",
    "sg:postcode":"2411 NS",
    "sg:province":"Zuid-Holland",
    "wof:name":"Bakker Bv, W",
    "wof:placetype":"venue"
},
  "geometry": {"coordinates":[4.751830101,52.0702705383],"type":"Point"}
}