{
  "type": "Feature",
  "properties": {
    "addr:full":"Dykwg 21 Naaldwyk South Holland 2671 GA",
    "addr:housenumber":"21",
    "addr:postcode":"2671 ga",
    "addr:street":"Dykwg",
    "iso:country":"NL",
    "sg:address":"Dykwg 21",
    "sg:city":"Naaldwyk",
    "sg:orig_category":"Begrafenisverzorging",
    "sg:phone":"+31 174 623 456",
    "sg:postcode":"2671 GA",
    "sg:province":"South Holland",
    "wof:name":"Horizon",
    "wof:placetype":"venue"
},
  "geometry": {"coordinates":[4.205249,51.991398],"type":"Point"}
}