{
  "type": "Feature",
  "properties": {
    "addr:full":"Nieuweweg 9 Hei En Boeicop Zuid-Holland 4126 RN",
    "addr:housenumber":"9",
    "addr:postcode":"4126 rn",
    "addr:street":"Nieuweweg",
    "iso:country":"NL",
    "sg:address":"Nieuweweg 9",
    "sg:city":"Hei En Boeicop",
    "sg:orig_category":"Overheidsdiensten",
    "sg:phone":"+31 347 341 979",
    "sg:postcode":"4126 RN",
    "sg:province":"Zuid-Holland",
    "wof:name":"Internos",
    "wof:placetype":"venue"
},
  "geometry": {"coordinates":[5.0733318329,51.9498291016],"type":"Point"}
}