{
  "type": "Feature",
  "properties": {
    "addr:full":"Groenestraat 24 Lienden Gelderland 4033 CR",
    "addr:housenumber":"24",
    "addr:postcode":"4033 cr",
    "addr:street":"Groenestraat;Gelderland",
    "iso:country":"NL",
    "sg:address":"Groenestraat 24",
    "sg:city":"Lienden",
    "sg:orig_category":"Film-, Tv- And Videoproductie",
    "sg:phone":"+31 344 601 748",
    "sg:postcode":"4033 CR",
    "sg:province":"Gelderland",
    "wof:name":"Katowee Holland Bv",
    "wof:placetype":"venue"
},
  "geometry": {"coordinates":[5.505763,51.953808],"type":"Point"}
}