{
  "type": "Feature",
  "properties": {
    "addr:full":"Heyermansln 49 Uithoorn North Holland 1422 GV",
    "addr:housenumber":"49",
    "addr:postcode":"1422 gv",
    "addr:street":"Heyermansln",
    "iso:country":"NL",
    "sg:address":"Heyermansln 49",
    "sg:city":"Uithoorn",
    "sg:orig_category":"Banken",
    "sg:phone":"+31 297 513 737",
    "sg:postcode":"1422 GV",
    "sg:province":"North Holland",
    "sg:website":"http://www.rabobank.nl",
    "wof:name":"Rabobank",
    "wof:placetype":"venue"
},
  "geometry": {"coordinates":[4.828947,52.233421],"type":"Point"}
}