{
  "type": "Feature",
  "properties": {
    "addr:full":"Kl Geertekerkhof 2A Bis Utrecht Utrecht 3511 XG",
    "addr:housenumber":"2a bis",
    "addr:postcode":"3511 xg",
    "addr:street":"Geertekerkhof",
    "iso:country":"NL",
    "sg:address":"Kl Geertekerkhof 2A Bis",
    "sg:city":"Utrecht",
    "sg:orig_category":"Autorijscholen",
    "sg:phone":"+31 30 231 7020",
    "sg:postcode":"3511 XG",
    "sg:province":"Utrecht",
    "wof:name":"Ham, Autorijschool H V/D",
    "wof:placetype":"venue"
},
  "geometry": {"coordinates":[5.115405,52.088932],"type":"Point"}
}