{
  "type": "Feature",
  "properties": {
    "addr:full":"Duizelstr 22 Tilburg North Brabant 5043 ED",
    "addr:housenumber":"22",
    "addr:postcode":"5043 ed",
    "addr:street":"Duizelstr",
    "iso:country":"NL",
    "sg:address":"Duizelstr 22",
    "sg:city":"Tilburg",
    "sg:orig_category":"Webdesign Bureaus",
    "sg:phone":"+31 13 570 3182",
    "sg:postcode":"5043 ED",
    "sg:province":"North Brabant",
    "sg:website":"http://www.xirus.nl",
    "wof:name":"Xirus",
    "wof:placetype":"venue"
},
  "geometry": {"coordinates":[5.0102148056,51.5779914856],"type":"Point"}
}