{
  "type": "Feature",
  "properties": {
    "addr:full":"Graaf Jansdijk B 42 Westdorpe Zeeland 4554 CB",
    "addr:housenumber":"b 42",
    "addr:postcode":"4554 cb",
    "addr:street":"Graaf Jansdijk",
    "iso:country":"NL",
    "sg:address":"Graaf Jansdijk B 42",
    "sg:city":"Westdorpe",
    "sg:classifiers":[
        {
            "category":"Shopping",
            "subcategory":"Gifts & Souvenirs",
            "type":"Retail Goods"
        }
    ],
    "sg:phone":"+31 115 451 454",
    "sg:postcode":"4554 CB",
    "sg:province":"Zeeland",
    "sg:tags":[
        "geschenken"
    ],
    "wof:name":"Wereldwinkel",
    "wof:placetype":"venue"
},
  "geometry": {"coordinates":[3.833854,51.234196],"type":"Point"}
}