{
  "type": "Feature",
  "properties": {
    "addr:full":"Scheldestraat 40 Winschoten Groningen 9673 CG",
    "addr:housenumber":"40",
    "addr:postcode":"9673 cg",
    "addr:street":"Scheldestraat",
    "iso:country":"NL",
    "sg:address":"Scheldestraat 40",
    "sg:city":"Winschoten",
    "sg:orig_category":"Overheidsdiensten",
    "sg:phone":"+31 597 457 777",
    "sg:postcode":"9673 CG",
    "sg:province":"Groningen",
    "wof:name":"Gak Groep Winschoten",
    "wof:placetype":"venue"
},
  "geometry": {"coordinates":[7.0317540169,53.1349983215],"type":"Point"}
}