{
  "type": "Feature",
  "properties": {
    "addr:full":"Singel 457/A/1 Amsterdam North Holland 1012 WP",
    "addr:housenumber":"457 / a / 1",
    "addr:postcode":"1012 wp",
    "addr:street":"Singel",
    "iso:country":"NL",
    "sg:address":"Singel 457/A/1",
    "sg:city":"Amsterdam",
    "sg:orig_category":"Warenhuizen",
    "sg:phone":"+31 20 422 8988",
    "sg:postcode":"1012 WP",
    "sg:province":"North Holland",
    "wof:name":"Hema",
    "wof:placetype":"venue"
},
  "geometry": {"coordinates":[4.8931951523,52.3731193542],"type":"Point"}
}