{
  "type": "Feature",
  "properties": {
    "addr:full":"Osdorppln 673 Amsterdam Noord-Holland 1068 TC",
    "addr:housenumber":"673",
    "addr:postcode":"1068 tc",
    "iso:country":"NL",
    "sg:address":"Osdorppln 673",
    "sg:city":"Amsterdam",
    "sg:orig_category":"Juweliers",
    "sg:phone":"+31 20 619 5405",
    "sg:postcode":"1068 TC",
    "sg:province":"Noord-Holland",
    "wof:name":"Istanbul",
    "wof:placetype":"venue"
},
  "geometry": {"coordinates":[4.804017,52.359047],"type":"Point"}
}