{
  "type": "Feature",
  "properties": {
    "addr:full":"Sparrenhof 64 Made Noord-Brabant 4921 DS",
    "addr:housenumber":"64",
    "addr:postcode":"4921 ds",
    "addr:street":"Sparrenhof",
    "iso:country":"NL",
    "sg:address":"Sparrenhof 64",
    "sg:city":"Made",
    "sg:orig_category":"Adviesbureaus Bouwkunde",
    "sg:phone":"+31 162 670 280",
    "sg:postcode":"4921 DS",
    "sg:province":"Noord-Brabant",
    "wof:name":"Tempo",
    "wof:placetype":"venue"
},
  "geometry": {"coordinates":[-120.06399500000001,36.962055],"type":"Point"}
}