{
  "type": "Feature",
  "properties": {
    "iso:country":"NL",
    "sg:address":"Aldebaranstr 49",
    "sg:city":"Groningen",
    "sg:orig_category":"Elektronica - Ontwikkeling En Groothandel",
    "sg:phone":"+31 50 577 8415",
    "sg:postcode":"9742 LH",
    "sg:province":"Groningen",
    "wof:name":"Drijver",
    "wof:placetype":"venue"
},
  "geometry": {"coordinates":[6.540607,53.229584],"type":"Point"}
}