{
  "type": "Feature",
  "properties": {
    "addr:full":"Schiedamsedijk 40 Vlaardingen Zuid-Holland 3134 KK",
    "addr:housenumber":"40",
    "addr:postcode":"3134 kk",
    "addr:street":"Schiedamsedijk",
    "iso:country":"NL",
    "sg:address":"Schiedamsedijk 40",
    "sg:city":"Vlaardingen",
    "sg:orig_category":"Papier- And Kartonverpakkingen Fab",
    "sg:phone":"+31 10 234 0975",
    "sg:postcode":"3134 KK",
    "sg:province":"Zuid-Holland",
    "wof:name":"Delney International Product Centre",
    "wof:placetype":"venue"
},
  "geometry": {"coordinates":[4.369544,51.905014],"type":"Point"}
}