{
  "type": "Feature",
  "properties": {
    "addr:full":"Fontainebleaulaan 15 Eindhoven North Brabant 5627 TM",
    "addr:housenumber":"15",
    "addr:postcode":"5627 tm",
    "addr:street":"Fontainebleaulaan",
    "iso:country":"NL",
    "sg:address":"Fontainebleaulaan 15",
    "sg:city":"Eindhoven",
    "sg:orig_category":"Meubels And Huishoudapparatuur Gh",
    "sg:phone":"+31 40 241 2328",
    "sg:postcode":"5627 TM",
    "sg:province":"North Brabant",
    "wof:name":"Promode",
    "wof:placetype":"venue"
},
  "geometry": {"coordinates":[5.439647,51.490597],"type":"Point"}
}