{
  "type": "Feature",
  "properties": {
    "addr:full":"Alddijk 14 Beetgum Provincie Friesland 9044 MN",
    "addr:housenumber":"14;9044",
    "addr:postcode":"mn",
    "addr:street":"Alddijk;Provincie Friesland",
    "iso:country":"NL",
    "sg:address":"Alddijk 14",
    "sg:city":"Beetgum",
    "sg:orig_category":"Goederenvervoer Over De Weg",
    "sg:phone":"+31 58 253 1381",
    "sg:postcode":"9044 MN",
    "sg:province":"Provincie Friesland",
    "wof:name":"Geert De Vries Containerverhuur Bv",
    "wof:placetype":"venue"
},
  "geometry": {"coordinates":[5.688921,53.238068],"type":"Point"}
}