{
  "type": "Feature",
  "properties": {
    "addr:full":"Burg Bakhuizenln 16 Leimuiden Zuid-Holland 2451 AA",
    "addr:housenumber":"16",
    "addr:postcode":"2451 aa",
    "addr:street":"Burg",
    "iso:country":"NL",
    "sg:address":"Burg Bakhuizenln 16",
    "sg:city":"Leimuiden",
    "sg:classifiers":[
        {
            "category":"Retail",
            "subcategory":"Auto Repair",
            "type":"Services"
        }
    ],
    "sg:phone":"+31 172 508 127",
    "sg:postcode":"2451 AA",
    "sg:province":"Zuid-Holland",
    "sg:tags":[
        "garage"
    ],
    "wof:name":"Pau & Van Haaster Vof, Du",
    "wof:placetype":"venue"
},
  "geometry": {"coordinates":[4.672745,52.222027],"type":"Point"}
}