{
  "type": "Feature",
  "properties": {
    "addr:full":"J Heymansln 185 Rosmalen North Brabant 5246 BL",
    "addr:housenumber":"185",
    "addr:postcode":"5246 bl",
    "iso:country":"NL",
    "sg:address":"J Heymansln 185",
    "sg:city":"Rosmalen",
    "sg:orig_category":"Grafisch Ontwerpers",
    "sg:phone":"+31 73 644 4573",
    "sg:postcode":"5246 BL",
    "sg:province":"North Brabant",
    "sg:website":"http://www.a-lijn.nl",
    "wof:name":"A-Lijn",
    "wof:placetype":"venue"
},
  "geometry": {"coordinates":[5.348721,51.69873],"type":"Point"}
}