{
  "type": "Feature",
  "properties": {
    "addr:full":"Boterdiep 7 Capelle Ad Yssel South Holland 2904 ED",
    "addr:housenumber":"7;2904",
    "addr:postcode":"ed",
    "addr:street":"Boterdiep;Yssel",
    "iso:country":"NL",
    "sg:address":"Boterdiep 7",
    "sg:city":"Capelle Ad Yssel",
    "sg:orig_category":"Postzegels",
    "sg:phone":"+31 10 451 2925",
    "sg:postcode":"2904 ED",
    "sg:province":"South Holland",
    "wof:name":"Postzegelver Ijssel- & Lekstreek",
    "wof:placetype":"venue"
},
  "geometry": {"coordinates":[4.601699,51.935081],"type":"Point"}
}