{
  "type": "Feature",
  "properties": {
    "addr:full":"Lupine-Oord 57 Houten Utrecht 3991 VH",
    "addr:housenumber":"57",
    "addr:postcode":"3991 vh",
    "addr:street":"Lupine-Oord",
    "iso:country":"NL",
    "sg:address":"Lupine-Oord 57",
    "sg:city":"Houten",
    "sg:orig_category":"Keramische Producten Fab",
    "sg:phone":"+31 30 637 4123",
    "sg:postcode":"3991 VH",
    "sg:province":"Utrecht",
    "wof:name":"De Heksenketel",
    "wof:placetype":"venue"
},
  "geometry": {"coordinates":[5.158032,52.03257],"type":"Point"}
}