{
  "type": "Feature",
  "properties": {
    "addr:full":"Wethouder Venteweg 139 Gouda Zuid-Holland 2805 JN",
    "addr:housenumber":"139",
    "addr:postcode":"2805 jn",
    "addr:street":"Wethouder Venteweg",
    "iso:country":"NL",
    "sg:address":"Wethouder Venteweg 139",
    "sg:city":"Gouda",
    "sg:orig_category":"Wegen And Sportterreinen",
    "sg:phone":"+31 182 518 954",
    "sg:postcode":"2805 JN",
    "sg:province":"Zuid-Holland",
    "wof:name":"Aannemersbedrijf A. Holthuysen Bv",
    "wof:placetype":"venue"
},
  "geometry": {"coordinates":[4.7214388847,52.0214385986],"type":"Point"}
}