{
  "type": "Feature",
  "properties": {
    "addr:full":"C De Vriesweg 40D Dirkshorn Noord-Holland 1746 CM",
    "addr:housenumber":"40d",
    "addr:postcode":"1746 cm",
    "addr:street":"C De Vriesweg",
    "iso:country":"NL",
    "sg:address":"C De Vriesweg 40D",
    "sg:city":"Dirkshorn",
    "sg:orig_category":"Medische And Orthopedische Artikelen",
    "sg:phone":"+31 224 552 443",
    "sg:postcode":"1746 CM",
    "sg:province":"Noord-Holland",
    "wof:name":"Revatech Jan Jissink",
    "wof:placetype":"venue"
},
  "geometry": {"coordinates":[4.778168,52.731995],"type":"Point"}
}