{
  "type": "Feature",
  "properties": {
    "iso:country":"NL",
    "sg:address":"Langestraat 129",
    "sg:city":"Klazienaveen",
    "sg:classifiers":[
        {
            "category":"Shopping",
            "subcategory":"Clothing, Apparel, & Fashions",
            "type":"Retail Goods"
        }
    ],
    "sg:phone":"+31 591 312 391",
    "sg:postcode":"7891 GH",
    "sg:province":"Drenthe",
    "sg:tags":[
        "ondergoed",
        "lingerie"
    ],
    "wof:name":"Heldring Mode Bv",
    "wof:placetype":"venue"
},
  "geometry": {"coordinates":[6.9932,52.724483],"type":"Point"}
}