{
  "type": "Feature",
  "properties": {
    "addr:full":"Oudste Poortstr 2 S Heerenberg Gelderland 7041 AR",
    "addr:housenumber":"2",
    "addr:postcode":"7041",
    "addr:street":"Poortstr;Heerenberg Gelderland",
    "iso:country":"NL",
    "sg:address":"Oudste Poortstr 2",
    "sg:city":"S Heerenberg",
    "sg:classifiers":[
        {
            "category":"Travel",
            "subcategory":"Hotels & Motels",
            "type":"Entertainment"
        }
    ],
    "sg:phone":"+31 314 661 209",
    "sg:postcode":"7041 AR",
    "sg:province":"Gelderland",
    "wof:name":"Heitkamp",
    "wof:placetype":"venue"
},
  "geometry": {"coordinates":[6.243992,51.873684],"type":"Point"}
}