{
  "type": "Feature",
  "properties": {
    "addr:full":"Kattenburg 21A Druten Gelderland 6651 AL",
    "addr:housenumber":"21a",
    "addr:postcode":"6651 al",
    "addr:street":"Kattenburg",
    "iso:country":"NL",
    "sg:address":"Kattenburg 21A",
    "sg:city":"Druten",
    "sg:orig_category":"Drukkerijen",
    "sg:phone":"+31 487 512 252",
    "sg:postcode":"6651 AL",
    "sg:province":"Gelderland",
    "wof:name":"Maas En Waler, De",
    "wof:placetype":"venue"
},
  "geometry": {"coordinates":[5.611065,51.892075],"type":"Point"}
}