{
  "type": "Feature",
  "properties": {
    "iso:country":"NL",
    "sg:address":"Engelenburgstraat 15",
    "sg:city":"Twello",
    "sg:orig_category":"Diverse Bedrijfsinstallaties Gh",
    "sg:phone":"+31 571 276 677",
    "sg:postcode":"7391 AM",
    "sg:province":"Gelderland",
    "wof:name":"Het Cv Onderdeel Bv",
    "wof:placetype":"venue"
},
  "geometry": {"coordinates":[6.086938,52.22279],"type":"Point"}
}