{
  "type": "Feature",
  "properties": {
    "iso:country":"NL",
    "sg:address":"Haaksbergerstr 331",
    "sg:city":"Enschede",
    "sg:orig_category":"Zonweringen",
    "sg:phone":"+31 53 431 3455",
    "sg:postcode":"7545 GK",
    "sg:province":"Overijssel",
    "wof:name":"Hendriks Bv, Henny",
    "wof:placetype":"venue"
},
  "geometry": {"coordinates":[6.874306,52.208717],"type":"Point"}
}