{
  "type": "Feature",
  "properties": {
    "addr:full":"Cobbenhagenln 95 Tilburg Noord-Brabant 5037 DB",
    "addr:housenumber":"95",
    "addr:postcode":"5037 db",
    "addr:street":"Cobbenhagenln",
    "iso:country":"NL",
    "sg:address":"Cobbenhagenln 95",
    "sg:city":"Tilburg",
    "sg:classifiers":[
        {
            "category":"Professional",
            "subcategory":"Accounting & Tax Preparation",
            "type":"Services"
        }
    ],
    "sg:phone":"+31 13 594 0202",
    "sg:postcode":"5037 DB",
    "sg:province":"Noord-Brabant",
    "sg:tags":[
        "accountant",
        "en",
        "-kantoren",
        "register-"
    ],
    "sg:website":"http://www.bdo.nl",
    "wof:name":"Bdo",
    "wof:placetype":"venue"
},
  "geometry": {"coordinates":[5.05094,51.556992],"type":"Point"}
}