{
  "type": "Feature",
  "properties": {
    "addr:full":"Verl Stationsstr 1 Zwaagwesteinde Provincie Friesland 9271 CA",
    "addr:housenumber":"1",
    "addr:postcode":"9271 ca",
    "addr:street":"Stationsstr;Provincie Friesland",
    "iso:country":"NL",
    "sg:address":"Verl Stationsstr 1",
    "sg:city":"Zwaagwesteinde",
    "sg:orig_category":"Banken",
    "sg:phone":"+31 511 441 815",
    "sg:postcode":"9271 CA",
    "sg:province":"Provincie Friesland",
    "sg:website":"http://www.rabobank.nl",
    "wof:name":"Rabobank",
    "wof:placetype":"venue"
},
  "geometry": {"coordinates":[6.038138,53.255524],"type":"Point"}
}