{
  "type": "Feature",
  "properties": {
    "iso:country":"NL",
    "sg:address":"Hengeloln 1061",
    "sg:city":"S Gravenhage",
    "sg:orig_category":"Sportverenigingen En Ontspannings- Verenigingen",
    "sg:phone":"+31 70 367 7665",
    "sg:postcode":"2544 GH",
    "sg:province":"Noord-Holland",
    "wof:name":"Goede Worp Jeu De Boules Cl, De",
    "wof:placetype":"venue"
},
  "geometry": {"coordinates":[4.25157,52.039551],"type":"Point"}
}