{
  "type": "Feature",
  "properties": {
    "addr:full":"Abdis V Thornstr 70 Oosterhout Nb Noord-Brabant 4901 ZB",
    "addr:housenumber":"70",
    "addr:postcode":"4901 zb",
    "addr:street":"Abdis;Thornstr",
    "iso:country":"NL",
    "sg:address":"Abdis V Thornstr 70",
    "sg:city":"Oosterhout Nb",
    "sg:classifiers":[
        {
            "category":"Retail",
            "subcategory":"Auto Repair",
            "type":"Services"
        }
    ],
    "sg:phone":"+31 162 457 590",
    "sg:postcode":"4901 ZB",
    "sg:province":"Noord-Brabant",
    "sg:tags":[
        "garage"
    ],
    "wof:name":"Quality Fit",
    "wof:placetype":"venue"
},
  "geometry": {"coordinates":[4.85625,51.643051],"type":"Point"}
}