{
  "type": "Feature",
  "properties": {
    "iso:country":"NL",
    "sg:address":"Gasstraat 1",
    "sg:city":"Lisse",
    "sg:orig_category":"Metaalwerken",
    "sg:phone":"+31 252 411 395",
    "sg:postcode":"2161 WB",
    "sg:province":"Zuid-Holland",
    "wof:name":"V Scheurwater Montage",
    "wof:placetype":"venue"
},
  "geometry": {"coordinates":[4.567755,52.255764],"type":"Point"}
}