{
  "type": "Feature",
  "properties": {
    "addr:full":"V W Poelmanwg 25 Rotterdam Zuid-Holland 3088 EA",
    "addr:housenumber":"25",
    "addr:postcode":"3088 ea",
    "iso:country":"NL",
    "sg:address":"V W Poelmanwg 25",
    "sg:city":"Rotterdam",
    "sg:orig_category":"Verzekeringen - Verzekeringskantoren",
    "sg:phone":"+31 10 481 5609",
    "sg:postcode":"3088 EA",
    "sg:province":"Zuid-Holland",
    "wof:name":"Beau",
    "wof:placetype":"venue"
},
  "geometry": {"coordinates":[4.4430999756,51.8727302551],"type":"Point"}
}