{
  "type": "Feature",
  "properties": {
    "addr:full":"Tussen Meer 79 Amsterdam Noord-Holland 1068 EZ",
    "addr:housenumber":"79",
    "addr:postcode":"1068 ez",
    "addr:street":"Tussen Meer",
    "iso:country":"NL",
    "sg:address":"Tussen Meer 79",
    "sg:city":"Amsterdam",
    "sg:orig_category":"Wasserettes And Stomerijen",
    "sg:phone":"+31 20 619 2595",
    "sg:postcode":"1068 EZ",
    "sg:province":"Noord-Holland",
    "wof:name":"Palthe Stomerijen Bv",
    "wof:placetype":"venue"
},
  "geometry": {"coordinates":[4.8005108833,52.3580589294],"type":"Point"}
}