{
  "type": "Feature",
  "properties": {
    "addr:full":"Ludingaweg 8 Harlingen Provincie Friesland 8862 BM",
    "addr:housenumber":"8",
    "addr:postcode":"8862 bm",
    "addr:street":"Ludingaweg;Provincie Friesland",
    "iso:country":"NL",
    "sg:address":"Ludingaweg 8",
    "sg:city":"Harlingen",
    "sg:orig_category":"Diverse Grafische Activiteiten",
    "sg:phone":"+31 517 641 770",
    "sg:postcode":"8862 BM",
    "sg:province":"Provincie Friesland",
    "wof:name":"Grafisch Ontwerpburo Signum",
    "wof:placetype":"venue"
},
  "geometry": {"coordinates":[5.473599,53.156151],"type":"Point"}
}