{
  "type": "Feature",
  "properties": {
    "addr:full":"M De Boerstr 18 Drachten Provincie Friesland 9203 RD",
    "addr:housenumber":"18",
    "addr:postcode":"9203",
    "addr:street":"M;Provincie Friesland;Rd",
    "iso:country":"NL",
    "sg:address":"M De Boerstr 18",
    "sg:city":"Drachten",
    "sg:orig_category":"Vakantieverblijven",
    "sg:phone":"+31 512 520 545",
    "sg:postcode":"9203 RD",
    "sg:province":"Provincie Friesland",
    "wof:name":"Hier Is'T Bv",
    "wof:placetype":"venue"
},
  "geometry": {"coordinates":[6.084597,53.100998],"type":"Point"}
}