{
  "type": "Feature",
  "properties": {
    "addr:full":"Herman Gorterhof 100 Uithoorn Noord-Holland 1422 JS",
    "addr:housenumber":"100",
    "addr:postcode":"1422 js",
    "addr:street":"Herman Gorterhof",
    "iso:country":"NL",
    "sg:address":"Herman Gorterhof 100",
    "sg:city":"Uithoorn",
    "sg:orig_category":"Goederenvervoer Over De Weg",
    "sg:phone":"+31 297 521 020",
    "sg:postcode":"1422 JS",
    "sg:province":"Noord-Holland",
    "wof:name":"K En S Services",
    "wof:placetype":"venue"
},
  "geometry": {"coordinates":[4.824303,52.249672],"type":"Point"}
}