{
  "type": "Feature",
  "properties": {
    "addr:full":"Postbus 64 De Ryp Noord-Holland 1483 ZH",
    "addr:housenumber":"64",
    "addr:postcode":"1483 zh",
    "addr:street":"Postbus;De Ryp",
    "iso:country":"NL",
    "sg:address":"Postbus 64",
    "sg:city":"De Ryp",
    "sg:orig_category":"Verenigingen En Stichtingen",
    "sg:phone":"+31 299 674 649",
    "sg:postcode":"1483 ZH",
    "sg:province":"Noord-Holland",
    "wof:name":"Desembrood, Sticht",
    "wof:placetype":"venue"
},
  "geometry": {"coordinates":[4.846465,52.560177],"type":"Point"}
}