{
  "type": "Feature",
  "properties": {
    "iso:country":"NL",
    "sg:address":"Leiakker 10",
    "sg:city":"Sliedrecht",
    "sg:classifiers":[
        {
            "category":"Personal",
            "subcategory":"Nail Salon",
            "type":"Services"
        }
    ],
    "sg:phone":"+31 184 419 764",
    "sg:postcode":"3362 JC",
    "sg:province":"Zuid-Holland",
    "sg:tags":[
        "pedicure"
    ],
    "wof:name":"Versluis-Overduin, Monique",
    "wof:placetype":"venue"
},
  "geometry": {"coordinates":[4.795777,51.823994],"type":"Point"}
}