{
  "type": "Feature",
  "properties": {
    "addr:full":"Langemeer 83 Kaatsheuvel Noord-Brabant 5171 WL",
    "addr:housenumber":"83",
    "addr:postcode":"5171 wl",
    "addr:street":"Langemeer",
    "iso:country":"NL",
    "sg:address":"Langemeer 83",
    "sg:city":"Kaatsheuvel",
    "sg:orig_category":"Administratie- En Boekhoudkantoren",
    "sg:phone":"+31 416 540 834",
    "sg:postcode":"5171 WL",
    "sg:province":"Noord-Brabant",
    "wof:name":"Adkatel",
    "wof:placetype":"venue"
},
  "geometry": {"coordinates":[5.033175,51.659588],"type":"Point"}
}