{
  "type": "Feature",
  "properties": {
    "addr:full":"Stationsstraat 64 Almere Flevoland 1315 KJ",
    "addr:housenumber":"64",
    "addr:postcode":"1315 kj",
    "addr:street":"Stationsstraat;Flevoland",
    "iso:country":"NL",
    "sg:address":"Stationsstraat 64",
    "sg:city":"Almere",
    "sg:classifiers":[
        {
            "category":"Bakery",
            "type":"Food & Drink"
        }
    ],
    "sg:phone":"+31 36 534 7803",
    "sg:postcode":"1315 KJ",
    "sg:province":"Flevoland",
    "sg:tags":[
        "brood",
        "banket"
    ],
    "wof:name":"Jamin",
    "wof:placetype":"venue"
},
  "geometry": {"coordinates":[5.219977,52.372681],"type":"Point"}
}