{
  "type": "Feature",
  "properties": {
    "addr:full":"Meloenstraat 110 'S Gravenhage South Holland 2564 TK",
    "addr:housenumber":"110 '",
    "addr:postcode":"2564 tk",
    "addr:street":"Meloenstraat",
    "iso:country":"NL",
    "sg:address":"Meloenstraat 110",
    "sg:city":"'S Gravenhage",
    "sg:orig_category":"Partycatering And -Organisatie",
    "sg:phone":"+31 70 368 1598",
    "sg:postcode":"2564 TK",
    "sg:province":"South Holland",
    "wof:name":"Randstad Catering Serv.",
    "wof:placetype":"venue"
},
  "geometry": {"coordinates":[4.254815,52.068119],"type":"Point"}
}