{
  "type": "Feature",
  "properties": {
    "iso:country":"NL",
    "sg:address":"Professor Zeemanweg 23",
    "sg:city":"Waalwijk",
    "sg:orig_category":"Farmaceutische Producten Gh",
    "sg:phone":"+31 416 650 250",
    "sg:postcode":"5144 NN",
    "sg:province":"North Brabant",
    "wof:name":"Sbr Trading",
    "wof:placetype":"venue"
},
  "geometry": {"coordinates":[5.058871,51.673798],"type":"Point"}
}