{
  "type": "Feature",
  "properties": {
    "iso:country":"NL",
    "sg:address":"Waalbandk 97",
    "sg:city":"Ochten",
    "sg:orig_category":"Koeltechniek",
    "sg:phone":"+31 488 412 944",
    "sg:postcode":"4051 CK",
    "sg:province":"Gelderland",
    "wof:name":"Vooren Kesteren Bv, Van De",
    "wof:placetype":"venue"
},
  "geometry": {"coordinates":[5.620588,51.904976],"type":"Point"}
}