{
  "type": "Feature",
  "properties": {
    "addr:full":"Kinkerstraat 323 Amsterdam Noord-Holland 1053 EV",
    "addr:housenumber":"323",
    "addr:street":"Kinkerstraat",
    "iso:country":"NL",
    "sg:address":"Kinkerstraat 323",
    "sg:city":"Amsterdam",
    "sg:orig_category":"Kappers",
    "sg:phone":"+31 20 612 2594",
    "sg:postcode":"1053 EV",
    "sg:province":"Noord-Holland",
    "wof:name":"Kapsalon Meijers",
    "wof:placetype":"venue"
},
  "geometry": {"coordinates":[4.8622059822,52.3645439148],"type":"Point"}
}