{
  "type": "Feature",
  "properties": {
    "iso:country":"NL",
    "sg:address":"Zuid Parallelweg 58",
    "sg:city":"Velp Gld",
    "sg:orig_category":"Schoonheidssalons",
    "sg:phone":"+31 26 363 0435",
    "sg:postcode":"6882 AH",
    "sg:province":"Gelderland",
    "wof:name":"Schoonheidssalon Beau Visage",
    "wof:placetype":"venue"
},
  "geometry": {"coordinates":[5.961356,51.99403],"type":"Point"}
}