{
  "type": "Feature",
  "properties": {
    "iso:country":"NL",
    "sg:address":"Langstraat 7",
    "sg:city":"Zeeland (Nb)",
    "sg:orig_category":"Bloemen And Planten",
    "sg:phone":"+31 486 432 171",
    "sg:postcode":"5411 LE",
    "sg:province":"Noord-Brabant",
    "wof:name":"Achza Bloemenatelier",
    "wof:placetype":"venue"
},
  "geometry": {"coordinates":[5.718774,51.688469],"type":"Point"}
}