{
  "type": "Feature",
  "properties": {
    "addr:full":"Brinkstr 2 Haarzuilens Utrecht 3455 SK",
    "addr:housenumber":"2",
    "addr:street":"Brinkstr;3455",
    "iso:country":"NL",
    "sg:address":"Brinkstr 2",
    "sg:city":"Haarzuilens",
    "sg:orig_category":"Grafisch Ontwerpers",
    "sg:phone":"+31 30 677 3587",
    "sg:postcode":"3455 SK",
    "sg:province":"Utrecht",
    "wof:name":"Wierda, A",
    "wof:placetype":"venue"
},
  "geometry": {"coordinates":[4.997998,52.120098],"type":"Point"}
}