{
  "type": "Feature",
  "properties": {
    "addr:full":"Touwslagersstraat 6 Sneek Friesland 8601 WE",
    "addr:housenumber":"6",
    "addr:postcode":"8601 we",
    "addr:street":"Touwslagersstraat",
    "iso:country":"NL",
    "sg:address":"Touwslagersstraat 6",
    "sg:city":"Sneek",
    "sg:orig_category":"Metaalafval, Schrootrecycling And Sloperijen",
    "sg:phone":"+31 515 424 089",
    "sg:postcode":"8601 WE",
    "sg:province":"Friesland",
    "wof:name":"Autosloopbedrijf Sneek",
    "wof:placetype":"venue"
},
  "geometry": {"coordinates":[5.629992,53.033493],"type":"Point"}
}