{
  "type": "Feature",
  "properties": {
    "addr:full":"Stationsweg 19 Venray Limburg 5802 AA",
    "addr:housenumber":"19",
    "addr:postcode":"5802 aa",
    "addr:street":"Stationsweg",
    "iso:country":"NL",
    "sg:address":"Stationsweg 19",
    "sg:city":"Venray",
    "sg:orig_category":"Bloemen And Planten",
    "sg:phone":"+31 478 587 627",
    "sg:postcode":"5802 AA",
    "sg:province":"Limburg",
    "wof:name":"Bloemsierkunst Semperflorens",
    "wof:placetype":"venue"
},
  "geometry": {"coordinates":[5.978847,51.528873],"type":"Point"}
}