{
  "type": "Feature",
  "properties": {
    "addr:full":"Bronckhorststraat 16 Amsterdam North Holland 1071 WR",
    "addr:housenumber":"16",
    "addr:postcode":"1071 wr",
    "addr:street":"Bronckhorststraat",
    "iso:country":"NL",
    "sg:address":"Bronckhorststraat 16",
    "sg:city":"Amsterdam",
    "sg:orig_category":"Verzekeringen",
    "sg:phone":"+31 20 679 1336",
    "sg:postcode":"1071 WR",
    "sg:province":"North Holland",
    "wof:name":"Lobbes Insurance Consultants Cv",
    "wof:placetype":"venue"
},
  "geometry": {"coordinates":[4.880804,52.353062],"type":"Point"}
}