{
  "type": "Feature",
  "properties": {
    "addr:full":"Wachtelstraat 46 Gouda Zuid-Holland 2802 EV",
    "addr:housenumber":"46",
    "addr:postcode":"2802 ev",
    "addr:street":"Wachtelstraat",
    "iso:country":"NL",
    "sg:address":"Wachtelstraat 46",
    "sg:city":"Gouda",
    "sg:orig_category":"Meubelreparatie And -Restauratie",
    "sg:phone":"+31 182 521 074",
    "sg:postcode":"2802 EV",
    "sg:province":"Zuid-Holland",
    "wof:name":"T.H. Faase",
    "wof:placetype":"venue"
},
  "geometry": {"coordinates":[4.700348,52.009933],"type":"Point"}
}