{
  "type": "Feature",
  "properties": {
    "addr:full":"Dorpsstr 40/A St Willebrord New Hampshire 4711 NH",
    "addr:housenumber":"40 / a",
    "addr:postcode":"4711 nh",
    "addr:street":"Dorpsstr;St;Hampshire",
    "iso:country":"NL",
    "sg:address":"Dorpsstr 40/A",
    "sg:city":"St Willebrord",
    "sg:orig_category":"Kappers",
    "sg:phone":"+31 165 387 429",
    "sg:postcode":"4711 NH",
    "sg:province":"New Hampshire",
    "wof:name":"Jan",
    "wof:placetype":"venue"
},
  "geometry": {"coordinates":[-71.6328277588,44.0013008118],"type":"Point"}
}