{
  "type": "Feature",
  "properties": {
    "addr:full":"P V M Geld Blauw 11 Heteren Gelderland 6666 LR",
    "addr:housenumber":"11",
    "addr:postcode":"6666 lr",
    "addr:street":"Blauw;Gelderland",
    "iso:country":"NL",
    "sg:address":"P V M Geld Blauw 11",
    "sg:city":"Heteren",
    "sg:orig_category":"Metaalbewerking",
    "sg:phone":"+31 26 472 2823",
    "sg:postcode":"6666 LR",
    "sg:province":"Gelderland",
    "wof:name":"Bal Bv",
    "wof:placetype":"venue"
},
  "geometry": {"coordinates":[5.75695,51.958275],"type":"Point"}
}