{
  "type": "Feature",
  "properties": {
    "addr:full":"Roserije 47 Maastricht Limburg 6228 DH",
    "addr:housenumber":"47",
    "addr:postcode":"6228 dh",
    "addr:street":"Roserije",
    "iso:country":"NL",
    "sg:address":"Roserije 47",
    "sg:city":"Maastricht",
    "sg:orig_category":"Kappers",
    "sg:phone":"+31 43 361 5787",
    "sg:postcode":"6228 DH",
    "sg:province":"Limburg",
    "wof:name":"Hairpoint",
    "wof:placetype":"venue"
},
  "geometry": {"coordinates":[5.7260007858,50.8277778625],"type":"Point"}
}