{
  "type": "Feature",
  "properties": {
    "iso:country":"NL",
    "sg:address":"Dr Schaepmanstr 3",
    "sg:city":"Oldenzaal",
    "sg:orig_category":"Verenigingen En Stichtingen",
    "sg:phone":"+31 541 522 827",
    "sg:postcode":"7572 XT",
    "sg:province":"Overijssel",
    "wof:name":"Vluchtelingenwerk Oldenzaal, Sticht",
    "wof:placetype":"venue"
},
  "geometry": {"coordinates":[6.926164,52.315727],"type":"Point"}
}