{
  "type": "Feature",
  "properties": {
    "addr:full":"Radebinnensingel 36 Groningen Groningen 9711 EM",
    "addr:housenumber":"36",
    "addr:postcode":"9711 em",
    "addr:street":"Radebinnensingel",
    "iso:country":"NL",
    "sg:address":"Radebinnensingel 36",
    "sg:city":"Groningen",
    "sg:orig_category":"Film-, Tv- And Videoproductie",
    "sg:phone":"+31 50 318 1217",
    "sg:postcode":"9711 EM",
    "sg:province":"Groningen",
    "wof:name":"Buis Audiovisuele Produkties",
    "wof:placetype":"venue"
},
  "geometry": {"coordinates":[6.574082,53.21595],"type":"Point"}
}