{
  "type": "Feature",
  "properties": {
    "addr:full":"Veenschapswg 43 Coevorden Drenthe 7741 NL",
    "addr:housenumber":"43",
    "addr:postcode":"7741 nl",
    "addr:street":"Veenschapswg",
    "iso:country":"NL",
    "sg:address":"Veenschapswg 43",
    "sg:city":"Coevorden",
    "sg:orig_category":"Voegwerken",
    "sg:phone":"+31 524 513 380",
    "sg:postcode":"7741 NL",
    "sg:province":"Drenthe",
    "wof:name":"Kroezen, M",
    "wof:placetype":"venue"
},
  "geometry": {"coordinates":[6.680526,52.676048],"type":"Point"}
}