{
  "type": "Feature",
  "properties": {
    "iso:country":"NL",
    "sg:address":"Bosstraat 14",
    "sg:city":"Driebergen-Rijsenburg",
    "sg:orig_category":"Banken And Kredietinstellingen",
    "sg:phone":"+31 30 698 3666",
    "sg:postcode":"3971 XE",
    "sg:province":"Utrecht",
    "wof:name":"Rabobank",
    "wof:placetype":"venue"
},
  "geometry": {"coordinates":[5.281826,52.053463],"type":"Point"}
}