{
  "type": "Feature",
  "properties": {
    "addr:full":"1E V Swindenstr 427 Amsterdam Noord-Holland 1093 GB",
    "addr:housenumber":"427",
    "addr:postcode":"1093 gb",
    "addr:street":"1E V Swindenstr",
    "iso:country":"NL",
    "sg:address":"1E V Swindenstr 427",
    "sg:city":"Amsterdam",
    "sg:orig_category":"Juweliers",
    "sg:phone":"+31 20 665 3696",
    "sg:postcode":"1093 GB",
    "sg:province":"Noord-Holland",
    "sg:website":"http://www.baldevjewellers.com",
    "wof:name":"Baldev Juwelier",
    "wof:placetype":"venue"
},
  "geometry": {"coordinates":[4.928322,52.362972],"type":"Point"}
}