{
  "type": "Feature",
  "properties": {
    "addr:full":"Oude Haagweg 32 Den Haag Bezuidenhout Zuid-Holland 2552 EP",
    "addr:housenumber":"32",
    "addr:postcode":"2552 ep",
    "addr:street":"Oude Haagweg",
    "iso:country":"NL",
    "sg:address":"Oude Haagweg 32",
    "sg:city":"Den Haag Bezuidenhout",
    "sg:orig_category":"Glaszetten",
    "sg:phone":"+31 70 391 2675",
    "sg:postcode":"2552 EP",
    "sg:province":"Zuid-Holland",
    "wof:name":"Blom Glasservice",
    "wof:placetype":"venue"
},
  "geometry": {"coordinates":[4.244563,52.055855],"type":"Point"}
}