{
  "type": "Feature",
  "properties": {
    "addr:full":"Operaln 152 Oldenzaal Overijssel 7577 JA",
    "addr:housenumber":"152",
    "addr:postcode":"7577 ja",
    "iso:country":"NL",
    "sg:address":"Operaln 152",
    "sg:city":"Oldenzaal",
    "sg:orig_category":"Kinderactiviteiten",
    "sg:phone":"+31 541 510 925",
    "sg:postcode":"7577 JA",
    "sg:province":"Overijssel",
    "wof:name":"H\u00f6fte, De",
    "wof:placetype":"venue"
},
  "geometry": {"coordinates":[6.927277,52.309284],"type":"Point"}
}