{
  "type": "Feature",
  "properties": {
    "iso:country":"NL",
    "sg:address":"De Oude Veiling 46",
    "sg:city":"Zwaag",
    "sg:orig_category":"Beveiliging",
    "sg:phone":"+31 229 271 378",
    "sg:postcode":"1689 AB",
    "sg:province":"North Holland",
    "sg:website":"http://www.vermeerbeveiliging.nl",
    "wof:name":"Vermeer Beveiligings Techniek",
    "wof:placetype":"venue"
},
  "geometry": {"coordinates":[5.061934,52.66283],"type":"Point"}
}