{
  "type": "Feature",
  "properties": {
    "iso:country":"NL",
    "sg:address":"Herenstr 1",
    "sg:city":"Schagen",
    "sg:orig_category":"Juweliers",
    "sg:phone":"+31 224 218 433",
    "sg:postcode":"1741 BM",
    "sg:province":"North Holland",
    "wof:name":"Vries, Jannie",
    "wof:placetype":"venue"
},
  "geometry": {"coordinates":[4.796375,52.786129],"type":"Point"}
}