{
  "type": "Feature",
  "properties": {
    "addr:full":"Centrum Assen Provincie Drenthe 9401 DL",
    "addr:postcode":"9401 dl",
    "addr:street":"Provincie Drenthe",
    "iso:country":"NL",
    "sg:address":"Centrum",
    "sg:city":"Assen",
    "sg:orig_category":"Koopzondagen Zondag 10 Maart 2002",
    "sg:phone":"+31 0",
    "sg:postcode":"9401 DL",
    "sg:province":"Provincie Drenthe",
    "wof:name":"Assen Binnnenstad",
    "wof:placetype":"venue"
},
  "geometry": {"coordinates":[6.559343,52.995865],"type":"Point"}
}