{
  "type": "Feature",
  "properties": {
    "iso:country":"NL",
    "sg:address":"Walstroweg 21",
    "sg:city":"Haren Gn",
    "sg:orig_category":"Overheidsdiensten",
    "sg:phone":"+31 50 535 0935",
    "sg:postcode":"9753 AK",
    "sg:province":"Groningen",
    "wof:name":"Thuiszorg Buro Haren",
    "wof:placetype":"venue"
},
  "geometry": {"coordinates":[6.6199579239,53.1747627258],"type":"Point"}
}