{
  "type": "Feature",
  "properties": {
    "addr:full":"G V Assendelftstr 36F Heemskerk Noord-Holland 1964 NL",
    "addr:housenumber":"36f",
    "addr:postcode":"1964 nl",
    "addr:street":"V Assendelftstr",
    "iso:country":"NL",
    "sg:address":"G V Assendelftstr 36F",
    "sg:city":"Heemskerk",
    "sg:orig_category":"Loodgieters",
    "sg:phone":"+31 251 254 072",
    "sg:postcode":"1964 NL",
    "sg:province":"Noord-Holland",
    "wof:name":"Huzon Meesterdak Bv",
    "wof:placetype":"venue"
},
  "geometry": {"coordinates":[4.66983,52.513546],"type":"Point"}
}