{
  "type": "Feature",
  "properties": {
    "addr:full":"Edeseweg 106 Wekerom Gelderland 6733 AH",
    "addr:housenumber":"106",
    "addr:postcode":"6733 ah",
    "addr:street":"Edeseweg;Gelderland",
    "iso:country":"NL",
    "sg:address":"Edeseweg 106",
    "sg:city":"Wekerom",
    "sg:classifiers":[
        {
            "category":"Fast Food",
            "type":"Food & Drink"
        }
    ],
    "sg:phone":"+31 318 463 011",
    "sg:postcode":"6733 AH",
    "sg:province":"Gelderland",
    "sg:tags":[
        "afhaal",
        "restaurant"
    ],
    "wof:name":"Eetcafe Dick'S Grill",
    "wof:placetype":"venue"
},
  "geometry": {"coordinates":[5.715972,52.112106],"type":"Point"}
}