{
  "type": "Feature",
  "properties": {
    "addr:full":"V Coothpln 46 Breda Noord-Brabant 4811 NG",
    "addr:housenumber":"46",
    "addr:postcode":"4811 ng",
    "iso:country":"NL",
    "sg:address":"V Coothpln 46",
    "sg:city":"Breda",
    "sg:orig_category":"Keukens",
    "sg:phone":"+31 76 522 2269",
    "sg:postcode":"4811 NG",
    "sg:province":"Noord-Brabant",
    "sg:website":"http://www.montall.nl",
    "wof:name":"Montall Breda Bv - Keukens",
    "wof:placetype":"venue"
},
  "geometry": {"coordinates":[4.771685,51.591351],"type":"Point"}
}