{
  "type": "Feature",
  "properties": {
    "addr:full":"Vondelstraat 25 Amsterdam Noord-Holland 1054 GH",
    "addr:housenumber":"25",
    "addr:postcode":"1054 gh",
    "addr:street":"Vondelstraat",
    "iso:country":"NL",
    "sg:address":"Vondelstraat 25",
    "sg:city":"Amsterdam",
    "sg:orig_category":"Makelaars In Onroerend Goed",
    "sg:phone":"+31 20 683 8911",
    "sg:postcode":"1054 GH",
    "sg:province":"Noord-Holland",
    "wof:name":"Hansen + Constandse, Makelaars O.G.",
    "wof:placetype":"venue"
},
  "geometry": {"coordinates":[4.877245,52.362118],"type":"Point"}
}