{
  "type": "Feature",
  "properties": {
    "addr:full":"Dorpsstr 32 Wagenberg Noord-Brabant 4845 CG",
    "addr:housenumber":"32",
    "addr:postcode":"4845 cg",
    "addr:street":"Dorpsstr",
    "iso:country":"NL",
    "sg:address":"Dorpsstr 32",
    "sg:city":"Wagenberg",
    "sg:orig_category":"Koeltechniek",
    "sg:phone":"+31 76 593 1018",
    "sg:postcode":"4845 CG",
    "sg:province":"Noord-Brabant",
    "wof:name":"Vakma Bv",
    "wof:placetype":"venue"
},
  "geometry": {"coordinates":[4.745043,51.664043],"type":"Point"}
}