{
  "type": "Feature",
  "properties": {
    "addr:full":"De Hooge Hoek 16 Renswoude Utrecht 3927 GG",
    "addr:housenumber":"16",
    "addr:postcode":"3927 gg",
    "addr:street":"De Hooge Hoek",
    "iso:country":"NL",
    "sg:address":"De Hooge Hoek 16",
    "sg:city":"Renswoude",
    "sg:orig_category":"Onderhoudswerken",
    "sg:phone":"+31 318 573 836",
    "sg:postcode":"3927 GG",
    "sg:province":"Utrecht",
    "wof:name":"Doorn Vof, J J Van",
    "wof:placetype":"venue"
},
  "geometry": {"coordinates":[5.535968,52.079063],"type":"Point"}
}