{
  "type": "Feature",
  "properties": {
    "addr:full":"Aalsterwg 230 Eindhoven North Brabant 5644 RK",
    "addr:housenumber":"230",
    "addr:postcode":"5644 rk",
    "iso:country":"NL",
    "sg:address":"Aalsterwg 230",
    "sg:city":"Eindhoven",
    "sg:orig_category":"Artsen - Specialisten Orthopedie",
    "sg:phone":"+31 40 211 8888",
    "sg:postcode":"5644 RK",
    "sg:province":"North Brabant",
    "wof:name":"Mts Eindhoven-Z",
    "wof:placetype":"venue"
},
  "geometry": {"coordinates":[5.484397,51.420673],"type":"Point"}
}