{
  "type": "Feature",
  "properties": {
    "iso:country":"NL",
    "sg:address":"Albert Verweijstraat 1",
    "sg:city":"Winschoten",
    "sg:classifiers":[
        {
            "category":"Education",
            "subcategory":"Preschool",
            "type":"Public Place"
        }
    ],
    "sg:phone":"+31 597 416 162",
    "sg:postcode":"9673 BL",
    "sg:province":"Groningen",
    "sg:tags":[
        "kleuteronderwijs",
        "basis-"
    ],
    "wof:name":"Openbare Basisschool De Waterlelie",
    "wof:placetype":"venue"
},
  "geometry": {"coordinates":[7.034061,53.138329],"type":"Point"}
}