{
  "type": "Feature",
  "properties": {
    "addr:full":"Kievitstr 15 Hengelo Ov Overijssel 7557 AP",
    "addr:housenumber":"15",
    "addr:postcode":"7557 ap",
    "addr:street":"Kievitstr;Ov",
    "iso:country":"NL",
    "sg:address":"Kievitstr 15",
    "sg:city":"Hengelo Ov",
    "sg:orig_category":"Gehandicapteninformatie",
    "sg:phone":"+31 74 255 6600",
    "sg:postcode":"7557 AP",
    "sg:province":"Overijssel",
    "sg:website":"http://www.wztw.nl",
    "wof:name":"Woonzorg Twente",
    "wof:placetype":"venue"
},
  "geometry": {"coordinates":[6.802739,52.264111],"type":"Point"}
}