{
  "type": "Feature",
  "properties": {
    "addr:full":"Nieuwstr 12 Schiedam Zuid-Holland 3111 JP",
    "addr:housenumber":"12",
    "addr:postcode":"3111 jp",
    "addr:street":"Nieuwstr",
    "iso:country":"NL",
    "sg:address":"Nieuwstr 12",
    "sg:city":"Schiedam",
    "sg:orig_category":"Verenigingen En Stichtingen",
    "sg:phone":"+31 10 426 4356",
    "sg:postcode":"3111 JP",
    "sg:province":"Zuid-Holland",
    "wof:name":"Teerstoof, Sticht De",
    "wof:placetype":"venue"
},
  "geometry": {"coordinates":[4.39816,51.918472],"type":"Point"}
}