{
  "type": "Feature",
  "properties": {
    "addr:full":"Vd Spiegelstr 30B Vlaardingen South Holland 3135 SH",
    "addr:housenumber":"30b",
    "addr:postcode":"3135 sh",
    "iso:country":"NL",
    "sg:address":"Vd Spiegelstr 30B",
    "sg:city":"Vlaardingen",
    "sg:orig_category":"Vertaalbureaus",
    "sg:phone":"+31 10 471 1889",
    "sg:postcode":"3135 SH",
    "sg:province":"South Holland",
    "wof:name":"Vlah, D",
    "wof:placetype":"venue"
},
  "geometry": {"coordinates":[4.36206,51.91568],"type":"Point"}
}