{
  "type": "Feature",
  "properties": {
    "iso:country":"NL",
    "sg:address":"H Diesveldsngl 41",
    "sg:city":"Amsterdam",
    "sg:orig_category":"Sportverenigingen En Ontspannings- Verenigingen",
    "sg:phone":"+31 20 619 9510",
    "sg:postcode":"1060 RL",
    "sg:province":"Noord-Holland",
    "wof:name":"Hengelsportver Naarden-Bussum",
    "wof:placetype":"venue"
},
  "geometry": {"coordinates":[4.788789,52.351265],"type":"Point"}
}