{
  "type": "Feature",
  "properties": {
    "addr:full":"H Diesveldsngl 41 Amsterdam Noord-Holland 1060 RL",
    "addr:housenumber":"41",
    "addr:postcode":"1060 rl",
    "iso:country":"NL",
    "sg:address":"H Diesveldsngl 41",
    "sg:city":"Amsterdam",
    "sg:orig_category":"Sportverenigingen En Ontspannings- Verenigingen",
    "sg:phone":"+31 20 619 9510",
    "sg:postcode":"1060 RL",
    "sg:province":"Noord-Holland",
    "wof:name":"Hengelsportver Naarden-Bussum",
    "wof:placetype":"venue"
},
  "geometry": {"coordinates":[4.788789,52.351265],"type":"Point"}
}