{
  "type": "Feature",
  "properties": {
    "addr:full":"Abcouderstrwg 77 Amsterdam Zuidoost Noord-Holland 1105 AA",
    "addr:housenumber":"77",
    "addr:postcode":"zuidoost;1105 aa",
    "addr:street":"Abcouderstrwg",
    "iso:country":"NL",
    "sg:address":"Abcouderstrwg 77",
    "sg:city":"Amsterdam Zuidoost",
    "sg:orig_category":"Natuur- En Milieuorganisaties",
    "sg:phone":"+31 294 285 021",
    "sg:postcode":"1105 AA",
    "sg:province":"Noord-Holland",
    "wof:name":"Ruige Hof Natuurver, De",
    "wof:placetype":"venue"
},
  "geometry": {"coordinates":[4.96103,52.28899],"type":"Point"}
}