{
  "type": "Feature",
  "properties": {
    "iso:country":"NL",
    "sg:address":"Kruisstr 35",
    "sg:city":"Zutphen",
    "sg:orig_category":"Administratie- En Boekhoudkantoren",
    "sg:phone":"+31 575 541 854",
    "sg:postcode":"7205 BG",
    "sg:province":"Gelderland",
    "wof:name":"Nugteren",
    "wof:placetype":"venue"
},
  "geometry": {"coordinates":[6.191525,52.140202],"type":"Point"}
}