{
  "type": "Feature",
  "properties": {
    "iso:country":"NL",
    "sg:address":"Mauritshof 35",
    "sg:city":"Koningsbosch",
    "sg:orig_category":"Diverse Grafische Activiteiten",
    "sg:phone":"+31 475 301 708",
    "sg:postcode":"6104 CD",
    "sg:province":"North Rhine-Westphalia",
    "wof:name":"L.W.M. Wilms",
    "wof:placetype":"venue"
},
  "geometry": {"coordinates":[5.954071,51.052361],"type":"Point"}
}