{
  "type": "Feature",
  "properties": {
    "iso:country":"NL",
    "sg:address":"Hilleln 49D",
    "sg:city":"Rotterdam",
    "sg:orig_category":"Zonweringen",
    "sg:phone":"+31 10 485 9464",
    "sg:postcode":"3072 JE",
    "sg:province":"Zuid-Holland",
    "wof:name":"Lamel Fashion",
    "wof:placetype":"venue"
},
  "geometry": {"coordinates":[4.49005,51.9025],"type":"Point"}
}