{
  "type": "Feature",
  "properties": {
    "addr:full":"Jan Van Arkelstraat 28 Vianen Zh Utrecht 4131 ZS",
    "addr:housenumber":"28",
    "addr:postcode":"zh;4131 zs",
    "addr:street":"Jan Van Arkelstraat",
    "iso:country":"NL",
    "sg:address":"Jan Van Arkelstraat 28",
    "sg:city":"Vianen Zh",
    "sg:orig_category":"Boekhouders",
    "sg:phone":"+31 347 320 946",
    "sg:postcode":"4131 ZS",
    "sg:province":"Utrecht",
    "wof:name":"De Klinkende Munt",
    "wof:placetype":"venue"
},
  "geometry": {"coordinates":[5.101465,51.991547],"type":"Point"}
}