{
  "type": "Feature",
  "properties": {
    "addr:full":"Dodewaardln 7 Tiel Gelderland 4006 EA",
    "addr:housenumber":"7",
    "addr:postcode":"4006 ea",
    "addr:street":"Dodewaardln;Gelderland",
    "iso:country":"NL",
    "sg:address":"Dodewaardln 7",
    "sg:city":"Tiel",
    "sg:orig_category":"Scholen: Hoger Beroepsonderwijs",
    "sg:phone":"+31 344 613 935",
    "sg:postcode":"4006 EA",
    "sg:province":"Gelderland",
    "wof:name":"Vanck, 'T",
    "wof:placetype":"venue"
},
  "geometry": {"coordinates":[5.430696,51.888096],"type":"Point"}
}