{
  "type": "Feature",
  "properties": {
    "iso:country":"NL",
    "sg:address":"Sterrenkamp 9",
    "sg:city":"Emmen",
    "sg:orig_category":"Makelaars In Onroerend Goed",
    "sg:phone":"+31 591 614 158",
    "sg:postcode":"7811 HA",
    "sg:province":"Provincie Drenthe",
    "wof:name":"Baron W",
    "wof:placetype":"venue"
},
  "geometry": {"coordinates":[6.897621,52.783745],"type":"Point"}
}