{
  "type": "Feature",
  "properties": {
    "addr:full":"Bovenhuizen 6 Uithuizen Groningen 9981 HB",
    "addr:housenumber":"6",
    "addr:postcode":"9981 hb",
    "addr:street":"Bovenhuizen",
    "iso:country":"NL",
    "sg:address":"Bovenhuizen 6",
    "sg:city":"Uithuizen",
    "sg:orig_category":"Wielen",
    "sg:phone":"+31 595 431 983",
    "sg:postcode":"9981 HB",
    "sg:province":"Groningen",
    "wof:name":"Wielenspecialist, De",
    "wof:placetype":"venue"
},
  "geometry": {"coordinates":[6.6586298943,53.4089126587],"type":"Point"}
}