{
  "type": "Feature",
  "properties": {
    "addr:full":"V Hoorns Houtwg 10 Huizen Noord-Holland 1272 AH",
    "addr:housenumber":"10",
    "addr:postcode":"1272 ah",
    "addr:street":"V Hoorns Houtwg",
    "iso:country":"NL",
    "sg:address":"V Hoorns Houtwg 10",
    "sg:city":"Huizen",
    "sg:orig_category":"Bloemen En Planten",
    "sg:phone":"+31 35 525 3716",
    "sg:postcode":"1272 AH",
    "sg:province":"Noord-Holland",
    "wof:name":"Palet",
    "wof:placetype":"venue"
},
  "geometry": {"coordinates":[5.23421,52.29504],"type":"Point"}
}