{
  "type": "Feature",
  "properties": {
    "addr:full":"Ten Busschekamp 1 Zwolle NL.08 8014 ED",
    "addr:housenumber":"1",
    "addr:postcode":"8014 ed",
    "addr:street":"Ten Busschekamp",
    "iso:country":"NL",
    "sg:address":"Ten Busschekamp 1",
    "sg:city":"Zwolle",
    "sg:orig_category":"Voetverzorging",
    "sg:phone":"+31 38 465 9922",
    "sg:postcode":"8014 ED",
    "sg:province":"NL.08",
    "wof:name":"Haas, A F De",
    "wof:placetype":"venue"
},
  "geometry": {"coordinates":[6.113798,52.491512],"type":"Point"}
}