{
  "type": "Feature",
  "properties": {
    "addr:full":"Mackayware 48 Zwolle NL.08 8014 RW",
    "addr:housenumber":"48",
    "addr:postcode":"8014",
    "addr:street":"Mackayware;Rw",
    "iso:country":"NL",
    "sg:address":"Mackayware 48",
    "sg:city":"Zwolle",
    "sg:orig_category":"Juweliers",
    "sg:phone":"+31 38 465 2215",
    "sg:postcode":"8014 RW",
    "sg:province":"NL.08",
    "sg:website":"http://www.goldbusiness.org",
    "wof:name":"Gold Business Vof",
    "wof:placetype":"venue"
},
  "geometry": {"coordinates":[6.112779,52.47736],"type":"Point"}
}