{
  "type": "Feature",
  "properties": {
    "addr:full":"Stationsplein 3 Heiloo North Holland 1851 LN",
    "addr:housenumber":"3",
    "addr:postcode":"1851 ln",
    "addr:street":"Stationsplein",
    "iso:country":"NL",
    "sg:address":"Stationsplein 3",
    "sg:city":"Heiloo",
    "sg:orig_category":"Antiekzaken",
    "sg:phone":"+31 72 533 9675",
    "sg:postcode":"1851 LN",
    "sg:province":"North Holland",
    "wof:name":"Eldorado Curiosa",
    "wof:placetype":"venue"
},
  "geometry": {"coordinates":[4.702266,52.599831],"type":"Point"}
}