{
  "type": "Feature",
  "properties": {
    "addr:full":"Voortsepad 57 Hilvarenbeek Noord-Brabant 5081 ZJ",
    "addr:housenumber":"57",
    "addr:postcode":"5081 zj",
    "addr:street":"Voortsepad",
    "iso:country":"NL",
    "sg:address":"Voortsepad 57",
    "sg:city":"Hilvarenbeek",
    "sg:orig_category":"Vertaal- And Tolkenbureaus",
    "sg:phone":"+31 13 505 4865",
    "sg:postcode":"5081 ZJ",
    "sg:province":"Noord-Brabant",
    "wof:name":"A.A. Klimov",
    "wof:placetype":"venue"
},
  "geometry": {"coordinates":[5.135408,51.490456],"type":"Point"}
}