{
  "type": "Feature",
  "properties": {
    "addr:full":"Buitentuin 20 Dokkum Friesland 9101 AT",
    "addr:housenumber":"20",
    "addr:postcode":"9101",
    "addr:street":"Buitentuin",
    "iso:country":"NL",
    "sg:address":"Buitentuin 20",
    "sg:city":"Dokkum",
    "sg:orig_category":"Drukkerijen And Copyshops",
    "sg:phone":"+31 519 293 491",
    "sg:postcode":"9101 AT",
    "sg:province":"Friesland",
    "wof:name":"S-Print",
    "wof:placetype":"venue"
},
  "geometry": {"coordinates":[5.991853,53.326965],"type":"Point"}
}