{
  "type": "Feature",
  "properties": {
    "addr:full":"Stationstraat 171 Nuth Limburg 6361 BH",
    "addr:housenumber":"171",
    "addr:postcode":"6361 bh",
    "addr:street":"Stationstraat",
    "iso:country":"NL",
    "sg:address":"Stationstraat 171",
    "sg:city":"Nuth",
    "sg:orig_category":"Banken And Kredietinstellingen",
    "sg:phone":"+31 45 560 1701",
    "sg:postcode":"6361 BH",
    "sg:province":"Limburg",
    "wof:name":"Rabobank",
    "wof:placetype":"venue"
},
  "geometry": {"coordinates":[5.885999,50.918785],"type":"Point"}
}