{
  "type": "Feature",
  "properties": {
    "addr:full":"Schagerln 18 Amsterdam North Holland 1097 HR",
    "addr:housenumber":"18",
    "addr:postcode":"1097 hr",
    "addr:street":"Schagerln",
    "iso:country":"NL",
    "sg:address":"Schagerln 18",
    "sg:city":"Amsterdam",
    "sg:orig_category":"Verenigingen En Stichtingen",
    "sg:phone":"+31 20 465 3806",
    "sg:postcode":"1097 HR",
    "sg:province":"North Holland",
    "wof:name":"Ornis",
    "wof:placetype":"venue"
},
  "geometry": {"coordinates":[4.89319,52.373119],"type":"Point"}
}