{
  "type": "Feature",
  "properties": {
    "addr:full":"De Tienden 38 Nuenen Noord-Brabant 5674 TB",
    "addr:housenumber":"38",
    "addr:postcode":"5674 tb",
    "addr:street":"De Tienden",
    "iso:country":"NL",
    "sg:address":"De Tienden 38",
    "sg:city":"Nuenen",
    "sg:orig_category":"Autokeuringen",
    "sg:phone":"+31 40 283 5181",
    "sg:postcode":"5674 TB",
    "sg:province":"Noord-Brabant",
    "wof:name":"Motorservice Ad Van Den Boomen Bv",
    "wof:placetype":"venue"
},
  "geometry": {"coordinates":[5.552417,51.450165],"type":"Point"}
}