{
  "type": "Feature",
  "properties": {
    "addr:full":"Kleine Houtstraat 26 Haarlem Noord-Holland 2011 DM",
    "addr:housenumber":"26",
    "addr:postcode":"2011 dm",
    "addr:street":"Kleine Houtstraat",
    "iso:country":"NL",
    "sg:address":"Kleine Houtstraat 26",
    "sg:city":"Haarlem",
    "sg:orig_category":"Kappers",
    "sg:phone":"+31 23 532 0681",
    "sg:postcode":"2011 DM",
    "sg:province":"Noord-Holland",
    "wof:name":"City Hair",
    "wof:placetype":"venue"
},
  "geometry": {"coordinates":[4.636356,52.379017],"type":"Point"}
}