{
  "type": "Feature",
  "properties": {
    "iso:country":"NL",
    "sg:address":"Pr Beatrixln 6",
    "sg:city":"Waddinxveen",
    "sg:orig_category":"Administratie- En Boekhoudkantoren",
    "sg:phone":"+31 182 641 414",
    "sg:postcode":"2741 DH",
    "sg:province":"Zuid-Holland",
    "sg:website":"http://www.vanderlooadvies.nl",
    "wof:name":"Loo Bv Administratiekantoor, V/D",
    "wof:placetype":"venue"
},
  "geometry": {"coordinates":[4.650945,52.04723],"type":"Point"}
}