{
  "type": "Feature",
  "properties": {
    "addr:full":"Jhr. Von Heijdenstraat 17 Haaksbergen NL.08 7481 EC",
    "addr:housenumber":"17;nl.08",
    "addr:postcode":"7481 ec",
    "addr:street":"Jhr. Von Heijdenstraat",
    "iso:country":"NL",
    "sg:address":"Jhr. Von Heijdenstraat 17",
    "sg:city":"Haaksbergen",
    "sg:orig_category":"Damesmodezaken",
    "sg:phone":"+31 53 572 7835",
    "sg:postcode":"7481 EC",
    "sg:province":"NL.08",
    "wof:name":"Modehuis Mensink",
    "wof:placetype":"venue"
},
  "geometry": {"coordinates":[6.74443,52.154167],"type":"Point"}
}