{
  "type": "Feature",
  "properties": {
    "addr:full":"T Veld 23 Almelo Overijssel 7603 EC",
    "addr:housenumber":"23",
    "addr:postcode":"7603 ec",
    "addr:street":"T Veld",
    "iso:country":"NL",
    "sg:address":"T Veld 23",
    "sg:city":"Almelo",
    "sg:orig_category":"Autorijscholen",
    "sg:phone":"+31 546 861 438",
    "sg:postcode":"7603 EC",
    "sg:province":"Overijssel",
    "wof:name":"Veldhuis",
    "wof:placetype":"venue"
},
  "geometry": {"coordinates":[6.664543,52.354954],"type":"Point"}
}