{
  "type": "Feature",
  "properties": {
    "addr:full":"Lyndraaier 37 Hoorn Nh Noord-Holland 1625 ZL",
    "addr:housenumber":"37",
    "addr:postcode":"1625 zl",
    "addr:street":"Lyndraaier",
    "iso:country":"NL",
    "sg:address":"Lyndraaier 37",
    "sg:city":"Hoorn Nh",
    "sg:orig_category":"Adviesbureaus Bedrijfsorganisatie",
    "sg:phone":"+31 229 243 507",
    "sg:postcode":"1625 ZL",
    "sg:province":"Noord-Holland",
    "wof:name":"Bvmd",
    "wof:placetype":"venue"
},
  "geometry": {"coordinates":[5.049278,52.651478],"type":"Point"}
}