{
  "type": "Feature",
  "properties": {
    "addr:full":"Bernarduswg 12 Lage Mierde Noord-Brabant 5094 GK",
    "addr:housenumber":"12",
    "addr:postcode":"5094 gk",
    "addr:street":"Bernarduswg",
    "iso:country":"NL",
    "sg:address":"Bernarduswg 12",
    "sg:city":"Lage Mierde",
    "sg:orig_category":"Verenigingsgebouwen",
    "sg:phone":"+31 13 509 1615",
    "sg:postcode":"5094 GK",
    "sg:province":"Noord-Brabant",
    "wof:name":"Ster, De",
    "wof:placetype":"venue"
},
  "geometry": {"coordinates":[5.151143,51.406418],"type":"Point"}
}