{
  "type": "Feature",
  "properties": {
    "iso:country":"NL",
    "sg:address":"Raadhuisstr 10A",
    "sg:city":"Hillegom",
    "sg:orig_category":"Fietsen En Bromfietsen",
    "sg:phone":"+31 252 522 387",
    "sg:postcode":"2181 AT",
    "sg:province":"Zuid-Holland",
    "wof:name":"Edwin Groen, Tweewielers",
    "wof:placetype":"venue"
},
  "geometry": {"coordinates":[4.580169,52.291885],"type":"Point"}
}