{
  "type": "Feature",
  "properties": {
    "addr:full":"Zuidplasln 426 Waddinxveen Zuid-Holland 2743 KE",
    "addr:housenumber":"426",
    "addr:postcode":"waddinxveen;2743 ke",
    "iso:country":"NL",
    "sg:address":"Zuidplasln 426",
    "sg:city":"Waddinxveen",
    "sg:orig_category":"Verzekeringen - Verzekeringskantoren",
    "sg:phone":"+31 182 622 388",
    "sg:postcode":"2743 KE",
    "sg:province":"Zuid-Holland",
    "sg:website":"http://www.dgep.nl",
    "wof:name":"Graaf & Partner, De",
    "wof:placetype":"venue"
},
  "geometry": {"coordinates":[4.636811,52.036655],"type":"Point"}
}