{
  "type": "Feature",
  "properties": {
    "addr:full":"Prof Jordanln 74 Utrecht Utrecht 3571 KB",
    "addr:housenumber":"74",
    "addr:postcode":"3571 kb",
    "iso:country":"NL",
    "sg:address":"Prof Jordanln 74",
    "sg:city":"Utrecht",
    "sg:classifiers":[
        {
            "category":"Retail",
            "subcategory":"Auto Repair",
            "type":"Services"
        }
    ],
    "sg:phone":"+31 30 271 4767",
    "sg:postcode":"3571 KB",
    "sg:province":"Utrecht",
    "sg:tags":[
        "garage"
    ],
    "wof:name":"Jordan",
    "wof:placetype":"venue"
},
  "geometry": {"coordinates":[5.1331,52.106686],"type":"Point"}
}