{
  "type": "Feature",
  "properties": {
    "iso:country":"NL",
    "sg:address":"Loeswyk 17",
    "sg:city":"Mierlo",
    "sg:orig_category":"Honden- En Kattentrimsalons",
    "sg:phone":"+31 492 432 440",
    "sg:postcode":"5731 VK",
    "sg:province":"Noord-Brabant",
    "wof:name":"Loeswijk Hondentrimsalon",
    "wof:placetype":"venue"
},
  "geometry": {"coordinates":[5.619782,51.4436],"type":"Point"}
}