{
  "type": "Feature",
  "properties": {
    "addr:full":"Hantumerweg 28 Dokkum Provincie Friesland 9101 AB",
    "addr:housenumber":"28",
    "addr:postcode":"9101 ab",
    "addr:street":"Hantumerweg;Provincie Friesland",
    "iso:country":"NL",
    "sg:address":"Hantumerweg 28",
    "sg:city":"Dokkum",
    "sg:classifiers":[
        {
            "category":"Education",
            "subcategory":"Preschool",
            "type":"Public Place"
        }
    ],
    "sg:phone":"+31 519 292 474",
    "sg:postcode":"9101 AB",
    "sg:province":"Provincie Friesland",
    "sg:tags":[
        "kleuteronderwijs",
        "basis-"
    ],
    "wof:name":"Haezer Chr Basisschool Eben",
    "wof:placetype":"venue"
},
  "geometry": {"coordinates":[5.99846,53.331039],"type":"Point"}
}