{
  "type": "Feature",
  "properties": {
    "iso:country":"NL",
    "sg:address":"Parkweg 381",
    "sg:city":"Hellevoetsluis",
    "sg:classifiers":[
        {
            "category":"Fast Food",
            "type":"Food & Drink"
        }
    ],
    "sg:phone":"+31 6 53354235",
    "sg:postcode":"3221 LV",
    "sg:province":"South Holland",
    "sg:tags":[
        "afhaal",
        "restaurant"
    ],
    "wof:name":"Jean-Paul Ladage Verse Patat",
    "wof:placetype":"venue"
},
  "geometry": {"coordinates":[4.09131,51.838943],"type":"Point"}
}