{
  "type": "Feature",
  "properties": {
    "iso:country":"NL",
    "sg:address":"Veilingstraat 1",
    "sg:city":"Enschede",
    "sg:orig_category":"Airconditioning And Ventilatie",
    "sg:phone":"+31 53 430 0444",
    "sg:postcode":"7545 LZ",
    "sg:province":"Overijssel",
    "wof:name":"P & R Verhuur Enschede Bv",
    "wof:placetype":"venue"
},
  "geometry": {"coordinates":[6.871217,52.217113],"type":"Point"}
}