{
  "type": "Feature",
  "properties": {
    "iso:country":"NL",
    "sg:address":"V Brederodestr 6",
    "sg:city":"Gilze",
    "sg:classifiers":[
        {
            "category":"Personal",
            "subcategory":"Nail Salon",
            "type":"Services"
        }
    ],
    "sg:phone":"+31 161 456 140",
    "sg:postcode":"5126 HZ",
    "sg:province":"Noord-Brabant",
    "sg:tags":[
        "pedicure"
    ],
    "wof:name":"Paulissen, A",
    "wof:placetype":"venue"
},
  "geometry": {"coordinates":[4.942423,51.541756],"type":"Point"}
}