{
  "type": "Feature",
  "properties": {
    "addr:full":"Middelburgsewg 1 Reeuwyk Zuid-Holland 2811 PL",
    "addr:housenumber":"1",
    "addr:postcode":"2811 pl",
    "addr:street":"Middelburgsewg",
    "iso:country":"NL",
    "sg:address":"Middelburgsewg 1",
    "sg:city":"Reeuwyk",
    "sg:orig_category":"Bloemen En Planten",
    "sg:phone":"+31 182 395 044",
    "sg:postcode":"2811 PL",
    "sg:province":"Zuid-Holland",
    "wof:name":"Boezem, De",
    "wof:placetype":"venue"
},
  "geometry": {"coordinates":[4.67978,52.051811],"type":"Point"}
}