{
  "type": "Feature",
  "properties": {
    "addr:full":"Oudewg 65 Marknesse Flevoland 8316 AD",
    "addr:housenumber":"65",
    "addr:postcode":"8316 ad",
    "addr:street":"Oudewg;Flevoland",
    "iso:country":"NL",
    "sg:address":"Oudewg 65",
    "sg:city":"Marknesse",
    "sg:orig_category":"Bloemisterijartikelen - Fabrieken En Groothandel",
    "sg:phone":"+31 527 201 297",
    "sg:postcode":"8316 AD",
    "sg:province":"Flevoland",
    "sg:website":"HTTP://www.brouwer-europarenco.nl",
    "wof:name":"Brouwer Europarenco Vof",
    "wof:placetype":"venue"
},
  "geometry": {"coordinates":[5.869925,52.711666],"type":"Point"}
}