{
  "type": "Feature",
  "properties": {
    "iso:country":"NL",
    "sg:address":"Westerstraat 130",
    "sg:city":"Delft",
    "sg:orig_category":"Bedrijfs- And Managementsconsultants",
    "sg:phone":"+31 15 213 6217",
    "sg:postcode":"2613 RL",
    "sg:province":"South Holland",
    "wof:name":"Salomon",
    "wof:placetype":"venue"
},
  "geometry": {"coordinates":[4.352577,52.006607],"type":"Point"}
}