{
  "type": "Feature",
  "properties": {
    "addr:full":"Middelweg 28 Nieuw Lekkerland Zuid-Holland 2957 TG",
    "addr:housenumber":"28",
    "addr:postcode":"2957 tg",
    "addr:street":"Middelweg",
    "iso:country":"NL",
    "sg:address":"Middelweg 28",
    "sg:city":"Nieuw Lekkerland",
    "sg:orig_category":"Metaalwerken",
    "sg:phone":"+31 184 684 128",
    "sg:postcode":"2957 TG",
    "sg:province":"Zuid-Holland",
    "wof:name":"L. Holleman Montage",
    "wof:placetype":"venue"
},
  "geometry": {"coordinates":[4.665203,51.885929],"type":"Point"}
}