{
  "type": "Feature",
  "properties": {
    "addr:full":"Monseigneur Geurtsstraat 41 Maashees Noord-Brabant 5823 AC",
    "addr:housenumber":"41",
    "addr:postcode":"5823 ac",
    "addr:street":"Monseigneur Geurtsstraat",
    "iso:country":"NL",
    "sg:address":"Monseigneur Geurtsstraat 41",
    "sg:city":"Maashees",
    "sg:orig_category":"Huisdierenvoer Fab",
    "sg:phone":"+31 478 638 238",
    "sg:postcode":"5823 AC",
    "sg:province":"Noord-Brabant",
    "wof:name":"Havens Graanhandel Nv",
    "wof:placetype":"venue"
},
  "geometry": {"coordinates":[6.031785,51.571381],"type":"Point"}
}