{
  "type": "Feature",
  "properties": {
    "iso:country":"NL",
    "sg:address":"Engstr 4",
    "sg:city":"Heusden Gem Heusd",
    "sg:orig_category":"Herenkleding",
    "sg:phone":"+31 416 665 290",
    "sg:postcode":"5256 BD",
    "sg:province":"Noord-Brabant",
    "wof:name":"Bonte Schaep, Het",
    "wof:placetype":"venue"
},
  "geometry": {"coordinates":[5.13721,51.73444],"type":"Point"}
}