{
  "type": "Feature",
  "properties": {
    "addr:full":"Distelstraat 6 Groesbeek Gelderland 6561 DB",
    "addr:housenumber":"6",
    "addr:postcode":"6561 db",
    "addr:street":"Distelstraat;Gelderland",
    "iso:country":"NL",
    "sg:address":"Distelstraat 6",
    "sg:city":"Groesbeek",
    "sg:orig_category":"Kappers",
    "sg:phone":"+31 24 397 6716",
    "sg:postcode":"6561 DB",
    "sg:province":"Gelderland",
    "wof:name":"P.J.J.M. Smulders-Eemers",
    "wof:placetype":"venue"
},
  "geometry": {"coordinates":[5.921307,51.784142],"type":"Point"}
}