{
  "type": "Feature",
  "properties": {
    "addr:full":"Havenstr 5 Veendam Groningen 9641 BP",
    "addr:housenumber":"5",
    "addr:postcode":"9641 bp",
    "addr:street":"Havenstr",
    "iso:country":"NL",
    "sg:address":"Havenstr 5",
    "sg:city":"Veendam",
    "sg:orig_category":"Arbo- En Bedrijfsgezondheids- Diensten",
    "sg:phone":"+31 598 696 777",
    "sg:postcode":"9641 BP",
    "sg:province":"Groningen",
    "wof:name":"Arbo -Dienst Noord Bv",
    "wof:placetype":"venue"
},
  "geometry": {"coordinates":[6.885684,53.107246],"type":"Point"}
}