{
  "type": "Feature",
  "properties": {
    "iso:country":"NL",
    "sg:address":"Meulenberg 12",
    "sg:city":"Ossendrecht",
    "sg:classifiers":[
        {
            "category":"Personal",
            "subcategory":"Nail Salon",
            "type":"Services"
        }
    ],
    "sg:phone":"+31 164 673 215",
    "sg:postcode":"4641 CL",
    "sg:province":"North Brabant",
    "sg:tags":[
        "pedicure"
    ],
    "wof:name":"Sebrechts-Den Ouden, L",
    "wof:placetype":"venue"
},
  "geometry": {"coordinates":[4.331309,51.394512],"type":"Point"}
}