{
  "type": "Feature",
  "properties": {
    "addr:full":"Herengr 495 Amsterdam Noord-Holland 1017 BT",
    "addr:housenumber":"495",
    "addr:postcode":"1017 bt",
    "iso:country":"NL",
    "sg:address":"Herengr 495",
    "sg:city":"Amsterdam",
    "sg:orig_category":"Reisbureaus",
    "sg:phone":"+31 20 626 1325",
    "sg:postcode":"1017 BT",
    "sg:province":"Noord-Holland",
    "wof:name":"Pacific Island Travel",
    "wof:placetype":"venue"
},
  "geometry": {"coordinates":[4.891268,52.365677],"type":"Point"}
}