{
  "type": "Feature",
  "properties": {
    "addr:full":"Zwolsmanweg 2 Sneek Friesland 8606 KC",
    "addr:housenumber":"2",
    "addr:postcode":"8606 kc",
    "addr:street":"Zwolsmanweg",
    "iso:country":"NL",
    "sg:address":"Zwolsmanweg 2",
    "sg:city":"Sneek",
    "sg:orig_category":"Metaalbekleding And -Behandeling",
    "sg:phone":"+31 515 431 414",
    "sg:postcode":"8606 KC",
    "sg:province":"Friesland",
    "wof:name":"Tj. Tjalsma Rvs",
    "wof:placetype":"venue"
},
  "geometry": {"coordinates":[5.697563,53.021271],"type":"Point"}
}