{
  "type": "Feature",
  "properties": {
    "addr:full":"De Raat 12 Winkelcentrum Het Rond Houten Utrecht 3995 EP",
    "addr:housenumber":"12",
    "addr:postcode":"3995 ep",
    "addr:street":"De Raat;Het Rond Houten",
    "iso:country":"NL",
    "sg:address":"De Raat 12 Winkelcentrum Het Rond",
    "sg:city":"Houten",
    "sg:orig_category":"Opticiens",
    "sg:phone":"+31 30 637 5570",
    "sg:postcode":"3995 EP",
    "sg:province":"Utrecht",
    "wof:name":"Vecht Optiek, Van De",
    "wof:placetype":"venue"
},
  "geometry": {"coordinates":[5.1694350243,52.0365409851],"type":"Point"}
}