{
  "type": "Feature",
  "properties": {
    "addr:full":"Weth Potstr 1 Vriezenveen NL.08 7671 HK",
    "addr:housenumber":"1;nl.08",
    "addr:postcode":"7671 hk",
    "addr:street":"Weth Potstr",
    "iso:country":"NL",
    "sg:address":"Weth Potstr 1",
    "sg:city":"Vriezenveen",
    "sg:orig_category":"Verloskundigen",
    "sg:phone":"+31 546 567 755",
    "sg:postcode":"7671 HK",
    "sg:province":"NL.08",
    "wof:name":"Verloskundige Praktijk Vriezenveen",
    "wof:placetype":"venue"
},
  "geometry": {"coordinates":[6.62829,52.410248],"type":"Point"}
}