{
  "type": "Feature",
  "properties": {
    "addr:full":"Oostdam 16 Steenbergen Nb Noord-Brabant 4651 AW",
    "addr:housenumber":"16",
    "addr:postcode":"4651 aw",
    "addr:street":"Oostdam",
    "iso:country":"NL",
    "sg:address":"Oostdam 16",
    "sg:city":"Steenbergen Nb",
    "sg:orig_category":"Koeriersdiensten",
    "sg:phone":"+31 167 566 912",
    "sg:postcode":"4651 AW",
    "sg:province":"Noord-Brabant",
    "wof:name":"Multiroute",
    "wof:placetype":"venue"
},
  "geometry": {"coordinates":[4.314555,51.585594],"type":"Point"}
}