{
  "type": "Feature",
  "properties": {
    "addr:full":"Hoofdweg 165 Bellingwolde Groningen 9695 AE",
    "addr:housenumber":"165",
    "addr:postcode":"9695 ae",
    "addr:street":"Hoofdweg",
    "iso:country":"NL",
    "sg:address":"Hoofdweg 165",
    "sg:city":"Bellingwolde",
    "sg:orig_category":"Bloemen And Planten",
    "sg:phone":"+31 597 532 283",
    "sg:postcode":"9695 AE",
    "sg:province":"Groningen",
    "wof:name":"Vof Mourus",
    "wof:placetype":"venue"
},
  "geometry": {"coordinates":[7.163115,53.11348],"type":"Point"}
}