{
  "type": "Feature",
  "properties": {
    "addr:full":"Brabantse Turfmarkt 62 Delft South Holland 2611 CP",
    "addr:housenumber":"62",
    "addr:postcode":"2611 cp",
    "addr:street":"Brabantse Turfmarkt",
    "iso:country":"NL",
    "sg:address":"Brabantse Turfmarkt 62",
    "sg:city":"Delft",
    "sg:orig_category":"Fotozaken",
    "sg:phone":"+31 15 212 0325",
    "sg:postcode":"2611 CP",
    "sg:province":"South Holland",
    "wof:name":"Dekker",
    "wof:placetype":"venue"
},
  "geometry": {"coordinates":[4.361128,52.00988],"type":"Point"}
}