{
  "type": "Feature",
  "properties": {
    "addr:full":"Grt Houtstr 139-141 Haarlem North Holland 2011 SK",
    "addr:housenumber":"139-141",
    "addr:street":"2011",
    "iso:country":"NL",
    "sg:address":"Grt Houtstr 139-141",
    "sg:city":"Haarlem",
    "sg:orig_category":"Wintersportkleding En -Artikelen",
    "sg:phone":"+31 23 531 0135",
    "sg:postcode":"2011 SK",
    "sg:province":"North Holland",
    "wof:name":"Sport 'N Styles",
    "wof:placetype":"venue"
},
  "geometry": {"coordinates":[4.6319527626,52.3774833679],"type":"Point"}
}