{
  "type": "Feature",
  "properties": {
    "iso:country":"NL",
    "sg:address":"1E Vd Helststr 67",
    "sg:city":"Amsterdam",
    "sg:orig_category":"Messen En Scharen - Winkels",
    "sg:phone":"+31 20 662 6347",
    "sg:postcode":"1073 AD",
    "sg:province":"New York",
    "wof:name":"Moes, Fa L",
    "wof:placetype":"venue"
},
  "geometry": {"coordinates":[-74.071022,42.973381],"type":"Point"}
}