{
  "type": "Feature",
  "properties": {
    "iso:country":"NL",
    "sg:address":"Hooiland 14",
    "sg:city":"Urk",
    "sg:orig_category":"Visspeciaalzaken",
    "sg:phone":"+31 527 687 047",
    "sg:postcode":"8321 CX",
    "sg:province":"Flevoland",
    "wof:name":"S. Snoek",
    "wof:placetype":"venue"
},
  "geometry": {"coordinates":[5.612112,52.667233],"type":"Point"}
}