{
  "type": "Feature",
  "properties": {
    "addr:full":"K Nieuwstr 3 Hulst Zeeland 4561 AX",
    "addr:housenumber":"3",
    "addr:postcode":"4561 ax",
    "addr:street":"Nieuwstr",
    "iso:country":"NL",
    "sg:address":"K Nieuwstr 3",
    "sg:city":"Hulst",
    "sg:orig_category":"Opticiens",
    "sg:phone":"+31 114 312 327",
    "sg:postcode":"4561 AX",
    "sg:province":"Zeeland",
    "wof:name":"Bosch Optiek",
    "wof:placetype":"venue"
},
  "geometry": {"coordinates":[4.0531020164,51.2806625366],"type":"Point"}
}