{
  "type": "Feature",
  "properties": {
    "iso:country":"NL",
    "sg:address":"Tuinmanslaan 24",
    "sg:city":"Apeldoorn",
    "sg:orig_category":"Fruitteelt",
    "sg:phone":"+31 55 521 7002",
    "sg:postcode":"7315 HJ",
    "sg:province":"Gelderland",
    "wof:name":"T.J.M. Bouwman",
    "wof:placetype":"venue"
},
  "geometry": {"coordinates":[5.95014,52.2365],"type":"Point"}
}