{
  "type": "Feature",
  "properties": {
    "addr:full":"Bylmerpln 150 Amsterdam Zuidoost North Holland 1102 DB",
    "addr:housenumber":"150",
    "addr:postcode":"1102 db",
    "iso:country":"NL",
    "sg:address":"Bylmerpln 150",
    "sg:city":"Amsterdam Zuidoost",
    "sg:orig_category":"Kappers",
    "sg:phone":"+31 20 696 8548",
    "sg:postcode":"1102 DB",
    "sg:province":"North Holland",
    "sg:website":"http://www.cosmo.nl/",
    "wof:name":"Cosmo",
    "wof:placetype":"venue"
},
  "geometry": {"coordinates":[4.9513149261,52.3161659241],"type":"Point"}
}