{
  "type": "Feature",
  "properties": {
    "iso:country":"NL",
    "sg:address":"Spui 10A",
    "sg:city":"Amsterdam",
    "sg:orig_category":"Zalenverhuur",
    "sg:phone":"+31 20 622 1967",
    "sg:postcode":"1012 WZ",
    "sg:province":"North Holland",
    "wof:name":"Esprit Caff?",
    "wof:placetype":"venue"
},
  "geometry": {"coordinates":[4.890654,52.369015],"type":"Point"}
}