{
  "type": "Feature",
  "properties": {
    "addr:full":"Hoofdstr 76 Hoensbroek Limburg 6432 GG",
    "addr:housenumber":"76",
    "addr:postcode":"6432 gg",
    "addr:street":"Hoofdstr",
    "iso:country":"NL",
    "sg:address":"Hoofdstr 76",
    "sg:city":"Hoensbroek",
    "sg:orig_category":"Kaas",
    "sg:phone":"+31 45 522 8794",
    "sg:postcode":"6432 GG",
    "sg:province":"Limburg",
    "wof:name":"Kaasstolpke, 'T",
    "wof:placetype":"venue"
},
  "geometry": {"coordinates":[5.923555851,50.9232940674],"type":"Point"}
}