{
  "type": "Feature",
  "properties": {
    "addr:full":"Appelstraat 184 'S Gravenhage South Holland 2564 EK",
    "addr:housenumber":"184 '",
    "addr:postcode":"2564 ek",
    "addr:street":"Appelstraat",
    "iso:country":"NL",
    "sg:address":"Appelstraat 184",
    "sg:city":"'S Gravenhage",
    "sg:orig_category":"Verzekeringen",
    "sg:phone":"+31 70 325 0806",
    "sg:postcode":"2564 EK",
    "sg:province":"South Holland",
    "wof:name":"Burg Assurantien Bv",
    "wof:placetype":"venue"
},
  "geometry": {"coordinates":[4.253488,52.066013],"type":"Point"}
}