{
  "type": "Feature",
  "properties": {
    "iso:country":"NL",
    "sg:address":"Groenedk 6",
    "sg:city":"Oost Graftdyk",
    "sg:orig_category":"Zalenverhuur",
    "sg:phone":"+31 75 641 1262",
    "sg:postcode":"1487 ME",
    "sg:province":"Noord-Holland",
    "wof:name":"Rietbos",
    "wof:placetype":"venue"
},
  "geometry": {"coordinates":[4.810263,52.546963],"type":"Point"}
}