{
  "type": "Feature",
  "properties": {
    "addr:full":"Maarsbergseweg 47 Leersum Utrecht 3956 KT",
    "addr:housenumber":"47",
    "addr:postcode":"3956 kt",
    "addr:street":"Maarsbergseweg",
    "iso:country":"NL",
    "sg:address":"Maarsbergseweg 47",
    "sg:city":"Leersum",
    "sg:orig_category":"Diverse Bedrijfsinstallaties Gh",
    "sg:phone":"+31 343 456 114",
    "sg:postcode":"3956 KT",
    "sg:province":"Utrecht",
    "wof:name":"Technische Handelsonderneming Linders",
    "wof:placetype":"venue"
},
  "geometry": {"coordinates":[5.416695,52.027454],"type":"Point"}
}