{
  "type": "Feature",
  "properties": {
    "addr:full":"John F Kennedyplein 1 Purmerend Noord-Holland 1443 EA",
    "addr:housenumber":"1",
    "addr:postcode":"1443 ea",
    "addr:street":"John F Kennedyplein",
    "iso:country":"NL",
    "sg:address":"John F Kennedyplein 1",
    "sg:city":"Purmerend",
    "sg:orig_category":"Boekhandels",
    "sg:phone":"+31 299 424 952",
    "sg:postcode":"1443 EA",
    "sg:province":"Noord-Holland",
    "wof:name":"H.L. Van Oostrom En Compagnon Cv",
    "wof:placetype":"venue"
},
  "geometry": {"coordinates":[4.968428,52.508678],"type":"Point"}
}