{
  "type": "Feature",
  "properties": {
    "addr:full":"Graslaan 44 Arnhem Gelderland 6833 CK",
    "addr:housenumber":"44",
    "addr:postcode":"6833 ck",
    "addr:street":"Graslaan",
    "iso:country":"NL",
    "sg:address":"Graslaan 44",
    "sg:city":"Arnhem",
    "sg:orig_category":"Meubelreparatie And -Restauratie",
    "sg:phone":"+31 26 322 9717",
    "sg:postcode":"6833 CK",
    "sg:province":"Gelderland",
    "wof:name":"J & R Stoffeerbedrijf",
    "wof:placetype":"venue"
},
  "geometry": {"coordinates":[5.910858,51.969627],"type":"Point"}
}