{
  "type": "Feature",
  "properties": {
    "addr:full":"Coehoornstr 8 Arnhem Gelderland 6811 LA",
    "addr:housenumber":"8",
    "addr:postcode":"6811 la",
    "addr:street":"Coehoornstr",
    "iso:country":"NL",
    "sg:address":"Coehoornstr 8",
    "sg:city":"Arnhem",
    "sg:orig_category":"Onroerende Goederen",
    "sg:phone":"+31 26 443 2130",
    "sg:postcode":"6811 LA",
    "sg:province":"Gelderland",
    "wof:name":"Coehoorn Staete Bv, De",
    "wof:placetype":"venue"
},
  "geometry": {"coordinates":[5.901224,51.983105],"type":"Point"}
}