{
  "type": "Feature",
  "properties": {
    "addr:full":"Postbus 306 Ijsselstein Ut 3400 AH",
    "addr:housenumber":"306",
    "addr:postcode":"3400 ah",
    "addr:street":"Postbus",
    "iso:country":"NL",
    "sg:address":"Postbus 306",
    "sg:city":"Ijsselstein Ut",
    "sg:orig_category":"Psychotherapeuten",
    "sg:phone":"+31 30 688 5764",
    "sg:postcode":"3400 AH",
    "wof:name":"Chi-Up",
    "wof:placetype":"venue"
},
  "geometry": {"coordinates":[5.04266,52.01704],"type":"Point"}
}