{
  "type": "Feature",
  "properties": {
    "addr:full":"Kaart 4 Terschelling Kaart Friesland 8883 HD",
    "addr:housenumber":"4",
    "addr:postcode":"8883 hd",
    "addr:street":"Kaart",
    "iso:country":"NL",
    "sg:address":"Kaart 4",
    "sg:city":"Terschelling Kaart",
    "sg:classifiers":[
        {
            "category":"Travel",
            "subcategory":"Hotels & Motels",
            "type":"Entertainment"
        }
    ],
    "sg:phone":"+31 562 448 200",
    "sg:postcode":"8883 HD",
    "sg:province":"Friesland",
    "wof:name":"Horper Wielen, De",
    "wof:placetype":"venue"
},
  "geometry": {"coordinates":[5.27111,53.376823],"type":"Point"}
}