{
  "type": "Feature",
  "properties": {
    "iso:country":"NL",
    "sg:address":"Kamperdk 3",
    "sg:city":"Genemuiden",
    "sg:orig_category":"Verenigingen En Stichtingen",
    "sg:phone":"+31 38 385 4577",
    "sg:postcode":"8281 PB",
    "sg:province":"Overijssel",
    "wof:name":"Zwartewaterruiters",
    "wof:placetype":"venue"
},
  "geometry": {"coordinates":[6.035892,52.61618],"type":"Point"}
}