{
  "type": "Feature",
  "properties": {
    "addr:full":"Posthoornsbredeh 10 Zwolle NL.08 8011 XB",
    "addr:housenumber":"10",
    "addr:postcode":"8011 xb",
    "addr:street":"Posthoornsbredeh",
    "iso:country":"NL",
    "sg:address":"Posthoornsbredeh 10",
    "sg:city":"Zwolle",
    "sg:orig_category":"Kappers",
    "sg:phone":"+31 38 423 3654",
    "sg:postcode":"8011 XB",
    "sg:province":"NL.08",
    "wof:name":"Hair Unlimited",
    "wof:placetype":"venue"
},
  "geometry": {"coordinates":[6.0957918167,52.5150489807],"type":"Point"}
}