{
  "type": "Feature",
  "properties": {
    "iso:country":"NL",
    "sg:address":"Maanhuizenlaan 10",
    "sg:city":"Marknesse",
    "sg:orig_category":"Sportcentra",
    "sg:phone":"+31 527 203 385",
    "sg:postcode":"8316 AB",
    "sg:province":"Flevoland",
    "wof:name":"Sporthal Triangel",
    "wof:placetype":"venue"
},
  "geometry": {"coordinates":[5.864498,52.708179],"type":"Point"}
}