{
  "type": "Feature",
  "properties": {
    "addr:full":"Wilgstraat 47 'S Gravenhage Zuid-Holland 2565 MB",
    "addr:housenumber":"47",
    "addr:postcode":"2565 mb",
    "addr:street":"Wilgstraat;' S",
    "iso:country":"NL",
    "sg:address":"Wilgstraat 47",
    "sg:city":"'S Gravenhage",
    "sg:orig_category":"Drukkerijen And Copyshops",
    "sg:phone":"+31 70 360 0257",
    "sg:postcode":"2565 MB",
    "sg:province":"Zuid-Holland",
    "wof:name":"Drukkerij/Boek - En Kantoorboekhandel Al",
    "wof:placetype":"venue"
},
  "geometry": {"coordinates":[4.271677,52.07983],"type":"Point"}
}