{
  "type": "Feature",
  "properties": {
    "addr:full":"Hoofdwg 6 Midwolda Groningen 9681 AH",
    "addr:housenumber":"6",
    "addr:postcode":"9681 ah",
    "addr:street":"Hoofdwg",
    "iso:country":"NL",
    "sg:address":"Hoofdwg 6",
    "sg:city":"Midwolda",
    "sg:orig_category":"Grondwerken",
    "sg:phone":"+31 597 593 382",
    "sg:postcode":"9681 AH",
    "sg:province":"Groningen",
    "wof:name":"Ahlers, R",
    "wof:placetype":"venue"
},
  "geometry": {"coordinates":[6.987311,53.189339],"type":"Point"}
}