{
  "type": "Feature",
  "properties": {
    "addr:full":"Wilhelminastr 15C Mynsheerenland Zuid-Holland 3271 BX",
    "addr:housenumber":"15c",
    "addr:postcode":"3271 bx",
    "addr:street":"Wilhelminastr",
    "iso:country":"NL",
    "sg:address":"Wilhelminastr 15C",
    "sg:city":"Mynsheerenland",
    "sg:orig_category":"Kappers",
    "sg:phone":"+31 186 603 637",
    "sg:postcode":"3271 BX",
    "sg:province":"Zuid-Holland",
    "wof:name":"Ingrid",
    "wof:placetype":"venue"
},
  "geometry": {"coordinates":[4.4924650192,51.7975997925],"type":"Point"}
}