{
  "type": "Feature",
  "properties": {
    "addr:full":"Hoogeind 2 Casteren Noord-Brabant 5529 NB",
    "addr:housenumber":"2",
    "addr:postcode":"5529 nb",
    "addr:street":"Hoogeind",
    "iso:country":"NL",
    "sg:address":"Hoogeind 2",
    "sg:city":"Casteren",
    "sg:orig_category":"Adviesbureaus Bedrijfsorganisatie",
    "sg:phone":"+31 497 684 044",
    "sg:postcode":"5529 NB",
    "sg:province":"Noord-Brabant",
    "wof:name":"Benne Fit",
    "wof:placetype":"venue"
},
  "geometry": {"coordinates":[5.241374,51.399719],"type":"Point"}
}