{
  "type": "Feature",
  "properties": {
    "addr:full":"Wieldrechtstr 19 Rotterdam South Holland 3081 EK",
    "addr:housenumber":"19",
    "addr:postcode":"3081 ek",
    "addr:street":"Wieldrechtstr",
    "iso:country":"NL",
    "sg:address":"Wieldrechtstr 19",
    "sg:city":"Rotterdam",
    "sg:orig_category":"Kinderopvang",
    "sg:phone":"+31 10 484 8620",
    "sg:postcode":"3081 EK",
    "sg:province":"South Holland",
    "wof:name":"Wieltje, 'T",
    "wof:placetype":"venue"
},
  "geometry": {"coordinates":[4.49235,51.895477],"type":"Point"}
}