{
  "type": "Feature",
  "properties": {
    "iso:country":"NL",
    "sg:address":"Vermeerstraat 9",
    "sg:city":"Eerbeek",
    "sg:orig_category":"Beautyfarms And Sauna'S",
    "sg:phone":"+31 313 651 717",
    "sg:postcode":"6961 ZC",
    "sg:province":"Gelderland",
    "wof:name":"Liesbeth Zonnestudio",
    "wof:placetype":"venue"
},
  "geometry": {"coordinates":[6.052511,52.10408],"type":"Point"}
}