{
  "type": "Feature",
  "properties": {
    "addr:full":"De Trompet 18B Enkhuizen Noord-Holland 1601 MK",
    "addr:housenumber":"18b",
    "addr:postcode":"1601",
    "addr:street":"De Trompet",
    "iso:country":"NL",
    "sg:address":"De Trompet 18B",
    "sg:city":"Enkhuizen",
    "sg:orig_category":"Letters - Fabrieken En Groothandel",
    "sg:phone":"+31 228 592 437",
    "sg:postcode":"1601 MK",
    "sg:province":"Noord-Holland",
    "sg:website":"http://www.marcstyl.nl",
    "wof:name":"Marc Style",
    "wof:placetype":"venue"
},
  "geometry": {"coordinates":[5.2677,52.692894],"type":"Point"}
}