{
  "type": "Feature",
  "properties": {
    "iso:country":"NL",
    "sg:address":"Kernwg 20",
    "sg:city":"Hoorn Nh",
    "sg:orig_category":"Veiligheidsuitrusting En -Kleding",
    "sg:phone":"+31 229 250 303",
    "sg:postcode":"1627 LH",
    "sg:province":"North Holland",
    "sg:website":"http://www.msaned.nl",
    "wof:name":"Msa Nederland Bv",
    "wof:placetype":"venue"
},
  "geometry": {"coordinates":[5.099705,52.639061],"type":"Point"}
}