{
  "type": "Feature",
  "properties": {
    "addr:full":"Postbus 82259 S Gravenhage Flevoland 2508 EG",
    "addr:housenumber":"82259",
    "addr:postcode":"2508 eg",
    "addr:street":"Postbus;S Gravenhage Flevoland",
    "iso:country":"NL",
    "sg:address":"Postbus 82259",
    "sg:city":"S Gravenhage",
    "sg:orig_category":"Begrafenisverzorging",
    "sg:phone":"+31 70 350 7000",
    "sg:postcode":"2508 EG",
    "sg:province":"Flevoland",
    "sg:website":"http://www.engelenuitvaartverzorging,nl",
    "wof:name":"Engelen",
    "wof:placetype":"venue"
},
  "geometry": {"coordinates":[4.31361,52.07832],"type":"Point"}
}