{
  "type": "Feature",
  "properties": {
    "addr:full":"Sorghvlietln 51 Andyk Noord-Holland 1619 XA",
    "addr:housenumber":"51",
    "addr:postcode":"1619 xa",
    "addr:street":"Sorghvlietln",
    "iso:country":"NL",
    "sg:address":"Sorghvlietln 51",
    "sg:city":"Andyk",
    "sg:orig_category":"Wereldwinkels",
    "sg:phone":"+31 228 596 776",
    "sg:postcode":"1619 XA",
    "sg:province":"Noord-Holland",
    "wof:name":"Wereldwinkel",
    "wof:placetype":"venue"
},
  "geometry": {"coordinates":[5.2225251198,52.7443618774],"type":"Point"}
}