{
  "type": "Feature",
  "properties": {
    "addr:full":"K Doormanstr 35A Arnhem Gelderland 6826 RC",
    "addr:housenumber":"35a",
    "addr:postcode":"6826 rc",
    "addr:street":"Doormanstr",
    "iso:country":"NL",
    "sg:address":"K Doormanstr 35A",
    "sg:city":"Arnhem",
    "sg:orig_category":"Fietsen En Bromfietsen",
    "sg:phone":"+31 6 51852914",
    "sg:postcode":"6826 RC",
    "sg:province":"Gelderland",
    "wof:name":"Arnhemse Rijwielservice",
    "wof:placetype":"venue"
},
  "geometry": {"coordinates":[5.95546,51.97924],"type":"Point"}
}