{
  "type": "Feature",
  "properties": {
    "addr:full":"Pieter Jacobszdwstr 15 Amsterdam Noord-Holland 1012 HK",
    "addr:housenumber":"15",
    "addr:postcode":"1012 hk",
    "addr:street":"Pieter Jacobszdwstr",
    "iso:country":"NL",
    "sg:address":"Pieter Jacobszdwstr 15",
    "sg:city":"Amsterdam",
    "sg:orig_category":"Drukkerijen And Copyshops",
    "sg:phone":"+31 20 620 8770",
    "sg:postcode":"1012 HK",
    "sg:province":"Noord-Holland",
    "wof:name":"Stilett",
    "wof:placetype":"venue"
},
  "geometry": {"coordinates":[4.894653,52.371834],"type":"Point"}
}