{
  "type": "Feature",
  "properties": {
    "addr:full":"Sniedersln 55 Bladel Noord-Brabant 5531 EH",
    "addr:housenumber":"55",
    "addr:postcode":"5531 eh",
    "addr:street":"Sniedersln",
    "iso:country":"NL",
    "sg:address":"Sniedersln 55",
    "sg:city":"Bladel",
    "sg:orig_category":"Makelaars En Adviseurs Onroerende Goederen",
    "sg:phone":"+31 497 369 898",
    "sg:postcode":"5531 EH",
    "sg:province":"Noord-Brabant",
    "sg:website":"http://www.roblommers.nl",
    "wof:name":"Rob Lommers & Nathalie V Gisbergen",
    "wof:placetype":"venue"
},
  "geometry": {"coordinates":[5.221196,51.367901],"type":"Point"}
}