{
  "type": "Feature",
  "properties": {
    "addr:full":"Welhoeksedk 2A Poortugaal South Holland 3171 TB",
    "addr:housenumber":"2a",
    "addr:postcode":"3171 tb",
    "addr:street":"Welhoeksedk",
    "iso:country":"NL",
    "sg:address":"Welhoeksedk 2A",
    "sg:city":"Poortugaal",
    "sg:orig_category":"Bloemen En Planten",
    "sg:phone":"+31 10 501 5929",
    "sg:postcode":"3171 TB",
    "sg:province":"South Holland",
    "wof:name":"Tournesol",
    "wof:placetype":"venue"
},
  "geometry": {"coordinates":[4.388852,51.855137],"type":"Point"}
}