{
  "type": "Feature",
  "properties": {
    "addr:full":"1E Johannastr 68 Apeldoorn Gelderland 7331 CD",
    "addr:housenumber":"68",
    "addr:postcode":"7331 cd",
    "addr:street":"1E Johannastr;Gelderland",
    "iso:country":"NL",
    "sg:address":"1E Johannastr 68",
    "sg:city":"Apeldoorn",
    "sg:orig_category":"Organisatiebureaus",
    "sg:phone":"+31 55 533 9522",
    "sg:postcode":"7331 CD",
    "sg:province":"Gelderland",
    "wof:name":"Evers",
    "wof:placetype":"venue"
},
  "geometry": {"coordinates":[5.9639167786,52.2054901123],"type":"Point"}
}