{
  "type": "Feature",
  "properties": {
    "addr:full":"Nieuwendijk 94 Someren North Brabant 5712 EN",
    "addr:housenumber":"94",
    "addr:postcode":"5712 en",
    "addr:street":"Nieuwendijk",
    "iso:country":"NL",
    "sg:address":"Nieuwendijk 94",
    "sg:city":"Someren",
    "sg:orig_category":"Verzekeringen",
    "sg:phone":"+31 493 440 151",
    "sg:postcode":"5712 EN",
    "sg:province":"North Brabant",
    "wof:name":"Assurantiebedrijf H M G Koenders",
    "wof:placetype":"venue"
},
  "geometry": {"coordinates":[5.723523,51.349525],"type":"Point"}
}