{
  "type": "Feature",
  "properties": {
    "addr:full":"Wilhelminastr 4 Haelen Limburg 6081 GA",
    "addr:housenumber":"4",
    "addr:postcode":"6081 ga",
    "addr:street":"Wilhelminastr",
    "iso:country":"NL",
    "sg:address":"Wilhelminastr 4",
    "sg:city":"Haelen",
    "sg:orig_category":"Kappers",
    "sg:phone":"+31 475 319 563",
    "sg:postcode":"6081 GA",
    "sg:province":"Limburg",
    "wof:name":"Kuijpers, W C J",
    "wof:placetype":"venue"
},
  "geometry": {"coordinates":[5.957284,51.23991],"type":"Point"}
}