{
  "type": "Feature",
  "properties": {
    "addr:full":"Huigendijk 3 Ursem Noord-Holland 1645 RD",
    "addr:housenumber":"3",
    "addr:postcode":"1645 rd",
    "addr:street":"Huigendijk",
    "iso:country":"NL",
    "sg:address":"Huigendijk 3",
    "sg:city":"Ursem",
    "sg:classifiers":[
        {
            "category":"Travel",
            "subcategory":"Hotels & Motels",
            "type":"Entertainment"
        }
    ],
    "sg:phone":"+31 72 502 1282",
    "sg:postcode":"1645 RD",
    "sg:province":"Noord-Holland",
    "wof:name":"De Gouden Karper",
    "wof:placetype":"venue"
},
  "geometry": {"coordinates":[4.875567,52.634777],"type":"Point"}
}