{
  "type": "Feature",
  "properties": {
    "addr:full":"Emmeriksewg 52 Zutphen Gelderland 7204 SM",
    "addr:housenumber":"52",
    "addr:postcode":"7204 sm",
    "addr:street":"Emmeriksewg;Gelderland",
    "iso:country":"NL",
    "sg:address":"Emmeriksewg 52",
    "sg:city":"Zutphen",
    "sg:classifiers":[
        {
            "category":"Food & Beverages",
            "subcategory":"Bakery",
            "type":"Retail Goods"
        }
    ],
    "sg:phone":"+31 575 522 784",
    "sg:postcode":"7204 SM",
    "sg:province":"Gelderland",
    "sg:tags":[
        "pizza"
    ],
    "wof:name":"Da Enzo",
    "wof:placetype":"venue"
},
  "geometry": {"coordinates":[6.202463,52.133701],"type":"Point"}
}