{
  "type": "Feature",
  "properties": {
    "iso:country":"NL",
    "sg:address":"Pieter Langendijkstraat 57",
    "sg:city":"Amsterdam",
    "sg:orig_category":"Kappers",
    "sg:phone":"+31 20 612 6841",
    "sg:postcode":"1054 XZ",
    "sg:province":"North Holland",
    "wof:name":"P.C. Breemer",
    "wof:placetype":"venue"
},
  "geometry": {"coordinates":[4.861911,52.359634],"type":"Point"}
}