{
  "type": "Feature",
  "properties": {
    "addr:full":"Rembrandtstr 17A Krimpen A/D Lek Zuid-Holland 2931 CZ",
    "addr:housenumber":"17a;a / d",
    "addr:postcode":"2931",
    "addr:street":"Rembrandtstr",
    "iso:country":"NL",
    "sg:address":"Rembrandtstr 17A",
    "sg:city":"Krimpen A/D Lek",
    "sg:orig_category":"Woningbouw- Verenigingen En -Stichtingen",
    "sg:phone":"+31 180 511 471",
    "sg:postcode":"2931 CZ",
    "sg:province":"Zuid-Holland",
    "wof:name":"Ons Belang",
    "wof:placetype":"venue"
},
  "geometry": {"coordinates":[4.6306061745,51.8967399597],"type":"Point"}
}