{
  "type": "Feature",
  "properties": {
    "addr:full":"Meyery 24 Riel North Brabant 5133 CT",
    "addr:housenumber":"24",
    "addr:postcode":"5133 ct",
    "addr:street":"Meyery",
    "iso:country":"NL",
    "sg:address":"Meyery 24",
    "sg:city":"Riel",
    "sg:orig_category":"Verenigingen En Stichtingen",
    "sg:phone":"+31 13 518 2157",
    "sg:postcode":"5133 CT",
    "sg:province":"North Brabant",
    "wof:name":"Amarant, Sticht",
    "wof:placetype":"venue"
},
  "geometry": {"coordinates":[5.023561,51.526455],"type":"Point"}
}