{
  "type": "Feature",
  "properties": {
    "addr:full":"Zaanstr 18 Winschoten Groningen 9673 CC",
    "addr:housenumber":"18",
    "addr:postcode":"9673 cc",
    "addr:street":"Zaanstr",
    "iso:country":"NL",
    "sg:address":"Zaanstr 18",
    "sg:city":"Winschoten",
    "sg:orig_category":"Nagelstudio'S",
    "sg:phone":"+31 597 422 197",
    "sg:postcode":"9673 CC",
    "sg:province":"Groningen",
    "wof:name":"Johanna",
    "wof:placetype":"venue"
},
  "geometry": {"coordinates":[7.02917,53.135956],"type":"Point"}
}