{
  "type": "Feature",
  "properties": {
    "addr:full":"Ridderkerkpad 1 Arnhem Gelderland 6843 JV",
    "addr:housenumber":"1",
    "addr:postcode":"6843 jv",
    "addr:street":"Ridderkerkpad",
    "iso:country":"NL",
    "sg:address":"Ridderkerkpad 1",
    "sg:city":"Arnhem",
    "sg:orig_category":"Kappers",
    "sg:phone":"+31 26 382 0859",
    "sg:postcode":"6843 JV",
    "sg:province":"Gelderland",
    "wof:name":"Haarmode Kreatief",
    "wof:placetype":"venue"
},
  "geometry": {"coordinates":[5.858812809,51.9586486816],"type":"Point"}
}