{
  "type": "Feature",
  "properties": {
    "addr:full":"Distelvinkenpln 4 S Gravenhage South Holland 2566 GH",
    "addr:housenumber":"4",
    "addr:postcode":"2566 gh",
    "addr:street":"Distelvinkenpln;S Gravenhage",
    "iso:country":"NL",
    "sg:address":"Distelvinkenpln 4",
    "sg:city":"S Gravenhage",
    "sg:orig_category":"Kappers",
    "sg:phone":"+31 70 364 4223",
    "sg:postcode":"2566 GH",
    "sg:province":"South Holland",
    "wof:name":"Etienne Coiffure",
    "wof:placetype":"venue"
},
  "geometry": {"coordinates":[4.2555298805,52.0791282654],"type":"Point"}
}