{
  "type": "Feature",
  "properties": {
    "iso:country":"NL",
    "sg:address":"Dorpspln 2",
    "sg:city":"Soesterberg",
    "sg:orig_category":"Manueel Therapeuten",
    "sg:phone":"+31 346 350 335",
    "sg:postcode":"3769 DA",
    "sg:province":"Utrecht",
    "wof:name":"Hoelen",
    "wof:placetype":"venue"
},
  "geometry": {"coordinates":[5.28244,52.118984],"type":"Point"}
}