{
  "type": "Feature",
  "properties": {
    "addr:full":"Fongersplaats 192 Groningen Groningen 9725 LL",
    "addr:housenumber":"192",
    "addr:postcode":"9725 ll",
    "addr:street":"Fongersplaats",
    "iso:country":"NL",
    "sg:address":"Fongersplaats 192",
    "sg:city":"Groningen",
    "sg:orig_category":"Public Relationbureaus",
    "sg:phone":"+31 50 526 4923",
    "sg:postcode":"9725 LL",
    "sg:province":"Groningen",
    "wof:name":"Veenstra Consultancy",
    "wof:placetype":"venue"
},
  "geometry": {"coordinates":[6.571278,53.207874],"type":"Point"}
}