{
  "type": "Feature",
  "properties": {
    "addr:full":"Geysendorfferstraat 13 Helmond Noord-Brabant 5703 GA",
    "addr:housenumber":"13",
    "addr:postcode":"5703 ga",
    "addr:street":"Geysendorfferstraat",
    "iso:country":"NL",
    "sg:address":"Geysendorfferstraat 13",
    "sg:city":"Helmond",
    "sg:orig_category":"Zuivelproducten",
    "sg:phone":"+31 492 545 206",
    "sg:postcode":"5703 GA",
    "sg:province":"Noord-Brabant",
    "wof:name":"T Huukske",
    "wof:placetype":"venue"
},
  "geometry": {"coordinates":[5.6799,51.481258],"type":"Point"}
}