{
  "type": "Feature",
  "properties": {
    "addr:full":"Jachtln 278 Apeldoorn Gelderland 7312 GT",
    "addr:housenumber":"278",
    "addr:postcode":"7312 gt",
    "addr:street":"Gelderland",
    "iso:country":"NL",
    "sg:address":"Jachtln 278",
    "sg:city":"Apeldoorn",
    "sg:orig_category":"Verzekeringen - Verzekeringskantoren",
    "sg:phone":"+31 55 355 7755",
    "sg:postcode":"7312 GT",
    "sg:province":"Gelderland",
    "wof:name":"Dorgelo Bv",
    "wof:placetype":"venue"
},
  "geometry": {"coordinates":[5.93318,52.209259],"type":"Point"}
}