{
  "type": "Feature",
  "properties": {
    "iso:country":"NL",
    "sg:address":"Loosterwg 3-5",
    "sg:city":"Voorhout",
    "sg:orig_category":"Woninginrichting",
    "sg:phone":"+31 252 210 898",
    "sg:postcode":"2215 TL",
    "sg:province":"Zuid-Holland",
    "wof:name":"Top Floor",
    "wof:placetype":"venue"
},
  "geometry": {"coordinates":[4.5115180016,52.2430915833],"type":"Point"}
}