{
  "type": "Feature",
  "properties": {
    "addr:full":"Edisonweg 4 Tholen Zeeland 4691 RB",
    "addr:housenumber":"4",
    "addr:postcode":"4691 rb",
    "addr:street":"Edisonweg",
    "iso:country":"NL",
    "sg:address":"Edisonweg 4",
    "sg:city":"Tholen",
    "sg:orig_category":"Vers Brood And Banket Fab",
    "sg:phone":"+31 166 602 754",
    "sg:postcode":"4691 RB",
    "sg:province":"Zeeland",
    "wof:name":"De Waal Banket Bv",
    "wof:placetype":"venue"
},
  "geometry": {"coordinates":[4.22508,51.53577],"type":"Point"}
}