{
  "type": "Feature",
  "properties": {
    "addr:full":"Voorstraat 23 Woudenberg Utrecht 3931 HB",
    "addr:housenumber":"23",
    "addr:postcode":"3931 hb",
    "addr:street":"Voorstraat",
    "iso:country":"NL",
    "sg:address":"Voorstraat 23",
    "sg:city":"Woudenberg",
    "sg:orig_category":"Opticiens",
    "sg:phone":"+31 33 286 2991",
    "sg:postcode":"3931 HB",
    "sg:province":"Utrecht",
    "wof:name":"Valkenburg Optiek Bv",
    "wof:placetype":"venue"
},
  "geometry": {"coordinates":[5.4126219749,52.0822906494],"type":"Point"}
}