{
  "type": "Feature",
  "properties": {
    "iso:country":"NL",
    "sg:address":"Reitsepln 1",
    "sg:city":"Tilburg",
    "sg:orig_category":"Bedrijfsorganisaties",
    "sg:phone":"+31 13 594 4466",
    "sg:postcode":"5037 AA",
    "sg:province":"North Brabant",
    "wof:name":"Vut Voor Wasserijbedrijven",
    "wof:placetype":"venue"
},
  "geometry": {"coordinates":[5.062885,51.56086],"type":"Point"}
}