{
  "type": "Feature",
  "properties": {
    "addr:full":"P M Van Gentstraat 23 Leerdam South Holland 4142 BM",
    "addr:housenumber":"23",
    "addr:postcode":"4142 bm",
    "addr:street":"P M Van Gentstraat",
    "iso:country":"NL",
    "sg:address":"P M Van Gentstraat 23",
    "sg:city":"Leerdam",
    "sg:orig_category":"Verenigingen En Stichtingen",
    "sg:phone":"+31 6 50816815",
    "sg:postcode":"4142 BM",
    "sg:province":"South Holland",
    "wof:name":"Vogelvriend, De",
    "wof:placetype":"venue"
},
  "geometry": {"coordinates":[5.080648,51.893047],"type":"Point"}
}