{
  "type": "Feature",
  "properties": {
    "iso:country":"NL",
    "sg:address":"Flevoweg 4",
    "sg:city":"Leiden",
    "sg:orig_category":"Glaszetten",
    "sg:phone":"+31 71 522 3439",
    "sg:postcode":"2318 BZ",
    "sg:province":"South Holland",
    "wof:name":"Van Muiden Glas",
    "wof:placetype":"venue"
},
  "geometry": {"coordinates":[4.497536,52.173969],"type":"Point"}
}