{
  "type": "Feature",
  "properties": {
    "addr:full":"Julianastraat 49 Poeldijk Zuid-Holland 2685 BB",
    "addr:housenumber":"49",
    "addr:postcode":"2685 bb",
    "addr:street":"Julianastraat",
    "iso:country":"NL",
    "sg:address":"Julianastraat 49",
    "sg:city":"Poeldijk",
    "sg:orig_category":"Verenigingsgebouwen",
    "sg:phone":"+31 174 246 330",
    "sg:postcode":"2685 BB",
    "sg:province":"Zuid-Holland",
    "wof:name":"Leuningjes, De",
    "wof:placetype":"venue"
},
  "geometry": {"coordinates":[4.215826,52.024906],"type":"Point"}
}