{
  "type": "Feature",
  "properties": {
    "addr:full":"Hegewei 25 Hemelum Friesland 8584 VK",
    "addr:housenumber":"25",
    "addr:postcode":"8584 vk",
    "addr:street":"Hegewei",
    "iso:country":"NL",
    "sg:address":"Hegewei 25",
    "sg:city":"Hemelum",
    "sg:orig_category":"Drukkerijen And Copyshops",
    "sg:phone":"+31 514 581 998",
    "sg:postcode":"8584 VK",
    "sg:province":"Friesland",
    "wof:name":"Vof Van Stroe",
    "wof:placetype":"venue"
},
  "geometry": {"coordinates":[5.459012,52.881565],"type":"Point"}
}