{
  "type": "Feature",
  "properties": {
    "addr:full":"Nw Westerdokstr 100 Amsterdam North Holland 1013 AG",
    "addr:housenumber":"100",
    "addr:postcode":"1013",
    "iso:country":"NL",
    "sg:address":"Nw Westerdokstr 100",
    "sg:city":"Amsterdam",
    "sg:orig_category":"Loopbaanbegeleiding",
    "sg:phone":"+31 20 625 3577",
    "sg:postcode":"1013 AG",
    "sg:province":"North Holland",
    "wof:name":"Ketelaars, Anke",
    "wof:placetype":"venue"
},
  "geometry": {"coordinates":[4.892689,52.380905],"type":"Point"}
}