{
  "type": "Feature",
  "properties": {
    "addr:full":"Uniastate 67 Eindhoven Noord-Brabant 5655 HH",
    "addr:housenumber":"67",
    "addr:postcode":"5655 hh",
    "addr:street":"Uniastate",
    "iso:country":"NL",
    "sg:address":"Uniastate 67",
    "sg:city":"Eindhoven",
    "sg:orig_category":"Fotostudio'S And Fotografen",
    "sg:phone":"+31 40 252 6439",
    "sg:postcode":"5655 HH",
    "sg:province":"Noord-Brabant",
    "wof:name":"Fotografie Henk Selder",
    "wof:placetype":"venue"
},
  "geometry": {"coordinates":[5.437537,51.41367],"type":"Point"}
}