{
  "type": "Feature",
  "properties": {
    "addr:full":"Snoekstr 14 Helmond Noord-Brabant 5706 BZ",
    "addr:housenumber":"14",
    "addr:postcode":"5706 bz",
    "addr:street":"Snoekstr",
    "iso:country":"NL",
    "sg:address":"Snoekstr 14",
    "sg:city":"Helmond",
    "sg:orig_category":"Parketvloeren",
    "sg:phone":"+31 492 549 791",
    "sg:postcode":"5706 BZ",
    "sg:province":"Noord-Brabant",
    "wof:name":"Greef Parketvloeren, De",
    "wof:placetype":"venue"
},
  "geometry": {"coordinates":[5.635143,51.460159],"type":"Point"}
}