{
  "type": "Feature",
  "properties": {
    "addr:full":"Cesar Franckrode 79 Zoetermeer South Holland 2717 BC",
    "addr:housenumber":"79",
    "addr:postcode":"2717 bc",
    "addr:street":"Cesar Franckrode",
    "iso:country":"NL",
    "sg:address":"Cesar Franckrode 79",
    "sg:city":"Zoetermeer",
    "sg:orig_category":"Elektronische Bedrijfsinstallaties",
    "sg:phone":"+31 79 351 4305",
    "sg:postcode":"2717 BC",
    "sg:province":"South Holland",
    "wof:name":"Rsmcartronics",
    "wof:placetype":"venue"
},
  "geometry": {"coordinates":[4.469998,52.068932],"type":"Point"}
}