{
  "type": "Feature",
  "properties": {
    "iso:country":"NL",
    "sg:address":"Wassenaarstraat 17",
    "sg:city":"Schiedam",
    "sg:orig_category":"Boekenuitgeverijen",
    "sg:phone":"+31 10 426 7351",
    "sg:postcode":"3117 PD",
    "sg:province":"South Holland",
    "wof:name":"Pol For Music",
    "wof:placetype":"venue"
},
  "geometry": {"coordinates":[4.387451,51.912525],"type":"Point"}
}