{
  "type": "Feature",
  "properties": {
    "iso:country":"NL",
    "sg:address":"Wilde Wingerdln 8",
    "sg:city":"Gouda",
    "sg:orig_category":"Modevakscholen",
    "sg:phone":"+31 182 572 549",
    "sg:postcode":"2803 WC",
    "sg:province":"South Holland",
    "wof:name":"Movon",
    "wof:placetype":"venue"
},
  "geometry": {"coordinates":[4.694986,52.024181],"type":"Point"}
}