{
  "type": "Feature",
  "properties": {
    "addr:full":"Fazantstr 46 Ommen Overijssel 7731 ZA",
    "addr:housenumber":"46",
    "addr:postcode":"7731",
    "addr:street":"Fazantstr",
    "iso:country":"NL",
    "sg:address":"Fazantstr 46",
    "sg:city":"Ommen",
    "sg:orig_category":"Administratie- En Boekhoudkantoren",
    "sg:phone":"+31 529 451 101",
    "sg:postcode":"7731 ZA",
    "sg:province":"Overijssel",
    "wof:name":"Lohuis, G A J",
    "wof:placetype":"venue"
},
  "geometry": {"coordinates":[6.41163,52.52681],"type":"Point"}
}