{
  "type": "Feature",
  "properties": {
    "iso:country":"NL",
    "sg:address":"Capelsewg 33",
    "sg:city":"Capelle Ad Yssel",
    "sg:orig_category":"Verenigingsgebouwen",
    "sg:phone":"+31 10 450 0273",
    "sg:postcode":"2907 XA",
    "sg:province":"Zuid-Holland",
    "wof:name":"Hockeycl Capelle",
    "wof:placetype":"venue"
},
  "geometry": {"coordinates":[4.574772,51.941498],"type":"Point"}
}