{
  "type": "Feature",
  "properties": {
    "addr:full":"Lindenlaan 35 Alkmaar North Holland 1815 HC",
    "addr:housenumber":"35",
    "addr:postcode":"1815 hc",
    "addr:street":"Lindenlaan",
    "iso:country":"NL",
    "sg:address":"Lindenlaan 35",
    "sg:city":"Alkmaar",
    "sg:classifiers":[
        {
            "category":"Fast Food",
            "type":"Food & Drink"
        }
    ],
    "sg:phone":"+31 72 515 2472",
    "sg:postcode":"1815 HC",
    "sg:province":"North Holland",
    "sg:tags":[
        "afhaal",
        "restaurant"
    ],
    "wof:name":"Willem Schut",
    "wof:placetype":"venue"
},
  "geometry": {"coordinates":[4.737575,52.630066],"type":"Point"}
}