{
  "type": "Feature",
  "properties": {
    "addr:full":"Kon Julianawg 26A Maasland Zuid-Holland 3155 XD",
    "addr:housenumber":"26a",
    "addr:postcode":"3155 xd",
    "addr:street":"Kon",
    "iso:country":"NL",
    "sg:address":"Kon Julianawg 26A",
    "sg:city":"Maasland",
    "sg:orig_category":"Architecten En Architectenbureaus",
    "sg:phone":"+31 10 592 8843",
    "sg:postcode":"3155 XD",
    "sg:province":"Zuid-Holland",
    "wof:name":"Rassel Bv, Van",
    "wof:placetype":"venue"
},
  "geometry": {"coordinates":[4.268625,51.929977],"type":"Point"}
}