{
  "type": "Feature",
  "properties": {
    "addr:full":"Beiroetdreef 5 Utrecht Utrecht 3564 XC",
    "addr:housenumber":"5",
    "addr:postcode":"3564 xc",
    "addr:street":"Beiroetdreef",
    "iso:country":"NL",
    "sg:address":"Beiroetdreef 5",
    "sg:city":"Utrecht",
    "sg:classifiers":[
        {
            "category":"Education",
            "subcategory":"Preschool",
            "type":"Public Place"
        }
    ],
    "sg:phone":"+31 30 261 6234",
    "sg:postcode":"3564 XC",
    "sg:province":"Utrecht",
    "sg:tags":[
        "kleuteronderwijs",
        "basis-"
    ],
    "wof:name":"Openbare Basisschool Overvecht Locatie M",
    "wof:placetype":"venue"
},
  "geometry": {"coordinates":[5.101249,52.126106],"type":"Point"}
}