{
  "type": "Feature",
  "properties": {
    "addr:full":"Molenraai 7 Sappemeer Groningen 9611 TH",
    "addr:housenumber":"7",
    "addr:postcode":"9611 th",
    "addr:street":"Molenraai",
    "iso:country":"NL",
    "sg:address":"Molenraai 7",
    "sg:city":"Sappemeer",
    "sg:orig_category":"Horecabenodigdheden",
    "sg:phone":"+31 598 382 158",
    "sg:postcode":"9611 TH",
    "sg:province":"Groningen",
    "sg:website":"http://www.vanderveensnacks.nl",
    "wof:name":"Veen Snacks, Van Der",
    "wof:placetype":"venue"
},
  "geometry": {"coordinates":[6.813463,53.161388],"type":"Point"}
}