{
  "type": "Feature",
  "properties": {
    "iso:country":"NL",
    "sg:address":"Nieuwehaven 148-152",
    "sg:city":"Gouda",
    "sg:orig_category":"Muziekinstrumenten En Bladmuziek",
    "sg:phone":"+31 182 527 616",
    "sg:postcode":"2801 EC",
    "sg:province":"South Holland",
    "sg:website":"http://www.opus1.nl",
    "wof:name":"Opus 1 Vof, Muziekhandel",
    "wof:placetype":"venue"
},
  "geometry": {"coordinates":[4.706951,52.013123],"type":"Point"}
}