{
  "type": "Feature",
  "properties": {
    "addr:full":"Kapperswg 1 Spankeren Ohio 6956 CC",
    "addr:housenumber":"1",
    "addr:postcode":"6956 cc",
    "addr:street":"Kapperswg",
    "iso:country":"NL",
    "sg:address":"Kapperswg 1",
    "sg:city":"Spankeren",
    "sg:orig_category":"Beeldende Kunstenaars",
    "sg:phone":"+31 313 619 576",
    "sg:postcode":"6956 CC",
    "sg:province":"Ohio",
    "wof:name":"Reulink, R G J",
    "wof:placetype":"venue"
},
  "geometry": {"coordinates":[-84.245392,39.856728],"type":"Point"}
}