{
  "type": "Feature",
  "properties": {
    "addr:full":"Zandpad 1 Utrecht Utrecht 3552 TJ",
    "addr:housenumber":"1",
    "addr:postcode":"3552 tj",
    "addr:street":"Zandpad",
    "iso:country":"NL",
    "sg:address":"Zandpad 1",
    "sg:city":"Utrecht",
    "sg:orig_category":"Adviesbureaus Bouwkunde",
    "sg:phone":"+31 30 261 3272",
    "sg:postcode":"3552 TJ",
    "sg:province":"Utrecht",
    "sg:website":"http://www.abocad.demon.nl",
    "wof:name":"Abocad",
    "wof:placetype":"venue"
},
  "geometry": {"coordinates":[5.106979,52.107986],"type":"Point"}
}