{
  "type": "Feature",
  "properties": {
    "iso:country":"NL",
    "sg:address":"Pastoor Oomenlaan 14",
    "sg:city":"Prinsenbeek",
    "sg:orig_category":"Goederenvervoer Over De Weg",
    "sg:phone":"+31 76 541 2513",
    "sg:postcode":"4841 XB",
    "sg:province":"Noord-Brabant",
    "wof:name":"J.H. Maatjens Transport",
    "wof:placetype":"venue"
},
  "geometry": {"coordinates":[4.715379,51.598938],"type":"Point"}
}