{
  "type": "Feature",
  "properties": {
    "iso:country":"NL",
    "sg:address":"Cambridgeln 677",
    "sg:city":"Utrecht",
    "sg:orig_category":"Fotografie Reclame En Mode",
    "sg:phone":"+31 30 254 5785",
    "sg:postcode":"3584 DS",
    "sg:province":"Utrecht",
    "wof:name":"Fic Tomms",
    "wof:placetype":"venue"
},
  "geometry": {"coordinates":[5.172685,52.081802],"type":"Point"}
}