{
  "type": "Feature",
  "properties": {
    "addr:full":"Oranjeboomstr 9 Mill Noord-Brabant 5451 BL",
    "addr:housenumber":"9",
    "addr:postcode":"5451 bl",
    "addr:street":"Oranjeboomstr",
    "iso:country":"NL",
    "sg:address":"Oranjeboomstr 9",
    "sg:city":"Mill",
    "sg:orig_category":"Verenigingen En Stichtingen",
    "sg:phone":"+31 485 451 781",
    "sg:postcode":"5451 BL",
    "sg:province":"Noord-Brabant",
    "sg:website":"http://www.ssomill.nl",
    "wof:name":"Samenlevingsopbouw Mill",
    "wof:placetype":"venue"
},
  "geometry": {"coordinates":[-80.146202,38.164333],"type":"Point"}
}