{
  "type": "Feature",
  "properties": {
    "iso:country":"NL",
    "sg:address":"Cliostr 39",
    "sg:city":"Amsterdam",
    "sg:orig_category":"Geschenkartikelen",
    "sg:phone":"+31 20 679 3438",
    "sg:postcode":"1077 KC",
    "sg:province":"North Holland",
    "sg:website":"http://www.citywalks.nl",
    "wof:name":"Citywalks",
    "wof:placetype":"venue"
},
  "geometry": {"coordinates":[4.875335,52.347324],"type":"Point"}
}