{
  "type": "Feature",
  "properties": {
    "iso:country":"NL",
    "sg:address":"Rijksstraatweg 120",
    "sg:city":"Hellevoetsluis",
    "sg:orig_category":"Meubelzaken, Woning- And Keukeninrichting",
    "sg:phone":"+31 181 312 529",
    "sg:postcode":"3223 KB",
    "sg:province":"Zuid-Holland",
    "wof:name":"Moerman Meubelpromenade Vof",
    "wof:placetype":"venue"
},
  "geometry": {"coordinates":[4.134322,51.838051],"type":"Point"}
}