{
  "type": "Feature",
  "properties": {
    "addr:full":"1E Wormenseweg 25 Apeldoorn Gelderland 7331 DA",
    "addr:housenumber":"25",
    "addr:postcode":"7331 da",
    "addr:street":"1E Wormenseweg;Gelderland",
    "iso:country":"NL",
    "sg:address":"1E Wormenseweg 25",
    "sg:city":"Apeldoorn",
    "sg:orig_category":"Boekenuitgeverijen",
    "sg:phone":"+31 55 533 3497",
    "sg:postcode":"7331 DA",
    "sg:province":"Gelderland",
    "wof:name":"Madrigaal",
    "wof:placetype":"venue"
},
  "geometry": {"coordinates":[5.968003,52.208309],"type":"Point"}
}