{
  "type": "Feature",
  "properties": {
    "iso:country":"NL",
    "sg:address":"Jan Mankeslaan 86",
    "sg:city":"Heerenveen",
    "sg:orig_category":"Boekhouders",
    "sg:phone":"+31 513 624 278",
    "sg:postcode":"8442 HS",
    "sg:province":"Friesland",
    "wof:name":"Administratieburo G. Atsma",
    "wof:placetype":"venue"
},
  "geometry": {"coordinates":[5.934761,52.954685],"type":"Point"}
}