{
  "type": "Feature",
  "properties": {
    "iso:country":"NL",
    "sg:address":"Dwarswg 10",
    "sg:city":"Zaltbommel",
    "sg:orig_category":"Keuringsdiensten",
    "sg:phone":"+31 418 541 021",
    "sg:postcode":"5301 KT",
    "sg:province":"Gelderland",
    "sg:website":"http://www.r2b.nl",
    "wof:name":"R2B Bv",
    "wof:placetype":"venue"
},
  "geometry": {"coordinates":[5.268996,51.811768],"type":"Point"}
}