{
  "type": "Feature",
  "properties": {
    "addr:full":"Touwslager 26 Brunssum Limburg 6444 LC",
    "addr:housenumber":"26",
    "addr:postcode":"6444 lc",
    "addr:street":"Touwslager",
    "iso:country":"NL",
    "sg:address":"Touwslager 26",
    "sg:city":"Brunssum",
    "sg:orig_category":"Onroerende Goederen",
    "sg:phone":"+31 45 527 4939",
    "sg:postcode":"6444 LC",
    "sg:province":"Limburg",
    "wof:name":"Suvo-Development Bv",
    "wof:placetype":"venue"
},
  "geometry": {"coordinates":[5.95262,50.942467],"type":"Point"}
}