{
  "type": "Feature",
  "properties": {
    "addr:full":"Rohofstraat 2 Almelo Overijssel 7605 AV",
    "addr:housenumber":"2",
    "addr:postcode":"7605 av",
    "addr:street":"Rohofstraat",
    "iso:country":"NL",
    "sg:address":"Rohofstraat 2",
    "sg:city":"Almelo",
    "sg:orig_category":"Wasserettes And Stomerijen",
    "sg:phone":"+31 546 814 354",
    "sg:postcode":"7605 AV",
    "sg:province":"Overijssel",
    "wof:name":"Tempo Cleaning Service",
    "wof:placetype":"venue"
},
  "geometry": {"coordinates":[6.6538829803,52.350227356],"type":"Point"}
}