{
  "type": "Feature",
  "properties": {
    "addr:full":"Bylmerdreef 820 Amsterdam Zuidoost Noord-Holland 1103 DT",
    "addr:housenumber":"820",
    "addr:postcode":"zuidoost;1103 dt",
    "iso:country":"NL",
    "sg:address":"Bylmerdreef 820",
    "sg:city":"Amsterdam Zuidoost",
    "sg:orig_category":"Elektronica - Ontwikkeling En Groothandel",
    "sg:phone":"+31 20 773 1226",
    "sg:postcode":"1103 DT",
    "sg:province":"Noord-Holland",
    "sg:website":"http://www.mobiletrackingsystem.com",
    "wof:name":"Nice Engineering",
    "wof:placetype":"venue"
},
  "geometry": {"coordinates":[4.965983,52.320385],"type":"Point"}
}