{
  "type": "Feature",
  "properties": {
    "iso:country":"NL",
    "sg:address":"Broekstraat 30",
    "sg:city":"Bergeyk",
    "sg:orig_category":"Huizensloop And Bouwrijp Maken",
    "sg:phone":"+31 497 571 367",
    "sg:postcode":"5571 KL",
    "sg:province":"North Brabant",
    "wof:name":"H. Vos",
    "wof:placetype":"venue"
},
  "geometry": {"coordinates":[5.354566,51.312836],"type":"Point"}
}