{
  "type": "Feature",
  "properties": {
    "iso:country":"NL",
    "sg:address":"De Amert 210",
    "sg:city":"Veghel",
    "sg:orig_category":"Hijswerktuigen",
    "sg:phone":"+31 413 311 977",
    "sg:postcode":"5462 GH",
    "sg:province":"Noord-Brabant",
    "sg:website":"http://mtc-games.com",
    "wof:name":"Mtc",
    "wof:placetype":"venue"
},
  "geometry": {"coordinates":[5.519116,51.618912],"type":"Point"}
}