{
  "type": "Feature",
  "properties": {
    "iso:country":"NL",
    "sg:address":"Oude Looiersstraat 20",
    "sg:city":"Amsterdam",
    "sg:orig_category":"Fotostudio'S And Fotografen",
    "sg:phone":"+31 20 622 2869",
    "sg:postcode":"1016 VJ",
    "sg:province":"North Holland",
    "wof:name":"Marcel Van Der Vlugt Photography",
    "wof:placetype":"venue"
},
  "geometry": {"coordinates":[4.881655,52.369488],"type":"Point"}
}