{
  "type": "Feature",
  "properties": {
    "addr:full":"Morsweg 188 Leiden Zuid-Holland 2332 ET",
    "addr:housenumber":"188",
    "addr:postcode":"2332 et",
    "addr:street":"Morsweg",
    "iso:country":"NL",
    "sg:address":"Morsweg 188",
    "sg:city":"Leiden",
    "sg:orig_category":"Diverse Bedrijfsinstallaties Gh",
    "sg:phone":"+31 71 531 3931",
    "sg:postcode":"2332 ET",
    "sg:province":"Zuid-Holland",
    "wof:name":"Rob Hasselbach",
    "wof:placetype":"venue"
},
  "geometry": {"coordinates":[4.47231,52.158566],"type":"Point"}
}