{
  "type": "Feature",
  "properties": {
    "addr:full":"Kenaupk 5 Haarlem North Holland 2011 MP",
    "addr:housenumber":"5",
    "addr:postcode":"2011 mp",
    "addr:street":"Kenaupk",
    "iso:country":"NL",
    "sg:address":"Kenaupk 5",
    "sg:city":"Haarlem",
    "sg:orig_category":"Verzekeringen - Verzekeringskantoren",
    "sg:phone":"+31 23 511 2233",
    "sg:postcode":"2011 MP",
    "sg:province":"North Holland",
    "sg:website":"http://www.herenvest.nl",
    "wof:name":"Herenvest Groep",
    "wof:placetype":"venue"
},
  "geometry": {"coordinates":[4.633624,52.387527],"type":"Point"}
}