{
  "type": "Feature",
  "properties": {
    "addr:full":"Herenstr 48 Voorhout Zuid-Holland 2215 KH",
    "addr:housenumber":"48",
    "addr:postcode":"2215 kh",
    "addr:street":"Herenstr",
    "iso:country":"NL",
    "sg:address":"Herenstr 48",
    "sg:city":"Voorhout",
    "sg:orig_category":"Huishoudelijke Apparaten En Artikelen",
    "sg:phone":"+31 252 221 255",
    "sg:postcode":"2215 KH",
    "sg:province":"Zuid-Holland",
    "wof:name":"Blokker Bv",
    "wof:placetype":"venue"
},
  "geometry": {"coordinates":[4.479182,52.21983],"type":"Point"}
}