{
  "type": "Feature",
  "properties": {
    "addr:full":"Geelvinckstr 41 Castricum Noord-Holland 1901 AE",
    "addr:housenumber":"41",
    "addr:postcode":"1901 ae",
    "addr:street":"Geelvinckstr",
    "iso:country":"NL",
    "sg:address":"Geelvinckstr 41",
    "sg:city":"Castricum",
    "sg:orig_category":"Adviesbureaus Bedrijfsorganisatie",
    "sg:phone":"+31 251 652 144",
    "sg:postcode":"1901 AE",
    "sg:province":"Noord-Holland",
    "wof:name":"Sense Of Communication",
    "wof:placetype":"venue"
},
  "geometry": {"coordinates":[4.659592,52.548756],"type":"Point"}
}