{
  "type": "Feature",
  "properties": {
    "addr:full":"Heemskerkstraat 15 Delft South Holland 2613 AK",
    "addr:housenumber":"15",
    "addr:postcode":"2613 ak",
    "addr:street":"Heemskerkstraat",
    "iso:country":"NL",
    "sg:address":"Heemskerkstraat 15",
    "sg:city":"Delft",
    "sg:orig_category":"Paramedische Behandelingen",
    "sg:phone":"+31 15 214 4774",
    "sg:postcode":"2613 AK",
    "sg:province":"South Holland",
    "wof:name":"Logopediepraktijk M.L.C. Van De Meer Knottenbelt",
    "wof:placetype":"venue"
},
  "geometry": {"coordinates":[4.346773,52.014412],"type":"Point"}
}