{
  "type": "Feature",
  "properties": {
    "iso:country":"NL",
    "sg:address":"Loosduinsekd 175",
    "sg:city":"S Gravenhage",
    "sg:orig_category":"Glas",
    "sg:phone":"+31 70 360 3927",
    "sg:postcode":"2571 BW",
    "sg:province":"South Holland",
    "wof:name":"Vlugt Glashandel Vof, Van Der",
    "wof:placetype":"venue"
},
  "geometry": {"coordinates":[4.29037,52.06884],"type":"Point"}
}