{
  "type": "Feature",
  "properties": {
    "iso:country":"NL",
    "sg:address":"Ossekamp 3",
    "sg:city":"Lemmer",
    "sg:orig_category":"Veren - Fabrieken En Groothandel",
    "sg:phone":"+31 514 568 101",
    "sg:postcode":"8531 XK",
    "sg:province":"Friesland",
    "sg:website":"http://www.springfactory.com",
    "wof:name":"Dtv Bv",
    "wof:placetype":"venue"
},
  "geometry": {"coordinates":[5.668781,52.854015],"type":"Point"}
}