{
  "type": "Feature",
  "properties": {
    "addr:full":"Botanicusln 4A Haren Gn Groningen 9751 AC",
    "addr:housenumber":"4a",
    "addr:postcode":"9751 ac",
    "addr:street":"Botanicusln",
    "iso:country":"NL",
    "sg:address":"Botanicusln 4A",
    "sg:city":"Haren Gn",
    "sg:orig_category":"Adviesbureaus Bedrijfsorganisatie",
    "sg:phone":"+31 50 535 1283",
    "sg:postcode":"9751 AC",
    "sg:province":"Groningen",
    "sg:website":"http://www.wijnorganisatieadvies.nl",
    "wof:name":"Wijn",
    "wof:placetype":"venue"
},
  "geometry": {"coordinates":[6.600441,53.177265],"type":"Point"}
}