{
  "type": "Feature",
  "properties": {
    "addr:full":"Molendk 3 Hoek Zeeland 4542 BJ",
    "addr:housenumber":"3",
    "addr:postcode":"4542 bj",
    "addr:street":"Molendk",
    "iso:country":"NL",
    "sg:address":"Molendk 3",
    "sg:city":"Hoek",
    "sg:orig_category":"Drukkerijen",
    "sg:phone":"+31 115 442 397",
    "sg:postcode":"4542 BJ",
    "sg:province":"Zeeland",
    "wof:name":"Polka, Printing",
    "wof:placetype":"venue"
},
  "geometry": {"coordinates":[3.778522,51.309685],"type":"Point"}
}