{
  "type": "Feature",
  "properties": {
    "addr:full":"Rembrandtstr 69 Dongen Noord-Brabant 5102 DK",
    "addr:housenumber":"69",
    "addr:postcode":"5102 dk",
    "addr:street":"Rembrandtstr",
    "iso:country":"NL",
    "sg:address":"Rembrandtstr 69",
    "sg:city":"Dongen",
    "sg:orig_category":"Verenigingsgebouwen",
    "sg:phone":"+31 162 314 631",
    "sg:postcode":"5102 DK",
    "sg:province":"Noord-Brabant",
    "wof:name":"Schouw, 'T",
    "wof:placetype":"venue"
},
  "geometry": {"coordinates":[9.51668,56.2757],"type":"Point"}
}