{
  "type": "Feature",
  "properties": {
    "addr:full":"Broekdijk 46 Kesteren Gelderland 4041 CW",
    "addr:housenumber":"46",
    "addr:postcode":"4041 cw",
    "addr:street":"Broekdijk;Gelderland",
    "iso:country":"NL",
    "sg:address":"Broekdijk 46",
    "sg:city":"Kesteren",
    "sg:orig_category":"Bloemen And Planten",
    "sg:phone":"+31 488 481 601",
    "sg:postcode":"4041 CW",
    "sg:province":"Gelderland",
    "wof:name":"Kuus Tuincentra",
    "wof:placetype":"venue"
},
  "geometry": {"coordinates":[5.57798,51.927517],"type":"Point"}
}