{
  "type": "Feature",
  "properties": {
    "addr:full":"Ruigendijk 24 Oudenhoorn Zuid-Holland 3227 CG",
    "addr:housenumber":"24",
    "addr:postcode":"3227 cg",
    "addr:street":"Ruigendijk",
    "iso:country":"NL",
    "sg:address":"Ruigendijk 24",
    "sg:city":"Oudenhoorn",
    "sg:orig_category":"Binnenhuisarchitecten",
    "sg:phone":"+31 181 461 665",
    "sg:postcode":"3227 CG",
    "sg:province":"Zuid-Holland",
    "wof:name":"Ltb Interieurverzorging Bv",
    "wof:placetype":"venue"
},
  "geometry": {"coordinates":[4.207318,51.81731],"type":"Point"}
}