{
  "type": "Feature",
  "properties": {
    "addr:full":"Holzikwg 12 Enschede Overijssel 7541 PC",
    "addr:housenumber":"12",
    "addr:postcode":"7541 pc",
    "addr:street":"Holzikwg",
    "iso:country":"NL",
    "sg:address":"Holzikwg 12",
    "sg:city":"Enschede",
    "sg:orig_category":"Psychologen",
    "sg:phone":"+31 53 431 1585",
    "sg:postcode":"7541 PC",
    "sg:province":"Overijssel",
    "wof:name":"Eerstelijns Psychologie Praktijk Twente",
    "wof:placetype":"venue"
},
  "geometry": {"coordinates":[6.911613,52.200558],"type":"Point"}
}