{
  "type": "Feature",
  "properties": {
    "addr:full":"Ncb Ln 117A Veghel North Brabant 5462 GC",
    "addr:housenumber":"117a",
    "addr:postcode":"5462 gc",
    "addr:street":"Ncb Ln",
    "iso:country":"NL",
    "sg:address":"Ncb Ln 117A",
    "sg:city":"Veghel",
    "sg:orig_category":"Autopoetsbedrijven",
    "sg:phone":"+31 413 351 289",
    "sg:postcode":"5462 GC",
    "sg:province":"North Brabant",
    "wof:name":"Sonax Car Care Veghel",
    "wof:placetype":"venue"
},
  "geometry": {"coordinates":[5.528348,51.61729],"type":"Point"}
}