{
  "type": "Feature",
  "properties": {
    "addr:full":"Bagijnhof 20 Medemblik Noord-Holland 1671 CD",
    "addr:housenumber":"20",
    "addr:postcode":"1671 cd",
    "addr:street":"Bagijnhof",
    "iso:country":"NL",
    "sg:address":"Bagijnhof 20",
    "sg:city":"Medemblik",
    "sg:orig_category":"Huishoudapparatuur, Televisies And Radio'S",
    "sg:phone":"+31 227 542 185",
    "sg:postcode":"1671 CD",
    "sg:province":"Noord-Holland",
    "wof:name":"Shop Everything",
    "wof:placetype":"venue"
},
  "geometry": {"coordinates":[5.104993,52.772465],"type":"Point"}
}