{
  "type": "Feature",
  "properties": {
    "addr:full":"Oude Haagweg 497 'S Gravenhage South Holland 2552 GG",
    "addr:housenumber":"497 '",
    "addr:postcode":"2552 gg",
    "addr:street":"Oude Haagweg",
    "iso:country":"NL",
    "sg:address":"Oude Haagweg 497",
    "sg:city":"'S Gravenhage",
    "sg:orig_category":"Wasserettes And Stomerijen",
    "sg:phone":"+31 70 368 6464",
    "sg:postcode":"2552 GG",
    "sg:province":"South Holland",
    "wof:name":"Wasserijbedrijf Giezeman De Wasman Bv",
    "wof:placetype":"venue"
},
  "geometry": {"coordinates":[4.2570958138,52.0617675781],"type":"Point"}
}