{
  "type": "Feature",
  "properties": {
    "addr:full":"Hoefboomgaard 12 Maastricht Limburg 6227 ER",
    "addr:housenumber":"12",
    "addr:postcode":"6227 er",
    "addr:street":"Hoefboomgaard",
    "iso:country":"NL",
    "sg:address":"Hoefboomgaard 12",
    "sg:city":"Maastricht",
    "sg:classifiers":[
        {
            "category":"Government",
            "subcategory":"Post Office",
            "type":"Public Place"
        }
    ],
    "sg:phone":"+31 43 356 1200",
    "sg:postcode":"6227 ER",
    "sg:province":"Limburg",
    "sg:tags":[
        "poster"
    ],
    "sg:website":"http://www.A2-art.com",
    "wof:name":"A2 Art",
    "wof:placetype":"venue"
},
  "geometry": {"coordinates":[5.721113,50.833279],"type":"Point"}
}