{
  "type": "Feature",
  "properties": {
    "addr:full":"Lewestraat 43 Kloetinge Zeeland 4481 BC",
    "addr:housenumber":"43",
    "addr:postcode":"4481 bc",
    "addr:street":"Lewestraat",
    "iso:country":"NL",
    "sg:address":"Lewestraat 43",
    "sg:city":"Kloetinge",
    "sg:orig_category":"Loodgieterswerk, Verwarming And Sanitaire Installaties",
    "sg:phone":"+31 113 213 720",
    "sg:postcode":"4481 BC",
    "sg:province":"Zeeland",
    "wof:name":"Colijn Bv",
    "wof:placetype":"venue"
},
  "geometry": {"coordinates":[3.910064,51.497959],"type":"Point"}
}