{
  "type": "Feature",
  "properties": {
    "addr:full":"J Stratiusln 4 Wolfheze Gelderland 6874 AM",
    "addr:housenumber":"4",
    "addr:postcode":"6874",
    "addr:street":"Gelderland",
    "iso:country":"NL",
    "sg:address":"J Stratiusln 4",
    "sg:city":"Wolfheze",
    "sg:orig_category":"Beeldende Kunstenaars",
    "sg:phone":"+31 26 482 1307",
    "sg:postcode":"6874 AM",
    "sg:province":"Gelderland",
    "wof:name":"Wit, Marjon De",
    "wof:placetype":"venue"
},
  "geometry": {"coordinates":[5.794633,52.000156],"type":"Point"}
}