{
  "type": "Feature",
  "properties": {
    "addr:full":"Valkstraat 2 Sneek Friesland 8605 AV",
    "addr:housenumber":"2",
    "addr:postcode":"8605 av",
    "addr:street":"Valkstraat",
    "iso:country":"NL",
    "sg:address":"Valkstraat 2",
    "sg:city":"Sneek",
    "sg:orig_category":"Autokeuringen",
    "sg:phone":"+31 515 413 807",
    "sg:postcode":"8605 AV",
    "sg:province":"Friesland",
    "wof:name":"Autoverhuur En Garage Betten",
    "wof:placetype":"venue"
},
  "geometry": {"coordinates":[5.670045,53.032948],"type":"Point"}
}