{
  "type": "Feature",
  "properties": {
    "iso:country":"NL",
    "sg:address":"Ambachtsweg 28",
    "sg:city":"Pijnacker",
    "sg:orig_category":"Diverse Bedrijfsinstallaties Gh",
    "sg:phone":"+31 15 369 5444",
    "sg:postcode":"2641 KS",
    "sg:province":"Zuid-Holland",
    "wof:name":"Muller Beltex Bv",
    "wof:placetype":"venue"
},
  "geometry": {"coordinates":[4.441749,52.027473],"type":"Point"}
}