{
  "type": "Feature",
  "properties": {
    "addr:full":"Baarsjeswg 206 Amsterdam Noord-Holland 1057 HT",
    "addr:housenumber":"206",
    "addr:postcode":"1057 ht",
    "iso:country":"NL",
    "sg:address":"Baarsjeswg 206",
    "sg:city":"Amsterdam",
    "sg:classifiers":[
        {
            "category":"Retail",
            "subcategory":"Auto Repair",
            "type":"Services"
        }
    ],
    "sg:phone":"+31 20 618 5799",
    "sg:postcode":"1057 HT",
    "sg:province":"Noord-Holland",
    "sg:tags":[
        "garage"
    ],
    "wof:name":"Snel",
    "wof:placetype":"venue"
},
  "geometry": {"coordinates":[4.860135,52.36544],"type":"Point"}
}