{
  "type": "Feature",
  "properties": {
    "iso:country":"NL",
    "sg:address":"Prof Kochstr 55",
    "sg:city":"Hilversum",
    "sg:orig_category":"Verbouwingen",
    "sg:phone":"+31 6 22224993",
    "sg:postcode":"1221 KE",
    "sg:province":"Noord-Holland",
    "wof:name":"Berg",
    "wof:placetype":"venue"
},
  "geometry": {"coordinates":[5.186492,52.225506],"type":"Point"}
}