{
  "type": "Feature",
  "properties": {
    "addr:full":"Meerland 2A Purmerend Noord-Holland 1447 KC",
    "addr:housenumber":"2a",
    "addr:postcode":"1447 kc",
    "addr:street":"Meerland",
    "iso:country":"NL",
    "sg:address":"Meerland 2A",
    "sg:city":"Purmerend",
    "sg:orig_category":"Verzekeringen - Verzekeringskantoren",
    "sg:phone":"+31 299 666 677",
    "sg:postcode":"1447 KC",
    "sg:province":"Noord-Holland",
    "sg:website":"http://www.hetdealeradvies.nl",
    "wof:name":"Dealer Advies, Het",
    "wof:placetype":"venue"
},
  "geometry": {"coordinates":[4.974297,52.492809],"type":"Point"}
}