{
  "type": "Feature",
  "properties": {
    "addr:full":"Brusselsestr 105 Maastricht Limburg 6211 PD",
    "addr:housenumber":"105",
    "addr:postcode":"6211 pd",
    "iso:country":"NL",
    "sg:address":"Brusselsestr 105",
    "sg:city":"Maastricht",
    "sg:orig_category":"Bloemen En Planten",
    "sg:phone":"+31 43 321 7902",
    "sg:postcode":"6211 PD",
    "sg:province":"Limburg",
    "wof:name":"Jar?",
    "wof:placetype":"venue"
},
  "geometry": {"coordinates":[5.680707,50.849472],"type":"Point"}
}