{
  "type": "Feature",
  "properties": {
    "addr:full":"Utrechtsewg 67B Zeist Utrecht 3704 HB",
    "addr:housenumber":"67b",
    "addr:postcode":"3704 hb",
    "addr:street":"Utrechtsewg",
    "iso:country":"NL",
    "sg:address":"Utrechtsewg 67B",
    "sg:city":"Zeist",
    "sg:orig_category":"Adviesbureaus Financieel",
    "sg:phone":"+31 30 636 1260",
    "sg:postcode":"3704 HB",
    "sg:province":"Utrecht",
    "wof:name":"Trimoteur Bv",
    "wof:placetype":"venue"
},
  "geometry": {"coordinates":[5.22518,52.091671],"type":"Point"}
}