{
  "type": "Feature",
  "properties": {
    "iso:country":"NL",
    "sg:address":"C T Storkwg 9",
    "sg:city":"Assen",
    "sg:classifiers":[
        {
            "category":"Retail",
            "subcategory":"Auto Repair",
            "type":"Services"
        }
    ],
    "sg:phone":"+31 592 315 851",
    "sg:postcode":"9403 AG",
    "sg:province":"Drenthe",
    "sg:tags":[
        "garage"
    ],
    "wof:name":"Refat",
    "wof:placetype":"venue"
},
  "geometry": {"coordinates":[6.573112,52.998932],"type":"Point"}
}