{
  "type": "Feature",
  "properties": {
    "addr:full":"Keppelskamp 88 Hattem Gelderland 8051 LZ",
    "addr:housenumber":"88",
    "addr:postcode":"8051 lz",
    "addr:street":"Keppelskamp;Gelderland",
    "iso:country":"NL",
    "sg:address":"Keppelskamp 88",
    "sg:city":"Hattem",
    "sg:orig_category":"Hek- En Rasterwerken",
    "sg:phone":"+31 38 444 8060",
    "sg:postcode":"8051 LZ",
    "sg:province":"Gelderland",
    "sg:website":"http://www.abcelrejo.nl",
    "wof:name":"Abc-Elrejo Bv",
    "wof:placetype":"venue"
},
  "geometry": {"coordinates":[6.051355,52.470242],"type":"Point"}
}