{
  "type": "Feature",
  "properties": {
    "addr:full":"Frambozenwg 147 Leiden Zuid-Holland 2321 KA",
    "addr:housenumber":"147",
    "addr:postcode":"2321 ka",
    "iso:country":"NL",
    "sg:address":"Frambozenwg 147",
    "sg:city":"Leiden",
    "sg:orig_category":"Handelscentra",
    "sg:phone":"+31 71 573 0647",
    "sg:postcode":"2321 KA",
    "sg:province":"Zuid-Holland",
    "wof:name":"Europe Trade Office",
    "wof:placetype":"venue"
},
  "geometry": {"coordinates":[4.488543,52.14716],"type":"Point"}
}