{
  "type": "Feature",
  "properties": {
    "addr:full":"Ootmarsumsestr 18 Rossum Ov Overijssel 7596 NT",
    "addr:housenumber":"18",
    "addr:postcode":"7596 nt",
    "addr:street":"Ootmarsumsestr;Ov",
    "iso:country":"NL",
    "sg:address":"Ootmarsumsestr 18",
    "sg:city":"Rossum Ov",
    "sg:orig_category":"Hondenscholen",
    "sg:phone":"+31 74 277 3314",
    "sg:postcode":"7596 NT",
    "sg:province":"Overijssel",
    "wof:name":"Bob",
    "wof:placetype":"venue"
},
  "geometry": {"coordinates":[6.916249,52.363029],"type":"Point"}
}