{
  "type": "Feature",
  "properties": {
    "addr:full":"Cambuurplein 1 Leeuwarden Friesland 8921 RD",
    "addr:housenumber":"1",
    "addr:postcode":"8921 rd",
    "addr:street":"Cambuurplein",
    "iso:country":"NL",
    "sg:address":"Cambuurplein 1",
    "sg:city":"Leeuwarden",
    "sg:orig_category":"Banken And Kredietinstellingen",
    "sg:phone":"+31 58 233 4505",
    "sg:postcode":"8921 RD",
    "sg:province":"Friesland",
    "wof:name":"Rabobank",
    "wof:placetype":"venue"
},
  "geometry": {"coordinates":[5.812594,53.204906],"type":"Point"}
}