{
  "type": "Feature",
  "properties": {
    "iso:country":"NL",
    "sg:address":"Baarle Hertoglaan 61",
    "sg:city":"Eindhoven",
    "sg:orig_category":"Loodgieterswerk, Verwarming And Sanitaire Installaties",
    "sg:phone":"+31 40 242 1454",
    "sg:postcode":"5628 PN",
    "sg:province":"Noord-Brabant",
    "wof:name":"Koster En Zn. Houtbouw",
    "wof:placetype":"venue"
},
  "geometry": {"coordinates":[5.475772,51.482948],"type":"Point"}
}