{
  "type": "Feature",
  "properties": {
    "iso:country":"NL",
    "sg:address":"Herenwg 358",
    "sg:city":"Noordwykerhout",
    "sg:orig_category":"Koel- En Vrieshuizen",
    "sg:phone":"+31 252 372 411",
    "sg:postcode":"2211 VH",
    "sg:province":"Zuid-Holland",
    "wof:name":"Berg Bv, Van Den",
    "wof:placetype":"venue"
},
  "geometry": {"coordinates":[4.51565,52.280239],"type":"Point"}
}