{
  "type": "Feature",
  "properties": {
    "addr:full":"Voorsterweg 20 Brummen Gelderland 6971 GP",
    "addr:housenumber":"20",
    "addr:postcode":"6971 gp",
    "addr:street":"Voorsterweg;Gelderland",
    "iso:country":"NL",
    "sg:address":"Voorsterweg 20",
    "sg:city":"Brummen",
    "sg:orig_category":"Fietshandelaren",
    "sg:phone":"+31 575 561 458",
    "sg:postcode":"6971 GP",
    "sg:province":"Gelderland",
    "wof:name":"Ten Broek",
    "wof:placetype":"venue"
},
  "geometry": {"coordinates":[6.152432,52.098396],"type":"Point"}
}