{
  "type": "Feature",
  "properties": {
    "addr:full":"Westeinde 287 Vriezenveen Overijssel 7671 ES",
    "addr:housenumber":"287",
    "addr:postcode":"7671 es",
    "addr:street":"Westeinde",
    "iso:country":"NL",
    "sg:address":"Westeinde 287",
    "sg:city":"Vriezenveen",
    "sg:orig_category":"Autorijscholen",
    "sg:phone":"+31 546 563 050",
    "sg:postcode":"7671 ES",
    "sg:province":"Overijssel",
    "wof:name":"Hulsegge",
    "wof:placetype":"venue"
},
  "geometry": {"coordinates":[6.613856,52.407455],"type":"Point"}
}