{
  "type": "Feature",
  "properties": {
    "addr:full":"Dotterlei 331 Capelle Ad Yssel South Holland 2906 BH",
    "addr:housenumber":"331",
    "addr:postcode":"2906 bh",
    "addr:street":"Dotterlei;Yssel",
    "iso:country":"NL",
    "sg:address":"Dotterlei 331",
    "sg:city":"Capelle Ad Yssel",
    "sg:orig_category":"Bouwbureaus",
    "sg:phone":"+31 10 451 6994",
    "sg:postcode":"2906 BH",
    "sg:province":"South Holland",
    "wof:name":"Pane, Iskandar",
    "wof:placetype":"venue"
},
  "geometry": {"coordinates":[4.563609,51.93465],"type":"Point"}
}