{
  "type": "Feature",
  "properties": {
    "addr:full":"De Eglantier 532 Apeldoorn Gelderland 7329 DM",
    "addr:housenumber":"532",
    "addr:postcode":"7329 dm",
    "addr:street":"De Eglantier;Gelderland",
    "iso:country":"NL",
    "sg:address":"De Eglantier 532",
    "sg:city":"Apeldoorn",
    "sg:orig_category":"Juridische Adviseurs",
    "sg:phone":"+31 55 534 4294",
    "sg:postcode":"7329 DM",
    "sg:province":"Gelderland",
    "wof:name":"C & R Cons Bv",
    "wof:placetype":"venue"
},
  "geometry": {"coordinates":[6.005498,52.194523],"type":"Point"}
}