{
  "type": "Feature",
  "properties": {
    "addr:full":"Woendsbergweg 2 Blaricum Noord-Holland 1261 AP",
    "addr:housenumber":"2",
    "addr:postcode":"1261 ap",
    "addr:street":"Woendsbergweg",
    "iso:country":"NL",
    "sg:address":"Woendsbergweg 2",
    "sg:city":"Blaricum",
    "sg:orig_category":"Binnenhuisarchitecten",
    "sg:phone":"+31 35 531 0734",
    "sg:postcode":"1261 AP",
    "sg:province":"Noord-Holland",
    "wof:name":"G. Vogel Interieurs",
    "wof:placetype":"venue"
},
  "geometry": {"coordinates":[5.243439,52.273277],"type":"Point"}
}