{
  "type": "Feature",
  "properties": {
    "addr:full":"Wegaln 57 Hoofddorp Noord-Holland 2132 JD",
    "addr:housenumber":"57",
    "addr:postcode":"2132 jd",
    "addr:street":"Wegaln",
    "iso:country":"NL",
    "sg:address":"Wegaln 57",
    "sg:city":"Hoofddorp",
    "sg:orig_category":"Medische Installaties En Instrumenten",
    "sg:phone":"+31 23 568 1200",
    "sg:postcode":"2132 JD",
    "sg:province":"Noord-Holland",
    "wof:name":"Omron Health Carebv",
    "wof:placetype":"venue"
},
  "geometry": {"coordinates":[4.69296,52.305393],"type":"Point"}
}