{
  "type": "Feature",
  "properties": {
    "addr:full":"Koepelweg 1 Noordwijk Zh Zuid-Holland 2202 AJ",
    "addr:housenumber":"1",
    "addr:postcode":"2202 aj",
    "addr:street":"Koepelweg",
    "iso:country":"NL",
    "sg:address":"Koepelweg 1",
    "sg:city":"Noordwijk Zh",
    "sg:classifiers":[
        {
            "category":"Travel",
            "subcategory":"Hotels & Motels",
            "type":"Entertainment"
        }
    ],
    "sg:phone":"+31 71 361 2916",
    "sg:postcode":"2202 AJ",
    "sg:province":"Zuid-Holland",
    "wof:name":"Familiehotel Duinlust",
    "wof:placetype":"venue"
},
  "geometry": {"coordinates":[4.433699,52.238205],"type":"Point"}
}