{
  "type": "Feature",
  "properties": {
    "addr:full":"T Loo 57 Heiloo North Holland 1851 HT",
    "addr:housenumber":"57",
    "addr:postcode":"1851 ht",
    "addr:street":"T Loo",
    "iso:country":"NL",
    "sg:address":"T Loo 57",
    "sg:city":"Heiloo",
    "sg:orig_category":"Zoetwaren - Winkels",
    "sg:phone":"+31 72 533 6015",
    "sg:postcode":"1851 HT",
    "sg:province":"North Holland",
    "wof:name":"Jamin Bv",
    "wof:placetype":"venue"
},
  "geometry": {"coordinates":[4.712161,52.605328],"type":"Point"}
}