{
  "type": "Feature",
  "properties": {
    "addr:full":"Groenhof 19 Joure Friesland 8501 VZ",
    "addr:housenumber":"19",
    "addr:postcode":"8501 vz",
    "addr:street":"Groenhof",
    "iso:country":"NL",
    "sg:address":"Groenhof 19",
    "sg:city":"Joure",
    "sg:orig_category":"Boekhouders",
    "sg:phone":"+31 513 414 362",
    "sg:postcode":"8501 VZ",
    "sg:province":"Friesland",
    "wof:name":"Administratiekantoor B. Buwalda",
    "wof:placetype":"venue"
},
  "geometry": {"coordinates":[5.791238,52.95969],"type":"Point"}
}