{
  "type": "Feature",
  "properties": {
    "addr:full":"Westzeedk 507 Rotterdam Zuid-Holland 3024 EL",
    "addr:housenumber":"507",
    "addr:postcode":"3024 el",
    "iso:country":"NL",
    "sg:address":"Westzeedk 507",
    "sg:city":"Rotterdam",
    "sg:orig_category":"Montagebedrijven",
    "sg:phone":"+31 10 425 2597",
    "sg:postcode":"3024 EL",
    "sg:province":"Zuid-Holland",
    "wof:name":"Industromontaza",
    "wof:placetype":"venue"
},
  "geometry": {"coordinates":[4.456342,51.904453],"type":"Point"}
}