{
  "type": "Feature",
  "properties": {
    "addr:full":"P Goedkoopwg 12 Haarlem Noord-Holland 2031 EL",
    "addr:housenumber":"12;2031",
    "addr:postcode":"el",
    "addr:street":"P",
    "iso:country":"NL",
    "sg:address":"P Goedkoopwg 12",
    "sg:city":"Haarlem",
    "sg:orig_category":"Medische Installaties En Instrumenten",
    "sg:phone":"+31 23 531 9043",
    "sg:postcode":"2031 EL",
    "sg:province":"Noord-Holland",
    "wof:name":"Mathot Medische Speciaalzaken",
    "wof:placetype":"venue"
},
  "geometry": {"coordinates":[4.654311,52.394291],"type":"Point"}
}