{
  "type": "Feature",
  "properties": {
    "iso:country":"NL",
    "sg:address":"Wisselpad 9",
    "sg:city":"Groesbeek",
    "sg:orig_category":"Hypotheken And Hypotheekbanken",
    "sg:phone":"+31 24 397 5866",
    "sg:postcode":"6561 CN",
    "sg:province":"Gelderland",
    "wof:name":"Henk Grim Assurantien En Hypotheken",
    "wof:placetype":"venue"
},
  "geometry": {"coordinates":[5.938694,51.778381],"type":"Point"}
}