{
  "type": "Feature",
  "properties": {
    "addr:full":"Laanenderweg 37 Alkmaar Noord-Holland 1812 PW",
    "addr:housenumber":"37",
    "addr:postcode":"1812 pw",
    "addr:street":"Laanenderweg",
    "iso:country":"NL",
    "sg:address":"Laanenderweg 37",
    "sg:city":"Alkmaar",
    "sg:orig_category":"Kantoorartikelen",
    "sg:phone":"+31 72 540 2744",
    "sg:postcode":"1812 PW",
    "sg:province":"Noord-Holland",
    "wof:name":"Kantoorservice Oudejans",
    "wof:placetype":"venue"
},
  "geometry": {"coordinates":[4.7638602257,52.6122398376],"type":"Point"}
}