{
  "type": "Feature",
  "properties": {
    "iso:country":"NL",
    "sg:address":"Herengr 495",
    "sg:city":"Amsterdam",
    "sg:orig_category":"Werving En Selectie",
    "sg:phone":"+31 20 428 6386",
    "sg:postcode":"1017 BT",
    "sg:province":"North Holland",
    "wof:name":"Kaderfuncties",
    "wof:placetype":"venue"
},
  "geometry": {"coordinates":[4.8912677765,52.3656768799],"type":"Point"}
}