{
  "type": "Feature",
  "properties": {
    "addr:full":"Vriesewg 25 Dordrecht Zuid-Holland 3311 NT",
    "addr:housenumber":"25",
    "addr:postcode":"3311 nt",
    "addr:street":"Vriesewg",
    "iso:country":"NL",
    "sg:address":"Vriesewg 25",
    "sg:city":"Dordrecht",
    "sg:orig_category":"Verenigingen En Stichtingen",
    "sg:phone":"+31 78 614 0812",
    "sg:postcode":"3311 NT",
    "sg:province":"Zuid-Holland",
    "wof:name":"Cli\u00ebntenraad Dordrecht, Sticht",
    "wof:placetype":"venue"
},
  "geometry": {"coordinates":[4.671995,51.811501],"type":"Point"}
}