{
  "type": "Feature",
  "properties": {
    "addr:full":"Wrightln 19 Ryswyk Zh Zuid-Holland 2289 KJ",
    "addr:housenumber":"19",
    "addr:postcode":"2289 kj",
    "addr:street":"Wrightln",
    "iso:country":"NL",
    "sg:address":"Wrightln 19",
    "sg:city":"Ryswyk Zh",
    "sg:orig_category":"Adviesbureaus Bedrijfsorganisatie",
    "sg:phone":"+31 70 390 6211",
    "sg:postcode":"2289 KJ",
    "sg:province":"Zuid-Holland",
    "wof:name":"Inkoop Interim",
    "wof:placetype":"venue"
},
  "geometry": {"coordinates":[4.35055,52.038219],"type":"Point"}
}