{
  "type": "Feature",
  "properties": {
    "addr:full":"Blankenstr 368 Amsterdam Noord-Holland 1018 SK",
    "addr:housenumber":"368",
    "addr:street":"1018",
    "iso:country":"NL",
    "sg:address":"Blankenstr 368",
    "sg:city":"Amsterdam",
    "sg:orig_category":"Meubelmakerijen",
    "sg:phone":"+31 20 427 7455",
    "sg:postcode":"1018 SK",
    "sg:province":"Noord-Holland",
    "wof:name":"Wolfrat",
    "wof:placetype":"venue"
},
  "geometry": {"coordinates":[4.931336,52.37056],"type":"Point"}
}