{
  "type": "Feature",
  "properties": {
    "addr:full":"Briljant 52 Heerhugowaard Noord-Holland 1703 GR",
    "addr:housenumber":"52",
    "addr:postcode":"1703",
    "addr:street":"Briljant",
    "iso:country":"NL",
    "sg:address":"Briljant 52",
    "sg:city":"Heerhugowaard",
    "sg:orig_category":"Boekhouders",
    "sg:phone":"+31 72 574 1865",
    "sg:postcode":"1703 GR",
    "sg:province":"Noord-Holland",
    "wof:name":"C.W.M. Konijn",
    "wof:placetype":"venue"
},
  "geometry": {"coordinates":[4.821088,52.663685],"type":"Point"}
}