{
  "type": "Feature",
  "properties": {
    "addr:full":"Cobbingstraat 26 Ootmarsum Overijssel 7631 DB",
    "addr:housenumber":"26",
    "addr:postcode":"7631 db",
    "addr:street":"Cobbingstraat",
    "iso:country":"NL",
    "sg:address":"Cobbingstraat 26",
    "sg:city":"Ootmarsum",
    "sg:classifiers":[
        {
            "category":"Shopping",
            "subcategory":"Gifts & Souvenirs",
            "type":"Retail Goods"
        }
    ],
    "sg:phone":"+31 541 293 589",
    "sg:postcode":"7631 DB",
    "sg:province":"Overijssel",
    "sg:tags":[
        "geschenken"
    ],
    "wof:name":"Harmsen",
    "wof:placetype":"venue"
},
  "geometry": {"coordinates":[6.909149,52.404984],"type":"Point"}
}