{
  "type": "Feature",
  "properties": {
    "addr:full":"Belder 24B Roosendaal Noord-Brabant 4704 RK",
    "addr:housenumber":"24b",
    "addr:postcode":"4704 rk",
    "addr:street":"Belder",
    "iso:country":"NL",
    "sg:address":"Belder 24B",
    "sg:city":"Roosendaal",
    "sg:orig_category":"Keuringsdiensten",
    "sg:phone":"+31 165 394 417",
    "sg:postcode":"4704 RK",
    "sg:province":"Noord-Brabant",
    "wof:name":"Askb",
    "wof:placetype":"venue"
},
  "geometry": {"coordinates":[4.469868,51.559471],"type":"Point"}
}