{
  "type": "Feature",
  "properties": {
    "addr:full":"Zuiderzeestrwg 155 Oldebroek Gelderland 8096 BG",
    "addr:housenumber":"155",
    "addr:postcode":"8096",
    "addr:street":"Gelderland",
    "iso:country":"NL",
    "sg:address":"Zuiderzeestrwg 155",
    "sg:city":"Oldebroek",
    "sg:orig_category":"Bloemen En Planten",
    "sg:phone":"+31 525 631 888",
    "sg:postcode":"8096 BG",
    "sg:province":"Gelderland",
    "wof:name":"Orchidee, De",
    "wof:placetype":"venue"
},
  "geometry": {"coordinates":[5.8934,52.445419],"type":"Point"}
}