{
  "type": "Feature",
  "properties": {
    "iso:country":"NL",
    "sg:address":"Vuurtorenplein 15",
    "sg:city":"Noordwijk Zh",
    "sg:orig_category":"Kappers",
    "sg:phone":"+31 71 361 4746",
    "sg:postcode":"2202 PA",
    "sg:province":"Zuid-Holland",
    "wof:name":"Eugenie'S Coiffure",
    "wof:placetype":"venue"
},
  "geometry": {"coordinates":[4.4347491264,52.2487564087],"type":"Point"}
}