{
  "type": "Feature",
  "properties": {
    "addr:full":"Spoordonkseweg 13 Oirschot Noord-Brabant 5688 KB",
    "addr:housenumber":"13",
    "addr:postcode":"5688 kb",
    "addr:street":"Spoordonkseweg",
    "iso:country":"NL",
    "sg:address":"Spoordonkseweg 13",
    "sg:city":"Oirschot",
    "sg:orig_category":"Schoenen",
    "sg:phone":"+31 499 572 749",
    "sg:postcode":"5688 KB",
    "sg:province":"Noord-Brabant",
    "wof:name":"Schoenenhuis Majorette",
    "wof:placetype":"venue"
},
  "geometry": {"coordinates":[5.304145,51.50742],"type":"Point"}
}