{
  "type": "Feature",
  "properties": {
    "addr:full":"Constantyn Prom 19 Ryswyk Zh Zuid-Holland 2284 DL",
    "addr:housenumber":"19",
    "addr:postcode":"2284 dl",
    "addr:street":"Prom",
    "iso:country":"NL",
    "sg:address":"Constantyn Prom 19",
    "sg:city":"Ryswyk Zh",
    "sg:orig_category":"Opticiens",
    "sg:phone":"+31 70 394 1100",
    "sg:postcode":"2284 DL",
    "sg:province":"Zuid-Holland",
    "wof:name":"Specsavers",
    "wof:placetype":"venue"
},
  "geometry": {"coordinates":[4.3131899834,52.0413017273],"type":"Point"}
}