{
  "type": "Feature",
  "properties": {
    "addr:full":"De Kwakel 8 Kortenhoef Noord-Holland 1241 LC",
    "addr:housenumber":"8",
    "addr:postcode":"1241 lc",
    "addr:street":"De Kwakel",
    "iso:country":"NL",
    "sg:address":"De Kwakel 8",
    "sg:city":"Kortenhoef",
    "sg:orig_category":"Zuivelproducten",
    "sg:phone":"+31 35 656 0024",
    "sg:postcode":"1241 LC",
    "sg:province":"Noord-Holland",
    "wof:name":"Kaasboerderij Kemp",
    "wof:placetype":"venue"
},
  "geometry": {"coordinates":[5.11431,52.248241],"type":"Point"}
}