{
  "type": "Feature",
  "properties": {
    "addr:full":"Barentszstr 10A S Gravenhage Zuid-Holland 2518 XG",
    "addr:housenumber":"10a;gravenhage",
    "addr:postcode":"2518 xg",
    "addr:street":"Barentszstr;S",
    "iso:country":"NL",
    "sg:address":"Barentszstr 10A",
    "sg:city":"S Gravenhage",
    "sg:orig_category":"Adviesbureaus Personeel",
    "sg:phone":"+31 70 361 4870",
    "sg:postcode":"2518 XG",
    "sg:province":"Zuid-Holland",
    "sg:website":"http://www.ferm-p-en-o.nl",
    "wof:name":"Ferm",
    "wof:placetype":"venue"
},
  "geometry": {"coordinates":[4.29348,52.080318],"type":"Point"}
}