{
  "type": "Feature",
  "properties": {
    "addr:full":"Garderensewg 128 Ermelo Gelderland 3852 NL",
    "addr:housenumber":"128",
    "addr:postcode":"3852",
    "addr:street":"Gelderland",
    "iso:country":"NL",
    "sg:address":"Garderensewg 128",
    "sg:city":"Ermelo",
    "sg:orig_category":"Montagebedrijven",
    "sg:phone":"+31 577 407 562",
    "sg:postcode":"3852 NL",
    "sg:province":"Gelderland",
    "wof:name":"Mulderij Montage Cv",
    "wof:placetype":"venue"
},
  "geometry": {"coordinates":[5.71455,52.271332],"type":"Point"}
}