{
  "type": "Feature",
  "properties": {
    "addr:full":"Postillonstraat 35 Breda North Brabant 4813 EV",
    "addr:housenumber":"35",
    "addr:postcode":"4813 ev",
    "addr:street":"Postillonstraat",
    "iso:country":"NL",
    "sg:address":"Postillonstraat 35",
    "sg:city":"Breda",
    "sg:orig_category":"Glaszetten",
    "sg:phone":"+31 76 522 9285",
    "sg:postcode":"4813 EV",
    "sg:province":"North Brabant",
    "wof:name":"Firma Brugel",
    "wof:placetype":"venue"
},
  "geometry": {"coordinates":[4.744917,51.575146],"type":"Point"}
}