{
  "type": "Feature",
  "properties": {
    "addr:full":"Leeghwaterstraat 50 Sliedrecht Zuid-Holland 3364 AE",
    "addr:housenumber":"50",
    "addr:postcode":"3364 ae",
    "addr:street":"Leeghwaterstraat",
    "iso:country":"NL",
    "sg:address":"Leeghwaterstraat 50",
    "sg:city":"Sliedrecht",
    "sg:orig_category":"Goederenvervoer Over De Weg",
    "sg:phone":"+31 184 422 283",
    "sg:postcode":"3364 AE",
    "sg:province":"Zuid-Holland",
    "wof:name":"Braanker Transport Bv",
    "wof:placetype":"venue"
},
  "geometry": {"coordinates":[4.766583,51.829323],"type":"Point"}
}