{
  "type": "Feature",
  "properties": {
    "addr:full":"Transformatorhof 4 Hengelo Ov Overijssel 7556 RA",
    "addr:housenumber":"4",
    "addr:postcode":"7556 ra",
    "addr:street":"Transformatorhof;Ov",
    "iso:country":"NL",
    "sg:address":"Transformatorhof 4",
    "sg:city":"Hengelo Ov",
    "sg:orig_category":"Elektronica - Ontwikkeling En Groothandel",
    "sg:phone":"+31 74 243 6452",
    "sg:postcode":"7556 RA",
    "sg:province":"Overijssel",
    "sg:website":"HTTP://www.digutronics.nl",
    "wof:name":"Digutronics",
    "wof:placetype":"venue"
},
  "geometry": {"coordinates":[6.777817,52.271801],"type":"Point"}
}