{
  "type": "Feature",
  "properties": {
    "addr:full":"Jutestr 5 Rijssen NL.08 7461 TS",
    "addr:housenumber":"5;nl.08",
    "addr:postcode":"7461 ts",
    "addr:street":"Jutestr",
    "iso:country":"NL",
    "sg:address":"Jutestr 5",
    "sg:city":"Rijssen",
    "sg:orig_category":"Autorijscholen",
    "sg:phone":"+31 548 516 398",
    "sg:postcode":"7461 TS",
    "sg:province":"NL.08",
    "wof:name":"Morsche Vof, Te",
    "wof:placetype":"venue"
},
  "geometry": {"coordinates":[6.506228,52.315384],"type":"Point"}
}