{
  "type": "Feature",
  "properties": {
    "iso:country":"NL",
    "sg:address":"Vissershavenweg 66",
    "sg:city":"'S Gravenhage",
    "sg:orig_category":"Visspeciaalzaken",
    "sg:phone":"+31 70 355 6724",
    "sg:postcode":"2583 DL",
    "sg:province":"South Holland",
    "wof:name":"Het Haringhuisje C G Antonisse",
    "wof:placetype":"venue"
},
  "geometry": {"coordinates":[4.267714,52.102184],"type":"Point"}
}