{
  "type": "Feature",
  "properties": {
    "addr:full":"A Westlandstr 10 Leeuwarden Friesland 8923 BD",
    "addr:housenumber":"10",
    "addr:postcode":"8923 bd",
    "iso:country":"NL",
    "sg:address":"A Westlandstr 10",
    "sg:city":"Leeuwarden",
    "sg:orig_category":"Projectinrichting",
    "sg:phone":"+31 58 266 2813",
    "sg:postcode":"8923 BD",
    "sg:province":"Friesland",
    "wof:name":"Vrijheidswijk",
    "wof:placetype":"venue"
},
  "geometry": {"coordinates":[5.81269,53.215557],"type":"Point"}
}