{
  "type": "Feature",
  "properties": {
    "addr:full":"Bogerdln 23-25 Limmen Noord-Holland 1906 XR",
    "addr:housenumber":"23-25",
    "addr:postcode":"1906 xr",
    "iso:country":"NL",
    "sg:address":"Bogerdln 23-25",
    "sg:city":"Limmen",
    "sg:orig_category":"Houtplaatmaterialen",
    "sg:phone":"+31 72 505 1379",
    "sg:postcode":"1906 XR",
    "sg:province":"Noord-Holland",
    "wof:name":"Metzelaar & Zn, Fa J",
    "wof:placetype":"venue"
},
  "geometry": {"coordinates":[4.692436,52.570141],"type":"Point"}
}