{
  "type": "Feature",
  "properties": {
    "addr:full":"Lohengrinlaan 21 Eindhoven Noord-Brabant 5625 EK",
    "addr:housenumber":"21",
    "addr:postcode":"5625 ek",
    "addr:street":"Lohengrinlaan",
    "iso:country":"NL",
    "sg:address":"Lohengrinlaan 21",
    "sg:city":"Eindhoven",
    "sg:orig_category":"Technische Studies And Onderzoek",
    "sg:phone":"+31 40 242 5304",
    "sg:postcode":"5625 EK",
    "sg:province":"Noord-Brabant",
    "wof:name":"Roebroek Design",
    "wof:placetype":"venue"
},
  "geometry": {"coordinates":[5.467936,51.473953],"type":"Point"}
}