{
  "type": "Feature",
  "properties": {
    "addr:full":"Deltastr 16 Nieuwerkerk Zeeland 4306 BK",
    "addr:housenumber":"16",
    "addr:postcode":"4306 bk",
    "addr:street":"Deltastr",
    "iso:country":"NL",
    "sg:address":"Deltastr 16",
    "sg:city":"Nieuwerkerk",
    "sg:orig_category":"Adviesbureaus Bedrijfsorganisatie",
    "sg:phone":"+31 111 644 088",
    "sg:postcode":"4306 BK",
    "sg:province":"Zeeland",
    "wof:name":"Bodde",
    "wof:placetype":"venue"
},
  "geometry": {"coordinates":[4.000462,51.648354],"type":"Point"}
}