{
  "type": "Feature",
  "properties": {
    "addr:full":"Arnhemseweg 79 Ede Gld Gelderland 6711 GT",
    "addr:housenumber":"79;6711",
    "addr:postcode":"gt",
    "addr:street":"Arnhemseweg;Gld Gelderland",
    "iso:country":"NL",
    "sg:address":"Arnhemseweg 79",
    "sg:city":"Ede Gld",
    "sg:orig_category":"Musea And Historische Gebouwen",
    "sg:phone":"+31 318 611 618",
    "sg:postcode":"6711 GT",
    "sg:province":"Gelderland",
    "wof:name":"J Haffmans",
    "wof:placetype":"venue"
},
  "geometry": {"coordinates":[5.687753,52.041931],"type":"Point"}
}