{
  "type": "Feature",
  "properties": {
    "iso:country":"NL",
    "sg:address":"Van Meeuwenstraat 10",
    "sg:city":"Spaarndam",
    "sg:orig_category":"Boekhouders",
    "sg:phone":"+31 23 539 0984",
    "sg:postcode":"2064 LD",
    "sg:province":"Noord-Holland",
    "wof:name":"Jon Jansen Administraties",
    "wof:placetype":"venue"
},
  "geometry": {"coordinates":[4.692781,52.41433],"type":"Point"}
}