{
  "type": "Feature",
  "properties": {
    "addr:full":"Erfgooiersstraat 76 Hilversum North Holland 1222 BB",
    "addr:housenumber":"76",
    "addr:postcode":"1222 bb",
    "addr:street":"Erfgooiersstraat",
    "iso:country":"NL",
    "sg:address":"Erfgooiersstraat 76",
    "sg:city":"Hilversum",
    "sg:orig_category":"Loodgieterswerk, Verwarming And Sanitaire Installaties",
    "sg:phone":"+31 35 685 7809",
    "sg:postcode":"1222 BB",
    "sg:province":"North Holland",
    "wof:name":"Loodgietersbedrijf M Wildschut",
    "wof:placetype":"venue"
},
  "geometry": {"coordinates":[5.191822,52.239048],"type":"Point"}
}