{
  "type": "Feature",
  "properties": {
    "addr:full":"Prins Bernhardstraat 13 Asten Noord-Brabant 5721 GA",
    "addr:housenumber":"13",
    "addr:postcode":"5721 ga",
    "addr:street":"Prins Bernhardstraat",
    "iso:country":"NL",
    "sg:address":"Prins Bernhardstraat 13",
    "sg:city":"Asten",
    "sg:orig_category":"Verzekeringen",
    "sg:phone":"+31 493 691 286",
    "sg:postcode":"5721 GA",
    "sg:province":"Noord-Brabant",
    "wof:name":"Assurantiekantoor Schriks",
    "wof:placetype":"venue"
},
  "geometry": {"coordinates":[5.746114,51.405045],"type":"Point"}
}