{
  "type": "Feature",
  "properties": {
    "iso:country":"NL",
    "sg:address":"Fideliohof 44",
    "sg:city":"Amersfoort",
    "sg:orig_category":"Grafisch Ontwerpers",
    "sg:phone":"+31 6 29596343",
    "sg:postcode":"3816 HC",
    "sg:province":"Utrecht",
    "sg:website":"http://www.vier4ict.nl",
    "wof:name":"Vier4Ict",
    "wof:placetype":"venue"
},
  "geometry": {"coordinates":[5.411378,52.158176],"type":"Point"}
}