{
  "type": "Feature",
  "properties": {
    "iso:country":"NL",
    "sg:address":"Schoolstr 5B",
    "sg:city":"Rosmalen",
    "sg:orig_category":"Postkantoren",
    "sg:phone":"+31 73 522 1221",
    "sg:postcode":"5241 VA",
    "sg:province":"Noord-Brabant",
    "sg:website":"http://www.postkantoor.nl",
    "wof:name":"Postkantoor",
    "wof:placetype":"venue"
},
  "geometry": {"coordinates":[5.363537,51.719028],"type":"Point"}
}