{
  "type": "Feature",
  "properties": {
    "addr:full":"Kloosterstr 44 Haarlem Noord-Holland 2021 VP",
    "addr:housenumber":"44",
    "addr:postcode":"2021 vp",
    "addr:street":"Kloosterstr",
    "iso:country":"NL",
    "sg:address":"Kloosterstr 44",
    "sg:city":"Haarlem",
    "sg:orig_category":"Keukens",
    "sg:phone":"+31 23 527 3889",
    "sg:postcode":"2021 VP",
    "sg:province":"Noord-Holland",
    "wof:name":"Acosta",
    "wof:placetype":"venue"
},
  "geometry": {"coordinates":[4.644852,52.393406],"type":"Point"}
}