{
  "type": "Feature",
  "properties": {
    "addr:full":"Mastbosstr 78A Breda Noord-Brabant 4813 GV",
    "addr:housenumber":"78a",
    "addr:postcode":"4813 gv",
    "addr:street":"Mastbosstr",
    "iso:country":"NL",
    "sg:address":"Mastbosstr 78A",
    "sg:city":"Breda",
    "sg:orig_category":"Offsetdrukkerijen",
    "sg:phone":"+31 76 522 2911",
    "sg:postcode":"4813 GV",
    "sg:province":"Noord-Brabant",
    "wof:name":"Boerrigter Jansen",
    "wof:placetype":"venue"
},
  "geometry": {"coordinates":[4.742901,51.571484],"type":"Point"}
}