{
  "type": "Feature",
  "properties": {
    "iso:country":"NL",
    "sg:address":"D Nieuwenhuiswg 9",
    "sg:city":"Ny Beets",
    "sg:orig_category":"Onderhoudswerken",
    "sg:phone":"+31 512 461 883",
    "sg:postcode":"9245 VA",
    "sg:province":"Provincie Friesland",
    "wof:name":"Annema",
    "wof:placetype":"venue"
},
  "geometry": {"coordinates":[5.997525,53.069118],"type":"Point"}
}