{
  "type": "Feature",
  "properties": {
    "iso:country":"NL",
    "sg:address":"Vondelpk 3",
    "sg:city":"Amsterdam",
    "sg:classifiers":[
        {
            "category":"Shopping",
            "subcategory":"News",
            "type":"Retail Goods"
        }
    ],
    "sg:phone":"+31 20 689 3831",
    "sg:postcode":"1071 AA",
    "sg:province":"Noord-Holland",
    "sg:tags":[
        "maandbladen",
        "en",
        "week-"
    ],
    "wof:name":"Skrien",
    "wof:placetype":"venue"
},
  "geometry": {"coordinates":[4.8723669052,52.3591384888],"type":"Point"}
}