{
  "type": "Feature",
  "properties": {
    "iso:country":"NL",
    "sg:address":"Vechtstr 50",
    "sg:city":"Zwolle",
    "sg:orig_category":"Satellietontvangst- En Antenne-Installaties",
    "sg:phone":"+31 38 454 1676",
    "sg:postcode":"8021 AX",
    "sg:province":"Overijssel",
    "wof:name":"Transonic",
    "wof:placetype":"venue"
},
  "geometry": {"coordinates":[6.106177,52.515434],"type":"Point"}
}