{
  "type": "Feature",
  "properties": {
    "addr:full":"Zetstee 81 Zuidlaren Provincie Drenthe 9472 VH",
    "addr:housenumber":"81",
    "addr:postcode":"9472 vh",
    "addr:street":"Zetstee;Provincie Drenthe",
    "iso:country":"NL",
    "sg:address":"Zetstee 81",
    "sg:city":"Zuidlaren",
    "sg:orig_category":"Boekbinderijen",
    "sg:phone":"+31 50 402 9218",
    "sg:postcode":"9472 VH",
    "sg:province":"Provincie Drenthe",
    "wof:name":"Jannink, A J",
    "wof:placetype":"venue"
},
  "geometry": {"coordinates":[6.694328,53.078278],"type":"Point"}
}