{
  "type": "Feature",
  "properties": {
    "addr:full":"Veerdam 7 Aalst Gld Gelderland 5308 JH",
    "addr:housenumber":"7",
    "addr:postcode":"5308 jh",
    "addr:street":"Veerdam;Gld Gelderland",
    "iso:country":"NL",
    "sg:address":"Veerdam 7",
    "sg:city":"Aalst Gld",
    "sg:orig_category":"Lasbedrijven",
    "sg:phone":"+31 418 670 242",
    "sg:postcode":"5308 JH",
    "sg:province":"Gelderland",
    "wof:name":"Mansvelder",
    "wof:placetype":"venue"
},
  "geometry": {"coordinates":[5.116763,51.781876],"type":"Point"}
}