{
  "type": "Feature",
  "properties": {
    "iso:country":"NL",
    "sg:address":"Hoveniersland 58",
    "sg:city":"Noordscheschut",
    "sg:orig_category":"Zaden",
    "sg:phone":"+31 528 344 147",
    "sg:postcode":"7914 PV",
    "sg:province":"Provincie Drenthe",
    "wof:name":"Klunder, Wilco",
    "wof:placetype":"venue"
},
  "geometry": {"coordinates":[6.532193,52.722794],"type":"Point"}
}