{
  "type": "Feature",
  "properties": {
    "iso:country":"NL",
    "sg:address":"Ruysstr 20",
    "sg:city":"Panningen",
    "sg:orig_category":"Kinderopvang",
    "sg:phone":"+31 77 307 2697",
    "sg:postcode":"5981 CM",
    "sg:province":"Limburg",
    "wof:name":"Bobo",
    "wof:placetype":"venue"
},
  "geometry": {"coordinates":[5.984496,51.32756],"type":"Point"}
}