{
  "type": "Feature",
  "properties": {
    "addr:full":"Huybergsewg 36 Hoogerheide North Brabant 4631 GG",
    "addr:housenumber":"36",
    "addr:postcode":"4631 gg",
    "addr:street":"Huybergsewg",
    "iso:country":"NL",
    "sg:address":"Huybergsewg 36",
    "sg:city":"Hoogerheide",
    "sg:classifiers":[
        {
            "category":"Farming",
            "subcategory":"Fish & Marine Products",
            "type":"Manufacturing & Wholesale Goods"
        }
    ],
    "sg:phone":"+31 164 616 411",
    "sg:postcode":"4631 GG",
    "sg:province":"North Brabant",
    "sg:tags":[
        "vi"
    ],
    "wof:name":"Visspecialist, De",
    "wof:placetype":"venue"
},
  "geometry": {"coordinates":[4.328316,51.422993],"type":"Point"}
}