{
  "type": "Feature",
  "properties": {
    "addr:full":"Maasdijk 25 Poederoijen Gelderland 5307 HM",
    "addr:housenumber":"25",
    "addr:postcode":"5307 hm",
    "addr:street":"Maasdijk;Gelderland",
    "iso:country":"NL",
    "sg:address":"Maasdijk 25",
    "sg:city":"Poederoijen",
    "sg:orig_category":"Autokeuringen",
    "sg:phone":"+31 418 671 580",
    "sg:postcode":"5307 HM",
    "sg:province":"Gelderland",
    "wof:name":"Handels En Reparatieondern Van Der Ven",
    "wof:placetype":"venue"
},
  "geometry": {"coordinates":[5.080878,51.785206],"type":"Point"}
}