{
  "type": "Feature",
  "properties": {
    "addr:full":"Rijnkade 66 Arnhem Gelderland 6811 HC",
    "addr:housenumber":"66",
    "addr:postcode":"6811 hc",
    "addr:street":"Rijnkade",
    "iso:country":"NL",
    "sg:address":"Rijnkade 66",
    "sg:city":"Arnhem",
    "sg:orig_category":"Makelaars In Onroerend Goed",
    "sg:phone":"+31 26 351 2781",
    "sg:postcode":"6811 HC",
    "sg:province":"Gelderland",
    "wof:name":"Hochrath Assurantien",
    "wof:placetype":"venue"
},
  "geometry": {"coordinates":[5.906995,51.977348],"type":"Point"}
}