{
  "type": "Feature",
  "properties": {
    "addr:full":"Akkerweg 2 Musselkanaal Groningen 9581 GK",
    "addr:housenumber":"2",
    "addr:postcode":"9581 gk",
    "addr:street":"Akkerweg",
    "iso:country":"NL",
    "sg:address":"Akkerweg 2",
    "sg:city":"Musselkanaal",
    "sg:classifiers":[
        {
            "category":"Education",
            "subcategory":"Preschool",
            "type":"Public Place"
        }
    ],
    "sg:phone":"+31 599 615 847",
    "sg:postcode":"9581 GK",
    "sg:province":"Groningen",
    "sg:tags":[
        "kleuteronderwijs",
        "basis-"
    ],
    "wof:name":"De Stobbe",
    "wof:placetype":"venue"
},
  "geometry": {"coordinates":[6.974936,52.965389],"type":"Point"}
}