{
  "type": "Feature",
  "properties": {
    "addr:full":"H. De Grootplein 9-11 Amsterdam Noord-Holland 1052 KV",
    "addr:housenumber":"9-11",
    "addr:postcode":"1052 kv",
    "addr:street":"H. De Grootplein",
    "iso:country":"NL",
    "sg:address":"H. De Grootplein 9-11",
    "sg:city":"Amsterdam",
    "sg:orig_category":"Diverse Kredietdiensten",
    "sg:postcode":"1052 KV",
    "sg:province":"Noord-Holland",
    "wof:name":"Rabobank Geldautomaat",
    "wof:placetype":"venue"
},
  "geometry": {"coordinates":[4.873079,52.374344],"type":"Point"}
}