{
  "type": "Feature",
  "properties": {
    "addr:full":"Vierhuisterweg 3 Surhuisterveen Friesland 9231 AR",
    "addr:housenumber":"3",
    "addr:postcode":"9231",
    "addr:street":"Vierhuisterweg",
    "iso:country":"NL",
    "sg:address":"Vierhuisterweg 3",
    "sg:city":"Surhuisterveen",
    "sg:orig_category":"Huishoudapparatuur, Televisies And Radio'S",
    "sg:phone":"+31 512 363 239",
    "sg:postcode":"9231 AR",
    "sg:province":"Friesland",
    "wof:name":"Pool Hifi Video Centre",
    "wof:placetype":"venue"
},
  "geometry": {"coordinates":[6.168885,53.182072],"type":"Point"}
}