{
  "type": "Feature",
  "properties": {
    "iso:country":"NL",
    "sg:address":"Oude Oosterstraat 7",
    "sg:city":"Leeuwarden",
    "sg:classifiers":[
        {
            "category":"Restaurant",
            "type":"Food & Drink"
        }
    ],
    "sg:phone":"+31 58 215 3060",
    "sg:postcode":"8911 LD",
    "sg:province":"Friesland",
    "wof:name":"Las Tapas",
    "wof:placetype":"venue"
},
  "geometry": {"coordinates":[5.798978,53.200932],"type":"Point"}
}