{
  "type": "Feature",
  "properties": {
    "iso:country":"NL",
    "sg:address":"V W Poelmanstr 253",
    "sg:city":"Heerlen",
    "sg:orig_category":"Adviesbureaus Bouwkunde",
    "sg:phone":"+31 45 542 1685",
    "sg:postcode":"6417 EM",
    "sg:province":"Limburg",
    "sg:website":"http://www.drie-m-bouwsupport.nl",
    "wof:name":"Drie-M Bouwsupport",
    "wof:placetype":"venue"
},
  "geometry": {"coordinates":[5.98098,50.885506],"type":"Point"}
}