{
  "type": "Feature",
  "properties": {
    "addr:full":"Zandstr 88A Gennep Limburg 6591 DE",
    "addr:housenumber":"88a",
    "addr:postcode":"6591 de",
    "addr:street":"Zandstr",
    "iso:country":"NL",
    "sg:address":"Zandstr 88A",
    "sg:city":"Gennep",
    "sg:orig_category":"Opticiens",
    "sg:phone":"+31 485 512 276",
    "sg:postcode":"6591 DE",
    "sg:province":"Limburg",
    "wof:name":"Briljant Bv",
    "wof:placetype":"venue"
},
  "geometry": {"coordinates":[5.9711899757,51.6992988586],"type":"Point"}
}