{
  "type": "Feature",
  "properties": {
    "addr:full":"Postbus 475 Spykenisse 3200 AL",
    "addr:housenumber":"475",
    "addr:postcode":"3200",
    "addr:street":"Postbus;Al",
    "iso:country":"NL",
    "sg:address":"Postbus 475",
    "sg:city":"Spykenisse",
    "sg:orig_category":"Administratie- En Boekhoudkantoren",
    "sg:phone":"+31 181 619 959",
    "sg:postcode":"3200 AL",
    "wof:name":"Jls",
    "wof:placetype":"venue"
},
  "geometry": {"coordinates":[4.35844,51.837879],"type":"Point"}
}