{
  "type": "Feature",
  "properties": {
    "addr:full":"L Deurloostr 17-21 Scherpenisse Zeeland 4694 BP",
    "addr:housenumber":"17-21",
    "addr:postcode":"4694 bp",
    "iso:country":"NL",
    "sg:address":"L Deurloostr 17-21",
    "sg:city":"Scherpenisse",
    "sg:orig_category":"Scholen Voor Basisonderwijs",
    "sg:phone":"+31 166 662 471",
    "sg:postcode":"4694 BP",
    "sg:province":"Zeeland",
    "wof:name":"Groen Van Prinsterersch Reform",
    "wof:placetype":"venue"
},
  "geometry": {"coordinates":[4.107692,51.548328],"type":"Point"}
}