{
  "type": "Feature",
  "properties": {
    "iso:country":"NL",
    "sg:address":"Beatrixstraat 10",
    "sg:city":"Groenlo",
    "sg:orig_category":"Warenhuizen",
    "sg:phone":"+31 544 466 871",
    "sg:postcode":"7141 XW",
    "sg:province":"Gelderland",
    "sg:website":"http://www.budgetland.nl",
    "wof:name":"Budgetland",
    "wof:placetype":"venue"
},
  "geometry": {"coordinates":[6.6082987785,52.0439567566],"type":"Point"}
}