{
  "type": "Feature",
  "properties": {
    "addr:full":"Noordeinde 92 Roelofarendsveen South Holland 2371 CW",
    "addr:housenumber":"92",
    "addr:postcode":"2371 cw",
    "addr:street":"Noordeinde",
    "iso:country":"NL",
    "sg:address":"Noordeinde 92",
    "sg:city":"Roelofarendsveen",
    "sg:orig_category":"Kappers",
    "sg:phone":"+31 71 331 4519",
    "sg:postcode":"2371 CW",
    "sg:province":"South Holland",
    "wof:name":"Marian",
    "wof:placetype":"venue"
},
  "geometry": {"coordinates":[4.629821,52.198597],"type":"Point"}
}