{
  "type": "Feature",
  "properties": {
    "addr:full":"L B Pearsonstr 19 Groningen Groningen 9728 WR",
    "addr:housenumber":"19",
    "addr:postcode":"9728 wr",
    "addr:street":"L;Pearsonstr",
    "iso:country":"NL",
    "sg:address":"L B Pearsonstr 19",
    "sg:city":"Groningen",
    "sg:orig_category":"Artiesten/Gezelschappen",
    "sg:phone":"+31 50 525 1811",
    "sg:postcode":"9728 WR",
    "sg:province":"Groningen",
    "wof:name":"Dolores",
    "wof:placetype":"venue"
},
  "geometry": {"coordinates":[6.553477,53.184464],"type":"Point"}
}