{
  "type": "Feature",
  "properties": {
    "addr:full":"Smedenstr 21 Deventer NL.08 7411 RB",
    "addr:housenumber":"21;nl.08",
    "addr:postcode":"7411 rb",
    "addr:street":"Smedenstr",
    "iso:country":"NL",
    "sg:address":"Smedenstr 21",
    "sg:city":"Deventer",
    "sg:orig_category":"Herenkleding",
    "sg:phone":"+31 570 618 194",
    "sg:postcode":"7411 RB",
    "sg:province":"NL.08",
    "wof:name":"Moda",
    "wof:placetype":"venue"
},
  "geometry": {"coordinates":[6.15713,52.254875],"type":"Point"}
}