{
  "type": "Feature",
  "properties": {
    "iso:country":"NL",
    "sg:address":"Peelo 18",
    "sg:city":"Assen",
    "sg:orig_category":"Tuinaanleg En -Onderhoud",
    "sg:phone":"+31 592 341 207",
    "sg:postcode":"9403 TZ",
    "sg:province":"Drenthe",
    "wof:name":"Arbo Groencentrum",
    "wof:placetype":"venue"
},
  "geometry": {"coordinates":[6.571826,53.019962],"type":"Point"}
}