{
  "type": "Feature",
  "properties": {
    "addr:full":"Groenewg 28 Numansdorp Zuid-Holland 3281 XC",
    "addr:housenumber":"28",
    "addr:postcode":"3281 xc",
    "addr:street":"Groenewg",
    "iso:country":"NL",
    "sg:address":"Groenewg 28",
    "sg:city":"Numansdorp",
    "sg:orig_category":"Honden- En Kattentrimsalons",
    "sg:phone":"+31 6 23180410",
    "sg:postcode":"3281 XC",
    "sg:province":"Zuid-Holland",
    "wof:name":"Hondenstudio Numansdorp",
    "wof:placetype":"venue"
},
  "geometry": {"coordinates":[4.437684,51.731434],"type":"Point"}
}