{
  "type": "Feature",
  "properties": {
    "addr:full":"Bos En Lommerweg 379 Amsterdam Noord-Holland 1061 DH",
    "addr:housenumber":"379",
    "addr:postcode":"1061 dh",
    "addr:street":"Bos En Lommerweg",
    "iso:country":"NL",
    "sg:address":"Bos En Lommerweg 379",
    "sg:city":"Amsterdam",
    "sg:orig_category":"Discountwinkels",
    "sg:phone":"+31 20 684 9109",
    "sg:postcode":"1061 DH",
    "sg:province":"Noord-Holland",
    "wof:name":"Wibra Bv",
    "wof:placetype":"venue"
},
  "geometry": {"coordinates":[4.839526,52.378368],"type":"Point"}
}