{
  "type": "Feature",
  "properties": {
    "addr:full":"Almelosestraat 52 Raalte Overijssel 8102 HD",
    "addr:housenumber":"52",
    "addr:postcode":"8102 hd",
    "addr:street":"Almelosestraat",
    "iso:country":"NL",
    "sg:address":"Almelosestraat 52",
    "sg:city":"Raalte",
    "sg:orig_category":"Voeding, Dranken And Tabak Gh",
    "sg:phone":"+31 572 359 911",
    "sg:postcode":"8102 HD",
    "sg:province":"Overijssel",
    "wof:name":"Schuitema Oost Bv",
    "wof:placetype":"venue"
},
  "geometry": {"coordinates":[6.284531,52.382801],"type":"Point"}
}