{
  "type": "Feature",
  "properties": {
    "iso:country":"NL",
    "sg:address":"Dykstr 39",
    "sg:city":"Franeker",
    "sg:orig_category":"Kunstgebitten",
    "sg:phone":"+31 517 393 580",
    "sg:postcode":"8801 LS",
    "sg:province":"Provincie Friesland",
    "wof:name":"Woude, Van Der",
    "wof:placetype":"venue"
},
  "geometry": {"coordinates":[5.538215,53.18536],"type":"Point"}
}