{
  "type": "Feature",
  "properties": {
    "addr:full":"Prinsendam 62 Oosterhout Nb Noord-Brabant 4908 AB",
    "addr:housenumber":"62",
    "addr:postcode":"4908 ab",
    "addr:street":"Prinsendam",
    "iso:country":"NL",
    "sg:address":"Prinsendam 62",
    "sg:city":"Oosterhout Nb",
    "sg:orig_category":"Verzekeringen - Verzekeringskantoren",
    "sg:phone":"+31 162 470 120",
    "sg:postcode":"4908 AB",
    "sg:province":"Noord-Brabant",
    "sg:website":"http://www.vanzon.nl/",
    "wof:name":"Vanzon",
    "wof:placetype":"venue"
},
  "geometry": {"coordinates":[4.858466,51.66349],"type":"Point"}
}