{
  "type": "Feature",
  "properties": {
    "addr:full":"Postbus 6321 Eindhoven North Brabant 5600 HH",
    "addr:housenumber":"6321",
    "addr:postcode":"5600 hh",
    "addr:street":"Postbus",
    "iso:country":"NL",
    "sg:address":"Postbus 6321",
    "sg:city":"Eindhoven",
    "sg:orig_category":"Verenigingen En Stichtingen",
    "sg:phone":"+31 40 292 6684",
    "sg:postcode":"5600 HH",
    "sg:province":"North Brabant",
    "sg:website":"http://eindhoven.scouting.nl",
    "wof:name":"Scouting Regio Eindhoven",
    "wof:placetype":"venue"
},
  "geometry": {"coordinates":[5.48411,51.434471],"type":"Point"}
}