{
  "type": "Feature",
  "properties": {
    "addr:full":"Schagerweg 34 Schagerbrug North Holland 1751 CC",
    "addr:housenumber":"34",
    "addr:postcode":"1751 cc",
    "addr:street":"Schagerweg",
    "iso:country":"NL",
    "sg:address":"Schagerweg 34",
    "sg:city":"Schagerbrug",
    "sg:orig_category":"Zuivelproducten",
    "sg:phone":"+31 224 571 236",
    "sg:postcode":"1751 CC",
    "sg:province":"North Holland",
    "wof:name":"J.H. Bakker",
    "wof:placetype":"venue"
},
  "geometry": {"coordinates":[4.759732,52.801754],"type":"Point"}
}