{
  "type": "Feature",
  "properties": {
    "addr:full":"Havenkade 1 Ijmuiden Noord-Holland 1973 AH",
    "addr:housenumber":"1",
    "addr:postcode":"1973 ah",
    "addr:street":"Havenkade",
    "iso:country":"NL",
    "sg:address":"Havenkade 1",
    "sg:city":"Ijmuiden",
    "sg:orig_category":"Makelaars In Onroerend Goed",
    "sg:phone":"+31 255 511 544",
    "sg:postcode":"1973 AH",
    "sg:province":"Noord-Holland",
    "wof:name":"Prins Bv",
    "wof:placetype":"venue"
},
  "geometry": {"coordinates":[4.601497,52.460789],"type":"Point"}
}