{
  "type": "Feature",
  "properties": {
    "addr:full":"Tournoysveld 79 Woerden South Holland 3443 ES",
    "addr:housenumber":"79",
    "addr:postcode":"3443 es",
    "addr:street":"Tournoysveld",
    "iso:country":"NL",
    "sg:address":"Tournoysveld 79",
    "sg:city":"Woerden",
    "sg:classifiers":[
        {
            "category":"Fast Food",
            "type":"Food & Drink"
        }
    ],
    "sg:phone":"+31 348 414 789",
    "sg:postcode":"3443 ES",
    "sg:province":"South Holland",
    "sg:tags":[
        "afhaal",
        "restaurant"
    ],
    "wof:name":"Cafetaria Tournoysveld",
    "wof:placetype":"venue"
},
  "geometry": {"coordinates":[4.871191,52.088287],"type":"Point"}
}