{
  "type": "Feature",
  "properties": {
    "iso:country":"NL",
    "sg:address":"Klaasboerstraat 6",
    "sg:city":"Zwolle",
    "sg:orig_category":"Film-, Tv- And Videoproductie",
    "sg:phone":"+31 38 422 6901",
    "sg:postcode":"8012 DR",
    "sg:province":"Overijssel",
    "sg:website":"http://www.korenberg.com",
    "wof:name":"Kodenberg Video Produkties",
    "wof:placetype":"venue"
},
  "geometry": {"coordinates":[6.101698,52.506638],"type":"Point"}
}