{
  "type": "Feature",
  "properties": {
    "addr:full":"Aamsestr 90E Elst Gld Gelderland 6662 NK",
    "addr:housenumber":"90e",
    "addr:postcode":"6662 nk",
    "addr:street":"Aamsestr;Gld Gelderland",
    "iso:country":"NL",
    "sg:address":"Aamsestr 90E",
    "sg:city":"Elst Gld",
    "sg:orig_category":"Makelaars En Adviseurs Overnames",
    "sg:phone":"+31 481 454 314",
    "sg:postcode":"6662 NK",
    "sg:province":"Gelderland",
    "sg:website":"http://www.nunes.nl",
    "wof:name":"Consulting Group",
    "wof:placetype":"venue"
},
  "geometry": {"coordinates":[5.869215,51.914482],"type":"Point"}
}