{
  "type": "Feature",
  "properties": {
    "iso:country":"NL",
    "sg:address":"Singel 1",
    "sg:city":"Deventer",
    "sg:orig_category":"Verzekeringen",
    "sg:phone":"+31 570 610 757",
    "sg:postcode":"7411 HV",
    "sg:province":"Overijssel",
    "wof:name":"Sjoerts & Partners",
    "wof:placetype":"venue"
},
  "geometry": {"coordinates":[6.150501,52.257015],"type":"Point"}
}