{
  "type": "Feature",
  "properties": {
    "addr:full":"Van Immerseelstraat 11 Loon Op Zand Noord-Brabant 5175 CH",
    "addr:housenumber":"11",
    "addr:postcode":"5175",
    "addr:street":"Van Immerseelstraat",
    "iso:country":"NL",
    "sg:address":"Van Immerseelstraat 11",
    "sg:city":"Loon Op Zand",
    "sg:orig_category":"Boekhouders",
    "sg:phone":"+31 416 362 951",
    "sg:postcode":"5175 CH",
    "sg:province":"Noord-Brabant",
    "wof:name":"C.M. Kooij-Trooster",
    "wof:placetype":"venue"
},
  "geometry": {"coordinates":[5.071181,51.630413],"type":"Point"}
}