{
  "type": "Feature",
  "properties": {
    "addr:full":"De Beaufortwg 16 Leusden Utrecht 3833 AG",
    "addr:housenumber":"16",
    "addr:postcode":"3833",
    "iso:country":"NL",
    "sg:address":"De Beaufortwg 16",
    "sg:city":"Leusden",
    "sg:orig_category":"Grafische Bedrijven",
    "sg:phone":"+31 33 433 5333",
    "sg:postcode":"3833 AG",
    "sg:province":"Utrecht",
    "sg:website":"http://www.brouwergroep.nl",
    "wof:name":"Brouwer Groep Bv",
    "wof:placetype":"venue"
},
  "geometry": {"coordinates":[5.421843,52.137424],"type":"Point"}
}