{
  "type": "Feature",
  "properties": {
    "iso:country":"NL",
    "sg:address":"Th A Kempisstraat 113",
    "sg:city":"Zwolle",
    "sg:classifiers":[
        {
            "category":"Fast Food",
            "type":"Food & Drink"
        }
    ],
    "sg:phone":"+31 38 454 2160",
    "sg:postcode":"8021 BL",
    "sg:province":"Overijssel",
    "sg:tags":[
        "afhaal",
        "restaurant"
    ],
    "wof:name":"Pizza Sandro Bezorgservice",
    "wof:placetype":"venue"
},
  "geometry": {"coordinates":[6.105734,52.516483],"type":"Point"}
}