{
  "type": "Feature",
  "properties": {
    "addr:full":"Zwarteweg 12 Spijk Gn Groningen 9909 BG",
    "addr:housenumber":"12",
    "addr:postcode":"gn;9909",
    "addr:street":"Zwarteweg",
    "iso:country":"NL",
    "sg:address":"Zwarteweg 12",
    "sg:city":"Spijk Gn",
    "sg:orig_category":"Drukkerijen And Copyshops",
    "sg:phone":"+31 596 592 137",
    "sg:postcode":"9909 BG",
    "sg:province":"Groningen",
    "wof:name":"Speed-Print",
    "wof:placetype":"venue"
},
  "geometry": {"coordinates":[6.833737,53.388718],"type":"Point"}
}