{
  "type": "Feature",
  "properties": {
    "addr:full":"Spaarnwouderstraat 39 Haarlem North Holland 2011 AB",
    "addr:housenumber":"39",
    "addr:postcode":"2011 ab",
    "addr:street":"Spaarnwouderstraat",
    "iso:country":"NL",
    "sg:address":"Spaarnwouderstraat 39",
    "sg:city":"Haarlem",
    "sg:orig_category":"Muziekinstrumenten Fab",
    "sg:phone":"+31 23 536 1205",
    "sg:postcode":"2011 AB",
    "sg:province":"North Holland",
    "wof:name":"F. Bettenhausen Klavecimbelbouw/Harpsichords",
    "wof:placetype":"venue"
},
  "geometry": {"coordinates":[4.643386,52.380066],"type":"Point"}
}