{
  "type": "Feature",
  "properties": {
    "addr:full":"Vuursteeglaan 9 Lisse Zuid-Holland 2161 GD",
    "addr:housenumber":"9",
    "addr:postcode":"2161 gd",
    "addr:street":"Vuursteeglaan",
    "iso:country":"NL",
    "sg:address":"Vuursteeglaan 9",
    "sg:city":"Lisse",
    "sg:orig_category":"Bibliotheken And Openbare Archieven",
    "sg:phone":"+31 252 415 782",
    "sg:postcode":"2161 GD",
    "sg:province":"Zuid-Holland",
    "wof:name":"Bibliotheek",
    "wof:placetype":"venue"
},
  "geometry": {"coordinates":[4.548142,52.256126],"type":"Point"}
}