{
  "type": "Feature",
  "properties": {
    "iso:country":"NL",
    "sg:address":"Kerkstraat 19",
    "sg:city":"Strijen",
    "sg:orig_category":"Opticiens",
    "sg:phone":"+31 78 674 2674",
    "sg:postcode":"3291 AJ",
    "sg:province":"Zuid-Holland",
    "wof:name":"Firma J. Stolk & Zn",
    "wof:placetype":"venue"
},
  "geometry": {"coordinates":[4.5531449318,51.7427940369],"type":"Point"}
}