{
  "type": "Feature",
  "properties": {
    "addr:full":"Leidsewg 93A Utrecht Utrecht 3533 HA",
    "addr:housenumber":"93a",
    "addr:postcode":"3533 ha",
    "addr:street":"Leidsewg",
    "iso:country":"NL",
    "sg:address":"Leidsewg 93A",
    "sg:city":"Utrecht",
    "sg:orig_category":"Verzekeringen - Verzekeringskantoren",
    "sg:phone":"+31 30 293 4847",
    "sg:postcode":"3533 HA",
    "sg:province":"Utrecht",
    "wof:name":"Wildschut Bv",
    "wof:placetype":"venue"
},
  "geometry": {"coordinates":[5.095572,52.086159],"type":"Point"}
}