{
  "type": "Feature",
  "properties": {
    "iso:country":"NL",
    "sg:address":"Friesestr 11",
    "sg:city":"Coevorden",
    "sg:orig_category":"Hypotheken",
    "sg:phone":"+31 524 523 744",
    "sg:postcode":"7741 GR",
    "sg:province":"Drenthe",
    "wof:name":"Hypotheekhuus, 'T",
    "wof:placetype":"venue"
},
  "geometry": {"coordinates":[6.739625,52.661343],"type":"Point"}
}