{
  "type": "Feature",
  "properties": {
    "addr:full":"Pepynstr 12 Venlo Limburg 5921 HM",
    "addr:housenumber":"12",
    "addr:postcode":"5921 hm",
    "addr:street":"Pepynstr",
    "iso:country":"NL",
    "sg:address":"Pepynstr 12",
    "sg:city":"Venlo",
    "sg:orig_category":"Cafetaria'S",
    "sg:phone":"+31 77 387 5152",
    "sg:postcode":"5921 HM",
    "sg:province":"Limburg",
    "wof:name":"Joseph",
    "wof:placetype":"venue"
},
  "geometry": {"coordinates":[6.15458,51.366665],"type":"Point"}
}