{
  "type": "Feature",
  "properties": {
    "iso:country":"NL",
    "sg:address":"Binnendamseweg 64",
    "sg:city":"Giessenburg",
    "sg:orig_category":"Bloemen And Planten",
    "sg:phone":"+31 184 616 035",
    "sg:postcode":"3381 GD",
    "sg:province":"Zuid-Holland",
    "wof:name":"Vof A. Visser",
    "wof:placetype":"venue"
},
  "geometry": {"coordinates":[4.85434,51.832684],"type":"Point"}
}