{
  "type": "Feature",
  "properties": {
    "addr:full":"Albionstraat 53 Tilburg North Brabant 5047 SJ",
    "addr:housenumber":"53",
    "addr:postcode":"5047",
    "addr:street":"Albionstraat",
    "iso:country":"NL",
    "sg:address":"Albionstraat 53",
    "sg:city":"Tilburg",
    "sg:orig_category":"Autokeuringen",
    "sg:phone":"+31 13 570 0787",
    "sg:postcode":"5047 SJ",
    "sg:province":"North Brabant",
    "wof:name":"P. Vesseur",
    "wof:placetype":"venue"
},
  "geometry": {"coordinates":[5.037857,51.582981],"type":"Point"}
}