{
  "type": "Feature",
  "properties": {
    "iso:country":"NL",
    "sg:address":"Albionstraat 53",
    "sg:city":"Tilburg",
    "sg:orig_category":"Autokeuringen",
    "sg:phone":"+31 13 570 0787",
    "sg:postcode":"5047 SJ",
    "sg:province":"North Brabant",
    "wof:name":"P. Vesseur",
    "wof:placetype":"venue"
},
  "geometry": {"coordinates":[5.037857,51.582981],"type":"Point"}
}