{
  "type": "Feature",
  "properties": {
    "addr:full":"Alida De Jongstraat 8 Alphen A/D Rijn South Holland 2401 KT",
    "addr:housenumber":"8",
    "addr:postcode":"2401 kt",
    "addr:street":"Alida De Jongstraat",
    "iso:country":"NL",
    "sg:address":"Alida De Jongstraat 8",
    "sg:city":"Alphen A/D Rijn",
    "sg:orig_category":"Verzekeringen",
    "sg:phone":"+31 172 421 773",
    "sg:postcode":"2401 KT",
    "sg:province":"South Holland",
    "wof:name":"Mellink Assurantien Cv",
    "wof:placetype":"venue"
},
  "geometry": {"coordinates":[4.661435,52.156013],"type":"Point"}
}