{
  "type": "Feature",
  "properties": {
    "addr:full":"Dennenln 5 Putte Noord-Brabant 4645 RP",
    "addr:housenumber":"5",
    "addr:postcode":"4645 rp",
    "addr:street":"Dennenln",
    "iso:country":"NL",
    "sg:address":"Dennenln 5",
    "sg:city":"Putte",
    "sg:orig_category":"Antiquiteiten - Restauratie",
    "sg:phone":"+31 164 606 238",
    "sg:postcode":"4645 RP",
    "sg:province":"Noord-Brabant",
    "wof:name":"Witte Schilderijenrestauratie, F",
    "wof:placetype":"venue"
},
  "geometry": {"coordinates":[4.3986067772,51.3671875],"type":"Point"}
}