{
  "type": "Feature",
  "properties": {
    "iso:country":"NL",
    "sg:address":"Bosstr 66",
    "sg:city":"Didam",
    "sg:orig_category":"Adviesbureaus Financieel",
    "sg:phone":"+31 316 540 235",
    "sg:postcode":"6942 HG",
    "sg:province":"Gelderland",
    "wof:name":"Rosendahl",
    "wof:placetype":"venue"
},
  "geometry": {"coordinates":[6.155576,51.933922],"type":"Point"}
}