{
  "type": "Feature",
  "properties": {
    "addr:full":"Maarsbergenstr 32 S Gravenhage South Holland 2546 SR",
    "addr:housenumber":"32",
    "addr:postcode":"2546 sr",
    "addr:street":"Maarsbergenstr;S Gravenhage",
    "iso:country":"NL",
    "sg:address":"Maarsbergenstr 32",
    "sg:city":"S Gravenhage",
    "sg:orig_category":"Scholen Voor Basisonderwijs",
    "sg:phone":"+31 70 366 8900",
    "sg:postcode":"2546 SR",
    "sg:province":"South Holland",
    "wof:name":"Ark, De",
    "wof:placetype":"venue"
},
  "geometry": {"coordinates":[4.274271,52.058716],"type":"Point"}
}