{
  "type": "Feature",
  "properties": {
    "addr:full":"V Echtenstr 47A Hoogeveen Drenthe 7902 EL",
    "addr:housenumber":"47a;7902",
    "addr:postcode":"el",
    "iso:country":"NL",
    "sg:address":"V Echtenstr 47A",
    "sg:city":"Hoogeveen",
    "sg:orig_category":"Boeken Antiquarische En Gebruikte",
    "sg:phone":"+31 528 264 151",
    "sg:postcode":"7902 EL",
    "sg:province":"Drenthe",
    "wof:name":"Onder De Molen",
    "wof:placetype":"venue"
},
  "geometry": {"coordinates":[6.47552,52.725975],"type":"Point"}
}