{
  "type": "Feature",
  "properties": {
    "addr:full":"Molenvaart 99 Anna Paulowna Noord-Holland 1761 AC",
    "addr:housenumber":"99",
    "addr:postcode":"1761 ac",
    "addr:street":"Molenvaart",
    "iso:country":"NL",
    "sg:address":"Molenvaart 99",
    "sg:city":"Anna Paulowna",
    "sg:classifiers":[
        {
            "category":"Retail",
            "subcategory":"Auto Repair",
            "type":"Services"
        }
    ],
    "sg:phone":"+31 223 531 643",
    "sg:postcode":"1761 AC",
    "sg:province":"Noord-Holland",
    "sg:tags":[
        "garage"
    ],
    "wof:name":"Plompen, A",
    "wof:placetype":"venue"
},
  "geometry": {"coordinates":[4.828781,52.863628],"type":"Point"}
}