{
  "type": "Feature",
  "properties": {
    "addr:full":"Blokland 100 Montfoort Utrecht 3417 MR",
    "addr:housenumber":"100",
    "addr:postcode":"3417 mr",
    "addr:street":"Blokland",
    "iso:country":"NL",
    "sg:address":"Blokland 100",
    "sg:city":"Montfoort",
    "sg:orig_category":"Loodgieterswerk, Verwarming And Sanitaire Installaties",
    "sg:phone":"+31 348 475 291",
    "sg:postcode":"3417 MR",
    "sg:province":"Utrecht",
    "wof:name":"H Van Krimpen",
    "wof:placetype":"venue"
},
  "geometry": {"coordinates":[4.950154,52.029633],"type":"Point"}
}