{
  "type": "Feature",
  "properties": {
    "addr:full":"Industriewg 15 Drunen Noord-Brabant 5151 RV",
    "addr:housenumber":"15",
    "addr:postcode":"5151 rv",
    "addr:street":"Industriewg",
    "iso:country":"NL",
    "sg:address":"Industriewg 15",
    "sg:city":"Drunen",
    "sg:orig_category":"Meubelen",
    "sg:phone":"+31 416 378 723",
    "sg:postcode":"5151 RV",
    "sg:province":"Noord-Brabant",
    "wof:name":"Weert, Van",
    "wof:placetype":"venue"
},
  "geometry": {"coordinates":[5.160327,51.692158],"type":"Point"}
}