{
  "type": "Feature",
  "properties": {
    "addr:full":"F Bolstr 152 Amsterdam North Holland 1072 LS",
    "addr:housenumber":"152",
    "addr:postcode":"1072 ls",
    "iso:country":"NL",
    "sg:address":"F Bolstr 152",
    "sg:city":"Amsterdam",
    "sg:orig_category":"Schoenen",
    "sg:phone":"+31 20 662 1592",
    "sg:postcode":"1072 LS",
    "sg:province":"North Holland",
    "wof:name":"Jong En Zn, C De",
    "wof:placetype":"venue"
},
  "geometry": {"coordinates":[4.89067,52.354012],"type":"Point"}
}