{
  "type": "Feature",
  "properties": {
    "addr:full":"Tarbotstraat 185 Hoogvliet Rt Zuid-Holland 3192 BS",
    "addr:housenumber":"185",
    "addr:postcode":"rt;3192 bs",
    "addr:street":"Tarbotstraat",
    "iso:country":"NL",
    "sg:address":"Tarbotstraat 185",
    "sg:city":"Hoogvliet Rt",
    "sg:orig_category":"Verhuur Bouwmachines",
    "sg:phone":"+31 10 416 2018",
    "sg:postcode":"3192 BS",
    "sg:province":"Zuid-Holland",
    "wof:name":"Van Winssen",
    "wof:placetype":"venue"
},
  "geometry": {"coordinates":[4.36189,51.8526],"type":"Point"}
}