{
  "type": "Feature",
  "properties": {
    "addr:full":"K Ploegstr 1 Breda North Brabant 4818 EM",
    "addr:housenumber":"1",
    "addr:postcode":"4818 em",
    "addr:street":"Ploegstr",
    "iso:country":"NL",
    "sg:address":"K Ploegstr 1",
    "sg:city":"Breda",
    "sg:orig_category":"Cafetaria'S",
    "sg:phone":"+31 76 522 5591",
    "sg:postcode":"4818 EM",
    "sg:province":"North Brabant",
    "wof:name":"Kever Vof, De",
    "wof:placetype":"venue"
},
  "geometry": {"coordinates":[4.79102,51.578648],"type":"Point"}
}