{
  "type": "Feature",
  "properties": {
    "addr:full":"Lange Kleiweg 30 Rijswijk Zh South Holland 2288 GK",
    "addr:housenumber":"30",
    "addr:postcode":"2288 gk",
    "addr:street":"Lange Kleiweg",
    "iso:country":"NL",
    "sg:address":"Lange Kleiweg 30",
    "sg:city":"Rijswijk Zh",
    "sg:orig_category":"Overheidsdiensten",
    "sg:phone":"+31 70 413 0300",
    "sg:postcode":"2288 GK",
    "sg:province":"South Holland",
    "wof:name":"Bureau Nader Onderzoek Rijvaardigheid",
    "wof:placetype":"venue"
},
  "geometry": {"coordinates":[4.3262581825,52.0360221863],"type":"Point"}
}