{
  "type": "Feature",
  "properties": {
    "iso:country":"NL",
    "sg:address":"Hoofdstr 88",
    "sg:city":"Voorthuizen",
    "sg:orig_category":"Onderhoudswerken",
    "sg:phone":"+31 342 473 691",
    "sg:postcode":"3781 AJ",
    "sg:province":"Gelderland",
    "wof:name":"Batenburg",
    "wof:placetype":"venue"
},
  "geometry": {"coordinates":[5.597948,52.183067],"type":"Point"}
}