{
  "type": "Feature",
  "properties": {
    "addr:full":"J Vroegopsngl 6 Amsterdam Noord-Holland 1096 CN",
    "addr:housenumber":"6",
    "addr:postcode":"1096 cn",
    "iso:country":"NL",
    "sg:address":"J Vroegopsngl 6",
    "sg:city":"Amsterdam",
    "sg:orig_category":"Sportverenigingen En Ontspannings- Verenigingen",
    "sg:phone":"+31 20 693 1599",
    "sg:postcode":"1096 CN",
    "sg:province":"Noord-Holland",
    "sg:website":"http://www.skoll.nl",
    "wof:name":"Aasr Skoll Roeiver",
    "wof:placetype":"venue"
},
  "geometry": {"coordinates":[4.909056,52.336422],"type":"Point"}
}