{
  "type": "Feature",
  "properties": {
    "iso:country":"NL",
    "sg:address":"Graafsebaan 5",
    "sg:city":"Oss",
    "sg:orig_category":"Benzinestations And Brandstoffen",
    "sg:phone":"+31 412 646 912",
    "sg:postcode":"5342 LJ",
    "sg:province":"Virginia",
    "wof:name":"Total-Station Dananhof",
    "wof:placetype":"venue"
},
  "geometry": {"coordinates":[-77.235214,38.312599],"type":"Point"}
}