{
  "type": "Feature",
  "properties": {
    "iso:country":"NL",
    "sg:address":"Dorpsstr 53",
    "sg:city":"Lieshout",
    "sg:orig_category":"Montagebedrijven",
    "sg:phone":"+31 6 20367840",
    "sg:postcode":"5737 GA",
    "sg:province":"Noord-Brabant",
    "wof:name":"Brouwers",
    "wof:placetype":"venue"
},
  "geometry": {"coordinates":[5.593565,51.5233],"type":"Point"}
}