{
  "type": "Feature",
  "properties": {
    "addr:full":"Margrietstr 72 Mierlo North Brabant 5731 BR",
    "addr:housenumber":"72",
    "addr:postcode":"5731 br",
    "addr:street":"Margrietstr",
    "iso:country":"NL",
    "sg:address":"Margrietstr 72",
    "sg:city":"Mierlo",
    "sg:orig_category":"Kappers",
    "sg:phone":"+31 492 663 794",
    "sg:postcode":"5731 BR",
    "sg:province":"North Brabant",
    "wof:name":"Kapperke, Ons",
    "wof:placetype":"venue"
},
  "geometry": {"coordinates":[5.619494915,51.4418907166],"type":"Point"}
}