{
  "type": "Feature",
  "properties": {
    "iso:country":"NL",
    "sg:address":"Spinveld 21",
    "sg:city":"Breda",
    "sg:classifiers":[
        {
            "category":"Wholesale",
            "subcategory":"Meat",
            "type":"Manufacturing & Wholesale Goods"
        }
    ],
    "sg:phone":"+31 76 530 7530",
    "sg:postcode":"4815 HR",
    "sg:province":"Noord-Brabant",
    "sg:tags":[
        "hang-",
        "sluitwerk",
        "en"
    ],
    "wof:name":"Holtgrefe",
    "wof:placetype":"venue"
},
  "geometry": {"coordinates":[4.757056,51.599937],"type":"Point"}
}