{
  "type": "Feature",
  "properties": {
    "addr:full":"Pallietergaarde 3 Apeldoorn Gelderland 7329 HB",
    "addr:housenumber":"3",
    "addr:postcode":"7329 hb",
    "addr:street":"Pallietergaarde;Gelderland",
    "iso:country":"NL",
    "sg:address":"Pallietergaarde 3",
    "sg:city":"Apeldoorn",
    "sg:orig_category":"Verenigingen En Stichtingen",
    "sg:phone":"+31 55 542 9998",
    "sg:postcode":"7329 HB",
    "sg:province":"Gelderland",
    "sg:website":"http://www.wijk-werk.nl",
    "wof:name":"Wijkwerk, Sticht",
    "wof:placetype":"venue"
},
  "geometry": {"coordinates":[6.001357,52.199509],"type":"Point"}
}