{
  "type": "Feature",
  "properties": {
    "addr:full":"Delst 1 Nistelrode North Brabant 5388 EG",
    "addr:housenumber":"1",
    "addr:postcode":"5388 eg",
    "addr:street":"Delst",
    "iso:country":"NL",
    "sg:address":"Delst 1",
    "sg:city":"Nistelrode",
    "sg:orig_category":"Logopedisten",
    "sg:phone":"+31 412 611 422",
    "sg:postcode":"5388 EG",
    "sg:province":"North Brabant",
    "wof:name":"Smits-Jochems, J C M",
    "wof:placetype":"venue"
},
  "geometry": {"coordinates":[5.568409,51.700317],"type":"Point"}
}