{
  "type": "Feature",
  "properties": {
    "addr:full":"Postbus 806 Capelle Ad Yssel 2900 AV",
    "addr:housenumber":"806",
    "addr:postcode":"2900 av",
    "addr:street":"Postbus;Yssel",
    "iso:country":"NL",
    "sg:address":"Postbus 806",
    "sg:city":"Capelle Ad Yssel",
    "sg:orig_category":"Kabelexploitanten",
    "sg:phone":"+31 900 1580",
    "sg:postcode":"2900 AV",
    "sg:website":"http://www.upc.nl",
    "wof:name":"Upc Nederland Regio Zuid",
    "wof:placetype":"venue"
},
  "geometry": {"coordinates":[4.589700222,51.9327583313],"type":"Point"}
}