{
  "type": "Feature",
  "properties": {
    "addr:full":"Essendijk 38 Rhoon South Holland 3161 EE",
    "addr:housenumber":"38",
    "addr:postcode":"3161 ee",
    "addr:street":"Essendijk",
    "iso:country":"NL",
    "sg:address":"Essendijk 38",
    "sg:city":"Rhoon",
    "sg:orig_category":"Wegen And Sportterreinen",
    "sg:phone":"+31 10 501 5638",
    "sg:postcode":"3161 EE",
    "sg:province":"South Holland",
    "wof:name":"Gebrs. Barendregt Vof",
    "wof:placetype":"venue"
},
  "geometry": {"coordinates":[4.4470529556,51.8499565125],"type":"Point"}
}