{
  "type": "Feature",
  "properties": {
    "iso:country":"NL",
    "sg:address":"Noorderhoofdstr 1",
    "sg:city":"Krommenie",
    "sg:orig_category":"Verzekeringen - Verzekeringskantoren",
    "sg:phone":"+31 75 621 7302",
    "sg:postcode":"1561 AS",
    "sg:province":"Noord-Holland",
    "sg:website":"http://www.assudes.nl",
    "wof:name":"Assudes & Dietz",
    "wof:placetype":"venue"
},
  "geometry": {"coordinates":[4.769444,52.500195],"type":"Point"}
}