{
  "type": "Feature",
  "properties": {
    "addr:full":"Gulperberg 20 De Meern Utrecht 3453 RX",
    "addr:housenumber":"20",
    "addr:postcode":"3453 rx",
    "addr:street":"Gulperberg",
    "iso:country":"NL",
    "sg:address":"Gulperberg 20",
    "sg:city":"De Meern",
    "sg:orig_category":"Verenigingen En Stichtingen",
    "sg:phone":"+31 30 244 6237",
    "sg:postcode":"3453 RX",
    "sg:province":"Utrecht",
    "wof:name":"Heeren Loo Veluwse Alliantie, Sticht'S",
    "wof:placetype":"venue"
},
  "geometry": {"coordinates":[5.013594,52.082638],"type":"Point"}
}