{
  "type": "Feature",
  "properties": {
    "addr:full":"Olympiaweg 97 Wervershoof Noord-Holland 1693 EK",
    "addr:housenumber":"97",
    "addr:postcode":"1693 ek",
    "addr:street":"Olympiaweg",
    "iso:country":"NL",
    "sg:address":"Olympiaweg 97",
    "sg:city":"Wervershoof",
    "sg:orig_category":"Metaalwerken",
    "sg:phone":"+31 228 584 536",
    "sg:postcode":"1693 EK",
    "sg:province":"Noord-Holland",
    "wof:name":"R.J. Meijerink",
    "wof:placetype":"venue"
},
  "geometry": {"coordinates":[5.156183,52.730331],"type":"Point"}
}