{
  "type": "Feature",
  "properties": {
    "addr:full":"Moskouwei 4 Wijnjewoude Provincie Friesland 9241 WJ",
    "addr:housenumber":"4",
    "addr:postcode":"9241 wj",
    "addr:street":"Moskouwei;Provincie Friesland",
    "iso:country":"NL",
    "sg:address":"Moskouwei 4",
    "sg:city":"Wijnjewoude",
    "sg:orig_category":"Huizensloop And Bouwrijp Maken",
    "sg:phone":"+31 516 481 940",
    "sg:postcode":"9241 WJ",
    "sg:province":"Provincie Friesland",
    "wof:name":"Veenstra'S Loonbedrijf En Kraanverhuur",
    "wof:placetype":"venue"
},
  "geometry": {"coordinates":[6.205768,53.042664],"type":"Point"}
}