{
  "type": "Feature",
  "properties": {
    "addr:full":"Geerdinkhof 128 Amsterdam Zuidoost Noord-Holland 1103 PT",
    "addr:housenumber":"128",
    "addr:postcode":"zuidoost;1103 pt",
    "addr:street":"Geerdinkhof",
    "iso:country":"NL",
    "sg:address":"Geerdinkhof 128",
    "sg:city":"Amsterdam Zuidoost",
    "sg:orig_category":"Adviesbureaus Bouwkunde",
    "sg:phone":"+31 20 690 9560",
    "sg:postcode":"1103 PT",
    "sg:province":"Noord-Holland",
    "wof:name":"Graaff, Ing B P De",
    "wof:placetype":"venue"
},
  "geometry": {"coordinates":[4.985599,52.324326],"type":"Point"}
}