{
  "type": "Feature",
  "properties": {
    "iso:country":"NL",
    "sg:address":"De Huesmolen 157",
    "sg:city":"Hoorn Nh",
    "sg:orig_category":"Bloemen And Planten",
    "sg:phone":"+31 229 270 306",
    "sg:postcode":"1625 HX",
    "sg:province":"Noord-Holland",
    "wof:name":"Het Groene Paradijs",
    "wof:placetype":"venue"
},
  "geometry": {"coordinates":[5.054516,52.658092],"type":"Point"}
}