{
  "type": "Feature",
  "properties": {
    "addr:full":"Kast Annendaelstr 33 Roermond Limburg 6043 XS",
    "addr:housenumber":"33",
    "addr:postcode":"6043 xs",
    "iso:country":"NL",
    "sg:address":"Kast Annendaelstr 33",
    "sg:city":"Roermond",
    "sg:orig_category":"Mensendieck - Oefentherapeuten",
    "sg:phone":"+31 475 328 810",
    "sg:postcode":"6043 XS",
    "sg:province":"Limburg",
    "wof:name":"Breukers, A E P",
    "wof:placetype":"venue"
},
  "geometry": {"coordinates":[6.007661,51.187176],"type":"Point"}
}