{
  "type": "Feature",
  "properties": {
    "iso:country":"NL",
    "sg:address":"Vogelzankweg 20",
    "sg:city":"Landgraaf",
    "sg:orig_category":"Kappers",
    "sg:phone":"+31 45 531 2944",
    "sg:postcode":"6374 AH",
    "sg:province":"Limburg",
    "wof:name":"Kapsalon Miranka",
    "wof:placetype":"venue"
},
  "geometry": {"coordinates":[6.0376520157,50.9132652283],"type":"Point"}
}