{
  "type": "Feature",
  "properties": {
    "addr:full":"Korte Kruisweg 153 Maasdijk South Holland 2676 BS",
    "addr:housenumber":"153",
    "addr:postcode":"2676 bs",
    "addr:street":"Korte Kruisweg",
    "iso:country":"NL",
    "sg:address":"Korte Kruisweg 153",
    "sg:city":"Maasdijk",
    "sg:orig_category":"Verhuur Audiovisuele Apparatuur",
    "sg:phone":"+31 174 510 541",
    "sg:postcode":"2676 BS",
    "sg:province":"South Holland",
    "wof:name":"Ende Systems",
    "wof:placetype":"venue"
},
  "geometry": {"coordinates":[4.204507,51.953411],"type":"Point"}
}