{
  "type": "Feature",
  "properties": {
    "addr:full":"Vicarystr 1 Losser NL.08 7581 XZ",
    "addr:housenumber":"1;nl.08",
    "addr:postcode":"7581 xz",
    "addr:street":"Vicarystr",
    "iso:country":"NL",
    "sg:address":"Vicarystr 1",
    "sg:city":"Losser",
    "sg:orig_category":"Bejaarden - Verzorgingstehuizen",
    "sg:phone":"+31 53 537 5444",
    "sg:postcode":"7581 XZ",
    "sg:province":"NL.08",
    "wof:name":"Twente-Oost, Zorgcentr",
    "wof:placetype":"venue"
},
  "geometry": {"coordinates":[7.005908,52.264473],"type":"Point"}
}