{
  "type": "Feature",
  "properties": {
    "iso:country":"NL",
    "sg:address":"Jacob Ekelmansstraat 11",
    "sg:city":"Nieuwaal",
    "sg:orig_category":"Bloemen And Planten",
    "sg:phone":"+31 418 561 294",
    "sg:postcode":"5313 AS",
    "sg:province":"Gelderland",
    "wof:name":"Bloemisterij Van Steenbergen",
    "wof:placetype":"venue"
},
  "geometry": {"coordinates":[5.178946,51.808826],"type":"Point"}
}