{
  "type": "Feature",
  "properties": {
    "addr:full":"Viskenyln 2 Siddeburen Groningen 9628 AZ",
    "addr:housenumber":"2",
    "addr:postcode":"9628 az",
    "addr:street":"Viskenyln",
    "iso:country":"NL",
    "sg:address":"Viskenyln 2",
    "sg:city":"Siddeburen",
    "sg:orig_category":"Verenigingsgebouwen",
    "sg:phone":"+31 598 431 304",
    "sg:postcode":"9628 AZ",
    "sg:province":"Groningen",
    "wof:name":"Viskenij, De",
    "wof:placetype":"venue"
},
  "geometry": {"coordinates":[6.865007,53.248501],"type":"Point"}
}