{
  "type": "Feature",
  "properties": {
    "addr:full":"Oudeschans 63D Amsterdam Noord-Holland 1011 KW",
    "addr:housenumber":"63d",
    "addr:postcode":"1011 kw",
    "addr:street":"Oudeschans",
    "iso:country":"NL",
    "sg:address":"Oudeschans 63D",
    "sg:city":"Amsterdam",
    "sg:orig_category":"Antiquiteiten - Restauratie",
    "sg:phone":"+31 20 320 4623",
    "sg:postcode":"1011 KW",
    "sg:province":"Noord-Holland",
    "wof:name":"Zurcher, B",
    "wof:placetype":"venue"
},
  "geometry": {"coordinates":[4.903554,52.370407],"type":"Point"}
}