{
  "type": "Feature",
  "properties": {
    "addr:full":"Kromstraat 12 Veldhoven Noord-Brabant 5504 BC",
    "addr:housenumber":"12",
    "addr:postcode":"5504 bc",
    "addr:street":"Kromstraat",
    "iso:country":"NL",
    "sg:address":"Kromstraat 12",
    "sg:city":"Veldhoven",
    "sg:orig_category":"Herenmodezaken",
    "sg:phone":"+31 40 255 3252",
    "sg:postcode":"5504 BC",
    "sg:province":"Noord-Brabant",
    "wof:name":"Ziezo",
    "wof:placetype":"venue"
},
  "geometry": {"coordinates":[5.395608,51.403889],"type":"Point"}
}