{
  "type": "Feature",
  "properties": {
    "addr:full":"Noorderwg 9 Slochteren Groningen 9621 BM",
    "addr:housenumber":"9",
    "addr:postcode":"9621 bm",
    "addr:street":"Noorderwg",
    "iso:country":"NL",
    "sg:address":"Noorderwg 9",
    "sg:city":"Slochteren",
    "sg:orig_category":"Boeken En Tijdschriften",
    "sg:phone":"+31 598 422 777",
    "sg:postcode":"9621 BM",
    "sg:province":"Groningen",
    "wof:name":"Renso Vonk",
    "wof:placetype":"venue"
},
  "geometry": {"coordinates":[6.80256,53.215599],"type":"Point"}
}