{
  "type": "Feature",
  "properties": {
    "iso:country":"NL",
    "sg:address":"Nw Haagdk 46",
    "sg:city":"Breda",
    "sg:orig_category":"Biljartzalen",
    "sg:phone":"+31 76 521 1676",
    "sg:postcode":"4811 TE",
    "sg:province":"Noord-Brabant",
    "wof:name":"Michielsen",
    "wof:placetype":"venue"
},
  "geometry": {"coordinates":[4.763713,51.586185],"type":"Point"}
}