{
  "type": "Feature",
  "properties": {
    "addr:full":"Bozenhoven 61 Mijdrecht Utrecht 3641 AC",
    "addr:housenumber":"61",
    "addr:postcode":"3641 ac",
    "addr:street":"Bozenhoven",
    "iso:country":"NL",
    "sg:address":"Bozenhoven 61",
    "sg:city":"Mijdrecht",
    "sg:orig_category":"Verlichting And Huishoudartikelen",
    "sg:phone":"+31 297 282 006",
    "sg:postcode":"3641 AC",
    "sg:province":"Utrecht",
    "wof:name":"Henk Zuidervaart Elektroshop Vof",
    "wof:placetype":"venue"
},
  "geometry": {"coordinates":[4.867219,52.204475],"type":"Point"}
}