{
  "type": "Feature",
  "properties": {
    "addr:full":"Couperusstr 92 Groningen Groningen 9721 JJ",
    "addr:housenumber":"92",
    "addr:postcode":"9721 jj",
    "addr:street":"Couperusstr",
    "iso:country":"NL",
    "sg:address":"Couperusstr 92",
    "sg:city":"Groningen",
    "sg:orig_category":"Sportverenigingen En Ontspannings- Verenigingen",
    "sg:phone":"+31 50 526 8935",
    "sg:postcode":"9721 JJ",
    "sg:province":"Groningen",
    "wof:name":"Gruno Hengelsp Ver",
    "wof:placetype":"venue"
},
  "geometry": {"coordinates":[6.570161,53.199108],"type":"Point"}
}