{
  "type": "Feature",
  "properties": {
    "addr:full":"Stadhuisplein 10 Eindhoven Noord-Brabant 5611 EM",
    "addr:housenumber":"10",
    "addr:postcode":"5611 em",
    "addr:street":"Stadhuisplein",
    "iso:country":"NL",
    "sg:address":"Stadhuisplein 10",
    "sg:city":"Eindhoven",
    "sg:orig_category":"Overheidsdiensten",
    "sg:phone":"+31 40 238 9111",
    "sg:postcode":"5611 EM",
    "sg:province":"Noord-Brabant",
    "wof:name":"Gemeente Eindhoven",
    "wof:placetype":"venue"
},
  "geometry": {"coordinates":[5.4801211357,51.4355621338],"type":"Point"}
}