{
  "type": "Feature",
  "properties": {
    "addr:full":"Amperestr 21A Ymuiden Noord-Holland 1976 BG",
    "addr:housenumber":"21a",
    "addr:postcode":"1976",
    "addr:street":"Amperestr",
    "iso:country":"NL",
    "sg:address":"Amperestr 21A",
    "sg:city":"Ymuiden",
    "sg:orig_category":"Adviesbureaus",
    "sg:phone":"+31 255 537 846",
    "sg:postcode":"1976 BG",
    "sg:province":"Noord-Holland",
    "wof:name":"Tamalone Cons Bv",
    "wof:placetype":"venue"
},
  "geometry": {"coordinates":[4.5859,52.452972],"type":"Point"}
}