{
  "type": "Feature",
  "properties": {
    "addr:full":"Achterom 6A S Gravenhage South Holland 2511 AJ",
    "addr:housenumber":"6a",
    "addr:postcode":"2511 aj",
    "addr:street":"Achterom;S Gravenhage",
    "iso:country":"NL",
    "sg:address":"Achterom 6A",
    "sg:city":"S Gravenhage",
    "sg:orig_category":"Vertaalbureaus",
    "sg:phone":"+31 70 392 3822",
    "sg:postcode":"2511 AJ",
    "sg:province":"South Holland",
    "wof:name":"Portutext",
    "wof:placetype":"venue"
},
  "geometry": {"coordinates":[4.31627,52.07896],"type":"Point"}
}