{
  "type": "Feature",
  "properties": {
    "addr:full":"Robijnstraat 7 Alkmaar Noord-Holland 1812 RB",
    "addr:housenumber":"7",
    "addr:postcode":"1812 rb",
    "addr:street":"Robijnstraat",
    "iso:country":"NL",
    "sg:address":"Robijnstraat 7",
    "sg:city":"Alkmaar",
    "sg:orig_category":"Hypotheken And Hypotheekbanken",
    "sg:phone":"+31 72 541 4243",
    "sg:postcode":"1812 RB",
    "sg:province":"Noord-Holland",
    "wof:name":"Vlieg Assurantie Makelaars",
    "wof:placetype":"venue"
},
  "geometry": {"coordinates":[4.75763,52.615192],"type":"Point"}
}