{
  "type": "Feature",
  "properties": {
    "iso:country":"NL",
    "sg:address":"Stokhoekstraat 1",
    "sg:city":"Sint Michielsgestel",
    "sg:orig_category":"Loodgieterswerk, Verwarming And Sanitaire Installaties",
    "sg:phone":"+31 73 551 7957",
    "sg:postcode":"5271 AJ",
    "sg:province":"North Brabant",
    "wof:name":"Kapteijns Renovatie",
    "wof:placetype":"venue"
},
  "geometry": {"coordinates":[5.354411,51.649326],"type":"Point"}
}