{
  "type": "Feature",
  "properties": {
    "addr:full":"Stokhoekstraat 1 Sint Michielsgestel North Brabant 5271 AJ",
    "addr:housenumber":"1;michielsgestel",
    "addr:postcode":"5271 aj",
    "addr:street":"Stokhoekstraat",
    "iso:country":"NL",
    "sg:address":"Stokhoekstraat 1",
    "sg:city":"Sint Michielsgestel",
    "sg:orig_category":"Loodgieterswerk, Verwarming And Sanitaire Installaties",
    "sg:phone":"+31 73 551 7957",
    "sg:postcode":"5271 AJ",
    "sg:province":"North Brabant",
    "wof:name":"Kapteijns Renovatie",
    "wof:placetype":"venue"
},
  "geometry": {"coordinates":[5.354411,51.649326],"type":"Point"}
}