{
  "type": "Feature",
  "properties": {
    "addr:full":"Brederodestr 120 Amsterdam North Holland 1054 VH",
    "addr:housenumber":"120",
    "addr:postcode":"1054 vh",
    "iso:country":"NL",
    "sg:address":"Brederodestr 120",
    "sg:city":"Amsterdam",
    "sg:orig_category":"Beeldende Kunstenaars",
    "sg:phone":"+31 20 683 3522",
    "sg:postcode":"1054 VH",
    "sg:province":"North Holland",
    "wof:name":"Vian",
    "wof:placetype":"venue"
},
  "geometry": {"coordinates":[4.861568,52.360725],"type":"Point"}
}