{
  "type": "Feature",
  "properties": {
    "iso:country":"NL",
    "sg:address":"De Koumen 28",
    "sg:city":"Hoensbroek",
    "sg:orig_category":"Wasmachines En Wasdrogers - Onderhoud En Reparatie",
    "sg:phone":"+31 45 522 6315",
    "sg:postcode":"6433 KD",
    "sg:province":"Limburg",
    "sg:website":"http://www.siemens.nl",
    "wof:name":"Siemens",
    "wof:placetype":"venue"
},
  "geometry": {"coordinates":[5.9429512024,50.9083976746],"type":"Point"}
}