{
  "type": "Feature",
  "properties": {
    "addr:full":"Groenstraat 23 Maren Kessel Noord-Brabant 5398 HE",
    "addr:housenumber":"23",
    "addr:postcode":"5398 he",
    "addr:street":"Groenstraat;Maren Kessel",
    "iso:country":"NL",
    "sg:address":"Groenstraat 23",
    "sg:city":"Maren Kessel",
    "sg:classifiers":[
        {
            "category":"Fast Food",
            "type":"Food & Drink"
        }
    ],
    "sg:phone":"+31 412 479 465",
    "sg:postcode":"5398 HE",
    "sg:province":"Noord-Brabant",
    "sg:tags":[
        "afhaal",
        "restaurant"
    ],
    "wof:name":"Mark Van Den Hurk Evenementen Service",
    "wof:placetype":"venue"
},
  "geometry": {"coordinates":[5.396948,51.795605],"type":"Point"}
}