{
  "type": "Feature",
  "properties": {
    "addr:full":"Asselsestr 112 Apeldoorn Gelderland 7311 ES",
    "addr:housenumber":"112",
    "addr:postcode":"7311 es",
    "addr:street":"Gelderland",
    "iso:country":"NL",
    "sg:address":"Asselsestr 112",
    "sg:city":"Apeldoorn",
    "sg:orig_category":"Opticiens",
    "sg:phone":"+31 55 521 4640",
    "sg:postcode":"7311 ES",
    "sg:province":"Gelderland",
    "wof:name":"Charles Zuidgeest",
    "wof:placetype":"venue"
},
  "geometry": {"coordinates":[5.9538598061,52.2124595642],"type":"Point"}
}