{
  "type": "Feature",
  "properties": {
    "addr:full":"Kerkstr 12 Eibergen Gelderland 7151 BW",
    "addr:housenumber":"12",
    "addr:postcode":"7151 bw",
    "addr:street":"Kerkstr;Gelderland",
    "iso:country":"NL",
    "sg:address":"Kerkstr 12",
    "sg:city":"Eibergen",
    "sg:orig_category":"Woningbouw- Verenigingen En -Stichtingen",
    "sg:phone":"+31 545 473 685",
    "sg:postcode":"7151 BW",
    "sg:province":"Gelderland",
    "wof:name":"Std",
    "wof:placetype":"venue"
},
  "geometry": {"coordinates":[6.6450529099,52.1018791199],"type":"Point"}
}