{
  "type": "Feature",
  "properties": {
    "iso:country":"NL",
    "sg:address":"Koningstr 16A",
    "sg:city":"Arnhem",
    "sg:orig_category":"Kinderkleding",
    "sg:phone":"+31 26 351 9656",
    "sg:postcode":"6811 DE",
    "sg:province":"Gelderland",
    "wof:name":"Woods",
    "wof:placetype":"venue"
},
  "geometry": {"coordinates":[5.910204,51.981155],"type":"Point"}
}