{
  "type": "Feature",
  "properties": {
    "iso:country":"NL",
    "sg:address":"Vredenburchsngl 32",
    "sg:city":"Breda",
    "sg:orig_category":"Marktonderzoekbureaus",
    "sg:phone":"+31 76 520 6109",
    "sg:postcode":"4811 SJ",
    "sg:province":"North Brabant",
    "wof:name":"Hintzen",
    "wof:placetype":"venue"
},
  "geometry": {"coordinates":[4.770172,51.582359],"type":"Point"}
}