{
  "type": "Feature",
  "properties": {
    "addr:full":"Stokkumbrink 38 Enschede NL.08 7544 EC",
    "addr:housenumber":"38",
    "addr:postcode":"7544 ec",
    "addr:street":"Stokkumbrink",
    "iso:country":"NL",
    "sg:address":"Stokkumbrink 38",
    "sg:city":"Enschede",
    "sg:classifiers":[
        {
            "category":"Professional",
            "subcategory":"Accounting & Tax Preparation",
            "type":"Services"
        }
    ],
    "sg:phone":"+31 53 476 1742",
    "sg:postcode":"7544 EC",
    "sg:province":"NL.08",
    "sg:tags":[
        "accountant"
    ],
    "wof:name":"H. Broekhuizen Bv",
    "wof:placetype":"venue"
},
  "geometry": {"coordinates":[6.871519,52.187599],"type":"Point"}
}