{
  "type": "Feature",
  "properties": {
    "iso:country":"NL",
    "sg:address":"F Halsstr 67",
    "sg:city":"Amsterdam",
    "sg:orig_category":"Wijnkoperijen En -Groothandel",
    "sg:phone":"+31 20 671 6130",
    "sg:postcode":"1072 BM",
    "sg:province":"Noord-Holland",
    "sg:website":"http://www.vankrimpen-wijn.nl",
    "wof:name":"Krimpen Bv, Wijnhandel Van",
    "wof:placetype":"venue"
},
  "geometry": {"coordinates":[4.8887300491,52.3558273315],"type":"Point"}
}