{
  "type": "Feature",
  "properties": {
    "iso:country":"NL",
    "sg:address":"Dr Bauerstr 86",
    "sg:city":"Gorinchem",
    "sg:orig_category":"Nagelstudio'S",
    "sg:phone":"+31 183 629 643",
    "sg:postcode":"4205 KC",
    "sg:province":"Zuid-Holland",
    "wof:name":"Nicolien",
    "wof:placetype":"venue"
},
  "geometry": {"coordinates":[4.958973,51.840988],"type":"Point"}
}