{
  "type": "Feature",
  "properties": {
    "addr:full":"Zuiderwg 15 Schagen Noord-Holland 1741 NA",
    "addr:housenumber":"15",
    "addr:postcode":"1741 na",
    "addr:street":"Zuiderwg",
    "iso:country":"NL",
    "sg:address":"Zuiderwg 15",
    "sg:city":"Schagen",
    "sg:orig_category":"Scholen Voor Algemeen Voortgezet Onderwijs",
    "sg:phone":"+31 224 212 616",
    "sg:postcode":"1741 NA",
    "sg:province":"Noord-Holland",
    "wof:name":"Roc Kop Van Noord-Holland",
    "wof:placetype":"venue"
},
  "geometry": {"coordinates":[4.804307,52.782715],"type":"Point"}
}