{
  "type": "Feature",
  "properties": {
    "addr:full":"G Voetiusstr 1 Heusden Gem Heusd Noord-Brabant 5256 GM",
    "addr:housenumber":"1",
    "addr:postcode":"heusd;5256 gm",
    "iso:country":"NL",
    "sg:address":"G Voetiusstr 1",
    "sg:city":"Heusden Gem Heusd",
    "sg:orig_category":"Verenigingen En Stichtingen",
    "sg:phone":"+31 416 663 588",
    "sg:postcode":"5256 GM",
    "sg:province":"Noord-Brabant",
    "wof:name":"Orgel 2000",
    "wof:placetype":"venue"
},
  "geometry": {"coordinates":[5.13727,51.733074],"type":"Point"}
}