{
  "type": "Feature",
  "properties": {
    "addr:full":"De Weiert 10 Emmen Drenthe 7811 BH",
    "addr:housenumber":"10",
    "addr:postcode":"7811 bh",
    "addr:street":"De Weiert",
    "iso:country":"NL",
    "sg:address":"De Weiert 10",
    "sg:city":"Emmen",
    "sg:orig_category":"Boeken En Tijdschriften",
    "sg:phone":"+31 591 649 910",
    "sg:postcode":"7811 BH",
    "sg:province":"Drenthe",
    "wof:name":"Boekenvoordeel Bv",
    "wof:placetype":"venue"
},
  "geometry": {"coordinates":[6.89298,52.782429],"type":"Point"}
}