{
  "type": "Feature",
  "properties": {
    "addr:full":"Bereklauw 5A Cuijk Noord-Brabant 5432 AN",
    "addr:housenumber":"5a",
    "addr:postcode":"5432 an",
    "addr:street":"Bereklauw",
    "iso:country":"NL",
    "sg:address":"Bereklauw 5A",
    "sg:city":"Cuijk",
    "sg:orig_category":"Loodgieterswerk, Verwarming And Sanitaire Installaties",
    "sg:phone":"+31 485 317 134",
    "sg:postcode":"5432 AN",
    "sg:province":"Noord-Brabant",
    "wof:name":"J.W.J. Van Geelen",
    "wof:placetype":"venue"
},
  "geometry": {"coordinates":[5.86579,51.735802],"type":"Point"}
}