{
  "type": "Feature",
  "properties": {
    "iso:country":"NL",
    "sg:address":"Noordstr 6",
    "sg:city":"Bodegraven",
    "sg:orig_category":"Parketvloeren",
    "sg:phone":"+31 172 619 409",
    "sg:postcode":"2411 BJ",
    "sg:province":"Zuid-Holland",
    "wof:name":"Sfeer",
    "wof:placetype":"venue"
},
  "geometry": {"coordinates":[4.747547,52.085552],"type":"Point"}
}