{
  "type": "Feature",
  "properties": {
    "addr:full":"Winkelc Woensel 119 Eindhoven Noord-Brabant 5625 AG",
    "addr:housenumber":"119",
    "addr:postcode":"5625",
    "addr:street":"Winkelc Woensel",
    "iso:country":"NL",
    "sg:address":"Winkelc Woensel 119",
    "sg:city":"Eindhoven",
    "sg:orig_category":"Kaas",
    "sg:phone":"+31 40 248 1178",
    "sg:postcode":"5625 AG",
    "sg:province":"Noord-Brabant",
    "wof:name":"Waayer Bv",
    "wof:placetype":"venue"
},
  "geometry": {"coordinates":[5.4745368958,51.4678611755],"type":"Point"}
}