{
  "type": "Feature",
  "properties": {
    "addr:full":"Kerkwg 48 Heemskerk Noord-Holland 1961 JD",
    "addr:housenumber":"48",
    "addr:postcode":"1961 jd",
    "addr:street":"Kerkwg",
    "iso:country":"NL",
    "sg:address":"Kerkwg 48",
    "sg:city":"Heemskerk",
    "sg:orig_category":"Juweliers",
    "sg:phone":"+31 251 230 206",
    "sg:postcode":"1961 JD",
    "sg:province":"Noord-Holland",
    "wof:name":"Komen",
    "wof:placetype":"venue"
},
  "geometry": {"coordinates":[4.669473,52.510712],"type":"Point"}
}