{
  "type": "Feature",
  "properties": {
    "addr:full":"Veld En Beemd 19 Krimpen A/D Ijssel Zuid-Holland 2923 ER",
    "addr:housenumber":"19;a / d",
    "addr:postcode":"2923 er",
    "addr:street":"Veld En Beemd",
    "iso:country":"NL",
    "sg:address":"Veld En Beemd 19",
    "sg:city":"Krimpen A/D Ijssel",
    "sg:orig_category":"Loodgieterswerk, Verwarming And Sanitaire Installaties",
    "sg:phone":"+31 180 510 419",
    "sg:postcode":"2923 ER",
    "sg:province":"Zuid-Holland",
    "wof:name":"Techne",
    "wof:placetype":"venue"
},
  "geometry": {"coordinates":[4.603645,51.915333],"type":"Point"}
}