{
  "type": "Feature",
  "properties": {
    "addr:full":"Ln D Veren Naties 150 Ede Gld Gelderland 6716 JE",
    "addr:housenumber":"150",
    "addr:postcode":"6716 je",
    "addr:street":"Ln;Veren Naties;Gld Gelderland",
    "iso:country":"NL",
    "sg:address":"Ln D Veren Naties 150",
    "sg:city":"Ede Gld",
    "sg:orig_category":"Bioscopen",
    "sg:phone":"+31 900 3210321",
    "sg:postcode":"6716 JE",
    "sg:province":"Gelderland",
    "sg:website":"http://www.cinemec.nl",
    "wof:name":"Cinemec",
    "wof:placetype":"venue"
},
  "geometry": {"coordinates":[5.66767,52.044979],"type":"Point"}
}