{
  "type": "Feature",
  "properties": {
    "addr:full":"Lemel 31 Hapert Noord-Brabant 5527 JL",
    "addr:housenumber":"31",
    "addr:postcode":"5527 jl",
    "addr:street":"Lemel",
    "iso:country":"NL",
    "sg:address":"Lemel 31",
    "sg:city":"Hapert",
    "sg:orig_category":"Machineonderhoud En -Reparatie",
    "sg:phone":"+31 497 385 753",
    "sg:postcode":"5527 JL",
    "sg:province":"Noord-Brabant",
    "wof:name":"Heijden Vof, Van Der",
    "wof:placetype":"venue"
},
  "geometry": {"coordinates":[5.264272,51.373684],"type":"Point"}
}