{
  "type": "Feature",
  "properties": {
    "addr:full":"Jan Joostenstraat 43 Angeren Gelderland 6687 AB",
    "addr:housenumber":"43",
    "addr:postcode":"6687 ab",
    "addr:street":"Jan Joostenstraat;Gelderland",
    "iso:country":"NL",
    "sg:address":"Jan Joostenstraat 43",
    "sg:city":"Angeren",
    "sg:orig_category":"Banken And Kredietinstellingen",
    "sg:phone":"+31 26 325 9021",
    "sg:postcode":"6687 AB",
    "sg:province":"Gelderland",
    "wof:name":"Regiobank",
    "wof:placetype":"venue"
},
  "geometry": {"coordinates":[5.957818,51.915112],"type":"Point"}
}