{
  "type": "Feature",
  "properties": {
    "addr:full":"Nassaukade 1 Schoonhoven Zuid-Holland 2871 AR",
    "addr:housenumber":"1",
    "addr:postcode":"2871",
    "addr:street":"Nassaukade",
    "iso:country":"NL",
    "sg:address":"Nassaukade 1",
    "sg:city":"Schoonhoven",
    "sg:orig_category":"Metaalbekleding And -Behandeling",
    "sg:phone":"+31 182 382 292",
    "sg:postcode":"2871 AR",
    "sg:province":"Zuid-Holland",
    "wof:name":"Emaille-Atelier J.C. Boonstoppel",
    "wof:placetype":"venue"
},
  "geometry": {"coordinates":[4.856336,51.948349],"type":"Point"}
}