{
  "type": "Feature",
  "properties": {
    "addr:full":"Soerln 42 Amstelveen Noord-Holland 1185 JK",
    "addr:housenumber":"42",
    "addr:postcode":"1185 jk",
    "addr:street":"Soerln",
    "iso:country":"NL",
    "sg:address":"Soerln 42",
    "sg:city":"Amstelveen",
    "sg:orig_category":"Fotojournalisten Freelance",
    "sg:phone":"+31 20 643 7878",
    "sg:postcode":"1185 JK",
    "sg:province":"Noord-Holland",
    "wof:name":"Kuck, E J",
    "wof:placetype":"venue"
},
  "geometry": {"coordinates":[4.856945,52.303444],"type":"Point"}
}