{
  "type": "Feature",
  "properties": {
    "addr:full":"Hesseplaats 50 Rotterdam Zuid-Holland 3068 EA",
    "addr:housenumber":"50",
    "addr:postcode":"3068 ea",
    "addr:street":"Hesseplaats",
    "iso:country":"NL",
    "sg:address":"Hesseplaats 50",
    "sg:city":"Rotterdam",
    "sg:orig_category":"Bloemen And Planten",
    "sg:phone":"+31 10 421 4207",
    "sg:postcode":"3068 EA",
    "sg:province":"Zuid-Holland",
    "wof:name":"Bloemenboetiek Diane Van Dijk",
    "wof:placetype":"venue"
},
  "geometry": {"coordinates":[4.553186,51.962845],"type":"Point"}
}