{
  "type": "Feature",
  "properties": {
    "iso:country":"NL",
    "sg:address":"Kerkstraat 7",
    "sg:city":"Montfort",
    "sg:orig_category":"Schoenen",
    "sg:phone":"+31 475 541 437",
    "sg:postcode":"6065 AR",
    "sg:province":"Limburg",
    "wof:name":"J.H.H.P. Cuipers",
    "wof:placetype":"venue"
},
  "geometry": {"coordinates":[-90.431702,42.966061],"type":"Point"}
}