{
  "type": "Feature",
  "properties": {
    "iso:country":"NL",
    "sg:address":"Zuiderzeestrwg 620",
    "sg:city":"Wezep",
    "sg:orig_category":"Voetbalverenigingen",
    "sg:phone":"+31 38 376 0500",
    "sg:postcode":"8091 CX",
    "sg:province":"Gelderland",
    "wof:name":"Sc Glen Mills",
    "wof:placetype":"venue"
},
  "geometry": {"coordinates":[5.99888,52.458267],"type":"Point"}
}