{
  "type": "Feature",
  "properties": {
    "iso:country":"NL",
    "sg:address":"Hoxwier 63",
    "sg:city":"Almelo",
    "sg:orig_category":"Vertaalbureaus",
    "sg:phone":"+31 546 871 470",
    "sg:postcode":"7608 HB",
    "sg:province":"Overijssel",
    "wof:name":"Claude Tigrinate",
    "wof:placetype":"venue"
},
  "geometry": {"coordinates":[6.674778,52.382915],"type":"Point"}
}