{
  "type": "Feature",
  "properties": {
    "addr:full":"A V Bergenstr 108 Breda North Brabant 4811 SR",
    "addr:housenumber":"108",
    "addr:postcode":"4811 sr",
    "addr:street":"A;Bergenstr",
    "iso:country":"NL",
    "sg:address":"A V Bergenstr 108",
    "sg:city":"Breda",
    "sg:orig_category":"Verhuur",
    "sg:phone":"+31 76 520 9646",
    "sg:postcode":"4811 SR",
    "sg:province":"North Brabant",
    "wof:name":"Brouwer, De",
    "wof:placetype":"venue"
},
  "geometry": {"coordinates":[4.771685,51.591351],"type":"Point"}
}