{
  "type": "Feature",
  "properties": {
    "addr:full":"Postbus 85999 S Gravenhage South Holland 2508 CR",
    "addr:housenumber":"85999",
    "addr:postcode":"2508 cr",
    "addr:street":"Postbus;S Gravenhage",
    "iso:country":"NL",
    "sg:address":"Postbus 85999",
    "sg:city":"S Gravenhage",
    "sg:orig_category":"Verzekerings- Maatschappijen",
    "sg:phone":"+31 70 353 2100",
    "sg:postcode":"2508 CR",
    "sg:province":"South Holland",
    "sg:website":"http://www.oomverzekeringen.nl",
    "wof:name":"Oom",
    "wof:placetype":"venue"
},
  "geometry": {"coordinates":[4.31361,52.07832],"type":"Point"}
}