{
  "type": "Feature",
  "properties": {
    "iso:country":"NL",
    "sg:address":"Klinkenbergerwg 72",
    "sg:city":"Ede Gld",
    "sg:orig_category":"Autorijscholen",
    "sg:phone":"+31 318 612 141",
    "sg:postcode":"6711 ML",
    "sg:province":"Gelderland",
    "wof:name":"Braaksma, Fred",
    "wof:placetype":"venue"
},
  "geometry": {"coordinates":[5.671246,52.035522],"type":"Point"}
}