{
  "type": "Feature",
  "properties": {
    "addr:full":"Klinkenbergerwg 72 Ede Gld Gelderland 6711 ML",
    "addr:housenumber":"72",
    "addr:postcode":"6711 ml",
    "addr:street":"Klinkenbergerwg;Gld Gelderland",
    "iso:country":"NL",
    "sg:address":"Klinkenbergerwg 72",
    "sg:city":"Ede Gld",
    "sg:orig_category":"Autorijscholen",
    "sg:phone":"+31 318 612 141",
    "sg:postcode":"6711 ML",
    "sg:province":"Gelderland",
    "wof:name":"Braaksma, Fred",
    "wof:placetype":"venue"
},
  "geometry": {"coordinates":[5.671246,52.035522],"type":"Point"}
}