{
  "type": "Feature",
  "properties": {
    "addr:full":"Kerkweg-Oost 169 Waddinxveen South Holland 2741 HC",
    "addr:housenumber":"169",
    "addr:postcode":"2741 hc",
    "addr:street":"Kerkweg-Oost",
    "iso:country":"NL",
    "sg:address":"Kerkweg-Oost 169",
    "sg:city":"Waddinxveen",
    "sg:orig_category":"Wasserettes And Stomerijen",
    "sg:phone":"+31 182 617 840",
    "sg:postcode":"2741 HC",
    "sg:province":"South Holland",
    "wof:name":"Karin'S Wassalon",
    "wof:placetype":"venue"
},
  "geometry": {"coordinates":[4.6567611694,52.0442123413],"type":"Point"}
}