{
  "type": "Feature",
  "properties": {
    "iso:country":"NL",
    "sg:address":"Van Der Takstraat 31",
    "sg:city":"Rotterdam",
    "sg:orig_category":"Film-, Tv- And Videoproductie",
    "sg:phone":"+31 10 413 6209",
    "sg:postcode":"3071 LK",
    "sg:province":"South Holland",
    "wof:name":"Exro",
    "wof:placetype":"venue"
},
  "geometry": {"coordinates":[4.495395,51.914341],"type":"Point"}
}