{
  "type": "Feature",
  "properties": {
    "addr:full":"Hermanus Boexstraat 23 Eindhoven North Brabant 5611 AH",
    "addr:housenumber":"23",
    "addr:postcode":"5611 ah",
    "addr:street":"Hermanus Boexstraat",
    "iso:country":"NL",
    "sg:address":"Hermanus Boexstraat 23",
    "sg:city":"Eindhoven",
    "sg:orig_category":"Kappers",
    "sg:phone":"+31 40 244 1971",
    "sg:postcode":"5611 AH",
    "sg:province":"North Brabant",
    "wof:name":"Herenkapsalon Louwers En Van Rysingen Bv",
    "wof:placetype":"venue"
},
  "geometry": {"coordinates":[5.4784750938,51.4401893616],"type":"Point"}
}