{
  "type": "Feature",
  "properties": {
    "iso:country":"NL",
    "sg:address":"Binnensingel 53",
    "sg:city":"Deventer",
    "sg:orig_category":"Schilderwerk",
    "sg:phone":"+31 570 614 128",
    "sg:postcode":"7411 PL",
    "sg:province":"Overijssel",
    "wof:name":"Afdichtingsbedrijf Oostendorp",
    "wof:placetype":"venue"
},
  "geometry": {"coordinates":[6.157717,52.256134],"type":"Point"}
}