{
  "type": "Feature",
  "properties": {
    "addr:full":"Marconistr 29 Didam Gelderland 6942 PX",
    "addr:housenumber":"29",
    "addr:postcode":"6942 px",
    "addr:street":"Marconistr;Gelderland",
    "iso:country":"NL",
    "sg:address":"Marconistr 29",
    "sg:city":"Didam",
    "sg:orig_category":"Metaalbewerking",
    "sg:phone":"+31 316 373 302",
    "sg:postcode":"6942 PX",
    "sg:province":"Gelderland",
    "sg:website":"http://www.hettooling.nl",
    "wof:name":"Hts",
    "wof:placetype":"venue"
},
  "geometry": {"coordinates":[6.128348,51.936817],"type":"Point"}
}