{
  "type": "Feature",
  "properties": {
    "addr:full":"Fuut 23 Kockengen Utrecht 3628 CR",
    "addr:housenumber":"23",
    "addr:postcode":"3628 cr",
    "addr:street":"Fuut",
    "iso:country":"NL",
    "sg:address":"Fuut 23",
    "sg:city":"Kockengen",
    "sg:orig_category":"Vertaalbureaus",
    "sg:phone":"+31 346 241 615",
    "sg:postcode":"3628 CR",
    "sg:province":"Utrecht",
    "wof:name":"Koopmans-Wind, L",
    "wof:placetype":"venue"
},
  "geometry": {"coordinates":[4.950194,52.152843],"type":"Point"}
}