{
  "type": "Feature",
  "properties": {
    "iso:country":"NL",
    "sg:address":"Heemraadssngl 122",
    "sg:city":"Rotterdam",
    "sg:orig_category":"Kamerverhuur En -Bemiddeling",
    "sg:phone":"+31 10 478 1878",
    "sg:postcode":"3021 DH",
    "sg:province":"South Holland",
    "wof:name":"Efficiency",
    "wof:placetype":"venue"
},
  "geometry": {"coordinates":[4.4558949471,51.9176979065],"type":"Point"}
}