{
  "type": "Feature",
  "properties": {
    "addr:full":"Marathonln 11 Almere Flevoland 1318 ED",
    "addr:housenumber":"11",
    "addr:postcode":"1318 ed",
    "addr:street":"Marathonln;Flevoland",
    "iso:country":"NL",
    "sg:address":"Marathonln 11",
    "sg:city":"Almere",
    "sg:orig_category":"Scholen Voor Basisonderwijs",
    "sg:phone":"+31 36 529 2252",
    "sg:postcode":"1318 ED",
    "sg:province":"Flevoland",
    "wof:name":"Estafette, De",
    "wof:placetype":"venue"
},
  "geometry": {"coordinates":[5.250508,52.389187],"type":"Point"}
}