{
  "type": "Feature",
  "properties": {
    "addr:full":"Burg De Withstr 2 De Bilt Utrecht 3732 EK",
    "addr:housenumber":"2",
    "addr:postcode":"3732 ek",
    "iso:country":"NL",
    "sg:address":"Burg De Withstr 2",
    "sg:city":"De Bilt",
    "sg:orig_category":"Peuterspeelzalen",
    "sg:phone":"+31 30 220 0518",
    "sg:postcode":"3732 EK",
    "sg:province":"Utrecht",
    "wof:name":"Peuterland / 1E Stap",
    "wof:placetype":"venue"
},
  "geometry": {"coordinates":[5.18368,52.104729],"type":"Point"}
}