{
  "type": "Feature",
  "properties": {
    "iso:country":"NL",
    "sg:address":"Zanglijster 37",
    "sg:city":"Bunschoten Spakenburg",
    "sg:orig_category":"Goederenvervoer Over De Weg",
    "sg:phone":"+31 33 298 1551",
    "sg:postcode":"3752 ME",
    "sg:province":"Utrecht",
    "wof:name":"Koelewijn Transport Service",
    "wof:placetype":"venue"
},
  "geometry": {"coordinates":[5.360831,52.239655],"type":"Point"}
}