{
  "type": "Feature",
  "properties": {
    "addr:full":"Hertenhoek 36 Prinsenbeek Noord-Brabant 4841 SM",
    "addr:housenumber":"36",
    "addr:postcode":"4841 sm",
    "addr:street":"Hertenhoek",
    "iso:country":"NL",
    "sg:address":"Hertenhoek 36",
    "sg:city":"Prinsenbeek",
    "sg:orig_category":"Kappers",
    "sg:phone":"+31 76 587 8089",
    "sg:postcode":"4841 SM",
    "sg:province":"Noord-Brabant",
    "wof:name":"Pebbles",
    "wof:placetype":"venue"
},
  "geometry": {"coordinates":[4.720929,51.595188],"type":"Point"}
}