{
  "type": "Feature",
  "properties": {
    "iso:country":"NL",
    "sg:address":"Burg Woltersstraat 39",
    "sg:city":"Heesch",
    "sg:classifiers":[
        {
            "category":"Fast Food",
            "type":"Food & Drink"
        }
    ],
    "sg:phone":"+31 412 453 710",
    "sg:postcode":"5384 KT",
    "sg:province":"North Brabant",
    "sg:tags":[
        "afhaal",
        "restaurant"
    ],
    "wof:name":"Loderus",
    "wof:placetype":"venue"
},
  "geometry": {"coordinates":[5.517674,51.72924],"type":"Point"}
}