{
  "type": "Feature",
  "properties": {
    "iso:country":"NL",
    "sg:address":"Dorpsstraat 20",
    "sg:city":"Wilnis",
    "sg:orig_category":"Overheidsdiensten",
    "sg:phone":"+31 297 282 058",
    "sg:postcode":"3648 AH",
    "sg:province":"Utrecht",
    "wof:name":"De Schakel",
    "wof:placetype":"venue"
},
  "geometry": {"coordinates":[4.9027910233,52.1950683594],"type":"Point"}
}