{
  "type": "Feature",
  "properties": {
    "iso:country":"NL",
    "sg:address":"Wilhelminastr 57",
    "sg:city":"Haarlem",
    "sg:orig_category":"Psychologen",
    "sg:phone":"+31 23 531 7364",
    "sg:postcode":"2011 VL",
    "sg:province":"Noord-Holland",
    "sg:website":"http://www.home.wanadoo.nl/psycentrum",
    "wof:name":"Psychologengroep Centrum",
    "wof:placetype":"venue"
},
  "geometry": {"coordinates":[4.627228,52.378693],"type":"Point"}
}