{
  "type": "Feature",
  "properties": {
    "addr:full":"Steenwg 48 Utrecht Utrecht 3511 JS",
    "addr:housenumber":"48",
    "addr:postcode":"3511 js",
    "addr:street":"Steenwg",
    "iso:country":"NL",
    "sg:address":"Steenwg 48",
    "sg:city":"Utrecht",
    "sg:orig_category":"Kinderkleding",
    "sg:phone":"+31 30 236 4044",
    "sg:postcode":"3511 JS",
    "sg:province":"Utrecht",
    "wof:name":"Tusa",
    "wof:placetype":"venue"
},
  "geometry": {"coordinates":[5.117681,52.09063],"type":"Point"}
}