{
  "type": "Feature",
  "properties": {
    "addr:full":"Burg Buskensstr 50 Uden Noord-Brabant 5401 EE",
    "addr:housenumber":"50",
    "addr:postcode":"5401 ee",
    "addr:street":"Burg",
    "iso:country":"NL",
    "sg:address":"Burg Buskensstr 50",
    "sg:city":"Uden",
    "sg:orig_category":"Administratie- En Boekhoudkantoren",
    "sg:phone":"+31 413 251 751",
    "sg:postcode":"5401 EE",
    "sg:province":"Noord-Brabant",
    "wof:name":"Berg, Van Den",
    "wof:placetype":"venue"
},
  "geometry": {"coordinates":[-95.996078,34.580372],"type":"Point"}
}