{
  "type": "Feature",
  "properties": {
    "iso:country":"NL",
    "sg:address":"Buitenweistr 2",
    "sg:city":"Hardinxv Giessend",
    "sg:orig_category":"Betonijzervlechten",
    "sg:phone":"+31 184 620 320",
    "sg:postcode":"3372 BC",
    "sg:province":"British Columbia",
    "wof:name":"Diepstraten Bv",
    "wof:placetype":"venue"
},
  "geometry": {"coordinates":[-126.555511,54.485668],"type":"Point"}
}