{
  "type": "Feature",
  "properties": {
    "addr:full":"Hoogewaard 225 Koudekerk A/D Rijn Zuid-Holland 2396 AS",
    "addr:housenumber":"225;a / d",
    "addr:postcode":"2396 as",
    "addr:street":"Hoogewaard",
    "iso:country":"NL",
    "sg:address":"Hoogewaard 225",
    "sg:city":"Koudekerk A/D Rijn",
    "sg:orig_category":"Goederenvervoer Over De Weg",
    "sg:phone":"+31 71 342 0020",
    "sg:postcode":"2396 AS",
    "sg:province":"Zuid-Holland",
    "wof:name":"W. Van Der Meijden Bv",
    "wof:placetype":"venue"
},
  "geometry": {"coordinates":[4.625981,52.137764],"type":"Point"}
}