{
  "type": "Feature",
  "properties": {
    "iso:country":"NL",
    "sg:address":"Kerkpad 1",
    "sg:city":"Ter Aar",
    "sg:orig_category":"Banken And Kredietinstellingen",
    "sg:phone":"+31 172 536 460",
    "sg:postcode":"2461 CT",
    "sg:province":"Zuid-Holland",
    "wof:name":"Rabobank",
    "wof:placetype":"venue"
},
  "geometry": {"coordinates":[4.727107,52.18119],"type":"Point"}
}