{
  "type": "Feature",
  "properties": {
    "addr:full":"Voortswg 4 Saasveld Overijssel 7597 KC",
    "addr:housenumber":"4",
    "addr:postcode":"7597 kc",
    "addr:street":"Voortswg",
    "iso:country":"NL",
    "sg:address":"Voortswg 4",
    "sg:city":"Saasveld",
    "sg:orig_category":"Foerage",
    "sg:phone":"+31 74 349 4421",
    "sg:postcode":"7597 KC",
    "sg:province":"Overijssel",
    "wof:name":"Munsterhuis, H",
    "wof:placetype":"venue"
},
  "geometry": {"coordinates":[6.839935,52.327824],"type":"Point"}
}