{
  "type": "Feature",
  "properties": {
    "iso:country":"NL",
    "sg:address":"Zernikedreef 12",
    "sg:city":"Leiden",
    "sg:orig_category":"Farmaceutische Industrie En Groothandel",
    "sg:phone":"+31 71 524 4044",
    "sg:postcode":"2333 CL",
    "sg:province":"South Holland",
    "wof:name":"Octoplus",
    "wof:placetype":"venue"
},
  "geometry": {"coordinates":[4.468282,52.166843],"type":"Point"}
}