{
  "type": "Feature",
  "properties": {
    "addr:full":"Turfmarkt 10 Katwijk Zh South Holland 2223 EH",
    "addr:housenumber":"10",
    "addr:postcode":"zh;2223 eh",
    "addr:street":"Turfmarkt",
    "iso:country":"NL",
    "sg:address":"Turfmarkt 10",
    "sg:city":"Katwijk Zh",
    "sg:orig_category":"Boekhouders",
    "sg:phone":"+31 71 402 7624",
    "sg:postcode":"2223 EH",
    "sg:province":"South Holland",
    "wof:name":"Administratiekantoor Kok & Van Schie",
    "wof:placetype":"venue"
},
  "geometry": {"coordinates":[4.424835,52.194057],"type":"Point"}
}