{
  "type": "Feature",
  "properties": {
    "addr:full":"Meester Hofstraat 19 Giethoorn NL.08 8355 DA",
    "addr:housenumber":"19;nl.08",
    "addr:postcode":"8355 da",
    "addr:street":"Meester Hofstraat",
    "iso:country":"NL",
    "sg:address":"Meester Hofstraat 19",
    "sg:city":"Giethoorn",
    "sg:orig_category":"Watersport-, Sport- And Kampeerbenodigdheden Verhuur",
    "sg:phone":"+31 521 362 187",
    "sg:postcode":"8355 DA",
    "sg:province":"NL.08",
    "wof:name":"Cirrus -Jachtverhuur",
    "wof:placetype":"venue"
},
  "geometry": {"coordinates":[6.081911087,52.7211341858],"type":"Point"}
}