{
  "type": "Feature",
  "properties": {
    "addr:full":"Breewg 31 Linne Obwalden 6067 CH",
    "addr:housenumber":"31",
    "addr:postcode":"6067",
    "addr:street":"Breewg",
    "iso:country":"NL",
    "sg:address":"Breewg 31",
    "sg:city":"Linne",
    "sg:orig_category":"Begrafenisverzorging",
    "sg:phone":"+31 475 468 150",
    "sg:postcode":"6067 CH",
    "sg:province":"Obwalden",
    "wof:name":"Schuren",
    "wof:placetype":"venue"
},
  "geometry": {"coordinates":[8.278651,46.802223],"type":"Point"}
}