{
  "type": "Feature",
  "properties": {
    "iso:country":"NL",
    "sg:address":"Atelier Ns Station Den Dolder",
    "sg:city":"Dolder",
    "sg:orig_category":"Beeldende Kunstenaars",
    "sg:phone":"+31 6 25077665",
    "sg:postcode":"DEN ",
    "wof:name":"Bos Schilderkunsten, I",
    "wof:placetype":"venue"
},
  "geometry": {"coordinates":[5.241445,52.139938],"type":"Point"}
}