{
  "type": "Feature",
  "properties": {
    "addr:full":"Engwg 15 Hoogland Utrecht 3828 CJ",
    "addr:housenumber":"15",
    "addr:postcode":"3828 cj",
    "addr:street":"Engwg",
    "iso:country":"NL",
    "sg:address":"Engwg 15",
    "sg:city":"Hoogland",
    "sg:orig_category":"Sportverenigingen En Ontspannings- Verenigingen",
    "sg:phone":"+31 33 480 1904",
    "sg:postcode":"3828 CJ",
    "sg:province":"Utrecht",
    "wof:name":"Eemruiters, De",
    "wof:placetype":"venue"
},
  "geometry": {"coordinates":[5.381369,52.18581],"type":"Point"}
}