{
  "type": "Feature",
  "properties": {
    "addr:full":"Hoofdwg 50 Zuurdyk Groningen 9966 VC",
    "addr:housenumber":"50",
    "addr:postcode":"9966 vc",
    "addr:street":"Hoofdwg",
    "iso:country":"NL",
    "sg:address":"Hoofdwg 50",
    "sg:city":"Zuurdyk",
    "sg:orig_category":"Biljartzalen",
    "sg:phone":"+31 595 571 545",
    "sg:postcode":"9966 VC",
    "sg:province":"Groningen",
    "wof:name":"Billeke De Beer",
    "wof:placetype":"venue"
},
  "geometry": {"coordinates":[6.377062,53.33741],"type":"Point"}
}