{
  "type": "Feature",
  "properties": {
    "addr:full":"P Ellingstr 14 Almere Flevoland 1333 PT",
    "addr:housenumber":"14",
    "addr:postcode":"1333",
    "addr:street":"P;Flevoland;Pt",
    "iso:country":"NL",
    "sg:address":"P Ellingstr 14",
    "sg:city":"Almere",
    "sg:orig_category":"Artiesten/Gezelschappen",
    "sg:phone":"+31 36 532 9981",
    "sg:postcode":"1333 PT",
    "sg:province":"Flevoland",
    "sg:website":"http://www.fratrescorona.com",
    "wof:name":"Salonduo, Het",
    "wof:placetype":"venue"
},
  "geometry": {"coordinates":[5.251628,52.397125],"type":"Point"}
}