{
  "type": "Feature",
  "properties": {
    "addr:full":"Achterom 5 Almere Flevoland 1334 BE",
    "addr:housenumber":"5",
    "addr:postcode":"1334",
    "addr:street":"Achterom;Flevoland",
    "iso:country":"NL",
    "sg:address":"Achterom 5",
    "sg:city":"Almere",
    "sg:orig_category":"Balletscholen",
    "sg:phone":"+31 36 532 9771",
    "sg:postcode":"1334 BE",
    "sg:province":"Flevoland",
    "wof:name":"Tendens Studio'S",
    "wof:placetype":"venue"
},
  "geometry": {"coordinates":[5.277399,52.393562],"type":"Point"}
}