{
  "type": "Feature",
  "properties": {
    "addr:full":"Kerkstr 28 Baarn Utrecht 3741 AK",
    "addr:housenumber":"28",
    "addr:postcode":"3741 ak",
    "addr:street":"Kerkstr",
    "iso:country":"NL",
    "sg:address":"Kerkstr 28",
    "sg:city":"Baarn",
    "sg:orig_category":"Omroep",
    "sg:phone":"+31 35 541 1420",
    "sg:postcode":"3741 AK",
    "sg:province":"Utrecht",
    "wof:name":"Baarnse Ziekenomroep, Sticht",
    "wof:placetype":"venue"
},
  "geometry": {"coordinates":[5.312465,52.224945],"type":"Point"}
}