{
  "type": "Feature",
  "properties": {
    "iso:country":"NL",
    "sg:address":"Aarstraat 7",
    "sg:city":"Almere",
    "sg:orig_category":"Kappers",
    "sg:phone":"+31 36 533 1866",
    "sg:postcode":"1316 GR",
    "sg:province":"Flevoland",
    "wof:name":"M.S. Bellinga",
    "wof:placetype":"venue"
},
  "geometry": {"coordinates":[5.222804,52.383728],"type":"Point"}
}