{
  "type": "Feature",
  "properties": {
    "addr:full":"Royaards Van Den Hamkade 48 Utrecht Utrecht 3552 CP",
    "addr:housenumber":"48",
    "addr:postcode":"3552 cp",
    "addr:street":"Royaards Van Den Hamkade",
    "iso:country":"NL",
    "sg:address":"Royaards Van Den Hamkade 48",
    "sg:city":"Utrecht",
    "sg:orig_category":"Woningbouw- Verenigingen En -Stichtingen",
    "sg:phone":"+31 30 243 8097",
    "sg:postcode":"3552 CP",
    "sg:province":"Utrecht",
    "sg:website":"http://www.woningstichtingonsbelang.nl",
    "wof:name":"Ons Belang",
    "wof:placetype":"venue"
},
  "geometry": {"coordinates":[5.0952401161,52.105556488],"type":"Point"}
}