{
  "type": "Feature",
  "properties": {
    "addr:full":"Calvariestr 50 Maastricht Limburg 6211 NK",
    "addr:housenumber":"50",
    "addr:postcode":"6211 nk",
    "addr:street":"Calvariestr",
    "iso:country":"NL",
    "sg:address":"Calvariestr 50",
    "sg:city":"Maastricht",
    "sg:orig_category":"Gelegenheidskleding",
    "sg:phone":"+31 43 321 4120",
    "sg:postcode":"6211 NK",
    "sg:province":"Limburg",
    "wof:name":"Pieter Walters Mannenmode",
    "wof:placetype":"venue"
},
  "geometry": {"coordinates":[5.680289,50.847439],"type":"Point"}
}