{
  "type": "Feature",
  "properties": {
    "addr:full":"Rachmaninovstraat 26 Almere NL. 1323 NG",
    "addr:housenumber":"26",
    "addr:postcode":"1323 ng",
    "addr:street":"Rachmaninovstraat;Nl.",
    "iso:country":"NL",
    "sg:address":"Rachmaninovstraat 26",
    "sg:city":"Almere",
    "sg:orig_category":"Bloemen And Planten",
    "sg:phone":"+31 36 546 4652",
    "sg:postcode":"1323 NG",
    "sg:province":"NL.",
    "wof:name":"Jung Ok",
    "wof:placetype":"venue"
},
  "geometry": {"coordinates":[5.193047,52.367874],"type":"Point"}
}