{
  "type": "Feature",
  "properties": {
    "addr:full":"Arkansasdreef 19 Utrecht Utrecht 3565 AP",
    "addr:housenumber":"19",
    "addr:postcode":"3565 ap",
    "addr:street":"Arkansasdreef",
    "iso:country":"NL",
    "sg:address":"Arkansasdreef 19",
    "sg:city":"Utrecht",
    "sg:orig_category":"Farmaceutische Producten Gh",
    "sg:phone":"+31 30 261 2083",
    "sg:postcode":"3565 AP",
    "sg:province":"Utrecht",
    "wof:name":"Meekers Medical",
    "wof:placetype":"venue"
},
  "geometry": {"coordinates":[5.089231,52.128151],"type":"Point"}
}