{
  "type": "Feature",
  "properties": {
    "addr:full":"Cornelisstg 12 Haarlem Noord-Holland 2011 EA",
    "addr:housenumber":"12",
    "addr:postcode":"2011 ea",
    "addr:street":"Cornelisstg",
    "iso:country":"NL",
    "sg:address":"Cornelisstg 12",
    "sg:city":"Haarlem",
    "sg:orig_category":"Antiquiteiten",
    "sg:phone":"+31 23 532 3305",
    "sg:postcode":"2011 EA",
    "sg:province":"Noord-Holland",
    "wof:name":"Pelgrom, J",
    "wof:placetype":"venue"
},
  "geometry": {"coordinates":[4.63259,52.377579],"type":"Point"}
}