{
  "type": "Feature",
  "properties": {
    "addr:full":"Weversstraat 23 Rhenen Utrecht 3911 KE",
    "addr:housenumber":"23",
    "addr:postcode":"3911 ke",
    "addr:street":"Weversstraat",
    "iso:country":"NL",
    "sg:address":"Weversstraat 23",
    "sg:city":"Rhenen",
    "sg:orig_category":"Boekhouders",
    "sg:phone":"+31 317 615 037",
    "sg:postcode":"3911 KE",
    "sg:province":"Utrecht",
    "wof:name":"3B Plus",
    "wof:placetype":"venue"
},
  "geometry": {"coordinates":[5.566304,51.956635],"type":"Point"}
}