{
  "type": "Feature",
  "properties": {
    "addr:full":"Beatrixstraat 78 Nederweert Limburg 6031 BC",
    "addr:housenumber":"78",
    "addr:postcode":"6031 bc",
    "addr:street":"Beatrixstraat",
    "iso:country":"NL",
    "sg:address":"Beatrixstraat 78",
    "sg:city":"Nederweert",
    "sg:orig_category":"Metaalwerken",
    "sg:phone":"+31 495 632 901",
    "sg:postcode":"6031 BC",
    "sg:province":"Limburg",
    "wof:name":"Stukadoorsbedrijf G. Peeters",
    "wof:placetype":"venue"
},
  "geometry": {"coordinates":[5.761176,51.285404],"type":"Point"}
}