{
  "type": "Feature",
  "properties": {
    "iso:country":"NL",
    "sg:address":"Industriewg 46",
    "sg:city":"Grootebroek",
    "sg:orig_category":"Verzekeringen - Verzekeringskantoren",
    "sg:phone":"+31 228 524 898",
    "sg:postcode":"1613 KV",
    "sg:province":"North Holland",
    "wof:name":"Hbp",
    "wof:placetype":"venue"
},
  "geometry": {"coordinates":[5.229345,52.694061],"type":"Point"}
}