{
  "type": "Feature",
  "properties": {
    "addr:full":"Korenstr 134 Apeldoorn Gelderland 7311 LP",
    "addr:housenumber":"134",
    "addr:postcode":"7311 lp",
    "addr:street":"Gelderland",
    "iso:country":"NL",
    "sg:address":"Korenstr 134",
    "sg:city":"Apeldoorn",
    "sg:orig_category":"Bloemen En Planten",
    "sg:phone":"+31 55 522 1722",
    "sg:postcode":"7311 LP",
    "sg:province":"Gelderland",
    "wof:name":"Bloemerie, De",
    "wof:placetype":"venue"
},
  "geometry": {"coordinates":[5.960132,52.214603],"type":"Point"}
}