{
  "type": "Feature",
  "properties": {
    "addr:full":"L H Pottstr 4 Olst Overijssel 8121 BN",
    "addr:housenumber":"4",
    "addr:postcode":"8121 bn",
    "iso:country":"NL",
    "sg:address":"L H Pottstr 4",
    "sg:city":"Olst",
    "sg:orig_category":"Artsen - Huisartsen",
    "sg:phone":"+31 570 562 722",
    "sg:postcode":"8121 BN",
    "sg:province":"Overijssel",
    "wof:name":"Numan, J J C",
    "wof:placetype":"venue"
},
  "geometry": {"coordinates":[6.114156,52.33836],"type":"Point"}
}