{
  "type": "Feature",
  "properties": {
    "addr:full":"Grotestr 312 Waalwyk Noord-Brabant 5142 CD",
    "addr:housenumber":"312",
    "addr:postcode":"5142 cd",
    "addr:street":"Waalwyk",
    "iso:country":"NL",
    "sg:address":"Grotestr 312",
    "sg:city":"Waalwyk",
    "sg:orig_category":"Bloemen En Planten",
    "sg:phone":"+31 416 332 571",
    "sg:postcode":"5142 CD",
    "sg:province":"Noord-Brabant",
    "wof:name":"Bladel, A Van",
    "wof:placetype":"venue"
},
  "geometry": {"coordinates":[5.073529,51.691051],"type":"Point"}
}