{
  "type": "Feature",
  "properties": {
    "addr:full":"Badelochstraat 6 Ouderkerk A/D Amstel Noord-Holland 1191 AL",
    "addr:housenumber":"6;a / d",
    "addr:postcode":"1191 al",
    "addr:street":"Badelochstraat",
    "iso:country":"NL",
    "sg:address":"Badelochstraat 6",
    "sg:city":"Ouderkerk A/D Amstel",
    "sg:orig_category":"Artsen And Specialisten",
    "sg:phone":"+31 20 496 4938",
    "sg:postcode":"1191 AL",
    "sg:province":"Noord-Holland",
    "wof:name":"Drs. M. Van Breukelen",
    "wof:placetype":"venue"
},
  "geometry": {"coordinates":[4.902142,52.298561],"type":"Point"}
}