{
  "type": "Feature",
  "properties": {
    "iso:country":"NL",
    "sg:address":"Marcusstr 29 I",
    "sg:city":"Amsterdam",
    "sg:orig_category":"Glazenwasserijen",
    "sg:phone":"+31 20 470 1453",
    "sg:postcode":"1091 TJ",
    "sg:province":"Noord-Holland",
    "wof:name":"Salex",
    "wof:placetype":"venue"
},
  "geometry": {"coordinates":[4.91306,52.35487],"type":"Point"}
}