{
  "type": "Feature",
  "properties": {
    "addr:full":"Torenveld 6 Boekel Noord-Brabant 5427 JJ",
    "addr:housenumber":"6",
    "addr:postcode":"5427 jj",
    "addr:street":"Torenveld",
    "iso:country":"NL",
    "sg:address":"Torenveld 6",
    "sg:city":"Boekel",
    "sg:orig_category":"Metselwerken",
    "sg:phone":"+31 492 324 687",
    "sg:postcode":"5427 JJ",
    "sg:province":"Noord-Brabant",
    "wof:name":"Lankveld, W G M Van",
    "wof:placetype":"venue"
},
  "geometry": {"coordinates":[5.690457,51.600895],"type":"Point"}
}