{
  "type": "Feature",
  "properties": {
    "iso:country":"NL",
    "sg:address":"Torenveld 6",
    "sg:city":"Boekel",
    "sg:orig_category":"Metselwerken",
    "sg:phone":"+31 492 324 687",
    "sg:postcode":"5427 JJ",
    "sg:province":"Noord-Brabant",
    "wof:name":"Lankveld, W G M Van",
    "wof:placetype":"venue"
},
  "geometry": {"coordinates":[5.690457,51.600895],"type":"Point"}
}