{
  "type": "Feature",
  "properties": {
    "addr:full":"Tarweveld 6 Woudenberg Utrecht 3931 WP",
    "addr:housenumber":"6",
    "addr:postcode":"3931 wp",
    "addr:street":"Tarweveld",
    "iso:country":"NL",
    "sg:address":"Tarweveld 6",
    "sg:city":"Woudenberg",
    "sg:orig_category":"Werving En Selectie",
    "sg:phone":"+31 33 432 3751",
    "sg:postcode":"3931 WP",
    "sg:province":"Utrecht",
    "wof:name":"Aelerdinck",
    "wof:placetype":"venue"
},
  "geometry": {"coordinates":[5.4291372299,52.0796127319],"type":"Point"}
}