{
  "type": "Feature",
  "properties": {
    "addr:full":"Parkdreef 165 Zoetermeer Zuid-Holland 2724 ET",
    "addr:housenumber":"165",
    "addr:postcode":"2724 et",
    "addr:street":"Parkdreef",
    "iso:country":"NL",
    "sg:address":"Parkdreef 165",
    "sg:city":"Zoetermeer",
    "sg:orig_category":"Woningstoffeerders",
    "sg:phone":"+31 79 342 3281",
    "sg:postcode":"2724 ET",
    "sg:province":"Zuid-Holland",
    "wof:name":"Gall?",
    "wof:placetype":"venue"
},
  "geometry": {"coordinates":[4.5117387772,52.0658798218],"type":"Point"}
}