{
  "type": "Feature",
  "properties": {
    "iso:country":"NL",
    "sg:address":"Parkdreef 165",
    "sg:city":"Zoetermeer",
    "sg:orig_category":"Woningstoffeerders",
    "sg:phone":"+31 79 342 3281",
    "sg:postcode":"2724 ET",
    "sg:province":"Zuid-Holland",
    "wof:name":"Gall?",
    "wof:placetype":"venue"
},
  "geometry": {"coordinates":[4.5117387772,52.0658798218],"type":"Point"}
}