{
  "type": "Feature",
  "properties": {
    "addr:full":"Vendeliers 4 Ulft Gelderland 7071 KM",
    "addr:housenumber":"4",
    "addr:postcode":"7071",
    "addr:street":"Vendeliers;Gelderland;Km",
    "iso:country":"NL",
    "sg:address":"Vendeliers 4",
    "sg:city":"Ulft",
    "sg:orig_category":"Schilders",
    "sg:phone":"+31 315 685 389",
    "sg:postcode":"7071 KM",
    "sg:province":"Gelderland",
    "wof:name":"Bruil, Gerrie",
    "wof:placetype":"venue"
},
  "geometry": {"coordinates":[6.373204,51.891647],"type":"Point"}
}