{
  "type": "Feature",
  "properties": {
    "addr:full":"Danielstr 4 Wemeldinge Zeeland 4424 AZ",
    "addr:housenumber":"4",
    "addr:postcode":"4424",
    "addr:street":"Danielstr",
    "iso:country":"NL",
    "sg:address":"Danielstr 4",
    "sg:city":"Wemeldinge",
    "sg:orig_category":"Wolartikelen En Breiwol",
    "sg:phone":"+31 113 622 312",
    "sg:postcode":"4424 AZ",
    "sg:province":"Zeeland",
    "wof:name":"Nelie",
    "wof:placetype":"venue"
},
  "geometry": {"coordinates":[3.9987859726,51.5169677734],"type":"Point"}
}