{
  "type": "Feature",
  "properties": {
    "addr:full":"Dr Bardetplaats 10 Doetinchem Gelderland 7001 DV",
    "addr:housenumber":"10",
    "addr:postcode":"7001",
    "addr:street":"Dr Bardetplaats;Gelderland",
    "iso:country":"NL",
    "sg:address":"Dr Bardetplaats 10",
    "sg:city":"Doetinchem",
    "sg:orig_category":"Warenhuizen",
    "sg:phone":"+31 314 354 566",
    "sg:postcode":"7001 DV",
    "sg:province":"Gelderland",
    "sg:website":"http://www.action.nl",
    "wof:name":"Action",
    "wof:placetype":"venue"
},
  "geometry": {"coordinates":[6.295527935,51.9669075012],"type":"Point"}
}