{
  "type": "Feature",
  "properties": {
    "iso:country":"NL",
    "sg:address":"Bastiaansstraat 17",
    "sg:city":"Haarlem",
    "sg:orig_category":"Gebouwenafwerking, Renovaties And Reiniging",
    "sg:phone":"+31 23 535 7585",
    "sg:postcode":"2033 RG",
    "sg:province":"Noord-Holland",
    "wof:name":"P.J.Van Olphen",
    "wof:placetype":"venue"
},
  "geometry": {"coordinates":[4.654858,52.373554],"type":"Point"}
}