{
  "type": "Feature",
  "properties": {
    "addr:full":"Boschdk 391 Eindhoven Noord-Brabant 5621 JB",
    "addr:housenumber":"391",
    "addr:postcode":"5621 jb",
    "iso:country":"NL",
    "sg:address":"Boschdk 391",
    "sg:city":"Eindhoven",
    "sg:orig_category":"Verzekeringen - Verzekeringskantoren",
    "sg:phone":"+31 40 290 3435",
    "sg:postcode":"5621 JB",
    "sg:province":"Noord-Brabant",
    "wof:name":"Paul Van 'T Hof Assuranti\u00ebn",
    "wof:placetype":"venue"
},
  "geometry": {"coordinates":[5.461579,51.454483],"type":"Point"}
}