{
  "type": "Feature",
  "properties": {
    "addr:full":"Keppelseweg 51 Doetinchem Gelderland 7001 CE",
    "addr:housenumber":"51",
    "addr:postcode":"7001 ce",
    "addr:street":"Keppelseweg;Gelderland",
    "iso:country":"NL",
    "sg:address":"Keppelseweg 51",
    "sg:city":"Doetinchem",
    "sg:orig_category":"Naai- And Breimachines",
    "sg:phone":"+31 314 326 648",
    "sg:postcode":"7001 CE",
    "sg:province":"Gelderland",
    "wof:name":"Koenders Naaimachines",
    "wof:placetype":"venue"
},
  "geometry": {"coordinates":[6.282004,51.969524],"type":"Point"}
}