{
  "type": "Feature",
  "properties": {
    "addr:full":"Merwedepln 52 Amsterdam Noord-Holland 1078 NG",
    "addr:housenumber":"52",
    "addr:postcode":"1078 ng",
    "addr:street":"Merwedepln",
    "iso:country":"NL",
    "sg:address":"Merwedepln 52",
    "sg:city":"Amsterdam",
    "sg:orig_category":"Advocaten En Advocatenkantoren",
    "sg:phone":"+31 20 671 5679",
    "sg:postcode":"1078 NG",
    "sg:province":"Noord-Holland",
    "wof:name":"Lionarons, Mr T L",
    "wof:placetype":"venue"
},
  "geometry": {"coordinates":[4.900104,52.346016],"type":"Point"}
}