{
  "type": "Feature",
  "properties": {
    "iso:country":"NL",
    "sg:address":"Keup 9",
    "sg:city":"Egchel",
    "sg:orig_category":"Meubelreparatie And -Restauratie",
    "sg:phone":"+31 77 307 2855",
    "sg:postcode":"5987 NB",
    "sg:province":"Limburg",
    "wof:name":"Stoelenmatterij Emhelni",
    "wof:placetype":"venue"
},
  "geometry": {"coordinates":[5.98473,51.307819],"type":"Point"}
}