{
  "type": "Feature",
  "properties": {
    "iso:country":"NL",
    "sg:address":"Industrieweg 34",
    "sg:city":"Assen",
    "sg:classifiers":[
        {
            "category":"Retail",
            "subcategory":"Storage",
            "type":"Services"
        }
    ],
    "sg:phone":"+31 592 346 868",
    "sg:postcode":"9403 AB",
    "sg:province":"Drenthe",
    "sg:tags":[
        "opslag",
        "bewaring"
    ],
    "wof:name":"Prisma Food Retail Bv",
    "wof:placetype":"venue"
},
  "geometry": {"coordinates":[6.5696501732,53.0044937134],"type":"Point"}
}