{
  "type": "Feature",
  "properties": {
    "addr:full":"Twekkeler Es 34 Enschede NL.08 7547 SM",
    "addr:housenumber":"34",
    "addr:postcode":"7547 sm",
    "addr:street":"Twekkeler Es",
    "iso:country":"NL",
    "sg:address":"Twekkeler Es 34",
    "sg:city":"Enschede",
    "sg:orig_category":"Hek- En Rasterwerken",
    "sg:phone":"+31 53 430 3016",
    "sg:postcode":"7547 SM",
    "sg:province":"NL.08",
    "wof:name":"Twentse Hekwerken Onderneming Bv",
    "wof:placetype":"venue"
},
  "geometry": {"coordinates":[6.838921,52.221859],"type":"Point"}
}