{
  "type": "Feature",
  "properties": {
    "iso:country":"NL",
    "sg:address":"Wencopperwg 20",
    "sg:city":"Barneveld",
    "sg:orig_category":"Verhuur",
    "sg:phone":"+31 342 450 468",
    "sg:postcode":"3771 PP",
    "sg:province":"Gelderland",
    "sg:website":"http://www.skippy-rent.nl",
    "wof:name":"Skippy",
    "wof:placetype":"venue"
},
  "geometry": {"coordinates":[5.603393,52.161793],"type":"Point"}
}