{
  "type": "Feature",
  "properties": {
    "iso:country":"NL",
    "sg:address":"Noordkade 23",
    "sg:city":"Drachten",
    "sg:orig_category":"Werving And Selectie Van Tijdelijk Personeel And Uitzendkantoren",
    "sg:phone":"+31 512 522 411",
    "sg:postcode":"9203 CD",
    "sg:province":"Provincie Friesland",
    "wof:name":"Adecco",
    "wof:placetype":"venue"
},
  "geometry": {"coordinates":[6.1015467644,53.1069374084],"type":"Point"}
}