{
  "type": "Feature",
  "properties": {
    "addr:full":"Tweede Haagstr 37 Helmond North Brabant 5707 VJ",
    "addr:housenumber":"37",
    "addr:postcode":"5707 vj",
    "addr:street":"Tweede Haagstr",
    "iso:country":"NL",
    "sg:address":"Tweede Haagstr 37",
    "sg:city":"Helmond",
    "sg:orig_category":"Sportverenigingen En Ontspannings- Verenigingen",
    "sg:phone":"+31 492 529 064",
    "sg:postcode":"5707 VJ",
    "sg:province":"North Brabant",
    "wof:name":"Helmondse Sportvissers, De",
    "wof:placetype":"venue"
},
  "geometry": {"coordinates":[5.644348,51.475525],"type":"Point"}
}