{
  "type": "Feature",
  "properties": {
    "addr:full":"Antwerpsestr 116 Putte Noord-Brabant 4645 BM",
    "addr:housenumber":"116",
    "addr:postcode":"putte;4645 bm",
    "iso:country":"NL",
    "sg:address":"Antwerpsestr 116",
    "sg:city":"Putte",
    "sg:orig_category":"Cafetaria'S",
    "sg:phone":"+31 164 602 509",
    "sg:postcode":"4645 BM",
    "sg:province":"Noord-Brabant",
    "wof:name":"Pauw, De",
    "wof:placetype":"venue"
},
  "geometry": {"coordinates":[4.393114,51.360661],"type":"Point"}
}