{
  "type": "Feature",
  "properties": {
    "addr:full":"Eisenhowerln 150 S Gravenhage Zuid-Holland 2517 KP",
    "addr:housenumber":"150;gravenhage",
    "addr:postcode":"2517 kp",
    "addr:street":"S",
    "iso:country":"NL",
    "sg:address":"Eisenhowerln 150",
    "sg:city":"S Gravenhage",
    "sg:orig_category":"Persbureaus",
    "sg:phone":"+31 70 350 0978",
    "sg:postcode":"2517 KP",
    "sg:province":"Zuid-Holland",
    "wof:name":"Afp",
    "wof:placetype":"venue"
},
  "geometry": {"coordinates":[4.28708,52.08667],"type":"Point"}
}