{
  "type": "Feature",
  "properties": {
    "iso:country":"NL",
    "sg:address":"Strandweg 3",
    "sg:city":"'S Gravenhage",
    "sg:classifiers":[
        {
            "category":"Fast Food",
            "type":"Food & Drink"
        }
    ],
    "sg:phone":"+31 70 354 2506",
    "sg:postcode":"2586 JK",
    "sg:province":"Zuid-Holland",
    "sg:tags":[
        "afhaal",
        "restaurant"
    ],
    "wof:name":"Beach Point",
    "wof:placetype":"venue"
},
  "geometry": {"coordinates":[4.278286,52.112038],"type":"Point"}
}