{
  "type": "Feature",
  "properties": {
    "addr:full":"Schiedamsewg 137 Rotterdam Zuid-Holland 3026 AH",
    "addr:housenumber":"137",
    "addr:postcode":"3026 ah",
    "iso:country":"NL",
    "sg:address":"Schiedamsewg 137",
    "sg:city":"Rotterdam",
    "sg:orig_category":"Behangselpapier En Wandbekleding",
    "sg:phone":"+31 10 476 3077",
    "sg:postcode":"3026 AH",
    "sg:province":"Zuid-Holland",
    "wof:name":"Alper",
    "wof:placetype":"venue"
},
  "geometry": {"coordinates":[4.441995,51.910877],"type":"Point"}
}