{
  "type": "Feature",
  "properties": {
    "addr:full":"Schroeder Van De Kolkln 16 Den Dolder Utrecht 3734 VG",
    "addr:housenumber":"16",
    "addr:postcode":"3734 vg",
    "addr:street":"Schroeder Van",
    "iso:country":"NL",
    "sg:address":"Schroeder Van De Kolkln 16",
    "sg:city":"Den Dolder",
    "sg:orig_category":"Artiestenbureaus",
    "sg:phone":"+31 30 225 1644",
    "sg:postcode":"3734 VG",
    "sg:province":"Utrecht",
    "wof:name":"Ton Braams",
    "wof:placetype":"venue"
},
  "geometry": {"coordinates":[5.232721,52.140751],"type":"Point"}
}