{
  "type": "Feature",
  "properties": {
    "addr:full":"Dennenwg 8 Terschelling West Provincie Friesland 8881 CJ",
    "addr:housenumber":"8",
    "addr:postcode":"8881 cj",
    "addr:street":"Dennenwg;Friesland",
    "iso:country":"NL",
    "sg:address":"Dennenwg 8",
    "sg:city":"Terschelling West",
    "sg:orig_category":"Kappers",
    "sg:phone":"+31 562 442 976",
    "sg:postcode":"8881 CJ",
    "sg:province":"Provincie Friesland",
    "wof:name":"Zwol, Y Van",
    "wof:placetype":"venue"
},
  "geometry": {"coordinates":[5.212758,53.36422],"type":"Point"}
}