{
  "type": "Feature",
  "properties": {
    "addr:full":"Venusstr 34 Hardinxveld Giessendam Zuid-Holland 3371 TR",
    "addr:housenumber":"34",
    "addr:postcode":"giessendam;3371 tr",
    "addr:street":"Venusstr",
    "iso:country":"NL",
    "sg:address":"Venusstr 34",
    "sg:city":"Hardinxveld Giessendam",
    "sg:orig_category":"Autorijscholen",
    "sg:phone":"+31 184 613 023",
    "sg:postcode":"3371 TR",
    "sg:province":"Zuid-Holland",
    "wof:name":"Muilwijk, W",
    "wof:placetype":"venue"
},
  "geometry": {"coordinates":[4.821333,51.822491],"type":"Point"}
}