{
  "type": "Feature",
  "properties": {
    "addr:full":"Middenwaard 51 Heerhugowaard Noord-Holland 1703 SC",
    "addr:housenumber":"51",
    "addr:postcode":"1703 sc",
    "addr:street":"Middenwaard",
    "iso:country":"NL",
    "sg:address":"Middenwaard 51",
    "sg:city":"Heerhugowaard",
    "sg:orig_category":"Apothekers",
    "sg:phone":"+31 72 574 1198",
    "sg:postcode":"1703 SC",
    "sg:province":"Noord-Holland",
    "wof:name":"Apotheek Van Zanten",
    "wof:placetype":"venue"
},
  "geometry": {"coordinates":[4.829586,52.662792],"type":"Point"}
}