{
  "type": "Feature",
  "properties": {
    "addr:full":"P De Hoochwg 125D Rotterdam Zuid-Holland 3024 BG",
    "addr:housenumber":"125d",
    "addr:postcode":"3024",
    "addr:street":"P",
    "iso:country":"NL",
    "sg:address":"P De Hoochwg 125D",
    "sg:city":"Rotterdam",
    "sg:orig_category":"Adviesbureaus Financieel",
    "sg:phone":"+31 10 436 0191",
    "sg:postcode":"3024 BG",
    "sg:province":"Zuid-Holland",
    "wof:name":"Fit",
    "wof:placetype":"venue"
},
  "geometry": {"coordinates":[4.459389,51.906673],"type":"Point"}
}