{
  "type": "Feature",
  "properties": {
    "iso:country":"NL",
    "sg:address":"Stephensonstr 33",
    "sg:city":"S Gravenhage",
    "sg:orig_category":"Adviesbureaus Bedrijfsorganisatie",
    "sg:phone":"+31 70 363 8835",
    "sg:postcode":"2561 XR",
    "sg:province":"Zuid-Holland",
    "wof:name":"Rutjens, J",
    "wof:placetype":"venue"
},
  "geometry": {"coordinates":[4.27581,52.074532],"type":"Point"}
}