{
  "type": "Feature",
  "properties": {
    "addr:full":"Apeldoornseln 228 S Gravenhage Zuid-Holland 2573 LV",
    "addr:housenumber":"228;gravenhage",
    "addr:postcode":"2573",
    "addr:street":"S",
    "iso:country":"NL",
    "sg:address":"Apeldoornseln 228",
    "sg:city":"S Gravenhage",
    "sg:orig_category":"Opticiens",
    "sg:phone":"+31 70 345 4848",
    "sg:postcode":"2573 LV",
    "sg:province":"Zuid-Holland",
    "wof:name":"Asperen Speciaal Optiek, V",
    "wof:placetype":"venue"
},
  "geometry": {"coordinates":[4.2843999863,52.0649108887],"type":"Point"}
}