{
  "type": "Feature",
  "properties": {
    "iso:country":"NL",
    "sg:address":"Nijverheidsweg 26",
    "sg:city":"Stolwijk",
    "sg:orig_category":"Binnenhuisarchitecten",
    "sg:phone":"+31 182 341 694",
    "sg:postcode":"2821 AW",
    "sg:province":"South Holland",
    "wof:name":"Magna Vloerenbedrijf Bv",
    "wof:placetype":"venue"
},
  "geometry": {"coordinates":[4.775245,51.964745],"type":"Point"}
}