{
  "type": "Feature",
  "properties": {
    "addr:full":"Burgemeester Eekhoutstr 32 Oldenzaal Overijssel 7574 ZB",
    "addr:housenumber":"32",
    "addr:postcode":"7574 zb",
    "addr:street":"Burgemeester Eekhoutstr",
    "iso:country":"NL",
    "sg:address":"Burgemeester Eekhoutstr 32",
    "sg:city":"Oldenzaal",
    "sg:orig_category":"Loodgieterswerk, Verwarming And Sanitaire Installaties",
    "sg:phone":"+31 541 512 933",
    "sg:postcode":"7574 ZB",
    "sg:province":"Overijssel",
    "wof:name":"A. Eveleens Bv",
    "wof:placetype":"venue"
},
  "geometry": {"coordinates":[6.934222,52.299412],"type":"Point"}
}