{
  "type": "Feature",
  "properties": {
    "addr:full":"J Muyskenwg 32A Amsterdam Noord-Holland 1099 CK",
    "addr:housenumber":"32a",
    "addr:postcode":"1099 ck",
    "iso:country":"NL",
    "sg:address":"J Muyskenwg 32A",
    "sg:city":"Amsterdam",
    "sg:orig_category":"Parkeersystemen",
    "sg:phone":"+31 20 568 9689",
    "sg:postcode":"1099 CK",
    "sg:province":"Noord-Holland",
    "sg:website":"http://www.eww.nl",
    "wof:name":"Eww Technische Bedrijven Bv",
    "wof:placetype":"venue"
},
  "geometry": {"coordinates":[4.92788,52.320251],"type":"Point"}
}