{
  "type": "Feature",
  "properties": {
    "addr:full":"Het Rondeel 12 Maastricht Limburg 6219 PG",
    "addr:housenumber":"12",
    "addr:postcode":"6219 pg",
    "addr:street":"Het Rondeel",
    "iso:country":"NL",
    "sg:address":"Het Rondeel 12",
    "sg:city":"Maastricht",
    "sg:classifiers":[
        {
            "category":"Bakery",
            "type":"Food & Drink"
        }
    ],
    "sg:phone":"+31 43 325 9444",
    "sg:postcode":"6219 PG",
    "sg:province":"Limburg",
    "sg:tags":[
        "brood",
        "banket"
    ],
    "wof:name":"Jolivier Chocolaterie Bv",
    "wof:placetype":"venue"
},
  "geometry": {"coordinates":[5.6789,50.860664],"type":"Point"}
}