{
  "type": "Feature",
  "properties": {
    "addr:full":"Morsebelln 26 Oegstgeest South Holland 2343 BM",
    "addr:housenumber":"26",
    "addr:postcode":"2343 bm",
    "addr:street":"Morsebelln",
    "iso:country":"NL",
    "sg:address":"Morsebelln 26",
    "sg:city":"Oegstgeest",
    "sg:orig_category":"Onderhoudswerken",
    "sg:phone":"+31 71 531 5970",
    "sg:postcode":"2343 BM",
    "sg:province":"South Holland",
    "wof:name":"Hartman, J",
    "wof:placetype":"venue"
},
  "geometry": {"coordinates":[4.468242,52.176617],"type":"Point"}
}