{
  "type": "Feature",
  "properties": {
    "addr:full":"J De Meesterstr 10 Zeist Utrecht 3702 BX",
    "addr:housenumber":"10",
    "addr:postcode":"3702 bx",
    "addr:street":"J De Meesterstr",
    "iso:country":"NL",
    "sg:address":"J De Meesterstr 10",
    "sg:city":"Zeist",
    "sg:orig_category":"Voegwerken",
    "sg:phone":"+31 30 692 3516",
    "sg:postcode":"3702 BX",
    "sg:province":"Utrecht",
    "wof:name":"Kastrati",
    "wof:placetype":"venue"
},
  "geometry": {"coordinates":[5.234631,52.089485],"type":"Point"}
}