{
  "type": "Feature",
  "properties": {
    "addr:full":"Willem De Zwijgerstraat 23 Rotterdam Zuid-Holland 3043 VB",
    "addr:housenumber":"23",
    "addr:postcode":"3043 vb",
    "addr:street":"Willem De Zwijgerstraat",
    "iso:country":"NL",
    "sg:address":"Willem De Zwijgerstraat 23",
    "sg:city":"Rotterdam",
    "sg:classifiers":[
        {
            "category":"Retail",
            "subcategory":"Photofinishing",
            "type":"Services"
        }
    ],
    "sg:phone":"+31 10 415 9136",
    "sg:postcode":"3043 VB",
    "sg:province":"Zuid-Holland",
    "sg:tags":[
        "foto",
        "film"
    ],
    "wof:name":"The Quality Camerashop",
    "wof:placetype":"venue"
},
  "geometry": {"coordinates":[4.423783,51.941811],"type":"Point"}
}