{
  "type": "Feature",
  "properties": {
    "iso:country":"NL",
    "sg:address":"Dotterbloem 4",
    "sg:city":"Wilnis",
    "sg:orig_category":"Kousen En Sokken",
    "sg:phone":"+31 297 273 363",
    "sg:postcode":"3648 NS",
    "sg:province":"Utrecht",
    "wof:name":"Amerongen & Kostman Vof, Van",
    "wof:placetype":"venue"
},
  "geometry": {"coordinates":[4.892973,52.176678],"type":"Point"}
}