{
  "type": "Feature",
  "properties": {
    "iso:country":"NL",
    "sg:address":"Carel Fabritiuslaan 35",
    "sg:city":"Voorschoten",
    "sg:orig_category":"Adviesbureaus Bedrijfsorganisatie",
    "sg:phone":"+31 71 561 9204",
    "sg:postcode":"2251 XB",
    "sg:province":"Zuid-Holland",
    "wof:name":"Parker@Work",
    "wof:placetype":"venue"
},
  "geometry": {"coordinates":[4.454848,52.121883],"type":"Point"}
}