{
  "type": "Feature",
  "properties": {
    "iso:country":"NL",
    "sg:address":"Stobbenven 29",
    "sg:city":"Roden",
    "sg:orig_category":"Timmerwerk Van Hout And Kunststof",
    "sg:phone":"+31 50 501 0382",
    "sg:postcode":"9302 EN",
    "sg:province":"Drenthe",
    "wof:name":"Bosma Montage",
    "wof:placetype":"venue"
},
  "geometry": {"coordinates":[6.403147,53.13961],"type":"Point"}
}