{
  "type": "Feature",
  "properties": {
    "addr:full":"Meibergdreef 9 Amsterdam Zuidoost Noord-Holland 1105 AZ",
    "addr:housenumber":"9",
    "addr:postcode":"zuidoost;1105 az",
    "addr:street":"Meibergdreef",
    "iso:country":"NL",
    "sg:address":"Meibergdreef 9",
    "sg:city":"Amsterdam Zuidoost",
    "sg:orig_category":"Bloemen En Planten",
    "sg:phone":"+31 20 696 9622",
    "sg:postcode":"1105 AZ",
    "sg:province":"Noord-Holland",
    "wof:name":"Amc Bloemenstal",
    "wof:placetype":"venue"
},
  "geometry": {"coordinates":[4.957035,52.295952],"type":"Point"}
}