{
  "type": "Feature",
  "properties": {
    "iso:country":"NL",
    "sg:address":"Wilgenlaan 11",
    "sg:city":"Nijkerk Gld",
    "sg:orig_category":"Kappers",
    "sg:phone":"+31 33 245 3136",
    "sg:postcode":"3862 VD",
    "sg:province":"Gelderland",
    "wof:name":"H J Mulder",
    "wof:placetype":"venue"
},
  "geometry": {"coordinates":[5.4939007759,52.2163734436],"type":"Point"}
}