{
  "type": "Feature",
  "properties": {
    "addr:full":"Koningswg 23 Harlingen Friesland 8861 KN",
    "addr:housenumber":"23",
    "addr:postcode":"8861 kn",
    "addr:street":"Koningswg",
    "iso:country":"NL",
    "sg:address":"Koningswg 23",
    "sg:city":"Harlingen",
    "sg:orig_category":"Autosloperijen En Autodemontagebedrijven",
    "sg:phone":"+31 517 414 929",
    "sg:postcode":"8861 KN",
    "sg:province":"Friesland",
    "wof:name":"Poelstra",
    "wof:placetype":"venue"
},
  "geometry": {"coordinates":[5.446453,53.175163],"type":"Point"}
}