{
  "type": "Feature",
  "properties": {
    "iso:country":"NL",
    "sg:address":"Dorpsstraat 44",
    "sg:city":"Renswoude",
    "sg:orig_category":"Autokeuringen",
    "sg:phone":"+31 318 571 233",
    "sg:postcode":"3927 BD",
    "sg:province":"Utrecht",
    "wof:name":"Garage Vlastuin",
    "wof:placetype":"venue"
},
  "geometry": {"coordinates":[5.543492,52.072731],"type":"Point"}
}