{
  "type": "Feature",
  "properties": {
    "addr:full":"Charlie Parkerstraat 68 Almere Flevoland 1311 PJ",
    "addr:housenumber":"68",
    "addr:postcode":"1311 pj",
    "addr:street":"Charlie Parkerstraat;Flevoland",
    "iso:country":"NL",
    "sg:address":"Charlie Parkerstraat 68",
    "sg:city":"Almere",
    "sg:orig_category":"Artsen And Specialisten",
    "sg:phone":"+31 36 536 3452",
    "sg:postcode":"1311 PJ",
    "sg:province":"Flevoland",
    "wof:name":"E. Del Prado",
    "wof:placetype":"venue"
},
  "geometry": {"coordinates":[5.181656,52.36692],"type":"Point"}
}