{
  "type": "Feature",
  "properties": {
    "addr:full":"Bachrode 50 Zoetermeer Zuid-Holland 2717 AN",
    "addr:housenumber":"50",
    "addr:postcode":"2717 an",
    "addr:street":"Bachrode",
    "iso:country":"NL",
    "sg:address":"Bachrode 50",
    "sg:city":"Zoetermeer",
    "sg:orig_category":"Artsen - Huisartsen",
    "sg:phone":"+31 79 321 3362",
    "sg:postcode":"2717 AN",
    "sg:province":"Zuid-Holland",
    "wof:name":"Eenink, W J",
    "wof:placetype":"venue"
},
  "geometry": {"coordinates":[4.469029,52.066025],"type":"Point"}
}