{
  "type": "Feature",
  "properties": {
    "addr:full":"Gluckstr 38 Tilburg Noord-Brabant 5011 VG",
    "addr:housenumber":"38",
    "addr:postcode":"5011 vg",
    "addr:street":"Gluckstr",
    "iso:country":"NL",
    "sg:address":"Gluckstr 38",
    "sg:city":"Tilburg",
    "sg:orig_category":"Vertaalbureaus",
    "sg:phone":"+31 6 24507840",
    "sg:postcode":"5011 VG",
    "sg:province":"Noord-Brabant",
    "wof:name":"Konovalova-Volovitch, Drs E",
    "wof:placetype":"venue"
},
  "geometry": {"coordinates":[5.078971,51.579472],"type":"Point"}
}