{
  "type": "Feature",
  "properties": {
    "addr:full":"Heliotroopdijk 39 Roosendaal North Brabant 4706 JN",
    "addr:housenumber":"39",
    "addr:postcode":"4706 jn",
    "addr:street":"Heliotroopdijk",
    "iso:country":"NL",
    "sg:address":"Heliotroopdijk 39",
    "sg:city":"Roosendaal",
    "sg:orig_category":"Public Relationbureaus",
    "sg:phone":"+31 165 562 460",
    "sg:postcode":"4706 JN",
    "sg:province":"North Brabant",
    "wof:name":"Parmi P.R.",
    "wof:placetype":"venue"
},
  "geometry": {"coordinates":[4.494583,51.529713],"type":"Point"}
}