{
  "type": "Feature",
  "properties": {
    "addr:full":"Grotestraat 61 Almelo Overijssel 7607 CD",
    "addr:housenumber":"61",
    "addr:postcode":"7607 cd",
    "addr:street":"Grotestraat",
    "iso:country":"NL",
    "sg:address":"Grotestraat 61",
    "sg:city":"Almelo",
    "sg:orig_category":"Verlichting And Huishoudartikelen",
    "sg:phone":"+31 546 456 232",
    "sg:postcode":"7607 CD",
    "sg:province":"Overijssel",
    "wof:name":"Xenos Bv",
    "wof:placetype":"venue"
},
  "geometry": {"coordinates":[6.66457,52.357101],"type":"Point"}
}