{
  "type": "Feature",
  "properties": {
    "addr:full":"Lammerenhof 38 Zevenaar Gelderland 6902 BA",
    "addr:housenumber":"38",
    "addr:postcode":"6902 ba",
    "addr:street":"Lammerenhof",
    "iso:country":"NL",
    "sg:address":"Lammerenhof 38",
    "sg:city":"Zevenaar",
    "sg:orig_category":"Huishoudapparatuur, Televisies And Radio'S",
    "sg:phone":"+31 316 524 034",
    "sg:postcode":"6902 BA",
    "sg:province":"Gelderland",
    "wof:name":"Antenne-Installatiebedrijf H Peterse",
    "wof:placetype":"venue"
},
  "geometry": {"coordinates":[6.088346,51.931274],"type":"Point"}
}