{
  "type": "Feature",
  "properties": {
    "addr:full":"Kennedyln 31 Beek Lb Missouri 6191 XA",
    "addr:housenumber":"31",
    "addr:postcode":"6191 xa",
    "addr:street":"Kennedyln",
    "iso:country":"NL",
    "sg:address":"Kennedyln 31",
    "sg:city":"Beek Lb",
    "sg:orig_category":"Verenigingen En Stichtingen",
    "sg:phone":"+31 46 428 0150",
    "sg:postcode":"6191 XA",
    "sg:province":"Missouri",
    "wof:name":"Carmel, De",
    "wof:placetype":"venue"
},
  "geometry": {"coordinates":[-93.129936,36.705662],"type":"Point"}
}