{
  "type": "Feature",
  "properties": {
    "addr:full":"V L V Sandenb Ln 43 Utrecht Utrecht 3571 BB",
    "addr:housenumber":"43",
    "addr:postcode":"3571 bb",
    "addr:street":"V L V Sandenb Ln",
    "iso:country":"NL",
    "sg:address":"V L V Sandenb Ln 43",
    "sg:city":"Utrecht",
    "sg:orig_category":"Adviesbureaus Bedrijfsorganisatie",
    "sg:phone":"+31 30 273 0940",
    "sg:postcode":"3571 BB",
    "sg:province":"Utrecht",
    "wof:name":"Maria Camarasa",
    "wof:placetype":"venue"
},
  "geometry": {"coordinates":[5.12917,52.108181],"type":"Point"}
}