{
  "type": "Feature",
  "properties": {
    "addr:full":"Chromiumwg 29 Amersfoort Utrecht 3812 NL",
    "addr:housenumber":"29",
    "addr:postcode":"3812 nl",
    "addr:street":"Chromiumwg",
    "iso:country":"NL",
    "sg:address":"Chromiumwg 29",
    "sg:city":"Amersfoort",
    "sg:orig_category":"Loodgieters",
    "sg:phone":"+31 33 461 3173",
    "sg:postcode":"3812 NL",
    "sg:province":"Utrecht",
    "wof:name":"Dijen En Zn, W B Van",
    "wof:placetype":"venue"
},
  "geometry": {"coordinates":[5.360512,52.166149],"type":"Point"}
}