{
  "type": "Feature",
  "properties": {
    "addr:full":"Dr Stamstr 44 Enschede NL.08 7534 CM",
    "addr:housenumber":"44",
    "addr:postcode":"7534 cm",
    "iso:country":"NL",
    "sg:address":"Dr Stamstr 44",
    "sg:city":"Enschede",
    "sg:classifiers":[
        {
            "category":"Retail",
            "subcategory":"Auto Repair",
            "type":"Services"
        }
    ],
    "sg:phone":"+31 53 461 1616",
    "sg:postcode":"7534 CM",
    "sg:province":"NL.08",
    "sg:tags":[
        "garage"
    ],
    "wof:name":"B\u00f7Sing Autobedrijf",
    "wof:placetype":"venue"
},
  "geometry": {"coordinates":[6.975298,52.2136],"type":"Point"}
}