{
  "type": "Feature",
  "properties": {
    "addr:full":"Kromwykerkd 55 Woerden Utrecht 3442 EJ",
    "addr:housenumber":"55",
    "addr:postcode":"3442 ej",
    "addr:street":"Kromwykerkd",
    "iso:country":"NL",
    "sg:address":"Kromwykerkd 55",
    "sg:city":"Woerden",
    "sg:orig_category":"Verenigingen En Stichtingen",
    "sg:phone":"+31 348 418 772",
    "sg:postcode":"3442 EJ",
    "sg:province":"Utrecht",
    "wof:name":"Federatie Christelijke Jongere",
    "wof:placetype":"venue"
},
  "geometry": {"coordinates":[4.877475,52.082031],"type":"Point"}
}