{
  "type": "Feature",
  "properties": {
    "addr:full":"Lindeln 2 Renesse Zeeland 4325 EE",
    "addr:housenumber":"2",
    "addr:postcode":"4325 ee",
    "addr:street":"Lindeln",
    "iso:country":"NL",
    "sg:address":"Lindeln 2",
    "sg:city":"Renesse",
    "sg:orig_category":"Onderhoudswerken",
    "sg:phone":"+31 111 461 465",
    "sg:postcode":"4325 EE",
    "sg:province":"Zeeland",
    "wof:name":"Put, Gebr",
    "wof:placetype":"venue"
},
  "geometry": {"coordinates":[3.773377,51.732834],"type":"Point"}
}