{
  "type": "Feature",
  "properties": {
    "addr:full":"Postbus 74721 Amsterdam Noord-Brabant 1070 BS",
    "addr:postcode":"74721;1070 bs",
    "addr:street":"Postbus",
    "iso:country":"NL",
    "sg:address":"Postbus 74721",
    "sg:city":"Amsterdam",
    "sg:orig_category":"Vertaalbureaus",
    "sg:phone":"+31 299 471 095",
    "sg:postcode":"1070 BS",
    "sg:province":"Noord-Brabant",
    "wof:name":"Accuwrite",
    "wof:placetype":"venue"
},
  "geometry": {"coordinates":[4.89205,52.37355],"type":"Point"}
}