{
  "type": "Feature",
  "properties": {
    "iso:country":"NL",
    "sg:address":"Grotestraat 39",
    "sg:city":"Deest",
    "sg:orig_category":"Verzekeringen",
    "sg:phone":"+31 487 514 723",
    "sg:postcode":"6653 BJ",
    "sg:province":"Gelderland",
    "wof:name":"Assurantie Adviesbedrijf Peperkamp",
    "wof:placetype":"venue"
},
  "geometry": {"coordinates":[5.666188,51.886295],"type":"Point"}
}