{
  "type": "Feature",
  "properties": {
    "iso:country":"NL",
    "sg:address":"Modemweg 26",
    "sg:city":"Amersfoort",
    "sg:orig_category":"Chemische Producten Gh",
    "sg:phone":"+31 33 454 3100",
    "sg:postcode":"3821 BS",
    "sg:province":"Utrecht",
    "wof:name":"Grada Bv",
    "wof:placetype":"venue"
},
  "geometry": {"coordinates":[5.418817,52.171837],"type":"Point"}
}