{
  "type": "Feature",
  "properties": {
    "addr:full":"Zeelt 7 Tiel Gelderland 4007 NV",
    "addr:housenumber":"7",
    "addr:postcode":"4007 nv",
    "addr:street":"Zeelt;Gelderland",
    "iso:country":"NL",
    "sg:address":"Zeelt 7",
    "sg:city":"Tiel",
    "sg:orig_category":"Goederenvervoer Over De Weg",
    "sg:phone":"+31 344 630 265",
    "sg:postcode":"4007 NV",
    "sg:province":"Gelderland",
    "wof:name":"Veenstra Transport",
    "wof:placetype":"venue"
},
  "geometry": {"coordinates":[5.394741,51.867947],"type":"Point"}
}