{
  "type": "Feature",
  "properties": {
    "addr:full":"Botenmakersstr 50 Zaandam Noord-Holland 1506 TE",
    "addr:housenumber":"50;1506",
    "addr:postcode":"te",
    "addr:street":"Botenmakersstr",
    "iso:country":"NL",
    "sg:address":"Botenmakersstr 50",
    "sg:city":"Zaandam",
    "sg:orig_category":"Architecten En Architectenbureaus",
    "sg:phone":"+31 75 670 8218",
    "sg:postcode":"1506 TE",
    "sg:province":"Noord-Holland",
    "sg:website":"http://www.architectuurstudiokramer.nl",
    "wof:name":"Kramer",
    "wof:placetype":"venue"
},
  "geometry": {"coordinates":[4.819055,52.442097],"type":"Point"}
}