{
  "type": "Feature",
  "properties": {
    "addr:full":"Horicherhofstr 18 Heerlen Limburg 6418 AZ",
    "addr:housenumber":"18",
    "addr:postcode":"6418 az",
    "addr:street":"Horicherhofstr",
    "iso:country":"NL",
    "sg:address":"Horicherhofstr 18",
    "sg:city":"Heerlen",
    "sg:orig_category":"Schilders",
    "sg:phone":"+31 45 541 2073",
    "sg:postcode":"6418 AZ",
    "sg:province":"Limburg",
    "wof:name":"Derks",
    "wof:placetype":"venue"
},
  "geometry": {"coordinates":[6.000201,50.869923],"type":"Point"}
}