{
  "type": "Feature",
  "properties": {
    "addr:full":"Hoofdstraat 45 Gorssel Gelderland 7213 CR",
    "addr:housenumber":"45;7213",
    "addr:postcode":"cr",
    "addr:street":"Hoofdstraat;Gelderland",
    "iso:country":"NL",
    "sg:address":"Hoofdstraat 45",
    "sg:city":"Gorssel",
    "sg:orig_category":"Artsen And Specialisten",
    "sg:phone":"+31 575 491 570",
    "sg:postcode":"7213 CR",
    "sg:province":"Gelderland",
    "wof:name":"Huisartsenpraktijk Van Gelderen",
    "wof:placetype":"venue"
},
  "geometry": {"coordinates":[6.199318,52.199726],"type":"Point"}
}