{
  "type": "Feature",
  "properties": {
    "iso:country":"NL",
    "sg:address":"Industriestr 8",
    "sg:city":"Wamel",
    "sg:classifiers":[
        {
            "category":"Home & Garden",
            "subcategory":"Building Materials",
            "type":"Retail Goods"
        }
    ],
    "sg:phone":"+31 487 501 017",
    "sg:postcode":"6659 AL",
    "sg:province":"Gelderland",
    "sg:tags":[
        "hout",
        "en",
        "board",
        "triplex"
    ],
    "wof:name":"Wh",
    "wof:placetype":"venue"
},
  "geometry": {"coordinates":[5.479761,51.878757],"type":"Point"}
}