{
  "type": "Feature",
  "properties": {
    "addr:full":"De Eiken 5 Delden Overijssel 7491 HP",
    "addr:housenumber":"5",
    "addr:postcode":"7491 hp",
    "addr:street":"De Eiken",
    "iso:country":"NL",
    "sg:address":"De Eiken 5",
    "sg:city":"Delden",
    "sg:orig_category":"Loodgieters- And Verwarmingsmateriaal Gh",
    "sg:phone":"+31 74 376 2733",
    "sg:postcode":"7491 HP",
    "sg:province":"Overijssel",
    "wof:name":"Jowitherm Nederland Bv",
    "wof:placetype":"venue"
},
  "geometry": {"coordinates":[6.700865,52.255844],"type":"Point"}
}