{
  "type": "Feature",
  "properties": {
    "addr:full":"Oosterstr 90 Vlaardingen South Holland 3134 NT",
    "addr:housenumber":"90",
    "addr:postcode":"3134 nt",
    "addr:street":"Oosterstr",
    "iso:country":"NL",
    "sg:address":"Oosterstr 90",
    "sg:city":"Vlaardingen",
    "sg:classifiers":[
        {
            "category":"Utilities",
            "subcategory":"Cable",
            "type":"Services"
        }
    ],
    "sg:phone":"+31 10 234 1367",
    "sg:postcode":"3134 NT",
    "sg:province":"South Holland",
    "sg:tags":[
        "masseur",
        "en",
        "heilgymnasten"
    ],
    "wof:name":"Stout, Jeannette",
    "wof:placetype":"venue"
},
  "geometry": {"coordinates":[4.351372,51.907082],"type":"Point"}
}