{
  "type": "Feature",
  "properties": {
    "addr:full":"Hogeweyselaan 25 Weesp North Holland 1382 JK",
    "addr:housenumber":"25",
    "addr:postcode":"1382 jk",
    "addr:street":"Hogeweyselaan",
    "iso:country":"NL",
    "sg:address":"Hogeweyselaan 25",
    "sg:city":"Weesp",
    "sg:orig_category":"Diverse Consumentenartikelen Gh",
    "sg:phone":"+31 20 314 0700",
    "sg:postcode":"1382 JK",
    "sg:province":"North Holland",
    "wof:name":"Curacaosche Handelmij Bv",
    "wof:placetype":"venue"
},
  "geometry": {"coordinates":[5.027062,52.310966],"type":"Point"}
}