{
  "type": "Feature",
  "properties": {
    "addr:full":"Jacques Oppenheimstraat 19 Tilburg North Brabant 5042 NM",
    "addr:housenumber":"19",
    "addr:postcode":"5042",
    "addr:street":"Jacques Oppenheimstraat",
    "iso:country":"NL",
    "sg:address":"Jacques Oppenheimstraat 19",
    "sg:city":"Tilburg",
    "sg:orig_category":"Fietshandelaren",
    "sg:phone":"+31 13 468 5926",
    "sg:postcode":"5042 NM",
    "sg:province":"North Brabant",
    "wof:name":"Noud Van Loon Bv",
    "wof:placetype":"venue"
},
  "geometry": {"coordinates":[5.05446,51.568352],"type":"Point"}
}