{
  "type": "Feature",
  "properties": {
    "addr:full":"Weissenbruchlaan 156 Rotterdam South Holland 3054 LS",
    "addr:housenumber":"156",
    "addr:postcode":"3054 ls",
    "addr:street":"Weissenbruchlaan",
    "iso:country":"NL",
    "sg:address":"Weissenbruchlaan 156",
    "sg:city":"Rotterdam",
    "sg:orig_category":"Damesmodezaken",
    "sg:phone":"+31 10 418 4622",
    "sg:postcode":"3054 LS",
    "sg:province":"South Holland",
    "wof:name":"Novita Fashion Bv",
    "wof:placetype":"venue"
},
  "geometry": {"coordinates":[4.496281,51.957066],"type":"Point"}
}