{
  "type": "Feature",
  "properties": {
    "addr:full":"Schouw 50 Schipluiden South Holland 2636 DJ",
    "addr:housenumber":"50",
    "addr:postcode":"2636 dj",
    "addr:street":"Schouw",
    "iso:country":"NL",
    "sg:address":"Schouw 50",
    "sg:city":"Schipluiden",
    "sg:orig_category":"Verenigingen En Stichtingen",
    "sg:phone":"+31 15 380 9672",
    "sg:postcode":"2636 DJ",
    "sg:province":"South Holland",
    "wof:name":"Ehbo Den Hoorn",
    "wof:placetype":"venue"
},
  "geometry": {"coordinates":[4.317048,51.979282],"type":"Point"}
}