{
  "type": "Feature",
  "properties": {
    "addr:full":"Schaesbergerstraat 27 Kerkrade Limburg 6467 EA",
    "addr:housenumber":"27",
    "addr:postcode":"6467 ea",
    "addr:street":"Schaesbergerstraat",
    "iso:country":"NL",
    "sg:address":"Schaesbergerstraat 27",
    "sg:city":"Kerkrade",
    "sg:orig_category":"Overheidsdiensten",
    "sg:phone":"+31 45 541 5010",
    "sg:postcode":"6467 EA",
    "sg:province":"Limburg",
    "wof:name":"Terwinselen",
    "wof:placetype":"venue"
},
  "geometry": {"coordinates":[6.0238208771,50.8646202087],"type":"Point"}
}