{
  "type": "Feature",
  "properties": {
    "addr:full":"Slenerwg 118 Schoonoord Drenthe 7848 AK",
    "addr:housenumber":"118",
    "addr:postcode":"7848 ak",
    "addr:street":"Schoonoord",
    "iso:country":"NL",
    "sg:address":"Slenerwg 118",
    "sg:city":"Schoonoord",
    "sg:orig_category":"Huifkarren - Verhuur En Verkoop",
    "sg:phone":"+31 591 381 679",
    "sg:postcode":"7848 AK",
    "sg:province":"Drenthe",
    "wof:name":"Rij Maar An",
    "wof:placetype":"venue"
},
  "geometry": {"coordinates":[6.777153,52.822861],"type":"Point"}
}