{
  "type": "Feature",
  "properties": {
    "addr:full":"Rodewg 20 Assen Drenthe 9404 RN",
    "addr:housenumber":"20",
    "addr:postcode":"9404 rn",
    "addr:street":"Rodewg",
    "iso:country":"NL",
    "sg:address":"Rodewg 20",
    "sg:city":"Assen",
    "sg:orig_category":"Kappers",
    "sg:phone":"+31 592 311 296",
    "sg:postcode":"9404 RN",
    "sg:province":"Drenthe",
    "wof:name":"Coral",
    "wof:placetype":"venue"
},
  "geometry": {"coordinates":[6.5729632378,52.9874534607],"type":"Point"}
}