{
  "type": "Feature",
  "properties": {
    "addr:full":"Mt Ondinawg 15 Amsterdam Noord-Holland 1033 RE",
    "addr:housenumber":"15",
    "addr:postcode":"1033 re",
    "addr:street":"Mt Ondinawg",
    "iso:country":"NL",
    "sg:address":"Mt Ondinawg 15",
    "sg:city":"Amsterdam",
    "sg:orig_category":"Verenigingen En Stichtingen",
    "sg:phone":"+31 20 633 4859",
    "sg:postcode":"1033 RE",
    "sg:province":"Noord-Holland",
    "wof:name":"Gallant, De",
    "wof:placetype":"venue"
},
  "geometry": {"coordinates":[4.892441,52.401501],"type":"Point"}
}