{
  "type": "Feature",
  "properties": {
    "addr:full":"Rijnhaven 11 Wageningen Gelderland 6702 DT",
    "addr:housenumber":"11",
    "addr:postcode":"6702 dt",
    "addr:street":"Rijnhaven;Gelderland",
    "iso:country":"NL",
    "sg:address":"Rijnhaven 11",
    "sg:city":"Wageningen",
    "sg:orig_category":"Goederenvervoer Over De Weg",
    "sg:phone":"+31 317 412 491",
    "sg:postcode":"6702 DT",
    "sg:province":"Gelderland",
    "wof:name":"Bouw Overslag- En Transportbedrijf Bv",
    "wof:placetype":"venue"
},
  "geometry": {"coordinates":[5.656356,51.961178],"type":"Point"}
}