{
  "type": "Feature",
  "properties": {
    "addr:full":"Hoofdstr 230 Velp Gld Gelderland 6881 TR",
    "addr:housenumber":"230",
    "addr:postcode":"6881 tr",
    "addr:street":"Gld Gelderland",
    "iso:country":"NL",
    "sg:address":"Hoofdstr 230",
    "sg:city":"Velp Gld",
    "sg:classifiers":[
        {
            "category":"Food & Beverages",
            "subcategory":"Bakery",
            "type":"Retail Goods"
        }
    ],
    "sg:phone":"+31 26 364 4008",
    "sg:postcode":"6881 TR",
    "sg:province":"Gelderland",
    "sg:tags":[
        "brood",
        "en",
        "banket"
    ],
    "wof:name":"Bart",
    "wof:placetype":"venue"
},
  "geometry": {"coordinates":[5.968904,51.995907],"type":"Point"}
}