{
  "type": "Feature",
  "properties": {
    "addr:full":"Noordeindsewg 286A Berkel En Rodenrys Zuid-Holland 2651 LL",
    "addr:housenumber":"286a",
    "addr:postcode":"2651 ll",
    "addr:street":"Berkel",
    "iso:country":"NL",
    "sg:address":"Noordeindsewg 286A",
    "sg:city":"Berkel En Rodenrys",
    "sg:orig_category":"Lichtreclame",
    "sg:phone":"+31 10 512 0775",
    "sg:postcode":"2651 LL",
    "sg:province":"Zuid-Holland",
    "sg:website":"http://www.beslite.nl",
    "wof:name":"Bes Lite",
    "wof:placetype":"venue"
},
  "geometry": {"coordinates":[4.484614,52.014717],"type":"Point"}
}