{
  "type": "Feature",
  "properties": {
    "addr:full":"Zuiderdiep 145 Nieuw Buinen Drenthe 9521 AD",
    "addr:housenumber":"145",
    "addr:postcode":"9521 ad",
    "addr:street":"Zuiderdiep;Nieuw Buinen",
    "iso:country":"NL",
    "sg:address":"Zuiderdiep 145",
    "sg:city":"Nieuw Buinen",
    "sg:orig_category":"Hengelsportartikelen",
    "sg:phone":"+31 599 212 196",
    "sg:postcode":"9521 AD",
    "sg:province":"Drenthe",
    "wof:name":"Hollandia",
    "wof:placetype":"venue"
},
  "geometry": {"coordinates":[6.908814,52.946171],"type":"Point"}
}