{
  "type": "Feature",
  "properties": {
    "addr:full":"Voorstadslaan 49 Nijmegen Gelderland 6541 AB",
    "addr:housenumber":"49",
    "addr:postcode":"6541 ab",
    "addr:street":"Voorstadslaan;Gelderland",
    "iso:country":"NL",
    "sg:address":"Voorstadslaan 49",
    "sg:city":"Nijmegen",
    "sg:orig_category":"Verhuur Catering-, Feest- En Evenementbenodigdheden",
    "sg:phone":"+31 24 377 1413",
    "sg:postcode":"6541 AB",
    "sg:province":"Gelderland",
    "wof:name":"Vereniging De Markies",
    "wof:placetype":"venue"
},
  "geometry": {"coordinates":[5.850543,51.848087],"type":"Point"}
}