{
  "type": "Feature",
  "properties": {
    "addr:full":"Oosteinde 85 Oosthuizen Noord-Holland 1474 ME",
    "addr:housenumber":"85",
    "addr:postcode":"1474 me",
    "addr:street":"Oosteinde",
    "iso:country":"NL",
    "sg:address":"Oosteinde 85",
    "sg:city":"Oosthuizen",
    "sg:orig_category":"Verenigingen En Stichtingen",
    "sg:phone":"+31 299 401 377",
    "sg:postcode":"1474 ME",
    "sg:province":"Noord-Holland",
    "wof:name":"Kalligrafenkring",
    "wof:placetype":"venue"
},
  "geometry": {"coordinates":[5.013846,52.5802],"type":"Point"}
}