{
  "type": "Feature",
  "properties": {
    "addr:full":"Bloemenlaan 14 Vlissingen Zeeland 4382 SC",
    "addr:housenumber":"14",
    "addr:postcode":"4382",
    "addr:street":"Bloemenlaan",
    "iso:country":"NL",
    "sg:address":"Bloemenlaan 14",
    "sg:city":"Vlissingen",
    "sg:classifiers":[
        {
            "category":"Food & Beverages",
            "subcategory":"Fruits & Vegetables",
            "type":"Retail Goods"
        }
    ],
    "sg:phone":"+31 118 418 332",
    "sg:postcode":"4382 SC",
    "sg:province":"Zeeland",
    "sg:tags":[
        "groenten"
    ],
    "wof:name":"Karaman",
    "wof:placetype":"venue"
},
  "geometry": {"coordinates":[3.573553,51.450859],"type":"Point"}
}