{
  "type": "Feature",
  "properties": {
    "addr:full":"Capellaln 65 Hoofddorp North Holland 2132 JL",
    "addr:housenumber":"65",
    "addr:postcode":"2132 jl",
    "addr:street":"Capellaln",
    "iso:country":"NL",
    "sg:address":"Capellaln 65",
    "sg:city":"Hoofddorp",
    "sg:classifiers":[
        {
            "category":"Shopping",
            "subcategory":"News",
            "type":"Retail Goods"
        }
    ],
    "sg:phone":"+31 23 556 4800",
    "sg:postcode":"2132 JL",
    "sg:province":"North Holland",
    "sg:tags":[
        "maandbladen",
        "en",
        "week-"
    ],
    "wof:name":"Beaumonde",
    "wof:placetype":"venue"
},
  "geometry": {"coordinates":[4.6929597855,52.305393219],"type":"Point"}
}