{
  "type": "Feature",
  "properties": {
    "addr:full":"Houtstr 118 Tilburg Noord-Brabant 5046 DM",
    "addr:housenumber":"118",
    "addr:postcode":"5046 dm",
    "addr:street":"Tilburg",
    "iso:country":"NL",
    "sg:address":"Houtstr 118",
    "sg:city":"Tilburg",
    "sg:orig_category":"Duikmaterialen",
    "sg:phone":"+31 13 542 7308",
    "sg:postcode":"5046 DM",
    "sg:province":"Noord-Brabant",
    "sg:website":"http://www.aalscholvers.nl",
    "wof:name":"Aalscholvers, De",
    "wof:placetype":"venue"
},
  "geometry": {"coordinates":[5.07823,51.57272],"type":"Point"}
}