{
  "type": "Feature",
  "properties": {
    "addr:full":"Breskensstr 15 Tilburg North Brabant 5043 WP",
    "addr:housenumber":"15",
    "addr:postcode":"5043 wp",
    "addr:street":"Breskensstr",
    "iso:country":"NL",
    "sg:address":"Breskensstr 15",
    "sg:city":"Tilburg",
    "sg:orig_category":"Autopoetsbedrijven",
    "sg:phone":"+31 13 572 0844",
    "sg:postcode":"5043 WP",
    "sg:province":"North Brabant",
    "wof:name":"Puweca",
    "wof:placetype":"venue"
},
  "geometry": {"coordinates":[5.01805,51.58493],"type":"Point"}
}