{
  "type": "Feature",
  "properties": {
    "addr:full":"Achterstr 10B Asch Gelderland 4115 RP",
    "addr:housenumber":"10b",
    "addr:postcode":"4115",
    "addr:street":"Achterstr;Gelderland",
    "iso:country":"NL",
    "sg:address":"Achterstr 10B",
    "sg:city":"Asch",
    "sg:orig_category":"Banden - Fabrieken En Groothandel",
    "sg:phone":"+31 345 501 741",
    "sg:postcode":"4115 RP",
    "sg:province":"Gelderland",
    "wof:name":"Kranenburg Vof",
    "wof:placetype":"venue"
},
  "geometry": {"coordinates":[5.308479,51.930309],"type":"Point"}
}