{
  "type": "Feature",
  "properties": {
    "addr:full":"Damrak 95 Amsterdam North Holland 1012 LP",
    "addr:housenumber":"95",
    "addr:postcode":"1012 lp",
    "addr:street":"Damrak",
    "iso:country":"NL",
    "sg:address":"Damrak 95",
    "sg:city":"Amsterdam",
    "sg:orig_category":"Wisselkantoren",
    "sg:phone":"+31 20 626 3658",
    "sg:postcode":"1012 LP",
    "sg:province":"North Holland",
    "wof:name":"Pott Bv",
    "wof:placetype":"venue"
},
  "geometry": {"coordinates":[4.8934779167,52.3736000061],"type":"Point"}
}