{
  "type": "Feature",
  "properties": {
    "addr:full":"Platinastraat 63 Lelystad Flevoland 8211 AR",
    "addr:housenumber":"63",
    "addr:postcode":"8211",
    "addr:street":"Platinastraat;Flevoland",
    "iso:country":"NL",
    "sg:address":"Platinastraat 63",
    "sg:city":"Lelystad",
    "sg:orig_category":"Airconditioning And Ventilatie",
    "sg:phone":"+31 320 281 166",
    "sg:postcode":"8211 AR",
    "sg:province":"Flevoland",
    "wof:name":"Monair Luchttechniek Bv",
    "wof:placetype":"venue"
},
  "geometry": {"coordinates":[5.516229,52.540936],"type":"Point"}
}