{
  "type": "Feature",
  "properties": {
    "addr:full":"Boschmeersngl 139 S Hertogenbosch North Brabant 5223 HH",
    "addr:housenumber":"139",
    "addr:postcode":"5223 hh",
    "addr:street":"S Hertogenbosch",
    "iso:country":"NL",
    "sg:address":"Boschmeersngl 139",
    "sg:city":"S Hertogenbosch",
    "sg:orig_category":"Behangselpapier En Wandbekleding",
    "sg:phone":"+31 73 621 7581",
    "sg:postcode":"5223 HH",
    "sg:province":"North Brabant",
    "wof:name":"Stezo Verf En Behang",
    "wof:placetype":"venue"
},
  "geometry": {"coordinates":[5.26181,51.689812],"type":"Point"}
}