{
  "type": "Feature",
  "properties": {
    "addr:full":"Burg Beerenbroekstr 11B Roermond Limburg 6043 AB",
    "addr:housenumber":"11b",
    "addr:postcode":"6043 ab",
    "addr:street":"Burg Beerenbroekstr",
    "iso:country":"NL",
    "sg:address":"Burg Beerenbroekstr 11B",
    "sg:city":"Roermond",
    "sg:orig_category":"Vertaal- And Tolkenbureaus",
    "sg:phone":"+31 475 316 419",
    "sg:postcode":"6043 AB",
    "sg:province":"Limburg",
    "wof:name":"R. Shakarchi",
    "wof:placetype":"venue"
},
  "geometry": {"coordinates":[5.996908,51.184513],"type":"Point"}
}