{
  "type": "Feature",
  "properties": {
    "iso:country":"NL",
    "sg:address":"Kanaalstr 66",
    "sg:city":"Roden",
    "sg:orig_category":"Fietsen En Bromfietsen",
    "sg:phone":"+31 50 503 3907",
    "sg:postcode":"9301 LT",
    "sg:province":"Drenthe",
    "wof:name":"Bike Store Roden",
    "wof:placetype":"venue"
},
  "geometry": {"coordinates":[6.432508,53.14473],"type":"Point"}
}