{
  "type": "Feature",
  "properties": {
    "addr:full":"Molenbossen 614 Venlo Limburg 5923 AJ",
    "addr:housenumber":"614",
    "addr:postcode":"5923 aj",
    "addr:street":"Molenbossen",
    "iso:country":"NL",
    "sg:address":"Molenbossen 614",
    "sg:city":"Venlo",
    "sg:orig_category":"Peuterspeelzalen",
    "sg:phone":"+31 77 326 6860",
    "sg:postcode":"5923 AJ",
    "sg:province":"Limburg",
    "wof:name":"Molenbossen, De",
    "wof:placetype":"venue"
},
  "geometry": {"coordinates":[6.1424741745,51.3586997986],"type":"Point"}
}