{
  "type": "Feature",
  "properties": {
    "iso:country":"NL",
    "sg:address":"M Harpertsz Trompln 8",
    "sg:city":"Enschede",
    "sg:orig_category":"Paramedische Behandelingen",
    "sg:phone":"+31 53 435 6516",
    "sg:postcode":"7511 JK",
    "sg:province":"NL.08",
    "wof:name":"Polay Vof",
    "wof:placetype":"venue"
},
  "geometry": {"coordinates":[6.895374,52.223576],"type":"Point"}
}