{
  "type": "Feature",
  "properties": {
    "addr:full":"Weversstraat 18 Lelystad Flevoland 8223 AC",
    "addr:housenumber":"18",
    "addr:postcode":"8223 ac",
    "addr:street":"Weversstraat;Flevoland",
    "iso:country":"NL",
    "sg:address":"Weversstraat 18",
    "sg:city":"Lelystad",
    "sg:orig_category":"Verzekeringen",
    "sg:phone":"+31 320 222 018",
    "sg:postcode":"8223 AC",
    "sg:province":"Flevoland",
    "wof:name":"Hessels & Hessels Ass. En Fin. Adviesbur",
    "wof:placetype":"venue"
},
  "geometry": {"coordinates":[5.48312,52.519714],"type":"Point"}
}