{
  "type": "Feature",
  "properties": {
    "addr:full":"Westerweg 346 Alkmaar Noord-Holland 1815 JM",
    "addr:housenumber":"346",
    "addr:postcode":"1815 jm",
    "addr:street":"Westerweg",
    "iso:country":"NL",
    "sg:address":"Westerweg 346",
    "sg:city":"Alkmaar",
    "sg:orig_category":"Marktonderzoekbureaus",
    "sg:phone":"+31 72 515 1068",
    "sg:postcode":"1815 JM",
    "sg:province":"Noord-Holland",
    "wof:name":"Drs. K.E. Vrijburg",
    "wof:placetype":"venue"
},
  "geometry": {"coordinates":[4.746258,52.634361],"type":"Point"}
}