{
  "type": "Feature",
  "properties": {
    "addr:full":"Dorpsstr 12 Bleiswijk Zuid-Holland 2665 BJ",
    "addr:housenumber":"12",
    "addr:postcode":"2665 bj",
    "addr:street":"Dorpsstr",
    "iso:country":"NL",
    "sg:address":"Dorpsstr 12",
    "sg:city":"Bleiswijk",
    "sg:orig_category":"Artsen - Huisartsen",
    "sg:phone":"+31 10 521 2500",
    "sg:postcode":"2665 BJ",
    "sg:province":"Zuid-Holland",
    "wof:name":"Warnaar, R L",
    "wof:placetype":"venue"
},
  "geometry": {"coordinates":[4.529693,52.009899],"type":"Point"}
}