{
  "type": "Feature",
  "properties": {
    "iso:country":"NL",
    "sg:address":"Puttensteinsv Wg 15",
    "sg:city":"Wezep",
    "sg:orig_category":"Adviesbureaus",
    "sg:phone":"+31 38 376 5802",
    "sg:postcode":"8091 BS",
    "sg:province":"Gelderland",
    "wof:name":"Grotenhuis",
    "wof:placetype":"venue"
},
  "geometry": {"coordinates":[5.993983,52.454288],"type":"Point"}
}