{
  "type": "Feature",
  "properties": {
    "addr:full":"Havenwg 10 Waalwyk Noord-Brabant 5145 NJ",
    "addr:housenumber":"10",
    "addr:postcode":"5145 nj",
    "addr:street":"Havenwg",
    "iso:country":"NL",
    "sg:address":"Havenwg 10",
    "sg:city":"Waalwyk",
    "sg:orig_category":"Machinefabrieken",
    "sg:phone":"+31 416 344 655",
    "sg:postcode":"5145 NJ",
    "sg:province":"Noord-Brabant",
    "wof:name":"Rabro Machinefabrieken Bv",
    "wof:placetype":"venue"
},
  "geometry": {"coordinates":[5.050999,51.694122],"type":"Point"}
}