{
  "type": "Feature",
  "properties": {
    "addr:full":"Prumelaan 2 Arnhem Gelderland 6824 HS",
    "addr:housenumber":"2",
    "addr:postcode":"6824 hs",
    "addr:street":"Prumelaan",
    "iso:country":"NL",
    "sg:address":"Prumelaan 2",
    "sg:city":"Arnhem",
    "sg:orig_category":"Medische Apparatuur And Prothesen Fab",
    "sg:phone":"+31 26 362 0455",
    "sg:postcode":"6824 HS",
    "sg:province":"Gelderland",
    "wof:name":"Tandprotheticus P Andriessen",
    "wof:placetype":"venue"
},
  "geometry": {"coordinates":[5.934361,51.989033],"type":"Point"}
}