{
  "type": "Feature",
  "properties": {
    "addr:full":"Den Oldenhoek 3 Groessen Gelderland 6923 SE",
    "addr:housenumber":"3",
    "addr:postcode":"6923",
    "addr:street":"Den Oldenhoek;Gelderland;Se",
    "iso:country":"NL",
    "sg:address":"Den Oldenhoek 3",
    "sg:city":"Groessen",
    "sg:classifiers":[
        {
            "category":"Sports & Exercise",
            "subcategory":"Stables",
            "type":"Entertainment"
        }
    ],
    "sg:phone":"+31 316 527 142",
    "sg:postcode":"6923 SE",
    "sg:province":"Gelderland",
    "sg:tags":[
        "maneges"
    ],
    "wof:name":"Landsmaat",
    "wof:placetype":"venue"
},
  "geometry": {"coordinates":[6.018187,51.924641],"type":"Point"}
}