{
  "type": "Feature",
  "properties": {
    "addr:full":"Terveenlaan 33 Hoofddorp North Holland 2132 WK",
    "addr:housenumber":"33",
    "addr:postcode":"2132 wk",
    "addr:street":"Terveenlaan",
    "iso:country":"NL",
    "sg:address":"Terveenlaan 33",
    "sg:city":"Hoofddorp",
    "sg:orig_category":"Verhuur Audiovisuele Apparatuur",
    "sg:phone":"+31 23 562 4157",
    "sg:postcode":"2132 WK",
    "sg:province":"North Holland",
    "wof:name":"Enzler Sound Service",
    "wof:placetype":"venue"
},
  "geometry": {"coordinates":[4.687637,52.30518],"type":"Point"}
}