{
  "type": "Feature",
  "properties": {
    "addr:full":"Markt 12 Beesel Limburg 5954 BH",
    "addr:housenumber":"12",
    "addr:postcode":"5954 bh",
    "addr:street":"Markt",
    "iso:country":"NL",
    "sg:address":"Markt 12",
    "sg:city":"Beesel",
    "sg:orig_category":"Bibliotheken And Openbare Archieven",
    "sg:phone":"+31 77 474 2535",
    "sg:postcode":"5954 BH",
    "sg:province":"Limburg",
    "wof:name":"Stichting Openbare Bibliotheek",
    "wof:placetype":"venue"
},
  "geometry": {"coordinates":[6.039425,51.26733],"type":"Point"}
}