{
  "type": "Feature",
  "properties": {
    "addr:full":"Sarphatipark 80 Amsterdam Noord-Holland 1073 EB",
    "addr:housenumber":"80",
    "addr:postcode":"1073 eb",
    "addr:street":"Sarphatipark",
    "iso:country":"NL",
    "sg:address":"Sarphatipark 80",
    "sg:city":"Amsterdam",
    "sg:orig_category":"Verzekeringen",
    "sg:phone":"+31 20 675 2266",
    "sg:postcode":"1073 EB",
    "sg:province":"Noord-Holland",
    "wof:name":"Amsterdamse Assurantie Groep",
    "wof:placetype":"venue"
},
  "geometry": {"coordinates":[4.896567,52.353519],"type":"Point"}
}