{
  "type": "Feature",
  "properties": {
    "addr:full":"Susannadonk 23 Roosendaal North Brabant 4707 WN",
    "addr:housenumber":"23",
    "addr:postcode":"4707 wn",
    "addr:street":"Susannadonk",
    "iso:country":"NL",
    "sg:address":"Susannadonk 23",
    "sg:city":"Roosendaal",
    "sg:orig_category":"Bodemonderzoek",
    "sg:phone":"+31 165 570 537",
    "sg:postcode":"4707 WN",
    "sg:province":"North Brabant",
    "wof:name":"Bms",
    "wof:placetype":"venue"
},
  "geometry": {"coordinates":[4.469273,51.519882],"type":"Point"}
}