{
  "type": "Feature",
  "properties": {
    "iso:country":"NL",
    "sg:address":"Slinge 580",
    "sg:city":"Rotterdam",
    "sg:orig_category":"Kaas",
    "sg:phone":"+31 10 210 1341",
    "sg:postcode":"3086 EW",
    "sg:province":"Zuid-Holland",
    "wof:name":"Besten Vof, Den",
    "wof:placetype":"venue"
},
  "geometry": {"coordinates":[4.4694361687,51.8746109009],"type":"Point"}
}