{
  "type": "Feature",
  "properties": {
    "addr:full":"Heuvellaan 3 Gouda South Holland 2803 DT",
    "addr:housenumber":"3",
    "addr:postcode":"2803 dt",
    "addr:street":"Heuvellaan",
    "iso:country":"NL",
    "sg:address":"Heuvellaan 3",
    "sg:city":"Gouda",
    "sg:orig_category":"Diverse Grafische Activiteiten",
    "sg:phone":"+31 182 534 311",
    "sg:postcode":"2803 DT",
    "sg:province":"South Holland",
    "wof:name":"Quint Concept",
    "wof:placetype":"venue"
},
  "geometry": {"coordinates":[4.690715,52.022438],"type":"Point"}
}