{
  "type": "Feature",
  "properties": {
    "addr:full":"V V Goghsngl 29 Hillegom North Holland 2182 LM",
    "addr:housenumber":"29",
    "addr:postcode":"2182 lm",
    "addr:street":"Goghsngl",
    "iso:country":"NL",
    "sg:address":"V V Goghsngl 29",
    "sg:city":"Hillegom",
    "sg:orig_category":"Onderwijsmateriaal",
    "sg:phone":"+31 252 532 158",
    "sg:postcode":"2182 LM",
    "sg:province":"North Holland",
    "wof:name":"Leeuwen, Karel Van",
    "wof:placetype":"venue"
},
  "geometry": {"coordinates":[4.578603,52.290993],"type":"Point"}
}