{
  "type": "Feature",
  "properties": {
    "iso:country":"NL",
    "sg:address":"V V Goghsngl 29",
    "sg:city":"Hillegom",
    "sg:orig_category":"Onderwijsmateriaal",
    "sg:phone":"+31 252 532 158",
    "sg:postcode":"2182 LM",
    "sg:province":"North Holland",
    "wof:name":"Leeuwen, Karel Van",
    "wof:placetype":"venue"
},
  "geometry": {"coordinates":[4.578603,52.290993],"type":"Point"}
}