{
  "type": "Feature",
  "properties": {
    "addr:full":"Rietakker 30 Koog Aan De Zaan North Holland 1541 TT",
    "addr:housenumber":"30",
    "addr:postcode":"1541 tt",
    "addr:street":"Rietakker",
    "iso:country":"NL",
    "sg:address":"Rietakker 30",
    "sg:city":"Koog Aan De Zaan",
    "sg:orig_category":"Verzekeringen - Verzekeringskantoren",
    "sg:phone":"+31 75 628 6820",
    "sg:postcode":"1541 TT",
    "sg:province":"North Holland",
    "wof:name":"Chin, L G",
    "wof:placetype":"venue"
},
  "geometry": {"coordinates":[4.791808,52.460808],"type":"Point"}
}