{
  "type": "Feature",
  "properties": {
    "iso:country":"NL",
    "sg:address":"Hongkongstr 52",
    "sg:city":"Rotterdam",
    "sg:orig_category":"Accumulatoren - Fabrieken En Groothandel",
    "sg:phone":"+31 10 413 4840",
    "sg:postcode":"3047 BS",
    "sg:province":"South Holland",
    "wof:name":"Wilco Nederland Bv",
    "wof:placetype":"venue"
},
  "geometry": {"coordinates":[4.405312,51.942726],"type":"Point"}
}