{
  "type": "Feature",
  "properties": {
    "addr:full":"Okapistr 33 Almere NL. 1338 JT",
    "addr:housenumber":"33",
    "addr:postcode":"1338 jt",
    "addr:street":"Okapistr;Nl.",
    "iso:country":"NL",
    "sg:address":"Okapistr 33",
    "sg:city":"Almere",
    "sg:orig_category":"Kappers",
    "sg:phone":"+31 36 532 6311",
    "sg:postcode":"1338 JT",
    "sg:province":"NL.",
    "wof:name":"Mobile Knip Service",
    "wof:placetype":"venue"
},
  "geometry": {"coordinates":[5.274145,52.383728],"type":"Point"}
}