{
  "type": "Feature",
  "properties": {
    "addr:full":"Kolperstr 21 S Hertogenbosch North Brabant 5211 KB",
    "addr:housenumber":"21",
    "addr:postcode":"5211 kb",
    "addr:street":"Kolperstr;S Hertogenbosch",
    "iso:country":"NL",
    "sg:address":"Kolperstr 21",
    "sg:city":"S Hertogenbosch",
    "sg:orig_category":"Boetieks",
    "sg:phone":"+31 73 613 9579",
    "sg:postcode":"5211 KB",
    "sg:province":"North Brabant",
    "wof:name":"Boetnick",
    "wof:placetype":"venue"
},
  "geometry": {"coordinates":[5.304075,51.688229],"type":"Point"}
}