{
  "type": "Feature",
  "properties": {
    "addr:full":"Raaphorstln 26 S Gravenhage Zuid-Holland 2532 BH",
    "addr:housenumber":"26;gravenhage",
    "addr:postcode":"2532 bh",
    "addr:street":"Raaphorstln;S",
    "iso:country":"NL",
    "sg:address":"Raaphorstln 26",
    "sg:city":"S Gravenhage",
    "sg:classifiers":[
        {
            "category":"Food & Beverages",
            "subcategory":"Bakery",
            "type":"Retail Goods"
        }
    ],
    "sg:phone":"+31 70 300 0900",
    "sg:postcode":"2532 BH",
    "sg:province":"Zuid-Holland",
    "sg:tags":[
        "pizza"
    ],
    "wof:name":"Original Pizza Company",
    "wof:placetype":"venue"
},
  "geometry": {"coordinates":[4.29807,52.048569],"type":"Point"}
}