{
  "type": "Feature",
  "properties": {
    "addr:full":"Kastelenstr 4 Amsterdam Noord-Holland 1083 CD",
    "addr:housenumber":"4",
    "addr:postcode":"1083 cd",
    "addr:street":"Kastelenstr",
    "iso:country":"NL",
    "sg:address":"Kastelenstr 4",
    "sg:city":"Amsterdam",
    "sg:orig_category":"Kappers",
    "sg:phone":"+31 20 642 0254",
    "sg:postcode":"1083 CD",
    "sg:province":"Noord-Holland",
    "wof:name":"Le R\u00eave",
    "wof:placetype":"venue"
},
  "geometry": {"coordinates":[4.884383,52.326199],"type":"Point"}
}