{
  "type": "Feature",
  "properties": {
    "addr:full":"Polstr 29 Wyk En Aalburg Gelderland 4261 BP",
    "addr:housenumber":"29",
    "addr:postcode":"4261 bp",
    "addr:street":"Polstr",
    "iso:country":"NL",
    "sg:address":"Polstr 29",
    "sg:city":"Wyk En Aalburg",
    "sg:orig_category":"Leder",
    "sg:phone":"+31 416 692 549",
    "sg:postcode":"4261 BP",
    "sg:province":"Gelderland",
    "wof:name":"Pal",
    "wof:placetype":"venue"
},
  "geometry": {"coordinates":[5.130571,51.751259],"type":"Point"}
}