{
  "type": "Feature",
  "properties": {
    "addr:full":"Rochussenstr 724 Rotterdam South Holland 3015 ZG",
    "addr:housenumber":"724",
    "addr:postcode":"3015 zg",
    "iso:country":"NL",
    "sg:address":"Rochussenstr 724",
    "sg:city":"Rotterdam",
    "sg:orig_category":"Webdesign Bureaus",
    "sg:phone":"+31 10 225 1143",
    "sg:postcode":"3015 ZG",
    "sg:province":"South Holland",
    "sg:website":"http://www.globalinnovation.nl",
    "wof:name":"Global Innovation",
    "wof:placetype":"venue"
},
  "geometry": {"coordinates":[4.4610328674,51.9108581543],"type":"Point"}
}