{
  "type": "Feature",
  "properties": {
    "addr:full":"Kruisstraat 12 Duizel North Brabant 5525 AX",
    "addr:housenumber":"12",
    "addr:postcode":"5525 ax",
    "addr:street":"Kruisstraat",
    "iso:country":"NL",
    "sg:address":"Kruisstraat 12",
    "sg:city":"Duizel",
    "sg:orig_category":"Kappers",
    "sg:phone":"+31 497 517 632",
    "sg:postcode":"5525 AX",
    "sg:province":"North Brabant",
    "wof:name":"Scissors Duizel",
    "wof:placetype":"venue"
},
  "geometry": {"coordinates":[5.296188,51.368874],"type":"Point"}
}