{
  "type": "Feature",
  "properties": {
    "addr:full":"G V Assendelftstr 24 Heemskerk Noord-Holland 1961 NK",
    "addr:housenumber":"24",
    "addr:postcode":"1961 nk",
    "addr:street":"V Assendelftstr",
    "iso:country":"NL",
    "sg:address":"G V Assendelftstr 24",
    "sg:city":"Heemskerk",
    "sg:orig_category":"Kappers",
    "sg:phone":"+31 251 248 967",
    "sg:postcode":"1961 NK",
    "sg:province":"Noord-Holland",
    "sg:website":"http://www.jacquescoiffures.nl",
    "wof:name":"Jacques Coiffures",
    "wof:placetype":"venue"
},
  "geometry": {"coordinates":[4.6706857681,52.5113677979],"type":"Point"}
}