{
  "type": "Feature",
  "properties": {
    "addr:full":"Lobeliusstraat 22 Zaandam Noord-Holland 1504 EM",
    "addr:housenumber":"22",
    "addr:postcode":"1504 em",
    "addr:street":"Lobeliusstraat",
    "iso:country":"NL",
    "sg:address":"Lobeliusstraat 22",
    "sg:city":"Zaandam",
    "sg:orig_category":"Drogisterijen",
    "sg:phone":"+31 75 616 9282",
    "sg:postcode":"1504 EM",
    "sg:province":"Noord-Holland",
    "wof:name":"Da Drogisterij Aker",
    "wof:placetype":"venue"
},
  "geometry": {"coordinates":[4.851275,52.43531],"type":"Point"}
}