{
  "type": "Feature",
  "properties": {
    "addr:full":"Postbus 754 Buren Gld Gelderland 4116 ZK",
    "addr:housenumber":"754",
    "addr:postcode":"4116",
    "addr:street":"Postbus;Gld Gelderland",
    "iso:country":"NL",
    "sg:address":"Postbus 754",
    "sg:city":"Buren Gld",
    "sg:orig_category":"Verzekeringen - Verzekeringskantoren",
    "sg:phone":"+31 344 572 757",
    "sg:postcode":"4116 ZK",
    "sg:province":"Gelderland",
    "sg:website":"http://www.dividus.nl",
    "wof:name":"Dividus",
    "wof:placetype":"venue"
},
  "geometry": {"coordinates":[5.335208,51.909687],"type":"Point"}
}