{
  "type": "Feature",
  "properties": {
    "iso:country":"NL",
    "sg:address":"Hoofdweg 180",
    "sg:city":"Amsterdam",
    "sg:orig_category":"Advocaten And Juridische Adviseurs",
    "sg:phone":"+31 20 618 1046",
    "sg:postcode":"1057 DD",
    "sg:province":"Noord-Holland",
    "wof:name":"Advocatenkantoor De Baarsjes",
    "wof:placetype":"venue"
},
  "geometry": {"coordinates":[4.853238,52.365879],"type":"Point"}
}