{
  "type": "Feature",
  "properties": {
    "addr:full":"Julianastr 1 Linne Limburg 6067 EV",
    "addr:housenumber":"1",
    "addr:postcode":"6067 ev",
    "addr:street":"Julianastr",
    "iso:country":"NL",
    "sg:address":"Julianastr 1",
    "sg:city":"Linne",
    "sg:orig_category":"Adviesbureaus Waterbouwkunde",
    "sg:phone":"+31 475 468 442",
    "sg:postcode":"6067 EV",
    "sg:province":"Limburg",
    "wof:name":"Geloof, V A Van 'T",
    "wof:placetype":"venue"
},
  "geometry": {"coordinates":[-67.840874,46.241039],"type":"Point"}
}