{
  "type": "Feature",
  "properties": {
    "iso:country":"NL",
    "sg:address":"Hoogstr 14",
    "sg:city":"Tholen",
    "sg:orig_category":"Kantoor- En Bedrijfsmeubelen",
    "sg:phone":"+31 166 602 597",
    "sg:postcode":"4691 CB",
    "sg:province":"Zeeland",
    "wof:name":"Dieleman",
    "wof:placetype":"venue"
},
  "geometry": {"coordinates":[4.218682766,51.53565979],"type":"Point"}
}