{
  "type": "Feature",
  "properties": {
    "addr:full":"Pelikaansngl 90 Delft Zuid-Holland 2623 JK",
    "addr:housenumber":"90",
    "addr:postcode":"2623 jk",
    "addr:street":"Pelikaansngl",
    "iso:country":"NL",
    "sg:address":"Pelikaansngl 90",
    "sg:city":"Delft",
    "sg:orig_category":"Verenigingen En Stichtingen",
    "sg:phone":"+31 15 261 2215",
    "sg:postcode":"2623 JK",
    "sg:province":"Zuid-Holland",
    "wof:name":"Bernardus Ehbo Ver",
    "wof:placetype":"venue"
},
  "geometry": {"coordinates":[4.361076,51.980892],"type":"Point"}
}