{
  "type": "Feature",
  "properties": {
    "iso:country":"NL",
    "sg:address":"Niasstraat 10",
    "sg:city":"Amsterdam",
    "sg:classifiers":[
        {
            "category":"Fast Food",
            "type":"Food & Drink"
        }
    ],
    "sg:phone":"+31 20 665 0789",
    "sg:postcode":"1095 VA",
    "sg:province":"Noord-Holland",
    "sg:tags":[
        "afhaal",
        "restaurant"
    ],
    "wof:name":"R. Schenk",
    "wof:placetype":"venue"
},
  "geometry": {"coordinates":[-74.129097,42.961079],"type":"Point"}
}