{
  "type": "Feature",
  "properties": {
    "addr:full":"V L V Pabststr 33 Arnhem Gelderland 6814 HA",
    "addr:housenumber":"33",
    "addr:postcode":"6814 ha",
    "addr:street":"V L V Pabststr",
    "iso:country":"NL",
    "sg:address":"V L V Pabststr 33",
    "sg:city":"Arnhem",
    "sg:orig_category":"Adviesbureaus Bedrijfsorganisatie",
    "sg:phone":"+31 26 446 1822",
    "sg:postcode":"6814 HA",
    "sg:province":"Gelderland",
    "wof:name":"Gerritsma Bv",
    "wof:placetype":"venue"
},
  "geometry": {"coordinates":[5.904585,51.985519],"type":"Point"}
}