{
  "type": "Feature",
  "properties": {
    "iso:country":"NL",
    "sg:address":"Rijksweg 17",
    "sg:city":"Naarden",
    "sg:orig_category":"Bloemen And Planten",
    "sg:phone":"+31 35 694 7819",
    "sg:postcode":"1411 GD",
    "sg:province":"Noord-Holland",
    "wof:name":"Ecr",
    "wof:placetype":"venue"
},
  "geometry": {"coordinates":[5.157765,52.287655],"type":"Point"}
}