{
  "type": "Feature",
  "properties": {
    "addr:full":"Binnenlandse Baan 68 Barendrecht Zuid-Holland 2991 EB",
    "addr:housenumber":"68",
    "addr:postcode":"2991 eb",
    "addr:street":"Binnenlandse Baan",
    "iso:country":"NL",
    "sg:address":"Binnenlandse Baan 68",
    "sg:city":"Barendrecht",
    "sg:orig_category":"Adviesbureaus Bedrijfsorganisatie",
    "sg:phone":"+31 180 614 664",
    "sg:postcode":"2991 EB",
    "sg:province":"Zuid-Holland",
    "wof:name":"Pyramid",
    "wof:placetype":"venue"
},
  "geometry": {"coordinates":[4.544975,51.852947],"type":"Point"}
}