{
  "type": "Feature",
  "properties": {
    "addr:full":"Ir Blankenstr 9 Werkendam North Brabant 4251 NR",
    "addr:housenumber":"9",
    "addr:postcode":"4251 nr",
    "iso:country":"NL",
    "sg:address":"Ir Blankenstr 9",
    "sg:city":"Werkendam",
    "sg:orig_category":"Waterbouwkundige Werken",
    "sg:phone":"+31 183 508 888",
    "sg:postcode":"4251 NR",
    "sg:province":"North Brabant",
    "sg:website":"http://www.vrieswerkendam.nl",
    "wof:name":"Vries Werkendam Bv, De",
    "wof:placetype":"venue"
},
  "geometry": {"coordinates":[4.8793478012,51.8056335449],"type":"Point"}
}