{
  "type": "Feature",
  "properties": {
    "addr:full":"Handelsstr 20 Stadskanaal Groningen 9501 ET",
    "addr:housenumber":"20",
    "addr:postcode":"9501 et",
    "addr:street":"Handelsstr",
    "iso:country":"NL",
    "sg:address":"Handelsstr 20",
    "sg:city":"Stadskanaal",
    "sg:orig_category":"Onderwijsmateriaal",
    "sg:phone":"+31 599 612 620",
    "sg:postcode":"9501 ET",
    "sg:province":"Groningen",
    "wof:name":"Binco Bv",
    "wof:placetype":"venue"
},
  "geometry": {"coordinates":[6.933985,52.999245],"type":"Point"}
}