{
  "type": "Feature",
  "properties": {
    "addr:full":"Buitenkwartier 10 Zwartsluis NL.08 8064 AE",
    "addr:housenumber":"10;nl.08",
    "addr:postcode":"8064 ae",
    "addr:street":"Buitenkwartier",
    "iso:country":"NL",
    "sg:address":"Buitenkwartier 10",
    "sg:city":"Zwartsluis",
    "sg:orig_category":"Verlichting And Huishoudartikelen",
    "sg:phone":"+31 38 386 6893",
    "sg:postcode":"8064 AE",
    "sg:province":"NL.08",
    "wof:name":"Oegema",
    "wof:placetype":"venue"
},
  "geometry": {"coordinates":[6.067547,52.640015],"type":"Point"}
}