{
  "type": "Feature",
  "properties": {
    "addr:full":"Nieuwstr 38 Deventer Overijssel 7411 LM",
    "addr:housenumber":"38",
    "addr:postcode":"7411 lm",
    "addr:street":"Nieuwstr",
    "iso:country":"NL",
    "sg:address":"Nieuwstr 38",
    "sg:city":"Deventer",
    "sg:orig_category":"Boeken En Tijdschriften",
    "sg:phone":"+31 570 616 879",
    "sg:postcode":"7411 LM",
    "sg:province":"Overijssel",
    "wof:name":"Knibbel Comics",
    "wof:placetype":"venue"
},
  "geometry": {"coordinates":[6.159899,52.251034],"type":"Point"}
}