{
  "type": "Feature",
  "properties": {
    "addr:full":"Woldpromenade 25 Steenwijk Overijssel 8331 JD",
    "addr:housenumber":"25",
    "addr:postcode":"8331 jd",
    "addr:street":"Woldpromenade",
    "iso:country":"NL",
    "sg:address":"Woldpromenade 25",
    "sg:city":"Steenwijk",
    "sg:orig_category":"Kappers",
    "sg:phone":"+31 521 514 809",
    "sg:postcode":"8331 JD",
    "sg:province":"Overijssel",
    "wof:name":"Kuipers Beautycenter",
    "wof:placetype":"venue"
},
  "geometry": {"coordinates":[6.113341,52.786472],"type":"Point"}
}