{
  "type": "Feature",
  "properties": {
    "iso:country":"NL",
    "sg:address":"Badhuiswg 18A",
    "sg:city":"S Gravenhage",
    "sg:orig_category":"Adviesbureaus Bedrijfsorganisatie",
    "sg:phone":"+31 70 355 9607",
    "sg:postcode":"2587 CH",
    "sg:province":"Zuid-Holland",
    "wof:name":"Besteman Cons",
    "wof:placetype":"venue"
},
  "geometry": {"coordinates":[4.29118,52.112942],"type":"Point"}
}