{
  "type": "Feature",
  "properties": {
    "addr:full":"Nieuwstr 2 Baarle Nassau Noord-Brabant 5111 CW",
    "addr:housenumber":"2",
    "addr:postcode":"5111 cw",
    "addr:street":"Nieuwstr",
    "iso:country":"NL",
    "sg:address":"Nieuwstr 2",
    "sg:city":"Baarle Nassau",
    "sg:orig_category":"Kappers",
    "sg:phone":"+31 13 507 9885",
    "sg:postcode":"5111 CW",
    "sg:province":"Noord-Brabant",
    "wof:name":"Haar Hoek",
    "wof:placetype":"venue"
},
  "geometry": {"coordinates":[4.9262900352,51.4497413635],"type":"Point"}
}