{
  "type": "Feature",
  "properties": {
    "addr:full":"Engelandln 169 Haarlem Noord-Holland 2034 PK",
    "addr:housenumber":"169",
    "addr:postcode":"2034 pk",
    "iso:country":"NL",
    "sg:address":"Engelandln 169",
    "sg:city":"Haarlem",
    "sg:orig_category":"Meubelen - Fabrieken En Groothandel",
    "sg:phone":"+31 23 540 4555",
    "sg:postcode":"2034 PK",
    "sg:province":"Noord-Holland",
    "sg:website":"HTTP://www.zydante.com",
    "wof:name":"Zydante",
    "wof:placetype":"venue"
},
  "geometry": {"coordinates":[4.643523,52.362278],"type":"Point"}
}