{
  "type": "Feature",
  "properties": {
    "addr:full":"Marnixstraat 76 Amsterdam North Holland 1015 VX",
    "addr:housenumber":"76",
    "addr:postcode":"1015 vx",
    "addr:street":"Marnixstraat",
    "iso:country":"NL",
    "sg:address":"Marnixstraat 76",
    "sg:city":"Amsterdam",
    "sg:orig_category":"Verhuur Catering-, Feest- En Evenementbenodigdheden",
    "sg:phone":"+31 20 421 2016",
    "sg:postcode":"1015 VX",
    "sg:province":"North Holland",
    "wof:name":"Euro Amusement",
    "wof:placetype":"venue"
},
  "geometry": {"coordinates":[4.879592,52.379501],"type":"Point"}
}