{
  "type": "Feature",
  "properties": {
    "addr:full":"Nijverheidstr 15 Someren North Brabant 5711 CZ",
    "addr:housenumber":"15",
    "addr:postcode":"5711",
    "addr:street":"Nijverheidstr",
    "iso:country":"NL",
    "sg:address":"Nijverheidstr 15",
    "sg:city":"Someren",
    "sg:orig_category":"Wegenbouw - Materieel",
    "sg:phone":"+31 493 494 884",
    "sg:postcode":"5711 CZ",
    "sg:province":"North Brabant",
    "wof:name":"Smitma Bv",
    "wof:placetype":"venue"
},
  "geometry": {"coordinates":[5.7272229195,51.3919143677],"type":"Point"}
}