{
  "type": "Feature",
  "properties": {
    "addr:full":"Willem Barentszstraat 19 Barneveld Gelderland 3772 KZ",
    "addr:housenumber":"19",
    "addr:postcode":"3772",
    "addr:street":"Willem Barentszstraat;Gelderland",
    "iso:country":"NL",
    "sg:address":"Willem Barentszstraat 19",
    "sg:city":"Barneveld",
    "sg:orig_category":"Voeding, Dranken And Tabak Gh",
    "sg:phone":"+31 342 415 520",
    "sg:postcode":"3772 KZ",
    "sg:province":"Gelderland",
    "wof:name":"Gsb Trading Bv",
    "wof:placetype":"venue"
},
  "geometry": {"coordinates":[5.573216,52.131073],"type":"Point"}
}