{
  "type": "Feature",
  "properties": {
    "addr:full":"Brede Haven 30 'S Hertogenbosch North Brabant 5211 TM",
    "addr:housenumber":"30",
    "addr:postcode":"5211 tm",
    "addr:street":"Brede Haven;' S Hertogenbosch",
    "iso:country":"NL",
    "sg:address":"Brede Haven 30",
    "sg:city":"'S Hertogenbosch",
    "sg:orig_category":"Meubelreparatie And -Restauratie",
    "sg:phone":"+31 73 614 7438",
    "sg:postcode":"5211 TM",
    "sg:province":"North Brabant",
    "wof:name":"Fa F Van Herwijnen",
    "wof:placetype":"venue"
},
  "geometry": {"coordinates":[5.299825,51.691662],"type":"Point"}
}