{
  "type": "Feature",
  "properties": {
    "iso:country":"NL",
    "sg:address":"Paadje 18",
    "sg:city":"Nieuwe Niedorp",
    "sg:orig_category":"Zuivelproducten And Spijsoli?n Gh",
    "sg:phone":"+31 226 411 219",
    "sg:postcode":"1733 NE",
    "sg:province":"Noord-Holland",
    "wof:name":"De Elzenhof Bv",
    "wof:placetype":"venue"
},
  "geometry": {"coordinates":[4.909797,52.74036],"type":"Point"}
}