{
  "type": "Feature",
  "properties": {
    "addr:full":"Rykswg 152 Hoogersmilde Provincie Drenthe 9423 PB",
    "addr:housenumber":"152",
    "addr:postcode":"9423 pb",
    "addr:street":"Provincie Drenthe",
    "iso:country":"NL",
    "sg:address":"Rykswg 152",
    "sg:city":"Hoogersmilde",
    "sg:orig_category":"Scholen Voor Basisonderwijs",
    "sg:phone":"+31 592 459 055",
    "sg:postcode":"9423 PB",
    "sg:province":"Provincie Drenthe",
    "wof:name":"Vaart Chr, De",
    "wof:placetype":"venue"
},
  "geometry": {"coordinates":[6.405702,52.913322],"type":"Point"}
}