{
  "type": "Feature",
  "properties": {
    "addr:full":"J.C. Bloemstraat 8 Vleuten Utrecht 3451 AA",
    "addr:housenumber":"8",
    "addr:postcode":"3451 aa",
    "addr:street":"J.C. Bloemstraat",
    "iso:country":"NL",
    "sg:address":"J.C. Bloemstraat 8",
    "sg:city":"Vleuten",
    "sg:orig_category":"Schilderwerk",
    "sg:phone":"+31 30 677 5000",
    "sg:postcode":"3451 AA",
    "sg:province":"Utrecht",
    "wof:name":"H C Molenaar",
    "wof:placetype":"venue"
},
  "geometry": {"coordinates":[5.01342,52.105862],"type":"Point"}
}