{
  "type": "Feature",
  "properties": {
    "iso:country":"NL",
    "sg:address":"Roselaar 14",
    "sg:city":"Roosendaal",
    "sg:classifiers":[
        {
            "category":"Bakery",
            "type":"Food & Drink"
        }
    ],
    "sg:phone":"+31 165 537 725",
    "sg:postcode":"4701 BC",
    "sg:province":"Noord-Brabant",
    "sg:tags":[
        "brood",
        "banket"
    ],
    "wof:name":"Jamin",
    "wof:placetype":"venue"
},
  "geometry": {"coordinates":[4.453341,51.530678],"type":"Point"}
}