{
  "type": "Feature",
  "properties": {
    "addr:full":"Burg V Oordstr 22 Ermelo Gelderland 3851 JT",
    "addr:housenumber":"22",
    "addr:postcode":"3851 jt",
    "addr:street":"Burg V Oordstr;Gelderland",
    "iso:country":"NL",
    "sg:address":"Burg V Oordstr 22",
    "sg:city":"Ermelo",
    "sg:classifiers":[
        {
            "category":"Home & Garden",
            "subcategory":"Hardware",
            "type":"Retail Goods"
        }
    ],
    "sg:phone":"+31 341 552 003",
    "sg:postcode":"3851 JT",
    "sg:province":"Gelderland",
    "sg:tags":[
        "machine",
        "-",
        "metaalbewerking"
    ],
    "wof:name":"Ringnalda En Zn Bv",
    "wof:placetype":"venue"
},
  "geometry": {"coordinates":[5.63146,52.297852],"type":"Point"}
}