{
  "type": "Feature",
  "properties": {
    "addr:full":"Chassestraat 71 'S Gravenhage South Holland 2518 RW",
    "addr:housenumber":"71",
    "addr:postcode":"2518 rw",
    "addr:street":"Chassestraat;' S Gravenhage",
    "iso:country":"NL",
    "sg:address":"Chassestraat 71",
    "sg:city":"'S Gravenhage",
    "sg:orig_category":"Boekhandels",
    "sg:phone":"+31 70 365 0738",
    "sg:postcode":"2518 RW",
    "sg:province":"South Holland",
    "wof:name":"Mieke'S Striptiek",
    "wof:placetype":"venue"
},
  "geometry": {"coordinates":[4.28848,52.077843],"type":"Point"}
}