{
  "type": "Feature",
  "properties": {
    "addr:full":"Lamsoor 13 Groningen Groningen 9738 AL",
    "addr:housenumber":"13",
    "addr:postcode":"9738 al",
    "addr:street":"Lamsoor",
    "iso:country":"NL",
    "sg:address":"Lamsoor 13",
    "sg:city":"Groningen",
    "sg:orig_category":"Accountants - Administratie- Consulenten En -Kantoren",
    "sg:phone":"+31 50 525 1485",
    "sg:postcode":"9738 AL",
    "sg:province":"Groningen",
    "wof:name":"Noorda Bv, Accountantskantoor",
    "wof:placetype":"venue"
},
  "geometry": {"coordinates":[6.57451,53.246189],"type":"Point"}
}