{
  "type": "Feature",
  "properties": {
    "iso:country":"NL",
    "sg:address":"Wesselmanln 12",
    "sg:city":"Helmond",
    "sg:orig_category":"Adviesbureaus Bedrijfsorganisatie",
    "sg:phone":"+31 492 335 171",
    "sg:postcode":"5707 HC",
    "sg:province":"Noord-Brabant",
    "wof:name":"Aston Hill Bv",
    "wof:placetype":"venue"
},
  "geometry": {"coordinates":[5.645332,51.481609],"type":"Point"}
}