{
  "type": "Feature",
  "properties": {
    "addr:full":"Praamkade 1 Maastricht Limburg 6222 NN",
    "addr:housenumber":"1",
    "addr:postcode":"6222 nn",
    "addr:street":"Praamkade",
    "iso:country":"NL",
    "sg:address":"Praamkade 1",
    "sg:city":"Maastricht",
    "sg:orig_category":"Chemische Producten Gh",
    "sg:phone":"+31 43 362 6500",
    "sg:postcode":"6222 NN",
    "sg:province":"Limburg",
    "wof:name":"Metals Chemicals Maastricht Bv",
    "wof:placetype":"venue"
},
  "geometry": {"coordinates":[5.713623,50.88726],"type":"Point"}
}