{
  "type": "Feature",
  "properties": {
    "addr:full":"5 Meipln 98 Leiden Zuid-Holland 2321 BS",
    "addr:housenumber":"5;98",
    "addr:postcode":"2321 bs",
    "addr:street":"Meipln",
    "iso:country":"NL",
    "sg:address":"5 Meipln 98",
    "sg:city":"Leiden",
    "sg:orig_category":"Schoenen",
    "sg:phone":"+31 71 532 0200",
    "sg:postcode":"2321 BS",
    "sg:province":"Zuid-Holland",
    "wof:name":"Loos, De",
    "wof:placetype":"venue"
},
  "geometry": {"coordinates":[4.480197,52.147552],"type":"Point"}
}