{
  "type": "Feature",
  "properties": {
    "addr:full":"Levie Vorstkade 27 Rotterdam Zuid-Holland 3071 AG",
    "addr:housenumber":"27",
    "addr:postcode":"3071",
    "addr:street":"Levie Vorstkade",
    "iso:country":"NL",
    "sg:address":"Levie Vorstkade 27",
    "sg:city":"Rotterdam",
    "sg:orig_category":"Architecten",
    "sg:phone":"+31 10 215 2032",
    "sg:postcode":"3071 AG",
    "sg:province":"Zuid-Holland",
    "wof:name":"Docovas Architecten/Ontwerpers",
    "wof:placetype":"venue"
},
  "geometry": {"coordinates":[4.496153,51.908928],"type":"Point"}
}