{
  "type": "Feature",
  "properties": {
    "addr:full":"Akkerstr 91 Tilburg Noord-Brabant 5025 MG",
    "addr:housenumber":"91",
    "addr:postcode":"5025 mg",
    "addr:street":"Akkerstr",
    "iso:country":"NL",
    "sg:address":"Akkerstr 91",
    "sg:city":"Tilburg",
    "sg:orig_category":"Geluidsinstallaties - Verhuur",
    "sg:phone":"+31 13 543 7779",
    "sg:postcode":"5025 MG",
    "sg:province":"Noord-Brabant",
    "wof:name":"Jl Productions",
    "wof:placetype":"venue"
},
  "geometry": {"coordinates":[5.071465,51.55397],"type":"Point"}
}