{
  "type": "Feature",
  "properties": {
    "addr:full":"Deldenerstr 70 Hengelo Ov Overijssel 7551 AH",
    "addr:housenumber":"70",
    "addr:postcode":"7551 ah",
    "addr:street":"Deldenerstr;Ov",
    "iso:country":"NL",
    "sg:address":"Deldenerstr 70",
    "sg:city":"Hengelo Ov",
    "sg:orig_category":"Modeontwerpen",
    "sg:phone":"+31 74 291 4828",
    "sg:postcode":"7551 AH",
    "sg:province":"Overijssel",
    "wof:name":"Mulder, M",
    "wof:placetype":"venue"
},
  "geometry": {"coordinates":[6.785349,52.266312],"type":"Point"}
}