{
  "type": "Feature",
  "properties": {
    "addr:full":"Molenhornstraat 54 Winschoten Groningen 9671 KV",
    "addr:housenumber":"54",
    "addr:postcode":"9671 kv",
    "addr:street":"Molenhornstraat",
    "iso:country":"NL",
    "sg:address":"Molenhornstraat 54",
    "sg:city":"Winschoten",
    "sg:orig_category":"Bloemen And Planten",
    "sg:phone":"+31 597 415 589",
    "sg:postcode":"9671 KV",
    "sg:province":"Groningen",
    "wof:name":"Tuinmarkt Kloosterhuis",
    "wof:placetype":"venue"
},
  "geometry": {"coordinates":[7.027634,53.143284],"type":"Point"}
}