{
  "type": "Feature",
  "properties": {
    "addr:full":"Poelestr 9 Groningen Groningen 9711 PG",
    "addr:housenumber":"9",
    "addr:postcode":"9711 pg",
    "addr:street":"Poelestr",
    "iso:country":"NL",
    "sg:address":"Poelestr 9",
    "sg:city":"Groningen",
    "sg:orig_category":"Banket",
    "sg:phone":"+31 50 314 8942",
    "sg:postcode":"9711 PG",
    "sg:province":"Groningen",
    "sg:website":"http://www.multivlaai.nl",
    "wof:name":"Multi-Vlaai",
    "wof:placetype":"venue"
},
  "geometry": {"coordinates":[6.57047,53.218349],"type":"Point"}
}