{
  "type": "Feature",
  "properties": {
    "addr:full":"Guldenwaard 133 Rotterdam Zuid-Holland 3078 AJ",
    "addr:housenumber":"133",
    "addr:postcode":"3078 aj",
    "addr:street":"Guldenwaard",
    "iso:country":"NL",
    "sg:address":"Guldenwaard 133",
    "sg:city":"Rotterdam",
    "sg:orig_category":"Chemische Producten Gh",
    "sg:phone":"+31 10 413 6310",
    "sg:postcode":"3078 AJ",
    "sg:province":"Zuid-Holland",
    "wof:name":"Kronos Bv",
    "wof:placetype":"venue"
},
  "geometry": {"coordinates":[4.547441,51.886986],"type":"Point"}
}