{
  "type": "Feature",
  "properties": {
    "addr:full":"Zeven Eikenlaan 23 Veghel North Brabant 5461 EC",
    "addr:housenumber":"23",
    "addr:postcode":"5461 ec",
    "addr:street":"Zeven Eikenlaan",
    "iso:country":"NL",
    "sg:address":"Zeven Eikenlaan 23",
    "sg:city":"Veghel",
    "sg:orig_category":"Vertaal- And Tolkenbureaus",
    "sg:phone":"+31 413 350 839",
    "sg:postcode":"5461 EC",
    "sg:province":"North Brabant",
    "wof:name":"Mouwen Vertaalhuis",
    "wof:placetype":"venue"
},
  "geometry": {"coordinates":[5.549263,51.6185],"type":"Point"}
}