{
  "type": "Feature",
  "properties": {
    "addr:full":"Middelwg 54 Leersum Utrecht 3956 TN",
    "addr:housenumber":"54",
    "addr:postcode":"3956",
    "addr:street":"Middelwg",
    "iso:country":"NL",
    "sg:address":"Middelwg 54",
    "sg:city":"Leersum",
    "sg:orig_category":"Grondboringen En Bronbemalingen",
    "sg:phone":"+31 343 452 842",
    "sg:postcode":"3956 TN",
    "sg:province":"Utrecht",
    "wof:name":"Schuppen Bv, H Van",
    "wof:placetype":"venue"
},
  "geometry": {"coordinates":[5.41888,52.012756],"type":"Point"}
}