{
  "type": "Feature",
  "properties": {
    "addr:full":"Landjuweel 3 Veenendaal Utrecht 3905 PE",
    "addr:housenumber":"3",
    "addr:postcode":"3905 pe",
    "addr:street":"Landjuweel",
    "iso:country":"NL",
    "sg:address":"Landjuweel 3",
    "sg:city":"Veenendaal",
    "sg:orig_category":"Verzekeringen",
    "sg:phone":"+31 318 509 910",
    "sg:postcode":"3905 PE",
    "sg:province":"Utrecht",
    "wof:name":"D.T. De Vries",
    "wof:placetype":"venue"
},
  "geometry": {"coordinates":[5.551206,52.040127],"type":"Point"}
}