{
  "type": "Feature",
  "properties": {
    "addr:full":"Geererf 8 Breda Noord-Brabant 4824 GL",
    "addr:housenumber":"8",
    "addr:postcode":"4824 gl",
    "addr:street":"Geererf",
    "iso:country":"NL",
    "sg:address":"Geererf 8",
    "sg:city":"Breda",
    "sg:orig_category":"Psychologen",
    "sg:phone":"+31 76 541 0214",
    "sg:postcode":"4824 GL",
    "sg:province":"Noord-Brabant",
    "wof:name":"Post, Drs A",
    "wof:placetype":"venue"
},
  "geometry": {"coordinates":[4.750681,51.613392],"type":"Point"}
}