{
  "type": "Feature",
  "properties": {
    "addr:full":"Hoofdstraat 44 Hillegom Zuid-Holland 2181 ED",
    "addr:housenumber":"44",
    "addr:postcode":"2181 ed",
    "addr:street":"Hoofdstraat",
    "iso:country":"NL",
    "sg:address":"Hoofdstraat 44",
    "sg:city":"Hillegom",
    "sg:classifiers":[
        {
            "category":"Retail",
            "subcategory":"Photofinishing",
            "type":"Services"
        }
    ],
    "sg:phone":"+31 252 515 669",
    "sg:postcode":"2181 ED",
    "sg:province":"Zuid-Holland",
    "sg:tags":[
        "foto",
        "film"
    ],
    "wof:name":"Foto De Geus",
    "wof:placetype":"venue"
},
  "geometry": {"coordinates":[4.580046,52.29414],"type":"Point"}
}