{
  "type": "Feature",
  "properties": {
    "iso:country":"NL",
    "sg:address":"Bentheimergraven 35",
    "sg:city":"Oldenzaal",
    "sg:orig_category":"Sportterreinen And Installaties Behalve Sportcentra",
    "sg:phone":"+31 541 513 656",
    "sg:postcode":"7577 DA",
    "sg:province":"Overijssel",
    "wof:name":"Zwemschool Siers",
    "wof:placetype":"venue"
},
  "geometry": {"coordinates":[6.923485,52.320358],"type":"Point"}
}