{
  "type": "Feature",
  "properties": {
    "addr:full":"Hondsruglaan 87 Eindhoven Noord-Brabant 5628 DB",
    "addr:housenumber":"87",
    "addr:postcode":"5628 db",
    "addr:street":"Hondsruglaan",
    "iso:country":"NL",
    "sg:address":"Hondsruglaan 87",
    "sg:city":"Eindhoven",
    "sg:orig_category":"Kantoorapparatuur Gh",
    "sg:phone":"+31 40 241 1133",
    "sg:postcode":"5628 DB",
    "sg:province":"Noord-Brabant",
    "wof:name":"Kantoorinstallatiebedrijf Van Den Broek",
    "wof:placetype":"venue"
},
  "geometry": {"coordinates":[5.4586791992,51.4830207825],"type":"Point"}
}