{
  "type": "Feature",
  "properties": {
    "addr:full":"A V Leeuwenhoekwg 28 Alphen Aan Den Ryn South Holland 2408 AM",
    "addr:housenumber":"28",
    "addr:postcode":"2408",
    "addr:street":"A;Leeuwenhoekwg;Aan Den Ryn",
    "iso:country":"NL",
    "sg:address":"A V Leeuwenhoekwg 28",
    "sg:city":"Alphen Aan Den Ryn",
    "sg:orig_category":"Keukens",
    "sg:phone":"+31 172 460 160",
    "sg:postcode":"2408 AM",
    "sg:province":"South Holland",
    "wof:name":"Erbi Bv",
    "wof:placetype":"venue"
},
  "geometry": {"coordinates":[4.65273,52.120281],"type":"Point"}
}