{
  "type": "Feature",
  "properties": {
    "addr:full":"J Rebelstr 21 Amsterdam New York 1069 CA",
    "addr:housenumber":"21;1069",
    "iso:country":"NL",
    "sg:address":"J Rebelstr 21",
    "sg:city":"Amsterdam",
    "sg:orig_category":"Zalenverhuur",
    "sg:phone":"+31 20 619 5055",
    "sg:postcode":"1069 CA",
    "sg:province":"New York",
    "wof:name":"Salon Osdorp",
    "wof:placetype":"venue"
},
  "geometry": {"coordinates":[-74.24232499999999,42.979591],"type":"Point"}
}