{
  "type": "Feature",
  "properties": {
    "iso:country":"NL",
    "sg:address":"Ereprijshof 33",
    "sg:city":"Leusden",
    "sg:orig_category":"Fotoreportages",
    "sg:phone":"+31 33 432 1652",
    "sg:postcode":"3831 BB",
    "sg:province":"Utrecht",
    "wof:name":"Jan Evert Meijer, Fotografie",
    "wof:placetype":"venue"
},
  "geometry": {"coordinates":[5.445017,52.13726],"type":"Point"}
}