{
  "type": "Feature",
  "properties": {
    "addr:full":"Veldstr 12 Groningen Groningen 9717 LP",
    "addr:housenumber":"12",
    "addr:postcode":"9717 lp",
    "addr:street":"Veldstr",
    "iso:country":"NL",
    "sg:address":"Veldstr 12",
    "sg:city":"Groningen",
    "sg:orig_category":"Accountants - Administratie- Consulenten En -Kantoren",
    "sg:phone":"+31 50 577 3558",
    "sg:postcode":"9717 LP",
    "sg:province":"Groningen",
    "wof:name":"Sing Pacak Bv",
    "wof:placetype":"venue"
},
  "geometry": {"coordinates":[6.551722,53.226051],"type":"Point"}
}