{
  "type": "Feature",
  "properties": {
    "addr:full":"Steenbakkersstr 36 Krimpen Ad Yssel Zuid-Holland 2922 XL",
    "addr:housenumber":"36",
    "addr:postcode":"2922 xl",
    "addr:street":"Steenbakkersstr",
    "iso:country":"NL",
    "sg:address":"Steenbakkersstr 36",
    "sg:city":"Krimpen Ad Yssel",
    "sg:classifiers":[
        {
            "category":"Retail",
            "subcategory":"Storage",
            "type":"Services"
        }
    ],
    "sg:phone":"+31 180 512 066",
    "sg:postcode":"2922 XL",
    "sg:province":"Zuid-Holland",
    "sg:tags":[
        "op-",
        "en",
        "overslagbedrijven"
    ],
    "wof:name":"Heuvelman Bv, M & M",
    "wof:placetype":"venue"
},
  "geometry": {"coordinates":[4.583452,51.915825],"type":"Point"}
}