{
  "type": "Feature",
  "properties": {
    "addr:full":"Gen Kockstraat 2A Tilburg Noord-Brabant 5025 BB",
    "addr:housenumber":"2a",
    "addr:postcode":"5025 bb",
    "addr:street":"Gen Kockstraat",
    "iso:country":"NL",
    "sg:address":"Gen Kockstraat 2A",
    "sg:city":"Tilburg",
    "sg:orig_category":"Overheidsdiensten",
    "sg:phone":"+31 13 533 2894",
    "sg:postcode":"5025 BB",
    "sg:province":"Noord-Brabant",
    "wof:name":"Soekmekaar",
    "wof:placetype":"venue"
},
  "geometry": {"coordinates":[5.0760560036,51.5462532043],"type":"Point"}
}