{
  "type": "Feature",
  "properties": {
    "addr:full":"Hofwg 15 Warnsveld Gelderland 7231 BG",
    "addr:housenumber":"15",
    "addr:postcode":"7231",
    "addr:street":"Hofwg;Gelderland",
    "iso:country":"NL",
    "sg:address":"Hofwg 15",
    "sg:city":"Warnsveld",
    "sg:orig_category":"Loopbaanbegeleiding",
    "sg:phone":"+31 575 571 539",
    "sg:postcode":"7231 BG",
    "sg:province":"Gelderland",
    "wof:name":"Maria De Goeij",
    "wof:placetype":"venue"
},
  "geometry": {"coordinates":[6.224009,52.141899],"type":"Point"}
}