{
  "type": "Feature",
  "properties": {
    "addr:full":"Klapstraat 17 Westervoort Gelderland 6931 CA",
    "addr:housenumber":"17",
    "addr:postcode":"6931 ca",
    "addr:street":"Klapstraat;Gelderland",
    "iso:country":"NL",
    "sg:address":"Klapstraat 17",
    "sg:city":"Westervoort",
    "sg:orig_category":"Meubelzaken, Woning- And Keukeninrichting",
    "sg:phone":"+31 26 311 5882",
    "sg:postcode":"6931 CA",
    "sg:province":"Gelderland",
    "wof:name":"Dolfijn Slaapwinkels",
    "wof:placetype":"venue"
},
  "geometry": {"coordinates":[5.960234,51.962456],"type":"Point"}
}