{
  "type": "Feature",
  "properties": {
    "iso:country":"NL",
    "sg:address":"Molenbeekstraat 11",
    "sg:city":"'S Hertogenbosch",
    "sg:orig_category":"Chemische Producten Gh",
    "sg:phone":"+31 73 612 0720",
    "sg:postcode":"5215 BH",
    "sg:province":"Noord-Brabant",
    "wof:name":"H. Doomernik",
    "wof:placetype":"venue"
},
  "geometry": {"coordinates":[5.332764,51.687496],"type":"Point"}
}