{
  "type": "Feature",
  "properties": {
    "addr:full":"Molenbeekstraat 11 'S Hertogenbosch Noord-Brabant 5215 BH",
    "addr:housenumber":"11",
    "addr:postcode":"5215 bh",
    "addr:street":"Molenbeekstraat;' S",
    "iso:country":"NL",
    "sg:address":"Molenbeekstraat 11",
    "sg:city":"'S Hertogenbosch",
    "sg:orig_category":"Chemische Producten Gh",
    "sg:phone":"+31 73 612 0720",
    "sg:postcode":"5215 BH",
    "sg:province":"Noord-Brabant",
    "wof:name":"H. Doomernik",
    "wof:placetype":"venue"
},
  "geometry": {"coordinates":[5.332764,51.687496],"type":"Point"}
}