{
  "type": "Feature",
  "properties": {
    "addr:full":"Noordendk 189 Dordrecht Zuid-Holland 3311 RN",
    "addr:housenumber":"189",
    "addr:postcode":"3311 rn",
    "iso:country":"NL",
    "sg:address":"Noordendk 189",
    "sg:city":"Dordrecht",
    "sg:orig_category":"Administratie- En Boekhoudkantoren",
    "sg:phone":"+31 78 648 1550",
    "sg:postcode":"3311 RN",
    "sg:province":"Zuid-Holland",
    "wof:name":"Onp Verstegen Bv",
    "wof:placetype":"venue"
},
  "geometry": {"coordinates":[4.682085,51.814106],"type":"Point"}
}