{
  "type": "Feature",
  "properties": {
    "addr:full":"Ereprysln 69 Scherpenzeel Gld Utrecht 3925 RX",
    "addr:housenumber":"69",
    "addr:postcode":"3925 rx",
    "addr:street":"Ereprysln;Gld",
    "iso:country":"NL",
    "sg:address":"Ereprysln 69",
    "sg:city":"Scherpenzeel Gld",
    "sg:orig_category":"On- Offshore",
    "sg:phone":"+31 33 277 2594",
    "sg:postcode":"3925 RX",
    "sg:province":"Utrecht",
    "wof:name":"Koehein, T C",
    "wof:placetype":"venue"
},
  "geometry": {"coordinates":[5.485805,52.079689],"type":"Point"}
}