{
  "type": "Feature",
  "properties": {
    "iso:country":"NL",
    "sg:address":"Plantage 199",
    "sg:city":"Beverwyk",
    "sg:orig_category":"Koeriersdiensten",
    "sg:phone":"+31 251 228 875",
    "sg:postcode":"1944 LX",
    "sg:province":"Noord-Holland",
    "wof:name":"Jr Express",
    "wof:placetype":"venue"
},
  "geometry": {"coordinates":[4.650015,52.490105],"type":"Point"}
}