{
  "type": "Feature",
  "properties": {
    "addr:full":"Geldropsewg 48-54 Eindhoven North Brabant 5611 SJ",
    "addr:housenumber":"48-54",
    "addr:postcode":"5611",
    "iso:country":"NL",
    "sg:address":"Geldropsewg 48-54",
    "sg:city":"Eindhoven",
    "sg:orig_category":"Meubelen",
    "sg:phone":"+31 40 211 7588",
    "sg:postcode":"5611 SJ",
    "sg:province":"North Brabant",
    "sg:website":"http://www.elx.nl",
    "wof:name":"Elx Meubel",
    "wof:placetype":"venue"
},
  "geometry": {"coordinates":[5.488078,51.433743],"type":"Point"}
}