{
  "type": "Feature",
  "properties": {
    "addr:full":"Dahliastr 39 Bergen Op Zoom North Brabant 4613 DS",
    "addr:housenumber":"39",
    "addr:postcode":"4613 ds",
    "addr:street":"Dahliastr",
    "iso:country":"NL",
    "sg:address":"Dahliastr 39",
    "sg:city":"Bergen Op Zoom",
    "sg:orig_category":"Psychologen",
    "sg:phone":"+31 164 259 427",
    "sg:postcode":"4613 DS",
    "sg:province":"North Brabant",
    "wof:name":"Luijpen, Drs M",
    "wof:placetype":"venue"
},
  "geometry": {"coordinates":[4.281963,51.505192],"type":"Point"}
}