{
  "type": "Feature",
  "properties": {
    "addr:full":"Krekenburg 36 Montfoort Utrecht 3417 MH",
    "addr:housenumber":"36",
    "addr:postcode":"3417 mh",
    "addr:street":"Krekenburg",
    "iso:country":"NL",
    "sg:address":"Krekenburg 36",
    "sg:city":"Montfoort",
    "sg:orig_category":"Jachten - Schilderwerken En Onderhoud",
    "sg:phone":"+31 348 418 505",
    "sg:postcode":"3417 MH",
    "sg:province":"Utrecht",
    "sg:website":"http://www.evon.nl",
    "wof:name":"Evon Bv",
    "wof:placetype":"venue"
},
  "geometry": {"coordinates":[4.929373,52.032227],"type":"Point"}
}