{
  "type": "Feature",
  "properties": {
    "addr:full":"De Kloet 6 Bladel Noord-Brabant 5531 MA",
    "addr:housenumber":"6",
    "addr:postcode":"5531 ma",
    "addr:street":"De Kloet",
    "iso:country":"NL",
    "sg:address":"De Kloet 6",
    "sg:city":"Bladel",
    "sg:orig_category":"Meubelmakerijen",
    "sg:phone":"+31 497 385 135",
    "sg:postcode":"5531 MA",
    "sg:province":"Noord-Brabant",
    "wof:name":"Maatmeubel",
    "wof:placetype":"venue"
},
  "geometry": {"coordinates":[5.20732,51.358311],"type":"Point"}
}