{
  "type": "Feature",
  "properties": {
    "iso:country":"NL",
    "sg:address":"Ceintuurbaan 250-252",
    "sg:city":"Amsterdam",
    "sg:orig_category":"Banden",
    "sg:phone":"+31 20 671 2161",
    "sg:postcode":"1072 GH",
    "sg:province":"North Holland",
    "sg:website":"http://www.kwik-fit.nl",
    "wof:name":"Kwik-Fit",
    "wof:placetype":"venue"
},
  "geometry": {"coordinates":[4.889897,52.352413],"type":"Point"}
}