{
  "type": "Feature",
  "properties": {
    "iso:country":"NL",
    "sg:address":"Postbus 65",
    "sg:city":"Bruinisse",
    "sg:orig_category":"Jachthavens - Jachtwerven",
    "sg:phone":"+31 111 481 485",
    "sg:postcode":"4310 AB",
    "sg:province":"Zeeland",
    "wof:name":"Bruinisse Bv",
    "wof:placetype":"venue"
},
  "geometry": {"coordinates":[4.0953,51.663269],"type":"Point"}
}