{
  "type": "Feature",
  "properties": {
    "addr:full":"Randwijksingel 6 Malden Gelderland 6581 CE",
    "addr:housenumber":"6",
    "addr:postcode":"6581 ce",
    "addr:street":"Randwijksingel;Gelderland",
    "iso:country":"NL",
    "sg:address":"Randwijksingel 6",
    "sg:city":"Malden",
    "sg:orig_category":"Boekhouders",
    "sg:phone":"+31 24 358 2213",
    "sg:postcode":"6581 CE",
    "sg:province":"Gelderland",
    "wof:name":"Adm.-En Belastingadviesburo Bisseling Bv",
    "wof:placetype":"venue"
},
  "geometry": {"coordinates":[5.860106,51.783443],"type":"Point"}
}