{
  "type": "Feature",
  "properties": {
    "iso:country":"NL",
    "sg:address":"Breedspoor 176",
    "sg:city":"Capelle A/D Ijssel",
    "sg:orig_category":"Goederenvervoer Over De Weg",
    "sg:phone":"+31 10 451 7296",
    "sg:postcode":"2908 AA",
    "sg:province":"South Holland",
    "wof:name":"Ron Van Son Transport",
    "wof:placetype":"venue"
},
  "geometry": {"coordinates":[4.585905,51.957695],"type":"Point"}
}