{
  "type": "Feature",
  "properties": {
    "addr:full":"Nobelstraat 153 Utrecht Utrecht 3512 EM",
    "addr:housenumber":"153",
    "addr:postcode":"3512 em",
    "addr:street":"Nobelstraat",
    "iso:country":"NL",
    "sg:address":"Nobelstraat 153",
    "sg:city":"Utrecht",
    "sg:orig_category":"Visspeciaalzaken",
    "sg:phone":"+31 30 231 1007",
    "sg:postcode":"3512 EM",
    "sg:province":"Utrecht",
    "wof:name":"Vishandel P J Oostveen Bv",
    "wof:placetype":"venue"
},
  "geometry": {"coordinates":[5.124713,52.092964],"type":"Point"}
}