{
  "type": "Feature",
  "properties": {
    "addr:full":"Valckstr 7 Zutphen Gelderland 7203 GB",
    "addr:housenumber":"7",
    "addr:postcode":"7203 gb",
    "addr:street":"Valckstr;Gelderland",
    "iso:country":"NL",
    "sg:address":"Valckstr 7",
    "sg:city":"Zutphen",
    "sg:orig_category":"Modeontwerpen",
    "sg:phone":"+31 575 544 236",
    "sg:postcode":"7203 GB",
    "sg:province":"Gelderland",
    "wof:name":"Mals Design",
    "wof:placetype":"venue"
},
  "geometry": {"coordinates":[6.212771,52.148003],"type":"Point"}
}