{
  "type": "Feature",
  "properties": {
    "iso:country":"NL",
    "sg:address":"Aa Of Weerijs 13",
    "sg:city":"Tilburg",
    "sg:orig_category":"Verzekeringen",
    "sg:phone":"+31 13 467 1460",
    "sg:postcode":"5032 BA",
    "sg:province":"Noord-Brabant",
    "wof:name":"Assurantiekantoor Doorakkers-Van Drunen",
    "wof:placetype":"venue"
},
  "geometry": {"coordinates":[5.040181,51.546658],"type":"Point"}
}