{
  "type": "Feature",
  "properties": {
    "addr:full":"Houtlaan 61 Drachten Friesland 9203 AP",
    "addr:housenumber":"61",
    "addr:postcode":"9203 ap",
    "addr:street":"Houtlaan",
    "iso:country":"NL",
    "sg:address":"Houtlaan 61",
    "sg:city":"Drachten",
    "sg:orig_category":"Boekhandels",
    "sg:phone":"+31 512 541 737",
    "sg:postcode":"9203 AP",
    "sg:province":"Friesland",
    "wof:name":"Evangelische Boekwinkel",
    "wof:placetype":"venue"
},
  "geometry": {"coordinates":[6.103289,53.109108],"type":"Point"}
}