{
  "type": "Feature",
  "properties": {
    "addr:full":"Noordeinde 22B Leiden Zuid-Holland 2311 CD",
    "addr:housenumber":"22b",
    "addr:postcode":"2311 cd",
    "addr:street":"Noordeinde",
    "iso:country":"NL",
    "sg:address":"Noordeinde 22B",
    "sg:city":"Leiden",
    "sg:orig_category":"Kunsthandel",
    "sg:phone":"+31 6 22667814",
    "sg:postcode":"2311 CD",
    "sg:province":"Zuid-Holland",
    "wof:name":"Dukel, R C T",
    "wof:placetype":"venue"
},
  "geometry": {"coordinates":[4.483103,52.160221],"type":"Point"}
}