{
  "type": "Feature",
  "properties": {
    "addr:full":"Zuringstraat 5 Rotterdam Zuid-Holland 3053 JT",
    "addr:housenumber":"5",
    "addr:postcode":"3053 jt",
    "addr:street":"Zuringstraat",
    "iso:country":"NL",
    "sg:address":"Zuringstraat 5",
    "sg:city":"Rotterdam",
    "sg:orig_category":"Werving And Selectie Van Tijdelijk Personeel And Uitzendkantoren",
    "sg:phone":"+31 10 285 4554",
    "sg:postcode":"3053 JT",
    "sg:province":"Zuid-Holland",
    "wof:name":"Horeca Bemiddelings Bureau",
    "wof:placetype":"venue"
},
  "geometry": {"coordinates":[4.4655489922,51.9674415588],"type":"Point"}
}