{
  "type": "Feature",
  "properties": {
    "addr:full":"Nieuwe Laaklaan 6 Putten Gelderland 3881 MH",
    "addr:housenumber":"6",
    "addr:postcode":"3881 mh",
    "addr:street":"Nieuwe Laaklaan;Gelderland",
    "iso:country":"NL",
    "sg:address":"Nieuwe Laaklaan 6",
    "sg:city":"Putten",
    "sg:orig_category":"Paramedische Behandelingen",
    "sg:phone":"+31 341 354 860",
    "sg:postcode":"3881 MH",
    "sg:province":"Gelderland",
    "wof:name":"Dr. J. Katus",
    "wof:placetype":"venue"
},
  "geometry": {"coordinates":[5.618569,52.270863],"type":"Point"}
}