{
  "type": "Feature",
  "properties": {
    "addr:full":"Paardekraalstr 3 Amsterdam North Holland 1092 JA",
    "addr:housenumber":"3",
    "addr:postcode":"1092 ja",
    "addr:street":"Paardekraalstr",
    "iso:country":"NL",
    "sg:address":"Paardekraalstr 3",
    "sg:city":"Amsterdam",
    "sg:orig_category":"Vertaalbureaus",
    "sg:phone":"+31 20 463 8412",
    "sg:postcode":"1092 JA",
    "sg:province":"North Holland",
    "wof:name":"Jem",
    "wof:placetype":"venue"
},
  "geometry": {"coordinates":[4.924709,52.355453],"type":"Point"}
}