{
  "type": "Feature",
  "properties": {
    "iso:country":"NL",
    "sg:address":"Gearen 1",
    "sg:city":"Nij Beets",
    "sg:orig_category":"Goederenvervoer Over De Weg",
    "sg:phone":"+31 512 461 538",
    "sg:postcode":"9245 VE",
    "sg:province":"Friesland",
    "wof:name":"Transportbedrijf De Visser",
    "wof:placetype":"venue"
},
  "geometry": {"coordinates":[-85.39325714109999,30.5372390747],"type":"Point"}
}