{
  "type": "Feature",
  "properties": {
    "addr:full":"N Snydershof 2 Wyk Aan Zee Noord-Holland 1949 BR",
    "addr:housenumber":"2",
    "addr:postcode":"zee;1949 br",
    "addr:street":"N Snydershof",
    "iso:country":"NL",
    "sg:address":"N Snydershof 2",
    "sg:city":"Wyk Aan Zee",
    "sg:orig_category":"Adviesbureaus",
    "sg:phone":"+31 251 375 437",
    "sg:postcode":"1949 BR",
    "sg:province":"Noord-Holland",
    "wof:name":"Scholten, S",
    "wof:placetype":"venue"
},
  "geometry": {"coordinates":[4.594696,52.491993],"type":"Point"}
}