{
  "type": "Feature",
  "properties": {
    "addr:full":"Koloniewg O 1 Vinkenbuurt Overijssel 7739 PX",
    "addr:housenumber":"1",
    "addr:postcode":"7739 px",
    "iso:country":"NL",
    "sg:address":"Koloniewg O 1",
    "sg:city":"Vinkenbuurt",
    "sg:orig_category":"Grondwerken",
    "sg:phone":"+31 523 657 216",
    "sg:postcode":"7739 PX",
    "sg:province":"Overijssel",
    "wof:name":"Knol",
    "wof:placetype":"venue"
},
  "geometry": {"coordinates":[6.407299,52.582294],"type":"Point"}
}