{
  "type": "Feature",
  "properties": {
    "iso:country":"NL",
    "sg:address":"Atoomwg 12",
    "sg:city":"Utrecht",
    "sg:orig_category":"Open Haarden",
    "sg:phone":"+31 30 241 0007",
    "sg:postcode":"3542 AB",
    "sg:province":"Utrecht",
    "sg:website":"http://www.reka.nl",
    "wof:name":"Reka",
    "wof:placetype":"venue"
},
  "geometry": {"coordinates":[5.068413,52.1022],"type":"Point"}
}