{
  "type": "Feature",
  "properties": {
    "addr:full":"Stationsweg 63 Zwolle (Wezep) NL.08 8011  A",
    "addr:housenumber":"63;8011 a",
    "addr:postcode":"nl.08",
    "addr:street":"Stationsweg",
    "iso:country":"NL",
    "sg:address":"Stationsweg 63",
    "sg:city":"Zwolle (Wezep)",
    "sg:orig_category":"Meubelzaken, Woning- And Keukeninrichting",
    "sg:phone":"+31 38 376 9608",
    "sg:postcode":"8011  A",
    "sg:province":"NL.08",
    "wof:name":"Spakman Crown Interstyle",
    "wof:placetype":"venue"
},
  "geometry": {"coordinates":[6.088738,52.512566],"type":"Point"}
}