{
  "type": "Feature",
  "properties": {
    "addr:full":"Vrijbuiterstraat 4 Sneek Provincie Friesland 8605 AX",
    "addr:housenumber":"4",
    "addr:postcode":"8605 ax",
    "addr:street":"Vrijbuiterstraat;Provincie Friesland",
    "iso:country":"NL",
    "sg:address":"Vrijbuiterstraat 4",
    "sg:city":"Sneek",
    "sg:orig_category":"Verhuur Catering-, Feest- En Evenementbenodigdheden",
    "sg:phone":"+31 515 417 574",
    "sg:postcode":"8605 AX",
    "sg:province":"Provincie Friesland",
    "wof:name":"Reen",
    "wof:placetype":"venue"
},
  "geometry": {"coordinates":[5.672004,53.032314],"type":"Point"}
}