{
  "type": "Feature",
  "properties": {
    "iso:country":"NL",
    "sg:address":"De Schacht 11",
    "sg:city":"Dongen",
    "sg:orig_category":"Projectontwikkeling",
    "sg:phone":"+31 162 377 300",
    "sg:postcode":"5107 RD",
    "sg:province":"North Brabant",
    "wof:name":"Dungha Bv",
    "wof:placetype":"venue"
},
  "geometry": {"coordinates":[4.928498,51.614986],"type":"Point"}
}