{
  "type": "Feature",
  "properties": {
    "iso:country":"NL",
    "sg:address":"Westwagenstr 113",
    "sg:city":"Gorinchem",
    "sg:orig_category":"Juweliers",
    "sg:phone":"+31 183 630 202",
    "sg:postcode":"4201 HG",
    "sg:province":"Zuid-Holland",
    "wof:name":"Keuvelaar, A",
    "wof:placetype":"venue"
},
  "geometry": {"coordinates":[4.968945,51.830547],"type":"Point"}
}