{
  "type": "Feature",
  "properties": {
    "addr:full":"Wilbrinkbos 33 Hoofddorp Noord-Holland 2134 HN",
    "addr:housenumber":"33",
    "addr:postcode":"2134 hn",
    "addr:street":"Wilbrinkbos",
    "iso:country":"NL",
    "sg:address":"Wilbrinkbos 33",
    "sg:city":"Hoofddorp",
    "sg:orig_category":"Webdesign Bureaus",
    "sg:phone":"+31 23 565 8518",
    "sg:postcode":"2134 HN",
    "sg:province":"Noord-Holland",
    "sg:website":"http://www.webexcellence.nl",
    "wof:name":"Web Excellence",
    "wof:placetype":"venue"
},
  "geometry": {"coordinates":[4.6533041,52.3155822754],"type":"Point"}
}