{
  "type": "Feature",
  "properties": {
    "addr:full":"Westerbinnensngl 7A Groningen Groningen 9718 BR",
    "addr:housenumber":"7a",
    "addr:postcode":"9718 br",
    "addr:street":"Westerbinnensngl",
    "iso:country":"NL",
    "sg:address":"Westerbinnensngl 7A",
    "sg:city":"Groningen",
    "sg:orig_category":"Watersportartikelen",
    "sg:phone":"+31 50 311 0845",
    "sg:postcode":"9718 BR",
    "sg:province":"Groningen",
    "wof:name":"Fox",
    "wof:placetype":"venue"
},
  "geometry": {"coordinates":[6.5583209991,53.2168960571],"type":"Point"}
}