{
  "type": "Feature",
  "properties": {
    "iso:country":"NL",
    "sg:address":"Fagotlaan 1",
    "sg:city":"Nieuwegein",
    "sg:orig_category":"Bloemen And Planten",
    "sg:phone":"+31 30 604 5645",
    "sg:postcode":"3438 CE",
    "sg:province":"Utrecht",
    "wof:name":"Gerrit Emo",
    "wof:placetype":"venue"
},
  "geometry": {"coordinates":[5.083096,52.042248],"type":"Point"}
}