{
  "type": "Feature",
  "properties": {
    "addr:full":"Fagotlaan 1 Nieuwegein Utrecht 3438 CE",
    "addr:housenumber":"1",
    "addr:postcode":"3438 ce",
    "addr:street":"Fagotlaan",
    "iso:country":"NL",
    "sg:address":"Fagotlaan 1",
    "sg:city":"Nieuwegein",
    "sg:orig_category":"Bloemen And Planten",
    "sg:phone":"+31 30 604 5645",
    "sg:postcode":"3438 CE",
    "sg:province":"Utrecht",
    "wof:name":"Gerrit Emo",
    "wof:placetype":"venue"
},
  "geometry": {"coordinates":[5.083096,52.042248],"type":"Point"}
}