{
  "type": "Feature",
  "properties": {
    "addr:full":"Oosterdwarsreed 4 Opende Groningen 9865 AP",
    "addr:housenumber":"4",
    "addr:postcode":"9865 ap",
    "addr:street":"Oosterdwarsreed",
    "iso:country":"NL",
    "sg:address":"Oosterdwarsreed 4",
    "sg:city":"Opende",
    "sg:orig_category":"Bedrijfsmechanisatie En -Automatisering",
    "sg:phone":"+31 594 659 385",
    "sg:postcode":"9865 AP",
    "sg:province":"Groningen",
    "wof:name":"Hybrid-Systems",
    "wof:placetype":"venue"
},
  "geometry": {"coordinates":[6.19374,53.18185],"type":"Point"}
}