{
  "type": "Feature",
  "properties": {
    "addr:full":"Stationsstr 33 Maastricht Limburg 6221 BN",
    "addr:housenumber":"33",
    "addr:postcode":"6221 bn",
    "addr:street":"Stationsstr",
    "iso:country":"NL",
    "sg:address":"Stationsstr 33",
    "sg:city":"Maastricht",
    "sg:orig_category":"Hulpverlening Sociaal",
    "sg:phone":"+31 43 350 3570",
    "sg:postcode":"6221 BN",
    "sg:province":"Limburg",
    "wof:name":"Adicon Bv",
    "wof:placetype":"venue"
},
  "geometry": {"coordinates":[5.70237,50.8494],"type":"Point"}
}