{
  "type": "Feature",
  "properties": {
    "addr:full":"Koekoeksln 93 Schiedam Zuid-Holland 3121 XJ",
    "addr:housenumber":"93",
    "addr:postcode":"3121 xj",
    "addr:street":"Koekoeksln",
    "iso:country":"NL",
    "sg:address":"Koekoeksln 93",
    "sg:city":"Schiedam",
    "sg:orig_category":"Verzekeringen - Verzekeringskantoren",
    "sg:phone":"+31 10 470 5700",
    "sg:postcode":"3121 XJ",
    "sg:province":"Zuid-Holland",
    "wof:name":"Meder, J",
    "wof:placetype":"venue"
},
  "geometry": {"coordinates":[4.38635,51.932911],"type":"Point"}
}