{
  "type": "Feature",
  "properties": {
    "addr:full":"Dantestraat 355 Rotterdam Zuid-Holland 3076 KM",
    "addr:housenumber":"355",
    "addr:postcode":"3076 km",
    "addr:street":"Dantestraat",
    "iso:country":"NL",
    "sg:address":"Dantestraat 355",
    "sg:city":"Rotterdam",
    "sg:orig_category":"Bibliotheken And Openbare Archieven",
    "sg:phone":"+31 10 432 0085",
    "sg:postcode":"3076 KM",
    "sg:province":"Zuid-Holland",
    "wof:name":"Centrale Bibliotheek",
    "wof:placetype":"venue"
},
  "geometry": {"coordinates":[4.525908,51.87479],"type":"Point"}
}