{
  "type": "Feature",
  "properties": {
    "addr:full":"Molenacker 61 Oisterwijk Noord-Brabant 5061 KS",
    "addr:housenumber":"61",
    "addr:postcode":"5061 ks",
    "addr:street":"Molenacker",
    "iso:country":"NL",
    "sg:address":"Molenacker 61",
    "sg:city":"Oisterwijk",
    "sg:orig_category":"Kantoorartikelen",
    "sg:phone":"+31 13 528 8363",
    "sg:postcode":"5061 KS",
    "sg:province":"Noord-Brabant",
    "wof:name":"Oisterwijk Supplies",
    "wof:placetype":"venue"
},
  "geometry": {"coordinates":[5.1789898872,51.5860443115],"type":"Point"}
}