{
  "type": "Feature",
  "properties": {
    "iso:country":"NL",
    "sg:address":"Sneevliethof 35",
    "sg:city":"'S Hertogenbosch",
    "sg:orig_category":"Schoenen",
    "sg:phone":"+31 73 641 8158",
    "sg:postcode":"5237 DK",
    "sg:province":"Noord-Brabant",
    "wof:name":"J.A. Eekels",
    "wof:placetype":"venue"
},
  "geometry": {"coordinates":[5.298452,51.729176],"type":"Point"}
}