{
  "type": "Feature",
  "properties": {
    "addr:full":"Coppeliaschouw 18 Zoetermeer South Holland 2726 JA",
    "addr:housenumber":"18",
    "addr:postcode":"2726 ja",
    "addr:street":"Coppeliaschouw",
    "iso:country":"NL",
    "sg:address":"Coppeliaschouw 18",
    "sg:city":"Zoetermeer",
    "sg:classifiers":[
        {
            "category":"Fast Food",
            "type":"Food & Drink"
        }
    ],
    "sg:phone":"+31 70 331 7200",
    "sg:postcode":"2726 JA",
    "sg:province":"South Holland",
    "sg:tags":[
        "afhaal",
        "restaurant"
    ],
    "wof:name":"De Parasol",
    "wof:placetype":"venue"
},
  "geometry": {"coordinates":[4.49136,52.065392],"type":"Point"}
}