{
  "type": "Feature",
  "properties": {
    "addr:full":"Symfoniestraat 204 Nijmegen Gelderland 6544 TN",
    "addr:housenumber":"204",
    "addr:postcode":"6544",
    "addr:street":"Symfoniestraat;Gelderland",
    "iso:country":"NL",
    "sg:address":"Symfoniestraat 204",
    "sg:city":"Nijmegen",
    "sg:orig_category":"Overheidsdiensten",
    "sg:phone":"+31 24 377 2460",
    "sg:postcode":"6544 TN",
    "sg:province":"Gelderland",
    "wof:name":"De Schalmei",
    "wof:placetype":"venue"
},
  "geometry": {"coordinates":[5.812338829,51.8312187195],"type":"Point"}
}