{
  "type": "Feature",
  "properties": {
    "addr:full":"Acaciastraat 141 'S Gravenhage Zuid-Holland 2565 JZ",
    "addr:housenumber":"141 '",
    "addr:postcode":"2565 jz",
    "addr:street":"Acaciastraat",
    "iso:country":"NL",
    "sg:address":"Acaciastraat 141",
    "sg:city":"'S Gravenhage",
    "sg:classifiers":[
        {
            "category":"Education",
            "subcategory":"Preschool",
            "type":"Public Place"
        }
    ],
    "sg:phone":"+31 70 345 0369",
    "sg:postcode":"2565 JZ",
    "sg:province":"Zuid-Holland",
    "sg:tags":[
        "kleuteronderwijs",
        "basis-"
    ],
    "wof:name":"Bavinckschool",
    "wof:placetype":"venue"
},
  "geometry": {"coordinates":[4.2705378532,52.0771942139],"type":"Point"}
}