{
  "type": "Feature",
  "properties": {
    "iso:country":"NL",
    "sg:address":"A Vd Zwaardhof 2",
    "sg:city":"Rysenhout",
    "sg:orig_category":"Adviesbureaus Bouwkunde",
    "sg:phone":"+31 297 328 162",
    "sg:postcode":"1435 DH",
    "sg:province":"Noord-Holland",
    "wof:name":"Vrie-Ad",
    "wof:placetype":"venue"
},
  "geometry": {"coordinates":[6.582975,46.72892],"type":"Point"}
}