{
  "type": "Feature",
  "properties": {
    "addr:full":"Zeemansstraat 39 Zaandam Noord-Holland 1506 CT",
    "addr:housenumber":"39",
    "addr:postcode":"1506 ct",
    "addr:street":"Zeemansstraat",
    "iso:country":"NL",
    "sg:address":"Zeemansstraat 39",
    "sg:city":"Zaandam",
    "sg:orig_category":"Visspeciaalzaken",
    "sg:phone":"+31 75 616 3202",
    "sg:postcode":"1506 CT",
    "sg:province":"Noord-Holland",
    "wof:name":"Fa D Broek En Zoon",
    "wof:placetype":"venue"
},
  "geometry": {"coordinates":[4.820783,52.440575],"type":"Point"}
}