{
  "type": "Feature",
  "properties": {
    "iso:country":"NL",
    "sg:address":"Langebuorren 8",
    "sg:city":"Stiens",
    "sg:classifiers":[
        {
            "category":"Retail",
            "subcategory":"Photofinishing",
            "type":"Services"
        }
    ],
    "sg:phone":"+31 58 257 4800",
    "sg:postcode":"9051 BG",
    "sg:province":"Friesland",
    "sg:tags":[
        "foto",
        "film"
    ],
    "wof:name":"Vof Foto Thomas Sijtsma",
    "wof:placetype":"venue"
},
  "geometry": {"coordinates":[5.757962,53.261379],"type":"Point"}
}