{
  "type": "Feature",
  "properties": {
    "addr:full":"Govert Flinckstraat 324 Amsterdam North Holland 1073 CJ",
    "addr:housenumber":"324",
    "addr:postcode":"1073 cj",
    "addr:street":"Govert Flinckstraat",
    "iso:country":"NL",
    "sg:address":"Govert Flinckstraat 324",
    "sg:city":"Amsterdam",
    "sg:classifiers":[
        {
            "category":"Food & Beverages",
            "subcategory":"Fruits & Vegetables",
            "type":"Retail Goods"
        }
    ],
    "sg:phone":"+31 20 662 7591",
    "sg:postcode":"1073 CJ",
    "sg:province":"North Holland",
    "sg:tags":[
        "groenten"
    ],
    "wof:name":"M De Meij",
    "wof:placetype":"venue"
},
  "geometry": {"coordinates":[4.899525,52.35648],"type":"Point"}
}