{
  "type": "Feature",
  "properties": {
    "addr:full":"Westendorpwg 2 Aalten Gelderland 7122 JT",
    "addr:housenumber":"2",
    "addr:postcode":"7122 jt",
    "addr:street":"Westendorpwg;Gelderland",
    "iso:country":"NL",
    "sg:address":"Westendorpwg 2",
    "sg:city":"Aalten",
    "sg:orig_category":"Beurzen",
    "sg:phone":"+31 543 466 294",
    "sg:postcode":"7122 JT",
    "sg:province":"Gelderland",
    "wof:name":"Ijzerl'S Landschap Bv",
    "wof:placetype":"venue"
},
  "geometry": {"coordinates":[6.519412,51.883625],"type":"Point"}
}