{
  "type": "Feature",
  "properties": {
    "addr:full":"Schummel 6 Nederweert Limburg 6031 GD",
    "addr:housenumber":"6",
    "addr:postcode":"6031 gd",
    "addr:street":"Schummel",
    "iso:country":"NL",
    "sg:address":"Schummel 6",
    "sg:city":"Nederweert",
    "sg:orig_category":"Pallets - Fabrieken En Groothandel",
    "sg:phone":"+31 6 54362323",
    "sg:postcode":"6031 GD",
    "sg:province":"Limburg",
    "wof:name":"Pege",
    "wof:placetype":"venue"
},
  "geometry": {"coordinates":[5.735093,51.285343],"type":"Point"}
}