{
  "type": "Feature",
  "properties": {
    "iso:country":"NL",
    "sg:address":"J Minneepad 21",
    "sg:city":"Rotterdam",
    "sg:orig_category":"Psychologen",
    "sg:phone":"+31 10 420 3194",
    "sg:postcode":"3067 KD",
    "sg:province":"Zuid-Holland",
    "wof:name":"Jacobs, H P",
    "wof:placetype":"venue"
},
  "geometry": {"coordinates":[4.5389,51.94397],"type":"Point"}
}