{
  "type": "Feature",
  "properties": {
    "addr:full":"Voorstad 5 Borculo Gelderland 7271 BE",
    "addr:housenumber":"5",
    "addr:postcode":"7271",
    "addr:street":"Voorstad;Gelderland",
    "iso:country":"NL",
    "sg:address":"Voorstad 5",
    "sg:city":"Borculo",
    "sg:orig_category":"Meubelzaken, Woning- And Keukeninrichting",
    "sg:phone":"+31 545 271 207",
    "sg:postcode":"7271 BE",
    "sg:province":"Gelderland",
    "wof:name":"Barink Woonmode",
    "wof:placetype":"venue"
},
  "geometry": {"coordinates":[6.5223507881,52.1145057678],"type":"Point"}
}