{
  "type": "Feature",
  "properties": {
    "addr:full":"S Gravenhekje 1A Amsterdam Noord-Holland 1011 TG",
    "addr:housenumber":"1a",
    "addr:postcode":"1011 tg",
    "iso:country":"NL",
    "sg:address":"S Gravenhekje 1A",
    "sg:city":"Amsterdam",
    "sg:orig_category":"Public Relationbureaus",
    "sg:phone":"+31 20 521 3131",
    "sg:postcode":"1011 TG",
    "sg:province":"Noord-Holland",
    "wof:name":"Motivision Bv",
    "wof:placetype":"venue"
},
  "geometry": {"coordinates":[4.907661,52.372425],"type":"Point"}
}