{
  "type": "Feature",
  "properties": {
    "iso:country":"NL",
    "sg:address":"Meerforel 1",
    "sg:city":"Leiden",
    "sg:orig_category":"Binnenhuisarchitecten",
    "sg:phone":"+31 71 521 6985",
    "sg:postcode":"2318 MR",
    "sg:province":"Zuid-Holland",
    "wof:name":"R.A.G. Van Zessen",
    "wof:placetype":"venue"
},
  "geometry": {"coordinates":[4.506086,52.183029],"type":"Point"}
}