{
  "type": "Feature",
  "properties": {
    "iso:country":"NL",
    "sg:address":"Oude Langstraat 39",
    "sg:city":"Tilburg",
    "sg:orig_category":"Boekhouders",
    "sg:phone":"+31 13 544 5545",
    "sg:postcode":"5041 CD",
    "sg:province":"North Brabant",
    "wof:name":"E.A. Roestenberg",
    "wof:placetype":"venue"
},
  "geometry": {"coordinates":[5.08436,51.566307],"type":"Point"}
}