{
  "type": "Feature",
  "properties": {
    "addr:full":"Handwerkerszyde 106 Drachten Provincie Friesland 9201 CP",
    "addr:housenumber":"106",
    "addr:postcode":"9201 cp",
    "addr:street":"Provincie Friesland",
    "iso:country":"NL",
    "sg:address":"Handwerkerszyde 106",
    "sg:city":"Drachten",
    "sg:orig_category":"Bloemen En Planten",
    "sg:phone":"+31 512 530 350",
    "sg:postcode":"9201 CP",
    "sg:province":"Provincie Friesland",
    "wof:name":"Stuivenberg, H",
    "wof:placetype":"venue"
},
  "geometry": {"coordinates":[6.0943,53.115231],"type":"Point"}
}