{
  "type": "Feature",
  "properties": {
    "addr:full":"Brouwerskade 9 Haarlem North Holland 2013 GJ",
    "addr:housenumber":"9",
    "addr:postcode":"2013 gj",
    "addr:street":"Brouwerskade",
    "iso:country":"NL",
    "sg:address":"Brouwerskade 9",
    "sg:city":"Haarlem",
    "sg:orig_category":"Loodgieterswerk, Verwarming And Sanitaire Installaties",
    "sg:phone":"+31 23 531 4204",
    "sg:postcode":"2013 GJ",
    "sg:province":"North Holland",
    "wof:name":"Installatie Bedrijf R. Kuperus",
    "wof:placetype":"venue"
},
  "geometry": {"coordinates":[4.625857,52.383007],"type":"Point"}
}