{
  "type": "Feature",
  "properties": {
    "addr:full":"Spinnery 65 Amstelveen Noord-Holland 1185 ZS",
    "addr:housenumber":"65",
    "addr:postcode":"1185 zs",
    "addr:street":"Spinnery",
    "iso:country":"NL",
    "sg:address":"Spinnery 65",
    "sg:city":"Amstelveen",
    "sg:orig_category":"Fotografie Reclame En Mode",
    "sg:phone":"+31 20 640 4782",
    "sg:postcode":"1185 ZS",
    "sg:province":"Noord-Holland",
    "wof:name":"John De Koning, Studio",
    "wof:placetype":"venue"
},
  "geometry": {"coordinates":[4.8331,52.280762],"type":"Point"}
}