{
  "type": "Feature",
  "properties": {
    "iso:country":"NL",
    "sg:address":"Spinnery 65",
    "sg:city":"Amstelveen",
    "sg:orig_category":"Fotografie Reclame En Mode",
    "sg:phone":"+31 20 640 4782",
    "sg:postcode":"1185 ZS",
    "sg:province":"Noord-Holland",
    "wof:name":"John De Koning, Studio",
    "wof:placetype":"venue"
},
  "geometry": {"coordinates":[4.8331,52.280762],"type":"Point"}
}