{
  "type": "Feature",
  "properties": {
    "addr:full":"Laaressingel 84 Enschede NL.08 7514 ES",
    "addr:housenumber":"84",
    "addr:postcode":"7514 es",
    "addr:street":"Laaressingel",
    "iso:country":"NL",
    "sg:address":"Laaressingel 84",
    "sg:city":"Enschede",
    "sg:orig_category":"Binnenhuisarchitecten",
    "sg:phone":"+31 53 433 8009",
    "sg:postcode":"7514 ES",
    "sg:province":"NL.08",
    "wof:name":"Ch Slutter",
    "wof:placetype":"venue"
},
  "geometry": {"coordinates":[6.908464,52.227734],"type":"Point"}
}