{
  "type": "Feature",
  "properties": {
    "addr:full":"Raadhuispln 77 Drachten Friesland 9203 EA",
    "addr:housenumber":"77",
    "addr:postcode":"9203 ea",
    "addr:street":"Raadhuispln",
    "iso:country":"NL",
    "sg:address":"Raadhuispln 77",
    "sg:city":"Drachten",
    "sg:orig_category":"Drukkerijen",
    "sg:phone":"+31 512 516 480",
    "sg:postcode":"9203 EA",
    "sg:province":"Friesland",
    "wof:name":"Drukservice",
    "wof:placetype":"venue"
},
  "geometry": {"coordinates":[6.098565,53.102871],"type":"Point"}
}