{
  "type": "Feature",
  "properties": {
    "addr:full":"Dorpsstraat 13 Esbeek North Brabant 5085 EH",
    "addr:housenumber":"13",
    "addr:postcode":"5085 eh",
    "addr:street":"Dorpsstraat",
    "iso:country":"NL",
    "sg:address":"Dorpsstraat 13",
    "sg:city":"Esbeek",
    "sg:orig_category":"Banken And Kredietinstellingen",
    "sg:phone":"+31 13 505 8505",
    "sg:postcode":"5085 EH",
    "sg:province":"North Brabant",
    "wof:name":"Rabobank",
    "wof:placetype":"venue"
},
  "geometry": {"coordinates":[5.137886,51.461819],"type":"Point"}
}