{
  "type": "Feature",
  "properties": {
    "addr:full":"Voorstraat 27 Egmond Aan Zee North Holland 1931 AG",
    "addr:housenumber":"27",
    "addr:postcode":"1931",
    "addr:street":"Voorstraat",
    "iso:country":"NL",
    "sg:address":"Voorstraat 27",
    "sg:city":"Egmond Aan Zee",
    "sg:orig_category":"Muziekinstrumenten Fab",
    "sg:phone":"+31 72 506 3346",
    "sg:postcode":"1931 AG",
    "sg:province":"North Holland",
    "wof:name":"P Visser",
    "wof:placetype":"venue"
},
  "geometry": {"coordinates":[4.629255,52.618504],"type":"Point"}
}