{
  "type": "Feature",
  "properties": {
    "addr:full":"Prins Willem V Oranjeln 5 Naarden North Holland 1412 GJ",
    "addr:housenumber":"5",
    "addr:postcode":"1412 gj",
    "addr:street":"Prins Willem V Oranjeln",
    "iso:country":"NL",
    "sg:address":"Prins Willem V Oranjeln 5",
    "sg:city":"Naarden",
    "sg:orig_category":"Juridische Dienstverlening",
    "sg:phone":"+31 35 694 8388",
    "sg:postcode":"1412 GJ",
    "sg:province":"North Holland",
    "wof:name":"Juridisch Adviesbureau De Wilde Bv",
    "wof:placetype":"venue"
},
  "geometry": {"coordinates":[5.15689,52.285427],"type":"Point"}
}