{
  "type": "Feature",
  "properties": {
    "addr:full":"Laurastr 13 Eygelshoven Limburg 6471 JG",
    "addr:housenumber":"13",
    "addr:postcode":"6471 jg",
    "addr:street":"Laurastr",
    "iso:country":"NL",
    "sg:address":"Laurastr 13",
    "sg:city":"Eygelshoven",
    "sg:orig_category":"Kaas",
    "sg:phone":"+31 45 535 2831",
    "sg:postcode":"6471 JG",
    "sg:province":"Limburg",
    "wof:name":"Ramakers, J",
    "wof:placetype":"venue"
},
  "geometry": {"coordinates":[6.059319973,50.893447876],"type":"Point"}
}