{
  "type": "Feature",
  "properties": {
    "addr:full":"Noordlangewg 22 Kats Zeeland 4485 AP",
    "addr:housenumber":"22",
    "addr:postcode":"4485 ap",
    "addr:street":"Noordlangewg",
    "iso:country":"NL",
    "sg:address":"Noordlangewg 22",
    "sg:city":"Kats",
    "sg:orig_category":"Onderhoudswerken",
    "sg:phone":"+31 113 600 148",
    "sg:postcode":"4485 AP",
    "sg:province":"Zeeland",
    "wof:name":"Nelis, F L M",
    "wof:placetype":"venue"
},
  "geometry": {"coordinates":[3.88495,51.569496],"type":"Point"}
}