{
  "type": "Feature",
  "properties": {
    "addr:full":"Weezebeeksingel 12 Almelo Overijssel 7609 PP",
    "addr:housenumber":"12",
    "addr:postcode":"7609 pp",
    "addr:street":"Weezebeeksingel",
    "iso:country":"NL",
    "sg:address":"Weezebeeksingel 12",
    "sg:city":"Almelo",
    "sg:orig_category":"Benzinestations And Brandstoffen",
    "sg:phone":"+31 546 817 546",
    "sg:postcode":"7609 PP",
    "sg:province":"Overijssel",
    "wof:name":"Total-Station Weezebeek",
    "wof:placetype":"venue"
},
  "geometry": {"coordinates":[6.624046,52.353031],"type":"Point"}
}