{
  "type": "Feature",
  "properties": {
    "iso:country":"NL",
    "sg:address":"Wethoudersln 9",
    "sg:city":"Tilburg",
    "sg:orig_category":"Ziekenhuizen, Sanatoria, Verpleeghuizen",
    "sg:phone":"+31 13 583 1000",
    "sg:postcode":"5021 AK",
    "sg:province":"North Brabant",
    "sg:website":"http://www.ztz.nl",
    "wof:name":"Zorgcentrum Tilburg Zuid",
    "wof:placetype":"venue"
},
  "geometry": {"coordinates":[5.09061,51.548569],"type":"Point"}
}