{
  "type": "Feature",
  "properties": {
    "addr:full":"Rodestr 22 Wittem Limburg 6286 AW",
    "addr:housenumber":"22",
    "addr:postcode":"6286 aw",
    "addr:street":"Rodestr",
    "iso:country":"NL",
    "sg:address":"Rodestr 22",
    "sg:city":"Wittem",
    "sg:orig_category":"Beeldende Kunstenaars",
    "sg:phone":"+31 43 450 1343",
    "sg:postcode":"6286 AW",
    "sg:province":"Limburg",
    "wof:name":"Lumey, P",
    "wof:placetype":"venue"
},
  "geometry": {"coordinates":[5.923211,50.809731],"type":"Point"}
}