{
  "type": "Feature",
  "properties": {
    "addr:full":"Zwolsewg 1 Deventer Overijssel 7412 AA",
    "addr:housenumber":"1",
    "addr:postcode":"7412 aa",
    "addr:street":"Zwolsewg",
    "iso:country":"NL",
    "sg:address":"Zwolsewg 1",
    "sg:city":"Deventer",
    "sg:orig_category":"Wijnkoperijen En -Groothandel",
    "sg:phone":"+31 570 614 737",
    "sg:postcode":"7412 AA",
    "sg:province":"Overijssel",
    "wof:name":"Slot-Kleverkamp",
    "wof:placetype":"venue"
},
  "geometry": {"coordinates":[6.1488618851,52.2582588196],"type":"Point"}
}