{
  "type": "Feature",
  "properties": {
    "addr:full":"Wezelrade 65 'S Gravenhage Zuid-Holland 2544 VW",
    "addr:housenumber":"65",
    "addr:postcode":"2544 vw",
    "addr:street":"Wezelrade;' S",
    "iso:country":"NL",
    "sg:address":"Wezelrade 65",
    "sg:city":"'S Gravenhage",
    "sg:orig_category":"Loodgieterswerk, Verwarming And Sanitaire Installaties",
    "sg:phone":"+31 70 329 9110",
    "sg:postcode":"2544 VW",
    "sg:province":"Zuid-Holland",
    "wof:name":"L. Grimmelikhuizen Loodg En Dakbed Bedrijf",
    "wof:placetype":"venue"
},
  "geometry": {"coordinates":[4.258859,52.047436],"type":"Point"}
}