{
  "type": "Feature",
  "properties": {
    "addr:full":"Nieuwestad 99 Leeuwarden Friesland 8911 CL",
    "addr:housenumber":"99",
    "addr:postcode":"8911",
    "addr:street":"Nieuwestad",
    "iso:country":"NL",
    "sg:address":"Nieuwestad 99",
    "sg:city":"Leeuwarden",
    "sg:orig_category":"Broodjeszaken",
    "sg:phone":"+31 58 212 2703",
    "sg:postcode":"8911 CL",
    "sg:province":"Friesland",
    "wof:name":"Broodhuys, Het",
    "wof:placetype":"venue"
},
  "geometry": {"coordinates":[5.794311,53.201],"type":"Point"}
}