{
  "type": "Feature",
  "properties": {
    "addr:full":"Akkerstr 99A Groningen Groningen 9717 KZ",
    "addr:housenumber":"99a",
    "addr:postcode":"9717 kz",
    "addr:street":"Akkerstr",
    "iso:country":"NL",
    "sg:address":"Akkerstr 99A",
    "sg:city":"Groningen",
    "sg:orig_category":"Organisatiebureaus",
    "sg:phone":"+31 50 577 7858",
    "sg:postcode":"9717 KZ",
    "sg:province":"Groningen",
    "wof:name":"Lameris, Geert",
    "wof:placetype":"venue"
},
  "geometry": {"coordinates":[6.5577330589,53.2273712158],"type":"Point"}
}