{
  "type": "Feature",
  "properties": {
    "addr:full":"Godetiawg 149 S Gravenhage Zuid-Holland 2555 RT",
    "addr:housenumber":"149;gravenhage",
    "addr:postcode":"2555 rt",
    "addr:street":"S",
    "iso:country":"NL",
    "sg:address":"Godetiawg 149",
    "sg:city":"S Gravenhage",
    "sg:orig_category":"Onroerende Goederen",
    "sg:phone":"+31 70 358 8408",
    "sg:postcode":"2555 RT",
    "sg:province":"Zuid-Holland",
    "wof:name":"Keyserlei Bv",
    "wof:placetype":"venue"
},
  "geometry": {"coordinates":[4.2417,52.06638],"type":"Point"}
}