{
  "type": "Feature",
  "properties": {
    "iso:country":"NL",
    "sg:address":"Agro Business Pk 48",
    "sg:city":"Wageningen",
    "sg:orig_category":"Octrooigemachtigden- Bureaus",
    "sg:phone":"+31 317 479 790",
    "sg:postcode":"6708 PW",
    "sg:province":"Gelderland",
    "wof:name":"Nederlands Octrooibureau",
    "wof:placetype":"venue"
},
  "geometry": {"coordinates":[5.646365,51.977619],"type":"Point"}
}