{
  "type": "Feature",
  "properties": {
    "iso:country":"NL",
    "sg:address":"Kupperswg 57",
    "sg:city":"Haarlem",
    "sg:orig_category":"Arbo- En Bedrijfsgezondheids- Diensten",
    "sg:phone":"+31 23 549 0484",
    "sg:postcode":"2031 EB",
    "sg:province":"Noord-Holland",
    "wof:name":"Arbo Advies En Maatwerk Bv",
    "wof:placetype":"venue"
},
  "geometry": {"coordinates":[4.65497,52.391354],"type":"Point"}
}