{
  "type": "Feature",
  "properties": {
    "addr:full":"Hackfort 10 Doetinchem Gelderland 7006 JC",
    "addr:housenumber":"10",
    "addr:postcode":"7006 jc",
    "addr:street":"Hackfort;Gelderland",
    "iso:country":"NL",
    "sg:address":"Hackfort 10",
    "sg:city":"Doetinchem",
    "sg:orig_category":"Yoga-Instituten",
    "sg:phone":"+31 314 342 749",
    "sg:postcode":"7006 JC",
    "sg:province":"Gelderland",
    "wof:name":"Broeke-Jonkman, Ten",
    "wof:placetype":"venue"
},
  "geometry": {"coordinates":[6.261223,51.966015],"type":"Point"}
}