{
  "type": "Feature",
  "properties": {
    "iso:country":"NL",
    "sg:address":"Stroomdal 35",
    "sg:city":"Steenwijk",
    "sg:orig_category":"Verlichting And Huishoudartikelen",
    "sg:phone":"+31 521 517 605",
    "sg:postcode":"8332 KG",
    "sg:province":"Overijssel",
    "wof:name":"Rilise",
    "wof:placetype":"venue"
},
  "geometry": {"coordinates":[6.142166,52.792187],"type":"Point"}
}