{
  "type": "Feature",
  "properties": {
    "addr:full":"Dasseburcht 23 Etten Leur Noord-Brabant 4874 JM",
    "addr:housenumber":"23",
    "addr:postcode":"4874 jm",
    "addr:street":"Dasseburcht",
    "iso:country":"NL",
    "sg:address":"Dasseburcht 23",
    "sg:city":"Etten Leur",
    "sg:orig_category":"Geluidsinstallaties - Verhuur",
    "sg:phone":"+31 76 501 9022",
    "sg:postcode":"4874 JM",
    "sg:province":"Noord-Brabant",
    "wof:name":"Mies Vof",
    "wof:placetype":"venue"
},
  "geometry": {"coordinates":[4.627724,51.575283],"type":"Point"}
}