{
  "type": "Feature",
  "properties": {
    "iso:country":"NL",
    "sg:address":"Eglaan 8",
    "sg:city":"Bemmel",
    "sg:orig_category":"Vertaal- And Tolkenbureaus",
    "sg:phone":"+31 481 464 230",
    "sg:postcode":"6681 GK",
    "sg:province":"Gelderland",
    "wof:name":"Vertaalbureau Meurs",
    "wof:placetype":"venue"
},
  "geometry": {"coordinates":[5.896925,51.897251],"type":"Point"}
}