{
  "type": "Feature",
  "properties": {
    "iso:country":"NL",
    "sg:address":"Raadhuisweg 51",
    "sg:city":"Reeuwijk",
    "sg:classifiers":[
        {
            "category":"Retail",
            "subcategory":"Photofinishing",
            "type":"Services"
        }
    ],
    "sg:phone":"+31 182 394 911",
    "sg:postcode":"2811 HV",
    "sg:province":"South Holland",
    "sg:tags":[
        "foto",
        "film"
    ],
    "wof:name":"Fotografie Rob Van Der Horst",
    "wof:placetype":"venue"
},
  "geometry": {"coordinates":[4.722649,52.046162],"type":"Point"}
}