{
  "type": "Feature",
  "properties": {
    "addr:full":"Lange Reke 2 Renesse Zeeland 4325 AA",
    "addr:housenumber":"2",
    "addr:postcode":"4325 aa",
    "addr:street":"Lange Reke",
    "iso:country":"NL",
    "sg:address":"Lange Reke 2",
    "sg:city":"Renesse",
    "sg:classifiers":[
        {
            "category":"Communications",
            "subcategory":"Television Station",
            "type":"Services"
        }
    ],
    "sg:phone":"+31 111 462 124",
    "sg:postcode":"4325 AA",
    "sg:province":"Zeeland",
    "sg:tags":[
        "video",
        "audio",
        "verhuur"
    ],
    "wof:name":"Frank",
    "wof:placetype":"venue"
},
  "geometry": {"coordinates":[3.773161,51.732292],"type":"Point"}
}