{
  "type": "Feature",
  "properties": {
    "addr:full":"Roskam 38 Veldhoven North Brabant 5505 JJ",
    "addr:housenumber":"38",
    "addr:postcode":"5505 jj",
    "addr:street":"Roskam",
    "iso:country":"NL",
    "sg:address":"Roskam 38",
    "sg:city":"Veldhoven",
    "sg:orig_category":"Beregeningsinstallaties",
    "sg:phone":"+31 40 253 2539",
    "sg:postcode":"5505 JJ",
    "sg:province":"North Brabant",
    "wof:name":"Smits Bv, Gebr",
    "wof:placetype":"venue"
},
  "geometry": {"coordinates":[5.378937,51.408669],"type":"Point"}
}