{
  "type": "Feature",
  "properties": {
    "addr:full":"Boschdk 21 Eindhoven North Brabant 5612 HA",
    "addr:housenumber":"21",
    "addr:postcode":"5612 ha",
    "addr:street":"Boschdk",
    "iso:country":"NL",
    "sg:address":"Boschdk 21",
    "sg:city":"Eindhoven",
    "sg:orig_category":"Onroerende Goederen",
    "sg:phone":"+31 40 239 3730",
    "sg:postcode":"5612 HA",
    "sg:province":"North Brabant",
    "wof:name":"Azl",
    "wof:placetype":"venue"
},
  "geometry": {"coordinates":[5.471394,51.444683],"type":"Point"}
}