{
  "type": "Feature",
  "properties": {
    "addr:full":"Eemslandweg 13 Emmen Provincie Drenthe 7894 AA",
    "addr:housenumber":"13",
    "addr:postcode":"7894 aa",
    "addr:street":"Eemslandweg;Provincie Drenthe",
    "iso:country":"NL",
    "sg:address":"Eemslandweg 13",
    "sg:city":"Emmen",
    "sg:orig_category":"Huishoudapparatuur, Televisies And Radio'S",
    "sg:phone":"+31 591 313 813",
    "sg:postcode":"7894 AA",
    "sg:province":"Provincie Drenthe",
    "wof:name":"Van Ommen",
    "wof:placetype":"venue"
},
  "geometry": {"coordinates":[7.028638,52.722904],"type":"Point"}
}