{
  "type": "Feature",
  "properties": {
    "addr:full":"Prinseneiland 22 Amsterdam Noord-Holland 1013 LR",
    "addr:housenumber":"22",
    "addr:postcode":"1013 lr",
    "addr:street":"Prinseneiland",
    "iso:country":"NL",
    "sg:address":"Prinseneiland 22",
    "sg:city":"Amsterdam",
    "sg:orig_category":"Meubelmakerijen",
    "sg:phone":"+31 20 627 3092",
    "sg:postcode":"1013 LR",
    "sg:province":"Noord-Holland",
    "wof:name":"Bais & Van Wijk",
    "wof:placetype":"venue"
},
  "geometry": {"coordinates":[4.886383,52.385883],"type":"Point"}
}