{
  "type": "Feature",
  "properties": {
    "addr:full":"Groesbeekseweg 244 Nijmegen Gelderland 6523 PJ",
    "addr:housenumber":"244",
    "addr:postcode":"6523 pj",
    "addr:street":"Groesbeekseweg;Gelderland",
    "iso:country":"NL",
    "sg:address":"Groesbeekseweg 244",
    "sg:city":"Nijmegen",
    "sg:orig_category":"Technische Studies And Onderzoek",
    "sg:phone":"+31 24 322 4417",
    "sg:postcode":"6523 PJ",
    "sg:province":"Gelderland",
    "wof:name":"Raadgevend Ingenieursbureau Osse Bv",
    "wof:placetype":"venue"
},
  "geometry": {"coordinates":[5.873313,51.831005],"type":"Point"}
}