{
  "type": "Feature",
  "properties": {
    "addr:full":"Lange Brinkweg 60 Soest Utrecht 3764 AE",
    "addr:housenumber":"60",
    "addr:postcode":"3764 ae",
    "addr:street":"Lange Brinkweg",
    "iso:country":"NL",
    "sg:address":"Lange Brinkweg 60",
    "sg:city":"Soest",
    "sg:orig_category":"Accountants - Administratie- Consulenten En -Kantoren",
    "sg:phone":"+31 35 602 6272",
    "sg:postcode":"3764 AE",
    "sg:province":"Utrecht",
    "wof:name":"Asselt, Van",
    "wof:placetype":"venue"
},
  "geometry": {"coordinates":[5.308982,52.178699],"type":"Point"}
}