{
  "type": "Feature",
  "properties": {
    "iso:country":"NL",
    "sg:address":"Steenloper 5",
    "sg:city":"Etten Leur",
    "sg:orig_category":"Horecabenodigdheden",
    "sg:phone":"+31 6 50668672",
    "sg:postcode":"4872 CV",
    "sg:province":"Noord-Brabant",
    "wof:name":"Hgk",
    "wof:placetype":"venue"
},
  "geometry": {"coordinates":[4.658719,51.572701],"type":"Point"}
}