{
  "type": "Feature",
  "properties": {
    "addr:full":"Couwervestraat 2 Goes Ohio 4461 XD",
    "addr:housenumber":"2",
    "addr:postcode":"4461 xd",
    "addr:street":"Couwervestraat",
    "iso:country":"NL",
    "sg:address":"Couwervestraat 2",
    "sg:city":"Goes",
    "sg:classifiers":[
        {
            "category":"Food & Beverages",
            "subcategory":"Fruits & Vegetables",
            "type":"Retail Goods"
        }
    ],
    "sg:phone":"+31 113 216 619",
    "sg:postcode":"4461 XD",
    "sg:province":"Ohio",
    "sg:tags":[
        "groenten"
    ],
    "wof:name":"Firma Fokke",
    "wof:placetype":"venue"
},
  "geometry": {"coordinates":[-83.914169,39.768833],"type":"Point"}
}