{
  "type": "Feature",
  "properties": {
    "addr:full":"Lavendelplnts 59 Almere Flevoland 1313 EX",
    "addr:housenumber":"59",
    "addr:postcode":"1313 ex",
    "addr:street":"Lavendelplnts;Flevoland",
    "iso:country":"NL",
    "sg:address":"Lavendelplnts 59",
    "sg:city":"Almere",
    "sg:orig_category":"Verenigingen En Stichtingen",
    "sg:phone":"+31 36 534 4643",
    "sg:postcode":"1313 EX",
    "sg:province":"Flevoland",
    "wof:name":"Karwij, 'T",
    "wof:placetype":"venue"
},
  "geometry": {"coordinates":[5.22223,52.376598],"type":"Point"}
}