{
  "type": "Feature",
  "properties": {
    "addr:full":"Hedel 6 Oirschot Noord-Brabant 5688 LD",
    "addr:housenumber":"6",
    "addr:postcode":"5688 ld",
    "addr:street":"Hedel",
    "iso:country":"NL",
    "sg:address":"Hedel 6",
    "sg:city":"Oirschot",
    "sg:orig_category":"Bloemen And Planten Gh",
    "sg:phone":"+31 499 575 306",
    "sg:postcode":"5688 LD",
    "sg:province":"Noord-Brabant",
    "wof:name":"Handelskwekerij J. Van Rulo Vof",
    "wof:placetype":"venue"
},
  "geometry": {"coordinates":[5.298547,51.520283],"type":"Point"}
}