{
  "type": "Feature",
  "properties": {
    "iso:country":"NL",
    "sg:address":"Oude Bredaseweg 35",
    "sg:city":"Etten-Leur",
    "sg:orig_category":"Kappers",
    "sg:phone":"+31 76 501 7457",
    "sg:postcode":"4872 AB",
    "sg:province":"Noord-Brabant",
    "wof:name":"Mark De Kapper",
    "wof:placetype":"venue"
},
  "geometry": {"coordinates":[4.640471,51.570576],"type":"Point"}
}