{
  "type": "Feature",
  "properties": {
    "addr:full":"Mauritsln 111 Geleen Limburg 6161 HT",
    "addr:housenumber":"111",
    "addr:postcode":"6161 ht",
    "addr:street":"Geleen Limburg",
    "iso:country":"NL",
    "sg:address":"Mauritsln 111",
    "sg:city":"Geleen",
    "sg:orig_category":"Beveiliging",
    "sg:phone":"+31 46 423 7610",
    "sg:postcode":"6161 HT",
    "sg:province":"Limburg",
    "sg:website":"http://www.securicor.nl",
    "wof:name":"Securicor",
    "wof:placetype":"venue"
},
  "geometry": {"coordinates":[5.828143,50.967567],"type":"Point"}
}