{
  "type": "Feature",
  "properties": {
    "addr:full":"Buitenhuizenpoort 2 Buren Gld Gelderland 4116 CA",
    "addr:housenumber":"2",
    "addr:postcode":"4116 ca",
    "addr:street":"Buitenhuizenpoort;Gld Gelderland",
    "iso:country":"NL",
    "sg:address":"Buitenhuizenpoort 2",
    "sg:city":"Buren Gld",
    "sg:orig_category":"Bloemen And Planten",
    "sg:phone":"+31 344 571 265",
    "sg:postcode":"4116 CA",
    "sg:province":"Gelderland",
    "wof:name":"Bloemsierkunst De Rozeknop",
    "wof:placetype":"venue"
},
  "geometry": {"coordinates":[5.333065,51.911682],"type":"Point"}
}