{
  "type": "Feature",
  "properties": {
    "addr:full":"Geulwg 13 St Maartensdyk Zeeland 4695 RE",
    "addr:housenumber":"13",
    "addr:postcode":"4695",
    "addr:street":"Geulwg",
    "iso:country":"NL",
    "sg:address":"Geulwg 13",
    "sg:city":"St Maartensdyk",
    "sg:orig_category":"Verpakkingsbedrijven",
    "sg:phone":"+31 166 661 919",
    "sg:postcode":"4695 RE",
    "sg:province":"Zeeland",
    "wof:name":"Seafood Bv",
    "wof:placetype":"venue"
},
  "geometry": {"coordinates":[4.090532,51.547058],"type":"Point"}
}