{
  "type": "Feature",
  "properties": {
    "addr:full":"Nyverheidswg 9 Oosterhout Nymegen Gelderland 6679 AH",
    "addr:housenumber":"9",
    "addr:postcode":"6679 ah",
    "addr:street":"Nyverheidswg",
    "iso:country":"NL",
    "sg:address":"Nyverheidswg 9",
    "sg:city":"Oosterhout Nymegen",
    "sg:classifiers":[
        {
            "category":"Retail",
            "subcategory":"Storage",
            "type":"Services"
        }
    ],
    "sg:phone":"+31 24 348 9990",
    "sg:postcode":"6679 AH",
    "sg:province":"Gelderland",
    "sg:tags":[
        "op-",
        "en",
        "overslagbedrijven"
    ],
    "wof:name":"Danzas",
    "wof:placetype":"venue"
},
  "geometry": {"coordinates":[5.848114,51.89016],"type":"Point"}
}