{
  "type": "Feature",
  "properties": {
    "addr:full":"Kruijsenstr 34 Gilze North Brabant 5126 GM",
    "addr:housenumber":"34",
    "addr:postcode":"5126 gm",
    "addr:street":"Kruijsenstr",
    "iso:country":"NL",
    "sg:address":"Kruijsenstr 34",
    "sg:city":"Gilze",
    "sg:orig_category":"Parketvloeren - Onderhoud En Reparatie",
    "sg:phone":"+31 161 456 309",
    "sg:postcode":"5126 GM",
    "sg:province":"North Brabant",
    "wof:name":"Jos Van Dongen",
    "wof:placetype":"venue"
},
  "geometry": {"coordinates":[4.934163,51.541176],"type":"Point"}
}