{
  "type": "Feature",
  "properties": {
    "addr:full":"Kreeft 16 Yerseke Zeeland 4401 NZ",
    "addr:housenumber":"16",
    "addr:postcode":"4401 nz",
    "addr:street":"Kreeft",
    "iso:country":"NL",
    "sg:address":"Kreeft 16",
    "sg:city":"Yerseke",
    "sg:orig_category":"Autokeuringen",
    "sg:phone":"+31 113 503 555",
    "sg:postcode":"4401 NZ",
    "sg:province":"Zeeland",
    "wof:name":"Westerwind Nederland",
    "wof:placetype":"venue"
},
  "geometry": {"coordinates":[4.052693,51.481113],"type":"Point"}
}