{
  "type": "Feature",
  "properties": {
    "addr:full":"Geuzenkade 72 Amsterdam Noord-Holland 1056 KP",
    "addr:housenumber":"72",
    "addr:postcode":"1056 kp",
    "addr:street":"Geuzenkade",
    "iso:country":"NL",
    "sg:address":"Geuzenkade 72",
    "sg:city":"Amsterdam",
    "sg:orig_category":"Diverse Grafische Activiteiten",
    "sg:phone":"+31 20 685 1830",
    "sg:postcode":"1056 KP",
    "sg:province":"Noord-Holland",
    "wof:name":"Studio Simone",
    "wof:placetype":"venue"
},
  "geometry": {"coordinates":[4.864064,52.374336],"type":"Point"}
}