{
  "type": "Feature",
  "properties": {
    "addr:full":"Christiaan Huygensstraat 7 Strijen Zuid-Holland 3291 CN",
    "addr:housenumber":"7",
    "addr:postcode":"3291 cn",
    "addr:street":"Christiaan Huygensstraat",
    "iso:country":"NL",
    "sg:address":"Christiaan Huygensstraat 7",
    "sg:city":"Strijen",
    "sg:orig_category":"Gespecialiseerde Bouw",
    "sg:phone":"+31 78 674 3478",
    "sg:postcode":"3291 CN",
    "sg:province":"Zuid-Holland",
    "wof:name":"D.A. De Ruiter",
    "wof:placetype":"venue"
},
  "geometry": {"coordinates":[4.559235,51.752247],"type":"Point"}
}