{
  "type": "Feature",
  "properties": {
    "addr:full":"M Bauerstr 10 Woerden Utrecht 3443 HL",
    "addr:housenumber":"10",
    "addr:postcode":"3443 hl",
    "addr:street":"Woerden",
    "iso:country":"NL",
    "sg:address":"M Bauerstr 10",
    "sg:city":"Woerden",
    "sg:orig_category":"Architecten En Architectenbureaus",
    "sg:phone":"+31 348 413 916",
    "sg:postcode":"3443 HL",
    "sg:province":"Utrecht",
    "wof:name":"Kort Bv, F J Van Der",
    "wof:placetype":"venue"
},
  "geometry": {"coordinates":[4.866287,52.090275],"type":"Point"}
}