{
  "type": "Feature",
  "properties": {
    "addr:full":"Haagweg 63 Breda North Brabant 4814 GB",
    "addr:housenumber":"63",
    "addr:postcode":"4814 gb",
    "addr:street":"Haagweg",
    "iso:country":"NL",
    "sg:address":"Haagweg 63",
    "sg:city":"Breda",
    "sg:orig_category":"Discountwinkels",
    "sg:phone":"+31 76 521 0345",
    "sg:postcode":"4814 GB",
    "sg:province":"North Brabant",
    "wof:name":"Modehuis Concurrent",
    "wof:placetype":"venue"
},
  "geometry": {"coordinates":[4.759096,51.583515],"type":"Point"}
}