{
  "type": "Feature",
  "properties": {
    "iso:country":"NL",
    "sg:address":"Huizermaatwg 570",
    "sg:city":"Huizen",
    "sg:orig_category":"Voorlichtingsbureaus",
    "sg:phone":"+31 35 541 7821",
    "sg:postcode":"1276 LN",
    "sg:province":"Noord-Holland",
    "sg:website":"http://www.RASinfo.nl",
    "wof:name":"Raad Ambtenaren",
    "wof:placetype":"venue"
},
  "geometry": {"coordinates":[5.25378,52.296928],"type":"Point"}
}