{
  "type": "Feature",
  "properties": {
    "iso:country":"NL",
    "sg:address":"Suikerdoossingel 19",
    "sg:city":"Maasbracht",
    "sg:orig_category":"Kinderopvang Behalve Thuis",
    "sg:phone":"+31 475 466 218",
    "sg:postcode":"6051 HN",
    "sg:province":"Limburg",
    "wof:name":"Kinderdagverblijf Dribbel",
    "wof:placetype":"venue"
},
  "geometry": {"coordinates":[5.89381,51.145111],"type":"Point"}
}