{
  "type": "Feature",
  "properties": {
    "iso:country":"NL",
    "sg:address":"Dorpsstraat 45",
    "sg:city":"Noordwijkerhout",
    "sg:orig_category":"Kappers",
    "sg:phone":"+31 252 371 154",
    "sg:postcode":"2211 GB",
    "sg:province":"South Holland",
    "wof:name":"Eugenie",
    "wof:placetype":"venue"
},
  "geometry": {"coordinates":[4.4909968376,52.2611808777],"type":"Point"}
}