{
  "type": "Feature",
  "properties": {
    "addr:full":"V Houten Ind Pk 25 Weesp North Holland 1381 MZ",
    "addr:postcode":"1381 mz",
    "addr:street":"V;Pk 25",
    "iso:country":"NL",
    "sg:address":"V Houten Ind Pk 25",
    "sg:city":"Weesp",
    "sg:orig_category":"Farmaceutische Industrie En Groothandel",
    "sg:phone":"+31 294 465 905",
    "sg:postcode":"1381 MZ",
    "sg:province":"North Holland",
    "wof:name":"Vemedia Bv",
    "wof:placetype":"venue"
},
  "geometry": {"coordinates":[5.03828,52.308315],"type":"Point"}
}