{
  "type": "Feature",
  "properties": {
    "addr:full":"Kerkstraat 41 Boekel North Brabant 5427 BB",
    "addr:housenumber":"41",
    "addr:postcode":"5427 bb",
    "addr:street":"Kerkstraat",
    "iso:country":"NL",
    "sg:address":"Kerkstraat 41",
    "sg:city":"Boekel",
    "sg:orig_category":"Kappers",
    "sg:phone":"+31 492 323 813",
    "sg:postcode":"5427 BB",
    "sg:province":"North Brabant",
    "wof:name":"Topline Kappers",
    "wof:placetype":"venue"
},
  "geometry": {"coordinates":[5.673952,51.603268],"type":"Point"}
}