{
  "type": "Feature",
  "properties": {
    "addr:full":"Boulevard Heuvelink 142 Arnhem Gelderland 6828 KW",
    "addr:housenumber":"142",
    "addr:postcode":"6828 kw",
    "addr:street":"Boulevard Heuvelink",
    "iso:country":"NL",
    "sg:address":"Boulevard Heuvelink 142",
    "sg:city":"Arnhem",
    "sg:orig_category":"Verhuur Catering-, Feest- En Evenementbenodigdheden",
    "sg:phone":"+31 313 419 239",
    "sg:postcode":"6828 KW",
    "sg:province":"Gelderland",
    "wof:name":"J.L. De Rouw",
    "wof:placetype":"venue"
},
  "geometry": {"coordinates":[5.922335,51.980629],"type":"Point"}
}