{
  "type": "Feature",
  "properties": {
    "iso:country":"NL",
    "sg:address":"Klarendalseweg 376",
    "sg:city":"Arnhem",
    "sg:orig_category":"Krantenuitgeverijen",
    "sg:phone":"+31 26 445 9031",
    "sg:postcode":"6822 GT",
    "sg:province":"Gelderland",
    "wof:name":"Uitgeverij Het Marktblad",
    "wof:placetype":"venue"
},
  "geometry": {"coordinates":[5.92387,51.98951],"type":"Point"}
}