{
  "type": "Feature",
  "properties": {
    "addr:full":"Zorggras 33 Wilnis Utrecht 3648 HT",
    "addr:housenumber":"33",
    "addr:postcode":"3648 ht",
    "addr:street":"Zorggras",
    "iso:country":"NL",
    "sg:address":"Zorggras 33",
    "sg:city":"Wilnis",
    "sg:orig_category":"Webdesign Bureaus",
    "sg:phone":"+31 297 282 960",
    "sg:postcode":"3648 HT",
    "sg:province":"Utrecht",
    "sg:website":"http://www.kuiter.nl",
    "wof:name":"Kuiter",
    "wof:placetype":"venue"
},
  "geometry": {"coordinates":[4.8902988434,52.2000007629],"type":"Point"}
}