{
  "type": "Feature",
  "properties": {
    "addr:full":"Marktstraat 4 Roermond Limburg 6041 EN",
    "addr:housenumber":"4",
    "addr:postcode":"6041 en",
    "addr:street":"Marktstraat",
    "iso:country":"NL",
    "sg:address":"Marktstraat 4",
    "sg:city":"Roermond",
    "sg:orig_category":"Metaalwerken",
    "sg:phone":"+31 475 333 082",
    "sg:postcode":"6041 EN",
    "sg:province":"Limburg",
    "wof:name":"J. Heitzer",
    "wof:placetype":"venue"
},
  "geometry": {"coordinates":[5.984939,51.195126],"type":"Point"}
}