{
  "type": "Feature",
  "properties": {
    "addr:full":"Bredevoortsestraatweg 39 Aalten Gelderland 7121 BB",
    "addr:housenumber":"39",
    "addr:postcode":"7121 bb",
    "addr:street":"Bredevoortsestraatweg;Gelderland",
    "iso:country":"NL",
    "sg:address":"Bredevoortsestraatweg 39",
    "sg:city":"Aalten",
    "sg:orig_category":"Boekenuitgeverijen",
    "sg:phone":"+31 543 472 473",
    "sg:postcode":"7121 BB",
    "sg:province":"Gelderland",
    "wof:name":"Boek- En Kantboekhandel Messink & Prinsen Bv",
    "wof:placetype":"venue"
},
  "geometry": {"coordinates":[6.585049,51.928959],"type":"Point"}
}