{
  "type": "Feature",
  "properties": {
    "addr:full":"Fazantstr 40 Zaltbommel Gelderland 5301 SC",
    "addr:housenumber":"40",
    "addr:postcode":"5301",
    "addr:street":"Fazantstr;Gelderland",
    "iso:country":"NL",
    "sg:address":"Fazantstr 40",
    "sg:city":"Zaltbommel",
    "sg:orig_category":"Hondenscholen",
    "sg:phone":"+31 418 516 444",
    "sg:postcode":"5301 SC",
    "sg:province":"Gelderland",
    "wof:name":"Jumpy",
    "wof:placetype":"venue"
},
  "geometry": {"coordinates":[5.247317,51.804741],"type":"Point"}
}