{
  "type": "Feature",
  "properties": {
    "addr:full":"Hofstr 10 Wouw North Brabant 4724 AK",
    "addr:housenumber":"10",
    "addr:postcode":"4724 ak",
    "addr:street":"Hofstr",
    "iso:country":"NL",
    "sg:address":"Hofstr 10",
    "sg:city":"Wouw",
    "sg:orig_category":"Autorijscholen",
    "sg:phone":"+31 165 303 452",
    "sg:postcode":"4724 AK",
    "sg:province":"North Brabant",
    "wof:name":"Meer, Johan Van",
    "wof:placetype":"venue"
},
  "geometry": {"coordinates":[4.390064,51.524166],"type":"Point"}
}