{
  "type": "Feature",
  "properties": {
    "addr:full":"Barnflair O 51 Ter Apel Groningen 9561 PC",
    "addr:housenumber":"51",
    "addr:postcode":"9561 pc",
    "addr:street":"Barnflair O",
    "iso:country":"NL",
    "sg:address":"Barnflair O 51",
    "sg:city":"Ter Apel",
    "sg:orig_category":"Schilders",
    "sg:phone":"+31 599 584 873",
    "sg:postcode":"9561 PC",
    "sg:province":"Groningen",
    "wof:name":"Dummer, L M",
    "wof:placetype":"venue"
},
  "geometry": {"coordinates":[7.081816,52.857288],"type":"Point"}
}