{
  "type": "Feature",
  "properties": {
    "addr:full":"Arnhemseweg 28 Beek Gem Bergh Gelderland 7037 DB",
    "addr:housenumber":"28",
    "addr:postcode":"7037 db",
    "addr:street":"Arnhemseweg",
    "iso:country":"NL",
    "sg:address":"Arnhemseweg 28",
    "sg:city":"Beek Gem Bergh",
    "sg:orig_category":"Koeriersdiensten",
    "sg:phone":"+31 316 224 314",
    "sg:postcode":"7037 DB",
    "sg:province":"Gelderland",
    "wof:name":"P.H. Ambting",
    "wof:placetype":"venue"
},
  "geometry": {"coordinates":[6.168156,51.914337],"type":"Point"}
}