{
  "type": "Feature",
  "properties": {
    "addr:full":"K P C De Bazelstr 82 Bussum Noord-Holland 1402 XE",
    "addr:housenumber":"82",
    "addr:postcode":"1402 xe",
    "addr:street":"K P C De Bazelstr",
    "iso:country":"NL",
    "sg:address":"K P C De Bazelstr 82",
    "sg:city":"Bussum",
    "sg:orig_category":"Facilitaire Dienstverlening",
    "sg:phone":"+31 35 693 6384",
    "sg:postcode":"1402 XE",
    "sg:province":"Noord-Holland",
    "wof:name":"Aaa",
    "wof:placetype":"venue"
},
  "geometry": {"coordinates":[5.182148,52.275005],"type":"Point"}
}