{
  "type": "Feature",
  "properties": {
    "addr:full":"Julianastr 66 Brunssum Limburg 6441 BV",
    "addr:housenumber":"66",
    "addr:postcode":"6441 bv",
    "addr:street":"Julianastr",
    "iso:country":"NL",
    "sg:address":"Julianastr 66",
    "sg:city":"Brunssum",
    "sg:orig_category":"Gelegenheidskleding",
    "sg:phone":"+31 45 525 2965",
    "sg:postcode":"6441 BV",
    "sg:province":"Limburg",
    "wof:name":"Winthagen-Janssen, A J M",
    "wof:placetype":"venue"
},
  "geometry": {"coordinates":[5.973666,50.948063],"type":"Point"}
}