{
  "type": "Feature",
  "properties": {
    "addr:full":"Heuvelakkersestraat 15 Aerdt Gelderland 6913 AA",
    "addr:housenumber":"15",
    "addr:postcode":"6913 aa",
    "addr:street":"Heuvelakkersestraat;Gelderland",
    "iso:country":"NL",
    "sg:address":"Heuvelakkersestraat 15",
    "sg:city":"Aerdt",
    "sg:orig_category":"Goederenvervoer Over De Weg",
    "sg:phone":"+31 316 247 204",
    "sg:postcode":"6913 AA",
    "sg:province":"Gelderland",
    "wof:name":"Vof Luub Transport-Commissie Groenten &",
    "wof:placetype":"venue"
},
  "geometry": {"coordinates":[6.089612,51.890228],"type":"Point"}
}