{
  "type": "Feature",
  "properties": {
    "addr:full":"Galvanistr 7 Ede Gld Gelderland 6716 AE",
    "addr:housenumber":"7",
    "addr:postcode":"6716 ae",
    "addr:street":"Galvanistr;Gld Gelderland",
    "iso:country":"NL",
    "sg:address":"Galvanistr 7",
    "sg:city":"Ede Gld",
    "sg:orig_category":"Verenigingen En Stichtingen",
    "sg:phone":"+31 318 645 700",
    "sg:postcode":"6716 AE",
    "sg:province":"Gelderland",
    "sg:website":"http://www.ipc-training.nl",
    "wof:name":"Ipc Plant En Dier",
    "wof:placetype":"venue"
},
  "geometry": {"coordinates":[5.644313,52.02626],"type":"Point"}
}