{
  "type": "Feature",
  "properties": {
    "addr:full":"Binnenveer 9 Weesp Noord-Holland 1381 BT",
    "addr:housenumber":"9",
    "addr:postcode":"1381 bt",
    "addr:street":"Binnenveer",
    "iso:country":"NL",
    "sg:address":"Binnenveer 9",
    "sg:city":"Weesp",
    "sg:orig_category":"Woninginrichting",
    "sg:phone":"+31 294 412 510",
    "sg:postcode":"1381 BT",
    "sg:province":"Noord-Holland",
    "wof:name":"Bos",
    "wof:placetype":"venue"
},
  "geometry": {"coordinates":[5.0392642021,52.3082199097],"type":"Point"}
}