{
  "type": "Feature",
  "properties": {
    "addr:full":"Witte De Withweg 20 Breda North Brabant 4819 AH",
    "addr:housenumber":"20",
    "addr:postcode":"4819 ah",
    "addr:street":"Witte De Withweg",
    "iso:country":"NL",
    "sg:address":"Witte De Withweg 20",
    "sg:city":"Breda",
    "sg:orig_category":"Fotostudio'S And Fotografen",
    "sg:phone":"+31 76 530 9219",
    "sg:postcode":"4819 AH",
    "sg:province":"North Brabant",
    "wof:name":"Ruurd Van Der Noord Fotografie",
    "wof:placetype":"venue"
},
  "geometry": {"coordinates":[4.771553,51.57687],"type":"Point"}
}