{
  "type": "Feature",
  "properties": {
    "addr:full":"Raadhuisstr 257 Alphen A/D Rijn South Holland 2406 AD",
    "addr:housenumber":"257",
    "addr:postcode":"2406 ad",
    "iso:country":"NL",
    "sg:address":"Raadhuisstr 257",
    "sg:city":"Alphen A/D Rijn",
    "sg:orig_category":"Kappers",
    "sg:phone":"+31 172 475 339",
    "sg:postcode":"2406 AD",
    "sg:province":"South Holland",
    "wof:name":"Aat'S",
    "wof:placetype":"venue"
},
  "geometry": {"coordinates":[4.6630277634,52.1278457642],"type":"Point"}
}