{
  "type": "Feature",
  "properties": {
    "iso:country":"NL",
    "sg:address":"Sion 13",
    "sg:city":"Pynacker",
    "sg:orig_category":"Loodgieters",
    "sg:phone":"+31 6 51055541",
    "sg:postcode":"2641 MP",
    "sg:province":"South Holland",
    "wof:name":"Bonefaas, P H",
    "wof:placetype":"venue"
},
  "geometry": {"coordinates":[4.442455,52.009399],"type":"Point"}
}