{
  "type": "Feature",
  "properties": {
    "addr:full":"Hugo Molenaarstr 18 Delfshaven Rotterdam South Holland 3022 NR",
    "addr:housenumber":"18",
    "addr:postcode":"3022 nr",
    "iso:country":"NL",
    "sg:address":"Hugo Molenaarstr 18",
    "sg:city":"Delfshaven Rotterdam",
    "sg:orig_category":"Bibliotheken And Openbare Archieven",
    "sg:phone":"+31 10 477 3238",
    "sg:postcode":"3022 NR",
    "sg:province":"South Holland",
    "wof:name":"Speelotheek Katrijn",
    "wof:placetype":"venue"
},
  "geometry": {"coordinates":[4.452481,51.919888],"type":"Point"}
}