{
  "type": "Feature",
  "properties": {
    "addr:full":"Pelgrimstraat 1B Nuland Noord-Brabant 5391 BL",
    "addr:housenumber":"1b",
    "addr:postcode":"5391 bl",
    "addr:street":"Pelgrimstraat",
    "iso:country":"NL",
    "sg:address":"Pelgrimstraat 1B",
    "sg:city":"Nuland",
    "sg:classifiers":[
        {
            "category":"Communications",
            "subcategory":"Television Station",
            "type":"Services"
        }
    ],
    "sg:phone":"+31 73 532 1827",
    "sg:postcode":"5391 BL",
    "sg:province":"Noord-Brabant",
    "sg:tags":[
        "video",
        "audio",
        "verhuur"
    ],
    "wof:name":"Videotheek Ster",
    "wof:placetype":"venue"
},
  "geometry": {"coordinates":[5.436103,51.725384],"type":"Point"}
}