{
  "type": "Feature",
  "properties": {
    "addr:full":"Het Lentfert 51 Enschede NL.08 7547 SN",
    "addr:housenumber":"51",
    "addr:postcode":"7547 sn",
    "addr:street":"Het Lentfert",
    "iso:country":"NL",
    "sg:address":"Het Lentfert 51",
    "sg:city":"Enschede",
    "sg:orig_category":"Metaalwerken",
    "sg:phone":"+31 53 488 3883",
    "sg:postcode":"7547 SN",
    "sg:province":"NL.08",
    "wof:name":"Dutch Trading Dutra Bv",
    "wof:placetype":"venue"
},
  "geometry": {"coordinates":[6.839567,52.222321],"type":"Point"}
}