{
  "type": "Feature",
  "properties": {
    "iso:country":"NL",
    "sg:address":"Willem Barentszstraat 12",
    "sg:city":"Terneuzen",
    "sg:orig_category":"Binnenhuisarchitecten",
    "sg:phone":"+31 115 616 689",
    "sg:postcode":"4535 BD",
    "sg:province":"Zeeland",
    "wof:name":"Jacqueline De Smet",
    "wof:placetype":"venue"
},
  "geometry": {"coordinates":[3.853895,51.319305],"type":"Point"}
}