{
  "type": "Feature",
  "properties": {
    "iso:country":"NL",
    "sg:address":"Ipenrodestr 6",
    "sg:city":"Haarlem",
    "sg:orig_category":"Psychologen",
    "sg:phone":"+31 23 551 0545",
    "sg:postcode":"2012 MG",
    "sg:province":"Noord-Holland",
    "wof:name":"Hechten, A I E Van",
    "wof:placetype":"venue"
},
  "geometry": {"coordinates":[4.618398,52.368233],"type":"Point"}
}