{
  "type": "Feature",
  "properties": {
    "addr:full":"Idzardaweg 39 Ter Idzard Friesland 8476 EN",
    "addr:housenumber":"39",
    "addr:postcode":"8476 en",
    "addr:street":"Idzardaweg",
    "iso:country":"NL",
    "sg:address":"Idzardaweg 39",
    "sg:city":"Ter Idzard",
    "sg:orig_category":"Schilderwerk",
    "sg:phone":"+31 561 688 601",
    "sg:postcode":"8476 EN",
    "sg:province":"Friesland",
    "wof:name":"Glaszettersbedrijf P. De Vries",
    "wof:placetype":"venue"
},
  "geometry": {"coordinates":[6.030041,52.902775],"type":"Point"}
}