{
  "type": "Feature",
  "properties": {
    "addr:full":"Ipperhoeve 36 Haarsteeg North Brabant 5254 JA",
    "addr:housenumber":"36",
    "addr:postcode":"5254 ja",
    "addr:street":"Ipperhoeve",
    "iso:country":"NL",
    "sg:address":"Ipperhoeve 36",
    "sg:city":"Haarsteeg",
    "sg:orig_category":"Adviesbureaus Bedrijfsorganisatie",
    "sg:phone":"+31 73 511 2102",
    "sg:postcode":"5254 JA",
    "sg:province":"North Brabant",
    "wof:name":"Vierhout Bv, P J M",
    "wof:placetype":"venue"
},
  "geometry": {"coordinates":[5.200577,51.713318],"type":"Point"}
}