{
  "type": "Feature",
  "properties": {
    "addr:full":"Veerstoep 1 Sliedrecht Zuid-Holland 3361 CE",
    "addr:housenumber":"1",
    "addr:postcode":"3361 ce",
    "addr:street":"Veerstoep",
    "iso:country":"NL",
    "sg:address":"Veerstoep 1",
    "sg:city":"Sliedrecht",
    "sg:orig_category":"Fotoreportages",
    "sg:phone":"+31 6 22559459",
    "sg:postcode":"3361 CE",
    "sg:province":"Zuid-Holland",
    "wof:name":"Dane, Geert",
    "wof:placetype":"venue"
},
  "geometry": {"coordinates":[4.783878,51.817104],"type":"Point"}
}