{
  "type": "Feature",
  "properties": {
    "iso:country":"NL",
    "sg:address":"J Greshoffln 14",
    "sg:city":"Kloetinge",
    "sg:orig_category":"Machinehandel",
    "sg:phone":"+31 113 212 340",
    "sg:postcode":"4481 DD",
    "sg:province":"Zeeland",
    "wof:name":"Thokler",
    "wof:placetype":"venue"
},
  "geometry": {"coordinates":[3.909783,51.491421],"type":"Point"}
}