{
  "type": "Feature",
  "properties": {
    "addr:full":"Ryswykstr 175 Amsterdam Noord-Holland 1062 EV",
    "addr:housenumber":"175",
    "iso:country":"NL",
    "sg:address":"Ryswykstr 175",
    "sg:city":"Amsterdam",
    "sg:orig_category":"Kantoor- En Bedrijfsmeubelen",
    "sg:phone":"+31 20 615 2121",
    "sg:postcode":"1062 EV",
    "sg:province":"Noord-Holland",
    "wof:name":"Pfs",
    "wof:placetype":"venue"
},
  "geometry": {"coordinates":[4.8397498131,52.3510818481],"type":"Point"}
}