{
  "type": "Feature",
  "properties": {
    "addr:full":"Nassaukd 379 Amsterdam Noord-Holland 1054 AD",
    "addr:housenumber":"379",
    "addr:postcode":"1054 ad",
    "iso:country":"NL",
    "sg:address":"Nassaukd 379",
    "sg:city":"Amsterdam",
    "sg:orig_category":"Vertaalbureaus",
    "sg:phone":"+31 20 683 0694",
    "sg:postcode":"1054 AD",
    "sg:province":"Noord-Holland",
    "wof:name":"Anglo Output",
    "wof:placetype":"venue"
},
  "geometry": {"coordinates":[4.86857,52.361408],"type":"Point"}
}