{
  "type": "Feature",
  "properties": {
    "addr:full":"1E Helmersstr 265 Amsterdam North Holland 1054 DZ",
    "addr:housenumber":"265",
    "addr:postcode":"1054 dz",
    "addr:street":"1E Helmersstr",
    "iso:country":"NL",
    "sg:address":"1E Helmersstr 265",
    "sg:city":"Amsterdam",
    "sg:orig_category":"Verenigingen En Stichtingen",
    "sg:phone":"+31 20 412 5758",
    "sg:postcode":"1054 DZ",
    "sg:province":"North Holland",
    "wof:name":"Hjs Guesthouse",
    "wof:placetype":"venue"
},
  "geometry": {"coordinates":[4.864443,52.360622],"type":"Point"}
}