{
  "type": "Feature",
  "properties": {
    "iso:country":"NL",
    "sg:address":"Nieuwe Nonnendaalseweg 336",
    "sg:city":"Nijmegen",
    "sg:orig_category":"Granen, Zaden And Diervoeders Gh",
    "sg:phone":"+31 24 377 4991",
    "sg:postcode":"6542 PM",
    "sg:province":"Gelderland",
    "wof:name":"Zaad- En Vogelhandel Thijssen",
    "wof:placetype":"venue"
},
  "geometry": {"coordinates":[5.842786,51.841026],"type":"Point"}
}