{
  "type": "Feature",
  "properties": {
    "iso:country":"NL",
    "sg:address":"Pr Hendrikln 72",
    "sg:city":"Bilthoven",
    "sg:orig_category":"Bedrijfsopleidingen",
    "sg:phone":"+31 30 225 9520",
    "sg:postcode":"3721 AT",
    "sg:province":"Utrecht",
    "wof:name":"A & O",
    "wof:placetype":"venue"
},
  "geometry": {"coordinates":[5.201445,52.127697],"type":"Point"}
}