{
  "type": "Feature",
  "properties": {
    "iso:country":"NL",
    "sg:address":"Redemark 7",
    "sg:city":"Almere",
    "sg:orig_category":"Loodgieterswerk, Verwarming And Sanitaire Installaties",
    "sg:phone":"+31 36 538 6026",
    "sg:postcode":"1355 LA",
    "sg:province":"NL.",
    "wof:name":"Jk Bouwservice",
    "wof:placetype":"venue"
},
  "geometry": {"coordinates":[5.229392,52.347481],"type":"Point"}
}