{
  "type": "Feature",
  "properties": {
    "iso:country":"NL",
    "sg:address":"Noord Ijsseldijk 107",
    "sg:city":"Ijsselstein Ut",
    "sg:orig_category":"Bedrijfs- And Managementsconsultants",
    "sg:phone":"+31 30 687 6406",
    "sg:postcode":"3402 PG",
    "sg:province":"Utrecht",
    "wof:name":"Power Of 4 Bv",
    "wof:placetype":"venue"
},
  "geometry": {"coordinates":[5.039801,52.033669],"type":"Point"}
}