{
  "type": "Feature",
  "properties": {
    "addr:full":"Kerkstraat 33 Koningsbosch North Rhine-Westphalia 6104 AA",
    "addr:housenumber":"33",
    "addr:postcode":"6104 aa",
    "addr:street":"Kerkstraat",
    "iso:country":"NL",
    "sg:address":"Kerkstraat 33",
    "sg:city":"Koningsbosch",
    "sg:orig_category":"Verhuur Bouwmachines",
    "sg:phone":"+31 475 301 860",
    "sg:postcode":"6104 AA",
    "sg:province":"North Rhine-Westphalia",
    "wof:name":"Decorent Bouwmaterieel",
    "wof:placetype":"venue"
},
  "geometry": {"coordinates":[5.95307,51.056133],"type":"Point"}
}