{
  "type": "Feature",
  "properties": {
    "iso:country":"NL",
    "sg:address":"Anna Hoevestraat 4",
    "sg:city":"Brielle",
    "sg:orig_category":"Kinderopvang Behalve Thuis",
    "sg:phone":"+31 181 415 880",
    "sg:postcode":"3232 VC",
    "sg:province":"South Holland",
    "wof:name":"Kinderopvang Stichting Doerak",
    "wof:placetype":"venue"
},
  "geometry": {"coordinates":[4.150577,51.902184],"type":"Point"}
}