{
  "type": "Feature",
  "properties": {
    "addr:full":"T Dorp 33 Heesch Noord-Brabant 5384 MB",
    "addr:housenumber":"33",
    "addr:postcode":"5384 mb",
    "addr:street":"T Dorp",
    "iso:country":"NL",
    "sg:address":"T Dorp 33",
    "sg:city":"Heesch",
    "sg:orig_category":"Loodgieters",
    "sg:phone":"+31 412 452 004",
    "sg:postcode":"5384 MB",
    "sg:province":"Noord-Brabant",
    "wof:name":"Dijk, J Van",
    "wof:placetype":"venue"
},
  "geometry": {"coordinates":[5.530458,51.735565],"type":"Point"}
}