{
  "type": "Feature",
  "properties": {
    "addr:full":"Prins Hendrikstraat 99 Alphen A/D Rijn South Holland 2405 AH",
    "addr:housenumber":"99",
    "addr:postcode":"2405 ah",
    "addr:street":"Prins Hendrikstraat",
    "iso:country":"NL",
    "sg:address":"Prins Hendrikstraat 99",
    "sg:city":"Alphen A/D Rijn",
    "sg:orig_category":"Muziekinstrumenten",
    "sg:phone":"+31 172 494 977",
    "sg:postcode":"2405 AH",
    "sg:province":"South Holland",
    "wof:name":"Muziekhandel City Music",
    "wof:placetype":"venue"
},
  "geometry": {"coordinates":[4.662338,52.123745],"type":"Point"}
}