{
  "type": "Feature",
  "properties": {
    "addr:full":"Cantateln 6 Nieuwegein Utrecht 3438 TW",
    "addr:housenumber":"6",
    "addr:postcode":"3438 tw",
    "addr:street":"Cantateln",
    "iso:country":"NL",
    "sg:address":"Cantateln 6",
    "sg:city":"Nieuwegein",
    "sg:orig_category":"Adviesbureaus Bouwkunde",
    "sg:phone":"+31 30 603 4795",
    "sg:postcode":"3438 TW",
    "sg:province":"Utrecht",
    "wof:name":"Avo",
    "wof:placetype":"venue"
},
  "geometry": {"coordinates":[5.082197,52.027325],"type":"Point"}
}