{
  "type": "Feature",
  "properties": {
    "addr:full":"Morelgaarde 18 Nieuwegein Utrecht 3436 GE",
    "addr:housenumber":"18",
    "addr:postcode":"3436",
    "addr:street":"Morelgaarde",
    "iso:country":"NL",
    "sg:address":"Morelgaarde 18",
    "sg:city":"Nieuwegein",
    "sg:orig_category":"Werving And Selectie Van Vast Personeel",
    "sg:phone":"+31 6 21976882",
    "sg:postcode":"3436 GE",
    "sg:province":"Utrecht",
    "wof:name":"Langenberg Loopbaandienstverlening",
    "wof:placetype":"venue"
},
  "geometry": {"coordinates":[5.0711159706,52.0332984924],"type":"Point"}
}