{
  "type": "Feature",
  "properties": {
    "addr:full":"Stadhouderslaan 19 Hilversum North Holland 1213 AG",
    "addr:housenumber":"19",
    "addr:postcode":"1213",
    "addr:street":"Stadhouderslaan",
    "iso:country":"NL",
    "sg:address":"Stadhouderslaan 19",
    "sg:city":"Hilversum",
    "sg:orig_category":"Marktonderzoekbureaus",
    "sg:phone":"+31 35 621 8300",
    "sg:postcode":"1213 AG",
    "sg:province":"North Holland",
    "wof:name":"Idetra Bv",
    "wof:placetype":"venue"
},
  "geometry": {"coordinates":[5.186378,52.217876],"type":"Point"}
}