{
  "type": "Feature",
  "properties": {
    "iso:country":"NL",
    "sg:address":"Brouwerstr 4",
    "sg:city":"Uden",
    "sg:orig_category":"Meubellakkerijen En -Spuiterijen",
    "sg:phone":"+31 413 263 645",
    "sg:postcode":"5405 BK",
    "sg:province":"Noord-Brabant",
    "wof:name":"Kanto",
    "wof:placetype":"venue"
},
  "geometry": {"coordinates":[5.648987,51.654175],"type":"Point"}
}