{
  "type": "Feature",
  "properties": {
    "addr:full":"Hillegomstr 12 Amsterdam Noord-Holland 1058 LS",
    "addr:housenumber":"12",
    "addr:postcode":"1058 ls",
    "addr:street":"Hillegomstr",
    "iso:country":"NL",
    "sg:address":"Hillegomstr 12",
    "sg:city":"Amsterdam",
    "sg:orig_category":"Adviesbureaus Bedrijfsorganisatie",
    "sg:phone":"+31 20 615 7492",
    "sg:postcode":"1058 LS",
    "sg:province":"Noord-Holland",
    "sg:website":"http://www.research-network.nl",
    "wof:name":"Research Network",
    "wof:placetype":"venue"
},
  "geometry": {"coordinates":[4.848558,52.35231],"type":"Point"}
}