{
  "type": "Feature",
  "properties": {
    "addr:full":"Woerdsestr 4A Ressen Gem Nymegen Gelderland 6683 GD",
    "addr:housenumber":"4a",
    "addr:postcode":"6683 gd",
    "addr:street":"Woerdsestr;Gelderland",
    "iso:country":"NL",
    "sg:address":"Woerdsestr 4A",
    "sg:city":"Ressen Gem Nymegen",
    "sg:orig_category":"Bloemen En Planten - Groothandel",
    "sg:phone":"+31 481 462 096",
    "sg:postcode":"6683 GD",
    "sg:province":"Gelderland",
    "wof:name":"Schouten & Marwijk Vof",
    "wof:placetype":"venue"
},
  "geometry": {"coordinates":[5.860094,51.888256],"type":"Point"}
}