{
  "type": "Feature",
  "properties": {
    "iso:country":"NL",
    "sg:address":"Den Uitvanck 10",
    "sg:city":"Oirschot",
    "sg:orig_category":"Fotostudio'S And Fotografen",
    "sg:phone":"+31 499 572 407",
    "sg:postcode":"5688 XG",
    "sg:province":"Noord-Brabant",
    "wof:name":"Andre Wouters Fotografie",
    "wof:placetype":"venue"
},
  "geometry": {"coordinates":[5.335477,51.501762],"type":"Point"}
}