{
  "type": "Feature",
  "properties": {
    "iso:country":"NL",
    "sg:address":"Herenstraat 24",
    "sg:city":"Domburg",
    "sg:classifiers":[
        {
            "category":"Travel",
            "subcategory":"Hotels & Motels",
            "type":"Entertainment"
        }
    ],
    "sg:phone":"+31 118 581 684",
    "sg:postcode":"4357 AL",
    "sg:province":"Zeeland",
    "wof:name":"Apart Hotel Bommelje",
    "wof:placetype":"venue"
},
  "geometry": {"coordinates":[3.493834,51.56332],"type":"Point"}
}