{
  "type": "Feature",
  "properties": {
    "iso:country":"NL",
    "sg:address":"Troelstrastr 3",
    "sg:city":"Alblasserdam",
    "sg:orig_category":"Schilders",
    "sg:phone":"+31 78 691 7808",
    "sg:postcode":"2953 BK",
    "sg:province":"Zuid-Holland",
    "wof:name":"Berkhoudt, P",
    "wof:placetype":"venue"
},
  "geometry": {"coordinates":[4.653246,51.869621],"type":"Point"}
}