{
  "type": "Feature",
  "properties": {
    "iso:country":"NL",
    "sg:address":"Hezelaar 2",
    "sg:city":"Gemert",
    "sg:orig_category":"Onderzoekbureaus",
    "sg:phone":"+31 492 363 406",
    "sg:postcode":"5422 BX",
    "sg:province":"North Brabant",
    "wof:name":"Thelen Bureau",
    "wof:placetype":"venue"
},
  "geometry": {"coordinates":[5.701816,51.555794],"type":"Point"}
}