{
  "type": "Feature",
  "properties": {
    "addr:full":"Hezelaar 2 Gemert North Brabant 5422 BX",
    "addr:housenumber":"2",
    "addr:postcode":"5422 bx",
    "addr:street":"Hezelaar",
    "iso:country":"NL",
    "sg:address":"Hezelaar 2",
    "sg:city":"Gemert",
    "sg:orig_category":"Onderzoekbureaus",
    "sg:phone":"+31 492 363 406",
    "sg:postcode":"5422 BX",
    "sg:province":"North Brabant",
    "wof:name":"Thelen Bureau",
    "wof:placetype":"venue"
},
  "geometry": {"coordinates":[5.701816,51.555794],"type":"Point"}
}