{
  "type": "Feature",
  "properties": {
    "addr:full":"Oudewand 13 Zutphen Gelderland 7201 LJ",
    "addr:housenumber":"13;lj",
    "addr:postcode":"7201",
    "addr:street":"Oudewand;Gelderland",
    "iso:country":"NL",
    "sg:address":"Oudewand 13",
    "sg:city":"Zutphen",
    "sg:orig_category":"Acupunctuur",
    "sg:phone":"+31 575 546 826",
    "sg:postcode":"7201 LJ",
    "sg:province":"Gelderland",
    "wof:name":"Velthuis, R A W",
    "wof:placetype":"venue"
},
  "geometry": {"coordinates":[6.197248,52.142578],"type":"Point"}
}