{
  "type": "Feature",
  "properties": {
    "addr:full":"Postbus 226 Etten Leur 4870 AE",
    "addr:housenumber":"226",
    "addr:postcode":"4870 ae",
    "addr:street":"Postbus;Leur",
    "iso:country":"NL",
    "sg:address":"Postbus 226",
    "sg:city":"Etten Leur",
    "sg:orig_category":"Webdesign Bureaus",
    "sg:phone":"+31 76 526 3374",
    "sg:postcode":"4870 AE",
    "sg:website":"http://www.blauwvis.nl",
    "wof:name":"Blauwvis Webdesign",
    "wof:placetype":"venue"
},
  "geometry": {"coordinates":[4.6395220757,51.5706939697],"type":"Point"}
}