{
  "type": "Feature",
  "properties": {
    "addr:full":"Past Hendrikspk 51 Laren Nh Noord-Holland 1251 MC",
    "addr:housenumber":"51",
    "addr:postcode":"1251 mc",
    "iso:country":"NL",
    "sg:address":"Past Hendrikspk 51",
    "sg:city":"Laren Nh",
    "sg:orig_category":"Ziekenhuizen, Sanatoria, Verpleeghuizen",
    "sg:phone":"+31 35 539 1926",
    "sg:postcode":"1251 MC",
    "sg:province":"Noord-Holland",
    "wof:name":"Janshuis",
    "wof:placetype":"venue"
},
  "geometry": {"coordinates":[5.231612,52.2547],"type":"Point"}
}