{
  "type": "Feature",
  "properties": {
    "iso:country":"NL",
    "sg:address":"Rensgars 10",
    "sg:city":"Schagen",
    "sg:orig_category":"Makelaars En Adviseurs Onroerende Goederen",
    "sg:phone":"+31 224 274 757",
    "sg:postcode":"1741 BR",
    "sg:province":"North Holland",
    "wof:name":"Holland Noord Bv",
    "wof:placetype":"venue"
},
  "geometry": {"coordinates":[4.795715,52.786163],"type":"Point"}
}