{
  "type": "Feature",
  "properties": {
    "addr:full":"Industriepk 3/2 Leek Groningen 9351 PA",
    "addr:housenumber":"3 / 2",
    "addr:postcode":"9351 pa",
    "addr:street":"Industriepk",
    "iso:country":"NL",
    "sg:address":"Industriepk 3/2",
    "sg:city":"Leek",
    "sg:orig_category":"Autopoetsbedrijven",
    "sg:phone":"+31 594 518 254",
    "sg:postcode":"9351 PA",
    "sg:province":"Groningen",
    "wof:name":"Zaagman",
    "wof:placetype":"venue"
},
  "geometry": {"coordinates":[6.377585,53.168102],"type":"Point"}
}