{
  "type": "Feature",
  "properties": {
    "addr:full":"Lindenstr 19 S Gravenzande Zuid-Holland 2691 DP",
    "addr:housenumber":"19;gravenzande",
    "addr:postcode":"2691 dp",
    "addr:street":"Lindenstr;S",
    "iso:country":"NL",
    "sg:address":"Lindenstr 19",
    "sg:city":"S Gravenzande",
    "sg:orig_category":"Kassenbouw",
    "sg:phone":"+31 174 413 703",
    "sg:postcode":"2691 DP",
    "sg:province":"Zuid-Holland",
    "wof:name":"Wissenburg, W C",
    "wof:placetype":"venue"
},
  "geometry": {"coordinates":[4.166579,51.998497],"type":"Point"}
}