{
  "type": "Feature",
  "properties": {
    "iso:country":"NL",
    "sg:address":"Poolster 40",
    "sg:city":"Oostburg",
    "sg:orig_category":"Verzekeringen",
    "sg:phone":"+31 117 453 563",
    "sg:postcode":"4501 GN",
    "sg:province":"Zeeland",
    "wof:name":"Assuvis",
    "wof:placetype":"venue"
},
  "geometry": {"coordinates":[3.50076,51.324753],"type":"Point"}
}