{
  "type": "Feature",
  "properties": {
    "addr:full":"5E Industriestraat 31 Vlaardingen Zuid-Holland 3133 EL",
    "addr:housenumber":"31",
    "addr:postcode":"3133 el",
    "addr:street":"5E Industriestraat",
    "iso:country":"NL",
    "sg:address":"5E Industriestraat 31",
    "sg:city":"Vlaardingen",
    "sg:orig_category":"Autokeuringen",
    "sg:phone":"+31 10 434 7574",
    "sg:postcode":"3133 EL",
    "sg:province":"Zuid-Holland",
    "wof:name":"Timmers Autoschade",
    "wof:placetype":"venue"
},
  "geometry": {"coordinates":[4.328856,51.90382],"type":"Point"}
}