{
  "type": "Feature",
  "properties": {
    "addr:full":"Molenweg 12 Eibergen Gelderland 7151 HA",
    "addr:housenumber":"12",
    "addr:postcode":"7151 ha",
    "addr:street":"Molenweg;Gelderland",
    "iso:country":"NL",
    "sg:address":"Molenweg 12",
    "sg:city":"Eibergen",
    "sg:orig_category":"Hoefdierhouderijen",
    "sg:phone":"+31 545 475 666",
    "sg:postcode":"7151 HA",
    "sg:province":"Gelderland",
    "wof:name":"Handelsstal E. Reesink",
    "wof:placetype":"venue"
},
  "geometry": {"coordinates":[6.616251,52.073635],"type":"Point"}
}