{
  "type": "Feature",
  "properties": {
    "addr:full":"Tolwg 4 Baarn Utrecht 3741 LK",
    "addr:housenumber":"4",
    "addr:postcode":"3741 lk",
    "addr:street":"Tolwg",
    "iso:country":"NL",
    "sg:address":"Tolwg 4",
    "sg:city":"Baarn",
    "sg:orig_category":"Fotoapparatuur En -Artikelen - Groothandel",
    "sg:phone":"+31 35 541 8094",
    "sg:postcode":"3741 LK",
    "sg:province":"Utrecht",
    "wof:name":"Technotape Int Bv",
    "wof:placetype":"venue"
},
  "geometry": {"coordinates":[5.301223,52.215298],"type":"Point"}
}