{
  "type": "Feature",
  "properties": {
    "addr:full":"De Rietvink 12 Heiloo North Holland 1852 RM",
    "addr:housenumber":"12",
    "addr:postcode":"1852 rm",
    "addr:street":"De Rietvink",
    "iso:country":"NL",
    "sg:address":"De Rietvink 12",
    "sg:city":"Heiloo",
    "sg:orig_category":"Makelaars In Onroerend Goed",
    "sg:phone":"+31 72 532 1721",
    "sg:postcode":"1852 RM",
    "sg:province":"North Holland",
    "wof:name":"Domein Vastgoed Advies",
    "wof:placetype":"venue"
},
  "geometry": {"coordinates":[4.68614,52.608501],"type":"Point"}
}