{
  "type": "Feature",
  "properties": {
    "iso:country":"NL",
    "sg:address":"Ryksstrwg 21",
    "sg:city":"Heemskerk",
    "sg:orig_category":"Verzekeringen - Verzekeringskantoren",
    "sg:phone":"+31 251 252 921",
    "sg:postcode":"1969 LB",
    "sg:province":"North Holland",
    "wof:name":"Enfa",
    "wof:placetype":"venue"
},
  "geometry": {"coordinates":[4.626871,52.507214],"type":"Point"}
}