{
  "type": "Feature",
  "properties": {
    "addr:full":"Zeeburgerpad 81 Amsterdam North Holland 1019 AD",
    "addr:housenumber":"81",
    "addr:postcode":"1019 ad",
    "addr:street":"Zeeburgerpad",
    "iso:country":"NL",
    "sg:address":"Zeeburgerpad 81",
    "sg:city":"Amsterdam",
    "sg:orig_category":"Autokeuringen",
    "sg:phone":"+31 20 665 3663",
    "sg:postcode":"1019 AD",
    "sg:province":"North Holland",
    "wof:name":"Oost Automobielen",
    "wof:placetype":"venue"
},
  "geometry": {"coordinates":[4.943242,52.367062],"type":"Point"}
}