{
  "type": "Feature",
  "properties": {
    "iso:country":"NL",
    "sg:address":"De Eendracht 2",
    "sg:city":"Amstelveen",
    "sg:orig_category":"Kunst And Kunstenaarsbenodigdheden",
    "sg:phone":"+31 20 679 1901",
    "sg:postcode":"1188 GS",
    "sg:province":"Noord-Holland",
    "wof:name":"Salomon Int Dutch Artists",
    "wof:placetype":"venue"
},
  "geometry": {"coordinates":[4.849717,52.279015],"type":"Point"}
}