{
  "type": "Feature",
  "properties": {
    "iso:country":"NL",
    "sg:address":"Dukdalf 1C",
    "sg:city":"Wyk By Duurstede",
    "sg:orig_category":"Administratie- En Boekhoudkantoren",
    "sg:phone":"+31 343 591 960",
    "sg:postcode":"3961 LA",
    "sg:province":"Utrecht",
    "sg:website":"http://www.chevre.nl",
    "wof:name":"Ch\u00e8vre Administratie",
    "wof:placetype":"venue"
},
  "geometry": {"coordinates":[5.327503,51.973885],"type":"Point"}
}