{
  "type": "Feature",
  "properties": {
    "addr:full":"Reinaldstraat 95 Velp Gld Gelderland 6883 HL",
    "addr:housenumber":"95",
    "addr:postcode":"6883 hl",
    "addr:street":"Reinaldstraat;Gld Gelderland",
    "iso:country":"NL",
    "sg:address":"Reinaldstraat 95",
    "sg:city":"Velp Gld",
    "sg:orig_category":"Architecten",
    "sg:phone":"+31 26 363 7444",
    "sg:postcode":"6883 HL",
    "sg:province":"Gelderland",
    "wof:name":"P. Kranendonk",
    "wof:placetype":"venue"
},
  "geometry": {"coordinates":[5.981043,51.991734],"type":"Point"}
}