{
  "type": "Feature",
  "properties": {
    "iso:country":"NL",
    "sg:address":"Snipweg 20",
    "sg:city":"Apeldoorn",
    "sg:orig_category":"Kappers",
    "sg:phone":"+31 55 533 3222",
    "sg:postcode":"7331 LV",
    "sg:province":"Gelderland",
    "wof:name":"Dameskapsalon Maison Harry",
    "wof:placetype":"venue"
},
  "geometry": {"coordinates":[5.9726390839,52.1979827881],"type":"Point"}
}