{
  "type": "Feature",
  "properties": {
    "addr:full":"Vredenhofstraat 7 Haarlem Noord-Holland 2012 MD",
    "addr:housenumber":"7",
    "addr:postcode":"2012",
    "addr:street":"Vredenhofstraat",
    "iso:country":"NL",
    "sg:address":"Vredenhofstraat 7",
    "sg:city":"Haarlem",
    "sg:orig_category":"Bioscopen",
    "sg:phone":"+31 23 531 4067",
    "sg:postcode":"2012 MD",
    "sg:province":"Noord-Holland",
    "wof:name":"Firefox Film Organization",
    "wof:placetype":"venue"
},
  "geometry": {"coordinates":[4.616942,52.367916],"type":"Point"}
}