{
  "type": "Feature",
  "properties": {
    "addr:full":"Medelsestraat 13 Tiel Gelderland 4005 VA",
    "addr:housenumber":"13",
    "addr:postcode":"4005",
    "addr:street":"Medelsestraat;Gelderland",
    "iso:country":"NL",
    "sg:address":"Medelsestraat 13",
    "sg:city":"Tiel",
    "sg:orig_category":"Fotostudio'S And Fotografen",
    "sg:phone":"+31 344 616 296",
    "sg:postcode":"4005 VA",
    "sg:province":"Gelderland",
    "wof:name":"Foto Jan Bouwhuis",
    "wof:placetype":"venue"
},
  "geometry": {"coordinates":[5.442098,51.895596],"type":"Point"}
}