{
  "type": "Feature",
  "properties": {
    "addr:full":"Van Der Meerstraat 11 Heythuysen Limburg 6093 BE",
    "addr:housenumber":"11",
    "addr:postcode":"6093",
    "addr:street":"Van Der Meerstraat",
    "iso:country":"NL",
    "sg:address":"Van Der Meerstraat 11",
    "sg:city":"Heythuysen",
    "sg:orig_category":"Diverse Artikelen Fab",
    "sg:phone":"+31 475 495 195",
    "sg:postcode":"6093 BE",
    "sg:province":"Limburg",
    "wof:name":"S Blackshaw",
    "wof:placetype":"venue"
},
  "geometry": {"coordinates":[5.893185,51.245354],"type":"Point"}
}