{
  "type": "Feature",
  "properties": {
    "addr:full":"L Nobelstr 43 Zierikzee Zeeland 4301 HD",
    "addr:housenumber":"43",
    "addr:postcode":"4301 hd",
    "iso:country":"NL",
    "sg:address":"L Nobelstr 43",
    "sg:city":"Zierikzee",
    "sg:orig_category":"Meel - Fabrieken En Groothandel",
    "sg:phone":"+31 111 416 700",
    "sg:postcode":"4301 HD",
    "sg:province":"Zeeland",
    "wof:name":"Molen De Hoop Vof",
    "wof:placetype":"venue"
},
  "geometry": {"coordinates":[3.920082,51.652069],"type":"Point"}
}