{
  "type": "Feature",
  "properties": {
    "addr:full":"Stevinstr 210212 S Gravenhage Noord-Holland 2587 EV",
    "addr:housenumber":"210212",
    "addr:street":"S Gravenhage",
    "iso:country":"NL",
    "sg:address":"Stevinstr 210212",
    "sg:city":"S Gravenhage",
    "sg:orig_category":"Behangselpapier En Wandbekleding",
    "sg:phone":"+31 70 355 6728",
    "sg:postcode":"2587 EV",
    "sg:province":"Noord-Holland",
    "wof:name":"Haco Stevin",
    "wof:placetype":"venue"
},
  "geometry": {"coordinates":[4.29118,52.112942],"type":"Point"}
}