{
  "type": "Feature",
  "properties": {
    "addr:full":"C Houtmanstr 25 Bunschoten Spakenb Utrecht 3752 XE",
    "addr:housenumber":"25",
    "addr:postcode":"3752 xe",
    "addr:street":"Houtmanstr",
    "iso:country":"NL",
    "sg:address":"C Houtmanstr 25",
    "sg:city":"Bunschoten Spakenb",
    "sg:classifiers":[
        {
            "category":"Farming",
            "subcategory":"Fish & Marine Products",
            "type":"Manufacturing & Wholesale Goods"
        }
    ],
    "sg:phone":"+31 33 298 4248",
    "sg:postcode":"3752 XE",
    "sg:province":"Utrecht",
    "sg:tags":[
        "vi"
    ],
    "wof:name":"Duijst, J",
    "wof:placetype":"venue"
},
  "geometry": {"coordinates":[5.369293,52.234268],"type":"Point"}
}