{
  "type": "Feature",
  "properties": {
    "addr:full":"Hendrick De Keyserlaan 23 Hilversum North Holland 1222 NE",
    "addr:housenumber":"23",
    "addr:postcode":"1222 ne",
    "addr:street":"Hendrick De Keyserlaan",
    "iso:country":"NL",
    "sg:address":"Hendrick De Keyserlaan 23",
    "sg:city":"Hilversum",
    "sg:orig_category":"Loodgieterswerk, Verwarming And Sanitaire Installaties",
    "sg:phone":"+31 35 685 0665",
    "sg:postcode":"1222 NE",
    "sg:province":"North Holland",
    "wof:name":"J. De Ridder",
    "wof:placetype":"venue"
},
  "geometry": {"coordinates":[5.185021,52.234898],"type":"Point"}
}