{
  "type": "Feature",
  "properties": {
    "addr:full":"Verlengde Stationsweg 8 Zuidlaren Drenthe 9471 PL",
    "addr:housenumber":"8",
    "addr:postcode":"9471 pl",
    "addr:street":"Verlengde Stationsweg",
    "iso:country":"NL",
    "sg:address":"Verlengde Stationsweg 8",
    "sg:city":"Zuidlaren",
    "sg:orig_category":"Meubelzaken, Woning- And Keukeninrichting",
    "sg:phone":"+31 50 409 3607",
    "sg:postcode":"9471 PL",
    "sg:province":"Drenthe",
    "wof:name":"Meubelfabriek Oisterwijk",
    "wof:placetype":"venue"
},
  "geometry": {"coordinates":[6.664274,53.088459],"type":"Point"}
}