{
  "type": "Feature",
  "properties": {
    "addr:full":"Prinsengr 604 Amsterdam Noord-Holland 1017 KS",
    "addr:housenumber":"604",
    "addr:postcode":"1017 ks",
    "iso:country":"NL",
    "sg:address":"Prinsengr 604",
    "sg:city":"Amsterdam",
    "sg:orig_category":"Adviesbureaus Bouwkunde",
    "sg:phone":"+31 20 623 8483",
    "sg:postcode":"1017 KS",
    "sg:province":"Noord-Holland",
    "wof:name":"Adviplan Bouwadvisering",
    "wof:placetype":"venue"
},
  "geometry": {"coordinates":[4.889522,52.362171],"type":"Point"}
}