{
  "type": "Feature",
  "properties": {
    "addr:full":"Noordvliet 48 Maassluis South Holland 3142 CM",
    "addr:housenumber":"48",
    "addr:postcode":"3142 cm",
    "addr:street":"Noordvliet",
    "iso:country":"NL",
    "sg:address":"Noordvliet 48",
    "sg:city":"Maassluis",
    "sg:orig_category":"Kinderopvang Behalve Thuis",
    "sg:phone":"+31 10 591 0581",
    "sg:postcode":"3142 CM",
    "sg:province":"South Holland",
    "wof:name":"Stichting Kinderopvang Maassluis",
    "wof:placetype":"venue"
},
  "geometry": {"coordinates":[4.256454,51.922901],"type":"Point"}
}