{
  "type": "Feature",
  "properties": {
    "addr:full":"Soendastraat 4 'S Gravenhage South Holland 2585 VD",
    "addr:housenumber":"4 '",
    "addr:postcode":"2585 vd",
    "addr:street":"Soendastraat",
    "iso:country":"NL",
    "sg:address":"Soendastraat 4",
    "sg:city":"'S Gravenhage",
    "sg:orig_category":"Artsen And Specialisten",
    "sg:phone":"+31 70 354 0522",
    "sg:postcode":"2585 VD",
    "sg:province":"South Holland",
    "wof:name":"Drs. L.M.A.D. Pesch",
    "wof:placetype":"venue"
},
  "geometry": {"coordinates":[4.30402,52.091629],"type":"Point"}
}