{
  "type": "Feature",
  "properties": {
    "iso:country":"NL",
    "sg:address":"Vaart 11",
    "sg:city":"Gorinchem",
    "sg:orig_category":"Loodgieters",
    "sg:phone":"+31 183 301 394",
    "sg:postcode":"4206 CC",
    "sg:province":"South Holland",
    "wof:name":"Nuvelstijn Vof",
    "wof:placetype":"venue"
},
  "geometry": {"coordinates":[4.988839,51.849869],"type":"Point"}
}