{
  "type": "Feature",
  "properties": {
    "addr:full":"Kr Elleboog 64 Haren Gn Groningen 9751 RE",
    "addr:housenumber":"64",
    "addr:postcode":"9751 re",
    "addr:street":"Kr Elleboog",
    "iso:country":"NL",
    "sg:address":"Kr Elleboog 64",
    "sg:city":"Haren Gn",
    "sg:orig_category":"Hypotheken",
    "sg:phone":"+31 50 534 1019",
    "sg:postcode":"9751 RE",
    "sg:province":"Groningen",
    "sg:website":"http://www.ridderbos.nl",
    "wof:name":"Ridderbos",
    "wof:placetype":"venue"
},
  "geometry": {"coordinates":[6.60632,53.170658],"type":"Point"}
}