{
  "type": "Feature",
  "properties": {
    "iso:country":"NL",
    "sg:address":"Nieuweweg 5",
    "sg:city":"Groningen",
    "sg:orig_category":"Kantoorartikelen",
    "sg:phone":"+31 50 312 6218",
    "sg:postcode":"9711 TA",
    "sg:province":"Groningen",
    "wof:name":"Boekhandel Edzes Bv",
    "wof:placetype":"venue"
},
  "geometry": {"coordinates":[6.5738019943,53.2182731628],"type":"Point"}
}