{
  "type": "Feature",
  "properties": {
    "iso:country":"NL",
    "sg:address":"Kapellerlaan 148",
    "sg:city":"Roermond",
    "sg:orig_category":"Medische Apparatuur And Prothesen Fab",
    "sg:phone":"+31 475 315 080",
    "sg:postcode":"6045 AJ",
    "sg:province":"Limburg",
    "wof:name":"Tandtechnisch Laboratorium J.B.H.B. Vaes",
    "wof:placetype":"venue"
},
  "geometry": {"coordinates":[5.995758,51.182335],"type":"Point"}
}