{
  "type": "Feature",
  "properties": {
    "addr:full":"De Vyf Boeken 1E Nieuwerkerk Yssel Zuid-Holland 2911 BL",
    "addr:housenumber":"1e",
    "addr:postcode":"2911 bl",
    "iso:country":"NL",
    "sg:address":"De Vyf Boeken 1E",
    "sg:city":"Nieuwerkerk Yssel",
    "sg:orig_category":"Verpakkingsbedrijven",
    "sg:phone":"+31 180 331 166",
    "sg:postcode":"2911 BL",
    "sg:province":"Zuid-Holland",
    "wof:name":"Velca-Pack",
    "wof:placetype":"venue"
},
  "geometry": {"coordinates":[4.62252,51.959648],"type":"Point"}
}