{
  "type": "Feature",
  "properties": {
    "addr:full":"Nyverheidsstr 16 Kerkdriel Gelderland 5331 PT",
    "addr:housenumber":"16",
    "addr:postcode":"5331",
    "addr:street":"Nyverheidsstr;Gelderland;Pt",
    "iso:country":"NL",
    "sg:address":"Nyverheidsstr 16",
    "sg:city":"Kerkdriel",
    "sg:orig_category":"Oud Metaal",
    "sg:phone":"+31 418 631 327",
    "sg:postcode":"5331 PT",
    "sg:province":"Gelderland",
    "wof:name":"Duijts, Herman",
    "wof:placetype":"venue"
},
  "geometry": {"coordinates":[5.3236651421,51.7725486755],"type":"Point"}
}