{
  "type": "Feature",
  "properties": {
    "addr:full":"Lobeliastraat 45 Ittervoort Limburg 6014 BV",
    "addr:housenumber":"45",
    "addr:postcode":"6014 bv",
    "addr:street":"Lobeliastraat",
    "iso:country":"NL",
    "sg:address":"Lobeliastraat 45",
    "sg:city":"Ittervoort",
    "sg:orig_category":"Boekhouders",
    "sg:phone":"+31 475 565 464",
    "sg:postcode":"6014 BV",
    "sg:province":"Limburg",
    "wof:name":"Fa. Coenen, Adm.- Belastingadviesburo",
    "wof:placetype":"venue"
},
  "geometry": {"coordinates":[5.816805,51.17149],"type":"Point"}
}