{
  "type": "Feature",
  "properties": {
    "addr:full":"Nieuwstraat 2 Schagen North Holland 1741 BT",
    "addr:housenumber":"2",
    "addr:postcode":"1741 bt",
    "addr:street":"Nieuwstraat",
    "iso:country":"NL",
    "sg:address":"Nieuwstraat 2",
    "sg:city":"Schagen",
    "sg:orig_category":"Banken And Kredietinstellingen",
    "sg:phone":"+31 224 214 544",
    "sg:postcode":"1741 BT",
    "sg:province":"North Holland",
    "wof:name":"Ing Bank",
    "wof:placetype":"venue"
},
  "geometry": {"coordinates":[4.797101,52.787083],"type":"Point"}
}