{
  "type": "Feature",
  "properties": {
    "addr:full":"Postbus 438 Leiden Zuid-Holland 2300 AK",
    "addr:housenumber":"438",
    "addr:postcode":"2300 ak",
    "addr:street":"Postbus",
    "iso:country":"NL",
    "sg:address":"Postbus 438",
    "sg:city":"Leiden",
    "sg:orig_category":"Scheepssleep- En Duwvaart",
    "sg:phone":"+31 6 53294887",
    "sg:postcode":"2300 AK",
    "sg:province":"Zuid-Holland",
    "wof:name":"Groenen Sleepdienst",
    "wof:placetype":"venue"
},
  "geometry": {"coordinates":[4.49015,52.161091],"type":"Point"}
}