{
  "type": "Feature",
  "properties": {
    "addr:full":"Koewei 24 Arnhem Gelderland 6843 ZK",
    "addr:housenumber":"24",
    "addr:postcode":"6843",
    "addr:street":"Koewei;Zk",
    "iso:country":"NL",
    "sg:address":"Koewei 24",
    "sg:city":"Arnhem",
    "sg:orig_category":"Juridische Dienstverlening",
    "sg:phone":"+31 26 381 4244",
    "sg:postcode":"6843 ZK",
    "sg:province":"Gelderland",
    "wof:name":"Rechtskundigadviesbureau Mr C J Resink",
    "wof:placetype":"venue"
},
  "geometry": {"coordinates":[5.865367,51.965469],"type":"Point"}
}