{
  "type": "Feature",
  "properties": {
    "iso:country":"NL",
    "sg:address":"Tasveld 15",
    "sg:city":"Montfoort",
    "sg:orig_category":"Verpakkingen En Verpakkingsmaterialen",
    "sg:phone":"+31 348 475 045",
    "sg:postcode":"3417 XS",
    "sg:province":"Utrecht",
    "wof:name":"Flex-Film Int Bv",
    "wof:placetype":"venue"
},
  "geometry": {"coordinates":[4.932576,52.045422],"type":"Point"}
}