{
  "type": "Feature",
  "properties": {
    "addr:full":"Daalder 9 Deurne Noord-Brabant 5753 SZ",
    "addr:housenumber":"9",
    "addr:postcode":"5753 sz",
    "addr:street":"Daalder",
    "iso:country":"NL",
    "sg:address":"Daalder 9",
    "sg:city":"Deurne",
    "sg:orig_category":"Product-Promotie",
    "sg:phone":"+31 493 316 469",
    "sg:postcode":"5753 SZ",
    "sg:province":"Noord-Brabant",
    "wof:name":"Movico Bv",
    "wof:placetype":"venue"
},
  "geometry": {"coordinates":[5.771695,51.457874],"type":"Point"}
}