{
  "type": "Feature",
  "properties": {
    "addr:full":"Salamanderveen 352 Spijkenisse Zuid-Holland 3205 TG",
    "addr:housenumber":"352",
    "addr:postcode":"3205 tg",
    "addr:street":"Salamanderveen",
    "iso:country":"NL",
    "sg:address":"Salamanderveen 352",
    "sg:city":"Spijkenisse",
    "sg:classifiers":[
        {
            "category":"Education",
            "subcategory":"Preschool",
            "type":"Public Place"
        }
    ],
    "sg:phone":"+31 181 635 634",
    "sg:postcode":"3205 TG",
    "sg:province":"Zuid-Holland",
    "sg:tags":[
        "kleuteronderwijs",
        "basis-"
    ],
    "wof:name":"Montessorischool Spijkenisse",
    "wof:placetype":"venue"
},
  "geometry": {"coordinates":[4.338404,51.83411],"type":"Point"}
}