{
  "type": "Feature",
  "properties": {
    "addr:full":"Rietveldenwg 41B S Hertogenbosch Noord-Brabant 5222 AP",
    "addr:housenumber":"41b",
    "addr:postcode":"5222 ap",
    "addr:street":"Rietveldenwg;S Hertogenbosch",
    "iso:country":"NL",
    "sg:address":"Rietveldenwg 41B",
    "sg:city":"S Hertogenbosch",
    "sg:orig_category":"Mobiele- En Autotelefoons",
    "sg:phone":"+31 73 621 6388",
    "sg:postcode":"5222 AP",
    "sg:province":"Noord-Brabant",
    "sg:website":"http://www.vitec.nl",
    "wof:name":"Vitec Callstore",
    "wof:placetype":"venue"
},
  "geometry": {"coordinates":[5.271269,51.703678],"type":"Point"}
}