{
  "type": "Feature",
  "properties": {
    "iso:country":"NL",
    "sg:address":"Zevenhuizerlaan 59",
    "sg:city":"Heiloo",
    "sg:orig_category":"Kappers",
    "sg:phone":"+31 72 533 1928",
    "sg:postcode":"1851 MS",
    "sg:province":"North Holland",
    "wof:name":"Dames-En Heren Kapsalon Bijwaard",
    "wof:placetype":"venue"
},
  "geometry": {"coordinates":[4.700428009,52.5944747925],"type":"Point"}
}