{
  "type": "Feature",
  "properties": {
    "addr:full":"Una-Corda 34 Krimpen A/D Ijssel South Holland 2925 BX",
    "addr:housenumber":"34;a / d",
    "addr:postcode":"2925 bx",
    "addr:street":"Una-Corda;Ijssel South",
    "iso:country":"NL",
    "sg:address":"Una-Corda 34",
    "sg:city":"Krimpen A/D Ijssel",
    "sg:classifiers":[
        {
            "category":"Education",
            "subcategory":"Preschool",
            "type":"Public Place"
        }
    ],
    "sg:phone":"+31 180 518 726",
    "sg:postcode":"2925 BX",
    "sg:province":"South Holland",
    "sg:tags":[
        "kleuteronderwijs",
        "basis-"
    ],
    "wof:name":"Gereformeerde Basisschool Mozaiek Het",
    "wof:placetype":"venue"
},
  "geometry": {"coordinates":[4.610304,51.919785],"type":"Point"}
}