{
  "type": "Feature",
  "properties": {
    "addr:full":"Industrieweg 2 Vorden Gelderland 7251 JT",
    "addr:housenumber":"2",
    "addr:postcode":"7251 jt",
    "addr:street":"Industrieweg;Gelderland",
    "iso:country":"NL",
    "sg:address":"Industrieweg 2",
    "sg:city":"Vorden",
    "sg:orig_category":"Hout Gh",
    "sg:phone":"+31 575 551 216",
    "sg:postcode":"7251 JT",
    "sg:province":"Gelderland",
    "wof:name":"Bijenhof'S Fijnhout Bewerking Bv",
    "wof:placetype":"venue"
},
  "geometry": {"coordinates":[6.326418,52.105526],"type":"Point"}
}