{
  "type": "Feature",
  "properties": {
    "addr:full":"Handelswg 5 Meerkerk Zuid-Holland 4231 EZ",
    "addr:housenumber":"5",
    "addr:postcode":"4231 ez",
    "addr:street":"Handelswg",
    "iso:country":"NL",
    "sg:address":"Handelswg 5",
    "sg:city":"Meerkerk",
    "sg:orig_category":"Kaasgroothandel",
    "sg:phone":"+31 183 353 088",
    "sg:postcode":"4231 EZ",
    "sg:province":"Zuid-Holland",
    "wof:name":"Schep Bv, Nico",
    "wof:placetype":"venue"
},
  "geometry": {"coordinates":[4.9860601425,51.9081687927],"type":"Point"}
}