{
  "type": "Feature",
  "properties": {
    "addr:full":"In De Bogerd 20 Stolwijk South Holland 2821 WZ",
    "addr:housenumber":"20",
    "addr:postcode":"2821 wz",
    "addr:street":"In De Bogerd",
    "iso:country":"NL",
    "sg:address":"In De Bogerd 20",
    "sg:city":"Stolwijk",
    "sg:orig_category":"Woningbouwverenigingen",
    "sg:phone":"+31 182 341 301",
    "sg:postcode":"2821 WZ",
    "sg:province":"South Holland",
    "wof:name":"Woningbouwvereniging Stolwijk",
    "wof:placetype":"venue"
},
  "geometry": {"coordinates":[4.7721791267,51.9727020264],"type":"Point"}
}