{
  "type": "Feature",
  "properties": {
    "addr:full":"Poolster 184 Hoorn Nh Noord-Holland 1622 EM",
    "addr:housenumber":"184",
    "addr:postcode":"1622 em",
    "addr:street":"Poolster",
    "iso:country":"NL",
    "sg:address":"Poolster 184",
    "sg:city":"Hoorn Nh",
    "sg:orig_category":"Beeldende Kunstenaars",
    "sg:phone":"+31 229 218 214",
    "sg:postcode":"1622 EM",
    "sg:province":"Noord-Holland",
    "sg:website":"http://www.ellensmozaiek.com",
    "wof:name":"Ellen",
    "wof:placetype":"venue"
},
  "geometry": {"coordinates":[5.038002,52.63818],"type":"Point"}
}