{
  "type": "Feature",
  "properties": {
    "addr:full":"Raadhuispln 24 Heeswyk Dinther North Brabant 5473 GC",
    "addr:housenumber":"24",
    "addr:postcode":"5473 gc",
    "addr:street":"Raadhuispln",
    "iso:country":"NL",
    "sg:address":"Raadhuispln 24",
    "sg:city":"Heeswyk Dinther",
    "sg:orig_category":"Verenigingen En Stichtingen",
    "sg:phone":"+31 413 294 077",
    "sg:postcode":"5473 GC",
    "sg:province":"North Brabant",
    "wof:name":"Sociaal Cultureel Centrum Servaes",
    "wof:placetype":"venue"
},
  "geometry": {"coordinates":[5.481096,51.647366],"type":"Point"}
}