{
  "type": "Feature",
  "properties": {
    "addr:full":"Heuvelstraat 105 A Tilburg Noord-Brabant 5038 AD",
    "addr:housenumber":"105 a",
    "addr:postcode":"5038 ad",
    "addr:street":"Heuvelstraat",
    "iso:country":"NL",
    "sg:address":"Heuvelstraat 105 A",
    "sg:city":"Tilburg",
    "sg:orig_category":"Discountwinkels",
    "sg:phone":"+31 13 580 1535",
    "sg:postcode":"5038 AD",
    "sg:province":"Noord-Brabant",
    "wof:name":"Wibra Bv",
    "wof:placetype":"venue"
},
  "geometry": {"coordinates":[5.084396,51.555485],"type":"Point"}
}