{
  "type": "Feature",
  "properties": {
    "addr:full":"Kervelweg 4 Helenaveen North Brabant 5759 PN",
    "addr:housenumber":"4",
    "addr:postcode":"5759 pn",
    "addr:street":"Kervelweg",
    "iso:country":"NL",
    "sg:address":"Kervelweg 4",
    "sg:city":"Helenaveen",
    "sg:classifiers":[
        {
            "category":"Food & Beverages",
            "subcategory":"Fruits & Vegetables",
            "type":"Retail Goods"
        }
    ],
    "sg:phone":"+31 493 536 104",
    "sg:postcode":"5759 PN",
    "sg:province":"North Brabant",
    "sg:tags":[
        "groenten"
    ],
    "wof:name":"Veldhuijzen Vof",
    "wof:placetype":"venue"
},
  "geometry": {"coordinates":[5.921482,51.385719],"type":"Point"}
}