{
  "type": "Feature",
  "properties": {
    "addr:full":"Fransekampwg 1 Bennekom Gelderland 6721 MC",
    "addr:housenumber":"1;6721",
    "addr:street":"Fransekampwg;Gelderland;Mc",
    "iso:country":"NL",
    "sg:address":"Fransekampwg 1",
    "sg:city":"Bennekom",
    "sg:orig_category":"Adviesbureaus Bedrijfsorganisatie",
    "sg:phone":"+31 318 415 833",
    "sg:postcode":"6721 MC",
    "sg:province":"Gelderland",
    "wof:name":"Kleisen En Partn Bv",
    "wof:placetype":"venue"
},
  "geometry": {"coordinates":[5.70818,52.005676],"type":"Point"}
}