{
  "type": "Feature",
  "properties": {
    "addr:full":"Matseweg 1 Putten Gelderland 3882 TD",
    "addr:housenumber":"1",
    "addr:postcode":"3882 td",
    "addr:street":"Matseweg;Gelderland",
    "iso:country":"NL",
    "sg:address":"Matseweg 1",
    "sg:city":"Putten",
    "sg:orig_category":"Zuivelproducten And Spijsoli?n Gh",
    "sg:phone":"+31 341 358 004",
    "sg:postcode":"3882 TD",
    "sg:province":"Gelderland",
    "wof:name":"Marco Kleijer Eierhandel",
    "wof:placetype":"venue"
},
  "geometry": {"coordinates":[5.600938,52.240463],"type":"Point"}
}