{
  "type": "Feature",
  "properties": {
    "addr:full":"Schietspoel 22 Wierden Overijssel 7641 LT",
    "addr:housenumber":"22",
    "addr:postcode":"7641 lt",
    "addr:street":"Schietspoel",
    "iso:country":"NL",
    "sg:address":"Schietspoel 22",
    "sg:city":"Wierden",
    "sg:orig_category":"Modevakscholen",
    "sg:phone":"+31 546 577 773",
    "sg:postcode":"7641 LT",
    "sg:province":"Overijssel",
    "wof:name":"Ensaid",
    "wof:placetype":"venue"
},
  "geometry": {"coordinates":[6.597965,52.372189],"type":"Point"}
}