{
  "type": "Feature",
  "properties": {
    "iso:country":"NL",
    "sg:address":"Nieuwe Schans 47",
    "sg:city":"Bunschoten Spakenburg",
    "sg:orig_category":"Visspeciaalzaken",
    "sg:phone":"+31 33 298 2325",
    "sg:postcode":"3751 BB",
    "sg:province":"Utrecht",
    "wof:name":"P Van Diermen Jr",
    "wof:placetype":"venue"
},
  "geometry": {"coordinates":[5.380809,52.253761],"type":"Point"}
}