{
  "type": "Feature",
  "properties": {
    "addr:full":"Oudedk 12 Maasdyk Zuid-Holland 2676 NC",
    "addr:housenumber":"12",
    "addr:postcode":"2676 nc",
    "addr:street":"Oudedk",
    "iso:country":"NL",
    "sg:address":"Oudedk 12",
    "sg:city":"Maasdyk",
    "sg:orig_category":"Bloemen En Planten - Groothandel",
    "sg:phone":"+31 174 521 980",
    "sg:postcode":"2676 NC",
    "sg:province":"Zuid-Holland",
    "wof:name":"Songrow Cv",
    "wof:placetype":"venue"
},
  "geometry": {"coordinates":[4.214916,51.967258],"type":"Point"}
}