{
  "type": "Feature",
  "properties": {
    "addr:full":"Eikenschoor 4 Soerendonk Noord-Brabant 6027 ND",
    "addr:housenumber":"4",
    "addr:postcode":"6027 nd",
    "addr:street":"Eikenschoor",
    "iso:country":"NL",
    "sg:address":"Eikenschoor 4",
    "sg:city":"Soerendonk",
    "sg:orig_category":"Houtvezelperserijen",
    "sg:phone":"+31 495 599 260",
    "sg:postcode":"6027 ND",
    "sg:province":"Noord-Brabant",
    "wof:name":"Meijl, J Van",
    "wof:placetype":"venue"
},
  "geometry": {"coordinates":[-100.30171199999999,47.467731],"type":"Point"}
}