{
  "type": "Feature",
  "properties": {
    "addr:full":"Schoenmakersstraat 4 Best Texas 5684 ZH",
    "addr:housenumber":"4",
    "addr:postcode":"5684 zh",
    "addr:street":"Schoenmakersstraat",
    "iso:country":"NL",
    "sg:address":"Schoenmakersstraat 4",
    "sg:city":"Best",
    "sg:orig_category":"Onderhoud And Reparatie Kantoorapparatuur",
    "sg:phone":"+31 499 376 836",
    "sg:postcode":"5684 ZH",
    "sg:province":"Texas",
    "wof:name":"Welvos",
    "wof:placetype":"venue"
},
  "geometry": {"coordinates":[-101.46476699999999,31.193575],"type":"Point"}
}