{
  "type": "Feature",
  "properties": {
    "addr:full":"Borchsateln 105 Rotterdam Zuid-Holland 3055 ZH",
    "addr:housenumber":"105",
    "addr:postcode":"3055 zh",
    "iso:country":"NL",
    "sg:address":"Borchsateln 105",
    "sg:city":"Rotterdam",
    "sg:orig_category":"Antiquiteiten - Restauratie",
    "sg:phone":"+31 10 461 1662",
    "sg:postcode":"3055 ZH",
    "sg:province":"Zuid-Holland",
    "wof:name":"Martine V/D Plas Schilderijenrest",
    "wof:placetype":"venue"
},
  "geometry": {"coordinates":[4.50689,51.961319],"type":"Point"}
}