{
  "type": "Feature",
  "properties": {
    "addr:full":"Rietveen 8 Ter Aar Zuid-Holland 2461 HB",
    "addr:housenumber":"8",
    "addr:postcode":"aar;2461 hb",
    "addr:street":"Rietveen",
    "iso:country":"NL",
    "sg:address":"Rietveen 8",
    "sg:city":"Ter Aar",
    "sg:orig_category":"Schilders",
    "sg:phone":"+31 172 603 052",
    "sg:postcode":"2461 HB",
    "sg:province":"Zuid-Holland",
    "wof:name":"Aartman Schilderwerken Bv",
    "wof:placetype":"venue"
},
  "geometry": {"coordinates":[4.703534,52.170444],"type":"Point"}
}