{
  "type": "Feature",
  "properties": {
    "addr:full":"Bentemmerstr 11 Didam Gelderland 6942 EZ",
    "addr:housenumber":"11",
    "addr:postcode":"6942 ez",
    "addr:street":"Bentemmerstr;Gelderland",
    "iso:country":"NL",
    "sg:address":"Bentemmerstr 11",
    "sg:city":"Didam",
    "sg:classifiers":[
        {
            "category":"Retail",
            "subcategory":"Auto Repair",
            "type":"Services"
        }
    ],
    "sg:phone":"+31 316 228 888",
    "sg:postcode":"6942 EZ",
    "sg:province":"Gelderland",
    "sg:tags":[
        "garage"
    ],
    "wof:name":"Rutjes Autobedrijf",
    "wof:placetype":"venue"
},
  "geometry": {"coordinates":[6.140174,51.933434],"type":"Point"}
}