{
  "type": "Feature",
  "properties": {
    "addr:full":"Parade 6 'S Hertogenbosch North Brabant 5211 KL",
    "addr:housenumber":"6 ' s",
    "addr:postcode":"5211 kl",
    "addr:street":"Parade;Hertogenbosch",
    "iso:country":"NL",
    "sg:address":"Parade 6",
    "sg:city":"'S Hertogenbosch",
    "sg:orig_category":"Zalenexploitatie",
    "sg:phone":"+31 73 656 5588",
    "sg:postcode":"5211 KL",
    "sg:province":"North Brabant",
    "wof:name":"De Speeldoos Cc",
    "wof:placetype":"venue"
},
  "geometry": {"coordinates":[5.307193,51.687397],"type":"Point"}
}