{
  "type": "Feature",
  "properties": {
    "iso:country":"NL",
    "sg:address":"Vd Meerwg 16",
    "sg:city":"Oostvoorne",
    "sg:orig_category":"Koeriersdiensten",
    "sg:phone":"+31 181 484 252",
    "sg:postcode":"3233 BX",
    "sg:province":"Zuid-Holland",
    "wof:name":"Muller, M",
    "wof:placetype":"venue"
},
  "geometry": {"coordinates":[4.097827,51.911354],"type":"Point"}
}