{
  "type": "Feature",
  "properties": {
    "addr:full":"De Haak 8A Valkenswaard North Brabant 5555 XK",
    "addr:housenumber":"8a",
    "addr:postcode":"5555 xk",
    "addr:street":"De Haak",
    "iso:country":"NL",
    "sg:address":"De Haak 8A",
    "sg:city":"Valkenswaard",
    "sg:orig_category":"Koeltechniek",
    "sg:phone":"+31 40 207 6913",
    "sg:postcode":"5555 XK",
    "sg:province":"North Brabant",
    "wof:name":"Gerven, Van",
    "wof:placetype":"venue"
},
  "geometry": {"coordinates":[5.487831,51.352581],"type":"Point"}
}