{
  "type": "Feature",
  "properties": {
    "addr:full":"Hogeweg 11 Amsterdam Noord-Holland 1098 BV",
    "addr:housenumber":"11",
    "addr:postcode":"1098 bv",
    "addr:street":"Hogeweg",
    "iso:country":"NL",
    "sg:address":"Hogeweg 11",
    "sg:city":"Amsterdam",
    "sg:orig_category":"Medische Apparatuur And Prothesen Fab",
    "sg:phone":"+31 20 665 6951",
    "sg:postcode":"1098 BV",
    "sg:province":"Noord-Holland",
    "wof:name":"Van Haeften'S Horophoon",
    "wof:placetype":"venue"
},
  "geometry": {"coordinates":[4.931078,52.354187],"type":"Point"}
}