{
  "type": "Feature",
  "properties": {
    "addr:full":"Obrechthof 12 Alphen Aan Den Ryn South Holland 2402 EB",
    "addr:housenumber":"12",
    "addr:postcode":"2402 eb",
    "addr:street":"Obrechthof;Aan Den Ryn",
    "iso:country":"NL",
    "sg:address":"Obrechthof 12",
    "sg:city":"Alphen Aan Den Ryn",
    "sg:orig_category":"Verenigingen En Stichtingen",
    "sg:phone":"+31 172 444 559",
    "sg:postcode":"2402 EB",
    "sg:province":"South Holland",
    "wof:name":"Vor, Sticht",
    "wof:placetype":"venue"
},
  "geometry": {"coordinates":[4.667596,52.144943],"type":"Point"}
}