{
  "type": "Feature",
  "properties": {
    "addr:full":"J A Vd Goeskd 69 Goes Zeeland 4461 BJ",
    "addr:housenumber":"69",
    "addr:postcode":"4461 bj",
    "addr:street":"J A",
    "iso:country":"NL",
    "sg:address":"J A Vd Goeskd 69",
    "sg:city":"Goes",
    "sg:orig_category":"Woningbouw- Verenigingen En -Stichtingen",
    "sg:phone":"+31 113 215 659",
    "sg:postcode":"4461 BJ",
    "sg:province":"Zeeland",
    "wof:name":"Maatschappelijke Belangen, Sticht",
    "wof:placetype":"venue"
},
  "geometry": {"coordinates":[-83.9141693115,39.7688331604],"type":"Point"}
}