{
  "type": "Feature",
  "properties": {
    "iso:country":"NL",
    "sg:address":"Forellendaal 332",
    "sg:city":"S Gravenhage",
    "sg:orig_category":"Bloemen En Planten",
    "sg:phone":"+31 70 397 7888",
    "sg:postcode":"2553 LM",
    "sg:province":"Zuid-Holland",
    "wof:name":"Margriet",
    "wof:placetype":"venue"
},
  "geometry": {"coordinates":[4.21987,52.046589],"type":"Point"}
}