{
  "type": "Feature",
  "properties": {
    "addr:full":"Dr Ariensstraat 13 Ulft Gelderland 7071 AH",
    "addr:housenumber":"13",
    "addr:postcode":"7071 ah",
    "addr:street":"Dr Ariensstraat;Gelderland",
    "iso:country":"NL",
    "sg:address":"Dr Ariensstraat 13",
    "sg:city":"Ulft",
    "sg:orig_category":"Verlichting And Huishoudartikelen",
    "sg:phone":"+31 315 681 471",
    "sg:postcode":"7071 AH",
    "sg:province":"Gelderland",
    "wof:name":"Interieurverzorging Th.J. Peters",
    "wof:placetype":"venue"
},
  "geometry": {"coordinates":[6.375304,51.900848],"type":"Point"}
}