{
  "type": "Feature",
  "properties": {
    "addr:full":"Schoterwg 36 Rotstergaast Friesland 8462 TE",
    "addr:housenumber":"36",
    "addr:postcode":"8462 te",
    "addr:street":"Schoterwg",
    "iso:country":"NL",
    "sg:address":"Schoterwg 36",
    "sg:city":"Rotstergaast",
    "sg:orig_category":"Loonbedrijven",
    "sg:phone":"+31 513 551 750",
    "sg:postcode":"8462 TE",
    "sg:province":"Friesland",
    "wof:name":"Heide, Peter Van Der",
    "wof:placetype":"venue"
},
  "geometry": {"coordinates":[5.885561,52.897903],"type":"Point"}
}