{
  "type": "Feature",
  "properties": {
    "addr:full":"Theemsstr 62 Haarlem Noord-Holland 2014 RZ",
    "addr:housenumber":"62",
    "addr:postcode":"2014 rz",
    "addr:street":"Theemsstr",
    "iso:country":"NL",
    "sg:address":"Theemsstr 62",
    "sg:city":"Haarlem",
    "sg:orig_category":"Acupunctuur",
    "sg:phone":"+31 23 544 1571",
    "sg:postcode":"2014 RZ",
    "sg:province":"Noord-Holland",
    "wof:name":"Prak Voor Trad Acupunctuur",
    "wof:placetype":"venue"
},
  "geometry": {"coordinates":[4.613559,52.375538],"type":"Point"}
}