{
  "type": "Feature",
  "properties": {
    "addr:full":"Pastoor Van Leijsenstr 9 Schijf Noord-Brabant 4721 AR",
    "addr:housenumber":"9",
    "addr:postcode":"4721",
    "addr:street":"Pastoor Van Leijsenstr",
    "iso:country":"NL",
    "sg:address":"Pastoor Van Leijsenstr 9",
    "sg:city":"Schijf",
    "sg:orig_category":"Auto'S And Voertuigen",
    "sg:phone":"+31 165 341 561",
    "sg:postcode":"4721 AR",
    "sg:province":"Noord-Brabant",
    "wof:name":"A S Kustermans",
    "wof:placetype":"venue"
},
  "geometry": {"coordinates":[4.562983,51.498638],"type":"Point"}
}