{
  "type": "Feature",
  "properties": {
    "addr:full":"Maarsbergsewg 45 Leersum Utrecht 3956 KT",
    "addr:housenumber":"45",
    "addr:postcode":"3956 kt",
    "addr:street":"Maarsbergsewg",
    "iso:country":"NL",
    "sg:address":"Maarsbergsewg 45",
    "sg:city":"Leersum",
    "sg:classifiers":[
        {
            "category":"Shopping",
            "subcategory":"Adult",
            "type":"Retail Goods"
        }
    ],
    "sg:phone":"+31 343 457 505",
    "sg:postcode":"3956 KT",
    "sg:province":"Utrecht",
    "sg:tags":[
        "lingerie",
        "en",
        "tricotage"
    ],
    "wof:name":"Latente",
    "wof:placetype":"venue"
},
  "geometry": {"coordinates":[5.416816,52.027142],"type":"Point"}
}