{
  "type": "Feature",
  "properties": {
    "addr:full":"Zijlmakerssteeg 3 Spakenburg Utrecht 3751 AZ",
    "addr:housenumber":"3",
    "addr:postcode":"3751",
    "addr:street":"Zijlmakerssteeg",
    "iso:country":"NL",
    "sg:address":"Zijlmakerssteeg 3",
    "sg:city":"Spakenburg",
    "sg:orig_category":"Meubeltextiel Fab",
    "sg:phone":"+31 33 298 1346",
    "sg:postcode":"3751 AZ",
    "sg:province":"Utrecht",
    "wof:name":"W. Van Der Schuur & Zoon Zeilmakerij",
    "wof:placetype":"venue"
},
  "geometry": {"coordinates":[5.37481,52.243553],"type":"Point"}
}