{
  "type": "Feature",
  "properties": {
    "iso:country":"NL",
    "sg:address":"Prof Vt Hoffln 3",
    "sg:city":"Voorschoten",
    "sg:orig_category":"Balletscholen",
    "sg:phone":"+31 71 561 8037",
    "sg:postcode":"2251 GK",
    "sg:province":"South Holland",
    "wof:name":"Sylvia",
    "wof:placetype":"venue"
},
  "geometry": {"coordinates":[4.452245,52.123543],"type":"Point"}
}