{
  "type": "Feature",
  "properties": {
    "iso:country":"NL",
    "sg:address":"Nassauln 44",
    "sg:city":"Oegstgeest",
    "sg:orig_category":"Onroerende Goederen",
    "sg:phone":"+31 71 519 0065",
    "sg:postcode":"2341 EE",
    "sg:province":"South Holland",
    "wof:name":"Huisraad Op Maat",
    "wof:placetype":"venue"
},
  "geometry": {"coordinates":[4.468242,52.176617],"type":"Point"}
}