{
  "type": "Feature",
  "properties": {
    "addr:full":"Hoogstr 110 Rotterdam Zuid-Holland 3011 PV",
    "addr:housenumber":"110",
    "addr:postcode":"3011 pv",
    "iso:country":"NL",
    "sg:address":"Hoogstr 110",
    "sg:city":"Rotterdam",
    "sg:orig_category":"Bibliotheken En Leeszalen Openbare",
    "sg:phone":"+31 10 281 6100",
    "sg:postcode":"3011 PV",
    "sg:province":"Zuid-Holland",
    "sg:website":"http://www.bibliotheek.rotterdam.nl",
    "wof:name":"Bibliotheek Rotterdam",
    "wof:placetype":"venue"
},
  "geometry": {"coordinates":[4.488855,51.921391],"type":"Point"}
}