{
  "type": "Feature",
  "properties": {
    "addr:full":"Toven 2 Ledeacker North Brabant 5846 AS",
    "addr:housenumber":"2",
    "addr:postcode":"5846 as",
    "addr:street":"Toven",
    "iso:country":"NL",
    "sg:address":"Toven 2",
    "sg:city":"Ledeacker",
    "sg:orig_category":"Kantoorartikelen",
    "sg:phone":"+31 485 371 975",
    "sg:postcode":"5846 AS",
    "sg:province":"North Brabant",
    "wof:name":"Facon",
    "wof:placetype":"venue"
},
  "geometry": {"coordinates":[5.861951828,51.6410064697],"type":"Point"}
}