{
  "type": "Feature",
  "properties": {
    "addr:full":"Middenweg 29 Veendam Groningen 9645 BA",
    "addr:housenumber":"29",
    "addr:postcode":"9645 ba",
    "addr:street":"Middenweg",
    "iso:country":"NL",
    "sg:address":"Middenweg 29",
    "sg:city":"Veendam",
    "sg:orig_category":"Visspeciaalzaken",
    "sg:phone":"+31 598 626 512",
    "sg:postcode":"9645 BA",
    "sg:province":"Groningen",
    "wof:name":"Vis En Snackpaleis Noordzee",
    "wof:placetype":"venue"
},
  "geometry": {"coordinates":[6.875431,53.119965],"type":"Point"}
}