{
  "type": "Feature",
  "properties": {
    "addr:full":"Vliestroom 67 Alphen Aan Den Ryn Zuid-Holland 2401 VB",
    "addr:housenumber":"67",
    "addr:postcode":"2401 vb",
    "addr:street":"Vliestroom;Aan Den Ryn",
    "iso:country":"NL",
    "sg:address":"Vliestroom 67",
    "sg:city":"Alphen Aan Den Ryn",
    "sg:orig_category":"On- Offshore",
    "sg:phone":"+31 172 244 589",
    "sg:postcode":"2401 VB",
    "sg:province":"Zuid-Holland",
    "wof:name":"Mennink",
    "wof:placetype":"venue"
},
  "geometry": {"coordinates":[4.656934,52.147617],"type":"Point"}
}