{
  "type": "Feature",
  "properties": {
    "addr:full":"Maalsteenstraat 9 Urmond Limburg 6129 JH",
    "addr:housenumber":"9",
    "addr:postcode":"6129 jh",
    "addr:street":"Maalsteenstraat",
    "iso:country":"NL",
    "sg:address":"Maalsteenstraat 9",
    "sg:city":"Urmond",
    "sg:orig_category":"Kappers",
    "sg:phone":"+31 46 433 3142",
    "sg:postcode":"6129 JH",
    "sg:province":"Limburg",
    "wof:name":"Kapsalon Riny",
    "wof:placetype":"venue"
},
  "geometry": {"coordinates":[5.7734999657,50.994594574],"type":"Point"}
}