{
  "type": "Feature",
  "properties": {
    "addr:full":"Tielsestraat 11 Maurik Gelderland 4021 HA",
    "addr:housenumber":"11",
    "addr:postcode":"4021 ha",
    "addr:street":"Tielsestraat;Gelderland",
    "iso:country":"NL",
    "sg:address":"Tielsestraat 11",
    "sg:city":"Maurik",
    "sg:orig_category":"Verzekeringen",
    "sg:phone":"+31 344 691 631",
    "sg:postcode":"4021 HA",
    "sg:province":"Gelderland",
    "wof:name":"Assurantiekantoor T. Willemse",
    "wof:placetype":"venue"
},
  "geometry": {"coordinates":[5.419645,51.960014],"type":"Point"}
}