{
  "type": "Feature",
  "properties": {
    "iso:country":"NL",
    "sg:address":"Postbus 40023",
    "sg:city":"Nymegen",
    "sg:orig_category":"Verenigingen En Stichtingen",
    "sg:phone":"+31 24 377 3082",
    "sg:postcode":"6504 AA",
    "sg:province":"Gelderland",
    "wof:name":"Schoolraad Zuidelijk Gelderl, Ver Rk",
    "wof:placetype":"venue"
},
  "geometry": {"coordinates":[-85.441704,38.164711],"type":"Point"}
}