{
  "type": "Feature",
  "properties": {
    "addr:full":"Hoorn 131 Alphen Aan Den Ryn Zuid-Holland 2404 HH",
    "addr:housenumber":"131",
    "addr:postcode":"2404 hh",
    "addr:street":"Hoorn;Aan Den Ryn",
    "iso:country":"NL",
    "sg:address":"Hoorn 131",
    "sg:city":"Alphen Aan Den Ryn",
    "sg:orig_category":"Galeries",
    "sg:phone":"+31 172 421 174",
    "sg:postcode":"2404 HH",
    "sg:province":"Zuid-Holland",
    "wof:name":"Hofman, Helga",
    "wof:placetype":"venue"
},
  "geometry": {"coordinates":[4.624551,52.133362],"type":"Point"}
}