{
  "type": "Feature",
  "properties": {
    "iso:country":"NL",
    "sg:address":"Nw Loosdrechtsedk 270",
    "sg:city":"Loosdrecht",
    "sg:orig_category":"Jachthavens - Jachtwerven",
    "sg:phone":"+31 35 582 3277",
    "sg:postcode":"1231 LH",
    "sg:province":"Utrecht",
    "wof:name":"Muyeveld",
    "wof:placetype":"venue"
},
  "geometry": {"coordinates":[5.071921,52.207092],"type":"Point"}
}