{
  "type": "Feature",
  "properties": {
    "addr:full":"Past Op Heystr 26 Venlo Limburg 5912 BT",
    "addr:housenumber":"26",
    "addr:postcode":"5912 bt",
    "addr:street":"Past;Heystr",
    "iso:country":"NL",
    "sg:address":"Past Op Heystr 26",
    "sg:city":"Venlo",
    "sg:orig_category":"Scholen Voor Basisonderwijs",
    "sg:phone":"+31 77 351 7906",
    "sg:postcode":"5912 BT",
    "sg:province":"Limburg",
    "wof:name":"Verrekijker Rk, De",
    "wof:placetype":"venue"
},
  "geometry": {"coordinates":[6.17286,51.372421],"type":"Point"}
}