{
  "type": "Feature",
  "properties": {
    "addr:full":"Hogeweg 10 Wamel Gelderland 6659 AJ",
    "addr:housenumber":"10",
    "addr:postcode":"6659 aj",
    "addr:street":"Hogeweg;Gelderland",
    "iso:country":"NL",
    "sg:address":"Hogeweg 10",
    "sg:city":"Wamel",
    "sg:orig_category":"Verhuur Gereedschapsmachines And Gereedschappen",
    "sg:phone":"+31 487 501 429",
    "sg:postcode":"6659 AJ",
    "sg:province":"Gelderland",
    "wof:name":"C.A.M. Den Biezen",
    "wof:placetype":"venue"
},
  "geometry": {"coordinates":[5.486748,51.880028],"type":"Point"}
}