{
  "type": "Feature",
  "properties": {
    "iso:country":"NL",
    "sg:address":"Visstr 4",
    "sg:city":"'S Hertogenbosch",
    "sg:orig_category":"Schoenen",
    "sg:phone":"+31 73 613 0500",
    "sg:postcode":"5211 DN",
    "sg:province":"North Brabant",
    "wof:name":"Laporta Bv",
    "wof:placetype":"venue"
},
  "geometry": {"coordinates":[5.301358,51.690327],"type":"Point"}
}