{
  "type": "Feature",
  "properties": {
    "iso:country":"NL",
    "sg:address":"Huissteden 1304",
    "sg:city":"Wijchen",
    "sg:classifiers":[
        {
            "category":"Education",
            "subcategory":"Preschool",
            "type":"Public Place"
        }
    ],
    "sg:phone":"+31 24 645 2764",
    "sg:postcode":"6605 HJ",
    "sg:province":"Gelderland",
    "sg:tags":[
        "kleuteronderwijs",
        "basis-"
    ],
    "wof:name":"Openbare Basisschool De Smalle Weegbree",
    "wof:placetype":"venue"
},
  "geometry": {"coordinates":[5.722797,51.79998],"type":"Point"}
}