{
  "type": "Feature",
  "properties": {
    "addr:full":"Odilia Van Salmstraat 25 Breda Noord-Brabant 4811 LA",
    "addr:housenumber":"25",
    "addr:postcode":"4811 la",
    "addr:street":"Odilia Van Salmstraat",
    "iso:country":"NL",
    "sg:address":"Odilia Van Salmstraat 25",
    "sg:city":"Breda",
    "sg:orig_category":"Overheidsdiensten",
    "sg:phone":"+31 76 521 7974",
    "sg:postcode":"4811 LA",
    "sg:province":"Noord-Brabant",
    "wof:name":"Gerardus Majella",
    "wof:placetype":"venue"
},
  "geometry": {"coordinates":[4.7718558311,51.5866394043],"type":"Point"}
}