{
  "type": "Feature",
  "properties": {
    "addr:full":"A Schelfhoutstr 28 Almelo Overijssel 7606 KP",
    "addr:housenumber":"28",
    "addr:postcode":"7606 kp",
    "iso:country":"NL",
    "sg:address":"A Schelfhoutstr 28",
    "sg:city":"Almelo",
    "sg:orig_category":"Huidtherapeuten",
    "sg:phone":"+31 546 826 236",
    "sg:postcode":"7606 KP",
    "sg:province":"Overijssel",
    "wof:name":"Strijtveen-Jonkman, J M",
    "wof:placetype":"venue"
},
  "geometry": {"coordinates":[6.646745,52.343639],"type":"Point"}
}