{
  "type": "Feature",
  "properties": {
    "addr:full":"Wilhelminastr 36 Amsterdam North Holland 1054 WJ",
    "addr:housenumber":"36",
    "addr:postcode":"1054 wj",
    "addr:street":"Wilhelminastr",
    "iso:country":"NL",
    "sg:address":"Wilhelminastr 36",
    "sg:city":"Amsterdam",
    "sg:orig_category":"Vertaalbureaus",
    "sg:phone":"+31 20 689 7524",
    "sg:postcode":"1054 WJ",
    "sg:province":"North Holland",
    "wof:name":"Wiegmann",
    "wof:placetype":"venue"
},
  "geometry": {"coordinates":[4.865882,52.362377],"type":"Point"}
}