{
  "type": "Feature",
  "properties": {
    "addr:full":"Petrus Dondersstraat 85 Eindhoven North Brabant 5613 LS",
    "addr:housenumber":"85",
    "addr:postcode":"5613 ls",
    "addr:street":"Petrus Dondersstraat",
    "iso:country":"NL",
    "sg:address":"Petrus Dondersstraat 85",
    "sg:city":"Eindhoven",
    "sg:orig_category":"Vertaal- And Tolkenbureaus",
    "sg:phone":"+31 40 294 0666",
    "sg:postcode":"5613 LS",
    "sg:province":"North Brabant",
    "wof:name":"Japans Vertaalbur",
    "wof:placetype":"venue"
},
  "geometry": {"coordinates":[5.496304,51.42934],"type":"Point"}
}