{
  "type": "Feature",
  "properties": {
    "addr:full":"Hoornespln 25 Katwyk Zh South Holland 2221 BC",
    "addr:housenumber":"25;zh",
    "addr:postcode":"2221 bc",
    "addr:street":"Hoornespln",
    "iso:country":"NL",
    "sg:address":"Hoornespln 25",
    "sg:city":"Katwyk Zh",
    "sg:classifiers":[
        {
            "category":"Food & Beverages",
            "subcategory":"Bakery",
            "type":"Retail Goods"
        }
    ],
    "sg:phone":"+31 71 408 4433",
    "sg:postcode":"2221 BC",
    "sg:province":"South Holland",
    "sg:tags":[
        "pizza"
    ],
    "wof:name":"Bella Cyprus Pizzeria",
    "wof:placetype":"venue"
},
  "geometry": {"coordinates":[4.419026,52.205849],"type":"Point"}
}