{
  "type": "Feature",
  "properties": {
    "iso:country":"NL",
    "sg:address":"Kortewg 2",
    "sg:city":"Kampen",
    "sg:orig_category":"Verenigingen En Stichtingen",
    "sg:phone":"+31 38 331 3708",
    "sg:postcode":"8261 DC",
    "sg:province":"District of Columbia",
    "wof:name":"Cvo Adm, Ver Voor",
    "wof:placetype":"venue"
},
  "geometry": {"coordinates":[-77.01458700000001,38.8937],"type":"Point"}
}