{
  "type": "Feature",
  "properties": {
    "addr:full":"Duurstedeweg 33010 Deventer NL.08 7418 CK",
    "addr:postcode":"33010;nl.08 7418 ck",
    "addr:street":"Duurstedeweg",
    "iso:country":"NL",
    "sg:address":"Duurstedeweg 33010",
    "sg:city":"Deventer",
    "sg:orig_category":"Loodgieterswerk, Verwarming And Sanitaire Installaties",
    "sg:phone":"+31 570 633 933",
    "sg:postcode":"7418 CK",
    "sg:province":"NL.08",
    "wof:name":"Tb & O Deventer Bv",
    "wof:placetype":"venue"
},
  "geometry": {"coordinates":[6.18665,52.251122],"type":"Point"}
}