{
  "type": "Feature",
  "properties": {
    "addr:full":"Grt Haarsekd 120 Gorinchem Zuid-Holland 4205 VL",
    "addr:housenumber":"120",
    "addr:postcode":"gorinchem;4205 vl",
    "iso:country":"NL",
    "sg:address":"Grt Haarsekd 120",
    "sg:city":"Gorinchem",
    "sg:orig_category":"Verenigingsgebouwen",
    "sg:phone":"+31 183 623 912",
    "sg:postcode":"4205 VL",
    "sg:province":"Zuid-Holland",
    "wof:name":"Haarhorst, De",
    "wof:placetype":"venue"
},
  "geometry": {"coordinates":[4.972132,51.84602],"type":"Point"}
}