{
  "type": "Feature",
  "properties": {
    "addr:full":"Midstr 83 Woudsend Friesland 8551 PK",
    "addr:housenumber":"83",
    "addr:postcode":"8551 pk",
    "addr:street":"Midstr",
    "iso:country":"NL",
    "sg:address":"Midstr 83",
    "sg:city":"Woudsend",
    "sg:orig_category":"Bloemen En Planten",
    "sg:phone":"+31 514 591 651",
    "sg:postcode":"8551 PK",
    "sg:province":"Friesland",
    "wof:name":"Pompebl?d, 'T",
    "wof:placetype":"venue"
},
  "geometry": {"coordinates":[5.628582,52.942806],"type":"Point"}
}