{
  "type": "Feature",
  "properties": {
    "addr:full":"Eeweg 44 Oudenhoorn Zuid-Holland 3227 AH",
    "addr:housenumber":"44",
    "addr:postcode":"3227 ah",
    "addr:street":"Eeweg",
    "iso:country":"NL",
    "sg:address":"Eeweg 44",
    "sg:city":"Oudenhoorn",
    "sg:classifiers":[
        {
            "category":"Travel",
            "subcategory":"Hotels & Motels",
            "type":"Entertainment"
        }
    ],
    "sg:phone":"+31 181 461 789",
    "sg:postcode":"3227 AH",
    "sg:province":"Zuid-Holland",
    "wof:name":"Mw. S. Vrij",
    "wof:placetype":"venue"
},
  "geometry": {"coordinates":[4.184219,51.821823],"type":"Point"}
}