{
  "type": "Feature",
  "properties": {
    "addr:full":"Vrythof 22 Maastricht Limburg 6211 LD",
    "addr:housenumber":"22",
    "addr:postcode":"6211 ld",
    "addr:street":"Vrythof",
    "iso:country":"NL",
    "sg:address":"Vrythof 22",
    "sg:city":"Maastricht",
    "sg:orig_category":"Projectontwikkeling",
    "sg:phone":"+31 43 390 0929",
    "sg:postcode":"6211 LD",
    "sg:province":"Limburg",
    "wof:name":"Profond Bv",
    "wof:placetype":"venue"
},
  "geometry": {"coordinates":[5.688391,50.848358],"type":"Point"}
}