{
  "type": "Feature",
  "properties": {
    "addr:full":"Diepenbroeklaan 70 Baarlo Lb Limburg 5991 PT",
    "addr:housenumber":"70",
    "addr:postcode":"lb;5991 pt",
    "addr:street":"Diepenbroeklaan",
    "iso:country":"NL",
    "sg:address":"Diepenbroeklaan 70",
    "sg:city":"Baarlo Lb",
    "sg:orig_category":"Film-, Tv- And Videoproductie",
    "sg:phone":"+31 77 477 8095",
    "sg:postcode":"5991 PT",
    "sg:province":"Limburg",
    "wof:name":"Video Producties Vermeulen",
    "wof:placetype":"venue"
},
  "geometry": {"coordinates":[6.090759,51.323887],"type":"Point"}
}