{
  "type": "Feature",
  "properties": {
    "addr:full":"Marconiwg 9 Delft South Holland 2627 BA",
    "addr:housenumber":"9",
    "addr:postcode":"2627 ba",
    "addr:street":"Marconiwg",
    "iso:country":"NL",
    "sg:address":"Marconiwg 9",
    "sg:city":"Delft",
    "sg:orig_category":"Banden - Fabrieken En Groothandel",
    "sg:phone":"+31 15 257 8310",
    "sg:postcode":"2627 BA",
    "sg:province":"South Holland",
    "wof:name":"Newco Bv",
    "wof:placetype":"venue"
},
  "geometry": {"coordinates":[4.372181,51.985092],"type":"Point"}
}