{
  "type": "Feature",
  "properties": {
    "addr:full":"Noordeinde 241 Almere Flevoland 1334 AS",
    "addr:housenumber":"241",
    "addr:postcode":"1334 as",
    "addr:street":"Noordeinde;Flevoland",
    "iso:country":"NL",
    "sg:address":"Noordeinde 241",
    "sg:city":"Almere",
    "sg:classifiers":[
        {
            "category":"Shopping",
            "subcategory":"Gifts & Souvenirs",
            "type":"Retail Goods"
        }
    ],
    "sg:phone":"+31 36 532 4882",
    "sg:postcode":"1334 AS",
    "sg:province":"Flevoland",
    "sg:tags":[
        "geschenken"
    ],
    "wof:name":"Zodiak",
    "wof:placetype":"venue"
},
  "geometry": {"coordinates":[5.277954,52.394588],"type":"Point"}
}