{
  "type": "Feature",
  "properties": {
    "addr:full":"Barchemsewg 32 Ruurlo Gelderland 7261 DD",
    "addr:housenumber":"32",
    "addr:postcode":"7261 dd",
    "addr:street":"Barchemsewg;Gelderland",
    "iso:country":"NL",
    "sg:address":"Barchemsewg 32",
    "sg:city":"Ruurlo",
    "sg:classifiers":[
        {
            "category":"Home & Garden",
            "subcategory":"Hardware",
            "type":"Retail Goods"
        }
    ],
    "sg:phone":"+31 573 454 251",
    "sg:postcode":"7261 DD",
    "sg:province":"Gelderland",
    "sg:tags":[
        "machine",
        "-",
        "metaalbewerking"
    ],
    "wof:name":"Ernst",
    "wof:placetype":"venue"
},
  "geometry": {"coordinates":[6.450153,52.090858],"type":"Point"}
}