{
  "type": "Feature",
  "properties": {
    "addr:full":"Maasln 10 Heemstede Noord-Holland 2105 XC",
    "addr:housenumber":"10",
    "addr:postcode":"2105 xc",
    "addr:street":"Maasln",
    "iso:country":"NL",
    "sg:address":"Maasln 10",
    "sg:city":"Heemstede",
    "sg:orig_category":"Meubelmakerijen",
    "sg:phone":"+31 23 529 5448",
    "sg:postcode":"2105 XC",
    "sg:province":"Noord-Holland",
    "wof:name":"Houten Kroon, De",
    "wof:placetype":"venue"
},
  "geometry": {"coordinates":[4.621248,52.345287],"type":"Point"}
}