{
  "type": "Feature",
  "properties": {
    "addr:full":"Van Dorenborchstraat 1/K320 Zutphen Gelderland 7203 CA",
    "addr:housenumber":"1 / k320",
    "addr:postcode":"7203 ca",
    "addr:street":"Van Dorenborchstraat;Gelderland",
    "iso:country":"NL",
    "sg:address":"Van Dorenborchstraat 1/K320",
    "sg:city":"Zutphen",
    "sg:orig_category":"Kappers",
    "sg:phone":"+31 575 516 857",
    "sg:postcode":"7203 CA",
    "sg:province":"Gelderland",
    "wof:name":"C.J. Ronk",
    "wof:placetype":"venue"
},
  "geometry": {"coordinates":[6.1915249825,52.1402015686],"type":"Point"}
}