{
  "type": "Feature",
  "properties": {
    "addr:full":"Parkln 48 Bussum North Holland 1405 GR",
    "addr:housenumber":"48",
    "addr:postcode":"1405",
    "addr:street":"Parkln",
    "iso:country":"NL",
    "sg:address":"Parkln 48",
    "sg:city":"Bussum",
    "sg:orig_category":"Vertaalbureaus",
    "sg:phone":"+31 35 693 8659",
    "sg:postcode":"1405 GR",
    "sg:province":"North Holland",
    "wof:name":"Manning, Phil",
    "wof:placetype":"venue"
},
  "geometry": {"coordinates":[5.162605,52.276829],"type":"Point"}
}