{
  "type": "Feature",
  "properties": {
    "addr:full":"Julianalaan 6 Weert Limburg 6006 AN",
    "addr:housenumber":"6",
    "addr:postcode":"6006 an",
    "addr:street":"Julianalaan",
    "iso:country":"NL",
    "sg:address":"Julianalaan 6",
    "sg:city":"Weert",
    "sg:orig_category":"Meubelzaken, Woning- And Keukeninrichting",
    "sg:phone":"+31 495 540 692",
    "sg:postcode":"6006 AN",
    "sg:province":"Limburg",
    "wof:name":"Van Driel Meubelen",
    "wof:placetype":"venue"
},
  "geometry": {"coordinates":[5.7028,51.248116],"type":"Point"}
}