{
  "type": "Feature",
  "properties": {
    "iso:country":"NL",
    "sg:address":"Deventerstr 517",
    "sg:city":"Apeldoorn",
    "sg:orig_category":"Acupunctuur",
    "sg:phone":"+31 55 323 1927",
    "sg:postcode":"7325 WB",
    "sg:province":"Gelderland",
    "wof:name":"Oostrum, L Van",
    "wof:placetype":"venue"
},
  "geometry": {"coordinates":[6.020004,52.229279],"type":"Point"}
}