{
  "type": "Feature",
  "properties": {
    "iso:country":"NL",
    "sg:address":"Zwarteland 18",
    "sg:city":"Haaksbergen",
    "sg:orig_category":"Artiestenbureaus",
    "sg:phone":"+31 53 572 7748",
    "sg:postcode":"7482 DA",
    "sg:province":"Overijssel",
    "wof:name":"Lemon Band",
    "wof:placetype":"venue"
},
  "geometry": {"coordinates":[6.73007,52.156246],"type":"Point"}
}