{
  "type": "Feature",
  "properties": {
    "iso:country":"NL",
    "sg:address":"Toermalijnlaan 65",
    "sg:city":"Utrecht",
    "sg:orig_category":"Verhuur Audiovisuele Apparatuur",
    "sg:phone":"+31 30 251 2098",
    "sg:postcode":"3523 BG",
    "sg:province":"Utrecht",
    "wof:name":"Duijf Geluid",
    "wof:placetype":"venue"
},
  "geometry": {"coordinates":[-73.996292,40.613091],"type":"Point"}
}