{
  "type": "Feature",
  "properties": {
    "addr:full":"Burg Haspelsln 131 Amstelveen Noord-Holland 1181 NC",
    "addr:housenumber":"131",
    "addr:postcode":"1181 nc",
    "addr:street":"Burg",
    "iso:country":"NL",
    "sg:address":"Burg Haspelsln 131",
    "sg:city":"Amstelveen",
    "sg:orig_category":"Adviesbureaus",
    "sg:phone":"+31 20 640 5262",
    "sg:postcode":"1181 NC",
    "sg:province":"Noord-Holland",
    "wof:name":"Hanzen Bv",
    "wof:placetype":"venue"
},
  "geometry": {"coordinates":[4.867448,52.305462],"type":"Point"}
}