{
  "type": "Feature",
  "properties": {
    "addr:full":"Geerdinkhof 325 Amsterdam Zuidoost Noord-Holland 1103 RB",
    "addr:housenumber":"325",
    "addr:postcode":"zuidoost;1103 rb",
    "addr:street":"Geerdinkhof",
    "iso:country":"NL",
    "sg:address":"Geerdinkhof 325",
    "sg:city":"Amsterdam Zuidoost",
    "sg:classifiers":[
        {
            "category":"Food & Beverages",
            "subcategory":"Candy",
            "type":"Retail Goods"
        }
    ],
    "sg:phone":"+31 20 698 0154",
    "sg:postcode":"1103 RB",
    "sg:province":"Noord-Holland",
    "sg:tags":[
        "sport-",
        "en",
        "spelartikelen"
    ],
    "wof:name":"Verhagen",
    "wof:placetype":"venue"
},
  "geometry": {"coordinates":[4.981324,52.327072],"type":"Point"}
}