{
  "type": "Feature",
  "properties": {
    "addr:full":"St. Canisiussingel 26 Nijmegen Gelderland 6511 TJ",
    "addr:housenumber":"26",
    "addr:postcode":"6511 tj",
    "addr:street":"Canisiussingel;Gelderland",
    "iso:country":"NL",
    "sg:address":"St. Canisiussingel 26",
    "sg:city":"Nijmegen",
    "sg:orig_category":"Technische Studies And Onderzoek",
    "sg:phone":"+31 24 381 3333",
    "sg:postcode":"6511 TJ",
    "sg:province":"Gelderland",
    "wof:name":"Novioconsult",
    "wof:placetype":"venue"
},
  "geometry": {"coordinates":[5.870517,51.844158],"type":"Point"}
}