{
  "type": "Feature",
  "properties": {
    "addr:full":"Romerostr 604 Utrecht Utrecht 3573 AW",
    "addr:housenumber":"604",
    "addr:postcode":"3573 aw",
    "iso:country":"NL",
    "sg:address":"Romerostr 604",
    "sg:city":"Utrecht",
    "sg:orig_category":"Haptotherapeuten",
    "sg:phone":"+31 30 272 4980",
    "sg:postcode":"3573 AW",
    "sg:province":"Utrecht",
    "sg:website":"http://www.haptotherapeuten-vvh.nl",
    "wof:name":"Ellen Schoemaker",
    "wof:placetype":"venue"
},
  "geometry": {"coordinates":[5.15159,52.108509],"type":"Point"}
}