{
  "type": "Feature",
  "properties": {
    "addr:full":"Steegoversloot 56 Dordrecht Zuid-Holland 3311 PP",
    "addr:housenumber":"56",
    "addr:postcode":"3311 pp",
    "addr:street":"Steegoversloot",
    "iso:country":"NL",
    "sg:address":"Steegoversloot 56",
    "sg:city":"Dordrecht",
    "sg:orig_category":"Boeken Antiquarische En Gebruikte",
    "sg:phone":"+31 78 613 9522",
    "sg:postcode":"3311 PP",
    "sg:province":"Zuid-Holland",
    "sg:website":"http://www.tol.nl",
    "wof:name":"Tol, J P Van Den",
    "wof:placetype":"venue"
},
  "geometry": {"coordinates":[4.672575,51.815289],"type":"Point"}
}