{
  "type": "Feature",
  "properties": {
    "iso:country":"NL",
    "sg:address":"Bellendreef 4",
    "sg:city":"Etten Leur",
    "sg:classifiers":[
        {
            "category":"Sports & Exercise",
            "subcategory":"Stables",
            "type":"Entertainment"
        }
    ],
    "sg:phone":"+31 76 501 3533",
    "sg:postcode":"4873 LJ",
    "sg:province":"Noord-Brabant",
    "sg:tags":[
        "maneges"
    ],
    "wof:name":"Belle, Manege De",
    "wof:placetype":"venue"
},
  "geometry": {"coordinates":[4.6569,51.558929],"type":"Point"}
}