{
  "type": "Feature",
  "properties": {
    "addr:full":"P De Hoochstr 72 Amsterdam Noord-Holland 1071 EH",
    "addr:housenumber":"72",
    "addr:postcode":"1071 eh",
    "addr:street":"P",
    "iso:country":"NL",
    "sg:address":"P De Hoochstr 72",
    "sg:city":"Amsterdam",
    "sg:orig_category":"Binnenhuisarchitectuur",
    "sg:phone":"+31 20 624 6379",
    "sg:postcode":"1071 EH",
    "sg:province":"Noord-Holland",
    "wof:name":"Niessen, Joshua",
    "wof:placetype":"venue"
},
  "geometry": {"coordinates":[4.884827,52.355473],"type":"Point"}
}