{
  "type": "Feature",
  "properties": {
    "addr:full":"Puccinistr 11 Tilburg North Brabant 5049 GD",
    "addr:housenumber":"11",
    "addr:postcode":"5049 gd",
    "addr:street":"Puccinistr",
    "iso:country":"NL",
    "sg:address":"Puccinistr 11",
    "sg:city":"Tilburg",
    "sg:orig_category":"Waterbehandeling En Waterzuiverings- Systemen",
    "sg:phone":"+31 13 455 0540",
    "sg:postcode":"5049 GD",
    "sg:province":"North Brabant",
    "wof:name":"Pro Living Bv",
    "wof:placetype":"venue"
},
  "geometry": {"coordinates":[5.0738749504,51.5900764465],"type":"Point"}
}