{
  "type": "Feature",
  "properties": {
    "addr:full":"Daalseweg 48 Nijmegen Gelderland 6521 GN",
    "addr:housenumber":"48",
    "addr:postcode":"6521 gn",
    "addr:street":"Daalseweg;Gelderland",
    "iso:country":"NL",
    "sg:address":"Daalseweg 48",
    "sg:city":"Nijmegen",
    "sg:orig_category":"Discountwinkels",
    "sg:phone":"+31 24 323 4205",
    "sg:postcode":"6521 GN",
    "sg:province":"Gelderland",
    "wof:name":"Piet'S Dump En Trend",
    "wof:placetype":"venue"
},
  "geometry": {"coordinates":[5.871267,51.840927],"type":"Point"}
}