{
  "type": "Feature",
  "properties": {
    "addr:full":"Stommeerkade 87 Aalsmeer Noord-Holland 1431 EL",
    "addr:housenumber":"87",
    "addr:postcode":"1431 el",
    "addr:street":"Stommeerkade",
    "iso:country":"NL",
    "sg:address":"Stommeerkade 87",
    "sg:city":"Aalsmeer",
    "sg:orig_category":"Bloemen And Planten",
    "sg:phone":"+31 297 324 416",
    "sg:postcode":"1431 EL",
    "sg:province":"Noord-Holland",
    "wof:name":"Fa Joh. Van Leeuwen En Zonen",
    "wof:placetype":"venue"
},
  "geometry": {"coordinates":[4.767063,52.270435],"type":"Point"}
}