{
  "type": "Feature",
  "properties": {
    "addr:full":"Korvelseweg 56 Tilburg Noord-Brabant 5025 JJ",
    "addr:housenumber":"56",
    "addr:postcode":"5025 jj",
    "addr:street":"Korvelseweg",
    "iso:country":"NL",
    "sg:address":"Korvelseweg 56",
    "sg:city":"Tilburg",
    "sg:orig_category":"Bruidskleding",
    "sg:phone":"+31 13 542 4283",
    "sg:postcode":"5025 JJ",
    "sg:province":"Noord-Brabant",
    "wof:name":"Maas Kleding Bv",
    "wof:placetype":"venue"
},
  "geometry": {"coordinates":[5.077466,51.552132],"type":"Point"}
}