{
  "type": "Feature",
  "properties": {
    "iso:country":"NL",
    "sg:address":"Korvelseweg 56",
    "sg:city":"Tilburg",
    "sg:orig_category":"Bruidskleding",
    "sg:phone":"+31 13 542 4283",
    "sg:postcode":"5025 JJ",
    "sg:province":"Noord-Brabant",
    "wof:name":"Maas Kleding Bv",
    "wof:placetype":"venue"
},
  "geometry": {"coordinates":[5.077466,51.552132],"type":"Point"}
}