{
  "type": "Feature",
  "properties": {
    "iso:country":"NL",
    "sg:address":"Lange Bisschopstraat 16",
    "sg:city":"Deventer",
    "sg:classifiers":[
        {
            "category":"Retail",
            "subcategory":"Photofinishing",
            "type":"Services"
        }
    ],
    "sg:phone":"+31 570 641 200",
    "sg:postcode":"7411 KK",
    "sg:province":"Overijssel",
    "sg:tags":[
        "foto",
        "film"
    ],
    "wof:name":"Vof T.M. Kemerlings",
    "wof:placetype":"venue"
},
  "geometry": {"coordinates":[6.156668,52.252666],"type":"Point"}
}