{
  "type": "Feature",
  "properties": {
    "addr:full":"Vredehofwg 30 Rotterdam Zuid-Holland 3062 EP",
    "addr:housenumber":"30",
    "addr:postcode":"3062 ep",
    "addr:street":"Vredehofwg",
    "iso:country":"NL",
    "sg:address":"Vredehofwg 30",
    "sg:city":"Rotterdam",
    "sg:orig_category":"Scholen Voor Basisonderwijs",
    "sg:phone":"+31 10 452 6519",
    "sg:postcode":"3062 EP",
    "sg:province":"Zuid-Holland",
    "wof:name":"Vredehof",
    "wof:placetype":"venue"
},
  "geometry": {"coordinates":[4.515973,51.925991],"type":"Point"}
}