{
  "type": "Feature",
  "properties": {
    "addr:full":"Marktpln 4 Esch North Brabant 5296 NA",
    "addr:housenumber":"4",
    "addr:postcode":"5296 na",
    "addr:street":"Marktpln",
    "iso:country":"NL",
    "sg:address":"Marktpln 4",
    "sg:city":"Esch",
    "sg:orig_category":"Adviesbureaus Bedrijfsorganisatie",
    "sg:phone":"+31 411 601 998",
    "sg:postcode":"5296 NA",
    "sg:province":"North Brabant",
    "wof:name":"Comab Bv",
    "wof:placetype":"venue"
},
  "geometry": {"coordinates":[5.291129,51.611526],"type":"Point"}
}