{
  "type": "Feature",
  "properties": {
    "iso:country":"NL",
    "sg:address":"Achter St Aagten 6",
    "sg:city":"Lisse",
    "sg:orig_category":"Adviesbureaus Bedrijfsorganisatie",
    "sg:phone":"+31 252 418 884",
    "sg:postcode":"2161 KA",
    "sg:province":"Zuid-Holland",
    "wof:name":"Bostelaar-Mulder, D",
    "wof:placetype":"venue"
},
  "geometry": {"coordinates":[4.555543,52.256283],"type":"Point"}
}