{
  "type": "Feature",
  "properties": {
    "addr:full":"Vlier 1 Geldrop Noord-Brabant 5662 TM",
    "addr:housenumber":"1",
    "addr:postcode":"5662 tm",
    "addr:street":"Vlier",
    "iso:country":"NL",
    "sg:address":"Vlier 1",
    "sg:city":"Geldrop",
    "sg:orig_category":"Evenementenverzorging",
    "sg:phone":"+31 40 286 9630",
    "sg:postcode":"5662 TM",
    "sg:province":"Noord-Brabant",
    "wof:name":"Department B",
    "wof:placetype":"venue"
},
  "geometry": {"coordinates":[5.545196,51.426197],"type":"Point"}
}