{
  "type": "Feature",
  "properties": {
    "addr:full":"Oosterdorpsstr 102A Hoevelaken Gelderland 3871 AG",
    "addr:housenumber":"102a",
    "addr:postcode":"3871",
    "addr:street":"Gelderland",
    "iso:country":"NL",
    "sg:address":"Oosterdorpsstr 102A",
    "sg:city":"Hoevelaken",
    "sg:orig_category":"Wasmachines En Wasdrogers",
    "sg:phone":"+31 33 253 6538",
    "sg:postcode":"3871 AG",
    "sg:province":"Gelderland",
    "wof:name":"Veluw Witgoed",
    "wof:placetype":"venue"
},
  "geometry": {"coordinates":[5.468506813,52.1752357483],"type":"Point"}
}