{
  "type": "Feature",
  "properties": {
    "addr:full":"Frans Rietveldpad 42 Schiedam South Holland 3123 CD",
    "addr:housenumber":"42",
    "addr:postcode":"3123 cd",
    "addr:street":"Frans Rietveldpad",
    "iso:country":"NL",
    "sg:address":"Frans Rietveldpad 42",
    "sg:city":"Schiedam",
    "sg:orig_category":"Elektronische Bedrijfsinstallaties",
    "sg:phone":"+31 10 247 0371",
    "sg:postcode":"3123 CD",
    "sg:province":"South Holland",
    "wof:name":"Total Dutch",
    "wof:placetype":"venue"
},
  "geometry": {"coordinates":[4.367047,51.942341],"type":"Point"}
}