{
  "type": "Feature",
  "properties": {
    "addr:full":"Boterdijk 160 De Kwakel Noord-Holland 1424 NK",
    "addr:housenumber":"160",
    "addr:postcode":"1424 nk",
    "addr:street":"Boterdijk",
    "iso:country":"NL",
    "sg:address":"Boterdijk 160",
    "sg:city":"De Kwakel",
    "sg:orig_category":"Gemengde Landbouwbedrijven",
    "sg:phone":"+31 297 565 089",
    "sg:postcode":"1424 NK",
    "sg:province":"Noord-Holland",
    "wof:name":"A. Van Zanten",
    "wof:placetype":"venue"
},
  "geometry": {"coordinates":[4.799595,52.240898],"type":"Point"}
}