{
  "type": "Feature",
  "properties": {
    "addr:full":"Wingerdweg 45 Amsterdam North Holland 1031 BZ",
    "addr:housenumber":"45",
    "addr:postcode":"1031 bz",
    "addr:street":"Wingerdweg",
    "iso:country":"NL",
    "sg:address":"Wingerdweg 45",
    "sg:city":"Amsterdam",
    "sg:orig_category":"Gespecialiseerde Voeding",
    "sg:phone":"+31 20 636 1978",
    "sg:postcode":"1031 BZ",
    "sg:province":"North Holland",
    "wof:name":"Yildiz Market",
    "wof:placetype":"venue"
},
  "geometry": {"coordinates":[4.915,52.389923],"type":"Point"}
}