{
  "type": "Feature",
  "properties": {
    "addr:full":"Ghijseland 114 Rhoon South Holland 3161 VJ",
    "addr:housenumber":"114",
    "addr:postcode":"3161 vj",
    "addr:street":"Ghijseland",
    "iso:country":"NL",
    "sg:address":"Ghijseland 114",
    "sg:city":"Rhoon",
    "sg:orig_category":"Fitnesscentra",
    "sg:phone":"+31 10 501 6700",
    "sg:postcode":"3161 VJ",
    "sg:province":"South Holland",
    "wof:name":"Sportschool Roel Van Ravens Bv",
    "wof:placetype":"venue"
},
  "geometry": {"coordinates":[4.432151,51.856602],"type":"Point"}
}