{
  "type": "Feature",
  "properties": {
    "iso:country":"NL",
    "sg:address":"Melkwg 2-2A",
    "sg:city":"Doetinchem",
    "sg:orig_category":"Administratie- En Boekhoudkantoren",
    "sg:phone":"+31 314 345 135",
    "sg:postcode":"7005 AH",
    "sg:province":"Gelderland",
    "wof:name":"B & P",
    "wof:placetype":"venue"
},
  "geometry": {"coordinates":[6.292611,51.961449],"type":"Point"}
}