{
  "type": "Feature",
  "properties": {
    "addr:full":"Eiberstr 65 Velp Gld Gelderland 6883 ED",
    "addr:housenumber":"65",
    "addr:postcode":"6883 ed",
    "addr:street":"Eiberstr;Gld Gelderland",
    "iso:country":"NL",
    "sg:address":"Eiberstr 65",
    "sg:city":"Velp Gld",
    "sg:orig_category":"Boomrooierijen",
    "sg:phone":"+31 26 364 2477",
    "sg:postcode":"6883 ED",
    "sg:province":"Gelderland",
    "wof:name":"Nikai Koot Boomrooierij",
    "wof:placetype":"venue"
},
  "geometry": {"coordinates":[5.987084,51.989006],"type":"Point"}
}