{
  "type": "Feature",
  "properties": {
    "iso:country":"NL",
    "sg:address":"Lijsterbesstr 22",
    "sg:city":"Gouda",
    "sg:classifiers":[
        {
            "category":"Personal",
            "subcategory":"Nail Salon",
            "type":"Services"
        }
    ],
    "sg:phone":"+31 182 528 102",
    "sg:postcode":"2802 KT",
    "sg:province":"Zuid-Holland",
    "sg:tags":[
        "pedicure"
    ],
    "wof:name":"Kammeraat, W",
    "wof:placetype":"venue"
},
  "geometry": {"coordinates":[4.704691,52.007175],"type":"Point"}
}