{
  "type": "Feature",
  "properties": {
    "addr:full":"De Kl Elst 36 Rosmalen Noord-Brabant 5246 JJ",
    "addr:housenumber":"36",
    "addr:postcode":"5246 jj",
    "addr:street":"De Kl Elst",
    "iso:country":"NL",
    "sg:address":"De Kl Elst 36",
    "sg:city":"Rosmalen",
    "sg:orig_category":"Verpakkingen En Verpakkingsmaterialen",
    "sg:phone":"+31 73 643 1655",
    "sg:postcode":"5246 JJ",
    "sg:province":"Noord-Brabant",
    "wof:name":"Ottenheijm, Theo",
    "wof:placetype":"venue"
},
  "geometry": {"coordinates":[5.341287,51.70536],"type":"Point"}
}