{
  "type": "Feature",
  "properties": {
    "addr:full":"Westerdorpsstraat 19 Hoevelaken Gelderland 3871 AT",
    "addr:housenumber":"19",
    "addr:postcode":"3871",
    "addr:street":"Westerdorpsstraat;Gelderland",
    "iso:country":"NL",
    "sg:address":"Westerdorpsstraat 19",
    "sg:city":"Hoevelaken",
    "sg:orig_category":"Damesmodezaken",
    "sg:phone":"+31 33 253 6140",
    "sg:postcode":"3871 AT",
    "sg:province":"Gelderland",
    "wof:name":"Boutique 'T Klavertje",
    "wof:placetype":"venue"
},
  "geometry": {"coordinates":[5.455697,52.175331],"type":"Point"}
}