{
  "type": "Feature",
  "properties": {
    "iso:country":"NL",
    "sg:address":"Mendelssohnstraat 15",
    "sg:city":"Amersfoort",
    "sg:orig_category":"Koeriersdiensten",
    "sg:phone":"+31 33 475 2813",
    "sg:postcode":"3816 NW",
    "sg:province":"Utrecht",
    "wof:name":"E. Van Ouwerkerk Koeriersdienst Almere",
    "wof:placetype":"venue"
},
  "geometry": {"coordinates":[5.406453,52.154877],"type":"Point"}
}