{
  "type": "Feature",
  "properties": {
    "iso:country":"NL",
    "sg:address":"Straatwg 74",
    "sg:city":"Breukelen Ut",
    "sg:orig_category":"Onroerende Goederen",
    "sg:phone":"+31 346 261 747",
    "sg:postcode":"3621 BR",
    "sg:province":"Utrecht",
    "wof:name":"Habeas Corpus Bv",
    "wof:placetype":"venue"
},
  "geometry": {"coordinates":[5.004455,52.169453],"type":"Point"}
}