{
  "type": "Feature",
  "properties": {
    "addr:full":"Raadhuisstraat 8 Oirsbeek Limburg 6438 GZ",
    "addr:housenumber":"8",
    "addr:postcode":"6438 gz",
    "addr:street":"Raadhuisstraat",
    "iso:country":"NL",
    "sg:address":"Raadhuisstraat 8",
    "sg:city":"Oirsbeek",
    "sg:orig_category":"Overheidsdiensten",
    "sg:phone":"+31 46 442 1029",
    "sg:postcode":"6438 GZ",
    "sg:province":"Limburg",
    "wof:name":"Gemeenschapshuis",
    "wof:placetype":"venue"
},
  "geometry": {"coordinates":[5.9080600739,50.9507751465],"type":"Point"}
}