{
  "type": "Feature",
  "properties": {
    "iso:country":"NL",
    "sg:address":"Ina Boudier-Bakkerlaan 75",
    "sg:city":"Utrecht",
    "sg:orig_category":"Vertaal- And Tolkenbureaus",
    "sg:phone":"+31 30 258 1121",
    "sg:postcode":"3582 VW",
    "sg:province":"Utrecht",
    "wof:name":"Albanese Taalservice",
    "wof:placetype":"venue"
},
  "geometry": {"coordinates":[5.131943,52.080505],"type":"Point"}
}