{
  "type": "Feature",
  "properties": {
    "iso:country":"NL",
    "sg:address":"Provincialewg 1C",
    "sg:city":"Veldhoven",
    "sg:orig_category":"Fietsen En Bromfietsen",
    "sg:phone":"+31 40 253 2680",
    "sg:postcode":"5503 HA",
    "sg:province":"Noord-Brabant",
    "wof:name":"Herk",
    "wof:placetype":"venue"
},
  "geometry": {"coordinates":[5.41184,51.41098],"type":"Point"}
}