{
  "type": "Feature",
  "properties": {
    "addr:full":"Nagelbeek 7 Schinnen Limburg 6365 EH",
    "addr:housenumber":"7",
    "addr:postcode":"6365 eh",
    "addr:street":"Nagelbeek",
    "iso:country":"NL",
    "sg:address":"Nagelbeek 7",
    "sg:city":"Schinnen",
    "sg:orig_category":"Verhuur Audiovisuele Apparatuur",
    "sg:phone":"+31 46 443 6100",
    "sg:postcode":"6365 EH",
    "sg:province":"Limburg",
    "wof:name":"Stock Audio",
    "wof:placetype":"venue"
},
  "geometry": {"coordinates":[5.873724,50.937553],"type":"Point"}
}