{
  "type": "Feature",
  "properties": {
    "addr:full":"Truyenhoekweg 1B Weert Limburg 6004 PV",
    "addr:housenumber":"1b",
    "addr:postcode":"6004 pv",
    "addr:street":"Truyenhoekweg",
    "iso:country":"NL",
    "sg:address":"Truyenhoekweg 1B",
    "sg:city":"Weert",
    "sg:orig_category":"Pluimveehouderijen",
    "sg:phone":"+31 495 533 163",
    "sg:postcode":"6004 PV",
    "sg:province":"Limburg",
    "wof:name":"J.H. Tullemans Teeuwen",
    "wof:placetype":"venue"
},
  "geometry": {"coordinates":[5.738881,51.265499],"type":"Point"}
}