{
  "type": "Feature",
  "properties": {
    "addr:full":"Snekerveste 28 Nieuwegein Utrecht 3432 RC",
    "addr:housenumber":"28",
    "addr:postcode":"3432 rc",
    "addr:street":"Snekerveste",
    "iso:country":"NL",
    "sg:address":"Snekerveste 28",
    "sg:city":"Nieuwegein",
    "sg:orig_category":"Makelaars En Adviseurs Onroerende Goederen",
    "sg:phone":"+31 30 604 8152",
    "sg:postcode":"3432 RC",
    "sg:province":"Utrecht",
    "wof:name":"Woudenberg",
    "wof:placetype":"venue"
},
  "geometry": {"coordinates":[5.09612,52.025063],"type":"Point"}
}