{
  "type": "Feature",
  "properties": {
    "addr:full":"Bunschotenstraat 91 Tilburg Noord-Brabant 5043 BB",
    "addr:housenumber":"91",
    "addr:postcode":"5043 bb",
    "addr:street":"Bunschotenstraat",
    "iso:country":"NL",
    "sg:address":"Bunschotenstraat 91",
    "sg:city":"Tilburg",
    "sg:orig_category":"Kappers",
    "sg:phone":"+31 13 570 1591",
    "sg:postcode":"5043 BB",
    "sg:province":"Noord-Brabant",
    "wof:name":"Dameskappersbedrijf Inge Van Groesen",
    "wof:placetype":"venue"
},
  "geometry": {"coordinates":[5.0154671669,51.5823287964],"type":"Point"}
}