{
  "type": "Feature",
  "properties": {
    "addr:full":"Zuiddijk 18 Helmond North Brabant 5705 CS",
    "addr:housenumber":"18",
    "addr:postcode":"5705 cs",
    "addr:street":"Zuiddijk",
    "iso:country":"NL",
    "sg:address":"Zuiddijk 18",
    "sg:city":"Helmond",
    "sg:orig_category":"Meubelzaken, Woning- And Keukeninrichting",
    "sg:phone":"+31 492 548 186",
    "sg:postcode":"5705 CS",
    "sg:province":"North Brabant",
    "wof:name":"Aswa Bv",
    "wof:placetype":"venue"
},
  "geometry": {"coordinates":[5.658284,51.482239],"type":"Point"}
}