{
  "type": "Feature",
  "properties": {
    "iso:country":"NL",
    "sg:address":"Dykln 188",
    "sg:city":"Bergambacht",
    "sg:orig_category":"Keukens",
    "sg:phone":"+31 182 353 692",
    "sg:postcode":"2861 EL",
    "sg:province":"South Holland",
    "wof:name":"Bruchem Montagebedrijf Van",
    "wof:placetype":"venue"
},
  "geometry": {"coordinates":[4.783119,51.936462],"type":"Point"}
}