{
  "type": "Feature",
  "properties": {
    "addr:full":"Zuiderzeestraatweg 82 Oldebroek Gelderland 8096 CC",
    "addr:housenumber":"82",
    "addr:postcode":"8096 cc",
    "addr:street":"Zuiderzeestraatweg;Gelderland",
    "iso:country":"NL",
    "sg:address":"Zuiderzeestraatweg 82",
    "sg:city":"Oldebroek",
    "sg:orig_category":"Meubelzaken, Woning- And Keukeninrichting",
    "sg:phone":"+31 525 631 454",
    "sg:postcode":"8096 CC",
    "sg:province":"Gelderland",
    "wof:name":"Rietshop De Bedstede Jannetta Van Der Ziel",
    "wof:placetype":"venue"
},
  "geometry": {"coordinates":[5.895279,52.446358],"type":"Point"}
}