{
  "type": "Feature",
  "properties": {
    "iso:country":"NL",
    "sg:address":"Kon Julianapln 20",
    "sg:city":"Voorburg",
    "sg:orig_category":"Herenkleding",
    "sg:phone":"+31 70 386 4931",
    "sg:postcode":"2273 BR",
    "sg:province":"Zuid-Holland",
    "wof:name":"Verbakel Modehuis Voorburg Bv",
    "wof:placetype":"venue"
},
  "geometry": {"coordinates":[4.357588,52.076378],"type":"Point"}
}