{
  "type": "Feature",
  "properties": {
    "addr:full":"P Cornelisz Hooftstr 154 Amsterdam North Holland 1071 CG",
    "addr:housenumber":"154",
    "addr:postcode":"1071 cg",
    "addr:street":"P Cornelisz Hooftstr",
    "iso:country":"NL",
    "sg:address":"P Cornelisz Hooftstr 154",
    "sg:city":"Amsterdam",
    "sg:orig_category":"Filmstudio'S En -Productie",
    "sg:phone":"+31 20 470 4446",
    "sg:postcode":"1071 CG",
    "sg:province":"North Holland",
    "wof:name":"Movie Masters Productions",
    "wof:placetype":"venue"
},
  "geometry": {"coordinates":[4.876954,52.359402],"type":"Point"}
}