{
  "type": "Feature",
  "properties": {
    "addr:full":"Nederlandplein 100 Eindhoven North Brabant 5628 AJ",
    "addr:housenumber":"100",
    "addr:postcode":"5628 aj",
    "addr:street":"Nederlandplein",
    "iso:country":"NL",
    "sg:address":"Nederlandplein 100",
    "sg:city":"Eindhoven",
    "sg:orig_category":"Banken And Kredietinstellingen",
    "sg:phone":"+31 40 242 7203",
    "sg:postcode":"5628 AJ",
    "sg:province":"North Brabant",
    "wof:name":"Postkantoor",
    "wof:placetype":"venue"
},
  "geometry": {"coordinates":[5.463175,51.478878],"type":"Point"}
}