{
  "type": "Feature",
  "properties": {
    "addr:full":"Jan Binneslaan 84 Surhuisterveen Friesland 9231 CC",
    "addr:housenumber":"84",
    "addr:postcode":"9231 cc",
    "addr:street":"Jan Binneslaan",
    "iso:country":"NL",
    "sg:address":"Jan Binneslaan 84",
    "sg:city":"Surhuisterveen",
    "sg:orig_category":"Verhuur Catering-, Feest- En Evenementbenodigdheden",
    "sg:phone":"+31 512 361 962",
    "sg:postcode":"9231 CC",
    "sg:province":"Friesland",
    "wof:name":"Firma G.B. Droogers",
    "wof:placetype":"venue"
},
  "geometry": {"coordinates":[6.169053,53.179974],"type":"Point"}
}