{
  "type": "Feature",
  "properties": {
    "addr:full":"Waterstr 68 Delfzyl Groningen 9934 AX",
    "addr:housenumber":"68",
    "addr:postcode":"9934 ax",
    "addr:street":"Waterstr",
    "iso:country":"NL",
    "sg:address":"Waterstr 68",
    "sg:city":"Delfzyl",
    "sg:orig_category":"Herenkleding",
    "sg:phone":"+31 596 613 686",
    "sg:postcode":"9934 AX",
    "sg:province":"Groningen",
    "wof:name":"Hulst",
    "wof:placetype":"venue"
},
  "geometry": {"coordinates":[6.925883,53.3326],"type":"Point"}
}