{
  "type": "Feature",
  "properties": {
    "addr:full":"Produktiewg 44 Zoeterwoude Zuid-Holland 2382 PC",
    "addr:housenumber":"44",
    "addr:postcode":"2382 pc",
    "addr:street":"Produktiewg",
    "iso:country":"NL",
    "sg:address":"Produktiewg 44",
    "sg:city":"Zoeterwoude",
    "sg:orig_category":"Horeca-Inrichtingen En -Uitrustingen",
    "sg:phone":"+31 71 589 9353",
    "sg:postcode":"2382 PC",
    "sg:province":"Zuid-Holland",
    "wof:name":"Schoondergang Bv",
    "wof:placetype":"venue"
},
  "geometry": {"coordinates":[4.516476,52.140972],"type":"Point"}
}