{
  "type": "Feature",
  "properties": {
    "addr:full":"K Water 282 Amsterdam North Holland 1069 GT",
    "addr:housenumber":"282",
    "addr:postcode":"1069 gt",
    "addr:street":"K Water",
    "iso:country":"NL",
    "sg:address":"K Water 282",
    "sg:city":"Amsterdam",
    "sg:orig_category":"Verenigingen En Stichtingen",
    "sg:phone":"+31 20 685 1722",
    "sg:postcode":"1069 GT",
    "sg:province":"North Holland",
    "wof:name":"Mantaan",
    "wof:placetype":"venue"
},
  "geometry": {"coordinates":[4.79634,52.349709],"type":"Point"}
}