{
  "type": "Feature",
  "properties": {
    "addr:full":"Dorpsstr 52 Bleiswyk South Holland 2665 BJ",
    "addr:housenumber":"52",
    "addr:postcode":"2665 bj",
    "addr:street":"Dorpsstr",
    "iso:country":"NL",
    "sg:address":"Dorpsstr 52",
    "sg:city":"Bleiswyk",
    "sg:orig_category":"Makelaars En Adviseurs Onroerende Goederen",
    "sg:phone":"+31 10 521 7377",
    "sg:postcode":"2665 BJ",
    "sg:province":"South Holland",
    "sg:website":"http://www.nvm.nl",
    "wof:name":"Schaefer Bv",
    "wof:placetype":"venue"
},
  "geometry": {"coordinates":[4.529839,52.010075],"type":"Point"}
}