{
  "type": "Feature",
  "properties": {
    "addr:full":"M De Vriesstr 6A Breda Noord-Brabant 4812 GC",
    "addr:housenumber":"6a",
    "addr:postcode":"4812 gc",
    "addr:street":"M;Vriesstr",
    "iso:country":"NL",
    "sg:address":"M De Vriesstr 6A",
    "sg:city":"Breda",
    "sg:orig_category":"Adviesbureaus Bedrijfsorganisatie",
    "sg:phone":"+31 76 520 4734",
    "sg:postcode":"4812 GC",
    "sg:province":"Noord-Brabant",
    "wof:name":"Humanz",
    "wof:placetype":"venue"
},
  "geometry": {"coordinates":[4.755995,51.574764],"type":"Point"}
}