{
  "type": "Feature",
  "properties": {
    "addr:full":"Ossewg 52 Berghem Noord-Brabant 5351 AE",
    "addr:housenumber":"52",
    "addr:postcode":"5351 ae",
    "addr:street":"Ossewg",
    "iso:country":"NL",
    "sg:address":"Ossewg 52",
    "sg:city":"Berghem",
    "sg:orig_category":"Keukens",
    "sg:phone":"+31 412 403 362",
    "sg:postcode":"5351 AE",
    "sg:province":"Noord-Brabant",
    "wof:name":"Schadewijk, N Van",
    "wof:placetype":"venue"
},
  "geometry": {"coordinates":[5.556436,51.769756],"type":"Point"}
}