{
  "type": "Feature",
  "properties": {
    "iso:country":"NL",
    "sg:address":"Klaasstr 3",
    "sg:city":"Venlo",
    "sg:orig_category":"Opticiens",
    "sg:phone":"+31 77 354 4580",
    "sg:postcode":"5911 JM",
    "sg:province":"Limburg",
    "wof:name":"Huis Havelaer, Het",
    "wof:placetype":"venue"
},
  "geometry": {"coordinates":[6.1691789627,51.3692092896],"type":"Point"}
}