{
  "type": "Feature",
  "properties": {
    "iso:country":"NL",
    "sg:address":"Iepenlaan 4",
    "sg:city":"Bilthoven",
    "sg:orig_category":"Verzekeringen",
    "sg:phone":"+31 30 228 7825",
    "sg:postcode":"3723 XH",
    "sg:province":"Utrecht",
    "wof:name":"Assurantiekantoor Rob Boon",
    "wof:placetype":"venue"
},
  "geometry": {"coordinates":[5.187286,52.128521],"type":"Point"}
}