{
  "type": "Feature",
  "properties": {
    "iso:country":"NL",
    "sg:address":"Kerkstraat 25",
    "sg:city":"Nieuwkuijk",
    "sg:orig_category":"Autokeuringen",
    "sg:phone":"+31 73 511 9556",
    "sg:postcode":"5253 AN",
    "sg:province":"Noord-Brabant",
    "wof:name":"A.J. Van Drunen",
    "wof:placetype":"venue"
},
  "geometry": {"coordinates":[5.176037,51.694813],"type":"Point"}
}