{
  "type": "Feature",
  "properties": {
    "addr:full":"Buitenhofdreef 268 Delft South Holland 2625 RE",
    "addr:housenumber":"268",
    "addr:postcode":"2625 re",
    "addr:street":"Buitenhofdreef",
    "iso:country":"NL",
    "sg:address":"Buitenhofdreef 268",
    "sg:city":"Delft",
    "sg:orig_category":"Banken And Kredietinstellingen",
    "sg:phone":"+31 15 270 0600",
    "sg:postcode":"2625 RE",
    "sg:province":"South Holland",
    "wof:name":"Rabobank",
    "wof:placetype":"venue"
},
  "geometry": {"coordinates":[4.344155,51.991859],"type":"Point"}
}