{
  "type": "Feature",
  "properties": {
    "iso:country":"NL",
    "sg:address":"J V Deventerstr 2",
    "sg:city":"Deventer",
    "sg:orig_category":"Verzekeringen - Verzekeringskantoren",
    "sg:phone":"+31 570 672 404",
    "sg:postcode":"7412 EV",
    "sg:province":"NL.08",
    "wof:name":"Athena & Kamminga Vof",
    "wof:placetype":"venue"
},
  "geometry": {"coordinates":[6.159899,52.251034],"type":"Point"}
}