{
  "type": "Feature",
  "properties": {
    "addr:full":"Lorentzwg 6 Spykenisse Zuid-Holland 3208 LJ",
    "addr:housenumber":"6",
    "addr:postcode":"3208 lj",
    "addr:street":"Lorentzwg",
    "iso:country":"NL",
    "sg:address":"Lorentzwg 6",
    "sg:city":"Spykenisse",
    "sg:classifiers":[
        {
            "category":"Retail",
            "subcategory":"Storage",
            "type":"Services"
        }
    ],
    "sg:phone":"+31 181 627 555",
    "sg:postcode":"3208 LJ",
    "sg:province":"Zuid-Holland",
    "sg:tags":[
        "op-",
        "en",
        "overslagbedrijven"
    ],
    "wof:name":"Warehouse",
    "wof:placetype":"venue"
},
  "geometry": {"coordinates":[4.294964,51.851704],"type":"Point"}
}