{
  "type": "Feature",
  "properties": {
    "addr:full":"Alexandrium 1 Rotterdam Zuid-Holland 3067 LX",
    "addr:housenumber":"1",
    "addr:postcode":"3067 lx",
    "addr:street":"Alexandrium",
    "iso:country":"NL",
    "sg:address":"Alexandrium 1",
    "sg:city":"Rotterdam",
    "sg:orig_category":"Opticiens",
    "sg:phone":"+31 10 286 7512",
    "sg:postcode":"3067 LX",
    "sg:province":"Zuid-Holland",
    "wof:name":"Brillen Kabinet, Het",
    "wof:placetype":"venue"
},
  "geometry": {"coordinates":[4.5638389587,51.9493179321],"type":"Point"}
}