{
  "type": "Feature",
  "properties": {
    "addr:full":"Binnenhavenstraat 53 Hengelo Ov NL.08 7553 GH",
    "addr:housenumber":"53",
    "addr:postcode":"7553 gh",
    "addr:street":"Binnenhavenstraat;Ov",
    "iso:country":"NL",
    "sg:address":"Binnenhavenstraat 53",
    "sg:city":"Hengelo Ov",
    "sg:orig_category":"Metaalbekleding And -Behandeling",
    "sg:phone":"+31 74 242 0000",
    "sg:postcode":"7553 GH",
    "sg:province":"NL.08",
    "wof:name":"Satink Coatingsystems Bv",
    "wof:placetype":"venue"
},
  "geometry": {"coordinates":[6.779601,52.250977],"type":"Point"}
}