{
  "type": "Feature",
  "properties": {
    "addr:full":"Keytenburgstr 8A Rucphen Noord-Brabant 4715 PN",
    "addr:housenumber":"8a",
    "addr:postcode":"4715 pn",
    "addr:street":"Keytenburgstr",
    "iso:country":"NL",
    "sg:address":"Keytenburgstr 8A",
    "sg:city":"Rucphen",
    "sg:classifiers":[
        {
            "category":"Sports & Exercise",
            "subcategory":"Stables",
            "type":"Entertainment"
        }
    ],
    "sg:phone":"+31 165 341 450",
    "sg:postcode":"4715 PN",
    "sg:province":"Noord-Brabant",
    "sg:tags":[
        "maneges"
    ],
    "sg:website":"http://www.manegekeytenburg.nl",
    "wof:name":"Nieuw Keytenburg",
    "wof:placetype":"venue"
},
  "geometry": {"coordinates":[4.536328,51.532448],"type":"Point"}
}