{
  "type": "Feature",
  "properties": {
    "addr:full":"Postbus 2 Wilnis Utrecht 3648 ZG",
    "addr:housenumber":"2",
    "addr:postcode":"3648 zg",
    "addr:street":"Postbus",
    "iso:country":"NL",
    "sg:address":"Postbus 2",
    "sg:city":"Wilnis",
    "sg:orig_category":"Voetbalverenigingen",
    "sg:phone":"+31 297 272 415",
    "sg:postcode":"3648 ZG",
    "sg:province":"Utrecht",
    "wof:name":"Csw",
    "wof:placetype":"venue"
},
  "geometry": {"coordinates":[4.90548,52.196732],"type":"Point"}
}