{
  "type": "Feature",
  "properties": {
    "addr:full":"Postbus 400 Oostvoorne South Holland 3233 ZJ",
    "addr:housenumber":"400",
    "addr:postcode":"3233 zj",
    "addr:street":"Postbus",
    "iso:country":"NL",
    "sg:address":"Postbus 400",
    "sg:city":"Oostvoorne",
    "sg:orig_category":"Verenigingen En Stichtingen",
    "sg:phone":"+31 181 402 198",
    "sg:postcode":"3233 ZJ",
    "sg:province":"South Holland",
    "wof:name":"Historische Ver Westelijk Voorne",
    "wof:placetype":"venue"
},
  "geometry": {"coordinates":[4.103859,51.913956],"type":"Point"}
}