{
  "type": "Feature",
  "properties": {
    "iso:country":"NL",
    "sg:address":"Van Gentstraat 18E",
    "sg:city":"Nijmegen",
    "sg:orig_category":"Fotostudio'S And Fotografen",
    "sg:phone":"+31 24 323 9817",
    "sg:postcode":"6524 BC",
    "sg:province":"Gelderland",
    "wof:name":"B.G.J.M. Joppen",
    "wof:placetype":"venue"
},
  "geometry": {"coordinates":[5.866405,51.839924],"type":"Point"}
}