{
  "type": "Feature",
  "properties": {
    "addr:full":"Dokter Delissenstraat 15 Gulpen Limburg 6271 GG",
    "addr:housenumber":"15",
    "addr:postcode":"6271 gg",
    "addr:street":"Dokter Delissenstraat",
    "iso:country":"NL",
    "sg:address":"Dokter Delissenstraat 15",
    "sg:city":"Gulpen",
    "sg:orig_category":"Verhuur Diversen",
    "sg:phone":"+31 43 450 3437",
    "sg:postcode":"6271 GG",
    "sg:province":"Limburg",
    "wof:name":"Marktkramenverhuurbedrijf J. Van Der Sangen",
    "wof:placetype":"venue"
},
  "geometry": {"coordinates":[5.888646,50.818539],"type":"Point"}
}