{
  "type": "Feature",
  "properties": {
    "iso:country":"NL",
    "sg:address":"Lingedk 96",
    "sg:city":"Rhenoy",
    "sg:orig_category":"Verzekeringen - Verzekeringskantoren",
    "sg:phone":"+31 345 681 382",
    "sg:postcode":"4152 EC",
    "sg:province":"Gelderland",
    "sg:website":"http://storyass.nl",
    "wof:name":"Story Bv",
    "wof:placetype":"venue"
},
  "geometry": {"coordinates":[5.155246,51.881943],"type":"Point"}
}