{
  "type": "Feature",
  "properties": {
    "addr:full":"Kaldenkerkerweg 57 Venlo Limburg 5915 AA",
    "addr:housenumber":"57",
    "addr:postcode":"5915 aa",
    "addr:street":"Kaldenkerkerweg",
    "iso:country":"NL",
    "sg:address":"Kaldenkerkerweg 57",
    "sg:city":"Venlo",
    "sg:orig_category":"Autokeuringen",
    "sg:phone":"+31 77 351 8375",
    "sg:postcode":"5915 AA",
    "sg:province":"Limburg",
    "wof:name":"P.S. Bogdanski",
    "wof:placetype":"venue"
},
  "geometry": {"coordinates":[6.177468,51.36047],"type":"Point"}
}