{
  "type": "Feature",
  "properties": {
    "iso:country":"NL",
    "sg:address":"Platinalaan 511",
    "sg:city":"Groningen",
    "sg:orig_category":"Verzekeringen",
    "sg:phone":"+31 50 571 8169",
    "sg:postcode":"9743 GZ",
    "sg:province":"Groningen",
    "wof:name":"J. Schulenklopper",
    "wof:placetype":"venue"
},
  "geometry": {"coordinates":[6.529311,53.224606],"type":"Point"}
}