{
  "type": "Feature",
  "properties": {
    "addr:full":"Wierssewg 7 Ruurlo Gelderland 7261 AA",
    "addr:housenumber":"7",
    "addr:postcode":"7261 aa",
    "addr:street":"Wierssewg;Gelderland",
    "iso:country":"NL",
    "sg:address":"Wierssewg 7",
    "sg:city":"Ruurlo",
    "sg:orig_category":"Administratie- En Boekhoudkantoren",
    "sg:phone":"+31 573 452 152",
    "sg:postcode":"7261 AA",
    "sg:province":"Gelderland",
    "wof:name":"Md Support",
    "wof:placetype":"venue"
},
  "geometry": {"coordinates":[6.447577,52.085075],"type":"Point"}
}