{
  "type": "Feature",
  "properties": {
    "addr:full":"Pauvrewg 21A Etten Leur Noord-Brabant 4879 NJ",
    "addr:housenumber":"21a",
    "addr:postcode":"4879 nj",
    "addr:street":"Pauvrewg",
    "iso:country":"NL",
    "sg:address":"Pauvrewg 21A",
    "sg:city":"Etten Leur",
    "sg:orig_category":"Machinehandel",
    "sg:phone":"+31 76 503 3100",
    "sg:postcode":"4879 NJ",
    "sg:province":"Noord-Brabant",
    "wof:name":"Metalmeccanica Plast Bv",
    "wof:placetype":"venue"
},
  "geometry": {"coordinates":[4.6244,51.558613],"type":"Point"}
}