{
  "type": "Feature",
  "properties": {
    "iso:country":"NL",
    "sg:address":"Ameidestr 186A",
    "sg:city":"Rotterdam",
    "sg:orig_category":"Logopedisten",
    "sg:phone":"+31 10 415 5875",
    "sg:postcode":"3042 DA",
    "sg:province":"South Holland",
    "wof:name":"Logopediepraktijk Overschie",
    "wof:placetype":"venue"
},
  "geometry": {"coordinates":[4.438845,51.932858],"type":"Point"}
}