{
  "type": "Feature",
  "properties": {
    "addr:full":"Kennemerpark 20 Alkmaar Noord-Holland 1811 DE",
    "addr:housenumber":"20",
    "addr:postcode":"1811 de",
    "addr:street":"Kennemerpark",
    "iso:country":"NL",
    "sg:address":"Kennemerpark 20",
    "sg:city":"Alkmaar",
    "sg:classifiers":[
        {
            "category":"Professional",
            "subcategory":"Accounting & Tax Preparation",
            "type":"Services"
        }
    ],
    "sg:phone":"+31 72 512 2281",
    "sg:postcode":"1811 DE",
    "sg:province":"Noord-Holland",
    "sg:tags":[
        "accountant"
    ],
    "wof:name":"Accountantskantoor De Man Bv",
    "wof:placetype":"venue"
},
  "geometry": {"coordinates":[4.745594,52.629032],"type":"Point"}
}