{
  "type": "Feature",
  "properties": {
    "addr:full":"Amperestr 34 Heerhugowaard North Holland 1704 SN",
    "addr:housenumber":"34",
    "addr:postcode":"1704 sn",
    "addr:street":"Amperestr",
    "iso:country":"NL",
    "sg:address":"Amperestr 34",
    "sg:city":"Heerhugowaard",
    "sg:orig_category":"Verf En Lak - Fabrieken En Groothandel",
    "sg:phone":"+31 72 572 0231",
    "sg:postcode":"1704 SN",
    "sg:province":"North Holland",
    "sg:website":"http://www.weezenbeek.nl",
    "wof:name":"Weezenbeek, Van",
    "wof:placetype":"venue"
},
  "geometry": {"coordinates":[4.833477,52.69014],"type":"Point"}
}