{
  "type": "Feature",
  "properties": {
    "addr:full":"Bellstr 4 Barneveld Gelderland 3771 AH",
    "addr:housenumber":"4",
    "addr:postcode":"3771 ah",
    "addr:street":"Bellstr;Gelderland",
    "iso:country":"NL",
    "sg:address":"Bellstr 4",
    "sg:city":"Barneveld",
    "sg:orig_category":"Beleggingen",
    "sg:phone":"+31 342 415 315",
    "sg:postcode":"3771 AH",
    "sg:province":"Gelderland",
    "sg:website":"http://www.vosfinance.nl",
    "wof:name":"Bovo Bv",
    "wof:placetype":"venue"
},
  "geometry": {"coordinates":[5.598209,52.136581],"type":"Point"}
}