{
  "type": "Feature",
  "properties": {
    "addr:full":"Verl Herewg 137 Groningen Groningen 9721 AL",
    "addr:housenumber":"137",
    "addr:postcode":"9721 al",
    "iso:country":"NL",
    "sg:address":"Verl Herewg 137",
    "sg:city":"Groningen",
    "sg:orig_category":"Haptotherapeuten",
    "sg:phone":"+31 50 527 1645",
    "sg:postcode":"9721 AL",
    "sg:province":"Groningen",
    "sg:website":"http://www.haptotherapeuten-vvh.nl",
    "wof:name":"Nauta, W",
    "wof:placetype":"venue"
},
  "geometry": {"coordinates":[6.58123,53.195782],"type":"Point"}
}