{
  "type": "Feature",
  "properties": {
    "addr:full":"5E Donk 61 S Hertogenbosch North Brabant 5233 XM",
    "addr:housenumber":"61",
    "addr:postcode":"5233 xm",
    "addr:street":"5E Donk;S Hertogenbosch",
    "iso:country":"NL",
    "sg:address":"5E Donk 61",
    "sg:city":"S Hertogenbosch",
    "sg:orig_category":"Verenigingen En Stichtingen",
    "sg:phone":"+31 73 642 8743",
    "sg:postcode":"5233 XM",
    "sg:province":"North Brabant",
    "wof:name":"Pelita, Sticht",
    "wof:placetype":"venue"
},
  "geometry": {"coordinates":[5.321473,51.717766],"type":"Point"}
}