{
  "type": "Feature",
  "properties": {
    "iso:country":"NL",
    "sg:address":"Tielsestr 52",
    "sg:city":"Maurik",
    "sg:orig_category":"Pallets - Fabrieken En Groothandel",
    "sg:phone":"+31 344 691 580",
    "sg:postcode":"4021 HD",
    "sg:province":"Gelderland",
    "wof:name":"Rijn-Delta Bv",
    "wof:placetype":"venue"
},
  "geometry": {"coordinates":[5.423815,51.952106],"type":"Point"}
}