{
  "type": "Feature",
  "properties": {
    "addr:full":"Dukaat 59 Dronten NL. 8253 BM",
    "addr:housenumber":"59",
    "addr:postcode":"8253 bm",
    "addr:street":"Dukaat;Nl.",
    "iso:country":"NL",
    "sg:address":"Dukaat 59",
    "sg:city":"Dronten",
    "sg:orig_category":"Etaleurs And Showroominrichters",
    "sg:phone":"+31 321 313 842",
    "sg:postcode":"8253 BM",
    "sg:province":"NL.",
    "wof:name":"Zoe",
    "wof:placetype":"venue"
},
  "geometry": {"coordinates":[5.707148,52.530506],"type":"Point"}
}