{
  "type": "Feature",
  "properties": {
    "addr:full":"Molenweg 42 Koningsbosch Limburg 6104 RG",
    "addr:housenumber":"42",
    "addr:postcode":"6104 rg",
    "addr:street":"Molenweg",
    "iso:country":"NL",
    "sg:address":"Molenweg 42",
    "sg:city":"Koningsbosch",
    "sg:orig_category":"Hoefdierhouderijen",
    "sg:phone":"+31 475 301 760",
    "sg:postcode":"6104 RG",
    "sg:province":"Limburg",
    "wof:name":"Vof Willems",
    "wof:placetype":"venue"
},
  "geometry": {"coordinates":[5.937319,51.05389],"type":"Point"}
}