{
  "type": "Feature",
  "properties": {
    "addr:full":"Herengracht 269 Amsterdam Noord-Holland 1016 BJ",
    "addr:housenumber":"269",
    "addr:postcode":"1016 bj",
    "addr:street":"Herengracht",
    "iso:country":"NL",
    "sg:address":"Herengracht 269",
    "sg:city":"Amsterdam",
    "sg:classifiers":[
        {
            "category":"Travel",
            "subcategory":"Hotels & Motels",
            "type":"Entertainment"
        }
    ],
    "sg:phone":"+31 20 623 7877",
    "sg:postcode":"1016 BJ",
    "sg:province":"Noord-Holland",
    "wof:name":"Hotel Hegra",
    "wof:placetype":"venue"
},
  "geometry": {"coordinates":[4.887342,52.371429],"type":"Point"}
}