{
  "type": "Feature",
  "properties": {
    "iso:country":"NL",
    "sg:address":"Mercuriusstr 13",
    "sg:city":"Venlo",
    "sg:orig_category":"Vertaalbureaus",
    "sg:phone":"+31 77 352 1543",
    "sg:postcode":"5914 CR",
    "sg:province":"Limburg",
    "wof:name":"Meijers",
    "wof:placetype":"venue"
},
  "geometry": {"coordinates":[6.170427,51.378727],"type":"Point"}
}