{
  "type": "Feature",
  "properties": {
    "addr:full":"2E Vd Helststr 12 Amsterdam Noord-Holland 1072 PC",
    "addr:housenumber":"12",
    "addr:postcode":"1072 pc",
    "addr:street":"2E Vd Helststr",
    "iso:country":"NL",
    "sg:address":"2E Vd Helststr 12",
    "sg:city":"Amsterdam",
    "sg:classifiers":[
        {
            "category":"Food & Beverages",
            "subcategory":"Bakery",
            "type":"Retail Goods"
        }
    ],
    "sg:phone":"+31 20 671 2907",
    "sg:postcode":"1072 PC",
    "sg:province":"Noord-Holland",
    "sg:tags":[
        "pizza"
    ],
    "wof:name":"Hayran",
    "wof:placetype":"venue"
},
  "geometry": {"coordinates":[-94.58503,38.350479],"type":"Point"}
}