{
  "type": "Feature",
  "properties": {
    "addr:full":"Raadhuisstraat 11 Didam Gelderland 6942 BE",
    "addr:housenumber":"11",
    "addr:postcode":"6942",
    "addr:street":"Raadhuisstraat;Gelderland",
    "iso:country":"NL",
    "sg:address":"Raadhuisstraat 11",
    "sg:city":"Didam",
    "sg:orig_category":"Kunst And Kunstenaarsbenodigdheden",
    "sg:phone":"+31 316 224 974",
    "sg:postcode":"6942 BE",
    "sg:province":"Gelderland",
    "wof:name":"Le Mariage 1296",
    "wof:placetype":"venue"
},
  "geometry": {"coordinates":[6.128348,51.936817],"type":"Point"}
}