{
  "type": "Feature",
  "properties": {
    "addr:full":"Vlindermeent 87 Hilversum Noord-Holland 1218 CW",
    "addr:housenumber":"87",
    "addr:postcode":"1218 cw",
    "addr:street":"Vlindermeent",
    "iso:country":"NL",
    "sg:address":"Vlindermeent 87",
    "sg:city":"Hilversum",
    "sg:orig_category":"Boekhouders",
    "sg:phone":"+31 35 693 4246",
    "sg:postcode":"1218 CW",
    "sg:province":"Noord-Holland",
    "wof:name":"Administratiekantoor A. Caldenhove",
    "wof:placetype":"venue"
},
  "geometry": {"coordinates":[5.136846,52.268867],"type":"Point"}
}