{
  "type": "Feature",
  "properties": {
    "addr:full":"F V Eedenpln 4B Hazerswoude Ryndyk Zuid-Holland 2394 EB",
    "addr:housenumber":"4b;ryndyk",
    "addr:postcode":"2394 eb",
    "addr:street":"Eedenpln",
    "iso:country":"NL",
    "sg:address":"F V Eedenpln 4B",
    "sg:city":"Hazerswoude Ryndyk",
    "sg:orig_category":"Omroep",
    "sg:phone":"+31 71 341 4749",
    "sg:postcode":"2394 EB",
    "sg:province":"Zuid-Holland",
    "sg:website":"http://www.omroeprijnwoude.nl",
    "wof:name":"Radio/Tv-Krant Rijnwoude",
    "wof:placetype":"venue"
},
  "geometry": {"coordinates":[4.595154,52.131054],"type":"Point"}
}