{
  "type": "Feature",
  "properties": {
    "addr:full":"De Factory 28N Zwaag North Holland 1689 AL",
    "addr:housenumber":"28n;1689",
    "addr:postcode":"al",
    "addr:street":"De Factory;Holland",
    "iso:country":"NL",
    "sg:address":"De Factory 28N",
    "sg:city":"Zwaag",
    "sg:orig_category":"Bedrijfsopleidingen",
    "sg:phone":"+31 229 275 014",
    "sg:postcode":"1689 AL",
    "sg:province":"North Holland",
    "wof:name":"Renforce Bv",
    "wof:placetype":"venue"
},
  "geometry": {"coordinates":[5.064945,52.670143],"type":"Point"}
}