{
  "type": "Feature",
  "properties": {
    "addr:full":"Atelierwg 6 Werkpl Groesbeek Gelderland 6562 AS",
    "addr:housenumber":"6",
    "addr:postcode":"6562 as",
    "addr:street":"Atelierwg;Gelderland",
    "iso:country":"NL",
    "sg:address":"Atelierwg 6 Werkpl",
    "sg:city":"Groesbeek",
    "sg:orig_category":"Wegenbouw",
    "sg:phone":"+31 24 397 1892",
    "sg:postcode":"6562 AS",
    "sg:province":"Gelderland",
    "wof:name":"Berg Bv, Van Der",
    "wof:placetype":"venue"
},
  "geometry": {"coordinates":[5.932489872,51.7767448425],"type":"Point"}
}