{
  "type": "Feature",
  "properties": {
    "addr:full":"Mr Nennstiehlwg 85 De Wilp Gn Groningen 9367 PC",
    "addr:housenumber":"85",
    "addr:postcode":"gn;9367 pc",
    "iso:country":"NL",
    "sg:address":"Mr Nennstiehlwg 85",
    "sg:city":"De Wilp Gn",
    "sg:orig_category":"Ventilatiesystemen",
    "sg:phone":"+31 594 641 238",
    "sg:postcode":"9367 PC",
    "sg:province":"Groningen",
    "sg:website":"http://www.gebrmeijer.com",
    "wof:name":"Meijer Bv, Gebroeders",
    "wof:placetype":"venue"
},
  "geometry": {"coordinates":[6.252655,53.11512],"type":"Point"}
}