{
  "type": "Feature",
  "properties": {
    "addr:full":"Weverstraat 116A Oosterbeek Gelderland 6862 DS",
    "addr:housenumber":"116a",
    "addr:postcode":"6862 ds",
    "addr:street":"Weverstraat;Gelderland",
    "iso:country":"NL",
    "sg:address":"Weverstraat 116A",
    "sg:city":"Oosterbeek",
    "sg:orig_category":"Paramedische Behandelingen",
    "sg:phone":"+31 26 334 2050",
    "sg:postcode":"6862 DS",
    "sg:province":"Gelderland",
    "wof:name":"J.E.M. Klopper",
    "wof:placetype":"venue"
},
  "geometry": {"coordinates":[5.840001,51.982338],"type":"Point"}
}