{
  "type": "Feature",
  "properties": {
    "iso:country":"NL",
    "sg:address":"Heiakker 5",
    "sg:city":"Prinsenbeek",
    "sg:orig_category":"Kantoor- En Secretariaatsservice",
    "sg:phone":"+31 6 23464994",
    "sg:postcode":"4841 CN",
    "sg:province":"Noord-Brabant",
    "wof:name":"Jass",
    "wof:placetype":"venue"
},
  "geometry": {"coordinates":[4.7088699341,51.5991516113],"type":"Point"}
}