{
  "type": "Feature",
  "properties": {
    "addr:full":"Rijksstraatweg 285 Ridderkerk South Holland 2988 BG",
    "addr:housenumber":"285",
    "addr:postcode":"2988",
    "addr:street":"Rijksstraatweg",
    "iso:country":"NL",
    "sg:address":"Rijksstraatweg 285",
    "sg:city":"Ridderkerk",
    "sg:orig_category":"Farmaceutische Producten Gh",
    "sg:phone":"+31 180 623 323",
    "sg:postcode":"2988 BG",
    "sg:province":"South Holland",
    "wof:name":"Fytosan Benelux Bv",
    "wof:placetype":"venue"
},
  "geometry": {"coordinates":[4.567778,51.858021],"type":"Point"}
}