{
  "type": "Feature",
  "properties": {
    "addr:full":"M Klompehof 3 Almere NL. 1314 WL",
    "addr:housenumber":"3",
    "addr:postcode":"1314",
    "addr:street":"Nl.",
    "iso:country":"NL",
    "sg:address":"M Klompehof 3",
    "sg:city":"Almere",
    "sg:orig_category":"Ontbijtservice",
    "sg:phone":"+31 36 533 9254",
    "sg:postcode":"1314 WL",
    "sg:province":"NL.",
    "sg:website":"http://www.123ontbijt.nl",
    "wof:name":"Aan De Zuiderzee",
    "wof:placetype":"venue"
},
  "geometry": {"coordinates":[5.22223,52.376598],"type":"Point"}
}