{
  "type": "Feature",
  "properties": {
    "addr:full":"Buitengaats 60 Amstelveen Noord-Holland 1186 MC",
    "addr:housenumber":"60;1186",
    "addr:postcode":"mc",
    "addr:street":"Buitengaats",
    "iso:country":"NL",
    "sg:address":"Buitengaats 60",
    "sg:city":"Amstelveen",
    "sg:orig_category":"Verzekeringen",
    "sg:phone":"+31 20 640 3069",
    "sg:postcode":"1186 MC",
    "sg:province":"Noord-Holland",
    "wof:name":"Frans Snoeck Assurantien",
    "wof:placetype":"venue"
},
  "geometry": {"coordinates":[4.856765,52.27631],"type":"Point"}
}