{
  "type": "Feature",
  "properties": {
    "addr:full":"Capelsewg 1 Waspik Noord-Brabant 5165 RB",
    "addr:housenumber":"1",
    "addr:postcode":"5165 rb",
    "addr:street":"Capelsewg",
    "iso:country":"NL",
    "sg:address":"Capelsewg 1",
    "sg:city":"Waspik",
    "sg:orig_category":"Bloemen En Planten",
    "sg:phone":"+31 162 313 065",
    "sg:postcode":"5165 RB",
    "sg:province":"Noord-Brabant",
    "wof:name":"Marrewijk Bv, N J J Van",
    "wof:placetype":"venue"
},
  "geometry": {"coordinates":[4.965404,51.660954],"type":"Point"}
}