{
  "type": "Feature",
  "properties": {
    "addr:full":"Uilenbosweg 34 Veenendaal Utrecht 3903 DR",
    "addr:housenumber":"34",
    "addr:postcode":"3903 dr",
    "addr:street":"Uilenbosweg",
    "iso:country":"NL",
    "sg:address":"Uilenbosweg 34",
    "sg:city":"Veenendaal",
    "sg:orig_category":"Technische Studies And Onderzoek",
    "sg:phone":"+31 318 556 152",
    "sg:postcode":"3903 DR",
    "sg:province":"Utrecht",
    "wof:name":"Vsf",
    "wof:placetype":"venue"
},
  "geometry": {"coordinates":[5.548476,52.002308],"type":"Point"}
}