{
  "type": "Feature",
  "properties": {
    "addr:full":"Zoutmanstr 54 Noordwyk Zh Zuid-Holland 2202 LP",
    "addr:housenumber":"54",
    "addr:postcode":"2202 lp",
    "addr:street":"Zoutmanstr",
    "iso:country":"NL",
    "sg:address":"Zoutmanstr 54",
    "sg:city":"Noordwyk Zh",
    "sg:orig_category":"Metselwerken",
    "sg:phone":"+31 71 361 6952",
    "sg:postcode":"2202 LP",
    "sg:province":"Zuid-Holland",
    "wof:name":"Noordwijk Bv",
    "wof:placetype":"venue"
},
  "geometry": {"coordinates":[4.435614,52.248837],"type":"Point"}
}