{
  "type": "Feature",
  "properties": {
    "addr:full":"Wittevrouwenstr 40 Utrecht Utrecht 3512 CV",
    "addr:housenumber":"40",
    "addr:postcode":"3512 cv",
    "addr:street":"Wittevrouwenstr",
    "iso:country":"NL",
    "sg:address":"Wittevrouwenstr 40",
    "sg:city":"Utrecht",
    "sg:orig_category":"Gelegenheidskleding",
    "sg:phone":"+31 30 233 2612",
    "sg:postcode":"3512 CV",
    "sg:province":"Utrecht",
    "wof:name":"Lantijn",
    "wof:placetype":"venue"
},
  "geometry": {"coordinates":[5.125508,52.095112],"type":"Point"}
}