{
  "type": "Feature",
  "properties": {
    "addr:full":"Piet Heinplein 3 'S Gravenhage Zuid-Holland 2518 CA",
    "addr:housenumber":"3 '",
    "addr:postcode":"2518 ca",
    "addr:street":"Piet Heinplein",
    "iso:country":"NL",
    "sg:address":"Piet Heinplein 3",
    "sg:city":"'S Gravenhage",
    "sg:orig_category":"Kappers",
    "sg:phone":"+31 70 346 4696",
    "sg:postcode":"2518 CA",
    "sg:province":"Zuid-Holland",
    "wof:name":"Lex-Kapper",
    "wof:placetype":"venue"
},
  "geometry": {"coordinates":[4.300743,52.082554],"type":"Point"}
}