{
  "type": "Feature",
  "properties": {
    "addr:full":"Burmanstr 30 Amsterdam North Holland 1091 SK",
    "addr:housenumber":"30",
    "addr:street":"Burmanstr;1091",
    "iso:country":"NL",
    "sg:address":"Burmanstr 30",
    "sg:city":"Amsterdam",
    "sg:orig_category":"Video - Faciliteiten En Producties",
    "sg:phone":"+31 20 694 3545",
    "sg:postcode":"1091 SK",
    "sg:province":"North Holland",
    "wof:name":"Mooibroek",
    "wof:placetype":"venue"
},
  "geometry": {"coordinates":[4.910198,52.354538],"type":"Point"}
}