{
  "type": "Feature",
  "properties": {
    "addr:full":"Elisabethdreef 4 Culemborg Gelderland 4101 KL",
    "addr:housenumber":"4",
    "addr:postcode":"4101 kl",
    "addr:street":"Elisabethdreef;Gelderland",
    "iso:country":"NL",
    "sg:address":"Elisabethdreef 4",
    "sg:city":"Culemborg",
    "sg:orig_category":"Poliklinieken",
    "sg:phone":"+31 345 519 777",
    "sg:postcode":"4101 KL",
    "sg:province":"Gelderland",
    "wof:name":"Barbara",
    "wof:placetype":"venue"
},
  "geometry": {"coordinates":[5.228516,51.958714],"type":"Point"}
}