{
  "type": "Feature",
  "properties": {
    "addr:full":"Molenstraat 5 Westdorpe Zeeland 4554 CE",
    "addr:housenumber":"5",
    "addr:postcode":"4554 ce",
    "addr:street":"Molenstraat",
    "iso:country":"NL",
    "sg:address":"Molenstraat 5",
    "sg:city":"Westdorpe",
    "sg:orig_category":"Banken And Kredietinstellingen",
    "sg:phone":"+31 115 462 140",
    "sg:postcode":"4554 CE",
    "sg:province":"Zeeland",
    "wof:name":"Rabobank",
    "wof:placetype":"venue"
},
  "geometry": {"coordinates":[3.829653,51.233528],"type":"Point"}
}