{
  "type": "Feature",
  "properties": {
    "addr:full":"Brededwarsstraat 20 Roermond Limburg 6042 GH",
    "addr:housenumber":"20",
    "addr:postcode":"6042 gh",
    "addr:street":"Brededwarsstraat",
    "iso:country":"NL",
    "sg:address":"Brededwarsstraat 20",
    "sg:city":"Roermond",
    "sg:orig_category":"Schoonheidssalons",
    "sg:phone":"+31 475 320 712",
    "sg:postcode":"6042 GH",
    "sg:province":"Limburg",
    "wof:name":"Salon Naturelle",
    "wof:placetype":"venue"
},
  "geometry": {"coordinates":[6.006705,51.201378],"type":"Point"}
}