{
  "type": "Feature",
  "properties": {
    "addr:full":"Dorpsstraat 778 Oudkarspel Noord-Holland 1724 NS",
    "addr:housenumber":"778",
    "addr:postcode":"1724 ns",
    "addr:street":"Dorpsstraat",
    "iso:country":"NL",
    "sg:address":"Dorpsstraat 778",
    "sg:city":"Oudkarspel",
    "sg:orig_category":"Schoenen",
    "sg:phone":"+31 226 312 572",
    "sg:postcode":"1724 NS",
    "sg:province":"Noord-Holland",
    "wof:name":"J Koomen",
    "wof:placetype":"venue"
},
  "geometry": {"coordinates":[4.807958,52.710567],"type":"Point"}
}