{
  "type": "Feature",
  "properties": {
    "iso:country":"NL",
    "sg:address":"Keizersgr 19",
    "sg:city":"Eindhoven",
    "sg:orig_category":"Bioscopen",
    "sg:phone":"+31 40 297 4747",
    "sg:postcode":"5611 GC",
    "sg:province":"Noord-Brabant",
    "sg:website":"http://www.jtbioscopen.nl",
    "wof:name":"Euro Cinema",
    "wof:placetype":"venue"
},
  "geometry": {"coordinates":[5.477728,51.437054],"type":"Point"}
}