{
  "type": "Feature",
  "properties": {
    "iso:country":"NL",
    "sg:address":"Hof V Blom 5",
    "sg:city":"Hattem",
    "sg:orig_category":"Bejaarden - Verzorgingstehuizen",
    "sg:phone":"+31 38 444 1641",
    "sg:postcode":"8051 JT",
    "sg:province":"Gelderland",
    "wof:name":"Hof Van Blom, Sticht",
    "wof:placetype":"venue"
},
  "geometry": {"coordinates":[6.072084,52.474659],"type":"Point"}
}