{
  "type": "Feature",
  "properties": {
    "addr:full":"Verlengde Duinstraat 17 Hoogerheide North Brabant 4631 HN",
    "addr:housenumber":"17",
    "addr:postcode":"4631 hn",
    "addr:street":"Verlengde Duinstraat",
    "iso:country":"NL",
    "sg:address":"Verlengde Duinstraat 17",
    "sg:city":"Hoogerheide",
    "sg:orig_category":"Kappers",
    "sg:phone":"+31 164 614 842",
    "sg:postcode":"4631 HN",
    "sg:province":"North Brabant",
    "wof:name":"Dameskapsalon Luyks-Soffers",
    "wof:placetype":"venue"
},
  "geometry": {"coordinates":[4.3305921555,51.4290084839],"type":"Point"}
}