{
  "type": "Feature",
  "properties": {
    "iso:country":"NL",
    "sg:address":"Pr Bernhardstr 21",
    "sg:city":"Hillegom",
    "sg:orig_category":"Handelscentra",
    "sg:phone":"+31 252 519 923",
    "sg:postcode":"2181 RH",
    "sg:province":"Zuid-Holland",
    "wof:name":"Itc",
    "wof:placetype":"venue"
},
  "geometry": {"coordinates":[4.582113,52.294228],"type":"Point"}
}