{
  "type": "Feature",
  "properties": {
    "addr:full":"Ekselerbrink 70 Emmen Drenthe 7812 VM",
    "addr:housenumber":"70",
    "addr:postcode":"7812 vm",
    "addr:street":"Ekselerbrink",
    "iso:country":"NL",
    "sg:address":"Ekselerbrink 70",
    "sg:city":"Emmen",
    "sg:orig_category":"Verenigingen En Stichtingen",
    "sg:phone":"+31 591 615 294",
    "sg:postcode":"7812 VM",
    "sg:province":"Drenthe",
    "wof:name":"Jnm Jeugdbond Voor Natuur En Milieustudie",
    "wof:placetype":"venue"
},
  "geometry": {"coordinates":[6.875876,52.761269],"type":"Point"}
}