{
  "type": "Feature",
  "properties": {
    "addr:full":"Mezenpln 15 S Gravenhage Zuid-Holland 2566 ZS",
    "addr:housenumber":"15;gravenhage",
    "addr:postcode":"2566 zs",
    "addr:street":"Mezenpln;S",
    "iso:country":"NL",
    "sg:address":"Mezenpln 15",
    "sg:city":"S Gravenhage",
    "sg:orig_category":"Woningstoffeerders",
    "sg:phone":"+31 6 13955396",
    "sg:postcode":"2566 ZS",
    "sg:province":"Zuid-Holland",
    "wof:name":"Meijer, M",
    "wof:placetype":"venue"
},
  "geometry": {"coordinates":[4.2555298805,52.0791282654],"type":"Point"}
}