{
  "type": "Feature",
  "properties": {
    "addr:full":"Amsterdamsestraatweg 54 Utrecht Utrecht 3513 AG",
    "addr:housenumber":"54",
    "addr:postcode":"3513",
    "addr:street":"Amsterdamsestraatweg",
    "iso:country":"NL",
    "sg:address":"Amsterdamsestraatweg 54",
    "sg:city":"Utrecht",
    "sg:orig_category":"Feestartikelen",
    "sg:phone":"+31 30 231 2119",
    "sg:postcode":"3513 AG",
    "sg:province":"Utrecht",
    "wof:name":"Feestwinkel G. Bakker En Zn Bv",
    "wof:placetype":"venue"
},
  "geometry": {"coordinates":[5.108065,52.096039],"type":"Point"}
}