{
  "type": "Feature",
  "properties": {
    "addr:full":"Spaarndammerstr 53-Ii Amsterdam Noord-Holland 1013 TA",
    "addr:housenumber":"53-ii",
    "addr:postcode":"1013 ta",
    "addr:street":"Spaarndammerstr",
    "iso:country":"NL",
    "sg:address":"Spaarndammerstr 53-Ii",
    "sg:city":"Amsterdam",
    "sg:orig_category":"Autorijscholen",
    "sg:phone":"+31 6 24984174",
    "sg:postcode":"1013 TA",
    "sg:province":"Noord-Holland",
    "sg:website":"http://www.rijschooldetoekomst.nl",
    "wof:name":"Toekomst, De",
    "wof:placetype":"venue"
},
  "geometry": {"coordinates":[4.893195,52.373119],"type":"Point"}
}