{
  "type": "Feature",
  "properties": {
    "addr:full":"Eindhovensebaan 36 Veldhoven Noord-Brabant 5505 JB",
    "addr:housenumber":"36",
    "addr:postcode":"5505 jb",
    "addr:street":"Eindhovensebaan",
    "iso:country":"NL",
    "sg:address":"Eindhovensebaan 36",
    "sg:city":"Veldhoven",
    "sg:orig_category":"Marktonderzoekbureaus",
    "sg:phone":"+31 40 205 2641",
    "sg:postcode":"5505 JB",
    "sg:province":"Noord-Brabant",
    "wof:name":"Marketing Adviesbureau Modus Veldhoven",
    "wof:placetype":"venue"
},
  "geometry": {"coordinates":[5.373206,51.413231],"type":"Point"}
}