{
  "type": "Feature",
  "properties": {
    "addr:full":"Waagstraat 1 Oldenzaal Overijssel 7571 EA",
    "addr:housenumber":"1",
    "addr:postcode":"7571 ea",
    "addr:street":"Waagstraat",
    "iso:country":"NL",
    "sg:address":"Waagstraat 1",
    "sg:city":"Oldenzaal",
    "sg:classifiers":[
        {
            "category":"Fast Food",
            "type":"Food & Drink"
        }
    ],
    "sg:phone":"+31 541 515 325",
    "sg:postcode":"7571 EA",
    "sg:province":"Overijssel",
    "sg:tags":[
        "afhaal",
        "restaurant"
    ],
    "wof:name":"Snackbar De Buurvrouw",
    "wof:placetype":"venue"
},
  "geometry": {"coordinates":[6.929339,52.313923],"type":"Point"}
}