{
  "type": "Feature",
  "properties": {
    "iso:country":"NL",
    "sg:address":"Papeweg 1",
    "sg:city":"Wolphaartsdijk",
    "sg:orig_category":"Visspeciaalzaken",
    "sg:phone":"+31 113 581 592",
    "sg:postcode":"4471 BD",
    "sg:province":"Zeeland",
    "wof:name":"Firma Kees Van De Kreeke & Zn.",
    "wof:placetype":"venue"
},
  "geometry": {"coordinates":[3.821121,51.531391],"type":"Point"}
}