{
  "type": "Feature",
  "properties": {
    "iso:country":"NL",
    "sg:address":"Gr Willemln 6",
    "sg:city":"Monnickendam",
    "sg:classifiers":[
        {
            "category":"Personal",
            "subcategory":"Nail Salon",
            "type":"Services"
        }
    ],
    "sg:phone":"+31 299 653 792",
    "sg:postcode":"1141 XK",
    "sg:province":"Noord-Holland",
    "sg:tags":[
        "pedicure"
    ],
    "wof:name":"Joosten-Vlug, C",
    "wof:placetype":"venue"
},
  "geometry": {"coordinates":[5.040328,52.455681],"type":"Point"}
}