{
  "type": "Feature",
  "properties": {
    "addr:full":"Houtse Parallelwg 133 Helmond North Brabant 5706 AG",
    "addr:housenumber":"133",
    "addr:postcode":"5706",
    "addr:street":"Houtse",
    "iso:country":"NL",
    "sg:address":"Houtse Parallelwg 133",
    "sg:city":"Helmond",
    "sg:orig_category":"Kampeerartikelen",
    "sg:phone":"+31 492 550 284",
    "sg:postcode":"5706 AG",
    "sg:province":"North Brabant",
    "wof:name":"Broekx Caravan Shop",
    "wof:placetype":"venue"
},
  "geometry": {"coordinates":[5.6360502243,51.4690208435],"type":"Point"}
}