{
  "type": "Feature",
  "properties": {
    "addr:full":"Oosteinderweg 398 Aalsmeer Noord-Holland 1432 BN",
    "addr:housenumber":"398",
    "addr:postcode":"1432 bn",
    "addr:street":"Oosteinderweg",
    "iso:country":"NL",
    "sg:address":"Oosteinderweg 398",
    "sg:city":"Aalsmeer",
    "sg:orig_category":"Autokeuringen",
    "sg:phone":"+31 297 329 943",
    "sg:postcode":"1432 BN",
    "sg:province":"Noord-Holland",
    "wof:name":"Motorenrevisie De Jong",
    "wof:placetype":"venue"
},
  "geometry": {"coordinates":[4.801467,52.285446],"type":"Point"}
}