{
  "type": "Feature",
  "properties": {
    "iso:country":"NL",
    "sg:address":"Admiraalsplein 484",
    "sg:city":"Dordrecht",
    "sg:orig_category":"Huizensloop And Bouwrijp Maken",
    "sg:phone":"+31 78 617 2393",
    "sg:postcode":"3317 NA",
    "sg:province":"South Holland",
    "wof:name":"Machine Grondverzetbedrijf W Neels",
    "wof:placetype":"venue"
},
  "geometry": {"coordinates":[4.655341,51.790646],"type":"Point"}
}