{
  "type": "Feature",
  "properties": {
    "addr:full":"J Weitkampln 8K Hardenberg NL.08 7772 SE",
    "addr:housenumber":"8k;nl.08 7772",
    "addr:street":"Se",
    "iso:country":"NL",
    "sg:address":"J Weitkampln 8K",
    "sg:city":"Hardenberg",
    "sg:orig_category":"Koeriersdiensten",
    "sg:phone":"+31 523 271 556",
    "sg:postcode":"7772 SE",
    "sg:province":"NL.08",
    "sg:website":"http://www.sneldienst-hardenberg.nl",
    "wof:name":"Sneldienst Hardenberg",
    "wof:placetype":"venue"
},
  "geometry": {"coordinates":[6.6378,52.57016],"type":"Point"}
}