{
  "type": "Feature",
  "properties": {
    "addr:full":"Zekkenstr 5 Hoek Van Holland Zuid-Holland 3151 XP",
    "addr:housenumber":"5",
    "addr:postcode":"3151 xp",
    "addr:street":"Zekkenstr",
    "iso:country":"NL",
    "sg:address":"Zekkenstr 5",
    "sg:city":"Hoek Van Holland",
    "sg:orig_category":"Fietsen - Fabrieken En Groothandel",
    "sg:phone":"+31 174 386 050",
    "sg:postcode":"3151 XP",
    "sg:province":"Zuid-Holland",
    "wof:name":"Duell",
    "wof:placetype":"venue"
},
  "geometry": {"coordinates":[4.146451,51.969913],"type":"Point"}
}