{
  "type": "Feature",
  "properties": {
    "addr:full":"Windroospln 8 Amsterdam Noord-Holland 1018 ZW",
    "addr:housenumber":"8",
    "addr:postcode":"1018 zw",
    "addr:street":"Windroospln",
    "iso:country":"NL",
    "sg:address":"Windroospln 8",
    "sg:city":"Amsterdam",
    "sg:orig_category":"Video - Faciliteiten En Producties",
    "sg:phone":"+31 20 624 2928",
    "sg:postcode":"1018 ZW",
    "sg:province":"Noord-Holland",
    "wof:name":"Smulders",
    "wof:placetype":"venue"
},
  "geometry": {"coordinates":[4.924732,52.372955],"type":"Point"}
}