{
  "type": "Feature",
  "properties": {
    "addr:full":"Pr Hendrikpln 20 S Gravenhage South Holland 2518 JC",
    "addr:housenumber":"20",
    "addr:postcode":"2518 jc",
    "addr:street":"S Gravenhage",
    "iso:country":"NL",
    "sg:address":"Pr Hendrikpln 20",
    "sg:city":"S Gravenhage",
    "sg:orig_category":"Kappers",
    "sg:phone":"+31 70 346 7574",
    "sg:postcode":"2518 JC",
    "sg:province":"South Holland",
    "wof:name":"Future Hairstyling",
    "wof:placetype":"venue"
},
  "geometry": {"coordinates":[4.2934799194,52.0803184509],"type":"Point"}
}