{
  "type": "Feature",
  "properties": {
    "addr:full":"Nijverheidstraat 21 Hengelo Ov NL.08 7555 HL",
    "addr:housenumber":"21",
    "addr:postcode":"7555 hl",
    "addr:street":"Nijverheidstraat;Ov",
    "iso:country":"NL",
    "sg:address":"Nijverheidstraat 21",
    "sg:city":"Hengelo Ov",
    "sg:orig_category":"Vloer- And Wandbedekkingen",
    "sg:phone":"+31 74 242 2526",
    "sg:postcode":"7555 HL",
    "sg:province":"NL.08",
    "wof:name":"H. Heinink",
    "wof:placetype":"venue"
},
  "geometry": {"coordinates":[6.773768,52.258934],"type":"Point"}
}