{
  "type": "Feature",
  "properties": {
    "addr:full":"Warmoesstr 67 Wormerveer Noord-Holland 1521 CL",
    "addr:housenumber":"67",
    "addr:postcode":"1521",
    "addr:street":"Warmoesstr",
    "iso:country":"NL",
    "sg:address":"Warmoesstr 67",
    "sg:city":"Wormerveer",
    "sg:orig_category":"Metaalbewerking",
    "sg:phone":"+31 75 622 8699",
    "sg:postcode":"1521 CL",
    "sg:province":"Noord-Holland",
    "wof:name":"Hartog",
    "wof:placetype":"venue"
},
  "geometry": {"coordinates":[4.802453,52.486359],"type":"Point"}
}