{
  "type": "Feature",
  "properties": {
    "addr:full":"Weg Voor De Jagerskampen 73 Haren Gn Groningen 9751 EL",
    "addr:housenumber":"73",
    "addr:postcode":"9751 el",
    "addr:street":"Weg Voor De Jagerskampen",
    "iso:country":"NL",
    "sg:address":"Weg Voor De Jagerskampen 73",
    "sg:city":"Haren Gn",
    "sg:orig_category":"Sportterreinen And Installaties Behalve Sportcentra",
    "sg:phone":"+31 50 534 8769",
    "sg:postcode":"9751 EL",
    "sg:province":"Groningen",
    "wof:name":"Zwemschool Hennie Vos",
    "wof:placetype":"venue"
},
  "geometry": {"coordinates":[6.612958,53.164955],"type":"Point"}
}