{
  "type": "Feature",
  "properties": {
    "addr:full":"M Harpertsz Trompln 4 Enschede Overijssel 7511 JK",
    "addr:housenumber":"4",
    "addr:postcode":"7511 jk",
    "addr:street":"M Harpertsz Trompln",
    "iso:country":"NL",
    "sg:address":"M Harpertsz Trompln 4",
    "sg:city":"Enschede",
    "sg:orig_category":"Diverse Grafische Activiteiten",
    "sg:phone":"+31 53 480 7788",
    "sg:postcode":"7511 JK",
    "sg:province":"Overijssel",
    "wof:name":"Wesspoint Reklamemakers Bv",
    "wof:placetype":"venue"
},
  "geometry": {"coordinates":[6.895374,52.223576],"type":"Point"}
}