{
  "type": "Feature",
  "properties": {
    "iso:country":"NL",
    "sg:address":"Herenstr 69",
    "sg:city":"Hilversum",
    "sg:orig_category":"Webdesign Bureaus",
    "sg:phone":"+31 35 631 0367",
    "sg:postcode":"1211 CA",
    "sg:province":"North Holland",
    "sg:website":"http://www.ontwwwerp.nl",
    "wof:name":"Ontwwwerp",
    "wof:placetype":"venue"
},
  "geometry": {"coordinates":[5.1730861664,52.2237129211],"type":"Point"}
}