{
  "type": "Feature",
  "properties": {
    "addr:full":"Heuvelsepad 34 Ede Gld Gelderland 6711 JP",
    "addr:housenumber":"34",
    "addr:postcode":"6711 jp",
    "addr:street":"Heuvelsepad;Gld Gelderland",
    "iso:country":"NL",
    "sg:address":"Heuvelsepad 34",
    "sg:city":"Ede Gld",
    "sg:orig_category":"Handelscentra",
    "sg:phone":"+31 318 617 874",
    "sg:postcode":"6711 JP",
    "sg:province":"Gelderland",
    "wof:name":"Jansen, J",
    "wof:placetype":"venue"
},
  "geometry": {"coordinates":[5.67402,52.042606],"type":"Point"}
}