{
  "type": "Feature",
  "properties": {
    "iso:country":"NL",
    "sg:address":"Aziering 54",
    "sg:city":"Amersfoort",
    "sg:orig_category":"Adviesbureaus Bedrijfsorganisatie",
    "sg:phone":"+31 33 472 7183",
    "sg:postcode":"3823 WR",
    "sg:province":"Utrecht",
    "sg:website":"http://www.leveltbpr.nl",
    "wof:name":"Levelt",
    "wof:placetype":"venue"
},
  "geometry": {"coordinates":[5.395655,52.18985],"type":"Point"}
}