{
  "type": "Feature",
  "properties": {
    "addr:full":"Geestwg 9 Bergen Nh Noord-Holland 1861 TL",
    "addr:housenumber":"9",
    "addr:postcode":"1861 tl",
    "addr:street":"Geestwg",
    "iso:country":"NL",
    "sg:address":"Geestwg 9",
    "sg:city":"Bergen Nh",
    "sg:orig_category":"Beeldende Kunstenaars",
    "sg:phone":"+31 72 589 5202",
    "sg:postcode":"1861 TL",
    "sg:province":"Noord-Holland",
    "wof:name":"Wal, E C Van Der",
    "wof:placetype":"venue"
},
  "geometry": {"coordinates":[4.701744,52.664795],"type":"Point"}
}