{
  "type": "Feature",
  "properties": {
    "addr:full":"Verl Hoogeveensev 138 Geesbrug Provincie Drenthe 7917 TG",
    "addr:housenumber":"138;7917",
    "addr:postcode":"tg",
    "addr:street":"Provincie Drenthe",
    "iso:country":"NL",
    "sg:address":"Verl Hoogeveensev 138",
    "sg:city":"Geesbrug",
    "sg:orig_category":"Vakantieverblijven",
    "sg:phone":"+31 524 291 131",
    "sg:postcode":"7917 TG",
    "sg:province":"Provincie Drenthe",
    "wof:name":"Kakelbont, Sticht",
    "wof:placetype":"venue"
},
  "geometry": {"coordinates":[6.65546,52.728409],"type":"Point"}
}