{
  "type": "Feature",
  "properties": {
    "addr:full":"Nicolaistraat 15 'S Gravenhage South Holland 2517 SX",
    "addr:housenumber":"15",
    "addr:postcode":"2517 sx",
    "addr:street":"Nicolaistraat;' S Gravenhage",
    "iso:country":"NL",
    "sg:address":"Nicolaistraat 15",
    "sg:city":"'S Gravenhage",
    "sg:orig_category":"Architecten",
    "sg:phone":"+31 70 360 7704",
    "sg:postcode":"2517 SX",
    "sg:province":"South Holland",
    "wof:name":"Ir Cor Westerduin Architektenbureau",
    "wof:placetype":"venue"
},
  "geometry": {"coordinates":[4.280342,52.08569],"type":"Point"}
}