{
  "type": "Feature",
  "properties": {
    "addr:full":"Meidoornstr 36 Zaandam Noord-Holland 1505 TV",
    "addr:housenumber":"36",
    "addr:postcode":"1505 tv",
    "addr:street":"Meidoornstr",
    "iso:country":"NL",
    "sg:address":"Meidoornstr 36",
    "sg:city":"Zaandam",
    "sg:orig_category":"Onderhoudswerken",
    "sg:phone":"+31 75 616 2210",
    "sg:postcode":"1505 TV",
    "sg:province":"Noord-Holland",
    "wof:name":"Ben, W Van Der",
    "wof:placetype":"venue"
},
  "geometry": {"coordinates":[4.838915,52.4314],"type":"Point"}
}