{
  "type": "Feature",
  "properties": {
    "addr:full":"Graswinkelln 104 Weert Limburg 6005 KB",
    "addr:housenumber":"104",
    "addr:postcode":"6005 kb",
    "addr:street":"Weert Limburg",
    "iso:country":"NL",
    "sg:address":"Graswinkelln 104",
    "sg:city":"Weert",
    "sg:orig_category":"Scheidingswanden - Fabrieken",
    "sg:phone":"+31 495 525 794",
    "sg:postcode":"6005 KB",
    "sg:province":"Limburg",
    "wof:name":"Wab",
    "wof:placetype":"venue"
},
  "geometry": {"coordinates":[5.722655,51.243618],"type":"Point"}
}