{
  "type": "Feature",
  "properties": {
    "addr:full":"Dr Willemsln 150 Slagharen NL.08 7776 CD",
    "addr:housenumber":"150;nl.08",
    "addr:postcode":"7776 cd",
    "iso:country":"NL",
    "sg:address":"Dr Willemsln 150",
    "sg:city":"Slagharen",
    "sg:orig_category":"Logopedisten",
    "sg:phone":"+31 523 681 283",
    "sg:postcode":"7776 CD",
    "sg:province":"NL.08",
    "wof:name":"Verbeek, R",
    "wof:placetype":"venue"
},
  "geometry": {"coordinates":[6.558658,52.62859],"type":"Point"}
}