{
  "type": "Feature",
  "properties": {
    "addr:full":"Haaswijkw O 12 Dordrecht Zuid-Holland 3319 GC",
    "addr:housenumber":"12",
    "addr:postcode":"3319 gc",
    "iso:country":"NL",
    "sg:address":"Haaswijkw O 12",
    "sg:city":"Dordrecht",
    "sg:orig_category":"Lasbedrijven",
    "sg:phone":"+31 78 616 0498",
    "sg:postcode":"3319 GC",
    "sg:province":"Zuid-Holland",
    "wof:name":"Es, A Van",
    "wof:placetype":"venue"
},
  "geometry": {"coordinates":[4.7148,51.795345],"type":"Point"}
}