{
  "type": "Feature",
  "properties": {
    "addr:full":"Industriewg 2 Pynacker Zuid-Holland 2641 RM",
    "addr:housenumber":"2",
    "addr:postcode":"2641 rm",
    "addr:street":"Industriewg",
    "iso:country":"NL",
    "sg:address":"Industriewg 2",
    "sg:city":"Pynacker",
    "sg:orig_category":"Woningbouw- Verenigingen En -Stichtingen",
    "sg:phone":"+31 15 362 0520",
    "sg:postcode":"2641 RM",
    "sg:province":"Zuid-Holland",
    "sg:website":"http://www.rondomwonen.nl",
    "wof:name":"Rondom Wonen, Sticht",
    "wof:placetype":"venue"
},
  "geometry": {"coordinates":[4.4250707626,51.9879684448],"type":"Point"}
}