{
  "type": "Feature",
  "properties": {
    "addr:full":"Koningskd 30 S Gravenhage Zuid-Holland 2596 AA",
    "addr:housenumber":"30;gravenhage",
    "addr:postcode":"2596 aa",
    "addr:street":"Koningskd;S",
    "iso:country":"NL",
    "sg:address":"Koningskd 30",
    "sg:city":"S Gravenhage",
    "sg:orig_category":"Verenigingen En Stichtingen",
    "sg:phone":"+31 70 314 3647",
    "sg:postcode":"2596 AA",
    "sg:province":"Zuid-Holland",
    "sg:website":"http://www.nedeco.nl",
    "wof:name":"Nedeco",
    "wof:placetype":"venue"
},
  "geometry": {"coordinates":[4.31846,52.093311],"type":"Point"}
}