{
  "type": "Feature",
  "properties": {
    "addr:full":"L Elisabethstr 29 Utrecht Utrecht 3511 JB",
    "addr:housenumber":"29",
    "addr:postcode":"3511 jb",
    "iso:country":"NL",
    "sg:address":"L Elisabethstr 29",
    "sg:city":"Utrecht",
    "sg:orig_category":"Mode-Artikelen Dames En Heren",
    "sg:phone":"+31 30 266 2223",
    "sg:postcode":"3511 JB",
    "sg:province":"Utrecht",
    "sg:website":"http://www.frontrunner.nl",
    "wof:name":"Front Runner",
    "wof:placetype":"venue"
},
  "geometry": {"coordinates":[5.115731,52.091591],"type":"Point"}
}