{
  "type": "Feature",
  "properties": {
    "iso:country":"NL",
    "sg:address":"C Huygenswg 29",
    "sg:city":"Alphen Aan Den Ryn",
    "sg:orig_category":"Kermisexploitatie",
    "sg:phone":"+31 6 22967605",
    "sg:postcode":"2408 AJ",
    "sg:province":"South Holland",
    "wof:name":"Weerdt Jr, T C Van Der",
    "wof:placetype":"venue"
},
  "geometry": {"coordinates":[4.65273,52.120281],"type":"Point"}
}