{
  "type": "Feature",
  "properties": {
    "iso:country":"NL",
    "sg:address":"Oldenzaalsestr 71A",
    "sg:city":"Losser",
    "sg:classifiers":[
        {
            "category":"Personal",
            "subcategory":"Nail Salon",
            "type":"Services"
        }
    ],
    "sg:phone":"+31 546 490 675",
    "sg:postcode":"7581 AT",
    "sg:province":"Overijssel",
    "sg:tags":[
        "pedicure"
    ],
    "wof:name":"Podo-Fysio-Care",
    "wof:placetype":"venue"
},
  "geometry": {"coordinates":[6.998458,52.265755],"type":"Point"}
}