{
  "type": "Feature",
  "properties": {
    "addr:full":"Langeweg 1 Heinenoord Zuid-Holland 3274 LZ",
    "addr:housenumber":"1",
    "addr:postcode":"3274 lz",
    "addr:street":"Langeweg",
    "iso:country":"NL",
    "sg:address":"Langeweg 1",
    "sg:city":"Heinenoord",
    "sg:orig_category":"Aannemers Woningbouw",
    "sg:phone":"+31 186 601 655",
    "sg:postcode":"3274 LZ",
    "sg:province":"Zuid-Holland",
    "wof:name":"L. Naaktgeboren Bv",
    "wof:placetype":"venue"
},
  "geometry": {"coordinates":[4.521553,51.811333],"type":"Point"}
}