{
  "type": "Feature",
  "properties": {
    "iso:country":"NL",
    "sg:address":"Anthony Fokkerweg 57",
    "sg:city":"Rotterdam",
    "sg:orig_category":"Beveiligingsdiensten And Bewakingsbedrijven",
    "sg:phone":"+31 10 428 2311",
    "sg:postcode":"3088 GE",
    "sg:province":"South Holland",
    "wof:name":"Hofland Electronica Bv",
    "wof:placetype":"venue"
},
  "geometry": {"coordinates":[4.447966,51.873768],"type":"Point"}
}