{
  "type": "Feature",
  "properties": {
    "iso:country":"NL",
    "sg:address":"Laan Van Middenburg 10",
    "sg:city":"Voorburg",
    "sg:orig_category":"Kappers",
    "sg:phone":"+31 70 386 0336",
    "sg:postcode":"2275 CC",
    "sg:province":"South Holland",
    "wof:name":"Gerard Knoop Hair Fashion",
    "wof:placetype":"venue"
},
  "geometry": {"coordinates":[4.3554620743,52.0634803772],"type":"Point"}
}