{
  "type": "Feature",
  "properties": {
    "addr:full":"Zaadmarkt 107 Zutphen Gelderland 7201 DD",
    "addr:housenumber":"107",
    "addr:postcode":"7201 dd",
    "addr:street":"Zaadmarkt;Gelderland",
    "iso:country":"NL",
    "sg:address":"Zaadmarkt 107",
    "sg:city":"Zutphen",
    "sg:classifiers":[
        {
            "category":"Food & Beverages",
            "subcategory":"Bakery",
            "type":"Retail Goods"
        }
    ],
    "sg:phone":"+31 575 517 724",
    "sg:postcode":"7201 DD",
    "sg:province":"Gelderland",
    "sg:tags":[
        "pizza"
    ],
    "wof:name":"Shalom",
    "wof:placetype":"venue"
},
  "geometry": {"coordinates":[6.197557,52.139622],"type":"Point"}
}