{
  "type": "Feature",
  "properties": {
    "addr:full":"Maarssev Vaart 15 Tienhoven Ut Utrecht 3612 AA",
    "addr:housenumber":"15",
    "addr:postcode":"3612 aa",
    "addr:street":"Vaart",
    "iso:country":"NL",
    "sg:address":"Maarssev Vaart 15",
    "sg:city":"Tienhoven Ut",
    "sg:classifiers":[
        {
            "category":"Sports & Exercise",
            "subcategory":"Stables",
            "type":"Entertainment"
        }
    ],
    "sg:phone":"+31 346 561 489",
    "sg:postcode":"3612 AA",
    "sg:province":"Utrecht",
    "sg:tags":[
        "maneges"
    ],
    "wof:name":"Baas",
    "wof:placetype":"venue"
},
  "geometry": {"coordinates":[5.08764,52.161224],"type":"Point"}
}