{
  "type": "Feature",
  "properties": {
    "addr:full":"Brouwersstraat 12 Maasbracht Limburg 6051 AA",
    "addr:housenumber":"12",
    "addr:postcode":"6051 aa",
    "addr:street":"Brouwersstraat",
    "iso:country":"NL",
    "sg:address":"Brouwersstraat 12",
    "sg:city":"Maasbracht",
    "sg:classifiers":[
        {
            "category":"Professional",
            "subcategory":"Accounting & Tax Preparation",
            "type":"Services"
        }
    ],
    "sg:phone":"+31 475 464 144",
    "sg:postcode":"6051 AA",
    "sg:province":"Limburg",
    "sg:tags":[
        "accountant"
    ],
    "wof:name":"Daemen & Dings Accountants En Belastingsadviseurs",
    "wof:placetype":"venue"
},
  "geometry": {"coordinates":[5.892316,51.150375],"type":"Point"}
}