{
  "type": "Feature",
  "properties": {
    "addr:full":"Hofstr 48 Schagen North Holland 1741 CD",
    "addr:housenumber":"48",
    "addr:postcode":"1741 cd",
    "addr:street":"Hofstr",
    "iso:country":"NL",
    "sg:address":"Hofstr 48",
    "sg:city":"Schagen",
    "sg:orig_category":"Fitnesscentra",
    "sg:phone":"+31 224 214 714",
    "sg:postcode":"1741 CD",
    "sg:province":"North Holland",
    "sg:website":"http://www.henkmiddelbeek.nl",
    "wof:name":"Middelbeek Henk Sportcentrum",
    "wof:placetype":"venue"
},
  "geometry": {"coordinates":[4.79403,52.784771],"type":"Point"}
}