{
  "type": "Feature",
  "properties": {
    "addr:full":"Eigenhaard 36 Dordrecht South Holland 3312 EH",
    "addr:housenumber":"36",
    "addr:postcode":"3312 eh",
    "addr:street":"Eigenhaard",
    "iso:country":"NL",
    "sg:address":"Eigenhaard 36",
    "sg:city":"Dordrecht",
    "sg:orig_category":"Begrafenisverzorging",
    "sg:phone":"+31 78 639 9127",
    "sg:postcode":"3312 EH",
    "sg:province":"South Holland",
    "sg:website":"http://www.de-staatsie.nl",
    "wof:name":"Staatsie, De",
    "wof:placetype":"venue"
},
  "geometry": {"coordinates":[4.676346,51.807514],"type":"Point"}
}