{
  "type": "Feature",
  "properties": {
    "addr:full":"Hoogeveenseweg 12 Slagharen Overijssel 7776 RP",
    "addr:housenumber":"12",
    "addr:postcode":"7776 rp",
    "addr:street":"Hoogeveenseweg",
    "iso:country":"NL",
    "sg:address":"Hoogeveenseweg 12",
    "sg:city":"Slagharen",
    "sg:orig_category":"Pluimveehouderijen",
    "sg:phone":"+31 523 681 027",
    "sg:postcode":"7776 RP",
    "sg:province":"Overijssel",
    "wof:name":"Pluimveebedrijf Van Dam Slagharen",
    "wof:placetype":"venue"
},
  "geometry": {"coordinates":[6.530783,52.641251],"type":"Point"}
}