{
  "type": "Feature",
  "properties": {
    "addr:full":"Kastanjeln 12 Helvoirt Noord-Brabant 5268 CA",
    "addr:housenumber":"12",
    "addr:postcode":"5268 ca",
    "addr:street":"Kastanjeln",
    "iso:country":"NL",
    "sg:address":"Kastanjeln 12",
    "sg:city":"Helvoirt",
    "sg:orig_category":"Peuterspeelzalen",
    "sg:phone":"+31 411 642 293",
    "sg:postcode":"5268 CA",
    "sg:province":"Noord-Brabant",
    "wof:name":"Hummelhonk",
    "wof:placetype":"venue"
},
  "geometry": {"coordinates":[5.231339,51.634872],"type":"Point"}
}