{
  "type": "Feature",
  "properties": {
    "addr:full":"Valkenierslaan 324 Breda North Brabant 4834 CP",
    "addr:housenumber":"324",
    "addr:postcode":"4834 cp",
    "addr:street":"Valkenierslaan",
    "iso:country":"NL",
    "sg:address":"Valkenierslaan 324",
    "sg:city":"Breda",
    "sg:orig_category":"Bedrijfs- And Managementsconsultants",
    "sg:phone":"+31 76 565 3243",
    "sg:postcode":"4834 CP",
    "sg:province":"North Brabant",
    "wof:name":"J.M. Poncin Organisatieadviesburo",
    "wof:placetype":"venue"
},
  "geometry": {"coordinates":[4.80436,51.576851],"type":"Point"}
}