{
  "type": "Feature",
  "properties": {
    "iso:country":"NL",
    "sg:address":"Maaierstr 28",
    "sg:city":"Enschede",
    "sg:orig_category":"Adviesbureaus Bedrijfsorganisatie",
    "sg:phone":"+31 53 430 4460",
    "sg:postcode":"7545 XL",
    "sg:province":"Overijssel",
    "wof:name":"Resoluut",
    "wof:placetype":"venue"
},
  "geometry": {"coordinates":[6.867448,52.210609],"type":"Point"}
}