{
  "type": "Feature",
  "properties": {
    "addr:full":"Driesprong 11 Wervershoof Noord-Holland 1693 DG",
    "addr:housenumber":"11",
    "addr:postcode":"1693 dg",
    "addr:street":"Driesprong",
    "iso:country":"NL",
    "sg:address":"Driesprong 11",
    "sg:city":"Wervershoof",
    "sg:orig_category":"Schilders",
    "sg:phone":"+31 6 21571000",
    "sg:postcode":"1693 DG",
    "sg:province":"Noord-Holland",
    "wof:name":"Bas Groot",
    "wof:placetype":"venue"
},
  "geometry": {"coordinates":[5.14762,52.730137],"type":"Point"}
}