{
  "type": "Feature",
  "properties": {
    "iso:country":"NL",
    "sg:address":"Concordialn 207A",
    "sg:city":"Etten Leur",
    "sg:orig_category":"Kappers",
    "sg:phone":"+31 76 501 7077",
    "sg:postcode":"4871 ZA",
    "sg:province":"North Brabant",
    "wof:name":"Salonneke, 'T",
    "wof:placetype":"venue"
},
  "geometry": {"coordinates":[4.644215,51.58073],"type":"Point"}
}