{
  "type": "Feature",
  "properties": {
    "addr:full":"Pachtersweide 1 Nieuwegein Utrecht 3437 DA",
    "addr:housenumber":"1",
    "addr:postcode":"3437 da",
    "addr:street":"Pachtersweide",
    "iso:country":"NL",
    "sg:address":"Pachtersweide 1",
    "sg:city":"Nieuwegein",
    "sg:orig_category":"Accountants - Administratie- Consulenten En -Kantoren",
    "sg:phone":"+31 30 604 1970",
    "sg:postcode":"3437 DA",
    "sg:province":"Utrecht",
    "wof:name":"Jonas, G R A",
    "wof:placetype":"venue"
},
  "geometry": {"coordinates":[5.070373,52.046207],"type":"Point"}
}