{
  "type": "Feature",
  "properties": {
    "addr:full":"C Bakkerln 25 Laren Nh Noord-Holland 1251 BP",
    "addr:housenumber":"25",
    "addr:postcode":"1251 bp",
    "iso:country":"NL",
    "sg:address":"C Bakkerln 25",
    "sg:city":"Laren Nh",
    "sg:orig_category":"Adviesbureaus Bedrijfsorganisatie",
    "sg:phone":"+31 35 533 4051",
    "sg:postcode":"1251 BP",
    "sg:province":"Noord-Holland",
    "wof:name":"Morvenna Bv",
    "wof:placetype":"venue"
},
  "geometry": {"coordinates":[5.22387,52.256741],"type":"Point"}
}