{
  "type": "Feature",
  "properties": {
    "addr:full":"Dorpsstr 56 Terschelling Hoorn Provincie Friesland 8896 JG",
    "addr:housenumber":"56",
    "addr:postcode":"8896 jg",
    "addr:street":"Dorpsstr;Friesland",
    "iso:country":"NL",
    "sg:address":"Dorpsstr 56",
    "sg:city":"Terschelling Hoorn",
    "sg:orig_category":"Onroerende Goederen",
    "sg:phone":"+31 562 449 579",
    "sg:postcode":"8896 JG",
    "sg:province":"Provincie Friesland",
    "wof:name":"Mier Cupido Vof",
    "wof:placetype":"venue"
},
  "geometry": {"coordinates":[5.343626,53.39687],"type":"Point"}
}