{
  "type": "Feature",
  "properties": {
    "addr:full":"Postbus 95961 'S-Gravenhage Limburg 2509 CZ",
    "addr:housenumber":"95961;2509",
    "addr:street":"Postbus",
    "iso:country":"NL",
    "sg:address":"Postbus 95961",
    "sg:city":"'S-Gravenhage",
    "sg:orig_category":"Adviesbureaus Bedrijfsorganisatie",
    "sg:phone":"+31 70 381 4376",
    "sg:postcode":"2509 CZ",
    "sg:province":"Limburg",
    "wof:name":"Consuls Oti Bv",
    "wof:placetype":"venue"
},
  "geometry": {"coordinates":[2.543226,49.007736],"type":"Point"}
}