{
  "type": "Feature",
  "properties": {
    "addr:full":"Ceintuurbaan 47 Amsterdam Noord-Holland 1072 ET",
    "addr:housenumber":"47",
    "addr:postcode":"1072 et",
    "addr:street":"Ceintuurbaan",
    "iso:country":"NL",
    "sg:address":"Ceintuurbaan 47",
    "sg:city":"Amsterdam",
    "sg:orig_category":"Kappers",
    "sg:phone":"+31 20 673 0103",
    "sg:postcode":"1072 ET",
    "sg:province":"Noord-Holland",
    "wof:name":"1E Amsterdamsche Knip En Kapsalon Americ",
    "wof:placetype":"venue"
},
  "geometry": {"coordinates":[4.8886427879,52.3525886536],"type":"Point"}
}