{
  "type": "Feature",
  "properties": {
    "addr:full":"Beekerheide 24A Beek En Donk Noord-Brabant 5741 HC",
    "addr:housenumber":"24a",
    "addr:postcode":"5741 hc",
    "addr:street":"Beekerheide",
    "iso:country":"NL",
    "sg:address":"Beekerheide 24A",
    "sg:city":"Beek En Donk",
    "sg:classifiers":[
        {
            "category":"Retail",
            "subcategory":"Auto Repair",
            "type":"Services"
        }
    ],
    "sg:phone":"+31 492 463 432",
    "sg:postcode":"5741 HC",
    "sg:province":"Noord-Brabant",
    "sg:tags":[
        "garage"
    ],
    "sg:website":"http://www.jacobsautos.nl",
    "wof:name":"Jacobs",
    "wof:placetype":"venue"
},
  "geometry": {"coordinates":[5.642917,51.524071],"type":"Point"}
}