{
  "type": "Feature",
  "properties": {
    "addr:full":"Nw Uilenburgerstr 30-38 Amsterdam Noord-Holland 1011 LR",
    "addr:housenumber":"30-38",
    "addr:postcode":"1011 lr",
    "iso:country":"NL",
    "sg:address":"Nw Uilenburgerstr 30-38",
    "sg:city":"Amsterdam",
    "sg:orig_category":"Loodgieters",
    "sg:phone":"+31 20 624 2139",
    "sg:postcode":"1011 LR",
    "sg:province":"Noord-Holland",
    "wof:name":"Herfst Bv",
    "wof:placetype":"venue"
},
  "geometry": {"coordinates":[4.90454,52.370045],"type":"Point"}
}