{
  "type": "Feature",
  "properties": {
    "iso:country":"NL",
    "sg:address":"Klinkenberg 61",
    "sg:city":"Wezep",
    "sg:orig_category":"Bejaarden - Verzorgingstehuizen",
    "sg:phone":"+31 38 376 2626",
    "sg:postcode":"8091 GN",
    "sg:province":"Gelderland",
    "wof:name":"Veldheem",
    "wof:placetype":"venue"
},
  "geometry": {"coordinates":[6.003607,52.465256],"type":"Point"}
}