{
  "type": "Feature",
  "properties": {
    "addr:full":"Nijenrodestraat 13 Nijmegen Gelderland 6535 MK",
    "addr:housenumber":"13",
    "addr:postcode":"6535",
    "addr:street":"Nijenrodestraat;Gelderland",
    "iso:country":"NL",
    "sg:address":"Nijenrodestraat 13",
    "sg:city":"Nijmegen",
    "sg:orig_category":"Keramische Producten Fab",
    "sg:phone":"+31 24 356 3911",
    "sg:postcode":"6535 MK",
    "sg:province":"Gelderland",
    "wof:name":"Jacqueline Manders",
    "wof:placetype":"venue"
},
  "geometry": {"coordinates":[5.827664,51.804012],"type":"Point"}
}