{
  "type": "Feature",
  "properties": {
    "addr:full":"Jufferkd 30 Rotterdam Zuid-Holland 3011 VW",
    "addr:housenumber":"30",
    "addr:postcode":"3011 vw",
    "addr:street":"Jufferkd",
    "iso:country":"NL",
    "sg:address":"Jufferkd 30",
    "sg:city":"Rotterdam",
    "sg:orig_category":"Scheepvaartservice- Bureaus",
    "sg:phone":"+31 10 240 9819",
    "sg:postcode":"3011 VW",
    "sg:province":"Zuid-Holland",
    "wof:name":"Tacc Bv",
    "wof:placetype":"venue"
},
  "geometry": {"coordinates":[4.478455,51.922836],"type":"Point"}
}