{
  "type": "Feature",
  "properties": {
    "iso:country":"NL",
    "sg:address":"Prins Clausstraat 25",
    "sg:city":"Terborg",
    "sg:orig_category":"Drukkerijen And Copyshops",
    "sg:phone":"+31 314 362 891",
    "sg:postcode":"7061 XM",
    "sg:province":"Gelderland",
    "wof:name":"P S Druk Doetinchem",
    "wof:placetype":"venue"
},
  "geometry": {"coordinates":[6.346143,51.922817],"type":"Point"}
}