{
  "type": "Feature",
  "properties": {
    "addr:full":"Prins Clausstraat 25 Terborg Gelderland 7061 XM",
    "addr:housenumber":"25",
    "addr:postcode":"7061 xm",
    "addr:street":"Prins Clausstraat;Gelderland",
    "iso:country":"NL",
    "sg:address":"Prins Clausstraat 25",
    "sg:city":"Terborg",
    "sg:orig_category":"Drukkerijen And Copyshops",
    "sg:phone":"+31 314 362 891",
    "sg:postcode":"7061 XM",
    "sg:province":"Gelderland",
    "wof:name":"P S Druk Doetinchem",
    "wof:placetype":"venue"
},
  "geometry": {"coordinates":[6.346143,51.922817],"type":"Point"}
}