{
  "type": "Feature",
  "properties": {
    "iso:country":"NL",
    "sg:address":"Hoofdstraat 28",
    "sg:city":"Oirlo",
    "sg:classifiers":[
        {
            "category":"Education",
            "subcategory":"Preschool",
            "type":"Public Place"
        }
    ],
    "sg:phone":"+31 478 571 685",
    "sg:postcode":"5808 AV",
    "sg:province":"Limburg",
    "sg:tags":[
        "kleuteronderwijs",
        "basis-"
    ],
    "wof:name":"Basisschool Maria",
    "wof:placetype":"venue"
},
  "geometry": {"coordinates":[6.036982,51.509979],"type":"Point"}
}