{
  "type": "Feature",
  "properties": {
    "iso:country":"NL",
    "sg:address":"Postbus 189",
    "sg:city":"Woerden",
    "sg:orig_category":"Farmaceutische Industrie En Groothandel",
    "sg:phone":"+31 348 432 360",
    "sg:postcode":"3440 AD",
    "sg:province":"Utrecht",
    "wof:name":"Menarini Farma Ned",
    "wof:placetype":"venue"
},
  "geometry": {"coordinates":[4.887371,52.085117],"type":"Point"}
}