{
  "type": "Feature",
  "properties": {
    "iso:country":"NL",
    "sg:address":"Sloetsweg 230",
    "sg:city":"Hengelo Ov",
    "sg:orig_category":"Marktonderzoekbureaus",
    "sg:phone":"+31 74 250 5103",
    "sg:postcode":"7556 HV",
    "sg:province":"Overijssel",
    "wof:name":"Quinfoon",
    "wof:placetype":"venue"
},
  "geometry": {"coordinates":[6.795177,52.275169],"type":"Point"}
}