{
  "type": "Feature",
  "properties": {
    "iso:country":"NL",
    "sg:address":"Diamant 24",
    "sg:city":"Middelburg",
    "sg:orig_category":"Afslankinstituten",
    "sg:phone":"+31 118 629 367",
    "sg:postcode":"4337 MD",
    "sg:province":"Zeeland",
    "wof:name":"Slank '82",
    "wof:placetype":"venue"
},
  "geometry": {"coordinates":[3.623476,51.495831],"type":"Point"}
}