{
  "type": "Feature",
  "properties": {
    "addr:full":"De Vier Uitersten 17 Oirschot Noord-Brabant 5688 BN",
    "addr:housenumber":"17",
    "addr:postcode":"5688 bn",
    "addr:street":"De Vier Uitersten",
    "iso:country":"NL",
    "sg:address":"De Vier Uitersten 17",
    "sg:city":"Oirschot",
    "sg:classifiers":[
        {
            "category":"Education",
            "subcategory":"Preschool",
            "type":"Public Place"
        }
    ],
    "sg:phone":"+31 499 571 751",
    "sg:postcode":"5688 BN",
    "sg:province":"Noord-Brabant",
    "sg:tags":[
        "kleuteronderwijs",
        "basis-"
    ],
    "wof:name":"Ooievaarsnest Peuterspeelzaal Het",
    "wof:placetype":"venue"
},
  "geometry": {"coordinates":[5.310324,51.508362],"type":"Point"}
}