{
  "type": "Feature",
  "properties": {
    "iso:country":"NL",
    "sg:address":"Elbewg 125",
    "sg:city":"Europoort Rt",
    "sg:orig_category":"Levensmiddelen- Grondstoffen - Fabrieken En Groothandel",
    "sg:phone":"+31 181 257 200",
    "sg:postcode":"3198 LC",
    "sg:province":"South Holland",
    "wof:name":"Adm Europoort Bv",
    "wof:placetype":"venue"
},
  "geometry": {"coordinates":[4.121611,51.954052],"type":"Point"}
}