{
  "type": "Feature",
  "properties": {
    "addr:full":"Kerkplein 36 Voerendaal Limburg 6367 ER",
    "addr:housenumber":"36",
    "addr:postcode":"6367 er",
    "addr:street":"Kerkplein",
    "iso:country":"NL",
    "sg:address":"Kerkplein 36",
    "sg:city":"Voerendaal",
    "sg:orig_category":"Banken And Kredietinstellingen",
    "sg:phone":"+31 45 575 0300",
    "sg:postcode":"6367 ER",
    "sg:province":"Limburg",
    "wof:name":"Abn Amro",
    "wof:placetype":"venue"
},
  "geometry": {"coordinates":[5.926728,50.883011],"type":"Point"}
}