{
  "type": "Feature",
  "properties": {
    "addr:full":"Oude Boteringestr 47 Groningen Groningen 9712 GD",
    "addr:housenumber":"47",
    "addr:postcode":"9712 gd",
    "addr:street":"Oude Boteringestr",
    "iso:country":"NL",
    "sg:address":"Oude Boteringestr 47",
    "sg:city":"Groningen",
    "sg:orig_category":"Verenigingen En Stichtingen",
    "sg:phone":"+31 50 363 8090",
    "sg:postcode":"9712 GD",
    "sg:province":"Groningen",
    "wof:name":"Kei, Sticht",
    "wof:placetype":"venue"
},
  "geometry": {"coordinates":[6.563925,53.220123],"type":"Point"}
}