{
  "type": "Feature",
  "properties": {
    "addr:full":"Jonkerswg 3 Gelselaar Gelderland 7275 AV",
    "addr:housenumber":"3",
    "addr:postcode":"7275 av",
    "addr:street":"Jonkerswg;Gelderland",
    "iso:country":"NL",
    "sg:address":"Jonkerswg 3",
    "sg:city":"Gelselaar",
    "sg:orig_category":"Antiquiteiten - Restauratie",
    "sg:phone":"+31 545 481 498",
    "sg:postcode":"7275 AV",
    "sg:province":"Gelderland",
    "wof:name":"Bovenschutte, Meubelmakerij",
    "wof:placetype":"venue"
},
  "geometry": {"coordinates":[6.5322179794,52.1706924438],"type":"Point"}
}