{
  "type": "Feature",
  "properties": {
    "addr:full":"Wildenborch 93 Doetinchem Gelderland 7006 HL",
    "addr:housenumber":"93",
    "addr:postcode":"7006 hl",
    "addr:street":"Wildenborch;Gelderland",
    "iso:country":"NL",
    "sg:address":"Wildenborch 93",
    "sg:city":"Doetinchem",
    "sg:orig_category":"Verzekeringen - Verzekeringskantoren",
    "sg:phone":"+31 314 345 909",
    "sg:postcode":"7006 HL",
    "sg:province":"Gelderland",
    "wof:name":"Lemmens, Jan",
    "wof:placetype":"venue"
},
  "geometry": {"coordinates":[6.263656,51.964657],"type":"Point"}
}