{
  "type": "Feature",
  "properties": {
    "addr:full":"Tarwekamp 13 'S Gravenhage Zuid-Holland 2592 XG",
    "addr:housenumber":"13",
    "addr:postcode":"2592 xg",
    "addr:street":"Tarwekamp;' S",
    "iso:country":"NL",
    "sg:address":"Tarwekamp 13",
    "sg:city":"'S Gravenhage",
    "sg:orig_category":"Metaalwerken",
    "sg:phone":"+31 70 383 7414",
    "sg:postcode":"2592 XG",
    "sg:province":"Zuid-Holland",
    "wof:name":"Gebroeders Lanza Bv",
    "wof:placetype":"venue"
},
  "geometry": {"coordinates":[4.353282,52.088573],"type":"Point"}
}