{
  "type": "Feature",
  "properties": {
    "addr:full":"Kuipersweg 9 Woerden Utrecht 3449 JA",
    "addr:housenumber":"9",
    "addr:postcode":"3449 ja",
    "addr:street":"Kuipersweg",
    "iso:country":"NL",
    "sg:address":"Kuipersweg 9",
    "sg:city":"Woerden",
    "sg:orig_category":"Farmaceutische Producten Gh",
    "sg:phone":"+31 348 416 945",
    "sg:postcode":"3449 JA",
    "sg:province":"Utrecht",
    "wof:name":"Alfasan Nederland",
    "wof:placetype":"venue"
},
  "geometry": {"coordinates":[4.86154,52.085411],"type":"Point"}
}