{
  "type": "Feature",
  "properties": {
    "addr:full":"Aalsmeerderwg 489 Aalsmeer Noord-Holland 1432 ED",
    "addr:housenumber":"489",
    "addr:postcode":"aalsmeer;1432 ed",
    "iso:country":"NL",
    "sg:address":"Aalsmeerderwg 489",
    "sg:city":"Aalsmeer",
    "sg:orig_category":"Koeriersdiensten",
    "sg:phone":"+31 6 28763674",
    "sg:postcode":"1432 ED",
    "sg:province":"Noord-Holland",
    "wof:name":"Dvo",
    "wof:placetype":"venue"
},
  "geometry": {"coordinates":[4.820475,52.288696],"type":"Point"}
}