{
  "type": "Feature",
  "properties": {
    "addr:full":"Heuvelstr 140 Breda Noord-Brabant 4813 GC",
    "addr:housenumber":"140",
    "addr:postcode":"4813 gc",
    "iso:country":"NL",
    "sg:address":"Heuvelstr 140",
    "sg:city":"Breda",
    "sg:orig_category":"Bestratingen",
    "sg:phone":"+31 6 20557004",
    "sg:postcode":"4813 GC",
    "sg:province":"Noord-Brabant",
    "wof:name":"Gool, F M Van",
    "wof:placetype":"venue"
},
  "geometry": {"coordinates":[4.75042,51.5769],"type":"Point"}
}