{
  "type": "Feature",
  "properties": {
    "iso:country":"NL",
    "sg:address":"Reigerstr 11",
    "sg:city":"Breda",
    "sg:orig_category":"Antiquiteiten",
    "sg:phone":"+31 76 522 3200",
    "sg:postcode":"4811 XA",
    "sg:province":"Noord-Brabant",
    "wof:name":"Manu",
    "wof:placetype":"venue"
},
  "geometry": {"coordinates":[4.774984,51.589233],"type":"Point"}
}