{
  "type": "Feature",
  "properties": {
    "iso:country":"NL",
    "sg:address":"Raadhuisstr 36",
    "sg:city":"Rosmalen",
    "sg:orig_category":"Grafisch Ontwerpers",
    "sg:phone":"+31 73 523 6436",
    "sg:postcode":"5241 BL",
    "sg:province":"Noord-Brabant",
    "wof:name":"Hf",
    "wof:placetype":"venue"
},
  "geometry": {"coordinates":[5.357685,51.716232],"type":"Point"}
}