{
  "type": "Feature",
  "properties": {
    "addr:full":"Brandebeemd 33 Breda Noord-Brabant 4824 NT",
    "addr:housenumber":"33",
    "addr:postcode":"4824 nt",
    "addr:street":"Brandebeemd",
    "iso:country":"NL",
    "sg:address":"Brandebeemd 33",
    "sg:city":"Breda",
    "sg:orig_category":"Adviesbureaus Bedrijfsorganisatie",
    "sg:phone":"+31 6 55355094",
    "sg:postcode":"4824 NT",
    "sg:province":"Noord-Brabant",
    "wof:name":"Lagerwaard",
    "wof:placetype":"venue"
},
  "geometry": {"coordinates":[4.742146,51.606773],"type":"Point"}
}