{
  "type": "Feature",
  "properties": {
    "addr:full":"Dorpswg 15 Rotterdam South Holland 3082 LA",
    "addr:housenumber":"15",
    "addr:postcode":"3082 la",
    "addr:street":"Dorpswg",
    "iso:country":"NL",
    "sg:address":"Dorpswg 15",
    "sg:city":"Rotterdam",
    "sg:classifiers":[
        {
            "category":"Wholesale",
            "subcategory":"Meat",
            "type":"Manufacturing & Wholesale Goods"
        }
    ],
    "sg:phone":"+31 10 495 0899",
    "sg:postcode":"3082 LA",
    "sg:province":"South Holland",
    "sg:tags":[
        "hang-",
        "sluitwerk",
        "en"
    ],
    "sg:website":"http://www.safe-beveiliging.nl",
    "wof:name":"Safe Beveiliging",
    "wof:placetype":"venue"
},
  "geometry": {"coordinates":[4.473333,51.891262],"type":"Point"}
}