{
  "type": "Feature",
  "properties": {
    "addr:full":"Noordeindsewg 134 Berkel En Rodenrys Zuid-Holland 2651 CX",
    "addr:housenumber":"134",
    "addr:postcode":"2651 cx",
    "addr:street":"Berkel",
    "iso:country":"NL",
    "sg:address":"Noordeindsewg 134",
    "sg:city":"Berkel En Rodenrys",
    "sg:orig_category":"Woninginrichting",
    "sg:phone":"+31 10 511 2321",
    "sg:postcode":"2651 CX",
    "sg:province":"Zuid-Holland",
    "wof:name":"Wilt, Van Der",
    "wof:placetype":"venue"
},
  "geometry": {"coordinates":[4.4827208519,52.0029258728],"type":"Point"}
}