{
  "type": "Feature",
  "properties": {
    "addr:full":"Stille Veerkade 48 'S Gravenhage Zuid-Holland 2512 BG",
    "addr:housenumber":"48",
    "addr:postcode":"2512",
    "addr:street":"Stille Veerkade;' S",
    "iso:country":"NL",
    "sg:address":"Stille Veerkade 48",
    "sg:city":"'S Gravenhage",
    "sg:classifiers":[
        {
            "category":"Fast Food",
            "type":"Food & Drink"
        }
    ],
    "sg:phone":"+31 70 360 6069",
    "sg:postcode":"2512 BG",
    "sg:province":"Zuid-Holland",
    "sg:tags":[
        "afhaal",
        "restaurant"
    ],
    "wof:name":"Shoarma Medina",
    "wof:placetype":"venue"
},
  "geometry": {"coordinates":[4.313738,52.07349],"type":"Point"}
}