{
  "type": "Feature",
  "properties": {
    "iso:country":"NL",
    "sg:address":"Nyverheidspln 21L",
    "sg:city":"Barneveld",
    "sg:orig_category":"Werving En Selectie",
    "sg:phone":"+31 342 405 959",
    "sg:postcode":"3771 MR",
    "sg:province":"Gelderland",
    "wof:name":"Humatch Group Bv",
    "wof:placetype":"venue"
},
  "geometry": {"coordinates":[5.5959157944,52.1657447815],"type":"Point"}
}