{
  "type": "Feature",
  "properties": {
    "iso:country":"NL",
    "sg:address":"Kornewal 14",
    "sg:city":"Buren Gld",
    "sg:orig_category":"Verzekeringen",
    "sg:phone":"+31 344 572 891",
    "sg:postcode":"4116 BJ",
    "sg:province":"Gelderland",
    "wof:name":"Van Der Vossen Advies",
    "wof:placetype":"venue"
},
  "geometry": {"coordinates":[5.332477,51.910423],"type":"Point"}
}