{
  "type": "Feature",
  "properties": {
    "iso:country":"NL",
    "sg:address":"St Janskerkhof 38",
    "sg:city":"Amersfoort",
    "sg:orig_category":"Adviesbureaus Bedrijfsorganisatie",
    "sg:phone":"+31 6 55340493",
    "sg:postcode":"3811 HW",
    "sg:province":"Utrecht",
    "wof:name":"Laroche",
    "wof:placetype":"venue"
},
  "geometry": {"coordinates":[5.394828,52.156536],"type":"Point"}
}