{
  "type": "Feature",
  "properties": {
    "addr:full":"Ruitersstraat 6 Landgraaf Limburg 6371 GP",
    "addr:housenumber":"6",
    "addr:postcode":"6371 gp",
    "addr:street":"Ruitersstraat",
    "iso:country":"NL",
    "sg:address":"Ruitersstraat 6",
    "sg:city":"Landgraaf",
    "sg:orig_category":"Kinderopvang Behalve Thuis",
    "sg:phone":"+31 45 532 5665",
    "sg:postcode":"6371 GP",
    "sg:province":"Limburg",
    "wof:name":"Griebel Kinderdagverblijf",
    "wof:placetype":"venue"
},
  "geometry": {"coordinates":[6.015224,50.898052],"type":"Point"}
}