{
  "type": "Feature",
  "properties": {
    "iso:country":"NL",
    "sg:address":"Castricummer Werf 11",
    "sg:city":"Castricum",
    "sg:orig_category":"Schilders",
    "sg:phone":"+31 251 659 412",
    "sg:postcode":"1901 RW",
    "sg:province":"Noord-Holland",
    "sg:website":"http://www.nicocastricum.nl",
    "wof:name":"Castricum, Nico",
    "wof:placetype":"venue"
},
  "geometry": {"coordinates":[4.664483,52.539783],"type":"Point"}
}