{
  "type": "Feature",
  "properties": {
    "addr:full":"Oosterpark 30 Amsterdam Noord-Holland 1092 AJ",
    "addr:housenumber":"30",
    "addr:postcode":"1092 aj",
    "addr:street":"Oosterpark",
    "iso:country":"NL",
    "sg:address":"Oosterpark 30",
    "sg:city":"Amsterdam",
    "sg:orig_category":"Begrafenisondernemers",
    "sg:phone":"+31 20 694 4737",
    "sg:postcode":"1092 AJ",
    "sg:province":"Noord-Holland",
    "wof:name":"Vital Van Looveren",
    "wof:placetype":"venue"
},
  "geometry": {"coordinates":[4.919451,52.35841],"type":"Point"}
}