{
  "type": "Feature",
  "properties": {
    "addr:full":"W De Withstr 48 Rotterdam Zuid-Holland 3012 BR",
    "addr:housenumber":"48",
    "addr:postcode":"3012 br",
    "addr:street":"W De Withstr",
    "iso:country":"NL",
    "sg:address":"W De Withstr 48",
    "sg:city":"Rotterdam",
    "sg:orig_category":"Galeries",
    "sg:phone":"+31 10 411 5662",
    "sg:postcode":"3012 BR",
    "sg:province":"Zuid-Holland",
    "wof:name":"Oplichterij, De",
    "wof:placetype":"venue"
},
  "geometry": {"coordinates":[4.477057,51.915447],"type":"Point"}
}