{
  "type": "Feature",
  "properties": {
    "iso:country":"NL",
    "sg:address":"J P Coenstr 82",
    "sg:city":"Utrecht",
    "sg:orig_category":"Huishoudelijke Apparaten En Artikelen",
    "sg:phone":"+31 30 296 7928",
    "sg:postcode":"3531 EX",
    "sg:province":"Utrecht",
    "wof:name":"Bazar-Lombok",
    "wof:placetype":"venue"
},
  "geometry": {"coordinates":[5.09574,52.090012],"type":"Point"}
}