{
  "type": "Feature",
  "properties": {
    "addr:full":"Delfgauwsewg 299 Delft Zuid-Holland 2628 ES",
    "addr:housenumber":"299",
    "addr:postcode":"delft;2628 es",
    "iso:country":"NL",
    "sg:address":"Delfgauwsewg 299",
    "sg:city":"Delft",
    "sg:orig_category":"Adviesbureaus Bedrijfsorganisatie",
    "sg:phone":"+31 15 285 0958",
    "sg:postcode":"2628 ES",
    "sg:province":"Zuid-Holland",
    "sg:website":"http://www.ini-consult.nl",
    "wof:name":"Ini Consult",
    "wof:placetype":"venue"
},
  "geometry": {"coordinates":[4.380683,52.007114],"type":"Point"}
}