{
  "type": "Feature",
  "properties": {
    "addr:full":"Oelemarkt 11 Weert Limburg 6001 ES",
    "addr:housenumber":"11",
    "addr:postcode":"6001 es",
    "addr:street":"Oelemarkt",
    "iso:country":"NL",
    "sg:address":"Oelemarkt 11",
    "sg:city":"Weert",
    "sg:orig_category":"Discotheken",
    "sg:phone":"+31 495 534 841",
    "sg:postcode":"6001 ES",
    "sg:province":"Limburg",
    "wof:name":"Carte Blanche",
    "wof:placetype":"venue"
},
  "geometry": {"coordinates":[5.708745,51.255493],"type":"Point"}
}