{
  "type": "Feature",
  "properties": {
    "iso:country":"NL",
    "sg:address":"Kruisstr 9",
    "sg:city":"Meerssen",
    "sg:orig_category":"Drukkerijen",
    "sg:phone":"+31 43 364 2225",
    "sg:postcode":"6231 LJ",
    "sg:province":"Limburg",
    "wof:name":"Maenen Bv",
    "wof:placetype":"venue"
},
  "geometry": {"coordinates":[5.756351,50.884403],"type":"Point"}
}