{
  "type": "Feature",
  "properties": {
    "addr:full":"Dorpsstr 577 Noord Scharwoude Noord-Holland 1723 HB",
    "addr:housenumber":"577",
    "addr:postcode":"1723 hb",
    "iso:country":"NL",
    "sg:address":"Dorpsstr 577",
    "sg:city":"Noord Scharwoude",
    "sg:orig_category":"Banken",
    "sg:phone":"+31 226 319 661",
    "sg:postcode":"1723 HB",
    "sg:province":"Noord-Holland",
    "sg:website":"http://www.rabobank.nl",
    "wof:name":"Rabobank",
    "wof:placetype":"venue"
},
  "geometry": {"coordinates":[4.810671,52.701115],"type":"Point"}
}