{
  "type": "Feature",
  "properties": {
    "addr:full":"Markt 28 Ter Apel Groningen 9561 KB",
    "addr:housenumber":"28",
    "addr:postcode":"9561 kb",
    "addr:street":"Markt",
    "iso:country":"NL",
    "sg:address":"Markt 28",
    "sg:city":"Ter Apel",
    "sg:orig_category":"Warenhuizen",
    "sg:phone":"+31 599 583 202",
    "sg:postcode":"9561 KB",
    "sg:province":"Groningen",
    "wof:name":"Action Bv",
    "wof:placetype":"venue"
},
  "geometry": {"coordinates":[7.0588951111,52.8748245239],"type":"Point"}
}