{
  "type": "Feature",
  "properties": {
    "addr:full":"Knipmolenwg 2A Gouda Zuid-Holland 2807 DC",
    "addr:housenumber":"2a",
    "addr:postcode":"2807",
    "addr:street":"Knipmolenwg",
    "iso:country":"NL",
    "sg:address":"Knipmolenwg 2A",
    "sg:city":"Gouda",
    "sg:orig_category":"Peuterspeelzalen",
    "sg:phone":"+31 182 581 753",
    "sg:postcode":"2807 DC",
    "sg:province":"Zuid-Holland",
    "wof:name":"Draaimolen, De",
    "wof:placetype":"venue"
},
  "geometry": {"coordinates":[4.743207,52.00824],"type":"Point"}
}