{
  "type": "Feature",
  "properties": {
    "addr:full":"Stadhouderskade 2 Amsterdam North Holland 1054 ES",
    "addr:housenumber":"2",
    "addr:postcode":"1054 es",
    "addr:street":"Stadhouderskade",
    "iso:country":"NL",
    "sg:address":"Stadhouderskade 2",
    "sg:city":"Amsterdam",
    "sg:orig_category":"Bioscopen",
    "sg:phone":"+31 20 668 6126",
    "sg:postcode":"1054 ES",
    "sg:province":"North Holland",
    "wof:name":"Ace",
    "wof:placetype":"venue"
},
  "geometry": {"coordinates":[4.878868,52.363449],"type":"Point"}
}