{
  "type": "Feature",
  "properties": {
    "iso:country":"NL",
    "sg:address":"Prins Bernhardstraat 43",
    "sg:city":"Bodegraven",
    "sg:orig_category":"Metaalwerken",
    "sg:phone":"+31 172 651 712",
    "sg:postcode":"2411 TK",
    "sg:province":"South Holland",
    "wof:name":"Sunproned Prefab Zonwering Nederland",
    "wof:placetype":"venue"
},
  "geometry": {"coordinates":[4.751919,52.081993],"type":"Point"}
}