{
  "type": "Feature",
  "properties": {
    "addr:full":"Eperwg 9 Nunspeet Gelderland 8071 AW",
    "addr:housenumber":"9",
    "addr:postcode":"8071 aw",
    "addr:street":"Eperwg;Gelderland",
    "iso:country":"NL",
    "sg:address":"Eperwg 9",
    "sg:city":"Nunspeet",
    "sg:orig_category":"Projectontwikkeling",
    "sg:phone":"+31 341 258 099",
    "sg:postcode":"8071 AW",
    "sg:province":"Gelderland",
    "wof:name":"Noord Ned Bouwbeheer Bv",
    "wof:placetype":"venue"
},
  "geometry": {"coordinates":[5.789135,52.37672],"type":"Point"}
}