{
  "type": "Feature",
  "properties": {
    "addr:full":"Hoff V Hollantln 7 Rosmalen Noord-Brabant 5243 SR",
    "addr:housenumber":"7",
    "addr:postcode":"5243 sr",
    "addr:street":"Hollantln",
    "iso:country":"NL",
    "sg:address":"Hoff V Hollantln 7",
    "sg:city":"Rosmalen",
    "sg:orig_category":"Adviesbureaus",
    "sg:phone":"+31 73 523 3900",
    "sg:postcode":"5243 SR",
    "sg:province":"Noord-Brabant",
    "sg:website":"http://www.croonen.nl",
    "wof:name":"Croonen Adviseurs",
    "wof:placetype":"venue"
},
  "geometry": {"coordinates":[5.395368,51.731022],"type":"Point"}
}