{
  "type": "Feature",
  "properties": {
    "iso:country":"NL",
    "sg:address":"Venlosingel 21",
    "sg:city":"Arnhem",
    "sg:orig_category":"Meubelzaken, Woning- And Keukeninrichting",
    "sg:phone":"+31 26 382 1077",
    "sg:postcode":"6845 JL",
    "sg:province":"Gelderland",
    "wof:name":"Trendhopper",
    "wof:placetype":"venue"
},
  "geometry": {"coordinates":[5.875695,51.949661],"type":"Point"}
}