{
  "type": "Feature",
  "properties": {
    "addr:full":"M Rutgersstr 18 Maassluis Zuid-Holland 3141 XS",
    "addr:housenumber":"18",
    "addr:postcode":"3141 xs",
    "iso:country":"NL",
    "sg:address":"M Rutgersstr 18",
    "sg:city":"Maassluis",
    "sg:orig_category":"Adviesbureaus Bedrijfsorganisatie",
    "sg:phone":"+31 10 599 7175",
    "sg:postcode":"3141 XS",
    "sg:province":"Zuid-Holland",
    "wof:name":"Hge",
    "wof:placetype":"venue"
},
  "geometry": {"coordinates":[4.272656,51.920174],"type":"Point"}
}