{
  "type": "Feature",
  "properties": {
    "addr:full":"Meelstraat 69 Tilburg Noord-Brabant 5025 KL",
    "addr:housenumber":"69",
    "addr:postcode":"5025 kl",
    "addr:street":"Meelstraat",
    "iso:country":"NL",
    "sg:address":"Meelstraat 69",
    "sg:city":"Tilburg",
    "sg:orig_category":"Huishoudapparatuur, Televisies And Radio'S",
    "sg:phone":"+31 13 542 4415",
    "sg:postcode":"5025 KL",
    "sg:province":"Noord-Brabant",
    "wof:name":"Leo Van Deursen",
    "wof:placetype":"venue"
},
  "geometry": {"coordinates":[5.070994,51.552898],"type":"Point"}
}