{
  "type": "Feature",
  "properties": {
    "addr:full":"J V Beierenln 176 Leiderdorp South Holland 2353 DW",
    "addr:housenumber":"176",
    "addr:postcode":"2353 dw",
    "addr:street":"J;Beierenln",
    "iso:country":"NL",
    "sg:address":"J V Beierenln 176",
    "sg:city":"Leiderdorp",
    "sg:orig_category":"Autorijscholen",
    "sg:phone":"+31 71 542 0293",
    "sg:postcode":"2353 DW",
    "sg:province":"South Holland",
    "wof:name":"My Way Autorijschool",
    "wof:placetype":"venue"
},
  "geometry": {"coordinates":[4.534218,52.156174],"type":"Point"}
}