{
  "type": "Feature",
  "properties": {
    "addr:full":"Dorpstr 125 Brunssum Limburg 6441 CD",
    "addr:housenumber":"125",
    "addr:postcode":"6441 cd",
    "addr:street":"Brunssum Limburg",
    "iso:country":"NL",
    "sg:address":"Dorpstr 125",
    "sg:city":"Brunssum",
    "sg:orig_category":"Makelaars En Adviseurs Onroerende Goederen",
    "sg:phone":"+31 45 525 1465",
    "sg:postcode":"6441 CD",
    "sg:province":"Limburg",
    "wof:name":"Winkens",
    "wof:placetype":"venue"
},
  "geometry": {"coordinates":[5.970823,50.950771],"type":"Point"}
}