{
  "type": "Feature",
  "properties": {
    "iso:country":"NL",
    "sg:address":"Vlotbrugwg 24",
    "sg:city":"Almere",
    "sg:orig_category":"Bijouterie?n - Fabrieken En Groothandel",
    "sg:phone":"+31 36 532 0777",
    "sg:postcode":"1332 AJ",
    "sg:province":"Flevoland",
    "wof:name":"Inter-Byoux Holl Vof",
    "wof:placetype":"venue"
},
  "geometry": {"coordinates":[5.246817,52.402508],"type":"Point"}
}