{
  "type": "Feature",
  "properties": {
    "addr:full":"Castorwg 19 Leeuwarden Provincie Friesland 8938 BE",
    "addr:housenumber":"19",
    "addr:postcode":"8938",
    "addr:street":"Castorwg;Provincie Friesland",
    "iso:country":"NL",
    "sg:address":"Castorwg 19",
    "sg:city":"Leeuwarden",
    "sg:orig_category":"Grafische Bedrijven",
    "sg:phone":"+31 58 213 6585",
    "sg:postcode":"8938 BE",
    "sg:province":"Provincie Friesland",
    "sg:website":"http://www.bgc-bv.nl",
    "wof:name":"Bgc Bv",
    "wof:placetype":"venue"
},
  "geometry": {"coordinates":[5.852985,53.200764],"type":"Point"}
}