{
  "type": "Feature",
  "properties": {
    "iso:country":"NL",
    "sg:address":"Sloterwg 182/A",
    "sg:city":"Badhoevedorp",
    "sg:orig_category":"Fotografie Reclame En Mode",
    "sg:phone":"+31 20 659 6705",
    "sg:postcode":"1171 CW",
    "sg:province":"Noord-Holland",
    "sg:website":"http://www.reclame.net/brightview",
    "wof:name":"Brandwijk Studio, Van",
    "wof:placetype":"venue"
},
  "geometry": {"coordinates":[4.777575,52.336658],"type":"Point"}
}