{
  "type": "Feature",
  "properties": {
    "addr:full":"Oude Wetering 34 Mastenbroek NL.08 8294 PB",
    "addr:housenumber":"34;nl.08",
    "addr:postcode":"8294 pb",
    "addr:street":"Oude Wetering",
    "iso:country":"NL",
    "sg:address":"Oude Wetering 34",
    "sg:city":"Mastenbroek",
    "sg:orig_category":"Loodgieterswerk, Verwarming And Sanitaire Installaties",
    "sg:phone":"+31 38 344 6382",
    "sg:postcode":"8294 PB",
    "sg:province":"NL.08",
    "wof:name":"L.M.B. Van Den Berg Bv",
    "wof:placetype":"venue"
},
  "geometry": {"coordinates":[6.031841,52.561146],"type":"Point"}
}