{
  "type": "Feature",
  "properties": {
    "addr:full":"Barteljorisstraat 7 Haarlem North Holland 2011 RA",
    "addr:housenumber":"7",
    "addr:postcode":"2011 ra",
    "addr:street":"Barteljorisstraat",
    "iso:country":"NL",
    "sg:address":"Barteljorisstraat 7",
    "sg:city":"Haarlem",
    "sg:orig_category":"Werving And Selectie Van Tijdelijk Personeel And Uitzendkantoren",
    "sg:phone":"+31 23 531 9157",
    "sg:postcode":"2011 RA",
    "sg:province":"North Holland",
    "wof:name":"Vedior",
    "wof:placetype":"venue"
},
  "geometry": {"coordinates":[4.6354417801,52.3826293945],"type":"Point"}
}