{
  "type": "Feature",
  "properties": {
    "addr:full":"Te Winkelhof 27 Heemstede Noord-Holland 2105 TA",
    "addr:housenumber":"27",
    "addr:postcode":"2105 ta",
    "addr:street":"Te Winkelhof",
    "iso:country":"NL",
    "sg:address":"Te Winkelhof 27",
    "sg:city":"Heemstede",
    "sg:orig_category":"Medische Apparatuur And Prothesen Fab",
    "sg:phone":"+31 23 528 0280",
    "sg:postcode":"2105 TA",
    "sg:province":"Noord-Holland",
    "wof:name":"Hoortechniek Heemstede",
    "wof:placetype":"venue"
},
  "geometry": {"coordinates":[4.608885,52.352009],"type":"Point"}
}