{
  "type": "Feature",
  "properties": {
    "addr:full":"Oudlandsedijk 2 Oudenbosch North Brabant 4731 TB",
    "addr:housenumber":"2",
    "addr:postcode":"4731 tb",
    "addr:street":"Oudlandsedijk",
    "iso:country":"NL",
    "sg:address":"Oudlandsedijk 2",
    "sg:city":"Oudenbosch",
    "sg:orig_category":"Kantoor- And Schoolbenodigdheden Gh",
    "sg:phone":"+31 165 314 752",
    "sg:postcode":"4731 TB",
    "sg:province":"North Brabant",
    "wof:name":"Jadepa Trading Bv",
    "wof:placetype":"venue"
},
  "geometry": {"coordinates":[4.5186100006,51.6069412231],"type":"Point"}
}