{
  "type": "Feature",
  "properties": {
    "addr:full":"Kosmonaut 26 Amersfoort Utrecht 3824 MK",
    "addr:housenumber":"26",
    "addr:postcode":"3824",
    "addr:street":"Kosmonaut",
    "iso:country":"NL",
    "sg:address":"Kosmonaut 26",
    "sg:city":"Amersfoort",
    "sg:orig_category":"Hydraulische Apparaten En Installaties",
    "sg:phone":"+31 33 454 3210",
    "sg:postcode":"3824 MK",
    "sg:province":"Utrecht",
    "wof:name":"Hydropack Systemen Bv",
    "wof:placetype":"venue"
},
  "geometry": {"coordinates":[5.392475,52.198742],"type":"Point"}
}