{
  "type": "Feature",
  "properties": {
    "addr:full":"Velperweg 143 Arnhem Gelderland 6824 HK",
    "addr:housenumber":"143",
    "addr:postcode":"6824 hk",
    "addr:street":"Velperweg",
    "iso:country":"NL",
    "sg:address":"Velperweg 143",
    "sg:city":"Arnhem",
    "sg:orig_category":"Fruit And Groenten Gh",
    "sg:phone":"+31 26 361 6554",
    "sg:postcode":"6824 HK",
    "sg:province":"Gelderland",
    "wof:name":"A Derksen",
    "wof:placetype":"venue"
},
  "geometry": {"coordinates":[5.946502,51.992416],"type":"Point"}
}