{
  "type": "Feature",
  "properties": {
    "addr:full":"Jan Steenlaan 8 Oosterhout Nb Noord-Brabant 4907 RJ",
    "addr:housenumber":"8",
    "addr:postcode":"4907 rj",
    "addr:street":"Jan Steenlaan",
    "iso:country":"NL",
    "sg:address":"Jan Steenlaan 8",
    "sg:city":"Oosterhout Nb",
    "sg:orig_category":"Binnenhuisarchitecten",
    "sg:phone":"+31 162 471 179",
    "sg:postcode":"4907 RJ",
    "sg:province":"Noord-Brabant",
    "wof:name":"M. Van Noort",
    "wof:placetype":"venue"
},
  "geometry": {"coordinates":[4.87708,51.661438],"type":"Point"}
}