{
  "type": "Feature",
  "properties": {
    "addr:full":"Bessemvlinderstraat 135 Eindhoven North Brabant 5641 EC",
    "addr:housenumber":"135",
    "addr:postcode":"5641 ec",
    "addr:street":"Bessemvlinderstraat",
    "iso:country":"NL",
    "sg:address":"Bessemvlinderstraat 135",
    "sg:city":"Eindhoven",
    "sg:orig_category":"Diverse Grafische Activiteiten",
    "sg:phone":"+31 40 281 4688",
    "sg:postcode":"5641 EC",
    "sg:province":"North Brabant",
    "wof:name":"Stan Groenland",
    "wof:placetype":"venue"
},
  "geometry": {"coordinates":[5.520312,51.452999],"type":"Point"}
}