{
  "type": "Feature",
  "properties": {
    "addr:full":"Aalscholverlaan 4 Zeist Utrecht 3704 HN",
    "addr:housenumber":"4",
    "addr:postcode":"3704 hn",
    "addr:street":"Aalscholverlaan",
    "iso:country":"NL",
    "sg:address":"Aalscholverlaan 4",
    "sg:city":"Zeist",
    "sg:orig_category":"Drukkerijen And Copyshops",
    "sg:phone":"+31 30 695 6444",
    "sg:postcode":"3704 HN",
    "sg:province":"Utrecht",
    "wof:name":"Roveka Bv",
    "wof:placetype":"venue"
},
  "geometry": {"coordinates":[5.212642,52.088924],"type":"Point"}
}