{
  "type": "Feature",
  "properties": {
    "iso:country":"NL",
    "sg:address":"Eindstr 10",
    "sg:city":"Breda",
    "sg:orig_category":"Schoenen",
    "sg:phone":"+31 76 514 1621",
    "sg:postcode":"4811 KL",
    "sg:province":"North Brabant",
    "wof:name":"Dalen Bv, Van",
    "wof:placetype":"venue"
},
  "geometry": {"coordinates":[4.775811,51.586666],"type":"Point"}
}