{
  "type": "Feature",
  "properties": {
    "addr:full":"Torenlaan 1 Voorhout Zuid-Holland 2215 RW",
    "addr:housenumber":"1",
    "addr:postcode":"2215 rw",
    "addr:street":"Torenlaan",
    "iso:country":"NL",
    "sg:address":"Torenlaan 1",
    "sg:city":"Voorhout",
    "sg:orig_category":"Advocaten And Juridische Adviseurs",
    "sg:phone":"+31 252 231 564",
    "sg:postcode":"2215 RW",
    "sg:province":"Zuid-Holland",
    "wof:name":"Advocatenkantoor Dekker",
    "wof:placetype":"venue"
},
  "geometry": {"coordinates":[4.513622,52.238018],"type":"Point"}
}