{
  "type": "Feature",
  "properties": {
    "addr:full":"T De Bockstr 27 Amsterdam Noord-Holland 1058 TW",
    "addr:housenumber":"27",
    "addr:postcode":"1058 tw",
    "addr:street":"T",
    "iso:country":"NL",
    "sg:address":"T De Bockstr 27",
    "sg:city":"Amsterdam",
    "sg:orig_category":"Onderhoudswerken",
    "sg:phone":"+31 20 777 3567",
    "sg:postcode":"1058 TW",
    "sg:province":"Noord-Holland",
    "wof:name":"Robben Onderhoudswerken J W",
    "wof:placetype":"venue"
},
  "geometry": {"coordinates":[4.850031,52.354713],"type":"Point"}
}