{
  "type": "Feature",
  "properties": {
    "addr:full":"Markt 211 Helmond North Brabant 5701 RJ",
    "addr:housenumber":"211",
    "addr:postcode":"5701 rj",
    "addr:street":"Markt",
    "iso:country":"NL",
    "sg:address":"Markt 211",
    "sg:city":"Helmond",
    "sg:orig_category":"Public Relationbureaus",
    "sg:phone":"+31 492 554 184",
    "sg:postcode":"5701 RJ",
    "sg:province":"North Brabant",
    "wof:name":"Stadpromotie Helmond",
    "wof:placetype":"venue"
},
  "geometry": {"coordinates":[5.656927,51.480732],"type":"Point"}
}