{
  "type": "Feature",
  "properties": {
    "iso:country":"NL",
    "sg:address":"Markt 211",
    "sg:city":"Helmond",
    "sg:orig_category":"Public Relationbureaus",
    "sg:phone":"+31 492 554 184",
    "sg:postcode":"5701 RJ",
    "sg:province":"North Brabant",
    "wof:name":"Stadpromotie Helmond",
    "wof:placetype":"venue"
},
  "geometry": {"coordinates":[5.656927,51.480732],"type":"Point"}
}