{
  "type": "Feature",
  "properties": {
    "addr:full":"Kennedylaan 1 Leiden South Holland 2324 ER",
    "addr:housenumber":"1",
    "addr:postcode":"2324 er",
    "addr:street":"Kennedylaan",
    "iso:country":"NL",
    "sg:address":"Kennedylaan 1",
    "sg:city":"Leiden",
    "sg:classifiers":[
        {
            "category":"Education",
            "subcategory":"Preschool",
            "type":"Public Place"
        }
    ],
    "sg:phone":"+31 71 576 3314",
    "sg:postcode":"2324 ER",
    "sg:province":"South Holland",
    "sg:tags":[
        "kleuteronderwijs",
        "basis-"
    ],
    "wof:name":"De Sleutelbloem",
    "wof:placetype":"venue"
},
  "geometry": {"coordinates":[4.475081,52.141705],"type":"Point"}
}