{
  "type": "Feature",
  "properties": {
    "addr:full":"Julianapark 16 Haarlem Noord-Holland 2022 AA",
    "addr:housenumber":"16",
    "addr:postcode":"2022 aa",
    "addr:street":"Julianapark",
    "iso:country":"NL",
    "sg:address":"Julianapark 16",
    "sg:city":"Haarlem",
    "sg:orig_category":"Visspeciaalzaken",
    "sg:phone":"+31 23 525 4636",
    "sg:postcode":"2022 AA",
    "sg:province":"Noord-Holland",
    "wof:name":"Harms Viskiosk",
    "wof:placetype":"venue"
},
  "geometry": {"coordinates":[4.643091,52.396706],"type":"Point"}
}