{
  "type": "Feature",
  "properties": {
    "addr:full":"Rusland 17 Amsterdam North Holland 1012 CK",
    "addr:housenumber":"17",
    "addr:postcode":"1012 ck",
    "addr:street":"Rusland",
    "iso:country":"NL",
    "sg:address":"Rusland 17",
    "sg:city":"Amsterdam",
    "sg:classifiers":[
        {
            "category":"Travel",
            "subcategory":"Hotels & Motels",
            "type":"Entertainment"
        }
    ],
    "sg:phone":"+31 20 623 1231",
    "sg:postcode":"1012 CK",
    "sg:province":"North Holland",
    "sg:website":"http://www.lookandbook.com/amsterdam/radisson_sas.htm",
    "wof:name":"Radisson Sas",
    "wof:placetype":"venue"
},
  "geometry": {"coordinates":[4.896718,52.370163],"type":"Point"}
}