{
  "type": "Feature",
  "properties": {
    "addr:full":"Ambachtsweg 8 Katwijk Zh Zuid-Holland 2222 AK",
    "addr:housenumber":"8",
    "addr:postcode":"2222 ak",
    "addr:street":"Ambachtsweg",
    "iso:country":"NL",
    "sg:address":"Ambachtsweg 8",
    "sg:city":"Katwijk Zh",
    "sg:orig_category":"Visspeciaalzaken",
    "sg:phone":"+31 71 408 0808",
    "sg:postcode":"2222 AK",
    "sg:province":"Zuid-Holland",
    "wof:name":"Vishandel Almelo",
    "wof:placetype":"venue"
},
  "geometry": {"coordinates":[4.430366,52.201828],"type":"Point"}
}