{
  "type": "Feature",
  "properties": {
    "addr:full":"Molendijk 22 Numansdorp South Holland 3281 LT",
    "addr:housenumber":"22",
    "addr:postcode":"3281 lt",
    "addr:street":"Molendijk",
    "iso:country":"NL",
    "sg:address":"Molendijk 22",
    "sg:city":"Numansdorp",
    "sg:orig_category":"Pluimveehouderijen",
    "sg:phone":"+31 186 651 485",
    "sg:postcode":"3281 LT",
    "sg:province":"South Holland",
    "wof:name":"A.H. Huisert",
    "wof:placetype":"venue"
},
  "geometry": {"coordinates":[4.399872,51.737553],"type":"Point"}
}