{
  "type": "Feature",
  "properties": {
    "iso:country":"NL",
    "sg:address":"Thomsonplein 13",
    "sg:city":"'S Gravenhage",
    "sg:orig_category":"Verzekeringen",
    "sg:phone":"+31 70 363 7070",
    "sg:postcode":"2565 KT",
    "sg:province":"Zuid-Holland",
    "wof:name":"Ass Bedr Eklana",
    "wof:placetype":"venue"
},
  "geometry": {"coordinates":[4.271074,52.079605],"type":"Point"}
}