{
  "type": "Feature",
  "properties": {
    "addr:full":"Marnixstr 92 Amsterdam Noord-Holland 1015 VZ",
    "addr:housenumber":"92",
    "addr:postcode":"1015 vz",
    "addr:street":"Marnixstr",
    "iso:country":"NL",
    "sg:address":"Marnixstr 92",
    "sg:city":"Amsterdam",
    "sg:orig_category":"Vertalers",
    "sg:phone":"+31 20 623 5301",
    "sg:postcode":"1015 VZ",
    "sg:province":"Noord-Holland",
    "wof:name":"Al-Tamimi, K R",
    "wof:placetype":"venue"
},
  "geometry": {"coordinates":[4.879355,52.379139],"type":"Point"}
}