{
  "type": "Feature",
  "properties": {
    "iso:country":"NL",
    "sg:address":"Linie 107-111",
    "sg:city":"Apeldoorn",
    "sg:orig_category":"Banken",
    "sg:phone":"+31 55 578 4911",
    "sg:postcode":"7325 DP",
    "sg:province":"Gelderland",
    "sg:website":"http://www.rabobank.nl",
    "wof:name":"Rabobank",
    "wof:placetype":"venue"
},
  "geometry": {"coordinates":[6.003281,52.217587],"type":"Point"}
}