{
  "type": "Feature",
  "properties": {
    "addr:full":"Waterviolier 142 Breda North Brabant 4823 MA",
    "addr:housenumber":"142",
    "addr:postcode":"4823 ma",
    "addr:street":"Waterviolier",
    "iso:country":"NL",
    "sg:address":"Waterviolier 142",
    "sg:city":"Breda",
    "sg:orig_category":"Parketvloeren",
    "sg:phone":"+31 76 541 2420",
    "sg:postcode":"4823 MA",
    "sg:province":"North Brabant",
    "wof:name":"Jadeko",
    "wof:placetype":"venue"
},
  "geometry": {"coordinates":[4.728261,51.620113],"type":"Point"}
}