{
  "type": "Feature",
  "properties": {
    "iso:country":"NL",
    "sg:address":"Wilgenpad 2",
    "sg:city":"Ter Aar",
    "sg:orig_category":"Artsen - Huisartsen",
    "sg:phone":"+31 172 602 811",
    "sg:postcode":"2461 DZ",
    "sg:province":"South Holland",
    "wof:name":"Zandstra En M L Jansen, T F",
    "wof:placetype":"venue"
},
  "geometry": {"coordinates":[4.709681,52.167084],"type":"Point"}
}