{
  "type": "Feature",
  "properties": {
    "addr:full":"Wilgenpad 2 Ter Aar South Holland 2461 DZ",
    "addr:housenumber":"2",
    "addr:postcode":"2461 dz",
    "addr:street":"Wilgenpad",
    "iso:country":"NL",
    "sg:address":"Wilgenpad 2",
    "sg:city":"Ter Aar",
    "sg:orig_category":"Artsen - Huisartsen",
    "sg:phone":"+31 172 602 811",
    "sg:postcode":"2461 DZ",
    "sg:province":"South Holland",
    "wof:name":"Zandstra En M L Jansen, T F",
    "wof:placetype":"venue"
},
  "geometry": {"coordinates":[4.709681,52.167084],"type":"Point"}
}