{
  "type": "Feature",
  "properties": {
    "addr:full":"Ravelyn 13 Amersfoort Utrecht 3823 AD",
    "addr:housenumber":"13",
    "addr:postcode":"3823 ad",
    "addr:street":"Ravelyn",
    "iso:country":"NL",
    "sg:address":"Ravelyn 13",
    "sg:city":"Amersfoort",
    "sg:classifiers":[
        {
            "category":"Personal",
            "subcategory":"Nail Salon",
            "type":"Services"
        }
    ],
    "sg:phone":"+31 33 456 2852",
    "sg:postcode":"3823 AD",
    "sg:province":"Utrecht",
    "sg:tags":[
        "pedicure"
    ],
    "wof:name":"Koetsier, Ine",
    "wof:placetype":"venue"
},
  "geometry": {"coordinates":[5.387476,52.18314],"type":"Point"}
}