{
  "type": "Feature",
  "properties": {
    "iso:country":"NL",
    "sg:address":"Zuiderpk 11",
    "sg:city":"Groningen",
    "sg:orig_category":"Architecten En Architectenbureaus",
    "sg:phone":"+31 50 318 2100",
    "sg:postcode":"9724 AE",
    "sg:province":"Groningen",
    "wof:name":"Nederlandse Architecten Regio Noord, Bond Van",
    "wof:placetype":"venue"
},
  "geometry": {"coordinates":[6.573147,53.212414],"type":"Point"}
}