{
  "type": "Feature",
  "properties": {
    "addr:full":"Mathenesserln 467A Rotterdam Zuid-Holland 3023 GK",
    "addr:housenumber":"467a",
    "addr:postcode":"3023 gk",
    "iso:country":"NL",
    "sg:address":"Mathenesserln 467A",
    "sg:city":"Rotterdam",
    "sg:orig_category":"Adviesbureaus Personeel",
    "sg:phone":"+31 10 276 2010",
    "sg:postcode":"3023 GK",
    "sg:province":"Zuid-Holland",
    "wof:name":"Pbn",
    "wof:placetype":"venue"
},
  "geometry": {"coordinates":[4.447599,51.91563],"type":"Point"}
}