{
  "type": "Feature",
  "properties": {
    "iso:country":"NL",
    "sg:address":"Reestr 24",
    "sg:city":"Amsterdam",
    "sg:orig_category":"Boekhandels",
    "sg:phone":"+31 20 489 5985",
    "sg:postcode":"1016 DN",
    "sg:province":"Noord-Holland",
    "wof:name":"Demodokos",
    "wof:placetype":"venue"
},
  "geometry": {"coordinates":[4.88362,52.372528],"type":"Point"}
}