{
  "type": "Feature",
  "properties": {
    "addr:full":"Ganzerikpln 50 Rotterdam Zuid-Holland 3053 EA",
    "addr:housenumber":"50",
    "addr:postcode":"3053 ea",
    "addr:street":"Ganzerikpln",
    "iso:country":"NL",
    "sg:address":"Ganzerikpln 50",
    "sg:city":"Rotterdam",
    "sg:orig_category":"Woningbouw- Verenigingen En -Stichtingen",
    "sg:phone":"+31 10 890 0250",
    "sg:postcode":"3053 EA",
    "sg:province":"Zuid-Holland",
    "sg:website":"http://www.combinatie.nl",
    "wof:name":"Combinatie, De",
    "wof:placetype":"venue"
},
  "geometry": {"coordinates":[4.4712519646,51.9587516785],"type":"Point"}
}