{
  "type": "Feature",
  "properties": {
    "addr:full":"Laanacker 7 Castricum Noord-Holland 1902 AK",
    "addr:housenumber":"7",
    "addr:postcode":"1902 ak",
    "addr:street":"Laanacker",
    "iso:country":"NL",
    "sg:address":"Laanacker 7",
    "sg:city":"Castricum",
    "sg:orig_category":"Onderhoud And Reparatie Kantoorapparatuur",
    "sg:phone":"+31 251 650 310",
    "sg:postcode":"1902 AK",
    "sg:province":"Noord-Holland",
    "wof:name":"Pc - Servoort",
    "wof:placetype":"venue"
},
  "geometry": {"coordinates":[4.672862,52.545372],"type":"Point"}
}