{
  "type": "Feature",
  "properties": {
    "addr:full":"Vormtweg 14 Tollebeek Flevoland 8309 PW",
    "addr:housenumber":"14",
    "addr:postcode":"8309 pw",
    "addr:street":"Vormtweg;Flevoland",
    "iso:country":"NL",
    "sg:address":"Vormtweg 14",
    "sg:city":"Tollebeek",
    "sg:orig_category":"Levende Dieren Gh",
    "sg:phone":"+31 527 684 825",
    "sg:postcode":"8309 PW",
    "sg:province":"Flevoland",
    "wof:name":"A Driesen En Zn",
    "wof:placetype":"venue"
},
  "geometry": {"coordinates":[5.615535,52.681717],"type":"Point"}
}