{
  "type": "Feature",
  "properties": {
    "addr:full":"Schepenstr 96A Rotterdam Zuid-Holland 3039 NN",
    "addr:housenumber":"96a",
    "addr:postcode":"3039 nn",
    "addr:street":"Schepenstr",
    "iso:country":"NL",
    "sg:address":"Schepenstr 96A",
    "sg:city":"Rotterdam",
    "sg:orig_category":"Adviesbureaus",
    "sg:phone":"+31 10 466 3674",
    "sg:postcode":"3039 NN",
    "sg:province":"Zuid-Holland",
    "wof:name":"Gu\u00e9pin",
    "wof:placetype":"venue"
},
  "geometry": {"coordinates":[4.464303,51.927956],"type":"Point"}
}