{
  "type": "Feature",
  "properties": {
    "addr:full":"Antwerpsestr 9 Bergen Op Zoom Noord-Brabant 4611 AA",
    "addr:housenumber":"9",
    "addr:postcode":"4611 aa",
    "addr:street":"Antwerpsestr",
    "iso:country":"NL",
    "sg:address":"Antwerpsestr 9",
    "sg:city":"Bergen Op Zoom",
    "sg:orig_category":"Accountants - Administratie- Consulenten En -Kantoren",
    "sg:phone":"+31 164 250 300",
    "sg:postcode":"4611 AA",
    "sg:province":"Noord-Brabant",
    "wof:name":"Harthoorn Bv, Accountants",
    "wof:placetype":"venue"
},
  "geometry": {"coordinates":[4.288356,51.491886],"type":"Point"}
}