{
  "type": "Feature",
  "properties": {
    "addr:full":"Platinaln 10 S Hertogenbosch Noord-Brabant 5234 GH",
    "addr:housenumber":"10",
    "addr:postcode":"5234 gh",
    "addr:street":"Platinaln;S",
    "iso:country":"NL",
    "sg:address":"Platinaln 10",
    "sg:city":"S Hertogenbosch",
    "sg:orig_category":"Kantoorbenodigdheden - Fabrieken En Groothandel",
    "sg:phone":"+31 73 642 6488",
    "sg:postcode":"5234 GH",
    "sg:province":"Noord-Brabant",
    "wof:name":"Q Systems Bv",
    "wof:placetype":"venue"
},
  "geometry": {"coordinates":[5.287694931,51.7235031128],"type":"Point"}
}