{
  "type": "Feature",
  "properties": {
    "iso:country":"NL",
    "sg:address":"Boulevard Heuvelink 117",
    "sg:city":"Arnhem",
    "sg:orig_category":"Verzekeringen",
    "sg:phone":"+31 26 327 2717",
    "sg:postcode":"6828 KK",
    "sg:province":"Gelderland",
    "wof:name":"Financierings- En Assbedr J Eskes & Zn",
    "wof:placetype":"venue"
},
  "geometry": {"coordinates":[5.919868,51.979637],"type":"Point"}
}