{
  "type": "Feature",
  "properties": {
    "addr:full":"K Kamperstr 6 Zwolle NL.08 8011 MP",
    "addr:housenumber":"6",
    "addr:postcode":"8011 mp",
    "addr:street":"Kamperstr",
    "iso:country":"NL",
    "sg:address":"K Kamperstr 6",
    "sg:city":"Zwolle",
    "sg:orig_category":"Fotoreportages",
    "sg:phone":"+31 38 421 0797",
    "sg:postcode":"8011 MP",
    "sg:province":"NL.08",
    "wof:name":"Eelco Boeijinga",
    "wof:placetype":"venue"
},
  "geometry": {"coordinates":[6.090324,52.511349],"type":"Point"}
}