{
  "type": "Feature",
  "properties": {
    "iso:country":"NL",
    "sg:address":"Holthe 64",
    "sg:city":"Beilen",
    "sg:orig_category":"Banden",
    "sg:phone":"+31 593 527 100",
    "sg:postcode":"9411 TL",
    "sg:province":"Provincie Drenthe",
    "wof:name":"Gils Bandenmontage",
    "wof:placetype":"venue"
},
  "geometry": {"coordinates":[6.541802,52.84269],"type":"Point"}
}