{
  "type": "Feature",
  "properties": {
    "addr:full":"Stationspln 36 Arnhem Gelderland 6811 KK",
    "addr:housenumber":"36",
    "addr:postcode":"6811 kk",
    "addr:street":"Stationspln",
    "iso:country":"NL",
    "sg:address":"Stationspln 36",
    "sg:city":"Arnhem",
    "sg:orig_category":"Fietsen En Bromfietsen Stalling",
    "sg:phone":"+31 26 442 1782",
    "sg:postcode":"6811 KK",
    "sg:province":"Gelderland",
    "wof:name":"Rijwielshop",
    "wof:placetype":"venue"
},
  "geometry": {"coordinates":[5.901133,51.983711],"type":"Point"}
}