{
  "type": "Feature",
  "properties": {
    "addr:full":"Amentstr 17/A Stramproy Limburg 6039 RA",
    "addr:housenumber":"17 / a",
    "addr:postcode":"6039 ra",
    "addr:street":"Amentstr",
    "iso:country":"NL",
    "sg:address":"Amentstr 17/A",
    "sg:city":"Stramproy",
    "sg:orig_category":"Beeldende Kunstenaars",
    "sg:phone":"+31 495 562 938",
    "sg:postcode":"6039 RA",
    "sg:province":"Limburg",
    "wof:name":"Kleef, G J Van",
    "wof:placetype":"venue"
},
  "geometry": {"coordinates":[5.720376,51.201668],"type":"Point"}
}