{
  "type": "Feature",
  "properties": {
    "addr:full":"Sinnigvelderstr 149 Weesp Noord-Holland 1382 ET",
    "addr:housenumber":"149",
    "addr:postcode":"1382 et",
    "iso:country":"NL",
    "sg:address":"Sinnigvelderstr 149",
    "sg:city":"Weesp",
    "sg:orig_category":"Verzekeringen - Verzekeringskantoren",
    "sg:phone":"+31 294 484 847",
    "sg:postcode":"1382 ET",
    "sg:province":"Noord-Holland",
    "wof:name":"Vries, J De",
    "wof:placetype":"venue"
},
  "geometry": {"coordinates":[5.028874,52.311123],"type":"Point"}
}