{
  "type": "Feature",
  "properties": {
    "addr:full":"Burg Conraetzstr 36 Venlo Limburg 5913 BC",
    "addr:housenumber":"36",
    "addr:postcode":"5913 bc",
    "addr:street":"Burg",
    "iso:country":"NL",
    "sg:address":"Burg Conraetzstr 36",
    "sg:city":"Venlo",
    "sg:orig_category":"Boekbinderijen",
    "sg:phone":"+31 77 351 1244",
    "sg:postcode":"5913 BC",
    "sg:province":"Limburg",
    "wof:name":"Henny Den Dekker, Reliure D'Art",
    "wof:placetype":"venue"
},
  "geometry": {"coordinates":[6.178759,51.368145],"type":"Point"}
}