{
  "type": "Feature",
  "properties": {
    "iso:country":"NL",
    "sg:address":"Dommel 32",
    "sg:city":"Gemert",
    "sg:orig_category":"Logerijen",
    "sg:phone":"+31 492 363 325",
    "sg:postcode":"5422 VH",
    "sg:province":"North Brabant",
    "wof:name":"Le Nain",
    "wof:placetype":"venue"
},
  "geometry": {"coordinates":[5.705427,51.562763],"type":"Point"}
}