{
  "type": "Feature",
  "properties": {
    "addr:full":"Zyde 67 Boskoop Zuid-Holland 2771 EK",
    "addr:housenumber":"67",
    "addr:postcode":"2771 ek",
    "addr:street":"Zyde",
    "iso:country":"NL",
    "sg:address":"Zyde 67",
    "sg:city":"Boskoop",
    "sg:orig_category":"Adviesbureaus Personeel",
    "sg:phone":"+31 172 232 181",
    "sg:postcode":"2771 EK",
    "sg:province":"Zuid-Holland",
    "wof:name":"Bma",
    "wof:placetype":"venue"
},
  "geometry": {"coordinates":[4.651309,52.074989],"type":"Point"}
}