{
  "type": "Feature",
  "properties": {
    "addr:full":"Gladiolenstr 10 Zwolle NL.08 8013 ZB",
    "addr:housenumber":"10",
    "addr:postcode":"8013 zb",
    "addr:street":"Gladiolenstr",
    "iso:country":"NL",
    "sg:address":"Gladiolenstr 10",
    "sg:city":"Zwolle",
    "sg:orig_category":"Voetbalverenigingen",
    "sg:phone":"+31 38 421 2487",
    "sg:postcode":"8013 ZB",
    "sg:province":"NL.08",
    "wof:name":"Zwolle Sv",
    "wof:placetype":"venue"
},
  "geometry": {"coordinates":[6.11288,52.503307],"type":"Point"}
}