{
  "type": "Feature",
  "properties": {
    "addr:full":"Industriestraat 10 Dongen North Carolina 5107 NC",
    "addr:housenumber":"10",
    "addr:postcode":"5107 nc",
    "addr:street":"Industriestraat",
    "iso:country":"NL",
    "sg:address":"Industriestraat 10",
    "sg:city":"Dongen",
    "sg:orig_category":"Meubelzaken, Woning- And Keukeninrichting",
    "sg:phone":"+31 162 319 201",
    "sg:postcode":"5107 NC",
    "sg:province":"North Carolina",
    "wof:name":"Pacific Waterbeds Bv",
    "wof:placetype":"venue"
},
  "geometry": {"coordinates":[-80.018333,35.21941],"type":"Point"}
}