{
  "type": "Feature",
  "properties": {
    "addr:full":"Zaailand 141 Leeuwarden Friesland 8911 BL",
    "addr:housenumber":"141",
    "addr:postcode":"8911 bl",
    "addr:street":"Zaailand",
    "iso:country":"NL",
    "sg:address":"Zaailand 141",
    "sg:city":"Leeuwarden",
    "sg:orig_category":"Herenmodezaken",
    "sg:phone":"+31 58 213 8895",
    "sg:postcode":"8911 BL",
    "sg:province":"Friesland",
    "wof:name":"Flex",
    "wof:placetype":"venue"
},
  "geometry": {"coordinates":[5.795284,53.199375],"type":"Point"}
}