{
  "type": "Feature",
  "properties": {
    "addr:full":"Zeesluiswg 90 X S Gravenhage Zuid-Holland 2583 DS",
    "addr:housenumber":"90 x",
    "addr:postcode":"2583 ds",
    "addr:street":"Zeesluiswg",
    "iso:country":"NL",
    "sg:address":"Zeesluiswg 90 X",
    "sg:city":"S Gravenhage",
    "sg:classifiers":[
        {
            "category":"Personal",
            "subcategory":"Nail Salon",
            "type":"Services"
        }
    ],
    "sg:phone":"+31 70 354 7752",
    "sg:postcode":"2583 DS",
    "sg:province":"Zuid-Holland",
    "sg:tags":[
        "pedicure"
    ],
    "wof:name":"Jol-Van Duijn, D",
    "wof:placetype":"venue"
},
  "geometry": {"coordinates":[4.25526,52.09124],"type":"Point"}
}