{
  "type": "Feature",
  "properties": {
    "addr:full":"Beestenmarkt 2 Leiden Zuid-Holland 2312 CC",
    "addr:housenumber":"2",
    "addr:postcode":"2312 cc",
    "addr:street":"Beestenmarkt",
    "iso:country":"NL",
    "sg:address":"Beestenmarkt 2",
    "sg:city":"Leiden",
    "sg:classifiers":[
        {
            "category":"Travel",
            "subcategory":"Hotels & Motels",
            "type":"Entertainment"
        }
    ],
    "sg:phone":"+31 71 514 2641",
    "sg:postcode":"2312 CC",
    "sg:province":"Zuid-Holland",
    "wof:name":"May Flower",
    "wof:placetype":"venue"
},
  "geometry": {"coordinates":[4.484812,52.162994],"type":"Point"}
}