{
  "type": "Feature",
  "properties": {
    "iso:country":"NL",
    "sg:address":"Aabeekstraat 43",
    "sg:city":"Goirle",
    "sg:orig_category":"Elektronische Bedrijfsinstallaties",
    "sg:phone":"+31 13 534 1179",
    "sg:postcode":"5051 VN",
    "sg:province":"North Brabant",
    "wof:name":"Recherche En Onderzoekenbureau M.O.",
    "wof:placetype":"venue"
},
  "geometry": {"coordinates":[5.073459,51.521816],"type":"Point"}
}