{
  "type": "Feature",
  "properties": {
    "addr:full":"R Holstln 888 Delft Zuid-Holland 2624 JJ",
    "addr:housenumber":"888",
    "addr:postcode":"delft;2624 jj",
    "iso:country":"NL",
    "sg:address":"R Holstln 888",
    "sg:city":"Delft",
    "sg:classifiers":[
        {
            "category":"Education",
            "subcategory":"Special Training",
            "type":"Public Place"
        }
    ],
    "sg:phone":"+31 15 257 8381",
    "sg:postcode":"2624 JJ",
    "sg:province":"Zuid-Holland",
    "sg:tags":[
        "expertise"
    ],
    "wof:name":"Karsen Bv, W M Van",
    "wof:placetype":"venue"
},
  "geometry": {"coordinates":[4.35634,51.995491],"type":"Point"}
}