{
  "type": "Feature",
  "properties": {
    "iso:country":"NL",
    "sg:address":"Zwolseweg 50",
    "sg:city":"'S Heerenbroek",
    "sg:orig_category":"Benzinestations And Brandstoffen",
    "sg:phone":"+31 38 355 7659",
    "sg:postcode":"8275 AA",
    "sg:province":"Overijssel",
    "wof:name":"Brand Oil Bv",
    "wof:placetype":"venue"
},
  "geometry": {"coordinates":[6.004274,52.535984],"type":"Point"}
}