{
  "type": "Feature",
  "properties": {
    "addr:full":"Koningin Wilhelminakade 259 Ijmuiden Noord-Holland 1975 GL",
    "addr:housenumber":"259",
    "addr:postcode":"1975 gl",
    "addr:street":"Koningin Wilhelminakade",
    "iso:country":"NL",
    "sg:address":"Koningin Wilhelminakade 259",
    "sg:city":"Ijmuiden",
    "sg:orig_category":"Metaalwerken",
    "sg:phone":"+31 255 517 767",
    "sg:postcode":"1975 GL",
    "sg:province":"Noord-Holland",
    "wof:name":"Ron Visser Montage",
    "wof:placetype":"venue"
},
  "geometry": {"coordinates":[4.603778,52.462524],"type":"Point"}
}