{
  "type": "Feature",
  "properties": {
    "addr:full":"Verl Spoorln 20 Veenendaal Utrecht 3904 MB",
    "addr:housenumber":"20",
    "addr:postcode":"3904 mb",
    "iso:country":"NL",
    "sg:address":"Verl Spoorln 20",
    "sg:city":"Veenendaal",
    "sg:orig_category":"Bedrijfshuisvesting",
    "sg:phone":"+31 318 589 904",
    "sg:postcode":"3904 MB",
    "sg:province":"Utrecht",
    "wof:name":"Accomconsult",
    "wof:placetype":"venue"
},
  "geometry": {"coordinates":[5.55418,52.024902],"type":"Point"}
}