{
  "type": "Feature",
  "properties": {
    "addr:full":"Gildestr 1B Heerhugowaard North Holland 1704 AG",
    "addr:housenumber":"1b",
    "addr:postcode":"1704",
    "addr:street":"Gildestr",
    "iso:country":"NL",
    "sg:address":"Gildestr 1B",
    "sg:city":"Heerhugowaard",
    "sg:orig_category":"Loopbaanbegeleiding",
    "sg:phone":"+31 72 571 8283",
    "sg:postcode":"1704 AG",
    "sg:province":"North Holland",
    "sg:website":"http://www.faktor2.nl",
    "wof:name":"Faktor 2",
    "wof:placetype":"venue"
},
  "geometry": {"coordinates":[4.818344,52.668484],"type":"Point"}
}