{
  "type": "Feature",
  "properties": {
    "addr:full":"Molenstr 21 Swolgen Limburg 5866 AA",
    "addr:housenumber":"21",
    "addr:postcode":"5866 aa",
    "addr:street":"Molenstr",
    "iso:country":"NL",
    "sg:address":"Molenstr 21",
    "sg:city":"Swolgen",
    "sg:orig_category":"Kunststof Ramen",
    "sg:phone":"+31 478 691 259",
    "sg:postcode":"5866 AA",
    "sg:province":"Limburg",
    "wof:name":"Jacobs, P G M",
    "wof:placetype":"venue"
},
  "geometry": {"coordinates":[6.113714,51.49231],"type":"Point"}
}