{
  "type": "Feature",
  "properties": {
    "iso:country":"NL",
    "sg:address":"Oosterhuiswg 1",
    "sg:city":"Makkinga",
    "sg:classifiers":[
        {
            "category":"Personal",
            "subcategory":"Nail Salon",
            "type":"Services"
        }
    ],
    "sg:phone":"+31 516 441 767",
    "sg:postcode":"8423 TG",
    "sg:province":"Provincie Friesland",
    "sg:tags":[
        "pedicure"
    ],
    "wof:name":"Vries, Agnes De",
    "wof:placetype":"venue"
},
  "geometry": {"coordinates":[6.218168,52.980808],"type":"Point"}
}