{
  "type": "Feature",
  "properties": {
    "addr:full":"Bosln 1 Bilthoven Utrecht 3722 BA",
    "addr:housenumber":"1",
    "addr:postcode":"3722 ba",
    "addr:street":"Bosln",
    "iso:country":"NL",
    "sg:address":"Bosln 1",
    "sg:city":"Bilthoven",
    "sg:orig_category":"Verenigingen En Stichtingen",
    "sg:phone":"+31 30 228 4593",
    "sg:postcode":"3722 BA",
    "sg:province":"Utrecht",
    "wof:name":"Vogelnest, 'T",
    "wof:placetype":"venue"
},
  "geometry": {"coordinates":[5.21093,52.121498],"type":"Point"}
}