{
  "type": "Feature",
  "properties": {
    "addr:full":"Duifstr 38 Utrecht Utrecht 3514 ER",
    "addr:housenumber":"38",
    "addr:postcode":"3514 er",
    "addr:street":"Duifstr",
    "iso:country":"NL",
    "sg:address":"Duifstr 38",
    "sg:city":"Utrecht",
    "sg:orig_category":"Grafisch Ontwerpers",
    "sg:phone":"+31 30 271 0064",
    "sg:postcode":"3514 ER",
    "sg:province":"Utrecht",
    "wof:name":"2 Pk Prod",
    "wof:placetype":"venue"
},
  "geometry": {"coordinates":[5.119011,52.097729],"type":"Point"}
}