{
  "type": "Feature",
  "properties": {
    "addr:full":"Kerkstr 20 Loon Op Zand Noord-Brabant 5175 BB",
    "addr:housenumber":"20",
    "addr:postcode":"5175 bb",
    "addr:street":"Kerkstr",
    "iso:country":"NL",
    "sg:address":"Kerkstr 20",
    "sg:city":"Loon Op Zand",
    "sg:orig_category":"Houtbewerking",
    "sg:phone":"+31 416 364 455",
    "sg:postcode":"5175 BB",
    "sg:province":"Noord-Brabant",
    "sg:website":"http://www-d-j-t.nl",
    "wof:name":"Jong Vof, De",
    "wof:placetype":"venue"
},
  "geometry": {"coordinates":[5.076348,51.627399],"type":"Point"}
}