{
  "type": "Feature",
  "properties": {
    "iso:country":"NL",
    "sg:address":"Lotusbloemwg 86",
    "sg:city":"Almere",
    "sg:orig_category":"Autorijscholen",
    "sg:phone":"+31 36 532 4699",
    "sg:postcode":"1338 ZD",
    "sg:province":"Flevoland",
    "sg:website":"http://www.rijschool-alfa.com",
    "wof:name":"Alfa",
    "wof:placetype":"venue"
},
  "geometry": {"coordinates":[5.287656,52.387394],"type":"Point"}
}