{
  "type": "Feature",
  "properties": {
    "addr:full":"Rembrandtln 22 Loosdrecht Noord-Holland 1231 AC",
    "addr:housenumber":"22",
    "addr:postcode":"1231 ac",
    "addr:street":"Rembrandtln",
    "iso:country":"NL",
    "sg:address":"Rembrandtln 22",
    "sg:city":"Loosdrecht",
    "sg:orig_category":"Zonnebank- En Solariumcentra",
    "sg:phone":"+31 35 582 4180",
    "sg:postcode":"1231 AC",
    "sg:province":"Noord-Holland",
    "wof:name":"Bree, Liesbeth De",
    "wof:placetype":"venue"
},
  "geometry": {"coordinates":[5.1319,52.205402],"type":"Point"}
}