{
  "type": "Feature",
  "properties": {
    "iso:country":"NL",
    "sg:address":"Plein 1940 20",
    "sg:city":"Middelburg",
    "sg:orig_category":"Herenkleding",
    "sg:phone":"+31 118 612 508",
    "sg:postcode":"4331 LH",
    "sg:province":"Zeeland",
    "sg:website":"http://lavooy.com/mode",
    "wof:name":"Lavooy",
    "wof:placetype":"venue"
},
  "geometry": {"coordinates":[3.610403,51.497562],"type":"Point"}
}