{
  "type": "Feature",
  "properties": {
    "addr:full":"M Polorede 29 Zoetermeer South Holland 2725 KS",
    "addr:housenumber":"29",
    "addr:postcode":"2725 ks",
    "addr:street":"M Polorede",
    "iso:country":"NL",
    "sg:address":"M Polorede 29",
    "sg:city":"Zoetermeer",
    "sg:orig_category":"Vertaalbureaus",
    "sg:phone":"+31 79 346 0447",
    "sg:postcode":"2725 KS",
    "sg:province":"South Holland",
    "sg:website":"http://www.helena.nl",
    "wof:name":"Helena Bv",
    "wof:placetype":"venue"
},
  "geometry": {"coordinates":[4.500878,52.078117],"type":"Point"}
}