{
  "type": "Feature",
  "properties": {
    "addr:full":"E Rooseveltln 139 Amstelveen North Holland 1183 CG",
    "addr:housenumber":"139",
    "addr:postcode":"1183 cg",
    "iso:country":"NL",
    "sg:address":"E Rooseveltln 139",
    "sg:city":"Amstelveen",
    "sg:orig_category":"Autorijscholen",
    "sg:phone":"+31 20 647 2868",
    "sg:postcode":"1183 CG",
    "sg:province":"North Holland",
    "wof:name":"Lith, J G",
    "wof:placetype":"venue"
},
  "geometry": {"coordinates":[4.87272,52.314541],"type":"Point"}
}