{
  "type": "Feature",
  "properties": {
    "iso:country":"NL",
    "sg:address":"Miggelenbergwg 56",
    "sg:city":"Hoenderloo",
    "sg:orig_category":"Discotheken",
    "sg:phone":"+31 55 378 2182",
    "sg:postcode":"7351 BP",
    "sg:province":"Gelderland",
    "wof:name":"Gate Discotheek, The",
    "wof:placetype":"venue"
},
  "geometry": {"coordinates":[5.902841,52.127399],"type":"Point"}
}