{
  "type": "Feature",
  "properties": {
    "iso:country":"NL",
    "sg:address":"Bomansplaats 3",
    "sg:city":"Eindhoven",
    "sg:orig_category":"Vakorganisaties",
    "sg:phone":"+31 40 211 6674",
    "sg:postcode":"5611 NT",
    "sg:province":"North Brabant",
    "wof:name":"Cnv",
    "wof:placetype":"venue"
},
  "geometry": {"coordinates":[5.484039,51.431019],"type":"Point"}
}