{
  "type": "Feature",
  "properties": {
    "addr:full":"Zevenhuizerwg 51 Eelde Provincie Drenthe 9761 AD",
    "addr:housenumber":"51",
    "addr:postcode":"9761 ad",
    "addr:street":"Zevenhuizerwg;Provincie Drenthe",
    "iso:country":"NL",
    "sg:address":"Zevenhuizerwg 51",
    "sg:city":"Eelde",
    "sg:orig_category":"Onderhoudswerken",
    "sg:phone":"+31 50 309 3425",
    "sg:postcode":"9761 AD",
    "sg:province":"Provincie Drenthe",
    "wof:name":"Steunebrink",
    "wof:placetype":"venue"
},
  "geometry": {"coordinates":[6.570907,53.139351],"type":"Point"}
}