{
  "type": "Feature",
  "properties": {
    "iso:country":"NL",
    "sg:address":"Drouwenerstraat 10",
    "sg:city":"Borger",
    "sg:orig_category":"Glaszetten",
    "sg:phone":"+31 599 235 536",
    "sg:postcode":"9531 JZ",
    "sg:province":"Drenthe",
    "wof:name":"Siepel Isolatiewerken",
    "wof:placetype":"venue"
},
  "geometry": {"coordinates":[6.789993,52.928707],"type":"Point"}
}