{
  "type": "Feature",
  "properties": {
    "iso:country":"NL",
    "sg:address":"Weeshuisstr 31",
    "sg:city":"Coevorden",
    "sg:orig_category":"Amusementshallen",
    "sg:phone":"+31 524 517 273",
    "sg:postcode":"7741 GP",
    "sg:province":"Drenthe",
    "wof:name":"Playland Bv",
    "wof:placetype":"venue"
},
  "geometry": {"coordinates":[6.739304,52.662632],"type":"Point"}
}