{
  "type": "Feature",
  "properties": {
    "addr:full":"Markt 48 Delft Zuid-Holland 2611 GV",
    "addr:housenumber":"48",
    "addr:postcode":"2611 gv",
    "addr:street":"Markt",
    "iso:country":"NL",
    "sg:address":"Markt 48",
    "sg:city":"Delft",
    "sg:classifiers":[
        {
            "category":"Shopping",
            "subcategory":"Gifts & Souvenirs",
            "type":"Retail Goods"
        }
    ],
    "sg:phone":"+31 15 212 3165",
    "sg:postcode":"2611 GV",
    "sg:province":"Zuid-Holland",
    "sg:tags":[
        "geschenken"
    ],
    "wof:name":"Holland House",
    "wof:placetype":"venue"
},
  "geometry": {"coordinates":[4.358759,52.011826],"type":"Point"}
}