{
  "type": "Feature",
  "properties": {
    "addr:full":"Oudendk 83 Stryen Zuid-Holland 3291 LM",
    "addr:housenumber":"83",
    "addr:postcode":"3291 lm",
    "addr:street":"Oudendk",
    "iso:country":"NL",
    "sg:address":"Oudendk 83",
    "sg:city":"Stryen",
    "sg:orig_category":"Machinehandel",
    "sg:phone":"+31 186 575 262",
    "sg:postcode":"3291 LM",
    "sg:province":"Zuid-Holland",
    "wof:name":"Uijterlinde, M",
    "wof:placetype":"venue"
},
  "geometry": {"coordinates":[4.54727,51.750832],"type":"Point"}
}