{
  "type": "Feature",
  "properties": {
    "addr:full":"Dr Martin Luther Kingstr 91 Landsmeer North Holland 1121 CS",
    "addr:housenumber":"91",
    "addr:postcode":"1121 cs",
    "iso:country":"NL",
    "sg:address":"Dr Martin Luther Kingstr 91",
    "sg:city":"Landsmeer",
    "sg:orig_category":"Schilderwerk",
    "sg:phone":"+31 20 482 5006",
    "sg:postcode":"1121 CS",
    "sg:province":"North Holland",
    "wof:name":"R. Joling Schildersbedrijf",
    "wof:placetype":"venue"
},
  "geometry": {"coordinates":[4.917531,52.427284],"type":"Point"}
}