{
  "type": "Feature",
  "properties": {
    "addr:full":"Hertogstraat 9 Arnhem Gelderland 6828 ER",
    "addr:housenumber":"9",
    "addr:postcode":"6828 er",
    "addr:street":"Hertogstraat",
    "iso:country":"NL",
    "sg:address":"Hertogstraat 9",
    "sg:city":"Arnhem",
    "sg:orig_category":"Boekhouders",
    "sg:phone":"+31 26 443 9552",
    "sg:postcode":"6828 ER",
    "sg:province":"Gelderland",
    "wof:name":"Adm. En Belastingadvieskantoor Tychon",
    "wof:placetype":"venue"
},
  "geometry": {"coordinates":[5.92128,51.984444],"type":"Point"}
}