{
  "type": "Feature",
  "properties": {
    "addr:full":"Havenstr 19-21 Rotterdam South Holland 3024 SG",
    "addr:housenumber":"19-21",
    "addr:postcode":"3024 sg",
    "iso:country":"NL",
    "sg:address":"Havenstr 19-21",
    "sg:city":"Rotterdam",
    "sg:orig_category":"Verf En Lak",
    "sg:phone":"+31 10 476 3088",
    "sg:postcode":"3024 SG",
    "sg:province":"South Holland",
    "sg:website":"http://www.kroonpart.nl",
    "wof:name":"Kroonpart, De Vakman Vlakbij",
    "wof:placetype":"venue"
},
  "geometry": {"coordinates":[4.44939,51.909088],"type":"Point"}
}