{
  "type": "Feature",
  "properties": {
    "addr:full":"Broeksloot 21 Zegveld Utrecht 3474 HS",
    "addr:housenumber":"21",
    "addr:postcode":"3474 hs",
    "addr:street":"Broeksloot",
    "iso:country":"NL",
    "sg:address":"Broeksloot 21",
    "sg:city":"Zegveld",
    "sg:orig_category":"Grafisch Ontwerpers",
    "sg:phone":"+31 348 691 484",
    "sg:postcode":"3474 HS",
    "sg:province":"Utrecht",
    "wof:name":"Trea Hoogeveen",
    "wof:placetype":"venue"
},
  "geometry": {"coordinates":[4.836913,52.117416],"type":"Point"}
}