{
  "type": "Feature",
  "properties": {
    "addr:full":"Dorpsstraat 84 Bleiswijk Zuid-Holland 2665 BK",
    "addr:housenumber":"84",
    "addr:postcode":"2665 bk",
    "addr:street":"Dorpsstraat",
    "iso:country":"NL",
    "sg:address":"Dorpsstraat 84",
    "sg:city":"Bleiswijk",
    "sg:orig_category":"Banken And Kredietinstellingen",
    "sg:phone":"+31 10 521 2284",
    "sg:postcode":"2665 BK",
    "sg:province":"Zuid-Holland",
    "wof:name":"Postkantoor",
    "wof:placetype":"venue"
},
  "geometry": {"coordinates":[4.530473,52.011715],"type":"Point"}
}