{
  "type": "Feature",
  "properties": {
    "iso:country":"NL",
    "sg:address":"Kikkerstraat 14",
    "sg:city":"'S Gravenhage",
    "sg:orig_category":"Fietshandelaren",
    "sg:phone":"+31 70 389 0784",
    "sg:postcode":"2515 NB",
    "sg:province":"Zuid-Holland",
    "wof:name":"Tweewielershop L.M. Van Zijl",
    "wof:placetype":"venue"
},
  "geometry": {"coordinates":[4.319037,52.074081],"type":"Point"}
}