{
  "type": "Feature",
  "properties": {
    "iso:country":"NL",
    "sg:address":"Kempenaar 72",
    "sg:city":"Barendrecht",
    "sg:orig_category":"Benzine En Olie - Groothandel",
    "sg:phone":"+31 180 616 159",
    "sg:postcode":"2991 PJ",
    "sg:province":"Zuid-Holland",
    "wof:name":"Joore Bv",
    "wof:placetype":"venue"
},
  "geometry": {"coordinates":[4.537452,51.848278],"type":"Point"}
}