{
  "type": "Feature",
  "properties": {
    "addr:full":"Kapelstraat 30 Maasbommel Gelderland 6627 AW",
    "addr:housenumber":"30",
    "addr:postcode":"6627 aw",
    "addr:street":"Kapelstraat;Gelderland",
    "iso:country":"NL",
    "sg:address":"Kapelstraat 30",
    "sg:city":"Maasbommel",
    "sg:orig_category":"Meubelzaken, Woning- And Keukeninrichting",
    "sg:phone":"+31 487 562 484",
    "sg:postcode":"6627 AW",
    "sg:province":"Gelderland",
    "wof:name":"Van Gelder Meubelen",
    "wof:placetype":"venue"
},
  "geometry": {"coordinates":[5.532223,51.823994],"type":"Point"}
}