{
  "type": "Feature",
  "properties": {
    "iso:country":"NL",
    "sg:address":"Manaupln 10-12",
    "sg:city":"Noordwolde Fr",
    "sg:orig_category":"Hengelsportartikelen",
    "sg:phone":"+31 561 432 943",
    "sg:postcode":"8391 BZ",
    "sg:province":"Provincie Friesland",
    "wof:name":"Tiede",
    "wof:placetype":"venue"
},
  "geometry": {"coordinates":[6.140909,52.891003],"type":"Point"}
}