{
  "type": "Feature",
  "properties": {
    "addr:full":"A Fokkersngl 13 S Gravenhage 2497 BJ",
    "addr:housenumber":"13",
    "addr:postcode":"2497 bj",
    "addr:street":"S Gravenhage",
    "iso:country":"NL",
    "sg:address":"A Fokkersngl 13",
    "sg:city":"S Gravenhage",
    "sg:orig_category":"Kantoor- En Secretariaatsservice",
    "sg:phone":"+31 70 414 0654",
    "sg:postcode":"2497 BJ",
    "sg:website":"http://www.secretariaatservice-haaglanden.nl",
    "wof:name":"Secretariaatservice Haaglanden",
    "wof:placetype":"venue"
},
  "geometry": {"coordinates":[4.3660202026,52.0359115601],"type":"Point"}
}