{
  "type": "Feature",
  "properties": {
    "addr:full":"Livingstonelaan 40 Gouda Zuid-Holland 2803 EL",
    "addr:housenumber":"40;2803",
    "addr:postcode":"el",
    "addr:street":"Livingstonelaan",
    "iso:country":"NL",
    "sg:address":"Livingstonelaan 40",
    "sg:city":"Gouda",
    "sg:orig_category":"Artiesten",
    "sg:phone":"+31 182 539 298",
    "sg:postcode":"2803 EL",
    "sg:province":"Zuid-Holland",
    "wof:name":"I.C.K. Zandstra",
    "wof:placetype":"venue"
},
  "geometry": {"coordinates":[4.705746,52.023682],"type":"Point"}
}