{
  "type": "Feature",
  "properties": {
    "addr:full":"Steenweg 43 Utrecht Utrecht 3511 JM",
    "addr:housenumber":"43",
    "addr:postcode":"3511 jm",
    "addr:street":"Steenweg",
    "iso:country":"NL",
    "sg:address":"Steenweg 43",
    "sg:city":"Utrecht",
    "sg:orig_category":"Juweliers",
    "sg:phone":"+31 30 231 6361",
    "sg:postcode":"3511 JM",
    "sg:province":"Utrecht",
    "wof:name":"Van Dijk Juweliers Utrecht Bv",
    "wof:placetype":"venue"
},
  "geometry": {"coordinates":[5.117917,52.090912],"type":"Point"}
}