{
  "type": "Feature",
  "properties": {
    "addr:full":"Laan Van De Iemenhees 532 Emmen Drenthe 7823 JW",
    "addr:housenumber":"532",
    "addr:postcode":"7823 jw",
    "addr:street":"Laan Van De Iemenhees",
    "iso:country":"NL",
    "sg:address":"Laan Van De Iemenhees 532",
    "sg:city":"Emmen",
    "sg:orig_category":"Beautyfarms And Sauna'S",
    "sg:phone":"+31 591 629 404",
    "sg:postcode":"7823 JW",
    "sg:province":"Drenthe",
    "wof:name":"F. V.D. Heide",
    "wof:placetype":"venue"
},
  "geometry": {"coordinates":[6.946193,52.786766],"type":"Point"}
}