{
  "type": "Feature",
  "properties": {
    "addr:full":"Linnaeusstr 31 Utrecht Utrecht 3553 CC",
    "addr:housenumber":"31",
    "addr:postcode":"3553 cc",
    "addr:street":"Linnaeusstr",
    "iso:country":"NL",
    "sg:address":"Linnaeusstr 31",
    "sg:city":"Utrecht",
    "sg:orig_category":"Lasbedrijven",
    "sg:phone":"+31 30 242 1681",
    "sg:postcode":"3553 CC",
    "sg:province":"Utrecht",
    "wof:name":"Michel Kurtz Lasbedrijf",
    "wof:placetype":"venue"
},
  "geometry": {"coordinates":[5.086594,52.111107],"type":"Point"}
}