{
  "type": "Feature",
  "properties": {
    "addr:full":"Spaarnewg 12G Cruquius Noord-Holland 2142 EN",
    "addr:housenumber":"12g",
    "addr:postcode":"2142 en",
    "addr:street":"Spaarnewg",
    "iso:country":"NL",
    "sg:address":"Spaarnewg 12G",
    "sg:city":"Cruquius",
    "sg:orig_category":"Verhuizingen",
    "sg:phone":"+31 23 563 0939",
    "sg:postcode":"2142 EN",
    "sg:province":"Noord-Holland",
    "sg:website":"http://www.wesselingverhuizers.nl",
    "wof:name":"Wesseling Verhuizers",
    "wof:placetype":"venue"
},
  "geometry": {"coordinates":[4.633244,52.334549],"type":"Point"}
}