{
  "type": "Feature",
  "properties": {
    "addr:full":"Postelstr 45 Someren Noord-Brabant 5711 EM",
    "addr:housenumber":"45",
    "addr:postcode":"5711 em",
    "addr:street":"Postelstr",
    "iso:country":"NL",
    "sg:address":"Postelstr 45",
    "sg:city":"Someren",
    "sg:orig_category":"Wasserijen",
    "sg:phone":"+31 493 490 109",
    "sg:postcode":"5711 EM",
    "sg:province":"Noord-Brabant",
    "wof:name":"Dentex Wasserij",
    "wof:placetype":"venue"
},
  "geometry": {"coordinates":[5.7112498283,51.3827438354],"type":"Point"}
}