{
  "type": "Feature",
  "properties": {
    "iso:country":"NL",
    "sg:address":"Ncb Ln 21",
    "sg:city":"Veghel",
    "sg:orig_category":"Medische Installaties En Instrumenten - Fabrieken",
    "sg:phone":"+31 413 362 804",
    "sg:postcode":"5462 GA",
    "sg:province":"North Brabant",
    "wof:name":"Renja",
    "wof:placetype":"venue"
},
  "geometry": {"coordinates":[5.528348,51.61729],"type":"Point"}
}