{
  "type": "Feature",
  "properties": {
    "addr:full":"Wilhelminaplantsoen 120 Diemen North Holland 1111 CP",
    "addr:housenumber":"120",
    "addr:postcode":"1111 cp",
    "addr:street":"Wilhelminaplantsoen",
    "iso:country":"NL",
    "sg:address":"Wilhelminaplantsoen 120",
    "sg:city":"Diemen",
    "sg:orig_category":"Banken And Kredietinstellingen",
    "sg:phone":"+31 20 777 8899",
    "sg:postcode":"1111 CP",
    "sg:province":"North Holland",
    "wof:name":"Rabobank",
    "wof:placetype":"venue"
},
  "geometry": {"coordinates":[4.96216,52.341228],"type":"Point"}
}