{
  "type": "Feature",
  "properties": {
    "addr:full":"Maria Stuartstraat 34 Eindhoven North Brabant 5616 AM",
    "addr:housenumber":"34",
    "addr:postcode":"5616",
    "addr:street":"Maria Stuartstraat",
    "iso:country":"NL",
    "sg:address":"Maria Stuartstraat 34",
    "sg:city":"Eindhoven",
    "sg:orig_category":"Binnenhuisarchitecten",
    "sg:phone":"+31 40 236 6501",
    "sg:postcode":"5616 AM",
    "sg:province":"North Brabant",
    "wof:name":"Blanc",
    "wof:placetype":"venue"
},
  "geometry": {"coordinates":[5.468298,51.43515],"type":"Point"}
}