{
  "type": "Feature",
  "properties": {
    "addr:full":"Croeseln 229 Utrecht Utrecht 3521 BP",
    "addr:housenumber":"229",
    "addr:postcode":"3521 bp",
    "iso:country":"NL",
    "sg:address":"Croeseln 229",
    "sg:city":"Utrecht",
    "sg:orig_category":"Kunstgebitten",
    "sg:phone":"+31 30 290 0707",
    "sg:postcode":"3521 BP",
    "sg:province":"Utrecht",
    "wof:name":"Rijn Tandprothetiek, Van",
    "wof:placetype":"venue"
},
  "geometry": {"coordinates":[5.11037,52.084572],"type":"Point"}
}