{
  "type": "Feature",
  "properties": {
    "addr:full":"Rijnstraat 226 'S Hertogenbosch North Brabant 5215 EP",
    "addr:housenumber":"226 ' s",
    "addr:postcode":"5215 ep",
    "addr:street":"Rijnstraat;Hertogenbosch",
    "iso:country":"NL",
    "sg:address":"Rijnstraat 226",
    "sg:city":"'S Hertogenbosch",
    "sg:classifiers":[
        {
            "category":"Fast Food",
            "type":"Food & Drink"
        }
    ],
    "sg:phone":"+31 73 613 0629",
    "sg:postcode":"5215 EP",
    "sg:province":"North Brabant",
    "sg:tags":[
        "afhaal",
        "restaurant"
    ],
    "wof:name":"Chinees-Indisch Restaurant Fine Food",
    "wof:placetype":"venue"
},
  "geometry": {"coordinates":[5.335714,51.690475],"type":"Point"}
}