{
  "type": "Feature",
  "properties": {
    "addr:full":"Vaartweg Hilversum Noord-Holland 1211 JH",
    "addr:housenumber":"hilversum",
    "addr:postcode":"1211 jh",
    "addr:street":"Vaartweg",
    "iso:country":"NL",
    "sg:address":"Vaartweg",
    "sg:city":"Hilversum",
    "sg:orig_category":"Overheidsdiensten",
    "sg:phone":"+31 35 628 4858",
    "sg:postcode":"1211 JH",
    "sg:province":"Noord-Holland",
    "wof:name":"Vereninging Club 14-16",
    "wof:placetype":"venue"
},
  "geometry": {"coordinates":[5.1650791168,52.2225036621],"type":"Point"}
}