{
  "type": "Feature",
  "properties": {
    "addr:full":"Groningerstrwg 17 Grijpskerk Groningen 9843 AA",
    "addr:housenumber":"17",
    "addr:postcode":"9843 aa",
    "addr:street":"Groningerstrwg",
    "iso:country":"NL",
    "sg:address":"Groningerstrwg 17",
    "sg:city":"Grijpskerk",
    "sg:orig_category":"Artsen - Huisartsen",
    "sg:phone":"+31 594 213 600",
    "sg:postcode":"9843 AA",
    "sg:province":"Groningen",
    "wof:name":"Rademaker, P L I",
    "wof:placetype":"venue"
},
  "geometry": {"coordinates":[6.313955,53.263794],"type":"Point"}
}