{
  "type": "Feature",
  "properties": {
    "iso:country":"NL",
    "sg:address":"Koestraat 1",
    "sg:city":"Hooge Mierde",
    "sg:classifiers":[
        {
            "category":"Professional",
            "subcategory":"Accounting & Tax Preparation",
            "type":"Services"
        }
    ],
    "sg:phone":"+31 13 509 2540",
    "sg:postcode":"5095 BD",
    "sg:province":"North Brabant",
    "sg:tags":[
        "accountant"
    ],
    "wof:name":"Accountantskantoor Corsten Bv",
    "wof:placetype":"venue"
},
  "geometry": {"coordinates":[5.132333,51.398567],"type":"Point"}
}