{
  "type": "Feature",
  "properties": {
    "addr:full":"Steenbakkerswg 3 Erm New Jersey 7843 RM",
    "addr:housenumber":"3",
    "addr:postcode":"7843 rm",
    "addr:street":"Steenbakkerswg",
    "iso:country":"NL",
    "sg:address":"Steenbakkerswg 3",
    "sg:city":"Erm",
    "sg:orig_category":"Zoetwaren - Fabrieken En Groothandel",
    "sg:phone":"+31 591 564 217",
    "sg:postcode":"7843 RM",
    "sg:province":"New Jersey",
    "wof:name":"Sprinkle Bv",
    "wof:placetype":"venue"
},
  "geometry": {"coordinates":[-74.90799,38.980587],"type":"Point"}
}