{
  "type": "Feature",
  "properties": {
    "addr:full":"Hanzestraat 33 Arnhem Gelderland 6826 ME",
    "addr:housenumber":"33",
    "addr:postcode":"6826 me",
    "addr:street":"Hanzestraat",
    "iso:country":"NL",
    "sg:address":"Hanzestraat 33",
    "sg:city":"Arnhem",
    "sg:orig_category":"Huishoudapparatuur, Televisies And Radio'S",
    "sg:phone":"+31 26 364 2785",
    "sg:postcode":"6826 ME",
    "sg:province":"Gelderland",
    "wof:name":"Verlichting Besselink Licht Elektro",
    "wof:placetype":"venue"
},
  "geometry": {"coordinates":[5.949324,51.982822],"type":"Point"}
}