{
  "type": "Feature",
  "properties": {
    "iso:country":"NL",
    "sg:address":"Ambachtswg 5",
    "sg:city":"Pynacker",
    "sg:classifiers":[
        {
            "category":"Retail",
            "subcategory":"Auto Repair",
            "type":"Services"
        }
    ],
    "sg:phone":"+31 15 369 8044",
    "sg:postcode":"2641 KS",
    "sg:province":"Zuid-Holland",
    "sg:tags":[
        "garage"
    ],
    "sg:website":"http://www.kevershop.nl",
    "wof:name":"Keverland",
    "wof:placetype":"venue"
},
  "geometry": {"coordinates":[4.442513,52.028053],"type":"Point"}
}