{
  "type": "Feature",
  "properties": {
    "addr:full":"De Savornin Lohmanweg 13 Dordrecht Zuid-Holland 3317 LA",
    "addr:housenumber":"13",
    "addr:postcode":"3317 la",
    "addr:street":"De Savornin Lohmanweg",
    "iso:country":"NL",
    "sg:address":"De Savornin Lohmanweg 13",
    "sg:city":"Dordrecht",
    "sg:orig_category":"Voeding, Dranken And Tabak Gh",
    "sg:phone":"+31 78 617 0088",
    "sg:postcode":"3317 LA",
    "sg:province":"Zuid-Holland",
    "wof:name":"R. Nolle Bv",
    "wof:placetype":"venue"
},
  "geometry": {"coordinates":[4.663479,51.790169],"type":"Point"}
}