{
  "type": "Feature",
  "properties": {
    "addr:full":"P Oosterleestraat 18 Tiel Gelderland 4007 WL",
    "addr:housenumber":"18",
    "addr:postcode":"4007",
    "addr:street":"P Oosterleestraat;Gelderland",
    "iso:country":"NL",
    "sg:address":"P Oosterleestraat 18",
    "sg:city":"Tiel",
    "sg:orig_category":"Visspeciaalzaken",
    "sg:phone":"+31 344 623 261",
    "sg:postcode":"4007 WL",
    "sg:province":"Gelderland",
    "wof:name":"Vishandel Van Bokhoven",
    "wof:placetype":"venue"
},
  "geometry": {"coordinates":[5.396178,51.872025],"type":"Point"}
}