{
  "type": "Feature",
  "properties": {
    "iso:country":"NL",
    "sg:address":"Ruimtesonde 6",
    "sg:city":"Amersfoort",
    "sg:orig_category":"Public Relationbureaus",
    "sg:phone":"+31 33 456 0741",
    "sg:postcode":"3824 MZ",
    "sg:province":"Utrecht",
    "wof:name":"Lensen Partners Bv",
    "wof:placetype":"venue"
},
  "geometry": {"coordinates":[5.38878,52.200661],"type":"Point"}
}