{
  "type": "Feature",
  "properties": {
    "addr:full":"Bosstr 95 Driebergen Rysenb Utrecht 3971 XC",
    "addr:housenumber":"95",
    "addr:postcode":"3971 xc",
    "addr:street":"Bosstr;Rysenb",
    "iso:country":"NL",
    "sg:address":"Bosstr 95",
    "sg:city":"Driebergen Rysenb",
    "sg:orig_category":"Adviesbureaus Bedrijfsorganisatie",
    "sg:phone":"+31 343 521 285",
    "sg:postcode":"3971 XC",
    "sg:province":"Utrecht",
    "wof:name":"Kreuninck Bv",
    "wof:placetype":"venue"
},
  "geometry": {"coordinates":[5.286168,52.056084],"type":"Point"}
}