{
  "type": "Feature",
  "properties": {
    "iso:country":"NL",
    "sg:address":"Rondehoep O 19",
    "sg:city":"Ouderkerk Amstel",
    "sg:orig_category":"Fietsen En Bromfietsen",
    "sg:phone":"+31 20 496 1348",
    "sg:postcode":"1191 KC",
    "sg:province":"North Holland",
    "wof:name":"Bas Koenders",
    "wof:placetype":"venue"
},
  "geometry": {"coordinates":[4.905934,52.294086],"type":"Point"}
}