{
  "type": "Feature",
  "properties": {
    "addr:full":"Chopinstr 57 Lisse North Holland 2162 VR",
    "addr:housenumber":"57",
    "addr:postcode":"2162 vr",
    "addr:street":"Chopinstr",
    "iso:country":"NL",
    "sg:address":"Chopinstr 57",
    "sg:city":"Lisse",
    "sg:orig_category":"Accountants - Administratie- Consulenten En -Kantoren",
    "sg:phone":"+31 252 420 261",
    "sg:postcode":"2162 VR",
    "sg:province":"North Holland",
    "wof:name":"Sideacc Bv",
    "wof:placetype":"venue"
},
  "geometry": {"coordinates":[4.565614,52.248119],"type":"Point"}
}