{
  "type": "Feature",
  "properties": {
    "iso:country":"NL",
    "sg:address":"Bonnikestraat 37",
    "sg:city":"Hilversum",
    "sg:orig_category":"Watersport-, Sport- And Kampeerbenodigdheden Verhuur",
    "sg:phone":"+31 35 683 5313",
    "sg:postcode":"1222 EJ",
    "sg:province":"Noord-Holland",
    "wof:name":"A.W.M. Ode",
    "wof:placetype":"venue"
},
  "geometry": {"coordinates":[5.1742010117,52.240032196],"type":"Point"}
}