{
  "type": "Feature",
  "properties": {
    "addr:full":"Raadhuisplein 1 Veenendaal Utrecht 3901 GA",
    "addr:housenumber":"1",
    "addr:postcode":"3901 ga",
    "addr:street":"Raadhuisplein",
    "iso:country":"NL",
    "sg:address":"Raadhuisplein 1",
    "sg:city":"Veenendaal",
    "sg:orig_category":"Overheidsdiensten",
    "sg:phone":"+31 318 538 911",
    "sg:postcode":"3901 GA",
    "sg:province":"Utrecht",
    "wof:name":"Gemeente Veenendaal",
    "wof:placetype":"venue"
},
  "geometry": {"coordinates":[5.5571107864,52.0238342285],"type":"Point"}
}