{
  "type": "Feature",
  "properties": {
    "addr:full":"Haagweg 21 Rijswijk Zh Zuid-Holland 2281 AA",
    "addr:housenumber":"21",
    "addr:postcode":"zh;2281 aa",
    "addr:street":"Haagweg",
    "iso:country":"NL",
    "sg:address":"Haagweg 21",
    "sg:city":"Rijswijk Zh",
    "sg:orig_category":"Medische Apparatuur And Prothesen Fab",
    "sg:phone":"+31 70 390 3606",
    "sg:postcode":"2281 AA",
    "sg:province":"Zuid-Holland",
    "wof:name":"De Groot Tandtechn",
    "wof:placetype":"venue"
},
  "geometry": {"coordinates":[4.336268,52.058937],"type":"Point"}
}