{
  "type": "Feature",
  "properties": {
    "addr:full":"Bredasebaan 4 Bladel Noord-Brabant 5531 NB",
    "addr:housenumber":"4",
    "addr:postcode":"5531 nb",
    "addr:street":"Bredasebaan",
    "iso:country":"NL",
    "sg:address":"Bredasebaan 4",
    "sg:city":"Bladel",
    "sg:orig_category":"Projectontwikkeling",
    "sg:phone":"+31 497 383 618",
    "sg:postcode":"5531 NB",
    "sg:province":"Noord-Brabant",
    "wof:name":"Bouwontwikkeling Onroerend Goed",
    "wof:placetype":"venue"
},
  "geometry": {"coordinates":[5.219793,51.360077],"type":"Point"}
}