{
  "type": "Feature",
  "properties": {
    "iso:country":"NL",
    "sg:address":"Aldengoor 25",
    "sg:city":"Almelo",
    "sg:orig_category":"Autoradio'S",
    "sg:phone":"+31 6 54938234",
    "sg:postcode":"7608 NM",
    "sg:province":"Overijssel",
    "wof:name":"Tcs",
    "wof:placetype":"venue"
},
  "geometry": {"coordinates":[6.681246,52.375935],"type":"Point"}
}