{
  "type": "Feature",
  "properties": {
    "addr:full":"Eindhovenseweg 8 Geldrop Noord-Brabant 5662 AA",
    "addr:housenumber":"8",
    "addr:postcode":"5662 aa",
    "addr:street":"Eindhovenseweg",
    "iso:country":"NL",
    "sg:address":"Eindhovenseweg 8",
    "sg:city":"Geldrop",
    "sg:orig_category":"Film-, Tv- And Videoproductie",
    "sg:phone":"+31 40 286 8658",
    "sg:postcode":"5662 AA",
    "sg:province":"Noord-Brabant",
    "wof:name":"Verbeek & Van Der Loo Tv Productions",
    "wof:placetype":"venue"
},
  "geometry": {"coordinates":[5.550831,51.424088],"type":"Point"}
}