{
  "type": "Feature",
  "properties": {
    "addr:full":"Dorpsstr 34 Groesbeek Gelderland 6561 CB",
    "addr:housenumber":"34",
    "addr:postcode":"6561 cb",
    "addr:street":"Dorpsstr;Gelderland",
    "iso:country":"NL",
    "sg:address":"Dorpsstr 34",
    "sg:city":"Groesbeek",
    "sg:orig_category":"Verzekeringen - Verzekeringskantoren",
    "sg:phone":"+31 24 397 5755",
    "sg:postcode":"6561 CB",
    "sg:province":"Gelderland",
    "sg:website":"http://www.hvmakerlaardij.nl",
    "wof:name":"Hv",
    "wof:placetype":"venue"
},
  "geometry": {"coordinates":[5.93249,51.776745],"type":"Point"}
}