{
  "type": "Feature",
  "properties": {
    "addr:full":"Vloeddijk 26 Kampen Overijssel 8261 GB",
    "addr:housenumber":"26",
    "addr:postcode":"8261 gb",
    "addr:street":"Vloeddijk",
    "iso:country":"NL",
    "sg:address":"Vloeddijk 26",
    "sg:city":"Kampen",
    "sg:orig_category":"Binnenhuisarchitecten",
    "sg:phone":"+31 38 332 7161",
    "sg:postcode":"8261 GB",
    "sg:province":"Overijssel",
    "wof:name":"Marmo Art",
    "wof:placetype":"venue"
},
  "geometry": {"coordinates":[-2.23218,54.313919],"type":"Point"}
}