{
  "type": "Feature",
  "properties": {
    "addr:full":"Maaspoortweg 182 'S Hertogenbosch Noord-Brabant 5235 KB",
    "addr:housenumber":"182 ' s",
    "addr:postcode":"5235 kb",
    "addr:street":"Maaspoortweg",
    "iso:country":"NL",
    "sg:address":"Maaspoortweg 182",
    "sg:city":"'S Hertogenbosch",
    "sg:orig_category":"Fysiotherapeuten",
    "sg:phone":"+31 73 642 6363",
    "sg:postcode":"5235 KB",
    "sg:province":"Noord-Brabant",
    "wof:name":"Fysiotherapie Maaspoort",
    "wof:placetype":"venue"
},
  "geometry": {"coordinates":[5.307975,51.725899],"type":"Point"}
}