{
  "type": "Feature",
  "properties": {
    "addr:full":"Postbus 112 Eindhoven Noord-Brabant 5600 AC",
    "addr:housenumber":"112",
    "addr:postcode":"5600 ac",
    "addr:street":"Postbus",
    "iso:country":"NL",
    "sg:address":"Postbus 112",
    "sg:city":"Eindhoven",
    "sg:orig_category":"Accountants - Administratie- Consulenten En -Kantoren",
    "sg:phone":"+31 40 244 1868",
    "sg:postcode":"5600 AC",
    "sg:province":"Noord-Brabant",
    "wof:name":"Vvaa",
    "wof:placetype":"venue"
},
  "geometry": {"coordinates":[5.48411,51.434471],"type":"Point"}
}