{
  "type": "Feature",
  "properties": {
    "addr:full":"Tarwekamp 71 'S Gravenhage South Holland 2592 XH",
    "addr:housenumber":"71",
    "addr:postcode":"2592 xh",
    "addr:street":"Tarwekamp;' S Gravenhage",
    "iso:country":"NL",
    "sg:address":"Tarwekamp 71",
    "sg:city":"'S Gravenhage",
    "sg:orig_category":"Loodgieterswerk, Verwarming And Sanitaire Installaties",
    "sg:phone":"+31 70 383 3981",
    "sg:postcode":"2592 XH",
    "sg:province":"South Holland",
    "wof:name":"Dienstenwinkel Mariahoeve",
    "wof:placetype":"venue"
},
  "geometry": {"coordinates":[4.353178,52.088547],"type":"Point"}
}