{
  "type": "Feature",
  "properties": {
    "addr:full":"J C Beetslaan 163 Hoofddorp Noord-Holland 2131 AL",
    "addr:housenumber":"163",
    "addr:postcode":"2131 al",
    "addr:street":"J C Beetslaan",
    "iso:country":"NL",
    "sg:address":"J C Beetslaan 163",
    "sg:city":"Hoofddorp",
    "sg:orig_category":"Meubels And Huishoudapparatuur Gh",
    "sg:phone":"+31 23 528 1244",
    "sg:postcode":"2131 AL",
    "sg:province":"Noord-Holland",
    "wof:name":"Bremafa Bv",
    "wof:placetype":"venue"
},
  "geometry": {"coordinates":[4.688152,52.314419],"type":"Point"}
}