{
  "type": "Feature",
  "properties": {
    "addr:full":"Padualaan 8 Room Z110 Utrecht 3584 CH",
    "addr:housenumber":"8 room z110",
    "addr:postcode":"3584",
    "addr:street":"Padualaan",
    "iso:country":"NL",
    "sg:address":"Padualaan 8 Room Z110",
    "sg:city":"Utrecht",
    "sg:classifiers":[
        {
            "category":"Professional",
            "subcategory":"Research",
            "type":"Services"
        }
    ],
    "sg:postcode":"3584 CH",
    "sg:tags":[
        "genetic",
        "genetics",
        "cloning",
        "software",
        "dna",
        "assembly",
        "analysis",
        "restriction-enzymes",
        "enzymes",
        "proteins",
        "genes"
    ],
    "sg:website":"http://www.crimsonbase.com",
    "wof:name":"CrimsonBase",
    "wof:placetype":"venue"
},
  "geometry": {"coordinates":[5.1682449,52.0848526],"type":"Point"}
}