{
  "type": "Feature",
  "properties": {
    "addr:full":"Vrijheid 55 Zwolle Overijssel 8014 XZ",
    "addr:housenumber":"55",
    "addr:postcode":"8014 xz",
    "addr:street":"Vrijheid",
    "iso:country":"NL",
    "sg:address":"Vrijheid 55",
    "sg:city":"Zwolle",
    "sg:orig_category":"Artsen And Specialisten",
    "sg:phone":"+31 38 460 0956",
    "sg:postcode":"8014 XZ",
    "sg:province":"Overijssel",
    "wof:name":"Drs. G.J. Gerrits",
    "wof:placetype":"venue"
},
  "geometry": {"coordinates":[6.110349,52.481735],"type":"Point"}
}