{
  "type": "Feature",
  "properties": {
    "iso:country":"NL",
    "sg:address":"Zichtenburgln 1A",
    "sg:city":"S Gravenhage",
    "sg:orig_category":"Babyartikelen",
    "sg:phone":"+31 70 368 1097",
    "sg:postcode":"2544 EA",
    "sg:province":"Zuid-Holland",
    "sg:website":"http://www.gijsje.nl",
    "wof:name":"Gijsje, Kraammanden & Baby Kado'S",
    "wof:placetype":"venue"
},
  "geometry": {"coordinates":[4.25157,52.039551],"type":"Point"}
}