{
  "type": "Feature",
  "properties": {
    "addr:full":"Rijksweg 57 Limmen Noord-Holland 1906 BD",
    "addr:housenumber":"57",
    "addr:postcode":"1906 bd",
    "addr:street":"Rijksweg",
    "iso:country":"NL",
    "sg:address":"Rijksweg 57",
    "sg:city":"Limmen",
    "sg:orig_category":"Schoonheidssalons",
    "sg:phone":"+31 72 505 3272",
    "sg:postcode":"1906 BD",
    "sg:province":"Noord-Holland",
    "wof:name":"Beauty Face",
    "wof:placetype":"venue"
},
  "geometry": {"coordinates":[4.691764,52.56918],"type":"Point"}
}