{
  "type": "Feature",
  "properties": {
    "addr:full":"Meeussenstr 1 Bergen Op Zoom North Brabant 4611 BP",
    "addr:housenumber":"1",
    "addr:postcode":"4611 bp",
    "addr:street":"Meeussenstr",
    "iso:country":"NL",
    "sg:address":"Meeussenstr 1",
    "sg:city":"Bergen Op Zoom",
    "sg:orig_category":"Meubelmakerijen",
    "sg:phone":"+31 164 254 203",
    "sg:postcode":"4611 BP",
    "sg:province":"North Brabant",
    "wof:name":"Sonnenberg Design Meubelontwerp",
    "wof:placetype":"venue"
},
  "geometry": {"coordinates":[4.294549,51.493607],"type":"Point"}
}