{
  "type": "Feature",
  "properties": {
    "addr:full":"Kobaltstraat 18 Naarden Noord-Holland 1411 AM",
    "addr:housenumber":"18",
    "addr:postcode":"1411",
    "addr:street":"Kobaltstraat",
    "iso:country":"NL",
    "sg:address":"Kobaltstraat 18",
    "sg:city":"Naarden",
    "sg:orig_category":"Schilderwerk",
    "sg:phone":"+31 35 694 7561",
    "sg:postcode":"1411 AM",
    "sg:province":"Noord-Holland",
    "wof:name":"Hartman Schilderwerken En Totaalonderhoud Bv",
    "wof:placetype":"venue"
},
  "geometry": {"coordinates":[5.154294,52.301933],"type":"Point"}
}