{
  "type": "Feature",
  "properties": {
    "addr:full":"Arkpln 125 Alkmaar Noord-Holland 1826 DM",
    "addr:housenumber":"125",
    "addr:postcode":"1826 dm",
    "iso:country":"NL",
    "sg:address":"Arkpln 125",
    "sg:city":"Alkmaar",
    "sg:orig_category":"Verenigingsgebouwen",
    "sg:phone":"+31 72 561 7026",
    "sg:postcode":"1826 DM",
    "sg:province":"Noord-Holland",
    "wof:name":"Dobber, De",
    "wof:placetype":"venue"
},
  "geometry": {"coordinates":[4.760685,52.653839],"type":"Point"}
}