{
  "type": "Feature",
  "properties": {
    "addr:full":"Schellestr 8A Alphen Nb Noord-Brabant 5131 RJ",
    "addr:housenumber":"8a",
    "addr:postcode":"5131 rj",
    "addr:street":"Schellestr",
    "iso:country":"NL",
    "sg:address":"Schellestr 8A",
    "sg:city":"Alphen Nb",
    "sg:orig_category":"Loonbedrijven",
    "sg:phone":"+31 13 508 1426",
    "sg:postcode":"5131 RJ",
    "sg:province":"Noord-Brabant",
    "wof:name":"Jong, A De",
    "wof:placetype":"venue"
},
  "geometry": {"coordinates":[4.968306,51.488533],"type":"Point"}
}