{
  "type": "Feature",
  "properties": {
    "addr:full":"Thorbeckestr 6 Naaldwyk Zuid-Holland 2672 AX",
    "addr:housenumber":"6",
    "addr:postcode":"2672 ax",
    "addr:street":"Thorbeckestr",
    "iso:country":"NL",
    "sg:address":"Thorbeckestr 6",
    "sg:city":"Naaldwyk",
    "sg:orig_category":"Administratie- En Boekhoudkantoren",
    "sg:phone":"+31 174 630 668",
    "sg:postcode":"2672 AX",
    "sg:province":"Zuid-Holland",
    "sg:website":"http://www.deltasalaris.nl",
    "wof:name":"Delta Salarisadministraties",
    "wof:placetype":"venue"
},
  "geometry": {"coordinates":[4.216379,51.99411],"type":"Point"}
}