{
  "type": "Feature",
  "properties": {
    "addr:full":"Gronausestr 1307 Enschede Overijssel 7534 AK",
    "addr:housenumber":"1307",
    "addr:postcode":"7534 ak",
    "iso:country":"NL",
    "sg:address":"Gronausestr 1307",
    "sg:city":"Enschede",
    "sg:classifiers":[
        {
            "category":"Food & Beverages",
            "subcategory":"Bakery",
            "type":"Retail Goods"
        }
    ],
    "sg:phone":"+31 53 461 6553",
    "sg:postcode":"7534 AK",
    "sg:province":"Overijssel",
    "sg:tags":[
        "pizza"
    ],
    "wof:name":"Pyramide",
    "wof:placetype":"venue"
},
  "geometry": {"coordinates":[6.95548,52.21645],"type":"Point"}
}