{
  "type": "Feature",
  "properties": {
    "addr:full":"Wilhelminakade 69 Waddinxveen Zuid-Holland 2741 JV",
    "addr:housenumber":"69",
    "addr:postcode":"2741 jv",
    "addr:street":"Wilhelminakade",
    "iso:country":"NL",
    "sg:address":"Wilhelminakade 69",
    "sg:city":"Waddinxveen",
    "sg:orig_category":"Meubelreparatie And -Restauratie",
    "sg:phone":"+31 182 631 720",
    "sg:postcode":"2741 JV",
    "sg:province":"Zuid-Holland",
    "wof:name":"M Van Deest Jr Woninginr En Meubelstofferen",
    "wof:placetype":"venue"
},
  "geometry": {"coordinates":[4.668726,52.023087],"type":"Point"}
}