{
  "type": "Feature",
  "properties": {
    "iso:country":"NL",
    "sg:address":"Oranjestraat 7",
    "sg:city":"Denekamp",
    "sg:orig_category":"Autokeuringen",
    "sg:phone":"+31 541 351 666",
    "sg:postcode":"7591 GA",
    "sg:province":"Overijssel",
    "wof:name":"H.B. Mensink Bv",
    "wof:placetype":"venue"
},
  "geometry": {"coordinates":[7.001486,52.372883],"type":"Point"}
}