{
  "type": "Feature",
  "properties": {
    "addr:full":"O Woltersstr 6 Venlo Limburg 5913 RM",
    "addr:housenumber":"6",
    "addr:postcode":"5913 rm",
    "iso:country":"NL",
    "sg:address":"O Woltersstr 6",
    "sg:city":"Venlo",
    "sg:orig_category":"Kantoor- En Secretariaatsservice",
    "sg:phone":"+31 77 351 3380",
    "sg:postcode":"5913 RM",
    "sg:province":"Limburg",
    "wof:name":"Mulders",
    "wof:placetype":"venue"
},
  "geometry": {"coordinates":[6.1851620674,51.3645172119],"type":"Point"}
}