{
  "type": "Feature",
  "properties": {
    "addr:full":"Eemnesserweg 7 Hilversum North Holland 1221 CT",
    "addr:housenumber":"7",
    "addr:postcode":"1221 ct",
    "addr:street":"Eemnesserweg",
    "iso:country":"NL",
    "sg:address":"Eemnesserweg 7",
    "sg:city":"Hilversum",
    "sg:orig_category":"Bloemen And Planten",
    "sg:phone":"+31 35 685 9868",
    "sg:postcode":"1221 CT",
    "sg:province":"North Holland",
    "wof:name":"Bloemenboetiek Marja",
    "wof:placetype":"venue"
},
  "geometry": {"coordinates":[5.186041,52.228622],"type":"Point"}
}