{
  "type": "Feature",
  "properties": {
    "addr:full":"Van Der Heimstraat 17 Delft South Holland 2613 DZ",
    "addr:housenumber":"17",
    "addr:postcode":"2613 dz",
    "addr:street":"Van Der Heimstraat",
    "iso:country":"NL",
    "sg:address":"Van Der Heimstraat 17",
    "sg:city":"Delft",
    "sg:classifiers":[
        {
            "category":"Travel",
            "subcategory":"Hotels & Motels",
            "type":"Entertainment"
        }
    ],
    "sg:phone":"+31 15 213 4223",
    "sg:postcode":"2613 DZ",
    "sg:province":"South Holland",
    "wof:name":"Pension- En Recreatiebedrijf Prins",
    "wof:placetype":"venue"
},
  "geometry": {"coordinates":[4.349107,52.010178],"type":"Point"}
}