{
  "type": "Feature",
  "properties": {
    "addr:full":"Heinsbergerweg 73 Roermond Limburg 6045 CC",
    "addr:housenumber":"73",
    "addr:postcode":"6045 cc",
    "addr:street":"Heinsbergerweg",
    "iso:country":"NL",
    "sg:address":"Heinsbergerweg 73",
    "sg:city":"Roermond",
    "sg:orig_category":"Wasserettes And Stomerijen",
    "sg:phone":"+31 475 316 904",
    "sg:postcode":"6045 CC",
    "sg:province":"Limburg",
    "wof:name":"H.W.E.M. Stams",
    "wof:placetype":"venue"
},
  "geometry": {"coordinates":[5.9989261627,51.1785812378],"type":"Point"}
}