{
  "type": "Feature",
  "properties": {
    "addr:full":"Koemarkt 20 Schiedam Zuid-Holland 3111 JH",
    "addr:housenumber":"20",
    "addr:postcode":"3111 jh",
    "addr:street":"Koemarkt",
    "iso:country":"NL",
    "sg:address":"Koemarkt 20",
    "sg:city":"Schiedam",
    "sg:classifiers":[
        {
            "category":"Fast Food",
            "type":"Food & Drink"
        }
    ],
    "sg:phone":"+31 10 473 2757",
    "sg:postcode":"3111 JH",
    "sg:province":"Zuid-Holland",
    "sg:tags":[
        "afhaal",
        "restaurant"
    ],
    "wof:name":"Bram Ladage Verse Patat",
    "wof:placetype":"venue"
},
  "geometry": {"coordinates":[4.401645,51.913994],"type":"Point"}
}