{
  "type": "Feature",
  "properties": {
    "addr:full":"Westeinde 30 Oosthuizen Noord-Holland 1474 HB",
    "addr:housenumber":"30",
    "addr:postcode":"1474 hb",
    "addr:street":"Westeinde",
    "iso:country":"NL",
    "sg:address":"Westeinde 30",
    "sg:city":"Oosthuizen",
    "sg:orig_category":"Diverse Grafische Activiteiten",
    "sg:phone":"+31 299 401 053",
    "sg:postcode":"1474 HB",
    "sg:province":"Noord-Holland",
    "wof:name":"Tdg Prod",
    "wof:placetype":"venue"
},
  "geometry": {"coordinates":[4.99894,52.574059],"type":"Point"}
}