{
  "type": "Feature",
  "properties": {
    "addr:full":"Roermondsewg 32 Haelen Limburg 6081 NV",
    "addr:housenumber":"32",
    "addr:postcode":"6081 nv",
    "addr:street":"Roermondsewg",
    "iso:country":"NL",
    "sg:address":"Roermondsewg 32",
    "sg:city":"Haelen",
    "sg:orig_category":"Kassenbouw",
    "sg:phone":"+31 475 595 454",
    "sg:postcode":"6081 NV",
    "sg:province":"Limburg",
    "sg:website":"http://www.arkoo.nl",
    "wof:name":"Arkoo Tuinkassen",
    "wof:placetype":"venue"
},
  "geometry": {"coordinates":[5.96349,51.228577],"type":"Point"}
}