{
  "type": "Feature",
  "properties": {
    "iso:country":"NL",
    "sg:address":"Oudeschans 46A",
    "sg:city":"Amsterdam",
    "sg:orig_category":"Verenigingen En Stichtingen",
    "sg:phone":"+31 20 422 1616",
    "sg:postcode":"1011 LC",
    "sg:province":"North Holland",
    "sg:website":"http://www.andrewcohen.org",
    "wof:name":"Impersonal Enlightenment Fellowship",
    "wof:placetype":"venue"
},
  "geometry": {"coordinates":[4.903382,52.371292],"type":"Point"}
}