{
  "type": "Feature",
  "properties": {
    "addr:full":"Waaier 27 Leimuiden Zuid-Holland 2451 VV",
    "addr:housenumber":"27",
    "addr:postcode":"2451 vv",
    "addr:street":"Waaier",
    "iso:country":"NL",
    "sg:address":"Waaier 27",
    "sg:city":"Leimuiden",
    "sg:orig_category":"Keukens",
    "sg:phone":"+31 172 507 454",
    "sg:postcode":"2451 VV",
    "sg:province":"Zuid-Holland",
    "sg:website":"http://www.bloksmakeukens.nl",
    "wof:name":"Bloksma Leimuiden Bv",
    "wof:placetype":"venue"
},
  "geometry": {"coordinates":[4.682705,52.223873],"type":"Point"}
}