{
  "type": "Feature",
  "properties": {
    "addr:full":"F Schurerstr 2 Franeker Friesland 8802 ZZ",
    "addr:housenumber":"2",
    "addr:postcode":"8802 zz",
    "addr:street":"Schurerstr",
    "iso:country":"NL",
    "sg:address":"F Schurerstr 2",
    "sg:city":"Franeker",
    "sg:orig_category":"Administratie- En Boekhoudkantoren",
    "sg:phone":"+31 517 390 991",
    "sg:postcode":"8802 ZZ",
    "sg:province":"Friesland",
    "wof:name":"Prins",
    "wof:placetype":"venue"
},
  "geometry": {"coordinates":[5.556932,53.192188],"type":"Point"}
}