{
  "type": "Feature",
  "properties": {
    "iso:country":"NL",
    "sg:address":"Hanekamp 2-8",
    "sg:city":"Zwolle",
    "sg:orig_category":"Pianovervoer",
    "sg:phone":"+31 38 453 5587",
    "sg:postcode":"8023 TH",
    "sg:province":"Overijssel",
    "wof:name":"Graaf Bv, De",
    "wof:placetype":"venue"
},
  "geometry": {"coordinates":[6.109726,52.513981],"type":"Point"}
}