{
  "type": "Feature",
  "properties": {
    "addr:full":"Herculesweg 10-14 Delft South Holland 2624 VM",
    "addr:housenumber":"10-14",
    "addr:postcode":"2624 vm",
    "addr:street":"Herculesweg",
    "iso:country":"NL",
    "sg:address":"Herculesweg 10-14",
    "sg:city":"Delft",
    "sg:orig_category":"Kinderopvang Behalve Thuis",
    "sg:phone":"+31 15 256 5017",
    "sg:postcode":"2624 VM",
    "sg:province":"South Holland",
    "wof:name":"Kinderdagverblijf Pippeloentje",
    "wof:placetype":"venue"
},
  "geometry": {"coordinates":[4.355898,51.998203],"type":"Point"}
}