{
  "type": "Feature",
  "properties": {
    "addr:full":"Over Boeicop 44 Schoonrewoerd Zuid-Holland 4145 NR",
    "addr:housenumber":"44",
    "addr:postcode":"4145 nr",
    "addr:street":"Over Boeicop",
    "iso:country":"NL",
    "sg:address":"Over Boeicop 44",
    "sg:city":"Schoonrewoerd",
    "sg:orig_category":"Granen, Zaden And Diervoeders Gh",
    "sg:phone":"+31 345 641 608",
    "sg:postcode":"4145 NR",
    "sg:province":"Zuid-Holland",
    "wof:name":"Fa. W. Oskam",
    "wof:placetype":"venue"
},
  "geometry": {"coordinates":[5.105875,51.937756],"type":"Point"}
}