{
  "type": "Feature",
  "properties": {
    "addr:full":"Utrechtsestr 118 Amsterdam Noord-Holland 1017 VT",
    "addr:housenumber":"118",
    "addr:postcode":"1017",
    "iso:country":"NL",
    "sg:address":"Utrechtsestr 118",
    "sg:city":"Amsterdam",
    "sg:orig_category":"Kappers",
    "sg:phone":"+31 6 21897971",
    "sg:postcode":"1017 VT",
    "sg:province":"Noord-Holland",
    "sg:website":"http://www.quahaar.nl",
    "wof:name":"Qua Haar",
    "wof:placetype":"venue"
},
  "geometry": {"coordinates":[4.898944,52.361618],"type":"Point"}
}