{
  "type": "Feature",
  "properties": {
    "addr:full":"Geldropseweg 114 Heeze Noord-Brabant 5591 ED",
    "addr:housenumber":"114",
    "addr:postcode":"5591 ed",
    "addr:street":"Geldropseweg",
    "iso:country":"NL",
    "sg:address":"Geldropseweg 114",
    "sg:city":"Heeze",
    "sg:orig_category":"Geluidsopnamen",
    "sg:phone":"+31 40 226 4130",
    "sg:postcode":"5591 ED",
    "sg:province":"Noord-Brabant",
    "wof:name":"Markant Recording Studios Bv",
    "wof:placetype":"venue"
},
  "geometry": {"coordinates":[5.577001,51.386021],"type":"Point"}
}