{
  "type": "Feature",
  "properties": {
    "addr:full":"Kerkallee 73 Velp Gld Gelderland 6882 AN",
    "addr:housenumber":"73",
    "addr:postcode":"6882 an",
    "addr:street":"Kerkallee;Gld Gelderland",
    "iso:country":"NL",
    "sg:address":"Kerkallee 73",
    "sg:city":"Velp Gld",
    "sg:orig_category":"Bedrijfs- And Managementsconsultants",
    "sg:phone":"+31 26 362 2790",
    "sg:postcode":"6882 AN",
    "sg:province":"Gelderland",
    "wof:name":"Gelderkamp Adviesburo Bv",
    "wof:placetype":"venue"
},
  "geometry": {"coordinates":[5.969053,51.992752],"type":"Point"}
}