{
  "type": "Feature",
  "properties": {
    "iso:country":"NL",
    "sg:address":"Ambachtsweg 5",
    "sg:city":"Nijverdal",
    "sg:orig_category":"Wegen And Sportterreinen",
    "sg:phone":"+31 548 618 200",
    "sg:postcode":"7442 CS",
    "sg:province":"NL.08",
    "wof:name":"Ballast Nedam",
    "wof:placetype":"venue"
},
  "geometry": {"coordinates":[6.4951338768,52.3565940857],"type":"Point"}
}