{
  "type": "Feature",
  "properties": {
    "addr:full":"Rietkerkwg 53 Rotterdam Zuid-Holland 3066 TN",
    "addr:housenumber":"53",
    "addr:postcode":"3066",
    "addr:street":"Rietkerkwg",
    "iso:country":"NL",
    "sg:address":"Rietkerkwg 53",
    "sg:city":"Rotterdam",
    "sg:orig_category":"Loopbaanbegeleiding",
    "sg:phone":"+31 10 220 4253",
    "sg:postcode":"3066 TN",
    "sg:province":"Zuid-Holland",
    "sg:website":"http://www.chilon.nl",
    "wof:name":"Chilon",
    "wof:placetype":"venue"
},
  "geometry": {"coordinates":[4.556675,51.933773],"type":"Point"}
}