{
  "type": "Feature",
  "properties": {
    "iso:country":"NL",
    "sg:address":"Roosbergsewg 16 A",
    "sg:city":"Bavel",
    "sg:orig_category":"Bestratingen",
    "sg:phone":"+31 6 51321414",
    "sg:postcode":"4854 PM",
    "sg:province":"Noord-Brabant",
    "wof:name":"Eric Voeten",
    "wof:placetype":"venue"
},
  "geometry": {"coordinates":[4.827832,51.559071],"type":"Point"}
}