{
  "type": "Feature",
  "properties": {
    "iso:country":"NL",
    "sg:address":"Dr Kuyperkade 28",
    "sg:city":"Maassluis",
    "sg:orig_category":"Boekhandels",
    "sg:phone":"+31 10 591 2823",
    "sg:postcode":"3142 GC",
    "sg:province":"Zuid-Holland",
    "wof:name":"Maassluise Courant Bv",
    "wof:placetype":"venue"
},
  "geometry": {"coordinates":[4.256442,51.922585],"type":"Point"}
}