{
  "type": "Feature",
  "properties": {
    "iso:country":"NL",
    "sg:address":"Bostonweg 10",
    "sg:city":"Almere",
    "sg:orig_category":"Meubelzaken, Woning- And Keukeninrichting",
    "sg:phone":"+31 36 532 8880",
    "sg:postcode":"1334 KS",
    "sg:province":"Flevoland",
    "wof:name":"Trendhopper Doe Mere Bv",
    "wof:placetype":"venue"
},
  "geometry": {"coordinates":[5.274438,52.394722],"type":"Point"}
}