{
  "type": "Feature",
  "properties": {
    "addr:full":"Nieuwe Ebbingestraat 56 Groningen Groningen 9712 NM",
    "addr:housenumber":"56",
    "addr:postcode":"9712",
    "addr:street":"Nieuwe Ebbingestraat",
    "iso:country":"NL",
    "sg:address":"Nieuwe Ebbingestraat 56",
    "sg:city":"Groningen",
    "sg:classifiers":[
        {
            "category":"Fast Food",
            "type":"Food & Drink"
        }
    ],
    "sg:phone":"+31 50 312 8010",
    "sg:postcode":"9712 NM",
    "sg:province":"Groningen",
    "sg:tags":[
        "afhaal",
        "restaurant"
    ],
    "wof:name":"Man Wah",
    "wof:placetype":"venue"
},
  "geometry": {"coordinates":[6.562852,53.22401],"type":"Point"}
}