{
  "type": "Feature",
  "properties": {
    "iso:country":"NL",
    "sg:address":"Burgemeester Hogguerstr 1097",
    "sg:city":"Amsterdam",
    "sg:orig_category":"Bedrijfs- And Managementsconsultants",
    "sg:phone":"+31 20 611 1970",
    "sg:postcode":"1064 EH",
    "sg:province":"North Holland",
    "wof:name":"Stein Communications Bv",
    "wof:placetype":"venue"
},
  "geometry": {"coordinates":[4.828096,52.373596],"type":"Point"}
}