{
  "type": "Feature",
  "properties": {
    "addr:full":"Coppeliaschouw 28 Zoetermeer Zuid-Holland 2726 JA",
    "addr:housenumber":"28",
    "addr:postcode":"2726 ja",
    "addr:street":"Coppeliaschouw",
    "iso:country":"NL",
    "sg:address":"Coppeliaschouw 28",
    "sg:city":"Zoetermeer",
    "sg:orig_category":"Meubelzaken, Woning- And Keukeninrichting",
    "sg:phone":"+31 79 331 4749",
    "sg:postcode":"2726 JA",
    "sg:province":"Zuid-Holland",
    "wof:name":"Beter Bed",
    "wof:placetype":"venue"
},
  "geometry": {"coordinates":[4.49136,52.065392],"type":"Point"}
}