{
  "type": "Feature",
  "properties": {
    "addr:full":"Edisonbaan 26 Nieuwegein Utrecht 3439 MN",
    "addr:housenumber":"26",
    "addr:postcode":"3439 mn",
    "addr:street":"Edisonbaan",
    "iso:country":"NL",
    "sg:address":"Edisonbaan 26",
    "sg:city":"Nieuwegein",
    "sg:orig_category":"Farmaceutische Industrie En Groothandel",
    "sg:phone":"+31 30 600 5790",
    "sg:postcode":"3439 MN",
    "sg:province":"Utrecht",
    "wof:name":"Alk-Abell\u00f3 Bv",
    "wof:placetype":"venue"
},
  "geometry": {"coordinates":[5.09992,52.032539],"type":"Point"}
}