{
  "type": "Feature",
  "properties": {
    "addr:full":"Pastorijfinne 17 Jorwert Friesland 9023 AK",
    "addr:housenumber":"17",
    "addr:postcode":"9023 ak",
    "addr:street":"Pastorijfinne",
    "iso:country":"NL",
    "sg:address":"Pastorijfinne 17",
    "sg:city":"Jorwert",
    "sg:orig_category":"Banken And Kredietinstellingen",
    "sg:phone":"+31 58 251 9445",
    "sg:postcode":"9023 AK",
    "sg:province":"Friesland",
    "wof:name":"Rabobank",
    "wof:placetype":"venue"
},
  "geometry": {"coordinates":[5.714754,53.143799],"type":"Point"}
}