{
  "type": "Feature",
  "properties": {
    "iso:country":"NL",
    "sg:address":"Enkstr 67",
    "sg:city":"Zwolle",
    "sg:orig_category":"Verenigingsgebouwen",
    "sg:phone":"+31 38 423 3000",
    "sg:postcode":"8012 VA",
    "sg:province":"Overijssel",
    "wof:name":"Assendorp",
    "wof:placetype":"venue"
},
  "geometry": {"coordinates":[6.099218,52.506786],"type":"Point"}
}