{
  "type": "Feature",
  "properties": {
    "addr:full":"Zwanenkamp 767 Maarssen Utrecht 3607 PP",
    "addr:housenumber":"767",
    "addr:postcode":"3607 pp",
    "addr:street":"Zwanenkamp",
    "iso:country":"NL",
    "sg:address":"Zwanenkamp 767",
    "sg:city":"Maarssen",
    "sg:orig_category":"Fotostudio'S And Fotografen",
    "sg:phone":"+31 346 573 983",
    "sg:postcode":"3607 PP",
    "sg:province":"Utrecht",
    "wof:name":"Fotopersburo Ron Richel",
    "wof:placetype":"venue"
},
  "geometry": {"coordinates":[5.01191,52.144501],"type":"Point"}
}