{
  "type": "Feature",
  "properties": {
    "iso:country":"NL",
    "sg:address":"Grondzyl 27",
    "sg:city":"Groningen",
    "sg:orig_category":"Voegwerken",
    "sg:phone":"+31 50 541 6947",
    "sg:postcode":"9731 DG",
    "sg:province":"Groningen",
    "wof:name":"Vries, P J De",
    "wof:placetype":"venue"
},
  "geometry": {"coordinates":[6.589147,53.238083],"type":"Point"}
}