{
  "type": "Feature",
  "properties": {
    "addr:full":"Lindengr 193 Amsterdam Noord-Holland 1015 KE",
    "addr:housenumber":"193",
    "addr:postcode":"1015 ke",
    "iso:country":"NL",
    "sg:address":"Lindengr 193",
    "sg:city":"Amsterdam",
    "sg:orig_category":"Kunstbloemen En -Planten - Verhuur",
    "sg:phone":"+31 20 624 6931",
    "sg:postcode":"1015 KE",
    "sg:province":"Noord-Holland",
    "wof:name":"Deco-Rent",
    "wof:placetype":"venue"
},
  "geometry": {"coordinates":[4.882426,52.379715],"type":"Point"}
}