{
  "type": "Feature",
  "properties": {
    "addr:full":"Grotenhuisweg 44 Wilp Gld Gelderland 7384 CT",
    "addr:housenumber":"44",
    "addr:postcode":"7384 ct",
    "addr:street":"Grotenhuisweg;Gld Gelderland",
    "iso:country":"NL",
    "sg:address":"Grotenhuisweg 44",
    "sg:city":"Wilp Gld",
    "sg:orig_category":"Goederenvervoer Over De Weg",
    "sg:phone":"+31 571 261 582",
    "sg:postcode":"7384 CT",
    "sg:province":"Gelderland",
    "wof:name":"G.J. Koldenhof",
    "wof:placetype":"venue"
},
  "geometry": {"coordinates":[6.109879,52.209869],"type":"Point"}
}