{
  "type": "Feature",
  "properties": {
    "iso:country":"NL",
    "sg:address":"Schouwtjesln 12A",
    "sg:city":"Haarlem",
    "sg:classifiers":[
        {
            "category":"Retail",
            "subcategory":"Auto Repair",
            "type":"Services"
        }
    ],
    "sg:phone":"+31 23 532 1882",
    "sg:postcode":"2012 KH",
    "sg:province":"Noord-Holland",
    "sg:tags":[
        "garage"
    ],
    "wof:name":"Special Car Service",
    "wof:placetype":"venue"
},
  "geometry": {"coordinates":[4.622531,52.370911],"type":"Point"}
}