{
  "type": "Feature",
  "properties": {
    "addr:full":"Roselaar 22 Roosendaal North Brabant 4701 BC",
    "addr:housenumber":"22",
    "addr:postcode":"4701 bc",
    "addr:street":"Roselaar",
    "iso:country":"NL",
    "sg:address":"Roselaar 22",
    "sg:city":"Roosendaal",
    "sg:orig_category":"Huishoudapparatuur, Televisies And Radio'S",
    "sg:phone":"+31 165 549 058",
    "sg:postcode":"4701 BC",
    "sg:province":"North Brabant",
    "wof:name":"Megapool",
    "wof:placetype":"venue"
},
  "geometry": {"coordinates":[4.453406,51.53064],"type":"Point"}
}