{
  "type": "Feature",
  "properties": {
    "iso:country":"NL",
    "sg:address":"Ceintuurbaan 111/1Hg",
    "sg:city":"Rotterdam",
    "sg:orig_category":"Film-, Tv- And Videoproductie",
    "sg:phone":"+31 10 461 8581",
    "sg:postcode":"3051 KA",
    "sg:province":"Zuid-Holland",
    "wof:name":"Correct Professional Audio-Video",
    "wof:placetype":"venue"
},
  "geometry": {"coordinates":[4.478608,51.942402],"type":"Point"}
}