{
  "type": "Feature",
  "properties": {
    "addr:full":"Geertespln 20 Kloetinge Zeeland 4481 AN",
    "addr:housenumber":"20",
    "addr:postcode":"4481 an",
    "addr:street":"Geertespln",
    "iso:country":"NL",
    "sg:address":"Geertespln 20",
    "sg:city":"Kloetinge",
    "sg:orig_category":"Beeldende Kunstenaars",
    "sg:phone":"+31 113 228 825",
    "sg:postcode":"4481 AN",
    "sg:province":"Zeeland",
    "wof:name":"Kuys, A",
    "wof:placetype":"venue"
},
  "geometry": {"coordinates":[3.915817,51.498764],"type":"Point"}
}