{
  "type": "Feature",
  "properties": {
    "addr:full":"Lg Brink 11 Apeldoorn Gelderland 7317 BD",
    "addr:housenumber":"11",
    "addr:postcode":"7317 bd",
    "addr:street":"Lg Brink;Gelderland",
    "iso:country":"NL",
    "sg:address":"Lg Brink 11",
    "sg:city":"Apeldoorn",
    "sg:orig_category":"Verlichtingsartikelen - Fabrieken",
    "sg:phone":"+31 55 521 6535",
    "sg:postcode":"7317 BD",
    "sg:province":"Gelderland",
    "wof:name":"Steinhauer Bv",
    "wof:placetype":"venue"
},
  "geometry": {"coordinates":[5.971572,52.243645],"type":"Point"}
}