{
  "type": "Feature",
  "properties": {
    "addr:full":"Deurneseweg 1 Oploo Noord-Brabant 5841 CK",
    "addr:housenumber":"1",
    "addr:postcode":"5841 ck",
    "addr:street":"Deurneseweg",
    "iso:country":"NL",
    "sg:address":"Deurneseweg 1",
    "sg:city":"Oploo",
    "sg:orig_category":"Krantenuitgeverijen",
    "sg:phone":"+31 485 384 647",
    "sg:postcode":"5841 CK",
    "sg:province":"Noord-Brabant",
    "wof:name":"Triplo Bv",
    "wof:placetype":"venue"
},
  "geometry": {"coordinates":[5.86777,51.603146],"type":"Point"}
}