{
  "type": "Feature",
  "properties": {
    "iso:country":"NL",
    "sg:address":"Spuistraat 52",
    "sg:city":"Amsterdam",
    "sg:classifiers":[
        {
            "category":"Travel",
            "subcategory":"Hotels & Motels",
            "type":"Entertainment"
        }
    ],
    "sg:phone":"+31 20 421 5841",
    "sg:postcode":"1012 TV",
    "sg:province":"North Holland",
    "wof:name":"Tourist Inn",
    "wof:placetype":"venue"
},
  "geometry": {"coordinates":[4.892361,52.376282],"type":"Point"}
}