{
  "type": "Feature",
  "properties": {
    "iso:country":"NL",
    "sg:address":"Postbus 20",
    "sg:city":"Schiermonnikoog",
    "sg:orig_category":"Jachthavens - Jachtwerven",
    "sg:phone":"+31 519 531 544",
    "sg:postcode":"9166 ZP",
    "sg:province":"Friesland",
    "wof:name":"Oude Veerdam, De",
    "wof:placetype":"venue"
},
  "geometry": {"coordinates":[6.161215,53.477234],"type":"Point"}
}