{
  "type": "Feature",
  "properties": {
    "iso:country":"NL",
    "sg:address":"De Brauwweg 50",
    "sg:city":"Schiedam",
    "sg:orig_category":"Juridische Dienstverlening",
    "sg:phone":"+31 10 245 0537",
    "sg:postcode":"3125 AE",
    "sg:province":"South Holland",
    "wof:name":"Mr. N.G. De Leede",
    "wof:placetype":"venue"
},
  "geometry": {"coordinates":[4.408621,51.928898],"type":"Point"}
}