{
  "type": "Feature",
  "properties": {
    "addr:full":"Straelseweg 333 Venlo Limburg 5916 AB",
    "addr:housenumber":"333",
    "addr:postcode":"5916 ab",
    "addr:street":"Straelseweg",
    "iso:country":"NL",
    "sg:address":"Straelseweg 333",
    "sg:city":"Venlo",
    "sg:orig_category":"Kappers",
    "sg:phone":"+31 77 351 9168",
    "sg:postcode":"5916 AB",
    "sg:province":"Limburg",
    "wof:name":"Dames- En Herenkapsalon L'Avenir",
    "wof:placetype":"venue"
},
  "geometry": {"coordinates":[6.1879239082,51.3833312988],"type":"Point"}
}