{
  "type": "Feature",
  "properties": {
    "addr:full":"Havik 36 Etten Leur Noord-Brabant 4872 WG",
    "addr:housenumber":"36",
    "addr:postcode":"4872 wg",
    "addr:street":"Havik",
    "iso:country":"NL",
    "sg:address":"Havik 36",
    "sg:city":"Etten Leur",
    "sg:orig_category":"Administratie- En Boekhoudkantoren",
    "sg:phone":"+31 76 501 3316",
    "sg:postcode":"4872 WG",
    "sg:province":"Noord-Brabant",
    "wof:name":"Dekkers",
    "wof:placetype":"venue"
},
  "geometry": {"coordinates":[4.653313,51.571934],"type":"Point"}
}