{
  "type": "Feature",
  "properties": {
    "addr:full":"Dorpsstraat 123 Hekelingen Zuid-Holland 3209 AE",
    "addr:housenumber":"123",
    "addr:postcode":"3209 ae",
    "addr:street":"Dorpsstraat",
    "iso:country":"NL",
    "sg:address":"Dorpsstraat 123",
    "sg:city":"Hekelingen",
    "sg:orig_category":"Boekhouders",
    "sg:phone":"+31 181 646 381",
    "sg:postcode":"3209 AE",
    "sg:province":"Zuid-Holland",
    "wof:name":"Administratieburo Hekelingen Cv",
    "wof:placetype":"venue"
},
  "geometry": {"coordinates":[4.346383,51.826488],"type":"Point"}
}