{
  "type": "Feature",
  "properties": {
    "iso:country":"NL",
    "sg:address":"Postbus 1203",
    "sg:city":"'S-Hertogenbosch",
    "sg:orig_category":"Verenigingen En Stichtingen",
    "sg:phone":"+31 486 461 982",
    "sg:postcode":"5200 BG",
    "wof:name":"Brabants Heem, Sticht",
    "wof:placetype":"venue"
},
  "geometry": {"coordinates":[19.02564,47.455776],"type":"Point"}
}