{
  "type": "Feature",
  "properties": {
    "addr:full":"Marktstr 13 Winschoten Groningen 9671 BN",
    "addr:housenumber":"13",
    "addr:postcode":"9671 bn",
    "addr:street":"Marktstr",
    "iso:country":"NL",
    "sg:address":"Marktstr 13",
    "sg:city":"Winschoten",
    "sg:classifiers":[
        {
            "category":"Utilities",
            "subcategory":"Cable",
            "type":"Services"
        }
    ],
    "sg:phone":"+31 597 418 783",
    "sg:postcode":"9671 BN",
    "sg:province":"Groningen",
    "sg:tags":[
        "masseur",
        "en",
        "heilgymnasten"
    ],
    "wof:name":"2000",
    "wof:placetype":"venue"
},
  "geometry": {"coordinates":[7.041849,53.142197],"type":"Point"}
}