{
  "type": "Feature",
  "properties": {
    "addr:full":"Halfwg 36 Hendr Ido Ambacht Zuid-Holland 3341 BC",
    "addr:housenumber":"36;ido ambacht",
    "addr:postcode":"3341 bc",
    "addr:street":"Halfwg",
    "iso:country":"NL",
    "sg:address":"Halfwg 36",
    "sg:city":"Hendr Ido Ambacht",
    "sg:orig_category":"Administratie- En Boekhoudkantoren",
    "sg:phone":"+31 78 681 5398",
    "sg:postcode":"3341 BC",
    "sg:province":"Zuid-Holland",
    "sg:website":"http://www.exactadministraties.nl",
    "wof:name":"Exact Adm & Belastingaangiften",
    "wof:placetype":"venue"
},
  "geometry": {"coordinates":[-126.555511,54.485668],"type":"Point"}
}