{
  "type": "Feature",
  "properties": {
    "iso:country":"NL",
    "sg:address":"De Ververt 1166",
    "sg:city":"Wijchen",
    "sg:orig_category":"Loodgieterswerk, Verwarming And Sanitaire Installaties",
    "sg:phone":"+31 24 355 0967",
    "sg:postcode":"6605 AD",
    "sg:province":"Gelderland",
    "wof:name":"Installatiebedrijf Nicolasen",
    "wof:placetype":"venue"
},
  "geometry": {"coordinates":[5.733884,51.797417],"type":"Point"}
}