{
  "type": "Feature",
  "properties": {
    "addr:full":"Aalsmeerwg 18 Amsterdam North Holland 1059 AJ",
    "addr:housenumber":"18",
    "addr:postcode":"1059 aj",
    "addr:street":"Aalsmeerwg",
    "iso:country":"NL",
    "sg:address":"Aalsmeerwg 18",
    "sg:city":"Amsterdam",
    "sg:orig_category":"Autorijscholen",
    "sg:phone":"+31 20 615 2717",
    "sg:postcode":"1059 AJ",
    "sg:province":"North Holland",
    "wof:name":"Sabrina",
    "wof:placetype":"venue"
},
  "geometry": {"coordinates":[4.849208,52.350349],"type":"Point"}
}