{
  "type": "Feature",
  "properties": {
    "iso:country":"NL",
    "sg:address":"Schmidtstr 13",
    "sg:city":"Spaarndam",
    "sg:orig_category":"Bedrijfsopleidingen",
    "sg:phone":"+31 23 549 3409",
    "sg:postcode":"2064 LC",
    "sg:province":"Noord-Holland",
    "wof:name":"Marjon Steenbeek",
    "wof:placetype":"venue"
},
  "geometry": {"coordinates":[4.693536,52.414875],"type":"Point"}
}