{
  "type": "Feature",
  "properties": {
    "addr:full":"Hellestraat 19 Amersfoort Utrecht 3811 LK",
    "addr:housenumber":"19",
    "addr:postcode":"3811 lk",
    "addr:street":"Hellestraat",
    "iso:country":"NL",
    "sg:address":"Hellestraat 19",
    "sg:city":"Amersfoort",
    "sg:orig_category":"Werving And Selectie Van Tijdelijk Personeel And Uitzendkantoren",
    "sg:phone":"+31 900 7002503",
    "sg:postcode":"3811 LK",
    "sg:province":"Utrecht",
    "wof:name":"Tempo Team",
    "wof:placetype":"venue"
},
  "geometry": {"coordinates":[5.3862400055,52.1547851562],"type":"Point"}
}