{
  "type": "Feature",
  "properties": {
    "addr:full":"Prins Hendrikstraat 4 Zevenbergen North Brabant 4761 AH",
    "addr:housenumber":"4",
    "addr:postcode":"4761 ah",
    "addr:street":"Prins Hendrikstraat",
    "iso:country":"NL",
    "sg:address":"Prins Hendrikstraat 4",
    "sg:city":"Zevenbergen",
    "sg:classifiers":[
        {
            "category":"Retail",
            "subcategory":"Storage",
            "type":"Services"
        }
    ],
    "sg:phone":"+31 168 327 930",
    "sg:postcode":"4761 AH",
    "sg:province":"North Brabant",
    "sg:tags":[
        "opslag",
        "bewaring"
    ],
    "wof:name":"Regionaal Archief West-Brabant",
    "wof:placetype":"venue"
},
  "geometry": {"coordinates":[4.6102919579,51.6428909302],"type":"Point"}
}