{
  "type": "Feature",
  "properties": {
    "addr:full":"Boulev Heuvelink 7 Arnhem Gelderland 6828 KG",
    "addr:housenumber":"7",
    "addr:postcode":"6828 kg",
    "addr:street":"Boulev Heuvelink",
    "iso:country":"NL",
    "sg:address":"Boulev Heuvelink 7",
    "sg:city":"Arnhem",
    "sg:orig_category":"Orthopedisch Schoeisel",
    "sg:phone":"+31 26 442 5812",
    "sg:postcode":"6828 KG",
    "sg:province":"Gelderland",
    "wof:name":"Brands, Orthop Schoentechniek",
    "wof:placetype":"venue"
},
  "geometry": {"coordinates":[5.9175000191,51.9785499573],"type":"Point"}
}