{
  "type": "Feature",
  "properties": {
    "addr:full":"Jonkheer C Roelllaan 18 Eemnes Utrecht 3755 CL",
    "addr:housenumber":"18",
    "addr:postcode":"3755",
    "addr:street":"Jonkheer C Roelllaan",
    "iso:country":"NL",
    "sg:address":"Jonkheer C Roelllaan 18",
    "sg:city":"Eemnes",
    "sg:orig_category":"Metaalwerken",
    "sg:phone":"+31 35 538 9735",
    "sg:postcode":"3755 CL",
    "sg:province":"Utrecht",
    "wof:name":"Gebr. Hilhorst",
    "wof:placetype":"venue"
},
  "geometry": {"coordinates":[5.265305,52.251659],"type":"Point"}
}