{
  "type": "Feature",
  "properties": {
    "addr:full":"Zamenhofdreef 1 Utrecht Utrecht 3562 JT",
    "addr:housenumber":"1",
    "addr:postcode":"3562 jt",
    "addr:street":"Zamenhofdreef",
    "iso:country":"NL",
    "sg:address":"Zamenhofdreef 1",
    "sg:city":"Utrecht",
    "sg:orig_category":"Kappers",
    "sg:phone":"+31 30 261 4973",
    "sg:postcode":"3562 JT",
    "sg:province":"Utrecht",
    "wof:name":"Haarfijn",
    "wof:placetype":"venue"
},
  "geometry": {"coordinates":[5.1116509438,52.1147918701],"type":"Point"}
}