{
  "type": "Feature",
  "properties": {
    "addr:full":"Stadhoudersln 62 Schiedam South Holland 3116 HS",
    "addr:housenumber":"62",
    "addr:postcode":"3116 hs",
    "addr:street":"Stadhoudersln",
    "iso:country":"NL",
    "sg:address":"Stadhoudersln 62",
    "sg:city":"Schiedam",
    "sg:classifiers":[
        {
            "category":"Wholesale",
            "subcategory":"Meat",
            "type":"Manufacturing & Wholesale Goods"
        }
    ],
    "sg:phone":"+31 6 53124150",
    "sg:postcode":"3116 HS",
    "sg:province":"South Holland",
    "sg:tags":[
        "regeltechniek",
        "en",
        "meet-"
    ],
    "wof:name":"Loop-Doctor Bv",
    "wof:placetype":"venue"
},
  "geometry": {"coordinates":[4.39816,51.918472],"type":"Point"}
}