{
  "type": "Feature",
  "properties": {
    "addr:full":"Beekstr 9 Hunsel Limburg 6013 RV",
    "addr:housenumber":"9",
    "addr:postcode":"6013 rv",
    "addr:street":"Beekstr",
    "iso:country":"NL",
    "sg:address":"Beekstr 9",
    "sg:city":"Hunsel",
    "sg:orig_category":"Groepsaccommodaties",
    "sg:phone":"+31 475 565 457",
    "sg:postcode":"6013 RV",
    "sg:province":"Limburg",
    "wof:name":"Bekerhof",
    "wof:placetype":"venue"
},
  "geometry": {"coordinates":[5.813556,51.190632],"type":"Point"}
}