{
  "type": "Feature",
  "properties": {
    "iso:country":"NL",
    "sg:address":"Gorechtkade 118",
    "sg:city":"Groningen",
    "sg:orig_category":"Diverse Grafische Activiteiten",
    "sg:phone":"+31 50 313 3508",
    "sg:postcode":"9713 CJ",
    "sg:province":"Groningen",
    "wof:name":"R.L. Tienstra",
    "wof:placetype":"venue"
},
  "geometry": {"coordinates":[6.576956,53.225777],"type":"Point"}
}