{
  "type": "Feature",
  "properties": {
    "addr:full":"Industrieweg 19 Zoeterwoude Zuid-Holland 2382 NR",
    "addr:housenumber":"19",
    "addr:postcode":"2382 nr",
    "addr:street":"Industrieweg",
    "iso:country":"NL",
    "sg:address":"Industrieweg 19",
    "sg:city":"Zoeterwoude",
    "sg:classifiers":[
        {
            "category":"Retail",
            "subcategory":"Storage",
            "type":"Services"
        }
    ],
    "sg:phone":"+31 71 521 5070",
    "sg:postcode":"2382 NR",
    "sg:province":"Zuid-Holland",
    "sg:tags":[
        "opslag",
        "bewaring"
    ],
    "sg:website":"http://www.certo.nl",
    "wof:name":"Certo",
    "wof:placetype":"venue"
},
  "geometry": {"coordinates":[4.5237140656,52.139591217],"type":"Point"}
}