{
  "type": "Feature",
  "properties": {
    "iso:country":"NL",
    "sg:address":"Van Den Berghlaan 301",
    "sg:city":"Hoofddorp",
    "sg:orig_category":"Verzekeringen",
    "sg:phone":"+31 23 563 3281",
    "sg:postcode":"2132 AH",
    "sg:province":"Noord-Holland",
    "wof:name":"Assurantiekantoor P. Heikens",
    "wof:placetype":"venue"
},
  "geometry": {"coordinates":[4.704111,52.304836],"type":"Point"}
}