{
  "type": "Feature",
  "properties": {
    "addr:full":"Evertswyk 60 Zevenhuizen Gn Groningen 9354 AX",
    "addr:housenumber":"60;gn",
    "addr:postcode":"9354 ax",
    "addr:street":"Evertswyk",
    "iso:country":"NL",
    "sg:address":"Evertswyk 60",
    "sg:city":"Zevenhuizen Gn",
    "sg:orig_category":"Fotoreportages",
    "sg:phone":"+31 594 631 677",
    "sg:postcode":"9354 AX",
    "sg:province":"Groningen",
    "wof:name":"Lodewijk Ten Have",
    "wof:placetype":"venue"
},
  "geometry": {"coordinates":[6.348505,53.124569],"type":"Point"}
}