{
  "type": "Feature",
  "properties": {
    "addr:full":"Jachtln 283 Apeldoorn Gelderland 7336 AA",
    "addr:housenumber":"283",
    "addr:postcode":"7336 aa",
    "addr:street":"Gelderland",
    "iso:country":"NL",
    "sg:address":"Jachtln 283",
    "sg:city":"Apeldoorn",
    "sg:orig_category":"Schilders",
    "sg:phone":"+31 55 542 4079",
    "sg:postcode":"7336 AA",
    "sg:province":"Gelderland",
    "sg:website":"http://www.stevenjansen.nl",
    "wof:name":"Steven Jansen Bv",
    "wof:placetype":"venue"
},
  "geometry": {"coordinates":[5.93963,52.19878],"type":"Point"}
}