{
  "type": "Feature",
  "properties": {
    "addr:full":"Hof 80 Bergeyk Noord-Brabant 5571 CC",
    "addr:housenumber":"80",
    "addr:postcode":"5571 cc",
    "addr:street":"Hof",
    "iso:country":"NL",
    "sg:address":"Hof 80",
    "sg:city":"Bergeyk",
    "sg:orig_category":"Kinderkleding",
    "sg:phone":"+31 497 575 955",
    "sg:postcode":"5571 CC",
    "sg:province":"Noord-Brabant",
    "wof:name":"Kaya",
    "wof:placetype":"venue"
},
  "geometry": {"coordinates":[5.358297,51.322346],"type":"Point"}
}