{
  "type": "Feature",
  "properties": {
    "iso:country":"NL",
    "sg:address":"Katendrechtsestr 211",
    "sg:city":"Rotterdam",
    "sg:orig_category":"Verpakkingen En Verpakkingsmaterialen",
    "sg:phone":"+31 10 486 5089",
    "sg:postcode":"3072 NS",
    "sg:province":"Zuid-Holland",
    "wof:name":"Hemba, Technical Services",
    "wof:placetype":"venue"
},
  "geometry": {"coordinates":[4.478991,51.90028],"type":"Point"}
}