{
  "type": "Feature",
  "properties": {
    "addr:full":"Herenstr 11 Rhenen Utrecht 3911 JA",
    "addr:housenumber":"11",
    "addr:postcode":"3911 ja",
    "addr:street":"Herenstr",
    "iso:country":"NL",
    "sg:address":"Herenstr 11",
    "sg:city":"Rhenen",
    "sg:orig_category":"Machineonderhoud En -Reparatie",
    "sg:phone":"+31 317 619 479",
    "sg:postcode":"3911 JA",
    "sg:province":"Utrecht",
    "wof:name":"Miltenburg, A C Van",
    "wof:placetype":"venue"
},
  "geometry": {"coordinates":[5.567089,51.957729],"type":"Point"}
}