{
  "type": "Feature",
  "properties": {
    "addr:full":"Gijsbrecht Van Amstelstr 425 Hilversum North Holland 1216 CA",
    "addr:housenumber":"425",
    "addr:postcode":"1216 ca",
    "addr:street":"Gijsbrecht Van Amstelstr",
    "iso:country":"NL",
    "sg:address":"Gijsbrecht Van Amstelstr 425",
    "sg:city":"Hilversum",
    "sg:orig_category":"Boekhouders",
    "sg:phone":"+31 35 624 6675",
    "sg:postcode":"1216 CA",
    "sg:province":"North Holland",
    "wof:name":"G.F. Visser Administratie Bv",
    "wof:placetype":"venue"
},
  "geometry": {"coordinates":[5.151322,52.222721],"type":"Point"}
}