{
  "type": "Feature",
  "properties": {
    "addr:full":"Sligtmaan 2 Alphen Nb Noord-Brabant 5131 GC",
    "addr:housenumber":"2",
    "addr:postcode":"5131 gc",
    "addr:street":"Sligtmaan",
    "iso:country":"NL",
    "sg:address":"Sligtmaan 2",
    "sg:city":"Alphen Nb",
    "sg:orig_category":"Artsen - Huisartsen",
    "sg:phone":"+31 13 508 2300",
    "sg:postcode":"5131 GC",
    "sg:province":"Noord-Brabant",
    "wof:name":"Schepens, A H F M",
    "wof:placetype":"venue"
},
  "geometry": {"coordinates":[4.958561,51.485012],"type":"Point"}
}