{
  "type": "Feature",
  "properties": {
    "addr:full":"Nw Oosterstr 26 Leeuwarden Provincie Friesland 8911 KN",
    "addr:housenumber":"26",
    "addr:postcode":"8911 kn",
    "addr:street":"Provincie Friesland",
    "iso:country":"NL",
    "sg:address":"Nw Oosterstr 26",
    "sg:city":"Leeuwarden",
    "sg:orig_category":"Kappers",
    "sg:phone":"+31 58 213 1211",
    "sg:postcode":"8911 KN",
    "sg:province":"Provincie Friesland",
    "wof:name":"De Haarkunstenaars",
    "wof:placetype":"venue"
},
  "geometry": {"coordinates":[5.8015837669,53.2005996704],"type":"Point"}
}