{
  "type": "Feature",
  "properties": {
    "addr:full":"Zandstr 118 Beneden Leeuwen Gelderland 6658 CX",
    "addr:housenumber":"118",
    "addr:postcode":"6658 cx",
    "iso:country":"NL",
    "sg:address":"Zandstr 118",
    "sg:city":"Beneden Leeuwen",
    "sg:orig_category":"Juweliers",
    "sg:phone":"+31 487 593 609",
    "sg:postcode":"6658 CX",
    "sg:province":"Gelderland",
    "wof:name":"Susteren, P Van",
    "wof:placetype":"venue"
},
  "geometry": {"coordinates":[5.510484,51.881256],"type":"Point"}
}