{
  "type": "Feature",
  "properties": {
    "iso:country":"NL",
    "sg:address":"Smederij 11",
    "sg:city":"Noordwijkerhout",
    "sg:orig_category":"Fotostudio'S And Fotografen",
    "sg:phone":"+31 252 376 589",
    "sg:postcode":"2211 SM",
    "sg:province":"South Holland",
    "wof:name":"Fotografie Steven Bemelman",
    "wof:placetype":"venue"
},
  "geometry": {"coordinates":[4.490242,52.248638],"type":"Point"}
}