{
  "type": "Feature",
  "properties": {
    "addr:full":"Theresialaan 99 Vught North Brabant 5262 BM",
    "addr:housenumber":"99",
    "addr:postcode":"5262 bm",
    "addr:street":"Theresialaan",
    "iso:country":"NL",
    "sg:address":"Theresialaan 99",
    "sg:city":"Vught",
    "sg:orig_category":"Juridische Dienstverlening",
    "sg:phone":"+31 73 656 8240",
    "sg:postcode":"5262 BM",
    "sg:province":"North Brabant",
    "wof:name":"Juridisch Adviesbureau Spoor",
    "wof:placetype":"venue"
},
  "geometry": {"coordinates":[5.283122,51.649776],"type":"Point"}
}