{
  "type": "Feature",
  "properties": {
    "addr:full":"Westerwg 370B Heiloo North Holland 1852 PS",
    "addr:housenumber":"370b",
    "addr:postcode":"1852 ps",
    "iso:country":"NL",
    "sg:address":"Westerwg 370B",
    "sg:city":"Heiloo",
    "sg:orig_category":"Gordijnenateliers",
    "sg:phone":"+31 72 532 4430",
    "sg:postcode":"1852 PS",
    "sg:province":"North Holland",
    "wof:name":"Mee",
    "wof:placetype":"venue"
},
  "geometry": {"coordinates":[4.688887,52.587444],"type":"Point"}
}