{
  "type": "Feature",
  "properties": {
    "addr:full":"Kerkakkerstraat 2 Rijsbergen Noord-Brabant 4891 AG",
    "addr:housenumber":"2",
    "addr:postcode":"4891",
    "addr:street":"Kerkakkerstraat",
    "iso:country":"NL",
    "sg:address":"Kerkakkerstraat 2",
    "sg:city":"Rijsbergen",
    "sg:orig_category":"Herenmodezaken",
    "sg:phone":"+31 76 596 1298",
    "sg:postcode":"4891 AG",
    "sg:province":"Noord-Brabant",
    "wof:name":"P.A.E.M. Van Kuijck",
    "wof:placetype":"venue"
},
  "geometry": {"coordinates":[4.700817,51.515957],"type":"Point"}
}