{
  "type": "Feature",
  "properties": {
    "addr:full":"Dorpsstr 183 Winkel Noord-Holland 1731 RE",
    "addr:housenumber":"183",
    "addr:postcode":"1731 re",
    "iso:country":"NL",
    "sg:address":"Dorpsstr 183",
    "sg:city":"Winkel",
    "sg:classifiers":[
        {
            "category":"Retail",
            "subcategory":"Auto Repair",
            "type":"Services"
        }
    ],
    "sg:phone":"+31 224 541 744",
    "sg:postcode":"1731 RE",
    "sg:province":"Noord-Holland",
    "sg:tags":[
        "garage"
    ],
    "wof:name":"Groenewoud Bv",
    "wof:placetype":"venue"
},
  "geometry": {"coordinates":[-89.62237500000001,40.348873],"type":"Point"}
}