{
  "type": "Feature",
  "properties": {
    "iso:country":"NL",
    "sg:address":"Steenstr 71A",
    "sg:city":"Arnhem",
    "sg:orig_category":"Woningbureaus",
    "sg:phone":"+31 26 370 3666",
    "sg:postcode":"6828 CD",
    "sg:province":"Gelderland",
    "sg:website":"http://www.rotsvast.nl",
    "wof:name":"Rots-Vast Groep",
    "wof:placetype":"venue"
},
  "geometry": {"coordinates":[5.9174790382,51.9841117859],"type":"Point"}
}