{
  "type": "Feature",
  "properties": {
    "addr:full":"Tamarindestr 25 Terneuzen Zeeland 4537 XG",
    "addr:housenumber":"25",
    "addr:postcode":"4537 xg",
    "addr:street":"Tamarindestr",
    "iso:country":"NL",
    "sg:address":"Tamarindestr 25",
    "sg:city":"Terneuzen",
    "sg:orig_category":"Onroerende Goederen",
    "sg:phone":"+31 115 616 767",
    "sg:postcode":"4537 XG",
    "sg:province":"Zeeland",
    "wof:name":"Waterpolder, De",
    "wof:placetype":"venue"
},
  "geometry": {"coordinates":[3.835013,51.323032],"type":"Point"}
}