{
  "type": "Feature",
  "properties": {
    "iso:country":"NL",
    "sg:address":"Oude Kijk In 'T Jatstr 52",
    "sg:city":"Groningen",
    "sg:orig_category":"Kantoorartikelen",
    "sg:phone":"+31 50 314 4002",
    "sg:postcode":"9712 EL",
    "sg:province":"Groningen",
    "wof:name":"Donkel & Donkel Copieersystemen Bv",
    "wof:placetype":"venue"
},
  "geometry": {"coordinates":[6.563680172,53.2214813232],"type":"Point"}
}