{
  "type": "Feature",
  "properties": {
    "addr:full":"De Koperwiek 35 Zuidhorn Groningen 9801 JG",
    "addr:housenumber":"35",
    "addr:postcode":"9801 jg",
    "addr:street":"De Koperwiek",
    "iso:country":"NL",
    "sg:address":"De Koperwiek 35",
    "sg:city":"Zuidhorn",
    "sg:orig_category":"Artsen And Specialisten",
    "sg:phone":"+31 594 503 231",
    "sg:postcode":"9801 JG",
    "sg:province":"Groningen",
    "wof:name":"J. Sarolea",
    "wof:placetype":"venue"
},
  "geometry": {"coordinates":[6.399074,53.247997],"type":"Point"}
}