{
  "type": "Feature",
  "properties": {
    "addr:full":"Choorstraat 16 'S Hertogenbosch Noord-Brabant 5211 KZ",
    "addr:housenumber":"16",
    "addr:postcode":"5211 kz",
    "addr:street":"Choorstraat;' S",
    "iso:country":"NL",
    "sg:address":"Choorstraat 16",
    "sg:city":"'S Hertogenbosch",
    "sg:orig_category":"Musea And Historische Gebouwen",
    "sg:phone":"+31 73 613 3216",
    "sg:postcode":"5211 KZ",
    "sg:province":"Noord-Brabant",
    "wof:name":"Museum Slager",
    "wof:placetype":"venue"
},
  "geometry": {"coordinates":[5.310014,51.687756],"type":"Point"}
}