{
  "type": "Feature",
  "properties": {
    "addr:full":"Sint Agathaplein 27 Boekel Noord-Brabant 5427 AA",
    "addr:housenumber":"27",
    "addr:postcode":"5427 aa",
    "addr:street":"Sint Agathaplein",
    "iso:country":"NL",
    "sg:address":"Sint Agathaplein 27",
    "sg:city":"Boekel",
    "sg:orig_category":"Verlichting And Huishoudartikelen",
    "sg:phone":"+31 492 321 987",
    "sg:postcode":"5427 AA",
    "sg:province":"Noord-Brabant",
    "wof:name":"Woninginrichting A. Snijders",
    "wof:placetype":"venue"
},
  "geometry": {"coordinates":[5.672976,51.602589],"type":"Point"}
}