{
  "type": "Feature",
  "properties": {
    "addr:full":"Cypergrasweg 6 Almere Flevoland 1313 AL",
    "addr:housenumber":"6;1313",
    "addr:postcode":"al",
    "addr:street":"Cypergrasweg;Flevoland",
    "iso:country":"NL",
    "sg:address":"Cypergrasweg 6",
    "sg:city":"Almere",
    "sg:orig_category":"Wasserettes And Stomerijen",
    "sg:phone":"+31 36 533 0944",
    "sg:postcode":"1313 AL",
    "sg:province":"Flevoland",
    "wof:name":"Stomerij Medo",
    "wof:placetype":"venue"
},
  "geometry": {"coordinates":[5.2034168243,52.3852386475],"type":"Point"}
}