{
  "type": "Feature",
  "properties": {
    "addr:full":"Diergaardesngl 56 Rotterdam South Holland 3014 AC",
    "addr:housenumber":"56",
    "addr:postcode":"3014 ac",
    "addr:street":"Diergaardesngl",
    "iso:country":"NL",
    "sg:address":"Diergaardesngl 56",
    "sg:city":"Rotterdam",
    "sg:orig_category":"Verenigingen En Stichtingen",
    "sg:phone":"+31 6 24226006",
    "sg:postcode":"3014 AC",
    "sg:province":"South Holland",
    "wof:name":"Akyazili",
    "wof:placetype":"venue"
},
  "geometry": {"coordinates":[4.478455,51.922836],"type":"Point"}
}