{
  "type": "Feature",
  "properties": {
    "addr:full":"Burg De Bruinelaan 74 Zwijndrecht Zuid-Holland 3331 AG",
    "addr:housenumber":"74",
    "addr:postcode":"3331",
    "addr:street":"Bruinelaan",
    "iso:country":"NL",
    "sg:address":"Burg De Bruinelaan 74",
    "sg:city":"Zwijndrecht",
    "sg:classifiers":[
        {
            "category":"Retail",
            "subcategory":"Photofinishing",
            "type":"Services"
        }
    ],
    "sg:phone":"+31 78 619 3063",
    "sg:postcode":"3331 AG",
    "sg:province":"Zuid-Holland",
    "sg:tags":[
        "foto",
        "film"
    ],
    "wof:name":"Foto Gaaf",
    "wof:placetype":"venue"
},
  "geometry": {"coordinates":[4.648683,51.817387],"type":"Point"}
}