{
  "type": "Feature",
  "properties": {
    "addr:full":"Westeinde 26 Vriezenveen Overijssel 7671 CC",
    "addr:housenumber":"26",
    "addr:postcode":"7671 cc",
    "addr:street":"Westeinde",
    "iso:country":"NL",
    "sg:address":"Westeinde 26",
    "sg:city":"Vriezenveen",
    "sg:orig_category":"Bloemen And Planten",
    "sg:phone":"+31 546 564 950",
    "sg:postcode":"7671 CC",
    "sg:province":"Overijssel",
    "wof:name":"De Bloemendoos",
    "wof:placetype":"venue"
},
  "geometry": {"coordinates":[6.627155,52.412907],"type":"Point"}
}