{
  "type": "Feature",
  "properties": {
    "addr:full":"Berkendreef 47 Renkum Gelderland 6871 LD",
    "addr:housenumber":"47",
    "addr:postcode":"6871 ld",
    "addr:street":"Berkendreef;Gelderland",
    "iso:country":"NL",
    "sg:address":"Berkendreef 47",
    "sg:city":"Renkum",
    "sg:orig_category":"Autorijscholen",
    "sg:phone":"+31 317 316 062",
    "sg:postcode":"6871 LD",
    "sg:province":"Gelderland",
    "sg:website":"http://www.teamvandijk.nl",
    "wof:name":"Team Van Dijk",
    "wof:placetype":"venue"
},
  "geometry": {"coordinates":[5.744363,51.985371],"type":"Point"}
}