{
  "type": "Feature",
  "properties": {
    "addr:full":"Koningslaan 44 Amsterdam Noord-Holland 1075 AE",
    "addr:housenumber":"44",
    "addr:postcode":"1075 ae",
    "addr:street":"Koningslaan",
    "iso:country":"NL",
    "sg:address":"Koningslaan 44",
    "sg:city":"Amsterdam",
    "sg:orig_category":"Ambassades And Consulaten",
    "sg:phone":"+31 20 676 4343",
    "sg:postcode":"1075 AE",
    "sg:province":"Noord-Holland",
    "wof:name":"Consulaat Van Groot Brittannie En Noord Ierland",
    "wof:placetype":"venue"
},
  "geometry": {"coordinates":[4.862941,52.355537],"type":"Point"}
}