{
  "type": "Feature",
  "properties": {
    "addr:full":"Marggraffstr 26 Vught North Brabant 5262 AV",
    "addr:housenumber":"26",
    "addr:postcode":"5262 av",
    "addr:street":"Marggraffstr",
    "iso:country":"NL",
    "sg:address":"Marggraffstr 26",
    "sg:city":"Vught",
    "sg:orig_category":"Verenigingen En Stichtingen",
    "sg:phone":"+31 73 657 8196",
    "sg:postcode":"5262 AV",
    "sg:province":"North Brabant",
    "wof:name":"Landelijke Organisatie Voor Veiligheid En Respect",
    "wof:placetype":"venue"
},
  "geometry": {"coordinates":[5.290521,51.653954],"type":"Point"}
}