{
  "type": "Feature",
  "properties": {
    "addr:full":"Tunisstr 16 Hengelo Ov Overijssel 7559 CB",
    "addr:housenumber":"16",
    "addr:postcode":"7559 cb",
    "addr:street":"Tunisstr;Ov",
    "iso:country":"NL",
    "sg:address":"Tunisstr 16",
    "sg:city":"Hengelo Ov",
    "sg:orig_category":"Adviesbureaus Bedrijfsorganisatie",
    "sg:phone":"+31 74 278 2620",
    "sg:postcode":"7559 CB",
    "sg:province":"Overijssel",
    "sg:website":"http://www.handelton.nl",
    "wof:name":"H\u00e4ndelton Management Advies Bv",
    "wof:placetype":"venue"
},
  "geometry": {"coordinates":[6.813063,52.290207],"type":"Point"}
}