{
  "type": "Feature",
  "properties": {
    "addr:full":"Dorpswg 52 Ysselmuiden Overijssel 8271 BN",
    "addr:housenumber":"52",
    "addr:postcode":"8271 bn",
    "addr:street":"Dorpswg;Overijssel",
    "iso:country":"NL",
    "sg:address":"Dorpswg 52",
    "sg:city":"Ysselmuiden",
    "sg:orig_category":"Verenigingen En Stichtingen",
    "sg:phone":"+31 38 355 6987",
    "sg:postcode":"8271 BN",
    "sg:province":"Overijssel",
    "wof:name":"Dagverblijven Kampen Eo, Sticht",
    "wof:placetype":"venue"
},
  "geometry": {"coordinates":[5.927726,52.565365],"type":"Point"}
}