{
  "type": "Feature",
  "properties": {
    "addr:full":"Haarlemmerstr 231 Leiden South Holland 2312 DR",
    "addr:housenumber":"231",
    "addr:postcode":"2312 dr",
    "iso:country":"NL",
    "sg:address":"Haarlemmerstr 231",
    "sg:city":"Leiden",
    "sg:orig_category":"Juweliers",
    "sg:phone":"+31 71 514 2206",
    "sg:postcode":"2312 DR",
    "sg:province":"South Holland",
    "wof:name":"Has Gold-2-3",
    "wof:placetype":"venue"
},
  "geometry": {"coordinates":[4.495927,52.160416],"type":"Point"}
}