{
  "type": "Feature",
  "properties": {
    "addr:full":"Napoleonswg 6 Haelen Limburg 6081 AD",
    "addr:housenumber":"6",
    "addr:postcode":"6081 ad",
    "addr:street":"Napoleonswg",
    "iso:country":"NL",
    "sg:address":"Napoleonswg 6",
    "sg:city":"Haelen",
    "sg:orig_category":"Oud Metaal",
    "sg:phone":"+31 475 591 722",
    "sg:postcode":"6081 AD",
    "sg:province":"Limburg",
    "wof:name":"Menten, P",
    "wof:placetype":"venue"
},
  "geometry": {"coordinates":[5.9442601204,51.2246627808],"type":"Point"}
}