{
  "type": "Feature",
  "properties": {
    "iso:country":"NL",
    "sg:address":"Talmalaan 42",
    "sg:city":"Soest",
    "sg:orig_category":"Kinderopvang Behalve Thuis",
    "sg:phone":"+31 35 602 5307",
    "sg:postcode":"3761 AN",
    "sg:province":"Utrecht",
    "wof:name":"Kinderdagverblijf Het Kasteel",
    "wof:placetype":"venue"
},
  "geometry": {"coordinates":[5.29742,52.181194],"type":"Point"}
}