{
  "type": "Feature",
  "properties": {
    "addr:full":"Talmalaan 42 Soest Utrecht 3761 AN",
    "addr:housenumber":"42",
    "addr:postcode":"3761 an",
    "addr:street":"Talmalaan",
    "iso:country":"NL",
    "sg:address":"Talmalaan 42",
    "sg:city":"Soest",
    "sg:orig_category":"Kinderopvang Behalve Thuis",
    "sg:phone":"+31 35 602 5307",
    "sg:postcode":"3761 AN",
    "sg:province":"Utrecht",
    "wof:name":"Kinderdagverblijf Het Kasteel",
    "wof:placetype":"venue"
},
  "geometry": {"coordinates":[5.29742,52.181194],"type":"Point"}
}