{
  "type": "Feature",
  "properties": {
    "addr:full":"Oostereinde 3 Winschoten Groningen 9672 TB",
    "addr:housenumber":"3",
    "addr:postcode":"9672 tb",
    "addr:street":"Oostereinde",
    "iso:country":"NL",
    "sg:address":"Oostereinde 3",
    "sg:city":"Winschoten",
    "sg:orig_category":"Autopoetsbedrijven",
    "sg:phone":"+31 597 424 379",
    "sg:postcode":"9672 TB",
    "sg:province":"Groningen",
    "wof:name":"Smith Carcleaning",
    "wof:placetype":"venue"
},
  "geometry": {"coordinates":[7.067523,53.153843],"type":"Point"}
}