{
  "type": "Feature",
  "properties": {
    "addr:full":"V Rynwg 3 Ryswyk Zh Zuid-Holland 2286 KC",
    "addr:housenumber":"3",
    "addr:postcode":"2286 kc",
    "addr:street":"Rynwg",
    "iso:country":"NL",
    "sg:address":"V Rynwg 3",
    "sg:city":"Ryswyk Zh",
    "sg:orig_category":"Schilders",
    "sg:phone":"+31 15 213 2724",
    "sg:postcode":"2286 KC",
    "sg:province":"Zuid-Holland",
    "wof:name":"Jansen, R",
    "wof:placetype":"venue"
},
  "geometry": {"coordinates":[4.32436,52.037251],"type":"Point"}
}