{
  "type": "Feature",
  "properties": {
    "iso:country":"NL",
    "sg:address":"Theresiastraat 97",
    "sg:city":"'S Gravenhage",
    "sg:orig_category":"Banken And Kredietinstellingen",
    "sg:phone":"+31 70 383 9830",
    "sg:postcode":"2593 AC",
    "sg:province":"South Holland",
    "wof:name":"Postkantoor",
    "wof:placetype":"venue"
},
  "geometry": {"coordinates":[4.34266,52.086121],"type":"Point"}
}