{
  "type": "Feature",
  "properties": {
    "addr:full":"L.J. Costerstraat 53 Venlo Limburg 5916 PR",
    "addr:housenumber":"53",
    "addr:postcode":"5916 pr",
    "addr:street":"L.J. Costerstraat",
    "iso:country":"NL",
    "sg:address":"L.J. Costerstraat 53",
    "sg:city":"Venlo",
    "sg:orig_category":"Autoverhuur",
    "sg:phone":"+31 77 321 1469",
    "sg:postcode":"5916 PR",
    "sg:province":"Limburg",
    "wof:name":"Sixt Rent A Car",
    "wof:placetype":"venue"
},
  "geometry": {"coordinates":[6.184508,51.391132],"type":"Point"}
}