{
  "type": "Feature",
  "properties": {
    "iso:country":"NL",
    "sg:address":"J C Van Hattumweg 13",
    "sg:city":"Amstelveen",
    "sg:orig_category":"Bloemen- And Plantenteelt",
    "sg:phone":"+31 20 441 2124",
    "sg:postcode":"1187 ZN",
    "sg:province":"Noord-Holland",
    "wof:name":"Rozenkwekerij C.A.H. Brockhoff",
    "wof:placetype":"venue"
},
  "geometry": {"coordinates":[4.816541,52.274826],"type":"Point"}
}