{
  "type": "Feature",
  "properties": {
    "addr:full":"K Jansstr 2 Haarlem Noord-Holland 2011 JR",
    "addr:housenumber":"2",
    "addr:postcode":"2011 jr",
    "addr:street":"Jansstr",
    "iso:country":"NL",
    "sg:address":"K Jansstr 2",
    "sg:city":"Haarlem",
    "sg:orig_category":"Projectinrichting",
    "sg:phone":"+31 23 532 7001",
    "sg:postcode":"2011 JR",
    "sg:province":"Noord-Holland",
    "wof:name":"Duijn & Zn",
    "wof:placetype":"venue"
},
  "geometry": {"coordinates":[4.638441,52.384537],"type":"Point"}
}