{
  "type": "Feature",
  "properties": {
    "addr:full":"Langebuurt 7 Uitgeest Noord-Holland 1911 AS",
    "addr:housenumber":"7",
    "addr:postcode":"1911 as",
    "addr:street":"Langebuurt",
    "iso:country":"NL",
    "sg:address":"Langebuurt 7",
    "sg:city":"Uitgeest",
    "sg:orig_category":"Verhuur",
    "sg:phone":"+31 251 312 617",
    "sg:postcode":"1911 AS",
    "sg:province":"Noord-Holland",
    "wof:name":"Vreeburg",
    "wof:placetype":"venue"
},
  "geometry": {"coordinates":[4.714992,52.528522],"type":"Point"}
}