{
  "type": "Feature",
  "properties": {
    "addr:full":"Maandereind 56 Ede Gld Gelderland 6711 AE",
    "addr:housenumber":"56",
    "addr:postcode":"6711 ae",
    "addr:street":"Maandereind;Gld Gelderland",
    "iso:country":"NL",
    "sg:address":"Maandereind 56",
    "sg:city":"Ede Gld",
    "sg:orig_category":"Werving And Selectie Van Tijdelijk Personeel And Uitzendkantoren",
    "sg:phone":"+31 318 619 261",
    "sg:postcode":"6711 AE",
    "sg:province":"Gelderland",
    "wof:name":"Accord",
    "wof:placetype":"venue"
},
  "geometry": {"coordinates":[5.6687808037,52.0423164368],"type":"Point"}
}