{
  "type": "Feature",
  "properties": {
    "addr:full":"W De Zwygerln 16 Hoevelaken Gelderland 3871 CE",
    "addr:housenumber":"16",
    "addr:postcode":"3871 ce",
    "addr:street":"W De Zwygerln;Gelderland",
    "iso:country":"NL",
    "sg:address":"W De Zwygerln 16",
    "sg:city":"Hoevelaken",
    "sg:orig_category":"Kantoor- En Secretariaatsservice",
    "sg:phone":"+31 33 257 1709",
    "sg:postcode":"3871 CE",
    "sg:province":"Gelderland",
    "wof:name":"Franchette Management Support",
    "wof:placetype":"venue"
},
  "geometry": {"coordinates":[5.457736969,52.1758308411],"type":"Point"}
}