{
  "type": "Feature",
  "properties": {
    "iso:country":"NL",
    "sg:address":"Wikkestr 19",
    "sg:city":"Riethoven",
    "sg:orig_category":"Webdesign Bureaus",
    "sg:phone":"+31 6 51526825",
    "sg:postcode":"5561 AE",
    "sg:province":"Noord-Brabant",
    "sg:website":"http://www.dehomepagefabriek.nl",
    "wof:name":"Homepagefabriek, De",
    "wof:placetype":"venue"
},
  "geometry": {"coordinates":[5.3873820305,51.3558158875],"type":"Point"}
}