{
  "type": "Feature",
  "properties": {
    "addr:full":"Capellehof 10 Spanbroek Noord-Holland 1715 EV",
    "addr:housenumber":"10",
    "addr:postcode":"1715 ev",
    "addr:street":"Capellehof",
    "iso:country":"NL",
    "sg:address":"Capellehof 10",
    "sg:city":"Spanbroek",
    "sg:orig_category":"Apotheken",
    "sg:phone":"+31 226 352 886",
    "sg:postcode":"1715 EV",
    "sg:province":"Noord-Holland",
    "wof:name":"West Friesland",
    "wof:placetype":"venue"
},
  "geometry": {"coordinates":[4.947485,52.70232],"type":"Point"}
}