{
  "type": "Feature",
  "properties": {
    "addr:full":"Munnikenweg 26 Berkel En Rodenrijs South Holland 2651 LZ",
    "addr:housenumber":"26",
    "addr:postcode":"2651 lz",
    "addr:street":"Munnikenweg",
    "iso:country":"NL",
    "sg:address":"Munnikenweg 26",
    "sg:city":"Berkel En Rodenrijs",
    "sg:orig_category":"Bloemen And Planten",
    "sg:phone":"+31 10 511 5235",
    "sg:postcode":"2651 LZ",
    "sg:province":"South Holland",
    "wof:name":"Leo Ammerlaan Bv",
    "wof:placetype":"venue"
},
  "geometry": {"coordinates":[4.486168,52.030849],"type":"Point"}
}