{
  "type": "Feature",
  "properties": {
    "addr:full":"Luyksgestelstr 8 Tilburg Noord-Brabant 5045 XG",
    "addr:housenumber":"8",
    "addr:postcode":"5045 xg",
    "addr:street":"Luyksgestelstr",
    "iso:country":"NL",
    "sg:address":"Luyksgestelstr 8",
    "sg:city":"Tilburg",
    "sg:orig_category":"Loopbaanbegeleiding",
    "sg:phone":"+31 13 571 2544",
    "sg:postcode":"5045 XG",
    "sg:province":"Noord-Brabant",
    "wof:name":"L'Etoile",
    "wof:placetype":"venue"
},
  "geometry": {"coordinates":[4.998977,51.586475],"type":"Point"}
}