{
  "type": "Feature",
  "properties": {
    "addr:full":"Ondernemingswg 1 Mydrecht Utrecht 3641 RZ",
    "addr:housenumber":"1;3641",
    "addr:postcode":"rz",
    "addr:street":"Ondernemingswg",
    "iso:country":"NL",
    "sg:address":"Ondernemingswg 1",
    "sg:city":"Mydrecht",
    "sg:orig_category":"Autolakken",
    "sg:phone":"+31 297 288 441",
    "sg:postcode":"3641 RZ",
    "sg:province":"Utrecht",
    "wof:name":"Alkemade Autolakken Vof",
    "wof:placetype":"venue"
},
  "geometry": {"coordinates":[4.879412,52.205437],"type":"Point"}
}