{
  "type": "Feature",
  "properties": {
    "addr:full":"Gerbrandypln 1 Zwyndrecht Zuid-Holland 3332 XA",
    "addr:housenumber":"1",
    "addr:postcode":"3332 xa",
    "addr:street":"Gerbrandypln",
    "iso:country":"NL",
    "sg:address":"Gerbrandypln 1",
    "sg:city":"Zwyndrecht",
    "sg:orig_category":"Zonnebank- En Solariumcentra",
    "sg:phone":"+31 78 620 9740",
    "sg:postcode":"3332 XA",
    "sg:province":"Zuid-Holland",
    "wof:name":"Ergoline Zwijndrecht",
    "wof:placetype":"venue"
},
  "geometry": {"coordinates":[4.65566,51.821232],"type":"Point"}
}