{
  "type": "Feature",
  "properties": {
    "addr:full":"Zeilmakerstr 37 Amsterdam Noord-Holland 1013 DJ",
    "addr:housenumber":"37",
    "addr:postcode":"1013 dj",
    "addr:street":"Zeilmakerstr",
    "iso:country":"NL",
    "sg:address":"Zeilmakerstr 37",
    "sg:city":"Amsterdam",
    "sg:orig_category":"Hypotheken",
    "sg:phone":"+31 20 626 0018",
    "sg:postcode":"1013 DJ",
    "sg:province":"Noord-Holland",
    "sg:website":"http://www.actafinance.nl",
    "wof:name":"Acta",
    "wof:placetype":"venue"
},
  "geometry": {"coordinates":[4.889887,52.384315],"type":"Point"}
}