{
  "type": "Feature",
  "properties": {
    "addr:full":"Struytse Hoeck 42 Hellevoetsluis South Holland 3224 HB",
    "addr:housenumber":"42",
    "addr:postcode":"3224 hb",
    "addr:street":"Struytse Hoeck",
    "iso:country":"NL",
    "sg:address":"Struytse Hoeck 42",
    "sg:city":"Hellevoetsluis",
    "sg:orig_category":"Boekhandels",
    "sg:phone":"+31 181 311 032",
    "sg:postcode":"3224 HB",
    "sg:province":"South Holland",
    "sg:website":"http://www.edelboek.nl",
    "wof:name":"Edel",
    "wof:placetype":"venue"
},
  "geometry": {"coordinates":[4.14519,51.829845],"type":"Point"}
}