{
  "type": "Feature",
  "properties": {
    "iso:country":"NL",
    "sg:address":"Dorpstr 49",
    "sg:city":"Heythuysen",
    "sg:orig_category":"Opticiens",
    "sg:phone":"+31 475 492 295",
    "sg:postcode":"6093 EB",
    "sg:province":"Limburg",
    "wof:name":"Aerle, Van",
    "wof:placetype":"venue"
},
  "geometry": {"coordinates":[5.8984971046,51.250289917],"type":"Point"}
}