{
  "type": "Feature",
  "properties": {
    "iso:country":"NL",
    "sg:address":"Gageldonksewg 1",
    "sg:city":"Breda",
    "sg:classifiers":[
        {
            "category":"Wholesale",
            "subcategory":"Motor Vehicles",
            "type":"Manufacturing & Wholesale Goods"
        }
    ],
    "sg:phone":"+31 76 541 7651",
    "sg:postcode":"4815 PD",
    "sg:province":"Noord-Brabant",
    "sg:tags":[
        "scooter",
        "en"
    ],
    "wof:name":"V-Twin Workshop",
    "wof:placetype":"venue"
},
  "geometry": {"coordinates":[4.729099,51.599339],"type":"Point"}
}