{
  "type": "Feature",
  "properties": {
    "iso:country":"NL",
    "sg:address":"Vaartwg 83",
    "sg:city":"Lelystad",
    "sg:orig_category":"Boten",
    "sg:phone":"+31 320 261 363",
    "sg:postcode":"8243 PD",
    "sg:province":"NL.",
    "wof:name":"Kappa Marine",
    "wof:placetype":"venue"
},
  "geometry": {"coordinates":[5.438577,52.49884],"type":"Point"}
}