{
  "type": "Feature",
  "properties": {
    "iso:country":"NL",
    "sg:address":"Molendijk 50",
    "sg:city":"Oud Beijerland",
    "sg:orig_category":"Babyartikelen Detailhandel",
    "sg:phone":"+31 186 614 844",
    "sg:postcode":"3262 AL",
    "sg:province":"Zuid-Holland",
    "wof:name":"Modecentrum Bas Hollaar Bv",
    "wof:placetype":"venue"
},
  "geometry": {"coordinates":[4.408982,51.827152],"type":"Point"}
}