{
  "type": "Feature",
  "properties": {
    "addr:full":"Fokkerstr 16 Hoogeveen Provincie Drenthe 7903 AP",
    "addr:housenumber":"16",
    "addr:postcode":"7903 ap",
    "addr:street":"Fokkerstr;Provincie",
    "iso:country":"NL",
    "sg:address":"Fokkerstr 16",
    "sg:city":"Hoogeveen",
    "sg:orig_category":"Milieu",
    "sg:phone":"+31 528 229 922",
    "sg:postcode":"7903 AP",
    "sg:province":"Provincie Drenthe",
    "wof:name":"Gansewinkel Ned, Van",
    "wof:placetype":"venue"
},
  "geometry": {"coordinates":[6.515096,52.738316],"type":"Point"}
}