{
  "type": "Feature",
  "properties": {
    "addr:full":"Westrupstraat 10 Sleen Provincie Drenthe 7841 AZ",
    "addr:housenumber":"10",
    "addr:postcode":"7841",
    "addr:street":"Westrupstraat;Provincie Drenthe",
    "iso:country":"NL",
    "sg:address":"Westrupstraat 10",
    "sg:city":"Sleen",
    "sg:classifiers":[
        {
            "category":"Education",
            "subcategory":"Preschool",
            "type":"Public Place"
        }
    ],
    "sg:phone":"+31 591 361 910",
    "sg:postcode":"7841 AZ",
    "sg:province":"Provincie Drenthe",
    "sg:tags":[
        "kleuteronderwijs",
        "basis-"
    ],
    "wof:name":"Christelijke Basisschool De Fontein",
    "wof:placetype":"venue"
},
  "geometry": {"coordinates":[6.800745,52.768173],"type":"Point"}
}