{
  "type": "Feature",
  "properties": {
    "iso:country":"NL",
    "sg:address":"Vismarkt 4",
    "sg:city":"Hulst",
    "sg:orig_category":"Schoenen",
    "sg:phone":"+31 114 313 314",
    "sg:postcode":"4561 AZ",
    "sg:province":"Zeeland",
    "wof:name":"Kramers",
    "wof:placetype":"venue"
},
  "geometry": {"coordinates":[4.051567,51.281639],"type":"Point"}
}