{
  "type": "Feature",
  "properties": {
    "iso:country":"NL",
    "sg:address":"Karel Schaapstraat 44",
    "sg:city":"Vriezenveen",
    "sg:orig_category":"Fotostudio'S And Fotografen",
    "sg:phone":"+31 546 561 840",
    "sg:postcode":"7672 AK",
    "sg:province":"Overijssel",
    "wof:name":"Fotografie Bart Wieldraaijer",
    "wof:placetype":"venue"
},
  "geometry": {"coordinates":[6.610848,52.411961],"type":"Point"}
}