{
  "type": "Feature",
  "properties": {
    "iso:country":"NL",
    "sg:address":"Witte De Withstraat 42",
    "sg:city":"Rotterdam",
    "sg:orig_category":"Kappers",
    "sg:phone":"+31 10 413 8877",
    "sg:postcode":"3012 BR",
    "sg:province":"Zuid-Holland",
    "wof:name":"Kapsalon Haar Van Boven",
    "wof:placetype":"venue"
},
  "geometry": {"coordinates":[4.4774308205,51.9155426025],"type":"Point"}
}