{
  "type": "Feature",
  "properties": {
    "iso:country":"NL",
    "sg:address":"Poolsterstraat 124",
    "sg:city":"Rotterdam",
    "sg:orig_category":"Boekenuitgeverijen",
    "sg:phone":"+31 10 455 9398",
    "sg:postcode":"3067  L",
    "sg:province":"Zuid-Holland",
    "wof:name":"Bruna",
    "wof:placetype":"venue"
},
  "geometry": {"coordinates":[4.552844,51.950203],"type":"Point"}
}