{
  "type": "Feature",
  "properties": {
    "addr:full":"Past Lemmensstr 5 Ulvenhout Noord-Brabant 4851 CT",
    "addr:housenumber":"5",
    "addr:postcode":"4851 ct",
    "iso:country":"NL",
    "sg:address":"Past Lemmensstr 5",
    "sg:city":"Ulvenhout",
    "sg:orig_category":"Bestratingen",
    "sg:phone":"+31 76 561 2649",
    "sg:postcode":"4851 CT",
    "sg:province":"Noord-Brabant",
    "wof:name":"Martens, Gebr",
    "wof:placetype":"venue"
},
  "geometry": {"coordinates":[4.796382,51.550636],"type":"Point"}
}