{
  "type": "Feature",
  "properties": {
    "addr:full":"J V Campenpln 41 Rotterdam Zuid-Holland 3067 LA",
    "addr:housenumber":"41",
    "addr:postcode":"3067 la",
    "addr:street":"J;Campenpln",
    "iso:country":"NL",
    "sg:address":"J V Campenpln 41",
    "sg:city":"Rotterdam",
    "sg:orig_category":"Zonnebank- En Solariumcentra",
    "sg:phone":"+31 10 220 1324",
    "sg:postcode":"3067 LA",
    "sg:province":"Zuid-Holland",
    "sg:website":"http://www.allesinrotterdam.nl/ergoline",
    "wof:name":"Ergoline Zonnestudio",
    "wof:placetype":"venue"
},
  "geometry": {"coordinates":[4.55193,51.944969],"type":"Point"}
}