{
  "type": "Feature",
  "properties": {
    "addr:full":"Binderseind 20A Gemert North Brabant 5421 CJ",
    "addr:housenumber":"20a",
    "addr:postcode":"5421 cj",
    "addr:street":"Binderseind",
    "iso:country":"NL",
    "sg:address":"Binderseind 20A",
    "sg:city":"Gemert",
    "sg:orig_category":"Geschenkartikelen",
    "sg:phone":"+31 492 365 179",
    "sg:postcode":"5421 CJ",
    "sg:province":"North Brabant",
    "wof:name":"Mirell",
    "wof:placetype":"venue"
},
  "geometry": {"coordinates":[5.683708,51.552517],"type":"Point"}
}