{
  "type": "Feature",
  "properties": {
    "addr:full":"Hyacinthweg 71 'S Gravenhage South Holland 2565 RG",
    "addr:housenumber":"71",
    "addr:postcode":"2565 rg",
    "addr:street":"Hyacinthweg;' S Gravenhage",
    "iso:country":"NL",
    "sg:address":"Hyacinthweg 71",
    "sg:city":"'S Gravenhage",
    "sg:orig_category":"Verzekeringen",
    "sg:phone":"+31 70 325 2255",
    "sg:postcode":"2565 RG",
    "sg:province":"South Holland",
    "wof:name":"Van Den Hoogen Ass",
    "wof:placetype":"venue"
},
  "geometry": {"coordinates":[4.250384,52.070015],"type":"Point"}
}