{
  "type": "Feature",
  "properties": {
    "addr:full":"Bertelindisln 29 Waalre Noord-Brabant 5581 CS",
    "addr:housenumber":"29",
    "addr:postcode":"5581 cs",
    "addr:street":"Bertelindisln",
    "iso:country":"NL",
    "sg:address":"Bertelindisln 29",
    "sg:city":"Waalre",
    "sg:orig_category":"Woninginrichting",
    "sg:phone":"+31 40 221 8497",
    "sg:postcode":"5581 CS",
    "sg:province":"Noord-Brabant",
    "wof:name":"Welbo",
    "wof:placetype":"venue"
},
  "geometry": {"coordinates":[5.4487009048,51.3892669678],"type":"Point"}
}