{
  "type": "Feature",
  "properties": {
    "iso:country":"NL",
    "sg:address":"Tirolstr 113",
    "sg:city":"Alkmaar",
    "sg:orig_category":"Honden- En Kattentrimsalons",
    "sg:phone":"+31 72 561 9060",
    "sg:postcode":"1827 ET",
    "sg:province":"North Holland",
    "wof:name":"True Model",
    "wof:placetype":"venue"
},
  "geometry": {"coordinates":[4.76508,52.663528],"type":"Point"}
}