{
  "type": "Feature",
  "properties": {
    "addr:full":"Marconistr 13 Zevenaar Gelderland 6902 PC",
    "addr:housenumber":"13",
    "addr:postcode":"6902 pc",
    "addr:street":"Marconistr",
    "iso:country":"NL",
    "sg:address":"Marconistr 13",
    "sg:city":"Zevenaar",
    "sg:orig_category":"Zonnebanken En Solaria - Fabrieken En Groothandel",
    "sg:phone":"+31 316 529 541",
    "sg:postcode":"6902 PC",
    "sg:province":"Gelderland",
    "wof:name":"Eurosol",
    "wof:placetype":"venue"
},
  "geometry": {"coordinates":[6.090862,51.933533],"type":"Point"}
}