{
  "type": "Feature",
  "properties": {
    "addr:full":"Techniekwg 18 Ysselstein Ut Utrecht 3401 MJ",
    "addr:housenumber":"18",
    "addr:postcode":"3401 mj",
    "addr:street":"Techniekwg",
    "iso:country":"NL",
    "sg:address":"Techniekwg 18",
    "sg:city":"Ysselstein Ut",
    "sg:orig_category":"Ziekenhuizen, Sanatoria, Verpleeghuizen",
    "sg:phone":"+31 30 688 0181",
    "sg:postcode":"3401 MJ",
    "sg:province":"Utrecht",
    "wof:name":"Vermaat Winkels Holding Bv",
    "wof:placetype":"venue"
},
  "geometry": {"coordinates":[5.056908,52.010281],"type":"Point"}
}