{
  "type": "Feature",
  "properties": {
    "addr:full":"Da Costastraat 8 Barneveld Gelderland 3771 ZB",
    "addr:housenumber":"8",
    "addr:postcode":"3771 zb",
    "addr:street":"Da Costastraat;Gelderland",
    "iso:country":"NL",
    "sg:address":"Da Costastraat 8",
    "sg:city":"Barneveld",
    "sg:orig_category":"Wegen And Sportterreinen",
    "sg:phone":"+31 342 400 210",
    "sg:postcode":"3771 ZB",
    "sg:province":"Gelderland",
    "wof:name":"A.A. Bakker",
    "wof:placetype":"venue"
},
  "geometry": {"coordinates":[5.5707421303,52.1413459778],"type":"Point"}
}