{
  "type": "Feature",
  "properties": {
    "addr:full":"De Stroet 32 Lunteren Gelderland 6741 PT",
    "addr:housenumber":"32",
    "addr:postcode":"6741",
    "addr:street":"De Stroet;Gelderland;Pt",
    "iso:country":"NL",
    "sg:address":"De Stroet 32",
    "sg:city":"Lunteren",
    "sg:orig_category":"Goederenvervoer Over De Weg",
    "sg:phone":"+31 318 483 907",
    "sg:postcode":"6741 PT",
    "sg:province":"Gelderland",
    "wof:name":"Van Den Top Transporten Bv",
    "wof:placetype":"venue"
},
  "geometry": {"coordinates":[5.599268,52.084827],"type":"Point"}
}