{
  "type": "Feature",
  "properties": {
    "addr:full":"Perkstraat 69 Zevenhuizen Zh South Holland 2761 LM",
    "addr:housenumber":"69;zh",
    "addr:postcode":"2761 lm",
    "addr:street":"Perkstraat",
    "iso:country":"NL",
    "sg:address":"Perkstraat 69",
    "sg:city":"Zevenhuizen Zh",
    "sg:orig_category":"Metaalbekleding And -Behandeling",
    "sg:phone":"+31 6 22370339",
    "sg:postcode":"2761 LM",
    "sg:province":"South Holland",
    "wof:name":"De Kruijf",
    "wof:placetype":"venue"
},
  "geometry": {"coordinates":[4.584972,52.01614],"type":"Point"}
}