{
  "type": "Feature",
  "properties": {
    "addr:full":"Zuidplein Hoog 570 Rotterdam South Holland 3083 BM",
    "addr:housenumber":"570",
    "addr:postcode":"3083 bm",
    "addr:street":"Zuidplein Hoog",
    "iso:country":"NL",
    "sg:address":"Zuidplein Hoog 570",
    "sg:city":"Rotterdam",
    "sg:orig_category":"Fotolaboratoria",
    "sg:phone":"+31 10 410 2358",
    "sg:postcode":"3083 BM",
    "sg:province":"South Holland",
    "wof:name":"Fotolaboratorium A.V. Hartman Bv",
    "wof:placetype":"venue"
},
  "geometry": {"coordinates":[4.49014,51.887051],"type":"Point"}
}