{
  "type": "Feature",
  "properties": {
    "addr:full":"De Kweek 18 Lunteren Gelderland 6741 ET",
    "addr:housenumber":"18",
    "addr:postcode":"6741 et",
    "addr:street":"De Kweek;Gelderland",
    "iso:country":"NL",
    "sg:address":"De Kweek 18",
    "sg:city":"Lunteren",
    "sg:orig_category":"Bedrijfsopleidingen",
    "sg:phone":"+31 318 487 135",
    "sg:postcode":"6741 ET",
    "sg:province":"Gelderland",
    "sg:website":"http://www.snelleren.nl",
    "wof:name":"Hera",
    "wof:placetype":"venue"
},
  "geometry": {"coordinates":[5.632166,52.08144],"type":"Point"}
}