{
  "type": "Feature",
  "properties": {
    "addr:full":"Nieuwstr 56 Someren North Brabant 5712 LE",
    "addr:housenumber":"56",
    "addr:postcode":"5712 le",
    "addr:street":"Nieuwstr",
    "iso:country":"NL",
    "sg:address":"Nieuwstr 56",
    "sg:city":"Someren",
    "sg:orig_category":"Boomrooierijen",
    "sg:phone":"+31 493 494 016",
    "sg:postcode":"5712 LE",
    "sg:province":"North Brabant",
    "wof:name":"Otterdijk, Van",
    "wof:placetype":"venue"
},
  "geometry": {"coordinates":[5.733936,51.356915],"type":"Point"}
}