{
  "type": "Feature",
  "properties": {
    "iso:country":"NL",
    "sg:address":"Breesaperhof 48",
    "sg:city":"Velsen Noord",
    "sg:orig_category":"Artsen - Huisartsen",
    "sg:phone":"+31 251 224 987",
    "sg:postcode":"1951 KH",
    "sg:province":"Noord-Holland",
    "wof:name":"Bartels, E P",
    "wof:placetype":"venue"
},
  "geometry": {"coordinates":[4.641086,52.47485],"type":"Point"}
}