{
  "type": "Feature",
  "properties": {
    "iso:country":"NL",
    "sg:address":"2E Lambertusstr 16",
    "sg:city":"Venlo",
    "sg:orig_category":"Kabels",
    "sg:phone":"+31 77 382 2226",
    "sg:postcode":"5921 HX",
    "sg:province":"Limburg",
    "wof:name":"Eltraco",
    "wof:placetype":"venue"
},
  "geometry": {"coordinates":[6.152256012,51.3703384399],"type":"Point"}
}