{
  "type": "Feature",
  "properties": {
    "addr:full":"W V Harselaarln 9 Nykerk Gld Gelderland 3863 XX",
    "addr:housenumber":"9",
    "addr:postcode":"3863 xx",
    "addr:street":"W V Harselaarln;Gld Gelderland",
    "iso:country":"NL",
    "sg:address":"W V Harselaarln 9",
    "sg:city":"Nykerk Gld",
    "sg:classifiers":[
        {
            "category":"Personal",
            "subcategory":"Nail Salon",
            "type":"Services"
        }
    ],
    "sg:phone":"+31 33 245 8572",
    "sg:postcode":"3863 XX",
    "sg:province":"Gelderland",
    "sg:tags":[
        "pedicure"
    ],
    "wof:name":"Kamp, E",
    "wof:placetype":"venue"
},
  "geometry": {"coordinates":[5.464432,52.21619],"type":"Point"}
}