{
  "type": "Feature",
  "properties": {
    "addr:full":"Nybracht 47 Emmen Provincie Drenthe 7821 CB",
    "addr:housenumber":"47;7821",
    "addr:postcode":"cb",
    "addr:street":"Nybracht;Provincie Drenthe",
    "iso:country":"NL",
    "sg:address":"Nybracht 47",
    "sg:city":"Emmen",
    "sg:orig_category":"Keukens",
    "sg:phone":"+31 591 613 827",
    "sg:postcode":"7821 CB",
    "sg:province":"Provincie Drenthe",
    "wof:name":"Horn Emmen",
    "wof:placetype":"venue"
},
  "geometry": {"coordinates":[6.900536,52.762577],"type":"Point"}
}