{
  "type": "Feature",
  "properties": {
    "addr:full":"Burg Smitwg 8 Hazerswoude Dorp South Holland 2391 ND",
    "addr:housenumber":"8",
    "addr:postcode":"2391 nd",
    "addr:street":"Burg Smitwg;Dorp",
    "iso:country":"NL",
    "sg:address":"Burg Smitwg 8",
    "sg:city":"Hazerswoude Dorp",
    "sg:orig_category":"Bloemen En Planten - Groothandel",
    "sg:phone":"+31 172 588 810",
    "sg:postcode":"2391 ND",
    "sg:province":"South Holland",
    "wof:name":"Tol Bv, F En K Van",
    "wof:placetype":"venue"
},
  "geometry": {"coordinates":[4.59104,52.097099],"type":"Point"}
}