{
  "type": "Feature",
  "properties": {
    "addr:full":"Beukenlaan 70 Soest Utrecht 3762 AJ",
    "addr:housenumber":"70",
    "addr:postcode":"3762 aj",
    "addr:street":"Beukenlaan",
    "iso:country":"NL",
    "sg:address":"Beukenlaan 70",
    "sg:city":"Soest",
    "sg:orig_category":"Verzekeringen",
    "sg:phone":"+31 35 601 6122",
    "sg:postcode":"3762 AJ",
    "sg:province":"Utrecht",
    "wof:name":"Assurantie Adviesburo J Van Kooij",
    "wof:placetype":"venue"
},
  "geometry": {"coordinates":[5.290773,52.175297],"type":"Point"}
}