{
  "type": "Feature",
  "properties": {
    "addr:full":"Stationsbuurt 4 Benningbroek Noord-Holland 1654 EH",
    "addr:housenumber":"4",
    "addr:postcode":"1654 eh",
    "addr:street":"Stationsbuurt",
    "iso:country":"NL",
    "sg:address":"Stationsbuurt 4",
    "sg:city":"Benningbroek",
    "sg:orig_category":"Onderhoudswerken",
    "sg:phone":"+31 229 591 534",
    "sg:postcode":"1654 EH",
    "sg:province":"Noord-Holland",
    "wof:name":"Worp, J",
    "wof:placetype":"venue"
},
  "geometry": {"coordinates":[5.027159,52.715214],"type":"Point"}
}