{
  "type": "Feature",
  "properties": {
    "iso:country":"NL",
    "sg:address":"Hg Steenwg 23A",
    "sg:city":"Loon Op Zand",
    "sg:orig_category":"Meubelstoffering",
    "sg:phone":"+31 416 362 710",
    "sg:postcode":"5175 AG",
    "sg:province":"Noord-Brabant",
    "wof:name":"Timmermans",
    "wof:placetype":"venue"
},
  "geometry": {"coordinates":[5.068033,51.627205],"type":"Point"}
}