{
  "type": "Feature",
  "properties": {
    "addr:full":"Bergschild 23 Deventer NL.08 7411 EL",
    "addr:housenumber":"23;nl.08",
    "addr:postcode":"7411 el",
    "addr:street":"Bergschild",
    "iso:country":"NL",
    "sg:address":"Bergschild 23",
    "sg:city":"Deventer",
    "sg:orig_category":"Webdesign Bureaus",
    "sg:phone":"+31 570 671 234",
    "sg:postcode":"7411 EL",
    "sg:province":"NL.08",
    "sg:website":"http://www.internetrijk.nl",
    "wof:name":"Internetrijk, Het",
    "wof:placetype":"venue"
},
  "geometry": {"coordinates":[6.1628861427,52.251499176],"type":"Point"}
}