{
  "type": "Feature",
  "properties": {
    "addr:full":"Uthof 9 Drachten Friesland 9202 HL",
    "addr:housenumber":"9",
    "addr:postcode":"9202 hl",
    "addr:street":"Uthof",
    "iso:country":"NL",
    "sg:address":"Uthof 9",
    "sg:city":"Drachten",
    "sg:orig_category":"Tandartsen",
    "sg:phone":"+31 512 518 988",
    "sg:postcode":"9202 HL",
    "sg:province":"Friesland",
    "wof:name":"J.H. Meijer",
    "wof:placetype":"venue"
},
  "geometry": {"coordinates":[6.111547,53.108822],"type":"Point"}
}