{
  "type": "Feature",
  "properties": {
    "addr:full":"Wilhelminapln 6A Someren Noord-Brabant 5711 EK",
    "addr:housenumber":"6a",
    "addr:postcode":"5711 ek",
    "addr:street":"Wilhelminapln",
    "iso:country":"NL",
    "sg:address":"Wilhelminapln 6A",
    "sg:city":"Someren",
    "sg:orig_category":"Adviesbureaus Bouwkunde",
    "sg:phone":"+31 493 470 047",
    "sg:postcode":"5711 EK",
    "sg:province":"Noord-Brabant",
    "wof:name":"Gianotten",
    "wof:placetype":"venue"
},
  "geometry": {"coordinates":[5.711272,51.384651],"type":"Point"}
}