{
  "type": "Feature",
  "properties": {
    "addr:full":"Tempelplein 11 Sittard Limburg 6131 JC",
    "addr:housenumber":"11",
    "addr:postcode":"6131 jc",
    "addr:street":"Tempelplein",
    "iso:country":"NL",
    "sg:address":"Tempelplein 11",
    "sg:city":"Sittard",
    "sg:orig_category":"Bloemen And Planten",
    "sg:phone":"+31 46 451 8901",
    "sg:postcode":"6131 JC",
    "sg:province":"Limburg",
    "wof:name":"Ger Drenth Bloemsierkunst Den Tempel Bv",
    "wof:placetype":"venue"
},
  "geometry": {"coordinates":[5.868124,50.996746],"type":"Point"}
}