{
  "type": "Feature",
  "properties": {
    "addr:full":"Vennewg 4 Ryen Noord-Brabant 5121 RA",
    "addr:housenumber":"4",
    "addr:postcode":"5121 ra",
    "addr:street":"Vennewg",
    "iso:country":"NL",
    "sg:address":"Vennewg 4",
    "sg:city":"Ryen",
    "sg:orig_category":"Juridische Adviseurs",
    "sg:phone":"+31 161 230 272",
    "sg:postcode":"5121 RA",
    "sg:province":"Noord-Brabant",
    "sg:website":"http://www.janvandenbosch.com",
    "wof:name":"Bosch, Mr J A P M Van Den",
    "wof:placetype":"venue"
},
  "geometry": {"coordinates":[4.9197,51.588017],"type":"Point"}
}