{
  "type": "Feature",
  "properties": {
    "iso:country":"NL",
    "sg:address":"Stoofwg 16",
    "sg:city":"Dreischor",
    "sg:orig_category":"Onderhoudswerken",
    "sg:phone":"+31 111 401 887",
    "sg:postcode":"4315 CA",
    "sg:province":"Zeeland",
    "wof:name":"Verton, Timmer- En Onderhbedr",
    "wof:placetype":"venue"
},
  "geometry": {"coordinates":[3.978543,51.690422],"type":"Point"}
}