{
  "type": "Feature",
  "properties": {
    "iso:country":"NL",
    "sg:address":"Oranje Nassaustraat 15",
    "sg:city":"Bovenkarspel",
    "sg:classifiers":[
        {
            "category":"Professional",
            "subcategory":"Accounting & Tax Preparation",
            "type":"Services"
        }
    ],
    "sg:phone":"+31 228 513 370",
    "sg:postcode":"1611 EA",
    "sg:province":"Noord-Holland",
    "sg:tags":[
        "accountant"
    ],
    "wof:name":"Accountantskantoor Hoff",
    "wof:placetype":"venue"
},
  "geometry": {"coordinates":[5.25196,52.690628],"type":"Point"}
}