{
  "type": "Feature",
  "properties": {
    "iso:country":"NL",
    "sg:address":"K Doormanstr 21",
    "sg:city":"Druten",
    "sg:orig_category":"Gordijnenateliers",
    "sg:phone":"+31 487 512 524",
    "sg:postcode":"6651 ZL",
    "sg:province":"Gelderland",
    "wof:name":"Javamo",
    "wof:placetype":"venue"
},
  "geometry": {"coordinates":[5.60526,51.88567],"type":"Point"}
}