{
  "type": "Feature",
  "properties": {
    "addr:full":"Touwslagersbaan 4 Wijchen Gelderland 6602 AK",
    "addr:housenumber":"4",
    "addr:postcode":"6602 ak",
    "addr:street":"Touwslagersbaan;Gelderland",
    "iso:country":"NL",
    "sg:address":"Touwslagersbaan 4",
    "sg:city":"Wijchen",
    "sg:orig_category":"Bloemen And Planten",
    "sg:phone":"+31 24 642 5185",
    "sg:postcode":"6602 AK",
    "sg:province":"Gelderland",
    "wof:name":"Jan Arts Bloemerie",
    "wof:placetype":"venue"
},
  "geometry": {"coordinates":[5.725294,51.807259],"type":"Point"}
}