{
  "type": "Feature",
  "properties": {
    "addr:full":"Karel Doormanlaan 37 Terneuzen Zeeland 4535 BP",
    "addr:housenumber":"37",
    "addr:postcode":"4535 bp",
    "addr:street":"Karel Doormanlaan",
    "iso:country":"NL",
    "sg:address":"Karel Doormanlaan 37",
    "sg:city":"Terneuzen",
    "sg:orig_category":"Onderhoud And Reparatie Kantoorapparatuur",
    "sg:phone":"+31 115 615 801",
    "sg:postcode":"4535 BP",
    "sg:province":"Zeeland",
    "wof:name":"P.C.S.-Automatisering",
    "wof:placetype":"venue"
},
  "geometry": {"coordinates":[3.856878,51.318298],"type":"Point"}
}