{
  "type": "Feature",
  "properties": {
    "addr:full":"Eikenln 1/B Leusden Utrecht 3831 XD",
    "addr:housenumber":"1 / b",
    "addr:postcode":"3831 xd",
    "addr:street":"Eikenln",
    "iso:country":"NL",
    "sg:address":"Eikenln 1/B",
    "sg:city":"Leusden",
    "sg:orig_category":"Verzekeringen - Verzekeringskantoren",
    "sg:phone":"+31 33 494 4398",
    "sg:postcode":"3831 XD",
    "sg:province":"Utrecht",
    "wof:name":"Saaltink, H M",
    "wof:placetype":"venue"
},
  "geometry": {"coordinates":[5.42959,52.131248],"type":"Point"}
}