{
  "type": "Feature",
  "properties": {
    "addr:full":"Boulevard Heuvelink 38 Arnhem Gelderland 6828 KR",
    "addr:housenumber":"38",
    "addr:postcode":"6828 kr",
    "addr:street":"Boulevard Heuvelink",
    "iso:country":"NL",
    "sg:address":"Boulevard Heuvelink 38",
    "sg:city":"Arnhem",
    "sg:orig_category":"Fotostudio'S And Fotografen",
    "sg:phone":"+31 26 443 6768",
    "sg:postcode":"6828 KR",
    "sg:province":"Gelderland",
    "wof:name":"Bas Klimbie Scheepvaart-En Bergingsrepor",
    "wof:placetype":"venue"
},
  "geometry": {"coordinates":[5.918878,51.978127],"type":"Point"}
}