{
  "type": "Feature",
  "properties": {
    "addr:full":"Statensngl 193B Rotterdam Zuid-Holland 3039 LM",
    "addr:housenumber":"193b",
    "addr:postcode":"3039 lm",
    "iso:country":"NL",
    "sg:address":"Statensngl 193B",
    "sg:city":"Rotterdam",
    "sg:orig_category":"Vertaalbureaus",
    "sg:phone":"+31 10 465 1935",
    "sg:postcode":"3039 LM",
    "sg:province":"Zuid-Holland",
    "sg:website":"http://www.pinstripe.nl",
    "wof:name":"Pinstripe",
    "wof:placetype":"venue"
},
  "geometry": {"coordinates":[4.45595,51.930851],"type":"Point"}
}