{
  "type": "Feature",
  "properties": {
    "addr:full":"Gele Kwikstaart 3 Kwintsheul Zuid-Holland 2295 NN",
    "addr:housenumber":"3",
    "addr:postcode":"2295 nn",
    "addr:street":"Gele Kwikstaart",
    "iso:country":"NL",
    "sg:address":"Gele Kwikstaart 3",
    "sg:city":"Kwintsheul",
    "sg:orig_category":"Adviesbureaus Bouwkunde",
    "sg:phone":"+31 174 294 083",
    "sg:postcode":"2295 NN",
    "sg:province":"Zuid-Holland",
    "wof:name":"Gier, Hans De",
    "wof:placetype":"venue"
},
  "geometry": {"coordinates":[4.25338,52.013592],"type":"Point"}
}