{
  "type": "Feature",
  "properties": {
    "iso:country":"NL",
    "sg:address":"Zeeweg 117",
    "sg:city":"Katwijk Zh",
    "sg:orig_category":"Notarissen",
    "sg:phone":"+31 71 407 1646",
    "sg:postcode":"2224 CD",
    "sg:province":"Zuid-Holland",
    "wof:name":"Verhees Van Der Plas Cs Netwerk Notarissen",
    "wof:placetype":"venue"
},
  "geometry": {"coordinates":[4.410683,52.201099],"type":"Point"}
}