{
  "type": "Feature",
  "properties": {
    "addr:full":"Hoogstr 182 Schiedam Zuid-Holland 3111 HP",
    "addr:housenumber":"182",
    "addr:postcode":"3111 hp",
    "iso:country":"NL",
    "sg:address":"Hoogstr 182",
    "sg:city":"Schiedam",
    "sg:orig_category":"Kinderkleding",
    "sg:phone":"+31 10 426 4377",
    "sg:postcode":"3111 HP",
    "sg:province":"Zuid-Holland",
    "wof:name":"Carousel Jr",
    "wof:placetype":"venue"
},
  "geometry": {"coordinates":[4.39816,51.918472],"type":"Point"}
}