{
  "type": "Feature",
  "properties": {
    "iso:country":"NL",
    "sg:address":"De Millystraat 1",
    "sg:city":"Zuidlaren",
    "sg:orig_category":"Fitnesscentra",
    "sg:phone":"+31 50 409 0347",
    "sg:postcode":"9471 AG",
    "sg:province":"Provincie Drenthe",
    "wof:name":"Sportcentrum Dave Jonkers",
    "wof:placetype":"venue"
},
  "geometry": {"coordinates":[6.688189,53.096333],"type":"Point"}
}