{
  "type": "Feature",
  "properties": {
    "iso:country":"NL",
    "sg:address":"De Giek 18",
    "sg:city":"Drachten",
    "sg:orig_category":"Verzekeringen",
    "sg:phone":"+31 512 582 000",
    "sg:postcode":"9206 AT",
    "sg:province":"Friesland",
    "wof:name":"Querforth Pensioen & Financieel Adv Bv",
    "wof:placetype":"venue"
},
  "geometry": {"coordinates":[6.07476,53.11496],"type":"Point"}
}