{
  "type": "Feature",
  "properties": {
    "iso:country":"NL",
    "sg:address":"Vastenow 88",
    "sg:city":"Nieuw Dordrecht",
    "sg:orig_category":"Hoefdierhouderijen",
    "sg:phone":"+31 591 316 844",
    "sg:postcode":"7885 AN",
    "sg:province":"Drenthe",
    "wof:name":"A Hidding",
    "wof:placetype":"venue"
},
  "geometry": {"coordinates":[6.983199,52.737888],"type":"Point"}
}