{
  "type": "Feature",
  "properties": {
    "iso:country":"NL",
    "sg:address":"Spechthorstdwarsweg 5",
    "sg:city":"Goor",
    "sg:orig_category":"Diverse Bedrijfsinstallaties Gh",
    "sg:phone":"+31 547 272 771",
    "sg:postcode":"7471 GJ",
    "sg:province":"Overijssel",
    "wof:name":"Latrago Bv",
    "wof:placetype":"venue"
},
  "geometry": {"coordinates":[6.58628,52.242348],"type":"Point"}
}