{
  "type": "Feature",
  "properties": {
    "addr:full":"Voorstr 74 Zwaagwesteinde Friesland 9271 KJ",
    "addr:housenumber":"74",
    "addr:postcode":"9271 kj",
    "addr:street":"Voorstr",
    "iso:country":"NL",
    "sg:address":"Voorstr 74",
    "sg:city":"Zwaagwesteinde",
    "sg:orig_category":"Watersportartikelen",
    "sg:phone":"+31 511 441 401",
    "sg:postcode":"9271 KJ",
    "sg:province":"Friesland",
    "wof:name":"Koperen Scheepsbel, De",
    "wof:placetype":"venue"
},
  "geometry": {"coordinates":[6.0405220985,53.2614898682],"type":"Point"}
}