{
  "type": "Feature",
  "properties": {
    "addr:full":"Sloothaak 69 Soest Utrecht 3763 ZB",
    "addr:housenumber":"69",
    "addr:postcode":"3763 zb",
    "addr:street":"Sloothaak",
    "iso:country":"NL",
    "sg:address":"Sloothaak 69",
    "sg:city":"Soest",
    "sg:orig_category":"Adviesbureaus Bedrijfsorganisatie",
    "sg:phone":"+31 35 538 0327",
    "sg:postcode":"3763 ZB",
    "sg:province":"Utrecht",
    "wof:name":"Joint Interest Bv",
    "wof:placetype":"venue"
},
  "geometry": {"coordinates":[5.266493,52.17403],"type":"Point"}
}