{
  "type": "Feature",
  "properties": {
    "addr:full":"Windmolenerf 2 Gouda South Holland 2807 EE",
    "addr:housenumber":"2",
    "addr:postcode":"2807 ee",
    "addr:street":"Windmolenerf",
    "iso:country":"NL",
    "sg:address":"Windmolenerf 2",
    "sg:city":"Gouda",
    "sg:orig_category":"Autorijscholen",
    "sg:phone":"+31 182 526 712",
    "sg:postcode":"2807 EE",
    "sg:province":"South Holland",
    "wof:name":"Zeverboom",
    "wof:placetype":"venue"
},
  "geometry": {"coordinates":[4.74196,52.009159],"type":"Point"}
}