{
  "type": "Feature",
  "properties": {
    "iso:country":"NL",
    "sg:address":"Sluispolderwg 51",
    "sg:city":"Zaandam",
    "sg:orig_category":"Jachthavens - Jachtwerven",
    "sg:phone":"+31 75 615 8181",
    "sg:postcode":"1505 HJ",
    "sg:province":"Noord-Holland",
    "wof:name":"Kokernoot, K",
    "wof:placetype":"venue"
},
  "geometry": {"coordinates":[4.855371,52.419556],"type":"Point"}
}