{
  "type": "Feature",
  "properties": {
    "addr:full":"Mijnsherenlaan 177A Rotterdam Zuid-Holland 3081 GM",
    "addr:housenumber":"177a",
    "addr:postcode":"3081 gm",
    "addr:street":"Mijnsherenlaan",
    "iso:country":"NL",
    "sg:address":"Mijnsherenlaan 177A",
    "sg:city":"Rotterdam",
    "sg:orig_category":"Werving And Selectie Van Tijdelijk Personeel And Uitzendkantoren",
    "sg:phone":"+31 10 484 0744",
    "sg:postcode":"3081 GM",
    "sg:province":"Zuid-Holland",
    "wof:name":"Nacom Bv",
    "wof:placetype":"venue"
},
  "geometry": {"coordinates":[4.4891638756,51.891708374],"type":"Point"}
}