{
  "type": "Feature",
  "properties": {
    "addr:full":"Flevoln 27C Weesp Noord-Holland 1382 JX",
    "addr:housenumber":"27c",
    "addr:postcode":"1382 jx",
    "addr:street":"Flevoln",
    "iso:country":"NL",
    "sg:address":"Flevoln 27C",
    "sg:city":"Weesp",
    "sg:orig_category":"Verhuur",
    "sg:phone":"+31 294 418 303",
    "sg:postcode":"1382 JX",
    "sg:province":"Noord-Holland",
    "wof:name":"Voskuil Verhuur Service",
    "wof:placetype":"venue"
},
  "geometry": {"coordinates":[5.03828,52.308315],"type":"Point"}
}