{
  "type": "Feature",
  "properties": {
    "addr:full":"Obrechtstr 165 Zwolle Overijssel 8031 AN",
    "addr:housenumber":"165",
    "addr:postcode":"8031 an",
    "iso:country":"NL",
    "sg:address":"Obrechtstr 165",
    "sg:city":"Zwolle",
    "sg:orig_category":"Cafetaria'S",
    "sg:phone":"+31 38 421 2154",
    "sg:postcode":"8031 AN",
    "sg:province":"Overijssel",
    "wof:name":"Patatje, Het",
    "wof:placetype":"venue"
},
  "geometry": {"coordinates":[6.08304,52.521454],"type":"Point"}
}