{
  "type": "Feature",
  "properties": {
    "iso:country":"NL",
    "sg:address":"T A Kempisstr 94B",
    "sg:city":"Zwolle",
    "sg:orig_category":"Journalisten Freelance",
    "sg:phone":"+31 6 50903570",
    "sg:postcode":"8022 AB",
    "sg:province":"Overijssel",
    "wof:name":"Marcus, Jorien",
    "wof:placetype":"venue"
},
  "geometry": {"coordinates":[6.106886,52.516575],"type":"Point"}
}