{
  "type": "Feature",
  "properties": {
    "addr:full":"Deurningerstr 37 Oldenzaal Overijssel 7571 BA",
    "addr:housenumber":"37",
    "addr:postcode":"7571 ba",
    "addr:street":"Deurningerstr",
    "iso:country":"NL",
    "sg:address":"Deurningerstr 37",
    "sg:city":"Oldenzaal",
    "sg:orig_category":"Kinderkleding",
    "sg:phone":"+31 541 534 327",
    "sg:postcode":"7571 BA",
    "sg:province":"Overijssel",
    "wof:name":"Willemsen Jeugdmode",
    "wof:placetype":"venue"
},
  "geometry": {"coordinates":[6.925473,52.311893],"type":"Point"}
}