{
  "type": "Feature",
  "properties": {
    "addr:full":"Plantsoenstraat 3 Purmerend Noord-Holland 1441 CW",
    "addr:housenumber":"3",
    "addr:postcode":"1441 cw",
    "addr:street":"Plantsoenstraat",
    "iso:country":"NL",
    "sg:address":"Plantsoenstraat 3",
    "sg:city":"Purmerend",
    "sg:orig_category":"Meubelzaken, Woning- And Keukeninrichting",
    "sg:phone":"+31 299 470 146",
    "sg:postcode":"1441 CW",
    "sg:province":"Noord-Holland",
    "wof:name":"Sonny'S Groothandel In Oosterse Meubelen",
    "wof:placetype":"venue"
},
  "geometry": {"coordinates":[4.948399,52.508167],"type":"Point"}
}