{
  "type": "Feature",
  "properties": {
    "addr:full":"Zuidlaarderwg 97 Noordlaren Provincie Drenthe 9479 PR",
    "addr:housenumber":"97",
    "addr:postcode":"9479 pr",
    "addr:street":"Zuidlaarderwg;Provincie Drenthe",
    "iso:country":"NL",
    "sg:address":"Zuidlaarderwg 97",
    "sg:city":"Noordlaren",
    "sg:orig_category":"Metselwerken",
    "sg:phone":"+31 50 409 2782",
    "sg:postcode":"9479 PR",
    "sg:province":"Provincie Drenthe",
    "wof:name":"Mark Wieland",
    "wof:placetype":"venue"
},
  "geometry": {"coordinates":[6.67021,53.116329],"type":"Point"}
}