{
  "type": "Feature",
  "properties": {
    "addr:full":"Muziekpln 11 Barendrecht South Holland 2992 GH",
    "addr:housenumber":"11",
    "addr:postcode":"2992 gh",
    "addr:street":"Muziekpln",
    "iso:country":"NL",
    "sg:address":"Muziekpln 11",
    "sg:city":"Barendrecht",
    "sg:orig_category":"Kappers",
    "sg:phone":"+31 180 623 555",
    "sg:postcode":"2992 GH",
    "sg:province":"South Holland",
    "sg:website":"http://www.pinobaris.nl",
    "wof:name":"Pino & Baris",
    "wof:placetype":"venue"
},
  "geometry": {"coordinates":[4.523058,51.854126],"type":"Point"}
}