{
  "type": "Feature",
  "properties": {
    "addr:full":"Pr Julianapln 1 Amersfoort Utrecht 3811 NM",
    "addr:housenumber":"1",
    "addr:postcode":"3811",
    "iso:country":"NL",
    "sg:address":"Pr Julianapln 1",
    "sg:city":"Amersfoort",
    "sg:orig_category":"Webdesign Bureaus",
    "sg:phone":"+31 33 422 9191",
    "sg:postcode":"3811 NM",
    "sg:province":"Utrecht",
    "sg:website":"http://www.mda.nl",
    "wof:name":"Media Dell Arte Bv",
    "wof:placetype":"venue"
},
  "geometry": {"coordinates":[5.3860850334,52.1523246765],"type":"Point"}
}