{
  "type": "Feature",
  "properties": {
    "addr:full":"Lekstr Arnhem Gelderland 6826 AH",
    "addr:postcode":"6826 ah",
    "addr:street":"Gelderland",
    "iso:country":"NL",
    "sg:address":"Lekstr",
    "sg:city":"Arnhem",
    "sg:orig_category":"Sportverenigingen En Ontspannings- Verenigingen",
    "sg:phone":"+31 26 361 7803",
    "sg:postcode":"6826 AH",
    "sg:province":"Gelderland",
    "wof:name":"Groene Kamer Tennisver, De",
    "wof:placetype":"venue"
},
  "geometry": {"coordinates":[5.938207,51.985043],"type":"Point"}
}