{
  "type": "Feature",
  "properties": {
    "iso:country":"NL",
    "sg:address":"Stadionwg 42",
    "sg:city":"Amsterdam",
    "sg:orig_category":"Acupunctuur",
    "sg:phone":"+31 20 673 3554",
    "sg:postcode":"1077 SM",
    "sg:province":"Noord-Holland",
    "wof:name":"Groepspraktijk Stadionweg 42",
    "wof:placetype":"venue"
},
  "geometry": {"coordinates":[4.880459,52.347614],"type":"Point"}
}