{
  "type": "Feature",
  "properties": {
    "addr:full":"Pieterswijk 101 Elim Drenthe 7916 TH",
    "addr:housenumber":"101",
    "addr:postcode":"7916 th",
    "addr:street":"Pieterswijk",
    "iso:country":"NL",
    "sg:address":"Pieterswijk 101",
    "sg:city":"Elim",
    "sg:orig_category":"Bloemen And Planten",
    "sg:phone":"+31 528 351 445",
    "sg:postcode":"7916 TH",
    "sg:province":"Drenthe",
    "wof:name":"G.A. Tangenberg",
    "wof:placetype":"venue"
},
  "geometry": {"coordinates":[6.582092,52.672394],"type":"Point"}
}