{
  "type": "Feature",
  "properties": {
    "iso:country":"NL",
    "sg:address":"Perziklaan 19",
    "sg:city":"'S Gravenhage",
    "sg:orig_category":"Loodgieterswerk, Verwarming And Sanitaire Installaties",
    "sg:phone":"+31 70 368 5126",
    "sg:postcode":"2564 TV",
    "sg:province":"Zuid-Holland",
    "wof:name":"Meijer & Zoon Loodgietersbedrijf",
    "wof:placetype":"venue"
},
  "geometry": {"coordinates":[4.259767,52.071041],"type":"Point"}
}