{
  "type": "Feature",
  "properties": {
    "addr:full":"A Kuyperln 38 Rotterdam Zuid-Holland 3038 PL",
    "addr:housenumber":"38",
    "addr:postcode":"3038 pl",
    "iso:country":"NL",
    "sg:address":"A Kuyperln 38",
    "sg:city":"Rotterdam",
    "sg:orig_category":"Verenigingsgebouwen",
    "sg:phone":"+31 10 465 6397",
    "sg:postcode":"3038 PL",
    "sg:province":"Zuid-Holland",
    "wof:name":"Tijensoos, Van",
    "wof:placetype":"venue"
},
  "geometry": {"coordinates":[4.46465,51.935558],"type":"Point"}
}