{
  "type": "Feature",
  "properties": {
    "iso:country":"NL",
    "sg:address":"Timmermansstr 15",
    "sg:city":"Nieuw Heeten",
    "sg:orig_category":"Kopieerservice",
    "sg:phone":"+31 572 321 316",
    "sg:postcode":"8112 AG",
    "sg:province":"Overijssel",
    "wof:name":"Succes",
    "wof:placetype":"venue"
},
  "geometry": {"coordinates":[6.352137,52.318851],"type":"Point"}
}