{
  "type": "Feature",
  "properties": {
    "addr:full":"Tijvoortsebaan 9C Goirle Noord-Brabant 5051 HJ",
    "addr:housenumber":"9c",
    "addr:postcode":"5051 hj",
    "addr:street":"Tijvoortsebaan",
    "iso:country":"NL",
    "sg:address":"Tijvoortsebaan 9C",
    "sg:city":"Goirle",
    "sg:orig_category":"Geluidsopnamen",
    "sg:phone":"+31 13 534 8376",
    "sg:postcode":"5051 HJ",
    "sg:province":"Noord-Brabant",
    "wof:name":"Robby'S Bv",
    "wof:placetype":"venue"
},
  "geometry": {"coordinates":[5.053099,51.511784],"type":"Point"}
}