{
  "type": "Feature",
  "properties": {
    "addr:full":"Westhavenplaats 20 Vlaardingen Zuid-Holland 3131 BT",
    "addr:housenumber":"20",
    "addr:postcode":"3131 bt",
    "addr:street":"Westhavenplaats",
    "iso:country":"NL",
    "sg:address":"Westhavenplaats 20",
    "sg:city":"Vlaardingen",
    "sg:orig_category":"Hulpverlening Sociaal",
    "sg:phone":"+31 10 445 0670",
    "sg:postcode":"3131 BT",
    "sg:province":"Zuid-Holland",
    "wof:name":"Nidos, Sticht",
    "wof:placetype":"venue"
},
  "geometry": {"coordinates":[4.343567,51.90974],"type":"Point"}
}