{
  "type": "Feature",
  "properties": {
    "addr:full":"Kerkweg 4 Leersum Utrecht 3956  R",
    "addr:housenumber":"4",
    "addr:postcode":"3956 r",
    "addr:street":"Kerkweg",
    "iso:country":"NL",
    "sg:address":"Kerkweg 4",
    "sg:city":"Leersum",
    "sg:orig_category":"Bloemen And Planten",
    "sg:phone":"+31 343 450 006",
    "sg:postcode":"3956  R",
    "sg:province":"Utrecht",
    "wof:name":"Dorriene Bloemenatelier",
    "wof:placetype":"venue"
},
  "geometry": {"coordinates":[5.432761,52.010155],"type":"Point"}
}