{
  "type": "Feature",
  "properties": {
    "addr:full":"Westerbadstr 6 Groningen Groningen 9726 CR",
    "addr:housenumber":"6",
    "addr:postcode":"9726 cr",
    "addr:street":"Westerbadstr",
    "iso:country":"NL",
    "sg:address":"Westerbadstr 6",
    "sg:city":"Groningen",
    "sg:orig_category":"Beeldende Kunstenaars",
    "sg:phone":"+31 50 311 2615",
    "sg:postcode":"9726 CR",
    "sg:province":"Groningen",
    "wof:name":"Klopper, T Y",
    "wof:placetype":"venue"
},
  "geometry": {"coordinates":[6.556559,53.21273],"type":"Point"}
}