{
  "type": "Feature",
  "properties": {
    "addr:full":"Opperbos 13 Purmerend Noord-Holland 1447 TN",
    "addr:housenumber":"13",
    "addr:postcode":"1447",
    "addr:street":"Opperbos",
    "iso:country":"NL",
    "sg:address":"Opperbos 13",
    "sg:city":"Purmerend",
    "sg:orig_category":"Public Relationbureaus",
    "sg:phone":"+31 299 648 273",
    "sg:postcode":"1447 TN",
    "sg:province":"Noord-Holland",
    "wof:name":"Van Kopij Tot Boek",
    "wof:placetype":"venue"
},
  "geometry": {"coordinates":[4.974437,52.491508],"type":"Point"}
}