{
  "type": "Feature",
  "properties": {
    "addr:full":"Anjerstraat 4 Drunen Noord-Brabant 5151 GC",
    "addr:housenumber":"4",
    "addr:postcode":"5151 gc",
    "addr:street":"Anjerstraat",
    "iso:country":"NL",
    "sg:address":"Anjerstraat 4",
    "sg:city":"Drunen",
    "sg:orig_category":"Film-, Tv- And Videoproductie",
    "sg:phone":"+31 416 377 780",
    "sg:postcode":"5151 GC",
    "sg:province":"Noord-Brabant",
    "wof:name":"Direct Effect",
    "wof:placetype":"venue"
},
  "geometry": {"coordinates":[5.138614,51.691746],"type":"Point"}
}