{
  "type": "Feature",
  "properties": {
    "addr:full":"Bachstr 1A Heemskerk Noord-Holland 1962 BA",
    "addr:housenumber":"1a",
    "addr:postcode":"1962 ba",
    "addr:street":"Bachstr",
    "iso:country":"NL",
    "sg:address":"Bachstr 1A",
    "sg:city":"Heemskerk",
    "sg:orig_category":"Artsen - Huisartsen",
    "sg:phone":"+31 251 232 484",
    "sg:postcode":"1962 BA",
    "sg:province":"Noord-Holland",
    "wof:name":"Schumacher, T J M",
    "wof:placetype":"venue"
},
  "geometry": {"coordinates":[4.669106,52.513332],"type":"Point"}
}