{
  "type": "Feature",
  "properties": {
    "addr:full":"Jan Scheplaan 15 Zeist Utrecht 3705 LJ",
    "addr:housenumber":"15",
    "addr:postcode":"3705 lj",
    "addr:street":"Jan Scheplaan",
    "iso:country":"NL",
    "sg:address":"Jan Scheplaan 15",
    "sg:city":"Zeist",
    "sg:orig_category":"Kinderopvang Behalve Thuis",
    "sg:phone":"+31 30 699 0285",
    "sg:postcode":"3705 LJ",
    "sg:province":"Utrecht",
    "wof:name":"Kiekeboe",
    "wof:placetype":"venue"
},
  "geometry": {"coordinates":[5.247933,52.101158],"type":"Point"}
}