{
  "type": "Feature",
  "properties": {
    "iso:country":"NL",
    "sg:address":"Langbroekerdk A 104",
    "sg:city":"Langbroek",
    "sg:orig_category":"Loonbedrijven",
    "sg:phone":"+31 343 561 726",
    "sg:postcode":"3947 BK",
    "sg:province":"Utrecht",
    "wof:name":"Legemaat, T N",
    "wof:placetype":"venue"
},
  "geometry": {"coordinates":[5.304178,52.017315],"type":"Point"}
}