{
  "type": "Feature",
  "properties": {
    "addr:full":"P Kleynstr 10 Rosmalen Noord-Brabant 5246 GT",
    "addr:housenumber":"10",
    "addr:postcode":"5246 gt",
    "iso:country":"NL",
    "sg:address":"P Kleynstr 10",
    "sg:city":"Rosmalen",
    "sg:orig_category":"Sportverenigingen En Ontspannings- Verenigingen",
    "sg:phone":"+31 73 642 4636",
    "sg:postcode":"5246 GT",
    "sg:province":"Noord-Brabant",
    "wof:name":"Hertogenbossche Verzamelaarsver, 'S",
    "wof:placetype":"venue"
},
  "geometry": {"coordinates":[5.34293,51.700851],"type":"Point"}
}