{
  "type": "Feature",
  "properties": {
    "addr:full":"Coehoornstraat 89 Nijmegen Gelderland 6521 CD",
    "addr:housenumber":"89",
    "addr:postcode":"6521 cd",
    "addr:street":"Coehoornstraat;Gelderland",
    "iso:country":"NL",
    "sg:address":"Coehoornstraat 89",
    "sg:city":"Nijmegen",
    "sg:orig_category":"Artsen And Specialisten",
    "sg:phone":"+31 24 324 1988",
    "sg:postcode":"6521 CD",
    "sg:province":"Gelderland",
    "wof:name":"C.L.T.M. V.D. Ven",
    "wof:placetype":"venue"
},
  "geometry": {"coordinates":[5.869413,51.836262],"type":"Point"}
}