{
  "type": "Feature",
  "properties": {
    "addr:full":"Schwartzenberghln 120 Drachten Friesland 9201 KG",
    "addr:housenumber":"120",
    "addr:postcode":"9201 kg",
    "iso:country":"NL",
    "sg:address":"Schwartzenberghln 120",
    "sg:city":"Drachten",
    "sg:orig_category":"Elektronica - Onderdelen",
    "sg:phone":"+31 512 511 938",
    "sg:postcode":"9201 KG",
    "sg:province":"Friesland",
    "wof:name":"Zuidema",
    "wof:placetype":"venue"
},
  "geometry": {"coordinates":[6.10619,53.115566],"type":"Point"}
}