{
  "type": "Feature",
  "properties": {
    "addr:full":"Algemeer 61 Bennekom Gelderland 6721 GB",
    "addr:housenumber":"61",
    "addr:postcode":"6721 gb",
    "addr:street":"Algemeer;Gelderland",
    "iso:country":"NL",
    "sg:address":"Algemeer 61",
    "sg:city":"Bennekom",
    "sg:orig_category":"Milieu",
    "sg:phone":"+31 318 431 504",
    "sg:postcode":"6721 GB",
    "sg:province":"Gelderland",
    "wof:name":"Kappen Bv",
    "wof:placetype":"venue"
},
  "geometry": {"coordinates":[5.682956,51.999069],"type":"Point"}
}