{
  "type": "Feature",
  "properties": {
    "addr:full":"Dorpsstraat 100 Zevenhuizen Zh Zuid-Holland 2761 AH",
    "addr:housenumber":"100",
    "addr:postcode":"2761 ah",
    "addr:street":"Dorpsstraat",
    "iso:country":"NL",
    "sg:address":"Dorpsstraat 100",
    "sg:city":"Zevenhuizen Zh",
    "sg:orig_category":"Notarissen",
    "sg:phone":"+31 180 631 611",
    "sg:postcode":"2761 AH",
    "sg:province":"Zuid-Holland",
    "wof:name":"Mr. E.H. Jansen Notariskantoor",
    "wof:placetype":"venue"
},
  "geometry": {"coordinates":[4.582741,52.010296],"type":"Point"}
}