{
  "type": "Feature",
  "properties": {
    "iso:country":"NL",
    "sg:address":"Spegelt 50",
    "sg:city":"Nuenen",
    "sg:orig_category":"Plaatwerk",
    "sg:phone":"+31 40 283 1584",
    "sg:postcode":"5674 CD",
    "sg:province":"Noord-Brabant",
    "wof:name":"Psn",
    "wof:placetype":"venue"
},
  "geometry": {"coordinates":[5.533303,51.464634],"type":"Point"}
}