{
  "type": "Feature",
  "properties": {
    "addr:full":"Uranuswg 8 Leeuwarden Friesland 8938 AJ",
    "addr:housenumber":"8",
    "addr:postcode":"8938 aj",
    "addr:street":"Uranuswg",
    "iso:country":"NL",
    "sg:address":"Uranuswg 8",
    "sg:city":"Leeuwarden",
    "sg:orig_category":"Overheidsdiensten",
    "sg:phone":"+31 58 234 7940",
    "sg:postcode":"8938 AJ",
    "sg:province":"Friesland",
    "wof:name":"Dienst Sociale Werkvoorziening",
    "wof:placetype":"venue"
},
  "geometry": {"coordinates":[5.8448767662,53.1989555359],"type":"Point"}
}