{
  "type": "Feature",
  "properties": {
    "iso:country":"NL",
    "sg:address":"De Etgaarde 1",
    "sg:city":"Oosterhesselen",
    "sg:orig_category":"Bejaarden - Verzorgingstehuizen",
    "sg:phone":"+31 524 581 510",
    "sg:postcode":"7861 BT",
    "sg:province":"Drenthe",
    "wof:name":"Etgaarde, De",
    "wof:placetype":"venue"
},
  "geometry": {"coordinates":[6.724308,52.753635],"type":"Point"}
}