{
  "type": "Feature",
  "properties": {
    "iso:country":"NL",
    "sg:address":"Nw Markt 33",
    "sg:city":"Roosendaal",
    "sg:orig_category":"Woninginrichting",
    "sg:phone":"+31 165 535 632",
    "sg:postcode":"4701 AB",
    "sg:province":"North Brabant",
    "wof:name":"Egmond Binnenhuisadv, Paul Van",
    "wof:placetype":"venue"
},
  "geometry": {"coordinates":[4.4575557709,51.5317192078],"type":"Point"}
}