{
  "type": "Feature",
  "properties": {
    "addr:full":"Hogewg 32 Zandvoort North Holland 2042 GH",
    "addr:housenumber":"32",
    "addr:postcode":"2042 gh",
    "addr:street":"Hogewg",
    "iso:country":"NL",
    "sg:address":"Hogewg 32",
    "sg:city":"Zandvoort",
    "sg:orig_category":"Onroerende Goederen",
    "sg:phone":"+31 23 571 7964",
    "sg:postcode":"2042 GH",
    "sg:province":"North Holland",
    "wof:name":"Cobert Bv",
    "wof:placetype":"venue"
},
  "geometry": {"coordinates":[4.527231,52.370647],"type":"Point"}
}