{
  "type": "Feature",
  "properties": {
    "iso:country":"NL",
    "sg:address":"Kopenhagenstraat 5",
    "sg:city":"Groningen",
    "sg:orig_category":"Hout Gh",
    "sg:phone":"+31 50 319 2888",
    "sg:postcode":"9723 BA",
    "sg:province":"Groningen",
    "wof:name":"Jongeneel Groningen Bv",
    "wof:placetype":"venue"
},
  "geometry": {"coordinates":[6.595214,53.218307],"type":"Point"}
}