{
  "type": "Feature",
  "properties": {
    "addr:full":"Traay 40 Driebergen Rysenb Utrecht 3971 GP",
    "addr:housenumber":"40",
    "addr:postcode":"3971 gp",
    "addr:street":"Traay;Rysenb",
    "iso:country":"NL",
    "sg:address":"Traay 40",
    "sg:city":"Driebergen Rysenb",
    "sg:orig_category":"Huishoudelijke Apparaten En Artikelen",
    "sg:phone":"+31 343 512 760",
    "sg:postcode":"3971 GP",
    "sg:province":"Utrecht",
    "wof:name":"Blokker Bv",
    "wof:placetype":"venue"
},
  "geometry": {"coordinates":[5.285762,52.05299],"type":"Point"}
}