{
  "type": "Feature",
  "properties": {
    "addr:full":"Katijdeweg 20 Beesd Gelderland 4153 RG",
    "addr:housenumber":"20",
    "addr:postcode":"4153 rg",
    "addr:street":"Katijdeweg;Gelderland",
    "iso:country":"NL",
    "sg:address":"Katijdeweg 20",
    "sg:city":"Beesd",
    "sg:orig_category":"Wegen And Sportterreinen",
    "sg:phone":"+31 345 681 298",
    "sg:postcode":"4153 RG",
    "sg:province":"Gelderland",
    "wof:name":"Aannemingsbedrijf De Jong En Zoon Beesd Bv",
    "wof:placetype":"venue"
},
  "geometry": {"coordinates":[5.1858878136,51.9126663208],"type":"Point"}
}