{
  "type": "Feature",
  "properties": {
    "addr:full":"Binnenweg 16 Nijeholtpade Provincie Friesland 8475 EG",
    "addr:housenumber":"16",
    "addr:postcode":"8475 eg",
    "addr:street":"Binnenweg;Provincie Friesland",
    "iso:country":"NL",
    "sg:address":"Binnenweg 16",
    "sg:city":"Nijeholtpade",
    "sg:orig_category":"Kappers",
    "sg:phone":"+31 561 688 297",
    "sg:postcode":"8475 EG",
    "sg:province":"Provincie Friesland",
    "wof:name":"Kapsalon Karola",
    "wof:placetype":"venue"
},
  "geometry": {"coordinates":[6.0843148232,52.9150886536],"type":"Point"}
}