{
  "type": "Feature",
  "properties": {
    "iso:country":"NL",
    "sg:address":"Pr Hendrikln 32",
    "sg:city":"Bergen Nh",
    "sg:orig_category":"Verzekeringen - Verzekeringskantoren",
    "sg:phone":"+31 72 581 3663",
    "sg:postcode":"1862 EL",
    "sg:province":"Noord-Holland",
    "wof:name":"Frans",
    "wof:placetype":"venue"
},
  "geometry": {"coordinates":[4.707698,52.671448],"type":"Point"}
}