{
  "type": "Feature",
  "properties": {
    "addr:full":"De Bosporus 45 Amstelveen Noord-Holland 1183 GE",
    "addr:housenumber":"45",
    "addr:postcode":"1183",
    "addr:street":"De Bosporus",
    "iso:country":"NL",
    "sg:address":"De Bosporus 45",
    "sg:city":"Amstelveen",
    "sg:orig_category":"Fotojournalisten Freelance",
    "sg:phone":"+31 20 645 6218",
    "sg:postcode":"1183 GE",
    "sg:province":"Noord-Holland",
    "wof:name":"Bruggen, S",
    "wof:placetype":"venue"
},
  "geometry": {"coordinates":[4.878133,52.310806],"type":"Point"}
}