{
  "type": "Feature",
  "properties": {
    "addr:full":"Lidwinastr 57 Vught Noord-Brabant 5262 EN",
    "addr:housenumber":"57",
    "addr:postcode":"5262 en",
    "addr:street":"Lidwinastr",
    "iso:country":"NL",
    "sg:address":"Lidwinastr 57",
    "sg:city":"Vught",
    "sg:orig_category":"Psychotherapeuten",
    "sg:phone":"+31 73 656 7675",
    "sg:postcode":"5262 EN",
    "sg:province":"Noord-Brabant",
    "wof:name":"Kobussen & Partners",
    "wof:placetype":"venue"
},
  "geometry": {"coordinates":[5.282858,51.644016],"type":"Point"}
}