{
  "type": "Feature",
  "properties": {
    "addr:full":"Damstraat 4 Leidschendam Zuid-Holland 2265 AG",
    "addr:housenumber":"4",
    "addr:postcode":"2265",
    "addr:street":"Damstraat",
    "iso:country":"NL",
    "sg:address":"Damstraat 4",
    "sg:city":"Leidschendam",
    "sg:orig_category":"Fruit And Groenten Gh",
    "sg:phone":"+31 70 320 4739",
    "sg:postcode":"2265 AG",
    "sg:province":"Zuid-Holland",
    "wof:name":"Van Rijn Groenten En Fruit",
    "wof:placetype":"venue"
},
  "geometry": {"coordinates":[4.397938,52.080727],"type":"Point"}
}