{
  "type": "Feature",
  "properties": {
    "addr:full":"Oeral 33 Utrecht Utrecht 3524 DS",
    "addr:housenumber":"33",
    "addr:postcode":"3524 ds",
    "addr:street":"Oeral",
    "iso:country":"NL",
    "sg:address":"Oeral 33",
    "sg:city":"Utrecht",
    "sg:orig_category":"Modeontwerpen",
    "sg:phone":"+31 30 289 0252",
    "sg:postcode":"3524 DS",
    "sg:province":"Utrecht",
    "wof:name":"Nemesis",
    "wof:placetype":"venue"
},
  "geometry": {"coordinates":[5.133974,52.064579],"type":"Point"}
}