{
  "type": "Feature",
  "properties": {
    "iso:country":"NL",
    "sg:address":"Markt 33",
    "sg:city":"Eersel",
    "sg:orig_category":"Kaas",
    "sg:phone":"+31 497 513 374",
    "sg:postcode":"5521 AK",
    "sg:province":"North Brabant",
    "wof:name":"Kuyten Specialiteiten, Ad",
    "wof:placetype":"venue"
},
  "geometry": {"coordinates":[5.3083438873,51.3592147827],"type":"Point"}
}