{
  "type": "Feature",
  "properties": {
    "addr:full":"Plein 14 Fil Nykerk Gld Gelderland 3861 AB",
    "addr:housenumber":"14",
    "addr:postcode":"3861 ab",
    "addr:street":"Plein;Gelderland",
    "iso:country":"NL",
    "sg:address":"Plein 14 Fil",
    "sg:city":"Nykerk Gld",
    "sg:orig_category":"Warenhuizen",
    "sg:phone":"+31 33 245 2011",
    "sg:postcode":"3861 AB",
    "sg:province":"Gelderland",
    "wof:name":"Hema",
    "wof:placetype":"venue"
},
  "geometry": {"coordinates":[5.4830999374,52.2215690613],"type":"Point"}
}