{
  "type": "Feature",
  "properties": {
    "addr:full":"Zuidpolderstraat 63 Rotterdam Zuid-Holland 3074 XT",
    "addr:housenumber":"63",
    "addr:postcode":"3074 xt",
    "addr:street":"Zuidpolderstraat",
    "iso:country":"NL",
    "sg:address":"Zuidpolderstraat 63",
    "sg:city":"Rotterdam",
    "sg:classifiers":[
        {
            "category":"Education",
            "subcategory":"Preschool",
            "type":"Public Place"
        }
    ],
    "sg:phone":"+31 10 485 1879",
    "sg:postcode":"3074 XT",
    "sg:province":"Zuid-Holland",
    "sg:tags":[
        "kleuteronderwijs",
        "basis-"
    ],
    "wof:name":"De Savornin Lohmanschool",
    "wof:placetype":"venue"
},
  "geometry": {"coordinates":[4.5090718269,51.8947296143],"type":"Point"}
}