{
  "type": "Feature",
  "properties": {
    "addr:full":"Langewolderwg 36 Oldekerk Groningen 9821 PP",
    "addr:housenumber":"36",
    "addr:postcode":"9821 pp",
    "addr:street":"Langewolderwg",
    "iso:country":"NL",
    "sg:address":"Langewolderwg 36",
    "sg:city":"Oldekerk",
    "sg:orig_category":"Land- En Tuinbouw - Mechanisatie",
    "sg:phone":"+31 594 695 600",
    "sg:postcode":"9821 PP",
    "sg:province":"Groningen",
    "wof:name":"Tjalma Bv, S",
    "wof:placetype":"venue"
},
  "geometry": {"coordinates":[6.318246,53.221088],"type":"Point"}
}