{
  "type": "Feature",
  "properties": {
    "addr:full":"Badwg 19 De Koog Noord-Holland 1796 AA",
    "addr:housenumber":"19",
    "addr:postcode":"1796 aa",
    "addr:street":"Badwg",
    "iso:country":"NL",
    "sg:address":"Badwg 19",
    "sg:city":"De Koog",
    "sg:orig_category":"Fietsen En Bromfietsen Verhuur",
    "sg:phone":"+31 222 317 215",
    "sg:postcode":"1796 AA",
    "sg:province":"Noord-Holland",
    "wof:name":"Kikkert",
    "wof:placetype":"venue"
},
  "geometry": {"coordinates":[4.761642,53.099987],"type":"Point"}
}