{
  "type": "Feature",
  "properties": {
    "addr:full":"Meerkoet 325 Diemen North Holland 1113 EB",
    "addr:housenumber":"325",
    "addr:postcode":"1113 eb",
    "addr:street":"Meerkoet",
    "iso:country":"NL",
    "sg:address":"Meerkoet 325",
    "sg:city":"Diemen",
    "sg:orig_category":"Kantoor- En Secretariaatsservice",
    "sg:phone":"+31 20 699 6320",
    "sg:postcode":"1113 EB",
    "sg:province":"North Holland",
    "wof:name":"Mexs",
    "wof:placetype":"venue"
},
  "geometry": {"coordinates":[4.9781727791,52.351600647],"type":"Point"}
}