{
  "type": "Feature",
  "properties": {
    "addr:full":"Heuvelstr 60 Veldhoven North Brabant 5502 AE",
    "addr:housenumber":"60",
    "addr:postcode":"5502 ae",
    "addr:street":"Heuvelstr",
    "iso:country":"NL",
    "sg:address":"Heuvelstr 60",
    "sg:city":"Veldhoven",
    "sg:orig_category":"Kopieerservice",
    "sg:phone":"+31 40 255 4895",
    "sg:postcode":"5502 AE",
    "sg:province":"North Brabant",
    "wof:name":"Montis",
    "wof:placetype":"venue"
},
  "geometry": {"coordinates":[5.408145,51.422909],"type":"Point"}
}