{
  "type": "Feature",
  "properties": {
    "addr:full":"Ambachtswg 72 Utrecht Utrecht 3542 DH",
    "addr:housenumber":"72",
    "addr:postcode":"3542 dh",
    "addr:street":"Ambachtswg",
    "iso:country":"NL",
    "sg:address":"Ambachtswg 72",
    "sg:city":"Utrecht",
    "sg:orig_category":"Drukkerijen",
    "sg:phone":"+31 30 241 6975",
    "sg:postcode":"3542 DH",
    "sg:province":"Utrecht",
    "sg:website":"http://www.print-en-web.com",
    "wof:name":"Print-En-Web Communicatie",
    "wof:placetype":"venue"
},
  "geometry": {"coordinates":[5.047052,52.122589],"type":"Point"}
}