{
  "type": "Feature",
  "properties": {
    "iso:country":"NL",
    "sg:address":"Muurhuizen 34",
    "sg:city":"Amersfoort",
    "sg:orig_category":"Psychotherapeuten",
    "sg:phone":"+31 33 462 1581",
    "sg:postcode":"3811 EJ",
    "sg:province":"Utrecht",
    "wof:name":"Praktijk Voor Psychosynthese",
    "wof:placetype":"venue"
},
  "geometry": {"coordinates":[5.391641,52.154911],"type":"Point"}
}