{
  "type": "Feature",
  "properties": {
    "addr:full":"Clara Visserstraat 122 Purmerend North Holland 1447 HT",
    "addr:housenumber":"122",
    "addr:postcode":"1447 ht",
    "addr:street":"Clara Visserstraat",
    "iso:country":"NL",
    "sg:address":"Clara Visserstraat 122",
    "sg:city":"Purmerend",
    "sg:orig_category":"Paramedische Behandelingen",
    "sg:phone":"+31 299 647 643",
    "sg:postcode":"1447 HT",
    "sg:province":"North Holland",
    "wof:name":"Praktijk Voor Logopedie",
    "wof:placetype":"venue"
},
  "geometry": {"coordinates":[4.963391,52.493458],"type":"Point"}
}