{
  "type": "Feature",
  "properties": {
    "iso:country":"NL",
    "sg:address":"Oostersngl 28",
    "sg:city":"Medemblik",
    "sg:orig_category":"Artsen - Huisartsen",
    "sg:phone":"+31 227 547 547",
    "sg:postcode":"1671 HC",
    "sg:province":"Noord-Holland",
    "sg:website":"http://www.ajdejager.praktijkinfo.nl",
    "wof:name":"Jager, A J De",
    "wof:placetype":"venue"
},
  "geometry": {"coordinates":[5.106715,52.771942],"type":"Point"}
}