{
  "type": "Feature",
  "properties": {
    "addr:full":"Akkerwinde 40 Zwaag Noord-Holland 1689 NT",
    "addr:housenumber":"40",
    "addr:postcode":"1689 nt",
    "addr:street":"Akkerwinde",
    "iso:country":"NL",
    "sg:address":"Akkerwinde 40",
    "sg:city":"Zwaag",
    "sg:orig_category":"Administratie- En Boekhoudkantoren",
    "sg:phone":"+31 229 235 151",
    "sg:postcode":"1689 NT",
    "sg:province":"Noord-Holland",
    "wof:name":"Bab",
    "wof:placetype":"venue"
},
  "geometry": {"coordinates":[5.047185,52.666435],"type":"Point"}
}