{
  "type": "Feature",
  "properties": {
    "iso:country":"NL",
    "sg:address":"Atlantischestr 18",
    "sg:city":"Emmeloord",
    "sg:orig_category":"Verenigingsgebouwen",
    "sg:phone":"+31 527 698 236",
    "sg:postcode":"8303 VW",
    "sg:province":"NL.",
    "wof:name":"Espelervaart",
    "wof:placetype":"venue"
},
  "geometry": {"coordinates":[5.732693,52.712948],"type":"Point"}
}