{
  "type": "Feature",
  "properties": {
    "addr:full":"Atlantischestr 18 Emmeloord NL. 8303 VW",
    "addr:housenumber":"18",
    "addr:postcode":"8303",
    "addr:street":"Atlantischestr;Nl.;Vw",
    "iso:country":"NL",
    "sg:address":"Atlantischestr 18",
    "sg:city":"Emmeloord",
    "sg:orig_category":"Verenigingsgebouwen",
    "sg:phone":"+31 527 698 236",
    "sg:postcode":"8303 VW",
    "sg:province":"NL.",
    "wof:name":"Espelervaart",
    "wof:placetype":"venue"
},
  "geometry": {"coordinates":[5.732693,52.712948],"type":"Point"}
}