{
  "type": "Feature",
  "properties": {
    "iso:country":"NL",
    "sg:address":"Joubertstraat 23",
    "sg:city":"Den Helder",
    "sg:orig_category":"Huishoudapparatuur, Televisies And Radio'S",
    "sg:phone":"+31 223 624 053",
    "sg:postcode":"1782 SB",
    "sg:province":"Noord-Holland",
    "wof:name":"Sp Janssen",
    "wof:placetype":"venue"
},
  "geometry": {"coordinates":[4.754233,52.959156],"type":"Point"}
}