{
  "type": "Feature",
  "properties": {
    "addr:full":"Groenestraat 294 Nijmegen Gelderland 6531 JC",
    "addr:housenumber":"294",
    "addr:postcode":"6531 jc",
    "addr:street":"Groenestraat;Gelderland",
    "iso:country":"NL",
    "sg:address":"Groenestraat 294",
    "sg:city":"Nijmegen",
    "sg:orig_category":"Krantenuitgeverijen",
    "sg:phone":"+31 24 350 1130",
    "sg:postcode":"6531 JC",
    "sg:province":"Gelderland",
    "wof:name":"Etnicom",
    "wof:placetype":"venue"
},
  "geometry": {"coordinates":[5.844907,51.831577],"type":"Point"}
}