{
  "type": "Feature",
  "properties": {
    "addr:full":"Graafsewg 241J S Hertogenbosch North Brabant 5213 AH",
    "addr:housenumber":"241j",
    "addr:postcode":"5213 ah",
    "addr:street":"Graafsewg;S Hertogenbosch",
    "iso:country":"NL",
    "sg:address":"Graafsewg 241J",
    "sg:city":"S Hertogenbosch",
    "sg:orig_category":"Accountants - Administratie- Consulenten En -Kantoren",
    "sg:phone":"+31 73 613 5099",
    "sg:postcode":"5213 AH",
    "sg:province":"North Brabant",
    "wof:name":"Verdaasdonk, F J C",
    "wof:placetype":"venue"
},
  "geometry": {"coordinates":[5.328136,51.697132],"type":"Point"}
}