{
  "type": "Feature",
  "properties": {
    "addr:full":"S-Gravendreef 10 Capelle A/D Ijssel Zuid-Holland 2902 LJ",
    "addr:housenumber":"10;a / d",
    "addr:postcode":"2902 lj",
    "addr:street":"S-Gravendreef",
    "iso:country":"NL",
    "sg:address":"S-Gravendreef 10",
    "sg:city":"Capelle A/D Ijssel",
    "sg:classifiers":[
        {
            "category":"Professional",
            "subcategory":"Accounting & Tax Preparation",
            "type":"Services"
        }
    ],
    "sg:phone":"+31 10 450 8725",
    "sg:postcode":"2902 LJ",
    "sg:province":"Zuid-Holland",
    "sg:tags":[
        "accountant"
    ],
    "wof:name":"W J V Prooijen Accountant-Administratiec",
    "wof:placetype":"venue"
},
  "geometry": {"coordinates":[4.578109,51.933392],"type":"Point"}
}