{
  "type": "Feature",
  "properties": {
    "addr:full":"Past V Leeuwenstr 90 Helmond Noord-Brabant 5701 JW",
    "addr:housenumber":"90",
    "addr:postcode":"5701 jw",
    "addr:street":"Past;Leeuwenstr",
    "iso:country":"NL",
    "sg:address":"Past V Leeuwenstr 90",
    "sg:city":"Helmond",
    "sg:orig_category":"Meubelstoffering",
    "sg:phone":"+31 492 550 612",
    "sg:postcode":"5701 JW",
    "sg:province":"Noord-Brabant",
    "sg:website":"http://www.lederdokter.nl",
    "wof:name":"Lederdokter, De",
    "wof:placetype":"venue"
},
  "geometry": {"coordinates":[5.658284,51.482239],"type":"Point"}
}