{
  "type": "Feature",
  "properties": {
    "addr:full":"Burg Colynstr 40 Boskoop Zuid-Holland 2771 GG",
    "addr:housenumber":"40",
    "addr:postcode":"2771 gg",
    "addr:street":"Burg",
    "iso:country":"NL",
    "sg:address":"Burg Colynstr 40",
    "sg:city":"Boskoop",
    "sg:orig_category":"Hoefsmederijen",
    "sg:phone":"+31 6 27043510",
    "sg:postcode":"2771 GG",
    "sg:province":"Zuid-Holland",
    "wof:name":"Arbouw Hoefsmederij C",
    "wof:placetype":"venue"
},
  "geometry": {"coordinates":[4.65922,52.074268],"type":"Point"}
}