{
  "type": "Feature",
  "properties": {
    "iso:country":"NL",
    "sg:address":"O Zeedk 4",
    "sg:city":"Colynsplaat",
    "sg:orig_category":"Machinefabrieken",
    "sg:phone":"+31 113 693 010",
    "sg:postcode":"4486 PN",
    "sg:province":"Zeeland",
    "sg:website":"http://www.wissekramer.nl",
    "wof:name":"Wisse Kramer Bv",
    "wof:placetype":"venue"
},
  "geometry": {"coordinates":[3.84761,51.599251],"type":"Point"}
}