{
  "type": "Feature",
  "properties": {
    "addr:full":"Zuiderhavenweg 4 Tiel Gelderland 4004 JJ",
    "addr:housenumber":"4",
    "addr:postcode":"4004 jj",
    "addr:street":"Zuiderhavenweg;Gelderland",
    "iso:country":"NL",
    "sg:address":"Zuiderhavenweg 4",
    "sg:city":"Tiel",
    "sg:orig_category":"Zuivelproducten And Spijsoli?n Gh",
    "sg:phone":"+31 344 611 056",
    "sg:postcode":"4004 JJ",
    "sg:province":"Gelderland",
    "wof:name":"Craamer & Co Bv",
    "wof:placetype":"venue"
},
  "geometry": {"coordinates":[5.436657,51.903389],"type":"Point"}
}