{
  "type": "Feature",
  "properties": {
    "iso:country":"NL",
    "sg:address":"Molendk 4A",
    "sg:city":"Beesd",
    "sg:orig_category":"Bloemen En Planten",
    "sg:phone":"+31 345 681 386",
    "sg:postcode":"4153 AV",
    "sg:province":"Gelderland",
    "wof:name":"Vaal, H G A",
    "wof:placetype":"venue"
},
  "geometry": {"coordinates":[5.197965,51.884548],"type":"Point"}
}