{
  "type": "Feature",
  "properties": {
    "addr:full":"Plein 21 Kerkrade Limburg 6466 GG",
    "addr:housenumber":"21",
    "addr:postcode":"6466 gg",
    "addr:street":"Plein",
    "iso:country":"NL",
    "sg:address":"Plein 21",
    "sg:city":"Kerkrade",
    "sg:orig_category":"Kappers",
    "sg:phone":"+31 45 541 1505",
    "sg:postcode":"6466 GG",
    "sg:province":"Limburg",
    "wof:name":"Kapsalon Danielle",
    "wof:placetype":"venue"
},
  "geometry": {"coordinates":[6.0251197815,50.8548851013],"type":"Point"}
}