{
  "type": "Feature",
  "properties": {
    "addr:full":"Bouwlustln 57 S Gravenhage Zuid-Holland 2544 JN",
    "addr:housenumber":"57;gravenhage",
    "addr:postcode":"2544 jn",
    "addr:street":"Bouwlustln;S",
    "iso:country":"NL",
    "sg:address":"Bouwlustln 57",
    "sg:city":"S Gravenhage",
    "sg:orig_category":"Kappers",
    "sg:phone":"+31 70 366 5549",
    "sg:postcode":"2544 JN",
    "sg:province":"Zuid-Holland",
    "wof:name":"Marga'S",
    "wof:placetype":"venue"
},
  "geometry": {"coordinates":[4.25157,52.039551],"type":"Point"}
}