{
  "type": "Feature",
  "properties": {
    "addr:full":"Linnaeusstraat 87 Amsterdam North Holland 1093 EK",
    "addr:housenumber":"87",
    "addr:postcode":"1093 ek",
    "addr:street":"Linnaeusstraat",
    "iso:country":"NL",
    "sg:address":"Linnaeusstraat 87",
    "sg:city":"Amsterdam",
    "sg:orig_category":"Opticiens",
    "sg:phone":"+31 20 665 4663",
    "sg:postcode":"1093 EK",
    "sg:province":"North Holland",
    "wof:name":"Paul Bas Optiek",
    "wof:placetype":"venue"
},
  "geometry": {"coordinates":[4.9257497787,52.3595695496],"type":"Point"}
}