{
  "type": "Feature",
  "properties": {
    "iso:country":"NL",
    "sg:address":"Boerhaavestraat 23",
    "sg:city":"Kruiningen",
    "sg:orig_category":"Beautyfarms And Sauna'S",
    "sg:phone":"+31 113 382 534",
    "sg:postcode":"4416 EH",
    "sg:province":"Zeeland",
    "wof:name":"M.J. Mieras",
    "wof:placetype":"venue"
},
  "geometry": {"coordinates":[4.030982,51.447136],"type":"Point"}
}