{
  "type": "Feature",
  "properties": {
    "iso:country":"NL",
    "sg:address":"Drs F Bylwg 242",
    "sg:city":"Den Helder",
    "sg:orig_category":"Bedrijfskleding",
    "sg:phone":"+31 223 660 377",
    "sg:postcode":"1784 MC",
    "sg:province":"Noord-Holland",
    "sg:website":"http://www.rutransenpartners.nl",
    "wof:name":"Rutrans & Partn",
    "wof:placetype":"venue"
},
  "geometry": {"coordinates":[4.75598,52.936436],"type":"Point"}
}