{
  "type": "Feature",
  "properties": {
    "addr:full":"Vronkenln 46 Leiderdorp South Holland 2352 EP",
    "addr:housenumber":"46",
    "addr:postcode":"2352 ep",
    "addr:street":"Vronkenln",
    "iso:country":"NL",
    "sg:address":"Vronkenln 46",
    "sg:city":"Leiderdorp",
    "sg:orig_category":"Scholen Voor Basisonderwijs",
    "sg:phone":"+31 71 589 1910",
    "sg:postcode":"2352 EP",
    "sg:province":"South Holland",
    "wof:name":"Gomarus",
    "wof:placetype":"venue"
},
  "geometry": {"coordinates":[4.527157,52.161865],"type":"Point"}
}