{
  "type": "Feature",
  "properties": {
    "iso:country":"NL",
    "sg:address":"Holzstraat 138",
    "sg:city":"Kerkrade",
    "sg:orig_category":"Bloemen And Planten",
    "sg:phone":"+31 45 545 5175",
    "sg:postcode":"6461 HS",
    "sg:province":"Limburg",
    "wof:name":"Bloemenhandel De Humaan",
    "wof:placetype":"venue"
},
  "geometry": {"coordinates":[6.076615,50.860905],"type":"Point"}
}