{
  "type": "Feature",
  "properties": {
    "addr:full":"Koeveldsestr 4 Helmond Noord-Brabant 5706 AT",
    "addr:housenumber":"4",
    "addr:postcode":"5706",
    "addr:street":"Koeveldsestr",
    "iso:country":"NL",
    "sg:address":"Koeveldsestr 4",
    "sg:city":"Helmond",
    "sg:orig_category":"Verenigingsgebouwen",
    "sg:phone":"+31 492 524 041",
    "sg:postcode":"5706 AT",
    "sg:province":"Noord-Brabant",
    "wof:name":"Zulderke, 'T",
    "wof:placetype":"venue"
},
  "geometry": {"coordinates":[5.634486,51.464088],"type":"Point"}
}