{
  "type": "Feature",
  "properties": {
    "addr:full":"Fazantenstr 16 Zandvoort Noord-Holland 2042 CK",
    "addr:housenumber":"16",
    "addr:postcode":"2042 ck",
    "addr:street":"Fazantenstr",
    "iso:country":"NL",
    "sg:address":"Fazantenstr 16",
    "sg:city":"Zandvoort",
    "sg:orig_category":"Juweliers",
    "sg:phone":"+31 23 571 7218",
    "sg:postcode":"2042 CK",
    "sg:province":"Noord-Holland",
    "wof:name":"Pearl Service",
    "wof:placetype":"venue"
},
  "geometry": {"coordinates":[4.533178,52.368446],"type":"Point"}
}