{
  "type": "Feature",
  "properties": {
    "addr:full":"Rozemarijnhof 15 Leidschendam Zuid-Holland 2262 AD",
    "addr:housenumber":"15",
    "addr:postcode":"2262 ad",
    "addr:street":"Rozemarijnhof",
    "iso:country":"NL",
    "sg:address":"Rozemarijnhof 15",
    "sg:city":"Leidschendam",
    "sg:orig_category":"Boekenuitgeverijen",
    "sg:phone":"+31 70 317 7381",
    "sg:postcode":"2262 AD",
    "sg:province":"Zuid-Holland",
    "wof:name":"Boekenvoordeel Bv",
    "wof:placetype":"venue"
},
  "geometry": {"coordinates":[4.383174,52.088131],"type":"Point"}
}