{
  "type": "Feature",
  "properties": {
    "addr:full":"Zeilmakerstraat 40 Velserbroek Noord-Holland 1991 JC",
    "addr:housenumber":"40",
    "addr:postcode":"1991 jc",
    "addr:street":"Zeilmakerstraat",
    "iso:country":"NL",
    "sg:address":"Zeilmakerstraat 40",
    "sg:city":"Velserbroek",
    "sg:orig_category":"Apothekers",
    "sg:phone":"+31 23 538 3874",
    "sg:postcode":"1991 JC",
    "sg:province":"Noord-Holland",
    "wof:name":"Farmaceutische Thuiszorg Kennemerland",
    "wof:placetype":"venue"
},
  "geometry": {"coordinates":[4.653765,52.436321],"type":"Point"}
}