{
  "type": "Feature",
  "properties": {
    "addr:full":"Voorstr 3 Piershil South Holland 3265 BT",
    "addr:housenumber":"3",
    "addr:postcode":"3265 bt",
    "addr:street":"Voorstr",
    "iso:country":"NL",
    "sg:address":"Voorstr 3",
    "sg:city":"Piershil",
    "sg:orig_category":"Verhuur",
    "sg:phone":"+31 186 690 999",
    "sg:postcode":"3265 BT",
    "sg:province":"South Holland",
    "wof:name":"H20 Bv",
    "wof:placetype":"venue"
},
  "geometry": {"coordinates":[4.312532,51.793636],"type":"Point"}
}