{
  "type": "Feature",
  "properties": {
    "iso:country":"NL",
    "sg:address":"Kortelingstr 70",
    "sg:city":"Deventer",
    "sg:orig_category":"Behangers",
    "sg:phone":"+31 570 643 308",
    "sg:postcode":"7412 JM",
    "sg:province":"Overijssel",
    "wof:name":"Sneller, M S",
    "wof:placetype":"venue"
},
  "geometry": {"coordinates":[6.138081,52.260921],"type":"Point"}
}