{
  "type": "Feature",
  "properties": {
    "addr:full":"Hg Maasdk 9 Heusden Gem Heusd Noord-Brabant 5256 TE",
    "addr:housenumber":"9",
    "addr:postcode":"heusd;5256 te",
    "iso:country":"NL",
    "sg:address":"Hg Maasdk 9",
    "sg:city":"Heusden Gem Heusd",
    "sg:orig_category":"Galeries",
    "sg:phone":"+31 416 662 615",
    "sg:postcode":"5256 TE",
    "sg:province":"Noord-Brabant",
    "sg:website":"http://www.galerie-inipi.nl",
    "wof:name":"Inipi, Galerie",
    "wof:placetype":"venue"
},
  "geometry": {"coordinates":[5.189993,51.729622],"type":"Point"}
}