{
  "type": "Feature",
  "properties": {
    "addr:full":"Albionstr 60 Tilburg Noord-Brabant 5047 SN",
    "addr:housenumber":"60",
    "addr:postcode":"5047 sn",
    "addr:street":"Albionstr",
    "iso:country":"NL",
    "sg:address":"Albionstr 60",
    "sg:city":"Tilburg",
    "sg:orig_category":"Grondwerken",
    "sg:phone":"+31 13 570 0816",
    "sg:postcode":"5047 SN",
    "sg:province":"Noord-Brabant",
    "wof:name":"Gaal Bv, C J M Van",
    "wof:placetype":"venue"
},
  "geometry": {"coordinates":[5.036505,51.584824],"type":"Point"}
}