{
  "type": "Feature",
  "properties": {
    "addr:full":"Heesakkerweg 26 Asten North Brabant 5721 KR",
    "addr:housenumber":"26",
    "addr:postcode":"5721 kr",
    "addr:street":"Heesakkerweg",
    "iso:country":"NL",
    "sg:address":"Heesakkerweg 26",
    "sg:city":"Asten",
    "sg:orig_category":"Kappers",
    "sg:phone":"+31 493 691 589",
    "sg:postcode":"5721 KR",
    "sg:province":"North Brabant",
    "wof:name":"Salon Unique",
    "wof:placetype":"venue"
},
  "geometry": {"coordinates":[5.735305,51.398579],"type":"Point"}
}