{
  "type": "Feature",
  "properties": {
    "addr:full":"Klaproosweide 24 Woerden South Holland 3448 JH",
    "addr:housenumber":"24",
    "addr:postcode":"3448 jh",
    "addr:street":"Klaproosweide",
    "iso:country":"NL",
    "sg:address":"Klaproosweide 24",
    "sg:city":"Woerden",
    "sg:orig_category":"Bestratingen",
    "sg:phone":"+31 348 412 034",
    "sg:postcode":"3448 JH",
    "sg:province":"South Holland",
    "wof:name":"Duuren Bv, J Van",
    "wof:placetype":"venue"
},
  "geometry": {"coordinates":[4.859881,52.076401],"type":"Point"}
}