{
  "type": "Feature",
  "properties": {
    "addr:full":"Boerhaaveln 296 Leiden Zuid-Holland 2334 EZ",
    "addr:housenumber":"296",
    "addr:postcode":"2334 ez",
    "iso:country":"NL",
    "sg:address":"Boerhaaveln 296",
    "sg:city":"Leiden",
    "sg:orig_category":"Geluidsopnamestudio'S",
    "sg:phone":"+31 71 515 7881",
    "sg:postcode":"2334 EZ",
    "sg:province":"Zuid-Holland",
    "wof:name":"Castle",
    "wof:placetype":"venue"
},
  "geometry": {"coordinates":[4.48274,52.173561],"type":"Point"}
}