{
  "type": "Feature",
  "properties": {
    "addr:full":"Spieghelstr 2 Groningen Groningen 9721 JW",
    "addr:housenumber":"2",
    "addr:postcode":"9721 jw",
    "addr:street":"Spieghelstr",
    "iso:country":"NL",
    "sg:address":"Spieghelstr 2",
    "sg:city":"Groningen",
    "sg:orig_category":"Kappers",
    "sg:phone":"+31 50 525 0819",
    "sg:postcode":"9721 JW",
    "sg:province":"Groningen",
    "wof:name":"Mb",
    "wof:placetype":"venue"
},
  "geometry": {"coordinates":[6.574736,53.195496],"type":"Point"}
}