{
  "type": "Feature",
  "properties": {
    "iso:country":"NL",
    "sg:address":"C Westerveldstraat 1",
    "sg:city":"Steggerda",
    "sg:classifiers":[
        {
            "category":"Education",
            "subcategory":"Preschool",
            "type":"Public Place"
        }
    ],
    "sg:phone":"+31 561 441 601",
    "sg:postcode":"8395 PW",
    "sg:province":"Friesland",
    "sg:tags":[
        "kleuteronderwijs",
        "basis-"
    ],
    "wof:name":"Openbare Basisschool Triangel",
    "wof:placetype":"venue"
},
  "geometry": {"coordinates":[6.076981,52.857014],"type":"Point"}
}