{
  "type": "Feature",
  "properties": {
    "iso:country":"NL",
    "sg:address":"Dorpsdijk 21",
    "sg:city":"Rhoon",
    "sg:orig_category":"Autokeuringen",
    "sg:phone":"+31 10 501 5101",
    "sg:postcode":"3161 KB",
    "sg:province":"Zuid-Holland",
    "wof:name":"L Kolpa",
    "wof:placetype":"venue"
},
  "geometry": {"coordinates":[4.413963,51.863552],"type":"Point"}
}