{
  "type": "Feature",
  "properties": {
    "addr:full":"Morgenster 2 Nijverdal NL.08 7443 LA",
    "addr:housenumber":"2;nl.08",
    "addr:postcode":"7443 la",
    "addr:street":"Morgenster",
    "iso:country":"NL",
    "sg:address":"Morgenster 2",
    "sg:city":"Nijverdal",
    "sg:classifiers":[
        {
            "category":"Education",
            "subcategory":"Preschool",
            "type":"Public Place"
        }
    ],
    "sg:phone":"+31 548 617 316",
    "sg:postcode":"7443 LA",
    "sg:province":"NL.08",
    "sg:tags":[
        "kleuteronderwijs",
        "basis-"
    ],
    "wof:name":"Basisschool De Tormentil",
    "wof:placetype":"venue"
},
  "geometry": {"coordinates":[6.485121,52.37838],"type":"Point"}
}