{
  "type": "Feature",
  "properties": {
    "addr:full":"Raadhuisstraat 60 Heemstede North Holland 2101 HJ",
    "addr:housenumber":"60",
    "addr:postcode":"2101 hj",
    "addr:street":"Raadhuisstraat",
    "iso:country":"NL",
    "sg:address":"Raadhuisstraat 60",
    "sg:city":"Heemstede",
    "sg:orig_category":"Damesmodezaken",
    "sg:phone":"+31 23 529 4186",
    "sg:postcode":"2101 HJ",
    "sg:province":"North Holland",
    "wof:name":"Bon Coeur Mode",
    "wof:placetype":"venue"
},
  "geometry": {"coordinates":[4.62119,52.348976],"type":"Point"}
}