{
  "type": "Feature",
  "properties": {
    "iso:country":"NL",
    "sg:address":"Juliana Van Stolberglaan 114",
    "sg:city":"Naarden",
    "sg:orig_category":"Huishoudapparatuur, Televisies And Radio'S",
    "sg:phone":"+31 35 694 6395",
    "sg:postcode":"1412 BK",
    "sg:province":"Noord-Holland",
    "wof:name":"Luxcrypt Bv",
    "wof:placetype":"venue"
},
  "geometry": {"coordinates":[5.150823,52.288223],"type":"Point"}
}