{
  "type": "Feature",
  "properties": {
    "addr:full":"Paletplein 5 Tilburg Noord-Brabant 5044 JB",
    "addr:housenumber":"5",
    "addr:postcode":"5044 jb",
    "addr:street":"Paletplein",
    "iso:country":"NL",
    "sg:address":"Paletplein 5",
    "sg:city":"Tilburg",
    "sg:classifiers":[
        {
            "category":"Fast Food",
            "type":"Food & Drink"
        }
    ],
    "sg:phone":"+31 13 467 6676",
    "sg:postcode":"5044 JB",
    "sg:province":"Noord-Brabant",
    "sg:tags":[
        "afhaal",
        "restaurant"
    ],
    "wof:name":"Snackbar Paletplein",
    "wof:placetype":"venue"
},
  "geometry": {"coordinates":[5.039361,51.576138],"type":"Point"}
}