{
  "type": "Feature",
  "properties": {
    "iso:country":"NL",
    "sg:address":"Boksdoornstraat 1",
    "sg:city":"Ridderkerk",
    "sg:orig_category":"Beautyfarms And Sauna'S",
    "sg:phone":"+31 180 418 178",
    "sg:postcode":"2982 BA",
    "sg:province":"Zuid-Holland",
    "wof:name":"La Maison Cosmetique",
    "wof:placetype":"venue"
},
  "geometry": {"coordinates":[4.58853,51.87051],"type":"Point"}
}