{
  "type": "Feature",
  "properties": {
    "addr:full":"Oliemulderswg 43 Groningen Groningen 9713 VA",
    "addr:housenumber":"43",
    "addr:postcode":"9713",
    "addr:street":"Oliemulderswg",
    "iso:country":"NL",
    "sg:address":"Oliemulderswg 43",
    "sg:city":"Groningen",
    "sg:orig_category":"Zalenverhuur",
    "sg:phone":"+31 50 312 6937",
    "sg:postcode":"9713 VA",
    "sg:province":"Groningen",
    "wof:name":"Jannes Van Der Wal, Centrum",
    "wof:placetype":"venue"
},
  "geometry": {"coordinates":[6.588945,53.223167],"type":"Point"}
}