{
  "type": "Feature",
  "properties": {
    "iso:country":"NL",
    "sg:address":"Stoeldraaierstr 3",
    "sg:city":"Groningen",
    "sg:orig_category":"Juweliers",
    "sg:phone":"+31 50 318 1111",
    "sg:postcode":"9712 BT",
    "sg:province":"Groningen",
    "sg:website":"http://www.deschatkamer.nl",
    "wof:name":"Schatkamer Juwelier, De",
    "wof:placetype":"venue"
},
  "geometry": {"coordinates":[6.563831,53.217182],"type":"Point"}
}