{
  "type": "Feature",
  "properties": {
    "iso:country":"NL",
    "sg:address":"Humperdinckln 1",
    "sg:city":"Eindhoven",
    "sg:classifiers":[
        {
            "category":"Personal",
            "subcategory":"Nail Salon",
            "type":"Services"
        }
    ],
    "sg:phone":"+31 40 251 2656",
    "sg:postcode":"5654 PA",
    "sg:province":"North Brabant",
    "sg:tags":[
        "pedicure"
    ],
    "wof:name":"Velden, C A Van Der",
    "wof:placetype":"venue"
},
  "geometry": {"coordinates":[5.45901,51.420891],"type":"Point"}
}