{
  "type": "Feature",
  "properties": {
    "addr:full":"Steengrachtstr 45 Vlissingen Zeeland 4386 AS",
    "addr:housenumber":"45",
    "addr:postcode":"4386 as",
    "addr:street":"Steengrachtstr",
    "iso:country":"NL",
    "sg:address":"Steengrachtstr 45",
    "sg:city":"Vlissingen",
    "sg:orig_category":"Glazenwasserijen",
    "sg:phone":"+31 118 468 169",
    "sg:postcode":"4386 AS",
    "sg:province":"Zeeland",
    "wof:name":"Best",
    "wof:placetype":"venue"
},
  "geometry": {"coordinates":[3.590487,51.466518],"type":"Point"}
}