{
  "type": "Feature",
  "properties": {
    "addr:full":"Ambyerstr N 48A Maastricht Limburg 6225 EE",
    "addr:housenumber":"48a",
    "addr:postcode":"6225 ee",
    "addr:street":"N",
    "iso:country":"NL",
    "sg:address":"Ambyerstr N 48A",
    "sg:city":"Maastricht",
    "sg:orig_category":"Kappers",
    "sg:phone":"+31 43 363 6960",
    "sg:postcode":"6225 EE",
    "sg:province":"Limburg",
    "wof:name":"Tjua",
    "wof:placetype":"venue"
},
  "geometry": {"coordinates":[5.732632,50.863285],"type":"Point"}
}