{
  "type": "Feature",
  "properties": {
    "iso:country":"NL",
    "sg:address":"Menninckstr 92",
    "sg:city":"S Gravenhage",
    "sg:orig_category":"Vakantievervoer",
    "sg:phone":"+31 70 354 7372",
    "sg:postcode":"2583 BS",
    "sg:province":"South Holland",
    "wof:name":"Jong, Gebr De",
    "wof:placetype":"venue"
},
  "geometry": {"coordinates":[4.25526,52.09124],"type":"Point"}
}