{
  "type": "Feature",
  "properties": {
    "addr:full":"Schubertstr 13 Hengelo Ov NL.08 7557 CJ",
    "addr:housenumber":"13",
    "addr:postcode":"7557",
    "addr:street":"Schubertstr;Ov;Cj",
    "iso:country":"NL",
    "sg:address":"Schubertstr 13",
    "sg:city":"Hengelo Ov",
    "sg:orig_category":"Artsen - Huisartsen",
    "sg:phone":"+31 74 291 2125",
    "sg:postcode":"7557 CJ",
    "sg:province":"NL.08",
    "wof:name":"D\u00e1hollosy, H A",
    "wof:placetype":"venue"
},
  "geometry": {"coordinates":[6.817276,52.271969],"type":"Point"}
}