{
  "type": "Feature",
  "properties": {
    "addr:full":"Emmastr 33 S Gravenhage Zuid-Holland 2595 EH",
    "addr:housenumber":"33;gravenhage",
    "addr:postcode":"2595 eh",
    "addr:street":"Emmastr;S",
    "iso:country":"NL",
    "sg:address":"Emmastr 33",
    "sg:city":"S Gravenhage",
    "sg:orig_category":"Kinderopvang",
    "sg:phone":"+31 70 383 7954",
    "sg:postcode":"2595 EH",
    "sg:province":"Zuid-Holland",
    "wof:name":"Thera",
    "wof:placetype":"venue"
},
  "geometry": {"coordinates":[4.33507,52.081421],"type":"Point"}
}