{
  "type": "Feature",
  "properties": {
    "addr:full":"Stationspln 2 Bergen Op Zoom North Brabant 4611 BX",
    "addr:housenumber":"2",
    "addr:postcode":"4611 bx",
    "addr:street":"Stationspln",
    "iso:country":"NL",
    "sg:address":"Stationspln 2",
    "sg:city":"Bergen Op Zoom",
    "sg:orig_category":"Bloemen En Planten",
    "sg:phone":"+31 164 235 354",
    "sg:postcode":"4611 BX",
    "sg:province":"North Brabant",
    "wof:name":"Station Bergen",
    "wof:placetype":"venue"
},
  "geometry": {"coordinates":[4.295618,51.494846],"type":"Point"}
}