{
  "type": "Feature",
  "properties": {
    "addr:full":"Vorenseindsewg 1C Sprundel North Brabant 4714 BE",
    "addr:housenumber":"1c",
    "addr:postcode":"4714",
    "addr:street":"Vorenseindsewg",
    "iso:country":"NL",
    "sg:address":"Vorenseindsewg 1C",
    "sg:city":"Sprundel",
    "sg:orig_category":"Kappers",
    "sg:phone":"+31 165 387 262",
    "sg:postcode":"4714 BE",
    "sg:province":"North Brabant",
    "wof:name":"Kim Kim Haaridee",
    "wof:placetype":"venue"
},
  "geometry": {"coordinates":[4.5951528549,51.5364456177],"type":"Point"}
}