{
  "type": "Feature",
  "properties": {
    "addr:full":"Postbus 1016 Maastricht Noord-Holland 6201 BA",
    "addr:housenumber":"1016",
    "addr:postcode":"6201 ba",
    "addr:street":"Postbus",
    "iso:country":"NL",
    "sg:address":"Postbus 1016",
    "sg:city":"Maastricht",
    "sg:orig_category":"Adviesbureaus Economie",
    "sg:phone":"+31 43 388 3955",
    "sg:postcode":"6201 BA",
    "sg:province":"Noord-Holland",
    "wof:name":"Etil Bv",
    "wof:placetype":"venue"
},
  "geometry": {"coordinates":[5.68726,50.84985],"type":"Point"}
}