{
  "type": "Feature",
  "properties": {
    "addr:full":"Nw Langendk 77 Delft Zuid-Holland 2611 VJ",
    "addr:housenumber":"77",
    "addr:postcode":"2611 vj",
    "addr:street":"Delft",
    "iso:country":"NL",
    "sg:address":"Nw Langendk 77",
    "sg:city":"Delft",
    "sg:orig_category":"Feestartikelen",
    "sg:phone":"+31 15 212 5404",
    "sg:postcode":"2611 VJ",
    "sg:province":"Zuid-Holland",
    "wof:name":"Brehm, Feestartikelenhuis",
    "wof:placetype":"venue"
},
  "geometry": {"coordinates":[4.364651,52.01358],"type":"Point"}
}