{
  "type": "Feature",
  "properties": {
    "addr:full":"V Haersolteln 30 Hasselt Overijssel 8061 EH",
    "addr:housenumber":"30",
    "addr:postcode":"8061 eh",
    "iso:country":"NL",
    "sg:address":"V Haersolteln 30",
    "sg:city":"Hasselt",
    "sg:orig_category":"Autorijscholen",
    "sg:phone":"+31 38 477 2375",
    "sg:postcode":"8061 EH",
    "sg:province":"Overijssel",
    "wof:name":"Berg, Van Den",
    "wof:placetype":"venue"
},
  "geometry": {"coordinates":[6.088755,52.592861],"type":"Point"}
}