{
  "type": "Feature",
  "properties": {
    "addr:full":"Plantagewg 25B Alblasserdam Zuid-Holland 2951 GN",
    "addr:housenumber":"25b",
    "addr:postcode":"2951 gn",
    "addr:street":"Plantagewg",
    "iso:country":"NL",
    "sg:address":"Plantagewg 25B",
    "sg:city":"Alblasserdam",
    "sg:orig_category":"Modelbouw",
    "sg:phone":"+31 78 691 8650",
    "sg:postcode":"2951 GN",
    "sg:province":"Zuid-Holland",
    "wof:name":"Howi",
    "wof:placetype":"venue"
},
  "geometry": {"coordinates":[4.661158,51.8624],"type":"Point"}
}