{
  "type": "Feature",
  "properties": {
    "iso:country":"NL",
    "sg:address":"Schoolstr 5",
    "sg:city":"Halfweg Nh",
    "sg:orig_category":"Scholen Voor Basisonderwijs",
    "sg:phone":"+31 20 497 5391",
    "sg:postcode":"1165 HB",
    "sg:province":"Noord-Holland",
    "wof:name":"Halverwege Chr",
    "wof:placetype":"venue"
},
  "geometry": {"coordinates":[4.753119,52.383213],"type":"Point"}
}