{
  "type": "Feature",
  "properties": {
    "addr:full":"Schoolstr 5 Halfweg Nh Noord-Holland 1165 HB",
    "addr:housenumber":"5",
    "addr:postcode":"1165 hb",
    "addr:street":"Schoolstr",
    "iso:country":"NL",
    "sg:address":"Schoolstr 5",
    "sg:city":"Halfweg Nh",
    "sg:orig_category":"Scholen Voor Basisonderwijs",
    "sg:phone":"+31 20 497 5391",
    "sg:postcode":"1165 HB",
    "sg:province":"Noord-Holland",
    "wof:name":"Halverwege Chr",
    "wof:placetype":"venue"
},
  "geometry": {"coordinates":[4.753119,52.383213],"type":"Point"}
}