{
  "type": "Feature",
  "properties": {
    "addr:full":"J A Lebbinkln 25 Rotterdam Zuid-Holland 3062 CG",
    "addr:housenumber":"25",
    "addr:postcode":"3062 cg",
    "addr:street":"J A Lebbinkln",
    "iso:country":"NL",
    "sg:address":"J A Lebbinkln 25",
    "sg:city":"Rotterdam",
    "sg:orig_category":"Verenigingen En Stichtingen",
    "sg:phone":"+31 10 213 1112",
    "sg:postcode":"3062 CG",
    "sg:province":"Zuid-Holland",
    "wof:name":"Haasje, Sticht Het",
    "wof:placetype":"venue"
},
  "geometry": {"coordinates":[4.51759,51.931339],"type":"Point"}
}