{
  "type": "Feature",
  "properties": {
    "addr:full":"Parkweg 70 Groningen Groningen 9725 EL",
    "addr:housenumber":"70",
    "addr:postcode":"9725 el",
    "addr:street":"Parkweg",
    "iso:country":"NL",
    "sg:address":"Parkweg 70",
    "sg:city":"Groningen",
    "sg:orig_category":"Schilderwerk",
    "sg:phone":"+31 50 526 5226",
    "sg:postcode":"9725 EL",
    "sg:province":"Groningen",
    "wof:name":"E D J Glastra",
    "wof:placetype":"venue"
},
  "geometry": {"coordinates":[6.564749,53.208012],"type":"Point"}
}