{
  "type": "Feature",
  "properties": {
    "addr:full":"Europawg 143A Nieuw Schoonebeek Drenthe 7766 AE",
    "addr:housenumber":"143a",
    "addr:postcode":"7766 ae",
    "addr:street":"Nieuw Schoonebeek",
    "iso:country":"NL",
    "sg:address":"Europawg 143A",
    "sg:city":"Nieuw Schoonebeek",
    "sg:orig_category":"Bibliotheken En Leeszalen Openbare",
    "sg:phone":"+31 524 541 419",
    "sg:postcode":"7766 AE",
    "sg:province":"Drenthe",
    "wof:name":"Openb Bibliotheek",
    "wof:placetype":"venue"
},
  "geometry": {"coordinates":[6.9877800941,52.6464042664],"type":"Point"}
}