{
  "type": "Feature",
  "properties": {
    "iso:country":"NL",
    "sg:address":"Koningskade 30",
    "sg:city":"'S Gravenhage",
    "sg:orig_category":"Bedrijfs- And Werkgeversorganisaties",
    "sg:phone":"+31 70 328 7100",
    "sg:postcode":"2596 AA",
    "sg:province":"Zuid-Holland",
    "wof:name":"Kamer Van Koophandel Haaglanden",
    "wof:placetype":"venue"
},
  "geometry": {"coordinates":[4.313465,52.089127],"type":"Point"}
}