{
  "type": "Feature",
  "properties": {
    "addr:full":"Schelpwg 26 Domburg Zeeland 4357 BP",
    "addr:housenumber":"26",
    "addr:postcode":"4357 bp",
    "addr:street":"Schelpwg",
    "iso:country":"NL",
    "sg:address":"Schelpwg 26",
    "sg:city":"Domburg",
    "sg:orig_category":"Golfbanen",
    "sg:phone":"+31 118 586 107",
    "sg:postcode":"4357 BP",
    "sg:province":"Zeeland",
    "wof:name":"Domburgse Golfclub",
    "wof:placetype":"venue"
},
  "geometry": {"coordinates":[3.489642,51.561314],"type":"Point"}
}