{
  "type": "Feature",
  "properties": {
    "addr:full":"Nobelstr 63B Brielle South Holland 3231 BB",
    "addr:housenumber":"63b",
    "addr:postcode":"3231 bb",
    "addr:street":"Nobelstr",
    "iso:country":"NL",
    "sg:address":"Nobelstr 63B",
    "sg:city":"Brielle",
    "sg:orig_category":"Kappers",
    "sg:phone":"+31 181 413 655",
    "sg:postcode":"3231 BB",
    "sg:province":"South Holland",
    "sg:website":"http://www.knappekoppen.net",
    "wof:name":"Knappe Koppen Hairart",
    "wof:placetype":"venue"
},
  "geometry": {"coordinates":[4.163505,51.900703],"type":"Point"}
}