{
  "type": "Feature",
  "properties": {
    "addr:full":"Het Zwanevlot 184 Zutphen Gelderland 7206 CK",
    "addr:housenumber":"184",
    "addr:postcode":"7206 ck",
    "addr:street":"Het Zwanevlot;Gelderland",
    "iso:country":"NL",
    "sg:address":"Het Zwanevlot 184",
    "sg:city":"Zutphen",
    "sg:orig_category":"Beautyfarms And Sauna'S",
    "sg:phone":"+31 575 530 705",
    "sg:postcode":"7206 CK",
    "sg:province":"Gelderland",
    "wof:name":"J M Van Der Zande",
    "wof:placetype":"venue"
},
  "geometry": {"coordinates":[6.202355,52.125504],"type":"Point"}
}