{
  "type": "Feature",
  "properties": {
    "addr:full":"Colenso 151 Soest Utrecht 3761 GM",
    "addr:housenumber":"151",
    "addr:postcode":"3761 gm",
    "addr:street":"Colenso",
    "iso:country":"NL",
    "sg:address":"Colenso 151",
    "sg:city":"Soest",
    "sg:orig_category":"Adviesbureaus Bedrijfsorganisatie",
    "sg:phone":"+31 35 588 0929",
    "sg:postcode":"3761 GM",
    "sg:province":"Utrecht",
    "wof:name":"Hageman, Timo",
    "wof:placetype":"venue"
},
  "geometry": {"coordinates":[5.288111,52.191856],"type":"Point"}
}