{
  "type": "Feature",
  "properties": {
    "addr:full":"Weidestr 32 Den Dungen Noord-Brabant 5275 AR",
    "addr:housenumber":"32",
    "addr:postcode":"5275",
    "addr:street":"Weidestr",
    "iso:country":"NL",
    "sg:address":"Weidestr 32",
    "sg:city":"Den Dungen",
    "sg:orig_category":"Kabels",
    "sg:phone":"+31 73 594 1704",
    "sg:postcode":"5275 AR",
    "sg:province":"Noord-Brabant",
    "wof:name":"Psg",
    "wof:placetype":"venue"
},
  "geometry": {"coordinates":[-123.1367111206,48.1442337036],"type":"Point"}
}