{
  "type": "Feature",
  "properties": {
    "addr:full":"Schelphoek 10 Alkmaar North Holland 1813 SE",
    "addr:housenumber":"10",
    "addr:postcode":"1813 se",
    "addr:street":"Schelphoek",
    "iso:country":"NL",
    "sg:address":"Schelphoek 10",
    "sg:city":"Alkmaar",
    "sg:orig_category":"Autokeuringen",
    "sg:phone":"+31 72 540 4159",
    "sg:postcode":"1813 SE",
    "sg:province":"North Holland",
    "wof:name":"Autoschadebedrijf Rob Van Orden",
    "wof:placetype":"venue"
},
  "geometry": {"coordinates":[4.755034,52.626869],"type":"Point"}
}