{
  "type": "Feature",
  "properties": {
    "addr:full":"Koningspln 77 Delft Zuid-Holland 2611 XE",
    "addr:housenumber":"77",
    "addr:postcode":"2611 xe",
    "addr:street":"Koningspln",
    "iso:country":"NL",
    "sg:address":"Koningspln 77",
    "sg:city":"Delft",
    "sg:orig_category":"Adviesbureaus Bedrijfsorganisatie",
    "sg:phone":"+31 15 219 0761",
    "sg:postcode":"2611 XE",
    "sg:province":"Zuid-Holland",
    "wof:name":"Komiat",
    "wof:placetype":"venue"
},
  "geometry": {"coordinates":[4.356321,52.017735],"type":"Point"}
}