{
  "type": "Feature",
  "properties": {
    "addr:full":"S-Gravenbroekseweg 14 Reeuwijk South Holland 2811 GE",
    "addr:housenumber":"14",
    "addr:postcode":"2811",
    "addr:street":"S-Gravenbroekseweg",
    "iso:country":"NL",
    "sg:address":"S-Gravenbroekseweg 14",
    "sg:city":"Reeuwijk",
    "sg:orig_category":"Pleziervaartuigen And Reparatie",
    "sg:phone":"+31 182 392 585",
    "sg:postcode":"2811 GE",
    "sg:province":"South Holland",
    "wof:name":"Motech Service Reeuwijk",
    "wof:placetype":"venue"
},
  "geometry": {"coordinates":[4.73051,52.042709],"type":"Point"}
}