{
  "type": "Feature",
  "properties": {
    "addr:full":"Keizersgr 618 Amsterdam Noord-Holland 1017 ER",
    "addr:housenumber":"618",
    "addr:postcode":"1017 er",
    "iso:country":"NL",
    "sg:address":"Keizersgr 618",
    "sg:city":"Amsterdam",
    "sg:orig_category":"Advocaten En Advocatenkantoren",
    "sg:phone":"+31 20 627 5161",
    "sg:postcode":"1017 ER",
    "sg:province":"Noord-Holland",
    "wof:name":"Wieringa & Rameckers",
    "wof:placetype":"venue"
},
  "geometry": {"coordinates":[4.890515,52.363773],"type":"Point"}
}