{
  "type": "Feature",
  "properties": {
    "addr:full":"Nieuweweg 25 Groningen Groningen 9711 TB",
    "addr:housenumber":"25",
    "addr:postcode":"9711 tb",
    "addr:street":"Nieuweweg",
    "iso:country":"NL",
    "sg:address":"Nieuweweg 25",
    "sg:city":"Groningen",
    "sg:orig_category":"Kappers",
    "sg:phone":"+31 50 313 0851",
    "sg:postcode":"9711 TB",
    "sg:province":"Groningen",
    "wof:name":"Eef Groenewal",
    "wof:placetype":"venue"
},
  "geometry": {"coordinates":[6.5749020576,53.218170166],"type":"Point"}
}