{
  "type": "Feature",
  "properties": {
    "addr:full":"Oostgrasdijk 1 Schoorl North Holland 1871 AL",
    "addr:housenumber":"1",
    "addr:postcode":"1871 al",
    "addr:street":"Oostgrasdijk",
    "iso:country":"NL",
    "sg:address":"Oostgrasdijk 1",
    "sg:city":"Schoorl",
    "sg:orig_category":"Kampeerterreinen",
    "sg:phone":"+31 72 509 1759",
    "sg:postcode":"1871 AL",
    "sg:province":"North Holland",
    "wof:name":"Caravanpark Het Lange Veld Bv",
    "wof:placetype":"venue"
},
  "geometry": {"coordinates":[4.7089710236,52.6904144287],"type":"Point"}
}