{
  "type": "Feature",
  "properties": {
    "iso:country":"NL",
    "sg:address":"Koningin Julianalaan 86-88",
    "sg:city":"Voorburg",
    "sg:orig_category":"Huishoudapparatuur, Televisies And Radio'S",
    "sg:phone":"+31 70 387 2979",
    "sg:postcode":"2274 JM",
    "sg:province":"Zuid-Holland",
    "wof:name":"Aad Stolk",
    "wof:placetype":"venue"
},
  "geometry": {"coordinates":[4.350798,52.077515],"type":"Point"}
}