{
  "type": "Feature",
  "properties": {
    "addr:full":"Riddergaard 3 Maastricht Limburg 6227 GA",
    "addr:housenumber":"3",
    "addr:postcode":"6227 ga",
    "addr:street":"Riddergaard",
    "iso:country":"NL",
    "sg:address":"Riddergaard 3",
    "sg:city":"Maastricht",
    "sg:orig_category":"Vertaal- And Tolkenbureaus",
    "sg:phone":"+31 43 361 6596",
    "sg:postcode":"6227 GA",
    "sg:province":"Limburg",
    "wof:name":"On Speaking Terms",
    "wof:placetype":"venue"
},
  "geometry": {"coordinates":[5.723636,50.833244],"type":"Point"}
}