{
  "type": "Feature",
  "properties": {
    "iso:country":"NL",
    "sg:address":"Kerkstraat 5",
    "sg:city":"Oosterhout Nb",
    "sg:orig_category":"Herenmodezaken",
    "sg:phone":"+31 162 426 095",
    "sg:postcode":"4901 JE",
    "sg:province":"Noord-Brabant",
    "wof:name":"Herenmode Peddel'S Clothing",
    "wof:placetype":"venue"
},
  "geometry": {"coordinates":[4.860656,51.644325],"type":"Point"}
}