{
  "type": "Feature",
  "properties": {
    "iso:country":"NL",
    "sg:address":"Asserln 9",
    "sg:city":"Schoonhoven",
    "sg:orig_category":"Metselwerken",
    "sg:phone":"+31 182 386 324",
    "sg:postcode":"2871 LJ",
    "sg:province":"South Holland",
    "wof:name":"Pelicon",
    "wof:placetype":"venue"
},
  "geometry": {"coordinates":[4.85103,51.946453],"type":"Point"}
}