{
  "type": "Feature",
  "properties": {
    "addr:full":"Gestelsestraat 7 Eindhoven Noord-Brabant 5615 LA",
    "addr:housenumber":"7",
    "addr:postcode":"5615 la",
    "addr:street":"Gestelsestraat",
    "iso:country":"NL",
    "sg:address":"Gestelsestraat 7",
    "sg:city":"Eindhoven",
    "sg:orig_category":"Bloemen And Planten",
    "sg:phone":"+31 40 244 4901",
    "sg:postcode":"5615 LA",
    "sg:province":"Noord-Brabant",
    "wof:name":"Bloemboetiek Ton Welp",
    "wof:placetype":"venue"
},
  "geometry": {"coordinates":[5.472086,51.433456],"type":"Point"}
}