{
  "type": "Feature",
  "properties": {
    "addr:full":"Saturnusstr 21 S Gravenhage Zuid-Holland 2516 AD",
    "addr:housenumber":"21;gravenhage",
    "addr:postcode":"2516 ad",
    "addr:street":"Saturnusstr;S",
    "iso:country":"NL",
    "sg:address":"Saturnusstr 21",
    "sg:city":"S Gravenhage",
    "sg:orig_category":"Grafische Bedrijven",
    "sg:phone":"+31 70 382 1616",
    "sg:postcode":"2516 AD",
    "sg:province":"Zuid-Holland",
    "wof:name":"Sa-Tur",
    "wof:placetype":"venue"
},
  "geometry": {"coordinates":[4.33931,52.06786],"type":"Point"}
}