{
  "type": "Feature",
  "properties": {
    "addr:full":"Geleenstr 23Hs Amsterdam Noord-Holland 1078 LC",
    "addr:postcode":"1078 lc",
    "iso:country":"NL",
    "sg:address":"Geleenstr 23Hs",
    "sg:city":"Amsterdam",
    "sg:orig_category":"Kinderopvang",
    "sg:phone":"+31 6 50526591",
    "sg:postcode":"1078 LC",
    "sg:province":"Noord-Holland",
    "sg:website":"http://www.kindcare.nl",
    "wof:name":"Atlantis",
    "wof:placetype":"venue"
},
  "geometry": {"coordinates":[4.893002,52.344208],"type":"Point"}
}