{
  "type": "Feature",
  "properties": {
    "iso:country":"NL",
    "sg:address":"Pompmolenln 25-27",
    "sg:city":"Woerden",
    "sg:orig_category":"Ventilatiesystemen",
    "sg:phone":"+31 348 415 814",
    "sg:postcode":"3447 GK",
    "sg:province":"Utrecht",
    "wof:name":"Eltag Bv",
    "wof:placetype":"venue"
},
  "geometry": {"coordinates":[4.889509,52.074844],"type":"Point"}
}