{
  "type": "Feature",
  "properties": {
    "addr:full":"L Nieuwstr 57-59 Tilburg Noord-Brabant 5041 DA",
    "addr:housenumber":"57-59",
    "addr:postcode":"5041 da",
    "addr:street":"Tilburg",
    "iso:country":"NL",
    "sg:address":"L Nieuwstr 57-59",
    "sg:city":"Tilburg",
    "sg:orig_category":"Verenigingen En Stichtingen",
    "sg:phone":"+31 13 536 7548",
    "sg:postcode":"5041 DA",
    "sg:province":"Noord-Brabant",
    "wof:name":"Welzijnssticht Voor Surinamers In Tilburg",
    "wof:placetype":"venue"
},
  "geometry": {"coordinates":[5.090677,51.562546],"type":"Point"}
}