{
  "type": "Feature",
  "properties": {
    "addr:full":"Cluselaan 15 Eindhoven Noord-Brabant 5627 DC",
    "addr:housenumber":"15",
    "addr:postcode":"5627",
    "addr:street":"Cluselaan",
    "iso:country":"NL",
    "sg:address":"Cluselaan 15",
    "sg:city":"Eindhoven",
    "sg:orig_category":"Kinderopvang Behalve Thuis",
    "sg:phone":"+31 40 248 1813",
    "sg:postcode":"5627 DC",
    "sg:province":"Noord-Brabant",
    "wof:name":"De Klaver",
    "wof:placetype":"venue"
},
  "geometry": {"coordinates":[5.439033,51.484531],"type":"Point"}
}