{
  "type": "Feature",
  "properties": {
    "addr:full":"Saturnusstr 22 Berghem North Brabant 5351 GX",
    "addr:housenumber":"22",
    "addr:postcode":"5351 gx",
    "addr:street":"Saturnusstr",
    "iso:country":"NL",
    "sg:address":"Saturnusstr 22",
    "sg:city":"Berghem",
    "sg:orig_category":"Kinderkleding",
    "sg:phone":"+31 412 402 041",
    "sg:postcode":"5351 GX",
    "sg:province":"North Brabant",
    "wof:name":"Boeijen",
    "wof:placetype":"venue"
},
  "geometry": {"coordinates":[5.580358,51.771797],"type":"Point"}
}