{
  "type": "Feature",
  "properties": {
    "addr:full":"Lijteplein 1 Ureterp Friesland 9247 EP",
    "addr:housenumber":"1",
    "addr:postcode":"9247 ep",
    "addr:street":"Lijteplein",
    "iso:country":"NL",
    "sg:address":"Lijteplein 1",
    "sg:city":"Ureterp",
    "sg:orig_category":"Bloemen And Planten",
    "sg:phone":"+31 512 302 277",
    "sg:postcode":"9247 EP",
    "sg:province":"Friesland",
    "wof:name":"De Blommerij",
    "wof:placetype":"venue"
},
  "geometry": {"coordinates":[6.172026,53.094521],"type":"Point"}
}