{
  "type": "Feature",
  "properties": {
    "addr:full":"Brahmsstr 17 Almelo Overijssel 7604 ES",
    "addr:housenumber":"17",
    "addr:postcode":"7604 es",
    "addr:street":"Brahmsstr",
    "iso:country":"NL",
    "sg:address":"Brahmsstr 17",
    "sg:city":"Almelo",
    "sg:orig_category":"Verenigingen En Stichtingen",
    "sg:phone":"+31 546 538 686",
    "sg:postcode":"7604 ES",
    "sg:province":"Overijssel",
    "wof:name":"Unicef",
    "wof:placetype":"venue"
},
  "geometry": {"coordinates":[6.641502,52.356544],"type":"Point"}
}