{
  "type": "Feature",
  "properties": {
    "addr:full":"Van De Lagemaathof 27 Leusden Utrecht 3833 HW",
    "addr:housenumber":"27",
    "addr:postcode":"3833 hw",
    "addr:street":"Van De Lagemaathof",
    "iso:country":"NL",
    "sg:address":"Van De Lagemaathof 27",
    "sg:city":"Leusden",
    "sg:orig_category":"Vertaal- And Tolkenbureaus",
    "sg:phone":"+31 33 432 3333",
    "sg:postcode":"3833 HW",
    "sg:province":"Utrecht",
    "wof:name":"Smit Translations",
    "wof:placetype":"venue"
},
  "geometry": {"coordinates":[5.417605,52.123859],"type":"Point"}
}