{
  "type": "Feature",
  "properties": {
    "addr:full":"M Zeldenruststr 39 Amsterdam Noord-Holland 1091 DL",
    "addr:housenumber":"39",
    "addr:postcode":"1091 dl",
    "iso:country":"NL",
    "sg:address":"M Zeldenruststr 39",
    "sg:city":"Amsterdam",
    "sg:orig_category":"Grafmonumenten",
    "sg:phone":"+31 20 665 0960",
    "sg:postcode":"1091 DL",
    "sg:province":"Noord-Holland",
    "sg:website":"http://www.memento-gedenkbeelden.nl",
    "wof:name":"Memento",
    "wof:placetype":"venue"
},
  "geometry": {"coordinates":[4.913718,52.360439],"type":"Point"}
}