{
  "type": "Feature",
  "properties": {
    "addr:full":"Henseniusplein 6 Venray Limburg 5801 BB",
    "addr:housenumber":"6",
    "addr:postcode":"5801 bb",
    "addr:street":"Henseniusplein",
    "iso:country":"NL",
    "sg:address":"Henseniusplein 6",
    "sg:city":"Venray",
    "sg:classifiers":[
        {
            "category":"Retail",
            "subcategory":"Photofinishing",
            "type":"Services"
        }
    ],
    "sg:phone":"+31 478 581 391",
    "sg:postcode":"5801 BB",
    "sg:province":"Limburg",
    "sg:tags":[
        "foto",
        "film"
    ],
    "wof:name":"Vof Foto Hoedemaekers",
    "wof:placetype":"venue"
},
  "geometry": {"coordinates":[5.974749,51.524284],"type":"Point"}
}