{
  "type": "Feature",
  "properties": {
    "addr:full":"Hoogend 20 Sneek Friesland 8601 AE",
    "addr:housenumber":"20",
    "addr:postcode":"8601 ae",
    "addr:street":"Hoogend",
    "iso:country":"NL",
    "sg:address":"Hoogend 20",
    "sg:city":"Sneek",
    "sg:orig_category":"Huishoudapparatuur, Televisies And Radio'S",
    "sg:phone":"+31 515 427 325",
    "sg:postcode":"8601 AE",
    "sg:province":"Friesland",
    "wof:name":"De Harense Smid",
    "wof:placetype":"venue"
},
  "geometry": {"coordinates":[5.660731,53.029366],"type":"Point"}
}