{
  "type": "Feature",
  "properties": {
    "addr:full":"Keucheniusstraat 1 Huizen North Holland 1271 BM",
    "addr:housenumber":"1",
    "addr:postcode":"1271 bm",
    "addr:street":"Keucheniusstraat",
    "iso:country":"NL",
    "sg:address":"Keucheniusstraat 1",
    "sg:city":"Huizen",
    "sg:orig_category":"Visspeciaalzaken",
    "sg:phone":"+31 35 524 0214",
    "sg:postcode":"1271 BM",
    "sg:province":"North Holland",
    "wof:name":"Jan Veerman Vis",
    "wof:placetype":"venue"
},
  "geometry": {"coordinates":[5.233852,52.29734],"type":"Point"}
}