{
  "type": "Feature",
  "properties": {
    "addr:full":"R Luxemburgpk 23 Purmerend Noord-Holland 1447 WC",
    "addr:housenumber":"23",
    "addr:postcode":"1447 wc",
    "iso:country":"NL",
    "sg:address":"R Luxemburgpk 23",
    "sg:city":"Purmerend",
    "sg:orig_category":"Glazenwasserijen",
    "sg:phone":"+31 299 645 895",
    "sg:postcode":"1447 WC",
    "sg:province":"Noord-Holland",
    "wof:name":"Reggy",
    "wof:placetype":"venue"
},
  "geometry": {"coordinates":[4.95986,52.48621],"type":"Point"}
}