{
  "type": "Feature",
  "properties": {
    "addr:full":"Hagedoornwg 52 Amsterdam North Holland 1031 BS",
    "addr:housenumber":"52",
    "addr:postcode":"1031 bs",
    "addr:street":"Hagedoornwg",
    "iso:country":"NL",
    "sg:address":"Hagedoornwg 52",
    "sg:city":"Amsterdam",
    "sg:orig_category":"Kantoorbenodigdheden",
    "sg:phone":"+31 20 636 0711",
    "sg:postcode":"1031 BS",
    "sg:province":"North Holland",
    "wof:name":"Read Shop, The",
    "wof:placetype":"venue"
},
  "geometry": {"coordinates":[4.9122161865,52.3901901245],"type":"Point"}
}