{
  "type": "Feature",
  "properties": {
    "addr:full":"Caumerbeeklaan 76 Heerlen Limburg 6416 GB",
    "addr:housenumber":"76",
    "addr:postcode":"6416 gb",
    "addr:street":"Caumerbeeklaan",
    "iso:country":"NL",
    "sg:address":"Caumerbeeklaan 76",
    "sg:city":"Heerlen",
    "sg:orig_category":"Autokeuringen",
    "sg:phone":"+31 45 541 1799",
    "sg:postcode":"6416 GB",
    "sg:province":"Limburg",
    "wof:name":"J G Mous Bv",
    "wof:placetype":"venue"
},
  "geometry": {"coordinates":[5.990529,50.880138],"type":"Point"}
}