{
  "type": "Feature",
  "properties": {
    "iso:country":"NL",
    "sg:address":"Spoorln 15",
    "sg:city":"Capelle Ad Yssel",
    "sg:orig_category":"Adviesbureaus Bedrijfsorganisatie",
    "sg:phone":"+31 10 284 9410",
    "sg:postcode":"2908 BG",
    "sg:province":"Zuid-Holland",
    "wof:name":"Kuik Bv",
    "wof:placetype":"venue"
},
  "geometry": {"coordinates":[4.5846,51.923401],"type":"Point"}
}