{
  "type": "Feature",
  "properties": {
    "addr:full":"W V Pruisenln 139 Gouda South Holland 2807 KH",
    "addr:housenumber":"139",
    "addr:postcode":"2807 kh",
    "addr:street":"W V Pruisenln",
    "iso:country":"NL",
    "sg:address":"W V Pruisenln 139",
    "sg:city":"Gouda",
    "sg:classifiers":[
        {
            "category":"Professional",
            "subcategory":"Accounting & Tax Preparation",
            "type":"Services"
        }
    ],
    "sg:phone":"+31 187 487 177",
    "sg:postcode":"2807 KH",
    "sg:province":"South Holland",
    "sg:tags":[
        "accountant",
        "en",
        "-kantoren",
        "register-"
    ],
    "sg:website":"http://www.deheerenenco.nl",
    "wof:name":"Pr?Count",
    "wof:placetype":"venue"
},
  "geometry": {"coordinates":[4.710715,52.010006],"type":"Point"}
}