{
  "type": "Feature",
  "properties": {
    "iso:country":"NL",
    "sg:address":"Brasemdaal 67",
    "sg:city":"S Gravenhage",
    "sg:orig_category":"Persoonlijke Leningen",
    "sg:phone":"+31 6 53186104",
    "sg:postcode":"2553 NB",
    "sg:province":"Zuid-Holland",
    "wof:name":"Smits",
    "wof:placetype":"venue"
},
  "geometry": {"coordinates":[4.21987,52.046589],"type":"Point"}
}