{
  "type": "Feature",
  "properties": {
    "addr:full":"Wilgenln 4 Hoogland Utrecht 3828 CH",
    "addr:housenumber":"4",
    "addr:postcode":"3828",
    "addr:street":"Wilgenln",
    "iso:country":"NL",
    "sg:address":"Wilgenln 4",
    "sg:city":"Hoogland",
    "sg:orig_category":"Sportverenigingen En Ontspannings- Verenigingen",
    "sg:phone":"+31 33 480 7804",
    "sg:postcode":"3828 CH",
    "sg:province":"Utrecht",
    "wof:name":"Adg Amersfoorts Damgenootschap",
    "wof:placetype":"venue"
},
  "geometry": {"coordinates":[5.379809,52.185986],"type":"Point"}
}