{
  "type": "Feature",
  "properties": {
    "iso:country":"NL",
    "sg:address":"Wilgenln 4",
    "sg:city":"Hoogland",
    "sg:orig_category":"Sportverenigingen En Ontspannings- Verenigingen",
    "sg:phone":"+31 33 480 7804",
    "sg:postcode":"3828 CH",
    "sg:province":"Utrecht",
    "wof:name":"Adg Amersfoorts Damgenootschap",
    "wof:placetype":"venue"
},
  "geometry": {"coordinates":[5.379809,52.185986],"type":"Point"}
}