{
  "type": "Feature",
  "properties": {
    "addr:full":"Molenlaan 20 Siddeburen Groningen 9628 AK",
    "addr:housenumber":"20",
    "addr:postcode":"9628 ak",
    "addr:street":"Molenlaan",
    "iso:country":"NL",
    "sg:address":"Molenlaan 20",
    "sg:city":"Siddeburen",
    "sg:classifiers":[
        {
            "category":"Fast Food",
            "type":"Food & Drink"
        }
    ],
    "sg:phone":"+31 598 431 205",
    "sg:postcode":"9628 AK",
    "sg:province":"Groningen",
    "sg:tags":[
        "afhaal",
        "restaurant"
    ],
    "wof:name":"Snackbar De Molen",
    "wof:placetype":"venue"
},
  "geometry": {"coordinates":[6.869525,53.249172],"type":"Point"}
}