{
  "type": "Feature",
  "properties": {
    "addr:full":"J V Wierdsmastr 100 Hoek Van Holland South Holland 3151 EE",
    "addr:housenumber":"100",
    "addr:postcode":"3151 ee",
    "addr:street":"J;Wierdsmastr",
    "iso:country":"NL",
    "sg:address":"J V Wierdsmastr 100",
    "sg:city":"Hoek Van Holland",
    "sg:orig_category":"Onderhoudswerken",
    "sg:phone":"+31 174 387 202",
    "sg:postcode":"3151 EE",
    "sg:province":"South Holland",
    "wof:name":"Odera",
    "wof:placetype":"venue"
},
  "geometry": {"coordinates":[4.132599,51.985542],"type":"Point"}
}