{
  "type": "Feature",
  "properties": {
    "iso:country":"NL",
    "sg:address":"Krugerln 61",
    "sg:city":"Gouda",
    "sg:orig_category":"Sanitaire Artikelen",
    "sg:phone":"+31 182 521 202",
    "sg:postcode":"2806 EC",
    "sg:province":"Zuid-Holland",
    "wof:name":"Kalmeijer, R",
    "wof:placetype":"venue"
},
  "geometry": {"coordinates":[4.710715,52.010006],"type":"Point"}
}