{
  "type": "Feature",
  "properties": {
    "addr:full":"Dorpsstr 32A Ulicoten Noord-Brabant 5113 TE",
    "addr:housenumber":"32a",
    "addr:postcode":"5113 te",
    "addr:street":"Dorpsstr",
    "iso:country":"NL",
    "sg:address":"Dorpsstr 32A",
    "sg:city":"Ulicoten",
    "sg:orig_category":"Banken",
    "sg:phone":"+31 13 507 6600",
    "sg:postcode":"5113 TE",
    "sg:province":"Noord-Brabant",
    "sg:website":"http://www.rabobank.nl",
    "wof:name":"Rabobank",
    "wof:placetype":"venue"
},
  "geometry": {"coordinates":[4.86047,51.456802],"type":"Point"}
}