{
  "type": "Feature",
  "properties": {
    "addr:full":"Hasselaersplein 3 Haarlem Noord-Holland 2013 GB",
    "addr:housenumber":"3",
    "addr:postcode":"2013 gb",
    "addr:street":"Hasselaersplein",
    "iso:country":"NL",
    "sg:address":"Hasselaersplein 3",
    "sg:city":"Haarlem",
    "sg:orig_category":"Bedrijfs- And Managementsconsultants",
    "sg:phone":"+31 23 532 3383",
    "sg:postcode":"2013 GB",
    "sg:province":"Noord-Holland",
    "wof:name":"Adviesbureau Van Der Putten",
    "wof:placetype":"venue"
},
  "geometry": {"coordinates":[4.627533,52.383335],"type":"Point"}
}