{
  "type": "Feature",
  "properties": {
    "addr:full":"Groene Kruiswg 4 Numansdorp South Holland 3281 KB",
    "addr:housenumber":"4",
    "addr:postcode":"3281 kb",
    "addr:street":"Groene Kruiswg",
    "iso:country":"NL",
    "sg:address":"Groene Kruiswg 4",
    "sg:city":"Numansdorp",
    "sg:orig_category":"Papierwaren - Fabrieken En Groothandel",
    "sg:phone":"+31 186 651 055",
    "sg:postcode":"3281 KB",
    "sg:province":"South Holland",
    "wof:name":"Haers Bv, J B",
    "wof:placetype":"venue"
},
  "geometry": {"coordinates":[4.4399,51.749245],"type":"Point"}
}