{
  "type": "Feature",
  "properties": {
    "addr:full":"Delftselaan 79 'S Gravenhage Zuid-Holland 2512 RB",
    "addr:housenumber":"79",
    "addr:postcode":"2512 rb",
    "addr:street":"Delftselaan;' S",
    "iso:country":"NL",
    "sg:address":"Delftselaan 79",
    "sg:city":"'S Gravenhage",
    "sg:classifiers":[
        {
            "category":"Communications",
            "subcategory":"Television Station",
            "type":"Services"
        }
    ],
    "sg:phone":"+31 70 389 4651",
    "sg:postcode":"2512 RB",
    "sg:province":"Zuid-Holland",
    "sg:tags":[
        "video",
        "audio",
        "verhuur"
    ],
    "wof:name":"Yoti Trading",
    "wof:placetype":"venue"
},
  "geometry": {"coordinates":[4.298026,52.070137],"type":"Point"}
}