{
  "type": "Feature",
  "properties": {
    "addr:full":"Plein 15 Wateringen Zuid-Holland 2291 CA",
    "addr:housenumber":"15",
    "addr:postcode":"2291 ca",
    "addr:street":"Plein",
    "iso:country":"NL",
    "sg:address":"Plein 15",
    "sg:city":"Wateringen",
    "sg:orig_category":"Juweliers",
    "sg:phone":"+31 174 292 501",
    "sg:postcode":"2291 CA",
    "sg:province":"Zuid-Holland",
    "sg:website":"http://www.mosterd.nl",
    "wof:name":"Mosterd",
    "wof:placetype":"venue"
},
  "geometry": {"coordinates":[4.274428,52.024174],"type":"Point"}
}