{
  "type": "Feature",
  "properties": {
    "addr:full":"Ringdk 1 Wydewormer North Holland 1456 AH",
    "addr:housenumber":"1",
    "addr:postcode":"1456 ah",
    "addr:street":"Ringdk;North",
    "iso:country":"NL",
    "sg:address":"Ringdk 1",
    "sg:city":"Wydewormer",
    "sg:orig_category":"Autorijscholen",
    "sg:phone":"+31 299 473 155",
    "sg:postcode":"1456 AH",
    "sg:province":"North Holland",
    "sg:website":"http://www.nicoboots.nl",
    "wof:name":"Boots, Autorijschool Nico",
    "wof:placetype":"venue"
},
  "geometry": {"coordinates":[4.917311,52.508053],"type":"Point"}
}