{
  "type": "Feature",
  "properties": {
    "addr:full":"Collenkamp 15 Zevenaar Gelderland 6903 VR",
    "addr:housenumber":"15",
    "addr:postcode":"6903 vr",
    "addr:street":"Collenkamp",
    "iso:country":"NL",
    "sg:address":"Collenkamp 15",
    "sg:city":"Zevenaar",
    "sg:orig_category":"Logopedisten",
    "sg:phone":"+31 316 529 420",
    "sg:postcode":"6903 VR",
    "sg:province":"Gelderland",
    "wof:name":"Steins, A J M M",
    "wof:placetype":"venue"
},
  "geometry": {"coordinates":[6.06889,51.939789],"type":"Point"}
}