{
  "type": "Feature",
  "properties": {
    "addr:full":"Drieschstraat 2A Heerlen Limburg 6412 XX",
    "addr:housenumber":"2a",
    "addr:postcode":"6412 xx",
    "addr:street":"Drieschstraat",
    "iso:country":"NL",
    "sg:address":"Drieschstraat 2A",
    "sg:city":"Heerlen",
    "sg:orig_category":"Meubelreparatie And -Restauratie",
    "sg:phone":"+31 45 572 8448",
    "sg:postcode":"6412 XX",
    "sg:province":"Limburg",
    "wof:name":"Broquantiek",
    "wof:placetype":"venue"
},
  "geometry": {"coordinates":[5.981679,50.891773],"type":"Point"}
}