{
  "type": "Feature",
  "properties": {
    "iso:country":"NL",
    "sg:address":"Zwartewg 4",
    "sg:city":"Milsbeek",
    "sg:orig_category":"Webdesign Bureaus",
    "sg:phone":"+31 485 516 372",
    "sg:postcode":"6596 AG",
    "sg:province":"Limburg",
    "sg:website":"http://www.dutchmarketing.nl",
    "wof:name":"Dutchmarketing",
    "wof:placetype":"venue"
},
  "geometry": {"coordinates":[5.9510669708,51.72240448],"type":"Point"}
}