{
  "type": "Feature",
  "properties": {
    "addr:full":"Heinsbergerwg 176 Roermond Limburg 6045 CK",
    "addr:housenumber":"176",
    "addr:postcode":"6045 ck",
    "iso:country":"NL",
    "sg:address":"Heinsbergerwg 176",
    "sg:city":"Roermond",
    "sg:orig_category":"Bejaarden - Verzorgingstehuizen",
    "sg:phone":"+31 475 345 345",
    "sg:postcode":"6045 CK",
    "sg:province":"Limburg",
    "wof:name":"Land Van Gelre En Gulick, Sticht",
    "wof:placetype":"venue"
},
  "geometry": {"coordinates":[6.001313,51.172176],"type":"Point"}
}