{
  "type": "Feature",
  "properties": {
    "addr:full":"Quarantainewg 5 Rotterdam Zuid-Holland 3089 KP",
    "addr:housenumber":"5",
    "addr:postcode":"3089 kp",
    "addr:street":"Quarantainewg",
    "iso:country":"NL",
    "sg:address":"Quarantainewg 5",
    "sg:city":"Rotterdam",
    "sg:orig_category":"On- Offshore",
    "sg:phone":"+31 10 495 4544",
    "sg:postcode":"3089 KP",
    "sg:province":"Zuid-Holland",
    "wof:name":"Anker Bv",
    "wof:placetype":"venue"
},
  "geometry": {"coordinates":[4.410946846,51.8953704834],"type":"Point"}
}