{
  "type": "Feature",
  "properties": {
    "iso:country":"NL",
    "sg:address":"Ged Zalmhaven 103",
    "sg:city":"Rotterdam",
    "sg:orig_category":"Elektrotechnische Apparatuur - Fabrieken En Groothandel",
    "sg:phone":"+31 10 403 5544",
    "sg:postcode":"3011 BT",
    "sg:province":"South Holland",
    "wof:name":"Waw",
    "wof:placetype":"venue"
},
  "geometry": {"coordinates":[4.478228,51.910973],"type":"Point"}
}