{
  "type": "Feature",
  "properties": {
    "iso:country":"NL",
    "sg:address":"Schoolwg 33",
    "sg:city":"Ermelo",
    "sg:orig_category":"Sportverenigingen En Ontspannings- Verenigingen",
    "sg:phone":"+31 341 554 731",
    "sg:postcode":"3852 ZA",
    "sg:province":"Gelderland",
    "wof:name":"Irminloo Tenniscl",
    "wof:placetype":"venue"
},
  "geometry": {"coordinates":[5.64396,52.292915],"type":"Point"}
}