{
  "type": "Feature",
  "properties": {
    "addr:full":"Wisselwerking 12 Diemen Noord-Holland 1112 XM",
    "addr:housenumber":"12",
    "addr:postcode":"1112 xm",
    "addr:street":"Wisselwerking",
    "iso:country":"NL",
    "sg:address":"Wisselwerking 12",
    "sg:city":"Diemen",
    "sg:orig_category":"Verzekeringen",
    "sg:phone":"+31 20 699 3331",
    "sg:postcode":"1112 XM",
    "sg:province":"Noord-Holland",
    "wof:name":"Assurantiebedrijf Hoofdstad Bv",
    "wof:placetype":"venue"
},
  "geometry": {"coordinates":[4.952432,52.326847],"type":"Point"}
}