{
  "type": "Feature",
  "properties": {
    "addr:full":"Wilhelminapln 23 Roermond Limburg 6041 CE",
    "addr:housenumber":"23",
    "addr:postcode":"6041 ce",
    "addr:street":"Wilhelminapln",
    "iso:country":"NL",
    "sg:address":"Wilhelminapln 23",
    "sg:city":"Roermond",
    "sg:orig_category":"Verzekeringen - Verzekeringskantoren",
    "sg:phone":"+31 475 338 377",
    "sg:postcode":"6041 CE",
    "sg:province":"Limburg",
    "wof:name":"Oijen, Van",
    "wof:placetype":"venue"
},
  "geometry": {"coordinates":[5.992885,51.197399],"type":"Point"}
}