{
  "type": "Feature",
  "properties": {
    "addr:full":"Kuilven 23 Erp Noord-Brabant 5469 GA",
    "addr:housenumber":"23",
    "addr:postcode":"5469 ga",
    "addr:street":"Kuilven",
    "iso:country":"NL",
    "sg:address":"Kuilven 23",
    "sg:city":"Erp",
    "sg:orig_category":"Metselwerken",
    "sg:phone":"+31 413 212 143",
    "sg:postcode":"5469 GA",
    "sg:province":"Noord-Brabant",
    "wof:name":"Donkers",
    "wof:placetype":"venue"
},
  "geometry": {"coordinates":[-83.222931,32.678131],"type":"Point"}
}