{
  "type": "Feature",
  "properties": {
    "addr:full":"Prof Vd Waalsstr 7-9 Alkmaar Noord-Holland 1821 BT",
    "addr:housenumber":"7-9",
    "addr:postcode":"1821 bt",
    "addr:street":"Prof",
    "iso:country":"NL",
    "sg:address":"Prof Vd Waalsstr 7-9",
    "sg:city":"Alkmaar",
    "sg:classifiers":[
        {
            "category":"Wholesale",
            "subcategory":"Meat",
            "type":"Manufacturing & Wholesale Goods"
        }
    ],
    "sg:phone":"+31 72 512 3235",
    "sg:postcode":"1821 BT",
    "sg:province":"Noord-Holland",
    "sg:tags":[
        "hang-",
        "sluitwerk",
        "en"
    ],
    "wof:name":"Ree Bv, Van",
    "wof:placetype":"venue"
},
  "geometry": {"coordinates":[4.769924,52.624744],"type":"Point"}
}