{
  "type": "Feature",
  "properties": {
    "addr:full":"Prinsenstr 32 Dalfsen NL.08 7721 AJ",
    "addr:housenumber":"32;nl.08",
    "addr:postcode":"7721 aj",
    "addr:street":"Prinsenstr",
    "iso:country":"NL",
    "sg:address":"Prinsenstr 32",
    "sg:city":"Dalfsen",
    "sg:orig_category":"Verzekeringen - Verzekeringskantoren",
    "sg:phone":"+31 529 431 854",
    "sg:postcode":"7721 AJ",
    "sg:province":"NL.08",
    "sg:website":"http://www.accesnet.nl/univehgv",
    "wof:name":"Univ\u00e9 De Onderlinge",
    "wof:placetype":"venue"
},
  "geometry": {"coordinates":[6.260462,52.504311],"type":"Point"}
}