{
  "type": "Feature",
  "properties": {
    "addr:full":"Contactweg 48 Amsterdam Noord-Holland 1014 AN",
    "addr:housenumber":"48",
    "addr:postcode":"1014 an",
    "addr:street":"Contactweg",
    "iso:country":"NL",
    "sg:address":"Contactweg 48",
    "sg:city":"Amsterdam",
    "sg:orig_category":"Autokeuringen",
    "sg:phone":"+31 20 687 0130",
    "sg:postcode":"1014 AN",
    "sg:province":"Noord-Holland",
    "wof:name":"Ambacht Autoschade Amsterdam Bv",
    "wof:placetype":"venue"
},
  "geometry": {"coordinates":[4.855934,52.393757],"type":"Point"}
}