{
  "type": "Feature",
  "properties": {
    "addr:full":"Hoenkoops Buurtwg 40 Haastrecht Zuid-Holland 2851 AK",
    "addr:housenumber":"40",
    "addr:postcode":"2851 ak",
    "iso:country":"NL",
    "sg:address":"Hoenkoops Buurtwg 40",
    "sg:city":"Haastrecht",
    "sg:orig_category":"Geluidsinstallaties - Verhuur",
    "sg:phone":"+31 348 564 255",
    "sg:postcode":"2851 AK",
    "sg:province":"Zuid-Holland",
    "sg:website":"http://www.klaproos.nl",
    "wof:name":"Klaproos",
    "wof:placetype":"venue"
},
  "geometry": {"coordinates":[4.823974,52.000687],"type":"Point"}
}