{
  "type": "Feature",
  "properties": {
    "addr:full":"Hemmerbuurt 148 Hem Noord-Holland 1607 CN",
    "addr:housenumber":"148",
    "addr:postcode":"1607 cn",
    "addr:street":"Hemmerbuurt",
    "iso:country":"NL",
    "sg:address":"Hemmerbuurt 148",
    "sg:city":"Hem",
    "sg:orig_category":"Diverse Consumentenartikelen Gh",
    "sg:phone":"+31 228 542 432",
    "sg:postcode":"1607 CN",
    "sg:province":"Noord-Holland",
    "wof:name":"Sjerps - Groot",
    "wof:placetype":"venue"
},
  "geometry": {"coordinates":[-84.171921,34.890556],"type":"Point"}
}