{
  "type": "Feature",
  "properties": {
    "addr:full":"Schieweg 233 Rotterdam Zuid-Holland 3038 AW",
    "addr:housenumber":"233",
    "addr:postcode":"3038 aw",
    "addr:street":"Schieweg",
    "iso:country":"NL",
    "sg:address":"Schieweg 233",
    "sg:city":"Rotterdam",
    "sg:orig_category":"Paramedische Behandelingen",
    "sg:phone":"+31 10 465 7763",
    "sg:postcode":"3038 AW",
    "sg:province":"Zuid-Holland",
    "wof:name":"Praktijk Podotherapie Noord",
    "wof:placetype":"venue"
},
  "geometry": {"coordinates":[4.463418,51.936382],"type":"Point"}
}