{
  "type": "Feature",
  "properties": {
    "iso:country":"NL",
    "sg:address":"Essenerweg 166",
    "sg:city":"Kootwijkerbroek",
    "sg:orig_category":"Levende Dieren Gh",
    "sg:phone":"+31 342 442 408",
    "sg:postcode":"3774 LD",
    "sg:province":"Gelderland",
    "wof:name":"J. Van Zanten Bv",
    "wof:placetype":"venue"
},
  "geometry": {"coordinates":[5.711546,52.151573],"type":"Point"}
}