{
  "type": "Feature",
  "properties": {
    "addr:full":"Essenerweg 166 Kootwijkerbroek Gelderland 3774 LD",
    "addr:housenumber":"166",
    "addr:postcode":"3774 ld",
    "addr:street":"Essenerweg;Gelderland",
    "iso:country":"NL",
    "sg:address":"Essenerweg 166",
    "sg:city":"Kootwijkerbroek",
    "sg:orig_category":"Levende Dieren Gh",
    "sg:phone":"+31 342 442 408",
    "sg:postcode":"3774 LD",
    "sg:province":"Gelderland",
    "wof:name":"J. Van Zanten Bv",
    "wof:placetype":"venue"
},
  "geometry": {"coordinates":[5.711546,52.151573],"type":"Point"}
}