{
  "type": "Feature",
  "properties": {
    "addr:full":"Conradweg 5 Haarlem Noord-Holland 2031 CM",
    "addr:housenumber":"5",
    "addr:postcode":"2031 cm",
    "addr:street":"Conradweg",
    "iso:country":"NL",
    "sg:address":"Conradweg 5",
    "sg:city":"Haarlem",
    "sg:orig_category":"Airconditioning And Ventilatie",
    "sg:phone":"+31 23 551 5050",
    "sg:postcode":"2031 CM",
    "sg:province":"Noord-Holland",
    "wof:name":"Afr Koeltechniek",
    "wof:placetype":"venue"
},
  "geometry": {"coordinates":[4.661719,52.386745],"type":"Point"}
}