{
  "type": "Feature",
  "properties": {
    "addr:full":"West Zandberg 47 Kruisland North Brabant 4756 BP",
    "addr:housenumber":"47",
    "addr:postcode":"4756 bp",
    "addr:street":"West Zandberg",
    "iso:country":"NL",
    "sg:address":"West Zandberg 47",
    "sg:city":"Kruisland",
    "sg:classifiers":[
        {
            "category":"Education",
            "subcategory":"Preschool",
            "type":"Public Place"
        }
    ],
    "sg:phone":"+31 167 532 352",
    "sg:postcode":"4756 BP",
    "sg:province":"North Brabant",
    "sg:tags":[
        "kleuteronderwijs",
        "basis-"
    ],
    "wof:name":"Basisschool De Zonneberg",
    "wof:placetype":"venue"
},
  "geometry": {"coordinates":[4.410611,51.57093],"type":"Point"}
}