{
  "type": "Feature",
  "properties": {
    "addr:full":"Wendtsteinweg 39 Marum Groningen 9363 AL",
    "addr:housenumber":"39",
    "addr:postcode":"9363 al",
    "addr:street":"Wendtsteinweg",
    "iso:country":"NL",
    "sg:address":"Wendtsteinweg 39",
    "sg:city":"Marum",
    "sg:orig_category":"Fietshandelaren",
    "sg:phone":"+31 594 641 392",
    "sg:postcode":"9363 AL",
    "sg:province":"Groningen",
    "wof:name":"Hiemstra",
    "wof:placetype":"venue"
},
  "geometry": {"coordinates":[6.269875,53.145214],"type":"Point"}
}