{
  "type": "Feature",
  "properties": {
    "addr:full":"Voorstraat 20 Spijkenisse South Holland 3201 BB",
    "addr:housenumber":"20",
    "addr:postcode":"3201 bb",
    "addr:street":"Voorstraat",
    "iso:country":"NL",
    "sg:address":"Voorstraat 20",
    "sg:city":"Spijkenisse",
    "sg:orig_category":"Verlichting And Huishoudartikelen",
    "sg:phone":"+31 181 612 777",
    "sg:postcode":"3201 BB",
    "sg:province":"South Holland",
    "wof:name":"Van Genderen Cv",
    "wof:placetype":"venue"
},
  "geometry": {"coordinates":[4.325045,51.849525],"type":"Point"}
}