{
  "type": "Feature",
  "properties": {
    "iso:country":"NL",
    "sg:address":"Mendelssohnstraat 34",
    "sg:city":"Numansdorp",
    "sg:orig_category":"Verhuur Catering-, Feest- En Evenementbenodigdheden",
    "sg:phone":"+31 186 652 108",
    "sg:postcode":"3281 VJ",
    "sg:province":"South Holland",
    "wof:name":"Razenberg Horeca Benodigdheden Bv",
    "wof:placetype":"venue"
},
  "geometry": {"coordinates":[4.434897,51.736668],"type":"Point"}
}