{
  "type": "Feature",
  "properties": {
    "addr:full":"Nieuweweg 52 Lochem Gelderland 7241 EW",
    "addr:housenumber":"52",
    "addr:postcode":"7241 ew",
    "addr:street":"Nieuweweg;Gelderland",
    "iso:country":"NL",
    "sg:address":"Nieuweweg 52",
    "sg:city":"Lochem",
    "sg:orig_category":"Marktonderzoekbureaus",
    "sg:phone":"+31 573 254 169",
    "sg:postcode":"7241 EW",
    "sg:province":"Gelderland",
    "wof:name":"Drs. F.D.M.M. Simons Bedrijfsadv. En Opl",
    "wof:placetype":"venue"
},
  "geometry": {"coordinates":[6.421027,52.156773],"type":"Point"}
}