{
  "type": "Feature",
  "properties": {
    "addr:full":"Ravenstraat 26 Oene Gelderland 8167 NS",
    "addr:housenumber":"26",
    "addr:postcode":"8167 ns",
    "addr:street":"Ravenstraat;Gelderland",
    "iso:country":"NL",
    "sg:address":"Ravenstraat 26",
    "sg:city":"Oene",
    "sg:orig_category":"Public Relationbureaus",
    "sg:phone":"+31 578 641 464",
    "sg:postcode":"8167 NS",
    "sg:province":"Gelderland",
    "wof:name":"Wiertz Pr & Communicatie",
    "wof:placetype":"venue"
},
  "geometry": {"coordinates":[6.034651,52.335751],"type":"Point"}
}