{
  "type": "Feature",
  "properties": {
    "addr:full":"Oude Kijk In 'T Jatstr 30 Groningen Groningen 9712 EK",
    "addr:housenumber":"30",
    "addr:postcode":"9712 ek",
    "addr:street":"Oude Kijk In ' T Jatstr",
    "iso:country":"NL",
    "sg:address":"Oude Kijk In 'T Jatstr 30",
    "sg:city":"Groningen",
    "sg:orig_category":"Verlichting And Huishoudartikelen",
    "sg:phone":"+31 50 313 7715",
    "sg:postcode":"9712 EK",
    "sg:province":"Groningen",
    "wof:name":"John John 'S Homedecorations",
    "wof:placetype":"venue"
},
  "geometry": {"coordinates":[6.56368,53.221481],"type":"Point"}
}