{
  "type": "Feature",
  "properties": {
    "addr:full":"Uithoornstr 59 Amsterdam Noord-Holland 1078 SW",
    "addr:housenumber":"59;1078",
    "addr:street":"Uithoornstr;Sw",
    "iso:country":"NL",
    "sg:address":"Uithoornstr 59",
    "sg:city":"Amsterdam",
    "sg:orig_category":"Onderhoudswerken",
    "sg:phone":"+31 6 24528938",
    "sg:postcode":"1078 SW",
    "sg:province":"Noord-Holland",
    "wof:name":"Kevklus",
    "wof:placetype":"venue"
},
  "geometry": {"coordinates":[4.90638,52.347057],"type":"Point"}
}