{
  "type": "Feature",
  "properties": {
    "iso:country":"NL",
    "sg:address":"Uithoornstr 59",
    "sg:city":"Amsterdam",
    "sg:orig_category":"Onderhoudswerken",
    "sg:phone":"+31 6 24528938",
    "sg:postcode":"1078 SW",
    "sg:province":"Noord-Holland",
    "wof:name":"Kevklus",
    "wof:placetype":"venue"
},
  "geometry": {"coordinates":[4.90638,52.347057],"type":"Point"}
}