{
  "type": "Feature",
  "properties": {
    "addr:full":"Steurstr 28 Woudrichem North Brabant 4285 XG",
    "addr:housenumber":"28",
    "addr:postcode":"4285 xg",
    "addr:street":"Steurstr",
    "iso:country":"NL",
    "sg:address":"Steurstr 28",
    "sg:city":"Woudrichem",
    "sg:orig_category":"Organisatiebureaus",
    "sg:phone":"+31 183 304 430",
    "sg:postcode":"4285 XG",
    "sg:province":"North Brabant",
    "wof:name":"Wb",
    "wof:placetype":"venue"
},
  "geometry": {"coordinates":[4.9939770699,51.8120651245],"type":"Point"}
}