{
  "type": "Feature",
  "properties": {
    "iso:country":"NL",
    "sg:address":"Bernadettestraat 4A",
    "sg:city":"Bergen Op Zoom",
    "sg:orig_category":"Verenigingen En Stichtingen",
    "sg:phone":"+31 164 241 397",
    "sg:postcode":"4615 EV",
    "sg:province":"Noord-Brabant",
    "wof:name":"Uithof, De",
    "wof:placetype":"venue"
},
  "geometry": {"coordinates":[4.28741,51.487045],"type":"Point"}
}