{
  "type": "Feature",
  "properties": {
    "addr:full":"Bernadettestraat 4A Bergen Op Zoom Noord-Brabant 4615 EV",
    "addr:housenumber":"4a",
    "addr:postcode":"4615 ev",
    "addr:street":"Bernadettestraat",
    "iso:country":"NL",
    "sg:address":"Bernadettestraat 4A",
    "sg:city":"Bergen Op Zoom",
    "sg:orig_category":"Verenigingen En Stichtingen",
    "sg:phone":"+31 164 241 397",
    "sg:postcode":"4615 EV",
    "sg:province":"Noord-Brabant",
    "wof:name":"Uithof, De",
    "wof:placetype":"venue"
},
  "geometry": {"coordinates":[4.28741,51.487045],"type":"Point"}
}