{
  "type": "Feature",
  "properties": {
    "iso:country":"NL",
    "sg:address":"Schoolstr 45",
    "sg:city":"Prinsenbeek",
    "sg:orig_category":"Scholen Voor Basisonderwijs",
    "sg:phone":"+31 76 541 2948",
    "sg:postcode":"4841 XC",
    "sg:province":"North Brabant",
    "wof:name":"Griffioen Rk, De",
    "wof:placetype":"venue"
},
  "geometry": {"coordinates":[4.710322,51.599876],"type":"Point"}
}