{
  "type": "Feature",
  "properties": {
    "addr:full":"Regentesselaan 125 'S Gravenhage Zuid-Holland 2562 CW",
    "addr:housenumber":"125 '",
    "addr:postcode":"2562 cw",
    "addr:street":"Regentesselaan",
    "iso:country":"NL",
    "sg:address":"Regentesselaan 125",
    "sg:city":"'S Gravenhage",
    "sg:orig_category":"Wasserettes And Stomerijen",
    "sg:phone":"+31 70 345 3745",
    "sg:postcode":"2562 CW",
    "sg:province":"Zuid-Holland",
    "wof:name":"Fristamatic Wassalon",
    "wof:placetype":"venue"
},
  "geometry": {"coordinates":[4.2826581001,52.0761375427],"type":"Point"}
}