{
  "type": "Feature",
  "properties": {
    "iso:country":"NL",
    "sg:address":"Roosendaalsestraat 1",
    "sg:city":"Wouw",
    "sg:orig_category":"Bloemen And Planten",
    "sg:phone":"+31 165 304 661",
    "sg:postcode":"4724 AA",
    "sg:province":"Noord-Brabant",
    "wof:name":"Muurbloem Plant En Kado",
    "wof:placetype":"venue"
},
  "geometry": {"coordinates":[4.388827,51.522877],"type":"Point"}
}