{
  "type": "Feature",
  "properties": {
    "iso:country":"NL",
    "sg:address":"Hilledk 97A",
    "sg:city":"Rotterdam",
    "sg:orig_category":"Verenigingen En Stichtingen",
    "sg:phone":"+31 10 486 4066",
    "sg:postcode":"3072 RE",
    "sg:province":"South Holland",
    "wof:name":"Feyenoord Welzijn",
    "wof:placetype":"venue"
},
  "geometry": {"coordinates":[4.504777,51.902153],"type":"Point"}
}