{
  "type": "Feature",
  "properties": {
    "iso:country":"NL",
    "sg:address":"Brielsemeer 30",
    "sg:city":"Purmerend",
    "sg:orig_category":"Autorijscholen",
    "sg:phone":"+31 299 649 420",
    "sg:postcode":"1447 JG",
    "sg:province":"Noord-Holland",
    "wof:name":"Aida",
    "wof:placetype":"venue"
},
  "geometry": {"coordinates":[4.972745,52.496662],"type":"Point"}
}