{
  "type": "Feature",
  "properties": {
    "iso:country":"NL",
    "sg:address":"Bentinckstraat 36",
    "sg:city":"Arnhem",
    "sg:orig_category":"Opticiens",
    "sg:phone":"+31 26 370 3705",
    "sg:postcode":"6811 EE",
    "sg:province":"Gelderland",
    "sg:website":"http://www.4doptiek",
    "wof:name":"4D-D Optiek",
    "wof:placetype":"venue"
},
  "geometry": {"coordinates":[5.909055233,51.9809265137],"type":"Point"}
}