{
  "type": "Feature",
  "properties": {
    "addr:full":"Elegaststr 9 Alkmaar Noord-Holland 1813 LA",
    "addr:housenumber":"9",
    "addr:postcode":"1813 la",
    "addr:street":"Elegaststr",
    "iso:country":"NL",
    "sg:address":"Elegaststr 9",
    "sg:city":"Alkmaar",
    "sg:orig_category":"Boeken En Tijdschriften",
    "sg:phone":"+31 72 540 6134",
    "sg:postcode":"1813 LA",
    "sg:province":"Noord-Holland",
    "wof:name":"Bruin, R De",
    "wof:placetype":"venue"
},
  "geometry": {"coordinates":[4.753465,52.617672],"type":"Point"}
}