{
  "type": "Feature",
  "properties": {
    "addr:full":"Zuidlandstraat 24 Terneuzen Zeeland 4532 CG",
    "addr:housenumber":"24",
    "addr:postcode":"4532 cg",
    "addr:street":"Zuidlandstraat",
    "iso:country":"NL",
    "sg:address":"Zuidlandstraat 24",
    "sg:city":"Terneuzen",
    "sg:classifiers":[
        {
            "category":"Bakery",
            "type":"Food & Drink"
        }
    ],
    "sg:phone":"+31 115 612 456",
    "sg:postcode":"4532 CG",
    "sg:province":"Zeeland",
    "sg:tags":[
        "brood",
        "banket"
    ],
    "wof:name":"J P Vd Velde Brood En Banketbakkerij",
    "wof:placetype":"venue"
},
  "geometry": {"coordinates":[3.837691,51.32835],"type":"Point"}
}