{
  "type": "Feature",
  "properties": {
    "iso:country":"NL",
    "sg:address":"Vliegersveld 21",
    "sg:city":"Biddinghuizen",
    "sg:orig_category":"Antiekzaken",
    "sg:phone":"+31 321 331 989",
    "sg:postcode":"8256 GN",
    "sg:province":"Flevoland",
    "wof:name":"Context",
    "wof:placetype":"venue"
},
  "geometry": {"coordinates":[5.697052002,52.4486694336],"type":"Point"}
}