{
  "type": "Feature",
  "properties": {
    "iso:country":"NL",
    "sg:address":"Achterom 67",
    "sg:city":"Hoorn",
    "sg:orig_category":"Journalisten Freelance",
    "sg:phone":"+31 229 217 783",
    "sg:postcode":"1621 KS",
    "sg:province":"North Holland",
    "wof:name":"Rijswijk Prod",
    "wof:placetype":"venue"
},
  "geometry": {"coordinates":[5.055629,52.640842],"type":"Point"}
}