{
  "type": "Feature",
  "properties": {
    "addr:full":"Dorpsstr 3 Nigtevecht Utrecht 1393 NE",
    "addr:housenumber":"3",
    "addr:postcode":"1393 ne",
    "addr:street":"Dorpsstr",
    "iso:country":"NL",
    "sg:address":"Dorpsstr 3",
    "sg:city":"Nigtevecht",
    "sg:orig_category":"Adviesbureaus Bedrijfsorganisatie",
    "sg:phone":"+31 294 252 381",
    "sg:postcode":"1393 NE",
    "sg:province":"Utrecht",
    "wof:name":"Goes Cons",
    "wof:placetype":"venue"
},
  "geometry": {"coordinates":[5.023294,52.274097],"type":"Point"}
}