{
  "type": "Feature",
  "properties": {
    "addr:full":"Scheldeplein 20 Amsterdam Noord-Holland 1078 GR",
    "addr:housenumber":"20",
    "addr:postcode":"1078",
    "addr:street":"Scheldeplein",
    "iso:country":"NL",
    "sg:address":"Scheldeplein 20",
    "sg:city":"Amsterdam",
    "sg:orig_category":"Sportprijzen, Postzegels And Munten",
    "sg:phone":"+31 20 664 1202",
    "sg:postcode":"1078 GR",
    "sg:province":"Noord-Holland",
    "wof:name":"Thurn & Taxis",
    "wof:placetype":"venue"
},
  "geometry": {"coordinates":[4.889798,52.34444],"type":"Point"}
}