{
  "type": "Feature",
  "properties": {
    "addr:full":"Grotestraat 136 Drunen North Brabant 5151 BN",
    "addr:housenumber":"136",
    "addr:postcode":"5151 bn",
    "addr:street":"Grotestraat",
    "iso:country":"NL",
    "sg:address":"Grotestraat 136",
    "sg:city":"Drunen",
    "sg:orig_category":"Fotostudio'S And Fotografen",
    "sg:phone":"+31 416 372 964",
    "sg:postcode":"5151 BN",
    "sg:province":"North Brabant",
    "wof:name":"Fotografie Henk De Jong",
    "wof:placetype":"venue"
},
  "geometry": {"coordinates":[5.133114,51.686382],"type":"Point"}
}