{
  "type": "Feature",
  "properties": {
    "iso:country":"NL",
    "sg:address":"De Orion 14",
    "sg:city":"Drachten",
    "sg:orig_category":"Autorijscholen",
    "sg:phone":"+31 512 543 408",
    "sg:postcode":"9207 BA",
    "sg:province":"Provincie Friesland",
    "wof:name":"Sluis, Van Der",
    "wof:placetype":"venue"
},
  "geometry": {"coordinates":[6.087222,53.11755],"type":"Point"}
}