{
  "type": "Feature",
  "properties": {
    "iso:country":"NL",
    "sg:address":"Herwendaalsehoek 18",
    "sg:city":"Groesbeek",
    "sg:orig_category":"Honden- En Kattentrimsalons",
    "sg:phone":"+31 24 397 7344",
    "sg:postcode":"6562 ZP",
    "sg:province":"Gelderland",
    "wof:name":"Sandra'S Trimsalon",
    "wof:placetype":"venue"
},
  "geometry": {"coordinates":[5.93,51.7728],"type":"Point"}
}