{
  "type": "Feature",
  "properties": {
    "iso:country":"NL",
    "sg:address":"Rusthofln 100",
    "sg:city":"Rotterdam",
    "sg:orig_category":"Meubelstoffering",
    "sg:phone":"+31 10 413 5778",
    "sg:postcode":"3034 XP",
    "sg:province":"South Holland",
    "wof:name":"Lindhout, Rinus & Jan",
    "wof:placetype":"venue"
},
  "geometry": {"coordinates":[4.497681,51.934647],"type":"Point"}
}