{
  "type": "Feature",
  "properties": {
    "addr:full":"Bornerweg 13 Limbricht Limburg 6141 BJ",
    "addr:housenumber":"13",
    "addr:postcode":"6141 bj",
    "addr:street":"Bornerweg",
    "iso:country":"NL",
    "sg:address":"Bornerweg 13",
    "sg:city":"Limbricht",
    "sg:orig_category":"Beursorganisaties And Standbouw",
    "sg:phone":"+31 46 451 6323",
    "sg:postcode":"6141 BJ",
    "sg:province":"Limburg",
    "wof:name":"Janssen Reklameprodukties",
    "wof:placetype":"venue"
},
  "geometry": {"coordinates":[5.833935,51.014977],"type":"Point"}
}