{
  "type": "Feature",
  "properties": {
    "iso:country":"NL",
    "sg:address":"Buizerderf 65",
    "sg:city":"Voorschoten",
    "sg:orig_category":"Administratie- En Boekhoudkantoren",
    "sg:phone":"+31 71 561 2003",
    "sg:postcode":"2251 MS",
    "sg:province":"Zuid-Holland",
    "wof:name":"Buizerd, De",
    "wof:placetype":"venue"
},
  "geometry": {"coordinates":[4.451366,52.119534],"type":"Point"}
}