{
  "type": "Feature",
  "properties": {
    "addr:full":"Vismarkt 15 Groningen Groningen 9712 CA",
    "addr:housenumber":"15",
    "addr:postcode":"9712 ca",
    "addr:street":"Vismarkt",
    "iso:country":"NL",
    "sg:address":"Vismarkt 15",
    "sg:city":"Groningen",
    "sg:orig_category":"Juweliers",
    "sg:phone":"+31 50 318 8190",
    "sg:postcode":"9712 CA",
    "sg:province":"Groningen",
    "wof:name":"Copini, Jac",
    "wof:placetype":"venue"
},
  "geometry": {"coordinates":[6.565096,53.21756],"type":"Point"}
}