{
  "type": "Feature",
  "properties": {
    "addr:full":"Jeltje De Bosch Kemperpd 120 Amsterdam Noord-Holland 1054 PM",
    "addr:housenumber":"120",
    "addr:postcode":"1054 pm",
    "addr:street":"Jeltje De Bosch Kemperpd",
    "iso:country":"NL",
    "sg:address":"Jeltje De Bosch Kemperpd 120",
    "sg:city":"Amsterdam",
    "sg:orig_category":"Artiesten",
    "sg:phone":"+31 20 689 2438",
    "sg:postcode":"1054 PM",
    "sg:province":"Noord-Holland",
    "wof:name":"O Hetterscheid",
    "wof:placetype":"venue"
},
  "geometry": {"coordinates":[4.868135,52.362728],"type":"Point"}
}