{
  "type": "Feature",
  "properties": {
    "iso:country":"NL",
    "sg:address":"Klifrakplnts 168",
    "sg:city":"Utrecht",
    "sg:classifiers":[
        {
            "category":"Personal",
            "subcategory":"Nail Salon",
            "type":"Services"
        }
    ],
    "sg:phone":"+31 30 288 7925",
    "sg:postcode":"3544 RC",
    "sg:province":"Utrecht",
    "sg:tags":[
        "pedicure"
    ],
    "wof:name":"Jalila",
    "wof:placetype":"venue"
},
  "geometry": {"coordinates":[5.057141,52.084812],"type":"Point"}
}