{
  "type": "Feature",
  "properties": {
    "iso:country":"NL",
    "sg:address":"Keizersgr 77",
    "sg:city":"Amsterdam",
    "sg:orig_category":"Architecten En Architectenbureaus",
    "sg:phone":"+31 20 422 0825",
    "sg:postcode":"1015 CE",
    "sg:province":"Noord-Holland",
    "wof:name":"Mullerners + Mullerners Bv",
    "wof:placetype":"venue"
},
  "geometry": {"coordinates":[4.888808,52.377869],"type":"Point"}
}