{
  "type": "Feature",
  "properties": {
    "iso:country":"NL",
    "sg:address":"Palenbergstraat 46",
    "sg:city":"Heerlen",
    "sg:orig_category":"Bedrijfs- And Managementsconsultants",
    "sg:phone":"+31 45 572 6537",
    "sg:postcode":"6415 RD",
    "sg:province":"Limburg",
    "wof:name":"A.H.L. Thomas Counselling En Consultancy",
    "wof:placetype":"venue"
},
  "geometry": {"coordinates":[5.983351,50.903049],"type":"Point"}
}