{
  "type": "Feature",
  "properties": {
    "iso:country":"NL",
    "sg:address":"Brouwer 8",
    "sg:city":"Eersel",
    "sg:orig_category":"Geluidshinderbestrijding",
    "sg:phone":"+31 497 515 809",
    "sg:postcode":"5521 DK",
    "sg:province":"Noord-Brabant",
    "sg:website":"http://www.havoo.com",
    "wof:name":"Havoo Lawaaibestrijding Bv",
    "wof:placetype":"venue"
},
  "geometry": {"coordinates":[5.316923,51.367451],"type":"Point"}
}