{
  "type": "Feature",
  "properties": {
    "addr:full":"Willem De Clercqstraat 89 Almelo NL.08 7604 AR",
    "addr:housenumber":"89;nl.08",
    "addr:postcode":"7604",
    "addr:street":"Willem De Clercqstraat",
    "iso:country":"NL",
    "sg:address":"Willem De Clercqstraat 89",
    "sg:city":"Almelo",
    "sg:orig_category":"Begrafenisondernemers",
    "sg:phone":"+31 546 813 334",
    "sg:postcode":"7604 AR",
    "sg:province":"NL.08",
    "wof:name":"Vredehof Uitvaartverzorging",
    "wof:placetype":"venue"
},
  "geometry": {"coordinates":[6.647207,52.352341],"type":"Point"}
}