{
  "type": "Feature",
  "properties": {
    "addr:full":"Bosrand 25 Ede Gld Gelderland 6718 ZN",
    "addr:housenumber":"25",
    "addr:postcode":"6718 zn",
    "addr:street":"Bosrand;Gld Gelderland",
    "iso:country":"NL",
    "sg:address":"Bosrand 25",
    "sg:city":"Ede Gld",
    "sg:orig_category":"Makelaars In Onroerend Goed",
    "sg:phone":"+31 318 616 772",
    "sg:postcode":"6718 ZN",
    "sg:province":"Gelderland",
    "wof:name":"B. Van Dasselaar",
    "wof:placetype":"venue"
},
  "geometry": {"coordinates":[5.681025,52.052116],"type":"Point"}
}