{
  "type": "Feature",
  "properties": {
    "addr:full":"Yzerwg 1C Heerenveen Provincie Friesland 8445 PK",
    "addr:housenumber":"1c",
    "addr:postcode":"8445 pk",
    "addr:street":"Yzerwg;Provincie Friesland",
    "iso:country":"NL",
    "sg:address":"Yzerwg 1C",
    "sg:city":"Heerenveen",
    "sg:orig_category":"Metaalbewerking",
    "sg:phone":"+31 513 633 733",
    "sg:postcode":"8445 PK",
    "sg:province":"Provincie Friesland",
    "wof:name":"Tolsma",
    "wof:placetype":"venue"
},
  "geometry": {"coordinates":[5.943658,52.934483],"type":"Point"}
}