{
  "type": "Feature",
  "properties": {
    "addr:full":"Jasmynstr 55 Ridderkerk Zuid-Holland 2982 CL",
    "addr:housenumber":"55",
    "addr:postcode":"2982",
    "addr:street":"Jasmynstr",
    "iso:country":"NL",
    "sg:address":"Jasmynstr 55",
    "sg:city":"Ridderkerk",
    "sg:orig_category":"Vertalers",
    "sg:phone":"+31 180 480 079",
    "sg:postcode":"2982 CL",
    "sg:province":"Zuid-Holland",
    "wof:name":"Quality Translation China",
    "wof:placetype":"venue"
},
  "geometry": {"coordinates":[4.584594,51.872314],"type":"Point"}
}