{
  "type": "Feature",
  "properties": {
    "iso:country":"NL",
    "sg:address":"Achter De Hoven 193",
    "sg:city":"Leeuwarden",
    "sg:orig_category":"Agenturen En Commissiehandel",
    "sg:phone":"+31 58 216 5290",
    "sg:postcode":"8933 CL",
    "sg:province":"Friesland",
    "wof:name":"Tca",
    "wof:placetype":"venue"
},
  "geometry": {"coordinates":[5.808249,53.196404],"type":"Point"}
}