{
  "type": "Feature",
  "properties": {
    "iso:country":"NL",
    "sg:address":"Wilhelminastr 35",
    "sg:city":"Emmen",
    "sg:orig_category":"Wereldwinkels",
    "sg:phone":"+31 591 645 804",
    "sg:postcode":"7811 JC",
    "sg:province":"Provincie Drenthe",
    "wof:name":"Emmen",
    "wof:placetype":"venue"
},
  "geometry": {"coordinates":[6.8968558311,52.7809410095],"type":"Point"}
}