{
  "type": "Feature",
  "properties": {
    "iso:country":"NL",
    "sg:address":"Bakkerstr 64",
    "sg:city":"Haarlem",
    "sg:orig_category":"Onderhoudswerken",
    "sg:phone":"+31 23 542 0385",
    "sg:postcode":"2012 ZL",
    "sg:province":"Noord-Holland",
    "wof:name":"Heppener, P J",
    "wof:placetype":"venue"
},
  "geometry": {"coordinates":[4.6401290894,52.372592926],"type":"Point"}
}