{
  "type": "Feature",
  "properties": {
    "addr:full":"Merwedestraat 25 Beverwijk Noord-Holland 1946 TM",
    "addr:housenumber":"25",
    "addr:postcode":"1946 tm",
    "addr:street":"Merwedestraat",
    "iso:country":"NL",
    "sg:address":"Merwedestraat 25",
    "sg:city":"Beverwijk",
    "sg:orig_category":"Diverse Bedrijfsinstallaties Gh",
    "sg:phone":"+31 251 239 275",
    "sg:postcode":"1946 TM",
    "sg:province":"Noord-Holland",
    "wof:name":"T.H.C. Technische Handels Centrum",
    "wof:placetype":"venue"
},
  "geometry": {"coordinates":[4.679758,52.490696],"type":"Point"}
}