{
  "type": "Feature",
  "properties": {
    "addr:full":"Nieuwsteeg 16 Hoorn Nh North Holland 1621 ED",
    "addr:housenumber":"16",
    "addr:postcode":"1621 ed",
    "addr:street":"Nieuwsteeg;Nh North",
    "iso:country":"NL",
    "sg:address":"Nieuwsteeg 16",
    "sg:city":"Hoorn Nh",
    "sg:orig_category":"Schoenen",
    "sg:phone":"+31 229 214 198",
    "sg:postcode":"1621 ED",
    "sg:province":"North Holland",
    "wof:name":"Eccolet / Kids Shoes",
    "wof:placetype":"venue"
},
  "geometry": {"coordinates":[5.057746,52.640976],"type":"Point"}
}