{
  "type": "Feature",
  "properties": {
    "iso:country":"NL",
    "sg:address":"Van Hallstraat 99/ 103",
    "sg:city":"Amsterdam",
    "sg:orig_category":"Bloemen And Planten",
    "sg:phone":"+31 20 684 5054",
    "sg:postcode":"1051 HA",
    "sg:province":"Noord-Holland",
    "wof:name":"T Groene Paradijs",
    "wof:placetype":"venue"
},
  "geometry": {"coordinates":[4.871426,52.380848],"type":"Point"}
}