{
  "type": "Feature",
  "properties": {
    "addr:full":"Dykstr 7 Wageningen Gelderland 6701 CH",
    "addr:housenumber":"7",
    "addr:postcode":"6701",
    "addr:street":"Dykstr;Gelderland",
    "iso:country":"NL",
    "sg:address":"Dykstr 7",
    "sg:city":"Wageningen",
    "sg:orig_category":"Geluidsinstallaties - Verhuur",
    "sg:phone":"+31 6 24476190",
    "sg:postcode":"6701 CH",
    "sg:province":"Gelderland",
    "wof:name":"Basstec",
    "wof:placetype":"venue"
},
  "geometry": {"coordinates":[5.660976,51.964355],"type":"Point"}
}