{
  "type": "Feature",
  "properties": {
    "addr:full":"Zomerakker 103 Spijkenisse South Holland 3206 TH",
    "addr:housenumber":"103",
    "addr:postcode":"3206 th",
    "addr:street":"Zomerakker",
    "iso:country":"NL",
    "sg:address":"Zomerakker 103",
    "sg:city":"Spijkenisse",
    "sg:classifiers":[
        {
            "category":"Fast Food",
            "type":"Food & Drink"
        }
    ],
    "sg:phone":"+31 181 638 475",
    "sg:postcode":"3206 TH",
    "sg:province":"South Holland",
    "sg:tags":[
        "afhaal",
        "restaurant"
    ],
    "wof:name":"Snackbar Halte Akkerhof",
    "wof:placetype":"venue"
},
  "geometry": {"coordinates":[4.31923,51.832352],"type":"Point"}
}