{
  "type": "Feature",
  "properties": {
    "addr:full":"Lynbaan 42 Heemskerk Noord-Holland 1969 NE",
    "addr:housenumber":"42;1969",
    "addr:postcode":"ne",
    "addr:street":"Lynbaan",
    "iso:country":"NL",
    "sg:address":"Lynbaan 42",
    "sg:city":"Heemskerk",
    "sg:orig_category":"Hoogwerkers",
    "sg:phone":"+31 251 241 076",
    "sg:postcode":"1969 NE",
    "sg:province":"Noord-Holland",
    "wof:name":"Cas Pronk Schilderwerken & Glashandel",
    "wof:placetype":"venue"
},
  "geometry": {"coordinates":[4.62565,52.513199],"type":"Point"}
}