{
  "type": "Feature",
  "properties": {
    "iso:country":"NL",
    "sg:address":"Miening 40",
    "sg:city":"Zoeterwoude",
    "sg:orig_category":"Goederenvervoer Over De Weg",
    "sg:phone":"+31 71 580 1868",
    "sg:postcode":"2381 GP",
    "sg:province":"Zuid-Holland",
    "wof:name":"Piet Onderwater International Transportb",
    "wof:placetype":"venue"
},
  "geometry": {"coordinates":[4.496267,52.130398],"type":"Point"}
}