{
  "type": "Feature",
  "properties": {
    "iso:country":"NL",
    "sg:address":"Duinwg 5",
    "sg:city":"Bergen Nh",
    "sg:classifiers":[
        {
            "category":"Travel",
            "subcategory":"Hotels & Motels",
            "type":"Entertainment"
        }
    ],
    "sg:phone":"+31 72 582 0520",
    "sg:postcode":"1861 GL",
    "sg:province":"Noord-Holland",
    "sg:website":"http://www.blooming-hotels.com",
    "wof:name":"Blooming Bv",
    "wof:placetype":"venue"
},
  "geometry": {"coordinates":[4.695027,52.679218],"type":"Point"}
}