{
  "type": "Feature",
  "properties": {
    "iso:country":"NL",
    "sg:address":"Uitmaat 5",
    "sg:city":"Giesbeek",
    "sg:orig_category":"Goederenvervoer Over De Weg",
    "sg:phone":"+31 313 631 390",
    "sg:postcode":"6987 ER",
    "sg:province":"Gelderland",
    "wof:name":"Transportbedrijf Ries Wieggers Bv",
    "wof:placetype":"venue"
},
  "geometry": {"coordinates":[6.057381,51.987606],"type":"Point"}
}