{
  "type": "Feature",
  "properties": {
    "iso:country":"NL",
    "sg:address":"Inundatiedk Z 1",
    "sg:city":"Tiel",
    "sg:orig_category":"Projectontwikkeling",
    "sg:phone":"+31 344 626 457",
    "sg:postcode":"4006 PD",
    "sg:province":"Gelderland",
    "wof:name":"Gob Bv",
    "wof:placetype":"venue"
},
  "geometry": {"coordinates":[5.423559,51.877483],"type":"Point"}
}