{
  "type": "Feature",
  "properties": {
    "addr:full":"Schoutenstraat 14 Mijdrecht Utrecht 3641 HW",
    "addr:housenumber":"14",
    "addr:postcode":"3641 hw",
    "addr:street":"Schoutenstraat",
    "iso:country":"NL",
    "sg:address":"Schoutenstraat 14",
    "sg:city":"Mijdrecht",
    "sg:orig_category":"Kantoorartikelen",
    "sg:phone":"+31 297 285 798",
    "sg:postcode":"3641 HW",
    "sg:province":"Utrecht",
    "wof:name":"Van Herpt Kantoormachines",
    "wof:placetype":"venue"
},
  "geometry": {"coordinates":[4.8589711189,52.2060623169],"type":"Point"}
}