{
  "type": "Feature",
  "properties": {
    "iso:country":"NL",
    "sg:address":"Ryksstrwg 247B",
    "sg:city":"Hellevoetsluis",
    "sg:orig_category":"Hengelsportartikelen",
    "sg:phone":"+31 181 316 363",
    "sg:postcode":"3222 KE",
    "sg:province":"Zuid-Holland",
    "sg:website":"http://www.fish-ing.nl",
    "wof:name":"Fish-Ing",
    "wof:placetype":"venue"
},
  "geometry": {"coordinates":[4.143085,51.855431],"type":"Point"}
}