{
  "type": "Feature",
  "properties": {
    "addr:full":"Burg Weertsstr 38 Arnhem Gelderland 6814 HP",
    "addr:housenumber":"38",
    "addr:postcode":"6814 hp",
    "addr:street":"Burg",
    "iso:country":"NL",
    "sg:address":"Burg Weertsstr 38",
    "sg:city":"Arnhem",
    "sg:orig_category":"Optische Instrumenten",
    "sg:phone":"+31 26 442 1784",
    "sg:postcode":"6814 HP",
    "sg:province":"Gelderland",
    "wof:name":"Engelhard",
    "wof:placetype":"venue"
},
  "geometry": {"coordinates":[5.8976259232,51.9898109436],"type":"Point"}
}