{
  "type": "Feature",
  "properties": {
    "addr:full":"Cinnaberstr 28 Almere Flevoland 1339 CL",
    "addr:housenumber":"28",
    "addr:postcode":"1339",
    "addr:street":"Cinnaberstr;Flevoland",
    "iso:country":"NL",
    "sg:address":"Cinnaberstr 28",
    "sg:city":"Almere",
    "sg:orig_category":"Natuurvoeding En Reformartikelen - Fabrieken En Groothandel",
    "sg:phone":"+31 36 535 1431",
    "sg:postcode":"1339 CL",
    "sg:province":"Flevoland",
    "wof:name":"Meerten, M R Van",
    "wof:placetype":"venue"
},
  "geometry": {"coordinates":[5.298894,52.396374],"type":"Point"}
}