{
  "type": "Feature",
  "properties": {
    "addr:full":"Prinsenhof 19 Pynacker Zuid-Holland 2641 RP",
    "addr:housenumber":"19",
    "addr:postcode":"2641 rp",
    "addr:street":"Prinsenhof",
    "iso:country":"NL",
    "sg:address":"Prinsenhof 19",
    "sg:city":"Pynacker",
    "sg:orig_category":"Schilders",
    "sg:phone":"+31 15 369 5533",
    "sg:postcode":"2641 RP",
    "sg:province":"Zuid-Holland",
    "wof:name":"F & E, Schildersbedrijf",
    "wof:placetype":"venue"
},
  "geometry": {"coordinates":[4.436975,52.013458],"type":"Point"}
}