{
  "type": "Feature",
  "properties": {
    "addr:full":"De Kempenaerstr 25 Oegstgeest Zuid-Holland 2341 GG",
    "addr:housenumber":"25",
    "addr:postcode":"2341 gg",
    "iso:country":"NL",
    "sg:address":"De Kempenaerstr 25",
    "sg:city":"Oegstgeest",
    "sg:orig_category":"Postkantoren",
    "sg:phone":"+31 71 517 5902",
    "sg:postcode":"2341 GG",
    "sg:province":"Zuid-Holland",
    "sg:website":"http://www.postkantoor.nl",
    "wof:name":"Postkantoor",
    "wof:placetype":"venue"
},
  "geometry": {"coordinates":[4.469058,52.177521],"type":"Point"}
}