{
  "type": "Feature",
  "properties": {
    "iso:country":"NL",
    "sg:address":"Weerdingerstraat 46",
    "sg:city":"Emmen",
    "sg:orig_category":"Kappers",
    "sg:phone":"+31 591 611 956",
    "sg:postcode":"7815 SC",
    "sg:province":"Provincie Drenthe",
    "wof:name":"Kapsalon Joling",
    "wof:placetype":"venue"
},
  "geometry": {"coordinates":[6.897245,52.791779],"type":"Point"}
}