{
  "type": "Feature",
  "properties": {
    "iso:country":"NL",
    "sg:address":"Horsterweg 1",
    "sg:city":"Elsloo Lb",
    "sg:orig_category":"Landbouwmachines Gh",
    "sg:phone":"+31 46 437 2556",
    "sg:postcode":"6181 JX",
    "sg:province":"Limburg",
    "wof:name":"Agrimaas",
    "wof:placetype":"venue"
},
  "geometry": {"coordinates":[5.771398,50.931633],"type":"Point"}
}