{
  "type": "Feature",
  "properties": {
    "addr:full":"Horsterweg 1 Elsloo Lb Limburg 6181 JX",
    "addr:housenumber":"1",
    "addr:postcode":"lb;6181 jx",
    "addr:street":"Horsterweg",
    "iso:country":"NL",
    "sg:address":"Horsterweg 1",
    "sg:city":"Elsloo Lb",
    "sg:orig_category":"Landbouwmachines Gh",
    "sg:phone":"+31 46 437 2556",
    "sg:postcode":"6181 JX",
    "sg:province":"Limburg",
    "wof:name":"Agrimaas",
    "wof:placetype":"venue"
},
  "geometry": {"coordinates":[5.771398,50.931633],"type":"Point"}
}