{
  "type": "Feature",
  "properties": {
    "addr:full":"Alexanderstr 12 Waalre Noord-Brabant 5583 BK",
    "addr:housenumber":"12",
    "addr:postcode":"5583 bk",
    "addr:street":"Alexanderstr",
    "iso:country":"NL",
    "sg:address":"Alexanderstr 12",
    "sg:city":"Waalre",
    "sg:orig_category":"Administratie- En Boekhoudkantoren",
    "sg:phone":"+31 40 221 5067",
    "sg:postcode":"5583 BK",
    "sg:province":"Noord-Brabant",
    "wof:name":"Latu",
    "wof:placetype":"venue"
},
  "geometry": {"coordinates":[5.479317,51.394943],"type":"Point"}
}