{
  "type": "Feature",
  "properties": {
    "addr:full":"Kerklaan 55 Scheemda Groningen 9679 AD",
    "addr:housenumber":"55",
    "addr:postcode":"9679 ad",
    "addr:street":"Kerklaan",
    "iso:country":"NL",
    "sg:address":"Kerklaan 55",
    "sg:city":"Scheemda",
    "sg:orig_category":"Architecten",
    "sg:phone":"+31 597 592 455",
    "sg:postcode":"9679 AD",
    "sg:province":"Groningen",
    "wof:name":"Timmer Bna Bv",
    "wof:placetype":"venue"
},
  "geometry": {"coordinates":[6.964022,53.174648],"type":"Point"}
}