{
  "type": "Feature",
  "properties": {
    "addr:full":"Past Vullinghspln 5 Grubbenvorst Limburg 5971 CB",
    "addr:housenumber":"5",
    "addr:postcode":"5971 cb",
    "iso:country":"NL",
    "sg:address":"Past Vullinghspln 5",
    "sg:city":"Grubbenvorst",
    "sg:orig_category":"Hek- En Rasterwerken",
    "sg:phone":"+31 77 366 3020",
    "sg:postcode":"5971 CB",
    "sg:province":"Limburg",
    "wof:name":"Simons, Ronald",
    "wof:placetype":"venue"
},
  "geometry": {"coordinates":[6.14795,51.419304],"type":"Point"}
}