{
  "type": "Feature",
  "properties": {
    "addr:full":"Koningin Julianastraat 34 Bergeyk Noord-Brabant 5571 GE",
    "addr:housenumber":"34",
    "addr:postcode":"5571",
    "addr:street":"Koningin Julianastraat",
    "iso:country":"NL",
    "sg:address":"Koningin Julianastraat 34",
    "sg:city":"Bergeyk",
    "sg:orig_category":"Bedrijfs- And Managementsconsultants",
    "sg:phone":"+31 497 573 488",
    "sg:postcode":"5571 GE",
    "sg:province":"Noord-Brabant",
    "wof:name":"Adviesbureau Vervest",
    "wof:placetype":"venue"
},
  "geometry": {"coordinates":[5.367336,51.320549],"type":"Point"}
}