{
  "type": "Feature",
  "properties": {
    "addr:full":"Verdiplein 107 Tilburg Noord-Brabant 5049 NR",
    "addr:housenumber":"107",
    "addr:postcode":"5049 nr",
    "addr:street":"Verdiplein",
    "iso:country":"NL",
    "sg:address":"Verdiplein 107",
    "sg:city":"Tilburg",
    "sg:classifiers":[
        {
            "category":"Bakery",
            "type":"Food & Drink"
        }
    ],
    "sg:phone":"+31 13 455 3155",
    "sg:postcode":"5049 NR",
    "sg:province":"Noord-Brabant",
    "sg:tags":[
        "brood",
        "banket"
    ],
    "wof:name":"Echte Bakker Toon Van Gastel",
    "wof:placetype":"venue"
},
  "geometry": {"coordinates":[5.079801,51.590775],"type":"Point"}
}