{
  "type": "Feature",
  "properties": {
    "iso:country":"NL",
    "sg:address":"Turfkade 15",
    "sg:city":"Goes",
    "sg:orig_category":"Onderhoud And Reparatie Kantoorapparatuur",
    "sg:phone":"+31 113 271 234",
    "sg:postcode":"4461 AP",
    "sg:province":"Kansas",
    "wof:name":"De Witte Supplies",
    "wof:placetype":"venue"
},
  "geometry": {"coordinates":[-97.33519699999999,38.24715],"type":"Point"}
}