{
  "type": "Feature",
  "properties": {
    "iso:country":"NL",
    "sg:address":"Korte Loef 64",
    "sg:city":"Malden",
    "sg:orig_category":"Farmaceutische Producten Gh",
    "sg:phone":"+31 24 357 2129",
    "sg:postcode":"6581 JB",
    "sg:province":"Gelderland",
    "wof:name":"Advanced Dental Diagnostics Bv",
    "wof:placetype":"venue"
},
  "geometry": {"coordinates":[5.85398,51.775612],"type":"Point"}
}