{
  "type": "Feature",
  "properties": {
    "addr:full":"Akerdijk 144 Badhoevedorp Noord-Holland 1171 PV",
    "addr:housenumber":"144",
    "addr:postcode":"1171 pv",
    "addr:street":"Akerdijk",
    "iso:country":"NL",
    "sg:address":"Akerdijk 144",
    "sg:city":"Badhoevedorp",
    "sg:orig_category":"Meubelreparatie And -Restauratie",
    "sg:phone":"+31 20 659 2728",
    "sg:postcode":"1171 PV",
    "sg:province":"Noord-Holland",
    "wof:name":"J C H Van Dyk",
    "wof:placetype":"venue"
},
  "geometry": {"coordinates":[4.77462,52.348042],"type":"Point"}
}