{
  "type": "Feature",
  "properties": {
    "addr:full":"Buurtwg 20/20A Akersloot Noord-Holland 1921 CK",
    "addr:housenumber":"20 / 20a",
    "addr:postcode":"1921 ck",
    "addr:street":"Buurtwg",
    "iso:country":"NL",
    "sg:address":"Buurtwg 20/20A",
    "sg:city":"Akersloot",
    "sg:orig_category":"Scholen Voor Basisonderwijs",
    "sg:phone":"+31 251 313 761",
    "sg:postcode":"1921 CK",
    "sg:province":"Noord-Holland",
    "wof:name":"Johannessch",
    "wof:placetype":"venue"
},
  "geometry": {"coordinates":[4.7311458588,52.5638542175],"type":"Point"}
}