{
  "type": "Feature",
  "properties": {
    "addr:full":"Rykswg Z 23 Sittard Limburg 6131 AK",
    "addr:housenumber":"23",
    "addr:postcode":"6131 ak",
    "addr:street":"Sittard Limburg",
    "iso:country":"NL",
    "sg:address":"Rykswg Z 23",
    "sg:city":"Sittard",
    "sg:classifiers":[
        {
            "category":"Travel",
            "subcategory":"Hotels & Motels",
            "type":"Entertainment"
        }
    ],
    "sg:phone":"+31 46 451 3673",
    "sg:postcode":"6131 AK",
    "sg:province":"Limburg",
    "wof:name":"Oranje",
    "wof:placetype":"venue"
},
  "geometry": {"coordinates":[5.862688,50.998627],"type":"Point"}
}