{
  "type": "Feature",
  "properties": {
    "addr:full":"Fresiastr 20 Katwijk Zuid-Holland 2223 XA",
    "addr:housenumber":"20",
    "addr:postcode":"2223 xa",
    "addr:street":"Fresiastr",
    "iso:country":"NL",
    "sg:address":"Fresiastr 20",
    "sg:city":"Katwijk",
    "sg:orig_category":"Bibliotheken En Leeszalen Openbare",
    "sg:phone":"+31 71 407 5490",
    "sg:postcode":"2223 XA",
    "sg:province":"Zuid-Holland",
    "wof:name":"Openb Bibliotheek",
    "wof:placetype":"venue"
},
  "geometry": {"coordinates":[4.422709,52.186626],"type":"Point"}
}