{
  "type": "Feature",
  "properties": {
    "iso:country":"NL",
    "sg:address":"Varkensmarkt 11",
    "sg:city":"Amersfoort",
    "sg:classifiers":[
        {
            "category":"Shopping",
            "subcategory":"Clothing, Apparel, & Fashions",
            "type":"Retail Goods"
        }
    ],
    "sg:phone":"+31 33 461 2742",
    "sg:postcode":"3811 LD",
    "sg:province":"Utrecht",
    "sg:tags":[
        "ondergoed",
        "lingerie"
    ],
    "wof:name":"Livera",
    "wof:placetype":"venue"
},
  "geometry": {"coordinates":[5.387686,52.15395],"type":"Point"}
}