{
  "type": "Feature",
  "properties": {
    "iso:country":"NL",
    "sg:address":"Marnixstr 317",
    "sg:city":"Amsterdam",
    "sg:orig_category":"Verenigingen En Stichtingen",
    "sg:phone":"+31 20 512 6573",
    "sg:postcode":"1016 TB",
    "sg:province":"North Holland",
    "wof:name":"Srm Bv",
    "wof:placetype":"venue"
},
  "geometry": {"coordinates":[4.876358,52.373482],"type":"Point"}
}