{
  "type": "Feature",
  "properties": {
    "iso:country":"NL",
    "sg:address":"Rooswykwg 220",
    "sg:city":"Velsen Noord",
    "sg:orig_category":"Pompinstallaties En -Onderhoud",
    "sg:phone":"+31 251 268 050",
    "sg:postcode":"1951 MD",
    "sg:province":"Noord-Holland",
    "wof:name":"Nedelandse Pomp Service Bv",
    "wof:placetype":"venue"
},
  "geometry": {"coordinates":[4.645905,52.472397],"type":"Point"}
}