{
  "type": "Feature",
  "properties": {
    "addr:full":"Spakenburgstraat 42 Amsterdam Zuidoost Noord-Holland 1107 WS",
    "addr:housenumber":"42",
    "addr:postcode":"zuidoost;1107 ws",
    "addr:street":"Spakenburgstraat",
    "iso:country":"NL",
    "sg:address":"Spakenburgstraat 42",
    "sg:city":"Amsterdam Zuidoost",
    "sg:orig_category":"Bedrijfs- And Managementsconsultants",
    "sg:phone":"+31 20 696 9370",
    "sg:postcode":"1107 WS",
    "sg:province":"Noord-Holland",
    "wof:name":"Ter Burg Business Support",
    "wof:placetype":"venue"
},
  "geometry": {"coordinates":[4.978407,52.291496],"type":"Point"}
}