{
  "type": "Feature",
  "properties": {
    "addr:full":"Keizersgr 425 Amsterdam Noord-Holland 1017 DJ",
    "addr:housenumber":"425",
    "addr:postcode":"1017 dj",
    "iso:country":"NL",
    "sg:address":"Keizersgr 425",
    "sg:city":"Amsterdam",
    "sg:orig_category":"Adviesbureaus Financieringen",
    "sg:phone":"+31 20 623 1332",
    "sg:postcode":"1017 DJ",
    "sg:province":"Noord-Holland",
    "wof:name":"Beril Bv",
    "wof:placetype":"venue"
},
  "geometry": {"coordinates":[4.885657,52.366825],"type":"Point"}
}