{
  "type": "Feature",
  "properties": {
    "iso:country":"NL",
    "sg:address":"Hoofd 19",
    "sg:city":"Zuidland",
    "sg:orig_category":"Fitnesscentra",
    "sg:phone":"+31 181 452 522",
    "sg:postcode":"3214 AH",
    "sg:province":"Zuid-Holland",
    "wof:name":"Wims Gym",
    "wof:placetype":"venue"
},
  "geometry": {"coordinates":[4.262423,51.823341],"type":"Point"}
}