{
  "type": "Feature",
  "properties": {
    "addr:full":"Kerkplein 18 Landgraaf Limburg 6372 EZ",
    "addr:housenumber":"18",
    "addr:postcode":"6372 ez",
    "addr:street":"Kerkplein",
    "iso:country":"NL",
    "sg:address":"Kerkplein 18",
    "sg:city":"Landgraaf",
    "sg:orig_category":"Verzekeringen",
    "sg:phone":"+31 45 531 9655",
    "sg:postcode":"6372 EZ",
    "sg:province":"Limburg",
    "wof:name":"Kleijkers Adviesgroep Bv",
    "wof:placetype":"venue"
},
  "geometry": {"coordinates":[6.014598,50.89423],"type":"Point"}
}