{
  "type": "Feature",
  "properties": {
    "addr:full":"Merelln 38 Capelle Ad Yssel South Holland 2902 JG",
    "addr:housenumber":"38",
    "addr:postcode":"2902 jg",
    "addr:street":"Merelln;Yssel",
    "iso:country":"NL",
    "sg:address":"Merelln 38",
    "sg:city":"Capelle Ad Yssel",
    "sg:orig_category":"Psychotherapeuten",
    "sg:phone":"+31 10 458 8277",
    "sg:postcode":"2902 JG",
    "sg:province":"South Holland",
    "wof:name":"Conjunctio Eveline Den Boef",
    "wof:placetype":"venue"
},
  "geometry": {"coordinates":[4.57697,51.926311],"type":"Point"}
}