{
  "type": "Feature",
  "properties": {
    "addr:full":"Tjalk 49 Hoorn Nh North Holland 1625 EC",
    "addr:housenumber":"49",
    "addr:postcode":"1625 ec",
    "addr:street":"Tjalk;Nh North",
    "iso:country":"NL",
    "sg:address":"Tjalk 49",
    "sg:city":"Hoorn Nh",
    "sg:orig_category":"Verhuur Audiovisuele Apparatuur",
    "sg:phone":"+31 229 248 126",
    "sg:postcode":"1625 EC",
    "sg:province":"North Holland",
    "wof:name":"Jan Schoen A/V Produkties",
    "wof:placetype":"venue"
},
  "geometry": {"coordinates":[5.05946,52.661572],"type":"Point"}
}