{
  "type": "Feature",
  "properties": {
    "addr:full":"Toekomstwg 15 Gaanderen Gelderland 7011 ET",
    "addr:housenumber":"15",
    "addr:postcode":"7011 et",
    "addr:street":"Toekomstwg;Gelderland",
    "iso:country":"NL",
    "sg:address":"Toekomstwg 15",
    "sg:city":"Gaanderen",
    "sg:orig_category":"Metaalbewerking",
    "sg:phone":"+31 315 324 357",
    "sg:postcode":"7011 ET",
    "sg:province":"Gelderland",
    "wof:name":"Forga-Hollander",
    "wof:placetype":"venue"
},
  "geometry": {"coordinates":[6.336158,51.926846],"type":"Point"}
}