{
  "type": "Feature",
  "properties": {
    "addr:full":"Rijnstraat 73 Amsterdam North Holland 1079 GX",
    "addr:housenumber":"73",
    "addr:postcode":"1079 gx",
    "addr:street":"Rijnstraat",
    "iso:country":"NL",
    "sg:address":"Rijnstraat 73",
    "sg:city":"Amsterdam",
    "sg:orig_category":"Wasserettes And Stomerijen",
    "sg:phone":"+31 20 644 9069",
    "sg:postcode":"1079 GX",
    "sg:province":"North Holland",
    "wof:name":"Pamba Textielreiniging Bv",
    "wof:placetype":"venue"
},
  "geometry": {"coordinates":[4.9056382179,52.3458061218],"type":"Point"}
}