{
  "type": "Feature",
  "properties": {
    "addr:full":"Rietstr 143 Almelo Overijssel 7601 XC",
    "addr:housenumber":"143",
    "addr:postcode":"7601 xc",
    "iso:country":"NL",
    "sg:address":"Rietstr 143",
    "sg:city":"Almelo",
    "sg:orig_category":"Bloemen En Planten",
    "sg:phone":"+31 546 819 805",
    "sg:postcode":"7601 XC",
    "sg:province":"Overijssel",
    "wof:name":"Riet, De",
    "wof:placetype":"venue"
},
  "geometry": {"coordinates":[6.664543,52.354954],"type":"Point"}
}