{
  "type": "Feature",
  "properties": {
    "addr:full":"Berkheide 11 Rotterdam Zuid-Holland 3069 KS",
    "addr:housenumber":"11",
    "addr:postcode":"3069 ks",
    "addr:street":"Berkheide",
    "iso:country":"NL",
    "sg:address":"Berkheide 11",
    "sg:city":"Rotterdam",
    "sg:orig_category":"Webdesign Bureaus",
    "sg:phone":"+31 10 251 8885",
    "sg:postcode":"3069 KS",
    "sg:province":"Zuid-Holland",
    "wof:name":"Enin Bv",
    "wof:placetype":"venue"
},
  "geometry": {"coordinates":[4.5481281281,51.9693412781],"type":"Point"}
}