{
  "type": "Feature",
  "properties": {
    "iso:country":"NL",
    "sg:address":"Euregiowg 225",
    "sg:city":"Enschede",
    "sg:orig_category":"Behangselpapier En Wandbekleding - Fabr. En Grooth",
    "sg:phone":"+31 53 460 1010",
    "sg:postcode":"7532 SM",
    "sg:province":"NL.08",
    "wof:name":"E&S Home Of Color",
    "wof:placetype":"venue"
},
  "geometry": {"coordinates":[6.944365,52.225216],"type":"Point"}
}