{
  "type": "Feature",
  "properties": {
    "addr:full":"Plesmanstr 1 Veenendaal Utrecht 3905 KZ",
    "addr:housenumber":"1",
    "addr:postcode":"3905",
    "addr:street":"Plesmanstr",
    "iso:country":"NL",
    "sg:address":"Plesmanstr 1",
    "sg:city":"Veenendaal",
    "sg:orig_category":"Administratie- En Boekhoudkantoren",
    "sg:phone":"+31 318 505 581",
    "sg:postcode":"3905 KZ",
    "sg:province":"Utrecht",
    "wof:name":"Adfimo",
    "wof:placetype":"venue"
},
  "geometry": {"coordinates":[5.557393,52.038872],"type":"Point"}
}