{
  "type": "Feature",
  "properties": {
    "addr:full":"Zaagbekstraat 1 'S Gravenhage South Holland 2492 NT",
    "addr:housenumber":"1 '",
    "addr:postcode":"2492 nt",
    "addr:street":"Zaagbekstraat",
    "iso:country":"NL",
    "sg:address":"Zaagbekstraat 1",
    "sg:city":"'S Gravenhage",
    "sg:orig_category":"Kinderopvang",
    "sg:phone":"+31 70 444 4215",
    "sg:postcode":"2492 NT",
    "sg:province":"South Holland",
    "wof:name":"Crescendo",
    "wof:placetype":"venue"
},
  "geometry": {"coordinates":[4.412165,52.066391],"type":"Point"}
}