{
  "type": "Feature",
  "properties": {
    "iso:country":"NL",
    "sg:address":"A V Scharnln D 1D",
    "sg:city":"Maastricht",
    "sg:classifiers":[
        {
            "category":"Food & Beverages",
            "subcategory":"Bakery",
            "type":"Retail Goods"
        }
    ],
    "sg:phone":"+31 43 363 2222",
    "sg:postcode":"6226 EG",
    "sg:province":"Limburg",
    "sg:tags":[
        "pizza"
    ],
    "wof:name":"Da Roberto",
    "wof:placetype":"venue"
},
  "geometry": {"coordinates":[5.73651,50.848919],"type":"Point"}
}