{
  "type": "Feature",
  "properties": {
    "addr:full":"Feithspark 1 Tolbert Groningen 9356 BX",
    "addr:housenumber":"1",
    "addr:postcode":"9356 bx",
    "addr:street":"Feithspark",
    "iso:country":"NL",
    "sg:address":"Feithspark 1",
    "sg:city":"Tolbert",
    "sg:orig_category":"Fotostudio'S And Fotografen",
    "sg:phone":"+31 594 516 888",
    "sg:postcode":"9356 BX",
    "sg:province":"Groningen",
    "wof:name":"Fotografie Roelof Feringa",
    "wof:placetype":"venue"
},
  "geometry": {"coordinates":[-99.414536,34.226662],"type":"Point"}
}