{
  "type": "Feature",
  "properties": {
    "iso:country":"NL",
    "sg:address":"Kleine Poellaan 12",
    "sg:city":"Rijsenhout",
    "sg:orig_category":"Boekhouders",
    "sg:phone":"+31 297 327 167",
    "sg:postcode":"1435 GP",
    "sg:province":"Noord-Holland",
    "wof:name":"Demmendaal Assurantie",
    "wof:placetype":"venue"
},
  "geometry": {"coordinates":[4.704571,52.255657],"type":"Point"}
}