{
  "type": "Feature",
  "properties": {
    "addr:full":"Kastanjeln 72-74 Bergen Op Zoom North Brabant 4621 HH",
    "addr:housenumber":"72-74",
    "addr:postcode":"4621 hh",
    "iso:country":"NL",
    "sg:address":"Kastanjeln 72-74",
    "sg:city":"Bergen Op Zoom",
    "sg:orig_category":"Cafetaria'S",
    "sg:phone":"+31 164 245 251",
    "sg:postcode":"4621 HH",
    "sg:province":"North Brabant",
    "wof:name":"Vijfde, 'T",
    "wof:placetype":"venue"
},
  "geometry": {"coordinates":[4.298699,51.492119],"type":"Point"}
}