{
  "type": "Feature",
  "properties": {
    "addr:full":"Oosterhamrikkade 6 Groningen Groningen 9714 BB",
    "addr:housenumber":"6",
    "addr:postcode":"9714 bb",
    "addr:street":"Oosterhamrikkade",
    "iso:country":"NL",
    "sg:address":"Oosterhamrikkade 6",
    "sg:city":"Groningen",
    "sg:orig_category":"Autokeuringen",
    "sg:phone":"+31 50 573 0144",
    "sg:postcode":"9714 BB",
    "sg:province":"Groningen",
    "wof:name":"J Kiezebrink",
    "wof:placetype":"venue"
},
  "geometry": {"coordinates":[6.568868,53.22681],"type":"Point"}
}