{
  "type": "Feature",
  "properties": {
    "addr:full":"Carl Muckstraat 40 Hengelo Ov Overijssel 7558 ER",
    "addr:housenumber":"40",
    "addr:postcode":"7558 er",
    "addr:street":"Carl Muckstraat;Ov",
    "iso:country":"NL",
    "sg:address":"Carl Muckstraat 40",
    "sg:city":"Hengelo Ov",
    "sg:orig_category":"Koeriersdiensten",
    "sg:phone":"+31 74 277 7072",
    "sg:postcode":"7558 ER",
    "sg:province":"Overijssel",
    "wof:name":"Schildkamp",
    "wof:placetype":"venue"
},
  "geometry": {"coordinates":[6.830923,52.283752],"type":"Point"}
}