{
  "type": "Feature",
  "properties": {
    "addr:full":"V Swinderenstr 7 Balk Friesland 8561 AP",
    "addr:housenumber":"7",
    "addr:postcode":"8561 ap",
    "addr:street":"Swinderenstr",
    "iso:country":"NL",
    "sg:address":"V Swinderenstr 7",
    "sg:city":"Balk",
    "sg:orig_category":"Antiquiteiten - Restauratie",
    "sg:phone":"+31 514 605 554",
    "sg:postcode":"8561 AP",
    "sg:province":"Friesland",
    "sg:website":"http://www.vriesart.nl",
    "wof:name":"Vriesart",
    "wof:placetype":"venue"
},
  "geometry": {"coordinates":[-100.82858299999999,36.608829],"type":"Point"}
}