{
  "type": "Feature",
  "properties": {
    "iso:country":"NL",
    "sg:address":"J V Bergenstr 21",
    "sg:city":"Heemskerk",
    "sg:orig_category":"Verzekeringen - Verzekeringskantoren",
    "sg:phone":"+31 251 201 527",
    "sg:postcode":"1962 VH",
    "sg:province":"North Holland",
    "wof:name":"Janssen Assurantien",
    "wof:placetype":"venue"
},
  "geometry": {"coordinates":[4.66983,52.513546],"type":"Point"}
}