{
  "type": "Feature",
  "properties": {
    "iso:country":"NL",
    "sg:address":"Bosln 2C",
    "sg:city":"Hoofddorp",
    "sg:orig_category":"Adviesbureaus Bedrijfsorganisatie",
    "sg:phone":"+31 23 567 0066",
    "sg:postcode":"2132 DX",
    "sg:province":"Noord-Holland",
    "sg:website":"http://www.manconsultants.nl",
    "wof:name":"Man Consultants",
    "wof:placetype":"venue"
},
  "geometry": {"coordinates":[4.69296,52.305393],"type":"Point"}
}