{
  "type": "Feature",
  "properties": {
    "iso:country":"NL",
    "sg:address":"K Doormanstr 1",
    "sg:city":"Oud Beyerland",
    "sg:orig_category":"Hypotheken",
    "sg:phone":"+31 186 618 777",
    "sg:postcode":"3262 PB",
    "sg:province":"Zuid-Holland",
    "sg:website":"http://www.geldxpert.nl",
    "wof:name":"Geldxpert",
    "wof:placetype":"venue"
},
  "geometry": {"coordinates":[4.41701,51.823044],"type":"Point"}
}