{
  "type": "Feature",
  "properties": {
    "addr:full":"Raadhuisstr 75 Heemstede Noord-Holland 2101 HD",
    "addr:housenumber":"75",
    "addr:postcode":"2101 hd",
    "addr:street":"Raadhuisstr",
    "iso:country":"NL",
    "sg:address":"Raadhuisstr 75",
    "sg:city":"Heemstede",
    "sg:orig_category":"Verlichting",
    "sg:phone":"+31 23 528 3333",
    "sg:postcode":"2101 HD",
    "sg:province":"Noord-Holland",
    "wof:name":"Lampe D'Or Verlichtingspeciaalzaak",
    "wof:placetype":"venue"
},
  "geometry": {"coordinates":[4.620706,52.348915],"type":"Point"}
}