{
  "type": "Feature",
  "properties": {
    "addr:full":"St. Annastraat 53 Nijmegen Gelderland 6524 EG",
    "addr:housenumber":"53",
    "addr:postcode":"6524 eg",
    "addr:street":"St. Annastraat;Gelderland",
    "iso:country":"NL",
    "sg:address":"St. Annastraat 53",
    "sg:city":"Nijmegen",
    "sg:classifiers":[
        {
            "category":"Fast Food",
            "type":"Food & Drink"
        }
    ],
    "sg:phone":"+31 24 323 1957",
    "sg:postcode":"6524 EG",
    "sg:province":"Gelderland",
    "sg:tags":[
        "afhaal",
        "restaurant"
    ],
    "wof:name":"Chinees Afhaalrestaurant Iwan",
    "wof:placetype":"venue"
},
  "geometry": {"coordinates":[5.8603978157,51.8384552002],"type":"Point"}
}