{
  "type": "Feature",
  "properties": {
    "addr:full":"Moleneind 55 Kortenhoef Noord-Holland 1241 NJ",
    "addr:housenumber":"55",
    "addr:postcode":"1241 nj",
    "addr:street":"Moleneind",
    "iso:country":"NL",
    "sg:address":"Moleneind 55",
    "sg:city":"Kortenhoef",
    "sg:orig_category":"Architecten",
    "sg:phone":"+31 35 656 0067",
    "sg:postcode":"1241 NJ",
    "sg:province":"Noord-Holland",
    "wof:name":"Adviesbureau Voor Cultuurhistorie Verwev",
    "wof:placetype":"venue"
},
  "geometry": {"coordinates":[5.075377,52.221046],"type":"Point"}
}