{
  "type": "Feature",
  "properties": {
    "addr:full":"Groningsestr 14 S Gravenhage Zuid-Holland 2587 RK",
    "addr:housenumber":"14;gravenhage",
    "addr:postcode":"2587 rk",
    "addr:street":"Groningsestr;S",
    "iso:country":"NL",
    "sg:address":"Groningsestr 14",
    "sg:city":"S Gravenhage",
    "sg:orig_category":"Bedrijfsopleidingen",
    "sg:phone":"+31 70 306 3895",
    "sg:postcode":"2587 RK",
    "sg:province":"Zuid-Holland",
    "wof:name":"Peptalk",
    "wof:placetype":"venue"
},
  "geometry": {"coordinates":[4.29118,52.112942],"type":"Point"}
}