{
  "type": "Feature",
  "properties": {
    "iso:country":"NL",
    "sg:address":"Weerdingerstraat 39",
    "sg:city":"Emmen",
    "sg:orig_category":"Gebouwenafwerking, Renovaties And Reiniging",
    "sg:phone":"+31 591 613 951",
    "sg:postcode":"7815 SC",
    "sg:province":"Provincie Drenthe",
    "wof:name":"Schuur Schilderwerken",
    "wof:placetype":"venue"
},
  "geometry": {"coordinates":[6.895484,52.790298],"type":"Point"}
}