{
  "type": "Feature",
  "properties": {
    "addr:full":"C W Lubbersstraat 33 Wildervank Groningen 9648 LA",
    "addr:housenumber":"33",
    "addr:postcode":"9648 la",
    "addr:street":"C W Lubbersstraat",
    "iso:country":"NL",
    "sg:address":"C W Lubbersstraat 33",
    "sg:city":"Wildervank",
    "sg:orig_category":"Begrafenisondernemers",
    "sg:phone":"+31 598 621 084",
    "sg:postcode":"9648 LA",
    "sg:province":"Groningen",
    "wof:name":"Onderlinge Uitvaartvereniging Wildervank Wa",
    "wof:placetype":"venue"
},
  "geometry": {"coordinates":[6.869638,53.084583],"type":"Point"}
}