{
  "type": "Feature",
  "properties": {
    "addr:full":"Hosingenhof 53 Eindhoven North Brabant 5625 NK",
    "addr:housenumber":"53",
    "addr:postcode":"5625 nk",
    "addr:street":"Hosingenhof",
    "iso:country":"NL",
    "sg:address":"Hosingenhof 53",
    "sg:city":"Eindhoven",
    "sg:orig_category":"Verenigingen En Stichtingen",
    "sg:phone":"+31 40 241 3739",
    "sg:postcode":"5625 NK",
    "sg:province":"North Brabant",
    "wof:name":"Anthroposofische Vereniging",
    "wof:placetype":"venue"
},
  "geometry": {"coordinates":[5.475825,51.474369],"type":"Point"}
}