{
  "type": "Feature",
  "properties": {
    "addr:full":"Sloterkd 20 Amsterdam North Holland 1058 HE",
    "addr:housenumber":"20",
    "addr:postcode":"1058 he",
    "addr:street":"Sloterkd",
    "iso:country":"NL",
    "sg:address":"Sloterkd 20",
    "sg:city":"Amsterdam",
    "sg:orig_category":"Verenigingen En Stichtingen",
    "sg:phone":"+31 20 615 1122",
    "sg:postcode":"1058 HE",
    "sg:province":"North Holland",
    "wof:name":"Cuba Si",
    "wof:placetype":"venue"
},
  "geometry": {"coordinates":[4.85094,52.357658],"type":"Point"}
}