{
  "type": "Feature",
  "properties": {
    "addr:full":"Deurningerstr 368 Enschede NL.08 7522 CP",
    "addr:housenumber":"368",
    "addr:postcode":"7522 cp",
    "iso:country":"NL",
    "sg:address":"Deurningerstr 368",
    "sg:city":"Enschede",
    "sg:orig_category":"Verenigingen En Stichtingen",
    "sg:phone":"+31 53 431 5740",
    "sg:postcode":"7522 CP",
    "sg:province":"NL.08",
    "wof:name":"Democratische Jongeren, Sticht",
    "wof:placetype":"venue"
},
  "geometry": {"coordinates":[6.884853,52.237064],"type":"Point"}
}