{
  "type": "Feature",
  "properties": {
    "addr:full":"Dammerweg 66 Nederhorst Den Berg Noord-Holland 1394 GP",
    "addr:housenumber":"66",
    "addr:postcode":"1394 gp",
    "addr:street":"Dammerweg",
    "iso:country":"NL",
    "sg:address":"Dammerweg 66",
    "sg:city":"Nederhorst Den Berg",
    "sg:orig_category":"Bedrijfs- And Managementsconsultants",
    "sg:phone":"+31 294 254 679",
    "sg:postcode":"1394 GP",
    "sg:province":"Noord-Holland",
    "wof:name":"Second Line Services",
    "wof:placetype":"venue"
},
  "geometry": {"coordinates":[5.047109,52.270569],"type":"Point"}
}