{
  "type": "Feature",
  "properties": {
    "iso:country":"NL",
    "sg:address":"Grotestraat 110",
    "sg:city":"Borne Ov",
    "sg:orig_category":"Hypotheken And Hypotheekbanken",
    "sg:phone":"+31 74 267 0072",
    "sg:postcode":"7622 GP",
    "sg:province":"Overijssel",
    "wof:name":"Hypotheek Adviescentrum Borne",
    "wof:placetype":"venue"
},
  "geometry": {"coordinates":[6.760214,52.298359],"type":"Point"}
}