{
  "type": "Feature",
  "properties": {
    "addr:full":"Gank 63 Landgraaf Limburg 6374 NK",
    "addr:housenumber":"63",
    "addr:postcode":"6374 nk",
    "addr:street":"Gank",
    "iso:country":"NL",
    "sg:address":"Gank 63",
    "sg:city":"Landgraaf",
    "sg:orig_category":"Adviesbureaus",
    "sg:phone":"+31 45 531 3995",
    "sg:postcode":"6374 NK",
    "sg:province":"Limburg",
    "wof:name":"Erwee",
    "wof:placetype":"venue"
},
  "geometry": {"coordinates":[6.038447,50.918495],"type":"Point"}
}