{
  "type": "Feature",
  "properties": {
    "addr:full":"Tongerensewg 25 Vierhouten Gelderland 8076 PV",
    "addr:housenumber":"25",
    "addr:postcode":"8076 pv",
    "addr:street":"Tongerensewg;Gelderland",
    "iso:country":"NL",
    "sg:address":"Tongerensewg 25",
    "sg:city":"Vierhouten",
    "sg:orig_category":"Afslankinstituten",
    "sg:phone":"+31 577 411 420",
    "sg:postcode":"8076 PV",
    "sg:province":"Gelderland",
    "wof:name":"Compact Herbs Int",
    "wof:placetype":"venue"
},
  "geometry": {"coordinates":[5.834268,52.334206],"type":"Point"}
}