{
  "type": "Feature",
  "properties": {
    "addr:full":"Jagersln 5 Doorwerth Gelderland 6865 DB",
    "addr:housenumber":"5",
    "addr:postcode":"6865 db",
    "addr:street":"Jagersln;Gelderland",
    "iso:country":"NL",
    "sg:address":"Jagersln 5",
    "sg:city":"Doorwerth",
    "sg:orig_category":"Adviesbureaus Bouwkunde",
    "sg:phone":"+31 26 333 4350",
    "sg:postcode":"6865 DB",
    "sg:province":"Gelderland",
    "wof:name":"Zebeq Man Bv",
    "wof:placetype":"venue"
},
  "geometry": {"coordinates":[5.811587,51.974442],"type":"Point"}
}