{
  "type": "Feature",
  "properties": {
    "addr:full":"1E Daalsedk 240 Utrecht Utrecht 3513 TK",
    "addr:housenumber":"240",
    "addr:postcode":"3513 tk",
    "addr:street":"1E Daalsedk",
    "iso:country":"NL",
    "sg:address":"1E Daalsedk 240",
    "sg:city":"Utrecht",
    "sg:orig_category":"Adviesbureaus Elektrotechniek",
    "sg:phone":"+31 30 231 6211",
    "sg:postcode":"3513 TK",
    "sg:province":"Utrecht",
    "wof:name":"Desda",
    "wof:placetype":"venue"
},
  "geometry": {"coordinates":[5.106143,52.096348],"type":"Point"}
}