{
  "type": "Feature",
  "properties": {
    "addr:full":"Broekweg 5 Valkenburg Zh South Holland 2235 BG",
    "addr:housenumber":"5",
    "addr:postcode":"zh;2235",
    "addr:street":"Broekweg",
    "iso:country":"NL",
    "sg:address":"Broekweg 5",
    "sg:city":"Valkenburg Zh",
    "sg:orig_category":"Verlichting And Huishoudartikelen",
    "sg:phone":"+31 71 401 2608",
    "sg:postcode":"2235 BG",
    "sg:province":"South Holland",
    "wof:name":"M.H. Van Stijn En Zonen Vof",
    "wof:placetype":"venue"
},
  "geometry": {"coordinates":[4.433108,52.180122],"type":"Point"}
}