{
  "type": "Feature",
  "properties": {
    "addr:full":"Drechtdk 45 De Kwakel North Holland 1424 RB",
    "addr:housenumber":"45",
    "addr:postcode":"1424 rb",
    "addr:street":"Drechtdk",
    "iso:country":"NL",
    "sg:address":"Drechtdk 45",
    "sg:city":"De Kwakel",
    "sg:orig_category":"Bloemen En Planten",
    "sg:phone":"+31 297 561 578",
    "sg:postcode":"1424 RB",
    "sg:province":"North Holland",
    "sg:website":"http://www.themadecoraties.nl",
    "wof:name":"Lek Bloemenservice",
    "wof:placetype":"venue"
},
  "geometry": {"coordinates":[4.792514,52.23698],"type":"Point"}
}