{
  "type": "Feature",
  "properties": {
    "addr:full":"Refeling 66 Nuenen Noord-Brabant 5672 CK",
    "addr:housenumber":"66",
    "addr:postcode":"5672 ck",
    "addr:street":"Refeling",
    "iso:country":"NL",
    "sg:address":"Refeling 66",
    "sg:city":"Nuenen",
    "sg:orig_category":"Marktonderzoekbureaus",
    "sg:phone":"+31 40 283 8703",
    "sg:postcode":"5672 CK",
    "sg:province":"Noord-Brabant",
    "wof:name":"Jabarika Bv",
    "wof:placetype":"venue"
},
  "geometry": {"coordinates":[5.55282,51.466091],"type":"Point"}
}