{
  "type": "Feature",
  "properties": {
    "iso:country":"NL",
    "sg:address":"Brink 93",
    "sg:city":"Deventer",
    "sg:orig_category":"Huishoudapparatuur, Televisies And Radio'S",
    "sg:phone":"+31 570 611 515",
    "sg:postcode":"7411 BZ",
    "sg:province":"Overijssel",
    "wof:name":"Scheer & Foppen Bv",
    "wof:placetype":"venue"
},
  "geometry": {"coordinates":[6.159848,52.252995],"type":"Point"}
}