{
  "type": "Feature",
  "properties": {
    "addr:full":"Worth Rhedensewg 28A Rheden Gelderland 6991 DW",
    "addr:housenumber":"28a",
    "addr:postcode":"6991 dw",
    "addr:street":"Gelderland",
    "iso:country":"NL",
    "sg:address":"Worth Rhedensewg 28A",
    "sg:city":"Rheden",
    "sg:orig_category":"Verenigingen En Stichtingen",
    "sg:phone":"+31 26 495 2063",
    "sg:postcode":"6991 DW",
    "sg:province":"Gelderland",
    "wof:name":"Blokhut, Sticht De",
    "wof:placetype":"venue"
},
  "geometry": {"coordinates":[6.028257,52.0051],"type":"Point"}
}