{
  "type": "Feature",
  "properties": {
    "addr:full":"Kerklaan 13 Heemstede North Holland 2101 HK",
    "addr:housenumber":"13",
    "addr:postcode":"2101 hk",
    "addr:street":"Kerklaan",
    "iso:country":"NL",
    "sg:address":"Kerklaan 13",
    "sg:city":"Heemstede",
    "sg:orig_category":"Makelaars In Onroerend Goed",
    "sg:phone":"+31 23 528 1005",
    "sg:postcode":"2101 HK",
    "sg:province":"North Holland",
    "wof:name":"Makelaars- & Assurantiekantoor Mevr. J.G.M. Van De",
    "wof:placetype":"venue"
},
  "geometry": {"coordinates":[4.621248,52.345287],"type":"Point"}
}