{
  "type": "Feature",
  "properties": {
    "addr:full":"Lepelstraat 10 Sint Anthonis Noord-Brabant 5845 BJ",
    "addr:housenumber":"10",
    "addr:postcode":"anthonis;5845 bj",
    "addr:street":"Lepelstraat",
    "iso:country":"NL",
    "sg:address":"Lepelstraat 10",
    "sg:city":"Sint Anthonis",
    "sg:classifiers":[
        {
            "category":"Shopping",
            "subcategory":"Gifts & Souvenirs",
            "type":"Retail Goods"
        }
    ],
    "sg:phone":"+31 485 381 817",
    "sg:postcode":"5845 BJ",
    "sg:province":"Noord-Brabant",
    "sg:tags":[
        "geschenken"
    ],
    "wof:name":"Wereldwinkel",
    "wof:placetype":"venue"
},
  "geometry": {"coordinates":[5.882777,51.625824],"type":"Point"}
}