{
  "type": "Feature",
  "properties": {
    "addr:full":"Reiger 40 Sprang Capelle North Brabant 5161 TZ",
    "addr:housenumber":"40",
    "addr:postcode":"5161 tz",
    "addr:street":"Reiger",
    "iso:country":"NL",
    "sg:address":"Reiger 40",
    "sg:city":"Sprang Capelle",
    "sg:orig_category":"Adviesbureaus Marketing",
    "sg:phone":"+31 416 544 132",
    "sg:postcode":"5161 TZ",
    "sg:province":"North Brabant",
    "sg:website":"http://www.veriza.nl",
    "wof:name":"Veriza",
    "wof:placetype":"venue"
},
  "geometry": {"coordinates":[5.019617,51.67799],"type":"Point"}
}