{
  "type": "Feature",
  "properties": {
    "iso:country":"NL",
    "sg:address":"Beverhof 1",
    "sg:city":"Beverwyk",
    "sg:orig_category":"Boeken En Tijdschriften",
    "sg:phone":"+31 251 224 921",
    "sg:postcode":"1941 EC",
    "sg:province":"Noord-Holland",
    "wof:name":"Bruna",
    "wof:placetype":"venue"
},
  "geometry": {"coordinates":[4.660199,52.4818],"type":"Point"}
}