{
  "type": "Feature",
  "properties": {
    "addr:full":"Nijverheidstr 15 Enschede NL.08 7511 JM",
    "addr:housenumber":"15",
    "addr:postcode":"7511 jm",
    "addr:street":"Nijverheidstr",
    "iso:country":"NL",
    "sg:address":"Nijverheidstr 15",
    "sg:city":"Enschede",
    "sg:orig_category":"Adviesbureaus Warmtetechniek",
    "sg:phone":"+31 53 431 2709",
    "sg:postcode":"7511 JM",
    "sg:province":"NL.08",
    "wof:name":"Wiecherink Bv",
    "wof:placetype":"venue"
},
  "geometry": {"coordinates":[6.891563,52.219791],"type":"Point"}
}