{
  "type": "Feature",
  "properties": {
    "addr:full":"Nieuwe Ginnekenstraat 45 Breda Noord-Brabant 4811 NN",
    "addr:housenumber":"45",
    "addr:postcode":"4811 nn",
    "addr:street":"Nieuwe Ginnekenstraat",
    "iso:country":"NL",
    "sg:address":"Nieuwe Ginnekenstraat 45",
    "sg:city":"Breda",
    "sg:orig_category":"Werving And Selectie Van Tijdelijk Personeel And Uitzendkantoren",
    "sg:phone":"+31 76 522 3000",
    "sg:postcode":"4811 NN",
    "sg:province":"Noord-Brabant",
    "wof:name":"Starjob Secretaresse Uitzendbureau",
    "wof:placetype":"venue"
},
  "geometry": {"coordinates":[4.7776870728,51.581325531],"type":"Point"}
}