{
  "type": "Feature",
  "properties": {
    "addr:full":"Overcingeln 1 Havelte Drenthe 7971 RC",
    "addr:housenumber":"1",
    "addr:postcode":"7971 rc",
    "addr:street":"Overcingeln",
    "iso:country":"NL",
    "sg:address":"Overcingeln 1",
    "sg:city":"Havelte",
    "sg:orig_category":"Bloemen En Planten - Groothandel",
    "sg:phone":"+31 521 341 396",
    "sg:postcode":"7971 RC",
    "sg:province":"Drenthe",
    "wof:name":"Pijper, R",
    "wof:placetype":"venue"
},
  "geometry": {"coordinates":[6.228468,52.768101],"type":"Point"}
}