{
  "type": "Feature",
  "properties": {
    "addr:full":"Grotestr 409A Waalwyk North Brabant 5142 CB",
    "addr:housenumber":"409a",
    "addr:postcode":"5142 cb",
    "addr:street":"Waalwyk North",
    "iso:country":"NL",
    "sg:address":"Grotestr 409A",
    "sg:city":"Waalwyk",
    "sg:orig_category":"Omroep",
    "sg:phone":"+31 416 652 652",
    "sg:postcode":"5142 CB",
    "sg:province":"North Brabant",
    "sg:website":"http://www.maasstadmedia.nl",
    "wof:name":"Maasstad Radio",
    "wof:placetype":"venue"
},
  "geometry": {"coordinates":[5.078974,51.691555],"type":"Point"}
}