{
  "type": "Feature",
  "properties": {
    "addr:full":"Hessenwg 2 Stoutenburg Utrecht 3835 PJ",
    "addr:housenumber":"2",
    "addr:postcode":"3835 pj",
    "addr:street":"Hessenwg",
    "iso:country":"NL",
    "sg:address":"Hessenwg 2",
    "sg:city":"Stoutenburg",
    "sg:orig_category":"Kaas",
    "sg:phone":"+31 33 494 0305",
    "sg:postcode":"3835 PJ",
    "sg:province":"Utrecht",
    "wof:name":"Kopermolen, Kaasboerderij De",
    "wof:placetype":"venue"
},
  "geometry": {"coordinates":[5.4267778397,52.157623291],"type":"Point"}
}