{
  "type": "Feature",
  "properties": {
    "addr:full":"Zuidpln 616 Rotterdam South Holland 3083 CX",
    "addr:housenumber":"616",
    "addr:postcode":"3083 cx",
    "iso:country":"NL",
    "sg:address":"Zuidpln 616",
    "sg:city":"Rotterdam",
    "sg:orig_category":"Postkantoren",
    "sg:phone":"+31 10 410 2922",
    "sg:postcode":"3083 CX",
    "sg:province":"South Holland",
    "sg:website":"http://www.postkantoor.nl",
    "wof:name":"Postkantoor",
    "wof:placetype":"venue"
},
  "geometry": {"coordinates":[4.491792,51.888302],"type":"Point"}
}