{
  "type": "Feature",
  "properties": {
    "addr:full":"Meekertweg 8 Winterswijk Gelderland 7102 GE",
    "addr:housenumber":"8",
    "addr:postcode":"7102",
    "addr:street":"Meekertweg;Gelderland",
    "iso:country":"NL",
    "sg:address":"Meekertweg 8",
    "sg:city":"Winterswijk",
    "sg:orig_category":"Geluidsopnamen",
    "sg:phone":"+31 543 530 185",
    "sg:postcode":"7102 GE",
    "sg:province":"Gelderland",
    "wof:name":"Rednas Malv Prod",
    "wof:placetype":"venue"
},
  "geometry": {"coordinates":[6.675748,51.986324],"type":"Point"}
}