{
  "type": "Feature",
  "properties": {
    "iso:country":"NL",
    "sg:address":"Noorderkd 150",
    "sg:city":"Alkmaar",
    "sg:classifiers":[
        {
            "category":"Food & Beverages",
            "subcategory":"Fruits & Vegetables",
            "type":"Retail Goods"
        }
    ],
    "sg:phone":"+31 72 512 3764",
    "sg:postcode":"1823 CJ",
    "sg:province":"Noord-Holland",
    "sg:tags":[
        "en",
        "groenten"
    ],
    "wof:name":"Arcade Bv",
    "wof:placetype":"venue"
},
  "geometry": {"coordinates":[4.76043,52.638321],"type":"Point"}
}