{
  "type": "Feature",
  "properties": {
    "iso:country":"NL",
    "sg:address":"Olde Hof 1",
    "sg:city":"Garminge",
    "sg:orig_category":"Vertaalbureaus",
    "sg:phone":"+31 593 552 695",
    "sg:postcode":"9438 TE",
    "sg:province":"Drenthe",
    "wof:name":"Accuratext",
    "wof:placetype":"venue"
},
  "geometry": {"coordinates":[6.623123,52.817894],"type":"Point"}
}