{
  "type": "Feature",
  "properties": {
    "addr:full":"Mon Plaisir 19 Etten-Leur Noord-Brabant 4879 AK",
    "addr:housenumber":"19",
    "addr:postcode":"4879 ak",
    "addr:street":"Mon Plaisir",
    "iso:country":"NL",
    "sg:address":"Mon Plaisir 19",
    "sg:city":"Etten-Leur",
    "sg:orig_category":"Meubelzaken, Woning- And Keukeninrichting",
    "sg:phone":"+31 76 501 9710",
    "sg:postcode":"4879 AK",
    "sg:province":"Noord-Brabant",
    "wof:name":"J. Suijkerbuijk",
    "wof:placetype":"venue"
},
  "geometry": {"coordinates":[4.625326,51.562614],"type":"Point"}
}