{
  "type": "Feature",
  "properties": {
    "addr:full":"Kabbelaarsbank 11 Ouddorp Zh Zuid-Holland 3253 ME",
    "addr:housenumber":"11",
    "addr:postcode":"3253 me",
    "addr:street":"Kabbelaarsbank",
    "iso:country":"NL",
    "sg:address":"Kabbelaarsbank 11",
    "sg:city":"Ouddorp Zh",
    "sg:orig_category":"Jachthavens - Jachtwerven",
    "sg:phone":"+31 111 677 111",
    "sg:postcode":"3253 ME",
    "sg:province":"Zuid-Holland",
    "wof:name":"Brielle Yachting Bv",
    "wof:placetype":"venue"
},
  "geometry": {"coordinates":[3.855037,51.759087],"type":"Point"}
}