{
  "type": "Feature",
  "properties": {
    "addr:full":"Jeker 24 Tilburg Noord-Brabant 5032 AW",
    "addr:housenumber":"24",
    "addr:postcode":"5032 aw",
    "addr:street":"Jeker",
    "iso:country":"NL",
    "sg:address":"Jeker 24",
    "sg:city":"Tilburg",
    "sg:orig_category":"Architecten",
    "sg:phone":"+31 13 467 4937",
    "sg:postcode":"5032 AW",
    "sg:province":"Noord-Brabant",
    "wof:name":"Architectenbureau Jan Venmans",
    "wof:placetype":"venue"
},
  "geometry": {"coordinates":[5.043922,51.54554],"type":"Point"}
}