{
  "type": "Feature",
  "properties": {
    "addr:full":"Wiekenlaan 2 Uitgeest Noord-Holland 1911 XR",
    "addr:housenumber":"2",
    "addr:postcode":"1911 xr",
    "addr:street":"Wiekenlaan",
    "iso:country":"NL",
    "sg:address":"Wiekenlaan 2",
    "sg:city":"Uitgeest",
    "sg:classifiers":[
        {
            "category":"Education",
            "subcategory":"Preschool",
            "type":"Public Place"
        }
    ],
    "sg:phone":"+31 251 313 650",
    "sg:postcode":"1911 XR",
    "sg:province":"Noord-Holland",
    "sg:tags":[
        "kleuteronderwijs",
        "basis-"
    ],
    "wof:name":"Openbare Basisschool De Paltrok",
    "wof:placetype":"venue"
},
  "geometry": {"coordinates":[4.710334,52.531803],"type":"Point"}
}