{
  "type": "Feature",
  "properties": {
    "addr:full":"Corlesewg 11 Winterswyk Corle Gelderland 7119 AA",
    "addr:housenumber":"11",
    "addr:postcode":"7119 aa",
    "addr:street":"Corlesewg;Corle Gelderland",
    "iso:country":"NL",
    "sg:address":"Corlesewg 11",
    "sg:city":"Winterswyk Corle",
    "sg:orig_category":"Voegwerken",
    "sg:phone":"+31 543 532 541",
    "sg:postcode":"7119 AA",
    "sg:province":"Gelderland",
    "wof:name":"Winterswijk",
    "wof:placetype":"venue"
},
  "geometry": {"coordinates":[6.658821,51.968658],"type":"Point"}
}