{
  "type": "Feature",
  "properties": {
    "addr:full":"Onderdoor 62 Houten Utrecht 3995  D",
    "addr:housenumber":"62;3995 d",
    "addr:street":"Onderdoor",
    "iso:country":"NL",
    "sg:address":"Onderdoor 62",
    "sg:city":"Houten",
    "sg:orig_category":"Boekenuitgeverijen",
    "sg:phone":"+31 30 634 2239",
    "sg:postcode":"3995  D",
    "sg:province":"Utrecht",
    "wof:name":"Bruna",
    "wof:placetype":"venue"
},
  "geometry": {"coordinates":[5.168418,52.034439],"type":"Point"}
}