{
  "type": "Feature",
  "properties": {
    "addr:full":"L Giessen 33A Hoornaar Zuid-Holland 4223 SH",
    "addr:housenumber":"33a",
    "addr:postcode":"4223 sh",
    "addr:street":"L Giessen",
    "iso:country":"NL",
    "sg:address":"L Giessen 33A",
    "sg:city":"Hoornaar",
    "sg:orig_category":"Oldtimers",
    "sg:phone":"+31 184 651 481",
    "sg:postcode":"4223 SH",
    "sg:province":"Zuid-Holland",
    "wof:name":"Duijzer, A W",
    "wof:placetype":"venue"
},
  "geometry": {"coordinates":[4.944933,51.875271],"type":"Point"}
}