{
  "type": "Feature",
  "properties": {
    "addr:full":"Bemmelenberg 12 Bergen Op Zoom Noord-Brabant 4614 PG",
    "addr:housenumber":"12",
    "addr:postcode":"4614 pg",
    "addr:street":"Bemmelenberg",
    "iso:country":"NL",
    "sg:address":"Bemmelenberg 12",
    "sg:city":"Bergen Op Zoom",
    "sg:orig_category":"Kampeerterreinen",
    "sg:phone":"+31 164 235 659",
    "sg:postcode":"4614 PG",
    "sg:province":"Noord-Brabant",
    "wof:name":"Camping De Heide",
    "wof:placetype":"venue"
},
  "geometry": {"coordinates":[4.3172369003,51.5108337402],"type":"Point"}
}