{
  "type": "Feature",
  "properties": {
    "addr:full":"Keerberg 94 Voerendaal Limburg 6367 EL",
    "addr:housenumber":"94",
    "addr:postcode":"6367 el",
    "addr:street":"Keerberg",
    "iso:country":"NL",
    "sg:address":"Keerberg 94",
    "sg:city":"Voerendaal",
    "sg:orig_category":"Autoreclame",
    "sg:phone":"+31 45 575 3036",
    "sg:postcode":"6367 EL",
    "sg:province":"Limburg",
    "wof:name":"Bpu",
    "wof:placetype":"venue"
},
  "geometry": {"coordinates":[5.930168,50.877861],"type":"Point"}
}