{
  "type": "Feature",
  "properties": {
    "addr:full":"Kerkpln 3 Driebergen Rysenb Utrecht 3972 EK",
    "addr:housenumber":"3",
    "addr:postcode":"3972 ek",
    "addr:street":"Kerkpln;Rysenb",
    "iso:country":"NL",
    "sg:address":"Kerkpln 3",
    "sg:city":"Driebergen Rysenb",
    "sg:orig_category":"Herenkleding",
    "sg:phone":"+31 343 521 931",
    "sg:postcode":"3972 EK",
    "sg:province":"Utrecht",
    "sg:website":"http://www.edgar-n.nl",
    "wof:name":"Edgar N",
    "wof:placetype":"venue"
},
  "geometry": {"coordinates":[5.275983,52.055408],"type":"Point"}
}