{
  "type": "Feature",
  "properties": {
    "addr:full":"Kerkstraat 11 Vught Noord-Brabant 5261 CP",
    "addr:housenumber":"11",
    "addr:postcode":"5261 cp",
    "addr:street":"Kerkstraat",
    "iso:country":"NL",
    "sg:address":"Kerkstraat 11",
    "sg:city":"Vught",
    "sg:classifiers":[
        {
            "category":"Retail",
            "subcategory":"Photofinishing",
            "type":"Services"
        }
    ],
    "sg:phone":"+31 73 656 4270",
    "sg:postcode":"5261 CP",
    "sg:province":"Noord-Brabant",
    "sg:tags":[
        "foto",
        "film"
    ],
    "wof:name":"Ortho-Foto",
    "wof:placetype":"venue"
},
  "geometry": {"coordinates":[5.297663,51.660519],"type":"Point"}
}