{
  "type": "Feature",
  "properties": {
    "iso:country":"NL",
    "sg:address":"Julianastr 41",
    "sg:city":"Kerkdriel",
    "sg:orig_category":"Schilders",
    "sg:phone":"+31 418 634 878",
    "sg:postcode":"5331 BH",
    "sg:province":"Gelderland",
    "wof:name":"Ackermans",
    "wof:placetype":"venue"
},
  "geometry": {"coordinates":[5.334794,51.774982],"type":"Point"}
}