{
  "type": "Feature",
  "properties": {
    "addr:full":"S Gravenwg 805 Rotterdam South Holland 3065 SC",
    "addr:housenumber":"805",
    "addr:postcode":"3065 sc",
    "iso:country":"NL",
    "sg:address":"S Gravenwg 805",
    "sg:city":"Rotterdam",
    "sg:orig_category":"Adviesbureaus Bouwkunde",
    "sg:phone":"+31 10 202 2810",
    "sg:postcode":"3065 SC",
    "sg:province":"South Holland",
    "wof:name":"Delft Bv, A Van",
    "wof:placetype":"venue"
},
  "geometry": {"coordinates":[4.564335,51.92495],"type":"Point"}
}