{
  "type": "Feature",
  "properties": {
    "addr:full":"Gasthuislaan 78 Steenwijk NL.08 8331 MZ",
    "addr:housenumber":"78;nl.08",
    "addr:postcode":"8331 mz",
    "addr:street":"Gasthuislaan",
    "iso:country":"NL",
    "sg:address":"Gasthuislaan 78",
    "sg:city":"Steenwijk",
    "sg:classifiers":[
        {
            "category":"Professional",
            "subcategory":"Accounting & Tax Preparation",
            "type":"Services"
        }
    ],
    "sg:phone":"+31 521 510 260",
    "sg:postcode":"8331 MZ",
    "sg:province":"NL.08",
    "sg:tags":[
        "accountant"
    ],
    "wof:name":"Zwolse Accountants Maatschap",
    "wof:placetype":"venue"
},
  "geometry": {"coordinates":[6.111042,52.781612],"type":"Point"}
}