{
  "type": "Feature",
  "properties": {
    "iso:country":"NL",
    "sg:address":"Ln V Keulen 63",
    "sg:city":"Alkmaar",
    "sg:orig_category":"Administratie- En Boekhoudkantoren",
    "sg:phone":"+31 72 562 9210",
    "sg:postcode":"1827 KS",
    "sg:province":"Noord-Holland",
    "wof:name":"Beemsterboer, E",
    "wof:placetype":"venue"
},
  "geometry": {"coordinates":[4.76605,52.671101],"type":"Point"}
}