{
  "type": "Feature",
  "properties": {
    "addr:full":"Ln V Keulen 63 Alkmaar Noord-Holland 1827 KS",
    "addr:housenumber":"63",
    "addr:postcode":"1827 ks",
    "addr:street":"Ln V Keulen",
    "iso:country":"NL",
    "sg:address":"Ln V Keulen 63",
    "sg:city":"Alkmaar",
    "sg:orig_category":"Administratie- En Boekhoudkantoren",
    "sg:phone":"+31 72 562 9210",
    "sg:postcode":"1827 KS",
    "sg:province":"Noord-Holland",
    "wof:name":"Beemsterboer, E",
    "wof:placetype":"venue"
},
  "geometry": {"coordinates":[4.76605,52.671101],"type":"Point"}
}