{
  "type": "Feature",
  "properties": {
    "addr:full":"Mazerhard 37 Zeewolde Flevoland 3891 BR",
    "addr:housenumber":"37",
    "addr:postcode":"3891 br",
    "addr:street":"Mazerhard;Flevoland",
    "iso:country":"NL",
    "sg:address":"Mazerhard 37",
    "sg:city":"Zeewolde",
    "sg:orig_category":"Haptotherapeuten",
    "sg:phone":"+31 36 522 7034",
    "sg:postcode":"3891 BR",
    "sg:province":"Flevoland",
    "wof:name":"Paramedische Praktijk",
    "wof:placetype":"venue"
},
  "geometry": {"coordinates":[5.538724,52.333904],"type":"Point"}
}