{
  "type": "Feature",
  "properties": {
    "iso:country":"NL",
    "sg:address":"Puttelaar 37",
    "sg:city":"Zeeland",
    "sg:orig_category":"Overheidsdiensten",
    "sg:phone":"+31 486 451 921",
    "sg:postcode":"5411 AA",
    "sg:province":"Noord-Brabant",
    "wof:name":"Vlashoeve",
    "wof:placetype":"venue"
},
  "geometry": {"coordinates":[5.6799201965,51.6949005127],"type":"Point"}
}