{
  "type": "Feature",
  "properties": {
    "addr:full":"Postbus 164 Apeldoorn Gelderland 7300 AD",
    "addr:housenumber":"164",
    "addr:postcode":"7300 ad",
    "addr:street":"Postbus;Gelderland",
    "iso:country":"NL",
    "sg:address":"Postbus 164",
    "sg:city":"Apeldoorn",
    "sg:orig_category":"Wasserettes, Stomerijen And Reiniging",
    "sg:phone":"+31 55 543 0666",
    "sg:postcode":"7300 AD",
    "sg:province":"Gelderland",
    "wof:name":"Chemdry",
    "wof:placetype":"venue"
},
  "geometry": {"coordinates":[5.962460041,52.2143287659],"type":"Point"}
}