{
  "type": "Feature",
  "properties": {
    "addr:full":"Meerstraat 5 Emmen Drenthe 7815 XA",
    "addr:housenumber":"5",
    "addr:postcode":"7815 xa",
    "addr:street":"Meerstraat",
    "iso:country":"NL",
    "sg:address":"Meerstraat 5",
    "sg:city":"Emmen",
    "sg:orig_category":"Kappers",
    "sg:phone":"+31 591 640 803",
    "sg:postcode":"7815 XA",
    "sg:province":"Drenthe",
    "wof:name":"Haarstudio Anniek",
    "wof:placetype":"venue"
},
  "geometry": {"coordinates":[6.8947749138,52.7900733948],"type":"Point"}
}