{
  "type": "Feature",
  "properties": {
    "addr:full":"1E Weteringplnts 2C Amsterdam North Holland 1017 SJ",
    "addr:housenumber":"2c",
    "addr:postcode":"1017",
    "addr:street":"1E Weteringplnts",
    "iso:country":"NL",
    "sg:address":"1E Weteringplnts 2C",
    "sg:city":"Amsterdam",
    "sg:orig_category":"Verenigingen En Stichtingen",
    "sg:phone":"+31 20 622 1820",
    "sg:postcode":"1017 SJ",
    "sg:province":"North Holland",
    "wof:name":"Htib-Amsterdam",
    "wof:placetype":"venue"
},
  "geometry": {"coordinates":[4.887644,52.361958],"type":"Point"}
}