{
  "type": "Feature",
  "properties": {
    "iso:country":"NL",
    "sg:address":"Schiewg 15D",
    "sg:city":"Delft",
    "sg:orig_category":"Galeries",
    "sg:phone":"+31 15 261 4499",
    "sg:postcode":"2627 AN",
    "sg:province":"Zuid-Holland",
    "sg:website":"http://www.dutchart.com",
    "wof:name":"Dutchart",
    "wof:placetype":"venue"
},
  "geometry": {"coordinates":[4.367686,51.994865],"type":"Point"}
}