{
  "type": "Feature",
  "properties": {
    "addr:full":"Provincialeweg 106 Veldhoven Noord-Brabant 5503 HJ",
    "addr:housenumber":"106",
    "addr:postcode":"5503 hj",
    "addr:street":"Provincialeweg",
    "iso:country":"NL",
    "sg:address":"Provincialeweg 106",
    "sg:city":"Veldhoven",
    "sg:orig_category":"Verzekeringen",
    "sg:phone":"+31 40 253 8632",
    "sg:postcode":"5503 HJ",
    "sg:province":"Noord-Brabant",
    "wof:name":"De Groot Assurantien",
    "wof:placetype":"venue"
},
  "geometry": {"coordinates":[5.421025,51.414455],"type":"Point"}
}