{
  "type": "Feature",
  "properties": {
    "addr:full":"Schans 3 A Heerenveen Provincie Friesland 8441 AB",
    "addr:housenumber":"3 a",
    "addr:postcode":"8441 ab",
    "addr:street":"Schans;Provincie Friesland",
    "iso:country":"NL",
    "sg:address":"Schans 3 A",
    "sg:city":"Heerenveen",
    "sg:orig_category":"Verlichting And Huishoudartikelen",
    "sg:phone":"+31 513 620 608",
    "sg:postcode":"8441 AB",
    "sg:province":"Provincie Friesland",
    "wof:name":"Leo Van Der Veen Woonmode",
    "wof:placetype":"venue"
},
  "geometry": {"coordinates":[5.911381,52.967442],"type":"Point"}
}