{
  "type": "Feature",
  "properties": {
    "addr:full":"Kerkweg 5 Roelofarendsveen South Holland 2371 CE",
    "addr:housenumber":"5",
    "addr:postcode":"2371 ce",
    "addr:street":"Kerkweg",
    "iso:country":"NL",
    "sg:address":"Kerkweg 5",
    "sg:city":"Roelofarendsveen",
    "sg:orig_category":"Bloemen And Planten",
    "sg:phone":"+31 71 331 2242",
    "sg:postcode":"2371 CE",
    "sg:province":"South Holland",
    "wof:name":"L.J. Van Der Meer Bv",
    "wof:placetype":"venue"
},
  "geometry": {"coordinates":[4.6235,52.195011],"type":"Point"}
}