{
  "type": "Feature",
  "properties": {
    "iso:country":"NL",
    "sg:address":"J V Nassaustr 2",
    "sg:city":"S Gravenzande",
    "sg:orig_category":"Loonbedrijven",
    "sg:phone":"+31 6 28253409",
    "sg:postcode":"2691 GP",
    "sg:province":"South Holland",
    "wof:name":"Yalman, A",
    "wof:placetype":"venue"
},
  "geometry": {"coordinates":[4.16946,51.994629],"type":"Point"}
}