{
  "type": "Feature",
  "properties": {
    "addr:full":"Wilgenbos 1 Dordrecht South Holland 3311 JX",
    "addr:housenumber":"1",
    "addr:postcode":"3311 jx",
    "addr:street":"Wilgenbos",
    "iso:country":"NL",
    "sg:address":"Wilgenbos 1",
    "sg:city":"Dordrecht",
    "sg:orig_category":"Banken And Kredietinstellingen",
    "sg:phone":"+31 78 633 9666",
    "sg:postcode":"3311 JX",
    "sg:province":"South Holland",
    "wof:name":"Rabobank",
    "wof:placetype":"venue"
},
  "geometry": {"coordinates":[4.65494,51.811081],"type":"Point"}
}