{
  "type": "Feature",
  "properties": {
    "addr:full":"Hinmanwg 11E Oldenzaal Overijssel 7575 BE",
    "addr:housenumber":"11e",
    "addr:postcode":"7575",
    "addr:street":"Hinmanwg",
    "iso:country":"NL",
    "sg:address":"Hinmanwg 11E",
    "sg:city":"Oldenzaal",
    "sg:orig_category":"Onroerende Goederen",
    "sg:phone":"+31 541 532 798",
    "sg:postcode":"7575 BE",
    "sg:province":"Overijssel",
    "wof:name":"Venturasol Bv",
    "wof:placetype":"venue"
},
  "geometry": {"coordinates":[6.92891,52.289799],"type":"Point"}
}