{
  "type": "Feature",
  "properties": {
    "addr:full":"Maatgravenweg 12 Zwolle NL.08 8026 RG",
    "addr:housenumber":"12",
    "addr:postcode":"8026 rg",
    "addr:street":"Maatgravenweg",
    "iso:country":"NL",
    "sg:address":"Maatgravenweg 12",
    "sg:city":"Zwolle",
    "sg:orig_category":"Diverse Dierenfokkers",
    "sg:phone":"+31 529 401 759",
    "sg:postcode":"8026 RG",
    "sg:province":"NL.08",
    "wof:name":"C.A.J. Bruin",
    "wof:placetype":"venue"
},
  "geometry": {"coordinates":[6.179223,52.519768],"type":"Point"}
}