{
  "type": "Feature",
  "properties": {
    "addr:full":"Akerstr N 94 Hoensbroek Limburg 6431 HP",
    "addr:postcode":"6431 hp",
    "addr:street":"N 94",
    "iso:country":"NL",
    "sg:address":"Akerstr N 94",
    "sg:city":"Hoensbroek",
    "sg:orig_category":"Bloemen En Planten",
    "sg:phone":"+31 45 521 2688",
    "sg:postcode":"6431 HP",
    "sg:province":"Limburg",
    "wof:name":"Ogenlust",
    "wof:placetype":"venue"
},
  "geometry": {"coordinates":[5.933698,50.931507],"type":"Point"}
}