{
  "type": "Feature",
  "properties": {
    "iso:country":"NL",
    "sg:address":"Bedryfswg 50",
    "sg:city":"Emmeloord",
    "sg:orig_category":"Autoschade- Herstelbedrijven",
    "sg:phone":"+31 527 618 839",
    "sg:postcode":"8304 AA",
    "sg:province":"NL.",
    "wof:name":"Stuut, Jan",
    "wof:placetype":"venue"
},
  "geometry": {"coordinates":[5.755026,52.694778],"type":"Point"}
}