{
  "type": "Feature",
  "properties": {
    "addr:full":"Esterweg 12 Est Gelderland 4185 NN",
    "addr:housenumber":"12",
    "addr:postcode":"4185 nn",
    "addr:street":"Esterweg;Gelderland",
    "iso:country":"NL",
    "sg:address":"Esterweg 12",
    "sg:city":"Est",
    "sg:orig_category":"Fruit And Groenten Gh",
    "sg:phone":"+31 345 569 432",
    "sg:postcode":"4185 NN",
    "sg:province":"Gelderland",
    "wof:name":"Roel Wellner Handelsonderneming",
    "wof:placetype":"venue"
},
  "geometry": {"coordinates":[-85.646378,30.984421],"type":"Point"}
}