{
  "type": "Feature",
  "properties": {
    "addr:full":"Dorpspln 40 Duivendrecht North Holland 1115 CW",
    "addr:housenumber":"40",
    "addr:postcode":"1115 cw",
    "addr:street":"Dorpspln",
    "iso:country":"NL",
    "sg:address":"Dorpspln 40",
    "sg:city":"Duivendrecht",
    "sg:orig_category":"Banken",
    "sg:phone":"+31 20 496 9700",
    "sg:postcode":"1115 CW",
    "sg:province":"North Holland",
    "sg:website":"http://www.rabobank.nl",
    "wof:name":"Rabobank",
    "wof:placetype":"venue"
},
  "geometry": {"coordinates":[4.93975,52.33231],"type":"Point"}
}