{
  "type": "Feature",
  "properties": {
    "addr:full":"J C Rysdykstr 18 Leerdam Zuid-Holland 4141 CV",
    "addr:housenumber":"18",
    "addr:postcode":"4141 cv",
    "addr:street":"J C Rysdykstr",
    "iso:country":"NL",
    "sg:address":"J C Rysdykstr 18",
    "sg:city":"Leerdam",
    "sg:orig_category":"Woninginrichting",
    "sg:phone":"+31 345 473 075",
    "sg:postcode":"4141 CV",
    "sg:province":"Zuid-Holland",
    "wof:name":"Dijk Stoffering, Van",
    "wof:placetype":"venue"
},
  "geometry": {"coordinates":[5.0910449028,51.8906745911],"type":"Point"}
}