{
  "type": "Feature",
  "properties": {
    "addr:full":"P De Hooghln 18 Oud Beyerland South Holland 3262 RE",
    "addr:housenumber":"18",
    "addr:postcode":"3262 re",
    "addr:street":"P;Oud Beyerland",
    "iso:country":"NL",
    "sg:address":"P De Hooghln 18",
    "sg:city":"Oud Beyerland",
    "sg:orig_category":"Belastingconsulenten/ Belastingadviseurs",
    "sg:phone":"+31 186 613 592",
    "sg:postcode":"3262 RE",
    "sg:province":"South Holland",
    "wof:name":"Bentum, M J",
    "wof:placetype":"venue"
},
  "geometry": {"coordinates":[4.41701,51.823044],"type":"Point"}
}