{
  "type": "Feature",
  "properties": {
    "addr:full":"Zuiderwouder Dorpsstraat 60 Zuiderwoude Noord-Holland 1153 PE",
    "addr:housenumber":"60",
    "addr:postcode":"1153 pe",
    "addr:street":"Zuiderwouder Dorpsstraat",
    "iso:country":"NL",
    "sg:address":"Zuiderwouder Dorpsstraat 60",
    "sg:city":"Zuiderwoude",
    "sg:orig_category":"Verhuur Bouwmachines",
    "sg:phone":"+31 20 403 1453",
    "sg:postcode":"1153 PE",
    "sg:province":"Noord-Holland",
    "wof:name":"Firma Schoon",
    "wof:placetype":"venue"
},
  "geometry": {"coordinates":[5.039479,52.429523],"type":"Point"}
}