{
  "type": "Feature",
  "properties": {
    "addr:full":"Goudenheuvel 13B S Hertogenbosch Noord-Brabant 5234 GA",
    "addr:housenumber":"13b",
    "addr:postcode":"5234 ga",
    "addr:street":"Goudenheuvel;S Hertogenbosch",
    "iso:country":"NL",
    "sg:address":"Goudenheuvel 13B",
    "sg:city":"S Hertogenbosch",
    "sg:orig_category":"Airconditioning",
    "sg:phone":"+31 73 644 7740",
    "sg:postcode":"5234 GA",
    "sg:province":"Noord-Brabant",
    "wof:name":"Ias Bv",
    "wof:placetype":"venue"
},
  "geometry": {"coordinates":[5.285147,51.724037],"type":"Point"}
}