{
  "type": "Feature",
  "properties": {
    "addr:full":"Marktstr 2 Ootmarsum Overijssel 7631 BZ",
    "addr:housenumber":"2",
    "addr:postcode":"7631 bz",
    "addr:street":"Marktstr",
    "iso:country":"NL",
    "sg:address":"Marktstr 2",
    "sg:city":"Ootmarsum",
    "sg:orig_category":"Kappers",
    "sg:phone":"+31 541 293 165",
    "sg:postcode":"7631 BZ",
    "sg:province":"Overijssel",
    "wof:name":"Vivaldi",
    "wof:placetype":"venue"
},
  "geometry": {"coordinates":[6.89731,52.408176],"type":"Point"}
}