{
  "type": "Feature",
  "properties": {
    "addr:full":"Goudsesingel 2 Rotterdam South Holland 3011 KA",
    "addr:housenumber":"2",
    "addr:postcode":"3011 ka",
    "addr:street":"Goudsesingel",
    "iso:country":"NL",
    "sg:address":"Goudsesingel 2",
    "sg:city":"Rotterdam",
    "sg:orig_category":"Bedrijfs- And Managementsconsultants",
    "sg:phone":"+31 10 411 1950",
    "sg:postcode":"3011 KA",
    "sg:province":"South Holland",
    "wof:name":"Risico Beheergroep Bv",
    "wof:placetype":"venue"
},
  "geometry": {"coordinates":[4.4936,51.92395],"type":"Point"}
}