{
  "type": "Feature",
  "properties": {
    "addr:full":"Modelmakerstr 6 Amsterdam Noord-Holland 1033 DN",
    "addr:housenumber":"6",
    "addr:postcode":"1033 dn",
    "addr:street":"Modelmakerstr",
    "iso:country":"NL",
    "sg:address":"Modelmakerstr 6",
    "sg:city":"Amsterdam",
    "sg:orig_category":"Loodgieters",
    "sg:phone":"+31 20 770 2957",
    "sg:postcode":"1033 DN",
    "sg:province":"Noord-Holland",
    "wof:name":"Waas, Van",
    "wof:placetype":"venue"
},
  "geometry": {"coordinates":[4.896127,52.404755],"type":"Point"}
}