{
  "type": "Feature",
  "properties": {
    "addr:full":"Egelantier 6 Noordwykerhout Zuid-Holland 2211 NN",
    "addr:housenumber":"6",
    "addr:postcode":"2211 nn",
    "addr:street":"Egelantier",
    "iso:country":"NL",
    "sg:address":"Egelantier 6",
    "sg:city":"Noordwykerhout",
    "sg:orig_category":"Schelpenhandel",
    "sg:phone":"+31 252 374 108",
    "sg:postcode":"2211 NN",
    "sg:province":"Zuid-Holland",
    "wof:name":"Duivenvoorden, G A",
    "wof:placetype":"venue"
},
  "geometry": {"coordinates":[4.49169,52.254284],"type":"Point"}
}