{
  "type": "Feature",
  "properties": {
    "iso:country":"NL",
    "sg:address":"Geert Knolweg 52B",
    "sg:city":"Joure",
    "sg:orig_category":"Benzinestations And Brandstoffen",
    "sg:phone":"+31 513 416 947",
    "sg:postcode":"8501 MK",
    "sg:province":"Provincie Friesland",
    "wof:name":"Slump Oil Bv",
    "wof:placetype":"venue"
},
  "geometry": {"coordinates":[5.808957,52.961281],"type":"Point"}
}