{
  "type": "Feature",
  "properties": {
    "iso:country":"NL",
    "sg:address":"Goudenheuvel 1",
    "sg:city":"S Hertogenbosch",
    "sg:classifiers":[
        {
            "category":"Manufacturing",
            "subcategory":"Electronics",
            "type":"Manufacturing & Wholesale Goods"
        }
    ],
    "sg:phone":"+31 73 644 7544",
    "sg:postcode":"5234 GA",
    "sg:province":"Noord-Brabant",
    "sg:tags":[
        "en",
        "laser",
        "lasertechniek"
    ],
    "sg:website":"http://www.laserprinting.nl",
    "wof:name":"Bieling",
    "wof:placetype":"venue"
},
  "geometry": {"coordinates":[5.28666,51.7239],"type":"Point"}
}