{
  "type": "Feature",
  "properties": {
    "addr:full":"J Smitstr 3 Deventer Overijssel 7421 HM",
    "addr:housenumber":"3",
    "addr:postcode":"7421 hm",
    "iso:country":"NL",
    "sg:address":"J Smitstr 3",
    "sg:city":"Deventer",
    "sg:orig_category":"Adviesbureaus Bedrijfsorganisatie",
    "sg:phone":"+31 570 657 320",
    "sg:postcode":"7421 HM",
    "sg:province":"Overijssel",
    "wof:name":"Mco",
    "wof:placetype":"venue"
},
  "geometry": {"coordinates":[6.21918,52.245281],"type":"Point"}
}