{
  "type": "Feature",
  "properties": {
    "addr:full":"M Samuelstr 42 Enter Pennsylvania 7468 BP",
    "addr:housenumber":"42",
    "addr:postcode":"7468 bp",
    "iso:country":"NL",
    "sg:address":"M Samuelstr 42",
    "sg:city":"Enter",
    "sg:orig_category":"Voetbalverenigingen",
    "sg:phone":"+31 547 381 521",
    "sg:postcode":"7468 BP",
    "sg:province":"Pennsylvania",
    "sg:website":"http://come.to/ev2",
    "wof:name":"Enter Vooruit",
    "wof:placetype":"venue"
},
  "geometry": {"coordinates":[-76.841904,40.463078],"type":"Point"}
}