{
  "type": "Feature",
  "properties": {
    "addr:full":"Karel Doormanplein 12 Roermond Limburg 6045 EE",
    "addr:housenumber":"12",
    "addr:postcode":"6045 ee",
    "addr:street":"Karel Doormanplein",
    "iso:country":"NL",
    "sg:address":"Karel Doormanplein 12",
    "sg:city":"Roermond",
    "sg:orig_category":"Bloemen And Planten",
    "sg:phone":"+31 475 321 616",
    "sg:postcode":"6045 EE",
    "sg:province":"Limburg",
    "wof:name":"P. Peters Bloemenhal Bv",
    "wof:placetype":"venue"
},
  "geometry": {"coordinates":[6.002301,51.176552],"type":"Point"}
}