{
  "type": "Feature",
  "properties": {
    "addr:full":"Meteoorstr 13 Dordrecht Zuid-Holland 3328 GK",
    "addr:housenumber":"13",
    "addr:postcode":"3328 gk",
    "addr:street":"Meteoorstr",
    "iso:country":"NL",
    "sg:address":"Meteoorstr 13",
    "sg:city":"Dordrecht",
    "sg:orig_category":"Behangers",
    "sg:phone":"+31 78 616 5150",
    "sg:postcode":"3328 GK",
    "sg:province":"Zuid-Holland",
    "wof:name":"Paus, Behang- & Schildersbedrijf De",
    "wof:placetype":"venue"
},
  "geometry": {"coordinates":[4.679825,51.78046],"type":"Point"}
}