{
  "type": "Feature",
  "properties": {
    "addr:full":"Weerdingerstr 82 Emmen Provincie Drenthe 7815 SG",
    "addr:housenumber":"82",
    "addr:postcode":"7815",
    "addr:street":"Weerdingerstr;Provincie Drenthe",
    "iso:country":"NL",
    "sg:address":"Weerdingerstr 82",
    "sg:city":"Emmen",
    "sg:orig_category":"Fietsen En Bromfietsen",
    "sg:phone":"+31 591 613 585",
    "sg:postcode":"7815 SG",
    "sg:province":"Provincie Drenthe",
    "wof:name":"Profile Pro",
    "wof:placetype":"venue"
},
  "geometry": {"coordinates":[6.898667,52.794476],"type":"Point"}
}