{
  "type": "Feature",
  "properties": {
    "addr:full":"Weegbreegaarde 3 Gouda Zuid-Holland 2803 TH",
    "addr:housenumber":"3",
    "addr:postcode":"2803 th",
    "addr:street":"Weegbreegaarde",
    "iso:country":"NL",
    "sg:address":"Weegbreegaarde 3",
    "sg:city":"Gouda",
    "sg:orig_category":"Adviesbureaus",
    "sg:phone":"+31 182 572 463",
    "sg:postcode":"2803 TH",
    "sg:province":"Zuid-Holland",
    "wof:name":"Wissema Consultancy",
    "wof:placetype":"venue"
},
  "geometry": {"coordinates":[4.691462,52.026062],"type":"Point"}
}