{
  "type": "Feature",
  "properties": {
    "addr:full":"Kamperstraat 35 Haarlem Noord-Holland 2012 XB",
    "addr:housenumber":"35",
    "addr:postcode":"2012 xb",
    "addr:street":"Kamperstraat",
    "iso:country":"NL",
    "sg:address":"Kamperstraat 35",
    "sg:city":"Haarlem",
    "sg:orig_category":"Gespecialiseerde Bouw",
    "sg:phone":"+31 23 532 3174",
    "sg:postcode":"2012 XB",
    "sg:province":"Noord-Holland",
    "wof:name":"A.H. Vermeulen",
    "wof:placetype":"venue"
},
  "geometry": {"coordinates":[4.638143,52.374924],"type":"Point"}
}