{
  "type": "Feature",
  "properties": {
    "iso:country":"NL",
    "sg:address":"Uithuizerweg 6",
    "sg:city":"Uithuizermeeden",
    "sg:orig_category":"Huizensloop And Bouwrijp Maken",
    "sg:phone":"+31 595 413 972",
    "sg:postcode":"9982 ND",
    "sg:province":"Groningen",
    "wof:name":"Loonbedrijf Vegter",
    "wof:placetype":"venue"
},
  "geometry": {"coordinates":[6.723411,53.413601],"type":"Point"}
}