{
  "type": "Feature",
  "properties": {
    "addr:full":"Veerwg 5-7 Numansdorp Zuid-Holland 3281 LX",
    "addr:housenumber":"5-7",
    "addr:postcode":"3281 lx",
    "addr:street":"Veerwg",
    "iso:country":"NL",
    "sg:address":"Veerwg 5-7",
    "sg:city":"Numansdorp",
    "sg:orig_category":"Jachthavens - Jachtwerven",
    "sg:phone":"+31 186 650 415",
    "sg:postcode":"3281 LX",
    "sg:province":"Zuid-Holland",
    "sg:website":"http://www.marina-numansdorp.nl",
    "wof:name":"Marina Bv",
    "wof:placetype":"venue"
},
  "geometry": {"coordinates":[4.438345,51.731369],"type":"Point"}
}