{
  "type": "Feature",
  "properties": {
    "addr:full":"Breitnerstraat 32 Goes Zeeland 4462 SN",
    "addr:housenumber":"32",
    "addr:postcode":"4462 sn",
    "addr:street":"Breitnerstraat",
    "iso:country":"NL",
    "sg:address":"Breitnerstraat 32",
    "sg:city":"Goes",
    "sg:orig_category":"Wegen And Sportterreinen",
    "sg:phone":"+31 113 250 808",
    "sg:postcode":"4462 SN",
    "sg:province":"Zeeland",
    "wof:name":"Deal Bestrating Vof",
    "wof:placetype":"venue"
},
  "geometry": {"coordinates":[13.945309639,50.9286308289],"type":"Point"}
}