{
  "type": "Feature",
  "properties": {
    "addr:full":"Biessumerwaard 39 Delfzyl Groningen 9931 EB",
    "addr:housenumber":"39",
    "addr:postcode":"9931 eb",
    "addr:street":"Biessumerwaard",
    "iso:country":"NL",
    "sg:address":"Biessumerwaard 39",
    "sg:city":"Delfzyl",
    "sg:orig_category":"Verenigingen En Stichtingen",
    "sg:phone":"+31 596 616 132",
    "sg:postcode":"9931 EB",
    "sg:province":"Groningen",
    "wof:name":"Wordship Centrum Capitol, Sticht",
    "wof:placetype":"venue"
},
  "geometry": {"coordinates":[6.898064,53.336002],"type":"Point"}
}