{
  "type": "Feature",
  "properties": {
    "addr:full":"Stevenzandsestr 17 Tilburg North Brabant 5021 HA",
    "addr:housenumber":"17",
    "addr:postcode":"5021 ha",
    "addr:street":"Stevenzandsestr",
    "iso:country":"NL",
    "sg:address":"Stevenzandsestr 17",
    "sg:city":"Tilburg",
    "sg:orig_category":"Projectontwikkeling",
    "sg:phone":"+31 13 543 5376",
    "sg:postcode":"5021 HA",
    "sg:province":"North Brabant",
    "wof:name":"Cruijssen Bv, Robjan",
    "wof:placetype":"venue"
},
  "geometry": {"coordinates":[5.091758,51.551155],"type":"Point"}
}