{
  "type": "Feature",
  "properties": {
    "iso:country":"NL",
    "sg:address":"Dusseldorperwg 64",
    "sg:city":"Limmen",
    "sg:orig_category":"Verenigingsgebouwen",
    "sg:phone":"+31 72 505 1950",
    "sg:postcode":"1906 AL",
    "sg:province":"North Holland",
    "wof:name":"Vredeburg",
    "wof:placetype":"venue"
},
  "geometry": {"coordinates":[4.700112,52.570675],"type":"Point"}
}