{
  "type": "Feature",
  "properties": {
    "iso:country":"NL",
    "sg:address":"De Weid 24",
    "sg:city":"Velserbroek",
    "sg:orig_category":"Scholen Voor Basisonderwijs",
    "sg:phone":"+31 23 537 8198",
    "sg:postcode":"1991 ET",
    "sg:province":"North Holland",
    "wof:name":"Hoeksteen Prot Chr, De",
    "wof:placetype":"venue"
},
  "geometry": {"coordinates":[4.663499,52.436039],"type":"Point"}
}