{
  "type": "Feature",
  "properties": {
    "addr:full":"Eindstr 23 Brunssum Limburg 6442 PA",
    "addr:housenumber":"23",
    "addr:postcode":"6442 pa",
    "addr:street":"Eindstr",
    "iso:country":"NL",
    "sg:address":"Eindstr 23",
    "sg:city":"Brunssum",
    "sg:orig_category":"Gehandicapten - Hulpmiddelen",
    "sg:phone":"+31 45 564 0506",
    "sg:postcode":"6442 PA",
    "sg:province":"Limburg",
    "wof:name":"Rida",
    "wof:placetype":"venue"
},
  "geometry": {"coordinates":[5.994708,50.953358],"type":"Point"}
}