{
  "type": "Feature",
  "properties": {
    "addr:full":"Stadhoudersring 5 Zoetermeer Zuid-Holland 2713 GA",
    "addr:housenumber":"5",
    "addr:postcode":"2713 ga",
    "addr:street":"Stadhoudersring",
    "iso:country":"NL",
    "sg:address":"Stadhoudersring 5",
    "sg:city":"Zoetermeer",
    "sg:orig_category":"Verenigingen En Stichtingen",
    "sg:phone":"+31 79 316 6640",
    "sg:postcode":"2713 GA",
    "sg:province":"Zuid-Holland",
    "wof:name":"Spil, De",
    "wof:placetype":"venue"
},
  "geometry": {"coordinates":[4.48138,52.050659],"type":"Point"}
}