{
  "type": "Feature",
  "properties": {
    "addr:full":"Kamerlingh Onnesstraat 100 Vlaardingen Zuid-Holland 3132 RS",
    "addr:housenumber":"100",
    "addr:postcode":"3132 rs",
    "addr:street":"Kamerlingh Onnesstraat",
    "iso:country":"NL",
    "sg:address":"Kamerlingh Onnesstraat 100",
    "sg:city":"Vlaardingen",
    "sg:orig_category":"Kinderopvang Behalve Thuis",
    "sg:phone":"+31 10 460 0733",
    "sg:postcode":"3132 RS",
    "sg:province":"Zuid-Holland",
    "wof:name":"Medisch Kleuterdagverblijf Vlaardingen",
    "wof:placetype":"venue"
},
  "geometry": {"coordinates":[4.313461,51.915623],"type":"Point"}
}