{
  "type": "Feature",
  "properties": {
    "addr:full":"Kraaiennest 63 Amsterdam Zuidoost North Holland 1104 CD",
    "addr:housenumber":"63",
    "addr:postcode":"1104 cd",
    "addr:street":"Kraaiennest",
    "iso:country":"NL",
    "sg:address":"Kraaiennest 63",
    "sg:city":"Amsterdam Zuidoost",
    "sg:orig_category":"Postkantoren",
    "sg:phone":"+31 20 690 4939",
    "sg:postcode":"1104 CD",
    "sg:province":"North Holland",
    "sg:website":"http://www.postkantoor.nl",
    "wof:name":"Postkantoor",
    "wof:placetype":"venue"
},
  "geometry": {"coordinates":[4.980199,52.316967],"type":"Point"}
}