{
  "type": "Feature",
  "properties": {
    "iso:country":"NL",
    "sg:address":"Dorpsstraat 10",
    "sg:city":"Renkum",
    "sg:orig_category":"Paramedische Behandelingen",
    "sg:phone":"+31 317 316 533",
    "sg:postcode":"6871 AL",
    "sg:province":"Gelderland",
    "wof:name":"Thuiszorg Op Maat",
    "wof:placetype":"venue"
},
  "geometry": {"coordinates":[5.728326,51.971867],"type":"Point"}
}