{
  "type": "Feature",
  "properties": {
    "addr:full":"Oude Watering 262 Rotterdam Zuid-Holland 3077 RD",
    "addr:housenumber":"262",
    "addr:postcode":"3077 rd",
    "addr:street":"Oude Watering",
    "iso:country":"NL",
    "sg:address":"Oude Watering 262",
    "sg:city":"Rotterdam",
    "sg:orig_category":"Verenigingen En Stichtingen",
    "sg:phone":"+31 10 482 7922",
    "sg:postcode":"3077 RD",
    "sg:province":"Zuid-Holland",
    "wof:name":"Stichting Ijsselmonds Welzijnswerk",
    "wof:placetype":"venue"
},
  "geometry": {"coordinates":[4.568325,51.892101],"type":"Point"}
}