{
  "type": "Feature",
  "properties": {
    "addr:full":"Nunspeterwg 17 Elburg Gelderland 8081 BV",
    "addr:housenumber":"17",
    "addr:postcode":"8081 bv",
    "addr:street":"Nunspeterwg;Gelderland",
    "iso:country":"NL",
    "sg:address":"Nunspeterwg 17",
    "sg:city":"Elburg",
    "sg:orig_category":"Accountants - Administratie- Consulenten En -Kantoren",
    "sg:phone":"+31 525 681 640",
    "sg:postcode":"8081 BV",
    "sg:province":"Gelderland",
    "sg:website":"http://www.fitacc.nl",
    "wof:name":"Fitacc",
    "wof:placetype":"venue"
},
  "geometry": {"coordinates":[5.832172,52.444416],"type":"Point"}
}