{
  "type": "Feature",
  "properties": {
    "addr:full":"Landlust 3 Diemen Noord-Holland 1111 HP",
    "addr:housenumber":"3",
    "addr:postcode":"1111 hp",
    "addr:street":"Landlust",
    "iso:country":"NL",
    "sg:address":"Landlust 3",
    "sg:city":"Diemen",
    "sg:classifiers":[
        {
            "category":"Sports & Exercise",
            "subcategory":"Stables",
            "type":"Entertainment"
        }
    ],
    "sg:phone":"+31 20 695 3161",
    "sg:postcode":"1111 HP",
    "sg:province":"Noord-Holland",
    "sg:tags":[
        "maneges"
    ],
    "wof:name":"Eenhoorn, De",
    "wof:placetype":"venue"
},
  "geometry": {"coordinates":[4.97197,52.347576],"type":"Point"}
}