{
  "type": "Feature",
  "properties": {
    "addr:full":"Multatuliwg 26 Almere NL. 1321 EB",
    "addr:housenumber":"26",
    "addr:postcode":"1321 eb",
    "addr:street":"Multatuliwg;Nl.",
    "iso:country":"NL",
    "sg:address":"Multatuliwg 26",
    "sg:city":"Almere",
    "sg:orig_category":"Bedrijfshuisvesting",
    "sg:phone":"+31 36 529 5234",
    "sg:postcode":"1321 EB",
    "sg:province":"NL.",
    "wof:name":"Flevo Real Estate Bv",
    "wof:placetype":"venue"
},
  "geometry": {"coordinates":[5.183207,52.361622],"type":"Point"}
}