{
  "type": "Feature",
  "properties": {
    "addr:full":"Sperwerhorst 2 Honselersdyk Zuid-Holland 2675 WT",
    "addr:housenumber":"2",
    "addr:postcode":"2675 wt",
    "addr:street":"Sperwerhorst",
    "iso:country":"NL",
    "sg:address":"Sperwerhorst 2",
    "sg:city":"Honselersdyk",
    "sg:orig_category":"Kappers",
    "sg:phone":"+31 174 628 924",
    "sg:postcode":"2675 WT",
    "sg:province":"Zuid-Holland",
    "wof:name":"Marian",
    "wof:placetype":"venue"
},
  "geometry": {"coordinates":[4.230916,52.003792],"type":"Point"}
}