{
  "type": "Feature",
  "properties": {
    "addr:full":"De Gouw 61 Lutjebroek Noord-Holland 1614 MB",
    "addr:housenumber":"61",
    "addr:postcode":"1614 mb",
    "addr:street":"De Gouw",
    "iso:country":"NL",
    "sg:address":"De Gouw 61",
    "sg:city":"Lutjebroek",
    "sg:orig_category":"Bloembollen - Groothandel",
    "sg:phone":"+31 228 563 106",
    "sg:postcode":"1614 MB",
    "sg:province":"Noord-Holland",
    "wof:name":"Reus Bv, Gebr",
    "wof:placetype":"venue"
},
  "geometry": {"coordinates":[5.193425,52.70557],"type":"Point"}
}