{
  "type": "Feature",
  "properties": {
    "addr:full":"Richel 12 Emmeloord NL. 8303 KX",
    "addr:housenumber":"12",
    "addr:postcode":"8303 kx",
    "addr:street":"Richel;Nl.",
    "iso:country":"NL",
    "sg:address":"Richel 12",
    "sg:city":"Emmeloord",
    "sg:orig_category":"Adviesbureaus Waterbouwkunde",
    "sg:phone":"+31 527 611 941",
    "sg:postcode":"8303 KX",
    "sg:province":"NL.",
    "wof:name":"Coastal Man",
    "wof:placetype":"venue"
},
  "geometry": {"coordinates":[5.721832,52.714603],"type":"Point"}
}