{
  "type": "Feature",
  "properties": {
    "iso:country":"NL",
    "sg:address":"Oostvaardersdk 31",
    "sg:city":"Lelystad",
    "sg:classifiers":[
        {
            "category":"Banks & Credit Unions",
            "subcategory":"Investment Brokerage",
            "type":"Services"
        }
    ],
    "sg:phone":"+31 320 260 415",
    "sg:postcode":"8244 PB",
    "sg:province":"Flevoland",
    "sg:tags":[
        "pension"
    ],
    "wof:name":"Lange Jammer, De",
    "wof:placetype":"venue"
},
  "geometry": {"coordinates":[5.416416,52.502476],"type":"Point"}
}