{
  "type": "Feature",
  "properties": {
    "addr:full":"Ambachtstr 8 Didam Gelderland 6942 AG",
    "addr:housenumber":"8",
    "addr:postcode":"6942",
    "addr:street":"Ambachtstr;Gelderland",
    "iso:country":"NL",
    "sg:address":"Ambachtstr 8",
    "sg:city":"Didam",
    "sg:orig_category":"Offsetdrukkerijen",
    "sg:phone":"+31 316 221 681",
    "sg:postcode":"6942 AG",
    "sg:province":"Gelderland",
    "sg:website":"http://www.leonards.nl",
    "wof:name":"Leonards Didam Bv",
    "wof:placetype":"venue"
},
  "geometry": {"coordinates":[6.131301,51.940144],"type":"Point"}
}