{
  "type": "Feature",
  "properties": {
    "addr:full":"Hoornseschans 101 Nieuwegein Utrecht 3432 TK",
    "addr:housenumber":"101",
    "addr:postcode":"3432 tk",
    "addr:street":"Hoornseschans",
    "iso:country":"NL",
    "sg:address":"Hoornseschans 101",
    "sg:city":"Nieuwegein",
    "sg:orig_category":"Verenigingsgebouwen",
    "sg:phone":"+31 30 606 1063",
    "sg:postcode":"3432 TK",
    "sg:province":"Utrecht",
    "wof:name":"Dok Buurtcentr, 'T",
    "wof:placetype":"venue"
},
  "geometry": {"coordinates":[5.092874,52.017895],"type":"Point"}
}