{
  "type": "Feature",
  "properties": {
    "addr:full":"Vivaldilaan 44 Assen Provincie Drenthe 9402 VE",
    "addr:housenumber":"44",
    "addr:postcode":"9402",
    "addr:street":"Vivaldilaan;Provincie Drenthe;Ve",
    "iso:country":"NL",
    "sg:address":"Vivaldilaan 44",
    "sg:city":"Assen",
    "sg:orig_category":"Meubelzaken, Woning- And Keukeninrichting",
    "sg:phone":"+31 592 346 530",
    "sg:postcode":"9402 VE",
    "sg:province":"Provincie Drenthe",
    "wof:name":"Handelsonderneming Ecolit",
    "wof:placetype":"venue"
},
  "geometry": {"coordinates":[6.561606,53.009304],"type":"Point"}
}