{
  "type": "Feature",
  "properties": {
    "addr:full":"W De Haasstr 52 Gemert Noord-Brabant 5421 TP",
    "addr:housenumber":"52",
    "addr:postcode":"5421 tp",
    "addr:street":"W De Haasstr",
    "iso:country":"NL",
    "sg:address":"W De Haasstr 52",
    "sg:city":"Gemert",
    "sg:orig_category":"Psychotherapeuten",
    "sg:phone":"+31 492 368 929",
    "sg:postcode":"5421 TP",
    "sg:province":"Noord-Brabant",
    "wof:name":"Smeur, J M",
    "wof:placetype":"venue"
},
  "geometry": {"coordinates":[5.684041,51.560028],"type":"Point"}
}