{
  "type": "Feature",
  "properties": {
    "addr:full":"Smidsweg 102 Nijverdal NL.08 7441 ER",
    "addr:housenumber":"102;nl.08",
    "addr:postcode":"7441 er",
    "addr:street":"Smidsweg",
    "iso:country":"NL",
    "sg:address":"Smidsweg 102",
    "sg:city":"Nijverdal",
    "sg:orig_category":"Benzinestations And Brandstoffen",
    "sg:phone":"+31 548 612 874",
    "sg:postcode":"7441 ER",
    "sg:province":"NL.08",
    "wof:name":"Vof Autobedrijf Servicestation Morsink",
    "wof:placetype":"venue"
},
  "geometry": {"coordinates":[6.4596,52.361034],"type":"Point"}
}