{
  "type": "Feature",
  "properties": {
    "addr:full":"Hulsterweg 47 Kloosterzande Zeeland 4587 EA",
    "addr:housenumber":"47",
    "addr:postcode":"4587 ea",
    "addr:street":"Hulsterweg",
    "iso:country":"NL",
    "sg:address":"Hulsterweg 47",
    "sg:city":"Kloosterzande",
    "sg:classifiers":[
        {
            "category":"Travel",
            "subcategory":"Hotels & Motels",
            "type":"Entertainment"
        }
    ],
    "sg:phone":"+31 114 681 320",
    "sg:postcode":"4587 EA",
    "sg:province":"Zeeland",
    "wof:name":"Dorpshotel De Linde",
    "wof:placetype":"venue"
},
  "geometry": {"coordinates":[4.02127,51.366795],"type":"Point"}
}