{
  "type": "Feature",
  "properties": {
    "addr:full":"Stephensonwg 4A Hellevoetsluis South Holland 3225 LW",
    "addr:housenumber":"4a",
    "addr:postcode":"3225 lw",
    "addr:street":"Stephensonwg",
    "iso:country":"NL",
    "sg:address":"Stephensonwg 4A",
    "sg:city":"Hellevoetsluis",
    "sg:orig_category":"Automaterialen En Gereedschappen",
    "sg:phone":"+31 181 311 300",
    "sg:postcode":"3225 LW",
    "sg:province":"South Holland",
    "sg:website":"http://www.penk.nl",
    "wof:name":"P En K Automaterialen",
    "wof:placetype":"venue"
},
  "geometry": {"coordinates":[4.169354,51.839165],"type":"Point"}
}