{
  "type": "Feature",
  "properties": {
    "addr:full":"Rijdersstraat 82 'T Veld Noord-Holland 1735 GE",
    "addr:housenumber":"82",
    "addr:postcode":"1735",
    "addr:street":"Rijdersstraat",
    "iso:country":"NL",
    "sg:address":"Rijdersstraat 82",
    "sg:city":"'T Veld",
    "sg:orig_category":"Autokeuringen",
    "sg:phone":"+31 226 421 327",
    "sg:postcode":"1735 GE",
    "sg:province":"Noord-Holland",
    "wof:name":"Schildersbedrijf Plaatwerkerij En Autospuiterij Gr",
    "wof:placetype":"venue"
},
  "geometry": {"coordinates":[4.859809,52.739925],"type":"Point"}
}