{
  "type": "Feature",
  "properties": {
    "iso:country":"NL",
    "sg:address":"Rijdersstraat 82",
    "sg:city":"'T Veld",
    "sg:orig_category":"Autokeuringen",
    "sg:phone":"+31 226 421 327",
    "sg:postcode":"1735 GE",
    "sg:province":"Noord-Holland",
    "wof:name":"Schildersbedrijf Plaatwerkerij En Autospuiterij Gr",
    "wof:placetype":"venue"
},
  "geometry": {"coordinates":[4.859809,52.739925],"type":"Point"}
}