{
  "type": "Feature",
  "properties": {
    "addr:full":"Maalstroom 27 Oostzaan North Holland 1511 JL",
    "addr:housenumber":"27",
    "addr:postcode":"1511 jl",
    "addr:street":"Maalstroom",
    "iso:country":"NL",
    "sg:address":"Maalstroom 27",
    "sg:city":"Oostzaan",
    "sg:orig_category":"Boekhouders",
    "sg:phone":"+31 75 684 3798",
    "sg:postcode":"1511 JL",
    "sg:province":"North Holland",
    "wof:name":"Administratiekantoor Hermans",
    "wof:placetype":"venue"
},
  "geometry": {"coordinates":[4.878259,52.433823],"type":"Point"}
}