{
  "type": "Feature",
  "properties": {
    "iso:country":"NL",
    "sg:address":"Het Wielsem 21",
    "sg:city":"'S Hertogenbosch",
    "sg:orig_category":"Overheidsdiensten",
    "sg:phone":"+31 73 641 7914",
    "sg:postcode":"5231 BV",
    "sg:province":"North Brabant",
    "wof:name":"Wijkgebouw De Inham",
    "wof:placetype":"venue"
},
  "geometry": {"coordinates":[5.301856041,51.7157287598],"type":"Point"}
}