{
  "type": "Feature",
  "properties": {
    "addr:full":"Leemslagenwg 14 Almelo Overijssel 7609 PN",
    "addr:housenumber":"14",
    "addr:postcode":"7609 pn",
    "addr:street":"Leemslagenwg",
    "iso:country":"NL",
    "sg:address":"Leemslagenwg 14",
    "sg:city":"Almelo",
    "sg:orig_category":"Adviesbureaus Bedrijfsorganisatie",
    "sg:phone":"+31 546 454 859",
    "sg:postcode":"7609 PN",
    "sg:province":"Overijssel",
    "wof:name":"Eefting, Dick",
    "wof:placetype":"venue"
},
  "geometry": {"coordinates":[6.652133,52.335796],"type":"Point"}
}