{
  "type": "Feature",
  "properties": {
    "addr:full":"Groenloseweg 56 Winterswijk Gelderland 7101 AJ",
    "addr:housenumber":"56",
    "addr:postcode":"7101 aj",
    "addr:street":"Groenloseweg;Gelderland",
    "iso:country":"NL",
    "sg:address":"Groenloseweg 56",
    "sg:city":"Winterswijk",
    "sg:orig_category":"Metaalbekleding And -Behandeling",
    "sg:phone":"+31 543 519 566",
    "sg:postcode":"7101 AJ",
    "sg:province":"Gelderland",
    "wof:name":"Staalkozijn Nederland Bv",
    "wof:placetype":"venue"
},
  "geometry": {"coordinates":[6.712446,51.977669],"type":"Point"}
}