{
  "type": "Feature",
  "properties": {
    "addr:full":"Mozartlaan 1 Doorwerth Gelderland 6865 GA",
    "addr:housenumber":"1",
    "addr:postcode":"6865 ga",
    "addr:street":"Mozartlaan;Gelderland",
    "iso:country":"NL",
    "sg:address":"Mozartlaan 1",
    "sg:city":"Doorwerth",
    "sg:classifiers":[
        {
            "category":"Education",
            "subcategory":"Preschool",
            "type":"Public Place"
        }
    ],
    "sg:phone":"+31 26 333 3782",
    "sg:postcode":"6865 GA",
    "sg:province":"Gelderland",
    "sg:tags":[
        "kleuteronderwijs",
        "basis-"
    ],
    "wof:name":"De Wegwijzer",
    "wof:placetype":"venue"
},
  "geometry": {"coordinates":[5.795803,51.979736],"type":"Point"}
}