{
  "type": "Feature",
  "properties": {
    "iso:country":"NL",
    "sg:address":"Courtine 20",
    "sg:city":"Zaltbommel",
    "sg:orig_category":"Voetbalverenigingen",
    "sg:phone":"+31 418 515 337",
    "sg:postcode":"5301 DH",
    "sg:province":"Gelderland",
    "wof:name":"Ash",
    "wof:placetype":"venue"
},
  "geometry": {"coordinates":[5.233344,51.802322],"type":"Point"}
}