{
  "type": "Feature",
  "properties": {
    "iso:country":"NL",
    "sg:address":"Van Coevenhovenstraat 16",
    "sg:city":"Heemskerk",
    "sg:classifiers":[
        {
            "category":"Fast Food",
            "type":"Food & Drink"
        }
    ],
    "sg:phone":"+31 251 230 731",
    "sg:postcode":"1961 NX",
    "sg:province":"North Holland",
    "sg:tags":[
        "afhaal",
        "restaurant"
    ],
    "wof:name":"Chinees Indisch Restaurant De Lange Muur",
    "wof:placetype":"venue"
},
  "geometry": {"coordinates":[4.6693367958,52.5114173889],"type":"Point"}
}