{
  "type": "Feature",
  "properties": {
    "addr:full":"Industriestraat 6 Lage Zwaluwe Noord-Brabant 4926 AJ",
    "addr:housenumber":"6",
    "addr:postcode":"zwaluwe;4926 aj",
    "addr:street":"Industriestraat",
    "iso:country":"NL",
    "sg:address":"Industriestraat 6",
    "sg:city":"Lage Zwaluwe",
    "sg:orig_category":"Pleziervaartuigen And Reparatie",
    "sg:phone":"+31 168 484 334",
    "sg:postcode":"4926 AJ",
    "sg:province":"Noord-Brabant",
    "wof:name":"Scheepstimmerbedrijf Bas Van 'T Geloof Bv",
    "wof:placetype":"venue"
},
  "geometry": {"coordinates":[4.692338,51.714272],"type":"Point"}
}