{
  "type": "Feature",
  "properties": {
    "iso:country":"NL",
    "sg:address":"Bongerdstraat 2",
    "sg:city":"Almere",
    "sg:classifiers":[
        {
            "category":"Education",
            "subcategory":"Preschool",
            "type":"Public Place"
        }
    ],
    "sg:phone":"+31 36 537 3326",
    "sg:postcode":"1326 AB",
    "sg:province":"NL.",
    "sg:tags":[
        "kleuteronderwijs",
        "basis-"
    ],
    "wof:name":"De Olijfboom",
    "wof:placetype":"venue"
},
  "geometry": {"coordinates":[5.23763,52.374748],"type":"Point"}
}