{
  "type": "Feature",
  "properties": {
    "addr:full":"Singel 25 Amsterdam Noord-Holland 1012 VC",
    "addr:housenumber":"25",
    "addr:postcode":"1012 vc",
    "addr:street":"Singel",
    "iso:country":"NL",
    "sg:address":"Singel 25",
    "sg:city":"Amsterdam",
    "sg:orig_category":"Boekenuitgeverijen",
    "sg:phone":"+31 20 530 2570",
    "sg:postcode":"1012 VC",
    "sg:province":"Noord-Holland",
    "wof:name":"Bv Uitgeverij Blvd",
    "wof:placetype":"venue"
},
  "geometry": {"coordinates":[4.893144,52.377468],"type":"Point"}
}