{
  "type": "Feature",
  "properties": {
    "addr:full":"Bergwg 102A Zeist Utrecht 3707 AE",
    "addr:housenumber":"102a",
    "addr:postcode":"3707 ae",
    "iso:country":"NL",
    "sg:address":"Bergwg 102A",
    "sg:city":"Zeist",
    "sg:orig_category":"Adviesbureaus Bedrijfsorganisatie",
    "sg:phone":"+31 30 693 3446",
    "sg:postcode":"3707 AE",
    "sg:province":"Utrecht",
    "wof:name":"Esser Bv",
    "wof:placetype":"venue"
},
  "geometry": {"coordinates":[5.24387,52.08548],"type":"Point"}
}