{
  "type": "Feature",
  "properties": {
    "addr:full":"Keizerstraat 27 Den Helder North Holland 1781 GD",
    "addr:housenumber":"27",
    "addr:postcode":"1781 gd",
    "addr:street":"Keizerstraat",
    "iso:country":"NL",
    "sg:address":"Keizerstraat 27",
    "sg:city":"Den Helder",
    "sg:orig_category":"Juweliers",
    "sg:phone":"+31 223 616 168",
    "sg:postcode":"1781 GD",
    "sg:province":"North Holland",
    "wof:name":"Het Gouden Anker",
    "wof:placetype":"venue"
},
  "geometry": {"coordinates":[4.763161,52.958431],"type":"Point"}
}