{
  "type": "Feature",
  "properties": {
    "addr:full":"Ruysdaelkade 29 Amsterdam Noord-Holland 1072 AH",
    "addr:housenumber":"29",
    "addr:postcode":"1072 ah",
    "addr:street":"Ruysdaelkade",
    "iso:country":"NL",
    "sg:address":"Ruysdaelkade 29",
    "sg:city":"Amsterdam",
    "sg:orig_category":"Vertaal- And Tolkenbureaus",
    "sg:phone":"+31 20 664 2253",
    "sg:postcode":"1072 AH",
    "sg:province":"Noord-Holland",
    "wof:name":"I.T.O. International Translation Office",
    "wof:placetype":"venue"
},
  "geometry": {"coordinates":[4.887212,52.358608],"type":"Point"}
}