{
  "type": "Feature",
  "properties": {
    "addr:full":"Neptunuslaan 198 Krommenie North Holland 1562 XS",
    "addr:housenumber":"198",
    "addr:postcode":"1562 xs",
    "addr:street":"Neptunuslaan",
    "iso:country":"NL",
    "sg:address":"Neptunuslaan 198",
    "sg:city":"Krommenie",
    "sg:orig_category":"Woninginrichting- Fournituren - Fabrieken En Groothandel",
    "sg:phone":"+31 75 771 9670",
    "sg:postcode":"1562 XS",
    "sg:province":"North Holland",
    "wof:name":"Fox & Hunter'S",
    "wof:placetype":"venue"
},
  "geometry": {"coordinates":[4.7489471436,52.498966217],"type":"Point"}
}