{
  "type": "Feature",
  "properties": {
    "addr:full":"Roggelsedijk 16 Meijel Limburg 5768 RB",
    "addr:housenumber":"16",
    "addr:postcode":"5768 rb",
    "addr:street":"Roggelsedijk",
    "iso:country":"NL",
    "sg:address":"Roggelsedijk 16",
    "sg:city":"Meijel",
    "sg:orig_category":"Gebouwenafwerking, Renovaties And Reiniging",
    "sg:phone":"+31 77 466 1462",
    "sg:postcode":"5768 RB",
    "sg:province":"Limburg",
    "wof:name":"Dekclo Klus- En Schoonmaakbedrijf",
    "wof:placetype":"venue"
},
  "geometry": {"coordinates":[5.882679,51.321705],"type":"Point"}
}