{
  "type": "Feature",
  "properties": {
    "addr:full":"Pieter Christiaanstraat 2 Breda Noord-Brabant 4811 PS",
    "addr:housenumber":"2",
    "addr:postcode":"4811 ps",
    "addr:street":"Pieter Christiaanstraat",
    "iso:country":"NL",
    "sg:address":"Pieter Christiaanstraat 2",
    "sg:city":"Breda",
    "sg:orig_category":"Sportterreinen And Installaties Behalve Sportcentra",
    "sg:phone":"+31 76 524 6500",
    "sg:postcode":"4811 PS",
    "sg:province":"Noord-Brabant",
    "wof:name":"Zwembad Sonsbeeck",
    "wof:placetype":"venue"
},
  "geometry": {"coordinates":[4.768126,51.580208],"type":"Point"}
}