{
  "type": "Feature",
  "properties": {
    "addr:full":"Lipsstr 1-13 Drunen North Brabant 5151 BH",
    "addr:housenumber":"1-13",
    "addr:postcode":"5151 bh",
    "iso:country":"NL",
    "sg:address":"Lipsstr 1-13",
    "sg:city":"Drunen",
    "sg:orig_category":"Lederwaren - Fabrieken En Groothandel",
    "sg:phone":"+31 416 322 556",
    "sg:postcode":"5151 BH",
    "sg:province":"North Brabant",
    "sg:website":"http://www.bretoniere.nl",
    "wof:name":"Estral Bv",
    "wof:placetype":"venue"
},
  "geometry": {"coordinates":[5.14605,51.68676],"type":"Point"}
}