{
  "type": "Feature",
  "properties": {
    "addr:full":"Westblaak 75 Rotterdam South Holland 3012 KE",
    "addr:housenumber":"75",
    "addr:postcode":"3012 ke",
    "addr:street":"Westblaak",
    "iso:country":"NL",
    "sg:address":"Westblaak 75",
    "sg:city":"Rotterdam",
    "sg:orig_category":"Makelaars In Onroerend Goed",
    "sg:phone":"+31 10 411 0677",
    "sg:postcode":"3012 KE",
    "sg:province":"South Holland",
    "wof:name":"Blok & Nederlof Bedrijfsmakelaardij Og",
    "wof:placetype":"venue"
},
  "geometry": {"coordinates":[4.476929,51.917271],"type":"Point"}
}