{
  "type": "Feature",
  "properties": {
    "iso:country":"NL",
    "sg:address":"Westblaak 75",
    "sg:city":"Rotterdam",
    "sg:orig_category":"Makelaars In Onroerend Goed",
    "sg:phone":"+31 10 411 0677",
    "sg:postcode":"3012 KE",
    "sg:province":"South Holland",
    "wof:name":"Blok & Nederlof Bedrijfsmakelaardij Og",
    "wof:placetype":"venue"
},
  "geometry": {"coordinates":[4.476929,51.917271],"type":"Point"}
}