{
  "type": "Feature",
  "properties": {
    "addr:full":"Brouwerijstraat 49 Hengelo Ov Overijssel 7553 LE",
    "addr:housenumber":"49",
    "addr:postcode":"7553 le",
    "addr:street":"Brouwerijstraat;Ov",
    "iso:country":"NL",
    "sg:address":"Brouwerijstraat 49",
    "sg:city":"Hengelo Ov",
    "sg:orig_category":"Diverse Consumentenartikelen Gh",
    "sg:phone":"+31 74 250 1057",
    "sg:postcode":"7553 LE",
    "sg:province":"Overijssel",
    "wof:name":"Handelsmaatschappij Pots Bv",
    "wof:placetype":"venue"
},
  "geometry": {"coordinates":[6.800631,52.260017],"type":"Point"}
}