{
  "type": "Feature",
  "properties": {
    "iso:country":"NL",
    "sg:address":"Poppelsedijk 1",
    "sg:city":"Hooge Mierde",
    "sg:orig_category":"Verhuur Catering-, Feest- En Evenementbenodigdheden",
    "sg:phone":"+31 13 509 2237",
    "sg:postcode":"5095 AJ",
    "sg:province":"Noord-Brabant",
    "wof:name":"Antonis Verhuur Vof",
    "wof:placetype":"venue"
},
  "geometry": {"coordinates":[5.130678,51.396477],"type":"Point"}
}