{
  "type": "Feature",
  "properties": {
    "iso:country":"NL",
    "sg:address":"Zandstr 2",
    "sg:city":"Overloon",
    "sg:orig_category":"Verzekeringen - Verzekeringskantoren",
    "sg:phone":"+31 478 641 313",
    "sg:postcode":"5825 HC",
    "sg:province":"Noord-Brabant",
    "wof:name":"Meijer",
    "wof:placetype":"venue"
},
  "geometry": {"coordinates":[5.938915,51.570202],"type":"Point"}
}