{
  "type": "Feature",
  "properties": {
    "iso:country":"NL",
    "sg:address":"Bladstraat 10",
    "sg:city":"Tuitjenhorn",
    "sg:classifiers":[
        {
            "category":"Education",
            "subcategory":"Preschool",
            "type":"Public Place"
        }
    ],
    "sg:phone":"+31 226 393 905",
    "sg:postcode":"1747 HJ",
    "sg:province":"North Holland",
    "sg:tags":[
        "kleuteronderwijs",
        "basis-"
    ],
    "wof:name":"Peuterspeelzaal De Paddestoel",
    "wof:placetype":"venue"
},
  "geometry": {"coordinates":[4.746829,52.73735],"type":"Point"}
}