{
  "type": "Feature",
  "properties": {
    "addr:full":"Veneind 3 Wintelre Noord-Brabant 5513 NE",
    "addr:housenumber":"3",
    "addr:postcode":"5513 ne",
    "addr:street":"Veneind",
    "iso:country":"NL",
    "sg:address":"Veneind 3",
    "sg:city":"Wintelre",
    "sg:orig_category":"Artiestenbureaus",
    "sg:phone":"+31 40 205 1570",
    "sg:postcode":"5513 NE",
    "sg:province":"Noord-Brabant",
    "wof:name":"Die Stall-Freunde",
    "wof:placetype":"venue"
},
  "geometry": {"coordinates":[5.337131,51.435291],"type":"Point"}
}