{
  "type": "Feature",
  "properties": {
    "addr:full":"Slotlaan 126 Zeist Utrecht 3701 GR",
    "addr:housenumber":"126",
    "addr:postcode":"3701",
    "addr:street":"Slotlaan",
    "iso:country":"NL",
    "sg:address":"Slotlaan 126",
    "sg:city":"Zeist",
    "sg:orig_category":"Herenmodezaken",
    "sg:phone":"+31 30 693 0300",
    "sg:postcode":"3701 GR",
    "sg:province":"Utrecht",
    "wof:name":"Ron Enters Bv",
    "wof:placetype":"venue"
},
  "geometry": {"coordinates":[5.24317,52.084782],"type":"Point"}
}