{
  "type": "Feature",
  "properties": {
    "iso:country":"NL",
    "sg:address":"Zevenend 67",
    "sg:city":"Laren Nh",
    "sg:orig_category":"Fotoreportages",
    "sg:phone":"+31 35 538 9452",
    "sg:postcode":"1251 RM",
    "sg:province":"North Holland",
    "wof:name":"John Ruis",
    "wof:placetype":"venue"
},
  "geometry": {"coordinates":[5.229959,52.25087],"type":"Point"}
}