{
  "type": "Feature",
  "properties": {
    "iso:country":"NL",
    "sg:address":"Calandweg 2",
    "sg:city":"Arnemuiden",
    "sg:orig_category":"Luchtvaart",
    "sg:phone":"+31 113 612 406",
    "sg:postcode":"4341 RA",
    "sg:province":"Zeeland",
    "wof:name":"Transal Bv",
    "wof:placetype":"venue"
},
  "geometry": {"coordinates":[3.724129,51.513824],"type":"Point"}
}