{
  "type": "Feature",
  "properties": {
    "addr:full":"Spinozahof 61 Amsterdam Noord-Holland 1018 AN",
    "addr:housenumber":"61",
    "addr:postcode":"1018 an",
    "addr:street":"Spinozahof",
    "iso:country":"NL",
    "sg:address":"Spinozahof 61",
    "sg:city":"Amsterdam",
    "sg:orig_category":"Webdesign Bureaus",
    "sg:phone":"+31 20 623 7127",
    "sg:postcode":"1018 AN",
    "sg:province":"Noord-Holland",
    "wof:name":"Waljango",
    "wof:placetype":"venue"
},
  "geometry": {"coordinates":[4.9134821892,52.3616447449],"type":"Point"}
}