{
  "type": "Feature",
  "properties": {
    "iso:country":"NL",
    "sg:address":"Forsythiastraat 17",
    "sg:city":"Berkel En Rodenrijs",
    "sg:orig_category":"Kappers",
    "sg:phone":"+31 10 511 4231",
    "sg:postcode":"2651 TC",
    "sg:province":"South Holland",
    "wof:name":"Kapsalon Marianne Boer",
    "wof:placetype":"venue"
},
  "geometry": {"coordinates":[4.486415863,52.0015487671],"type":"Point"}
}