{
  "type": "Feature",
  "properties": {
    "addr:full":"Monseigneur Broerestraat 29 Voorhout South Holland 2215 ER",
    "addr:housenumber":"29",
    "addr:postcode":"2215 er",
    "addr:street":"Monseigneur Broerestraat",
    "iso:country":"NL",
    "sg:address":"Monseigneur Broerestraat 29",
    "sg:city":"Voorhout",
    "sg:orig_category":"Juweliers",
    "sg:phone":"+31 252 212 294",
    "sg:postcode":"2215 ER",
    "sg:province":"South Holland",
    "wof:name":"Kortekaas",
    "wof:placetype":"venue"
},
  "geometry": {"coordinates":[4.481025,52.219307],"type":"Point"}
}