{
  "type": "Feature",
  "properties": {
    "addr:full":"Plantage 2A Beverwijk Noord-Holland 1943 LM",
    "addr:housenumber":"2a",
    "addr:postcode":"1943 lm",
    "addr:street":"Plantage",
    "iso:country":"NL",
    "sg:address":"Plantage 2A",
    "sg:city":"Beverwijk",
    "sg:orig_category":"Alternatieve Geneeskunde",
    "sg:phone":"+31 251 228 298",
    "sg:postcode":"1943 LM",
    "sg:province":"Noord-Holland",
    "wof:name":"Arends Simon",
    "wof:placetype":"venue"
},
  "geometry": {"coordinates":[4.653411,52.487492],"type":"Point"}
}