{
  "type": "Feature",
  "properties": {
    "iso:country":"NL",
    "sg:address":"Voorstr 25",
    "sg:city":"Franeker",
    "sg:orig_category":"Huishoudelijke Apparaten En Artikelen",
    "sg:phone":"+31 517 390 010",
    "sg:postcode":"8801 KZ",
    "sg:province":"Provincie Friesland",
    "wof:name":"Weerd Bv, Van Der",
    "wof:placetype":"venue"
},
  "geometry": {"coordinates":[5.542619,53.186455],"type":"Point"}
}