{
  "type": "Feature",
  "properties": {
    "addr:full":"Wilhelminapark 132 Tilburg North Brabant 5041 EH",
    "addr:housenumber":"132",
    "addr:postcode":"5041 eh",
    "addr:street":"Wilhelminapark",
    "iso:country":"NL",
    "sg:address":"Wilhelminapark 132",
    "sg:city":"Tilburg",
    "sg:classifiers":[
        {
            "category":"Bars & Pubs",
            "type":"Food & Drink"
        }
    ],
    "sg:phone":"+31 13 542 2087",
    "sg:postcode":"5041 EH",
    "sg:province":"North Brabant",
    "wof:name":"Theehuis Caliskanlar",
    "wof:placetype":"venue"
},
  "geometry": {"coordinates":[5.0786,51.56432],"type":"Point"}
}