{
  "type": "Feature",
  "properties": {
    "addr:full":"Slappedel 4 Woudenberg Utrecht 3931 MN",
    "addr:housenumber":"4",
    "addr:postcode":"3931 mn",
    "addr:street":"Slappedel",
    "iso:country":"NL",
    "sg:address":"Slappedel 4",
    "sg:city":"Woudenberg",
    "sg:orig_category":"Bloemen And Planten",
    "sg:phone":"+31 33 286 3663",
    "sg:postcode":"3931 MN",
    "sg:province":"Utrecht",
    "wof:name":"Bloemin Bv",
    "wof:placetype":"venue"
},
  "geometry": {"coordinates":[5.403836,52.080715],"type":"Point"}
}