{
  "type": "Feature",
  "properties": {
    "addr:full":"Parnassusweg 21/3 Amsterdam North Holland 1077 DB",
    "addr:housenumber":"21 / 3",
    "addr:postcode":"1077 db",
    "addr:street":"Parnassusweg",
    "iso:country":"NL",
    "sg:address":"Parnassusweg 21/3",
    "sg:city":"Amsterdam",
    "sg:orig_category":"Binnenhuisarchitecten",
    "sg:phone":"+31 20 671 1994",
    "sg:postcode":"1077 DB",
    "sg:province":"North Holland",
    "wof:name":"A. Bueno De Mesquita",
    "wof:placetype":"venue"
},
  "geometry": {"coordinates":[4.867689,52.345264],"type":"Point"}
}