{
  "type": "Feature",
  "properties": {
    "addr:full":"Eemwg 29B Eemnes Utrecht 3755 LC",
    "addr:housenumber":"29b",
    "addr:postcode":"3755 lc",
    "addr:street":"Eemwg",
    "iso:country":"NL",
    "sg:address":"Eemwg 29B",
    "sg:city":"Eemnes",
    "sg:orig_category":"Projectinrichting",
    "sg:phone":"+31 35 541 7537",
    "sg:postcode":"3755 LC",
    "sg:province":"Utrecht",
    "wof:name":"Uitvoering Eemland, Bureau Van",
    "wof:placetype":"venue"
},
  "geometry": {"coordinates":[5.310381,52.22171],"type":"Point"}
}