{
  "type": "Feature",
  "properties": {
    "addr:full":"Het Hoekje 45 Hollandscheveld Provincie Drenthe 7913 BB",
    "addr:housenumber":"45",
    "addr:postcode":"7913 bb",
    "addr:street":"Het Hoekje;Provincie Drenthe",
    "iso:country":"NL",
    "sg:address":"Het Hoekje 45",
    "sg:city":"Hollandscheveld",
    "sg:orig_category":"Loodgieters",
    "sg:phone":"+31 528 341 482",
    "sg:postcode":"7913 BB",
    "sg:province":"Provincie Drenthe",
    "wof:name":"Leijssenaar Vof",
    "wof:placetype":"venue"
},
  "geometry": {"coordinates":[6.538746,52.706345],"type":"Point"}
}