{
  "type": "Feature",
  "properties": {
    "iso:country":"NL",
    "sg:address":"Het Hoekje 45",
    "sg:city":"Hollandscheveld",
    "sg:orig_category":"Loodgieters",
    "sg:phone":"+31 528 341 482",
    "sg:postcode":"7913 BB",
    "sg:province":"Provincie Drenthe",
    "wof:name":"Leijssenaar Vof",
    "wof:placetype":"venue"
},
  "geometry": {"coordinates":[6.538746,52.706345],"type":"Point"}
}