{
  "type": "Feature",
  "properties": {
    "iso:country":"NL",
    "sg:address":"Wederikwg 116",
    "sg:city":"Haren Gn",
    "sg:orig_category":"Psychologen",
    "sg:phone":"+31 50 534 6834",
    "sg:postcode":"9753 AG",
    "sg:province":"Groningen",
    "wof:name":"Astrid Prins Drs",
    "wof:placetype":"venue"
},
  "geometry": {"coordinates":[6.619824,53.176468],"type":"Point"}
}