{
  "type": "Feature",
  "properties": {
    "iso:country":"NL",
    "sg:address":"Stephensonstraat 50",
    "sg:city":"Haarlem",
    "sg:orig_category":"Zuivelproducten",
    "sg:phone":"+31 23 524 5601",
    "sg:postcode":"2014 KD",
    "sg:province":"North Holland",
    "wof:name":"Waayer De Kaasboer Bv",
    "wof:placetype":"venue"
},
  "geometry": {"coordinates":[4.613704,52.369057],"type":"Point"}
}