{
  "type": "Feature",
  "properties": {
    "iso:country":"NL",
    "sg:address":"Engelbertsstr 30",
    "sg:city":"Zandvoort",
    "sg:orig_category":"Beveiliging",
    "sg:phone":"+31 23 573 9278",
    "sg:postcode":"2042 KN",
    "sg:province":"North Holland",
    "wof:name":"Willemse, H",
    "wof:placetype":"venue"
},
  "geometry": {"coordinates":[4.527368,52.373455],"type":"Point"}
}