{
  "type": "Feature",
  "properties": {
    "iso:country":"NL",
    "sg:address":"Berenbroekwg 6",
    "sg:city":"Venlo",
    "sg:orig_category":"Ademhalingstherapeuten",
    "sg:phone":"+31 77 323 0637",
    "sg:postcode":"5926 PB",
    "sg:province":"Limburg",
    "wof:name":"Timmerman, L",
    "wof:placetype":"venue"
},
  "geometry": {"coordinates":[6.123435,51.348297],"type":"Point"}
}