{
  "type": "Feature",
  "properties": {
    "iso:country":"NL",
    "sg:address":"Arena Boulev 106",
    "sg:city":"Amsterdam Zuidoost",
    "sg:orig_category":"Keukens",
    "sg:phone":"+31 20 567 3000",
    "sg:postcode":"1101 DJ",
    "sg:province":"North Holland",
    "sg:website":"http://www.brugman.nl",
    "wof:name":"Brugman",
    "wof:placetype":"venue"
},
  "geometry": {"coordinates":[4.944247,52.312698],"type":"Point"}
}