{
  "type": "Feature",
  "properties": {
    "addr:full":"A Jacobsstr 26 Veenoord Drenthe 7844 PA",
    "addr:housenumber":"26",
    "addr:postcode":"7844 pa",
    "addr:street":"Veenoord",
    "iso:country":"NL",
    "sg:address":"A Jacobsstr 26",
    "sg:city":"Veenoord",
    "sg:orig_category":"Artiesten/Gezelschappen",
    "sg:phone":"+31 591 553 422",
    "sg:postcode":"7844 PA",
    "sg:province":"Drenthe",
    "wof:name":"Karampoek",
    "wof:placetype":"venue"
},
  "geometry": {"coordinates":[-77.604507,40.99464],"type":"Point"}
}