{
  "type": "Feature",
  "properties": {
    "addr:full":"M D De Grootstraat 72 Goes Zeeland 4461 WD",
    "addr:housenumber":"72",
    "addr:postcode":"4461 wd",
    "addr:street":"De Grootstraat",
    "iso:country":"NL",
    "sg:address":"M D De Grootstraat 72",
    "sg:city":"Goes",
    "sg:orig_category":"Goederenvervoer Over De Weg",
    "sg:phone":"+31 113 233 262",
    "sg:postcode":"4461 WD",
    "sg:province":"Zeeland",
    "wof:name":"Corstanje Transport",
    "wof:placetype":"venue"
},
  "geometry": {"coordinates":[-83.914169,39.768833],"type":"Point"}
}