{
  "type": "Feature",
  "properties": {
    "iso:country":"NL",
    "sg:address":"Flierenhofstraat 34",
    "sg:city":"Bemmel",
    "sg:classifiers":[
        {
            "category":"Education",
            "subcategory":"Preschool",
            "type":"Public Place"
        }
    ],
    "sg:phone":"+31 481 461 827",
    "sg:postcode":"6681 BZ",
    "sg:province":"Gelderland",
    "sg:tags":[
        "kleuteronderwijs",
        "basis-"
    ],
    "wof:name":"Jenaplan Basisschool Donatushof",
    "wof:placetype":"venue"
},
  "geometry": {"coordinates":[5.899914,51.889881],"type":"Point"}
}