{
  "type": "Feature",
  "properties": {
    "addr:full":"Hoofdstr 74 Borger Drenthe 9531 AJ",
    "addr:housenumber":"74",
    "addr:postcode":"9531 aj",
    "addr:street":"Hoofdstr",
    "iso:country":"NL",
    "sg:address":"Hoofdstr 74",
    "sg:city":"Borger",
    "sg:orig_category":"Administratie- En Boekhoudkantoren",
    "sg:phone":"+31 599 235 056",
    "sg:postcode":"9531 AJ",
    "sg:province":"Drenthe",
    "wof:name":"Dijk, J H",
    "wof:placetype":"venue"
},
  "geometry": {"coordinates":[6.792787,52.919807],"type":"Point"}
}