{
  "type": "Feature",
  "properties": {
    "addr:full":"Burg De Zeeuwstr 88A Numansdorp Zuid-Holland 3281 AK",
    "addr:housenumber":"88a",
    "addr:postcode":"3281 ak",
    "iso:country":"NL",
    "sg:address":"Burg De Zeeuwstr 88A",
    "sg:city":"Numansdorp",
    "sg:classifiers":[
        {
            "category":"Retail",
            "subcategory":"Auto Repair",
            "type":"Services"
        }
    ],
    "sg:phone":"+31 186 651 432",
    "sg:postcode":"3281 AK",
    "sg:province":"Zuid-Holland",
    "sg:tags":[
        "garage"
    ],
    "wof:name":"Man Bandenservice En Garage, A De",
    "wof:placetype":"venue"
},
  "geometry": {"coordinates":[4.43901,51.735214],"type":"Point"}
}