{
  "type": "Feature",
  "properties": {
    "addr:full":"Lijsterbesstraat 18 Den Helder Noord-Holland 1783 HT",
    "addr:housenumber":"18",
    "addr:postcode":"1783 ht",
    "addr:street":"Lijsterbesstraat",
    "iso:country":"NL",
    "sg:address":"Lijsterbesstraat 18",
    "sg:city":"Den Helder",
    "sg:orig_category":"Bedrijfs- And Managementsconsultants",
    "sg:phone":"+31 223 623 935",
    "sg:postcode":"1783 HT",
    "sg:province":"Noord-Holland",
    "wof:name":"Goja Fashion",
    "wof:placetype":"venue"
},
  "geometry": {"coordinates":[4.734913,52.941631],"type":"Point"}
}