{
  "type": "Feature",
  "properties": {
    "addr:full":"Stevensbloem 169 Leiden Zuid-Holland 2331 JC",
    "addr:housenumber":"169",
    "addr:postcode":"2331 jc",
    "addr:street":"Stevensbloem",
    "iso:country":"NL",
    "sg:address":"Stevensbloem 169",
    "sg:city":"Leiden",
    "sg:orig_category":"Zonnebank- En Solariumcentra",
    "sg:phone":"+31 71 576 9030",
    "sg:postcode":"2331 JC",
    "sg:province":"Zuid-Holland",
    "wof:name":"Coresd?",
    "wof:placetype":"venue"
},
  "geometry": {"coordinates":[4.45352,52.151569],"type":"Point"}
}