{
  "type": "Feature",
  "properties": {
    "iso:country":"NL",
    "sg:address":"Venraysewg 26",
    "sg:city":"Overloon",
    "sg:classifiers":[
        {
            "category":"Banks & Credit Unions",
            "subcategory":"Investment Brokerage",
            "type":"Services"
        }
    ],
    "sg:phone":"+31 478 641 968",
    "sg:postcode":"5825 AC",
    "sg:province":"Noord-Brabant",
    "sg:tags":[
        "pension"
    ],
    "wof:name":"Gabri\u00ebls Plats",
    "wof:placetype":"venue"
},
  "geometry": {"coordinates":[5.947948,51.566597],"type":"Point"}
}