{
  "type": "Feature",
  "properties": {
    "addr:full":"Kasteelplein 5 Montfoort Utrecht 3417 JG",
    "addr:housenumber":"5",
    "addr:postcode":"3417 jg",
    "addr:street":"Kasteelplein",
    "iso:country":"NL",
    "sg:address":"Kasteelplein 5",
    "sg:city":"Montfoort",
    "sg:orig_category":"Overheidsdiensten",
    "sg:phone":"+31 348 476 400",
    "sg:postcode":"3417 JG",
    "sg:province":"Utrecht",
    "wof:name":"Gemeente Montfoort",
    "wof:placetype":"venue"
},
  "geometry": {"coordinates":[4.9508810043,52.0447349548],"type":"Point"}
}