{
  "type": "Feature",
  "properties": {
    "iso:country":"NL",
    "sg:address":"Wielstr 6",
    "sg:city":"Beneden Leeuwen",
    "sg:orig_category":"Adviesbureaus Bedrijfsveiligheid",
    "sg:phone":"+31 487 593 790",
    "sg:postcode":"6658 BD",
    "sg:province":"Gelderland",
    "wof:name":"Vgs",
    "wof:placetype":"venue"
},
  "geometry": {"coordinates":[5.516478,51.884804],"type":"Point"}
}