{
  "type": "Feature",
  "properties": {
    "addr:full":"Oostzeestraat 5 Zutphen Gelderland 7202 CM",
    "addr:housenumber":"5",
    "addr:postcode":"7202 cm",
    "addr:street":"Oostzeestraat;Gelderland",
    "iso:country":"NL",
    "sg:address":"Oostzeestraat 5",
    "sg:city":"Zutphen",
    "sg:orig_category":"Overheidsdiensten",
    "sg:phone":"+31 575 517 038",
    "sg:postcode":"7202 CM",
    "sg:province":"Gelderland",
    "wof:name":"Rwzi",
    "wof:placetype":"venue"
},
  "geometry": {"coordinates":[6.202586174,52.1579208374],"type":"Point"}
}