{
  "type": "Feature",
  "properties": {
    "addr:full":"Dielishoek 7 Bavel Noord-Brabant 4854 BK",
    "addr:housenumber":"7",
    "addr:postcode":"4854 bk",
    "addr:street":"Dielishoek",
    "iso:country":"NL",
    "sg:address":"Dielishoek 7",
    "sg:city":"Bavel",
    "sg:orig_category":"Vloer- And Wandbedekkingen",
    "sg:phone":"+31 161 434 394",
    "sg:postcode":"4854 BK",
    "sg:province":"Noord-Brabant",
    "wof:name":"Eric Voeten Straatmakersbedrijf",
    "wof:placetype":"venue"
},
  "geometry": {"coordinates":[4.824761,51.56638],"type":"Point"}
}