{
  "type": "Feature",
  "properties": {
    "addr:full":"Oelerwg 26 Hengelo Ov Overijssel 7555 GS",
    "addr:housenumber":"26",
    "addr:postcode":"7555 gs",
    "addr:street":"Oelerwg;Ov",
    "iso:country":"NL",
    "sg:address":"Oelerwg 26",
    "sg:city":"Hengelo Ov",
    "sg:orig_category":"Webdesign Bureaus",
    "sg:phone":"+31 74 256 9333",
    "sg:postcode":"7555 GS",
    "sg:province":"Overijssel",
    "sg:website":"http://www.atraction-design.nl",
    "wof:name":"@Traction Design",
    "wof:placetype":"venue"
},
  "geometry": {"coordinates":[6.7781472206,52.259563446],"type":"Point"}
}