{
  "type": "Feature",
  "properties": {
    "addr:full":"Schipholweg 343 Badhoevedorp North Holland 1171 PL",
    "addr:housenumber":"343",
    "addr:postcode":"1171 pl",
    "addr:street":"Schipholweg",
    "iso:country":"NL",
    "sg:address":"Schipholweg 343",
    "sg:city":"Badhoevedorp",
    "sg:orig_category":"Kantoorapparatuur Gh",
    "sg:phone":"+31 20 658 4141",
    "sg:postcode":"1171 PL",
    "sg:province":"North Holland",
    "wof:name":"Kopieersystemen Nederland Bv",
    "wof:placetype":"venue"
},
  "geometry": {"coordinates":[4.7882070541,52.3307342529],"type":"Point"}
}