{
  "type": "Feature",
  "properties": {
    "iso:country":"NL",
    "sg:address":"Industriewg 35",
    "sg:city":"Den Helder",
    "sg:orig_category":"Olie - Exploratie",
    "sg:phone":"+31 223 639 639",
    "sg:postcode":"1785 AG",
    "sg:province":"Noord-Holland",
    "sg:website":"http://www.gazdefrance.com",
    "wof:name":"Gdf Ned Bv",
    "wof:placetype":"venue"
},
  "geometry": {"coordinates":[4.775688,52.944565],"type":"Point"}
}