{
  "type": "Feature",
  "properties": {
    "addr:full":"Blekerstraat 5 Katwijk Zh South Holland 2222 AN",
    "addr:housenumber":"5",
    "addr:postcode":"zh;2222 an",
    "addr:street":"Blekerstraat",
    "iso:country":"NL",
    "sg:address":"Blekerstraat 5",
    "sg:city":"Katwijk Zh",
    "sg:orig_category":"Fotolaboratoria",
    "sg:phone":"+31 71 402 8144",
    "sg:postcode":"2222 AN",
    "sg:province":"South Holland",
    "wof:name":"Renovo Film Bv",
    "wof:placetype":"venue"
},
  "geometry": {"coordinates":[4.433498,52.20182],"type":"Point"}
}