{
  "type": "Feature",
  "properties": {
    "addr:full":"Ysselln 139 Gouda Zuid-Holland 2806 TG",
    "addr:housenumber":"139",
    "addr:postcode":"2806 tg",
    "iso:country":"NL",
    "sg:address":"Ysselln 139",
    "sg:city":"Gouda",
    "sg:orig_category":"Bedrijfsopleidingen",
    "sg:phone":"+31 6 26122870",
    "sg:postcode":"2806 TG",
    "sg:province":"Zuid-Holland",
    "wof:name":"Middel, Het",
    "wof:placetype":"venue"
},
  "geometry": {"coordinates":[4.710715,52.010006],"type":"Point"}
}