{
  "type": "Feature",
  "properties": {
    "addr:full":"Merkenburg 13 Vlissingen Zeeland 4385 ET",
    "addr:housenumber":"13",
    "addr:postcode":"4385 et",
    "addr:street":"Merkenburg",
    "iso:country":"NL",
    "sg:address":"Merkenburg 13",
    "sg:city":"Vlissingen",
    "sg:orig_category":"Autorijscholen",
    "sg:phone":"+31 118 464 930",
    "sg:postcode":"4385 ET",
    "sg:province":"Zeeland",
    "wof:name":"Focke, Bob",
    "wof:placetype":"venue"
},
  "geometry": {"coordinates":[3.574558,51.461678],"type":"Point"}
}