{
  "type": "Feature",
  "properties": {
    "addr:full":"Vd Palmstr 24 Gouda Zuid-Holland 2802 VE",
    "addr:housenumber":"24",
    "addr:postcode":"2802",
    "addr:street":"Ve",
    "iso:country":"NL",
    "sg:address":"Vd Palmstr 24",
    "sg:city":"Gouda",
    "sg:classifiers":[
        {
            "category":"Wholesale",
            "subcategory":"Meat",
            "type":"Manufacturing & Wholesale Goods"
        }
    ],
    "sg:phone":"+31 182 517 281",
    "sg:postcode":"2802 VE",
    "sg:province":"Zuid-Holland",
    "sg:tags":[
        "hang-",
        "sluitwerk",
        "en"
    ],
    "wof:name":"Boudewijn",
    "wof:placetype":"venue"
},
  "geometry": {"coordinates":[4.703657,52.003429],"type":"Point"}
}