{
  "type": "Feature",
  "properties": {
    "addr:full":"Nyverheidswg 1 Medemblik Noord-Holland 1671 GC",
    "addr:housenumber":"1",
    "addr:postcode":"1671 gc",
    "addr:street":"Nyverheidswg",
    "iso:country":"NL",
    "sg:address":"Nyverheidswg 1",
    "sg:city":"Medemblik",
    "sg:orig_category":"Medische Installaties En Instrumenten",
    "sg:phone":"+31 227 546 680",
    "sg:postcode":"1671 GC",
    "sg:province":"Noord-Holland",
    "sg:website":"http://www.eurosteriel-medical.nl",
    "wof:name":"Eurosteriel Medical Bv",
    "wof:placetype":"venue"
},
  "geometry": {"coordinates":[5.093436,52.766384],"type":"Point"}
}