{
  "type": "Feature",
  "properties": {
    "addr:full":"Stadslaan 70 Hattem Gelderland 8051 NE",
    "addr:housenumber":"70",
    "addr:postcode":"8051",
    "addr:street":"Stadslaan;Gelderland;Ne",
    "iso:country":"NL",
    "sg:address":"Stadslaan 70",
    "sg:city":"Hattem",
    "sg:orig_category":"Boekhouders",
    "sg:phone":"+31 38 444 2335",
    "sg:postcode":"8051 NE",
    "sg:province":"Gelderland",
    "wof:name":"Raad Noord Veluwe",
    "wof:placetype":"venue"
},
  "geometry": {"coordinates":[6.064711,52.467178],"type":"Point"}
}