{
  "type": "Feature",
  "properties": {
    "addr:full":"Merbau 48 Dordrecht Zuid-Holland 3315 RP",
    "addr:housenumber":"48",
    "addr:postcode":"3315 rp",
    "addr:street":"Merbau",
    "iso:country":"NL",
    "sg:address":"Merbau 48",
    "sg:city":"Dordrecht",
    "sg:orig_category":"Fotoreportages",
    "sg:phone":"+31 78 621 1709",
    "sg:postcode":"3315 RP",
    "sg:province":"Zuid-Holland",
    "sg:website":"http://members.rott.chello.nl/tvink",
    "wof:name":"Theo Vink Fotografie",
    "wof:placetype":"venue"
},
  "geometry": {"coordinates":[4.713563,51.804173],"type":"Point"}
}