{
  "type": "Feature",
  "properties": {
    "iso:country":"NL",
    "sg:address":"Middenveer 58",
    "sg:city":"Sliedrecht",
    "sg:classifiers":[
        {
            "category":"Personal",
            "subcategory":"Nail Salon",
            "type":"Services"
        }
    ],
    "sg:phone":"+31 184 410 649",
    "sg:postcode":"3361 TL",
    "sg:province":"Zuid-Holland",
    "sg:tags":[
        "pedicure"
    ],
    "wof:name":"Graafland, G",
    "wof:placetype":"venue"
},
  "geometry": {"coordinates":[4.783213,51.816959],"type":"Point"}
}