{
  "type": "Feature",
  "properties": {
    "addr:full":"Beekstr 62A Meerssen Limburg 6231 LH",
    "addr:housenumber":"62a",
    "addr:postcode":"6231 lh",
    "addr:street":"Beekstr",
    "iso:country":"NL",
    "sg:address":"Beekstr 62A",
    "sg:city":"Meerssen",
    "sg:orig_category":"Kinderkleding",
    "sg:phone":"+31 43 364 2046",
    "sg:postcode":"6231 LH",
    "sg:province":"Limburg",
    "wof:name":"Pompidou",
    "wof:placetype":"venue"
},
  "geometry": {"coordinates":[5.753014,50.885056],"type":"Point"}
}