{
  "type": "Feature",
  "properties": {
    "iso:country":"NL",
    "sg:address":"Beukenln 19",
    "sg:city":"Dronten",
    "sg:orig_category":"Adviesbureaus Bedrijfsorganisatie",
    "sg:phone":"+31 321 337 849",
    "sg:postcode":"8253 AK",
    "sg:province":"Flevoland",
    "wof:name":"Jaarsveld Faba, Van",
    "wof:placetype":"venue"
},
  "geometry": {"coordinates":[5.761847,52.576595],"type":"Point"}
}