{
  "type": "Feature",
  "properties": {
    "addr:full":"Varkevisserstr 220A Katwyk Zh Zuid-Holland 2225 LK",
    "addr:housenumber":"220a",
    "addr:postcode":"2225 lk",
    "addr:street":"Katwyk",
    "iso:country":"NL",
    "sg:address":"Varkevisserstr 220A",
    "sg:city":"Katwyk Zh",
    "sg:orig_category":"Schelpenhandel",
    "sg:phone":"+31 71 401 5917",
    "sg:postcode":"2225 LK",
    "sg:province":"Zuid-Holland",
    "wof:name":"Rijn, H Van",
    "wof:placetype":"venue"
},
  "geometry": {"coordinates":[4.42057,52.187599],"type":"Point"}
}