{
  "type": "Feature",
  "properties": {
    "addr:full":"Kosmonaut 16 Amersfoort Utrecht 3824 MK",
    "addr:housenumber":"16",
    "addr:postcode":"3824",
    "addr:street":"Kosmonaut",
    "iso:country":"NL",
    "sg:address":"Kosmonaut 16",
    "sg:city":"Amersfoort",
    "sg:classifiers":[
        {
            "category":"Home & Garden",
            "subcategory":"Hardware",
            "type":"Retail Goods"
        }
    ],
    "sg:phone":"+31 33 456 4037",
    "sg:postcode":"3824 MK",
    "sg:province":"Utrecht",
    "sg:tags":[
        "machine",
        "-",
        "metaalbewerking"
    ],
    "sg:website":"http://www.ijzeron.nl",
    "wof:name":"Ijzeron",
    "wof:placetype":"venue"
},
  "geometry": {"coordinates":[5.391139,52.197735],"type":"Point"}
}