{
  "type": "Feature",
  "properties": {
    "addr:full":"Postbus 1169 Hilversum North Holland 1200 BD",
    "addr:housenumber":"1169",
    "addr:postcode":"1200 bd",
    "addr:street":"Postbus",
    "iso:country":"NL",
    "sg:address":"Postbus 1169",
    "sg:city":"Hilversum",
    "sg:orig_category":"Verzekeringen - Verzekeringskantoren",
    "sg:phone":"+31 6 51501097",
    "sg:postcode":"1200 BD",
    "sg:province":"North Holland",
    "wof:name":"Eg",
    "wof:placetype":"venue"
},
  "geometry": {"coordinates":[5.171,52.223991],"type":"Point"}
}