{
  "type": "Feature",
  "properties": {
    "iso:country":"NL",
    "sg:address":"Havenstr 11",
    "sg:city":"Wassenaar",
    "sg:orig_category":"Schilders",
    "sg:phone":"+31 70 511 6856",
    "sg:postcode":"2242 LZ",
    "sg:province":"Zuid-Holland",
    "wof:name":"Raaphorst, B C W",
    "wof:placetype":"venue"
},
  "geometry": {"coordinates":[4.396397,52.146484],"type":"Point"}
}