{
  "type": "Feature",
  "properties": {
    "addr:full":"Reigerpad 21 Soest Utrecht 3766 XA",
    "addr:housenumber":"21",
    "addr:postcode":"3766 xa",
    "addr:street":"Reigerpad",
    "iso:country":"NL",
    "sg:address":"Reigerpad 21",
    "sg:city":"Soest",
    "sg:orig_category":"Metaalwerken",
    "sg:phone":"+31 35 525 5209",
    "sg:postcode":"3766 XA",
    "sg:province":"Utrecht",
    "wof:name":"Bert Van De Vlag",
    "wof:placetype":"venue"
},
  "geometry": {"coordinates":[5.279743,52.164234],"type":"Point"}
}