{
  "type": "Feature",
  "properties": {
    "addr:full":"A Agnesstr 30 Leiden South Holland 2316 EV",
    "addr:housenumber":"30",
    "addr:postcode":"2316 ev",
    "iso:country":"NL",
    "sg:address":"A Agnesstr 30",
    "sg:city":"Leiden",
    "sg:orig_category":"Kinderopvang",
    "sg:phone":"+31 71 521 2254",
    "sg:postcode":"2316 EV",
    "sg:province":"South Holland",
    "wof:name":"Peuterhaven, De",
    "wof:placetype":"venue"
},
  "geometry": {"coordinates":[4.503482,52.16798],"type":"Point"}
}