{
  "type": "Feature",
  "properties": {
    "addr:full":"Stoofdijk 28 Dinteloord North Brabant 4671 CS",
    "addr:housenumber":"28",
    "addr:postcode":"4671 cs",
    "addr:street":"Stoofdijk",
    "iso:country":"NL",
    "sg:address":"Stoofdijk 28",
    "sg:city":"Dinteloord",
    "sg:orig_category":"Verhuisdiensten",
    "sg:phone":"+31 167 524 823",
    "sg:postcode":"4671 CS",
    "sg:province":"North Brabant",
    "wof:name":"E. Van Der Veken Transportdiensten",
    "wof:placetype":"venue"
},
  "geometry": {"coordinates":[4.370741,51.638962],"type":"Point"}
}