{
  "type": "Feature",
  "properties": {
    "addr:full":"Veckdk 21 Vierpolders South Holland 3237 LT",
    "addr:housenumber":"21",
    "addr:postcode":"3237 lt",
    "addr:street":"Veckdk",
    "iso:country":"NL",
    "sg:address":"Veckdk 21",
    "sg:city":"Vierpolders",
    "sg:orig_category":"Loonbedrijven",
    "sg:phone":"+31 181 416 760",
    "sg:postcode":"3237 LT",
    "sg:province":"South Holland",
    "wof:name":"Hokke & Zn",
    "wof:placetype":"venue"
},
  "geometry": {"coordinates":[4.17768,51.889091],"type":"Point"}
}