{
  "type": "Feature",
  "properties": {
    "addr:full":"Hoofdstraat 8 De Lier Zuid-Holland 2678 CK",
    "addr:housenumber":"8",
    "addr:postcode":"2678 ck",
    "addr:street":"Hoofdstraat",
    "iso:country":"NL",
    "sg:address":"Hoofdstraat 8",
    "sg:city":"De Lier",
    "sg:orig_category":"Banken And Kredietinstellingen",
    "sg:phone":"+31 174 512 411",
    "sg:postcode":"2678 CK",
    "sg:province":"Zuid-Holland",
    "wof:name":"Postkantoor",
    "wof:placetype":"venue"
},
  "geometry": {"coordinates":[4.247457,51.973618],"type":"Point"}
}