{
  "type": "Feature",
  "properties": {
    "addr:full":"Velperweg 99 Arnhem Gelderland 6824 HH",
    "addr:housenumber":"99",
    "addr:postcode":"6824 hh",
    "addr:street":"Velperweg",
    "iso:country":"NL",
    "sg:address":"Velperweg 99",
    "sg:city":"Arnhem",
    "sg:orig_category":"Juridische Dienstverlening",
    "sg:phone":"+31 26 368 7520",
    "sg:postcode":"6824 HH",
    "sg:province":"Gelderland",
    "wof:name":"Vereenigde Octrooibureaux",
    "wof:placetype":"venue"
},
  "geometry": {"coordinates":[5.936255,51.98946],"type":"Point"}
}