{
  "type": "Feature",
  "properties": {
    "iso:country":"NL",
    "sg:address":"Voorkamp 31",
    "sg:city":"Beets Nh",
    "sg:orig_category":"Boekhouders",
    "sg:phone":"+31 299 401 838",
    "sg:postcode":"1475 JN",
    "sg:province":"Noord-Holland",
    "wof:name":"E.J. Timmerman",
    "wof:placetype":"venue"
},
  "geometry": {"coordinates":[4.97685,52.589153],"type":"Point"}
}