{
  "type": "Feature",
  "properties": {
    "addr:full":"Sesamstr 5 Enschede NL.08 7547 AL",
    "addr:housenumber":"5",
    "addr:postcode":"7547",
    "addr:street":"Sesamstr;Al",
    "iso:country":"NL",
    "sg:address":"Sesamstr 5",
    "sg:city":"Enschede",
    "sg:classifiers":[
        {
            "category":"Home & Garden",
            "subcategory":"Garden Supply",
            "type":"Retail Goods"
        }
    ],
    "sg:phone":"+31 53 431 1237",
    "sg:postcode":"7547 AL",
    "sg:province":"NL.08",
    "sg:tags":[
        "zand",
        "en",
        "grind"
    ],
    "wof:name":"Twenthe Bv",
    "wof:placetype":"venue"
},
  "geometry": {"coordinates":[6.858523,52.222176],"type":"Point"}
}