{
  "type": "Feature",
  "properties": {
    "addr:full":"Hemonystraat 26/1 Amsterdam North Holland 1074 BR",
    "addr:housenumber":"26 / 1",
    "addr:postcode":"1074 br",
    "addr:street":"Hemonystraat",
    "iso:country":"NL",
    "sg:address":"Hemonystraat 26/1",
    "sg:city":"Amsterdam",
    "sg:orig_category":"Vertaal- And Tolkenbureaus",
    "sg:phone":"+31 20 676 7850",
    "sg:postcode":"1074 BR",
    "sg:province":"North Holland",
    "wof:name":"E. Rientjes",
    "wof:placetype":"venue"
},
  "geometry": {"coordinates":[4.902239,52.357067],"type":"Point"}
}