{
  "type": "Feature",
  "properties": {
    "addr:full":"Wieldrechtsewg 28 Dordrecht Zuid-Holland 3316 BG",
    "addr:housenumber":"28",
    "addr:postcode":"3316",
    "addr:street":"Wieldrechtsewg",
    "iso:country":"NL",
    "sg:address":"Wieldrechtsewg 28",
    "sg:city":"Dordrecht",
    "sg:classifiers":[
        {
            "category":"Home & Garden",
            "subcategory":"Garden Supply",
            "type":"Retail Goods"
        }
    ],
    "sg:phone":"+31 78 691 9572",
    "sg:postcode":"3316 BG",
    "sg:province":"Zuid-Holland",
    "sg:tags":[
        "zand",
        "en",
        "grind"
    ],
    "wof:name":"Hto Dordrecht Vof",
    "wof:placetype":"venue"
},
  "geometry": {"coordinates":[4.646015,51.785309],"type":"Point"}
}