{
  "type": "Feature",
  "properties": {
    "addr:full":"Lierderholthuisweg 21 Lierderholthuis NL.08 8144 RG",
    "addr:housenumber":"21;nl.08",
    "addr:postcode":"8144 rg",
    "addr:street":"Lierderholthuisweg",
    "iso:country":"NL",
    "sg:address":"Lierderholthuisweg 21",
    "sg:city":"Lierderholthuis",
    "sg:orig_category":"Levende Dieren Gh",
    "sg:phone":"+31 572 391 221",
    "sg:postcode":"8144 RG",
    "sg:province":"NL.08",
    "wof:name":"Kalverhandel G J Van Dam",
    "wof:placetype":"venue"
},
  "geometry": {"coordinates":[6.192746,52.431808],"type":"Point"}
}