{
  "type": "Feature",
  "properties": {
    "addr:full":"Op Den Bosch 4 Baarlo Lb Limburg 5991 NE",
    "addr:housenumber":"4;5991",
    "addr:postcode":"lb;ne",
    "addr:street":"Op Den Bosch",
    "iso:country":"NL",
    "sg:address":"Op Den Bosch 4",
    "sg:city":"Baarlo Lb",
    "sg:orig_category":"Video - Faciliteiten En Producties",
    "sg:phone":"+31 77 477 0265",
    "sg:postcode":"5991 NE",
    "sg:province":"Limburg",
    "sg:website":"http://www.rovision-video.nl",
    "wof:name":"Rovision",
    "wof:placetype":"venue"
},
  "geometry": {"coordinates":[6.066667,51.316639],"type":"Point"}
}