{
  "type": "Feature",
  "properties": {
    "iso:country":"NL",
    "sg:address":"Meester Lovinkln 30",
    "sg:city":"Doetinchem",
    "sg:classifiers":[
        {
            "category":"Education",
            "subcategory":"School",
            "type":"Public Place"
        }
    ],
    "sg:phone":"+31 314 324 168",
    "sg:postcode":"7004 BJ",
    "sg:province":"Gelderland",
    "sg:tags":[
        "studiebegeleiding",
        "en",
        "school-"
    ],
    "wof:name":"Huiswerk Begeleidings Instituut",
    "wof:placetype":"venue"
},
  "geometry": {"coordinates":[6.307673,51.951942],"type":"Point"}
}