{
  "type": "Feature",
  "properties": {
    "addr:full":"Steenweg 22 Utrecht Utrecht 3511 JR",
    "addr:housenumber":"22",
    "addr:postcode":"3511 jr",
    "addr:street":"Steenweg",
    "iso:country":"NL",
    "sg:address":"Steenweg 22",
    "sg:city":"Utrecht",
    "sg:classifiers":[
        {
            "category":"Shopping",
            "subcategory":"Gifts & Souvenirs",
            "type":"Retail Goods"
        }
    ],
    "sg:phone":"+31 30 234 3470",
    "sg:postcode":"3511 JR",
    "sg:province":"Utrecht",
    "sg:tags":[
        "geschenken"
    ],
    "wof:name":"La Parisienne Glasboutique",
    "wof:placetype":"venue"
},
  "geometry": {"coordinates":[5.118643,52.090775],"type":"Point"}
}