{
  "type": "Feature",
  "properties": {
    "addr:full":"Past Vd Rietstr 45 Molenschot North Brabant 5124 RR",
    "addr:housenumber":"45",
    "addr:postcode":"5124 rr",
    "addr:street":"Past",
    "iso:country":"NL",
    "sg:address":"Past Vd Rietstr 45",
    "sg:city":"Molenschot",
    "sg:orig_category":"Banken",
    "sg:phone":"+31 161 412 223",
    "sg:postcode":"5124 RR",
    "sg:province":"North Brabant",
    "wof:name":"Cvb",
    "wof:placetype":"venue"
},
  "geometry": {"coordinates":[4.881122,51.572117],"type":"Point"}
}