{
  "type": "Feature",
  "properties": {
    "addr:full":"Soestdijksekade 531 'S Gravenhage South Holland 2574 BE",
    "addr:housenumber":"531 '",
    "addr:postcode":"2574",
    "addr:street":"Soestdijksekade",
    "iso:country":"NL",
    "sg:address":"Soestdijksekade 531",
    "sg:city":"'S Gravenhage",
    "sg:orig_category":"Verlichting And Huishoudartikelen",
    "sg:phone":"+31 70 329 0833",
    "sg:postcode":"2574 BE",
    "sg:province":"South Holland",
    "wof:name":"P.J. Bochove",
    "wof:placetype":"venue"
},
  "geometry": {"coordinates":[4.276167,52.061562],"type":"Point"}
}