{
  "type": "Feature",
  "properties": {
    "addr:full":"L Bernsteinstr 1 Almere Flevoland 1311 KP",
    "addr:housenumber":"1",
    "addr:postcode":"1311 kp",
    "addr:street":"Flevoland",
    "iso:country":"NL",
    "sg:address":"L Bernsteinstr 1",
    "sg:city":"Almere",
    "sg:orig_category":"Kunsthandel",
    "sg:phone":"+31 36 536 8314",
    "sg:postcode":"1311 KP",
    "sg:province":"Flevoland",
    "wof:name":"Kunst In Opdracht",
    "wof:placetype":"venue"
},
  "geometry": {"coordinates":[5.175464,52.369705],"type":"Point"}
}