{
  "type": "Feature",
  "properties": {
    "iso:country":"NL",
    "sg:address":"Buitenvaart 1711",
    "sg:city":"Hoogeveen",
    "sg:orig_category":"Bestratingen",
    "sg:phone":"+31 6 51808426",
    "sg:postcode":"7905 SN",
    "sg:province":"Provincie Drenthe",
    "wof:name":"Mekro Bestratingen",
    "wof:placetype":"venue"
},
  "geometry": {"coordinates":[6.508267,52.709129],"type":"Point"}
}