{
  "type": "Feature",
  "properties": {
    "addr:full":"Patrimoniumwg 57 Heelsum Gelderland 6866 AW",
    "addr:housenumber":"57",
    "addr:postcode":"6866 aw",
    "addr:street":"Patrimoniumwg;Gelderland",
    "iso:country":"NL",
    "sg:address":"Patrimoniumwg 57",
    "sg:city":"Heelsum",
    "sg:orig_category":"Plafonds",
    "sg:phone":"+31 317 317 650",
    "sg:postcode":"6866 AW",
    "sg:province":"Gelderland",
    "wof:name":"Dam, Van Den",
    "wof:placetype":"venue"
},
  "geometry": {"coordinates":[5.748603,51.982063],"type":"Point"}
}