{
  "type": "Feature",
  "properties": {
    "iso:country":"NL",
    "sg:address":"Jislumerdk 15",
    "sg:city":"Burdaard",
    "sg:orig_category":"Banken",
    "sg:phone":"+31 519 332 230",
    "sg:postcode":"9111 HC",
    "sg:province":"Provincie Friesland",
    "sg:website":"http://www.rabobank.nl",
    "wof:name":"Rabobank",
    "wof:placetype":"venue"
},
  "geometry": {"coordinates":[5.877561,53.29731],"type":"Point"}
}