{
  "type": "Feature",
  "properties": {
    "addr:full":"Ewoltstede 24 Gorssel Gelderland 7213 TD",
    "addr:housenumber":"24",
    "addr:postcode":"7213 td",
    "addr:street":"Ewoltstede;Gelderland",
    "iso:country":"NL",
    "sg:address":"Ewoltstede 24",
    "sg:city":"Gorssel",
    "sg:orig_category":"Vertaalbureaus",
    "sg:phone":"+31 575 494 561",
    "sg:postcode":"7213 TD",
    "sg:province":"Gelderland",
    "wof:name":"Dk Promotion",
    "wof:placetype":"venue"
},
  "geometry": {"coordinates":[6.204585,52.207695],"type":"Point"}
}