{
  "type": "Feature",
  "properties": {
    "addr:full":"Brilliant Starstr 18 Bovenkarspel Noord-Holland 1611 DS",
    "addr:housenumber":"18",
    "addr:postcode":"1611 ds",
    "iso:country":"NL",
    "sg:address":"Brilliant Starstr 18",
    "sg:city":"Bovenkarspel",
    "sg:orig_category":"Handenarbeid",
    "sg:phone":"+31 228 513 007",
    "sg:postcode":"1611 DS",
    "sg:province":"Noord-Holland",
    "sg:website":"http://www.studiokrealine.nl",
    "wof:name":"Studiokrealine",
    "wof:placetype":"venue"
},
  "geometry": {"coordinates":[5.249815,52.693016],"type":"Point"}
}