{
  "type": "Feature",
  "properties": {
    "iso:country":"NL",
    "sg:address":"Hoefweg 103",
    "sg:city":"Bleiswijk",
    "sg:orig_category":"Schilderwerk",
    "sg:phone":"+31 10 521 4150",
    "sg:postcode":"2665 CD",
    "sg:province":"Zuid-Holland",
    "wof:name":"John Ploeg",
    "wof:placetype":"venue"
},
  "geometry": {"coordinates":[4.532954,52.016205],"type":"Point"}
}