{
  "type": "Feature",
  "properties": {
    "addr:full":"Groesbeeksedwarsweg 227 Nijmegen Gelderland 6521 DJ",
    "addr:housenumber":"227",
    "addr:postcode":"6521 dj",
    "addr:street":"Groesbeeksedwarsweg;Gelderland",
    "iso:country":"NL",
    "sg:address":"Groesbeeksedwarsweg 227",
    "sg:city":"Nijmegen",
    "sg:orig_category":"Reclamebureaus",
    "sg:phone":"+31 24 360 5562",
    "sg:postcode":"6521 DJ",
    "sg:province":"Gelderland",
    "wof:name":"Van Oorschot Commedia",
    "wof:placetype":"venue"
},
  "geometry": {"coordinates":[5.871587,51.836067],"type":"Point"}
}