{
  "type": "Feature",
  "properties": {
    "addr:full":"Vissendreef 119 Zoetermeer Zuid-Holland 2724 EJ",
    "addr:housenumber":"119",
    "addr:postcode":"2724 ej",
    "addr:street":"Vissendreef",
    "iso:country":"NL",
    "sg:address":"Vissendreef 119",
    "sg:city":"Zoetermeer",
    "sg:orig_category":"Binnenhuisarchitecten",
    "sg:phone":"+31 79 341 2059",
    "sg:postcode":"2724 EJ",
    "sg:province":"Zuid-Holland",
    "wof:name":"Cornelis & Sevink Advies Vof",
    "wof:placetype":"venue"
},
  "geometry": {"coordinates":[4.511471,52.063431],"type":"Point"}
}