{
  "type": "Feature",
  "properties": {
    "addr:full":"Waltherln 7 Bussum Noord-Holland 1402 XJ",
    "addr:housenumber":"7",
    "addr:postcode":"1402 xj",
    "addr:street":"Waltherln",
    "iso:country":"NL",
    "sg:address":"Waltherln 7",
    "sg:city":"Bussum",
    "sg:orig_category":"Adviesbureaus Bouwkunde",
    "sg:phone":"+31 35 691 5929",
    "sg:postcode":"1402 XJ",
    "sg:province":"Noord-Holland",
    "wof:name":"Kooy, J N M",
    "wof:placetype":"venue"
},
  "geometry": {"coordinates":[5.162605,52.276829],"type":"Point"}
}