{
  "type": "Feature",
  "properties": {
    "addr:full":"Aan Het Broek 3 Sittard Limburg 6137 TJ",
    "addr:housenumber":"3",
    "addr:postcode":"6137 tj",
    "addr:street":"Aan Het Broek",
    "iso:country":"NL",
    "sg:address":"Aan Het Broek 3",
    "sg:city":"Sittard",
    "sg:orig_category":"Schoenen - Reparaties",
    "sg:phone":"+31 46 451 5903",
    "sg:postcode":"6137 TJ",
    "sg:province":"Limburg",
    "wof:name":"Willems, P J",
    "wof:placetype":"venue"
},
  "geometry": {"coordinates":[5.892658,51.005238],"type":"Point"}
}