{
  "type": "Feature",
  "properties": {
    "addr:full":"Straatwg 66A Breukelen Ut Utrecht 3621 BR",
    "addr:housenumber":"66a",
    "addr:postcode":"3621 br",
    "addr:street":"Straatwg",
    "iso:country":"NL",
    "sg:address":"Straatwg 66A",
    "sg:city":"Breukelen Ut",
    "sg:orig_category":"Milieu",
    "sg:phone":"+31 346 260 600",
    "sg:postcode":"3621 BR",
    "sg:province":"Utrecht",
    "wof:name":"Milieudienst Nw Utrecht",
    "wof:placetype":"venue"
},
  "geometry": {"coordinates":[5.007207,52.167686],"type":"Point"}
}