{
  "type": "Feature",
  "properties": {
    "addr:full":"Kromhout 95 Dordrecht South Holland 3311 RE",
    "addr:housenumber":"95",
    "addr:postcode":"3311 re",
    "addr:street":"Kromhout",
    "iso:country":"NL",
    "sg:address":"Kromhout 95",
    "sg:city":"Dordrecht",
    "sg:orig_category":"Verenigingen En Stichtingen",
    "sg:phone":"+31 78 614 6173",
    "sg:postcode":"3311 RE",
    "sg:province":"South Holland",
    "sg:website":"http://www.revivalfellowship.org/holland",
    "wof:name":"Revival Fellowship Holland",
    "wof:placetype":"venue"
},
  "geometry": {"coordinates":[4.673747,51.814308],"type":"Point"}
}