{
  "type": "Feature",
  "properties": {
    "addr:full":"Rustenburgerstr 10 Amsterdam Noord-Holland 1074 ET",
    "addr:housenumber":"10",
    "addr:postcode":"1074 et",
    "addr:street":"Rustenburgerstr",
    "iso:country":"NL",
    "sg:address":"Rustenburgerstr 10",
    "sg:city":"Amsterdam",
    "sg:orig_category":"Drukkerijen",
    "sg:phone":"+31 20 673 8881",
    "sg:postcode":"1074 ET",
    "sg:province":"Noord-Holland",
    "wof:name":"Print 81 Drukkerij Bv",
    "wof:placetype":"venue"
},
  "geometry": {"coordinates":[4.90588,52.354141],"type":"Point"}
}