{
  "type": "Feature",
  "properties": {
    "addr:full":"G. Van Dort Kroonweg 12 Waddinxveen Zuid-Holland 2742 KG",
    "addr:housenumber":"12",
    "addr:postcode":"2742 kg",
    "addr:street":"G. Van Dort Kroonweg",
    "iso:country":"NL",
    "sg:address":"G. Van Dort Kroonweg 12",
    "sg:city":"Waddinxveen",
    "sg:orig_category":"Huizensloop And Bouwrijp Maken",
    "sg:phone":"+31 182 631 216",
    "sg:postcode":"2742 KG",
    "sg:province":"Zuid-Holland",
    "wof:name":"Hamstra Vof",
    "wof:placetype":"venue"
},
  "geometry": {"coordinates":[4.624838,52.026661],"type":"Point"}
}