{
  "type": "Feature",
  "properties": {
    "addr:full":"De Rypgr 12-3 Amsterdam New York 1055 VS",
    "addr:housenumber":"12-3;1055",
    "addr:postcode":"vs",
    "iso:country":"NL",
    "sg:address":"De Rypgr 12-3",
    "sg:city":"Amsterdam",
    "sg:orig_category":"Verbouwingen",
    "sg:phone":"+31 6 14192383",
    "sg:postcode":"1055 VS",
    "sg:province":"New York",
    "wof:name":"Travail Paul De Bruyne",
    "wof:placetype":"venue"
},
  "geometry": {"coordinates":[-74.11232800000001,42.977543],"type":"Point"}
}