{
  "type": "Feature",
  "properties": {
    "addr:full":"De Slufter 32 Wieringerwerf Noord-Holland 1771 JB",
    "addr:housenumber":"32",
    "addr:postcode":"1771 jb",
    "addr:street":"De Slufter",
    "iso:country":"NL",
    "sg:address":"De Slufter 32",
    "sg:city":"Wieringerwerf",
    "sg:orig_category":"Jachten - Schilderwerken En Onderhoud",
    "sg:phone":"+31 227 602 643",
    "sg:postcode":"1771 JB",
    "sg:province":"Noord-Holland",
    "wof:name":"Douwe De Jonge, Jachtschilders",
    "wof:placetype":"venue"
},
  "geometry": {"coordinates":[5.031795,52.854973],"type":"Point"}
}