{
  "type": "Feature",
  "properties": {
    "addr:full":"Markt 15 Roosendaal North Brabant 4701 PA",
    "addr:housenumber":"15",
    "addr:postcode":"4701 pa",
    "addr:street":"Markt",
    "iso:country":"NL",
    "sg:address":"Markt 15",
    "sg:city":"Roosendaal",
    "sg:orig_category":"Fotostudio'S And Fotografen",
    "sg:phone":"+31 165 533 327",
    "sg:postcode":"4701 PA",
    "sg:province":"North Brabant",
    "wof:name":"Hein Manne Vakfotografie",
    "wof:placetype":"venue"
},
  "geometry": {"coordinates":[4.45588,51.532909],"type":"Point"}
}