{
  "type": "Feature",
  "properties": {
    "addr:full":"Veldkamp 44 Havelte Drenthe 7971 BW",
    "addr:housenumber":"44",
    "addr:postcode":"7971 bw",
    "addr:street":"Veldkamp",
    "iso:country":"NL",
    "sg:address":"Veldkamp 44",
    "sg:city":"Havelte",
    "sg:orig_category":"Public Relationbureaus",
    "sg:phone":"+31 521 343 069",
    "sg:postcode":"7971 BW",
    "sg:province":"Drenthe",
    "wof:name":"Kees Vingerhoets Public Relations",
    "wof:placetype":"venue"
},
  "geometry": {"coordinates":[6.233321,52.775005],"type":"Point"}
}