{
  "type": "Feature",
  "properties": {
    "addr:full":"Boletenpln 2 Asten Noord-Brabant 5721 NE",
    "addr:housenumber":"2",
    "addr:postcode":"5721 ne",
    "addr:street":"Boletenpln",
    "iso:country":"NL",
    "sg:address":"Boletenpln 2",
    "sg:city":"Asten",
    "sg:orig_category":"Fotoreportages",
    "sg:phone":"+31 493 697 521",
    "sg:postcode":"5721 NE",
    "sg:province":"Noord-Brabant",
    "wof:name":"Creatief",
    "wof:placetype":"venue"
},
  "geometry": {"coordinates":[5.756756,51.407196],"type":"Point"}
}