{
  "type": "Feature",
  "properties": {
    "addr:full":"Langestr 32 Nykerk Gld Gelderland 3861 BN",
    "addr:housenumber":"32",
    "addr:postcode":"3861 bn",
    "addr:street":"Langestr;Gld Gelderland",
    "iso:country":"NL",
    "sg:address":"Langestr 32",
    "sg:city":"Nykerk Gld",
    "sg:orig_category":"Verenigingen En Stichtingen",
    "sg:phone":"+31 33 247 5555",
    "sg:postcode":"3861 BN",
    "sg:province":"Gelderland",
    "wof:name":"Bakkersbelang, Sticht",
    "wof:placetype":"venue"
},
  "geometry": {"coordinates":[5.4831,52.221569],"type":"Point"}
}