{
  "type": "Feature",
  "properties": {
    "addr:full":"Zwaluw 92 Etten Leur Noord-Brabant 4872 SL",
    "addr:housenumber":"92",
    "addr:postcode":"4872 sl",
    "addr:street":"Zwaluw",
    "iso:country":"NL",
    "sg:address":"Zwaluw 92",
    "sg:city":"Etten Leur",
    "sg:orig_category":"Administratie- En Boekhoudkantoren",
    "sg:phone":"+31 76 501 2634",
    "sg:postcode":"4872 SL",
    "sg:province":"Noord-Brabant",
    "wof:name":"Frijters, M J J M",
    "wof:placetype":"venue"
},
  "geometry": {"coordinates":[4.662199,51.574032],"type":"Point"}
}