{
  "type": "Feature",
  "properties": {
    "addr:full":"Postbus 40078 Zwolle NL.08 8004 DB",
    "addr:postcode":"40078;8004 db",
    "addr:street":"Postbus",
    "iso:country":"NL",
    "sg:address":"Postbus 40078",
    "sg:city":"Zwolle",
    "sg:orig_category":"Bedrijfsopleidingen",
    "sg:phone":"+31 6 29426482",
    "sg:postcode":"8004 DB",
    "sg:province":"NL.08",
    "sg:website":"http://www.selectrain.nl",
    "wof:name":"Selectrain",
    "wof:placetype":"venue"
},
  "geometry": {"coordinates":[6.09243,52.51223],"type":"Point"}
}