{
  "type": "Feature",
  "properties": {
    "addr:full":"Kapelweg 2 Eersel Noord-Brabant 5521 JJ",
    "addr:housenumber":"2",
    "addr:postcode":"5521 jj",
    "addr:street":"Kapelweg",
    "iso:country":"NL",
    "sg:address":"Kapelweg 2",
    "sg:city":"Eersel",
    "sg:orig_category":"Musea And Historische Gebouwen",
    "sg:phone":"+31 497 515 649",
    "sg:postcode":"5521 JJ",
    "sg:province":"Noord-Brabant",
    "wof:name":"Museum De Acht Zaligheden",
    "wof:placetype":"venue"
},
  "geometry": {"coordinates":[5.311751,51.353519],"type":"Point"}
}