{
  "type": "Feature",
  "properties": {
    "iso:country":"NL",
    "sg:address":"Prunusln 2",
    "sg:city":"Nieuwe Pekela",
    "sg:orig_category":"Bejaarden - Verzorgingstehuizen",
    "sg:phone":"+31 597 645 250",
    "sg:postcode":"9663 CW",
    "sg:province":"Groningen",
    "wof:name":"Clockstede",
    "wof:placetype":"venue"
},
  "geometry": {"coordinates":[6.956866,53.070999],"type":"Point"}
}