{
  "type": "Feature",
  "properties": {
    "addr:full":"Produktiewg 28 Zoeterwoude Zuid-Holland 2382 PC",
    "addr:housenumber":"28",
    "addr:postcode":"2382 pc",
    "addr:street":"Produktiewg",
    "iso:country":"NL",
    "sg:address":"Produktiewg 28",
    "sg:city":"Zoeterwoude",
    "sg:orig_category":"Kunststof Ramen",
    "sg:phone":"+31 71 541 5137",
    "sg:postcode":"2382 PC",
    "sg:province":"Zuid-Holland",
    "wof:name":"Hulst, B Van Der",
    "wof:placetype":"venue"
},
  "geometry": {"coordinates":[4.516453,52.139393],"type":"Point"}
}