{
  "type": "Feature",
  "properties": {
    "addr:full":"Inundatiedijk Zuid 21 Tiel Gelderland 4006 PD",
    "addr:housenumber":"21",
    "addr:postcode":"4006 pd",
    "addr:street":"Zuid;Gelderland",
    "iso:country":"NL",
    "sg:address":"Inundatiedijk Zuid 21",
    "sg:city":"Tiel",
    "sg:orig_category":"Metaalafval, Schrootrecycling And Sloperijen",
    "sg:phone":"+31 344 617 114",
    "sg:postcode":"4006 PD",
    "sg:province":"Gelderland",
    "wof:name":"C Damen",
    "wof:placetype":"venue"
},
  "geometry": {"coordinates":[5.41621,51.87698],"type":"Point"}
}