{
  "type": "Feature",
  "properties": {
    "addr:full":"Dukdalfweg 10 Amsterdam Noord-Holland 1041 BD",
    "addr:housenumber":"10",
    "addr:postcode":"1041 bd",
    "addr:street":"Dukdalfweg",
    "iso:country":"NL",
    "sg:address":"Dukdalfweg 10",
    "sg:city":"Amsterdam",
    "sg:orig_category":"Goederenvervoer Over De Weg",
    "sg:phone":"+31 20 681 5008",
    "sg:postcode":"1041 BD",
    "sg:province":"Noord-Holland",
    "wof:name":"Dutch Sneltransport",
    "wof:placetype":"venue"
},
  "geometry": {"coordinates":[4.825645,52.415627],"type":"Point"}
}