{
  "type": "Feature",
  "properties": {
    "iso:country":"NL",
    "sg:address":"P.A. De Kok-Plein 130",
    "sg:city":"Dordrecht",
    "sg:classifiers":[
        {
            "category":"Bakery",
            "type":"Food & Drink"
        }
    ],
    "sg:phone":"+31 78 617 3009",
    "sg:postcode":"3318 JW",
    "sg:province":"Zuid-Holland",
    "sg:tags":[
        "brood",
        "banket"
    ],
    "wof:name":"Echte Bakker Korteweg",
    "wof:placetype":"venue"
},
  "geometry": {"coordinates":[4.67641,51.784904],"type":"Point"}
}