{
  "type": "Feature",
  "properties": {
    "iso:country":"NL",
    "sg:address":"Kerkstr 20",
    "sg:city":"Wierden",
    "sg:classifiers":[
        {
            "category":"Food & Beverages",
            "subcategory":"Bakery",
            "type":"Retail Goods"
        }
    ],
    "sg:phone":"+31 546 571 201",
    "sg:postcode":"7641 BT",
    "sg:province":"Overijssel",
    "sg:tags":[
        "brood",
        "en",
        "banket"
    ],
    "wof:name":"Kamphuis",
    "wof:placetype":"venue"
},
  "geometry": {"coordinates":[6.590523,52.36058],"type":"Point"}
}