{
  "type": "Feature",
  "properties": {
    "addr:full":"Grote Visserijstraat 1 Rotterdam South Holland 3026 CA",
    "addr:housenumber":"1",
    "addr:postcode":"3026 ca",
    "addr:street":"Grote Visserijstraat",
    "iso:country":"NL",
    "sg:address":"Grote Visserijstraat 1",
    "sg:city":"Rotterdam",
    "sg:orig_category":"Gespecialiseerde Voeding",
    "sg:phone":"+31 10 462 1184",
    "sg:postcode":"3026 CA",
    "sg:province":"South Holland",
    "wof:name":"Kazmi",
    "wof:placetype":"venue"
},
  "geometry": {"coordinates":[4.442853,51.915859],"type":"Point"}
}