{
  "type": "Feature",
  "properties": {
    "iso:country":"NL",
    "sg:address":"Schoolpad 13",
    "sg:city":"Laren Nh",
    "sg:orig_category":"Verlichting And Huishoudartikelen",
    "sg:phone":"+31 35 531 4840",
    "sg:postcode":"1251 ZN",
    "sg:province":"Noord-Holland",
    "wof:name":"Woninginrichting Havo Bv",
    "wof:placetype":"venue"
},
  "geometry": {"coordinates":[5.231605,52.257263],"type":"Point"}
}