{
  "type": "Feature",
  "properties": {
    "iso:country":"NL",
    "sg:address":"Klimopstr 1/B",
    "sg:city":"Zwolle",
    "sg:orig_category":"Meubelstoffering",
    "sg:phone":"+31 38 421 5930",
    "sg:postcode":"8012 DD",
    "sg:province":"NL.08",
    "wof:name":"Moddejonge",
    "wof:placetype":"venue"
},
  "geometry": {"coordinates":[6.107587,52.501095],"type":"Point"}
}