{
  "type": "Feature",
  "properties": {
    "addr:full":"Kiekendief 9 Groet Noord-Holland 1873 JR",
    "addr:housenumber":"9",
    "addr:postcode":"1873 jr",
    "addr:street":"Kiekendief",
    "iso:country":"NL",
    "sg:address":"Kiekendief 9",
    "sg:city":"Groet",
    "sg:orig_category":"Autopoetsbedrijven",
    "sg:phone":"+31 6 18525691",
    "sg:postcode":"1873 JR",
    "sg:province":"Noord-Holland",
    "wof:name":"Rob",
    "wof:placetype":"venue"
},
  "geometry": {"coordinates":[4.668226,52.725414],"type":"Point"}
}