{
  "type": "Feature",
  "properties": {
    "iso:country":"NL",
    "sg:address":"Scheepmakerskd 44",
    "sg:city":"Rotterdam",
    "sg:orig_category":"Kappers",
    "sg:phone":"+31 10 414 5157",
    "sg:postcode":"3011 VX",
    "sg:province":"Zuid-Holland",
    "wof:name":"Sahara",
    "wof:placetype":"venue"
},
  "geometry": {"coordinates":[4.487361,51.91618],"type":"Point"}
}