{
  "type": "Feature",
  "properties": {
    "addr:full":"F V Borselenstr 1 Brielle Zuid-Holland 3232 VM",
    "addr:housenumber":"1",
    "addr:postcode":"3232 vm",
    "addr:street":"Borselenstr",
    "iso:country":"NL",
    "sg:address":"F V Borselenstr 1",
    "sg:city":"Brielle",
    "sg:orig_category":"Koeriersdiensten",
    "sg:phone":"+31 181 418 415",
    "sg:postcode":"3232 VM",
    "sg:province":"Zuid-Holland",
    "sg:website":"http://www.kcm.nl",
    "wof:name":"Rijnmond, Centr",
    "wof:placetype":"venue"
},
  "geometry": {"coordinates":[4.167875,51.90406],"type":"Point"}
}