{
  "type": "Feature",
  "properties": {
    "addr:full":"H De Jongstr 6 Rotterdam South Holland 3067 AB",
    "addr:housenumber":"6",
    "addr:postcode":"3067 ab",
    "iso:country":"NL",
    "sg:address":"H De Jongstr 6",
    "sg:city":"Rotterdam",
    "sg:orig_category":"Accountants - Administratie- Consulenten En -Kantoren",
    "sg:phone":"+31 10 266 0876",
    "sg:postcode":"3067 AB",
    "sg:province":"South Holland",
    "sg:website":"http://www.kompasgroep.com",
    "wof:name":"Kompas Bv",
    "wof:placetype":"venue"
},
  "geometry": {"coordinates":[4.549286,51.941254],"type":"Point"}
}