{
  "type": "Feature",
  "properties": {
    "addr:full":"Havenstraat 121 Hilversum Noord-Holland 1211 KK",
    "addr:housenumber":"121",
    "addr:postcode":"1211 kk",
    "addr:street":"Havenstraat",
    "iso:country":"NL",
    "sg:address":"Havenstraat 121",
    "sg:city":"Hilversum",
    "sg:classifiers":[
        {
            "category":"Food & Beverages",
            "subcategory":"Fruits & Vegetables",
            "type":"Retail Goods"
        }
    ],
    "sg:phone":"+31 35 624 8912",
    "sg:postcode":"1211 KK",
    "sg:province":"Noord-Holland",
    "sg:tags":[
        "groenten"
    ],
    "wof:name":"A. Smits & Zoon",
    "wof:placetype":"venue"
},
  "geometry": {"coordinates":[5.1695,52.228565],"type":"Point"}
}