{
  "type": "Feature",
  "properties": {
    "addr:full":"Postbus 264 Alkmaar Noord-Holland 1800 AG",
    "addr:housenumber":"264",
    "addr:postcode":"1800",
    "addr:street":"Postbus",
    "iso:country":"NL",
    "sg:address":"Postbus 264",
    "sg:city":"Alkmaar",
    "sg:orig_category":"Hulpverlening Sociaal",
    "sg:phone":"+31 72 567 0088",
    "sg:postcode":"1800 AG",
    "sg:province":"Noord-Holland",
    "wof:name":"Cluster Holland Nw",
    "wof:placetype":"venue"
},
  "geometry": {"coordinates":[4.74625,52.634361],"type":"Point"}
}