{
  "type": "Feature",
  "properties": {
    "addr:full":"Magalhaeswg 1 Venlo Limburg 5928 LN",
    "addr:housenumber":"1",
    "addr:postcode":"5928 ln",
    "addr:street":"Magalhaeswg",
    "iso:country":"NL",
    "sg:address":"Magalhaeswg 1",
    "sg:city":"Venlo",
    "sg:orig_category":"Levensmiddelen - Fabrieken En Groothandel",
    "sg:phone":"+31 77 320 4204",
    "sg:postcode":"5928 LN",
    "sg:province":"Limburg",
    "wof:name":"Hela-Thissen Bv",
    "wof:placetype":"venue"
},
  "geometry": {"coordinates":[6.087387,51.393333],"type":"Point"}
}