{
  "type": "Feature",
  "properties": {
    "addr:full":"Tolwg 2A Kaatsheuvel North Brabant 5171 PV",
    "addr:housenumber":"2a",
    "addr:postcode":"5171 pv",
    "addr:street":"Tolwg",
    "iso:country":"NL",
    "sg:address":"Tolwg 2A",
    "sg:city":"Kaatsheuvel",
    "sg:orig_category":"Lederwaren - Fabrieken En Groothandel",
    "sg:phone":"+31 416 283 324",
    "sg:postcode":"5171 PV",
    "sg:province":"North Brabant",
    "wof:name":"Ledrie Int Bv",
    "wof:placetype":"venue"
},
  "geometry": {"coordinates":[5.039138,51.663097],"type":"Point"}
}