{
  "type": "Feature",
  "properties": {
    "iso:country":"NL",
    "sg:address":"Nw Bouwlingstr 2",
    "sg:city":"Oosterhout Nb",
    "sg:orig_category":"Bloemen En Planten",
    "sg:phone":"+31 162 438 577",
    "sg:postcode":"4901 KJ",
    "sg:province":"North Brabant",
    "wof:name":"Bloemist, De",
    "wof:placetype":"venue"
},
  "geometry": {"coordinates":[4.85625,51.643051],"type":"Point"}
}