{
  "type": "Feature",
  "properties": {
    "addr:full":"Dejonghestraat 12 Waalwijk North Brabant 5142 WS",
    "addr:housenumber":"12",
    "addr:postcode":"5142 ws",
    "addr:street":"Dejonghestraat",
    "iso:country":"NL",
    "sg:address":"Dejonghestraat 12",
    "sg:city":"Waalwijk",
    "sg:classifiers":[
        {
            "category":"Travel",
            "subcategory":"Hotels & Motels",
            "type":"Entertainment"
        }
    ],
    "sg:phone":"+31 416 334 177",
    "sg:postcode":"5142 WS",
    "sg:province":"North Brabant",
    "wof:name":"Fam. Van Riel",
    "wof:placetype":"venue"
},
  "geometry": {"coordinates":[5.087703,51.690372],"type":"Point"}
}