{
  "type": "Feature",
  "properties": {
    "addr:full":"Haagstraat 38 Sittard Limburg 6133 VT",
    "addr:housenumber":"38",
    "addr:postcode":"6133",
    "addr:street":"Haagstraat",
    "iso:country":"NL",
    "sg:address":"Haagstraat 38",
    "sg:city":"Sittard",
    "sg:orig_category":"Goederenvervoer Over De Weg",
    "sg:phone":"+31 46 451 5569",
    "sg:postcode":"6133 VT",
    "sg:province":"Limburg",
    "wof:name":"J W H Hochstenbach",
    "wof:placetype":"venue"
},
  "geometry": {"coordinates":[5.855745,50.988853],"type":"Point"}
}