{
  "type": "Feature",
  "properties": {
    "addr:full":"Eiberwg 24 Dedemsvaart Overijssel 7701 VE",
    "addr:housenumber":"24",
    "addr:postcode":"7701",
    "addr:street":"Eiberwg;Ve",
    "iso:country":"NL",
    "sg:address":"Eiberwg 24",
    "sg:city":"Dedemsvaart",
    "sg:orig_category":"Administratie- En Boekhoudkantoren",
    "sg:phone":"+31 523 613 920",
    "sg:postcode":"7701 VE",
    "sg:province":"Overijssel",
    "wof:name":"Brander, Y",
    "wof:placetype":"venue"
},
  "geometry": {"coordinates":[6.455437,52.596764],"type":"Point"}
}