{
  "type": "Feature",
  "properties": {
    "addr:full":"Ambachtswg 9 Oosterhout Nb North Brabant 4906 CH",
    "addr:housenumber":"9;nb",
    "addr:postcode":"4906",
    "addr:street":"Ambachtswg",
    "iso:country":"NL",
    "sg:address":"Ambachtswg 9",
    "sg:city":"Oosterhout Nb",
    "sg:orig_category":"Verf En Lak - Fabrieken En Groothandel",
    "sg:phone":"+31 162 471 114",
    "sg:postcode":"4906 CH",
    "sg:province":"North Brabant",
    "wof:name":"Teolin Bv",
    "wof:placetype":"venue"
},
  "geometry": {"coordinates":[4.838182,51.658997],"type":"Point"}
}