{
  "type": "Feature",
  "properties": {
    "addr:full":"A Frankln 49 Bussum Noord-Holland 1403 HK",
    "addr:housenumber":"49",
    "addr:postcode":"1403 hk",
    "iso:country":"NL",
    "sg:address":"A Frankln 49",
    "sg:city":"Bussum",
    "sg:orig_category":"Organisatiebureaus",
    "sg:phone":"+31 35 691 3106",
    "sg:postcode":"1403 HK",
    "sg:province":"Noord-Holland",
    "wof:name":"Vries, De",
    "wof:placetype":"venue"
},
  "geometry": {"coordinates":[5.1933670044,52.2672920227],"type":"Point"}
}