{
  "type": "Feature",
  "properties": {
    "addr:full":"F Huyckln 22 Soest Utrecht 3768 HX",
    "addr:housenumber":"22",
    "addr:postcode":"3768 hx",
    "addr:street":"Soest",
    "iso:country":"NL",
    "sg:address":"F Huyckln 22",
    "sg:city":"Soest",
    "sg:orig_category":"Horecabenodigdheden",
    "sg:phone":"+31 35 602 2843",
    "sg:postcode":"3768 HX",
    "sg:province":"Utrecht",
    "wof:name":"Hoka Soest Bv",
    "wof:placetype":"venue"
},
  "geometry": {"coordinates":[5.30052,52.145535],"type":"Point"}
}