{
  "type": "Feature",
  "properties": {
    "iso:country":"NL",
    "sg:address":"Middelweg 7",
    "sg:city":"Numansdorp",
    "sg:orig_category":"Paramedische Behandelingen",
    "sg:phone":"+31 186 651 362",
    "sg:postcode":"3281 KH",
    "sg:province":"South Holland",
    "wof:name":"E. Van Oosterom-Van Schaardenburg",
    "wof:placetype":"venue"
},
  "geometry": {"coordinates":[4.440274,51.734707],"type":"Point"}
}