{
  "type": "Feature",
  "properties": {
    "addr:full":"Middenhavenstraat 86 Ijmuiden North Holland 1976 CM",
    "addr:housenumber":"86",
    "addr:postcode":"1976 cm",
    "addr:street":"Middenhavenstraat",
    "iso:country":"NL",
    "sg:address":"Middenhavenstraat 86",
    "sg:city":"Ijmuiden",
    "sg:orig_category":"Autokeuringen",
    "sg:phone":"+31 255 516 671",
    "sg:postcode":"1976 CM",
    "sg:province":"North Holland",
    "wof:name":"M. Hensen",
    "wof:placetype":"venue"
},
  "geometry": {"coordinates":[4.592744,52.456917],"type":"Point"}
}