{
  "type": "Feature",
  "properties": {
    "iso:country":"NL",
    "sg:address":"Debussyln 47",
    "sg:city":"Apeldoorn",
    "sg:orig_category":"Bloemen En Planten",
    "sg:phone":"+31 55 542 2240",
    "sg:postcode":"7333 DC",
    "sg:province":"Gelderland",
    "wof:name":"Bloemensteeg",
    "wof:placetype":"venue"
},
  "geometry": {"coordinates":[5.97203,52.183609],"type":"Point"}
}