{
  "type": "Feature",
  "properties": {
    "addr:full":"Burg Raymakersln 119 Grave Louisiana 5361 KD",
    "addr:housenumber":"119",
    "addr:postcode":"5361 kd",
    "addr:street":"Burg;Louisiana",
    "iso:country":"NL",
    "sg:address":"Burg Raymakersln 119",
    "sg:city":"Grave",
    "sg:classifiers":[
        {
            "category":"Personal",
            "subcategory":"Nail Salon",
            "type":"Services"
        }
    ],
    "sg:phone":"+31 486 473 825",
    "sg:postcode":"5361 KD",
    "sg:province":"Louisiana",
    "sg:tags":[
        "pedicure"
    ],
    "wof:name":"Teunen-Van Beek, N",
    "wof:placetype":"venue"
},
  "geometry": {"coordinates":[-92.151741,32.929253],"type":"Point"}
}