{
  "type": "Feature",
  "properties": {
    "addr:full":"Veemarktstraat 38 Breda Noord-Brabant 4811 ZG",
    "addr:housenumber":"38",
    "addr:postcode":"4811 zg",
    "addr:street":"Veemarktstraat",
    "iso:country":"NL",
    "sg:address":"Veemarktstraat 38",
    "sg:city":"Breda",
    "sg:orig_category":"Verlichting And Huishoudartikelen",
    "sg:phone":"+31 76 521 1480",
    "sg:postcode":"4811 ZG",
    "sg:province":"Noord-Brabant",
    "wof:name":"Brandpunt Verlichtingspassage Bv",
    "wof:placetype":"venue"
},
  "geometry": {"coordinates":[4.778139,51.588238],"type":"Point"}
}