{
  "type": "Feature",
  "properties": {
    "addr:full":"Krabbenbosweg 54 Hengelo Ov Overijssel 7555 EM",
    "addr:housenumber":"54",
    "addr:postcode":"7555 em",
    "addr:street":"Krabbenbosweg;Ov",
    "iso:country":"NL",
    "sg:address":"Krabbenbosweg 54",
    "sg:city":"Hengelo Ov",
    "sg:orig_category":"Loodgieterswerk, Verwarming And Sanitaire Installaties",
    "sg:phone":"+31 74 250 5775",
    "sg:postcode":"7555 EM",
    "sg:province":"Overijssel",
    "wof:name":"Loodgietersbedrijf E.J.H. Meijer",
    "wof:placetype":"venue"
},
  "geometry": {"coordinates":[6.777429,52.261265],"type":"Point"}
}