{
  "type": "Feature",
  "properties": {
    "addr:full":"Maarnse Grindweg 12 Maarn Utrecht 3951 LK",
    "addr:housenumber":"12",
    "addr:postcode":"3951 lk",
    "addr:street":"Maarnse Grindweg",
    "iso:country":"NL",
    "sg:address":"Maarnse Grindweg 12",
    "sg:city":"Maarn",
    "sg:orig_category":"Loodgieterswerk, Verwarming And Sanitaire Installaties",
    "sg:phone":"+31 343 441 312",
    "sg:postcode":"3951 LK",
    "sg:province":"Utrecht",
    "wof:name":"Firma E.M. Renes",
    "wof:placetype":"venue"
},
  "geometry": {"coordinates":[5.359011,52.062851],"type":"Point"}
}