{
  "type": "Feature",
  "properties": {
    "addr:full":"St Servatiusstr 32 Heeswyk Dinther Noord-Brabant 5473 GB",
    "addr:housenumber":"32",
    "addr:postcode":"5473 gb",
    "addr:street":"Heeswyk Dinther",
    "iso:country":"NL",
    "sg:address":"St Servatiusstr 32",
    "sg:city":"Heeswyk Dinther",
    "sg:orig_category":"Adviesbureaus",
    "sg:phone":"+31 413 224 106",
    "sg:postcode":"5473 GB",
    "sg:province":"Noord-Brabant",
    "wof:name":"Lagant",
    "wof:placetype":"venue"
},
  "geometry": {"coordinates":[5.477337,51.648762],"type":"Point"}
}