{
  "type": "Feature",
  "properties": {
    "addr:full":"Zekkenwg 53 Hoek Van Holland South Holland 3151 ZC",
    "addr:housenumber":"53",
    "addr:postcode":"3151 zc",
    "addr:street":"Zekkenwg",
    "iso:country":"NL",
    "sg:address":"Zekkenwg 53",
    "sg:city":"Hoek Van Holland",
    "sg:orig_category":"Machinetransporten",
    "sg:phone":"+31 174 387 231",
    "sg:postcode":"3151 ZC",
    "sg:province":"South Holland",
    "wof:name":"Ballering Bv, H J",
    "wof:placetype":"venue"
},
  "geometry": {"coordinates":[4.143709,51.970585],"type":"Point"}
}