{
  "type": "Feature",
  "properties": {
    "addr:full":"Gorecht O 141 Hoogezand Groningen 9603 AE",
    "addr:housenumber":"141",
    "addr:postcode":"9603 ae",
    "iso:country":"NL",
    "sg:address":"Gorecht O 141",
    "sg:city":"Hoogezand",
    "sg:orig_category":"Zoetwaren - Winkels",
    "sg:phone":"+31 598 351 410",
    "sg:postcode":"9603 AE",
    "sg:province":"Groningen",
    "wof:name":"Snoepexpress",
    "wof:placetype":"venue"
},
  "geometry": {"coordinates":[6.757966,53.155083],"type":"Point"}
}