{
  "type": "Feature",
  "properties": {
    "iso:country":"NL",
    "sg:address":"Prof Krabbeln 1A",
    "sg:city":"Baarn",
    "sg:orig_category":"Zonweringen",
    "sg:phone":"+31 35 656 3565",
    "sg:postcode":"3741 EM",
    "sg:province":"Utrecht",
    "wof:name":"Gooijer, Zonweringsbedrijf De",
    "wof:placetype":"venue"
},
  "geometry": {"coordinates":[5.2824,52.218792],"type":"Point"}
}