{
  "type": "Feature",
  "properties": {
    "addr:full":"Hommerterwg 1 Nuth Limburg 6361 HR",
    "addr:housenumber":"1",
    "addr:postcode":"6361 hr",
    "addr:street":"Hommerterwg",
    "iso:country":"NL",
    "sg:address":"Hommerterwg 1",
    "sg:city":"Nuth",
    "sg:orig_category":"Bloemen En Planten",
    "sg:phone":"+31 46 442 2888",
    "sg:postcode":"6361 HR",
    "sg:province":"Limburg",
    "wof:name":"Hommert, Bloemenhof De",
    "wof:placetype":"venue"
},
  "geometry": {"coordinates":[5.91743,50.934399],"type":"Point"}
}