{
  "type": "Feature",
  "properties": {
    "addr:full":"Wilgenhoekwg 15 Serooskerke Walch Zeeland 4353 EA",
    "addr:housenumber":"15",
    "addr:postcode":"4353 ea",
    "addr:street":"Wilgenhoekwg;Walch",
    "iso:country":"NL",
    "sg:address":"Wilgenhoekwg 15",
    "sg:city":"Serooskerke Walch",
    "sg:orig_category":"Kunsthandel",
    "sg:phone":"+31 118 593 482",
    "sg:postcode":"4353 EA",
    "sg:province":"Zeeland",
    "wof:name":"Horn, De",
    "wof:placetype":"venue"
},
  "geometry": {"coordinates":[3.602567,51.542637],"type":"Point"}
}