{
  "type": "Feature",
  "properties": {
    "iso:country":"NL",
    "sg:address":"Weesperzyde 29",
    "sg:city":"Amsterdam",
    "sg:orig_category":"Journalisten Freelance",
    "sg:phone":"+31 20 693 5495",
    "sg:postcode":"1091 EC",
    "sg:province":"Noord-Holland",
    "wof:name":"Janssen Keijsers & Samwel",
    "wof:placetype":"venue"
},
  "geometry": {"coordinates":[4.91306,52.35487],"type":"Point"}
}