{
  "type": "Feature",
  "properties": {
    "iso:country":"NL",
    "sg:address":"Oude Zwolsewg 149A",
    "sg:city":"Wenum Wiesel",
    "sg:orig_category":"Kampeerauto'S",
    "sg:phone":"+31 55 312 2927",
    "sg:postcode":"7345 DG",
    "sg:province":"Gelderland",
    "wof:name":"Dusschoten, A Van",
    "wof:placetype":"venue"
},
  "geometry": {"coordinates":[5.9641361237,52.2550735474],"type":"Point"}
}