{
  "type": "Feature",
  "properties": {
    "addr:full":"Lievendaal 12 Druten Gelderland 6651 EW",
    "addr:housenumber":"12",
    "addr:postcode":"6651 ew",
    "addr:street":"Lievendaal",
    "iso:country":"NL",
    "sg:address":"Lievendaal 12",
    "sg:city":"Druten",
    "sg:orig_category":"Vertaal- And Tolkenbureaus",
    "sg:phone":"+31 487 515 429",
    "sg:postcode":"6651 EW",
    "sg:province":"Gelderland",
    "wof:name":"A.C. De Graaf-Hess",
    "wof:placetype":"venue"
},
  "geometry": {"coordinates":[5.598627,51.884544],"type":"Point"}
}