{
  "type": "Feature",
  "properties": {
    "iso:country":"NL",
    "sg:address":"Herenweg 83",
    "sg:city":"Warmond",
    "sg:orig_category":"Banken And Kredietinstellingen",
    "sg:phone":"+31 252 243 243",
    "sg:postcode":"2361 EJ",
    "sg:province":"Zuid-Holland",
    "wof:name":"Rabobank",
    "wof:placetype":"venue"
},
  "geometry": {"coordinates":[4.503966,52.197891],"type":"Point"}
}