{
  "type": "Feature",
  "properties": {
    "addr:full":"Wierhuisterwg 15 Pieterburen Groningen 9968 AN",
    "addr:housenumber":"15",
    "addr:postcode":"9968 an",
    "addr:street":"Wierhuisterwg",
    "iso:country":"NL",
    "sg:address":"Wierhuisterwg 15",
    "sg:city":"Pieterburen",
    "sg:orig_category":"Onderhoudswerken",
    "sg:phone":"+31 595 528 613",
    "sg:postcode":"9968 AN",
    "sg:province":"Groningen",
    "wof:name":"Cordes",
    "wof:placetype":"venue"
},
  "geometry": {"coordinates":[6.424587,53.397102],"type":"Point"}
}