{
  "type": "Feature",
  "properties": {
    "iso:country":"NL",
    "sg:address":"Burg Haspelsln 137",
    "sg:city":"Amstelveen",
    "sg:orig_category":"Scholen Voor Basisonderwijs",
    "sg:phone":"+31 20 641 6117",
    "sg:postcode":"1181 NC",
    "sg:province":"Noord-Holland",
    "wof:name":"Eerste Amstelveense Montessori",
    "wof:placetype":"venue"
},
  "geometry": {"coordinates":[4.867517,52.306427],"type":"Point"}
}