{
  "type": "Feature",
  "properties": {
    "addr:full":"Brinkenhalte 16 Emmen Provincie Drenthe 7812 HX",
    "addr:housenumber":"16",
    "addr:postcode":"7812 hx",
    "addr:street":"Brinkenhalte;Provincie Drenthe",
    "iso:country":"NL",
    "sg:address":"Brinkenhalte 16",
    "sg:city":"Emmen",
    "sg:orig_category":"Fitnesscentra",
    "sg:phone":"+31 591 633 699",
    "sg:postcode":"7812 HX",
    "sg:province":"Provincie Drenthe",
    "sg:website":"http://www.fitnessoase.nl",
    "wof:name":"Fitness-Oase",
    "wof:placetype":"venue"
},
  "geometry": {"coordinates":[6.884064,52.754787],"type":"Point"}
}