{
  "type": "Feature",
  "properties": {
    "addr:full":"Lagezoom 1 Burgh Haamstede Zeeland 4328 EN",
    "addr:housenumber":"1",
    "addr:postcode":"4328 en",
    "addr:street":"Lagezoom;Haamstede",
    "iso:country":"NL",
    "sg:address":"Lagezoom 1",
    "sg:city":"Burgh Haamstede",
    "sg:orig_category":"Bloemen And Planten Gh",
    "sg:phone":"+31 111 651 376",
    "sg:postcode":"4328 EN",
    "sg:province":"Zeeland",
    "wof:name":"L. Baumann",
    "wof:placetype":"venue"
},
  "geometry": {"coordinates":[3.755083,51.710995],"type":"Point"}
}