{
  "type": "Feature",
  "properties": {
    "addr:full":"Populierendreef 329 Voorburg Zuid-Holland 2272 RH",
    "addr:housenumber":"329",
    "addr:postcode":"2272 rh",
    "addr:street":"Populierendreef",
    "iso:country":"NL",
    "sg:address":"Populierendreef 329",
    "sg:city":"Voorburg",
    "sg:orig_category":"Elektrische Apparatuur Gh",
    "sg:phone":"+31 70 387 6800",
    "sg:postcode":"2272 RH",
    "sg:province":"Zuid-Holland",
    "wof:name":"Ib Kracht Bv",
    "wof:placetype":"venue"
},
  "geometry": {"coordinates":[4.361445,52.084942],"type":"Point"}
}