{
  "type": "Feature",
  "properties": {
    "iso:country":"NL",
    "sg:address":"Oud Loosdrechtsedijk 166",
    "sg:city":"Loosdrecht",
    "sg:orig_category":"Diverse Consumentenartikelen Gh",
    "sg:phone":"+31 35 582 6022",
    "sg:postcode":"1231 NE",
    "sg:province":"Noord-Holland",
    "wof:name":"R.J. Van Binsbergen",
    "wof:placetype":"venue"
},
  "geometry": {"coordinates":[5.084201,52.206924],"type":"Point"}
}