{
  "type": "Feature",
  "properties": {
    "addr:full":"Tegelseweg 26 Venlo Limburg 5912 BH",
    "addr:housenumber":"26",
    "addr:postcode":"5912 bh",
    "addr:street":"Tegelseweg",
    "iso:country":"NL",
    "sg:address":"Tegelseweg 26",
    "sg:city":"Venlo",
    "sg:orig_category":"Kappers",
    "sg:phone":"+31 77 352 0498",
    "sg:postcode":"5912 BH",
    "sg:province":"Limburg",
    "wof:name":"Coiffures Emile",
    "wof:placetype":"venue"
},
  "geometry": {"coordinates":[6.1613001823,51.3627853394],"type":"Point"}
}