{
  "type": "Feature",
  "properties": {
    "iso:country":"NL",
    "sg:address":"Nachtegaallaan 3",
    "sg:city":"Eindhoven",
    "sg:orig_category":"Werving And Selectie Van Tijdelijk Personeel And Uitzendkantoren",
    "sg:phone":"+31 40 246 4055",
    "sg:postcode":"5613 CM",
    "sg:province":"Noord-Brabant",
    "wof:name":"Operator Groep Delft",
    "wof:placetype":"venue"
},
  "geometry": {"coordinates":[5.48726511,51.4408988953],"type":"Point"}
}