{
  "type": "Feature",
  "properties": {
    "addr:full":"Engwg 14B Laren Nh Noord-Holland 1251 LL",
    "addr:housenumber":"14b",
    "addr:postcode":"1251 ll",
    "addr:street":"Engwg",
    "iso:country":"NL",
    "sg:address":"Engwg 14B",
    "sg:city":"Laren Nh",
    "sg:orig_category":"Bedrijfsopleidingen",
    "sg:phone":"+31 35 531 7485",
    "sg:postcode":"1251 LL",
    "sg:province":"Noord-Holland",
    "wof:name":"Hemmer",
    "wof:placetype":"venue"
},
  "geometry": {"coordinates":[5.219234,52.252419],"type":"Point"}
}