{
  "type": "Feature",
  "properties": {
    "addr:full":"Moutheuvelln 2 Schinnen Limburg 6365 AZ",
    "addr:housenumber":"2",
    "addr:postcode":"6365 az",
    "addr:street":"Moutheuvelln",
    "iso:country":"NL",
    "sg:address":"Moutheuvelln 2",
    "sg:city":"Schinnen",
    "sg:orig_category":"Scholen Voor Basisonderwijs",
    "sg:phone":"+31 46 443 1885",
    "sg:postcode":"6365 AZ",
    "sg:province":"Limburg",
    "wof:name":"Dionysius Rk, St",
    "wof:placetype":"venue"
},
  "geometry": {"coordinates":[5.886837,50.942345],"type":"Point"}
}