{
  "type": "Feature",
  "properties": {
    "addr:full":"Gaesbeekstr 119 Rotterdam Zuid-Holland 3081 NH",
    "addr:housenumber":"119",
    "addr:postcode":"3081 nh",
    "iso:country":"NL",
    "sg:address":"Gaesbeekstr 119",
    "sg:city":"Rotterdam",
    "sg:orig_category":"Afslankinstituten",
    "sg:phone":"+31 10 484 5443",
    "sg:postcode":"3081 NH",
    "sg:province":"Zuid-Holland",
    "wof:name":"K & M",
    "wof:placetype":"venue"
},
  "geometry": {"coordinates":[4.488659,51.895237],"type":"Point"}
}