{
  "type": "Feature",
  "properties": {
    "addr:full":"Witte De Withstraat 119 'S Gravenhage Zuid-Holland 2518 CS",
    "addr:housenumber":"119 '",
    "addr:postcode":"2518 cs",
    "addr:street":"Witte De Withstraat",
    "iso:country":"NL",
    "sg:address":"Witte De Withstraat 119",
    "sg:city":"'S Gravenhage",
    "sg:orig_category":"Overheidsdiensten",
    "sg:phone":"+31 70 345 7129",
    "sg:postcode":"2518 CS",
    "sg:province":"Zuid-Holland",
    "wof:name":"Deedrie",
    "wof:placetype":"venue"
},
  "geometry": {"coordinates":[4.292383194,52.0791969299],"type":"Point"}
}