{
  "type": "Feature",
  "properties": {
    "addr:full":"Schoolstraat 24 'S Gravenhage Zuid-Holland 2511 AX",
    "addr:housenumber":"24",
    "addr:postcode":"2511 ax",
    "addr:street":"Schoolstraat;' S",
    "iso:country":"NL",
    "sg:address":"Schoolstraat 24",
    "sg:city":"'S Gravenhage",
    "sg:orig_category":"Discountwinkels",
    "sg:phone":"+31 70 362 1672",
    "sg:postcode":"2511 AX",
    "sg:province":"Zuid-Holland",
    "wof:name":"Wibra Textielsupermarkt Bv",
    "wof:placetype":"venue"
},
  "geometry": {"coordinates":[4.30853,52.076511],"type":"Point"}
}