{
  "type": "Feature",
  "properties": {
    "addr:full":"Wieringsestraat 208 'S Gravenhage South Holland 2583 VE",
    "addr:housenumber":"208 '",
    "addr:postcode":"2583",
    "addr:street":"Wieringsestraat;Ve",
    "iso:country":"NL",
    "sg:address":"Wieringsestraat 208",
    "sg:city":"'S Gravenhage",
    "sg:orig_category":"Visserij",
    "sg:phone":"+31 70 350 0208",
    "sg:postcode":"2583 VE",
    "sg:province":"South Holland",
    "wof:name":"Vof A. Rog & B. Rog",
    "wof:placetype":"venue"
},
  "geometry": {"coordinates":[4.257173,52.091568],"type":"Point"}
}