{
  "type": "Feature",
  "properties": {
    "addr:full":"Schoolpad 2 Ermelo Gelderland 3851 JE",
    "addr:housenumber":"2",
    "addr:postcode":"3851 je",
    "addr:street":"Schoolpad;Gelderland",
    "iso:country":"NL",
    "sg:address":"Schoolpad 2",
    "sg:city":"Ermelo",
    "sg:orig_category":"Goederenvervoer Over De Weg",
    "sg:phone":"+31 341 552 529",
    "sg:postcode":"3851 JE",
    "sg:province":"Gelderland",
    "wof:name":"Transportbedrijf W. Van Den Top Bv",
    "wof:placetype":"venue"
},
  "geometry": {"coordinates":[5.613905,52.298553],"type":"Point"}
}