{
  "type": "Feature",
  "properties": {
    "addr:full":"Diezerstraat 76 Zwolle Overijssel 8011 RH",
    "addr:housenumber":"76",
    "addr:postcode":"8011 rh",
    "addr:street":"Diezerstraat",
    "iso:country":"NL",
    "sg:address":"Diezerstraat 76",
    "sg:city":"Zwolle",
    "sg:orig_category":"Verlichting And Huishoudartikelen",
    "sg:phone":"+31 38 421 6495",
    "sg:postcode":"8011 RH",
    "sg:province":"Overijssel",
    "wof:name":"Van Heerde Licht",
    "wof:placetype":"venue"
},
  "geometry": {"coordinates":[6.096501,52.512646],"type":"Point"}
}