{
  "type": "Feature",
  "properties": {
    "addr:full":"Odysseusln 81 Eindhoven Noord-Brabant 5631 JL",
    "addr:housenumber":"81",
    "addr:postcode":"5631 jl",
    "addr:street":"Odysseusln",
    "iso:country":"NL",
    "sg:address":"Odysseusln 81",
    "sg:city":"Eindhoven",
    "sg:orig_category":"Beeldende Kunstenaars",
    "sg:phone":"+31 40 245 4783",
    "sg:postcode":"5631 JL",
    "sg:province":"Noord-Brabant",
    "wof:name":"Oya Arte Vivere",
    "wof:placetype":"venue"
},
  "geometry": {"coordinates":[5.50844,51.45776],"type":"Point"}
}