{
  "type": "Feature",
  "properties": {
    "addr:full":"Schaarsbergendr 3 Helmond Noord-Brabant 5709 RZ",
    "addr:housenumber":"3",
    "addr:postcode":"5709 rz",
    "addr:street":"Schaarsbergendr",
    "iso:country":"NL",
    "sg:address":"Schaarsbergendr 3",
    "sg:city":"Helmond",
    "sg:orig_category":"Woninginrichting",
    "sg:phone":"+31 492 515 651",
    "sg:postcode":"5709 RZ",
    "sg:province":"Noord-Brabant",
    "wof:name":"Brouwer, J",
    "wof:placetype":"venue"
},
  "geometry": {"coordinates":[5.7034578323,51.4910507202],"type":"Point"}
}