{
  "type": "Feature",
  "properties": {
    "addr:full":"H.J.E. Wenckebachweg 163 Amsterdam Noord-Holland 1096 AM",
    "addr:housenumber":"163",
    "addr:postcode":"1096",
    "addr:street":"H.J.E. Wenckebachweg",
    "iso:country":"NL",
    "sg:address":"H.J.E. Wenckebachweg 163",
    "sg:city":"Amsterdam",
    "sg:orig_category":"Diverse Grafische Activiteiten",
    "sg:phone":"+31 20 463 9240",
    "sg:postcode":"1096 AM",
    "sg:province":"Noord-Holland",
    "wof:name":"Moving Magic",
    "wof:placetype":"venue"
},
  "geometry": {"coordinates":[4.93378,52.335461],"type":"Point"}
}