{
  "type": "Feature",
  "properties": {
    "iso:country":"NL",
    "sg:address":"Newtonpln 14A",
    "sg:city":"Eindhoven",
    "sg:orig_category":"Verzekeringen - Verzekeringskantoren",
    "sg:phone":"+31 40 296 3379",
    "sg:postcode":"5621 CM",
    "sg:province":"North Brabant",
    "wof:name":"Hoof, Van",
    "wof:placetype":"venue"
},
  "geometry": {"coordinates":[5.454982,51.4575],"type":"Point"}
}