{
  "type": "Feature",
  "properties": {
    "addr:full":"Anemoonstraat 78 Hoogeveen Drenthe 7906 PG",
    "addr:housenumber":"78",
    "addr:postcode":"7906 pg",
    "addr:street":"Anemoonstraat",
    "iso:country":"NL",
    "sg:address":"Anemoonstraat 78",
    "sg:city":"Hoogeveen",
    "sg:orig_category":"Verhuur Huishoudartikelen",
    "sg:phone":"+31 528 266 200",
    "sg:postcode":"7906 PG",
    "sg:province":"Drenthe",
    "wof:name":"Groote-Ijmker",
    "wof:placetype":"venue"
},
  "geometry": {"coordinates":[6.490739,52.715725],"type":"Point"}
}