{
  "type": "Feature",
  "properties": {
    "addr:full":"G J Van Heekstraat 115 Enschede NL.08 7521 EB",
    "addr:housenumber":"115",
    "addr:postcode":"7521 eb",
    "addr:street":"G J Van Heekstraat",
    "iso:country":"NL",
    "sg:address":"G J Van Heekstraat 115",
    "sg:city":"Enschede",
    "sg:orig_category":"Bloemen And Planten",
    "sg:phone":"+31 53 433 2221",
    "sg:postcode":"7521 EB",
    "sg:province":"NL.08",
    "wof:name":"G.A. Beimer",
    "wof:placetype":"venue"
},
  "geometry": {"coordinates":[6.8650870323,52.2279167175],"type":"Point"}
}