{
  "type": "Feature",
  "properties": {
    "addr:full":"Palmenhuizerweg 1 Harskamp Gelderland 6732 EH",
    "addr:housenumber":"1",
    "addr:postcode":"6732 eh",
    "addr:street":"Palmenhuizerweg;Gelderland",
    "iso:country":"NL",
    "sg:address":"Palmenhuizerweg 1",
    "sg:city":"Harskamp",
    "sg:orig_category":"Kampeerterreinen",
    "sg:phone":"+31 318 456 491",
    "sg:postcode":"6732 EH",
    "sg:province":"Gelderland",
    "wof:name":"Camping De Midden Veluwe Bv",
    "wof:placetype":"venue"
},
  "geometry": {"coordinates":[5.7591838837,52.1375427246],"type":"Point"}
}