{
  "type": "Feature",
  "properties": {
    "addr:full":"Luchthavenwg 24 Eindhoven Noord-Brabant 5657 EB",
    "addr:housenumber":"24",
    "addr:postcode":"5657 eb",
    "addr:street":"Luchthavenwg",
    "iso:country":"NL",
    "sg:address":"Luchthavenwg 24",
    "sg:city":"Eindhoven",
    "sg:classifiers":[
        {
            "category":"Retail",
            "subcategory":"Storage",
            "type":"Services"
        }
    ],
    "sg:phone":"+31 40 292 2922",
    "sg:postcode":"5657 EB",
    "sg:province":"Noord-Brabant",
    "sg:tags":[
        "op-",
        "en",
        "overslagbedrijven"
    ],
    "wof:name":"Fedex Supply Chain Services",
    "wof:placetype":"venue"
},
  "geometry": {"coordinates":[5.392666,51.456413],"type":"Point"}
}