{
  "type": "Feature",
  "properties": {
    "addr:full":"Wedesteinbroek 1118 Nijmegen Gelderland 6546 RE",
    "addr:housenumber":"1118",
    "addr:postcode":"6546",
    "addr:street":"Wedesteinbroek;Gelderland",
    "iso:country":"NL",
    "sg:address":"Wedesteinbroek 1118",
    "sg:city":"Nijmegen",
    "sg:orig_category":"Glaszetten",
    "sg:phone":"+31 24 377 5087",
    "sg:postcode":"6546 RE",
    "sg:province":"Gelderland",
    "wof:name":"Glasservice J Van Leth",
    "wof:placetype":"venue"
},
  "geometry": {"coordinates":[5.781399,51.828419],"type":"Point"}
}