{
  "type": "Feature",
  "properties": {
    "iso:country":"NL",
    "sg:address":"Voorstr 42",
    "sg:city":"Harlingen",
    "sg:orig_category":"Hoortoestellen",
    "sg:phone":"+31 517 412 987",
    "sg:postcode":"8861 BM",
    "sg:province":"Friesland",
    "wof:name":"Beter Horen",
    "wof:placetype":"venue"
},
  "geometry": {"coordinates":[5.418514,53.174747],"type":"Point"}
}