{
  "type": "Feature",
  "properties": {
    "addr:full":"Bovendijk 132 Rotterdam Zuid-Holland 3045 PC",
    "addr:housenumber":"132",
    "addr:postcode":"3045 pc",
    "addr:street":"Bovendijk",
    "iso:country":"NL",
    "sg:address":"Bovendijk 132",
    "sg:city":"Rotterdam",
    "sg:orig_category":"Metalen And Ertsen Gh",
    "sg:phone":"+31 10 422 0533",
    "sg:postcode":"3045 PC",
    "sg:province":"Zuid-Holland",
    "wof:name":"Edelstahlwerke Buderus Nederland Bv",
    "wof:placetype":"venue"
},
  "geometry": {"coordinates":[4.457139,51.953976],"type":"Point"}
}