{
  "type": "Feature",
  "properties": {
    "addr:full":"Westlandgr 205/3Hg Amsterdam Noord-Holland 1059 TM",
    "addr:housenumber":"205 / 3hg",
    "addr:postcode":"1059 tm",
    "iso:country":"NL",
    "sg:address":"Westlandgr 205/3Hg",
    "sg:city":"Amsterdam",
    "sg:orig_category":"Verenigingen En Stichtingen",
    "sg:phone":"+31 20 614 0840",
    "sg:postcode":"1059 TM",
    "sg:province":"Noord-Holland",
    "wof:name":"Daina, Ver",
    "wof:placetype":"venue"
},
  "geometry": {"coordinates":[4.846246,52.349274],"type":"Point"}
}