{
  "type": "Feature",
  "properties": {
    "addr:full":"Hoofdstr 52 Hoogezand Groningen 9601 EJ",
    "addr:housenumber":"52",
    "addr:postcode":"9601 ej",
    "addr:street":"Hoofdstr",
    "iso:country":"NL",
    "sg:address":"Hoofdstr 52",
    "sg:city":"Hoogezand",
    "sg:orig_category":"Administratie- En Boekhoudkantoren",
    "sg:phone":"+31 598 398 300",
    "sg:postcode":"9601 EJ",
    "sg:province":"Groningen",
    "wof:name":"Doezum, Van",
    "wof:placetype":"venue"
},
  "geometry": {"coordinates":[6.7588949203,53.1635665894],"type":"Point"}
}