{
  "type": "Feature",
  "properties": {
    "iso:country":"NL",
    "sg:address":"Duitslandwg 11",
    "sg:city":"Bodegraven",
    "sg:orig_category":"Telecommunicatie - Apparatuur",
    "sg:phone":"+31 172 635 500",
    "sg:postcode":"2411 NT",
    "sg:province":"Zuid-Holland",
    "sg:website":"http://www.css.nl",
    "wof:name":"Cabling & Connectivity Bodegraven",
    "wof:placetype":"venue"
},
  "geometry": {"coordinates":[4.754682,52.068195],"type":"Point"}
}