{
  "type": "Feature",
  "properties": {
    "addr:full":"Nunspeetlaan 428 'S Gravenhage Zuid-Holland 2573 GV",
    "addr:housenumber":"428 '",
    "addr:postcode":"2573 gv",
    "addr:street":"Nunspeetlaan",
    "iso:country":"NL",
    "sg:address":"Nunspeetlaan 428",
    "sg:city":"'S Gravenhage",
    "sg:orig_category":"Metaalwerken",
    "sg:phone":"+31 70 388 5776",
    "sg:postcode":"2573 GV",
    "sg:province":"Zuid-Holland",
    "wof:name":"Zonweringbedrijf Ernst",
    "wof:placetype":"venue"
},
  "geometry": {"coordinates":[4.288106,52.063198],"type":"Point"}
}