{
  "type": "Feature",
  "properties": {
    "addr:full":"Sliffertsestr 21 Eindhoven Noord-Brabant 5657 AL",
    "addr:housenumber":"21",
    "addr:postcode":"5657 al",
    "addr:street":"Sliffertsestr",
    "iso:country":"NL",
    "sg:address":"Sliffertsestr 21",
    "sg:city":"Eindhoven",
    "sg:orig_category":"Cafetaria'S",
    "sg:phone":"+31 40 293 2354",
    "sg:postcode":"5657 AL",
    "sg:province":"Noord-Brabant",
    "wof:name":"Vierrijk",
    "wof:placetype":"venue"
},
  "geometry": {"coordinates":[5.418155,51.444435],"type":"Point"}
}