{
  "type": "Feature",
  "properties": {
    "addr:full":"Den Biest 1 Eindhoven Noord-Brabant 5615 AT",
    "addr:housenumber":"1",
    "addr:postcode":"5615",
    "addr:street":"Den Biest",
    "iso:country":"NL",
    "sg:address":"Den Biest 1",
    "sg:city":"Eindhoven",
    "sg:orig_category":"Werving And Selectie Van Vast Personeel",
    "sg:phone":"+31 40 211 7576",
    "sg:postcode":"5615 AT",
    "sg:province":"Noord-Brabant",
    "wof:name":"Start",
    "wof:placetype":"venue"
},
  "geometry": {"coordinates":[5.4876680374,51.427192688],"type":"Point"}
}