{
  "type": "Feature",
  "properties": {
    "iso:country":"NL",
    "sg:address":"Stappegoorwg 3A",
    "sg:city":"Tilburg",
    "sg:orig_category":"Zalenverhuur",
    "sg:phone":"+31 13 464 8989",
    "sg:postcode":"5022 DA",
    "sg:province":"North Brabant",
    "sg:website":"http://www.trappers.nl",
    "wof:name":"Trapperij Caf?-Restaurant, De",
    "wof:placetype":"venue"
},
  "geometry": {"coordinates":[5.08201,51.540661],"type":"Point"}
}