{
  "type": "Feature",
  "properties": {
    "addr:full":"Halstersebaan 29 Bergen Op Zoom North Brabant 4614 RW",
    "addr:housenumber":"29",
    "addr:postcode":"4614 rw",
    "addr:street":"Halstersebaan",
    "iso:country":"NL",
    "sg:address":"Halstersebaan 29",
    "sg:city":"Bergen Op Zoom",
    "sg:orig_category":"Hondenscholen",
    "sg:phone":"+31 165 301 125",
    "sg:postcode":"4614 RW",
    "sg:province":"North Brabant",
    "wof:name":"Martin Gaus",
    "wof:placetype":"venue"
},
  "geometry": {"coordinates":[4.340783,51.526016],"type":"Point"}
}