{
  "type": "Feature",
  "properties": {
    "addr:full":"Terborchlaan 2 Alkmaar Noord-Holland 1816 LD",
    "addr:housenumber":"2",
    "addr:postcode":"1816 ld",
    "addr:street":"Terborchlaan",
    "iso:country":"NL",
    "sg:address":"Terborchlaan 2",
    "sg:city":"Alkmaar",
    "sg:orig_category":"Kappers",
    "sg:phone":"+31 72 512 0710",
    "sg:postcode":"1816 LD",
    "sg:province":"Noord-Holland",
    "wof:name":"F M Hairstyling",
    "wof:placetype":"venue"
},
  "geometry": {"coordinates":[4.7265610695,52.6299209595],"type":"Point"}
}