{
  "type": "Feature",
  "properties": {
    "addr:full":"Kolkwg 80 Lelystad Flevoland 8243 PN",
    "addr:housenumber":"80",
    "addr:postcode":"8243 pn",
    "addr:street":"Kolkwg;Flevoland",
    "iso:country":"NL",
    "sg:address":"Kolkwg 80",
    "sg:city":"Lelystad",
    "sg:orig_category":"Parketvloeren - Fabrieken",
    "sg:phone":"+31 320 260 207",
    "sg:postcode":"8243 PN",
    "sg:province":"Flevoland",
    "wof:name":"Selecta Bv",
    "wof:placetype":"venue"
},
  "geometry": {"coordinates":[5.433,52.504089],"type":"Point"}
}