{
  "type": "Feature",
  "properties": {
    "addr:full":"Parkstr 1 Kerkrade Limburg 6466 BA",
    "addr:housenumber":"1",
    "addr:postcode":"6466 ba",
    "addr:street":"Parkstr",
    "iso:country":"NL",
    "sg:address":"Parkstr 1",
    "sg:city":"Kerkrade",
    "sg:orig_category":"Autoruiten",
    "sg:phone":"+31 45 541 9612",
    "sg:postcode":"6466 BA",
    "sg:province":"Limburg",
    "wof:name":"Baartz Mobiler Autoglasservice",
    "wof:placetype":"venue"
},
  "geometry": {"coordinates":[6.037303,50.860043],"type":"Point"}
}