{
  "type": "Feature",
  "properties": {
    "addr:full":"Plaswyk 24 Vinkeveen Utrecht 3645 AV",
    "addr:housenumber":"24",
    "addr:postcode":"3645 av",
    "addr:street":"Plaswyk",
    "iso:country":"NL",
    "sg:address":"Plaswyk 24",
    "sg:city":"Vinkeveen",
    "sg:orig_category":"Jachthavens - Jachtwerven",
    "sg:phone":"+31 294 293 321",
    "sg:postcode":"3645 AV",
    "sg:province":"Utrecht",
    "wof:name":"Bosch & Roth",
    "wof:placetype":"venue"
},
  "geometry": {"coordinates":[4.926377,52.214134],"type":"Point"}
}