{
  "type": "Feature",
  "properties": {
    "addr:full":"Dr Bosstr 4 Tiel Gelderland 4001 CK",
    "addr:housenumber":"4",
    "addr:postcode":"4001 ck",
    "addr:street":"Gelderland",
    "iso:country":"NL",
    "sg:address":"Dr Bosstr 4",
    "sg:city":"Tiel",
    "sg:orig_category":"Verzekerings- Maatschappijen",
    "sg:phone":"+31 344 613 064",
    "sg:postcode":"4001 CK",
    "sg:province":"Gelderland",
    "wof:name":"Onderl Glasverz Mij Tiel En Omstr",
    "wof:placetype":"venue"
},
  "geometry": {"coordinates":[5.430696,51.888096],"type":"Point"}
}