{
  "type": "Feature",
  "properties": {
    "addr:full":"Pleinstr 15A Etten Leur Noord-Brabant 4871 NS",
    "addr:housenumber":"15a",
    "addr:postcode":"4871 ns",
    "addr:street":"Pleinstr",
    "iso:country":"NL",
    "sg:address":"Pleinstr 15A",
    "sg:city":"Etten Leur",
    "sg:orig_category":"Geluidsopnamestudio'S",
    "sg:phone":"+31 76 504 1713",
    "sg:postcode":"4871 NS",
    "sg:province":"Noord-Brabant",
    "wof:name":"B15",
    "wof:placetype":"venue"
},
  "geometry": {"coordinates":[4.668792,51.584568],"type":"Point"}
}