{
  "type": "Feature",
  "properties": {
    "addr:full":"Klapbrugwg 6 Almere NL. 1332 AK",
    "addr:housenumber":"6",
    "addr:postcode":"1332 ak",
    "addr:street":"Klapbrugwg;Nl.",
    "iso:country":"NL",
    "sg:address":"Klapbrugwg 6",
    "sg:city":"Almere",
    "sg:orig_category":"Kantoorbenodigdheden - Fabrieken En Groothandel",
    "sg:phone":"+31 36 549 5400",
    "sg:postcode":"1332 AK",
    "sg:province":"NL.",
    "wof:name":"O' Harris Bv",
    "wof:placetype":"venue"
},
  "geometry": {"coordinates":[5.2552452087,52.4052085876],"type":"Point"}
}