{
  "type": "Feature",
  "properties": {
    "iso:country":"NL",
    "sg:address":"Chopinln 9",
    "sg:city":"Delft",
    "sg:orig_category":"Bejaarden - Verzorgingstehuizen",
    "sg:phone":"+31 15 256 0800",
    "sg:postcode":"2625 TD",
    "sg:province":"South Holland",
    "wof:name":"Die Buytenweye",
    "wof:placetype":"venue"
},
  "geometry": {"coordinates":[4.338099,51.9935],"type":"Point"}
}