{
  "type": "Feature",
  "properties": {
    "addr:full":"Leemstr 6 Roosendaal Noord-Brabant 4705 RH",
    "addr:housenumber":"6",
    "addr:postcode":"4705 rh",
    "addr:street":"Leemstr",
    "iso:country":"NL",
    "sg:address":"Leemstr 6",
    "sg:city":"Roosendaal",
    "sg:orig_category":"Pijpleidingen",
    "sg:phone":"+31 165 559 772",
    "sg:postcode":"4705 RH",
    "sg:province":"Noord-Brabant",
    "wof:name":"Hecri",
    "wof:placetype":"venue"
},
  "geometry": {"coordinates":[4.484729,51.545918],"type":"Point"}
}