{
  "type": "Feature",
  "properties": {
    "iso:country":"NL",
    "sg:address":"Eperweg 78",
    "sg:city":"'T Harde",
    "sg:classifiers":[
        {
            "category":"Bakery",
            "type":"Food & Drink"
        }
    ],
    "sg:phone":"+31 525 651 227",
    "sg:postcode":"8084 HJ",
    "sg:province":"Gelderland",
    "sg:tags":[
        "brood",
        "banket"
    ],
    "wof:name":"J. Uit De Fles",
    "wof:placetype":"venue"
},
  "geometry": {"coordinates":[5.886175,52.413551],"type":"Point"}
}