{
  "type": "Feature",
  "properties": {
    "addr:full":"Nobeldwarsstraat 24 Utrecht Utrecht 3512 EX",
    "addr:housenumber":"24",
    "addr:postcode":"3512 ex",
    "addr:street":"Nobeldwarsstraat",
    "iso:country":"NL",
    "sg:address":"Nobeldwarsstraat 24",
    "sg:city":"Utrecht",
    "sg:orig_category":"Fotostudio'S And Fotografen",
    "sg:phone":"+31 30 231 3780",
    "sg:postcode":"3512 EX",
    "sg:province":"Utrecht",
    "wof:name":"Lankveld Persfotografie",
    "wof:placetype":"venue"
},
  "geometry": {"coordinates":[5.126926,52.09169],"type":"Point"}
}