{
  "type": "Feature",
  "properties": {
    "addr:full":"Deventerstr 13 Apeldoorn Gelderland 7311 BH",
    "addr:housenumber":"13",
    "addr:postcode":"7311 bh",
    "addr:street":"Deventerstr;Gelderland",
    "iso:country":"NL",
    "sg:address":"Deventerstr 13",
    "sg:city":"Apeldoorn",
    "sg:orig_category":"Opticiens",
    "sg:phone":"+31 55 522 2930",
    "sg:postcode":"7311 BH",
    "sg:province":"Gelderland",
    "sg:website":"http://www.hansanders.nl",
    "wof:name":"Hans Anders",
    "wof:placetype":"venue"
},
  "geometry": {"coordinates":[5.9626398087,52.2159729004],"type":"Point"}
}