{
  "type": "Feature",
  "properties": {
    "addr:full":"Pieterskerk-Choorsteeg 3 Leiden South Holland 2311 TR",
    "addr:housenumber":"3",
    "addr:postcode":"2311 tr",
    "addr:street":"Pieterskerk-Choorsteeg",
    "iso:country":"NL",
    "sg:address":"Pieterskerk-Choorsteeg 3",
    "sg:city":"Leiden",
    "sg:orig_category":"Verlichting And Huishoudartikelen",
    "sg:phone":"+31 71 513 2499",
    "sg:postcode":"2311 TR",
    "sg:province":"South Holland",
    "wof:name":"J & R Collection",
    "wof:placetype":"venue"
},
  "geometry": {"coordinates":[4.48957,52.158409],"type":"Point"}
}