{
  "type": "Feature",
  "properties": {
    "addr:full":"Hugo De Grootstraat 394 Delft Zuid-Holland 2613 VD",
    "addr:housenumber":"394",
    "addr:postcode":"2613 vd",
    "addr:street":"Hugo De Grootstraat",
    "iso:country":"NL",
    "sg:address":"Hugo De Grootstraat 394",
    "sg:city":"Delft",
    "sg:orig_category":"Verzekeringen",
    "sg:phone":"+31 15 213 2427",
    "sg:postcode":"2613 VD",
    "sg:province":"Zuid-Holland",
    "wof:name":"Assurantiekantoor Van Stolk",
    "wof:placetype":"venue"
},
  "geometry": {"coordinates":[4.3465900421,52.006565094],"type":"Point"}
}