{
  "type": "Feature",
  "properties": {
    "addr:full":"Groenmarkt 16-20 Dordrecht Zuid-Holland 3311 BE",
    "addr:housenumber":"16-20",
    "addr:postcode":"3311",
    "addr:street":"Groenmarkt",
    "iso:country":"NL",
    "sg:address":"Groenmarkt 16-20",
    "sg:city":"Dordrecht",
    "sg:orig_category":"Verpleegartikelen",
    "sg:phone":"+31 78 613 4120",
    "sg:postcode":"3311 BE",
    "sg:province":"Zuid-Holland",
    "wof:name":"Welzorg Care Prod",
    "wof:placetype":"venue"
},
  "geometry": {"coordinates":[4.666065,51.81472],"type":"Point"}
}