{
  "type": "Feature",
  "properties": {
    "iso:country":"NL",
    "sg:address":"De Hoek 6",
    "sg:city":"Veenwouden",
    "sg:orig_category":"Webdesign Bureaus",
    "sg:phone":"+31 511 475 387",
    "sg:postcode":"9269 TT",
    "sg:province":"Friesland",
    "sg:website":"http://www.ksites.nl",
    "wof:name":"Ksites",
    "wof:placetype":"venue"
},
  "geometry": {"coordinates":[5.9715938568,53.2337417603],"type":"Point"}
}