{
  "type": "Feature",
  "properties": {
    "addr:full":"Paardenmarkt 3 Steenwijk Overijssel 8331 JW",
    "addr:housenumber":"3",
    "addr:postcode":"8331 jw",
    "addr:street":"Paardenmarkt",
    "iso:country":"NL",
    "sg:address":"Paardenmarkt 3",
    "sg:city":"Steenwijk",
    "sg:orig_category":"Diverse Consumentenartikelen Gh",
    "sg:phone":"+31 521 513 051",
    "sg:postcode":"8331 JW",
    "sg:province":"Overijssel",
    "wof:name":"De Woldpoort",
    "wof:placetype":"venue"
},
  "geometry": {"coordinates":[6.112077,52.788006],"type":"Point"}
}