{
  "type": "Feature",
  "properties": {
    "iso:country":"NL",
    "sg:address":"Moesstr 50",
    "sg:city":"Groningen",
    "sg:orig_category":"Verenigingen En Stichtingen",
    "sg:phone":"+31 50 579 1640",
    "sg:postcode":"9717 JX",
    "sg:province":"Groningen",
    "wof:name":"Humanitas, Sticht",
    "wof:placetype":"venue"
},
  "geometry": {"coordinates":[6.554803,53.227856],"type":"Point"}
}