{
  "type": "Feature",
  "properties": {
    "addr:full":"Fultonstr 12 S Gravenhage Zuid-Holland 2562 XH",
    "addr:housenumber":"12;gravenhage",
    "addr:postcode":"2562 xh",
    "addr:street":"Fultonstr;S",
    "iso:country":"NL",
    "sg:address":"Fultonstr 12",
    "sg:city":"S Gravenhage",
    "sg:classifiers":[
        {
            "category":"Travel",
            "subcategory":"Hotels & Motels",
            "type":"Entertainment"
        }
    ],
    "sg:phone":"+31 70 360 8193",
    "sg:postcode":"2562 XH",
    "sg:province":"Zuid-Holland",
    "wof:name":"Uitkomst, De",
    "wof:placetype":"venue"
},
  "geometry": {"coordinates":[4.28326,52.075001],"type":"Point"}
}