{
  "type": "Feature",
  "properties": {
    "iso:country":"NL",
    "sg:address":"Kuipersveer 15",
    "sg:city":"Heinenoord",
    "sg:orig_category":"Boekhouders",
    "sg:phone":"+31 78 676 5357",
    "sg:postcode":"3274 KH",
    "sg:province":"Zuid-Holland",
    "wof:name":"Advies Buro Beekes",
    "wof:placetype":"venue"
},
  "geometry": {"coordinates":[4.555614,51.820061],"type":"Point"}
}