{
  "type": "Feature",
  "properties": {
    "addr:full":"Buijgersstraat 16 Leeuwarden Provincie Friesland 8934 BB",
    "addr:housenumber":"16",
    "addr:postcode":"8934 bb",
    "addr:street":"Buijgersstraat;Provincie Friesland",
    "iso:country":"NL",
    "sg:address":"Buijgersstraat 16",
    "sg:city":"Leeuwarden",
    "sg:orig_category":"Vertaal- And Tolkenbureaus",
    "sg:phone":"+31 58 213 6169",
    "sg:postcode":"8934 BB",
    "sg:province":"Provincie Friesland",
    "wof:name":"Damaris A. Van Der Beek",
    "wof:placetype":"venue"
},
  "geometry": {"coordinates":[5.805044,53.192284],"type":"Point"}
}