{
  "type": "Feature",
  "properties": {
    "iso:country":"NL",
    "sg:address":"Vissersstg 4",
    "sg:city":"Bunschoten Spakenb",
    "sg:orig_category":"Boeken En Tijdschriften",
    "sg:phone":"+31 33 299 6063",
    "sg:postcode":"3752 BZ",
    "sg:province":"Utrecht",
    "sg:website":"http://www.hetbaken.net",
    "wof:name":"Baken, Het",
    "wof:placetype":"venue"
},
  "geometry": {"coordinates":[5.376754,52.254166],"type":"Point"}
}