{
  "type": "Feature",
  "properties": {
    "addr:full":"Zilverdistel 5 Rotterdam Zuid-Holland 3068 NT",
    "addr:housenumber":"5",
    "addr:postcode":"3068 nt",
    "addr:street":"Zilverdistel",
    "iso:country":"NL",
    "sg:address":"Zilverdistel 5",
    "sg:city":"Rotterdam",
    "sg:orig_category":"Onteigening",
    "sg:phone":"+31 10 455 9528",
    "sg:postcode":"3068 NT",
    "sg:province":"Zuid-Holland",
    "wof:name":"Adriaans",
    "wof:placetype":"venue"
},
  "geometry": {"coordinates":[4.540442,51.953926],"type":"Point"}
}