{
  "type": "Feature",
  "properties": {
    "addr:full":"Industriewg 12B Oost W Middelbeers Noord-Brabant 5091 BG",
    "addr:housenumber":"12b",
    "addr:postcode":"middelbeers;5091",
    "addr:street":"Industriewg;W",
    "iso:country":"NL",
    "sg:address":"Industriewg 12B",
    "sg:city":"Oost W Middelbeers",
    "sg:orig_category":"Hoefsmederijen",
    "sg:phone":"+31 13 514 2560",
    "sg:postcode":"5091 BG",
    "sg:province":"Noord-Brabant",
    "wof:name":"Evers",
    "wof:placetype":"venue"
},
  "geometry": {"coordinates":[25.9494,43.04475],"type":"Point"}
}