{
  "type": "Feature",
  "properties": {
    "addr:full":"Diamantlaan 8 Groningen Groningen 9743 BG",
    "addr:housenumber":"8",
    "addr:postcode":"9743",
    "addr:street":"Diamantlaan",
    "iso:country":"NL",
    "sg:address":"Diamantlaan 8",
    "sg:city":"Groningen",
    "sg:orig_category":"Bouwmaterialen Gh",
    "sg:phone":"+31 50 318 5090",
    "sg:postcode":"9743 BG",
    "sg:province":"Groningen",
    "wof:name":"Schriever Bouwspecialiteiten Bv",
    "wof:placetype":"venue"
},
  "geometry": {"coordinates":[6.528605,53.215736],"type":"Point"}
}