{
  "type": "Feature",
  "properties": {
    "addr:full":"Kerkstraat 37 Kwintsheul South Holland 2295 LB",
    "addr:housenumber":"37",
    "addr:postcode":"2295 lb",
    "addr:street":"Kerkstraat",
    "iso:country":"NL",
    "sg:address":"Kerkstraat 37",
    "sg:city":"Kwintsheul",
    "sg:orig_category":"Bloemen And Planten",
    "sg:phone":"+31 174 292 220",
    "sg:postcode":"2295 LB",
    "sg:province":"South Holland",
    "wof:name":"Bloemenboetiek Leny",
    "wof:placetype":"venue"
},
  "geometry": {"coordinates":[4.254595,52.014999],"type":"Point"}
}