{
  "type": "Feature",
  "properties": {
    "addr:full":"Bongerd 60 Lelystad Flevoland 8212 BC",
    "addr:housenumber":"60",
    "addr:postcode":"8212 bc",
    "addr:street":"Bongerd;Flevoland",
    "iso:country":"NL",
    "sg:address":"Bongerd 60",
    "sg:city":"Lelystad",
    "sg:orig_category":"Diverse Grafische Activiteiten",
    "sg:phone":"+31 320 221 131",
    "sg:postcode":"8212 BC",
    "sg:province":"Flevoland",
    "wof:name":"Martis Reklame Lelystad",
    "wof:placetype":"venue"
},
  "geometry": {"coordinates":[5.499097,52.514854],"type":"Point"}
}