{
  "type": "Feature",
  "properties": {
    "addr:full":"Wallenbergstraat 71 Hoofddorp North Holland 2131 TS",
    "addr:housenumber":"71",
    "addr:postcode":"2131 ts",
    "addr:street":"Wallenbergstraat",
    "iso:country":"NL",
    "sg:address":"Wallenbergstraat 71",
    "sg:city":"Hoofddorp",
    "sg:orig_category":"Paramedische Behandelingen",
    "sg:phone":"+31 23 561 6893",
    "sg:postcode":"2131 TS",
    "sg:province":"North Holland",
    "wof:name":"Verloskundige Praktijk D L J De Jonge-Pool",
    "wof:placetype":"venue"
},
  "geometry": {"coordinates":[4.682207,52.300255],"type":"Point"}
}