{
  "type": "Feature",
  "properties": {
    "addr:full":"Markt 16 Sittard Limburg 6131 EK",
    "addr:housenumber":"16",
    "addr:postcode":"6131 ek",
    "addr:street":"Markt",
    "iso:country":"NL",
    "sg:address":"Markt 16",
    "sg:city":"Sittard",
    "sg:orig_category":"Cafetaria'S",
    "sg:phone":"+31 46 458 2218",
    "sg:postcode":"6131 EK",
    "sg:province":"Limburg",
    "wof:name":"Schrage",
    "wof:placetype":"venue"
},
  "geometry": {"coordinates":[5.869795,50.998901],"type":"Point"}
}