{
  "type": "Feature",
  "properties": {
    "addr:full":"Sellekamp 6 Zwolle Overijssel 8014 DR",
    "addr:housenumber":"6",
    "addr:postcode":"8014 dr",
    "addr:street":"Sellekamp",
    "iso:country":"NL",
    "sg:address":"Sellekamp 6",
    "sg:city":"Zwolle",
    "sg:classifiers":[
        {
            "category":"Food & Beverages",
            "subcategory":"Bakery",
            "type":"Retail Goods"
        }
    ],
    "sg:phone":"+31 38 465 8452",
    "sg:postcode":"8014 DR",
    "sg:province":"Overijssel",
    "sg:tags":[
        "brood",
        "en",
        "banket"
    ],
    "wof:name":"Kamphuis",
    "wof:placetype":"venue"
},
  "geometry": {"coordinates":[6.116715,52.487919],"type":"Point"}
}