{
  "type": "Feature",
  "properties": {
    "addr:full":"Kerkhofln 66 Lunteren Gelderland 6741 BN",
    "addr:housenumber":"66",
    "addr:postcode":"6741 bn",
    "addr:street":"Kerkhofln;Gelderland",
    "iso:country":"NL",
    "sg:address":"Kerkhofln 66",
    "sg:city":"Lunteren",
    "sg:orig_category":"Schilders",
    "sg:phone":"+31 318 482 897",
    "sg:postcode":"6741 BN",
    "sg:province":"Gelderland",
    "wof:name":"Boon, A",
    "wof:placetype":"venue"
},
  "geometry": {"coordinates":[5.618998,52.08688],"type":"Point"}
}