{
  "type": "Feature",
  "properties": {
    "addr:full":"Ommerkanaal 11 Dedemsvaart Overijssel 7701 RC",
    "addr:housenumber":"11",
    "addr:postcode":"7701 rc",
    "addr:street":"Ommerkanaal",
    "iso:country":"NL",
    "sg:address":"Ommerkanaal 11",
    "sg:city":"Dedemsvaart",
    "sg:orig_category":"Bouwmaterialen Gh",
    "sg:phone":"+31 523 612 820",
    "sg:postcode":"7701 RC",
    "sg:province":"Overijssel",
    "wof:name":"K.E. Kooiker'S Handelsonderneming",
    "wof:placetype":"venue"
},
  "geometry": {"coordinates":[6.44441,52.590752],"type":"Point"}
}