{
  "type": "Feature",
  "properties": {
    "addr:full":"Margrietstraat 9 Groesbeek Gelderland 6561 WS",
    "addr:housenumber":"9",
    "addr:postcode":"6561 ws",
    "addr:street":"Margrietstraat;Gelderland",
    "iso:country":"NL",
    "sg:address":"Margrietstraat 9",
    "sg:city":"Groesbeek",
    "sg:orig_category":"Discountwinkels",
    "sg:phone":"+31 24 397 5238",
    "sg:postcode":"6561 WS",
    "sg:province":"Gelderland",
    "wof:name":"Zeeman Textielsupers",
    "wof:placetype":"venue"
},
  "geometry": {"coordinates":[5.925398,51.784103],"type":"Point"}
}