{
  "type": "Feature",
  "properties": {
    "addr:full":"Postbus 764 Hilversum North Holland 1200 AT",
    "addr:housenumber":"764",
    "addr:postcode":"1200",
    "addr:street":"Postbus",
    "iso:country":"NL",
    "sg:address":"Postbus 764",
    "sg:city":"Hilversum",
    "sg:orig_category":"Verenigingen En Stichtingen",
    "sg:phone":"+31 900 8212166",
    "sg:postcode":"1200 AT",
    "sg:province":"North Holland",
    "sg:website":"http://www.donorvoorlichting.nl",
    "wof:name":"Donorvoorlichting, Stichting",
    "wof:placetype":"venue"
},
  "geometry": {"coordinates":[5.171,52.223991],"type":"Point"}
}