{
  "type": "Feature",
  "properties": {
    "addr:full":"Smallegang 1 Emmeloord Flevoland 8302 EC",
    "addr:housenumber":"1",
    "addr:postcode":"8302 ec",
    "addr:street":"Smallegang;Flevoland",
    "iso:country":"NL",
    "sg:address":"Smallegang 1",
    "sg:city":"Emmeloord",
    "sg:classifiers":[
        {
            "category":"Fast Food",
            "type":"Food & Drink"
        }
    ],
    "sg:phone":"+31 527 614 512",
    "sg:postcode":"8302 EC",
    "sg:province":"Flevoland",
    "sg:tags":[
        "afhaal",
        "restaurant"
    ],
    "wof:name":"Snackbar Harsevoort",
    "wof:placetype":"venue"
},
  "geometry": {"coordinates":[5.754836,52.711018],"type":"Point"}
}