{
  "type": "Feature",
  "properties": {
    "addr:full":"Segeersstraat 26 Middelburg Zeeland 4331 JP",
    "addr:housenumber":"26",
    "addr:postcode":"4331 jp",
    "addr:street":"Segeersstraat",
    "iso:country":"NL",
    "sg:address":"Segeersstraat 26",
    "sg:city":"Middelburg",
    "sg:orig_category":"Baby- And Kinderkleding",
    "sg:phone":"+31 118 640 481",
    "sg:postcode":"4331 JP",
    "sg:province":"Zeeland",
    "wof:name":"Jou Jou Bv",
    "wof:placetype":"venue"
},
  "geometry": {"coordinates":[3.615558,51.497978],"type":"Point"}
}