{
  "type": "Feature",
  "properties": {
    "addr:full":"Nieuwe Hammerweg 10 Ommen NL.08 7731 TV",
    "addr:housenumber":"10;nl.08",
    "addr:postcode":"7731 tv",
    "addr:street":"Nieuwe Hammerweg",
    "iso:country":"NL",
    "sg:address":"Nieuwe Hammerweg 10",
    "sg:city":"Ommen",
    "sg:orig_category":"Kampeerterreinen",
    "sg:phone":"+31 546 672 017",
    "sg:postcode":"7731 TV",
    "sg:province":"NL.08",
    "wof:name":"De Vogelsangh",
    "wof:placetype":"venue"
},
  "geometry": {"coordinates":[6.50893116,52.4916305542],"type":"Point"}
}