{
  "type": "Feature",
  "properties": {
    "addr:full":"Calandweg 10 Arnemuiden Zeeland 4341 RA",
    "addr:housenumber":"10",
    "addr:postcode":"4341 ra",
    "addr:street":"Calandweg",
    "iso:country":"NL",
    "sg:address":"Calandweg 10",
    "sg:city":"Arnemuiden",
    "sg:orig_category":"Luchtvaart",
    "sg:phone":"+31 113 613 293",
    "sg:postcode":"4341 RA",
    "sg:province":"Zeeland",
    "wof:name":"Vliegwerk Holland Bv Zeeland Airport",
    "wof:placetype":"venue"
},
  "geometry": {"coordinates":[3.728119,51.513554],"type":"Point"}
}