{
  "type": "Feature",
  "properties": {
    "addr:full":"H Vd Meystr 7 Heemskerk Noord-Holland 1963 DH",
    "addr:housenumber":"7",
    "addr:postcode":"1963 dh",
    "iso:country":"NL",
    "sg:address":"H Vd Meystr 7",
    "sg:city":"Heemskerk",
    "sg:orig_category":"Adviesbureaus Bedrijfsorganisatie",
    "sg:phone":"+31 251 235 875",
    "sg:postcode":"1963 DH",
    "sg:province":"Noord-Holland",
    "sg:website":"http://www.pleysierbusinesssupport.nl",
    "wof:name":"Pleysier Support Bv",
    "wof:placetype":"venue"
},
  "geometry": {"coordinates":[4.66983,52.513546],"type":"Point"}
}