{
  "type": "Feature",
  "properties": {
    "addr:full":"Fahrenheitstr 608 S Gravenhage Zuid-Holland 2561 DK",
    "addr:housenumber":"608;gravenhage",
    "addr:postcode":"2561 dk",
    "addr:street":"S",
    "iso:country":"NL",
    "sg:address":"Fahrenheitstr 608",
    "sg:city":"S Gravenhage",
    "sg:orig_category":"Juweliers",
    "sg:phone":"+31 70 362 3012",
    "sg:postcode":"2561 DK",
    "sg:province":"Zuid-Holland",
    "wof:name":"Ros & Zn Bv",
    "wof:placetype":"venue"
},
  "geometry": {"coordinates":[4.27581,52.074532],"type":"Point"}
}