{
  "type": "Feature",
  "properties": {
    "addr:full":"Marsmanstr 1 Ridderkerk Zuid-Holland 2985 BG",
    "addr:housenumber":"1",
    "addr:postcode":"2985",
    "addr:street":"Marsmanstr",
    "iso:country":"NL",
    "sg:address":"Marsmanstr 1",
    "sg:city":"Ridderkerk",
    "sg:orig_category":"Kinderopvang",
    "sg:phone":"+31 180 421 170",
    "sg:postcode":"2985 BG",
    "sg:province":"Zuid-Holland",
    "wof:name":"Baloe",
    "wof:placetype":"venue"
},
  "geometry": {"coordinates":[4.60507,51.862141],"type":"Point"}
}