{
  "type": "Feature",
  "properties": {
    "iso:country":"NL",
    "sg:address":"Richtersln 58",
    "sg:city":"Nieuwegein",
    "sg:classifiers":[
        {
            "category":"Professional",
            "subcategory":"Accounting & Tax Preparation",
            "type":"Services"
        }
    ],
    "sg:phone":"+31 30 602 3602",
    "sg:postcode":"3431 AK",
    "sg:province":"Utrecht",
    "sg:tags":[
        "accountant",
        "en",
        "-kantoren",
        "register-"
    ],
    "sg:website":"http://www.mooring.nl",
    "wof:name":"Mooring",
    "wof:placetype":"venue"
},
  "geometry": {"coordinates":[5.078629,52.035744],"type":"Point"}
}