{
  "type": "Feature",
  "properties": {
    "addr:full":"Kelvinstr 19 Wychen Gelderland 6601 HH",
    "addr:housenumber":"19",
    "addr:postcode":"6601 hh",
    "addr:street":"Kelvinstr;Gelderland",
    "iso:country":"NL",
    "sg:address":"Kelvinstr 19",
    "sg:city":"Wychen",
    "sg:orig_category":"Meubelmakerijen",
    "sg:phone":"+31 24 373 7351",
    "sg:postcode":"6601 HH",
    "sg:province":"Gelderland",
    "wof:name":"Ferdinand Rossen",
    "wof:placetype":"venue"
},
  "geometry": {"coordinates":[5.742591,51.814678],"type":"Point"}
}