{
  "type": "Feature",
  "properties": {
    "addr:full":"Lynbaan 8 Lemmer Provincie Friesland 8531 JR",
    "addr:housenumber":"8;8531",
    "addr:street":"Lynbaan;Provincie Friesland",
    "iso:country":"NL",
    "sg:address":"Lynbaan 8",
    "sg:city":"Lemmer",
    "sg:orig_category":"Bloemen En Planten",
    "sg:phone":"+31 514 561 913",
    "sg:postcode":"8531 JR",
    "sg:province":"Provincie Friesland",
    "wof:name":"He-As",
    "wof:placetype":"venue"
},
  "geometry": {"coordinates":[5.712385,52.844051],"type":"Point"}
}