{
  "type": "Feature",
  "properties": {
    "addr:full":"Burg Prinsln 22 Ede Gld Gelderland 6711 KD",
    "addr:housenumber":"22",
    "addr:postcode":"6711 kd",
    "addr:street":"Burg;Gld Gelderland",
    "iso:country":"NL",
    "sg:address":"Burg Prinsln 22",
    "sg:city":"Ede Gld",
    "sg:orig_category":"Bedrijfsopleidingen",
    "sg:phone":"+31 318 655 268",
    "sg:postcode":"6711 KD",
    "sg:province":"Gelderland",
    "sg:website":"http://www.translearn.com",
    "wof:name":"Translearn",
    "wof:placetype":"venue"
},
  "geometry": {"coordinates":[5.66767,52.044979],"type":"Point"}
}