{
  "type": "Feature",
  "properties": {
    "addr:full":"Bedryvenwg 18D Leiderdorp Zuid-Holland 2351 BC",
    "addr:housenumber":"18d",
    "addr:postcode":"2351 bc",
    "addr:street":"Bedryvenwg",
    "iso:country":"NL",
    "sg:address":"Bedryvenwg 18D",
    "sg:city":"Leiderdorp",
    "sg:orig_category":"Wasmachines En Wasdrogers - Onderhoud En Reparatie",
    "sg:phone":"+31 71 589 1436",
    "sg:postcode":"2351 BC",
    "sg:province":"Zuid-Holland",
    "wof:name":"Steenbergen Bv",
    "wof:placetype":"venue"
},
  "geometry": {"coordinates":[4.5463209152,52.1413879395],"type":"Point"}
}