{
  "type": "Feature",
  "properties": {
    "addr:full":"Hoogstraat 19 Werkendam Noord-Brabant 4251 CH",
    "addr:housenumber":"19",
    "addr:postcode":"4251",
    "addr:street":"Hoogstraat",
    "iso:country":"NL",
    "sg:address":"Hoogstraat 19",
    "sg:city":"Werkendam",
    "sg:orig_category":"Kappers",
    "sg:phone":"+31 183 502 100",
    "sg:postcode":"4251 CH",
    "sg:province":"Noord-Brabant",
    "wof:name":"Hairline The Family Hairshop",
    "wof:placetype":"venue"
},
  "geometry": {"coordinates":[4.8953170776,51.8083724976],"type":"Point"}
}