{
  "type": "Feature",
  "properties": {
    "addr:full":"Overtoom 1 Ijsselstein Ut Utrecht 3401 BK",
    "addr:housenumber":"1",
    "addr:postcode":"3401 bk",
    "addr:street":"Overtoom",
    "iso:country":"NL",
    "sg:address":"Overtoom 1",
    "sg:city":"Ijsselstein Ut",
    "sg:orig_category":"Overheidsdiensten",
    "sg:phone":"+31 30 686 1611",
    "sg:postcode":"3401 BK",
    "sg:province":"Utrecht",
    "wof:name":"Gemeente Ijsselstein",
    "wof:placetype":"venue"
},
  "geometry": {"coordinates":[5.0426602364,52.0170440674],"type":"Point"}
}