{
  "type": "Feature",
  "properties": {
    "addr:full":"Heeleind 31 Bladel Noord-Brabant 5531 CA",
    "addr:housenumber":"31",
    "addr:postcode":"5531 ca",
    "addr:street":"Heeleind",
    "iso:country":"NL",
    "sg:address":"Heeleind 31",
    "sg:city":"Bladel",
    "sg:orig_category":"Fotostudio'S And Fotografen",
    "sg:phone":"+31 497 387 389",
    "sg:postcode":"5531 CA",
    "sg:province":"Noord-Brabant",
    "wof:name":"Ad Biemans Fotografie",
    "wof:placetype":"venue"
},
  "geometry": {"coordinates":[5.222791,51.364235],"type":"Point"}
}