{
  "type": "Feature",
  "properties": {
    "addr:full":"Industriestr 43 Tegelen Limburg 5931 PH",
    "addr:housenumber":"43",
    "addr:postcode":"5931",
    "addr:street":"Industriestr",
    "iso:country":"NL",
    "sg:address":"Industriestr 43",
    "sg:city":"Tegelen",
    "sg:orig_category":"Horeca-Inrichtingen En -Uitrustingen",
    "sg:phone":"+31 77 373 3939",
    "sg:postcode":"5931 PH",
    "sg:province":"Limburg",
    "wof:name":"Ress Nederland Bv",
    "wof:placetype":"venue"
},
  "geometry": {"coordinates":[6.138634,51.338814],"type":"Point"}
}