{
  "type": "Feature",
  "properties": {
    "addr:full":"Rietdekkersdreef 415 Apeldoorn Gelderland 7328 AE",
    "addr:housenumber":"415",
    "addr:postcode":"7328 ae",
    "addr:street":"Rietdekkersdreef;Gelderland",
    "iso:country":"NL",
    "sg:address":"Rietdekkersdreef 415",
    "sg:city":"Apeldoorn",
    "sg:orig_category":"Webdesign Bureaus",
    "sg:phone":"+31 55 355 1889",
    "sg:postcode":"7328 AE",
    "sg:province":"Gelderland",
    "sg:website":"http://www.vanderschaardevelopments.net",
    "wof:name":"Schaar, Van Der",
    "wof:placetype":"venue"
},
  "geometry": {"coordinates":[5.9851732254,52.1963233948],"type":"Point"}
}