{
  "type": "Feature",
  "properties": {
    "iso:country":"NL",
    "sg:address":"Keskesweg 17",
    "sg:city":"Asten",
    "sg:orig_category":"Elektriciens",
    "sg:phone":"+31 493 692 375",
    "sg:postcode":"5721 WS",
    "sg:province":"North Brabant",
    "wof:name":"Van Der Kruissen Electro Bv",
    "wof:placetype":"venue"
},
  "geometry": {"coordinates":[5.742277,51.411873],"type":"Point"}
}