{
  "type": "Feature",
  "properties": {
    "iso:country":"NL",
    "sg:address":"Raadhuisplein 11",
    "sg:city":"Stein Lb",
    "sg:orig_category":"Banken And Kredietinstellingen",
    "sg:phone":"+31 46 433 1260",
    "sg:postcode":"6171 JB",
    "sg:province":"Limburg",
    "wof:name":"Postkantoor",
    "wof:placetype":"venue"
},
  "geometry": {"coordinates":[-93.129936,36.705662],"type":"Point"}
}