{
  "type": "Feature",
  "properties": {
    "addr:full":"Benedenrywg 461 Ridderkerk Zuid-Holland 2983 LA",
    "addr:housenumber":"461",
    "addr:postcode":"2983 la",
    "iso:country":"NL",
    "sg:address":"Benedenrywg 461",
    "sg:city":"Ridderkerk",
    "sg:orig_category":"Verenigingen En Stichtingen",
    "sg:phone":"+31 180 622 133",
    "sg:postcode":"2983 LA",
    "sg:province":"Zuid-Holland",
    "wof:name":"Huys Ten Donck, Sticht Het",
    "wof:placetype":"venue"
},
  "geometry": {"coordinates":[4.594253,51.889984],"type":"Point"}
}