{
  "type": "Feature",
  "properties": {
    "iso:country":"NL",
    "sg:address":"Provincialewg 12",
    "sg:city":"Amsterdam Zuidoost",
    "sg:orig_category":"Beeldende Kunstenaars",
    "sg:phone":"+31 294 410 405",
    "sg:postcode":"1108 AA",
    "sg:province":"North Holland",
    "wof:name":"Wiering, J H",
    "wof:placetype":"venue"
},
  "geometry": {"coordinates":[4.998471,52.312206],"type":"Point"}
}