{
  "type": "Feature",
  "properties": {
    "iso:country":"NL",
    "sg:address":"Lauriergr 47B",
    "sg:city":"Amsterdam",
    "sg:orig_category":"Homeopathie",
    "sg:phone":"+31 20 622 3290",
    "sg:postcode":"1016 RG",
    "sg:province":"Noord-Holland",
    "wof:name":"Z?rcher Christine Kinderhomeopaat",
    "wof:placetype":"venue"
},
  "geometry": {"coordinates":[4.880891,52.371181],"type":"Point"}
}