{
  "type": "Feature",
  "properties": {
    "addr:full":"Dreef 20 Haarlem Noord-Holland 2012 HS",
    "addr:housenumber":"20",
    "addr:postcode":"2012 hs",
    "addr:street":"Dreef",
    "iso:country":"NL",
    "sg:address":"Dreef 20",
    "sg:city":"Haarlem",
    "sg:classifiers":[
        {
            "category":"Education",
            "subcategory":"Preschool",
            "type":"Public Place"
        }
    ],
    "sg:phone":"+31 23 531 2912",
    "sg:postcode":"2012 HS",
    "sg:province":"Noord-Holland",
    "sg:tags":[
        "kleuteronderwijs",
        "basis-"
    ],
    "wof:name":"Dreefschool",
    "wof:placetype":"venue"
},
  "geometry": {"coordinates":[4.629425,52.372921],"type":"Point"}
}