{
  "type": "Feature",
  "properties": {
    "addr:full":"Zwaanshals 281 Rotterdam Zuid-Holland 3035 KG",
    "addr:housenumber":"281",
    "addr:postcode":"3035 kg",
    "addr:street":"Zwaanshals",
    "iso:country":"NL",
    "sg:address":"Zwaanshals 281",
    "sg:city":"Rotterdam",
    "sg:orig_category":"Kappers",
    "sg:phone":"+31 10 467 3747",
    "sg:postcode":"3035 KG",
    "sg:province":"Zuid-Holland",
    "wof:name":"Dameskapsalon Esra",
    "wof:placetype":"venue"
},
  "geometry": {"coordinates":[4.4858498573,51.933139801],"type":"Point"}
}