{
  "type": "Feature",
  "properties": {
    "addr:full":"V Beukelaarwg 42 Bleskensgraaf Ca South Holland 2971 VL",
    "addr:housenumber":"42",
    "addr:postcode":"ca;2971 vl",
    "iso:country":"NL",
    "sg:address":"V Beukelaarwg 42",
    "sg:city":"Bleskensgraaf Ca",
    "sg:orig_category":"Autoschade- Herstelbedrijven",
    "sg:phone":"+31 184 694 069",
    "sg:postcode":"2971 VL",
    "sg:province":"South Holland",
    "wof:name":"Bakker",
    "wof:placetype":"venue"
},
  "geometry": {"coordinates":[4.784609,51.870838],"type":"Point"}
}