{
  "type": "Feature",
  "properties": {
    "addr:full":"Lord Kelvinstr 4 Amsterdam Noord-Holland 1098 SC",
    "addr:housenumber":"4",
    "addr:postcode":"1098 sc",
    "iso:country":"NL",
    "sg:address":"Lord Kelvinstr 4",
    "sg:city":"Amsterdam",
    "sg:orig_category":"Ballonnen - Fabrieken En Groothandel",
    "sg:phone":"+31 20 463 3091",
    "sg:postcode":"1098 SC",
    "sg:province":"Noord-Holland",
    "wof:name":"Zeppelin",
    "wof:placetype":"venue"
},
  "geometry": {"coordinates":[4.941511,52.350788],"type":"Point"}
}