{
  "type": "Feature",
  "properties": {
    "iso:country":"NL",
    "sg:address":"Zuiderzeestr 38",
    "sg:city":"Aartswoud",
    "sg:orig_category":"Houtgroothandel Rondhout",
    "sg:phone":"+31 229 582 771",
    "sg:postcode":"1719 LB",
    "sg:province":"Noord-Holland",
    "wof:name":"Graafland, Bosbouwaannemer H T",
    "wof:placetype":"venue"
},
  "geometry": {"coordinates":[4.95557,52.749836],"type":"Point"}
}