{
  "type": "Feature",
  "properties": {
    "addr:full":"Singel 10B Lippenhuizen California 8408 CA",
    "addr:housenumber":"10b",
    "addr:postcode":"8408 ca",
    "addr:street":"Singel",
    "iso:country":"NL",
    "sg:address":"Singel 10B",
    "sg:city":"Lippenhuizen",
    "sg:orig_category":"Metselwerken",
    "sg:phone":"+31 516 462 273",
    "sg:postcode":"8408 CA",
    "sg:province":"California",
    "wof:name":"Leeuw Bv, De",
    "wof:placetype":"venue"
},
  "geometry": {"coordinates":[-119.270203,37.271832],"type":"Point"}
}