{
  "type": "Feature",
  "properties": {
    "addr:full":"Hobeinstraat 52 Vlissingen Zeeland 4381 PE",
    "addr:housenumber":"52",
    "addr:postcode":"4381 pe",
    "addr:street":"Hobeinstraat",
    "iso:country":"NL",
    "sg:address":"Hobeinstraat 52",
    "sg:city":"Vlissingen",
    "sg:orig_category":"Medische Apparatuur And Prothesen Fab",
    "sg:phone":"+31 118 414 533",
    "sg:postcode":"4381 PE",
    "sg:province":"Zeeland",
    "wof:name":"Tandtechn. Lab.Bedrijf J.P.A. Rossel",
    "wof:placetype":"venue"
},
  "geometry": {"coordinates":[3.57002,51.447212],"type":"Point"}
}