{
  "type": "Feature",
  "properties": {
    "addr:full":"Van Haersoltelaan 48 Barneveld Gelderland 3771 JW",
    "addr:housenumber":"48",
    "addr:postcode":"3771 jw",
    "addr:street":"Van Haersoltelaan;Gelderland",
    "iso:country":"NL",
    "sg:address":"Van Haersoltelaan 48",
    "sg:city":"Barneveld",
    "sg:orig_category":"Bloemen And Planten",
    "sg:phone":"+31 342 413 248",
    "sg:postcode":"3771 JW",
    "sg:province":"Gelderland",
    "wof:name":"Annemijn",
    "wof:placetype":"venue"
},
  "geometry": {"coordinates":[5.591999,52.154453],"type":"Point"}
}