{
  "type": "Feature",
  "properties": {
    "iso:country":"NL",
    "sg:address":"Volmolen 12",
    "sg:city":"Enkhuizen",
    "sg:orig_category":"Goederenvervoer Over De Weg",
    "sg:phone":"+31 228 321 856",
    "sg:postcode":"1601 ET",
    "sg:province":"North Holland",
    "wof:name":"Int Transportbedrijf De Zwaluw Bv",
    "wof:placetype":"venue"
},
  "geometry": {"coordinates":[5.277775,52.692226],"type":"Point"}
}