{
  "type": "Feature",
  "properties": {
    "addr:full":"Koppelstraat 95 Beek En Donk Noord-Brabant 5741 GB",
    "addr:housenumber":"95",
    "addr:postcode":"5741 gb",
    "addr:street":"Koppelstraat",
    "iso:country":"NL",
    "sg:address":"Koppelstraat 95",
    "sg:city":"Beek En Donk",
    "sg:orig_category":"Chemische Producten Gh",
    "sg:phone":"+31 492 465 520",
    "sg:postcode":"5741 GB",
    "sg:province":"Noord-Brabant",
    "wof:name":"Ovem Bv",
    "wof:placetype":"venue"
},
  "geometry": {"coordinates":[5.630218,51.539291],"type":"Point"}
}