{
  "type": "Feature",
  "properties": {
    "iso:country":"NL",
    "sg:address":"Kortlandstraat 41",
    "sg:city":"Krimpen A/D Ijssel",
    "sg:orig_category":"Bloemen And Planten",
    "sg:phone":"+31 180 590 590",
    "sg:postcode":"2922 XC",
    "sg:province":"Zuid-Holland",
    "wof:name":"Tuincentrum Krimpen",
    "wof:placetype":"venue"
},
  "geometry": {"coordinates":[4.583809,51.91674],"type":"Point"}
}