{
  "type": "Feature",
  "properties": {
    "addr:full":"Rosegracht 1 Terneuzen Zeeland 4531 HB",
    "addr:housenumber":"1",
    "addr:postcode":"4531 hb",
    "addr:street":"Rosegracht",
    "iso:country":"NL",
    "sg:address":"Rosegracht 1",
    "sg:city":"Terneuzen",
    "sg:orig_category":"Overheidsdiensten",
    "sg:phone":"+31 115 681 500",
    "sg:postcode":"4531 HB",
    "sg:province":"Zeeland",
    "wof:name":"Belastingdienst Ondernemingen Goes Vestiging Terne",
    "wof:placetype":"venue"
},
  "geometry": {"coordinates":[3.82899189,51.334854126],"type":"Point"}
}