{
  "type": "Feature",
  "properties": {
    "addr:full":"Patio 180 Hoorn Nh Noord-Holland 1628 LJ",
    "addr:housenumber":"180",
    "addr:postcode":"1628 lj",
    "addr:street":"Patio",
    "iso:country":"NL",
    "sg:address":"Patio 180",
    "sg:city":"Hoorn Nh",
    "sg:orig_category":"Partycatering And -Organisatie",
    "sg:phone":"+31 229 232 024",
    "sg:postcode":"1628 LJ",
    "sg:province":"Noord-Holland",
    "wof:name":"Pierre Rent A Cook",
    "wof:placetype":"venue"
},
  "geometry": {"coordinates":[5.088616,52.64946],"type":"Point"}
}