{
  "type": "Feature",
  "properties": {
    "addr:full":"Stadhouderswg 76 St Annaparochie Provincie Friesland 9076 AG",
    "addr:housenumber":"76",
    "addr:postcode":"9076",
    "addr:street":"Stadhouderswg;St;Provincie Friesland",
    "iso:country":"NL",
    "sg:address":"Stadhouderswg 76",
    "sg:city":"St Annaparochie",
    "sg:orig_category":"Begrafenisverzorging",
    "sg:phone":"+31 518 402 376",
    "sg:postcode":"9076 AG",
    "sg:province":"Provincie Friesland",
    "wof:name":"Annaparochie, St",
    "wof:placetype":"venue"
},
  "geometry": {"coordinates":[5.655625,53.284798],"type":"Point"}
}