{
  "type": "Feature",
  "properties": {
    "addr:full":"Pasmaatwg 36 Hengelo Ov NL.08 7556 PH",
    "addr:housenumber":"36",
    "addr:postcode":"7556",
    "addr:street":"Pasmaatwg;Ov",
    "iso:country":"NL",
    "sg:address":"Pasmaatwg 36",
    "sg:city":"Hengelo Ov",
    "sg:orig_category":"Keukens",
    "sg:phone":"+31 74 250 0540",
    "sg:postcode":"7556 PH",
    "sg:province":"NL.08",
    "wof:name":"Nieuwenhuis",
    "wof:placetype":"venue"
},
  "geometry": {"coordinates":[6.780024,52.277412],"type":"Point"}
}