{
  "type": "Feature",
  "properties": {
    "iso:country":"NL",
    "sg:address":"Maanlander 41",
    "sg:city":"Amersfoort",
    "sg:orig_category":"Grafisch Ontwerpers",
    "sg:phone":"+31 33 457 1264",
    "sg:postcode":"3824 MN",
    "sg:province":"Utrecht",
    "wof:name":"Intens Design",
    "wof:placetype":"venue"
},
  "geometry": {"coordinates":[5.39507,52.195118],"type":"Point"}
}