{
  "type": "Feature",
  "properties": {
    "addr:full":"Boommarkt 9 Leiden Zuid-Holland 2311 EA",
    "addr:housenumber":"9",
    "addr:postcode":"2311 ea",
    "addr:street":"Boommarkt",
    "iso:country":"NL",
    "sg:address":"Boommarkt 9",
    "sg:city":"Leiden",
    "sg:orig_category":"Diverse Grafische Activiteiten",
    "sg:phone":"+31 71 514 4812",
    "sg:postcode":"2311 EA",
    "sg:province":"Zuid-Holland",
    "wof:name":"De Leydsche Boeckbinder",
    "wof:placetype":"venue"
},
  "geometry": {"coordinates":[4.486702,52.160316],"type":"Point"}
}