{
  "type": "Feature",
  "properties": {
    "addr:full":"Rondstaai 2 Grevenbicht Limburg 6127 AD",
    "addr:housenumber":"2",
    "addr:postcode":"6127 ad",
    "addr:street":"Rondstaai",
    "iso:country":"NL",
    "sg:address":"Rondstaai 2",
    "sg:city":"Grevenbicht",
    "sg:orig_category":"Bloemen En Planten",
    "sg:phone":"+31 46 485 7632",
    "sg:postcode":"6127 AD",
    "sg:province":"Limburg",
    "wof:name":"Valkenburg",
    "wof:placetype":"venue"
},
  "geometry": {"coordinates":[5.774465,51.044479],"type":"Point"}
}