{
  "type": "Feature",
  "properties": {
    "addr:full":"Einsteinstr 13 Vlierden North Brabant 5756 AX",
    "addr:housenumber":"13",
    "addr:postcode":"5756 ax",
    "addr:street":"Einsteinstr",
    "iso:country":"NL",
    "sg:address":"Einsteinstr 13",
    "sg:city":"Vlierden",
    "sg:orig_category":"Kappers",
    "sg:phone":"+31 493 316 312",
    "sg:postcode":"5756 AX",
    "sg:province":"North Brabant",
    "wof:name":"Marjon",
    "wof:placetype":"venue"
},
  "geometry": {"coordinates":[5.757824,51.445847],"type":"Point"}
}