{
  "type": "Feature",
  "properties": {
    "addr:full":"P Bedynstr 22 Noordwyk Zh Zuid-Holland 2202 VK",
    "addr:housenumber":"22",
    "addr:postcode":"2202 vk",
    "addr:street":"P;Noordwyk",
    "iso:country":"NL",
    "sg:address":"P Bedynstr 22",
    "sg:city":"Noordwyk Zh",
    "sg:orig_category":"Bloemen En Planten - Groothandel",
    "sg:phone":"+31 71 361 4635",
    "sg:postcode":"2202 VK",
    "sg:province":"Zuid-Holland",
    "wof:name":"Oostdam Bv, Ben",
    "wof:placetype":"venue"
},
  "geometry": {"coordinates":[4.4274601936,52.2360305786],"type":"Point"}
}