{
  "type": "Feature",
  "properties": {
    "addr:full":"Groenstraat 198 Landgraaf Limburg 6374 JV",
    "addr:housenumber":"198",
    "addr:postcode":"6374 jv",
    "addr:street":"Groenstraat",
    "iso:country":"NL",
    "sg:address":"Groenstraat 198",
    "sg:city":"Landgraaf",
    "sg:orig_category":"Autokeuringen",
    "sg:phone":"+31 45 531 2932",
    "sg:postcode":"6374 JV",
    "sg:province":"Limburg",
    "wof:name":"J H Horbach",
    "wof:placetype":"venue"
},
  "geometry": {"coordinates":[6.054946,50.910854],"type":"Point"}
}