{
  "type": "Feature",
  "properties": {
    "addr:full":"Zonnehoven 9 Zeewolde Flevoland 3893 CA",
    "addr:housenumber":"9",
    "addr:postcode":"3893 ca",
    "addr:street":"Zonnehoven;Flevoland",
    "iso:country":"NL",
    "sg:address":"Zonnehoven 9",
    "sg:city":"Zeewolde",
    "sg:orig_category":"Administratie- En Boekhoudkantoren",
    "sg:phone":"+31 36 522 2406",
    "sg:postcode":"3893 CA",
    "sg:province":"Flevoland",
    "wof:name":"Brons, W",
    "wof:placetype":"venue"
},
  "geometry": {"coordinates":[5.522374,52.330585],"type":"Point"}
}