{
  "type": "Feature",
  "properties": {
    "addr:full":"Werftseweg 1 Breda Noord-Brabant 4823 ZG",
    "addr:housenumber":"1",
    "addr:postcode":"4823 zg",
    "addr:street":"Werftseweg",
    "iso:country":"NL",
    "sg:address":"Werftseweg 1",
    "sg:city":"Breda",
    "sg:orig_category":"Bloemen And Planten Gh",
    "sg:phone":"+31 76 541 1152",
    "sg:postcode":"4823 ZG",
    "sg:province":"Noord-Brabant",
    "wof:name":"Theeuwes Mengvoeders Breda",
    "wof:placetype":"venue"
},
  "geometry": {"coordinates":[4.725335,51.625549],"type":"Point"}
}