{
  "type": "Feature",
  "properties": {
    "addr:full":"Rochus Meeuwiszoonweg 8 Brielle Zuid-Holland 3231 CM",
    "addr:housenumber":"8",
    "addr:postcode":"3231 cm",
    "addr:street":"Meeuwiszoonweg",
    "iso:country":"NL",
    "sg:address":"Rochus Meeuwiszoonweg 8",
    "sg:city":"Brielle",
    "sg:orig_category":"Pleziervaartuigen And Reparatie",
    "sg:phone":"+31 181 412 073",
    "sg:postcode":"3231 CM",
    "sg:province":"Zuid-Holland",
    "wof:name":"Holland Boat Parts",
    "wof:placetype":"venue"
},
  "geometry": {"coordinates":[4.174108,51.90897],"type":"Point"}
}