{
  "type": "Feature",
  "properties": {
    "addr:full":"Avignonln 27 Eindhoven Noord-Brabant 5627 GA",
    "addr:housenumber":"27",
    "addr:postcode":"5627 ga",
    "addr:street":"Avignonln",
    "iso:country":"NL",
    "sg:address":"Avignonln 27",
    "sg:city":"Eindhoven",
    "sg:orig_category":"Waterkoelers En Drinkwaterinstallaties",
    "sg:phone":"+31 499 477 077",
    "sg:postcode":"5627 GA",
    "sg:province":"Noord-Brabant",
    "wof:name":"Culligan",
    "wof:placetype":"venue"
},
  "geometry": {"coordinates":[5.4414200783,51.4846382141],"type":"Point"}
}