{
  "type": "Feature",
  "properties": {
    "addr:full":"Noordloo 27 Annen South Carolina 9468 AV",
    "addr:housenumber":"27;9468",
    "addr:street":"Noordloo;Av",
    "iso:country":"NL",
    "sg:address":"Noordloo 27",
    "sg:city":"Annen",
    "sg:orig_category":"Bedrijfs- And Managementsconsultants",
    "sg:phone":"+31 592 272 842",
    "sg:postcode":"9468 AV",
    "sg:province":"South Carolina",
    "wof:name":"Adviesbureau Roozeboom",
    "wof:placetype":"venue"
},
  "geometry": {"coordinates":[-79.253815,33.471233],"type":"Point"}
}