{
  "type": "Feature",
  "properties": {
    "iso:country":"NL",
    "sg:address":"Fokkerstr 505",
    "sg:city":"Schiedam",
    "sg:orig_category":"Drukkerijen",
    "sg:phone":"+31 10 238 0400",
    "sg:postcode":"3125 BD",
    "sg:province":"Zuid-Holland",
    "sg:website":"http://www.tds.nu",
    "wof:name":"Tds Printmaildata",
    "wof:placetype":"venue"
},
  "geometry": {"coordinates":[4.398311,51.932289],"type":"Point"}
}