{
  "type": "Feature",
  "properties": {
    "addr:full":"G Flinckstraat 195 Amsterdam Noord-Holland 1072 BV",
    "addr:housenumber":"195",
    "addr:postcode":"1072 bv",
    "addr:street":"Flinckstraat",
    "iso:country":"NL",
    "sg:address":"G Flinckstraat 195",
    "sg:city":"Amsterdam",
    "sg:orig_category":"Bibliotheken And Openbare Archieven",
    "sg:phone":"+31 20 662 7881",
    "sg:postcode":"1072 BV",
    "sg:province":"Noord-Holland",
    "wof:name":"Jochem Wijnands Photos & Features",
    "wof:placetype":"venue"
},
  "geometry": {"coordinates":[4.89332,52.355042],"type":"Point"}
}