{
  "type": "Feature",
  "properties": {
    "addr:full":"Ruysdaelstr 110 Amsterdam Noord-Holland 1071 XH",
    "addr:housenumber":"110",
    "addr:postcode":"1071 xh",
    "iso:country":"NL",
    "sg:address":"Ruysdaelstr 110",
    "sg:city":"Amsterdam",
    "sg:orig_category":"Kinderopvang",
    "sg:phone":"+31 20 675 5554",
    "sg:postcode":"1071 XH",
    "sg:province":"Noord-Holland",
    "wof:name":"Trompet, De",
    "wof:placetype":"venue"
},
  "geometry": {"coordinates":[4.880003,52.353516],"type":"Point"}
}