{
  "type": "Feature",
  "properties": {
    "addr:full":"Het Ruim 11 Dronten NL. 8251 EL",
    "addr:housenumber":"11",
    "addr:postcode":"8251 el",
    "addr:street":"Het Ruim;Nl.",
    "iso:country":"NL",
    "sg:address":"Het Ruim 11",
    "sg:city":"Dronten",
    "sg:orig_category":"Banken And Kredietinstellingen",
    "sg:phone":"+31 321 312 555",
    "sg:postcode":"8251 EL",
    "sg:province":"NL.",
    "wof:name":"Ing Bank",
    "wof:placetype":"venue"
},
  "geometry": {"coordinates":[5.718907,52.525173],"type":"Point"}
}