{
  "type": "Feature",
  "properties": {
    "iso:country":"NL",
    "sg:address":"Avercampstraat 76",
    "sg:city":"Amsterdam",
    "sg:orig_category":"Meubelzaken, Woning- And Keukeninrichting",
    "sg:phone":"+31 20 670 1578",
    "sg:postcode":"1072 RB",
    "sg:province":"North Holland",
    "wof:name":"Meubelrandus",
    "wof:placetype":"venue"
},
  "geometry": {"coordinates":[4.8927,52.350044],"type":"Point"}
}