{
  "type": "Feature",
  "properties": {
    "iso:country":"NL",
    "sg:address":"Kranewg 76",
    "sg:city":"Groningen",
    "sg:orig_category":"Kappers",
    "sg:phone":"+31 50 314 6240",
    "sg:postcode":"9718 JV",
    "sg:province":"Groningen",
    "wof:name":"Binnenhof, Het",
    "wof:placetype":"venue"
},
  "geometry": {"coordinates":[6.5489959717,53.21667099],"type":"Point"}
}