{
  "type": "Feature",
  "properties": {
    "addr:full":"Walstro 9 Leusden Utrecht 3831 WT",
    "addr:housenumber":"9",
    "addr:postcode":"3831 wt",
    "addr:street":"Walstro",
    "iso:country":"NL",
    "sg:address":"Walstro 9",
    "sg:city":"Leusden",
    "sg:orig_category":"Kantoor- En Secretariaatsservice",
    "sg:phone":"+31 33 432 2033",
    "sg:postcode":"3831 WT",
    "sg:province":"Utrecht",
    "wof:name":"Swarts, I",
    "wof:placetype":"venue"
},
  "geometry": {"coordinates":[5.4459600449,52.1367797852],"type":"Point"}
}