{
  "type": "Feature",
  "properties": {
    "addr:full":"Voorthuizerstraat 16 Putten Gelderland 3881 SH",
    "addr:housenumber":"16;3881",
    "addr:postcode":"sh",
    "addr:street":"Voorthuizerstraat;Gelderland",
    "iso:country":"NL",
    "sg:address":"Voorthuizerstraat 16",
    "sg:city":"Putten",
    "sg:orig_category":"Bedrijfs- And Managementsconsultants",
    "sg:phone":"+31 341 358 327",
    "sg:postcode":"3881 SH",
    "sg:province":"Gelderland",
    "wof:name":"Bv Veluwse Associatie Van Adviseurs",
    "wof:placetype":"venue"
},
  "geometry": {"coordinates":[5.61008,52.258106],"type":"Point"}
}