{
  "type": "Feature",
  "properties": {
    "addr:full":"Gedempte Gracht 47 Zaandam Noord-Holland 1506  C",
    "addr:housenumber":"47;1506 c",
    "addr:street":"Gedempte Gracht",
    "iso:country":"NL",
    "sg:address":"Gedempte Gracht 47",
    "sg:city":"Zaandam",
    "sg:orig_category":"Boekenuitgeverijen",
    "sg:phone":"+31 75 612 3247",
    "sg:postcode":"1506  C",
    "sg:province":"Noord-Holland",
    "wof:name":"Bruna",
    "wof:placetype":"venue"
},
  "geometry": {"coordinates":[4.822318,52.439552],"type":"Point"}
}