{
  "type": "Feature",
  "properties": {
    "iso:country":"NL",
    "sg:address":"Poststr 11",
    "sg:city":"Krabbendyke",
    "sg:orig_category":"Postkantoren",
    "sg:phone":"+31 113 504 650",
    "sg:postcode":"4413 CJ",
    "sg:province":"Zeeland",
    "wof:name":"Countrystore Lemar",
    "wof:placetype":"venue"
},
  "geometry": {"coordinates":[4.111191,51.431664],"type":"Point"}
}