{
  "type": "Feature",
  "properties": {
    "addr:full":"Marconibaan 42A Nieuwegein Utrecht 3439 MS",
    "addr:housenumber":"42a",
    "addr:postcode":"3439 ms",
    "addr:street":"Marconibaan",
    "iso:country":"NL",
    "sg:address":"Marconibaan 42A",
    "sg:city":"Nieuwegein",
    "sg:orig_category":"Projectinrichting",
    "sg:phone":"+31 30 605 8020",
    "sg:postcode":"3439 MS",
    "sg:province":"Utrecht",
    "sg:website":"http://www.todaydesign.nl",
    "wof:name":"Today Design Bv",
    "wof:placetype":"venue"
},
  "geometry": {"coordinates":[5.102418,52.027725],"type":"Point"}
}