{
  "type": "Feature",
  "properties": {
    "addr:full":"Blokjesplaat 49 Goes Zeeland 4465 BG",
    "addr:housenumber":"49",
    "addr:postcode":"4465",
    "addr:street":"Blokjesplaat",
    "iso:country":"NL",
    "sg:address":"Blokjesplaat 49",
    "sg:city":"Goes",
    "sg:orig_category":"Adviesbureaus Economie",
    "sg:phone":"+31 113 270 150",
    "sg:postcode":"4465 BG",
    "sg:province":"Zeeland",
    "wof:name":"Louisse",
    "wof:placetype":"venue"
},
  "geometry": {"coordinates":[24.05335,42.361012],"type":"Point"}
}