{
  "type": "Feature",
  "properties": {
    "iso:country":"NL",
    "sg:address":"Boerhaavelaan 75 B",
    "sg:city":"Schiedam",
    "sg:orig_category":"Loodgieterswerk, Verwarming And Sanitaire Installaties",
    "sg:phone":"+31 10 273 4920",
    "sg:postcode":"3112  L",
    "sg:province":"Zuid-Holland",
    "wof:name":"Altech",
    "wof:placetype":"venue"
},
  "geometry": {"coordinates":[4.412235,51.916817],"type":"Point"}
}