{
  "type": "Feature",
  "properties": {
    "addr:full":"Vincent Van Goghplein 4 Helvoirt North Brabant 5268 BZ",
    "addr:housenumber":"4",
    "addr:postcode":"5268 bz",
    "addr:street":"Vincent Van Goghplein",
    "iso:country":"NL",
    "sg:address":"Vincent Van Goghplein 4",
    "sg:city":"Helvoirt",
    "sg:classifiers":[
        {
            "category":"Fast Food",
            "type":"Food & Drink"
        }
    ],
    "sg:phone":"+31 411 643 448",
    "sg:postcode":"5268 BZ",
    "sg:province":"North Brabant",
    "sg:tags":[
        "afhaal",
        "restaurant"
    ],
    "wof:name":"T Passantje",
    "wof:placetype":"venue"
},
  "geometry": {"coordinates":[5.229969,51.630733],"type":"Point"}
}