{
  "type": "Feature",
  "properties": {
    "iso:country":"NL",
    "sg:address":"Laan Van Nieuw Guinea 80",
    "sg:city":"Utrecht",
    "sg:classifiers":[
        {
            "category":"Bakery",
            "type":"Food & Drink"
        }
    ],
    "sg:phone":"+31 30 293 1436",
    "sg:postcode":"3531 JM",
    "sg:province":"Utrecht",
    "sg:tags":[
        "brood",
        "banket"
    ],
    "wof:name":"Fa Uyterwaal",
    "wof:placetype":"venue"
},
  "geometry": {"coordinates":[5.085586,52.09367],"type":"Point"}
}