{
  "type": "Feature",
  "properties": {
    "addr:full":"Schepersmaat 14 Beltrum Gelderland 7156 JZ",
    "addr:housenumber":"14",
    "addr:postcode":"7156 jz",
    "addr:street":"Schepersmaat;Gelderland",
    "iso:country":"NL",
    "sg:address":"Schepersmaat 14",
    "sg:city":"Beltrum",
    "sg:orig_category":"Schoenen",
    "sg:phone":"+31 544 481 381",
    "sg:postcode":"7156 JZ",
    "sg:province":"Gelderland",
    "wof:name":"Schoenhandel Delsing",
    "wof:placetype":"venue"
},
  "geometry": {"coordinates":[6.569202,52.066391],"type":"Point"}
}