{
  "type": "Feature",
  "properties": {
    "addr:full":"Steenbakkerstr 16 Haastrecht Zuid-Holland 2851 AX",
    "addr:housenumber":"16",
    "addr:postcode":"2851 ax",
    "addr:street":"Steenbakkerstr",
    "iso:country":"NL",
    "sg:address":"Steenbakkerstr 16",
    "sg:city":"Haastrecht",
    "sg:orig_category":"Ventilatiesystemen",
    "sg:phone":"+31 182 503 111",
    "sg:postcode":"2851 AX",
    "sg:province":"Zuid-Holland",
    "wof:name":"Ventilatie Techniek Gouda",
    "wof:placetype":"venue"
},
  "geometry": {"coordinates":[4.783867,52.002113],"type":"Point"}
}