{
  "type": "Feature",
  "properties": {
    "iso:country":"NL",
    "sg:address":"Snip 20",
    "sg:city":"Groningen",
    "sg:orig_category":"Vertaalbureaus",
    "sg:phone":"+31 50 525 3278",
    "sg:postcode":"9728 XR",
    "sg:province":"Groningen",
    "wof:name":"Ferwerda Drs, A G",
    "wof:placetype":"venue"
},
  "geometry": {"coordinates":[6.541756,53.180592],"type":"Point"}
}