{
  "type": "Feature",
  "properties": {
    "addr:full":"Heimanswg 35 Amsterdam Noord-Holland 1031 TZ",
    "addr:housenumber":"35",
    "addr:postcode":"1031 tz",
    "addr:street":"Heimanswg",
    "iso:country":"NL",
    "sg:address":"Heimanswg 35",
    "sg:city":"Amsterdam",
    "sg:orig_category":"Geluidsinstallaties - Verhuur",
    "sg:phone":"+31 20 634 1753",
    "sg:postcode":"1031 TZ",
    "sg:province":"Noord-Holland",
    "wof:name":"Adss",
    "wof:placetype":"venue"
},
  "geometry": {"coordinates":[4.907171,52.389523],"type":"Point"}
}