{
  "type": "Feature",
  "properties": {
    "addr:full":"Kerkweg 30 Cothen Utrecht 3945 BN",
    "addr:housenumber":"30",
    "addr:postcode":"3945 bn",
    "addr:street":"Kerkweg",
    "iso:country":"NL",
    "sg:address":"Kerkweg 30",
    "sg:city":"Cothen",
    "sg:orig_category":"Kantoorartikelen",
    "sg:phone":"+31 343 562 155",
    "sg:postcode":"3945 BN",
    "sg:province":"Utrecht",
    "wof:name":"Van Bommel Bv",
    "wof:placetype":"venue"
},
  "geometry": {"coordinates":[5.3079957962,51.9993934631],"type":"Point"}
}