{
  "type": "Feature",
  "properties": {
    "addr:full":"Verwersstraat 5 'S Hertogenbosch North Brabant 5211 HS",
    "addr:housenumber":"5 ' s",
    "addr:postcode":"5211 hs",
    "addr:street":"Verwersstraat;Hertogenbosch",
    "iso:country":"NL",
    "sg:address":"Verwersstraat 5",
    "sg:city":"'S Hertogenbosch",
    "sg:orig_category":"Herenmodezaken",
    "sg:phone":"+31 73 614 6423",
    "sg:postcode":"5211 HS",
    "sg:province":"North Brabant",
    "wof:name":"Confectiebedrijf Van Dal Bv",
    "wof:placetype":"venue"
},
  "geometry": {"coordinates":[5.304134,51.687675],"type":"Point"}
}