{
  "type": "Feature",
  "properties": {
    "iso:country":"NL",
    "sg:address":"Winkelc Woensel 83D",
    "sg:city":"Eindhoven",
    "sg:orig_category":"Hulpverlening Sociaal",
    "sg:phone":"+31 40 292 6680",
    "sg:postcode":"5625 AE",
    "sg:province":"Noord-Brabant",
    "wof:name":"Maatschappelijk Werk Woensel Noord",
    "wof:placetype":"venue"
},
  "geometry": {"coordinates":[5.475628,51.470615],"type":"Point"}
}