{
  "type": "Feature",
  "properties": {
    "iso:country":"NL",
    "sg:address":"Zichtenburgln 46",
    "sg:city":"S Gravenhage",
    "sg:orig_category":"Horecabenodigdheden",
    "sg:phone":"+31 70 367 7156",
    "sg:postcode":"2544 EB",
    "sg:province":"South Holland",
    "wof:name":"Amex",
    "wof:placetype":"venue"
},
  "geometry": {"coordinates":[4.25157,52.039551],"type":"Point"}
}