{
  "type": "Feature",
  "properties": {
    "iso:country":"NL",
    "sg:address":"Oosterblokker 28",
    "sg:city":"Oosterblokker",
    "sg:orig_category":"Adviesbureaus Bedrijfsorganisatie",
    "sg:phone":"+31 229 264 797",
    "sg:postcode":"1696 BH",
    "sg:province":"Noord-Holland",
    "sg:website":"http://www.itsme.nl",
    "wof:name":"It'S Me",
    "wof:placetype":"venue"
},
  "geometry": {"coordinates":[5.110263,52.66552],"type":"Point"}
}