{
  "type": "Feature",
  "properties": {
    "addr:full":"Akerkhof 43B Groningen Groningen 9712 BC",
    "addr:housenumber":"43b",
    "addr:postcode":"9712 bc",
    "addr:street":"Akerkhof",
    "iso:country":"NL",
    "sg:address":"Akerkhof 43B",
    "sg:city":"Groningen",
    "sg:orig_category":"Psychologen",
    "sg:phone":"+31 50 311 1135",
    "sg:postcode":"9712 BC",
    "sg:province":"Groningen",
    "sg:website":"http://www.christinebrons.nl",
    "wof:name":"Brons Bv Drs T C",
    "wof:placetype":"venue"
},
  "geometry": {"coordinates":[6.561643,53.21666],"type":"Point"}
}