{
  "type": "Feature",
  "properties": {
    "addr:full":"Aelderstraat 42 Aalden Drenthe 7854 RR",
    "addr:housenumber":"42",
    "addr:postcode":"7854 rr",
    "addr:street":"Aelderstraat",
    "iso:country":"NL",
    "sg:address":"Aelderstraat 42",
    "sg:city":"Aalden",
    "sg:orig_category":"Banken And Kredietinstellingen",
    "sg:phone":"+31 591 371 215",
    "sg:postcode":"7854 RR",
    "sg:province":"Drenthe",
    "wof:name":"Postkantoor",
    "wof:placetype":"venue"
},
  "geometry": {"coordinates":[6.72154,52.790249],"type":"Point"}
}