{
  "type": "Feature",
  "properties": {
    "addr:full":"West-Kruiskade 33 Rotterdam Zuid-Holland 3014 AK",
    "addr:housenumber":"33",
    "addr:postcode":"3014 ak",
    "addr:street":"West-Kruiskade",
    "iso:country":"NL",
    "sg:address":"West-Kruiskade 33",
    "sg:city":"Rotterdam",
    "sg:orig_category":"Kappers",
    "sg:phone":"+31 10 414 0447",
    "sg:postcode":"3014 AK",
    "sg:province":"Zuid-Holland",
    "wof:name":"Kapsalon Elaine",
    "wof:placetype":"venue"
},
  "geometry": {"coordinates":[4.4693260193,51.9205627441],"type":"Point"}
}