{
  "type": "Feature",
  "properties": {
    "addr:full":"Trimpertstraat 12 Deurne North Brabant 5752 AN",
    "addr:housenumber":"12",
    "addr:postcode":"5752 an",
    "addr:street":"Trimpertstraat",
    "iso:country":"NL",
    "sg:address":"Trimpertstraat 12",
    "sg:city":"Deurne",
    "sg:orig_category":"Kappers",
    "sg:phone":"+31 493 323 327",
    "sg:postcode":"5752 AN",
    "sg:province":"North Brabant",
    "wof:name":"Happy Hair",
    "wof:placetype":"venue"
},
  "geometry": {"coordinates":[5.8046870232,51.4743881226],"type":"Point"}
}