{
  "type": "Feature",
  "properties": {
    "addr:full":"Stellingmune 2 Dokkum Friesland 9102 EC",
    "addr:housenumber":"2",
    "addr:postcode":"9102 ec",
    "addr:street":"Stellingmune",
    "iso:country":"NL",
    "sg:address":"Stellingmune 2",
    "sg:city":"Dokkum",
    "sg:classifiers":[
        {
            "category":"Personal",
            "subcategory":"Nail Salon",
            "type":"Services"
        }
    ],
    "sg:phone":"+31 519 220 605",
    "sg:postcode":"9102 EC",
    "sg:province":"Friesland",
    "sg:tags":[
        "pedicure"
    ],
    "wof:name":"Wiersma-Van Der Zwaag",
    "wof:placetype":"venue"
},
  "geometry": {"coordinates":[5.995749,53.331341],"type":"Point"}
}