{
  "type": "Feature",
  "properties": {
    "addr:full":"Dorpsstraat 13 Schoonrewoerd South Holland 4145  K",
    "addr:housenumber":"13",
    "addr:postcode":"4145 k",
    "addr:street":"Dorpsstraat",
    "iso:country":"NL",
    "sg:address":"Dorpsstraat 13",
    "sg:city":"Schoonrewoerd",
    "sg:orig_category":"Huishoudapparatuur, Televisies And Radio'S",
    "sg:phone":"+31 345 641 773",
    "sg:postcode":"4145  K",
    "sg:province":"South Holland",
    "wof:name":"W.I.J.A. Zonnebankservice",
    "wof:placetype":"venue"
},
  "geometry": {"coordinates":[5.116395,51.92009],"type":"Point"}
}