{
  "type": "Feature",
  "properties": {
    "addr:full":"V Duivenvoordeln 21B Wassenaar Zuid-Holland 2241 SM",
    "addr:housenumber":"21b",
    "addr:postcode":"2241 sm",
    "addr:street":"V Duivenvoordeln",
    "iso:country":"NL",
    "sg:address":"V Duivenvoordeln 21B",
    "sg:city":"Wassenaar",
    "sg:orig_category":"Handwerkartikelen",
    "sg:phone":"+31 70 514 5535",
    "sg:postcode":"2241 SM",
    "sg:province":"Zuid-Holland",
    "wof:name":"Lalis",
    "wof:placetype":"venue"
},
  "geometry": {"coordinates":[4.404514,52.145847],"type":"Point"}
}