{
  "type": "Feature",
  "properties": {
    "addr:full":"Rodehaanstr 10 Zwolle Overijssel 8011 RR",
    "addr:housenumber":"10",
    "addr:postcode":"8011 rr",
    "addr:street":"Rodehaanstr",
    "iso:country":"NL",
    "sg:address":"Rodehaanstr 10",
    "sg:city":"Zwolle",
    "sg:classifiers":[
        {
            "category":"Shopping",
            "subcategory":"Adult",
            "type":"Retail Goods"
        }
    ],
    "sg:phone":"+31 38 422 2768",
    "sg:postcode":"8011 RR",
    "sg:province":"Overijssel",
    "sg:tags":[
        "lingerie",
        "en",
        "tricotage"
    ],
    "wof:name":"Sandrabra",
    "wof:placetype":"venue"
},
  "geometry": {"coordinates":[6.096626,52.512371],"type":"Point"}
}