{
  "type": "Feature",
  "properties": {
    "addr:full":"De Oude Bleijk 4 Leidschendam Zuid-Holland 2266 CK",
    "addr:housenumber":"4",
    "addr:postcode":"2266 ck",
    "addr:street":"De Oude Bleijk",
    "iso:country":"NL",
    "sg:address":"De Oude Bleijk 4",
    "sg:city":"Leidschendam",
    "sg:classifiers":[
        {
            "category":"Education",
            "subcategory":"Preschool",
            "type":"Public Place"
        }
    ],
    "sg:phone":"+31 70 327 4042",
    "sg:postcode":"2266 CK",
    "sg:province":"Zuid-Holland",
    "sg:tags":[
        "kleuteronderwijs",
        "basis-"
    ],
    "wof:name":"Joannes Xxiiie School",
    "wof:placetype":"venue"
},
  "geometry": {"coordinates":[4.399363,52.07774],"type":"Point"}
}