{
  "type": "Feature",
  "properties": {
    "addr:full":"Nassauwg 30 S Heerenhoek Zeeland 4453 VJ",
    "addr:housenumber":"30",
    "addr:postcode":"4453 vj",
    "addr:street":"Nassauwg;S Heerenhoek Zeeland",
    "iso:country":"NL",
    "sg:address":"Nassauwg 30",
    "sg:city":"S Heerenhoek",
    "sg:orig_category":"Land- En Tuinbouw - Loonbedrijven",
    "sg:phone":"+31 113 351 425",
    "sg:postcode":"4453 VJ",
    "sg:province":"Zeeland",
    "wof:name":"Rentmeester, Gebr",
    "wof:placetype":"venue"
},
  "geometry": {"coordinates":[3.774921,51.462616],"type":"Point"}
}