{
  "type": "Feature",
  "properties": {
    "iso:country":"NL",
    "sg:address":"Scheendijk 21",
    "sg:city":"Breukelen Ut",
    "sg:orig_category":"Architecten",
    "sg:phone":"+31 346 265 663",
    "sg:postcode":"3621 VC",
    "sg:province":"Utrecht",
    "wof:name":"Van Gelder Procesmanagement",
    "wof:placetype":"venue"
},
  "geometry": {"coordinates":[5.020621,52.178604],"type":"Point"}
}