{
  "type": "Feature",
  "properties": {
    "addr:full":"Kamp 16 Amersfoort Utrecht 3811 AR",
    "addr:housenumber":"16",
    "addr:postcode":"3811",
    "addr:street":"Kamp",
    "iso:country":"NL",
    "sg:address":"Kamp 16",
    "sg:city":"Amersfoort",
    "sg:classifiers":[
        {
            "category":"Shopping",
            "subcategory":"Gifts & Souvenirs",
            "type":"Retail Goods"
        }
    ],
    "sg:phone":"+31 33 253 8606",
    "sg:postcode":"3811 AR",
    "sg:province":"Utrecht",
    "sg:tags":[
        "geschenken"
    ],
    "wof:name":"Merapi",
    "wof:placetype":"venue"
},
  "geometry": {"coordinates":[5.393811,52.157562],"type":"Point"}
}