{
  "type": "Feature",
  "properties": {
    "iso:country":"NL",
    "sg:address":"Stephensonstr 20",
    "sg:city":"Zoetermeer",
    "sg:classifiers":[
        {
            "category":"Wholesale",
            "subcategory":"Meat",
            "type":"Manufacturing & Wholesale Goods"
        }
    ],
    "sg:phone":"+31 79 346 4242",
    "sg:postcode":"2723 RN",
    "sg:province":"Zuid-Holland",
    "sg:tags":[
        "regeltechniek",
        "en",
        "meet-"
    ],
    "sg:website":"http://www.servomex.com",
    "wof:name":"Servomex Bv",
    "wof:placetype":"venue"
},
  "geometry": {"coordinates":[4.52735,52.063457],"type":"Point"}
}