{
  "type": "Feature",
  "properties": {
    "iso:country":"NL",
    "sg:address":"Kwakschewg 4",
    "sg:city":"Oud Beyerland",
    "sg:orig_category":"Adviesbureaus Bedrijfsorganisatie",
    "sg:phone":"+31 186 627 016",
    "sg:postcode":"3261 LG",
    "sg:province":"Zuid-Holland",
    "wof:name":"Lakmoes",
    "wof:placetype":"venue"
},
  "geometry": {"coordinates":[4.427664,51.81036],"type":"Point"}
}