{
  "type": "Feature",
  "properties": {
    "addr:full":"Sint Joosterweg 5 Maasbracht Limburg 6051 HE",
    "addr:housenumber":"5",
    "addr:postcode":"6051 he",
    "addr:street":"Sint Joosterweg",
    "iso:country":"NL",
    "sg:address":"Sint Joosterweg 5",
    "sg:city":"Maasbracht",
    "sg:orig_category":"Overheidsdiensten",
    "sg:phone":"+31 475 437 100",
    "sg:postcode":"6051 HE",
    "sg:province":"Limburg",
    "wof:name":"Rijkswaterstaat Dienstkring St. Joost",
    "wof:placetype":"venue"
},
  "geometry": {"coordinates":[5.8948459625,51.1373443604],"type":"Point"}
}