{
  "type": "Feature",
  "properties": {
    "addr:full":"Oostlaarsestraat 28 Roosendaal Noord-Brabant 4703 SB",
    "addr:housenumber":"28",
    "addr:postcode":"4703 sb",
    "addr:street":"Oostlaarsestraat",
    "iso:country":"NL",
    "sg:address":"Oostlaarsestraat 28",
    "sg:city":"Roosendaal",
    "sg:classifiers":[
        {
            "category":"Fast Food",
            "type":"Food & Drink"
        }
    ],
    "sg:phone":"+31 165 304 081",
    "sg:postcode":"4703 SB",
    "sg:province":"Noord-Brabant",
    "sg:tags":[
        "afhaal",
        "restaurant"
    ],
    "wof:name":"J. Maas Frituur",
    "wof:placetype":"venue"
},
  "geometry": {"coordinates":[4.412261,51.511131],"type":"Point"}
}