{
  "type": "Feature",
  "properties": {
    "addr:full":"Varkevisserstraat 249 Katwijk Nb South Holland 2225 LB",
    "addr:housenumber":"249",
    "addr:postcode":"2225 lb",
    "addr:street":"Varkevisserstraat;Nb",
    "iso:country":"NL",
    "sg:address":"Varkevisserstraat 249",
    "sg:city":"Katwijk Nb",
    "sg:orig_category":"Huisdierenfokkers",
    "sg:phone":"+31 71 407 7586",
    "sg:postcode":"2225 LB",
    "sg:province":"South Holland",
    "wof:name":"Norfolk Terrier Club Nederland",
    "wof:placetype":"venue"
},
  "geometry": {"coordinates":[4.396585,52.205109],"type":"Point"}
}