{
  "type": "Feature",
  "properties": {
    "iso:country":"NL",
    "sg:address":"Maxwellstr 29",
    "sg:city":"Ede Gld",
    "sg:orig_category":"Autoreclame",
    "sg:phone":"+31 318 668 848",
    "sg:postcode":"6716 BX",
    "sg:province":"Gelderland",
    "wof:name":"One Day",
    "wof:placetype":"venue"
},
  "geometry": {"coordinates":[5.61684,52.028542],"type":"Point"}
}