{
  "type": "Feature",
  "properties": {
    "addr:full":"Oosterengweg 32 Hilversum Noord-Holland 1221 JV",
    "addr:housenumber":"32",
    "addr:postcode":"1221 jv",
    "addr:street":"Oosterengweg",
    "iso:country":"NL",
    "sg:address":"Oosterengweg 32",
    "sg:city":"Hilversum",
    "sg:orig_category":"Diverse Bedrijfsinstallaties Gh",
    "sg:phone":"+31 35 683 8444",
    "sg:postcode":"1221 JV",
    "sg:province":"Noord-Holland",
    "wof:name":"P.H. Van Vugt Jr Bv",
    "wof:placetype":"venue"
},
  "geometry": {"coordinates":[5.193977,52.221001],"type":"Point"}
}