{
  "type": "Feature",
  "properties": {
    "addr:full":"Hoge Der A 3 Groningen Groningen 9712 AC",
    "addr:housenumber":"3",
    "addr:postcode":"9712 ac",
    "addr:street":"Hoge Der A",
    "iso:country":"NL",
    "sg:address":"Hoge Der A 3",
    "sg:city":"Groningen",
    "sg:orig_category":"Discotheken",
    "sg:phone":"+31 50 312 7188",
    "sg:postcode":"9712 AC",
    "sg:province":"Groningen",
    "wof:name":"Mac, The",
    "wof:placetype":"venue"
},
  "geometry": {"coordinates":[6.559849,53.216854],"type":"Point"}
}