{
  "type": "Feature",
  "properties": {
    "addr:full":"Beetsstraat 200 'S Gravenhage Zuid-Holland 2524 RE",
    "addr:housenumber":"200 '",
    "addr:postcode":"2524 re",
    "addr:street":"Beetsstraat",
    "iso:country":"NL",
    "sg:address":"Beetsstraat 200",
    "sg:city":"'S Gravenhage",
    "sg:orig_category":"Overheidsdiensten",
    "sg:phone":"+31 70 394 8958",
    "sg:postcode":"2524 RE",
    "sg:province":"Zuid-Holland",
    "wof:name":"De Fram Buurtcentrum",
    "wof:placetype":"venue"
},
  "geometry": {"coordinates":[4.3111028671,52.0512886047],"type":"Point"}
}