{
  "type": "Feature",
  "properties": {
    "addr:full":"L Kerkdam 6 Wassenaar Zuid-Holland 2242 BV",
    "addr:housenumber":"6",
    "addr:postcode":"2242 bv",
    "addr:street":"Kerkdam",
    "iso:country":"NL",
    "sg:address":"L Kerkdam 6",
    "sg:city":"Wassenaar",
    "sg:orig_category":"Notarissen En Notariskantoren",
    "sg:phone":"+31 70 512 3131",
    "sg:postcode":"2242 BV",
    "sg:province":"Zuid-Holland",
    "wof:name":"Hartog, Mr B Den",
    "wof:placetype":"venue"
},
  "geometry": {"coordinates":[4.397,52.142094],"type":"Point"}
}