{
  "type": "Feature",
  "properties": {
    "addr:full":"Bloemgr 66 Amsterdam Noord-Holland 1015 TL",
    "addr:housenumber":"66",
    "addr:postcode":"1015 tl",
    "addr:street":"Bloemgr",
    "iso:country":"NL",
    "sg:address":"Bloemgr 66",
    "sg:city":"Amsterdam",
    "sg:orig_category":"Adviesbureaus Bedrijfsorganisatie",
    "sg:phone":"+31 20 625 4639",
    "sg:postcode":"1015 TL",
    "sg:province":"Noord-Holland",
    "wof:name":"Greep",
    "wof:placetype":"venue"
},
  "geometry": {"coordinates":[4.881526,52.375114],"type":"Point"}
}