{
  "type": "Feature",
  "properties": {
    "iso:country":"NL",
    "sg:address":"Koningshoek 91",
    "sg:city":"Maassluis",
    "sg:orig_category":"Schoenen",
    "sg:phone":"+31 10 591 1800",
    "sg:postcode":"3144 BA",
    "sg:province":"Zuid-Holland",
    "wof:name":"Toe Sjoe",
    "wof:placetype":"venue"
},
  "geometry": {"coordinates":[4.24083,51.92754],"type":"Point"}
}