{
  "type": "Feature",
  "properties": {
    "addr:full":"Punter 2910 Lelystad Flevoland 8242 EB",
    "addr:postcode":"2910;8242 eb",
    "addr:street":"Punter;Flevoland",
    "iso:country":"NL",
    "sg:address":"Punter 2910",
    "sg:city":"Lelystad",
    "sg:orig_category":"Tandartsen",
    "sg:phone":"+31 320 247 867",
    "sg:postcode":"8242 EB",
    "sg:province":"Flevoland",
    "wof:name":"J.G.P.M. Gruyters",
    "wof:placetype":"venue"
},
  "geometry": {"coordinates":[5.449527,52.515259],"type":"Point"}
}