{
  "type": "Feature",
  "properties": {
    "addr:full":"Walakkers 5 Dalen Drenthe 7751 DC",
    "addr:housenumber":"5",
    "addr:postcode":"7751",
    "addr:street":"Walakkers",
    "iso:country":"NL",
    "sg:address":"Walakkers 5",
    "sg:city":"Dalen",
    "sg:orig_category":"Adviesbureaus Economie",
    "sg:phone":"+31 524 551 620",
    "sg:postcode":"7751 DC",
    "sg:province":"Drenthe",
    "wof:name":"Wieloo Bv",
    "wof:placetype":"venue"
},
  "geometry": {"coordinates":[6.7545,52.705589],"type":"Point"}
}