{
  "type": "Feature",
  "properties": {
    "iso:country":"NL",
    "sg:address":"Fahrenheitstr 5-7",
    "sg:city":"Dordrecht",
    "sg:classifiers":[
        {
            "category":"Manufacturing",
            "subcategory":"Textiles",
            "type":"Manufacturing & Wholesale Goods"
        }
    ],
    "sg:phone":"+31 78 613 9089",
    "sg:postcode":"3316 AG",
    "sg:province":"Zuid-Holland",
    "sg:tags":[
        "polyester"
    ],
    "wof:name":"Harjon Ned Kunststof Centrum Bv",
    "wof:placetype":"venue"
},
  "geometry": {"coordinates":[4.641975,51.798847],"type":"Point"}
}