{
  "type": "Feature",
  "properties": {
    "addr:full":"Egmondstraat 7 Weert Limburg 6001 XH",
    "addr:housenumber":"7",
    "addr:postcode":"6001 xh",
    "addr:street":"Egmondstraat",
    "iso:country":"NL",
    "sg:address":"Egmondstraat 7",
    "sg:city":"Weert",
    "sg:orig_category":"Diverse Grafische Activiteiten",
    "sg:phone":"+31 495 451 725",
    "sg:postcode":"6001 XH",
    "sg:province":"Limburg",
    "wof:name":"Drukkerij Art-Is",
    "wof:placetype":"venue"
},
  "geometry": {"coordinates":[5.711351,51.256607],"type":"Point"}
}