{
  "type": "Feature",
  "properties": {
    "addr:full":"St Jansberg 1 Milsbeek Limburg 6596 MK",
    "addr:housenumber":"1",
    "addr:postcode":"6596",
    "addr:street":"St Jansberg",
    "iso:country":"NL",
    "sg:address":"St Jansberg 1",
    "sg:city":"Milsbeek",
    "sg:orig_category":"Verkoopautomaten",
    "sg:phone":"+31 485 516 506",
    "sg:postcode":"6596 MK",
    "sg:province":"Limburg",
    "wof:name":"Bever",
    "wof:placetype":"venue"
},
  "geometry": {"coordinates":[5.951602,51.741314],"type":"Point"}
}