{
  "type": "Feature",
  "properties": {
    "addr:full":"Burg V Raaystr 26 Beers Nb Noord-Brabant 5437 BD",
    "addr:housenumber":"26",
    "addr:postcode":"5437 bd",
    "addr:street":"Burg V Raaystr",
    "iso:country":"NL",
    "sg:address":"Burg V Raaystr 26",
    "sg:city":"Beers Nb",
    "sg:orig_category":"Voetbalverenigingen",
    "sg:phone":"+31 485 318 430",
    "sg:postcode":"5437 BD",
    "sg:province":"Noord-Brabant",
    "wof:name":"Hbv",
    "wof:placetype":"venue"
},
  "geometry": {"coordinates":[5.82934,51.72488],"type":"Point"}
}