{
  "type": "Feature",
  "properties": {
    "addr:full":"K Delfswg 4 Beverwyk North Holland 1942 ES",
    "addr:housenumber":"4",
    "addr:postcode":"1942 es",
    "addr:street":"Delfswg;North",
    "iso:country":"NL",
    "sg:address":"K Delfswg 4",
    "sg:city":"Beverwyk",
    "sg:classifiers":[
        {
            "category":"Home & Garden",
            "subcategory":"Building Materials",
            "type":"Retail Goods"
        }
    ],
    "sg:phone":"+31 251 223 862",
    "sg:postcode":"1942 ES",
    "sg:province":"North Holland",
    "sg:tags":[
        "hout",
        "en",
        "board",
        "triplex"
    ],
    "wof:name":"Veen'S Houthandel Beverwijk, V/D",
    "wof:placetype":"venue"
},
  "geometry": {"coordinates":[4.654929,52.483471],"type":"Point"}
}