{
  "type": "Feature",
  "properties": {
    "addr:full":"De Wal 12 Oss Noord-Brabant 5341 EH",
    "addr:housenumber":"12",
    "addr:postcode":"5341 eh",
    "addr:street":"De Wal",
    "iso:country":"NL",
    "sg:address":"De Wal 12",
    "sg:city":"Oss",
    "sg:orig_category":"Werving And Selectie Van Tijdelijk Personeel And Uitzendkantoren",
    "sg:phone":"+31 412 637 733",
    "sg:postcode":"5341 EH",
    "sg:province":"Noord-Brabant",
    "wof:name":"Content",
    "wof:placetype":"venue"
},
  "geometry": {"coordinates":[-91.2236175537,44.5808181763],"type":"Point"}
}