{
  "type": "Feature",
  "properties": {
    "iso:country":"NL",
    "sg:address":"Eperweg 6",
    "sg:city":"Heerde",
    "sg:orig_category":"Bloemen And Planten",
    "sg:phone":"+31 578 560 200",
    "sg:postcode":"8181 EW",
    "sg:province":"Gelderland",
    "wof:name":"De Binnentuin Bloemen&Woonaccessoires",
    "wof:placetype":"venue"
},
  "geometry": {"coordinates":[6.036035,52.386322],"type":"Point"}
}