{
  "type": "Feature",
  "properties": {
    "addr:full":"Grote Markt 20 'S Gravenhage Zuid-Holland 2511 BG",
    "addr:housenumber":"20",
    "addr:postcode":"2511",
    "addr:street":"Grote Markt;' S",
    "iso:country":"NL",
    "sg:address":"Grote Markt 20",
    "sg:city":"'S Gravenhage",
    "sg:orig_category":"Metaalwerken",
    "sg:phone":"+31 70 365 1059",
    "sg:postcode":"2511 BG",
    "sg:province":"Zuid-Holland",
    "wof:name":"Center Tapijt",
    "wof:placetype":"venue"
},
  "geometry": {"coordinates":[4.309633,52.075714],"type":"Point"}
}