{
  "type": "Feature",
  "properties": {
    "addr:full":"Brinkstraat 11 Denekamp NL.08 7591 DM",
    "addr:housenumber":"11;nl.08",
    "addr:postcode":"7591 dm",
    "addr:street":"Brinkstraat",
    "iso:country":"NL",
    "sg:address":"Brinkstraat 11",
    "sg:city":"Denekamp",
    "sg:orig_category":"Kappers",
    "sg:phone":"+31 541 351 544",
    "sg:postcode":"7591 DM",
    "sg:province":"NL.08",
    "wof:name":"Salon Huub",
    "wof:placetype":"venue"
},
  "geometry": {"coordinates":[7.004037,52.376228],"type":"Point"}
}