{
  "type": "Feature",
  "properties": {
    "addr:full":"Wedderweg 173 Oude Pekela Groningen 9665 JP",
    "addr:housenumber":"173",
    "addr:postcode":"pekela;9665 jp",
    "addr:street":"Wedderweg",
    "iso:country":"NL",
    "sg:address":"Wedderweg 173",
    "sg:city":"Oude Pekela",
    "sg:orig_category":"Fruit And Groenten Gh",
    "sg:phone":"+31 597 612 779",
    "sg:postcode":"9665 JP",
    "sg:province":"Groningen",
    "wof:name":"C.G. Dijkhuizen",
    "wof:placetype":"venue"
},
  "geometry": {"coordinates":[7.024726,53.083679],"type":"Point"}
}