{
  "type": "Feature",
  "properties": {
    "addr:full":"Veerweg 40 Kamperland Zeeland 4493 AS",
    "addr:housenumber":"40",
    "addr:postcode":"4493 as",
    "addr:street":"Veerweg",
    "iso:country":"NL",
    "sg:address":"Veerweg 40",
    "sg:city":"Kamperland",
    "sg:orig_category":"Autokeuringen",
    "sg:phone":"+31 113 371 234",
    "sg:postcode":"4493 AS",
    "sg:province":"Zeeland",
    "wof:name":"Garage C.J. Van Halst En Zoon",
    "wof:placetype":"venue"
},
  "geometry": {"coordinates":[3.703314,51.571228],"type":"Point"}
}