{
  "type": "Feature",
  "properties": {
    "addr:full":"Huenderstraat 2 Eibergen Gelderland 7151 DC",
    "addr:housenumber":"2",
    "addr:postcode":"7151",
    "addr:street":"Huenderstraat;Gelderland",
    "iso:country":"NL",
    "sg:address":"Huenderstraat 2",
    "sg:city":"Eibergen",
    "sg:orig_category":"Bibliotheken And Openbare Archieven",
    "sg:phone":"+31 545 475 631",
    "sg:postcode":"7151 DC",
    "sg:province":"Gelderland",
    "wof:name":"Speel-O-Theek De Bromtol",
    "wof:placetype":"venue"
},
  "geometry": {"coordinates":[6.644993,52.101242],"type":"Point"}
}