{
  "type": "Feature",
  "properties": {
    "addr:full":"F Halsstr 1 Nijmegen Gelderland 6521 NA",
    "addr:housenumber":"1",
    "addr:postcode":"6521 na",
    "addr:street":"Halsstr;Gelderland",
    "iso:country":"NL",
    "sg:address":"F Halsstr 1",
    "sg:city":"Nijmegen",
    "sg:orig_category":"Journalisten Freelance",
    "sg:phone":"+31 24 324 0580",
    "sg:postcode":"6521 NA",
    "sg:province":"Gelderland",
    "wof:name":"Smits, M",
    "wof:placetype":"venue"
},
  "geometry": {"coordinates":[5.880507,51.83762],"type":"Point"}
}