{
  "type": "Feature",
  "properties": {
    "addr:full":"T Rikkelder 101 Ruurlo Gelderland 7261 BE",
    "addr:housenumber":"101",
    "addr:postcode":"7261",
    "addr:street":"T Rikkelder;Gelderland",
    "iso:country":"NL",
    "sg:address":"T Rikkelder 101",
    "sg:city":"Ruurlo",
    "sg:orig_category":"Bejaardeninstellingen And Serviceflats",
    "sg:phone":"+31 573 458 300",
    "sg:postcode":"7261 BE",
    "sg:province":"Gelderland",
    "wof:name":"Stichting Ouderenzorg Ruurlo Vorden Lokatie De Bun",
    "wof:placetype":"venue"
},
  "geometry": {"coordinates":[6.45198,52.086262],"type":"Point"}
}