{
  "type": "Feature",
  "properties": {
    "iso:country":"NL",
    "sg:address":"Noordende 27/27A",
    "sg:city":"Helmond",
    "sg:orig_category":"Metaalwerken",
    "sg:phone":"+31 492 535 804",
    "sg:postcode":"5701 SN",
    "sg:province":"Noord-Brabant",
    "wof:name":"Henk Van Den Hurk",
    "wof:placetype":"venue"
},
  "geometry": {"coordinates":[5.657291,51.483822],"type":"Point"}
}