{
  "type": "Feature",
  "properties": {
    "addr:full":"Burgerweg 28 Burgerbrug North Holland 1754 KC",
    "addr:housenumber":"28",
    "addr:postcode":"1754 kc",
    "addr:street":"Burgerweg",
    "iso:country":"NL",
    "sg:address":"Burgerweg 28",
    "sg:city":"Burgerbrug",
    "sg:orig_category":"Bloemen And Planten",
    "sg:phone":"+31 226 381 942",
    "sg:postcode":"1754 KC",
    "sg:province":"North Holland",
    "wof:name":"N.A.C. Slijkerman",
    "wof:placetype":"venue"
},
  "geometry": {"coordinates":[4.693518,52.750202],"type":"Point"}
}