{
  "type": "Feature",
  "properties": {
    "addr:full":"K Munkwg 41 Hoofddorp Noord-Holland 2131 RV",
    "addr:housenumber":"41",
    "addr:postcode":"2131 rv",
    "addr:street":"Munkwg",
    "iso:country":"NL",
    "sg:address":"K Munkwg 41",
    "sg:city":"Hoofddorp",
    "sg:orig_category":"Kinderopvang",
    "sg:phone":"+31 23 562 7028",
    "sg:postcode":"2131 RV",
    "sg:province":"Noord-Holland",
    "wof:name":"Bobijn",
    "wof:placetype":"venue"
},
  "geometry": {"coordinates":[4.679646,52.309566],"type":"Point"}
}