{
  "type": "Feature",
  "properties": {
    "addr:full":"K Boekestr 5 Alkmaar Noord-Holland 1817 EZ",
    "addr:housenumber":"5",
    "addr:postcode":"1817 ez",
    "addr:street":"Boekestr",
    "iso:country":"NL",
    "sg:address":"K Boekestr 5",
    "sg:city":"Alkmaar",
    "sg:orig_category":"Ziekenhuizen, Sanatoria, Verpleeghuizen",
    "sg:phone":"+31 72 514 0400",
    "sg:postcode":"1817 EZ",
    "sg:province":"Noord-Holland",
    "sg:website":"http://www.triversum.nl",
    "wof:name":"Triversum",
    "wof:placetype":"venue"
},
  "geometry": {"coordinates":[4.726106,52.646946],"type":"Point"}
}