{
  "type": "Feature",
  "properties": {
    "iso:country":"NL",
    "sg:address":"Koninginnewg 4",
    "sg:city":"Boskoop",
    "sg:orig_category":"Juweliers",
    "sg:phone":"+31 172 214 076",
    "sg:postcode":"2771 DN",
    "sg:province":"South Holland",
    "wof:name":"Does",
    "wof:placetype":"venue"
},
  "geometry": {"coordinates":[4.658667,52.074089],"type":"Point"}
}