{
  "type": "Feature",
  "properties": {
    "iso:country":"NL",
    "sg:address":"Kampstr 7",
    "sg:city":"Baarn",
    "sg:orig_category":"Beeldende Kunstenaars",
    "sg:phone":"+31 35 542 4799",
    "sg:postcode":"3741 AP",
    "sg:province":"Utrecht",
    "wof:name":"Beeldende Kunstenaars, Ver",
    "wof:placetype":"venue"
},
  "geometry": {"coordinates":[5.29169,52.213448],"type":"Point"}
}