{
  "type": "Feature",
  "properties": {
    "addr:full":"Pr Hendrikkd 48L Amsterdam North Holland 1012 AC",
    "addr:housenumber":"48l",
    "addr:postcode":"1012 ac",
    "iso:country":"NL",
    "sg:address":"Pr Hendrikkd 48L",
    "sg:city":"Amsterdam",
    "sg:orig_category":"Verenigingen En Stichtingen",
    "sg:phone":"+31 20 624 4067",
    "sg:postcode":"1012 AC",
    "sg:province":"North Holland",
    "wof:name":"Anbo",
    "wof:placetype":"venue"
},
  "geometry": {"coordinates":[4.898629,52.377144],"type":"Point"}
}