{
  "type": "Feature",
  "properties": {
    "addr:full":"J F Kennedyln 18 Valkenswaard North Brabant 5555 XD",
    "addr:housenumber":"18",
    "addr:postcode":"5555 xd",
    "addr:street":"J F Kennedyln",
    "iso:country":"NL",
    "sg:address":"J F Kennedyln 18",
    "sg:city":"Valkenswaard",
    "sg:orig_category":"Grafische Machines",
    "sg:phone":"+31 40 201 4436",
    "sg:postcode":"5555 XD",
    "sg:province":"North Brabant",
    "sg:website":"http://www.tampotechniek.com",
    "wof:name":"Tampo Techniek Ned Bv",
    "wof:placetype":"venue"
},
  "geometry": {"coordinates":[5.45897,51.35051],"type":"Point"}
}