{
  "type": "Feature",
  "properties": {
    "addr:full":"Stellingmolen 66 Heerhugowaard Noord-Holland 1703 TH",
    "addr:housenumber":"66",
    "addr:postcode":"1703 th",
    "addr:street":"Stellingmolen",
    "iso:country":"NL",
    "sg:address":"Stellingmolen 66",
    "sg:city":"Heerhugowaard",
    "sg:orig_category":"Parfum And Cosmetica Gh",
    "sg:phone":"+31 72 571 4006",
    "sg:postcode":"1703 TH",
    "sg:province":"Noord-Holland",
    "wof:name":"European Cosmetics Partnership (Ecp) Bv",
    "wof:placetype":"venue"
},
  "geometry": {"coordinates":[4.836967,52.658504],"type":"Point"}
}