{
  "type": "Feature",
  "properties": {
    "addr:full":"In T Oord 18 Vaals Limburg 6291 VP",
    "addr:housenumber":"18",
    "addr:postcode":"6291 vp",
    "addr:street":"T Oord",
    "iso:country":"NL",
    "sg:address":"In T Oord 18",
    "sg:city":"Vaals",
    "sg:orig_category":"Woningbouw- Verenigingen En -Stichtingen",
    "sg:phone":"+31 43 308 8200",
    "sg:postcode":"6291 VP",
    "sg:province":"Limburg",
    "wof:name":"Woningsticht Vaals",
    "wof:placetype":"venue"
},
  "geometry": {"coordinates":[6.0121917725,50.7706642151],"type":"Point"}
}