{
  "type": "Feature",
  "properties": {
    "addr:full":"Marktpln 15 Wormerveer Noord-Holland 1521 HS",
    "addr:housenumber":"15",
    "addr:postcode":"1521 hs",
    "addr:street":"Marktpln",
    "iso:country":"NL",
    "sg:address":"Marktpln 15",
    "sg:city":"Wormerveer",
    "sg:orig_category":"Huishoudelijke Apparaten En Artikelen",
    "sg:phone":"+31 75 640 2086",
    "sg:postcode":"1521 HS",
    "sg:province":"Noord-Holland",
    "wof:name":"Blokker Bv",
    "wof:placetype":"venue"
},
  "geometry": {"coordinates":[4.785525,52.49482],"type":"Point"}
}