{
  "type": "Feature",
  "properties": {
    "addr:full":"Westerwg 34 Noordwyk Gn Groningen 9824 TG",
    "addr:housenumber":"34",
    "addr:postcode":"gn;9824 tg",
    "addr:street":"Westerwg",
    "iso:country":"NL",
    "sg:address":"Westerwg 34",
    "sg:city":"Noordwyk Gn",
    "sg:orig_category":"Beeldende Kunstenaars",
    "sg:phone":"+31 594 659 610",
    "sg:postcode":"9824 TG",
    "sg:province":"Groningen",
    "sg:website":"http://www.mv-art.nl",
    "wof:name":"Martien Veldman",
    "wof:placetype":"venue"
},
  "geometry": {"coordinates":[6.257535,53.169701],"type":"Point"}
}