{
  "type": "Feature",
  "properties": {
    "addr:full":"Klaproos 5 Driebergen Rysenb Utrecht 3972 PW",
    "addr:housenumber":"5",
    "addr:postcode":"3972 pw",
    "addr:street":"Klaproos;Rysenb",
    "iso:country":"NL",
    "sg:address":"Klaproos 5",
    "sg:city":"Driebergen Rysenb",
    "sg:orig_category":"Verenigingen En Stichtingen",
    "sg:phone":"+31 343 531 147",
    "sg:postcode":"3972 PW",
    "sg:province":"Utrecht",
    "wof:name":"Abbeyfield",
    "wof:placetype":"venue"
},
  "geometry": {"coordinates":[5.270338,52.05267],"type":"Point"}
}