{
  "type": "Feature",
  "properties": {
    "addr:full":"Kon Julianawg 46 Leidschendam Zuid-Holland 2264 BD",
    "addr:housenumber":"46",
    "addr:postcode":"2264 bd",
    "addr:street":"Kon",
    "iso:country":"NL",
    "sg:address":"Kon Julianawg 46",
    "sg:city":"Leidschendam",
    "sg:orig_category":"Wasmachines En Wasdrogers",
    "sg:phone":"+31 70 320 0703",
    "sg:postcode":"2264 BD",
    "sg:province":"Zuid-Holland",
    "wof:name":"Bemmel & Kroon Bv",
    "wof:placetype":"venue"
},
  "geometry": {"coordinates":[4.3938131332,52.08360672],"type":"Point"}
}