{
  "type": "Feature",
  "properties": {
    "addr:full":"Asterstraat 41 Almere NL. 1338 WS",
    "addr:housenumber":"41",
    "addr:postcode":"1338 ws",
    "addr:street":"Asterstraat;Nl.",
    "iso:country":"NL",
    "sg:address":"Asterstraat 41",
    "sg:city":"Almere",
    "sg:classifiers":[
        {
            "category":"Education",
            "subcategory":"Preschool",
            "type":"Public Place"
        }
    ],
    "sg:phone":"+31 36 532 6593",
    "sg:postcode":"1338 WS",
    "sg:province":"NL.",
    "sg:tags":[
        "kleuteronderwijs",
        "basis-"
    ],
    "wof:name":"Openbare Basisschool De Torteltuin",
    "wof:placetype":"venue"
},
  "geometry": {"coordinates":[5.28489,52.388351],"type":"Point"}
}