{
  "type": "Feature",
  "properties": {
    "addr:full":"V Leeuwenhoekstr 1 Stryen Zuid-Holland 3291 CR",
    "addr:housenumber":"1;3291",
    "addr:postcode":"cr",
    "addr:street":"Leeuwenhoekstr",
    "iso:country":"NL",
    "sg:address":"V Leeuwenhoekstr 1",
    "sg:city":"Stryen",
    "sg:orig_category":"Houtverduurzaming",
    "sg:phone":"+31 78 674 8800",
    "sg:postcode":"3291 CR",
    "sg:province":"Zuid-Holland",
    "wof:name":"Sijde Bv, Van Der",
    "wof:placetype":"venue"
},
  "geometry": {"coordinates":[4.54727,51.750832],"type":"Point"}
}