{
  "type": "Feature",
  "properties": {
    "addr:full":"Kosteryland 74 Bunnik Utrecht 3981 AJ",
    "addr:housenumber":"74",
    "addr:postcode":"3981 aj",
    "addr:street":"Kosteryland",
    "iso:country":"NL",
    "sg:address":"Kosteryland 74",
    "sg:city":"Bunnik",
    "sg:classifiers":[
        {
            "category":"Professional",
            "type":"Services"
        }
    ],
    "sg:phone":"+31 30 659 5700",
    "sg:postcode":"3981 AJ",
    "sg:province":"Utrecht",
    "sg:tags":[
        "leasing"
    ],
    "sg:website":"http://www.golease.nl",
    "wof:name":"Go Lease Bv",
    "wof:placetype":"venue"
},
  "geometry": {"coordinates":[5.208107,52.061604],"type":"Point"}
}