{
  "type": "Feature",
  "properties": {
    "iso:country":"NL",
    "sg:address":"Herenstraat 50",
    "sg:city":"Rijswijk Zh",
    "sg:orig_category":"Schoenen",
    "sg:phone":"+31 70 399 8199",
    "sg:postcode":"2282 BW",
    "sg:province":"Zuid-Holland",
    "wof:name":"Brokx Shoes",
    "wof:placetype":"venue"
},
  "geometry": {"coordinates":[4.335491,52.056084],"type":"Point"}
}