{
  "type": "Feature",
  "properties": {
    "addr:full":"Marssteden 56 Enschede NL.08 7547 TD",
    "addr:housenumber":"56",
    "addr:postcode":"7547 td",
    "addr:street":"Marssteden",
    "iso:country":"NL",
    "sg:address":"Marssteden 56",
    "sg:city":"Enschede",
    "sg:orig_category":"Bakkerijbenodigdheden En -Grondstoffen",
    "sg:phone":"+31 53 428 3366",
    "sg:postcode":"7547 TD",
    "sg:province":"NL.08",
    "wof:name":"Dipasa Eur Bv",
    "wof:placetype":"venue"
},
  "geometry": {"coordinates":[6.814372,52.214779],"type":"Point"}
}