{
  "type": "Feature",
  "properties": {
    "addr:full":"Grotestraat 90 Tegelen Limburg 5931 CZ",
    "addr:housenumber":"90",
    "addr:postcode":"5931",
    "addr:street":"Grotestraat",
    "iso:country":"NL",
    "sg:address":"Grotestraat 90",
    "sg:city":"Tegelen",
    "sg:classifiers":[
        {
            "category":"Fast Food",
            "type":"Food & Drink"
        }
    ],
    "sg:phone":"+31 77 373 0542",
    "sg:postcode":"5931 CZ",
    "sg:province":"Limburg",
    "sg:tags":[
        "afhaal",
        "restaurant"
    ],
    "wof:name":"Pizzeria Da Franco",
    "wof:placetype":"venue"
},
  "geometry": {"coordinates":[6.135523,51.3423],"type":"Point"}
}