{
  "type": "Feature",
  "properties": {
    "iso:country":"NL",
    "sg:address":"Wegaln 43",
    "sg:city":"Hoofddorp",
    "sg:orig_category":"Verzekerings- Maatschappijen",
    "sg:phone":"+31 23 566 1800",
    "sg:postcode":"2132 JD",
    "sg:province":"North Holland",
    "sg:website":"http://www.chubb.com",
    "wof:name":"Chubb",
    "wof:placetype":"venue"
},
  "geometry": {"coordinates":[4.69296,52.305393],"type":"Point"}
}