{
  "type": "Feature",
  "properties": {
    "addr:full":"Laaressingel 8 Enschede NL.08 7514 ER",
    "addr:housenumber":"8",
    "addr:postcode":"7514",
    "addr:street":"Laaressingel;Er",
    "iso:country":"NL",
    "sg:address":"Laaressingel 8",
    "sg:city":"Enschede",
    "sg:orig_category":"Vertaal- And Tolkenbureaus",
    "sg:phone":"+31 53 433 3249",
    "sg:postcode":"7514 ER",
    "sg:province":"NL.08",
    "wof:name":"Vertaalbureau Nicole M.E.Bloemers-De Bru",
    "wof:placetype":"venue"
},
  "geometry": {"coordinates":[6.901536,52.227692],"type":"Point"}
}