{
  "type": "Feature",
  "properties": {
    "addr:full":"Bakboord 36 Amstelveen North Holland 1186 VA",
    "addr:housenumber":"36",
    "addr:postcode":"1186",
    "addr:street":"Bakboord",
    "iso:country":"NL",
    "sg:address":"Bakboord 36",
    "sg:city":"Amstelveen",
    "sg:orig_category":"Kappers",
    "sg:phone":"+31 20 647 2308",
    "sg:postcode":"1186 VA",
    "sg:province":"North Holland",
    "wof:name":"Hairstudio 36",
    "wof:placetype":"venue"
},
  "geometry": {"coordinates":[4.8596529961,52.2778358459],"type":"Point"}
}