{
  "type": "Feature",
  "properties": {
    "addr:full":"Botplein 22 Almere Flevoland 1317 SL",
    "addr:housenumber":"22;1317",
    "addr:postcode":"sl",
    "addr:street":"Botplein;Flevoland",
    "iso:country":"NL",
    "sg:address":"Botplein 22",
    "sg:city":"Almere",
    "sg:classifiers":[
        {
            "category":"Fast Food",
            "type":"Food & Drink"
        }
    ],
    "sg:phone":"+31 36 533 8385",
    "sg:postcode":"1317 SL",
    "sg:province":"Flevoland",
    "sg:tags":[
        "afhaal",
        "restaurant"
    ],
    "wof:name":"Erno'S Snackcorner",
    "wof:placetype":"venue"
},
  "geometry": {"coordinates":[5.232164,52.388893],"type":"Point"}
}