{
  "type": "Feature",
  "properties": {
    "iso:country":"NL",
    "sg:address":"Zuidelijke Meentsteeg 1",
    "sg:city":"Rhenen",
    "sg:orig_category":"Sportclubs",
    "sg:phone":"+31 317 614 750",
    "sg:postcode":"3911 TD",
    "sg:province":"Utrecht",
    "wof:name":"Voetbalvereniging Vva '71",
    "wof:placetype":"venue"
},
  "geometry": {"coordinates":[5.57227,51.983631],"type":"Point"}
}