{
  "type": "Feature",
  "properties": {
    "addr:full":"Oosterdorpsstraat 67 Hoevelaken Gelderland 3871 AB",
    "addr:housenumber":"67",
    "addr:postcode":"3871 ab",
    "addr:street":"Oosterdorpsstraat;Gelderland",
    "iso:country":"NL",
    "sg:address":"Oosterdorpsstraat 67",
    "sg:city":"Hoevelaken",
    "sg:orig_category":"Parfum And Cosmetica Gh",
    "sg:phone":"+31 33 253 8555",
    "sg:postcode":"3871 AB",
    "sg:province":"Gelderland",
    "wof:name":"Promex Nederland Bv",
    "wof:placetype":"venue"
},
  "geometry": {"coordinates":[5.466538,52.175491],"type":"Point"}
}