{
  "type": "Feature",
  "properties": {
    "addr:full":"Heesakkerstr 10 St Michielsgestel North Brabant 5271 CB",
    "addr:housenumber":"10",
    "addr:postcode":"5271 cb",
    "addr:street":"Heesakkerstr",
    "iso:country":"NL",
    "sg:address":"Heesakkerstr 10",
    "sg:city":"St Michielsgestel",
    "sg:orig_category":"Autorijscholen",
    "sg:phone":"+31 73 551 2622",
    "sg:postcode":"5271 CB",
    "sg:province":"North Brabant",
    "wof:name":"Grinsven Rijopleidingen, Jan Van",
    "wof:placetype":"venue"
},
  "geometry": {"coordinates":[5.35438,51.640476],"type":"Point"}
}