{
  "type": "Feature",
  "properties": {
    "iso:country":"NL",
    "sg:address":"Crosestein 1101",
    "sg:city":"Zeist",
    "sg:orig_category":"Acupunctuur",
    "sg:phone":"+31 30 699 2920",
    "sg:postcode":"3704 NA",
    "sg:province":"Utrecht",
    "wof:name":"Heijer, Paul",
    "wof:placetype":"venue"
},
  "geometry": {"coordinates":[5.216091,52.090714],"type":"Point"}
}