{
  "type": "Feature",
  "properties": {
    "addr:full":"Uitstr 55 Spykenisse South Holland 3201 EN",
    "addr:housenumber":"55",
    "addr:postcode":"3201 en",
    "addr:street":"Uitstr",
    "iso:country":"NL",
    "sg:address":"Uitstr 55",
    "sg:city":"Spykenisse",
    "sg:orig_category":"Huishoudelijke Apparaten En Artikelen",
    "sg:phone":"+31 181 697 214",
    "sg:postcode":"3201 EN",
    "sg:province":"South Holland",
    "wof:name":"Blokker Bv",
    "wof:placetype":"venue"
},
  "geometry": {"coordinates":[4.325045,51.849525],"type":"Point"}
}