{
  "type": "Feature",
  "properties": {
    "iso:country":"NL",
    "sg:address":"Nieuwezijds Voorburgwal 292",
    "sg:city":"Amsterdam",
    "sg:orig_category":"Boekenuitgeverijen",
    "sg:phone":"+31 20 521 6767",
    "sg:postcode":"1012 RT",
    "sg:province":"Noord-Holland",
    "wof:name":"Uitgeverij Maarten Muntinga Bv",
    "wof:placetype":"venue"
},
  "geometry": {"coordinates":[4.889944,52.370892],"type":"Point"}
}