{
  "type": "Feature",
  "properties": {
    "addr:full":"Nieuwezijds Voorburgwal 292 Amsterdam Noord-Holland 1012 RT",
    "addr:housenumber":"292",
    "addr:postcode":"1012 rt",
    "addr:street":"Nieuwezijds Voorburgwal",
    "iso:country":"NL",
    "sg:address":"Nieuwezijds Voorburgwal 292",
    "sg:city":"Amsterdam",
    "sg:orig_category":"Boekenuitgeverijen",
    "sg:phone":"+31 20 521 6767",
    "sg:postcode":"1012 RT",
    "sg:province":"Noord-Holland",
    "wof:name":"Uitgeverij Maarten Muntinga Bv",
    "wof:placetype":"venue"
},
  "geometry": {"coordinates":[4.889944,52.370892],"type":"Point"}
}