{
  "type": "Feature",
  "properties": {
    "addr:full":"Hoogewg 17 Rynsburg Zuid-Holland 2231 MS",
    "addr:housenumber":"17",
    "addr:postcode":"2231 ms",
    "addr:street":"Hoogewg",
    "iso:country":"NL",
    "sg:address":"Hoogewg 17",
    "sg:city":"Rynsburg",
    "sg:orig_category":"Bloemen En Planten - Groothandel",
    "sg:phone":"+31 71 403 0998",
    "sg:postcode":"2231 MS",
    "sg:province":"Zuid-Holland",
    "wof:name":"Delphinium, Fa",
    "wof:placetype":"venue"
},
  "geometry": {"coordinates":[4.45026,52.209251],"type":"Point"}
}