{
  "type": "Feature",
  "properties": {
    "addr:full":"Nies Van Der Schansstr 19 Sprang-Capelle North Brabant 5161 CE",
    "addr:housenumber":"19",
    "addr:postcode":"5161 ce",
    "addr:street":"Nies Van Der Schansstr",
    "iso:country":"NL",
    "sg:address":"Nies Van Der Schansstr 19",
    "sg:city":"Sprang-Capelle",
    "sg:orig_category":"Kantoorapparatuur Gh",
    "sg:phone":"+31 416 283 126",
    "sg:postcode":"5161 CE",
    "sg:province":"North Brabant",
    "wof:name":"Alrecar Nederland Bv",
    "wof:placetype":"venue"
},
  "geometry": {"coordinates":[5.0331501961,51.667339325],"type":"Point"}
}