{
  "type": "Feature",
  "properties": {
    "iso:country":"NL",
    "sg:address":"Northgodreef 25",
    "sg:city":"Noordwijk Zh",
    "sg:orig_category":"Verzekeringen",
    "sg:phone":"+31 71 361 6431",
    "sg:postcode":"2202 XZ",
    "sg:province":"South Holland",
    "wof:name":"Alkemade Assurantien Vof",
    "wof:placetype":"venue"
},
  "geometry": {"coordinates":[4.445029,52.251019],"type":"Point"}
}