{
  "type": "Feature",
  "properties": {
    "addr:full":"V Oosthuyseln 83 Driebergen Rysenb Utrecht 3971 PE",
    "addr:housenumber":"83",
    "addr:postcode":"3971 pe",
    "addr:street":"Rysenb",
    "iso:country":"NL",
    "sg:address":"V Oosthuyseln 83",
    "sg:city":"Driebergen Rysenb",
    "sg:orig_category":"Fitnesscentra",
    "sg:phone":"+31 343 513 333",
    "sg:postcode":"3971 PE",
    "sg:province":"Utrecht",
    "wof:name":"Fitnesscentrum Driebergen",
    "wof:placetype":"venue"
},
  "geometry": {"coordinates":[5.30052,52.065571],"type":"Point"}
}