{
  "type": "Feature",
  "properties": {
    "iso:country":"NL",
    "sg:address":"Voorweg 5 A",
    "sg:city":"Groote Keeten",
    "sg:orig_category":"Kampeerterreinen",
    "sg:phone":"+31 224 581 663",
    "sg:postcode":"1759 NX",
    "sg:province":"Noord-Holland",
    "wof:name":"Camping Callassande Callantsoog",
    "wof:placetype":"venue"
},
  "geometry": {"coordinates":[4.7178988457,52.8563728333],"type":"Point"}
}