{
  "type": "Feature",
  "properties": {
    "addr:full":"Krugerstraat 79 Vaassen Gelderland 8172 BG",
    "addr:housenumber":"79",
    "addr:postcode":"8172",
    "addr:street":"Krugerstraat;Gelderland",
    "iso:country":"NL",
    "sg:address":"Krugerstraat 79",
    "sg:city":"Vaassen",
    "sg:classifiers":[
        {
            "category":"Food & Beverages",
            "subcategory":"Fruits & Vegetables",
            "type":"Retail Goods"
        }
    ],
    "sg:phone":"+31 578 571 705",
    "sg:postcode":"8172 BG",
    "sg:province":"Gelderland",
    "sg:tags":[
        "groenten"
    ],
    "wof:name":"Groentehandel Zieverink",
    "wof:placetype":"venue"
},
  "geometry": {"coordinates":[5.958752,52.283047],"type":"Point"}
}