{
  "type": "Feature",
  "properties": {
    "addr:full":"Hoofdstr 43 Bergambacht Zuid-Holland 2861 AL",
    "addr:housenumber":"43",
    "addr:postcode":"2861 al",
    "addr:street":"Hoofdstr",
    "iso:country":"NL",
    "sg:address":"Hoofdstr 43",
    "sg:city":"Bergambacht",
    "sg:orig_category":"Opticiens",
    "sg:phone":"+31 182 354 063",
    "sg:postcode":"2861 AL",
    "sg:province":"Zuid-Holland",
    "wof:name":"Bergambacht Optiek",
    "wof:placetype":"venue"
},
  "geometry": {"coordinates":[4.7831578255,51.9337081909],"type":"Point"}
}