{
  "type": "Feature",
  "properties": {
    "iso:country":"NL",
    "sg:address":"Westfalenstr 14",
    "sg:city":"Deventer",
    "sg:orig_category":"Plakband - Fabrieken En Groothandel",
    "sg:phone":"+31 570 627 529",
    "sg:postcode":"7418 DB",
    "sg:province":"Overijssel",
    "wof:name":"Verpakkings Industrie Deventer Vof",
    "wof:placetype":"venue"
},
  "geometry": {"coordinates":[6.188718,52.247066],"type":"Point"}
}