{
  "type": "Feature",
  "properties": {
    "addr:full":"Eburonenwg 7-9 Maastricht Limburg 6224 HT",
    "addr:housenumber":"7-9",
    "addr:postcode":"6224 ht",
    "addr:street":"Eburonenwg",
    "iso:country":"NL",
    "sg:address":"Eburonenwg 7-9",
    "sg:city":"Maastricht",
    "sg:orig_category":"Verpakkingen En Verpakkingsmaterialen",
    "sg:phone":"+31 43 363 7042",
    "sg:postcode":"6224 HT",
    "sg:province":"Limburg",
    "wof:name":"Bonn\u00e9 Papier Verpakkingsmaterialen",
    "wof:placetype":"venue"
},
  "geometry": {"coordinates":[5.714281,50.85041],"type":"Point"}
}