{
  "type": "Feature",
  "properties": {
    "iso:country":"NL",
    "sg:address":"Raadhuisstraat 52",
    "sg:city":"Maurik",
    "sg:orig_category":"Beursorganisaties And Standbouw",
    "sg:phone":"+31 344 694 652",
    "sg:postcode":"4021 EJ",
    "sg:province":"Gelderland",
    "wof:name":"Proforma Tentoonstellingsarchitectuur",
    "wof:placetype":"venue"
},
  "geometry": {"coordinates":[5.420528,51.962509],"type":"Point"}
}