{
  "type": "Feature",
  "properties": {
    "addr:full":"Philips Willemstraat 9 Rotterdam Zuid-Holland 3051 PL",
    "addr:housenumber":"9",
    "addr:postcode":"3051 pl",
    "addr:street":"Philips Willemstraat",
    "iso:country":"NL",
    "sg:address":"Philips Willemstraat 9",
    "sg:city":"Rotterdam",
    "sg:orig_category":"Pleziervaartuigen And Reparatie",
    "sg:phone":"+31 10 418 8520",
    "sg:postcode":"3051 PL",
    "sg:province":"Zuid-Holland",
    "wof:name":"Jachtwerf Vial",
    "wof:placetype":"venue"
},
  "geometry": {"coordinates":[4.484576,51.946346],"type":"Point"}
}