{
  "type": "Feature",
  "properties": {
    "iso:country":"NL",
    "sg:address":"De Bengele 2",
    "sg:city":"Nederweert",
    "sg:classifiers":[
        {
            "category":"Education",
            "subcategory":"Preschool",
            "type":"Public Place"
        }
    ],
    "sg:phone":"+31 495 632 747",
    "sg:postcode":"6031 TZ",
    "sg:province":"Limburg",
    "sg:tags":[
        "kleuteronderwijs",
        "basis-"
    ],
    "wof:name":"Basisschool De Bongerd",
    "wof:placetype":"venue"
},
  "geometry": {"coordinates":[5.74182,51.280983],"type":"Point"}
}