{
  "type": "Feature",
  "properties": {
    "addr:full":"Componistensngl 59 Veenendaal Utrecht 3906 BT",
    "addr:housenumber":"59",
    "addr:postcode":"3906 bt",
    "addr:street":"Componistensngl",
    "iso:country":"NL",
    "sg:address":"Componistensngl 59",
    "sg:city":"Veenendaal",
    "sg:orig_category":"Onderhoudswerken",
    "sg:phone":"+31 318 554 513",
    "sg:postcode":"3906 BT",
    "sg:province":"Utrecht",
    "wof:name":"Pannekoek, S",
    "wof:placetype":"venue"
},
  "geometry": {"coordinates":[5.53068,52.036278],"type":"Point"}
}