{
  "type": "Feature",
  "properties": {
    "addr:full":"T B Huurmanlaan 3 Bussum North Holland 1403 SL",
    "addr:housenumber":"3",
    "addr:postcode":"1403 sl",
    "addr:street":"Huurmanlaan",
    "iso:country":"NL",
    "sg:address":"T B Huurmanlaan 3",
    "sg:city":"Bussum",
    "sg:orig_category":"Bloemen And Planten",
    "sg:phone":"+31 35 693 6724",
    "sg:postcode":"1403 SL",
    "sg:province":"North Holland",
    "wof:name":"Bloemenhuis Lobelia",
    "wof:placetype":"venue"
},
  "geometry": {"coordinates":[5.174175,52.267445],"type":"Point"}
}