{
  "type": "Feature",
  "properties": {
    "addr:full":"Anne Franklaan 46 Deventer Overijssel 7421 HK",
    "addr:housenumber":"46",
    "addr:postcode":"7421 hk",
    "addr:street":"Anne Franklaan",
    "iso:country":"NL",
    "sg:address":"Anne Franklaan 46",
    "sg:city":"Deventer",
    "sg:orig_category":"Boekhouders",
    "sg:phone":"+31 570 657 750",
    "sg:postcode":"7421 HK",
    "sg:province":"Overijssel",
    "wof:name":"Administratiekantoor Ageeth Kientz",
    "wof:placetype":"venue"
},
  "geometry": {"coordinates":[6.229223,52.242889],"type":"Point"}
}