{
  "type": "Feature",
  "properties": {
    "iso:country":"NL",
    "sg:address":"Abel Tasmanplein 1",
    "sg:city":"Assen",
    "sg:orig_category":"Overheidsdiensten",
    "sg:phone":"+31 592 304 999",
    "sg:postcode":"9401 AZ",
    "sg:province":"Provincie Drenthe",
    "wof:name":"Kadaster Directie Noord Vestiging Assen",
    "wof:placetype":"venue"
},
  "geometry": {"coordinates":[6.5703911781,52.9959754944],"type":"Point"}
}