{
  "type": "Feature",
  "properties": {
    "addr:full":"Vriesestraat 96 Dordrecht South Holland 3311 NR",
    "addr:housenumber":"96",
    "addr:postcode":"3311 nr",
    "addr:street":"Vriesestraat",
    "iso:country":"NL",
    "sg:address":"Vriesestraat 96",
    "sg:city":"Dordrecht",
    "sg:orig_category":"Opticiens",
    "sg:phone":"+31 78 613 8415",
    "sg:postcode":"3311 NR",
    "sg:province":"South Holland",
    "wof:name":"Van Der Ham Dordt Bv",
    "wof:placetype":"venue"
},
  "geometry": {"coordinates":[4.6687178612,51.8132400513],"type":"Point"}
}