{
  "type": "Feature",
  "properties": {
    "addr:full":"Karel Doormanweg 18 Amstelveen Noord-Holland 1181 WE",
    "addr:housenumber":"18",
    "addr:postcode":"1181 we",
    "addr:street":"Karel Doormanweg",
    "iso:country":"NL",
    "sg:address":"Karel Doormanweg 18",
    "sg:city":"Amstelveen",
    "sg:orig_category":"Boekhandels",
    "sg:phone":"+31 20 643 1783",
    "sg:postcode":"1181 WE",
    "sg:province":"Noord-Holland",
    "wof:name":"Kantoorboekhandel Voorheen Gebroeders Wi",
    "wof:placetype":"venue"
},
  "geometry": {"coordinates":[4.869817,52.305103],"type":"Point"}
}