{
  "type": "Feature",
  "properties": {
    "addr:full":"Torenakker 46 Berkel Enschot North Brabant 5056 LP",
    "addr:housenumber":"46",
    "addr:postcode":"5056 lp",
    "addr:street":"Torenakker;Enschot",
    "iso:country":"NL",
    "sg:address":"Torenakker 46",
    "sg:city":"Berkel Enschot",
    "sg:orig_category":"Onderhoudswerken",
    "sg:phone":"+31 13 533 4434",
    "sg:postcode":"5056 LP",
    "sg:province":"North Brabant",
    "sg:website":"http://www.goedvoorvastgoed.nl",
    "wof:name":"Goed Voor Vastgoed",
    "wof:placetype":"venue"
},
  "geometry": {"coordinates":[5.146624,51.592422],"type":"Point"}
}