{
  "type": "Feature",
  "properties": {
    "iso:country":"NL",
    "sg:address":"Leiboom 18",
    "sg:city":"Oudenbosch",
    "sg:orig_category":"Meubelreparatie And -Restauratie",
    "sg:phone":"+31 165 321 276",
    "sg:postcode":"4731 XG",
    "sg:province":"North Brabant",
    "wof:name":"D Bruyninckx",
    "wof:placetype":"venue"
},
  "geometry": {"coordinates":[4.535205,51.585712],"type":"Point"}
}