{
  "type": "Feature",
  "properties": {
    "iso:country":"NL",
    "sg:address":"Slochterenlaan 12",
    "sg:city":"Bussum",
    "sg:orig_category":"Adviesbureaus Bedrijfsorganisatie",
    "sg:phone":"+31 35 699 3099",
    "sg:postcode":"1405 AM",
    "sg:province":"Noord-Holland",
    "wof:name":"Denc Netherlands",
    "wof:placetype":"venue"
},
  "geometry": {"coordinates":[5.155458,52.281055],"type":"Point"}
}