{
  "type": "Feature",
  "properties": {
    "addr:full":"Slochterenlaan 12 Bussum Noord-Holland 1405 AM",
    "addr:housenumber":"12",
    "addr:postcode":"1405",
    "addr:street":"Slochterenlaan",
    "iso:country":"NL",
    "sg:address":"Slochterenlaan 12",
    "sg:city":"Bussum",
    "sg:orig_category":"Adviesbureaus Bedrijfsorganisatie",
    "sg:phone":"+31 35 699 3099",
    "sg:postcode":"1405 AM",
    "sg:province":"Noord-Holland",
    "wof:name":"Denc Netherlands",
    "wof:placetype":"venue"
},
  "geometry": {"coordinates":[5.155458,52.281055],"type":"Point"}
}