{
  "type": "Feature",
  "properties": {
    "addr:full":"Vuile Riete 1 Linde Dr Drenthe 7925 PL",
    "addr:housenumber":"1",
    "addr:postcode":"7925 pl",
    "addr:street":"Vuile Riete;Linde Dr",
    "iso:country":"NL",
    "sg:address":"Vuile Riete 1",
    "sg:city":"Linde Dr",
    "sg:orig_category":"Honden- En Kattentrimsalons",
    "sg:phone":"+31 523 620 851",
    "sg:postcode":"7925 PL",
    "sg:province":"Drenthe",
    "wof:name":"Donja",
    "wof:placetype":"venue"
},
  "geometry": {"coordinates":[6.450442,52.638271],"type":"Point"}
}