{
  "type": "Feature",
  "properties": {
    "iso:country":"NL",
    "sg:address":"Brink 12",
    "sg:city":"Ottersum",
    "sg:orig_category":"Kinderopvang Behalve Thuis",
    "sg:phone":"+31 485 541 757",
    "sg:postcode":"6595 AN",
    "sg:province":"Limburg",
    "wof:name":"Kindercentrum Kiekeboe",
    "wof:placetype":"venue"
},
  "geometry": {"coordinates":[5.980776,51.704594],"type":"Point"}
}