{
  "type": "Feature",
  "properties": {
    "addr:full":"Pisastr 115 S Hertogenbosch North Brabant 5237 EL",
    "addr:housenumber":"115",
    "addr:postcode":"5237 el",
    "addr:street":"S Hertogenbosch",
    "iso:country":"NL",
    "sg:address":"Pisastr 115",
    "sg:city":"S Hertogenbosch",
    "sg:orig_category":"Vertalers",
    "sg:phone":"+31 73 642 7523",
    "sg:postcode":"5237 EL",
    "sg:province":"North Brabant",
    "wof:name":"Heesewijk, Drs C O J M Van",
    "wof:placetype":"venue"
},
  "geometry": {"coordinates":[5.296002,51.724113],"type":"Point"}
}