{
  "type": "Feature",
  "properties": {
    "addr:full":"Burg Kuntzeln 25 Barneveld Gelderland 3771 EP",
    "addr:housenumber":"25",
    "addr:postcode":"3771 ep",
    "addr:street":"Burg;Gelderland",
    "iso:country":"NL",
    "sg:address":"Burg Kuntzeln 25",
    "sg:city":"Barneveld",
    "sg:orig_category":"Accountants - Administratie- Consulenten En -Kantoren",
    "sg:phone":"+31 342 411 411",
    "sg:postcode":"3771 EP",
    "sg:province":"Gelderland",
    "wof:name":"Alfa Bv",
    "wof:placetype":"venue"
},
  "geometry": {"coordinates":[5.590566,52.138863],"type":"Point"}
}