{
  "type": "Feature",
  "properties": {
    "iso:country":"NL",
    "sg:address":"Hommerterwg 220",
    "sg:city":"Hoensbroek",
    "sg:orig_category":"Honden- En Kattentrimsalons",
    "sg:phone":"+31 45 521 5679",
    "sg:postcode":"6431 EZ",
    "sg:province":"Limburg",
    "wof:name":"Dog-Side Hondentrimsalon",
    "wof:placetype":"venue"
},
  "geometry": {"coordinates":[5.923019,50.933395],"type":"Point"}
}