{
  "type": "Feature",
  "properties": {
    "addr:full":"Boterbloem 12 Haastrecht South Holland 2851 ZD",
    "addr:housenumber":"12",
    "addr:postcode":"2851 zd",
    "addr:street":"Boterbloem",
    "iso:country":"NL",
    "sg:address":"Boterbloem 12",
    "sg:city":"Haastrecht",
    "sg:orig_category":"Verlichtingsartikelen - Groothandel",
    "sg:phone":"+31 182 502 900",
    "sg:postcode":"2851 ZD",
    "sg:province":"South Holland",
    "wof:name":"Hof, Van 'T",
    "wof:placetype":"venue"
},
  "geometry": {"coordinates":[4.777982,51.996082],"type":"Point"}
}