{
  "type": "Feature",
  "properties": {
    "addr:full":"Lambalgerkom 95 Leusden Utrecht 3831 RL",
    "addr:housenumber":"95",
    "addr:postcode":"3831 rl",
    "addr:street":"Lambalgerkom",
    "iso:country":"NL",
    "sg:address":"Lambalgerkom 95",
    "sg:city":"Leusden",
    "sg:orig_category":"Grafisch Ontwerpers",
    "sg:phone":"+31 6 55828484",
    "sg:postcode":"3831 RL",
    "sg:province":"Utrecht",
    "wof:name":"Jaaan Design",
    "wof:placetype":"venue"
},
  "geometry": {"coordinates":[5.430874,52.144424],"type":"Point"}
}