{
  "type": "Feature",
  "properties": {
    "addr:full":"Langlaar 11 Nuenen Noord-Brabant 5674 SK",
    "addr:housenumber":"11",
    "addr:street":"Langlaar;5674",
    "iso:country":"NL",
    "sg:address":"Langlaar 11",
    "sg:city":"Nuenen",
    "sg:orig_category":"Bouwmaterialen Gh",
    "sg:phone":"+31 40 283 3128",
    "sg:postcode":"5674 SK",
    "sg:province":"Noord-Brabant",
    "wof:name":"Liebregts-Lama Bv",
    "wof:placetype":"venue"
},
  "geometry": {"coordinates":[5.560588,51.482906],"type":"Point"}
}