{
  "type": "Feature",
  "properties": {
    "addr:full":"Pieter De Hooghlaan 47 Oud Beijerland South Holland 3262 RD",
    "addr:housenumber":"47",
    "addr:postcode":"3262 rd",
    "addr:street":"Pieter De Hooghlaan;Oud Beijerland",
    "iso:country":"NL",
    "sg:address":"Pieter De Hooghlaan 47",
    "sg:city":"Oud Beijerland",
    "sg:orig_category":"Bedrijfs- And Managementsconsultants",
    "sg:phone":"+31 186 617 803",
    "sg:postcode":"3262 RD",
    "sg:province":"South Holland",
    "wof:name":"C. Donkersloot Bedrijfsadvisering",
    "wof:placetype":"venue"
},
  "geometry": {"coordinates":[4.409731,51.817787],"type":"Point"}
}