{
  "type": "Feature",
  "properties": {
    "addr:full":"Zandumerwg 74 Oldekerk Groningen 9821 TH",
    "addr:housenumber":"74",
    "addr:postcode":"9821 th",
    "addr:street":"Zandumerwg",
    "iso:country":"NL",
    "sg:address":"Zandumerwg 74",
    "sg:city":"Oldekerk",
    "sg:classifiers":[
        {
            "category":"Retail",
            "subcategory":"Storage",
            "type":"Services"
        }
    ],
    "sg:phone":"+31 594 504 941",
    "sg:postcode":"9821 TH",
    "sg:province":"Groningen",
    "sg:tags":[
        "op-",
        "en",
        "overslagbedrijven"
    ],
    "wof:name":"Bos, R",
    "wof:placetype":"venue"
},
  "geometry": {"coordinates":[6.315015,53.235077],"type":"Point"}
}