{
  "type": "Feature",
  "properties": {
    "addr:full":"Mauritskade 77 'S Gravenhage South Holland 2514 HH",
    "addr:housenumber":"77",
    "addr:postcode":"2514 hh",
    "addr:street":"Mauritskade;' S Gravenhage",
    "iso:country":"NL",
    "sg:address":"Mauritskade 77",
    "sg:city":"'S Gravenhage",
    "sg:orig_category":"Kappers",
    "sg:phone":"+31 70 345 2813",
    "sg:postcode":"2514 HH",
    "sg:province":"South Holland",
    "wof:name":"Kapsalon To Cut Cut Cut",
    "wof:placetype":"venue"
},
  "geometry": {"coordinates":[4.3113021851,52.0862236023],"type":"Point"}
}