{
  "type": "Feature",
  "properties": {
    "addr:full":"Denekamperwg 248 Vasse North Carolina 7661 RM",
    "addr:housenumber":"248",
    "addr:postcode":"7661 rm",
    "iso:country":"NL",
    "sg:address":"Denekamperwg 248",
    "sg:city":"Vasse",
    "sg:orig_category":"Afslankinstituten",
    "sg:phone":"+31 541 292 066",
    "sg:postcode":"7661 RM",
    "sg:province":"North Carolina",
    "wof:name":"Brinkman, Jolande",
    "wof:placetype":"venue"
},
  "geometry": {"coordinates":[-79.281837,35.257744],"type":"Point"}
}