{
  "type": "Feature",
  "properties": {
    "addr:full":"Papaverweg 34 Amsterdam Noord-Holland 1032 KJ",
    "addr:housenumber":"34",
    "addr:postcode":"1032 kj",
    "addr:street":"Papaverweg",
    "iso:country":"NL",
    "sg:address":"Papaverweg 34",
    "sg:city":"Amsterdam",
    "sg:orig_category":"Kantoorapparatuur Gh",
    "sg:phone":"+31 20 632 4142",
    "sg:postcode":"1032 KJ",
    "sg:province":"Noord-Holland",
    "wof:name":"Hilkman Alles Voor Uw Supermarkt Bv",
    "wof:placetype":"venue"
},
  "geometry": {"coordinates":[4.9090209007,52.3956642151],"type":"Point"}
}