{
  "type": "Feature",
  "properties": {
    "addr:full":"Denekamperstr 45A Ootmarsum Overijssel 7631 AB",
    "addr:housenumber":"45a",
    "addr:postcode":"7631 ab",
    "addr:street":"Denekamperstr",
    "iso:country":"NL",
    "sg:address":"Denekamperstr 45A",
    "sg:city":"Ootmarsum",
    "sg:orig_category":"Kabelwerken",
    "sg:phone":"+31 541 283 333",
    "sg:postcode":"7631 AB",
    "sg:province":"Overijssel",
    "sg:website":"HTTP://www.bamnbm.nl",
    "wof:name":"Bam Nbm Infratechniek Noordoost",
    "wof:placetype":"venue"
},
  "geometry": {"coordinates":[6.910118103,52.4099197388],"type":"Point"}
}