{
  "type": "Feature",
  "properties": {
    "addr:full":"Tromplaan 49 Hendrik Ido Ambacht Zuid-Holland 3342 TR",
    "addr:housenumber":"49",
    "addr:postcode":"ido ambacht;3342 tr",
    "addr:street":"Tromplaan",
    "iso:country":"NL",
    "sg:address":"Tromplaan 49",
    "sg:city":"Hendrik Ido Ambacht",
    "sg:classifiers":[
        {
            "category":"Education",
            "subcategory":"Preschool",
            "type":"Public Place"
        }
    ],
    "sg:phone":"+31 78 684 0336",
    "sg:postcode":"3342 TR",
    "sg:province":"Zuid-Holland",
    "sg:tags":[
        "kleuteronderwijs",
        "basis-"
    ],
    "wof:name":"Openbare Basisschool De Bron",
    "wof:placetype":"venue"
},
  "geometry": {"coordinates":[4.628067,51.843884],"type":"Point"}
}