{
  "type": "Feature",
  "properties": {
    "addr:full":"Papaverweg 34 Amsterdam North Holland 1032 KJ",
    "addr:housenumber":"34",
    "addr:postcode":"1032 kj",
    "addr:street":"Papaverweg",
    "iso:country":"NL",
    "sg:address":"Papaverweg 34",
    "sg:city":"Amsterdam",
    "sg:orig_category":"Administratie- En Boekhoudkantoren",
    "sg:phone":"+31 6 53872728",
    "sg:postcode":"1032 KJ",
    "sg:province":"North Holland",
    "wof:name":"Kaptein Vof",
    "wof:placetype":"venue"
},
  "geometry": {"coordinates":[4.909021,52.395664],"type":"Point"}
}