{
  "type": "Feature",
  "properties": {
    "iso:country":"NL",
    "sg:address":"Havenkade 8",
    "sg:city":"Middenmeer",
    "sg:orig_category":"Autokeuringen",
    "sg:phone":"+31 227 501 203",
    "sg:postcode":"1775 BA",
    "sg:province":"Noord-Holland",
    "wof:name":"Garage Smit",
    "wof:placetype":"venue"
},
  "geometry": {"coordinates":[4.996947,52.813358],"type":"Point"}
}