{
  "type": "Feature",
  "properties": {
    "iso:country":"NL",
    "sg:address":"V Diepeningenln 21",
    "sg:city":"Leiderdorp",
    "sg:orig_category":"Kappers",
    "sg:phone":"+31 71 589 0143",
    "sg:postcode":"2352 KA",
    "sg:province":"Zuid-Holland",
    "wof:name":"Hair Maxx",
    "wof:placetype":"venue"
},
  "geometry": {"coordinates":[4.5342178345,52.1561737061],"type":"Point"}
}