{
  "type": "Feature",
  "properties": {
    "addr:full":"Bankastr 191 Dordrecht Zuid-Holland 3312 GA",
    "addr:housenumber":"191",
    "addr:postcode":"3312 ga",
    "iso:country":"NL",
    "sg:address":"Bankastr 191",
    "sg:city":"Dordrecht",
    "sg:orig_category":"Adviesbureaus Bedrijfsorganisatie",
    "sg:phone":"+31 78 614 0041",
    "sg:postcode":"3312 GA",
    "sg:province":"Zuid-Holland",
    "wof:name":"Claire",
    "wof:placetype":"venue"
},
  "geometry": {"coordinates":[4.686142,51.807621],"type":"Point"}
}