{
  "type": "Feature",
  "properties": {
    "addr:full":"Zwettestraat 21 Leeuwarden Provincie Friesland 8912 AH",
    "addr:housenumber":"21",
    "addr:postcode":"8912 ah",
    "addr:street":"Zwettestraat;Provincie Friesland",
    "iso:country":"NL",
    "sg:address":"Zwettestraat 21",
    "sg:city":"Leeuwarden",
    "sg:orig_category":"Meubelzaken, Woning- And Keukeninrichting",
    "sg:phone":"+31 58 213 2040",
    "sg:postcode":"8912 AH",
    "sg:province":"Provincie Friesland",
    "wof:name":"Runner Meubelen",
    "wof:placetype":"venue"
},
  "geometry": {"coordinates":[5.7695708275,53.1945075989],"type":"Point"}
}