{
  "type": "Feature",
  "properties": {
    "addr:full":"Spuistr 23 S Gravenhage South Holland 2511 BC",
    "addr:housenumber":"23",
    "addr:postcode":"2511 bc",
    "addr:street":"Spuistr;S Gravenhage",
    "iso:country":"NL",
    "sg:address":"Spuistr 23",
    "sg:city":"S Gravenhage",
    "sg:orig_category":"Schoenen",
    "sg:phone":"+31 70 345 3099",
    "sg:postcode":"2511 BC",
    "sg:province":"South Holland",
    "wof:name":"Invito Bv",
    "wof:placetype":"venue"
},
  "geometry": {"coordinates":[4.31627,52.07896],"type":"Point"}
}