{
  "type": "Feature",
  "properties": {
    "iso:country":"NL",
    "sg:address":"Putweg 21",
    "sg:city":"America",
    "sg:orig_category":"Beautyfarms And Sauna'S",
    "sg:phone":"+31 77 464 1388",
    "sg:postcode":"5966 PS",
    "sg:province":"Limburg",
    "wof:name":"Christel Van Hees",
    "wof:placetype":"venue"
},
  "geometry": {"coordinates":[5.967175,51.437637],"type":"Point"}
}