{
  "type": "Feature",
  "properties": {
    "addr:full":"Dr Schaepmanln 65 Roosendaal Noord-Brabant 4702 GV",
    "addr:housenumber":"65",
    "addr:postcode":"4702 gv",
    "iso:country":"NL",
    "sg:address":"Dr Schaepmanln 65",
    "sg:city":"Roosendaal",
    "sg:orig_category":"Verenigingen En Stichtingen",
    "sg:phone":"+31 165 560 202",
    "sg:postcode":"4702 GV",
    "sg:province":"Noord-Brabant",
    "wof:name":"Aopa Netherlands",
    "wof:placetype":"venue"
},
  "geometry": {"coordinates":[4.473999,51.534771],"type":"Point"}
}