{
  "type": "Feature",
  "properties": {
    "addr:full":"De Brink 180 Groningen Groningen 9723 AM",
    "addr:housenumber":"180",
    "addr:postcode":"9723",
    "addr:street":"De Brink",
    "iso:country":"NL",
    "sg:address":"De Brink 180",
    "sg:city":"Groningen",
    "sg:orig_category":"Boekhouders",
    "sg:phone":"+31 50 318 0305",
    "sg:postcode":"9723 AM",
    "sg:province":"Groningen",
    "wof:name":"Administratiekantoor E. Poeder",
    "wof:placetype":"venue"
},
  "geometry": {"coordinates":[6.647589,53.208031],"type":"Point"}
}