{
  "type": "Feature",
  "properties": {
    "iso:country":"NL",
    "sg:address":"Thomsonln 23",
    "sg:city":"S Gravenhage",
    "sg:orig_category":"Vertaalbureaus",
    "sg:phone":"+31 70 360 9524",
    "sg:postcode":"2565 KZ",
    "sg:province":"Zuid-Holland",
    "sg:website":"http://www.aber-yes.nl",
    "wof:name":"Aber Yes",
    "wof:placetype":"venue"
},
  "geometry": {"coordinates":[4.26129,52.076382],"type":"Point"}
}