{
  "type": "Feature",
  "properties": {
    "addr:full":"Vismarkt 13 Heusden Gem Heusd Noord-Brabant 5256 BC",
    "addr:housenumber":"13",
    "addr:postcode":"heusd;5256 bc",
    "addr:street":"Vismarkt",
    "iso:country":"NL",
    "sg:address":"Vismarkt 13",
    "sg:city":"Heusden Gem Heusd",
    "sg:orig_category":"Zoetwaren - Winkels",
    "sg:phone":"+31 416 665 432",
    "sg:postcode":"5256 BC",
    "sg:province":"Noord-Brabant",
    "wof:name":"Langen Lick, In Den",
    "wof:placetype":"venue"
},
  "geometry": {"coordinates":[5.137448,51.73457],"type":"Point"}
}