{
  "type": "Feature",
  "properties": {
    "addr:full":"Wakkerendk 228 Eemnes Utrecht 3755 DJ",
    "addr:housenumber":"228",
    "addr:postcode":"3755 dj",
    "addr:street":"Eemnes",
    "iso:country":"NL",
    "sg:address":"Wakkerendk 228",
    "sg:city":"Eemnes",
    "sg:orig_category":"Adviesbureaus Financieel",
    "sg:phone":"+31 35 621 0341",
    "sg:postcode":"3755 DJ",
    "sg:province":"Utrecht",
    "wof:name":"Mulders, M D",
    "wof:placetype":"venue"
},
  "geometry": {"coordinates":[5.256748,52.23056],"type":"Point"}
}