{
  "type": "Feature",
  "properties": {
    "addr:full":"Raadhuislaan 80 Eemnes Utrecht 3755 HD",
    "addr:housenumber":"80",
    "addr:postcode":"3755 hd",
    "addr:street":"Raadhuislaan",
    "iso:country":"NL",
    "sg:address":"Raadhuislaan 80",
    "sg:city":"Eemnes",
    "sg:classifiers":[
        {
            "category":"Education",
            "subcategory":"Preschool",
            "type":"Public Place"
        }
    ],
    "sg:phone":"+31 35 538 3855",
    "sg:postcode":"3755 HD",
    "sg:province":"Utrecht",
    "sg:tags":[
        "kleuteronderwijs",
        "basis-"
    ],
    "wof:name":"De Zuidwend",
    "wof:placetype":"venue"
},
  "geometry": {"coordinates":[5.259504,52.250927],"type":"Point"}
}