{
  "type": "Feature",
  "properties": {
    "addr:full":"Auroraweg 6 Doetinchem Gelderland 7007 GZ",
    "addr:housenumber":"6",
    "addr:postcode":"7007 gz",
    "addr:street":"Auroraweg;Gelderland",
    "iso:country":"NL",
    "sg:address":"Auroraweg 6",
    "sg:city":"Doetinchem",
    "sg:orig_category":"Fietshandelaren",
    "sg:phone":"+31 314 330 921",
    "sg:postcode":"7007 GZ",
    "sg:province":"Gelderland",
    "wof:name":"Wielerspeciaalzaak De Pedaleur",
    "wof:placetype":"venue"
},
  "geometry": {"coordinates":[6.271822,51.955017],"type":"Point"}
}