{
  "type": "Feature",
  "properties": {
    "addr:full":"Banmolen 16 Meijel Limburg 5768 ET",
    "addr:housenumber":"16",
    "addr:postcode":"5768 et",
    "addr:street":"Banmolen",
    "iso:country":"NL",
    "sg:address":"Banmolen 16",
    "sg:city":"Meijel",
    "sg:orig_category":"Verhuur Audiovisuele Apparatuur",
    "sg:phone":"+31 77 466 3774",
    "sg:postcode":"5768 ET",
    "sg:province":"Limburg",
    "wof:name":"Geluids En Lichtverhuur J.M.S. Vof",
    "wof:placetype":"venue"
},
  "geometry": {"coordinates":[5.878574,51.352341],"type":"Point"}
}