{
  "type": "Feature",
  "properties": {
    "addr:full":"Handellaan 4 'S Gravenhage Zuid-Holland 2555 WD",
    "addr:housenumber":"4 '",
    "addr:postcode":"2555 wd",
    "addr:street":"Handellaan",
    "iso:country":"NL",
    "sg:address":"Handellaan 4",
    "sg:city":"'S Gravenhage",
    "sg:orig_category":"Kappers",
    "sg:phone":"+31 70 368 8735",
    "sg:postcode":"2555 WD",
    "sg:province":"Zuid-Holland",
    "wof:name":"Haarverzorging Marianne",
    "wof:placetype":"venue"
},
  "geometry": {"coordinates":[4.2407298088,52.0654258728],"type":"Point"}
}