{
  "type": "Feature",
  "properties": {
    "addr:full":"Maastrichtsewg 66 S Hertogenbosch Noord-Brabant 5215 AD",
    "addr:housenumber":"66",
    "addr:postcode":"5215 ad",
    "addr:street":"Maastrichtsewg;S Hertogenbosch",
    "iso:country":"NL",
    "sg:address":"Maastrichtsewg 66",
    "sg:city":"S Hertogenbosch",
    "sg:orig_category":"Organisatiebureaus",
    "sg:phone":"+31 73 614 3371",
    "sg:postcode":"5215 AD",
    "sg:province":"Noord-Brabant",
    "sg:website":"http://www.dialogistiek.com",
    "wof:name":"Dialogstiek",
    "wof:placetype":"venue"
},
  "geometry": {"coordinates":[5.3226480484,51.6879806519],"type":"Point"}
}