{
  "type": "Feature",
  "properties": {
    "addr:full":"Stichtseweg 2 Blaricum Noord-Holland 1261 TA",
    "addr:housenumber":"2",
    "addr:postcode":"1261 ta",
    "addr:street":"Stichtseweg",
    "iso:country":"NL",
    "sg:address":"Stichtseweg 2",
    "sg:city":"Blaricum",
    "sg:orig_category":"Bloemen And Planten",
    "sg:phone":"+31 35 526 7976",
    "sg:postcode":"1261 TA",
    "sg:province":"Noord-Holland",
    "wof:name":"Hoveniersbedrijf J. Koster En Zoon Vof",
    "wof:placetype":"venue"
},
  "geometry": {"coordinates":[5.26827,52.282135],"type":"Point"}
}