{
  "type": "Feature",
  "properties": {
    "addr:full":"Kon Julianapln 1 Spykenisse Zuid-Holland 3201 CH",
    "addr:housenumber":"1",
    "addr:postcode":"3201",
    "addr:street":"Kon Julianapln",
    "iso:country":"NL",
    "sg:address":"Kon Julianapln 1",
    "sg:city":"Spykenisse",
    "sg:orig_category":"Verenigingen En Stichtingen",
    "sg:phone":"+31 181 678 787",
    "sg:postcode":"3201 CH",
    "sg:province":"Zuid-Holland",
    "wof:name":"Clusterkantoor Pameijerkeerkring",
    "wof:placetype":"venue"
},
  "geometry": {"coordinates":[4.325045,51.849525],"type":"Point"}
}