{
  "type": "Feature",
  "properties": {
    "iso:country":"NL",
    "sg:address":"Hardenbergerweg 7",
    "sg:city":"Marienberg",
    "sg:orig_category":"Goederenvervoer Over De Weg",
    "sg:phone":"+31 523 251 901",
    "sg:postcode":"7692 PA",
    "sg:province":"NL.08",
    "wof:name":"Koerierservice Klokkers",
    "wof:placetype":"venue"
},
  "geometry": {"coordinates":[6.576033,52.513786],"type":"Point"}
}