{
  "type": "Feature",
  "properties": {
    "addr:full":"Nieuwstraat 13 Apeldoorn Gelderland 7311 HX",
    "addr:housenumber":"13",
    "addr:postcode":"7311 hx",
    "addr:street":"Nieuwstraat;Gelderland",
    "iso:country":"NL",
    "sg:address":"Nieuwstraat 13",
    "sg:city":"Apeldoorn",
    "sg:classifiers":[
        {
            "category":"Communications",
            "subcategory":"Television Station",
            "type":"Services"
        }
    ],
    "sg:phone":"+31 55 522 0415",
    "sg:postcode":"7311 HX",
    "sg:province":"Gelderland",
    "sg:tags":[
        "video",
        "audio",
        "verhuur"
    ],
    "wof:name":"Videotheek Nieuwstraat",
    "wof:placetype":"venue"
},
  "geometry": {"coordinates":[5.961509,52.212082],"type":"Point"}
}