{
  "type": "Feature",
  "properties": {
    "addr:full":"Brahmsstr 17 Capelle Ad Yssel Zuid-Holland 2901 HG",
    "addr:housenumber":"17;2901",
    "addr:postcode":"hg",
    "addr:street":"Brahmsstr",
    "iso:country":"NL",
    "sg:address":"Brahmsstr 17",
    "sg:city":"Capelle Ad Yssel",
    "sg:orig_category":"Schilders",
    "sg:phone":"+31 6 41505090",
    "sg:postcode":"2901 HG",
    "sg:province":"Zuid-Holland",
    "wof:name":"Crezee",
    "wof:placetype":"venue"
},
  "geometry": {"coordinates":[4.561218,51.918285],"type":"Point"}
}