{
  "type": "Feature",
  "properties": {
    "addr:full":"Goudsewg 12 Gouda Zuid-Holland 2808 NJ",
    "addr:housenumber":"12",
    "addr:postcode":"2808 nj",
    "addr:street":"Goudsewg",
    "iso:country":"NL",
    "sg:address":"Goudsewg 12",
    "sg:city":"Gouda",
    "sg:orig_category":"Adviesbureaus Bouwkunde",
    "sg:phone":"+31 182 687 875",
    "sg:postcode":"2808 NJ",
    "sg:province":"Zuid-Holland",
    "wof:name":"Q4U Bv",
    "wof:placetype":"venue"
},
  "geometry": {"coordinates":[4.720558,52.004314],"type":"Point"}
}