{
  "type": "Feature",
  "properties": {
    "addr:full":"Plantsoen 2 Geertruidenberg North Brabant 4931 AT",
    "addr:housenumber":"2",
    "addr:postcode":"4931",
    "addr:street":"Plantsoen",
    "iso:country":"NL",
    "sg:address":"Plantsoen 2",
    "sg:city":"Geertruidenberg",
    "sg:orig_category":"Organisatiebureaus",
    "sg:phone":"+31 162 517 028",
    "sg:postcode":"4931 AT",
    "sg:province":"North Brabant",
    "wof:name":"New Gereration Concept",
    "wof:placetype":"venue"
},
  "geometry": {"coordinates":[4.8637561798,51.699596405],"type":"Point"}
}