{
  "type": "Feature",
  "properties": {
    "addr:full":"Gemullehoekenweg 9 Oisterwijk Noord-Brabant 5061 MA",
    "addr:housenumber":"9",
    "addr:postcode":"5061 ma",
    "addr:street":"Gemullehoekenweg",
    "iso:country":"NL",
    "sg:address":"Gemullehoekenweg 9",
    "sg:city":"Oisterwijk",
    "sg:orig_category":"Bloemen And Planten",
    "sg:phone":"+31 13 528 8620",
    "sg:postcode":"5061 MA",
    "sg:province":"Noord-Brabant",
    "wof:name":"T Klavertje",
    "wof:placetype":"venue"
},
  "geometry": {"coordinates":[5.200273,51.580788],"type":"Point"}
}