{
  "type": "Feature",
  "properties": {
    "iso:country":"NL",
    "sg:address":"Elandsgr 93-97",
    "sg:city":"Amsterdam",
    "sg:orig_category":"Verf En Lak",
    "sg:phone":"+31 20 626 3030",
    "sg:postcode":"1016 TS",
    "sg:province":"North Holland",
    "sg:website":"http://www.engels.nu",
    "wof:name":"Engels",
    "wof:placetype":"venue"
},
  "geometry": {"coordinates":[4.879459,52.369034],"type":"Point"}
}