{
  "type": "Feature",
  "properties": {
    "addr:full":"Levendaal 18 Ede Gld Gelderland 6715 KK",
    "addr:housenumber":"18",
    "addr:postcode":"6715 kk",
    "addr:street":"Levendaal;Gld Gelderland",
    "iso:country":"NL",
    "sg:address":"Levendaal 18",
    "sg:city":"Ede Gld",
    "sg:classifiers":[
        {
            "category":"Personal",
            "subcategory":"Nail Salon",
            "type":"Services"
        }
    ],
    "sg:phone":"+31 318 639 941",
    "sg:postcode":"6715 KK",
    "sg:province":"Gelderland",
    "sg:tags":[
        "pedicure"
    ],
    "wof:name":"Velde, Marja Van De",
    "wof:placetype":"venue"
},
  "geometry": {"coordinates":[5.633497,52.038208],"type":"Point"}
}