{
  "type": "Feature",
  "properties": {
    "iso:country":"NL",
    "sg:address":"Overtoom 245",
    "sg:city":"Amsterdam",
    "sg:orig_category":"Kappers",
    "sg:phone":"+31 20 689 4553",
    "sg:postcode":"1054 HW",
    "sg:province":"North Holland",
    "sg:website":"http://www.kinki.nl",
    "wof:name":"Kinki Kappers",
    "wof:placetype":"venue"
},
  "geometry": {"coordinates":[4.8688678741,52.3608932495],"type":"Point"}
}