{
  "type": "Feature",
  "properties": {
    "iso:country":"NL",
    "sg:address":"Oosterblokker 47",
    "sg:city":"Oosterblokker",
    "sg:orig_category":"Gespecialiseerde Bouw",
    "sg:phone":"+31 229 262 441",
    "sg:postcode":"1696 BB",
    "sg:province":"North Holland",
    "wof:name":"O.J. Koedooder",
    "wof:placetype":"venue"
},
  "geometry": {"coordinates":[5.117142,52.668201],"type":"Point"}
}