{
  "type": "Feature",
  "properties": {
    "addr:full":"Schrijverstraat 1 Almere Flevoland 1315 HW",
    "addr:housenumber":"1",
    "addr:postcode":"1315 hw",
    "addr:street":"Schrijverstraat;Flevoland",
    "iso:country":"NL",
    "sg:address":"Schrijverstraat 1",
    "sg:city":"Almere",
    "sg:orig_category":"Bibliotheken And Openbare Archieven",
    "sg:phone":"+31 36 548 6000",
    "sg:postcode":"1315 HW",
    "sg:province":"Flevoland",
    "wof:name":"Openbare Bibliotheek",
    "wof:placetype":"venue"
},
  "geometry": {"coordinates":[5.221869,52.372662],"type":"Point"}
}