{
  "type": "Feature",
  "properties": {
    "addr:full":"Lagelandsepad 47 Rotterdam Zuid-Holland 3062 CH",
    "addr:housenumber":"47",
    "addr:postcode":"3062",
    "addr:street":"Lagelandsepad",
    "iso:country":"NL",
    "sg:address":"Lagelandsepad 47",
    "sg:city":"Rotterdam",
    "sg:orig_category":"Verenigingen En Stichtingen",
    "sg:phone":"+31 10 420 4651",
    "sg:postcode":"3062 CH",
    "sg:province":"Zuid-Holland",
    "wof:name":"Impeesa Scouting Voor Lichamelijk Gehandicapte Jongeren",
    "wof:placetype":"venue"
},
  "geometry": {"coordinates":[4.53083,51.939899],"type":"Point"}
}