{
  "type": "Feature",
  "properties": {
    "iso:country":"NL",
    "sg:address":"Heemraadssingel 122",
    "sg:city":"Rotterdam Centrum",
    "sg:orig_category":"Makelaars In Onroerend Goed",
    "sg:phone":"+31 10 478 3335",
    "sg:postcode":"3021 DH",
    "sg:province":"South Holland",
    "wof:name":"El Jawa Beheer",
    "wof:placetype":"venue"
},
  "geometry": {"coordinates":[4.455895,51.917698],"type":"Point"}
}