{
  "type": "Feature",
  "properties": {
    "addr:full":"J Vd Vondelstr 17 Sliedrecht Zuid-Holland 3362 TK",
    "addr:housenumber":"17",
    "addr:postcode":"3362 tk",
    "iso:country":"NL",
    "sg:address":"J Vd Vondelstr 17",
    "sg:city":"Sliedrecht",
    "sg:orig_category":"Bedrijfsopleidingen",
    "sg:phone":"+31 184 424 220",
    "sg:postcode":"3362 TK",
    "sg:province":"Zuid-Holland",
    "sg:website":"http://www.stuij.nl",
    "wof:name":"Stuij",
    "wof:placetype":"venue"
},
  "geometry": {"coordinates":[4.776595,51.819195],"type":"Point"}
}