{
  "type": "Feature",
  "properties": {
    "addr:full":"Pouwelslaan 1 Honselersdijk South Holland 2675 BK",
    "addr:housenumber":"1",
    "addr:postcode":"2675 bk",
    "addr:street":"Pouwelslaan",
    "iso:country":"NL",
    "sg:address":"Pouwelslaan 1",
    "sg:city":"Honselersdijk",
    "sg:orig_category":"Pleziervaartuigen And Reparatie",
    "sg:phone":"+31 174 245 279",
    "sg:postcode":"2675 BK",
    "sg:province":"South Holland",
    "wof:name":"N.A.M. Van Zeijl",
    "wof:placetype":"venue"
},
  "geometry": {"coordinates":[4.209024,52.01886],"type":"Point"}
}