{
  "type": "Feature",
  "properties": {
    "addr:full":"R De Graafwg 392 Delft Zuid-Holland 2625 DL",
    "addr:housenumber":"392",
    "addr:postcode":"delft;2625 dl",
    "iso:country":"NL",
    "sg:address":"R De Graafwg 392",
    "sg:city":"Delft",
    "sg:orig_category":"Hypnotherapeuten",
    "sg:phone":"+31 15 261 3306",
    "sg:postcode":"2625 DL",
    "sg:province":"Zuid-Holland",
    "sg:website":"http://home-planet.nl~zwenn017",
    "wof:name":"Zwennes, Sonja",
    "wof:placetype":"venue"
},
  "geometry": {"coordinates":[4.336821,51.998207],"type":"Point"}
}