{
  "type": "Feature",
  "properties": {
    "addr:full":"Gaedsberghwg 75 Hattem Gelderland 8051 LM",
    "addr:housenumber":"75",
    "addr:postcode":"8051 lm",
    "addr:street":"Gaedsberghwg;Gelderland",
    "iso:country":"NL",
    "sg:address":"Gaedsberghwg 75",
    "sg:city":"Hattem",
    "sg:orig_category":"Adviesbureaus Marketing",
    "sg:phone":"+31 38 355 6685",
    "sg:postcode":"8051 LM",
    "sg:province":"Gelderland",
    "wof:name":"Metaphor",
    "wof:placetype":"venue"
},
  "geometry": {"coordinates":[6.054762,52.472923],"type":"Point"}
}