{
  "type": "Feature",
  "properties": {
    "addr:full":"Ln V Meerdervoort 236 S Gravenhage Zuid-Holland 2563 AH",
    "addr:housenumber":"236;gravenhage",
    "addr:postcode":"2563 ah",
    "addr:street":"Ln;Meerdervoort;S",
    "iso:country":"NL",
    "sg:address":"Ln V Meerdervoort 236",
    "sg:city":"S Gravenhage",
    "sg:orig_category":"Horloges En Klokken - Reparatie En Onderhoud",
    "sg:phone":"+31 70 365 7665",
    "sg:postcode":"2563 AH",
    "sg:province":"Zuid-Holland",
    "wof:name":"Tol, A Van",
    "wof:placetype":"venue"
},
  "geometry": {"coordinates":[4.270956,52.072578],"type":"Point"}
}