{
  "type": "Feature",
  "properties": {
    "addr:full":"Zwaanwg 18 Werkhoven Utrecht 3985 PL",
    "addr:housenumber":"18",
    "addr:postcode":"3985 pl",
    "addr:street":"Zwaanwg",
    "iso:country":"NL",
    "sg:address":"Zwaanwg 18",
    "sg:city":"Werkhoven",
    "sg:orig_category":"Schilders",
    "sg:phone":"+31 343 551 725",
    "sg:postcode":"3985 PL",
    "sg:province":"Utrecht",
    "wof:name":"Lam, Schilders- & Behangbedrijf J G",
    "wof:placetype":"venue"
},
  "geometry": {"coordinates":[5.242656,52.023788],"type":"Point"}
}