{
  "type": "Feature",
  "properties": {
    "addr:full":"Mient 229 S Gravenhage Zuid-Holland 2564 KL",
    "addr:housenumber":"229;gravenhage",
    "addr:postcode":"2564 kl",
    "addr:street":"Mient;S",
    "iso:country":"NL",
    "sg:address":"Mient 229",
    "sg:city":"S Gravenhage",
    "sg:orig_category":"Journalisten Freelance",
    "sg:phone":"+31 70 323 7455",
    "sg:postcode":"2564 KL",
    "sg:province":"Zuid-Holland",
    "wof:name":"Vijverman & Van Leeuwen",
    "wof:placetype":"venue"
},
  "geometry": {"coordinates":[4.25946,52.06805],"type":"Point"}
}