{
  "type": "Feature",
  "properties": {
    "iso:country":"NL",
    "sg:address":"Spaaihoefwg 15",
    "sg:city":"Eindhoven",
    "sg:orig_category":"Woningstoffeerders",
    "sg:phone":"+31 40 262 1431",
    "sg:postcode":"5627 BC",
    "sg:province":"Noord-Brabant",
    "wof:name":"Alberts",
    "wof:placetype":"venue"
},
  "geometry": {"coordinates":[5.4362139702,51.4842910767],"type":"Point"}
}