{
  "type": "Feature",
  "properties": {
    "addr:full":"Roerdompstraat 3 Zwijndrecht South Holland 3334 AG",
    "addr:housenumber":"3",
    "addr:postcode":"3334",
    "addr:street":"Roerdompstraat",
    "iso:country":"NL",
    "sg:address":"Roerdompstraat 3",
    "sg:city":"Zwijndrecht",
    "sg:classifiers":[
        {
            "category":"Education",
            "subcategory":"Preschool",
            "type":"Public Place"
        }
    ],
    "sg:phone":"+31 78 612 9029",
    "sg:postcode":"3334 AG",
    "sg:province":"South Holland",
    "sg:tags":[
        "kleuteronderwijs",
        "basis-"
    ],
    "wof:name":"Openbare Basisschool De Twee Wieken",
    "wof:placetype":"venue"
},
  "geometry": {"coordinates":[4.619814,51.814632],"type":"Point"}
}