{
  "type": "Feature",
  "properties": {
    "iso:country":"NL",
    "sg:address":"Kleine Buitenom 1",
    "sg:city":"Culemborg",
    "sg:orig_category":"Onderhoud And Reparatie Kantoorapparatuur",
    "sg:phone":"+31 345 533 802",
    "sg:postcode":"4101 AP",
    "sg:province":"Gelderland",
    "wof:name":"Abraxus",
    "wof:placetype":"venue"
},
  "geometry": {"coordinates":[5.220185,51.957325],"type":"Point"}
}