{
  "type": "Feature",
  "properties": {
    "iso:country":"NL",
    "sg:address":"Den Bogerd 15",
    "sg:city":"Hardinxveld Giessend",
    "sg:orig_category":"Kledingzaken",
    "sg:phone":"+31 184 670 949",
    "sg:postcode":"3371 AM",
    "sg:province":"Zuid-Holland",
    "wof:name":"Albert De Vries",
    "wof:placetype":"venue"
},
  "geometry": {"coordinates":[4.833621,51.827072],"type":"Point"}
}