{
  "type": "Feature",
  "properties": {
    "addr:full":"Boterhoek 3 Leeuwarden Friesland 8911 DH",
    "addr:housenumber":"3",
    "addr:postcode":"8911 dh",
    "addr:street":"Boterhoek",
    "iso:country":"NL",
    "sg:address":"Boterhoek 3",
    "sg:city":"Leeuwarden",
    "sg:orig_category":"Bibliotheken And Openbare Archieven",
    "sg:phone":"+31 58 212 7103",
    "sg:postcode":"8911 DH",
    "sg:province":"Friesland",
    "wof:name":"Rijksarchief",
    "wof:placetype":"venue"
},
  "geometry": {"coordinates":[5.790661,53.20348],"type":"Point"}
}