{
  "type": "Feature",
  "properties": {
    "addr:full":"Aardster 253 Alphen A/D Rijn Zuid-Holland 2403 RR",
    "addr:housenumber":"253",
    "addr:postcode":"2403 rr",
    "addr:street":"Aardster",
    "iso:country":"NL",
    "sg:address":"Aardster 253",
    "sg:city":"Alphen A/D Rijn",
    "sg:orig_category":"Goederenvervoer Over De Weg",
    "sg:phone":"+31 172 443 993",
    "sg:postcode":"2403 RR",
    "sg:province":"Zuid-Holland",
    "wof:name":"M Blijleven En Zn",
    "wof:placetype":"venue"
},
  "geometry": {"coordinates":[4.679488,52.150265],"type":"Point"}
}