{
  "type": "Feature",
  "properties": {
    "iso:country":"NL",
    "sg:address":"Witgeellaan 160",
    "sg:city":"Zoetermeer",
    "sg:orig_category":"Glaszetten",
    "sg:phone":"+31 79 362 0144",
    "sg:postcode":"2718 CK",
    "sg:province":"Zuid-Holland",
    "wof:name":"Schildersbedrijf Th. Hansen",
    "wof:placetype":"venue"
},
  "geometry": {"coordinates":[4.484165,52.039272],"type":"Point"}
}