{
  "type": "Feature",
  "properties": {
    "addr:full":"Yselstr 41 Amsterdam Noord-Holland 1078 CB",
    "addr:housenumber":"41",
    "addr:postcode":"1078 cb",
    "addr:street":"Yselstr",
    "iso:country":"NL",
    "sg:address":"Yselstr 41",
    "sg:city":"Amsterdam",
    "sg:orig_category":"Adviesbureaus Bedrijfsorganisatie",
    "sg:phone":"+31 20 675 0996",
    "sg:postcode":"1078 CB",
    "sg:province":"Noord-Holland",
    "wof:name":"Raatgever, M",
    "wof:placetype":"venue"
},
  "geometry": {"coordinates":[4.902363,52.347118],"type":"Point"}
}