{
  "type": "Feature",
  "properties": {
    "iso:country":"NL",
    "sg:address":"Everbest 56",
    "sg:city":"Beek En Donk",
    "sg:orig_category":"Land- En Tuinbouw - Mechanisatie",
    "sg:phone":"+31 492 464 876",
    "sg:postcode":"5741 PM",
    "sg:province":"North Brabant",
    "wof:name":"Verkuijlen, Adrie",
    "wof:placetype":"venue"
},
  "geometry": {"coordinates":[5.634493,51.546608],"type":"Point"}
}