{
  "type": "Feature",
  "properties": {
    "addr:full":"Neerynense Mark 1 Neerynen Gelderland 4182 SB",
    "addr:housenumber":"1",
    "addr:postcode":"4182 sb",
    "addr:street":"Mark;Gelderland",
    "iso:country":"NL",
    "sg:address":"Neerynense Mark 1",
    "sg:city":"Neerynen",
    "sg:orig_category":"Kabelwerken",
    "sg:phone":"+31 345 569 798",
    "sg:postcode":"4182 SB",
    "sg:province":"Gelderland",
    "wof:name":"Beek Bv, Van De",
    "wof:placetype":"venue"
},
  "geometry": {"coordinates":[5.2790617943,51.8556518555],"type":"Point"}
}