{
  "type": "Feature",
  "properties": {
    "addr:full":"Kapelstr 8 Tilburg Noord-Brabant 5046 CM",
    "addr:housenumber":"8",
    "addr:postcode":"5046 cm",
    "addr:street":"Kapelstr",
    "iso:country":"NL",
    "sg:address":"Kapelstr 8",
    "sg:city":"Tilburg",
    "sg:orig_category":"Geluidsinstallaties - Verhuur",
    "sg:phone":"+31 6 54368873",
    "sg:postcode":"5046 CM",
    "sg:province":"Noord-Brabant",
    "sg:website":"http://www.jlsound.nl",
    "wof:name":"Jl Sound",
    "wof:placetype":"venue"
},
  "geometry": {"coordinates":[5.077628,51.576099],"type":"Point"}
}