{
  "type": "Feature",
  "properties": {
    "iso:country":"NL",
    "sg:address":"Tienhovensewg 29",
    "sg:city":"Hagestein",
    "sg:orig_category":"Schilders",
    "sg:phone":"+31 347 352 424",
    "sg:postcode":"4124 KV",
    "sg:province":"Utrecht",
    "wof:name":"Bor Hagestein",
    "wof:placetype":"venue"
},
  "geometry": {"coordinates":[5.135906,51.963493],"type":"Point"}
}