{
  "type": "Feature",
  "properties": {
    "addr:full":"Sprundelsewg 53 Rucphen Noord-Brabant 4715 RB",
    "addr:housenumber":"53",
    "addr:postcode":"4715 rb",
    "addr:street":"Sprundelsewg",
    "iso:country":"NL",
    "sg:address":"Sprundelsewg 53",
    "sg:city":"Rucphen",
    "sg:orig_category":"Pijpleidingen - Installatie En Onderhoud",
    "sg:phone":"+31 165 348 982",
    "sg:postcode":"4715 RB",
    "sg:province":"Noord-Brabant",
    "wof:name":"Gorter, E",
    "wof:placetype":"venue"
},
  "geometry": {"coordinates":[4.577512,51.531727],"type":"Point"}
}