{
  "type": "Feature",
  "properties": {
    "addr:full":"Groene Kruisstraat 1 Herten Baden-W\u00fcrttemberg 6049 BW",
    "addr:housenumber":"1",
    "addr:postcode":"6049 bw",
    "addr:street":"Groene Kruisstraat",
    "iso:country":"NL",
    "sg:address":"Groene Kruisstraat 1",
    "sg:city":"Herten",
    "sg:orig_category":"Paramedische Behandelingen",
    "sg:phone":"+31 475 334 110",
    "sg:postcode":"6049 BW",
    "sg:province":"Baden-W\u00fcrttemberg",
    "wof:name":"Stichting Thuiszorg Midden-Limburg",
    "wof:placetype":"venue"
},
  "geometry": {"coordinates":[7.72902,47.554932],"type":"Point"}
}