{
  "type": "Feature",
  "properties": {
    "addr:full":"Karspeldreef 15 Amsterdam Zuidoost Noord-Holland 1102 BB",
    "addr:housenumber":"15",
    "addr:postcode":"zuidoost;1102 bb",
    "addr:street":"Karspeldreef",
    "iso:country":"NL",
    "sg:address":"Karspeldreef 15",
    "sg:city":"Amsterdam Zuidoost",
    "sg:orig_category":"Verzekerings- Maatschappijen",
    "sg:phone":"+31 20 651 7517",
    "sg:postcode":"1102 BB",
    "sg:province":"Noord-Holland",
    "sg:website":"http://www.das.nl",
    "wof:name":"Das",
    "wof:placetype":"venue"
},
  "geometry": {"coordinates":[4.95323,52.307331],"type":"Point"}
}