{
  "type": "Feature",
  "properties": {
    "addr:full":"Wellerondom 11 Brielle Zuid-Holland 3231 XV",
    "addr:housenumber":"11",
    "addr:postcode":"3231 xv",
    "addr:street":"Wellerondom",
    "iso:country":"NL",
    "sg:address":"Wellerondom 11",
    "sg:city":"Brielle",
    "sg:orig_category":"Petrochemische Industrie",
    "sg:phone":"+31 181 414 000",
    "sg:postcode":"3231 XV",
    "sg:province":"Zuid-Holland",
    "sg:website":"http://www.sjb.com",
    "wof:name":"Sjb Bv",
    "wof:placetype":"venue"
},
  "geometry": {"coordinates":[4.163814,51.902554],"type":"Point"}
}