{
  "type": "Feature",
  "properties": {
    "addr:full":"Den Bommelaer 8 Bergeyk North Brabant 5571 SR",
    "addr:housenumber":"8",
    "addr:postcode":"5571 sr",
    "addr:street":"Den Bommelaer",
    "iso:country":"NL",
    "sg:address":"Den Bommelaer 8",
    "sg:city":"Bergeyk",
    "sg:orig_category":"Geluidsinstallaties - Verhuur",
    "sg:phone":"+31 497 572 309",
    "sg:postcode":"5571 SR",
    "sg:province":"North Brabant",
    "wof:name":"Weert, F Van",
    "wof:placetype":"venue"
},
  "geometry": {"coordinates":[5.360135,51.323326],"type":"Point"}
}