{
  "type": "Feature",
  "properties": {
    "addr:full":"Marga Klompelaan 11 Olst Overijssel 8121 KJ",
    "addr:housenumber":"11",
    "addr:postcode":"8121 kj",
    "addr:street":"Marga Klompelaan",
    "iso:country":"NL",
    "sg:address":"Marga Klompelaan 11",
    "sg:city":"Olst",
    "sg:orig_category":"Binnenhuisarchitecten",
    "sg:phone":"+31 570 563 379",
    "sg:postcode":"8121 KJ",
    "sg:province":"Overijssel",
    "wof:name":"Karin Blonk",
    "wof:placetype":"venue"
},
  "geometry": {"coordinates":[6.111504,52.335651],"type":"Point"}
}