{
  "type": "Feature",
  "properties": {
    "iso:country":"NL",
    "sg:address":"Lariksstr 29",
    "sg:city":"Dordrecht",
    "sg:orig_category":"Administratie- En Boekhoudkantoren",
    "sg:phone":"+31 78 616 2538",
    "sg:postcode":"3329 AJ",
    "sg:province":"Zuid-Holland",
    "wof:name":"Kaw",
    "wof:placetype":"venue"
},
  "geometry": {"coordinates":[4.708483,51.78727],"type":"Point"}
}