{
  "type": "Feature",
  "properties": {
    "addr:full":"St Jacobsstr 400 Utrecht Utrecht 3511 BT",
    "addr:housenumber":"400",
    "addr:postcode":"3511 bt",
    "iso:country":"NL",
    "sg:address":"St Jacobsstr 400",
    "sg:city":"Utrecht",
    "sg:orig_category":"Hypotheken",
    "sg:phone":"+31 30 239 1300",
    "sg:postcode":"3511 BT",
    "sg:province":"Utrecht",
    "sg:website":"http://www.wubank.nl",
    "wof:name":"Westland/Utrecht",
    "wof:placetype":"venue"
},
  "geometry": {"coordinates":[5.113538,52.095909],"type":"Point"}
}