{
  "type": "Feature",
  "properties": {
    "iso:country":"NL",
    "sg:address":"Nijlring 65",
    "sg:city":"Drunen",
    "sg:orig_category":"Boekhouders",
    "sg:phone":"+31 416 376 195",
    "sg:postcode":"5152 VJ",
    "sg:province":"Noord-Brabant",
    "wof:name":"C.A. Elshout-Kuhn",
    "wof:placetype":"venue"
},
  "geometry": {"coordinates":[5.118373,51.681477],"type":"Point"}
}