{
  "type": "Feature",
  "properties": {
    "addr:full":"Noordkade 4 Weert Limburg 6003 ND",
    "addr:housenumber":"4",
    "addr:postcode":"6003 nd",
    "addr:street":"Noordkade",
    "iso:country":"NL",
    "sg:address":"Noordkade 4",
    "sg:city":"Weert",
    "sg:orig_category":"Accountants - Administratie- Consulenten En -Kantoren",
    "sg:phone":"+31 495 534 252",
    "sg:postcode":"6003 ND",
    "sg:province":"Limburg",
    "sg:website":"http://www.abab.nl",
    "wof:name":"Abab",
    "wof:placetype":"venue"
},
  "geometry": {"coordinates":[5.706232,51.258778],"type":"Point"}
}