{
  "type": "Feature",
  "properties": {
    "addr:full":"Stationsplein 92 Haarlem North Holland 2011 LM",
    "addr:housenumber":"92",
    "addr:postcode":"2011 lm",
    "addr:street":"Stationsplein",
    "iso:country":"NL",
    "sg:address":"Stationsplein 92",
    "sg:city":"Haarlem",
    "sg:orig_category":"Technische Studies And Onderzoek",
    "sg:phone":"+31 23 512 8010",
    "sg:postcode":"2011 LM",
    "sg:province":"North Holland",
    "wof:name":"Maetis Arbo",
    "wof:placetype":"venue"
},
  "geometry": {"coordinates":[4.638262,52.386929],"type":"Point"}
}