{
  "type": "Feature",
  "properties": {
    "addr:full":"De Visserlaan 16 Hillegom North Holland 2181 XH",
    "addr:housenumber":"16",
    "addr:postcode":"2181 xh",
    "addr:street":"De Visserlaan",
    "iso:country":"NL",
    "sg:address":"De Visserlaan 16",
    "sg:city":"Hillegom",
    "sg:orig_category":"Boekhouders",
    "sg:phone":"+31 252 525 644",
    "sg:postcode":"2181 XH",
    "sg:province":"North Holland",
    "wof:name":"Administratiekantoor Vdl",
    "wof:placetype":"venue"
},
  "geometry": {"coordinates":[4.593769,52.293114],"type":"Point"}
}