{
  "type": "Feature",
  "properties": {
    "addr:full":"Roebelhof 3 Valkenswaard Noord-Brabant 5551 DJ",
    "addr:housenumber":"3",
    "addr:postcode":"5551 dj",
    "addr:street":"Roebelhof",
    "iso:country":"NL",
    "sg:address":"Roebelhof 3",
    "sg:city":"Valkenswaard",
    "sg:orig_category":"Webdesign Bureaus",
    "sg:phone":"+31 6 55848645",
    "sg:postcode":"5551 DJ",
    "sg:province":"Noord-Brabant",
    "sg:website":"http://www.basontwerpt.nl",
    "wof:name":"Bas Ontwerpt",
    "wof:placetype":"venue"
},
  "geometry": {"coordinates":[5.4273781776,51.3555526733],"type":"Point"}
}