{
  "type": "Feature",
  "properties": {
    "addr:full":"Egstraat 10 Dordrecht South Holland 3319 LA",
    "addr:housenumber":"10",
    "addr:postcode":"3319 la",
    "addr:street":"Egstraat",
    "iso:country":"NL",
    "sg:address":"Egstraat 10",
    "sg:city":"Dordrecht",
    "sg:orig_category":"Banken And Kredietinstellingen",
    "sg:phone":"+31 78 621 0888",
    "sg:postcode":"3319 LA",
    "sg:province":"South Holland",
    "wof:name":"Ptt Post Vestiging Dordrecht",
    "wof:placetype":"venue"
},
  "geometry": {"coordinates":[4.71575,51.796261],"type":"Point"}
}