{
  "type": "Feature",
  "properties": {
    "iso:country":"NL",
    "sg:address":"A Plesmanwg 35H",
    "sg:city":"Rotterdam",
    "sg:orig_category":"Verlichtingsartikelen - Groothandel",
    "sg:phone":"+31 10 294 4404",
    "sg:postcode":"3088 GA",
    "sg:province":"South Holland",
    "sg:website":"http://www.lichtfocus.nl",
    "wof:name":"Lichtfocus Bv",
    "wof:placetype":"venue"
},
  "geometry": {"coordinates":[4.452922,51.876358],"type":"Point"}
}