{
  "type": "Feature",
  "properties": {
    "addr:full":"De Jonge Gerard 12 Amstelveen Noord-Holland 1189 WH",
    "addr:housenumber":"12",
    "addr:postcode":"1189 wh",
    "addr:street":"De Jonge Gerard",
    "iso:country":"NL",
    "sg:address":"De Jonge Gerard 12",
    "sg:city":"Amstelveen",
    "sg:orig_category":"Bloemen En Planten - Decoratie",
    "sg:phone":"+31 6 20434541",
    "sg:postcode":"1189 WH",
    "sg:province":"Noord-Holland",
    "wof:name":"Fontijn, Anne Marie",
    "wof:placetype":"venue"
},
  "geometry": {"coordinates":[4.871319,52.259438],"type":"Point"}
}