{
  "type": "Feature",
  "properties": {
    "addr:full":"Zwanestraat 13 Groningen Groningen 9712 CJ",
    "addr:housenumber":"13",
    "addr:postcode":"9712 cj",
    "addr:street":"Zwanestraat",
    "iso:country":"NL",
    "sg:address":"Zwanestraat 13",
    "sg:city":"Groningen",
    "sg:orig_category":"Kunst And Kunstenaarsbenodigdheden",
    "sg:phone":"+31 50 313 7983",
    "sg:postcode":"9712 CJ",
    "sg:province":"Groningen",
    "wof:name":"Kunstcentrum De Zwaan",
    "wof:placetype":"venue"
},
  "geometry": {"coordinates":[6.564538,53.218555],"type":"Point"}
}