{
  "type": "Feature",
  "properties": {
    "iso:country":"NL",
    "sg:address":"Postbus 138",
    "sg:city":"Wormerveer",
    "sg:orig_category":"Verpakkingen En Verpakkingsmaterialen",
    "sg:phone":"+31 75 642 0214",
    "sg:postcode":"1520 AC",
    "sg:province":"North Holland",
    "sg:website":"http://www.vercom.nl",
    "wof:name":"Vercom International Bv",
    "wof:placetype":"venue"
},
  "geometry": {"coordinates":[4.79178,52.493271],"type":"Point"}
}