{
  "type": "Feature",
  "properties": {
    "addr:full":"Kerkstraat 28 Oisterwijk North Brabant 5061 EJ",
    "addr:housenumber":"28",
    "addr:postcode":"5061 ej",
    "addr:street":"Kerkstraat",
    "iso:country":"NL",
    "sg:address":"Kerkstraat 28",
    "sg:city":"Oisterwijk",
    "sg:orig_category":"Boekenuitgeverijen",
    "sg:phone":"+31 13 521 7197",
    "sg:postcode":"5061 EJ",
    "sg:province":"North Brabant",
    "wof:name":"Boekhandel Oisterwijk",
    "wof:placetype":"venue"
},
  "geometry": {"coordinates":[5.190045,51.580021],"type":"Point"}
}