{
  "type": "Feature",
  "properties": {
    "iso:country":"NL",
    "sg:address":"Raam 88",
    "sg:city":"Gouda",
    "sg:orig_category":"Metaalwerken",
    "sg:phone":"+31 182 511 872",
    "sg:postcode":"2801 VN",
    "sg:province":"Zuid-Holland",
    "wof:name":"Wonen Van Vliet",
    "wof:placetype":"venue"
},
  "geometry": {"coordinates":[4.70726,52.008705],"type":"Point"}
}