{
  "type": "Feature",
  "properties": {
    "addr:full":"Rhijnhofweg 10 Oegstgeest Zuid-Holland 2342 BB",
    "addr:housenumber":"10",
    "addr:postcode":"2342 bb",
    "addr:street":"Rhijnhofweg",
    "iso:country":"NL",
    "sg:address":"Rhijnhofweg 10",
    "sg:city":"Oegstgeest",
    "sg:orig_category":"Bloemen And Planten Gh",
    "sg:phone":"+31 71 517 7400",
    "sg:postcode":"2342 BB",
    "sg:province":"Zuid-Holland",
    "wof:name":"Machiel Verhaar Bloemenexport Oegstgeest",
    "wof:placetype":"venue"
},
  "geometry": {"coordinates":[4.447318,52.165413],"type":"Point"}
}