{
  "type": "Feature",
  "properties": {
    "iso:country":"NL",
    "sg:address":"Lindenlaan 34",
    "sg:city":"Heemstede",
    "sg:orig_category":"Boekhouders",
    "sg:phone":"+31 23 528 2385",
    "sg:postcode":"2101 XJ",
    "sg:province":"Noord-Holland",
    "wof:name":"Administratie- & Adviesbureau Prins",
    "wof:placetype":"venue"
},
  "geometry": {"coordinates":[4.620509,52.352013],"type":"Point"}
}