{
  "type": "Feature",
  "properties": {
    "addr:full":"Achter De Muur 6 Groningen Groningen 9711 PR",
    "addr:housenumber":"6",
    "addr:postcode":"9711 pr",
    "addr:street":"Achter De Muur",
    "iso:country":"NL",
    "sg:address":"Achter De Muur 6",
    "sg:city":"Groningen",
    "sg:orig_category":"Beeldende Kunstenaars",
    "sg:phone":"+31 50 318 7007",
    "sg:postcode":"9711 PR",
    "sg:province":"Groningen",
    "wof:name":"Osc'Art",
    "wof:placetype":"venue"
},
  "geometry": {"coordinates":[6.571506,53.217964],"type":"Point"}
}