{
  "type": "Feature",
  "properties": {
    "iso:country":"NL",
    "sg:address":"Skagerrak 29",
    "sg:city":"Zaandam",
    "sg:orig_category":"Administratie- En Boekhoudkantoren",
    "sg:phone":"+31 75 616 5583",
    "sg:postcode":"1501 AX",
    "sg:province":"Noord-Holland",
    "wof:name":"Plekker-Van Sante, G M M",
    "wof:placetype":"venue"
},
  "geometry": {"coordinates":[4.831118,52.433685],"type":"Point"}
}