{
  "type": "Feature",
  "properties": {
    "iso:country":"NL",
    "sg:address":"Metropolestr 31",
    "sg:city":"Almere",
    "sg:orig_category":"Schoenen",
    "sg:phone":"+31 36 533 9944",
    "sg:postcode":"1315 KK",
    "sg:province":"Flevoland",
    "wof:name":"Kerkhof Bv, P W",
    "wof:placetype":"venue"
},
  "geometry": {"coordinates":[5.220251,52.374432],"type":"Point"}
}