{
  "type": "Feature",
  "properties": {
    "iso:country":"NL",
    "sg:address":"Stationsstr 16C",
    "sg:city":"Oosterwolde Fr",
    "sg:orig_category":"Schoenen - Reparaties",
    "sg:phone":"+31 516 515 951",
    "sg:postcode":"8431 EV",
    "sg:province":"Provincie Friesland",
    "wof:name":"Ypma, J",
    "wof:placetype":"venue"
},
  "geometry": {"coordinates":[6.291094,52.990379],"type":"Point"}
}