{
  "type": "Feature",
  "properties": {
    "iso:country":"NL",
    "sg:address":"Semarangstr 51A",
    "sg:city":"Groningen",
    "sg:orig_category":"Bedrijfsopleidingen",
    "sg:phone":"+31 50 577 2261",
    "sg:postcode":"9715 JV",
    "sg:province":"Groningen",
    "wof:name":"Act Two",
    "wof:placetype":"venue"
},
  "geometry": {"coordinates":[6.571152,53.233688],"type":"Point"}
}