{
  "type": "Feature",
  "properties": {
    "addr:full":"Semarangstr 51A Groningen Groningen 9715 JV",
    "addr:housenumber":"51a",
    "addr:postcode":"9715 jv",
    "addr:street":"Semarangstr",
    "iso:country":"NL",
    "sg:address":"Semarangstr 51A",
    "sg:city":"Groningen",
    "sg:orig_category":"Bedrijfsopleidingen",
    "sg:phone":"+31 50 577 2261",
    "sg:postcode":"9715 JV",
    "sg:province":"Groningen",
    "wof:name":"Act Two",
    "wof:placetype":"venue"
},
  "geometry": {"coordinates":[6.571152,53.233688],"type":"Point"}
}