{
  "type": "Feature",
  "properties": {
    "addr:full":"Voorstraat 11 Colijnsplaat Zeeland 4486 AH",
    "addr:housenumber":"11",
    "addr:postcode":"4486 ah",
    "addr:street":"Voorstraat",
    "iso:country":"NL",
    "sg:address":"Voorstraat 11",
    "sg:city":"Colijnsplaat",
    "sg:orig_category":"Elektriciens",
    "sg:phone":"+31 113 695 271",
    "sg:postcode":"4486 AH",
    "sg:province":"Zeeland",
    "wof:name":"Van Der Heijde",
    "wof:placetype":"venue"
},
  "geometry": {"coordinates":[3.847686,51.599617],"type":"Point"}
}