{
  "type": "Feature",
  "properties": {
    "addr:full":"Andromedastr 3 Ymuiden North Holland 1973 VW",
    "addr:housenumber":"3",
    "addr:postcode":"1973 vw",
    "addr:street":"Andromedastr;North",
    "iso:country":"NL",
    "sg:address":"Andromedastr 3",
    "sg:city":"Ymuiden",
    "sg:orig_category":"Logopedisten",
    "sg:phone":"+31 255 533 322",
    "sg:postcode":"1973 VW",
    "sg:province":"North Holland",
    "wof:name":"Zee- En Duijnwijk, Praktijk",
    "wof:placetype":"venue"
},
  "geometry": {"coordinates":[4.597655,52.454666],"type":"Point"}
}