{
  "type": "Feature",
  "properties": {
    "iso:country":"NL",
    "sg:address":"Plesmanwg 28",
    "sg:city":"Almelo",
    "sg:orig_category":"Keuken- Groot-Installaties",
    "sg:phone":"+31 546 873 335",
    "sg:postcode":"7602 PE",
    "sg:province":"Overijssel",
    "sg:website":"http://www.koksmaat.nl",
    "wof:name":"Koksmaat Bv, De",
    "wof:placetype":"venue"
},
  "geometry": {"coordinates":[6.639088,52.372887],"type":"Point"}
}