{
  "type": "Feature",
  "properties": {
    "addr:full":"Trommel 40 Hoogvliet Rt Zuid-Holland 3192 HK",
    "addr:housenumber":"40",
    "addr:postcode":"rt;3192 hk",
    "addr:street":"Trommel",
    "iso:country":"NL",
    "sg:address":"Trommel 40",
    "sg:city":"Hoogvliet Rt",
    "sg:orig_category":"Mensendieck - Oefentherapeuten",
    "sg:phone":"+31 10 472 2785",
    "sg:postcode":"3192 HK",
    "sg:province":"Zuid-Holland",
    "wof:name":"Boer, K Den",
    "wof:placetype":"venue"
},
  "geometry": {"coordinates":[4.368839,51.851192],"type":"Point"}
}