{
  "type": "Feature",
  "properties": {
    "addr:full":"Postbus 240 Maastricht Limburg 6200 AE",
    "addr:housenumber":"240",
    "addr:postcode":"6200 ae",
    "addr:street":"Postbus",
    "iso:country":"NL",
    "sg:address":"Postbus 240",
    "sg:city":"Maastricht",
    "sg:orig_category":"Elektronische Informatie- Systemen Off-Line",
    "sg:phone":"+31 43 388 2755",
    "sg:postcode":"6200 AE",
    "sg:province":"Limburg",
    "sg:website":"http://www.epitec.com",
    "wof:name":"Epitec",
    "wof:placetype":"venue"
},
  "geometry": {"coordinates":[5.68726,50.84985],"type":"Point"}
}