{
  "type": "Feature",
  "properties": {
    "addr:full":"Standerdmolen 8-301 Houten Utrecht 3995 AA",
    "addr:housenumber":"8-301",
    "addr:postcode":"3995 aa",
    "addr:street":"Standerdmolen",
    "iso:country":"NL",
    "sg:address":"Standerdmolen 8-301",
    "sg:city":"Houten",
    "sg:orig_category":"Adviesbureaus Bedrijfsorganisatie",
    "sg:phone":"+31 30 670 3450",
    "sg:postcode":"3995 AA",
    "sg:province":"Utrecht",
    "wof:name":"Puls",
    "wof:placetype":"venue"
},
  "geometry": {"coordinates":[5.172159,52.029762],"type":"Point"}
}