{
  "type": "Feature",
  "properties": {
    "addr:full":"Kr Mydrechtstr 110 Amsterdam Noord-Holland 1079 LD",
    "addr:housenumber":"110",
    "addr:postcode":"1079 ld",
    "iso:country":"NL",
    "sg:address":"Kr Mydrechtstr 110",
    "sg:city":"Amsterdam",
    "sg:orig_category":"Filmstudio'S En -Productie",
    "sg:phone":"+31 20 442 1760",
    "sg:postcode":"1079 LD",
    "sg:province":"Noord-Holland",
    "sg:website":"http://www.ijswater.nl",
    "wof:name":"Ijswater Bv",
    "wof:placetype":"venue"
},
  "geometry": {"coordinates":[4.912056,52.344669],"type":"Point"}
}