{
  "type": "Feature",
  "properties": {
    "addr:full":"A V Schendelln 17 Ede Gld Gelderland 6711 DA",
    "addr:housenumber":"17;6711",
    "addr:postcode":"da",
    "addr:street":"A;Schendelln;Gld Gelderland",
    "iso:country":"NL",
    "sg:address":"A V Schendelln 17",
    "sg:city":"Ede Gld",
    "sg:orig_category":"Adviesbureaus Economie",
    "sg:phone":"+31 318 612 422",
    "sg:postcode":"6711 DA",
    "sg:province":"Gelderland",
    "wof:name":"Stolp",
    "wof:placetype":"venue"
},
  "geometry": {"coordinates":[5.66767,52.044979],"type":"Point"}
}