{
  "type": "Feature",
  "properties": {
    "addr:full":"Wintersoord 12 Nijmegen Gelderland 6511 RR",
    "addr:housenumber":"12",
    "addr:postcode":"6511 rr",
    "addr:street":"Wintersoord;Gelderland",
    "iso:country":"NL",
    "sg:address":"Wintersoord 12",
    "sg:city":"Nijmegen",
    "sg:orig_category":"Kappers",
    "sg:phone":"+31 24 360 5139",
    "sg:postcode":"6511 RR",
    "sg:province":"Gelderland",
    "wof:name":"Arno'S Haarchitecten",
    "wof:placetype":"venue"
},
  "geometry": {"coordinates":[5.8681459427,51.8458824158],"type":"Point"}
}