{
  "type": "Feature",
  "properties": {
    "iso:country":"NL",
    "sg:address":"Gentsestr 32",
    "sg:city":"S Gravenhage",
    "sg:orig_category":"Hoeden",
    "sg:phone":"+31 70 355 1463",
    "sg:postcode":"2587 HT",
    "sg:province":"South Holland",
    "wof:name":"Multicolore Boutique",
    "wof:placetype":"venue"
},
  "geometry": {"coordinates":[4.29118,52.112942],"type":"Point"}
}