{
  "type": "Feature",
  "properties": {
    "addr:full":"Lupineberg 42 Roosendaal Noord-Brabant 4708 LV",
    "addr:housenumber":"42",
    "addr:postcode":"4708",
    "addr:street":"Lupineberg",
    "iso:country":"NL",
    "sg:address":"Lupineberg 42",
    "sg:city":"Roosendaal",
    "sg:orig_category":"Werving En Selectie",
    "sg:phone":"+31 165 542 510",
    "sg:postcode":"4708 LV",
    "sg:province":"Noord-Brabant",
    "wof:name":"Psychopers",
    "wof:placetype":"venue"
},
  "geometry": {"coordinates":[-94.82066345210001,40.0440406799],"type":"Point"}
}