{
  "type": "Feature",
  "properties": {
    "iso:country":"NL",
    "sg:address":"Bremwg 1",
    "sg:city":"Zuidlaren",
    "sg:orig_category":"Keukens",
    "sg:phone":"+31 50 409 0201",
    "sg:postcode":"9471 SJ",
    "sg:province":"Drenthe",
    "wof:name":"Buist, Jeroen",
    "wof:placetype":"venue"
},
  "geometry": {"coordinates":[6.666267,53.083138],"type":"Point"}
}