{
  "type": "Feature",
  "properties": {
    "addr:full":"Kwelderwg 6 Eemshaven Groningen 9979 XN",
    "addr:housenumber":"6",
    "addr:postcode":"9979 xn",
    "addr:street":"Kwelderwg",
    "iso:country":"NL",
    "sg:address":"Kwelderwg 6",
    "sg:city":"Eemshaven",
    "sg:orig_category":"Cafetaria'S",
    "sg:phone":"+31 596 516 405",
    "sg:postcode":"9979 XN",
    "sg:province":"Groningen",
    "wof:name":"Molenzicht Petit/Rest, Het",
    "wof:placetype":"venue"
},
  "geometry": {"coordinates":[6.807665,53.443939],"type":"Point"}
}