{
  "type": "Feature",
  "properties": {
    "addr:full":"Laanenderwg 57 Alkmaar North Holland 1812 PW",
    "addr:housenumber":"57",
    "addr:postcode":"1812 pw",
    "addr:street":"Laanenderwg",
    "iso:country":"NL",
    "sg:address":"Laanenderwg 57",
    "sg:city":"Alkmaar",
    "sg:orig_category":"Directmail",
    "sg:phone":"+31 72 540 8760",
    "sg:postcode":"1812 PW",
    "sg:province":"North Holland",
    "wof:name":"Favourite Mail Bv",
    "wof:placetype":"venue"
},
  "geometry": {"coordinates":[4.764786,52.610855],"type":"Point"}
}