{
  "type": "Feature",
  "properties": {
    "addr:full":"De Wissel 14 Lelystad Flevoland 8232  D",
    "addr:housenumber":"14;8232 d",
    "addr:street":"De Wissel;Flevoland",
    "iso:country":"NL",
    "sg:address":"De Wissel 14",
    "sg:city":"Lelystad",
    "sg:orig_category":"Boekenuitgeverijen",
    "sg:phone":"+31 320 243 004",
    "sg:postcode":"8232  D",
    "sg:province":"Flevoland",
    "wof:name":"Bruna",
    "wof:placetype":"venue"
},
  "geometry": {"coordinates":[5.475977,52.509491],"type":"Point"}
}