{
  "type": "Feature",
  "properties": {
    "addr:full":"Toereppel 13 Enkhuizen North Holland 1602 KG",
    "addr:housenumber":"13",
    "addr:postcode":"1602 kg",
    "addr:street":"Toereppel",
    "iso:country":"NL",
    "sg:address":"Toereppel 13",
    "sg:city":"Enkhuizen",
    "sg:orig_category":"Autorijscholen",
    "sg:phone":"+31 228 317 697",
    "sg:postcode":"1602 KG",
    "sg:province":"North Holland",
    "wof:name":"Goedkoop",
    "wof:placetype":"venue"
},
  "geometry": {"coordinates":[5.268714,52.712311],"type":"Point"}
}