{
  "type": "Feature",
  "properties": {
    "iso:country":"NL",
    "sg:address":"Eindenhoutstr 10",
    "sg:city":"Haarlem",
    "sg:orig_category":"Psychologen",
    "sg:phone":"+31 6 26086520",
    "sg:postcode":"2012 ML",
    "sg:province":"North Holland",
    "wof:name":"Woudenberg, M B Van",
    "wof:placetype":"venue"
},
  "geometry": {"coordinates":[4.619881,52.36758],"type":"Point"}
}