{
  "type": "Feature",
  "properties": {
    "iso:country":"NL",
    "sg:address":"Madurastr 32",
    "sg:city":"Amsterdam",
    "sg:orig_category":"Fotoreportages",
    "sg:phone":"+31 6 52025680",
    "sg:postcode":"1094 GN",
    "sg:province":"North Holland",
    "sg:website":"http://www.hirez.nl",
    "wof:name":"Hirez",
    "wof:placetype":"venue"
},
  "geometry": {"coordinates":[4.933096,52.364101],"type":"Point"}
}