{
  "type": "Feature",
  "properties": {
    "addr:full":"Madurastr 32 Amsterdam North Holland 1094 GN",
    "addr:housenumber":"32",
    "addr:postcode":"1094 gn",
    "addr:street":"Madurastr",
    "iso:country":"NL",
    "sg:address":"Madurastr 32",
    "sg:city":"Amsterdam",
    "sg:orig_category":"Fotoreportages",
    "sg:phone":"+31 6 52025680",
    "sg:postcode":"1094 GN",
    "sg:province":"North Holland",
    "sg:website":"http://www.hirez.nl",
    "wof:name":"Hirez",
    "wof:placetype":"venue"
},
  "geometry": {"coordinates":[4.933096,52.364101],"type":"Point"}
}