{
  "type": "Feature",
  "properties": {
    "addr:full":"W V Hallhof 14 Soest Utrecht 3762 XP",
    "addr:housenumber":"14",
    "addr:postcode":"3762 xp",
    "addr:street":"W V Hallhof",
    "iso:country":"NL",
    "sg:address":"W V Hallhof 14",
    "sg:city":"Soest",
    "sg:orig_category":"Beeldende Kunstenaars",
    "sg:phone":"+31 35 601 6305",
    "sg:postcode":"3762 XP",
    "sg:province":"Utrecht",
    "wof:name":"Gor, J",
    "wof:placetype":"venue"
},
  "geometry": {"coordinates":[5.300385,52.184044],"type":"Point"}
}