{
  "type": "Feature",
  "properties": {
    "iso:country":"NL",
    "sg:address":"Hoge Naarderweg 42",
    "sg:city":"Hilversum",
    "sg:orig_category":"Accountants - Administratie- Consulenten En -Kantoren",
    "sg:phone":"+31 35 623 7355",
    "sg:postcode":"1217 AG",
    "sg:province":"Noord-Holland",
    "wof:name":"K & S",
    "wof:placetype":"venue"
},
  "geometry": {"coordinates":[5.168037,52.231102],"type":"Point"}
}