{
  "type": "Feature",
  "properties": {
    "addr:full":"Backenhagenln 76 Hengelo Ov NL.08 7557 KE",
    "addr:housenumber":"76",
    "addr:postcode":"7557 ke",
    "addr:street":"Backenhagenln;Ov",
    "iso:country":"NL",
    "sg:address":"Backenhagenln 76",
    "sg:city":"Hengelo Ov",
    "sg:orig_category":"Ziekenhuizen, Sanatoria, Verpleeghuizen",
    "sg:phone":"+31 74 250 6435",
    "sg:postcode":"7557 KE",
    "sg:province":"NL.08",
    "wof:name":"Herinckhave",
    "wof:placetype":"venue"
},
  "geometry": {"coordinates":[6.78971,52.266331],"type":"Point"}
}