{
  "type": "Feature",
  "properties": {
    "iso:country":"NL",
    "sg:address":"Gedempte Appelhaven 13",
    "sg:city":"Hoorn Nh",
    "sg:orig_category":"Pleziervaartuigen And Reparatie",
    "sg:phone":"+31 229 215 834",
    "sg:postcode":"1621 BL",
    "sg:province":"North Holland",
    "wof:name":"J. Roorda",
    "wof:placetype":"venue"
},
  "geometry": {"coordinates":[5.063602,52.639347],"type":"Point"}
}