{
  "type": "Feature",
  "properties": {
    "addr:full":"Industriewg 23 Zoetermeer South Holland 2712 LA",
    "addr:housenumber":"23",
    "addr:postcode":"2712 la",
    "addr:street":"Industriewg",
    "iso:country":"NL",
    "sg:address":"Industriewg 23",
    "sg:city":"Zoetermeer",
    "sg:orig_category":"Elektrotechnische Artikelen",
    "sg:phone":"+31 79 341 6641",
    "sg:postcode":"2712 LA",
    "sg:province":"South Holland",
    "wof:name":"Elt\u00e9ma Bv",
    "wof:placetype":"venue"
},
  "geometry": {"coordinates":[4.510688,52.047153],"type":"Point"}
}