{
  "type": "Feature",
  "properties": {
    "addr:full":"Sterrenln 38 Hoogeveen Provincie Drenthe 7904 LL",
    "addr:housenumber":"38",
    "addr:postcode":"7904 ll",
    "addr:street":"Sterrenln;Provincie",
    "iso:country":"NL",
    "sg:address":"Sterrenln 38",
    "sg:city":"Hoogeveen",
    "sg:orig_category":"Zonweringen",
    "sg:phone":"+31 528 276 317",
    "sg:postcode":"7904 LL",
    "sg:province":"Provincie Drenthe",
    "wof:name":"Zmr",
    "wof:placetype":"venue"
},
  "geometry": {"coordinates":[6.507553,52.725399],"type":"Point"}
}