{
  "type": "Feature",
  "properties": {
    "iso:country":"NL",
    "sg:address":"Bontwerkersdreef 34",
    "sg:city":"Maastricht",
    "sg:orig_category":"Glas, Porselein En Aardewerk",
    "sg:phone":"+31 43 347 5609",
    "sg:postcode":"6216 SH",
    "sg:province":"Limburg",
    "wof:name":"Hees-Smits, P Th Van",
    "wof:placetype":"venue"
},
  "geometry": {"coordinates":[5.657407,50.847843],"type":"Point"}
}