{
  "type": "Feature",
  "properties": {
    "addr:full":"Koestr 2 Liempde North Brabant 5298 AR",
    "addr:housenumber":"2",
    "addr:postcode":"5298",
    "addr:street":"Koestr",
    "iso:country":"NL",
    "sg:address":"Koestr 2",
    "sg:city":"Liempde",
    "sg:orig_category":"Kabels",
    "sg:phone":"+31 411 631 115",
    "sg:postcode":"5298 AR",
    "sg:province":"North Brabant",
    "sg:website":"http://www.fiberpartners.nl",
    "wof:name":"Fiber Partners",
    "wof:placetype":"venue"
},
  "geometry": {"coordinates":[5.3750429153,51.5650749207],"type":"Point"}
}