{
  "type": "Feature",
  "properties": {
    "addr:full":"Nieuwstr 4 Oirschot North Brabant 5688 BE",
    "addr:housenumber":"4",
    "addr:postcode":"5688",
    "addr:street":"Nieuwstr",
    "iso:country":"NL",
    "sg:address":"Nieuwstr 4",
    "sg:city":"Oirschot",
    "sg:orig_category":"Verzekeringen - Verzekeringskantoren",
    "sg:phone":"+31 499 572 706",
    "sg:postcode":"5688 BE",
    "sg:province":"North Brabant",
    "wof:name":"Ven, Van De",
    "wof:placetype":"venue"
},
  "geometry": {"coordinates":[5.30584,51.503902],"type":"Point"}
}