{
  "type": "Feature",
  "properties": {
    "addr:full":"Bremstr 8 Halsteren Noord-Brabant 4661 WH",
    "addr:housenumber":"8",
    "addr:postcode":"4661 wh",
    "addr:street":"Bremstr",
    "iso:country":"NL",
    "sg:address":"Bremstr 8",
    "sg:city":"Halsteren",
    "sg:orig_category":"Verhuur",
    "sg:phone":"+31 164 684 534",
    "sg:postcode":"4661 WH",
    "sg:province":"Noord-Brabant",
    "wof:name":"Koenraadt Bv",
    "wof:placetype":"venue"
},
  "geometry": {"coordinates":[4.28498,51.530651],"type":"Point"}
}