{
  "type": "Feature",
  "properties": {
    "addr:full":"Wilhelminalaan 1 Sas Van Gent Zeeland 4551 EP",
    "addr:housenumber":"1",
    "addr:postcode":"4551 ep",
    "addr:street":"Wilhelminalaan",
    "iso:country":"NL",
    "sg:address":"Wilhelminalaan 1",
    "sg:city":"Sas Van Gent",
    "sg:orig_category":"Bibliotheken And Openbare Archieven",
    "sg:phone":"+31 115 451 239",
    "sg:postcode":"4551 EP",
    "sg:province":"Zeeland",
    "wof:name":"Openbare Bibliotheken",
    "wof:placetype":"venue"
},
  "geometry": {"coordinates":[3.799612,51.226528],"type":"Point"}
}