{
  "type": "Feature",
  "properties": {
    "addr:full":"Ln V D H Meesters 8 Amstelveen Noord-Holland 1186 AM",
    "addr:housenumber":"8",
    "addr:postcode":"1186",
    "addr:street":"Ln V D H Meesters",
    "iso:country":"NL",
    "sg:address":"Ln V D H Meesters 8",
    "sg:city":"Amstelveen",
    "sg:orig_category":"Ziekenhuizen, Sanatoria, Verpleeghuizen",
    "sg:phone":"+31 20 347 4747",
    "sg:postcode":"1186 AM",
    "sg:province":"Noord-Holland",
    "wof:name":"Ziekenhuis Amstelveen",
    "wof:placetype":"venue"
},
  "geometry": {"coordinates":[4.856945,52.303444],"type":"Point"}
}