{
  "type": "Feature",
  "properties": {
    "iso:country":"NL",
    "sg:address":"Korenstraat 5",
    "sg:city":"Valkenswaard",
    "sg:orig_category":"Bloemen And Planten",
    "sg:phone":"+31 40 204 0949",
    "sg:postcode":"5554 JS",
    "sg:province":"Noord-Brabant",
    "wof:name":"De Hakketak",
    "wof:placetype":"venue"
},
  "geometry": {"coordinates":[5.456616,51.346203],"type":"Point"}
}