{
  "type": "Feature",
  "properties": {
    "iso:country":"NL",
    "sg:address":"Looiersplantsoen 12",
    "sg:city":"Diepenheim",
    "sg:orig_category":"Artsen And Specialisten",
    "sg:phone":"+31 547 351 234",
    "sg:postcode":"7478 AR",
    "sg:province":"Overijssel",
    "wof:name":"J.A.C. Van Oosterbosch Huisartsenpraktij",
    "wof:placetype":"venue"
},
  "geometry": {"coordinates":[6.554878,52.200073],"type":"Point"}
}