{
  "type": "Feature",
  "properties": {
    "addr:full":"Middellandse Zee 51 Zaandam North Holland 1503 BZ",
    "addr:housenumber":"51",
    "addr:postcode":"1503 bz",
    "addr:street":"Middellandse Zee",
    "iso:country":"NL",
    "sg:address":"Middellandse Zee 51",
    "sg:city":"Zaandam",
    "sg:orig_category":"Kinderopvang",
    "sg:phone":"+31 75 612 2095",
    "sg:postcode":"1503 BZ",
    "sg:province":"North Holland",
    "sg:website":"http://www.maximummultidiensten.nl/kind",
    "wof:name":"Davidka",
    "wof:placetype":"venue"
},
  "geometry": {"coordinates":[4.845806,52.447224],"type":"Point"}
}