{
  "type": "Feature",
  "properties": {
    "addr:full":"Rederykerstr 139 S Gravenhage South Holland 2531 VJ",
    "addr:housenumber":"139",
    "addr:postcode":"2531 vj",
    "addr:street":"S Gravenhage",
    "iso:country":"NL",
    "sg:address":"Rederykerstr 139",
    "sg:city":"S Gravenhage",
    "sg:orig_category":"Elektrotechnische Artikelen",
    "sg:phone":"+31 70 330 0835",
    "sg:postcode":"2531 VJ",
    "sg:province":"South Holland",
    "wof:name":"Windfall",
    "wof:placetype":"venue"
},
  "geometry": {"coordinates":[4.30122,52.052898],"type":"Point"}
}