{
  "type": "Feature",
  "properties": {
    "addr:full":"Jacob Marisstraat 114 Amsterdam Noord-Holland 1058 JB",
    "addr:housenumber":"114",
    "addr:postcode":"1058 jb",
    "addr:street":"Jacob Marisstraat",
    "iso:country":"NL",
    "sg:address":"Jacob Marisstraat 114",
    "sg:city":"Amsterdam",
    "sg:orig_category":"Bedrijfs- And Managementsconsultants",
    "sg:phone":"+31 20 408 0421",
    "sg:postcode":"1058 JB",
    "sg:province":"Noord-Holland",
    "wof:name":"A.J.M. Reichling",
    "wof:placetype":"venue"
},
  "geometry": {"coordinates":[4.852418,52.356983],"type":"Point"}
}