{
  "type": "Feature",
  "properties": {
    "iso:country":"NL",
    "sg:address":"Nieuweweg 78",
    "sg:city":"Wijchen",
    "sg:orig_category":"Goederenvervoer Over De Weg",
    "sg:phone":"+31 24 645 1700",
    "sg:postcode":"6603 BR",
    "sg:province":"Gelderland",
    "wof:name":"Netwerk Int. Transport & Logistiek Vof",
    "wof:placetype":"venue"
},
  "geometry": {"coordinates":[5.744887,51.811298],"type":"Point"}
}