{
  "type": "Feature",
  "properties": {
    "iso:country":"NL",
    "sg:address":"Borchgraven 6",
    "sg:city":"Varsseveld",
    "sg:orig_category":"Werving And Selectie Van Tijdelijk Personeel And Uitzendkantoren",
    "sg:phone":"+31 315 248 888",
    "sg:postcode":"7051 CW",
    "sg:province":"Gelderland",
    "wof:name":"Randstad Uitzendbureau",
    "wof:placetype":"venue"
},
  "geometry": {"coordinates":[6.4622130394,51.9438896179],"type":"Point"}
}