{
  "type": "Feature",
  "properties": {
    "iso:country":"NL",
    "sg:address":"Rijckholterf 7",
    "sg:city":"Rotterdam",
    "sg:orig_category":"Gespecialiseerde Bouw",
    "sg:phone":"+31 10 483 5461",
    "sg:postcode":"3077 JN",
    "sg:province":"South Holland",
    "wof:name":"Duba Vof",
    "wof:placetype":"venue"
},
  "geometry": {"coordinates":[4.569761,51.895199],"type":"Point"}
}