{
  "type": "Feature",
  "properties": {
    "iso:country":"NL",
    "sg:address":"Munnikenakker 14",
    "sg:city":"Mierlo",
    "sg:orig_category":"Bibliotheken And Openbare Archieven",
    "sg:phone":"+31 492 662 246",
    "sg:postcode":"5731 EC",
    "sg:province":"Noord-Brabant",
    "wof:name":"Bibliotheek Faso",
    "wof:placetype":"venue"
},
  "geometry": {"coordinates":[5.616829,51.437553],"type":"Point"}
}