{
  "type": "Feature",
  "properties": {
    "addr:full":"Chevalleraustraat 2 Ommen NL.08 7731 EE",
    "addr:housenumber":"2;nl.08",
    "addr:postcode":"7731 ee",
    "addr:street":"Chevalleraustraat",
    "iso:country":"NL",
    "sg:address":"Chevalleraustraat 2",
    "sg:city":"Ommen",
    "sg:orig_category":"Overheidsdiensten",
    "sg:phone":"+31 529 459 100",
    "sg:postcode":"7731 EE",
    "sg:province":"NL.08",
    "wof:name":"Gemeente Ommen",
    "wof:placetype":"venue"
},
  "geometry": {"coordinates":[6.4232521057,52.5259628296],"type":"Point"}
}