{
  "type": "Feature",
  "properties": {
    "addr:full":"Sarphatistr 660 Amsterdam Noord-Holland 1018 AV",
    "addr:housenumber":"660",
    "addr:postcode":"1018 av",
    "iso:country":"NL",
    "sg:address":"Sarphatistr 660",
    "sg:city":"Amsterdam",
    "sg:orig_category":"Loopbaanbegeleiding",
    "sg:phone":"+31 20 620 8881",
    "sg:postcode":"1018 AV",
    "sg:province":"Noord-Holland",
    "sg:website":"http://www.bcr.nl",
    "wof:name":"Bcr",
    "wof:placetype":"venue"
},
  "geometry": {"coordinates":[4.923897,52.366394],"type":"Point"}
}