{
  "type": "Feature",
  "properties": {
    "iso:country":"NL",
    "sg:address":"J J Allanstr 53",
    "sg:city":"Westzaan",
    "sg:orig_category":"Wijnkoperijen En -Groothandel",
    "sg:phone":"+31 75 612 2811",
    "sg:postcode":"1551 RA",
    "sg:province":"North Holland",
    "sg:website":"http://www.ribouvin.nl",
    "wof:name":"Ribouvin Wijnkoperij",
    "wof:placetype":"venue"
},
  "geometry": {"coordinates":[4.7762150764,52.4482879639],"type":"Point"}
}