{
  "type": "Feature",
  "properties": {
    "iso:country":"NL",
    "sg:address":"Pr Bernhardstr 79",
    "sg:city":"Silvolde",
    "sg:orig_category":"Wasmachines En Wasdrogers - Onderhoud En Reparatie",
    "sg:phone":"+31 315 328 030",
    "sg:postcode":"7064 GE",
    "sg:province":"Gelderland",
    "wof:name":"Bergervoet",
    "wof:placetype":"venue"
},
  "geometry": {"coordinates":[6.3913178444,51.9112815857],"type":"Point"}
}