{
  "type": "Feature",
  "properties": {
    "iso:country":"NL",
    "sg:address":"Lopikerwg W 28A",
    "sg:city":"Lopik",
    "sg:orig_category":"Houtgroothandel Hardhout",
    "sg:phone":"+31 348 551 249",
    "sg:postcode":"3411 AM",
    "sg:province":"Utrecht",
    "wof:name":"Haar, Hout En Transport V/D",
    "wof:placetype":"venue"
},
  "geometry": {"coordinates":[4.93079,51.976078],"type":"Point"}
}