{
  "type": "Feature",
  "properties": {
    "addr:full":"Pernestraat 20 Castricum Noord-Holland 1901 AX",
    "addr:housenumber":"20",
    "addr:postcode":"1901 ax",
    "addr:street":"Pernestraat",
    "iso:country":"NL",
    "sg:address":"Pernestraat 20",
    "sg:city":"Castricum",
    "sg:orig_category":"Huishoudapparatuur, Televisies And Radio'S",
    "sg:phone":"+31 251 652 698",
    "sg:postcode":"1901 AX",
    "sg:province":"Noord-Holland",
    "wof:name":"Molenaar Geluids Installaties (M.G.I.)",
    "wof:placetype":"venue"
},
  "geometry": {"coordinates":[4.660215,52.548119],"type":"Point"}
}