{
  "type": "Feature",
  "properties": {
    "addr:full":"Lijster 13 Sprang-Capelle North Brabant 5161 SR",
    "addr:housenumber":"13",
    "addr:postcode":"5161 sr",
    "addr:street":"Lijster",
    "iso:country":"NL",
    "sg:address":"Lijster 13",
    "sg:city":"Sprang-Capelle",
    "sg:orig_category":"Boekhouders",
    "sg:phone":"+31 416 540 695",
    "sg:postcode":"5161 SR",
    "sg:province":"North Brabant",
    "wof:name":"Majoto Vof",
    "wof:placetype":"venue"
},
  "geometry": {"coordinates":[5.01996,51.675903],"type":"Point"}
}