{
  "type": "Feature",
  "properties": {
    "addr:full":"Egge 8 Poortugaal Zuid-Holland 3171 DE",
    "addr:housenumber":"8",
    "addr:postcode":"3171 de",
    "addr:street":"Egge",
    "iso:country":"NL",
    "sg:address":"Egge 8",
    "sg:city":"Poortugaal",
    "sg:orig_category":"Wegen And Sportterreinen",
    "sg:phone":"+31 10 416 8680",
    "sg:postcode":"3171 DE",
    "sg:province":"Zuid-Holland",
    "wof:name":"C. Noordijk Pernis Bv",
    "wof:placetype":"venue"
},
  "geometry": {"coordinates":[4.401447773,51.8575553894],"type":"Point"}
}