{
  "type": "Feature",
  "properties": {
    "addr:full":"Hoofdstr 146 Driebergen Rysenb Utrecht 3972 LE",
    "addr:housenumber":"146",
    "addr:postcode":"3972 le",
    "addr:street":"Driebergen Rysenb",
    "iso:country":"NL",
    "sg:address":"Hoofdstr 146",
    "sg:city":"Driebergen Rysenb",
    "sg:orig_category":"Postkantoren",
    "sg:phone":"+31 343 517 641",
    "sg:postcode":"3972 LE",
    "sg:province":"Utrecht",
    "sg:website":"http://www.postkantoor.nl",
    "wof:name":"Postkantoor",
    "wof:placetype":"venue"
},
  "geometry": {"coordinates":[5.278507,52.054062],"type":"Point"}
}