{
  "type": "Feature",
  "properties": {
    "addr:full":"Wielingenln 2 Terneuzen Zeeland 4535 PA",
    "addr:housenumber":"2",
    "addr:postcode":"4535",
    "addr:street":"Wielingenln",
    "iso:country":"NL",
    "sg:address":"Wielingenln 2",
    "sg:city":"Terneuzen",
    "sg:orig_category":"Orthopedische Artikelen",
    "sg:phone":"+31 115 688 586",
    "sg:postcode":"4535 PA",
    "sg:province":"Zeeland",
    "wof:name":"Jacqueline Karmelk",
    "wof:placetype":"venue"
},
  "geometry": {"coordinates":[3.8275589943,51.3381462097],"type":"Point"}
}