{
  "type": "Feature",
  "properties": {
    "iso:country":"NL",
    "sg:address":"Drieboomln 129",
    "sg:city":"Hoorn Nh",
    "sg:orig_category":"Verzekeringen - Verzekeringskantoren",
    "sg:phone":"+31 229 210 679",
    "sg:postcode":"1624 BD",
    "sg:province":"North Holland",
    "wof:name":"Secar",
    "wof:placetype":"venue"
},
  "geometry": {"coordinates":[5.06369,52.647102],"type":"Point"}
}