{
  "type": "Feature",
  "properties": {
    "iso:country":"NL",
    "sg:address":"Jasmynstr 35",
    "sg:city":"Utrecht",
    "sg:orig_category":"Adviesbureaus Bouwkunde",
    "sg:phone":"+31 6 13632167",
    "sg:postcode":"3551 SP",
    "sg:province":"Utrecht",
    "sg:website":"http://www.jspinternational.com",
    "wof:name":"Jim Schlepers",
    "wof:placetype":"venue"
},
  "geometry": {"coordinates":[5.100032,52.099586],"type":"Point"}
}