{
  "type": "Feature",
  "properties": {
    "addr:full":"Professor Rommehoek 6 Oosterhout Nb Noord-Brabant 4908 CD",
    "addr:housenumber":"6",
    "addr:postcode":"4908 cd",
    "addr:street":"Professor Rommehoek",
    "iso:country":"NL",
    "sg:address":"Professor Rommehoek 6",
    "sg:city":"Oosterhout Nb",
    "sg:orig_category":"Binnenhuisarchitecten",
    "sg:phone":"+31 162 425 800",
    "sg:postcode":"4908 CD",
    "sg:province":"Noord-Brabant",
    "wof:name":"Ontwerp En Adviesburo De Kind",
    "wof:placetype":"venue"
},
  "geometry": {"coordinates":[4.866584,51.664734],"type":"Point"}
}