{
  "type": "Feature",
  "properties": {
    "addr:full":"Snelliusln 26 Hilversum Noord-Holland 1222 TE",
    "addr:housenumber":"26",
    "addr:postcode":"1222 te",
    "addr:street":"Snelliusln",
    "iso:country":"NL",
    "sg:address":"Snelliusln 26",
    "sg:city":"Hilversum",
    "sg:orig_category":"Tuinontwerp En -Advies",
    "sg:phone":"+31 35 640 9030",
    "sg:postcode":"1222 TE",
    "sg:province":"Noord-Holland",
    "wof:name":"Athmer, Anneke",
    "wof:placetype":"venue"
},
  "geometry": {"coordinates":[5.18488,52.2495],"type":"Point"}
}