{
  "type": "Feature",
  "properties": {
    "addr:full":"Kl Tocht 33 Zaandam Noord-Holland 1507 CA",
    "addr:housenumber":"33",
    "addr:postcode":"1507 ca",
    "addr:street":"Tocht",
    "iso:country":"NL",
    "sg:address":"Kl Tocht 33",
    "sg:city":"Zaandam",
    "sg:orig_category":"Drukkerijen",
    "sg:phone":"+31 75 635 1206",
    "sg:postcode":"1507 CA",
    "sg:province":"Noord-Holland",
    "wof:name":"Prestess Print",
    "wof:placetype":"venue"
},
  "geometry": {"coordinates":[4.808836,52.430649],"type":"Point"}
}