{
  "type": "Feature",
  "properties": {
    "addr:full":"Assendorperstr 97 Zwolle NL.08 8012 DH",
    "addr:housenumber":"97",
    "addr:postcode":"8012 dh",
    "addr:street":"Assendorperstr",
    "iso:country":"NL",
    "sg:address":"Assendorperstr 97",
    "sg:city":"Zwolle",
    "sg:orig_category":"Kinderkleding",
    "sg:phone":"+31 38 423 4088",
    "sg:postcode":"8012 DH",
    "sg:province":"NL.08",
    "wof:name":"Flash",
    "wof:placetype":"venue"
},
  "geometry": {"coordinates":[6.102374,52.505638],"type":"Point"}
}