{
  "type": "Feature",
  "properties": {
    "addr:full":"Vinkenln 3 Baarle Nassau Noord-Brabant 5111 DK",
    "addr:housenumber":"3",
    "addr:postcode":"5111 dk",
    "addr:street":"Vinkenln",
    "iso:country":"NL",
    "sg:address":"Vinkenln 3",
    "sg:city":"Baarle Nassau",
    "sg:orig_category":"Verzekeringen - Verzekeringskantoren",
    "sg:phone":"+31 13 507 7601",
    "sg:postcode":"5111 DK",
    "sg:province":"Noord-Brabant",
    "wof:name":"Gillis, Guus",
    "wof:placetype":"venue"
},
  "geometry": {"coordinates":[4.926252,51.448341],"type":"Point"}
}