{
  "type": "Feature",
  "properties": {
    "iso:country":"NL",
    "sg:address":"Walhoven 76",
    "sg:city":"Zevenbergen",
    "sg:orig_category":"Organisatiebureaus",
    "sg:phone":"+31 168 325 487",
    "sg:postcode":"4761 MV",
    "sg:province":"Noord-Brabant",
    "wof:name":"Jonker",
    "wof:placetype":"venue"
},
  "geometry": {"coordinates":[4.5877242088,51.6445579529],"type":"Point"}
}