{
  "type": "Feature",
  "properties": {
    "iso:country":"NL",
    "sg:address":"Kaiserstraat 18",
    "sg:city":"Leiden",
    "sg:orig_category":"Vertaal- And Tolkenbureaus",
    "sg:phone":"+31 71 512 2860",
    "sg:postcode":"2311 GR",
    "sg:province":"Zuid-Holland",
    "wof:name":"Akebono Translation Service",
    "wof:placetype":"venue"
},
  "geometry": {"coordinates":[4.486365,52.155849],"type":"Point"}
}