{
  "type": "Feature",
  "properties": {
    "addr:full":"Aelbrechtskolk 45B Rotterdam South Holland 3025 HB",
    "addr:housenumber":"45b",
    "addr:postcode":"3025 hb",
    "addr:street":"Aelbrechtskolk",
    "iso:country":"NL",
    "sg:address":"Aelbrechtskolk 45B",
    "sg:city":"Rotterdam",
    "sg:orig_category":"Grafisch Ontwerpers",
    "sg:phone":"+31 10 476 7810",
    "sg:postcode":"3025 HB",
    "sg:province":"South Holland",
    "sg:website":"http://www.Quin's.nl",
    "wof:name":"Quin'S",
    "wof:placetype":"venue"
},
  "geometry": {"coordinates":[4.447985,51.90871],"type":"Point"}
}