{
  "type": "Feature",
  "properties": {
    "addr:full":"Speelkamp 28 Leusden Utrecht 3831 PE",
    "addr:housenumber":"28",
    "addr:postcode":"3831 pe",
    "addr:street":"Speelkamp",
    "iso:country":"NL",
    "sg:address":"Speelkamp 28",
    "sg:city":"Leusden",
    "sg:orig_category":"Verenigingen En Stichtingen",
    "sg:phone":"+31 33 434 1212",
    "sg:postcode":"3831 PE",
    "sg:province":"Utrecht",
    "sg:website":"http://www.astmafonds.nl",
    "wof:name":"Astma Fonds",
    "wof:placetype":"venue"
},
  "geometry": {"coordinates":[5.427587,52.142132],"type":"Point"}
}