{
  "type": "Feature",
  "properties": {
    "addr:full":"Ysselveld 23 Montfoort Utrecht 3417 XH",
    "addr:housenumber":"23",
    "addr:postcode":"3417 xh",
    "addr:street":"Ysselveld",
    "iso:country":"NL",
    "sg:address":"Ysselveld 23",
    "sg:city":"Montfoort",
    "sg:classifiers":[
        {
            "category":"Home & Garden",
            "subcategory":"Garden Supply",
            "type":"Retail Goods"
        }
    ],
    "sg:phone":"+31 348 474 553",
    "sg:postcode":"3417 XH",
    "sg:province":"Utrecht",
    "sg:tags":[
        "zand",
        "en",
        "grind"
    ],
    "wof:name":"Dirk Stigter Grondwerken",
    "wof:placetype":"venue"
},
  "geometry": {"coordinates":[4.94618,52.04567],"type":"Point"}
}