{
  "type": "Feature",
  "properties": {
    "addr:full":"Burgemeester Leenstraat 1 Lochem Gelderland 7242 AA",
    "addr:housenumber":"1",
    "addr:postcode":"7242 aa",
    "addr:street":"Burgemeester Leenstraat;Gelderland",
    "iso:country":"NL",
    "sg:address":"Burgemeester Leenstraat 1",
    "sg:city":"Lochem",
    "sg:classifiers":[
        {
            "category":"Fast Food",
            "type":"Food & Drink"
        }
    ],
    "sg:phone":"+31 573 256 778",
    "sg:postcode":"7242 AA",
    "sg:province":"Gelderland",
    "sg:tags":[
        "afhaal",
        "restaurant"
    ],
    "wof:name":"Snackwagenverhuur Lochem",
    "wof:placetype":"venue"
},
  "geometry": {"coordinates":[6.413483,52.160206],"type":"Point"}
}