{
  "type": "Feature",
  "properties": {
    "iso:country":"NL",
    "sg:address":"Bergstr 73",
    "sg:city":"Leerdam",
    "sg:orig_category":"Kappers",
    "sg:phone":"+31 345 616 100",
    "sg:postcode":"4141 BT",
    "sg:province":"South Holland",
    "wof:name":"Trendy Hair",
    "wof:placetype":"venue"
},
  "geometry": {"coordinates":[5.090944,51.891506],"type":"Point"}
}