{
  "type": "Feature",
  "properties": {
    "addr:full":"Mauritslaan 33 Geleen Limburg 6161 HP",
    "addr:housenumber":"33",
    "addr:postcode":"6161 hp",
    "addr:street":"Mauritslaan",
    "iso:country":"NL",
    "sg:address":"Mauritslaan 33",
    "sg:city":"Geleen",
    "sg:orig_category":"Diverse Consumentenartikelen Gh",
    "sg:phone":"+31 46 475 8080",
    "sg:postcode":"6161 HP",
    "sg:province":"Limburg",
    "wof:name":"Totalfeed Bv",
    "wof:placetype":"venue"
},
  "geometry": {"coordinates":[5.824134,50.968864],"type":"Point"}
}