{
  "type": "Feature",
  "properties": {
    "addr:full":"B V Moerdregtpad 2 Moordrecht Zuid-Holland 2841 SR",
    "addr:housenumber":"2",
    "addr:postcode":"2841 sr",
    "addr:street":"V Moerdregtpad",
    "iso:country":"NL",
    "sg:address":"B V Moerdregtpad 2",
    "sg:city":"Moordrecht",
    "sg:orig_category":"Vertalers",
    "sg:phone":"+31 182 378 502",
    "sg:postcode":"2841 SR",
    "sg:province":"Zuid-Holland",
    "wof:name":"Hora",
    "wof:placetype":"venue"
},
  "geometry": {"coordinates":[4.667987,51.987827],"type":"Point"}
}