{
  "type": "Feature",
  "properties": {
    "addr:full":"Bramenberg 26 Eemnes Utrecht 3755 BZ",
    "addr:housenumber":"26",
    "addr:postcode":"3755 bz",
    "addr:street":"Bramenberg",
    "iso:country":"NL",
    "sg:address":"Bramenberg 26",
    "sg:city":"Eemnes",
    "sg:orig_category":"Vertaalbureaus",
    "sg:phone":"+31 35 531 5516",
    "sg:postcode":"3755 BZ",
    "sg:province":"Utrecht",
    "wof:name":"Reintaal",
    "wof:placetype":"venue"
},
  "geometry": {"coordinates":[5.249822,52.247776],"type":"Point"}
}