{
  "type": "Feature",
  "properties": {
    "addr:full":"Markt 10 Asten Noord-Brabant 5721 GE",
    "addr:housenumber":"10",
    "addr:postcode":"5721",
    "addr:street":"Markt",
    "iso:country":"NL",
    "sg:address":"Markt 10",
    "sg:city":"Asten",
    "sg:classifiers":[
        {
            "category":"Food & Beverages",
            "subcategory":"Bakery",
            "type":"Retail Goods"
        }
    ],
    "sg:phone":"+31 493 696 044",
    "sg:postcode":"5721 GE",
    "sg:province":"Noord-Brabant",
    "sg:tags":[
        "brood",
        "en",
        "banket"
    ],
    "wof:name":"Broekmans",
    "wof:placetype":"venue"
},
  "geometry": {"coordinates":[5.746438,51.403835],"type":"Point"}
}