{
  "type": "Feature",
  "properties": {
    "addr:full":"Centaurenhof 21 Maastricht Limburg 6215 EE",
    "addr:housenumber":"21",
    "addr:postcode":"6215 ee",
    "addr:street":"Centaurenhof",
    "iso:country":"NL",
    "sg:address":"Centaurenhof 21",
    "sg:city":"Maastricht",
    "sg:orig_category":"Woningstoffeerders",
    "sg:phone":"+31 43 347 7917",
    "sg:postcode":"6215 EE",
    "sg:province":"Limburg",
    "wof:name":"Frerejean, J A",
    "wof:placetype":"venue"
},
  "geometry": {"coordinates":[5.6446418762,50.842830658],"type":"Point"}
}