{
  "type": "Feature",
  "properties": {
    "iso:country":"NL",
    "sg:address":"Kapelstr Z 33",
    "sg:city":"Veldhoven",
    "sg:orig_category":"Montagebedrijven",
    "sg:phone":"+31 40 254 1657",
    "sg:postcode":"5503 CV",
    "sg:province":"North Brabant",
    "wof:name":"Groenen, Gebr",
    "wof:placetype":"venue"
},
  "geometry": {"coordinates":[5.414351,51.41629],"type":"Point"}
}