{
  "type": "Feature",
  "properties": {
    "iso:country":"NL",
    "sg:address":"Staddk 117",
    "sg:city":"Nijmegen",
    "sg:orig_category":"Sportverenigingen En Ontspannings- Verenigingen",
    "sg:phone":"+31 24 344 7988",
    "sg:postcode":"6537 TW",
    "sg:province":"Gelderland",
    "wof:name":"Csv Oranje Blauw Sportver",
    "wof:placetype":"venue"
},
  "geometry": {"coordinates":[5.79003,51.812908],"type":"Point"}
}