{
  "type": "Feature",
  "properties": {
    "addr:full":"Vlietwg 8A Leidschendam Zuid-Holland 2266 KA",
    "addr:housenumber":"8a",
    "addr:postcode":"2266 ka",
    "addr:street":"Vlietwg",
    "iso:country":"NL",
    "sg:address":"Vlietwg 8A",
    "sg:city":"Leidschendam",
    "sg:orig_category":"Autoschade- Herstelbedrijven",
    "sg:phone":"+31 70 320 3131",
    "sg:postcode":"2266 KA",
    "sg:province":"Zuid-Holland",
    "wof:name":"Berg, W Van Den",
    "wof:placetype":"venue"
},
  "geometry": {"coordinates":[4.3885,52.07695],"type":"Point"}
}