{
  "type": "Feature",
  "properties": {
    "addr:full":"Martin Luther Kingsngl 26 Drachten Friesland 9203 JC",
    "addr:housenumber":"26",
    "addr:postcode":"9203 jc",
    "addr:street":"Martin",
    "iso:country":"NL",
    "sg:address":"Martin Luther Kingsngl 26",
    "sg:city":"Drachten",
    "sg:orig_category":"Verhuur Gereedschapsmachines And Gereedschappen",
    "sg:phone":"+31 512 540 080",
    "sg:postcode":"9203 JC",
    "sg:province":"Friesland",
    "wof:name":"Boels Verhuur",
    "wof:placetype":"venue"
},
  "geometry": {"coordinates":[6.105602,53.096336],"type":"Point"}
}