{
  "type": "Feature",
  "properties": {
    "iso:country":"NL",
    "sg:address":"Stationsstr 34",
    "sg:city":"Bergen Op Zoom",
    "sg:orig_category":"Adviesbureaus Verzekeringen",
    "sg:phone":"+31 164 233 833",
    "sg:postcode":"4611 CD",
    "sg:province":"Noord-Brabant",
    "wof:name":"Loos, Bur De",
    "wof:placetype":"venue"
},
  "geometry": {"coordinates":[4.294647,51.494904],"type":"Point"}
}