{
  "type": "Feature",
  "properties": {
    "addr:full":"Tichelwerk 15 Makkum Fr Provincie Friesland 8754 CA",
    "addr:housenumber":"15",
    "addr:postcode":"8754 ca",
    "addr:street":"Tichelwerk;Friesland",
    "iso:country":"NL",
    "sg:address":"Tichelwerk 15",
    "sg:city":"Makkum Fr",
    "sg:orig_category":"Fitnesscentra",
    "sg:phone":"+31 515 232 189",
    "sg:postcode":"8754 CA",
    "sg:province":"Provincie Friesland",
    "wof:name":"Trainingscentrum Fitness Te Vree",
    "wof:placetype":"venue"
},
  "geometry": {"coordinates":[5.409403,53.055962],"type":"Point"}
}