{
  "type": "Feature",
  "properties": {
    "iso:country":"NL",
    "sg:address":"M Krusemanpk 19",
    "sg:city":"Heemskerk",
    "sg:orig_category":"Olie - Exploratie",
    "sg:phone":"+31 251 236 634",
    "sg:postcode":"1963 EE",
    "sg:province":"Noord-Holland",
    "wof:name":"Tool Support & Supply",
    "wof:placetype":"venue"
},
  "geometry": {"coordinates":[4.681659,52.521648],"type":"Point"}
}