{
  "type": "Feature",
  "properties": {
    "addr:full":"Fenacoliusln 8A Maassluis Zuid-Holland 3143 AD",
    "addr:housenumber":"8a",
    "addr:postcode":"3143 ad",
    "addr:street":"Fenacoliusln",
    "iso:country":"NL",
    "sg:address":"Fenacoliusln 8A",
    "sg:city":"Maassluis",
    "sg:orig_category":"Administratie- En Boekhoudkantoren",
    "sg:phone":"+31 10 591 9549",
    "sg:postcode":"3143 AD",
    "sg:province":"Zuid-Holland",
    "wof:name":"Ijdo",
    "wof:placetype":"venue"
},
  "geometry": {"coordinates":[4.253951,51.920013],"type":"Point"}
}