{
  "type": "Feature",
  "properties": {
    "addr:full":"Molenacker 46 Oisterwijk North Brabant 5061 KT",
    "addr:housenumber":"46",
    "addr:postcode":"5061 kt",
    "addr:street":"Molenacker",
    "iso:country":"NL",
    "sg:address":"Molenacker 46",
    "sg:city":"Oisterwijk",
    "sg:orig_category":"Bloemen And Planten Gh",
    "sg:phone":"+31 13 523 0200",
    "sg:postcode":"5061 KT",
    "sg:province":"North Brabant",
    "wof:name":"Hortus",
    "wof:placetype":"venue"
},
  "geometry": {"coordinates":[5.181653,51.586212],"type":"Point"}
}