{
  "type": "Feature",
  "properties": {
    "addr:full":"J. Pienenmanstraat 91 Den Haag Zuid-Holland 2526 WK",
    "addr:housenumber":"91",
    "addr:postcode":"2526 wk",
    "addr:street":"Pienenmanstraat",
    "iso:country":"NL",
    "sg:address":"J. Pienenmanstraat 91",
    "sg:city":"Den Haag",
    "sg:orig_category":"Werving And Selectie Van Tijdelijk Personeel And Uitzendkantoren",
    "sg:phone":"+31 6 53355756",
    "sg:postcode":"2526 WK",
    "sg:province":"Zuid-Holland",
    "wof:name":"Fatih",
    "wof:placetype":"venue"
},
  "geometry": {"coordinates":[4.3118691444,52.0666389465],"type":"Point"}
}