{
  "type": "Feature",
  "properties": {
    "iso:country":"NL",
    "sg:address":"Fenkelstraat 27",
    "sg:city":"Oudenbosch",
    "sg:classifiers":[
        {
            "category":"Shopping",
            "subcategory":"Clothing, Apparel, & Fashions",
            "type":"Retail Goods"
        }
    ],
    "sg:phone":"+31 165 312 228",
    "sg:postcode":"4731 JA",
    "sg:province":"Noord-Brabant",
    "sg:tags":[
        "ondergoed",
        "lingerie"
    ],
    "wof:name":"Takx Modes",
    "wof:placetype":"venue"
},
  "geometry": {"coordinates":[4.525932,51.589664],"type":"Point"}
}