{
  "type": "Feature",
  "properties": {
    "addr:full":"Rusthovenln 30 S Gravenzande Zuid-Holland 2691 JT",
    "addr:housenumber":"30;gravenzande",
    "addr:postcode":"2691 jt",
    "addr:street":"Rusthovenln;S",
    "iso:country":"NL",
    "sg:address":"Rusthovenln 30",
    "sg:city":"S Gravenzande",
    "sg:orig_category":"Bloemen En Planten - Groothandel",
    "sg:phone":"+31 174 283 657",
    "sg:postcode":"2691 JT",
    "sg:province":"Zuid-Holland",
    "wof:name":"Treffers, Fa Gebr",
    "wof:placetype":"venue"
},
  "geometry": {"coordinates":[4.178198,52.009132],"type":"Point"}
}