{
  "type": "Feature",
  "properties": {
    "iso:country":"NL",
    "sg:address":"V Heutszstr 1A",
    "sg:city":"Tilburg",
    "sg:orig_category":"Verenigingen En Stichtingen",
    "sg:phone":"+31 13 536 1427",
    "sg:postcode":"5018 EV",
    "sg:province":"North Brabant",
    "wof:name":"Jong Nederland Heuka, Sticht",
    "wof:placetype":"venue"
},
  "geometry": {"coordinates":[5.106271,51.554928],"type":"Point"}
}