{
  "type": "Feature",
  "properties": {
    "addr:full":"Sluitersdijk 42 Hengelo Ov Overijssel 7554 PG",
    "addr:housenumber":"42",
    "addr:postcode":"7554 pg",
    "addr:street":"Sluitersdijk;Ov",
    "iso:country":"NL",
    "sg:address":"Sluitersdijk 42",
    "sg:city":"Hengelo Ov",
    "sg:orig_category":"Levende Dieren Gh",
    "sg:phone":"+31 74 367 6636",
    "sg:postcode":"7554 PG",
    "sg:province":"Overijssel",
    "wof:name":"Asbroek Beckum Bv",
    "wof:placetype":"venue"
},
  "geometry": {"coordinates":[6.76104,52.221939],"type":"Point"}
}