{
  "type": "Feature",
  "properties": {
    "addr:full":"Bronsstr 9 Naarden Noord-Holland 1411 AV",
    "addr:housenumber":"9",
    "addr:postcode":"1411 av",
    "addr:street":"Bronsstr",
    "iso:country":"NL",
    "sg:address":"Bronsstr 9",
    "sg:city":"Naarden",
    "sg:orig_category":"Hydrocultuur",
    "sg:phone":"+31 35 642 2344",
    "sg:postcode":"1411 AV",
    "sg:province":"Noord-Holland",
    "sg:website":"http://www.boesboes.nl",
    "wof:name":"Boes Boes",
    "wof:placetype":"venue"
},
  "geometry": {"coordinates":[5.15115,52.30304],"type":"Point"}
}