{
  "type": "Feature",
  "properties": {
    "addr:full":"Stadsgravenstr 29-37 Enschede NL.08 7511 EP",
    "addr:housenumber":"29-37",
    "addr:postcode":"7511",
    "iso:country":"NL",
    "sg:address":"Stadsgravenstr 29-37",
    "sg:city":"Enschede",
    "sg:orig_category":"Bioscopen",
    "sg:phone":"+31 53 431 2525",
    "sg:postcode":"7511 EP",
    "sg:province":"NL.08",
    "wof:name":"Alhambra Theaters",
    "wof:placetype":"venue"
},
  "geometry": {"coordinates":[6.89525,52.221416],"type":"Point"}
}