{
  "type": "Feature",
  "properties": {
    "addr:full":"Sloterdijkstraat 6 Amsterdam Noord-Holland 1013 LZ",
    "addr:housenumber":"6",
    "addr:postcode":"1013 lz",
    "addr:street":"Sloterdijkstraat",
    "iso:country":"NL",
    "sg:address":"Sloterdijkstraat 6",
    "sg:city":"Amsterdam",
    "sg:orig_category":"Boekenuitgeverijen",
    "sg:phone":"+31 20 623 0780",
    "sg:postcode":"1013 LZ",
    "sg:province":"Noord-Holland",
    "wof:name":"J. De Bot",
    "wof:placetype":"venue"
},
  "geometry": {"coordinates":[4.884787,52.385853],"type":"Point"}
}