{
  "type": "Feature",
  "properties": {
    "addr:full":"Benedenkerkseweg 68 Stolwijk Zuid-Holland 2821 LD",
    "addr:housenumber":"68",
    "addr:postcode":"2821 ld",
    "addr:street":"Benedenkerkseweg",
    "iso:country":"NL",
    "sg:address":"Benedenkerkseweg 68",
    "sg:city":"Stolwijk",
    "sg:orig_category":"Bloemen And Planten",
    "sg:phone":"+31 182 347 088",
    "sg:postcode":"2821 LD",
    "sg:province":"Zuid-Holland",
    "wof:name":"Kwekerij Kees Breedijk",
    "wof:placetype":"venue"
},
  "geometry": {"coordinates":[4.761841,51.970837],"type":"Point"}
}