{
  "type": "Feature",
  "properties": {
    "addr:full":"Nijenburg 152 Amsterdam Noord-Holland 1081 GG",
    "addr:housenumber":"152",
    "addr:postcode":"1081 gg",
    "addr:street":"Nijenburg",
    "iso:country":"NL",
    "sg:address":"Nijenburg 152",
    "sg:city":"Amsterdam",
    "sg:orig_category":"Public Relationbureaus",
    "sg:phone":"+31 20 404 4707",
    "sg:postcode":"1081 GG",
    "sg:province":"Noord-Holland",
    "wof:name":"Hill And Knowlton Nederland Bv",
    "wof:placetype":"venue"
},
  "geometry": {"coordinates":[4.86571,52.328232],"type":"Point"}
}