{
  "type": "Feature",
  "properties": {
    "addr:full":"Hoofdbrug 7 Heerenveen Friesland 8442 PA",
    "addr:housenumber":"7",
    "addr:postcode":"8442 pa",
    "addr:street":"Hoofdbrug",
    "iso:country":"NL",
    "sg:address":"Hoofdbrug 7",
    "sg:city":"Heerenveen",
    "sg:orig_category":"Parketvloeren",
    "sg:phone":"+31 513 650 604",
    "sg:postcode":"8442 PA",
    "sg:province":"Friesland",
    "wof:name":"D\u00e9cork",
    "wof:placetype":"venue"
},
  "geometry": {"coordinates":[5.923083,52.959911],"type":"Point"}
}