{
  "type": "Feature",
  "properties": {
    "addr:full":"Dreesln 69 Nunspeet Gelderland 8072 XN",
    "addr:housenumber":"69",
    "addr:postcode":"8072 xn",
    "addr:street":"Dreesln;Gelderland",
    "iso:country":"NL",
    "sg:address":"Dreesln 69",
    "sg:city":"Nunspeet",
    "sg:orig_category":"Autorijscholen",
    "sg:phone":"+31 341 251 321",
    "sg:postcode":"8072 XN",
    "sg:province":"Gelderland",
    "wof:name":"Ton Heerink",
    "wof:placetype":"venue"
},
  "geometry": {"coordinates":[5.772205,52.374981],"type":"Point"}
}