{
  "type": "Feature",
  "properties": {
    "iso:country":"NL",
    "sg:address":"Zanddreef 15",
    "sg:city":"Prinsenbeek",
    "sg:orig_category":"Partycatering And -Organisatie",
    "sg:phone":"+31 76 541 8109",
    "sg:postcode":"4841 LC",
    "sg:province":"North Brabant",
    "wof:name":"Easy Party-Service",
    "wof:placetype":"venue"
},
  "geometry": {"coordinates":[4.694178,51.597126],"type":"Point"}
}