{
  "type": "Feature",
  "properties": {
    "iso:country":"NL",
    "sg:address":"Bergstraat 30",
    "sg:city":"Banholt",
    "sg:orig_category":"Elektriciens",
    "sg:phone":"+31 43 457 2068",
    "sg:postcode":"6262 NT",
    "sg:province":"Limburg",
    "wof:name":"Installateursbedrijf P. Colen",
    "wof:placetype":"venue"
},
  "geometry": {"coordinates":[5.806054,50.79459],"type":"Point"}
}