{
  "type": "Feature",
  "properties": {
    "iso:country":"NL",
    "sg:address":"Purperreigerlaan 2",
    "sg:city":"Zwartsluis",
    "sg:orig_category":"Begrafenisondernemers",
    "sg:phone":"+31 521 512 638",
    "sg:postcode":"8064 DC",
    "sg:province":"NL.08",
    "wof:name":"Monuta Verzorging Nv",
    "wof:placetype":"venue"
},
  "geometry": {"coordinates":[6.072445,52.643162],"type":"Point"}
}