{
  "type": "Feature",
  "properties": {
    "addr:full":"Purperreigerlaan 2 Zwartsluis NL.08 8064 DC",
    "addr:housenumber":"2;nl.08",
    "addr:postcode":"8064",
    "addr:street":"Purperreigerlaan",
    "iso:country":"NL",
    "sg:address":"Purperreigerlaan 2",
    "sg:city":"Zwartsluis",
    "sg:orig_category":"Begrafenisondernemers",
    "sg:phone":"+31 521 512 638",
    "sg:postcode":"8064 DC",
    "sg:province":"NL.08",
    "wof:name":"Monuta Verzorging Nv",
    "wof:placetype":"venue"
},
  "geometry": {"coordinates":[6.072445,52.643162],"type":"Point"}
}