{
  "type": "Feature",
  "properties": {
    "addr:full":"Prinses Irenelaan 81 Voorburg South Holland 2273 DH",
    "addr:housenumber":"81",
    "addr:postcode":"2273 dh",
    "addr:street":"Prinses Irenelaan",
    "iso:country":"NL",
    "sg:address":"Prinses Irenelaan 81",
    "sg:city":"Voorburg",
    "sg:orig_category":"Metaalwerken",
    "sg:phone":"+31 70 386 4413",
    "sg:postcode":"2273 DH",
    "sg:province":"South Holland",
    "wof:name":"Gezo Zonwering",
    "wof:placetype":"venue"
},
  "geometry": {"coordinates":[4.358284,52.083942],"type":"Point"}
}