{
  "type": "Feature",
  "properties": {
    "iso:country":"NL",
    "sg:address":"Nieuwestad 101",
    "sg:city":"Leeuwarden",
    "sg:orig_category":"Huishoudapparatuur, Televisies And Radio'S",
    "sg:phone":"+31 58 212 6699",
    "sg:postcode":"8911 CM",
    "sg:province":"Provincie Friesland",
    "wof:name":"Firma Koelmans-Van Der Lep",
    "wof:placetype":"venue"
},
  "geometry": {"coordinates":[5.79438,53.200981],"type":"Point"}
}