{
  "type": "Feature",
  "properties": {
    "addr:full":"Oude Ijselstraat 15Bg Amsterdam Noord-Holland 1078 CL",
    "addr:housenumber":"15bg",
    "addr:postcode":"1078",
    "addr:street":"Oude Ijselstraat",
    "iso:country":"NL",
    "sg:address":"Oude Ijselstraat 15Bg",
    "sg:city":"Amsterdam",
    "sg:orig_category":"Kinderopvang Behalve Thuis",
    "sg:phone":"+31 20 676 1543",
    "sg:postcode":"1078 CL",
    "sg:province":"Noord-Holland",
    "wof:name":"Creche De Ladder",
    "wof:placetype":"venue"
},
  "geometry": {"coordinates":[4.900512,52.347691],"type":"Point"}
}