{
  "type": "Feature",
  "properties": {
    "addr:full":"Oostergo 53 Zoetermeer Zuid-Holland 2716 AP",
    "addr:housenumber":"53",
    "addr:postcode":"2716 ap",
    "addr:street":"Oostergo",
    "iso:country":"NL",
    "sg:address":"Oostergo 53",
    "sg:city":"Zoetermeer",
    "sg:orig_category":"Homeopathie",
    "sg:phone":"+31 6 51555138",
    "sg:postcode":"2716 AP",
    "sg:province":"Zuid-Holland",
    "wof:name":"Duindam, Ilse",
    "wof:placetype":"venue"
},
  "geometry": {"coordinates":[4.465825,52.052956],"type":"Point"}
}