{
  "type": "Feature",
  "properties": {
    "addr:full":"Zomerstr 26 Haarlem Noord-Holland 2033 EP",
    "addr:housenumber":"26",
    "addr:postcode":"2033 ep",
    "addr:street":"Zomerstr",
    "iso:country":"NL",
    "sg:address":"Zomerstr 26",
    "sg:city":"Haarlem",
    "sg:orig_category":"Montagebedrijven",
    "sg:phone":"+31 23 535 7450",
    "sg:postcode":"2033 EP",
    "sg:province":"Noord-Holland",
    "wof:name":"Mul",
    "wof:placetype":"venue"
},
  "geometry": {"coordinates":[4.64565,52.375996],"type":"Point"}
}