{
  "type": "Feature",
  "properties": {
    "addr:full":"Piusstraat 14 Kerkrade Limburg 6467 EH",
    "addr:housenumber":"14",
    "addr:postcode":"6467 eh",
    "addr:street":"Piusstraat",
    "iso:country":"NL",
    "sg:address":"Piusstraat 14",
    "sg:city":"Kerkrade",
    "sg:classifiers":[
        {
            "category":"Food & Beverages",
            "subcategory":"Fruits & Vegetables",
            "type":"Retail Goods"
        }
    ],
    "sg:phone":"+31 45 542 4875",
    "sg:postcode":"6467 EH",
    "sg:province":"Limburg",
    "sg:tags":[
        "groenten"
    ],
    "wof:name":"A.G.F. Kiwi",
    "wof:placetype":"venue"
},
  "geometry": {"coordinates":[6.025146,50.867683],"type":"Point"}
}