{
  "type": "Feature",
  "properties": {
    "addr:full":"Gerestraat 36 Heesselt Gelderland 4063 CS",
    "addr:housenumber":"36",
    "addr:postcode":"4063 cs",
    "addr:street":"Gerestraat;Gelderland",
    "iso:country":"NL",
    "sg:address":"Gerestraat 36",
    "sg:city":"Heesselt",
    "sg:orig_category":"Wegen And Sportterreinen",
    "sg:phone":"+31 344 651 527",
    "sg:postcode":"4063 CS",
    "sg:province":"Gelderland",
    "wof:name":"Makajo Vof",
    "wof:placetype":"venue"
},
  "geometry": {"coordinates":[5.3500380516,51.8143882751],"type":"Point"}
}