{
  "type": "Feature",
  "properties": {
    "addr:full":"Hammarskjoldstr 230A Hoofddorp Noord-Holland 2131 VN",
    "addr:housenumber":"230a",
    "addr:postcode":"2131 vn",
    "iso:country":"NL",
    "sg:address":"Hammarskjoldstr 230A",
    "sg:city":"Hoofddorp",
    "sg:orig_category":"Scholen Voor Basisonderwijs",
    "sg:phone":"+31 23 562 3146",
    "sg:postcode":"2131 VN",
    "sg:province":"Noord-Holland",
    "wof:name":"Haarlemmermeer Vrije Sch",
    "wof:placetype":"venue"
},
  "geometry": {"coordinates":[4.676531,52.301308],"type":"Point"}
}