{
  "type": "Feature",
  "properties": {
    "addr:full":"Postbus 18510 S Gravenhage Noord-Holland 2502 EM",
    "addr:housenumber":"18510",
    "addr:postcode":"2502 em",
    "addr:street":"Postbus;S Gravenhage",
    "iso:country":"NL",
    "sg:address":"Postbus 18510",
    "sg:city":"S Gravenhage",
    "sg:orig_category":"Adviesbureaus",
    "sg:phone":"+31 70 362 4896",
    "sg:postcode":"2502 EM",
    "sg:province":"Noord-Holland",
    "sg:website":"http://www.eurocomform.com",
    "wof:name":"European Conformity Serv",
    "wof:placetype":"venue"
},
  "geometry": {"coordinates":[4.31361,52.07832],"type":"Point"}
}