{
  "type": "Feature",
  "properties": {
    "addr:full":"Hornwg 77A Aalsmeer North Holland 1432 GD",
    "addr:housenumber":"77a",
    "addr:postcode":"1432 gd",
    "addr:street":"Hornwg",
    "iso:country":"NL",
    "sg:address":"Hornwg 77A",
    "sg:city":"Aalsmeer",
    "sg:orig_category":"Woninginrichting- Fournituren - Fabrieken En Groothandel",
    "sg:phone":"+31 297 329 222",
    "sg:postcode":"1432 GD",
    "sg:province":"North Holland",
    "wof:name":"Pol'S Potten Bv",
    "wof:placetype":"venue"
},
  "geometry": {"coordinates":[4.784427166,52.2681694031],"type":"Point"}
}