{
  "type": "Feature",
  "properties": {
    "addr:full":"Bokhovense Maasdk 12 S Hertogenbosch Gelderland 5221 BP",
    "addr:housenumber":"12",
    "addr:postcode":"5221 bp",
    "addr:street":"S Hertogenbosch Gelderland",
    "iso:country":"NL",
    "sg:address":"Bokhovense Maasdk 12",
    "sg:city":"S Hertogenbosch",
    "sg:orig_category":"Zalenverhuur",
    "sg:phone":"+31 73 631 1242",
    "sg:postcode":"5221 BP",
    "sg:province":"Gelderland",
    "wof:name":"Veerhuis, Het",
    "wof:placetype":"venue"
},
  "geometry": {"coordinates":[5.241039,51.734451],"type":"Point"}
}