{
  "type": "Feature",
  "properties": {
    "addr:full":"Lariksln 12 Sleeuwyk Noord-Brabant 4254 BG",
    "addr:housenumber":"12",
    "addr:postcode":"4254",
    "addr:street":"Lariksln",
    "iso:country":"NL",
    "sg:address":"Lariksln 12",
    "sg:city":"Sleeuwyk",
    "sg:orig_category":"Goudsmeden En Zilversmeden",
    "sg:phone":"+31 183 304 657",
    "sg:postcode":"4254 BG",
    "sg:province":"Noord-Brabant",
    "wof:name":"Verschoor, Sandra",
    "wof:placetype":"venue"
},
  "geometry": {"coordinates":[4.950798,51.813931],"type":"Point"}
}