{
  "type": "Feature",
  "properties": {
    "addr:full":"Stationswg 2 Aalsmeer Noord-Holland 1431 EG",
    "addr:housenumber":"2",
    "addr:postcode":"1431 eg",
    "addr:street":"Stationswg",
    "iso:country":"NL",
    "sg:address":"Stationswg 2",
    "sg:city":"Aalsmeer",
    "sg:orig_category":"Opticiens",
    "sg:phone":"+31 297 320 478",
    "sg:postcode":"1431 EG",
    "sg:province":"Noord-Holland",
    "sg:website":"http://www.edkriekoptiek.nl",
    "wof:name":"Ed Kriek Optiek Aalsmeer",
    "wof:placetype":"venue"
},
  "geometry": {"coordinates":[4.7487659454,52.2666931152],"type":"Point"}
}