{
  "type": "Feature",
  "properties": {
    "addr:full":"Merel 88 Heemskerk Noord-Holland 1965 ET",
    "addr:housenumber":"88",
    "addr:postcode":"1965 et",
    "addr:street":"Merel",
    "iso:country":"NL",
    "sg:address":"Merel 88",
    "sg:city":"Heemskerk",
    "sg:classifiers":[
        {
            "category":"Personal",
            "subcategory":"Nail Salon",
            "type":"Services"
        }
    ],
    "sg:phone":"+31 251 244 075",
    "sg:postcode":"1965 ET",
    "sg:province":"Noord-Holland",
    "sg:tags":[
        "pedicure"
    ],
    "wof:name":"Voetensalon, De",
    "wof:placetype":"venue"
},
  "geometry": {"coordinates":[4.672283,52.502903],"type":"Point"}
}