{
  "type": "Feature",
  "properties": {
    "iso:country":"NL",
    "sg:address":"De Aa 7",
    "sg:city":"Wierden",
    "sg:orig_category":"Kinderactiviteiten",
    "sg:phone":"+31 546 579 640",
    "sg:postcode":"7642 HA",
    "sg:province":"NL.08",
    "sg:website":"HTTP://www.derodeballon.nl",
    "wof:name":"Rode Ballon, De",
    "wof:placetype":"venue"
},
  "geometry": {"coordinates":[6.601989,52.355366],"type":"Point"}
}