{
  "type": "Feature",
  "properties": {
    "addr:full":"Kweldergrasveld 3 Almere Flevoland 1313 CA",
    "addr:housenumber":"3",
    "addr:postcode":"1313 ca",
    "addr:street":"Kweldergrasveld;Flevoland",
    "iso:country":"NL",
    "sg:address":"Kweldergrasveld 3",
    "sg:city":"Almere",
    "sg:orig_category":"Kantoor- En Secretariaatsservice",
    "sg:phone":"+31 36 530 5631",
    "sg:postcode":"1313 CA",
    "sg:province":"Flevoland",
    "wof:name":"Tobra",
    "wof:placetype":"venue"
},
  "geometry": {"coordinates":[5.199988842,52.3842506409],"type":"Point"}
}