{
  "type": "Feature",
  "properties": {
    "addr:full":"Europasngl 1 Vroomshoop Overijssel 7681 NA",
    "addr:housenumber":"1",
    "addr:postcode":"7681 na",
    "addr:street":"Europasngl",
    "iso:country":"NL",
    "sg:address":"Europasngl 1",
    "sg:city":"Vroomshoop",
    "sg:orig_category":"Meubelmakerijen",
    "sg:phone":"+31 546 643 353",
    "sg:postcode":"7681 NA",
    "sg:province":"Overijssel",
    "wof:name":"Hankamp",
    "wof:placetype":"venue"
},
  "geometry": {"coordinates":[6.571005,52.461327],"type":"Point"}
}