{
  "type": "Feature",
  "properties": {
    "addr:full":"Hoofdwg Z 22A Nieuwerkerk Yssel South Holland 2912 ED",
    "addr:housenumber":"22a",
    "addr:postcode":"2912 ed",
    "iso:country":"NL",
    "sg:address":"Hoofdwg Z 22A",
    "sg:city":"Nieuwerkerk Yssel",
    "sg:orig_category":"Verpakkingen En Verpakkingsmaterialen",
    "sg:phone":"+31 180 321 311",
    "sg:postcode":"2912 ED",
    "sg:province":"South Holland",
    "wof:name":"Leeder Bv, Den",
    "wof:placetype":"venue"
},
  "geometry": {"coordinates":[4.6028,51.963692],"type":"Point"}
}