{
  "type": "Feature",
  "properties": {
    "addr:full":"Fatimastr 100 Breda Noord-Brabant 4835 BE",
    "addr:housenumber":"100",
    "addr:postcode":"4835",
    "iso:country":"NL",
    "sg:address":"Fatimastr 100",
    "sg:city":"Breda",
    "sg:orig_category":"Kunststoffen- Verwerkende Industrie",
    "sg:phone":"+31 76 561 1950",
    "sg:postcode":"4835 BE",
    "sg:province":"Noord-Brabant",
    "sg:website":"http://www.flitsbv.com",
    "wof:name":"Flits / Donka",
    "wof:placetype":"venue"
},
  "geometry": {"coordinates":[4.791486,51.5728],"type":"Point"}
}