{
  "type": "Feature",
  "properties": {
    "addr:full":"Raadhuisplein 22 Barneveld Gelderland 3771 ER",
    "addr:housenumber":"22",
    "addr:postcode":"3771 er",
    "addr:street":"Raadhuisplein;Gelderland",
    "iso:country":"NL",
    "sg:address":"Raadhuisplein 22",
    "sg:city":"Barneveld",
    "sg:orig_category":"Wasserettes And Stomerijen",
    "sg:phone":"+31 342 415 176",
    "sg:postcode":"3771 ER",
    "sg:province":"Gelderland",
    "wof:name":"Ascot-A2 Stomerij",
    "wof:placetype":"venue"
},
  "geometry": {"coordinates":[5.5859508514,52.1395263672],"type":"Point"}
}