{
  "type": "Feature",
  "properties": {
    "addr:full":"Burgerhoutsestraat 107 , (Mobiele Telefoon) Roosendaal Noord-Brabant 4702 BC",
    "addr:housenumber":"107",
    "addr:postcode":"4702 bc",
    "addr:street":"Burgerhoutsestraat;Telefoon",
    "iso:country":"NL",
    "sg:address":"Burgerhoutsestraat 107 , (Mobiele Telefoon)",
    "sg:city":"Roosendaal",
    "sg:orig_category":"Verkoopautomaten",
    "sg:phone":"+31 165 533 754",
    "sg:postcode":"4702 BC",
    "sg:province":"Noord-Brabant",
    "wof:name":"Ellis Nederland Bv",
    "wof:placetype":"venue"
},
  "geometry": {"coordinates":[4.469215,51.528889],"type":"Point"}
}