{
  "type": "Feature",
  "properties": {
    "addr:full":"Vondelstraat 14A Beek Lb Missouri 6191 CN",
    "addr:housenumber":"14a",
    "addr:postcode":"6191 cn",
    "addr:street":"Vondelstraat",
    "iso:country":"NL",
    "sg:address":"Vondelstraat 14A",
    "sg:city":"Beek Lb",
    "sg:orig_category":"Koeriersdiensten",
    "sg:phone":"+31 46 437 4461",
    "sg:postcode":"6191 CN",
    "sg:province":"Missouri",
    "wof:name":"H.D. Vervoer",
    "wof:placetype":"venue"
},
  "geometry": {"coordinates":[-93.129936,36.705662],"type":"Point"}
}