{
  "type": "Feature",
  "properties": {
    "addr:full":"Newtonstr 3 Tiel Gelderland 4004 KD",
    "addr:housenumber":"3",
    "addr:postcode":"4004 kd",
    "addr:street":"Newtonstr;Gelderland",
    "iso:country":"NL",
    "sg:address":"Newtonstr 3",
    "sg:city":"Tiel",
    "sg:orig_category":"Verpakkingen En Verpakkingsmaterialen",
    "sg:phone":"+31 344 623 128",
    "sg:postcode":"4004 KD",
    "sg:province":"Gelderland",
    "wof:name":"Primapack",
    "wof:placetype":"venue"
},
  "geometry": {"coordinates":[5.43447,51.915119],"type":"Point"}
}