{
  "type": "Feature",
  "properties": {
    "iso:country":"NL",
    "sg:address":"De Els 36",
    "sg:city":"Waalwijk",
    "sg:orig_category":"Damesmodezaken",
    "sg:phone":"+31 416 330 568",
    "sg:postcode":"5141 HH",
    "sg:province":"Noord-Brabant",
    "wof:name":"Next Mode",
    "wof:placetype":"venue"
},
  "geometry": {"coordinates":[5.064747,51.689423],"type":"Point"}
}