{
  "type": "Feature",
  "properties": {
    "addr:full":"Hongkongstraat 72 Rotterdam Zuid-Holland 3047 BS",
    "addr:housenumber":"72",
    "addr:postcode":"3047 bs",
    "addr:street":"Hongkongstraat",
    "iso:country":"NL",
    "sg:address":"Hongkongstraat 72",
    "sg:city":"Rotterdam",
    "sg:orig_category":"Architecten",
    "sg:phone":"+31 10 462 7878",
    "sg:postcode":"3047 BS",
    "sg:province":"Zuid-Holland",
    "wof:name":"E & F Architekten Bv",
    "wof:placetype":"venue"
},
  "geometry": {"coordinates":[4.400897,51.941788],"type":"Point"}
}