{
  "type": "Feature",
  "properties": {
    "iso:country":"NL",
    "sg:address":"Andreas Schelfhoutstraat 3",
    "sg:city":"Amsterdam",
    "sg:orig_category":"Diverse Grafische Activiteiten",
    "sg:phone":"+31 20 617 0301",
    "sg:postcode":"1058 HP",
    "sg:province":"North Holland",
    "wof:name":"Astrid Janssen",
    "wof:placetype":"venue"
},
  "geometry": {"coordinates":[4.853627,52.357029],"type":"Point"}
}