{
  "type": "Feature",
  "properties": {
    "addr:full":"Middenwg 24 Ysselstein Ut Utrecht 3401 MB",
    "addr:housenumber":"24",
    "addr:postcode":"3401 mb",
    "addr:street":"Middenwg",
    "iso:country":"NL",
    "sg:address":"Middenwg 24",
    "sg:city":"Ysselstein Ut",
    "sg:orig_category":"Etiketten",
    "sg:phone":"+31 30 688 1829",
    "sg:postcode":"3401 MB",
    "sg:province":"Utrecht",
    "wof:name":"Labelfabr Holland",
    "wof:placetype":"venue"
},
  "geometry": {"coordinates":[5.054414,52.013851],"type":"Point"}
}