{
  "type": "Feature",
  "properties": {
    "addr:full":"Overgauwsewg 65 Pynacker Zuid-Holland 2641 ND",
    "addr:housenumber":"65",
    "addr:postcode":"2641 nd",
    "addr:street":"Overgauwsewg",
    "iso:country":"NL",
    "sg:address":"Overgauwsewg 65",
    "sg:city":"Pynacker",
    "sg:orig_category":"Autoruiten",
    "sg:phone":"+31 15 361 0923",
    "sg:postcode":"2641 ND",
    "sg:province":"Zuid-Holland",
    "sg:website":"http://www.glasgarage.nl",
    "wof:name":"Glasgarage Pijnacker",
    "wof:placetype":"venue"
},
  "geometry": {"coordinates":[4.426423,52.009411],"type":"Point"}
}