{
  "type": "Feature",
  "properties": {
    "addr:full":"Pompmakker 14 Heerenveen Friesland 8447 GJ",
    "addr:housenumber":"14",
    "addr:postcode":"8447 gj",
    "addr:street":"Pompmakker",
    "iso:country":"NL",
    "sg:address":"Pompmakker 14",
    "sg:city":"Heerenveen",
    "sg:orig_category":"Elektronische Bedrijfsinstallaties",
    "sg:phone":"+31 513 650 504",
    "sg:postcode":"8447 GJ",
    "sg:province":"Friesland",
    "wof:name":"Chubb Flame Control Bv",
    "wof:placetype":"venue"
},
  "geometry": {"coordinates":[5.900547,52.964706],"type":"Point"}
}