{
  "type": "Feature",
  "properties": {
    "iso:country":"NL",
    "sg:address":"Heuvelstraat 99",
    "sg:city":"Tilburg",
    "sg:orig_category":"Verlichting And Huishoudartikelen",
    "sg:phone":"+31 13 542 5124",
    "sg:postcode":"5038 AC",
    "sg:province":"Noord-Brabant",
    "wof:name":"Pierson Bv",
    "wof:placetype":"venue"
},
  "geometry": {"coordinates":[5.084759,51.555592],"type":"Point"}
}