{
  "type": "Feature",
  "properties": {
    "addr:full":"Speelhuisln 66 Breda North Brabant 4815 CG",
    "addr:housenumber":"66",
    "addr:postcode":"4815 cg",
    "addr:street":"Speelhuisln",
    "iso:country":"NL",
    "sg:address":"Speelhuisln 66",
    "sg:city":"Breda",
    "sg:orig_category":"Beeldende Kunstenaars",
    "sg:phone":"+31 76 587 6460",
    "sg:postcode":"4815 CG",
    "sg:province":"North Brabant",
    "wof:name":"Koolen, H",
    "wof:placetype":"venue"
},
  "geometry": {"coordinates":[4.771685,51.591351],"type":"Point"}
}