{
  "type": "Feature",
  "properties": {
    "addr:full":"Moliereln 64 Venlo Limburg 5924 AN",
    "addr:housenumber":"64",
    "addr:postcode":"5924 an",
    "addr:street":"Moliereln",
    "iso:country":"NL",
    "sg:address":"Moliereln 64",
    "sg:city":"Venlo",
    "sg:orig_category":"Geschenkartikelen",
    "sg:phone":"+31 77 382 5586",
    "sg:postcode":"5924 AN",
    "sg:province":"Limburg",
    "wof:name":"Mio Casa",
    "wof:placetype":"venue"
},
  "geometry": {"coordinates":[6.1300001144,51.3665008545],"type":"Point"}
}