{
  "type": "Feature",
  "properties": {
    "iso:country":"NL",
    "sg:address":"Energieweg 6",
    "sg:city":"Renkum",
    "sg:orig_category":"Meubels And Huishoudapparatuur Gh",
    "sg:phone":"+31 317 319 115",
    "sg:postcode":"6871 KB",
    "sg:province":"Gelderland",
    "wof:name":"Hofstede Renkum Bv",
    "wof:placetype":"venue"
},
  "geometry": {"coordinates":[5.739873,51.985786],"type":"Point"}
}