{
  "type": "Feature",
  "properties": {
    "iso:country":"NL",
    "sg:address":"Strangewg 17A",
    "sg:city":"Ommen",
    "sg:orig_category":"Autoruiten",
    "sg:phone":"+31 529 462 501",
    "sg:postcode":"7731 GV",
    "sg:province":"Overijssel",
    "wof:name":"Riss Almelo",
    "wof:placetype":"venue"
},
  "geometry": {"coordinates":[6.431878,52.525509],"type":"Point"}
}