{
  "type": "Feature",
  "properties": {
    "addr:full":"Bonhoeffersingel 26 Amsterdam Noord-Holland 1069 NB",
    "addr:housenumber":"26",
    "addr:postcode":"1069 nb",
    "addr:street":"Bonhoeffersingel",
    "iso:country":"NL",
    "sg:address":"Bonhoeffersingel 26",
    "sg:city":"Amsterdam",
    "sg:orig_category":"Technische Studies And Onderzoek",
    "sg:phone":"+31 20 619 3770",
    "sg:postcode":"1069 NB",
    "sg:province":"Noord-Holland",
    "wof:name":"S. Litvinov",
    "wof:placetype":"venue"
},
  "geometry": {"coordinates":[4.779654,52.355419],"type":"Point"}
}