{
  "type": "Feature",
  "properties": {
    "iso:country":"NL",
    "sg:address":"Spykermakersstr 130",
    "sg:city":"S Gravenhage",
    "sg:orig_category":"Administratie- En Boekhoudkantoren",
    "sg:phone":"+31 70 305 0440",
    "sg:postcode":"2512 ET",
    "sg:province":"Zuid-Holland",
    "wof:name":"Bos, Frank Van Den",
    "wof:placetype":"venue"
},
  "geometry": {"coordinates":[4.30618,52.073212],"type":"Point"}
}