{
  "type": "Feature",
  "properties": {
    "addr:full":"Theresiastr 115 Den Haag Zuid-Holland 2593 AE",
    "addr:housenumber":"115",
    "addr:postcode":"2593 ae",
    "iso:country":"NL",
    "sg:address":"Theresiastr 115",
    "sg:city":"Den Haag",
    "sg:orig_category":"Banken",
    "sg:phone":"+31 70 371 8888",
    "sg:postcode":"2593 AE",
    "sg:province":"Zuid-Holland",
    "sg:website":"http://www.rabobank.nl",
    "wof:name":"Rabobank",
    "wof:placetype":"venue"
},
  "geometry": {"coordinates":[4.335635,52.085464],"type":"Point"}
}