{
  "type": "Feature",
  "properties": {
    "iso:country":"NL",
    "sg:address":"Vasteland 28",
    "sg:city":"Rotterdam",
    "sg:orig_category":"Kappers",
    "sg:phone":"+31 10 412 3302",
    "sg:postcode":"3011 BL",
    "sg:province":"Zuid-Holland",
    "wof:name":"Matena Kapsalon",
    "wof:placetype":"venue"
},
  "geometry": {"coordinates":[4.480328,51.911831],"type":"Point"}
}