{
  "type": "Feature",
  "properties": {
    "addr:full":"Gijsbrecht Van Amstelstr 107 Hilversum North Holland 1214 AW",
    "addr:housenumber":"107",
    "addr:postcode":"1214 aw",
    "addr:street":"Gijsbrecht Van Amstelstr",
    "iso:country":"NL",
    "sg:address":"Gijsbrecht Van Amstelstr 107",
    "sg:city":"Hilversum",
    "sg:orig_category":"Wasserettes And Stomerijen",
    "sg:phone":"+31 35 624 6023",
    "sg:postcode":"1214 AW",
    "sg:province":"North Holland",
    "wof:name":"Stomerij De Gijsbrecht",
    "wof:placetype":"venue"
},
  "geometry": {"coordinates":[5.1713628769,52.2157936096],"type":"Point"}
}