{
  "type": "Feature",
  "properties": {
    "addr:full":"Molendyksewg 2 Yerseke Zeeland 4401 NM",
    "addr:housenumber":"2",
    "addr:postcode":"4401",
    "addr:street":"Molendyksewg",
    "iso:country":"NL",
    "sg:address":"Molendyksewg 2",
    "sg:city":"Yerseke",
    "sg:orig_category":"Drukkerijen",
    "sg:phone":"+31 113 571 404",
    "sg:postcode":"4401 NM",
    "sg:province":"Zeeland",
    "wof:name":"Zoeteweij",
    "wof:placetype":"venue"
},
  "geometry": {"coordinates":[4.046035,51.491943],"type":"Point"}
}