{
  "type": "Feature",
  "properties": {
    "addr:full":"Voorschoterln 40 Rotterdam Zuid-Holland 3062 KP",
    "addr:housenumber":"40",
    "addr:postcode":"3062 kp",
    "addr:street":"Voorschoterln",
    "iso:country":"NL",
    "sg:address":"Voorschoterln 40",
    "sg:city":"Rotterdam",
    "sg:orig_category":"Verloskundigen",
    "sg:phone":"+31 10 414 1351",
    "sg:postcode":"3062 KP",
    "sg:province":"Zuid-Holland",
    "wof:name":"Maatschap Rotterdam Oost",
    "wof:placetype":"venue"
},
  "geometry": {"coordinates":[4.51759,51.931339],"type":"Point"}
}