{
  "type": "Feature",
  "properties": {
    "addr:full":"2E Kostverlorenkd 119 Amsterdam North Holland 1053 SC",
    "addr:housenumber":"119",
    "addr:postcode":"1053 sc",
    "addr:street":"2E Kostverlorenkd",
    "iso:country":"NL",
    "sg:address":"2E Kostverlorenkd 119",
    "sg:city":"Amsterdam",
    "sg:orig_category":"Adviesbureaus Bouwkunde",
    "sg:phone":"+31 20 683 0159",
    "sg:postcode":"1053 SC",
    "sg:province":"North Holland",
    "wof:name":"B A B Bouwadviesbureau",
    "wof:placetype":"venue"
},
  "geometry": {"coordinates":[4.860959,52.365002],"type":"Point"}
}