{
  "type": "Feature",
  "properties": {
    "addr:full":"Biensma 31 Grou Friesland 9001 XZ",
    "addr:housenumber":"31",
    "addr:postcode":"9001 xz",
    "addr:street":"Biensma",
    "iso:country":"NL",
    "sg:address":"Biensma 31",
    "sg:city":"Grou",
    "sg:orig_category":"Gehandicapteninformatie",
    "sg:phone":"+31 566 625 111",
    "sg:postcode":"9001 XZ",
    "sg:province":"Friesland",
    "sg:website":"http://www.start.nl",
    "wof:name":"Start Kans",
    "wof:placetype":"venue"
},
  "geometry": {"coordinates":[-113.611923,43.688873],"type":"Point"}
}