{
  "type": "Feature",
  "properties": {
    "addr:full":"Filosofentuin 49 Capelle Ad Yssel Zuid-Holland 2908 XA",
    "addr:housenumber":"49",
    "addr:postcode":"2908 xa",
    "addr:street":"Filosofentuin",
    "iso:country":"NL",
    "sg:address":"Filosofentuin 49",
    "sg:city":"Capelle Ad Yssel",
    "sg:orig_category":"Loopbaanbegeleiding",
    "sg:phone":"+31 10 458 5995",
    "sg:postcode":"2908 XA",
    "sg:province":"Zuid-Holland",
    "wof:name":"Balanz",
    "wof:placetype":"venue"
},
  "geometry": {"coordinates":[4.591699,51.957352],"type":"Point"}
}