{
  "type": "Feature",
  "properties": {
    "addr:full":"Nachtegaalstr 2 Marum Groningen 9363 GB",
    "addr:housenumber":"2",
    "addr:postcode":"9363 gb",
    "addr:street":"Nachtegaalstr",
    "iso:country":"NL",
    "sg:address":"Nachtegaalstr 2",
    "sg:city":"Marum",
    "sg:orig_category":"Bejaarden - Verzorgingstehuizen",
    "sg:phone":"+31 594 641 812",
    "sg:postcode":"9363 GB",
    "sg:province":"Groningen",
    "wof:name":"Westkwartier, Sticht De",
    "wof:placetype":"venue"
},
  "geometry": {"coordinates":[6.263651,53.144489],"type":"Point"}
}