{
  "type": "Feature",
  "properties": {
    "addr:full":"Appelweg 6 Moerdijk Noord-Brabant 4782 PX",
    "addr:housenumber":"6",
    "addr:postcode":"4782 px",
    "addr:street":"Appelweg",
    "iso:country":"NL",
    "sg:address":"Appelweg 6",
    "sg:city":"Moerdijk",
    "sg:orig_category":"Goederenvervoer Over De Weg",
    "sg:phone":"+31 168 415 161",
    "sg:postcode":"4782 PX",
    "sg:province":"Noord-Brabant",
    "wof:name":"Sintra International Bv",
    "wof:placetype":"venue"
},
  "geometry": {"coordinates":[4.615945,51.695892],"type":"Point"}
}