{
  "type": "Feature",
  "properties": {
    "addr:full":"Koepoortswg 69 Hoorn Nh Noord-Holland 1624 AC",
    "addr:housenumber":"69",
    "addr:postcode":"1624 ac",
    "addr:street":"Koepoortswg",
    "iso:country":"NL",
    "sg:address":"Koepoortswg 69",
    "sg:city":"Hoorn Nh",
    "sg:classifiers":[
        {
            "category":"Food & Beverages",
            "subcategory":"Bakery",
            "type":"Retail Goods"
        }
    ],
    "sg:phone":"+31 229 214 786",
    "sg:postcode":"1624 AC",
    "sg:province":"Noord-Holland",
    "sg:tags":[
        "brood",
        "en",
        "banket"
    ],
    "wof:name":"Otten",
    "wof:placetype":"venue"
},
  "geometry": {"coordinates":[5.057111,52.647202],"type":"Point"}
}