{
  "type": "Feature",
  "properties": {
    "iso:country":"NL",
    "sg:address":"Eursing 53",
    "sg:city":"Beilen",
    "sg:orig_category":"Cafetaria'S",
    "sg:phone":"+31 593 522 658",
    "sg:postcode":"9411 XB",
    "sg:province":"Drenthe",
    "wof:name":"Oosterloo'S",
    "wof:placetype":"venue"
},
  "geometry": {"coordinates":[6.532215,52.890293],"type":"Point"}
}