{
  "type": "Feature",
  "properties": {
    "addr:full":"Prinsenweier 19 Nuenen North Brabant 5673 TX",
    "addr:housenumber":"19",
    "addr:postcode":"5673 tx",
    "addr:street":"Prinsenweier",
    "iso:country":"NL",
    "sg:address":"Prinsenweier 19",
    "sg:city":"Nuenen",
    "sg:orig_category":"Verloskundigen",
    "sg:phone":"+31 40 283 3160",
    "sg:postcode":"5673 TX",
    "sg:province":"North Brabant",
    "wof:name":"Verloskundigenpraktijk Nuenen",
    "wof:placetype":"venue"
},
  "geometry": {"coordinates":[5.577357,51.465912],"type":"Point"}
}