{
  "type": "Feature",
  "properties": {
    "addr:full":"F C Dondersstr 48 Utrecht Utrecht 3572 JK",
    "addr:housenumber":"48",
    "addr:postcode":"3572 jk",
    "addr:street":"F;Dondersstr",
    "iso:country":"NL",
    "sg:address":"F C Dondersstr 48",
    "sg:city":"Utrecht",
    "sg:orig_category":"Adviesbureaus",
    "sg:phone":"+31 30 273 1061",
    "sg:postcode":"3572 JK",
    "sg:province":"Utrecht",
    "wof:name":"Transformotion",
    "wof:placetype":"venue"
},
  "geometry": {"coordinates":[5.138442,52.09726],"type":"Point"}
}