{
  "type": "Feature",
  "properties": {
    "addr:full":"Sluiswg 14A Katwyk Zh South Holland 2225 XL",
    "addr:housenumber":"14a;zh",
    "addr:postcode":"2225 xl",
    "addr:street":"Sluiswg",
    "iso:country":"NL",
    "sg:address":"Sluiswg 14A",
    "sg:city":"Katwyk Zh",
    "sg:orig_category":"Kunsthandel",
    "sg:phone":"+31 71 401 3675",
    "sg:postcode":"2225 XL",
    "sg:province":"South Holland",
    "wof:name":"Bentrijk",
    "wof:placetype":"venue"
},
  "geometry": {"coordinates":[4.397819,52.205772],"type":"Point"}
}