{
  "type": "Feature",
  "properties": {
    "addr:full":"Wandelbosln 48 Tilburg North Brabant 5042 PD",
    "addr:housenumber":"48",
    "addr:postcode":"5042 pd",
    "addr:street":"Wandelbosln",
    "iso:country":"NL",
    "sg:address":"Wandelbosln 48",
    "sg:city":"Tilburg",
    "sg:orig_category":"Webdesign Bureaus",
    "sg:phone":"+31 13 590 0455",
    "sg:postcode":"5042 PD",
    "sg:province":"North Brabant",
    "sg:website":"http://www.baakbeeld.nl",
    "wof:name":"Baakbeeld",
    "wof:placetype":"venue"
},
  "geometry": {"coordinates":[5.0545401573,51.5718803406],"type":"Point"}
}