{
  "type": "Feature",
  "properties": {
    "addr:full":"Zwaardvegerstr 288 Zwolle Overijssel 8043 DZ",
    "addr:housenumber":"288",
    "addr:postcode":"8043 dz",
    "iso:country":"NL",
    "sg:address":"Zwaardvegerstr 288",
    "sg:city":"Zwolle",
    "sg:orig_category":"Onroerende Goederen",
    "sg:phone":"+31 38 444 3206",
    "sg:postcode":"8043 DZ",
    "sg:province":"Overijssel",
    "wof:name":"Hbu Bv",
    "wof:placetype":"venue"
},
  "geometry": {"coordinates":[6.061502,52.531536],"type":"Point"}
}