{
  "type": "Feature",
  "properties": {
    "addr:full":"Kon Emmakd 65 S Gravenhage South Holland 2518 RL",
    "addr:housenumber":"65",
    "addr:postcode":"2518 rl",
    "addr:street":"Kon;S Gravenhage",
    "iso:country":"NL",
    "sg:address":"Kon Emmakd 65",
    "sg:city":"S Gravenhage",
    "sg:orig_category":"Autorijscholen",
    "sg:phone":"+31 70 346 9391",
    "sg:postcode":"2518 RL",
    "sg:province":"South Holland",
    "sg:website":"http://www.rijtempo.nl",
    "wof:name":"Tempo Verkeersschool",
    "wof:placetype":"venue"
},
  "geometry": {"coordinates":[4.29348,52.080318],"type":"Point"}
}