{
  "type": "Feature",
  "properties": {
    "addr:full":"Zuiveringweg 26 Lelystad Flevoland 8243 PZ",
    "addr:housenumber":"26",
    "addr:postcode":"8243 pz",
    "addr:street":"Zuiveringweg;Flevoland",
    "iso:country":"NL",
    "sg:address":"Zuiveringweg 26",
    "sg:city":"Lelystad",
    "sg:orig_category":"Voeding, Dranken And Tabak Gh",
    "sg:phone":"+31 320 281 213",
    "sg:postcode":"8243 PZ",
    "sg:province":"Flevoland",
    "wof:name":"Tanis Food Tec Bv",
    "wof:placetype":"venue"
},
  "geometry": {"coordinates":[5.446275,52.501289],"type":"Point"}
}