{
  "type": "Feature",
  "properties": {
    "addr:full":"Nieuwez Voorburgw 87A Amsterdam North Holland 1012 RE",
    "addr:housenumber":"87a",
    "addr:postcode":"1012 re",
    "iso:country":"NL",
    "sg:address":"Nieuwez Voorburgw 87A",
    "sg:city":"Amsterdam",
    "sg:orig_category":"Koffie- En Theehuizen",
    "sg:phone":"+31 20 627 5683",
    "sg:postcode":"1012 RE",
    "sg:province":"North Holland",
    "sg:website":"http://www.homegrownfantasy.com",
    "wof:name":"Homegrown Fantasy",
    "wof:placetype":"venue"
},
  "geometry": {"coordinates":[4.892122,52.374962],"type":"Point"}
}