{
  "type": "Feature",
  "properties": {
    "addr:full":"Lubeckweg 2 Groningen Groningen 9723 HE",
    "addr:housenumber":"2",
    "addr:postcode":"9723 he",
    "addr:street":"Lubeckweg",
    "iso:country":"NL",
    "sg:address":"Lubeckweg 2",
    "sg:city":"Groningen",
    "sg:orig_category":"Krantenuitgeverijen",
    "sg:phone":"+31 50 584 4444",
    "sg:postcode":"9723 HE",
    "sg:province":"Groningen",
    "wof:name":"Hazewinkel Pers",
    "wof:placetype":"venue"
},
  "geometry": {"coordinates":[6.590406,53.213078],"type":"Point"}
}