{
  "type": "Feature",
  "properties": {
    "addr:full":"Rijksweg 103 Gronsveld Limburg 6247 AC",
    "addr:housenumber":"103",
    "addr:postcode":"6247 ac",
    "addr:street":"Rijksweg",
    "iso:country":"NL",
    "sg:address":"Rijksweg 103",
    "sg:city":"Gronsveld",
    "sg:orig_category":"Zuivelproducten",
    "sg:phone":"+31 43 408 1424",
    "sg:postcode":"6247 AC",
    "sg:province":"Limburg",
    "wof:name":"Zuivelhandel Wolfs-Schreurs",
    "wof:placetype":"venue"
},
  "geometry": {"coordinates":[5.732339,50.809078],"type":"Point"}
}