{
  "type": "Feature",
  "properties": {
    "addr:full":"Oude Molenstraat 37 Assen Drenthe 9401 DB",
    "addr:housenumber":"37",
    "addr:postcode":"9401 db",
    "addr:street":"Oude Molenstraat",
    "iso:country":"NL",
    "sg:address":"Oude Molenstraat 37",
    "sg:city":"Assen",
    "sg:orig_category":"Juweliers",
    "sg:phone":"+31 592 312 348",
    "sg:postcode":"9401 DB",
    "sg:province":"Drenthe",
    "wof:name":"De Goudspecialist",
    "wof:placetype":"venue"
},
  "geometry": {"coordinates":[6.561438,52.996666],"type":"Point"}
}