{
  "type": "Feature",
  "properties": {
    "iso:country":"NL",
    "sg:address":"Hoogstr 47",
    "sg:city":"Werkendam",
    "sg:orig_category":"Kaas",
    "sg:phone":"+31 183 503 856",
    "sg:postcode":"4251 CJ",
    "sg:province":"Noord-Brabant",
    "wof:name":"Vers Shop",
    "wof:placetype":"venue"
},
  "geometry": {"coordinates":[4.8953170776,51.8083724976],"type":"Point"}
}