{
  "type": "Feature",
  "properties": {
    "iso:country":"NL",
    "sg:address":"Kerkstraat 39",
    "sg:city":"Haren Gn",
    "sg:orig_category":"Schilderwerk",
    "sg:phone":"+31 50 534 5562",
    "sg:postcode":"9751 BB",
    "sg:province":"Groningen",
    "wof:name":"Schildersbedrijf J Haverdings",
    "wof:placetype":"venue"
},
  "geometry": {"coordinates":[6.608705,53.173248],"type":"Point"}
}