{
  "type": "Feature",
  "properties": {
    "addr:full":"Lommerlust 29 Zeist Utrecht 3702 BT",
    "addr:housenumber":"29",
    "addr:postcode":"3702 bt",
    "addr:street":"Lommerlust",
    "iso:country":"NL",
    "sg:address":"Lommerlust 29",
    "sg:city":"Zeist",
    "sg:orig_category":"Public Relationbureaus",
    "sg:phone":"+31 30 693 0266",
    "sg:postcode":"3702 BT",
    "sg:province":"Utrecht",
    "wof:name":"Mvm Tekst Advies & Onderwijs",
    "wof:placetype":"venue"
},
  "geometry": {"coordinates":[5.236794,52.086212],"type":"Point"}
}