{
  "type": "Feature",
  "properties": {
    "addr:full":"Ryksstrwg 3A Den Hoorn Zh South Holland 2635 AC",
    "addr:housenumber":"3a",
    "addr:postcode":"2635 ac",
    "addr:street":"Ryksstrwg",
    "iso:country":"NL",
    "sg:address":"Ryksstrwg 3A",
    "sg:city":"Den Hoorn Zh",
    "sg:orig_category":"Fietsen En Bromfietsen",
    "sg:phone":"+31 15 257 2988",
    "sg:postcode":"2635 AC",
    "sg:province":"South Holland",
    "wof:name":"Sunder, Bromfietshandel",
    "wof:placetype":"venue"
},
  "geometry": {"coordinates":[4.331055,51.99958],"type":"Point"}
}