{
  "type": "Feature",
  "properties": {
    "addr:full":"Zandstraat 84 Beneden Leeuwen Gelderland 6658 CW",
    "addr:housenumber":"84",
    "addr:postcode":"6658 cw",
    "addr:street":"Zandstraat",
    "iso:country":"NL",
    "sg:address":"Zandstraat 84",
    "sg:city":"Beneden Leeuwen",
    "sg:orig_category":"Banken And Kredietinstellingen",
    "sg:phone":"+31 487 592 764",
    "sg:postcode":"6658 CW",
    "sg:province":"Gelderland",
    "wof:name":"Ing Bank",
    "wof:placetype":"venue"
},
  "geometry": {"coordinates":[5.51491,51.882244],"type":"Point"}
}