{
  "type": "Feature",
  "properties": {
    "addr:full":"Koerillen 5 Capelle A/D Ijssel Zuid-Holland 2904 VL",
    "addr:housenumber":"5;a / d",
    "addr:postcode":"2904 vl",
    "addr:street":"Koerillen",
    "iso:country":"NL",
    "sg:address":"Koerillen 5",
    "sg:city":"Capelle A/D Ijssel",
    "sg:classifiers":[
        {
            "category":"Professional",
            "subcategory":"Accounting & Tax Preparation",
            "type":"Services"
        }
    ],
    "sg:phone":"+31 10 450 0617",
    "sg:postcode":"2904 VL",
    "sg:province":"Zuid-Holland",
    "sg:tags":[
        "accountant"
    ],
    "wof:name":"Famuco Bv",
    "wof:placetype":"venue"
},
  "geometry": {"coordinates":[4.607197,51.931324],"type":"Point"}
}