{
  "type": "Feature",
  "properties": {
    "addr:full":"V Marnixln 37 Amersfoort Utrecht 3818 VA",
    "addr:housenumber":"37",
    "addr:postcode":"3818",
    "iso:country":"NL",
    "sg:address":"V Marnixln 37",
    "sg:city":"Amersfoort",
    "sg:orig_category":"Projectontwikkeling",
    "sg:phone":"+31 33 445 0480",
    "sg:postcode":"3818 VA",
    "sg:province":"Utrecht",
    "wof:name":"Hop Iv Bv",
    "wof:placetype":"venue"
},
  "geometry": {"coordinates":[5.386085,52.152325],"type":"Point"}
}