{
  "type": "Feature",
  "properties": {
    "addr:full":"Klipper 14 Velserbroek Noord-Holland 1991 MV",
    "addr:housenumber":"14",
    "addr:postcode":"1991 mv",
    "addr:street":"Klipper",
    "iso:country":"NL",
    "sg:address":"Klipper 14",
    "sg:city":"Velserbroek",
    "sg:orig_category":"Adviesbureaus Bedrijfsorganisatie",
    "sg:phone":"+31 23 539 1197",
    "sg:postcode":"1991 MV",
    "sg:province":"Noord-Holland",
    "sg:website":"http://www.buroparsifal.nl",
    "wof:name":"Buro Parsifal Training & Opleiding",
    "wof:placetype":"venue"
},
  "geometry": {"coordinates":[4.663725,52.432453],"type":"Point"}
}