{
  "type": "Feature",
  "properties": {
    "addr:full":"Cereshof 10 Maastricht Limburg 6215 VR",
    "addr:housenumber":"10",
    "addr:postcode":"6215 vr",
    "addr:street":"Cereshof",
    "iso:country":"NL",
    "sg:address":"Cereshof 10",
    "sg:city":"Maastricht",
    "sg:orig_category":"Verenigingen En Stichtingen",
    "sg:phone":"+31 43 347 5711",
    "sg:postcode":"6215 VR",
    "sg:province":"Limburg",
    "wof:name":"Melati, Sticht",
    "wof:placetype":"venue"
},
  "geometry": {"coordinates":[5.654115,50.839703],"type":"Point"}
}