{
  "type": "Feature",
  "properties": {
    "addr:full":"Broekheurnerweg 76 Haaksbergen Overijssel 7481 PZ",
    "addr:housenumber":"76",
    "addr:postcode":"7481 pz",
    "addr:street":"Broekheurnerweg",
    "iso:country":"NL",
    "sg:address":"Broekheurnerweg 76",
    "sg:city":"Haaksbergen",
    "sg:orig_category":"Juridische Dienstverlening",
    "sg:phone":"+31 53 569 6423",
    "sg:postcode":"7481 PZ",
    "sg:province":"Overijssel",
    "wof:name":"Mr H A M Kamphuis",
    "wof:placetype":"venue"
},
  "geometry": {"coordinates":[6.82766,52.14785],"type":"Point"}
}