{
  "type": "Feature",
  "properties": {
    "addr:full":"Boveneindsestraat 1 Kesteren Gelderland 4041 EH",
    "addr:housenumber":"1",
    "addr:postcode":"4041 eh",
    "addr:street":"Boveneindsestraat;Gelderland",
    "iso:country":"NL",
    "sg:address":"Boveneindsestraat 1",
    "sg:city":"Kesteren",
    "sg:orig_category":"Metaalbekleding And -Behandeling",
    "sg:phone":"+31 488 481 710",
    "sg:postcode":"4041 EH",
    "sg:province":"Gelderland",
    "wof:name":"D. Tijssen",
    "wof:placetype":"venue"
},
  "geometry": {"coordinates":[5.57741,51.935272],"type":"Point"}
}