{
  "type": "Feature",
  "properties": {
    "addr:full":"Schoonhovenseveer 3133 Groot Ammers Zuid-Holland 2964 GB",
    "addr:postcode":"3133;ammers;2964 gb",
    "addr:street":"Schoonhovenseveer;Groot",
    "iso:country":"NL",
    "sg:address":"Schoonhovenseveer 3133",
    "sg:city":"Groot Ammers",
    "sg:orig_category":"Adviesbureaus Bedrijfsorganisatie",
    "sg:phone":"+31 184 602 353",
    "sg:postcode":"2964 GB",
    "sg:province":"Zuid-Holland",
    "sg:website":"HTTP://www.shelterconsult.nl",
    "wof:name":"Shelter Bv",
    "wof:placetype":"venue"
},
  "geometry": {"coordinates":[4.85369,51.939999],"type":"Point"}
}