{
  "type": "Feature",
  "properties": {
    "addr:full":"Heggepad 48 Rotterdam Zuid-Holland 3075 TD",
    "addr:housenumber":"48",
    "addr:postcode":"3075 td",
    "addr:street":"Heggepad",
    "iso:country":"NL",
    "sg:address":"Heggepad 48",
    "sg:city":"Rotterdam",
    "sg:orig_category":"Meubelreparatie And -Restauratie",
    "sg:phone":"+31 10 419 1504",
    "sg:postcode":"3075 TD",
    "sg:province":"Zuid-Holland",
    "wof:name":"W Bulters",
    "wof:placetype":"venue"
},
  "geometry": {"coordinates":[4.50812,51.887295],"type":"Point"}
}