{
  "type": "Feature",
  "properties": {
    "addr:full":"Lewestr 59 Kloetinge Zeeland 4481 BC",
    "addr:housenumber":"59",
    "addr:postcode":"4481 bc",
    "addr:street":"Lewestr",
    "iso:country":"NL",
    "sg:address":"Lewestr 59",
    "sg:city":"Kloetinge",
    "sg:orig_category":"Vakantieverblijven",
    "sg:phone":"+31 113 223 042",
    "sg:postcode":"4481 BC",
    "sg:province":"Zeeland",
    "wof:name":"Texel-Zeeland",
    "wof:placetype":"venue"
},
  "geometry": {"coordinates":[3.909354,51.497631],"type":"Point"}
}