{
  "type": "Feature",
  "properties": {
    "addr:full":"Lyts Dk 20 Langweer Provincie Friesland 8525 GC",
    "addr:housenumber":"20",
    "addr:postcode":"8525 gc",
    "addr:street":"Lyts Dk;Provincie Friesland",
    "iso:country":"NL",
    "sg:address":"Lyts Dk 20",
    "sg:city":"Langweer",
    "sg:orig_category":"Voetbalverenigingen",
    "sg:phone":"+31 513 499 101",
    "sg:postcode":"8525 GC",
    "sg:province":"Provincie Friesland",
    "wof:name":"Langweer",
    "wof:placetype":"venue"
},
  "geometry": {"coordinates":[5.720212,52.956902],"type":"Point"}
}