{
  "type": "Feature",
  "properties": {
    "addr:full":"Velvewg 59 Enschede Overijssel 7533 XE",
    "addr:housenumber":"59",
    "addr:postcode":"7533 xe",
    "addr:street":"Velvewg",
    "iso:country":"NL",
    "sg:address":"Velvewg 59",
    "sg:city":"Enschede",
    "sg:orig_category":"Kappers",
    "sg:phone":"+31 53 431 6786",
    "sg:postcode":"7533 XE",
    "sg:province":"Overijssel",
    "wof:name":"Vandenberg, Rosita",
    "wof:placetype":"venue"
},
  "geometry": {"coordinates":[6.92012,52.220745],"type":"Point"}
}