{
  "type": "Feature",
  "properties": {
    "addr:full":"Hullerwg 44 Nunspeet Gelderland 8071 RN",
    "addr:housenumber":"44",
    "addr:postcode":"8071 rn",
    "addr:street":"Hullerwg;Gelderland",
    "iso:country":"NL",
    "sg:address":"Hullerwg 44",
    "sg:city":"Nunspeet",
    "sg:classifiers":[
        {
            "category":"Sports & Exercise",
            "subcategory":"Stables",
            "type":"Entertainment"
        }
    ],
    "sg:phone":"+31 6 53291758",
    "sg:postcode":"8071 RN",
    "sg:province":"Gelderland",
    "sg:tags":[
        "maneges"
    ],
    "wof:name":"Verdonk, Mieke",
    "wof:placetype":"venue"
},
  "geometry": {"coordinates":[5.776766,52.385082],"type":"Point"}
}