{
  "type": "Feature",
  "properties": {
    "iso:country":"NL",
    "sg:address":"Torenstraat 93",
    "sg:city":"'S Gravenhage",
    "sg:orig_category":"Werving And Selectie Van Tijdelijk Personeel And Uitzendkantoren",
    "sg:phone":"+31 70 392 1400",
    "sg:postcode":"2513 BP",
    "sg:province":"Zuid-Holland",
    "wof:name":"Iq Uitzendbureau",
    "wof:placetype":"venue"
},
  "geometry": {"coordinates":[4.3039669991,52.0787658691],"type":"Point"}
}