{
  "type": "Feature",
  "properties": {
    "addr:full":"Kerkuil 79 Emmen Drenthe 7827 GD",
    "addr:housenumber":"79",
    "addr:postcode":"7827 gd",
    "addr:street":"Kerkuil",
    "iso:country":"NL",
    "sg:address":"Kerkuil 79",
    "sg:city":"Emmen",
    "sg:orig_category":"Adviesbureaus Bedrijfsorganisatie",
    "sg:phone":"+31 591 673 128",
    "sg:postcode":"7827 GD",
    "sg:province":"Drenthe",
    "wof:name":"Jonge Logistiek Advies, De",
    "wof:placetype":"venue"
},
  "geometry": {"coordinates":[6.890521,52.755711],"type":"Point"}
}