{
  "type": "Feature",
  "properties": {
    "iso:country":"NL",
    "sg:address":"Marktplein 49",
    "sg:city":"Broek Op Langedijk",
    "sg:orig_category":"Kappers",
    "sg:phone":"+31 226 316 374",
    "sg:postcode":"1721 CK",
    "sg:province":"Noord-Holland",
    "wof:name":"Kapsalon Knip-In",
    "wof:placetype":"venue"
},
  "geometry": {"coordinates":[4.8038511276,52.6788482666],"type":"Point"}
}