{
  "type": "Feature",
  "properties": {
    "addr:full":"Schutsestr 4 Prinsenbeek Noord-Brabant 4841 EE",
    "addr:housenumber":"4",
    "addr:postcode":"4841 ee",
    "addr:street":"Schutsestr",
    "iso:country":"NL",
    "sg:address":"Schutsestr 4",
    "sg:city":"Prinsenbeek",
    "sg:orig_category":"Adviesbureaus Bedrijfsorganisatie",
    "sg:phone":"+31 76 542 3110",
    "sg:postcode":"4841 EE",
    "sg:province":"Noord-Brabant",
    "wof:name":"Noordhoek",
    "wof:placetype":"venue"
},
  "geometry": {"coordinates":[4.709918,51.602448],"type":"Point"}
}