{
  "type": "Feature",
  "properties": {
    "addr:full":"Dolphynstr 39 Hoek Van Holland Zuid-Holland 3151 RC",
    "addr:housenumber":"39",
    "addr:postcode":"3151 rc",
    "addr:street":"Dolphynstr",
    "iso:country":"NL",
    "sg:address":"Dolphynstr 39",
    "sg:city":"Hoek Van Holland",
    "sg:orig_category":"Postorderbedrijven",
    "sg:phone":"+31 174 310 285",
    "sg:postcode":"3151 RC",
    "sg:province":"Zuid-Holland",
    "sg:website":"http://www.dvdtheater.nl",
    "wof:name":"Dvd Theater",
    "wof:placetype":"venue"
},
  "geometry": {"coordinates":[4.143446,51.976322],"type":"Point"}
}