{
  "type": "Feature",
  "properties": {
    "addr:full":"Sondelstr 4 Emmeloord Flevoland 8304 GA",
    "addr:housenumber":"4",
    "addr:postcode":"8304 ga",
    "addr:street":"Sondelstr;Flevoland",
    "iso:country":"NL",
    "sg:address":"Sondelstr 4",
    "sg:city":"Emmeloord",
    "sg:orig_category":"Scholen Voor Basisonderwijs",
    "sg:phone":"+31 527 613 253",
    "sg:postcode":"8304 GA",
    "sg:province":"Flevoland",
    "wof:name":"Kompas Sch Met De Bijbel, 'T",
    "wof:placetype":"venue"
},
  "geometry": {"coordinates":[5.7638030052,52.7037124634],"type":"Point"}
}