{
  "type": "Feature",
  "properties": {
    "iso:country":"NL",
    "sg:address":"Looerheideweg 7",
    "sg:city":"Bergeyk",
    "sg:orig_category":"Landbouwmachines Gh",
    "sg:phone":"+31 497 541 365",
    "sg:postcode":"5571 TZ",
    "sg:province":"North Brabant",
    "wof:name":"Frakoo",
    "wof:placetype":"venue"
},
  "geometry": {"coordinates":[5.361301,51.29274],"type":"Point"}
}