{
  "type": "Feature",
  "properties": {
    "addr:full":"Uranusstraat 8A Alphen A/D Rijn Zuid-Holland 2402 AG",
    "addr:housenumber":"8a",
    "addr:postcode":"2402",
    "addr:street":"Uranusstraat",
    "iso:country":"NL",
    "sg:address":"Uranusstraat 8A",
    "sg:city":"Alphen A/D Rijn",
    "sg:orig_category":"Beautyfarms And Sauna'S",
    "sg:phone":"+31 172 445 600",
    "sg:postcode":"2402 AG",
    "sg:province":"Zuid-Holland",
    "wof:name":"Fysiotherapie De Driehoorne",
    "wof:placetype":"venue"
},
  "geometry": {"coordinates":[4.666414,52.142494],"type":"Point"}
}