{
  "type": "Feature",
  "properties": {
    "addr:full":"D Hoogenraadstr 16 S Gravenhage South Holland 2586 TH",
    "addr:housenumber":"16",
    "addr:postcode":"2586 th",
    "addr:street":"S Gravenhage",
    "iso:country":"NL",
    "sg:address":"D Hoogenraadstr 16",
    "sg:city":"S Gravenhage",
    "sg:classifiers":[
        {
            "category":"Personal",
            "subcategory":"Nail Salon",
            "type":"Services"
        }
    ],
    "sg:phone":"+31 70 352 3180",
    "sg:postcode":"2586 TH",
    "sg:province":"South Holland",
    "sg:tags":[
        "pedicure"
    ],
    "wof:name":"Seventer, M Van",
    "wof:placetype":"venue"
},
  "geometry": {"coordinates":[4.277215,52.10672],"type":"Point"}
}