{
  "type": "Feature",
  "properties": {
    "addr:full":"Zaaiwaard 3 Aalst Gld Gelderland 5308 JK",
    "addr:housenumber":"3",
    "addr:postcode":"5308 jk",
    "addr:street":"Zaaiwaard;Gld Gelderland",
    "iso:country":"NL",
    "sg:address":"Zaaiwaard 3",
    "sg:city":"Aalst Gld",
    "sg:orig_category":"Kampeerterreinen",
    "sg:phone":"+31 418 673 232",
    "sg:postcode":"5308 JK",
    "sg:province":"Gelderland",
    "wof:name":"Camping De Maasplas",
    "wof:placetype":"venue"
},
  "geometry": {"coordinates":[5.113424778,51.7848854065],"type":"Point"}
}