{
  "type": "Feature",
  "properties": {
    "addr:full":"Noorddijk 81 Maassluis Zuid-Holland 3142 EC",
    "addr:housenumber":"81",
    "addr:postcode":"3142 ec",
    "addr:street":"Noorddijk",
    "iso:country":"NL",
    "sg:address":"Noorddijk 81",
    "sg:city":"Maassluis",
    "sg:orig_category":"Glaszetten",
    "sg:phone":"+31 10 590 0681",
    "sg:postcode":"3142 EC",
    "sg:province":"Zuid-Holland",
    "wof:name":"De Hardglas Specialist",
    "wof:placetype":"venue"
},
  "geometry": {"coordinates":[4.24915,51.92477],"type":"Point"}
}