{
  "type": "Feature",
  "properties": {
    "iso:country":"NL",
    "sg:address":"Vossenberg 12A",
    "sg:city":"Breda",
    "sg:orig_category":"Hydrocultuur",
    "sg:phone":"+31 76 571 2917",
    "sg:postcode":"4825 BH",
    "sg:province":"Noord-Brabant",
    "wof:name":"Anjer, De",
    "wof:placetype":"venue"
},
  "geometry": {"coordinates":[4.770742,51.612793],"type":"Point"}
}