{
  "type": "Feature",
  "properties": {
    "addr:full":"Hoofdstraat 126 Herveld Gelderland 6674 BD",
    "addr:housenumber":"126",
    "addr:postcode":"6674 bd",
    "addr:street":"Hoofdstraat;Gelderland",
    "iso:country":"NL",
    "sg:address":"Hoofdstraat 126",
    "sg:city":"Herveld",
    "sg:orig_category":"Banken And Kredietinstellingen",
    "sg:phone":"+31 488 452 575",
    "sg:postcode":"6674 BD",
    "sg:province":"Gelderland",
    "wof:name":"Rabobank",
    "wof:placetype":"venue"
},
  "geometry": {"coordinates":[5.737116,51.909866],"type":"Point"}
}