{
  "type": "Feature",
  "properties": {
    "addr:full":"Korte Marktstraat 3 Veghel Noord-Brabant 5461 KJ",
    "addr:housenumber":"3",
    "addr:postcode":"5461 kj",
    "addr:street":"Korte Marktstraat",
    "iso:country":"NL",
    "sg:address":"Korte Marktstraat 3",
    "sg:city":"Veghel",
    "sg:orig_category":"Discountwinkels",
    "sg:phone":"+31 413 310 131",
    "sg:postcode":"5461 KJ",
    "sg:province":"Noord-Brabant",
    "wof:name":"Zeeman Textielsupers",
    "wof:placetype":"venue"
},
  "geometry": {"coordinates":[5.5417499542,51.6172218323],"type":"Point"}
}