{
  "type": "Feature",
  "properties": {
    "addr:full":"Danslaan 72 Almere NL. 1326 PL",
    "addr:housenumber":"72",
    "addr:postcode":"1326 pl",
    "addr:street":"Danslaan;Nl.",
    "iso:country":"NL",
    "sg:address":"Danslaan 72",
    "sg:city":"Almere",
    "sg:orig_category":"Kinderopvang Behalve Thuis",
    "sg:phone":"+31 36 523 1058",
    "sg:postcode":"1326 PL",
    "sg:province":"NL.",
    "wof:name":"Ska Buitenschoolse Opvang Joepie-Joepie",
    "wof:placetype":"venue"
},
  "geometry": {"coordinates":[5.257213,52.364799],"type":"Point"}
}