{
  "type": "Feature",
  "properties": {
    "addr:full":"Jacques Oppenheimstraat 7 Tilburg Noord-Brabant 5042 NM",
    "addr:housenumber":"7",
    "addr:postcode":"5042",
    "addr:street":"Jacques Oppenheimstraat",
    "iso:country":"NL",
    "sg:address":"Jacques Oppenheimstraat 7",
    "sg:city":"Tilburg",
    "sg:classifiers":[
        {
            "category":"Communications",
            "subcategory":"Television Station",
            "type":"Services"
        }
    ],
    "sg:phone":"+31 13 467 0788",
    "sg:postcode":"5042 NM",
    "sg:province":"Noord-Brabant",
    "sg:tags":[
        "video",
        "audio",
        "verhuur"
    ],
    "wof:name":"Svo Familievideotheek Bv",
    "wof:placetype":"venue"
},
  "geometry": {"coordinates":[5.054671,51.568985],"type":"Point"}
}