{
  "type": "Feature",
  "properties": {
    "addr:full":"Rechterstr 19 Boxtel Noord-Brabant 5281 BS",
    "addr:housenumber":"19",
    "addr:postcode":"5281 bs",
    "addr:street":"Rechterstr",
    "iso:country":"NL",
    "sg:address":"Rechterstr 19",
    "sg:city":"Boxtel",
    "sg:orig_category":"Boeken En Tijdschriften",
    "sg:phone":"+31 411 673 577",
    "sg:postcode":"5281 BS",
    "sg:province":"Noord-Brabant",
    "sg:website":"http://www.bruna.nl/",
    "wof:name":"Bruna",
    "wof:placetype":"venue"
},
  "geometry": {"coordinates":[5.326374,51.588001],"type":"Point"}
}