{
  "type": "Feature",
  "properties": {
    "iso:country":"NL",
    "sg:address":"Schouwwg 72 Johannahuis",
    "sg:city":"Wassenaar",
    "sg:orig_category":"Verenigingen En Stichtingen",
    "sg:phone":"+31 70 517 9041",
    "sg:postcode":"2243 BJ",
    "sg:province":"Zuid-Holland",
    "wof:name":"Wilhelmina Alida, Sticht",
    "wof:placetype":"venue"
},
  "geometry": {"coordinates":[4.393863,52.14307],"type":"Point"}
}