{
  "type": "Feature",
  "properties": {
    "addr:full":"Dieterenstraat 2 Stein Lb Missouri 6171 JK",
    "addr:housenumber":"2",
    "addr:postcode":"6171 jk",
    "addr:street":"Dieterenstraat",
    "iso:country":"NL",
    "sg:address":"Dieterenstraat 2",
    "sg:city":"Stein Lb",
    "sg:classifiers":[
        {
            "category":"Education",
            "subcategory":"Preschool",
            "type":"Public Place"
        }
    ],
    "sg:phone":"+31 46 433 2938",
    "sg:postcode":"6171 JK",
    "sg:province":"Missouri",
    "sg:tags":[
        "kleuteronderwijs",
        "basis-"
    ],
    "wof:name":"Openbare Basisschool De Maaskei",
    "wof:placetype":"venue"
},
  "geometry": {"coordinates":[-93.129936,36.705662],"type":"Point"}
}