{
  "type": "Feature",
  "properties": {
    "iso:country":"NL",
    "sg:address":"Viergang 145",
    "sg:city":"Mijdrecht",
    "sg:classifiers":[
        {
            "category":"Professional",
            "subcategory":"Accounting & Tax Preparation",
            "type":"Services"
        }
    ],
    "sg:phone":"+31 297 362 733",
    "sg:postcode":"3642 ZT",
    "sg:province":"Utrecht",
    "sg:tags":[
        "accountant"
    ],
    "wof:name":"Kooijman",
    "wof:placetype":"venue"
},
  "geometry": {"coordinates":[4.860793,52.196182],"type":"Point"}
}