{
  "type": "Feature",
  "properties": {
    "addr:full":"Horatiusstr 43 Heerlen Limburg 6417 TN",
    "addr:housenumber":"43",
    "addr:postcode":"6417",
    "addr:street":"Horatiusstr",
    "iso:country":"NL",
    "sg:address":"Horatiusstr 43",
    "sg:city":"Heerlen",
    "sg:orig_category":"Luchtbehandelings- Apparaten",
    "sg:phone":"+31 45 574 0915",
    "sg:postcode":"6417 TN",
    "sg:province":"Limburg",
    "sg:website":"http://www.houbenagency.com",
    "wof:name":"Houben Agency",
    "wof:placetype":"venue"
},
  "geometry": {"coordinates":[5.978986,50.876434],"type":"Point"}
}