{
  "type": "Feature",
  "properties": {
    "addr:full":"Grienden 14 Leusden Utrecht 3831 HR",
    "addr:housenumber":"14",
    "addr:postcode":"3831 hr",
    "addr:street":"Grienden",
    "iso:country":"NL",
    "sg:address":"Grienden 14",
    "sg:city":"Leusden",
    "sg:orig_category":"Loopbaanbegeleiding",
    "sg:phone":"+31 33 433 2211",
    "sg:postcode":"3831 HR",
    "sg:province":"Utrecht",
    "wof:name":"Cocky Swinkels",
    "wof:placetype":"venue"
},
  "geometry": {"coordinates":[5.444645,52.132484],"type":"Point"}
}