{
  "type": "Feature",
  "properties": {
    "addr:full":"Duikerweg 7 Waalwijk Noord-Brabant 5145 NV",
    "addr:housenumber":"7",
    "addr:postcode":"5145 nv",
    "addr:street":"Duikerweg",
    "iso:country":"NL",
    "sg:address":"Duikerweg 7",
    "sg:city":"Waalwijk",
    "sg:orig_category":"Wegen And Sportterreinen",
    "sg:phone":"+31 416 650 274",
    "sg:postcode":"5145 NV",
    "sg:province":"Noord-Brabant",
    "wof:name":"Aannemingsbedrijf Karbet Bv",
    "wof:placetype":"venue"
},
  "geometry": {"coordinates":[5.0493311882,51.7011260986],"type":"Point"}
}