{
  "type": "Feature",
  "properties": {
    "addr:full":"De Hermey 2 Veghel North Brabant 5461 BD",
    "addr:housenumber":"2",
    "addr:postcode":"5461 bd",
    "addr:street":"De Hermey",
    "iso:country":"NL",
    "sg:address":"De Hermey 2",
    "sg:city":"Veghel",
    "sg:orig_category":"Adviesbureaus Bedrijfsorganisatie",
    "sg:phone":"+31 413 310 220",
    "sg:postcode":"5461 BD",
    "sg:province":"North Brabant",
    "wof:name":"Vm Bv",
    "wof:placetype":"venue"
},
  "geometry": {"coordinates":[5.541603,51.617371],"type":"Point"}
}