{
  "type": "Feature",
  "properties": {
    "addr:full":"Sophiastraat 12 Breda North Brabant 4811 EK",
    "addr:housenumber":"12",
    "addr:postcode":"4811 ek",
    "addr:street":"Sophiastraat",
    "iso:country":"NL",
    "sg:address":"Sophiastraat 12",
    "sg:city":"Breda",
    "sg:orig_category":"Kappers",
    "sg:phone":"+31 76 520 3250",
    "sg:postcode":"4811 EK",
    "sg:province":"North Brabant",
    "wof:name":"Dames- En Herenkapsalon De Jong",
    "wof:placetype":"venue"
},
  "geometry": {"coordinates":[4.7846431732,51.5920753479],"type":"Point"}
}