{
  "type": "Feature",
  "properties": {
    "iso:country":"NL",
    "sg:address":"Klokstraat 8",
    "sg:city":"Aarle Rixtel",
    "sg:orig_category":"Juweliers",
    "sg:phone":"+31 492 381 226",
    "sg:postcode":"5735 GN",
    "sg:province":"North Brabant",
    "wof:name":"Firma W F Vd Kerkhof",
    "wof:placetype":"venue"
},
  "geometry": {"coordinates":[5.638031,51.508549],"type":"Point"}
}