{
  "type": "Feature",
  "properties": {
    "addr:full":"Het Meuke 39 Haaksbergen Overijssel 7481 JH",
    "addr:housenumber":"39",
    "addr:postcode":"7481 jh",
    "addr:street":"Het Meuke",
    "iso:country":"NL",
    "sg:address":"Het Meuke 39",
    "sg:city":"Haaksbergen",
    "sg:orig_category":"Verpakkingsbedrijven",
    "sg:phone":"+31 53 574 1600",
    "sg:postcode":"7481 JH",
    "sg:province":"Overijssel",
    "wof:name":"Orwol",
    "wof:placetype":"venue"
},
  "geometry": {"coordinates":[6.737351,52.154644],"type":"Point"}
}