{
  "type": "Feature",
  "properties": {
    "iso:country":"NL",
    "sg:address":"Molenstr 15-17",
    "sg:city":"Scheemda",
    "sg:orig_category":"Kinderkleding",
    "sg:phone":"+31 597 593 454",
    "sg:postcode":"9679 KA",
    "sg:province":"Groningen",
    "wof:name":"Multistyle",
    "wof:placetype":"venue"
},
  "geometry": {"coordinates":[6.969081,53.178562],"type":"Point"}
}