{
  "type": "Feature",
  "properties": {
    "addr:full":"Molenstr 15-17 Scheemda Groningen 9679 KA",
    "addr:housenumber":"15-17",
    "addr:postcode":"9679 ka",
    "addr:street":"Molenstr",
    "iso:country":"NL",
    "sg:address":"Molenstr 15-17",
    "sg:city":"Scheemda",
    "sg:orig_category":"Kinderkleding",
    "sg:phone":"+31 597 593 454",
    "sg:postcode":"9679 KA",
    "sg:province":"Groningen",
    "wof:name":"Multistyle",
    "wof:placetype":"venue"
},
  "geometry": {"coordinates":[6.969081,53.178562],"type":"Point"}
}