{
  "type": "Feature",
  "properties": {
    "addr:full":"Mantingerbrink 87 Emmen Drenthe 7812 MB",
    "addr:housenumber":"87",
    "addr:postcode":"7812 mb",
    "addr:street":"Mantingerbrink",
    "iso:country":"NL",
    "sg:address":"Mantingerbrink 87",
    "sg:city":"Emmen",
    "sg:orig_category":"Logopedisten",
    "sg:phone":"+31 591 641 296",
    "sg:postcode":"7812 MB",
    "sg:province":"Drenthe",
    "wof:name":"Sione Molenaar",
    "wof:placetype":"venue"
},
  "geometry": {"coordinates":[6.88905,52.768177],"type":"Point"}
}