{
  "type": "Feature",
  "properties": {
    "addr:full":"Dorpsstr 48 Harmelen Utrecht 3481 EM",
    "addr:housenumber":"48",
    "addr:postcode":"3481 em",
    "addr:street":"Dorpsstr",
    "iso:country":"NL",
    "sg:address":"Dorpsstr 48",
    "sg:city":"Harmelen",
    "sg:orig_category":"Fotoreportages",
    "sg:phone":"+31 348 441 043",
    "sg:postcode":"3481 EM",
    "sg:province":"Utrecht",
    "wof:name":"Lique",
    "wof:placetype":"venue"
},
  "geometry": {"coordinates":[4.962831,52.091648],"type":"Point"}
}