{
  "type": "Feature",
  "properties": {
    "iso:country":"NL",
    "sg:address":"Zuideruitweg 64",
    "sg:city":"Wijdenes",
    "sg:orig_category":"Kampeerterreinen",
    "sg:phone":"+31 229 501 435",
    "sg:postcode":"1608 EX",
    "sg:province":"Noord-Holland",
    "wof:name":"Camping Het Hof",
    "wof:placetype":"venue"
},
  "geometry": {"coordinates":[5.1548290253,52.6258468628],"type":"Point"}
}