{
  "type": "Feature",
  "properties": {
    "addr:full":"Schoutenstr 6 Alkmaar Noord-Holland 1811 HD",
    "addr:housenumber":"6",
    "addr:postcode":"1811 hd",
    "addr:street":"Schoutenstr",
    "iso:country":"NL",
    "sg:address":"Schoutenstr 6",
    "sg:city":"Alkmaar",
    "sg:orig_category":"Glas, Porselein En Aardewerk",
    "sg:phone":"+31 72 512 0321",
    "sg:postcode":"1811 HD",
    "sg:province":"Noord-Holland",
    "wof:name":"Porceleyn Huys Bv, Het",
    "wof:placetype":"venue"
},
  "geometry": {"coordinates":[4.745069,52.631939],"type":"Point"}
}