{
  "type": "Feature",
  "properties": {
    "iso:country":"NL",
    "sg:address":"Anna Paulownastraat 37",
    "sg:city":"'S Gravenhage",
    "sg:orig_category":"Antiekzaken",
    "sg:phone":"+31 70 346 6570",
    "sg:postcode":"2518 BB",
    "sg:province":"Zuid-Holland",
    "wof:name":"Rondom 1920",
    "wof:placetype":"venue"
},
  "geometry": {"coordinates":[4.3005,52.083958],"type":"Point"}
}