{
  "type": "Feature",
  "properties": {
    "addr:full":"Diestlaan 14 Eindhoven North Brabant 5628 TV",
    "addr:housenumber":"14",
    "addr:postcode":"5628 tv",
    "addr:street":"Diestlaan",
    "iso:country":"NL",
    "sg:address":"Diestlaan 14",
    "sg:city":"Eindhoven",
    "sg:orig_category":"Technische Studies And Onderzoek",
    "sg:phone":"+31 40 248 1025",
    "sg:postcode":"5628 TV",
    "sg:province":"North Brabant",
    "wof:name":"Orbit Design Services",
    "wof:placetype":"venue"
},
  "geometry": {"coordinates":[5.48042,51.480602],"type":"Point"}
}