{
  "type": "Feature",
  "properties": {
    "addr:full":"Stationsln 60 Nunspeet Gelderland 8071 CN",
    "addr:housenumber":"60",
    "addr:postcode":"8071 cn",
    "addr:street":"Stationsln;Gelderland",
    "iso:country":"NL",
    "sg:address":"Stationsln 60",
    "sg:city":"Nunspeet",
    "sg:orig_category":"Schoenen",
    "sg:phone":"+31 341 252 175",
    "sg:postcode":"8071 CN",
    "sg:province":"Gelderland",
    "wof:name":"Kamp",
    "wof:placetype":"venue"
},
  "geometry": {"coordinates":[5.772205,52.374981],"type":"Point"}
}