{
  "type": "Feature",
  "properties": {
    "addr:full":"Mienterglop 11 De Koog Noord-Holland 1796 MR",
    "addr:housenumber":"11",
    "addr:postcode":"1796 mr",
    "addr:street":"Mienterglop",
    "iso:country":"NL",
    "sg:address":"Mienterglop 11",
    "sg:city":"De Koog",
    "sg:orig_category":"Vakantieverblijven",
    "sg:phone":"+31 222 317 280",
    "sg:postcode":"1796 MR",
    "sg:province":"Noord-Holland",
    "wof:name":"Mantje-Bonne, A C",
    "wof:placetype":"venue"
},
  "geometry": {"coordinates":[4.7738451958,53.1011924744],"type":"Point"}
}