{
  "type": "Feature",
  "properties": {
    "addr:full":"Dykstr 43B Rotterdam Zuid-Holland 3061 TC",
    "addr:housenumber":"43b",
    "addr:postcode":"3061 tc",
    "addr:street":"Dykstr",
    "iso:country":"NL",
    "sg:address":"Dykstr 43B",
    "sg:city":"Rotterdam",
    "sg:orig_category":"Autorijscholen",
    "sg:phone":"+31 10 412 1735",
    "sg:postcode":"3061 TC",
    "sg:province":"Zuid-Holland",
    "wof:name":"Relax",
    "wof:placetype":"venue"
},
  "geometry": {"coordinates":[4.50434,51.927422],"type":"Point"}
}