{
  "type": "Feature",
  "properties": {
    "addr:full":"Hulstakker 2 Baarle Nassau Noord-Brabant 5111 XN",
    "addr:housenumber":"2",
    "addr:postcode":"5111 xn",
    "addr:street":"Hulstakker",
    "iso:country":"NL",
    "sg:address":"Hulstakker 2",
    "sg:city":"Baarle Nassau",
    "sg:orig_category":"Elektrotechnische Apparatuur - Fabrieken En Groothandel",
    "sg:phone":"+31 13 507 7162",
    "sg:postcode":"5111 XN",
    "sg:province":"Noord-Brabant",
    "wof:name":"Vermeer, J",
    "wof:placetype":"venue"
},
  "geometry": {"coordinates":[4.9296078682,51.4507331848],"type":"Point"}
}