{
  "type": "Feature",
  "properties": {
    "addr:full":"Houtln 141 Nymegen Gelderland 6525 ZD",
    "addr:housenumber":"141",
    "addr:postcode":"6525 zd",
    "addr:street":"Nymegen Gelderland",
    "iso:country":"NL",
    "sg:address":"Houtln 141",
    "sg:city":"Nymegen",
    "sg:orig_category":"Artsen - Huisartsen",
    "sg:phone":"+31 24 355 3562",
    "sg:postcode":"6525 ZD",
    "sg:province":"Gelderland",
    "wof:name":"Nuyens, A M J",
    "wof:placetype":"venue"
},
  "geometry": {"coordinates":[5.83296,51.842651],"type":"Point"}
}