{
  "type": "Feature",
  "properties": {
    "addr:full":"Birkholm 26 Hoofddorp North Holland 2133 CE",
    "addr:housenumber":"26",
    "addr:postcode":"2133 ce",
    "addr:street":"Birkholm",
    "iso:country":"NL",
    "sg:address":"Birkholm 26",
    "sg:city":"Hoofddorp",
    "sg:orig_category":"Koeriersdiensten",
    "sg:phone":"+31 23 563 0135",
    "sg:postcode":"2133 CE",
    "sg:province":"North Holland",
    "wof:name":"A.R.S.P. Koeriers",
    "wof:placetype":"venue"
},
  "geometry": {"coordinates":[4.667447,52.306911],"type":"Point"}
}