{
  "type": "Feature",
  "properties": {
    "addr:full":"Kl Drift 128A Hilversum Noord-Holland 1221 KC",
    "addr:housenumber":"128a",
    "addr:postcode":"1221 kc",
    "addr:street":"Kl Drift",
    "iso:country":"NL",
    "sg:address":"Kl Drift 128A",
    "sg:city":"Hilversum",
    "sg:orig_category":"Verenigingen En Stichtingen",
    "sg:phone":"+31 35 642 3322",
    "sg:postcode":"1221 KC",
    "sg:province":"Noord-Holland",
    "wof:name":"Sis, Sticht",
    "wof:placetype":"venue"
},
  "geometry": {"coordinates":[5.189955,52.226292],"type":"Point"}
}