{
  "type": "Feature",
  "properties": {
    "addr:full":"Heesweg 26 Raalte Overijssel 8102 HJ",
    "addr:housenumber":"26",
    "addr:postcode":"8102 hj",
    "addr:street":"Heesweg",
    "iso:country":"NL",
    "sg:address":"Heesweg 26",
    "sg:city":"Raalte",
    "sg:orig_category":"Meubelreparatie And -Restauratie",
    "sg:phone":"+31 572 357 885",
    "sg:postcode":"8102 HJ",
    "sg:province":"Overijssel",
    "wof:name":"Meubelstoffeerderij Helmond",
    "wof:placetype":"venue"
},
  "geometry": {"coordinates":[6.280208,52.377888],"type":"Point"}
}