{
  "type": "Feature",
  "properties": {
    "iso:country":"NL",
    "sg:address":"Rotterdamse Rijweg 143",
    "sg:city":"Rotterdam",
    "sg:orig_category":"Architecten",
    "sg:phone":"+31 10 415 8845",
    "sg:postcode":"3042 AN",
    "sg:province":"Zuid-Holland",
    "wof:name":"Architectenbureau John Fahmel Bv",
    "wof:placetype":"venue"
},
  "geometry": {"coordinates":[4.427839,51.934223],"type":"Point"}
}