{
  "type": "Feature",
  "properties": {
    "addr:full":"Past Somstr 2 Epe Gelderland 8162 AK",
    "addr:housenumber":"2",
    "addr:postcode":"8162 ak",
    "addr:street":"Gelderland",
    "iso:country":"NL",
    "sg:address":"Past Somstr 2",
    "sg:city":"Epe",
    "sg:classifiers":[
        {
            "category":"Professional",
            "subcategory":"Accounting & Tax Preparation",
            "type":"Services"
        }
    ],
    "sg:phone":"+31 578 677 377",
    "sg:postcode":"8162 AK",
    "sg:province":"Gelderland",
    "sg:tags":[
        "accountant",
        "en",
        "-kantoren",
        "register-"
    ],
    "wof:name":"Huffelen & Meenink, Van",
    "wof:placetype":"venue"
},
  "geometry": {"coordinates":[5.984016,52.349697],"type":"Point"}
}