{
  "type": "Feature",
  "properties": {
    "iso:country":"NL",
    "sg:address":"Kerkstr 1A",
    "sg:city":"Noordwyk Zh",
    "sg:orig_category":"Huishoudelijke Apparaten En Artikelen",
    "sg:phone":"+31 71 361 6979",
    "sg:postcode":"2201 KK",
    "sg:province":"Zuid-Holland",
    "wof:name":"Fair Price",
    "wof:placetype":"venue"
},
  "geometry": {"coordinates":[4.447704,52.234268],"type":"Point"}
}