{
  "type": "Feature",
  "properties": {
    "iso:country":"NL",
    "sg:address":"Gasthuisstraat 40",
    "sg:city":"Haarlem",
    "sg:orig_category":"Loodgieterswerk, Verwarming And Sanitaire Installaties",
    "sg:phone":"+31 23 531 4849",
    "sg:postcode":"2011 XP",
    "sg:province":"North Holland",
    "wof:name":"J.M. Honschoten",
    "wof:placetype":"venue"
},
  "geometry": {"coordinates":[4.631077,52.379978],"type":"Point"}
}