{
  "type": "Feature",
  "properties": {
    "addr:full":"Koldingwg 14 Groningen Groningen 9723 HK",
    "addr:housenumber":"14",
    "addr:postcode":"9723 hk",
    "addr:street":"Koldingwg",
    "iso:country":"NL",
    "sg:address":"Koldingwg 14",
    "sg:city":"Groningen",
    "sg:orig_category":"Autopoetsbedrijven",
    "sg:phone":"+31 50 549 0705",
    "sg:postcode":"9723 HK",
    "sg:province":"Groningen",
    "sg:website":"http://www.totalwash.nl",
    "wof:name":"Total Wash",
    "wof:placetype":"venue"
},
  "geometry": {"coordinates":[6.606978,53.22036],"type":"Point"}
}