{
  "type": "Feature",
  "properties": {
    "addr:full":"St Sebastiaanstr 48 Oss Virginia 5341 LH",
    "addr:housenumber":"48",
    "addr:postcode":"5341 lh",
    "iso:country":"NL",
    "sg:address":"St Sebastiaanstr 48",
    "sg:city":"Oss",
    "sg:orig_category":"Kappers",
    "sg:phone":"+31 412 640 222",
    "sg:postcode":"5341 LH",
    "sg:province":"Virginia",
    "wof:name":"Adriaansen, Hairfashion Marco",
    "wof:placetype":"venue"
},
  "geometry": {"coordinates":[-77.2352142334,38.3125991821],"type":"Point"}
}