{
  "type": "Feature",
  "properties": {
    "addr:full":"Julianapln 3 S Hertogenbosch Noord-Brabant 5211 BA",
    "addr:housenumber":"3",
    "addr:postcode":"5211 ba",
    "addr:street":"Julianapln",
    "iso:country":"NL",
    "sg:address":"Julianapln 3",
    "sg:city":"S Hertogenbosch",
    "sg:orig_category":"Administratie- En Boekhoudkantoren",
    "sg:phone":"+31 73 614 6663",
    "sg:postcode":"5211 BA",
    "sg:province":"Noord-Brabant",
    "wof:name":"Adoron Bv",
    "wof:placetype":"venue"
},
  "geometry": {"coordinates":[5.295208,51.688847],"type":"Point"}
}