{
  "type": "Feature",
  "properties": {
    "addr:full":"Papaverstr 26 Volendam CN. 1131 HK",
    "addr:housenumber":"26",
    "addr:postcode":"1131 hk",
    "addr:street":"Papaverstr;Cn.",
    "iso:country":"NL",
    "sg:address":"Papaverstr 26",
    "sg:city":"Volendam",
    "sg:orig_category":"Machinefabrieken",
    "sg:phone":"+31 299 363 562",
    "sg:postcode":"1131 HK",
    "sg:province":"CN.",
    "wof:name":"Noord Amsterdamse Machinefabriek Bv",
    "wof:placetype":"venue"
},
  "geometry": {"coordinates":[114.153542,22.411249],"type":"Point"}
}