{
  "type": "Feature",
  "properties": {
    "addr:full":"Hoge Nieuwstraat 20 'S Gravenhage South Holland 2514 EL",
    "addr:housenumber":"20",
    "addr:postcode":"2514 el",
    "addr:street":"Hoge Nieuwstraat;' S Gravenhage",
    "iso:country":"NL",
    "sg:address":"Hoge Nieuwstraat 20",
    "sg:city":"'S Gravenhage",
    "sg:orig_category":"Grafologen, Handlezers And Helderzienden",
    "sg:phone":"+31 70 362 2064",
    "sg:postcode":"2514 EL",
    "sg:province":"South Holland",
    "wof:name":"Grafologisch Bur Joca Vd Leest",
    "wof:placetype":"venue"
},
  "geometry": {"coordinates":[4.31251,52.081673],"type":"Point"}
}