{
  "type": "Feature",
  "properties": {
    "iso:country":"NL",
    "sg:address":"Pleywg 59",
    "sg:city":"Heerlen",
    "sg:orig_category":"Beeldende Kunstenaars",
    "sg:phone":"+31 45 572 1568",
    "sg:postcode":"6415 RE",
    "sg:province":"Limburg",
    "sg:website":"http://www.sjef-dolmans.com",
    "wof:name":"Sjef Dolmans",
    "wof:placetype":"venue"
},
  "geometry": {"coordinates":[5.98098,50.885506],"type":"Point"}
}