{
  "type": "Feature",
  "properties": {
    "addr:full":"Koninginnewg 253 Amsterdam Noord-Holland 1075 CV",
    "addr:housenumber":"253",
    "addr:postcode":"1075 cv",
    "iso:country":"NL",
    "sg:address":"Koninginnewg 253",
    "sg:city":"Amsterdam",
    "sg:orig_category":"Schoenen - Reparaties",
    "sg:phone":"+31 20 671 3212",
    "sg:postcode":"1075 CV",
    "sg:province":"Noord-Holland",
    "wof:name":"Jong Meester-Schoenmaker, De",
    "wof:placetype":"venue"
},
  "geometry": {"coordinates":[4.858026,52.351738],"type":"Point"}
}