{
  "type": "Feature",
  "properties": {
    "iso:country":"NL",
    "sg:address":"Amandelstraat 42",
    "sg:city":"'S Gravenhage",
    "sg:orig_category":"Kappers",
    "sg:phone":"+31 70 325 8630",
    "sg:postcode":"2564 EZ",
    "sg:province":"Zuid-Holland",
    "wof:name":"Mevr J Maree-Lessing",
    "wof:placetype":"venue"
},
  "geometry": {"coordinates":[4.251649,52.066566],"type":"Point"}
}