{
  "type": "Feature",
  "properties": {
    "addr:full":"Bakkerswg 3 Maarn Utrecht 3951 CS",
    "addr:housenumber":"3",
    "addr:postcode":"3951 cs",
    "addr:street":"Bakkerswg",
    "iso:country":"NL",
    "sg:address":"Bakkerswg 3",
    "sg:city":"Maarn",
    "sg:orig_category":"Vertaalbureaus",
    "sg:phone":"+31 343 441 788",
    "sg:postcode":"3951 CS",
    "sg:province":"Utrecht",
    "wof:name":"Lambooy",
    "wof:placetype":"venue"
},
  "geometry": {"coordinates":[5.381871,52.066257],"type":"Point"}
}