{
  "type": "Feature",
  "properties": {
    "addr:full":"Paradijslaan 106 Breda Noord-Brabant 4822 PG",
    "addr:housenumber":"106",
    "addr:postcode":"4822 pg",
    "addr:street":"Paradijslaan",
    "iso:country":"NL",
    "sg:address":"Paradijslaan 106",
    "sg:city":"Breda",
    "sg:orig_category":"Koeriersdiensten",
    "sg:phone":"+31 76 542 1235",
    "sg:postcode":"4822 PG",
    "sg:province":"Noord-Brabant",
    "wof:name":"Wessels Express Service",
    "wof:placetype":"venue"
},
  "geometry": {"coordinates":[4.735919,51.618015],"type":"Point"}
}