{
  "type": "Feature",
  "properties": {
    "addr:full":"Haarlemmerdijk 94 Amsterdam Noord-Holland 1013 JG",
    "addr:housenumber":"94",
    "addr:postcode":"1013 jg",
    "addr:street":"Haarlemmerdijk",
    "iso:country":"NL",
    "sg:address":"Haarlemmerdijk 94",
    "sg:city":"Amsterdam",
    "sg:classifiers":[
        {
            "category":"Communications",
            "subcategory":"Television Station",
            "type":"Services"
        }
    ],
    "sg:phone":"+31 20 638 1341",
    "sg:postcode":"1013 JG",
    "sg:province":"Noord-Holland",
    "sg:tags":[
        "video",
        "audio",
        "verhuur"
    ],
    "wof:name":"Cinemashop The Silver Screen",
    "wof:placetype":"venue"
},
  "geometry": {"coordinates":[4.886807,52.382984],"type":"Point"}
}