{
  "type": "Feature",
  "properties": {
    "addr:full":"Bontekoestraat 4 Rhenen Utrecht 3911 KC",
    "addr:housenumber":"4",
    "addr:postcode":"3911 kc",
    "addr:street":"Bontekoestraat",
    "iso:country":"NL",
    "sg:address":"Bontekoestraat 4",
    "sg:city":"Rhenen",
    "sg:classifiers":[
        {
            "category":"Fast Food",
            "type":"Food & Drink"
        }
    ],
    "sg:phone":"+31 317 615 056",
    "sg:postcode":"3911 KC",
    "sg:province":"Utrecht",
    "sg:tags":[
        "afhaal",
        "restaurant"
    ],
    "wof:name":"M. Colijn",
    "wof:placetype":"venue"
},
  "geometry": {"coordinates":[5.568102,51.957142],"type":"Point"}
}