{
  "type": "Feature",
  "properties": {
    "addr:full":"Postbus 85494 'S-Gravenhage South Holland 2508 CD",
    "addr:housenumber":"85494",
    "addr:postcode":"2508 cd",
    "addr:street":"Postbus",
    "iso:country":"NL",
    "sg:address":"Postbus 85494",
    "sg:city":"'S-Gravenhage",
    "sg:orig_category":"Vertalers",
    "sg:phone":"+31 70 350 5802",
    "sg:postcode":"2508 CD",
    "sg:province":"South Holland",
    "wof:name":"Romtext",
    "wof:placetype":"venue"
},
  "geometry": {"coordinates":[4.3136100769,52.0783195496],"type":"Point"}
}