{
  "type": "Feature",
  "properties": {
    "addr:full":"Aquamarynstraat 114 Hengelo Ov Overijssel 7554 NT",
    "addr:housenumber":"114",
    "addr:postcode":"7554 nt",
    "addr:street":"Aquamarynstraat;Ov",
    "iso:country":"NL",
    "sg:address":"Aquamarynstraat 114",
    "sg:city":"Hengelo Ov",
    "sg:orig_category":"Verhuur Bouwmachines",
    "sg:phone":"+31 74 245 2010",
    "sg:postcode":"7554 NT",
    "sg:province":"Overijssel",
    "wof:name":"Skyworks Bv",
    "wof:placetype":"venue"
},
  "geometry": {"coordinates":[6.76553,52.238659],"type":"Point"}
}