{
  "type": "Feature",
  "properties": {
    "addr:full":"De Nachtegaal 15 Heemstede Noord-Holland 2104 BN",
    "addr:housenumber":"15",
    "addr:postcode":"2104 bn",
    "addr:street":"De Nachtegaal",
    "iso:country":"NL",
    "sg:address":"De Nachtegaal 15",
    "sg:city":"Heemstede",
    "sg:orig_category":"Platenmaatschappijen",
    "sg:phone":"+31 23 547 2014",
    "sg:postcode":"2104 BN",
    "sg:province":"Noord-Holland",
    "wof:name":"Soul Relation",
    "wof:placetype":"venue"
},
  "geometry": {"coordinates":[4.608431,52.329285],"type":"Point"}
}