{
  "type": "Feature",
  "properties": {
    "addr:full":"Industrieweg 32A Zoeterwoude Zuid-Holland 2382 NW",
    "addr:housenumber":"32a",
    "addr:postcode":"2382 nw",
    "addr:street":"Industrieweg",
    "iso:country":"NL",
    "sg:address":"Industrieweg 32A",
    "sg:city":"Zoeterwoude",
    "sg:orig_category":"Voeding, Dranken And Tabak Gh",
    "sg:phone":"+31 71 589 6300",
    "sg:postcode":"2382 NW",
    "sg:province":"Zuid-Holland",
    "wof:name":"Gastronoom Horeca",
    "wof:placetype":"venue"
},
  "geometry": {"coordinates":[4.524822,52.138493],"type":"Point"}
}