{
  "type": "Feature",
  "properties": {
    "iso:country":"NL",
    "sg:address":"Groeskuilen 101",
    "sg:city":"Gemert",
    "sg:orig_category":"Bloemen And Planten",
    "sg:phone":"+31 492 366 630",
    "sg:postcode":"5421 ZW",
    "sg:province":"Noord-Brabant",
    "wof:name":"Tuincentrum En Bloemboetiek De Paashoef",
    "wof:placetype":"venue"
},
  "geometry": {"coordinates":[5.702771,51.560097],"type":"Point"}
}