{
  "type": "Feature",
  "properties": {
    "addr:full":"Zeeburgerpad 102 Amsterdam North Holland 1019 AD",
    "addr:housenumber":"102",
    "addr:postcode":"1019 ad",
    "addr:street":"Zeeburgerpad",
    "iso:country":"NL",
    "sg:address":"Zeeburgerpad 102",
    "sg:city":"Amsterdam",
    "sg:orig_category":"Autokeuringen",
    "sg:phone":"+31 20 665 7709",
    "sg:postcode":"1019 AD",
    "sg:province":"North Holland",
    "wof:name":"Machine-En Motorenfabriek Firma Kleyer",
    "wof:placetype":"venue"
},
  "geometry": {"coordinates":[4.9466,52.367085],"type":"Point"}
}