{
  "type": "Feature",
  "properties": {
    "iso:country":"NL",
    "sg:address":"Andereggln 4",
    "sg:city":"Nuenen",
    "sg:orig_category":"Schilders",
    "sg:phone":"+31 6 53817666",
    "sg:postcode":"5673 AL",
    "sg:province":"Noord-Brabant",
    "wof:name":"Verhallen, N",
    "wof:placetype":"venue"
},
  "geometry": {"coordinates":[5.560088,51.476124],"type":"Point"}
}