{
  "type": "Feature",
  "properties": {
    "iso:country":"NL",
    "sg:address":"Raadhuisstr 64",
    "sg:city":"Westwoud",
    "sg:orig_category":"Verenigingen En Stichtingen",
    "sg:phone":"+31 228 561 946",
    "sg:postcode":"1617 VM",
    "sg:province":"Noord-Holland",
    "wof:name":"Zonnewende, Sticht",
    "wof:placetype":"venue"
},
  "geometry": {"coordinates":[5.128574,52.688328],"type":"Point"}
}