{
  "type": "Feature",
  "properties": {
    "addr:full":"Tollensstr 60 Amsterdam North Holland 1053 RW",
    "addr:housenumber":"60",
    "addr:postcode":"1053 rw",
    "addr:street":"Tollensstr",
    "iso:country":"NL",
    "sg:address":"Tollensstr 60",
    "sg:city":"Amsterdam",
    "sg:orig_category":"Fotografie Reclame En Mode",
    "sg:phone":"+31 20 689 4636",
    "sg:postcode":"1053 RW",
    "sg:province":"North Holland",
    "wof:name":"Matthijs Van Roon",
    "wof:placetype":"venue"
},
  "geometry": {"coordinates":[4.869036,52.366852],"type":"Point"}
}