{
  "type": "Feature",
  "properties": {
    "iso:country":"NL",
    "sg:address":"Folgersterlaan 46",
    "sg:city":"Drachtstercompagnie",
    "sg:orig_category":"Benzinestations And Brandstoffen",
    "sg:phone":"+31 512 341 438",
    "sg:postcode":"9222 LJ",
    "sg:province":"Friesland",
    "wof:name":"Bezinestation Belt Vd Oliehandel",
    "wof:placetype":"venue"
},
  "geometry": {"coordinates":[6.108552,53.131779],"type":"Point"}
}