{
  "type": "Feature",
  "properties": {
    "addr:full":"Bastiaansensngl 17 St Willebrord Noord-Brabant 4711 EC",
    "addr:housenumber":"17",
    "addr:postcode":"4711 ec",
    "addr:street":"Bastiaansensngl",
    "iso:country":"NL",
    "sg:address":"Bastiaansensngl 17",
    "sg:city":"St Willebrord",
    "sg:orig_category":"Zalenverhuur",
    "sg:phone":"+31 165 383 591",
    "sg:postcode":"4711 EC",
    "sg:province":"Noord-Brabant",
    "sg:website":"http://www.dancingparkzicht.nl",
    "wof:name":"Parkzicht",
    "wof:placetype":"venue"
},
  "geometry": {"coordinates":[-78.095787,-1.78994],"type":"Point"}
}