{
  "type": "Feature",
  "properties": {
    "addr:full":"Oudestraat 148 Kampen Overijssel 8261 CZ",
    "addr:housenumber":"148",
    "addr:postcode":"8261",
    "addr:street":"Oudestraat",
    "iso:country":"NL",
    "sg:address":"Oudestraat 148",
    "sg:city":"Kampen",
    "sg:classifiers":[
        {
            "category":"Bakery",
            "type":"Food & Drink"
        }
    ],
    "sg:phone":"+31 38 331 2091",
    "sg:postcode":"8261 CZ",
    "sg:province":"Overijssel",
    "sg:tags":[
        "brood",
        "banket"
    ],
    "wof:name":"Banketbakkerij Lunchroom J.E.J. Aalberts",
    "wof:placetype":"venue"
},
  "geometry": {"coordinates":[15.47527,49.803791],"type":"Point"}
}