{
  "type": "Feature",
  "properties": {
    "addr:full":"Herenstr 24 Nieuwegein Utrecht 3431 CV",
    "addr:housenumber":"24",
    "addr:postcode":"3431 cv",
    "addr:street":"Herenstr",
    "iso:country":"NL",
    "sg:address":"Herenstr 24",
    "sg:city":"Nieuwegein",
    "sg:orig_category":"Timmerwerken",
    "sg:phone":"+31 30 630 1027",
    "sg:postcode":"3431 CV",
    "sg:province":"Utrecht",
    "wof:name":"Sios",
    "wof:placetype":"venue"
},
  "geometry": {"coordinates":[5.094575,52.037392],"type":"Point"}
}