{
  "type": "Feature",
  "properties": {
    "addr:full":"Botermarkt 16-18 Haarlem Noord-Holland 2011 XM",
    "addr:housenumber":"16-18",
    "addr:postcode":"2011 xm",
    "addr:street":"Botermarkt",
    "iso:country":"NL",
    "sg:address":"Botermarkt 16-18",
    "sg:city":"Haarlem",
    "sg:orig_category":"Piano'S",
    "sg:phone":"+31 23 532 2922",
    "sg:postcode":"2011 XM",
    "sg:province":"Noord-Holland",
    "sg:website":"http://www.andriessen-piano.nl",
    "wof:name":"Andriessen Piano'S - Vleugels",
    "wof:placetype":"venue"
},
  "geometry": {"coordinates":[4.631917,52.379551],"type":"Point"}
}