{
  "type": "Feature",
  "properties": {
    "addr:full":"Gr Florisstr 40 Rotterdam Zuid-Holland 3021 CH",
    "addr:housenumber":"40",
    "addr:postcode":"3021",
    "iso:country":"NL",
    "sg:address":"Gr Florisstr 40",
    "sg:city":"Rotterdam",
    "sg:orig_category":"Arbo- En Bedrijfsgezondheids- Diensten",
    "sg:phone":"+31 10 244 9500",
    "sg:postcode":"3021 CH",
    "sg:province":"Zuid-Holland",
    "wof:name":"Algra A-5",
    "wof:placetype":"venue"
},
  "geometry": {"coordinates":[4.458718,51.92033],"type":"Point"}
}