{
  "type": "Feature",
  "properties": {
    "iso:country":"NL",
    "sg:address":"Gruttostr 9",
    "sg:city":"Numansdorp",
    "sg:orig_category":"Verzekeringen - Verzekeringskantoren",
    "sg:phone":"+31 186 681 458",
    "sg:postcode":"3281 RM",
    "sg:province":"South Holland",
    "wof:name":"Swindregt",
    "wof:placetype":"venue"
},
  "geometry": {"coordinates":[4.444362,51.730984],"type":"Point"}
}