{
  "type": "Feature",
  "properties": {
    "iso:country":"NL",
    "sg:address":"Dkn Spieringsstr 6",
    "sg:city":"Boxtel",
    "sg:orig_category":"Muziekinstrumenten En Bladmuziek",
    "sg:phone":"+31 411 674 822",
    "sg:postcode":"5281 HZ",
    "sg:province":"North Brabant",
    "wof:name":"Alphen, Van",
    "wof:placetype":"venue"
},
  "geometry": {"coordinates":[5.324559,51.592163],"type":"Point"}
}