{
  "type": "Feature",
  "properties": {
    "addr:full":"Vlierberg 20 Eemnes Utrecht 3755 BS",
    "addr:housenumber":"20",
    "addr:postcode":"3755 bs",
    "addr:street":"Vlierberg",
    "iso:country":"NL",
    "sg:address":"Vlierberg 20",
    "sg:city":"Eemnes",
    "sg:orig_category":"Bewakingsdiensten",
    "sg:phone":"+31 35 525 9918",
    "sg:postcode":"3755 BS",
    "sg:province":"Utrecht",
    "wof:name":"Gooiland Beveiliging Bv",
    "wof:placetype":"venue"
},
  "geometry": {"coordinates":[5.249548,52.24688],"type":"Point"}
}