{
  "type": "Feature",
  "properties": {
    "addr:full":"Rijnstraat 17 Eindhoven Noord-Brabant 5626 AK",
    "addr:housenumber":"17",
    "addr:postcode":"5626 ak",
    "addr:street":"Rijnstraat",
    "iso:country":"NL",
    "sg:address":"Rijnstraat 17",
    "sg:city":"Eindhoven",
    "sg:orig_category":"Loodgieterswerk, Verwarming And Sanitaire Installaties",
    "sg:phone":"+31 40 262 1273",
    "sg:postcode":"5626 AK",
    "sg:province":"Noord-Brabant",
    "wof:name":"H. Oerlemans Beheer Bv",
    "wof:placetype":"venue"
},
  "geometry": {"coordinates":[5.43423,51.479313],"type":"Point"}
}