{
  "type": "Feature",
  "properties": {
    "addr:full":"Brahmsstr 79 Zevenaar Gelderland 6904 DC",
    "addr:housenumber":"79",
    "addr:postcode":"6904",
    "addr:street":"Brahmsstr",
    "iso:country":"NL",
    "sg:address":"Brahmsstr 79",
    "sg:city":"Zevenaar",
    "sg:orig_category":"Psychotherapeuten",
    "sg:phone":"+31 316 529 023",
    "sg:postcode":"6904 DC",
    "sg:province":"Gelderland",
    "wof:name":"Poortman, Wim",
    "wof:placetype":"venue"
},
  "geometry": {"coordinates":[6.057127,51.92804],"type":"Point"}
}