{
  "type": "Feature",
  "properties": {
    "addr:full":"Walenburg 25 'S Gravenhage Zuid-Holland 2591 BR",
    "addr:housenumber":"25",
    "addr:postcode":"2591 br",
    "addr:street":"Walenburg;' S",
    "iso:country":"NL",
    "sg:address":"Walenburg 25",
    "sg:city":"'S Gravenhage",
    "sg:orig_category":"Kinderopvang Behalve Thuis",
    "sg:phone":"+31 70 347 4443",
    "sg:postcode":"2591 BR",
    "sg:province":"Zuid-Holland",
    "wof:name":"Rietje Kinderopvang Dak",
    "wof:placetype":"venue"
},
  "geometry": {"coordinates":[4.363618,52.091373],"type":"Point"}
}