{
  "type": "Feature",
  "properties": {
    "iso:country":"NL",
    "sg:address":"Burgemeester Hovylaan 12",
    "sg:city":"'S Gravenhage",
    "sg:orig_category":"Geluidsopnamen",
    "sg:phone":"+31 70 391 1704",
    "sg:postcode":"2552 AW",
    "sg:province":"Zuid-Holland",
    "wof:name":"Hollandspoor Geluidsstudio",
    "wof:placetype":"venue"
},
  "geometry": {"coordinates":[4.242198,52.054615],"type":"Point"}
}