{
  "type": "Feature",
  "properties": {
    "addr:full":"Laanstr 65D Baarn Utrecht 3743 BB",
    "addr:housenumber":"65d",
    "addr:postcode":"3743 bb",
    "addr:street":"Laanstr",
    "iso:country":"NL",
    "sg:address":"Laanstr 65D",
    "sg:city":"Baarn",
    "sg:orig_category":"Herenkleding",
    "sg:phone":"+31 35 541 4036",
    "sg:postcode":"3743 BB",
    "sg:province":"Utrecht",
    "wof:name":"Hogeveen, Wim",
    "wof:placetype":"venue"
},
  "geometry": {"coordinates":[5.287622,52.211708],"type":"Point"}
}