{
  "type": "Feature",
  "properties": {
    "addr:full":"Vd Mondestr 129 Utrecht Utrecht 3515 BE",
    "addr:housenumber":"129",
    "addr:postcode":"3515",
    "iso:country":"NL",
    "sg:address":"Vd Mondestr 129",
    "sg:city":"Utrecht",
    "sg:orig_category":"Grafisch Ontwerpers",
    "sg:phone":"+31 30 276 3931",
    "sg:postcode":"3515 BE",
    "sg:province":"Utrecht",
    "wof:name":"Jong, Teatske De",
    "wof:placetype":"venue"
},
  "geometry": {"coordinates":[5.119522,52.104633],"type":"Point"}
}