{
  "type": "Feature",
  "properties": {
    "addr:full":"Adm De Ruyterwg 271 Amsterdam Noord-Holland 1055 LV",
    "addr:housenumber":"271",
    "addr:postcode":"1055",
    "iso:country":"NL",
    "sg:address":"Adm De Ruyterwg 271",
    "sg:city":"Amsterdam",
    "sg:orig_category":"Journalisten Freelance",
    "sg:phone":"+31 20 684 2890",
    "sg:postcode":"1055 LV",
    "sg:province":"Noord-Holland",
    "wof:name":"Faasse",
    "wof:placetype":"venue"
},
  "geometry": {"coordinates":[-94.58503,38.350479],"type":"Point"}
}