{
  "type": "Feature",
  "properties": {
    "iso:country":"NL",
    "sg:address":"Hengelosestr 579",
    "sg:city":"Enschede",
    "sg:classifiers":[
        {
            "category":"Professional",
            "subcategory":"Accounting & Tax Preparation",
            "type":"Services"
        }
    ],
    "sg:phone":"+31 53 480 9010",
    "sg:postcode":"7521 AG",
    "sg:province":"NL.08",
    "sg:tags":[
        "accountant",
        "en",
        "-kantoren",
        "register-"
    ],
    "sg:website":"http://www.dekok-dejong.nl",
    "wof:name":"Kok-De Jong, De",
    "wof:placetype":"venue"
},
  "geometry": {"coordinates":[6.849753,52.237453],"type":"Point"}
}