{
  "type": "Feature",
  "properties": {
    "addr:full":"Zwart Janstr 35 Rotterdam Zuid-Holland 3035 AK",
    "addr:housenumber":"35",
    "addr:postcode":"3035 ak",
    "iso:country":"NL",
    "sg:address":"Zwart Janstr 35",
    "sg:city":"Rotterdam",
    "sg:orig_category":"Sportschoenen - Winkels",
    "sg:phone":"+31 10 243 9294",
    "sg:postcode":"3035 AK",
    "sg:province":"Zuid-Holland",
    "wof:name":"Aktiesport",
    "wof:placetype":"venue"
},
  "geometry": {"coordinates":[4.479455,51.933022],"type":"Point"}
}