{
  "type": "Feature",
  "properties": {
    "addr:full":"Postbus 59999 Rotterdam Groningen 3008 RA",
    "addr:housenumber":"59999",
    "addr:postcode":"3008 ra",
    "addr:street":"Postbus",
    "iso:country":"NL",
    "sg:address":"Postbus 59999",
    "sg:city":"Rotterdam",
    "sg:orig_category":"Waterleidingbedrijven",
    "sg:phone":"+31 10 293 5031",
    "sg:postcode":"3008 RA",
    "sg:province":"Groningen",
    "sg:website":"http://www.waterbedrijfeuropoort.nl",
    "wof:name":"Europoort Bv",
    "wof:placetype":"venue"
},
  "geometry": {"coordinates":[4.470749855,51.922618866],"type":"Point"}
}