{
  "type": "Feature",
  "properties": {
    "iso:country":"NL",
    "sg:address":"Oudenoord 172",
    "sg:city":"Utrecht",
    "sg:orig_category":"Vakorganisaties",
    "sg:phone":"+31 30 232 6430",
    "sg:postcode":"3513 EV",
    "sg:province":"Utrecht",
    "sg:website":"http://www.fnv.nl",
    "wof:name":"Fnv",
    "wof:placetype":"venue"
},
  "geometry": {"coordinates":[5.110466,52.098396],"type":"Point"}
}