{
  "type": "Feature",
  "properties": {
    "addr:full":"Voorstraat 56 Beesd Gelderland 4153 AM",
    "addr:housenumber":"56",
    "addr:postcode":"4153",
    "addr:street":"Voorstraat;Gelderland",
    "iso:country":"NL",
    "sg:address":"Voorstraat 56",
    "sg:city":"Beesd",
    "sg:orig_category":"Meubelzaken, Woning- And Keukeninrichting",
    "sg:phone":"+31 345 681 755",
    "sg:postcode":"4153 AM",
    "sg:province":"Gelderland",
    "wof:name":"Vof De Hoog - Van Bremen",
    "wof:placetype":"venue"
},
  "geometry": {"coordinates":[5.194679,51.884525],"type":"Point"}
}