{
  "type": "Feature",
  "properties": {
    "addr:full":"F Halsstr 1 Kesteren Gelderland 4041 GX",
    "addr:housenumber":"1",
    "addr:postcode":"4041 gx",
    "addr:street":"Halsstr;Gelderland",
    "iso:country":"NL",
    "sg:address":"F Halsstr 1",
    "sg:city":"Kesteren",
    "sg:orig_category":"Meubelstoffering",
    "sg:phone":"+31 488 482 263",
    "sg:postcode":"4041 GX",
    "sg:province":"Gelderland",
    "wof:name":"Looijen",
    "wof:placetype":"venue"
},
  "geometry": {"coordinates":[5.569001,51.936607],"type":"Point"}
}