{
  "type": "Feature",
  "properties": {
    "iso:country":"NL",
    "sg:address":"De Merodestr 29",
    "sg:city":"Dordrecht",
    "sg:classifiers":[
        {
            "category":"Personal",
            "subcategory":"Nail Salon",
            "type":"Services"
        }
    ],
    "sg:phone":"+31 78 616 2670",
    "sg:postcode":"3319 BG",
    "sg:province":"Zuid-Holland",
    "sg:tags":[
        "pedicure"
    ],
    "wof:name":"Vught, J M Van",
    "wof:placetype":"venue"
},
  "geometry": {"coordinates":[4.702656,51.796585],"type":"Point"}
}