{
  "type": "Feature",
  "properties": {
    "addr:full":"Dorpsstr 163A Zoetermeer Zuid-Holland 2712 AH",
    "addr:housenumber":"163a",
    "addr:postcode":"2712 ah",
    "iso:country":"NL",
    "sg:address":"Dorpsstr 163A",
    "sg:city":"Zoetermeer",
    "sg:orig_category":"Herenkleding",
    "sg:phone":"+31 79 316 3910",
    "sg:postcode":"2712 AH",
    "sg:province":"Zuid-Holland",
    "wof:name":"Waay, Van",
    "wof:placetype":"venue"
},
  "geometry": {"coordinates":[4.500228,52.054531],"type":"Point"}
}