{
  "type": "Feature",
  "properties": {
    "iso:country":"NL",
    "sg:address":"Schouwburgring 162",
    "sg:city":"Tilburg",
    "sg:orig_category":"Energiebesparing",
    "sg:phone":"+31 13 536 0308",
    "sg:postcode":"5038 TM",
    "sg:province":"Noord-Brabant",
    "wof:name":"Heuvel, H W C M Van Den",
    "wof:placetype":"venue"
},
  "geometry": {"coordinates":[5.07945,51.554955],"type":"Point"}
}