{
  "type": "Feature",
  "properties": {
    "addr:full":"Deventerwg 1 Bathmen Overijssel 7437 BH",
    "addr:housenumber":"1",
    "addr:postcode":"7437 bh",
    "addr:street":"Deventerwg",
    "iso:country":"NL",
    "sg:address":"Deventerwg 1",
    "sg:city":"Bathmen",
    "sg:orig_category":"Elektrotechnische Installatiebureaus",
    "sg:phone":"+31 570 541 268",
    "sg:postcode":"7437 BH",
    "sg:province":"Overijssel",
    "wof:name":"Gorssel, Van",
    "wof:placetype":"venue"
},
  "geometry": {"coordinates":[6.283892,52.250458],"type":"Point"}
}