{
  "type": "Feature",
  "properties": {
    "addr:full":"Scheldestraat 19 Amsterdam Noord-Holland 1078 GD",
    "addr:housenumber":"19",
    "addr:postcode":"1078 gd",
    "addr:street":"Scheldestraat",
    "iso:country":"NL",
    "sg:address":"Scheldestraat 19",
    "sg:city":"Amsterdam",
    "sg:orig_category":"Koffers And Tassen Fab",
    "sg:phone":"+31 20 662 1957",
    "sg:postcode":"1078 GD",
    "sg:province":"Noord-Holland",
    "wof:name":"Tretsom Luggage Bv",
    "wof:placetype":"venue"
},
  "geometry": {"coordinates":[4.891261,52.347485],"type":"Point"}
}