{
  "type": "Feature",
  "properties": {
    "addr:full":"De Geren 23 Wamel Gelderland 6659 CX",
    "addr:housenumber":"23",
    "addr:postcode":"6659 cx",
    "addr:street":"De Geren;Gelderland",
    "iso:country":"NL",
    "sg:address":"De Geren 23",
    "sg:city":"Wamel",
    "sg:orig_category":"Kappers",
    "sg:phone":"+31 487 502 146",
    "sg:postcode":"6659 CX",
    "sg:province":"Gelderland",
    "wof:name":"Jolanda Loeffen",
    "wof:placetype":"venue"
},
  "geometry": {"coordinates":[5.4548039436,51.8765144348],"type":"Point"}
}