{
  "type": "Feature",
  "properties": {
    "addr:full":"Vrouwe Udasngl 224 Lent Gelderland 6663 GW",
    "addr:housenumber":"224",
    "addr:postcode":"6663 gw",
    "addr:street":"Vrouwe;Gelderland",
    "iso:country":"NL",
    "sg:address":"Vrouwe Udasngl 224",
    "sg:city":"Lent",
    "sg:orig_category":"Muziekinstrumenten - Reparatie En Onderhoud",
    "sg:phone":"+31 24 355 6645",
    "sg:postcode":"6663 GW",
    "sg:province":"Gelderland",
    "wof:name":"Itankala",
    "wof:placetype":"venue"
},
  "geometry": {"coordinates":[-77.241432,38.151344],"type":"Point"}
}