{
  "type": "Feature",
  "properties": {
    "addr:full":"Stratinghpad 4 Tilburg Noord-Brabant 5025 DS",
    "addr:housenumber":"4",
    "addr:postcode":"5025 ds",
    "addr:street":"Stratinghpad",
    "iso:country":"NL",
    "sg:address":"Stratinghpad 4",
    "sg:city":"Tilburg",
    "sg:orig_category":"Bestratingen",
    "sg:phone":"+31 13 571 5954",
    "sg:postcode":"5025 DS",
    "sg:province":"Noord-Brabant",
    "wof:name":"Fey, Bestratingen",
    "wof:placetype":"venue"
},
  "geometry": {"coordinates":[5.073315,51.550789],"type":"Point"}
}