{
  "type": "Feature",
  "properties": {
    "addr:full":"Amersfoortseweg 50 Doorn Utrecht 3941 EN",
    "addr:housenumber":"50",
    "addr:postcode":"3941 en",
    "addr:street":"Amersfoortseweg",
    "iso:country":"NL",
    "sg:address":"Amersfoortseweg 50",
    "sg:city":"Doorn",
    "sg:orig_category":"Meubelzaken, Woning- And Keukeninrichting",
    "sg:phone":"+31 343 416 112",
    "sg:postcode":"3941 EN",
    "sg:province":"Utrecht",
    "wof:name":"Prima Meubel",
    "wof:placetype":"venue"
},
  "geometry": {"coordinates":[5.345558,52.036598],"type":"Point"}
}