{
  "type": "Feature",
  "properties": {
    "addr:full":"Stationsstraat 3 Wierden Overijssel 7641 BV",
    "addr:housenumber":"3",
    "addr:postcode":"7641 bv",
    "addr:street":"Stationsstraat",
    "iso:country":"NL",
    "sg:address":"Stationsstraat 3",
    "sg:city":"Wierden",
    "sg:orig_category":"Kantoorartikelen",
    "sg:phone":"+31 546 571 383",
    "sg:postcode":"7641 BV",
    "sg:province":"Overijssel",
    "wof:name":"Reterink",
    "wof:placetype":"venue"
},
  "geometry": {"coordinates":[6.5907840729,52.3568153381],"type":"Point"}
}