{
  "type": "Feature",
  "properties": {
    "addr:full":"Ypemaheerd 55 Groningen Groningen 9736 ME",
    "addr:housenumber":"55",
    "addr:postcode":"9736 me",
    "addr:street":"Ypemaheerd",
    "iso:country":"NL",
    "sg:address":"Ypemaheerd 55",
    "sg:city":"Groningen",
    "sg:orig_category":"Kappers",
    "sg:phone":"+31 50 541 3331",
    "sg:postcode":"9736 ME",
    "sg:province":"Groningen",
    "wof:name":"Time Out",
    "wof:placetype":"venue"
},
  "geometry": {"coordinates":[6.601566,53.249149],"type":"Point"}
}