{
  "type": "Feature",
  "properties": {
    "addr:full":"Bremsngl 20 Jubbega Provincie Friesland 8411 VX",
    "addr:housenumber":"20",
    "addr:postcode":"8411 vx",
    "addr:street":"Bremsngl;Provincie Friesland",
    "iso:country":"NL",
    "sg:address":"Bremsngl 20",
    "sg:city":"Jubbega",
    "sg:orig_category":"Bloemen En Planten",
    "sg:phone":"+31 516 462 580",
    "sg:postcode":"8411 VX",
    "sg:province":"Provincie Friesland",
    "wof:name":"Sandra",
    "wof:placetype":"venue"
},
  "geometry": {"coordinates":[6.124435,53.004986],"type":"Point"}
}