{
  "type": "Feature",
  "properties": {
    "addr:full":"Parmentierwg 8 Almelo Overijssel 7602 PW",
    "addr:housenumber":"8",
    "addr:postcode":"7602 pw",
    "addr:street":"Parmentierwg",
    "iso:country":"NL",
    "sg:address":"Parmentierwg 8",
    "sg:city":"Almelo",
    "sg:orig_category":"Lasapparaten En Benodigdheden",
    "sg:phone":"+31 546 491 966",
    "sg:postcode":"7602 PW",
    "sg:province":"Overijssel",
    "wof:name":"Linker Almelo",
    "wof:placetype":"venue"
},
  "geometry": {"coordinates":[6.649145,52.375362],"type":"Point"}
}