{
  "type": "Feature",
  "properties": {
    "iso:country":"NL",
    "sg:address":"Zamenhofdreef 22",
    "sg:city":"Utrecht",
    "sg:orig_category":"Grafisch Ontwerpers",
    "sg:phone":"+31 6 54285492",
    "sg:postcode":"3562 JX",
    "sg:province":"Utrecht",
    "wof:name":"Eijzenga, Martine",
    "wof:placetype":"venue"
},
  "geometry": {"coordinates":[5.112605,52.114841],"type":"Point"}
}