{
  "type": "Feature",
  "properties": {
    "addr:full":"Burg Beelaertspk 122 Dordrecht Zuid-Holland 3319 AW",
    "addr:housenumber":"122",
    "addr:postcode":"3319 aw",
    "addr:street":"Burg",
    "iso:country":"NL",
    "sg:address":"Burg Beelaertspk 122",
    "sg:city":"Dordrecht",
    "sg:orig_category":"Administratie- En Boekhoudkantoren",
    "sg:phone":"+31 78 616 9307",
    "sg:postcode":"3319 AW",
    "sg:province":"Zuid-Holland",
    "wof:name":"Bilan",
    "wof:placetype":"venue"
},
  "geometry": {"coordinates":[4.693129,51.79166],"type":"Point"}
}