{
  "type": "Feature",
  "properties": {
    "addr:full":"Marconiwg 27 Nunspeet Gelderland 8071 RB",
    "addr:housenumber":"27",
    "addr:postcode":"8071 rb",
    "addr:street":"Marconiwg;Gelderland",
    "iso:country":"NL",
    "sg:address":"Marconiwg 27",
    "sg:city":"Nunspeet",
    "sg:orig_category":"Fietsen En Bromfietsen",
    "sg:phone":"+31 341 258 520",
    "sg:postcode":"8071 RB",
    "sg:province":"Gelderland",
    "sg:website":"http://www.bonenbergtweewielers.nl",
    "wof:name":"Bonenberg, Jacob",
    "wof:placetype":"venue"
},
  "geometry": {"coordinates":[5.769725,52.37788],"type":"Point"}
}