{
  "type": "Feature",
  "properties": {
    "addr:full":"Egginklaan 51 Utrecht Utrecht 3527 XP",
    "addr:housenumber":"51",
    "addr:postcode":"3527 xp",
    "addr:street":"Egginklaan",
    "iso:country":"NL",
    "sg:address":"Egginklaan 51",
    "sg:city":"Utrecht",
    "sg:orig_category":"Begrafenisondernemers",
    "sg:phone":"+31 30 296 6666",
    "sg:postcode":"3527 XP",
    "sg:province":"Utrecht",
    "wof:name":"Coop Vereniging Uitvaartcentrum Barbara Ua",
    "wof:placetype":"venue"
},
  "geometry": {"coordinates":[5.099401,52.076805],"type":"Point"}
}