{
  "type": "Feature",
  "properties": {
    "iso:country":"NL",
    "sg:address":"Rynln 22",
    "sg:city":"Bergen Op Zoom",
    "sg:orig_category":"Keuken- Groot-Installaties",
    "sg:phone":"+31 6 54675297",
    "sg:postcode":"4615 CB",
    "sg:province":"North Brabant",
    "wof:name":"Huffel, Van",
    "wof:placetype":"venue"
},
  "geometry": {"coordinates":[4.281987,51.495953],"type":"Point"}
}