{
  "type": "Feature",
  "properties": {
    "addr:full":"Zwavertswg 108 Hengelo Ov Overijssel 7552 ML",
    "addr:housenumber":"108",
    "addr:postcode":"7552 ml",
    "addr:street":"Ov",
    "iso:country":"NL",
    "sg:address":"Zwavertswg 108",
    "sg:city":"Hengelo Ov",
    "sg:orig_category":"Verenigingsgebouwen",
    "sg:phone":"+31 74 242 2578",
    "sg:postcode":"7552 ML",
    "sg:province":"Overijssel",
    "wof:name":"Juliana 32 Sportver",
    "wof:placetype":"venue"
},
  "geometry": {"coordinates":[6.820958,52.268314],"type":"Point"}
}