{
  "type": "Feature",
  "properties": {
    "iso:country":"NL",
    "sg:address":"Lekstr 77",
    "sg:city":"Amsterdam",
    "sg:orig_category":"Administratie- En Boekhoudkantoren",
    "sg:phone":"+31 20 642 8248",
    "sg:postcode":"1079 EM",
    "sg:province":"Noord-Holland",
    "sg:website":"http://www.denhengstbeheer.nl",
    "wof:name":"Hengst Beheer, Den",
    "wof:placetype":"venue"
},
  "geometry": {"coordinates":[4.901623,52.343849],"type":"Point"}
}