{
  "type": "Feature",
  "properties": {
    "addr:full":"Lekstr 77 Amsterdam Noord-Holland 1079 EM",
    "addr:housenumber":"77",
    "addr:postcode":"1079 em",
    "addr:street":"Lekstr",
    "iso:country":"NL",
    "sg:address":"Lekstr 77",
    "sg:city":"Amsterdam",
    "sg:orig_category":"Administratie- En Boekhoudkantoren",
    "sg:phone":"+31 20 642 8248",
    "sg:postcode":"1079 EM",
    "sg:province":"Noord-Holland",
    "sg:website":"http://www.denhengstbeheer.nl",
    "wof:name":"Hengst Beheer, Den",
    "wof:placetype":"venue"
},
  "geometry": {"coordinates":[4.901623,52.343849],"type":"Point"}
}