{
  "type": "Feature",
  "properties": {
    "iso:country":"NL",
    "sg:address":"Lynbaanplnts 13",
    "sg:city":"Medemblik",
    "sg:orig_category":"Onderhoudswerken",
    "sg:phone":"+31 227 544 024",
    "sg:postcode":"1671 KK",
    "sg:province":"Noord-Holland",
    "wof:name":"Nijs, M G De",
    "wof:placetype":"venue"
},
  "geometry": {"coordinates":[5.106715,52.771942],"type":"Point"}
}