{
  "type": "Feature",
  "properties": {
    "addr:full":"Susannadonk 115 Roosendaal Noord-Brabant 4707 WT",
    "addr:housenumber":"115",
    "addr:postcode":"4707 wt",
    "addr:street":"Susannadonk",
    "iso:country":"NL",
    "sg:address":"Susannadonk 115",
    "sg:city":"Roosendaal",
    "sg:orig_category":"Helderzienden",
    "sg:phone":"+31 165 569 542",
    "sg:postcode":"4707 WT",
    "sg:province":"Noord-Brabant",
    "wof:name":"Zwennis, K A",
    "wof:placetype":"venue"
},
  "geometry": {"coordinates":[4.469216,51.518967],"type":"Point"}
}