{
  "type": "Feature",
  "properties": {
    "addr:full":"V Hogendorpln 1C Hilversum Noord-Holland 1215 EG",
    "addr:housenumber":"1c",
    "addr:postcode":"1215 eg",
    "addr:street":"Hogendorpln",
    "iso:country":"NL",
    "sg:address":"V Hogendorpln 1C",
    "sg:city":"Hilversum",
    "sg:orig_category":"Kinderopvang",
    "sg:phone":"+31 35 628 2095",
    "sg:postcode":"1215 EG",
    "sg:province":"Noord-Holland",
    "sg:website":"http://www.kinderopvanghilversum.nl",
    "wof:name":"Basisbende, De",
    "wof:placetype":"venue"
},
  "geometry": {"coordinates":[5.1695,52.228565],"type":"Point"}
}