{
  "type": "Feature",
  "properties": {
    "addr:full":"Aalsmeerwg 78 Amsterdam Noord-Holland 1059 AM",
    "addr:housenumber":"78",
    "addr:postcode":"1059",
    "addr:street":"Aalsmeerwg",
    "iso:country":"NL",
    "sg:address":"Aalsmeerwg 78",
    "sg:city":"Amsterdam",
    "sg:orig_category":"Verzekeringen - Verzekeringskantoren",
    "sg:phone":"+31 20 615 8175",
    "sg:postcode":"1059 AM",
    "sg:province":"Noord-Holland",
    "wof:name":"Havenaar, J",
    "wof:placetype":"venue"
},
  "geometry": {"coordinates":[4.847942,52.34848],"type":"Point"}
}