{
  "type": "Feature",
  "properties": {
    "iso:country":"NL",
    "sg:address":"Alpacastr 38",
    "sg:city":"Almere",
    "sg:orig_category":"Keukens",
    "sg:phone":"+31 6 52056622",
    "sg:postcode":"1338 HR",
    "sg:province":"Flevoland",
    "wof:name":"Akt Almere",
    "wof:placetype":"venue"
},
  "geometry": {"coordinates":[5.267911,52.384857],"type":"Point"}
}