{
  "type": "Feature",
  "properties": {
    "addr:full":"Stationswg 75 Hillegom North Holland 2182 BB",
    "addr:housenumber":"75",
    "addr:postcode":"2182 bb",
    "addr:street":"Stationswg",
    "iso:country":"NL",
    "sg:address":"Stationswg 75",
    "sg:city":"Hillegom",
    "sg:orig_category":"Koeriersdiensten",
    "sg:phone":"+31 6 40105192",
    "sg:postcode":"2182 BB",
    "sg:province":"North Holland",
    "wof:name":"Ringo Koeriersdiensten",
    "wof:placetype":"venue"
},
  "geometry": {"coordinates":[4.574466,52.300179],"type":"Point"}
}