{
  "type": "Feature",
  "properties": {
    "addr:full":"Nyverheidswg 26 Mydrecht Utrecht 3641 RR",
    "addr:housenumber":"26;3641",
    "addr:postcode":"rr",
    "addr:street":"Nyverheidswg",
    "iso:country":"NL",
    "sg:address":"Nyverheidswg 26",
    "sg:city":"Mydrecht",
    "sg:orig_category":"Zoetwaren - Fabrieken En Groothandel",
    "sg:phone":"+31 297 239 239",
    "sg:postcode":"3641 RR",
    "sg:province":"Utrecht",
    "wof:name":"Sanaro",
    "wof:placetype":"venue"
},
  "geometry": {"coordinates":[4.86178,52.20578],"type":"Point"}
}