{
  "type": "Feature",
  "properties": {
    "addr:full":"Loonsevaert 62 Kaatsheuvel North Brabant 5171 LK",
    "addr:housenumber":"62",
    "addr:postcode":"5171 lk",
    "addr:street":"Loonsevaert",
    "iso:country":"NL",
    "sg:address":"Loonsevaert 62",
    "sg:city":"Kaatsheuvel",
    "sg:orig_category":"Schoenen",
    "sg:phone":"+31 416 282 330",
    "sg:postcode":"5171 LK",
    "sg:province":"North Brabant",
    "wof:name":"Hendriks Schoenen Bv",
    "wof:placetype":"venue"
},
  "geometry": {"coordinates":[5.045163,51.659027],"type":"Point"}
}