{
  "type": "Feature",
  "properties": {
    "addr:full":"Weteringschans 74 Amsterdam Noord-Holland 1017 XR",
    "addr:housenumber":"74",
    "addr:postcode":"1017 xr",
    "addr:street":"Weteringschans",
    "iso:country":"NL",
    "sg:address":"Weteringschans 74",
    "sg:city":"Amsterdam",
    "sg:orig_category":"Verenigingen En Stichtingen",
    "sg:phone":"+31 20 694 4686",
    "sg:postcode":"1017 XR",
    "sg:province":"Noord-Holland",
    "wof:name":"Hesperis Antroposofische Patienenver",
    "wof:placetype":"venue"
},
  "geometry": {"coordinates":[4.892343,52.35939],"type":"Point"}
}