{
  "type": "Feature",
  "properties": {
    "iso:country":"NL",
    "sg:address":"De Bongerd 50",
    "sg:city":"Winssen",
    "sg:orig_category":"Verzekeringen",
    "sg:phone":"+31 487 523 011",
    "sg:postcode":"6645 AZ",
    "sg:province":"Gelderland",
    "wof:name":"Assurantie-Adviesburo Johan Wiebe",
    "wof:placetype":"venue"
},
  "geometry": {"coordinates":[5.706064,51.879173],"type":"Point"}
}