{
  "type": "Feature",
  "properties": {
    "addr:full":"Pr Alexanderpln 20 Rotterdam Zuid-Holland 3067 GC",
    "addr:housenumber":"20",
    "addr:postcode":"3067 gc",
    "iso:country":"NL",
    "sg:address":"Pr Alexanderpln 20",
    "sg:city":"Rotterdam",
    "sg:orig_category":"Gehandicapten - Hulpmiddelen",
    "sg:phone":"+31 10 289 9799",
    "sg:postcode":"3067 GC",
    "sg:province":"Zuid-Holland",
    "wof:name":"Voorzieningen Gehandicapten Noord-Oost",
    "wof:placetype":"venue"
},
  "geometry": {"coordinates":[4.552451,51.951008],"type":"Point"}
}