{
  "type": "Feature",
  "properties": {
    "addr:full":"Grotestraat 21 Cuijk North Brabant 5431 DG",
    "addr:housenumber":"21",
    "addr:postcode":"5431 dg",
    "addr:street":"Grotestraat",
    "iso:country":"NL",
    "sg:address":"Grotestraat 21",
    "sg:city":"Cuijk",
    "sg:orig_category":"Opticiens",
    "sg:phone":"+31 900 7004541",
    "sg:postcode":"5431 DG",
    "sg:province":"North Brabant",
    "wof:name":"Briljant Optiek",
    "wof:placetype":"venue"
},
  "geometry": {"coordinates":[5.8293590546,51.7250175476],"type":"Point"}
}