{
  "type": "Feature",
  "properties": {
    "addr:full":"Petuniadal 1 Leiden South Holland 2317 HZ",
    "addr:housenumber":"1",
    "addr:postcode":"2317 hz",
    "addr:street":"Petuniadal",
    "iso:country":"NL",
    "sg:address":"Petuniadal 1",
    "sg:city":"Leiden",
    "sg:orig_category":"Verzekeringen - Verzekeringskantoren",
    "sg:phone":"+31 71 521 6177",
    "sg:postcode":"2317 HZ",
    "sg:province":"South Holland",
    "wof:name":"Duijm, H",
    "wof:placetype":"venue"
},
  "geometry": {"coordinates":[4.511545,52.182243],"type":"Point"}
}