{
  "type": "Feature",
  "properties": {
    "addr:full":"1E Middellandstr 70B Rotterdam South Holland 3021 BE",
    "addr:housenumber":"70b",
    "addr:postcode":"3021",
    "addr:street":"1E Middellandstr",
    "iso:country":"NL",
    "sg:address":"1E Middellandstr 70B",
    "sg:city":"Rotterdam",
    "sg:orig_category":"Kappers",
    "sg:phone":"+31 10 476 2244",
    "sg:postcode":"3021 BE",
    "sg:province":"South Holland",
    "wof:name":"Ameri",
    "wof:placetype":"venue"
},
  "geometry": {"coordinates":[4.462911129,51.9187583923],"type":"Point"}
}