{
  "type": "Feature",
  "properties": {
    "addr:full":"Kruisvoort 54 Breda Noord-Brabant 4814 RZ",
    "addr:housenumber":"54",
    "addr:postcode":"4814 rz",
    "addr:street":"Kruisvoort",
    "iso:country":"NL",
    "sg:address":"Kruisvoort 54",
    "sg:city":"Breda",
    "sg:orig_category":"Meubelzaken, Woning- And Keukeninrichting",
    "sg:phone":"+31 76 530 9599",
    "sg:postcode":"4814 RZ",
    "sg:province":"Noord-Brabant",
    "wof:name":"Beter Bed",
    "wof:placetype":"venue"
},
  "geometry": {"coordinates":[4.732281,51.581543],"type":"Point"}
}