{
  "type": "Feature",
  "properties": {
    "addr:full":"Dahliastr 11 Badhoevedorp Noord-Holland 1171 WN",
    "addr:housenumber":"11",
    "addr:postcode":"1171 wn",
    "addr:street":"Dahliastr",
    "iso:country":"NL",
    "sg:address":"Dahliastr 11",
    "sg:city":"Badhoevedorp",
    "sg:orig_category":"Autorijscholen",
    "sg:phone":"+31 20 659 6194",
    "sg:postcode":"1171 WN",
    "sg:province":"Noord-Holland",
    "wof:name":"Peetoom, J J S",
    "wof:placetype":"venue"
},
  "geometry": {"coordinates":[4.772216,52.345829],"type":"Point"}
}