{
  "type": "Feature",
  "properties": {
    "addr:full":"Oberonweg 260 Spijkenisse Zuid-Holland 3208 PG",
    "addr:housenumber":"260",
    "addr:postcode":"3208 pg",
    "addr:street":"Oberonweg",
    "iso:country":"NL",
    "sg:address":"Oberonweg 260",
    "sg:city":"Spijkenisse",
    "sg:orig_category":"Beautyfarms And Sauna'S",
    "sg:phone":"+31 181 632 838",
    "sg:postcode":"3208 PG",
    "sg:province":"Zuid-Holland",
    "wof:name":"Zonnestudio Marianne",
    "wof:placetype":"venue"
},
  "geometry": {"coordinates":[4.319379,51.834896],"type":"Point"}
}