{
  "type": "Feature",
  "properties": {
    "addr:full":"Kromstr 5 Oss Virginia 5341 JA",
    "addr:housenumber":"5",
    "addr:postcode":"5341 ja",
    "addr:street":"Kromstr",
    "iso:country":"NL",
    "sg:address":"Kromstr 5",
    "sg:city":"Oss",
    "sg:orig_category":"Kappers",
    "sg:phone":"+31 412 643 624",
    "sg:postcode":"5341 JA",
    "sg:province":"Virginia",
    "wof:name":"Dana Hairfashion",
    "wof:placetype":"venue"
},
  "geometry": {"coordinates":[-77.2352142334,38.3125991821],"type":"Point"}
}