{
  "type": "Feature",
  "properties": {
    "addr:full":"Geesterwg 2 Alkmaar North Holland 1815 CR",
    "addr:housenumber":"2",
    "addr:postcode":"1815 cr",
    "addr:street":"Geesterwg",
    "iso:country":"NL",
    "sg:address":"Geesterwg 2",
    "sg:city":"Alkmaar",
    "sg:orig_category":"Projectontwikkeling",
    "sg:phone":"+31 72 540 5467",
    "sg:postcode":"1815 CR",
    "sg:province":"North Holland",
    "wof:name":"Interselectbouw Bv",
    "wof:placetype":"venue"
},
  "geometry": {"coordinates":[4.741467,52.63446],"type":"Point"}
}