{
  "type": "Feature",
  "properties": {
    "addr:full":"Cuneraweg 20 Rhenen Utrecht 3911 RN",
    "addr:housenumber":"20",
    "addr:postcode":"3911 rn",
    "addr:street":"Cuneraweg",
    "iso:country":"NL",
    "sg:address":"Cuneraweg 20",
    "sg:city":"Rhenen",
    "sg:orig_category":"Zuivelproducten And Spijsoli?n Gh",
    "sg:phone":"+31 317 615 297",
    "sg:postcode":"3911 RN",
    "sg:province":"Utrecht",
    "wof:name":"J. En C. Van De Westeringh Vof",
    "wof:placetype":"venue"
},
  "geometry": {"coordinates":[5.60558,51.96043],"type":"Point"}
}