{
  "type": "Feature",
  "properties": {
    "addr:full":"Enkstr 6 Zwolle NL.08 8011 JT",
    "addr:housenumber":"6",
    "addr:postcode":"8011 jt",
    "addr:street":"Enkstr",
    "iso:country":"NL",
    "sg:address":"Enkstr 6",
    "sg:city":"Zwolle",
    "sg:orig_category":"Artiesten/Gezelschappen",
    "sg:phone":"+31 38 423 2249",
    "sg:postcode":"8011 JT",
    "sg:province":"NL.08",
    "wof:name":"Tourdion",
    "wof:placetype":"venue"
},
  "geometry": {"coordinates":[6.096167,52.506588],"type":"Point"}
}