{
  "type": "Feature",
  "properties": {
    "addr:full":"Ripselaan 22 Nieuwe Wetering South Holland 2376 BJ",
    "addr:housenumber":"22",
    "addr:postcode":"2376 bj",
    "addr:street":"Ripselaan",
    "iso:country":"NL",
    "sg:address":"Ripselaan 22",
    "sg:city":"Nieuwe Wetering",
    "sg:orig_category":"Goederenvervoer Over De Weg",
    "sg:phone":"+31 71 331 2267",
    "sg:postcode":"2376 BJ",
    "sg:province":"South Holland",
    "wof:name":"Van Ruiten & Kreyger Bv",
    "wof:placetype":"venue"
},
  "geometry": {"coordinates":[4.609799,52.198395],"type":"Point"}
}