{
  "type": "Feature",
  "properties": {
    "addr:full":"A Bosstr 31 Almere Flevoland 1325 NL",
    "addr:housenumber":"31",
    "addr:postcode":"1325",
    "addr:street":"Flevoland",
    "iso:country":"NL",
    "sg:address":"A Bosstr 31",
    "sg:city":"Almere",
    "sg:orig_category":"Luchtvrachtexpediteurs",
    "sg:phone":"+31 36 537 3903",
    "sg:postcode":"1325 NL",
    "sg:province":"Flevoland",
    "wof:name":"Joy Handling",
    "wof:placetype":"venue"
},
  "geometry": {"coordinates":[5.239468,52.366215],"type":"Point"}
}