{
  "type": "Feature",
  "properties": {
    "addr:full":"Kamelenspoor 380 Maarssen Utrecht 3605 TC",
    "addr:housenumber":"380",
    "addr:postcode":"3605 tc",
    "addr:street":"Kamelenspoor",
    "iso:country":"NL",
    "sg:address":"Kamelenspoor 380",
    "sg:city":"Maarssen",
    "sg:orig_category":"Autorijscholen",
    "sg:phone":"+31 346 568 662",
    "sg:postcode":"3605 TC",
    "sg:province":"Utrecht",
    "wof:name":"Discipline",
    "wof:placetype":"venue"
},
  "geometry": {"coordinates":[5.026578,52.136654],"type":"Point"}
}