{
  "type": "Feature",
  "properties": {
    "addr:full":"Slotmakersstr 2 Leeuwarden Friesland 8911 GM",
    "addr:housenumber":"2",
    "addr:postcode":"8911 gm",
    "addr:street":"Slotmakersstr",
    "iso:country":"NL",
    "sg:address":"Slotmakersstr 2",
    "sg:city":"Leeuwarden",
    "sg:orig_category":"Hulpverlening Sociaal",
    "sg:phone":"+31 58 212 9821",
    "sg:postcode":"8911 GM",
    "sg:province":"Friesland",
    "wof:name":"Jsf",
    "wof:placetype":"venue"
},
  "geometry": {"coordinates":[5.799296,53.203194],"type":"Point"}
}