{
  "type": "Feature",
  "properties": {
    "addr:full":"Koopmansstraat 11 Lelystad NL. 8223 AH",
    "addr:housenumber":"11",
    "addr:postcode":"8223 ah",
    "addr:street":"Koopmansstraat;Nl.",
    "iso:country":"NL",
    "sg:address":"Koopmansstraat 11",
    "sg:city":"Lelystad",
    "sg:orig_category":"Huishoudapparatuur, Televisies And Radio'S",
    "sg:phone":"+31 320 221 216",
    "sg:postcode":"8223 AH",
    "sg:province":"NL.",
    "wof:name":"Megapool",
    "wof:placetype":"venue"
},
  "geometry": {"coordinates":[5.485242,52.520561],"type":"Point"}
}