{
  "type": "Feature",
  "properties": {
    "addr:full":"P H V Rynstr 13A Veenendaal Utrecht 3904 HG",
    "addr:housenumber":"13a",
    "addr:postcode":"3904 hg",
    "addr:street":"P H V Rynstr",
    "iso:country":"NL",
    "sg:address":"P H V Rynstr 13A",
    "sg:city":"Veenendaal",
    "sg:orig_category":"Zonne-Energie",
    "sg:phone":"+31 318 500 726",
    "sg:postcode":"3904 HG",
    "sg:province":"Utrecht",
    "sg:website":"http://www.2wcollectors.nl",
    "wof:name":"2W Collectors",
    "wof:placetype":"venue"
},
  "geometry": {"coordinates":[5.55418,52.024902],"type":"Point"}
}