{
  "type": "Feature",
  "properties": {
    "addr:full":"Saffierstr 12A Amsterdam Noord-Holland 1074 GS",
    "addr:housenumber":"12a",
    "addr:postcode":"1074 gs",
    "addr:street":"Saffierstr",
    "iso:country":"NL",
    "sg:address":"Saffierstr 12A",
    "sg:city":"Amsterdam",
    "sg:orig_category":"Artiesten/Gezelschappen",
    "sg:phone":"+31 20 664 7848",
    "sg:postcode":"1074 GS",
    "sg:province":"Noord-Holland",
    "wof:name":"Kluiving, Ren\u00e9",
    "wof:placetype":"venue"
},
  "geometry": {"coordinates":[4.905471,52.351212],"type":"Point"}
}