{
  "type": "Feature",
  "properties": {
    "addr:full":"Breelaan 3 Ede Gld Gelderland 6711 MR",
    "addr:housenumber":"3",
    "addr:postcode":"6711 mr",
    "addr:street":"Breelaan;Gld Gelderland",
    "iso:country":"NL",
    "sg:address":"Breelaan 3",
    "sg:city":"Ede Gld",
    "sg:orig_category":"Werving And Selectie Van Tijdelijk Personeel And Uitzendkantoren",
    "sg:phone":"+31 318 652 260",
    "sg:postcode":"6711 MR",
    "sg:province":"Gelderland",
    "wof:name":"Creyf'S Interim",
    "wof:placetype":"venue"
},
  "geometry": {"coordinates":[5.6703119278,52.0414161682],"type":"Point"}
}