{
  "type": "Feature",
  "properties": {
    "iso:country":"NL",
    "sg:address":"Breelaan 3",
    "sg:city":"Ede Gld",
    "sg:orig_category":"Werving And Selectie Van Tijdelijk Personeel And Uitzendkantoren",
    "sg:phone":"+31 318 652 260",
    "sg:postcode":"6711 MR",
    "sg:province":"Gelderland",
    "wof:name":"Creyf'S Interim",
    "wof:placetype":"venue"
},
  "geometry": {"coordinates":[5.6703119278,52.0414161682],"type":"Point"}
}