{
  "type": "Feature",
  "properties": {
    "addr:full":"Oal Diek 3 Ekehaar Drenthe 9454 PL",
    "addr:housenumber":"3",
    "addr:postcode":"9454 pl",
    "addr:street":"Oal Diek",
    "iso:country":"NL",
    "sg:address":"Oal Diek 3",
    "sg:city":"Ekehaar",
    "sg:orig_category":"Overheidsdiensten",
    "sg:phone":"+31 592 389 226",
    "sg:postcode":"9454 PL",
    "sg:province":"Drenthe",
    "wof:name":"Dorphuis De Eekhof",
    "wof:placetype":"venue"
},
  "geometry": {"coordinates":[6.6046700478,52.9525642395],"type":"Point"}
}