{
  "type": "Feature",
  "properties": {
    "addr:full":"Houtstr 1 Almere Flevoland 1353 BA",
    "addr:housenumber":"1",
    "addr:postcode":"1353 ba",
    "addr:street":"Houtstr;Flevoland",
    "iso:country":"NL",
    "sg:address":"Houtstr 1",
    "sg:city":"Almere",
    "sg:orig_category":"Scholen Voor Algemeen Voortgezet Onderwijs",
    "sg:phone":"+31 36 531 3564",
    "sg:postcode":"1353 BA",
    "sg:province":"Flevoland",
    "wof:name":"Buitengronden Dep Sg De Meergrond",
    "wof:placetype":"venue"
},
  "geometry": {"coordinates":[5.216297,52.334629],"type":"Point"}
}