{
  "type": "Feature",
  "properties": {
    "addr:full":"Nijverheidsweg 13 Doetinchem Gelderland 7005 AS",
    "addr:housenumber":"13",
    "addr:postcode":"7005 as",
    "addr:street":"Nijverheidsweg;Gelderland",
    "iso:country":"NL",
    "sg:address":"Nijverheidsweg 13",
    "sg:city":"Doetinchem",
    "sg:orig_category":"Loodgieters- And Verwarmingsmateriaal Gh",
    "sg:phone":"+31 314 344 352",
    "sg:postcode":"7005 AS",
    "sg:province":"Gelderland",
    "wof:name":"Interwarm-Doetinchem Bv",
    "wof:placetype":"venue"
},
  "geometry": {"coordinates":[6.2939,51.951962],"type":"Point"}
}