{
  "type": "Feature",
  "properties": {
    "iso:country":"NL",
    "sg:address":"Kannenburg 131",
    "sg:city":"Deventer",
    "sg:orig_category":"Loodgieterswerk, Verwarming And Sanitaire Installaties",
    "sg:phone":"+31 570 650 347",
    "sg:postcode":"7423 AA",
    "sg:province":"NL.08",
    "wof:name":"Montagebedrijf Ajeki",
    "wof:placetype":"venue"
},
  "geometry": {"coordinates":[6.207764,52.251019],"type":"Point"}
}