{
  "type": "Feature",
  "properties": {
    "iso:country":"NL",
    "sg:address":"Viandenhof 4",
    "sg:city":"Sittard",
    "sg:orig_category":"Technische Studies And Onderzoek",
    "sg:phone":"+31 46 458 9033",
    "sg:postcode":"6137 LJ",
    "sg:province":"North Rhine-Westphalia",
    "wof:name":"Tms Tailor Made Serv",
    "wof:placetype":"venue"
},
  "geometry": {"coordinates":[5.903426,50.99789],"type":"Point"}
}