{
  "type": "Feature",
  "properties": {
    "iso:country":"NL",
    "sg:address":"Pr Margrietwg 2",
    "sg:city":"Houten",
    "sg:orig_category":"Vertalers",
    "sg:phone":"+31 30 637 1812",
    "sg:postcode":"3991 BM",
    "sg:province":"Utrecht",
    "wof:name":"Streamline",
    "wof:placetype":"venue"
},
  "geometry": {"coordinates":[5.165955,52.028839],"type":"Point"}
}