{
  "type": "Feature",
  "properties": {
    "iso:country":"NL",
    "sg:address":"Maaskd 119",
    "sg:city":"Rotterdam",
    "sg:orig_category":"Bedrijfsopleidingen",
    "sg:phone":"+31 10 413 3232",
    "sg:postcode":"3071 NK",
    "sg:province":"Zuid-Holland",
    "sg:website":"http://www.talentacademy.nl",
    "wof:name":"Talent Academy, The",
    "wof:placetype":"venue"
},
  "geometry": {"coordinates":[4.50327,51.910591],"type":"Point"}
}