{
  "type": "Feature",
  "properties": {
    "addr:full":"Hoofdwg 10 Langelo Dr Drenthe 9333 PB",
    "addr:housenumber":"10",
    "addr:postcode":"9333 pb",
    "addr:street":"Hoofdwg;Langelo Dr",
    "iso:country":"NL",
    "sg:address":"Hoofdwg 10",
    "sg:city":"Langelo Dr",
    "sg:classifiers":[
        {
            "category":"Banks & Credit Unions",
            "subcategory":"Investment Brokerage",
            "type":"Services"
        }
    ],
    "sg:phone":"+31 592 612 289",
    "sg:postcode":"9333 PB",
    "sg:province":"Drenthe",
    "sg:tags":[
        "pension"
    ],
    "wof:name":"Bralts",
    "wof:placetype":"venue"
},
  "geometry": {"coordinates":[6.446675,53.091682],"type":"Point"}
}