{
  "type": "Feature",
  "properties": {
    "addr:full":"J W V Puttestr 2 Ameide Zuid-Holland 4233 EL",
    "addr:housenumber":"2",
    "addr:postcode":"4233 el",
    "addr:street":"W V Puttestr",
    "iso:country":"NL",
    "sg:address":"J W V Puttestr 2",
    "sg:city":"Ameide",
    "sg:orig_category":"Bloemen En Planten",
    "sg:phone":"+31 183 601 356",
    "sg:postcode":"4233 EL",
    "sg:province":"Zuid-Holland",
    "wof:name":"Kersbergen, Ron",
    "wof:placetype":"venue"
},
  "geometry": {"coordinates":[4.960446,51.95668],"type":"Point"}
}