{
  "type": "Feature",
  "properties": {
    "addr:full":"Marktpln 5 Lienden Gelderland 4033 EG",
    "addr:housenumber":"5",
    "addr:postcode":"4033 eg",
    "addr:street":"Marktpln;Gelderland",
    "iso:country":"NL",
    "sg:address":"Marktpln 5",
    "sg:city":"Lienden",
    "sg:orig_category":"Schoenen - Reparaties",
    "sg:phone":"+31 344 604 020",
    "sg:postcode":"4033 EG",
    "sg:province":"Gelderland",
    "wof:name":"Ingen, Bert Van",
    "wof:placetype":"venue"
},
  "geometry": {"coordinates":[5.517645,51.950089],"type":"Point"}
}