{
  "type": "Feature",
  "properties": {
    "addr:full":"V Beekstr 69 Landsmeer North Holland 1121 NG",
    "addr:housenumber":"69",
    "addr:postcode":"1121 ng",
    "iso:country":"NL",
    "sg:address":"V Beekstr 69",
    "sg:city":"Landsmeer",
    "sg:orig_category":"Psychologen",
    "sg:phone":"+31 20 482 0677",
    "sg:postcode":"1121 NG",
    "sg:province":"North Holland",
    "wof:name":"Ouderschap En Scheiding, Bureau Voor",
    "wof:placetype":"venue"
},
  "geometry": {"coordinates":[4.91374,52.429974],"type":"Point"}
}