{
  "type": "Feature",
  "properties": {
    "addr:full":"Wollegras 12 Wognum Noord-Holland 1687 WC",
    "addr:housenumber":"12",
    "addr:postcode":"1687 wc",
    "addr:street":"Wollegras",
    "iso:country":"NL",
    "sg:address":"Wollegras 12",
    "sg:city":"Wognum",
    "sg:orig_category":"Glaszetten",
    "sg:phone":"+31 229 574 335",
    "sg:postcode":"1687 WC",
    "sg:province":"Noord-Holland",
    "wof:name":"Wiron",
    "wof:placetype":"venue"
},
  "geometry": {"coordinates":[5.022625,52.678631],"type":"Point"}
}