{
  "type": "Feature",
  "properties": {
    "iso:country":"NL",
    "sg:address":"Slachthuiswg 127",
    "sg:city":"Hengelo Ov",
    "sg:orig_category":"Woninginrichting- Fournituren - Fabrieken En Groothandel",
    "sg:phone":"+31 74 242 8734",
    "sg:postcode":"7556 AZ",
    "sg:province":"Overijssel",
    "wof:name":"Wijnants Bv",
    "wof:placetype":"venue"
},
  "geometry": {"coordinates":[6.7771267891,52.2737350464],"type":"Point"}
}