{
  "type": "Feature",
  "properties": {
    "addr:full":"Slachthuiswg 127 Hengelo Ov Overijssel 7556 AZ",
    "addr:housenumber":"127",
    "addr:postcode":"7556 az",
    "addr:street":"Ov",
    "iso:country":"NL",
    "sg:address":"Slachthuiswg 127",
    "sg:city":"Hengelo Ov",
    "sg:orig_category":"Woninginrichting- Fournituren - Fabrieken En Groothandel",
    "sg:phone":"+31 74 242 8734",
    "sg:postcode":"7556 AZ",
    "sg:province":"Overijssel",
    "wof:name":"Wijnants Bv",
    "wof:placetype":"venue"
},
  "geometry": {"coordinates":[6.7771267891,52.2737350464],"type":"Point"}
}