{
  "type": "Feature",
  "properties": {
    "addr:full":"Boskwei 10 Zwagerbosch Friesland 9299 HT",
    "addr:housenumber":"10",
    "addr:postcode":"9299 ht",
    "addr:street":"Boskwei",
    "iso:country":"NL",
    "sg:address":"Boskwei 10",
    "sg:city":"Zwagerbosch",
    "sg:orig_category":"Verenigingsgebouwen",
    "sg:phone":"+31 511 444 238",
    "sg:postcode":"9299 HT",
    "sg:province":"Friesland",
    "wof:name":"Bosk, De",
    "wof:placetype":"venue"
},
  "geometry": {"coordinates":[6.047464,53.249004],"type":"Point"}
}