{
  "type": "Feature",
  "properties": {
    "addr:full":"Kuifvlinder 7 Diemen Noord-Holland 1113 LP",
    "addr:housenumber":"7",
    "addr:postcode":"1113 lp",
    "addr:street":"Kuifvlinder",
    "iso:country":"NL",
    "sg:address":"Kuifvlinder 7",
    "sg:city":"Diemen",
    "sg:orig_category":"Adviesbureaus Bedrijfsorganisatie",
    "sg:phone":"+31 20 416 1227",
    "sg:postcode":"1113 LP",
    "sg:province":"Noord-Holland",
    "wof:name":"Meijer Bv, A M F",
    "wof:placetype":"venue"
},
  "geometry": {"coordinates":[4.98417,52.347157],"type":"Point"}
}