{
  "type": "Feature",
  "properties": {
    "iso:country":"NL",
    "sg:address":"Tolbrugstr 2",
    "sg:city":"Breda",
    "sg:orig_category":"Kantoorbenodigdheden",
    "sg:phone":"+31 76 521 6468",
    "sg:postcode":"4811 WN",
    "sg:province":"Noord-Brabant",
    "wof:name":"Atlas Tecocel",
    "wof:placetype":"venue"
},
  "geometry": {"coordinates":[4.7727909088,51.5882263184],"type":"Point"}
}