{
  "type": "Feature",
  "properties": {
    "addr:full":"Sierbloem 9 Rotterdam Zuid-Holland 3068 AP",
    "addr:housenumber":"9",
    "addr:postcode":"3068 ap",
    "addr:street":"Sierbloem",
    "iso:country":"NL",
    "sg:address":"Sierbloem 9",
    "sg:city":"Rotterdam",
    "sg:orig_category":"Verzekeringen",
    "sg:phone":"+31 10 455 0053",
    "sg:postcode":"3068 AP",
    "sg:province":"Zuid-Holland",
    "wof:name":"F J J Van De Panne Assurantien Bv",
    "wof:placetype":"venue"
},
  "geometry": {"coordinates":[4.535252,51.955448],"type":"Point"}
}