{
  "type": "Feature",
  "properties": {
    "addr:full":"Lopikerwg O 200A Lopikerkapel Utrecht 3412 KJ",
    "addr:housenumber":"200a",
    "addr:postcode":"3412 kj",
    "addr:street":"Lopikerkapel",
    "iso:country":"NL",
    "sg:address":"Lopikerwg O 200A",
    "sg:city":"Lopikerkapel",
    "sg:orig_category":"Onderhoudswerken",
    "sg:phone":"+31 30 687 1083",
    "sg:postcode":"3412 KJ",
    "sg:province":"Utrecht",
    "wof:name":"Akker, A Van Den",
    "wof:placetype":"venue"
},
  "geometry": {"coordinates":[5.050421,51.994736],"type":"Point"}
}