{
  "type": "Feature",
  "properties": {
    "addr:full":"Spoorstr 55 Ysselmuiden NL.08 8271 RG",
    "addr:housenumber":"55",
    "addr:postcode":"8271 rg",
    "addr:street":"Spoorstr",
    "iso:country":"NL",
    "sg:address":"Spoorstr 55",
    "sg:city":"Ysselmuiden",
    "sg:orig_category":"Hek- En Rasterwerken",
    "sg:phone":"+31 38 333 1917",
    "sg:postcode":"8271 RG",
    "sg:province":"NL.08",
    "wof:name":"Heass",
    "wof:placetype":"venue"
},
  "geometry": {"coordinates":[5.93834,52.555],"type":"Point"}
}