{
  "type": "Feature",
  "properties": {
    "addr:full":"Siriusstraat 104 Tilburg North Brabant 5015 BT",
    "addr:housenumber":"104",
    "addr:postcode":"5015 bt",
    "addr:street":"Siriusstraat",
    "iso:country":"NL",
    "sg:address":"Siriusstraat 104",
    "sg:city":"Tilburg",
    "sg:orig_category":"Autokeuringen",
    "sg:phone":"+31 13 464 8180",
    "sg:postcode":"5015 BT",
    "sg:province":"North Brabant",
    "wof:name":"Wadgep Bv",
    "wof:placetype":"venue"
},
  "geometry": {"coordinates":[5.108,51.571072],"type":"Point"}
}