{
  "type": "Feature",
  "properties": {
    "addr:full":"Schulpstraat 5 Wassenaar Zuid-Holland 2242 XG",
    "addr:housenumber":"5",
    "addr:postcode":"2242 xg",
    "addr:street":"Schulpstraat",
    "iso:country":"NL",
    "sg:address":"Schulpstraat 5",
    "sg:city":"Wassenaar",
    "sg:orig_category":"Reinigingsdiensten",
    "sg:phone":"+31 70 511 5277",
    "sg:postcode":"2242 XG",
    "sg:province":"Zuid-Holland",
    "wof:name":"Briljant",
    "wof:placetype":"venue"
},
  "geometry": {"coordinates":[4.394098,52.148872],"type":"Point"}
}