{
  "type": "Feature",
  "properties": {
    "addr:full":"Ondernemingswg 254 Uithoorn Noord-Holland 1422 DZ",
    "addr:housenumber":"254",
    "addr:postcode":"1422 dz",
    "iso:country":"NL",
    "sg:address":"Ondernemingswg 254",
    "sg:city":"Uithoorn",
    "sg:orig_category":"Horecabenodigdheden",
    "sg:phone":"+31 297 526 597",
    "sg:postcode":"1422 DZ",
    "sg:province":"Noord-Holland",
    "wof:name":"Porcelijn Bv, H",
    "wof:placetype":"venue"
},
  "geometry": {"coordinates":[4.844536,52.243801],"type":"Point"}
}