{
  "type": "Feature",
  "properties": {
    "addr:full":"Voorsboersstr 12 Holten Overijssel 7451 GX",
    "addr:housenumber":"12",
    "addr:postcode":"7451 gx",
    "addr:street":"Voorsboersstr",
    "iso:country":"NL",
    "sg:address":"Voorsboersstr 12",
    "sg:city":"Holten",
    "sg:orig_category":"Schilders",
    "sg:phone":"+31 548 363 061",
    "sg:postcode":"7451 GX",
    "sg:province":"Overijssel",
    "wof:name":"Aanstoot, G",
    "wof:placetype":"venue"
},
  "geometry": {"coordinates":[6.431175,52.281166],"type":"Point"}
}