{
  "type": "Feature",
  "properties": {
    "iso:country":"NL",
    "sg:address":"Randweg 28",
    "sg:city":"Emmeloord",
    "sg:orig_category":"Autokeuringen",
    "sg:phone":"+31 527 634 300",
    "sg:postcode":"8304 AS",
    "sg:province":"NL.",
    "wof:name":"Van Wieren Bv",
    "wof:placetype":"venue"
},
  "geometry": {"coordinates":[5.752304,52.699608],"type":"Point"}
}