{
  "type": "Feature",
  "properties": {
    "addr:full":"K Hoogstr 13A Vlaardingen South Holland 3131 BH",
    "addr:housenumber":"13a",
    "addr:postcode":"3131 bh",
    "addr:street":"Hoogstr",
    "iso:country":"NL",
    "sg:address":"K Hoogstr 13A",
    "sg:city":"Vlaardingen",
    "sg:orig_category":"Zonnebank- En Solariumcentra",
    "sg:phone":"+31 10 434 4242",
    "sg:postcode":"3131 BH",
    "sg:province":"South Holland",
    "sg:website":"http://www.thesuncompany.nl",
    "wof:name":"Sun Company, The",
    "wof:placetype":"venue"
},
  "geometry": {"coordinates":[4.344406,51.912678],"type":"Point"}
}