{
  "type": "Feature",
  "properties": {
    "addr:full":"Verl Spoorln 28 Veenendaal Utrecht 3904 MB",
    "addr:housenumber":"28",
    "addr:postcode":"3904 mb",
    "iso:country":"NL",
    "sg:address":"Verl Spoorln 28",
    "sg:city":"Veenendaal",
    "sg:orig_category":"Verzekeringen - Verzekeringskantoren",
    "sg:phone":"+31 318 516 813",
    "sg:postcode":"3904 MB",
    "sg:province":"Utrecht",
    "sg:website":"http://www.janzegers.nl",
    "wof:name":"Jan Zegers Verzekeringen Bv",
    "wof:placetype":"venue"
},
  "geometry": {"coordinates":[5.55418,52.024902],"type":"Point"}
}