{
  "type": "Feature",
  "properties": {
    "addr:full":"Prinsengr 94 Amsterdam Noord-Holland 1015 DZ",
    "addr:housenumber":"94",
    "addr:postcode":"1015 dz",
    "addr:street":"Prinsengr",
    "iso:country":"NL",
    "sg:address":"Prinsengr 94",
    "sg:city":"Amsterdam",
    "sg:orig_category":"Makelaars En Adviseurs Onroerende Goederen",
    "sg:phone":"+31 20 623 4073",
    "sg:postcode":"1015 DZ",
    "sg:province":"Noord-Holland",
    "wof:name":"Keijzer, D",
    "wof:placetype":"venue"
},
  "geometry": {"coordinates":[4.88491,52.377197],"type":"Point"}
}