{
  "type": "Feature",
  "properties": {
    "addr:full":"Calsln 60 Enschede NL.08 7522 MG",
    "addr:housenumber":"60",
    "addr:postcode":"7522 mg",
    "addr:street":"Calsln",
    "iso:country":"NL",
    "sg:address":"Calsln 60",
    "sg:city":"Enschede",
    "sg:orig_category":"Kappers",
    "sg:phone":"+31 53 489 4158",
    "sg:postcode":"7522 MG",
    "sg:province":"NL.08",
    "wof:name":"Barreboks, De",
    "wof:placetype":"venue"
},
  "geometry": {"coordinates":[6.858520031,52.251449585],"type":"Point"}
}