{
  "type": "Feature",
  "properties": {
    "addr:full":"Hofcampweg 9 Wassenaar South Holland 2241 KD",
    "addr:housenumber":"9",
    "addr:postcode":"2241 kd",
    "addr:street":"Hofcampweg",
    "iso:country":"NL",
    "sg:address":"Hofcampweg 9",
    "sg:city":"Wassenaar",
    "sg:orig_category":"Paramedische Behandelingen",
    "sg:phone":"+31 70 511 5562",
    "sg:postcode":"2241 KD",
    "sg:province":"South Holland",
    "wof:name":"G.C. Daalhuizen",
    "wof:placetype":"venue"
},
  "geometry": {"coordinates":[4.406976,52.142746],"type":"Point"}
}