{
  "type": "Feature",
  "properties": {
    "iso:country":"NL",
    "sg:address":"Haagweg 120",
    "sg:city":"Rijswijk Zh",
    "sg:orig_category":"Artsen And Specialisten",
    "sg:phone":"+31 70 399 2115",
    "sg:postcode":"2282 AH",
    "sg:province":"Zuid-Holland",
    "wof:name":"C.M. De Putter",
    "wof:placetype":"venue"
},
  "geometry": {"coordinates":[4.339209,52.055103],"type":"Point"}
}