{
  "type": "Feature",
  "properties": {
    "addr:full":"A Reynvaanstr 4 Heemskerk Noord-Holland 1963 BV",
    "addr:housenumber":"4",
    "addr:postcode":"1963 bv",
    "iso:country":"NL",
    "sg:address":"A Reynvaanstr 4",
    "sg:city":"Heemskerk",
    "sg:classifiers":[
        {
            "category":"Retail",
            "subcategory":"Auto Repair",
            "type":"Services"
        }
    ],
    "sg:phone":"+31 251 235 291",
    "sg:postcode":"1963 BV",
    "sg:province":"Noord-Holland",
    "sg:tags":[
        "garage"
    ],
    "wof:name":"Brethouwer",
    "wof:placetype":"venue"
},
  "geometry": {"coordinates":[4.686828,52.520229],"type":"Point"}
}