{
  "type": "Feature",
  "properties": {
    "addr:full":"Hoofdstr 275 Sassenheim South Holland 2171 BE",
    "addr:housenumber":"275",
    "addr:postcode":"2171",
    "iso:country":"NL",
    "sg:address":"Hoofdstr 275",
    "sg:city":"Sassenheim",
    "sg:orig_category":"Psychologen",
    "sg:phone":"+31 252 213 726",
    "sg:postcode":"2171 BE",
    "sg:province":"South Holland",
    "wof:name":"Schreuder, Drs T L",
    "wof:placetype":"venue"
},
  "geometry": {"coordinates":[4.524958,52.228474],"type":"Point"}
}