{
  "type": "Feature",
  "properties": {
    "iso:country":"NL",
    "sg:address":"Energiewg 4-6",
    "sg:city":"Beneden Leeuwen",
    "sg:orig_category":"Meubelen - Fabrieken En Groothandel",
    "sg:phone":"+31 487 595 320",
    "sg:postcode":"6658 AD",
    "sg:province":"Gelderland",
    "wof:name":"Ha-Es Vof",
    "wof:placetype":"venue"
},
  "geometry": {"coordinates":[5.533331,51.886631],"type":"Point"}
}