{
  "type": "Feature",
  "properties": {
    "iso:country":"NL",
    "sg:address":"Oosteinde 2B",
    "sg:city":"Roden",
    "sg:orig_category":"Adviesbureaus Bedrijfsorganisatie",
    "sg:phone":"+31 50 501 3434",
    "sg:postcode":"9301 LJ",
    "sg:province":"Provincie Drenthe",
    "wof:name":"Vdp",
    "wof:placetype":"venue"
},
  "geometry": {"coordinates":[6.440399,53.142097],"type":"Point"}
}