{
  "type": "Feature",
  "properties": {
    "iso:country":"NL",
    "sg:address":"Bruispad 2",
    "sg:city":"Amersfoort",
    "sg:orig_category":"Bibliotheken And Openbare Archieven",
    "sg:phone":"+31 33 480 6032",
    "sg:postcode":"3813 PV",
    "sg:province":"Utrecht",
    "wof:name":"Stichting Welzijnswerk De Trefhorst",
    "wof:placetype":"venue"
},
  "geometry": {"coordinates":[5.38707,52.173016],"type":"Point"}
}