{
  "type": "Feature",
  "properties": {
    "addr:full":"Pastoor Meriusstraat 187 Spanbroek Noord-Holland 1715 VD",
    "addr:housenumber":"187",
    "addr:postcode":"1715 vd",
    "addr:street":"Pastoor Meriusstraat",
    "iso:country":"NL",
    "sg:address":"Pastoor Meriusstraat 187",
    "sg:city":"Spanbroek",
    "sg:orig_category":"Begrafenisondernemers",
    "sg:phone":"+31 226 352 198",
    "sg:postcode":"1715 VD",
    "sg:province":"Noord-Holland",
    "wof:name":"Uitvaartverzorging P J M Sneek",
    "wof:placetype":"venue"
},
  "geometry": {"coordinates":[4.95258,52.698914],"type":"Point"}
}