{
  "type": "Feature",
  "properties": {
    "addr:full":"M V Coehoornsngl 16 Zwolle NL.08 8011 XA",
    "addr:housenumber":"16",
    "addr:postcode":"8011 xa",
    "addr:street":"Coehoornsngl",
    "iso:country":"NL",
    "sg:address":"M V Coehoornsngl 16",
    "sg:city":"Zwolle",
    "sg:orig_category":"Verenigingen En Stichtingen",
    "sg:phone":"+31 38 426 2000",
    "sg:postcode":"8011 XA",
    "sg:province":"NL.08",
    "wof:name":"Pati\u00ebnten Consumenten Platform Zwolle",
    "wof:placetype":"venue"
},
  "geometry": {"coordinates":[6.088738,52.512566],"type":"Point"}
}