{
  "type": "Feature",
  "properties": {
    "iso:country":"NL",
    "sg:address":"Muiderslotweg 135",
    "sg:city":"Haarlem",
    "sg:orig_category":"Verzekeringen",
    "sg:phone":"+31 23 537 1970",
    "sg:postcode":"2026 AL",
    "sg:province":"Noord-Holland",
    "wof:name":"C.F.M. De Jong Financiele Dienstverlenin",
    "wof:placetype":"venue"
},
  "geometry": {"coordinates":[4.653719,52.418747],"type":"Point"}
}