{
  "type": "Feature",
  "properties": {
    "addr:full":"Regentessepln 220 S Gravenhage Zuid-Holland 2562 EZ",
    "addr:housenumber":"220;gravenhage",
    "addr:postcode":"2562 ez",
    "addr:street":"S",
    "iso:country":"NL",
    "sg:address":"Regentessepln 220",
    "sg:city":"S Gravenhage",
    "sg:orig_category":"Kampeerartikelen",
    "sg:phone":"+31 70 345 7915",
    "sg:postcode":"2562 EZ",
    "sg:province":"Zuid-Holland",
    "wof:name":"Huna, Camping- & Outdoorshop",
    "wof:placetype":"venue"
},
  "geometry": {"coordinates":[4.2832598686,52.0750007629],"type":"Point"}
}