{
  "type": "Feature",
  "properties": {
    "addr:full":"Veurseweg 210 Voorschoten Zuid-Holland 2252 AH",
    "addr:housenumber":"210",
    "addr:postcode":"2252 ah",
    "addr:street":"Veurseweg",
    "iso:country":"NL",
    "sg:address":"Veurseweg 210",
    "sg:city":"Voorschoten",
    "sg:orig_category":"Juridische Dienstverlening",
    "sg:phone":"+31 71 561 5699",
    "sg:postcode":"2252 AH",
    "sg:province":"Zuid-Holland",
    "wof:name":"Bbb",
    "wof:placetype":"venue"
},
  "geometry": {"coordinates":[4.433199,52.114338],"type":"Point"}
}