{
  "type": "Feature",
  "properties": {
    "addr:full":"Kryptonweg 11 Amersfoort Utrecht 3812 RZ",
    "addr:housenumber":"11",
    "addr:postcode":"3812 rz",
    "addr:street":"Kryptonweg",
    "iso:country":"NL",
    "sg:address":"Kryptonweg 11",
    "sg:city":"Amersfoort",
    "sg:orig_category":"Autoreparatie And Auto-Onderhoud",
    "sg:phone":"+31 33 461 3858",
    "sg:postcode":"3812 RZ",
    "sg:province":"Utrecht",
    "wof:name":"Autoschade Rijnders Amersfoort Bv",
    "wof:placetype":"venue"
},
  "geometry": {"coordinates":[5.350161,52.16573],"type":"Point"}
}