{
  "type": "Feature",
  "properties": {
    "addr:full":"Koggeln 46 Heerhugowaard Noord-Holland 1705 EM",
    "addr:housenumber":"46",
    "addr:postcode":"1705 em",
    "addr:street":"Koggeln",
    "iso:country":"NL",
    "sg:address":"Koggeln 46",
    "sg:city":"Heerhugowaard",
    "sg:orig_category":"Administratie- En Boekhoudkantoren",
    "sg:phone":"+31 72 572 6460",
    "sg:postcode":"1705 EM",
    "sg:province":"Noord-Holland",
    "wof:name":"Mulder",
    "wof:placetype":"venue"
},
  "geometry": {"coordinates":[4.827522,52.665195],"type":"Point"}
}