{
  "type": "Feature",
  "properties": {
    "addr:full":"Parijsln 50 Eindhoven Noord-Brabant 5627 TR",
    "addr:housenumber":"50",
    "addr:postcode":"5627 tr",
    "addr:street":"Parijsln",
    "iso:country":"NL",
    "sg:address":"Parijsln 50",
    "sg:city":"Eindhoven",
    "sg:orig_category":"Fotopersbureaus",
    "sg:phone":"+31 40 262 2560",
    "sg:postcode":"5627 TR",
    "sg:province":"Noord-Brabant",
    "wof:name":"Smulders Bv, Peter",
    "wof:placetype":"venue"
},
  "geometry": {"coordinates":[5.44142,51.484638],"type":"Point"}
}