{
  "type": "Feature",
  "properties": {
    "addr:full":"Prinsengr 206 Amsterdam Noord-Holland 1016 HD",
    "addr:housenumber":"206",
    "addr:postcode":"1016 hd",
    "iso:country":"NL",
    "sg:address":"Prinsengr 206",
    "sg:city":"Amsterdam",
    "sg:orig_category":"Woningbureaus",
    "sg:phone":"+31 20 422 0970",
    "sg:postcode":"1016 HD",
    "sg:province":"Noord-Holland",
    "wof:name":"Prinsen Residence",
    "wof:placetype":"venue"
},
  "geometry": {"coordinates":[4.8826198578,52.3733100891],"type":"Point"}
}