{
  "type": "Feature",
  "properties": {
    "iso:country":"NL",
    "sg:address":"Horsterplein 20",
    "sg:city":"Zeewolde",
    "sg:classifiers":[
        {
            "category":"Fast Food",
            "type":"Food & Drink"
        }
    ],
    "sg:phone":"+31 36 522 1173",
    "sg:postcode":"3891 ES",
    "sg:province":"Flevoland",
    "sg:tags":[
        "afhaal",
        "restaurant"
    ],
    "wof:name":"Twilight",
    "wof:placetype":"venue"
},
  "geometry": {"coordinates":[5.543201,52.330475],"type":"Point"}
}