{
  "type": "Feature",
  "properties": {
    "addr:full":"Vertrekpassage 233 Luchth Schiphol Noord-Holland 1118 AV",
    "addr:housenumber":"233",
    "addr:postcode":"1118 av",
    "addr:street":"Vertrekpassage",
    "iso:country":"NL",
    "sg:address":"Vertrekpassage 233",
    "sg:city":"Luchth Schiphol",
    "sg:orig_category":"Luchtvaart- Maatschappijen",
    "sg:phone":"+31 20 405 7816",
    "sg:postcode":"1118 AV",
    "sg:province":"Noord-Holland",
    "wof:name":"Royal Air Maroc",
    "wof:placetype":"venue"
},
  "geometry": {"coordinates":[4.761103,52.309837],"type":"Point"}
}