{
  "type": "Feature",
  "properties": {
    "iso:country":"NL",
    "sg:address":"Tolnasngl 3",
    "sg:city":"Bodegraven",
    "sg:orig_category":"Bedrijfshuisvesting",
    "sg:phone":"+31 172 632 732",
    "sg:postcode":"2411 PV",
    "sg:province":"South Holland",
    "sg:website":"http://www.deraad.nl",
    "wof:name":"Crown",
    "wof:placetype":"venue"
},
  "geometry": {"coordinates":[4.747547,52.085552],"type":"Point"}
}