{
  "type": "Feature",
  "properties": {
    "addr:full":"Nijbracht 78 Emmen Drenthe 7821 CA",
    "addr:housenumber":"78",
    "addr:postcode":"7821 ca",
    "addr:street":"Nijbracht",
    "iso:country":"NL",
    "sg:address":"Nijbracht 78",
    "sg:city":"Emmen",
    "sg:orig_category":"Meubelzaken, Woning- And Keukeninrichting",
    "sg:phone":"+31 591 658 711",
    "sg:postcode":"7821 CA",
    "sg:province":"Drenthe",
    "wof:name":"H.J. Wortelboer",
    "wof:placetype":"venue"
},
  "geometry": {"coordinates":[6.902595,52.763737],"type":"Point"}
}