{
  "type": "Feature",
  "properties": {
    "addr:full":"Giessenwg 19-21 Rotterdam Zuid-Holland 3044 AK",
    "addr:housenumber":"19-21",
    "addr:postcode":"rotterdam;3044 ak",
    "iso:country":"NL",
    "sg:address":"Giessenwg 19-21",
    "sg:city":"Rotterdam",
    "sg:orig_category":"Meubelen - Fabrieken En Groothandel",
    "sg:phone":"+31 10 462 7370",
    "sg:postcode":"3044 AK",
    "sg:province":"Zuid-Holland",
    "sg:website":"http://www.pareldesign.nl",
    "wof:name":"Parel",
    "wof:placetype":"venue"
},
  "geometry": {"coordinates":[4.424451,51.92593],"type":"Point"}
}