{
  "type": "Feature",
  "properties": {
    "addr:full":"Tammingecamp 42 Emmen Provincie Drenthe 7824 GP",
    "addr:housenumber":"42",
    "addr:postcode":"7824 gp",
    "addr:street":"Tammingecamp;Provincie Drenthe",
    "iso:country":"NL",
    "sg:address":"Tammingecamp 42",
    "sg:city":"Emmen",
    "sg:orig_category":"Verzekeringen",
    "sg:phone":"+31 591 624 079",
    "sg:postcode":"7824 GP",
    "sg:province":"Provincie Drenthe",
    "wof:name":"Emmer-Assurantiekantoor Middelveld",
    "wof:placetype":"venue"
},
  "geometry": {"coordinates":[6.928271,52.781673],"type":"Point"}
}