{
  "type": "Feature",
  "properties": {
    "iso:country":"NL",
    "sg:address":"Tammingecamp 42",
    "sg:city":"Emmen",
    "sg:orig_category":"Verzekeringen",
    "sg:phone":"+31 591 624 079",
    "sg:postcode":"7824 GP",
    "sg:province":"Provincie Drenthe",
    "wof:name":"Emmer-Assurantiekantoor Middelveld",
    "wof:placetype":"venue"
},
  "geometry": {"coordinates":[6.928271,52.781673],"type":"Point"}
}