{
  "type": "Feature",
  "properties": {
    "addr:full":"Van Borseleln 1 Veere Zeeland 4351 NR",
    "addr:housenumber":"1",
    "addr:postcode":"4351 nr",
    "iso:country":"NL",
    "sg:address":"Van Borseleln 1",
    "sg:city":"Veere",
    "sg:classifiers":[
        {
            "category":"Personal",
            "subcategory":"Nail Salon",
            "type":"Services"
        }
    ],
    "sg:phone":"+31 118 501 923",
    "sg:postcode":"4351 NR",
    "sg:province":"Zeeland",
    "sg:tags":[
        "pedicure"
    ],
    "wof:name":"Pieters, Y",
    "wof:placetype":"venue"
},
  "geometry": {"coordinates":[3.667145,51.548683],"type":"Point"}
}