{
  "type": "Feature",
  "properties": {
    "iso:country":"NL",
    "sg:address":"Oude Deldensestraat 8",
    "sg:city":"Diepenheim",
    "sg:orig_category":"Autokeuringen",
    "sg:phone":"+31 545 293 724",
    "sg:postcode":"7478 PL",
    "sg:province":"Overijssel",
    "wof:name":"F.L.J. Ten Dam",
    "wof:placetype":"venue"
},
  "geometry": {"coordinates":[6.613125,52.16552],"type":"Point"}
}