{
  "type": "Feature",
  "properties": {
    "addr:full":"Graafsebaan 61/B Rosmalen North Brabant 5248 JT",
    "addr:housenumber":"61 / b",
    "addr:postcode":"5248 jt",
    "addr:street":"Graafsebaan",
    "iso:country":"NL",
    "sg:address":"Graafsebaan 61/B",
    "sg:city":"Rosmalen",
    "sg:orig_category":"Kappers",
    "sg:phone":"+31 73 521 7188",
    "sg:postcode":"5248 JT",
    "sg:province":"North Brabant",
    "wof:name":"Petit",
    "wof:placetype":"venue"
},
  "geometry": {"coordinates":[5.359786,51.702747],"type":"Point"}
}