{
  "type": "Feature",
  "properties": {
    "addr:full":"Westeinde 10 'S Gravenhage South Holland 2512 HD",
    "addr:housenumber":"10",
    "addr:postcode":"2512 hd",
    "addr:street":"Westeinde;' S Gravenhage",
    "iso:country":"NL",
    "sg:address":"Westeinde 10",
    "sg:city":"'S Gravenhage",
    "sg:orig_category":"Platenmaatschappijen",
    "sg:phone":"+31 70 346 9494",
    "sg:postcode":"2512 HD",
    "sg:province":"South Holland",
    "wof:name":"Ottavo Recordings Vof",
    "wof:placetype":"venue"
},
  "geometry": {"coordinates":[4.306171,52.076611],"type":"Point"}
}