{
  "type": "Feature",
  "properties": {
    "addr:full":"Boscheind 73 Luyksgestel North Brabant 5575 AA",
    "addr:housenumber":"73",
    "addr:postcode":"5575 aa",
    "addr:street":"Boscheind",
    "iso:country":"NL",
    "sg:address":"Boscheind 73",
    "sg:city":"Luyksgestel",
    "sg:classifiers":[
        {
            "category":"Travel",
            "subcategory":"Hotels & Motels",
            "type":"Entertainment"
        }
    ],
    "sg:phone":"+31 497 541 426",
    "sg:postcode":"5575 AA",
    "sg:province":"North Brabant",
    "sg:website":"http://www.postelhoef.nl",
    "wof:name":"Postelhoef, De",
    "wof:placetype":"venue"
},
  "geometry": {"coordinates":[5.305565,51.281815],"type":"Point"}
}