{
  "type": "Feature",
  "properties": {
    "addr:full":"Couwenhoven 6217 Zeist Limburg 3703 HM",
    "addr:housenumber":"6217",
    "addr:postcode":"3703 hm",
    "addr:street":"Couwenhoven",
    "iso:country":"NL",
    "sg:address":"Couwenhoven 6217",
    "sg:city":"Zeist",
    "sg:orig_category":"Architecten En Architectenbureaus",
    "sg:phone":"+31 30 696 3921",
    "sg:postcode":"3703 HM",
    "sg:province":"Limburg",
    "sg:website":"http://www.funon.nl",
    "wof:name":"Funon, Bouwkundig Ontwerpburo",
    "wof:placetype":"venue"
},
  "geometry": {"coordinates":[5.224387,52.077538],"type":"Point"}
}