{
  "type": "Feature",
  "properties": {
    "iso:country":"NL",
    "sg:address":"Meester Strikstr 5",
    "sg:city":"Helmond",
    "sg:classifiers":[
        {
            "category":"Wholesale",
            "subcategory":"Motor Vehicles",
            "type":"Manufacturing & Wholesale Goods"
        }
    ],
    "sg:phone":"+31 492 474 727",
    "sg:postcode":"5708 GA",
    "sg:province":"North Brabant",
    "sg:tags":[
        "scooter",
        "en"
    ],
    "wof:name":"Pk",
    "wof:placetype":"venue"
},
  "geometry": {"coordinates":[5.617066,51.487316],"type":"Point"}
}