{
  "type": "Feature",
  "properties": {
    "addr:full":"Stephensonweg 7 Gorinchem Zuid-Holland 4207 HA",
    "addr:housenumber":"7",
    "addr:postcode":"4207 ha",
    "addr:street":"Stephensonweg",
    "iso:country":"NL",
    "sg:address":"Stephensonweg 7",
    "sg:city":"Gorinchem",
    "sg:orig_category":"Huishoudapparatuur, Televisies And Radio'S",
    "sg:phone":"+31 183 627 500",
    "sg:postcode":"4207 HA",
    "sg:province":"Zuid-Holland",
    "wof:name":"Mubo Bv",
    "wof:placetype":"venue"
},
  "geometry": {"coordinates":[5.000729,51.842358],"type":"Point"}
}