{
  "type": "Feature",
  "properties": {
    "iso:country":"NL",
    "sg:address":"Wooldstraat 20",
    "sg:city":"Winterswijk",
    "sg:orig_category":"Bloemen And Planten",
    "sg:phone":"+31 543 512 399",
    "sg:postcode":"7101 NR",
    "sg:province":"Gelderland",
    "wof:name":"Oxalis Bloemen- En Plantenshop",
    "wof:placetype":"venue"
},
  "geometry": {"coordinates":[6.720704,51.970436],"type":"Point"}
}