{
  "type": "Feature",
  "properties": {
    "addr:full":"Zusterpln 22A Zeist Utrecht 3703 CB",
    "addr:housenumber":"22a",
    "addr:postcode":"3703 cb",
    "addr:street":"Zusterpln",
    "iso:country":"NL",
    "sg:address":"Zusterpln 22A",
    "sg:city":"Zeist",
    "sg:orig_category":"Verenigingen En Stichtingen",
    "sg:phone":"+31 30 692 7811",
    "sg:postcode":"3703 CB",
    "sg:province":"Utrecht",
    "sg:website":"http://www.icco.nl",
    "wof:name":"Icco",
    "wof:placetype":"venue"
},
  "geometry": {"coordinates":[5.235355,52.080452],"type":"Point"}
}