{
  "type": "Feature",
  "properties": {
    "addr:full":"Polakweg 3A Rijswijk Zh South Holland 2288 GE",
    "addr:housenumber":"3a",
    "addr:postcode":"2288",
    "addr:street":"Polakweg",
    "iso:country":"NL",
    "sg:address":"Polakweg 3A",
    "sg:city":"Rijswijk Zh",
    "sg:orig_category":"Werving And Selectie Van Tijdelijk Personeel And Uitzendkantoren",
    "sg:phone":"+31 70 319 0130",
    "sg:postcode":"2288 GE",
    "sg:province":"South Holland",
    "wof:name":"Condor Yasar Int.",
    "wof:placetype":"venue"
},
  "geometry": {"coordinates":[4.3349637985,52.0364379883],"type":"Point"}
}