{
  "type": "Feature",
  "properties": {
    "iso:country":"NL",
    "sg:address":"Postbus 16",
    "sg:city":"Bedum",
    "sg:orig_category":"Administratie- En Boekhoudkantoren",
    "sg:phone":"+31 50 301 5917",
    "sg:postcode":"9780 AA",
    "sg:province":"Groningen",
    "wof:name":"Huisman",
    "wof:placetype":"venue"
},
  "geometry": {"coordinates":[6.597629,53.300678],"type":"Point"}
}