{
  "type": "Feature",
  "properties": {
    "addr:full":"Roundeel 56 Oudega Gem Small North Carolina 9216 XA",
    "addr:housenumber":"56",
    "addr:postcode":"9216 xa",
    "addr:street":"Roundeel",
    "iso:country":"NL",
    "sg:address":"Roundeel 56",
    "sg:city":"Oudega Gem Small",
    "sg:orig_category":"Artsen - Huisartsen",
    "sg:phone":"+31 512 371 262",
    "sg:postcode":"9216 XA",
    "sg:province":"North Carolina",
    "wof:name":"Tholen, A Van Der",
    "wof:placetype":"venue"
},
  "geometry": {"coordinates":[-76.85424,35.284199],"type":"Point"}
}