{
  "type": "Feature",
  "properties": {
    "iso:country":"NL",
    "sg:address":"Noordeinde 12",
    "sg:city":"Monnickendam",
    "sg:orig_category":"Fietsen En Bromfietsen",
    "sg:phone":"+31 299 651 267",
    "sg:postcode":"1141 AM",
    "sg:province":"Noord-Holland",
    "wof:name":"Koning, L F",
    "wof:placetype":"venue"
},
  "geometry": {"coordinates":[5.035683,52.459625],"type":"Point"}
}