{
  "type": "Feature",
  "properties": {
    "addr:full":"Hoofdstr 159 Zuidwolde Dr Drenthe 7921 AJ",
    "addr:housenumber":"159",
    "addr:postcode":"7921 aj",
    "addr:street":"Zuidwolde Dr",
    "iso:country":"NL",
    "sg:address":"Hoofdstr 159",
    "sg:city":"Zuidwolde Dr",
    "sg:orig_category":"Kinderkleding",
    "sg:phone":"+31 6 27223888",
    "sg:postcode":"7921 AJ",
    "sg:province":"Drenthe",
    "wof:name":"Koko",
    "wof:placetype":"venue"
},
  "geometry": {"coordinates":[6.42853,52.67675],"type":"Point"}
}