{
  "type": "Feature",
  "properties": {
    "addr:full":"Nyverheidspln 7 Heerhugowaard Noord-Holland 1704 RB",
    "addr:housenumber":"7",
    "addr:postcode":"1704 rb",
    "addr:street":"Nyverheidspln",
    "iso:country":"NL",
    "sg:address":"Nyverheidspln 7",
    "sg:city":"Heerhugowaard",
    "sg:orig_category":"Houtwormverdelging",
    "sg:phone":"+31 72 574 1856",
    "sg:postcode":"1704 RB",
    "sg:province":"Noord-Holland",
    "wof:name":"Lierop Bv, Van",
    "wof:placetype":"venue"
},
  "geometry": {"coordinates":[4.830632,52.674641],"type":"Point"}
}