{
  "type": "Feature",
  "properties": {
    "addr:full":"Zegwaartseweg 166 Zoetermeer South Holland 2728 PC",
    "addr:housenumber":"166",
    "addr:postcode":"2728 pc",
    "addr:street":"Zegwaartseweg",
    "iso:country":"NL",
    "sg:address":"Zegwaartseweg 166",
    "sg:city":"Zoetermeer",
    "sg:orig_category":"Verzekeringen",
    "sg:phone":"+31 79 331 4863",
    "sg:postcode":"2728 PC",
    "sg:province":"South Holland",
    "wof:name":"Assurantiekantoor Zaal",
    "wof:placetype":"venue"
},
  "geometry": {"coordinates":[4.527738,52.068352],"type":"Point"}
}