{
  "type": "Feature",
  "properties": {
    "addr:full":"Bekemaheerd 111 Groningen Groningen 9737 PS",
    "addr:housenumber":"111",
    "addr:postcode":"9737 ps",
    "addr:street":"Bekemaheerd",
    "iso:country":"NL",
    "sg:address":"Bekemaheerd 111",
    "sg:city":"Groningen",
    "sg:orig_category":"Fotografie Reclame En Mode",
    "sg:phone":"+31 50 542 0590",
    "sg:postcode":"9737 PS",
    "sg:province":"Groningen",
    "wof:name":"Sfinx, Studio",
    "wof:placetype":"venue"
},
  "geometry": {"coordinates":[6.582772,53.248055],"type":"Point"}
}