{
  "type": "Feature",
  "properties": {
    "addr:full":"Verlaat 59 Veenendaal Utrecht 3901 RE",
    "addr:housenumber":"59",
    "addr:postcode":"3901",
    "addr:street":"Verlaat",
    "iso:country":"NL",
    "sg:address":"Verlaat 59",
    "sg:city":"Veenendaal",
    "sg:orig_category":"Zuivelproducten",
    "sg:phone":"+31 318 522 321",
    "sg:postcode":"3901 RE",
    "sg:province":"Utrecht",
    "wof:name":"De Zelfkazer",
    "wof:placetype":"venue"
},
  "geometry": {"coordinates":[5.56198,52.027061],"type":"Point"}
}