{
  "type": "Feature",
  "properties": {
    "addr:full":"Bovenveld 6 Donkerbroek Friesland 8435 VA",
    "addr:housenumber":"6",
    "addr:postcode":"8435",
    "addr:street":"Bovenveld",
    "iso:country":"NL",
    "sg:address":"Bovenveld 6",
    "sg:city":"Donkerbroek",
    "sg:orig_category":"Naamplaten - Fabrieken",
    "sg:phone":"+31 516 491 595",
    "sg:postcode":"8435 VA",
    "sg:province":"Friesland",
    "wof:name":"Ambachtelijk Atelier Moelee",
    "wof:placetype":"venue"
},
  "geometry": {"coordinates":[-79.771446,38.003349],"type":"Point"}
}