{
  "type": "Feature",
  "properties": {
    "iso:country":"NL",
    "sg:address":"Abbenesstr 10",
    "sg:city":"Amsterdam",
    "sg:orig_category":"Vertalers",
    "sg:phone":"+31 20 669 6496",
    "sg:postcode":"1059 TD",
    "sg:province":"Noord-Holland",
    "wof:name":"Piggott",
    "wof:placetype":"venue"
},
  "geometry": {"coordinates":[4.847262,52.348099],"type":"Point"}
}