{
  "type": "Feature",
  "properties": {
    "addr:full":"Molenstraat 22 Grijpskerke Zeeland 4364 AA",
    "addr:housenumber":"22",
    "addr:postcode":"4364 aa",
    "addr:street":"Molenstraat",
    "iso:country":"NL",
    "sg:address":"Molenstraat 22",
    "sg:city":"Grijpskerke",
    "sg:orig_category":"Schilderwerk",
    "sg:phone":"+31 118 591 658",
    "sg:postcode":"4364 AA",
    "sg:province":"Zeeland",
    "wof:name":"Vof Schildersbedrijf Schiboo Grijpskerke",
    "wof:placetype":"venue"
},
  "geometry": {"coordinates":[3.561873,51.530636],"type":"Point"}
}