{
  "type": "Feature",
  "properties": {
    "addr:full":"Slauerhoffln 22 Groningen Groningen 9721 ZP",
    "addr:housenumber":"22",
    "addr:postcode":"9721 zp",
    "addr:street":"Slauerhoffln",
    "iso:country":"NL",
    "sg:address":"Slauerhoffln 22",
    "sg:city":"Groningen",
    "sg:orig_category":"Bevestigingsmaterialen",
    "sg:phone":"+31 50 527 5656",
    "sg:postcode":"9721 ZP",
    "sg:province":"Groningen",
    "sg:website":"http://www.nord-lock.nl",
    "wof:name":"Nord Lock Benelux",
    "wof:placetype":"venue"
},
  "geometry": {"coordinates":[6.57473,53.194111],"type":"Point"}
}