{
  "type": "Feature",
  "properties": {
    "addr:full":"Celsiusweg 32 Venlo Limburg 5928 PR",
    "addr:housenumber":"32",
    "addr:postcode":"5928 pr",
    "addr:street":"Celsiusweg",
    "iso:country":"NL",
    "sg:address":"Celsiusweg 32",
    "sg:city":"Venlo",
    "sg:orig_category":"Krantenuitgeverijen",
    "sg:phone":"+31 77 387 2927",
    "sg:postcode":"5928 PR",
    "sg:province":"Limburg",
    "wof:name":"Allmedia Holland Management Bv",
    "wof:placetype":"venue"
},
  "geometry": {"coordinates":[6.134696,51.390839],"type":"Point"}
}