{
  "type": "Feature",
  "properties": {
    "addr:full":"Prinsenlaan 2 De Bilt Utrecht 3732 GN",
    "addr:housenumber":"2",
    "addr:postcode":"3732 gn",
    "addr:street":"Prinsenlaan",
    "iso:country":"NL",
    "sg:address":"Prinsenlaan 2",
    "sg:city":"De Bilt",
    "sg:orig_category":"Werving En Selectie",
    "sg:phone":"+31 30 697 7240",
    "sg:postcode":"3732 GN",
    "sg:province":"Utrecht",
    "wof:name":"Caspers, Rudolf",
    "wof:placetype":"venue"
},
  "geometry": {"coordinates":[5.1799149513,52.1026611328],"type":"Point"}
}