{
  "type": "Feature",
  "properties": {
    "addr:full":"Deltaplein 512-513 'S Gravenhage Zuid-Holland 2554 GH",
    "addr:housenumber":"512-513",
    "addr:postcode":"2554 gh",
    "addr:street":"Deltaplein;' S",
    "iso:country":"NL",
    "sg:address":"Deltaplein 512-513",
    "sg:city":"'S Gravenhage",
    "sg:orig_category":"Boekenuitgeverijen",
    "sg:phone":"+31 70 368 9461",
    "sg:postcode":"2554 GH",
    "sg:province":"Zuid-Holland",
    "wof:name":"Boekhand Vd Brande",
    "wof:placetype":"venue"
},
  "geometry": {"coordinates":[4.220688,52.068306],"type":"Point"}
}