{
  "type": "Feature",
  "properties": {
    "iso:country":"NL",
    "sg:address":"Prof Pulleln 32",
    "sg:city":"Utrecht",
    "sg:orig_category":"Adviesbureaus",
    "sg:phone":"+31 30 271 7610",
    "sg:postcode":"3571 JD",
    "sg:province":"Utrecht",
    "wof:name":"Rural Bv",
    "wof:placetype":"venue"
},
  "geometry": {"coordinates":[5.13077,52.106426],"type":"Point"}
}