{
  "type": "Feature",
  "properties": {
    "addr:full":"Binnenweg/Raadhuisstraat Heemstede North Holland 2001 JH",
    "addr:postcode":"2001 jh",
    "addr:street":"Raadhuisstraat",
    "iso:country":"NL",
    "sg:address":"Binnenweg/Raadhuisstraat",
    "sg:city":"Heemstede",
    "sg:orig_category":"Winkelcentra",
    "sg:phone":"+31 163",
    "sg:postcode":"2001 JH",
    "sg:province":"North Holland",
    "wof:name":"Heemstede Binnenstad",
    "wof:placetype":"venue"
},
  "geometry": {"coordinates":[4.621240139,52.3452987671],"type":"Point"}
}