{
  "type": "Feature",
  "properties": {
    "iso:country":"NL",
    "sg:address":"Julianastraat 4",
    "sg:city":"Nijkerk Gld",
    "sg:orig_category":"Persbureaus",
    "sg:phone":"+31 33 245 6761",
    "sg:postcode":"3862 CT",
    "sg:province":"Gelderland",
    "wof:name":"Optica",
    "wof:placetype":"venue"
},
  "geometry": {"coordinates":[5.491125,52.225883],"type":"Point"}
}