{
  "type": "Feature",
  "properties": {
    "addr:full":"Hoogstr 101 Eindhoven Noord-Brabant 5615 PB",
    "addr:housenumber":"101",
    "addr:postcode":"5615 pb",
    "iso:country":"NL",
    "sg:address":"Hoogstr 101",
    "sg:city":"Eindhoven",
    "sg:orig_category":"New Age-Artikelen En -Diensten",
    "sg:phone":"+31 40 244 1998",
    "sg:postcode":"5615 PB",
    "sg:province":"Noord-Brabant",
    "sg:website":"http://www.earthspirits.nl",
    "wof:name":"Earth Spirits",
    "wof:placetype":"venue"
},
  "geometry": {"coordinates":[5.484105,51.434471],"type":"Point"}
}