{
  "type": "Feature",
  "properties": {
    "addr:full":"Oranje Vrystaatkd 29 Amsterdam Noord-Holland 1093 KS",
    "addr:housenumber":"29",
    "addr:postcode":"1093 ks",
    "iso:country":"NL",
    "sg:address":"Oranje Vrystaatkd 29",
    "sg:city":"Amsterdam",
    "sg:orig_category":"Biljartzalen",
    "sg:phone":"+31 20 668 4018",
    "sg:postcode":"1093 KS",
    "sg:province":"Noord-Holland",
    "wof:name":"Snooker World",
    "wof:placetype":"venue"
},
  "geometry": {"coordinates":[4.929809,52.356361],"type":"Point"}
}