{
  "type": "Feature",
  "properties": {
    "addr:full":"Nieuwstraat 2 Zwolle NL.08 8011 TP",
    "addr:housenumber":"2",
    "addr:postcode":"8011",
    "addr:street":"Nieuwstraat;Tp",
    "iso:country":"NL",
    "sg:address":"Nieuwstraat 2",
    "sg:city":"Zwolle",
    "sg:orig_category":"Werving And Selectie Van Tijdelijk Personeel And Uitzendkantoren",
    "sg:phone":"+31 38 421 3070",
    "sg:postcode":"8011 TP",
    "sg:province":"NL.08",
    "wof:name":"All-Service",
    "wof:placetype":"venue"
},
  "geometry": {"coordinates":[6.0887379646,52.5125656128],"type":"Point"}
}