{
  "type": "Feature",
  "properties": {
    "addr:full":"Kerkstraat 15 Soest Utrecht 3764 CR",
    "addr:housenumber":"15",
    "addr:postcode":"3764 cr",
    "addr:street":"Kerkstraat",
    "iso:country":"NL",
    "sg:address":"Kerkstraat 15",
    "sg:city":"Soest",
    "sg:orig_category":"Kantoor- And Schoolbenodigdheden Gh",
    "sg:phone":"+31 35 603 2302",
    "sg:postcode":"3764 CR",
    "sg:province":"Utrecht",
    "wof:name":"Toppapier Bv",
    "wof:placetype":"venue"
},
  "geometry": {"coordinates":[5.3003849983,52.1840438843],"type":"Point"}
}