{
  "type": "Feature",
  "properties": {
    "addr:full":"Veenwg 9 Epe Gelderland 8162 RJ",
    "addr:housenumber":"9",
    "addr:postcode":"8162 rj",
    "addr:street":"Veenwg;Gelderland",
    "iso:country":"NL",
    "sg:address":"Veenwg 9",
    "sg:city":"Epe",
    "sg:orig_category":"Vakantieverblijven",
    "sg:phone":"+31 578 612 978",
    "sg:postcode":"8162 RJ",
    "sg:province":"Gelderland",
    "sg:website":"http://www.kampeerboerderijepe.nl",
    "wof:name":"Berghoeve, Kampeerboerderij De",
    "wof:placetype":"venue"
},
  "geometry": {"coordinates":[5.94129,52.335709],"type":"Point"}
}