{
  "type": "Feature",
  "properties": {
    "iso:country":"NL",
    "sg:address":"Haagseveer 122",
    "sg:city":"Rotterdam",
    "sg:orig_category":"Werving And Selectie Van Tijdelijk Personeel And Uitzendkantoren",
    "sg:phone":"+31 10 413 7333",
    "sg:postcode":"3011 DB",
    "sg:province":"South Holland",
    "wof:name":"Carriere",
    "wof:placetype":"venue"
},
  "geometry": {"coordinates":[4.4823179245,51.9221878052],"type":"Point"}
}