{
  "type": "Feature",
  "properties": {
    "addr:full":"Meenteweg 10 Havelte Drenthe 7971 RZ",
    "addr:housenumber":"10",
    "addr:postcode":"7971 rz",
    "addr:street":"Meenteweg",
    "iso:country":"NL",
    "sg:address":"Meenteweg 10",
    "sg:city":"Havelte",
    "sg:orig_category":"Zuivelproducten And Spijsoli?n Gh",
    "sg:phone":"+31 521 343 021",
    "sg:postcode":"7971 RZ",
    "sg:province":"Drenthe",
    "wof:name":"Stevens International Trading",
    "wof:placetype":"venue"
},
  "geometry": {"coordinates":[6.223182,52.751606],"type":"Point"}
}