{
  "type": "Feature",
  "properties": {
    "addr:full":"Brab Turfmarkt 79-81 Delft Zuid-Holland 2611 CM",
    "addr:housenumber":"79-81",
    "addr:postcode":"delft;2611 cm",
    "addr:street":"Turfmarkt",
    "iso:country":"NL",
    "sg:address":"Brab Turfmarkt 79-81",
    "sg:city":"Delft",
    "sg:orig_category":"Drogisterijen",
    "sg:phone":"+31 15 214 2369",
    "sg:postcode":"2611 CM",
    "sg:province":"Zuid-Holland",
    "wof:name":"Kruidvat",
    "wof:placetype":"venue"
},
  "geometry": {"coordinates":[4.360146,52.010342],"type":"Point"}
}