{
  "type": "Feature",
  "properties": {
    "iso:country":"NL",
    "sg:address":"Abdijweg 32",
    "sg:city":"Weerselo",
    "sg:orig_category":"Schoenen",
    "sg:phone":"+31 541 661 205",
    "sg:postcode":"7595 XN",
    "sg:province":"Overijssel",
    "wof:name":"Fa H. Kuipers & Zoon",
    "wof:placetype":"venue"
},
  "geometry": {"coordinates":[6.851308,52.3536],"type":"Point"}
}