{
  "type": "Feature",
  "properties": {
    "addr:full":"Provincialewg 88A Oosteind Noord-Brabant 4909 AL",
    "addr:housenumber":"88a",
    "addr:postcode":"4909 al",
    "addr:street":"Provincialewg",
    "iso:country":"NL",
    "sg:address":"Provincialewg 88A",
    "sg:city":"Oosteind",
    "sg:orig_category":"Bloemen En Planten - Decoratie",
    "sg:phone":"+31 162 467 021",
    "sg:postcode":"4909 AL",
    "sg:province":"Noord-Brabant",
    "wof:name":"Bax, La",
    "wof:placetype":"venue"
},
  "geometry": {"coordinates":[4.900891,51.64518],"type":"Point"}
}