{
  "type": "Feature",
  "properties": {
    "addr:full":"Heksenkruid 10 Breda Noord-Brabant 4823 JL",
    "addr:housenumber":"10",
    "addr:postcode":"4823 jl",
    "addr:street":"Heksenkruid",
    "iso:country":"NL",
    "sg:address":"Heksenkruid 10",
    "sg:city":"Breda",
    "sg:orig_category":"Fietsen En Bromfietsen",
    "sg:phone":"+31 76 541 9225",
    "sg:postcode":"4823 JL",
    "sg:province":"Noord-Brabant",
    "wof:name":"Profiel Breda",
    "wof:placetype":"venue"
},
  "geometry": {"coordinates":[4.743188,51.622444],"type":"Point"}
}