{
  "type": "Feature",
  "properties": {
    "addr:full":"Oosterdorpsstraat 74 Hoevelaken Gelderland 3871 AE",
    "addr:housenumber":"74",
    "addr:postcode":"3871 ae",
    "addr:street":"Oosterdorpsstraat;Gelderland",
    "iso:country":"NL",
    "sg:address":"Oosterdorpsstraat 74",
    "sg:city":"Hoevelaken",
    "sg:orig_category":"Loodgieterswerk, Verwarming And Sanitaire Installaties",
    "sg:phone":"+31 33 253 7889",
    "sg:postcode":"3871 AE",
    "sg:province":"Gelderland",
    "wof:name":"G Thiel",
    "wof:placetype":"venue"
},
  "geometry": {"coordinates":[5.466443,52.17527],"type":"Point"}
}