{
  "type": "Feature",
  "properties": {
    "addr:full":"Nyverheidswg 3B Appingedam Groningen 9902 AE",
    "addr:housenumber":"3b",
    "addr:postcode":"9902 ae",
    "addr:street":"Nyverheidswg",
    "iso:country":"NL",
    "sg:address":"Nyverheidswg 3B",
    "sg:city":"Appingedam",
    "sg:classifiers":[
        {
            "category":"Retail",
            "subcategory":"Auto Repair",
            "type":"Services"
        }
    ],
    "sg:phone":"+31 596 627 837",
    "sg:postcode":"9902 AE",
    "sg:province":"Groningen",
    "sg:tags":[
        "garage"
    ],
    "wof:name":"Gjb Auto'S",
    "wof:placetype":"venue"
},
  "geometry": {"coordinates":[6.851402,53.308952],"type":"Point"}
}