{
  "type": "Feature",
  "properties": {
    "addr:full":"Ommelanderdrift 43 Bedum Groningen 9781 LB",
    "addr:housenumber":"43",
    "addr:postcode":"9781 lb",
    "addr:street":"Ommelanderdrift",
    "iso:country":"NL",
    "sg:address":"Ommelanderdrift 43",
    "sg:city":"Bedum",
    "sg:orig_category":"Administratie- En Boekhoudkantoren",
    "sg:phone":"+31 50 301 0329",
    "sg:postcode":"9781 LB",
    "sg:province":"Groningen",
    "wof:name":"Balanz",
    "wof:placetype":"venue"
},
  "geometry": {"coordinates":[6.608554,53.29731],"type":"Point"}
}