{
  "type": "Feature",
  "properties": {
    "addr:full":"Gildeweg 18 Barneveld Gelderland 3771 NB",
    "addr:housenumber":"18",
    "addr:postcode":"3771 nb",
    "addr:street":"Gildeweg;Gelderland",
    "iso:country":"NL",
    "sg:address":"Gildeweg 18",
    "sg:city":"Barneveld",
    "sg:orig_category":"Kantoorapparatuur Gh",
    "sg:phone":"+31 342 415 777",
    "sg:postcode":"3771 NB",
    "sg:province":"Gelderland",
    "wof:name":"Dahle Nederland Bv",
    "wof:placetype":"venue"
},
  "geometry": {"coordinates":[5.6029081345,52.164806366],"type":"Point"}
}