{
  "type": "Feature",
  "properties": {
    "addr:full":"Wilhelminastr 1 Barendrecht South Holland 2991 BT",
    "addr:housenumber":"1",
    "addr:postcode":"2991 bt",
    "addr:street":"Wilhelminastr",
    "iso:country":"NL",
    "sg:address":"Wilhelminastr 1",
    "sg:city":"Barendrecht",
    "sg:orig_category":"Adviesbureaus Verzekeringen",
    "sg:phone":"+31 180 618 499",
    "sg:postcode":"2991 BT",
    "sg:province":"South Holland",
    "wof:name":"Andel, J Van",
    "wof:placetype":"venue"
},
  "geometry": {"coordinates":[4.54064,51.853176],"type":"Point"}
}