{
  "type": "Feature",
  "properties": {
    "addr:full":"Griffensteijnselaan 44 Zeist Utrecht 3703 AC",
    "addr:housenumber":"44",
    "addr:postcode":"3703 ac",
    "addr:street":"Griffensteijnselaan",
    "iso:country":"NL",
    "sg:address":"Griffensteijnselaan 44",
    "sg:city":"Zeist",
    "sg:orig_category":"Boekenuitgeverijen",
    "sg:phone":"+31 30 273 6569",
    "sg:postcode":"3703 AC",
    "sg:province":"Utrecht",
    "wof:name":"Stichting Achterland",
    "wof:placetype":"venue"
},
  "geometry": {"coordinates":[5.230088,52.080902],"type":"Point"}
}