{
  "type": "Feature",
  "properties": {
    "addr:full":"Hamseweg 2H Hoogland Utrecht 3828 AD",
    "addr:housenumber":"2h",
    "addr:postcode":"3828 ad",
    "addr:street":"Hamseweg",
    "iso:country":"NL",
    "sg:address":"Hamseweg 2H",
    "sg:city":"Hoogland",
    "sg:orig_category":"Fitnesscentra",
    "sg:phone":"+31 33 480 8468",
    "sg:postcode":"3828 AD",
    "sg:province":"Utrecht",
    "wof:name":"Actioncenter Hoogland",
    "wof:placetype":"venue"
},
  "geometry": {"coordinates":[5.372243,52.181343],"type":"Point"}
}