{
  "type": "Feature",
  "properties": {
    "iso:country":"NL",
    "sg:address":"Kruisweg 633",
    "sg:city":"Hoofddorp",
    "sg:orig_category":"Koeriersdiensten",
    "sg:phone":"+31 20 653 3969",
    "sg:postcode":"2132 NP",
    "sg:province":"Noord-Holland",
    "sg:website":"http://www.express-management.com",
    "wof:name":"Express Management Worldwide B.V.",
    "wof:placetype":"venue"
},
  "geometry": {"coordinates":[4.718027,52.292149],"type":"Point"}
}