{
  "type": "Feature",
  "properties": {
    "addr:full":"Wielewaal 85 Geldrop North Brabant 5667 AC",
    "addr:housenumber":"85",
    "addr:postcode":"5667 ac",
    "addr:street":"Wielewaal",
    "iso:country":"NL",
    "sg:address":"Wielewaal 85",
    "sg:city":"Geldrop",
    "sg:orig_category":"Bloemen En Planten",
    "sg:phone":"+31 40 280 1115",
    "sg:postcode":"5667 AC",
    "sg:province":"North Brabant",
    "wof:name":"Mimosa",
    "wof:placetype":"venue"
},
  "geometry": {"coordinates":[5.564142,51.431286],"type":"Point"}
}