{
  "type": "Feature",
  "properties": {
    "addr:full":"Hg Nieuwstr 44 Dordrecht South Holland 3311 AK",
    "addr:housenumber":"44",
    "addr:postcode":"3311 ak",
    "iso:country":"NL",
    "sg:address":"Hg Nieuwstr 44",
    "sg:city":"Dordrecht",
    "sg:orig_category":"Kinderactiviteiten",
    "sg:phone":"+31 78 614 5688",
    "sg:postcode":"3311 AK",
    "sg:province":"South Holland",
    "wof:name":"Making Eyes",
    "wof:placetype":"venue"
},
  "geometry": {"coordinates":[4.664239,51.816917],"type":"Point"}
}