{
  "type": "Feature",
  "properties": {
    "iso:country":"NL",
    "sg:address":"Siaerdamasngl 13",
    "sg:city":"Dronryp",
    "sg:orig_category":"Video - Faciliteiten En Producties",
    "sg:phone":"+31 517 232 439",
    "sg:postcode":"9035 GG",
    "sg:province":"Provincie Friesland",
    "wof:name":"Clear Image",
    "wof:placetype":"venue"
},
  "geometry": {"coordinates":[5.641847,53.191055],"type":"Point"}
}