{
  "type": "Feature",
  "properties": {
    "addr:full":"Ooster Mheenwg 24 Hierden Gelderland 3849 PB",
    "addr:housenumber":"24",
    "addr:postcode":"3849 pb",
    "addr:street":"Ooster Mheenwg;Gelderland",
    "iso:country":"NL",
    "sg:address":"Ooster Mheenwg 24",
    "sg:city":"Hierden",
    "sg:orig_category":"Grondboringen En Bronbemalingen",
    "sg:phone":"+31 6 53786780",
    "sg:postcode":"3849 PB",
    "sg:province":"Gelderland",
    "sg:website":"http://www.veluwedrilling.nl",
    "wof:name":"Veluwe Drilling",
    "wof:placetype":"venue"
},
  "geometry": {"coordinates":[5.67523,52.358692],"type":"Point"}
}