{
  "type": "Feature",
  "properties": {
    "iso:country":"NL",
    "sg:address":"Bautscherweg 34",
    "sg:city":"Heerlen",
    "sg:orig_category":"Kappers",
    "sg:phone":"+31 45 541 1810",
    "sg:postcode":"6418 EM",
    "sg:province":"Limburg",
    "wof:name":"Kapsalon Kratsborn",
    "wof:placetype":"venue"
},
  "geometry": {"coordinates":[6.0039229393,50.8666648865],"type":"Point"}
}