{
  "type": "Feature",
  "properties": {
    "addr:full":"Fahrenheitstr 1B Ede Gld Gelderland 6716 BR",
    "addr:housenumber":"1b",
    "addr:postcode":"6716 br",
    "addr:street":"Fahrenheitstr;Gld Gelderland",
    "iso:country":"NL",
    "sg:address":"Fahrenheitstr 1B",
    "sg:city":"Ede Gld",
    "sg:orig_category":"Organisatiebureaus",
    "sg:phone":"+31 318 697 800",
    "sg:postcode":"6716 BR",
    "sg:province":"Gelderland",
    "sg:website":"http://www.zakelijkfeest.nl",
    "wof:name":"Teka",
    "wof:placetype":"venue"
},
  "geometry": {"coordinates":[5.6205477715,52.031703949],"type":"Point"}
}