{
  "type": "Feature",
  "properties": {
    "addr:full":"Postbus 231 Hengelo Ov 7550 AE",
    "addr:housenumber":"231",
    "addr:postcode":"7550 ae",
    "addr:street":"Postbus;Ov",
    "iso:country":"NL",
    "sg:address":"Postbus 231",
    "sg:city":"Hengelo Ov",
    "sg:orig_category":"Verenigingen En Stichtingen",
    "sg:phone":"+31 74 250 1362",
    "sg:postcode":"7550 AE",
    "wof:name":"Leven Met Kanker, Sticht",
    "wof:placetype":"venue"
},
  "geometry": {"coordinates":[6.78971,52.266331],"type":"Point"}
}