{
  "type": "Feature",
  "properties": {
    "iso:country":"NL",
    "sg:address":"Elspeterwg 41",
    "sg:city":"Uddel",
    "sg:orig_category":"Zonweringen",
    "sg:phone":"+31 577 401 058",
    "sg:postcode":"3888 MS",
    "sg:province":"Gelderland",
    "wof:name":"Ehordo Uddel",
    "wof:placetype":"venue"
},
  "geometry": {"coordinates":[5.784169,52.261986],"type":"Point"}
}