{
  "type": "Feature",
  "properties": {
    "iso:country":"NL",
    "sg:address":"Molenstraat 163",
    "sg:city":"Soest",
    "sg:orig_category":"Visspeciaalzaken",
    "sg:phone":"+31 35 601 8402",
    "sg:postcode":"3764 TE",
    "sg:province":"Utrecht",
    "wof:name":"Vishandel 'T Hoekje",
    "wof:placetype":"venue"
},
  "geometry": {"coordinates":[5.293568,52.172859],"type":"Point"}
}