{
  "type": "Feature",
  "properties": {
    "addr:full":"Slotstr 11A Rotterdam Zuid-Holland 3062 PM",
    "addr:housenumber":"11a",
    "addr:postcode":"3062 pm",
    "addr:street":"Slotstr",
    "iso:country":"NL",
    "sg:address":"Slotstr 11A",
    "sg:city":"Rotterdam",
    "sg:orig_category":"Wasmachines En Wasdrogers - Onderhoud En Reparatie",
    "sg:phone":"+31 10 413 3130",
    "sg:postcode":"3062 PM",
    "sg:province":"Zuid-Holland",
    "wof:name":"Kruger",
    "wof:placetype":"venue"
},
  "geometry": {"coordinates":[4.514316082,51.9220123291],"type":"Point"}
}