{
  "type": "Feature",
  "properties": {
    "addr:full":"Mereveldpln 70 De Meern Utrecht 3454 CM",
    "addr:housenumber":"70",
    "addr:postcode":"3454 cm",
    "addr:street":"Mereveldpln",
    "iso:country":"NL",
    "sg:address":"Mereveldpln 70",
    "sg:city":"De Meern",
    "sg:orig_category":"Administratie- En Boekhoudkantoren",
    "sg:phone":"+31 30 662 1522",
    "sg:postcode":"3454 CM",
    "sg:province":"Utrecht",
    "wof:name":"Koning",
    "wof:placetype":"venue"
},
  "geometry": {"coordinates":[5.03851,52.078911],"type":"Point"}
}