{
  "type": "Feature",
  "properties": {
    "addr:full":"Doetinchemsewg 59 Doetinchem Gelderland 7007 CB",
    "addr:housenumber":"59",
    "addr:postcode":"7007 cb",
    "addr:street":"Doetinchemsewg;Gelderland",
    "iso:country":"NL",
    "sg:address":"Doetinchemsewg 59",
    "sg:city":"Doetinchem",
    "sg:orig_category":"Geluidshinderbestrijding",
    "sg:phone":"+31 314 320 960",
    "sg:postcode":"7007 CB",
    "sg:province":"Gelderland",
    "sg:website":"http://www.kemko.nl",
    "wof:name":"Kemko Bv",
    "wof:placetype":"venue"
},
  "geometry": {"coordinates":[6.281878,51.947872],"type":"Point"}
}