{
  "type": "Feature",
  "properties": {
    "iso:country":"NL",
    "sg:address":"Nyverheidstr 3",
    "sg:city":"Naaldwyk",
    "sg:orig_category":"Schilders",
    "sg:phone":"+31 174 627 693",
    "sg:postcode":"2671 DJ",
    "sg:province":"Zuid-Holland",
    "wof:name":"Dijkshoorn., A",
    "wof:placetype":"venue"
},
  "geometry": {"coordinates":[4.209131,52.001278],"type":"Point"}
}