{
  "type": "Feature",
  "properties": {
    "addr:full":"Keizersgr 453 Amsterdam Missouri 1017 DK",
    "addr:housenumber":"453",
    "addr:postcode":"1017 dk",
    "iso:country":"NL",
    "sg:address":"Keizersgr 453",
    "sg:city":"Amsterdam",
    "sg:orig_category":"Organisatiebureaus",
    "sg:phone":"+31 20 422 2505",
    "sg:postcode":"1017 DK",
    "sg:province":"Missouri",
    "wof:name":"Chemistry Bv",
    "wof:placetype":"venue"
},
  "geometry": {"coordinates":[-94.58502960209999,38.350479126],"type":"Point"}
}