{
  "type": "Feature",
  "properties": {
    "addr:full":"R Peereboomwg 13 Haarlem North Holland 2031 BC",
    "addr:housenumber":"13",
    "addr:postcode":"2031 bc",
    "iso:country":"NL",
    "sg:address":"R Peereboomwg 13",
    "sg:city":"Haarlem",
    "sg:orig_category":"Partyservice",
    "sg:phone":"+31 23 532 1136",
    "sg:postcode":"2031 BC",
    "sg:province":"North Holland",
    "wof:name":"Gelu",
    "wof:placetype":"venue"
},
  "geometry": {"coordinates":[4.666152,52.389668],"type":"Point"}
}