{
  "type": "Feature",
  "properties": {
    "iso:country":"NL",
    "sg:address":"Goudenregenstraat 271",
    "sg:city":"Den Haag",
    "sg:orig_category":"Makelaars In Onroerend Goed",
    "sg:phone":"+31 70 365 9905",
    "sg:postcode":"2565 EV",
    "sg:province":"South Holland",
    "wof:name":"Bliek Makelaardij O.G.",
    "wof:placetype":"venue"
},
  "geometry": {"coordinates":[4.262158,52.078621],"type":"Point"}
}