{
  "type": "Feature",
  "properties": {
    "addr:full":"Goudenregenstraat 271 Den Haag South Holland 2565 EV",
    "addr:housenumber":"271",
    "addr:postcode":"2565 ev",
    "addr:street":"Goudenregenstraat",
    "iso:country":"NL",
    "sg:address":"Goudenregenstraat 271",
    "sg:city":"Den Haag",
    "sg:orig_category":"Makelaars In Onroerend Goed",
    "sg:phone":"+31 70 365 9905",
    "sg:postcode":"2565 EV",
    "sg:province":"South Holland",
    "wof:name":"Bliek Makelaardij O.G.",
    "wof:placetype":"venue"
},
  "geometry": {"coordinates":[4.262158,52.078621],"type":"Point"}
}