{
  "type": "Feature",
  "properties": {
    "addr:full":"Nootwg 37 Loosdrecht North Holland 1231 CP",
    "addr:housenumber":"37",
    "addr:postcode":"1231 cp",
    "addr:street":"Nootwg",
    "iso:country":"NL",
    "sg:address":"Nootwg 37",
    "sg:city":"Loosdrecht",
    "sg:orig_category":"Fietsen En Bromfietsen",
    "sg:phone":"+31 35 582 7018",
    "sg:postcode":"1231 CP",
    "sg:province":"North Holland",
    "wof:name":"Bikeshop Loosdrecht",
    "wof:placetype":"venue"
},
  "geometry": {"coordinates":[5.13825,52.199917],"type":"Point"}
}