{
  "type": "Feature",
  "properties": {
    "addr:full":"Vechtstraat 15 Oss Noord-Brabant 5347 KH",
    "addr:housenumber":"15",
    "addr:postcode":"5347 kh",
    "addr:street":"Vechtstraat",
    "iso:country":"NL",
    "sg:address":"Vechtstraat 15",
    "sg:city":"Oss",
    "sg:orig_category":"Meubelzaken, Woning- And Keukeninrichting",
    "sg:phone":"+31 412 633 619",
    "sg:postcode":"5347 KH",
    "sg:province":"Noord-Brabant",
    "wof:name":"H & O Impex Bv",
    "wof:placetype":"venue"
},
  "geometry": {"coordinates":[-91.213196,44.582859],"type":"Point"}
}