{
  "type": "Feature",
  "properties": {
    "addr:full":"Leidsevaartwg 41A Heemstede North Holland 2106 NA",
    "addr:housenumber":"41a",
    "addr:postcode":"2106 na",
    "addr:street":"Leidsevaartwg",
    "iso:country":"NL",
    "sg:address":"Leidsevaartwg 41A",
    "sg:city":"Heemstede",
    "sg:orig_category":"Woninginrichting",
    "sg:phone":"+31 23 524 6063",
    "sg:postcode":"2106 NA",
    "sg:province":"North Holland",
    "wof:name":"Moolen, Van Der",
    "wof:placetype":"venue"
},
  "geometry": {"coordinates":[4.5946569443,52.335483551],"type":"Point"}
}