{
  "type": "Feature",
  "properties": {
    "iso:country":"NL",
    "sg:address":"S V Collemstr 192",
    "sg:city":"Almere",
    "sg:orig_category":"Makelaars En Adviseurs Onroerende Goederen",
    "sg:phone":"+31 36 537 6887",
    "sg:postcode":"1325 RR",
    "sg:province":"NL.",
    "wof:name":"Oerlemans, Erik",
    "wof:placetype":"venue"
},
  "geometry": {"coordinates":[5.23721,52.364529],"type":"Point"}
}