{
  "type": "Feature",
  "properties": {
    "addr:full":"Hoogstraat 9 Leerdam Zuid-Holland 4141 BA",
    "addr:housenumber":"9",
    "addr:postcode":"4141 ba",
    "addr:street":"Hoogstraat",
    "iso:country":"NL",
    "sg:address":"Hoogstraat 9",
    "sg:city":"Leerdam",
    "sg:orig_category":"Parfum And Cosmetica Gh",
    "sg:phone":"+31 345 613 279",
    "sg:postcode":"4141 BA",
    "sg:province":"Zuid-Holland",
    "wof:name":"Beauty Line Nederland",
    "wof:placetype":"venue"
},
  "geometry": {"coordinates":[5.095121,51.89061],"type":"Point"}
}