{
  "type": "Feature",
  "properties": {
    "addr:full":"Koningshoek 92-419 Maassluis South Holland 3144 BA",
    "addr:housenumber":"92-419",
    "addr:postcode":"3144 ba",
    "addr:street":"Koningshoek",
    "iso:country":"NL",
    "sg:address":"Koningshoek 92-419",
    "sg:city":"Maassluis",
    "sg:orig_category":"Opticiens",
    "sg:phone":"+31 10 592 0872",
    "sg:postcode":"3144 BA",
    "sg:province":"South Holland",
    "wof:name":"Hans Anders Opticiens",
    "wof:placetype":"venue"
},
  "geometry": {"coordinates":[4.2408299446,51.9275398254],"type":"Point"}
}