{
  "type": "Feature",
  "properties": {
    "iso:country":"NL",
    "sg:address":"C Fagelstr 76",
    "sg:city":"Delft",
    "sg:orig_category":"Grafisch Ontwerpers",
    "sg:phone":"+31 15 212 7771",
    "sg:postcode":"2613 GX",
    "sg:province":"South Holland",
    "wof:name":"Studioboven",
    "wof:placetype":"venue"
},
  "geometry": {"coordinates":[4.347722,52.00938],"type":"Point"}
}