{
  "type": "Feature",
  "properties": {
    "iso:country":"NL",
    "sg:address":"Nimrodel 8",
    "sg:city":"Geldrop",
    "sg:orig_category":"Juridische Dienstverlening",
    "sg:phone":"+31 40 285 8741",
    "sg:postcode":"5663 TE",
    "sg:province":"North Brabant",
    "wof:name":"Legal Beginning",
    "wof:placetype":"venue"
},
  "geometry": {"coordinates":[5.553953,51.409809],"type":"Point"}
}