{
  "type": "Feature",
  "properties": {
    "addr:full":"De Leegte 99 Epe Gelderland 8162 BW",
    "addr:housenumber":"99",
    "addr:postcode":"8162 bw",
    "addr:street":"De Leegte;Gelderland",
    "iso:country":"NL",
    "sg:address":"De Leegte 99",
    "sg:city":"Epe",
    "sg:orig_category":"Meubelen - Fabrieken En Groothandel",
    "sg:phone":"+31 578 627 784",
    "sg:postcode":"8162 BW",
    "sg:province":"Gelderland",
    "wof:name":"Prime Line Bv",
    "wof:placetype":"venue"
},
  "geometry": {"coordinates":[5.986696,52.356758],"type":"Point"}
}