{
  "type": "Feature",
  "properties": {
    "addr:full":"Smaragdln 6 Veendam Groningen 9646 BL",
    "addr:housenumber":"6",
    "addr:postcode":"9646 bl",
    "addr:street":"Smaragdln",
    "iso:country":"NL",
    "sg:address":"Smaragdln 6",
    "sg:city":"Veendam",
    "sg:orig_category":"Artsen - Huisartsen",
    "sg:phone":"+31 598 612 227",
    "sg:postcode":"9646 BL",
    "sg:province":"Groningen",
    "wof:name":"Veentjer, H",
    "wof:placetype":"venue"
},
  "geometry": {"coordinates":[6.868621,53.108883],"type":"Point"}
}