{
  "type": "Feature",
  "properties": {
    "addr:full":"Postbus 1558 Maarssen Utrecht 3600 BN",
    "addr:housenumber":"1558",
    "addr:postcode":"3600 bn",
    "addr:street":"Postbus",
    "iso:country":"NL",
    "sg:address":"Postbus 1558",
    "sg:city":"Maarssen",
    "sg:orig_category":"Vakorganisaties",
    "sg:phone":"+31 346 552 552",
    "sg:postcode":"3600 BN",
    "sg:province":"Utrecht",
    "wof:name":"Beroepsorg Banken Verzekeringen",
    "wof:placetype":"venue"
},
  "geometry": {"coordinates":[5.040446,52.142956],"type":"Point"}
}