{
  "type": "Feature",
  "properties": {
    "iso:country":"NL",
    "sg:address":"Enschedesestraat 76",
    "sg:city":"Haaksbergen",
    "sg:orig_category":"Begrafenisondernemers",
    "sg:phone":"+31 53 573 7490",
    "sg:postcode":"7481 CT",
    "sg:province":"NL.08",
    "wof:name":"Stichting Uitvaartverzorging Haaksbergen",
    "wof:placetype":"venue"
},
  "geometry": {"coordinates":[6.753545,52.158562],"type":"Point"}
}