{
  "type": "Feature",
  "properties": {
    "addr:full":"Amersfoortsewg 38 Maarn Utrecht 3951 LC",
    "addr:housenumber":"38",
    "addr:postcode":"3951 lc",
    "addr:street":"Amersfoortsewg",
    "iso:country":"NL",
    "sg:address":"Amersfoortsewg 38",
    "sg:city":"Maarn",
    "sg:orig_category":"Adviesbureaus Bedrijfsorganisatie",
    "sg:phone":"+31 343 444 789",
    "sg:postcode":"3951 LC",
    "sg:province":"Utrecht",
    "wof:name":"Organiek Bedrijfsontwikkeling",
    "wof:placetype":"venue"
},
  "geometry": {"coordinates":[5.357697,52.064201],"type":"Point"}
}