{
  "type": "Feature",
  "properties": {
    "addr:full":"Snoeckgensheuvel 22 Amersfoort Utrecht 3817 HM",
    "addr:housenumber":"22",
    "addr:postcode":"3817 hm",
    "addr:street":"Snoeckgensheuvel",
    "iso:country":"NL",
    "sg:address":"Snoeckgensheuvel 22",
    "sg:city":"Amersfoort",
    "sg:orig_category":"Psychotherapeuten",
    "sg:phone":"+31 33 461 9954",
    "sg:postcode":"3817 HM",
    "sg:province":"Utrecht",
    "wof:name":"Sande-Pennings, J Van De",
    "wof:placetype":"venue"
},
  "geometry": {"coordinates":[5.395506,52.142849],"type":"Point"}
}