{
  "type": "Feature",
  "properties": {
    "addr:full":"Badhuiswg 49 Apeldoorn Gelderland 7314 EA",
    "addr:housenumber":"49",
    "addr:postcode":"7314 ea",
    "addr:street":"Badhuiswg;Gelderland",
    "iso:country":"NL",
    "sg:address":"Badhuiswg 49",
    "sg:city":"Apeldoorn",
    "sg:orig_category":"Makelaars En Adviseurs Onroerende Goederen",
    "sg:phone":"+31 55 521 9277",
    "sg:postcode":"7314 EA",
    "sg:province":"Gelderland",
    "wof:name":"Hendriks",
    "wof:placetype":"venue"
},
  "geometry": {"coordinates":[5.951407,52.217464],"type":"Point"}
}