{
  "type": "Feature",
  "properties": {
    "iso:country":"NL",
    "sg:address":"Oosteinde 10",
    "sg:city":"Sint Jacobiparochie",
    "sg:orig_category":"Feestartikelen",
    "sg:phone":"+31 518 491 527",
    "sg:postcode":"9079 LC",
    "sg:province":"Provincie Friesland",
    "wof:name":"Kas Kledingverhuur",
    "wof:placetype":"venue"
},
  "geometry": {"coordinates":[5.604217,53.272568],"type":"Point"}
}