{
  "type": "Feature",
  "properties": {
    "iso:country":"NL",
    "sg:address":"Kastanjestr 20",
    "sg:city":"Ittervoort",
    "sg:orig_category":"Belastingconsulenten/ Belastingadviseurs",
    "sg:phone":"+31 475 565 464",
    "sg:postcode":"6014 EE",
    "sg:province":"Limburg",
    "wof:name":"Coenen",
    "wof:placetype":"venue"
},
  "geometry": {"coordinates":[5.82288,51.171459],"type":"Point"}
}