{
  "type": "Feature",
  "properties": {
    "addr:full":"Waterspinhof 40 S Gravenhage 2492 RK",
    "addr:housenumber":"40",
    "addr:postcode":"2492 rk",
    "addr:street":"Waterspinhof;S Gravenhage",
    "iso:country":"NL",
    "sg:address":"Waterspinhof 40",
    "sg:city":"S Gravenhage",
    "sg:orig_category":"Onderhoudswerken",
    "sg:phone":"+31 70 444 4051",
    "sg:postcode":"2492 RK",
    "wof:name":"Barends, Ron",
    "wof:placetype":"venue"
},
  "geometry": {"coordinates":[4.40783,52.067459],"type":"Point"}
}