{
  "type": "Feature",
  "properties": {
    "addr:full":"Populierenln 7 Krommenie Noord-Holland 1561 VA",
    "addr:housenumber":"7",
    "addr:postcode":"1561",
    "addr:street":"Populierenln",
    "iso:country":"NL",
    "sg:address":"Populierenln 7",
    "sg:city":"Krommenie",
    "sg:orig_category":"Kappers",
    "sg:phone":"+31 75 628 6918",
    "sg:postcode":"1561 VA",
    "sg:province":"Noord-Holland",
    "wof:name":"Mors, N A C",
    "wof:placetype":"venue"
},
  "geometry": {"coordinates":[4.766795,52.503574],"type":"Point"}
}