{
  "type": "Feature",
  "properties": {
    "addr:full":"Voorstraat 5 Kraggenburg Flevoland 8317 AG",
    "addr:housenumber":"5",
    "addr:postcode":"8317",
    "addr:street":"Voorstraat;Flevoland",
    "iso:country":"NL",
    "sg:address":"Voorstraat 5",
    "sg:city":"Kraggenburg",
    "sg:classifiers":[
        {
            "category":"Education",
            "subcategory":"Preschool",
            "type":"Public Place"
        }
    ],
    "sg:phone":"+31 527 252 345",
    "sg:postcode":"8317 AG",
    "sg:province":"Flevoland",
    "sg:tags":[
        "kleuteronderwijs",
        "basis-"
    ],
    "wof:name":"De Pionier",
    "wof:placetype":"venue"
},
  "geometry": {"coordinates":[5.899695,52.66246],"type":"Point"}
}