{
  "type": "Feature",
  "properties": {
    "addr:full":"Sniep 25 Diemen Noord-Holland 1112 AC",
    "addr:housenumber":"25",
    "addr:postcode":"1112 ac",
    "addr:street":"Sniep",
    "iso:country":"NL",
    "sg:address":"Sniep 25",
    "sg:city":"Diemen",
    "sg:orig_category":"Kopieerapparaten",
    "sg:phone":"+31 20 668 6622",
    "sg:postcode":"1112 AC",
    "sg:province":"Noord-Holland",
    "sg:website":"http://www.office-power.nl",
    "wof:name":"Office-Power",
    "wof:placetype":"venue"
},
  "geometry": {"coordinates":[4.97524,52.334309],"type":"Point"}
}