{
  "type": "Feature",
  "properties": {
    "addr:full":"Sloterwg 2 Badhoevedorp Noord-Holland 1171 CR",
    "addr:housenumber":"2;1171",
    "addr:postcode":"cr",
    "addr:street":"Sloterwg",
    "iso:country":"NL",
    "sg:address":"Sloterwg 2",
    "sg:city":"Badhoevedorp",
    "sg:orig_category":"Automaterialen En Gereedschappen",
    "sg:phone":"+31 20 659 3949",
    "sg:postcode":"1171 CR",
    "sg:province":"Noord-Holland",
    "sg:website":"http://www.brezan.nl",
    "wof:name":"Brezan",
    "wof:placetype":"venue"
},
  "geometry": {"coordinates":[4.786542,52.342903],"type":"Point"}
}