{
  "type": "Feature",
  "properties": {
    "addr:full":"Postbus 96 Oosterbeek Gelderland 6860 AB",
    "addr:housenumber":"96",
    "addr:postcode":"6860 ab",
    "addr:street":"Postbus;Gelderland",
    "iso:country":"NL",
    "sg:address":"Postbus 96",
    "sg:city":"Oosterbeek",
    "sg:orig_category":"Adviesbureaus Bouwkunde",
    "sg:phone":"+31 26 333 3888",
    "sg:postcode":"6860 AB",
    "sg:province":"Gelderland",
    "wof:name":"Renne & Partners Bv",
    "wof:placetype":"venue"
},
  "geometry": {"coordinates":[5.84188,51.987652],"type":"Point"}
}