{
  "type": "Feature",
  "properties": {
    "iso:country":"NL",
    "sg:address":"Postbus 96",
    "sg:city":"Oosterbeek",
    "sg:orig_category":"Adviesbureaus Bouwkunde",
    "sg:phone":"+31 26 333 3888",
    "sg:postcode":"6860 AB",
    "sg:province":"Gelderland",
    "wof:name":"Renne & Partners Bv",
    "wof:placetype":"venue"
},
  "geometry": {"coordinates":[5.84188,51.987652],"type":"Point"}
}