{
  "type": "Feature",
  "properties": {
    "addr:full":"Rijndijk Hazerswoude Rijndijk South Holland 2394 HA",
    "addr:postcode":"2394 ha",
    "addr:street":"Rijndijk Hazerswoude Rijndijk",
    "iso:country":"NL",
    "sg:address":"Rijndijk",
    "sg:city":"Hazerswoude Rijndijk",
    "sg:orig_category":"Koopzondagen Zondag 3 Maart 2002",
    "sg:phone":"+31 0",
    "sg:postcode":"2394 HA",
    "sg:province":"South Holland",
    "wof:name":"Hazerswoude Rijndijk Woonboulevard",
    "wof:placetype":"venue"
},
  "geometry": {"coordinates":[4.55278,52.135315],"type":"Point"}
}