{
  "type": "Feature",
  "properties": {
    "addr:full":"Harselaarsewg 23 Barneveld Gelderland 3771 MA",
    "addr:housenumber":"23",
    "addr:postcode":"3771 ma",
    "addr:street":"Harselaarsewg;Gelderland",
    "iso:country":"NL",
    "sg:address":"Harselaarsewg 23",
    "sg:city":"Barneveld",
    "sg:orig_category":"Machinehandel",
    "sg:phone":"+31 342 415 551",
    "sg:postcode":"3771 MA",
    "sg:province":"Gelderland",
    "sg:website":"http://www.foeth.nl.com",
    "wof:name":"Foeth Barneveld Bv, A",
    "wof:placetype":"venue"
},
  "geometry": {"coordinates":[5.57633,52.164551],"type":"Point"}
}