{
  "type": "Feature",
  "properties": {
    "addr:full":"Sterremuurwg 13 Haren Gn Groningen 9753 AT",
    "addr:housenumber":"13",
    "addr:postcode":"9753",
    "addr:street":"Sterremuurwg",
    "iso:country":"NL",
    "sg:address":"Sterremuurwg 13",
    "sg:city":"Haren Gn",
    "sg:orig_category":"Adviesbureaus Bedrijfsorganisatie",
    "sg:phone":"+31 50 534 3120",
    "sg:postcode":"9753 AT",
    "sg:province":"Groningen",
    "sg:website":"http://www.meijer.cent.nl",
    "wof:name":"Meijer",
    "wof:placetype":"venue"
},
  "geometry": {"coordinates":[6.6219,53.174915],"type":"Point"}
}