{
  "type": "Feature",
  "properties": {
    "addr:full":"Rietgrachtstr 6 Arnhem Gelderland 6828 KD",
    "addr:housenumber":"6",
    "addr:postcode":"6828 kd",
    "addr:street":"Rietgrachtstr",
    "iso:country":"NL",
    "sg:address":"Rietgrachtstr 6",
    "sg:city":"Arnhem",
    "sg:orig_category":"Loodgieters",
    "sg:phone":"+31 26 445 5089",
    "sg:postcode":"6828 KD",
    "sg:province":"Gelderland",
    "wof:name":"Krelo",
    "wof:placetype":"venue"
},
  "geometry": {"coordinates":[5.917915,51.979786],"type":"Point"}
}