{
  "type": "Feature",
  "properties": {
    "addr:full":"Wilhelminaplein 15 Eindhoven North Brabant 5611 HE",
    "addr:housenumber":"15",
    "addr:postcode":"5611 he",
    "addr:street":"Wilhelminaplein",
    "iso:country":"NL",
    "sg:address":"Wilhelminaplein 15",
    "sg:city":"Eindhoven",
    "sg:orig_category":"Medische Apparatuur And Prothesen Fab",
    "sg:phone":"+31 40 245 0580",
    "sg:postcode":"5611 HE",
    "sg:province":"North Brabant",
    "wof:name":"Dental Techniek Wilko Buiter",
    "wof:placetype":"venue"
},
  "geometry": {"coordinates":[5.484105,51.434471],"type":"Point"}
}