{
  "type": "Feature",
  "properties": {
    "iso:country":"NL",
    "sg:address":"Berkenln 33",
    "sg:city":"Velden",
    "sg:orig_category":"Logopedisten",
    "sg:phone":"+31 77 472 2444",
    "sg:postcode":"5941 EA",
    "sg:province":"Limburg",
    "wof:name":"Savelsbergh-Baghuis, M L",
    "wof:placetype":"venue"
},
  "geometry": {"coordinates":[6.173676,51.425659],"type":"Point"}
}