{
  "type": "Feature",
  "properties": {
    "addr:full":"Pater Eustachiuslaan 17 Aarle Rixtel North Brabant 5735 SK",
    "addr:housenumber":"17",
    "addr:postcode":"5735 sk",
    "addr:street":"Pater Eustachiuslaan",
    "iso:country":"NL",
    "sg:address":"Pater Eustachiuslaan 17",
    "sg:city":"Aarle Rixtel",
    "sg:orig_category":"Groententeelt",
    "sg:phone":"+31 492 461 345",
    "sg:postcode":"5735 SK",
    "sg:province":"North Brabant",
    "wof:name":"Gtl Vereijken En Zonen Bv",
    "wof:placetype":"venue"
},
  "geometry": {"coordinates":[5.65687,51.523205],"type":"Point"}
}