{
  "type": "Feature",
  "properties": {
    "addr:full":"Boschdijk 263 Eindhoven Noord-Brabant 5612 HD",
    "addr:housenumber":"263",
    "addr:postcode":"5612 hd",
    "addr:street":"Boschdijk",
    "iso:country":"NL",
    "sg:address":"Boschdijk 263",
    "sg:city":"Eindhoven",
    "sg:orig_category":"Meubelzaken, Woning- And Keukeninrichting",
    "sg:phone":"+31 40 244 4200",
    "sg:postcode":"5612 HD",
    "sg:province":"Noord-Brabant",
    "wof:name":"Morgana Slaapkamers",
    "wof:placetype":"venue"
},
  "geometry": {"coordinates":[5.465161,51.450829],"type":"Point"}
}