{
  "type": "Feature",
  "properties": {
    "addr:full":"Hilversumstraat 118 Amsterdam North Holland 1024 KB",
    "addr:housenumber":"118",
    "addr:postcode":"1024 kb",
    "addr:street":"Hilversumstraat",
    "iso:country":"NL",
    "sg:address":"Hilversumstraat 118",
    "sg:city":"Amsterdam",
    "sg:orig_category":"Boekhouders",
    "sg:phone":"+31 20 494 5159",
    "sg:postcode":"1024 KB",
    "sg:province":"North Holland",
    "wof:name":"Devos Automatisering",
    "wof:placetype":"venue"
},
  "geometry": {"coordinates":[4.963075,52.390453],"type":"Point"}
}