{
  "type": "Feature",
  "properties": {
    "addr:full":"Sintelstraat 27 Maasbracht Limburg 6051 BL",
    "addr:housenumber":"27",
    "addr:postcode":"6051 bl",
    "addr:street":"Sintelstraat",
    "iso:country":"NL",
    "sg:address":"Sintelstraat 27",
    "sg:city":"Maasbracht",
    "sg:orig_category":"Baby- And Kinderkleding",
    "sg:phone":"+31 475 466 360",
    "sg:postcode":"6051 BL",
    "sg:province":"Limburg",
    "wof:name":"Iris Vof",
    "wof:placetype":"venue"
},
  "geometry": {"coordinates":[5.886613,51.14571],"type":"Point"}
}