{
  "type": "Feature",
  "properties": {
    "addr:full":"Kerkstraat 2 Wassenaar South Holland 2242 HG",
    "addr:housenumber":"2",
    "addr:postcode":"2242 hg",
    "addr:street":"Kerkstraat",
    "iso:country":"NL",
    "sg:address":"Kerkstraat 2",
    "sg:city":"Wassenaar",
    "sg:orig_category":"Wasserettes And Stomerijen",
    "sg:phone":"+31 70 511 0510",
    "sg:postcode":"2242 HG",
    "sg:province":"South Holland",
    "wof:name":"Dompeling Cleaning Service",
    "wof:placetype":"venue"
},
  "geometry": {"coordinates":[4.3931589127,52.1439247131],"type":"Point"}
}