{
  "type": "Feature",
  "properties": {
    "addr:full":"Meye 2A Bodegraven Zuid-Holland 2411 PG",
    "addr:housenumber":"2a",
    "addr:postcode":"2411 pg",
    "addr:street":"Meye",
    "iso:country":"NL",
    "sg:address":"Meye 2A",
    "sg:city":"Bodegraven",
    "sg:orig_category":"Onroerende Goederen",
    "sg:phone":"+31 172 651 156",
    "sg:postcode":"2411 PG",
    "sg:province":"Zuid-Holland",
    "wof:name":"Wijk Bv, Van",
    "wof:placetype":"venue"
},
  "geometry": {"coordinates":[4.747547,52.085552],"type":"Point"}
}