{
  "type": "Feature",
  "properties": {
    "addr:full":"Pr Hendrikstr 12 Leeuwarden Provincie Friesland 8911 BK",
    "addr:housenumber":"12",
    "addr:postcode":"8911 bk",
    "addr:street":"Provincie Friesland",
    "iso:country":"NL",
    "sg:address":"Pr Hendrikstr 12",
    "sg:city":"Leeuwarden",
    "sg:orig_category":"Kappers",
    "sg:phone":"+31 58 212 4860",
    "sg:postcode":"8911 BK",
    "sg:province":"Provincie Friesland",
    "wof:name":"Remy",
    "wof:placetype":"venue"
},
  "geometry": {"coordinates":[5.792496,53.198887],"type":"Point"}
}