{
  "type": "Feature",
  "properties": {
    "addr:full":"Saffier 64 Duiven Gelderland 6922 NH",
    "addr:housenumber":"64",
    "addr:postcode":"6922 nh",
    "addr:street":"Saffier;Gelderland",
    "iso:country":"NL",
    "sg:address":"Saffier 64",
    "sg:city":"Duiven",
    "sg:orig_category":"Werving En Selectie",
    "sg:phone":"+31 316 268 664",
    "sg:postcode":"6922 NH",
    "sg:province":"Gelderland",
    "wof:name":"Hendriks, Jan",
    "wof:placetype":"venue"
},
  "geometry": {"coordinates":[-71.6328277588,44.0013008118],"type":"Point"}
}