{
  "type": "Feature",
  "properties": {
    "addr:full":"De Stouwe 15 Dalfsen NL.08 7722 VT",
    "addr:housenumber":"15;nl.08",
    "addr:postcode":"7722",
    "addr:street":"De Stouwe",
    "iso:country":"NL",
    "sg:address":"De Stouwe 15",
    "sg:city":"Dalfsen",
    "sg:orig_category":"Pluimveebedrijven En -Handelaren",
    "sg:phone":"+31 529 471 426",
    "sg:postcode":"7722 VT",
    "sg:province":"NL.08",
    "wof:name":"Bunskoek, H",
    "wof:placetype":"venue"
},
  "geometry": {"coordinates":[6.352976,52.538918],"type":"Point"}
}