{
  "type": "Feature",
  "properties": {
    "addr:full":"Professor Aalbersestraat 27 Nieuwegein Utrecht 3438 AT",
    "addr:housenumber":"27",
    "addr:postcode":"3438",
    "addr:street":"Professor Aalbersestraat",
    "iso:country":"NL",
    "sg:address":"Professor Aalbersestraat 27",
    "sg:city":"Nieuwegein",
    "sg:orig_category":"Wegen And Sportterreinen",
    "sg:phone":"+31 30 603 2083",
    "sg:postcode":"3438 AT",
    "sg:province":"Utrecht",
    "wof:name":"J.A.G. Zieltjens",
    "wof:placetype":"venue"
},
  "geometry": {"coordinates":[5.1020030975,52.0486297607],"type":"Point"}
}