{
  "type": "Feature",
  "properties": {
    "addr:full":"Marktstraat 1 Bodegraven South Holland 2411 BE",
    "addr:housenumber":"1",
    "addr:postcode":"2411",
    "addr:street":"Marktstraat",
    "iso:country":"NL",
    "sg:address":"Marktstraat 1",
    "sg:city":"Bodegraven",
    "sg:orig_category":"Banken And Kredietinstellingen",
    "sg:phone":"+31 172 632 500",
    "sg:postcode":"2411 BE",
    "sg:province":"South Holland",
    "wof:name":"Rabobank",
    "wof:placetype":"venue"
},
  "geometry": {"coordinates":[4.74747,52.085258],"type":"Point"}
}