{
  "type": "Feature",
  "properties": {
    "addr:full":"Kooikersgr 2 Leusden Utrecht 3831 NG",
    "addr:housenumber":"2",
    "addr:postcode":"3831 ng",
    "addr:street":"Kooikersgr",
    "iso:country":"NL",
    "sg:address":"Kooikersgr 2",
    "sg:city":"Leusden",
    "sg:orig_category":"Opticiens",
    "sg:phone":"+31 33 494 5217",
    "sg:postcode":"3831 NG",
    "sg:province":"Utrecht",
    "sg:website":"http://www.hansanders.nl",
    "wof:name":"Hans Anders",
    "wof:placetype":"venue"
},
  "geometry": {"coordinates":[5.4276161194,52.1297073364],"type":"Point"}
}