{
  "type": "Feature",
  "properties": {
    "iso:country":"NL",
    "sg:address":"Geererf 40",
    "sg:city":"Breda",
    "sg:orig_category":"Psychotherapeuten",
    "sg:phone":"+31 76 542 3830",
    "sg:postcode":"4824 GL",
    "sg:province":"North Brabant",
    "wof:name":"Meer, Marijke Van",
    "wof:placetype":"venue"
},
  "geometry": {"coordinates":[4.750328,51.614147],"type":"Point"}
}