{
  "type": "Feature",
  "properties": {
    "addr:full":"Seterseweg 4 Oosterhout (Nb) Noord-Brabant 4903 RV",
    "addr:housenumber":"4",
    "addr:postcode":"4903 rv",
    "addr:street":"Seterseweg",
    "iso:country":"NL",
    "sg:address":"Seterseweg 4",
    "sg:city":"Oosterhout (Nb)",
    "sg:orig_category":"Kampeerterreinen",
    "sg:phone":"+31 161 411 572",
    "sg:postcode":"4903 RV",
    "sg:province":"Noord-Brabant",
    "wof:name":"Camping De Eekhoorn",
    "wof:placetype":"venue"
},
  "geometry": {"coordinates":[4.8664860725,51.6111564636],"type":"Point"}
}