{
  "type": "Feature",
  "properties": {
    "addr:full":"Den Texstr 46 Amsterdam North Holland 1017 ZC",
    "addr:housenumber":"46",
    "addr:postcode":"1017 zc",
    "iso:country":"NL",
    "sg:address":"Den Texstr 46",
    "sg:city":"Amsterdam",
    "sg:orig_category":"Yoga-Instituten",
    "sg:phone":"+31 20 624 1977",
    "sg:postcode":"1017 ZC",
    "sg:province":"North Holland",
    "wof:name":"3Ho Foundation, Sticht",
    "wof:placetype":"venue"
},
  "geometry": {"coordinates":[4.895265,52.358688],"type":"Point"}
}