{
  "type": "Feature",
  "properties": {
    "addr:full":"Barnar 33 Emmen Drenthe 7826 EP",
    "addr:housenumber":"33",
    "addr:postcode":"7826 ep",
    "addr:street":"Barnar",
    "iso:country":"NL",
    "sg:address":"Barnar 33",
    "sg:city":"Emmen",
    "sg:orig_category":"Metselwerken",
    "sg:phone":"+31 6 21501313",
    "sg:postcode":"7826 EP",
    "sg:province":"Drenthe",
    "wof:name":"Gerdes",
    "wof:placetype":"venue"
},
  "geometry": {"coordinates":[6.960278,52.771191],"type":"Point"}
}