{
  "type": "Feature",
  "properties": {
    "addr:full":"Wildelandwg 20 Nunspeet Gelderland 8072 DM",
    "addr:housenumber":"20",
    "addr:postcode":"8072 dm",
    "addr:street":"Wildelandwg;Gelderland",
    "iso:country":"NL",
    "sg:address":"Wildelandwg 20",
    "sg:city":"Nunspeet",
    "sg:orig_category":"Scheepsstofferingen",
    "sg:phone":"+31 341 253 724",
    "sg:postcode":"8072 DM",
    "sg:province":"Gelderland",
    "wof:name":"Zaalberg",
    "wof:placetype":"venue"
},
  "geometry": {"coordinates":[5.7935781479,52.3819046021],"type":"Point"}
}