{
  "type": "Feature",
  "properties": {
    "addr:full":"Westerweg 51 Heiloo North Holland 1851 AB",
    "addr:housenumber":"51",
    "addr:postcode":"1851 ab",
    "addr:street":"Westerweg",
    "iso:country":"NL",
    "sg:address":"Westerweg 51",
    "sg:city":"Heiloo",
    "sg:classifiers":[
        {
            "category":"Professional",
            "subcategory":"Accounting & Tax Preparation",
            "type":"Services"
        }
    ],
    "sg:phone":"+31 72 515 5002",
    "sg:postcode":"1851 AB",
    "sg:province":"North Holland",
    "sg:tags":[
        "accountant"
    ],
    "wof:name":"Foliant Bv",
    "wof:placetype":"venue"
},
  "geometry": {"coordinates":[4.718398,52.615864],"type":"Point"}
}