{
  "type": "Feature",
  "properties": {
    "addr:full":"Hoensbroekstraat 56 Arnhem Gelderland 6845 DP",
    "addr:housenumber":"56",
    "addr:postcode":"6845 dp",
    "addr:street":"Hoensbroekstraat",
    "iso:country":"NL",
    "sg:address":"Hoensbroekstraat 56",
    "sg:city":"Arnhem",
    "sg:orig_category":"Medische Apparatuur And Prothesen Fab",
    "sg:phone":"+31 26 381 9020",
    "sg:postcode":"6845 DP",
    "sg:province":"Gelderland",
    "wof:name":"J. V.D. Kort",
    "wof:placetype":"venue"
},
  "geometry": {"coordinates":[5.863429,51.944141],"type":"Point"}
}