{
  "type": "Feature",
  "properties": {
    "addr:full":"Woudfennen 10 Joure Friesland 8503 BA",
    "addr:housenumber":"10",
    "addr:postcode":"8503 ba",
    "addr:street":"Woudfennen",
    "iso:country":"NL",
    "sg:address":"Woudfennen 10",
    "sg:city":"Joure",
    "sg:orig_category":"Sauna'S",
    "sg:phone":"+31 513 415 200",
    "sg:postcode":"8503 BA",
    "sg:province":"Friesland",
    "sg:website":"http://www.sauna-beauty-thermen.nl",
    "wof:name":"Sauna & Beauty-Thermen De Woudfennen",
    "wof:placetype":"venue"
},
  "geometry": {"coordinates":[5.766365,52.964115],"type":"Point"}
}