{
  "type": "Feature",
  "properties": {
    "addr:full":"Broekwal 24 Helvoirt Noord-Brabant 5268 HC",
    "addr:housenumber":"24",
    "addr:postcode":"5268 hc",
    "addr:street":"Broekwal",
    "iso:country":"NL",
    "sg:address":"Broekwal 24",
    "sg:city":"Helvoirt",
    "sg:orig_category":"Kantoor- En Secretariaatsservice",
    "sg:phone":"+31 411 643 037",
    "sg:postcode":"5268 HC",
    "sg:province":"Noord-Brabant",
    "wof:name":"Viersen, A",
    "wof:placetype":"venue"
},
  "geometry": {"coordinates":[5.2396512032,51.6329154968],"type":"Point"}
}