{
  "type": "Feature",
  "properties": {
    "addr:full":"Twyver 66 Venhuizen North Holland 1606 BW",
    "addr:housenumber":"66",
    "addr:postcode":"1606 bw",
    "addr:street":"Twyver",
    "iso:country":"NL",
    "sg:address":"Twyver 66",
    "sg:city":"Venhuizen",
    "sg:orig_category":"Verenigingsgebouwen",
    "sg:phone":"+31 228 541 294",
    "sg:postcode":"1606 BW",
    "sg:province":"North Holland",
    "wof:name":"Centrum, Dorpshuis 'T",
    "wof:placetype":"venue"
},
  "geometry": {"coordinates":[5.199493,52.662418],"type":"Point"}
}