{
  "type": "Feature",
  "properties": {
    "addr:full":"Zuiderzeestraatweg 60 Oldebroek Gelderland 8096 CB",
    "addr:housenumber":"60",
    "addr:postcode":"8096 cb",
    "addr:street":"Zuiderzeestraatweg;Gelderland",
    "iso:country":"NL",
    "sg:address":"Zuiderzeestraatweg 60",
    "sg:city":"Oldebroek",
    "sg:orig_category":"Overheidsdiensten",
    "sg:phone":"+31 525 631 807",
    "sg:postcode":"8096 CB",
    "sg:province":"Gelderland",
    "wof:name":"Atlantis",
    "wof:placetype":"venue"
},
  "geometry": {"coordinates":[5.8937549591,52.4451065063],"type":"Point"}
}