{
  "type": "Feature",
  "properties": {
    "addr:full":"Kruisweg 74 Marum Groningen 9363 AG",
    "addr:housenumber":"74",
    "addr:postcode":"9363",
    "addr:street":"Kruisweg",
    "iso:country":"NL",
    "sg:address":"Kruisweg 74",
    "sg:city":"Marum",
    "sg:orig_category":"Loodgieterswerk, Verwarming And Sanitaire Installaties",
    "sg:phone":"+31 594 643 246",
    "sg:postcode":"9363 AG",
    "sg:province":"Groningen",
    "wof:name":"K. Veenstra",
    "wof:placetype":"venue"
},
  "geometry": {"coordinates":[6.283432,53.149052],"type":"Point"}
}