{
  "type": "Feature",
  "properties": {
    "addr:full":"Hoofdstr 38 Kruiningen Zeeland 4416 AD",
    "addr:housenumber":"38",
    "addr:postcode":"4416 ad",
    "addr:street":"Hoofdstr",
    "iso:country":"NL",
    "sg:address":"Hoofdstr 38",
    "sg:city":"Kruiningen",
    "sg:orig_category":"Geluidsinstallaties - Verhuur",
    "sg:phone":"+31 113 320 025",
    "sg:postcode":"4416 AD",
    "sg:province":"Zeeland",
    "wof:name":"Lac Sound, Studio Reimerswaal",
    "wof:placetype":"venue"
},
  "geometry": {"coordinates":[4.032236,51.450253],"type":"Point"}
}