{
  "type": "Feature",
  "properties": {
    "iso:country":"NL",
    "sg:address":"Omtaplein 3",
    "sg:city":"Wieringerwerf",
    "sg:orig_category":"Banken And Kredietinstellingen",
    "sg:phone":"+31 227 601 241",
    "sg:postcode":"1771 CW",
    "sg:province":"Noord-Holland",
    "wof:name":"Abn Amro",
    "wof:placetype":"venue"
},
  "geometry": {"coordinates":[5.023444,52.854523],"type":"Point"}
}