{
  "type": "Feature",
  "properties": {
    "addr:full":"Koepelstraat 3 Rosmalen Noord-Brabant 5243 SC",
    "addr:housenumber":"3",
    "addr:postcode":"5243 sc",
    "addr:street":"Koepelstraat",
    "iso:country":"NL",
    "sg:address":"Koepelstraat 3",
    "sg:city":"Rosmalen",
    "sg:classifiers":[
        {
            "category":"Professional",
            "subcategory":"Accounting & Tax Preparation",
            "type":"Services"
        }
    ],
    "sg:phone":"+31 73 521 3735",
    "sg:postcode":"5243 SC",
    "sg:province":"Noord-Brabant",
    "sg:tags":[
        "accountant"
    ],
    "wof:name":"Hollander Bv",
    "wof:placetype":"venue"
},
  "geometry": {"coordinates":[5.371563,51.718548],"type":"Point"}
}