{
  "type": "Feature",
  "properties": {
    "addr:full":"Fazendadreef 46 Utrecht Utrecht 3563 EV",
    "addr:housenumber":"46",
    "addr:postcode":"3563 ev",
    "addr:street":"Fazendadreef",
    "iso:country":"NL",
    "sg:address":"Fazendadreef 46",
    "sg:city":"Utrecht",
    "sg:orig_category":"Kantoorbenodigdheden",
    "sg:phone":"+31 30 262 8164",
    "sg:postcode":"3563 EV",
    "sg:province":"Utrecht",
    "wof:name":"Joossen",
    "wof:placetype":"venue"
},
  "geometry": {"coordinates":[5.0986700058,52.120388031],"type":"Point"}
}