{
  "type": "Feature",
  "properties": {
    "addr:full":"Stationsstraat 81 Ermelo Gelderland 3851 NC",
    "addr:housenumber":"81",
    "addr:postcode":"3851 nc",
    "addr:street":"Stationsstraat;Gelderland",
    "iso:country":"NL",
    "sg:address":"Stationsstraat 81",
    "sg:city":"Ermelo",
    "sg:orig_category":"Juweliers",
    "sg:phone":"+31 341 554 479",
    "sg:postcode":"3851 NC",
    "sg:province":"Gelderland",
    "wof:name":"Wajer Juwelier",
    "wof:placetype":"venue"
},
  "geometry": {"coordinates":[5.62211,52.299755],"type":"Point"}
}