{
  "type": "Feature",
  "properties": {
    "iso:country":"NL",
    "sg:address":"Kreek 123 Wijkcentr",
    "sg:city":"Spykenisse",
    "sg:orig_category":"Verenigingsgebouwen",
    "sg:phone":"+31 181 632 539",
    "sg:postcode":"3206 HK",
    "sg:province":"Zuid-Holland",
    "wof:name":"Kreek, De",
    "wof:placetype":"venue"
},
  "geometry": {"coordinates":[4.32515,51.829128],"type":"Point"}
}