{
  "type": "Feature",
  "properties": {
    "addr:full":"Nieuwstr 50 Purmerend Noord-Holland 1441 CN",
    "addr:housenumber":"50",
    "addr:postcode":"1441 cn",
    "addr:street":"Nieuwstr",
    "iso:country":"NL",
    "sg:address":"Nieuwstr 50",
    "sg:city":"Purmerend",
    "sg:classifiers":[
        {
            "category":"Food & Beverages",
            "subcategory":"Bakery",
            "type":"Retail Goods"
        }
    ],
    "sg:phone":"+31 299 437 289",
    "sg:postcode":"1441 CN",
    "sg:province":"Noord-Holland",
    "sg:tags":[
        "pizza"
    ],
    "wof:name":"Babylon",
    "wof:placetype":"venue"
},
  "geometry": {"coordinates":[4.946484,52.507946],"type":"Point"}
}