{
  "type": "Feature",
  "properties": {
    "addr:full":"D Ben Goerionstr 57 Utrecht Utrecht 3573 XM",
    "addr:housenumber":"57",
    "addr:postcode":"3573 xm",
    "addr:street":"D",
    "iso:country":"NL",
    "sg:address":"D Ben Goerionstr 57",
    "sg:city":"Utrecht",
    "sg:orig_category":"Administratie- En Boekhoudkantoren",
    "sg:phone":"+31 30 273 5345",
    "sg:postcode":"3573 XM",
    "sg:province":"Utrecht",
    "wof:name":"Jb-Vze",
    "wof:placetype":"venue"
},
  "geometry": {"coordinates":[5.144518,52.113743],"type":"Point"}
}