{
  "type": "Feature",
  "properties": {
    "iso:country":"NL",
    "sg:address":"Adriaen Van Der Doeslaan 21",
    "sg:city":"Rotterdam",
    "sg:orig_category":"Autokeuringen",
    "sg:phone":"+31 10 418 3499",
    "sg:postcode":"3054 EA",
    "sg:province":"South Holland",
    "wof:name":"Garage Hillegersberg",
    "wof:placetype":"venue"
},
  "geometry": {"coordinates":[4.491394,51.957371],"type":"Point"}
}