{
  "type": "Feature",
  "properties": {
    "addr:full":"Kwekerswg 8 Uithuizen Groningen 9981 GE",
    "addr:housenumber":"8",
    "addr:postcode":"9981",
    "addr:street":"Kwekerswg",
    "iso:country":"NL",
    "sg:address":"Kwekerswg 8",
    "sg:city":"Uithuizen",
    "sg:orig_category":"Grondwerken",
    "sg:phone":"+31 595 431 203",
    "sg:postcode":"9981 GE",
    "sg:province":"Groningen",
    "wof:name":"Nieuwenhuyzen Uithuizen, Van",
    "wof:placetype":"venue"
},
  "geometry": {"coordinates":[6.678621,53.411453],"type":"Point"}
}