{
  "type": "Feature",
  "properties": {
    "addr:full":"Hoge Larenseweg 130 Hilversum Noord-Holland 1221 AT",
    "addr:housenumber":"130",
    "addr:postcode":"1221",
    "addr:street":"Hoge Larenseweg",
    "iso:country":"NL",
    "sg:address":"Hoge Larenseweg 130",
    "sg:city":"Hilversum",
    "sg:orig_category":"Drukkerijen And Copyshops",
    "sg:phone":"+31 35 685 5655",
    "sg:postcode":"1221 AT",
    "sg:province":"Noord-Holland",
    "wof:name":"Drukkerij Onkenhout Bv",
    "wof:placetype":"venue"
},
  "geometry": {"coordinates":[5.184505,52.232319],"type":"Point"}
}