{
  "type": "Feature",
  "properties": {
    "addr:full":"Holdaal 18 Maastricht Limburg 6228 GH",
    "addr:housenumber":"18",
    "addr:postcode":"6228 gh",
    "addr:street":"Holdaal",
    "iso:country":"NL",
    "sg:address":"Holdaal 18",
    "sg:city":"Maastricht",
    "sg:orig_category":"Boekhouders",
    "sg:phone":"+31 43 361 1113",
    "sg:postcode":"6228 GH",
    "sg:province":"Limburg",
    "wof:name":"Administratiekantoor Fraats",
    "wof:placetype":"venue"
},
  "geometry": {"coordinates":[5.720723,50.822605],"type":"Point"}
}