{
  "type": "Feature",
  "properties": {
    "iso:country":"NL",
    "sg:address":"Elleboogstr 7",
    "sg:city":"Huizen",
    "sg:orig_category":"Adviesbureaus",
    "sg:phone":"+31 35 525 7745",
    "sg:postcode":"1271 RG",
    "sg:province":"Noord-Holland",
    "wof:name":"Slikkerveer Bv",
    "wof:placetype":"venue"
},
  "geometry": {"coordinates":[5.236355,52.297386],"type":"Point"}
}