{
  "type": "Feature",
  "properties": {
    "addr:full":"Peperstraat 24 Egmond-Binnen North Holland 1935 BE",
    "addr:housenumber":"24",
    "addr:postcode":"1935",
    "addr:street":"Peperstraat",
    "iso:country":"NL",
    "sg:address":"Peperstraat 24",
    "sg:city":"Egmond-Binnen",
    "sg:orig_category":"Watersport-, Sport- And Kampeerbenodigdheden Verhuur",
    "sg:phone":"+31 72 506 9003",
    "sg:postcode":"1935 BE",
    "sg:province":"North Holland",
    "wof:name":"Bert'S Tweewielers Rijwielen",
    "wof:placetype":"venue"
},
  "geometry": {"coordinates":[4.6572918892,52.5949363708],"type":"Point"}
}