{
  "type": "Feature",
  "properties": {
    "iso:country":"NL",
    "sg:address":"Maast Brugstr 8",
    "sg:city":"Maastricht",
    "sg:orig_category":"Woninginrichting",
    "sg:phone":"+31 43 325 0972",
    "sg:postcode":"6211 ET",
    "sg:province":"Limburg",
    "wof:name":"Laura Ashley",
    "wof:placetype":"venue"
},
  "geometry": {"coordinates":[5.6938371658,50.8494644165],"type":"Point"}
}