{
  "type": "Feature",
  "properties": {
    "addr:full":"Ekkersrijt 2010 Son Noord-Brabant 5692 BA",
    "addr:housenumber":"2010",
    "addr:postcode":"son;5692 ba",
    "addr:street":"Ekkersrijt",
    "iso:country":"NL",
    "sg:address":"Ekkersrijt 2010",
    "sg:city":"Son",
    "sg:orig_category":"Naamplaten - Fabrieken",
    "sg:phone":"+31 499 398 925",
    "sg:postcode":"5692 BA",
    "sg:province":"Noord-Brabant",
    "sg:website":"http://www.verver-best.nl",
    "wof:name":"Verver-Best Bv",
    "wof:placetype":"venue"
},
  "geometry": {"coordinates":[-101.937622,35.189621],"type":"Point"}
}