{
  "type": "Feature",
  "properties": {
    "addr:full":"Kerkstraat 1 Kedichem South Holland 4247 EK",
    "addr:housenumber":"1",
    "addr:postcode":"4247 ek",
    "addr:street":"Kerkstraat",
    "iso:country":"NL",
    "sg:address":"Kerkstraat 1",
    "sg:city":"Kedichem",
    "sg:orig_category":"Meubelreparatie And -Restauratie",
    "sg:phone":"+31 183 563 448",
    "sg:postcode":"4247 EK",
    "sg:province":"South Holland",
    "wof:name":"Leersnijderij W.H. Peek",
    "wof:placetype":"venue"
},
  "geometry": {"coordinates":[5.052044,51.859852],"type":"Point"}
}