{
  "type": "Feature",
  "properties": {
    "addr:full":"Herengr 65 Amsterdam Noord-Holland 1015 BC",
    "addr:housenumber":"65",
    "addr:postcode":"1015 bc",
    "addr:street":"Herengr",
    "iso:country":"NL",
    "sg:address":"Herengr 65",
    "sg:city":"Amsterdam",
    "sg:orig_category":"Onroerende Goederen",
    "sg:phone":"+31 20 420 5753",
    "sg:postcode":"1015 BC",
    "sg:province":"Noord-Holland",
    "wof:name":"Herengracht Estate Vof",
    "wof:placetype":"venue"
},
  "geometry": {"coordinates":[4.891255,52.377827],"type":"Point"}
}