{
  "type": "Feature",
  "properties": {
    "addr:full":"Grenswg 1 Harlingen Friesland 8861 KX",
    "addr:housenumber":"1",
    "addr:postcode":"8861 kx",
    "addr:street":"Grenswg",
    "iso:country":"NL",
    "sg:address":"Grenswg 1",
    "sg:city":"Harlingen",
    "sg:orig_category":"Woninginrichting",
    "sg:phone":"+31 517 419 393",
    "sg:postcode":"8861 KX",
    "sg:province":"Friesland",
    "wof:name":"Walinga",
    "wof:placetype":"venue"
},
  "geometry": {"coordinates":[5.4382009506,53.1733703613],"type":"Point"}
}