{
  "type": "Feature",
  "properties": {
    "addr:full":"Paulus Buyslaan 25 Amersfoort Utrecht 3818 LC",
    "addr:housenumber":"25",
    "addr:postcode":"3818 lc",
    "addr:street":"Paulus Buyslaan",
    "iso:country":"NL",
    "sg:address":"Paulus Buyslaan 25",
    "sg:city":"Amersfoort",
    "sg:orig_category":"Artsen And Specialisten",
    "sg:phone":"+31 33 461 5924",
    "sg:postcode":"3818 LC",
    "sg:province":"Utrecht",
    "wof:name":"W. Opstelten",
    "wof:placetype":"venue"
},
  "geometry": {"coordinates":[5.377397,52.151466],"type":"Point"}
}