{
  "type": "Feature",
  "properties": {
    "addr:full":"Rykswg 29 Naarden Noord-Holland 1411 GD",
    "addr:housenumber":"29",
    "addr:postcode":"1411 gd",
    "addr:street":"Rykswg",
    "iso:country":"NL",
    "sg:address":"Rykswg 29",
    "sg:city":"Naarden",
    "sg:orig_category":"Projectontwikkeling",
    "sg:phone":"+31 35 695 0641",
    "sg:postcode":"1411 GD",
    "sg:province":"Noord-Holland",
    "wof:name":"Pcn",
    "wof:placetype":"venue"
},
  "geometry": {"coordinates":[5.156375,52.288097],"type":"Point"}
}