{
  "type": "Feature",
  "properties": {
    "addr:full":"Voorwg 1 Driesum Friesland 9114 RA",
    "addr:housenumber":"1",
    "addr:postcode":"9114 ra",
    "addr:street":"Voorwg",
    "iso:country":"NL",
    "sg:address":"Voorwg 1",
    "sg:city":"Driesum",
    "sg:orig_category":"Bloemen En Planten",
    "sg:phone":"+31 511 421 372",
    "sg:postcode":"9114 RA",
    "sg:province":"Friesland",
    "wof:name":"Posthuma, A En R",
    "wof:placetype":"venue"
},
  "geometry": {"coordinates":[6.04438,53.295273],"type":"Point"}
}