{
  "type": "Feature",
  "properties": {
    "addr:full":"1E Oosterparkstr 193 Amsterdam Noord-Holland 1091 HA",
    "addr:housenumber":"193",
    "addr:postcode":"1091 ha",
    "addr:street":"1E Oosterparkstr",
    "iso:country":"NL",
    "sg:address":"1E Oosterparkstr 193",
    "sg:city":"Amsterdam",
    "sg:orig_category":"Juweliers",
    "sg:phone":"+31 20 463 2173",
    "sg:postcode":"1091 HA",
    "sg:province":"Noord-Holland",
    "wof:name":"Taillie",
    "wof:placetype":"venue"
},
  "geometry": {"coordinates":[4.912672,52.356964],"type":"Point"}
}