{
  "type": "Feature",
  "properties": {
    "addr:full":"De Stad 1 Oirschot Noord-Brabant 5688 NX",
    "addr:housenumber":"1",
    "addr:postcode":"5688 nx",
    "addr:street":"De Stad",
    "iso:country":"NL",
    "sg:address":"De Stad 1",
    "sg:city":"Oirschot",
    "sg:classifiers":[
        {
            "category":"Bus Charters",
            "type":"Transportation"
        }
    ],
    "sg:phone":"+31 499 575 252",
    "sg:postcode":"5688 NX",
    "sg:province":"Noord-Brabant",
    "sg:tags":[
        "caravan"
    ],
    "sg:website":"http://www.sandecaravans.nl",
    "wof:name":"Sande, Van Der",
    "wof:placetype":"venue"
},
  "geometry": {"coordinates":[5.336137,51.503941],"type":"Point"}
}