{
  "type": "Feature",
  "properties": {
    "addr:full":"Eikenpln 3 Amsterdam Noord-Holland 1092 CC",
    "addr:housenumber":"3",
    "addr:postcode":"1092 cc",
    "addr:street":"Eikenpln",
    "iso:country":"NL",
    "sg:address":"Eikenpln 3",
    "sg:city":"Amsterdam",
    "sg:orig_category":"Peuterspeelzalen",
    "sg:phone":"+31 20 668 4345",
    "sg:postcode":"1092 CC",
    "sg:province":"Noord-Holland",
    "wof:name":"Dounia",
    "wof:placetype":"venue"
},
  "geometry": {"coordinates":[4.921952,52.35817],"type":"Point"}
}