{
  "type": "Feature",
  "properties": {
    "addr:full":"1E Industriewg 1 Hattem Gelderland 8051 CN",
    "addr:housenumber":"1",
    "addr:postcode":"8051 cn",
    "addr:street":"1E Industriewg;Gelderland",
    "iso:country":"NL",
    "sg:address":"1E Industriewg 1",
    "sg:city":"Hattem",
    "sg:orig_category":"Keukens",
    "sg:phone":"+31 38 444 1765",
    "sg:postcode":"8051 CN",
    "sg:province":"Gelderland",
    "wof:name":"Houtwerk Mkm Hattem Bv",
    "wof:placetype":"venue"
},
  "geometry": {"coordinates":[6.076549,52.465782],"type":"Point"}
}