{
  "type": "Feature",
  "properties": {
    "addr:full":"Heereweg 50 Schoorl North Holland 1871 EJ",
    "addr:housenumber":"50",
    "addr:postcode":"1871 ej",
    "addr:street":"Heereweg",
    "iso:country":"NL",
    "sg:address":"Heereweg 50",
    "sg:city":"Schoorl",
    "sg:orig_category":"Bedrijfs- And Managementsconsultants",
    "sg:phone":"+31 72 509 3487",
    "sg:postcode":"1871 EJ",
    "sg:province":"North Holland",
    "wof:name":"Adviesbureau Sellers En Sales",
    "wof:placetype":"venue"
},
  "geometry": {"coordinates":[4.693296,52.70343],"type":"Point"}
}