{
  "type": "Feature",
  "properties": {
    "iso:country":"NL",
    "sg:address":"Lochemseweg 94",
    "sg:city":"Harfsen",
    "sg:orig_category":"Fotostudio'S And Fotografen",
    "sg:phone":"+31 573 431 588",
    "sg:postcode":"7217 RJ",
    "sg:province":"Gelderland",
    "wof:name":"Foto W. Wichers",
    "wof:placetype":"venue"
},
  "geometry": {"coordinates":[6.283289,52.209129],"type":"Point"}
}