{
  "type": "Feature",
  "properties": {
    "addr:full":"Slijperweg 3 Amsterdam Noord-Holland 1032 KT",
    "addr:housenumber":"3",
    "addr:postcode":"1032 kt",
    "addr:street":"Slijperweg",
    "iso:country":"NL",
    "sg:address":"Slijperweg 3",
    "sg:city":"Amsterdam",
    "sg:orig_category":"Glaszetten",
    "sg:phone":"+31 20 632 3826",
    "sg:postcode":"1032 KT",
    "sg:province":"Noord-Holland",
    "wof:name":"Glashandel Noord",
    "wof:placetype":"venue"
},
  "geometry": {"coordinates":[4.906909,52.399986],"type":"Point"}
}