{
  "type": "Feature",
  "properties": {
    "addr:full":"Mauvestr 8A Baarn Utrecht 3741 TN",
    "addr:housenumber":"8a",
    "addr:postcode":"3741",
    "addr:street":"Mauvestr",
    "iso:country":"NL",
    "sg:address":"Mauvestr 8A",
    "sg:city":"Baarn",
    "sg:orig_category":"Koffie En Thee - Apparaten En Artikelen",
    "sg:phone":"+31 6 20372684",
    "sg:postcode":"3741 TN",
    "sg:province":"Utrecht",
    "wof:name":"Cedric",
    "wof:placetype":"venue"
},
  "geometry": {"coordinates":[5.290688,52.215122],"type":"Point"}
}