{
  "type": "Feature",
  "properties": {
    "addr:full":"Zuidergracht 5 Soest Utrecht 3763 LS",
    "addr:housenumber":"5",
    "addr:postcode":"3763 ls",
    "addr:street":"Zuidergracht",
    "iso:country":"NL",
    "sg:address":"Zuidergracht 5",
    "sg:city":"Soest",
    "sg:orig_category":"Papier- And Kartonverpakkingen Fab",
    "sg:phone":"+31 35 603 3555",
    "sg:postcode":"3763 LS",
    "sg:province":"Utrecht",
    "wof:name":"Cmm Bv",
    "wof:placetype":"venue"
},
  "geometry": {"coordinates":[5.268958,52.176567],"type":"Point"}
}