{
  "type": "Feature",
  "properties": {
    "addr:full":"N Beetsstr 82 Amsterdam Noord-Holland 1053 RP",
    "addr:housenumber":"82",
    "addr:postcode":"1053 rp",
    "addr:street":"N",
    "iso:country":"NL",
    "sg:address":"N Beetsstr 82",
    "sg:city":"Amsterdam",
    "sg:orig_category":"Kinderopvang",
    "sg:phone":"+31 20 489 5484",
    "sg:postcode":"1053 RP",
    "sg:province":"Noord-Holland",
    "wof:name":"Borgheem",
    "wof:placetype":"venue"
},
  "geometry": {"coordinates":[4.865478,52.365162],"type":"Point"}
}