{
  "type": "Feature",
  "properties": {
    "addr:full":"Ijsselweg 10 Terborg Gelderland 7061 XW",
    "addr:housenumber":"10",
    "addr:postcode":"7061 xw",
    "addr:street":"Ijsselweg;Gelderland",
    "iso:country":"NL",
    "sg:address":"Ijsselweg 10",
    "sg:city":"Terborg",
    "sg:orig_category":"Goederenvervoer Over De Weg",
    "sg:phone":"+31 315 324 930",
    "sg:postcode":"7061 XW",
    "sg:province":"Gelderland",
    "wof:name":"Transportbedrijf J.H.W. Hartemink",
    "wof:placetype":"venue"
},
  "geometry": {"coordinates":[6.347595,51.920063],"type":"Point"}
}