{
  "type": "Feature",
  "properties": {
    "iso:country":"NL",
    "sg:address":"Braspenning 24",
    "sg:city":"Dronten",
    "sg:orig_category":"Kantoorartikelen",
    "sg:phone":"+31 321 336 000",
    "sg:postcode":"8253 BB",
    "sg:province":"NL.",
    "wof:name":"Concept & Interieur Bv",
    "wof:placetype":"venue"
},
  "geometry": {"coordinates":[5.6993279457,52.5311203003],"type":"Point"}
}