{
  "type": "Feature",
  "properties": {
    "addr:full":"Braspenning 24 Dronten NL. 8253 BB",
    "addr:housenumber":"24",
    "addr:postcode":"8253 bb",
    "addr:street":"Braspenning;Nl.",
    "iso:country":"NL",
    "sg:address":"Braspenning 24",
    "sg:city":"Dronten",
    "sg:orig_category":"Kantoorartikelen",
    "sg:phone":"+31 321 336 000",
    "sg:postcode":"8253 BB",
    "sg:province":"NL.",
    "wof:name":"Concept & Interieur Bv",
    "wof:placetype":"venue"
},
  "geometry": {"coordinates":[5.6993279457,52.5311203003],"type":"Point"}
}