{
  "type": "Feature",
  "properties": {
    "addr:full":"Dorpsstraat 15 Elst Gld Gelderland 6661 EE",
    "addr:housenumber":"15",
    "addr:postcode":"6661 ee",
    "addr:street":"Dorpsstraat;Gld Gelderland",
    "iso:country":"NL",
    "sg:address":"Dorpsstraat 15",
    "sg:city":"Elst Gld",
    "sg:orig_category":"Juweliers",
    "sg:phone":"+31 481 371 677",
    "sg:postcode":"6661 EE",
    "sg:province":"Gelderland",
    "wof:name":"Juwelier Stekelenburg Vof",
    "wof:placetype":"venue"
},
  "geometry": {"coordinates":[5.848537,51.919147],"type":"Point"}
}