{
  "type": "Feature",
  "properties": {
    "addr:full":"Dommelshei 19 Veldhoven Noord-Brabant 5508 VE",
    "addr:housenumber":"19",
    "addr:postcode":"5508",
    "addr:street":"Dommelshei;Ve",
    "iso:country":"NL",
    "sg:address":"Dommelshei 19",
    "sg:city":"Veldhoven",
    "sg:orig_category":"Artsen And Specialisten",
    "sg:phone":"+31 40 253 1313",
    "sg:postcode":"5508 VE",
    "sg:province":"Noord-Brabant",
    "wof:name":"A.N.J. Daamen",
    "wof:placetype":"venue"
},
  "geometry": {"coordinates":[5.393225,51.427536],"type":"Point"}
}