{
  "type": "Feature",
  "properties": {
    "iso:country":"NL",
    "sg:address":"Postbus 14",
    "sg:city":"Winsum Gn",
    "sg:orig_category":"Voetbalverenigingen",
    "sg:phone":"+31 595 443 556",
    "sg:postcode":"9950 AA",
    "wof:name":"Hunsingo",
    "wof:placetype":"venue"
},
  "geometry": {"coordinates":[6.51739,53.334412],"type":"Point"}
}