{
  "type": "Feature",
  "properties": {
    "addr:full":"Larenseweg 44 Markelo Overijssel 7475 PW",
    "addr:housenumber":"44",
    "addr:postcode":"7475 pw",
    "addr:street":"Larenseweg",
    "iso:country":"NL",
    "sg:address":"Larenseweg 44",
    "sg:city":"Markelo",
    "sg:classifiers":[
        {
            "category":"Education",
            "subcategory":"Preschool",
            "type":"Public Place"
        }
    ],
    "sg:phone":"+31 547 362 723",
    "sg:postcode":"7475 PW",
    "sg:province":"Overijssel",
    "sg:tags":[
        "kleuteronderwijs",
        "basis-"
    ],
    "wof:name":"Brookschole",
    "wof:placetype":"venue"
},
  "geometry": {"coordinates":[6.449523,52.236294],"type":"Point"}
}