{
  "type": "Feature",
  "properties": {
    "addr:full":"Hillegomlaan 38 Tilburg North Brabant 5045 AD",
    "addr:housenumber":"38",
    "addr:postcode":"5045 ad",
    "addr:street":"Hillegomlaan",
    "iso:country":"NL",
    "sg:address":"Hillegomlaan 38",
    "sg:city":"Tilburg",
    "sg:orig_category":"Geluidsopnamen",
    "sg:phone":"+31 13 463 3159",
    "sg:postcode":"5045 AD",
    "sg:province":"North Brabant",
    "wof:name":"Zangstudio R Waagenaar",
    "wof:placetype":"venue"
},
  "geometry": {"coordinates":[5.002149,51.581085],"type":"Point"}
}