{
  "type": "Feature",
  "properties": {
    "addr:full":"Weth Voogtgeertstraat 7 Hengelo Ov Overijssel 7553 EL",
    "addr:housenumber":"7",
    "addr:postcode":"7553 el",
    "addr:street":"Weth Voogtgeertstraat;Ov",
    "iso:country":"NL",
    "sg:address":"Weth Voogtgeertstraat 7",
    "sg:city":"Hengelo Ov",
    "sg:orig_category":"Daken And Skeletbouw",
    "sg:phone":"+31 74 242 6508",
    "sg:postcode":"7553 EL",
    "sg:province":"Overijssel",
    "wof:name":"Brukodak",
    "wof:placetype":"venue"
},
  "geometry": {"coordinates":[6.78971,52.266331],"type":"Point"}
}