{
  "type": "Feature",
  "properties": {
    "addr:full":"J Smuldersstr 5C Vessem Noord-Brabant 5512 AW",
    "addr:housenumber":"5c",
    "addr:postcode":"5512 aw",
    "iso:country":"NL",
    "sg:address":"J Smuldersstr 5C",
    "sg:city":"Vessem",
    "sg:orig_category":"Kunststof Ramen",
    "sg:phone":"+31 497 592 307",
    "sg:postcode":"5512 AW",
    "sg:province":"Noord-Brabant",
    "sg:website":"http://www.aclass-montage.nl",
    "wof:name":"A Class",
    "wof:placetype":"venue"
},
  "geometry": {"coordinates":[5.285726,51.418236],"type":"Point"}
}