{
  "type": "Feature",
  "properties": {
    "iso:country":"NL",
    "sg:address":"Amsterdamsestrwg 59",
    "sg:city":"Utrecht",
    "sg:orig_category":"Kinderkleding",
    "sg:phone":"+31 30 288 6757",
    "sg:postcode":"3513 AB",
    "sg:province":"Utrecht",
    "wof:name":"Bengels Kindermode",
    "wof:placetype":"venue"
},
  "geometry": {"coordinates":[5.107472,52.096478],"type":"Point"}
}