{
  "type": "Feature",
  "properties": {
    "addr:full":"Henry Dunantweg 10 Alphen A/D Rijn Zuid-Holland 2402 NP",
    "addr:housenumber":"10",
    "addr:postcode":"2402 np",
    "addr:street":"Henry Dunantweg",
    "iso:country":"NL",
    "sg:address":"Henry Dunantweg 10",
    "sg:city":"Alphen A/D Rijn",
    "sg:orig_category":"Verzekeringen",
    "sg:phone":"+31 172 469 479",
    "sg:postcode":"2402 NP",
    "sg:province":"Zuid-Holland",
    "wof:name":"Bosma Advies Bv",
    "wof:placetype":"venue"
},
  "geometry": {"coordinates":[4.661268,52.145187],"type":"Point"}
}