{
  "type": "Feature",
  "properties": {
    "iso:country":"NL",
    "sg:address":"Rykswg 101",
    "sg:city":"Gaanderen",
    "sg:orig_category":"Opticiens",
    "sg:phone":"+31 315 341 245",
    "sg:postcode":"7011 DT",
    "sg:province":"Gelderland",
    "sg:website":"http://www.mariopunteoptiek.nl",
    "wof:name":"Mario Punte",
    "wof:placetype":"venue"
},
  "geometry": {"coordinates":[6.3447551727,51.9289932251],"type":"Point"}
}