{
  "type": "Feature",
  "properties": {
    "addr:full":"Rozengr 207B Amsterdam Noord-Holland 1016 LZ",
    "addr:housenumber":"207b",
    "addr:postcode":"1016 lz",
    "iso:country":"NL",
    "sg:address":"Rozengr 207B",
    "sg:city":"Amsterdam",
    "sg:orig_category":"Fotografie Reclame En Mode",
    "sg:phone":"+31 20 626 0418",
    "sg:postcode":"1016 LZ",
    "sg:province":"Noord-Holland",
    "wof:name":"Sweering, M",
    "wof:placetype":"venue"
},
  "geometry": {"coordinates":[4.877082,52.372353],"type":"Point"}
}