{
  "type": "Feature",
  "properties": {
    "addr:full":"Fultonstr 6 S Gravenhage South Holland 2562 XH",
    "addr:housenumber":"6",
    "addr:postcode":"2562 xh",
    "addr:street":"Fultonstr;S Gravenhage",
    "iso:country":"NL",
    "sg:address":"Fultonstr 6",
    "sg:city":"S Gravenhage",
    "sg:orig_category":"Onderhoudswerken",
    "sg:phone":"+31 70 363 7768",
    "sg:postcode":"2562 XH",
    "sg:province":"South Holland",
    "wof:name":"Soest, Van",
    "wof:placetype":"venue"
},
  "geometry": {"coordinates":[4.28326,52.075001],"type":"Point"}
}