{
  "type": "Feature",
  "properties": {
    "iso:country":"NL",
    "sg:address":"Bataviastr 81",
    "sg:city":"Utrecht",
    "sg:orig_category":"Adviesbureaus Bedrijfsorganisatie",
    "sg:phone":"+31 30 293 3551",
    "sg:postcode":"3531 XC",
    "sg:province":"Utrecht",
    "wof:name":"Eastwest Heeling",
    "wof:placetype":"venue"
},
  "geometry": {"coordinates":[5.087337,52.093651],"type":"Point"}
}