{
  "type": "Feature",
  "properties": {
    "addr:full":"Bessenvlinderstr 95A Eindhoven Noord-Brabant 5641 EB",
    "addr:housenumber":"95a",
    "addr:postcode":"5641 eb",
    "addr:street":"Bessenvlinderstr",
    "iso:country":"NL",
    "sg:address":"Bessenvlinderstr 95A",
    "sg:city":"Eindhoven",
    "sg:orig_category":"Organisatiebureaus",
    "sg:phone":"+31 40 290 8565",
    "sg:postcode":"5641 EB",
    "sg:province":"Noord-Brabant",
    "wof:name":"Panic Productions, Sticht",
    "wof:placetype":"venue"
},
  "geometry": {"coordinates":[5.520442009,51.4526023865],"type":"Point"}
}