{
  "type": "Feature",
  "properties": {
    "addr:full":"Westgroenewg 63 Dinteloord North Brabant 4671 CL",
    "addr:housenumber":"63",
    "addr:postcode":"4671",
    "addr:street":"Westgroenewg",
    "iso:country":"NL",
    "sg:address":"Westgroenewg 63",
    "sg:city":"Dinteloord",
    "sg:orig_category":"Postorderbedrijven",
    "sg:phone":"+31 167 523 754",
    "sg:postcode":"4671 CL",
    "sg:province":"North Brabant",
    "wof:name":"P + E",
    "wof:placetype":"venue"
},
  "geometry": {"coordinates":[4.366748,51.634834],"type":"Point"}
}