{
  "type": "Feature",
  "properties": {
    "iso:country":"NL",
    "sg:address":"Hinthamerstr 159",
    "sg:city":"S Hertogenbosch",
    "sg:orig_category":"Koffie- En Theehuizen",
    "sg:phone":"+31 73 613 5236",
    "sg:postcode":"5211 MK",
    "sg:province":"Noord-Brabant",
    "wof:name":"Chip'Ndale",
    "wof:placetype":"venue"
},
  "geometry": {"coordinates":[5.311632,51.688419],"type":"Point"}
}