{
  "type": "Feature",
  "properties": {
    "iso:country":"NL",
    "sg:address":"Gevers Deynootweg 1130",
    "sg:city":"'S Gravenhage",
    "sg:orig_category":"Kansspelen",
    "sg:phone":"+31 70 352 2502",
    "sg:postcode":"2586 BX",
    "sg:province":"Zuid-Holland",
    "wof:name":"Hommerson Arcades Bv",
    "wof:placetype":"venue"
},
  "geometry": {"coordinates":[4.284640789,52.1146240234],"type":"Point"}
}