{
  "type": "Feature",
  "properties": {
    "iso:country":"NL",
    "sg:address":"Ln V Diepenvoorde 9-14",
    "sg:city":"Waalre",
    "sg:orig_category":"Beveiliging",
    "sg:phone":"+31 40 223 2323",
    "sg:postcode":"5582 LA",
    "sg:province":"Noord-Brabant",
    "wof:name":"Tyco",
    "wof:placetype":"venue"
},
  "geometry": {"coordinates":[5.476642,51.402576],"type":"Point"}
}