{
  "type": "Feature",
  "properties": {
    "addr:full":"S Gravelandsewg 6 Hilversum North Holland 1211 BR",
    "addr:housenumber":"6",
    "addr:postcode":"1211 br",
    "iso:country":"NL",
    "sg:address":"S Gravelandsewg 6",
    "sg:city":"Hilversum",
    "sg:orig_category":"Keukens",
    "sg:phone":"+31 35 621 0412",
    "sg:postcode":"1211 BR",
    "sg:province":"North Holland",
    "sg:website":"http://www.poggenpohlstudio.nl",
    "wof:name":"Poggenpohl",
    "wof:placetype":"venue"
},
  "geometry": {"coordinates":[5.17193,52.22496],"type":"Point"}
}