{
  "type": "Feature",
  "properties": {
    "addr:full":"N Swygmanstr 152 Breda Noord-Brabant 4822 VC",
    "addr:housenumber":"152",
    "addr:postcode":"4822 vc",
    "addr:street":"N",
    "iso:country":"NL",
    "sg:address":"N Swygmanstr 152",
    "sg:city":"Breda",
    "sg:orig_category":"Kunsthandel",
    "sg:phone":"+31 76 541 8453",
    "sg:postcode":"4822 VC",
    "sg:province":"Noord-Brabant",
    "wof:name":"Wilart",
    "wof:placetype":"venue"
},
  "geometry": {"coordinates":[4.728807,51.608864],"type":"Point"}
}