{
  "type": "Feature",
  "properties": {
    "addr:full":"Koraalrood 12 Zoetermeer Zuid-Holland 2718 SC",
    "addr:housenumber":"12",
    "addr:postcode":"2718 sc",
    "addr:street":"Koraalrood",
    "iso:country":"NL",
    "sg:address":"Koraalrood 12",
    "sg:city":"Zoetermeer",
    "sg:orig_category":"Geluidsopnamen",
    "sg:phone":"+31 79 362 3043",
    "sg:postcode":"2718 SC",
    "sg:province":"Zuid-Holland",
    "wof:name":"Qcd Media Prod",
    "wof:placetype":"venue"
},
  "geometry": {"coordinates":[4.501892,52.040455],"type":"Point"}
}