{
  "type": "Feature",
  "properties": {
    "iso:country":"NL",
    "sg:address":"Berencamperwg 8",
    "sg:city":"Nykerk Gld",
    "sg:orig_category":"Verenigingen En Stichtingen",
    "sg:phone":"+31 33 245 5059",
    "sg:postcode":"3861 MC",
    "sg:province":"Gelderland",
    "wof:name":"Dealercouncil Vw En Audi",
    "wof:placetype":"venue"
},
  "geometry": {"coordinates":[5.4831,52.221569],"type":"Point"}
}