{
  "type": "Feature",
  "properties": {
    "iso:country":"NL",
    "sg:address":"Hobbemastr 1",
    "sg:city":"Hardinxv Giessend",
    "sg:orig_category":"Scholen Voor Basisonderwijs",
    "sg:phone":"+31 184 612 345",
    "sg:postcode":"3372 XG",
    "sg:province":"Zuid-Holland",
    "wof:name":"Regenboog Sch Met De Bijbel, De",
    "wof:placetype":"venue"
},
  "geometry": {"coordinates":[7.693745,47.199856],"type":"Point"}
}