{
  "type": "Feature",
  "properties": {
    "addr:full":"Oosterscheldestraat 12 Middelburg Zeeland 4335 PH",
    "addr:housenumber":"12",
    "addr:postcode":"4335",
    "addr:street":"Oosterscheldestraat",
    "iso:country":"NL",
    "sg:address":"Oosterscheldestraat 12",
    "sg:city":"Middelburg",
    "sg:orig_category":"Artsen And Specialisten",
    "sg:phone":"+31 118 614 664",
    "sg:postcode":"4335 PH",
    "sg:province":"Zeeland",
    "wof:name":"G H J Meyjer",
    "wof:placetype":"venue"
},
  "geometry": {"coordinates":[3.60204,51.490452],"type":"Point"}
}