{
  "type": "Feature",
  "properties": {
    "addr:full":"Marcantiln 195 Amsterdam North Holland 1051 NA",
    "addr:housenumber":"195",
    "addr:postcode":"1051 na",
    "iso:country":"NL",
    "sg:address":"Marcantiln 195",
    "sg:city":"Amsterdam",
    "sg:orig_category":"Fotojournalisten Freelance",
    "sg:phone":"+31 20 681 7702",
    "sg:postcode":"1051 NA",
    "sg:province":"North Holland",
    "wof:name":"Peter D",
    "wof:placetype":"venue"
},
  "geometry": {"coordinates":[4.866482,52.374203],"type":"Point"}
}