{
  "type": "Feature",
  "properties": {
    "addr:full":"Randwg 1 Spykenisse Zuid-Holland 3201 VN",
    "addr:housenumber":"1",
    "addr:postcode":"3201 vn",
    "addr:street":"Randwg",
    "iso:country":"NL",
    "sg:address":"Randwg 1",
    "sg:city":"Spykenisse",
    "sg:orig_category":"Autoschade- Herstelbedrijven",
    "sg:phone":"+31 181 615 454",
    "sg:postcode":"3201 VN",
    "sg:province":"Zuid-Holland",
    "sg:website":"http://www.hoogvliet-bv.nl",
    "wof:name":"Hoogvliet & Zn Bv",
    "wof:placetype":"venue"
},
  "geometry": {"coordinates":[4.325045,51.849525],"type":"Point"}
}