{
  "type": "Feature",
  "properties": {
    "iso:country":"NL",
    "sg:address":"Hoenderdk 5A",
    "sg:city":"Ouddorp Zh",
    "sg:orig_category":"Huishoudelijke Apparaten En Artikelen",
    "sg:phone":"+31 187 689 908",
    "sg:postcode":"3253 AK",
    "sg:province":"Zuid-Holland",
    "wof:name":"Marskramer Bv",
    "wof:placetype":"venue"
},
  "geometry": {"coordinates":[3.934896,51.809013],"type":"Point"}
}