{
  "type": "Feature",
  "properties": {
    "addr:full":"Molenhof 2 Someren Noord-Brabant 5711 JB",
    "addr:housenumber":"2",
    "addr:postcode":"5711 jb",
    "addr:street":"Molenhof",
    "iso:country":"NL",
    "sg:address":"Molenhof 2",
    "sg:city":"Someren",
    "sg:orig_category":"Loodgieterswerk, Verwarming And Sanitaire Installaties",
    "sg:phone":"+31 6 51439395",
    "sg:postcode":"5711 JB",
    "sg:province":"Noord-Brabant",
    "wof:name":"Ron Driessen",
    "wof:placetype":"venue"
},
  "geometry": {"coordinates":[5.71724,51.383636],"type":"Point"}
}