{
  "type": "Feature",
  "properties": {
    "addr:full":"Hiemerwaard 59 Alkmaar Noord-Holland 1824 SM",
    "addr:housenumber":"59",
    "addr:postcode":"1824 sm",
    "addr:street":"Hiemerwaard",
    "iso:country":"NL",
    "sg:address":"Hiemerwaard 59",
    "sg:city":"Alkmaar",
    "sg:orig_category":"Woningstoffeerders",
    "sg:phone":"+31 6 11381677",
    "sg:postcode":"1824 SM",
    "sg:province":"Noord-Holland",
    "wof:name":"Barhorst, Ed",
    "wof:placetype":"venue"
},
  "geometry": {"coordinates":[4.7482619286,52.6436691284],"type":"Point"}
}