{
  "type": "Feature",
  "properties": {
    "iso:country":"NL",
    "sg:address":"Oorsprongwg 3",
    "sg:city":"De Cocksdorp",
    "sg:classifiers":[
        {
            "category":"Retail",
            "subcategory":"Auto Repair",
            "type":"Services"
        }
    ],
    "sg:phone":"+31 222 311 611",
    "sg:postcode":"1795 LA",
    "sg:province":"Noord-Holland",
    "sg:tags":[
        "garage"
    ],
    "wof:name":"Dros",
    "wof:placetype":"venue"
},
  "geometry": {"coordinates":[4.849885,53.13456],"type":"Point"}
}