{
  "type": "Feature",
  "properties": {
    "addr:full":"Duinweg 115 Oostkapelle Zeeland 4356 GA",
    "addr:housenumber":"115",
    "addr:postcode":"4356 ga",
    "addr:street":"Duinweg",
    "iso:country":"NL",
    "sg:address":"Duinweg 115",
    "sg:city":"Oostkapelle",
    "sg:classifiers":[
        {
            "category":"Fast Food",
            "type":"Food & Drink"
        }
    ],
    "sg:phone":"+31 118 581 933",
    "sg:postcode":"4356 GA",
    "sg:province":"Zeeland",
    "sg:tags":[
        "afhaal",
        "restaurant"
    ],
    "wof:name":"De Bostent",
    "wof:placetype":"venue"
},
  "geometry": {"coordinates":[3.544969,51.579041],"type":"Point"}
}