{
  "type": "Feature",
  "properties": {
    "addr:full":"Past Potterspln 2 Breda Noord-Brabant 4815 BC",
    "addr:housenumber":"2",
    "addr:postcode":"4815 bc",
    "iso:country":"NL",
    "sg:address":"Past Potterspln 2",
    "sg:city":"Breda",
    "sg:orig_category":"Scholen Voor Basisonderwijs",
    "sg:phone":"+31 76 571 0964",
    "sg:postcode":"4815 BC",
    "sg:province":"Noord-Brabant",
    "wof:name":"Spoorzoeker Rk, De",
    "wof:placetype":"venue"
},
  "geometry": {"coordinates":[4.778658,51.59927],"type":"Point"}
}