{
  "type": "Feature",
  "properties": {
    "iso:country":"NL",
    "sg:address":"Past Potterspln 2",
    "sg:city":"Breda",
    "sg:orig_category":"Scholen Voor Basisonderwijs",
    "sg:phone":"+31 76 571 0964",
    "sg:postcode":"4815 BC",
    "sg:province":"Noord-Brabant",
    "wof:name":"Spoorzoeker Rk, De",
    "wof:placetype":"venue"
},
  "geometry": {"coordinates":[4.778658,51.59927],"type":"Point"}
}