{
  "type": "Feature",
  "properties": {
    "addr:full":"Dorpsstraat 130 Zevenhuizen Zh South Holland 2761 AH",
    "addr:housenumber":"130;zh",
    "addr:postcode":"2761 ah",
    "addr:street":"Dorpsstraat",
    "iso:country":"NL",
    "sg:address":"Dorpsstraat 130",
    "sg:city":"Zevenhuizen Zh",
    "sg:orig_category":"Waterbehandeling En Waterzuiverings- Systemen",
    "sg:phone":"+31 180 638 296",
    "sg:postcode":"2761 AH",
    "sg:province":"South Holland",
    "wof:name":"Arelbee Serv",
    "wof:placetype":"venue"
},
  "geometry": {"coordinates":[4.5820159912,52.0112876892],"type":"Point"}
}