{
  "type": "Feature",
  "properties": {
    "addr:full":"Industriewg 3F Moergestel North Brabant 5066 XJ",
    "addr:housenumber":"3f",
    "addr:postcode":"5066 xj",
    "iso:country":"NL",
    "sg:address":"Industriewg 3F",
    "sg:city":"Moergestel",
    "sg:orig_category":"Metaalbewerking",
    "sg:phone":"+31 13 513 1765",
    "sg:postcode":"5066 XJ",
    "sg:province":"North Brabant",
    "wof:name":"Metem",
    "wof:placetype":"venue"
},
  "geometry": {"coordinates":[5.177755,51.548275],"type":"Point"}
}