{
  "type": "Feature",
  "properties": {
    "addr:full":"Ljochtewei 1 Leeuwarden Friesland 8912 BC",
    "addr:housenumber":"1",
    "addr:postcode":"8912 bc",
    "addr:street":"Ljochtewei",
    "iso:country":"NL",
    "sg:address":"Ljochtewei 1",
    "sg:city":"Leeuwarden",
    "sg:orig_category":"Hoefdierhouderijen",
    "sg:phone":"+31 58 254 1596",
    "sg:postcode":"8912 BC",
    "sg:province":"Friesland",
    "wof:name":"B. Renken",
    "wof:placetype":"venue"
},
  "geometry": {"coordinates":[5.752395,53.189232],"type":"Point"}
}