{
  "type": "Feature",
  "properties": {
    "addr:full":"Klooster Leuterstraat 25 Wijk Bij Duurstede Utrecht 3961 AX",
    "addr:housenumber":"25",
    "addr:postcode":"3961 ax",
    "addr:street":"Klooster Leuterstraat",
    "iso:country":"NL",
    "sg:address":"Klooster Leuterstraat 25",
    "sg:city":"Wijk Bij Duurstede",
    "sg:orig_category":"Schilderwerk",
    "sg:phone":"+31 343 571 325",
    "sg:postcode":"3961 AX",
    "sg:province":"Utrecht",
    "wof:name":"Schildersbedrijf A.K. Verheul",
    "wof:placetype":"venue"
},
  "geometry": {"coordinates":[5.346636,51.972855],"type":"Point"}
}