{
  "type": "Feature",
  "properties": {
    "addr:full":"St Ignatiusstr 225C Breda Noord-Brabant 4817 KJ",
    "addr:housenumber":"225c",
    "addr:postcode":"4817 kj",
    "iso:country":"NL",
    "sg:address":"St Ignatiusstr 225C",
    "sg:city":"Breda",
    "sg:orig_category":"Administratie- En Boekhoudkantoren",
    "sg:phone":"+31 76 520 7520",
    "sg:postcode":"4817 KJ",
    "sg:province":"Noord-Brabant",
    "wof:name":"Mkb Breda",
    "wof:placetype":"venue"
},
  "geometry": {"coordinates":[4.801917,51.59132],"type":"Point"}
}