{
  "type": "Feature",
  "properties": {
    "addr:full":"Standaardruiter 9 Veenendaal Utrecht 3905 PT",
    "addr:housenumber":"9",
    "addr:postcode":"3905 pt",
    "addr:street":"Standaardruiter",
    "iso:country":"NL",
    "sg:address":"Standaardruiter 9",
    "sg:city":"Veenendaal",
    "sg:orig_category":"Architecten",
    "sg:phone":"+31 318 517 316",
    "sg:postcode":"3905 PT",
    "sg:province":"Utrecht",
    "wof:name":"Van Beek Jagtenberg Bv",
    "wof:placetype":"venue"
},
  "geometry": {"coordinates":[5.544163,52.038082],"type":"Point"}
}