{
  "type": "Feature",
  "properties": {
    "addr:full":"Lingebos 3 Purmerend North Holland 1447 SX",
    "addr:housenumber":"3",
    "addr:postcode":"1447 sx",
    "addr:street":"Lingebos",
    "iso:country":"NL",
    "sg:address":"Lingebos 3",
    "sg:city":"Purmerend",
    "sg:orig_category":"Onroerende Goederen",
    "sg:phone":"+31 6 53932102",
    "sg:postcode":"1447 SX",
    "sg:province":"North Holland",
    "wof:name":"Bock Bv, A R De",
    "wof:placetype":"venue"
},
  "geometry": {"coordinates":[4.975216,52.492744],"type":"Point"}
}