{
  "type": "Feature",
  "properties": {
    "addr:full":"J Israelsln 463 Ryswyk Zh Zuid-Holland 2282 TK",
    "addr:housenumber":"463",
    "addr:postcode":"2282 tk",
    "addr:street":"Ryswyk",
    "iso:country":"NL",
    "sg:address":"J Israelsln 463",
    "sg:city":"Ryswyk Zh",
    "sg:orig_category":"Administratie- En Boekhoudkantoren",
    "sg:phone":"+31 70 390 5433",
    "sg:postcode":"2282 TK",
    "sg:province":"Zuid-Holland",
    "wof:name":"Jabu",
    "wof:placetype":"venue"
},
  "geometry": {"coordinates":[4.33694,52.056503],"type":"Point"}
}