{
  "type": "Feature",
  "properties": {
    "iso:country":"NL",
    "sg:address":"Rotterdamsedk 139",
    "sg:city":"Schiedam",
    "sg:orig_category":"Webdesign Bureaus",
    "sg:phone":"+31 10 426 4218",
    "sg:postcode":"3112 AC",
    "sg:province":"Zuid-Holland",
    "wof:name":"Appl",
    "wof:placetype":"venue"
},
  "geometry": {"coordinates":[4.4101681709,51.9141654968],"type":"Point"}
}