{
  "type": "Feature",
  "properties": {
    "iso:country":"NL",
    "sg:address":"Lagoswg 15",
    "sg:city":"Delft",
    "sg:orig_category":"Autolakken",
    "sg:phone":"+31 15 257 1020",
    "sg:postcode":"2622 CZ",
    "sg:province":"Zuid-Holland",
    "wof:name":"Nieuwenhuis",
    "wof:placetype":"venue"
},
  "geometry": {"coordinates":[4.34187,51.984688],"type":"Point"}
}