{
  "type": "Feature",
  "properties": {
    "iso:country":"NL",
    "sg:address":"Graanwg 19",
    "sg:city":"Moerdyk",
    "sg:orig_category":"Havenbedrijven",
    "sg:phone":"+31 168 334 270",
    "sg:postcode":"4782 PP",
    "sg:province":"Noord-Brabant",
    "sg:website":"http://www.van-uden.nl",
    "wof:name":"Seaport Moerdijk Bv",
    "wof:placetype":"venue"
},
  "geometry": {"coordinates":[4.59528,51.685551],"type":"Point"}
}