{
  "type": "Feature",
  "properties": {
    "addr:full":"Spoorstraat 7 Haaksbergen Overijssel 7481 HV",
    "addr:housenumber":"7",
    "addr:postcode":"7481 hv",
    "addr:street":"Spoorstraat",
    "iso:country":"NL",
    "sg:address":"Spoorstraat 7",
    "sg:city":"Haaksbergen",
    "sg:orig_category":"Juweliers",
    "sg:phone":"+31 53 572 1488",
    "sg:postcode":"7481 HV",
    "sg:province":"Overijssel",
    "wof:name":"Horlogerie Aalbers",
    "wof:placetype":"venue"
},
  "geometry": {"coordinates":[6.741063,52.155369],"type":"Point"}
}