{
  "type": "Feature",
  "properties": {
    "addr:full":"Wilhelminastr 1 Meteren Gelderland 4194 TT",
    "addr:housenumber":"1",
    "addr:postcode":"4194 tt",
    "addr:street":"Wilhelminastr;Gelderland",
    "iso:country":"NL",
    "sg:address":"Wilhelminastr 1",
    "sg:city":"Meteren",
    "sg:orig_category":"Wasmachines En Wasdrogers",
    "sg:phone":"+31 345 642 691",
    "sg:postcode":"4194 TT",
    "sg:province":"Gelderland",
    "wof:name":"Veron",
    "wof:placetype":"venue"
},
  "geometry": {"coordinates":[5.2862057686,51.8643112183],"type":"Point"}
}