{
  "type": "Feature",
  "properties": {
    "addr:full":"Bergwg 65 Zeist Utrecht 3707 AB",
    "addr:housenumber":"65",
    "addr:postcode":"3707 ab",
    "addr:street":"Bergwg",
    "iso:country":"NL",
    "sg:address":"Bergwg 65",
    "sg:city":"Zeist",
    "sg:orig_category":"Psychotherapeuten",
    "sg:phone":"+31 30 692 4035",
    "sg:postcode":"3707 AB",
    "sg:province":"Utrecht",
    "wof:name":"Harten-Wissink, Drs K J Van",
    "wof:placetype":"venue"
},
  "geometry": {"coordinates":[5.24387,52.08548],"type":"Point"}
}