{
  "type": "Feature",
  "properties": {
    "iso:country":"NL",
    "sg:address":"Innsbruckwg 35",
    "sg:city":"Rotterdam",
    "sg:orig_category":"Petrochemische Industrie - Installaties En Onderhoud",
    "sg:phone":"+31 10 462 4811",
    "sg:postcode":"3047 AG",
    "sg:province":"Zuid-Holland",
    "sg:website":"http://www.analytical-controls.com",
    "wof:name":"Analytical Controls Bv",
    "wof:placetype":"venue"
},
  "geometry": {"coordinates":[4.412794,51.945374],"type":"Point"}
}