{
  "type": "Feature",
  "properties": {
    "addr:full":"Koematen 5 Steenwijk Overijssel 8331 TK",
    "addr:housenumber":"5",
    "addr:postcode":"8331 tk",
    "addr:street":"Koematen",
    "iso:country":"NL",
    "sg:address":"Koematen 5",
    "sg:city":"Steenwijk",
    "sg:orig_category":"Diverse Grafische Activiteiten",
    "sg:phone":"+31 521 517 689",
    "sg:postcode":"8331 TK",
    "sg:province":"Overijssel",
    "wof:name":"B'Ulah Print",
    "wof:placetype":"venue"
},
  "geometry": {"coordinates":[6.097871,52.777847],"type":"Point"}
}