{
  "type": "Feature",
  "properties": {
    "addr:full":"De Hove 3 Mook North Brabant 6585 AN",
    "addr:housenumber":"3",
    "addr:postcode":"6585 an",
    "addr:street":"De Hove",
    "iso:country":"NL",
    "sg:address":"De Hove 3",
    "sg:city":"Mook",
    "sg:orig_category":"Goudsmeden En Zilversmeden",
    "sg:phone":"+31 24 696 1461",
    "sg:postcode":"6585 AN",
    "sg:province":"North Brabant",
    "wof:name":"Roeper, Atelier Marc De",
    "wof:placetype":"venue"
},
  "geometry": {"coordinates":[5.880091,51.751331],"type":"Point"}
}