{
  "type": "Feature",
  "properties": {
    "addr:full":"Denekamperwg 44 Geesteren Ov NL.08 7678 SZ",
    "addr:housenumber":"44",
    "addr:postcode":"7678 sz",
    "addr:street":"Denekamperwg;Ov",
    "iso:country":"NL",
    "sg:address":"Denekamperwg 44",
    "sg:city":"Geesteren Ov",
    "sg:orig_category":"Accountants - Administratie- Consulenten En -Kantoren",
    "sg:phone":"+31 546 633 566",
    "sg:postcode":"7678 SZ",
    "sg:province":"NL.08",
    "wof:name":"Texdesk",
    "wof:placetype":"venue"
},
  "geometry": {"coordinates":[6.757265,52.425327],"type":"Point"}
}