{
  "type": "Feature",
  "properties": {
    "addr:full":"Diepmeerven 74 Eindhoven Noord-Brabant 5646 HB",
    "addr:housenumber":"74",
    "addr:postcode":"5646 hb",
    "addr:street":"Diepmeerven",
    "iso:country":"NL",
    "sg:address":"Diepmeerven 74",
    "sg:city":"Eindhoven",
    "sg:orig_category":"Babyartikelen",
    "sg:phone":"+31 40 212 7074",
    "sg:postcode":"5646 HB",
    "sg:province":"Noord-Brabant",
    "sg:website":"http://www.prulleke.nl",
    "wof:name":"Prulleke Babykado'S, 'T",
    "wof:placetype":"venue"
},
  "geometry": {"coordinates":[5.514616,51.421593],"type":"Point"}
}