{
  "type": "Feature",
  "properties": {
    "addr:full":"Egelantierstr 84 Utrecht Utrecht 3551 GE",
    "addr:housenumber":"84",
    "addr:postcode":"3551",
    "addr:street":"Egelantierstr",
    "iso:country":"NL",
    "sg:address":"Egelantierstr 84",
    "sg:city":"Utrecht",
    "sg:orig_category":"Fotografie Reclame En Mode",
    "sg:phone":"+31 6 28977643",
    "sg:postcode":"3551 GE",
    "sg:province":"Utrecht",
    "sg:website":"http://www.seventhheaven.com",
    "wof:name":"7Th Heaven",
    "wof:placetype":"venue"
},
  "geometry": {"coordinates":[5.093859,52.102177],"type":"Point"}
}