{
  "type": "Feature",
  "properties": {
    "addr:full":"Boulev De Wieling 53-02 Cadzand Zeeland 4506 JL",
    "addr:housenumber":"53-02",
    "addr:postcode":"4506 jl",
    "addr:street":"Boulev De Wieling",
    "iso:country":"NL",
    "sg:address":"Boulev De Wieling 53-02",
    "sg:city":"Cadzand",
    "sg:orig_category":"Vakantieverblijven",
    "sg:phone":"+31 117 391 872",
    "sg:postcode":"4506 JL",
    "sg:province":"Zeeland",
    "sg:website":"http://www.wodcadzand.com",
    "wof:name":"Wod",
    "wof:placetype":"venue"
},
  "geometry": {"coordinates":[3.391363,51.37888],"type":"Point"}
}