{
  "type": "Feature",
  "properties": {
    "iso:country":"NL",
    "sg:address":"Merseloseweg 76A",
    "sg:city":"Venray",
    "sg:orig_category":"Kappers",
    "sg:phone":"+31 478 510 700",
    "sg:postcode":"5801 CE",
    "sg:province":"Limburg",
    "wof:name":"Essenziale",
    "wof:placetype":"venue"
},
  "geometry": {"coordinates":[5.9714121819,51.5257797241],"type":"Point"}
}