{
  "type": "Feature",
  "properties": {
    "addr:full":"De Weer 10 Zaandam Noord-Holland 1504 AG",
    "addr:housenumber":"10",
    "addr:postcode":"1504",
    "addr:street":"De Weer",
    "iso:country":"NL",
    "sg:address":"De Weer 10",
    "sg:city":"Zaandam",
    "sg:orig_category":"Boekhouders",
    "sg:phone":"+31 75 616 8630",
    "sg:postcode":"1504 AG",
    "sg:province":"Noord-Holland",
    "wof:name":"Stichting Dienstverlening Bijzonder Onde",
    "wof:placetype":"venue"
},
  "geometry": {"coordinates":[4.847079,52.434349],"type":"Point"}
}