{
  "type": "Feature",
  "properties": {
    "addr:full":"Tempelstr 11 Overasselt Gelderland 6611 AW",
    "addr:housenumber":"11",
    "addr:postcode":"6611 aw",
    "addr:street":"Tempelstr;Gelderland",
    "iso:country":"NL",
    "sg:address":"Tempelstr 11",
    "sg:city":"Overasselt",
    "sg:orig_category":"Betonwerken",
    "sg:phone":"+31 24 622 2111",
    "sg:postcode":"6611 AW",
    "sg:province":"Gelderland",
    "wof:name":"Glaser Bv",
    "wof:placetype":"venue"
},
  "geometry": {"coordinates":[5.793033,51.757065],"type":"Point"}
}