{
  "type": "Feature",
  "properties": {
    "addr:full":"Apollovlinder 2 Bilthoven Utrecht 3723 RK",
    "addr:housenumber":"2",
    "addr:postcode":"3723 rk",
    "addr:street":"Apollovlinder",
    "iso:country":"NL",
    "sg:address":"Apollovlinder 2",
    "sg:city":"Bilthoven",
    "sg:orig_category":"Administratie- En Boekhoudkantoren",
    "sg:phone":"+31 30 228 6282",
    "sg:postcode":"3723 RK",
    "sg:province":"Utrecht",
    "wof:name":"Horst, P Van Der",
    "wof:placetype":"venue"
},
  "geometry": {"coordinates":[5.190897,52.131439],"type":"Point"}
}