{
  "type": "Feature",
  "properties": {
    "iso:country":"NL",
    "sg:address":"Hendrik Ravesteijnplein 85",
    "sg:city":"Rijswijk Zh",
    "sg:orig_category":"Banken And Kredietinstellingen",
    "sg:phone":"+31 70 399 0199",
    "sg:postcode":"2282 GX",
    "sg:province":"Zuid-Holland",
    "wof:name":"Abn Amro",
    "wof:placetype":"venue"
},
  "geometry": {"coordinates":[4.332724,52.048759],"type":"Point"}
}