{
  "type": "Feature",
  "properties": {
    "addr:full":"Braamkamp 429 Zutphen Gelderland 7206 HW",
    "addr:housenumber":"429",
    "addr:postcode":"7206 hw",
    "addr:street":"Braamkamp;Gelderland",
    "iso:country":"NL",
    "sg:address":"Braamkamp 429",
    "sg:city":"Zutphen",
    "sg:orig_category":"Boeken Antiquarische En Gebruikte",
    "sg:phone":"+31 575 573 281",
    "sg:postcode":"7206 HW",
    "sg:province":"Gelderland",
    "wof:name":"Reis-Boek Nl",
    "wof:placetype":"venue"
},
  "geometry": {"coordinates":[6.20196,52.121498],"type":"Point"}
}