{
  "type": "Feature",
  "properties": {
    "addr:full":"Anjerstraat 9 'S Gravenzande Zuid-Holland 2691 LL",
    "addr:housenumber":"9 ';2691",
    "addr:postcode":"ll",
    "addr:street":"Anjerstraat",
    "iso:country":"NL",
    "sg:address":"Anjerstraat 9",
    "sg:city":"'S Gravenzande",
    "sg:orig_category":"Goederenvervoer Over De Weg",
    "sg:phone":"+31 174 421 481",
    "sg:postcode":"2691 LL",
    "sg:province":"Zuid-Holland",
    "wof:name":"G. V.D. Zee",
    "wof:placetype":"venue"
},
  "geometry": {"coordinates":[4.18079,51.98259],"type":"Point"}
}