{
  "type": "Feature",
  "properties": {
    "addr:full":"Turfkd 15 Goes Zeeland 4461 AP",
    "addr:housenumber":"15",
    "addr:postcode":"4461 ap",
    "addr:street":"Turfkd",
    "iso:country":"NL",
    "sg:address":"Turfkd 15",
    "sg:city":"Goes",
    "sg:orig_category":"Kantoorbenodigdheden",
    "sg:phone":"+31 113 271 234",
    "sg:postcode":"4461 AP",
    "sg:province":"Zeeland",
    "sg:website":"http://www.dwszeeland.nl",
    "wof:name":"Dwszeeland",
    "wof:placetype":"venue"
},
  "geometry": {"coordinates":[-97.3351974487,38.2471504211],"type":"Point"}
}