{
  "type": "Feature",
  "properties": {
    "addr:full":"Kon Wilhelminapln 1 Amsterdam North Holland 1062 HG",
    "addr:housenumber":"1",
    "addr:postcode":"1062 hg",
    "addr:street":"Kon Wilhelminapln",
    "iso:country":"NL",
    "sg:address":"Kon Wilhelminapln 1",
    "sg:city":"Amsterdam",
    "sg:orig_category":"Mode-Artikelen Dames En Heren",
    "sg:phone":"+31 20 669 2001",
    "sg:postcode":"1062 HG",
    "sg:province":"North Holland",
    "wof:name":"Toenga Bv",
    "wof:placetype":"venue"
},
  "geometry": {"coordinates":[4.840995,52.355759],"type":"Point"}
}