{
  "type": "Feature",
  "properties": {
    "addr:full":"Vossenkamp 219 Winschoten Groningen 9675 KG",
    "addr:housenumber":"219",
    "addr:postcode":"9675 kg",
    "addr:street":"Vossenkamp",
    "iso:country":"NL",
    "sg:address":"Vossenkamp 219",
    "sg:city":"Winschoten",
    "sg:orig_category":"Verzekeringen - Verzekeringskantoren",
    "sg:phone":"+31 597 431 152",
    "sg:postcode":"9675 KG",
    "sg:province":"Groningen",
    "wof:name":"Klein, G A",
    "wof:placetype":"venue"
},
  "geometry": {"coordinates":[7.027453,53.157284],"type":"Point"}
}