{
  "type": "Feature",
  "properties": {
    "addr:full":"Erasmusln 1 De Kruimelkuil Haarlem North Holland 2037 LA",
    "addr:housenumber":"1",
    "addr:postcode":"2037 la",
    "addr:street":"Erasmusln",
    "iso:country":"NL",
    "sg:address":"Erasmusln 1 De Kruimelkuil",
    "sg:city":"Haarlem",
    "sg:orig_category":"Peuterspeelzalen",
    "sg:phone":"+31 23 533 8663",
    "sg:postcode":"2037 LA",
    "sg:province":"North Holland",
    "wof:name":"Kruimelkuil, De",
    "wof:placetype":"venue"
},
  "geometry": {"coordinates":[4.66426,52.353531],"type":"Point"}
}