{
  "type": "Feature",
  "properties": {
    "addr:full":"Achtereindsestr 1A Waalre North Brabant 5583 TB",
    "addr:housenumber":"1a",
    "addr:postcode":"5583 tb",
    "addr:street":"Achtereindsestr",
    "iso:country":"NL",
    "sg:address":"Achtereindsestr 1A",
    "sg:city":"Waalre",
    "sg:orig_category":"Accountants - Administratie- Consulenten En -Kantoren",
    "sg:phone":"+31 40 223 3707",
    "sg:postcode":"5583 TB",
    "sg:province":"North Brabant",
    "wof:name":"Simape Vof",
    "wof:placetype":"venue"
},
  "geometry": {"coordinates":[5.487986,51.385639],"type":"Point"}
}