{
  "type": "Feature",
  "properties": {
    "addr:full":"V Ekelenburgstr 17 Nieuw Amsterdam Drenthe 7833 HZ",
    "addr:housenumber":"17",
    "addr:postcode":"7833 hz",
    "addr:street":"Nieuw",
    "iso:country":"NL",
    "sg:address":"V Ekelenburgstr 17",
    "sg:city":"Nieuw Amsterdam",
    "sg:orig_category":"Kappers",
    "sg:phone":"+31 591 553 670",
    "sg:postcode":"7833 HZ",
    "sg:province":"Drenthe",
    "wof:name":"Ria",
    "wof:placetype":"venue"
},
  "geometry": {"coordinates":[-74.202896,42.97855],"type":"Point"}
}