{
  "type": "Feature",
  "properties": {
    "addr:full":"Czaar Peterstraat 78Hs Zaandam Noord-Holland 1506 SR",
    "addr:housenumber":"78hs;1506",
    "addr:postcode":"sr",
    "addr:street":"Czaar Peterstraat",
    "iso:country":"NL",
    "sg:address":"Czaar Peterstraat 78Hs",
    "sg:city":"Zaandam",
    "sg:orig_category":"Loodgieterswerk, Verwarming And Sanitaire Installaties",
    "sg:phone":"+31 75 615 8144",
    "sg:postcode":"1506 SR",
    "sg:province":"Noord-Holland",
    "wof:name":"Th.F. Ulendorp",
    "wof:placetype":"venue"
},
  "geometry": {"coordinates":[4.819386,52.438095],"type":"Point"}
}