{
  "type": "Feature",
  "properties": {
    "addr:full":"Kogendk 24S Bergen Nh Noord-Holland 1862 XD",
    "addr:housenumber":"24s",
    "addr:postcode":"1862 xd",
    "addr:street":"Kogendk",
    "iso:country":"NL",
    "sg:address":"Kogendk 24S",
    "sg:city":"Bergen Nh",
    "sg:orig_category":"Beeldende Kunstenaars",
    "sg:phone":"+31 72 589 4144",
    "sg:postcode":"1862 XD",
    "sg:province":"Noord-Holland",
    "wof:name":"Seldenthuis, Joop",
    "wof:placetype":"venue"
},
  "geometry": {"coordinates":[4.716237,52.664165],"type":"Point"}
}