{
  "type": "Feature",
  "properties": {
    "addr:full":"Valeriusstr 163 Amsterdam Noord-Holland 1075 EV",
    "addr:housenumber":"163",
    "iso:country":"NL",
    "sg:address":"Valeriusstr 163",
    "sg:city":"Amsterdam",
    "sg:orig_category":"Adviesbureaus Economie",
    "sg:phone":"+31 20 672 0908",
    "sg:postcode":"1075 EV",
    "sg:province":"Noord-Holland",
    "sg:website":"http://www.rrjmanagement.nl",
    "wof:name":"Rrj",
    "wof:placetype":"venue"
},
  "geometry": {"coordinates":[4.8619618416,52.3521766663],"type":"Point"}
}