{
  "type": "Feature",
  "properties": {
    "addr:full":"Donaudreef 25 Utrecht Utrecht 3561 EL",
    "addr:housenumber":"25",
    "addr:postcode":"3561 el",
    "addr:street":"Donaudreef",
    "iso:country":"NL",
    "sg:address":"Donaudreef 25",
    "sg:city":"Utrecht",
    "sg:orig_category":"Begrafenisondernemers",
    "sg:phone":"+31 30 262 2244",
    "sg:postcode":"3561 EL",
    "sg:province":"Utrecht",
    "wof:name":"Christ. Coop. Uitvaartver. Pcb Ua",
    "wof:placetype":"venue"
},
  "geometry": {"coordinates":[5.127166,52.113354],"type":"Point"}
}