{
  "type": "Feature",
  "properties": {
    "addr:full":"St Benedictusstr 45 Oosterhout Nb Noord-Brabant 4902 RV",
    "addr:housenumber":"45",
    "addr:postcode":"4902 rv",
    "iso:country":"NL",
    "sg:address":"St Benedictusstr 45",
    "sg:city":"Oosterhout Nb",
    "sg:orig_category":"Adviesbureaus Bedrijfsveiligheid",
    "sg:phone":"+31 162 450 378",
    "sg:postcode":"4902 RV",
    "sg:province":"Noord-Brabant",
    "wof:name":"Heffelaar Bedrijfsveiligheid-Opleidingen",
    "wof:placetype":"venue"
},
  "geometry": {"coordinates":[4.871131,51.637936],"type":"Point"}
}