{
  "type": "Feature",
  "properties": {
    "addr:full":"Blijhamsterweg 66 Winschoten Groningen 9672 AB",
    "addr:housenumber":"66",
    "addr:postcode":"9672 ab",
    "addr:street":"Blijhamsterweg",
    "iso:country":"NL",
    "sg:address":"Blijhamsterweg 66",
    "sg:city":"Winschoten",
    "sg:orig_category":"Beautyfarms And Sauna'S",
    "sg:phone":"+31 597 431 678",
    "sg:postcode":"9672 AB",
    "sg:province":"Groningen",
    "wof:name":"Euro Care",
    "wof:placetype":"venue"
},
  "geometry": {"coordinates":[7.045039,53.132927],"type":"Point"}
}