{
  "type": "Feature",
  "properties": {
    "addr:full":"Nw Loosdrechtsedk 300 Loosdrecht Noord-Holland 1231 LJ",
    "addr:housenumber":"300",
    "addr:postcode":"1231 lj",
    "iso:country":"NL",
    "sg:address":"Nw Loosdrechtsedk 300",
    "sg:city":"Loosdrecht",
    "sg:orig_category":"Adviesbureaus Bedrijfsorganisatie",
    "sg:phone":"+31 35 582 5074",
    "sg:postcode":"1231 LJ",
    "sg:province":"Noord-Holland",
    "wof:name":"Okapi",
    "wof:placetype":"venue"
},
  "geometry": {"coordinates":[5.069087,52.207127],"type":"Point"}
}