{
  "type": "Feature",
  "properties": {
    "iso:country":"NL",
    "sg:address":"Vondelpark 3",
    "sg:city":"Amsterdam",
    "sg:orig_category":"Bibliotheken And Openbare Archieven",
    "sg:phone":"+31 20 589 1400",
    "sg:postcode":"1071 AA",
    "sg:province":"Noord-Holland",
    "wof:name":"St Nederlands Filmmuseum",
    "wof:placetype":"venue"
},
  "geometry": {"coordinates":[4.872367,52.359138],"type":"Point"}
}