{
  "type": "Feature",
  "properties": {
    "addr:full":"Grotestr 11 Baarlo Lb Limburg 5991 AV",
    "addr:housenumber":"11",
    "addr:postcode":"lb;5991 av",
    "addr:street":"Grotestr",
    "iso:country":"NL",
    "sg:address":"Grotestr 11",
    "sg:city":"Baarlo Lb",
    "sg:orig_category":"Horecabenodigdheden",
    "sg:phone":"+31 77 477 1206",
    "sg:postcode":"5991 AV",
    "sg:province":"Limburg",
    "wof:name":"Super De Boer",
    "wof:placetype":"venue"
},
  "geometry": {"coordinates":[6.095251,51.331215],"type":"Point"}
}