{
  "type": "Feature",
  "properties": {
    "iso:country":"NL",
    "sg:address":"Grotestr 11",
    "sg:city":"Baarlo Lb",
    "sg:orig_category":"Horecabenodigdheden",
    "sg:phone":"+31 77 477 1206",
    "sg:postcode":"5991 AV",
    "sg:province":"Limburg",
    "wof:name":"Super De Boer",
    "wof:placetype":"venue"
},
  "geometry": {"coordinates":[6.095251,51.331215],"type":"Point"}
}