{
  "type": "Feature",
  "properties": {
    "addr:full":"Hoogstr 62-64 Wageningen Gelderland 6701 BX",
    "addr:housenumber":"62-64",
    "addr:postcode":"6701 bx",
    "addr:street":"Gelderland",
    "iso:country":"NL",
    "sg:address":"Hoogstr 62-64",
    "sg:city":"Wageningen",
    "sg:orig_category":"Schoenen",
    "sg:phone":"+31 317 418 600",
    "sg:postcode":"6701 BX",
    "sg:province":"Gelderland",
    "wof:name":"Schoenenreus",
    "wof:placetype":"venue"
},
  "geometry": {"coordinates":[5.6641068459,51.9666938782],"type":"Point"}
}