{
  "type": "Feature",
  "properties": {
    "iso:country":"NL",
    "sg:address":"Hoogstraat 21",
    "sg:city":"Werkendam",
    "sg:orig_category":"Wasserettes And Stomerijen",
    "sg:phone":"+31 183 501 559",
    "sg:postcode":"4251 CH",
    "sg:province":"North Brabant",
    "wof:name":"Stomerij Van Der Krogt",
    "wof:placetype":"venue"
},
  "geometry": {"coordinates":[4.8953170776,51.8083724976],"type":"Point"}
}