{
  "type": "Feature",
  "properties": {
    "addr:full":"Middelwg 10 Starnmeer Noord-Holland 1488 AL",
    "addr:housenumber":"10",
    "addr:postcode":"1488 al",
    "addr:street":"Middelwg",
    "iso:country":"NL",
    "sg:address":"Middelwg 10",
    "sg:city":"Starnmeer",
    "sg:orig_category":"Bloemen En Planten - Groothandel",
    "sg:phone":"+31 75 641 1494",
    "sg:postcode":"1488 AL",
    "sg:province":"Noord-Holland",
    "wof:name":"Ruyter, G J De",
    "wof:placetype":"venue"
},
  "geometry": {"coordinates":[4.790394,52.542019],"type":"Point"}
}