{
  "type": "Feature",
  "properties": {
    "addr:full":"Bredeln 9A Bussum Noord-Holland 1406 LN",
    "addr:housenumber":"9a",
    "addr:postcode":"1406 ln",
    "addr:street":"Bredeln",
    "iso:country":"NL",
    "sg:address":"Bredeln 9A",
    "sg:city":"Bussum",
    "sg:orig_category":"Levensmiddelen - Fabrieken En Groothandel",
    "sg:phone":"+31 35 691 0073",
    "sg:postcode":"1406 LN",
    "sg:province":"Noord-Holland",
    "wof:name":"Sanfoods Bv",
    "wof:placetype":"venue"
},
  "geometry": {"coordinates":[5.162605,52.276829],"type":"Point"}
}