{
  "type": "Feature",
  "properties": {
    "addr:full":"Dr Nolensln 15715 Sittard Limburg 6136 GM",
    "addr:postcode":"15715;6136 gm",
    "iso:country":"NL",
    "sg:address":"Dr Nolensln 15715",
    "sg:city":"Sittard",
    "sg:orig_category":"Kunststoffen- Verwerkende Industrie",
    "sg:phone":"+31 46 423 1454",
    "sg:postcode":"6136 GM",
    "sg:province":"Limburg",
    "wof:name":"Fermex Bv",
    "wof:placetype":"venue"
},
  "geometry": {"coordinates":[5.858792,51.018143],"type":"Point"}
}