{
  "type": "Feature",
  "properties": {
    "addr:full":"Cirkelpad 12 Baarle Nassau North Brabant 5111 BV",
    "addr:housenumber":"12",
    "addr:postcode":"5111 bv",
    "addr:street":"Cirkelpad",
    "iso:country":"NL",
    "sg:address":"Cirkelpad 12",
    "sg:city":"Baarle Nassau",
    "sg:orig_category":"Goederenvervoer Over De Weg",
    "sg:phone":"+31 13 507 8732",
    "sg:postcode":"5111 BV",
    "sg:province":"North Brabant",
    "wof:name":"Kees Jacobs Transport",
    "wof:placetype":"venue"
},
  "geometry": {"coordinates":[4.925075,51.449955],"type":"Point"}
}