{
  "type": "Feature",
  "properties": {
    "iso:country":"NL",
    "sg:address":"Diepertsewg 23",
    "sg:city":"Gemert",
    "sg:orig_category":"Pluimveebedrijven En -Handelaren",
    "sg:phone":"+31 492 319 227",
    "sg:postcode":"5421 XJ",
    "sg:province":"Noord-Brabant",
    "wof:name":"Vossenberg, J Van De",
    "wof:placetype":"venue"
},
  "geometry": {"coordinates":[5.745467,51.569775],"type":"Point"}
}