{
  "type": "Feature",
  "properties": {
    "addr:full":"Pres Kennedyln 579 Amsterdam Noord-Holland 1079 ML",
    "addr:housenumber":"579",
    "addr:postcode":"1079 ml",
    "iso:country":"NL",
    "sg:address":"Pres Kennedyln 579",
    "sg:city":"Amsterdam",
    "sg:orig_category":"Verenigingen En Stichtingen",
    "sg:phone":"+31 20 642 2221",
    "sg:postcode":"1079 ML",
    "sg:province":"Noord-Holland",
    "wof:name":"Sinatra Holland Int",
    "wof:placetype":"venue"
},
  "geometry": {"coordinates":[4.89319,52.373119],"type":"Point"}
}