{
  "type": "Feature",
  "properties": {
    "addr:full":"Zandwg 30-B Maarssen Utrecht 3601 AE",
    "addr:housenumber":"30-b",
    "addr:postcode":"3601 ae",
    "addr:street":"Zandwg",
    "iso:country":"NL",
    "sg:address":"Zandwg 30-B",
    "sg:city":"Maarssen",
    "sg:orig_category":"Fotoreportages",
    "sg:phone":"+31 346 561 791",
    "sg:postcode":"3601 AE",
    "sg:province":"Utrecht",
    "wof:name":"Dijk Fotografie, J J Van",
    "wof:placetype":"venue"
},
  "geometry": {"coordinates":[5.045108,52.138752],"type":"Point"}
}