{
  "type": "Feature",
  "properties": {
    "addr:full":"Achter De Vismarkt 10 Culemborg Gelderland 4101 AD",
    "addr:housenumber":"10",
    "addr:postcode":"4101 ad",
    "addr:street":"Achter De Vismarkt;Gelderland",
    "iso:country":"NL",
    "sg:address":"Achter De Vismarkt 10",
    "sg:city":"Culemborg",
    "sg:orig_category":"Elektronische Bedrijfsinstallaties",
    "sg:phone":"+31 345 519 173",
    "sg:postcode":"4101 AD",
    "sg:province":"Gelderland",
    "wof:name":"Wolters Beveiligingstechniek Bv",
    "wof:placetype":"venue"
},
  "geometry": {"coordinates":[5.222785,51.960293],"type":"Point"}
}