{
  "type": "Feature",
  "properties": {
    "iso:country":"NL",
    "sg:address":"Madame Curiestr 24",
    "sg:city":"Dordrecht",
    "sg:orig_category":"Verlichtingsartikelen - Groothandel",
    "sg:phone":"+31 78 654 3111",
    "sg:postcode":"3316 GN",
    "sg:province":"Zuid-Holland",
    "sg:website":"http://www.multicarenet.com",
    "wof:name":"Multicare Lighting Cv",
    "wof:placetype":"venue"
},
  "geometry": {"coordinates":[4.639708,51.777908],"type":"Point"}
}