{
  "type": "Feature",
  "properties": {
    "addr:full":"Dillenburgstraat 28 Eindhoven North Brabant 5652 AP",
    "addr:housenumber":"28",
    "addr:postcode":"5652 ap",
    "addr:street":"Dillenburgstraat",
    "iso:country":"NL",
    "sg:address":"Dillenburgstraat 28",
    "sg:city":"Eindhoven",
    "sg:orig_category":"Goederenvervoer Over De Weg",
    "sg:phone":"+31 40 251 3672",
    "sg:postcode":"5652 AP",
    "sg:province":"North Brabant",
    "wof:name":"Dtc Distri Transport Center Eindhoven",
    "wof:placetype":"venue"
},
  "geometry": {"coordinates":[5.434112,51.425526],"type":"Point"}
}