{
  "type": "Feature",
  "properties": {
    "addr:full":"Van Blommesteynweg 41 Rotterdam Zuid-Holland 3082 WD",
    "addr:housenumber":"41",
    "addr:postcode":"3082 wd",
    "addr:street":"Van Blommesteynweg",
    "iso:country":"NL",
    "sg:address":"Van Blommesteynweg 41",
    "sg:city":"Rotterdam",
    "sg:orig_category":"Schilderwerk",
    "sg:phone":"+31 10 429 1405",
    "sg:postcode":"3082 WD",
    "sg:province":"Zuid-Holland",
    "wof:name":"H J Rokus",
    "wof:placetype":"venue"
},
  "geometry": {"coordinates":[4.463371,51.887878],"type":"Point"}
}