{
  "type": "Feature",
  "properties": {
    "addr:full":"Bareveldkd 4 Wildervank Groningen 9648 GW",
    "addr:housenumber":"4",
    "addr:postcode":"9648 gw",
    "addr:street":"Bareveldkd",
    "iso:country":"NL",
    "sg:address":"Bareveldkd 4",
    "sg:city":"Wildervank",
    "sg:orig_category":"Meubelen",
    "sg:phone":"+31 598 623 826",
    "sg:postcode":"9648 GW",
    "sg:province":"Groningen",
    "wof:name":"Meubelhoeve",
    "wof:placetype":"venue"
},
  "geometry": {"coordinates":[6.849266,53.056839],"type":"Point"}
}