{
  "type": "Feature",
  "properties": {
    "iso:country":"NL",
    "sg:address":"Prinsenplein 44",
    "sg:city":"Meppel",
    "sg:classifiers":[
        {
            "category":"Fast Food",
            "type":"Food & Drink"
        }
    ],
    "sg:phone":"+31 522 262 158",
    "sg:postcode":"7941 KW",
    "sg:province":"Drenthe",
    "sg:tags":[
        "afhaal",
        "restaurant"
    ],
    "wof:name":"Pyramiden",
    "wof:placetype":"venue"
},
  "geometry": {"coordinates":[6.193245,52.696575],"type":"Point"}
}