{
  "type": "Feature",
  "properties": {
    "iso:country":"NL",
    "sg:address":"Nyverheidsstr 5",
    "sg:city":"Bladel",
    "sg:orig_category":"Woninginrichting- Fournituren - Fabrieken En Groothandel",
    "sg:phone":"+31 497 388 254",
    "sg:postcode":"5531 AA",
    "sg:province":"Noord-Brabant",
    "wof:name":"Inprotec Int Bv",
    "wof:placetype":"venue"
},
  "geometry": {"coordinates":[5.1997480392,51.3593292236],"type":"Point"}
}