{
  "type": "Feature",
  "properties": {
    "addr:full":"Ferdinand Bolstraat 147 Amsterdam Noord-Holland 1072 LH",
    "addr:housenumber":"147",
    "addr:postcode":"1072 lh",
    "addr:street":"Ferdinand Bolstraat",
    "iso:country":"NL",
    "sg:address":"Ferdinand Bolstraat 147",
    "sg:city":"Amsterdam",
    "sg:orig_category":"Bloemen And Planten",
    "sg:phone":"+31 20 673 4144",
    "sg:postcode":"1072 LH",
    "sg:province":"Noord-Holland",
    "wof:name":"Shabono Bloemsierkunst",
    "wof:placetype":"venue"
},
  "geometry": {"coordinates":[4.891548,52.351566],"type":"Point"}
}