{
  "type": "Feature",
  "properties": {
    "addr:full":"Strandpaviljoen 11 Katwijk Zh South Holland 2220 NA",
    "addr:housenumber":"11",
    "addr:postcode":"zh;2220 na",
    "iso:country":"NL",
    "sg:address":"Strandpaviljoen 11",
    "sg:city":"Katwijk Zh",
    "sg:classifiers":[
        {
            "category":"Fast Food",
            "type":"Food & Drink"
        }
    ],
    "sg:phone":"+31 71 401 3049",
    "sg:postcode":"2220 NA",
    "sg:province":"South Holland",
    "sg:tags":[
        "afhaal",
        "restaurant"
    ],
    "wof:name":"Vof Het Centrum/ Het Pandbos",
    "wof:placetype":"venue"
},
  "geometry": {"coordinates":[4.39656,52.205101],"type":"Point"}
}