{
  "type": "Feature",
  "properties": {
    "addr:full":"De Breekstr 52 Amsterdam Noord-Holland 1024 LK",
    "addr:housenumber":"52",
    "addr:postcode":"1024 lk",
    "iso:country":"NL",
    "sg:address":"De Breekstr 52",
    "sg:city":"Amsterdam",
    "sg:orig_category":"Artsen - Huisartsen",
    "sg:phone":"+31 20 636 8012",
    "sg:postcode":"1024 LK",
    "sg:province":"Noord-Holland",
    "wof:name":"Visser, K R",
    "wof:placetype":"venue"
},
  "geometry": {"coordinates":[4.954508,52.390064],"type":"Point"}
}