{
  "type": "Feature",
  "properties": {
    "addr:full":"Othellodreef 139-141 Utrecht Utrecht 3561 GV",
    "addr:housenumber":"139-141",
    "addr:postcode":"3561 gv",
    "addr:street":"Othellodreef",
    "iso:country":"NL",
    "sg:address":"Othellodreef 139-141",
    "sg:city":"Utrecht",
    "sg:orig_category":"Verenigingen En Stichtingen",
    "sg:phone":"+31 30 261 2814",
    "sg:postcode":"3561 GV",
    "sg:province":"Utrecht",
    "wof:name":"Mens En Samenleving",
    "wof:placetype":"venue"
},
  "geometry": {"coordinates":[5.122389,52.112015],"type":"Point"}
}