{
  "type": "Feature",
  "properties": {
    "addr:full":"Terneuzenstr 77 Arnhem Gelderland 6845 CS",
    "addr:housenumber":"77",
    "addr:postcode":"6845 cs",
    "addr:street":"Terneuzenstr",
    "iso:country":"NL",
    "sg:address":"Terneuzenstr 77",
    "sg:city":"Arnhem",
    "sg:orig_category":"Afslankinstituten",
    "sg:phone":"+31 26 381 5365",
    "sg:postcode":"6845 CS",
    "sg:province":"Gelderland",
    "wof:name":"Brons, H",
    "wof:placetype":"venue"
},
  "geometry": {"coordinates":[5.865965,51.948963],"type":"Point"}
}