{
  "type": "Feature",
  "properties": {
    "addr:full":"J Ligthartstr 41 Haarlem Noord-Holland 2037 ET",
    "addr:housenumber":"41",
    "addr:postcode":"2037 et",
    "iso:country":"NL",
    "sg:address":"J Ligthartstr 41",
    "sg:city":"Haarlem",
    "sg:orig_category":"Verenigingen En Stichtingen",
    "sg:phone":"+31 23 533 4689",
    "sg:postcode":"2037 ET",
    "sg:province":"Noord-Holland",
    "wof:name":"Werkgroep Ouders Van Homosexuele Kinderen",
    "wof:placetype":"venue"
},
  "geometry": {"coordinates":[4.661204,52.357548],"type":"Point"}
}