{
  "type": "Feature",
  "properties": {
    "addr:full":"Johanninkswg 3 Denekamp Overijssel 7591 NV",
    "addr:housenumber":"3",
    "addr:postcode":"7591 nv",
    "addr:street":"Johanninkswg",
    "iso:country":"NL",
    "sg:address":"Johanninkswg 3",
    "sg:city":"Denekamp",
    "sg:orig_category":"Verhuur",
    "sg:phone":"+31 541 352 257",
    "sg:postcode":"7591 NV",
    "sg:province":"Overijssel",
    "wof:name":"Geers, B F",
    "wof:placetype":"venue"
},
  "geometry": {"coordinates":[7.02644,52.396057],"type":"Point"}
}