{
  "type": "Feature",
  "properties": {
    "iso:country":"NL",
    "sg:address":"Vossestaart 12",
    "sg:city":"Huizen",
    "sg:orig_category":"Marktonderzoekbureaus",
    "sg:phone":"+31 35 526 1483",
    "sg:postcode":"1273 TR",
    "sg:province":"Noord-Holland",
    "wof:name":"Dfr",
    "wof:placetype":"venue"
},
  "geometry": {"coordinates":[5.25353,52.305416],"type":"Point"}
}