{
  "type": "Feature",
  "properties": {
    "iso:country":"NL",
    "sg:address":"V Hoornekd 6",
    "sg:city":"Utrecht",
    "sg:orig_category":"Scholen Voor Basisonderwijs",
    "sg:phone":"+31 30 244 6432",
    "sg:postcode":"3554 AW",
    "sg:province":"Utrecht",
    "wof:name":"Opvangsch Zuilen Voor Neveninstromers",
    "wof:placetype":"venue"
},
  "geometry": {"coordinates":[5.09225,52.112808],"type":"Point"}
}