{
  "type": "Feature",
  "properties": {
    "addr:full":"Baarleseweg 58C Alphen Nb Noord-Brabant 5131 BD",
    "addr:housenumber":"58c",
    "addr:postcode":"5131 bd",
    "addr:street":"Baarleseweg",
    "iso:country":"NL",
    "sg:address":"Baarleseweg 58C",
    "sg:city":"Alphen Nb",
    "sg:orig_category":"Goederenvervoer Over De Weg",
    "sg:phone":"+31 13 508 2799",
    "sg:postcode":"5131 BD",
    "sg:province":"Noord-Brabant",
    "wof:name":"Jac Kennes Int. Transport",
    "wof:placetype":"venue"
},
  "geometry": {"coordinates":[4.952886,51.475166],"type":"Point"}
}