{
  "type": "Feature",
  "properties": {
    "iso:country":"NL",
    "sg:address":"Baarleseweg 58C",
    "sg:city":"Alphen Nb",
    "sg:orig_category":"Goederenvervoer Over De Weg",
    "sg:phone":"+31 13 508 2799",
    "sg:postcode":"5131 BD",
    "sg:province":"Noord-Brabant",
    "wof:name":"Jac Kennes Int. Transport",
    "wof:placetype":"venue"
},
  "geometry": {"coordinates":[4.952886,51.475166],"type":"Point"}
}