{
  "type": "Feature",
  "properties": {
    "addr:full":"Gooierserf 126 Huizen North Holland 1276 KV",
    "addr:housenumber":"126",
    "addr:postcode":"1276 kv",
    "addr:street":"Gooierserf",
    "iso:country":"NL",
    "sg:address":"Gooierserf 126",
    "sg:city":"Huizen",
    "sg:orig_category":"Kinderopvang",
    "sg:phone":"+31 35 528 8200",
    "sg:postcode":"1276 KV",
    "sg:province":"North Holland",
    "wof:name":"Kasselemai",
    "wof:placetype":"venue"
},
  "geometry": {"coordinates":[5.246673,52.297916],"type":"Point"}
}