{
  "type": "Feature",
  "properties": {
    "iso:country":"NL",
    "sg:address":"Weijenbergstraat 28",
    "sg:city":"Hoensbroek",
    "sg:orig_category":"Begrafenisondernemers",
    "sg:phone":"+31 45 563 0202",
    "sg:postcode":"6431 AL",
    "sg:province":"Limburg",
    "wof:name":"Rk Begrafenisfonds Treebeek",
    "wof:placetype":"venue"
},
  "geometry": {"coordinates":[5.922241,50.930199],"type":"Point"}
}