{
  "type": "Feature",
  "properties": {
    "addr:full":"Weijenbergstraat 28 Hoensbroek Limburg 6431 AL",
    "addr:housenumber":"28",
    "addr:postcode":"6431 al",
    "addr:street":"Weijenbergstraat",
    "iso:country":"NL",
    "sg:address":"Weijenbergstraat 28",
    "sg:city":"Hoensbroek",
    "sg:orig_category":"Begrafenisondernemers",
    "sg:phone":"+31 45 563 0202",
    "sg:postcode":"6431 AL",
    "sg:province":"Limburg",
    "wof:name":"Rk Begrafenisfonds Treebeek",
    "wof:placetype":"venue"
},
  "geometry": {"coordinates":[5.922241,50.930199],"type":"Point"}
}