{
  "type": "Feature",
  "properties": {
    "addr:full":"Waarderwg 48 Haarlem Noord-Holland 2031 BP",
    "addr:housenumber":"48",
    "addr:postcode":"2031 bp",
    "addr:street":"Waarderwg",
    "iso:country":"NL",
    "sg:address":"Waarderwg 48",
    "sg:city":"Haarlem",
    "sg:classifiers":[
        {
            "category":"Retail",
            "subcategory":"Auto Repair",
            "type":"Services"
        }
    ],
    "sg:phone":"+31 23 515 5592",
    "sg:postcode":"2031 BP",
    "sg:province":"Noord-Holland",
    "sg:tags":[
        "garage"
    ],
    "sg:website":"http://www.technoservice.nl",
    "wof:name":"Techno Service Noord-Holland",
    "wof:placetype":"venue"
},
  "geometry": {"coordinates":[4.661497,52.395546],"type":"Point"}
}