{
  "type": "Feature",
  "properties": {
    "addr:full":"Kersbergenstr 8 Eindhoven Noord-Brabant 5654 LZ",
    "addr:housenumber":"8",
    "addr:postcode":"5654 lz",
    "addr:street":"Kersbergenstr",
    "iso:country":"NL",
    "sg:address":"Kersbergenstr 8",
    "sg:city":"Eindhoven",
    "sg:classifiers":[
        {
            "category":"Retail",
            "subcategory":"Auto Repair",
            "type":"Services"
        }
    ],
    "sg:phone":"+31 40 251 2607",
    "sg:postcode":"5654 LZ",
    "sg:province":"Noord-Brabant",
    "sg:tags":[
        "garage"
    ],
    "sg:website":"http://www.saabjc.nl",
    "wof:name":"Cuppens, Autobedrijf",
    "wof:placetype":"venue"
},
  "geometry": {"coordinates":[5.450565,51.420574],"type":"Point"}
}