{
  "type": "Feature",
  "properties": {
    "addr:full":"Vivaldiln 21 Rosmalen North Brabant 5242 HD",
    "addr:housenumber":"21",
    "addr:postcode":"5242 hd",
    "addr:street":"Vivaldiln",
    "iso:country":"NL",
    "sg:address":"Vivaldiln 21",
    "sg:city":"Rosmalen",
    "sg:orig_category":"Onroerende Goederen",
    "sg:phone":"+31 73 521 3653",
    "sg:postcode":"5242 HD",
    "sg:province":"North Brabant",
    "wof:name":"Vahebo Bv",
    "wof:placetype":"venue"
},
  "geometry": {"coordinates":[5.36381,51.708569],"type":"Point"}
}