{
  "type": "Feature",
  "properties": {
    "addr:full":"Messchaertstr 10 Amsterdam Noord-Holland 1077 WS",
    "addr:housenumber":"10",
    "addr:postcode":"1077 ws",
    "addr:street":"Messchaertstr",
    "iso:country":"NL",
    "sg:address":"Messchaertstr 10",
    "sg:city":"Amsterdam",
    "sg:orig_category":"Fotografie Reclame En Mode",
    "sg:phone":"+31 20 671 8170",
    "sg:postcode":"1077 WS",
    "sg:province":"Noord-Holland",
    "wof:name":"Klein, Eline",
    "wof:placetype":"venue"
},
  "geometry": {"coordinates":[4.884226,52.345329],"type":"Point"}
}