{
  "type": "Feature",
  "properties": {
    "addr:full":"Helenaveensewg 52 Griendtsveen Limburg 5766 PB",
    "addr:housenumber":"52",
    "addr:postcode":"5766 pb",
    "addr:street":"Helenaveensewg",
    "iso:country":"NL",
    "sg:address":"Helenaveensewg 52",
    "sg:city":"Griendtsveen",
    "sg:orig_category":"Scholen Voor Basisonderwijs",
    "sg:phone":"+31 493 529 468",
    "sg:postcode":"5766 PB",
    "sg:province":"Limburg",
    "wof:name":"Driehoek Rk, De",
    "wof:placetype":"venue"
},
  "geometry": {"coordinates":[5.880443,51.441948],"type":"Point"}
}