{
  "type": "Feature",
  "properties": {
    "addr:full":"Nieuwendamstr 2D Zaandam Noord-Holland 1507 JE",
    "addr:housenumber":"2d",
    "addr:postcode":"1507 je",
    "iso:country":"NL",
    "sg:address":"Nieuwendamstr 2D",
    "sg:city":"Zaandam",
    "sg:orig_category":"Scholen Voor Basisonderwijs",
    "sg:phone":"+31 75 614 2796",
    "sg:postcode":"1507 JE",
    "sg:province":"Noord-Holland",
    "wof:name":"Baken, Het",
    "wof:placetype":"venue"
},
  "geometry": {"coordinates":[4.80594,52.446991],"type":"Point"}
}