{
  "type": "Feature",
  "properties": {
    "addr:full":"Handelsweg 14 Lemelerveld Overijssel 8152 BN",
    "addr:housenumber":"14",
    "addr:postcode":"8152 bn",
    "addr:street":"Handelsweg",
    "iso:country":"NL",
    "sg:address":"Handelsweg 14",
    "sg:city":"Lemelerveld",
    "sg:orig_category":"Bloemen And Planten",
    "sg:phone":"+31 572 372 384",
    "sg:postcode":"8152 BN",
    "sg:province":"Overijssel",
    "wof:name":"Vof Theo Wispels Bloemenshops",
    "wof:placetype":"venue"
},
  "geometry": {"coordinates":[6.333824,52.440231],"type":"Point"}
}