{
  "type": "Feature",
  "properties": {
    "addr:full":"Albert Cuypstraat 127Bg Amsterdam North Holland 1072 CS",
    "addr:housenumber":"127bg",
    "addr:postcode":"1072 cs",
    "addr:street":"Albert Cuypstraat",
    "iso:country":"NL",
    "sg:address":"Albert Cuypstraat 127Bg",
    "sg:city":"Amsterdam",
    "sg:orig_category":"Verlichting And Huishoudartikelen",
    "sg:phone":"+31 20 664 7466",
    "sg:postcode":"1072 CS",
    "sg:province":"North Holland",
    "wof:name":"De Gordijnenspecialist",
    "wof:placetype":"venue"
},
  "geometry": {"coordinates":[4.892295,52.355415],"type":"Point"}
}