{
  "type": "Feature",
  "properties": {
    "addr:full":"Wilhelminastr 37 Dalfsen Overijssel 7721 CD",
    "addr:housenumber":"37",
    "addr:postcode":"7721 cd",
    "addr:street":"Wilhelminastr",
    "iso:country":"NL",
    "sg:address":"Wilhelminastr 37",
    "sg:city":"Dalfsen",
    "sg:orig_category":"Hypotheken",
    "sg:phone":"+31 529 433 342",
    "sg:postcode":"7721 CD",
    "sg:province":"Overijssel",
    "sg:website":"http://www.dalfsen.hypotheekshop.nl/300",
    "wof:name":"Hypotheekshop, De",
    "wof:placetype":"venue"
},
  "geometry": {"coordinates":[6.260744,52.507458],"type":"Point"}
}