{
  "type": "Feature",
  "properties": {
    "iso:country":"NL",
    "sg:address":"Zeedk 136",
    "sg:city":"Amsterdam",
    "sg:orig_category":"Boeken En Tijdschriften",
    "sg:phone":"+31 20 421 3688",
    "sg:postcode":"1012 BC",
    "sg:province":"North Holland",
    "wof:name":"Comics & Manga Store, The",
    "wof:placetype":"venue"
},
  "geometry": {"coordinates":[4.900169,52.373077],"type":"Point"}
}