{
  "type": "Feature",
  "properties": {
    "iso:country":"NL",
    "sg:address":"Nachtegaalstr 42",
    "sg:city":"Utrecht",
    "sg:orig_category":"Binnenhuisarchitectuur",
    "sg:phone":"+31 30 223 1723",
    "sg:postcode":"3581 AK",
    "sg:province":"Utrecht",
    "wof:name":"Haukes 100 %",
    "wof:placetype":"venue"
},
  "geometry": {"coordinates":[5.130514,52.092258],"type":"Point"}
}