{
  "type": "Feature",
  "properties": {
    "addr:full":"Bisschoplaan 16 Katlijk Friesland 8455 JM",
    "addr:housenumber":"16",
    "addr:postcode":"8455 jm",
    "addr:street":"Bisschoplaan",
    "iso:country":"NL",
    "sg:address":"Bisschoplaan 16",
    "sg:city":"Katlijk",
    "sg:orig_category":"Meubelzaken, Woning- And Keukeninrichting",
    "sg:phone":"+31 513 541 741",
    "sg:postcode":"8455 JM",
    "sg:province":"Friesland",
    "wof:name":"Firma Keukencentrum Haanstra",
    "wof:placetype":"venue"
},
  "geometry": {"coordinates":[6.011259,52.944828],"type":"Point"}
}