{
  "type": "Feature",
  "properties": {
    "addr:full":"Herenstraat 112 Voorhout Zuid-Holland 2215 KK",
    "addr:housenumber":"112",
    "addr:postcode":"2215 kk",
    "addr:street":"Herenstraat",
    "iso:country":"NL",
    "sg:address":"Herenstraat 112",
    "sg:city":"Voorhout",
    "sg:classifiers":[
        {
            "category":"Bakery",
            "type":"Food & Drink"
        }
    ],
    "sg:phone":"+31 252 211 530",
    "sg:postcode":"2215 KK",
    "sg:province":"Zuid-Holland",
    "sg:tags":[
        "brood",
        "banket"
    ],
    "wof:name":"Echte Bakker Ammerlaan",
    "wof:placetype":"venue"
},
  "geometry": {"coordinates":[4.482399,52.221989],"type":"Point"}
}