{
  "type": "Feature",
  "properties": {
    "addr:full":"V Caldenborghln 86 Maastricht Limburg 6226 BV",
    "addr:housenumber":"86",
    "addr:postcode":"6226 bv",
    "iso:country":"NL",
    "sg:address":"V Caldenborghln 86",
    "sg:city":"Maastricht",
    "sg:orig_category":"Keukens",
    "sg:phone":"+31 43 363 8693",
    "sg:postcode":"6226 BV",
    "sg:province":"Limburg",
    "wof:name":"Siematic Maastricht",
    "wof:placetype":"venue"
},
  "geometry": {"coordinates":[5.73651,50.848919],"type":"Point"}
}