{
  "type": "Feature",
  "properties": {
    "addr:full":"Nieuwstr 98 Koewacht Zeeland 4576 AM",
    "addr:housenumber":"98",
    "addr:postcode":"4576",
    "addr:street":"Nieuwstr",
    "iso:country":"NL",
    "sg:address":"Nieuwstr 98",
    "sg:city":"Koewacht",
    "sg:orig_category":"Verenigingsgebouwen",
    "sg:phone":"+31 114 361 451",
    "sg:postcode":"4576 AM",
    "sg:province":"Zeeland",
    "wof:name":"Vlaschaard, De",
    "wof:placetype":"venue"
},
  "geometry": {"coordinates":[3.970984,51.228794],"type":"Point"}
}