{
  "type": "Feature",
  "properties": {
    "iso:country":"NL",
    "sg:address":"Gropiuslyn 32",
    "sg:city":"Zoetermeer",
    "sg:orig_category":"Verzekeringen - Verzekeringskantoren",
    "sg:phone":"+31 79 331 3104",
    "sg:postcode":"2728 AV",
    "sg:province":"Zuid-Holland",
    "wof:name":"Rooij Assuranti\u00ebn, Van",
    "wof:placetype":"venue"
},
  "geometry": {"coordinates":[4.512822,52.076229],"type":"Point"}
}