{
  "type": "Feature",
  "properties": {
    "addr:full":"Uranusstraat 52 Groningen Groningen 9742 JX",
    "addr:housenumber":"52",
    "addr:postcode":"9742 jx",
    "addr:street":"Uranusstraat",
    "iso:country":"NL",
    "sg:address":"Uranusstraat 52",
    "sg:city":"Groningen",
    "sg:orig_category":"Boekenuitgeverijen",
    "sg:phone":"+31 50 571 7502",
    "sg:postcode":"9742 JX",
    "sg:province":"Groningen",
    "wof:name":"Styx Publications",
    "wof:placetype":"venue"
},
  "geometry": {"coordinates":[6.534603,53.232613],"type":"Point"}
}