{
  "type": "Feature",
  "properties": {
    "addr:full":"Nyverheidswg 9F Nieuwegein Utrecht 3433 NP",
    "addr:housenumber":"9f",
    "addr:postcode":"3433 np",
    "iso:country":"NL",
    "sg:address":"Nyverheidswg 9F",
    "sg:city":"Nieuwegein",
    "sg:orig_category":"Elektronica - Ontwikkeling En Groothandel",
    "sg:phone":"+31 30 606 4894",
    "sg:postcode":"3433 NP",
    "sg:province":"Utrecht",
    "sg:website":"http://www.aec.nl",
    "wof:name":"Aec Co\u00f6p Ua",
    "wof:placetype":"venue"
},
  "geometry": {"coordinates":[5.101162,52.014957],"type":"Point"}
}