{
  "type": "Feature",
  "properties": {
    "addr:full":"Radboudwg 16 Rhenen Utrecht 3911 BE",
    "addr:housenumber":"16",
    "addr:postcode":"3911",
    "addr:street":"Radboudwg",
    "iso:country":"NL",
    "sg:address":"Radboudwg 16",
    "sg:city":"Rhenen",
    "sg:orig_category":"Onroerende Goederen",
    "sg:phone":"+31 317 612 878",
    "sg:postcode":"3911 BE",
    "sg:province":"Utrecht",
    "wof:name":"Roma Bv",
    "wof:placetype":"venue"
},
  "geometry": {"coordinates":[5.581265,51.96069],"type":"Point"}
}