{
  "type": "Feature",
  "properties": {
    "addr:full":"Mathenesserwg 99 Rotterdam Zuid-Holland 3027 HK",
    "addr:housenumber":"99",
    "addr:postcode":"3027 hk",
    "addr:street":"Mathenesserwg",
    "iso:country":"NL",
    "sg:address":"Mathenesserwg 99",
    "sg:city":"Rotterdam",
    "sg:orig_category":"Grafisch Ontwerpers",
    "sg:phone":"+31 6 24652182",
    "sg:postcode":"3027 HK",
    "sg:province":"Zuid-Holland",
    "wof:name":"Serious Design",
    "wof:placetype":"venue"
},
  "geometry": {"coordinates":[4.438433,51.914864],"type":"Point"}
}