{
  "type": "Feature",
  "properties": {
    "addr:full":"Noordwg 64 Krabbendyke Zeeland 4413 AD",
    "addr:housenumber":"64",
    "addr:postcode":"4413 ad",
    "addr:street":"Noordwg;Zeeland",
    "iso:country":"NL",
    "sg:address":"Noordwg 64",
    "sg:city":"Krabbendyke",
    "sg:orig_category":"Banden",
    "sg:phone":"+31 113 501 235",
    "sg:postcode":"4413 AD",
    "sg:province":"Zeeland",
    "wof:name":"Pagee",
    "wof:placetype":"venue"
},
  "geometry": {"coordinates":[4.113577,51.434299],"type":"Point"}
}