{
  "type": "Feature",
  "properties": {
    "addr:full":"Karwystr 11 Nieuw Vennep North Holland 2153 GP",
    "addr:housenumber":"11",
    "addr:postcode":"2153 gp",
    "addr:street":"Karwystr;Nieuw Vennep North",
    "iso:country":"NL",
    "sg:address":"Karwystr 11",
    "sg:city":"Nieuw Vennep",
    "sg:orig_category":"Metaalbewerking",
    "sg:phone":"+31 252 624 589",
    "sg:postcode":"2153 GP",
    "sg:province":"North Holland",
    "sg:website":"http://www.grimach.nl",
    "wof:name":"Grimach Metaal",
    "wof:placetype":"venue"
},
  "geometry": {"coordinates":[4.650281,52.264839],"type":"Point"}
}