{
  "type": "Feature",
  "properties": {
    "addr:full":"Bijlmerplein 895 Amsterdam Zuidoost North Holland 1102 MG",
    "addr:housenumber":"895",
    "addr:postcode":"1102 mg",
    "addr:street":"Bijlmerplein",
    "iso:country":"NL",
    "sg:address":"Bijlmerplein 895",
    "sg:city":"Amsterdam Zuidoost",
    "sg:orig_category":"Werving And Selectie Van Vast Personeel",
    "sg:phone":"+31 20 651 3100",
    "sg:postcode":"1102 MG",
    "sg:province":"North Holland",
    "wof:name":"Arbeidsbureau Amsterdam Zuidoost",
    "wof:placetype":"venue"
},
  "geometry": {"coordinates":[4.9546141624,52.3134346008],"type":"Point"}
}