{
  "type": "Feature",
  "properties": {
    "addr:full":"Postwg 44 De Glind Gelderland 3794 MN",
    "addr:housenumber":"44",
    "addr:postcode":"3794 mn",
    "addr:street":"Postwg",
    "iso:country":"NL",
    "sg:address":"Postwg 44",
    "sg:city":"De Glind",
    "sg:orig_category":"Waterbouwkundige Werken",
    "sg:phone":"+31 342 452 568",
    "sg:postcode":"3794 MN",
    "sg:province":"Gelderland",
    "sg:website":"http://www.antwerpen.nl",
    "wof:name":"Antwerpen, Van",
    "wof:placetype":"venue"
},
  "geometry": {"coordinates":[5.5279831886,52.1193618774],"type":"Point"}
}