{
  "type": "Feature",
  "properties": {
    "addr:full":"Lorentzstr 2 Zevenaar Gelderland 6902 PZ",
    "addr:housenumber":"2",
    "addr:postcode":"6902 pz",
    "addr:street":"Lorentzstr",
    "iso:country":"NL",
    "sg:address":"Lorentzstr 2",
    "sg:city":"Zevenaar",
    "sg:orig_category":"Plastic Producten - Fabrieken En Groothandel",
    "sg:phone":"+31 316 528 229",
    "sg:postcode":"6902 PZ",
    "sg:province":"Gelderland",
    "wof:name":"Emaka Bv",
    "wof:placetype":"venue"
},
  "geometry": {"coordinates":[6.098697,51.925209],"type":"Point"}
}