{
  "type": "Feature",
  "properties": {
    "iso:country":"NL",
    "sg:address":"Hoofdstraat 118",
    "sg:city":"Apeldoorn",
    "sg:orig_category":"Schoenen",
    "sg:phone":"+31 55 521 7977",
    "sg:postcode":"7311 KJ",
    "sg:province":"Gelderland",
    "wof:name":"Le Papillon Apeldoorn Bv",
    "wof:placetype":"venue"
},
  "geometry": {"coordinates":[5.961699,52.21516],"type":"Point"}
}