{
  "type": "Feature",
  "properties": {
    "addr:full":"Oosterdiep 7 Dordrecht Zuid-Holland 3313 TE",
    "addr:housenumber":"7",
    "addr:postcode":"3313 te",
    "addr:street":"Oosterdiep",
    "iso:country":"NL",
    "sg:address":"Oosterdiep 7",
    "sg:city":"Dordrecht",
    "sg:orig_category":"Autorijscholen",
    "sg:phone":"+31 78 621 0749",
    "sg:postcode":"3313 TE",
    "sg:province":"Zuid-Holland",
    "wof:name":"Diem, K A Van",
    "wof:placetype":"venue"
},
  "geometry": {"coordinates":[4.721826,51.812935],"type":"Point"}
}