{
  "type": "Feature",
  "properties": {
    "iso:country":"NL",
    "sg:address":"Galjoen 27-29",
    "sg:city":"Lelystad",
    "sg:orig_category":"Meubelmakerijen",
    "sg:phone":"+31 320 227 284",
    "sg:postcode":"8243 LG",
    "sg:province":"North Holland",
    "wof:name":"Es Meubelmakerij Van",
    "wof:placetype":"venue"
},
  "geometry": {"coordinates":[5.43871,52.508282],"type":"Point"}
}