{
  "type": "Feature",
  "properties": {
    "addr:full":"Industriewg 40 Deurne North Brabant 5753 PC",
    "addr:housenumber":"40",
    "addr:postcode":"5753 pc",
    "addr:street":"Industriewg",
    "iso:country":"NL",
    "sg:address":"Industriewg 40",
    "sg:city":"Deurne",
    "sg:classifiers":[
        {
            "category":"Personal",
            "subcategory":"Nail Salon",
            "type":"Services"
        }
    ],
    "sg:phone":"+31 493 312 105",
    "sg:postcode":"5753 PC",
    "sg:province":"North Brabant",
    "sg:tags":[
        "pedicure"
    ],
    "wof:name":"Bree-Kadlickov\u00f4, H M Van",
    "wof:placetype":"venue"
},
  "geometry": {"coordinates":[5.781775,51.455093],"type":"Point"}
}