{
  "type": "Feature",
  "properties": {
    "addr:full":"Tabakstraat 24 Hulst Zeeland 4561 HW",
    "addr:housenumber":"24",
    "addr:postcode":"4561 hw",
    "addr:street":"Tabakstraat",
    "iso:country":"NL",
    "sg:address":"Tabakstraat 24",
    "sg:city":"Hulst",
    "sg:classifiers":[
        {
            "category":"Education",
            "subcategory":"Preschool",
            "type":"Public Place"
        }
    ],
    "sg:phone":"+31 114 314 079",
    "sg:postcode":"4561 HW",
    "sg:province":"Zeeland",
    "sg:tags":[
        "kleuteronderwijs",
        "basis-"
    ],
    "wof:name":"Christelijke Basisschool De Ark",
    "wof:placetype":"venue"
},
  "geometry": {"coordinates":[4.050292,51.288498],"type":"Point"}
}