{
  "type": "Feature",
  "properties": {
    "addr:full":"Kerkgr 8 Sneek Friesland 8601 EC",
    "addr:housenumber":"8",
    "addr:postcode":"8601 ec",
    "addr:street":"Kerkgr",
    "iso:country":"NL",
    "sg:address":"Kerkgr 8",
    "sg:city":"Sneek",
    "sg:orig_category":"Verenigingsgebouwen",
    "sg:phone":"+31 515 418 707",
    "sg:postcode":"8601 EC",
    "sg:province":"Friesland",
    "wof:name":"Bolwerk, Het",
    "wof:placetype":"venue"
},
  "geometry": {"coordinates":[5.66197,53.033459],"type":"Point"}
}