{
  "type": "Feature",
  "properties": {
    "addr:full":"Gordelwg 194D Rotterdam Zuid-Holland 3038 GJ",
    "addr:housenumber":"194d",
    "addr:postcode":"3038 gj",
    "addr:street":"Gordelwg",
    "iso:country":"NL",
    "sg:address":"Gordelwg 194D",
    "sg:city":"Rotterdam",
    "sg:orig_category":"Onderhoudswerken",
    "sg:phone":"+31 10 467 0639",
    "sg:postcode":"3038 GJ",
    "sg:province":"Zuid-Holland",
    "wof:name":"Brouwer, Fa J B",
    "wof:placetype":"venue"
},
  "geometry": {"coordinates":[4.461359,51.936508],"type":"Point"}
}