{
  "type": "Feature",
  "properties": {
    "addr:full":"Vlaamsestr 61 Zwyndrecht Zuid-Holland 3332 EM",
    "addr:housenumber":"61",
    "addr:postcode":"3332 em",
    "addr:street":"Vlaamsestr",
    "iso:country":"NL",
    "sg:address":"Vlaamsestr 61",
    "sg:city":"Zwyndrecht",
    "sg:classifiers":[
        {
            "category":"Personal",
            "subcategory":"Nail Salon",
            "type":"Services"
        }
    ],
    "sg:phone":"+31 78 612 8106",
    "sg:postcode":"3332 EM",
    "sg:province":"Zuid-Holland",
    "sg:tags":[
        "pedicure"
    ],
    "wof:name":"Vliet, Ria Van Der",
    "wof:placetype":"venue"
},
  "geometry": {"coordinates":[4.65647,51.822247],"type":"Point"}
}