{
  "type": "Feature",
  "properties": {
    "addr:full":"Drs. F. Bijlweg 240 Den Helder North Holland 1784 MC",
    "addr:housenumber":"240",
    "addr:postcode":"1784 mc",
    "addr:street":"Drs. F. Bijlweg",
    "iso:country":"NL",
    "sg:address":"Drs. F. Bijlweg 240",
    "sg:city":"Den Helder",
    "sg:orig_category":"Kantoorartikelen",
    "sg:phone":"+31 223 668 210",
    "sg:postcode":"1784 MC",
    "sg:province":"North Holland",
    "wof:name":"Rimi Groep Bv",
    "wof:placetype":"venue"
},
  "geometry": {"coordinates":[4.7563400269,52.9364242554],"type":"Point"}
}