{
  "type": "Feature",
  "properties": {
    "addr:full":"Molenvliet 35 Zwijndrecht Zuid-Holland 3335 LH",
    "addr:housenumber":"35",
    "addr:postcode":"3335 lh",
    "addr:street":"Molenvliet",
    "iso:country":"NL",
    "sg:address":"Molenvliet 35",
    "sg:city":"Zwijndrecht",
    "sg:orig_category":"Heftrucks",
    "sg:phone":"+31 78 610 0393",
    "sg:postcode":"3335 LH",
    "sg:province":"Zuid-Holland",
    "wof:name":"Monster Zwijndrecht Bv",
    "wof:placetype":"venue"
},
  "geometry": {"coordinates":[4.566215,51.839661],"type":"Point"}
}