{
  "type": "Feature",
  "properties": {
    "iso:country":"NL",
    "sg:address":"Kaakstr 12",
    "sg:city":"Uithuizen",
    "sg:orig_category":"Adviesbureaus Bouwkunde",
    "sg:phone":"+31 595 433 445",
    "sg:postcode":"9981 BG",
    "sg:province":"Groningen",
    "wof:name":"Juk, Bouwkundig Tekenadviesbureau",
    "wof:placetype":"venue"
},
  "geometry": {"coordinates":[6.67528,53.40786],"type":"Point"}
}