{
  "type": "Feature",
  "properties": {
    "addr:full":"Wallerstr 16A Delft Zuid-Holland 2613 ZS",
    "addr:housenumber":"16a",
    "addr:postcode":"2613 zs",
    "addr:street":"Wallerstr",
    "iso:country":"NL",
    "sg:address":"Wallerstr 16A",
    "sg:city":"Delft",
    "sg:orig_category":"Administratie- En Boekhoudkantoren",
    "sg:phone":"+31 15 214 1315",
    "sg:postcode":"2613 ZS",
    "sg:province":"Zuid-Holland",
    "wof:name":"Labore Delft Bv",
    "wof:placetype":"venue"
},
  "geometry": {"coordinates":[4.344893,52.015766],"type":"Point"}
}