{
  "type": "Feature",
  "properties": {
    "addr:full":"Kempstr 126 S Gravenhage South Holland 2572 GK",
    "addr:housenumber":"126",
    "addr:postcode":"2572 gk",
    "addr:street":"S Gravenhage",
    "iso:country":"NL",
    "sg:address":"Kempstr 126",
    "sg:city":"S Gravenhage",
    "sg:orig_category":"Scholen Voor Basisonderwijs",
    "sg:phone":"+31 70 380 6700",
    "sg:postcode":"2572 GK",
    "sg:province":"South Holland",
    "sg:website":"http://www.scoh.nl",
    "wof:name":"Comenius Chr",
    "wof:placetype":"venue"
},
  "geometry": {"coordinates":[4.29421,52.06422],"type":"Point"}
}