{
  "type": "Feature",
  "properties": {
    "iso:country":"NL",
    "sg:address":"D Vd Merwedestr 22",
    "sg:city":"Hendr Ido Ambacht",
    "sg:orig_category":"Marktkramen",
    "sg:phone":"+31 78 681 2081",
    "sg:postcode":"3341 GC",
    "sg:province":"Zuid-Holland",
    "wof:name":"Wit, Ad De",
    "wof:placetype":"venue"
},
  "geometry": {"coordinates":[6.65772,46.56155],"type":"Point"}
}