{
  "type": "Feature",
  "properties": {
    "addr:full":"S. Groeneweglaan 21 Amstelveen North Holland 1183 EK",
    "addr:housenumber":"21",
    "addr:postcode":"1183 ek",
    "addr:street":"S. Groeneweglaan",
    "iso:country":"NL",
    "sg:address":"S. Groeneweglaan 21",
    "sg:city":"Amstelveen",
    "sg:orig_category":"Film-, Tv- And Videoproductie",
    "sg:phone":"+31 20 641 8898",
    "sg:postcode":"1183 EK",
    "sg:province":"North Holland",
    "wof:name":"Artsite",
    "wof:placetype":"venue"
},
  "geometry": {"coordinates":[4.879284,52.313526],"type":"Point"}
}