{
  "type": "Feature",
  "properties": {
    "addr:full":"Kerkelaan 1 Nieuwolda Groningen 9944 BJ",
    "addr:housenumber":"1",
    "addr:postcode":"9944 bj",
    "addr:street":"Kerkelaan",
    "iso:country":"NL",
    "sg:address":"Kerkelaan 1",
    "sg:city":"Nieuwolda",
    "sg:orig_category":"Vakantiehuizen",
    "sg:phone":"+31 596 541 670",
    "sg:postcode":"9944 BJ",
    "sg:province":"Groningen",
    "wof:name":"J. Van 'T Westeinde",
    "wof:placetype":"venue"
},
  "geometry": {"coordinates":[6.987855,53.244873],"type":"Point"}
}