{
  "type": "Feature",
  "properties": {
    "iso:country":"NL",
    "sg:address":"S De Bruinestr 33",
    "sg:city":"Dordrecht",
    "sg:orig_category":"Orthopedische Artikelen",
    "sg:phone":"+31 15 262 4086",
    "sg:postcode":"3317 RV",
    "sg:province":"South Holland",
    "wof:name":"Westland",
    "wof:placetype":"venue"
},
  "geometry": {"coordinates":[4.6632018089,51.7891426086],"type":"Point"}
}