{
  "type": "Feature",
  "properties": {
    "addr:full":"S De Bruinestr 33 Dordrecht South Holland 3317 RV",
    "addr:housenumber":"33",
    "addr:postcode":"3317 rv",
    "addr:street":"S",
    "iso:country":"NL",
    "sg:address":"S De Bruinestr 33",
    "sg:city":"Dordrecht",
    "sg:orig_category":"Orthopedische Artikelen",
    "sg:phone":"+31 15 262 4086",
    "sg:postcode":"3317 RV",
    "sg:province":"South Holland",
    "wof:name":"Westland",
    "wof:placetype":"venue"
},
  "geometry": {"coordinates":[4.6632018089,51.7891426086],"type":"Point"}
}