{
  "type": "Feature",
  "properties": {
    "addr:full":"Hoofdstr 178 Hillegom Zuid-Holland 2182 ER",
    "addr:housenumber":"178",
    "addr:postcode":"2182 er",
    "iso:country":"NL",
    "sg:address":"Hoofdstr 178",
    "sg:city":"Hillegom",
    "sg:orig_category":"Herenkleding",
    "sg:phone":"+31 252 515 119",
    "sg:postcode":"2182 ER",
    "sg:province":"Zuid-Holland",
    "wof:name":"Spierings",
    "wof:placetype":"venue"
},
  "geometry": {"coordinates":[4.578054,52.290215],"type":"Point"}
}