{
  "type": "Feature",
  "properties": {
    "iso:country":"NL",
    "sg:address":"Bolgerijsekade 3B",
    "sg:city":"Vianen Zh",
    "sg:orig_category":"Dierenvoeder - Fabrieken",
    "sg:phone":"+31 347 374 162",
    "sg:postcode":"4131 NT",
    "sg:province":"Utrecht",
    "wof:name":"Scherpenzeel & Zn Bv, W",
    "wof:placetype":"venue"
},
  "geometry": {"coordinates":[5.078562,51.96806],"type":"Point"}
}