{
  "type": "Feature",
  "properties": {
    "addr:full":"Berkdijk 13 Sint Michielsgestel North Brabant 5271 SR",
    "addr:housenumber":"13;michielsgestel",
    "addr:postcode":"5271 sr",
    "addr:street":"Berkdijk",
    "iso:country":"NL",
    "sg:address":"Berkdijk 13",
    "sg:city":"Sint Michielsgestel",
    "sg:orig_category":"Bouwmaterialen Gh",
    "sg:phone":"+31 73 551 3471",
    "sg:postcode":"5271 SR",
    "sg:province":"North Brabant",
    "wof:name":"Gersjes Gietijzeren Ramen Bv",
    "wof:placetype":"venue"
},
  "geometry": {"coordinates":[5.361298,51.650726],"type":"Point"}
}