{
  "type": "Feature",
  "properties": {
    "addr:full":"Maluslaan 74 Groningen Groningen 9741 LN",
    "addr:housenumber":"74",
    "addr:postcode":"9741 ln",
    "addr:street":"Maluslaan",
    "iso:country":"NL",
    "sg:address":"Maluslaan 74",
    "sg:city":"Groningen",
    "sg:orig_category":"Marktonderzoekbureaus",
    "sg:phone":"+31 50 577 9991",
    "sg:postcode":"9741 LN",
    "sg:province":"Groningen",
    "wof:name":"Enqueteburo S Witterholt",
    "wof:placetype":"venue"
},
  "geometry": {"coordinates":[6.549486,53.235985],"type":"Point"}
}