{
  "type": "Feature",
  "properties": {
    "addr:full":"Lynbaan 38 Heemskerk Noord-Holland 1969 NE",
    "addr:housenumber":"38;1969",
    "addr:postcode":"ne",
    "addr:street":"Lynbaan",
    "iso:country":"NL",
    "sg:address":"Lynbaan 38",
    "sg:city":"Heemskerk",
    "sg:orig_category":"Meubellakkerijen En -Spuiterijen",
    "sg:phone":"+31 251 251 953",
    "sg:postcode":"1969 NE",
    "sg:province":"Noord-Holland",
    "wof:name":"Rumping",
    "wof:placetype":"venue"
},
  "geometry": {"coordinates":[4.626871,52.507214],"type":"Point"}
}