{
  "type": "Feature",
  "properties": {
    "addr:full":"Maliestr 8 Utrecht Utrecht 3581 SL",
    "addr:housenumber":"8",
    "addr:postcode":"3581 sl",
    "addr:street":"Maliestr",
    "iso:country":"NL",
    "sg:address":"Maliestr 8",
    "sg:city":"Utrecht",
    "sg:orig_category":"Fotojournalisten Freelance",
    "sg:phone":"+31 30 234 0015",
    "sg:postcode":"3581 SL",
    "sg:province":"Utrecht",
    "wof:name":"Cl\u00e9 Jansen",
    "wof:placetype":"venue"
},
  "geometry": {"coordinates":[5.136485,52.094276],"type":"Point"}
}