{
  "type": "Feature",
  "properties": {
    "addr:full":"Wierdensestr 40 Almelo Overijssel 7607 GJ",
    "addr:housenumber":"40",
    "addr:postcode":"7607 gj",
    "addr:street":"Wierdensestr",
    "iso:country":"NL",
    "sg:address":"Wierdensestr 40",
    "sg:city":"Almelo",
    "sg:orig_category":"Adviesbureaus Bedrijfsorganisatie",
    "sg:phone":"+31 546 456 406",
    "sg:postcode":"7607 GJ",
    "sg:province":"Overijssel",
    "sg:website":"http://www.atlasadviesgroep.nl",
    "wof:name":"Atlas Twente Bv",
    "wof:placetype":"venue"
},
  "geometry": {"coordinates":[6.658346,52.355007],"type":"Point"}
}