{
  "type": "Feature",
  "properties": {
    "addr:full":"Neptunusplein 40 Amersfoort Utrecht 3814 BR",
    "addr:housenumber":"40",
    "addr:postcode":"3814 br",
    "addr:street":"Neptunusplein",
    "iso:country":"NL",
    "sg:address":"Neptunusplein 40",
    "sg:city":"Amersfoort",
    "sg:orig_category":"Kappers",
    "sg:phone":"+31 33 472 1286",
    "sg:postcode":"3814 BR",
    "sg:province":"Utrecht",
    "wof:name":"Haarmode Nanny",
    "wof:placetype":"venue"
},
  "geometry": {"coordinates":[5.3989958763,52.1621704102],"type":"Point"}
}