{
  "type": "Feature",
  "properties": {
    "addr:full":"Nyverheidstr 91A Dordrecht Zuid-Holland 3316 AP",
    "addr:housenumber":"91a",
    "addr:postcode":"3316 ap",
    "addr:street":"Nyverheidstr",
    "iso:country":"NL",
    "sg:address":"Nyverheidstr 91A",
    "sg:city":"Dordrecht",
    "sg:orig_category":"Autoruiten",
    "sg:phone":"+31 78 614 8511",
    "sg:postcode":"3316 AP",
    "sg:province":"Zuid-Holland",
    "wof:name":"Autotaalglas",
    "wof:placetype":"venue"
},
  "geometry": {"coordinates":[4.647753,51.800728],"type":"Point"}
}