{
  "type": "Feature",
  "properties": {
    "addr:full":"Havik 45 Amersfoort Utrecht 3811 EX",
    "addr:housenumber":"45",
    "addr:postcode":"3811 ex",
    "addr:street":"Havik",
    "iso:country":"NL",
    "sg:address":"Havik 45",
    "sg:city":"Amersfoort",
    "sg:orig_category":"Werving And Selectie Van Vast Personeel",
    "sg:phone":"+31 33 465 6633",
    "sg:postcode":"3811 EX",
    "sg:province":"Utrecht",
    "wof:name":"Rog",
    "wof:placetype":"venue"
},
  "geometry": {"coordinates":[5.3893389702,52.1572990417],"type":"Point"}
}