{
  "type": "Feature",
  "properties": {
    "addr:full":"Maastrichterweg 156 Roermond Limburg 6041 PA",
    "addr:housenumber":"156",
    "addr:postcode":"6041 pa",
    "addr:street":"Maastrichterweg",
    "iso:country":"NL",
    "sg:address":"Maastrichterweg 156",
    "sg:city":"Roermond",
    "sg:orig_category":"Meubelzaken, Woning- And Keukeninrichting",
    "sg:phone":"+31 475 316 820",
    "sg:postcode":"6041 PA",
    "sg:province":"Limburg",
    "wof:name":"Masolijn Riet En Rotan",
    "wof:placetype":"venue"
},
  "geometry": {"coordinates":[5.978709,51.177094],"type":"Point"}
}