{
  "type": "Feature",
  "properties": {
    "addr:full":"Lonneker Markewg 115 Enschede Overijssel 7532 RZ",
    "addr:housenumber":"115",
    "addr:postcode":"7532 rz",
    "addr:street":"Lonneker",
    "iso:country":"NL",
    "sg:address":"Lonneker Markewg 115",
    "sg:city":"Enschede",
    "sg:orig_category":"Bloemen En Planten",
    "sg:phone":"+31 53 430 5167",
    "sg:postcode":"7532 RZ",
    "sg:province":"Overijssel",
    "wof:name":"Deltafleur",
    "wof:placetype":"venue"
},
  "geometry": {"coordinates":[6.964734,52.242767],"type":"Point"}
}