{
  "type": "Feature",
  "properties": {
    "iso:country":"NL",
    "sg:address":"Gorsselse Enkwg 5",
    "sg:city":"Gorssel",
    "sg:orig_category":"Grafisch Ontwerpers",
    "sg:phone":"+31 575 519 144",
    "sg:postcode":"7213 LM",
    "sg:province":"Gelderland",
    "wof:name":"Sjoeke",
    "wof:placetype":"venue"
},
  "geometry": {"coordinates":[6.197305,52.190952],"type":"Point"}
}