{
  "type": "Feature",
  "properties": {
    "addr:full":"De Haal 94/A Oostzaan North Holland 1511 AT",
    "addr:housenumber":"94 / a",
    "addr:postcode":"1511",
    "addr:street":"De Haal",
    "iso:country":"NL",
    "sg:address":"De Haal 94/A",
    "sg:city":"Oostzaan",
    "sg:orig_category":"Open Haard Houtblokken",
    "sg:phone":"+31 75 684 3130",
    "sg:postcode":"1511 AT",
    "sg:province":"North Holland",
    "wof:name":"Schaap",
    "wof:placetype":"venue"
},
  "geometry": {"coordinates":[4.896806,52.472214],"type":"Point"}
}