{
  "type": "Feature",
  "properties": {
    "addr:full":"Rondeln 4 Bergen Nh Noord-Holland 1861 ED",
    "addr:housenumber":"4",
    "addr:postcode":"1861 ed",
    "addr:street":"Rondeln",
    "iso:country":"NL",
    "sg:address":"Rondeln 4",
    "sg:city":"Bergen Nh",
    "sg:orig_category":"Bedrijfsopleidingen",
    "sg:phone":"+31 72 589 6331",
    "sg:postcode":"1861 ED",
    "sg:province":"Noord-Holland",
    "wof:name":"Human Change Technology Bv",
    "wof:placetype":"venue"
},
  "geometry": {"coordinates":[4.701395,52.669979],"type":"Point"}
}