{
  "type": "Feature",
  "properties": {
    "addr:full":"Mgr Diepenstr 17 S Hertogenbosch Noord-Brabant 5212 BT",
    "addr:housenumber":"17",
    "addr:postcode":"5212 bt",
    "addr:street":"Diepenstr;S",
    "iso:country":"NL",
    "sg:address":"Mgr Diepenstr 17",
    "sg:city":"S Hertogenbosch",
    "sg:orig_category":"Psychosociale Therapeuten",
    "sg:phone":"+31 73 612 4903",
    "sg:postcode":"5212 BT",
    "sg:province":"Noord-Brabant",
    "wof:name":"Deuss, J A M",
    "wof:placetype":"venue"
},
  "geometry": {"coordinates":[5.312525,51.698063],"type":"Point"}
}