{
  "type": "Feature",
  "properties": {
    "addr:full":"Oranjerie 270 Apeldoorn Gelderland 7311 WL",
    "addr:housenumber":"270",
    "addr:postcode":"7311",
    "addr:street":"Oranjerie;Gelderland",
    "iso:country":"NL",
    "sg:address":"Oranjerie 270",
    "sg:city":"Apeldoorn",
    "sg:orig_category":"Broodjeszaken",
    "sg:phone":"+31 55 578 7124",
    "sg:postcode":"7311 WL",
    "sg:province":"Gelderland",
    "sg:website":"http://www.le-passage.nl",
    "wof:name":"Passage, Le",
    "wof:placetype":"venue"
},
  "geometry": {"coordinates":[5.96253,52.21278],"type":"Point"}
}