{
  "type": "Feature",
  "properties": {
    "iso:country":"NL",
    "sg:address":"Takkenburg 22",
    "sg:city":"Hoofddorp",
    "sg:orig_category":"Webdesign Bureaus",
    "sg:phone":"+31 23 545 2347",
    "sg:postcode":"2135 BT",
    "sg:province":"Noord-Holland",
    "sg:website":"http://www.webdynamic.nl",
    "wof:name":"Webdynamic",
    "wof:placetype":"venue"
},
  "geometry": {"coordinates":[4.6553750038,52.303691864],"type":"Point"}
}