{
  "type": "Feature",
  "properties": {
    "addr:full":"Thorbeckelaan 2 'S Gravenhage Zuid-Holland 2564 BP",
    "addr:housenumber":"2 '",
    "addr:postcode":"2564 bp",
    "addr:street":"Thorbeckelaan",
    "iso:country":"NL",
    "sg:address":"Thorbeckelaan 2",
    "sg:city":"'S Gravenhage",
    "sg:orig_category":"Makelaars In Onroerend Goed",
    "sg:phone":"+31 70 325 6460",
    "sg:postcode":"2564 BP",
    "sg:province":"Zuid-Holland",
    "wof:name":"Makko Makelaardij Bv",
    "wof:placetype":"venue"
},
  "geometry": {"coordinates":[4.259007,52.06266],"type":"Point"}
}