{
  "type": "Feature",
  "properties": {
    "addr:full":"Wachtelenbergwg 4 Epe Gelderland 8162 XC",
    "addr:housenumber":"4",
    "addr:postcode":"8162 xc",
    "addr:street":"Wachtelenbergwg;Gelderland",
    "iso:country":"NL",
    "sg:address":"Wachtelenbergwg 4",
    "sg:city":"Epe",
    "sg:orig_category":"Webdesign Bureaus",
    "sg:phone":"+31 578 612 457",
    "sg:postcode":"8162 XC",
    "sg:province":"Gelderland",
    "sg:website":"http://www.basic-design.nl",
    "wof:name":"Basic",
    "wof:placetype":"venue"
},
  "geometry": {"coordinates":[5.9822950363,52.3547477722],"type":"Point"}
}