{
  "type": "Feature",
  "properties": {
    "addr:full":"Havenwg 47 Oosterhout Nb North Brabant 4905 AA",
    "addr:housenumber":"47;nb",
    "addr:postcode":"4905 aa",
    "addr:street":"Havenwg",
    "iso:country":"NL",
    "sg:address":"Havenwg 47",
    "sg:city":"Oosterhout Nb",
    "sg:orig_category":"Betonwaren - Fabrieken",
    "sg:phone":"+31 162 456 655",
    "sg:postcode":"4905 AA",
    "sg:province":"North Brabant",
    "sg:website":"http://www.struykverwo.nl",
    "wof:name":"Struyk Bv",
    "wof:placetype":"venue"
},
  "geometry": {"coordinates":[4.849703,51.652966],"type":"Point"}
}