{
  "type": "Feature",
  "properties": {
    "iso:country":"NL",
    "sg:address":"Dorpstr 11",
    "sg:city":"Horn",
    "sg:orig_category":"Kantoor- En Secretariaatsservice",
    "sg:phone":"+31 475 587 905",
    "sg:postcode":"6085 BE",
    "sg:province":"Limburg",
    "wof:name":"Hab?",
    "wof:placetype":"venue"
},
  "geometry": {"coordinates":[8.1985988617,46.7395782471],"type":"Point"}
}