{
  "type": "Feature",
  "properties": {
    "addr:full":"Benedictynenstr 31 Arnhem Gelderland 6823 PE",
    "addr:housenumber":"31",
    "addr:postcode":"6823 pe",
    "addr:street":"Benedictynenstr",
    "iso:country":"NL",
    "sg:address":"Benedictynenstr 31",
    "sg:city":"Arnhem",
    "sg:orig_category":"Adviesbureaus Economie",
    "sg:phone":"+31 26 446 2996",
    "sg:postcode":"6823 PE",
    "sg:province":"Gelderland",
    "wof:name":"Drunen, Van",
    "wof:placetype":"venue"
},
  "geometry": {"coordinates":[5.934936,51.997383],"type":"Point"}
}