{
  "type": "Feature",
  "properties": {
    "addr:full":"Legmeerdijk 291 Amstelveen Noord-Holland 1187 NC",
    "addr:housenumber":"291",
    "addr:postcode":"1187 nc",
    "addr:street":"Legmeerdijk",
    "iso:country":"NL",
    "sg:address":"Legmeerdijk 291",
    "sg:city":"Amstelveen",
    "sg:orig_category":"Bloemen And Planten",
    "sg:phone":"+31 20 441 2868",
    "sg:postcode":"1187 NC",
    "sg:province":"Noord-Holland",
    "wof:name":"Floraan Bloemwerk",
    "wof:placetype":"venue"
},
  "geometry": {"coordinates":[4.81028,52.276749],"type":"Point"}
}