{
  "type": "Feature",
  "properties": {
    "addr:full":"Grienden 42 Leusden Utrecht 3831 HS",
    "addr:housenumber":"42",
    "addr:postcode":"3831 hs",
    "addr:street":"Grienden",
    "iso:country":"NL",
    "sg:address":"Grienden 42",
    "sg:city":"Leusden",
    "sg:orig_category":"Video - Faciliteiten En Producties",
    "sg:phone":"+31 33 495 2928",
    "sg:postcode":"3831 HS",
    "sg:province":"Utrecht",
    "wof:name":"Palma",
    "wof:placetype":"venue"
},
  "geometry": {"coordinates":[5.445426,52.133446],"type":"Point"}
}