{
  "type": "Feature",
  "properties": {
    "addr:full":"Hogewg 34 Burgh Haamstede Zeeland 4328 PE",
    "addr:housenumber":"34",
    "addr:postcode":"4328 pe",
    "addr:street":"Hogewg;Haamstede",
    "iso:country":"NL",
    "sg:address":"Hogewg 34",
    "sg:city":"Burgh Haamstede",
    "sg:orig_category":"Beeldende Kunstenaars",
    "sg:phone":"+31 111 651 100",
    "sg:postcode":"4328 PE",
    "sg:province":"Zeeland",
    "sg:website":"http://www.orelio-art.com",
    "wof:name":"Orelio, Dani?lle",
    "wof:placetype":"venue"
},
  "geometry": {"coordinates":[3.7264,51.687042],"type":"Point"}
}