{
  "type": "Feature",
  "properties": {
    "addr:full":"Oude Ebbingestraat 60 Groningen Groningen 9712 HL",
    "addr:housenumber":"60",
    "addr:postcode":"9712 hl",
    "addr:street":"Oude Ebbingestraat",
    "iso:country":"NL",
    "sg:address":"Oude Ebbingestraat 60",
    "sg:city":"Groningen",
    "sg:orig_category":"Huishoudapparatuur, Televisies And Radio'S",
    "sg:phone":"+31 50 318 7384",
    "sg:postcode":"9712 HL",
    "sg:province":"Groningen",
    "wof:name":"Okaphone Radio",
    "wof:placetype":"venue"
},
  "geometry": {"coordinates":[6.565688,53.221008],"type":"Point"}
}