{
  "type": "Feature",
  "properties": {
    "addr:full":"Dennenln 116 Zwanenburg Noord-Holland 1161 CT",
    "addr:housenumber":"116",
    "addr:postcode":"1161 ct",
    "addr:street":"Zwanenburg",
    "iso:country":"NL",
    "sg:address":"Dennenln 116",
    "sg:city":"Zwanenburg",
    "sg:orig_category":"Accountants - Administratie- Consulenten En -Kantoren",
    "sg:phone":"+31 20 497 3862",
    "sg:postcode":"1161 CT",
    "sg:province":"Noord-Holland",
    "wof:name":"Boerdijk Accountancy",
    "wof:placetype":"venue"
},
  "geometry": {"coordinates":[4.747632,52.376705],"type":"Point"}
}