{
  "type": "Feature",
  "properties": {
    "addr:full":"Virulyln 17 Leidschendam Zuid-Holland 2267 BR",
    "addr:housenumber":"17",
    "addr:postcode":"2267 br",
    "addr:street":"Virulyln",
    "iso:country":"NL",
    "sg:address":"Virulyln 17",
    "sg:city":"Leidschendam",
    "sg:orig_category":"Verzekeringen - Verzekeringskantoren",
    "sg:phone":"+31 70 390 9575",
    "sg:postcode":"2267 BR",
    "sg:province":"Zuid-Holland",
    "wof:name":"Brombacher",
    "wof:placetype":"venue"
},
  "geometry": {"coordinates":[4.40032,52.07888],"type":"Point"}
}