{
  "type": "Feature",
  "properties": {
    "addr:full":"Elfwekenln 11 Zwartewaal Zuid-Holland 3238 BD",
    "addr:housenumber":"11",
    "addr:postcode":"3238 bd",
    "addr:street":"Elfwekenln",
    "iso:country":"NL",
    "sg:address":"Elfwekenln 11",
    "sg:city":"Zwartewaal",
    "sg:orig_category":"Jachthavens - Jachtwerven",
    "sg:phone":"+31 181 661 554",
    "sg:postcode":"3238 BD",
    "sg:province":"Zuid-Holland",
    "wof:name":"Witte Raaf, De",
    "wof:placetype":"venue"
},
  "geometry": {"coordinates":[4.225855,51.884056],"type":"Point"}
}