{
  "type": "Feature",
  "properties": {
    "addr:full":"Kneuterdk 2A S Gravenhage Zuid-Holland 2514 EN",
    "addr:housenumber":"2a;gravenhage",
    "addr:postcode":"2514 en",
    "addr:street":"Kneuterdk;S",
    "iso:country":"NL",
    "sg:address":"Kneuterdk 2A",
    "sg:city":"S Gravenhage",
    "sg:orig_category":"Herenkleding",
    "sg:phone":"+31 70 346 0780",
    "sg:postcode":"2514 EN",
    "sg:province":"Zuid-Holland",
    "wof:name":"Fonderie Herenmode",
    "wof:placetype":"venue"
},
  "geometry": {"coordinates":[4.30935,52.084148],"type":"Point"}
}