{
  "type": "Feature",
  "properties": {
    "iso:country":"NL",
    "sg:address":"Kerkwg 58",
    "sg:city":"Ridderkerk",
    "sg:orig_category":"Bloemen En Planten",
    "sg:phone":"+31 180 424 336",
    "sg:postcode":"2985 AV",
    "sg:province":"Zuid-Holland",
    "wof:name":"Waal & Zn, J Van Der",
    "wof:placetype":"venue"
},
  "geometry": {"coordinates":[4.599816,51.866665],"type":"Point"}
}