{
  "type": "Feature",
  "properties": {
    "addr:full":"Burg Kuntzeln 14 Wijkgeb Barneveld Gelderland 3771 EP",
    "addr:housenumber":"14",
    "addr:postcode":"3771 ep",
    "addr:street":"Burg;Wijkgeb;Gelderland",
    "iso:country":"NL",
    "sg:address":"Burg Kuntzeln 14 Wijkgeb",
    "sg:city":"Barneveld",
    "sg:orig_category":"Verenigingen En Stichtingen",
    "sg:phone":"+31 342 413 908",
    "sg:postcode":"3771 EP",
    "sg:province":"Gelderland",
    "wof:name":"Rode Kruis",
    "wof:placetype":"venue"
},
  "geometry": {"coordinates":[5.588843,52.141216],"type":"Point"}
}