{
  "type": "Feature",
  "properties": {
    "addr:full":"Maaswykwg 3 Spykenisse Zuid-Holland 3203 LG",
    "addr:housenumber":"3",
    "addr:postcode":"3203 lg",
    "addr:street":"Maaswykwg",
    "iso:country":"NL",
    "sg:address":"Maaswykwg 3",
    "sg:city":"Spykenisse",
    "sg:orig_category":"Benzine En Olie - Groothandel",
    "sg:phone":"+31 181 692 111",
    "sg:postcode":"3203 LG",
    "sg:province":"Zuid-Holland",
    "sg:website":"http://www.dcberkel.nl",
    "wof:name":"Berkel Bv, D C",
    "wof:placetype":"venue"
},
  "geometry": {"coordinates":[4.34116,51.840771],"type":"Point"}
}