{
  "type": "Feature",
  "properties": {
    "addr:full":"Cruquiusdijk 79 Cruquius Noord-Holland 2142 ES",
    "addr:housenumber":"79",
    "addr:postcode":"2142 es",
    "addr:street":"Cruquiusdijk",
    "iso:country":"NL",
    "sg:address":"Cruquiusdijk 79",
    "sg:city":"Cruquius",
    "sg:orig_category":"Open Haard Houtblokken",
    "sg:phone":"+31 23 558 1147",
    "sg:postcode":"2142 ES",
    "sg:province":"Noord-Holland",
    "wof:name":"Kruuk, De",
    "wof:placetype":"venue"
},
  "geometry": {"coordinates":[4.64473,52.339039],"type":"Point"}
}