{
  "type": "Feature",
  "properties": {
    "addr:full":"Draaiomswg 29A Diepenveen NL.08 7431 CW",
    "addr:housenumber":"29a;nl.08",
    "addr:postcode":"7431 cw",
    "addr:street":"Draaiomswg",
    "iso:country":"NL",
    "sg:address":"Draaiomswg 29A",
    "sg:city":"Diepenveen",
    "sg:orig_category":"Kappers",
    "sg:phone":"+31 570 591 163",
    "sg:postcode":"7431 CW",
    "sg:province":"NL.08",
    "wof:name":"Pavette, Maison",
    "wof:placetype":"venue"
},
  "geometry": {"coordinates":[6.146146,52.286793],"type":"Point"}
}