{
  "type": "Feature",
  "properties": {
    "addr:full":"Oester 2 Noord Scharwoude Noord-Holland 1723 HW",
    "addr:housenumber":"2",
    "addr:postcode":"1723 hw",
    "addr:street":"Oester",
    "iso:country":"NL",
    "sg:address":"Oester 2",
    "sg:city":"Noord Scharwoude",
    "sg:orig_category":"Machinefabrieken",
    "sg:phone":"+31 226 332 100",
    "sg:postcode":"1723 HW",
    "sg:province":"Noord-Holland",
    "wof:name":"Demaco Holl Bv",
    "wof:placetype":"venue"
},
  "geometry": {"coordinates":[4.802919,52.702785],"type":"Point"}
}