{
  "type": "Feature",
  "properties": {
    "addr:full":"Insula 39 Poortugaal Zuid-Holland 3176 TD",
    "addr:housenumber":"39",
    "addr:postcode":"3176 td",
    "addr:street":"Insula",
    "iso:country":"NL",
    "sg:address":"Insula 39",
    "sg:city":"Poortugaal",
    "sg:orig_category":"Kappers",
    "sg:phone":"+31 10 501 1818",
    "sg:postcode":"3176 TD",
    "sg:province":"Zuid-Holland",
    "wof:name":"Leoncino",
    "wof:placetype":"venue"
},
  "geometry": {"coordinates":[4.400529,51.862999],"type":"Point"}
}