{
  "type": "Feature",
  "properties": {
    "addr:full":"Knibbelallee 3 Wilp Gld Gelderland 7384 AN",
    "addr:housenumber":"3",
    "addr:postcode":"7384 an",
    "addr:street":"Knibbelallee;Gld Gelderland",
    "iso:country":"NL",
    "sg:address":"Knibbelallee 3",
    "sg:city":"Wilp Gld",
    "sg:orig_category":"Verenigingsgebouwen",
    "sg:phone":"+31 571 261 999",
    "sg:postcode":"7384 AN",
    "sg:province":"Gelderland",
    "wof:name":"Pampus, Sticht",
    "wof:placetype":"venue"
},
  "geometry": {"coordinates":[6.129991,52.212257],"type":"Point"}
}