{
  "type": "Feature",
  "properties": {
    "addr:full":"Geessinkwg 279 Enschede Overijssel 7544 TZ",
    "addr:housenumber":"279",
    "addr:postcode":"7544 tz",
    "iso:country":"NL",
    "sg:address":"Geessinkwg 279",
    "sg:city":"Enschede",
    "sg:orig_category":"Adviesbureaus Financieel",
    "sg:phone":"+31 53 477 5264",
    "sg:postcode":"7544 TZ",
    "sg:province":"Overijssel",
    "wof:name":"Rendementvisie",
    "wof:placetype":"venue"
},
  "geometry": {"coordinates":[6.866325,52.191036],"type":"Point"}
}