{
  "type": "Feature",
  "properties": {
    "addr:full":"Kerkpln 39 Hoorn Noord-Holland 1621 CZ",
    "addr:housenumber":"39",
    "addr:postcode":"1621",
    "addr:street":"Kerkpln",
    "iso:country":"NL",
    "sg:address":"Kerkpln 39",
    "sg:city":"Hoorn",
    "sg:orig_category":"Verenigingen En Stichtingen",
    "sg:phone":"+31 229 217 249",
    "sg:postcode":"1621 CZ",
    "sg:province":"Noord-Holland",
    "sg:website":"http://www.boterhal.com",
    "wof:name":"Kunstenaarsver Hoorn En Omstreken",
    "wof:placetype":"venue"
},
  "geometry": {"coordinates":[5.059624,52.640179],"type":"Point"}
}