{
  "type": "Feature",
  "properties": {
    "iso:country":"NL",
    "sg:address":"Tonnendijk 1",
    "sg:city":"Vroomshoop",
    "sg:orig_category":"Huishoudapparatuur, Televisies And Radio'S",
    "sg:phone":"+31 546 642 436",
    "sg:postcode":"7681 BJ",
    "sg:province":"NL.08",
    "wof:name":"Expert Berkhof Bv",
    "wof:placetype":"venue"
},
  "geometry": {"coordinates":[6.57372,52.461575],"type":"Point"}
}