{
  "type": "Feature",
  "properties": {
    "iso:country":"NL",
    "sg:address":"Wyst 61",
    "sg:city":"Gemert",
    "sg:orig_category":"Autorijscholen",
    "sg:phone":"+31 492 365 654",
    "sg:postcode":"5422 AS",
    "sg:province":"Noord-Brabant",
    "wof:name":"Kuijpers",
    "wof:placetype":"venue"
},
  "geometry": {"coordinates":[5.699631,51.556107],"type":"Point"}
}