{
  "type": "Feature",
  "properties": {
    "addr:full":"De Gors 20 Almelo Overijssel 7609 DV",
    "addr:housenumber":"20",
    "addr:postcode":"7609 dv",
    "addr:street":"De Gors",
    "iso:country":"NL",
    "sg:address":"De Gors 20",
    "sg:city":"Almelo",
    "sg:orig_category":"Artsen - Huisartsen",
    "sg:phone":"+31 546 811 212",
    "sg:postcode":"7609 DV",
    "sg:province":"Overijssel",
    "wof:name":"Vis, D V/D",
    "wof:placetype":"venue"
},
  "geometry": {"coordinates":[6.631174,52.335732],"type":"Point"}
}