{
  "type": "Feature",
  "properties": {
    "addr:full":"Postbus 18560 'S-Gravenhage South Holland 2502 EN",
    "addr:housenumber":"18560",
    "addr:postcode":"2502 en",
    "addr:street":"Postbus",
    "iso:country":"NL",
    "sg:address":"Postbus 18560",
    "sg:city":"'S-Gravenhage",
    "sg:orig_category":"Bedrijfsopleidingen",
    "sg:phone":"+31 70 365 1375",
    "sg:postcode":"2502 EN",
    "sg:province":"South Holland",
    "wof:name":"Stivu",
    "wof:placetype":"venue"
},
  "geometry": {"coordinates":[4.31741,52.083988],"type":"Point"}
}