{
  "type": "Feature",
  "properties": {
    "addr:full":"Landeweel 21 Wouw North Brabant 4724 CW",
    "addr:housenumber":"21",
    "addr:postcode":"4724 cw",
    "addr:street":"Landeweel",
    "iso:country":"NL",
    "sg:address":"Landeweel 21",
    "sg:city":"Wouw",
    "sg:orig_category":"Boekhouders",
    "sg:phone":"+31 165 303 250",
    "sg:postcode":"4724 CW",
    "sg:province":"North Brabant",
    "wof:name":"Administratie- En Adviesburo Timmermans",
    "wof:placetype":"venue"
},
  "geometry": {"coordinates":[4.396438,51.522644],"type":"Point"}
}