{
  "type": "Feature",
  "properties": {
    "iso:country":"NL",
    "sg:address":"Minkmaatstraat 134",
    "sg:city":"Enschede",
    "sg:orig_category":"Drukkerijen And Copyshops",
    "sg:phone":"+31 53 435 0401",
    "sg:postcode":"7514 EG",
    "sg:province":"Overijssel",
    "wof:name":"Weka Druk",
    "wof:placetype":"venue"
},
  "geometry": {"coordinates":[6.904201,52.22826],"type":"Point"}
}