{
  "type": "Feature",
  "properties": {
    "addr:full":"Herengr 141 Amsterdam North Holland 1015 BH",
    "addr:housenumber":"141",
    "addr:postcode":"1015 bh",
    "iso:country":"NL",
    "sg:address":"Herengr 141",
    "sg:city":"Amsterdam",
    "sg:orig_category":"Webdesign Bureaus",
    "sg:phone":"+31 20 320 8947",
    "sg:postcode":"1015 BH",
    "sg:province":"North Holland",
    "wof:name":"Bushbaby",
    "wof:placetype":"venue"
},
  "geometry": {"coordinates":[4.8889741898,52.3753433228],"type":"Point"}
}