{
  "type": "Feature",
  "properties": {
    "iso:country":"NL",
    "sg:address":"Talmastr 3G",
    "sg:city":"Rotterdam",
    "sg:orig_category":"Koeriersdiensten",
    "sg:phone":"+31 10 265 3799",
    "sg:postcode":"3038 SL",
    "sg:province":"South Holland",
    "wof:name":"Extra Fast",
    "wof:placetype":"venue"
},
  "geometry": {"coordinates":[4.465303,51.937237],"type":"Point"}
}