{
  "type": "Feature",
  "properties": {
    "iso:country":"NL",
    "sg:address":"Muzenstr 31",
    "sg:city":"S Gravenhage",
    "sg:orig_category":"Verzekerings- Maatschappijen",
    "sg:phone":"+31 70 418 4184",
    "sg:postcode":"2511 VW",
    "sg:province":"Zuid-Holland",
    "sg:website":"http://www.zurich.nl",
    "wof:name":"Zurich",
    "wof:placetype":"venue"
},
  "geometry": {"coordinates":[4.31627,52.07896],"type":"Point"}
}