{
  "type": "Feature",
  "properties": {
    "addr:full":"Oudegr 42 Utrecht Utrecht 3511 AR",
    "addr:housenumber":"42",
    "addr:postcode":"3511",
    "addr:street":"Oudegr",
    "iso:country":"NL",
    "sg:address":"Oudegr 42",
    "sg:city":"Utrecht",
    "sg:orig_category":"Adviesbureaus",
    "sg:phone":"+31 30 231 4314",
    "sg:postcode":"3511 AR",
    "sg:province":"Utrecht",
    "sg:website":"http://www.intouch.nl/strohalm/",
    "wof:name":"Aktie Strohalm, Sticht",
    "wof:placetype":"venue"
},
  "geometry": {"coordinates":[-73.996292,40.613091],"type":"Point"}
}