{
  "type": "Feature",
  "properties": {
    "addr:full":"Croy 4 Eindhoven Noord-Brabant 5653 LD",
    "addr:housenumber":"4",
    "addr:postcode":"5653 ld",
    "addr:street":"Croy",
    "iso:country":"NL",
    "sg:address":"Croy 4",
    "sg:city":"Eindhoven",
    "sg:classifiers":[
        {
            "category":"Food & Beverages",
            "subcategory":"Fruits & Vegetables",
            "type":"Retail Goods"
        }
    ],
    "sg:phone":"+31 40 251 6263",
    "sg:postcode":"5653 LD",
    "sg:province":"Noord-Brabant",
    "sg:tags":[
        "groenten"
    ],
    "wof:name":"R. Janssen M. Muller Vof",
    "wof:placetype":"venue"
},
  "geometry": {"coordinates":[5.432769,51.419262],"type":"Point"}
}