{
  "type": "Feature",
  "properties": {
    "iso:country":"NL",
    "sg:address":"Zeearend 74",
    "sg:city":"Heerhugowaard",
    "sg:orig_category":"Kappers",
    "sg:phone":"+31 72 574 3801",
    "sg:postcode":"1704 TE",
    "sg:province":"North Holland",
    "wof:name":"Kapsalon Esthe",
    "wof:placetype":"venue"
},
  "geometry": {"coordinates":[4.8134889603,52.6549911499],"type":"Point"}
}