{
  "type": "Feature",
  "properties": {
    "iso:country":"NL",
    "sg:address":"Tjalkstraat 44",
    "sg:city":"Zaltbommel",
    "sg:orig_category":"Koeriersdiensten",
    "sg:phone":"+31 418 512 100",
    "sg:postcode":"5301 VW",
    "sg:province":"Gelderland",
    "wof:name":"Fmc Koerierdiensten",
    "wof:placetype":"venue"
},
  "geometry": {"coordinates":[5.245641,51.805607],"type":"Point"}
}