{
  "type": "Feature",
  "properties": {
    "addr:full":"Gasthuisstraat 16 Gorinchem Zuid-Holland 4201 JP",
    "addr:housenumber":"16",
    "addr:postcode":"4201 jp",
    "addr:street":"Gasthuisstraat",
    "iso:country":"NL",
    "sg:address":"Gasthuisstraat 16",
    "sg:city":"Gorinchem",
    "sg:orig_category":"Opticiens",
    "sg:phone":"+31 183 632 144",
    "sg:postcode":"4201 JP",
    "sg:province":"Zuid-Holland",
    "wof:name":"Nort Groeneveld Opticiens",
    "wof:placetype":"venue"
},
  "geometry": {"coordinates":[4.9745469093,51.8304748535],"type":"Point"}
}