{
  "type": "Feature",
  "properties": {
    "addr:full":"Merwedestr 24 Ysselstein Ut Utrecht 3404 KA",
    "addr:housenumber":"24",
    "addr:postcode":"3404 ka",
    "addr:street":"Merwedestr",
    "iso:country":"NL",
    "sg:address":"Merwedestr 24",
    "sg:city":"Ysselstein Ut",
    "sg:orig_category":"Haptotherapeuten",
    "sg:phone":"+31 30 687 7678",
    "sg:postcode":"3404 KA",
    "sg:province":"Utrecht",
    "wof:name":"Egbers, F A",
    "wof:placetype":"venue"
},
  "geometry": {"coordinates":[5.037991,52.012516],"type":"Point"}
}