{
  "type": "Feature",
  "properties": {
    "iso:country":"NL",
    "sg:address":"De Heijgraeff 2",
    "sg:city":"Woudenberg",
    "sg:orig_category":"Recreatie- And Lunaparken",
    "sg:phone":"+31 33 286 2919",
    "sg:postcode":"3931 MK",
    "sg:province":"Utrecht",
    "wof:name":"Henschotermeer Recreatieterrein",
    "wof:placetype":"venue"
},
  "geometry": {"coordinates":[5.381225,52.082691],"type":"Point"}
}