{
  "type": "Feature",
  "properties": {
    "addr:full":"Stationserf 27 Houten Utrecht 3991 KX",
    "addr:housenumber":"27",
    "addr:postcode":"3991 kx",
    "addr:street":"Stationserf",
    "iso:country":"NL",
    "sg:address":"Stationserf 27",
    "sg:city":"Houten",
    "sg:orig_category":"Bloemen And Planten",
    "sg:phone":"+31 30 637 5133",
    "sg:postcode":"3991 KX",
    "sg:province":"Utrecht",
    "wof:name":"Flowers Forever",
    "wof:placetype":"venue"
},
  "geometry": {"coordinates":[5.171293,52.024639],"type":"Point"}
}