{
  "type": "Feature",
  "properties": {
    "addr:full":"Strandweg Tent 32 'S Gravenhage Zuid-Holland 2586 JK",
    "addr:housenumber":"32",
    "addr:postcode":"2586 jk",
    "addr:street":"Strandweg;' S",
    "iso:country":"NL",
    "sg:address":"Strandweg Tent 32",
    "sg:city":"'S Gravenhage",
    "sg:classifiers":[
        {
            "category":"Fast Food",
            "type":"Food & Drink"
        }
    ],
    "sg:phone":"+31 70 350 2073",
    "sg:postcode":"2586 JK",
    "sg:province":"Zuid-Holland",
    "sg:tags":[
        "afhaal",
        "restaurant"
    ],
    "wof:name":"Paviljoen Waterman",
    "wof:placetype":"venue"
},
  "geometry": {"coordinates":[4.28358,52.115429],"type":"Point"}
}