{
  "type": "Feature",
  "properties": {
    "addr:full":"Dyk 40A Eersel Noord-Brabant 5521 AZ",
    "addr:housenumber":"40a",
    "addr:postcode":"5521 az",
    "addr:street":"Dyk",
    "iso:country":"NL",
    "sg:address":"Dyk 40A",
    "sg:city":"Eersel",
    "sg:orig_category":"Fietsen En Bromfietsen",
    "sg:phone":"+31 497 513 098",
    "sg:postcode":"5521 AZ",
    "sg:province":"Noord-Brabant",
    "sg:website":"http://www.gazellehuis.nl",
    "wof:name":"Fietsland Eersel",
    "wof:placetype":"venue"
},
  "geometry": {"coordinates":[5.30905,51.358311],"type":"Point"}
}