{
  "type": "Feature",
  "properties": {
    "addr:full":"Gooiland 2 Beverwyk North Holland 1948 RC",
    "addr:housenumber":"2",
    "addr:postcode":"1948 rc",
    "addr:street":"Gooiland;North",
    "iso:country":"NL",
    "sg:address":"Gooiland 2",
    "sg:city":"Beverwyk",
    "sg:orig_category":"Product-Promotie",
    "sg:phone":"+31 251 210 430",
    "sg:postcode":"1948 RC",
    "sg:province":"North Holland",
    "wof:name":"Instore And More",
    "wof:placetype":"venue"
},
  "geometry": {"coordinates":[4.671263,52.467545],"type":"Point"}
}