{
  "type": "Feature",
  "properties": {
    "addr:full":"Westeinde 42 De Rijp Noord-Holland 1483 EB",
    "addr:housenumber":"42",
    "addr:postcode":"1483 eb",
    "addr:street":"Westeinde",
    "iso:country":"NL",
    "sg:address":"Westeinde 42",
    "sg:city":"De Rijp",
    "sg:orig_category":"Artsen And Specialisten",
    "sg:phone":"+31 299 671 383",
    "sg:postcode":"1483 EB",
    "sg:province":"Noord-Holland",
    "wof:name":"A.O. Molenaar",
    "wof:placetype":"venue"
},
  "geometry": {"coordinates":[4.841781,52.56057],"type":"Point"}
}