{
  "type": "Feature",
  "properties": {
    "addr:full":"Plutostr 3 Borne Massachusetts 7622 VR",
    "addr:housenumber":"3",
    "addr:postcode":"7622 vr",
    "addr:street":"Plutostr",
    "iso:country":"NL",
    "sg:address":"Plutostr 3",
    "sg:city":"Borne",
    "sg:orig_category":"Verhuur",
    "sg:phone":"+31 74 266 8658",
    "sg:postcode":"7622 VR",
    "sg:province":"Massachusetts",
    "sg:website":"http://www.lemerij.nl",
    "wof:name":"Lemerij Verhuur Bv",
    "wof:placetype":"venue"
},
  "geometry": {"coordinates":[-70.54347199999999,41.78083],"type":"Point"}
}