{
  "type": "Feature",
  "properties": {
    "addr:full":"Kerkwg 120 , (Mobiele Telefoon) Ridderkerk Zuid-Holland 2985 AW",
    "addr:housenumber":"120",
    "addr:postcode":"2985 aw",
    "addr:street":"Mobiele Telefoon",
    "iso:country":"NL",
    "sg:address":"Kerkwg 120 , (Mobiele Telefoon)",
    "sg:city":"Ridderkerk",
    "sg:orig_category":"Afslankinstituten",
    "sg:phone":"+31 180 424 229",
    "sg:postcode":"2985 AW",
    "sg:province":"Zuid-Holland",
    "wof:name":"Ineke",
    "wof:placetype":"venue"
},
  "geometry": {"coordinates":[4.598129,51.86425],"type":"Point"}
}