{
  "type": "Feature",
  "properties": {
    "addr:full":"Keizersgr 390-392 Amsterdam Noord-Holland 1016 GB",
    "addr:housenumber":"390-392",
    "addr:postcode":"1016 gb",
    "iso:country":"NL",
    "sg:address":"Keizersgr 390-392",
    "sg:city":"Amsterdam",
    "sg:orig_category":"Verenigingen En Stichtingen",
    "sg:phone":"+31 20 626 2669",
    "sg:postcode":"1016 GB",
    "sg:province":"Noord-Holland",
    "sg:website":"http://www.aidsfonds.nl",
    "wof:name":"Aids Fonds, Sticht",
    "wof:placetype":"venue"
},
  "geometry": {"coordinates":[4.884074,52.369186],"type":"Point"}
}