{
  "type": "Feature",
  "properties": {
    "addr:full":"Heinsiusln 2A Amersfoort Utrecht 3818 JH",
    "addr:housenumber":"2a",
    "addr:postcode":"3818 jh",
    "addr:street":"Heinsiusln",
    "iso:country":"NL",
    "sg:address":"Heinsiusln 2A",
    "sg:city":"Amersfoort",
    "sg:orig_category":"Scholen Voor Algemeen Voortgezet Onderwijs",
    "sg:phone":"+31 33 463 4747",
    "sg:postcode":"3818 JH",
    "sg:province":"Utrecht",
    "wof:name":"Roc De Amerlanden",
    "wof:placetype":"venue"
},
  "geometry": {"coordinates":[5.386085,52.152325],"type":"Point"}
}