{
  "type": "Feature",
  "properties": {
    "addr:full":"Noordstr 78 Terneuzen Zeeland 4531 GJ",
    "addr:housenumber":"78",
    "addr:postcode":"4531 gj",
    "addr:street":"Noordstr",
    "iso:country":"NL",
    "sg:address":"Noordstr 78",
    "sg:city":"Terneuzen",
    "sg:orig_category":"Schoenen",
    "sg:phone":"+31 115 622 875",
    "sg:postcode":"4531 GJ",
    "sg:province":"Zeeland",
    "sg:website":"http://www.dolcis.nl",
    "wof:name":"Dolcis",
    "wof:placetype":"venue"
},
  "geometry": {"coordinates":[3.826481,51.337536],"type":"Point"}
}