{
  "type": "Feature",
  "properties": {
    "addr:full":"Gershwinstraat 45 Zwijndrecht Zuid-Holland 3335 WJ",
    "addr:housenumber":"45",
    "addr:postcode":"3335 wj",
    "addr:street":"Gershwinstraat",
    "iso:country":"NL",
    "sg:address":"Gershwinstraat 45",
    "sg:city":"Zwijndrecht",
    "sg:classifiers":[
        {
            "category":"Professional",
            "subcategory":"Accounting & Tax Preparation",
            "type":"Services"
        }
    ],
    "sg:phone":"+31 78 610 3239",
    "sg:postcode":"3335 WJ",
    "sg:province":"Zuid-Holland",
    "sg:tags":[
        "accountant"
    ],
    "wof:name":"P.C.J. Middelweerd",
    "wof:placetype":"venue"
},
  "geometry": {"coordinates":[4.612635,51.822235],"type":"Point"}
}