{
  "type": "Feature",
  "properties": {
    "addr:full":"Pastorielaan 2 Oostvoorne Zuid-Holland 3233 CZ",
    "addr:housenumber":"2",
    "addr:postcode":"3233",
    "addr:street":"Pastorielaan",
    "iso:country":"NL",
    "sg:address":"Pastorielaan 2",
    "sg:city":"Oostvoorne",
    "sg:orig_category":"Verlichting And Huishoudartikelen",
    "sg:phone":"+31 181 487 003",
    "sg:postcode":"3233 CZ",
    "sg:province":"Zuid-Holland",
    "wof:name":"Marskramer Intertoys",
    "wof:placetype":"venue"
},
  "geometry": {"coordinates":[4.103859,51.913956],"type":"Point"}
}