{
  "type": "Feature",
  "properties": {
    "addr:full":"Wilhelminasingel 260 Weert Limburg 6001 GV",
    "addr:housenumber":"260",
    "addr:postcode":"6001 gv",
    "addr:street":"Wilhelminasingel",
    "iso:country":"NL",
    "sg:address":"Wilhelminasingel 260",
    "sg:city":"Weert",
    "sg:orig_category":"Beautyfarms And Sauna'S",
    "sg:phone":"+31 495 538 504",
    "sg:postcode":"6001 GV",
    "sg:province":"Limburg",
    "wof:name":"Helmie'S Beauty Concept Bv",
    "wof:placetype":"venue"
},
  "geometry": {"coordinates":[5.704177,51.25552],"type":"Point"}
}