{
  "type": "Feature",
  "properties": {
    "addr:full":"Westerstraat 52 Enkhuizen North Holland 1601 AL",
    "addr:housenumber":"52",
    "addr:postcode":"1601 al",
    "addr:street":"Westerstraat",
    "iso:country":"NL",
    "sg:address":"Westerstraat 52",
    "sg:city":"Enkhuizen",
    "sg:orig_category":"Babyartikelen Detailhandel",
    "sg:phone":"+31 228 318 415",
    "sg:postcode":"1601 AL",
    "sg:province":"North Holland",
    "wof:name":"Babyhuis Wilma",
    "wof:placetype":"venue"
},
  "geometry": {"coordinates":[5.29182,52.704277],"type":"Point"}
}