{
  "type": "Feature",
  "properties": {
    "iso:country":"NL",
    "sg:address":"Europasngl 132",
    "sg:city":"Wervershoof",
    "sg:orig_category":"Logopedisten",
    "sg:phone":"+31 228 584 380",
    "sg:postcode":"1693 GV",
    "sg:province":"Noord-Holland",
    "wof:name":"Logopediepraktijk Wervershoof/Medemblik",
    "wof:placetype":"venue"
},
  "geometry": {"coordinates":[5.14762,52.730137],"type":"Point"}
}