{
  "type": "Feature",
  "properties": {
    "addr:full":"Badhuiswg 54-56 S Gravenhage South Holland 2587 CJ",
    "addr:housenumber":"54-56",
    "addr:postcode":"2587 cj",
    "addr:street":"S Gravenhage",
    "iso:country":"NL",
    "sg:address":"Badhuiswg 54-56",
    "sg:city":"S Gravenhage",
    "sg:classifiers":[
        {
            "category":"Travel",
            "subcategory":"Hotels & Motels",
            "type":"Entertainment"
        }
    ],
    "sg:phone":"+31 70 355 9939",
    "sg:postcode":"2587 CJ",
    "sg:province":"South Holland",
    "wof:name":"Corel",
    "wof:placetype":"venue"
},
  "geometry": {"coordinates":[4.29118,52.112942],"type":"Point"}
}