{
  "type": "Feature",
  "properties": {
    "addr:full":"Larikswg 12 Epe Gelderland 8162 EG",
    "addr:housenumber":"12",
    "addr:postcode":"8162 eg",
    "addr:street":"Larikswg;Gelderland",
    "iso:country":"NL",
    "sg:address":"Larikswg 12",
    "sg:city":"Epe",
    "sg:orig_category":"Kunsthandel",
    "sg:phone":"+31 578 613 944",
    "sg:postcode":"8162 EG",
    "sg:province":"Gelderland",
    "wof:name":"Bockweg",
    "wof:placetype":"venue"
},
  "geometry": {"coordinates":[5.968832,52.360699],"type":"Point"}
}