{
  "type": "Feature",
  "properties": {
    "iso:country":"NL",
    "sg:address":"Amstel 126S",
    "sg:city":"Amsterdam",
    "sg:orig_category":"Organisatiebureaus",
    "sg:phone":"+31 20 620 5250",
    "sg:postcode":"1017 AD",
    "sg:province":"North Holland",
    "sg:website":"http://www.doubledutchtours.com",
    "wof:name":"Doubledutch",
    "wof:placetype":"venue"
},
  "geometry": {"coordinates":[4.8978161812,52.3668861389],"type":"Point"}
}