{
  "type": "Feature",
  "properties": {
    "addr:full":"Mosveen 12 Wateringen Zuid-Holland 2291 NL",
    "addr:housenumber":"12",
    "addr:postcode":"2291 nl",
    "addr:street":"Mosveen",
    "iso:country":"NL",
    "sg:address":"Mosveen 12",
    "sg:city":"Wateringen",
    "sg:orig_category":"Metaalwerken",
    "sg:phone":"+31 174 298 886",
    "sg:postcode":"2291 NL",
    "sg:province":"Zuid-Holland",
    "wof:name":"Van Hagen Kassenbouw",
    "wof:placetype":"venue"
},
  "geometry": {"coordinates":[4.281181,52.017918],"type":"Point"}
}