{
  "type": "Feature",
  "properties": {
    "addr:full":"Molenstr 1 Zaamslag Zeeland 4543 CM",
    "addr:housenumber":"1",
    "addr:postcode":"4543 cm",
    "addr:street":"Molenstr",
    "iso:country":"NL",
    "sg:address":"Molenstr 1",
    "sg:city":"Zaamslag",
    "sg:orig_category":"Gezondheidszorg Geestelijke -",
    "sg:phone":"+31 115 431 636",
    "sg:postcode":"4543 CM",
    "sg:province":"Zeeland",
    "wof:name":"Tragel De Tjasker, Stichting",
    "wof:placetype":"venue"
},
  "geometry": {"coordinates":[3.911245,51.309525],"type":"Point"}
}