{
  "type": "Feature",
  "properties": {
    "iso:country":"NL",
    "sg:address":"Zeeburgerdijk 25",
    "sg:city":"Amsterdam",
    "sg:classifiers":[
        {
            "category":"Shopping",
            "subcategory":"Gifts & Souvenirs",
            "type":"Retail Goods"
        }
    ],
    "sg:phone":"+31 20 463 9226",
    "sg:postcode":"1093 SK",
    "sg:province":"Noord-Holland",
    "sg:tags":[
        "geschenken"
    ],
    "wof:name":"Onno C Boerwinkel",
    "wof:placetype":"venue"
},
  "geometry": {"coordinates":[4.929137,52.366142],"type":"Point"}
}