{
  "type": "Feature",
  "properties": {
    "addr:full":"Iepln 92 S Gravenhage South Holland 2565 LP",
    "addr:housenumber":"92",
    "addr:postcode":"2565 lp",
    "addr:street":"Iepln;S Gravenhage",
    "iso:country":"NL",
    "sg:address":"Iepln 92",
    "sg:city":"S Gravenhage",
    "sg:orig_category":"Kantoormachines",
    "sg:phone":"+31 70 323 9619",
    "sg:postcode":"2565 LP",
    "sg:province":"South Holland",
    "sg:website":"http://www.helpoff.com",
    "wof:name":"Help Office",
    "wof:placetype":"venue"
},
  "geometry": {"coordinates":[4.2612900734,52.0763816833],"type":"Point"}
}