{
  "type": "Feature",
  "properties": {
    "addr:full":"Koopvaardijweg 1 Oosterhout (Nb) Noord-Brabant 4906 CV",
    "addr:housenumber":"1",
    "addr:postcode":"4906 cv",
    "addr:street":"Koopvaardijweg",
    "iso:country":"NL",
    "sg:address":"Koopvaardijweg 1",
    "sg:city":"Oosterhout (Nb)",
    "sg:orig_category":"Gebouwenafwerking, Renovaties And Reiniging",
    "sg:phone":"+31 162 459 440",
    "sg:postcode":"4906 CV",
    "sg:province":"Noord-Brabant",
    "wof:name":"Jos Hofkens H.I.G. Bv",
    "wof:placetype":"venue"
},
  "geometry": {"coordinates":[4.831832,51.66552],"type":"Point"}
}